Compiled from "AccessControlProtos.java"
final class org.apache.hadoop.hbase.protobuf.generated.AccessControlProtos$1 implements com.google.protobuf.Descriptors$FileDescriptor$InternalDescriptorAssigner {
  org.apache.hadoop.hbase.protobuf.generated.AccessControlProtos$1();
    Code:
       0: aload_0
       1: invokespecial #1                  // Method java/lang/Object."<init>":()V
       4: return

  public com.google.protobuf.ExtensionRegistry assignDescriptors(com.google.protobuf.Descriptors$FileDescriptor);
    Code:
       0: aload_1
       1: invokestatic  #2                  // Method org/apache/hadoop/hbase/protobuf/generated/AccessControlProtos.access$16502:(Lcom/google/protobuf/Descriptors$FileDescriptor;)Lcom/google/protobuf/Descriptors$FileDescriptor;
       4: pop
       5: invokestatic  #3                  // Method org/apache/hadoop/hbase/protobuf/generated/AccessControlProtos.getDescriptor:()Lcom/google/protobuf/Descriptors$FileDescriptor;
       8: invokevirtual #4                  // Method com/google/protobuf/Descriptors$FileDescriptor.getMessageTypes:()Ljava/util/List;
      11: iconst_0
      12: invokeinterface #5,  2            // InterfaceMethod java/util/List.get:(I)Ljava/lang/Object;
      17: checkcast     #6                  // class com/google/protobuf/Descriptors$Descriptor
      20: invokestatic  #7                  // Method org/apache/hadoop/hbase/protobuf/generated/AccessControlProtos.access$002:(Lcom/google/protobuf/Descriptors$Descriptor;)Lcom/google/protobuf/Descriptors$Descriptor;
      23: pop
      24: new           #8                  // class com/google/protobuf/GeneratedMessage$FieldAccessorTable
      27: dup
      28: invokestatic  #9                  // Method org/apache/hadoop/hbase/protobuf/generated/AccessControlProtos.access$000:()Lcom/google/protobuf/Descriptors$Descriptor;
      31: iconst_4
      32: anewarray     #10                 // class java/lang/String
      35: dup
      36: iconst_0
      37: ldc           #11                 // String Type
      39: aastore
      40: dup
      41: iconst_1
      42: ldc           #12                 // String GlobalPermission
      44: aastore
      45: dup
      46: iconst_2
      47: ldc           #13                 // String NamespacePermission
      49: aastore
      50: dup
      51: iconst_3
      52: ldc           #14                 // String TablePermission
      54: aastore
      55: invokespecial #15                 // Method com/google/protobuf/GeneratedMessage$FieldAccessorTable."<init>":(Lcom/google/protobuf/Descriptors$Descriptor;[Ljava/lang/String;)V
      58: invokestatic  #16                 // Method org/apache/hadoop/hbase/protobuf/generated/AccessControlProtos.access$102:(Lcom/google/protobuf/GeneratedMessage$FieldAccessorTable;)Lcom/google/protobuf/GeneratedMessage$FieldAccessorTable;
      61: pop
      62: invokestatic  #3                  // Method org/apache/hadoop/hbase/protobuf/generated/AccessControlProtos.getDescriptor:()Lcom/google/protobuf/Descriptors$FileDescriptor;
      65: invokevirtual #4                  // Method com/google/protobuf/Descriptors$FileDescriptor.getMessageTypes:()Ljava/util/List;
      68: iconst_1
      69: invokeinterface #5,  2            // InterfaceMethod java/util/List.get:(I)Ljava/lang/Object;
      74: checkcast     #6                  // class com/google/protobuf/Descriptors$Descriptor
      77: invokestatic  #17                 // Method org/apache/hadoop/hbase/protobuf/generated/AccessControlProtos.access$1202:(Lcom/google/protobuf/Descriptors$Descriptor;)Lcom/google/protobuf/Descriptors$Descriptor;
      80: pop
      81: new           #8                  // class com/google/protobuf/GeneratedMessage$FieldAccessorTable
      84: dup
      85: invokestatic  #18                 // Method org/apache/hadoop/hbase/protobuf/generated/AccessControlProtos.access$1200:()Lcom/google/protobuf/Descriptors$Descriptor;
      88: iconst_4
      89: anewarray     #10                 // class java/lang/String
      92: dup
      93: iconst_0
      94: ldc           #19                 // String TableName
      96: aastore
      97: dup
      98: iconst_1
      99: ldc           #20                 // String Family
     101: aastore
     102: dup
     103: iconst_2
     104: ldc           #21                 // String Qualifier
     106: aastore
     107: dup
     108: iconst_3
     109: ldc           #22                 // String Action
     111: aastore
     112: invokespecial #15                 // Method com/google/protobuf/GeneratedMessage$FieldAccessorTable."<init>":(Lcom/google/protobuf/Descriptors$Descriptor;[Ljava/lang/String;)V
     115: invokestatic  #23                 // Method org/apache/hadoop/hbase/protobuf/generated/AccessControlProtos.access$1302:(Lcom/google/protobuf/GeneratedMessage$FieldAccessorTable;)Lcom/google/protobuf/GeneratedMessage$FieldAccessorTable;
     118: pop
     119: invokestatic  #3                  // Method org/apache/hadoop/hbase/protobuf/generated/AccessControlProtos.getDescriptor:()Lcom/google/protobuf/Descriptors$FileDescriptor;
     122: invokevirtual #4                  // Method com/google/protobuf/Descriptors$FileDescriptor.getMessageTypes:()Ljava/util/List;
     125: iconst_2
     126: invokeinterface #5,  2            // InterfaceMethod java/util/List.get:(I)Ljava/lang/Object;
     131: checkcast     #6                  // class com/google/protobuf/Descriptors$Descriptor
     134: invokestatic  #24                 // Method org/apache/hadoop/hbase/protobuf/generated/AccessControlProtos.access$2402:(Lcom/google/protobuf/Descriptors$Descriptor;)Lcom/google/protobuf/Descriptors$Descriptor;
     137: pop
     138: new           #8                  // class com/google/protobuf/GeneratedMessage$FieldAccessorTable
     141: dup
     142: invokestatic  #25                 // Method org/apache/hadoop/hbase/protobuf/generated/AccessControlProtos.access$2400:()Lcom/google/protobuf/Descriptors$Descriptor;
     145: iconst_2
     146: anewarray     #10                 // class java/lang/String
     149: dup
     150: iconst_0
     151: ldc           #26                 // String NamespaceName
     153: aastore
     154: dup
     155: iconst_1
     156: ldc           #22                 // String Action
     158: aastore
     159: invokespecial #15                 // Method com/google/protobuf/GeneratedMessage$FieldAccessorTable."<init>":(Lcom/google/protobuf/Descriptors$Descriptor;[Ljava/lang/String;)V
     162: invokestatic  #27                 // Method org/apache/hadoop/hbase/protobuf/generated/AccessControlProtos.access$2502:(Lcom/google/protobuf/GeneratedMessage$FieldAccessorTable;)Lcom/google/protobuf/GeneratedMessage$FieldAccessorTable;
     165: pop
     166: invokestatic  #3                  // Method org/apache/hadoop/hbase/protobuf/generated/AccessControlProtos.getDescriptor:()Lcom/google/protobuf/Descriptors$FileDescriptor;
     169: invokevirtual #4                  // Method com/google/protobuf/Descriptors$FileDescriptor.getMessageTypes:()Ljava/util/List;
     172: iconst_3
     173: invokeinterface #5,  2            // InterfaceMethod java/util/List.get:(I)Ljava/lang/Object;
     178: checkcast     #6                  // class com/google/protobuf/Descriptors$Descriptor
     181: invokestatic  #28                 // Method org/apache/hadoop/hbase/protobuf/generated/AccessControlProtos.access$3402:(Lcom/google/protobuf/Descriptors$Descriptor;)Lcom/google/protobuf/Descriptors$Descriptor;
     184: pop
     185: new           #8                  // class com/google/protobuf/GeneratedMessage$FieldAccessorTable
     188: dup
     189: invokestatic  #29                 // Method org/apache/hadoop/hbase/protobuf/generated/AccessControlProtos.access$3400:()Lcom/google/protobuf/Descriptors$Descriptor;
     192: iconst_1
     193: anewarray     #10                 // class java/lang/String
     196: dup
     197: iconst_0
     198: ldc           #22                 // String Action
     200: aastore
     201: invokespecial #15                 // Method com/google/protobuf/GeneratedMessage$FieldAccessorTable."<init>":(Lcom/google/protobuf/Descriptors$Descriptor;[Ljava/lang/String;)V
     204: invokestatic  #30                 // Method org/apache/hadoop/hbase/protobuf/generated/AccessControlProtos.access$3502:(Lcom/google/protobuf/GeneratedMessage$FieldAccessorTable;)Lcom/google/protobuf/GeneratedMessage$FieldAccessorTable;
     207: pop
     208: invokestatic  #3                  // Method org/apache/hadoop/hbase/protobuf/generated/AccessControlProtos.getDescriptor:()Lcom/google/protobuf/Descriptors$FileDescriptor;
     211: invokevirtual #4                  // Method com/google/protobuf/Descriptors$FileDescriptor.getMessageTypes:()Ljava/util/List;
     214: iconst_4
     215: invokeinterface #5,  2            // InterfaceMethod java/util/List.get:(I)Ljava/lang/Object;
     220: checkcast     #6                  // class com/google/protobuf/Descriptors$Descriptor
     223: invokestatic  #31                 // Method org/apache/hadoop/hbase/protobuf/generated/AccessControlProtos.access$4202:(Lcom/google/protobuf/Descriptors$Descriptor;)Lcom/google/protobuf/Descriptors$Descriptor;
     226: pop
     227: new           #8                  // class com/google/protobuf/GeneratedMessage$FieldAccessorTable
     230: dup
     231: invokestatic  #32                 // Method org/apache/hadoop/hbase/protobuf/generated/AccessControlProtos.access$4200:()Lcom/google/protobuf/Descriptors$Descriptor;
     234: iconst_2
     235: anewarray     #10                 // class java/lang/String
     238: dup
     239: iconst_0
     240: ldc           #33                 // String User
     242: aastore
     243: dup
     244: iconst_1
     245: ldc           #34                 // String Permission
     247: aastore
     248: invokespecial #15                 // Method com/google/protobuf/GeneratedMessage$FieldAccessorTable."<init>":(Lcom/google/protobuf/Descriptors$Descriptor;[Ljava/lang/String;)V
     251: invokestatic  #35                 // Method org/apache/hadoop/hbase/protobuf/generated/AccessControlProtos.access$4302:(Lcom/google/protobuf/GeneratedMessage$FieldAccessorTable;)Lcom/google/protobuf/GeneratedMessage$FieldAccessorTable;
     254: pop
     255: invokestatic  #3                  // Method org/apache/hadoop/hbase/protobuf/generated/AccessControlProtos.getDescriptor:()Lcom/google/protobuf/Descriptors$FileDescriptor;
     258: invokevirtual #4                  // Method com/google/protobuf/Descriptors$FileDescriptor.getMessageTypes:()Ljava/util/List;
     261: iconst_5
     262: invokeinterface #5,  2            // InterfaceMethod java/util/List.get:(I)Ljava/lang/Object;
     267: checkcast     #6                  // class com/google/protobuf/Descriptors$Descriptor
     270: invokestatic  #36                 // Method org/apache/hadoop/hbase/protobuf/generated/AccessControlProtos.access$5202:(Lcom/google/protobuf/Descriptors$Descriptor;)Lcom/google/protobuf/Descriptors$Descriptor;
     273: pop
     274: new           #8                  // class com/google/protobuf/GeneratedMessage$FieldAccessorTable
     277: dup
     278: invokestatic  #37                 // Method org/apache/hadoop/hbase/protobuf/generated/AccessControlProtos.access$5200:()Lcom/google/protobuf/Descriptors$Descriptor;
     281: iconst_1
     282: anewarray     #10                 // class java/lang/String
     285: dup
     286: iconst_0
     287: ldc           #38                 // String UserPermissions
     289: aastore
     290: invokespecial #15                 // Method com/google/protobuf/GeneratedMessage$FieldAccessorTable."<init>":(Lcom/google/protobuf/Descriptors$Descriptor;[Ljava/lang/String;)V
     293: invokestatic  #39                 // Method org/apache/hadoop/hbase/protobuf/generated/AccessControlProtos.access$5302:(Lcom/google/protobuf/GeneratedMessage$FieldAccessorTable;)Lcom/google/protobuf/GeneratedMessage$FieldAccessorTable;
     296: pop
     297: invokestatic  #37                 // Method org/apache/hadoop/hbase/protobuf/generated/AccessControlProtos.access$5200:()Lcom/google/protobuf/Descriptors$Descriptor;
     300: invokevirtual #40                 // Method com/google/protobuf/Descriptors$Descriptor.getNestedTypes:()Ljava/util/List;
     303: iconst_0
     304: invokeinterface #5,  2            // InterfaceMethod java/util/List.get:(I)Ljava/lang/Object;
     309: checkcast     #6                  // class com/google/protobuf/Descriptors$Descriptor
     312: invokestatic  #41                 // Method org/apache/hadoop/hbase/protobuf/generated/AccessControlProtos.access$5502:(Lcom/google/protobuf/Descriptors$Descriptor;)Lcom/google/protobuf/Descriptors$Descriptor;
     315: pop
     316: new           #8                  // class com/google/protobuf/GeneratedMessage$FieldAccessorTable
     319: dup
     320: invokestatic  #42                 // Method org/apache/hadoop/hbase/protobuf/generated/AccessControlProtos.access$5500:()Lcom/google/protobuf/Descriptors$Descriptor;
     323: iconst_2
     324: anewarray     #10                 // class java/lang/String
     327: dup
     328: iconst_0
     329: ldc           #33                 // String User
     331: aastore
     332: dup
     333: iconst_1
     334: ldc           #43                 // String Permissions
     336: aastore
     337: invokespecial #15                 // Method com/google/protobuf/GeneratedMessage$FieldAccessorTable."<init>":(Lcom/google/protobuf/Descriptors$Descriptor;[Ljava/lang/String;)V
     340: invokestatic  #44                 // Method org/apache/hadoop/hbase/protobuf/generated/AccessControlProtos.access$5602:(Lcom/google/protobuf/GeneratedMessage$FieldAccessorTable;)Lcom/google/protobuf/GeneratedMessage$FieldAccessorTable;
     343: pop
     344: invokestatic  #3                  // Method org/apache/hadoop/hbase/protobuf/generated/AccessControlProtos.getDescriptor:()Lcom/google/protobuf/Descriptors$FileDescriptor;
     347: invokevirtual #4                  // Method com/google/protobuf/Descriptors$FileDescriptor.getMessageTypes:()Ljava/util/List;
     350: bipush        6
     352: invokeinterface #5,  2            // InterfaceMethod java/util/List.get:(I)Ljava/lang/Object;
     357: checkcast     #6                  // class com/google/protobuf/Descriptors$Descriptor
     360: invokestatic  #45                 // Method org/apache/hadoop/hbase/protobuf/generated/AccessControlProtos.access$7202:(Lcom/google/protobuf/Descriptors$Descriptor;)Lcom/google/protobuf/Descriptors$Descriptor;
     363: pop
     364: new           #8                  // class com/google/protobuf/GeneratedMessage$FieldAccessorTable
     367: dup
     368: invokestatic  #46                 // Method org/apache/hadoop/hbase/protobuf/generated/AccessControlProtos.access$7200:()Lcom/google/protobuf/Descriptors$Descriptor;
     371: iconst_2
     372: anewarray     #10                 // class java/lang/String
     375: dup
     376: iconst_0
     377: ldc           #47                 // String UserPermission
     379: aastore
     380: dup
     381: iconst_1
     382: ldc           #48                 // String MergeExistingPermissions
     384: aastore
     385: invokespecial #15                 // Method com/google/protobuf/GeneratedMessage$FieldAccessorTable."<init>":(Lcom/google/protobuf/Descriptors$Descriptor;[Ljava/lang/String;)V
     388: invokestatic  #49                 // Method org/apache/hadoop/hbase/protobuf/generated/AccessControlProtos.access$7302:(Lcom/google/protobuf/GeneratedMessage$FieldAccessorTable;)Lcom/google/protobuf/GeneratedMessage$FieldAccessorTable;
     391: pop
     392: invokestatic  #3                  // Method org/apache/hadoop/hbase/protobuf/generated/AccessControlProtos.getDescriptor:()Lcom/google/protobuf/Descriptors$FileDescriptor;
     395: invokevirtual #4                  // Method com/google/protobuf/Descriptors$FileDescriptor.getMessageTypes:()Ljava/util/List;
     398: bipush        7
     400: invokeinterface #5,  2            // InterfaceMethod java/util/List.get:(I)Ljava/lang/Object;
     405: checkcast     #6                  // class com/google/protobuf/Descriptors$Descriptor
     408: invokestatic  #50                 // Method org/apache/hadoop/hbase/protobuf/generated/AccessControlProtos.access$8202:(Lcom/google/protobuf/Descriptors$Descriptor;)Lcom/google/protobuf/Descriptors$Descriptor;
     411: pop
     412: new           #8                  // class com/google/protobuf/GeneratedMessage$FieldAccessorTable
     415: dup
     416: invokestatic  #51                 // Method org/apache/hadoop/hbase/protobuf/generated/AccessControlProtos.access$8200:()Lcom/google/protobuf/Descriptors$Descriptor;
     419: iconst_0
     420: anewarray     #10                 // class java/lang/String
     423: invokespecial #15                 // Method com/google/protobuf/GeneratedMessage$FieldAccessorTable."<init>":(Lcom/google/protobuf/Descriptors$Descriptor;[Ljava/lang/String;)V
     426: invokestatic  #52                 // Method org/apache/hadoop/hbase/protobuf/generated/AccessControlProtos.access$8302:(Lcom/google/protobuf/GeneratedMessage$FieldAccessorTable;)Lcom/google/protobuf/GeneratedMessage$FieldAccessorTable;
     429: pop
     430: invokestatic  #3                  // Method org/apache/hadoop/hbase/protobuf/generated/AccessControlProtos.getDescriptor:()Lcom/google/protobuf/Descriptors$FileDescriptor;
     433: invokevirtual #4                  // Method com/google/protobuf/Descriptors$FileDescriptor.getMessageTypes:()Ljava/util/List;
     436: bipush        8
     438: invokeinterface #5,  2            // InterfaceMethod java/util/List.get:(I)Ljava/lang/Object;
     443: checkcast     #6                  // class com/google/protobuf/Descriptors$Descriptor
     446: invokestatic  #53                 // Method org/apache/hadoop/hbase/protobuf/generated/AccessControlProtos.access$8902:(Lcom/google/protobuf/Descriptors$Descriptor;)Lcom/google/protobuf/Descriptors$Descriptor;
     449: pop
     450: new           #8                  // class com/google/protobuf/GeneratedMessage$FieldAccessorTable
     453: dup
     454: invokestatic  #54                 // Method org/apache/hadoop/hbase/protobuf/generated/AccessControlProtos.access$8900:()Lcom/google/protobuf/Descriptors$Descriptor;
     457: iconst_1
     458: anewarray     #10                 // class java/lang/String
     461: dup
     462: iconst_0
     463: ldc           #47                 // String UserPermission
     465: aastore
     466: invokespecial #15                 // Method com/google/protobuf/GeneratedMessage$FieldAccessorTable."<init>":(Lcom/google/protobuf/Descriptors$Descriptor;[Ljava/lang/String;)V
     469: invokestatic  #55                 // Method org/apache/hadoop/hbase/protobuf/generated/AccessControlProtos.access$9002:(Lcom/google/protobuf/GeneratedMessage$FieldAccessorTable;)Lcom/google/protobuf/GeneratedMessage$FieldAccessorTable;
     472: pop
     473: invokestatic  #3                  // Method org/apache/hadoop/hbase/protobuf/generated/AccessControlProtos.getDescriptor:()Lcom/google/protobuf/Descriptors$FileDescriptor;
     476: invokevirtual #4                  // Method com/google/protobuf/Descriptors$FileDescriptor.getMessageTypes:()Ljava/util/List;
     479: bipush        9
     481: invokeinterface #5,  2            // InterfaceMethod java/util/List.get:(I)Ljava/lang/Object;
     486: checkcast     #6                  // class com/google/protobuf/Descriptors$Descriptor
     489: invokestatic  #56                 // Method org/apache/hadoop/hbase/protobuf/generated/AccessControlProtos.access$9802:(Lcom/google/protobuf/Descriptors$Descriptor;)Lcom/google/protobuf/Descriptors$Descriptor;
     492: pop
     493: new           #8                  // class com/google/protobuf/GeneratedMessage$FieldAccessorTable
     496: dup
     497: invokestatic  #57                 // Method org/apache/hadoop/hbase/protobuf/generated/AccessControlProtos.access$9800:()Lcom/google/protobuf/Descriptors$Descriptor;
     500: iconst_0
     501: anewarray     #10                 // class java/lang/String
     504: invokespecial #15                 // Method com/google/protobuf/GeneratedMessage$FieldAccessorTable."<init>":(Lcom/google/protobuf/Descriptors$Descriptor;[Ljava/lang/String;)V
     507: invokestatic  #58                 // Method org/apache/hadoop/hbase/protobuf/generated/AccessControlProtos.access$9902:(Lcom/google/protobuf/GeneratedMessage$FieldAccessorTable;)Lcom/google/protobuf/GeneratedMessage$FieldAccessorTable;
     510: pop
     511: invokestatic  #3                  // Method org/apache/hadoop/hbase/protobuf/generated/AccessControlProtos.getDescriptor:()Lcom/google/protobuf/Descriptors$FileDescriptor;
     514: invokevirtual #4                  // Method com/google/protobuf/Descriptors$FileDescriptor.getMessageTypes:()Ljava/util/List;
     517: bipush        10
     519: invokeinterface #5,  2            // InterfaceMethod java/util/List.get:(I)Ljava/lang/Object;
     524: checkcast     #6                  // class com/google/protobuf/Descriptors$Descriptor
     527: invokestatic  #59                 // Method org/apache/hadoop/hbase/protobuf/generated/AccessControlProtos.access$10502:(Lcom/google/protobuf/Descriptors$Descriptor;)Lcom/google/protobuf/Descriptors$Descriptor;
     530: pop
     531: new           #8                  // class com/google/protobuf/GeneratedMessage$FieldAccessorTable
     534: dup
     535: invokestatic  #60                 // Method org/apache/hadoop/hbase/protobuf/generated/AccessControlProtos.access$10500:()Lcom/google/protobuf/Descriptors$Descriptor;
     538: bipush        6
     540: anewarray     #10                 // class java/lang/String
     543: dup
     544: iconst_0
     545: ldc           #11                 // String Type
     547: aastore
     548: dup
     549: iconst_1
     550: ldc           #19                 // String TableName
     552: aastore
     553: dup
     554: iconst_2
     555: ldc           #26                 // String NamespaceName
     557: aastore
     558: dup
     559: iconst_3
     560: ldc           #61                 // String ColumnFamily
     562: aastore
     563: dup
     564: iconst_4
     565: ldc           #62                 // String ColumnQualifier
     567: aastore
     568: dup
     569: iconst_5
     570: ldc           #63                 // String UserName
     572: aastore
     573: invokespecial #15                 // Method com/google/protobuf/GeneratedMessage$FieldAccessorTable."<init>":(Lcom/google/protobuf/Descriptors$Descriptor;[Ljava/lang/String;)V
     576: invokestatic  #64                 // Method org/apache/hadoop/hbase/protobuf/generated/AccessControlProtos.access$10602:(Lcom/google/protobuf/GeneratedMessage$FieldAccessorTable;)Lcom/google/protobuf/GeneratedMessage$FieldAccessorTable;
     579: pop
     580: invokestatic  #3                  // Method org/apache/hadoop/hbase/protobuf/generated/AccessControlProtos.getDescriptor:()Lcom/google/protobuf/Descriptors$FileDescriptor;
     583: invokevirtual #4                  // Method com/google/protobuf/Descriptors$FileDescriptor.getMessageTypes:()Ljava/util/List;
     586: bipush        11
     588: invokeinterface #5,  2            // InterfaceMethod java/util/List.get:(I)Ljava/lang/Object;
     593: checkcast     #6                  // class com/google/protobuf/Descriptors$Descriptor
     596: invokestatic  #65                 // Method org/apache/hadoop/hbase/protobuf/generated/AccessControlProtos.access$11902:(Lcom/google/protobuf/Descriptors$Descriptor;)Lcom/google/protobuf/Descriptors$Descriptor;
     599: pop
     600: new           #8                  // class com/google/protobuf/GeneratedMessage$FieldAccessorTable
     603: dup
     604: invokestatic  #66                 // Method org/apache/hadoop/hbase/protobuf/generated/AccessControlProtos.access$11900:()Lcom/google/protobuf/Descriptors$Descriptor;
     607: iconst_1
     608: anewarray     #10                 // class java/lang/String
     611: dup
     612: iconst_0
     613: ldc           #47                 // String UserPermission
     615: aastore
     616: invokespecial #15                 // Method com/google/protobuf/GeneratedMessage$FieldAccessorTable."<init>":(Lcom/google/protobuf/Descriptors$Descriptor;[Ljava/lang/String;)V
     619: invokestatic  #67                 // Method org/apache/hadoop/hbase/protobuf/generated/AccessControlProtos.access$12002:(Lcom/google/protobuf/GeneratedMessage$FieldAccessorTable;)Lcom/google/protobuf/GeneratedMessage$FieldAccessorTable;
     622: pop
     623: invokestatic  #3                  // Method org/apache/hadoop/hbase/protobuf/generated/AccessControlProtos.getDescriptor:()Lcom/google/protobuf/Descriptors$FileDescriptor;
     626: invokevirtual #4                  // Method com/google/protobuf/Descriptors$FileDescriptor.getMessageTypes:()Ljava/util/List;
     629: bipush        12
     631: invokeinterface #5,  2            // InterfaceMethod java/util/List.get:(I)Ljava/lang/Object;
     636: checkcast     #6                  // class com/google/protobuf/Descriptors$Descriptor
     639: invokestatic  #68                 // Method org/apache/hadoop/hbase/protobuf/generated/AccessControlProtos.access$12802:(Lcom/google/protobuf/Descriptors$Descriptor;)Lcom/google/protobuf/Descriptors$Descriptor;
     642: pop
     643: new           #8                  // class com/google/protobuf/GeneratedMessage$FieldAccessorTable
     646: dup
     647: invokestatic  #69                 // Method org/apache/hadoop/hbase/protobuf/generated/AccessControlProtos.access$12800:()Lcom/google/protobuf/Descriptors$Descriptor;
     650: iconst_1
     651: anewarray     #10                 // class java/lang/String
     654: dup
     655: iconst_0
     656: ldc           #34                 // String Permission
     658: aastore
     659: invokespecial #15                 // Method com/google/protobuf/GeneratedMessage$FieldAccessorTable."<init>":(Lcom/google/protobuf/Descriptors$Descriptor;[Ljava/lang/String;)V
     662: invokestatic  #70                 // Method org/apache/hadoop/hbase/protobuf/generated/AccessControlProtos.access$12902:(Lcom/google/protobuf/GeneratedMessage$FieldAccessorTable;)Lcom/google/protobuf/GeneratedMessage$FieldAccessorTable;
     665: pop
     666: invokestatic  #3                  // Method org/apache/hadoop/hbase/protobuf/generated/AccessControlProtos.getDescriptor:()Lcom/google/protobuf/Descriptors$FileDescriptor;
     669: invokevirtual #4                  // Method com/google/protobuf/Descriptors$FileDescriptor.getMessageTypes:()Ljava/util/List;
     672: bipush        13
     674: invokeinterface #5,  2            // InterfaceMethod java/util/List.get:(I)Ljava/lang/Object;
     679: checkcast     #6                  // class com/google/protobuf/Descriptors$Descriptor
     682: invokestatic  #71                 // Method org/apache/hadoop/hbase/protobuf/generated/AccessControlProtos.access$13702:(Lcom/google/protobuf/Descriptors$Descriptor;)Lcom/google/protobuf/Descriptors$Descriptor;
     685: pop
     686: new           #8                  // class com/google/protobuf/GeneratedMessage$FieldAccessorTable
     689: dup
     690: invokestatic  #72                 // Method org/apache/hadoop/hbase/protobuf/generated/AccessControlProtos.access$13700:()Lcom/google/protobuf/Descriptors$Descriptor;
     693: iconst_0
     694: anewarray     #10                 // class java/lang/String
     697: invokespecial #15                 // Method com/google/protobuf/GeneratedMessage$FieldAccessorTable."<init>":(Lcom/google/protobuf/Descriptors$Descriptor;[Ljava/lang/String;)V
     700: invokestatic  #73                 // Method org/apache/hadoop/hbase/protobuf/generated/AccessControlProtos.access$13802:(Lcom/google/protobuf/GeneratedMessage$FieldAccessorTable;)Lcom/google/protobuf/GeneratedMessage$FieldAccessorTable;
     703: pop
     704: invokestatic  #3                  // Method org/apache/hadoop/hbase/protobuf/generated/AccessControlProtos.getDescriptor:()Lcom/google/protobuf/Descriptors$FileDescriptor;
     707: invokevirtual #4                  // Method com/google/protobuf/Descriptors$FileDescriptor.getMessageTypes:()Ljava/util/List;
     710: bipush        14
     712: invokeinterface #5,  2            // InterfaceMethod java/util/List.get:(I)Ljava/lang/Object;
     717: checkcast     #6                  // class com/google/protobuf/Descriptors$Descriptor
     720: invokestatic  #74                 // Method org/apache/hadoop/hbase/protobuf/generated/AccessControlProtos.access$14402:(Lcom/google/protobuf/Descriptors$Descriptor;)Lcom/google/protobuf/Descriptors$Descriptor;
     723: pop
     724: new           #8                  // class com/google/protobuf/GeneratedMessage$FieldAccessorTable
     727: dup
     728: invokestatic  #75                 // Method org/apache/hadoop/hbase/protobuf/generated/AccessControlProtos.access$14400:()Lcom/google/protobuf/Descriptors$Descriptor;
     731: iconst_2
     732: anewarray     #10                 // class java/lang/String
     735: dup
     736: iconst_0
     737: ldc           #14                 // String TablePermission
     739: aastore
     740: dup
     741: iconst_1
     742: ldc           #63                 // String UserName
     744: aastore
     745: invokespecial #15                 // Method com/google/protobuf/GeneratedMessage$FieldAccessorTable."<init>":(Lcom/google/protobuf/Descriptors$Descriptor;[Ljava/lang/String;)V
     748: invokestatic  #76                 // Method org/apache/hadoop/hbase/protobuf/generated/AccessControlProtos.access$14502:(Lcom/google/protobuf/GeneratedMessage$FieldAccessorTable;)Lcom/google/protobuf/GeneratedMessage$FieldAccessorTable;
     751: pop
     752: invokestatic  #3                  // Method org/apache/hadoop/hbase/protobuf/generated/AccessControlProtos.getDescriptor:()Lcom/google/protobuf/Descriptors$FileDescriptor;
     755: invokevirtual #4                  // Method com/google/protobuf/Descriptors$FileDescriptor.getMessageTypes:()Ljava/util/List;
     758: bipush        15
     760: invokeinterface #5,  2            // InterfaceMethod java/util/List.get:(I)Ljava/lang/Object;
     765: checkcast     #6                  // class com/google/protobuf/Descriptors$Descriptor
     768: invokestatic  #77                 // Method org/apache/hadoop/hbase/protobuf/generated/AccessControlProtos.access$15402:(Lcom/google/protobuf/Descriptors$Descriptor;)Lcom/google/protobuf/Descriptors$Descriptor;
     771: pop
     772: new           #8                  // class com/google/protobuf/GeneratedMessage$FieldAccessorTable
     775: dup
     776: invokestatic  #78                 // Method org/apache/hadoop/hbase/protobuf/generated/AccessControlProtos.access$15400:()Lcom/google/protobuf/Descriptors$Descriptor;
     779: iconst_1
     780: anewarray     #10                 // class java/lang/String
     783: dup
     784: iconst_0
     785: ldc           #79                 // String HasPermission
     787: aastore
     788: invokespecial #15                 // Method com/google/protobuf/GeneratedMessage$FieldAccessorTable."<init>":(Lcom/google/protobuf/Descriptors$Descriptor;[Ljava/lang/String;)V
     791: invokestatic  #80                 // Method org/apache/hadoop/hbase/protobuf/generated/AccessControlProtos.access$15502:(Lcom/google/protobuf/GeneratedMessage$FieldAccessorTable;)Lcom/google/protobuf/GeneratedMessage$FieldAccessorTable;
     794: pop
     795: aconst_null
     796: areturn
}
