Compiled from "AccessController.java"
final class org.apache.hadoop.hbase.security.access.AccessController$OpType extends java.lang.Enum<org.apache.hadoop.hbase.security.access.AccessController$OpType> {
  public static final org.apache.hadoop.hbase.security.access.AccessController$OpType GET;

  public static final org.apache.hadoop.hbase.security.access.AccessController$OpType EXISTS;

  public static final org.apache.hadoop.hbase.security.access.AccessController$OpType SCAN;

  public static final org.apache.hadoop.hbase.security.access.AccessController$OpType PUT;

  public static final org.apache.hadoop.hbase.security.access.AccessController$OpType DELETE;

  public static final org.apache.hadoop.hbase.security.access.AccessController$OpType CHECK_AND_PUT;

  public static final org.apache.hadoop.hbase.security.access.AccessController$OpType CHECK_AND_DELETE;

  public static final org.apache.hadoop.hbase.security.access.AccessController$OpType INCREMENT_COLUMN_VALUE;

  public static final org.apache.hadoop.hbase.security.access.AccessController$OpType APPEND;

  public static final org.apache.hadoop.hbase.security.access.AccessController$OpType INCREMENT;

  public static org.apache.hadoop.hbase.security.access.AccessController$OpType[] values();
    Code:
       0: getstatic     #1                  // Field $VALUES:[Lorg/apache/hadoop/hbase/security/access/AccessController$OpType;
       3: invokevirtual #2                  // Method "[Lorg/apache/hadoop/hbase/security/access/AccessController$OpType;".clone:()Ljava/lang/Object;
       6: checkcast     #3                  // class "[Lorg/apache/hadoop/hbase/security/access/AccessController$OpType;"
       9: areturn

  public static org.apache.hadoop.hbase.security.access.AccessController$OpType valueOf(java.lang.String);
    Code:
       0: ldc           #4                  // class org/apache/hadoop/hbase/security/access/AccessController$OpType
       2: aload_0
       3: invokestatic  #5                  // Method java/lang/Enum.valueOf:(Ljava/lang/Class;Ljava/lang/String;)Ljava/lang/Enum;
       6: checkcast     #4                  // class org/apache/hadoop/hbase/security/access/AccessController$OpType
       9: areturn

  public java.lang.String toString();
    Code:
       0: aload_0
       1: getfield      #7                  // Field type:Ljava/lang/String;
       4: areturn

  static {};
    Code:
       0: new           #4                  // class org/apache/hadoop/hbase/security/access/AccessController$OpType
       3: dup
       4: ldc           #8                  // String GET
       6: iconst_0
       7: ldc           #9                  // String get
       9: invokespecial #10                 // Method "<init>":(Ljava/lang/String;ILjava/lang/String;)V
      12: putstatic     #11                 // Field GET:Lorg/apache/hadoop/hbase/security/access/AccessController$OpType;
      15: new           #4                  // class org/apache/hadoop/hbase/security/access/AccessController$OpType
      18: dup
      19: ldc           #12                 // String EXISTS
      21: iconst_1
      22: ldc           #13                 // String exists
      24: invokespecial #10                 // Method "<init>":(Ljava/lang/String;ILjava/lang/String;)V
      27: putstatic     #14                 // Field EXISTS:Lorg/apache/hadoop/hbase/security/access/AccessController$OpType;
      30: new           #4                  // class org/apache/hadoop/hbase/security/access/AccessController$OpType
      33: dup
      34: ldc           #15                 // String SCAN
      36: iconst_2
      37: ldc           #16                 // String scan
      39: invokespecial #10                 // Method "<init>":(Ljava/lang/String;ILjava/lang/String;)V
      42: putstatic     #17                 // Field SCAN:Lorg/apache/hadoop/hbase/security/access/AccessController$OpType;
      45: new           #4                  // class org/apache/hadoop/hbase/security/access/AccessController$OpType
      48: dup
      49: ldc           #18                 // String PUT
      51: iconst_3
      52: ldc           #19                 // String put
      54: invokespecial #10                 // Method "<init>":(Ljava/lang/String;ILjava/lang/String;)V
      57: putstatic     #20                 // Field PUT:Lorg/apache/hadoop/hbase/security/access/AccessController$OpType;
      60: new           #4                  // class org/apache/hadoop/hbase/security/access/AccessController$OpType
      63: dup
      64: ldc           #21                 // String DELETE
      66: iconst_4
      67: ldc           #22                 // String delete
      69: invokespecial #10                 // Method "<init>":(Ljava/lang/String;ILjava/lang/String;)V
      72: putstatic     #23                 // Field DELETE:Lorg/apache/hadoop/hbase/security/access/AccessController$OpType;
      75: new           #4                  // class org/apache/hadoop/hbase/security/access/AccessController$OpType
      78: dup
      79: ldc           #24                 // String CHECK_AND_PUT
      81: iconst_5
      82: ldc           #25                 // String checkAndPut
      84: invokespecial #10                 // Method "<init>":(Ljava/lang/String;ILjava/lang/String;)V
      87: putstatic     #26                 // Field CHECK_AND_PUT:Lorg/apache/hadoop/hbase/security/access/AccessController$OpType;
      90: new           #4                  // class org/apache/hadoop/hbase/security/access/AccessController$OpType
      93: dup
      94: ldc           #27                 // String CHECK_AND_DELETE
      96: bipush        6
      98: ldc           #28                 // String checkAndDelete
     100: invokespecial #10                 // Method "<init>":(Ljava/lang/String;ILjava/lang/String;)V
     103: putstatic     #29                 // Field CHECK_AND_DELETE:Lorg/apache/hadoop/hbase/security/access/AccessController$OpType;
     106: new           #4                  // class org/apache/hadoop/hbase/security/access/AccessController$OpType
     109: dup
     110: ldc           #30                 // String INCREMENT_COLUMN_VALUE
     112: bipush        7
     114: ldc           #31                 // String incrementColumnValue
     116: invokespecial #10                 // Method "<init>":(Ljava/lang/String;ILjava/lang/String;)V
     119: putstatic     #32                 // Field INCREMENT_COLUMN_VALUE:Lorg/apache/hadoop/hbase/security/access/AccessController$OpType;
     122: new           #4                  // class org/apache/hadoop/hbase/security/access/AccessController$OpType
     125: dup
     126: ldc           #33                 // String APPEND
     128: bipush        8
     130: ldc           #34                 // String append
     132: invokespecial #10                 // Method "<init>":(Ljava/lang/String;ILjava/lang/String;)V
     135: putstatic     #35                 // Field APPEND:Lorg/apache/hadoop/hbase/security/access/AccessController$OpType;
     138: new           #4                  // class org/apache/hadoop/hbase/security/access/AccessController$OpType
     141: dup
     142: ldc           #36                 // String INCREMENT
     144: bipush        9
     146: ldc           #37                 // String increment
     148: invokespecial #10                 // Method "<init>":(Ljava/lang/String;ILjava/lang/String;)V
     151: putstatic     #38                 // Field INCREMENT:Lorg/apache/hadoop/hbase/security/access/AccessController$OpType;
     154: bipush        10
     156: anewarray     #4                  // class org/apache/hadoop/hbase/security/access/AccessController$OpType
     159: dup
     160: iconst_0
     161: getstatic     #11                 // Field GET:Lorg/apache/hadoop/hbase/security/access/AccessController$OpType;
     164: aastore
     165: dup
     166: iconst_1
     167: getstatic     #14                 // Field EXISTS:Lorg/apache/hadoop/hbase/security/access/AccessController$OpType;
     170: aastore
     171: dup
     172: iconst_2
     173: getstatic     #17                 // Field SCAN:Lorg/apache/hadoop/hbase/security/access/AccessController$OpType;
     176: aastore
     177: dup
     178: iconst_3
     179: getstatic     #20                 // Field PUT:Lorg/apache/hadoop/hbase/security/access/AccessController$OpType;
     182: aastore
     183: dup
     184: iconst_4
     185: getstatic     #23                 // Field DELETE:Lorg/apache/hadoop/hbase/security/access/AccessController$OpType;
     188: aastore
     189: dup
     190: iconst_5
     191: getstatic     #26                 // Field CHECK_AND_PUT:Lorg/apache/hadoop/hbase/security/access/AccessController$OpType;
     194: aastore
     195: dup
     196: bipush        6
     198: getstatic     #29                 // Field CHECK_AND_DELETE:Lorg/apache/hadoop/hbase/security/access/AccessController$OpType;
     201: aastore
     202: dup
     203: bipush        7
     205: getstatic     #32                 // Field INCREMENT_COLUMN_VALUE:Lorg/apache/hadoop/hbase/security/access/AccessController$OpType;
     208: aastore
     209: dup
     210: bipush        8
     212: getstatic     #35                 // Field APPEND:Lorg/apache/hadoop/hbase/security/access/AccessController$OpType;
     215: aastore
     216: dup
     217: bipush        9
     219: getstatic     #38                 // Field INCREMENT:Lorg/apache/hadoop/hbase/security/access/AccessController$OpType;
     222: aastore
     223: putstatic     #1                  // Field $VALUES:[Lorg/apache/hadoop/hbase/security/access/AccessController$OpType;
     226: return
}
