Compiled from "AccessChecker.java"
public class org.apache.hadoop.hbase.security.access.AccessChecker$InputUser extends org.apache.hadoop.hbase.security.User {
  public org.apache.hadoop.hbase.security.access.AccessChecker$InputUser(java.lang.String, java.lang.String[]);
    Code:
       0: aload_0
       1: invokespecial #1                  // Method org/apache/hadoop/hbase/security/User."<init>":()V
       4: aload_0
       5: aconst_null
       6: putfield      #2                  // Field shortName:Ljava/lang/String;
       9: aload_0
      10: aload_1
      11: putfield      #3                  // Field name:Ljava/lang/String;
      14: aload_0
      15: aload_2
      16: putfield      #4                  // Field groups:[Ljava/lang/String;
      19: return

  public java.lang.String getShortName();
    Code:
       0: aload_0
       1: getfield      #2                  // Field shortName:Ljava/lang/String;
       4: ifnonnull     72
       7: aload_0
       8: new           #5                  // class org/apache/hadoop/security/HadoopKerberosName
      11: dup
      12: aload_0
      13: getfield      #3                  // Field name:Ljava/lang/String;
      16: invokespecial #6                  // Method org/apache/hadoop/security/HadoopKerberosName."<init>":(Ljava/lang/String;)V
      19: invokevirtual #7                  // Method org/apache/hadoop/security/HadoopKerberosName.getShortName:()Ljava/lang/String;
      22: putfield      #2                  // Field shortName:Ljava/lang/String;
      25: goto          72
      28: astore_1
      29: new           #9                  // class java/lang/IllegalArgumentException
      32: dup
      33: new           #10                 // class java/lang/StringBuilder
      36: dup
      37: invokespecial #11                 // Method java/lang/StringBuilder."<init>":()V
      40: ldc           #12                 // String Illegal principal name
      42: invokevirtual #13                 // Method java/lang/StringBuilder.append:(Ljava/lang/String;)Ljava/lang/StringBuilder;
      45: aload_0
      46: getfield      #3                  // Field name:Ljava/lang/String;
      49: invokevirtual #13                 // Method java/lang/StringBuilder.append:(Ljava/lang/String;)Ljava/lang/StringBuilder;
      52: ldc           #14                 // String :
      54: invokevirtual #13                 // Method java/lang/StringBuilder.append:(Ljava/lang/String;)Ljava/lang/StringBuilder;
      57: aload_1
      58: invokevirtual #15                 // Method java/io/IOException.toString:()Ljava/lang/String;
      61: invokevirtual #13                 // Method java/lang/StringBuilder.append:(Ljava/lang/String;)Ljava/lang/StringBuilder;
      64: invokevirtual #16                 // Method java/lang/StringBuilder.toString:()Ljava/lang/String;
      67: aload_1
      68: invokespecial #17                 // Method java/lang/IllegalArgumentException."<init>":(Ljava/lang/String;Ljava/lang/Throwable;)V
      71: athrow
      72: aload_0
      73: getfield      #2                  // Field shortName:Ljava/lang/String;
      76: areturn
    Exception table:
       from    to  target type
           7    25    28   Class java/io/IOException

  public java.lang.String getName();
    Code:
       0: aload_0
       1: getfield      #3                  // Field name:Ljava/lang/String;
       4: areturn

  public java.lang.String[] getGroupNames();
    Code:
       0: aload_0
       1: getfield      #4                  // Field groups:[Ljava/lang/String;
       4: areturn

  public <T> T runAs(java.security.PrivilegedAction<T>);
    Code:
       0: new           #18                 // class java/lang/UnsupportedOperationException
       3: dup
       4: ldc           #19                 // String Method not supported, this class has limited implementation
       6: invokespecial #20                 // Method java/lang/UnsupportedOperationException."<init>":(Ljava/lang/String;)V
       9: athrow

  public <T> T runAs(java.security.PrivilegedExceptionAction<T>) throws java.io.IOException, java.lang.InterruptedException;
    Code:
       0: new           #18                 // class java/lang/UnsupportedOperationException
       3: dup
       4: ldc           #19                 // String Method not supported, this class has limited implementation
       6: invokespecial #20                 // Method java/lang/UnsupportedOperationException."<init>":(Ljava/lang/String;)V
       9: athrow

  public java.lang.String toString();
    Code:
       0: aload_0
       1: getfield      #3                  // Field name:Ljava/lang/String;
       4: areturn
}
