Compiled from "AcidGuaranteesTestTool.java"
public class org.apache.hadoop.hbase.AcidGuaranteesTestTool$AtomicityWriter extends org.apache.hadoop.hbase.MultithreadedTestUtil$RepeatingTestThread {
  java.util.Random rand;

  byte[] data;

  byte[][] targetRows;

  byte[][] targetFamilies;

  org.apache.hadoop.hbase.client.Connection connection;

  org.apache.hadoop.hbase.client.Table table;

  java.util.concurrent.atomic.AtomicLong numWritten;

  public org.apache.hadoop.hbase.AcidGuaranteesTestTool$AtomicityWriter(org.apache.hadoop.hbase.MultithreadedTestUtil$TestContext, byte[][], byte[][], java.util.concurrent.ExecutorService) throws java.io.IOException;
    Code:
       0: aload_0
       1: aload_1
       2: invokespecial #1                  // Method org/apache/hadoop/hbase/MultithreadedTestUtil$RepeatingTestThread."<init>":(Lorg/apache/hadoop/hbase/MultithreadedTestUtil$TestContext;)V
       5: aload_0
       6: new           #2                  // class java/util/Random
       9: dup
      10: invokespecial #3                  // Method java/util/Random."<init>":()V
      13: putfield      #4                  // Field rand:Ljava/util/Random;
      16: aload_0
      17: bipush        10
      19: newarray       byte
      21: putfield      #5                  // Field data:[B
      24: aload_0
      25: new           #6                  // class java/util/concurrent/atomic/AtomicLong
      28: dup
      29: invokespecial #7                  // Method java/util/concurrent/atomic/AtomicLong."<init>":()V
      32: putfield      #8                  // Field numWritten:Ljava/util/concurrent/atomic/AtomicLong;
      35: aload_0
      36: aload_2
      37: putfield      #9                  // Field targetRows:[[B
      40: aload_0
      41: aload_3
      42: putfield      #10                 // Field targetFamilies:[[B
      45: aload_0
      46: aload_1
      47: invokevirtual #11                 // Method org/apache/hadoop/hbase/MultithreadedTestUtil$TestContext.getConf:()Lorg/apache/hadoop/conf/Configuration;
      50: aload         4
      52: invokestatic  #12                 // Method org/apache/hadoop/hbase/client/ConnectionFactory.createConnection:(Lorg/apache/hadoop/conf/Configuration;Ljava/util/concurrent/ExecutorService;)Lorg/apache/hadoop/hbase/client/Connection;
      55: putfield      #13                 // Field connection:Lorg/apache/hadoop/hbase/client/Connection;
      58: aload_0
      59: aload_0
      60: getfield      #13                 // Field connection:Lorg/apache/hadoop/hbase/client/Connection;
      63: getstatic     #14                 // Field org/apache/hadoop/hbase/AcidGuaranteesTestTool.TABLE_NAME:Lorg/apache/hadoop/hbase/TableName;
      66: invokeinterface #15,  2           // InterfaceMethod org/apache/hadoop/hbase/client/Connection.getTable:(Lorg/apache/hadoop/hbase/TableName;)Lorg/apache/hadoop/hbase/client/Table;
      71: putfield      #16                 // Field table:Lorg/apache/hadoop/hbase/client/Table;
      74: return

  public void doAnAction() throws java.lang.Exception;
    Code:
       0: aload_0
       1: getfield      #9                  // Field targetRows:[[B
       4: aload_0
       5: getfield      #4                  // Field rand:Ljava/util/Random;
       8: aload_0
       9: getfield      #9                  // Field targetRows:[[B
      12: arraylength
      13: invokevirtual #17                 // Method java/util/Random.nextInt:(I)I
      16: aaload
      17: astore_1
      18: new           #18                 // class org/apache/hadoop/hbase/client/Put
      21: dup
      22: aload_1
      23: invokespecial #19                 // Method org/apache/hadoop/hbase/client/Put."<init>":([B)V
      26: astore_2
      27: aload_0
      28: getfield      #4                  // Field rand:Ljava/util/Random;
      31: aload_0
      32: getfield      #5                  // Field data:[B
      35: invokevirtual #20                 // Method java/util/Random.nextBytes:([B)V
      38: aload_0
      39: getfield      #10                 // Field targetFamilies:[[B
      42: astore_3
      43: aload_3
      44: arraylength
      45: istore        4
      47: iconst_0
      48: istore        5
      50: iload         5
      52: iload         4
      54: if_icmpge     124
      57: aload_3
      58: iload         5
      60: aaload
      61: astore        6
      63: iconst_0
      64: istore        7
      66: iload         7
      68: getstatic     #21                 // Field org/apache/hadoop/hbase/AcidGuaranteesTestTool.NUM_COLS_TO_CHECK:I
      71: if_icmpge     118
      74: new           #22                 // class java/lang/StringBuilder
      77: dup
      78: invokespecial #23                 // Method java/lang/StringBuilder."<init>":()V
      81: ldc           #24                 // String col
      83: invokevirtual #25                 // Method java/lang/StringBuilder.append:(Ljava/lang/String;)Ljava/lang/StringBuilder;
      86: iload         7
      88: invokevirtual #26                 // Method java/lang/StringBuilder.append:(I)Ljava/lang/StringBuilder;
      91: invokevirtual #27                 // Method java/lang/StringBuilder.toString:()Ljava/lang/String;
      94: invokestatic  #28                 // Method org/apache/hadoop/hbase/util/Bytes.toBytes:(Ljava/lang/String;)[B
      97: astore        8
      99: aload_2
     100: aload         6
     102: aload         8
     104: aload_0
     105: getfield      #5                  // Field data:[B
     108: invokevirtual #29                 // Method org/apache/hadoop/hbase/client/Put.addColumn:([B[B[B)Lorg/apache/hadoop/hbase/client/Put;
     111: pop
     112: iinc          7, 1
     115: goto          66
     118: iinc          5, 1
     121: goto          50
     124: aload_0
     125: getfield      #16                 // Field table:Lorg/apache/hadoop/hbase/client/Table;
     128: aload_2
     129: invokeinterface #30,  2           // InterfaceMethod org/apache/hadoop/hbase/client/Table.put:(Lorg/apache/hadoop/hbase/client/Put;)V
     134: aload_0
     135: getfield      #8                  // Field numWritten:Ljava/util/concurrent/atomic/AtomicLong;
     138: invokevirtual #31                 // Method java/util/concurrent/atomic/AtomicLong.getAndIncrement:()J
     141: pop2
     142: return

  public void workDone() throws java.io.IOException;
    Code:
       0: aload_0
       1: getfield      #16                 // Field table:Lorg/apache/hadoop/hbase/client/Table;
       4: invokeinterface #32,  1           // InterfaceMethod org/apache/hadoop/hbase/client/Table.close:()V
       9: aload_0
      10: getfield      #13                 // Field connection:Lorg/apache/hadoop/hbase/client/Connection;
      13: invokeinterface #33,  1           // InterfaceMethod org/apache/hadoop/hbase/client/Connection.close:()V
      18: goto          33
      21: astore_1
      22: aload_0
      23: getfield      #13                 // Field connection:Lorg/apache/hadoop/hbase/client/Connection;
      26: invokeinterface #33,  1           // InterfaceMethod org/apache/hadoop/hbase/client/Connection.close:()V
      31: aload_1
      32: athrow
      33: return
    Exception table:
       from    to  target type
           0     9    21   any
}
