Compiled from "ActivePolicyEnforcement.java"
public class org.apache.hadoop.hbase.quotas.ActivePolicyEnforcement {
  public org.apache.hadoop.hbase.quotas.ActivePolicyEnforcement(java.util.Map<org.apache.hadoop.hbase.TableName, org.apache.hadoop.hbase.quotas.SpaceViolationPolicyEnforcement>, java.util.Map<org.apache.hadoop.hbase.TableName, org.apache.hadoop.hbase.quotas.SpaceQuotaSnapshot>, org.apache.hadoop.hbase.regionserver.RegionServerServices);
    Code:
       0: aload_0
       1: aload_1
       2: aload_2
       3: aload_3
       4: invokestatic  #1                  // Method org/apache/hadoop/hbase/quotas/SpaceViolationPolicyEnforcementFactory.getInstance:()Lorg/apache/hadoop/hbase/quotas/SpaceViolationPolicyEnforcementFactory;
       7: invokespecial #2                  // Method "<init>":(Ljava/util/Map;Ljava/util/Map;Lorg/apache/hadoop/hbase/regionserver/RegionServerServices;Lorg/apache/hadoop/hbase/quotas/SpaceViolationPolicyEnforcementFactory;)V
      10: return

  public org.apache.hadoop.hbase.quotas.ActivePolicyEnforcement(java.util.Map<org.apache.hadoop.hbase.TableName, org.apache.hadoop.hbase.quotas.SpaceViolationPolicyEnforcement>, java.util.Map<org.apache.hadoop.hbase.TableName, org.apache.hadoop.hbase.quotas.SpaceQuotaSnapshot>, org.apache.hadoop.hbase.regionserver.RegionServerServices, org.apache.hadoop.hbase.quotas.SpaceViolationPolicyEnforcementFactory);
    Code:
       0: aload_0
       1: invokespecial #3                  // Method java/lang/Object."<init>":()V
       4: aload_0
       5: aload_1
       6: putfield      #4                  // Field activePolicies:Ljava/util/Map;
       9: aload_0
      10: aload_2
      11: putfield      #5                  // Field snapshots:Ljava/util/Map;
      14: aload_0
      15: aload_3
      16: putfield      #6                  // Field rss:Lorg/apache/hadoop/hbase/regionserver/RegionServerServices;
      19: aload_0
      20: aload         4
      22: putfield      #7                  // Field factory:Lorg/apache/hadoop/hbase/quotas/SpaceViolationPolicyEnforcementFactory;
      25: aload_0
      26: new           #8                  // class java/util/HashMap
      29: dup
      30: invokespecial #9                  // Method java/util/HashMap."<init>":()V
      33: putfield      #10                 // Field locallyCachedPolicies:Ljava/util/Map;
      36: return

  public org.apache.hadoop.hbase.quotas.SpaceViolationPolicyEnforcement getPolicyEnforcement(org.apache.hadoop.hbase.regionserver.Region);
    Code:
       0: aload_0
       1: aload_1
       2: invokestatic  #11                 // Method java/util/Objects.requireNonNull:(Ljava/lang/Object;)Ljava/lang/Object;
       5: checkcast     #12                 // class org/apache/hadoop/hbase/regionserver/Region
       8: invokeinterface #13,  1           // InterfaceMethod org/apache/hadoop/hbase/regionserver/Region.getTableDescriptor:()Lorg/apache/hadoop/hbase/client/TableDescriptor;
      13: invokeinterface #14,  1           // InterfaceMethod org/apache/hadoop/hbase/client/TableDescriptor.getTableName:()Lorg/apache/hadoop/hbase/TableName;
      18: invokevirtual #15                 // Method getPolicyEnforcement:(Lorg/apache/hadoop/hbase/TableName;)Lorg/apache/hadoop/hbase/quotas/SpaceViolationPolicyEnforcement;
      21: areturn

  public org.apache.hadoop.hbase.quotas.SpaceViolationPolicyEnforcement getPolicyEnforcement(org.apache.hadoop.hbase.TableName);
    Code:
       0: aload_0
       1: getfield      #4                  // Field activePolicies:Ljava/util/Map;
       4: aload_1
       5: invokestatic  #11                 // Method java/util/Objects.requireNonNull:(Ljava/lang/Object;)Ljava/lang/Object;
       8: invokeinterface #16,  2           // InterfaceMethod java/util/Map.get:(Ljava/lang/Object;)Ljava/lang/Object;
      13: checkcast     #17                 // class org/apache/hadoop/hbase/quotas/SpaceViolationPolicyEnforcement
      16: astore_2
      17: aload_2
      18: ifnonnull     100
      21: aload_0
      22: getfield      #10                 // Field locallyCachedPolicies:Ljava/util/Map;
      25: dup
      26: astore_3
      27: monitorenter
      28: aload_0
      29: getfield      #10                 // Field locallyCachedPolicies:Ljava/util/Map;
      32: aload_1
      33: invokeinterface #16,  2           // InterfaceMethod java/util/Map.get:(Ljava/lang/Object;)Ljava/lang/Object;
      38: checkcast     #17                 // class org/apache/hadoop/hbase/quotas/SpaceViolationPolicyEnforcement
      41: astore_2
      42: aload_2
      43: ifnull        50
      46: aload_2
      47: aload_3
      48: monitorexit
      49: areturn
      50: aload_0
      51: getfield      #7                  // Field factory:Lorg/apache/hadoop/hbase/quotas/SpaceViolationPolicyEnforcementFactory;
      54: aload_0
      55: getfield      #6                  // Field rss:Lorg/apache/hadoop/hbase/regionserver/RegionServerServices;
      58: aload_1
      59: aload_0
      60: getfield      #5                  // Field snapshots:Ljava/util/Map;
      63: aload_1
      64: invokeinterface #16,  2           // InterfaceMethod java/util/Map.get:(Ljava/lang/Object;)Ljava/lang/Object;
      69: checkcast     #18                 // class org/apache/hadoop/hbase/quotas/SpaceQuotaSnapshot
      72: invokevirtual #19                 // Method org/apache/hadoop/hbase/quotas/SpaceViolationPolicyEnforcementFactory.createWithoutViolation:(Lorg/apache/hadoop/hbase/regionserver/RegionServerServices;Lorg/apache/hadoop/hbase/TableName;Lorg/apache/hadoop/hbase/quotas/SpaceQuotaSnapshot;)Lorg/apache/hadoop/hbase/quotas/SpaceViolationPolicyEnforcement;
      75: astore_2
      76: aload_0
      77: getfield      #10                 // Field locallyCachedPolicies:Ljava/util/Map;
      80: aload_1
      81: aload_2
      82: invokeinterface #20,  3           // InterfaceMethod java/util/Map.put:(Ljava/lang/Object;Ljava/lang/Object;)Ljava/lang/Object;
      87: pop
      88: aload_3
      89: monitorexit
      90: goto          100
      93: astore        4
      95: aload_3
      96: monitorexit
      97: aload         4
      99: athrow
     100: aload_2
     101: areturn
    Exception table:
       from    to  target type
          28    49    93   any
          50    90    93   any
          93    97    93   any

  public java.util.Map<org.apache.hadoop.hbase.TableName, org.apache.hadoop.hbase.quotas.SpaceViolationPolicyEnforcement> getPolicies();
    Code:
       0: aload_0
       1: getfield      #4                  // Field activePolicies:Ljava/util/Map;
       4: invokestatic  #21                 // Method java/util/Collections.unmodifiableMap:(Ljava/util/Map;)Ljava/util/Map;
       7: areturn

  java.util.Map<org.apache.hadoop.hbase.TableName, org.apache.hadoop.hbase.quotas.SpaceViolationPolicyEnforcement> getLocallyCachedPolicies();
    Code:
       0: aload_0
       1: getfield      #10                 // Field locallyCachedPolicies:Ljava/util/Map;
       4: invokestatic  #21                 // Method java/util/Collections.unmodifiableMap:(Ljava/util/Map;)Ljava/util/Map;
       7: areturn

  public java.lang.String toString();
    Code:
       0: new           #22                 // class java/lang/StringBuilder
       3: dup
       4: invokespecial #23                 // Method java/lang/StringBuilder."<init>":()V
       7: aload_0
       8: invokevirtual #24                 // Method java/lang/Object.getClass:()Ljava/lang/Class;
      11: invokevirtual #25                 // Method java/lang/Class.getSimpleName:()Ljava/lang/String;
      14: invokevirtual #26                 // Method java/lang/StringBuilder.append:(Ljava/lang/String;)Ljava/lang/StringBuilder;
      17: ldc           #27                 // String :
      19: invokevirtual #26                 // Method java/lang/StringBuilder.append:(Ljava/lang/String;)Ljava/lang/StringBuilder;
      22: aload_0
      23: getfield      #4                  // Field activePolicies:Ljava/util/Map;
      26: invokevirtual #28                 // Method java/lang/StringBuilder.append:(Ljava/lang/Object;)Ljava/lang/StringBuilder;
      29: invokevirtual #29                 // Method java/lang/StringBuilder.toString:()Ljava/lang/String;
      32: areturn
}
