Compiled from "AdminProtos.java"
final class org.apache.hadoop.hbase.protobuf.generated.AdminProtos$AdminService$1 extends org.apache.hadoop.hbase.protobuf.generated.AdminProtos$AdminService {
  final org.apache.hadoop.hbase.protobuf.generated.AdminProtos$AdminService$Interface val$impl;

  org.apache.hadoop.hbase.protobuf.generated.AdminProtos$AdminService$1(org.apache.hadoop.hbase.protobuf.generated.AdminProtos$AdminService$Interface);
    Code:
       0: aload_0
       1: aload_1
       2: putfield      #1                  // Field val$impl:Lorg/apache/hadoop/hbase/protobuf/generated/AdminProtos$AdminService$Interface;
       5: aload_0
       6: invokespecial #2                  // Method org/apache/hadoop/hbase/protobuf/generated/AdminProtos$AdminService."<init>":()V
       9: return

  public void getRegionInfo(com.google.protobuf.RpcController, org.apache.hadoop.hbase.protobuf.generated.AdminProtos$GetRegionInfoRequest, com.google.protobuf.RpcCallback<org.apache.hadoop.hbase.protobuf.generated.AdminProtos$GetRegionInfoResponse>);
    Code:
       0: aload_0
       1: getfield      #1                  // Field val$impl:Lorg/apache/hadoop/hbase/protobuf/generated/AdminProtos$AdminService$Interface;
       4: aload_1
       5: aload_2
       6: aload_3
       7: invokeinterface #3,  4            // InterfaceMethod org/apache/hadoop/hbase/protobuf/generated/AdminProtos$AdminService$Interface.getRegionInfo:(Lcom/google/protobuf/RpcController;Lorg/apache/hadoop/hbase/protobuf/generated/AdminProtos$GetRegionInfoRequest;Lcom/google/protobuf/RpcCallback;)V
      12: return

  public void getStoreFile(com.google.protobuf.RpcController, org.apache.hadoop.hbase.protobuf.generated.AdminProtos$GetStoreFileRequest, com.google.protobuf.RpcCallback<org.apache.hadoop.hbase.protobuf.generated.AdminProtos$GetStoreFileResponse>);
    Code:
       0: aload_0
       1: getfield      #1                  // Field val$impl:Lorg/apache/hadoop/hbase/protobuf/generated/AdminProtos$AdminService$Interface;
       4: aload_1
       5: aload_2
       6: aload_3
       7: invokeinterface #4,  4            // InterfaceMethod org/apache/hadoop/hbase/protobuf/generated/AdminProtos$AdminService$Interface.getStoreFile:(Lcom/google/protobuf/RpcController;Lorg/apache/hadoop/hbase/protobuf/generated/AdminProtos$GetStoreFileRequest;Lcom/google/protobuf/RpcCallback;)V
      12: return

  public void getOnlineRegion(com.google.protobuf.RpcController, org.apache.hadoop.hbase.protobuf.generated.AdminProtos$GetOnlineRegionRequest, com.google.protobuf.RpcCallback<org.apache.hadoop.hbase.protobuf.generated.AdminProtos$GetOnlineRegionResponse>);
    Code:
       0: aload_0
       1: getfield      #1                  // Field val$impl:Lorg/apache/hadoop/hbase/protobuf/generated/AdminProtos$AdminService$Interface;
       4: aload_1
       5: aload_2
       6: aload_3
       7: invokeinterface #5,  4            // InterfaceMethod org/apache/hadoop/hbase/protobuf/generated/AdminProtos$AdminService$Interface.getOnlineRegion:(Lcom/google/protobuf/RpcController;Lorg/apache/hadoop/hbase/protobuf/generated/AdminProtos$GetOnlineRegionRequest;Lcom/google/protobuf/RpcCallback;)V
      12: return

  public void openRegion(com.google.protobuf.RpcController, org.apache.hadoop.hbase.protobuf.generated.AdminProtos$OpenRegionRequest, com.google.protobuf.RpcCallback<org.apache.hadoop.hbase.protobuf.generated.AdminProtos$OpenRegionResponse>);
    Code:
       0: aload_0
       1: getfield      #1                  // Field val$impl:Lorg/apache/hadoop/hbase/protobuf/generated/AdminProtos$AdminService$Interface;
       4: aload_1
       5: aload_2
       6: aload_3
       7: invokeinterface #6,  4            // InterfaceMethod org/apache/hadoop/hbase/protobuf/generated/AdminProtos$AdminService$Interface.openRegion:(Lcom/google/protobuf/RpcController;Lorg/apache/hadoop/hbase/protobuf/generated/AdminProtos$OpenRegionRequest;Lcom/google/protobuf/RpcCallback;)V
      12: return

  public void warmupRegion(com.google.protobuf.RpcController, org.apache.hadoop.hbase.protobuf.generated.AdminProtos$WarmupRegionRequest, com.google.protobuf.RpcCallback<org.apache.hadoop.hbase.protobuf.generated.AdminProtos$WarmupRegionResponse>);
    Code:
       0: aload_0
       1: getfield      #1                  // Field val$impl:Lorg/apache/hadoop/hbase/protobuf/generated/AdminProtos$AdminService$Interface;
       4: aload_1
       5: aload_2
       6: aload_3
       7: invokeinterface #7,  4            // InterfaceMethod org/apache/hadoop/hbase/protobuf/generated/AdminProtos$AdminService$Interface.warmupRegion:(Lcom/google/protobuf/RpcController;Lorg/apache/hadoop/hbase/protobuf/generated/AdminProtos$WarmupRegionRequest;Lcom/google/protobuf/RpcCallback;)V
      12: return

  public void closeRegion(com.google.protobuf.RpcController, org.apache.hadoop.hbase.protobuf.generated.AdminProtos$CloseRegionRequest, com.google.protobuf.RpcCallback<org.apache.hadoop.hbase.protobuf.generated.AdminProtos$CloseRegionResponse>);
    Code:
       0: aload_0
       1: getfield      #1                  // Field val$impl:Lorg/apache/hadoop/hbase/protobuf/generated/AdminProtos$AdminService$Interface;
       4: aload_1
       5: aload_2
       6: aload_3
       7: invokeinterface #8,  4            // InterfaceMethod org/apache/hadoop/hbase/protobuf/generated/AdminProtos$AdminService$Interface.closeRegion:(Lcom/google/protobuf/RpcController;Lorg/apache/hadoop/hbase/protobuf/generated/AdminProtos$CloseRegionRequest;Lcom/google/protobuf/RpcCallback;)V
      12: return

  public void flushRegion(com.google.protobuf.RpcController, org.apache.hadoop.hbase.protobuf.generated.AdminProtos$FlushRegionRequest, com.google.protobuf.RpcCallback<org.apache.hadoop.hbase.protobuf.generated.AdminProtos$FlushRegionResponse>);
    Code:
       0: aload_0
       1: getfield      #1                  // Field val$impl:Lorg/apache/hadoop/hbase/protobuf/generated/AdminProtos$AdminService$Interface;
       4: aload_1
       5: aload_2
       6: aload_3
       7: invokeinterface #9,  4            // InterfaceMethod org/apache/hadoop/hbase/protobuf/generated/AdminProtos$AdminService$Interface.flushRegion:(Lcom/google/protobuf/RpcController;Lorg/apache/hadoop/hbase/protobuf/generated/AdminProtos$FlushRegionRequest;Lcom/google/protobuf/RpcCallback;)V
      12: return

  public void splitRegion(com.google.protobuf.RpcController, org.apache.hadoop.hbase.protobuf.generated.AdminProtos$SplitRegionRequest, com.google.protobuf.RpcCallback<org.apache.hadoop.hbase.protobuf.generated.AdminProtos$SplitRegionResponse>);
    Code:
       0: aload_0
       1: getfield      #1                  // Field val$impl:Lorg/apache/hadoop/hbase/protobuf/generated/AdminProtos$AdminService$Interface;
       4: aload_1
       5: aload_2
       6: aload_3
       7: invokeinterface #10,  4           // InterfaceMethod org/apache/hadoop/hbase/protobuf/generated/AdminProtos$AdminService$Interface.splitRegion:(Lcom/google/protobuf/RpcController;Lorg/apache/hadoop/hbase/protobuf/generated/AdminProtos$SplitRegionRequest;Lcom/google/protobuf/RpcCallback;)V
      12: return

  public void compactRegion(com.google.protobuf.RpcController, org.apache.hadoop.hbase.protobuf.generated.AdminProtos$CompactRegionRequest, com.google.protobuf.RpcCallback<org.apache.hadoop.hbase.protobuf.generated.AdminProtos$CompactRegionResponse>);
    Code:
       0: aload_0
       1: getfield      #1                  // Field val$impl:Lorg/apache/hadoop/hbase/protobuf/generated/AdminProtos$AdminService$Interface;
       4: aload_1
       5: aload_2
       6: aload_3
       7: invokeinterface #11,  4           // InterfaceMethod org/apache/hadoop/hbase/protobuf/generated/AdminProtos$AdminService$Interface.compactRegion:(Lcom/google/protobuf/RpcController;Lorg/apache/hadoop/hbase/protobuf/generated/AdminProtos$CompactRegionRequest;Lcom/google/protobuf/RpcCallback;)V
      12: return

  public void mergeRegions(com.google.protobuf.RpcController, org.apache.hadoop.hbase.protobuf.generated.AdminProtos$MergeRegionsRequest, com.google.protobuf.RpcCallback<org.apache.hadoop.hbase.protobuf.generated.AdminProtos$MergeRegionsResponse>);
    Code:
       0: aload_0
       1: getfield      #1                  // Field val$impl:Lorg/apache/hadoop/hbase/protobuf/generated/AdminProtos$AdminService$Interface;
       4: aload_1
       5: aload_2
       6: aload_3
       7: invokeinterface #12,  4           // InterfaceMethod org/apache/hadoop/hbase/protobuf/generated/AdminProtos$AdminService$Interface.mergeRegions:(Lcom/google/protobuf/RpcController;Lorg/apache/hadoop/hbase/protobuf/generated/AdminProtos$MergeRegionsRequest;Lcom/google/protobuf/RpcCallback;)V
      12: return

  public void replicateWALEntry(com.google.protobuf.RpcController, org.apache.hadoop.hbase.protobuf.generated.AdminProtos$ReplicateWALEntryRequest, com.google.protobuf.RpcCallback<org.apache.hadoop.hbase.protobuf.generated.AdminProtos$ReplicateWALEntryResponse>);
    Code:
       0: aload_0
       1: getfield      #1                  // Field val$impl:Lorg/apache/hadoop/hbase/protobuf/generated/AdminProtos$AdminService$Interface;
       4: aload_1
       5: aload_2
       6: aload_3
       7: invokeinterface #13,  4           // InterfaceMethod org/apache/hadoop/hbase/protobuf/generated/AdminProtos$AdminService$Interface.replicateWALEntry:(Lcom/google/protobuf/RpcController;Lorg/apache/hadoop/hbase/protobuf/generated/AdminProtos$ReplicateWALEntryRequest;Lcom/google/protobuf/RpcCallback;)V
      12: return

  public void replay(com.google.protobuf.RpcController, org.apache.hadoop.hbase.protobuf.generated.AdminProtos$ReplicateWALEntryRequest, com.google.protobuf.RpcCallback<org.apache.hadoop.hbase.protobuf.generated.AdminProtos$ReplicateWALEntryResponse>);
    Code:
       0: aload_0
       1: getfield      #1                  // Field val$impl:Lorg/apache/hadoop/hbase/protobuf/generated/AdminProtos$AdminService$Interface;
       4: aload_1
       5: aload_2
       6: aload_3
       7: invokeinterface #14,  4           // InterfaceMethod org/apache/hadoop/hbase/protobuf/generated/AdminProtos$AdminService$Interface.replay:(Lcom/google/protobuf/RpcController;Lorg/apache/hadoop/hbase/protobuf/generated/AdminProtos$ReplicateWALEntryRequest;Lcom/google/protobuf/RpcCallback;)V
      12: return

  public void rollWALWriter(com.google.protobuf.RpcController, org.apache.hadoop.hbase.protobuf.generated.AdminProtos$RollWALWriterRequest, com.google.protobuf.RpcCallback<org.apache.hadoop.hbase.protobuf.generated.AdminProtos$RollWALWriterResponse>);
    Code:
       0: aload_0
       1: getfield      #1                  // Field val$impl:Lorg/apache/hadoop/hbase/protobuf/generated/AdminProtos$AdminService$Interface;
       4: aload_1
       5: aload_2
       6: aload_3
       7: invokeinterface #15,  4           // InterfaceMethod org/apache/hadoop/hbase/protobuf/generated/AdminProtos$AdminService$Interface.rollWALWriter:(Lcom/google/protobuf/RpcController;Lorg/apache/hadoop/hbase/protobuf/generated/AdminProtos$RollWALWriterRequest;Lcom/google/protobuf/RpcCallback;)V
      12: return

  public void getServerInfo(com.google.protobuf.RpcController, org.apache.hadoop.hbase.protobuf.generated.AdminProtos$GetServerInfoRequest, com.google.protobuf.RpcCallback<org.apache.hadoop.hbase.protobuf.generated.AdminProtos$GetServerInfoResponse>);
    Code:
       0: aload_0
       1: getfield      #1                  // Field val$impl:Lorg/apache/hadoop/hbase/protobuf/generated/AdminProtos$AdminService$Interface;
       4: aload_1
       5: aload_2
       6: aload_3
       7: invokeinterface #16,  4           // InterfaceMethod org/apache/hadoop/hbase/protobuf/generated/AdminProtos$AdminService$Interface.getServerInfo:(Lcom/google/protobuf/RpcController;Lorg/apache/hadoop/hbase/protobuf/generated/AdminProtos$GetServerInfoRequest;Lcom/google/protobuf/RpcCallback;)V
      12: return

  public void stopServer(com.google.protobuf.RpcController, org.apache.hadoop.hbase.protobuf.generated.AdminProtos$StopServerRequest, com.google.protobuf.RpcCallback<org.apache.hadoop.hbase.protobuf.generated.AdminProtos$StopServerResponse>);
    Code:
       0: aload_0
       1: getfield      #1                  // Field val$impl:Lorg/apache/hadoop/hbase/protobuf/generated/AdminProtos$AdminService$Interface;
       4: aload_1
       5: aload_2
       6: aload_3
       7: invokeinterface #17,  4           // InterfaceMethod org/apache/hadoop/hbase/protobuf/generated/AdminProtos$AdminService$Interface.stopServer:(Lcom/google/protobuf/RpcController;Lorg/apache/hadoop/hbase/protobuf/generated/AdminProtos$StopServerRequest;Lcom/google/protobuf/RpcCallback;)V
      12: return

  public void updateFavoredNodes(com.google.protobuf.RpcController, org.apache.hadoop.hbase.protobuf.generated.AdminProtos$UpdateFavoredNodesRequest, com.google.protobuf.RpcCallback<org.apache.hadoop.hbase.protobuf.generated.AdminProtos$UpdateFavoredNodesResponse>);
    Code:
       0: aload_0
       1: getfield      #1                  // Field val$impl:Lorg/apache/hadoop/hbase/protobuf/generated/AdminProtos$AdminService$Interface;
       4: aload_1
       5: aload_2
       6: aload_3
       7: invokeinterface #18,  4           // InterfaceMethod org/apache/hadoop/hbase/protobuf/generated/AdminProtos$AdminService$Interface.updateFavoredNodes:(Lcom/google/protobuf/RpcController;Lorg/apache/hadoop/hbase/protobuf/generated/AdminProtos$UpdateFavoredNodesRequest;Lcom/google/protobuf/RpcCallback;)V
      12: return

  public void updateConfiguration(com.google.protobuf.RpcController, org.apache.hadoop.hbase.protobuf.generated.AdminProtos$UpdateConfigurationRequest, com.google.protobuf.RpcCallback<org.apache.hadoop.hbase.protobuf.generated.AdminProtos$UpdateConfigurationResponse>);
    Code:
       0: aload_0
       1: getfield      #1                  // Field val$impl:Lorg/apache/hadoop/hbase/protobuf/generated/AdminProtos$AdminService$Interface;
       4: aload_1
       5: aload_2
       6: aload_3
       7: invokeinterface #19,  4           // InterfaceMethod org/apache/hadoop/hbase/protobuf/generated/AdminProtos$AdminService$Interface.updateConfiguration:(Lcom/google/protobuf/RpcController;Lorg/apache/hadoop/hbase/protobuf/generated/AdminProtos$UpdateConfigurationRequest;Lcom/google/protobuf/RpcCallback;)V
      12: return
}
