Compiled from "AdminProtos.java"
public final class org.apache.hadoop.hbase.protobuf.generated.AdminProtos$CloseRegionRequest extends com.google.protobuf.GeneratedMessage implements org.apache.hadoop.hbase.protobuf.generated.AdminProtos$CloseRegionRequestOrBuilder {
  public static com.google.protobuf.Parser<org.apache.hadoop.hbase.protobuf.generated.AdminProtos$CloseRegionRequest> PARSER;

  public static final int REGION_FIELD_NUMBER;

  public static final int VERSION_OF_CLOSING_NODE_FIELD_NUMBER;

  public static final int TRANSITION_IN_ZK_FIELD_NUMBER;

  public static final int DESTINATION_SERVER_FIELD_NUMBER;

  public static final int SERVERSTARTCODE_FIELD_NUMBER;

  public static org.apache.hadoop.hbase.protobuf.generated.AdminProtos$CloseRegionRequest getDefaultInstance();
    Code:
       0: getstatic     #18                 // Field defaultInstance:Lorg/apache/hadoop/hbase/protobuf/generated/AdminProtos$CloseRegionRequest;
       3: areturn

  public org.apache.hadoop.hbase.protobuf.generated.AdminProtos$CloseRegionRequest getDefaultInstanceForType();
    Code:
       0: getstatic     #18                 // Field defaultInstance:Lorg/apache/hadoop/hbase/protobuf/generated/AdminProtos$CloseRegionRequest;
       3: areturn

  public final com.google.protobuf.UnknownFieldSet getUnknownFields();
    Code:
       0: aload_0
       1: getfield      #15                 // Field unknownFields:Lcom/google/protobuf/UnknownFieldSet;
       4: areturn

  public static final com.google.protobuf.Descriptors$Descriptor getDescriptor();
    Code:
       0: invokestatic  #44                 // Method org/apache/hadoop/hbase/protobuf/generated/AdminProtos.access$10200:()Lcom/google/protobuf/Descriptors$Descriptor;
       3: areturn

  protected com.google.protobuf.GeneratedMessage$FieldAccessorTable internalGetFieldAccessorTable();
    Code:
       0: invokestatic  #45                 // Method org/apache/hadoop/hbase/protobuf/generated/AdminProtos.access$10300:()Lcom/google/protobuf/GeneratedMessage$FieldAccessorTable;
       3: ldc           #46                 // class org/apache/hadoop/hbase/protobuf/generated/AdminProtos$CloseRegionRequest
       5: ldc           #47                 // class org/apache/hadoop/hbase/protobuf/generated/AdminProtos$CloseRegionRequest$Builder
       7: invokevirtual #48                 // Method com/google/protobuf/GeneratedMessage$FieldAccessorTable.ensureFieldAccessorsInitialized:(Ljava/lang/Class;Ljava/lang/Class;)Lcom/google/protobuf/GeneratedMessage$FieldAccessorTable;
      10: areturn

  public com.google.protobuf.Parser<org.apache.hadoop.hbase.protobuf.generated.AdminProtos$CloseRegionRequest> getParserForType();
    Code:
       0: getstatic     #49                 // Field PARSER:Lcom/google/protobuf/Parser;
       3: areturn

  public boolean hasRegion();
    Code:
       0: aload_0
       1: getfield      #1                  // Field bitField0_:I
       4: iconst_1
       5: iand
       6: iconst_1
       7: if_icmpne     14
      10: iconst_1
      11: goto          15
      14: iconst_0
      15: ireturn

  public org.apache.hadoop.hbase.protobuf.generated.HBaseProtos$RegionSpecifier getRegion();
    Code:
       0: aload_0
       1: getfield      #6                  // Field region_:Lorg/apache/hadoop/hbase/protobuf/generated/HBaseProtos$RegionSpecifier;
       4: areturn

  public org.apache.hadoop.hbase.protobuf.generated.HBaseProtos$RegionSpecifierOrBuilder getRegionOrBuilder();
    Code:
       0: aload_0
       1: getfield      #6                  // Field region_:Lorg/apache/hadoop/hbase/protobuf/generated/HBaseProtos$RegionSpecifier;
       4: areturn

  public boolean hasVersionOfClosingNode();
    Code:
       0: aload_0
       1: getfield      #1                  // Field bitField0_:I
       4: iconst_2
       5: iand
       6: iconst_2
       7: if_icmpne     14
      10: iconst_1
      11: goto          15
      14: iconst_0
      15: ireturn

  public int getVersionOfClosingNode();
    Code:
       0: aload_0
       1: getfield      #5                  // Field versionOfClosingNode_:I
       4: ireturn

  public boolean hasTransitionInZK();
    Code:
       0: aload_0
       1: getfield      #1                  // Field bitField0_:I
       4: iconst_4
       5: iand
       6: iconst_4
       7: if_icmpne     14
      10: iconst_1
      11: goto          15
      14: iconst_0
      15: ireturn

  public boolean getTransitionInZK();
    Code:
       0: aload_0
       1: getfield      #4                  // Field transitionInZK_:Z
       4: ireturn

  public boolean hasDestinationServer();
    Code:
       0: aload_0
       1: getfield      #1                  // Field bitField0_:I
       4: bipush        8
       6: iand
       7: bipush        8
       9: if_icmpne     16
      12: iconst_1
      13: goto          17
      16: iconst_0
      17: ireturn

  public org.apache.hadoop.hbase.protobuf.generated.HBaseProtos$ServerName getDestinationServer();
    Code:
       0: aload_0
       1: getfield      #3                  // Field destinationServer_:Lorg/apache/hadoop/hbase/protobuf/generated/HBaseProtos$ServerName;
       4: areturn

  public org.apache.hadoop.hbase.protobuf.generated.HBaseProtos$ServerNameOrBuilder getDestinationServerOrBuilder();
    Code:
       0: aload_0
       1: getfield      #3                  // Field destinationServer_:Lorg/apache/hadoop/hbase/protobuf/generated/HBaseProtos$ServerName;
       4: areturn

  public boolean hasServerStartCode();
    Code:
       0: aload_0
       1: getfield      #1                  // Field bitField0_:I
       4: bipush        16
       6: iand
       7: bipush        16
       9: if_icmpne     16
      12: iconst_1
      13: goto          17
      16: iconst_0
      17: ireturn

  public long getServerStartCode();
    Code:
       0: aload_0
       1: getfield      #2                  // Field serverStartCode_:J
       4: lreturn

  public final boolean isInitialized();
    Code:
       0: aload_0
       1: getfield      #11                 // Field memoizedIsInitialized:B
       4: istore_1
       5: iload_1
       6: iconst_m1
       7: if_icmpeq     21
      10: iload_1
      11: iconst_1
      12: if_icmpne     19
      15: iconst_1
      16: goto          20
      19: iconst_0
      20: ireturn
      21: aload_0
      22: invokevirtual #52                 // Method hasRegion:()Z
      25: ifne          35
      28: aload_0
      29: iconst_0
      30: putfield      #11                 // Field memoizedIsInitialized:B
      33: iconst_0
      34: ireturn
      35: aload_0
      36: invokevirtual #53                 // Method getRegion:()Lorg/apache/hadoop/hbase/protobuf/generated/HBaseProtos$RegionSpecifier;
      39: invokevirtual #54                 // Method org/apache/hadoop/hbase/protobuf/generated/HBaseProtos$RegionSpecifier.isInitialized:()Z
      42: ifne          52
      45: aload_0
      46: iconst_0
      47: putfield      #11                 // Field memoizedIsInitialized:B
      50: iconst_0
      51: ireturn
      52: aload_0
      53: invokevirtual #55                 // Method hasDestinationServer:()Z
      56: ifeq          76
      59: aload_0
      60: invokevirtual #56                 // Method getDestinationServer:()Lorg/apache/hadoop/hbase/protobuf/generated/HBaseProtos$ServerName;
      63: invokevirtual #57                 // Method org/apache/hadoop/hbase/protobuf/generated/HBaseProtos$ServerName.isInitialized:()Z
      66: ifne          76
      69: aload_0
      70: iconst_0
      71: putfield      #11                 // Field memoizedIsInitialized:B
      74: iconst_0
      75: ireturn
      76: aload_0
      77: iconst_1
      78: putfield      #11                 // Field memoizedIsInitialized:B
      81: iconst_1
      82: ireturn

  public void writeTo(com.google.protobuf.CodedOutputStream) throws java.io.IOException;
    Code:
       0: aload_0
       1: invokevirtual #58                 // Method getSerializedSize:()I
       4: pop
       5: aload_0
       6: getfield      #1                  // Field bitField0_:I
       9: iconst_1
      10: iand
      11: iconst_1
      12: if_icmpne     24
      15: aload_1
      16: iconst_1
      17: aload_0
      18: getfield      #6                  // Field region_:Lorg/apache/hadoop/hbase/protobuf/generated/HBaseProtos$RegionSpecifier;
      21: invokevirtual #59                 // Method com/google/protobuf/CodedOutputStream.writeMessage:(ILcom/google/protobuf/MessageLite;)V
      24: aload_0
      25: getfield      #1                  // Field bitField0_:I
      28: iconst_2
      29: iand
      30: iconst_2
      31: if_icmpne     43
      34: aload_1
      35: iconst_2
      36: aload_0
      37: getfield      #5                  // Field versionOfClosingNode_:I
      40: invokevirtual #60                 // Method com/google/protobuf/CodedOutputStream.writeUInt32:(II)V
      43: aload_0
      44: getfield      #1                  // Field bitField0_:I
      47: iconst_4
      48: iand
      49: iconst_4
      50: if_icmpne     62
      53: aload_1
      54: iconst_3
      55: aload_0
      56: getfield      #4                  // Field transitionInZK_:Z
      59: invokevirtual #61                 // Method com/google/protobuf/CodedOutputStream.writeBool:(IZ)V
      62: aload_0
      63: getfield      #1                  // Field bitField0_:I
      66: bipush        8
      68: iand
      69: bipush        8
      71: if_icmpne     83
      74: aload_1
      75: iconst_4
      76: aload_0
      77: getfield      #3                  // Field destinationServer_:Lorg/apache/hadoop/hbase/protobuf/generated/HBaseProtos$ServerName;
      80: invokevirtual #59                 // Method com/google/protobuf/CodedOutputStream.writeMessage:(ILcom/google/protobuf/MessageLite;)V
      83: aload_0
      84: getfield      #1                  // Field bitField0_:I
      87: bipush        16
      89: iand
      90: bipush        16
      92: if_icmpne     104
      95: aload_1
      96: iconst_5
      97: aload_0
      98: getfield      #2                  // Field serverStartCode_:J
     101: invokevirtual #62                 // Method com/google/protobuf/CodedOutputStream.writeUInt64:(IJ)V
     104: aload_0
     105: invokevirtual #63                 // Method getUnknownFields:()Lcom/google/protobuf/UnknownFieldSet;
     108: aload_1
     109: invokevirtual #64                 // Method com/google/protobuf/UnknownFieldSet.writeTo:(Lcom/google/protobuf/CodedOutputStream;)V
     112: return

  public int getSerializedSize();
    Code:
       0: aload_0
       1: getfield      #12                 // Field memoizedSerializedSize:I
       4: istore_1
       5: iload_1
       6: iconst_m1
       7: if_icmpeq     12
      10: iload_1
      11: ireturn
      12: iconst_0
      13: istore_1
      14: aload_0
      15: getfield      #1                  // Field bitField0_:I
      18: iconst_1
      19: iand
      20: iconst_1
      21: if_icmpne     35
      24: iload_1
      25: iconst_1
      26: aload_0
      27: getfield      #6                  // Field region_:Lorg/apache/hadoop/hbase/protobuf/generated/HBaseProtos$RegionSpecifier;
      30: invokestatic  #65                 // Method com/google/protobuf/CodedOutputStream.computeMessageSize:(ILcom/google/protobuf/MessageLite;)I
      33: iadd
      34: istore_1
      35: aload_0
      36: getfield      #1                  // Field bitField0_:I
      39: iconst_2
      40: iand
      41: iconst_2
      42: if_icmpne     56
      45: iload_1
      46: iconst_2
      47: aload_0
      48: getfield      #5                  // Field versionOfClosingNode_:I
      51: invokestatic  #66                 // Method com/google/protobuf/CodedOutputStream.computeUInt32Size:(II)I
      54: iadd
      55: istore_1
      56: aload_0
      57: getfield      #1                  // Field bitField0_:I
      60: iconst_4
      61: iand
      62: iconst_4
      63: if_icmpne     77
      66: iload_1
      67: iconst_3
      68: aload_0
      69: getfield      #4                  // Field transitionInZK_:Z
      72: invokestatic  #67                 // Method com/google/protobuf/CodedOutputStream.computeBoolSize:(IZ)I
      75: iadd
      76: istore_1
      77: aload_0
      78: getfield      #1                  // Field bitField0_:I
      81: bipush        8
      83: iand
      84: bipush        8
      86: if_icmpne     100
      89: iload_1
      90: iconst_4
      91: aload_0
      92: getfield      #3                  // Field destinationServer_:Lorg/apache/hadoop/hbase/protobuf/generated/HBaseProtos$ServerName;
      95: invokestatic  #65                 // Method com/google/protobuf/CodedOutputStream.computeMessageSize:(ILcom/google/protobuf/MessageLite;)I
      98: iadd
      99: istore_1
     100: aload_0
     101: getfield      #1                  // Field bitField0_:I
     104: bipush        16
     106: iand
     107: bipush        16
     109: if_icmpne     123
     112: iload_1
     113: iconst_5
     114: aload_0
     115: getfield      #2                  // Field serverStartCode_:J
     118: invokestatic  #68                 // Method com/google/protobuf/CodedOutputStream.computeUInt64Size:(IJ)I
     121: iadd
     122: istore_1
     123: iload_1
     124: aload_0
     125: invokevirtual #63                 // Method getUnknownFields:()Lcom/google/protobuf/UnknownFieldSet;
     128: invokevirtual #69                 // Method com/google/protobuf/UnknownFieldSet.getSerializedSize:()I
     131: iadd
     132: istore_1
     133: aload_0
     134: iload_1
     135: putfield      #12                 // Field memoizedSerializedSize:I
     138: iload_1
     139: ireturn

  protected java.lang.Object writeReplace() throws java.io.ObjectStreamException;
    Code:
       0: aload_0
       1: invokespecial #70                 // Method com/google/protobuf/GeneratedMessage.writeReplace:()Ljava/lang/Object;
       4: areturn

  public boolean equals(java.lang.Object);
    Code:
       0: aload_1
       1: aload_0
       2: if_acmpne     7
       5: iconst_1
       6: ireturn
       7: aload_1
       8: instanceof    #46                 // class org/apache/hadoop/hbase/protobuf/generated/AdminProtos$CloseRegionRequest
      11: ifne          20
      14: aload_0
      15: aload_1
      16: invokespecial #71                 // Method com/google/protobuf/GeneratedMessage.equals:(Ljava/lang/Object;)Z
      19: ireturn
      20: aload_1
      21: checkcast     #46                 // class org/apache/hadoop/hbase/protobuf/generated/AdminProtos$CloseRegionRequest
      24: astore_2
      25: iconst_1
      26: istore_3
      27: iload_3
      28: ifeq          46
      31: aload_0
      32: invokevirtual #52                 // Method hasRegion:()Z
      35: aload_2
      36: invokevirtual #52                 // Method hasRegion:()Z
      39: if_icmpne     46
      42: iconst_1
      43: goto          47
      46: iconst_0
      47: istore_3
      48: aload_0
      49: invokevirtual #52                 // Method hasRegion:()Z
      52: ifeq          79
      55: iload_3
      56: ifeq          77
      59: aload_0
      60: invokevirtual #53                 // Method getRegion:()Lorg/apache/hadoop/hbase/protobuf/generated/HBaseProtos$RegionSpecifier;
      63: aload_2
      64: invokevirtual #53                 // Method getRegion:()Lorg/apache/hadoop/hbase/protobuf/generated/HBaseProtos$RegionSpecifier;
      67: invokevirtual #72                 // Method org/apache/hadoop/hbase/protobuf/generated/HBaseProtos$RegionSpecifier.equals:(Ljava/lang/Object;)Z
      70: ifeq          77
      73: iconst_1
      74: goto          78
      77: iconst_0
      78: istore_3
      79: iload_3
      80: ifeq          98
      83: aload_0
      84: invokevirtual #73                 // Method hasVersionOfClosingNode:()Z
      87: aload_2
      88: invokevirtual #73                 // Method hasVersionOfClosingNode:()Z
      91: if_icmpne     98
      94: iconst_1
      95: goto          99
      98: iconst_0
      99: istore_3
     100: aload_0
     101: invokevirtual #73                 // Method hasVersionOfClosingNode:()Z
     104: ifeq          128
     107: iload_3
     108: ifeq          126
     111: aload_0
     112: invokevirtual #74                 // Method getVersionOfClosingNode:()I
     115: aload_2
     116: invokevirtual #74                 // Method getVersionOfClosingNode:()I
     119: if_icmpne     126
     122: iconst_1
     123: goto          127
     126: iconst_0
     127: istore_3
     128: iload_3
     129: ifeq          147
     132: aload_0
     133: invokevirtual #75                 // Method hasTransitionInZK:()Z
     136: aload_2
     137: invokevirtual #75                 // Method hasTransitionInZK:()Z
     140: if_icmpne     147
     143: iconst_1
     144: goto          148
     147: iconst_0
     148: istore_3
     149: aload_0
     150: invokevirtual #75                 // Method hasTransitionInZK:()Z
     153: ifeq          177
     156: iload_3
     157: ifeq          175
     160: aload_0
     161: invokevirtual #76                 // Method getTransitionInZK:()Z
     164: aload_2
     165: invokevirtual #76                 // Method getTransitionInZK:()Z
     168: if_icmpne     175
     171: iconst_1
     172: goto          176
     175: iconst_0
     176: istore_3
     177: iload_3
     178: ifeq          196
     181: aload_0
     182: invokevirtual #55                 // Method hasDestinationServer:()Z
     185: aload_2
     186: invokevirtual #55                 // Method hasDestinationServer:()Z
     189: if_icmpne     196
     192: iconst_1
     193: goto          197
     196: iconst_0
     197: istore_3
     198: aload_0
     199: invokevirtual #55                 // Method hasDestinationServer:()Z
     202: ifeq          229
     205: iload_3
     206: ifeq          227
     209: aload_0
     210: invokevirtual #56                 // Method getDestinationServer:()Lorg/apache/hadoop/hbase/protobuf/generated/HBaseProtos$ServerName;
     213: aload_2
     214: invokevirtual #56                 // Method getDestinationServer:()Lorg/apache/hadoop/hbase/protobuf/generated/HBaseProtos$ServerName;
     217: invokevirtual #77                 // Method org/apache/hadoop/hbase/protobuf/generated/HBaseProtos$ServerName.equals:(Ljava/lang/Object;)Z
     220: ifeq          227
     223: iconst_1
     224: goto          228
     227: iconst_0
     228: istore_3
     229: iload_3
     230: ifeq          248
     233: aload_0
     234: invokevirtual #78                 // Method hasServerStartCode:()Z
     237: aload_2
     238: invokevirtual #78                 // Method hasServerStartCode:()Z
     241: if_icmpne     248
     244: iconst_1
     245: goto          249
     248: iconst_0
     249: istore_3
     250: aload_0
     251: invokevirtual #78                 // Method hasServerStartCode:()Z
     254: ifeq          279
     257: iload_3
     258: ifeq          277
     261: aload_0
     262: invokevirtual #79                 // Method getServerStartCode:()J
     265: aload_2
     266: invokevirtual #79                 // Method getServerStartCode:()J
     269: lcmp
     270: ifne          277
     273: iconst_1
     274: goto          278
     277: iconst_0
     278: istore_3
     279: iload_3
     280: ifeq          301
     283: aload_0
     284: invokevirtual #63                 // Method getUnknownFields:()Lcom/google/protobuf/UnknownFieldSet;
     287: aload_2
     288: invokevirtual #63                 // Method getUnknownFields:()Lcom/google/protobuf/UnknownFieldSet;
     291: invokevirtual #80                 // Method com/google/protobuf/UnknownFieldSet.equals:(Ljava/lang/Object;)Z
     294: ifeq          301
     297: iconst_1
     298: goto          302
     301: iconst_0
     302: istore_3
     303: iload_3
     304: ireturn

  public int hashCode();
    Code:
       0: aload_0
       1: getfield      #13                 // Field memoizedHashCode:I
       4: ifeq          12
       7: aload_0
       8: getfield      #13                 // Field memoizedHashCode:I
      11: ireturn
      12: bipush        41
      14: istore_1
      15: bipush        19
      17: iload_1
      18: imul
      19: aload_0
      20: invokevirtual #81                 // Method getDescriptorForType:()Lcom/google/protobuf/Descriptors$Descriptor;
      23: invokevirtual #82                 // Method java/lang/Object.hashCode:()I
      26: iadd
      27: istore_1
      28: aload_0
      29: invokevirtual #52                 // Method hasRegion:()Z
      32: ifeq          55
      35: bipush        37
      37: iload_1
      38: imul
      39: iconst_1
      40: iadd
      41: istore_1
      42: bipush        53
      44: iload_1
      45: imul
      46: aload_0
      47: invokevirtual #53                 // Method getRegion:()Lorg/apache/hadoop/hbase/protobuf/generated/HBaseProtos$RegionSpecifier;
      50: invokevirtual #83                 // Method org/apache/hadoop/hbase/protobuf/generated/HBaseProtos$RegionSpecifier.hashCode:()I
      53: iadd
      54: istore_1
      55: aload_0
      56: invokevirtual #73                 // Method hasVersionOfClosingNode:()Z
      59: ifeq          79
      62: bipush        37
      64: iload_1
      65: imul
      66: iconst_2
      67: iadd
      68: istore_1
      69: bipush        53
      71: iload_1
      72: imul
      73: aload_0
      74: invokevirtual #74                 // Method getVersionOfClosingNode:()I
      77: iadd
      78: istore_1
      79: aload_0
      80: invokevirtual #75                 // Method hasTransitionInZK:()Z
      83: ifeq          106
      86: bipush        37
      88: iload_1
      89: imul
      90: iconst_3
      91: iadd
      92: istore_1
      93: bipush        53
      95: iload_1
      96: imul
      97: aload_0
      98: invokevirtual #76                 // Method getTransitionInZK:()Z
     101: invokestatic  #84                 // Method hashBoolean:(Z)I
     104: iadd
     105: istore_1
     106: aload_0
     107: invokevirtual #55                 // Method hasDestinationServer:()Z
     110: ifeq          133
     113: bipush        37
     115: iload_1
     116: imul
     117: iconst_4
     118: iadd
     119: istore_1
     120: bipush        53
     122: iload_1
     123: imul
     124: aload_0
     125: invokevirtual #56                 // Method getDestinationServer:()Lorg/apache/hadoop/hbase/protobuf/generated/HBaseProtos$ServerName;
     128: invokevirtual #85                 // Method org/apache/hadoop/hbase/protobuf/generated/HBaseProtos$ServerName.hashCode:()I
     131: iadd
     132: istore_1
     133: aload_0
     134: invokevirtual #78                 // Method hasServerStartCode:()Z
     137: ifeq          160
     140: bipush        37
     142: iload_1
     143: imul
     144: iconst_5
     145: iadd
     146: istore_1
     147: bipush        53
     149: iload_1
     150: imul
     151: aload_0
     152: invokevirtual #79                 // Method getServerStartCode:()J
     155: invokestatic  #86                 // Method hashLong:(J)I
     158: iadd
     159: istore_1
     160: bipush        29
     162: iload_1
     163: imul
     164: aload_0
     165: invokevirtual #63                 // Method getUnknownFields:()Lcom/google/protobuf/UnknownFieldSet;
     168: invokevirtual #87                 // Method com/google/protobuf/UnknownFieldSet.hashCode:()I
     171: iadd
     172: istore_1
     173: aload_0
     174: iload_1
     175: putfield      #13                 // Field memoizedHashCode:I
     178: iload_1
     179: ireturn

  public static org.apache.hadoop.hbase.protobuf.generated.AdminProtos$CloseRegionRequest parseFrom(com.google.protobuf.ByteString) throws com.google.protobuf.InvalidProtocolBufferException;
    Code:
       0: getstatic     #49                 // Field PARSER:Lcom/google/protobuf/Parser;
       3: aload_0
       4: invokeinterface #88,  2           // InterfaceMethod com/google/protobuf/Parser.parseFrom:(Lcom/google/protobuf/ByteString;)Ljava/lang/Object;
       9: checkcast     #46                 // class org/apache/hadoop/hbase/protobuf/generated/AdminProtos$CloseRegionRequest
      12: areturn

  public static org.apache.hadoop.hbase.protobuf.generated.AdminProtos$CloseRegionRequest parseFrom(com.google.protobuf.ByteString, com.google.protobuf.ExtensionRegistryLite) throws com.google.protobuf.InvalidProtocolBufferException;
    Code:
       0: getstatic     #49                 // Field PARSER:Lcom/google/protobuf/Parser;
       3: aload_0
       4: aload_1
       5: invokeinterface #89,  3           // InterfaceMethod com/google/protobuf/Parser.parseFrom:(Lcom/google/protobuf/ByteString;Lcom/google/protobuf/ExtensionRegistryLite;)Ljava/lang/Object;
      10: checkcast     #46                 // class org/apache/hadoop/hbase/protobuf/generated/AdminProtos$CloseRegionRequest
      13: areturn

  public static org.apache.hadoop.hbase.protobuf.generated.AdminProtos$CloseRegionRequest parseFrom(byte[]) throws com.google.protobuf.InvalidProtocolBufferException;
    Code:
       0: getstatic     #49                 // Field PARSER:Lcom/google/protobuf/Parser;
       3: aload_0
       4: invokeinterface #90,  2           // InterfaceMethod com/google/protobuf/Parser.parseFrom:([B)Ljava/lang/Object;
       9: checkcast     #46                 // class org/apache/hadoop/hbase/protobuf/generated/AdminProtos$CloseRegionRequest
      12: areturn

  public static org.apache.hadoop.hbase.protobuf.generated.AdminProtos$CloseRegionRequest parseFrom(byte[], com.google.protobuf.ExtensionRegistryLite) throws com.google.protobuf.InvalidProtocolBufferException;
    Code:
       0: getstatic     #49                 // Field PARSER:Lcom/google/protobuf/Parser;
       3: aload_0
       4: aload_1
       5: invokeinterface #91,  3           // InterfaceMethod com/google/protobuf/Parser.parseFrom:([BLcom/google/protobuf/ExtensionRegistryLite;)Ljava/lang/Object;
      10: checkcast     #46                 // class org/apache/hadoop/hbase/protobuf/generated/AdminProtos$CloseRegionRequest
      13: areturn

  public static org.apache.hadoop.hbase.protobuf.generated.AdminProtos$CloseRegionRequest parseFrom(java.io.InputStream) throws java.io.IOException;
    Code:
       0: getstatic     #49                 // Field PARSER:Lcom/google/protobuf/Parser;
       3: aload_0
       4: invokeinterface #92,  2           // InterfaceMethod com/google/protobuf/Parser.parseFrom:(Ljava/io/InputStream;)Ljava/lang/Object;
       9: checkcast     #46                 // class org/apache/hadoop/hbase/protobuf/generated/AdminProtos$CloseRegionRequest
      12: areturn

  public static org.apache.hadoop.hbase.protobuf.generated.AdminProtos$CloseRegionRequest parseFrom(java.io.InputStream, com.google.protobuf.ExtensionRegistryLite) throws java.io.IOException;
    Code:
       0: getstatic     #49                 // Field PARSER:Lcom/google/protobuf/Parser;
       3: aload_0
       4: aload_1
       5: invokeinterface #93,  3           // InterfaceMethod com/google/protobuf/Parser.parseFrom:(Ljava/io/InputStream;Lcom/google/protobuf/ExtensionRegistryLite;)Ljava/lang/Object;
      10: checkcast     #46                 // class org/apache/hadoop/hbase/protobuf/generated/AdminProtos$CloseRegionRequest
      13: areturn

  public static org.apache.hadoop.hbase.protobuf.generated.AdminProtos$CloseRegionRequest parseDelimitedFrom(java.io.InputStream) throws java.io.IOException;
    Code:
       0: getstatic     #49                 // Field PARSER:Lcom/google/protobuf/Parser;
       3: aload_0
       4: invokeinterface #94,  2           // InterfaceMethod com/google/protobuf/Parser.parseDelimitedFrom:(Ljava/io/InputStream;)Ljava/lang/Object;
       9: checkcast     #46                 // class org/apache/hadoop/hbase/protobuf/generated/AdminProtos$CloseRegionRequest
      12: areturn

  public static org.apache.hadoop.hbase.protobuf.generated.AdminProtos$CloseRegionRequest parseDelimitedFrom(java.io.InputStream, com.google.protobuf.ExtensionRegistryLite) throws java.io.IOException;
    Code:
       0: getstatic     #49                 // Field PARSER:Lcom/google/protobuf/Parser;
       3: aload_0
       4: aload_1
       5: invokeinterface #95,  3           // InterfaceMethod com/google/protobuf/Parser.parseDelimitedFrom:(Ljava/io/InputStream;Lcom/google/protobuf/ExtensionRegistryLite;)Ljava/lang/Object;
      10: checkcast     #46                 // class org/apache/hadoop/hbase/protobuf/generated/AdminProtos$CloseRegionRequest
      13: areturn

  public static org.apache.hadoop.hbase.protobuf.generated.AdminProtos$CloseRegionRequest parseFrom(com.google.protobuf.CodedInputStream) throws java.io.IOException;
    Code:
       0: getstatic     #49                 // Field PARSER:Lcom/google/protobuf/Parser;
       3: aload_0
       4: invokeinterface #96,  2           // InterfaceMethod com/google/protobuf/Parser.parseFrom:(Lcom/google/protobuf/CodedInputStream;)Ljava/lang/Object;
       9: checkcast     #46                 // class org/apache/hadoop/hbase/protobuf/generated/AdminProtos$CloseRegionRequest
      12: areturn

  public static org.apache.hadoop.hbase.protobuf.generated.AdminProtos$CloseRegionRequest parseFrom(com.google.protobuf.CodedInputStream, com.google.protobuf.ExtensionRegistryLite) throws java.io.IOException;
    Code:
       0: getstatic     #49                 // Field PARSER:Lcom/google/protobuf/Parser;
       3: aload_0
       4: aload_1
       5: invokeinterface #97,  3           // InterfaceMethod com/google/protobuf/Parser.parseFrom:(Lcom/google/protobuf/CodedInputStream;Lcom/google/protobuf/ExtensionRegistryLite;)Ljava/lang/Object;
      10: checkcast     #46                 // class org/apache/hadoop/hbase/protobuf/generated/AdminProtos$CloseRegionRequest
      13: areturn

  public static org.apache.hadoop.hbase.protobuf.generated.AdminProtos$CloseRegionRequest$Builder newBuilder();
    Code:
       0: invokestatic  #98                 // Method org/apache/hadoop/hbase/protobuf/generated/AdminProtos$CloseRegionRequest$Builder.access$10500:()Lorg/apache/hadoop/hbase/protobuf/generated/AdminProtos$CloseRegionRequest$Builder;
       3: areturn

  public org.apache.hadoop.hbase.protobuf.generated.AdminProtos$CloseRegionRequest$Builder newBuilderForType();
    Code:
       0: invokestatic  #99                 // Method newBuilder:()Lorg/apache/hadoop/hbase/protobuf/generated/AdminProtos$CloseRegionRequest$Builder;
       3: areturn

  public static org.apache.hadoop.hbase.protobuf.generated.AdminProtos$CloseRegionRequest$Builder newBuilder(org.apache.hadoop.hbase.protobuf.generated.AdminProtos$CloseRegionRequest);
    Code:
       0: invokestatic  #99                 // Method newBuilder:()Lorg/apache/hadoop/hbase/protobuf/generated/AdminProtos$CloseRegionRequest$Builder;
       3: aload_0
       4: invokevirtual #100                // Method org/apache/hadoop/hbase/protobuf/generated/AdminProtos$CloseRegionRequest$Builder.mergeFrom:(Lorg/apache/hadoop/hbase/protobuf/generated/AdminProtos$CloseRegionRequest;)Lorg/apache/hadoop/hbase/protobuf/generated/AdminProtos$CloseRegionRequest$Builder;
       7: areturn

  public org.apache.hadoop.hbase.protobuf.generated.AdminProtos$CloseRegionRequest$Builder toBuilder();
    Code:
       0: aload_0
       1: invokestatic  #101                // Method newBuilder:(Lorg/apache/hadoop/hbase/protobuf/generated/AdminProtos$CloseRegionRequest;)Lorg/apache/hadoop/hbase/protobuf/generated/AdminProtos$CloseRegionRequest$Builder;
       4: areturn

  protected org.apache.hadoop.hbase.protobuf.generated.AdminProtos$CloseRegionRequest$Builder newBuilderForType(com.google.protobuf.GeneratedMessage$BuilderParent);
    Code:
       0: new           #47                 // class org/apache/hadoop/hbase/protobuf/generated/AdminProtos$CloseRegionRequest$Builder
       3: dup
       4: aload_1
       5: aconst_null
       6: invokespecial #102                // Method org/apache/hadoop/hbase/protobuf/generated/AdminProtos$CloseRegionRequest$Builder."<init>":(Lcom/google/protobuf/GeneratedMessage$BuilderParent;Lorg/apache/hadoop/hbase/protobuf/generated/AdminProtos$1;)V
       9: astore_2
      10: aload_2
      11: areturn

  protected com.google.protobuf.Message$Builder newBuilderForType(com.google.protobuf.GeneratedMessage$BuilderParent);
    Code:
       0: aload_0
       1: aload_1
       2: invokevirtual #103                // Method newBuilderForType:(Lcom/google/protobuf/GeneratedMessage$BuilderParent;)Lorg/apache/hadoop/hbase/protobuf/generated/AdminProtos$CloseRegionRequest$Builder;
       5: areturn

  public com.google.protobuf.Message$Builder toBuilder();
    Code:
       0: aload_0
       1: invokevirtual #104                // Method toBuilder:()Lorg/apache/hadoop/hbase/protobuf/generated/AdminProtos$CloseRegionRequest$Builder;
       4: areturn

  public com.google.protobuf.Message$Builder newBuilderForType();
    Code:
       0: aload_0
       1: invokevirtual #105                // Method newBuilderForType:()Lorg/apache/hadoop/hbase/protobuf/generated/AdminProtos$CloseRegionRequest$Builder;
       4: areturn

  public com.google.protobuf.MessageLite$Builder toBuilder();
    Code:
       0: aload_0
       1: invokevirtual #104                // Method toBuilder:()Lorg/apache/hadoop/hbase/protobuf/generated/AdminProtos$CloseRegionRequest$Builder;
       4: areturn

  public com.google.protobuf.MessageLite$Builder newBuilderForType();
    Code:
       0: aload_0
       1: invokevirtual #105                // Method newBuilderForType:()Lorg/apache/hadoop/hbase/protobuf/generated/AdminProtos$CloseRegionRequest$Builder;
       4: areturn

  public com.google.protobuf.MessageLite getDefaultInstanceForType();
    Code:
       0: aload_0
       1: invokevirtual #106                // Method getDefaultInstanceForType:()Lorg/apache/hadoop/hbase/protobuf/generated/AdminProtos$CloseRegionRequest;
       4: areturn

  public com.google.protobuf.Message getDefaultInstanceForType();
    Code:
       0: aload_0
       1: invokevirtual #106                // Method getDefaultInstanceForType:()Lorg/apache/hadoop/hbase/protobuf/generated/AdminProtos$CloseRegionRequest;
       4: areturn

  org.apache.hadoop.hbase.protobuf.generated.AdminProtos$CloseRegionRequest(com.google.protobuf.CodedInputStream, com.google.protobuf.ExtensionRegistryLite, org.apache.hadoop.hbase.protobuf.generated.AdminProtos$1) throws com.google.protobuf.InvalidProtocolBufferException;
    Code:
       0: aload_0
       1: aload_1
       2: aload_2
       3: invokespecial #9                  // Method "<init>":(Lcom/google/protobuf/CodedInputStream;Lcom/google/protobuf/ExtensionRegistryLite;)V
       6: return

  static boolean access$10700();
    Code:
       0: getstatic     #8                  // Field alwaysUseFieldBuilders:Z
       3: ireturn

  org.apache.hadoop.hbase.protobuf.generated.AdminProtos$CloseRegionRequest(com.google.protobuf.GeneratedMessage$Builder, org.apache.hadoop.hbase.protobuf.generated.AdminProtos$1);
    Code:
       0: aload_0
       1: aload_1
       2: invokespecial #7                  // Method "<init>":(Lcom/google/protobuf/GeneratedMessage$Builder;)V
       5: return

  static org.apache.hadoop.hbase.protobuf.generated.HBaseProtos$RegionSpecifier access$10902(org.apache.hadoop.hbase.protobuf.generated.AdminProtos$CloseRegionRequest, org.apache.hadoop.hbase.protobuf.generated.HBaseProtos$RegionSpecifier);
    Code:
       0: aload_0
       1: aload_1
       2: dup_x1
       3: putfield      #6                  // Field region_:Lorg/apache/hadoop/hbase/protobuf/generated/HBaseProtos$RegionSpecifier;
       6: areturn

  static int access$11002(org.apache.hadoop.hbase.protobuf.generated.AdminProtos$CloseRegionRequest, int);
    Code:
       0: aload_0
       1: iload_1
       2: dup_x1
       3: putfield      #5                  // Field versionOfClosingNode_:I
       6: ireturn

  static boolean access$11102(org.apache.hadoop.hbase.protobuf.generated.AdminProtos$CloseRegionRequest, boolean);
    Code:
       0: aload_0
       1: iload_1
       2: dup_x1
       3: putfield      #4                  // Field transitionInZK_:Z
       6: ireturn

  static org.apache.hadoop.hbase.protobuf.generated.HBaseProtos$ServerName access$11202(org.apache.hadoop.hbase.protobuf.generated.AdminProtos$CloseRegionRequest, org.apache.hadoop.hbase.protobuf.generated.HBaseProtos$ServerName);
    Code:
       0: aload_0
       1: aload_1
       2: dup_x1
       3: putfield      #3                  // Field destinationServer_:Lorg/apache/hadoop/hbase/protobuf/generated/HBaseProtos$ServerName;
       6: areturn

  static long access$11302(org.apache.hadoop.hbase.protobuf.generated.AdminProtos$CloseRegionRequest, long);
    Code:
       0: aload_0
       1: lload_1
       2: dup2_x1
       3: putfield      #2                  // Field serverStartCode_:J
       6: lreturn

  static int access$11402(org.apache.hadoop.hbase.protobuf.generated.AdminProtos$CloseRegionRequest, int);
    Code:
       0: aload_0
       1: iload_1
       2: dup_x1
       3: putfield      #1                  // Field bitField0_:I
       6: ireturn

  static {};
    Code:
       0: new           #107                // class org/apache/hadoop/hbase/protobuf/generated/AdminProtos$CloseRegionRequest$1
       3: dup
       4: invokespecial #108                // Method org/apache/hadoop/hbase/protobuf/generated/AdminProtos$CloseRegionRequest$1."<init>":()V
       7: putstatic     #49                 // Field PARSER:Lcom/google/protobuf/Parser;
      10: new           #46                 // class org/apache/hadoop/hbase/protobuf/generated/AdminProtos$CloseRegionRequest
      13: dup
      14: iconst_1
      15: invokespecial #109                // Method "<init>":(Z)V
      18: putstatic     #18                 // Field defaultInstance:Lorg/apache/hadoop/hbase/protobuf/generated/AdminProtos$CloseRegionRequest;
      21: getstatic     #18                 // Field defaultInstance:Lorg/apache/hadoop/hbase/protobuf/generated/AdminProtos$CloseRegionRequest;
      24: invokespecial #19                 // Method initFields:()V
      27: return
}
