Compiled from "AdminProtos.java"
final class org.apache.hadoop.hbase.protobuf.generated.AdminProtos$1 implements com.google.protobuf.Descriptors$FileDescriptor$InternalDescriptorAssigner {
  org.apache.hadoop.hbase.protobuf.generated.AdminProtos$1();
    Code:
       0: aload_0
       1: invokespecial #1                  // Method java/lang/Object."<init>":()V
       4: return

  public com.google.protobuf.ExtensionRegistry assignDescriptors(com.google.protobuf.Descriptors$FileDescriptor);
    Code:
       0: aload_1
       1: invokestatic  #2                  // Method org/apache/hadoop/hbase/protobuf/generated/AdminProtos.access$33302:(Lcom/google/protobuf/Descriptors$FileDescriptor;)Lcom/google/protobuf/Descriptors$FileDescriptor;
       4: pop
       5: invokestatic  #3                  // Method org/apache/hadoop/hbase/protobuf/generated/AdminProtos.getDescriptor:()Lcom/google/protobuf/Descriptors$FileDescriptor;
       8: invokevirtual #4                  // Method com/google/protobuf/Descriptors$FileDescriptor.getMessageTypes:()Ljava/util/List;
      11: iconst_0
      12: invokeinterface #5,  2            // InterfaceMethod java/util/List.get:(I)Ljava/lang/Object;
      17: checkcast     #6                  // class com/google/protobuf/Descriptors$Descriptor
      20: invokestatic  #7                  // Method org/apache/hadoop/hbase/protobuf/generated/AdminProtos.access$002:(Lcom/google/protobuf/Descriptors$Descriptor;)Lcom/google/protobuf/Descriptors$Descriptor;
      23: pop
      24: new           #8                  // class com/google/protobuf/GeneratedMessage$FieldAccessorTable
      27: dup
      28: invokestatic  #9                  // Method org/apache/hadoop/hbase/protobuf/generated/AdminProtos.access$000:()Lcom/google/protobuf/Descriptors$Descriptor;
      31: iconst_2
      32: anewarray     #10                 // class java/lang/String
      35: dup
      36: iconst_0
      37: ldc           #11                 // String Region
      39: aastore
      40: dup
      41: iconst_1
      42: ldc           #12                 // String CompactionState
      44: aastore
      45: invokespecial #13                 // Method com/google/protobuf/GeneratedMessage$FieldAccessorTable."<init>":(Lcom/google/protobuf/Descriptors$Descriptor;[Ljava/lang/String;)V
      48: invokestatic  #14                 // Method org/apache/hadoop/hbase/protobuf/generated/AdminProtos.access$102:(Lcom/google/protobuf/GeneratedMessage$FieldAccessorTable;)Lcom/google/protobuf/GeneratedMessage$FieldAccessorTable;
      51: pop
      52: invokestatic  #3                  // Method org/apache/hadoop/hbase/protobuf/generated/AdminProtos.getDescriptor:()Lcom/google/protobuf/Descriptors$FileDescriptor;
      55: invokevirtual #4                  // Method com/google/protobuf/Descriptors$FileDescriptor.getMessageTypes:()Ljava/util/List;
      58: iconst_1
      59: invokeinterface #5,  2            // InterfaceMethod java/util/List.get:(I)Ljava/lang/Object;
      64: checkcast     #6                  // class com/google/protobuf/Descriptors$Descriptor
      67: invokestatic  #15                 // Method org/apache/hadoop/hbase/protobuf/generated/AdminProtos.access$1002:(Lcom/google/protobuf/Descriptors$Descriptor;)Lcom/google/protobuf/Descriptors$Descriptor;
      70: pop
      71: new           #8                  // class com/google/protobuf/GeneratedMessage$FieldAccessorTable
      74: dup
      75: invokestatic  #16                 // Method org/apache/hadoop/hbase/protobuf/generated/AdminProtos.access$1000:()Lcom/google/protobuf/Descriptors$Descriptor;
      78: iconst_2
      79: anewarray     #10                 // class java/lang/String
      82: dup
      83: iconst_0
      84: ldc           #17                 // String RegionInfo
      86: aastore
      87: dup
      88: iconst_1
      89: ldc           #12                 // String CompactionState
      91: aastore
      92: invokespecial #13                 // Method com/google/protobuf/GeneratedMessage$FieldAccessorTable."<init>":(Lcom/google/protobuf/Descriptors$Descriptor;[Ljava/lang/String;)V
      95: invokestatic  #18                 // Method org/apache/hadoop/hbase/protobuf/generated/AdminProtos.access$1102:(Lcom/google/protobuf/GeneratedMessage$FieldAccessorTable;)Lcom/google/protobuf/GeneratedMessage$FieldAccessorTable;
      98: pop
      99: invokestatic  #3                  // Method org/apache/hadoop/hbase/protobuf/generated/AdminProtos.getDescriptor:()Lcom/google/protobuf/Descriptors$FileDescriptor;
     102: invokevirtual #4                  // Method com/google/protobuf/Descriptors$FileDescriptor.getMessageTypes:()Ljava/util/List;
     105: iconst_2
     106: invokeinterface #5,  2            // InterfaceMethod java/util/List.get:(I)Ljava/lang/Object;
     111: checkcast     #6                  // class com/google/protobuf/Descriptors$Descriptor
     114: invokestatic  #19                 // Method org/apache/hadoop/hbase/protobuf/generated/AdminProtos.access$2002:(Lcom/google/protobuf/Descriptors$Descriptor;)Lcom/google/protobuf/Descriptors$Descriptor;
     117: pop
     118: new           #8                  // class com/google/protobuf/GeneratedMessage$FieldAccessorTable
     121: dup
     122: invokestatic  #20                 // Method org/apache/hadoop/hbase/protobuf/generated/AdminProtos.access$2000:()Lcom/google/protobuf/Descriptors$Descriptor;
     125: iconst_2
     126: anewarray     #10                 // class java/lang/String
     129: dup
     130: iconst_0
     131: ldc           #11                 // String Region
     133: aastore
     134: dup
     135: iconst_1
     136: ldc           #21                 // String Family
     138: aastore
     139: invokespecial #13                 // Method com/google/protobuf/GeneratedMessage$FieldAccessorTable."<init>":(Lcom/google/protobuf/Descriptors$Descriptor;[Ljava/lang/String;)V
     142: invokestatic  #22                 // Method org/apache/hadoop/hbase/protobuf/generated/AdminProtos.access$2102:(Lcom/google/protobuf/GeneratedMessage$FieldAccessorTable;)Lcom/google/protobuf/GeneratedMessage$FieldAccessorTable;
     145: pop
     146: invokestatic  #3                  // Method org/apache/hadoop/hbase/protobuf/generated/AdminProtos.getDescriptor:()Lcom/google/protobuf/Descriptors$FileDescriptor;
     149: invokevirtual #4                  // Method com/google/protobuf/Descriptors$FileDescriptor.getMessageTypes:()Ljava/util/List;
     152: iconst_3
     153: invokeinterface #5,  2            // InterfaceMethod java/util/List.get:(I)Ljava/lang/Object;
     158: checkcast     #6                  // class com/google/protobuf/Descriptors$Descriptor
     161: invokestatic  #23                 // Method org/apache/hadoop/hbase/protobuf/generated/AdminProtos.access$3002:(Lcom/google/protobuf/Descriptors$Descriptor;)Lcom/google/protobuf/Descriptors$Descriptor;
     164: pop
     165: new           #8                  // class com/google/protobuf/GeneratedMessage$FieldAccessorTable
     168: dup
     169: invokestatic  #24                 // Method org/apache/hadoop/hbase/protobuf/generated/AdminProtos.access$3000:()Lcom/google/protobuf/Descriptors$Descriptor;
     172: iconst_1
     173: anewarray     #10                 // class java/lang/String
     176: dup
     177: iconst_0
     178: ldc           #25                 // String StoreFile
     180: aastore
     181: invokespecial #13                 // Method com/google/protobuf/GeneratedMessage$FieldAccessorTable."<init>":(Lcom/google/protobuf/Descriptors$Descriptor;[Ljava/lang/String;)V
     184: invokestatic  #26                 // Method org/apache/hadoop/hbase/protobuf/generated/AdminProtos.access$3102:(Lcom/google/protobuf/GeneratedMessage$FieldAccessorTable;)Lcom/google/protobuf/GeneratedMessage$FieldAccessorTable;
     187: pop
     188: invokestatic  #3                  // Method org/apache/hadoop/hbase/protobuf/generated/AdminProtos.getDescriptor:()Lcom/google/protobuf/Descriptors$FileDescriptor;
     191: invokevirtual #4                  // Method com/google/protobuf/Descriptors$FileDescriptor.getMessageTypes:()Ljava/util/List;
     194: iconst_4
     195: invokeinterface #5,  2            // InterfaceMethod java/util/List.get:(I)Ljava/lang/Object;
     200: checkcast     #6                  // class com/google/protobuf/Descriptors$Descriptor
     203: invokestatic  #27                 // Method org/apache/hadoop/hbase/protobuf/generated/AdminProtos.access$3802:(Lcom/google/protobuf/Descriptors$Descriptor;)Lcom/google/protobuf/Descriptors$Descriptor;
     206: pop
     207: new           #8                  // class com/google/protobuf/GeneratedMessage$FieldAccessorTable
     210: dup
     211: invokestatic  #28                 // Method org/apache/hadoop/hbase/protobuf/generated/AdminProtos.access$3800:()Lcom/google/protobuf/Descriptors$Descriptor;
     214: iconst_0
     215: anewarray     #10                 // class java/lang/String
     218: invokespecial #13                 // Method com/google/protobuf/GeneratedMessage$FieldAccessorTable."<init>":(Lcom/google/protobuf/Descriptors$Descriptor;[Ljava/lang/String;)V
     221: invokestatic  #29                 // Method org/apache/hadoop/hbase/protobuf/generated/AdminProtos.access$3902:(Lcom/google/protobuf/GeneratedMessage$FieldAccessorTable;)Lcom/google/protobuf/GeneratedMessage$FieldAccessorTable;
     224: pop
     225: invokestatic  #3                  // Method org/apache/hadoop/hbase/protobuf/generated/AdminProtos.getDescriptor:()Lcom/google/protobuf/Descriptors$FileDescriptor;
     228: invokevirtual #4                  // Method com/google/protobuf/Descriptors$FileDescriptor.getMessageTypes:()Ljava/util/List;
     231: iconst_5
     232: invokeinterface #5,  2            // InterfaceMethod java/util/List.get:(I)Ljava/lang/Object;
     237: checkcast     #6                  // class com/google/protobuf/Descriptors$Descriptor
     240: invokestatic  #30                 // Method org/apache/hadoop/hbase/protobuf/generated/AdminProtos.access$4502:(Lcom/google/protobuf/Descriptors$Descriptor;)Lcom/google/protobuf/Descriptors$Descriptor;
     243: pop
     244: new           #8                  // class com/google/protobuf/GeneratedMessage$FieldAccessorTable
     247: dup
     248: invokestatic  #31                 // Method org/apache/hadoop/hbase/protobuf/generated/AdminProtos.access$4500:()Lcom/google/protobuf/Descriptors$Descriptor;
     251: iconst_1
     252: anewarray     #10                 // class java/lang/String
     255: dup
     256: iconst_0
     257: ldc           #17                 // String RegionInfo
     259: aastore
     260: invokespecial #13                 // Method com/google/protobuf/GeneratedMessage$FieldAccessorTable."<init>":(Lcom/google/protobuf/Descriptors$Descriptor;[Ljava/lang/String;)V
     263: invokestatic  #32                 // Method org/apache/hadoop/hbase/protobuf/generated/AdminProtos.access$4602:(Lcom/google/protobuf/GeneratedMessage$FieldAccessorTable;)Lcom/google/protobuf/GeneratedMessage$FieldAccessorTable;
     266: pop
     267: invokestatic  #3                  // Method org/apache/hadoop/hbase/protobuf/generated/AdminProtos.getDescriptor:()Lcom/google/protobuf/Descriptors$FileDescriptor;
     270: invokevirtual #4                  // Method com/google/protobuf/Descriptors$FileDescriptor.getMessageTypes:()Ljava/util/List;
     273: bipush        6
     275: invokeinterface #5,  2            // InterfaceMethod java/util/List.get:(I)Ljava/lang/Object;
     280: checkcast     #6                  // class com/google/protobuf/Descriptors$Descriptor
     283: invokestatic  #33                 // Method org/apache/hadoop/hbase/protobuf/generated/AdminProtos.access$5402:(Lcom/google/protobuf/Descriptors$Descriptor;)Lcom/google/protobuf/Descriptors$Descriptor;
     286: pop
     287: new           #8                  // class com/google/protobuf/GeneratedMessage$FieldAccessorTable
     290: dup
     291: invokestatic  #34                 // Method org/apache/hadoop/hbase/protobuf/generated/AdminProtos.access$5400:()Lcom/google/protobuf/Descriptors$Descriptor;
     294: iconst_3
     295: anewarray     #10                 // class java/lang/String
     298: dup
     299: iconst_0
     300: ldc           #35                 // String OpenInfo
     302: aastore
     303: dup
     304: iconst_1
     305: ldc           #36                 // String ServerStartCode
     307: aastore
     308: dup
     309: iconst_2
     310: ldc           #37                 // String MasterSystemTime
     312: aastore
     313: invokespecial #13                 // Method com/google/protobuf/GeneratedMessage$FieldAccessorTable."<init>":(Lcom/google/protobuf/Descriptors$Descriptor;[Ljava/lang/String;)V
     316: invokestatic  #38                 // Method org/apache/hadoop/hbase/protobuf/generated/AdminProtos.access$5502:(Lcom/google/protobuf/GeneratedMessage$FieldAccessorTable;)Lcom/google/protobuf/GeneratedMessage$FieldAccessorTable;
     319: pop
     320: invokestatic  #34                 // Method org/apache/hadoop/hbase/protobuf/generated/AdminProtos.access$5400:()Lcom/google/protobuf/Descriptors$Descriptor;
     323: invokevirtual #39                 // Method com/google/protobuf/Descriptors$Descriptor.getNestedTypes:()Ljava/util/List;
     326: iconst_0
     327: invokeinterface #5,  2            // InterfaceMethod java/util/List.get:(I)Ljava/lang/Object;
     332: checkcast     #6                  // class com/google/protobuf/Descriptors$Descriptor
     335: invokestatic  #40                 // Method org/apache/hadoop/hbase/protobuf/generated/AdminProtos.access$5702:(Lcom/google/protobuf/Descriptors$Descriptor;)Lcom/google/protobuf/Descriptors$Descriptor;
     338: pop
     339: new           #8                  // class com/google/protobuf/GeneratedMessage$FieldAccessorTable
     342: dup
     343: invokestatic  #41                 // Method org/apache/hadoop/hbase/protobuf/generated/AdminProtos.access$5700:()Lcom/google/protobuf/Descriptors$Descriptor;
     346: iconst_3
     347: anewarray     #10                 // class java/lang/String
     350: dup
     351: iconst_0
     352: ldc           #11                 // String Region
     354: aastore
     355: dup
     356: iconst_1
     357: ldc           #42                 // String VersionOfOfflineNode
     359: aastore
     360: dup
     361: iconst_2
     362: ldc           #43                 // String FavoredNodes
     364: aastore
     365: invokespecial #13                 // Method com/google/protobuf/GeneratedMessage$FieldAccessorTable."<init>":(Lcom/google/protobuf/Descriptors$Descriptor;[Ljava/lang/String;)V
     368: invokestatic  #44                 // Method org/apache/hadoop/hbase/protobuf/generated/AdminProtos.access$5802:(Lcom/google/protobuf/GeneratedMessage$FieldAccessorTable;)Lcom/google/protobuf/GeneratedMessage$FieldAccessorTable;
     371: pop
     372: invokestatic  #3                  // Method org/apache/hadoop/hbase/protobuf/generated/AdminProtos.getDescriptor:()Lcom/google/protobuf/Descriptors$FileDescriptor;
     375: invokevirtual #4                  // Method com/google/protobuf/Descriptors$FileDescriptor.getMessageTypes:()Ljava/util/List;
     378: bipush        7
     380: invokeinterface #5,  2            // InterfaceMethod java/util/List.get:(I)Ljava/lang/Object;
     385: checkcast     #6                  // class com/google/protobuf/Descriptors$Descriptor
     388: invokestatic  #45                 // Method org/apache/hadoop/hbase/protobuf/generated/AdminProtos.access$7802:(Lcom/google/protobuf/Descriptors$Descriptor;)Lcom/google/protobuf/Descriptors$Descriptor;
     391: pop
     392: new           #8                  // class com/google/protobuf/GeneratedMessage$FieldAccessorTable
     395: dup
     396: invokestatic  #46                 // Method org/apache/hadoop/hbase/protobuf/generated/AdminProtos.access$7800:()Lcom/google/protobuf/Descriptors$Descriptor;
     399: iconst_1
     400: anewarray     #10                 // class java/lang/String
     403: dup
     404: iconst_0
     405: ldc           #47                 // String OpeningState
     407: aastore
     408: invokespecial #13                 // Method com/google/protobuf/GeneratedMessage$FieldAccessorTable."<init>":(Lcom/google/protobuf/Descriptors$Descriptor;[Ljava/lang/String;)V
     411: invokestatic  #48                 // Method org/apache/hadoop/hbase/protobuf/generated/AdminProtos.access$7902:(Lcom/google/protobuf/GeneratedMessage$FieldAccessorTable;)Lcom/google/protobuf/GeneratedMessage$FieldAccessorTable;
     414: pop
     415: invokestatic  #3                  // Method org/apache/hadoop/hbase/protobuf/generated/AdminProtos.getDescriptor:()Lcom/google/protobuf/Descriptors$FileDescriptor;
     418: invokevirtual #4                  // Method com/google/protobuf/Descriptors$FileDescriptor.getMessageTypes:()Ljava/util/List;
     421: bipush        8
     423: invokeinterface #5,  2            // InterfaceMethod java/util/List.get:(I)Ljava/lang/Object;
     428: checkcast     #6                  // class com/google/protobuf/Descriptors$Descriptor
     431: invokestatic  #49                 // Method org/apache/hadoop/hbase/protobuf/generated/AdminProtos.access$8602:(Lcom/google/protobuf/Descriptors$Descriptor;)Lcom/google/protobuf/Descriptors$Descriptor;
     434: pop
     435: new           #8                  // class com/google/protobuf/GeneratedMessage$FieldAccessorTable
     438: dup
     439: invokestatic  #50                 // Method org/apache/hadoop/hbase/protobuf/generated/AdminProtos.access$8600:()Lcom/google/protobuf/Descriptors$Descriptor;
     442: iconst_1
     443: anewarray     #10                 // class java/lang/String
     446: dup
     447: iconst_0
     448: ldc           #17                 // String RegionInfo
     450: aastore
     451: invokespecial #13                 // Method com/google/protobuf/GeneratedMessage$FieldAccessorTable."<init>":(Lcom/google/protobuf/Descriptors$Descriptor;[Ljava/lang/String;)V
     454: invokestatic  #51                 // Method org/apache/hadoop/hbase/protobuf/generated/AdminProtos.access$8702:(Lcom/google/protobuf/GeneratedMessage$FieldAccessorTable;)Lcom/google/protobuf/GeneratedMessage$FieldAccessorTable;
     457: pop
     458: invokestatic  #3                  // Method org/apache/hadoop/hbase/protobuf/generated/AdminProtos.getDescriptor:()Lcom/google/protobuf/Descriptors$FileDescriptor;
     461: invokevirtual #4                  // Method com/google/protobuf/Descriptors$FileDescriptor.getMessageTypes:()Ljava/util/List;
     464: bipush        9
     466: invokeinterface #5,  2            // InterfaceMethod java/util/List.get:(I)Ljava/lang/Object;
     471: checkcast     #6                  // class com/google/protobuf/Descriptors$Descriptor
     474: invokestatic  #52                 // Method org/apache/hadoop/hbase/protobuf/generated/AdminProtos.access$9502:(Lcom/google/protobuf/Descriptors$Descriptor;)Lcom/google/protobuf/Descriptors$Descriptor;
     477: pop
     478: new           #8                  // class com/google/protobuf/GeneratedMessage$FieldAccessorTable
     481: dup
     482: invokestatic  #53                 // Method org/apache/hadoop/hbase/protobuf/generated/AdminProtos.access$9500:()Lcom/google/protobuf/Descriptors$Descriptor;
     485: iconst_0
     486: anewarray     #10                 // class java/lang/String
     489: invokespecial #13                 // Method com/google/protobuf/GeneratedMessage$FieldAccessorTable."<init>":(Lcom/google/protobuf/Descriptors$Descriptor;[Ljava/lang/String;)V
     492: invokestatic  #54                 // Method org/apache/hadoop/hbase/protobuf/generated/AdminProtos.access$9602:(Lcom/google/protobuf/GeneratedMessage$FieldAccessorTable;)Lcom/google/protobuf/GeneratedMessage$FieldAccessorTable;
     495: pop
     496: invokestatic  #3                  // Method org/apache/hadoop/hbase/protobuf/generated/AdminProtos.getDescriptor:()Lcom/google/protobuf/Descriptors$FileDescriptor;
     499: invokevirtual #4                  // Method com/google/protobuf/Descriptors$FileDescriptor.getMessageTypes:()Ljava/util/List;
     502: bipush        10
     504: invokeinterface #5,  2            // InterfaceMethod java/util/List.get:(I)Ljava/lang/Object;
     509: checkcast     #6                  // class com/google/protobuf/Descriptors$Descriptor
     512: invokestatic  #55                 // Method org/apache/hadoop/hbase/protobuf/generated/AdminProtos.access$10202:(Lcom/google/protobuf/Descriptors$Descriptor;)Lcom/google/protobuf/Descriptors$Descriptor;
     515: pop
     516: new           #8                  // class com/google/protobuf/GeneratedMessage$FieldAccessorTable
     519: dup
     520: invokestatic  #56                 // Method org/apache/hadoop/hbase/protobuf/generated/AdminProtos.access$10200:()Lcom/google/protobuf/Descriptors$Descriptor;
     523: iconst_5
     524: anewarray     #10                 // class java/lang/String
     527: dup
     528: iconst_0
     529: ldc           #11                 // String Region
     531: aastore
     532: dup
     533: iconst_1
     534: ldc           #57                 // String VersionOfClosingNode
     536: aastore
     537: dup
     538: iconst_2
     539: ldc           #58                 // String TransitionInZK
     541: aastore
     542: dup
     543: iconst_3
     544: ldc           #59                 // String DestinationServer
     546: aastore
     547: dup
     548: iconst_4
     549: ldc           #36                 // String ServerStartCode
     551: aastore
     552: invokespecial #13                 // Method com/google/protobuf/GeneratedMessage$FieldAccessorTable."<init>":(Lcom/google/protobuf/Descriptors$Descriptor;[Ljava/lang/String;)V
     555: invokestatic  #60                 // Method org/apache/hadoop/hbase/protobuf/generated/AdminProtos.access$10302:(Lcom/google/protobuf/GeneratedMessage$FieldAccessorTable;)Lcom/google/protobuf/GeneratedMessage$FieldAccessorTable;
     558: pop
     559: invokestatic  #3                  // Method org/apache/hadoop/hbase/protobuf/generated/AdminProtos.getDescriptor:()Lcom/google/protobuf/Descriptors$FileDescriptor;
     562: invokevirtual #4                  // Method com/google/protobuf/Descriptors$FileDescriptor.getMessageTypes:()Ljava/util/List;
     565: bipush        11
     567: invokeinterface #5,  2            // InterfaceMethod java/util/List.get:(I)Ljava/lang/Object;
     572: checkcast     #6                  // class com/google/protobuf/Descriptors$Descriptor
     575: invokestatic  #61                 // Method org/apache/hadoop/hbase/protobuf/generated/AdminProtos.access$11502:(Lcom/google/protobuf/Descriptors$Descriptor;)Lcom/google/protobuf/Descriptors$Descriptor;
     578: pop
     579: new           #8                  // class com/google/protobuf/GeneratedMessage$FieldAccessorTable
     582: dup
     583: invokestatic  #62                 // Method org/apache/hadoop/hbase/protobuf/generated/AdminProtos.access$11500:()Lcom/google/protobuf/Descriptors$Descriptor;
     586: iconst_1
     587: anewarray     #10                 // class java/lang/String
     590: dup
     591: iconst_0
     592: ldc           #63                 // String Closed
     594: aastore
     595: invokespecial #13                 // Method com/google/protobuf/GeneratedMessage$FieldAccessorTable."<init>":(Lcom/google/protobuf/Descriptors$Descriptor;[Ljava/lang/String;)V
     598: invokestatic  #64                 // Method org/apache/hadoop/hbase/protobuf/generated/AdminProtos.access$11602:(Lcom/google/protobuf/GeneratedMessage$FieldAccessorTable;)Lcom/google/protobuf/GeneratedMessage$FieldAccessorTable;
     601: pop
     602: invokestatic  #3                  // Method org/apache/hadoop/hbase/protobuf/generated/AdminProtos.getDescriptor:()Lcom/google/protobuf/Descriptors$FileDescriptor;
     605: invokevirtual #4                  // Method com/google/protobuf/Descriptors$FileDescriptor.getMessageTypes:()Ljava/util/List;
     608: bipush        12
     610: invokeinterface #5,  2            // InterfaceMethod java/util/List.get:(I)Ljava/lang/Object;
     615: checkcast     #6                  // class com/google/protobuf/Descriptors$Descriptor
     618: invokestatic  #65                 // Method org/apache/hadoop/hbase/protobuf/generated/AdminProtos.access$12402:(Lcom/google/protobuf/Descriptors$Descriptor;)Lcom/google/protobuf/Descriptors$Descriptor;
     621: pop
     622: new           #8                  // class com/google/protobuf/GeneratedMessage$FieldAccessorTable
     625: dup
     626: invokestatic  #66                 // Method org/apache/hadoop/hbase/protobuf/generated/AdminProtos.access$12400:()Lcom/google/protobuf/Descriptors$Descriptor;
     629: iconst_3
     630: anewarray     #10                 // class java/lang/String
     633: dup
     634: iconst_0
     635: ldc           #11                 // String Region
     637: aastore
     638: dup
     639: iconst_1
     640: ldc           #67                 // String IfOlderThanTs
     642: aastore
     643: dup
     644: iconst_2
     645: ldc           #68                 // String WriteFlushWalMarker
     647: aastore
     648: invokespecial #13                 // Method com/google/protobuf/GeneratedMessage$FieldAccessorTable."<init>":(Lcom/google/protobuf/Descriptors$Descriptor;[Ljava/lang/String;)V
     651: invokestatic  #69                 // Method org/apache/hadoop/hbase/protobuf/generated/AdminProtos.access$12502:(Lcom/google/protobuf/GeneratedMessage$FieldAccessorTable;)Lcom/google/protobuf/GeneratedMessage$FieldAccessorTable;
     654: pop
     655: invokestatic  #3                  // Method org/apache/hadoop/hbase/protobuf/generated/AdminProtos.getDescriptor:()Lcom/google/protobuf/Descriptors$FileDescriptor;
     658: invokevirtual #4                  // Method com/google/protobuf/Descriptors$FileDescriptor.getMessageTypes:()Ljava/util/List;
     661: bipush        13
     663: invokeinterface #5,  2            // InterfaceMethod java/util/List.get:(I)Ljava/lang/Object;
     668: checkcast     #6                  // class com/google/protobuf/Descriptors$Descriptor
     671: invokestatic  #70                 // Method org/apache/hadoop/hbase/protobuf/generated/AdminProtos.access$13502:(Lcom/google/protobuf/Descriptors$Descriptor;)Lcom/google/protobuf/Descriptors$Descriptor;
     674: pop
     675: new           #8                  // class com/google/protobuf/GeneratedMessage$FieldAccessorTable
     678: dup
     679: invokestatic  #71                 // Method org/apache/hadoop/hbase/protobuf/generated/AdminProtos.access$13500:()Lcom/google/protobuf/Descriptors$Descriptor;
     682: iconst_3
     683: anewarray     #10                 // class java/lang/String
     686: dup
     687: iconst_0
     688: ldc           #72                 // String LastFlushTime
     690: aastore
     691: dup
     692: iconst_1
     693: ldc           #73                 // String Flushed
     695: aastore
     696: dup
     697: iconst_2
     698: ldc           #74                 // String WroteFlushWalMarker
     700: aastore
     701: invokespecial #13                 // Method com/google/protobuf/GeneratedMessage$FieldAccessorTable."<init>":(Lcom/google/protobuf/Descriptors$Descriptor;[Ljava/lang/String;)V
     704: invokestatic  #75                 // Method org/apache/hadoop/hbase/protobuf/generated/AdminProtos.access$13602:(Lcom/google/protobuf/GeneratedMessage$FieldAccessorTable;)Lcom/google/protobuf/GeneratedMessage$FieldAccessorTable;
     707: pop
     708: invokestatic  #3                  // Method org/apache/hadoop/hbase/protobuf/generated/AdminProtos.getDescriptor:()Lcom/google/protobuf/Descriptors$FileDescriptor;
     711: invokevirtual #4                  // Method com/google/protobuf/Descriptors$FileDescriptor.getMessageTypes:()Ljava/util/List;
     714: bipush        14
     716: invokeinterface #5,  2            // InterfaceMethod java/util/List.get:(I)Ljava/lang/Object;
     721: checkcast     #6                  // class com/google/protobuf/Descriptors$Descriptor
     724: invokestatic  #76                 // Method org/apache/hadoop/hbase/protobuf/generated/AdminProtos.access$14602:(Lcom/google/protobuf/Descriptors$Descriptor;)Lcom/google/protobuf/Descriptors$Descriptor;
     727: pop
     728: new           #8                  // class com/google/protobuf/GeneratedMessage$FieldAccessorTable
     731: dup
     732: invokestatic  #77                 // Method org/apache/hadoop/hbase/protobuf/generated/AdminProtos.access$14600:()Lcom/google/protobuf/Descriptors$Descriptor;
     735: iconst_2
     736: anewarray     #10                 // class java/lang/String
     739: dup
     740: iconst_0
     741: ldc           #11                 // String Region
     743: aastore
     744: dup
     745: iconst_1
     746: ldc           #78                 // String SplitPoint
     748: aastore
     749: invokespecial #13                 // Method com/google/protobuf/GeneratedMessage$FieldAccessorTable."<init>":(Lcom/google/protobuf/Descriptors$Descriptor;[Ljava/lang/String;)V
     752: invokestatic  #79                 // Method org/apache/hadoop/hbase/protobuf/generated/AdminProtos.access$14702:(Lcom/google/protobuf/GeneratedMessage$FieldAccessorTable;)Lcom/google/protobuf/GeneratedMessage$FieldAccessorTable;
     755: pop
     756: invokestatic  #3                  // Method org/apache/hadoop/hbase/protobuf/generated/AdminProtos.getDescriptor:()Lcom/google/protobuf/Descriptors$FileDescriptor;
     759: invokevirtual #4                  // Method com/google/protobuf/Descriptors$FileDescriptor.getMessageTypes:()Ljava/util/List;
     762: bipush        15
     764: invokeinterface #5,  2            // InterfaceMethod java/util/List.get:(I)Ljava/lang/Object;
     769: checkcast     #6                  // class com/google/protobuf/Descriptors$Descriptor
     772: invokestatic  #80                 // Method org/apache/hadoop/hbase/protobuf/generated/AdminProtos.access$15602:(Lcom/google/protobuf/Descriptors$Descriptor;)Lcom/google/protobuf/Descriptors$Descriptor;
     775: pop
     776: new           #8                  // class com/google/protobuf/GeneratedMessage$FieldAccessorTable
     779: dup
     780: invokestatic  #81                 // Method org/apache/hadoop/hbase/protobuf/generated/AdminProtos.access$15600:()Lcom/google/protobuf/Descriptors$Descriptor;
     783: iconst_0
     784: anewarray     #10                 // class java/lang/String
     787: invokespecial #13                 // Method com/google/protobuf/GeneratedMessage$FieldAccessorTable."<init>":(Lcom/google/protobuf/Descriptors$Descriptor;[Ljava/lang/String;)V
     790: invokestatic  #82                 // Method org/apache/hadoop/hbase/protobuf/generated/AdminProtos.access$15702:(Lcom/google/protobuf/GeneratedMessage$FieldAccessorTable;)Lcom/google/protobuf/GeneratedMessage$FieldAccessorTable;
     793: pop
     794: invokestatic  #3                  // Method org/apache/hadoop/hbase/protobuf/generated/AdminProtos.getDescriptor:()Lcom/google/protobuf/Descriptors$FileDescriptor;
     797: invokevirtual #4                  // Method com/google/protobuf/Descriptors$FileDescriptor.getMessageTypes:()Ljava/util/List;
     800: bipush        16
     802: invokeinterface #5,  2            // InterfaceMethod java/util/List.get:(I)Ljava/lang/Object;
     807: checkcast     #6                  // class com/google/protobuf/Descriptors$Descriptor
     810: invokestatic  #83                 // Method org/apache/hadoop/hbase/protobuf/generated/AdminProtos.access$16302:(Lcom/google/protobuf/Descriptors$Descriptor;)Lcom/google/protobuf/Descriptors$Descriptor;
     813: pop
     814: new           #8                  // class com/google/protobuf/GeneratedMessage$FieldAccessorTable
     817: dup
     818: invokestatic  #84                 // Method org/apache/hadoop/hbase/protobuf/generated/AdminProtos.access$16300:()Lcom/google/protobuf/Descriptors$Descriptor;
     821: iconst_3
     822: anewarray     #10                 // class java/lang/String
     825: dup
     826: iconst_0
     827: ldc           #11                 // String Region
     829: aastore
     830: dup
     831: iconst_1
     832: ldc           #85                 // String Major
     834: aastore
     835: dup
     836: iconst_2
     837: ldc           #21                 // String Family
     839: aastore
     840: invokespecial #13                 // Method com/google/protobuf/GeneratedMessage$FieldAccessorTable."<init>":(Lcom/google/protobuf/Descriptors$Descriptor;[Ljava/lang/String;)V
     843: invokestatic  #86                 // Method org/apache/hadoop/hbase/protobuf/generated/AdminProtos.access$16402:(Lcom/google/protobuf/GeneratedMessage$FieldAccessorTable;)Lcom/google/protobuf/GeneratedMessage$FieldAccessorTable;
     846: pop
     847: invokestatic  #3                  // Method org/apache/hadoop/hbase/protobuf/generated/AdminProtos.getDescriptor:()Lcom/google/protobuf/Descriptors$FileDescriptor;
     850: invokevirtual #4                  // Method com/google/protobuf/Descriptors$FileDescriptor.getMessageTypes:()Ljava/util/List;
     853: bipush        17
     855: invokeinterface #5,  2            // InterfaceMethod java/util/List.get:(I)Ljava/lang/Object;
     860: checkcast     #6                  // class com/google/protobuf/Descriptors$Descriptor
     863: invokestatic  #87                 // Method org/apache/hadoop/hbase/protobuf/generated/AdminProtos.access$17402:(Lcom/google/protobuf/Descriptors$Descriptor;)Lcom/google/protobuf/Descriptors$Descriptor;
     866: pop
     867: new           #8                  // class com/google/protobuf/GeneratedMessage$FieldAccessorTable
     870: dup
     871: invokestatic  #88                 // Method org/apache/hadoop/hbase/protobuf/generated/AdminProtos.access$17400:()Lcom/google/protobuf/Descriptors$Descriptor;
     874: iconst_0
     875: anewarray     #10                 // class java/lang/String
     878: invokespecial #13                 // Method com/google/protobuf/GeneratedMessage$FieldAccessorTable."<init>":(Lcom/google/protobuf/Descriptors$Descriptor;[Ljava/lang/String;)V
     881: invokestatic  #89                 // Method org/apache/hadoop/hbase/protobuf/generated/AdminProtos.access$17502:(Lcom/google/protobuf/GeneratedMessage$FieldAccessorTable;)Lcom/google/protobuf/GeneratedMessage$FieldAccessorTable;
     884: pop
     885: invokestatic  #3                  // Method org/apache/hadoop/hbase/protobuf/generated/AdminProtos.getDescriptor:()Lcom/google/protobuf/Descriptors$FileDescriptor;
     888: invokevirtual #4                  // Method com/google/protobuf/Descriptors$FileDescriptor.getMessageTypes:()Ljava/util/List;
     891: bipush        18
     893: invokeinterface #5,  2            // InterfaceMethod java/util/List.get:(I)Ljava/lang/Object;
     898: checkcast     #6                  // class com/google/protobuf/Descriptors$Descriptor
     901: invokestatic  #90                 // Method org/apache/hadoop/hbase/protobuf/generated/AdminProtos.access$18102:(Lcom/google/protobuf/Descriptors$Descriptor;)Lcom/google/protobuf/Descriptors$Descriptor;
     904: pop
     905: new           #8                  // class com/google/protobuf/GeneratedMessage$FieldAccessorTable
     908: dup
     909: invokestatic  #91                 // Method org/apache/hadoop/hbase/protobuf/generated/AdminProtos.access$18100:()Lcom/google/protobuf/Descriptors$Descriptor;
     912: iconst_1
     913: anewarray     #10                 // class java/lang/String
     916: dup
     917: iconst_0
     918: ldc           #92                 // String UpdateInfo
     920: aastore
     921: invokespecial #13                 // Method com/google/protobuf/GeneratedMessage$FieldAccessorTable."<init>":(Lcom/google/protobuf/Descriptors$Descriptor;[Ljava/lang/String;)V
     924: invokestatic  #93                 // Method org/apache/hadoop/hbase/protobuf/generated/AdminProtos.access$18202:(Lcom/google/protobuf/GeneratedMessage$FieldAccessorTable;)Lcom/google/protobuf/GeneratedMessage$FieldAccessorTable;
     927: pop
     928: invokestatic  #91                 // Method org/apache/hadoop/hbase/protobuf/generated/AdminProtos.access$18100:()Lcom/google/protobuf/Descriptors$Descriptor;
     931: invokevirtual #39                 // Method com/google/protobuf/Descriptors$Descriptor.getNestedTypes:()Ljava/util/List;
     934: iconst_0
     935: invokeinterface #5,  2            // InterfaceMethod java/util/List.get:(I)Ljava/lang/Object;
     940: checkcast     #6                  // class com/google/protobuf/Descriptors$Descriptor
     943: invokestatic  #94                 // Method org/apache/hadoop/hbase/protobuf/generated/AdminProtos.access$18402:(Lcom/google/protobuf/Descriptors$Descriptor;)Lcom/google/protobuf/Descriptors$Descriptor;
     946: pop
     947: new           #8                  // class com/google/protobuf/GeneratedMessage$FieldAccessorTable
     950: dup
     951: invokestatic  #95                 // Method org/apache/hadoop/hbase/protobuf/generated/AdminProtos.access$18400:()Lcom/google/protobuf/Descriptors$Descriptor;
     954: iconst_2
     955: anewarray     #10                 // class java/lang/String
     958: dup
     959: iconst_0
     960: ldc           #11                 // String Region
     962: aastore
     963: dup
     964: iconst_1
     965: ldc           #43                 // String FavoredNodes
     967: aastore
     968: invokespecial #13                 // Method com/google/protobuf/GeneratedMessage$FieldAccessorTable."<init>":(Lcom/google/protobuf/Descriptors$Descriptor;[Ljava/lang/String;)V
     971: invokestatic  #96                 // Method org/apache/hadoop/hbase/protobuf/generated/AdminProtos.access$18502:(Lcom/google/protobuf/GeneratedMessage$FieldAccessorTable;)Lcom/google/protobuf/GeneratedMessage$FieldAccessorTable;
     974: pop
     975: invokestatic  #3                  // Method org/apache/hadoop/hbase/protobuf/generated/AdminProtos.getDescriptor:()Lcom/google/protobuf/Descriptors$FileDescriptor;
     978: invokevirtual #4                  // Method com/google/protobuf/Descriptors$FileDescriptor.getMessageTypes:()Ljava/util/List;
     981: bipush        19
     983: invokeinterface #5,  2            // InterfaceMethod java/util/List.get:(I)Ljava/lang/Object;
     988: checkcast     #6                  // class com/google/protobuf/Descriptors$Descriptor
     991: invokestatic  #97                 // Method org/apache/hadoop/hbase/protobuf/generated/AdminProtos.access$20102:(Lcom/google/protobuf/Descriptors$Descriptor;)Lcom/google/protobuf/Descriptors$Descriptor;
     994: pop
     995: new           #8                  // class com/google/protobuf/GeneratedMessage$FieldAccessorTable
     998: dup
     999: invokestatic  #98                 // Method org/apache/hadoop/hbase/protobuf/generated/AdminProtos.access$20100:()Lcom/google/protobuf/Descriptors$Descriptor;
    1002: iconst_1
    1003: anewarray     #10                 // class java/lang/String
    1006: dup
    1007: iconst_0
    1008: ldc           #99                 // String Response
    1010: aastore
    1011: invokespecial #13                 // Method com/google/protobuf/GeneratedMessage$FieldAccessorTable."<init>":(Lcom/google/protobuf/Descriptors$Descriptor;[Ljava/lang/String;)V
    1014: invokestatic  #100                // Method org/apache/hadoop/hbase/protobuf/generated/AdminProtos.access$20202:(Lcom/google/protobuf/GeneratedMessage$FieldAccessorTable;)Lcom/google/protobuf/GeneratedMessage$FieldAccessorTable;
    1017: pop
    1018: invokestatic  #3                  // Method org/apache/hadoop/hbase/protobuf/generated/AdminProtos.getDescriptor:()Lcom/google/protobuf/Descriptors$FileDescriptor;
    1021: invokevirtual #4                  // Method com/google/protobuf/Descriptors$FileDescriptor.getMessageTypes:()Ljava/util/List;
    1024: bipush        20
    1026: invokeinterface #5,  2            // InterfaceMethod java/util/List.get:(I)Ljava/lang/Object;
    1031: checkcast     #6                  // class com/google/protobuf/Descriptors$Descriptor
    1034: invokestatic  #101                // Method org/apache/hadoop/hbase/protobuf/generated/AdminProtos.access$21002:(Lcom/google/protobuf/Descriptors$Descriptor;)Lcom/google/protobuf/Descriptors$Descriptor;
    1037: pop
    1038: new           #8                  // class com/google/protobuf/GeneratedMessage$FieldAccessorTable
    1041: dup
    1042: invokestatic  #102                // Method org/apache/hadoop/hbase/protobuf/generated/AdminProtos.access$21000:()Lcom/google/protobuf/Descriptors$Descriptor;
    1045: iconst_4
    1046: anewarray     #10                 // class java/lang/String
    1049: dup
    1050: iconst_0
    1051: ldc           #103                // String RegionA
    1053: aastore
    1054: dup
    1055: iconst_1
    1056: ldc           #104                // String RegionB
    1058: aastore
    1059: dup
    1060: iconst_2
    1061: ldc           #105                // String Forcible
    1063: aastore
    1064: dup
    1065: iconst_3
    1066: ldc           #37                 // String MasterSystemTime
    1068: aastore
    1069: invokespecial #13                 // Method com/google/protobuf/GeneratedMessage$FieldAccessorTable."<init>":(Lcom/google/protobuf/Descriptors$Descriptor;[Ljava/lang/String;)V
    1072: invokestatic  #106                // Method org/apache/hadoop/hbase/protobuf/generated/AdminProtos.access$21102:(Lcom/google/protobuf/GeneratedMessage$FieldAccessorTable;)Lcom/google/protobuf/GeneratedMessage$FieldAccessorTable;
    1075: pop
    1076: invokestatic  #3                  // Method org/apache/hadoop/hbase/protobuf/generated/AdminProtos.getDescriptor:()Lcom/google/protobuf/Descriptors$FileDescriptor;
    1079: invokevirtual #4                  // Method com/google/protobuf/Descriptors$FileDescriptor.getMessageTypes:()Ljava/util/List;
    1082: bipush        21
    1084: invokeinterface #5,  2            // InterfaceMethod java/util/List.get:(I)Ljava/lang/Object;
    1089: checkcast     #6                  // class com/google/protobuf/Descriptors$Descriptor
    1092: invokestatic  #107                // Method org/apache/hadoop/hbase/protobuf/generated/AdminProtos.access$22202:(Lcom/google/protobuf/Descriptors$Descriptor;)Lcom/google/protobuf/Descriptors$Descriptor;
    1095: pop
    1096: new           #8                  // class com/google/protobuf/GeneratedMessage$FieldAccessorTable
    1099: dup
    1100: invokestatic  #108                // Method org/apache/hadoop/hbase/protobuf/generated/AdminProtos.access$22200:()Lcom/google/protobuf/Descriptors$Descriptor;
    1103: iconst_0
    1104: anewarray     #10                 // class java/lang/String
    1107: invokespecial #13                 // Method com/google/protobuf/GeneratedMessage$FieldAccessorTable."<init>":(Lcom/google/protobuf/Descriptors$Descriptor;[Ljava/lang/String;)V
    1110: invokestatic  #109                // Method org/apache/hadoop/hbase/protobuf/generated/AdminProtos.access$22302:(Lcom/google/protobuf/GeneratedMessage$FieldAccessorTable;)Lcom/google/protobuf/GeneratedMessage$FieldAccessorTable;
    1113: pop
    1114: invokestatic  #3                  // Method org/apache/hadoop/hbase/protobuf/generated/AdminProtos.getDescriptor:()Lcom/google/protobuf/Descriptors$FileDescriptor;
    1117: invokevirtual #4                  // Method com/google/protobuf/Descriptors$FileDescriptor.getMessageTypes:()Ljava/util/List;
    1120: bipush        22
    1122: invokeinterface #5,  2            // InterfaceMethod java/util/List.get:(I)Ljava/lang/Object;
    1127: checkcast     #6                  // class com/google/protobuf/Descriptors$Descriptor
    1130: invokestatic  #110                // Method org/apache/hadoop/hbase/protobuf/generated/AdminProtos.access$22902:(Lcom/google/protobuf/Descriptors$Descriptor;)Lcom/google/protobuf/Descriptors$Descriptor;
    1133: pop
    1134: new           #8                  // class com/google/protobuf/GeneratedMessage$FieldAccessorTable
    1137: dup
    1138: invokestatic  #111                // Method org/apache/hadoop/hbase/protobuf/generated/AdminProtos.access$22900:()Lcom/google/protobuf/Descriptors$Descriptor;
    1141: iconst_3
    1142: anewarray     #10                 // class java/lang/String
    1145: dup
    1146: iconst_0
    1147: ldc           #112                // String Key
    1149: aastore
    1150: dup
    1151: iconst_1
    1152: ldc           #113                // String KeyValueBytes
    1154: aastore
    1155: dup
    1156: iconst_2
    1157: ldc           #114                // String AssociatedCellCount
    1159: aastore
    1160: invokespecial #13                 // Method com/google/protobuf/GeneratedMessage$FieldAccessorTable."<init>":(Lcom/google/protobuf/Descriptors$Descriptor;[Ljava/lang/String;)V
    1163: invokestatic  #115                // Method org/apache/hadoop/hbase/protobuf/generated/AdminProtos.access$23002:(Lcom/google/protobuf/GeneratedMessage$FieldAccessorTable;)Lcom/google/protobuf/GeneratedMessage$FieldAccessorTable;
    1166: pop
    1167: invokestatic  #3                  // Method org/apache/hadoop/hbase/protobuf/generated/AdminProtos.getDescriptor:()Lcom/google/protobuf/Descriptors$FileDescriptor;
    1170: invokevirtual #4                  // Method com/google/protobuf/Descriptors$FileDescriptor.getMessageTypes:()Ljava/util/List;
    1173: bipush        23
    1175: invokeinterface #5,  2            // InterfaceMethod java/util/List.get:(I)Ljava/lang/Object;
    1180: checkcast     #6                  // class com/google/protobuf/Descriptors$Descriptor
    1183: invokestatic  #116                // Method org/apache/hadoop/hbase/protobuf/generated/AdminProtos.access$24002:(Lcom/google/protobuf/Descriptors$Descriptor;)Lcom/google/protobuf/Descriptors$Descriptor;
    1186: pop
    1187: new           #8                  // class com/google/protobuf/GeneratedMessage$FieldAccessorTable
    1190: dup
    1191: invokestatic  #117                // Method org/apache/hadoop/hbase/protobuf/generated/AdminProtos.access$24000:()Lcom/google/protobuf/Descriptors$Descriptor;
    1194: iconst_4
    1195: anewarray     #10                 // class java/lang/String
    1198: dup
    1199: iconst_0
    1200: ldc           #118                // String Entry
    1202: aastore
    1203: dup
    1204: iconst_1
    1205: ldc           #119                // String ReplicationClusterId
    1207: aastore
    1208: dup
    1209: iconst_2
    1210: ldc           #120                // String SourceBaseNamespaceDirPath
    1212: aastore
    1213: dup
    1214: iconst_3
    1215: ldc           #121                // String SourceHFileArchiveDirPath
    1217: aastore
    1218: invokespecial #13                 // Method com/google/protobuf/GeneratedMessage$FieldAccessorTable."<init>":(Lcom/google/protobuf/Descriptors$Descriptor;[Ljava/lang/String;)V
    1221: invokestatic  #122                // Method org/apache/hadoop/hbase/protobuf/generated/AdminProtos.access$24102:(Lcom/google/protobuf/GeneratedMessage$FieldAccessorTable;)Lcom/google/protobuf/GeneratedMessage$FieldAccessorTable;
    1224: pop
    1225: invokestatic  #3                  // Method org/apache/hadoop/hbase/protobuf/generated/AdminProtos.getDescriptor:()Lcom/google/protobuf/Descriptors$FileDescriptor;
    1228: invokevirtual #4                  // Method com/google/protobuf/Descriptors$FileDescriptor.getMessageTypes:()Ljava/util/List;
    1231: bipush        24
    1233: invokeinterface #5,  2            // InterfaceMethod java/util/List.get:(I)Ljava/lang/Object;
    1238: checkcast     #6                  // class com/google/protobuf/Descriptors$Descriptor
    1241: invokestatic  #123                // Method org/apache/hadoop/hbase/protobuf/generated/AdminProtos.access$25302:(Lcom/google/protobuf/Descriptors$Descriptor;)Lcom/google/protobuf/Descriptors$Descriptor;
    1244: pop
    1245: new           #8                  // class com/google/protobuf/GeneratedMessage$FieldAccessorTable
    1248: dup
    1249: invokestatic  #124                // Method org/apache/hadoop/hbase/protobuf/generated/AdminProtos.access$25300:()Lcom/google/protobuf/Descriptors$Descriptor;
    1252: iconst_0
    1253: anewarray     #10                 // class java/lang/String
    1256: invokespecial #13                 // Method com/google/protobuf/GeneratedMessage$FieldAccessorTable."<init>":(Lcom/google/protobuf/Descriptors$Descriptor;[Ljava/lang/String;)V
    1259: invokestatic  #125                // Method org/apache/hadoop/hbase/protobuf/generated/AdminProtos.access$25402:(Lcom/google/protobuf/GeneratedMessage$FieldAccessorTable;)Lcom/google/protobuf/GeneratedMessage$FieldAccessorTable;
    1262: pop
    1263: invokestatic  #3                  // Method org/apache/hadoop/hbase/protobuf/generated/AdminProtos.getDescriptor:()Lcom/google/protobuf/Descriptors$FileDescriptor;
    1266: invokevirtual #4                  // Method com/google/protobuf/Descriptors$FileDescriptor.getMessageTypes:()Ljava/util/List;
    1269: bipush        25
    1271: invokeinterface #5,  2            // InterfaceMethod java/util/List.get:(I)Ljava/lang/Object;
    1276: checkcast     #6                  // class com/google/protobuf/Descriptors$Descriptor
    1279: invokestatic  #126                // Method org/apache/hadoop/hbase/protobuf/generated/AdminProtos.access$26002:(Lcom/google/protobuf/Descriptors$Descriptor;)Lcom/google/protobuf/Descriptors$Descriptor;
    1282: pop
    1283: new           #8                  // class com/google/protobuf/GeneratedMessage$FieldAccessorTable
    1286: dup
    1287: invokestatic  #127                // Method org/apache/hadoop/hbase/protobuf/generated/AdminProtos.access$26000:()Lcom/google/protobuf/Descriptors$Descriptor;
    1290: iconst_0
    1291: anewarray     #10                 // class java/lang/String
    1294: invokespecial #13                 // Method com/google/protobuf/GeneratedMessage$FieldAccessorTable."<init>":(Lcom/google/protobuf/Descriptors$Descriptor;[Ljava/lang/String;)V
    1297: invokestatic  #128                // Method org/apache/hadoop/hbase/protobuf/generated/AdminProtos.access$26102:(Lcom/google/protobuf/GeneratedMessage$FieldAccessorTable;)Lcom/google/protobuf/GeneratedMessage$FieldAccessorTable;
    1300: pop
    1301: invokestatic  #3                  // Method org/apache/hadoop/hbase/protobuf/generated/AdminProtos.getDescriptor:()Lcom/google/protobuf/Descriptors$FileDescriptor;
    1304: invokevirtual #4                  // Method com/google/protobuf/Descriptors$FileDescriptor.getMessageTypes:()Ljava/util/List;
    1307: bipush        26
    1309: invokeinterface #5,  2            // InterfaceMethod java/util/List.get:(I)Ljava/lang/Object;
    1314: checkcast     #6                  // class com/google/protobuf/Descriptors$Descriptor
    1317: invokestatic  #129                // Method org/apache/hadoop/hbase/protobuf/generated/AdminProtos.access$26702:(Lcom/google/protobuf/Descriptors$Descriptor;)Lcom/google/protobuf/Descriptors$Descriptor;
    1320: pop
    1321: new           #8                  // class com/google/protobuf/GeneratedMessage$FieldAccessorTable
    1324: dup
    1325: invokestatic  #130                // Method org/apache/hadoop/hbase/protobuf/generated/AdminProtos.access$26700:()Lcom/google/protobuf/Descriptors$Descriptor;
    1328: iconst_1
    1329: anewarray     #10                 // class java/lang/String
    1332: dup
    1333: iconst_0
    1334: ldc           #131                // String RegionToFlush
    1336: aastore
    1337: invokespecial #13                 // Method com/google/protobuf/GeneratedMessage$FieldAccessorTable."<init>":(Lcom/google/protobuf/Descriptors$Descriptor;[Ljava/lang/String;)V
    1340: invokestatic  #132                // Method org/apache/hadoop/hbase/protobuf/generated/AdminProtos.access$26802:(Lcom/google/protobuf/GeneratedMessage$FieldAccessorTable;)Lcom/google/protobuf/GeneratedMessage$FieldAccessorTable;
    1343: pop
    1344: invokestatic  #3                  // Method org/apache/hadoop/hbase/protobuf/generated/AdminProtos.getDescriptor:()Lcom/google/protobuf/Descriptors$FileDescriptor;
    1347: invokevirtual #4                  // Method com/google/protobuf/Descriptors$FileDescriptor.getMessageTypes:()Ljava/util/List;
    1350: bipush        27
    1352: invokeinterface #5,  2            // InterfaceMethod java/util/List.get:(I)Ljava/lang/Object;
    1357: checkcast     #6                  // class com/google/protobuf/Descriptors$Descriptor
    1360: invokestatic  #133                // Method org/apache/hadoop/hbase/protobuf/generated/AdminProtos.access$27502:(Lcom/google/protobuf/Descriptors$Descriptor;)Lcom/google/protobuf/Descriptors$Descriptor;
    1363: pop
    1364: new           #8                  // class com/google/protobuf/GeneratedMessage$FieldAccessorTable
    1367: dup
    1368: invokestatic  #134                // Method org/apache/hadoop/hbase/protobuf/generated/AdminProtos.access$27500:()Lcom/google/protobuf/Descriptors$Descriptor;
    1371: iconst_1
    1372: anewarray     #10                 // class java/lang/String
    1375: dup
    1376: iconst_0
    1377: ldc           #135                // String Reason
    1379: aastore
    1380: invokespecial #13                 // Method com/google/protobuf/GeneratedMessage$FieldAccessorTable."<init>":(Lcom/google/protobuf/Descriptors$Descriptor;[Ljava/lang/String;)V
    1383: invokestatic  #136                // Method org/apache/hadoop/hbase/protobuf/generated/AdminProtos.access$27602:(Lcom/google/protobuf/GeneratedMessage$FieldAccessorTable;)Lcom/google/protobuf/GeneratedMessage$FieldAccessorTable;
    1386: pop
    1387: invokestatic  #3                  // Method org/apache/hadoop/hbase/protobuf/generated/AdminProtos.getDescriptor:()Lcom/google/protobuf/Descriptors$FileDescriptor;
    1390: invokevirtual #4                  // Method com/google/protobuf/Descriptors$FileDescriptor.getMessageTypes:()Ljava/util/List;
    1393: bipush        28
    1395: invokeinterface #5,  2            // InterfaceMethod java/util/List.get:(I)Ljava/lang/Object;
    1400: checkcast     #6                  // class com/google/protobuf/Descriptors$Descriptor
    1403: invokestatic  #137                // Method org/apache/hadoop/hbase/protobuf/generated/AdminProtos.access$28402:(Lcom/google/protobuf/Descriptors$Descriptor;)Lcom/google/protobuf/Descriptors$Descriptor;
    1406: pop
    1407: new           #8                  // class com/google/protobuf/GeneratedMessage$FieldAccessorTable
    1410: dup
    1411: invokestatic  #138                // Method org/apache/hadoop/hbase/protobuf/generated/AdminProtos.access$28400:()Lcom/google/protobuf/Descriptors$Descriptor;
    1414: iconst_0
    1415: anewarray     #10                 // class java/lang/String
    1418: invokespecial #13                 // Method com/google/protobuf/GeneratedMessage$FieldAccessorTable."<init>":(Lcom/google/protobuf/Descriptors$Descriptor;[Ljava/lang/String;)V
    1421: invokestatic  #139                // Method org/apache/hadoop/hbase/protobuf/generated/AdminProtos.access$28502:(Lcom/google/protobuf/GeneratedMessage$FieldAccessorTable;)Lcom/google/protobuf/GeneratedMessage$FieldAccessorTable;
    1424: pop
    1425: invokestatic  #3                  // Method org/apache/hadoop/hbase/protobuf/generated/AdminProtos.getDescriptor:()Lcom/google/protobuf/Descriptors$FileDescriptor;
    1428: invokevirtual #4                  // Method com/google/protobuf/Descriptors$FileDescriptor.getMessageTypes:()Ljava/util/List;
    1431: bipush        29
    1433: invokeinterface #5,  2            // InterfaceMethod java/util/List.get:(I)Ljava/lang/Object;
    1438: checkcast     #6                  // class com/google/protobuf/Descriptors$Descriptor
    1441: invokestatic  #140                // Method org/apache/hadoop/hbase/protobuf/generated/AdminProtos.access$29102:(Lcom/google/protobuf/Descriptors$Descriptor;)Lcom/google/protobuf/Descriptors$Descriptor;
    1444: pop
    1445: new           #8                  // class com/google/protobuf/GeneratedMessage$FieldAccessorTable
    1448: dup
    1449: invokestatic  #141                // Method org/apache/hadoop/hbase/protobuf/generated/AdminProtos.access$29100:()Lcom/google/protobuf/Descriptors$Descriptor;
    1452: iconst_0
    1453: anewarray     #10                 // class java/lang/String
    1456: invokespecial #13                 // Method com/google/protobuf/GeneratedMessage$FieldAccessorTable."<init>":(Lcom/google/protobuf/Descriptors$Descriptor;[Ljava/lang/String;)V
    1459: invokestatic  #142                // Method org/apache/hadoop/hbase/protobuf/generated/AdminProtos.access$29202:(Lcom/google/protobuf/GeneratedMessage$FieldAccessorTable;)Lcom/google/protobuf/GeneratedMessage$FieldAccessorTable;
    1462: pop
    1463: invokestatic  #3                  // Method org/apache/hadoop/hbase/protobuf/generated/AdminProtos.getDescriptor:()Lcom/google/protobuf/Descriptors$FileDescriptor;
    1466: invokevirtual #4                  // Method com/google/protobuf/Descriptors$FileDescriptor.getMessageTypes:()Ljava/util/List;
    1469: bipush        30
    1471: invokeinterface #5,  2            // InterfaceMethod java/util/List.get:(I)Ljava/lang/Object;
    1476: checkcast     #6                  // class com/google/protobuf/Descriptors$Descriptor
    1479: invokestatic  #143                // Method org/apache/hadoop/hbase/protobuf/generated/AdminProtos.access$29802:(Lcom/google/protobuf/Descriptors$Descriptor;)Lcom/google/protobuf/Descriptors$Descriptor;
    1482: pop
    1483: new           #8                  // class com/google/protobuf/GeneratedMessage$FieldAccessorTable
    1486: dup
    1487: invokestatic  #144                // Method org/apache/hadoop/hbase/protobuf/generated/AdminProtos.access$29800:()Lcom/google/protobuf/Descriptors$Descriptor;
    1490: iconst_2
    1491: anewarray     #10                 // class java/lang/String
    1494: dup
    1495: iconst_0
    1496: ldc           #145                // String ServerName
    1498: aastore
    1499: dup
    1500: iconst_1
    1501: ldc           #146                // String WebuiPort
    1503: aastore
    1504: invokespecial #13                 // Method com/google/protobuf/GeneratedMessage$FieldAccessorTable."<init>":(Lcom/google/protobuf/Descriptors$Descriptor;[Ljava/lang/String;)V
    1507: invokestatic  #147                // Method org/apache/hadoop/hbase/protobuf/generated/AdminProtos.access$29902:(Lcom/google/protobuf/GeneratedMessage$FieldAccessorTable;)Lcom/google/protobuf/GeneratedMessage$FieldAccessorTable;
    1510: pop
    1511: invokestatic  #3                  // Method org/apache/hadoop/hbase/protobuf/generated/AdminProtos.getDescriptor:()Lcom/google/protobuf/Descriptors$FileDescriptor;
    1514: invokevirtual #4                  // Method com/google/protobuf/Descriptors$FileDescriptor.getMessageTypes:()Ljava/util/List;
    1517: bipush        31
    1519: invokeinterface #5,  2            // InterfaceMethod java/util/List.get:(I)Ljava/lang/Object;
    1524: checkcast     #6                  // class com/google/protobuf/Descriptors$Descriptor
    1527: invokestatic  #148                // Method org/apache/hadoop/hbase/protobuf/generated/AdminProtos.access$30802:(Lcom/google/protobuf/Descriptors$Descriptor;)Lcom/google/protobuf/Descriptors$Descriptor;
    1530: pop
    1531: new           #8                  // class com/google/protobuf/GeneratedMessage$FieldAccessorTable
    1534: dup
    1535: invokestatic  #149                // Method org/apache/hadoop/hbase/protobuf/generated/AdminProtos.access$30800:()Lcom/google/protobuf/Descriptors$Descriptor;
    1538: iconst_1
    1539: anewarray     #10                 // class java/lang/String
    1542: dup
    1543: iconst_0
    1544: ldc           #150                // String ServerInfo
    1546: aastore
    1547: invokespecial #13                 // Method com/google/protobuf/GeneratedMessage$FieldAccessorTable."<init>":(Lcom/google/protobuf/Descriptors$Descriptor;[Ljava/lang/String;)V
    1550: invokestatic  #151                // Method org/apache/hadoop/hbase/protobuf/generated/AdminProtos.access$30902:(Lcom/google/protobuf/GeneratedMessage$FieldAccessorTable;)Lcom/google/protobuf/GeneratedMessage$FieldAccessorTable;
    1553: pop
    1554: invokestatic  #3                  // Method org/apache/hadoop/hbase/protobuf/generated/AdminProtos.getDescriptor:()Lcom/google/protobuf/Descriptors$FileDescriptor;
    1557: invokevirtual #4                  // Method com/google/protobuf/Descriptors$FileDescriptor.getMessageTypes:()Ljava/util/List;
    1560: bipush        32
    1562: invokeinterface #5,  2            // InterfaceMethod java/util/List.get:(I)Ljava/lang/Object;
    1567: checkcast     #6                  // class com/google/protobuf/Descriptors$Descriptor
    1570: invokestatic  #152                // Method org/apache/hadoop/hbase/protobuf/generated/AdminProtos.access$31702:(Lcom/google/protobuf/Descriptors$Descriptor;)Lcom/google/protobuf/Descriptors$Descriptor;
    1573: pop
    1574: new           #8                  // class com/google/protobuf/GeneratedMessage$FieldAccessorTable
    1577: dup
    1578: invokestatic  #153                // Method org/apache/hadoop/hbase/protobuf/generated/AdminProtos.access$31700:()Lcom/google/protobuf/Descriptors$Descriptor;
    1581: iconst_0
    1582: anewarray     #10                 // class java/lang/String
    1585: invokespecial #13                 // Method com/google/protobuf/GeneratedMessage$FieldAccessorTable."<init>":(Lcom/google/protobuf/Descriptors$Descriptor;[Ljava/lang/String;)V
    1588: invokestatic  #154                // Method org/apache/hadoop/hbase/protobuf/generated/AdminProtos.access$31802:(Lcom/google/protobuf/GeneratedMessage$FieldAccessorTable;)Lcom/google/protobuf/GeneratedMessage$FieldAccessorTable;
    1591: pop
    1592: invokestatic  #3                  // Method org/apache/hadoop/hbase/protobuf/generated/AdminProtos.getDescriptor:()Lcom/google/protobuf/Descriptors$FileDescriptor;
    1595: invokevirtual #4                  // Method com/google/protobuf/Descriptors$FileDescriptor.getMessageTypes:()Ljava/util/List;
    1598: bipush        33
    1600: invokeinterface #5,  2            // InterfaceMethod java/util/List.get:(I)Ljava/lang/Object;
    1605: checkcast     #6                  // class com/google/protobuf/Descriptors$Descriptor
    1608: invokestatic  #155                // Method org/apache/hadoop/hbase/protobuf/generated/AdminProtos.access$32402:(Lcom/google/protobuf/Descriptors$Descriptor;)Lcom/google/protobuf/Descriptors$Descriptor;
    1611: pop
    1612: new           #8                  // class com/google/protobuf/GeneratedMessage$FieldAccessorTable
    1615: dup
    1616: invokestatic  #156                // Method org/apache/hadoop/hbase/protobuf/generated/AdminProtos.access$32400:()Lcom/google/protobuf/Descriptors$Descriptor;
    1619: iconst_0
    1620: anewarray     #10                 // class java/lang/String
    1623: invokespecial #13                 // Method com/google/protobuf/GeneratedMessage$FieldAccessorTable."<init>":(Lcom/google/protobuf/Descriptors$Descriptor;[Ljava/lang/String;)V
    1626: invokestatic  #157                // Method org/apache/hadoop/hbase/protobuf/generated/AdminProtos.access$32502:(Lcom/google/protobuf/GeneratedMessage$FieldAccessorTable;)Lcom/google/protobuf/GeneratedMessage$FieldAccessorTable;
    1629: pop
    1630: aconst_null
    1631: areturn
}
