Compiled from "AllowPartialScanResultCache.java"
class org.apache.hadoop.hbase.client.AllowPartialScanResultCache implements org.apache.hadoop.hbase.client.ScanResultCache {
  org.apache.hadoop.hbase.client.AllowPartialScanResultCache();
    Code:
       0: aload_0
       1: invokespecial #1                  // Method java/lang/Object."<init>":()V
       4: return

  public org.apache.hadoop.hbase.client.Result[] addAndGet(org.apache.hadoop.hbase.client.Result[], boolean) throws java.io.IOException;
    Code:
       0: aload_1
       1: arraylength
       2: ifne          30
       5: iload_2
       6: ifne          26
       9: aload_0
      10: getfield      #5                  // Field lastResultPartial:Z
      13: ifeq          26
      16: aload_0
      17: dup
      18: getfield      #6                  // Field numberOfCompleteRows:I
      21: iconst_1
      22: iadd
      23: putfield      #6                  // Field numberOfCompleteRows:I
      26: getstatic     #7                  // Field EMPTY_RESULT_ARRAY:[Lorg/apache/hadoop/hbase/client/Result;
      29: areturn
      30: iconst_0
      31: istore_3
      32: iload_3
      33: aload_1
      34: arraylength
      35: if_icmpge     69
      38: aload_1
      39: iload_3
      40: aaload
      41: aload_0
      42: getfield      #3                  // Field lastCell:Lorg/apache/hadoop/hbase/Cell;
      45: invokestatic  #8                  // Method org/apache/hadoop/hbase/client/ConnectionUtils.filterCells:(Lorg/apache/hadoop/hbase/client/Result;Lorg/apache/hadoop/hbase/Cell;)Lorg/apache/hadoop/hbase/client/Result;
      48: astore        4
      50: aload         4
      52: ifnull        63
      55: aload_1
      56: iload_3
      57: aload         4
      59: aastore
      60: goto          69
      63: iinc          3, 1
      66: goto          32
      69: iload_3
      70: aload_1
      71: arraylength
      72: if_icmpne     79
      75: getstatic     #7                  // Field EMPTY_RESULT_ARRAY:[Lorg/apache/hadoop/hbase/client/Result;
      78: areturn
      79: aload_0
      80: getfield      #5                  // Field lastResultPartial:Z
      83: ifeq          112
      86: aload_0
      87: getfield      #3                  // Field lastCell:Lorg/apache/hadoop/hbase/Cell;
      90: aload_1
      91: iconst_0
      92: aaload
      93: invokevirtual #9                  // Method org/apache/hadoop/hbase/client/Result.getRow:()[B
      96: invokestatic  #10                 // Method org/apache/hadoop/hbase/CellUtil.matchingRows:(Lorg/apache/hadoop/hbase/Cell;[B)Z
      99: ifne          112
     102: aload_0
     103: dup
     104: getfield      #6                  // Field numberOfCompleteRows:I
     107: iconst_1
     108: iadd
     109: putfield      #6                  // Field numberOfCompleteRows:I
     112: aload_0
     113: aload_1
     114: aload_1
     115: arraylength
     116: iconst_1
     117: isub
     118: aaload
     119: invokespecial #11                 // Method recordLastResult:(Lorg/apache/hadoop/hbase/client/Result;)V
     122: iload_3
     123: ifle          137
     126: aload_1
     127: iload_3
     128: aload_1
     129: arraylength
     130: invokestatic  #12                 // Method java/util/Arrays.copyOfRange:([Ljava/lang/Object;II)[Ljava/lang/Object;
     133: checkcast     #13                 // class "[Lorg/apache/hadoop/hbase/client/Result;"
     136: astore_1
     137: aload_1
     138: astore        4
     140: aload         4
     142: arraylength
     143: istore        5
     145: iconst_0
     146: istore        6
     148: iload         6
     150: iload         5
     152: if_icmpge     186
     155: aload         4
     157: iload         6
     159: aaload
     160: astore        7
     162: aload         7
     164: invokevirtual #4                  // Method org/apache/hadoop/hbase/client/Result.mayHaveMoreCellsInRow:()Z
     167: ifne          180
     170: aload_0
     171: dup
     172: getfield      #6                  // Field numberOfCompleteRows:I
     175: iconst_1
     176: iadd
     177: putfield      #6                  // Field numberOfCompleteRows:I
     180: iinc          6, 1
     183: goto          148
     186: aload_1
     187: areturn

  public void clear();
    Code:
       0: return

  public int numberOfCompleteRows();
    Code:
       0: aload_0
       1: getfield      #6                  // Field numberOfCompleteRows:I
       4: ireturn
}
