Compiled from "Append.java"
public class org.apache.hadoop.hbase.client.Append extends org.apache.hadoop.hbase.client.Mutation {
  public org.apache.hadoop.hbase.client.Append setTimeRange(long, long);
    Code:
       0: aload_0
       1: new           #1                  // class org/apache/hadoop/hbase/io/TimeRange
       4: dup
       5: lload_1
       6: lload_3
       7: invokespecial #2                  // Method org/apache/hadoop/hbase/io/TimeRange."<init>":(JJ)V
      10: putfield      #3                  // Field tr:Lorg/apache/hadoop/hbase/io/TimeRange;
      13: aload_0
      14: areturn

  public org.apache.hadoop.hbase.io.TimeRange getTimeRange();
    Code:
       0: aload_0
       1: getfield      #3                  // Field tr:Lorg/apache/hadoop/hbase/io/TimeRange;
       4: areturn

  protected long extraHeapSize();
    Code:
       0: getstatic     #4                  // Field HEAP_OVERHEAD:J
       3: lreturn

  public org.apache.hadoop.hbase.client.Append setReturnResults(boolean);
    Code:
       0: aload_0
       1: iload_1
       2: invokespecial #5                  // Method org/apache/hadoop/hbase/client/Mutation.setReturnResults:(Z)Lorg/apache/hadoop/hbase/client/Mutation;
       5: pop
       6: aload_0
       7: areturn

  public boolean isReturnResults();
    Code:
       0: aload_0
       1: invokespecial #6                  // Method org/apache/hadoop/hbase/client/Mutation.isReturnResults:()Z
       4: ireturn

  public org.apache.hadoop.hbase.client.Append(byte[]);
    Code:
       0: aload_0
       1: aload_1
       2: iconst_0
       3: aload_1
       4: arraylength
       5: invokespecial #7                  // Method "<init>":([BII)V
       8: return

  public org.apache.hadoop.hbase.client.Append(org.apache.hadoop.hbase.client.Append);
    Code:
       0: aload_0
       1: aload_1
       2: invokespecial #8                  // Method org/apache/hadoop/hbase/client/Mutation."<init>":(Lorg/apache/hadoop/hbase/client/Mutation;)V
       5: aload_0
       6: invokestatic  #9                  // Method org/apache/hadoop/hbase/io/TimeRange.allTime:()Lorg/apache/hadoop/hbase/io/TimeRange;
       9: putfield      #3                  // Field tr:Lorg/apache/hadoop/hbase/io/TimeRange;
      12: aload_0
      13: aload_1
      14: invokevirtual #10                 // Method getTimeRange:()Lorg/apache/hadoop/hbase/io/TimeRange;
      17: putfield      #3                  // Field tr:Lorg/apache/hadoop/hbase/io/TimeRange;
      20: return

  public org.apache.hadoop.hbase.client.Append(byte[], int, int);
    Code:
       0: aload_0
       1: invokespecial #11                 // Method org/apache/hadoop/hbase/client/Mutation."<init>":()V
       4: aload_0
       5: invokestatic  #9                  // Method org/apache/hadoop/hbase/io/TimeRange.allTime:()Lorg/apache/hadoop/hbase/io/TimeRange;
       8: putfield      #3                  // Field tr:Lorg/apache/hadoop/hbase/io/TimeRange;
      11: aload_1
      12: iload_2
      13: iload_3
      14: invokestatic  #12                 // Method checkRow:([BII)[B
      17: pop
      18: aload_0
      19: aload_1
      20: iload_2
      21: iload_3
      22: invokestatic  #13                 // Method org/apache/hadoop/hbase/util/Bytes.copy:([BII)[B
      25: putfield      #14                 // Field row:[B
      28: return

  public org.apache.hadoop.hbase.client.Append(byte[], long, java.util.NavigableMap<byte[], java.util.List<org.apache.hadoop.hbase.Cell>>);
    Code:
       0: aload_0
       1: aload_1
       2: lload_2
       3: aload         4
       5: invokespecial #15                 // Method org/apache/hadoop/hbase/client/Mutation."<init>":([BJLjava/util/NavigableMap;)V
       8: aload_0
       9: invokestatic  #9                  // Method org/apache/hadoop/hbase/io/TimeRange.allTime:()Lorg/apache/hadoop/hbase/io/TimeRange;
      12: putfield      #3                  // Field tr:Lorg/apache/hadoop/hbase/io/TimeRange;
      15: return

  public org.apache.hadoop.hbase.client.Append add(byte[], byte[], byte[]);
    Code:
       0: aload_0
       1: aload_1
       2: aload_2
       3: aload_3
       4: invokevirtual #16                 // Method addColumn:([B[B[B)Lorg/apache/hadoop/hbase/client/Append;
       7: areturn

  public org.apache.hadoop.hbase.client.Append addColumn(byte[], byte[], byte[]);
    Code:
       0: new           #17                 // class org/apache/hadoop/hbase/KeyValue
       3: dup
       4: aload_0
       5: getfield      #14                 // Field row:[B
       8: aload_1
       9: aload_2
      10: aload_0
      11: getfield      #18                 // Field ts:J
      14: getstatic     #19                 // Field org/apache/hadoop/hbase/KeyValue$Type.Put:Lorg/apache/hadoop/hbase/KeyValue$Type;
      17: aload_3
      18: invokespecial #20                 // Method org/apache/hadoop/hbase/KeyValue."<init>":([B[B[BJLorg/apache/hadoop/hbase/KeyValue$Type;[B)V
      21: astore        4
      23: aload_0
      24: aload         4
      26: invokevirtual #21                 // Method add:(Lorg/apache/hadoop/hbase/Cell;)Lorg/apache/hadoop/hbase/client/Append;
      29: areturn

  public org.apache.hadoop.hbase.client.Append add(org.apache.hadoop.hbase.Cell);
    Code:
       0: aload_0
       1: aload_1
       2: invokespecial #22                 // Method org/apache/hadoop/hbase/client/Mutation.add:(Lorg/apache/hadoop/hbase/Cell;)Lorg/apache/hadoop/hbase/client/Mutation;
       5: pop
       6: goto          23
       9: astore_2
      10: getstatic     #24                 // Field LOG:Lorg/slf4j/Logger;
      13: aload_2
      14: invokevirtual #25                 // Method java/io/IOException.toString:()Ljava/lang/String;
      17: aload_2
      18: invokeinterface #26,  3           // InterfaceMethod org/slf4j/Logger.error:(Ljava/lang/String;Ljava/lang/Throwable;)V
      23: aload_0
      24: areturn
    Exception table:
       from    to  target type
           0     6     9   Class java/io/IOException

  public org.apache.hadoop.hbase.client.Append setTimestamp(long);
    Code:
       0: aload_0
       1: lload_1
       2: invokespecial #27                 // Method org/apache/hadoop/hbase/client/Mutation.setTimestamp:(J)Lorg/apache/hadoop/hbase/client/Mutation;
       5: pop
       6: aload_0
       7: areturn

  public org.apache.hadoop.hbase.client.Append setAttribute(java.lang.String, byte[]);
    Code:
       0: aload_0
       1: aload_1
       2: aload_2
       3: invokespecial #28                 // Method org/apache/hadoop/hbase/client/Mutation.setAttribute:(Ljava/lang/String;[B)Lorg/apache/hadoop/hbase/client/OperationWithAttributes;
       6: checkcast     #29                 // class org/apache/hadoop/hbase/client/Append
       9: areturn

  public org.apache.hadoop.hbase.client.Append setId(java.lang.String);
    Code:
       0: aload_0
       1: aload_1
       2: invokespecial #30                 // Method org/apache/hadoop/hbase/client/Mutation.setId:(Ljava/lang/String;)Lorg/apache/hadoop/hbase/client/OperationWithAttributes;
       5: checkcast     #29                 // class org/apache/hadoop/hbase/client/Append
       8: areturn

  public org.apache.hadoop.hbase.client.Append setDurability(org.apache.hadoop.hbase.client.Durability);
    Code:
       0: aload_0
       1: aload_1
       2: invokespecial #31                 // Method org/apache/hadoop/hbase/client/Mutation.setDurability:(Lorg/apache/hadoop/hbase/client/Durability;)Lorg/apache/hadoop/hbase/client/Mutation;
       5: checkcast     #29                 // class org/apache/hadoop/hbase/client/Append
       8: areturn

  public org.apache.hadoop.hbase.client.Append setFamilyCellMap(java.util.NavigableMap<byte[], java.util.List<org.apache.hadoop.hbase.Cell>>);
    Code:
       0: aload_0
       1: aload_1
       2: invokespecial #32                 // Method org/apache/hadoop/hbase/client/Mutation.setFamilyCellMap:(Ljava/util/NavigableMap;)Lorg/apache/hadoop/hbase/client/Mutation;
       5: checkcast     #29                 // class org/apache/hadoop/hbase/client/Append
       8: areturn

  public org.apache.hadoop.hbase.client.Append setClusterIds(java.util.List<java.util.UUID>);
    Code:
       0: aload_0
       1: aload_1
       2: invokespecial #33                 // Method org/apache/hadoop/hbase/client/Mutation.setClusterIds:(Ljava/util/List;)Lorg/apache/hadoop/hbase/client/Mutation;
       5: checkcast     #29                 // class org/apache/hadoop/hbase/client/Append
       8: areturn

  public org.apache.hadoop.hbase.client.Append setCellVisibility(org.apache.hadoop.hbase.security.visibility.CellVisibility);
    Code:
       0: aload_0
       1: aload_1
       2: invokespecial #34                 // Method org/apache/hadoop/hbase/client/Mutation.setCellVisibility:(Lorg/apache/hadoop/hbase/security/visibility/CellVisibility;)Lorg/apache/hadoop/hbase/client/Mutation;
       5: checkcast     #29                 // class org/apache/hadoop/hbase/client/Append
       8: areturn

  public org.apache.hadoop.hbase.client.Append setACL(java.lang.String, org.apache.hadoop.hbase.security.access.Permission);
    Code:
       0: aload_0
       1: aload_1
       2: aload_2
       3: invokespecial #35                 // Method org/apache/hadoop/hbase/client/Mutation.setACL:(Ljava/lang/String;Lorg/apache/hadoop/hbase/security/access/Permission;)Lorg/apache/hadoop/hbase/client/Mutation;
       6: checkcast     #29                 // class org/apache/hadoop/hbase/client/Append
       9: areturn

  public org.apache.hadoop.hbase.client.Append setACL(java.util.Map<java.lang.String, org.apache.hadoop.hbase.security.access.Permission>);
    Code:
       0: aload_0
       1: aload_1
       2: invokespecial #36                 // Method org/apache/hadoop/hbase/client/Mutation.setACL:(Ljava/util/Map;)Lorg/apache/hadoop/hbase/client/Mutation;
       5: checkcast     #29                 // class org/apache/hadoop/hbase/client/Append
       8: areturn

  public org.apache.hadoop.hbase.client.Append setPriority(int);
    Code:
       0: aload_0
       1: iload_1
       2: invokespecial #37                 // Method org/apache/hadoop/hbase/client/Mutation.setPriority:(I)Lorg/apache/hadoop/hbase/client/OperationWithAttributes;
       5: checkcast     #29                 // class org/apache/hadoop/hbase/client/Append
       8: areturn

  public org.apache.hadoop.hbase.client.Append setTTL(long);
    Code:
       0: aload_0
       1: lload_1
       2: invokespecial #38                 // Method org/apache/hadoop/hbase/client/Mutation.setTTL:(J)Lorg/apache/hadoop/hbase/client/Mutation;
       5: checkcast     #29                 // class org/apache/hadoop/hbase/client/Append
       8: areturn

  public org.apache.hadoop.hbase.client.Mutation add(org.apache.hadoop.hbase.Cell) throws java.io.IOException;
    Code:
       0: aload_0
       1: aload_1
       2: invokevirtual #21                 // Method add:(Lorg/apache/hadoop/hbase/Cell;)Lorg/apache/hadoop/hbase/client/Append;
       5: areturn

  public org.apache.hadoop.hbase.client.Mutation setTimestamp(long);
    Code:
       0: aload_0
       1: lload_1
       2: invokevirtual #39                 // Method setTimestamp:(J)Lorg/apache/hadoop/hbase/client/Append;
       5: areturn

  public org.apache.hadoop.hbase.client.Mutation setReturnResults(boolean);
    Code:
       0: aload_0
       1: iload_1
       2: invokevirtual #40                 // Method setReturnResults:(Z)Lorg/apache/hadoop/hbase/client/Append;
       5: areturn

  public org.apache.hadoop.hbase.client.Mutation setTTL(long);
    Code:
       0: aload_0
       1: lload_1
       2: invokevirtual #41                 // Method setTTL:(J)Lorg/apache/hadoop/hbase/client/Append;
       5: areturn

  public org.apache.hadoop.hbase.client.Mutation setACL(java.util.Map);
    Code:
       0: aload_0
       1: aload_1
       2: invokevirtual #42                 // Method setACL:(Ljava/util/Map;)Lorg/apache/hadoop/hbase/client/Append;
       5: areturn

  public org.apache.hadoop.hbase.client.Mutation setACL(java.lang.String, org.apache.hadoop.hbase.security.access.Permission);
    Code:
       0: aload_0
       1: aload_1
       2: aload_2
       3: invokevirtual #43                 // Method setACL:(Ljava/lang/String;Lorg/apache/hadoop/hbase/security/access/Permission;)Lorg/apache/hadoop/hbase/client/Append;
       6: areturn

  public org.apache.hadoop.hbase.client.Mutation setCellVisibility(org.apache.hadoop.hbase.security.visibility.CellVisibility);
    Code:
       0: aload_0
       1: aload_1
       2: invokevirtual #44                 // Method setCellVisibility:(Lorg/apache/hadoop/hbase/security/visibility/CellVisibility;)Lorg/apache/hadoop/hbase/client/Append;
       5: areturn

  public org.apache.hadoop.hbase.client.Mutation setClusterIds(java.util.List);
    Code:
       0: aload_0
       1: aload_1
       2: invokevirtual #45                 // Method setClusterIds:(Ljava/util/List;)Lorg/apache/hadoop/hbase/client/Append;
       5: areturn

  public org.apache.hadoop.hbase.client.Mutation setFamilyCellMap(java.util.NavigableMap);
    Code:
       0: aload_0
       1: aload_1
       2: invokevirtual #46                 // Method setFamilyCellMap:(Ljava/util/NavigableMap;)Lorg/apache/hadoop/hbase/client/Append;
       5: areturn

  public org.apache.hadoop.hbase.client.Mutation setDurability(org.apache.hadoop.hbase.client.Durability);
    Code:
       0: aload_0
       1: aload_1
       2: invokevirtual #47                 // Method setDurability:(Lorg/apache/hadoop/hbase/client/Durability;)Lorg/apache/hadoop/hbase/client/Append;
       5: areturn

  public org.apache.hadoop.hbase.client.OperationWithAttributes setPriority(int);
    Code:
       0: aload_0
       1: iload_1
       2: invokevirtual #48                 // Method setPriority:(I)Lorg/apache/hadoop/hbase/client/Append;
       5: areturn

  public org.apache.hadoop.hbase.client.OperationWithAttributes setId(java.lang.String);
    Code:
       0: aload_0
       1: aload_1
       2: invokevirtual #49                 // Method setId:(Ljava/lang/String;)Lorg/apache/hadoop/hbase/client/Append;
       5: areturn

  public org.apache.hadoop.hbase.client.OperationWithAttributes setAttribute(java.lang.String, byte[]);
    Code:
       0: aload_0
       1: aload_1
       2: aload_2
       3: invokevirtual #50                 // Method setAttribute:(Ljava/lang/String;[B)Lorg/apache/hadoop/hbase/client/Append;
       6: areturn

  public org.apache.hadoop.hbase.client.Attributes setAttribute(java.lang.String, byte[]);
    Code:
       0: aload_0
       1: aload_1
       2: aload_2
       3: invokevirtual #50                 // Method setAttribute:(Ljava/lang/String;[B)Lorg/apache/hadoop/hbase/client/Append;
       6: areturn

  static {};
    Code:
       0: ldc           #29                 // class org/apache/hadoop/hbase/client/Append
       2: invokestatic  #51                 // Method org/slf4j/LoggerFactory.getLogger:(Ljava/lang/Class;)Lorg/slf4j/Logger;
       5: putstatic     #24                 // Field LOG:Lorg/slf4j/Logger;
       8: getstatic     #52                 // Field org/apache/hadoop/hbase/util/ClassSize.REFERENCE:I
      11: getstatic     #53                 // Field org/apache/hadoop/hbase/util/ClassSize.TIMERANGE:I
      14: iadd
      15: i2l
      16: putstatic     #4                  // Field HEAP_OVERHEAD:J
      19: return
}
