Compiled from "AssignmentManager.java"
class org.apache.hadoop.hbase.master.assignment.AssignmentManager$1 implements org.apache.hadoop.hbase.master.assignment.RegionStateStore$RegionStateVisitor {
  static final boolean $assertionsDisabled;

  final org.apache.hadoop.hbase.master.assignment.AssignmentManager this$0;

  org.apache.hadoop.hbase.master.assignment.AssignmentManager$1(org.apache.hadoop.hbase.master.assignment.AssignmentManager);
    Code:
       0: aload_0
       1: aload_1
       2: putfield      #1                  // Field this$0:Lorg/apache/hadoop/hbase/master/assignment/AssignmentManager;
       5: aload_0
       6: invokespecial #2                  // Method java/lang/Object."<init>":()V
       9: return

  public void visitRegionState(org.apache.hadoop.hbase.client.Result, org.apache.hadoop.hbase.client.RegionInfo, org.apache.hadoop.hbase.master.RegionState$State, org.apache.hadoop.hbase.ServerName, org.apache.hadoop.hbase.ServerName, long);
    Code:
       0: aload_3
       1: ifnonnull     35
       4: aload         4
       6: ifnonnull     35
       9: aload         5
      11: ifnonnull     35
      14: lload         6
      16: ldc2_w        #4                  // long -1l
      19: lcmp
      20: ifne          35
      23: invokestatic  #6                  // Method org/apache/hadoop/hbase/master/assignment/AssignmentManager.access$200:()Lorg/slf4j/Logger;
      26: ldc           #7                  // String Skipping empty row={}
      28: aload_1
      29: invokeinterface #8,  3            // InterfaceMethod org/slf4j/Logger.warn:(Ljava/lang/String;Ljava/lang/Object;)V
      34: return
      35: aload_3
      36: astore        8
      38: aload         8
      40: ifnonnull     86
      43: invokestatic  #6                  // Method org/apache/hadoop/hbase/master/assignment/AssignmentManager.access$200:()Lorg/slf4j/Logger;
      46: new           #9                  // class java/lang/StringBuilder
      49: dup
      50: invokespecial #10                 // Method java/lang/StringBuilder."<init>":()V
      53: aload_2
      54: invokeinterface #11,  1           // InterfaceMethod org/apache/hadoop/hbase/client/RegionInfo.getEncodedName:()Ljava/lang/String;
      59: invokevirtual #12                 // Method java/lang/StringBuilder.append:(Ljava/lang/String;)Ljava/lang/StringBuilder;
      62: ldc           #13                 // String  regionState=null; presuming
      64: invokevirtual #12                 // Method java/lang/StringBuilder.append:(Ljava/lang/String;)Ljava/lang/StringBuilder;
      67: getstatic     #14                 // Field org/apache/hadoop/hbase/master/RegionState$State.OFFLINE:Lorg/apache/hadoop/hbase/master/RegionState$State;
      70: invokevirtual #15                 // Method java/lang/StringBuilder.append:(Ljava/lang/Object;)Ljava/lang/StringBuilder;
      73: invokevirtual #16                 // Method java/lang/StringBuilder.toString:()Ljava/lang/String;
      76: invokeinterface #17,  2           // InterfaceMethod org/slf4j/Logger.info:(Ljava/lang/String;)V
      81: getstatic     #14                 // Field org/apache/hadoop/hbase/master/RegionState$State.OFFLINE:Lorg/apache/hadoop/hbase/master/RegionState$State;
      84: astore        8
      86: aload_0
      87: getfield      #1                  // Field this$0:Lorg/apache/hadoop/hbase/master/assignment/AssignmentManager;
      90: invokestatic  #18                 // Method org/apache/hadoop/hbase/master/assignment/AssignmentManager.access$300:(Lorg/apache/hadoop/hbase/master/assignment/AssignmentManager;)Lorg/apache/hadoop/hbase/master/assignment/RegionStates;
      93: aload_2
      94: invokevirtual #19                 // Method org/apache/hadoop/hbase/master/assignment/RegionStates.getOrCreateRegionStateNode:(Lorg/apache/hadoop/hbase/client/RegionInfo;)Lorg/apache/hadoop/hbase/master/assignment/RegionStateNode;
      97: astore        9
      99: aload         9
     101: aload         8
     103: iconst_0
     104: anewarray     #20                 // class org/apache/hadoop/hbase/master/RegionState$State
     107: invokevirtual #21                 // Method org/apache/hadoop/hbase/master/assignment/RegionStateNode.setState:(Lorg/apache/hadoop/hbase/master/RegionState$State;[Lorg/apache/hadoop/hbase/master/RegionState$State;)Z
     110: pop
     111: aload         9
     113: aload         5
     115: invokevirtual #22                 // Method org/apache/hadoop/hbase/master/assignment/RegionStateNode.setLastHost:(Lorg/apache/hadoop/hbase/ServerName;)V
     118: aload         9
     120: aload         4
     122: invokevirtual #23                 // Method org/apache/hadoop/hbase/master/assignment/RegionStateNode.setRegionLocation:(Lorg/apache/hadoop/hbase/ServerName;)Lorg/apache/hadoop/hbase/ServerName;
     125: pop
     126: aload         9
     128: lload         6
     130: invokevirtual #24                 // Method org/apache/hadoop/hbase/master/assignment/RegionStateNode.setOpenSeqNum:(J)V
     133: aload         8
     135: iconst_5
     136: anewarray     #20                 // class org/apache/hadoop/hbase/master/RegionState$State
     139: dup
     140: iconst_0
     141: getstatic     #25                 // Field org/apache/hadoop/hbase/master/RegionState$State.OPEN:Lorg/apache/hadoop/hbase/master/RegionState$State;
     144: aastore
     145: dup
     146: iconst_1
     147: getstatic     #26                 // Field org/apache/hadoop/hbase/master/RegionState$State.OPENING:Lorg/apache/hadoop/hbase/master/RegionState$State;
     150: aastore
     151: dup
     152: iconst_2
     153: getstatic     #27                 // Field org/apache/hadoop/hbase/master/RegionState$State.CLOSING:Lorg/apache/hadoop/hbase/master/RegionState$State;
     156: aastore
     157: dup
     158: iconst_3
     159: getstatic     #28                 // Field org/apache/hadoop/hbase/master/RegionState$State.SPLITTING:Lorg/apache/hadoop/hbase/master/RegionState$State;
     162: aastore
     163: dup
     164: iconst_4
     165: getstatic     #29                 // Field org/apache/hadoop/hbase/master/RegionState$State.MERGING:Lorg/apache/hadoop/hbase/master/RegionState$State;
     168: aastore
     169: invokevirtual #30                 // Method org/apache/hadoop/hbase/master/RegionState$State.matches:([Lorg/apache/hadoop/hbase/master/RegionState$State;)Z
     172: ifeq          230
     175: getstatic     #31                 // Field $assertionsDisabled:Z
     178: ifne          214
     181: aload         4
     183: ifnonnull     214
     186: new           #32                 // class java/lang/AssertionError
     189: dup
     190: new           #9                  // class java/lang/StringBuilder
     193: dup
     194: invokespecial #10                 // Method java/lang/StringBuilder."<init>":()V
     197: ldc           #33                 // String found null region location for
     199: invokevirtual #12                 // Method java/lang/StringBuilder.append:(Ljava/lang/String;)Ljava/lang/StringBuilder;
     202: aload         9
     204: invokevirtual #15                 // Method java/lang/StringBuilder.append:(Ljava/lang/Object;)Ljava/lang/StringBuilder;
     207: invokevirtual #16                 // Method java/lang/StringBuilder.toString:()Ljava/lang/String;
     210: invokespecial #34                 // Method java/lang/AssertionError."<init>":(Ljava/lang/Object;)V
     213: athrow
     214: aload_0
     215: getfield      #1                  // Field this$0:Lorg/apache/hadoop/hbase/master/assignment/AssignmentManager;
     218: invokestatic  #18                 // Method org/apache/hadoop/hbase/master/assignment/AssignmentManager.access$300:(Lorg/apache/hadoop/hbase/master/assignment/AssignmentManager;)Lorg/apache/hadoop/hbase/master/assignment/RegionStates;
     221: aload         9
     223: invokevirtual #35                 // Method org/apache/hadoop/hbase/master/assignment/RegionStates.addRegionToServer:(Lorg/apache/hadoop/hbase/master/assignment/RegionStateNode;)Lorg/apache/hadoop/hbase/master/assignment/ServerStateNode;
     226: pop
     227: goto          259
     230: aload         8
     232: getstatic     #14                 // Field org/apache/hadoop/hbase/master/RegionState$State.OFFLINE:Lorg/apache/hadoop/hbase/master/RegionState$State;
     235: if_acmpeq     247
     238: aload_2
     239: invokeinterface #36,  1           // InterfaceMethod org/apache/hadoop/hbase/client/RegionInfo.isOffline:()Z
     244: ifeq          259
     247: aload_0
     248: getfield      #1                  // Field this$0:Lorg/apache/hadoop/hbase/master/assignment/AssignmentManager;
     251: invokestatic  #18                 // Method org/apache/hadoop/hbase/master/assignment/AssignmentManager.access$300:(Lorg/apache/hadoop/hbase/master/assignment/AssignmentManager;)Lorg/apache/hadoop/hbase/master/assignment/RegionStates;
     254: aload         9
     256: invokevirtual #37                 // Method org/apache/hadoop/hbase/master/assignment/RegionStates.addToOfflineRegions:(Lorg/apache/hadoop/hbase/master/assignment/RegionStateNode;)V
     259: aload         9
     261: invokevirtual #38                 // Method org/apache/hadoop/hbase/master/assignment/RegionStateNode.getProcedure:()Lorg/apache/hadoop/hbase/master/assignment/TransitRegionStateProcedure;
     264: ifnull        281
     267: aload         9
     269: invokevirtual #38                 // Method org/apache/hadoop/hbase/master/assignment/RegionStateNode.getProcedure:()Lorg/apache/hadoop/hbase/master/assignment/TransitRegionStateProcedure;
     272: aload_0
     273: getfield      #1                  // Field this$0:Lorg/apache/hadoop/hbase/master/assignment/AssignmentManager;
     276: aload         9
     278: invokevirtual #39                 // Method org/apache/hadoop/hbase/master/assignment/TransitRegionStateProcedure.stateLoaded:(Lorg/apache/hadoop/hbase/master/assignment/AssignmentManager;Lorg/apache/hadoop/hbase/master/assignment/RegionStateNode;)V
     281: return

  static {};
    Code:
       0: ldc           #40                 // class org/apache/hadoop/hbase/master/assignment/AssignmentManager
       2: invokevirtual #41                 // Method java/lang/Class.desiredAssertionStatus:()Z
       5: ifne          12
       8: iconst_1
       9: goto          13
      12: iconst_0
      13: putstatic     #31                 // Field $assertionsDisabled:Z
      16: return
}
