Compiled from "AssignmentManager.java"
class org.apache.hadoop.hbase.master.assignment.AssignmentManager$2 extends java.lang.Thread {
  final org.apache.hadoop.hbase.master.assignment.AssignmentManager this$0;

  org.apache.hadoop.hbase.master.assignment.AssignmentManager$2(org.apache.hadoop.hbase.master.assignment.AssignmentManager, java.lang.String);
    Code:
       0: aload_0
       1: aload_1
       2: putfield      #1                  // Field this$0:Lorg/apache/hadoop/hbase/master/assignment/AssignmentManager;
       5: aload_0
       6: aload_2
       7: invokespecial #2                  // Method java/lang/Thread."<init>":(Ljava/lang/String;)V
      10: return

  public void run();
    Code:
       0: aload_0
       1: getfield      #1                  // Field this$0:Lorg/apache/hadoop/hbase/master/assignment/AssignmentManager;
       4: invokevirtual #3                  // Method org/apache/hadoop/hbase/master/assignment/AssignmentManager.isRunning:()Z
       7: ifeq          20
      10: aload_0
      11: getfield      #1                  // Field this$0:Lorg/apache/hadoop/hbase/master/assignment/AssignmentManager;
      14: invokestatic  #4                  // Method org/apache/hadoop/hbase/master/assignment/AssignmentManager.access$400:(Lorg/apache/hadoop/hbase/master/assignment/AssignmentManager;)V
      17: goto          0
      20: aload_0
      21: getfield      #1                  // Field this$0:Lorg/apache/hadoop/hbase/master/assignment/AssignmentManager;
      24: invokestatic  #5                  // Method org/apache/hadoop/hbase/master/assignment/AssignmentManager.access$500:(Lorg/apache/hadoop/hbase/master/assignment/AssignmentManager;)Ljava/util/ArrayList;
      27: invokevirtual #6                  // Method java/util/ArrayList.clear:()V
      30: return
}
