Compiled from "AssignmentManagerStatusTmplImpl.java"
public class org.apache.hadoop.hbase.tmpl.master.AssignmentManagerStatusTmplImpl extends org.jamon.AbstractTemplateImpl implements org.apache.hadoop.hbase.tmpl.master.AssignmentManagerStatusTmpl$Intf {
  protected static org.apache.hadoop.hbase.tmpl.master.AssignmentManagerStatusTmpl$ImplData __jamon_setOptionalArguments(org.apache.hadoop.hbase.tmpl.master.AssignmentManagerStatusTmpl$ImplData);
    Code:
       0: aload_0
       1: invokevirtual #1                  // Method org/apache/hadoop/hbase/tmpl/master/AssignmentManagerStatusTmpl$ImplData.getLimit__IsNotDefault:()Z
       4: ifne          13
       7: aload_0
       8: bipush        100
      10: invokevirtual #2                  // Method org/apache/hadoop/hbase/tmpl/master/AssignmentManagerStatusTmpl$ImplData.setLimit:(I)V
      13: aload_0
      14: areturn

  public org.apache.hadoop.hbase.tmpl.master.AssignmentManagerStatusTmplImpl(org.jamon.TemplateManager, org.apache.hadoop.hbase.tmpl.master.AssignmentManagerStatusTmpl$ImplData);
    Code:
       0: aload_0
       1: aload_1
       2: aload_2
       3: invokestatic  #3                  // Method __jamon_setOptionalArguments:(Lorg/apache/hadoop/hbase/tmpl/master/AssignmentManagerStatusTmpl$ImplData;)Lorg/apache/hadoop/hbase/tmpl/master/AssignmentManagerStatusTmpl$ImplData;
       6: invokespecial #4                  // Method org/jamon/AbstractTemplateImpl."<init>":(Lorg/jamon/TemplateManager;Lorg/jamon/AbstractTemplateProxy$ImplData;)V
       9: aload_0
      10: aload_2
      11: invokevirtual #5                  // Method org/apache/hadoop/hbase/tmpl/master/AssignmentManagerStatusTmpl$ImplData.getAssignmentManager:()Lorg/apache/hadoop/hbase/master/assignment/AssignmentManager;
      14: putfield      #6                  // Field assignmentManager:Lorg/apache/hadoop/hbase/master/assignment/AssignmentManager;
      17: aload_0
      18: aload_2
      19: invokevirtual #7                  // Method org/apache/hadoop/hbase/tmpl/master/AssignmentManagerStatusTmpl$ImplData.getLimit:()I
      22: putfield      #8                  // Field limit:I
      25: return

  public void renderNoFlush(java.io.Writer) throws java.io.IOException;
    Code:
       0: aload_0
       1: getfield      #6                  // Field assignmentManager:Lorg/apache/hadoop/hbase/master/assignment/AssignmentManager;
       4: invokevirtual #9                  // Method org/apache/hadoop/hbase/master/assignment/AssignmentManager.getRegionStates:()Lorg/apache/hadoop/hbase/master/assignment/RegionStates;
       7: invokevirtual #10                 // Method org/apache/hadoop/hbase/master/assignment/RegionStates.getRegionsInTransitionOrderedByTimestamp:()Ljava/util/SortedSet;
      10: astore_2
      11: aload_2
      12: invokeinterface #11,  1           // InterfaceMethod java/util/SortedSet.isEmpty:()Z
      17: ifne          715
      20: aload_1
      21: ldc           #12                 // String \n
      23: invokevirtual #13                 // Method java/io/Writer.write:(Ljava/lang/String;)V
      26: invokestatic  #14                 // Method java/lang/System.currentTimeMillis:()J
      29: lstore_3
      30: aload_0
      31: getfield      #6                  // Field assignmentManager:Lorg/apache/hadoop/hbase/master/assignment/AssignmentManager;
      34: invokevirtual #15                 // Method org/apache/hadoop/hbase/master/assignment/AssignmentManager.computeRegionInTransitionStat:()Lorg/apache/hadoop/hbase/master/assignment/AssignmentManager$RegionInTransitionStat;
      37: astore        5
      39: aload_2
      40: invokeinterface #16,  1           // InterfaceMethod java/util/SortedSet.size:()I
      45: istore        6
      47: iconst_5
      48: iload         6
      50: invokestatic  #17                 // Method java/lang/Math.min:(II)I
      53: istore        7
      55: iload         6
      57: i2d
      58: dconst_1
      59: dmul
      60: iload         7
      62: i2d
      63: ddiv
      64: invokestatic  #18                 // Method java/lang/Math.ceil:(D)D
      67: d2i
      68: istore        8
      70: aload_1
      71: ldc           #19                 // String <section>\n    <h2><a name=\"rit\">Regions in Transition</a></h2>\n     <p><a href=\"/rits.jsp\">
      73: invokevirtual #13                 // Method java/io/Writer.write:(Ljava/lang/String;)V
      76: getstatic     #20                 // Field org/jamon/escaping/Escaping.HTML:Lorg/jamon/escaping/Escaping;
      79: iload         6
      81: invokestatic  #21                 // Method org/jamon/emit/StandardEmitter.valueOf:(I)Ljava/lang/String;
      84: aload_1
      85: invokeinterface #22,  3           // InterfaceMethod org/jamon/escaping/Escaping.write:(Ljava/lang/String;Ljava/io/Writer;)V
      90: aload_1
      91: ldc           #23                 // String  region(s) in transition.</a>\n
      93: invokevirtual #13                 // Method java/io/Writer.write:(Ljava/lang/String;)V
      96: aload         5
      98: invokevirtual #24                 // Method org/apache/hadoop/hbase/master/assignment/AssignmentManager$RegionInTransitionStat.hasRegionsTwiceOverThreshold:()Z
     101: ifeq          113
     104: aload_1
     105: ldc           #25                 // String \n         <span class=\"label label-danger\" style=\"font-size:100%;font-weight:normal\">\n
     107: invokevirtual #13                 // Method java/io/Writer.write:(Ljava/lang/String;)V
     110: goto          136
     113: aload         5
     115: invokevirtual #26                 // Method org/apache/hadoop/hbase/master/assignment/AssignmentManager$RegionInTransitionStat.hasRegionsOverThreshold:()Z
     118: ifeq          130
     121: aload_1
     122: ldc           #27                 // String \n         <span class=\"label label-warning\" style=\"font-size:100%;font-weight:normal\">\n
     124: invokevirtual #13                 // Method java/io/Writer.write:(Ljava/lang/String;)V
     127: goto          136
     130: aload_1
     131: ldc           #28                 // String \n         <span>\n
     133: invokevirtual #13                 // Method java/io/Writer.write:(Ljava/lang/String;)V
     136: aload_1
     137: ldc           #29                 // String \n
     139: invokevirtual #13                 // Method java/io/Writer.write:(Ljava/lang/String;)V
     142: getstatic     #20                 // Field org/jamon/escaping/Escaping.HTML:Lorg/jamon/escaping/Escaping;
     145: aload         5
     147: invokevirtual #30                 // Method org/apache/hadoop/hbase/master/assignment/AssignmentManager$RegionInTransitionStat.getTotalRITsOverThreshold:()I
     150: invokestatic  #21                 // Method org/jamon/emit/StandardEmitter.valueOf:(I)Ljava/lang/String;
     153: aload_1
     154: invokeinterface #22,  3           // InterfaceMethod org/jamon/escaping/Escaping.write:(Ljava/lang/String;Ljava/io/Writer;)V
     159: aload_1
     160: ldc           #31                 // String  region(s) in transition for\n             more than
     162: invokevirtual #13                 // Method java/io/Writer.write:(Ljava/lang/String;)V
     165: getstatic     #20                 // Field org/jamon/escaping/Escaping.HTML:Lorg/jamon/escaping/Escaping;
     168: aload         5
     170: invokevirtual #32                 // Method org/apache/hadoop/hbase/master/assignment/AssignmentManager$RegionInTransitionStat.getRITThreshold:()I
     173: invokestatic  #21                 // Method org/jamon/emit/StandardEmitter.valueOf:(I)Ljava/lang/String;
     176: aload_1
     177: invokeinterface #22,  3           // InterfaceMethod org/jamon/escaping/Escaping.write:(Ljava/lang/String;Ljava/io/Writer;)V
     182: aload_1
     183: ldc           #33                 // String  milliseconds.\n         </span>\n     </p>\n     <div class=\"tabbable\">\n         <div class=\"tab-content\">\n
     185: invokevirtual #13                 // Method java/io/Writer.write:(Ljava/lang/String;)V
     188: iconst_0
     189: istore        9
     191: aload_2
     192: invokeinterface #34,  1           // InterfaceMethod java/util/SortedSet.iterator:()Ljava/util/Iterator;
     197: astore        10
     199: aload         10
     201: invokeinterface #35,  1           // InterfaceMethod java/util/Iterator.hasNext:()Z
     206: ifeq          568
     209: aload         10
     211: invokeinterface #36,  1           // InterfaceMethod java/util/Iterator.next:()Ljava/lang/Object;
     216: checkcast     #37                 // class org/apache/hadoop/hbase/master/RegionState
     219: astore        11
     221: aload_1
     222: ldc           #38                 // String \n
     224: invokevirtual #13                 // Method java/io/Writer.write:(Ljava/lang/String;)V
     227: iload         9
     229: iload         7
     231: irem
     232: ifne          317
     235: aload_1
     236: ldc           #39                 // String \n
     238: invokevirtual #13                 // Method java/io/Writer.write:(Ljava/lang/String;)V
     241: iload         9
     243: ifne          280
     246: aload_1
     247: ldc           #40                 // String \n             <div class=\"tab-pane active\" id=\"tab_rits
     249: invokevirtual #13                 // Method java/io/Writer.write:(Ljava/lang/String;)V
     252: getstatic     #20                 // Field org/jamon/escaping/Escaping.HTML:Lorg/jamon/escaping/Escaping;
     255: iload         9
     257: iload         7
     259: idiv
     260: iconst_1
     261: iadd
     262: invokestatic  #21                 // Method org/jamon/emit/StandardEmitter.valueOf:(I)Ljava/lang/String;
     265: aload_1
     266: invokeinterface #22,  3           // InterfaceMethod org/jamon/escaping/Escaping.write:(Ljava/lang/String;Ljava/io/Writer;)V
     271: aload_1
     272: ldc           #41                 // String \">\n
     274: invokevirtual #13                 // Method java/io/Writer.write:(Ljava/lang/String;)V
     277: goto          311
     280: aload_1
     281: ldc           #42                 // String \n             <div class=\"tab-pane\" id=\"tab_rits
     283: invokevirtual #13                 // Method java/io/Writer.write:(Ljava/lang/String;)V
     286: getstatic     #20                 // Field org/jamon/escaping/Escaping.HTML:Lorg/jamon/escaping/Escaping;
     289: iload         9
     291: iload         7
     293: idiv
     294: iconst_1
     295: iadd
     296: invokestatic  #21                 // Method org/jamon/emit/StandardEmitter.valueOf:(I)Ljava/lang/String;
     299: aload_1
     300: invokeinterface #22,  3           // InterfaceMethod org/jamon/escaping/Escaping.write:(Ljava/lang/String;Ljava/io/Writer;)V
     305: aload_1
     306: ldc           #41                 // String \">\n
     308: invokevirtual #13                 // Method java/io/Writer.write:(Ljava/lang/String;)V
     311: aload_1
     312: ldc           #43                 // String \n                 <table class=\"table table-striped\" style=\"margin-bottom:0px;\"><tr><th>Region</th>\n                     <th>State</th><th>RIT time (ms)</th> <th>Retries </th></tr>\n
     314: invokevirtual #13                 // Method java/io/Writer.write:(Ljava/lang/String;)V
     317: aload_1
     318: ldc           #44                 // String \n\n
     320: invokevirtual #13                 // Method java/io/Writer.write:(Ljava/lang/String;)V
     323: aload         5
     325: aload         11
     327: invokevirtual #45                 // Method org/apache/hadoop/hbase/master/RegionState.getRegion:()Lorg/apache/hadoop/hbase/client/RegionInfo;
     330: invokevirtual #46                 // Method org/apache/hadoop/hbase/master/assignment/AssignmentManager$RegionInTransitionStat.isRegionTwiceOverThreshold:(Lorg/apache/hadoop/hbase/client/RegionInfo;)Z
     333: ifeq          345
     336: aload_1
     337: ldc           #47                 // String \n                     <tr class=\"alert alert-danger\" role=\"alert\">\n
     339: invokevirtual #13                 // Method java/io/Writer.write:(Ljava/lang/String;)V
     342: goto          373
     345: aload         5
     347: aload         11
     349: invokevirtual #45                 // Method org/apache/hadoop/hbase/master/RegionState.getRegion:()Lorg/apache/hadoop/hbase/client/RegionInfo;
     352: invokevirtual #48                 // Method org/apache/hadoop/hbase/master/assignment/AssignmentManager$RegionInTransitionStat.isRegionOverThreshold:(Lorg/apache/hadoop/hbase/client/RegionInfo;)Z
     355: ifeq          367
     358: aload_1
     359: ldc           #49                 // String \n                     <tr class=\"alert alert-warning\" role=\"alert\">\n
     361: invokevirtual #13                 // Method java/io/Writer.write:(Ljava/lang/String;)V
     364: goto          373
     367: aload_1
     368: ldc           #50                 // String \n                    <tr>\n
     370: invokevirtual #13                 // Method java/io/Writer.write:(Ljava/lang/String;)V
     373: aload_1
     374: ldc           #51                 // String \n
     376: invokevirtual #13                 // Method java/io/Writer.write:(Ljava/lang/String;)V
     379: ldc           #52                 // String 0
     381: astore        12
     383: aload_0
     384: getfield      #6                  // Field assignmentManager:Lorg/apache/hadoop/hbase/master/assignment/AssignmentManager;
     387: invokevirtual #9                  // Method org/apache/hadoop/hbase/master/assignment/AssignmentManager.getRegionStates:()Lorg/apache/hadoop/hbase/master/assignment/RegionStates;
     390: aload         11
     392: invokevirtual #45                 // Method org/apache/hadoop/hbase/master/RegionState.getRegion:()Lorg/apache/hadoop/hbase/client/RegionInfo;
     395: invokevirtual #53                 // Method org/apache/hadoop/hbase/master/assignment/RegionStates.getFailedOpen:(Lorg/apache/hadoop/hbase/client/RegionInfo;)Lorg/apache/hadoop/hbase/master/assignment/RegionStates$RegionFailedOpen;
     398: astore        13
     400: aload         13
     402: ifnull        418
     405: aload         13
     407: invokevirtual #54                 // Method org/apache/hadoop/hbase/master/assignment/RegionStates$RegionFailedOpen.getRetries:()I
     410: invokestatic  #55                 // Method java/lang/Integer.toString:(I)Ljava/lang/String;
     413: astore        12
     415: goto          433
     418: aload         11
     420: invokevirtual #56                 // Method org/apache/hadoop/hbase/master/RegionState.getState:()Lorg/apache/hadoop/hbase/master/RegionState$State;
     423: getstatic     #57                 // Field org/apache/hadoop/hbase/master/RegionState$State.FAILED_OPEN:Lorg/apache/hadoop/hbase/master/RegionState$State;
     426: if_acmpne     433
     429: ldc           #58                 // String Failed
     431: astore        12
     433: aload_1
     434: ldc           #59                 // String <td>
     436: invokevirtual #13                 // Method java/io/Writer.write:(Ljava/lang/String;)V
     439: getstatic     #20                 // Field org/jamon/escaping/Escaping.HTML:Lorg/jamon/escaping/Escaping;
     442: aload         11
     444: invokevirtual #45                 // Method org/apache/hadoop/hbase/master/RegionState.getRegion:()Lorg/apache/hadoop/hbase/client/RegionInfo;
     447: invokeinterface #60,  1           // InterfaceMethod org/apache/hadoop/hbase/client/RegionInfo.getEncodedName:()Ljava/lang/String;
     452: invokestatic  #61                 // Method org/jamon/emit/StandardEmitter.valueOf:(Ljava/lang/String;)Ljava/lang/String;
     455: aload_1
     456: invokeinterface #22,  3           // InterfaceMethod org/jamon/escaping/Escaping.write:(Ljava/lang/String;Ljava/io/Writer;)V
     461: aload_1
     462: ldc           #62                 // String </td><td>\n
     464: invokevirtual #13                 // Method java/io/Writer.write:(Ljava/lang/String;)V
     467: getstatic     #20                 // Field org/jamon/escaping/Escaping.HTML:Lorg/jamon/escaping/Escaping;
     470: aload         11
     472: aload_0
     473: getfield      #6                  // Field assignmentManager:Lorg/apache/hadoop/hbase/master/assignment/AssignmentManager;
     476: invokevirtual #63                 // Method org/apache/hadoop/hbase/master/assignment/AssignmentManager.getConfiguration:()Lorg/apache/hadoop/conf/Configuration;
     479: invokestatic  #64                 // Method org/apache/hadoop/hbase/client/RegionInfoDisplay.getDescriptiveNameFromRegionStateForDisplay:(Lorg/apache/hadoop/hbase/master/RegionState;Lorg/apache/hadoop/conf/Configuration;)Ljava/lang/String;
     482: invokestatic  #61                 // Method org/jamon/emit/StandardEmitter.valueOf:(Ljava/lang/String;)Ljava/lang/String;
     485: aload_1
     486: invokeinterface #22,  3           // InterfaceMethod org/jamon/escaping/Escaping.write:(Ljava/lang/String;Ljava/io/Writer;)V
     491: aload_1
     492: ldc           #65                 // String </td>\n                        <td>
     494: invokevirtual #13                 // Method java/io/Writer.write:(Ljava/lang/String;)V
     497: getstatic     #20                 // Field org/jamon/escaping/Escaping.HTML:Lorg/jamon/escaping/Escaping;
     500: lload_3
     501: aload         11
     503: invokevirtual #66                 // Method org/apache/hadoop/hbase/master/RegionState.getStamp:()J
     506: lsub
     507: invokestatic  #67                 // Method org/jamon/emit/StandardEmitter.valueOf:(J)Ljava/lang/String;
     510: aload_1
     511: invokeinterface #22,  3           // InterfaceMethod org/jamon/escaping/Escaping.write:(Ljava/lang/String;Ljava/io/Writer;)V
     516: aload_1
     517: ldc           #68                 // String  </td>\n                        <td>
     519: invokevirtual #13                 // Method java/io/Writer.write:(Ljava/lang/String;)V
     522: getstatic     #20                 // Field org/jamon/escaping/Escaping.HTML:Lorg/jamon/escaping/Escaping;
     525: aload         12
     527: invokestatic  #61                 // Method org/jamon/emit/StandardEmitter.valueOf:(Ljava/lang/String;)Ljava/lang/String;
     530: aload_1
     531: invokeinterface #22,  3           // InterfaceMethod org/jamon/escaping/Escaping.write:(Ljava/lang/String;Ljava/io/Writer;)V
     536: aload_1
     537: ldc           #69                 // String  </td>\n                     </tr>\n
     539: invokevirtual #13                 // Method java/io/Writer.write:(Ljava/lang/String;)V
     542: iinc          9, 1
     545: iload         9
     547: iload         7
     549: irem
     550: ifne          559
     553: aload_1
     554: ldc           #70                 // String \n                 </table>\n             </div>\n
     556: invokevirtual #13                 // Method java/io/Writer.write:(Ljava/lang/String;)V
     559: aload_1
     560: ldc           #29                 // String \n
     562: invokevirtual #13                 // Method java/io/Writer.write:(Ljava/lang/String;)V
     565: goto          199
     568: aload_1
     569: ldc           #71                 // String \n\n
     571: invokevirtual #13                 // Method java/io/Writer.write:(Ljava/lang/String;)V
     574: iload         9
     576: iload         7
     578: irem
     579: ifeq          614
     582: aload_1
     583: ldc           #38                 // String \n
     585: invokevirtual #13                 // Method java/io/Writer.write:(Ljava/lang/String;)V
     588: iload         9
     590: iload         7
     592: irem
     593: ifeq          608
     596: aload_1
     597: ldc           #72                 // String \n             <tr><td colspan=\"3\" style=\"height:61px\"></td></tr>\n
     599: invokevirtual #13                 // Method java/io/Writer.write:(Ljava/lang/String;)V
     602: iinc          9, 1
     605: goto          588
     608: aload_1
     609: ldc           #73                 // String \n                   </table>\n             </div>\n
     611: invokevirtual #13                 // Method java/io/Writer.write:(Ljava/lang/String;)V
     614: aload_1
     615: ldc           #74                 // String \n         </div>\n         <nav>\n             <ul class=\"nav nav-pills pagination\">\n
     617: invokevirtual #13                 // Method java/io/Writer.write:(Ljava/lang/String;)V
     620: iconst_1
     621: istore        10
     623: iload         10
     625: iload         8
     627: if_icmpgt     709
     630: aload_1
     631: ldc           #39                 // String \n
     633: invokevirtual #13                 // Method java/io/Writer.write:(Ljava/lang/String;)V
     636: iload         10
     638: iconst_1
     639: if_icmpne     651
     642: aload_1
     643: ldc           #75                 // String \n                 <li class=\"active\">\n
     645: invokevirtual #13                 // Method java/io/Writer.write:(Ljava/lang/String;)V
     648: goto          657
     651: aload_1
     652: ldc           #76                 // String \n                 <li>\n
     654: invokevirtual #13                 // Method java/io/Writer.write:(Ljava/lang/String;)V
     657: aload_1
     658: ldc           #77                 // String \n                 <a href=\"#tab_rits
     660: invokevirtual #13                 // Method java/io/Writer.write:(Ljava/lang/String;)V
     663: getstatic     #20                 // Field org/jamon/escaping/Escaping.HTML:Lorg/jamon/escaping/Escaping;
     666: iload         10
     668: invokestatic  #21                 // Method org/jamon/emit/StandardEmitter.valueOf:(I)Ljava/lang/String;
     671: aload_1
     672: invokeinterface #22,  3           // InterfaceMethod org/jamon/escaping/Escaping.write:(Ljava/lang/String;Ljava/io/Writer;)V
     677: aload_1
     678: ldc           #78                 // String \">
     680: invokevirtual #13                 // Method java/io/Writer.write:(Ljava/lang/String;)V
     683: getstatic     #20                 // Field org/jamon/escaping/Escaping.HTML:Lorg/jamon/escaping/Escaping;
     686: iload         10
     688: invokestatic  #21                 // Method org/jamon/emit/StandardEmitter.valueOf:(I)Ljava/lang/String;
     691: aload_1
     692: invokeinterface #22,  3           // InterfaceMethod org/jamon/escaping/Escaping.write:(Ljava/lang/String;Ljava/io/Writer;)V
     697: aload_1
     698: ldc           #79                 // String </a></li>\n
     700: invokevirtual #13                 // Method java/io/Writer.write:(Ljava/lang/String;)V
     703: iinc          10, 1
     706: goto          623
     709: aload_1
     710: ldc           #80                 // String \n             </ul>\n         </nav>\n     </div>\n   </section>\n
     712: invokevirtual #13                 // Method java/io/Writer.write:(Ljava/lang/String;)V
     715: aload_1
     716: ldc           #81                 // String \n\n
     718: invokevirtual #13                 // Method java/io/Writer.write:(Ljava/lang/String;)V
     721: return
}
