Compiled from "AssignProcedure.java"
public class org.apache.hadoop.hbase.master.assignment.AssignProcedure extends org.apache.hadoop.hbase.master.assignment.RegionTransitionProcedure {
  protected volatile org.apache.hadoop.hbase.ServerName targetServer;

  public org.apache.hadoop.hbase.master.assignment.AssignProcedure();
    Code:
       0: aload_0
       1: invokespecial #1                  // Method org/apache/hadoop/hbase/master/assignment/RegionTransitionProcedure."<init>":()V
       4: aload_0
       5: iconst_0
       6: putfield      #2                  // Field forceNewPlan:Z
       9: return

  public org.apache.hadoop.hbase.master.procedure.TableProcedureInterface$TableOperationType getTableOperationType();
    Code:
       0: getstatic     #3                  // Field org/apache/hadoop/hbase/master/procedure/TableProcedureInterface$TableOperationType.REGION_ASSIGN:Lorg/apache/hadoop/hbase/master/procedure/TableProcedureInterface$TableOperationType;
       3: areturn

  protected boolean isRollbackSupported(org.apache.hadoop.hbase.shaded.protobuf.generated.MasterProcedureProtos$RegionTransitionState);
    Code:
       0: getstatic     #4                  // Field org/apache/hadoop/hbase/master/assignment/AssignProcedure$1.$SwitchMap$org$apache$hadoop$hbase$shaded$protobuf$generated$MasterProcedureProtos$RegionTransitionState:[I
       3: aload_1
       4: invokevirtual #5                  // Method org/apache/hadoop/hbase/shaded/protobuf/generated/MasterProcedureProtos$RegionTransitionState.ordinal:()I
       7: iaload
       8: lookupswitch  { // 1
                     1: 28
               default: 30
          }
      28: iconst_1
      29: ireturn
      30: iconst_0
      31: ireturn

  protected void serializeStateData(org.apache.hadoop.hbase.procedure2.ProcedureStateSerializer) throws java.io.IOException;
    Code:
       0: invokestatic  #6                  // Method org/apache/hadoop/hbase/shaded/protobuf/generated/MasterProcedureProtos$AssignRegionStateData.newBuilder:()Lorg/apache/hadoop/hbase/shaded/protobuf/generated/MasterProcedureProtos$AssignRegionStateData$Builder;
       3: aload_0
       4: invokevirtual #7                  // Method getTransitionState:()Lorg/apache/hadoop/hbase/shaded/protobuf/generated/MasterProcedureProtos$RegionTransitionState;
       7: invokevirtual #8                  // Method org/apache/hadoop/hbase/shaded/protobuf/generated/MasterProcedureProtos$AssignRegionStateData$Builder.setTransitionState:(Lorg/apache/hadoop/hbase/shaded/protobuf/generated/MasterProcedureProtos$RegionTransitionState;)Lorg/apache/hadoop/hbase/shaded/protobuf/generated/MasterProcedureProtos$AssignRegionStateData$Builder;
      10: aload_0
      11: invokevirtual #9                  // Method getRegionInfo:()Lorg/apache/hadoop/hbase/client/RegionInfo;
      14: invokestatic  #10                 // Method org/apache/hadoop/hbase/shaded/protobuf/ProtobufUtil.toRegionInfo:(Lorg/apache/hadoop/hbase/client/RegionInfo;)Lorg/apache/hadoop/hbase/shaded/protobuf/generated/HBaseProtos$RegionInfo;
      17: invokevirtual #11                 // Method org/apache/hadoop/hbase/shaded/protobuf/generated/MasterProcedureProtos$AssignRegionStateData$Builder.setRegionInfo:(Lorg/apache/hadoop/hbase/shaded/protobuf/generated/HBaseProtos$RegionInfo;)Lorg/apache/hadoop/hbase/shaded/protobuf/generated/MasterProcedureProtos$AssignRegionStateData$Builder;
      20: astore_2
      21: aload_0
      22: getfield      #2                  // Field forceNewPlan:Z
      25: ifeq          34
      28: aload_2
      29: iconst_1
      30: invokevirtual #12                 // Method org/apache/hadoop/hbase/shaded/protobuf/generated/MasterProcedureProtos$AssignRegionStateData$Builder.setForceNewPlan:(Z)Lorg/apache/hadoop/hbase/shaded/protobuf/generated/MasterProcedureProtos$AssignRegionStateData$Builder;
      33: pop
      34: aload_0
      35: getfield      #13                 // Field targetServer:Lorg/apache/hadoop/hbase/ServerName;
      38: ifnull        53
      41: aload_2
      42: aload_0
      43: getfield      #13                 // Field targetServer:Lorg/apache/hadoop/hbase/ServerName;
      46: invokestatic  #14                 // Method org/apache/hadoop/hbase/shaded/protobuf/ProtobufUtil.toServerName:(Lorg/apache/hadoop/hbase/ServerName;)Lorg/apache/hadoop/hbase/shaded/protobuf/generated/HBaseProtos$ServerName;
      49: invokevirtual #15                 // Method org/apache/hadoop/hbase/shaded/protobuf/generated/MasterProcedureProtos$AssignRegionStateData$Builder.setTargetServer:(Lorg/apache/hadoop/hbase/shaded/protobuf/generated/HBaseProtos$ServerName;)Lorg/apache/hadoop/hbase/shaded/protobuf/generated/MasterProcedureProtos$AssignRegionStateData$Builder;
      52: pop
      53: aload_0
      54: invokevirtual #16                 // Method getAttempt:()I
      57: ifle          69
      60: aload_2
      61: aload_0
      62: invokevirtual #16                 // Method getAttempt:()I
      65: invokevirtual #17                 // Method org/apache/hadoop/hbase/shaded/protobuf/generated/MasterProcedureProtos$AssignRegionStateData$Builder.setAttempt:(I)Lorg/apache/hadoop/hbase/shaded/protobuf/generated/MasterProcedureProtos$AssignRegionStateData$Builder;
      68: pop
      69: aload_1
      70: aload_2
      71: invokevirtual #18                 // Method org/apache/hadoop/hbase/shaded/protobuf/generated/MasterProcedureProtos$AssignRegionStateData$Builder.build:()Lorg/apache/hadoop/hbase/shaded/protobuf/generated/MasterProcedureProtos$AssignRegionStateData;
      74: invokeinterface #19,  2           // InterfaceMethod org/apache/hadoop/hbase/procedure2/ProcedureStateSerializer.serialize:(Lorg/apache/hbase/thirdparty/com/google/protobuf/Message;)V
      79: return

  protected void deserializeStateData(org.apache.hadoop.hbase.procedure2.ProcedureStateSerializer) throws java.io.IOException;
    Code:
       0: aload_1
       1: ldc           #20                 // class org/apache/hadoop/hbase/shaded/protobuf/generated/MasterProcedureProtos$AssignRegionStateData
       3: invokeinterface #21,  2           // InterfaceMethod org/apache/hadoop/hbase/procedure2/ProcedureStateSerializer.deserialize:(Ljava/lang/Class;)Lorg/apache/hbase/thirdparty/com/google/protobuf/Message;
       8: checkcast     #20                 // class org/apache/hadoop/hbase/shaded/protobuf/generated/MasterProcedureProtos$AssignRegionStateData
      11: astore_2
      12: aload_0
      13: aload_2
      14: invokevirtual #22                 // Method org/apache/hadoop/hbase/shaded/protobuf/generated/MasterProcedureProtos$AssignRegionStateData.getTransitionState:()Lorg/apache/hadoop/hbase/shaded/protobuf/generated/MasterProcedureProtos$RegionTransitionState;
      17: invokevirtual #23                 // Method setTransitionState:(Lorg/apache/hadoop/hbase/shaded/protobuf/generated/MasterProcedureProtos$RegionTransitionState;)V
      20: aload_0
      21: aload_2
      22: invokevirtual #24                 // Method org/apache/hadoop/hbase/shaded/protobuf/generated/MasterProcedureProtos$AssignRegionStateData.getRegionInfo:()Lorg/apache/hadoop/hbase/shaded/protobuf/generated/HBaseProtos$RegionInfo;
      25: invokestatic  #25                 // Method org/apache/hadoop/hbase/shaded/protobuf/ProtobufUtil.toRegionInfo:(Lorg/apache/hadoop/hbase/shaded/protobuf/generated/HBaseProtos$RegionInfo;)Lorg/apache/hadoop/hbase/client/RegionInfo;
      28: invokevirtual #26                 // Method setRegionInfo:(Lorg/apache/hadoop/hbase/client/RegionInfo;)V
      31: aload_0
      32: aload_2
      33: invokevirtual #27                 // Method org/apache/hadoop/hbase/shaded/protobuf/generated/MasterProcedureProtos$AssignRegionStateData.getForceNewPlan:()Z
      36: putfield      #2                  // Field forceNewPlan:Z
      39: aload_2
      40: invokevirtual #28                 // Method org/apache/hadoop/hbase/shaded/protobuf/generated/MasterProcedureProtos$AssignRegionStateData.hasTargetServer:()Z
      43: ifeq          57
      46: aload_0
      47: aload_2
      48: invokevirtual #29                 // Method org/apache/hadoop/hbase/shaded/protobuf/generated/MasterProcedureProtos$AssignRegionStateData.getTargetServer:()Lorg/apache/hadoop/hbase/shaded/protobuf/generated/HBaseProtos$ServerName;
      51: invokestatic  #30                 // Method org/apache/hadoop/hbase/shaded/protobuf/ProtobufUtil.toServerName:(Lorg/apache/hadoop/hbase/shaded/protobuf/generated/HBaseProtos$ServerName;)Lorg/apache/hadoop/hbase/ServerName;
      54: putfield      #13                 // Field targetServer:Lorg/apache/hadoop/hbase/ServerName;
      57: aload_2
      58: invokevirtual #31                 // Method org/apache/hadoop/hbase/shaded/protobuf/generated/MasterProcedureProtos$AssignRegionStateData.hasAttempt:()Z
      61: ifeq          72
      64: aload_0
      65: aload_2
      66: invokevirtual #32                 // Method org/apache/hadoop/hbase/shaded/protobuf/generated/MasterProcedureProtos$AssignRegionStateData.getAttempt:()I
      69: invokevirtual #33                 // Method setAttempt:(I)V
      72: return

  protected boolean startTransition(org.apache.hadoop.hbase.master.procedure.MasterProcedureEnv, org.apache.hadoop.hbase.master.assignment.RegionStateNode) throws java.io.IOException;
    Code:
       0: iconst_1
       1: ireturn

  protected boolean updateTransition(org.apache.hadoop.hbase.master.procedure.MasterProcedureEnv, org.apache.hadoop.hbase.master.assignment.RegionStateNode) throws java.io.IOException, org.apache.hadoop.hbase.procedure2.ProcedureSuspendedException;
    Code:
       0: iconst_1
       1: ireturn

  protected void finishTransition(org.apache.hadoop.hbase.master.procedure.MasterProcedureEnv, org.apache.hadoop.hbase.master.assignment.RegionStateNode) throws java.io.IOException;
    Code:
       0: return

  protected void reportTransition(org.apache.hadoop.hbase.master.procedure.MasterProcedureEnv, org.apache.hadoop.hbase.master.assignment.RegionStateNode, org.apache.hadoop.hbase.shaded.protobuf.generated.RegionServerStatusProtos$RegionStateTransition$TransitionCode, long) throws org.apache.hadoop.hbase.exceptions.UnexpectedStateException;
    Code:
       0: return

  public java.util.Optional<org.apache.hadoop.hbase.procedure2.RemoteProcedureDispatcher$RemoteOperation> remoteCallBuild(org.apache.hadoop.hbase.master.procedure.MasterProcedureEnv, org.apache.hadoop.hbase.ServerName);
    Code:
       0: invokestatic  #34                 // Method java/util/Optional.empty:()Ljava/util/Optional;
       3: areturn

  protected boolean remoteCallFailed(org.apache.hadoop.hbase.master.procedure.MasterProcedureEnv, org.apache.hadoop.hbase.master.assignment.RegionStateNode, java.io.IOException);
    Code:
       0: iconst_1
       1: ireturn

  public void toStringClassDetails(java.lang.StringBuilder);
    Code:
       0: aload_0
       1: aload_1
       2: invokespecial #35                 // Method org/apache/hadoop/hbase/master/assignment/RegionTransitionProcedure.toStringClassDetails:(Ljava/lang/StringBuilder;)V
       5: aload_0
       6: getfield      #13                 // Field targetServer:Lorg/apache/hadoop/hbase/ServerName;
       9: ifnull        26
      12: aload_1
      13: ldc           #36                 // String , target=
      15: invokevirtual #37                 // Method java/lang/StringBuilder.append:(Ljava/lang/String;)Ljava/lang/StringBuilder;
      18: aload_0
      19: getfield      #13                 // Field targetServer:Lorg/apache/hadoop/hbase/ServerName;
      22: invokevirtual #38                 // Method java/lang/StringBuilder.append:(Ljava/lang/Object;)Ljava/lang/StringBuilder;
      25: pop
      26: return

  protected org.apache.hadoop.hbase.procedure2.ProcedureMetrics getProcedureMetrics(org.apache.hadoop.hbase.master.procedure.MasterProcedureEnv);
    Code:
       0: aload_1
       1: invokevirtual #39                 // Method org/apache/hadoop/hbase/master/procedure/MasterProcedureEnv.getAssignmentManager:()Lorg/apache/hadoop/hbase/master/assignment/AssignmentManager;
       4: invokevirtual #40                 // Method org/apache/hadoop/hbase/master/assignment/AssignmentManager.getAssignmentManagerMetrics:()Lorg/apache/hadoop/hbase/master/MetricsAssignmentManager;
       7: invokevirtual #41                 // Method org/apache/hadoop/hbase/master/MetricsAssignmentManager.getAssignProcMetrics:()Lorg/apache/hadoop/hbase/procedure2/ProcedureMetrics;
      10: areturn

  public java.util.Optional remoteCallBuild(java.lang.Object, java.lang.Object);
    Code:
       0: aload_0
       1: aload_1
       2: checkcast     #42                 // class org/apache/hadoop/hbase/master/procedure/MasterProcedureEnv
       5: aload_2
       6: checkcast     #43                 // class org/apache/hadoop/hbase/ServerName
       9: invokevirtual #44                 // Method remoteCallBuild:(Lorg/apache/hadoop/hbase/master/procedure/MasterProcedureEnv;Lorg/apache/hadoop/hbase/ServerName;)Ljava/util/Optional;
      12: areturn

  protected org.apache.hadoop.hbase.procedure2.ProcedureMetrics getProcedureMetrics(java.lang.Object);
    Code:
       0: aload_0
       1: aload_1
       2: checkcast     #42                 // class org/apache/hadoop/hbase/master/procedure/MasterProcedureEnv
       5: invokevirtual #45                 // Method getProcedureMetrics:(Lorg/apache/hadoop/hbase/master/procedure/MasterProcedureEnv;)Lorg/apache/hadoop/hbase/procedure2/ProcedureMetrics;
       8: areturn
}
