Compiled from "AssignmentManager.java"
public class org.apache.hadoop.hbase.master.assignment.AssignmentManager {
  public static final java.lang.String BOOTSTRAP_THREAD_POOL_SIZE_CONF_KEY;

  public static final java.lang.String ASSIGN_DISPATCH_WAIT_MSEC_CONF_KEY;

  public static final java.lang.String ASSIGN_DISPATCH_WAITQ_MAX_CONF_KEY;

  public static final java.lang.String RIT_CHORE_INTERVAL_MSEC_CONF_KEY;

  public static final java.lang.String ASSIGN_MAX_ATTEMPTS;

  public static final java.lang.String ASSIGN_RETRY_IMMEDIATELY_MAX_ATTEMPTS;

  public static final java.lang.String METRICS_RIT_STUCK_WARNING_THRESHOLD;

  static final boolean $assertionsDisabled;

  public org.apache.hadoop.hbase.master.assignment.AssignmentManager(org.apache.hadoop.hbase.master.MasterServices);
    Code:
       0: aload_0
       1: aload_1
       2: new           #8                  // class org/apache/hadoop/hbase/master/assignment/RegionStateStore
       5: dup
       6: aload_1
       7: invokespecial #9                  // Method org/apache/hadoop/hbase/master/assignment/RegionStateStore."<init>":(Lorg/apache/hadoop/hbase/master/MasterServices;)V
      10: invokespecial #10                 // Method "<init>":(Lorg/apache/hadoop/hbase/master/MasterServices;Lorg/apache/hadoop/hbase/master/assignment/RegionStateStore;)V
      13: return

  org.apache.hadoop.hbase.master.assignment.AssignmentManager(org.apache.hadoop.hbase.master.MasterServices, org.apache.hadoop.hbase.master.assignment.RegionStateStore);
    Code:
       0: aload_0
       1: invokespecial #11                 // Method java/lang/Object."<init>":()V
       4: aload_0
       5: new           #12                 // class org/apache/hadoop/hbase/procedure2/ProcedureEvent
       8: dup
       9: ldc           #13                 // String meta assign
      11: invokespecial #14                 // Method org/apache/hadoop/hbase/procedure2/ProcedureEvent."<init>":(Ljava/lang/Object;)V
      14: putfield      #15                 // Field metaAssignEvent:Lorg/apache/hadoop/hbase/procedure2/ProcedureEvent;
      17: aload_0
      18: new           #12                 // class org/apache/hadoop/hbase/procedure2/ProcedureEvent
      21: dup
      22: ldc           #16                 // String meta load
      24: invokespecial #14                 // Method org/apache/hadoop/hbase/procedure2/ProcedureEvent."<init>":(Ljava/lang/Object;)V
      27: putfield      #17                 // Field metaLoadEvent:Lorg/apache/hadoop/hbase/procedure2/ProcedureEvent;
      30: aload_0
      31: new           #18                 // class java/util/concurrent/atomic/AtomicBoolean
      34: dup
      35: iconst_0
      36: invokespecial #19                 // Method java/util/concurrent/atomic/AtomicBoolean."<init>":(Z)V
      39: putfield      #20                 // Field running:Ljava/util/concurrent/atomic/AtomicBoolean;
      42: aload_0
      43: new           #21                 // class org/apache/hadoop/hbase/master/assignment/RegionStates
      46: dup
      47: invokespecial #22                 // Method org/apache/hadoop/hbase/master/assignment/RegionStates."<init>":()V
      50: putfield      #4                  // Field regionStates:Lorg/apache/hadoop/hbase/master/assignment/RegionStates;
      53: aload_0
      54: new           #23                 // class java/lang/Object
      57: dup
      58: invokespecial #11                 // Method java/lang/Object."<init>":()V
      61: putfield      #24                 // Field checkIfShouldMoveSystemRegionLock:Ljava/lang/Object;
      64: aload_0
      65: new           #25                 // class java/util/ArrayList
      68: dup
      69: invokespecial #26                 // Method java/util/ArrayList."<init>":()V
      72: putfield      #2                  // Field pendingAssignQueue:Ljava/util/ArrayList;
      75: aload_0
      76: new           #27                 // class java/util/concurrent/locks/ReentrantLock
      79: dup
      80: invokespecial #28                 // Method java/util/concurrent/locks/ReentrantLock."<init>":()V
      83: putfield      #29                 // Field assignQueueLock:Ljava/util/concurrent/locks/ReentrantLock;
      86: aload_0
      87: aload_0
      88: getfield      #29                 // Field assignQueueLock:Ljava/util/concurrent/locks/ReentrantLock;
      91: invokevirtual #30                 // Method java/util/concurrent/locks/ReentrantLock.newCondition:()Ljava/util/concurrent/locks/Condition;
      94: putfield      #31                 // Field assignQueueFullCond:Ljava/util/concurrent/locks/Condition;
      97: aload_0
      98: aload_1
      99: putfield      #32                 // Field master:Lorg/apache/hadoop/hbase/master/MasterServices;
     102: aload_0
     103: aload_2
     104: putfield      #33                 // Field regionStateStore:Lorg/apache/hadoop/hbase/master/assignment/RegionStateStore;
     107: aload_0
     108: new           #34                 // class org/apache/hadoop/hbase/master/MetricsAssignmentManager
     111: dup
     112: invokespecial #35                 // Method org/apache/hadoop/hbase/master/MetricsAssignmentManager."<init>":()V
     115: putfield      #36                 // Field metrics:Lorg/apache/hadoop/hbase/master/MetricsAssignmentManager;
     118: aload_1
     119: invokeinterface #37,  1           // InterfaceMethod org/apache/hadoop/hbase/master/MasterServices.getConfiguration:()Lorg/apache/hadoop/conf/Configuration;
     124: astore_3
     125: aload_0
     126: ldc           #38                 // class org/apache/hadoop/hbase/master/balancer/FavoredStochasticBalancer
     128: aload_3
     129: ldc           #40                 // String hbase.master.loadbalancer.class
     131: ldc           #23                 // class java/lang/Object
     133: invokevirtual #41                 // Method org/apache/hadoop/conf/Configuration.getClass:(Ljava/lang/String;Ljava/lang/Class;)Ljava/lang/Class;
     136: invokevirtual #42                 // Method java/lang/Class.isAssignableFrom:(Ljava/lang/Class;)Z
     139: putfield      #43                 // Field shouldAssignRegionsWithFavoredNodes:Z
     142: aload_0
     143: aload_3
     144: ldc           #45                 // String hbase.assignment.dispatch.wait.msec
     146: sipush        150
     149: invokevirtual #46                 // Method org/apache/hadoop/conf/Configuration.getInt:(Ljava/lang/String;I)I
     152: putfield      #47                 // Field assignDispatchWaitMillis:I
     155: aload_0
     156: aload_3
     157: ldc           #48                 // String hbase.assignment.dispatch.wait.queue.max.size
     159: bipush        100
     161: invokevirtual #46                 // Method org/apache/hadoop/conf/Configuration.getInt:(Ljava/lang/String;I)I
     164: putfield      #49                 // Field assignDispatchWaitQueueMaxSize:I
     167: aload_0
     168: iconst_1
     169: aload_3
     170: ldc           #50                 // String hbase.assignment.maximum.attempts
     172: ldc           #51                 // int 2147483647
     174: invokevirtual #46                 // Method org/apache/hadoop/conf/Configuration.getInt:(Ljava/lang/String;I)I
     177: invokestatic  #52                 // Method java/lang/Math.max:(II)I
     180: putfield      #53                 // Field assignMaxAttempts:I
     183: aload_0
     184: aload_3
     185: ldc           #54                 // String hbase.assignment.retry.immediately.maximum.attempts
     187: iconst_3
     188: invokevirtual #46                 // Method org/apache/hadoop/conf/Configuration.getInt:(Ljava/lang/String;I)I
     191: putfield      #55                 // Field assignRetryImmediatelyMaxAttempts:I
     194: aload_3
     195: ldc           #56                 // String hbase.assignment.rit.chore.interval.msec
     197: ldc           #57                 // int 60000
     199: invokevirtual #46                 // Method org/apache/hadoop/conf/Configuration.getInt:(Ljava/lang/String;I)I
     202: istore        4
     204: aload_0
     205: new           #58                 // class org/apache/hadoop/hbase/master/assignment/AssignmentManager$RegionInTransitionChore
     208: dup
     209: iload         4
     211: invokespecial #59                 // Method org/apache/hadoop/hbase/master/assignment/AssignmentManager$RegionInTransitionChore."<init>":(I)V
     214: putfield      #60                 // Field ritChore:Lorg/apache/hadoop/hbase/master/assignment/AssignmentManager$RegionInTransitionChore;
     217: return

  public void start() throws java.io.IOException, org.apache.zookeeper.KeeperException;
    Code:
       0: aload_0
       1: getfield      #20                 // Field running:Ljava/util/concurrent/atomic/AtomicBoolean;
       4: iconst_0
       5: iconst_1
       6: invokevirtual #61                 // Method java/util/concurrent/atomic/AtomicBoolean.compareAndSet:(ZZ)Z
       9: ifne          13
      12: return
      13: getstatic     #5                  // Field LOG:Lorg/slf4j/Logger;
      16: ldc           #62                 // String Starting assignment manager
      18: invokeinterface #63,  2           // InterfaceMethod org/slf4j/Logger.trace:(Ljava/lang/String;)V
      23: aload_0
      24: invokespecial #64                 // Method startAssignmentThread:()V
      27: aload_0
      28: getfield      #32                 // Field master:Lorg/apache/hadoop/hbase/master/MasterServices;
      31: invokeinterface #65,  1           // InterfaceMethod org/apache/hadoop/hbase/master/MasterServices.getZooKeeper:()Lorg/apache/hadoop/hbase/zookeeper/ZKWatcher;
      36: astore_1
      37: aload_1
      38: ifnull        138
      41: aload_1
      42: invokestatic  #66                 // Method org/apache/hadoop/hbase/zookeeper/MetaTableLocator.getMetaRegionState:(Lorg/apache/hadoop/hbase/zookeeper/ZKWatcher;)Lorg/apache/hadoop/hbase/master/RegionState;
      45: astore_2
      46: aload_0
      47: getfield      #4                  // Field regionStates:Lorg/apache/hadoop/hbase/master/assignment/RegionStates;
      50: getstatic     #67                 // Field org/apache/hadoop/hbase/client/RegionInfoBuilder.FIRST_META_REGIONINFO:Lorg/apache/hadoop/hbase/client/RegionInfo;
      53: invokevirtual #68                 // Method org/apache/hadoop/hbase/master/assignment/RegionStates.getOrCreateRegionStateNode:(Lorg/apache/hadoop/hbase/client/RegionInfo;)Lorg/apache/hadoop/hbase/master/assignment/RegionStateNode;
      56: astore_3
      57: aload_3
      58: invokevirtual #69                 // Method org/apache/hadoop/hbase/master/assignment/RegionStateNode.lock:()V
      61: aload_3
      62: aload_2
      63: invokevirtual #70                 // Method org/apache/hadoop/hbase/master/RegionState.getServerName:()Lorg/apache/hadoop/hbase/ServerName;
      66: invokevirtual #71                 // Method org/apache/hadoop/hbase/master/assignment/RegionStateNode.setRegionLocation:(Lorg/apache/hadoop/hbase/ServerName;)Lorg/apache/hadoop/hbase/ServerName;
      69: pop
      70: aload_3
      71: aload_2
      72: invokevirtual #72                 // Method org/apache/hadoop/hbase/master/RegionState.getState:()Lorg/apache/hadoop/hbase/master/RegionState$State;
      75: iconst_0
      76: anewarray     #73                 // class org/apache/hadoop/hbase/master/RegionState$State
      79: invokevirtual #74                 // Method org/apache/hadoop/hbase/master/assignment/RegionStateNode.setState:(Lorg/apache/hadoop/hbase/master/RegionState$State;[Lorg/apache/hadoop/hbase/master/RegionState$State;)Z
      82: pop
      83: aload_3
      84: invokevirtual #75                 // Method org/apache/hadoop/hbase/master/assignment/RegionStateNode.getProcedure:()Lorg/apache/hadoop/hbase/master/assignment/TransitRegionStateProcedure;
      87: ifnull        99
      90: aload_3
      91: invokevirtual #75                 // Method org/apache/hadoop/hbase/master/assignment/RegionStateNode.getProcedure:()Lorg/apache/hadoop/hbase/master/assignment/TransitRegionStateProcedure;
      94: aload_0
      95: aload_3
      96: invokevirtual #76                 // Method org/apache/hadoop/hbase/master/assignment/TransitRegionStateProcedure.stateLoaded:(Lorg/apache/hadoop/hbase/master/assignment/AssignmentManager;Lorg/apache/hadoop/hbase/master/assignment/RegionStateNode;)V
      99: aload_0
     100: aload_2
     101: invokevirtual #77                 // Method org/apache/hadoop/hbase/master/RegionState.getRegion:()Lorg/apache/hadoop/hbase/client/RegionInfo;
     104: aload_2
     105: invokevirtual #72                 // Method org/apache/hadoop/hbase/master/RegionState.getState:()Lorg/apache/hadoop/hbase/master/RegionState$State;
     108: getstatic     #78                 // Field org/apache/hadoop/hbase/master/RegionState$State.OPEN:Lorg/apache/hadoop/hbase/master/RegionState$State;
     111: if_acmpne     118
     114: iconst_1
     115: goto          119
     118: iconst_0
     119: invokespecial #79                 // Method setMetaAssigned:(Lorg/apache/hadoop/hbase/client/RegionInfo;Z)V
     122: aload_3
     123: invokevirtual #80                 // Method org/apache/hadoop/hbase/master/assignment/RegionStateNode.unlock:()V
     126: goto          138
     129: astore        4
     131: aload_3
     132: invokevirtual #80                 // Method org/apache/hadoop/hbase/master/assignment/RegionStateNode.unlock:()V
     135: aload         4
     137: athrow
     138: return
    Exception table:
       from    to  target type
          61   122   129   any
         129   131   129   any

  public void setupRIT(java.util.List<org.apache.hadoop.hbase.master.assignment.TransitRegionStateProcedure>);
    Code:
       0: aload_1
       1: aload_0
       2: invokedynamic #81,  0             // InvokeDynamic #0:accept:(Lorg/apache/hadoop/hbase/master/assignment/AssignmentManager;)Ljava/util/function/Consumer;
       7: invokeinterface #82,  2           // InterfaceMethod java/util/List.forEach:(Ljava/util/function/Consumer;)V
      12: return

  public void stop();
    Code:
       0: aload_0
       1: getfield      #20                 // Field running:Ljava/util/concurrent/atomic/AtomicBoolean;
       4: iconst_1
       5: iconst_0
       6: invokevirtual #61                 // Method java/util/concurrent/atomic/AtomicBoolean.compareAndSet:(ZZ)Z
       9: ifne          13
      12: return
      13: getstatic     #5                  // Field LOG:Lorg/slf4j/Logger;
      16: ldc           #83                 // String Stopping assignment manager
      18: invokeinterface #84,  2           // InterfaceMethod org/slf4j/Logger.info:(Ljava/lang/String;)V
      23: aload_0
      24: getfield      #32                 // Field master:Lorg/apache/hadoop/hbase/master/MasterServices;
      27: invokeinterface #85,  1           // InterfaceMethod org/apache/hadoop/hbase/master/MasterServices.getMasterProcedureExecutor:()Lorg/apache/hadoop/hbase/procedure2/ProcedureExecutor;
      32: ifnull        39
      35: iconst_1
      36: goto          40
      39: iconst_0
      40: istore_1
      41: iload_1
      42: ifeq          62
      45: aload_0
      46: getfield      #32                 // Field master:Lorg/apache/hadoop/hbase/master/MasterServices;
      49: invokeinterface #85,  1           // InterfaceMethod org/apache/hadoop/hbase/master/MasterServices.getMasterProcedureExecutor:()Lorg/apache/hadoop/hbase/procedure2/ProcedureExecutor;
      54: aload_0
      55: getfield      #60                 // Field ritChore:Lorg/apache/hadoop/hbase/master/assignment/AssignmentManager$RegionInTransitionChore;
      58: invokevirtual #86                 // Method org/apache/hadoop/hbase/procedure2/ProcedureExecutor.removeChore:(Lorg/apache/hadoop/hbase/procedure2/ProcedureInMemoryChore;)Z
      61: pop
      62: aload_0
      63: invokespecial #87                 // Method stopAssignmentThread:()V
      66: aload_0
      67: getfield      #4                  // Field regionStates:Lorg/apache/hadoop/hbase/master/assignment/RegionStates;
      70: invokevirtual #88                 // Method org/apache/hadoop/hbase/master/assignment/RegionStates.clear:()V
      73: iload_1
      74: ifeq          122
      77: aload_0
      78: getfield      #17                 // Field metaLoadEvent:Lorg/apache/hadoop/hbase/procedure2/ProcedureEvent;
      81: invokevirtual #89                 // Method org/apache/hadoop/hbase/procedure2/ProcedureEvent.suspend:()V
      84: aload_0
      85: invokevirtual #90                 // Method getMetaRegionSet:()Ljava/util/Set;
      88: invokeinterface #91,  1           // InterfaceMethod java/util/Set.iterator:()Ljava/util/Iterator;
      93: astore_2
      94: aload_2
      95: invokeinterface #92,  1           // InterfaceMethod java/util/Iterator.hasNext:()Z
     100: ifeq          122
     103: aload_2
     104: invokeinterface #93,  1           // InterfaceMethod java/util/Iterator.next:()Ljava/lang/Object;
     109: checkcast     #94                 // class org/apache/hadoop/hbase/client/RegionInfo
     112: astore_3
     113: aload_0
     114: aload_3
     115: iconst_0
     116: invokespecial #79                 // Method setMetaAssigned:(Lorg/apache/hadoop/hbase/client/RegionInfo;Z)V
     119: goto          94
     122: return

  public boolean isRunning();
    Code:
       0: aload_0
       1: getfield      #20                 // Field running:Ljava/util/concurrent/atomic/AtomicBoolean;
       4: invokevirtual #95                 // Method java/util/concurrent/atomic/AtomicBoolean.get:()Z
       7: ireturn

  public org.apache.hadoop.conf.Configuration getConfiguration();
    Code:
       0: aload_0
       1: getfield      #32                 // Field master:Lorg/apache/hadoop/hbase/master/MasterServices;
       4: invokeinterface #37,  1           // InterfaceMethod org/apache/hadoop/hbase/master/MasterServices.getConfiguration:()Lorg/apache/hadoop/conf/Configuration;
       9: areturn

  public org.apache.hadoop.hbase.master.MetricsAssignmentManager getAssignmentManagerMetrics();
    Code:
       0: aload_0
       1: getfield      #36                 // Field metrics:Lorg/apache/hadoop/hbase/master/MetricsAssignmentManager;
       4: areturn

  int getAssignMaxAttempts();
    Code:
       0: aload_0
       1: getfield      #53                 // Field assignMaxAttempts:I
       4: ireturn

  int getAssignRetryImmediatelyMaxAttempts();
    Code:
       0: aload_0
       1: getfield      #55                 // Field assignRetryImmediatelyMaxAttempts:I
       4: ireturn

  public org.apache.hadoop.hbase.master.assignment.RegionStates getRegionStates();
    Code:
       0: aload_0
       1: getfield      #4                  // Field regionStates:Lorg/apache/hadoop/hbase/master/assignment/RegionStates;
       4: areturn

  public java.util.List<org.apache.hadoop.hbase.client.RegionInfo> getRegionsOnServer(org.apache.hadoop.hbase.ServerName);
    Code:
       0: aload_0
       1: getfield      #4                  // Field regionStates:Lorg/apache/hadoop/hbase/master/assignment/RegionStates;
       4: aload_1
       5: invokevirtual #101                // Method org/apache/hadoop/hbase/master/assignment/RegionStates.getServerNode:(Lorg/apache/hadoop/hbase/ServerName;)Lorg/apache/hadoop/hbase/master/assignment/ServerStateNode;
       8: astore_2
       9: aload_2
      10: ifnonnull     17
      13: invokestatic  #102                // Method java/util/Collections.emptyList:()Ljava/util/List;
      16: areturn
      17: aload_2
      18: invokevirtual #103                // Method org/apache/hadoop/hbase/master/assignment/ServerStateNode.getRegionInfoList:()Ljava/util/List;
      21: areturn

  public org.apache.hadoop.hbase.master.assignment.RegionStateStore getRegionStateStore();
    Code:
       0: aload_0
       1: getfield      #33                 // Field regionStateStore:Lorg/apache/hadoop/hbase/master/assignment/RegionStateStore;
       4: areturn

  public java.util.List<org.apache.hadoop.hbase.ServerName> getFavoredNodes(org.apache.hadoop.hbase.client.RegionInfo);
    Code:
       0: aload_0
       1: getfield      #43                 // Field shouldAssignRegionsWithFavoredNodes:Z
       4: ifeq          21
       7: aload_0
       8: invokespecial #104                // Method getBalancer:()Lorg/apache/hadoop/hbase/master/LoadBalancer;
      11: checkcast     #38                 // class org/apache/hadoop/hbase/master/balancer/FavoredStochasticBalancer
      14: aload_1
      15: invokevirtual #105                // Method org/apache/hadoop/hbase/master/balancer/FavoredStochasticBalancer.getFavoredNodes:(Lorg/apache/hadoop/hbase/client/RegionInfo;)Ljava/util/List;
      18: goto          24
      21: getstatic     #106                // Field org/apache/hadoop/hbase/ServerName.EMPTY_SERVER_LIST:Ljava/util/List;
      24: areturn

  org.apache.hadoop.hbase.master.TableStateManager getTableStateManager();
    Code:
       0: aload_0
       1: getfield      #32                 // Field master:Lorg/apache/hadoop/hbase/master/MasterServices;
       4: invokeinterface #107,  1          // InterfaceMethod org/apache/hadoop/hbase/master/MasterServices.getTableStateManager:()Lorg/apache/hadoop/hbase/master/TableStateManager;
       9: areturn

  public boolean isTableEnabled(org.apache.hadoop.hbase.TableName);
    Code:
       0: aload_0
       1: invokevirtual #108                // Method getTableStateManager:()Lorg/apache/hadoop/hbase/master/TableStateManager;
       4: aload_1
       5: iconst_1
       6: anewarray     #109                // class org/apache/hadoop/hbase/client/TableState$State
       9: dup
      10: iconst_0
      11: getstatic     #110                // Field org/apache/hadoop/hbase/client/TableState$State.ENABLED:Lorg/apache/hadoop/hbase/client/TableState$State;
      14: aastore
      15: invokevirtual #111                // Method org/apache/hadoop/hbase/master/TableStateManager.isTableState:(Lorg/apache/hadoop/hbase/TableName;[Lorg/apache/hadoop/hbase/client/TableState$State;)Z
      18: ireturn

  public boolean isTableDisabled(org.apache.hadoop.hbase.TableName);
    Code:
       0: aload_0
       1: invokevirtual #108                // Method getTableStateManager:()Lorg/apache/hadoop/hbase/master/TableStateManager;
       4: aload_1
       5: iconst_2
       6: anewarray     #109                // class org/apache/hadoop/hbase/client/TableState$State
       9: dup
      10: iconst_0
      11: getstatic     #112                // Field org/apache/hadoop/hbase/client/TableState$State.DISABLED:Lorg/apache/hadoop/hbase/client/TableState$State;
      14: aastore
      15: dup
      16: iconst_1
      17: getstatic     #113                // Field org/apache/hadoop/hbase/client/TableState$State.DISABLING:Lorg/apache/hadoop/hbase/client/TableState$State;
      20: aastore
      21: invokevirtual #111                // Method org/apache/hadoop/hbase/master/TableStateManager.isTableState:(Lorg/apache/hadoop/hbase/TableName;[Lorg/apache/hadoop/hbase/client/TableState$State;)Z
      24: ireturn

  public boolean isMetaRegion(byte[]);
    Code:
       0: aload_0
       1: aload_1
       2: invokevirtual #115                // Method getMetaRegionFromName:([B)Lorg/apache/hadoop/hbase/client/RegionInfo;
       5: ifnull        12
       8: iconst_1
       9: goto          13
      12: iconst_0
      13: ireturn

  public org.apache.hadoop.hbase.client.RegionInfo getMetaRegionFromName(byte[]);
    Code:
       0: aload_0
       1: invokevirtual #90                 // Method getMetaRegionSet:()Ljava/util/Set;
       4: invokeinterface #91,  1           // InterfaceMethod java/util/Set.iterator:()Ljava/util/Iterator;
       9: astore_2
      10: aload_2
      11: invokeinterface #92,  1           // InterfaceMethod java/util/Iterator.hasNext:()Z
      16: ifeq          47
      19: aload_2
      20: invokeinterface #93,  1           // InterfaceMethod java/util/Iterator.next:()Ljava/lang/Object;
      25: checkcast     #94                 // class org/apache/hadoop/hbase/client/RegionInfo
      28: astore_3
      29: aload_3
      30: invokeinterface #116,  1          // InterfaceMethod org/apache/hadoop/hbase/client/RegionInfo.getRegionName:()[B
      35: aload_1
      36: invokestatic  #117                // Method org/apache/hadoop/hbase/util/Bytes.equals:([B[B)Z
      39: ifeq          44
      42: aload_3
      43: areturn
      44: goto          10
      47: aconst_null
      48: areturn

  public boolean isCarryingMeta(org.apache.hadoop.hbase.ServerName);
    Code:
       0: aload_0
       1: aload_1
       2: getstatic     #67                 // Field org/apache/hadoop/hbase/client/RegionInfoBuilder.FIRST_META_REGIONINFO:Lorg/apache/hadoop/hbase/client/RegionInfo;
       5: invokespecial #118                // Method isCarryingRegion:(Lorg/apache/hadoop/hbase/ServerName;Lorg/apache/hadoop/hbase/client/RegionInfo;)Z
       8: ireturn

  public java.util.Set<org.apache.hadoop.hbase.client.RegionInfo> getMetaRegionSet();
    Code:
       0: getstatic     #122                // Field META_REGION_SET:Ljava/util/Set;
       3: areturn

  public boolean isMetaAssigned();
    Code:
       0: aload_0
       1: getfield      #15                 // Field metaAssignEvent:Lorg/apache/hadoop/hbase/procedure2/ProcedureEvent;
       4: invokevirtual #123                // Method org/apache/hadoop/hbase/procedure2/ProcedureEvent.isReady:()Z
       7: ireturn

  public boolean isMetaRegionInTransition();
    Code:
       0: aload_0
       1: invokevirtual #124                // Method isMetaAssigned:()Z
       4: ifne          11
       7: iconst_1
       8: goto          12
      11: iconst_0
      12: ireturn

  public boolean waitMetaAssigned(org.apache.hadoop.hbase.procedure2.Procedure<?>, org.apache.hadoop.hbase.client.RegionInfo);
    Code:
       0: aload_0
       1: aload_0
       2: aload_2
       3: invokespecial #125                // Method getMetaForRegion:(Lorg/apache/hadoop/hbase/client/RegionInfo;)Lorg/apache/hadoop/hbase/client/RegionInfo;
       6: invokespecial #126                // Method getMetaAssignEvent:(Lorg/apache/hadoop/hbase/client/RegionInfo;)Lorg/apache/hadoop/hbase/procedure2/ProcedureEvent;
       9: aload_1
      10: invokevirtual #127                // Method org/apache/hadoop/hbase/procedure2/ProcedureEvent.suspendIfNotReady:(Lorg/apache/hadoop/hbase/procedure2/Procedure;)Z
      13: ireturn

  public boolean waitMetaLoaded(org.apache.hadoop.hbase.procedure2.Procedure<?>);
    Code:
       0: aload_0
       1: getfield      #17                 // Field metaLoadEvent:Lorg/apache/hadoop/hbase/procedure2/ProcedureEvent;
       4: aload_1
       5: invokevirtual #127                // Method org/apache/hadoop/hbase/procedure2/ProcedureEvent.suspendIfNotReady:(Lorg/apache/hadoop/hbase/procedure2/Procedure;)Z
       8: ireturn

  void wakeMetaLoadedEvent();
    Code:
       0: aload_0
       1: getfield      #17                 // Field metaLoadEvent:Lorg/apache/hadoop/hbase/procedure2/ProcedureEvent;
       4: aload_0
       5: invokespecial #138                // Method getProcedureScheduler:()Lorg/apache/hadoop/hbase/master/procedure/MasterProcedureScheduler;
       8: invokevirtual #139                // Method org/apache/hadoop/hbase/procedure2/ProcedureEvent.wake:(Lorg/apache/hadoop/hbase/procedure2/AbstractProcedureScheduler;)V
      11: getstatic     #128                // Field $assertionsDisabled:Z
      14: ifne          34
      17: aload_0
      18: invokevirtual #140                // Method isMetaLoaded:()Z
      21: ifne          34
      24: new           #130                // class java/lang/AssertionError
      27: dup
      28: ldc           #141                // String expected meta to be loaded
      30: invokespecial #137                // Method java/lang/AssertionError."<init>":(Ljava/lang/Object;)V
      33: athrow
      34: return

  public boolean isMetaLoaded();
    Code:
       0: aload_0
       1: getfield      #17                 // Field metaLoadEvent:Lorg/apache/hadoop/hbase/procedure2/ProcedureEvent;
       4: invokevirtual #123                // Method org/apache/hadoop/hbase/procedure2/ProcedureEvent.isReady:()Z
       7: ireturn

  public void checkIfShouldMoveSystemRegionAsync();
    Code:
       0: aload_0
       1: getfield      #32                 // Field master:Lorg/apache/hadoop/hbase/master/MasterServices;
       4: invokeinterface #142,  1          // InterfaceMethod org/apache/hadoop/hbase/master/MasterServices.getServerManager:()Lorg/apache/hadoop/hbase/master/ServerManager;
       9: invokevirtual #143                // Method org/apache/hadoop/hbase/master/ServerManager.countOfRegionServers:()I
      12: iconst_1
      13: if_icmpgt     17
      16: return
      17: new           #144                // class java/lang/Thread
      20: dup
      21: aload_0
      22: invokedynamic #145,  0            // InvokeDynamic #1:run:(Lorg/apache/hadoop/hbase/master/assignment/AssignmentManager;)Ljava/lang/Runnable;
      27: invokespecial #146                // Method java/lang/Thread."<init>":(Ljava/lang/Runnable;)V
      30: invokevirtual #147                // Method java/lang/Thread.start:()V
      33: return

  public long assign(org.apache.hadoop.hbase.client.RegionInfo, org.apache.hadoop.hbase.ServerName) throws java.io.IOException;
    Code:
       0: aload_0
       1: getfield      #4                  // Field regionStates:Lorg/apache/hadoop/hbase/master/assignment/RegionStates;
       4: aload_1
       5: invokevirtual #68                 // Method org/apache/hadoop/hbase/master/assignment/RegionStates.getOrCreateRegionStateNode:(Lorg/apache/hadoop/hbase/client/RegionInfo;)Lorg/apache/hadoop/hbase/master/assignment/RegionStateNode;
       8: astore_3
       9: aload_3
      10: invokevirtual #69                 // Method org/apache/hadoop/hbase/master/assignment/RegionStateNode.lock:()V
      13: aload_0
      14: aload_3
      15: getstatic     #160                // Field STATES_EXPECTED_ON_ASSIGN:[Lorg/apache/hadoop/hbase/master/RegionState$State;
      18: invokespecial #161                // Method preTransitCheck:(Lorg/apache/hadoop/hbase/master/assignment/RegionStateNode;[Lorg/apache/hadoop/hbase/master/RegionState$State;)V
      21: aload_0
      22: invokespecial #99                 // Method getProcedureEnvironment:()Lorg/apache/hadoop/hbase/master/procedure/MasterProcedureEnv;
      25: aload_1
      26: aload_2
      27: invokestatic  #162                // Method org/apache/hadoop/hbase/master/assignment/TransitRegionStateProcedure.assign:(Lorg/apache/hadoop/hbase/master/procedure/MasterProcedureEnv;Lorg/apache/hadoop/hbase/client/RegionInfo;Lorg/apache/hadoop/hbase/ServerName;)Lorg/apache/hadoop/hbase/master/assignment/TransitRegionStateProcedure;
      30: astore        4
      32: aload_3
      33: aload         4
      35: invokevirtual #163                // Method org/apache/hadoop/hbase/master/assignment/RegionStateNode.setProcedure:(Lorg/apache/hadoop/hbase/master/assignment/TransitRegionStateProcedure;)V
      38: aload_3
      39: invokevirtual #80                 // Method org/apache/hadoop/hbase/master/assignment/RegionStateNode.unlock:()V
      42: goto          54
      45: astore        5
      47: aload_3
      48: invokevirtual #80                 // Method org/apache/hadoop/hbase/master/assignment/RegionStateNode.unlock:()V
      51: aload         5
      53: athrow
      54: aload_0
      55: getfield      #32                 // Field master:Lorg/apache/hadoop/hbase/master/MasterServices;
      58: invokeinterface #85,  1           // InterfaceMethod org/apache/hadoop/hbase/master/MasterServices.getMasterProcedureExecutor:()Lorg/apache/hadoop/hbase/procedure2/ProcedureExecutor;
      63: aload         4
      65: invokestatic  #164                // Method org/apache/hadoop/hbase/master/procedure/ProcedureSyncWait.submitAndWaitProcedure:(Lorg/apache/hadoop/hbase/procedure2/ProcedureExecutor;Lorg/apache/hadoop/hbase/procedure2/Procedure;)[B
      68: pop
      69: aload         4
      71: invokevirtual #165                // Method org/apache/hadoop/hbase/master/assignment/TransitRegionStateProcedure.getProcId:()J
      74: lreturn
    Exception table:
       from    to  target type
          13    38    45   any
          45    47    45   any

  public long assign(org.apache.hadoop.hbase.client.RegionInfo) throws java.io.IOException;
    Code:
       0: aload_0
       1: aload_1
       2: aconst_null
       3: invokevirtual #166                // Method assign:(Lorg/apache/hadoop/hbase/client/RegionInfo;Lorg/apache/hadoop/hbase/ServerName;)J
       6: lreturn

  public long unassign(org.apache.hadoop.hbase.client.RegionInfo) throws java.io.IOException;
    Code:
       0: aload_0
       1: getfield      #4                  // Field regionStates:Lorg/apache/hadoop/hbase/master/assignment/RegionStates;
       4: aload_1
       5: invokevirtual #119                // Method org/apache/hadoop/hbase/master/assignment/RegionStates.getRegionStateNode:(Lorg/apache/hadoop/hbase/client/RegionInfo;)Lorg/apache/hadoop/hbase/master/assignment/RegionStateNode;
       8: astore_2
       9: aload_2
      10: ifnonnull     45
      13: new           #167                // class org/apache/hadoop/hbase/UnknownRegionException
      16: dup
      17: new           #131                // class java/lang/StringBuilder
      20: dup
      21: invokespecial #132                // Method java/lang/StringBuilder."<init>":()V
      24: ldc           #168                // String No RegionState found for
      26: invokevirtual #134                // Method java/lang/StringBuilder.append:(Ljava/lang/String;)Ljava/lang/StringBuilder;
      29: aload_1
      30: invokeinterface #169,  1          // InterfaceMethod org/apache/hadoop/hbase/client/RegionInfo.getEncodedName:()Ljava/lang/String;
      35: invokevirtual #134                // Method java/lang/StringBuilder.append:(Ljava/lang/String;)Ljava/lang/StringBuilder;
      38: invokevirtual #136                // Method java/lang/StringBuilder.toString:()Ljava/lang/String;
      41: invokespecial #170                // Method org/apache/hadoop/hbase/UnknownRegionException."<init>":(Ljava/lang/String;)V
      44: athrow
      45: aload_2
      46: invokevirtual #69                 // Method org/apache/hadoop/hbase/master/assignment/RegionStateNode.lock:()V
      49: aload_0
      50: aload_2
      51: getstatic     #171                // Field STATES_EXPECTED_ON_UNASSIGN_OR_MOVE:[Lorg/apache/hadoop/hbase/master/RegionState$State;
      54: invokespecial #161                // Method preTransitCheck:(Lorg/apache/hadoop/hbase/master/assignment/RegionStateNode;[Lorg/apache/hadoop/hbase/master/RegionState$State;)V
      57: aload_0
      58: invokespecial #99                 // Method getProcedureEnvironment:()Lorg/apache/hadoop/hbase/master/procedure/MasterProcedureEnv;
      61: aload_1
      62: invokestatic  #172                // Method org/apache/hadoop/hbase/master/assignment/TransitRegionStateProcedure.unassign:(Lorg/apache/hadoop/hbase/master/procedure/MasterProcedureEnv;Lorg/apache/hadoop/hbase/client/RegionInfo;)Lorg/apache/hadoop/hbase/master/assignment/TransitRegionStateProcedure;
      65: astore_3
      66: aload_2
      67: aload_3
      68: invokevirtual #163                // Method org/apache/hadoop/hbase/master/assignment/RegionStateNode.setProcedure:(Lorg/apache/hadoop/hbase/master/assignment/TransitRegionStateProcedure;)V
      71: aload_2
      72: invokevirtual #80                 // Method org/apache/hadoop/hbase/master/assignment/RegionStateNode.unlock:()V
      75: goto          87
      78: astore        4
      80: aload_2
      81: invokevirtual #80                 // Method org/apache/hadoop/hbase/master/assignment/RegionStateNode.unlock:()V
      84: aload         4
      86: athrow
      87: aload_0
      88: getfield      #32                 // Field master:Lorg/apache/hadoop/hbase/master/MasterServices;
      91: invokeinterface #85,  1           // InterfaceMethod org/apache/hadoop/hbase/master/MasterServices.getMasterProcedureExecutor:()Lorg/apache/hadoop/hbase/procedure2/ProcedureExecutor;
      96: aload_3
      97: invokestatic  #164                // Method org/apache/hadoop/hbase/master/procedure/ProcedureSyncWait.submitAndWaitProcedure:(Lorg/apache/hadoop/hbase/procedure2/ProcedureExecutor;Lorg/apache/hadoop/hbase/procedure2/Procedure;)[B
     100: pop
     101: aload_3
     102: invokevirtual #165                // Method org/apache/hadoop/hbase/master/assignment/TransitRegionStateProcedure.getProcId:()J
     105: lreturn
    Exception table:
       from    to  target type
          49    71    78   any
          78    80    78   any

  public org.apache.hadoop.hbase.master.assignment.TransitRegionStateProcedure createMoveRegionProcedure(org.apache.hadoop.hbase.client.RegionInfo, org.apache.hadoop.hbase.ServerName) throws org.apache.hadoop.hbase.HBaseIOException;
    Code:
       0: aload_0
       1: getfield      #4                  // Field regionStates:Lorg/apache/hadoop/hbase/master/assignment/RegionStates;
       4: aload_1
       5: invokevirtual #119                // Method org/apache/hadoop/hbase/master/assignment/RegionStates.getRegionStateNode:(Lorg/apache/hadoop/hbase/client/RegionInfo;)Lorg/apache/hadoop/hbase/master/assignment/RegionStateNode;
       8: astore_3
       9: aload_3
      10: ifnonnull     45
      13: new           #167                // class org/apache/hadoop/hbase/UnknownRegionException
      16: dup
      17: new           #131                // class java/lang/StringBuilder
      20: dup
      21: invokespecial #132                // Method java/lang/StringBuilder."<init>":()V
      24: ldc           #168                // String No RegionState found for
      26: invokevirtual #134                // Method java/lang/StringBuilder.append:(Ljava/lang/String;)Ljava/lang/StringBuilder;
      29: aload_1
      30: invokeinterface #169,  1          // InterfaceMethod org/apache/hadoop/hbase/client/RegionInfo.getEncodedName:()Ljava/lang/String;
      35: invokevirtual #134                // Method java/lang/StringBuilder.append:(Ljava/lang/String;)Ljava/lang/StringBuilder;
      38: invokevirtual #136                // Method java/lang/StringBuilder.toString:()Ljava/lang/String;
      41: invokespecial #170                // Method org/apache/hadoop/hbase/UnknownRegionException."<init>":(Ljava/lang/String;)V
      44: athrow
      45: aload_3
      46: invokevirtual #69                 // Method org/apache/hadoop/hbase/master/assignment/RegionStateNode.lock:()V
      49: aload_0
      50: aload_3
      51: getstatic     #171                // Field STATES_EXPECTED_ON_UNASSIGN_OR_MOVE:[Lorg/apache/hadoop/hbase/master/RegionState$State;
      54: invokespecial #161                // Method preTransitCheck:(Lorg/apache/hadoop/hbase/master/assignment/RegionStateNode;[Lorg/apache/hadoop/hbase/master/RegionState$State;)V
      57: aload_3
      58: invokevirtual #173                // Method org/apache/hadoop/hbase/master/assignment/RegionStateNode.checkOnline:()V
      61: aload_0
      62: invokespecial #99                 // Method getProcedureEnvironment:()Lorg/apache/hadoop/hbase/master/procedure/MasterProcedureEnv;
      65: aload_1
      66: aload_2
      67: invokestatic  #174                // Method org/apache/hadoop/hbase/master/assignment/TransitRegionStateProcedure.move:(Lorg/apache/hadoop/hbase/master/procedure/MasterProcedureEnv;Lorg/apache/hadoop/hbase/client/RegionInfo;Lorg/apache/hadoop/hbase/ServerName;)Lorg/apache/hadoop/hbase/master/assignment/TransitRegionStateProcedure;
      70: astore        4
      72: aload_3
      73: aload         4
      75: invokevirtual #163                // Method org/apache/hadoop/hbase/master/assignment/RegionStateNode.setProcedure:(Lorg/apache/hadoop/hbase/master/assignment/TransitRegionStateProcedure;)V
      78: aload_3
      79: invokevirtual #80                 // Method org/apache/hadoop/hbase/master/assignment/RegionStateNode.unlock:()V
      82: goto          94
      85: astore        5
      87: aload_3
      88: invokevirtual #80                 // Method org/apache/hadoop/hbase/master/assignment/RegionStateNode.unlock:()V
      91: aload         5
      93: athrow
      94: aload         4
      96: areturn
    Exception table:
       from    to  target type
          49    78    85   any
          85    87    85   any

  public void move(org.apache.hadoop.hbase.client.RegionInfo) throws java.io.IOException;
    Code:
       0: aload_0
       1: aload_1
       2: aconst_null
       3: invokevirtual #175                // Method createMoveRegionProcedure:(Lorg/apache/hadoop/hbase/client/RegionInfo;Lorg/apache/hadoop/hbase/ServerName;)Lorg/apache/hadoop/hbase/master/assignment/TransitRegionStateProcedure;
       6: astore_2
       7: aload_0
       8: getfield      #32                 // Field master:Lorg/apache/hadoop/hbase/master/MasterServices;
      11: invokeinterface #85,  1           // InterfaceMethod org/apache/hadoop/hbase/master/MasterServices.getMasterProcedureExecutor:()Lorg/apache/hadoop/hbase/procedure2/ProcedureExecutor;
      16: aload_2
      17: invokestatic  #164                // Method org/apache/hadoop/hbase/master/procedure/ProcedureSyncWait.submitAndWaitProcedure:(Lorg/apache/hadoop/hbase/procedure2/ProcedureExecutor;Lorg/apache/hadoop/hbase/procedure2/Procedure;)[B
      20: pop
      21: return

  public java.util.concurrent.Future<byte[]> moveAsync(org.apache.hadoop.hbase.master.RegionPlan) throws org.apache.hadoop.hbase.HBaseIOException;
    Code:
       0: aload_0
       1: aload_1
       2: invokevirtual #176                // Method org/apache/hadoop/hbase/master/RegionPlan.getRegionInfo:()Lorg/apache/hadoop/hbase/client/RegionInfo;
       5: aload_1
       6: invokevirtual #177                // Method org/apache/hadoop/hbase/master/RegionPlan.getDestination:()Lorg/apache/hadoop/hbase/ServerName;
       9: invokevirtual #175                // Method createMoveRegionProcedure:(Lorg/apache/hadoop/hbase/client/RegionInfo;Lorg/apache/hadoop/hbase/ServerName;)Lorg/apache/hadoop/hbase/master/assignment/TransitRegionStateProcedure;
      12: astore_2
      13: aload_0
      14: getfield      #32                 // Field master:Lorg/apache/hadoop/hbase/master/MasterServices;
      17: invokeinterface #85,  1           // InterfaceMethod org/apache/hadoop/hbase/master/MasterServices.getMasterProcedureExecutor:()Lorg/apache/hadoop/hbase/procedure2/ProcedureExecutor;
      22: aload_2
      23: invokestatic  #178                // Method org/apache/hadoop/hbase/master/procedure/ProcedureSyncWait.submitProcedure:(Lorg/apache/hadoop/hbase/procedure2/ProcedureExecutor;Lorg/apache/hadoop/hbase/procedure2/Procedure;)Ljava/util/concurrent/Future;
      26: areturn

  public org.apache.hadoop.hbase.master.assignment.TransitRegionStateProcedure[] createRoundRobinAssignProcedures(java.util.List<org.apache.hadoop.hbase.client.RegionInfo>, java.util.List<org.apache.hadoop.hbase.ServerName>);
    Code:
       0: aload_1
       1: invokeinterface #179,  1          // InterfaceMethod java/util/List.isEmpty:()Z
       6: ifeq          14
       9: iconst_0
      10: anewarray     #180                // class org/apache/hadoop/hbase/master/assignment/TransitRegionStateProcedure
      13: areturn
      14: aload_2
      15: ifnull        51
      18: aload_0
      19: getfield      #32                 // Field master:Lorg/apache/hadoop/hbase/master/MasterServices;
      22: invokeinterface #142,  1          // InterfaceMethod org/apache/hadoop/hbase/master/MasterServices.getServerManager:()Lorg/apache/hadoop/hbase/master/ServerManager;
      27: invokevirtual #181                // Method org/apache/hadoop/hbase/master/ServerManager.getOnlineServersList:()Ljava/util/List;
      30: invokeinterface #182,  1          // InterfaceMethod java/util/List.size:()I
      35: iconst_1
      36: if_icmpne     51
      39: getstatic     #5                  // Field LOG:Lorg/slf4j/Logger;
      42: ldc           #183                // String Only one region server found and hence going ahead with the assignment
      44: invokeinterface #184,  2          // InterfaceMethod org/slf4j/Logger.debug:(Ljava/lang/String;)V
      49: aconst_null
      50: astore_2
      51: aload_0
      52: invokespecial #104                // Method getBalancer:()Lorg/apache/hadoop/hbase/master/LoadBalancer;
      55: aload_1
      56: aload_0
      57: getfield      #32                 // Field master:Lorg/apache/hadoop/hbase/master/MasterServices;
      60: invokeinterface #142,  1          // InterfaceMethod org/apache/hadoop/hbase/master/MasterServices.getServerManager:()Lorg/apache/hadoop/hbase/master/ServerManager;
      65: aload_2
      66: invokevirtual #185                // Method org/apache/hadoop/hbase/master/ServerManager.createDestinationServersList:(Ljava/util/List;)Ljava/util/List;
      69: invokeinterface #186,  3          // InterfaceMethod org/apache/hadoop/hbase/master/LoadBalancer.roundRobinAssignment:(Ljava/util/List;Ljava/util/List;)Ljava/util/Map;
      74: astore_3
      75: aload_0
      76: aload_3
      77: invokespecial #187                // Method createAssignProcedures:(Ljava/util/Map;)[Lorg/apache/hadoop/hbase/master/assignment/TransitRegionStateProcedure;
      80: areturn
      81: astore_3
      82: getstatic     #5                  // Field LOG:Lorg/slf4j/Logger;
      85: ldc           #188                // String Failed roundRobinAssignment
      87: aload_3
      88: invokeinterface #189,  3          // InterfaceMethod org/slf4j/Logger.warn:(Ljava/lang/String;Ljava/lang/Throwable;)V
      93: aload_0
      94: aload_1
      95: invokevirtual #190                // Method createAssignProcedures:(Ljava/util/List;)[Lorg/apache/hadoop/hbase/master/assignment/TransitRegionStateProcedure;
      98: areturn
    Exception table:
       from    to  target type
          51    80    81   Class org/apache/hadoop/hbase/HBaseIOException

  public org.apache.hadoop.hbase.master.assignment.TransitRegionStateProcedure[] createRoundRobinAssignProcedures(java.util.List<org.apache.hadoop.hbase.client.RegionInfo>);
    Code:
       0: aload_0
       1: aload_1
       2: aconst_null
       3: invokevirtual #191                // Method createRoundRobinAssignProcedures:(Ljava/util/List;Ljava/util/List;)[Lorg/apache/hadoop/hbase/master/assignment/TransitRegionStateProcedure;
       6: areturn

  static int compare(org.apache.hadoop.hbase.master.assignment.TransitRegionStateProcedure, org.apache.hadoop.hbase.master.assignment.TransitRegionStateProcedure);
    Code:
       0: aload_0
       1: invokevirtual #192                // Method org/apache/hadoop/hbase/master/assignment/TransitRegionStateProcedure.getRegion:()Lorg/apache/hadoop/hbase/client/RegionInfo;
       4: invokeinterface #114,  1          // InterfaceMethod org/apache/hadoop/hbase/client/RegionInfo.isMetaRegion:()Z
       9: ifeq          43
      12: aload_1
      13: invokevirtual #192                // Method org/apache/hadoop/hbase/master/assignment/TransitRegionStateProcedure.getRegion:()Lorg/apache/hadoop/hbase/client/RegionInfo;
      16: invokeinterface #114,  1          // InterfaceMethod org/apache/hadoop/hbase/client/RegionInfo.isMetaRegion:()Z
      21: ifeq          41
      24: getstatic     #193                // Field org/apache/hadoop/hbase/client/RegionInfo.COMPARATOR:Ljava/util/Comparator;
      27: aload_0
      28: invokevirtual #192                // Method org/apache/hadoop/hbase/master/assignment/TransitRegionStateProcedure.getRegion:()Lorg/apache/hadoop/hbase/client/RegionInfo;
      31: aload_1
      32: invokevirtual #192                // Method org/apache/hadoop/hbase/master/assignment/TransitRegionStateProcedure.getRegion:()Lorg/apache/hadoop/hbase/client/RegionInfo;
      35: invokeinterface #194,  3          // InterfaceMethod java/util/Comparator.compare:(Ljava/lang/Object;Ljava/lang/Object;)I
      40: ireturn
      41: iconst_m1
      42: ireturn
      43: aload_1
      44: invokevirtual #192                // Method org/apache/hadoop/hbase/master/assignment/TransitRegionStateProcedure.getRegion:()Lorg/apache/hadoop/hbase/client/RegionInfo;
      47: invokeinterface #114,  1          // InterfaceMethod org/apache/hadoop/hbase/client/RegionInfo.isMetaRegion:()Z
      52: ifeq          57
      55: iconst_1
      56: ireturn
      57: aload_0
      58: invokevirtual #192                // Method org/apache/hadoop/hbase/master/assignment/TransitRegionStateProcedure.getRegion:()Lorg/apache/hadoop/hbase/client/RegionInfo;
      61: invokeinterface #195,  1          // InterfaceMethod org/apache/hadoop/hbase/client/RegionInfo.getTable:()Lorg/apache/hadoop/hbase/TableName;
      66: invokevirtual #196                // Method org/apache/hadoop/hbase/TableName.isSystemTable:()Z
      69: ifeq          106
      72: aload_1
      73: invokevirtual #192                // Method org/apache/hadoop/hbase/master/assignment/TransitRegionStateProcedure.getRegion:()Lorg/apache/hadoop/hbase/client/RegionInfo;
      76: invokeinterface #195,  1          // InterfaceMethod org/apache/hadoop/hbase/client/RegionInfo.getTable:()Lorg/apache/hadoop/hbase/TableName;
      81: invokevirtual #196                // Method org/apache/hadoop/hbase/TableName.isSystemTable:()Z
      84: ifeq          104
      87: getstatic     #193                // Field org/apache/hadoop/hbase/client/RegionInfo.COMPARATOR:Ljava/util/Comparator;
      90: aload_0
      91: invokevirtual #192                // Method org/apache/hadoop/hbase/master/assignment/TransitRegionStateProcedure.getRegion:()Lorg/apache/hadoop/hbase/client/RegionInfo;
      94: aload_1
      95: invokevirtual #192                // Method org/apache/hadoop/hbase/master/assignment/TransitRegionStateProcedure.getRegion:()Lorg/apache/hadoop/hbase/client/RegionInfo;
      98: invokeinterface #194,  3          // InterfaceMethod java/util/Comparator.compare:(Ljava/lang/Object;Ljava/lang/Object;)I
     103: ireturn
     104: iconst_m1
     105: ireturn
     106: aload_1
     107: invokevirtual #192                // Method org/apache/hadoop/hbase/master/assignment/TransitRegionStateProcedure.getRegion:()Lorg/apache/hadoop/hbase/client/RegionInfo;
     110: invokeinterface #195,  1          // InterfaceMethod org/apache/hadoop/hbase/client/RegionInfo.getTable:()Lorg/apache/hadoop/hbase/TableName;
     115: invokevirtual #196                // Method org/apache/hadoop/hbase/TableName.isSystemTable:()Z
     118: ifeq          123
     121: iconst_1
     122: ireturn
     123: getstatic     #193                // Field org/apache/hadoop/hbase/client/RegionInfo.COMPARATOR:Ljava/util/Comparator;
     126: aload_0
     127: invokevirtual #192                // Method org/apache/hadoop/hbase/master/assignment/TransitRegionStateProcedure.getRegion:()Lorg/apache/hadoop/hbase/client/RegionInfo;
     130: aload_1
     131: invokevirtual #192                // Method org/apache/hadoop/hbase/master/assignment/TransitRegionStateProcedure.getRegion:()Lorg/apache/hadoop/hbase/client/RegionInfo;
     134: invokeinterface #194,  3          // InterfaceMethod java/util/Comparator.compare:(Ljava/lang/Object;Ljava/lang/Object;)I
     139: ireturn

  public org.apache.hadoop.hbase.master.assignment.TransitRegionStateProcedure createOneAssignProcedure(org.apache.hadoop.hbase.client.RegionInfo, boolean);
    Code:
       0: aload_0
       1: getfield      #4                  // Field regionStates:Lorg/apache/hadoop/hbase/master/assignment/RegionStates;
       4: aload_1
       5: invokevirtual #68                 // Method org/apache/hadoop/hbase/master/assignment/RegionStates.getOrCreateRegionStateNode:(Lorg/apache/hadoop/hbase/client/RegionInfo;)Lorg/apache/hadoop/hbase/master/assignment/RegionStateNode;
       8: astore_3
       9: aload_0
      10: aload_3
      11: aconst_null
      12: iload_2
      13: invokespecial #200                // Method createAssignProcedure:(Lorg/apache/hadoop/hbase/master/assignment/RegionStateNode;Lorg/apache/hadoop/hbase/ServerName;Z)Lorg/apache/hadoop/hbase/master/assignment/TransitRegionStateProcedure;
      16: areturn

  public org.apache.hadoop.hbase.master.assignment.TransitRegionStateProcedure createOneUnassignProcedure(org.apache.hadoop.hbase.client.RegionInfo, boolean);
    Code:
       0: aload_0
       1: getfield      #4                  // Field regionStates:Lorg/apache/hadoop/hbase/master/assignment/RegionStates;
       4: aload_1
       5: invokevirtual #68                 // Method org/apache/hadoop/hbase/master/assignment/RegionStates.getOrCreateRegionStateNode:(Lorg/apache/hadoop/hbase/client/RegionInfo;)Lorg/apache/hadoop/hbase/master/assignment/RegionStateNode;
       8: astore_3
       9: aload_0
      10: aload_3
      11: iload_2
      12: invokespecial #201                // Method createUnassignProcedure:(Lorg/apache/hadoop/hbase/master/assignment/RegionStateNode;Z)Lorg/apache/hadoop/hbase/master/assignment/TransitRegionStateProcedure;
      15: areturn

  public org.apache.hadoop.hbase.master.assignment.TransitRegionStateProcedure[] createAssignProcedures(java.util.List<org.apache.hadoop.hbase.client.RegionInfo>);
    Code:
       0: aload_1
       1: invokeinterface #202,  1          // InterfaceMethod java/util/List.stream:()Ljava/util/stream/Stream;
       6: aload_0
       7: invokedynamic #203,  0            // InvokeDynamic #2:apply:(Lorg/apache/hadoop/hbase/master/assignment/AssignmentManager;)Ljava/util/function/Function;
      12: invokeinterface #204,  2          // InterfaceMethod java/util/stream/Stream.map:(Ljava/util/function/Function;)Ljava/util/stream/Stream;
      17: aload_0
      18: invokedynamic #205,  0            // InvokeDynamic #3:apply:(Lorg/apache/hadoop/hbase/master/assignment/AssignmentManager;)Ljava/util/function/Function;
      23: invokeinterface #204,  2          // InterfaceMethod java/util/stream/Stream.map:(Ljava/util/function/Function;)Ljava/util/stream/Stream;
      28: invokedynamic #206,  0            // InvokeDynamic #4:compare:()Ljava/util/Comparator;
      33: invokeinterface #207,  2          // InterfaceMethod java/util/stream/Stream.sorted:(Ljava/util/Comparator;)Ljava/util/stream/Stream;
      38: invokedynamic #208,  0            // InvokeDynamic #5:apply:()Ljava/util/function/IntFunction;
      43: invokeinterface #209,  2          // InterfaceMethod java/util/stream/Stream.toArray:(Ljava/util/function/IntFunction;)[Ljava/lang/Object;
      48: checkcast     #210                // class "[Lorg/apache/hadoop/hbase/master/assignment/TransitRegionStateProcedure;"
      51: areturn

  public org.apache.hadoop.hbase.master.assignment.TransitRegionStateProcedure[] createUnassignProceduresForDisabling(org.apache.hadoop.hbase.TableName);
    Code:
       0: aload_0
       1: getfield      #4                  // Field regionStates:Lorg/apache/hadoop/hbase/master/assignment/RegionStates;
       4: aload_1
       5: invokevirtual #216                // Method org/apache/hadoop/hbase/master/assignment/RegionStates.getTableRegionStateNodes:(Lorg/apache/hadoop/hbase/TableName;)Ljava/util/ArrayList;
       8: invokevirtual #217                // Method java/util/ArrayList.stream:()Ljava/util/stream/Stream;
      11: aload_0
      12: invokedynamic #218,  0            // InvokeDynamic #8:apply:(Lorg/apache/hadoop/hbase/master/assignment/AssignmentManager;)Ljava/util/function/Function;
      17: invokeinterface #204,  2          // InterfaceMethod java/util/stream/Stream.map:(Ljava/util/function/Function;)Ljava/util/stream/Stream;
      22: invokedynamic #219,  0            // InvokeDynamic #9:test:()Ljava/util/function/Predicate;
      27: invokeinterface #220,  2          // InterfaceMethod java/util/stream/Stream.filter:(Ljava/util/function/Predicate;)Ljava/util/stream/Stream;
      32: invokedynamic #221,  0            // InvokeDynamic #10:apply:()Ljava/util/function/IntFunction;
      37: invokeinterface #209,  2          // InterfaceMethod java/util/stream/Stream.toArray:(Ljava/util/function/IntFunction;)[Ljava/lang/Object;
      42: checkcast     #210                // class "[Lorg/apache/hadoop/hbase/master/assignment/TransitRegionStateProcedure;"
      45: areturn

  public org.apache.hadoop.hbase.master.assignment.SplitTableRegionProcedure createSplitProcedure(org.apache.hadoop.hbase.client.RegionInfo, byte[]) throws java.io.IOException;
    Code:
       0: new           #222                // class org/apache/hadoop/hbase/master/assignment/SplitTableRegionProcedure
       3: dup
       4: aload_0
       5: invokespecial #99                 // Method getProcedureEnvironment:()Lorg/apache/hadoop/hbase/master/procedure/MasterProcedureEnv;
       8: aload_1
       9: aload_2
      10: invokespecial #223                // Method org/apache/hadoop/hbase/master/assignment/SplitTableRegionProcedure."<init>":(Lorg/apache/hadoop/hbase/master/procedure/MasterProcedureEnv;Lorg/apache/hadoop/hbase/client/RegionInfo;[B)V
      13: areturn

  public org.apache.hadoop.hbase.master.assignment.MergeTableRegionsProcedure createMergeProcedure(org.apache.hadoop.hbase.client.RegionInfo, org.apache.hadoop.hbase.client.RegionInfo) throws java.io.IOException;
    Code:
       0: new           #224                // class org/apache/hadoop/hbase/master/assignment/MergeTableRegionsProcedure
       3: dup
       4: aload_0
       5: invokespecial #99                 // Method getProcedureEnvironment:()Lorg/apache/hadoop/hbase/master/procedure/MasterProcedureEnv;
       8: aload_1
       9: aload_2
      10: invokespecial #225                // Method org/apache/hadoop/hbase/master/assignment/MergeTableRegionsProcedure."<init>":(Lorg/apache/hadoop/hbase/master/procedure/MasterProcedureEnv;Lorg/apache/hadoop/hbase/client/RegionInfo;Lorg/apache/hadoop/hbase/client/RegionInfo;)V
      13: areturn

  public void deleteTable(org.apache.hadoop.hbase.TableName) throws java.io.IOException;
    Code:
       0: aload_0
       1: getfield      #4                  // Field regionStates:Lorg/apache/hadoop/hbase/master/assignment/RegionStates;
       4: aload_1
       5: invokevirtual #226                // Method org/apache/hadoop/hbase/master/assignment/RegionStates.getTableRegionsInfo:(Lorg/apache/hadoop/hbase/TableName;)Ljava/util/ArrayList;
       8: astore_2
       9: aload_0
      10: getfield      #33                 // Field regionStateStore:Lorg/apache/hadoop/hbase/master/assignment/RegionStateStore;
      13: aload_2
      14: invokevirtual #227                // Method org/apache/hadoop/hbase/master/assignment/RegionStateStore.deleteRegions:(Ljava/util/List;)V
      17: iconst_0
      18: istore_3
      19: iload_3
      20: aload_2
      21: invokevirtual #228                // Method java/util/ArrayList.size:()I
      24: if_icmpge     61
      27: aload_2
      28: iload_3
      29: invokevirtual #229                // Method java/util/ArrayList.get:(I)Ljava/lang/Object;
      32: checkcast     #94                 // class org/apache/hadoop/hbase/client/RegionInfo
      35: astore        4
      37: aload_0
      38: getfield      #4                  // Field regionStates:Lorg/apache/hadoop/hbase/master/assignment/RegionStates;
      41: aload         4
      43: invokevirtual #230                // Method org/apache/hadoop/hbase/master/assignment/RegionStates.removeFromOfflineRegions:(Lorg/apache/hadoop/hbase/client/RegionInfo;)V
      46: aload_0
      47: getfield      #4                  // Field regionStates:Lorg/apache/hadoop/hbase/master/assignment/RegionStates;
      50: aload         4
      52: invokevirtual #231                // Method org/apache/hadoop/hbase/master/assignment/RegionStates.deleteRegion:(Lorg/apache/hadoop/hbase/client/RegionInfo;)V
      55: iinc          3, 1
      58: goto          19
      61: return

  public org.apache.hadoop.hbase.shaded.protobuf.generated.RegionServerStatusProtos$ReportRegionStateTransitionResponse reportRegionStateTransition(org.apache.hadoop.hbase.shaded.protobuf.generated.RegionServerStatusProtos$ReportRegionStateTransitionRequest) throws org.apache.hadoop.hbase.PleaseHoldException;
    Code:
       0: invokestatic  #250                // Method org/apache/hadoop/hbase/shaded/protobuf/generated/RegionServerStatusProtos$ReportRegionStateTransitionResponse.newBuilder:()Lorg/apache/hadoop/hbase/shaded/protobuf/generated/RegionServerStatusProtos$ReportRegionStateTransitionResponse$Builder;
       3: astore_2
       4: aload_1
       5: invokevirtual #251                // Method org/apache/hadoop/hbase/shaded/protobuf/generated/RegionServerStatusProtos$ReportRegionStateTransitionRequest.getServer:()Lorg/apache/hadoop/hbase/shaded/protobuf/generated/HBaseProtos$ServerName;
       8: invokestatic  #252                // Method org/apache/hadoop/hbase/shaded/protobuf/ProtobufUtil.toServerName:(Lorg/apache/hadoop/hbase/shaded/protobuf/generated/HBaseProtos$ServerName;)Lorg/apache/hadoop/hbase/ServerName;
      11: astore_3
      12: aload_0
      13: getfield      #4                  // Field regionStates:Lorg/apache/hadoop/hbase/master/assignment/RegionStates;
      16: aload_3
      17: invokevirtual #253                // Method org/apache/hadoop/hbase/master/assignment/RegionStates.getOrCreateServer:(Lorg/apache/hadoop/hbase/ServerName;)Lorg/apache/hadoop/hbase/master/assignment/ServerStateNode;
      20: astore        4
      22: aload         4
      24: invokevirtual #254                // Method org/apache/hadoop/hbase/master/assignment/ServerStateNode.readLock:()Ljava/util/concurrent/locks/Lock;
      27: invokeinterface #255,  1          // InterfaceMethod java/util/concurrent/locks/Lock.lock:()V
      32: aload         4
      34: iconst_1
      35: anewarray     #256                // class org/apache/hadoop/hbase/master/assignment/ServerState
      38: dup
      39: iconst_0
      40: getstatic     #257                // Field org/apache/hadoop/hbase/master/assignment/ServerState.ONLINE:Lorg/apache/hadoop/hbase/master/assignment/ServerState;
      43: aastore
      44: invokevirtual #258                // Method org/apache/hadoop/hbase/master/assignment/ServerStateNode.isInState:([Lorg/apache/hadoop/hbase/master/assignment/ServerState;)Z
      47: ifeq          128
      50: aload_0
      51: aload_2
      52: aload_3
      53: aload_1
      54: invokevirtual #259                // Method org/apache/hadoop/hbase/shaded/protobuf/generated/RegionServerStatusProtos$ReportRegionStateTransitionRequest.getTransitionList:()Ljava/util/List;
      57: invokespecial #260                // Method reportRegionStateTransition:(Lorg/apache/hadoop/hbase/shaded/protobuf/generated/RegionServerStatusProtos$ReportRegionStateTransitionResponse$Builder;Lorg/apache/hadoop/hbase/ServerName;Ljava/util/List;)V
      60: goto          148
      63: astore        5
      65: getstatic     #5                  // Field LOG:Lorg/slf4j/Logger;
      68: ldc_w         #262                // String Failed transition
      71: aload         5
      73: invokeinterface #263,  3          // InterfaceMethod org/slf4j/Logger.trace:(Ljava/lang/String;Ljava/lang/Throwable;)V
      78: aload         5
      80: athrow
      81: astore        5
      83: getstatic     #5                  // Field LOG:Lorg/slf4j/Logger;
      86: ldc_w         #266                // String Failed transition
      89: aload         5
      91: invokeinterface #189,  3          // InterfaceMethod org/slf4j/Logger.warn:(Ljava/lang/String;Ljava/lang/Throwable;)V
      96: aload_2
      97: new           #131                // class java/lang/StringBuilder
     100: dup
     101: invokespecial #132                // Method java/lang/StringBuilder."<init>":()V
     104: ldc_w         #262                // String Failed transition
     107: invokevirtual #134                // Method java/lang/StringBuilder.append:(Ljava/lang/String;)Ljava/lang/StringBuilder;
     110: aload         5
     112: invokevirtual #267                // Method java/lang/Exception.getMessage:()Ljava/lang/String;
     115: invokevirtual #134                // Method java/lang/StringBuilder.append:(Ljava/lang/String;)Ljava/lang/StringBuilder;
     118: invokevirtual #136                // Method java/lang/StringBuilder.toString:()Ljava/lang/String;
     121: invokevirtual #268                // Method org/apache/hadoop/hbase/shaded/protobuf/generated/RegionServerStatusProtos$ReportRegionStateTransitionResponse$Builder.setErrorMessage:(Ljava/lang/String;)Lorg/apache/hadoop/hbase/shaded/protobuf/generated/RegionServerStatusProtos$ReportRegionStateTransitionResponse$Builder;
     124: pop
     125: goto          148
     128: getstatic     #5                  // Field LOG:Lorg/slf4j/Logger;
     131: ldc_w         #269                // String The region server {} is already dead, skip reportRegionStateTransition call
     134: aload_3
     135: invokeinterface #270,  3          // InterfaceMethod org/slf4j/Logger.warn:(Ljava/lang/String;Ljava/lang/Object;)V
     140: aload_2
     141: ldc_w         #271                // String You are dead
     144: invokevirtual #268                // Method org/apache/hadoop/hbase/shaded/protobuf/generated/RegionServerStatusProtos$ReportRegionStateTransitionResponse$Builder.setErrorMessage:(Ljava/lang/String;)Lorg/apache/hadoop/hbase/shaded/protobuf/generated/RegionServerStatusProtos$ReportRegionStateTransitionResponse$Builder;
     147: pop
     148: aload         4
     150: invokevirtual #254                // Method org/apache/hadoop/hbase/master/assignment/ServerStateNode.readLock:()Ljava/util/concurrent/locks/Lock;
     153: invokeinterface #272,  1          // InterfaceMethod java/util/concurrent/locks/Lock.unlock:()V
     158: goto          176
     161: astore        6
     163: aload         4
     165: invokevirtual #254                // Method org/apache/hadoop/hbase/master/assignment/ServerStateNode.readLock:()Ljava/util/concurrent/locks/Lock;
     168: invokeinterface #272,  1          // InterfaceMethod java/util/concurrent/locks/Lock.unlock:()V
     173: aload         6
     175: athrow
     176: aload_2
     177: invokevirtual #273                // Method org/apache/hadoop/hbase/shaded/protobuf/generated/RegionServerStatusProtos$ReportRegionStateTransitionResponse$Builder.build:()Lorg/apache/hadoop/hbase/shaded/protobuf/generated/RegionServerStatusProtos$ReportRegionStateTransitionResponse;
     180: areturn
    Exception table:
       from    to  target type
          50    60    63   Class org/apache/hadoop/hbase/PleaseHoldException
          50    60    81   Class java/lang/UnsupportedOperationException
          50    60    81   Class java/io/IOException
          32   148   161   any
         161   163   161   any

  public void reportOnlineRegions(org.apache.hadoop.hbase.ServerName, java.util.Set<byte[]>);
    Code:
       0: aload_0
       1: invokevirtual #321                // Method isRunning:()Z
       4: ifne          8
       7: return
       8: getstatic     #5                  // Field LOG:Lorg/slf4j/Logger;
      11: invokeinterface #322,  1          // InterfaceMethod org/slf4j/Logger.isTraceEnabled:()Z
      16: ifeq          87
      19: getstatic     #5                  // Field LOG:Lorg/slf4j/Logger;
      22: ldc_w         #323                // String ReportOnlineRegions {} regionCount={}, metaLoaded={} {}
      25: iconst_4
      26: anewarray     #23                 // class java/lang/Object
      29: dup
      30: iconst_0
      31: aload_1
      32: aastore
      33: dup
      34: iconst_1
      35: aload_2
      36: invokeinterface #324,  1          // InterfaceMethod java/util/Set.size:()I
      41: invokestatic  #325                // Method java/lang/Integer.valueOf:(I)Ljava/lang/Integer;
      44: aastore
      45: dup
      46: iconst_2
      47: aload_0
      48: invokevirtual #140                // Method isMetaLoaded:()Z
      51: invokestatic  #326                // Method java/lang/Boolean.valueOf:(Z)Ljava/lang/Boolean;
      54: aastore
      55: dup
      56: iconst_3
      57: aload_2
      58: invokeinterface #212,  1          // InterfaceMethod java/util/Set.stream:()Ljava/util/stream/Stream;
      63: invokedynamic #327,  0            // InvokeDynamic #11:apply:()Ljava/util/function/Function;
      68: invokeinterface #204,  2          // InterfaceMethod java/util/stream/Stream.map:(Ljava/util/function/Function;)Ljava/util/stream/Stream;
      73: invokestatic  #328                // Method java/util/stream/Collectors.toList:()Ljava/util/stream/Collector;
      76: invokeinterface #329,  2          // InterfaceMethod java/util/stream/Stream.collect:(Ljava/util/stream/Collector;)Ljava/lang/Object;
      81: aastore
      82: invokeinterface #280,  3          // InterfaceMethod org/slf4j/Logger.trace:(Ljava/lang/String;[Ljava/lang/Object;)V
      87: aload_0
      88: getfield      #4                  // Field regionStates:Lorg/apache/hadoop/hbase/master/assignment/RegionStates;
      91: aload_1
      92: invokevirtual #253                // Method org/apache/hadoop/hbase/master/assignment/RegionStates.getOrCreateServer:(Lorg/apache/hadoop/hbase/ServerName;)Lorg/apache/hadoop/hbase/master/assignment/ServerStateNode;
      95: astore_3
      96: aload_3
      97: dup
      98: astore        4
     100: monitorenter
     101: aload_3
     102: iconst_1
     103: anewarray     #256                // class org/apache/hadoop/hbase/master/assignment/ServerState
     106: dup
     107: iconst_0
     108: getstatic     #257                // Field org/apache/hadoop/hbase/master/assignment/ServerState.ONLINE:Lorg/apache/hadoop/hbase/master/assignment/ServerState;
     111: aastore
     112: invokevirtual #258                // Method org/apache/hadoop/hbase/master/assignment/ServerStateNode.isInState:([Lorg/apache/hadoop/hbase/master/assignment/ServerState;)Z
     115: ifne          153
     118: getstatic     #5                  // Field LOG:Lorg/slf4j/Logger;
     121: new           #131                // class java/lang/StringBuilder
     124: dup
     125: invokespecial #132                // Method java/lang/StringBuilder."<init>":()V
     128: ldc_w         #330                // String Got a report from a server result in state
     131: invokevirtual #134                // Method java/lang/StringBuilder.append:(Ljava/lang/String;)Ljava/lang/StringBuilder;
     134: aload_3
     135: invokevirtual #331                // Method org/apache/hadoop/hbase/master/assignment/ServerStateNode.getState:()Lorg/apache/hadoop/hbase/master/assignment/ServerState;
     138: invokevirtual #135                // Method java/lang/StringBuilder.append:(Ljava/lang/Object;)Ljava/lang/StringBuilder;
     141: invokevirtual #136                // Method java/lang/StringBuilder.toString:()Ljava/lang/String;
     144: invokeinterface #332,  2          // InterfaceMethod org/slf4j/Logger.warn:(Ljava/lang/String;)V
     149: aload         4
     151: monitorexit
     152: return
     153: aload         4
     155: monitorexit
     156: goto          167
     159: astore        5
     161: aload         4
     163: monitorexit
     164: aload         5
     166: athrow
     167: aload_2
     168: invokeinterface #333,  1          // InterfaceMethod java/util/Set.isEmpty:()Z
     173: ifeq          189
     176: getstatic     #5                  // Field LOG:Lorg/slf4j/Logger;
     179: ldc_w         #334                // String no online region found on {}
     182: aload_1
     183: invokeinterface #335,  3          // InterfaceMethod org/slf4j/Logger.trace:(Ljava/lang/String;Ljava/lang/Object;)V
     188: return
     189: aload_0
     190: invokevirtual #140                // Method isMetaLoaded:()Z
     193: ifne          197
     196: return
     197: aload_0
     198: aload_3
     199: aload_2
     200: invokespecial #336                // Method checkOnlineRegionsReport:(Lorg/apache/hadoop/hbase/master/assignment/ServerStateNode;Ljava/util/Set;)V
     203: return
    Exception table:
       from    to  target type
         101   152   159   any
         153   156   159   any
         159   164   159   any

  public org.apache.hadoop.hbase.master.assignment.AssignmentManager$RegionInTransitionStat computeRegionInTransitionStat();
    Code:
       0: new           #351                // class org/apache/hadoop/hbase/master/assignment/AssignmentManager$RegionInTransitionStat
       3: dup
       4: aload_0
       5: invokevirtual #352                // Method getConfiguration:()Lorg/apache/hadoop/conf/Configuration;
       8: invokespecial #353                // Method org/apache/hadoop/hbase/master/assignment/AssignmentManager$RegionInTransitionStat."<init>":(Lorg/apache/hadoop/conf/Configuration;)V
      11: astore_1
      12: aload_1
      13: aload_0
      14: invokevirtual #354                // Method org/apache/hadoop/hbase/master/assignment/AssignmentManager$RegionInTransitionStat.update:(Lorg/apache/hadoop/hbase/master/assignment/AssignmentManager;)V
      17: aload_1
      18: areturn

  public void joinCluster() throws java.io.IOException;
    Code:
       0: invokestatic  #362                // Method java/lang/System.nanoTime:()J
       3: lstore_1
       4: getstatic     #5                  // Field LOG:Lorg/slf4j/Logger;
       7: ldc_w         #363                // String Joining cluster...
      10: invokeinterface #184,  2          // InterfaceMethod org/slf4j/Logger.debug:(Ljava/lang/String;)V
      15: aload_0
      16: invokespecial #364                // Method loadMeta:()V
      19: aload_0
      20: getfield      #32                 // Field master:Lorg/apache/hadoop/hbase/master/MasterServices;
      23: invokeinterface #142,  1          // InterfaceMethod org/apache/hadoop/hbase/master/MasterServices.getServerManager:()Lorg/apache/hadoop/hbase/master/ServerManager;
      28: invokevirtual #143                // Method org/apache/hadoop/hbase/master/ServerManager.countOfRegionServers:()I
      31: iconst_1
      32: if_icmpge     70
      35: getstatic     #5                  // Field LOG:Lorg/slf4j/Logger;
      38: ldc_w         #365                // String Waiting for RegionServers to join; current count={}
      41: aload_0
      42: getfield      #32                 // Field master:Lorg/apache/hadoop/hbase/master/MasterServices;
      45: invokeinterface #142,  1          // InterfaceMethod org/apache/hadoop/hbase/master/MasterServices.getServerManager:()Lorg/apache/hadoop/hbase/master/ServerManager;
      50: invokevirtual #143                // Method org/apache/hadoop/hbase/master/ServerManager.countOfRegionServers:()I
      53: invokestatic  #325                // Method java/lang/Integer.valueOf:(I)Ljava/lang/Integer;
      56: invokeinterface #366,  3          // InterfaceMethod org/slf4j/Logger.info:(Ljava/lang/String;Ljava/lang/Object;)V
      61: ldc2_w        #367                // long 250l
      64: invokestatic  #369                // Method org/apache/hadoop/hbase/util/Threads.sleep:(J)V
      67: goto          19
      70: getstatic     #5                  // Field LOG:Lorg/slf4j/Logger;
      73: ldc_w         #370                // String Number of RegionServers={}
      76: aload_0
      77: getfield      #32                 // Field master:Lorg/apache/hadoop/hbase/master/MasterServices;
      80: invokeinterface #142,  1          // InterfaceMethod org/apache/hadoop/hbase/master/MasterServices.getServerManager:()Lorg/apache/hadoop/hbase/master/ServerManager;
      85: invokevirtual #143                // Method org/apache/hadoop/hbase/master/ServerManager.countOfRegionServers:()I
      88: invokestatic  #325                // Method java/lang/Integer.valueOf:(I)Ljava/lang/Integer;
      91: invokeinterface #366,  3          // InterfaceMethod org/slf4j/Logger.info:(Ljava/lang/String;Ljava/lang/Object;)V
      96: aload_0
      97: getfield      #32                 // Field master:Lorg/apache/hadoop/hbase/master/MasterServices;
     100: invokeinterface #85,  1           // InterfaceMethod org/apache/hadoop/hbase/master/MasterServices.getMasterProcedureExecutor:()Lorg/apache/hadoop/hbase/procedure2/ProcedureExecutor;
     105: aload_0
     106: getfield      #60                 // Field ritChore:Lorg/apache/hadoop/hbase/master/assignment/AssignmentManager$RegionInTransitionChore;
     109: invokevirtual #371                // Method org/apache/hadoop/hbase/procedure2/ProcedureExecutor.addChore:(Lorg/apache/hadoop/hbase/procedure2/ProcedureInMemoryChore;)V
     112: getstatic     #372                // Field java/util/concurrent/TimeUnit.NANOSECONDS:Ljava/util/concurrent/TimeUnit;
     115: invokestatic  #362                // Method java/lang/System.nanoTime:()J
     118: lload_1
     119: lsub
     120: invokevirtual #373                // Method java/util/concurrent/TimeUnit.toMillis:(J)J
     123: lstore_3
     124: getstatic     #5                  // Field LOG:Lorg/slf4j/Logger;
     127: ldc_w         #374                // String Joined the cluster in {}
     130: lload_3
     131: invokestatic  #375                // Method org/apache/hadoop/hbase/procedure2/util/StringUtils.humanTimeDiff:(J)Ljava/lang/String;
     134: invokeinterface #366,  3          // InterfaceMethod org/slf4j/Logger.info:(Ljava/lang/String;Ljava/lang/Object;)V
     139: return

  public void processOfflineRegions();
    Code:
       0: aload_0
       1: getfield      #4                  // Field regionStates:Lorg/apache/hadoop/hbase/master/assignment/RegionStates;
       4: invokevirtual #376                // Method org/apache/hadoop/hbase/master/assignment/RegionStates.getRegionStates:()Ljava/util/ArrayList;
       7: invokevirtual #217                // Method java/util/ArrayList.stream:()Ljava/util/stream/Stream;
      10: invokedynamic #377,  0            // InvokeDynamic #12:test:()Ljava/util/function/Predicate;
      15: invokeinterface #220,  2          // InterfaceMethod java/util/stream/Stream.filter:(Ljava/util/function/Predicate;)Ljava/util/stream/Stream;
      20: aload_0
      21: invokedynamic #378,  0            // InvokeDynamic #13:test:(Lorg/apache/hadoop/hbase/master/assignment/AssignmentManager;)Ljava/util/function/Predicate;
      26: invokeinterface #220,  2          // InterfaceMethod java/util/stream/Stream.filter:(Ljava/util/function/Predicate;)Ljava/util/stream/Stream;
      31: invokedynamic #379,  0            // InvokeDynamic #14:apply:()Ljava/util/function/Function;
      36: invokeinterface #204,  2          // InterfaceMethod java/util/stream/Stream.map:(Ljava/util/function/Function;)Ljava/util/stream/Stream;
      41: invokestatic  #328                // Method java/util/stream/Collectors.toList:()Ljava/util/stream/Collector;
      44: invokeinterface #329,  2          // InterfaceMethod java/util/stream/Stream.collect:(Ljava/util/stream/Collector;)Ljava/lang/Object;
      49: checkcast     #380                // class java/util/List
      52: astore_1
      53: aload_1
      54: invokeinterface #179,  1          // InterfaceMethod java/util/List.isEmpty:()Z
      59: ifne          87
      62: aload_0
      63: getfield      #32                 // Field master:Lorg/apache/hadoop/hbase/master/MasterServices;
      66: invokeinterface #85,  1           // InterfaceMethod org/apache/hadoop/hbase/master/MasterServices.getMasterProcedureExecutor:()Lorg/apache/hadoop/hbase/procedure2/ProcedureExecutor;
      71: aload_0
      72: getfield      #32                 // Field master:Lorg/apache/hadoop/hbase/master/MasterServices;
      75: invokeinterface #381,  1          // InterfaceMethod org/apache/hadoop/hbase/master/MasterServices.getAssignmentManager:()Lorg/apache/hadoop/hbase/master/assignment/AssignmentManager;
      80: aload_1
      81: invokevirtual #382                // Method createRoundRobinAssignProcedures:(Ljava/util/List;)[Lorg/apache/hadoop/hbase/master/assignment/TransitRegionStateProcedure;
      84: invokevirtual #383                // Method org/apache/hadoop/hbase/procedure2/ProcedureExecutor.submitProcedures:([Lorg/apache/hadoop/hbase/procedure2/Procedure;)V
      87: return

  public int getNumRegionsOpened();
    Code:
       0: iconst_0
       1: ireturn

  public long submitServerCrash(org.apache.hadoop.hbase.ServerName, boolean);
    Code:
       0: aload_0
       1: getfield      #4                  // Field regionStates:Lorg/apache/hadoop/hbase/master/assignment/RegionStates;
       4: aload_1
       5: invokevirtual #101                // Method org/apache/hadoop/hbase/master/assignment/RegionStates.getServerNode:(Lorg/apache/hadoop/hbase/ServerName;)Lorg/apache/hadoop/hbase/master/assignment/ServerStateNode;
       8: astore        6
      10: aload         6
      12: ifnonnull     31
      15: getstatic     #5                  // Field LOG:Lorg/slf4j/Logger;
      18: ldc_w         #393                // String Skip to add SCP for {} since this server should be OFFLINE already
      21: aload_1
      22: invokeinterface #366,  3          // InterfaceMethod org/slf4j/Logger.info:(Ljava/lang/String;Ljava/lang/Object;)V
      27: ldc2_w        #243                // long -1l
      30: lreturn
      31: aload         6
      33: invokevirtual #394                // Method org/apache/hadoop/hbase/master/assignment/ServerStateNode.writeLock:()Ljava/util/concurrent/locks/Lock;
      36: invokeinterface #255,  1          // InterfaceMethod java/util/concurrent/locks/Lock.lock:()V
      41: aload_0
      42: getfield      #32                 // Field master:Lorg/apache/hadoop/hbase/master/MasterServices;
      45: invokeinterface #85,  1           // InterfaceMethod org/apache/hadoop/hbase/master/MasterServices.getMasterProcedureExecutor:()Lorg/apache/hadoop/hbase/procedure2/ProcedureExecutor;
      50: astore        7
      52: aload_0
      53: aload_1
      54: invokevirtual #395                // Method isCarryingMeta:(Lorg/apache/hadoop/hbase/ServerName;)Z
      57: istore_3
      58: aload         6
      60: iconst_1
      61: anewarray     #256                // class org/apache/hadoop/hbase/master/assignment/ServerState
      64: dup
      65: iconst_0
      66: getstatic     #257                // Field org/apache/hadoop/hbase/master/assignment/ServerState.ONLINE:Lorg/apache/hadoop/hbase/master/assignment/ServerState;
      69: aastore
      70: invokevirtual #258                // Method org/apache/hadoop/hbase/master/assignment/ServerStateNode.isInState:([Lorg/apache/hadoop/hbase/master/assignment/ServerState;)Z
      73: ifne          110
      76: getstatic     #5                  // Field LOG:Lorg/slf4j/Logger;
      79: ldc_w         #396                // String Skip to add SCP for {} with meta= {}, since there should be a SCP is processing or already done for this server node
      82: aload_1
      83: iload_3
      84: invokestatic  #326                // Method java/lang/Boolean.valueOf:(Z)Ljava/lang/Boolean;
      87: invokeinterface #286,  4          // InterfaceMethod org/slf4j/Logger.info:(Ljava/lang/String;Ljava/lang/Object;Ljava/lang/Object;)V
      92: ldc2_w        #243                // long -1l
      95: lstore        8
      97: aload         6
      99: invokevirtual #394                // Method org/apache/hadoop/hbase/master/assignment/ServerStateNode.writeLock:()Ljava/util/concurrent/locks/Lock;
     102: invokeinterface #272,  1          // InterfaceMethod java/util/concurrent/locks/Lock.unlock:()V
     107: lload         8
     109: lreturn
     110: aload         6
     112: getstatic     #397                // Field org/apache/hadoop/hbase/master/assignment/ServerState.CRASHED:Lorg/apache/hadoop/hbase/master/assignment/ServerState;
     115: invokevirtual #398                // Method org/apache/hadoop/hbase/master/assignment/ServerStateNode.setState:(Lorg/apache/hadoop/hbase/master/assignment/ServerState;)V
     118: aload         7
     120: new           #399                // class org/apache/hadoop/hbase/master/procedure/ServerCrashProcedure
     123: dup
     124: aload         7
     126: invokevirtual #97                 // Method org/apache/hadoop/hbase/procedure2/ProcedureExecutor.getEnvironment:()Ljava/lang/Object;
     129: checkcast     #98                 // class org/apache/hadoop/hbase/master/procedure/MasterProcedureEnv
     132: aload_1
     133: iload_2
     134: iload_3
     135: invokespecial #400                // Method org/apache/hadoop/hbase/master/procedure/ServerCrashProcedure."<init>":(Lorg/apache/hadoop/hbase/master/procedure/MasterProcedureEnv;Lorg/apache/hadoop/hbase/ServerName;ZZ)V
     138: invokevirtual #307                // Method org/apache/hadoop/hbase/procedure2/ProcedureExecutor.submitProcedure:(Lorg/apache/hadoop/hbase/procedure2/Procedure;)J
     141: lstore        4
     143: getstatic     #5                  // Field LOG:Lorg/slf4j/Logger;
     146: ldc_w         #401                // String Added {} to dead servers which carryingMeta={}, submitted ServerCrashProcedure pid={}
     149: iconst_3
     150: anewarray     #23                 // class java/lang/Object
     153: dup
     154: iconst_0
     155: aload_1
     156: aastore
     157: dup
     158: iconst_1
     159: iload_3
     160: invokestatic  #326                // Method java/lang/Boolean.valueOf:(Z)Ljava/lang/Boolean;
     163: aastore
     164: dup
     165: iconst_2
     166: lload         4
     168: invokestatic  #349                // Method java/lang/Long.valueOf:(J)Ljava/lang/Long;
     171: aastore
     172: invokeinterface #402,  3          // InterfaceMethod org/slf4j/Logger.info:(Ljava/lang/String;[Ljava/lang/Object;)V
     177: aload         6
     179: invokevirtual #394                // Method org/apache/hadoop/hbase/master/assignment/ServerStateNode.writeLock:()Ljava/util/concurrent/locks/Lock;
     182: invokeinterface #272,  1          // InterfaceMethod java/util/concurrent/locks/Lock.unlock:()V
     187: goto          205
     190: astore        10
     192: aload         6
     194: invokevirtual #394                // Method org/apache/hadoop/hbase/master/assignment/ServerStateNode.writeLock:()Ljava/util/concurrent/locks/Lock;
     197: invokeinterface #272,  1          // InterfaceMethod java/util/concurrent/locks/Lock.unlock:()V
     202: aload         10
     204: athrow
     205: lload         4
     207: lreturn
    Exception table:
       from    to  target type
          41    97   190   any
         110   177   190   any
         190   192   190   any

  public void offlineRegion(org.apache.hadoop.hbase.client.RegionInfo);
    Code:
       0: aload_0
       1: getfield      #4                  // Field regionStates:Lorg/apache/hadoop/hbase/master/assignment/RegionStates;
       4: aload_1
       5: invokevirtual #119                // Method org/apache/hadoop/hbase/master/assignment/RegionStates.getRegionStateNode:(Lorg/apache/hadoop/hbase/client/RegionInfo;)Lorg/apache/hadoop/hbase/master/assignment/RegionStateNode;
       8: astore_2
       9: aload_2
      10: ifnull        18
      13: aload_2
      14: invokevirtual #403                // Method org/apache/hadoop/hbase/master/assignment/RegionStateNode.offline:()Lorg/apache/hadoop/hbase/ServerName;
      17: pop
      18: return

  public void onlineRegion(org.apache.hadoop.hbase.client.RegionInfo, org.apache.hadoop.hbase.ServerName);
    Code:
       0: return

  public java.util.Map<org.apache.hadoop.hbase.ServerName, java.util.List<org.apache.hadoop.hbase.client.RegionInfo>> getSnapShotOfAssignment(java.util.Collection<org.apache.hadoop.hbase.client.RegionInfo>);
    Code:
       0: aload_0
       1: getfield      #4                  // Field regionStates:Lorg/apache/hadoop/hbase/master/assignment/RegionStates;
       4: aload_1
       5: invokevirtual #404                // Method org/apache/hadoop/hbase/master/assignment/RegionStates.getSnapShotOfAssignment:(Ljava/util/Collection;)Ljava/util/Map;
       8: areturn

  public org.apache.hadoop.hbase.util.Pair<java.lang.Integer, java.lang.Integer> getReopenStatus(org.apache.hadoop.hbase.TableName);
    Code:
       0: aload_0
       1: aload_1
       2: invokevirtual #405                // Method isTableDisabled:(Lorg/apache/hadoop/hbase/TableName;)Z
       5: ifeq          24
       8: new           #406                // class org/apache/hadoop/hbase/util/Pair
      11: dup
      12: iconst_0
      13: invokestatic  #325                // Method java/lang/Integer.valueOf:(I)Ljava/lang/Integer;
      16: iconst_0
      17: invokestatic  #325                // Method java/lang/Integer.valueOf:(I)Ljava/lang/Integer;
      20: invokespecial #407                // Method org/apache/hadoop/hbase/util/Pair."<init>":(Ljava/lang/Object;Ljava/lang/Object;)V
      23: areturn
      24: aload_0
      25: getfield      #4                  // Field regionStates:Lorg/apache/hadoop/hbase/master/assignment/RegionStates;
      28: aload_1
      29: invokevirtual #408                // Method org/apache/hadoop/hbase/master/assignment/RegionStates.getTableRegionStates:(Lorg/apache/hadoop/hbase/TableName;)Ljava/util/ArrayList;
      32: astore_2
      33: iconst_0
      34: istore_3
      35: aload_2
      36: invokeinterface #232,  1          // InterfaceMethod java/util/List.iterator:()Ljava/util/Iterator;
      41: astore        4
      43: aload         4
      45: invokeinterface #92,  1           // InterfaceMethod java/util/Iterator.hasNext:()Z
      50: ifeq          87
      53: aload         4
      55: invokeinterface #93,  1           // InterfaceMethod java/util/Iterator.next:()Ljava/lang/Object;
      60: checkcast     #409                // class org/apache/hadoop/hbase/master/RegionState
      63: astore        5
      65: aload         5
      67: invokevirtual #410                // Method org/apache/hadoop/hbase/master/RegionState.isOpened:()Z
      70: ifne          84
      73: aload         5
      75: invokevirtual #411                // Method org/apache/hadoop/hbase/master/RegionState.isSplit:()Z
      78: ifne          84
      81: iinc          3, 1
      84: goto          43
      87: new           #406                // class org/apache/hadoop/hbase/util/Pair
      90: dup
      91: iload_3
      92: invokestatic  #325                // Method java/lang/Integer.valueOf:(I)Ljava/lang/Integer;
      95: aload_2
      96: invokeinterface #182,  1          // InterfaceMethod java/util/List.size:()I
     101: invokestatic  #325                // Method java/lang/Integer.valueOf:(I)Ljava/lang/Integer;
     104: invokespecial #407                // Method org/apache/hadoop/hbase/util/Pair."<init>":(Ljava/lang/Object;Ljava/lang/Object;)V
     107: areturn

  public boolean hasRegionsInTransition();
    Code:
       0: aload_0
       1: getfield      #4                  // Field regionStates:Lorg/apache/hadoop/hbase/master/assignment/RegionStates;
       4: invokevirtual #412                // Method org/apache/hadoop/hbase/master/assignment/RegionStates.hasRegionsInTransition:()Z
       7: ireturn

  public java.util.List<org.apache.hadoop.hbase.master.assignment.RegionStateNode> getRegionsInTransition();
    Code:
       0: aload_0
       1: getfield      #4                  // Field regionStates:Lorg/apache/hadoop/hbase/master/assignment/RegionStates;
       4: invokevirtual #413                // Method org/apache/hadoop/hbase/master/assignment/RegionStates.getRegionsInTransition:()Ljava/util/List;
       7: areturn

  public java.util.List<org.apache.hadoop.hbase.client.RegionInfo> getAssignedRegions();
    Code:
       0: aload_0
       1: getfield      #4                  // Field regionStates:Lorg/apache/hadoop/hbase/master/assignment/RegionStates;
       4: invokevirtual #414                // Method org/apache/hadoop/hbase/master/assignment/RegionStates.getAssignedRegions:()Ljava/util/List;
       7: areturn

  public org.apache.hadoop.hbase.client.RegionInfo getRegionInfo(byte[]);
    Code:
       0: aload_0
       1: getfield      #4                  // Field regionStates:Lorg/apache/hadoop/hbase/master/assignment/RegionStates;
       4: aload_1
       5: invokevirtual #338                // Method org/apache/hadoop/hbase/master/assignment/RegionStates.getRegionStateNodeFromName:([B)Lorg/apache/hadoop/hbase/master/assignment/RegionStateNode;
       8: astore_2
       9: aload_2
      10: ifnull        20
      13: aload_2
      14: invokevirtual #199                // Method org/apache/hadoop/hbase/master/assignment/RegionStateNode.getRegionInfo:()Lorg/apache/hadoop/hbase/client/RegionInfo;
      17: goto          21
      20: aconst_null
      21: areturn

  void regionOpening(org.apache.hadoop.hbase.master.assignment.RegionStateNode) throws java.io.IOException;
    Code:
       0: aload_0
       1: aload_1
       2: getstatic     #342                // Field org/apache/hadoop/hbase/master/RegionState$State.OPENING:Lorg/apache/hadoop/hbase/master/RegionState$State;
       5: iconst_0
       6: anewarray     #73                 // class org/apache/hadoop/hbase/master/RegionState$State
       9: invokespecial #418                // Method transitStateAndUpdate:(Lorg/apache/hadoop/hbase/master/assignment/RegionStateNode;Lorg/apache/hadoop/hbase/master/RegionState$State;[Lorg/apache/hadoop/hbase/master/RegionState$State;)V
      12: aload_0
      13: getfield      #4                  // Field regionStates:Lorg/apache/hadoop/hbase/master/assignment/RegionStates;
      16: aload_1
      17: invokevirtual #419                // Method org/apache/hadoop/hbase/master/assignment/RegionStates.addRegionToServer:(Lorg/apache/hadoop/hbase/master/assignment/RegionStateNode;)Lorg/apache/hadoop/hbase/master/assignment/ServerStateNode;
      20: pop
      21: aload_0
      22: getfield      #36                 // Field metrics:Lorg/apache/hadoop/hbase/master/MetricsAssignmentManager;
      25: invokevirtual #420                // Method org/apache/hadoop/hbase/master/MetricsAssignmentManager.incrementOperationCounter:()V
      28: return

  void regionFailedOpen(org.apache.hadoop.hbase.master.assignment.RegionStateNode, boolean) throws java.io.IOException;
    Code:
       0: aload_1
       1: invokevirtual #415                // Method org/apache/hadoop/hbase/master/assignment/RegionStateNode.getState:()Lorg/apache/hadoop/hbase/master/RegionState$State;
       4: astore_3
       5: aload_1
       6: invokevirtual #120                // Method org/apache/hadoop/hbase/master/assignment/RegionStateNode.getRegionLocation:()Lorg/apache/hadoop/hbase/ServerName;
       9: astore        4
      11: iload_2
      12: ifeq          99
      15: aload_1
      16: getstatic     #421                // Field org/apache/hadoop/hbase/master/RegionState$State.FAILED_OPEN:Lorg/apache/hadoop/hbase/master/RegionState$State;
      19: iconst_0
      20: anewarray     #73                 // class org/apache/hadoop/hbase/master/RegionState$State
      23: invokevirtual #74                 // Method org/apache/hadoop/hbase/master/assignment/RegionStateNode.setState:(Lorg/apache/hadoop/hbase/master/RegionState$State;[Lorg/apache/hadoop/hbase/master/RegionState$State;)Z
      26: pop
      27: aload_1
      28: aconst_null
      29: invokevirtual #71                 // Method org/apache/hadoop/hbase/master/assignment/RegionStateNode.setRegionLocation:(Lorg/apache/hadoop/hbase/ServerName;)Lorg/apache/hadoop/hbase/ServerName;
      32: pop
      33: iconst_0
      34: istore        5
      36: aload_0
      37: getfield      #33                 // Field regionStateStore:Lorg/apache/hadoop/hbase/master/assignment/RegionStateStore;
      40: aload_1
      41: invokevirtual #417                // Method org/apache/hadoop/hbase/master/assignment/RegionStateStore.updateRegionLocation:(Lorg/apache/hadoop/hbase/master/assignment/RegionStateNode;)V
      44: iconst_1
      45: istore        5
      47: iload         5
      49: ifne          99
      52: aload_1
      53: aload_3
      54: iconst_0
      55: anewarray     #73                 // class org/apache/hadoop/hbase/master/RegionState$State
      58: invokevirtual #74                 // Method org/apache/hadoop/hbase/master/assignment/RegionStateNode.setState:(Lorg/apache/hadoop/hbase/master/RegionState$State;[Lorg/apache/hadoop/hbase/master/RegionState$State;)Z
      61: pop
      62: aload_1
      63: aload         4
      65: invokevirtual #71                 // Method org/apache/hadoop/hbase/master/assignment/RegionStateNode.setRegionLocation:(Lorg/apache/hadoop/hbase/ServerName;)Lorg/apache/hadoop/hbase/ServerName;
      68: pop
      69: goto          99
      72: astore        6
      74: iload         5
      76: ifne          96
      79: aload_1
      80: aload_3
      81: iconst_0
      82: anewarray     #73                 // class org/apache/hadoop/hbase/master/RegionState$State
      85: invokevirtual #74                 // Method org/apache/hadoop/hbase/master/assignment/RegionStateNode.setState:(Lorg/apache/hadoop/hbase/master/RegionState$State;[Lorg/apache/hadoop/hbase/master/RegionState$State;)Z
      88: pop
      89: aload_1
      90: aload         4
      92: invokevirtual #71                 // Method org/apache/hadoop/hbase/master/assignment/RegionStateNode.setRegionLocation:(Lorg/apache/hadoop/hbase/ServerName;)Lorg/apache/hadoop/hbase/ServerName;
      95: pop
      96: aload         6
      98: athrow
      99: aload         4
     101: ifnull        115
     104: aload_0
     105: getfield      #4                  // Field regionStates:Lorg/apache/hadoop/hbase/master/assignment/RegionStates;
     108: aload         4
     110: aload_1
     111: invokevirtual #422                // Method org/apache/hadoop/hbase/master/assignment/RegionStates.removeRegionFromServer:(Lorg/apache/hadoop/hbase/ServerName;Lorg/apache/hadoop/hbase/master/assignment/RegionStateNode;)Lorg/apache/hadoop/hbase/master/assignment/ServerStateNode;
     114: pop
     115: return
    Exception table:
       from    to  target type
          36    47    72   any
          72    74    72   any

  void regionClosing(org.apache.hadoop.hbase.master.assignment.RegionStateNode) throws java.io.IOException;
    Code:
       0: aload_0
       1: aload_1
       2: getstatic     #346                // Field org/apache/hadoop/hbase/master/RegionState$State.CLOSING:Lorg/apache/hadoop/hbase/master/RegionState$State;
       5: getstatic     #423                // Field STATES_EXPECTED_ON_CLOSING:[Lorg/apache/hadoop/hbase/master/RegionState$State;
       8: invokespecial #418                // Method transitStateAndUpdate:(Lorg/apache/hadoop/hbase/master/assignment/RegionStateNode;Lorg/apache/hadoop/hbase/master/RegionState$State;[Lorg/apache/hadoop/hbase/master/RegionState$State;)V
      11: aload_1
      12: invokevirtual #199                // Method org/apache/hadoop/hbase/master/assignment/RegionStateNode.getRegionInfo:()Lorg/apache/hadoop/hbase/client/RegionInfo;
      15: astore_2
      16: aload_0
      17: aload_2
      18: invokespecial #129                // Method isMetaRegion:(Lorg/apache/hadoop/hbase/client/RegionInfo;)Z
      21: ifeq          30
      24: aload_0
      25: aload_2
      26: iconst_0
      27: invokespecial #79                 // Method setMetaAssigned:(Lorg/apache/hadoop/hbase/client/RegionInfo;Z)V
      30: aload_0
      31: getfield      #4                  // Field regionStates:Lorg/apache/hadoop/hbase/master/assignment/RegionStates;
      34: aload_1
      35: invokevirtual #419                // Method org/apache/hadoop/hbase/master/assignment/RegionStates.addRegionToServer:(Lorg/apache/hadoop/hbase/master/assignment/RegionStateNode;)Lorg/apache/hadoop/hbase/master/assignment/ServerStateNode;
      38: pop
      39: aload_0
      40: getfield      #36                 // Field metrics:Lorg/apache/hadoop/hbase/master/MetricsAssignmentManager;
      43: invokevirtual #420                // Method org/apache/hadoop/hbase/master/MetricsAssignmentManager.incrementOperationCounter:()V
      46: return

  void regionOpenedWithoutPersistingToMeta(org.apache.hadoop.hbase.master.assignment.RegionStateNode) throws java.io.IOException;
    Code:
       0: aload_1
       1: getstatic     #78                 // Field org/apache/hadoop/hbase/master/RegionState$State.OPEN:Lorg/apache/hadoop/hbase/master/RegionState$State;
       4: getstatic     #424                // Field STATES_EXPECTED_ON_OPEN:[Lorg/apache/hadoop/hbase/master/RegionState$State;
       7: invokevirtual #416                // Method org/apache/hadoop/hbase/master/assignment/RegionStateNode.transitionState:(Lorg/apache/hadoop/hbase/master/RegionState$State;[Lorg/apache/hadoop/hbase/master/RegionState$State;)V
      10: aload_1
      11: invokevirtual #199                // Method org/apache/hadoop/hbase/master/assignment/RegionStateNode.getRegionInfo:()Lorg/apache/hadoop/hbase/client/RegionInfo;
      14: astore_2
      15: aload_0
      16: getfield      #4                  // Field regionStates:Lorg/apache/hadoop/hbase/master/assignment/RegionStates;
      19: aload_1
      20: invokevirtual #419                // Method org/apache/hadoop/hbase/master/assignment/RegionStates.addRegionToServer:(Lorg/apache/hadoop/hbase/master/assignment/RegionStateNode;)Lorg/apache/hadoop/hbase/master/assignment/ServerStateNode;
      23: pop
      24: aload_0
      25: getfield      #4                  // Field regionStates:Lorg/apache/hadoop/hbase/master/assignment/RegionStates;
      28: aload_2
      29: invokevirtual #425                // Method org/apache/hadoop/hbase/master/assignment/RegionStates.removeFromFailedOpen:(Lorg/apache/hadoop/hbase/client/RegionInfo;)V
      32: return

  void regionClosedWithoutPersistingToMeta(org.apache.hadoop.hbase.master.assignment.RegionStateNode) throws java.io.IOException;
    Code:
       0: aload_1
       1: invokevirtual #120                // Method org/apache/hadoop/hbase/master/assignment/RegionStateNode.getRegionLocation:()Lorg/apache/hadoop/hbase/ServerName;
       4: astore_2
       5: aload_1
       6: getstatic     #426                // Field org/apache/hadoop/hbase/master/RegionState$State.CLOSED:Lorg/apache/hadoop/hbase/master/RegionState$State;
       9: getstatic     #427                // Field STATES_EXPECTED_ON_CLOSED:[Lorg/apache/hadoop/hbase/master/RegionState$State;
      12: invokevirtual #416                // Method org/apache/hadoop/hbase/master/assignment/RegionStateNode.transitionState:(Lorg/apache/hadoop/hbase/master/RegionState$State;[Lorg/apache/hadoop/hbase/master/RegionState$State;)V
      15: aload_1
      16: aconst_null
      17: invokevirtual #71                 // Method org/apache/hadoop/hbase/master/assignment/RegionStateNode.setRegionLocation:(Lorg/apache/hadoop/hbase/ServerName;)Lorg/apache/hadoop/hbase/ServerName;
      20: pop
      21: aload_2
      22: ifnull        40
      25: aload_1
      26: aload_2
      27: invokevirtual #428                // Method org/apache/hadoop/hbase/master/assignment/RegionStateNode.setLastHost:(Lorg/apache/hadoop/hbase/ServerName;)V
      30: aload_0
      31: getfield      #4                  // Field regionStates:Lorg/apache/hadoop/hbase/master/assignment/RegionStates;
      34: aload_2
      35: aload_1
      36: invokevirtual #422                // Method org/apache/hadoop/hbase/master/assignment/RegionStates.removeRegionFromServer:(Lorg/apache/hadoop/hbase/ServerName;Lorg/apache/hadoop/hbase/master/assignment/RegionStateNode;)Lorg/apache/hadoop/hbase/master/assignment/ServerStateNode;
      39: pop
      40: return

  void regionClosedAbnormally(org.apache.hadoop.hbase.master.assignment.RegionStateNode) throws java.io.IOException;
    Code:
       0: aload_1
       1: invokevirtual #415                // Method org/apache/hadoop/hbase/master/assignment/RegionStateNode.getState:()Lorg/apache/hadoop/hbase/master/RegionState$State;
       4: astore_2
       5: aload_1
       6: invokevirtual #120                // Method org/apache/hadoop/hbase/master/assignment/RegionStateNode.getRegionLocation:()Lorg/apache/hadoop/hbase/ServerName;
       9: astore_3
      10: aload_1
      11: getstatic     #429                // Field org/apache/hadoop/hbase/master/RegionState$State.ABNORMALLY_CLOSED:Lorg/apache/hadoop/hbase/master/RegionState$State;
      14: iconst_0
      15: anewarray     #73                 // class org/apache/hadoop/hbase/master/RegionState$State
      18: invokevirtual #416                // Method org/apache/hadoop/hbase/master/assignment/RegionStateNode.transitionState:(Lorg/apache/hadoop/hbase/master/RegionState$State;[Lorg/apache/hadoop/hbase/master/RegionState$State;)V
      21: aload_1
      22: aconst_null
      23: invokevirtual #71                 // Method org/apache/hadoop/hbase/master/assignment/RegionStateNode.setRegionLocation:(Lorg/apache/hadoop/hbase/ServerName;)Lorg/apache/hadoop/hbase/ServerName;
      26: pop
      27: iconst_0
      28: istore        4
      30: aload_0
      31: getfield      #33                 // Field regionStateStore:Lorg/apache/hadoop/hbase/master/assignment/RegionStateStore;
      34: aload_1
      35: invokevirtual #417                // Method org/apache/hadoop/hbase/master/assignment/RegionStateStore.updateRegionLocation:(Lorg/apache/hadoop/hbase/master/assignment/RegionStateNode;)V
      38: iconst_1
      39: istore        4
      41: iload         4
      43: ifne          91
      46: aload_1
      47: aload_2
      48: iconst_0
      49: anewarray     #73                 // class org/apache/hadoop/hbase/master/RegionState$State
      52: invokevirtual #74                 // Method org/apache/hadoop/hbase/master/assignment/RegionStateNode.setState:(Lorg/apache/hadoop/hbase/master/RegionState$State;[Lorg/apache/hadoop/hbase/master/RegionState$State;)Z
      55: pop
      56: aload_1
      57: aload_3
      58: invokevirtual #71                 // Method org/apache/hadoop/hbase/master/assignment/RegionStateNode.setRegionLocation:(Lorg/apache/hadoop/hbase/ServerName;)Lorg/apache/hadoop/hbase/ServerName;
      61: pop
      62: goto          91
      65: astore        5
      67: iload         4
      69: ifne          88
      72: aload_1
      73: aload_2
      74: iconst_0
      75: anewarray     #73                 // class org/apache/hadoop/hbase/master/RegionState$State
      78: invokevirtual #74                 // Method org/apache/hadoop/hbase/master/assignment/RegionStateNode.setState:(Lorg/apache/hadoop/hbase/master/RegionState$State;[Lorg/apache/hadoop/hbase/master/RegionState$State;)Z
      81: pop
      82: aload_1
      83: aload_3
      84: invokevirtual #71                 // Method org/apache/hadoop/hbase/master/assignment/RegionStateNode.setRegionLocation:(Lorg/apache/hadoop/hbase/ServerName;)Lorg/apache/hadoop/hbase/ServerName;
      87: pop
      88: aload         5
      90: athrow
      91: aload_3
      92: ifnull        110
      95: aload_1
      96: aload_3
      97: invokevirtual #428                // Method org/apache/hadoop/hbase/master/assignment/RegionStateNode.setLastHost:(Lorg/apache/hadoop/hbase/ServerName;)V
     100: aload_0
     101: getfield      #4                  // Field regionStates:Lorg/apache/hadoop/hbase/master/assignment/RegionStates;
     104: aload_3
     105: aload_1
     106: invokevirtual #422                // Method org/apache/hadoop/hbase/master/assignment/RegionStates.removeRegionFromServer:(Lorg/apache/hadoop/hbase/ServerName;Lorg/apache/hadoop/hbase/master/assignment/RegionStateNode;)Lorg/apache/hadoop/hbase/master/assignment/ServerStateNode;
     109: pop
     110: return
    Exception table:
       from    to  target type
          30    41    65   any
          65    67    65   any

  void persistToMeta(org.apache.hadoop.hbase.master.assignment.RegionStateNode) throws java.io.IOException;
    Code:
       0: aload_0
       1: getfield      #33                 // Field regionStateStore:Lorg/apache/hadoop/hbase/master/assignment/RegionStateStore;
       4: aload_1
       5: invokevirtual #417                // Method org/apache/hadoop/hbase/master/assignment/RegionStateStore.updateRegionLocation:(Lorg/apache/hadoop/hbase/master/assignment/RegionStateNode;)V
       8: aload_1
       9: invokevirtual #199                // Method org/apache/hadoop/hbase/master/assignment/RegionStateNode.getRegionInfo:()Lorg/apache/hadoop/hbase/client/RegionInfo;
      12: astore_2
      13: aload_0
      14: aload_2
      15: invokespecial #129                // Method isMetaRegion:(Lorg/apache/hadoop/hbase/client/RegionInfo;)Z
      18: ifeq          37
      21: aload_1
      22: invokevirtual #415                // Method org/apache/hadoop/hbase/master/assignment/RegionStateNode.getState:()Lorg/apache/hadoop/hbase/master/RegionState$State;
      25: getstatic     #78                 // Field org/apache/hadoop/hbase/master/RegionState$State.OPEN:Lorg/apache/hadoop/hbase/master/RegionState$State;
      28: if_acmpne     37
      31: aload_0
      32: aload_2
      33: iconst_1
      34: invokespecial #79                 // Method setMetaAssigned:(Lorg/apache/hadoop/hbase/client/RegionInfo;Z)V
      37: return

  public void markRegionAsSplit(org.apache.hadoop.hbase.client.RegionInfo, org.apache.hadoop.hbase.ServerName, org.apache.hadoop.hbase.client.RegionInfo, org.apache.hadoop.hbase.client.RegionInfo) throws java.io.IOException;
    Code:
       0: aload_0
       1: getfield      #4                  // Field regionStates:Lorg/apache/hadoop/hbase/master/assignment/RegionStates;
       4: aload_1
       5: invokevirtual #68                 // Method org/apache/hadoop/hbase/master/assignment/RegionStates.getOrCreateRegionStateNode:(Lorg/apache/hadoop/hbase/client/RegionInfo;)Lorg/apache/hadoop/hbase/master/assignment/RegionStateNode;
       8: astore        5
      10: aload         5
      12: getstatic     #430                // Field org/apache/hadoop/hbase/master/RegionState$State.SPLIT:Lorg/apache/hadoop/hbase/master/RegionState$State;
      15: iconst_0
      16: anewarray     #73                 // class org/apache/hadoop/hbase/master/RegionState$State
      19: invokevirtual #74                 // Method org/apache/hadoop/hbase/master/assignment/RegionStateNode.setState:(Lorg/apache/hadoop/hbase/master/RegionState$State;[Lorg/apache/hadoop/hbase/master/RegionState$State;)Z
      22: pop
      23: aload_0
      24: getfield      #4                  // Field regionStates:Lorg/apache/hadoop/hbase/master/assignment/RegionStates;
      27: aload_3
      28: invokevirtual #68                 // Method org/apache/hadoop/hbase/master/assignment/RegionStates.getOrCreateRegionStateNode:(Lorg/apache/hadoop/hbase/client/RegionInfo;)Lorg/apache/hadoop/hbase/master/assignment/RegionStateNode;
      31: astore        6
      33: aload         6
      35: getstatic     #431                // Field org/apache/hadoop/hbase/master/RegionState$State.SPLITTING_NEW:Lorg/apache/hadoop/hbase/master/RegionState$State;
      38: iconst_0
      39: anewarray     #73                 // class org/apache/hadoop/hbase/master/RegionState$State
      42: invokevirtual #74                 // Method org/apache/hadoop/hbase/master/assignment/RegionStateNode.setState:(Lorg/apache/hadoop/hbase/master/RegionState$State;[Lorg/apache/hadoop/hbase/master/RegionState$State;)Z
      45: pop
      46: aload_0
      47: getfield      #4                  // Field regionStates:Lorg/apache/hadoop/hbase/master/assignment/RegionStates;
      50: aload         4
      52: invokevirtual #68                 // Method org/apache/hadoop/hbase/master/assignment/RegionStates.getOrCreateRegionStateNode:(Lorg/apache/hadoop/hbase/client/RegionInfo;)Lorg/apache/hadoop/hbase/master/assignment/RegionStateNode;
      55: astore        7
      57: aload         7
      59: getstatic     #431                // Field org/apache/hadoop/hbase/master/RegionState$State.SPLITTING_NEW:Lorg/apache/hadoop/hbase/master/RegionState$State;
      62: iconst_0
      63: anewarray     #73                 // class org/apache/hadoop/hbase/master/RegionState$State
      66: invokevirtual #74                 // Method org/apache/hadoop/hbase/master/assignment/RegionStateNode.setState:(Lorg/apache/hadoop/hbase/master/RegionState$State;[Lorg/apache/hadoop/hbase/master/RegionState$State;)Z
      69: pop
      70: aload_0
      71: getfield      #33                 // Field regionStateStore:Lorg/apache/hadoop/hbase/master/assignment/RegionStateStore;
      74: aload_1
      75: aload_3
      76: aload         4
      78: aload_2
      79: invokevirtual #432                // Method org/apache/hadoop/hbase/master/assignment/RegionStateStore.splitRegion:(Lorg/apache/hadoop/hbase/client/RegionInfo;Lorg/apache/hadoop/hbase/client/RegionInfo;Lorg/apache/hadoop/hbase/client/RegionInfo;Lorg/apache/hadoop/hbase/ServerName;)V
      82: aload_0
      83: aload_1
      84: invokespecial #433                // Method shouldAssignFavoredNodes:(Lorg/apache/hadoop/hbase/client/RegionInfo;)Z
      87: ifeq          122
      90: aload_0
      91: getfield      #32                 // Field master:Lorg/apache/hadoop/hbase/master/MasterServices;
      94: invokeinterface #142,  1          // InterfaceMethod org/apache/hadoop/hbase/master/MasterServices.getServerManager:()Lorg/apache/hadoop/hbase/master/ServerManager;
      99: invokevirtual #181                // Method org/apache/hadoop/hbase/master/ServerManager.getOnlineServersList:()Ljava/util/List;
     102: astore        8
     104: aload_0
     105: invokespecial #104                // Method getBalancer:()Lorg/apache/hadoop/hbase/master/LoadBalancer;
     108: checkcast     #434                // class org/apache/hadoop/hbase/favored/FavoredNodesPromoter
     111: aload         8
     113: aload_1
     114: aload_3
     115: aload         4
     117: invokeinterface #435,  5          // InterfaceMethod org/apache/hadoop/hbase/favored/FavoredNodesPromoter.generateFavoredNodesForDaughter:(Ljava/util/List;Lorg/apache/hadoop/hbase/client/RegionInfo;Lorg/apache/hadoop/hbase/client/RegionInfo;Lorg/apache/hadoop/hbase/client/RegionInfo;)V
     122: return

  public void markRegionAsMerged(org.apache.hadoop.hbase.client.RegionInfo, org.apache.hadoop.hbase.ServerName, org.apache.hadoop.hbase.client.RegionInfo, org.apache.hadoop.hbase.client.RegionInfo) throws java.io.IOException;
    Code:
       0: aload_0
       1: getfield      #4                  // Field regionStates:Lorg/apache/hadoop/hbase/master/assignment/RegionStates;
       4: aload_1
       5: invokevirtual #68                 // Method org/apache/hadoop/hbase/master/assignment/RegionStates.getOrCreateRegionStateNode:(Lorg/apache/hadoop/hbase/client/RegionInfo;)Lorg/apache/hadoop/hbase/master/assignment/RegionStateNode;
       8: astore        5
      10: aload         5
      12: getstatic     #436                // Field org/apache/hadoop/hbase/master/RegionState$State.MERGED:Lorg/apache/hadoop/hbase/master/RegionState$State;
      15: iconst_0
      16: anewarray     #73                 // class org/apache/hadoop/hbase/master/RegionState$State
      19: invokevirtual #74                 // Method org/apache/hadoop/hbase/master/assignment/RegionStateNode.setState:(Lorg/apache/hadoop/hbase/master/RegionState$State;[Lorg/apache/hadoop/hbase/master/RegionState$State;)Z
      22: pop
      23: aload_0
      24: getfield      #4                  // Field regionStates:Lorg/apache/hadoop/hbase/master/assignment/RegionStates;
      27: aload_3
      28: invokevirtual #231                // Method org/apache/hadoop/hbase/master/assignment/RegionStates.deleteRegion:(Lorg/apache/hadoop/hbase/client/RegionInfo;)V
      31: aload_0
      32: getfield      #4                  // Field regionStates:Lorg/apache/hadoop/hbase/master/assignment/RegionStates;
      35: aload         4
      37: invokevirtual #231                // Method org/apache/hadoop/hbase/master/assignment/RegionStates.deleteRegion:(Lorg/apache/hadoop/hbase/client/RegionInfo;)V
      40: aload_0
      41: getfield      #33                 // Field regionStateStore:Lorg/apache/hadoop/hbase/master/assignment/RegionStateStore;
      44: aload_1
      45: aload_3
      46: aload         4
      48: aload_2
      49: invokevirtual #437                // Method org/apache/hadoop/hbase/master/assignment/RegionStateStore.mergeRegions:(Lorg/apache/hadoop/hbase/client/RegionInfo;Lorg/apache/hadoop/hbase/client/RegionInfo;Lorg/apache/hadoop/hbase/client/RegionInfo;Lorg/apache/hadoop/hbase/ServerName;)V
      52: aload_0
      53: aload_1
      54: invokespecial #433                // Method shouldAssignFavoredNodes:(Lorg/apache/hadoop/hbase/client/RegionInfo;)Z
      57: ifeq          76
      60: aload_0
      61: invokespecial #104                // Method getBalancer:()Lorg/apache/hadoop/hbase/master/LoadBalancer;
      64: checkcast     #434                // class org/apache/hadoop/hbase/favored/FavoredNodesPromoter
      67: aload_1
      68: aload_3
      69: aload         4
      71: invokeinterface #438,  4          // InterfaceMethod org/apache/hadoop/hbase/favored/FavoredNodesPromoter.generateFavoredNodesForMergedRegion:(Lorg/apache/hadoop/hbase/client/RegionInfo;Lorg/apache/hadoop/hbase/client/RegionInfo;Lorg/apache/hadoop/hbase/client/RegionInfo;)V
      76: return

  protected void queueAssign(org.apache.hadoop.hbase.master.assignment.RegionStateNode);
    Code:
       0: aload_1
       1: invokevirtual #440                // Method org/apache/hadoop/hbase/master/assignment/RegionStateNode.getProcedureEvent:()Lorg/apache/hadoop/hbase/procedure2/ProcedureEvent;
       4: invokevirtual #89                 // Method org/apache/hadoop/hbase/procedure2/ProcedureEvent.suspend:()V
       7: aload_0
       8: getfield      #29                 // Field assignQueueLock:Ljava/util/concurrent/locks/ReentrantLock;
      11: invokevirtual #441                // Method java/util/concurrent/locks/ReentrantLock.lock:()V
      14: aload_0
      15: getfield      #2                  // Field pendingAssignQueue:Ljava/util/ArrayList;
      18: aload_1
      19: invokevirtual #442                // Method java/util/ArrayList.add:(Ljava/lang/Object;)Z
      22: pop
      23: aload_1
      24: invokevirtual #443                // Method org/apache/hadoop/hbase/master/assignment/RegionStateNode.isSystemTable:()Z
      27: ifne          55
      30: aload_0
      31: getfield      #2                  // Field pendingAssignQueue:Ljava/util/ArrayList;
      34: invokevirtual #228                // Method java/util/ArrayList.size:()I
      37: iconst_1
      38: if_icmpeq     55
      41: aload_0
      42: getfield      #2                  // Field pendingAssignQueue:Ljava/util/ArrayList;
      45: invokevirtual #228                // Method java/util/ArrayList.size:()I
      48: aload_0
      49: getfield      #49                 // Field assignDispatchWaitQueueMaxSize:I
      52: if_icmplt     64
      55: aload_0
      56: getfield      #31                 // Field assignQueueFullCond:Ljava/util/concurrent/locks/Condition;
      59: invokeinterface #444,  1          // InterfaceMethod java/util/concurrent/locks/Condition.signal:()V
      64: aload_0
      65: getfield      #29                 // Field assignQueueLock:Ljava/util/concurrent/locks/ReentrantLock;
      68: invokevirtual #445                // Method java/util/concurrent/locks/ReentrantLock.unlock:()V
      71: goto          84
      74: astore_2
      75: aload_0
      76: getfield      #29                 // Field assignQueueLock:Ljava/util/concurrent/locks/ReentrantLock;
      79: invokevirtual #445                // Method java/util/concurrent/locks/ReentrantLock.unlock:()V
      82: aload_2
      83: athrow
      84: return
    Exception table:
       from    to  target type
          14    64    74   any

  public java.util.List<org.apache.hadoop.hbase.ServerName> getExcludedServersForSystemTable();
    Code:
       0: aload_0
       1: getfield      #32                 // Field master:Lorg/apache/hadoop/hbase/master/MasterServices;
       4: invokeinterface #142,  1          // InterfaceMethod org/apache/hadoop/hbase/master/MasterServices.getServerManager:()Lorg/apache/hadoop/hbase/master/ServerManager;
       9: invokevirtual #181                // Method org/apache/hadoop/hbase/master/ServerManager.getOnlineServersList:()Ljava/util/List;
      12: invokeinterface #202,  1          // InterfaceMethod java/util/List.stream:()Ljava/util/stream/Stream;
      17: aload_0
      18: invokedynamic #515,  0            // InvokeDynamic #16:apply:(Lorg/apache/hadoop/hbase/master/assignment/AssignmentManager;)Ljava/util/function/Function;
      23: invokeinterface #204,  2          // InterfaceMethod java/util/stream/Stream.map:(Ljava/util/function/Function;)Ljava/util/stream/Stream;
      28: invokestatic  #328                // Method java/util/stream/Collectors.toList:()Ljava/util/stream/Collector;
      31: invokeinterface #329,  2          // InterfaceMethod java/util/stream/Stream.collect:(Ljava/util/stream/Collector;)Ljava/lang/Object;
      36: checkcast     #380                // class java/util/List
      39: astore_1
      40: aload_1
      41: invokeinterface #179,  1          // InterfaceMethod java/util/List.isEmpty:()Z
      46: ifeq          53
      49: invokestatic  #102                // Method java/util/Collections.emptyList:()Ljava/util/List;
      52: areturn
      53: aload_1
      54: invokedynamic #516,  0            // InvokeDynamic #17:compare:()Ljava/util/Comparator;
      59: invokestatic  #517                // Method java/util/Collections.max:(Ljava/util/Collection;Ljava/util/Comparator;)Ljava/lang/Object;
      62: checkcast     #406                // class org/apache/hadoop/hbase/util/Pair
      65: invokevirtual #518                // Method org/apache/hadoop/hbase/util/Pair.getSecond:()Ljava/lang/Object;
      68: checkcast     #519                // class java/lang/String
      71: astore_2
      72: aload_1
      73: invokeinterface #202,  1          // InterfaceMethod java/util/List.stream:()Ljava/util/stream/Stream;
      78: aload_2
      79: invokedynamic #520,  0            // InvokeDynamic #18:test:(Ljava/lang/String;)Ljava/util/function/Predicate;
      84: invokeinterface #220,  2          // InterfaceMethod java/util/stream/Stream.filter:(Ljava/util/function/Predicate;)Ljava/util/stream/Stream;
      89: invokedynamic #521,  0            // InvokeDynamic #19:apply:()Ljava/util/function/Function;
      94: invokeinterface #204,  2          // InterfaceMethod java/util/stream/Stream.map:(Ljava/util/function/Function;)Ljava/util/stream/Stream;
      99: invokestatic  #328                // Method java/util/stream/Collectors.toList:()Ljava/util/stream/Collector;
     102: invokeinterface #329,  2          // InterfaceMethod java/util/stream/Stream.collect:(Ljava/util/stream/Collector;)Ljava/lang/Object;
     107: checkcast     #380                // class java/util/List
     110: areturn

  org.apache.hadoop.hbase.master.MasterServices getMaster();
    Code:
       0: aload_0
       1: getfield      #32                 // Field master:Lorg/apache/hadoop/hbase/master/MasterServices;
       4: areturn

  static void access$000(org.apache.hadoop.hbase.master.assignment.AssignmentManager, org.apache.hadoop.hbase.client.RegionInfo);
    Code:
       0: aload_0
       1: aload_1
       2: invokespecial #7                  // Method handleRegionOverStuckWarningThreshold:(Lorg/apache/hadoop/hbase/client/RegionInfo;)V
       5: return

  static void access$100(org.apache.hadoop.hbase.master.assignment.AssignmentManager, org.apache.hadoop.hbase.master.assignment.AssignmentManager$RegionInTransitionStat);
    Code:
       0: aload_0
       1: aload_1
       2: invokespecial #6                  // Method updateRegionsInTransitionMetrics:(Lorg/apache/hadoop/hbase/master/assignment/AssignmentManager$RegionInTransitionStat;)V
       5: return

  static org.slf4j.Logger access$200();
    Code:
       0: getstatic     #5                  // Field LOG:Lorg/slf4j/Logger;
       3: areturn

  static org.apache.hadoop.hbase.master.assignment.RegionStates access$300(org.apache.hadoop.hbase.master.assignment.AssignmentManager);
    Code:
       0: aload_0
       1: getfield      #4                  // Field regionStates:Lorg/apache/hadoop/hbase/master/assignment/RegionStates;
       4: areturn

  static void access$400(org.apache.hadoop.hbase.master.assignment.AssignmentManager);
    Code:
       0: aload_0
       1: invokespecial #3                  // Method processAssignQueue:()V
       4: return

  static java.util.ArrayList access$500(org.apache.hadoop.hbase.master.assignment.AssignmentManager);
    Code:
       0: aload_0
       1: getfield      #2                  // Field pendingAssignQueue:Ljava/util/ArrayList;
       4: areturn

  static {};
    Code:
       0: ldc           #44                 // class org/apache/hadoop/hbase/master/assignment/AssignmentManager
       2: invokevirtual #541                // Method java/lang/Class.desiredAssertionStatus:()Z
       5: ifne          12
       8: iconst_1
       9: goto          13
      12: iconst_0
      13: putstatic     #128                // Field $assertionsDisabled:Z
      16: ldc           #44                 // class org/apache/hadoop/hbase/master/assignment/AssignmentManager
      18: invokestatic  #542                // Method org/slf4j/LoggerFactory.getLogger:(Ljava/lang/Class;)Lorg/slf4j/Logger;
      21: putstatic     #5                  // Field LOG:Lorg/slf4j/Logger;
      24: getstatic     #67                 // Field org/apache/hadoop/hbase/client/RegionInfoBuilder.FIRST_META_REGIONINFO:Lorg/apache/hadoop/hbase/client/RegionInfo;
      27: invokestatic  #543                // Method java/util/Collections.singleton:(Ljava/lang/Object;)Ljava/util/Set;
      30: putstatic     #122                // Field META_REGION_SET:Ljava/util/Set;
      33: iconst_2
      34: anewarray     #73                 // class org/apache/hadoop/hbase/master/RegionState$State
      37: dup
      38: iconst_0
      39: getstatic     #342                // Field org/apache/hadoop/hbase/master/RegionState$State.OPENING:Lorg/apache/hadoop/hbase/master/RegionState$State;
      42: aastore
      43: dup
      44: iconst_1
      45: getstatic     #78                 // Field org/apache/hadoop/hbase/master/RegionState$State.OPEN:Lorg/apache/hadoop/hbase/master/RegionState$State;
      48: aastore
      49: putstatic     #424                // Field STATES_EXPECTED_ON_OPEN:[Lorg/apache/hadoop/hbase/master/RegionState$State;
      52: iconst_4
      53: anewarray     #73                 // class org/apache/hadoop/hbase/master/RegionState$State
      56: dup
      57: iconst_0
      58: getstatic     #78                 // Field org/apache/hadoop/hbase/master/RegionState$State.OPEN:Lorg/apache/hadoop/hbase/master/RegionState$State;
      61: aastore
      62: dup
      63: iconst_1
      64: getstatic     #346                // Field org/apache/hadoop/hbase/master/RegionState$State.CLOSING:Lorg/apache/hadoop/hbase/master/RegionState$State;
      67: aastore
      68: dup
      69: iconst_2
      70: getstatic     #347                // Field org/apache/hadoop/hbase/master/RegionState$State.SPLITTING:Lorg/apache/hadoop/hbase/master/RegionState$State;
      73: aastore
      74: dup
      75: iconst_3
      76: getstatic     #544                // Field org/apache/hadoop/hbase/master/RegionState$State.MERGING:Lorg/apache/hadoop/hbase/master/RegionState$State;
      79: aastore
      80: putstatic     #423                // Field STATES_EXPECTED_ON_CLOSING:[Lorg/apache/hadoop/hbase/master/RegionState$State;
      83: iconst_2
      84: anewarray     #73                 // class org/apache/hadoop/hbase/master/RegionState$State
      87: dup
      88: iconst_0
      89: getstatic     #346                // Field org/apache/hadoop/hbase/master/RegionState$State.CLOSING:Lorg/apache/hadoop/hbase/master/RegionState$State;
      92: aastore
      93: dup
      94: iconst_1
      95: getstatic     #426                // Field org/apache/hadoop/hbase/master/RegionState$State.CLOSED:Lorg/apache/hadoop/hbase/master/RegionState$State;
      98: aastore
      99: putstatic     #427                // Field STATES_EXPECTED_ON_CLOSED:[Lorg/apache/hadoop/hbase/master/RegionState$State;
     102: iconst_2
     103: anewarray     #73                 // class org/apache/hadoop/hbase/master/RegionState$State
     106: dup
     107: iconst_0
     108: getstatic     #426                // Field org/apache/hadoop/hbase/master/RegionState$State.CLOSED:Lorg/apache/hadoop/hbase/master/RegionState$State;
     111: aastore
     112: dup
     113: iconst_1
     114: getstatic     #545                // Field org/apache/hadoop/hbase/master/RegionState$State.OFFLINE:Lorg/apache/hadoop/hbase/master/RegionState$State;
     117: aastore
     118: putstatic     #160                // Field STATES_EXPECTED_ON_ASSIGN:[Lorg/apache/hadoop/hbase/master/RegionState$State;
     121: iconst_1
     122: anewarray     #73                 // class org/apache/hadoop/hbase/master/RegionState$State
     125: dup
     126: iconst_0
     127: getstatic     #78                 // Field org/apache/hadoop/hbase/master/RegionState$State.OPEN:Lorg/apache/hadoop/hbase/master/RegionState$State;
     130: aastore
     131: putstatic     #171                // Field STATES_EXPECTED_ON_UNASSIGN_OR_MOVE:[Lorg/apache/hadoop/hbase/master/RegionState$State;
     134: return
}
