Compiled from "AsyncConnectionImpl.java"
class org.apache.hadoop.hbase.client.AsyncConnectionImpl$1 implements org.apache.hadoop.hbase.client.ClusterStatusListener$DeadServerHandler {
  final org.apache.hadoop.hbase.client.AsyncConnectionImpl this$0;

  org.apache.hadoop.hbase.client.AsyncConnectionImpl$1(org.apache.hadoop.hbase.client.AsyncConnectionImpl);
    Code:
       0: aload_0
       1: aload_1
       2: putfield      #1                  // Field this$0:Lorg/apache/hadoop/hbase/client/AsyncConnectionImpl;
       5: aload_0
       6: invokespecial #2                  // Method java/lang/Object."<init>":()V
       9: return

  public void newDead(org.apache.hadoop.hbase.ServerName);
    Code:
       0: aload_0
       1: getfield      #1                  // Field this$0:Lorg/apache/hadoop/hbase/client/AsyncConnectionImpl;
       4: invokestatic  #3                  // Method org/apache/hadoop/hbase/client/AsyncConnectionImpl.access$000:(Lorg/apache/hadoop/hbase/client/AsyncConnectionImpl;)Lorg/apache/hadoop/hbase/client/AsyncRegionLocator;
       7: aload_1
       8: invokevirtual #4                  // Method org/apache/hadoop/hbase/client/AsyncRegionLocator.clearCache:(Lorg/apache/hadoop/hbase/ServerName;)V
      11: aload_0
      12: getfield      #1                  // Field this$0:Lorg/apache/hadoop/hbase/client/AsyncConnectionImpl;
      15: invokestatic  #5                  // Method org/apache/hadoop/hbase/client/AsyncConnectionImpl.access$100:(Lorg/apache/hadoop/hbase/client/AsyncConnectionImpl;)Lorg/apache/hadoop/hbase/ipc/RpcClient;
      18: aload_1
      19: invokeinterface #6,  2            // InterfaceMethod org/apache/hadoop/hbase/ipc/RpcClient.cancelConnections:(Lorg/apache/hadoop/hbase/ServerName;)V
      24: return
}
