Compiled from "AsyncRequestFutureImpl.java"
final class org.apache.hadoop.hbase.client.AsyncRequestFutureImpl$SingleServerRequestRunnable implements java.lang.Runnable {
  final org.apache.hadoop.hbase.client.AsyncRequestFutureImpl this$0;

  org.apache.hadoop.hbase.client.AsyncRequestFutureImpl$SingleServerRequestRunnable(org.apache.hadoop.hbase.client.MultiAction, int, org.apache.hadoop.hbase.ServerName, java.util.Set<org.apache.hadoop.hbase.client.CancellableRegionServerCallable>);
    Code:
       0: aload_0
       1: aload_1
       2: putfield      #1                  // Field this$0:Lorg/apache/hadoop/hbase/client/AsyncRequestFutureImpl;
       5: aload_0
       6: invokespecial #2                  // Method java/lang/Object."<init>":()V
       9: aload_0
      10: aload_2
      11: putfield      #3                  // Field multiAction:Lorg/apache/hadoop/hbase/client/MultiAction;
      14: aload_0
      15: iload_3
      16: putfield      #4                  // Field numAttempt:I
      19: aload_0
      20: aload         4
      22: putfield      #5                  // Field server:Lorg/apache/hadoop/hbase/ServerName;
      25: aload_0
      26: aload         5
      28: putfield      #6                  // Field callsInProgress:Ljava/util/Set;
      31: return

  public void run();
    Code:
       0: aconst_null
       1: astore_1
       2: aload_0
       3: getfield      #1                  // Field this$0:Lorg/apache/hadoop/hbase/client/AsyncRequestFutureImpl;
       6: invokestatic  #7                  // Method org/apache/hadoop/hbase/client/AsyncRequestFutureImpl.access$1000:(Lorg/apache/hadoop/hbase/client/AsyncRequestFutureImpl;)Lorg/apache/hadoop/hbase/client/CancellableRegionServerCallable;
       9: astore_2
      10: aload_2
      11: ifnonnull     37
      14: aload_0
      15: getfield      #1                  // Field this$0:Lorg/apache/hadoop/hbase/client/AsyncRequestFutureImpl;
      18: aload_0
      19: getfield      #5                  // Field server:Lorg/apache/hadoop/hbase/ServerName;
      22: aload_0
      23: getfield      #1                  // Field this$0:Lorg/apache/hadoop/hbase/client/AsyncRequestFutureImpl;
      26: invokestatic  #8                  // Method org/apache/hadoop/hbase/client/AsyncRequestFutureImpl.access$1100:(Lorg/apache/hadoop/hbase/client/AsyncRequestFutureImpl;)Lorg/apache/hadoop/hbase/TableName;
      29: aload_0
      30: getfield      #3                  // Field multiAction:Lorg/apache/hadoop/hbase/client/MultiAction;
      33: invokestatic  #9                  // Method org/apache/hadoop/hbase/client/AsyncRequestFutureImpl.access$1200:(Lorg/apache/hadoop/hbase/client/AsyncRequestFutureImpl;Lorg/apache/hadoop/hbase/ServerName;Lorg/apache/hadoop/hbase/TableName;Lorg/apache/hadoop/hbase/client/MultiAction;)Lorg/apache/hadoop/hbase/client/MultiServerCallable;
      36: astore_2
      37: aload_0
      38: getfield      #1                  // Field this$0:Lorg/apache/hadoop/hbase/client/AsyncRequestFutureImpl;
      41: invokestatic  #10                 // Method org/apache/hadoop/hbase/client/AsyncRequestFutureImpl.access$000:(Lorg/apache/hadoop/hbase/client/AsyncRequestFutureImpl;)Lorg/apache/hadoop/hbase/client/AsyncProcess;
      44: aload_2
      45: aload_0
      46: getfield      #1                  // Field this$0:Lorg/apache/hadoop/hbase/client/AsyncRequestFutureImpl;
      49: invokestatic  #11                 // Method org/apache/hadoop/hbase/client/AsyncRequestFutureImpl.access$1300:(Lorg/apache/hadoop/hbase/client/AsyncRequestFutureImpl;)I
      52: invokevirtual #12                 // Method org/apache/hadoop/hbase/client/AsyncProcess.createCaller:(Lorg/apache/hadoop/hbase/client/CancellableRegionServerCallable;I)Lorg/apache/hadoop/hbase/client/RpcRetryingCaller;
      55: astore_3
      56: aload_0
      57: getfield      #6                  // Field callsInProgress:Ljava/util/Set;
      60: ifnull        74
      63: aload_0
      64: getfield      #6                  // Field callsInProgress:Ljava/util/Set;
      67: aload_2
      68: invokeinterface #13,  2           // InterfaceMethod java/util/Set.add:(Ljava/lang/Object;)Z
      73: pop
      74: aload_3
      75: aload_2
      76: aload_0
      77: getfield      #1                  // Field this$0:Lorg/apache/hadoop/hbase/client/AsyncRequestFutureImpl;
      80: invokestatic  #14                 // Method org/apache/hadoop/hbase/client/AsyncRequestFutureImpl.access$1400:(Lorg/apache/hadoop/hbase/client/AsyncRequestFutureImpl;)I
      83: invokeinterface #15,  3           // InterfaceMethod org/apache/hadoop/hbase/client/RpcRetryingCaller.callWithoutRetries:(Lorg/apache/hadoop/hbase/client/RetryingCallable;I)Ljava/lang/Object;
      88: checkcast     #16                 // class org/apache/hadoop/hbase/client/AbstractResponse
      91: astore_1
      92: aload_1
      93: ifnonnull     144
      96: aload_0
      97: getfield      #1                  // Field this$0:Lorg/apache/hadoop/hbase/client/AsyncRequestFutureImpl;
     100: invokestatic  #10                 // Method org/apache/hadoop/hbase/client/AsyncRequestFutureImpl.access$000:(Lorg/apache/hadoop/hbase/client/AsyncRequestFutureImpl;)Lorg/apache/hadoop/hbase/client/AsyncProcess;
     103: aload_0
     104: getfield      #3                  // Field multiAction:Lorg/apache/hadoop/hbase/client/MultiAction;
     107: invokevirtual #17                 // Method org/apache/hadoop/hbase/client/MultiAction.getRegions:()Ljava/util/Set;
     110: aload_0
     111: getfield      #5                  // Field server:Lorg/apache/hadoop/hbase/ServerName;
     114: invokevirtual #18                 // Method org/apache/hadoop/hbase/client/AsyncProcess.decTaskCounters:(Ljava/util/Collection;Lorg/apache/hadoop/hbase/ServerName;)V
     117: aload_0
     118: getfield      #6                  // Field callsInProgress:Ljava/util/Set;
     121: ifnull        143
     124: aload_2
     125: ifnull        143
     128: aload_1
     129: ifnull        143
     132: aload_0
     133: getfield      #6                  // Field callsInProgress:Ljava/util/Set;
     136: aload_2
     137: invokeinterface #19,  2           // InterfaceMethod java/util/Set.remove:(Ljava/lang/Object;)Z
     142: pop
     143: return
     144: goto          354
     147: astore        4
     149: aload_0
     150: getfield      #1                  // Field this$0:Lorg/apache/hadoop/hbase/client/AsyncRequestFutureImpl;
     153: aload_0
     154: getfield      #3                  // Field multiAction:Lorg/apache/hadoop/hbase/client/MultiAction;
     157: aload_0
     158: getfield      #5                  // Field server:Lorg/apache/hadoop/hbase/ServerName;
     161: aload_0
     162: getfield      #4                  // Field numAttempt:I
     165: aload         4
     167: invokestatic  #21                 // Method org/apache/hadoop/hbase/client/AsyncRequestFutureImpl.access$1500:(Lorg/apache/hadoop/hbase/client/AsyncRequestFutureImpl;Lorg/apache/hadoop/hbase/client/MultiAction;Lorg/apache/hadoop/hbase/ServerName;ILjava/lang/Throwable;)V
     170: aload_0
     171: getfield      #1                  // Field this$0:Lorg/apache/hadoop/hbase/client/AsyncRequestFutureImpl;
     174: invokestatic  #10                 // Method org/apache/hadoop/hbase/client/AsyncRequestFutureImpl.access$000:(Lorg/apache/hadoop/hbase/client/AsyncRequestFutureImpl;)Lorg/apache/hadoop/hbase/client/AsyncProcess;
     177: aload_0
     178: getfield      #3                  // Field multiAction:Lorg/apache/hadoop/hbase/client/MultiAction;
     181: invokevirtual #17                 // Method org/apache/hadoop/hbase/client/MultiAction.getRegions:()Ljava/util/Set;
     184: aload_0
     185: getfield      #5                  // Field server:Lorg/apache/hadoop/hbase/ServerName;
     188: invokevirtual #18                 // Method org/apache/hadoop/hbase/client/AsyncProcess.decTaskCounters:(Ljava/util/Collection;Lorg/apache/hadoop/hbase/ServerName;)V
     191: aload_0
     192: getfield      #6                  // Field callsInProgress:Ljava/util/Set;
     195: ifnull        217
     198: aload_2
     199: ifnull        217
     202: aload_1
     203: ifnull        217
     206: aload_0
     207: getfield      #6                  // Field callsInProgress:Ljava/util/Set;
     210: aload_2
     211: invokeinterface #19,  2           // InterfaceMethod java/util/Set.remove:(Ljava/lang/Object;)Z
     216: pop
     217: return
     218: astore        4
     220: invokestatic  #23                 // Method org/apache/hadoop/hbase/client/AsyncRequestFutureImpl.access$200:()Lorg/slf4j/Logger;
     223: new           #24                 // class java/lang/StringBuilder
     226: dup
     227: invokespecial #25                 // Method java/lang/StringBuilder."<init>":()V
     230: ldc           #26                 // String id=
     232: invokevirtual #27                 // Method java/lang/StringBuilder.append:(Ljava/lang/String;)Ljava/lang/StringBuilder;
     235: aload_0
     236: getfield      #1                  // Field this$0:Lorg/apache/hadoop/hbase/client/AsyncRequestFutureImpl;
     239: invokestatic  #10                 // Method org/apache/hadoop/hbase/client/AsyncRequestFutureImpl.access$000:(Lorg/apache/hadoop/hbase/client/AsyncRequestFutureImpl;)Lorg/apache/hadoop/hbase/client/AsyncProcess;
     242: getfield      #28                 // Field org/apache/hadoop/hbase/client/AsyncProcess.id:J
     245: invokevirtual #29                 // Method java/lang/StringBuilder.append:(J)Ljava/lang/StringBuilder;
     248: ldc           #30                 // String , caught throwable. Unexpected. Retrying. Server=
     250: invokevirtual #27                 // Method java/lang/StringBuilder.append:(Ljava/lang/String;)Ljava/lang/StringBuilder;
     253: aload_0
     254: getfield      #5                  // Field server:Lorg/apache/hadoop/hbase/ServerName;
     257: invokevirtual #31                 // Method java/lang/StringBuilder.append:(Ljava/lang/Object;)Ljava/lang/StringBuilder;
     260: ldc           #32                 // String , tableName=
     262: invokevirtual #27                 // Method java/lang/StringBuilder.append:(Ljava/lang/String;)Ljava/lang/StringBuilder;
     265: aload_0
     266: getfield      #1                  // Field this$0:Lorg/apache/hadoop/hbase/client/AsyncRequestFutureImpl;
     269: invokestatic  #8                  // Method org/apache/hadoop/hbase/client/AsyncRequestFutureImpl.access$1100:(Lorg/apache/hadoop/hbase/client/AsyncRequestFutureImpl;)Lorg/apache/hadoop/hbase/TableName;
     272: invokevirtual #31                 // Method java/lang/StringBuilder.append:(Ljava/lang/Object;)Ljava/lang/StringBuilder;
     275: invokevirtual #33                 // Method java/lang/StringBuilder.toString:()Ljava/lang/String;
     278: aload         4
     280: invokeinterface #34,  3           // InterfaceMethod org/slf4j/Logger.error:(Ljava/lang/String;Ljava/lang/Throwable;)V
     285: aload_0
     286: getfield      #1                  // Field this$0:Lorg/apache/hadoop/hbase/client/AsyncRequestFutureImpl;
     289: aload_0
     290: getfield      #3                  // Field multiAction:Lorg/apache/hadoop/hbase/client/MultiAction;
     293: aload_0
     294: getfield      #5                  // Field server:Lorg/apache/hadoop/hbase/ServerName;
     297: aload_0
     298: getfield      #4                  // Field numAttempt:I
     301: aload         4
     303: invokestatic  #21                 // Method org/apache/hadoop/hbase/client/AsyncRequestFutureImpl.access$1500:(Lorg/apache/hadoop/hbase/client/AsyncRequestFutureImpl;Lorg/apache/hadoop/hbase/client/MultiAction;Lorg/apache/hadoop/hbase/ServerName;ILjava/lang/Throwable;)V
     306: aload_0
     307: getfield      #1                  // Field this$0:Lorg/apache/hadoop/hbase/client/AsyncRequestFutureImpl;
     310: invokestatic  #10                 // Method org/apache/hadoop/hbase/client/AsyncRequestFutureImpl.access$000:(Lorg/apache/hadoop/hbase/client/AsyncRequestFutureImpl;)Lorg/apache/hadoop/hbase/client/AsyncProcess;
     313: aload_0
     314: getfield      #3                  // Field multiAction:Lorg/apache/hadoop/hbase/client/MultiAction;
     317: invokevirtual #17                 // Method org/apache/hadoop/hbase/client/MultiAction.getRegions:()Ljava/util/Set;
     320: aload_0
     321: getfield      #5                  // Field server:Lorg/apache/hadoop/hbase/ServerName;
     324: invokevirtual #18                 // Method org/apache/hadoop/hbase/client/AsyncProcess.decTaskCounters:(Ljava/util/Collection;Lorg/apache/hadoop/hbase/ServerName;)V
     327: aload_0
     328: getfield      #6                  // Field callsInProgress:Ljava/util/Set;
     331: ifnull        353
     334: aload_2
     335: ifnull        353
     338: aload_1
     339: ifnull        353
     342: aload_0
     343: getfield      #6                  // Field callsInProgress:Ljava/util/Set;
     346: aload_2
     347: invokeinterface #19,  2           // InterfaceMethod java/util/Set.remove:(Ljava/lang/Object;)Z
     352: pop
     353: return
     354: aload_1
     355: invokevirtual #35                 // Method org/apache/hadoop/hbase/client/AbstractResponse.type:()Lorg/apache/hadoop/hbase/client/AbstractResponse$ResponseType;
     358: getstatic     #36                 // Field org/apache/hadoop/hbase/client/AbstractResponse$ResponseType.MULTI:Lorg/apache/hadoop/hbase/client/AbstractResponse$ResponseType;
     361: if_acmpne     390
     364: aload_0
     365: getfield      #1                  // Field this$0:Lorg/apache/hadoop/hbase/client/AsyncRequestFutureImpl;
     368: aload_0
     369: getfield      #3                  // Field multiAction:Lorg/apache/hadoop/hbase/client/MultiAction;
     372: aload_0
     373: getfield      #5                  // Field server:Lorg/apache/hadoop/hbase/ServerName;
     376: aload_1
     377: checkcast     #37                 // class org/apache/hadoop/hbase/client/MultiResponse
     380: aload_0
     381: getfield      #4                  // Field numAttempt:I
     384: invokestatic  #38                 // Method org/apache/hadoop/hbase/client/AsyncRequestFutureImpl.access$1600:(Lorg/apache/hadoop/hbase/client/AsyncRequestFutureImpl;Lorg/apache/hadoop/hbase/client/MultiAction;Lorg/apache/hadoop/hbase/ServerName;Lorg/apache/hadoop/hbase/client/MultiResponse;I)V
     387: goto          427
     390: aload_0
     391: getfield      #1                  // Field this$0:Lorg/apache/hadoop/hbase/client/AsyncRequestFutureImpl;
     394: invokestatic  #39                 // Method org/apache/hadoop/hbase/client/AsyncRequestFutureImpl.access$400:(Lorg/apache/hadoop/hbase/client/AsyncRequestFutureImpl;)[Ljava/lang/Object;
     397: ifnull        419
     400: aload_1
     401: checkcast     #40                 // class org/apache/hadoop/hbase/client/SingleResponse
     404: astore        4
     406: aload_0
     407: getfield      #1                  // Field this$0:Lorg/apache/hadoop/hbase/client/AsyncRequestFutureImpl;
     410: iconst_0
     411: aload         4
     413: invokevirtual #41                 // Method org/apache/hadoop/hbase/client/SingleResponse.getEntry:()Lorg/apache/hadoop/hbase/client/SingleResponse$Entry;
     416: invokestatic  #42                 // Method org/apache/hadoop/hbase/client/AsyncRequestFutureImpl.access$700:(Lorg/apache/hadoop/hbase/client/AsyncRequestFutureImpl;ILjava/lang/Object;)V
     419: aload_0
     420: getfield      #1                  // Field this$0:Lorg/apache/hadoop/hbase/client/AsyncRequestFutureImpl;
     423: iconst_1
     424: invokestatic  #43                 // Method org/apache/hadoop/hbase/client/AsyncRequestFutureImpl.access$1700:(Lorg/apache/hadoop/hbase/client/AsyncRequestFutureImpl;I)V
     427: aload_0
     428: getfield      #1                  // Field this$0:Lorg/apache/hadoop/hbase/client/AsyncRequestFutureImpl;
     431: invokestatic  #10                 // Method org/apache/hadoop/hbase/client/AsyncRequestFutureImpl.access$000:(Lorg/apache/hadoop/hbase/client/AsyncRequestFutureImpl;)Lorg/apache/hadoop/hbase/client/AsyncProcess;
     434: aload_0
     435: getfield      #3                  // Field multiAction:Lorg/apache/hadoop/hbase/client/MultiAction;
     438: invokevirtual #17                 // Method org/apache/hadoop/hbase/client/MultiAction.getRegions:()Ljava/util/Set;
     441: aload_0
     442: getfield      #5                  // Field server:Lorg/apache/hadoop/hbase/ServerName;
     445: invokevirtual #18                 // Method org/apache/hadoop/hbase/client/AsyncProcess.decTaskCounters:(Ljava/util/Collection;Lorg/apache/hadoop/hbase/ServerName;)V
     448: aload_0
     449: getfield      #6                  // Field callsInProgress:Ljava/util/Set;
     452: ifnull        603
     455: aload_2
     456: ifnull        603
     459: aload_1
     460: ifnull        603
     463: aload_0
     464: getfield      #6                  // Field callsInProgress:Ljava/util/Set;
     467: aload_2
     468: invokeinterface #19,  2           // InterfaceMethod java/util/Set.remove:(Ljava/lang/Object;)Z
     473: pop
     474: goto          603
     477: astore_3
     478: invokestatic  #23                 // Method org/apache/hadoop/hbase/client/AsyncRequestFutureImpl.access$200:()Lorg/slf4j/Logger;
     481: new           #24                 // class java/lang/StringBuilder
     484: dup
     485: invokespecial #25                 // Method java/lang/StringBuilder."<init>":()V
     488: ldc           #26                 // String id=
     490: invokevirtual #27                 // Method java/lang/StringBuilder.append:(Ljava/lang/String;)Ljava/lang/StringBuilder;
     493: aload_0
     494: getfield      #1                  // Field this$0:Lorg/apache/hadoop/hbase/client/AsyncRequestFutureImpl;
     497: invokestatic  #10                 // Method org/apache/hadoop/hbase/client/AsyncRequestFutureImpl.access$000:(Lorg/apache/hadoop/hbase/client/AsyncRequestFutureImpl;)Lorg/apache/hadoop/hbase/client/AsyncProcess;
     500: getfield      #28                 // Field org/apache/hadoop/hbase/client/AsyncProcess.id:J
     503: invokevirtual #29                 // Method java/lang/StringBuilder.append:(J)Ljava/lang/StringBuilder;
     506: ldc           #44                 // String  error for
     508: invokevirtual #27                 // Method java/lang/StringBuilder.append:(Ljava/lang/String;)Ljava/lang/StringBuilder;
     511: aload_0
     512: getfield      #1                  // Field this$0:Lorg/apache/hadoop/hbase/client/AsyncRequestFutureImpl;
     515: invokestatic  #8                  // Method org/apache/hadoop/hbase/client/AsyncRequestFutureImpl.access$1100:(Lorg/apache/hadoop/hbase/client/AsyncRequestFutureImpl;)Lorg/apache/hadoop/hbase/TableName;
     518: invokevirtual #31                 // Method java/lang/StringBuilder.append:(Ljava/lang/Object;)Ljava/lang/StringBuilder;
     521: ldc           #45                 // String  processing
     523: invokevirtual #27                 // Method java/lang/StringBuilder.append:(Ljava/lang/String;)Ljava/lang/StringBuilder;
     526: aload_0
     527: getfield      #5                  // Field server:Lorg/apache/hadoop/hbase/ServerName;
     530: invokevirtual #31                 // Method java/lang/StringBuilder.append:(Ljava/lang/Object;)Ljava/lang/StringBuilder;
     533: invokevirtual #33                 // Method java/lang/StringBuilder.toString:()Ljava/lang/String;
     536: aload_3
     537: invokeinterface #34,  3           // InterfaceMethod org/slf4j/Logger.error:(Ljava/lang/String;Ljava/lang/Throwable;)V
     542: new           #46                 // class java/lang/RuntimeException
     545: dup
     546: aload_3
     547: invokespecial #47                 // Method java/lang/RuntimeException."<init>":(Ljava/lang/Throwable;)V
     550: athrow
     551: astore        5
     553: aload_0
     554: getfield      #1                  // Field this$0:Lorg/apache/hadoop/hbase/client/AsyncRequestFutureImpl;
     557: invokestatic  #10                 // Method org/apache/hadoop/hbase/client/AsyncRequestFutureImpl.access$000:(Lorg/apache/hadoop/hbase/client/AsyncRequestFutureImpl;)Lorg/apache/hadoop/hbase/client/AsyncProcess;
     560: aload_0
     561: getfield      #3                  // Field multiAction:Lorg/apache/hadoop/hbase/client/MultiAction;
     564: invokevirtual #17                 // Method org/apache/hadoop/hbase/client/MultiAction.getRegions:()Ljava/util/Set;
     567: aload_0
     568: getfield      #5                  // Field server:Lorg/apache/hadoop/hbase/ServerName;
     571: invokevirtual #18                 // Method org/apache/hadoop/hbase/client/AsyncProcess.decTaskCounters:(Ljava/util/Collection;Lorg/apache/hadoop/hbase/ServerName;)V
     574: aload_0
     575: getfield      #6                  // Field callsInProgress:Ljava/util/Set;
     578: ifnull        600
     581: aload_2
     582: ifnull        600
     585: aload_1
     586: ifnull        600
     589: aload_0
     590: getfield      #6                  // Field callsInProgress:Ljava/util/Set;
     593: aload_2
     594: invokeinterface #19,  2           // InterfaceMethod java/util/Set.remove:(Ljava/lang/Object;)Z
     599: pop
     600: aload         5
     602: athrow
     603: return
    Exception table:
       from    to  target type
          56    96   147   Class java/io/IOException
          56    96   218   Class java/lang/Throwable
          10    96   477   Class java/lang/Throwable
         144   170   477   Class java/lang/Throwable
         218   306   477   Class java/lang/Throwable
         354   427   477   Class java/lang/Throwable
          10    96   551   any
         144   170   551   any
         218   306   551   any
         354   427   551   any
         477   553   551   any
}
