Compiled from "AsyncProcessTask.java"
public class org.apache.hadoop.hbase.client.AsyncProcessTask<T> {
  public static <T> org.apache.hadoop.hbase.client.AsyncProcessTask$Builder<T> newBuilder(org.apache.hadoop.hbase.client.coprocessor.Batch$Callback<T>);
    Code:
       0: new           #1                  // class org/apache/hadoop/hbase/client/AsyncProcessTask$Builder
       3: dup
       4: aload_0
       5: aconst_null
       6: invokespecial #2                  // Method org/apache/hadoop/hbase/client/AsyncProcessTask$Builder."<init>":(Lorg/apache/hadoop/hbase/client/coprocessor/Batch$Callback;Lorg/apache/hadoop/hbase/client/AsyncProcessTask$1;)V
       9: areturn

  public static org.apache.hadoop.hbase.client.AsyncProcessTask$Builder newBuilder();
    Code:
       0: new           #1                  // class org/apache/hadoop/hbase/client/AsyncProcessTask$Builder
       3: dup
       4: aconst_null
       5: invokespecial #3                  // Method org/apache/hadoop/hbase/client/AsyncProcessTask$Builder."<init>":(Lorg/apache/hadoop/hbase/client/AsyncProcessTask$1;)V
       8: areturn

  org.apache.hadoop.hbase.client.AsyncProcessTask(org.apache.hadoop.hbase.client.AsyncProcessTask<T>);
    Code:
       0: aload_0
       1: aload_1
       2: invokevirtual #4                  // Method getPool:()Ljava/util/concurrent/ExecutorService;
       5: aload_1
       6: invokevirtual #5                  // Method getTableName:()Lorg/apache/hadoop/hbase/TableName;
       9: aload_1
      10: invokevirtual #6                  // Method getRowAccess:()Lorg/apache/hadoop/hbase/client/RowAccess;
      13: aload_1
      14: invokevirtual #7                  // Method getSubmittedRows:()Lorg/apache/hadoop/hbase/client/AsyncProcessTask$SubmittedRows;
      17: aload_1
      18: invokevirtual #8                  // Method getCallback:()Lorg/apache/hadoop/hbase/client/coprocessor/Batch$Callback;
      21: aload_1
      22: invokevirtual #9                  // Method getCallable:()Lorg/apache/hadoop/hbase/client/CancellableRegionServerCallable;
      25: aload_1
      26: invokevirtual #10                 // Method getNeedResults:()Z
      29: aload_1
      30: invokevirtual #11                 // Method getRpcTimeout:()I
      33: aload_1
      34: invokevirtual #12                 // Method getOperationTimeout:()I
      37: aload_1
      38: invokevirtual #13                 // Method getResults:()[Ljava/lang/Object;
      41: invokespecial #14                 // Method "<init>":(Ljava/util/concurrent/ExecutorService;Lorg/apache/hadoop/hbase/TableName;Lorg/apache/hadoop/hbase/client/RowAccess;Lorg/apache/hadoop/hbase/client/AsyncProcessTask$SubmittedRows;Lorg/apache/hadoop/hbase/client/coprocessor/Batch$Callback;Lorg/apache/hadoop/hbase/client/CancellableRegionServerCallable;ZII[Ljava/lang/Object;)V
      44: return

  org.apache.hadoop.hbase.client.AsyncProcessTask(java.util.concurrent.ExecutorService, org.apache.hadoop.hbase.TableName, org.apache.hadoop.hbase.client.RowAccess<? extends org.apache.hadoop.hbase.client.Row>, org.apache.hadoop.hbase.client.AsyncProcessTask$SubmittedRows, org.apache.hadoop.hbase.client.coprocessor.Batch$Callback<T>, org.apache.hadoop.hbase.client.CancellableRegionServerCallable, boolean, int, int, java.lang.Object[]);
    Code:
       0: aload_0
       1: invokespecial #15                 // Method java/lang/Object."<init>":()V
       4: aload_0
       5: aload_1
       6: putfield      #16                 // Field pool:Ljava/util/concurrent/ExecutorService;
       9: aload_0
      10: aload_2
      11: putfield      #17                 // Field tableName:Lorg/apache/hadoop/hbase/TableName;
      14: aload_0
      15: aload_3
      16: putfield      #18                 // Field rows:Lorg/apache/hadoop/hbase/client/RowAccess;
      19: aload_0
      20: aload         4
      22: putfield      #19                 // Field submittedRows:Lorg/apache/hadoop/hbase/client/AsyncProcessTask$SubmittedRows;
      25: aload_0
      26: aload         5
      28: putfield      #20                 // Field callback:Lorg/apache/hadoop/hbase/client/coprocessor/Batch$Callback;
      31: aload_0
      32: aload         6
      34: putfield      #21                 // Field callable:Lorg/apache/hadoop/hbase/client/CancellableRegionServerCallable;
      37: aload_0
      38: iload         7
      40: putfield      #22                 // Field needResults:Z
      43: aload_0
      44: iload         8
      46: putfield      #23                 // Field rpcTimeout:I
      49: aload_0
      50: iload         9
      52: putfield      #24                 // Field operationTimeout:I
      55: aload_0
      56: aload         10
      58: putfield      #25                 // Field results:[Ljava/lang/Object;
      61: return

  public int getOperationTimeout();
    Code:
       0: aload_0
       1: getfield      #24                 // Field operationTimeout:I
       4: ireturn

  public java.util.concurrent.ExecutorService getPool();
    Code:
       0: aload_0
       1: getfield      #16                 // Field pool:Ljava/util/concurrent/ExecutorService;
       4: areturn

  public org.apache.hadoop.hbase.TableName getTableName();
    Code:
       0: aload_0
       1: getfield      #17                 // Field tableName:Lorg/apache/hadoop/hbase/TableName;
       4: areturn

  public org.apache.hadoop.hbase.client.RowAccess<? extends org.apache.hadoop.hbase.client.Row> getRowAccess();
    Code:
       0: aload_0
       1: getfield      #18                 // Field rows:Lorg/apache/hadoop/hbase/client/RowAccess;
       4: areturn

  public org.apache.hadoop.hbase.client.AsyncProcessTask$SubmittedRows getSubmittedRows();
    Code:
       0: aload_0
       1: getfield      #19                 // Field submittedRows:Lorg/apache/hadoop/hbase/client/AsyncProcessTask$SubmittedRows;
       4: areturn

  public org.apache.hadoop.hbase.client.coprocessor.Batch$Callback<T> getCallback();
    Code:
       0: aload_0
       1: getfield      #20                 // Field callback:Lorg/apache/hadoop/hbase/client/coprocessor/Batch$Callback;
       4: areturn

  org.apache.hadoop.hbase.client.CancellableRegionServerCallable getCallable();
    Code:
       0: aload_0
       1: getfield      #21                 // Field callable:Lorg/apache/hadoop/hbase/client/CancellableRegionServerCallable;
       4: areturn

  java.lang.Object[] getResults();
    Code:
       0: aload_0
       1: getfield      #25                 // Field results:[Ljava/lang/Object;
       4: areturn

  public boolean getNeedResults();
    Code:
       0: aload_0
       1: getfield      #22                 // Field needResults:Z
       4: ireturn

  public int getRpcTimeout();
    Code:
       0: aload_0
       1: getfield      #23                 // Field rpcTimeout:I
       4: ireturn
}
