Compiled from "AsyncRpcRetryingCallerFactory.java"
public class org.apache.hadoop.hbase.client.AsyncRpcRetryingCallerFactory$SingleRequestCallerBuilder<T> extends org.apache.hadoop.hbase.client.AsyncRpcRetryingCallerFactory$BuilderBase {
  final org.apache.hadoop.hbase.client.AsyncRpcRetryingCallerFactory this$0;

  public org.apache.hadoop.hbase.client.AsyncRpcRetryingCallerFactory$SingleRequestCallerBuilder(org.apache.hadoop.hbase.client.AsyncRpcRetryingCallerFactory);
    Code:
       0: aload_0
       1: aload_1
       2: putfield      #2                  // Field this$0:Lorg/apache/hadoop/hbase/client/AsyncRpcRetryingCallerFactory;
       5: aload_0
       6: aload_1
       7: aconst_null
       8: invokespecial #3                  // Method org/apache/hadoop/hbase/client/AsyncRpcRetryingCallerFactory$BuilderBase."<init>":(Lorg/apache/hadoop/hbase/client/AsyncRpcRetryingCallerFactory;Lorg/apache/hadoop/hbase/client/AsyncRpcRetryingCallerFactory$1;)V
      11: aload_0
      12: ldc2_w        #4                  // long -1l
      15: putfield      #6                  // Field operationTimeoutNs:J
      18: aload_0
      19: ldc2_w        #4                  // long -1l
      22: putfield      #7                  // Field rpcTimeoutNs:J
      25: aload_0
      26: getstatic     #8                  // Field org/apache/hadoop/hbase/client/RegionLocateType.CURRENT:Lorg/apache/hadoop/hbase/client/RegionLocateType;
      29: putfield      #9                  // Field locateType:Lorg/apache/hadoop/hbase/client/RegionLocateType;
      32: aload_0
      33: iconst_0
      34: putfield      #11                 // Field replicaId:I
      37: aload_0
      38: iconst_m1
      39: putfield      #12                 // Field priority:I
      42: return

  public org.apache.hadoop.hbase.client.AsyncRpcRetryingCallerFactory$SingleRequestCallerBuilder<T> table(org.apache.hadoop.hbase.TableName);
    Code:
       0: aload_0
       1: aload_1
       2: putfield      #13                 // Field tableName:Lorg/apache/hadoop/hbase/TableName;
       5: aload_0
       6: areturn

  public org.apache.hadoop.hbase.client.AsyncRpcRetryingCallerFactory$SingleRequestCallerBuilder<T> row(byte[]);
    Code:
       0: aload_0
       1: aload_1
       2: putfield      #14                 // Field row:[B
       5: aload_0
       6: areturn

  public org.apache.hadoop.hbase.client.AsyncRpcRetryingCallerFactory$SingleRequestCallerBuilder<T> action(org.apache.hadoop.hbase.client.AsyncSingleRequestRpcRetryingCaller$Callable<T>);
    Code:
       0: aload_0
       1: aload_1
       2: putfield      #15                 // Field callable:Lorg/apache/hadoop/hbase/client/AsyncSingleRequestRpcRetryingCaller$Callable;
       5: aload_0
       6: areturn

  public org.apache.hadoop.hbase.client.AsyncRpcRetryingCallerFactory$SingleRequestCallerBuilder<T> operationTimeout(long, java.util.concurrent.TimeUnit);
    Code:
       0: aload_0
       1: aload_3
       2: lload_1
       3: invokevirtual #16                 // Method java/util/concurrent/TimeUnit.toNanos:(J)J
       6: putfield      #6                  // Field operationTimeoutNs:J
       9: aload_0
      10: areturn

  public org.apache.hadoop.hbase.client.AsyncRpcRetryingCallerFactory$SingleRequestCallerBuilder<T> rpcTimeout(long, java.util.concurrent.TimeUnit);
    Code:
       0: aload_0
       1: aload_3
       2: lload_1
       3: invokevirtual #16                 // Method java/util/concurrent/TimeUnit.toNanos:(J)J
       6: putfield      #7                  // Field rpcTimeoutNs:J
       9: aload_0
      10: areturn

  public org.apache.hadoop.hbase.client.AsyncRpcRetryingCallerFactory$SingleRequestCallerBuilder<T> locateType(org.apache.hadoop.hbase.client.RegionLocateType);
    Code:
       0: aload_0
       1: aload_1
       2: putfield      #9                  // Field locateType:Lorg/apache/hadoop/hbase/client/RegionLocateType;
       5: aload_0
       6: areturn

  public org.apache.hadoop.hbase.client.AsyncRpcRetryingCallerFactory$SingleRequestCallerBuilder<T> pause(long, java.util.concurrent.TimeUnit);
    Code:
       0: aload_0
       1: aload_3
       2: lload_1
       3: invokevirtual #16                 // Method java/util/concurrent/TimeUnit.toNanos:(J)J
       6: putfield      #17                 // Field pauseNs:J
       9: aload_0
      10: areturn

  public org.apache.hadoop.hbase.client.AsyncRpcRetryingCallerFactory$SingleRequestCallerBuilder<T> pauseForCQTBE(long, java.util.concurrent.TimeUnit);
    Code:
       0: aload_0
       1: aload_3
       2: lload_1
       3: invokevirtual #16                 // Method java/util/concurrent/TimeUnit.toNanos:(J)J
       6: putfield      #18                 // Field pauseForCQTBENs:J
       9: aload_0
      10: areturn

  public org.apache.hadoop.hbase.client.AsyncRpcRetryingCallerFactory$SingleRequestCallerBuilder<T> maxAttempts(int);
    Code:
       0: aload_0
       1: iload_1
       2: putfield      #19                 // Field maxAttempts:I
       5: aload_0
       6: areturn

  public org.apache.hadoop.hbase.client.AsyncRpcRetryingCallerFactory$SingleRequestCallerBuilder<T> startLogErrorsCnt(int);
    Code:
       0: aload_0
       1: iload_1
       2: putfield      #20                 // Field startLogErrorsCnt:I
       5: aload_0
       6: areturn

  public org.apache.hadoop.hbase.client.AsyncRpcRetryingCallerFactory$SingleRequestCallerBuilder<T> replicaId(int);
    Code:
       0: aload_0
       1: iload_1
       2: putfield      #11                 // Field replicaId:I
       5: aload_0
       6: areturn

  public org.apache.hadoop.hbase.client.AsyncRpcRetryingCallerFactory$SingleRequestCallerBuilder<T> priority(int);
    Code:
       0: aload_0
       1: iload_1
       2: putfield      #12                 // Field priority:I
       5: aload_0
       6: areturn

  public org.apache.hadoop.hbase.client.AsyncSingleRequestRpcRetryingCaller<T> build();
    Code:
       0: aload_0
       1: invokespecial #29                 // Method preCheck:()V
       4: new           #30                 // class org/apache/hadoop/hbase/client/AsyncSingleRequestRpcRetryingCaller
       7: dup
       8: aload_0
       9: getfield      #2                  // Field this$0:Lorg/apache/hadoop/hbase/client/AsyncRpcRetryingCallerFactory;
      12: invokestatic  #31                 // Method org/apache/hadoop/hbase/client/AsyncRpcRetryingCallerFactory.access$200:(Lorg/apache/hadoop/hbase/client/AsyncRpcRetryingCallerFactory;)Lorg/apache/hbase/thirdparty/io/netty/util/Timer;
      15: aload_0
      16: getfield      #2                  // Field this$0:Lorg/apache/hadoop/hbase/client/AsyncRpcRetryingCallerFactory;
      19: invokestatic  #32                 // Method org/apache/hadoop/hbase/client/AsyncRpcRetryingCallerFactory.access$000:(Lorg/apache/hadoop/hbase/client/AsyncRpcRetryingCallerFactory;)Lorg/apache/hadoop/hbase/client/AsyncConnectionImpl;
      22: aload_0
      23: getfield      #13                 // Field tableName:Lorg/apache/hadoop/hbase/TableName;
      26: aload_0
      27: getfield      #14                 // Field row:[B
      30: aload_0
      31: getfield      #11                 // Field replicaId:I
      34: aload_0
      35: getfield      #9                  // Field locateType:Lorg/apache/hadoop/hbase/client/RegionLocateType;
      38: aload_0
      39: getfield      #15                 // Field callable:Lorg/apache/hadoop/hbase/client/AsyncSingleRequestRpcRetryingCaller$Callable;
      42: aload_0
      43: getfield      #12                 // Field priority:I
      46: aload_0
      47: getfield      #17                 // Field pauseNs:J
      50: aload_0
      51: getfield      #18                 // Field pauseForCQTBENs:J
      54: aload_0
      55: getfield      #19                 // Field maxAttempts:I
      58: aload_0
      59: getfield      #6                  // Field operationTimeoutNs:J
      62: aload_0
      63: getfield      #7                  // Field rpcTimeoutNs:J
      66: aload_0
      67: getfield      #20                 // Field startLogErrorsCnt:I
      70: invokespecial #33                 // Method org/apache/hadoop/hbase/client/AsyncSingleRequestRpcRetryingCaller."<init>":(Lorg/apache/hbase/thirdparty/io/netty/util/Timer;Lorg/apache/hadoop/hbase/client/AsyncConnectionImpl;Lorg/apache/hadoop/hbase/TableName;[BILorg/apache/hadoop/hbase/client/RegionLocateType;Lorg/apache/hadoop/hbase/client/AsyncSingleRequestRpcRetryingCaller$Callable;IJJIJJI)V
      73: areturn

  public java.util.concurrent.CompletableFuture<T> call();
    Code:
       0: aload_0
       1: invokevirtual #34                 // Method build:()Lorg/apache/hadoop/hbase/client/AsyncSingleRequestRpcRetryingCaller;
       4: invokevirtual #35                 // Method org/apache/hadoop/hbase/client/AsyncSingleRequestRpcRetryingCaller.call:()Ljava/util/concurrent/CompletableFuture;
       7: areturn
}
