Compiled from "AsyncTableResultScanner.java"
class org.apache.hadoop.hbase.client.AsyncTableResultScanner implements org.apache.hadoop.hbase.client.ResultScanner,org.apache.hadoop.hbase.client.AdvancedScanResultConsumer {
  static final boolean $assertionsDisabled;

  public org.apache.hadoop.hbase.client.AsyncTableResultScanner(org.apache.hadoop.hbase.client.AsyncTable<org.apache.hadoop.hbase.client.AdvancedScanResultConsumer>, org.apache.hadoop.hbase.client.Scan, long);
    Code:
       0: aload_0
       1: invokespecial #1                  // Method java/lang/Object."<init>":()V
       4: aload_0
       5: new           #2                  // class java/util/ArrayDeque
       8: dup
       9: invokespecial #3                  // Method java/util/ArrayDeque."<init>":()V
      12: putfield      #4                  // Field queue:Ljava/util/Queue;
      15: aload_0
      16: iconst_0
      17: putfield      #5                  // Field closed:Z
      20: aload_0
      21: aload_1
      22: putfield      #6                  // Field rawTable:Lorg/apache/hadoop/hbase/client/AsyncTable;
      25: aload_0
      26: lload_3
      27: putfield      #7                  // Field maxCacheSize:J
      30: aload_0
      31: aload_2
      32: putfield      #8                  // Field scan:Lorg/apache/hadoop/hbase/client/Scan;
      35: aload_1
      36: aload_2
      37: aload_0
      38: invokeinterface #9,  3            // InterfaceMethod org/apache/hadoop/hbase/client/AsyncTable.scan:(Lorg/apache/hadoop/hbase/client/Scan;Lorg/apache/hadoop/hbase/client/ScanResultConsumerBase;)V
      43: return

  public synchronized void onNext(org.apache.hadoop.hbase.client.Result[], org.apache.hadoop.hbase.client.AdvancedScanResultConsumer$ScanController);
    Code:
       0: getstatic     #33                 // Field $assertionsDisabled:Z
       3: ifne          19
       6: aload_1
       7: arraylength
       8: ifgt          19
      11: new           #34                 // class java/lang/AssertionError
      14: dup
      15: invokespecial #35                 // Method java/lang/AssertionError."<init>":()V
      18: athrow
      19: aload_0
      20: getfield      #5                  // Field closed:Z
      23: ifeq          33
      26: aload_2
      27: invokeinterface #36,  1           // InterfaceMethod org/apache/hadoop/hbase/client/AdvancedScanResultConsumer$ScanController.terminate:()V
      32: return
      33: aload_1
      34: astore_3
      35: aload_3
      36: arraylength
      37: istore        4
      39: iconst_0
      40: istore        5
      42: iload         5
      44: iload         4
      46: if_icmpge     67
      49: aload_3
      50: iload         5
      52: aaload
      53: astore        6
      55: aload_0
      56: aload         6
      58: invokespecial #37                 // Method addToCache:(Lorg/apache/hadoop/hbase/client/Result;)V
      61: iinc          5, 1
      64: goto          42
      67: aload_0
      68: invokevirtual #38                 // Method java/lang/Object.notifyAll:()V
      71: aload_0
      72: getfield      #11                 // Field cacheSize:J
      75: aload_0
      76: getfield      #7                  // Field maxCacheSize:J
      79: lcmp
      80: iflt          88
      83: aload_0
      84: aload_2
      85: invokespecial #39                 // Method stopPrefetch:(Lorg/apache/hadoop/hbase/client/AdvancedScanResultConsumer$ScanController;)V
      88: return

  public synchronized void onHeartbeat(org.apache.hadoop.hbase.client.AdvancedScanResultConsumer$ScanController);
    Code:
       0: aload_0
       1: getfield      #5                  // Field closed:Z
       4: ifeq          14
       7: aload_1
       8: invokeinterface #36,  1           // InterfaceMethod org/apache/hadoop/hbase/client/AdvancedScanResultConsumer$ScanController.terminate:()V
      13: return
      14: aload_0
      15: getfield      #8                  // Field scan:Lorg/apache/hadoop/hbase/client/Scan;
      18: invokevirtual #40                 // Method org/apache/hadoop/hbase/client/Scan.isNeedCursorResult:()Z
      21: ifeq          39
      24: aload_1
      25: invokeinterface #41,  1           // InterfaceMethod org/apache/hadoop/hbase/client/AdvancedScanResultConsumer$ScanController.cursor:()Ljava/util/Optional;
      30: aload_0
      31: invokedynamic #42,  0             // InvokeDynamic #0:accept:(Lorg/apache/hadoop/hbase/client/AsyncTableResultScanner;)Ljava/util/function/Consumer;
      36: invokevirtual #43                 // Method java/util/Optional.ifPresent:(Ljava/util/function/Consumer;)V
      39: return

  public synchronized void onError(java.lang.Throwable);
    Code:
       0: aload_0
       1: aload_1
       2: putfield      #44                 // Field error:Ljava/lang/Throwable;
       5: aload_0
       6: invokevirtual #38                 // Method java/lang/Object.notifyAll:()V
       9: return

  public synchronized void onComplete();
    Code:
       0: aload_0
       1: iconst_1
       2: putfield      #5                  // Field closed:Z
       5: aload_0
       6: invokevirtual #38                 // Method java/lang/Object.notifyAll:()V
       9: return

  public void onScanMetricsCreated(org.apache.hadoop.hbase.client.metrics.ScanMetrics);
    Code:
       0: aload_0
       1: aload_1
       2: putfield      #45                 // Field scanMetrics:Lorg/apache/hadoop/hbase/client/metrics/ScanMetrics;
       5: return

  public synchronized org.apache.hadoop.hbase.client.Result next() throws java.io.IOException;
    Code:
       0: aload_0
       1: getfield      #4                  // Field queue:Ljava/util/Queue;
       4: invokeinterface #48,  1           // InterfaceMethod java/util/Queue.isEmpty:()Z
       9: ifeq          65
      12: aload_0
      13: getfield      #5                  // Field closed:Z
      16: ifeq          21
      19: aconst_null
      20: areturn
      21: aload_0
      22: getfield      #44                 // Field error:Ljava/lang/Throwable;
      25: ifnull        49
      28: aload_0
      29: getfield      #44                 // Field error:Ljava/lang/Throwable;
      32: ldc           #49                 // class java/io/IOException
      34: invokestatic  #50                 // Method org/apache/hbase/thirdparty/com/google/common/base/Throwables.propagateIfPossible:(Ljava/lang/Throwable;Ljava/lang/Class;)V
      37: new           #49                 // class java/io/IOException
      40: dup
      41: aload_0
      42: getfield      #44                 // Field error:Ljava/lang/Throwable;
      45: invokespecial #51                 // Method java/io/IOException."<init>":(Ljava/lang/Throwable;)V
      48: athrow
      49: aload_0
      50: invokevirtual #52                 // Method java/lang/Object.wait:()V
      53: goto          0
      56: astore_1
      57: new           #54                 // class java/io/InterruptedIOException
      60: dup
      61: invokespecial #55                 // Method java/io/InterruptedIOException."<init>":()V
      64: athrow
      65: aload_0
      66: getfield      #4                  // Field queue:Ljava/util/Queue;
      69: invokeinterface #56,  1           // InterfaceMethod java/util/Queue.poll:()Ljava/lang/Object;
      74: checkcast     #57                 // class org/apache/hadoop/hbase/client/Result
      77: astore_1
      78: aload_1
      79: invokevirtual #58                 // Method org/apache/hadoop/hbase/client/Result.isCursor:()Z
      82: ifne          125
      85: aload_0
      86: dup
      87: getfield      #11                 // Field cacheSize:J
      90: aload_1
      91: invokestatic  #12                 // Method org/apache/hadoop/hbase/client/ConnectionUtils.calcEstimatedSize:(Lorg/apache/hadoop/hbase/client/Result;)J
      94: lsub
      95: putfield      #11                 // Field cacheSize:J
      98: aload_0
      99: getfield      #32                 // Field resumer:Lorg/apache/hadoop/hbase/client/AdvancedScanResultConsumer$ScanResumer;
     102: ifnull        125
     105: aload_0
     106: getfield      #11                 // Field cacheSize:J
     109: aload_0
     110: getfield      #7                  // Field maxCacheSize:J
     113: ldc2_w        #59                 // long 2l
     116: ldiv
     117: lcmp
     118: ifgt          125
     121: aload_0
     122: invokespecial #61                 // Method resumePrefetch:()V
     125: aload_1
     126: areturn
    Exception table:
       from    to  target type
          49    53    56   Class java/lang/InterruptedException

  public synchronized void close();
    Code:
       0: aload_0
       1: iconst_1
       2: putfield      #5                  // Field closed:Z
       5: aload_0
       6: getfield      #4                  // Field queue:Ljava/util/Queue;
       9: invokeinterface #62,  1           // InterfaceMethod java/util/Queue.clear:()V
      14: aload_0
      15: lconst_0
      16: putfield      #11                 // Field cacheSize:J
      19: aload_0
      20: getfield      #32                 // Field resumer:Lorg/apache/hadoop/hbase/client/AdvancedScanResultConsumer$ScanResumer;
      23: ifnull        30
      26: aload_0
      27: invokespecial #61                 // Method resumePrefetch:()V
      30: aload_0
      31: invokevirtual #38                 // Method java/lang/Object.notifyAll:()V
      34: return

  public boolean renewLease();
    Code:
       0: iconst_0
       1: ireturn

  synchronized boolean isSuspended();
    Code:
       0: aload_0
       1: getfield      #32                 // Field resumer:Lorg/apache/hadoop/hbase/client/AdvancedScanResultConsumer$ScanResumer;
       4: ifnull        11
       7: iconst_1
       8: goto          12
      11: iconst_0
      12: ireturn

  public org.apache.hadoop.hbase.client.metrics.ScanMetrics getScanMetrics();
    Code:
       0: aload_0
       1: getfield      #45                 // Field scanMetrics:Lorg/apache/hadoop/hbase/client/metrics/ScanMetrics;
       4: areturn

  static {};
    Code:
       0: ldc           #64                 // class org/apache/hadoop/hbase/client/AsyncTableResultScanner
       2: invokevirtual #65                 // Method java/lang/Class.desiredAssertionStatus:()Z
       5: ifne          12
       8: iconst_1
       9: goto          13
      12: iconst_0
      13: putstatic     #33                 // Field $assertionsDisabled:Z
      16: ldc           #64                 // class org/apache/hadoop/hbase/client/AsyncTableResultScanner
      18: invokestatic  #66                 // Method org/slf4j/LoggerFactory.getLogger:(Ljava/lang/Class;)Lorg/slf4j/Logger;
      21: putstatic     #13                 // Field LOG:Lorg/slf4j/Logger;
      24: return
}
