Compiled from "AsyncProtobufLogWriter.java"
final class org.apache.hadoop.hbase.regionserver.wal.AsyncProtobufLogWriter$OutputStreamWrapper extends java.io.OutputStream implements org.apache.hadoop.hbase.io.ByteBufferWriter {
  public void write(int) throws java.io.IOException;
    Code:
       0: aload_0
       1: getfield      #1                  // Field oneByteBuf:[B
       4: iconst_0
       5: iload_1
       6: i2b
       7: bastore
       8: aload_0
       9: aload_0
      10: getfield      #1                  // Field oneByteBuf:[B
      13: invokevirtual #2                  // Method write:([B)V
      16: return

  public org.apache.hadoop.hbase.regionserver.wal.AsyncProtobufLogWriter$OutputStreamWrapper(org.apache.hadoop.hbase.io.asyncfs.AsyncFSOutput);
    Code:
       0: aload_0
       1: invokespecial #3                  // Method java/io/OutputStream."<init>":()V
       4: aload_0
       5: iconst_1
       6: newarray       byte
       8: putfield      #1                  // Field oneByteBuf:[B
      11: aload_0
      12: aload_1
      13: putfield      #4                  // Field out:Lorg/apache/hadoop/hbase/io/asyncfs/AsyncFSOutput;
      16: return

  public void write(java.nio.ByteBuffer, int, int) throws java.io.IOException;
    Code:
       0: aload_1
       1: invokevirtual #5                  // Method java/nio/ByteBuffer.duplicate:()Ljava/nio/ByteBuffer;
       4: astore        4
       6: aload         4
       8: iload_2
       9: invokevirtual #6                  // Method java/nio/ByteBuffer.position:(I)Ljava/nio/Buffer;
      12: pop
      13: aload         4
      15: iload_2
      16: iload_3
      17: iadd
      18: invokevirtual #7                  // Method java/nio/ByteBuffer.limit:(I)Ljava/nio/Buffer;
      21: pop
      22: aload_0
      23: getfield      #4                  // Field out:Lorg/apache/hadoop/hbase/io/asyncfs/AsyncFSOutput;
      26: aload         4
      28: invokeinterface #8,  2            // InterfaceMethod org/apache/hadoop/hbase/io/asyncfs/AsyncFSOutput.write:(Ljava/nio/ByteBuffer;)V
      33: return

  public void writeInt(int) throws java.io.IOException;
    Code:
       0: aload_0
       1: getfield      #4                  // Field out:Lorg/apache/hadoop/hbase/io/asyncfs/AsyncFSOutput;
       4: iload_1
       5: invokeinterface #9,  2            // InterfaceMethod org/apache/hadoop/hbase/io/asyncfs/AsyncFSOutput.writeInt:(I)V
      10: return

  public void write(byte[], int, int) throws java.io.IOException;
    Code:
       0: aload_0
       1: getfield      #4                  // Field out:Lorg/apache/hadoop/hbase/io/asyncfs/AsyncFSOutput;
       4: aload_1
       5: iload_2
       6: iload_3
       7: invokeinterface #10,  4           // InterfaceMethod org/apache/hadoop/hbase/io/asyncfs/AsyncFSOutput.write:([BII)V
      12: return

  public void close() throws java.io.IOException;
    Code:
       0: aload_0
       1: getfield      #4                  // Field out:Lorg/apache/hadoop/hbase/io/asyncfs/AsyncFSOutput;
       4: invokeinterface #11,  1           // InterfaceMethod org/apache/hadoop/hbase/io/asyncfs/AsyncFSOutput.close:()V
       9: return
}
