Compiled from "AsyncBufferedMutator.java"
public interface org.apache.hadoop.hbase.client.AsyncBufferedMutator extends java.io.Closeable {
  public abstract org.apache.hadoop.hbase.TableName getName();

  public abstract org.apache.hadoop.conf.Configuration getConfiguration();

  public java.util.concurrent.CompletableFuture<java.lang.Void> mutate(org.apache.hadoop.hbase.client.Mutation);
    Code:
       0: aload_0
       1: aload_1
       2: invokestatic  #1                  // Method java/util/Collections.singletonList:(Ljava/lang/Object;)Ljava/util/List;
       5: invokeinterface #2,  2            // InterfaceMethod mutate:(Ljava/util/List;)Ljava/util/List;
      10: invokestatic  #3                  // Method org/apache/hbase/thirdparty/com/google/common/collect/Iterables.getOnlyElement:(Ljava/lang/Iterable;)Ljava/lang/Object;
      13: checkcast     #4                  // class java/util/concurrent/CompletableFuture
      16: areturn

  public abstract java.util.List<java.util.concurrent.CompletableFuture<java.lang.Void>> mutate(java.util.List<? extends org.apache.hadoop.hbase.client.Mutation>);

  public abstract void flush();

  public abstract void close();

  public abstract long getWriteBufferSize();

  public long getPeriodicalFlushTimeout(java.util.concurrent.TimeUnit);
    Code:
       0: new           #5                  // class java/lang/UnsupportedOperationException
       3: dup
       4: ldc           #6                  // String Not implemented
       6: invokespecial #7                  // Method java/lang/UnsupportedOperationException."<init>":(Ljava/lang/String;)V
       9: athrow
}
