Compiled from "AsyncRpcRetryingCallerFactory.java"
public class org.apache.hadoop.hbase.client.AsyncRpcRetryingCallerFactory$BatchCallerBuilder extends org.apache.hadoop.hbase.client.AsyncRpcRetryingCallerFactory$BuilderBase {
  final org.apache.hadoop.hbase.client.AsyncRpcRetryingCallerFactory this$0;

  public org.apache.hadoop.hbase.client.AsyncRpcRetryingCallerFactory$BatchCallerBuilder(org.apache.hadoop.hbase.client.AsyncRpcRetryingCallerFactory);
    Code:
       0: aload_0
       1: aload_1
       2: putfield      #1                  // Field this$0:Lorg/apache/hadoop/hbase/client/AsyncRpcRetryingCallerFactory;
       5: aload_0
       6: aload_1
       7: aconst_null
       8: invokespecial #2                  // Method org/apache/hadoop/hbase/client/AsyncRpcRetryingCallerFactory$BuilderBase."<init>":(Lorg/apache/hadoop/hbase/client/AsyncRpcRetryingCallerFactory;Lorg/apache/hadoop/hbase/client/AsyncRpcRetryingCallerFactory$1;)V
      11: aload_0
      12: ldc2_w        #3                  // long -1l
      15: putfield      #5                  // Field operationTimeoutNs:J
      18: aload_0
      19: ldc2_w        #3                  // long -1l
      22: putfield      #6                  // Field rpcTimeoutNs:J
      25: return

  public org.apache.hadoop.hbase.client.AsyncRpcRetryingCallerFactory$BatchCallerBuilder table(org.apache.hadoop.hbase.TableName);
    Code:
       0: aload_0
       1: aload_1
       2: putfield      #7                  // Field tableName:Lorg/apache/hadoop/hbase/TableName;
       5: aload_0
       6: areturn

  public org.apache.hadoop.hbase.client.AsyncRpcRetryingCallerFactory$BatchCallerBuilder actions(java.util.List<? extends org.apache.hadoop.hbase.client.Row>);
    Code:
       0: aload_0
       1: aload_1
       2: putfield      #8                  // Field actions:Ljava/util/List;
       5: aload_0
       6: areturn

  public org.apache.hadoop.hbase.client.AsyncRpcRetryingCallerFactory$BatchCallerBuilder operationTimeout(long, java.util.concurrent.TimeUnit);
    Code:
       0: aload_0
       1: aload_3
       2: lload_1
       3: invokevirtual #9                  // Method java/util/concurrent/TimeUnit.toNanos:(J)J
       6: putfield      #5                  // Field operationTimeoutNs:J
       9: aload_0
      10: areturn

  public org.apache.hadoop.hbase.client.AsyncRpcRetryingCallerFactory$BatchCallerBuilder rpcTimeout(long, java.util.concurrent.TimeUnit);
    Code:
       0: aload_0
       1: aload_3
       2: lload_1
       3: invokevirtual #9                  // Method java/util/concurrent/TimeUnit.toNanos:(J)J
       6: putfield      #6                  // Field rpcTimeoutNs:J
       9: aload_0
      10: areturn

  public org.apache.hadoop.hbase.client.AsyncRpcRetryingCallerFactory$BatchCallerBuilder pause(long, java.util.concurrent.TimeUnit);
    Code:
       0: aload_0
       1: aload_3
       2: lload_1
       3: invokevirtual #9                  // Method java/util/concurrent/TimeUnit.toNanos:(J)J
       6: putfield      #10                 // Field pauseNs:J
       9: aload_0
      10: areturn

  public org.apache.hadoop.hbase.client.AsyncRpcRetryingCallerFactory$BatchCallerBuilder pauseForCQTBE(long, java.util.concurrent.TimeUnit);
    Code:
       0: aload_0
       1: aload_3
       2: lload_1
       3: invokevirtual #9                  // Method java/util/concurrent/TimeUnit.toNanos:(J)J
       6: putfield      #11                 // Field pauseForCQTBENs:J
       9: aload_0
      10: areturn

  public org.apache.hadoop.hbase.client.AsyncRpcRetryingCallerFactory$BatchCallerBuilder maxAttempts(int);
    Code:
       0: aload_0
       1: iload_1
       2: putfield      #12                 // Field maxAttempts:I
       5: aload_0
       6: areturn

  public org.apache.hadoop.hbase.client.AsyncRpcRetryingCallerFactory$BatchCallerBuilder startLogErrorsCnt(int);
    Code:
       0: aload_0
       1: iload_1
       2: putfield      #13                 // Field startLogErrorsCnt:I
       5: aload_0
       6: areturn

  public <T> org.apache.hadoop.hbase.client.AsyncBatchRpcRetryingCaller<T> build();
    Code:
       0: new           #14                 // class org/apache/hadoop/hbase/client/AsyncBatchRpcRetryingCaller
       3: dup
       4: aload_0
       5: getfield      #1                  // Field this$0:Lorg/apache/hadoop/hbase/client/AsyncRpcRetryingCallerFactory;
       8: invokestatic  #15                 // Method org/apache/hadoop/hbase/client/AsyncRpcRetryingCallerFactory.access$200:(Lorg/apache/hadoop/hbase/client/AsyncRpcRetryingCallerFactory;)Lorg/apache/hbase/thirdparty/io/netty/util/Timer;
      11: aload_0
      12: getfield      #1                  // Field this$0:Lorg/apache/hadoop/hbase/client/AsyncRpcRetryingCallerFactory;
      15: invokestatic  #16                 // Method org/apache/hadoop/hbase/client/AsyncRpcRetryingCallerFactory.access$000:(Lorg/apache/hadoop/hbase/client/AsyncRpcRetryingCallerFactory;)Lorg/apache/hadoop/hbase/client/AsyncConnectionImpl;
      18: aload_0
      19: getfield      #7                  // Field tableName:Lorg/apache/hadoop/hbase/TableName;
      22: aload_0
      23: getfield      #8                  // Field actions:Ljava/util/List;
      26: aload_0
      27: getfield      #10                 // Field pauseNs:J
      30: aload_0
      31: getfield      #11                 // Field pauseForCQTBENs:J
      34: aload_0
      35: getfield      #12                 // Field maxAttempts:I
      38: aload_0
      39: getfield      #5                  // Field operationTimeoutNs:J
      42: aload_0
      43: getfield      #6                  // Field rpcTimeoutNs:J
      46: aload_0
      47: getfield      #13                 // Field startLogErrorsCnt:I
      50: invokespecial #17                 // Method org/apache/hadoop/hbase/client/AsyncBatchRpcRetryingCaller."<init>":(Lorg/apache/hbase/thirdparty/io/netty/util/Timer;Lorg/apache/hadoop/hbase/client/AsyncConnectionImpl;Lorg/apache/hadoop/hbase/TableName;Ljava/util/List;JJIJJI)V
      53: areturn

  public <T> java.util.List<java.util.concurrent.CompletableFuture<T>> call();
    Code:
       0: aload_0
       1: invokevirtual #18                 // Method build:()Lorg/apache/hadoop/hbase/client/AsyncBatchRpcRetryingCaller;
       4: invokevirtual #19                 // Method org/apache/hadoop/hbase/client/AsyncBatchRpcRetryingCaller.call:()Ljava/util/List;
       7: areturn
}
