Compiled from "AsyncScanSingleRegionRpcRetryingCaller.java"
class org.apache.hadoop.hbase.client.AsyncScanSingleRegionRpcRetryingCaller {
  static final boolean $assertionsDisabled;

  public org.apache.hadoop.hbase.client.AsyncScanSingleRegionRpcRetryingCaller(org.apache.hbase.thirdparty.io.netty.util.Timer, org.apache.hadoop.hbase.client.AsyncConnectionImpl, org.apache.hadoop.hbase.client.Scan, org.apache.hadoop.hbase.client.metrics.ScanMetrics, long, org.apache.hadoop.hbase.client.ScanResultCache, org.apache.hadoop.hbase.client.AdvancedScanResultConsumer, org.apache.hadoop.hbase.shaded.protobuf.generated.ClientProtos$ClientService$Interface, org.apache.hadoop.hbase.HRegionLocation, boolean, int, long, long, long, int, long, long, int);
    Code:
       0: aload_0
       1: invokespecial #5                  // Method java/lang/Object."<init>":()V
       4: aload_0
       5: ldc2_w        #6                  // long -1l
       8: putfield      #8                  // Field nextCallSeq:J
      11: aload_0
      12: aload_1
      13: putfield      #2                  // Field retryTimer:Lorg/apache/hbase/thirdparty/io/netty/util/Timer;
      16: aload_0
      17: aload_3
      18: putfield      #9                  // Field scan:Lorg/apache/hadoop/hbase/client/Scan;
      21: aload_0
      22: aload         4
      24: putfield      #10                 // Field scanMetrics:Lorg/apache/hadoop/hbase/client/metrics/ScanMetrics;
      27: aload_0
      28: lload         5
      30: putfield      #11                 // Field scannerId:J
      33: aload_0
      34: aload         7
      36: putfield      #12                 // Field resultCache:Lorg/apache/hadoop/hbase/client/ScanResultCache;
      39: aload_0
      40: aload         8
      42: putfield      #13                 // Field consumer:Lorg/apache/hadoop/hbase/client/AdvancedScanResultConsumer;
      45: aload_0
      46: aload         9
      48: putfield      #14                 // Field stub:Lorg/apache/hadoop/hbase/shaded/protobuf/generated/ClientProtos$ClientService$Interface;
      51: aload_0
      52: aload         10
      54: putfield      #15                 // Field loc:Lorg/apache/hadoop/hbase/HRegionLocation;
      57: aload_0
      58: iload         11
      60: putfield      #16                 // Field regionServerRemote:Z
      63: aload_0
      64: lload         13
      66: putfield      #3                  // Field scannerLeaseTimeoutPeriodNs:J
      69: aload_0
      70: lload         15
      72: putfield      #17                 // Field pauseNs:J
      75: aload_0
      76: lload         17
      78: putfield      #18                 // Field pauseForCQTBENs:J
      81: aload_0
      82: iload         19
      84: putfield      #19                 // Field maxAttempts:I
      87: aload_0
      88: lload         20
      90: putfield      #20                 // Field scanTimeoutNs:J
      93: aload_0
      94: lload         22
      96: putfield      #21                 // Field rpcTimeoutNs:J
      99: aload_0
     100: iload         24
     102: putfield      #22                 // Field startLogErrorsCnt:I
     105: aload_3
     106: invokevirtual #23                 // Method org/apache/hadoop/hbase/client/Scan.isReversed:()Z
     109: ifeq          125
     112: aload_0
     113: aload_0
     114: invokedynamic #24,  0             // InvokeDynamic #0:run:(Lorg/apache/hadoop/hbase/client/AsyncScanSingleRegionRpcRetryingCaller;)Ljava/lang/Runnable;
     119: putfield      #25                 // Field completeWhenNoMoreResultsInRegion:Ljava/lang/Runnable;
     122: goto          135
     125: aload_0
     126: aload_0
     127: invokedynamic #26,  0             // InvokeDynamic #1:run:(Lorg/apache/hadoop/hbase/client/AsyncScanSingleRegionRpcRetryingCaller;)Ljava/lang/Runnable;
     132: putfield      #25                 // Field completeWhenNoMoreResultsInRegion:Ljava/lang/Runnable;
     135: aload_0
     136: new           #27                 // class java/util/concurrent/CompletableFuture
     139: dup
     140: invokespecial #28                 // Method java/util/concurrent/CompletableFuture."<init>":()V
     143: putfield      #29                 // Field future:Ljava/util/concurrent/CompletableFuture;
     146: aload_0
     147: iload         12
     149: putfield      #30                 // Field priority:I
     152: aload_0
     153: aload_2
     154: getfield      #31                 // Field org/apache/hadoop/hbase/client/AsyncConnectionImpl.rpcControllerFactory:Lorg/apache/hadoop/hbase/ipc/RpcControllerFactory;
     157: invokevirtual #32                 // Method org/apache/hadoop/hbase/ipc/RpcControllerFactory.newController:()Lorg/apache/hadoop/hbase/ipc/HBaseRpcController;
     160: putfield      #33                 // Field controller:Lorg/apache/hadoop/hbase/ipc/HBaseRpcController;
     163: aload_0
     164: getfield      #33                 // Field controller:Lorg/apache/hadoop/hbase/ipc/HBaseRpcController;
     167: iload         12
     169: invokeinterface #34,  2           // InterfaceMethod org/apache/hadoop/hbase/ipc/HBaseRpcController.setPriority:(I)V
     174: aload_0
     175: new           #35                 // class java/util/ArrayList
     178: dup
     179: invokespecial #36                 // Method java/util/ArrayList."<init>":()V
     182: putfield      #37                 // Field exceptions:Ljava/util/List;
     185: return

  public java.util.concurrent.CompletableFuture<java.lang.Boolean> start(org.apache.hadoop.hbase.ipc.HBaseRpcController, org.apache.hadoop.hbase.shaded.protobuf.generated.ClientProtos$ScanResponse);
    Code:
       0: aload_0
       1: aload_1
       2: aload_2
       3: invokespecial #164                // Method onComplete:(Lorg/apache/hadoop/hbase/ipc/HBaseRpcController;Lorg/apache/hadoop/hbase/shaded/protobuf/generated/ClientProtos$ScanResponse;)V
       6: aload_0
       7: getfield      #29                 // Field future:Ljava/util/concurrent/CompletableFuture;
      10: areturn

  static void access$100(org.apache.hadoop.hbase.client.AsyncScanSingleRegionRpcRetryingCaller, org.apache.hadoop.hbase.shaded.protobuf.generated.ClientProtos$ScanResponse, int);
    Code:
       0: aload_0
       1: aload_1
       2: iload_2
       3: invokespecial #4                  // Method completeOrNext:(Lorg/apache/hadoop/hbase/shaded/protobuf/generated/ClientProtos$ScanResponse;I)V
       6: return

  static long access$200(org.apache.hadoop.hbase.client.AsyncScanSingleRegionRpcRetryingCaller);
    Code:
       0: aload_0
       1: getfield      #3                  // Field scannerLeaseTimeoutPeriodNs:J
       4: lreturn

  static org.apache.hbase.thirdparty.io.netty.util.Timer access$300(org.apache.hadoop.hbase.client.AsyncScanSingleRegionRpcRetryingCaller);
    Code:
       0: aload_0
       1: getfield      #2                  // Field retryTimer:Lorg/apache/hbase/thirdparty/io/netty/util/Timer;
       4: areturn

  static void access$400(org.apache.hadoop.hbase.client.AsyncScanSingleRegionRpcRetryingCaller);
    Code:
       0: aload_0
       1: invokespecial #1                  // Method renewLease:()V
       4: return

  static {};
    Code:
       0: ldc           #167                // class org/apache/hadoop/hbase/client/AsyncScanSingleRegionRpcRetryingCaller
       2: invokevirtual #168                // Method java/lang/Class.desiredAssertionStatus:()Z
       5: ifne          12
       8: iconst_1
       9: goto          13
      12: iconst_0
      13: putstatic     #114                // Field $assertionsDisabled:Z
      16: ldc           #167                // class org/apache/hadoop/hbase/client/AsyncScanSingleRegionRpcRetryingCaller
      18: invokestatic  #169                // Method org/slf4j/LoggerFactory.getLogger:(Ljava/lang/Class;)Lorg/slf4j/Logger;
      21: putstatic     #60                 // Field LOG:Lorg/slf4j/Logger;
      24: return
}
