Compiled from "AsyncTable.java"
public interface org.apache.hadoop.hbase.client.AsyncTable<C extends org.apache.hadoop.hbase.client.ScanResultConsumerBase> {
  public abstract org.apache.hadoop.hbase.TableName getName();

  public abstract org.apache.hadoop.conf.Configuration getConfiguration();

  public abstract java.util.concurrent.CompletableFuture<org.apache.hadoop.hbase.client.TableDescriptor> getDescriptor();

  public abstract org.apache.hadoop.hbase.client.AsyncTableRegionLocator getRegionLocator();

  public abstract long getRpcTimeout(java.util.concurrent.TimeUnit);

  public abstract long getReadRpcTimeout(java.util.concurrent.TimeUnit);

  public abstract long getWriteRpcTimeout(java.util.concurrent.TimeUnit);

  public abstract long getOperationTimeout(java.util.concurrent.TimeUnit);

  public abstract long getScanTimeout(java.util.concurrent.TimeUnit);

  public java.util.concurrent.CompletableFuture<java.lang.Boolean> exists(org.apache.hadoop.hbase.client.Get);
    Code:
       0: aload_0
       1: aload_1
       2: invokestatic  #1                  // Method org/apache/hadoop/hbase/client/ConnectionUtils.toCheckExistenceOnly:(Lorg/apache/hadoop/hbase/client/Get;)Lorg/apache/hadoop/hbase/client/Get;
       5: invokeinterface #2,  2            // InterfaceMethod get:(Lorg/apache/hadoop/hbase/client/Get;)Ljava/util/concurrent/CompletableFuture;
      10: invokedynamic #3,  0              // InvokeDynamic #0:apply:()Ljava/util/function/Function;
      15: invokevirtual #4                  // Method java/util/concurrent/CompletableFuture.thenApply:(Ljava/util/function/Function;)Ljava/util/concurrent/CompletableFuture;
      18: areturn

  public abstract java.util.concurrent.CompletableFuture<org.apache.hadoop.hbase.client.Result> get(org.apache.hadoop.hbase.client.Get);

  public abstract java.util.concurrent.CompletableFuture<java.lang.Void> put(org.apache.hadoop.hbase.client.Put);

  public abstract java.util.concurrent.CompletableFuture<java.lang.Void> delete(org.apache.hadoop.hbase.client.Delete);

  public abstract java.util.concurrent.CompletableFuture<org.apache.hadoop.hbase.client.Result> append(org.apache.hadoop.hbase.client.Append);

  public abstract java.util.concurrent.CompletableFuture<org.apache.hadoop.hbase.client.Result> increment(org.apache.hadoop.hbase.client.Increment);

  public java.util.concurrent.CompletableFuture<java.lang.Long> incrementColumnValue(byte[], byte[], byte[], long);
    Code:
       0: aload_0
       1: aload_1
       2: aload_2
       3: aload_3
       4: lload         4
       6: getstatic     #5                  // Field org/apache/hadoop/hbase/client/Durability.SYNC_WAL:Lorg/apache/hadoop/hbase/client/Durability;
       9: invokeinterface #6,  7            // InterfaceMethod incrementColumnValue:([B[B[BJLorg/apache/hadoop/hbase/client/Durability;)Ljava/util/concurrent/CompletableFuture;
      14: areturn

  public java.util.concurrent.CompletableFuture<java.lang.Long> incrementColumnValue(byte[], byte[], byte[], long, org.apache.hadoop.hbase.client.Durability);
    Code:
       0: aload_1
       1: ldc           #7                  // String row is null
       3: invokestatic  #8                  // Method org/apache/hbase/thirdparty/com/google/common/base/Preconditions.checkNotNull:(Ljava/lang/Object;Ljava/lang/Object;)Ljava/lang/Object;
       6: pop
       7: aload_2
       8: ldc           #9                  // String family is null
      10: invokestatic  #8                  // Method org/apache/hbase/thirdparty/com/google/common/base/Preconditions.checkNotNull:(Ljava/lang/Object;Ljava/lang/Object;)Ljava/lang/Object;
      13: pop
      14: aload_0
      15: new           #10                 // class org/apache/hadoop/hbase/client/Increment
      18: dup
      19: aload_1
      20: invokespecial #11                 // Method org/apache/hadoop/hbase/client/Increment."<init>":([B)V
      23: aload_2
      24: aload_3
      25: lload         4
      27: invokevirtual #12                 // Method org/apache/hadoop/hbase/client/Increment.addColumn:([B[BJ)Lorg/apache/hadoop/hbase/client/Increment;
      30: aload         6
      32: invokevirtual #13                 // Method org/apache/hadoop/hbase/client/Increment.setDurability:(Lorg/apache/hadoop/hbase/client/Durability;)Lorg/apache/hadoop/hbase/client/Increment;
      35: invokeinterface #14,  2           // InterfaceMethod increment:(Lorg/apache/hadoop/hbase/client/Increment;)Ljava/util/concurrent/CompletableFuture;
      40: aload_2
      41: aload_3
      42: invokedynamic #15,  0             // InvokeDynamic #1:apply:([B[B)Ljava/util/function/Function;
      47: invokevirtual #4                  // Method java/util/concurrent/CompletableFuture.thenApply:(Ljava/util/function/Function;)Ljava/util/concurrent/CompletableFuture;
      50: areturn

  public abstract org.apache.hadoop.hbase.client.AsyncTable$CheckAndMutateBuilder checkAndMutate(byte[], byte[]);

  public abstract java.util.concurrent.CompletableFuture<java.lang.Void> mutateRow(org.apache.hadoop.hbase.client.RowMutations);

  public abstract void scan(org.apache.hadoop.hbase.client.Scan, C);

  public org.apache.hadoop.hbase.client.ResultScanner getScanner(byte[]);
    Code:
       0: aload_0
       1: new           #16                 // class org/apache/hadoop/hbase/client/Scan
       4: dup
       5: invokespecial #17                 // Method org/apache/hadoop/hbase/client/Scan."<init>":()V
       8: aload_1
       9: invokevirtual #18                 // Method org/apache/hadoop/hbase/client/Scan.addFamily:([B)Lorg/apache/hadoop/hbase/client/Scan;
      12: invokeinterface #19,  2           // InterfaceMethod getScanner:(Lorg/apache/hadoop/hbase/client/Scan;)Lorg/apache/hadoop/hbase/client/ResultScanner;
      17: areturn

  public org.apache.hadoop.hbase.client.ResultScanner getScanner(byte[], byte[]);
    Code:
       0: aload_0
       1: new           #16                 // class org/apache/hadoop/hbase/client/Scan
       4: dup
       5: invokespecial #17                 // Method org/apache/hadoop/hbase/client/Scan."<init>":()V
       8: aload_1
       9: aload_2
      10: invokevirtual #20                 // Method org/apache/hadoop/hbase/client/Scan.addColumn:([B[B)Lorg/apache/hadoop/hbase/client/Scan;
      13: invokeinterface #19,  2           // InterfaceMethod getScanner:(Lorg/apache/hadoop/hbase/client/Scan;)Lorg/apache/hadoop/hbase/client/ResultScanner;
      18: areturn

  public abstract org.apache.hadoop.hbase.client.ResultScanner getScanner(org.apache.hadoop.hbase.client.Scan);

  public abstract java.util.concurrent.CompletableFuture<java.util.List<org.apache.hadoop.hbase.client.Result>> scanAll(org.apache.hadoop.hbase.client.Scan);

  public java.util.List<java.util.concurrent.CompletableFuture<java.lang.Boolean>> exists(java.util.List<org.apache.hadoop.hbase.client.Get>);
    Code:
       0: aload_0
       1: aload_1
       2: invokestatic  #21                 // Method org/apache/hadoop/hbase/client/ConnectionUtils.toCheckExistenceOnly:(Ljava/util/List;)Ljava/util/List;
       5: invokeinterface #22,  2           // InterfaceMethod get:(Ljava/util/List;)Ljava/util/List;
      10: invokeinterface #23,  1           // InterfaceMethod java/util/List.stream:()Ljava/util/stream/Stream;
      15: invokedynamic #24,  0             // InvokeDynamic #2:apply:()Ljava/util/function/Function;
      20: invokeinterface #25,  2           // InterfaceMethod java/util/stream/Stream.map:(Ljava/util/function/Function;)Ljava/util/stream/Stream;
      25: invokestatic  #26                 // Method java/util/stream/Collectors.toList:()Ljava/util/stream/Collector;
      28: invokeinterface #27,  2           // InterfaceMethod java/util/stream/Stream.collect:(Ljava/util/stream/Collector;)Ljava/lang/Object;
      33: checkcast     #28                 // class java/util/List
      36: areturn

  public java.util.concurrent.CompletableFuture<java.util.List<java.lang.Boolean>> existsAll(java.util.List<org.apache.hadoop.hbase.client.Get>);
    Code:
       0: aload_0
       1: aload_1
       2: invokeinterface #29,  2           // InterfaceMethod exists:(Ljava/util/List;)Ljava/util/List;
       7: invokestatic  #30                 // Method org/apache/hadoop/hbase/client/ConnectionUtils.allOf:(Ljava/util/List;)Ljava/util/concurrent/CompletableFuture;
      10: areturn

  public abstract java.util.List<java.util.concurrent.CompletableFuture<org.apache.hadoop.hbase.client.Result>> get(java.util.List<org.apache.hadoop.hbase.client.Get>);

  public java.util.concurrent.CompletableFuture<java.util.List<org.apache.hadoop.hbase.client.Result>> getAll(java.util.List<org.apache.hadoop.hbase.client.Get>);
    Code:
       0: aload_0
       1: aload_1
       2: invokeinterface #22,  2           // InterfaceMethod get:(Ljava/util/List;)Ljava/util/List;
       7: invokestatic  #30                 // Method org/apache/hadoop/hbase/client/ConnectionUtils.allOf:(Ljava/util/List;)Ljava/util/concurrent/CompletableFuture;
      10: areturn

  public abstract java.util.List<java.util.concurrent.CompletableFuture<java.lang.Void>> put(java.util.List<org.apache.hadoop.hbase.client.Put>);

  public java.util.concurrent.CompletableFuture<java.lang.Void> putAll(java.util.List<org.apache.hadoop.hbase.client.Put>);
    Code:
       0: aload_0
       1: aload_1
       2: invokeinterface #31,  2           // InterfaceMethod put:(Ljava/util/List;)Ljava/util/List;
       7: invokestatic  #30                 // Method org/apache/hadoop/hbase/client/ConnectionUtils.allOf:(Ljava/util/List;)Ljava/util/concurrent/CompletableFuture;
      10: invokedynamic #32,  0             // InvokeDynamic #3:apply:()Ljava/util/function/Function;
      15: invokevirtual #4                  // Method java/util/concurrent/CompletableFuture.thenApply:(Ljava/util/function/Function;)Ljava/util/concurrent/CompletableFuture;
      18: areturn

  public abstract java.util.List<java.util.concurrent.CompletableFuture<java.lang.Void>> delete(java.util.List<org.apache.hadoop.hbase.client.Delete>);

  public java.util.concurrent.CompletableFuture<java.lang.Void> deleteAll(java.util.List<org.apache.hadoop.hbase.client.Delete>);
    Code:
       0: aload_0
       1: aload_1
       2: invokeinterface #33,  2           // InterfaceMethod delete:(Ljava/util/List;)Ljava/util/List;
       7: invokestatic  #30                 // Method org/apache/hadoop/hbase/client/ConnectionUtils.allOf:(Ljava/util/List;)Ljava/util/concurrent/CompletableFuture;
      10: invokedynamic #34,  0             // InvokeDynamic #4:apply:()Ljava/util/function/Function;
      15: invokevirtual #4                  // Method java/util/concurrent/CompletableFuture.thenApply:(Ljava/util/function/Function;)Ljava/util/concurrent/CompletableFuture;
      18: areturn

  public abstract <T> java.util.List<java.util.concurrent.CompletableFuture<T>> batch(java.util.List<? extends org.apache.hadoop.hbase.client.Row>);

  public <T> java.util.concurrent.CompletableFuture<java.util.List<T>> batchAll(java.util.List<? extends org.apache.hadoop.hbase.client.Row>);
    Code:
       0: aload_0
       1: aload_1
       2: invokeinterface #35,  2           // InterfaceMethod batch:(Ljava/util/List;)Ljava/util/List;
       7: invokestatic  #30                 // Method org/apache/hadoop/hbase/client/ConnectionUtils.allOf:(Ljava/util/List;)Ljava/util/concurrent/CompletableFuture;
      10: areturn

  public abstract <S, R> java.util.concurrent.CompletableFuture<R> coprocessorService(java.util.function.Function<com.google.protobuf.RpcChannel, S>, org.apache.hadoop.hbase.client.ServiceCaller<S, R>, byte[]);

  public abstract <S, R> org.apache.hadoop.hbase.client.AsyncTable$CoprocessorServiceBuilder<S, R> coprocessorService(java.util.function.Function<com.google.protobuf.RpcChannel, S>, org.apache.hadoop.hbase.client.ServiceCaller<S, R>, org.apache.hadoop.hbase.client.AsyncTable$CoprocessorCallback<R>);
}
