Compiled from "AsyncRpcRetryingCallerFactory.java"
public class org.apache.hadoop.hbase.client.AsyncRpcRetryingCallerFactory$ScanSingleRegionCallerBuilder extends org.apache.hadoop.hbase.client.AsyncRpcRetryingCallerFactory$BuilderBase {
  final org.apache.hadoop.hbase.client.AsyncRpcRetryingCallerFactory this$0;

  public org.apache.hadoop.hbase.client.AsyncRpcRetryingCallerFactory$ScanSingleRegionCallerBuilder(org.apache.hadoop.hbase.client.AsyncRpcRetryingCallerFactory);
    Code:
       0: aload_0
       1: aload_1
       2: putfield      #2                  // Field this$0:Lorg/apache/hadoop/hbase/client/AsyncRpcRetryingCallerFactory;
       5: aload_0
       6: aload_1
       7: aconst_null
       8: invokespecial #3                  // Method org/apache/hadoop/hbase/client/AsyncRpcRetryingCallerFactory$BuilderBase."<init>":(Lorg/apache/hadoop/hbase/client/AsyncRpcRetryingCallerFactory;Lorg/apache/hadoop/hbase/client/AsyncRpcRetryingCallerFactory$1;)V
      11: aload_0
      12: aconst_null
      13: putfield      #4                  // Field scannerId:Ljava/lang/Long;
      16: aload_0
      17: iconst_m1
      18: putfield      #5                  // Field priority:I
      21: return

  public org.apache.hadoop.hbase.client.AsyncRpcRetryingCallerFactory$ScanSingleRegionCallerBuilder id(long);
    Code:
       0: aload_0
       1: lload_1
       2: invokestatic  #6                  // Method java/lang/Long.valueOf:(J)Ljava/lang/Long;
       5: putfield      #4                  // Field scannerId:Ljava/lang/Long;
       8: aload_0
       9: areturn

  public org.apache.hadoop.hbase.client.AsyncRpcRetryingCallerFactory$ScanSingleRegionCallerBuilder setScan(org.apache.hadoop.hbase.client.Scan);
    Code:
       0: aload_0
       1: aload_1
       2: putfield      #7                  // Field scan:Lorg/apache/hadoop/hbase/client/Scan;
       5: aload_0
       6: aload_1
       7: invokevirtual #8                  // Method org/apache/hadoop/hbase/client/Scan.getPriority:()I
      10: putfield      #5                  // Field priority:I
      13: aload_0
      14: areturn

  public org.apache.hadoop.hbase.client.AsyncRpcRetryingCallerFactory$ScanSingleRegionCallerBuilder metrics(org.apache.hadoop.hbase.client.metrics.ScanMetrics);
    Code:
       0: aload_0
       1: aload_1
       2: putfield      #9                  // Field scanMetrics:Lorg/apache/hadoop/hbase/client/metrics/ScanMetrics;
       5: aload_0
       6: areturn

  public org.apache.hadoop.hbase.client.AsyncRpcRetryingCallerFactory$ScanSingleRegionCallerBuilder remote(boolean);
    Code:
       0: aload_0
       1: iload_1
       2: putfield      #10                 // Field isRegionServerRemote:Z
       5: aload_0
       6: areturn

  public org.apache.hadoop.hbase.client.AsyncRpcRetryingCallerFactory$ScanSingleRegionCallerBuilder resultCache(org.apache.hadoop.hbase.client.ScanResultCache);
    Code:
       0: aload_0
       1: aload_1
       2: putfield      #11                 // Field resultCache:Lorg/apache/hadoop/hbase/client/ScanResultCache;
       5: aload_0
       6: areturn

  public org.apache.hadoop.hbase.client.AsyncRpcRetryingCallerFactory$ScanSingleRegionCallerBuilder consumer(org.apache.hadoop.hbase.client.AdvancedScanResultConsumer);
    Code:
       0: aload_0
       1: aload_1
       2: putfield      #12                 // Field consumer:Lorg/apache/hadoop/hbase/client/AdvancedScanResultConsumer;
       5: aload_0
       6: areturn

  public org.apache.hadoop.hbase.client.AsyncRpcRetryingCallerFactory$ScanSingleRegionCallerBuilder stub(org.apache.hadoop.hbase.shaded.protobuf.generated.ClientProtos$ClientService$Interface);
    Code:
       0: aload_0
       1: aload_1
       2: putfield      #13                 // Field stub:Lorg/apache/hadoop/hbase/shaded/protobuf/generated/ClientProtos$ClientService$Interface;
       5: aload_0
       6: areturn

  public org.apache.hadoop.hbase.client.AsyncRpcRetryingCallerFactory$ScanSingleRegionCallerBuilder location(org.apache.hadoop.hbase.HRegionLocation);
    Code:
       0: aload_0
       1: aload_1
       2: putfield      #14                 // Field loc:Lorg/apache/hadoop/hbase/HRegionLocation;
       5: aload_0
       6: areturn

  public org.apache.hadoop.hbase.client.AsyncRpcRetryingCallerFactory$ScanSingleRegionCallerBuilder scannerLeaseTimeoutPeriod(long, java.util.concurrent.TimeUnit);
    Code:
       0: aload_0
       1: aload_3
       2: lload_1
       3: invokevirtual #15                 // Method java/util/concurrent/TimeUnit.toNanos:(J)J
       6: putfield      #16                 // Field scannerLeaseTimeoutPeriodNs:J
       9: aload_0
      10: areturn

  public org.apache.hadoop.hbase.client.AsyncRpcRetryingCallerFactory$ScanSingleRegionCallerBuilder scanTimeout(long, java.util.concurrent.TimeUnit);
    Code:
       0: aload_0
       1: aload_3
       2: lload_1
       3: invokevirtual #15                 // Method java/util/concurrent/TimeUnit.toNanos:(J)J
       6: putfield      #17                 // Field scanTimeoutNs:J
       9: aload_0
      10: areturn

  public org.apache.hadoop.hbase.client.AsyncRpcRetryingCallerFactory$ScanSingleRegionCallerBuilder rpcTimeout(long, java.util.concurrent.TimeUnit);
    Code:
       0: aload_0
       1: aload_3
       2: lload_1
       3: invokevirtual #15                 // Method java/util/concurrent/TimeUnit.toNanos:(J)J
       6: putfield      #18                 // Field rpcTimeoutNs:J
       9: aload_0
      10: areturn

  public org.apache.hadoop.hbase.client.AsyncRpcRetryingCallerFactory$ScanSingleRegionCallerBuilder pause(long, java.util.concurrent.TimeUnit);
    Code:
       0: aload_0
       1: aload_3
       2: lload_1
       3: invokevirtual #15                 // Method java/util/concurrent/TimeUnit.toNanos:(J)J
       6: putfield      #19                 // Field pauseNs:J
       9: aload_0
      10: areturn

  public org.apache.hadoop.hbase.client.AsyncRpcRetryingCallerFactory$ScanSingleRegionCallerBuilder pauseForCQTBE(long, java.util.concurrent.TimeUnit);
    Code:
       0: aload_0
       1: aload_3
       2: lload_1
       3: invokevirtual #15                 // Method java/util/concurrent/TimeUnit.toNanos:(J)J
       6: putfield      #20                 // Field pauseForCQTBENs:J
       9: aload_0
      10: areturn

  public org.apache.hadoop.hbase.client.AsyncRpcRetryingCallerFactory$ScanSingleRegionCallerBuilder maxAttempts(int);
    Code:
       0: aload_0
       1: iload_1
       2: putfield      #21                 // Field maxAttempts:I
       5: aload_0
       6: areturn

  public org.apache.hadoop.hbase.client.AsyncRpcRetryingCallerFactory$ScanSingleRegionCallerBuilder startLogErrorsCnt(int);
    Code:
       0: aload_0
       1: iload_1
       2: putfield      #22                 // Field startLogErrorsCnt:I
       5: aload_0
       6: areturn

  public org.apache.hadoop.hbase.client.AsyncScanSingleRegionRpcRetryingCaller build();
    Code:
       0: aload_0
       1: invokespecial #34                 // Method preCheck:()V
       4: new           #35                 // class org/apache/hadoop/hbase/client/AsyncScanSingleRegionRpcRetryingCaller
       7: dup
       8: aload_0
       9: getfield      #2                  // Field this$0:Lorg/apache/hadoop/hbase/client/AsyncRpcRetryingCallerFactory;
      12: invokestatic  #36                 // Method org/apache/hadoop/hbase/client/AsyncRpcRetryingCallerFactory.access$200:(Lorg/apache/hadoop/hbase/client/AsyncRpcRetryingCallerFactory;)Lorg/apache/hbase/thirdparty/io/netty/util/Timer;
      15: aload_0
      16: getfield      #2                  // Field this$0:Lorg/apache/hadoop/hbase/client/AsyncRpcRetryingCallerFactory;
      19: invokestatic  #37                 // Method org/apache/hadoop/hbase/client/AsyncRpcRetryingCallerFactory.access$000:(Lorg/apache/hadoop/hbase/client/AsyncRpcRetryingCallerFactory;)Lorg/apache/hadoop/hbase/client/AsyncConnectionImpl;
      22: aload_0
      23: getfield      #7                  // Field scan:Lorg/apache/hadoop/hbase/client/Scan;
      26: aload_0
      27: getfield      #9                  // Field scanMetrics:Lorg/apache/hadoop/hbase/client/metrics/ScanMetrics;
      30: aload_0
      31: getfield      #4                  // Field scannerId:Ljava/lang/Long;
      34: invokevirtual #38                 // Method java/lang/Long.longValue:()J
      37: aload_0
      38: getfield      #11                 // Field resultCache:Lorg/apache/hadoop/hbase/client/ScanResultCache;
      41: aload_0
      42: getfield      #12                 // Field consumer:Lorg/apache/hadoop/hbase/client/AdvancedScanResultConsumer;
      45: aload_0
      46: getfield      #13                 // Field stub:Lorg/apache/hadoop/hbase/shaded/protobuf/generated/ClientProtos$ClientService$Interface;
      49: aload_0
      50: getfield      #14                 // Field loc:Lorg/apache/hadoop/hbase/HRegionLocation;
      53: aload_0
      54: getfield      #10                 // Field isRegionServerRemote:Z
      57: aload_0
      58: getfield      #5                  // Field priority:I
      61: aload_0
      62: getfield      #16                 // Field scannerLeaseTimeoutPeriodNs:J
      65: aload_0
      66: getfield      #19                 // Field pauseNs:J
      69: aload_0
      70: getfield      #20                 // Field pauseForCQTBENs:J
      73: aload_0
      74: getfield      #21                 // Field maxAttempts:I
      77: aload_0
      78: getfield      #17                 // Field scanTimeoutNs:J
      81: aload_0
      82: getfield      #18                 // Field rpcTimeoutNs:J
      85: aload_0
      86: getfield      #22                 // Field startLogErrorsCnt:I
      89: invokespecial #39                 // Method org/apache/hadoop/hbase/client/AsyncScanSingleRegionRpcRetryingCaller."<init>":(Lorg/apache/hbase/thirdparty/io/netty/util/Timer;Lorg/apache/hadoop/hbase/client/AsyncConnectionImpl;Lorg/apache/hadoop/hbase/client/Scan;Lorg/apache/hadoop/hbase/client/metrics/ScanMetrics;JLorg/apache/hadoop/hbase/client/ScanResultCache;Lorg/apache/hadoop/hbase/client/AdvancedScanResultConsumer;Lorg/apache/hadoop/hbase/shaded/protobuf/generated/ClientProtos$ClientService$Interface;Lorg/apache/hadoop/hbase/HRegionLocation;ZIJJJIJJI)V
      92: areturn

  public java.util.concurrent.CompletableFuture<java.lang.Boolean> start(org.apache.hadoop.hbase.ipc.HBaseRpcController, org.apache.hadoop.hbase.shaded.protobuf.generated.ClientProtos$ScanResponse);
    Code:
       0: aload_0
       1: invokevirtual #40                 // Method build:()Lorg/apache/hadoop/hbase/client/AsyncScanSingleRegionRpcRetryingCaller;
       4: aload_1
       5: aload_2
       6: invokevirtual #41                 // Method org/apache/hadoop/hbase/client/AsyncScanSingleRegionRpcRetryingCaller.start:(Lorg/apache/hadoop/hbase/ipc/HBaseRpcController;Lorg/apache/hadoop/hbase/shaded/protobuf/generated/ClientProtos$ScanResponse;)Ljava/util/concurrent/CompletableFuture;
       9: areturn
}
