Compiled from "AsyncProcess.java"
final class org.apache.hadoop.hbase.client.AsyncProcess$1 implements org.apache.hadoop.hbase.client.AsyncRequestFuture {
  final java.lang.Object[] result;

  org.apache.hadoop.hbase.client.AsyncProcess$1();
    Code:
       0: aload_0
       1: invokespecial #1                  // Method java/lang/Object."<init>":()V
       4: aload_0
       5: iconst_0
       6: anewarray     #2                  // class java/lang/Object
       9: putfield      #3                  // Field result:[Ljava/lang/Object;
      12: return

  public boolean hasError();
    Code:
       0: iconst_0
       1: ireturn

  public org.apache.hadoop.hbase.client.RetriesExhaustedWithDetailsException getErrors();
    Code:
       0: aconst_null
       1: areturn

  public java.util.List<? extends org.apache.hadoop.hbase.client.Row> getFailedOperations();
    Code:
       0: aconst_null
       1: areturn

  public java.lang.Object[] getResults();
    Code:
       0: aload_0
       1: getfield      #3                  // Field result:[Ljava/lang/Object;
       4: areturn

  public void waitUntilDone() throws java.io.InterruptedIOException;
    Code:
       0: return
}
