Compiled from "AuthenticationTokenSecretManager.java"
class org.apache.hadoop.hbase.security.token.AuthenticationTokenSecretManager$LeaderElector extends java.lang.Thread implements org.apache.hadoop.hbase.Stoppable {
  final org.apache.hadoop.hbase.security.token.AuthenticationTokenSecretManager this$0;

  public org.apache.hadoop.hbase.security.token.AuthenticationTokenSecretManager$LeaderElector(org.apache.hadoop.hbase.security.token.AuthenticationTokenSecretManager, org.apache.hadoop.hbase.zookeeper.ZKWatcher, java.lang.String);
    Code:
       0: aload_0
       1: aload_1
       2: putfield      #1                  // Field this$0:Lorg/apache/hadoop/hbase/security/token/AuthenticationTokenSecretManager;
       5: aload_0
       6: invokespecial #2                  // Method java/lang/Thread."<init>":()V
       9: aload_0
      10: iconst_0
      11: putfield      #3                  // Field stopped:Z
      14: aload_0
      15: iconst_0
      16: putfield      #4                  // Field isMaster:Z
      19: aload_0
      20: iconst_1
      21: invokevirtual #5                  // Method setDaemon:(Z)V
      24: aload_0
      25: ldc           #6                  // String ZKSecretWatcher-leaderElector
      27: invokevirtual #7                  // Method setName:(Ljava/lang/String;)V
      30: aload_0
      31: new           #8                  // class org/apache/hadoop/hbase/zookeeper/ZKLeaderManager
      34: dup
      35: aload_2
      36: aload_1
      37: invokestatic  #9                  // Method org/apache/hadoop/hbase/security/token/AuthenticationTokenSecretManager.access$000:(Lorg/apache/hadoop/hbase/security/token/AuthenticationTokenSecretManager;)Lorg/apache/hadoop/hbase/security/token/ZKSecretWatcher;
      40: invokevirtual #10                 // Method org/apache/hadoop/hbase/security/token/ZKSecretWatcher.getRootKeyZNode:()Ljava/lang/String;
      43: ldc           #11                 // String keymaster
      45: invokestatic  #12                 // Method org/apache/hadoop/hbase/zookeeper/ZNodePaths.joinZNode:(Ljava/lang/String;Ljava/lang/String;)Ljava/lang/String;
      48: aload_3
      49: invokestatic  #13                 // Method org/apache/hadoop/hbase/util/Bytes.toBytes:(Ljava/lang/String;)[B
      52: aload_0
      53: invokespecial #14                 // Method org/apache/hadoop/hbase/zookeeper/ZKLeaderManager."<init>":(Lorg/apache/hadoop/hbase/zookeeper/ZKWatcher;Ljava/lang/String;[BLorg/apache/hadoop/hbase/Stoppable;)V
      56: putfield      #15                 // Field zkLeader:Lorg/apache/hadoop/hbase/zookeeper/ZKLeaderManager;
      59: return

  public boolean isMaster();
    Code:
       0: aload_0
       1: getfield      #4                  // Field isMaster:Z
       4: ireturn

  public boolean isStopped();
    Code:
       0: aload_0
       1: getfield      #3                  // Field stopped:Z
       4: ireturn

  public void stop(java.lang.String);
    Code:
       0: aload_0
       1: getfield      #3                  // Field stopped:Z
       4: ifeq          8
       7: return
       8: aload_0
       9: iconst_1
      10: putfield      #3                  // Field stopped:Z
      13: aload_0
      14: getfield      #4                  // Field isMaster:Z
      17: ifeq          27
      20: aload_0
      21: getfield      #15                 // Field zkLeader:Lorg/apache/hadoop/hbase/zookeeper/ZKLeaderManager;
      24: invokevirtual #16                 // Method org/apache/hadoop/hbase/zookeeper/ZKLeaderManager.stepDownAsLeader:()V
      27: aload_0
      28: iconst_0
      29: putfield      #4                  // Field isMaster:Z
      32: invokestatic  #17                 // Method org/apache/hadoop/hbase/security/token/AuthenticationTokenSecretManager.access$100:()Lorg/slf4j/Logger;
      35: new           #18                 // class java/lang/StringBuilder
      38: dup
      39: invokespecial #19                 // Method java/lang/StringBuilder."<init>":()V
      42: ldc           #20                 // String Stopping leader election, because:
      44: invokevirtual #21                 // Method java/lang/StringBuilder.append:(Ljava/lang/String;)Ljava/lang/StringBuilder;
      47: aload_1
      48: invokevirtual #21                 // Method java/lang/StringBuilder.append:(Ljava/lang/String;)Ljava/lang/StringBuilder;
      51: invokevirtual #22                 // Method java/lang/StringBuilder.toString:()Ljava/lang/String;
      54: invokeinterface #23,  2           // InterfaceMethod org/slf4j/Logger.info:(Ljava/lang/String;)V
      59: aload_0
      60: invokevirtual #24                 // Method interrupt:()V
      63: return

  public void run();
    Code:
       0: aload_0
       1: getfield      #15                 // Field zkLeader:Lorg/apache/hadoop/hbase/zookeeper/ZKLeaderManager;
       4: invokevirtual #25                 // Method org/apache/hadoop/hbase/zookeeper/ZKLeaderManager.start:()V
       7: aload_0
       8: getfield      #15                 // Field zkLeader:Lorg/apache/hadoop/hbase/zookeeper/ZKLeaderManager;
      11: invokevirtual #26                 // Method org/apache/hadoop/hbase/zookeeper/ZKLeaderManager.waitToBecomeLeader:()V
      14: aload_0
      15: iconst_1
      16: putfield      #4                  // Field isMaster:Z
      19: aload_0
      20: getfield      #3                  // Field stopped:Z
      23: ifne          103
      26: invokestatic  #27                 // Method org/apache/hadoop/hbase/util/EnvironmentEdgeManager.currentTime:()J
      29: lstore_1
      30: aload_0
      31: getfield      #1                  // Field this$0:Lorg/apache/hadoop/hbase/security/token/AuthenticationTokenSecretManager;
      34: invokevirtual #28                 // Method org/apache/hadoop/hbase/security/token/AuthenticationTokenSecretManager.removeExpiredKeys:()V
      37: aload_0
      38: getfield      #1                  // Field this$0:Lorg/apache/hadoop/hbase/security/token/AuthenticationTokenSecretManager;
      41: invokevirtual #29                 // Method org/apache/hadoop/hbase/security/token/AuthenticationTokenSecretManager.getLastKeyUpdate:()J
      44: lstore_3
      45: lload_3
      46: aload_0
      47: getfield      #1                  // Field this$0:Lorg/apache/hadoop/hbase/security/token/AuthenticationTokenSecretManager;
      50: invokestatic  #30                 // Method org/apache/hadoop/hbase/security/token/AuthenticationTokenSecretManager.access$200:(Lorg/apache/hadoop/hbase/security/token/AuthenticationTokenSecretManager;)J
      53: ladd
      54: lload_1
      55: lcmp
      56: ifge          66
      59: aload_0
      60: getfield      #1                  // Field this$0:Lorg/apache/hadoop/hbase/security/token/AuthenticationTokenSecretManager;
      63: invokevirtual #31                 // Method org/apache/hadoop/hbase/security/token/AuthenticationTokenSecretManager.rollCurrentKey:()V
      66: ldc2_w        #32                 // long 5000l
      69: invokestatic  #34                 // Method java/lang/Thread.sleep:(J)V
      72: goto          100
      75: astore        5
      77: invokestatic  #17                 // Method org/apache/hadoop/hbase/security/token/AuthenticationTokenSecretManager.access$100:()Lorg/slf4j/Logger;
      80: invokeinterface #36,  1           // InterfaceMethod org/slf4j/Logger.isDebugEnabled:()Z
      85: ifeq          100
      88: invokestatic  #17                 // Method org/apache/hadoop/hbase/security/token/AuthenticationTokenSecretManager.access$100:()Lorg/slf4j/Logger;
      91: ldc           #37                 // String Interrupted waiting for next update
      93: aload         5
      95: invokeinterface #38,  3           // InterfaceMethod org/slf4j/Logger.debug:(Ljava/lang/String;Ljava/lang/Throwable;)V
     100: goto          19
     103: return
    Exception table:
       from    to  target type
          66    72    75   Class java/lang/InterruptedException
}
