Compiled from "AuthUtil.java"
final class org.apache.hadoop.hbase.AuthUtil$1 extends org.apache.hadoop.hbase.ScheduledChore {
  final org.apache.hadoop.security.UserGroupInformation val$user;

  org.apache.hadoop.hbase.AuthUtil$1(java.lang.String, org.apache.hadoop.hbase.Stoppable, int, org.apache.hadoop.security.UserGroupInformation);
    Code:
       0: aload_0
       1: aload         4
       3: putfield      #1                  // Field val$user:Lorg/apache/hadoop/security/UserGroupInformation;
       6: aload_0
       7: aload_1
       8: aload_2
       9: iload_3
      10: invokespecial #2                  // Method org/apache/hadoop/hbase/ScheduledChore."<init>":(Ljava/lang/String;Lorg/apache/hadoop/hbase/Stoppable;I)V
      13: return

  protected void chore();
    Code:
       0: aload_0
       1: getfield      #1                  // Field val$user:Lorg/apache/hadoop/security/UserGroupInformation;
       4: invokevirtual #3                  // Method org/apache/hadoop/security/UserGroupInformation.checkTGTAndReloginFromKeytab:()V
       7: goto          42
      10: astore_1
      11: invokestatic  #5                  // Method org/apache/hadoop/hbase/AuthUtil.access$000:()Lorg/slf4j/Logger;
      14: new           #6                  // class java/lang/StringBuilder
      17: dup
      18: invokespecial #7                  // Method java/lang/StringBuilder."<init>":()V
      21: ldc           #8                  // String Got exception while trying to refresh credentials:
      23: invokevirtual #9                  // Method java/lang/StringBuilder.append:(Ljava/lang/String;)Ljava/lang/StringBuilder;
      26: aload_1
      27: invokevirtual #10                 // Method java/io/IOException.getMessage:()Ljava/lang/String;
      30: invokevirtual #9                  // Method java/lang/StringBuilder.append:(Ljava/lang/String;)Ljava/lang/StringBuilder;
      33: invokevirtual #11                 // Method java/lang/StringBuilder.toString:()Ljava/lang/String;
      36: aload_1
      37: invokeinterface #12,  3           // InterfaceMethod org/slf4j/Logger.error:(Ljava/lang/String;Ljava/lang/Throwable;)V
      42: return
    Exception table:
       from    to  target type
           0     7    10   Class java/io/IOException
}
