Compiled from "AuthResult.java"
public class org.apache.hadoop.hbase.security.access.AuthResult {
  public org.apache.hadoop.hbase.security.access.AuthResult(boolean, java.lang.String, java.lang.String, org.apache.hadoop.hbase.security.User, org.apache.hadoop.hbase.security.access.Permission$Action, org.apache.hadoop.hbase.TableName, byte[], byte[]);
    Code:
       0: aload_0
       1: invokespecial #2                  // Method java/lang/Object."<init>":()V
       4: aload_0
       5: iload_1
       6: putfield      #3                  // Field allowed:Z
       9: aload_0
      10: aload_2
      11: putfield      #4                  // Field request:Ljava/lang/String;
      14: aload_0
      15: aload_3
      16: putfield      #5                  // Field reason:Ljava/lang/String;
      19: aload_0
      20: aload         4
      22: putfield      #6                  // Field user:Lorg/apache/hadoop/hbase/security/User;
      25: aload_0
      26: aload         6
      28: putfield      #7                  // Field table:Lorg/apache/hadoop/hbase/TableName;
      31: aload_0
      32: aload         7
      34: putfield      #8                  // Field family:[B
      37: aload_0
      38: aload         8
      40: putfield      #9                  // Field qualifier:[B
      43: aload_0
      44: aload         5
      46: putfield      #10                 // Field action:Lorg/apache/hadoop/hbase/security/access/Permission$Action;
      49: aload_0
      50: aconst_null
      51: putfield      #11                 // Field families:Ljava/util/Map;
      54: aload_0
      55: aconst_null
      56: putfield      #12                 // Field namespace:Ljava/lang/String;
      59: aload_0
      60: new           #13                 // class org/apache/hadoop/hbase/security/access/AuthResult$Params
      63: dup
      64: invokespecial #14                 // Method org/apache/hadoop/hbase/security/access/AuthResult$Params."<init>":()V
      67: aload         6
      69: invokevirtual #15                 // Method org/apache/hadoop/hbase/security/access/AuthResult$Params.setTableName:(Lorg/apache/hadoop/hbase/TableName;)Lorg/apache/hadoop/hbase/security/access/AuthResult$Params;
      72: aload         7
      74: invokevirtual #16                 // Method org/apache/hadoop/hbase/security/access/AuthResult$Params.setFamily:([B)Lorg/apache/hadoop/hbase/security/access/AuthResult$Params;
      77: aload         8
      79: invokevirtual #17                 // Method org/apache/hadoop/hbase/security/access/AuthResult$Params.setQualifier:([B)Lorg/apache/hadoop/hbase/security/access/AuthResult$Params;
      82: putfield      #18                 // Field params:Lorg/apache/hadoop/hbase/security/access/AuthResult$Params;
      85: return

  public org.apache.hadoop.hbase.security.access.AuthResult(boolean, java.lang.String, java.lang.String, org.apache.hadoop.hbase.security.User, org.apache.hadoop.hbase.security.access.Permission$Action, org.apache.hadoop.hbase.TableName, java.util.Map<byte[], ? extends java.util.Collection<?>>);
    Code:
       0: aload_0
       1: invokespecial #2                  // Method java/lang/Object."<init>":()V
       4: aload_0
       5: iload_1
       6: putfield      #3                  // Field allowed:Z
       9: aload_0
      10: aload_2
      11: putfield      #4                  // Field request:Ljava/lang/String;
      14: aload_0
      15: aload_3
      16: putfield      #5                  // Field reason:Ljava/lang/String;
      19: aload_0
      20: aload         4
      22: putfield      #6                  // Field user:Lorg/apache/hadoop/hbase/security/User;
      25: aload_0
      26: aload         6
      28: putfield      #7                  // Field table:Lorg/apache/hadoop/hbase/TableName;
      31: aload_0
      32: aconst_null
      33: putfield      #8                  // Field family:[B
      36: aload_0
      37: aconst_null
      38: putfield      #9                  // Field qualifier:[B
      41: aload_0
      42: aload         5
      44: putfield      #10                 // Field action:Lorg/apache/hadoop/hbase/security/access/Permission$Action;
      47: aload_0
      48: aload         7
      50: putfield      #11                 // Field families:Ljava/util/Map;
      53: aload_0
      54: aconst_null
      55: putfield      #12                 // Field namespace:Ljava/lang/String;
      58: aload_0
      59: new           #13                 // class org/apache/hadoop/hbase/security/access/AuthResult$Params
      62: dup
      63: invokespecial #14                 // Method org/apache/hadoop/hbase/security/access/AuthResult$Params."<init>":()V
      66: aload         6
      68: invokevirtual #15                 // Method org/apache/hadoop/hbase/security/access/AuthResult$Params.setTableName:(Lorg/apache/hadoop/hbase/TableName;)Lorg/apache/hadoop/hbase/security/access/AuthResult$Params;
      71: aload         7
      73: invokevirtual #19                 // Method org/apache/hadoop/hbase/security/access/AuthResult$Params.setFamilies:(Ljava/util/Map;)Lorg/apache/hadoop/hbase/security/access/AuthResult$Params;
      76: putfield      #18                 // Field params:Lorg/apache/hadoop/hbase/security/access/AuthResult$Params;
      79: return

  public org.apache.hadoop.hbase.security.access.AuthResult(boolean, java.lang.String, java.lang.String, org.apache.hadoop.hbase.security.User, org.apache.hadoop.hbase.security.access.Permission$Action, java.lang.String);
    Code:
       0: aload_0
       1: invokespecial #2                  // Method java/lang/Object."<init>":()V
       4: aload_0
       5: iload_1
       6: putfield      #3                  // Field allowed:Z
       9: aload_0
      10: aload_2
      11: putfield      #4                  // Field request:Ljava/lang/String;
      14: aload_0
      15: aload_3
      16: putfield      #5                  // Field reason:Ljava/lang/String;
      19: aload_0
      20: aload         4
      22: putfield      #6                  // Field user:Lorg/apache/hadoop/hbase/security/User;
      25: aload_0
      26: aload         6
      28: putfield      #12                 // Field namespace:Ljava/lang/String;
      31: aload_0
      32: aload         5
      34: putfield      #10                 // Field action:Lorg/apache/hadoop/hbase/security/access/Permission$Action;
      37: aload_0
      38: aconst_null
      39: putfield      #7                  // Field table:Lorg/apache/hadoop/hbase/TableName;
      42: aload_0
      43: aconst_null
      44: putfield      #8                  // Field family:[B
      47: aload_0
      48: aconst_null
      49: putfield      #9                  // Field qualifier:[B
      52: aload_0
      53: aconst_null
      54: putfield      #11                 // Field families:Ljava/util/Map;
      57: aload_0
      58: new           #13                 // class org/apache/hadoop/hbase/security/access/AuthResult$Params
      61: dup
      62: invokespecial #14                 // Method org/apache/hadoop/hbase/security/access/AuthResult$Params."<init>":()V
      65: aload         6
      67: invokevirtual #20                 // Method org/apache/hadoop/hbase/security/access/AuthResult$Params.setNamespace:(Ljava/lang/String;)Lorg/apache/hadoop/hbase/security/access/AuthResult$Params;
      70: putfield      #18                 // Field params:Lorg/apache/hadoop/hbase/security/access/AuthResult$Params;
      73: return

  public boolean isAllowed();
    Code:
       0: aload_0
       1: getfield      #3                  // Field allowed:Z
       4: ireturn

  public org.apache.hadoop.hbase.security.User getUser();
    Code:
       0: aload_0
       1: getfield      #6                  // Field user:Lorg/apache/hadoop/hbase/security/User;
       4: areturn

  public java.lang.String getReason();
    Code:
       0: aload_0
       1: getfield      #5                  // Field reason:Ljava/lang/String;
       4: areturn

  public org.apache.hadoop.hbase.TableName getTableName();
    Code:
       0: aload_0
       1: getfield      #7                  // Field table:Lorg/apache/hadoop/hbase/TableName;
       4: areturn

  public byte[] getFamily();
    Code:
       0: aload_0
       1: getfield      #8                  // Field family:[B
       4: areturn

  public byte[] getQualifier();
    Code:
       0: aload_0
       1: getfield      #9                  // Field qualifier:[B
       4: areturn

  public org.apache.hadoop.hbase.security.access.Permission$Action getAction();
    Code:
       0: aload_0
       1: getfield      #10                 // Field action:Lorg/apache/hadoop/hbase/security/access/Permission$Action;
       4: areturn

  public java.lang.String getRequest();
    Code:
       0: aload_0
       1: getfield      #4                  // Field request:Ljava/lang/String;
       4: areturn

  public org.apache.hadoop.hbase.security.access.AuthResult$Params getParams();
    Code:
       0: aload_0
       1: getfield      #18                 // Field params:Lorg/apache/hadoop/hbase/security/access/AuthResult$Params;
       4: areturn

  public void setAllowed(boolean);
    Code:
       0: aload_0
       1: iload_1
       2: putfield      #3                  // Field allowed:Z
       5: return

  public void setReason(java.lang.String);
    Code:
       0: aload_0
       1: aload_1
       2: putfield      #5                  // Field reason:Ljava/lang/String;
       5: return

  public java.lang.String toContextString();
    Code:
       0: new           #21                 // class java/lang/StringBuilder
       3: dup
       4: invokespecial #22                 // Method java/lang/StringBuilder."<init>":()V
       7: astore_1
       8: aload_0
       9: getfield      #11                 // Field families:Ljava/util/Map;
      12: aload_0
      13: getfield      #8                  // Field family:[B
      16: aload_0
      17: getfield      #9                  // Field qualifier:[B
      20: invokestatic  #1                  // Method toFamiliesString:(Ljava/util/Map;[B[B)Ljava/lang/String;
      23: astore_2
      24: aload_1
      25: ldc           #45                 // String (user=
      27: invokevirtual #42                 // Method java/lang/StringBuilder.append:(Ljava/lang/String;)Ljava/lang/StringBuilder;
      30: aload_0
      31: getfield      #6                  // Field user:Lorg/apache/hadoop/hbase/security/User;
      34: ifnull        47
      37: aload_0
      38: getfield      #6                  // Field user:Lorg/apache/hadoop/hbase/security/User;
      41: invokevirtual #46                 // Method org/apache/hadoop/hbase/security/User.getName:()Ljava/lang/String;
      44: goto          49
      47: ldc           #47                 // String UNKNOWN
      49: invokevirtual #42                 // Method java/lang/StringBuilder.append:(Ljava/lang/String;)Ljava/lang/StringBuilder;
      52: ldc           #48                 // String ,
      54: invokevirtual #42                 // Method java/lang/StringBuilder.append:(Ljava/lang/String;)Ljava/lang/StringBuilder;
      57: pop
      58: aload_1
      59: ldc           #49                 // String scope=
      61: invokevirtual #42                 // Method java/lang/StringBuilder.append:(Ljava/lang/String;)Ljava/lang/StringBuilder;
      64: aload_0
      65: getfield      #12                 // Field namespace:Ljava/lang/String;
      68: ifnull        78
      71: aload_0
      72: getfield      #12                 // Field namespace:Ljava/lang/String;
      75: goto          97
      78: aload_0
      79: getfield      #7                  // Field table:Lorg/apache/hadoop/hbase/TableName;
      82: ifnonnull     90
      85: ldc           #50                 // String GLOBAL
      87: goto          97
      90: aload_0
      91: getfield      #7                  // Field table:Lorg/apache/hadoop/hbase/TableName;
      94: invokevirtual #51                 // Method org/apache/hadoop/hbase/TableName.getNameWithNamespaceInclAsString:()Ljava/lang/String;
      97: invokevirtual #42                 // Method java/lang/StringBuilder.append:(Ljava/lang/String;)Ljava/lang/StringBuilder;
     100: ldc           #48                 // String ,
     102: invokevirtual #42                 // Method java/lang/StringBuilder.append:(Ljava/lang/String;)Ljava/lang/StringBuilder;
     105: pop
     106: aload_0
     107: getfield      #12                 // Field namespace:Ljava/lang/String;
     110: ifnonnull     136
     113: aload_2
     114: invokevirtual #52                 // Method java/lang/String.length:()I
     117: ifle          136
     120: aload_1
     121: ldc           #53                 // String family=
     123: invokevirtual #42                 // Method java/lang/StringBuilder.append:(Ljava/lang/String;)Ljava/lang/StringBuilder;
     126: aload_2
     127: invokevirtual #42                 // Method java/lang/StringBuilder.append:(Ljava/lang/String;)Ljava/lang/StringBuilder;
     130: ldc           #48                 // String ,
     132: invokevirtual #42                 // Method java/lang/StringBuilder.append:(Ljava/lang/String;)Ljava/lang/StringBuilder;
     135: pop
     136: aload_0
     137: getfield      #18                 // Field params:Lorg/apache/hadoop/hbase/security/access/AuthResult$Params;
     140: invokevirtual #54                 // Method org/apache/hadoop/hbase/security/access/AuthResult$Params.toString:()Ljava/lang/String;
     143: astore_3
     144: aload_3
     145: invokevirtual #52                 // Method java/lang/String.length:()I
     148: ifle          167
     151: aload_1
     152: ldc           #55                 // String params=[
     154: invokevirtual #42                 // Method java/lang/StringBuilder.append:(Ljava/lang/String;)Ljava/lang/StringBuilder;
     157: aload_3
     158: invokevirtual #42                 // Method java/lang/StringBuilder.append:(Ljava/lang/String;)Ljava/lang/StringBuilder;
     161: ldc           #56                 // String ],
     163: invokevirtual #42                 // Method java/lang/StringBuilder.append:(Ljava/lang/String;)Ljava/lang/StringBuilder;
     166: pop
     167: aload_1
     168: ldc           #57                 // String action=
     170: invokevirtual #42                 // Method java/lang/StringBuilder.append:(Ljava/lang/String;)Ljava/lang/StringBuilder;
     173: aload_0
     174: getfield      #10                 // Field action:Lorg/apache/hadoop/hbase/security/access/Permission$Action;
     177: ifnull        190
     180: aload_0
     181: getfield      #10                 // Field action:Lorg/apache/hadoop/hbase/security/access/Permission$Action;
     184: invokevirtual #58                 // Method org/apache/hadoop/hbase/security/access/Permission$Action.toString:()Ljava/lang/String;
     187: goto          192
     190: ldc           #59                 // String
     192: invokevirtual #42                 // Method java/lang/StringBuilder.append:(Ljava/lang/String;)Ljava/lang/StringBuilder;
     195: ldc           #60                 // String )
     197: invokevirtual #42                 // Method java/lang/StringBuilder.append:(Ljava/lang/String;)Ljava/lang/StringBuilder;
     200: pop
     201: aload_1
     202: invokevirtual #44                 // Method java/lang/StringBuilder.toString:()Ljava/lang/String;
     205: areturn

  public java.lang.String toString();
    Code:
       0: new           #21                 // class java/lang/StringBuilder
       3: dup
       4: invokespecial #22                 // Method java/lang/StringBuilder."<init>":()V
       7: ldc           #61                 // String AuthResult
       9: invokevirtual #42                 // Method java/lang/StringBuilder.append:(Ljava/lang/String;)Ljava/lang/StringBuilder;
      12: aload_0
      13: invokevirtual #62                 // Method toContextString:()Ljava/lang/String;
      16: invokevirtual #42                 // Method java/lang/StringBuilder.append:(Ljava/lang/String;)Ljava/lang/StringBuilder;
      19: invokevirtual #44                 // Method java/lang/StringBuilder.toString:()Ljava/lang/String;
      22: areturn

  public static org.apache.hadoop.hbase.security.access.AuthResult allow(java.lang.String, java.lang.String, org.apache.hadoop.hbase.security.User, org.apache.hadoop.hbase.security.access.Permission$Action, java.lang.String);
    Code:
       0: new           #63                 // class org/apache/hadoop/hbase/security/access/AuthResult
       3: dup
       4: iconst_1
       5: aload_0
       6: aload_1
       7: aload_2
       8: aload_3
       9: aload         4
      11: invokespecial #64                 // Method "<init>":(ZLjava/lang/String;Ljava/lang/String;Lorg/apache/hadoop/hbase/security/User;Lorg/apache/hadoop/hbase/security/access/Permission$Action;Ljava/lang/String;)V
      14: areturn

  public static org.apache.hadoop.hbase.security.access.AuthResult allow(java.lang.String, java.lang.String, org.apache.hadoop.hbase.security.User, org.apache.hadoop.hbase.security.access.Permission$Action, org.apache.hadoop.hbase.TableName, byte[], byte[]);
    Code:
       0: new           #63                 // class org/apache/hadoop/hbase/security/access/AuthResult
       3: dup
       4: iconst_1
       5: aload_0
       6: aload_1
       7: aload_2
       8: aload_3
       9: aload         4
      11: aload         5
      13: aload         6
      15: invokespecial #65                 // Method "<init>":(ZLjava/lang/String;Ljava/lang/String;Lorg/apache/hadoop/hbase/security/User;Lorg/apache/hadoop/hbase/security/access/Permission$Action;Lorg/apache/hadoop/hbase/TableName;[B[B)V
      18: areturn

  public static org.apache.hadoop.hbase.security.access.AuthResult allow(java.lang.String, java.lang.String, org.apache.hadoop.hbase.security.User, org.apache.hadoop.hbase.security.access.Permission$Action, org.apache.hadoop.hbase.TableName, java.util.Map<byte[], ? extends java.util.Collection<?>>);
    Code:
       0: new           #63                 // class org/apache/hadoop/hbase/security/access/AuthResult
       3: dup
       4: iconst_1
       5: aload_0
       6: aload_1
       7: aload_2
       8: aload_3
       9: aload         4
      11: aload         5
      13: invokespecial #66                 // Method "<init>":(ZLjava/lang/String;Ljava/lang/String;Lorg/apache/hadoop/hbase/security/User;Lorg/apache/hadoop/hbase/security/access/Permission$Action;Lorg/apache/hadoop/hbase/TableName;Ljava/util/Map;)V
      16: areturn

  public static org.apache.hadoop.hbase.security.access.AuthResult deny(java.lang.String, java.lang.String, org.apache.hadoop.hbase.security.User, org.apache.hadoop.hbase.security.access.Permission$Action, java.lang.String);
    Code:
       0: new           #63                 // class org/apache/hadoop/hbase/security/access/AuthResult
       3: dup
       4: iconst_0
       5: aload_0
       6: aload_1
       7: aload_2
       8: aload_3
       9: aload         4
      11: invokespecial #64                 // Method "<init>":(ZLjava/lang/String;Ljava/lang/String;Lorg/apache/hadoop/hbase/security/User;Lorg/apache/hadoop/hbase/security/access/Permission$Action;Ljava/lang/String;)V
      14: areturn

  public static org.apache.hadoop.hbase.security.access.AuthResult deny(java.lang.String, java.lang.String, org.apache.hadoop.hbase.security.User, org.apache.hadoop.hbase.security.access.Permission$Action, org.apache.hadoop.hbase.TableName, byte[], byte[]);
    Code:
       0: new           #63                 // class org/apache/hadoop/hbase/security/access/AuthResult
       3: dup
       4: iconst_0
       5: aload_0
       6: aload_1
       7: aload_2
       8: aload_3
       9: aload         4
      11: aload         5
      13: aload         6
      15: invokespecial #65                 // Method "<init>":(ZLjava/lang/String;Ljava/lang/String;Lorg/apache/hadoop/hbase/security/User;Lorg/apache/hadoop/hbase/security/access/Permission$Action;Lorg/apache/hadoop/hbase/TableName;[B[B)V
      18: areturn

  public static org.apache.hadoop.hbase.security.access.AuthResult deny(java.lang.String, java.lang.String, org.apache.hadoop.hbase.security.User, org.apache.hadoop.hbase.security.access.Permission$Action, org.apache.hadoop.hbase.TableName, java.util.Map<byte[], ? extends java.util.Collection<?>>);
    Code:
       0: new           #63                 // class org/apache/hadoop/hbase/security/access/AuthResult
       3: dup
       4: iconst_0
       5: aload_0
       6: aload_1
       7: aload_2
       8: aload_3
       9: aload         4
      11: aload         5
      13: invokespecial #66                 // Method "<init>":(ZLjava/lang/String;Ljava/lang/String;Lorg/apache/hadoop/hbase/security/User;Lorg/apache/hadoop/hbase/security/access/Permission$Action;Lorg/apache/hadoop/hbase/TableName;Ljava/util/Map;)V
      16: areturn

  public java.lang.String toFamilyString();
    Code:
       0: aload_0
       1: getfield      #11                 // Field families:Ljava/util/Map;
       4: aload_0
       5: getfield      #8                  // Field family:[B
       8: aload_0
       9: getfield      #9                  // Field qualifier:[B
      12: invokestatic  #1                  // Method toFamiliesString:(Ljava/util/Map;[B[B)Ljava/lang/String;
      15: areturn

  static java.lang.String access$000(java.util.Map, byte[], byte[]);
    Code:
       0: aload_0
       1: aload_1
       2: aload_2
       3: invokestatic  #1                  // Method toFamiliesString:(Ljava/util/Map;[B[B)Ljava/lang/String;
       6: areturn
}
