Compiled from "AvlUtil.java"
public class org.apache.hadoop.hbase.util.AvlUtil$AvlTreeIterator<TNode extends org.apache.hadoop.hbase.util.AvlUtil$AvlNode> implements java.util.Iterator<TNode> {
  public org.apache.hadoop.hbase.util.AvlUtil$AvlTreeIterator();
    Code:
       0: aload_0
       1: invokespecial #1                  // Method java/lang/Object."<init>":()V
       4: aload_0
       5: bipush        64
       7: anewarray     #2                  // class java/lang/Object
      10: putfield      #3                  // Field stack:[Ljava/lang/Object;
      13: aload_0
      14: aconst_null
      15: putfield      #4                  // Field current:Lorg/apache/hadoop/hbase/util/AvlUtil$AvlNode;
      18: aload_0
      19: iconst_0
      20: putfield      #5                  // Field height:I
      23: return

  public org.apache.hadoop.hbase.util.AvlUtil$AvlTreeIterator(TNode);
    Code:
       0: aload_0
       1: invokespecial #1                  // Method java/lang/Object."<init>":()V
       4: aload_0
       5: bipush        64
       7: anewarray     #2                  // class java/lang/Object
      10: putfield      #3                  // Field stack:[Ljava/lang/Object;
      13: aload_0
      14: aconst_null
      15: putfield      #4                  // Field current:Lorg/apache/hadoop/hbase/util/AvlUtil$AvlNode;
      18: aload_0
      19: iconst_0
      20: putfield      #5                  // Field height:I
      23: aload_0
      24: aload_1
      25: invokevirtual #6                  // Method seekFirst:(Lorg/apache/hadoop/hbase/util/AvlUtil$AvlNode;)V
      28: return

  public org.apache.hadoop.hbase.util.AvlUtil$AvlTreeIterator(TNode, java.lang.Object, org.apache.hadoop.hbase.util.AvlUtil$AvlKeyComparator<TNode>);
    Code:
       0: aload_0
       1: invokespecial #1                  // Method java/lang/Object."<init>":()V
       4: aload_0
       5: bipush        64
       7: anewarray     #2                  // class java/lang/Object
      10: putfield      #3                  // Field stack:[Ljava/lang/Object;
      13: aload_0
      14: aconst_null
      15: putfield      #4                  // Field current:Lorg/apache/hadoop/hbase/util/AvlUtil$AvlNode;
      18: aload_0
      19: iconst_0
      20: putfield      #5                  // Field height:I
      23: aload_0
      24: aload_1
      25: aload_2
      26: aload_3
      27: invokevirtual #7                  // Method seekTo:(Lorg/apache/hadoop/hbase/util/AvlUtil$AvlNode;Ljava/lang/Object;Lorg/apache/hadoop/hbase/util/AvlUtil$AvlKeyComparator;)V
      30: return

  public boolean hasNext();
    Code:
       0: aload_0
       1: getfield      #4                  // Field current:Lorg/apache/hadoop/hbase/util/AvlUtil$AvlNode;
       4: ifnull        11
       7: iconst_1
       8: goto          12
      11: iconst_0
      12: ireturn

  public TNode next();
    Code:
       0: aload_0
       1: getfield      #4                  // Field current:Lorg/apache/hadoop/hbase/util/AvlUtil$AvlNode;
       4: astore_1
       5: aload_0
       6: invokespecial #8                  // Method seekNext:()V
       9: aload_1
      10: areturn

  public void remove();
    Code:
       0: new           #9                  // class java/lang/UnsupportedOperationException
       3: dup
       4: invokespecial #10                 // Method java/lang/UnsupportedOperationException."<init>":()V
       7: athrow

  public void seekFirst(TNode);
    Code:
       0: aload_0
       1: aload_1
       2: putfield      #4                  // Field current:Lorg/apache/hadoop/hbase/util/AvlUtil$AvlNode;
       5: aload_0
       6: iconst_0
       7: putfield      #5                  // Field height:I
      10: aload_1
      11: ifnull        58
      14: aload_0
      15: getfield      #4                  // Field current:Lorg/apache/hadoop/hbase/util/AvlUtil$AvlNode;
      18: getfield      #11                 // Field org/apache/hadoop/hbase/util/AvlUtil$AvlNode.avlLeft:Lorg/apache/hadoop/hbase/util/AvlUtil$AvlNode;
      21: ifnull        58
      24: aload_0
      25: getfield      #3                  // Field stack:[Ljava/lang/Object;
      28: aload_0
      29: dup
      30: getfield      #5                  // Field height:I
      33: dup_x1
      34: iconst_1
      35: iadd
      36: putfield      #5                  // Field height:I
      39: aload_0
      40: getfield      #4                  // Field current:Lorg/apache/hadoop/hbase/util/AvlUtil$AvlNode;
      43: aastore
      44: aload_0
      45: aload_0
      46: getfield      #4                  // Field current:Lorg/apache/hadoop/hbase/util/AvlUtil$AvlNode;
      49: getfield      #11                 // Field org/apache/hadoop/hbase/util/AvlUtil$AvlNode.avlLeft:Lorg/apache/hadoop/hbase/util/AvlUtil$AvlNode;
      52: putfield      #4                  // Field current:Lorg/apache/hadoop/hbase/util/AvlUtil$AvlNode;
      55: goto          14
      58: return

  public void seekTo(TNode, java.lang.Object, org.apache.hadoop.hbase.util.AvlUtil$AvlKeyComparator<TNode>);
    Code:
       0: aload_0
       1: aconst_null
       2: putfield      #4                  // Field current:Lorg/apache/hadoop/hbase/util/AvlUtil$AvlNode;
       5: aload_0
       6: iconst_0
       7: putfield      #5                  // Field height:I
      10: aload_1
      11: astore        4
      13: aload         4
      15: ifnull        201
      18: aload_3
      19: aload         4
      21: aload_2
      22: invokeinterface #12,  3           // InterfaceMethod org/apache/hadoop/hbase/util/AvlUtil$AvlKeyComparator.compareKey:(Lorg/apache/hadoop/hbase/util/AvlUtil$AvlNode;Ljava/lang/Object;)I
      27: iflt          73
      30: aload         4
      32: getfield      #11                 // Field org/apache/hadoop/hbase/util/AvlUtil$AvlNode.avlLeft:Lorg/apache/hadoop/hbase/util/AvlUtil$AvlNode;
      35: ifnull        66
      38: aload_0
      39: getfield      #3                  // Field stack:[Ljava/lang/Object;
      42: aload_0
      43: dup
      44: getfield      #5                  // Field height:I
      47: dup_x1
      48: iconst_1
      49: iadd
      50: putfield      #5                  // Field height:I
      53: aload         4
      55: aastore
      56: aload         4
      58: getfield      #11                 // Field org/apache/hadoop/hbase/util/AvlUtil$AvlNode.avlLeft:Lorg/apache/hadoop/hbase/util/AvlUtil$AvlNode;
      61: astore        4
      63: goto          13
      66: aload_0
      67: aload         4
      69: putfield      #4                  // Field current:Lorg/apache/hadoop/hbase/util/AvlUtil$AvlNode;
      72: return
      73: aload         4
      75: getfield      #13                 // Field org/apache/hadoop/hbase/util/AvlUtil$AvlNode.avlRight:Lorg/apache/hadoop/hbase/util/AvlUtil$AvlNode;
      78: ifnull        109
      81: aload_0
      82: getfield      #3                  // Field stack:[Ljava/lang/Object;
      85: aload_0
      86: dup
      87: getfield      #5                  // Field height:I
      90: dup_x1
      91: iconst_1
      92: iadd
      93: putfield      #5                  // Field height:I
      96: aload         4
      98: aastore
      99: aload         4
     101: getfield      #13                 // Field org/apache/hadoop/hbase/util/AvlUtil$AvlNode.avlRight:Lorg/apache/hadoop/hbase/util/AvlUtil$AvlNode;
     104: astore        4
     106: goto          13
     109: aload_0
     110: getfield      #5                  // Field height:I
     113: ifle          195
     116: aload_0
     117: getfield      #3                  // Field stack:[Ljava/lang/Object;
     120: aload_0
     121: dup
     122: getfield      #5                  // Field height:I
     125: iconst_1
     126: isub
     127: dup_x1
     128: putfield      #5                  // Field height:I
     131: aaload
     132: checkcast     #14                 // class org/apache/hadoop/hbase/util/AvlUtil$AvlNode
     135: astore        5
     137: aload         4
     139: aload         5
     141: getfield      #13                 // Field org/apache/hadoop/hbase/util/AvlUtil$AvlNode.avlRight:Lorg/apache/hadoop/hbase/util/AvlUtil$AvlNode;
     144: if_acmpne     188
     147: aload_0
     148: getfield      #5                  // Field height:I
     151: ifne          160
     154: aload_0
     155: aconst_null
     156: putfield      #4                  // Field current:Lorg/apache/hadoop/hbase/util/AvlUtil$AvlNode;
     159: return
     160: aload         5
     162: astore        4
     164: aload_0
     165: getfield      #3                  // Field stack:[Ljava/lang/Object;
     168: aload_0
     169: dup
     170: getfield      #5                  // Field height:I
     173: iconst_1
     174: isub
     175: dup_x1
     176: putfield      #5                  // Field height:I
     179: aaload
     180: checkcast     #14                 // class org/apache/hadoop/hbase/util/AvlUtil$AvlNode
     183: astore        5
     185: goto          137
     188: aload_0
     189: aload         5
     191: putfield      #4                  // Field current:Lorg/apache/hadoop/hbase/util/AvlUtil$AvlNode;
     194: return
     195: aload_0
     196: aconst_null
     197: putfield      #4                  // Field current:Lorg/apache/hadoop/hbase/util/AvlUtil$AvlNode;
     200: return
     201: return

  public java.lang.Object next();
    Code:
       0: aload_0
       1: invokevirtual #15                 // Method next:()Lorg/apache/hadoop/hbase/util/AvlUtil$AvlNode;
       4: areturn
}
