Compiled from "AvlUtil.java"
public class org.apache.hadoop.hbase.util.AvlUtil$AvlIterableList {
  static final boolean $assertionsDisabled;

  public org.apache.hadoop.hbase.util.AvlUtil$AvlIterableList();
    Code:
       0: aload_0
       1: invokespecial #1                  // Method java/lang/Object."<init>":()V
       4: return

  public static <TNode extends org.apache.hadoop.hbase.util.AvlUtil$AvlLinkedNode> TNode readNext(TNode);
    Code:
       0: aload_0
       1: getfield      #2                  // Field org/apache/hadoop/hbase/util/AvlUtil$AvlLinkedNode.iterNext:Lorg/apache/hadoop/hbase/util/AvlUtil$AvlLinkedNode;
       4: areturn

  public static <TNode extends org.apache.hadoop.hbase.util.AvlUtil$AvlLinkedNode> TNode readPrev(TNode);
    Code:
       0: aload_0
       1: getfield      #3                  // Field org/apache/hadoop/hbase/util/AvlUtil$AvlLinkedNode.iterPrev:Lorg/apache/hadoop/hbase/util/AvlUtil$AvlLinkedNode;
       4: areturn

  public static <TNode extends org.apache.hadoop.hbase.util.AvlUtil$AvlLinkedNode> TNode prepend(TNode, TNode);
    Code:
       0: getstatic     #4                  // Field $assertionsDisabled:Z
       3: ifne          40
       6: aload_1
       7: invokestatic  #5                  // Method isLinked:(Lorg/apache/hadoop/hbase/util/AvlUtil$AvlLinkedNode;)Z
      10: ifeq          40
      13: new           #6                  // class java/lang/AssertionError
      16: dup
      17: new           #7                  // class java/lang/StringBuilder
      20: dup
      21: invokespecial #8                  // Method java/lang/StringBuilder."<init>":()V
      24: aload_1
      25: invokevirtual #9                  // Method java/lang/StringBuilder.append:(Ljava/lang/Object;)Ljava/lang/StringBuilder;
      28: ldc           #10                 // String  is already linked
      30: invokevirtual #11                 // Method java/lang/StringBuilder.append:(Ljava/lang/String;)Ljava/lang/StringBuilder;
      33: invokevirtual #12                 // Method java/lang/StringBuilder.toString:()Ljava/lang/String;
      36: invokespecial #13                 // Method java/lang/AssertionError."<init>":(Ljava/lang/Object;)V
      39: athrow
      40: aload_0
      41: ifnull        72
      44: aload_0
      45: getfield      #3                  // Field org/apache/hadoop/hbase/util/AvlUtil$AvlLinkedNode.iterPrev:Lorg/apache/hadoop/hbase/util/AvlUtil$AvlLinkedNode;
      48: astore_2
      49: aload_2
      50: aload_1
      51: putfield      #2                  // Field org/apache/hadoop/hbase/util/AvlUtil$AvlLinkedNode.iterNext:Lorg/apache/hadoop/hbase/util/AvlUtil$AvlLinkedNode;
      54: aload_0
      55: aload_1
      56: putfield      #3                  // Field org/apache/hadoop/hbase/util/AvlUtil$AvlLinkedNode.iterPrev:Lorg/apache/hadoop/hbase/util/AvlUtil$AvlLinkedNode;
      59: aload_1
      60: aload_0
      61: putfield      #2                  // Field org/apache/hadoop/hbase/util/AvlUtil$AvlLinkedNode.iterNext:Lorg/apache/hadoop/hbase/util/AvlUtil$AvlLinkedNode;
      64: aload_1
      65: aload_2
      66: putfield      #3                  // Field org/apache/hadoop/hbase/util/AvlUtil$AvlLinkedNode.iterPrev:Lorg/apache/hadoop/hbase/util/AvlUtil$AvlLinkedNode;
      69: goto          82
      72: aload_1
      73: aload_1
      74: putfield      #2                  // Field org/apache/hadoop/hbase/util/AvlUtil$AvlLinkedNode.iterNext:Lorg/apache/hadoop/hbase/util/AvlUtil$AvlLinkedNode;
      77: aload_1
      78: aload_1
      79: putfield      #3                  // Field org/apache/hadoop/hbase/util/AvlUtil$AvlLinkedNode.iterPrev:Lorg/apache/hadoop/hbase/util/AvlUtil$AvlLinkedNode;
      82: aload_1
      83: areturn

  public static <TNode extends org.apache.hadoop.hbase.util.AvlUtil$AvlLinkedNode> TNode append(TNode, TNode);
    Code:
       0: getstatic     #4                  // Field $assertionsDisabled:Z
       3: ifne          40
       6: aload_1
       7: invokestatic  #5                  // Method isLinked:(Lorg/apache/hadoop/hbase/util/AvlUtil$AvlLinkedNode;)Z
      10: ifeq          40
      13: new           #6                  // class java/lang/AssertionError
      16: dup
      17: new           #7                  // class java/lang/StringBuilder
      20: dup
      21: invokespecial #8                  // Method java/lang/StringBuilder."<init>":()V
      24: aload_1
      25: invokevirtual #9                  // Method java/lang/StringBuilder.append:(Ljava/lang/Object;)Ljava/lang/StringBuilder;
      28: ldc           #10                 // String  is already linked
      30: invokevirtual #11                 // Method java/lang/StringBuilder.append:(Ljava/lang/String;)Ljava/lang/StringBuilder;
      33: invokevirtual #12                 // Method java/lang/StringBuilder.toString:()Ljava/lang/String;
      36: invokespecial #13                 // Method java/lang/AssertionError."<init>":(Ljava/lang/Object;)V
      39: athrow
      40: aload_0
      41: ifnull        71
      44: aload_0
      45: getfield      #3                  // Field org/apache/hadoop/hbase/util/AvlUtil$AvlLinkedNode.iterPrev:Lorg/apache/hadoop/hbase/util/AvlUtil$AvlLinkedNode;
      48: astore_2
      49: aload_2
      50: aload_1
      51: putfield      #2                  // Field org/apache/hadoop/hbase/util/AvlUtil$AvlLinkedNode.iterNext:Lorg/apache/hadoop/hbase/util/AvlUtil$AvlLinkedNode;
      54: aload_1
      55: aload_0
      56: putfield      #2                  // Field org/apache/hadoop/hbase/util/AvlUtil$AvlLinkedNode.iterNext:Lorg/apache/hadoop/hbase/util/AvlUtil$AvlLinkedNode;
      59: aload_1
      60: aload_2
      61: putfield      #3                  // Field org/apache/hadoop/hbase/util/AvlUtil$AvlLinkedNode.iterPrev:Lorg/apache/hadoop/hbase/util/AvlUtil$AvlLinkedNode;
      64: aload_0
      65: aload_1
      66: putfield      #3                  // Field org/apache/hadoop/hbase/util/AvlUtil$AvlLinkedNode.iterPrev:Lorg/apache/hadoop/hbase/util/AvlUtil$AvlLinkedNode;
      69: aload_0
      70: areturn
      71: aload_1
      72: aload_1
      73: putfield      #2                  // Field org/apache/hadoop/hbase/util/AvlUtil$AvlLinkedNode.iterNext:Lorg/apache/hadoop/hbase/util/AvlUtil$AvlLinkedNode;
      76: aload_1
      77: aload_1
      78: putfield      #3                  // Field org/apache/hadoop/hbase/util/AvlUtil$AvlLinkedNode.iterPrev:Lorg/apache/hadoop/hbase/util/AvlUtil$AvlLinkedNode;
      81: aload_1
      82: areturn

  public static <TNode extends org.apache.hadoop.hbase.util.AvlUtil$AvlLinkedNode> TNode appendList(TNode, TNode);
    Code:
       0: aload_0
       1: ifnonnull     6
       4: aload_1
       5: areturn
       6: aload_1
       7: ifnonnull     12
      10: aload_0
      11: areturn
      12: aload_0
      13: getfield      #3                  // Field org/apache/hadoop/hbase/util/AvlUtil$AvlLinkedNode.iterPrev:Lorg/apache/hadoop/hbase/util/AvlUtil$AvlLinkedNode;
      16: astore_2
      17: aload_1
      18: getfield      #3                  // Field org/apache/hadoop/hbase/util/AvlUtil$AvlLinkedNode.iterPrev:Lorg/apache/hadoop/hbase/util/AvlUtil$AvlLinkedNode;
      21: astore_3
      22: aload_2
      23: aload_1
      24: putfield      #2                  // Field org/apache/hadoop/hbase/util/AvlUtil$AvlLinkedNode.iterNext:Lorg/apache/hadoop/hbase/util/AvlUtil$AvlLinkedNode;
      27: aload_1
      28: aload_2
      29: putfield      #3                  // Field org/apache/hadoop/hbase/util/AvlUtil$AvlLinkedNode.iterPrev:Lorg/apache/hadoop/hbase/util/AvlUtil$AvlLinkedNode;
      32: aload_3
      33: aload_0
      34: putfield      #2                  // Field org/apache/hadoop/hbase/util/AvlUtil$AvlLinkedNode.iterNext:Lorg/apache/hadoop/hbase/util/AvlUtil$AvlLinkedNode;
      37: aload_0
      38: aload_3
      39: putfield      #3                  // Field org/apache/hadoop/hbase/util/AvlUtil$AvlLinkedNode.iterPrev:Lorg/apache/hadoop/hbase/util/AvlUtil$AvlLinkedNode;
      42: aload_0
      43: areturn

  public static <TNode extends org.apache.hadoop.hbase.util.AvlUtil$AvlLinkedNode> TNode remove(TNode, TNode);
    Code:
       0: getstatic     #4                  // Field $assertionsDisabled:Z
       3: ifne          40
       6: aload_1
       7: invokestatic  #5                  // Method isLinked:(Lorg/apache/hadoop/hbase/util/AvlUtil$AvlLinkedNode;)Z
      10: ifne          40
      13: new           #6                  // class java/lang/AssertionError
      16: dup
      17: new           #7                  // class java/lang/StringBuilder
      20: dup
      21: invokespecial #8                  // Method java/lang/StringBuilder."<init>":()V
      24: aload_1
      25: invokevirtual #9                  // Method java/lang/StringBuilder.append:(Ljava/lang/Object;)Ljava/lang/StringBuilder;
      28: ldc           #14                 // String  is not linked
      30: invokevirtual #11                 // Method java/lang/StringBuilder.append:(Ljava/lang/String;)Ljava/lang/StringBuilder;
      33: invokevirtual #12                 // Method java/lang/StringBuilder.toString:()Ljava/lang/String;
      36: invokespecial #13                 // Method java/lang/AssertionError."<init>":(Ljava/lang/Object;)V
      39: athrow
      40: aload_1
      41: aload_1
      42: getfield      #2                  // Field org/apache/hadoop/hbase/util/AvlUtil$AvlLinkedNode.iterNext:Lorg/apache/hadoop/hbase/util/AvlUtil$AvlLinkedNode;
      45: if_acmpeq     87
      48: aload_1
      49: getfield      #3                  // Field org/apache/hadoop/hbase/util/AvlUtil$AvlLinkedNode.iterPrev:Lorg/apache/hadoop/hbase/util/AvlUtil$AvlLinkedNode;
      52: aload_1
      53: getfield      #2                  // Field org/apache/hadoop/hbase/util/AvlUtil$AvlLinkedNode.iterNext:Lorg/apache/hadoop/hbase/util/AvlUtil$AvlLinkedNode;
      56: putfield      #2                  // Field org/apache/hadoop/hbase/util/AvlUtil$AvlLinkedNode.iterNext:Lorg/apache/hadoop/hbase/util/AvlUtil$AvlLinkedNode;
      59: aload_1
      60: getfield      #2                  // Field org/apache/hadoop/hbase/util/AvlUtil$AvlLinkedNode.iterNext:Lorg/apache/hadoop/hbase/util/AvlUtil$AvlLinkedNode;
      63: aload_1
      64: getfield      #3                  // Field org/apache/hadoop/hbase/util/AvlUtil$AvlLinkedNode.iterPrev:Lorg/apache/hadoop/hbase/util/AvlUtil$AvlLinkedNode;
      67: putfield      #3                  // Field org/apache/hadoop/hbase/util/AvlUtil$AvlLinkedNode.iterPrev:Lorg/apache/hadoop/hbase/util/AvlUtil$AvlLinkedNode;
      70: aload_0
      71: aload_1
      72: if_acmpne     82
      75: aload_1
      76: getfield      #2                  // Field org/apache/hadoop/hbase/util/AvlUtil$AvlLinkedNode.iterNext:Lorg/apache/hadoop/hbase/util/AvlUtil$AvlLinkedNode;
      79: goto          83
      82: aload_0
      83: astore_0
      84: goto          89
      87: aconst_null
      88: astore_0
      89: aload_1
      90: aconst_null
      91: putfield      #2                  // Field org/apache/hadoop/hbase/util/AvlUtil$AvlLinkedNode.iterNext:Lorg/apache/hadoop/hbase/util/AvlUtil$AvlLinkedNode;
      94: aload_1
      95: aconst_null
      96: putfield      #3                  // Field org/apache/hadoop/hbase/util/AvlUtil$AvlLinkedNode.iterPrev:Lorg/apache/hadoop/hbase/util/AvlUtil$AvlLinkedNode;
      99: aload_0
     100: areturn

  public static <TNode extends org.apache.hadoop.hbase.util.AvlUtil$AvlLinkedNode> TNode prepend(TNode, TNode, TNode);
    Code:
       0: getstatic     #4                  // Field $assertionsDisabled:Z
       3: ifne          40
       6: aload_2
       7: invokestatic  #5                  // Method isLinked:(Lorg/apache/hadoop/hbase/util/AvlUtil$AvlLinkedNode;)Z
      10: ifeq          40
      13: new           #6                  // class java/lang/AssertionError
      16: dup
      17: new           #7                  // class java/lang/StringBuilder
      20: dup
      21: invokespecial #8                  // Method java/lang/StringBuilder."<init>":()V
      24: aload_2
      25: invokevirtual #9                  // Method java/lang/StringBuilder.append:(Ljava/lang/Object;)Ljava/lang/StringBuilder;
      28: ldc           #10                 // String  is already linked
      30: invokevirtual #11                 // Method java/lang/StringBuilder.append:(Ljava/lang/String;)Ljava/lang/StringBuilder;
      33: invokevirtual #12                 // Method java/lang/StringBuilder.toString:()Ljava/lang/String;
      36: invokespecial #13                 // Method java/lang/AssertionError."<init>":(Ljava/lang/Object;)V
      39: athrow
      40: aload_2
      41: aload_1
      42: putfield      #2                  // Field org/apache/hadoop/hbase/util/AvlUtil$AvlLinkedNode.iterNext:Lorg/apache/hadoop/hbase/util/AvlUtil$AvlLinkedNode;
      45: aload_2
      46: aload_1
      47: getfield      #3                  // Field org/apache/hadoop/hbase/util/AvlUtil$AvlLinkedNode.iterPrev:Lorg/apache/hadoop/hbase/util/AvlUtil$AvlLinkedNode;
      50: putfield      #3                  // Field org/apache/hadoop/hbase/util/AvlUtil$AvlLinkedNode.iterPrev:Lorg/apache/hadoop/hbase/util/AvlUtil$AvlLinkedNode;
      53: aload_1
      54: getfield      #3                  // Field org/apache/hadoop/hbase/util/AvlUtil$AvlLinkedNode.iterPrev:Lorg/apache/hadoop/hbase/util/AvlUtil$AvlLinkedNode;
      57: aload_2
      58: putfield      #2                  // Field org/apache/hadoop/hbase/util/AvlUtil$AvlLinkedNode.iterNext:Lorg/apache/hadoop/hbase/util/AvlUtil$AvlLinkedNode;
      61: aload_1
      62: aload_2
      63: putfield      #3                  // Field org/apache/hadoop/hbase/util/AvlUtil$AvlLinkedNode.iterPrev:Lorg/apache/hadoop/hbase/util/AvlUtil$AvlLinkedNode;
      66: aload_0
      67: aload_1
      68: if_acmpne     75
      71: aload_2
      72: goto          76
      75: aload_0
      76: areturn

  public static <TNode extends org.apache.hadoop.hbase.util.AvlUtil$AvlLinkedNode> boolean isLinked(TNode);
    Code:
       0: aload_0
       1: getfield      #3                  // Field org/apache/hadoop/hbase/util/AvlUtil$AvlLinkedNode.iterPrev:Lorg/apache/hadoop/hbase/util/AvlUtil$AvlLinkedNode;
       4: ifnull        18
       7: aload_0
       8: getfield      #2                  // Field org/apache/hadoop/hbase/util/AvlUtil$AvlLinkedNode.iterNext:Lorg/apache/hadoop/hbase/util/AvlUtil$AvlLinkedNode;
      11: ifnull        18
      14: iconst_1
      15: goto          19
      18: iconst_0
      19: ireturn

  static {};
    Code:
       0: ldc           #15                 // class org/apache/hadoop/hbase/util/AvlUtil
       2: invokevirtual #16                 // Method java/lang/Class.desiredAssertionStatus:()Z
       5: ifne          12
       8: iconst_1
       9: goto          13
      12: iconst_0
      13: putstatic     #4                  // Field $assertionsDisabled:Z
      16: return
}
