Compiled from "BackupProtos.java"
public final class org.apache.hadoop.hbase.shaded.protobuf.generated.BackupProtos$BackupImage$Builder extends org.apache.hbase.thirdparty.com.google.protobuf.GeneratedMessageV3$Builder<org.apache.hadoop.hbase.shaded.protobuf.generated.BackupProtos$BackupImage$Builder> implements org.apache.hadoop.hbase.shaded.protobuf.generated.BackupProtos$BackupImageOrBuilder {
  public static final org.apache.hbase.thirdparty.com.google.protobuf.Descriptors$Descriptor getDescriptor();
    Code:
       0: invokestatic  #3                  // Method org/apache/hadoop/hbase/shaded/protobuf/generated/BackupProtos.access$2300:()Lorg/apache/hbase/thirdparty/com/google/protobuf/Descriptors$Descriptor;
       3: areturn

  protected org.apache.hbase.thirdparty.com.google.protobuf.GeneratedMessageV3$FieldAccessorTable internalGetFieldAccessorTable();
    Code:
       0: invokestatic  #4                  // Method org/apache/hadoop/hbase/shaded/protobuf/generated/BackupProtos.access$2400:()Lorg/apache/hbase/thirdparty/com/google/protobuf/GeneratedMessageV3$FieldAccessorTable;
       3: ldc           #5                  // class org/apache/hadoop/hbase/shaded/protobuf/generated/BackupProtos$BackupImage
       5: ldc           #6                  // class org/apache/hadoop/hbase/shaded/protobuf/generated/BackupProtos$BackupImage$Builder
       7: invokevirtual #7                  // Method org/apache/hbase/thirdparty/com/google/protobuf/GeneratedMessageV3$FieldAccessorTable.ensureFieldAccessorsInitialized:(Ljava/lang/Class;Ljava/lang/Class;)Lorg/apache/hbase/thirdparty/com/google/protobuf/GeneratedMessageV3$FieldAccessorTable;
      10: areturn

  public org.apache.hadoop.hbase.shaded.protobuf.generated.BackupProtos$BackupImage$Builder clear();
    Code:
       0: aload_0
       1: invokespecial #23                 // Method org/apache/hbase/thirdparty/com/google/protobuf/GeneratedMessageV3$Builder.clear:()Lorg/apache/hbase/thirdparty/com/google/protobuf/GeneratedMessageV3$Builder;
       4: pop
       5: aload_0
       6: ldc           #9                  // String
       8: putfield      #10                 // Field backupId_:Ljava/lang/Object;
      11: aload_0
      12: aload_0
      13: getfield      #24                 // Field bitField0_:I
      16: bipush        -2
      18: iand
      19: putfield      #24                 // Field bitField0_:I
      22: aload_0
      23: iconst_0
      24: putfield      #11                 // Field backupType_:I
      27: aload_0
      28: aload_0
      29: getfield      #24                 // Field bitField0_:I
      32: bipush        -3
      34: iand
      35: putfield      #24                 // Field bitField0_:I
      38: aload_0
      39: ldc           #9                  // String
      41: putfield      #12                 // Field backupRootDir_:Ljava/lang/Object;
      44: aload_0
      45: aload_0
      46: getfield      #24                 // Field bitField0_:I
      49: bipush        -5
      51: iand
      52: putfield      #24                 // Field bitField0_:I
      55: aload_0
      56: getfield      #25                 // Field tableListBuilder_:Lorg/apache/hbase/thirdparty/com/google/protobuf/RepeatedFieldBuilderV3;
      59: ifnonnull     83
      62: aload_0
      63: invokestatic  #13                 // Method java/util/Collections.emptyList:()Ljava/util/List;
      66: putfield      #14                 // Field tableList_:Ljava/util/List;
      69: aload_0
      70: aload_0
      71: getfield      #24                 // Field bitField0_:I
      74: bipush        -9
      76: iand
      77: putfield      #24                 // Field bitField0_:I
      80: goto          90
      83: aload_0
      84: getfield      #25                 // Field tableListBuilder_:Lorg/apache/hbase/thirdparty/com/google/protobuf/RepeatedFieldBuilderV3;
      87: invokevirtual #26                 // Method org/apache/hbase/thirdparty/com/google/protobuf/RepeatedFieldBuilderV3.clear:()V
      90: aload_0
      91: lconst_0
      92: putfield      #27                 // Field startTs_:J
      95: aload_0
      96: aload_0
      97: getfield      #24                 // Field bitField0_:I
     100: bipush        -17
     102: iand
     103: putfield      #24                 // Field bitField0_:I
     106: aload_0
     107: lconst_0
     108: putfield      #28                 // Field completeTs_:J
     111: aload_0
     112: aload_0
     113: getfield      #24                 // Field bitField0_:I
     116: bipush        -33
     118: iand
     119: putfield      #24                 // Field bitField0_:I
     122: aload_0
     123: getfield      #29                 // Field ancestorsBuilder_:Lorg/apache/hbase/thirdparty/com/google/protobuf/RepeatedFieldBuilderV3;
     126: ifnonnull     150
     129: aload_0
     130: invokestatic  #13                 // Method java/util/Collections.emptyList:()Ljava/util/List;
     133: putfield      #15                 // Field ancestors_:Ljava/util/List;
     136: aload_0
     137: aload_0
     138: getfield      #24                 // Field bitField0_:I
     141: bipush        -65
     143: iand
     144: putfield      #24                 // Field bitField0_:I
     147: goto          157
     150: aload_0
     151: getfield      #29                 // Field ancestorsBuilder_:Lorg/apache/hbase/thirdparty/com/google/protobuf/RepeatedFieldBuilderV3;
     154: invokevirtual #26                 // Method org/apache/hbase/thirdparty/com/google/protobuf/RepeatedFieldBuilderV3.clear:()V
     157: aload_0
     158: getfield      #30                 // Field tstMapBuilder_:Lorg/apache/hbase/thirdparty/com/google/protobuf/RepeatedFieldBuilderV3;
     161: ifnonnull     186
     164: aload_0
     165: invokestatic  #13                 // Method java/util/Collections.emptyList:()Ljava/util/List;
     168: putfield      #16                 // Field tstMap_:Ljava/util/List;
     171: aload_0
     172: aload_0
     173: getfield      #24                 // Field bitField0_:I
     176: sipush        -129
     179: iand
     180: putfield      #24                 // Field bitField0_:I
     183: goto          193
     186: aload_0
     187: getfield      #30                 // Field tstMapBuilder_:Lorg/apache/hbase/thirdparty/com/google/protobuf/RepeatedFieldBuilderV3;
     190: invokevirtual #26                 // Method org/apache/hbase/thirdparty/com/google/protobuf/RepeatedFieldBuilderV3.clear:()V
     193: aload_0
     194: areturn

  public org.apache.hbase.thirdparty.com.google.protobuf.Descriptors$Descriptor getDescriptorForType();
    Code:
       0: invokestatic  #3                  // Method org/apache/hadoop/hbase/shaded/protobuf/generated/BackupProtos.access$2300:()Lorg/apache/hbase/thirdparty/com/google/protobuf/Descriptors$Descriptor;
       3: areturn

  public org.apache.hadoop.hbase.shaded.protobuf.generated.BackupProtos$BackupImage getDefaultInstanceForType();
    Code:
       0: invokestatic  #31                 // Method org/apache/hadoop/hbase/shaded/protobuf/generated/BackupProtos$BackupImage.getDefaultInstance:()Lorg/apache/hadoop/hbase/shaded/protobuf/generated/BackupProtos$BackupImage;
       3: areturn

  public org.apache.hadoop.hbase.shaded.protobuf.generated.BackupProtos$BackupImage build();
    Code:
       0: aload_0
       1: invokevirtual #32                 // Method buildPartial:()Lorg/apache/hadoop/hbase/shaded/protobuf/generated/BackupProtos$BackupImage;
       4: astore_1
       5: aload_1
       6: invokevirtual #33                 // Method org/apache/hadoop/hbase/shaded/protobuf/generated/BackupProtos$BackupImage.isInitialized:()Z
       9: ifne          17
      12: aload_1
      13: invokestatic  #34                 // Method newUninitializedMessageException:(Lorg/apache/hbase/thirdparty/com/google/protobuf/Message;)Lorg/apache/hbase/thirdparty/com/google/protobuf/UninitializedMessageException;
      16: athrow
      17: aload_1
      18: areturn

  public org.apache.hadoop.hbase.shaded.protobuf.generated.BackupProtos$BackupImage buildPartial();
    Code:
       0: new           #5                  // class org/apache/hadoop/hbase/shaded/protobuf/generated/BackupProtos$BackupImage
       3: dup
       4: aload_0
       5: aconst_null
       6: invokespecial #35                 // Method org/apache/hadoop/hbase/shaded/protobuf/generated/BackupProtos$BackupImage."<init>":(Lorg/apache/hbase/thirdparty/com/google/protobuf/GeneratedMessageV3$Builder;Lorg/apache/hadoop/hbase/shaded/protobuf/generated/BackupProtos$1;)V
       9: astore_1
      10: aload_0
      11: getfield      #24                 // Field bitField0_:I
      14: istore_2
      15: iconst_0
      16: istore_3
      17: iload_2
      18: iconst_1
      19: iand
      20: iconst_1
      21: if_icmpne     28
      24: iload_3
      25: iconst_1
      26: ior
      27: istore_3
      28: aload_1
      29: aload_0
      30: getfield      #10                 // Field backupId_:Ljava/lang/Object;
      33: invokestatic  #36                 // Method org/apache/hadoop/hbase/shaded/protobuf/generated/BackupProtos$BackupImage.access$2902:(Lorg/apache/hadoop/hbase/shaded/protobuf/generated/BackupProtos$BackupImage;Ljava/lang/Object;)Ljava/lang/Object;
      36: pop
      37: iload_2
      38: iconst_2
      39: iand
      40: iconst_2
      41: if_icmpne     48
      44: iload_3
      45: iconst_2
      46: ior
      47: istore_3
      48: aload_1
      49: aload_0
      50: getfield      #11                 // Field backupType_:I
      53: invokestatic  #37                 // Method org/apache/hadoop/hbase/shaded/protobuf/generated/BackupProtos$BackupImage.access$3002:(Lorg/apache/hadoop/hbase/shaded/protobuf/generated/BackupProtos$BackupImage;I)I
      56: pop
      57: iload_2
      58: iconst_4
      59: iand
      60: iconst_4
      61: if_icmpne     68
      64: iload_3
      65: iconst_4
      66: ior
      67: istore_3
      68: aload_1
      69: aload_0
      70: getfield      #12                 // Field backupRootDir_:Ljava/lang/Object;
      73: invokestatic  #38                 // Method org/apache/hadoop/hbase/shaded/protobuf/generated/BackupProtos$BackupImage.access$3102:(Lorg/apache/hadoop/hbase/shaded/protobuf/generated/BackupProtos$BackupImage;Ljava/lang/Object;)Ljava/lang/Object;
      76: pop
      77: aload_0
      78: getfield      #25                 // Field tableListBuilder_:Lorg/apache/hbase/thirdparty/com/google/protobuf/RepeatedFieldBuilderV3;
      81: ifnonnull     130
      84: aload_0
      85: getfield      #24                 // Field bitField0_:I
      88: bipush        8
      90: iand
      91: bipush        8
      93: if_icmpne     118
      96: aload_0
      97: aload_0
      98: getfield      #14                 // Field tableList_:Ljava/util/List;
     101: invokestatic  #39                 // Method java/util/Collections.unmodifiableList:(Ljava/util/List;)Ljava/util/List;
     104: putfield      #14                 // Field tableList_:Ljava/util/List;
     107: aload_0
     108: aload_0
     109: getfield      #24                 // Field bitField0_:I
     112: bipush        -9
     114: iand
     115: putfield      #24                 // Field bitField0_:I
     118: aload_1
     119: aload_0
     120: getfield      #14                 // Field tableList_:Ljava/util/List;
     123: invokestatic  #40                 // Method org/apache/hadoop/hbase/shaded/protobuf/generated/BackupProtos$BackupImage.access$3202:(Lorg/apache/hadoop/hbase/shaded/protobuf/generated/BackupProtos$BackupImage;Ljava/util/List;)Ljava/util/List;
     126: pop
     127: goto          142
     130: aload_1
     131: aload_0
     132: getfield      #25                 // Field tableListBuilder_:Lorg/apache/hbase/thirdparty/com/google/protobuf/RepeatedFieldBuilderV3;
     135: invokevirtual #41                 // Method org/apache/hbase/thirdparty/com/google/protobuf/RepeatedFieldBuilderV3.build:()Ljava/util/List;
     138: invokestatic  #40                 // Method org/apache/hadoop/hbase/shaded/protobuf/generated/BackupProtos$BackupImage.access$3202:(Lorg/apache/hadoop/hbase/shaded/protobuf/generated/BackupProtos$BackupImage;Ljava/util/List;)Ljava/util/List;
     141: pop
     142: iload_2
     143: bipush        16
     145: iand
     146: bipush        16
     148: if_icmpne     156
     151: iload_3
     152: bipush        8
     154: ior
     155: istore_3
     156: aload_1
     157: aload_0
     158: getfield      #27                 // Field startTs_:J
     161: invokestatic  #42                 // Method org/apache/hadoop/hbase/shaded/protobuf/generated/BackupProtos$BackupImage.access$3302:(Lorg/apache/hadoop/hbase/shaded/protobuf/generated/BackupProtos$BackupImage;J)J
     164: pop2
     165: iload_2
     166: bipush        32
     168: iand
     169: bipush        32
     171: if_icmpne     179
     174: iload_3
     175: bipush        16
     177: ior
     178: istore_3
     179: aload_1
     180: aload_0
     181: getfield      #28                 // Field completeTs_:J
     184: invokestatic  #43                 // Method org/apache/hadoop/hbase/shaded/protobuf/generated/BackupProtos$BackupImage.access$3402:(Lorg/apache/hadoop/hbase/shaded/protobuf/generated/BackupProtos$BackupImage;J)J
     187: pop2
     188: aload_0
     189: getfield      #29                 // Field ancestorsBuilder_:Lorg/apache/hbase/thirdparty/com/google/protobuf/RepeatedFieldBuilderV3;
     192: ifnonnull     241
     195: aload_0
     196: getfield      #24                 // Field bitField0_:I
     199: bipush        64
     201: iand
     202: bipush        64
     204: if_icmpne     229
     207: aload_0
     208: aload_0
     209: getfield      #15                 // Field ancestors_:Ljava/util/List;
     212: invokestatic  #39                 // Method java/util/Collections.unmodifiableList:(Ljava/util/List;)Ljava/util/List;
     215: putfield      #15                 // Field ancestors_:Ljava/util/List;
     218: aload_0
     219: aload_0
     220: getfield      #24                 // Field bitField0_:I
     223: bipush        -65
     225: iand
     226: putfield      #24                 // Field bitField0_:I
     229: aload_1
     230: aload_0
     231: getfield      #15                 // Field ancestors_:Ljava/util/List;
     234: invokestatic  #44                 // Method org/apache/hadoop/hbase/shaded/protobuf/generated/BackupProtos$BackupImage.access$3502:(Lorg/apache/hadoop/hbase/shaded/protobuf/generated/BackupProtos$BackupImage;Ljava/util/List;)Ljava/util/List;
     237: pop
     238: goto          253
     241: aload_1
     242: aload_0
     243: getfield      #29                 // Field ancestorsBuilder_:Lorg/apache/hbase/thirdparty/com/google/protobuf/RepeatedFieldBuilderV3;
     246: invokevirtual #41                 // Method org/apache/hbase/thirdparty/com/google/protobuf/RepeatedFieldBuilderV3.build:()Ljava/util/List;
     249: invokestatic  #44                 // Method org/apache/hadoop/hbase/shaded/protobuf/generated/BackupProtos$BackupImage.access$3502:(Lorg/apache/hadoop/hbase/shaded/protobuf/generated/BackupProtos$BackupImage;Ljava/util/List;)Ljava/util/List;
     252: pop
     253: aload_0
     254: getfield      #30                 // Field tstMapBuilder_:Lorg/apache/hbase/thirdparty/com/google/protobuf/RepeatedFieldBuilderV3;
     257: ifnonnull     309
     260: aload_0
     261: getfield      #24                 // Field bitField0_:I
     264: sipush        128
     267: iand
     268: sipush        128
     271: if_icmpne     297
     274: aload_0
     275: aload_0
     276: getfield      #16                 // Field tstMap_:Ljava/util/List;
     279: invokestatic  #39                 // Method java/util/Collections.unmodifiableList:(Ljava/util/List;)Ljava/util/List;
     282: putfield      #16                 // Field tstMap_:Ljava/util/List;
     285: aload_0
     286: aload_0
     287: getfield      #24                 // Field bitField0_:I
     290: sipush        -129
     293: iand
     294: putfield      #24                 // Field bitField0_:I
     297: aload_1
     298: aload_0
     299: getfield      #16                 // Field tstMap_:Ljava/util/List;
     302: invokestatic  #45                 // Method org/apache/hadoop/hbase/shaded/protobuf/generated/BackupProtos$BackupImage.access$3602:(Lorg/apache/hadoop/hbase/shaded/protobuf/generated/BackupProtos$BackupImage;Ljava/util/List;)Ljava/util/List;
     305: pop
     306: goto          321
     309: aload_1
     310: aload_0
     311: getfield      #30                 // Field tstMapBuilder_:Lorg/apache/hbase/thirdparty/com/google/protobuf/RepeatedFieldBuilderV3;
     314: invokevirtual #41                 // Method org/apache/hbase/thirdparty/com/google/protobuf/RepeatedFieldBuilderV3.build:()Ljava/util/List;
     317: invokestatic  #45                 // Method org/apache/hadoop/hbase/shaded/protobuf/generated/BackupProtos$BackupImage.access$3602:(Lorg/apache/hadoop/hbase/shaded/protobuf/generated/BackupProtos$BackupImage;Ljava/util/List;)Ljava/util/List;
     320: pop
     321: aload_1
     322: iload_3
     323: invokestatic  #46                 // Method org/apache/hadoop/hbase/shaded/protobuf/generated/BackupProtos$BackupImage.access$3702:(Lorg/apache/hadoop/hbase/shaded/protobuf/generated/BackupProtos$BackupImage;I)I
     326: pop
     327: aload_0
     328: invokevirtual #47                 // Method onBuilt:()V
     331: aload_1
     332: areturn

  public org.apache.hadoop.hbase.shaded.protobuf.generated.BackupProtos$BackupImage$Builder clone();
    Code:
       0: aload_0
       1: invokespecial #48                 // Method org/apache/hbase/thirdparty/com/google/protobuf/GeneratedMessageV3$Builder.clone:()Lorg/apache/hbase/thirdparty/com/google/protobuf/GeneratedMessageV3$Builder;
       4: checkcast     #6                  // class org/apache/hadoop/hbase/shaded/protobuf/generated/BackupProtos$BackupImage$Builder
       7: areturn

  public org.apache.hadoop.hbase.shaded.protobuf.generated.BackupProtos$BackupImage$Builder setField(org.apache.hbase.thirdparty.com.google.protobuf.Descriptors$FieldDescriptor, java.lang.Object);
    Code:
       0: aload_0
       1: aload_1
       2: aload_2
       3: invokespecial #49                 // Method org/apache/hbase/thirdparty/com/google/protobuf/GeneratedMessageV3$Builder.setField:(Lorg/apache/hbase/thirdparty/com/google/protobuf/Descriptors$FieldDescriptor;Ljava/lang/Object;)Lorg/apache/hbase/thirdparty/com/google/protobuf/GeneratedMessageV3$Builder;
       6: checkcast     #6                  // class org/apache/hadoop/hbase/shaded/protobuf/generated/BackupProtos$BackupImage$Builder
       9: areturn

  public org.apache.hadoop.hbase.shaded.protobuf.generated.BackupProtos$BackupImage$Builder clearField(org.apache.hbase.thirdparty.com.google.protobuf.Descriptors$FieldDescriptor);
    Code:
       0: aload_0
       1: aload_1
       2: invokespecial #50                 // Method org/apache/hbase/thirdparty/com/google/protobuf/GeneratedMessageV3$Builder.clearField:(Lorg/apache/hbase/thirdparty/com/google/protobuf/Descriptors$FieldDescriptor;)Lorg/apache/hbase/thirdparty/com/google/protobuf/GeneratedMessageV3$Builder;
       5: checkcast     #6                  // class org/apache/hadoop/hbase/shaded/protobuf/generated/BackupProtos$BackupImage$Builder
       8: areturn

  public org.apache.hadoop.hbase.shaded.protobuf.generated.BackupProtos$BackupImage$Builder clearOneof(org.apache.hbase.thirdparty.com.google.protobuf.Descriptors$OneofDescriptor);
    Code:
       0: aload_0
       1: aload_1
       2: invokespecial #51                 // Method org/apache/hbase/thirdparty/com/google/protobuf/GeneratedMessageV3$Builder.clearOneof:(Lorg/apache/hbase/thirdparty/com/google/protobuf/Descriptors$OneofDescriptor;)Lorg/apache/hbase/thirdparty/com/google/protobuf/GeneratedMessageV3$Builder;
       5: checkcast     #6                  // class org/apache/hadoop/hbase/shaded/protobuf/generated/BackupProtos$BackupImage$Builder
       8: areturn

  public org.apache.hadoop.hbase.shaded.protobuf.generated.BackupProtos$BackupImage$Builder setRepeatedField(org.apache.hbase.thirdparty.com.google.protobuf.Descriptors$FieldDescriptor, int, java.lang.Object);
    Code:
       0: aload_0
       1: aload_1
       2: iload_2
       3: aload_3
       4: invokespecial #52                 // Method org/apache/hbase/thirdparty/com/google/protobuf/GeneratedMessageV3$Builder.setRepeatedField:(Lorg/apache/hbase/thirdparty/com/google/protobuf/Descriptors$FieldDescriptor;ILjava/lang/Object;)Lorg/apache/hbase/thirdparty/com/google/protobuf/GeneratedMessageV3$Builder;
       7: checkcast     #6                  // class org/apache/hadoop/hbase/shaded/protobuf/generated/BackupProtos$BackupImage$Builder
      10: areturn

  public org.apache.hadoop.hbase.shaded.protobuf.generated.BackupProtos$BackupImage$Builder addRepeatedField(org.apache.hbase.thirdparty.com.google.protobuf.Descriptors$FieldDescriptor, java.lang.Object);
    Code:
       0: aload_0
       1: aload_1
       2: aload_2
       3: invokespecial #53                 // Method org/apache/hbase/thirdparty/com/google/protobuf/GeneratedMessageV3$Builder.addRepeatedField:(Lorg/apache/hbase/thirdparty/com/google/protobuf/Descriptors$FieldDescriptor;Ljava/lang/Object;)Lorg/apache/hbase/thirdparty/com/google/protobuf/GeneratedMessageV3$Builder;
       6: checkcast     #6                  // class org/apache/hadoop/hbase/shaded/protobuf/generated/BackupProtos$BackupImage$Builder
       9: areturn

  public org.apache.hadoop.hbase.shaded.protobuf.generated.BackupProtos$BackupImage$Builder mergeFrom(org.apache.hbase.thirdparty.com.google.protobuf.Message);
    Code:
       0: aload_1
       1: instanceof    #5                  // class org/apache/hadoop/hbase/shaded/protobuf/generated/BackupProtos$BackupImage
       4: ifeq          16
       7: aload_0
       8: aload_1
       9: checkcast     #5                  // class org/apache/hadoop/hbase/shaded/protobuf/generated/BackupProtos$BackupImage
      12: invokevirtual #54                 // Method mergeFrom:(Lorg/apache/hadoop/hbase/shaded/protobuf/generated/BackupProtos$BackupImage;)Lorg/apache/hadoop/hbase/shaded/protobuf/generated/BackupProtos$BackupImage$Builder;
      15: areturn
      16: aload_0
      17: aload_1
      18: invokespecial #55                 // Method org/apache/hbase/thirdparty/com/google/protobuf/GeneratedMessageV3$Builder.mergeFrom:(Lorg/apache/hbase/thirdparty/com/google/protobuf/Message;)Lorg/apache/hbase/thirdparty/com/google/protobuf/AbstractMessage$Builder;
      21: pop
      22: aload_0
      23: areturn

  public org.apache.hadoop.hbase.shaded.protobuf.generated.BackupProtos$BackupImage$Builder mergeFrom(org.apache.hadoop.hbase.shaded.protobuf.generated.BackupProtos$BackupImage);
    Code:
       0: aload_1
       1: invokestatic  #31                 // Method org/apache/hadoop/hbase/shaded/protobuf/generated/BackupProtos$BackupImage.getDefaultInstance:()Lorg/apache/hadoop/hbase/shaded/protobuf/generated/BackupProtos$BackupImage;
       4: if_acmpne     9
       7: aload_0
       8: areturn
       9: aload_1
      10: invokevirtual #56                 // Method org/apache/hadoop/hbase/shaded/protobuf/generated/BackupProtos$BackupImage.hasBackupId:()Z
      13: ifeq          38
      16: aload_0
      17: dup
      18: getfield      #24                 // Field bitField0_:I
      21: iconst_1
      22: ior
      23: putfield      #24                 // Field bitField0_:I
      26: aload_0
      27: aload_1
      28: invokestatic  #57                 // Method org/apache/hadoop/hbase/shaded/protobuf/generated/BackupProtos$BackupImage.access$2900:(Lorg/apache/hadoop/hbase/shaded/protobuf/generated/BackupProtos$BackupImage;)Ljava/lang/Object;
      31: putfield      #10                 // Field backupId_:Ljava/lang/Object;
      34: aload_0
      35: invokevirtual #58                 // Method onChanged:()V
      38: aload_1
      39: invokevirtual #59                 // Method org/apache/hadoop/hbase/shaded/protobuf/generated/BackupProtos$BackupImage.hasBackupType:()Z
      42: ifeq          54
      45: aload_0
      46: aload_1
      47: invokevirtual #60                 // Method org/apache/hadoop/hbase/shaded/protobuf/generated/BackupProtos$BackupImage.getBackupType:()Lorg/apache/hadoop/hbase/shaded/protobuf/generated/BackupProtos$BackupType;
      50: invokevirtual #61                 // Method setBackupType:(Lorg/apache/hadoop/hbase/shaded/protobuf/generated/BackupProtos$BackupType;)Lorg/apache/hadoop/hbase/shaded/protobuf/generated/BackupProtos$BackupImage$Builder;
      53: pop
      54: aload_1
      55: invokevirtual #62                 // Method org/apache/hadoop/hbase/shaded/protobuf/generated/BackupProtos$BackupImage.hasBackupRootDir:()Z
      58: ifeq          83
      61: aload_0
      62: dup
      63: getfield      #24                 // Field bitField0_:I
      66: iconst_4
      67: ior
      68: putfield      #24                 // Field bitField0_:I
      71: aload_0
      72: aload_1
      73: invokestatic  #63                 // Method org/apache/hadoop/hbase/shaded/protobuf/generated/BackupProtos$BackupImage.access$3100:(Lorg/apache/hadoop/hbase/shaded/protobuf/generated/BackupProtos$BackupImage;)Ljava/lang/Object;
      76: putfield      #12                 // Field backupRootDir_:Ljava/lang/Object;
      79: aload_0
      80: invokevirtual #58                 // Method onChanged:()V
      83: aload_0
      84: getfield      #25                 // Field tableListBuilder_:Lorg/apache/hbase/thirdparty/com/google/protobuf/RepeatedFieldBuilderV3;
      87: ifnonnull     161
      90: aload_1
      91: invokestatic  #64                 // Method org/apache/hadoop/hbase/shaded/protobuf/generated/BackupProtos$BackupImage.access$3200:(Lorg/apache/hadoop/hbase/shaded/protobuf/generated/BackupProtos$BackupImage;)Ljava/util/List;
      94: invokeinterface #65,  1           // InterfaceMethod java/util/List.isEmpty:()Z
      99: ifne          247
     102: aload_0
     103: getfield      #14                 // Field tableList_:Ljava/util/List;
     106: invokeinterface #65,  1           // InterfaceMethod java/util/List.isEmpty:()Z
     111: ifeq          136
     114: aload_0
     115: aload_1
     116: invokestatic  #64                 // Method org/apache/hadoop/hbase/shaded/protobuf/generated/BackupProtos$BackupImage.access$3200:(Lorg/apache/hadoop/hbase/shaded/protobuf/generated/BackupProtos$BackupImage;)Ljava/util/List;
     119: putfield      #14                 // Field tableList_:Ljava/util/List;
     122: aload_0
     123: aload_0
     124: getfield      #24                 // Field bitField0_:I
     127: bipush        -9
     129: iand
     130: putfield      #24                 // Field bitField0_:I
     133: goto          154
     136: aload_0
     137: invokespecial #66                 // Method ensureTableListIsMutable:()V
     140: aload_0
     141: getfield      #14                 // Field tableList_:Ljava/util/List;
     144: aload_1
     145: invokestatic  #64                 // Method org/apache/hadoop/hbase/shaded/protobuf/generated/BackupProtos$BackupImage.access$3200:(Lorg/apache/hadoop/hbase/shaded/protobuf/generated/BackupProtos$BackupImage;)Ljava/util/List;
     148: invokeinterface #67,  2           // InterfaceMethod java/util/List.addAll:(Ljava/util/Collection;)Z
     153: pop
     154: aload_0
     155: invokevirtual #58                 // Method onChanged:()V
     158: goto          247
     161: aload_1
     162: invokestatic  #64                 // Method org/apache/hadoop/hbase/shaded/protobuf/generated/BackupProtos$BackupImage.access$3200:(Lorg/apache/hadoop/hbase/shaded/protobuf/generated/BackupProtos$BackupImage;)Ljava/util/List;
     165: invokeinterface #65,  1           // InterfaceMethod java/util/List.isEmpty:()Z
     170: ifne          247
     173: aload_0
     174: getfield      #25                 // Field tableListBuilder_:Lorg/apache/hbase/thirdparty/com/google/protobuf/RepeatedFieldBuilderV3;
     177: invokevirtual #68                 // Method org/apache/hbase/thirdparty/com/google/protobuf/RepeatedFieldBuilderV3.isEmpty:()Z
     180: ifeq          235
     183: aload_0
     184: getfield      #25                 // Field tableListBuilder_:Lorg/apache/hbase/thirdparty/com/google/protobuf/RepeatedFieldBuilderV3;
     187: invokevirtual #69                 // Method org/apache/hbase/thirdparty/com/google/protobuf/RepeatedFieldBuilderV3.dispose:()V
     190: aload_0
     191: aconst_null
     192: putfield      #25                 // Field tableListBuilder_:Lorg/apache/hbase/thirdparty/com/google/protobuf/RepeatedFieldBuilderV3;
     195: aload_0
     196: aload_1
     197: invokestatic  #64                 // Method org/apache/hadoop/hbase/shaded/protobuf/generated/BackupProtos$BackupImage.access$3200:(Lorg/apache/hadoop/hbase/shaded/protobuf/generated/BackupProtos$BackupImage;)Ljava/util/List;
     200: putfield      #14                 // Field tableList_:Ljava/util/List;
     203: aload_0
     204: aload_0
     205: getfield      #24                 // Field bitField0_:I
     208: bipush        -9
     210: iand
     211: putfield      #24                 // Field bitField0_:I
     214: aload_0
     215: invokestatic  #70                 // Method org/apache/hadoop/hbase/shaded/protobuf/generated/BackupProtos$BackupImage.access$3800:()Z
     218: ifeq          228
     221: aload_0
     222: invokespecial #20                 // Method getTableListFieldBuilder:()Lorg/apache/hbase/thirdparty/com/google/protobuf/RepeatedFieldBuilderV3;
     225: goto          229
     228: aconst_null
     229: putfield      #25                 // Field tableListBuilder_:Lorg/apache/hbase/thirdparty/com/google/protobuf/RepeatedFieldBuilderV3;
     232: goto          247
     235: aload_0
     236: getfield      #25                 // Field tableListBuilder_:Lorg/apache/hbase/thirdparty/com/google/protobuf/RepeatedFieldBuilderV3;
     239: aload_1
     240: invokestatic  #64                 // Method org/apache/hadoop/hbase/shaded/protobuf/generated/BackupProtos$BackupImage.access$3200:(Lorg/apache/hadoop/hbase/shaded/protobuf/generated/BackupProtos$BackupImage;)Ljava/util/List;
     243: invokevirtual #71                 // Method org/apache/hbase/thirdparty/com/google/protobuf/RepeatedFieldBuilderV3.addAllMessages:(Ljava/lang/Iterable;)Lorg/apache/hbase/thirdparty/com/google/protobuf/RepeatedFieldBuilderV3;
     246: pop
     247: aload_1
     248: invokevirtual #72                 // Method org/apache/hadoop/hbase/shaded/protobuf/generated/BackupProtos$BackupImage.hasStartTs:()Z
     251: ifeq          263
     254: aload_0
     255: aload_1
     256: invokevirtual #73                 // Method org/apache/hadoop/hbase/shaded/protobuf/generated/BackupProtos$BackupImage.getStartTs:()J
     259: invokevirtual #74                 // Method setStartTs:(J)Lorg/apache/hadoop/hbase/shaded/protobuf/generated/BackupProtos$BackupImage$Builder;
     262: pop
     263: aload_1
     264: invokevirtual #75                 // Method org/apache/hadoop/hbase/shaded/protobuf/generated/BackupProtos$BackupImage.hasCompleteTs:()Z
     267: ifeq          279
     270: aload_0
     271: aload_1
     272: invokevirtual #76                 // Method org/apache/hadoop/hbase/shaded/protobuf/generated/BackupProtos$BackupImage.getCompleteTs:()J
     275: invokevirtual #77                 // Method setCompleteTs:(J)Lorg/apache/hadoop/hbase/shaded/protobuf/generated/BackupProtos$BackupImage$Builder;
     278: pop
     279: aload_0
     280: getfield      #29                 // Field ancestorsBuilder_:Lorg/apache/hbase/thirdparty/com/google/protobuf/RepeatedFieldBuilderV3;
     283: ifnonnull     357
     286: aload_1
     287: invokestatic  #78                 // Method org/apache/hadoop/hbase/shaded/protobuf/generated/BackupProtos$BackupImage.access$3500:(Lorg/apache/hadoop/hbase/shaded/protobuf/generated/BackupProtos$BackupImage;)Ljava/util/List;
     290: invokeinterface #65,  1           // InterfaceMethod java/util/List.isEmpty:()Z
     295: ifne          443
     298: aload_0
     299: getfield      #15                 // Field ancestors_:Ljava/util/List;
     302: invokeinterface #65,  1           // InterfaceMethod java/util/List.isEmpty:()Z
     307: ifeq          332
     310: aload_0
     311: aload_1
     312: invokestatic  #78                 // Method org/apache/hadoop/hbase/shaded/protobuf/generated/BackupProtos$BackupImage.access$3500:(Lorg/apache/hadoop/hbase/shaded/protobuf/generated/BackupProtos$BackupImage;)Ljava/util/List;
     315: putfield      #15                 // Field ancestors_:Ljava/util/List;
     318: aload_0
     319: aload_0
     320: getfield      #24                 // Field bitField0_:I
     323: bipush        -65
     325: iand
     326: putfield      #24                 // Field bitField0_:I
     329: goto          350
     332: aload_0
     333: invokespecial #79                 // Method ensureAncestorsIsMutable:()V
     336: aload_0
     337: getfield      #15                 // Field ancestors_:Ljava/util/List;
     340: aload_1
     341: invokestatic  #78                 // Method org/apache/hadoop/hbase/shaded/protobuf/generated/BackupProtos$BackupImage.access$3500:(Lorg/apache/hadoop/hbase/shaded/protobuf/generated/BackupProtos$BackupImage;)Ljava/util/List;
     344: invokeinterface #67,  2           // InterfaceMethod java/util/List.addAll:(Ljava/util/Collection;)Z
     349: pop
     350: aload_0
     351: invokevirtual #58                 // Method onChanged:()V
     354: goto          443
     357: aload_1
     358: invokestatic  #78                 // Method org/apache/hadoop/hbase/shaded/protobuf/generated/BackupProtos$BackupImage.access$3500:(Lorg/apache/hadoop/hbase/shaded/protobuf/generated/BackupProtos$BackupImage;)Ljava/util/List;
     361: invokeinterface #65,  1           // InterfaceMethod java/util/List.isEmpty:()Z
     366: ifne          443
     369: aload_0
     370: getfield      #29                 // Field ancestorsBuilder_:Lorg/apache/hbase/thirdparty/com/google/protobuf/RepeatedFieldBuilderV3;
     373: invokevirtual #68                 // Method org/apache/hbase/thirdparty/com/google/protobuf/RepeatedFieldBuilderV3.isEmpty:()Z
     376: ifeq          431
     379: aload_0
     380: getfield      #29                 // Field ancestorsBuilder_:Lorg/apache/hbase/thirdparty/com/google/protobuf/RepeatedFieldBuilderV3;
     383: invokevirtual #69                 // Method org/apache/hbase/thirdparty/com/google/protobuf/RepeatedFieldBuilderV3.dispose:()V
     386: aload_0
     387: aconst_null
     388: putfield      #29                 // Field ancestorsBuilder_:Lorg/apache/hbase/thirdparty/com/google/protobuf/RepeatedFieldBuilderV3;
     391: aload_0
     392: aload_1
     393: invokestatic  #78                 // Method org/apache/hadoop/hbase/shaded/protobuf/generated/BackupProtos$BackupImage.access$3500:(Lorg/apache/hadoop/hbase/shaded/protobuf/generated/BackupProtos$BackupImage;)Ljava/util/List;
     396: putfield      #15                 // Field ancestors_:Ljava/util/List;
     399: aload_0
     400: aload_0
     401: getfield      #24                 // Field bitField0_:I
     404: bipush        -65
     406: iand
     407: putfield      #24                 // Field bitField0_:I
     410: aload_0
     411: invokestatic  #80                 // Method org/apache/hadoop/hbase/shaded/protobuf/generated/BackupProtos$BackupImage.access$3900:()Z
     414: ifeq          424
     417: aload_0
     418: invokespecial #21                 // Method getAncestorsFieldBuilder:()Lorg/apache/hbase/thirdparty/com/google/protobuf/RepeatedFieldBuilderV3;
     421: goto          425
     424: aconst_null
     425: putfield      #29                 // Field ancestorsBuilder_:Lorg/apache/hbase/thirdparty/com/google/protobuf/RepeatedFieldBuilderV3;
     428: goto          443
     431: aload_0
     432: getfield      #29                 // Field ancestorsBuilder_:Lorg/apache/hbase/thirdparty/com/google/protobuf/RepeatedFieldBuilderV3;
     435: aload_1
     436: invokestatic  #78                 // Method org/apache/hadoop/hbase/shaded/protobuf/generated/BackupProtos$BackupImage.access$3500:(Lorg/apache/hadoop/hbase/shaded/protobuf/generated/BackupProtos$BackupImage;)Ljava/util/List;
     439: invokevirtual #71                 // Method org/apache/hbase/thirdparty/com/google/protobuf/RepeatedFieldBuilderV3.addAllMessages:(Ljava/lang/Iterable;)Lorg/apache/hbase/thirdparty/com/google/protobuf/RepeatedFieldBuilderV3;
     442: pop
     443: aload_0
     444: getfield      #30                 // Field tstMapBuilder_:Lorg/apache/hbase/thirdparty/com/google/protobuf/RepeatedFieldBuilderV3;
     447: ifnonnull     522
     450: aload_1
     451: invokestatic  #81                 // Method org/apache/hadoop/hbase/shaded/protobuf/generated/BackupProtos$BackupImage.access$3600:(Lorg/apache/hadoop/hbase/shaded/protobuf/generated/BackupProtos$BackupImage;)Ljava/util/List;
     454: invokeinterface #65,  1           // InterfaceMethod java/util/List.isEmpty:()Z
     459: ifne          609
     462: aload_0
     463: getfield      #16                 // Field tstMap_:Ljava/util/List;
     466: invokeinterface #65,  1           // InterfaceMethod java/util/List.isEmpty:()Z
     471: ifeq          497
     474: aload_0
     475: aload_1
     476: invokestatic  #81                 // Method org/apache/hadoop/hbase/shaded/protobuf/generated/BackupProtos$BackupImage.access$3600:(Lorg/apache/hadoop/hbase/shaded/protobuf/generated/BackupProtos$BackupImage;)Ljava/util/List;
     479: putfield      #16                 // Field tstMap_:Ljava/util/List;
     482: aload_0
     483: aload_0
     484: getfield      #24                 // Field bitField0_:I
     487: sipush        -129
     490: iand
     491: putfield      #24                 // Field bitField0_:I
     494: goto          515
     497: aload_0
     498: invokespecial #82                 // Method ensureTstMapIsMutable:()V
     501: aload_0
     502: getfield      #16                 // Field tstMap_:Ljava/util/List;
     505: aload_1
     506: invokestatic  #81                 // Method org/apache/hadoop/hbase/shaded/protobuf/generated/BackupProtos$BackupImage.access$3600:(Lorg/apache/hadoop/hbase/shaded/protobuf/generated/BackupProtos$BackupImage;)Ljava/util/List;
     509: invokeinterface #67,  2           // InterfaceMethod java/util/List.addAll:(Ljava/util/Collection;)Z
     514: pop
     515: aload_0
     516: invokevirtual #58                 // Method onChanged:()V
     519: goto          609
     522: aload_1
     523: invokestatic  #81                 // Method org/apache/hadoop/hbase/shaded/protobuf/generated/BackupProtos$BackupImage.access$3600:(Lorg/apache/hadoop/hbase/shaded/protobuf/generated/BackupProtos$BackupImage;)Ljava/util/List;
     526: invokeinterface #65,  1           // InterfaceMethod java/util/List.isEmpty:()Z
     531: ifne          609
     534: aload_0
     535: getfield      #30                 // Field tstMapBuilder_:Lorg/apache/hbase/thirdparty/com/google/protobuf/RepeatedFieldBuilderV3;
     538: invokevirtual #68                 // Method org/apache/hbase/thirdparty/com/google/protobuf/RepeatedFieldBuilderV3.isEmpty:()Z
     541: ifeq          597
     544: aload_0
     545: getfield      #30                 // Field tstMapBuilder_:Lorg/apache/hbase/thirdparty/com/google/protobuf/RepeatedFieldBuilderV3;
     548: invokevirtual #69                 // Method org/apache/hbase/thirdparty/com/google/protobuf/RepeatedFieldBuilderV3.dispose:()V
     551: aload_0
     552: aconst_null
     553: putfield      #30                 // Field tstMapBuilder_:Lorg/apache/hbase/thirdparty/com/google/protobuf/RepeatedFieldBuilderV3;
     556: aload_0
     557: aload_1
     558: invokestatic  #81                 // Method org/apache/hadoop/hbase/shaded/protobuf/generated/BackupProtos$BackupImage.access$3600:(Lorg/apache/hadoop/hbase/shaded/protobuf/generated/BackupProtos$BackupImage;)Ljava/util/List;
     561: putfield      #16                 // Field tstMap_:Ljava/util/List;
     564: aload_0
     565: aload_0
     566: getfield      #24                 // Field bitField0_:I
     569: sipush        -129
     572: iand
     573: putfield      #24                 // Field bitField0_:I
     576: aload_0
     577: invokestatic  #83                 // Method org/apache/hadoop/hbase/shaded/protobuf/generated/BackupProtos$BackupImage.access$4000:()Z
     580: ifeq          590
     583: aload_0
     584: invokespecial #22                 // Method getTstMapFieldBuilder:()Lorg/apache/hbase/thirdparty/com/google/protobuf/RepeatedFieldBuilderV3;
     587: goto          591
     590: aconst_null
     591: putfield      #30                 // Field tstMapBuilder_:Lorg/apache/hbase/thirdparty/com/google/protobuf/RepeatedFieldBuilderV3;
     594: goto          609
     597: aload_0
     598: getfield      #30                 // Field tstMapBuilder_:Lorg/apache/hbase/thirdparty/com/google/protobuf/RepeatedFieldBuilderV3;
     601: aload_1
     602: invokestatic  #81                 // Method org/apache/hadoop/hbase/shaded/protobuf/generated/BackupProtos$BackupImage.access$3600:(Lorg/apache/hadoop/hbase/shaded/protobuf/generated/BackupProtos$BackupImage;)Ljava/util/List;
     605: invokevirtual #71                 // Method org/apache/hbase/thirdparty/com/google/protobuf/RepeatedFieldBuilderV3.addAllMessages:(Ljava/lang/Iterable;)Lorg/apache/hbase/thirdparty/com/google/protobuf/RepeatedFieldBuilderV3;
     608: pop
     609: aload_0
     610: aload_1
     611: invokestatic  #84                 // Method org/apache/hadoop/hbase/shaded/protobuf/generated/BackupProtos$BackupImage.access$4100:(Lorg/apache/hadoop/hbase/shaded/protobuf/generated/BackupProtos$BackupImage;)Lorg/apache/hbase/thirdparty/com/google/protobuf/UnknownFieldSet;
     614: invokevirtual #85                 // Method mergeUnknownFields:(Lorg/apache/hbase/thirdparty/com/google/protobuf/UnknownFieldSet;)Lorg/apache/hadoop/hbase/shaded/protobuf/generated/BackupProtos$BackupImage$Builder;
     617: pop
     618: aload_0
     619: invokevirtual #58                 // Method onChanged:()V
     622: aload_0
     623: areturn

  public final boolean isInitialized();
    Code:
       0: iconst_0
       1: istore_1
       2: iload_1
       3: aload_0
       4: invokevirtual #86                 // Method getTableListCount:()I
       7: if_icmpge     29
      10: aload_0
      11: iload_1
      12: invokevirtual #87                 // Method getTableList:(I)Lorg/apache/hadoop/hbase/shaded/protobuf/generated/HBaseProtos$TableName;
      15: invokevirtual #88                 // Method org/apache/hadoop/hbase/shaded/protobuf/generated/HBaseProtos$TableName.isInitialized:()Z
      18: ifne          23
      21: iconst_0
      22: ireturn
      23: iinc          1, 1
      26: goto          2
      29: iconst_0
      30: istore_1
      31: iload_1
      32: aload_0
      33: invokevirtual #89                 // Method getAncestorsCount:()I
      36: if_icmpge     58
      39: aload_0
      40: iload_1
      41: invokevirtual #90                 // Method getAncestors:(I)Lorg/apache/hadoop/hbase/shaded/protobuf/generated/BackupProtos$BackupImage;
      44: invokevirtual #33                 // Method org/apache/hadoop/hbase/shaded/protobuf/generated/BackupProtos$BackupImage.isInitialized:()Z
      47: ifne          52
      50: iconst_0
      51: ireturn
      52: iinc          1, 1
      55: goto          31
      58: iconst_0
      59: istore_1
      60: iload_1
      61: aload_0
      62: invokevirtual #91                 // Method getTstMapCount:()I
      65: if_icmpge     87
      68: aload_0
      69: iload_1
      70: invokevirtual #92                 // Method getTstMap:(I)Lorg/apache/hadoop/hbase/shaded/protobuf/generated/BackupProtos$TableServerTimestamp;
      73: invokevirtual #93                 // Method org/apache/hadoop/hbase/shaded/protobuf/generated/BackupProtos$TableServerTimestamp.isInitialized:()Z
      76: ifne          81
      79: iconst_0
      80: ireturn
      81: iinc          1, 1
      84: goto          60
      87: iconst_1
      88: ireturn

  public org.apache.hadoop.hbase.shaded.protobuf.generated.BackupProtos$BackupImage$Builder mergeFrom(org.apache.hbase.thirdparty.com.google.protobuf.CodedInputStream, org.apache.hbase.thirdparty.com.google.protobuf.ExtensionRegistryLite) throws java.io.IOException;
    Code:
       0: aconst_null
       1: astore_3
       2: getstatic     #94                 // Field org/apache/hadoop/hbase/shaded/protobuf/generated/BackupProtos$BackupImage.PARSER:Lorg/apache/hbase/thirdparty/com/google/protobuf/Parser;
       5: aload_1
       6: aload_2
       7: invokeinterface #95,  3           // InterfaceMethod org/apache/hbase/thirdparty/com/google/protobuf/Parser.parsePartialFrom:(Lorg/apache/hbase/thirdparty/com/google/protobuf/CodedInputStream;Lorg/apache/hbase/thirdparty/com/google/protobuf/ExtensionRegistryLite;)Ljava/lang/Object;
      12: checkcast     #5                  // class org/apache/hadoop/hbase/shaded/protobuf/generated/BackupProtos$BackupImage
      15: astore_3
      16: aload_3
      17: ifnull        61
      20: aload_0
      21: aload_3
      22: invokevirtual #54                 // Method mergeFrom:(Lorg/apache/hadoop/hbase/shaded/protobuf/generated/BackupProtos$BackupImage;)Lorg/apache/hadoop/hbase/shaded/protobuf/generated/BackupProtos$BackupImage$Builder;
      25: pop
      26: goto          61
      29: astore        4
      31: aload         4
      33: invokevirtual #97                 // Method org/apache/hbase/thirdparty/com/google/protobuf/InvalidProtocolBufferException.getUnfinishedMessage:()Lorg/apache/hbase/thirdparty/com/google/protobuf/MessageLite;
      36: checkcast     #5                  // class org/apache/hadoop/hbase/shaded/protobuf/generated/BackupProtos$BackupImage
      39: astore_3
      40: aload         4
      42: invokevirtual #98                 // Method org/apache/hbase/thirdparty/com/google/protobuf/InvalidProtocolBufferException.unwrapIOException:()Ljava/io/IOException;
      45: athrow
      46: astore        5
      48: aload_3
      49: ifnull        58
      52: aload_0
      53: aload_3
      54: invokevirtual #54                 // Method mergeFrom:(Lorg/apache/hadoop/hbase/shaded/protobuf/generated/BackupProtos$BackupImage;)Lorg/apache/hadoop/hbase/shaded/protobuf/generated/BackupProtos$BackupImage$Builder;
      57: pop
      58: aload         5
      60: athrow
      61: aload_0
      62: areturn
    Exception table:
       from    to  target type
           2    16    29   Class org/apache/hbase/thirdparty/com/google/protobuf/InvalidProtocolBufferException
           2    16    46   any
          29    48    46   any

  public boolean hasBackupId();
    Code:
       0: aload_0
       1: getfield      #24                 // Field bitField0_:I
       4: iconst_1
       5: iand
       6: iconst_1
       7: if_icmpne     14
      10: iconst_1
      11: goto          15
      14: iconst_0
      15: ireturn

  public java.lang.String getBackupId();
    Code:
       0: aload_0
       1: getfield      #10                 // Field backupId_:Ljava/lang/Object;
       4: astore_1
       5: aload_1
       6: instanceof    #99                 // class java/lang/String
       9: ifne          36
      12: aload_1
      13: checkcast     #100                // class org/apache/hbase/thirdparty/com/google/protobuf/ByteString
      16: astore_2
      17: aload_2
      18: invokevirtual #101                // Method org/apache/hbase/thirdparty/com/google/protobuf/ByteString.toStringUtf8:()Ljava/lang/String;
      21: astore_3
      22: aload_2
      23: invokevirtual #102                // Method org/apache/hbase/thirdparty/com/google/protobuf/ByteString.isValidUtf8:()Z
      26: ifeq          34
      29: aload_0
      30: aload_3
      31: putfield      #10                 // Field backupId_:Ljava/lang/Object;
      34: aload_3
      35: areturn
      36: aload_1
      37: checkcast     #99                 // class java/lang/String
      40: areturn

  public org.apache.hbase.thirdparty.com.google.protobuf.ByteString getBackupIdBytes();
    Code:
       0: aload_0
       1: getfield      #10                 // Field backupId_:Ljava/lang/Object;
       4: astore_1
       5: aload_1
       6: instanceof    #99                 // class java/lang/String
       9: ifeq          27
      12: aload_1
      13: checkcast     #99                 // class java/lang/String
      16: invokestatic  #103                // Method org/apache/hbase/thirdparty/com/google/protobuf/ByteString.copyFromUtf8:(Ljava/lang/String;)Lorg/apache/hbase/thirdparty/com/google/protobuf/ByteString;
      19: astore_2
      20: aload_0
      21: aload_2
      22: putfield      #10                 // Field backupId_:Ljava/lang/Object;
      25: aload_2
      26: areturn
      27: aload_1
      28: checkcast     #100                // class org/apache/hbase/thirdparty/com/google/protobuf/ByteString
      31: areturn

  public org.apache.hadoop.hbase.shaded.protobuf.generated.BackupProtos$BackupImage$Builder setBackupId(java.lang.String);
    Code:
       0: aload_1
       1: ifnonnull     12
       4: new           #104                // class java/lang/NullPointerException
       7: dup
       8: invokespecial #105                // Method java/lang/NullPointerException."<init>":()V
      11: athrow
      12: aload_0
      13: dup
      14: getfield      #24                 // Field bitField0_:I
      17: iconst_1
      18: ior
      19: putfield      #24                 // Field bitField0_:I
      22: aload_0
      23: aload_1
      24: putfield      #10                 // Field backupId_:Ljava/lang/Object;
      27: aload_0
      28: invokevirtual #58                 // Method onChanged:()V
      31: aload_0
      32: areturn

  public org.apache.hadoop.hbase.shaded.protobuf.generated.BackupProtos$BackupImage$Builder clearBackupId();
    Code:
       0: aload_0
       1: aload_0
       2: getfield      #24                 // Field bitField0_:I
       5: bipush        -2
       7: iand
       8: putfield      #24                 // Field bitField0_:I
      11: aload_0
      12: invokestatic  #31                 // Method org/apache/hadoop/hbase/shaded/protobuf/generated/BackupProtos$BackupImage.getDefaultInstance:()Lorg/apache/hadoop/hbase/shaded/protobuf/generated/BackupProtos$BackupImage;
      15: invokevirtual #106                // Method org/apache/hadoop/hbase/shaded/protobuf/generated/BackupProtos$BackupImage.getBackupId:()Ljava/lang/String;
      18: putfield      #10                 // Field backupId_:Ljava/lang/Object;
      21: aload_0
      22: invokevirtual #58                 // Method onChanged:()V
      25: aload_0
      26: areturn

  public org.apache.hadoop.hbase.shaded.protobuf.generated.BackupProtos$BackupImage$Builder setBackupIdBytes(org.apache.hbase.thirdparty.com.google.protobuf.ByteString);
    Code:
       0: aload_1
       1: ifnonnull     12
       4: new           #104                // class java/lang/NullPointerException
       7: dup
       8: invokespecial #105                // Method java/lang/NullPointerException."<init>":()V
      11: athrow
      12: aload_0
      13: dup
      14: getfield      #24                 // Field bitField0_:I
      17: iconst_1
      18: ior
      19: putfield      #24                 // Field bitField0_:I
      22: aload_0
      23: aload_1
      24: putfield      #10                 // Field backupId_:Ljava/lang/Object;
      27: aload_0
      28: invokevirtual #58                 // Method onChanged:()V
      31: aload_0
      32: areturn

  public boolean hasBackupType();
    Code:
       0: aload_0
       1: getfield      #24                 // Field bitField0_:I
       4: iconst_2
       5: iand
       6: iconst_2
       7: if_icmpne     14
      10: iconst_1
      11: goto          15
      14: iconst_0
      15: ireturn

  public org.apache.hadoop.hbase.shaded.protobuf.generated.BackupProtos$BackupType getBackupType();
    Code:
       0: aload_0
       1: getfield      #11                 // Field backupType_:I
       4: invokestatic  #107                // Method org/apache/hadoop/hbase/shaded/protobuf/generated/BackupProtos$BackupType.valueOf:(I)Lorg/apache/hadoop/hbase/shaded/protobuf/generated/BackupProtos$BackupType;
       7: astore_1
       8: aload_1
       9: ifnonnull     18
      12: getstatic     #108                // Field org/apache/hadoop/hbase/shaded/protobuf/generated/BackupProtos$BackupType.FULL:Lorg/apache/hadoop/hbase/shaded/protobuf/generated/BackupProtos$BackupType;
      15: goto          19
      18: aload_1
      19: areturn

  public org.apache.hadoop.hbase.shaded.protobuf.generated.BackupProtos$BackupImage$Builder setBackupType(org.apache.hadoop.hbase.shaded.protobuf.generated.BackupProtos$BackupType);
    Code:
       0: aload_1
       1: ifnonnull     12
       4: new           #104                // class java/lang/NullPointerException
       7: dup
       8: invokespecial #105                // Method java/lang/NullPointerException."<init>":()V
      11: athrow
      12: aload_0
      13: dup
      14: getfield      #24                 // Field bitField0_:I
      17: iconst_2
      18: ior
      19: putfield      #24                 // Field bitField0_:I
      22: aload_0
      23: aload_1
      24: invokevirtual #109                // Method org/apache/hadoop/hbase/shaded/protobuf/generated/BackupProtos$BackupType.getNumber:()I
      27: putfield      #11                 // Field backupType_:I
      30: aload_0
      31: invokevirtual #58                 // Method onChanged:()V
      34: aload_0
      35: areturn

  public org.apache.hadoop.hbase.shaded.protobuf.generated.BackupProtos$BackupImage$Builder clearBackupType();
    Code:
       0: aload_0
       1: aload_0
       2: getfield      #24                 // Field bitField0_:I
       5: bipush        -3
       7: iand
       8: putfield      #24                 // Field bitField0_:I
      11: aload_0
      12: iconst_0
      13: putfield      #11                 // Field backupType_:I
      16: aload_0
      17: invokevirtual #58                 // Method onChanged:()V
      20: aload_0
      21: areturn

  public boolean hasBackupRootDir();
    Code:
       0: aload_0
       1: getfield      #24                 // Field bitField0_:I
       4: iconst_4
       5: iand
       6: iconst_4
       7: if_icmpne     14
      10: iconst_1
      11: goto          15
      14: iconst_0
      15: ireturn

  public java.lang.String getBackupRootDir();
    Code:
       0: aload_0
       1: getfield      #12                 // Field backupRootDir_:Ljava/lang/Object;
       4: astore_1
       5: aload_1
       6: instanceof    #99                 // class java/lang/String
       9: ifne          36
      12: aload_1
      13: checkcast     #100                // class org/apache/hbase/thirdparty/com/google/protobuf/ByteString
      16: astore_2
      17: aload_2
      18: invokevirtual #101                // Method org/apache/hbase/thirdparty/com/google/protobuf/ByteString.toStringUtf8:()Ljava/lang/String;
      21: astore_3
      22: aload_2
      23: invokevirtual #102                // Method org/apache/hbase/thirdparty/com/google/protobuf/ByteString.isValidUtf8:()Z
      26: ifeq          34
      29: aload_0
      30: aload_3
      31: putfield      #12                 // Field backupRootDir_:Ljava/lang/Object;
      34: aload_3
      35: areturn
      36: aload_1
      37: checkcast     #99                 // class java/lang/String
      40: areturn

  public org.apache.hbase.thirdparty.com.google.protobuf.ByteString getBackupRootDirBytes();
    Code:
       0: aload_0
       1: getfield      #12                 // Field backupRootDir_:Ljava/lang/Object;
       4: astore_1
       5: aload_1
       6: instanceof    #99                 // class java/lang/String
       9: ifeq          27
      12: aload_1
      13: checkcast     #99                 // class java/lang/String
      16: invokestatic  #103                // Method org/apache/hbase/thirdparty/com/google/protobuf/ByteString.copyFromUtf8:(Ljava/lang/String;)Lorg/apache/hbase/thirdparty/com/google/protobuf/ByteString;
      19: astore_2
      20: aload_0
      21: aload_2
      22: putfield      #12                 // Field backupRootDir_:Ljava/lang/Object;
      25: aload_2
      26: areturn
      27: aload_1
      28: checkcast     #100                // class org/apache/hbase/thirdparty/com/google/protobuf/ByteString
      31: areturn

  public org.apache.hadoop.hbase.shaded.protobuf.generated.BackupProtos$BackupImage$Builder setBackupRootDir(java.lang.String);
    Code:
       0: aload_1
       1: ifnonnull     12
       4: new           #104                // class java/lang/NullPointerException
       7: dup
       8: invokespecial #105                // Method java/lang/NullPointerException."<init>":()V
      11: athrow
      12: aload_0
      13: dup
      14: getfield      #24                 // Field bitField0_:I
      17: iconst_4
      18: ior
      19: putfield      #24                 // Field bitField0_:I
      22: aload_0
      23: aload_1
      24: putfield      #12                 // Field backupRootDir_:Ljava/lang/Object;
      27: aload_0
      28: invokevirtual #58                 // Method onChanged:()V
      31: aload_0
      32: areturn

  public org.apache.hadoop.hbase.shaded.protobuf.generated.BackupProtos$BackupImage$Builder clearBackupRootDir();
    Code:
       0: aload_0
       1: aload_0
       2: getfield      #24                 // Field bitField0_:I
       5: bipush        -5
       7: iand
       8: putfield      #24                 // Field bitField0_:I
      11: aload_0
      12: invokestatic  #31                 // Method org/apache/hadoop/hbase/shaded/protobuf/generated/BackupProtos$BackupImage.getDefaultInstance:()Lorg/apache/hadoop/hbase/shaded/protobuf/generated/BackupProtos$BackupImage;
      15: invokevirtual #110                // Method org/apache/hadoop/hbase/shaded/protobuf/generated/BackupProtos$BackupImage.getBackupRootDir:()Ljava/lang/String;
      18: putfield      #12                 // Field backupRootDir_:Ljava/lang/Object;
      21: aload_0
      22: invokevirtual #58                 // Method onChanged:()V
      25: aload_0
      26: areturn

  public org.apache.hadoop.hbase.shaded.protobuf.generated.BackupProtos$BackupImage$Builder setBackupRootDirBytes(org.apache.hbase.thirdparty.com.google.protobuf.ByteString);
    Code:
       0: aload_1
       1: ifnonnull     12
       4: new           #104                // class java/lang/NullPointerException
       7: dup
       8: invokespecial #105                // Method java/lang/NullPointerException."<init>":()V
      11: athrow
      12: aload_0
      13: dup
      14: getfield      #24                 // Field bitField0_:I
      17: iconst_4
      18: ior
      19: putfield      #24                 // Field bitField0_:I
      22: aload_0
      23: aload_1
      24: putfield      #12                 // Field backupRootDir_:Ljava/lang/Object;
      27: aload_0
      28: invokevirtual #58                 // Method onChanged:()V
      31: aload_0
      32: areturn

  public java.util.List<org.apache.hadoop.hbase.shaded.protobuf.generated.HBaseProtos$TableName> getTableListList();
    Code:
       0: aload_0
       1: getfield      #25                 // Field tableListBuilder_:Lorg/apache/hbase/thirdparty/com/google/protobuf/RepeatedFieldBuilderV3;
       4: ifnonnull     15
       7: aload_0
       8: getfield      #14                 // Field tableList_:Ljava/util/List;
      11: invokestatic  #39                 // Method java/util/Collections.unmodifiableList:(Ljava/util/List;)Ljava/util/List;
      14: areturn
      15: aload_0
      16: getfield      #25                 // Field tableListBuilder_:Lorg/apache/hbase/thirdparty/com/google/protobuf/RepeatedFieldBuilderV3;
      19: invokevirtual #113                // Method org/apache/hbase/thirdparty/com/google/protobuf/RepeatedFieldBuilderV3.getMessageList:()Ljava/util/List;
      22: areturn

  public int getTableListCount();
    Code:
       0: aload_0
       1: getfield      #25                 // Field tableListBuilder_:Lorg/apache/hbase/thirdparty/com/google/protobuf/RepeatedFieldBuilderV3;
       4: ifnonnull     17
       7: aload_0
       8: getfield      #14                 // Field tableList_:Ljava/util/List;
      11: invokeinterface #114,  1          // InterfaceMethod java/util/List.size:()I
      16: ireturn
      17: aload_0
      18: getfield      #25                 // Field tableListBuilder_:Lorg/apache/hbase/thirdparty/com/google/protobuf/RepeatedFieldBuilderV3;
      21: invokevirtual #115                // Method org/apache/hbase/thirdparty/com/google/protobuf/RepeatedFieldBuilderV3.getCount:()I
      24: ireturn

  public org.apache.hadoop.hbase.shaded.protobuf.generated.HBaseProtos$TableName getTableList(int);
    Code:
       0: aload_0
       1: getfield      #25                 // Field tableListBuilder_:Lorg/apache/hbase/thirdparty/com/google/protobuf/RepeatedFieldBuilderV3;
       4: ifnonnull     21
       7: aload_0
       8: getfield      #14                 // Field tableList_:Ljava/util/List;
      11: iload_1
      12: invokeinterface #116,  2          // InterfaceMethod java/util/List.get:(I)Ljava/lang/Object;
      17: checkcast     #117                // class org/apache/hadoop/hbase/shaded/protobuf/generated/HBaseProtos$TableName
      20: areturn
      21: aload_0
      22: getfield      #25                 // Field tableListBuilder_:Lorg/apache/hbase/thirdparty/com/google/protobuf/RepeatedFieldBuilderV3;
      25: iload_1
      26: invokevirtual #118                // Method org/apache/hbase/thirdparty/com/google/protobuf/RepeatedFieldBuilderV3.getMessage:(I)Lorg/apache/hbase/thirdparty/com/google/protobuf/AbstractMessage;
      29: checkcast     #117                // class org/apache/hadoop/hbase/shaded/protobuf/generated/HBaseProtos$TableName
      32: areturn

  public org.apache.hadoop.hbase.shaded.protobuf.generated.BackupProtos$BackupImage$Builder setTableList(int, org.apache.hadoop.hbase.shaded.protobuf.generated.HBaseProtos$TableName);
    Code:
       0: aload_0
       1: getfield      #25                 // Field tableListBuilder_:Lorg/apache/hbase/thirdparty/com/google/protobuf/RepeatedFieldBuilderV3;
       4: ifnonnull     42
       7: aload_2
       8: ifnonnull     19
      11: new           #104                // class java/lang/NullPointerException
      14: dup
      15: invokespecial #105                // Method java/lang/NullPointerException."<init>":()V
      18: athrow
      19: aload_0
      20: invokespecial #66                 // Method ensureTableListIsMutable:()V
      23: aload_0
      24: getfield      #14                 // Field tableList_:Ljava/util/List;
      27: iload_1
      28: aload_2
      29: invokeinterface #119,  3          // InterfaceMethod java/util/List.set:(ILjava/lang/Object;)Ljava/lang/Object;
      34: pop
      35: aload_0
      36: invokevirtual #58                 // Method onChanged:()V
      39: goto          52
      42: aload_0
      43: getfield      #25                 // Field tableListBuilder_:Lorg/apache/hbase/thirdparty/com/google/protobuf/RepeatedFieldBuilderV3;
      46: iload_1
      47: aload_2
      48: invokevirtual #120                // Method org/apache/hbase/thirdparty/com/google/protobuf/RepeatedFieldBuilderV3.setMessage:(ILorg/apache/hbase/thirdparty/com/google/protobuf/AbstractMessage;)Lorg/apache/hbase/thirdparty/com/google/protobuf/RepeatedFieldBuilderV3;
      51: pop
      52: aload_0
      53: areturn

  public org.apache.hadoop.hbase.shaded.protobuf.generated.BackupProtos$BackupImage$Builder setTableList(int, org.apache.hadoop.hbase.shaded.protobuf.generated.HBaseProtos$TableName$Builder);
    Code:
       0: aload_0
       1: getfield      #25                 // Field tableListBuilder_:Lorg/apache/hbase/thirdparty/com/google/protobuf/RepeatedFieldBuilderV3;
       4: ifnonnull     33
       7: aload_0
       8: invokespecial #66                 // Method ensureTableListIsMutable:()V
      11: aload_0
      12: getfield      #14                 // Field tableList_:Ljava/util/List;
      15: iload_1
      16: aload_2
      17: invokevirtual #121                // Method org/apache/hadoop/hbase/shaded/protobuf/generated/HBaseProtos$TableName$Builder.build:()Lorg/apache/hadoop/hbase/shaded/protobuf/generated/HBaseProtos$TableName;
      20: invokeinterface #119,  3          // InterfaceMethod java/util/List.set:(ILjava/lang/Object;)Ljava/lang/Object;
      25: pop
      26: aload_0
      27: invokevirtual #58                 // Method onChanged:()V
      30: goto          46
      33: aload_0
      34: getfield      #25                 // Field tableListBuilder_:Lorg/apache/hbase/thirdparty/com/google/protobuf/RepeatedFieldBuilderV3;
      37: iload_1
      38: aload_2
      39: invokevirtual #121                // Method org/apache/hadoop/hbase/shaded/protobuf/generated/HBaseProtos$TableName$Builder.build:()Lorg/apache/hadoop/hbase/shaded/protobuf/generated/HBaseProtos$TableName;
      42: invokevirtual #120                // Method org/apache/hbase/thirdparty/com/google/protobuf/RepeatedFieldBuilderV3.setMessage:(ILorg/apache/hbase/thirdparty/com/google/protobuf/AbstractMessage;)Lorg/apache/hbase/thirdparty/com/google/protobuf/RepeatedFieldBuilderV3;
      45: pop
      46: aload_0
      47: areturn

  public org.apache.hadoop.hbase.shaded.protobuf.generated.BackupProtos$BackupImage$Builder addTableList(org.apache.hadoop.hbase.shaded.protobuf.generated.HBaseProtos$TableName);
    Code:
       0: aload_0
       1: getfield      #25                 // Field tableListBuilder_:Lorg/apache/hbase/thirdparty/com/google/protobuf/RepeatedFieldBuilderV3;
       4: ifnonnull     41
       7: aload_1
       8: ifnonnull     19
      11: new           #104                // class java/lang/NullPointerException
      14: dup
      15: invokespecial #105                // Method java/lang/NullPointerException."<init>":()V
      18: athrow
      19: aload_0
      20: invokespecial #66                 // Method ensureTableListIsMutable:()V
      23: aload_0
      24: getfield      #14                 // Field tableList_:Ljava/util/List;
      27: aload_1
      28: invokeinterface #122,  2          // InterfaceMethod java/util/List.add:(Ljava/lang/Object;)Z
      33: pop
      34: aload_0
      35: invokevirtual #58                 // Method onChanged:()V
      38: goto          50
      41: aload_0
      42: getfield      #25                 // Field tableListBuilder_:Lorg/apache/hbase/thirdparty/com/google/protobuf/RepeatedFieldBuilderV3;
      45: aload_1
      46: invokevirtual #123                // Method org/apache/hbase/thirdparty/com/google/protobuf/RepeatedFieldBuilderV3.addMessage:(Lorg/apache/hbase/thirdparty/com/google/protobuf/AbstractMessage;)Lorg/apache/hbase/thirdparty/com/google/protobuf/RepeatedFieldBuilderV3;
      49: pop
      50: aload_0
      51: areturn

  public org.apache.hadoop.hbase.shaded.protobuf.generated.BackupProtos$BackupImage$Builder addTableList(int, org.apache.hadoop.hbase.shaded.protobuf.generated.HBaseProtos$TableName);
    Code:
       0: aload_0
       1: getfield      #25                 // Field tableListBuilder_:Lorg/apache/hbase/thirdparty/com/google/protobuf/RepeatedFieldBuilderV3;
       4: ifnonnull     41
       7: aload_2
       8: ifnonnull     19
      11: new           #104                // class java/lang/NullPointerException
      14: dup
      15: invokespecial #105                // Method java/lang/NullPointerException."<init>":()V
      18: athrow
      19: aload_0
      20: invokespecial #66                 // Method ensureTableListIsMutable:()V
      23: aload_0
      24: getfield      #14                 // Field tableList_:Ljava/util/List;
      27: iload_1
      28: aload_2
      29: invokeinterface #124,  3          // InterfaceMethod java/util/List.add:(ILjava/lang/Object;)V
      34: aload_0
      35: invokevirtual #58                 // Method onChanged:()V
      38: goto          51
      41: aload_0
      42: getfield      #25                 // Field tableListBuilder_:Lorg/apache/hbase/thirdparty/com/google/protobuf/RepeatedFieldBuilderV3;
      45: iload_1
      46: aload_2
      47: invokevirtual #125                // Method org/apache/hbase/thirdparty/com/google/protobuf/RepeatedFieldBuilderV3.addMessage:(ILorg/apache/hbase/thirdparty/com/google/protobuf/AbstractMessage;)Lorg/apache/hbase/thirdparty/com/google/protobuf/RepeatedFieldBuilderV3;
      50: pop
      51: aload_0
      52: areturn

  public org.apache.hadoop.hbase.shaded.protobuf.generated.BackupProtos$BackupImage$Builder addTableList(org.apache.hadoop.hbase.shaded.protobuf.generated.HBaseProtos$TableName$Builder);
    Code:
       0: aload_0
       1: getfield      #25                 // Field tableListBuilder_:Lorg/apache/hbase/thirdparty/com/google/protobuf/RepeatedFieldBuilderV3;
       4: ifnonnull     32
       7: aload_0
       8: invokespecial #66                 // Method ensureTableListIsMutable:()V
      11: aload_0
      12: getfield      #14                 // Field tableList_:Ljava/util/List;
      15: aload_1
      16: invokevirtual #121                // Method org/apache/hadoop/hbase/shaded/protobuf/generated/HBaseProtos$TableName$Builder.build:()Lorg/apache/hadoop/hbase/shaded/protobuf/generated/HBaseProtos$TableName;
      19: invokeinterface #122,  2          // InterfaceMethod java/util/List.add:(Ljava/lang/Object;)Z
      24: pop
      25: aload_0
      26: invokevirtual #58                 // Method onChanged:()V
      29: goto          44
      32: aload_0
      33: getfield      #25                 // Field tableListBuilder_:Lorg/apache/hbase/thirdparty/com/google/protobuf/RepeatedFieldBuilderV3;
      36: aload_1
      37: invokevirtual #121                // Method org/apache/hadoop/hbase/shaded/protobuf/generated/HBaseProtos$TableName$Builder.build:()Lorg/apache/hadoop/hbase/shaded/protobuf/generated/HBaseProtos$TableName;
      40: invokevirtual #123                // Method org/apache/hbase/thirdparty/com/google/protobuf/RepeatedFieldBuilderV3.addMessage:(Lorg/apache/hbase/thirdparty/com/google/protobuf/AbstractMessage;)Lorg/apache/hbase/thirdparty/com/google/protobuf/RepeatedFieldBuilderV3;
      43: pop
      44: aload_0
      45: areturn

  public org.apache.hadoop.hbase.shaded.protobuf.generated.BackupProtos$BackupImage$Builder addTableList(int, org.apache.hadoop.hbase.shaded.protobuf.generated.HBaseProtos$TableName$Builder);
    Code:
       0: aload_0
       1: getfield      #25                 // Field tableListBuilder_:Lorg/apache/hbase/thirdparty/com/google/protobuf/RepeatedFieldBuilderV3;
       4: ifnonnull     32
       7: aload_0
       8: invokespecial #66                 // Method ensureTableListIsMutable:()V
      11: aload_0
      12: getfield      #14                 // Field tableList_:Ljava/util/List;
      15: iload_1
      16: aload_2
      17: invokevirtual #121                // Method org/apache/hadoop/hbase/shaded/protobuf/generated/HBaseProtos$TableName$Builder.build:()Lorg/apache/hadoop/hbase/shaded/protobuf/generated/HBaseProtos$TableName;
      20: invokeinterface #124,  3          // InterfaceMethod java/util/List.add:(ILjava/lang/Object;)V
      25: aload_0
      26: invokevirtual #58                 // Method onChanged:()V
      29: goto          45
      32: aload_0
      33: getfield      #25                 // Field tableListBuilder_:Lorg/apache/hbase/thirdparty/com/google/protobuf/RepeatedFieldBuilderV3;
      36: iload_1
      37: aload_2
      38: invokevirtual #121                // Method org/apache/hadoop/hbase/shaded/protobuf/generated/HBaseProtos$TableName$Builder.build:()Lorg/apache/hadoop/hbase/shaded/protobuf/generated/HBaseProtos$TableName;
      41: invokevirtual #125                // Method org/apache/hbase/thirdparty/com/google/protobuf/RepeatedFieldBuilderV3.addMessage:(ILorg/apache/hbase/thirdparty/com/google/protobuf/AbstractMessage;)Lorg/apache/hbase/thirdparty/com/google/protobuf/RepeatedFieldBuilderV3;
      44: pop
      45: aload_0
      46: areturn

  public org.apache.hadoop.hbase.shaded.protobuf.generated.BackupProtos$BackupImage$Builder addAllTableList(java.lang.Iterable<? extends org.apache.hadoop.hbase.shaded.protobuf.generated.HBaseProtos$TableName>);
    Code:
       0: aload_0
       1: getfield      #25                 // Field tableListBuilder_:Lorg/apache/hbase/thirdparty/com/google/protobuf/RepeatedFieldBuilderV3;
       4: ifnonnull     26
       7: aload_0
       8: invokespecial #66                 // Method ensureTableListIsMutable:()V
      11: aload_1
      12: aload_0
      13: getfield      #14                 // Field tableList_:Ljava/util/List;
      16: invokestatic  #126                // Method org/apache/hbase/thirdparty/com/google/protobuf/AbstractMessageLite$Builder.addAll:(Ljava/lang/Iterable;Ljava/util/List;)V
      19: aload_0
      20: invokevirtual #58                 // Method onChanged:()V
      23: goto          35
      26: aload_0
      27: getfield      #25                 // Field tableListBuilder_:Lorg/apache/hbase/thirdparty/com/google/protobuf/RepeatedFieldBuilderV3;
      30: aload_1
      31: invokevirtual #71                 // Method org/apache/hbase/thirdparty/com/google/protobuf/RepeatedFieldBuilderV3.addAllMessages:(Ljava/lang/Iterable;)Lorg/apache/hbase/thirdparty/com/google/protobuf/RepeatedFieldBuilderV3;
      34: pop
      35: aload_0
      36: areturn

  public org.apache.hadoop.hbase.shaded.protobuf.generated.BackupProtos$BackupImage$Builder clearTableList();
    Code:
       0: aload_0
       1: getfield      #25                 // Field tableListBuilder_:Lorg/apache/hbase/thirdparty/com/google/protobuf/RepeatedFieldBuilderV3;
       4: ifnonnull     32
       7: aload_0
       8: invokestatic  #13                 // Method java/util/Collections.emptyList:()Ljava/util/List;
      11: putfield      #14                 // Field tableList_:Ljava/util/List;
      14: aload_0
      15: aload_0
      16: getfield      #24                 // Field bitField0_:I
      19: bipush        -9
      21: iand
      22: putfield      #24                 // Field bitField0_:I
      25: aload_0
      26: invokevirtual #58                 // Method onChanged:()V
      29: goto          39
      32: aload_0
      33: getfield      #25                 // Field tableListBuilder_:Lorg/apache/hbase/thirdparty/com/google/protobuf/RepeatedFieldBuilderV3;
      36: invokevirtual #26                 // Method org/apache/hbase/thirdparty/com/google/protobuf/RepeatedFieldBuilderV3.clear:()V
      39: aload_0
      40: areturn

  public org.apache.hadoop.hbase.shaded.protobuf.generated.BackupProtos$BackupImage$Builder removeTableList(int);
    Code:
       0: aload_0
       1: getfield      #25                 // Field tableListBuilder_:Lorg/apache/hbase/thirdparty/com/google/protobuf/RepeatedFieldBuilderV3;
       4: ifnonnull     29
       7: aload_0
       8: invokespecial #66                 // Method ensureTableListIsMutable:()V
      11: aload_0
      12: getfield      #14                 // Field tableList_:Ljava/util/List;
      15: iload_1
      16: invokeinterface #127,  2          // InterfaceMethod java/util/List.remove:(I)Ljava/lang/Object;
      21: pop
      22: aload_0
      23: invokevirtual #58                 // Method onChanged:()V
      26: goto          37
      29: aload_0
      30: getfield      #25                 // Field tableListBuilder_:Lorg/apache/hbase/thirdparty/com/google/protobuf/RepeatedFieldBuilderV3;
      33: iload_1
      34: invokevirtual #128                // Method org/apache/hbase/thirdparty/com/google/protobuf/RepeatedFieldBuilderV3.remove:(I)V
      37: aload_0
      38: areturn

  public org.apache.hadoop.hbase.shaded.protobuf.generated.HBaseProtos$TableName$Builder getTableListBuilder(int);
    Code:
       0: aload_0
       1: invokespecial #20                 // Method getTableListFieldBuilder:()Lorg/apache/hbase/thirdparty/com/google/protobuf/RepeatedFieldBuilderV3;
       4: iload_1
       5: invokevirtual #129                // Method org/apache/hbase/thirdparty/com/google/protobuf/RepeatedFieldBuilderV3.getBuilder:(I)Lorg/apache/hbase/thirdparty/com/google/protobuf/AbstractMessage$Builder;
       8: checkcast     #130                // class org/apache/hadoop/hbase/shaded/protobuf/generated/HBaseProtos$TableName$Builder
      11: areturn

  public org.apache.hadoop.hbase.shaded.protobuf.generated.HBaseProtos$TableNameOrBuilder getTableListOrBuilder(int);
    Code:
       0: aload_0
       1: getfield      #25                 // Field tableListBuilder_:Lorg/apache/hbase/thirdparty/com/google/protobuf/RepeatedFieldBuilderV3;
       4: ifnonnull     21
       7: aload_0
       8: getfield      #14                 // Field tableList_:Ljava/util/List;
      11: iload_1
      12: invokeinterface #116,  2          // InterfaceMethod java/util/List.get:(I)Ljava/lang/Object;
      17: checkcast     #131                // class org/apache/hadoop/hbase/shaded/protobuf/generated/HBaseProtos$TableNameOrBuilder
      20: areturn
      21: aload_0
      22: getfield      #25                 // Field tableListBuilder_:Lorg/apache/hbase/thirdparty/com/google/protobuf/RepeatedFieldBuilderV3;
      25: iload_1
      26: invokevirtual #132                // Method org/apache/hbase/thirdparty/com/google/protobuf/RepeatedFieldBuilderV3.getMessageOrBuilder:(I)Lorg/apache/hbase/thirdparty/com/google/protobuf/MessageOrBuilder;
      29: checkcast     #131                // class org/apache/hadoop/hbase/shaded/protobuf/generated/HBaseProtos$TableNameOrBuilder
      32: areturn

  public java.util.List<? extends org.apache.hadoop.hbase.shaded.protobuf.generated.HBaseProtos$TableNameOrBuilder> getTableListOrBuilderList();
    Code:
       0: aload_0
       1: getfield      #25                 // Field tableListBuilder_:Lorg/apache/hbase/thirdparty/com/google/protobuf/RepeatedFieldBuilderV3;
       4: ifnull        15
       7: aload_0
       8: getfield      #25                 // Field tableListBuilder_:Lorg/apache/hbase/thirdparty/com/google/protobuf/RepeatedFieldBuilderV3;
      11: invokevirtual #133                // Method org/apache/hbase/thirdparty/com/google/protobuf/RepeatedFieldBuilderV3.getMessageOrBuilderList:()Ljava/util/List;
      14: areturn
      15: aload_0
      16: getfield      #14                 // Field tableList_:Ljava/util/List;
      19: invokestatic  #39                 // Method java/util/Collections.unmodifiableList:(Ljava/util/List;)Ljava/util/List;
      22: areturn

  public org.apache.hadoop.hbase.shaded.protobuf.generated.HBaseProtos$TableName$Builder addTableListBuilder();
    Code:
       0: aload_0
       1: invokespecial #20                 // Method getTableListFieldBuilder:()Lorg/apache/hbase/thirdparty/com/google/protobuf/RepeatedFieldBuilderV3;
       4: invokestatic  #134                // Method org/apache/hadoop/hbase/shaded/protobuf/generated/HBaseProtos$TableName.getDefaultInstance:()Lorg/apache/hadoop/hbase/shaded/protobuf/generated/HBaseProtos$TableName;
       7: invokevirtual #135                // Method org/apache/hbase/thirdparty/com/google/protobuf/RepeatedFieldBuilderV3.addBuilder:(Lorg/apache/hbase/thirdparty/com/google/protobuf/AbstractMessage;)Lorg/apache/hbase/thirdparty/com/google/protobuf/AbstractMessage$Builder;
      10: checkcast     #130                // class org/apache/hadoop/hbase/shaded/protobuf/generated/HBaseProtos$TableName$Builder
      13: areturn

  public org.apache.hadoop.hbase.shaded.protobuf.generated.HBaseProtos$TableName$Builder addTableListBuilder(int);
    Code:
       0: aload_0
       1: invokespecial #20                 // Method getTableListFieldBuilder:()Lorg/apache/hbase/thirdparty/com/google/protobuf/RepeatedFieldBuilderV3;
       4: iload_1
       5: invokestatic  #134                // Method org/apache/hadoop/hbase/shaded/protobuf/generated/HBaseProtos$TableName.getDefaultInstance:()Lorg/apache/hadoop/hbase/shaded/protobuf/generated/HBaseProtos$TableName;
       8: invokevirtual #136                // Method org/apache/hbase/thirdparty/com/google/protobuf/RepeatedFieldBuilderV3.addBuilder:(ILorg/apache/hbase/thirdparty/com/google/protobuf/AbstractMessage;)Lorg/apache/hbase/thirdparty/com/google/protobuf/AbstractMessage$Builder;
      11: checkcast     #130                // class org/apache/hadoop/hbase/shaded/protobuf/generated/HBaseProtos$TableName$Builder
      14: areturn

  public java.util.List<org.apache.hadoop.hbase.shaded.protobuf.generated.HBaseProtos$TableName$Builder> getTableListBuilderList();
    Code:
       0: aload_0
       1: invokespecial #20                 // Method getTableListFieldBuilder:()Lorg/apache/hbase/thirdparty/com/google/protobuf/RepeatedFieldBuilderV3;
       4: invokevirtual #137                // Method org/apache/hbase/thirdparty/com/google/protobuf/RepeatedFieldBuilderV3.getBuilderList:()Ljava/util/List;
       7: areturn

  public boolean hasStartTs();
    Code:
       0: aload_0
       1: getfield      #24                 // Field bitField0_:I
       4: bipush        16
       6: iand
       7: bipush        16
       9: if_icmpne     16
      12: iconst_1
      13: goto          17
      16: iconst_0
      17: ireturn

  public long getStartTs();
    Code:
       0: aload_0
       1: getfield      #27                 // Field startTs_:J
       4: lreturn

  public org.apache.hadoop.hbase.shaded.protobuf.generated.BackupProtos$BackupImage$Builder setStartTs(long);
    Code:
       0: aload_0
       1: dup
       2: getfield      #24                 // Field bitField0_:I
       5: bipush        16
       7: ior
       8: putfield      #24                 // Field bitField0_:I
      11: aload_0
      12: lload_1
      13: putfield      #27                 // Field startTs_:J
      16: aload_0
      17: invokevirtual #58                 // Method onChanged:()V
      20: aload_0
      21: areturn

  public org.apache.hadoop.hbase.shaded.protobuf.generated.BackupProtos$BackupImage$Builder clearStartTs();
    Code:
       0: aload_0
       1: aload_0
       2: getfield      #24                 // Field bitField0_:I
       5: bipush        -17
       7: iand
       8: putfield      #24                 // Field bitField0_:I
      11: aload_0
      12: lconst_0
      13: putfield      #27                 // Field startTs_:J
      16: aload_0
      17: invokevirtual #58                 // Method onChanged:()V
      20: aload_0
      21: areturn

  public boolean hasCompleteTs();
    Code:
       0: aload_0
       1: getfield      #24                 // Field bitField0_:I
       4: bipush        32
       6: iand
       7: bipush        32
       9: if_icmpne     16
      12: iconst_1
      13: goto          17
      16: iconst_0
      17: ireturn

  public long getCompleteTs();
    Code:
       0: aload_0
       1: getfield      #28                 // Field completeTs_:J
       4: lreturn

  public org.apache.hadoop.hbase.shaded.protobuf.generated.BackupProtos$BackupImage$Builder setCompleteTs(long);
    Code:
       0: aload_0
       1: dup
       2: getfield      #24                 // Field bitField0_:I
       5: bipush        32
       7: ior
       8: putfield      #24                 // Field bitField0_:I
      11: aload_0
      12: lload_1
      13: putfield      #28                 // Field completeTs_:J
      16: aload_0
      17: invokevirtual #58                 // Method onChanged:()V
      20: aload_0
      21: areturn

  public org.apache.hadoop.hbase.shaded.protobuf.generated.BackupProtos$BackupImage$Builder clearCompleteTs();
    Code:
       0: aload_0
       1: aload_0
       2: getfield      #24                 // Field bitField0_:I
       5: bipush        -33
       7: iand
       8: putfield      #24                 // Field bitField0_:I
      11: aload_0
      12: lconst_0
      13: putfield      #28                 // Field completeTs_:J
      16: aload_0
      17: invokevirtual #58                 // Method onChanged:()V
      20: aload_0
      21: areturn

  public java.util.List<org.apache.hadoop.hbase.shaded.protobuf.generated.BackupProtos$BackupImage> getAncestorsList();
    Code:
       0: aload_0
       1: getfield      #29                 // Field ancestorsBuilder_:Lorg/apache/hbase/thirdparty/com/google/protobuf/RepeatedFieldBuilderV3;
       4: ifnonnull     15
       7: aload_0
       8: getfield      #15                 // Field ancestors_:Ljava/util/List;
      11: invokestatic  #39                 // Method java/util/Collections.unmodifiableList:(Ljava/util/List;)Ljava/util/List;
      14: areturn
      15: aload_0
      16: getfield      #29                 // Field ancestorsBuilder_:Lorg/apache/hbase/thirdparty/com/google/protobuf/RepeatedFieldBuilderV3;
      19: invokevirtual #113                // Method org/apache/hbase/thirdparty/com/google/protobuf/RepeatedFieldBuilderV3.getMessageList:()Ljava/util/List;
      22: areturn

  public int getAncestorsCount();
    Code:
       0: aload_0
       1: getfield      #29                 // Field ancestorsBuilder_:Lorg/apache/hbase/thirdparty/com/google/protobuf/RepeatedFieldBuilderV3;
       4: ifnonnull     17
       7: aload_0
       8: getfield      #15                 // Field ancestors_:Ljava/util/List;
      11: invokeinterface #114,  1          // InterfaceMethod java/util/List.size:()I
      16: ireturn
      17: aload_0
      18: getfield      #29                 // Field ancestorsBuilder_:Lorg/apache/hbase/thirdparty/com/google/protobuf/RepeatedFieldBuilderV3;
      21: invokevirtual #115                // Method org/apache/hbase/thirdparty/com/google/protobuf/RepeatedFieldBuilderV3.getCount:()I
      24: ireturn

  public org.apache.hadoop.hbase.shaded.protobuf.generated.BackupProtos$BackupImage getAncestors(int);
    Code:
       0: aload_0
       1: getfield      #29                 // Field ancestorsBuilder_:Lorg/apache/hbase/thirdparty/com/google/protobuf/RepeatedFieldBuilderV3;
       4: ifnonnull     21
       7: aload_0
       8: getfield      #15                 // Field ancestors_:Ljava/util/List;
      11: iload_1
      12: invokeinterface #116,  2          // InterfaceMethod java/util/List.get:(I)Ljava/lang/Object;
      17: checkcast     #5                  // class org/apache/hadoop/hbase/shaded/protobuf/generated/BackupProtos$BackupImage
      20: areturn
      21: aload_0
      22: getfield      #29                 // Field ancestorsBuilder_:Lorg/apache/hbase/thirdparty/com/google/protobuf/RepeatedFieldBuilderV3;
      25: iload_1
      26: invokevirtual #118                // Method org/apache/hbase/thirdparty/com/google/protobuf/RepeatedFieldBuilderV3.getMessage:(I)Lorg/apache/hbase/thirdparty/com/google/protobuf/AbstractMessage;
      29: checkcast     #5                  // class org/apache/hadoop/hbase/shaded/protobuf/generated/BackupProtos$BackupImage
      32: areturn

  public org.apache.hadoop.hbase.shaded.protobuf.generated.BackupProtos$BackupImage$Builder setAncestors(int, org.apache.hadoop.hbase.shaded.protobuf.generated.BackupProtos$BackupImage);
    Code:
       0: aload_0
       1: getfield      #29                 // Field ancestorsBuilder_:Lorg/apache/hbase/thirdparty/com/google/protobuf/RepeatedFieldBuilderV3;
       4: ifnonnull     42
       7: aload_2
       8: ifnonnull     19
      11: new           #104                // class java/lang/NullPointerException
      14: dup
      15: invokespecial #105                // Method java/lang/NullPointerException."<init>":()V
      18: athrow
      19: aload_0
      20: invokespecial #79                 // Method ensureAncestorsIsMutable:()V
      23: aload_0
      24: getfield      #15                 // Field ancestors_:Ljava/util/List;
      27: iload_1
      28: aload_2
      29: invokeinterface #119,  3          // InterfaceMethod java/util/List.set:(ILjava/lang/Object;)Ljava/lang/Object;
      34: pop
      35: aload_0
      36: invokevirtual #58                 // Method onChanged:()V
      39: goto          52
      42: aload_0
      43: getfield      #29                 // Field ancestorsBuilder_:Lorg/apache/hbase/thirdparty/com/google/protobuf/RepeatedFieldBuilderV3;
      46: iload_1
      47: aload_2
      48: invokevirtual #120                // Method org/apache/hbase/thirdparty/com/google/protobuf/RepeatedFieldBuilderV3.setMessage:(ILorg/apache/hbase/thirdparty/com/google/protobuf/AbstractMessage;)Lorg/apache/hbase/thirdparty/com/google/protobuf/RepeatedFieldBuilderV3;
      51: pop
      52: aload_0
      53: areturn

  public org.apache.hadoop.hbase.shaded.protobuf.generated.BackupProtos$BackupImage$Builder setAncestors(int, org.apache.hadoop.hbase.shaded.protobuf.generated.BackupProtos$BackupImage$Builder);
    Code:
       0: aload_0
       1: getfield      #29                 // Field ancestorsBuilder_:Lorg/apache/hbase/thirdparty/com/google/protobuf/RepeatedFieldBuilderV3;
       4: ifnonnull     33
       7: aload_0
       8: invokespecial #79                 // Method ensureAncestorsIsMutable:()V
      11: aload_0
      12: getfield      #15                 // Field ancestors_:Ljava/util/List;
      15: iload_1
      16: aload_2
      17: invokevirtual #142                // Method build:()Lorg/apache/hadoop/hbase/shaded/protobuf/generated/BackupProtos$BackupImage;
      20: invokeinterface #119,  3          // InterfaceMethod java/util/List.set:(ILjava/lang/Object;)Ljava/lang/Object;
      25: pop
      26: aload_0
      27: invokevirtual #58                 // Method onChanged:()V
      30: goto          46
      33: aload_0
      34: getfield      #29                 // Field ancestorsBuilder_:Lorg/apache/hbase/thirdparty/com/google/protobuf/RepeatedFieldBuilderV3;
      37: iload_1
      38: aload_2
      39: invokevirtual #142                // Method build:()Lorg/apache/hadoop/hbase/shaded/protobuf/generated/BackupProtos$BackupImage;
      42: invokevirtual #120                // Method org/apache/hbase/thirdparty/com/google/protobuf/RepeatedFieldBuilderV3.setMessage:(ILorg/apache/hbase/thirdparty/com/google/protobuf/AbstractMessage;)Lorg/apache/hbase/thirdparty/com/google/protobuf/RepeatedFieldBuilderV3;
      45: pop
      46: aload_0
      47: areturn

  public org.apache.hadoop.hbase.shaded.protobuf.generated.BackupProtos$BackupImage$Builder addAncestors(org.apache.hadoop.hbase.shaded.protobuf.generated.BackupProtos$BackupImage);
    Code:
       0: aload_0
       1: getfield      #29                 // Field ancestorsBuilder_:Lorg/apache/hbase/thirdparty/com/google/protobuf/RepeatedFieldBuilderV3;
       4: ifnonnull     41
       7: aload_1
       8: ifnonnull     19
      11: new           #104                // class java/lang/NullPointerException
      14: dup
      15: invokespecial #105                // Method java/lang/NullPointerException."<init>":()V
      18: athrow
      19: aload_0
      20: invokespecial #79                 // Method ensureAncestorsIsMutable:()V
      23: aload_0
      24: getfield      #15                 // Field ancestors_:Ljava/util/List;
      27: aload_1
      28: invokeinterface #122,  2          // InterfaceMethod java/util/List.add:(Ljava/lang/Object;)Z
      33: pop
      34: aload_0
      35: invokevirtual #58                 // Method onChanged:()V
      38: goto          50
      41: aload_0
      42: getfield      #29                 // Field ancestorsBuilder_:Lorg/apache/hbase/thirdparty/com/google/protobuf/RepeatedFieldBuilderV3;
      45: aload_1
      46: invokevirtual #123                // Method org/apache/hbase/thirdparty/com/google/protobuf/RepeatedFieldBuilderV3.addMessage:(Lorg/apache/hbase/thirdparty/com/google/protobuf/AbstractMessage;)Lorg/apache/hbase/thirdparty/com/google/protobuf/RepeatedFieldBuilderV3;
      49: pop
      50: aload_0
      51: areturn

  public org.apache.hadoop.hbase.shaded.protobuf.generated.BackupProtos$BackupImage$Builder addAncestors(int, org.apache.hadoop.hbase.shaded.protobuf.generated.BackupProtos$BackupImage);
    Code:
       0: aload_0
       1: getfield      #29                 // Field ancestorsBuilder_:Lorg/apache/hbase/thirdparty/com/google/protobuf/RepeatedFieldBuilderV3;
       4: ifnonnull     41
       7: aload_2
       8: ifnonnull     19
      11: new           #104                // class java/lang/NullPointerException
      14: dup
      15: invokespecial #105                // Method java/lang/NullPointerException."<init>":()V
      18: athrow
      19: aload_0
      20: invokespecial #79                 // Method ensureAncestorsIsMutable:()V
      23: aload_0
      24: getfield      #15                 // Field ancestors_:Ljava/util/List;
      27: iload_1
      28: aload_2
      29: invokeinterface #124,  3          // InterfaceMethod java/util/List.add:(ILjava/lang/Object;)V
      34: aload_0
      35: invokevirtual #58                 // Method onChanged:()V
      38: goto          51
      41: aload_0
      42: getfield      #29                 // Field ancestorsBuilder_:Lorg/apache/hbase/thirdparty/com/google/protobuf/RepeatedFieldBuilderV3;
      45: iload_1
      46: aload_2
      47: invokevirtual #125                // Method org/apache/hbase/thirdparty/com/google/protobuf/RepeatedFieldBuilderV3.addMessage:(ILorg/apache/hbase/thirdparty/com/google/protobuf/AbstractMessage;)Lorg/apache/hbase/thirdparty/com/google/protobuf/RepeatedFieldBuilderV3;
      50: pop
      51: aload_0
      52: areturn

  public org.apache.hadoop.hbase.shaded.protobuf.generated.BackupProtos$BackupImage$Builder addAncestors(org.apache.hadoop.hbase.shaded.protobuf.generated.BackupProtos$BackupImage$Builder);
    Code:
       0: aload_0
       1: getfield      #29                 // Field ancestorsBuilder_:Lorg/apache/hbase/thirdparty/com/google/protobuf/RepeatedFieldBuilderV3;
       4: ifnonnull     32
       7: aload_0
       8: invokespecial #79                 // Method ensureAncestorsIsMutable:()V
      11: aload_0
      12: getfield      #15                 // Field ancestors_:Ljava/util/List;
      15: aload_1
      16: invokevirtual #142                // Method build:()Lorg/apache/hadoop/hbase/shaded/protobuf/generated/BackupProtos$BackupImage;
      19: invokeinterface #122,  2          // InterfaceMethod java/util/List.add:(Ljava/lang/Object;)Z
      24: pop
      25: aload_0
      26: invokevirtual #58                 // Method onChanged:()V
      29: goto          44
      32: aload_0
      33: getfield      #29                 // Field ancestorsBuilder_:Lorg/apache/hbase/thirdparty/com/google/protobuf/RepeatedFieldBuilderV3;
      36: aload_1
      37: invokevirtual #142                // Method build:()Lorg/apache/hadoop/hbase/shaded/protobuf/generated/BackupProtos$BackupImage;
      40: invokevirtual #123                // Method org/apache/hbase/thirdparty/com/google/protobuf/RepeatedFieldBuilderV3.addMessage:(Lorg/apache/hbase/thirdparty/com/google/protobuf/AbstractMessage;)Lorg/apache/hbase/thirdparty/com/google/protobuf/RepeatedFieldBuilderV3;
      43: pop
      44: aload_0
      45: areturn

  public org.apache.hadoop.hbase.shaded.protobuf.generated.BackupProtos$BackupImage$Builder addAncestors(int, org.apache.hadoop.hbase.shaded.protobuf.generated.BackupProtos$BackupImage$Builder);
    Code:
       0: aload_0
       1: getfield      #29                 // Field ancestorsBuilder_:Lorg/apache/hbase/thirdparty/com/google/protobuf/RepeatedFieldBuilderV3;
       4: ifnonnull     32
       7: aload_0
       8: invokespecial #79                 // Method ensureAncestorsIsMutable:()V
      11: aload_0
      12: getfield      #15                 // Field ancestors_:Ljava/util/List;
      15: iload_1
      16: aload_2
      17: invokevirtual #142                // Method build:()Lorg/apache/hadoop/hbase/shaded/protobuf/generated/BackupProtos$BackupImage;
      20: invokeinterface #124,  3          // InterfaceMethod java/util/List.add:(ILjava/lang/Object;)V
      25: aload_0
      26: invokevirtual #58                 // Method onChanged:()V
      29: goto          45
      32: aload_0
      33: getfield      #29                 // Field ancestorsBuilder_:Lorg/apache/hbase/thirdparty/com/google/protobuf/RepeatedFieldBuilderV3;
      36: iload_1
      37: aload_2
      38: invokevirtual #142                // Method build:()Lorg/apache/hadoop/hbase/shaded/protobuf/generated/BackupProtos$BackupImage;
      41: invokevirtual #125                // Method org/apache/hbase/thirdparty/com/google/protobuf/RepeatedFieldBuilderV3.addMessage:(ILorg/apache/hbase/thirdparty/com/google/protobuf/AbstractMessage;)Lorg/apache/hbase/thirdparty/com/google/protobuf/RepeatedFieldBuilderV3;
      44: pop
      45: aload_0
      46: areturn

  public org.apache.hadoop.hbase.shaded.protobuf.generated.BackupProtos$BackupImage$Builder addAllAncestors(java.lang.Iterable<? extends org.apache.hadoop.hbase.shaded.protobuf.generated.BackupProtos$BackupImage>);
    Code:
       0: aload_0
       1: getfield      #29                 // Field ancestorsBuilder_:Lorg/apache/hbase/thirdparty/com/google/protobuf/RepeatedFieldBuilderV3;
       4: ifnonnull     26
       7: aload_0
       8: invokespecial #79                 // Method ensureAncestorsIsMutable:()V
      11: aload_1
      12: aload_0
      13: getfield      #15                 // Field ancestors_:Ljava/util/List;
      16: invokestatic  #126                // Method org/apache/hbase/thirdparty/com/google/protobuf/AbstractMessageLite$Builder.addAll:(Ljava/lang/Iterable;Ljava/util/List;)V
      19: aload_0
      20: invokevirtual #58                 // Method onChanged:()V
      23: goto          35
      26: aload_0
      27: getfield      #29                 // Field ancestorsBuilder_:Lorg/apache/hbase/thirdparty/com/google/protobuf/RepeatedFieldBuilderV3;
      30: aload_1
      31: invokevirtual #71                 // Method org/apache/hbase/thirdparty/com/google/protobuf/RepeatedFieldBuilderV3.addAllMessages:(Ljava/lang/Iterable;)Lorg/apache/hbase/thirdparty/com/google/protobuf/RepeatedFieldBuilderV3;
      34: pop
      35: aload_0
      36: areturn

  public org.apache.hadoop.hbase.shaded.protobuf.generated.BackupProtos$BackupImage$Builder clearAncestors();
    Code:
       0: aload_0
       1: getfield      #29                 // Field ancestorsBuilder_:Lorg/apache/hbase/thirdparty/com/google/protobuf/RepeatedFieldBuilderV3;
       4: ifnonnull     32
       7: aload_0
       8: invokestatic  #13                 // Method java/util/Collections.emptyList:()Ljava/util/List;
      11: putfield      #15                 // Field ancestors_:Ljava/util/List;
      14: aload_0
      15: aload_0
      16: getfield      #24                 // Field bitField0_:I
      19: bipush        -65
      21: iand
      22: putfield      #24                 // Field bitField0_:I
      25: aload_0
      26: invokevirtual #58                 // Method onChanged:()V
      29: goto          39
      32: aload_0
      33: getfield      #29                 // Field ancestorsBuilder_:Lorg/apache/hbase/thirdparty/com/google/protobuf/RepeatedFieldBuilderV3;
      36: invokevirtual #26                 // Method org/apache/hbase/thirdparty/com/google/protobuf/RepeatedFieldBuilderV3.clear:()V
      39: aload_0
      40: areturn

  public org.apache.hadoop.hbase.shaded.protobuf.generated.BackupProtos$BackupImage$Builder removeAncestors(int);
    Code:
       0: aload_0
       1: getfield      #29                 // Field ancestorsBuilder_:Lorg/apache/hbase/thirdparty/com/google/protobuf/RepeatedFieldBuilderV3;
       4: ifnonnull     29
       7: aload_0
       8: invokespecial #79                 // Method ensureAncestorsIsMutable:()V
      11: aload_0
      12: getfield      #15                 // Field ancestors_:Ljava/util/List;
      15: iload_1
      16: invokeinterface #127,  2          // InterfaceMethod java/util/List.remove:(I)Ljava/lang/Object;
      21: pop
      22: aload_0
      23: invokevirtual #58                 // Method onChanged:()V
      26: goto          37
      29: aload_0
      30: getfield      #29                 // Field ancestorsBuilder_:Lorg/apache/hbase/thirdparty/com/google/protobuf/RepeatedFieldBuilderV3;
      33: iload_1
      34: invokevirtual #128                // Method org/apache/hbase/thirdparty/com/google/protobuf/RepeatedFieldBuilderV3.remove:(I)V
      37: aload_0
      38: areturn

  public org.apache.hadoop.hbase.shaded.protobuf.generated.BackupProtos$BackupImage$Builder getAncestorsBuilder(int);
    Code:
       0: aload_0
       1: invokespecial #21                 // Method getAncestorsFieldBuilder:()Lorg/apache/hbase/thirdparty/com/google/protobuf/RepeatedFieldBuilderV3;
       4: iload_1
       5: invokevirtual #129                // Method org/apache/hbase/thirdparty/com/google/protobuf/RepeatedFieldBuilderV3.getBuilder:(I)Lorg/apache/hbase/thirdparty/com/google/protobuf/AbstractMessage$Builder;
       8: checkcast     #6                  // class org/apache/hadoop/hbase/shaded/protobuf/generated/BackupProtos$BackupImage$Builder
      11: areturn

  public org.apache.hadoop.hbase.shaded.protobuf.generated.BackupProtos$BackupImageOrBuilder getAncestorsOrBuilder(int);
    Code:
       0: aload_0
       1: getfield      #29                 // Field ancestorsBuilder_:Lorg/apache/hbase/thirdparty/com/google/protobuf/RepeatedFieldBuilderV3;
       4: ifnonnull     21
       7: aload_0
       8: getfield      #15                 // Field ancestors_:Ljava/util/List;
      11: iload_1
      12: invokeinterface #116,  2          // InterfaceMethod java/util/List.get:(I)Ljava/lang/Object;
      17: checkcast     #143                // class org/apache/hadoop/hbase/shaded/protobuf/generated/BackupProtos$BackupImageOrBuilder
      20: areturn
      21: aload_0
      22: getfield      #29                 // Field ancestorsBuilder_:Lorg/apache/hbase/thirdparty/com/google/protobuf/RepeatedFieldBuilderV3;
      25: iload_1
      26: invokevirtual #132                // Method org/apache/hbase/thirdparty/com/google/protobuf/RepeatedFieldBuilderV3.getMessageOrBuilder:(I)Lorg/apache/hbase/thirdparty/com/google/protobuf/MessageOrBuilder;
      29: checkcast     #143                // class org/apache/hadoop/hbase/shaded/protobuf/generated/BackupProtos$BackupImageOrBuilder
      32: areturn

  public java.util.List<? extends org.apache.hadoop.hbase.shaded.protobuf.generated.BackupProtos$BackupImageOrBuilder> getAncestorsOrBuilderList();
    Code:
       0: aload_0
       1: getfield      #29                 // Field ancestorsBuilder_:Lorg/apache/hbase/thirdparty/com/google/protobuf/RepeatedFieldBuilderV3;
       4: ifnull        15
       7: aload_0
       8: getfield      #29                 // Field ancestorsBuilder_:Lorg/apache/hbase/thirdparty/com/google/protobuf/RepeatedFieldBuilderV3;
      11: invokevirtual #133                // Method org/apache/hbase/thirdparty/com/google/protobuf/RepeatedFieldBuilderV3.getMessageOrBuilderList:()Ljava/util/List;
      14: areturn
      15: aload_0
      16: getfield      #15                 // Field ancestors_:Ljava/util/List;
      19: invokestatic  #39                 // Method java/util/Collections.unmodifiableList:(Ljava/util/List;)Ljava/util/List;
      22: areturn

  public org.apache.hadoop.hbase.shaded.protobuf.generated.BackupProtos$BackupImage$Builder addAncestorsBuilder();
    Code:
       0: aload_0
       1: invokespecial #21                 // Method getAncestorsFieldBuilder:()Lorg/apache/hbase/thirdparty/com/google/protobuf/RepeatedFieldBuilderV3;
       4: invokestatic  #31                 // Method org/apache/hadoop/hbase/shaded/protobuf/generated/BackupProtos$BackupImage.getDefaultInstance:()Lorg/apache/hadoop/hbase/shaded/protobuf/generated/BackupProtos$BackupImage;
       7: invokevirtual #135                // Method org/apache/hbase/thirdparty/com/google/protobuf/RepeatedFieldBuilderV3.addBuilder:(Lorg/apache/hbase/thirdparty/com/google/protobuf/AbstractMessage;)Lorg/apache/hbase/thirdparty/com/google/protobuf/AbstractMessage$Builder;
      10: checkcast     #6                  // class org/apache/hadoop/hbase/shaded/protobuf/generated/BackupProtos$BackupImage$Builder
      13: areturn

  public org.apache.hadoop.hbase.shaded.protobuf.generated.BackupProtos$BackupImage$Builder addAncestorsBuilder(int);
    Code:
       0: aload_0
       1: invokespecial #21                 // Method getAncestorsFieldBuilder:()Lorg/apache/hbase/thirdparty/com/google/protobuf/RepeatedFieldBuilderV3;
       4: iload_1
       5: invokestatic  #31                 // Method org/apache/hadoop/hbase/shaded/protobuf/generated/BackupProtos$BackupImage.getDefaultInstance:()Lorg/apache/hadoop/hbase/shaded/protobuf/generated/BackupProtos$BackupImage;
       8: invokevirtual #136                // Method org/apache/hbase/thirdparty/com/google/protobuf/RepeatedFieldBuilderV3.addBuilder:(ILorg/apache/hbase/thirdparty/com/google/protobuf/AbstractMessage;)Lorg/apache/hbase/thirdparty/com/google/protobuf/AbstractMessage$Builder;
      11: checkcast     #6                  // class org/apache/hadoop/hbase/shaded/protobuf/generated/BackupProtos$BackupImage$Builder
      14: areturn

  public java.util.List<org.apache.hadoop.hbase.shaded.protobuf.generated.BackupProtos$BackupImage$Builder> getAncestorsBuilderList();
    Code:
       0: aload_0
       1: invokespecial #21                 // Method getAncestorsFieldBuilder:()Lorg/apache/hbase/thirdparty/com/google/protobuf/RepeatedFieldBuilderV3;
       4: invokevirtual #137                // Method org/apache/hbase/thirdparty/com/google/protobuf/RepeatedFieldBuilderV3.getBuilderList:()Ljava/util/List;
       7: areturn

  public java.util.List<org.apache.hadoop.hbase.shaded.protobuf.generated.BackupProtos$TableServerTimestamp> getTstMapList();
    Code:
       0: aload_0
       1: getfield      #30                 // Field tstMapBuilder_:Lorg/apache/hbase/thirdparty/com/google/protobuf/RepeatedFieldBuilderV3;
       4: ifnonnull     15
       7: aload_0
       8: getfield      #16                 // Field tstMap_:Ljava/util/List;
      11: invokestatic  #39                 // Method java/util/Collections.unmodifiableList:(Ljava/util/List;)Ljava/util/List;
      14: areturn
      15: aload_0
      16: getfield      #30                 // Field tstMapBuilder_:Lorg/apache/hbase/thirdparty/com/google/protobuf/RepeatedFieldBuilderV3;
      19: invokevirtual #113                // Method org/apache/hbase/thirdparty/com/google/protobuf/RepeatedFieldBuilderV3.getMessageList:()Ljava/util/List;
      22: areturn

  public int getTstMapCount();
    Code:
       0: aload_0
       1: getfield      #30                 // Field tstMapBuilder_:Lorg/apache/hbase/thirdparty/com/google/protobuf/RepeatedFieldBuilderV3;
       4: ifnonnull     17
       7: aload_0
       8: getfield      #16                 // Field tstMap_:Ljava/util/List;
      11: invokeinterface #114,  1          // InterfaceMethod java/util/List.size:()I
      16: ireturn
      17: aload_0
      18: getfield      #30                 // Field tstMapBuilder_:Lorg/apache/hbase/thirdparty/com/google/protobuf/RepeatedFieldBuilderV3;
      21: invokevirtual #115                // Method org/apache/hbase/thirdparty/com/google/protobuf/RepeatedFieldBuilderV3.getCount:()I
      24: ireturn

  public org.apache.hadoop.hbase.shaded.protobuf.generated.BackupProtos$TableServerTimestamp getTstMap(int);
    Code:
       0: aload_0
       1: getfield      #30                 // Field tstMapBuilder_:Lorg/apache/hbase/thirdparty/com/google/protobuf/RepeatedFieldBuilderV3;
       4: ifnonnull     21
       7: aload_0
       8: getfield      #16                 // Field tstMap_:Ljava/util/List;
      11: iload_1
      12: invokeinterface #116,  2          // InterfaceMethod java/util/List.get:(I)Ljava/lang/Object;
      17: checkcast     #144                // class org/apache/hadoop/hbase/shaded/protobuf/generated/BackupProtos$TableServerTimestamp
      20: areturn
      21: aload_0
      22: getfield      #30                 // Field tstMapBuilder_:Lorg/apache/hbase/thirdparty/com/google/protobuf/RepeatedFieldBuilderV3;
      25: iload_1
      26: invokevirtual #118                // Method org/apache/hbase/thirdparty/com/google/protobuf/RepeatedFieldBuilderV3.getMessage:(I)Lorg/apache/hbase/thirdparty/com/google/protobuf/AbstractMessage;
      29: checkcast     #144                // class org/apache/hadoop/hbase/shaded/protobuf/generated/BackupProtos$TableServerTimestamp
      32: areturn

  public org.apache.hadoop.hbase.shaded.protobuf.generated.BackupProtos$BackupImage$Builder setTstMap(int, org.apache.hadoop.hbase.shaded.protobuf.generated.BackupProtos$TableServerTimestamp);
    Code:
       0: aload_0
       1: getfield      #30                 // Field tstMapBuilder_:Lorg/apache/hbase/thirdparty/com/google/protobuf/RepeatedFieldBuilderV3;
       4: ifnonnull     42
       7: aload_2
       8: ifnonnull     19
      11: new           #104                // class java/lang/NullPointerException
      14: dup
      15: invokespecial #105                // Method java/lang/NullPointerException."<init>":()V
      18: athrow
      19: aload_0
      20: invokespecial #82                 // Method ensureTstMapIsMutable:()V
      23: aload_0
      24: getfield      #16                 // Field tstMap_:Ljava/util/List;
      27: iload_1
      28: aload_2
      29: invokeinterface #119,  3          // InterfaceMethod java/util/List.set:(ILjava/lang/Object;)Ljava/lang/Object;
      34: pop
      35: aload_0
      36: invokevirtual #58                 // Method onChanged:()V
      39: goto          52
      42: aload_0
      43: getfield      #30                 // Field tstMapBuilder_:Lorg/apache/hbase/thirdparty/com/google/protobuf/RepeatedFieldBuilderV3;
      46: iload_1
      47: aload_2
      48: invokevirtual #120                // Method org/apache/hbase/thirdparty/com/google/protobuf/RepeatedFieldBuilderV3.setMessage:(ILorg/apache/hbase/thirdparty/com/google/protobuf/AbstractMessage;)Lorg/apache/hbase/thirdparty/com/google/protobuf/RepeatedFieldBuilderV3;
      51: pop
      52: aload_0
      53: areturn

  public org.apache.hadoop.hbase.shaded.protobuf.generated.BackupProtos$BackupImage$Builder setTstMap(int, org.apache.hadoop.hbase.shaded.protobuf.generated.BackupProtos$TableServerTimestamp$Builder);
    Code:
       0: aload_0
       1: getfield      #30                 // Field tstMapBuilder_:Lorg/apache/hbase/thirdparty/com/google/protobuf/RepeatedFieldBuilderV3;
       4: ifnonnull     33
       7: aload_0
       8: invokespecial #82                 // Method ensureTstMapIsMutable:()V
      11: aload_0
      12: getfield      #16                 // Field tstMap_:Ljava/util/List;
      15: iload_1
      16: aload_2
      17: invokevirtual #145                // Method org/apache/hadoop/hbase/shaded/protobuf/generated/BackupProtos$TableServerTimestamp$Builder.build:()Lorg/apache/hadoop/hbase/shaded/protobuf/generated/BackupProtos$TableServerTimestamp;
      20: invokeinterface #119,  3          // InterfaceMethod java/util/List.set:(ILjava/lang/Object;)Ljava/lang/Object;
      25: pop
      26: aload_0
      27: invokevirtual #58                 // Method onChanged:()V
      30: goto          46
      33: aload_0
      34: getfield      #30                 // Field tstMapBuilder_:Lorg/apache/hbase/thirdparty/com/google/protobuf/RepeatedFieldBuilderV3;
      37: iload_1
      38: aload_2
      39: invokevirtual #145                // Method org/apache/hadoop/hbase/shaded/protobuf/generated/BackupProtos$TableServerTimestamp$Builder.build:()Lorg/apache/hadoop/hbase/shaded/protobuf/generated/BackupProtos$TableServerTimestamp;
      42: invokevirtual #120                // Method org/apache/hbase/thirdparty/com/google/protobuf/RepeatedFieldBuilderV3.setMessage:(ILorg/apache/hbase/thirdparty/com/google/protobuf/AbstractMessage;)Lorg/apache/hbase/thirdparty/com/google/protobuf/RepeatedFieldBuilderV3;
      45: pop
      46: aload_0
      47: areturn

  public org.apache.hadoop.hbase.shaded.protobuf.generated.BackupProtos$BackupImage$Builder addTstMap(org.apache.hadoop.hbase.shaded.protobuf.generated.BackupProtos$TableServerTimestamp);
    Code:
       0: aload_0
       1: getfield      #30                 // Field tstMapBuilder_:Lorg/apache/hbase/thirdparty/com/google/protobuf/RepeatedFieldBuilderV3;
       4: ifnonnull     41
       7: aload_1
       8: ifnonnull     19
      11: new           #104                // class java/lang/NullPointerException
      14: dup
      15: invokespecial #105                // Method java/lang/NullPointerException."<init>":()V
      18: athrow
      19: aload_0
      20: invokespecial #82                 // Method ensureTstMapIsMutable:()V
      23: aload_0
      24: getfield      #16                 // Field tstMap_:Ljava/util/List;
      27: aload_1
      28: invokeinterface #122,  2          // InterfaceMethod java/util/List.add:(Ljava/lang/Object;)Z
      33: pop
      34: aload_0
      35: invokevirtual #58                 // Method onChanged:()V
      38: goto          50
      41: aload_0
      42: getfield      #30                 // Field tstMapBuilder_:Lorg/apache/hbase/thirdparty/com/google/protobuf/RepeatedFieldBuilderV3;
      45: aload_1
      46: invokevirtual #123                // Method org/apache/hbase/thirdparty/com/google/protobuf/RepeatedFieldBuilderV3.addMessage:(Lorg/apache/hbase/thirdparty/com/google/protobuf/AbstractMessage;)Lorg/apache/hbase/thirdparty/com/google/protobuf/RepeatedFieldBuilderV3;
      49: pop
      50: aload_0
      51: areturn

  public org.apache.hadoop.hbase.shaded.protobuf.generated.BackupProtos$BackupImage$Builder addTstMap(int, org.apache.hadoop.hbase.shaded.protobuf.generated.BackupProtos$TableServerTimestamp);
    Code:
       0: aload_0
       1: getfield      #30                 // Field tstMapBuilder_:Lorg/apache/hbase/thirdparty/com/google/protobuf/RepeatedFieldBuilderV3;
       4: ifnonnull     41
       7: aload_2
       8: ifnonnull     19
      11: new           #104                // class java/lang/NullPointerException
      14: dup
      15: invokespecial #105                // Method java/lang/NullPointerException."<init>":()V
      18: athrow
      19: aload_0
      20: invokespecial #82                 // Method ensureTstMapIsMutable:()V
      23: aload_0
      24: getfield      #16                 // Field tstMap_:Ljava/util/List;
      27: iload_1
      28: aload_2
      29: invokeinterface #124,  3          // InterfaceMethod java/util/List.add:(ILjava/lang/Object;)V
      34: aload_0
      35: invokevirtual #58                 // Method onChanged:()V
      38: goto          51
      41: aload_0
      42: getfield      #30                 // Field tstMapBuilder_:Lorg/apache/hbase/thirdparty/com/google/protobuf/RepeatedFieldBuilderV3;
      45: iload_1
      46: aload_2
      47: invokevirtual #125                // Method org/apache/hbase/thirdparty/com/google/protobuf/RepeatedFieldBuilderV3.addMessage:(ILorg/apache/hbase/thirdparty/com/google/protobuf/AbstractMessage;)Lorg/apache/hbase/thirdparty/com/google/protobuf/RepeatedFieldBuilderV3;
      50: pop
      51: aload_0
      52: areturn

  public org.apache.hadoop.hbase.shaded.protobuf.generated.BackupProtos$BackupImage$Builder addTstMap(org.apache.hadoop.hbase.shaded.protobuf.generated.BackupProtos$TableServerTimestamp$Builder);
    Code:
       0: aload_0
       1: getfield      #30                 // Field tstMapBuilder_:Lorg/apache/hbase/thirdparty/com/google/protobuf/RepeatedFieldBuilderV3;
       4: ifnonnull     32
       7: aload_0
       8: invokespecial #82                 // Method ensureTstMapIsMutable:()V
      11: aload_0
      12: getfield      #16                 // Field tstMap_:Ljava/util/List;
      15: aload_1
      16: invokevirtual #145                // Method org/apache/hadoop/hbase/shaded/protobuf/generated/BackupProtos$TableServerTimestamp$Builder.build:()Lorg/apache/hadoop/hbase/shaded/protobuf/generated/BackupProtos$TableServerTimestamp;
      19: invokeinterface #122,  2          // InterfaceMethod java/util/List.add:(Ljava/lang/Object;)Z
      24: pop
      25: aload_0
      26: invokevirtual #58                 // Method onChanged:()V
      29: goto          44
      32: aload_0
      33: getfield      #30                 // Field tstMapBuilder_:Lorg/apache/hbase/thirdparty/com/google/protobuf/RepeatedFieldBuilderV3;
      36: aload_1
      37: invokevirtual #145                // Method org/apache/hadoop/hbase/shaded/protobuf/generated/BackupProtos$TableServerTimestamp$Builder.build:()Lorg/apache/hadoop/hbase/shaded/protobuf/generated/BackupProtos$TableServerTimestamp;
      40: invokevirtual #123                // Method org/apache/hbase/thirdparty/com/google/protobuf/RepeatedFieldBuilderV3.addMessage:(Lorg/apache/hbase/thirdparty/com/google/protobuf/AbstractMessage;)Lorg/apache/hbase/thirdparty/com/google/protobuf/RepeatedFieldBuilderV3;
      43: pop
      44: aload_0
      45: areturn

  public org.apache.hadoop.hbase.shaded.protobuf.generated.BackupProtos$BackupImage$Builder addTstMap(int, org.apache.hadoop.hbase.shaded.protobuf.generated.BackupProtos$TableServerTimestamp$Builder);
    Code:
       0: aload_0
       1: getfield      #30                 // Field tstMapBuilder_:Lorg/apache/hbase/thirdparty/com/google/protobuf/RepeatedFieldBuilderV3;
       4: ifnonnull     32
       7: aload_0
       8: invokespecial #82                 // Method ensureTstMapIsMutable:()V
      11: aload_0
      12: getfield      #16                 // Field tstMap_:Ljava/util/List;
      15: iload_1
      16: aload_2
      17: invokevirtual #145                // Method org/apache/hadoop/hbase/shaded/protobuf/generated/BackupProtos$TableServerTimestamp$Builder.build:()Lorg/apache/hadoop/hbase/shaded/protobuf/generated/BackupProtos$TableServerTimestamp;
      20: invokeinterface #124,  3          // InterfaceMethod java/util/List.add:(ILjava/lang/Object;)V
      25: aload_0
      26: invokevirtual #58                 // Method onChanged:()V
      29: goto          45
      32: aload_0
      33: getfield      #30                 // Field tstMapBuilder_:Lorg/apache/hbase/thirdparty/com/google/protobuf/RepeatedFieldBuilderV3;
      36: iload_1
      37: aload_2
      38: invokevirtual #145                // Method org/apache/hadoop/hbase/shaded/protobuf/generated/BackupProtos$TableServerTimestamp$Builder.build:()Lorg/apache/hadoop/hbase/shaded/protobuf/generated/BackupProtos$TableServerTimestamp;
      41: invokevirtual #125                // Method org/apache/hbase/thirdparty/com/google/protobuf/RepeatedFieldBuilderV3.addMessage:(ILorg/apache/hbase/thirdparty/com/google/protobuf/AbstractMessage;)Lorg/apache/hbase/thirdparty/com/google/protobuf/RepeatedFieldBuilderV3;
      44: pop
      45: aload_0
      46: areturn

  public org.apache.hadoop.hbase.shaded.protobuf.generated.BackupProtos$BackupImage$Builder addAllTstMap(java.lang.Iterable<? extends org.apache.hadoop.hbase.shaded.protobuf.generated.BackupProtos$TableServerTimestamp>);
    Code:
       0: aload_0
       1: getfield      #30                 // Field tstMapBuilder_:Lorg/apache/hbase/thirdparty/com/google/protobuf/RepeatedFieldBuilderV3;
       4: ifnonnull     26
       7: aload_0
       8: invokespecial #82                 // Method ensureTstMapIsMutable:()V
      11: aload_1
      12: aload_0
      13: getfield      #16                 // Field tstMap_:Ljava/util/List;
      16: invokestatic  #126                // Method org/apache/hbase/thirdparty/com/google/protobuf/AbstractMessageLite$Builder.addAll:(Ljava/lang/Iterable;Ljava/util/List;)V
      19: aload_0
      20: invokevirtual #58                 // Method onChanged:()V
      23: goto          35
      26: aload_0
      27: getfield      #30                 // Field tstMapBuilder_:Lorg/apache/hbase/thirdparty/com/google/protobuf/RepeatedFieldBuilderV3;
      30: aload_1
      31: invokevirtual #71                 // Method org/apache/hbase/thirdparty/com/google/protobuf/RepeatedFieldBuilderV3.addAllMessages:(Ljava/lang/Iterable;)Lorg/apache/hbase/thirdparty/com/google/protobuf/RepeatedFieldBuilderV3;
      34: pop
      35: aload_0
      36: areturn

  public org.apache.hadoop.hbase.shaded.protobuf.generated.BackupProtos$BackupImage$Builder clearTstMap();
    Code:
       0: aload_0
       1: getfield      #30                 // Field tstMapBuilder_:Lorg/apache/hbase/thirdparty/com/google/protobuf/RepeatedFieldBuilderV3;
       4: ifnonnull     33
       7: aload_0
       8: invokestatic  #13                 // Method java/util/Collections.emptyList:()Ljava/util/List;
      11: putfield      #16                 // Field tstMap_:Ljava/util/List;
      14: aload_0
      15: aload_0
      16: getfield      #24                 // Field bitField0_:I
      19: sipush        -129
      22: iand
      23: putfield      #24                 // Field bitField0_:I
      26: aload_0
      27: invokevirtual #58                 // Method onChanged:()V
      30: goto          40
      33: aload_0
      34: getfield      #30                 // Field tstMapBuilder_:Lorg/apache/hbase/thirdparty/com/google/protobuf/RepeatedFieldBuilderV3;
      37: invokevirtual #26                 // Method org/apache/hbase/thirdparty/com/google/protobuf/RepeatedFieldBuilderV3.clear:()V
      40: aload_0
      41: areturn

  public org.apache.hadoop.hbase.shaded.protobuf.generated.BackupProtos$BackupImage$Builder removeTstMap(int);
    Code:
       0: aload_0
       1: getfield      #30                 // Field tstMapBuilder_:Lorg/apache/hbase/thirdparty/com/google/protobuf/RepeatedFieldBuilderV3;
       4: ifnonnull     29
       7: aload_0
       8: invokespecial #82                 // Method ensureTstMapIsMutable:()V
      11: aload_0
      12: getfield      #16                 // Field tstMap_:Ljava/util/List;
      15: iload_1
      16: invokeinterface #127,  2          // InterfaceMethod java/util/List.remove:(I)Ljava/lang/Object;
      21: pop
      22: aload_0
      23: invokevirtual #58                 // Method onChanged:()V
      26: goto          37
      29: aload_0
      30: getfield      #30                 // Field tstMapBuilder_:Lorg/apache/hbase/thirdparty/com/google/protobuf/RepeatedFieldBuilderV3;
      33: iload_1
      34: invokevirtual #128                // Method org/apache/hbase/thirdparty/com/google/protobuf/RepeatedFieldBuilderV3.remove:(I)V
      37: aload_0
      38: areturn

  public org.apache.hadoop.hbase.shaded.protobuf.generated.BackupProtos$TableServerTimestamp$Builder getTstMapBuilder(int);
    Code:
       0: aload_0
       1: invokespecial #22                 // Method getTstMapFieldBuilder:()Lorg/apache/hbase/thirdparty/com/google/protobuf/RepeatedFieldBuilderV3;
       4: iload_1
       5: invokevirtual #129                // Method org/apache/hbase/thirdparty/com/google/protobuf/RepeatedFieldBuilderV3.getBuilder:(I)Lorg/apache/hbase/thirdparty/com/google/protobuf/AbstractMessage$Builder;
       8: checkcast     #146                // class org/apache/hadoop/hbase/shaded/protobuf/generated/BackupProtos$TableServerTimestamp$Builder
      11: areturn

  public org.apache.hadoop.hbase.shaded.protobuf.generated.BackupProtos$TableServerTimestampOrBuilder getTstMapOrBuilder(int);
    Code:
       0: aload_0
       1: getfield      #30                 // Field tstMapBuilder_:Lorg/apache/hbase/thirdparty/com/google/protobuf/RepeatedFieldBuilderV3;
       4: ifnonnull     21
       7: aload_0
       8: getfield      #16                 // Field tstMap_:Ljava/util/List;
      11: iload_1
      12: invokeinterface #116,  2          // InterfaceMethod java/util/List.get:(I)Ljava/lang/Object;
      17: checkcast     #147                // class org/apache/hadoop/hbase/shaded/protobuf/generated/BackupProtos$TableServerTimestampOrBuilder
      20: areturn
      21: aload_0
      22: getfield      #30                 // Field tstMapBuilder_:Lorg/apache/hbase/thirdparty/com/google/protobuf/RepeatedFieldBuilderV3;
      25: iload_1
      26: invokevirtual #132                // Method org/apache/hbase/thirdparty/com/google/protobuf/RepeatedFieldBuilderV3.getMessageOrBuilder:(I)Lorg/apache/hbase/thirdparty/com/google/protobuf/MessageOrBuilder;
      29: checkcast     #147                // class org/apache/hadoop/hbase/shaded/protobuf/generated/BackupProtos$TableServerTimestampOrBuilder
      32: areturn

  public java.util.List<? extends org.apache.hadoop.hbase.shaded.protobuf.generated.BackupProtos$TableServerTimestampOrBuilder> getTstMapOrBuilderList();
    Code:
       0: aload_0
       1: getfield      #30                 // Field tstMapBuilder_:Lorg/apache/hbase/thirdparty/com/google/protobuf/RepeatedFieldBuilderV3;
       4: ifnull        15
       7: aload_0
       8: getfield      #30                 // Field tstMapBuilder_:Lorg/apache/hbase/thirdparty/com/google/protobuf/RepeatedFieldBuilderV3;
      11: invokevirtual #133                // Method org/apache/hbase/thirdparty/com/google/protobuf/RepeatedFieldBuilderV3.getMessageOrBuilderList:()Ljava/util/List;
      14: areturn
      15: aload_0
      16: getfield      #16                 // Field tstMap_:Ljava/util/List;
      19: invokestatic  #39                 // Method java/util/Collections.unmodifiableList:(Ljava/util/List;)Ljava/util/List;
      22: areturn

  public org.apache.hadoop.hbase.shaded.protobuf.generated.BackupProtos$TableServerTimestamp$Builder addTstMapBuilder();
    Code:
       0: aload_0
       1: invokespecial #22                 // Method getTstMapFieldBuilder:()Lorg/apache/hbase/thirdparty/com/google/protobuf/RepeatedFieldBuilderV3;
       4: invokestatic  #148                // Method org/apache/hadoop/hbase/shaded/protobuf/generated/BackupProtos$TableServerTimestamp.getDefaultInstance:()Lorg/apache/hadoop/hbase/shaded/protobuf/generated/BackupProtos$TableServerTimestamp;
       7: invokevirtual #135                // Method org/apache/hbase/thirdparty/com/google/protobuf/RepeatedFieldBuilderV3.addBuilder:(Lorg/apache/hbase/thirdparty/com/google/protobuf/AbstractMessage;)Lorg/apache/hbase/thirdparty/com/google/protobuf/AbstractMessage$Builder;
      10: checkcast     #146                // class org/apache/hadoop/hbase/shaded/protobuf/generated/BackupProtos$TableServerTimestamp$Builder
      13: areturn

  public org.apache.hadoop.hbase.shaded.protobuf.generated.BackupProtos$TableServerTimestamp$Builder addTstMapBuilder(int);
    Code:
       0: aload_0
       1: invokespecial #22                 // Method getTstMapFieldBuilder:()Lorg/apache/hbase/thirdparty/com/google/protobuf/RepeatedFieldBuilderV3;
       4: iload_1
       5: invokestatic  #148                // Method org/apache/hadoop/hbase/shaded/protobuf/generated/BackupProtos$TableServerTimestamp.getDefaultInstance:()Lorg/apache/hadoop/hbase/shaded/protobuf/generated/BackupProtos$TableServerTimestamp;
       8: invokevirtual #136                // Method org/apache/hbase/thirdparty/com/google/protobuf/RepeatedFieldBuilderV3.addBuilder:(ILorg/apache/hbase/thirdparty/com/google/protobuf/AbstractMessage;)Lorg/apache/hbase/thirdparty/com/google/protobuf/AbstractMessage$Builder;
      11: checkcast     #146                // class org/apache/hadoop/hbase/shaded/protobuf/generated/BackupProtos$TableServerTimestamp$Builder
      14: areturn

  public java.util.List<org.apache.hadoop.hbase.shaded.protobuf.generated.BackupProtos$TableServerTimestamp$Builder> getTstMapBuilderList();
    Code:
       0: aload_0
       1: invokespecial #22                 // Method getTstMapFieldBuilder:()Lorg/apache/hbase/thirdparty/com/google/protobuf/RepeatedFieldBuilderV3;
       4: invokevirtual #137                // Method org/apache/hbase/thirdparty/com/google/protobuf/RepeatedFieldBuilderV3.getBuilderList:()Ljava/util/List;
       7: areturn

  public final org.apache.hadoop.hbase.shaded.protobuf.generated.BackupProtos$BackupImage$Builder setUnknownFields(org.apache.hbase.thirdparty.com.google.protobuf.UnknownFieldSet);
    Code:
       0: aload_0
       1: aload_1
       2: invokespecial #149                // Method org/apache/hbase/thirdparty/com/google/protobuf/GeneratedMessageV3$Builder.setUnknownFields:(Lorg/apache/hbase/thirdparty/com/google/protobuf/UnknownFieldSet;)Lorg/apache/hbase/thirdparty/com/google/protobuf/GeneratedMessageV3$Builder;
       5: checkcast     #6                  // class org/apache/hadoop/hbase/shaded/protobuf/generated/BackupProtos$BackupImage$Builder
       8: areturn

  public final org.apache.hadoop.hbase.shaded.protobuf.generated.BackupProtos$BackupImage$Builder mergeUnknownFields(org.apache.hbase.thirdparty.com.google.protobuf.UnknownFieldSet);
    Code:
       0: aload_0
       1: aload_1
       2: invokespecial #150                // Method org/apache/hbase/thirdparty/com/google/protobuf/GeneratedMessageV3$Builder.mergeUnknownFields:(Lorg/apache/hbase/thirdparty/com/google/protobuf/UnknownFieldSet;)Lorg/apache/hbase/thirdparty/com/google/protobuf/GeneratedMessageV3$Builder;
       5: checkcast     #6                  // class org/apache/hadoop/hbase/shaded/protobuf/generated/BackupProtos$BackupImage$Builder
       8: areturn

  public org.apache.hbase.thirdparty.com.google.protobuf.GeneratedMessageV3$Builder mergeUnknownFields(org.apache.hbase.thirdparty.com.google.protobuf.UnknownFieldSet);
    Code:
       0: aload_0
       1: aload_1
       2: invokevirtual #85                 // Method mergeUnknownFields:(Lorg/apache/hbase/thirdparty/com/google/protobuf/UnknownFieldSet;)Lorg/apache/hadoop/hbase/shaded/protobuf/generated/BackupProtos$BackupImage$Builder;
       5: areturn

  public org.apache.hbase.thirdparty.com.google.protobuf.GeneratedMessageV3$Builder setUnknownFields(org.apache.hbase.thirdparty.com.google.protobuf.UnknownFieldSet);
    Code:
       0: aload_0
       1: aload_1
       2: invokevirtual #151                // Method setUnknownFields:(Lorg/apache/hbase/thirdparty/com/google/protobuf/UnknownFieldSet;)Lorg/apache/hadoop/hbase/shaded/protobuf/generated/BackupProtos$BackupImage$Builder;
       5: areturn

  public org.apache.hbase.thirdparty.com.google.protobuf.GeneratedMessageV3$Builder addRepeatedField(org.apache.hbase.thirdparty.com.google.protobuf.Descriptors$FieldDescriptor, java.lang.Object);
    Code:
       0: aload_0
       1: aload_1
       2: aload_2
       3: invokevirtual #152                // Method addRepeatedField:(Lorg/apache/hbase/thirdparty/com/google/protobuf/Descriptors$FieldDescriptor;Ljava/lang/Object;)Lorg/apache/hadoop/hbase/shaded/protobuf/generated/BackupProtos$BackupImage$Builder;
       6: areturn

  public org.apache.hbase.thirdparty.com.google.protobuf.GeneratedMessageV3$Builder setRepeatedField(org.apache.hbase.thirdparty.com.google.protobuf.Descriptors$FieldDescriptor, int, java.lang.Object);
    Code:
       0: aload_0
       1: aload_1
       2: iload_2
       3: aload_3
       4: invokevirtual #153                // Method setRepeatedField:(Lorg/apache/hbase/thirdparty/com/google/protobuf/Descriptors$FieldDescriptor;ILjava/lang/Object;)Lorg/apache/hadoop/hbase/shaded/protobuf/generated/BackupProtos$BackupImage$Builder;
       7: areturn

  public org.apache.hbase.thirdparty.com.google.protobuf.GeneratedMessageV3$Builder clearOneof(org.apache.hbase.thirdparty.com.google.protobuf.Descriptors$OneofDescriptor);
    Code:
       0: aload_0
       1: aload_1
       2: invokevirtual #154                // Method clearOneof:(Lorg/apache/hbase/thirdparty/com/google/protobuf/Descriptors$OneofDescriptor;)Lorg/apache/hadoop/hbase/shaded/protobuf/generated/BackupProtos$BackupImage$Builder;
       5: areturn

  public org.apache.hbase.thirdparty.com.google.protobuf.GeneratedMessageV3$Builder clearField(org.apache.hbase.thirdparty.com.google.protobuf.Descriptors$FieldDescriptor);
    Code:
       0: aload_0
       1: aload_1
       2: invokevirtual #155                // Method clearField:(Lorg/apache/hbase/thirdparty/com/google/protobuf/Descriptors$FieldDescriptor;)Lorg/apache/hadoop/hbase/shaded/protobuf/generated/BackupProtos$BackupImage$Builder;
       5: areturn

  public org.apache.hbase.thirdparty.com.google.protobuf.GeneratedMessageV3$Builder setField(org.apache.hbase.thirdparty.com.google.protobuf.Descriptors$FieldDescriptor, java.lang.Object);
    Code:
       0: aload_0
       1: aload_1
       2: aload_2
       3: invokevirtual #156                // Method setField:(Lorg/apache/hbase/thirdparty/com/google/protobuf/Descriptors$FieldDescriptor;Ljava/lang/Object;)Lorg/apache/hadoop/hbase/shaded/protobuf/generated/BackupProtos$BackupImage$Builder;
       6: areturn

  public org.apache.hbase.thirdparty.com.google.protobuf.GeneratedMessageV3$Builder clear();
    Code:
       0: aload_0
       1: invokevirtual #157                // Method clear:()Lorg/apache/hadoop/hbase/shaded/protobuf/generated/BackupProtos$BackupImage$Builder;
       4: areturn

  public org.apache.hbase.thirdparty.com.google.protobuf.GeneratedMessageV3$Builder clone();
    Code:
       0: aload_0
       1: invokevirtual #158                // Method clone:()Lorg/apache/hadoop/hbase/shaded/protobuf/generated/BackupProtos$BackupImage$Builder;
       4: areturn

  public org.apache.hbase.thirdparty.com.google.protobuf.AbstractMessage$Builder mergeUnknownFields(org.apache.hbase.thirdparty.com.google.protobuf.UnknownFieldSet);
    Code:
       0: aload_0
       1: aload_1
       2: invokevirtual #85                 // Method mergeUnknownFields:(Lorg/apache/hbase/thirdparty/com/google/protobuf/UnknownFieldSet;)Lorg/apache/hadoop/hbase/shaded/protobuf/generated/BackupProtos$BackupImage$Builder;
       5: areturn

  public org.apache.hbase.thirdparty.com.google.protobuf.AbstractMessage$Builder mergeFrom(org.apache.hbase.thirdparty.com.google.protobuf.CodedInputStream, org.apache.hbase.thirdparty.com.google.protobuf.ExtensionRegistryLite) throws java.io.IOException;
    Code:
       0: aload_0
       1: aload_1
       2: aload_2
       3: invokevirtual #159                // Method mergeFrom:(Lorg/apache/hbase/thirdparty/com/google/protobuf/CodedInputStream;Lorg/apache/hbase/thirdparty/com/google/protobuf/ExtensionRegistryLite;)Lorg/apache/hadoop/hbase/shaded/protobuf/generated/BackupProtos$BackupImage$Builder;
       6: areturn

  public org.apache.hbase.thirdparty.com.google.protobuf.AbstractMessage$Builder mergeFrom(org.apache.hbase.thirdparty.com.google.protobuf.Message);
    Code:
       0: aload_0
       1: aload_1
       2: invokevirtual #160                // Method mergeFrom:(Lorg/apache/hbase/thirdparty/com/google/protobuf/Message;)Lorg/apache/hadoop/hbase/shaded/protobuf/generated/BackupProtos$BackupImage$Builder;
       5: areturn

  public org.apache.hbase.thirdparty.com.google.protobuf.AbstractMessage$Builder clear();
    Code:
       0: aload_0
       1: invokevirtual #157                // Method clear:()Lorg/apache/hadoop/hbase/shaded/protobuf/generated/BackupProtos$BackupImage$Builder;
       4: areturn

  public org.apache.hbase.thirdparty.com.google.protobuf.AbstractMessage$Builder clearOneof(org.apache.hbase.thirdparty.com.google.protobuf.Descriptors$OneofDescriptor);
    Code:
       0: aload_0
       1: aload_1
       2: invokevirtual #154                // Method clearOneof:(Lorg/apache/hbase/thirdparty/com/google/protobuf/Descriptors$OneofDescriptor;)Lorg/apache/hadoop/hbase/shaded/protobuf/generated/BackupProtos$BackupImage$Builder;
       5: areturn

  public org.apache.hbase.thirdparty.com.google.protobuf.AbstractMessage$Builder clone();
    Code:
       0: aload_0
       1: invokevirtual #158                // Method clone:()Lorg/apache/hadoop/hbase/shaded/protobuf/generated/BackupProtos$BackupImage$Builder;
       4: areturn

  public org.apache.hbase.thirdparty.com.google.protobuf.Message$Builder mergeUnknownFields(org.apache.hbase.thirdparty.com.google.protobuf.UnknownFieldSet);
    Code:
       0: aload_0
       1: aload_1
       2: invokevirtual #85                 // Method mergeUnknownFields:(Lorg/apache/hbase/thirdparty/com/google/protobuf/UnknownFieldSet;)Lorg/apache/hadoop/hbase/shaded/protobuf/generated/BackupProtos$BackupImage$Builder;
       5: areturn

  public org.apache.hbase.thirdparty.com.google.protobuf.Message$Builder setUnknownFields(org.apache.hbase.thirdparty.com.google.protobuf.UnknownFieldSet);
    Code:
       0: aload_0
       1: aload_1
       2: invokevirtual #151                // Method setUnknownFields:(Lorg/apache/hbase/thirdparty/com/google/protobuf/UnknownFieldSet;)Lorg/apache/hadoop/hbase/shaded/protobuf/generated/BackupProtos$BackupImage$Builder;
       5: areturn

  public org.apache.hbase.thirdparty.com.google.protobuf.Message$Builder addRepeatedField(org.apache.hbase.thirdparty.com.google.protobuf.Descriptors$FieldDescriptor, java.lang.Object);
    Code:
       0: aload_0
       1: aload_1
       2: aload_2
       3: invokevirtual #152                // Method addRepeatedField:(Lorg/apache/hbase/thirdparty/com/google/protobuf/Descriptors$FieldDescriptor;Ljava/lang/Object;)Lorg/apache/hadoop/hbase/shaded/protobuf/generated/BackupProtos$BackupImage$Builder;
       6: areturn

  public org.apache.hbase.thirdparty.com.google.protobuf.Message$Builder setRepeatedField(org.apache.hbase.thirdparty.com.google.protobuf.Descriptors$FieldDescriptor, int, java.lang.Object);
    Code:
       0: aload_0
       1: aload_1
       2: iload_2
       3: aload_3
       4: invokevirtual #153                // Method setRepeatedField:(Lorg/apache/hbase/thirdparty/com/google/protobuf/Descriptors$FieldDescriptor;ILjava/lang/Object;)Lorg/apache/hadoop/hbase/shaded/protobuf/generated/BackupProtos$BackupImage$Builder;
       7: areturn

  public org.apache.hbase.thirdparty.com.google.protobuf.Message$Builder clearOneof(org.apache.hbase.thirdparty.com.google.protobuf.Descriptors$OneofDescriptor);
    Code:
       0: aload_0
       1: aload_1
       2: invokevirtual #154                // Method clearOneof:(Lorg/apache/hbase/thirdparty/com/google/protobuf/Descriptors$OneofDescriptor;)Lorg/apache/hadoop/hbase/shaded/protobuf/generated/BackupProtos$BackupImage$Builder;
       5: areturn

  public org.apache.hbase.thirdparty.com.google.protobuf.Message$Builder clearField(org.apache.hbase.thirdparty.com.google.protobuf.Descriptors$FieldDescriptor);
    Code:
       0: aload_0
       1: aload_1
       2: invokevirtual #155                // Method clearField:(Lorg/apache/hbase/thirdparty/com/google/protobuf/Descriptors$FieldDescriptor;)Lorg/apache/hadoop/hbase/shaded/protobuf/generated/BackupProtos$BackupImage$Builder;
       5: areturn

  public org.apache.hbase.thirdparty.com.google.protobuf.Message$Builder setField(org.apache.hbase.thirdparty.com.google.protobuf.Descriptors$FieldDescriptor, java.lang.Object);
    Code:
       0: aload_0
       1: aload_1
       2: aload_2
       3: invokevirtual #156                // Method setField:(Lorg/apache/hbase/thirdparty/com/google/protobuf/Descriptors$FieldDescriptor;Ljava/lang/Object;)Lorg/apache/hadoop/hbase/shaded/protobuf/generated/BackupProtos$BackupImage$Builder;
       6: areturn

  public org.apache.hbase.thirdparty.com.google.protobuf.Message$Builder mergeFrom(org.apache.hbase.thirdparty.com.google.protobuf.CodedInputStream, org.apache.hbase.thirdparty.com.google.protobuf.ExtensionRegistryLite) throws java.io.IOException;
    Code:
       0: aload_0
       1: aload_1
       2: aload_2
       3: invokevirtual #159                // Method mergeFrom:(Lorg/apache/hbase/thirdparty/com/google/protobuf/CodedInputStream;Lorg/apache/hbase/thirdparty/com/google/protobuf/ExtensionRegistryLite;)Lorg/apache/hadoop/hbase/shaded/protobuf/generated/BackupProtos$BackupImage$Builder;
       6: areturn

  public org.apache.hbase.thirdparty.com.google.protobuf.Message$Builder clone();
    Code:
       0: aload_0
       1: invokevirtual #158                // Method clone:()Lorg/apache/hadoop/hbase/shaded/protobuf/generated/BackupProtos$BackupImage$Builder;
       4: areturn

  public org.apache.hbase.thirdparty.com.google.protobuf.Message buildPartial();
    Code:
       0: aload_0
       1: invokevirtual #32                 // Method buildPartial:()Lorg/apache/hadoop/hbase/shaded/protobuf/generated/BackupProtos$BackupImage;
       4: areturn

  public org.apache.hbase.thirdparty.com.google.protobuf.Message build();
    Code:
       0: aload_0
       1: invokevirtual #142                // Method build:()Lorg/apache/hadoop/hbase/shaded/protobuf/generated/BackupProtos$BackupImage;
       4: areturn

  public org.apache.hbase.thirdparty.com.google.protobuf.Message$Builder mergeFrom(org.apache.hbase.thirdparty.com.google.protobuf.Message);
    Code:
       0: aload_0
       1: aload_1
       2: invokevirtual #160                // Method mergeFrom:(Lorg/apache/hbase/thirdparty/com/google/protobuf/Message;)Lorg/apache/hadoop/hbase/shaded/protobuf/generated/BackupProtos$BackupImage$Builder;
       5: areturn

  public org.apache.hbase.thirdparty.com.google.protobuf.Message$Builder clear();
    Code:
       0: aload_0
       1: invokevirtual #157                // Method clear:()Lorg/apache/hadoop/hbase/shaded/protobuf/generated/BackupProtos$BackupImage$Builder;
       4: areturn

  public org.apache.hbase.thirdparty.com.google.protobuf.MessageLite$Builder mergeFrom(org.apache.hbase.thirdparty.com.google.protobuf.CodedInputStream, org.apache.hbase.thirdparty.com.google.protobuf.ExtensionRegistryLite) throws java.io.IOException;
    Code:
       0: aload_0
       1: aload_1
       2: aload_2
       3: invokevirtual #159                // Method mergeFrom:(Lorg/apache/hbase/thirdparty/com/google/protobuf/CodedInputStream;Lorg/apache/hbase/thirdparty/com/google/protobuf/ExtensionRegistryLite;)Lorg/apache/hadoop/hbase/shaded/protobuf/generated/BackupProtos$BackupImage$Builder;
       6: areturn

  public org.apache.hbase.thirdparty.com.google.protobuf.MessageLite$Builder clone();
    Code:
       0: aload_0
       1: invokevirtual #158                // Method clone:()Lorg/apache/hadoop/hbase/shaded/protobuf/generated/BackupProtos$BackupImage$Builder;
       4: areturn

  public org.apache.hbase.thirdparty.com.google.protobuf.MessageLite buildPartial();
    Code:
       0: aload_0
       1: invokevirtual #32                 // Method buildPartial:()Lorg/apache/hadoop/hbase/shaded/protobuf/generated/BackupProtos$BackupImage;
       4: areturn

  public org.apache.hbase.thirdparty.com.google.protobuf.MessageLite build();
    Code:
       0: aload_0
       1: invokevirtual #142                // Method build:()Lorg/apache/hadoop/hbase/shaded/protobuf/generated/BackupProtos$BackupImage;
       4: areturn

  public org.apache.hbase.thirdparty.com.google.protobuf.MessageLite$Builder clear();
    Code:
       0: aload_0
       1: invokevirtual #157                // Method clear:()Lorg/apache/hadoop/hbase/shaded/protobuf/generated/BackupProtos$BackupImage$Builder;
       4: areturn

  public org.apache.hbase.thirdparty.com.google.protobuf.MessageLite getDefaultInstanceForType();
    Code:
       0: aload_0
       1: invokevirtual #161                // Method getDefaultInstanceForType:()Lorg/apache/hadoop/hbase/shaded/protobuf/generated/BackupProtos$BackupImage;
       4: areturn

  public org.apache.hbase.thirdparty.com.google.protobuf.Message getDefaultInstanceForType();
    Code:
       0: aload_0
       1: invokevirtual #161                // Method getDefaultInstanceForType:()Lorg/apache/hadoop/hbase/shaded/protobuf/generated/BackupProtos$BackupImage;
       4: areturn

  public org.apache.hbase.thirdparty.com.google.protobuf.AbstractMessageLite$Builder mergeFrom(org.apache.hbase.thirdparty.com.google.protobuf.CodedInputStream, org.apache.hbase.thirdparty.com.google.protobuf.ExtensionRegistryLite) throws java.io.IOException;
    Code:
       0: aload_0
       1: aload_1
       2: aload_2
       3: invokevirtual #159                // Method mergeFrom:(Lorg/apache/hbase/thirdparty/com/google/protobuf/CodedInputStream;Lorg/apache/hbase/thirdparty/com/google/protobuf/ExtensionRegistryLite;)Lorg/apache/hadoop/hbase/shaded/protobuf/generated/BackupProtos$BackupImage$Builder;
       6: areturn

  public org.apache.hbase.thirdparty.com.google.protobuf.AbstractMessageLite$Builder clone();
    Code:
       0: aload_0
       1: invokevirtual #158                // Method clone:()Lorg/apache/hadoop/hbase/shaded/protobuf/generated/BackupProtos$BackupImage$Builder;
       4: areturn

  public java.lang.Object clone() throws java.lang.CloneNotSupportedException;
    Code:
       0: aload_0
       1: invokevirtual #158                // Method clone:()Lorg/apache/hadoop/hbase/shaded/protobuf/generated/BackupProtos$BackupImage$Builder;
       4: areturn

  org.apache.hadoop.hbase.shaded.protobuf.generated.BackupProtos$BackupImage$Builder(org.apache.hadoop.hbase.shaded.protobuf.generated.BackupProtos$1);
    Code:
       0: aload_0
       1: invokespecial #2                  // Method "<init>":()V
       4: return

  org.apache.hadoop.hbase.shaded.protobuf.generated.BackupProtos$BackupImage$Builder(org.apache.hbase.thirdparty.com.google.protobuf.GeneratedMessageV3$BuilderParent, org.apache.hadoop.hbase.shaded.protobuf.generated.BackupProtos$1);
    Code:
       0: aload_0
       1: aload_1
       2: invokespecial #1                  // Method "<init>":(Lorg/apache/hbase/thirdparty/com/google/protobuf/GeneratedMessageV3$BuilderParent;)V
       5: return
}
