Compiled from "BalancedQueueRpcExecutor.java"
public class org.apache.hadoop.hbase.ipc.BalancedQueueRpcExecutor extends org.apache.hadoop.hbase.ipc.RpcExecutor {
  public org.apache.hadoop.hbase.ipc.BalancedQueueRpcExecutor(java.lang.String, int, int, org.apache.hadoop.hbase.ipc.PriorityFunction, org.apache.hadoop.conf.Configuration, org.apache.hadoop.hbase.Abortable);
    Code:
       0: aload_0
       1: aload_1
       2: iload_2
       3: aload         5
       5: ldc           #2                  // String hbase.ipc.server.callqueue.type
       7: ldc           #3                  // String fifo
       9: invokevirtual #4                  // Method org/apache/hadoop/conf/Configuration.get:(Ljava/lang/String;Ljava/lang/String;)Ljava/lang/String;
      12: iload_3
      13: aload         4
      15: aload         5
      17: aload         6
      19: invokespecial #5                  // Method "<init>":(Ljava/lang/String;ILjava/lang/String;ILorg/apache/hadoop/hbase/ipc/PriorityFunction;Lorg/apache/hadoop/conf/Configuration;Lorg/apache/hadoop/hbase/Abortable;)V
      22: return

  public org.apache.hadoop.hbase.ipc.BalancedQueueRpcExecutor(java.lang.String, int, java.lang.String, int, org.apache.hadoop.hbase.ipc.PriorityFunction, org.apache.hadoop.conf.Configuration, org.apache.hadoop.hbase.Abortable);
    Code:
       0: aload_0
       1: aload_1
       2: iload_2
       3: aload_3
       4: iload         4
       6: aload         5
       8: aload         6
      10: aload         7
      12: invokespecial #6                  // Method org/apache/hadoop/hbase/ipc/RpcExecutor."<init>":(Ljava/lang/String;ILjava/lang/String;ILorg/apache/hadoop/hbase/ipc/PriorityFunction;Lorg/apache/hadoop/conf/Configuration;Lorg/apache/hadoop/hbase/Abortable;)V
      15: aload_0
      16: aload_0
      17: getfield      #7                  // Field numCallQueues:I
      20: invokestatic  #8                  // Method getBalancer:(I)Lorg/apache/hadoop/hbase/ipc/RpcExecutor$QueueBalancer;
      23: putfield      #9                  // Field balancer:Lorg/apache/hadoop/hbase/ipc/RpcExecutor$QueueBalancer;
      26: aload_0
      27: aload_0
      28: getfield      #7                  // Field numCallQueues:I
      31: invokevirtual #10                 // Method initializeQueues:(I)V
      34: return

  public boolean dispatch(org.apache.hadoop.hbase.ipc.CallRunner) throws java.lang.InterruptedException;
    Code:
       0: aload_0
       1: getfield      #9                  // Field balancer:Lorg/apache/hadoop/hbase/ipc/RpcExecutor$QueueBalancer;
       4: invokevirtual #11                 // Method org/apache/hadoop/hbase/ipc/RpcExecutor$QueueBalancer.getNextQueue:()I
       7: istore_2
       8: aload_0
       9: getfield      #12                 // Field queues:Ljava/util/List;
      12: iload_2
      13: invokeinterface #13,  2           // InterfaceMethod java/util/List.get:(I)Ljava/lang/Object;
      18: checkcast     #14                 // class java/util/concurrent/BlockingQueue
      21: astore_3
      22: aload_3
      23: invokeinterface #15,  1           // InterfaceMethod java/util/concurrent/BlockingQueue.size:()I
      28: aload_0
      29: getfield      #16                 // Field currentQueueLimit:I
      32: if_icmplt     37
      35: iconst_0
      36: ireturn
      37: aload_3
      38: aload_1
      39: invokeinterface #17,  2           // InterfaceMethod java/util/concurrent/BlockingQueue.offer:(Ljava/lang/Object;)Z
      44: ireturn
}
