Compiled from "BaseSourceImpl.java"
final class org.apache.hadoop.hbase.metrics.BaseSourceImpl$DefaultMetricsSystemInitializer extends java.lang.Enum<org.apache.hadoop.hbase.metrics.BaseSourceImpl$DefaultMetricsSystemInitializer> {
  public static final org.apache.hadoop.hbase.metrics.BaseSourceImpl$DefaultMetricsSystemInitializer INSTANCE;

  public static org.apache.hadoop.hbase.metrics.BaseSourceImpl$DefaultMetricsSystemInitializer[] values();
    Code:
       0: getstatic     #2                  // Field $VALUES:[Lorg/apache/hadoop/hbase/metrics/BaseSourceImpl$DefaultMetricsSystemInitializer;
       3: invokevirtual #3                  // Method "[Lorg/apache/hadoop/hbase/metrics/BaseSourceImpl$DefaultMetricsSystemInitializer;".clone:()Ljava/lang/Object;
       6: checkcast     #4                  // class "[Lorg/apache/hadoop/hbase/metrics/BaseSourceImpl$DefaultMetricsSystemInitializer;"
       9: areturn

  public static org.apache.hadoop.hbase.metrics.BaseSourceImpl$DefaultMetricsSystemInitializer valueOf(java.lang.String);
    Code:
       0: ldc           #5                  // class org/apache/hadoop/hbase/metrics/BaseSourceImpl$DefaultMetricsSystemInitializer
       2: aload_0
       3: invokestatic  #6                  // Method java/lang/Enum.valueOf:(Ljava/lang/Class;Ljava/lang/String;)Ljava/lang/Enum;
       6: checkcast     #5                  // class org/apache/hadoop/hbase/metrics/BaseSourceImpl$DefaultMetricsSystemInitializer
       9: areturn

  synchronized void init(java.lang.String);
    Code:
       0: aload_0
       1: getfield      #8                  // Field inited:Z
       4: ifeq          8
       7: return
       8: aload_0
       9: iconst_1
      10: putfield      #8                  // Field inited:Z
      13: ldc           #9                  // String HBase
      15: invokestatic  #10                 // Method org/apache/hadoop/metrics2/lib/DefaultMetricsSystem.initialize:(Ljava/lang/String;)Lorg/apache/hadoop/metrics2/MetricsSystem;
      18: pop
      19: aload_1
      20: ldc           #11                 // String
      22: invokestatic  #12                 // Method org/apache/hadoop/metrics2/source/JvmMetrics.initSingleton:(Ljava/lang/String;Ljava/lang/String;)Lorg/apache/hadoop/metrics2/source/JvmMetrics;
      25: pop
      26: invokestatic  #13                 // Method org/apache/hadoop/hbase/metrics/impl/GlobalMetricRegistriesAdapter.init:()Lorg/apache/hadoop/hbase/metrics/impl/GlobalMetricRegistriesAdapter;
      29: pop
      30: return

  static {};
    Code:
       0: new           #5                  // class org/apache/hadoop/hbase/metrics/BaseSourceImpl$DefaultMetricsSystemInitializer
       3: dup
       4: ldc           #14                 // String INSTANCE
       6: iconst_0
       7: invokespecial #15                 // Method "<init>":(Ljava/lang/String;I)V
      10: putstatic     #16                 // Field INSTANCE:Lorg/apache/hadoop/hbase/metrics/BaseSourceImpl$DefaultMetricsSystemInitializer;
      13: iconst_1
      14: anewarray     #5                  // class org/apache/hadoop/hbase/metrics/BaseSourceImpl$DefaultMetricsSystemInitializer
      17: dup
      18: iconst_0
      19: getstatic     #16                 // Field INSTANCE:Lorg/apache/hadoop/hbase/metrics/BaseSourceImpl$DefaultMetricsSystemInitializer;
      22: aastore
      23: putstatic     #2                  // Field $VALUES:[Lorg/apache/hadoop/hbase/metrics/BaseSourceImpl$DefaultMetricsSystemInitializer;
      26: return
}
