Compiled from "BaseReplicationEndpoint.java"
public abstract class org.apache.hadoop.hbase.replication.BaseReplicationEndpoint extends org.apache.hbase.thirdparty.com.google.common.util.concurrent.AbstractService implements org.apache.hadoop.hbase.replication.ReplicationEndpoint {
  public static final java.lang.String REPLICATION_WALENTRYFILTER_CONFIG_KEY;

  protected org.apache.hadoop.hbase.replication.ReplicationEndpoint$Context ctx;

  public org.apache.hadoop.hbase.replication.BaseReplicationEndpoint();
    Code:
       0: aload_0
       1: invokespecial #1                  // Method org/apache/hbase/thirdparty/com/google/common/util/concurrent/AbstractService."<init>":()V
       4: return

  public void init(org.apache.hadoop.hbase.replication.ReplicationEndpoint$Context) throws java.io.IOException;
    Code:
       0: aload_0
       1: aload_1
       2: putfield      #2                  // Field ctx:Lorg/apache/hadoop/hbase/replication/ReplicationEndpoint$Context;
       5: aload_0
       6: getfield      #2                  // Field ctx:Lorg/apache/hadoop/hbase/replication/ReplicationEndpoint$Context;
       9: ifnull        72
      12: aload_0
      13: getfield      #2                  // Field ctx:Lorg/apache/hadoop/hbase/replication/ReplicationEndpoint$Context;
      16: invokevirtual #3                  // Method org/apache/hadoop/hbase/replication/ReplicationEndpoint$Context.getReplicationPeer:()Lorg/apache/hadoop/hbase/replication/ReplicationPeer;
      19: astore_2
      20: aload_2
      21: ifnull        34
      24: aload_2
      25: aload_0
      26: invokeinterface #4,  2            // InterfaceMethod org/apache/hadoop/hbase/replication/ReplicationPeer.registerPeerConfigListener:(Lorg/apache/hadoop/hbase/replication/ReplicationPeerConfigListener;)V
      31: goto          72
      34: getstatic     #5                  // Field LOG:Lorg/slf4j/Logger;
      37: new           #6                  // class java/lang/StringBuilder
      40: dup
      41: invokespecial #7                  // Method java/lang/StringBuilder."<init>":()V
      44: ldc           #8                  // String Not tracking replication peer config changes for Peer Id
      46: invokevirtual #9                  // Method java/lang/StringBuilder.append:(Ljava/lang/String;)Ljava/lang/StringBuilder;
      49: aload_0
      50: getfield      #2                  // Field ctx:Lorg/apache/hadoop/hbase/replication/ReplicationEndpoint$Context;
      53: invokevirtual #10                 // Method org/apache/hadoop/hbase/replication/ReplicationEndpoint$Context.getPeerId:()Ljava/lang/String;
      56: invokevirtual #9                  // Method java/lang/StringBuilder.append:(Ljava/lang/String;)Ljava/lang/StringBuilder;
      59: ldc           #11                 // String  because there's no such peer
      61: invokevirtual #9                  // Method java/lang/StringBuilder.append:(Ljava/lang/String;)Ljava/lang/StringBuilder;
      64: invokevirtual #12                 // Method java/lang/StringBuilder.toString:()Ljava/lang/String;
      67: invokeinterface #13,  2           // InterfaceMethod org/slf4j/Logger.warn:(Ljava/lang/String;)V
      72: return

  public void peerConfigUpdated(org.apache.hadoop.hbase.replication.ReplicationPeerConfig);
    Code:
       0: return

  public org.apache.hadoop.hbase.replication.WALEntryFilter getWALEntryfilter();
    Code:
       0: invokestatic  #14                 // Method org/apache/hbase/thirdparty/com/google/common/collect/Lists.newArrayList:()Ljava/util/ArrayList;
       3: astore_1
       4: aload_0
       5: invokevirtual #15                 // Method getScopeWALEntryFilter:()Lorg/apache/hadoop/hbase/replication/WALEntryFilter;
       8: astore_2
       9: aload_2
      10: ifnull        19
      13: aload_1
      14: aload_2
      15: invokevirtual #16                 // Method java/util/ArrayList.add:(Ljava/lang/Object;)Z
      18: pop
      19: aload_0
      20: invokevirtual #17                 // Method getNamespaceTableCfWALEntryFilter:()Lorg/apache/hadoop/hbase/replication/WALEntryFilter;
      23: astore_3
      24: aload_3
      25: ifnull        34
      28: aload_1
      29: aload_3
      30: invokevirtual #16                 // Method java/util/ArrayList.add:(Ljava/lang/Object;)Z
      33: pop
      34: aload_0
      35: getfield      #2                  // Field ctx:Lorg/apache/hadoop/hbase/replication/ReplicationEndpoint$Context;
      38: ifnull        193
      41: aload_0
      42: getfield      #2                  // Field ctx:Lorg/apache/hadoop/hbase/replication/ReplicationEndpoint$Context;
      45: invokevirtual #18                 // Method org/apache/hadoop/hbase/replication/ReplicationEndpoint$Context.getPeerConfig:()Lorg/apache/hadoop/hbase/replication/ReplicationPeerConfig;
      48: ifnull        193
      51: aload_0
      52: getfield      #2                  // Field ctx:Lorg/apache/hadoop/hbase/replication/ReplicationEndpoint$Context;
      55: invokevirtual #18                 // Method org/apache/hadoop/hbase/replication/ReplicationEndpoint$Context.getPeerConfig:()Lorg/apache/hadoop/hbase/replication/ReplicationPeerConfig;
      58: invokevirtual #19                 // Method org/apache/hadoop/hbase/replication/ReplicationPeerConfig.getConfiguration:()Ljava/util/Map;
      61: ldc           #21                 // String hbase.replication.source.custom.walentryfilters
      63: invokeinterface #22,  2           // InterfaceMethod java/util/Map.get:(Ljava/lang/Object;)Ljava/lang/Object;
      68: checkcast     #23                 // class java/lang/String
      71: astore        4
      73: aload         4
      75: ifnull        193
      78: aload         4
      80: invokevirtual #24                 // Method java/lang/String.isEmpty:()Z
      83: ifne          193
      86: aload         4
      88: ldc           #25                 // String ,
      90: invokevirtual #26                 // Method java/lang/String.split:(Ljava/lang/String;)[Ljava/lang/String;
      93: astore        5
      95: aload         5
      97: astore        6
      99: aload         6
     101: arraylength
     102: istore        7
     104: iconst_0
     105: istore        8
     107: iload         8
     109: iload         7
     111: if_icmpge     193
     114: aload         6
     116: iload         8
     118: aaload
     119: astore        9
     121: aload         9
     123: invokestatic  #27                 // Method java/lang/Class.forName:(Ljava/lang/String;)Ljava/lang/Class;
     126: astore        10
     128: aload_1
     129: aload         10
     131: iconst_0
     132: anewarray     #28                 // class java/lang/Class
     135: invokevirtual #29                 // Method java/lang/Class.getDeclaredConstructor:([Ljava/lang/Class;)Ljava/lang/reflect/Constructor;
     138: iconst_0
     139: anewarray     #30                 // class java/lang/Object
     142: invokevirtual #31                 // Method java/lang/reflect/Constructor.newInstance:([Ljava/lang/Object;)Ljava/lang/Object;
     145: checkcast     #32                 // class org/apache/hadoop/hbase/replication/WALEntryFilter
     148: invokevirtual #16                 // Method java/util/ArrayList.add:(Ljava/lang/Object;)Z
     151: pop
     152: goto          187
     155: astore        10
     157: getstatic     #5                  // Field LOG:Lorg/slf4j/Logger;
     160: new           #6                  // class java/lang/StringBuilder
     163: dup
     164: invokespecial #7                  // Method java/lang/StringBuilder."<init>":()V
     167: ldc           #34                 // String Unable to create WALEntryFilter
     169: invokevirtual #9                  // Method java/lang/StringBuilder.append:(Ljava/lang/String;)Ljava/lang/StringBuilder;
     172: aload         9
     174: invokevirtual #9                  // Method java/lang/StringBuilder.append:(Ljava/lang/String;)Ljava/lang/StringBuilder;
     177: invokevirtual #12                 // Method java/lang/StringBuilder.toString:()Ljava/lang/String;
     180: aload         10
     182: invokeinterface #35,  3           // InterfaceMethod org/slf4j/Logger.error:(Ljava/lang/String;Ljava/lang/Throwable;)V
     187: iinc          8, 1
     190: goto          107
     193: aload_1
     194: invokevirtual #36                 // Method java/util/ArrayList.isEmpty:()Z
     197: ifeq          204
     200: aconst_null
     201: goto          212
     204: new           #37                 // class org/apache/hadoop/hbase/replication/ChainWALEntryFilter
     207: dup
     208: aload_1
     209: invokespecial #38                 // Method org/apache/hadoop/hbase/replication/ChainWALEntryFilter."<init>":(Ljava/util/List;)V
     212: areturn
    Exception table:
       from    to  target type
         121   152   155   Class java/lang/Exception

  protected org.apache.hadoop.hbase.replication.WALEntryFilter getScopeWALEntryFilter();
    Code:
       0: new           #39                 // class org/apache/hadoop/hbase/replication/ScopeWALEntryFilter
       3: dup
       4: invokespecial #40                 // Method org/apache/hadoop/hbase/replication/ScopeWALEntryFilter."<init>":()V
       7: areturn

  protected org.apache.hadoop.hbase.replication.WALEntryFilter getNamespaceTableCfWALEntryFilter();
    Code:
       0: new           #41                 // class org/apache/hadoop/hbase/replication/NamespaceTableCfWALEntryFilter
       3: dup
       4: aload_0
       5: getfield      #2                  // Field ctx:Lorg/apache/hadoop/hbase/replication/ReplicationEndpoint$Context;
       8: invokevirtual #3                  // Method org/apache/hadoop/hbase/replication/ReplicationEndpoint$Context.getReplicationPeer:()Lorg/apache/hadoop/hbase/replication/ReplicationPeer;
      11: invokespecial #42                 // Method org/apache/hadoop/hbase/replication/NamespaceTableCfWALEntryFilter."<init>":(Lorg/apache/hadoop/hbase/replication/ReplicationPeer;)V
      14: areturn

  public boolean canReplicateToSameCluster();
    Code:
       0: iconst_0
       1: ireturn

  public boolean isStarting();
    Code:
       0: aload_0
       1: invokevirtual #43                 // Method state:()Lorg/apache/hbase/thirdparty/com/google/common/util/concurrent/Service$State;
       4: getstatic     #44                 // Field org/apache/hbase/thirdparty/com/google/common/util/concurrent/Service$State.STARTING:Lorg/apache/hbase/thirdparty/com/google/common/util/concurrent/Service$State;
       7: if_acmpne     14
      10: iconst_1
      11: goto          15
      14: iconst_0
      15: ireturn

  static {};
    Code:
       0: ldc           #20                 // class org/apache/hadoop/hbase/replication/BaseReplicationEndpoint
       2: invokestatic  #45                 // Method org/slf4j/LoggerFactory.getLogger:(Ljava/lang/Class;)Lorg/slf4j/Logger;
       5: putstatic     #5                  // Field LOG:Lorg/slf4j/Logger;
       8: return
}
