Compiled from "BaseRowProcessorEndpoint.java"
public abstract class org.apache.hadoop.hbase.coprocessor.BaseRowProcessorEndpoint<S extends com.google.protobuf.Message, T extends com.google.protobuf.Message> extends org.apache.hadoop.hbase.protobuf.generated.RowProcessorProtos$RowProcessorService implements org.apache.hadoop.hbase.coprocessor.RegionCoprocessor {
  public org.apache.hadoop.hbase.coprocessor.BaseRowProcessorEndpoint();
    Code:
       0: aload_0
       1: invokespecial #1                  // Method org/apache/hadoop/hbase/protobuf/generated/RowProcessorProtos$RowProcessorService."<init>":()V
       4: return

  public void process(com.google.protobuf.RpcController, org.apache.hadoop.hbase.protobuf.generated.RowProcessorProtos$ProcessRequest, com.google.protobuf.RpcCallback<org.apache.hadoop.hbase.protobuf.generated.RowProcessorProtos$ProcessResponse>);
    Code:
       0: aconst_null
       1: astore        4
       3: aload_0
       4: aload_2
       5: invokevirtual #2                  // Method constructRowProcessorFromRequest:(Lorg/apache/hadoop/hbase/protobuf/generated/RowProcessorProtos$ProcessRequest;)Lorg/apache/hadoop/hbase/regionserver/RowProcessor;
       8: astore        5
      10: aload_0
      11: getfield      #3                  // Field env:Lorg/apache/hadoop/hbase/coprocessor/RegionCoprocessorEnvironment;
      14: invokeinterface #4,  1            // InterfaceMethod org/apache/hadoop/hbase/coprocessor/RegionCoprocessorEnvironment.getRegion:()Lorg/apache/hadoop/hbase/regionserver/Region;
      19: astore        6
      21: aload_2
      22: invokevirtual #5                  // Method org/apache/hadoop/hbase/protobuf/generated/RowProcessorProtos$ProcessRequest.hasNonceGroup:()Z
      25: ifeq          35
      28: aload_2
      29: invokevirtual #6                  // Method org/apache/hadoop/hbase/protobuf/generated/RowProcessorProtos$ProcessRequest.getNonceGroup:()J
      32: goto          36
      35: lconst_0
      36: lstore        7
      38: aload_2
      39: invokevirtual #8                  // Method org/apache/hadoop/hbase/protobuf/generated/RowProcessorProtos$ProcessRequest.hasNonce:()Z
      42: ifeq          52
      45: aload_2
      46: invokevirtual #9                  // Method org/apache/hadoop/hbase/protobuf/generated/RowProcessorProtos$ProcessRequest.getNonce:()J
      49: goto          53
      52: lconst_0
      53: lstore        9
      55: aload         6
      57: aload         5
      59: lload         7
      61: lload         9
      63: invokeinterface #10,  6           // InterfaceMethod org/apache/hadoop/hbase/regionserver/Region.processRowsWithLocks:(Lorg/apache/hadoop/hbase/regionserver/RowProcessor;JJ)V
      68: aload         5
      70: invokeinterface #11,  1           // InterfaceMethod org/apache/hadoop/hbase/regionserver/RowProcessor.getResult:()Lcom/google/protobuf/Message;
      75: astore        11
      77: invokestatic  #12                 // Method org/apache/hadoop/hbase/protobuf/generated/RowProcessorProtos$ProcessResponse.newBuilder:()Lorg/apache/hadoop/hbase/protobuf/generated/RowProcessorProtos$ProcessResponse$Builder;
      80: astore        12
      82: aload         12
      84: aload         11
      86: invokeinterface #13,  1           // InterfaceMethod com/google/protobuf/Message.toByteString:()Lcom/google/protobuf/ByteString;
      91: invokevirtual #14                 // Method org/apache/hadoop/hbase/protobuf/generated/RowProcessorProtos$ProcessResponse$Builder.setRowProcessorResult:(Lcom/google/protobuf/ByteString;)Lorg/apache/hadoop/hbase/protobuf/generated/RowProcessorProtos$ProcessResponse$Builder;
      94: pop
      95: aload         12
      97: invokevirtual #15                 // Method org/apache/hadoop/hbase/protobuf/generated/RowProcessorProtos$ProcessResponse$Builder.build:()Lorg/apache/hadoop/hbase/protobuf/generated/RowProcessorProtos$ProcessResponse;
     100: astore        4
     102: goto          120
     105: astore        5
     107: aload_1
     108: new           #17                 // class java/io/IOException
     111: dup
     112: aload         5
     114: invokespecial #18                 // Method java/io/IOException."<init>":(Ljava/lang/Throwable;)V
     117: invokestatic  #19                 // Method org/apache/hadoop/hbase/ipc/CoprocessorRpcUtils.setControllerException:(Lcom/google/protobuf/RpcController;Ljava/io/IOException;)V
     120: aload_3
     121: aload         4
     123: invokeinterface #20,  2           // InterfaceMethod com/google/protobuf/RpcCallback.run:(Ljava/lang/Object;)V
     128: return
    Exception table:
       from    to  target type
           3   102   105   Class java/lang/Exception

  public java.lang.Iterable<com.google.protobuf.Service> getServices();
    Code:
       0: aload_0
       1: invokestatic  #21                 // Method java/util/Collections.singleton:(Ljava/lang/Object;)Ljava/util/Set;
       4: areturn

  public void start(org.apache.hadoop.hbase.CoprocessorEnvironment) throws java.io.IOException;
    Code:
       0: aload_1
       1: instanceof    #22                 // class org/apache/hadoop/hbase/coprocessor/RegionCoprocessorEnvironment
       4: ifeq          18
       7: aload_0
       8: aload_1
       9: checkcast     #22                 // class org/apache/hadoop/hbase/coprocessor/RegionCoprocessorEnvironment
      12: putfield      #3                  // Field env:Lorg/apache/hadoop/hbase/coprocessor/RegionCoprocessorEnvironment;
      15: goto          28
      18: new           #23                 // class org/apache/hadoop/hbase/coprocessor/CoprocessorException
      21: dup
      22: ldc           #24                 // String Must be loaded on a table region!
      24: invokespecial #25                 // Method org/apache/hadoop/hbase/coprocessor/CoprocessorException."<init>":(Ljava/lang/String;)V
      27: athrow
      28: return

  public void stop(org.apache.hadoop.hbase.CoprocessorEnvironment) throws java.io.IOException;
    Code:
       0: return

  org.apache.hadoop.hbase.regionserver.RowProcessor<S, T> constructRowProcessorFromRequest(org.apache.hadoop.hbase.protobuf.generated.RowProcessorProtos$ProcessRequest) throws java.io.IOException;
    Code:
       0: aload_1
       1: invokevirtual #26                 // Method org/apache/hadoop/hbase/protobuf/generated/RowProcessorProtos$ProcessRequest.getRowProcessorClassName:()Ljava/lang/String;
       4: astore_2
       5: aload_2
       6: invokestatic  #27                 // Method java/lang/Class.forName:(Ljava/lang/String;)Ljava/lang/Class;
       9: astore_3
      10: aload_3
      11: iconst_0
      12: anewarray     #28                 // class java/lang/Class
      15: invokevirtual #29                 // Method java/lang/Class.getDeclaredConstructor:([Ljava/lang/Class;)Ljava/lang/reflect/Constructor;
      18: iconst_0
      19: anewarray     #30                 // class java/lang/Object
      22: invokevirtual #31                 // Method java/lang/reflect/Constructor.newInstance:([Ljava/lang/Object;)Ljava/lang/Object;
      25: checkcast     #32                 // class org/apache/hadoop/hbase/regionserver/RowProcessor
      28: astore        4
      30: aload_1
      31: invokevirtual #33                 // Method org/apache/hadoop/hbase/protobuf/generated/RowProcessorProtos$ProcessRequest.hasRowProcessorInitializerMessageName:()Z
      34: ifeq          154
      37: aload_1
      38: invokevirtual #34                 // Method org/apache/hadoop/hbase/protobuf/generated/RowProcessorProtos$ProcessRequest.getRowProcessorInitializerMessageName:()Ljava/lang/String;
      41: invokestatic  #27                 // Method java/lang/Class.forName:(Ljava/lang/String;)Ljava/lang/Class;
      44: ldc           #35                 // class com/google/protobuf/Message
      46: invokevirtual #36                 // Method java/lang/Class.asSubclass:(Ljava/lang/Class;)Ljava/lang/Class;
      49: astore        5
      51: aload         5
      53: ldc           #37                 // String parseFrom
      55: iconst_1
      56: anewarray     #28                 // class java/lang/Class
      59: dup
      60: iconst_0
      61: ldc           #38                 // class com/google/protobuf/ByteString
      63: aastore
      64: invokevirtual #39                 // Method java/lang/Class.getMethod:(Ljava/lang/String;[Ljava/lang/Class;)Ljava/lang/reflect/Method;
      67: astore        6
      69: goto          96
      72: astore        7
      74: new           #17                 // class java/io/IOException
      77: dup
      78: aload         7
      80: invokespecial #18                 // Method java/io/IOException."<init>":(Ljava/lang/Throwable;)V
      83: athrow
      84: astore        7
      86: new           #17                 // class java/io/IOException
      89: dup
      90: aload         7
      92: invokespecial #18                 // Method java/io/IOException."<init>":(Ljava/lang/Throwable;)V
      95: athrow
      96: aload         6
      98: aconst_null
      99: iconst_1
     100: anewarray     #30                 // class java/lang/Object
     103: dup
     104: iconst_0
     105: aload_1
     106: invokevirtual #42                 // Method org/apache/hadoop/hbase/protobuf/generated/RowProcessorProtos$ProcessRequest.getRowProcessorInitializerMessage:()Lcom/google/protobuf/ByteString;
     109: aastore
     110: invokevirtual #43                 // Method java/lang/reflect/Method.invoke:(Ljava/lang/Object;[Ljava/lang/Object;)Ljava/lang/Object;
     113: checkcast     #35                 // class com/google/protobuf/Message
     116: astore        7
     118: goto          145
     121: astore        8
     123: new           #17                 // class java/io/IOException
     126: dup
     127: aload         8
     129: invokespecial #18                 // Method java/io/IOException."<init>":(Ljava/lang/Throwable;)V
     132: athrow
     133: astore        8
     135: new           #17                 // class java/io/IOException
     138: dup
     139: aload         8
     141: invokespecial #18                 // Method java/io/IOException."<init>":(Ljava/lang/Throwable;)V
     144: athrow
     145: aload         4
     147: aload         7
     149: invokeinterface #46,  2           // InterfaceMethod org/apache/hadoop/hbase/regionserver/RowProcessor.initialize:(Lcom/google/protobuf/Message;)V
     154: aload         4
     156: areturn
     157: astore        4
     159: new           #17                 // class java/io/IOException
     162: dup
     163: aload         4
     165: invokespecial #18                 // Method java/io/IOException."<init>":(Ljava/lang/Throwable;)V
     168: athrow
    Exception table:
       from    to  target type
          51    69    72   Class java/lang/SecurityException
          51    69    84   Class java/lang/NoSuchMethodException
          96   118   121   Class java/lang/IllegalArgumentException
          96   118   133   Class java/lang/reflect/InvocationTargetException
           5   156   157   Class java/lang/Exception
}
