Compiled from "BaseFileCleanerDelegate.java"
public abstract class org.apache.hadoop.hbase.master.cleaner.BaseFileCleanerDelegate extends org.apache.hadoop.hbase.BaseConfigurable implements org.apache.hadoop.hbase.master.cleaner.FileCleanerDelegate {
  public org.apache.hadoop.hbase.master.cleaner.BaseFileCleanerDelegate();
    Code:
       0: aload_0
       1: invokespecial #1                  // Method org/apache/hadoop/hbase/BaseConfigurable."<init>":()V
       4: return

  public java.lang.Iterable<org.apache.hadoop.fs.FileStatus> getDeletableFiles(java.lang.Iterable<org.apache.hadoop.fs.FileStatus>);
    Code:
       0: aload_1
       1: aload_0
       2: invokedynamic #2,  0              // InvokeDynamic #0:apply:(Lorg/apache/hadoop/hbase/master/cleaner/BaseFileCleanerDelegate;)Lorg/apache/hbase/thirdparty/com/google/common/base/Predicate;
       7: invokestatic  #3                  // Method org/apache/hbase/thirdparty/com/google/common/collect/Iterables.filter:(Ljava/lang/Iterable;Lorg/apache/hbase/thirdparty/com/google/common/base/Predicate;)Ljava/lang/Iterable;
      10: areturn

  public void init(java.util.Map<java.lang.String, java.lang.Object>);
    Code:
       0: return

  protected abstract boolean isFileDeletable(org.apache.hadoop.fs.FileStatus);
}
