Compiled from "BaseLoadBalancer.java"
public class org.apache.hadoop.hbase.master.balancer.BaseLoadBalancer$Cluster$SwapRegionsAction extends org.apache.hadoop.hbase.master.balancer.BaseLoadBalancer$Cluster$Action {
  public int fromServer;

  public int fromRegion;

  public int toServer;

  public int toRegion;

  public org.apache.hadoop.hbase.master.balancer.BaseLoadBalancer$Cluster$SwapRegionsAction(int, int, int, int);
    Code:
       0: aload_0
       1: getstatic     #1                  // Field org/apache/hadoop/hbase/master/balancer/BaseLoadBalancer$Cluster$Action$Type.SWAP_REGIONS:Lorg/apache/hadoop/hbase/master/balancer/BaseLoadBalancer$Cluster$Action$Type;
       4: invokespecial #2                  // Method org/apache/hadoop/hbase/master/balancer/BaseLoadBalancer$Cluster$Action."<init>":(Lorg/apache/hadoop/hbase/master/balancer/BaseLoadBalancer$Cluster$Action$Type;)V
       7: aload_0
       8: iload_1
       9: putfield      #3                  // Field fromServer:I
      12: aload_0
      13: iload_2
      14: putfield      #4                  // Field fromRegion:I
      17: aload_0
      18: iload_3
      19: putfield      #5                  // Field toServer:I
      22: aload_0
      23: iload         4
      25: putfield      #6                  // Field toRegion:I
      28: return

  public org.apache.hadoop.hbase.master.balancer.BaseLoadBalancer$Cluster$Action undoAction();
    Code:
       0: new           #7                  // class org/apache/hadoop/hbase/master/balancer/BaseLoadBalancer$Cluster$SwapRegionsAction
       3: dup
       4: aload_0
       5: getfield      #3                  // Field fromServer:I
       8: aload_0
       9: getfield      #6                  // Field toRegion:I
      12: aload_0
      13: getfield      #5                  // Field toServer:I
      16: aload_0
      17: getfield      #4                  // Field fromRegion:I
      20: invokespecial #8                  // Method "<init>":(IIII)V
      23: areturn

  public java.lang.String toString();
    Code:
       0: new           #9                  // class java/lang/StringBuilder
       3: dup
       4: invokespecial #10                 // Method java/lang/StringBuilder."<init>":()V
       7: aload_0
       8: getfield      #11                 // Field type:Lorg/apache/hadoop/hbase/master/balancer/BaseLoadBalancer$Cluster$Action$Type;
      11: invokevirtual #12                 // Method java/lang/StringBuilder.append:(Ljava/lang/Object;)Ljava/lang/StringBuilder;
      14: ldc           #13                 // String :
      16: invokevirtual #14                 // Method java/lang/StringBuilder.append:(Ljava/lang/String;)Ljava/lang/StringBuilder;
      19: aload_0
      20: getfield      #4                  // Field fromRegion:I
      23: invokevirtual #15                 // Method java/lang/StringBuilder.append:(I)Ljava/lang/StringBuilder;
      26: ldc           #16                 // String :
      28: invokevirtual #14                 // Method java/lang/StringBuilder.append:(Ljava/lang/String;)Ljava/lang/StringBuilder;
      31: aload_0
      32: getfield      #3                  // Field fromServer:I
      35: invokevirtual #15                 // Method java/lang/StringBuilder.append:(I)Ljava/lang/StringBuilder;
      38: ldc           #17                 // String  <->
      40: invokevirtual #14                 // Method java/lang/StringBuilder.append:(Ljava/lang/String;)Ljava/lang/StringBuilder;
      43: aload_0
      44: getfield      #6                  // Field toRegion:I
      47: invokevirtual #15                 // Method java/lang/StringBuilder.append:(I)Ljava/lang/StringBuilder;
      50: ldc           #16                 // String :
      52: invokevirtual #14                 // Method java/lang/StringBuilder.append:(Ljava/lang/String;)Ljava/lang/StringBuilder;
      55: aload_0
      56: getfield      #5                  // Field toServer:I
      59: invokevirtual #15                 // Method java/lang/StringBuilder.append:(I)Ljava/lang/StringBuilder;
      62: invokevirtual #18                 // Method java/lang/StringBuilder.toString:()Ljava/lang/String;
      65: areturn
}
