Compiled from "BasicMemStoreCompactionStrategy.java"
public class org.apache.hadoop.hbase.regionserver.BasicMemStoreCompactionStrategy extends org.apache.hadoop.hbase.regionserver.MemStoreCompactionStrategy {
  public org.apache.hadoop.hbase.regionserver.BasicMemStoreCompactionStrategy(org.apache.hadoop.conf.Configuration, java.lang.String);
    Code:
       0: aload_0
       1: aload_1
       2: aload_2
       3: invokespecial #1                  // Method org/apache/hadoop/hbase/regionserver/MemStoreCompactionStrategy."<init>":(Lorg/apache/hadoop/conf/Configuration;Ljava/lang/String;)V
       6: return

  public org.apache.hadoop.hbase.regionserver.MemStoreCompactionStrategy$Action getAction(org.apache.hadoop.hbase.regionserver.VersionedSegmentsList);
    Code:
       0: aload_0
       1: aload_1
       2: aload_0
       3: invokevirtual #2                  // Method getName:()Ljava/lang/String;
       6: invokevirtual #3                  // Method simpleMergeOrFlatten:(Lorg/apache/hadoop/hbase/regionserver/VersionedSegmentsList;Ljava/lang/String;)Lorg/apache/hadoop/hbase/regionserver/MemStoreCompactionStrategy$Action;
       9: areturn

  protected java.lang.String getName();
    Code:
       0: ldc           #5                  // String BASIC
       2: areturn
}
