Compiled from "BatchErrors.java"
class org.apache.hadoop.hbase.client.BatchErrors {
  final java.util.List<java.lang.Throwable> throwables;

  final java.util.List<org.apache.hadoop.hbase.client.Row> actions;

  final java.util.List<java.lang.String> addresses;

  org.apache.hadoop.hbase.client.BatchErrors();
    Code:
       0: aload_0
       1: invokespecial #1                  // Method java/lang/Object."<init>":()V
       4: aload_0
       5: new           #2                  // class java/util/ArrayList
       8: dup
       9: invokespecial #3                  // Method java/util/ArrayList."<init>":()V
      12: putfield      #4                  // Field throwables:Ljava/util/List;
      15: aload_0
      16: new           #2                  // class java/util/ArrayList
      19: dup
      20: invokespecial #3                  // Method java/util/ArrayList."<init>":()V
      23: putfield      #5                  // Field actions:Ljava/util/List;
      26: aload_0
      27: new           #2                  // class java/util/ArrayList
      30: dup
      31: invokespecial #3                  // Method java/util/ArrayList."<init>":()V
      34: putfield      #6                  // Field addresses:Ljava/util/List;
      37: return

  public synchronized void add(java.lang.Throwable, org.apache.hadoop.hbase.client.Row, org.apache.hadoop.hbase.ServerName);
    Code:
       0: aload_2
       1: ifnonnull     31
       4: new           #7                  // class java/lang/IllegalArgumentException
       7: dup
       8: new           #8                  // class java/lang/StringBuilder
      11: dup
      12: invokespecial #9                  // Method java/lang/StringBuilder."<init>":()V
      15: ldc           #10                 // String row cannot be null. location=
      17: invokevirtual #11                 // Method java/lang/StringBuilder.append:(Ljava/lang/String;)Ljava/lang/StringBuilder;
      20: aload_3
      21: invokevirtual #12                 // Method java/lang/StringBuilder.append:(Ljava/lang/Object;)Ljava/lang/StringBuilder;
      24: invokevirtual #13                 // Method java/lang/StringBuilder.toString:()Ljava/lang/String;
      27: invokespecial #14                 // Method java/lang/IllegalArgumentException."<init>":(Ljava/lang/String;)V
      30: athrow
      31: aload_0
      32: getfield      #4                  // Field throwables:Ljava/util/List;
      35: aload_1
      36: invokeinterface #15,  2           // InterfaceMethod java/util/List.add:(Ljava/lang/Object;)Z
      41: pop
      42: aload_0
      43: getfield      #5                  // Field actions:Ljava/util/List;
      46: aload_2
      47: invokeinterface #15,  2           // InterfaceMethod java/util/List.add:(Ljava/lang/Object;)Z
      52: pop
      53: aload_0
      54: getfield      #6                  // Field addresses:Ljava/util/List;
      57: aload_3
      58: ifnull        68
      61: aload_3
      62: invokevirtual #16                 // Method org/apache/hadoop/hbase/ServerName.toString:()Ljava/lang/String;
      65: goto          70
      68: ldc           #17                 // String null
      70: invokeinterface #15,  2           // InterfaceMethod java/util/List.add:(Ljava/lang/Object;)Z
      75: pop
      76: return

  public boolean hasErrors();
    Code:
       0: aload_0
       1: getfield      #4                  // Field throwables:Ljava/util/List;
       4: invokeinterface #18,  1           // InterfaceMethod java/util/List.isEmpty:()Z
       9: ifne          16
      12: iconst_1
      13: goto          17
      16: iconst_0
      17: ireturn

  synchronized org.apache.hadoop.hbase.client.RetriesExhaustedWithDetailsException makeException(boolean);
    Code:
       0: iload_1
       1: ifeq          46
       4: getstatic     #19                 // Field LOG:Lorg/slf4j/Logger;
       7: new           #8                  // class java/lang/StringBuilder
      10: dup
      11: invokespecial #9                  // Method java/lang/StringBuilder."<init>":()V
      14: ldc           #20                 // String Exception occurred! Exception details:
      16: invokevirtual #11                 // Method java/lang/StringBuilder.append:(Ljava/lang/String;)Ljava/lang/StringBuilder;
      19: aload_0
      20: getfield      #4                  // Field throwables:Ljava/util/List;
      23: invokevirtual #12                 // Method java/lang/StringBuilder.append:(Ljava/lang/Object;)Ljava/lang/StringBuilder;
      26: ldc           #21                 // String ;\nActions:
      28: invokevirtual #11                 // Method java/lang/StringBuilder.append:(Ljava/lang/String;)Ljava/lang/StringBuilder;
      31: aload_0
      32: getfield      #5                  // Field actions:Ljava/util/List;
      35: invokevirtual #12                 // Method java/lang/StringBuilder.append:(Ljava/lang/Object;)Ljava/lang/StringBuilder;
      38: invokevirtual #13                 // Method java/lang/StringBuilder.toString:()Ljava/lang/String;
      41: invokeinterface #22,  2           // InterfaceMethod org/slf4j/Logger.error:(Ljava/lang/String;)V
      46: new           #23                 // class org/apache/hadoop/hbase/client/RetriesExhaustedWithDetailsException
      49: dup
      50: new           #2                  // class java/util/ArrayList
      53: dup
      54: aload_0
      55: getfield      #4                  // Field throwables:Ljava/util/List;
      58: invokespecial #24                 // Method java/util/ArrayList."<init>":(Ljava/util/Collection;)V
      61: new           #2                  // class java/util/ArrayList
      64: dup
      65: aload_0
      66: getfield      #5                  // Field actions:Ljava/util/List;
      69: invokespecial #24                 // Method java/util/ArrayList."<init>":(Ljava/util/Collection;)V
      72: new           #2                  // class java/util/ArrayList
      75: dup
      76: aload_0
      77: getfield      #6                  // Field addresses:Ljava/util/List;
      80: invokespecial #24                 // Method java/util/ArrayList."<init>":(Ljava/util/Collection;)V
      83: invokespecial #25                 // Method org/apache/hadoop/hbase/client/RetriesExhaustedWithDetailsException."<init>":(Ljava/util/List;Ljava/util/List;Ljava/util/List;)V
      86: areturn

  public synchronized void clear();
    Code:
       0: aload_0
       1: getfield      #4                  // Field throwables:Ljava/util/List;
       4: invokeinterface #26,  1           // InterfaceMethod java/util/List.clear:()V
       9: aload_0
      10: getfield      #5                  // Field actions:Ljava/util/List;
      13: invokeinterface #26,  1           // InterfaceMethod java/util/List.clear:()V
      18: aload_0
      19: getfield      #6                  // Field addresses:Ljava/util/List;
      22: invokeinterface #26,  1           // InterfaceMethod java/util/List.clear:()V
      27: return

  public synchronized void merge(org.apache.hadoop.hbase.client.BatchErrors);
    Code:
       0: aload_0
       1: getfield      #4                  // Field throwables:Ljava/util/List;
       4: aload_1
       5: getfield      #4                  // Field throwables:Ljava/util/List;
       8: invokeinterface #27,  2           // InterfaceMethod java/util/List.addAll:(Ljava/util/Collection;)Z
      13: pop
      14: aload_0
      15: getfield      #5                  // Field actions:Ljava/util/List;
      18: aload_1
      19: getfield      #5                  // Field actions:Ljava/util/List;
      22: invokeinterface #27,  2           // InterfaceMethod java/util/List.addAll:(Ljava/util/Collection;)Z
      27: pop
      28: aload_0
      29: getfield      #6                  // Field addresses:Ljava/util/List;
      32: aload_1
      33: getfield      #6                  // Field addresses:Ljava/util/List;
      36: invokeinterface #27,  2           // InterfaceMethod java/util/List.addAll:(Ljava/util/Collection;)Z
      41: pop
      42: return

  static {};
    Code:
       0: ldc           #28                 // class org/apache/hadoop/hbase/client/BatchErrors
       2: invokestatic  #29                 // Method org/slf4j/LoggerFactory.getLogger:(Ljava/lang/Class;)Lorg/slf4j/Logger;
       5: putstatic     #19                 // Field LOG:Lorg/slf4j/Logger;
       8: return
}
