Compiled from "BinaryPrefixComparator.java"
public class org.apache.hadoop.hbase.filter.BinaryPrefixComparator extends org.apache.hadoop.hbase.filter.ByteArrayComparable {
  public org.apache.hadoop.hbase.filter.BinaryPrefixComparator(byte[]);
    Code:
       0: aload_0
       1: aload_1
       2: invokespecial #1                  // Method org/apache/hadoop/hbase/filter/ByteArrayComparable."<init>":([B)V
       5: return

  public int compareTo(byte[], int, int);
    Code:
       0: aload_0
       1: getfield      #2                  // Field value:[B
       4: iconst_0
       5: aload_0
       6: getfield      #2                  // Field value:[B
       9: arraylength
      10: aload_1
      11: iload_2
      12: aload_0
      13: getfield      #2                  // Field value:[B
      16: arraylength
      17: iload_3
      18: if_icmpgt     29
      21: aload_0
      22: getfield      #2                  // Field value:[B
      25: arraylength
      26: goto          30
      29: iload_3
      30: invokestatic  #3                  // Method org/apache/hadoop/hbase/util/Bytes.compareTo:([BII[BII)I
      33: ireturn

  public int compareTo(java.nio.ByteBuffer, int, int);
    Code:
       0: aload_0
       1: getfield      #2                  // Field value:[B
       4: arraylength
       5: iload_3
       6: if_icmpgt     15
       9: aload_0
      10: getfield      #2                  // Field value:[B
      13: arraylength
      14: istore_3
      15: aload_0
      16: getfield      #2                  // Field value:[B
      19: iconst_0
      20: aload_0
      21: getfield      #2                  // Field value:[B
      24: arraylength
      25: aload_1
      26: iload_2
      27: iload_3
      28: invokestatic  #4                  // Method org/apache/hadoop/hbase/util/ByteBufferUtils.compareTo:([BIILjava/nio/ByteBuffer;II)I
      31: ireturn

  public byte[] toByteArray();
    Code:
       0: invokestatic  #5                  // Method org/apache/hadoop/hbase/shaded/protobuf/generated/ComparatorProtos$BinaryPrefixComparator.newBuilder:()Lorg/apache/hadoop/hbase/shaded/protobuf/generated/ComparatorProtos$BinaryPrefixComparator$Builder;
       3: astore_1
       4: aload_1
       5: aload_0
       6: getfield      #2                  // Field value:[B
       9: invokestatic  #6                  // Method org/apache/hadoop/hbase/shaded/protobuf/ProtobufUtil.toByteArrayComparable:([B)Lorg/apache/hadoop/hbase/shaded/protobuf/generated/ComparatorProtos$ByteArrayComparable;
      12: invokevirtual #7                  // Method org/apache/hadoop/hbase/shaded/protobuf/generated/ComparatorProtos$BinaryPrefixComparator$Builder.setComparable:(Lorg/apache/hadoop/hbase/shaded/protobuf/generated/ComparatorProtos$ByteArrayComparable;)Lorg/apache/hadoop/hbase/shaded/protobuf/generated/ComparatorProtos$BinaryPrefixComparator$Builder;
      15: pop
      16: aload_1
      17: invokevirtual #8                  // Method org/apache/hadoop/hbase/shaded/protobuf/generated/ComparatorProtos$BinaryPrefixComparator$Builder.build:()Lorg/apache/hadoop/hbase/shaded/protobuf/generated/ComparatorProtos$BinaryPrefixComparator;
      20: invokevirtual #9                  // Method org/apache/hadoop/hbase/shaded/protobuf/generated/ComparatorProtos$BinaryPrefixComparator.toByteArray:()[B
      23: areturn

  public static org.apache.hadoop.hbase.filter.BinaryPrefixComparator parseFrom(byte[]) throws org.apache.hadoop.hbase.exceptions.DeserializationException;
    Code:
       0: aload_0
       1: invokestatic  #10                 // Method org/apache/hadoop/hbase/shaded/protobuf/generated/ComparatorProtos$BinaryPrefixComparator.parseFrom:([B)Lorg/apache/hadoop/hbase/shaded/protobuf/generated/ComparatorProtos$BinaryPrefixComparator;
       4: astore_1
       5: goto          18
       8: astore_2
       9: new           #12                 // class org/apache/hadoop/hbase/exceptions/DeserializationException
      12: dup
      13: aload_2
      14: invokespecial #13                 // Method org/apache/hadoop/hbase/exceptions/DeserializationException."<init>":(Ljava/lang/Throwable;)V
      17: athrow
      18: new           #14                 // class org/apache/hadoop/hbase/filter/BinaryPrefixComparator
      21: dup
      22: aload_1
      23: invokevirtual #15                 // Method org/apache/hadoop/hbase/shaded/protobuf/generated/ComparatorProtos$BinaryPrefixComparator.getComparable:()Lorg/apache/hadoop/hbase/shaded/protobuf/generated/ComparatorProtos$ByteArrayComparable;
      26: invokevirtual #16                 // Method org/apache/hadoop/hbase/shaded/protobuf/generated/ComparatorProtos$ByteArrayComparable.getValue:()Lorg/apache/hbase/thirdparty/com/google/protobuf/ByteString;
      29: invokevirtual #17                 // Method org/apache/hbase/thirdparty/com/google/protobuf/ByteString.toByteArray:()[B
      32: invokespecial #18                 // Method "<init>":([B)V
      35: areturn
    Exception table:
       from    to  target type
           0     5     8   Class org/apache/hbase/thirdparty/com/google/protobuf/InvalidProtocolBufferException

  boolean areSerializedFieldsEqual(org.apache.hadoop.hbase.filter.ByteArrayComparable);
    Code:
       0: aload_1
       1: aload_0
       2: if_acmpne     7
       5: iconst_1
       6: ireturn
       7: aload_1
       8: instanceof    #14                 // class org/apache/hadoop/hbase/filter/BinaryPrefixComparator
      11: ifne          16
      14: iconst_0
      15: ireturn
      16: aload_0
      17: aload_1
      18: invokespecial #19                 // Method org/apache/hadoop/hbase/filter/ByteArrayComparable.areSerializedFieldsEqual:(Lorg/apache/hadoop/hbase/filter/ByteArrayComparable;)Z
      21: ireturn
}
