Compiled from "BoundedCompletionService.java"
class org.apache.hadoop.hbase.util.BoundedCompletionService$QueueingFuture extends java.util.concurrent.FutureTask<V> {
  final org.apache.hadoop.hbase.util.BoundedCompletionService this$0;

  public org.apache.hadoop.hbase.util.BoundedCompletionService$QueueingFuture(java.util.concurrent.Callable<V>);
    Code:
       0: aload_0
       1: aload_1
       2: putfield      #1                  // Field this$0:Lorg/apache/hadoop/hbase/util/BoundedCompletionService;
       5: aload_0
       6: aload_2
       7: invokespecial #2                  // Method java/util/concurrent/FutureTask."<init>":(Ljava/util/concurrent/Callable;)V
      10: return

  protected void done();
    Code:
       0: aload_0
       1: getfield      #1                  // Field this$0:Lorg/apache/hadoop/hbase/util/BoundedCompletionService;
       4: invokestatic  #3                  // Method org/apache/hadoop/hbase/util/BoundedCompletionService.access$000:(Lorg/apache/hadoop/hbase/util/BoundedCompletionService;)Ljava/util/concurrent/BlockingQueue;
       7: aload_0
       8: invokeinterface #4,  2            // InterfaceMethod java/util/concurrent/BlockingQueue.add:(Ljava/lang/Object;)Z
      13: pop
      14: return
}
