Compiled from "BucketAllocator.java"
class org.apache.hadoop.hbase.io.hfile.bucket.BucketAllocator$1 implements java.util.Comparator<java.lang.Integer> {
  final org.apache.hadoop.hbase.io.hfile.bucket.BucketAllocator this$0;

  org.apache.hadoop.hbase.io.hfile.bucket.BucketAllocator$1(org.apache.hadoop.hbase.io.hfile.bucket.BucketAllocator);
    Code:
       0: aload_0
       1: aload_1
       2: putfield      #1                  // Field this$0:Lorg/apache/hadoop/hbase/io/hfile/bucket/BucketAllocator;
       5: aload_0
       6: invokespecial #2                  // Method java/lang/Object."<init>":()V
       9: return

  public int compare(java.lang.Integer, java.lang.Integer);
    Code:
       0: aload_0
       1: getfield      #1                  // Field this$0:Lorg/apache/hadoop/hbase/io/hfile/bucket/BucketAllocator;
       4: invokestatic  #3                  // Method org/apache/hadoop/hbase/io/hfile/bucket/BucketAllocator.access$500:(Lorg/apache/hadoop/hbase/io/hfile/bucket/BucketAllocator;)[Lorg/apache/hadoop/hbase/io/hfile/bucket/BucketAllocator$Bucket;
       7: aload_1
       8: invokevirtual #4                  // Method java/lang/Integer.intValue:()I
      11: aaload
      12: invokestatic  #5                  // Method org/apache/hadoop/hbase/io/hfile/bucket/BucketAllocator$Bucket.access$600:(Lorg/apache/hadoop/hbase/io/hfile/bucket/BucketAllocator$Bucket;)I
      15: i2f
      16: aload_0
      17: getfield      #1                  // Field this$0:Lorg/apache/hadoop/hbase/io/hfile/bucket/BucketAllocator;
      20: invokestatic  #3                  // Method org/apache/hadoop/hbase/io/hfile/bucket/BucketAllocator.access$500:(Lorg/apache/hadoop/hbase/io/hfile/bucket/BucketAllocator;)[Lorg/apache/hadoop/hbase/io/hfile/bucket/BucketAllocator$Bucket;
      23: aload_1
      24: invokevirtual #4                  // Method java/lang/Integer.intValue:()I
      27: aaload
      28: invokestatic  #6                  // Method org/apache/hadoop/hbase/io/hfile/bucket/BucketAllocator$Bucket.access$700:(Lorg/apache/hadoop/hbase/io/hfile/bucket/BucketAllocator$Bucket;)I
      31: i2f
      32: fdiv
      33: aload_0
      34: getfield      #1                  // Field this$0:Lorg/apache/hadoop/hbase/io/hfile/bucket/BucketAllocator;
      37: invokestatic  #3                  // Method org/apache/hadoop/hbase/io/hfile/bucket/BucketAllocator.access$500:(Lorg/apache/hadoop/hbase/io/hfile/bucket/BucketAllocator;)[Lorg/apache/hadoop/hbase/io/hfile/bucket/BucketAllocator$Bucket;
      40: aload_2
      41: invokevirtual #4                  // Method java/lang/Integer.intValue:()I
      44: aaload
      45: invokestatic  #5                  // Method org/apache/hadoop/hbase/io/hfile/bucket/BucketAllocator$Bucket.access$600:(Lorg/apache/hadoop/hbase/io/hfile/bucket/BucketAllocator$Bucket;)I
      48: i2f
      49: aload_0
      50: getfield      #1                  // Field this$0:Lorg/apache/hadoop/hbase/io/hfile/bucket/BucketAllocator;
      53: invokestatic  #3                  // Method org/apache/hadoop/hbase/io/hfile/bucket/BucketAllocator.access$500:(Lorg/apache/hadoop/hbase/io/hfile/bucket/BucketAllocator;)[Lorg/apache/hadoop/hbase/io/hfile/bucket/BucketAllocator$Bucket;
      56: aload_2
      57: invokevirtual #4                  // Method java/lang/Integer.intValue:()I
      60: aaload
      61: invokestatic  #6                  // Method org/apache/hadoop/hbase/io/hfile/bucket/BucketAllocator$Bucket.access$700:(Lorg/apache/hadoop/hbase/io/hfile/bucket/BucketAllocator$Bucket;)I
      64: i2f
      65: fdiv
      66: invokestatic  #7                  // Method java/lang/Float.compare:(FF)I
      69: ireturn

  public int compare(java.lang.Object, java.lang.Object);
    Code:
       0: aload_0
       1: aload_1
       2: checkcast     #8                  // class java/lang/Integer
       5: aload_2
       6: checkcast     #8                  // class java/lang/Integer
       9: invokevirtual #9                  // Method compare:(Ljava/lang/Integer;Ljava/lang/Integer;)I
      12: ireturn
}
