Compiled from "BucketAllocator.java"
public final class org.apache.hadoop.hbase.io.hfile.bucket.BucketAllocator {
  public static final int FEWEST_ITEMS_IN_BUCKET;

  static final boolean $assertionsDisabled;

  public org.apache.hadoop.hbase.io.hfile.bucket.BucketAllocator$BucketSizeInfo roundUpToBucketSizeInfo(int);
    Code:
       0: iconst_0
       1: istore_2
       2: iload_2
       3: aload_0
       4: getfield      #4                  // Field bucketSizes:[I
       7: arraylength
       8: if_icmpge     34
      11: iload_1
      12: aload_0
      13: getfield      #4                  // Field bucketSizes:[I
      16: iload_2
      17: iaload
      18: if_icmpgt     28
      21: aload_0
      22: getfield      #5                  // Field bucketSizeInfos:[Lorg/apache/hadoop/hbase/io/hfile/bucket/BucketAllocator$BucketSizeInfo;
      25: iload_2
      26: aaload
      27: areturn
      28: iinc          2, 1
      31: goto          2
      34: aconst_null
      35: areturn

  org.apache.hadoop.hbase.io.hfile.bucket.BucketAllocator(long, int[]) throws org.apache.hadoop.hbase.io.hfile.bucket.BucketAllocatorException;
    Code:
       0: aload_0
       1: invokespecial #6                  // Method java/lang/Object."<init>":()V
       4: aload_0
       5: lconst_0
       6: putfield      #7                  // Field usedSize:J
       9: aload_0
      10: aload_3
      11: ifnonnull     20
      14: getstatic     #8                  // Field DEFAULT_BUCKET_SIZES:[I
      17: goto          21
      20: aload_3
      21: putfield      #4                  // Field bucketSizes:[I
      24: aload_0
      25: getfield      #4                  // Field bucketSizes:[I
      28: invokestatic  #9                  // Method java/util/Arrays.sort:([I)V
      31: aload_0
      32: aload_0
      33: getfield      #4                  // Field bucketSizes:[I
      36: invokestatic  #10                 // Method org/apache/hbase/thirdparty/com/google/common/primitives/Ints.max:([I)I
      39: putfield      #11                 // Field bigItemSize:I
      42: aload_0
      43: ldc2_w        #13                 // long 4l
      46: aload_0
      47: getfield      #11                 // Field bigItemSize:I
      50: i2l
      51: lmul
      52: putfield      #3                  // Field bucketCapacity:J
      55: aload_0
      56: lload_1
      57: aload_0
      58: getfield      #3                  // Field bucketCapacity:J
      61: ldiv
      62: l2i
      63: anewarray     #15                 // class org/apache/hadoop/hbase/io/hfile/bucket/BucketAllocator$Bucket
      66: putfield      #1                  // Field buckets:[Lorg/apache/hadoop/hbase/io/hfile/bucket/BucketAllocator$Bucket;
      69: aload_0
      70: getfield      #1                  // Field buckets:[Lorg/apache/hadoop/hbase/io/hfile/bucket/BucketAllocator$Bucket;
      73: arraylength
      74: aload_0
      75: getfield      #4                  // Field bucketSizes:[I
      78: arraylength
      79: if_icmpge     131
      82: new           #16                 // class org/apache/hadoop/hbase/io/hfile/bucket/BucketAllocatorException
      85: dup
      86: new           #17                 // class java/lang/StringBuilder
      89: dup
      90: invokespecial #18                 // Method java/lang/StringBuilder."<init>":()V
      93: ldc           #19                 // String Bucket allocator size too small (
      95: invokevirtual #20                 // Method java/lang/StringBuilder.append:(Ljava/lang/String;)Ljava/lang/StringBuilder;
      98: aload_0
      99: getfield      #1                  // Field buckets:[Lorg/apache/hadoop/hbase/io/hfile/bucket/BucketAllocator$Bucket;
     102: arraylength
     103: invokevirtual #21                 // Method java/lang/StringBuilder.append:(I)Ljava/lang/StringBuilder;
     106: ldc           #22                 // String ); must have room for at least
     108: invokevirtual #20                 // Method java/lang/StringBuilder.append:(Ljava/lang/String;)Ljava/lang/StringBuilder;
     111: aload_0
     112: getfield      #4                  // Field bucketSizes:[I
     115: arraylength
     116: invokevirtual #21                 // Method java/lang/StringBuilder.append:(I)Ljava/lang/StringBuilder;
     119: ldc           #23                 // String  buckets
     121: invokevirtual #20                 // Method java/lang/StringBuilder.append:(Ljava/lang/String;)Ljava/lang/StringBuilder;
     124: invokevirtual #24                 // Method java/lang/StringBuilder.toString:()Ljava/lang/String;
     127: invokespecial #25                 // Method org/apache/hadoop/hbase/io/hfile/bucket/BucketAllocatorException."<init>":(Ljava/lang/String;)V
     130: athrow
     131: aload_0
     132: aload_0
     133: getfield      #4                  // Field bucketSizes:[I
     136: arraylength
     137: anewarray     #26                 // class org/apache/hadoop/hbase/io/hfile/bucket/BucketAllocator$BucketSizeInfo
     140: putfield      #5                  // Field bucketSizeInfos:[Lorg/apache/hadoop/hbase/io/hfile/bucket/BucketAllocator$BucketSizeInfo;
     143: iconst_0
     144: istore        4
     146: iload         4
     148: aload_0
     149: getfield      #4                  // Field bucketSizes:[I
     152: arraylength
     153: if_icmpge     179
     156: aload_0
     157: getfield      #5                  // Field bucketSizeInfos:[Lorg/apache/hadoop/hbase/io/hfile/bucket/BucketAllocator$BucketSizeInfo;
     160: iload         4
     162: new           #26                 // class org/apache/hadoop/hbase/io/hfile/bucket/BucketAllocator$BucketSizeInfo
     165: dup
     166: aload_0
     167: iload         4
     169: invokespecial #27                 // Method org/apache/hadoop/hbase/io/hfile/bucket/BucketAllocator$BucketSizeInfo."<init>":(Lorg/apache/hadoop/hbase/io/hfile/bucket/BucketAllocator;I)V
     172: aastore
     173: iinc          4, 1
     176: goto          146
     179: iconst_0
     180: istore        4
     182: iload         4
     184: aload_0
     185: getfield      #1                  // Field buckets:[Lorg/apache/hadoop/hbase/io/hfile/bucket/BucketAllocator$Bucket;
     188: arraylength
     189: if_icmpge     257
     192: aload_0
     193: getfield      #1                  // Field buckets:[Lorg/apache/hadoop/hbase/io/hfile/bucket/BucketAllocator$Bucket;
     196: iload         4
     198: new           #15                 // class org/apache/hadoop/hbase/io/hfile/bucket/BucketAllocator$Bucket
     201: dup
     202: aload_0
     203: getfield      #3                  // Field bucketCapacity:J
     206: iload         4
     208: i2l
     209: lmul
     210: invokespecial #28                 // Method org/apache/hadoop/hbase/io/hfile/bucket/BucketAllocator$Bucket."<init>":(J)V
     213: aastore
     214: aload_0
     215: getfield      #5                  // Field bucketSizeInfos:[Lorg/apache/hadoop/hbase/io/hfile/bucket/BucketAllocator$BucketSizeInfo;
     218: iload         4
     220: aload_0
     221: getfield      #4                  // Field bucketSizes:[I
     224: arraylength
     225: if_icmpge     233
     228: iload         4
     230: goto          240
     233: aload_0
     234: getfield      #4                  // Field bucketSizes:[I
     237: arraylength
     238: iconst_1
     239: isub
     240: aaload
     241: aload_0
     242: getfield      #1                  // Field buckets:[Lorg/apache/hadoop/hbase/io/hfile/bucket/BucketAllocator$Bucket;
     245: iload         4
     247: aaload
     248: invokevirtual #29                 // Method org/apache/hadoop/hbase/io/hfile/bucket/BucketAllocator$BucketSizeInfo.instantiateBucket:(Lorg/apache/hadoop/hbase/io/hfile/bucket/BucketAllocator$Bucket;)V
     251: iinc          4, 1
     254: goto          182
     257: aload_0
     258: aload_0
     259: getfield      #1                  // Field buckets:[Lorg/apache/hadoop/hbase/io/hfile/bucket/BucketAllocator$Bucket;
     262: arraylength
     263: i2l
     264: aload_0
     265: getfield      #3                  // Field bucketCapacity:J
     268: lmul
     269: putfield      #30                 // Field totalSize:J
     272: getstatic     #31                 // Field LOG:Lorg/slf4j/Logger;
     275: invokeinterface #32,  1           // InterfaceMethod org/slf4j/Logger.isInfoEnabled:()Z
     280: ifeq          364
     283: getstatic     #31                 // Field LOG:Lorg/slf4j/Logger;
     286: new           #17                 // class java/lang/StringBuilder
     289: dup
     290: invokespecial #18                 // Method java/lang/StringBuilder."<init>":()V
     293: ldc           #33                 // String Cache totalSize=
     295: invokevirtual #20                 // Method java/lang/StringBuilder.append:(Ljava/lang/String;)Ljava/lang/StringBuilder;
     298: aload_0
     299: getfield      #30                 // Field totalSize:J
     302: invokevirtual #34                 // Method java/lang/StringBuilder.append:(J)Ljava/lang/StringBuilder;
     305: ldc           #35                 // String , buckets=
     307: invokevirtual #20                 // Method java/lang/StringBuilder.append:(Ljava/lang/String;)Ljava/lang/StringBuilder;
     310: aload_0
     311: getfield      #1                  // Field buckets:[Lorg/apache/hadoop/hbase/io/hfile/bucket/BucketAllocator$Bucket;
     314: arraylength
     315: invokevirtual #21                 // Method java/lang/StringBuilder.append:(I)Ljava/lang/StringBuilder;
     318: ldc           #36                 // String , bucket capacity=
     320: invokevirtual #20                 // Method java/lang/StringBuilder.append:(Ljava/lang/String;)Ljava/lang/StringBuilder;
     323: aload_0
     324: getfield      #3                  // Field bucketCapacity:J
     327: invokevirtual #34                 // Method java/lang/StringBuilder.append:(J)Ljava/lang/StringBuilder;
     330: ldc           #37                 // String =(
     332: invokevirtual #20                 // Method java/lang/StringBuilder.append:(Ljava/lang/String;)Ljava/lang/StringBuilder;
     335: iconst_4
     336: invokevirtual #21                 // Method java/lang/StringBuilder.append:(I)Ljava/lang/StringBuilder;
     339: ldc           #38                 // String *
     341: invokevirtual #20                 // Method java/lang/StringBuilder.append:(Ljava/lang/String;)Ljava/lang/StringBuilder;
     344: aload_0
     345: getfield      #11                 // Field bigItemSize:I
     348: invokevirtual #21                 // Method java/lang/StringBuilder.append:(I)Ljava/lang/StringBuilder;
     351: ldc           #39                 // String )=(FEWEST_ITEMS_IN_BUCKET*(largest configured bucketcache size))
     353: invokevirtual #20                 // Method java/lang/StringBuilder.append:(Ljava/lang/String;)Ljava/lang/StringBuilder;
     356: invokevirtual #24                 // Method java/lang/StringBuilder.toString:()Ljava/lang/String;
     359: invokeinterface #40,  2           // InterfaceMethod org/slf4j/Logger.info:(Ljava/lang/String;)V
     364: return

  org.apache.hadoop.hbase.io.hfile.bucket.BucketAllocator(long, int[], java.util.Map<org.apache.hadoop.hbase.io.hfile.BlockCacheKey, org.apache.hadoop.hbase.io.hfile.bucket.BucketCache$BucketEntry>, java.util.concurrent.atomic.LongAdder) throws org.apache.hadoop.hbase.io.hfile.bucket.BucketAllocatorException;
    Code:
       0: aload_0
       1: lload_1
       2: aload_3
       3: invokespecial #41                 // Method "<init>":(J[I)V
       6: aload_0
       7: getfield      #1                  // Field buckets:[Lorg/apache/hadoop/hbase/io/hfile/bucket/BucketAllocator$Bucket;
      10: arraylength
      11: newarray       boolean
      13: astore        6
      15: iconst_0
      16: istore        7
      18: iconst_0
      19: istore        8
      21: aload         4
      23: invokeinterface #42,  1           // InterfaceMethod java/util/Map.entrySet:()Ljava/util/Set;
      28: invokeinterface #43,  1           // InterfaceMethod java/util/Set.iterator:()Ljava/util/Iterator;
      33: astore        9
      35: aload         9
      37: invokeinterface #44,  1           // InterfaceMethod java/util/Iterator.hasNext:()Z
      42: ifeq          359
      45: aload         9
      47: invokeinterface #45,  1           // InterfaceMethod java/util/Iterator.next:()Ljava/lang/Object;
      52: checkcast     #46                 // class java/util/Map$Entry
      55: astore        10
      57: aload         10
      59: invokeinterface #47,  1           // InterfaceMethod java/util/Map$Entry.getValue:()Ljava/lang/Object;
      64: checkcast     #48                 // class org/apache/hadoop/hbase/io/hfile/bucket/BucketCache$BucketEntry
      67: invokevirtual #49                 // Method org/apache/hadoop/hbase/io/hfile/bucket/BucketCache$BucketEntry.offset:()J
      70: lstore        11
      72: aload         10
      74: invokeinterface #47,  1           // InterfaceMethod java/util/Map$Entry.getValue:()Ljava/lang/Object;
      79: checkcast     #48                 // class org/apache/hadoop/hbase/io/hfile/bucket/BucketCache$BucketEntry
      82: invokevirtual #50                 // Method org/apache/hadoop/hbase/io/hfile/bucket/BucketCache$BucketEntry.getLength:()I
      85: istore        13
      87: iconst_m1
      88: istore        14
      90: iconst_0
      91: istore        15
      93: iload         15
      95: aload_0
      96: getfield      #4                  // Field bucketSizes:[I
      99: arraylength
     100: if_icmpge     128
     103: iload         13
     105: aload_0
     106: getfield      #4                  // Field bucketSizes:[I
     109: iload         15
     111: iaload
     112: if_icmpgt     122
     115: iload         15
     117: istore        14
     119: goto          128
     122: iinc          15, 1
     125: goto          93
     128: iload         14
     130: iconst_m1
     131: if_icmpne     147
     134: iinc          7, 1
     137: aload         9
     139: invokeinterface #51,  1           // InterfaceMethod java/util/Iterator.remove:()V
     144: goto          35
     147: lload         11
     149: aload_0
     150: getfield      #3                  // Field bucketCapacity:J
     153: ldiv
     154: l2i
     155: istore        15
     157: iload         15
     159: iflt          172
     162: iload         15
     164: aload_0
     165: getfield      #1                  // Field buckets:[Lorg/apache/hadoop/hbase/io/hfile/bucket/BucketAllocator$Bucket;
     168: arraylength
     169: if_icmplt     185
     172: iinc          8, 1
     175: aload         9
     177: invokeinterface #51,  1           // InterfaceMethod java/util/Iterator.remove:()V
     182: goto          35
     185: aload_0
     186: getfield      #1                  // Field buckets:[Lorg/apache/hadoop/hbase/io/hfile/bucket/BucketAllocator$Bucket;
     189: iload         15
     191: aaload
     192: astore        16
     194: aload         6
     196: iload         15
     198: baload
     199: ifeq          222
     202: aload         16
     204: invokevirtual #52                 // Method org/apache/hadoop/hbase/io/hfile/bucket/BucketAllocator$Bucket.sizeIndex:()I
     207: iload         14
     209: if_icmpeq     304
     212: new           #16                 // class org/apache/hadoop/hbase/io/hfile/bucket/BucketAllocatorException
     215: dup
     216: ldc           #53                 // String Inconsistent allocation in bucket map;
     218: invokespecial #25                 // Method org/apache/hadoop/hbase/io/hfile/bucket/BucketAllocatorException."<init>":(Ljava/lang/String;)V
     221: athrow
     222: aload         16
     224: invokevirtual #54                 // Method org/apache/hadoop/hbase/io/hfile/bucket/BucketAllocator$Bucket.isCompletelyFree:()Z
     227: ifne          263
     230: new           #16                 // class org/apache/hadoop/hbase/io/hfile/bucket/BucketAllocatorException
     233: dup
     234: new           #17                 // class java/lang/StringBuilder
     237: dup
     238: invokespecial #18                 // Method java/lang/StringBuilder."<init>":()V
     241: ldc           #55                 // String Reconfiguring bucket
     243: invokevirtual #20                 // Method java/lang/StringBuilder.append:(Ljava/lang/String;)Ljava/lang/StringBuilder;
     246: iload         15
     248: invokevirtual #21                 // Method java/lang/StringBuilder.append:(I)Ljava/lang/StringBuilder;
     251: ldc           #56                 // String  but it's already allocated; corrupt data
     253: invokevirtual #20                 // Method java/lang/StringBuilder.append:(Ljava/lang/String;)Ljava/lang/StringBuilder;
     256: invokevirtual #24                 // Method java/lang/StringBuilder.toString:()Ljava/lang/String;
     259: invokespecial #25                 // Method org/apache/hadoop/hbase/io/hfile/bucket/BucketAllocatorException."<init>":(Ljava/lang/String;)V
     262: athrow
     263: aload_0
     264: getfield      #5                  // Field bucketSizeInfos:[Lorg/apache/hadoop/hbase/io/hfile/bucket/BucketAllocator$BucketSizeInfo;
     267: iload         14
     269: aaload
     270: astore        17
     272: aload_0
     273: getfield      #5                  // Field bucketSizeInfos:[Lorg/apache/hadoop/hbase/io/hfile/bucket/BucketAllocator$BucketSizeInfo;
     276: aload         16
     278: invokevirtual #52                 // Method org/apache/hadoop/hbase/io/hfile/bucket/BucketAllocator$Bucket.sizeIndex:()I
     281: aaload
     282: astore        18
     284: aload         18
     286: aload         16
     288: invokestatic  #57                 // Method org/apache/hadoop/hbase/io/hfile/bucket/BucketAllocator$BucketSizeInfo.access$400:(Lorg/apache/hadoop/hbase/io/hfile/bucket/BucketAllocator$BucketSizeInfo;Lorg/apache/hadoop/hbase/io/hfile/bucket/BucketAllocator$Bucket;)V
     291: aload         17
     293: aload         16
     295: invokevirtual #29                 // Method org/apache/hadoop/hbase/io/hfile/bucket/BucketAllocator$BucketSizeInfo.instantiateBucket:(Lorg/apache/hadoop/hbase/io/hfile/bucket/BucketAllocator$Bucket;)V
     298: aload         6
     300: iload         15
     302: iconst_1
     303: bastore
     304: aload         5
     306: iload         13
     308: i2l
     309: invokevirtual #58                 // Method java/util/concurrent/atomic/LongAdder.add:(J)V
     312: aload_0
     313: getfield      #1                  // Field buckets:[Lorg/apache/hadoop/hbase/io/hfile/bucket/BucketAllocator$Bucket;
     316: iload         15
     318: aaload
     319: lload         11
     321: invokevirtual #59                 // Method org/apache/hadoop/hbase/io/hfile/bucket/BucketAllocator$Bucket.addAllocation:(J)V
     324: aload_0
     325: dup
     326: getfield      #7                  // Field usedSize:J
     329: aload_0
     330: getfield      #1                  // Field buckets:[Lorg/apache/hadoop/hbase/io/hfile/bucket/BucketAllocator$Bucket;
     333: iload         15
     335: aaload
     336: invokevirtual #60                 // Method org/apache/hadoop/hbase/io/hfile/bucket/BucketAllocator$Bucket.getItemAllocationSize:()I
     339: i2l
     340: ladd
     341: putfield      #7                  // Field usedSize:J
     344: aload_0
     345: getfield      #5                  // Field bucketSizeInfos:[Lorg/apache/hadoop/hbase/io/hfile/bucket/BucketAllocator$BucketSizeInfo;
     348: iload         14
     350: aaload
     351: aload         16
     353: invokevirtual #61                 // Method org/apache/hadoop/hbase/io/hfile/bucket/BucketAllocator$BucketSizeInfo.blockAllocated:(Lorg/apache/hadoop/hbase/io/hfile/bucket/BucketAllocator$Bucket;)V
     356: goto          35
     359: iload         7
     361: ifle          397
     364: getstatic     #31                 // Field LOG:Lorg/slf4j/Logger;
     367: new           #17                 // class java/lang/StringBuilder
     370: dup
     371: invokespecial #18                 // Method java/lang/StringBuilder."<init>":()V
     374: ldc           #62                 // String There are
     376: invokevirtual #20                 // Method java/lang/StringBuilder.append:(Ljava/lang/String;)Ljava/lang/StringBuilder;
     379: iload         7
     381: invokevirtual #21                 // Method java/lang/StringBuilder.append:(I)Ljava/lang/StringBuilder;
     384: ldc           #63                 // String  blocks which can't be rebuilt because there is no matching bucket size for these blocks
     386: invokevirtual #20                 // Method java/lang/StringBuilder.append:(Ljava/lang/String;)Ljava/lang/StringBuilder;
     389: invokevirtual #24                 // Method java/lang/StringBuilder.toString:()Ljava/lang/String;
     392: invokeinterface #64,  2           // InterfaceMethod org/slf4j/Logger.warn:(Ljava/lang/String;)V
     397: iload         8
     399: ifle          435
     402: getstatic     #31                 // Field LOG:Lorg/slf4j/Logger;
     405: new           #17                 // class java/lang/StringBuilder
     408: dup
     409: invokespecial #18                 // Method java/lang/StringBuilder."<init>":()V
     412: ldc           #62                 // String There are
     414: invokevirtual #20                 // Method java/lang/StringBuilder.append:(Ljava/lang/String;)Ljava/lang/StringBuilder;
     417: iload         8
     419: invokevirtual #21                 // Method java/lang/StringBuilder.append:(I)Ljava/lang/StringBuilder;
     422: ldc           #65                 // String  blocks which can't be rebuilt - did you shrink the cache?
     424: invokevirtual #20                 // Method java/lang/StringBuilder.append:(Ljava/lang/String;)Ljava/lang/StringBuilder;
     427: invokevirtual #24                 // Method java/lang/StringBuilder.toString:()Ljava/lang/String;
     430: invokeinterface #64,  2           // InterfaceMethod org/slf4j/Logger.warn:(Ljava/lang/String;)V
     435: return

  public java.lang.String toString();
    Code:
       0: new           #17                 // class java/lang/StringBuilder
       3: dup
       4: sipush        1024
       7: invokespecial #66                 // Method java/lang/StringBuilder."<init>":(I)V
      10: astore_1
      11: iconst_0
      12: istore_2
      13: iload_2
      14: aload_0
      15: getfield      #1                  // Field buckets:[Lorg/apache/hadoop/hbase/io/hfile/bucket/BucketAllocator$Bucket;
      18: arraylength
      19: if_icmpge     95
      22: aload_0
      23: getfield      #1                  // Field buckets:[Lorg/apache/hadoop/hbase/io/hfile/bucket/BucketAllocator$Bucket;
      26: iload_2
      27: aaload
      28: astore_3
      29: iload_2
      30: ifle          40
      33: aload_1
      34: ldc           #67                 // String ,
      36: invokevirtual #20                 // Method java/lang/StringBuilder.append:(Ljava/lang/String;)Ljava/lang/StringBuilder;
      39: pop
      40: aload_1
      41: ldc           #68                 // String bucket.
      43: invokevirtual #20                 // Method java/lang/StringBuilder.append:(Ljava/lang/String;)Ljava/lang/StringBuilder;
      46: iload_2
      47: invokevirtual #21                 // Method java/lang/StringBuilder.append:(I)Ljava/lang/StringBuilder;
      50: ldc           #69                 // String : size=
      52: invokevirtual #20                 // Method java/lang/StringBuilder.append:(Ljava/lang/String;)Ljava/lang/StringBuilder;
      55: aload_3
      56: invokevirtual #60                 // Method org/apache/hadoop/hbase/io/hfile/bucket/BucketAllocator$Bucket.getItemAllocationSize:()I
      59: invokevirtual #21                 // Method java/lang/StringBuilder.append:(I)Ljava/lang/StringBuilder;
      62: pop
      63: aload_1
      64: ldc           #70                 // String , freeCount=
      66: invokevirtual #20                 // Method java/lang/StringBuilder.append:(Ljava/lang/String;)Ljava/lang/StringBuilder;
      69: aload_3
      70: invokevirtual #71                 // Method org/apache/hadoop/hbase/io/hfile/bucket/BucketAllocator$Bucket.freeCount:()I
      73: invokevirtual #21                 // Method java/lang/StringBuilder.append:(I)Ljava/lang/StringBuilder;
      76: ldc           #72                 // String , used=
      78: invokevirtual #20                 // Method java/lang/StringBuilder.append:(Ljava/lang/String;)Ljava/lang/StringBuilder;
      81: aload_3
      82: invokevirtual #73                 // Method org/apache/hadoop/hbase/io/hfile/bucket/BucketAllocator$Bucket.usedCount:()I
      85: invokevirtual #21                 // Method java/lang/StringBuilder.append:(I)Ljava/lang/StringBuilder;
      88: pop
      89: iinc          2, 1
      92: goto          13
      95: aload_1
      96: invokevirtual #24                 // Method java/lang/StringBuilder.toString:()Ljava/lang/String;
      99: areturn

  public long getUsedSize();
    Code:
       0: aload_0
       1: getfield      #7                  // Field usedSize:J
       4: lreturn

  public long getFreeSize();
    Code:
       0: aload_0
       1: getfield      #30                 // Field totalSize:J
       4: aload_0
       5: invokevirtual #74                 // Method getUsedSize:()J
       8: lsub
       9: lreturn

  public long getTotalSize();
    Code:
       0: aload_0
       1: getfield      #30                 // Field totalSize:J
       4: lreturn

  public synchronized long allocateBlock(int) throws org.apache.hadoop.hbase.io.hfile.bucket.CacheFullException, org.apache.hadoop.hbase.io.hfile.bucket.BucketAllocatorException;
    Code:
       0: getstatic     #75                 // Field $assertionsDisabled:Z
       3: ifne          18
       6: iload_1
       7: ifgt          18
      10: new           #76                 // class java/lang/AssertionError
      13: dup
      14: invokespecial #77                 // Method java/lang/AssertionError."<init>":()V
      17: athrow
      18: aload_0
      19: iload_1
      20: invokevirtual #78                 // Method roundUpToBucketSizeInfo:(I)Lorg/apache/hadoop/hbase/io/hfile/bucket/BucketAllocator$BucketSizeInfo;
      23: astore_2
      24: aload_2
      25: ifnonnull     70
      28: new           #16                 // class org/apache/hadoop/hbase/io/hfile/bucket/BucketAllocatorException
      31: dup
      32: new           #17                 // class java/lang/StringBuilder
      35: dup
      36: invokespecial #18                 // Method java/lang/StringBuilder."<init>":()V
      39: ldc           #79                 // String Allocation too big size=
      41: invokevirtual #20                 // Method java/lang/StringBuilder.append:(Ljava/lang/String;)Ljava/lang/StringBuilder;
      44: iload_1
      45: invokevirtual #21                 // Method java/lang/StringBuilder.append:(I)Ljava/lang/StringBuilder;
      48: ldc           #80                 // String ; adjust BucketCache sizes
      50: invokevirtual #20                 // Method java/lang/StringBuilder.append:(Ljava/lang/String;)Ljava/lang/StringBuilder;
      53: ldc           #82                 // String hbase.bucketcache.bucket.sizes
      55: invokevirtual #20                 // Method java/lang/StringBuilder.append:(Ljava/lang/String;)Ljava/lang/StringBuilder;
      58: ldc           #83                 // String  to accomodate if size seems reasonable and you want it cached.
      60: invokevirtual #20                 // Method java/lang/StringBuilder.append:(Ljava/lang/String;)Ljava/lang/StringBuilder;
      63: invokevirtual #24                 // Method java/lang/StringBuilder.toString:()Ljava/lang/String;
      66: invokespecial #25                 // Method org/apache/hadoop/hbase/io/hfile/bucket/BucketAllocatorException."<init>":(Ljava/lang/String;)V
      69: athrow
      70: aload_2
      71: invokevirtual #84                 // Method org/apache/hadoop/hbase/io/hfile/bucket/BucketAllocator$BucketSizeInfo.allocateBlock:()J
      74: lstore_3
      75: lload_3
      76: lconst_0
      77: lcmp
      78: ifge          94
      81: new           #85                 // class org/apache/hadoop/hbase/io/hfile/bucket/CacheFullException
      84: dup
      85: iload_1
      86: aload_2
      87: invokevirtual #86                 // Method org/apache/hadoop/hbase/io/hfile/bucket/BucketAllocator$BucketSizeInfo.sizeIndex:()I
      90: invokespecial #87                 // Method org/apache/hadoop/hbase/io/hfile/bucket/CacheFullException."<init>":(II)V
      93: athrow
      94: aload_0
      95: dup
      96: getfield      #7                  // Field usedSize:J
      99: aload_0
     100: getfield      #4                  // Field bucketSizes:[I
     103: aload_2
     104: invokevirtual #86                 // Method org/apache/hadoop/hbase/io/hfile/bucket/BucketAllocator$BucketSizeInfo.sizeIndex:()I
     107: iaload
     108: i2l
     109: ladd
     110: putfield      #7                  // Field usedSize:J
     113: lload_3
     114: lreturn

  public synchronized int freeBlock(long);
    Code:
       0: lload_1
       1: aload_0
       2: getfield      #3                  // Field bucketCapacity:J
       5: ldiv
       6: l2i
       7: istore_3
       8: getstatic     #75                 // Field $assertionsDisabled:Z
      11: ifne          35
      14: iload_3
      15: iflt          27
      18: iload_3
      19: aload_0
      20: getfield      #1                  // Field buckets:[Lorg/apache/hadoop/hbase/io/hfile/bucket/BucketAllocator$Bucket;
      23: arraylength
      24: if_icmplt     35
      27: new           #76                 // class java/lang/AssertionError
      30: dup
      31: invokespecial #77                 // Method java/lang/AssertionError."<init>":()V
      34: athrow
      35: aload_0
      36: getfield      #1                  // Field buckets:[Lorg/apache/hadoop/hbase/io/hfile/bucket/BucketAllocator$Bucket;
      39: iload_3
      40: aaload
      41: astore        4
      43: aload_0
      44: getfield      #5                  // Field bucketSizeInfos:[Lorg/apache/hadoop/hbase/io/hfile/bucket/BucketAllocator$BucketSizeInfo;
      47: aload         4
      49: invokevirtual #52                 // Method org/apache/hadoop/hbase/io/hfile/bucket/BucketAllocator$Bucket.sizeIndex:()I
      52: aaload
      53: aload         4
      55: lload_1
      56: invokevirtual #89                 // Method org/apache/hadoop/hbase/io/hfile/bucket/BucketAllocator$BucketSizeInfo.freeBlock:(Lorg/apache/hadoop/hbase/io/hfile/bucket/BucketAllocator$Bucket;J)V
      59: aload_0
      60: dup
      61: getfield      #7                  // Field usedSize:J
      64: aload         4
      66: invokevirtual #60                 // Method org/apache/hadoop/hbase/io/hfile/bucket/BucketAllocator$Bucket.getItemAllocationSize:()I
      69: i2l
      70: lsub
      71: putfield      #7                  // Field usedSize:J
      74: aload         4
      76: invokevirtual #60                 // Method org/apache/hadoop/hbase/io/hfile/bucket/BucketAllocator$Bucket.getItemAllocationSize:()I
      79: ireturn

  public int sizeIndexOfAllocation(long);
    Code:
       0: lload_1
       1: aload_0
       2: getfield      #3                  // Field bucketCapacity:J
       5: ldiv
       6: l2i
       7: istore_3
       8: getstatic     #75                 // Field $assertionsDisabled:Z
      11: ifne          35
      14: iload_3
      15: iflt          27
      18: iload_3
      19: aload_0
      20: getfield      #1                  // Field buckets:[Lorg/apache/hadoop/hbase/io/hfile/bucket/BucketAllocator$Bucket;
      23: arraylength
      24: if_icmplt     35
      27: new           #76                 // class java/lang/AssertionError
      30: dup
      31: invokespecial #77                 // Method java/lang/AssertionError."<init>":()V
      34: athrow
      35: aload_0
      36: getfield      #1                  // Field buckets:[Lorg/apache/hadoop/hbase/io/hfile/bucket/BucketAllocator$Bucket;
      39: iload_3
      40: aaload
      41: astore        4
      43: aload         4
      45: invokevirtual #52                 // Method org/apache/hadoop/hbase/io/hfile/bucket/BucketAllocator$Bucket.sizeIndex:()I
      48: ireturn

  public int sizeOfAllocation(long);
    Code:
       0: lload_1
       1: aload_0
       2: getfield      #3                  // Field bucketCapacity:J
       5: ldiv
       6: l2i
       7: istore_3
       8: getstatic     #75                 // Field $assertionsDisabled:Z
      11: ifne          35
      14: iload_3
      15: iflt          27
      18: iload_3
      19: aload_0
      20: getfield      #1                  // Field buckets:[Lorg/apache/hadoop/hbase/io/hfile/bucket/BucketAllocator$Bucket;
      23: arraylength
      24: if_icmplt     35
      27: new           #76                 // class java/lang/AssertionError
      30: dup
      31: invokespecial #77                 // Method java/lang/AssertionError."<init>":()V
      34: athrow
      35: aload_0
      36: getfield      #1                  // Field buckets:[Lorg/apache/hadoop/hbase/io/hfile/bucket/BucketAllocator$Bucket;
      39: iload_3
      40: aaload
      41: astore        4
      43: aload         4
      45: invokevirtual #60                 // Method org/apache/hadoop/hbase/io/hfile/bucket/BucketAllocator$Bucket.getItemAllocationSize:()I
      48: ireturn

  public org.apache.hadoop.hbase.io.hfile.bucket.BucketAllocator$Bucket[] getBuckets();
    Code:
       0: aload_0
       1: getfield      #1                  // Field buckets:[Lorg/apache/hadoop/hbase/io/hfile/bucket/BucketAllocator$Bucket;
       4: areturn

  void logStatistics();
    Code:
       0: new           #90                 // class org/apache/hadoop/hbase/io/hfile/bucket/BucketAllocator$IndexStatistics
       3: dup
       4: invokespecial #91                 // Method org/apache/hadoop/hbase/io/hfile/bucket/BucketAllocator$IndexStatistics."<init>":()V
       7: astore_1
       8: aload_0
       9: aload_1
      10: invokevirtual #92                 // Method getIndexStatistics:(Lorg/apache/hadoop/hbase/io/hfile/bucket/BucketAllocator$IndexStatistics;)[Lorg/apache/hadoop/hbase/io/hfile/bucket/BucketAllocator$IndexStatistics;
      13: astore_2
      14: getstatic     #31                 // Field LOG:Lorg/slf4j/Logger;
      17: ldc           #93                 // String Bucket allocator statistics follow:\n
      19: invokeinterface #40,  2           // InterfaceMethod org/slf4j/Logger.info:(Ljava/lang/String;)V
      24: getstatic     #31                 // Field LOG:Lorg/slf4j/Logger;
      27: new           #17                 // class java/lang/StringBuilder
      30: dup
      31: invokespecial #18                 // Method java/lang/StringBuilder."<init>":()V
      34: ldc           #94                 // String   Free bytes=
      36: invokevirtual #20                 // Method java/lang/StringBuilder.append:(Ljava/lang/String;)Ljava/lang/StringBuilder;
      39: aload_1
      40: invokevirtual #95                 // Method org/apache/hadoop/hbase/io/hfile/bucket/BucketAllocator$IndexStatistics.freeBytes:()J
      43: invokevirtual #34                 // Method java/lang/StringBuilder.append:(J)Ljava/lang/StringBuilder;
      46: ldc           #96                 // String +; used bytes=
      48: invokevirtual #20                 // Method java/lang/StringBuilder.append:(Ljava/lang/String;)Ljava/lang/StringBuilder;
      51: aload_1
      52: invokevirtual #97                 // Method org/apache/hadoop/hbase/io/hfile/bucket/BucketAllocator$IndexStatistics.usedBytes:()J
      55: invokevirtual #34                 // Method java/lang/StringBuilder.append:(J)Ljava/lang/StringBuilder;
      58: ldc           #98                 // String ; total bytes=
      60: invokevirtual #20                 // Method java/lang/StringBuilder.append:(Ljava/lang/String;)Ljava/lang/StringBuilder;
      63: aload_1
      64: invokevirtual #99                 // Method org/apache/hadoop/hbase/io/hfile/bucket/BucketAllocator$IndexStatistics.totalBytes:()J
      67: invokevirtual #34                 // Method java/lang/StringBuilder.append:(J)Ljava/lang/StringBuilder;
      70: invokevirtual #24                 // Method java/lang/StringBuilder.toString:()Ljava/lang/String;
      73: invokeinterface #40,  2           // InterfaceMethod org/slf4j/Logger.info:(Ljava/lang/String;)V
      78: aload_2
      79: astore_3
      80: aload_3
      81: arraylength
      82: istore        4
      84: iconst_0
      85: istore        5
      87: iload         5
      89: iload         4
      91: if_icmpge     176
      94: aload_3
      95: iload         5
      97: aaload
      98: astore        6
     100: getstatic     #31                 // Field LOG:Lorg/slf4j/Logger;
     103: new           #17                 // class java/lang/StringBuilder
     106: dup
     107: invokespecial #18                 // Method java/lang/StringBuilder."<init>":()V
     110: ldc           #100                // String   Object size
     112: invokevirtual #20                 // Method java/lang/StringBuilder.append:(Ljava/lang/String;)Ljava/lang/StringBuilder;
     115: aload         6
     117: invokevirtual #101                // Method org/apache/hadoop/hbase/io/hfile/bucket/BucketAllocator$IndexStatistics.itemSize:()J
     120: invokevirtual #34                 // Method java/lang/StringBuilder.append:(J)Ljava/lang/StringBuilder;
     123: ldc           #102                // String  used=
     125: invokevirtual #20                 // Method java/lang/StringBuilder.append:(Ljava/lang/String;)Ljava/lang/StringBuilder;
     128: aload         6
     130: invokevirtual #103                // Method org/apache/hadoop/hbase/io/hfile/bucket/BucketAllocator$IndexStatistics.usedCount:()J
     133: invokevirtual #34                 // Method java/lang/StringBuilder.append:(J)Ljava/lang/StringBuilder;
     136: ldc           #104                // String ; free=
     138: invokevirtual #20                 // Method java/lang/StringBuilder.append:(Ljava/lang/String;)Ljava/lang/StringBuilder;
     141: aload         6
     143: invokevirtual #105                // Method org/apache/hadoop/hbase/io/hfile/bucket/BucketAllocator$IndexStatistics.freeCount:()J
     146: invokevirtual #34                 // Method java/lang/StringBuilder.append:(J)Ljava/lang/StringBuilder;
     149: ldc           #106                // String ; total=
     151: invokevirtual #20                 // Method java/lang/StringBuilder.append:(Ljava/lang/String;)Ljava/lang/StringBuilder;
     154: aload         6
     156: invokevirtual #107                // Method org/apache/hadoop/hbase/io/hfile/bucket/BucketAllocator$IndexStatistics.totalCount:()J
     159: invokevirtual #34                 // Method java/lang/StringBuilder.append:(J)Ljava/lang/StringBuilder;
     162: invokevirtual #24                 // Method java/lang/StringBuilder.toString:()Ljava/lang/String;
     165: invokeinterface #40,  2           // InterfaceMethod org/slf4j/Logger.info:(Ljava/lang/String;)V
     170: iinc          5, 1
     173: goto          87
     176: return

  org.apache.hadoop.hbase.io.hfile.bucket.BucketAllocator$IndexStatistics[] getIndexStatistics(org.apache.hadoop.hbase.io.hfile.bucket.BucketAllocator$IndexStatistics);
    Code:
       0: aload_0
       1: invokevirtual #108                // Method getIndexStatistics:()[Lorg/apache/hadoop/hbase/io/hfile/bucket/BucketAllocator$IndexStatistics;
       4: astore_2
       5: lconst_0
       6: lstore_3
       7: lconst_0
       8: lstore        5
      10: aload_2
      11: astore        7
      13: aload         7
      15: arraylength
      16: istore        8
      18: iconst_0
      19: istore        9
      21: iload         9
      23: iload         8
      25: if_icmpge     59
      28: aload         7
      30: iload         9
      32: aaload
      33: astore        10
      35: lload_3
      36: aload         10
      38: invokevirtual #95                 // Method org/apache/hadoop/hbase/io/hfile/bucket/BucketAllocator$IndexStatistics.freeBytes:()J
      41: ladd
      42: lstore_3
      43: lload         5
      45: aload         10
      47: invokevirtual #97                 // Method org/apache/hadoop/hbase/io/hfile/bucket/BucketAllocator$IndexStatistics.usedBytes:()J
      50: ladd
      51: lstore        5
      53: iinc          9, 1
      56: goto          21
      59: aload_1
      60: lload_3
      61: lload         5
      63: lconst_1
      64: invokevirtual #109                // Method org/apache/hadoop/hbase/io/hfile/bucket/BucketAllocator$IndexStatistics.setTo:(JJJ)V
      67: aload_2
      68: areturn

  org.apache.hadoop.hbase.io.hfile.bucket.BucketAllocator$IndexStatistics[] getIndexStatistics();
    Code:
       0: aload_0
       1: getfield      #4                  // Field bucketSizes:[I
       4: arraylength
       5: anewarray     #90                 // class org/apache/hadoop/hbase/io/hfile/bucket/BucketAllocator$IndexStatistics
       8: astore_1
       9: iconst_0
      10: istore_2
      11: iload_2
      12: aload_1
      13: arraylength
      14: if_icmpge     35
      17: aload_1
      18: iload_2
      19: aload_0
      20: getfield      #5                  // Field bucketSizeInfos:[Lorg/apache/hadoop/hbase/io/hfile/bucket/BucketAllocator$BucketSizeInfo;
      23: iload_2
      24: aaload
      25: invokevirtual #110                // Method org/apache/hadoop/hbase/io/hfile/bucket/BucketAllocator$BucketSizeInfo.statistics:()Lorg/apache/hadoop/hbase/io/hfile/bucket/BucketAllocator$IndexStatistics;
      28: aastore
      29: iinc          2, 1
      32: goto          11
      35: aload_1
      36: areturn

  public long freeBlock(long[]);
    Code:
       0: lconst_0
       1: lstore_2
       2: iconst_0
       3: istore        4
       5: iload         4
       7: aload_1
       8: arraylength
       9: if_icmpge     30
      12: lload_2
      13: aload_0
      14: aload_1
      15: iload         4
      17: laload
      18: invokevirtual #111                // Method freeBlock:(J)I
      21: i2l
      22: ladd
      23: lstore_2
      24: iinc          4, 1
      27: goto          5
      30: lload_2
      31: lreturn

  public int getBucketIndex(long);
    Code:
       0: lload_1
       1: aload_0
       2: getfield      #3                  // Field bucketCapacity:J
       5: ldiv
       6: l2i
       7: ireturn

  public java.util.Set<java.lang.Integer> getLeastFilledBuckets(java.util.Set<java.lang.Integer>, int);
    Code:
       0: new           #112                // class org/apache/hadoop/hbase/io/hfile/bucket/BucketAllocator$1
       3: dup
       4: aload_0
       5: invokespecial #113                // Method org/apache/hadoop/hbase/io/hfile/bucket/BucketAllocator$1."<init>":(Lorg/apache/hadoop/hbase/io/hfile/bucket/BucketAllocator;)V
       8: invokestatic  #114                // Method org/apache/hbase/thirdparty/com/google/common/collect/MinMaxPriorityQueue.orderedBy:(Ljava/util/Comparator;)Lorg/apache/hbase/thirdparty/com/google/common/collect/MinMaxPriorityQueue$Builder;
      11: iload_2
      12: invokevirtual #115                // Method org/apache/hbase/thirdparty/com/google/common/collect/MinMaxPriorityQueue$Builder.maximumSize:(I)Lorg/apache/hbase/thirdparty/com/google/common/collect/MinMaxPriorityQueue$Builder;
      15: invokevirtual #116                // Method org/apache/hbase/thirdparty/com/google/common/collect/MinMaxPriorityQueue$Builder.create:()Lorg/apache/hbase/thirdparty/com/google/common/collect/MinMaxPriorityQueue;
      18: astore_3
      19: iconst_0
      20: istore        4
      22: iload         4
      24: aload_0
      25: getfield      #1                  // Field buckets:[Lorg/apache/hadoop/hbase/io/hfile/bucket/BucketAllocator$Bucket;
      28: arraylength
      29: if_icmpge     102
      32: aload_1
      33: iload         4
      35: invokestatic  #117                // Method java/lang/Integer.valueOf:(I)Ljava/lang/Integer;
      38: invokeinterface #118,  2          // InterfaceMethod java/util/Set.contains:(Ljava/lang/Object;)Z
      43: ifne          96
      46: aload_0
      47: getfield      #1                  // Field buckets:[Lorg/apache/hadoop/hbase/io/hfile/bucket/BucketAllocator$Bucket;
      50: iload         4
      52: aaload
      53: invokevirtual #119                // Method org/apache/hadoop/hbase/io/hfile/bucket/BucketAllocator$Bucket.isUninstantiated:()Z
      56: ifne          96
      59: aload_0
      60: getfield      #5                  // Field bucketSizeInfos:[Lorg/apache/hadoop/hbase/io/hfile/bucket/BucketAllocator$BucketSizeInfo;
      63: aload_0
      64: getfield      #1                  // Field buckets:[Lorg/apache/hadoop/hbase/io/hfile/bucket/BucketAllocator$Bucket;
      67: iload         4
      69: aaload
      70: invokevirtual #52                 // Method org/apache/hadoop/hbase/io/hfile/bucket/BucketAllocator$Bucket.sizeIndex:()I
      73: aaload
      74: invokestatic  #120                // Method org/apache/hadoop/hbase/io/hfile/bucket/BucketAllocator$BucketSizeInfo.access$800:(Lorg/apache/hadoop/hbase/io/hfile/bucket/BucketAllocator$BucketSizeInfo;)Lorg/apache/hbase/thirdparty/org/apache/commons/collections4/map/LinkedMap;
      77: invokevirtual #121                // Method org/apache/hbase/thirdparty/org/apache/commons/collections4/map/LinkedMap.size:()I
      80: iconst_1
      81: if_icmpeq     96
      84: aload_3
      85: iload         4
      87: invokestatic  #117                // Method java/lang/Integer.valueOf:(I)Ljava/lang/Integer;
      90: invokeinterface #122,  2          // InterfaceMethod java/util/Queue.add:(Ljava/lang/Object;)Z
      95: pop
      96: iinc          4, 1
      99: goto          22
     102: new           #123                // class java/util/HashSet
     105: dup
     106: iload_2
     107: invokespecial #124                // Method java/util/HashSet."<init>":(I)V
     110: astore        4
     112: aload         4
     114: aload_3
     115: invokeinterface #125,  2          // InterfaceMethod java/util/Set.addAll:(Ljava/util/Collection;)Z
     120: pop
     121: aload         4
     123: areturn

  static int[] access$000(org.apache.hadoop.hbase.io.hfile.bucket.BucketAllocator);
    Code:
       0: aload_0
       1: getfield      #4                  // Field bucketSizes:[I
       4: areturn

  static long access$100(org.apache.hadoop.hbase.io.hfile.bucket.BucketAllocator);
    Code:
       0: aload_0
       1: getfield      #3                  // Field bucketCapacity:J
       4: lreturn

  static org.apache.hadoop.hbase.io.hfile.bucket.BucketAllocator$Bucket access$200(org.apache.hadoop.hbase.io.hfile.bucket.BucketAllocator);
    Code:
       0: aload_0
       1: invokespecial #2                  // Method grabGlobalCompletelyFreeBucket:()Lorg/apache/hadoop/hbase/io/hfile/bucket/BucketAllocator$Bucket;
       4: areturn

  static org.apache.hadoop.hbase.io.hfile.bucket.BucketAllocator$Bucket[] access$500(org.apache.hadoop.hbase.io.hfile.bucket.BucketAllocator);
    Code:
       0: aload_0
       1: getfield      #1                  // Field buckets:[Lorg/apache/hadoop/hbase/io/hfile/bucket/BucketAllocator$Bucket;
       4: areturn

  static {};
    Code:
       0: ldc           #12                 // class org/apache/hadoop/hbase/io/hfile/bucket/BucketAllocator
       2: invokevirtual #126                // Method java/lang/Class.desiredAssertionStatus:()Z
       5: ifne          12
       8: iconst_1
       9: goto          13
      12: iconst_0
      13: putstatic     #75                 // Field $assertionsDisabled:Z
      16: ldc           #12                 // class org/apache/hadoop/hbase/io/hfile/bucket/BucketAllocator
      18: invokestatic  #127                // Method org/slf4j/LoggerFactory.getLogger:(Ljava/lang/Class;)Lorg/slf4j/Logger;
      21: putstatic     #31                 // Field LOG:Lorg/slf4j/Logger;
      24: bipush        14
      26: newarray       int
      28: dup
      29: iconst_0
      30: sipush        5120
      33: iastore
      34: dup
      35: iconst_1
      36: sipush        9216
      39: iastore
      40: dup
      41: iconst_2
      42: sipush        17408
      45: iastore
      46: dup
      47: iconst_3
      48: ldc           #128                // int 33792
      50: iastore
      51: dup
      52: iconst_4
      53: ldc           #129                // int 41984
      55: iastore
      56: dup
      57: iconst_5
      58: ldc           #130                // int 50176
      60: iastore
      61: dup
      62: bipush        6
      64: ldc           #131                // int 58368
      66: iastore
      67: dup
      68: bipush        7
      70: ldc           #132                // int 66560
      72: iastore
      73: dup
      74: bipush        8
      76: ldc           #133                // int 99328
      78: iastore
      79: dup
      80: bipush        9
      82: ldc           #134                // int 132096
      84: iastore
      85: dup
      86: bipush        10
      88: ldc           #135                // int 197632
      90: iastore
      91: dup
      92: bipush        11
      94: ldc           #136                // int 263168
      96: iastore
      97: dup
      98: bipush        12
     100: ldc           #137                // int 394240
     102: iastore
     103: dup
     104: bipush        13
     106: ldc           #138                // int 525312
     108: iastore
     109: putstatic     #8                  // Field DEFAULT_BUCKET_SIZES:[I
     112: return
}
