Compiled from "BucketCache.java"
class org.apache.hadoop.hbase.io.hfile.bucket.BucketCache$BucketEntry implements java.io.Serializable {
  static final java.util.Comparator<org.apache.hadoop.hbase.io.hfile.bucket.BucketCache$BucketEntry> COMPARATOR;

  byte deserialiserIndex;

  static final boolean $assertionsDisabled;

  org.apache.hadoop.hbase.io.hfile.bucket.BucketCache$BucketEntry(long, int, long, boolean);
    Code:
       0: aload_0
       1: invokespecial #1                  // Method java/lang/Object."<init>":()V
       4: aload_0
       5: invokestatic  #2                  // Method java/lang/System.nanoTime:()J
       8: putfield      #3                  // Field cachedTime:J
      11: aload_0
      12: lload_1
      13: invokespecial #4                  // Method setOffset:(J)V
      16: aload_0
      17: iload_3
      18: putfield      #5                  // Field length:I
      21: aload_0
      22: lload         4
      24: putfield      #6                  // Field accessCounter:J
      27: iload         6
      29: ifeq          42
      32: aload_0
      33: getstatic     #7                  // Field org/apache/hadoop/hbase/io/hfile/BlockPriority.MEMORY:Lorg/apache/hadoop/hbase/io/hfile/BlockPriority;
      36: putfield      #8                  // Field priority:Lorg/apache/hadoop/hbase/io/hfile/BlockPriority;
      39: goto          49
      42: aload_0
      43: getstatic     #9                  // Field org/apache/hadoop/hbase/io/hfile/BlockPriority.SINGLE:Lorg/apache/hadoop/hbase/io/hfile/BlockPriority;
      46: putfield      #8                  // Field priority:Lorg/apache/hadoop/hbase/io/hfile/BlockPriority;
      49: return

  long offset();
    Code:
       0: aload_0
       1: getfield      #10                 // Field offsetBase:I
       4: i2l
       5: ldc2_w        #11                 // long 4294967295l
       8: land
       9: lstore_1
      10: lload_1
      11: aload_0
      12: getfield      #13                 // Field offset1:B
      15: i2l
      16: ldc2_w        #14                 // long 255l
      19: land
      20: bipush        32
      22: lshl
      23: ladd
      24: lstore_1
      25: lload_1
      26: bipush        8
      28: lshl
      29: lreturn

  public int getLength();
    Code:
       0: aload_0
       1: getfield      #5                  // Field length:I
       4: ireturn

  protected org.apache.hadoop.hbase.io.hfile.CacheableDeserializer<org.apache.hadoop.hbase.io.hfile.Cacheable> deserializerReference();
    Code:
       0: aload_0
       1: getfield      #19                 // Field deserialiserIndex:B
       4: invokestatic  #20                 // Method org/apache/hadoop/hbase/io/hfile/CacheableDeserializerIdManager.getDeserializer:(I)Lorg/apache/hadoop/hbase/io/hfile/CacheableDeserializer;
       7: areturn

  protected void setDeserialiserReference(org.apache.hadoop.hbase.io.hfile.CacheableDeserializer<org.apache.hadoop.hbase.io.hfile.Cacheable>);
    Code:
       0: aload_0
       1: aload_1
       2: invokeinterface #21,  1           // InterfaceMethod org/apache/hadoop/hbase/io/hfile/CacheableDeserializer.getDeserialiserIdentifier:()I
       7: i2b
       8: putfield      #19                 // Field deserialiserIndex:B
      11: return

  public long getAccessCounter();
    Code:
       0: aload_0
       1: getfield      #6                  // Field accessCounter:J
       4: lreturn

  public void access(long);
    Code:
       0: aload_0
       1: lload_1
       2: putfield      #6                  // Field accessCounter:J
       5: aload_0
       6: getfield      #8                  // Field priority:Lorg/apache/hadoop/hbase/io/hfile/BlockPriority;
       9: getstatic     #9                  // Field org/apache/hadoop/hbase/io/hfile/BlockPriority.SINGLE:Lorg/apache/hadoop/hbase/io/hfile/BlockPriority;
      12: if_acmpne     22
      15: aload_0
      16: getstatic     #22                 // Field org/apache/hadoop/hbase/io/hfile/BlockPriority.MULTI:Lorg/apache/hadoop/hbase/io/hfile/BlockPriority;
      19: putfield      #8                  // Field priority:Lorg/apache/hadoop/hbase/io/hfile/BlockPriority;
      22: return

  public org.apache.hadoop.hbase.io.hfile.BlockPriority getPriority();
    Code:
       0: aload_0
       1: getfield      #8                  // Field priority:Lorg/apache/hadoop/hbase/io/hfile/BlockPriority;
       4: areturn

  public long getCachedTime();
    Code:
       0: aload_0
       1: getfield      #3                  // Field cachedTime:J
       4: lreturn

  protected int getRefCount();
    Code:
       0: iconst_0
       1: ireturn

  protected int incrementRefCountAndGet();
    Code:
       0: iconst_0
       1: ireturn

  protected int decrementRefCountAndGet();
    Code:
       0: iconst_0
       1: ireturn

  protected boolean isMarkedForEvict();
    Code:
       0: iconst_0
       1: ireturn

  protected void markForEvict();
    Code:
       0: return

  static {};
    Code:
       0: ldc           #23                 // class org/apache/hadoop/hbase/io/hfile/bucket/BucketCache
       2: invokevirtual #24                 // Method java/lang/Class.desiredAssertionStatus:()Z
       5: ifne          12
       8: iconst_1
       9: goto          13
      12: iconst_0
      13: putstatic     #16                 // Field $assertionsDisabled:Z
      16: invokedynamic #25,  0             // InvokeDynamic #0:applyAsLong:()Ljava/util/function/ToLongFunction;
      21: invokestatic  #26                 // InterfaceMethod java/util/Comparator.comparingLong:(Ljava/util/function/ToLongFunction;)Ljava/util/Comparator;
      24: invokeinterface #27,  1           // InterfaceMethod java/util/Comparator.reversed:()Ljava/util/Comparator;
      29: putstatic     #28                 // Field COMPARATOR:Ljava/util/Comparator;
      32: return
}
