Compiled from "BucketCacheProtos.java"
public final class org.apache.hadoop.hbase.shaded.protobuf.generated.BucketCacheProtos$BlockType extends java.lang.Enum<org.apache.hadoop.hbase.shaded.protobuf.generated.BucketCacheProtos$BlockType> implements org.apache.hbase.thirdparty.com.google.protobuf.ProtocolMessageEnum {
  public static final org.apache.hadoop.hbase.shaded.protobuf.generated.BucketCacheProtos$BlockType data;

  public static final org.apache.hadoop.hbase.shaded.protobuf.generated.BucketCacheProtos$BlockType encoded_data;

  public static final org.apache.hadoop.hbase.shaded.protobuf.generated.BucketCacheProtos$BlockType leaf_index;

  public static final org.apache.hadoop.hbase.shaded.protobuf.generated.BucketCacheProtos$BlockType bloom_chunk;

  public static final org.apache.hadoop.hbase.shaded.protobuf.generated.BucketCacheProtos$BlockType meta;

  public static final org.apache.hadoop.hbase.shaded.protobuf.generated.BucketCacheProtos$BlockType intermediate_index;

  public static final org.apache.hadoop.hbase.shaded.protobuf.generated.BucketCacheProtos$BlockType root_index;

  public static final org.apache.hadoop.hbase.shaded.protobuf.generated.BucketCacheProtos$BlockType file_info;

  public static final org.apache.hadoop.hbase.shaded.protobuf.generated.BucketCacheProtos$BlockType general_bloom_meta;

  public static final org.apache.hadoop.hbase.shaded.protobuf.generated.BucketCacheProtos$BlockType delete_family_bloom_meta;

  public static final org.apache.hadoop.hbase.shaded.protobuf.generated.BucketCacheProtos$BlockType trailer;

  public static final org.apache.hadoop.hbase.shaded.protobuf.generated.BucketCacheProtos$BlockType index_v1;

  public static final int data_VALUE;

  public static final int encoded_data_VALUE;

  public static final int leaf_index_VALUE;

  public static final int bloom_chunk_VALUE;

  public static final int meta_VALUE;

  public static final int intermediate_index_VALUE;

  public static final int root_index_VALUE;

  public static final int file_info_VALUE;

  public static final int general_bloom_meta_VALUE;

  public static final int delete_family_bloom_meta_VALUE;

  public static final int trailer_VALUE;

  public static final int index_v1_VALUE;

  public static org.apache.hadoop.hbase.shaded.protobuf.generated.BucketCacheProtos$BlockType[] values();
    Code:
       0: getstatic     #1                  // Field $VALUES:[Lorg/apache/hadoop/hbase/shaded/protobuf/generated/BucketCacheProtos$BlockType;
       3: invokevirtual #2                  // Method "[Lorg/apache/hadoop/hbase/shaded/protobuf/generated/BucketCacheProtos$BlockType;".clone:()Ljava/lang/Object;
       6: checkcast     #3                  // class "[Lorg/apache/hadoop/hbase/shaded/protobuf/generated/BucketCacheProtos$BlockType;"
       9: areturn

  public static org.apache.hadoop.hbase.shaded.protobuf.generated.BucketCacheProtos$BlockType valueOf(java.lang.String);
    Code:
       0: ldc           #4                  // class org/apache/hadoop/hbase/shaded/protobuf/generated/BucketCacheProtos$BlockType
       2: aload_0
       3: invokestatic  #5                  // Method java/lang/Enum.valueOf:(Ljava/lang/Class;Ljava/lang/String;)Ljava/lang/Enum;
       6: checkcast     #4                  // class org/apache/hadoop/hbase/shaded/protobuf/generated/BucketCacheProtos$BlockType
       9: areturn

  public final int getNumber();
    Code:
       0: aload_0
       1: getfield      #6                  // Field value:I
       4: ireturn

  public static org.apache.hadoop.hbase.shaded.protobuf.generated.BucketCacheProtos$BlockType valueOf(int);
    Code:
       0: iload_0
       1: invokestatic  #7                  // Method forNumber:(I)Lorg/apache/hadoop/hbase/shaded/protobuf/generated/BucketCacheProtos$BlockType;
       4: areturn

  public static org.apache.hadoop.hbase.shaded.protobuf.generated.BucketCacheProtos$BlockType forNumber(int);
    Code:
       0: iload_0
       1: tableswitch   { // 0 to 11
                     0: 64
                     1: 68
                     2: 72
                     3: 76
                     4: 80
                     5: 84
                     6: 88
                     7: 92
                     8: 96
                     9: 100
                    10: 104
                    11: 108
               default: 112
          }
      64: getstatic     #8                  // Field data:Lorg/apache/hadoop/hbase/shaded/protobuf/generated/BucketCacheProtos$BlockType;
      67: areturn
      68: getstatic     #9                  // Field encoded_data:Lorg/apache/hadoop/hbase/shaded/protobuf/generated/BucketCacheProtos$BlockType;
      71: areturn
      72: getstatic     #10                 // Field leaf_index:Lorg/apache/hadoop/hbase/shaded/protobuf/generated/BucketCacheProtos$BlockType;
      75: areturn
      76: getstatic     #11                 // Field bloom_chunk:Lorg/apache/hadoop/hbase/shaded/protobuf/generated/BucketCacheProtos$BlockType;
      79: areturn
      80: getstatic     #12                 // Field meta:Lorg/apache/hadoop/hbase/shaded/protobuf/generated/BucketCacheProtos$BlockType;
      83: areturn
      84: getstatic     #13                 // Field intermediate_index:Lorg/apache/hadoop/hbase/shaded/protobuf/generated/BucketCacheProtos$BlockType;
      87: areturn
      88: getstatic     #14                 // Field root_index:Lorg/apache/hadoop/hbase/shaded/protobuf/generated/BucketCacheProtos$BlockType;
      91: areturn
      92: getstatic     #15                 // Field file_info:Lorg/apache/hadoop/hbase/shaded/protobuf/generated/BucketCacheProtos$BlockType;
      95: areturn
      96: getstatic     #16                 // Field general_bloom_meta:Lorg/apache/hadoop/hbase/shaded/protobuf/generated/BucketCacheProtos$BlockType;
      99: areturn
     100: getstatic     #17                 // Field delete_family_bloom_meta:Lorg/apache/hadoop/hbase/shaded/protobuf/generated/BucketCacheProtos$BlockType;
     103: areturn
     104: getstatic     #18                 // Field trailer:Lorg/apache/hadoop/hbase/shaded/protobuf/generated/BucketCacheProtos$BlockType;
     107: areturn
     108: getstatic     #19                 // Field index_v1:Lorg/apache/hadoop/hbase/shaded/protobuf/generated/BucketCacheProtos$BlockType;
     111: areturn
     112: aconst_null
     113: areturn

  public static org.apache.hbase.thirdparty.com.google.protobuf.Internal$EnumLiteMap<org.apache.hadoop.hbase.shaded.protobuf.generated.BucketCacheProtos$BlockType> internalGetValueMap();
    Code:
       0: getstatic     #20                 // Field internalValueMap:Lorg/apache/hbase/thirdparty/com/google/protobuf/Internal$EnumLiteMap;
       3: areturn

  public final org.apache.hbase.thirdparty.com.google.protobuf.Descriptors$EnumValueDescriptor getValueDescriptor();
    Code:
       0: invokestatic  #21                 // Method getDescriptor:()Lorg/apache/hbase/thirdparty/com/google/protobuf/Descriptors$EnumDescriptor;
       3: invokevirtual #22                 // Method org/apache/hbase/thirdparty/com/google/protobuf/Descriptors$EnumDescriptor.getValues:()Ljava/util/List;
       6: aload_0
       7: invokevirtual #23                 // Method ordinal:()I
      10: invokeinterface #24,  2           // InterfaceMethod java/util/List.get:(I)Ljava/lang/Object;
      15: checkcast     #25                 // class org/apache/hbase/thirdparty/com/google/protobuf/Descriptors$EnumValueDescriptor
      18: areturn

  public final org.apache.hbase.thirdparty.com.google.protobuf.Descriptors$EnumDescriptor getDescriptorForType();
    Code:
       0: invokestatic  #21                 // Method getDescriptor:()Lorg/apache/hbase/thirdparty/com/google/protobuf/Descriptors$EnumDescriptor;
       3: areturn

  public static final org.apache.hbase.thirdparty.com.google.protobuf.Descriptors$EnumDescriptor getDescriptor();
    Code:
       0: invokestatic  #26                 // Method org/apache/hadoop/hbase/shaded/protobuf/generated/BucketCacheProtos.getDescriptor:()Lorg/apache/hbase/thirdparty/com/google/protobuf/Descriptors$FileDescriptor;
       3: invokevirtual #27                 // Method org/apache/hbase/thirdparty/com/google/protobuf/Descriptors$FileDescriptor.getEnumTypes:()Ljava/util/List;
       6: iconst_0
       7: invokeinterface #24,  2           // InterfaceMethod java/util/List.get:(I)Ljava/lang/Object;
      12: checkcast     #28                 // class org/apache/hbase/thirdparty/com/google/protobuf/Descriptors$EnumDescriptor
      15: areturn

  public static org.apache.hadoop.hbase.shaded.protobuf.generated.BucketCacheProtos$BlockType valueOf(org.apache.hbase.thirdparty.com.google.protobuf.Descriptors$EnumValueDescriptor);
    Code:
       0: aload_0
       1: invokevirtual #29                 // Method org/apache/hbase/thirdparty/com/google/protobuf/Descriptors$EnumValueDescriptor.getType:()Lorg/apache/hbase/thirdparty/com/google/protobuf/Descriptors$EnumDescriptor;
       4: invokestatic  #21                 // Method getDescriptor:()Lorg/apache/hbase/thirdparty/com/google/protobuf/Descriptors$EnumDescriptor;
       7: if_acmpeq     20
      10: new           #30                 // class java/lang/IllegalArgumentException
      13: dup
      14: ldc           #31                 // String EnumValueDescriptor is not for this type.
      16: invokespecial #32                 // Method java/lang/IllegalArgumentException."<init>":(Ljava/lang/String;)V
      19: athrow
      20: getstatic     #33                 // Field VALUES:[Lorg/apache/hadoop/hbase/shaded/protobuf/generated/BucketCacheProtos$BlockType;
      23: aload_0
      24: invokevirtual #34                 // Method org/apache/hbase/thirdparty/com/google/protobuf/Descriptors$EnumValueDescriptor.getIndex:()I
      27: aaload
      28: areturn

  static {};
    Code:
       0: new           #4                  // class org/apache/hadoop/hbase/shaded/protobuf/generated/BucketCacheProtos$BlockType
       3: dup
       4: ldc           #36                 // String data
       6: iconst_0
       7: iconst_0
       8: invokespecial #37                 // Method "<init>":(Ljava/lang/String;II)V
      11: putstatic     #8                  // Field data:Lorg/apache/hadoop/hbase/shaded/protobuf/generated/BucketCacheProtos$BlockType;
      14: new           #4                  // class org/apache/hadoop/hbase/shaded/protobuf/generated/BucketCacheProtos$BlockType
      17: dup
      18: ldc           #38                 // String encoded_data
      20: iconst_1
      21: iconst_1
      22: invokespecial #37                 // Method "<init>":(Ljava/lang/String;II)V
      25: putstatic     #9                  // Field encoded_data:Lorg/apache/hadoop/hbase/shaded/protobuf/generated/BucketCacheProtos$BlockType;
      28: new           #4                  // class org/apache/hadoop/hbase/shaded/protobuf/generated/BucketCacheProtos$BlockType
      31: dup
      32: ldc           #39                 // String leaf_index
      34: iconst_2
      35: iconst_2
      36: invokespecial #37                 // Method "<init>":(Ljava/lang/String;II)V
      39: putstatic     #10                 // Field leaf_index:Lorg/apache/hadoop/hbase/shaded/protobuf/generated/BucketCacheProtos$BlockType;
      42: new           #4                  // class org/apache/hadoop/hbase/shaded/protobuf/generated/BucketCacheProtos$BlockType
      45: dup
      46: ldc           #40                 // String bloom_chunk
      48: iconst_3
      49: iconst_3
      50: invokespecial #37                 // Method "<init>":(Ljava/lang/String;II)V
      53: putstatic     #11                 // Field bloom_chunk:Lorg/apache/hadoop/hbase/shaded/protobuf/generated/BucketCacheProtos$BlockType;
      56: new           #4                  // class org/apache/hadoop/hbase/shaded/protobuf/generated/BucketCacheProtos$BlockType
      59: dup
      60: ldc           #41                 // String meta
      62: iconst_4
      63: iconst_4
      64: invokespecial #37                 // Method "<init>":(Ljava/lang/String;II)V
      67: putstatic     #12                 // Field meta:Lorg/apache/hadoop/hbase/shaded/protobuf/generated/BucketCacheProtos$BlockType;
      70: new           #4                  // class org/apache/hadoop/hbase/shaded/protobuf/generated/BucketCacheProtos$BlockType
      73: dup
      74: ldc           #42                 // String intermediate_index
      76: iconst_5
      77: iconst_5
      78: invokespecial #37                 // Method "<init>":(Ljava/lang/String;II)V
      81: putstatic     #13                 // Field intermediate_index:Lorg/apache/hadoop/hbase/shaded/protobuf/generated/BucketCacheProtos$BlockType;
      84: new           #4                  // class org/apache/hadoop/hbase/shaded/protobuf/generated/BucketCacheProtos$BlockType
      87: dup
      88: ldc           #43                 // String root_index
      90: bipush        6
      92: bipush        6
      94: invokespecial #37                 // Method "<init>":(Ljava/lang/String;II)V
      97: putstatic     #14                 // Field root_index:Lorg/apache/hadoop/hbase/shaded/protobuf/generated/BucketCacheProtos$BlockType;
     100: new           #4                  // class org/apache/hadoop/hbase/shaded/protobuf/generated/BucketCacheProtos$BlockType
     103: dup
     104: ldc           #44                 // String file_info
     106: bipush        7
     108: bipush        7
     110: invokespecial #37                 // Method "<init>":(Ljava/lang/String;II)V
     113: putstatic     #15                 // Field file_info:Lorg/apache/hadoop/hbase/shaded/protobuf/generated/BucketCacheProtos$BlockType;
     116: new           #4                  // class org/apache/hadoop/hbase/shaded/protobuf/generated/BucketCacheProtos$BlockType
     119: dup
     120: ldc           #45                 // String general_bloom_meta
     122: bipush        8
     124: bipush        8
     126: invokespecial #37                 // Method "<init>":(Ljava/lang/String;II)V
     129: putstatic     #16                 // Field general_bloom_meta:Lorg/apache/hadoop/hbase/shaded/protobuf/generated/BucketCacheProtos$BlockType;
     132: new           #4                  // class org/apache/hadoop/hbase/shaded/protobuf/generated/BucketCacheProtos$BlockType
     135: dup
     136: ldc           #46                 // String delete_family_bloom_meta
     138: bipush        9
     140: bipush        9
     142: invokespecial #37                 // Method "<init>":(Ljava/lang/String;II)V
     145: putstatic     #17                 // Field delete_family_bloom_meta:Lorg/apache/hadoop/hbase/shaded/protobuf/generated/BucketCacheProtos$BlockType;
     148: new           #4                  // class org/apache/hadoop/hbase/shaded/protobuf/generated/BucketCacheProtos$BlockType
     151: dup
     152: ldc           #47                 // String trailer
     154: bipush        10
     156: bipush        10
     158: invokespecial #37                 // Method "<init>":(Ljava/lang/String;II)V
     161: putstatic     #18                 // Field trailer:Lorg/apache/hadoop/hbase/shaded/protobuf/generated/BucketCacheProtos$BlockType;
     164: new           #4                  // class org/apache/hadoop/hbase/shaded/protobuf/generated/BucketCacheProtos$BlockType
     167: dup
     168: ldc           #48                 // String index_v1
     170: bipush        11
     172: bipush        11
     174: invokespecial #37                 // Method "<init>":(Ljava/lang/String;II)V
     177: putstatic     #19                 // Field index_v1:Lorg/apache/hadoop/hbase/shaded/protobuf/generated/BucketCacheProtos$BlockType;
     180: bipush        12
     182: anewarray     #4                  // class org/apache/hadoop/hbase/shaded/protobuf/generated/BucketCacheProtos$BlockType
     185: dup
     186: iconst_0
     187: getstatic     #8                  // Field data:Lorg/apache/hadoop/hbase/shaded/protobuf/generated/BucketCacheProtos$BlockType;
     190: aastore
     191: dup
     192: iconst_1
     193: getstatic     #9                  // Field encoded_data:Lorg/apache/hadoop/hbase/shaded/protobuf/generated/BucketCacheProtos$BlockType;
     196: aastore
     197: dup
     198: iconst_2
     199: getstatic     #10                 // Field leaf_index:Lorg/apache/hadoop/hbase/shaded/protobuf/generated/BucketCacheProtos$BlockType;
     202: aastore
     203: dup
     204: iconst_3
     205: getstatic     #11                 // Field bloom_chunk:Lorg/apache/hadoop/hbase/shaded/protobuf/generated/BucketCacheProtos$BlockType;
     208: aastore
     209: dup
     210: iconst_4
     211: getstatic     #12                 // Field meta:Lorg/apache/hadoop/hbase/shaded/protobuf/generated/BucketCacheProtos$BlockType;
     214: aastore
     215: dup
     216: iconst_5
     217: getstatic     #13                 // Field intermediate_index:Lorg/apache/hadoop/hbase/shaded/protobuf/generated/BucketCacheProtos$BlockType;
     220: aastore
     221: dup
     222: bipush        6
     224: getstatic     #14                 // Field root_index:Lorg/apache/hadoop/hbase/shaded/protobuf/generated/BucketCacheProtos$BlockType;
     227: aastore
     228: dup
     229: bipush        7
     231: getstatic     #15                 // Field file_info:Lorg/apache/hadoop/hbase/shaded/protobuf/generated/BucketCacheProtos$BlockType;
     234: aastore
     235: dup
     236: bipush        8
     238: getstatic     #16                 // Field general_bloom_meta:Lorg/apache/hadoop/hbase/shaded/protobuf/generated/BucketCacheProtos$BlockType;
     241: aastore
     242: dup
     243: bipush        9
     245: getstatic     #17                 // Field delete_family_bloom_meta:Lorg/apache/hadoop/hbase/shaded/protobuf/generated/BucketCacheProtos$BlockType;
     248: aastore
     249: dup
     250: bipush        10
     252: getstatic     #18                 // Field trailer:Lorg/apache/hadoop/hbase/shaded/protobuf/generated/BucketCacheProtos$BlockType;
     255: aastore
     256: dup
     257: bipush        11
     259: getstatic     #19                 // Field index_v1:Lorg/apache/hadoop/hbase/shaded/protobuf/generated/BucketCacheProtos$BlockType;
     262: aastore
     263: putstatic     #1                  // Field $VALUES:[Lorg/apache/hadoop/hbase/shaded/protobuf/generated/BucketCacheProtos$BlockType;
     266: new           #49                 // class org/apache/hadoop/hbase/shaded/protobuf/generated/BucketCacheProtos$BlockType$1
     269: dup
     270: invokespecial #50                 // Method org/apache/hadoop/hbase/shaded/protobuf/generated/BucketCacheProtos$BlockType$1."<init>":()V
     273: putstatic     #20                 // Field internalValueMap:Lorg/apache/hbase/thirdparty/com/google/protobuf/Internal$EnumLiteMap;
     276: invokestatic  #51                 // Method values:()[Lorg/apache/hadoop/hbase/shaded/protobuf/generated/BucketCacheProtos$BlockType;
     279: putstatic     #33                 // Field VALUES:[Lorg/apache/hadoop/hbase/shaded/protobuf/generated/BucketCacheProtos$BlockType;
     282: return
}
