Compiled from "BufferedMutatorImpl.java"
class org.apache.hadoop.hbase.client.BufferedMutatorImpl$QueueRowAccess implements org.apache.hadoop.hbase.client.RowAccess<org.apache.hadoop.hbase.client.Row>, java.io.Closeable {
  final org.apache.hadoop.hbase.client.BufferedMutatorImpl this$0;

  org.apache.hadoop.hbase.client.BufferedMutatorImpl$QueueRowAccess(org.apache.hadoop.hbase.client.BufferedMutatorImpl);
    Code:
       0: aload_0
       1: aload_1
       2: putfield      #4                  // Field this$0:Lorg/apache/hadoop/hbase/client/BufferedMutatorImpl;
       5: aload_0
       6: invokespecial #5                  // Method java/lang/Object."<init>":()V
       9: aload_0
      10: aload_0
      11: getfield      #4                  // Field this$0:Lorg/apache/hadoop/hbase/client/BufferedMutatorImpl;
      14: invokestatic  #6                  // Method org/apache/hadoop/hbase/client/BufferedMutatorImpl.access$300:(Lorg/apache/hadoop/hbase/client/BufferedMutatorImpl;)Ljava/util/concurrent/atomic/AtomicInteger;
      17: iconst_0
      18: invokevirtual #7                  // Method java/util/concurrent/atomic/AtomicInteger.getAndSet:(I)I
      21: putfield      #3                  // Field remainder:I
      24: aload_0
      25: aconst_null
      26: putfield      #1                  // Field last:Lorg/apache/hadoop/hbase/client/Mutation;
      29: return

  public void close();
    Code:
       0: aload_0
       1: invokespecial #2                  // Method restoreLastMutation:()V
       4: aload_0
       5: getfield      #3                  // Field remainder:I
       8: ifle          31
      11: aload_0
      12: getfield      #4                  // Field this$0:Lorg/apache/hadoop/hbase/client/BufferedMutatorImpl;
      15: invokestatic  #6                  // Method org/apache/hadoop/hbase/client/BufferedMutatorImpl.access$300:(Lorg/apache/hadoop/hbase/client/BufferedMutatorImpl;)Ljava/util/concurrent/atomic/AtomicInteger;
      18: aload_0
      19: getfield      #3                  // Field remainder:I
      22: invokevirtual #13                 // Method java/util/concurrent/atomic/AtomicInteger.addAndGet:(I)I
      25: pop
      26: aload_0
      27: iconst_0
      28: putfield      #3                  // Field remainder:I
      31: return

  public java.util.Iterator<org.apache.hadoop.hbase.client.Row> iterator();
    Code:
       0: new           #14                 // class org/apache/hadoop/hbase/client/BufferedMutatorImpl$QueueRowAccess$1
       3: dup
       4: aload_0
       5: invokespecial #15                 // Method org/apache/hadoop/hbase/client/BufferedMutatorImpl$QueueRowAccess$1."<init>":(Lorg/apache/hadoop/hbase/client/BufferedMutatorImpl$QueueRowAccess;)V
       8: areturn

  public int size();
    Code:
       0: aload_0
       1: getfield      #3                  // Field remainder:I
       4: ireturn

  public boolean isEmpty();
    Code:
       0: aload_0
       1: getfield      #3                  // Field remainder:I
       4: ifgt          11
       7: iconst_1
       8: goto          12
      11: iconst_0
      12: ireturn

  static int access$600(org.apache.hadoop.hbase.client.BufferedMutatorImpl$QueueRowAccess);
    Code:
       0: aload_0
       1: getfield      #3                  // Field remainder:I
       4: ireturn

  static void access$700(org.apache.hadoop.hbase.client.BufferedMutatorImpl$QueueRowAccess);
    Code:
       0: aload_0
       1: invokespecial #2                  // Method restoreLastMutation:()V
       4: return

  static org.apache.hadoop.hbase.client.Mutation access$802(org.apache.hadoop.hbase.client.BufferedMutatorImpl$QueueRowAccess, org.apache.hadoop.hbase.client.Mutation);
    Code:
       0: aload_0
       1: aload_1
       2: dup_x1
       3: putfield      #1                  // Field last:Lorg/apache/hadoop/hbase/client/Mutation;
       6: areturn

  static org.apache.hadoop.hbase.client.Mutation access$800(org.apache.hadoop.hbase.client.BufferedMutatorImpl$QueueRowAccess);
    Code:
       0: aload_0
       1: getfield      #1                  // Field last:Lorg/apache/hadoop/hbase/client/Mutation;
       4: areturn

  static int access$606(org.apache.hadoop.hbase.client.BufferedMutatorImpl$QueueRowAccess);
    Code:
       0: aload_0
       1: dup
       2: getfield      #3                  // Field remainder:I
       5: iconst_1
       6: isub
       7: dup_x1
       8: putfield      #3                  // Field remainder:I
      11: ireturn
}
