Compiled from "BulkLoadCellFilter.java"
public class org.apache.hadoop.hbase.replication.BulkLoadCellFilter {
  public org.apache.hadoop.hbase.replication.BulkLoadCellFilter();
    Code:
       0: aload_0
       1: invokespecial #1                  // Method java/lang/Object."<init>":()V
       4: aload_0
       5: getstatic     #2                  // Field org/apache/hadoop/hbase/CellBuilderType.SHALLOW_COPY:Lorg/apache/hadoop/hbase/CellBuilderType;
       8: invokestatic  #3                  // Method org/apache/hadoop/hbase/ExtendedCellBuilderFactory.create:(Lorg/apache/hadoop/hbase/CellBuilderType;)Lorg/apache/hadoop/hbase/ExtendedCellBuilder;
      11: putfield      #4                  // Field cellBuilder:Lorg/apache/hadoop/hbase/ExtendedCellBuilder;
      14: return

  public org.apache.hadoop.hbase.Cell filterCell(org.apache.hadoop.hbase.Cell, org.apache.hbase.thirdparty.com.google.common.base.Predicate<byte[]>);
    Code:
       0: aconst_null
       1: astore        4
       3: aload_1
       4: invokestatic  #5                  // Method org/apache/hadoop/hbase/wal/WALEdit.getBulkLoadDescriptor:(Lorg/apache/hadoop/hbase/Cell;)Lorg/apache/hadoop/hbase/shaded/protobuf/generated/WALProtos$BulkLoadDescriptor;
       7: astore        4
       9: goto          28
      12: astore        5
      14: getstatic     #7                  // Field LOG:Lorg/slf4j/Logger;
      17: ldc           #8                  // String Failed to get bulk load events information from the WAL file.
      19: aload         5
      21: invokeinterface #9,  3            // InterfaceMethod org/slf4j/Logger.warn:(Ljava/lang/String;Ljava/lang/Throwable;)V
      26: aload_1
      27: areturn
      28: aload         4
      30: invokevirtual #10                 // Method org/apache/hadoop/hbase/shaded/protobuf/generated/WALProtos$BulkLoadDescriptor.getStoresList:()Ljava/util/List;
      33: astore        5
      35: new           #11                 // class java/util/ArrayList
      38: dup
      39: aload         5
      41: invokespecial #12                 // Method java/util/ArrayList."<init>":(Ljava/util/Collection;)V
      44: astore        6
      46: aload         6
      48: invokeinterface #13,  1           // InterfaceMethod java/util/List.iterator:()Ljava/util/Iterator;
      53: astore        7
      55: iconst_0
      56: istore        8
      58: aload         7
      60: invokeinterface #14,  1           // InterfaceMethod java/util/Iterator.hasNext:()Z
      65: ifeq          112
      68: aload         7
      70: invokeinterface #15,  1           // InterfaceMethod java/util/Iterator.next:()Ljava/lang/Object;
      75: checkcast     #16                 // class org/apache/hadoop/hbase/shaded/protobuf/generated/WALProtos$StoreDescriptor
      78: astore        9
      80: aload         9
      82: invokevirtual #17                 // Method org/apache/hadoop/hbase/shaded/protobuf/generated/WALProtos$StoreDescriptor.getFamilyName:()Lorg/apache/hbase/thirdparty/com/google/protobuf/ByteString;
      85: invokevirtual #18                 // Method org/apache/hbase/thirdparty/com/google/protobuf/ByteString.toByteArray:()[B
      88: astore_3
      89: aload_2
      90: aload_3
      91: invokeinterface #19,  2           // InterfaceMethod org/apache/hbase/thirdparty/com/google/common/base/Predicate.apply:(Ljava/lang/Object;)Z
      96: ifeq          109
      99: aload         7
     101: invokeinterface #20,  1           // InterfaceMethod java/util/Iterator.remove:()V
     106: iconst_1
     107: istore        8
     109: goto          58
     112: iload         8
     114: ifne          119
     117: aload_1
     118: areturn
     119: aload         6
     121: invokeinterface #21,  1           // InterfaceMethod java/util/List.isEmpty:()Z
     126: ifeq          131
     129: aconst_null
     130: areturn
     131: invokestatic  #22                 // Method org/apache/hadoop/hbase/shaded/protobuf/generated/WALProtos$BulkLoadDescriptor.newBuilder:()Lorg/apache/hadoop/hbase/shaded/protobuf/generated/WALProtos$BulkLoadDescriptor$Builder;
     134: aload         4
     136: invokevirtual #23                 // Method org/apache/hadoop/hbase/shaded/protobuf/generated/WALProtos$BulkLoadDescriptor.getTableName:()Lorg/apache/hadoop/hbase/shaded/protobuf/generated/HBaseProtos$TableName;
     139: invokevirtual #24                 // Method org/apache/hadoop/hbase/shaded/protobuf/generated/WALProtos$BulkLoadDescriptor$Builder.setTableName:(Lorg/apache/hadoop/hbase/shaded/protobuf/generated/HBaseProtos$TableName;)Lorg/apache/hadoop/hbase/shaded/protobuf/generated/WALProtos$BulkLoadDescriptor$Builder;
     142: aload         4
     144: invokevirtual #25                 // Method org/apache/hadoop/hbase/shaded/protobuf/generated/WALProtos$BulkLoadDescriptor.getEncodedRegionName:()Lorg/apache/hbase/thirdparty/com/google/protobuf/ByteString;
     147: invokevirtual #26                 // Method org/apache/hadoop/hbase/shaded/protobuf/generated/WALProtos$BulkLoadDescriptor$Builder.setEncodedRegionName:(Lorg/apache/hbase/thirdparty/com/google/protobuf/ByteString;)Lorg/apache/hadoop/hbase/shaded/protobuf/generated/WALProtos$BulkLoadDescriptor$Builder;
     150: aload         4
     152: invokevirtual #27                 // Method org/apache/hadoop/hbase/shaded/protobuf/generated/WALProtos$BulkLoadDescriptor.getBulkloadSeqNum:()J
     155: invokevirtual #28                 // Method org/apache/hadoop/hbase/shaded/protobuf/generated/WALProtos$BulkLoadDescriptor$Builder.setBulkloadSeqNum:(J)Lorg/apache/hadoop/hbase/shaded/protobuf/generated/WALProtos$BulkLoadDescriptor$Builder;
     158: astore        9
     160: aload         9
     162: aload         6
     164: invokevirtual #29                 // Method org/apache/hadoop/hbase/shaded/protobuf/generated/WALProtos$BulkLoadDescriptor$Builder.addAllStores:(Ljava/lang/Iterable;)Lorg/apache/hadoop/hbase/shaded/protobuf/generated/WALProtos$BulkLoadDescriptor$Builder;
     167: pop
     168: aload         9
     170: invokevirtual #30                 // Method org/apache/hadoop/hbase/shaded/protobuf/generated/WALProtos$BulkLoadDescriptor$Builder.build:()Lorg/apache/hadoop/hbase/shaded/protobuf/generated/WALProtos$BulkLoadDescriptor;
     173: astore        10
     175: aload_0
     176: getfield      #4                  // Field cellBuilder:Lorg/apache/hadoop/hbase/ExtendedCellBuilder;
     179: invokeinterface #31,  1           // InterfaceMethod org/apache/hadoop/hbase/ExtendedCellBuilder.clear:()Lorg/apache/hadoop/hbase/ExtendedCellBuilder;
     184: aload_1
     185: invokestatic  #32                 // Method org/apache/hadoop/hbase/CellUtil.cloneRow:(Lorg/apache/hadoop/hbase/Cell;)[B
     188: invokeinterface #33,  2           // InterfaceMethod org/apache/hadoop/hbase/ExtendedCellBuilder.setRow:([B)Lorg/apache/hadoop/hbase/ExtendedCellBuilder;
     193: getstatic     #34                 // Field org/apache/hadoop/hbase/wal/WALEdit.METAFAMILY:[B
     196: invokeinterface #35,  2           // InterfaceMethod org/apache/hadoop/hbase/ExtendedCellBuilder.setFamily:([B)Lorg/apache/hadoop/hbase/ExtendedCellBuilder;
     201: getstatic     #36                 // Field org/apache/hadoop/hbase/wal/WALEdit.BULK_LOAD:[B
     204: invokeinterface #37,  2           // InterfaceMethod org/apache/hadoop/hbase/ExtendedCellBuilder.setQualifier:([B)Lorg/apache/hadoop/hbase/ExtendedCellBuilder;
     209: aload_1
     210: invokeinterface #38,  1           // InterfaceMethod org/apache/hadoop/hbase/Cell.getTimestamp:()J
     215: invokeinterface #39,  3           // InterfaceMethod org/apache/hadoop/hbase/ExtendedCellBuilder.setTimestamp:(J)Lorg/apache/hadoop/hbase/ExtendedCellBuilder;
     220: aload_1
     221: invokeinterface #40,  1           // InterfaceMethod org/apache/hadoop/hbase/Cell.getTypeByte:()B
     226: invokeinterface #41,  2           // InterfaceMethod org/apache/hadoop/hbase/ExtendedCellBuilder.setType:(B)Lorg/apache/hadoop/hbase/ExtendedCellBuilder;
     231: aload         10
     233: invokevirtual #42                 // Method org/apache/hadoop/hbase/shaded/protobuf/generated/WALProtos$BulkLoadDescriptor.toByteArray:()[B
     236: invokeinterface #43,  2           // InterfaceMethod org/apache/hadoop/hbase/ExtendedCellBuilder.setValue:([B)Lorg/apache/hadoop/hbase/ExtendedCellBuilder;
     241: invokeinterface #44,  1           // InterfaceMethod org/apache/hadoop/hbase/ExtendedCellBuilder.build:()Lorg/apache/hadoop/hbase/ExtendedCell;
     246: areturn
    Exception table:
       from    to  target type
           3     9    12   Class java/io/IOException

  static {};
    Code:
       0: ldc           #45                 // class org/apache/hadoop/hbase/replication/BulkLoadCellFilter
       2: invokestatic  #46                 // Method org/slf4j/LoggerFactory.getLogger:(Ljava/lang/Class;)Lorg/slf4j/Logger;
       5: putstatic     #7                  // Field LOG:Lorg/slf4j/Logger;
       8: return
}
