Compiled from "BulkLoadHFilesTool.java"
public class org.apache.hadoop.hbase.tool.BulkLoadHFilesTool extends org.apache.hadoop.hbase.tool.LoadIncrementalHFiles implements org.apache.hadoop.hbase.tool.BulkLoadHFiles {
  public static final java.lang.String NAME;

  public org.apache.hadoop.hbase.tool.BulkLoadHFilesTool(org.apache.hadoop.conf.Configuration);
    Code:
       0: aload_0
       1: aload_1
       2: invokespecial #1                  // Method org/apache/hadoop/hbase/tool/LoadIncrementalHFiles."<init>":(Lorg/apache/hadoop/conf/Configuration;)V
       5: return

  public java.util.Map<org.apache.hadoop.hbase.tool.BulkLoadHFiles$LoadQueueItem, java.nio.ByteBuffer> bulkLoad(org.apache.hadoop.hbase.TableName, java.util.Map<byte[], java.util.List<org.apache.hadoop.fs.Path>>) throws org.apache.hadoop.hbase.TableNotFoundException, java.io.IOException;
    Code:
       0: aload_0
       1: aload_0
       2: aload_2
       3: aload_1
       4: invokevirtual #9                  // Method run:(Ljava/util/Map;Lorg/apache/hadoop/hbase/TableName;)Ljava/util/Map;
       7: invokespecial #10                 // Method convert:(Ljava/util/Map;)Ljava/util/Map;
      10: areturn

  public java.util.Map<org.apache.hadoop.hbase.tool.BulkLoadHFiles$LoadQueueItem, java.nio.ByteBuffer> bulkLoad(org.apache.hadoop.hbase.TableName, org.apache.hadoop.fs.Path) throws org.apache.hadoop.hbase.TableNotFoundException, java.io.IOException;
    Code:
       0: aload_0
       1: aload_0
       2: aload_2
       3: aload_1
       4: invokevirtual #11                 // Method run:(Lorg/apache/hadoop/fs/Path;Lorg/apache/hadoop/hbase/TableName;)Ljava/util/Map;
       7: invokespecial #10                 // Method convert:(Ljava/util/Map;)Ljava/util/Map;
      10: areturn

  public static void main(java.lang.String[]) throws java.lang.Exception;
    Code:
       0: invokestatic  #12                 // Method org/apache/hadoop/hbase/HBaseConfiguration.create:()Lorg/apache/hadoop/conf/Configuration;
       3: astore_1
       4: aload_1
       5: new           #13                 // class org/apache/hadoop/hbase/tool/BulkLoadHFilesTool
       8: dup
       9: aload_1
      10: invokespecial #14                 // Method "<init>":(Lorg/apache/hadoop/conf/Configuration;)V
      13: aload_0
      14: invokestatic  #15                 // Method org/apache/hadoop/util/ToolRunner.run:(Lorg/apache/hadoop/conf/Configuration;Lorg/apache/hadoop/util/Tool;[Ljava/lang/String;)I
      17: istore_2
      18: iload_2
      19: invokestatic  #16                 // Method java/lang/System.exit:(I)V
      22: return
}
