Compiled from "Bytes.java"
class org.apache.hadoop.hbase.util.Bytes$ConverterHolder {
  static final java.lang.String UNSAFE_CONVERTER_NAME;

  static final org.apache.hadoop.hbase.util.Bytes$Converter BEST_CONVERTER;

  org.apache.hadoop.hbase.util.Bytes$ConverterHolder();
    Code:
       0: aload_0
       1: invokespecial #1                  // Method java/lang/Object."<init>":()V
       4: return

  static org.apache.hadoop.hbase.util.Bytes$Converter getBestConverter();
    Code:
       0: getstatic     #2                  // Field UNSAFE_CONVERTER_NAME:Ljava/lang/String;
       3: invokestatic  #3                  // Method java/lang/Class.forName:(Ljava/lang/String;)Ljava/lang/Class;
       6: astore_0
       7: aload_0
       8: iconst_0
       9: anewarray     #4                  // class java/lang/Class
      12: invokevirtual #5                  // Method java/lang/Class.getConstructor:([Ljava/lang/Class;)Ljava/lang/reflect/Constructor;
      15: iconst_0
      16: anewarray     #6                  // class java/lang/Object
      19: invokevirtual #7                  // Method java/lang/reflect/Constructor.newInstance:([Ljava/lang/Object;)Ljava/lang/Object;
      22: checkcast     #8                  // class org/apache/hadoop/hbase/util/Bytes$Converter
      25: astore_1
      26: aload_1
      27: areturn
      28: astore_0
      29: getstatic     #10                 // Field org/apache/hadoop/hbase/util/Bytes$ConverterHolder$PureJavaConverter.INSTANCE:Lorg/apache/hadoop/hbase/util/Bytes$ConverterHolder$PureJavaConverter;
      32: areturn
    Exception table:
       from    to  target type
           0    27    28   Class java/lang/Throwable

  static {};
    Code:
       0: new           #11                 // class java/lang/StringBuilder
       3: dup
       4: invokespecial #12                 // Method java/lang/StringBuilder."<init>":()V
       7: ldc           #13                 // class org/apache/hadoop/hbase/util/Bytes$ConverterHolder
       9: invokevirtual #14                 // Method java/lang/Class.getName:()Ljava/lang/String;
      12: invokevirtual #15                 // Method java/lang/StringBuilder.append:(Ljava/lang/String;)Ljava/lang/StringBuilder;
      15: ldc           #16                 // String $UnsafeConverter
      17: invokevirtual #15                 // Method java/lang/StringBuilder.append:(Ljava/lang/String;)Ljava/lang/StringBuilder;
      20: invokevirtual #17                 // Method java/lang/StringBuilder.toString:()Ljava/lang/String;
      23: putstatic     #2                  // Field UNSAFE_CONVERTER_NAME:Ljava/lang/String;
      26: invokestatic  #18                 // Method getBestConverter:()Lorg/apache/hadoop/hbase/util/Bytes$Converter;
      29: putstatic     #19                 // Field BEST_CONVERTER:Lorg/apache/hadoop/hbase/util/Bytes$Converter;
      32: return
}
