Compiled from "Bytes.java"
public class org.apache.hadoop.hbase.util.Bytes$ByteArrayComparator implements org.apache.hadoop.io.RawComparator<byte[]> {
  public org.apache.hadoop.hbase.util.Bytes$ByteArrayComparator();
    Code:
       0: aload_0
       1: invokespecial #1                  // Method java/lang/Object."<init>":()V
       4: return

  public int compare(byte[], byte[]);
    Code:
       0: aload_1
       1: aload_2
       2: invokestatic  #2                  // Method org/apache/hadoop/hbase/util/Bytes.compareTo:([B[B)I
       5: ireturn

  public int compare(byte[], int, int, byte[], int, int);
    Code:
       0: getstatic     #3                  // Field org/apache/hadoop/hbase/util/Bytes$LexicographicalComparerHolder.BEST_COMPARER:Lorg/apache/hadoop/hbase/util/Bytes$Comparer;
       3: aload_1
       4: iload_2
       5: iload_3
       6: aload         4
       8: iload         5
      10: iload         6
      12: invokeinterface #4,  7            // InterfaceMethod org/apache/hadoop/hbase/util/Bytes$Comparer.compareTo:(Ljava/lang/Object;IILjava/lang/Object;II)I
      17: ireturn

  public int compare(java.lang.Object, java.lang.Object);
    Code:
       0: aload_0
       1: aload_1
       2: checkcast     #5                  // class "[B"
       5: aload_2
       6: checkcast     #5                  // class "[B"
       9: invokevirtual #6                  // Method compare:([B[B)I
      12: ireturn
}
