Compiled from "ByteBufferUtils.java"
final class org.apache.hadoop.hbase.util.ByteBufferUtils$ComparerHolder$PureJavaComparer extends org.apache.hadoop.hbase.util.ByteBufferUtils$Comparer {
  static final org.apache.hadoop.hbase.util.ByteBufferUtils$ComparerHolder$PureJavaComparer INSTANCE;

  public int compareTo(byte[], int, int, java.nio.ByteBuffer, int, int);
    Code:
       0: iload_2
       1: iload_3
       2: iadd
       3: istore        7
       5: iload         5
       7: iload         6
       9: iadd
      10: istore        8
      12: iload_2
      13: istore        9
      15: iload         5
      17: istore        10
      19: iload         9
      21: iload         7
      23: if_icmpge     78
      26: iload         10
      28: iload         8
      30: if_icmpge     78
      33: aload_1
      34: iload         9
      36: baload
      37: sipush        255
      40: iand
      41: istore        11
      43: aload         4
      45: iload         10
      47: invokevirtual #2                  // Method java/nio/ByteBuffer.get:(I)B
      50: sipush        255
      53: iand
      54: istore        12
      56: iload         11
      58: iload         12
      60: if_icmpeq     69
      63: iload         11
      65: iload         12
      67: isub
      68: ireturn
      69: iinc          9, 1
      72: iinc          10, 1
      75: goto          19
      78: iload_3
      79: iload         6
      81: isub
      82: ireturn

  public int compareTo(java.nio.ByteBuffer, int, int, java.nio.ByteBuffer, int, int);
    Code:
       0: iload_2
       1: iload_3
       2: iadd
       3: istore        7
       5: iload         5
       7: iload         6
       9: iadd
      10: istore        8
      12: iload_2
      13: istore        9
      15: iload         5
      17: istore        10
      19: iload         9
      21: iload         7
      23: if_icmpge     80
      26: iload         10
      28: iload         8
      30: if_icmpge     80
      33: aload_1
      34: iload         9
      36: invokevirtual #2                  // Method java/nio/ByteBuffer.get:(I)B
      39: sipush        255
      42: iand
      43: istore        11
      45: aload         4
      47: iload         10
      49: invokevirtual #2                  // Method java/nio/ByteBuffer.get:(I)B
      52: sipush        255
      55: iand
      56: istore        12
      58: iload         11
      60: iload         12
      62: if_icmpeq     71
      65: iload         11
      67: iload         12
      69: isub
      70: ireturn
      71: iinc          9, 1
      74: iinc          10, 1
      77: goto          19
      80: iload_3
      81: iload         6
      83: isub
      84: ireturn

  static {};
    Code:
       0: new           #3                  // class org/apache/hadoop/hbase/util/ByteBufferUtils$ComparerHolder$PureJavaComparer
       3: dup
       4: invokespecial #4                  // Method "<init>":()V
       7: putstatic     #5                  // Field INSTANCE:Lorg/apache/hadoop/hbase/util/ByteBufferUtils$ComparerHolder$PureJavaComparer;
      10: return
}
