Compiled from "ByteArrayHashKey.java"
public class org.apache.hadoop.hbase.util.ByteArrayHashKey extends org.apache.hadoop.hbase.util.HashKey<byte[]> {
  public org.apache.hadoop.hbase.util.ByteArrayHashKey(byte[], int, int);
    Code:
       0: aload_0
       1: aload_1
       2: invokespecial #1                  // Method org/apache/hadoop/hbase/util/HashKey."<init>":(Ljava/lang/Object;)V
       5: aload_0
       6: iload_2
       7: putfield      #2                  // Field offset:I
      10: aload_0
      11: iload_3
      12: putfield      #3                  // Field length:I
      15: return

  public byte get(int);
    Code:
       0: aload_0
       1: getfield      #4                  // Field t:Ljava/lang/Object;
       4: checkcast     #5                  // class "[B"
       7: aload_0
       8: iload_1
       9: invokespecial #6                  // Method getAbsolutePos:(I)I
      12: baload
      13: ireturn

  public int length();
    Code:
       0: aload_0
       1: getfield      #3                  // Field length:I
       4: ireturn
}
