Compiled from "ByteArrayComparable.java"
public abstract class org.apache.hadoop.hbase.filter.ByteArrayComparable implements java.lang.Comparable<byte[]> {
  byte[] value;

  public org.apache.hadoop.hbase.filter.ByteArrayComparable(byte[]);
    Code:
       0: aload_0
       1: invokespecial #1                  // Method java/lang/Object."<init>":()V
       4: aload_0
       5: aload_1
       6: putfield      #2                  // Field value:[B
       9: return

  public byte[] getValue();
    Code:
       0: aload_0
       1: getfield      #2                  // Field value:[B
       4: areturn

  public abstract byte[] toByteArray();

  public static org.apache.hadoop.hbase.filter.ByteArrayComparable parseFrom(byte[]) throws org.apache.hadoop.hbase.exceptions.DeserializationException;
    Code:
       0: new           #3                  // class org/apache/hadoop/hbase/exceptions/DeserializationException
       3: dup
       4: ldc           #4                  // String parseFrom called on base ByteArrayComparable, but should be called on derived type
       6: invokespecial #5                  // Method org/apache/hadoop/hbase/exceptions/DeserializationException."<init>":(Ljava/lang/String;)V
       9: athrow

  boolean areSerializedFieldsEqual(org.apache.hadoop.hbase.filter.ByteArrayComparable);
    Code:
       0: aload_1
       1: aload_0
       2: if_acmpne     7
       5: iconst_1
       6: ireturn
       7: aload_0
       8: invokevirtual #6                  // Method getValue:()[B
      11: aload_1
      12: invokevirtual #6                  // Method getValue:()[B
      15: invokestatic  #7                  // Method org/apache/hadoop/hbase/util/Bytes.equals:([B[B)Z
      18: ireturn

  public int compareTo(byte[]);
    Code:
       0: aload_0
       1: aload_1
       2: iconst_0
       3: aload_1
       4: arraylength
       5: invokevirtual #8                  // Method compareTo:([BII)I
       8: ireturn

  public abstract int compareTo(byte[], int, int);

  public int compareTo(java.nio.ByteBuffer, int, int);
    Code:
       0: iload_3
       1: newarray       byte
       3: astore        4
       5: aload         4
       7: aload_1
       8: iload_2
       9: iconst_0
      10: iload_3
      11: invokestatic  #9                  // Method org/apache/hadoop/hbase/util/ByteBufferUtils.copyFromBufferToArray:([BLjava/nio/ByteBuffer;III)V
      14: aload_0
      15: aload         4
      17: invokevirtual #10                 // Method compareTo:([B)I
      20: ireturn

  public int compareTo(java.lang.Object);
    Code:
       0: aload_0
       1: aload_1
       2: checkcast     #11                 // class "[B"
       5: invokevirtual #10                 // Method compareTo:([B)I
       8: ireturn
}
