Compiled from "CacheTestUtils.java"
public class org.apache.hadoop.hbase.io.hfile.CacheTestUtils {
  public org.apache.hadoop.hbase.io.hfile.CacheTestUtils();
    Code:
       0: aload_0
       1: invokespecial #1                  // Method java/lang/Object."<init>":()V
       4: return

  public static void testHeapSizeChanges(org.apache.hadoop.hbase.io.hfile.BlockCache, int);
    Code:
       0: iload_1
       1: iconst_1
       2: invokestatic  #2                  // Method generateHFileBlocks:(II)[Lorg/apache/hadoop/hbase/io/hfile/CacheTestUtils$HFileBlockPair;
       5: astore_2
       6: aload_0
       7: checkcast     #3                  // class org/apache/hadoop/hbase/io/HeapSize
      10: invokeinterface #4,  1            // InterfaceMethod org/apache/hadoop/hbase/io/HeapSize.heapSize:()J
      15: lstore_3
      16: aload_0
      17: aload_2
      18: iconst_0
      19: aaload
      20: getfield      #5                  // Field org/apache/hadoop/hbase/io/hfile/CacheTestUtils$HFileBlockPair.blockName:Lorg/apache/hadoop/hbase/io/hfile/BlockCacheKey;
      23: aload_2
      24: iconst_0
      25: aaload
      26: getfield      #6                  // Field org/apache/hadoop/hbase/io/hfile/CacheTestUtils$HFileBlockPair.block:Lorg/apache/hadoop/hbase/io/hfile/HFileBlock;
      29: invokeinterface #7,  3            // InterfaceMethod org/apache/hadoop/hbase/io/hfile/BlockCache.cacheBlock:(Lorg/apache/hadoop/hbase/io/hfile/BlockCacheKey;Lorg/apache/hadoop/hbase/io/hfile/Cacheable;)V
      34: lload_3
      35: aload_0
      36: checkcast     #3                  // class org/apache/hadoop/hbase/io/HeapSize
      39: invokeinterface #4,  1            // InterfaceMethod org/apache/hadoop/hbase/io/HeapSize.heapSize:()J
      44: lcmp
      45: ifge          52
      48: iconst_1
      49: goto          53
      52: iconst_0
      53: invokestatic  #8                  // Method org/junit/Assert.assertTrue:(Z)V
      56: aload_0
      57: aload_2
      58: iconst_0
      59: aaload
      60: getfield      #5                  // Field org/apache/hadoop/hbase/io/hfile/CacheTestUtils$HFileBlockPair.blockName:Lorg/apache/hadoop/hbase/io/hfile/BlockCacheKey;
      63: invokeinterface #9,  2            // InterfaceMethod org/apache/hadoop/hbase/io/hfile/BlockCache.evictBlock:(Lorg/apache/hadoop/hbase/io/hfile/BlockCacheKey;)Z
      68: pop
      69: lload_3
      70: aload_0
      71: checkcast     #3                  // class org/apache/hadoop/hbase/io/HeapSize
      74: invokeinterface #4,  1            // InterfaceMethod org/apache/hadoop/hbase/io/HeapSize.heapSize:()J
      79: invokestatic  #10                 // Method org/junit/Assert.assertEquals:(JJ)V
      82: return

  public static void testCacheMultiThreaded(org.apache.hadoop.hbase.io.hfile.BlockCache, int, int, int, double) throws java.lang.Exception;
    Code:
       0: new           #11                 // class org/apache/hadoop/conf/Configuration
       3: dup
       4: invokespecial #12                 // Method org/apache/hadoop/conf/Configuration."<init>":()V
       7: astore        6
       9: new           #13                 // class org/apache/hadoop/hbase/MultithreadedTestUtil$TestContext
      12: dup
      13: aload         6
      15: invokespecial #14                 // Method org/apache/hadoop/hbase/MultithreadedTestUtil$TestContext."<init>":(Lorg/apache/hadoop/conf/Configuration;)V
      18: astore        7
      20: new           #15                 // class java/util/concurrent/atomic/AtomicInteger
      23: dup
      24: invokespecial #16                 // Method java/util/concurrent/atomic/AtomicInteger."<init>":()V
      27: astore        8
      29: new           #17                 // class java/util/concurrent/ConcurrentLinkedQueue
      32: dup
      33: invokespecial #18                 // Method java/util/concurrent/ConcurrentLinkedQueue."<init>":()V
      36: astore        9
      38: new           #15                 // class java/util/concurrent/atomic/AtomicInteger
      41: dup
      42: invokespecial #16                 // Method java/util/concurrent/atomic/AtomicInteger."<init>":()V
      45: astore        10
      47: new           #15                 // class java/util/concurrent/atomic/AtomicInteger
      50: dup
      51: invokespecial #16                 // Method java/util/concurrent/atomic/AtomicInteger."<init>":()V
      54: astore        11
      56: iload_3
      57: iload_1
      58: invokestatic  #2                  // Method generateHFileBlocks:(II)[Lorg/apache/hadoop/hbase/io/hfile/CacheTestUtils$HFileBlockPair;
      61: astore        12
      63: aload         9
      65: aload         12
      67: invokestatic  #19                 // Method java/util/Arrays.asList:([Ljava/lang/Object;)Ljava/util/List;
      70: invokevirtual #20                 // Method java/util/concurrent/ConcurrentLinkedQueue.addAll:(Ljava/util/Collection;)Z
      73: pop
      74: iconst_0
      75: istore        13
      77: iload         13
      79: iload_2
      80: if_icmpge     122
      83: new           #21                 // class org/apache/hadoop/hbase/io/hfile/CacheTestUtils$1
      86: dup
      87: aload         7
      89: aload         9
      91: aload_0
      92: aload         10
      94: aload         11
      96: aload         8
      98: invokespecial #22                 // Method org/apache/hadoop/hbase/io/hfile/CacheTestUtils$1."<init>":(Lorg/apache/hadoop/hbase/MultithreadedTestUtil$TestContext;Ljava/util/concurrent/ConcurrentLinkedQueue;Lorg/apache/hadoop/hbase/io/hfile/BlockCache;Ljava/util/concurrent/atomic/AtomicInteger;Ljava/util/concurrent/atomic/AtomicInteger;Ljava/util/concurrent/atomic/AtomicInteger;)V
     101: astore        14
     103: aload         14
     105: iconst_1
     106: invokevirtual #23                 // Method org/apache/hadoop/hbase/MultithreadedTestUtil$TestThread.setDaemon:(Z)V
     109: aload         7
     111: aload         14
     113: invokevirtual #24                 // Method org/apache/hadoop/hbase/MultithreadedTestUtil$TestContext.addThread:(Lorg/apache/hadoop/hbase/MultithreadedTestUtil$TestThread;)V
     116: iinc          13, 1
     119: goto          77
     122: aload         7
     124: invokevirtual #25                 // Method org/apache/hadoop/hbase/MultithreadedTestUtil$TestContext.startThreads:()V
     127: aload         9
     129: invokevirtual #26                 // Method java/util/concurrent/ConcurrentLinkedQueue.isEmpty:()Z
     132: ifne          152
     135: aload         7
     137: invokevirtual #27                 // Method org/apache/hadoop/hbase/MultithreadedTestUtil$TestContext.shouldRun:()Z
     140: ifeq          152
     143: ldc2_w        #28                 // long 10l
     146: invokestatic  #30                 // Method java/lang/Thread.sleep:(J)V
     149: goto          127
     152: aload         7
     154: invokevirtual #31                 // Method org/apache/hadoop/hbase/MultithreadedTestUtil$TestContext.stop:()V
     157: aload         10
     159: invokevirtual #32                 // Method java/util/concurrent/atomic/AtomicInteger.get:()I
     162: i2d
     163: aload         10
     165: invokevirtual #32                 // Method java/util/concurrent/atomic/AtomicInteger.get:()I
     168: i2d
     169: aload         11
     171: invokevirtual #32                 // Method java/util/concurrent/atomic/AtomicInteger.get:()I
     174: i2d
     175: dadd
     176: ddiv
     177: dload         4
     179: dcmpg
     180: ifge          222
     183: new           #33                 // class java/lang/StringBuilder
     186: dup
     187: invokespecial #34                 // Method java/lang/StringBuilder."<init>":()V
     190: ldc           #35                 // String Too many nulls returned. Hits:
     192: invokevirtual #36                 // Method java/lang/StringBuilder.append:(Ljava/lang/String;)Ljava/lang/StringBuilder;
     195: aload         10
     197: invokevirtual #32                 // Method java/util/concurrent/atomic/AtomicInteger.get:()I
     200: invokevirtual #37                 // Method java/lang/StringBuilder.append:(I)Ljava/lang/StringBuilder;
     203: ldc           #38                 // String  Misses:
     205: invokevirtual #36                 // Method java/lang/StringBuilder.append:(Ljava/lang/String;)Ljava/lang/StringBuilder;
     208: aload         11
     210: invokevirtual #32                 // Method java/util/concurrent/atomic/AtomicInteger.get:()I
     213: invokevirtual #37                 // Method java/lang/StringBuilder.append:(I)Ljava/lang/StringBuilder;
     216: invokevirtual #39                 // Method java/lang/StringBuilder.toString:()Ljava/lang/String;
     219: invokestatic  #40                 // Method org/junit/Assert.fail:(Ljava/lang/String;)V
     222: return

  public static void testCacheSimple(org.apache.hadoop.hbase.io.hfile.BlockCache, int, int) throws java.lang.Exception;
    Code:
       0: iload_1
       1: iload_2
       2: invokestatic  #2                  // Method generateHFileBlocks:(II)[Lorg/apache/hadoop/hbase/io/hfile/CacheTestUtils$HFileBlockPair;
       5: astore_3
       6: aload_3
       7: astore        4
       9: aload         4
      11: arraylength
      12: istore        5
      14: iconst_0
      15: istore        6
      17: iload         6
      19: iload         5
      21: if_icmpge     54
      24: aload         4
      26: iload         6
      28: aaload
      29: astore        7
      31: aload_0
      32: aload         7
      34: getfield      #5                  // Field org/apache/hadoop/hbase/io/hfile/CacheTestUtils$HFileBlockPair.blockName:Lorg/apache/hadoop/hbase/io/hfile/BlockCacheKey;
      37: iconst_1
      38: iconst_0
      39: iconst_1
      40: invokeinterface #41,  5           // InterfaceMethod org/apache/hadoop/hbase/io/hfile/BlockCache.getBlock:(Lorg/apache/hadoop/hbase/io/hfile/BlockCacheKey;ZZZ)Lorg/apache/hadoop/hbase/io/hfile/Cacheable;
      45: invokestatic  #42                 // Method org/junit/Assert.assertNull:(Ljava/lang/Object;)V
      48: iinc          6, 1
      51: goto          17
      54: aload_3
      55: astore        4
      57: aload         4
      59: arraylength
      60: istore        5
      62: iconst_0
      63: istore        6
      65: iload         6
      67: iload         5
      69: if_icmpge     101
      72: aload         4
      74: iload         6
      76: aaload
      77: astore        7
      79: aload_0
      80: aload         7
      82: getfield      #5                  // Field org/apache/hadoop/hbase/io/hfile/CacheTestUtils$HFileBlockPair.blockName:Lorg/apache/hadoop/hbase/io/hfile/BlockCacheKey;
      85: aload         7
      87: getfield      #6                  // Field org/apache/hadoop/hbase/io/hfile/CacheTestUtils$HFileBlockPair.block:Lorg/apache/hadoop/hbase/io/hfile/HFileBlock;
      90: invokeinterface #7,  3            // InterfaceMethod org/apache/hadoop/hbase/io/hfile/BlockCache.cacheBlock:(Lorg/apache/hadoop/hbase/io/hfile/BlockCacheKey;Lorg/apache/hadoop/hbase/io/hfile/Cacheable;)V
      95: iinc          6, 1
      98: goto          65
     101: aload_3
     102: astore        4
     104: aload         4
     106: arraylength
     107: istore        5
     109: iconst_0
     110: istore        6
     112: iload         6
     114: iload         5
     116: if_icmpge     166
     119: aload         4
     121: iload         6
     123: aaload
     124: astore        7
     126: aload_0
     127: aload         7
     129: getfield      #5                  // Field org/apache/hadoop/hbase/io/hfile/CacheTestUtils$HFileBlockPair.blockName:Lorg/apache/hadoop/hbase/io/hfile/BlockCacheKey;
     132: iconst_1
     133: iconst_0
     134: iconst_1
     135: invokeinterface #41,  5           // InterfaceMethod org/apache/hadoop/hbase/io/hfile/BlockCache.getBlock:(Lorg/apache/hadoop/hbase/io/hfile/BlockCacheKey;ZZZ)Lorg/apache/hadoop/hbase/io/hfile/Cacheable;
     140: checkcast     #43                 // class org/apache/hadoop/hbase/io/hfile/HFileBlock
     143: astore        8
     145: aload         8
     147: ifnull        160
     150: aload         7
     152: getfield      #6                  // Field org/apache/hadoop/hbase/io/hfile/CacheTestUtils$HFileBlockPair.block:Lorg/apache/hadoop/hbase/io/hfile/HFileBlock;
     155: aload         8
     157: invokestatic  #44                 // Method org/junit/Assert.assertEquals:(Ljava/lang/Object;Ljava/lang/Object;)V
     160: iinc          6, 1
     163: goto          112
     166: aload_3
     167: astore        4
     169: aload         4
     171: arraylength
     172: istore        5
     174: iconst_0
     175: istore        6
     177: iload         6
     179: iload         5
     181: if_icmpge     247
     184: aload         4
     186: iload         6
     188: aaload
     189: astore        7
     191: aload_0
     192: aload         7
     194: getfield      #5                  // Field org/apache/hadoop/hbase/io/hfile/CacheTestUtils$HFileBlockPair.blockName:Lorg/apache/hadoop/hbase/io/hfile/BlockCacheKey;
     197: iconst_1
     198: iconst_0
     199: iconst_1
     200: invokeinterface #41,  5           // InterfaceMethod org/apache/hadoop/hbase/io/hfile/BlockCache.getBlock:(Lorg/apache/hadoop/hbase/io/hfile/BlockCacheKey;ZZZ)Lorg/apache/hadoop/hbase/io/hfile/Cacheable;
     205: ifnull        236
     208: aload_0
     209: aload         7
     211: getfield      #5                  // Field org/apache/hadoop/hbase/io/hfile/CacheTestUtils$HFileBlockPair.blockName:Lorg/apache/hadoop/hbase/io/hfile/BlockCacheKey;
     214: aload         7
     216: getfield      #6                  // Field org/apache/hadoop/hbase/io/hfile/CacheTestUtils$HFileBlockPair.block:Lorg/apache/hadoop/hbase/io/hfile/HFileBlock;
     219: invokeinterface #7,  3            // InterfaceMethod org/apache/hadoop/hbase/io/hfile/BlockCache.cacheBlock:(Lorg/apache/hadoop/hbase/io/hfile/BlockCacheKey;Lorg/apache/hadoop/hbase/io/hfile/Cacheable;)V
     224: aload_0
     225: instanceof    #45                 // class org/apache/hadoop/hbase/io/hfile/bucket/BucketCache
     228: ifne          236
     231: ldc           #46                 // String Cache should not allow re-caching a block
     233: invokestatic  #40                 // Method org/junit/Assert.fail:(Ljava/lang/String;)V
     236: goto          241
     239: astore        8
     241: iinc          6, 1
     244: goto          177
     247: return
    Exception table:
       from    to  target type
         191   236   239   Class java/lang/RuntimeException

  public static void hammerSingleKey(org.apache.hadoop.hbase.io.hfile.BlockCache, int, int, int) throws java.lang.Exception;
    Code:
       0: new           #48                 // class org/apache/hadoop/hbase/io/hfile/BlockCacheKey
       3: dup
       4: ldc           #49                 // String key
       6: lconst_0
       7: invokespecial #50                 // Method org/apache/hadoop/hbase/io/hfile/BlockCacheKey."<init>":(Ljava/lang/String;J)V
      10: astore        4
      12: sipush        5120
      15: newarray       byte
      17: astore        5
      19: aload         5
      21: iconst_5
      22: invokestatic  #51                 // Method java/util/Arrays.fill:([BB)V
      25: new           #52                 // class org/apache/hadoop/hbase/io/hfile/CacheTestUtils$ByteArrayCacheable
      28: dup
      29: aload         5
      31: invokespecial #53                 // Method org/apache/hadoop/hbase/io/hfile/CacheTestUtils$ByteArrayCacheable."<init>":([B)V
      34: astore        6
      36: new           #11                 // class org/apache/hadoop/conf/Configuration
      39: dup
      40: invokespecial #12                 // Method org/apache/hadoop/conf/Configuration."<init>":()V
      43: astore        7
      45: new           #13                 // class org/apache/hadoop/hbase/MultithreadedTestUtil$TestContext
      48: dup
      49: aload         7
      51: invokespecial #14                 // Method org/apache/hadoop/hbase/MultithreadedTestUtil$TestContext."<init>":(Lorg/apache/hadoop/conf/Configuration;)V
      54: astore        8
      56: new           #15                 // class java/util/concurrent/atomic/AtomicInteger
      59: dup
      60: invokespecial #16                 // Method java/util/concurrent/atomic/AtomicInteger."<init>":()V
      63: astore        9
      65: aload_0
      66: aload         4
      68: aload         6
      70: invokeinterface #7,  3            // InterfaceMethod org/apache/hadoop/hbase/io/hfile/BlockCache.cacheBlock:(Lorg/apache/hadoop/hbase/io/hfile/BlockCacheKey;Lorg/apache/hadoop/hbase/io/hfile/Cacheable;)V
      75: iconst_0
      76: istore        10
      78: iload         10
      80: iload_2
      81: if_icmpge     121
      84: new           #54                 // class org/apache/hadoop/hbase/io/hfile/CacheTestUtils$2
      87: dup
      88: aload         8
      90: aload_0
      91: aload         4
      93: aload         5
      95: aload         9
      97: invokespecial #55                 // Method org/apache/hadoop/hbase/io/hfile/CacheTestUtils$2."<init>":(Lorg/apache/hadoop/hbase/MultithreadedTestUtil$TestContext;Lorg/apache/hadoop/hbase/io/hfile/BlockCache;Lorg/apache/hadoop/hbase/io/hfile/BlockCacheKey;[BLjava/util/concurrent/atomic/AtomicInteger;)V
     100: astore        11
     102: aload         11
     104: iconst_1
     105: invokevirtual #23                 // Method org/apache/hadoop/hbase/MultithreadedTestUtil$TestThread.setDaemon:(Z)V
     108: aload         8
     110: aload         11
     112: invokevirtual #24                 // Method org/apache/hadoop/hbase/MultithreadedTestUtil$TestContext.addThread:(Lorg/apache/hadoop/hbase/MultithreadedTestUtil$TestThread;)V
     115: iinc          10, 1
     118: goto          78
     121: ldc2_w        #56                 // long 50l
     124: lstore        10
     126: new           #58                 // class org/apache/hadoop/hbase/io/hfile/CacheTestUtils$3
     129: dup
     130: aload         8
     132: aload_0
     133: aload         4
     135: aload         6
     137: invokespecial #59                 // Method org/apache/hadoop/hbase/io/hfile/CacheTestUtils$3."<init>":(Lorg/apache/hadoop/hbase/MultithreadedTestUtil$TestContext;Lorg/apache/hadoop/hbase/io/hfile/BlockCache;Lorg/apache/hadoop/hbase/io/hfile/BlockCacheKey;Lorg/apache/hadoop/hbase/io/hfile/CacheTestUtils$ByteArrayCacheable;)V
     140: astore        12
     142: aload         12
     144: iconst_1
     145: invokevirtual #23                 // Method org/apache/hadoop/hbase/MultithreadedTestUtil$TestThread.setDaemon:(Z)V
     148: aload         8
     150: aload         12
     152: invokevirtual #24                 // Method org/apache/hadoop/hbase/MultithreadedTestUtil$TestContext.addThread:(Lorg/apache/hadoop/hbase/MultithreadedTestUtil$TestThread;)V
     155: aload         8
     157: invokevirtual #25                 // Method org/apache/hadoop/hbase/MultithreadedTestUtil$TestContext.startThreads:()V
     160: aload         9
     162: invokevirtual #32                 // Method java/util/concurrent/atomic/AtomicInteger.get:()I
     165: iload_3
     166: if_icmpge     186
     169: aload         8
     171: invokevirtual #27                 // Method org/apache/hadoop/hbase/MultithreadedTestUtil$TestContext.shouldRun:()Z
     174: ifeq          186
     177: ldc2_w        #28                 // long 10l
     180: invokestatic  #30                 // Method java/lang/Thread.sleep:(J)V
     183: goto          160
     186: aload         8
     188: invokevirtual #31                 // Method org/apache/hadoop/hbase/MultithreadedTestUtil$TestContext.stop:()V
     191: return

  public static void hammerEviction(org.apache.hadoop.hbase.io.hfile.BlockCache, int, int, int) throws java.lang.Exception;
    Code:
       0: new           #11                 // class org/apache/hadoop/conf/Configuration
       3: dup
       4: invokespecial #12                 // Method org/apache/hadoop/conf/Configuration."<init>":()V
       7: astore        4
       9: new           #13                 // class org/apache/hadoop/hbase/MultithreadedTestUtil$TestContext
      12: dup
      13: aload         4
      15: invokespecial #14                 // Method org/apache/hadoop/hbase/MultithreadedTestUtil$TestContext."<init>":(Lorg/apache/hadoop/conf/Configuration;)V
      18: astore        5
      20: new           #15                 // class java/util/concurrent/atomic/AtomicInteger
      23: dup
      24: invokespecial #16                 // Method java/util/concurrent/atomic/AtomicInteger."<init>":()V
      27: astore        6
      29: iconst_0
      30: istore        7
      32: iload         7
      34: iload_2
      35: if_icmpge     86
      38: iload         7
      40: istore        8
      42: sipush        5120
      45: newarray       byte
      47: astore        9
      49: new           #60                 // class org/apache/hadoop/hbase/io/hfile/CacheTestUtils$4
      52: dup
      53: aload         5
      55: iload         8
      57: aload         9
      59: aload_0
      60: aload         6
      62: invokespecial #61                 // Method org/apache/hadoop/hbase/io/hfile/CacheTestUtils$4."<init>":(Lorg/apache/hadoop/hbase/MultithreadedTestUtil$TestContext;I[BLorg/apache/hadoop/hbase/io/hfile/BlockCache;Ljava/util/concurrent/atomic/AtomicInteger;)V
      65: astore        10
      67: aload         10
      69: iconst_1
      70: invokevirtual #23                 // Method org/apache/hadoop/hbase/MultithreadedTestUtil$TestThread.setDaemon:(Z)V
      73: aload         5
      75: aload         10
      77: invokevirtual #24                 // Method org/apache/hadoop/hbase/MultithreadedTestUtil$TestContext.addThread:(Lorg/apache/hadoop/hbase/MultithreadedTestUtil$TestThread;)V
      80: iinc          7, 1
      83: goto          32
      86: aload         5
      88: invokevirtual #25                 // Method org/apache/hadoop/hbase/MultithreadedTestUtil$TestContext.startThreads:()V
      91: aload         6
      93: invokevirtual #32                 // Method java/util/concurrent/atomic/AtomicInteger.get:()I
      96: iload_3
      97: if_icmpge     117
     100: aload         5
     102: invokevirtual #27                 // Method org/apache/hadoop/hbase/MultithreadedTestUtil$TestContext.shouldRun:()Z
     105: ifeq          117
     108: ldc2_w        #28                 // long 10l
     111: invokestatic  #30                 // Method java/lang/Thread.sleep:(J)V
     114: goto          91
     117: aload         5
     119: invokevirtual #31                 // Method org/apache/hadoop/hbase/MultithreadedTestUtil$TestContext.stop:()V
     122: aload_0
     123: invokeinterface #62,  1           // InterfaceMethod org/apache/hadoop/hbase/io/hfile/BlockCache.getStats:()Lorg/apache/hadoop/hbase/io/hfile/CacheStats;
     128: invokevirtual #63                 // Method org/apache/hadoop/hbase/io/hfile/CacheStats.getEvictedCount:()J
     131: lconst_0
     132: lcmp
     133: ifle          140
     136: iconst_1
     137: goto          141
     140: iconst_0
     141: invokestatic  #8                  // Method org/junit/Assert.assertTrue:(Z)V
     144: return

  public static org.apache.hadoop.hbase.io.hfile.CacheTestUtils$HFileBlockPair[] generateHFileBlocks(int, int);
    Code:
       0: iload_1
       1: anewarray     #64                 // class org/apache/hadoop/hbase/io/hfile/CacheTestUtils$HFileBlockPair
       4: astore_2
       5: new           #65                 // class java/util/Random
       8: dup
       9: invokespecial #66                 // Method java/util/Random."<init>":()V
      12: astore_3
      13: new           #67                 // class java/util/HashSet
      16: dup
      17: invokespecial #68                 // Method java/util/HashSet."<init>":()V
      20: astore        4
      22: iconst_0
      23: istore        5
      25: iload         5
      27: iload_1
      28: if_icmpge     247
      31: iload_0
      32: invokestatic  #69                 // Method java/nio/ByteBuffer.allocate:(I)Ljava/nio/ByteBuffer;
      35: astore        6
      37: aload_3
      38: aload         6
      40: invokevirtual #70                 // Method java/nio/ByteBuffer.array:()[B
      43: invokevirtual #71                 // Method java/util/Random.nextBytes:([B)V
      46: aload         6
      48: invokevirtual #72                 // Method java/nio/ByteBuffer.rewind:()Ljava/nio/Buffer;
      51: pop
      52: iload_0
      53: istore        7
      55: iload_0
      56: istore        8
      58: aload_3
      59: invokevirtual #73                 // Method java/util/Random.nextLong:()J
      62: lstore        9
      64: getstatic     #74                 // Field org/apache/hadoop/hbase/io/hfile/BlockType.DATA:Lorg/apache/hadoop/hbase/io/hfile/BlockType;
      67: aload         6
      69: invokevirtual #75                 // Method org/apache/hadoop/hbase/io/hfile/BlockType.write:(Ljava/nio/ByteBuffer;)V
      72: aload         6
      74: iload         7
      76: invokevirtual #76                 // Method java/nio/ByteBuffer.putInt:(I)Ljava/nio/ByteBuffer;
      79: pop
      80: aload         6
      82: iload         8
      84: invokevirtual #76                 // Method java/nio/ByteBuffer.putInt:(I)Ljava/nio/ByteBuffer;
      87: pop
      88: aload         6
      90: lload         9
      92: invokevirtual #77                 // Method java/nio/ByteBuffer.putLong:(J)Ljava/nio/ByteBuffer;
      95: pop
      96: aload         6
      98: invokevirtual #72                 // Method java/nio/ByteBuffer.rewind:()Ljava/nio/Buffer;
     101: pop
     102: new           #78                 // class org/apache/hadoop/hbase/io/hfile/HFileContextBuilder
     105: dup
     106: invokespecial #79                 // Method org/apache/hadoop/hbase/io/hfile/HFileContextBuilder."<init>":()V
     109: iconst_0
     110: invokevirtual #80                 // Method org/apache/hadoop/hbase/io/hfile/HFileContextBuilder.withHBaseCheckSum:(Z)Lorg/apache/hadoop/hbase/io/hfile/HFileContextBuilder;
     113: iconst_1
     114: invokevirtual #82                 // Method org/apache/hadoop/hbase/io/hfile/HFileContextBuilder.withIncludesMvcc:(Z)Lorg/apache/hadoop/hbase/io/hfile/HFileContextBuilder;
     117: iconst_0
     118: invokevirtual #83                 // Method org/apache/hadoop/hbase/io/hfile/HFileContextBuilder.withIncludesTags:(Z)Lorg/apache/hadoop/hbase/io/hfile/HFileContextBuilder;
     121: getstatic     #84                 // Field org/apache/hadoop/hbase/io/compress/Compression$Algorithm.NONE:Lorg/apache/hadoop/hbase/io/compress/Compression$Algorithm;
     124: invokevirtual #85                 // Method org/apache/hadoop/hbase/io/hfile/HFileContextBuilder.withCompression:(Lorg/apache/hadoop/hbase/io/compress/Compression$Algorithm;)Lorg/apache/hadoop/hbase/io/hfile/HFileContextBuilder;
     127: iconst_0
     128: invokevirtual #86                 // Method org/apache/hadoop/hbase/io/hfile/HFileContextBuilder.withBytesPerCheckSum:(I)Lorg/apache/hadoop/hbase/io/hfile/HFileContextBuilder;
     131: getstatic     #87                 // Field org/apache/hadoop/hbase/util/ChecksumType.NULL:Lorg/apache/hadoop/hbase/util/ChecksumType;
     134: invokevirtual #88                 // Method org/apache/hadoop/hbase/io/hfile/HFileContextBuilder.withChecksumType:(Lorg/apache/hadoop/hbase/util/ChecksumType;)Lorg/apache/hadoop/hbase/io/hfile/HFileContextBuilder;
     137: invokevirtual #89                 // Method org/apache/hadoop/hbase/io/hfile/HFileContextBuilder.build:()Lorg/apache/hadoop/hbase/io/hfile/HFileContext;
     140: astore        11
     142: new           #43                 // class org/apache/hadoop/hbase/io/hfile/HFileBlock
     145: dup
     146: getstatic     #74                 // Field org/apache/hadoop/hbase/io/hfile/BlockType.DATA:Lorg/apache/hadoop/hbase/io/hfile/BlockType;
     149: iload         7
     151: iload         8
     153: lload         9
     155: aload         6
     157: iconst_0
     158: iload_0
     159: i2l
     160: iload         7
     162: bipush        33
     164: iadd
     165: iconst_m1
     166: aload         11
     168: invokespecial #91                 // Method org/apache/hadoop/hbase/io/hfile/HFileBlock."<init>":(Lorg/apache/hadoop/hbase/io/hfile/BlockType;IIJLjava/nio/ByteBuffer;ZJIILorg/apache/hadoop/hbase/io/hfile/HFileContext;)V
     171: astore        12
     173: aload_3
     174: invokevirtual #73                 // Method java/util/Random.nextLong:()J
     177: invokestatic  #92                 // Method java/lang/Long.toString:(J)Ljava/lang/String;
     180: astore        13
     182: aload         4
     184: aload         13
     186: invokevirtual #93                 // Method java/util/HashSet.add:(Ljava/lang/Object;)Z
     189: ifne          204
     192: aload_3
     193: invokevirtual #73                 // Method java/util/Random.nextLong:()J
     196: invokestatic  #92                 // Method java/lang/Long.toString:(J)Ljava/lang/String;
     199: astore        13
     201: goto          182
     204: aload_2
     205: iload         5
     207: new           #64                 // class org/apache/hadoop/hbase/io/hfile/CacheTestUtils$HFileBlockPair
     210: dup
     211: invokespecial #94                 // Method org/apache/hadoop/hbase/io/hfile/CacheTestUtils$HFileBlockPair."<init>":()V
     214: aastore
     215: aload_2
     216: iload         5
     218: aaload
     219: new           #48                 // class org/apache/hadoop/hbase/io/hfile/BlockCacheKey
     222: dup
     223: aload         13
     225: lconst_0
     226: invokespecial #50                 // Method org/apache/hadoop/hbase/io/hfile/BlockCacheKey."<init>":(Ljava/lang/String;J)V
     229: putfield      #5                  // Field org/apache/hadoop/hbase/io/hfile/CacheTestUtils$HFileBlockPair.blockName:Lorg/apache/hadoop/hbase/io/hfile/BlockCacheKey;
     232: aload_2
     233: iload         5
     235: aaload
     236: aload         12
     238: putfield      #6                  // Field org/apache/hadoop/hbase/io/hfile/CacheTestUtils$HFileBlockPair.block:Lorg/apache/hadoop/hbase/io/hfile/HFileBlock;
     241: iinc          5, 1
     244: goto          25
     247: aload_2
     248: areturn

  public static void getBlockAndAssertEquals(org.apache.hadoop.hbase.io.hfile.BlockCache, org.apache.hadoop.hbase.io.hfile.BlockCacheKey, org.apache.hadoop.hbase.io.hfile.Cacheable, java.nio.ByteBuffer, java.nio.ByteBuffer);
    Code:
       0: aload_3
       1: invokevirtual #95                 // Method java/nio/ByteBuffer.clear:()Ljava/nio/Buffer;
       4: pop
       5: aload_0
       6: aload_1
       7: aload_2
       8: invokeinterface #7,  3            // InterfaceMethod org/apache/hadoop/hbase/io/hfile/BlockCache.cacheBlock:(Lorg/apache/hadoop/hbase/io/hfile/BlockCacheKey;Lorg/apache/hadoop/hbase/io/hfile/Cacheable;)V
      13: aload_0
      14: aload_1
      15: iconst_0
      16: iconst_0
      17: iconst_0
      18: invokeinterface #41,  5           // InterfaceMethod org/apache/hadoop/hbase/io/hfile/BlockCache.getBlock:(Lorg/apache/hadoop/hbase/io/hfile/BlockCacheKey;ZZZ)Lorg/apache/hadoop/hbase/io/hfile/Cacheable;
      23: astore        5
      25: aload         5
      27: aload_3
      28: iconst_1
      29: invokeinterface #96,  3           // InterfaceMethod org/apache/hadoop/hbase/io/hfile/Cacheable.serialize:(Ljava/nio/ByteBuffer;Z)V
      34: aload         4
      36: aload_3
      37: invokestatic  #44                 // Method org/junit/Assert.assertEquals:(Ljava/lang/Object;Ljava/lang/Object;)V
      40: aload_0
      41: aload_1
      42: aload         5
      44: invokeinterface #97,  3           // InterfaceMethod org/apache/hadoop/hbase/io/hfile/BlockCache.returnBlock:(Lorg/apache/hadoop/hbase/io/hfile/BlockCacheKey;Lorg/apache/hadoop/hbase/io/hfile/Cacheable;)V
      49: return
}
