Compiled from "CacheEvictionStatsBuilder.java"
public final class org.apache.hadoop.hbase.CacheEvictionStatsBuilder {
  long evictedBlocks;

  long maxCacheSize;

  java.util.Map<byte[], java.lang.Throwable> exceptions;

  org.apache.hadoop.hbase.CacheEvictionStatsBuilder();
    Code:
       0: aload_0
       1: invokespecial #1                  // Method java/lang/Object."<init>":()V
       4: aload_0
       5: lconst_0
       6: putfield      #2                  // Field evictedBlocks:J
       9: aload_0
      10: lconst_0
      11: putfield      #3                  // Field maxCacheSize:J
      14: aload_0
      15: new           #4                  // class java/util/HashMap
      18: dup
      19: invokespecial #5                  // Method java/util/HashMap."<init>":()V
      22: putfield      #6                  // Field exceptions:Ljava/util/Map;
      25: return

  public org.apache.hadoop.hbase.CacheEvictionStatsBuilder withEvictedBlocks(long);
    Code:
       0: aload_0
       1: lload_1
       2: putfield      #2                  // Field evictedBlocks:J
       5: aload_0
       6: areturn

  public org.apache.hadoop.hbase.CacheEvictionStatsBuilder withMaxCacheSize(long);
    Code:
       0: aload_0
       1: lload_1
       2: putfield      #3                  // Field maxCacheSize:J
       5: aload_0
       6: areturn

  public void addException(byte[], java.lang.Throwable);
    Code:
       0: aload_0
       1: getfield      #6                  // Field exceptions:Ljava/util/Map;
       4: aload_1
       5: aload_2
       6: invokeinterface #7,  3            // InterfaceMethod java/util/Map.put:(Ljava/lang/Object;Ljava/lang/Object;)Ljava/lang/Object;
      11: pop
      12: return

  public org.apache.hadoop.hbase.CacheEvictionStatsBuilder append(org.apache.hadoop.hbase.CacheEvictionStats);
    Code:
       0: aload_0
       1: dup
       2: getfield      #2                  // Field evictedBlocks:J
       5: aload_1
       6: invokevirtual #8                  // Method org/apache/hadoop/hbase/CacheEvictionStats.getEvictedBlocks:()J
       9: ladd
      10: putfield      #2                  // Field evictedBlocks:J
      13: aload_0
      14: dup
      15: getfield      #3                  // Field maxCacheSize:J
      18: aload_1
      19: invokevirtual #9                  // Method org/apache/hadoop/hbase/CacheEvictionStats.getMaxCacheSize:()J
      22: ladd
      23: putfield      #3                  // Field maxCacheSize:J
      26: aload_0
      27: getfield      #6                  // Field exceptions:Ljava/util/Map;
      30: aload_1
      31: invokevirtual #10                 // Method org/apache/hadoop/hbase/CacheEvictionStats.getExceptions:()Ljava/util/Map;
      34: invokeinterface #11,  2           // InterfaceMethod java/util/Map.putAll:(Ljava/util/Map;)V
      39: aload_0
      40: areturn

  public org.apache.hadoop.hbase.CacheEvictionStats build();
    Code:
       0: new           #12                 // class org/apache/hadoop/hbase/CacheEvictionStats
       3: dup
       4: aload_0
       5: invokespecial #13                 // Method org/apache/hadoop/hbase/CacheEvictionStats."<init>":(Lorg/apache/hadoop/hbase/CacheEvictionStatsBuilder;)V
       8: areturn
}
