Compiled from "CacheTestUtils.java"
public class org.apache.hadoop.hbase.io.hfile.CacheTestUtils$HFileBlockPair {
  org.apache.hadoop.hbase.io.hfile.BlockCacheKey blockName;

  org.apache.hadoop.hbase.io.hfile.HFileBlock block;

  public org.apache.hadoop.hbase.io.hfile.CacheTestUtils$HFileBlockPair();
    Code:
       0: aload_0
       1: invokespecial #1                  // Method java/lang/Object."<init>":()V
       4: return

  public org.apache.hadoop.hbase.io.hfile.BlockCacheKey getBlockName();
    Code:
       0: aload_0
       1: getfield      #2                  // Field blockName:Lorg/apache/hadoop/hbase/io/hfile/BlockCacheKey;
       4: areturn

  public org.apache.hadoop.hbase.io.hfile.HFileBlock getBlock();
    Code:
       0: aload_0
       1: getfield      #3                  // Field block:Lorg/apache/hadoop/hbase/io/hfile/HFileBlock;
       4: areturn
}
