Compiled from "Call.java"
class org.apache.hadoop.hbase.ipc.Call {
  final int id;

  final org.apache.hbase.thirdparty.com.google.protobuf.Message param;

  org.apache.hadoop.hbase.CellScanner cells;

  org.apache.hbase.thirdparty.com.google.protobuf.Message response;

  org.apache.hbase.thirdparty.com.google.protobuf.Message responseDefaultType;

  java.io.IOException error;

  final org.apache.hbase.thirdparty.com.google.protobuf.Descriptors$MethodDescriptor md;

  final int timeout;

  final int priority;

  final org.apache.hadoop.hbase.client.MetricsConnection$CallStats callStats;

  final org.apache.hbase.thirdparty.com.google.protobuf.RpcCallback<org.apache.hadoop.hbase.ipc.Call> callback;

  final org.apache.htrace.core.Span span;

  org.apache.hbase.thirdparty.io.netty.util.Timeout timeoutTask;

  protected org.apache.hadoop.hbase.ipc.Call(int, org.apache.hbase.thirdparty.com.google.protobuf.Descriptors$MethodDescriptor, org.apache.hbase.thirdparty.com.google.protobuf.Message, org.apache.hadoop.hbase.CellScanner, org.apache.hbase.thirdparty.com.google.protobuf.Message, int, int, org.apache.hbase.thirdparty.com.google.protobuf.RpcCallback<org.apache.hadoop.hbase.ipc.Call>, org.apache.hadoop.hbase.client.MetricsConnection$CallStats);
    Code:
       0: aload_0
       1: invokespecial #1                  // Method java/lang/Object."<init>":()V
       4: aload_0
       5: aload_3
       6: putfield      #2                  // Field param:Lorg/apache/hbase/thirdparty/com/google/protobuf/Message;
       9: aload_0
      10: aload_2
      11: putfield      #3                  // Field md:Lorg/apache/hbase/thirdparty/com/google/protobuf/Descriptors$MethodDescriptor;
      14: aload_0
      15: aload         4
      17: putfield      #4                  // Field cells:Lorg/apache/hadoop/hbase/CellScanner;
      20: aload_0
      21: aload         9
      23: putfield      #5                  // Field callStats:Lorg/apache/hadoop/hbase/client/MetricsConnection$CallStats;
      26: aload_0
      27: getfield      #5                  // Field callStats:Lorg/apache/hadoop/hbase/client/MetricsConnection$CallStats;
      30: invokestatic  #6                  // Method org/apache/hadoop/hbase/util/EnvironmentEdgeManager.currentTime:()J
      33: invokevirtual #7                  // Method org/apache/hadoop/hbase/client/MetricsConnection$CallStats.setStartTime:(J)V
      36: aload_0
      37: aload         5
      39: putfield      #8                  // Field responseDefaultType:Lorg/apache/hbase/thirdparty/com/google/protobuf/Message;
      42: aload_0
      43: iload_1
      44: putfield      #9                  // Field id:I
      47: aload_0
      48: iload         6
      50: putfield      #10                 // Field timeout:I
      53: aload_0
      54: iload         7
      56: putfield      #11                 // Field priority:I
      59: aload_0
      60: aload         8
      62: putfield      #12                 // Field callback:Lorg/apache/hbase/thirdparty/com/google/protobuf/RpcCallback;
      65: aload_0
      66: invokestatic  #13                 // Method org/apache/htrace/core/Tracer.getCurrentSpan:()Lorg/apache/htrace/core/Span;
      69: putfield      #14                 // Field span:Lorg/apache/htrace/core/Span;
      72: return

  public java.lang.String toString();
    Code:
       0: new           #15                 // class java/lang/StringBuilder
       3: dup
       4: invokespecial #16                 // Method java/lang/StringBuilder."<init>":()V
       7: ldc           #17                 // String callId:
       9: invokevirtual #18                 // Method java/lang/StringBuilder.append:(Ljava/lang/String;)Ljava/lang/StringBuilder;
      12: aload_0
      13: getfield      #9                  // Field id:I
      16: invokevirtual #19                 // Method java/lang/StringBuilder.append:(I)Ljava/lang/StringBuilder;
      19: ldc           #20                 // String  methodName:
      21: invokevirtual #18                 // Method java/lang/StringBuilder.append:(Ljava/lang/String;)Ljava/lang/StringBuilder;
      24: aload_0
      25: getfield      #3                  // Field md:Lorg/apache/hbase/thirdparty/com/google/protobuf/Descriptors$MethodDescriptor;
      28: invokevirtual #21                 // Method org/apache/hbase/thirdparty/com/google/protobuf/Descriptors$MethodDescriptor.getName:()Ljava/lang/String;
      31: invokevirtual #18                 // Method java/lang/StringBuilder.append:(Ljava/lang/String;)Ljava/lang/StringBuilder;
      34: ldc           #22                 // String  param {
      36: invokevirtual #18                 // Method java/lang/StringBuilder.append:(Ljava/lang/String;)Ljava/lang/StringBuilder;
      39: aload_0
      40: getfield      #2                  // Field param:Lorg/apache/hbase/thirdparty/com/google/protobuf/Message;
      43: ifnull        56
      46: aload_0
      47: getfield      #2                  // Field param:Lorg/apache/hbase/thirdparty/com/google/protobuf/Message;
      50: invokestatic  #23                 // Method org/apache/hadoop/hbase/shaded/protobuf/ProtobufUtil.getShortTextFormat:(Lorg/apache/hbase/thirdparty/com/google/protobuf/Message;)Ljava/lang/String;
      53: goto          58
      56: ldc           #24                 // String
      58: invokevirtual #18                 // Method java/lang/StringBuilder.append:(Ljava/lang/String;)Ljava/lang/StringBuilder;
      61: ldc           #25                 // String }
      63: invokevirtual #18                 // Method java/lang/StringBuilder.append:(Ljava/lang/String;)Ljava/lang/StringBuilder;
      66: invokevirtual #26                 // Method java/lang/StringBuilder.toString:()Ljava/lang/String;
      69: areturn

  public void setTimeout(java.io.IOException);
    Code:
       0: aload_0
       1: dup
       2: astore_2
       3: monitorenter
       4: aload_0
       5: getfield      #27                 // Field done:Z
       8: ifeq          14
      11: aload_2
      12: monitorexit
      13: return
      14: aload_0
      15: iconst_1
      16: putfield      #27                 // Field done:Z
      19: aload_0
      20: aload_1
      21: putfield      #28                 // Field error:Ljava/io/IOException;
      24: aload_2
      25: monitorexit
      26: goto          34
      29: astore_3
      30: aload_2
      31: monitorexit
      32: aload_3
      33: athrow
      34: aload_0
      35: getfield      #12                 // Field callback:Lorg/apache/hbase/thirdparty/com/google/protobuf/RpcCallback;
      38: aload_0
      39: invokeinterface #29,  2           // InterfaceMethod org/apache/hbase/thirdparty/com/google/protobuf/RpcCallback.run:(Ljava/lang/Object;)V
      44: return
    Exception table:
       from    to  target type
           4    13    29   any
          14    26    29   any
          29    32    29   any

  public void setException(java.io.IOException);
    Code:
       0: aload_0
       1: dup
       2: astore_2
       3: monitorenter
       4: aload_0
       5: getfield      #27                 // Field done:Z
       8: ifeq          14
      11: aload_2
      12: monitorexit
      13: return
      14: aload_0
      15: iconst_1
      16: putfield      #27                 // Field done:Z
      19: aload_0
      20: aload_1
      21: putfield      #28                 // Field error:Ljava/io/IOException;
      24: aload_2
      25: monitorexit
      26: goto          34
      29: astore_3
      30: aload_2
      31: monitorexit
      32: aload_3
      33: athrow
      34: aload_0
      35: invokespecial #32                 // Method callComplete:()V
      38: return
    Exception table:
       from    to  target type
           4    13    29   any
          14    26    29   any
          29    32    29   any

  public void setResponse(org.apache.hbase.thirdparty.com.google.protobuf.Message, org.apache.hadoop.hbase.CellScanner);
    Code:
       0: aload_0
       1: dup
       2: astore_3
       3: monitorenter
       4: aload_0
       5: getfield      #27                 // Field done:Z
       8: ifeq          14
      11: aload_3
      12: monitorexit
      13: return
      14: aload_0
      15: iconst_1
      16: putfield      #27                 // Field done:Z
      19: aload_0
      20: aload_1
      21: putfield      #33                 // Field response:Lorg/apache/hbase/thirdparty/com/google/protobuf/Message;
      24: aload_0
      25: aload_2
      26: putfield      #4                  // Field cells:Lorg/apache/hadoop/hbase/CellScanner;
      29: aload_3
      30: monitorexit
      31: goto          41
      34: astore        4
      36: aload_3
      37: monitorexit
      38: aload         4
      40: athrow
      41: aload_0
      42: invokespecial #32                 // Method callComplete:()V
      45: return
    Exception table:
       from    to  target type
           4    13    34   any
          14    31    34   any
          34    38    34   any

  public synchronized boolean isDone();
    Code:
       0: aload_0
       1: getfield      #27                 // Field done:Z
       4: ireturn

  public long getStartTime();
    Code:
       0: aload_0
       1: getfield      #5                  // Field callStats:Lorg/apache/hadoop/hbase/client/MetricsConnection$CallStats;
       4: invokevirtual #34                 // Method org/apache/hadoop/hbase/client/MetricsConnection$CallStats.getStartTime:()J
       7: lreturn
}
