Compiled from "Canary.java"
class org.apache.hadoop.hbase.tool.Canary$RegionServerMonitor extends org.apache.hadoop.hbase.tool.Canary$Monitor {
  public org.apache.hadoop.hbase.tool.Canary$RegionServerMonitor(org.apache.hadoop.hbase.client.Connection, java.lang.String[], boolean, org.apache.hadoop.hbase.tool.Canary$Sink, java.util.concurrent.ExecutorService, boolean, boolean, long);
    Code:
       0: aload_0
       1: aload_1
       2: aload_2
       3: iload_3
       4: aload         4
       6: aload         5
       8: iload         7
      10: lload         8
      12: invokespecial #2                  // Method org/apache/hadoop/hbase/tool/Canary$Monitor."<init>":(Lorg/apache/hadoop/hbase/client/Connection;[Ljava/lang/String;ZLorg/apache/hadoop/hbase/tool/Canary$Sink;Ljava/util/concurrent/ExecutorService;ZJ)V
      15: aload_0
      16: iload         6
      18: putfield      #3                  // Field allRegions:Z
      21: return

  public void run();
    Code:
       0: aload_0
       1: invokevirtual #9                  // Method initAdmin:()Z
       4: ifeq          57
       7: aload_0
       8: invokespecial #10                 // Method checkNoTableNames:()Z
      11: ifeq          57
      14: aconst_null
      15: astore_1
      16: aload_0
      17: invokespecial #11                 // Method getSink:()Lorg/apache/hadoop/hbase/tool/Canary$RegionServerStdOutSink;
      20: astore_1
      21: goto          41
      24: astore_2
      25: invokestatic  #12                 // Method org/apache/hadoop/hbase/tool/Canary.access$000:()Lorg/slf4j/Logger;
      28: ldc           #13                 // String Run RegionServerMonitor failed!
      30: aload_2
      31: invokeinterface #14,  3           // InterfaceMethod org/slf4j/Logger.error:(Ljava/lang/String;Ljava/lang/Throwable;)V
      36: aload_0
      37: iconst_4
      38: putfield      #15                 // Field errorCode:I
      41: aload_0
      42: invokespecial #16                 // Method filterRegionServerByName:()Ljava/util/Map;
      45: astore_2
      46: aload_0
      47: iconst_1
      48: putfield      #17                 // Field initialized:Z
      51: aload_0
      52: aload_2
      53: aload_1
      54: invokespecial #18                 // Method monitorRegionServers:(Ljava/util/Map;Lorg/apache/hadoop/hbase/tool/Canary$RegionServerStdOutSink;)V
      57: aload_0
      58: iconst_1
      59: putfield      #19                 // Field done:Z
      62: return
    Exception table:
       from    to  target type
          16    21    24   Class java/lang/RuntimeException
}
