Compiled from "Canary.java"
public final class org.apache.hadoop.hbase.tool.Canary implements org.apache.hadoop.util.Tool {
  public static final org.apache.hadoop.hbase.TableName DEFAULT_WRITE_TABLE_NAME;

  public org.apache.hadoop.hbase.tool.Canary();
    Code:
       0: aload_0
       1: new           #4                  // class java/util/concurrent/ScheduledThreadPoolExecutor
       4: dup
       5: iconst_1
       6: invokespecial #5                  // Method java/util/concurrent/ScheduledThreadPoolExecutor."<init>":(I)V
       9: invokespecial #6                  // Method "<init>":(Ljava/util/concurrent/ExecutorService;)V
      12: return

  public org.apache.hadoop.hbase.tool.Canary(java.util.concurrent.ExecutorService);
    Code:
       0: aload_0
       1: aload_1
       2: aconst_null
       3: invokespecial #7                  // Method "<init>":(Ljava/util/concurrent/ExecutorService;Lorg/apache/hadoop/hbase/tool/Canary$Sink;)V
       6: return

  org.apache.hadoop.hbase.tool.Canary(java.util.concurrent.ExecutorService, org.apache.hadoop.hbase.tool.Canary$Sink);
    Code:
       0: aload_0
       1: invokespecial #8                  // Method java/lang/Object."<init>":()V
       4: aload_0
       5: aconst_null
       6: putfield      #9                  // Field conf:Lorg/apache/hadoop/conf/Configuration;
       9: aload_0
      10: lconst_0
      11: putfield      #10                 // Field interval:J
      14: aload_0
      15: aconst_null
      16: putfield      #11                 // Field sink:Lorg/apache/hadoop/hbase/tool/Canary$Sink;
      19: aload_0
      20: ldc2_w        #13                 // long 600000l
      23: putfield      #15                 // Field timeout:J
      26: aload_0
      27: iconst_1
      28: putfield      #16                 // Field failOnError:Z
      31: aload_0
      32: iconst_0
      33: putfield      #17                 // Field regionServerMode:Z
      36: aload_0
      37: iconst_0
      38: putfield      #18                 // Field zookeeperMode:Z
      41: aload_0
      42: lconst_0
      43: putfield      #19                 // Field permittedFailures:J
      46: aload_0
      47: iconst_0
      48: putfield      #20                 // Field regionServerAllRegions:Z
      51: aload_0
      52: iconst_0
      53: putfield      #21                 // Field writeSniffing:Z
      56: aload_0
      57: ldc2_w        #13                 // long 600000l
      60: putfield      #22                 // Field configuredWriteTableTimeout:J
      63: aload_0
      64: iconst_0
      65: putfield      #23                 // Field treatFailureAsError:Z
      68: aload_0
      69: getstatic     #24                 // Field DEFAULT_WRITE_TABLE_NAME:Lorg/apache/hadoop/hbase/TableName;
      72: putfield      #25                 // Field writeTableName:Lorg/apache/hadoop/hbase/TableName;
      75: aload_0
      76: new           #26                 // class java/util/HashMap
      79: dup
      80: invokespecial #27                 // Method java/util/HashMap."<init>":()V
      83: putfield      #28                 // Field configuredReadTableTimeouts:Ljava/util/HashMap;
      86: aload_0
      87: aload_1
      88: putfield      #29                 // Field executor:Ljava/util/concurrent/ExecutorService;
      91: aload_0
      92: aload_2
      93: putfield      #11                 // Field sink:Lorg/apache/hadoop/hbase/tool/Canary$Sink;
      96: return

  public org.apache.hadoop.conf.Configuration getConf();
    Code:
       0: aload_0
       1: getfield      #9                  // Field conf:Lorg/apache/hadoop/conf/Configuration;
       4: areturn

  public void setConf(org.apache.hadoop.conf.Configuration);
    Code:
       0: aload_0
       1: aload_1
       2: putfield      #9                  // Field conf:Lorg/apache/hadoop/conf/Configuration;
       5: return

  public int run(java.lang.String[]) throws java.lang.Exception;
    Code:
       0: aload_0
       1: aload_1
       2: invokespecial #88                 // Method parseArgs:([Ljava/lang/String;)I
       5: istore_2
       6: aconst_null
       7: astore_3
       8: aload_0
       9: getfield      #9                  // Field conf:Lorg/apache/hadoop/conf/Configuration;
      12: invokestatic  #89                 // Method org/apache/hadoop/hbase/AuthUtil.getAuthChore:(Lorg/apache/hadoop/conf/Configuration;)Lorg/apache/hadoop/hbase/ScheduledChore;
      15: astore        4
      17: aload         4
      19: ifnull        39
      22: new           #90                 // class org/apache/hadoop/hbase/ChoreService
      25: dup
      26: ldc           #91                 // String CANARY_TOOL
      28: invokespecial #92                 // Method org/apache/hadoop/hbase/ChoreService."<init>":(Ljava/lang/String;)V
      31: astore_3
      32: aload_3
      33: aload         4
      35: invokevirtual #93                 // Method org/apache/hadoop/hbase/ChoreService.scheduleChore:(Lorg/apache/hadoop/hbase/ScheduledChore;)Z
      38: pop
      39: aconst_null
      40: astore        5
      42: aconst_null
      43: astore        6
      45: lconst_0
      46: lstore        7
      48: lconst_0
      49: lstore        9
      51: aload_0
      52: getfield      #9                  // Field conf:Lorg/apache/hadoop/conf/Configuration;
      55: invokestatic  #94                 // Method org/apache/hadoop/hbase/client/ConnectionFactory.createConnection:(Lorg/apache/hadoop/conf/Configuration;)Lorg/apache/hadoop/hbase/client/Connection;
      58: astore        11
      60: aconst_null
      61: astore        12
      63: aload_0
      64: aload         11
      66: iload_2
      67: aload_1
      68: invokevirtual #95                 // Method newMonitor:(Lorg/apache/hadoop/hbase/client/Connection;I[Ljava/lang/String;)Lorg/apache/hadoop/hbase/tool/Canary$Monitor;
      71: astore        5
      73: new           #96                 // class java/lang/Thread
      76: dup
      77: aload         5
      79: new           #78                 // class java/lang/StringBuilder
      82: dup
      83: invokespecial #79                 // Method java/lang/StringBuilder."<init>":()V
      86: ldc           #97                 // String CanaryMonitor-
      88: invokevirtual #80                 // Method java/lang/StringBuilder.append:(Ljava/lang/String;)Ljava/lang/StringBuilder;
      91: invokestatic  #98                 // Method java/lang/System.currentTimeMillis:()J
      94: invokevirtual #99                 // Method java/lang/StringBuilder.append:(J)Ljava/lang/StringBuilder;
      97: invokevirtual #82                 // Method java/lang/StringBuilder.toString:()Ljava/lang/String;
     100: invokespecial #100                // Method java/lang/Thread."<init>":(Ljava/lang/Runnable;Ljava/lang/String;)V
     103: astore        6
     105: invokestatic  #98                 // Method java/lang/System.currentTimeMillis:()J
     108: lstore        7
     110: aload         6
     112: invokevirtual #101                // Method java/lang/Thread.start:()V
     115: aload         5
     117: invokevirtual #102                // Method org/apache/hadoop/hbase/tool/Canary$Monitor.isDone:()Z
     120: ifne          452
     123: ldc2_w        #45                 // long 1000l
     126: invokestatic  #103                // Method java/lang/Thread.sleep:(J)V
     129: aload_0
     130: getfield      #16                 // Field failOnError:Z
     133: ifeq          271
     136: aload         5
     138: invokevirtual #104                // Method org/apache/hadoop/hbase/tool/Canary$Monitor.hasError:()Z
     141: ifeq          271
     144: aload         6
     146: invokevirtual #105                // Method java/lang/Thread.interrupt:()V
     149: aload         5
     151: getfield      #106                // Field org/apache/hadoop/hbase/tool/Canary$Monitor.initialized:Z
     154: ifeq          216
     157: aload         5
     159: getfield      #107                // Field org/apache/hadoop/hbase/tool/Canary$Monitor.errorCode:I
     162: istore        13
     164: aload         5
     166: ifnull        174
     169: aload         5
     171: invokevirtual #108                // Method org/apache/hadoop/hbase/tool/Canary$Monitor.close:()V
     174: aload         11
     176: ifnull        213
     179: aload         12
     181: ifnull        206
     184: aload         11
     186: invokeinterface #109,  1          // InterfaceMethod org/apache/hadoop/hbase/client/Connection.close:()V
     191: goto          213
     194: astore        14
     196: aload         12
     198: aload         14
     200: invokevirtual #111                // Method java/lang/Throwable.addSuppressed:(Ljava/lang/Throwable;)V
     203: goto          213
     206: aload         11
     208: invokeinterface #109,  1          // InterfaceMethod org/apache/hadoop/hbase/client/Connection.close:()V
     213: iload         13
     215: ireturn
     216: iconst_2
     217: istore        13
     219: aload         5
     221: ifnull        229
     224: aload         5
     226: invokevirtual #108                // Method org/apache/hadoop/hbase/tool/Canary$Monitor.close:()V
     229: aload         11
     231: ifnull        268
     234: aload         12
     236: ifnull        261
     239: aload         11
     241: invokeinterface #109,  1          // InterfaceMethod org/apache/hadoop/hbase/client/Connection.close:()V
     246: goto          268
     249: astore        14
     251: aload         12
     253: aload         14
     255: invokevirtual #111                // Method java/lang/Throwable.addSuppressed:(Ljava/lang/Throwable;)V
     258: goto          268
     261: aload         11
     263: invokeinterface #109,  1          // InterfaceMethod org/apache/hadoop/hbase/client/Connection.close:()V
     268: iload         13
     270: ireturn
     271: invokestatic  #98                 // Method java/lang/System.currentTimeMillis:()J
     274: lload         7
     276: lsub
     277: lstore        9
     279: lload         9
     281: aload_0
     282: getfield      #15                 // Field timeout:J
     285: lcmp
     286: ifle          115
     289: getstatic     #3                  // Field LOG:Lorg/slf4j/Logger;
     292: new           #78                 // class java/lang/StringBuilder
     295: dup
     296: invokespecial #79                 // Method java/lang/StringBuilder."<init>":()V
     299: ldc           #112                // String The monitor is running too long (
     301: invokevirtual #80                 // Method java/lang/StringBuilder.append:(Ljava/lang/String;)Ljava/lang/StringBuilder;
     304: lload         9
     306: invokevirtual #99                 // Method java/lang/StringBuilder.append:(J)Ljava/lang/StringBuilder;
     309: ldc           #113                // String ) after timeout limit:
     311: invokevirtual #80                 // Method java/lang/StringBuilder.append:(Ljava/lang/String;)Ljava/lang/StringBuilder;
     314: aload_0
     315: getfield      #15                 // Field timeout:J
     318: invokevirtual #99                 // Method java/lang/StringBuilder.append:(J)Ljava/lang/StringBuilder;
     321: ldc           #114                // String  will be killed itself !!
     323: invokevirtual #80                 // Method java/lang/StringBuilder.append:(Ljava/lang/String;)Ljava/lang/StringBuilder;
     326: invokevirtual #82                 // Method java/lang/StringBuilder.toString:()Ljava/lang/String;
     329: invokeinterface #115,  2          // InterfaceMethod org/slf4j/Logger.error:(Ljava/lang/String;)V
     334: aload         5
     336: getfield      #106                // Field org/apache/hadoop/hbase/tool/Canary$Monitor.initialized:Z
     339: ifeq          397
     342: iconst_3
     343: istore        13
     345: aload         5
     347: ifnull        355
     350: aload         5
     352: invokevirtual #108                // Method org/apache/hadoop/hbase/tool/Canary$Monitor.close:()V
     355: aload         11
     357: ifnull        394
     360: aload         12
     362: ifnull        387
     365: aload         11
     367: invokeinterface #109,  1          // InterfaceMethod org/apache/hadoop/hbase/client/Connection.close:()V
     372: goto          394
     375: astore        14
     377: aload         12
     379: aload         14
     381: invokevirtual #111                // Method java/lang/Throwable.addSuppressed:(Ljava/lang/Throwable;)V
     384: goto          394
     387: aload         11
     389: invokeinterface #109,  1          // InterfaceMethod org/apache/hadoop/hbase/client/Connection.close:()V
     394: iload         13
     396: ireturn
     397: iconst_2
     398: istore        13
     400: aload         5
     402: ifnull        410
     405: aload         5
     407: invokevirtual #108                // Method org/apache/hadoop/hbase/tool/Canary$Monitor.close:()V
     410: aload         11
     412: ifnull        449
     415: aload         12
     417: ifnull        442
     420: aload         11
     422: invokeinterface #109,  1          // InterfaceMethod org/apache/hadoop/hbase/client/Connection.close:()V
     427: goto          449
     430: astore        14
     432: aload         12
     434: aload         14
     436: invokevirtual #111                // Method java/lang/Throwable.addSuppressed:(Ljava/lang/Throwable;)V
     439: goto          449
     442: aload         11
     444: invokeinterface #109,  1          // InterfaceMethod org/apache/hadoop/hbase/client/Connection.close:()V
     449: iload         13
     451: ireturn
     452: aload_0
     453: getfield      #16                 // Field failOnError:Z
     456: ifeq          531
     459: aload         5
     461: invokevirtual #116                // Method org/apache/hadoop/hbase/tool/Canary$Monitor.finalCheckForErrors:()Z
     464: ifeq          531
     467: aload         6
     469: invokevirtual #105                // Method java/lang/Thread.interrupt:()V
     472: aload         5
     474: getfield      #107                // Field org/apache/hadoop/hbase/tool/Canary$Monitor.errorCode:I
     477: istore        13
     479: aload         5
     481: ifnull        489
     484: aload         5
     486: invokevirtual #108                // Method org/apache/hadoop/hbase/tool/Canary$Monitor.close:()V
     489: aload         11
     491: ifnull        528
     494: aload         12
     496: ifnull        521
     499: aload         11
     501: invokeinterface #109,  1          // InterfaceMethod org/apache/hadoop/hbase/client/Connection.close:()V
     506: goto          528
     509: astore        14
     511: aload         12
     513: aload         14
     515: invokevirtual #111                // Method java/lang/Throwable.addSuppressed:(Ljava/lang/Throwable;)V
     518: goto          528
     521: aload         11
     523: invokeinterface #109,  1          // InterfaceMethod org/apache/hadoop/hbase/client/Connection.close:()V
     528: iload         13
     530: ireturn
     531: aload         5
     533: ifnull        559
     536: aload         5
     538: invokevirtual #108                // Method org/apache/hadoop/hbase/tool/Canary$Monitor.close:()V
     541: goto          559
     544: astore        15
     546: aload         5
     548: ifnull        556
     551: aload         5
     553: invokevirtual #108                // Method org/apache/hadoop/hbase/tool/Canary$Monitor.close:()V
     556: aload         15
     558: athrow
     559: aload_0
     560: getfield      #10                 // Field interval:J
     563: invokestatic  #103                // Method java/lang/Thread.sleep:(J)V
     566: aload_0
     567: getfield      #10                 // Field interval:J
     570: lconst_0
     571: lcmp
     572: ifgt          63
     575: aload         11
     577: ifnull        670
     580: aload         12
     582: ifnull        607
     585: aload         11
     587: invokeinterface #109,  1          // InterfaceMethod org/apache/hadoop/hbase/client/Connection.close:()V
     592: goto          670
     595: astore        13
     597: aload         12
     599: aload         13
     601: invokevirtual #111                // Method java/lang/Throwable.addSuppressed:(Ljava/lang/Throwable;)V
     604: goto          670
     607: aload         11
     609: invokeinterface #109,  1          // InterfaceMethod org/apache/hadoop/hbase/client/Connection.close:()V
     614: goto          670
     617: astore        13
     619: aload         13
     621: astore        12
     623: aload         13
     625: athrow
     626: astore        16
     628: aload         11
     630: ifnull        667
     633: aload         12
     635: ifnull        660
     638: aload         11
     640: invokeinterface #109,  1          // InterfaceMethod org/apache/hadoop/hbase/client/Connection.close:()V
     645: goto          667
     648: astore        17
     650: aload         12
     652: aload         17
     654: invokevirtual #111                // Method java/lang/Throwable.addSuppressed:(Ljava/lang/Throwable;)V
     657: goto          667
     660: aload         11
     662: invokeinterface #109,  1          // InterfaceMethod org/apache/hadoop/hbase/client/Connection.close:()V
     667: aload         16
     669: athrow
     670: aload_3
     671: ifnull        678
     674: aload_3
     675: invokevirtual #117                // Method org/apache/hadoop/hbase/ChoreService.shutdown:()V
     678: aload         5
     680: getfield      #107                // Field org/apache/hadoop/hbase/tool/Canary$Monitor.errorCode:I
     683: ireturn
    Exception table:
       from    to  target type
         184   191   194   Class java/lang/Throwable
         239   246   249   Class java/lang/Throwable
         365   372   375   Class java/lang/Throwable
         420   427   430   Class java/lang/Throwable
         499   506   509   Class java/lang/Throwable
          63   164   544   any
         216   219   544   any
         271   345   544   any
         397   400   544   any
         452   479   544   any
         544   546   544   any
         585   592   595   Class java/lang/Throwable
          63   174   617   Class java/lang/Throwable
         216   229   617   Class java/lang/Throwable
         271   355   617   Class java/lang/Throwable
         397   410   617   Class java/lang/Throwable
         452   489   617   Class java/lang/Throwable
         531   575   617   Class java/lang/Throwable
          63   174   626   any
         216   229   626   any
         271   355   626   any
         397   410   626   any
         452   489   626   any
         531   575   626   any
         638   645   648   Class java/lang/Throwable
         617   628   626   any

  public java.util.Map<java.lang.String, java.lang.String> getReadFailures();
    Code:
       0: aload_0
       1: getfield      #11                 // Field sink:Lorg/apache/hadoop/hbase/tool/Canary$Sink;
       4: invokeinterface #118,  1          // InterfaceMethod org/apache/hadoop/hbase/tool/Canary$Sink.getReadFailures:()Ljava/util/Map;
       9: areturn

  public java.util.Map<java.lang.String, java.lang.String> getWriteFailures();
    Code:
       0: aload_0
       1: getfield      #11                 // Field sink:Lorg/apache/hadoop/hbase/tool/Canary$Sink;
       4: invokeinterface #119,  1          // InterfaceMethod org/apache/hadoop/hbase/tool/Canary$Sink.getWriteFailures:()Ljava/util/Map;
       9: areturn

  org.apache.hadoop.hbase.tool.Canary$Sink getSink(org.apache.hadoop.conf.Configuration, java.lang.Class);
    Code:
       0: aload_0
       1: getfield      #11                 // Field sink:Lorg/apache/hadoop/hbase/tool/Canary$Sink;
       4: ifnull        14
       7: aload_0
       8: getfield      #11                 // Field sink:Lorg/apache/hadoop/hbase/tool/Canary$Sink;
      11: goto          33
      14: aload_1
      15: ldc           #149                // String hbase.canary.sink.class
      17: aload_2
      18: ldc           #150                // class org/apache/hadoop/hbase/tool/Canary$Sink
      20: invokevirtual #151                // Method org/apache/hadoop/conf/Configuration.getClass:(Ljava/lang/String;Ljava/lang/Class;Ljava/lang/Class;)Ljava/lang/Class;
      23: iconst_0
      24: anewarray     #152                // class java/lang/Object
      27: invokestatic  #153                // Method org/apache/hadoop/hbase/util/ReflectionUtils.newInstance:(Ljava/lang/Class;[Ljava/lang/Object;)Ljava/lang/Object;
      30: checkcast     #150                // class org/apache/hadoop/hbase/tool/Canary$Sink
      33: areturn

  public org.apache.hadoop.hbase.tool.Canary$Monitor newMonitor(org.apache.hadoop.hbase.client.Connection, int, java.lang.String[]);
    Code:
       0: aconst_null
       1: astore        4
       3: aconst_null
       4: astore        5
       6: iload_2
       7: iflt          33
      10: aload_3
      11: arraylength
      12: iload_2
      13: isub
      14: istore        6
      16: iload         6
      18: anewarray     #154                // class java/lang/String
      21: astore        5
      23: aload_3
      24: iload_2
      25: aload         5
      27: iconst_0
      28: iload         6
      30: invokestatic  #155                // Method java/lang/System.arraycopy:(Ljava/lang/Object;ILjava/lang/Object;II)V
      33: aload_0
      34: getfield      #17                 // Field regionServerMode:Z
      37: ifeq          87
      40: new           #156                // class org/apache/hadoop/hbase/tool/Canary$RegionServerMonitor
      43: dup
      44: aload_1
      45: aload         5
      47: aload_0
      48: getfield      #56                 // Field useRegExp:Z
      51: aload_0
      52: aload_1
      53: invokeinterface #157,  1          // InterfaceMethod org/apache/hadoop/hbase/client/Connection.getConfiguration:()Lorg/apache/hadoop/conf/Configuration;
      58: ldc           #158                // class org/apache/hadoop/hbase/tool/Canary$RegionServerStdOutSink
      60: invokevirtual #159                // Method getSink:(Lorg/apache/hadoop/conf/Configuration;Ljava/lang/Class;)Lorg/apache/hadoop/hbase/tool/Canary$Sink;
      63: aload_0
      64: getfield      #29                 // Field executor:Ljava/util/concurrent/ExecutorService;
      67: aload_0
      68: getfield      #20                 // Field regionServerAllRegions:Z
      71: aload_0
      72: getfield      #23                 // Field treatFailureAsError:Z
      75: aload_0
      76: getfield      #19                 // Field permittedFailures:J
      79: invokespecial #160                // Method org/apache/hadoop/hbase/tool/Canary$RegionServerMonitor."<init>":(Lorg/apache/hadoop/hbase/client/Connection;[Ljava/lang/String;ZLorg/apache/hadoop/hbase/tool/Canary$Sink;Ljava/util/concurrent/ExecutorService;ZZJ)V
      82: astore        4
      84: goto          193
      87: aload_0
      88: getfield      #18                 // Field zookeeperMode:Z
      91: ifeq          137
      94: new           #161                // class org/apache/hadoop/hbase/tool/Canary$ZookeeperMonitor
      97: dup
      98: aload_1
      99: aload         5
     101: aload_0
     102: getfield      #56                 // Field useRegExp:Z
     105: aload_0
     106: aload_1
     107: invokeinterface #157,  1          // InterfaceMethod org/apache/hadoop/hbase/client/Connection.getConfiguration:()Lorg/apache/hadoop/conf/Configuration;
     112: ldc           #162                // class org/apache/hadoop/hbase/tool/Canary$ZookeeperStdOutSink
     114: invokevirtual #159                // Method getSink:(Lorg/apache/hadoop/conf/Configuration;Ljava/lang/Class;)Lorg/apache/hadoop/hbase/tool/Canary$Sink;
     117: aload_0
     118: getfield      #29                 // Field executor:Ljava/util/concurrent/ExecutorService;
     121: aload_0
     122: getfield      #23                 // Field treatFailureAsError:Z
     125: aload_0
     126: getfield      #19                 // Field permittedFailures:J
     129: invokespecial #163                // Method org/apache/hadoop/hbase/tool/Canary$ZookeeperMonitor."<init>":(Lorg/apache/hadoop/hbase/client/Connection;[Ljava/lang/String;ZLorg/apache/hadoop/hbase/tool/Canary$Sink;Ljava/util/concurrent/ExecutorService;ZJ)V
     132: astore        4
     134: goto          193
     137: new           #164                // class org/apache/hadoop/hbase/tool/Canary$RegionMonitor
     140: dup
     141: aload_1
     142: aload         5
     144: aload_0
     145: getfield      #56                 // Field useRegExp:Z
     148: aload_0
     149: aload_1
     150: invokeinterface #157,  1          // InterfaceMethod org/apache/hadoop/hbase/client/Connection.getConfiguration:()Lorg/apache/hadoop/conf/Configuration;
     155: ldc           #165                // class org/apache/hadoop/hbase/tool/Canary$RegionStdOutSink
     157: invokevirtual #159                // Method getSink:(Lorg/apache/hadoop/conf/Configuration;Ljava/lang/Class;)Lorg/apache/hadoop/hbase/tool/Canary$Sink;
     160: aload_0
     161: getfield      #29                 // Field executor:Ljava/util/concurrent/ExecutorService;
     164: aload_0
     165: getfield      #21                 // Field writeSniffing:Z
     168: aload_0
     169: getfield      #25                 // Field writeTableName:Lorg/apache/hadoop/hbase/TableName;
     172: aload_0
     173: getfield      #23                 // Field treatFailureAsError:Z
     176: aload_0
     177: getfield      #28                 // Field configuredReadTableTimeouts:Ljava/util/HashMap;
     180: aload_0
     181: getfield      #22                 // Field configuredWriteTableTimeout:J
     184: aload_0
     185: getfield      #19                 // Field permittedFailures:J
     188: invokespecial #166                // Method org/apache/hadoop/hbase/tool/Canary$RegionMonitor."<init>":(Lorg/apache/hadoop/hbase/client/Connection;[Ljava/lang/String;ZLorg/apache/hadoop/hbase/tool/Canary$Sink;Ljava/util/concurrent/ExecutorService;ZLorg/apache/hadoop/hbase/TableName;ZLjava/util/HashMap;JJ)V
     191: astore        4
     193: aload         4
     195: areturn

  public static void main(java.lang.String[]) throws java.lang.Exception;
    Code:
       0: invokestatic  #197                // Method org/apache/hadoop/hbase/HBaseConfiguration.create:()Lorg/apache/hadoop/conf/Configuration;
       3: astore_1
       4: new           #198                // class org/apache/hadoop/util/GenericOptionsParser
       7: dup
       8: aload_1
       9: aload_0
      10: invokespecial #199                // Method org/apache/hadoop/util/GenericOptionsParser."<init>":(Lorg/apache/hadoop/conf/Configuration;[Ljava/lang/String;)V
      13: pop
      14: aload_1
      15: ldc           #200                // String hbase.canary.threads.num
      17: bipush        16
      19: invokevirtual #201                // Method org/apache/hadoop/conf/Configuration.getInt:(Ljava/lang/String;I)I
      22: istore_2
      23: getstatic     #3                  // Field LOG:Lorg/slf4j/Logger;
      26: ldc           #202                // String Execution thread count={}
      28: iload_2
      29: invokestatic  #203                // Method java/lang/Integer.valueOf:(I)Ljava/lang/Integer;
      32: invokeinterface #204,  3          // InterfaceMethod org/slf4j/Logger.info:(Ljava/lang/String;Ljava/lang/Object;)V
      37: iconst_0
      38: istore_3
      39: new           #4                  // class java/util/concurrent/ScheduledThreadPoolExecutor
      42: dup
      43: iload_2
      44: invokespecial #5                  // Method java/util/concurrent/ScheduledThreadPoolExecutor."<init>":(I)V
      47: astore        4
      49: aload_1
      50: new           #12                 // class org/apache/hadoop/hbase/tool/Canary
      53: dup
      54: aload         4
      56: invokespecial #6                  // Method "<init>":(Ljava/util/concurrent/ExecutorService;)V
      59: aload_0
      60: invokestatic  #205                // Method org/apache/hadoop/util/ToolRunner.run:(Lorg/apache/hadoop/conf/Configuration;Lorg/apache/hadoop/util/Tool;[Ljava/lang/String;)I
      63: istore_3
      64: aload         4
      66: invokeinterface #206,  1          // InterfaceMethod java/util/concurrent/ExecutorService.shutdown:()V
      71: goto          86
      74: astore        5
      76: aload         4
      78: invokeinterface #206,  1          // InterfaceMethod java/util/concurrent/ExecutorService.shutdown:()V
      83: aload         5
      85: athrow
      86: iload_3
      87: invokestatic  #148                // Method java/lang/System.exit:(I)V
      90: return
    Exception table:
       from    to  target type
          49    64    74   any
          74    76    74   any

  static org.slf4j.Logger access$000();
    Code:
       0: getstatic     #3                  // Field LOG:Lorg/slf4j/Logger;
       3: areturn

  static java.util.List access$100(org.apache.hadoop.hbase.client.Admin, org.apache.hadoop.hbase.tool.Canary$Sink, java.lang.String, java.util.concurrent.ExecutorService, org.apache.hadoop.hbase.tool.Canary$RegionTask$TaskType, boolean, java.util.concurrent.atomic.LongAdder) throws java.lang.Exception;
    Code:
       0: aload_0
       1: aload_1
       2: aload_2
       3: aload_3
       4: aload         4
       6: iload         5
       8: aload         6
      10: invokestatic  #2                  // Method sniff:(Lorg/apache/hadoop/hbase/client/Admin;Lorg/apache/hadoop/hbase/tool/Canary$Sink;Ljava/lang/String;Ljava/util/concurrent/ExecutorService;Lorg/apache/hadoop/hbase/tool/Canary$RegionTask$TaskType;ZLjava/util/concurrent/atomic/LongAdder;)Ljava/util/List;
      13: areturn

  static java.util.List access$200(org.apache.hadoop.hbase.client.Admin, org.apache.hadoop.hbase.tool.Canary$Sink, org.apache.hadoop.hbase.client.TableDescriptor, java.util.concurrent.ExecutorService, org.apache.hadoop.hbase.tool.Canary$RegionTask$TaskType, boolean, java.util.concurrent.atomic.LongAdder) throws java.lang.Exception;
    Code:
       0: aload_0
       1: aload_1
       2: aload_2
       3: aload_3
       4: aload         4
       6: iload         5
       8: aload         6
      10: invokestatic  #1                  // Method sniff:(Lorg/apache/hadoop/hbase/client/Admin;Lorg/apache/hadoop/hbase/tool/Canary$Sink;Lorg/apache/hadoop/hbase/client/TableDescriptor;Ljava/util/concurrent/ExecutorService;Lorg/apache/hadoop/hbase/tool/Canary$RegionTask$TaskType;ZLjava/util/concurrent/atomic/LongAdder;)Ljava/util/List;
      13: areturn

  static {};
    Code:
       0: ldc           #12                 // class org/apache/hadoop/hbase/tool/Canary
       2: invokestatic  #207                // Method org/slf4j/LoggerFactory.getLogger:(Ljava/lang/Class;)Lorg/slf4j/Logger;
       5: putstatic     #3                  // Field LOG:Lorg/slf4j/Logger;
       8: getstatic     #208                // Field org/apache/hadoop/hbase/NamespaceDescriptor.SYSTEM_NAMESPACE_NAME_STR:Ljava/lang/String;
      11: ldc           #209                // String canary
      13: invokestatic  #210                // Method org/apache/hadoop/hbase/TableName.valueOf:(Ljava/lang/String;Ljava/lang/String;)Lorg/apache/hadoop/hbase/TableName;
      16: putstatic     #24                 // Field DEFAULT_WRITE_TABLE_NAME:Lorg/apache/hadoop/hbase/TableName;
      19: return
}
