Compiled from "CellFlatMap.java"
class org.apache.hadoop.hbase.regionserver.CellFlatMap$CellFlatMapEntry implements java.util.Map$Entry<org.apache.hadoop.hbase.Cell, org.apache.hadoop.hbase.Cell> {
  public org.apache.hadoop.hbase.regionserver.CellFlatMap$CellFlatMapEntry(org.apache.hadoop.hbase.Cell);
    Code:
       0: aload_0
       1: invokespecial #1                  // Method java/lang/Object."<init>":()V
       4: aload_0
       5: aload_1
       6: putfield      #2                  // Field cell:Lorg/apache/hadoop/hbase/Cell;
       9: return

  public org.apache.hadoop.hbase.Cell getKey();
    Code:
       0: aload_0
       1: getfield      #2                  // Field cell:Lorg/apache/hadoop/hbase/Cell;
       4: areturn

  public org.apache.hadoop.hbase.Cell getValue();
    Code:
       0: aload_0
       1: getfield      #2                  // Field cell:Lorg/apache/hadoop/hbase/Cell;
       4: areturn

  public org.apache.hadoop.hbase.Cell setValue(org.apache.hadoop.hbase.Cell);
    Code:
       0: new           #3                  // class java/lang/UnsupportedOperationException
       3: dup
       4: invokespecial #4                  // Method java/lang/UnsupportedOperationException."<init>":()V
       7: athrow

  public java.lang.Object setValue(java.lang.Object);
    Code:
       0: aload_0
       1: aload_1
       2: checkcast     #5                  // class org/apache/hadoop/hbase/Cell
       5: invokevirtual #6                  // Method setValue:(Lorg/apache/hadoop/hbase/Cell;)Lorg/apache/hadoop/hbase/Cell;
       8: areturn

  public java.lang.Object getValue();
    Code:
       0: aload_0
       1: invokevirtual #7                  // Method getValue:()Lorg/apache/hadoop/hbase/Cell;
       4: areturn

  public java.lang.Object getKey();
    Code:
       0: aload_0
       1: invokevirtual #8                  // Method getKey:()Lorg/apache/hadoop/hbase/Cell;
       4: areturn
}
