Compiled from "CellHashKey.java"
public abstract class org.apache.hadoop.hbase.util.CellHashKey extends org.apache.hadoop.hbase.util.HashKey<org.apache.hadoop.hbase.Cell> {
  protected static final byte[] LATEST_TS;

  protected static final byte MAX_TYPE;

  public org.apache.hadoop.hbase.util.CellHashKey(org.apache.hadoop.hbase.Cell);
    Code:
       0: aload_0
       1: aload_1
       2: invokespecial #1                  // Method org/apache/hadoop/hbase/util/HashKey."<init>":(Ljava/lang/Object;)V
       5: return

  static {};
    Code:
       0: ldc2_w        #3                  // long 9223372036854775807l
       3: invokestatic  #5                  // Method org/apache/hadoop/hbase/util/Bytes.toBytes:(J)[B
       6: putstatic     #6                  // Field LATEST_TS:[B
       9: getstatic     #7                  // Field org/apache/hadoop/hbase/KeyValue$Type.Maximum:Lorg/apache/hadoop/hbase/KeyValue$Type;
      12: invokevirtual #8                  // Method org/apache/hadoop/hbase/KeyValue$Type.getCode:()B
      15: putstatic     #9                  // Field MAX_TYPE:B
      18: return
}
