Compiled from "CellComparatorImpl.java"
public class org.apache.hadoop.hbase.CellComparatorImpl implements org.apache.hadoop.hbase.CellComparator {
  static final org.slf4j.Logger LOG;

  public static final org.apache.hadoop.hbase.CellComparatorImpl COMPARATOR;

  public static final org.apache.hadoop.hbase.CellComparatorImpl META_COMPARATOR;

  public org.apache.hadoop.hbase.CellComparatorImpl();
    Code:
       0: aload_0
       1: invokespecial #1                  // Method java/lang/Object."<init>":()V
       4: return

  public final int compare(org.apache.hadoop.hbase.Cell, org.apache.hadoop.hbase.Cell);
    Code:
       0: aload_0
       1: aload_1
       2: aload_2
       3: iconst_0
       4: invokevirtual #2                  // Method compare:(Lorg/apache/hadoop/hbase/Cell;Lorg/apache/hadoop/hbase/Cell;Z)I
       7: ireturn

  public int compare(org.apache.hadoop.hbase.Cell, org.apache.hadoop.hbase.Cell, boolean);
    Code:
       0: iconst_0
       1: istore        4
       3: aload_1
       4: instanceof    #3                  // class org/apache/hadoop/hbase/ByteBufferKeyValue
       7: ifeq          39
      10: aload_2
      11: instanceof    #3                  // class org/apache/hadoop/hbase/ByteBufferKeyValue
      14: ifeq          39
      17: aload_1
      18: checkcast     #3                  // class org/apache/hadoop/hbase/ByteBufferKeyValue
      21: aload_2
      22: checkcast     #3                  // class org/apache/hadoop/hbase/ByteBufferKeyValue
      25: iload_3
      26: invokestatic  #4                  // Method org/apache/hadoop/hbase/BBKVComparator.compare:(Lorg/apache/hadoop/hbase/ByteBufferKeyValue;Lorg/apache/hadoop/hbase/ByteBufferKeyValue;Z)I
      29: istore        4
      31: iload         4
      33: ifeq          71
      36: iload         4
      38: ireturn
      39: aload_0
      40: aload_1
      41: aload_2
      42: invokevirtual #5                  // Method compareRows:(Lorg/apache/hadoop/hbase/Cell;Lorg/apache/hadoop/hbase/Cell;)I
      45: istore        4
      47: iload         4
      49: ifeq          55
      52: iload         4
      54: ireturn
      55: aload_0
      56: aload_1
      57: aload_2
      58: invokevirtual #6                  // Method compareWithoutRow:(Lorg/apache/hadoop/hbase/Cell;Lorg/apache/hadoop/hbase/Cell;)I
      61: istore        4
      63: iload         4
      65: ifeq          71
      68: iload         4
      70: ireturn
      71: iload_3
      72: ifeq          80
      75: iload         4
      77: goto          95
      80: aload_2
      81: invokeinterface #7,  1            // InterfaceMethod org/apache/hadoop/hbase/Cell.getSequenceId:()J
      86: aload_1
      87: invokeinterface #7,  1            // InterfaceMethod org/apache/hadoop/hbase/Cell.getSequenceId:()J
      92: invokestatic  #8                  // Method java/lang/Long.compare:(JJ)I
      95: ireturn

  public final int compareColumns(org.apache.hadoop.hbase.Cell, org.apache.hadoop.hbase.Cell);
    Code:
       0: aload_0
       1: aload_1
       2: aload_2
       3: invokevirtual #9                  // Method compareFamilies:(Lorg/apache/hadoop/hbase/Cell;Lorg/apache/hadoop/hbase/Cell;)I
       6: istore_3
       7: iload_3
       8: ifeq          13
      11: iload_3
      12: ireturn
      13: aload_0
      14: aload_1
      15: aload_2
      16: invokevirtual #10                 // Method compareQualifiers:(Lorg/apache/hadoop/hbase/Cell;Lorg/apache/hadoop/hbase/Cell;)I
      19: ireturn

  public final int compareFamilies(org.apache.hadoop.hbase.Cell, org.apache.hadoop.hbase.Cell);
    Code:
       0: aload_1
       1: instanceof    #11                 // class org/apache/hadoop/hbase/ByteBufferExtendedCell
       4: ifeq          58
       7: aload_2
       8: instanceof    #11                 // class org/apache/hadoop/hbase/ByteBufferExtendedCell
      11: ifeq          58
      14: aload_1
      15: checkcast     #11                 // class org/apache/hadoop/hbase/ByteBufferExtendedCell
      18: invokevirtual #12                 // Method org/apache/hadoop/hbase/ByteBufferExtendedCell.getFamilyByteBuffer:()Ljava/nio/ByteBuffer;
      21: aload_1
      22: checkcast     #11                 // class org/apache/hadoop/hbase/ByteBufferExtendedCell
      25: invokevirtual #13                 // Method org/apache/hadoop/hbase/ByteBufferExtendedCell.getFamilyPosition:()I
      28: aload_1
      29: invokeinterface #14,  1           // InterfaceMethod org/apache/hadoop/hbase/Cell.getFamilyLength:()B
      34: aload_2
      35: checkcast     #11                 // class org/apache/hadoop/hbase/ByteBufferExtendedCell
      38: invokevirtual #12                 // Method org/apache/hadoop/hbase/ByteBufferExtendedCell.getFamilyByteBuffer:()Ljava/nio/ByteBuffer;
      41: aload_2
      42: checkcast     #11                 // class org/apache/hadoop/hbase/ByteBufferExtendedCell
      45: invokevirtual #13                 // Method org/apache/hadoop/hbase/ByteBufferExtendedCell.getFamilyPosition:()I
      48: aload_2
      49: invokeinterface #14,  1           // InterfaceMethod org/apache/hadoop/hbase/Cell.getFamilyLength:()B
      54: invokestatic  #15                 // Method org/apache/hadoop/hbase/util/ByteBufferUtils.compareTo:(Ljava/nio/ByteBuffer;IILjava/nio/ByteBuffer;II)I
      57: ireturn
      58: aload_1
      59: instanceof    #11                 // class org/apache/hadoop/hbase/ByteBufferExtendedCell
      62: ifeq          107
      65: aload_1
      66: checkcast     #11                 // class org/apache/hadoop/hbase/ByteBufferExtendedCell
      69: invokevirtual #12                 // Method org/apache/hadoop/hbase/ByteBufferExtendedCell.getFamilyByteBuffer:()Ljava/nio/ByteBuffer;
      72: aload_1
      73: checkcast     #11                 // class org/apache/hadoop/hbase/ByteBufferExtendedCell
      76: invokevirtual #13                 // Method org/apache/hadoop/hbase/ByteBufferExtendedCell.getFamilyPosition:()I
      79: aload_1
      80: invokeinterface #14,  1           // InterfaceMethod org/apache/hadoop/hbase/Cell.getFamilyLength:()B
      85: aload_2
      86: invokeinterface #16,  1           // InterfaceMethod org/apache/hadoop/hbase/Cell.getFamilyArray:()[B
      91: aload_2
      92: invokeinterface #17,  1           // InterfaceMethod org/apache/hadoop/hbase/Cell.getFamilyOffset:()I
      97: aload_2
      98: invokeinterface #14,  1           // InterfaceMethod org/apache/hadoop/hbase/Cell.getFamilyLength:()B
     103: invokestatic  #18                 // Method org/apache/hadoop/hbase/util/ByteBufferUtils.compareTo:(Ljava/nio/ByteBuffer;II[BII)I
     106: ireturn
     107: aload_2
     108: instanceof    #11                 // class org/apache/hadoop/hbase/ByteBufferExtendedCell
     111: ifeq          156
     114: aload_1
     115: invokeinterface #16,  1           // InterfaceMethod org/apache/hadoop/hbase/Cell.getFamilyArray:()[B
     120: aload_1
     121: invokeinterface #17,  1           // InterfaceMethod org/apache/hadoop/hbase/Cell.getFamilyOffset:()I
     126: aload_1
     127: invokeinterface #14,  1           // InterfaceMethod org/apache/hadoop/hbase/Cell.getFamilyLength:()B
     132: aload_2
     133: checkcast     #11                 // class org/apache/hadoop/hbase/ByteBufferExtendedCell
     136: invokevirtual #12                 // Method org/apache/hadoop/hbase/ByteBufferExtendedCell.getFamilyByteBuffer:()Ljava/nio/ByteBuffer;
     139: aload_2
     140: checkcast     #11                 // class org/apache/hadoop/hbase/ByteBufferExtendedCell
     143: invokevirtual #13                 // Method org/apache/hadoop/hbase/ByteBufferExtendedCell.getFamilyPosition:()I
     146: aload_2
     147: invokeinterface #14,  1           // InterfaceMethod org/apache/hadoop/hbase/Cell.getFamilyLength:()B
     152: invokestatic  #19                 // Method org/apache/hadoop/hbase/util/ByteBufferUtils.compareTo:([BIILjava/nio/ByteBuffer;II)I
     155: ireturn
     156: aload_1
     157: invokeinterface #16,  1           // InterfaceMethod org/apache/hadoop/hbase/Cell.getFamilyArray:()[B
     162: aload_1
     163: invokeinterface #17,  1           // InterfaceMethod org/apache/hadoop/hbase/Cell.getFamilyOffset:()I
     168: aload_1
     169: invokeinterface #14,  1           // InterfaceMethod org/apache/hadoop/hbase/Cell.getFamilyLength:()B
     174: aload_2
     175: invokeinterface #16,  1           // InterfaceMethod org/apache/hadoop/hbase/Cell.getFamilyArray:()[B
     180: aload_2
     181: invokeinterface #17,  1           // InterfaceMethod org/apache/hadoop/hbase/Cell.getFamilyOffset:()I
     186: aload_2
     187: invokeinterface #14,  1           // InterfaceMethod org/apache/hadoop/hbase/Cell.getFamilyLength:()B
     192: invokestatic  #20                 // Method org/apache/hadoop/hbase/util/Bytes.compareTo:([BII[BII)I
     195: ireturn

  public final int compareQualifiers(org.apache.hadoop.hbase.Cell, org.apache.hadoop.hbase.Cell);
    Code:
       0: aload_1
       1: instanceof    #11                 // class org/apache/hadoop/hbase/ByteBufferExtendedCell
       4: ifeq          58
       7: aload_2
       8: instanceof    #11                 // class org/apache/hadoop/hbase/ByteBufferExtendedCell
      11: ifeq          58
      14: aload_1
      15: checkcast     #11                 // class org/apache/hadoop/hbase/ByteBufferExtendedCell
      18: invokevirtual #21                 // Method org/apache/hadoop/hbase/ByteBufferExtendedCell.getQualifierByteBuffer:()Ljava/nio/ByteBuffer;
      21: aload_1
      22: checkcast     #11                 // class org/apache/hadoop/hbase/ByteBufferExtendedCell
      25: invokevirtual #22                 // Method org/apache/hadoop/hbase/ByteBufferExtendedCell.getQualifierPosition:()I
      28: aload_1
      29: invokeinterface #23,  1           // InterfaceMethod org/apache/hadoop/hbase/Cell.getQualifierLength:()I
      34: aload_2
      35: checkcast     #11                 // class org/apache/hadoop/hbase/ByteBufferExtendedCell
      38: invokevirtual #21                 // Method org/apache/hadoop/hbase/ByteBufferExtendedCell.getQualifierByteBuffer:()Ljava/nio/ByteBuffer;
      41: aload_2
      42: checkcast     #11                 // class org/apache/hadoop/hbase/ByteBufferExtendedCell
      45: invokevirtual #22                 // Method org/apache/hadoop/hbase/ByteBufferExtendedCell.getQualifierPosition:()I
      48: aload_2
      49: invokeinterface #23,  1           // InterfaceMethod org/apache/hadoop/hbase/Cell.getQualifierLength:()I
      54: invokestatic  #15                 // Method org/apache/hadoop/hbase/util/ByteBufferUtils.compareTo:(Ljava/nio/ByteBuffer;IILjava/nio/ByteBuffer;II)I
      57: ireturn
      58: aload_1
      59: instanceof    #11                 // class org/apache/hadoop/hbase/ByteBufferExtendedCell
      62: ifeq          107
      65: aload_1
      66: checkcast     #11                 // class org/apache/hadoop/hbase/ByteBufferExtendedCell
      69: invokevirtual #21                 // Method org/apache/hadoop/hbase/ByteBufferExtendedCell.getQualifierByteBuffer:()Ljava/nio/ByteBuffer;
      72: aload_1
      73: checkcast     #11                 // class org/apache/hadoop/hbase/ByteBufferExtendedCell
      76: invokevirtual #22                 // Method org/apache/hadoop/hbase/ByteBufferExtendedCell.getQualifierPosition:()I
      79: aload_1
      80: invokeinterface #23,  1           // InterfaceMethod org/apache/hadoop/hbase/Cell.getQualifierLength:()I
      85: aload_2
      86: invokeinterface #24,  1           // InterfaceMethod org/apache/hadoop/hbase/Cell.getQualifierArray:()[B
      91: aload_2
      92: invokeinterface #25,  1           // InterfaceMethod org/apache/hadoop/hbase/Cell.getQualifierOffset:()I
      97: aload_2
      98: invokeinterface #23,  1           // InterfaceMethod org/apache/hadoop/hbase/Cell.getQualifierLength:()I
     103: invokestatic  #18                 // Method org/apache/hadoop/hbase/util/ByteBufferUtils.compareTo:(Ljava/nio/ByteBuffer;II[BII)I
     106: ireturn
     107: aload_2
     108: instanceof    #11                 // class org/apache/hadoop/hbase/ByteBufferExtendedCell
     111: ifeq          156
     114: aload_1
     115: invokeinterface #24,  1           // InterfaceMethod org/apache/hadoop/hbase/Cell.getQualifierArray:()[B
     120: aload_1
     121: invokeinterface #25,  1           // InterfaceMethod org/apache/hadoop/hbase/Cell.getQualifierOffset:()I
     126: aload_1
     127: invokeinterface #23,  1           // InterfaceMethod org/apache/hadoop/hbase/Cell.getQualifierLength:()I
     132: aload_2
     133: checkcast     #11                 // class org/apache/hadoop/hbase/ByteBufferExtendedCell
     136: invokevirtual #21                 // Method org/apache/hadoop/hbase/ByteBufferExtendedCell.getQualifierByteBuffer:()Ljava/nio/ByteBuffer;
     139: aload_2
     140: checkcast     #11                 // class org/apache/hadoop/hbase/ByteBufferExtendedCell
     143: invokevirtual #22                 // Method org/apache/hadoop/hbase/ByteBufferExtendedCell.getQualifierPosition:()I
     146: aload_2
     147: invokeinterface #23,  1           // InterfaceMethod org/apache/hadoop/hbase/Cell.getQualifierLength:()I
     152: invokestatic  #19                 // Method org/apache/hadoop/hbase/util/ByteBufferUtils.compareTo:([BIILjava/nio/ByteBuffer;II)I
     155: ireturn
     156: aload_1
     157: invokeinterface #24,  1           // InterfaceMethod org/apache/hadoop/hbase/Cell.getQualifierArray:()[B
     162: aload_1
     163: invokeinterface #25,  1           // InterfaceMethod org/apache/hadoop/hbase/Cell.getQualifierOffset:()I
     168: aload_1
     169: invokeinterface #23,  1           // InterfaceMethod org/apache/hadoop/hbase/Cell.getQualifierLength:()I
     174: aload_2
     175: invokeinterface #24,  1           // InterfaceMethod org/apache/hadoop/hbase/Cell.getQualifierArray:()[B
     180: aload_2
     181: invokeinterface #25,  1           // InterfaceMethod org/apache/hadoop/hbase/Cell.getQualifierOffset:()I
     186: aload_2
     187: invokeinterface #23,  1           // InterfaceMethod org/apache/hadoop/hbase/Cell.getQualifierLength:()I
     192: invokestatic  #20                 // Method org/apache/hadoop/hbase/util/Bytes.compareTo:([BII[BII)I
     195: ireturn

  public int compareRows(org.apache.hadoop.hbase.Cell, org.apache.hadoop.hbase.Cell);
    Code:
       0: aload_1
       1: aload_1
       2: invokeinterface #26,  1           // InterfaceMethod org/apache/hadoop/hbase/Cell.getRowLength:()S
       7: aload_2
       8: aload_2
       9: invokeinterface #26,  1           // InterfaceMethod org/apache/hadoop/hbase/Cell.getRowLength:()S
      14: invokestatic  #27                 // Method compareRows:(Lorg/apache/hadoop/hbase/Cell;ILorg/apache/hadoop/hbase/Cell;I)I
      17: ireturn

  static int compareRows(org.apache.hadoop.hbase.Cell, int, org.apache.hadoop.hbase.Cell, int);
    Code:
       0: aload_0
       1: aload_2
       2: if_acmpne     7
       5: iconst_0
       6: ireturn
       7: aload_0
       8: instanceof    #11                 // class org/apache/hadoop/hbase/ByteBufferExtendedCell
      11: ifeq          55
      14: aload_2
      15: instanceof    #11                 // class org/apache/hadoop/hbase/ByteBufferExtendedCell
      18: ifeq          55
      21: aload_0
      22: checkcast     #11                 // class org/apache/hadoop/hbase/ByteBufferExtendedCell
      25: invokevirtual #28                 // Method org/apache/hadoop/hbase/ByteBufferExtendedCell.getRowByteBuffer:()Ljava/nio/ByteBuffer;
      28: aload_0
      29: checkcast     #11                 // class org/apache/hadoop/hbase/ByteBufferExtendedCell
      32: invokevirtual #29                 // Method org/apache/hadoop/hbase/ByteBufferExtendedCell.getRowPosition:()I
      35: iload_1
      36: aload_2
      37: checkcast     #11                 // class org/apache/hadoop/hbase/ByteBufferExtendedCell
      40: invokevirtual #28                 // Method org/apache/hadoop/hbase/ByteBufferExtendedCell.getRowByteBuffer:()Ljava/nio/ByteBuffer;
      43: aload_2
      44: checkcast     #11                 // class org/apache/hadoop/hbase/ByteBufferExtendedCell
      47: invokevirtual #29                 // Method org/apache/hadoop/hbase/ByteBufferExtendedCell.getRowPosition:()I
      50: iload_3
      51: invokestatic  #15                 // Method org/apache/hadoop/hbase/util/ByteBufferUtils.compareTo:(Ljava/nio/ByteBuffer;IILjava/nio/ByteBuffer;II)I
      54: ireturn
      55: aload_0
      56: instanceof    #11                 // class org/apache/hadoop/hbase/ByteBufferExtendedCell
      59: ifeq          94
      62: aload_0
      63: checkcast     #11                 // class org/apache/hadoop/hbase/ByteBufferExtendedCell
      66: invokevirtual #28                 // Method org/apache/hadoop/hbase/ByteBufferExtendedCell.getRowByteBuffer:()Ljava/nio/ByteBuffer;
      69: aload_0
      70: checkcast     #11                 // class org/apache/hadoop/hbase/ByteBufferExtendedCell
      73: invokevirtual #29                 // Method org/apache/hadoop/hbase/ByteBufferExtendedCell.getRowPosition:()I
      76: iload_1
      77: aload_2
      78: invokeinterface #30,  1           // InterfaceMethod org/apache/hadoop/hbase/Cell.getRowArray:()[B
      83: aload_2
      84: invokeinterface #31,  1           // InterfaceMethod org/apache/hadoop/hbase/Cell.getRowOffset:()I
      89: iload_3
      90: invokestatic  #18                 // Method org/apache/hadoop/hbase/util/ByteBufferUtils.compareTo:(Ljava/nio/ByteBuffer;II[BII)I
      93: ireturn
      94: aload_2
      95: instanceof    #11                 // class org/apache/hadoop/hbase/ByteBufferExtendedCell
      98: ifeq          133
     101: aload_0
     102: invokeinterface #30,  1           // InterfaceMethod org/apache/hadoop/hbase/Cell.getRowArray:()[B
     107: aload_0
     108: invokeinterface #31,  1           // InterfaceMethod org/apache/hadoop/hbase/Cell.getRowOffset:()I
     113: iload_1
     114: aload_2
     115: checkcast     #11                 // class org/apache/hadoop/hbase/ByteBufferExtendedCell
     118: invokevirtual #28                 // Method org/apache/hadoop/hbase/ByteBufferExtendedCell.getRowByteBuffer:()Ljava/nio/ByteBuffer;
     121: aload_2
     122: checkcast     #11                 // class org/apache/hadoop/hbase/ByteBufferExtendedCell
     125: invokevirtual #29                 // Method org/apache/hadoop/hbase/ByteBufferExtendedCell.getRowPosition:()I
     128: iload_3
     129: invokestatic  #19                 // Method org/apache/hadoop/hbase/util/ByteBufferUtils.compareTo:([BIILjava/nio/ByteBuffer;II)I
     132: ireturn
     133: aload_0
     134: invokeinterface #30,  1           // InterfaceMethod org/apache/hadoop/hbase/Cell.getRowArray:()[B
     139: aload_0
     140: invokeinterface #31,  1           // InterfaceMethod org/apache/hadoop/hbase/Cell.getRowOffset:()I
     145: aload_0
     146: invokeinterface #26,  1           // InterfaceMethod org/apache/hadoop/hbase/Cell.getRowLength:()S
     151: aload_2
     152: invokeinterface #30,  1           // InterfaceMethod org/apache/hadoop/hbase/Cell.getRowArray:()[B
     157: aload_2
     158: invokeinterface #31,  1           // InterfaceMethod org/apache/hadoop/hbase/Cell.getRowOffset:()I
     163: aload_2
     164: invokeinterface #26,  1           // InterfaceMethod org/apache/hadoop/hbase/Cell.getRowLength:()S
     169: invokestatic  #20                 // Method org/apache/hadoop/hbase/util/Bytes.compareTo:([BII[BII)I
     172: ireturn

  public int compareRows(org.apache.hadoop.hbase.Cell, byte[], int, int);
    Code:
       0: aload_1
       1: instanceof    #11                 // class org/apache/hadoop/hbase/ByteBufferExtendedCell
       4: ifeq          35
       7: aload_1
       8: checkcast     #11                 // class org/apache/hadoop/hbase/ByteBufferExtendedCell
      11: invokevirtual #28                 // Method org/apache/hadoop/hbase/ByteBufferExtendedCell.getRowByteBuffer:()Ljava/nio/ByteBuffer;
      14: aload_1
      15: checkcast     #11                 // class org/apache/hadoop/hbase/ByteBufferExtendedCell
      18: invokevirtual #29                 // Method org/apache/hadoop/hbase/ByteBufferExtendedCell.getRowPosition:()I
      21: aload_1
      22: invokeinterface #26,  1           // InterfaceMethod org/apache/hadoop/hbase/Cell.getRowLength:()S
      27: aload_2
      28: iload_3
      29: iload         4
      31: invokestatic  #18                 // Method org/apache/hadoop/hbase/util/ByteBufferUtils.compareTo:(Ljava/nio/ByteBuffer;II[BII)I
      34: ireturn
      35: aload_1
      36: invokeinterface #30,  1           // InterfaceMethod org/apache/hadoop/hbase/Cell.getRowArray:()[B
      41: aload_1
      42: invokeinterface #31,  1           // InterfaceMethod org/apache/hadoop/hbase/Cell.getRowOffset:()I
      47: aload_1
      48: invokeinterface #26,  1           // InterfaceMethod org/apache/hadoop/hbase/Cell.getRowLength:()S
      53: aload_2
      54: iload_3
      55: iload         4
      57: invokestatic  #20                 // Method org/apache/hadoop/hbase/util/Bytes.compareTo:([BII[BII)I
      60: ireturn

  public final int compareWithoutRow(org.apache.hadoop.hbase.Cell, org.apache.hadoop.hbase.Cell);
    Code:
       0: aload_1
       1: invokeinterface #14,  1           // InterfaceMethod org/apache/hadoop/hbase/Cell.getFamilyLength:()B
       6: istore_3
       7: aload_2
       8: invokeinterface #14,  1           // InterfaceMethod org/apache/hadoop/hbase/Cell.getFamilyLength:()B
      13: istore        4
      15: aload_1
      16: invokeinterface #23,  1           // InterfaceMethod org/apache/hadoop/hbase/Cell.getQualifierLength:()I
      21: istore        5
      23: aload_2
      24: invokeinterface #23,  1           // InterfaceMethod org/apache/hadoop/hbase/Cell.getQualifierLength:()I
      29: istore        6
      31: iload_3
      32: iload         5
      34: iadd
      35: ifne          55
      38: aload_1
      39: invokeinterface #32,  1           // InterfaceMethod org/apache/hadoop/hbase/Cell.getTypeByte:()B
      44: getstatic     #33                 // Field org/apache/hadoop/hbase/KeyValue$Type.Minimum:Lorg/apache/hadoop/hbase/KeyValue$Type;
      47: invokevirtual #34                 // Method org/apache/hadoop/hbase/KeyValue$Type.getCode:()B
      50: if_icmpne     55
      53: iconst_1
      54: ireturn
      55: iload         4
      57: iload         6
      59: iadd
      60: ifne          80
      63: aload_2
      64: invokeinterface #32,  1           // InterfaceMethod org/apache/hadoop/hbase/Cell.getTypeByte:()B
      69: getstatic     #33                 // Field org/apache/hadoop/hbase/KeyValue$Type.Minimum:Lorg/apache/hadoop/hbase/KeyValue$Type;
      72: invokevirtual #34                 // Method org/apache/hadoop/hbase/KeyValue$Type.getCode:()B
      75: if_icmpne     80
      78: iconst_m1
      79: ireturn
      80: iload_3
      81: iload         4
      83: if_icmpeq     93
      86: aload_0
      87: aload_1
      88: aload_2
      89: invokevirtual #9                  // Method compareFamilies:(Lorg/apache/hadoop/hbase/Cell;Lorg/apache/hadoop/hbase/Cell;)I
      92: ireturn
      93: aload_0
      94: aload_1
      95: aload_2
      96: invokevirtual #35                 // Method compareColumns:(Lorg/apache/hadoop/hbase/Cell;Lorg/apache/hadoop/hbase/Cell;)I
      99: istore        7
     101: iload         7
     103: ifeq          109
     106: iload         7
     108: ireturn
     109: aload_0
     110: aload_1
     111: invokeinterface #36,  1           // InterfaceMethod org/apache/hadoop/hbase/Cell.getTimestamp:()J
     116: aload_2
     117: invokeinterface #36,  1           // InterfaceMethod org/apache/hadoop/hbase/Cell.getTimestamp:()J
     122: invokevirtual #37                 // Method compareTimestamps:(JJ)I
     125: istore        7
     127: iload         7
     129: ifeq          135
     132: iload         7
     134: ireturn
     135: sipush        255
     138: aload_2
     139: invokeinterface #32,  1           // InterfaceMethod org/apache/hadoop/hbase/Cell.getTypeByte:()B
     144: iand
     145: sipush        255
     148: aload_1
     149: invokeinterface #32,  1           // InterfaceMethod org/apache/hadoop/hbase/Cell.getTypeByte:()B
     154: iand
     155: isub
     156: ireturn

  public int compareTimestamps(org.apache.hadoop.hbase.Cell, org.apache.hadoop.hbase.Cell);
    Code:
       0: aload_0
       1: aload_1
       2: invokeinterface #36,  1           // InterfaceMethod org/apache/hadoop/hbase/Cell.getTimestamp:()J
       7: aload_2
       8: invokeinterface #36,  1           // InterfaceMethod org/apache/hadoop/hbase/Cell.getTimestamp:()J
      13: invokevirtual #37                 // Method compareTimestamps:(JJ)I
      16: ireturn

  public int compareTimestamps(long, long);
    Code:
       0: lload_3
       1: lload_1
       2: invokestatic  #8                  // Method java/lang/Long.compare:(JJ)I
       5: ireturn

  public java.util.Comparator getSimpleComparator();
    Code:
       0: new           #38                 // class org/apache/hadoop/hbase/BBKVComparator
       3: dup
       4: aload_0
       5: invokespecial #39                 // Method org/apache/hadoop/hbase/BBKVComparator."<init>":(Ljava/util/Comparator;)V
       8: areturn

  public int compare(java.lang.Object, java.lang.Object);
    Code:
       0: aload_0
       1: aload_1
       2: checkcast     #40                 // class org/apache/hadoop/hbase/Cell
       5: aload_2
       6: checkcast     #40                 // class org/apache/hadoop/hbase/Cell
       9: invokevirtual #41                 // Method compare:(Lorg/apache/hadoop/hbase/Cell;Lorg/apache/hadoop/hbase/Cell;)I
      12: ireturn

  static {};
    Code:
       0: ldc           #42                 // class org/apache/hadoop/hbase/CellComparatorImpl
       2: invokestatic  #43                 // Method org/slf4j/LoggerFactory.getLogger:(Ljava/lang/Class;)Lorg/slf4j/Logger;
       5: putstatic     #44                 // Field LOG:Lorg/slf4j/Logger;
       8: new           #42                 // class org/apache/hadoop/hbase/CellComparatorImpl
      11: dup
      12: invokespecial #45                 // Method "<init>":()V
      15: putstatic     #46                 // Field COMPARATOR:Lorg/apache/hadoop/hbase/CellComparatorImpl;
      18: new           #47                 // class org/apache/hadoop/hbase/CellComparatorImpl$MetaCellComparator
      21: dup
      22: invokespecial #48                 // Method org/apache/hadoop/hbase/CellComparatorImpl$MetaCellComparator."<init>":()V
      25: putstatic     #49                 // Field META_COMPARATOR:Lorg/apache/hadoop/hbase/CellComparatorImpl;
      28: return
}
