Compiled from "ChunkCreator.java"
class org.apache.hadoop.hbase.regionserver.ChunkCreator$MemStoreChunkPool implements org.apache.hadoop.hbase.regionserver.HeapMemoryManager$HeapMemoryTuneObserver {
  final org.apache.hadoop.hbase.regionserver.ChunkCreator this$0;

  org.apache.hadoop.hbase.regionserver.ChunkCreator$MemStoreChunkPool(org.apache.hadoop.hbase.regionserver.ChunkCreator, java.lang.String, int, int, int, float);
    Code:
       0: aload_0
       1: aload_1
       2: putfield      #8                  // Field this$0:Lorg/apache/hadoop/hbase/regionserver/ChunkCreator;
       5: aload_0
       6: invokespecial #9                  // Method java/lang/Object."<init>":()V
       9: aload_0
      10: new           #10                 // class java/util/concurrent/atomic/AtomicLong
      13: dup
      14: invokespecial #11                 // Method java/util/concurrent/atomic/AtomicLong."<init>":()V
      17: putfield      #6                  // Field chunkCount:Ljava/util/concurrent/atomic/AtomicLong;
      20: aload_0
      21: new           #12                 // class java/util/concurrent/atomic/LongAdder
      24: dup
      25: invokespecial #13                 // Method java/util/concurrent/atomic/LongAdder."<init>":()V
      28: putfield      #5                  // Field reusedChunkCount:Ljava/util/concurrent/atomic/LongAdder;
      31: aload_0
      32: aload_2
      33: putfield      #4                  // Field label:Ljava/lang/String;
      36: aload_0
      37: iload_3
      38: putfield      #3                  // Field chunkSize:I
      41: aload_0
      42: iload         4
      44: putfield      #14                 // Field maxCount:I
      47: aload_0
      48: fload         6
      50: putfield      #15                 // Field poolSizePercentage:F
      53: aload_0
      54: new           #16                 // class java/util/concurrent/LinkedBlockingQueue
      57: dup
      58: invokespecial #17                 // Method java/util/concurrent/LinkedBlockingQueue."<init>":()V
      61: putfield      #2                  // Field reclaimedChunks:Ljava/util/concurrent/BlockingQueue;
      64: iconst_0
      65: istore        7
      67: iload         7
      69: iload         5
      71: if_icmpge     108
      74: aload_1
      75: iconst_1
      76: getstatic     #18                 // Field org/apache/hadoop/hbase/regionserver/CompactingMemStore$IndexType.ARRAY_MAP:Lorg/apache/hadoop/hbase/regionserver/CompactingMemStore$IndexType;
      79: iload_3
      80: invokestatic  #19                 // Method org/apache/hadoop/hbase/regionserver/ChunkCreator.access$100:(Lorg/apache/hadoop/hbase/regionserver/ChunkCreator;ZLorg/apache/hadoop/hbase/regionserver/CompactingMemStore$IndexType;I)Lorg/apache/hadoop/hbase/regionserver/Chunk;
      83: astore        8
      85: aload         8
      87: invokevirtual #20                 // Method org/apache/hadoop/hbase/regionserver/Chunk.init:()V
      90: aload_0
      91: getfield      #2                  // Field reclaimedChunks:Ljava/util/concurrent/BlockingQueue;
      94: aload         8
      96: invokeinterface #21,  2           // InterfaceMethod java/util/concurrent/BlockingQueue.add:(Ljava/lang/Object;)Z
     101: pop
     102: iinc          7, 1
     105: goto          67
     108: aload_0
     109: getfield      #6                  // Field chunkCount:Ljava/util/concurrent/atomic/AtomicLong;
     112: iload         5
     114: i2l
     115: invokevirtual #22                 // Method java/util/concurrent/atomic/AtomicLong.set:(J)V
     118: invokestatic  #23                 // Method java/lang/Thread.currentThread:()Ljava/lang/Thread;
     121: invokevirtual #24                 // Method java/lang/Thread.getName:()Ljava/lang/String;
     124: astore        7
     126: aload_0
     127: iconst_1
     128: new           #25                 // class org/apache/hbase/thirdparty/com/google/common/util/concurrent/ThreadFactoryBuilder
     131: dup
     132: invokespecial #26                 // Method org/apache/hbase/thirdparty/com/google/common/util/concurrent/ThreadFactoryBuilder."<init>":()V
     135: new           #27                 // class java/lang/StringBuilder
     138: dup
     139: invokespecial #28                 // Method java/lang/StringBuilder."<init>":()V
     142: aload         7
     144: invokevirtual #29                 // Method java/lang/StringBuilder.append:(Ljava/lang/String;)Ljava/lang/StringBuilder;
     147: ldc           #30                 // String -MemStoreChunkPool Statistics
     149: invokevirtual #29                 // Method java/lang/StringBuilder.append:(Ljava/lang/String;)Ljava/lang/StringBuilder;
     152: invokevirtual #31                 // Method java/lang/StringBuilder.toString:()Ljava/lang/String;
     155: invokevirtual #32                 // Method org/apache/hbase/thirdparty/com/google/common/util/concurrent/ThreadFactoryBuilder.setNameFormat:(Ljava/lang/String;)Lorg/apache/hbase/thirdparty/com/google/common/util/concurrent/ThreadFactoryBuilder;
     158: iconst_1
     159: invokevirtual #33                 // Method org/apache/hbase/thirdparty/com/google/common/util/concurrent/ThreadFactoryBuilder.setDaemon:(Z)Lorg/apache/hbase/thirdparty/com/google/common/util/concurrent/ThreadFactoryBuilder;
     162: invokevirtual #34                 // Method org/apache/hbase/thirdparty/com/google/common/util/concurrent/ThreadFactoryBuilder.build:()Ljava/util/concurrent/ThreadFactory;
     165: invokestatic  #35                 // Method java/util/concurrent/Executors.newScheduledThreadPool:(ILjava/util/concurrent/ThreadFactory;)Ljava/util/concurrent/ScheduledExecutorService;
     168: putfield      #36                 // Field scheduleThreadPool:Ljava/util/concurrent/ScheduledExecutorService;
     171: aload_0
     172: getfield      #36                 // Field scheduleThreadPool:Ljava/util/concurrent/ScheduledExecutorService;
     175: new           #37                 // class org/apache/hadoop/hbase/regionserver/ChunkCreator$MemStoreChunkPool$StatisticsThread
     178: dup
     179: aload_0
     180: invokespecial #38                 // Method org/apache/hadoop/hbase/regionserver/ChunkCreator$MemStoreChunkPool$StatisticsThread."<init>":(Lorg/apache/hadoop/hbase/regionserver/ChunkCreator$MemStoreChunkPool;)V
     183: ldc2_w        #40                 // long 300l
     186: ldc2_w        #40                 // long 300l
     189: getstatic     #42                 // Field java/util/concurrent/TimeUnit.SECONDS:Ljava/util/concurrent/TimeUnit;
     192: invokeinterface #43,  7           // InterfaceMethod java/util/concurrent/ScheduledExecutorService.scheduleAtFixedRate:(Ljava/lang/Runnable;JJLjava/util/concurrent/TimeUnit;)Ljava/util/concurrent/ScheduledFuture;
     197: pop
     198: return

  org.apache.hadoop.hbase.regionserver.Chunk getChunk();
    Code:
       0: aload_0
       1: getstatic     #18                 // Field org/apache/hadoop/hbase/regionserver/CompactingMemStore$IndexType.ARRAY_MAP:Lorg/apache/hadoop/hbase/regionserver/CompactingMemStore$IndexType;
       4: invokevirtual #44                 // Method getChunk:(Lorg/apache/hadoop/hbase/regionserver/CompactingMemStore$IndexType;)Lorg/apache/hadoop/hbase/regionserver/Chunk;
       7: areturn

  org.apache.hadoop.hbase.regionserver.Chunk getChunk(org.apache.hadoop.hbase.regionserver.CompactingMemStore$IndexType);
    Code:
       0: aload_0
       1: getfield      #2                  // Field reclaimedChunks:Ljava/util/concurrent/BlockingQueue;
       4: invokeinterface #45,  1           // InterfaceMethod java/util/concurrent/BlockingQueue.poll:()Ljava/lang/Object;
       9: checkcast     #46                 // class org/apache/hadoop/hbase/regionserver/Chunk
      12: astore_2
      13: aload_2
      14: ifnull        31
      17: aload_2
      18: invokevirtual #47                 // Method org/apache/hadoop/hbase/regionserver/Chunk.reset:()V
      21: aload_0
      22: getfield      #5                  // Field reusedChunkCount:Ljava/util/concurrent/atomic/LongAdder;
      25: invokevirtual #48                 // Method java/util/concurrent/atomic/LongAdder.increment:()V
      28: goto          82
      31: aload_0
      32: getfield      #6                  // Field chunkCount:Ljava/util/concurrent/atomic/AtomicLong;
      35: invokevirtual #49                 // Method java/util/concurrent/atomic/AtomicLong.get:()J
      38: lstore_3
      39: lload_3
      40: aload_0
      41: getfield      #14                 // Field maxCount:I
      44: i2l
      45: lcmp
      46: ifge          82
      49: aload_0
      50: getfield      #6                  // Field chunkCount:Ljava/util/concurrent/atomic/AtomicLong;
      53: lload_3
      54: lload_3
      55: lconst_1
      56: ladd
      57: invokevirtual #50                 // Method java/util/concurrent/atomic/AtomicLong.compareAndSet:(JJ)Z
      60: ifeq          79
      63: aload_0
      64: getfield      #8                  // Field this$0:Lorg/apache/hadoop/hbase/regionserver/ChunkCreator;
      67: aload_1
      68: aload_0
      69: getfield      #3                  // Field chunkSize:I
      72: invokestatic  #51                 // Method org/apache/hadoop/hbase/regionserver/ChunkCreator.access$200:(Lorg/apache/hadoop/hbase/regionserver/ChunkCreator;Lorg/apache/hadoop/hbase/regionserver/CompactingMemStore$IndexType;I)Lorg/apache/hadoop/hbase/regionserver/Chunk;
      75: astore_2
      76: goto          82
      79: goto          31
      82: aload_2
      83: areturn

  int getChunkSize();
    Code:
       0: aload_0
       1: getfield      #3                  // Field chunkSize:I
       4: ireturn

  public void onHeapMemoryTune(long, long);
    Code:
       0: aload_0
       1: getfield      #8                  // Field this$0:Lorg/apache/hadoop/hbase/regionserver/ChunkCreator;
       4: invokevirtual #57                 // Method org/apache/hadoop/hbase/regionserver/ChunkCreator.isOffheap:()Z
       7: ifeq          25
      10: invokestatic  #58                 // Method org/apache/hadoop/hbase/regionserver/ChunkCreator.access$300:()Lorg/slf4j/Logger;
      13: ldc           #59                 // String {} not tuning the chunk pool as it is offheap
      15: aload_0
      16: getfield      #4                  // Field label:Ljava/lang/String;
      19: invokeinterface #60,  3           // InterfaceMethod org/slf4j/Logger.warn:(Ljava/lang/String;Ljava/lang/Object;)V
      24: return
      25: lload_1
      26: l2f
      27: aload_0
      28: getfield      #15                 // Field poolSizePercentage:F
      31: fmul
      32: aload_0
      33: invokevirtual #61                 // Method getChunkSize:()I
      36: i2f
      37: fdiv
      38: f2i
      39: istore        5
      41: iload         5
      43: aload_0
      44: getfield      #14                 // Field maxCount:I
      47: if_icmpeq     212
      50: iload         5
      52: aload_0
      53: getfield      #14                 // Field maxCount:I
      56: if_icmple     107
      59: invokestatic  #58                 // Method org/apache/hadoop/hbase/regionserver/ChunkCreator.access$300:()Lorg/slf4j/Logger;
      62: ldc           #62                 // String {} max count for chunks increased from {} to {}
      64: iconst_3
      65: anewarray     #63                 // class java/lang/Object
      68: dup
      69: iconst_0
      70: aload_0
      71: getfield      #4                  // Field label:Ljava/lang/String;
      74: aastore
      75: dup
      76: iconst_1
      77: aload_0
      78: getfield      #14                 // Field maxCount:I
      81: invokestatic  #64                 // Method java/lang/Integer.valueOf:(I)Ljava/lang/Integer;
      84: aastore
      85: dup
      86: iconst_2
      87: iload         5
      89: invokestatic  #64                 // Method java/lang/Integer.valueOf:(I)Ljava/lang/Integer;
      92: aastore
      93: invokeinterface #65,  3           // InterfaceMethod org/slf4j/Logger.info:(Ljava/lang/String;[Ljava/lang/Object;)V
      98: aload_0
      99: iload         5
     101: putfield      #14                 // Field maxCount:I
     104: goto          212
     107: invokestatic  #58                 // Method org/apache/hadoop/hbase/regionserver/ChunkCreator.access$300:()Lorg/slf4j/Logger;
     110: ldc           #66                 // String {} max count for chunks decreased from {} to {}
     112: iconst_3
     113: anewarray     #63                 // class java/lang/Object
     116: dup
     117: iconst_0
     118: aload_0
     119: getfield      #4                  // Field label:Ljava/lang/String;
     122: aastore
     123: dup
     124: iconst_1
     125: aload_0
     126: getfield      #14                 // Field maxCount:I
     129: invokestatic  #64                 // Method java/lang/Integer.valueOf:(I)Ljava/lang/Integer;
     132: aastore
     133: dup
     134: iconst_2
     135: iload         5
     137: invokestatic  #64                 // Method java/lang/Integer.valueOf:(I)Ljava/lang/Integer;
     140: aastore
     141: invokeinterface #65,  3           // InterfaceMethod org/slf4j/Logger.info:(Ljava/lang/String;[Ljava/lang/Object;)V
     146: aload_0
     147: iload         5
     149: putfield      #14                 // Field maxCount:I
     152: aload_0
     153: getfield      #2                  // Field reclaimedChunks:Ljava/util/concurrent/BlockingQueue;
     156: invokeinterface #52,  1           // InterfaceMethod java/util/concurrent/BlockingQueue.size:()I
     161: iload         5
     163: if_icmple     212
     166: aload_0
     167: dup
     168: astore        6
     170: monitorenter
     171: aload_0
     172: getfield      #2                  // Field reclaimedChunks:Ljava/util/concurrent/BlockingQueue;
     175: invokeinterface #52,  1           // InterfaceMethod java/util/concurrent/BlockingQueue.size:()I
     180: iload         5
     182: if_icmple     198
     185: aload_0
     186: getfield      #2                  // Field reclaimedChunks:Ljava/util/concurrent/BlockingQueue;
     189: invokeinterface #45,  1           // InterfaceMethod java/util/concurrent/BlockingQueue.poll:()Ljava/lang/Object;
     194: pop
     195: goto          171
     198: aload         6
     200: monitorexit
     201: goto          212
     204: astore        7
     206: aload         6
     208: monitorexit
     209: aload         7
     211: athrow
     212: return
    Exception table:
       from    to  target type
         171   201   204   any
         204   209   204   any

  static int access$000(org.apache.hadoop.hbase.regionserver.ChunkCreator$MemStoreChunkPool);
    Code:
       0: aload_0
       1: invokespecial #7                  // Method getMaxCount:()I
       4: ireturn

  static java.util.concurrent.atomic.AtomicLong access$400(org.apache.hadoop.hbase.regionserver.ChunkCreator$MemStoreChunkPool);
    Code:
       0: aload_0
       1: getfield      #6                  // Field chunkCount:Ljava/util/concurrent/atomic/AtomicLong;
       4: areturn

  static java.util.concurrent.atomic.LongAdder access$500(org.apache.hadoop.hbase.regionserver.ChunkCreator$MemStoreChunkPool);
    Code:
       0: aload_0
       1: getfield      #5                  // Field reusedChunkCount:Ljava/util/concurrent/atomic/LongAdder;
       4: areturn

  static java.lang.String access$600(org.apache.hadoop.hbase.regionserver.ChunkCreator$MemStoreChunkPool);
    Code:
       0: aload_0
       1: getfield      #4                  // Field label:Ljava/lang/String;
       4: areturn

  static int access$700(org.apache.hadoop.hbase.regionserver.ChunkCreator$MemStoreChunkPool);
    Code:
       0: aload_0
       1: getfield      #3                  // Field chunkSize:I
       4: ireturn

  static java.util.concurrent.BlockingQueue access$800(org.apache.hadoop.hbase.regionserver.ChunkCreator$MemStoreChunkPool);
    Code:
       0: aload_0
       1: getfield      #2                  // Field reclaimedChunks:Ljava/util/concurrent/BlockingQueue;
       4: areturn

  static void access$900(org.apache.hadoop.hbase.regionserver.ChunkCreator$MemStoreChunkPool, org.apache.hadoop.hbase.regionserver.Chunk);
    Code:
       0: aload_0
       1: aload_1
       2: invokespecial #1                  // Method putbackChunks:(Lorg/apache/hadoop/hbase/regionserver/Chunk;)V
       5: return
}
