Compiled from "ClassFinder.java"
public class org.apache.hadoop.hbase.ClassFinder {
  public org.apache.hadoop.hbase.ClassFinder();
    Code:
       0: aload_0
       1: aconst_null
       2: aconst_null
       3: aconst_null
       4: invokespecial #2                  // Method "<init>":(Lorg/apache/hadoop/hbase/ClassFinder$ResourcePathFilter;Lorg/apache/hadoop/hbase/ClassFinder$FileNameFilter;Lorg/apache/hadoop/hbase/ClassFinder$ClassFilter;)V
       7: return

  public org.apache.hadoop.hbase.ClassFinder(org.apache.hadoop.hbase.ClassFinder$ResourcePathFilter, org.apache.hadoop.hbase.ClassFinder$FileNameFilter, org.apache.hadoop.hbase.ClassFinder$ClassFilter);
    Code:
       0: aload_0
       1: invokespecial #3                  // Method java/lang/Object."<init>":()V
       4: aload_0
       5: aload_1
       6: putfield      #4                  // Field resourcePathFilter:Lorg/apache/hadoop/hbase/ClassFinder$ResourcePathFilter;
       9: aload_0
      10: aload_3
      11: putfield      #5                  // Field classFilter:Lorg/apache/hadoop/hbase/ClassFinder$ClassFilter;
      14: aload_0
      15: aload_2
      16: putfield      #6                  // Field fileNameFilter:Lorg/apache/hadoop/hbase/ClassFinder$FileNameFilter;
      19: aload_0
      20: new           #7                  // class org/apache/hadoop/hbase/ClassFinder$FileFilterWithName
      23: dup
      24: aload_2
      25: invokespecial #8                  // Method org/apache/hadoop/hbase/ClassFinder$FileFilterWithName."<init>":(Lorg/apache/hadoop/hbase/ClassFinder$FileNameFilter;)V
      28: putfield      #9                  // Field fileFilter:Ljava/io/FileFilter;
      31: return

  public java.util.Set<java.lang.Class<?>> findClasses(boolean) throws java.lang.ClassNotFoundException, java.io.IOException, java.lang.LinkageError;
    Code:
       0: aload_0
       1: aload_0
       2: invokevirtual #10                 // Method java/lang/Object.getClass:()Ljava/lang/Class;
       5: invokevirtual #11                 // Method java/lang/Class.getPackage:()Ljava/lang/Package;
       8: invokevirtual #12                 // Method java/lang/Package.getName:()Ljava/lang/String;
      11: iload_1
      12: invokevirtual #13                 // Method findClasses:(Ljava/lang/String;Z)Ljava/util/Set;
      15: areturn

  public java.util.Set<java.lang.Class<?>> findClasses(java.lang.String, boolean) throws java.lang.ClassNotFoundException, java.io.IOException, java.lang.LinkageError;
    Code:
       0: aload_1
       1: bipush        46
       3: bipush        47
       5: invokevirtual #14                 // Method java/lang/String.replace:(CC)Ljava/lang/String;
       8: astore_3
       9: new           #15                 // class java/lang/StringBuilder
      12: dup
      13: invokespecial #16                 // Method java/lang/StringBuilder."<init>":()V
      16: ldc           #17                 // String ^file:(.+\.jar)!/
      18: invokevirtual #18                 // Method java/lang/StringBuilder.append:(Ljava/lang/String;)Ljava/lang/StringBuilder;
      21: aload_3
      22: invokevirtual #18                 // Method java/lang/StringBuilder.append:(Ljava/lang/String;)Ljava/lang/StringBuilder;
      25: ldc           #19                 // String $
      27: invokevirtual #18                 // Method java/lang/StringBuilder.append:(Ljava/lang/String;)Ljava/lang/StringBuilder;
      30: invokevirtual #20                 // Method java/lang/StringBuilder.toString:()Ljava/lang/String;
      33: invokestatic  #21                 // Method java/util/regex/Pattern.compile:(Ljava/lang/String;)Ljava/util/regex/Pattern;
      36: astore        4
      38: invokestatic  #22                 // Method java/lang/ClassLoader.getSystemClassLoader:()Ljava/lang/ClassLoader;
      41: aload_3
      42: invokevirtual #23                 // Method java/lang/ClassLoader.getResources:(Ljava/lang/String;)Ljava/util/Enumeration;
      45: astore        5
      47: new           #24                 // class java/util/ArrayList
      50: dup
      51: invokespecial #25                 // Method java/util/ArrayList."<init>":()V
      54: astore        6
      56: new           #24                 // class java/util/ArrayList
      59: dup
      60: invokespecial #25                 // Method java/util/ArrayList."<init>":()V
      63: astore        7
      65: aload         5
      67: invokeinterface #26,  1           // InterfaceMethod java/util/Enumeration.hasMoreElements:()Z
      72: ifeq          228
      75: aload         5
      77: invokeinterface #27,  1           // InterfaceMethod java/util/Enumeration.nextElement:()Ljava/lang/Object;
      82: checkcast     #28                 // class java/net/URL
      85: astore        8
      87: aload         8
      89: invokevirtual #29                 // Method java/net/URL.getFile:()Ljava/lang/String;
      92: astore        9
      94: aload         4
      96: aload         9
      98: invokevirtual #30                 // Method java/util/regex/Pattern.matcher:(Ljava/lang/CharSequence;)Ljava/util/regex/Matcher;
     101: astore        10
     103: aload         10
     105: invokevirtual #31                 // Method java/util/regex/Matcher.find:()Z
     108: istore        11
     110: iload         11
     112: ifeq          124
     115: aload         10
     117: iconst_1
     118: invokevirtual #32                 // Method java/util/regex/Matcher.group:(I)Ljava/lang/String;
     121: goto          126
     124: aload         9
     126: astore        9
     128: aconst_null
     129: aload_0
     130: getfield      #4                  // Field resourcePathFilter:Lorg/apache/hadoop/hbase/ClassFinder$ResourcePathFilter;
     133: if_acmpeq     152
     136: aload_0
     137: getfield      #4                  // Field resourcePathFilter:Lorg/apache/hadoop/hbase/ClassFinder$ResourcePathFilter;
     140: aload         9
     142: iload         11
     144: invokeinterface #33,  3           // InterfaceMethod org/apache/hadoop/hbase/ClassFinder$ResourcePathFilter.isCandidatePath:(Ljava/lang/String;Z)Z
     149: ifeq          225
     152: getstatic     #34                 // Field LOG:Lorg/slf4j/Logger;
     155: new           #15                 // class java/lang/StringBuilder
     158: dup
     159: invokespecial #16                 // Method java/lang/StringBuilder."<init>":()V
     162: ldc           #35                 // String Looking in
     164: invokevirtual #18                 // Method java/lang/StringBuilder.append:(Ljava/lang/String;)Ljava/lang/StringBuilder;
     167: aload         9
     169: invokevirtual #18                 // Method java/lang/StringBuilder.append:(Ljava/lang/String;)Ljava/lang/StringBuilder;
     172: ldc           #36                 // String ; isJar=
     174: invokevirtual #18                 // Method java/lang/StringBuilder.append:(Ljava/lang/String;)Ljava/lang/StringBuilder;
     177: iload         11
     179: invokevirtual #37                 // Method java/lang/StringBuilder.append:(Z)Ljava/lang/StringBuilder;
     182: invokevirtual #20                 // Method java/lang/StringBuilder.toString:()Ljava/lang/String;
     185: invokeinterface #38,  2           // InterfaceMethod org/slf4j/Logger.debug:(Ljava/lang/String;)V
     190: iload         11
     192: ifeq          208
     195: aload         7
     197: aload         9
     199: invokeinterface #39,  2           // InterfaceMethod java/util/List.add:(Ljava/lang/Object;)Z
     204: pop
     205: goto          225
     208: aload         6
     210: new           #40                 // class java/io/File
     213: dup
     214: aload         9
     216: invokespecial #41                 // Method java/io/File."<init>":(Ljava/lang/String;)V
     219: invokeinterface #39,  2           // InterfaceMethod java/util/List.add:(Ljava/lang/Object;)Z
     224: pop
     225: goto          65
     228: new           #42                 // class java/util/HashSet
     231: dup
     232: invokespecial #43                 // Method java/util/HashSet."<init>":()V
     235: astore        8
     237: aload         6
     239: invokeinterface #44,  1           // InterfaceMethod java/util/List.iterator:()Ljava/util/Iterator;
     244: astore        9
     246: aload         9
     248: invokeinterface #45,  1           // InterfaceMethod java/util/Iterator.hasNext:()Z
     253: ifeq          287
     256: aload         9
     258: invokeinterface #46,  1           // InterfaceMethod java/util/Iterator.next:()Ljava/lang/Object;
     263: checkcast     #40                 // class java/io/File
     266: astore        10
     268: aload         8
     270: aload_0
     271: aload         10
     273: aload_1
     274: iload_2
     275: invokespecial #47                 // Method findClassesFromFiles:(Ljava/io/File;Ljava/lang/String;Z)Ljava/util/Set;
     278: invokeinterface #48,  2           // InterfaceMethod java/util/Set.addAll:(Ljava/util/Collection;)Z
     283: pop
     284: goto          246
     287: aload         7
     289: invokeinterface #44,  1           // InterfaceMethod java/util/List.iterator:()Ljava/util/Iterator;
     294: astore        9
     296: aload         9
     298: invokeinterface #45,  1           // InterfaceMethod java/util/Iterator.hasNext:()Z
     303: ifeq          337
     306: aload         9
     308: invokeinterface #46,  1           // InterfaceMethod java/util/Iterator.next:()Ljava/lang/Object;
     313: checkcast     #49                 // class java/lang/String
     316: astore        10
     318: aload         8
     320: aload_0
     321: aload         10
     323: aload_1
     324: iload_2
     325: invokespecial #50                 // Method findClassesFromJar:(Ljava/lang/String;Ljava/lang/String;Z)Ljava/util/Set;
     328: invokeinterface #48,  2           // InterfaceMethod java/util/Set.addAll:(Ljava/util/Collection;)Z
     333: pop
     334: goto          296
     337: aload         8
     339: areturn

  static java.lang.String access$000();
    Code:
       0: getstatic     #1                  // Field CLASS_EXT:Ljava/lang/String;
       3: areturn

  static {};
    Code:
       0: ldc           #90                 // class org/apache/hadoop/hbase/ClassFinder
       2: invokestatic  #91                 // Method org/slf4j/LoggerFactory.getLogger:(Ljava/lang/Class;)Lorg/slf4j/Logger;
       5: putstatic     #34                 // Field LOG:Lorg/slf4j/Logger;
       8: ldc           #92                 // String .class
      10: putstatic     #1                  // Field CLASS_EXT:Ljava/lang/String;
      13: return
}
