Compiled from "ClassLoaderTestHelper.java"
public class org.apache.hadoop.hbase.util.ClassLoaderTestHelper {
  public org.apache.hadoop.hbase.util.ClassLoaderTestHelper();
    Code:
       0: aload_0
       1: invokespecial #1                  // Method java/lang/Object."<init>":()V
       4: return

  public static java.io.File buildJar(java.lang.String, java.lang.String, java.lang.String) throws java.lang.Exception;
    Code:
       0: aload_0
       1: aload_1
       2: aload_2
       3: aload_0
       4: invokestatic  #35                 // Method buildJar:(Ljava/lang/String;Ljava/lang/String;Ljava/lang/String;Ljava/lang/String;)Ljava/io/File;
       7: areturn

  public static java.io.File buildJar(java.lang.String, java.lang.String, java.lang.String, java.lang.String) throws java.lang.Exception;
    Code:
       0: aload_2
       1: ifnull        8
       4: aload_2
       5: goto          32
       8: new           #28                 // class java/lang/StringBuilder
      11: dup
      12: invokespecial #29                 // Method java/lang/StringBuilder."<init>":()V
      15: ldc           #36                 // String public class
      17: invokevirtual #31                 // Method java/lang/StringBuilder.append:(Ljava/lang/String;)Ljava/lang/StringBuilder;
      20: aload_1
      21: invokevirtual #31                 // Method java/lang/StringBuilder.append:(Ljava/lang/String;)Ljava/lang/StringBuilder;
      24: ldc           #37                 // String  {}
      26: invokevirtual #31                 // Method java/lang/StringBuilder.append:(Ljava/lang/String;)Ljava/lang/StringBuilder;
      29: invokevirtual #33                 // Method java/lang/StringBuilder.toString:()Ljava/lang/String;
      32: astore        4
      34: new           #38                 // class org/apache/hadoop/fs/Path
      37: dup
      38: aload_0
      39: ldc           #39                 // String src
      41: invokespecial #40                 // Method org/apache/hadoop/fs/Path."<init>":(Ljava/lang/String;Ljava/lang/String;)V
      44: astore        5
      46: new           #41                 // class java/io/File
      49: dup
      50: aload         5
      52: invokevirtual #42                 // Method org/apache/hadoop/fs/Path.toString:()Ljava/lang/String;
      55: invokespecial #43                 // Method java/io/File."<init>":(Ljava/lang/String;)V
      58: astore        6
      60: aload         6
      62: invokevirtual #44                 // Method java/io/File.mkdirs:()Z
      65: pop
      66: new           #41                 // class java/io/File
      69: dup
      70: aload         5
      72: invokevirtual #42                 // Method org/apache/hadoop/fs/Path.toString:()Ljava/lang/String;
      75: new           #28                 // class java/lang/StringBuilder
      78: dup
      79: invokespecial #29                 // Method java/lang/StringBuilder."<init>":()V
      82: aload_1
      83: invokevirtual #31                 // Method java/lang/StringBuilder.append:(Ljava/lang/String;)Ljava/lang/StringBuilder;
      86: ldc           #45                 // String .java
      88: invokevirtual #31                 // Method java/lang/StringBuilder.append:(Ljava/lang/String;)Ljava/lang/StringBuilder;
      91: invokevirtual #33                 // Method java/lang/StringBuilder.toString:()Ljava/lang/String;
      94: invokespecial #46                 // Method java/io/File."<init>":(Ljava/lang/String;Ljava/lang/String;)V
      97: astore        7
      99: aload         7
     101: invokevirtual #47                 // Method java/io/File.toPath:()Ljava/nio/file/Path;
     104: getstatic     #48                 // Field java/nio/charset/StandardCharsets.UTF_8:Ljava/nio/charset/Charset;
     107: iconst_0
     108: anewarray     #49                 // class java/nio/file/OpenOption
     111: invokestatic  #50                 // Method java/nio/file/Files.newBufferedWriter:(Ljava/nio/file/Path;Ljava/nio/charset/Charset;[Ljava/nio/file/OpenOption;)Ljava/io/BufferedWriter;
     114: astore        8
     116: aload         8
     118: aload         4
     120: invokevirtual #51                 // Method java/io/BufferedWriter.write:(Ljava/lang/String;)V
     123: aload         8
     125: invokevirtual #52                 // Method java/io/BufferedWriter.close:()V
     128: invokestatic  #53                 // Method javax/tools/ToolProvider.getSystemJavaCompiler:()Ljavax/tools/JavaCompiler;
     131: astore        9
     133: new           #54                 // class java/util/ArrayList
     136: dup
     137: iconst_1
     138: invokespecial #55                 // Method java/util/ArrayList."<init>":(I)V
     141: astore        10
     143: aload         10
     145: aload         7
     147: invokevirtual #56                 // Method java/io/File.toString:()Ljava/lang/String;
     150: invokevirtual #57                 // Method java/util/ArrayList.add:(Ljava/lang/Object;)Z
     153: pop
     154: aload         9
     156: aconst_null
     157: aconst_null
     158: aconst_null
     159: invokeinterface #58,  4           // InterfaceMethod javax/tools/JavaCompiler.getStandardFileManager:(Ljavax/tools/DiagnosticListener;Ljava/util/Locale;Ljava/nio/charset/Charset;)Ljavax/tools/StandardJavaFileManager;
     164: astore        11
     166: aload         11
     168: iconst_1
     169: anewarray     #41                 // class java/io/File
     172: dup
     173: iconst_0
     174: aload         7
     176: aastore
     177: invokeinterface #59,  2           // InterfaceMethod javax/tools/StandardJavaFileManager.getJavaFileObjects:([Ljava/io/File;)Ljava/lang/Iterable;
     182: astore        12
     184: new           #54                 // class java/util/ArrayList
     187: dup
     188: iconst_2
     189: invokespecial #55                 // Method java/util/ArrayList."<init>":(I)V
     192: astore        13
     194: aload         13
     196: ldc           #60                 // String -classpath
     198: invokeinterface #61,  2           // InterfaceMethod java/util/List.add:(Ljava/lang/Object;)Z
     203: pop
     204: new           #41                 // class java/io/File
     207: dup
     208: ldc           #62                 // String .
     210: invokespecial #43                 // Method java/io/File."<init>":(Ljava/lang/String;)V
     213: invokevirtual #63                 // Method java/io/File.getAbsolutePath:()Ljava/lang/String;
     216: astore        14
     218: new           #28                 // class java/lang/StringBuilder
     221: dup
     222: invokespecial #29                 // Method java/lang/StringBuilder."<init>":()V
     225: aload         14
     227: invokevirtual #31                 // Method java/lang/StringBuilder.append:(Ljava/lang/String;)Ljava/lang/StringBuilder;
     230: getstatic     #64                 // Field java/io/File.separator:Ljava/lang/String;
     233: invokevirtual #31                 // Method java/lang/StringBuilder.append:(Ljava/lang/String;)Ljava/lang/StringBuilder;
     236: ldc           #65                 // String target
     238: invokevirtual #31                 // Method java/lang/StringBuilder.append:(Ljava/lang/String;)Ljava/lang/StringBuilder;
     241: getstatic     #64                 // Field java/io/File.separator:Ljava/lang/String;
     244: invokevirtual #31                 // Method java/lang/StringBuilder.append:(Ljava/lang/String;)Ljava/lang/StringBuilder;
     247: ldc           #66                 // String classes
     249: invokevirtual #31                 // Method java/lang/StringBuilder.append:(Ljava/lang/String;)Ljava/lang/StringBuilder;
     252: ldc           #67                 // String path.separator
     254: invokestatic  #68                 // Method java/lang/System.getProperty:(Ljava/lang/String;)Ljava/lang/String;
     257: invokevirtual #31                 // Method java/lang/StringBuilder.append:(Ljava/lang/String;)Ljava/lang/StringBuilder;
     260: ldc           #69                 // String java.class.path
     262: invokestatic  #68                 // Method java/lang/System.getProperty:(Ljava/lang/String;)Ljava/lang/String;
     265: invokevirtual #31                 // Method java/lang/StringBuilder.append:(Ljava/lang/String;)Ljava/lang/StringBuilder;
     268: ldc           #67                 // String path.separator
     270: invokestatic  #68                 // Method java/lang/System.getProperty:(Ljava/lang/String;)Ljava/lang/String;
     273: invokevirtual #31                 // Method java/lang/StringBuilder.append:(Ljava/lang/String;)Ljava/lang/StringBuilder;
     276: ldc           #70                 // String surefire.test.class.path
     278: invokestatic  #68                 // Method java/lang/System.getProperty:(Ljava/lang/String;)Ljava/lang/String;
     281: invokevirtual #31                 // Method java/lang/StringBuilder.append:(Ljava/lang/String;)Ljava/lang/StringBuilder;
     284: invokevirtual #33                 // Method java/lang/StringBuilder.toString:()Ljava/lang/String;
     287: astore        15
     289: aload         13
     291: aload         15
     293: invokeinterface #61,  2           // InterfaceMethod java/util/List.add:(Ljava/lang/Object;)Z
     298: pop
     299: getstatic     #24                 // Field LOG:Lorg/slf4j/Logger;
     302: new           #28                 // class java/lang/StringBuilder
     305: dup
     306: invokespecial #29                 // Method java/lang/StringBuilder."<init>":()V
     309: ldc           #71                 // String Setting classpath to:
     311: invokevirtual #31                 // Method java/lang/StringBuilder.append:(Ljava/lang/String;)Ljava/lang/StringBuilder;
     314: aload         15
     316: invokevirtual #31                 // Method java/lang/StringBuilder.append:(Ljava/lang/String;)Ljava/lang/StringBuilder;
     319: invokevirtual #33                 // Method java/lang/StringBuilder.toString:()Ljava/lang/String;
     322: invokeinterface #72,  2           // InterfaceMethod org/slf4j/Logger.debug:(Ljava/lang/String;)V
     327: aload         9
     329: aconst_null
     330: aload         11
     332: aconst_null
     333: aload         13
     335: aconst_null
     336: aload         12
     338: invokeinterface #73,  7           // InterfaceMethod javax/tools/JavaCompiler.getTask:(Ljava/io/Writer;Ljavax/tools/JavaFileManager;Ljavax/tools/DiagnosticListener;Ljava/lang/Iterable;Ljava/lang/Iterable;Ljava/lang/Iterable;)Ljavax/tools/JavaCompiler$CompilationTask;
     343: astore        16
     345: new           #28                 // class java/lang/StringBuilder
     348: dup
     349: invokespecial #29                 // Method java/lang/StringBuilder."<init>":()V
     352: ldc           #74                 // String Compile file
     354: invokevirtual #31                 // Method java/lang/StringBuilder.append:(Ljava/lang/String;)Ljava/lang/StringBuilder;
     357: aload         7
     359: invokevirtual #75                 // Method java/lang/StringBuilder.append:(Ljava/lang/Object;)Ljava/lang/StringBuilder;
     362: ldc           #76                 // String  failed.
     364: invokevirtual #31                 // Method java/lang/StringBuilder.append:(Ljava/lang/String;)Ljava/lang/StringBuilder;
     367: invokevirtual #33                 // Method java/lang/StringBuilder.toString:()Ljava/lang/String;
     370: aload         16
     372: invokeinterface #77,  1           // InterfaceMethod javax/tools/JavaCompiler$CompilationTask.call:()Ljava/lang/Boolean;
     377: invokevirtual #78                 // Method java/lang/Boolean.booleanValue:()Z
     380: invokestatic  #79                 // Method org/junit/Assert.assertTrue:(Ljava/lang/String;Z)V
     383: new           #28                 // class java/lang/StringBuilder
     386: dup
     387: invokespecial #29                 // Method java/lang/StringBuilder."<init>":()V
     390: aload_1
     391: invokevirtual #31                 // Method java/lang/StringBuilder.append:(Ljava/lang/String;)Ljava/lang/StringBuilder;
     394: ldc           #80                 // String .jar
     396: invokevirtual #31                 // Method java/lang/StringBuilder.append:(Ljava/lang/String;)Ljava/lang/StringBuilder;
     399: invokevirtual #33                 // Method java/lang/StringBuilder.toString:()Ljava/lang/String;
     402: astore        17
     404: new           #41                 // class java/io/File
     407: dup
     408: aload_3
     409: aload         17
     411: invokespecial #46                 // Method java/io/File."<init>":(Ljava/lang/String;Ljava/lang/String;)V
     414: astore        18
     416: aload         18
     418: invokevirtual #81                 // Method java/io/File.getParentFile:()Ljava/io/File;
     421: invokevirtual #44                 // Method java/io/File.mkdirs:()Z
     424: pop
     425: aload         18
     427: iconst_1
     428: anewarray     #41                 // class java/io/File
     431: dup
     432: iconst_0
     433: new           #41                 // class java/io/File
     436: dup
     437: aload         5
     439: invokevirtual #42                 // Method org/apache/hadoop/fs/Path.toString:()Ljava/lang/String;
     442: new           #28                 // class java/lang/StringBuilder
     445: dup
     446: invokespecial #29                 // Method java/lang/StringBuilder."<init>":()V
     449: aload_1
     450: invokevirtual #31                 // Method java/lang/StringBuilder.append:(Ljava/lang/String;)Ljava/lang/StringBuilder;
     453: ldc           #82                 // String .class
     455: invokevirtual #31                 // Method java/lang/StringBuilder.append:(Ljava/lang/String;)Ljava/lang/StringBuilder;
     458: invokevirtual #33                 // Method java/lang/StringBuilder.toString:()Ljava/lang/String;
     461: invokespecial #46                 // Method java/io/File."<init>":(Ljava/lang/String;Ljava/lang/String;)V
     464: aastore
     465: invokestatic  #83                 // Method createJarArchive:(Ljava/io/File;[Ljava/io/File;)Z
     468: ifne          477
     471: ldc           #84                 // String Build jar file failed.
     473: iconst_0
     474: invokestatic  #79                 // Method org/junit/Assert.assertTrue:(Ljava/lang/String;Z)V
     477: aload         18
     479: areturn

  public static void addJarFilesToJar(java.io.File, java.lang.String, java.io.File...) throws java.lang.Exception;
    Code:
       0: new           #3                  // class java/io/FileOutputStream
       3: dup
       4: aload_0
       5: invokespecial #4                  // Method java/io/FileOutputStream."<init>":(Ljava/io/File;)V
       8: astore_3
       9: new           #5                  // class java/util/jar/JarOutputStream
      12: dup
      13: aload_3
      14: new           #6                  // class java/util/jar/Manifest
      17: dup
      18: invokespecial #7                  // Method java/util/jar/Manifest."<init>":()V
      21: invokespecial #8                  // Method java/util/jar/JarOutputStream."<init>":(Ljava/io/OutputStream;Ljava/util/jar/Manifest;)V
      24: astore        4
      26: sipush        4096
      29: newarray       byte
      31: astore        5
      33: aload_2
      34: astore        6
      36: aload         6
      38: arraylength
      39: istore        7
      41: iconst_0
      42: istore        8
      44: iload         8
      46: iload         7
      48: if_icmpge     162
      51: aload         6
      53: iload         8
      55: aaload
      56: astore        9
      58: new           #11                 // class java/util/jar/JarEntry
      61: dup
      62: new           #28                 // class java/lang/StringBuilder
      65: dup
      66: invokespecial #29                 // Method java/lang/StringBuilder."<init>":()V
      69: aload_1
      70: invokevirtual #31                 // Method java/lang/StringBuilder.append:(Ljava/lang/String;)Ljava/lang/StringBuilder;
      73: aload         9
      75: invokevirtual #12                 // Method java/io/File.getName:()Ljava/lang/String;
      78: invokevirtual #31                 // Method java/lang/StringBuilder.append:(Ljava/lang/String;)Ljava/lang/StringBuilder;
      81: invokevirtual #33                 // Method java/lang/StringBuilder.toString:()Ljava/lang/String;
      84: invokespecial #13                 // Method java/util/jar/JarEntry."<init>":(Ljava/lang/String;)V
      87: astore        10
      89: aload         10
      91: aload         9
      93: invokevirtual #14                 // Method java/io/File.lastModified:()J
      96: invokevirtual #15                 // Method java/util/jar/JarEntry.setTime:(J)V
      99: aload         4
     101: aload         10
     103: invokevirtual #16                 // Method java/util/jar/JarOutputStream.putNextEntry:(Ljava/util/zip/ZipEntry;)V
     106: new           #17                 // class java/io/FileInputStream
     109: dup
     110: aload         9
     112: invokespecial #18                 // Method java/io/FileInputStream."<init>":(Ljava/io/File;)V
     115: astore        11
     117: aload         11
     119: aload         5
     121: iconst_0
     122: aload         5
     124: arraylength
     125: invokevirtual #19                 // Method java/io/FileInputStream.read:([BII)I
     128: istore        12
     130: iload         12
     132: ifgt          138
     135: goto          151
     138: aload         4
     140: aload         5
     142: iconst_0
     143: iload         12
     145: invokevirtual #20                 // Method java/util/jar/JarOutputStream.write:([BII)V
     148: goto          117
     151: aload         11
     153: invokevirtual #21                 // Method java/io/FileInputStream.close:()V
     156: iinc          8, 1
     159: goto          44
     162: aload         4
     164: invokevirtual #22                 // Method java/util/jar/JarOutputStream.close:()V
     167: aload_3
     168: invokevirtual #23                 // Method java/io/FileOutputStream.close:()V
     171: getstatic     #24                 // Field LOG:Lorg/slf4j/Logger;
     174: ldc           #85                 // String Adding jar file to outer jar file completed
     176: invokeinterface #26,  2           // InterfaceMethod org/slf4j/Logger.info:(Ljava/lang/String;)V
     181: return

  static java.lang.String localDirPath(org.apache.hadoop.conf.Configuration);
    Code:
       0: new           #28                 // class java/lang/StringBuilder
       3: dup
       4: invokespecial #29                 // Method java/lang/StringBuilder."<init>":()V
       7: aload_0
       8: ldc           #87                 // String hbase.local.dir
      10: invokevirtual #88                 // Method org/apache/hadoop/conf/Configuration.get:(Ljava/lang/String;)Ljava/lang/String;
      13: invokevirtual #31                 // Method java/lang/StringBuilder.append:(Ljava/lang/String;)Ljava/lang/StringBuilder;
      16: getstatic     #64                 // Field java/io/File.separator:Ljava/lang/String;
      19: invokevirtual #31                 // Method java/lang/StringBuilder.append:(Ljava/lang/String;)Ljava/lang/StringBuilder;
      22: ldc           #89                 // String jars
      24: invokevirtual #31                 // Method java/lang/StringBuilder.append:(Ljava/lang/String;)Ljava/lang/StringBuilder;
      27: getstatic     #64                 // Field java/io/File.separator:Ljava/lang/String;
      30: invokevirtual #31                 // Method java/lang/StringBuilder.append:(Ljava/lang/String;)Ljava/lang/StringBuilder;
      33: invokevirtual #33                 // Method java/lang/StringBuilder.toString:()Ljava/lang/String;
      36: areturn

  static {};
    Code:
       0: ldc           #2                  // class org/apache/hadoop/hbase/util/ClassLoaderTestHelper
       2: invokestatic  #90                 // Method org/slf4j/LoggerFactory.getLogger:(Ljava/lang/Class;)Lorg/slf4j/Logger;
       5: putstatic     #24                 // Field LOG:Lorg/slf4j/Logger;
       8: return
}
