Compiled from "ClientProtos.java"
public abstract class org.apache.hadoop.hbase.protobuf.generated.ClientProtos$ClientService implements com.google.protobuf.Service {
  protected org.apache.hadoop.hbase.protobuf.generated.ClientProtos$ClientService();
    Code:
       0: aload_0
       1: invokespecial #1                  // Method java/lang/Object."<init>":()V
       4: return

  public static com.google.protobuf.Service newReflectiveService(org.apache.hadoop.hbase.protobuf.generated.ClientProtos$ClientService$Interface);
    Code:
       0: new           #2                  // class org/apache/hadoop/hbase/protobuf/generated/ClientProtos$ClientService$1
       3: dup
       4: aload_0
       5: invokespecial #3                  // Method org/apache/hadoop/hbase/protobuf/generated/ClientProtos$ClientService$1."<init>":(Lorg/apache/hadoop/hbase/protobuf/generated/ClientProtos$ClientService$Interface;)V
       8: areturn

  public static com.google.protobuf.BlockingService newReflectiveBlockingService(org.apache.hadoop.hbase.protobuf.generated.ClientProtos$ClientService$BlockingInterface);
    Code:
       0: new           #4                  // class org/apache/hadoop/hbase/protobuf/generated/ClientProtos$ClientService$2
       3: dup
       4: aload_0
       5: invokespecial #5                  // Method org/apache/hadoop/hbase/protobuf/generated/ClientProtos$ClientService$2."<init>":(Lorg/apache/hadoop/hbase/protobuf/generated/ClientProtos$ClientService$BlockingInterface;)V
       8: areturn

  public abstract void get(com.google.protobuf.RpcController, org.apache.hadoop.hbase.protobuf.generated.ClientProtos$GetRequest, com.google.protobuf.RpcCallback<org.apache.hadoop.hbase.protobuf.generated.ClientProtos$GetResponse>);

  public abstract void mutate(com.google.protobuf.RpcController, org.apache.hadoop.hbase.protobuf.generated.ClientProtos$MutateRequest, com.google.protobuf.RpcCallback<org.apache.hadoop.hbase.protobuf.generated.ClientProtos$MutateResponse>);

  public abstract void scan(com.google.protobuf.RpcController, org.apache.hadoop.hbase.protobuf.generated.ClientProtos$ScanRequest, com.google.protobuf.RpcCallback<org.apache.hadoop.hbase.protobuf.generated.ClientProtos$ScanResponse>);

  public abstract void bulkLoadHFile(com.google.protobuf.RpcController, org.apache.hadoop.hbase.protobuf.generated.ClientProtos$BulkLoadHFileRequest, com.google.protobuf.RpcCallback<org.apache.hadoop.hbase.protobuf.generated.ClientProtos$BulkLoadHFileResponse>);

  public abstract void prepareBulkLoad(com.google.protobuf.RpcController, org.apache.hadoop.hbase.protobuf.generated.ClientProtos$PrepareBulkLoadRequest, com.google.protobuf.RpcCallback<org.apache.hadoop.hbase.protobuf.generated.ClientProtos$PrepareBulkLoadResponse>);

  public abstract void cleanupBulkLoad(com.google.protobuf.RpcController, org.apache.hadoop.hbase.protobuf.generated.ClientProtos$CleanupBulkLoadRequest, com.google.protobuf.RpcCallback<org.apache.hadoop.hbase.protobuf.generated.ClientProtos$CleanupBulkLoadResponse>);

  public abstract void execService(com.google.protobuf.RpcController, org.apache.hadoop.hbase.protobuf.generated.ClientProtos$CoprocessorServiceRequest, com.google.protobuf.RpcCallback<org.apache.hadoop.hbase.protobuf.generated.ClientProtos$CoprocessorServiceResponse>);

  public abstract void execRegionServerService(com.google.protobuf.RpcController, org.apache.hadoop.hbase.protobuf.generated.ClientProtos$CoprocessorServiceRequest, com.google.protobuf.RpcCallback<org.apache.hadoop.hbase.protobuf.generated.ClientProtos$CoprocessorServiceResponse>);

  public abstract void multi(com.google.protobuf.RpcController, org.apache.hadoop.hbase.protobuf.generated.ClientProtos$MultiRequest, com.google.protobuf.RpcCallback<org.apache.hadoop.hbase.protobuf.generated.ClientProtos$MultiResponse>);

  public static final com.google.protobuf.Descriptors$ServiceDescriptor getDescriptor();
    Code:
       0: invokestatic  #6                  // Method org/apache/hadoop/hbase/protobuf/generated/ClientProtos.getDescriptor:()Lcom/google/protobuf/Descriptors$FileDescriptor;
       3: invokevirtual #7                  // Method com/google/protobuf/Descriptors$FileDescriptor.getServices:()Ljava/util/List;
       6: iconst_0
       7: invokeinterface #8,  2            // InterfaceMethod java/util/List.get:(I)Ljava/lang/Object;
      12: checkcast     #9                  // class com/google/protobuf/Descriptors$ServiceDescriptor
      15: areturn

  public final com.google.protobuf.Descriptors$ServiceDescriptor getDescriptorForType();
    Code:
       0: invokestatic  #10                 // Method getDescriptor:()Lcom/google/protobuf/Descriptors$ServiceDescriptor;
       3: areturn

  public final void callMethod(com.google.protobuf.Descriptors$MethodDescriptor, com.google.protobuf.RpcController, com.google.protobuf.Message, com.google.protobuf.RpcCallback<com.google.protobuf.Message>);
    Code:
       0: aload_1
       1: invokevirtual #11                 // Method com/google/protobuf/Descriptors$MethodDescriptor.getService:()Lcom/google/protobuf/Descriptors$ServiceDescriptor;
       4: invokestatic  #10                 // Method getDescriptor:()Lcom/google/protobuf/Descriptors$ServiceDescriptor;
       7: if_acmpeq     20
      10: new           #12                 // class java/lang/IllegalArgumentException
      13: dup
      14: ldc           #13                 // String Service.callMethod() given method descriptor for wrong service type.
      16: invokespecial #14                 // Method java/lang/IllegalArgumentException."<init>":(Ljava/lang/String;)V
      19: athrow
      20: aload_1
      21: invokevirtual #15                 // Method com/google/protobuf/Descriptors$MethodDescriptor.getIndex:()I
      24: tableswitch   { // 0 to 8
                     0: 76
                     1: 91
                     2: 106
                     3: 121
                     4: 136
                     5: 151
                     6: 166
                     7: 181
                     8: 196
               default: 211
          }
      76: aload_0
      77: aload_2
      78: aload_3
      79: checkcast     #16                 // class org/apache/hadoop/hbase/protobuf/generated/ClientProtos$GetRequest
      82: aload         4
      84: invokestatic  #17                 // Method com/google/protobuf/RpcUtil.specializeCallback:(Lcom/google/protobuf/RpcCallback;)Lcom/google/protobuf/RpcCallback;
      87: invokevirtual #18                 // Method get:(Lcom/google/protobuf/RpcController;Lorg/apache/hadoop/hbase/protobuf/generated/ClientProtos$GetRequest;Lcom/google/protobuf/RpcCallback;)V
      90: return
      91: aload_0
      92: aload_2
      93: aload_3
      94: checkcast     #19                 // class org/apache/hadoop/hbase/protobuf/generated/ClientProtos$MutateRequest
      97: aload         4
      99: invokestatic  #17                 // Method com/google/protobuf/RpcUtil.specializeCallback:(Lcom/google/protobuf/RpcCallback;)Lcom/google/protobuf/RpcCallback;
     102: invokevirtual #20                 // Method mutate:(Lcom/google/protobuf/RpcController;Lorg/apache/hadoop/hbase/protobuf/generated/ClientProtos$MutateRequest;Lcom/google/protobuf/RpcCallback;)V
     105: return
     106: aload_0
     107: aload_2
     108: aload_3
     109: checkcast     #21                 // class org/apache/hadoop/hbase/protobuf/generated/ClientProtos$ScanRequest
     112: aload         4
     114: invokestatic  #17                 // Method com/google/protobuf/RpcUtil.specializeCallback:(Lcom/google/protobuf/RpcCallback;)Lcom/google/protobuf/RpcCallback;
     117: invokevirtual #22                 // Method scan:(Lcom/google/protobuf/RpcController;Lorg/apache/hadoop/hbase/protobuf/generated/ClientProtos$ScanRequest;Lcom/google/protobuf/RpcCallback;)V
     120: return
     121: aload_0
     122: aload_2
     123: aload_3
     124: checkcast     #23                 // class org/apache/hadoop/hbase/protobuf/generated/ClientProtos$BulkLoadHFileRequest
     127: aload         4
     129: invokestatic  #17                 // Method com/google/protobuf/RpcUtil.specializeCallback:(Lcom/google/protobuf/RpcCallback;)Lcom/google/protobuf/RpcCallback;
     132: invokevirtual #24                 // Method bulkLoadHFile:(Lcom/google/protobuf/RpcController;Lorg/apache/hadoop/hbase/protobuf/generated/ClientProtos$BulkLoadHFileRequest;Lcom/google/protobuf/RpcCallback;)V
     135: return
     136: aload_0
     137: aload_2
     138: aload_3
     139: checkcast     #25                 // class org/apache/hadoop/hbase/protobuf/generated/ClientProtos$PrepareBulkLoadRequest
     142: aload         4
     144: invokestatic  #17                 // Method com/google/protobuf/RpcUtil.specializeCallback:(Lcom/google/protobuf/RpcCallback;)Lcom/google/protobuf/RpcCallback;
     147: invokevirtual #26                 // Method prepareBulkLoad:(Lcom/google/protobuf/RpcController;Lorg/apache/hadoop/hbase/protobuf/generated/ClientProtos$PrepareBulkLoadRequest;Lcom/google/protobuf/RpcCallback;)V
     150: return
     151: aload_0
     152: aload_2
     153: aload_3
     154: checkcast     #27                 // class org/apache/hadoop/hbase/protobuf/generated/ClientProtos$CleanupBulkLoadRequest
     157: aload         4
     159: invokestatic  #17                 // Method com/google/protobuf/RpcUtil.specializeCallback:(Lcom/google/protobuf/RpcCallback;)Lcom/google/protobuf/RpcCallback;
     162: invokevirtual #28                 // Method cleanupBulkLoad:(Lcom/google/protobuf/RpcController;Lorg/apache/hadoop/hbase/protobuf/generated/ClientProtos$CleanupBulkLoadRequest;Lcom/google/protobuf/RpcCallback;)V
     165: return
     166: aload_0
     167: aload_2
     168: aload_3
     169: checkcast     #29                 // class org/apache/hadoop/hbase/protobuf/generated/ClientProtos$CoprocessorServiceRequest
     172: aload         4
     174: invokestatic  #17                 // Method com/google/protobuf/RpcUtil.specializeCallback:(Lcom/google/protobuf/RpcCallback;)Lcom/google/protobuf/RpcCallback;
     177: invokevirtual #30                 // Method execService:(Lcom/google/protobuf/RpcController;Lorg/apache/hadoop/hbase/protobuf/generated/ClientProtos$CoprocessorServiceRequest;Lcom/google/protobuf/RpcCallback;)V
     180: return
     181: aload_0
     182: aload_2
     183: aload_3
     184: checkcast     #29                 // class org/apache/hadoop/hbase/protobuf/generated/ClientProtos$CoprocessorServiceRequest
     187: aload         4
     189: invokestatic  #17                 // Method com/google/protobuf/RpcUtil.specializeCallback:(Lcom/google/protobuf/RpcCallback;)Lcom/google/protobuf/RpcCallback;
     192: invokevirtual #31                 // Method execRegionServerService:(Lcom/google/protobuf/RpcController;Lorg/apache/hadoop/hbase/protobuf/generated/ClientProtos$CoprocessorServiceRequest;Lcom/google/protobuf/RpcCallback;)V
     195: return
     196: aload_0
     197: aload_2
     198: aload_3
     199: checkcast     #32                 // class org/apache/hadoop/hbase/protobuf/generated/ClientProtos$MultiRequest
     202: aload         4
     204: invokestatic  #17                 // Method com/google/protobuf/RpcUtil.specializeCallback:(Lcom/google/protobuf/RpcCallback;)Lcom/google/protobuf/RpcCallback;
     207: invokevirtual #33                 // Method multi:(Lcom/google/protobuf/RpcController;Lorg/apache/hadoop/hbase/protobuf/generated/ClientProtos$MultiRequest;Lcom/google/protobuf/RpcCallback;)V
     210: return
     211: new           #34                 // class java/lang/AssertionError
     214: dup
     215: ldc           #35                 // String Can't get here.
     217: invokespecial #36                 // Method java/lang/AssertionError."<init>":(Ljava/lang/Object;)V
     220: athrow

  public final com.google.protobuf.Message getRequestPrototype(com.google.protobuf.Descriptors$MethodDescriptor);
    Code:
       0: aload_1
       1: invokevirtual #11                 // Method com/google/protobuf/Descriptors$MethodDescriptor.getService:()Lcom/google/protobuf/Descriptors$ServiceDescriptor;
       4: invokestatic  #10                 // Method getDescriptor:()Lcom/google/protobuf/Descriptors$ServiceDescriptor;
       7: if_acmpeq     20
      10: new           #12                 // class java/lang/IllegalArgumentException
      13: dup
      14: ldc           #37                 // String Service.getRequestPrototype() given method descriptor for wrong service type.
      16: invokespecial #14                 // Method java/lang/IllegalArgumentException."<init>":(Ljava/lang/String;)V
      19: athrow
      20: aload_1
      21: invokevirtual #15                 // Method com/google/protobuf/Descriptors$MethodDescriptor.getIndex:()I
      24: tableswitch   { // 0 to 8
                     0: 76
                     1: 80
                     2: 84
                     3: 88
                     4: 92
                     5: 96
                     6: 100
                     7: 104
                     8: 108
               default: 112
          }
      76: invokestatic  #38                 // Method org/apache/hadoop/hbase/protobuf/generated/ClientProtos$GetRequest.getDefaultInstance:()Lorg/apache/hadoop/hbase/protobuf/generated/ClientProtos$GetRequest;
      79: areturn
      80: invokestatic  #39                 // Method org/apache/hadoop/hbase/protobuf/generated/ClientProtos$MutateRequest.getDefaultInstance:()Lorg/apache/hadoop/hbase/protobuf/generated/ClientProtos$MutateRequest;
      83: areturn
      84: invokestatic  #40                 // Method org/apache/hadoop/hbase/protobuf/generated/ClientProtos$ScanRequest.getDefaultInstance:()Lorg/apache/hadoop/hbase/protobuf/generated/ClientProtos$ScanRequest;
      87: areturn
      88: invokestatic  #41                 // Method org/apache/hadoop/hbase/protobuf/generated/ClientProtos$BulkLoadHFileRequest.getDefaultInstance:()Lorg/apache/hadoop/hbase/protobuf/generated/ClientProtos$BulkLoadHFileRequest;
      91: areturn
      92: invokestatic  #42                 // Method org/apache/hadoop/hbase/protobuf/generated/ClientProtos$PrepareBulkLoadRequest.getDefaultInstance:()Lorg/apache/hadoop/hbase/protobuf/generated/ClientProtos$PrepareBulkLoadRequest;
      95: areturn
      96: invokestatic  #43                 // Method org/apache/hadoop/hbase/protobuf/generated/ClientProtos$CleanupBulkLoadRequest.getDefaultInstance:()Lorg/apache/hadoop/hbase/protobuf/generated/ClientProtos$CleanupBulkLoadRequest;
      99: areturn
     100: invokestatic  #44                 // Method org/apache/hadoop/hbase/protobuf/generated/ClientProtos$CoprocessorServiceRequest.getDefaultInstance:()Lorg/apache/hadoop/hbase/protobuf/generated/ClientProtos$CoprocessorServiceRequest;
     103: areturn
     104: invokestatic  #44                 // Method org/apache/hadoop/hbase/protobuf/generated/ClientProtos$CoprocessorServiceRequest.getDefaultInstance:()Lorg/apache/hadoop/hbase/protobuf/generated/ClientProtos$CoprocessorServiceRequest;
     107: areturn
     108: invokestatic  #45                 // Method org/apache/hadoop/hbase/protobuf/generated/ClientProtos$MultiRequest.getDefaultInstance:()Lorg/apache/hadoop/hbase/protobuf/generated/ClientProtos$MultiRequest;
     111: areturn
     112: new           #34                 // class java/lang/AssertionError
     115: dup
     116: ldc           #35                 // String Can't get here.
     118: invokespecial #36                 // Method java/lang/AssertionError."<init>":(Ljava/lang/Object;)V
     121: athrow

  public final com.google.protobuf.Message getResponsePrototype(com.google.protobuf.Descriptors$MethodDescriptor);
    Code:
       0: aload_1
       1: invokevirtual #11                 // Method com/google/protobuf/Descriptors$MethodDescriptor.getService:()Lcom/google/protobuf/Descriptors$ServiceDescriptor;
       4: invokestatic  #10                 // Method getDescriptor:()Lcom/google/protobuf/Descriptors$ServiceDescriptor;
       7: if_acmpeq     20
      10: new           #12                 // class java/lang/IllegalArgumentException
      13: dup
      14: ldc           #46                 // String Service.getResponsePrototype() given method descriptor for wrong service type.
      16: invokespecial #14                 // Method java/lang/IllegalArgumentException."<init>":(Ljava/lang/String;)V
      19: athrow
      20: aload_1
      21: invokevirtual #15                 // Method com/google/protobuf/Descriptors$MethodDescriptor.getIndex:()I
      24: tableswitch   { // 0 to 8
                     0: 76
                     1: 80
                     2: 84
                     3: 88
                     4: 92
                     5: 96
                     6: 100
                     7: 104
                     8: 108
               default: 112
          }
      76: invokestatic  #47                 // Method org/apache/hadoop/hbase/protobuf/generated/ClientProtos$GetResponse.getDefaultInstance:()Lorg/apache/hadoop/hbase/protobuf/generated/ClientProtos$GetResponse;
      79: areturn
      80: invokestatic  #48                 // Method org/apache/hadoop/hbase/protobuf/generated/ClientProtos$MutateResponse.getDefaultInstance:()Lorg/apache/hadoop/hbase/protobuf/generated/ClientProtos$MutateResponse;
      83: areturn
      84: invokestatic  #49                 // Method org/apache/hadoop/hbase/protobuf/generated/ClientProtos$ScanResponse.getDefaultInstance:()Lorg/apache/hadoop/hbase/protobuf/generated/ClientProtos$ScanResponse;
      87: areturn
      88: invokestatic  #50                 // Method org/apache/hadoop/hbase/protobuf/generated/ClientProtos$BulkLoadHFileResponse.getDefaultInstance:()Lorg/apache/hadoop/hbase/protobuf/generated/ClientProtos$BulkLoadHFileResponse;
      91: areturn
      92: invokestatic  #51                 // Method org/apache/hadoop/hbase/protobuf/generated/ClientProtos$PrepareBulkLoadResponse.getDefaultInstance:()Lorg/apache/hadoop/hbase/protobuf/generated/ClientProtos$PrepareBulkLoadResponse;
      95: areturn
      96: invokestatic  #52                 // Method org/apache/hadoop/hbase/protobuf/generated/ClientProtos$CleanupBulkLoadResponse.getDefaultInstance:()Lorg/apache/hadoop/hbase/protobuf/generated/ClientProtos$CleanupBulkLoadResponse;
      99: areturn
     100: invokestatic  #53                 // Method org/apache/hadoop/hbase/protobuf/generated/ClientProtos$CoprocessorServiceResponse.getDefaultInstance:()Lorg/apache/hadoop/hbase/protobuf/generated/ClientProtos$CoprocessorServiceResponse;
     103: areturn
     104: invokestatic  #53                 // Method org/apache/hadoop/hbase/protobuf/generated/ClientProtos$CoprocessorServiceResponse.getDefaultInstance:()Lorg/apache/hadoop/hbase/protobuf/generated/ClientProtos$CoprocessorServiceResponse;
     107: areturn
     108: invokestatic  #54                 // Method org/apache/hadoop/hbase/protobuf/generated/ClientProtos$MultiResponse.getDefaultInstance:()Lorg/apache/hadoop/hbase/protobuf/generated/ClientProtos$MultiResponse;
     111: areturn
     112: new           #34                 // class java/lang/AssertionError
     115: dup
     116: ldc           #35                 // String Can't get here.
     118: invokespecial #36                 // Method java/lang/AssertionError."<init>":(Ljava/lang/Object;)V
     121: athrow

  public static org.apache.hadoop.hbase.protobuf.generated.ClientProtos$ClientService$Stub newStub(com.google.protobuf.RpcChannel);
    Code:
       0: new           #55                 // class org/apache/hadoop/hbase/protobuf/generated/ClientProtos$ClientService$Stub
       3: dup
       4: aload_0
       5: aconst_null
       6: invokespecial #56                 // Method org/apache/hadoop/hbase/protobuf/generated/ClientProtos$ClientService$Stub."<init>":(Lcom/google/protobuf/RpcChannel;Lorg/apache/hadoop/hbase/protobuf/generated/ClientProtos$1;)V
       9: areturn

  public static org.apache.hadoop.hbase.protobuf.generated.ClientProtos$ClientService$BlockingInterface newBlockingStub(com.google.protobuf.BlockingRpcChannel);
    Code:
       0: new           #57                 // class org/apache/hadoop/hbase/protobuf/generated/ClientProtos$ClientService$BlockingStub
       3: dup
       4: aload_0
       5: aconst_null
       6: invokespecial #58                 // Method org/apache/hadoop/hbase/protobuf/generated/ClientProtos$ClientService$BlockingStub."<init>":(Lcom/google/protobuf/BlockingRpcChannel;Lorg/apache/hadoop/hbase/protobuf/generated/ClientProtos$1;)V
       9: areturn
}
