Compiled from "ClientProtos.java"
public final class org.apache.hadoop.hbase.protobuf.generated.ClientProtos$ScanRequest extends com.google.protobuf.GeneratedMessage implements org.apache.hadoop.hbase.protobuf.generated.ClientProtos$ScanRequestOrBuilder {
  public static com.google.protobuf.Parser<org.apache.hadoop.hbase.protobuf.generated.ClientProtos$ScanRequest> PARSER;

  public static final int REGION_FIELD_NUMBER;

  public static final int SCAN_FIELD_NUMBER;

  public static final int SCANNER_ID_FIELD_NUMBER;

  public static final int NUMBER_OF_ROWS_FIELD_NUMBER;

  public static final int CLOSE_SCANNER_FIELD_NUMBER;

  public static final int NEXT_CALL_SEQ_FIELD_NUMBER;

  public static final int CLIENT_HANDLES_PARTIALS_FIELD_NUMBER;

  public static final int CLIENT_HANDLES_HEARTBEATS_FIELD_NUMBER;

  public static final int TRACK_SCAN_METRICS_FIELD_NUMBER;

  public static final int RENEW_FIELD_NUMBER;

  public static final int LIMIT_OF_ROWS_FIELD_NUMBER;

  public static org.apache.hadoop.hbase.protobuf.generated.ClientProtos$ScanRequest getDefaultInstance();
    Code:
       0: getstatic     #24                 // Field defaultInstance:Lorg/apache/hadoop/hbase/protobuf/generated/ClientProtos$ScanRequest;
       3: areturn

  public org.apache.hadoop.hbase.protobuf.generated.ClientProtos$ScanRequest getDefaultInstanceForType();
    Code:
       0: getstatic     #24                 // Field defaultInstance:Lorg/apache/hadoop/hbase/protobuf/generated/ClientProtos$ScanRequest;
       3: areturn

  public final com.google.protobuf.UnknownFieldSet getUnknownFields();
    Code:
       0: aload_0
       1: getfield      #21                 // Field unknownFields:Lcom/google/protobuf/UnknownFieldSet;
       4: areturn

  public static final com.google.protobuf.Descriptors$Descriptor getDescriptor();
    Code:
       0: invokestatic  #50                 // Method org/apache/hadoop/hbase/protobuf/generated/ClientProtos.access$19900:()Lcom/google/protobuf/Descriptors$Descriptor;
       3: areturn

  protected com.google.protobuf.GeneratedMessage$FieldAccessorTable internalGetFieldAccessorTable();
    Code:
       0: invokestatic  #51                 // Method org/apache/hadoop/hbase/protobuf/generated/ClientProtos.access$20000:()Lcom/google/protobuf/GeneratedMessage$FieldAccessorTable;
       3: ldc           #52                 // class org/apache/hadoop/hbase/protobuf/generated/ClientProtos$ScanRequest
       5: ldc           #53                 // class org/apache/hadoop/hbase/protobuf/generated/ClientProtos$ScanRequest$Builder
       7: invokevirtual #54                 // Method com/google/protobuf/GeneratedMessage$FieldAccessorTable.ensureFieldAccessorsInitialized:(Ljava/lang/Class;Ljava/lang/Class;)Lcom/google/protobuf/GeneratedMessage$FieldAccessorTable;
      10: areturn

  public com.google.protobuf.Parser<org.apache.hadoop.hbase.protobuf.generated.ClientProtos$ScanRequest> getParserForType();
    Code:
       0: getstatic     #55                 // Field PARSER:Lcom/google/protobuf/Parser;
       3: areturn

  public boolean hasRegion();
    Code:
       0: aload_0
       1: getfield      #1                  // Field bitField0_:I
       4: iconst_1
       5: iand
       6: iconst_1
       7: if_icmpne     14
      10: iconst_1
      11: goto          15
      14: iconst_0
      15: ireturn

  public org.apache.hadoop.hbase.protobuf.generated.HBaseProtos$RegionSpecifier getRegion();
    Code:
       0: aload_0
       1: getfield      #12                 // Field region_:Lorg/apache/hadoop/hbase/protobuf/generated/HBaseProtos$RegionSpecifier;
       4: areturn

  public org.apache.hadoop.hbase.protobuf.generated.HBaseProtos$RegionSpecifierOrBuilder getRegionOrBuilder();
    Code:
       0: aload_0
       1: getfield      #12                 // Field region_:Lorg/apache/hadoop/hbase/protobuf/generated/HBaseProtos$RegionSpecifier;
       4: areturn

  public boolean hasScan();
    Code:
       0: aload_0
       1: getfield      #1                  // Field bitField0_:I
       4: iconst_2
       5: iand
       6: iconst_2
       7: if_icmpne     14
      10: iconst_1
      11: goto          15
      14: iconst_0
      15: ireturn

  public org.apache.hadoop.hbase.protobuf.generated.ClientProtos$Scan getScan();
    Code:
       0: aload_0
       1: getfield      #11                 // Field scan_:Lorg/apache/hadoop/hbase/protobuf/generated/ClientProtos$Scan;
       4: areturn

  public org.apache.hadoop.hbase.protobuf.generated.ClientProtos$ScanOrBuilder getScanOrBuilder();
    Code:
       0: aload_0
       1: getfield      #11                 // Field scan_:Lorg/apache/hadoop/hbase/protobuf/generated/ClientProtos$Scan;
       4: areturn

  public boolean hasScannerId();
    Code:
       0: aload_0
       1: getfield      #1                  // Field bitField0_:I
       4: iconst_4
       5: iand
       6: iconst_4
       7: if_icmpne     14
      10: iconst_1
      11: goto          15
      14: iconst_0
      15: ireturn

  public long getScannerId();
    Code:
       0: aload_0
       1: getfield      #10                 // Field scannerId_:J
       4: lreturn

  public boolean hasNumberOfRows();
    Code:
       0: aload_0
       1: getfield      #1                  // Field bitField0_:I
       4: bipush        8
       6: iand
       7: bipush        8
       9: if_icmpne     16
      12: iconst_1
      13: goto          17
      16: iconst_0
      17: ireturn

  public int getNumberOfRows();
    Code:
       0: aload_0
       1: getfield      #9                  // Field numberOfRows_:I
       4: ireturn

  public boolean hasCloseScanner();
    Code:
       0: aload_0
       1: getfield      #1                  // Field bitField0_:I
       4: bipush        16
       6: iand
       7: bipush        16
       9: if_icmpne     16
      12: iconst_1
      13: goto          17
      16: iconst_0
      17: ireturn

  public boolean getCloseScanner();
    Code:
       0: aload_0
       1: getfield      #8                  // Field closeScanner_:Z
       4: ireturn

  public boolean hasNextCallSeq();
    Code:
       0: aload_0
       1: getfield      #1                  // Field bitField0_:I
       4: bipush        32
       6: iand
       7: bipush        32
       9: if_icmpne     16
      12: iconst_1
      13: goto          17
      16: iconst_0
      17: ireturn

  public long getNextCallSeq();
    Code:
       0: aload_0
       1: getfield      #7                  // Field nextCallSeq_:J
       4: lreturn

  public boolean hasClientHandlesPartials();
    Code:
       0: aload_0
       1: getfield      #1                  // Field bitField0_:I
       4: bipush        64
       6: iand
       7: bipush        64
       9: if_icmpne     16
      12: iconst_1
      13: goto          17
      16: iconst_0
      17: ireturn

  public boolean getClientHandlesPartials();
    Code:
       0: aload_0
       1: getfield      #6                  // Field clientHandlesPartials_:Z
       4: ireturn

  public boolean hasClientHandlesHeartbeats();
    Code:
       0: aload_0
       1: getfield      #1                  // Field bitField0_:I
       4: sipush        128
       7: iand
       8: sipush        128
      11: if_icmpne     18
      14: iconst_1
      15: goto          19
      18: iconst_0
      19: ireturn

  public boolean getClientHandlesHeartbeats();
    Code:
       0: aload_0
       1: getfield      #5                  // Field clientHandlesHeartbeats_:Z
       4: ireturn

  public boolean hasTrackScanMetrics();
    Code:
       0: aload_0
       1: getfield      #1                  // Field bitField0_:I
       4: sipush        256
       7: iand
       8: sipush        256
      11: if_icmpne     18
      14: iconst_1
      15: goto          19
      18: iconst_0
      19: ireturn

  public boolean getTrackScanMetrics();
    Code:
       0: aload_0
       1: getfield      #4                  // Field trackScanMetrics_:Z
       4: ireturn

  public boolean hasRenew();
    Code:
       0: aload_0
       1: getfield      #1                  // Field bitField0_:I
       4: sipush        512
       7: iand
       8: sipush        512
      11: if_icmpne     18
      14: iconst_1
      15: goto          19
      18: iconst_0
      19: ireturn

  public boolean getRenew();
    Code:
       0: aload_0
       1: getfield      #3                  // Field renew_:Z
       4: ireturn

  public boolean hasLimitOfRows();
    Code:
       0: aload_0
       1: getfield      #1                  // Field bitField0_:I
       4: sipush        1024
       7: iand
       8: sipush        1024
      11: if_icmpne     18
      14: iconst_1
      15: goto          19
      18: iconst_0
      19: ireturn

  public int getLimitOfRows();
    Code:
       0: aload_0
       1: getfield      #2                  // Field limitOfRows_:I
       4: ireturn

  public final boolean isInitialized();
    Code:
       0: aload_0
       1: getfield      #17                 // Field memoizedIsInitialized:B
       4: istore_1
       5: iload_1
       6: iconst_m1
       7: if_icmpeq     21
      10: iload_1
      11: iconst_1
      12: if_icmpne     19
      15: iconst_1
      16: goto          20
      19: iconst_0
      20: ireturn
      21: aload_0
      22: invokevirtual #58                 // Method hasRegion:()Z
      25: ifeq          45
      28: aload_0
      29: invokevirtual #59                 // Method getRegion:()Lorg/apache/hadoop/hbase/protobuf/generated/HBaseProtos$RegionSpecifier;
      32: invokevirtual #60                 // Method org/apache/hadoop/hbase/protobuf/generated/HBaseProtos$RegionSpecifier.isInitialized:()Z
      35: ifne          45
      38: aload_0
      39: iconst_0
      40: putfield      #17                 // Field memoizedIsInitialized:B
      43: iconst_0
      44: ireturn
      45: aload_0
      46: invokevirtual #61                 // Method hasScan:()Z
      49: ifeq          69
      52: aload_0
      53: invokevirtual #62                 // Method getScan:()Lorg/apache/hadoop/hbase/protobuf/generated/ClientProtos$Scan;
      56: invokevirtual #63                 // Method org/apache/hadoop/hbase/protobuf/generated/ClientProtos$Scan.isInitialized:()Z
      59: ifne          69
      62: aload_0
      63: iconst_0
      64: putfield      #17                 // Field memoizedIsInitialized:B
      67: iconst_0
      68: ireturn
      69: aload_0
      70: iconst_1
      71: putfield      #17                 // Field memoizedIsInitialized:B
      74: iconst_1
      75: ireturn

  public void writeTo(com.google.protobuf.CodedOutputStream) throws java.io.IOException;
    Code:
       0: aload_0
       1: invokevirtual #64                 // Method getSerializedSize:()I
       4: pop
       5: aload_0
       6: getfield      #1                  // Field bitField0_:I
       9: iconst_1
      10: iand
      11: iconst_1
      12: if_icmpne     24
      15: aload_1
      16: iconst_1
      17: aload_0
      18: getfield      #12                 // Field region_:Lorg/apache/hadoop/hbase/protobuf/generated/HBaseProtos$RegionSpecifier;
      21: invokevirtual #65                 // Method com/google/protobuf/CodedOutputStream.writeMessage:(ILcom/google/protobuf/MessageLite;)V
      24: aload_0
      25: getfield      #1                  // Field bitField0_:I
      28: iconst_2
      29: iand
      30: iconst_2
      31: if_icmpne     43
      34: aload_1
      35: iconst_2
      36: aload_0
      37: getfield      #11                 // Field scan_:Lorg/apache/hadoop/hbase/protobuf/generated/ClientProtos$Scan;
      40: invokevirtual #65                 // Method com/google/protobuf/CodedOutputStream.writeMessage:(ILcom/google/protobuf/MessageLite;)V
      43: aload_0
      44: getfield      #1                  // Field bitField0_:I
      47: iconst_4
      48: iand
      49: iconst_4
      50: if_icmpne     62
      53: aload_1
      54: iconst_3
      55: aload_0
      56: getfield      #10                 // Field scannerId_:J
      59: invokevirtual #66                 // Method com/google/protobuf/CodedOutputStream.writeUInt64:(IJ)V
      62: aload_0
      63: getfield      #1                  // Field bitField0_:I
      66: bipush        8
      68: iand
      69: bipush        8
      71: if_icmpne     83
      74: aload_1
      75: iconst_4
      76: aload_0
      77: getfield      #9                  // Field numberOfRows_:I
      80: invokevirtual #67                 // Method com/google/protobuf/CodedOutputStream.writeUInt32:(II)V
      83: aload_0
      84: getfield      #1                  // Field bitField0_:I
      87: bipush        16
      89: iand
      90: bipush        16
      92: if_icmpne     104
      95: aload_1
      96: iconst_5
      97: aload_0
      98: getfield      #8                  // Field closeScanner_:Z
     101: invokevirtual #68                 // Method com/google/protobuf/CodedOutputStream.writeBool:(IZ)V
     104: aload_0
     105: getfield      #1                  // Field bitField0_:I
     108: bipush        32
     110: iand
     111: bipush        32
     113: if_icmpne     126
     116: aload_1
     117: bipush        6
     119: aload_0
     120: getfield      #7                  // Field nextCallSeq_:J
     123: invokevirtual #66                 // Method com/google/protobuf/CodedOutputStream.writeUInt64:(IJ)V
     126: aload_0
     127: getfield      #1                  // Field bitField0_:I
     130: bipush        64
     132: iand
     133: bipush        64
     135: if_icmpne     148
     138: aload_1
     139: bipush        7
     141: aload_0
     142: getfield      #6                  // Field clientHandlesPartials_:Z
     145: invokevirtual #68                 // Method com/google/protobuf/CodedOutputStream.writeBool:(IZ)V
     148: aload_0
     149: getfield      #1                  // Field bitField0_:I
     152: sipush        128
     155: iand
     156: sipush        128
     159: if_icmpne     172
     162: aload_1
     163: bipush        8
     165: aload_0
     166: getfield      #5                  // Field clientHandlesHeartbeats_:Z
     169: invokevirtual #68                 // Method com/google/protobuf/CodedOutputStream.writeBool:(IZ)V
     172: aload_0
     173: getfield      #1                  // Field bitField0_:I
     176: sipush        256
     179: iand
     180: sipush        256
     183: if_icmpne     196
     186: aload_1
     187: bipush        9
     189: aload_0
     190: getfield      #4                  // Field trackScanMetrics_:Z
     193: invokevirtual #68                 // Method com/google/protobuf/CodedOutputStream.writeBool:(IZ)V
     196: aload_0
     197: getfield      #1                  // Field bitField0_:I
     200: sipush        512
     203: iand
     204: sipush        512
     207: if_icmpne     220
     210: aload_1
     211: bipush        10
     213: aload_0
     214: getfield      #3                  // Field renew_:Z
     217: invokevirtual #68                 // Method com/google/protobuf/CodedOutputStream.writeBool:(IZ)V
     220: aload_0
     221: getfield      #1                  // Field bitField0_:I
     224: sipush        1024
     227: iand
     228: sipush        1024
     231: if_icmpne     244
     234: aload_1
     235: bipush        11
     237: aload_0
     238: getfield      #2                  // Field limitOfRows_:I
     241: invokevirtual #67                 // Method com/google/protobuf/CodedOutputStream.writeUInt32:(II)V
     244: aload_0
     245: invokevirtual #69                 // Method getUnknownFields:()Lcom/google/protobuf/UnknownFieldSet;
     248: aload_1
     249: invokevirtual #70                 // Method com/google/protobuf/UnknownFieldSet.writeTo:(Lcom/google/protobuf/CodedOutputStream;)V
     252: return

  public int getSerializedSize();
    Code:
       0: aload_0
       1: getfield      #18                 // Field memoizedSerializedSize:I
       4: istore_1
       5: iload_1
       6: iconst_m1
       7: if_icmpeq     12
      10: iload_1
      11: ireturn
      12: iconst_0
      13: istore_1
      14: aload_0
      15: getfield      #1                  // Field bitField0_:I
      18: iconst_1
      19: iand
      20: iconst_1
      21: if_icmpne     35
      24: iload_1
      25: iconst_1
      26: aload_0
      27: getfield      #12                 // Field region_:Lorg/apache/hadoop/hbase/protobuf/generated/HBaseProtos$RegionSpecifier;
      30: invokestatic  #71                 // Method com/google/protobuf/CodedOutputStream.computeMessageSize:(ILcom/google/protobuf/MessageLite;)I
      33: iadd
      34: istore_1
      35: aload_0
      36: getfield      #1                  // Field bitField0_:I
      39: iconst_2
      40: iand
      41: iconst_2
      42: if_icmpne     56
      45: iload_1
      46: iconst_2
      47: aload_0
      48: getfield      #11                 // Field scan_:Lorg/apache/hadoop/hbase/protobuf/generated/ClientProtos$Scan;
      51: invokestatic  #71                 // Method com/google/protobuf/CodedOutputStream.computeMessageSize:(ILcom/google/protobuf/MessageLite;)I
      54: iadd
      55: istore_1
      56: aload_0
      57: getfield      #1                  // Field bitField0_:I
      60: iconst_4
      61: iand
      62: iconst_4
      63: if_icmpne     77
      66: iload_1
      67: iconst_3
      68: aload_0
      69: getfield      #10                 // Field scannerId_:J
      72: invokestatic  #72                 // Method com/google/protobuf/CodedOutputStream.computeUInt64Size:(IJ)I
      75: iadd
      76: istore_1
      77: aload_0
      78: getfield      #1                  // Field bitField0_:I
      81: bipush        8
      83: iand
      84: bipush        8
      86: if_icmpne     100
      89: iload_1
      90: iconst_4
      91: aload_0
      92: getfield      #9                  // Field numberOfRows_:I
      95: invokestatic  #73                 // Method com/google/protobuf/CodedOutputStream.computeUInt32Size:(II)I
      98: iadd
      99: istore_1
     100: aload_0
     101: getfield      #1                  // Field bitField0_:I
     104: bipush        16
     106: iand
     107: bipush        16
     109: if_icmpne     123
     112: iload_1
     113: iconst_5
     114: aload_0
     115: getfield      #8                  // Field closeScanner_:Z
     118: invokestatic  #74                 // Method com/google/protobuf/CodedOutputStream.computeBoolSize:(IZ)I
     121: iadd
     122: istore_1
     123: aload_0
     124: getfield      #1                  // Field bitField0_:I
     127: bipush        32
     129: iand
     130: bipush        32
     132: if_icmpne     147
     135: iload_1
     136: bipush        6
     138: aload_0
     139: getfield      #7                  // Field nextCallSeq_:J
     142: invokestatic  #72                 // Method com/google/protobuf/CodedOutputStream.computeUInt64Size:(IJ)I
     145: iadd
     146: istore_1
     147: aload_0
     148: getfield      #1                  // Field bitField0_:I
     151: bipush        64
     153: iand
     154: bipush        64
     156: if_icmpne     171
     159: iload_1
     160: bipush        7
     162: aload_0
     163: getfield      #6                  // Field clientHandlesPartials_:Z
     166: invokestatic  #74                 // Method com/google/protobuf/CodedOutputStream.computeBoolSize:(IZ)I
     169: iadd
     170: istore_1
     171: aload_0
     172: getfield      #1                  // Field bitField0_:I
     175: sipush        128
     178: iand
     179: sipush        128
     182: if_icmpne     197
     185: iload_1
     186: bipush        8
     188: aload_0
     189: getfield      #5                  // Field clientHandlesHeartbeats_:Z
     192: invokestatic  #74                 // Method com/google/protobuf/CodedOutputStream.computeBoolSize:(IZ)I
     195: iadd
     196: istore_1
     197: aload_0
     198: getfield      #1                  // Field bitField0_:I
     201: sipush        256
     204: iand
     205: sipush        256
     208: if_icmpne     223
     211: iload_1
     212: bipush        9
     214: aload_0
     215: getfield      #4                  // Field trackScanMetrics_:Z
     218: invokestatic  #74                 // Method com/google/protobuf/CodedOutputStream.computeBoolSize:(IZ)I
     221: iadd
     222: istore_1
     223: aload_0
     224: getfield      #1                  // Field bitField0_:I
     227: sipush        512
     230: iand
     231: sipush        512
     234: if_icmpne     249
     237: iload_1
     238: bipush        10
     240: aload_0
     241: getfield      #3                  // Field renew_:Z
     244: invokestatic  #74                 // Method com/google/protobuf/CodedOutputStream.computeBoolSize:(IZ)I
     247: iadd
     248: istore_1
     249: aload_0
     250: getfield      #1                  // Field bitField0_:I
     253: sipush        1024
     256: iand
     257: sipush        1024
     260: if_icmpne     275
     263: iload_1
     264: bipush        11
     266: aload_0
     267: getfield      #2                  // Field limitOfRows_:I
     270: invokestatic  #73                 // Method com/google/protobuf/CodedOutputStream.computeUInt32Size:(II)I
     273: iadd
     274: istore_1
     275: iload_1
     276: aload_0
     277: invokevirtual #69                 // Method getUnknownFields:()Lcom/google/protobuf/UnknownFieldSet;
     280: invokevirtual #75                 // Method com/google/protobuf/UnknownFieldSet.getSerializedSize:()I
     283: iadd
     284: istore_1
     285: aload_0
     286: iload_1
     287: putfield      #18                 // Field memoizedSerializedSize:I
     290: iload_1
     291: ireturn

  protected java.lang.Object writeReplace() throws java.io.ObjectStreamException;
    Code:
       0: aload_0
       1: invokespecial #76                 // Method com/google/protobuf/GeneratedMessage.writeReplace:()Ljava/lang/Object;
       4: areturn

  public boolean equals(java.lang.Object);
    Code:
       0: aload_1
       1: aload_0
       2: if_acmpne     7
       5: iconst_1
       6: ireturn
       7: aload_1
       8: instanceof    #52                 // class org/apache/hadoop/hbase/protobuf/generated/ClientProtos$ScanRequest
      11: ifne          20
      14: aload_0
      15: aload_1
      16: invokespecial #77                 // Method com/google/protobuf/GeneratedMessage.equals:(Ljava/lang/Object;)Z
      19: ireturn
      20: aload_1
      21: checkcast     #52                 // class org/apache/hadoop/hbase/protobuf/generated/ClientProtos$ScanRequest
      24: astore_2
      25: iconst_1
      26: istore_3
      27: iload_3
      28: ifeq          46
      31: aload_0
      32: invokevirtual #58                 // Method hasRegion:()Z
      35: aload_2
      36: invokevirtual #58                 // Method hasRegion:()Z
      39: if_icmpne     46
      42: iconst_1
      43: goto          47
      46: iconst_0
      47: istore_3
      48: aload_0
      49: invokevirtual #58                 // Method hasRegion:()Z
      52: ifeq          79
      55: iload_3
      56: ifeq          77
      59: aload_0
      60: invokevirtual #59                 // Method getRegion:()Lorg/apache/hadoop/hbase/protobuf/generated/HBaseProtos$RegionSpecifier;
      63: aload_2
      64: invokevirtual #59                 // Method getRegion:()Lorg/apache/hadoop/hbase/protobuf/generated/HBaseProtos$RegionSpecifier;
      67: invokevirtual #78                 // Method org/apache/hadoop/hbase/protobuf/generated/HBaseProtos$RegionSpecifier.equals:(Ljava/lang/Object;)Z
      70: ifeq          77
      73: iconst_1
      74: goto          78
      77: iconst_0
      78: istore_3
      79: iload_3
      80: ifeq          98
      83: aload_0
      84: invokevirtual #61                 // Method hasScan:()Z
      87: aload_2
      88: invokevirtual #61                 // Method hasScan:()Z
      91: if_icmpne     98
      94: iconst_1
      95: goto          99
      98: iconst_0
      99: istore_3
     100: aload_0
     101: invokevirtual #61                 // Method hasScan:()Z
     104: ifeq          131
     107: iload_3
     108: ifeq          129
     111: aload_0
     112: invokevirtual #62                 // Method getScan:()Lorg/apache/hadoop/hbase/protobuf/generated/ClientProtos$Scan;
     115: aload_2
     116: invokevirtual #62                 // Method getScan:()Lorg/apache/hadoop/hbase/protobuf/generated/ClientProtos$Scan;
     119: invokevirtual #79                 // Method org/apache/hadoop/hbase/protobuf/generated/ClientProtos$Scan.equals:(Ljava/lang/Object;)Z
     122: ifeq          129
     125: iconst_1
     126: goto          130
     129: iconst_0
     130: istore_3
     131: iload_3
     132: ifeq          150
     135: aload_0
     136: invokevirtual #80                 // Method hasScannerId:()Z
     139: aload_2
     140: invokevirtual #80                 // Method hasScannerId:()Z
     143: if_icmpne     150
     146: iconst_1
     147: goto          151
     150: iconst_0
     151: istore_3
     152: aload_0
     153: invokevirtual #80                 // Method hasScannerId:()Z
     156: ifeq          181
     159: iload_3
     160: ifeq          179
     163: aload_0
     164: invokevirtual #81                 // Method getScannerId:()J
     167: aload_2
     168: invokevirtual #81                 // Method getScannerId:()J
     171: lcmp
     172: ifne          179
     175: iconst_1
     176: goto          180
     179: iconst_0
     180: istore_3
     181: iload_3
     182: ifeq          200
     185: aload_0
     186: invokevirtual #82                 // Method hasNumberOfRows:()Z
     189: aload_2
     190: invokevirtual #82                 // Method hasNumberOfRows:()Z
     193: if_icmpne     200
     196: iconst_1
     197: goto          201
     200: iconst_0
     201: istore_3
     202: aload_0
     203: invokevirtual #82                 // Method hasNumberOfRows:()Z
     206: ifeq          230
     209: iload_3
     210: ifeq          228
     213: aload_0
     214: invokevirtual #83                 // Method getNumberOfRows:()I
     217: aload_2
     218: invokevirtual #83                 // Method getNumberOfRows:()I
     221: if_icmpne     228
     224: iconst_1
     225: goto          229
     228: iconst_0
     229: istore_3
     230: iload_3
     231: ifeq          249
     234: aload_0
     235: invokevirtual #84                 // Method hasCloseScanner:()Z
     238: aload_2
     239: invokevirtual #84                 // Method hasCloseScanner:()Z
     242: if_icmpne     249
     245: iconst_1
     246: goto          250
     249: iconst_0
     250: istore_3
     251: aload_0
     252: invokevirtual #84                 // Method hasCloseScanner:()Z
     255: ifeq          279
     258: iload_3
     259: ifeq          277
     262: aload_0
     263: invokevirtual #85                 // Method getCloseScanner:()Z
     266: aload_2
     267: invokevirtual #85                 // Method getCloseScanner:()Z
     270: if_icmpne     277
     273: iconst_1
     274: goto          278
     277: iconst_0
     278: istore_3
     279: iload_3
     280: ifeq          298
     283: aload_0
     284: invokevirtual #86                 // Method hasNextCallSeq:()Z
     287: aload_2
     288: invokevirtual #86                 // Method hasNextCallSeq:()Z
     291: if_icmpne     298
     294: iconst_1
     295: goto          299
     298: iconst_0
     299: istore_3
     300: aload_0
     301: invokevirtual #86                 // Method hasNextCallSeq:()Z
     304: ifeq          329
     307: iload_3
     308: ifeq          327
     311: aload_0
     312: invokevirtual #87                 // Method getNextCallSeq:()J
     315: aload_2
     316: invokevirtual #87                 // Method getNextCallSeq:()J
     319: lcmp
     320: ifne          327
     323: iconst_1
     324: goto          328
     327: iconst_0
     328: istore_3
     329: iload_3
     330: ifeq          348
     333: aload_0
     334: invokevirtual #88                 // Method hasClientHandlesPartials:()Z
     337: aload_2
     338: invokevirtual #88                 // Method hasClientHandlesPartials:()Z
     341: if_icmpne     348
     344: iconst_1
     345: goto          349
     348: iconst_0
     349: istore_3
     350: aload_0
     351: invokevirtual #88                 // Method hasClientHandlesPartials:()Z
     354: ifeq          378
     357: iload_3
     358: ifeq          376
     361: aload_0
     362: invokevirtual #89                 // Method getClientHandlesPartials:()Z
     365: aload_2
     366: invokevirtual #89                 // Method getClientHandlesPartials:()Z
     369: if_icmpne     376
     372: iconst_1
     373: goto          377
     376: iconst_0
     377: istore_3
     378: iload_3
     379: ifeq          397
     382: aload_0
     383: invokevirtual #90                 // Method hasClientHandlesHeartbeats:()Z
     386: aload_2
     387: invokevirtual #90                 // Method hasClientHandlesHeartbeats:()Z
     390: if_icmpne     397
     393: iconst_1
     394: goto          398
     397: iconst_0
     398: istore_3
     399: aload_0
     400: invokevirtual #90                 // Method hasClientHandlesHeartbeats:()Z
     403: ifeq          427
     406: iload_3
     407: ifeq          425
     410: aload_0
     411: invokevirtual #91                 // Method getClientHandlesHeartbeats:()Z
     414: aload_2
     415: invokevirtual #91                 // Method getClientHandlesHeartbeats:()Z
     418: if_icmpne     425
     421: iconst_1
     422: goto          426
     425: iconst_0
     426: istore_3
     427: iload_3
     428: ifeq          446
     431: aload_0
     432: invokevirtual #92                 // Method hasTrackScanMetrics:()Z
     435: aload_2
     436: invokevirtual #92                 // Method hasTrackScanMetrics:()Z
     439: if_icmpne     446
     442: iconst_1
     443: goto          447
     446: iconst_0
     447: istore_3
     448: aload_0
     449: invokevirtual #92                 // Method hasTrackScanMetrics:()Z
     452: ifeq          476
     455: iload_3
     456: ifeq          474
     459: aload_0
     460: invokevirtual #93                 // Method getTrackScanMetrics:()Z
     463: aload_2
     464: invokevirtual #93                 // Method getTrackScanMetrics:()Z
     467: if_icmpne     474
     470: iconst_1
     471: goto          475
     474: iconst_0
     475: istore_3
     476: iload_3
     477: ifeq          495
     480: aload_0
     481: invokevirtual #94                 // Method hasRenew:()Z
     484: aload_2
     485: invokevirtual #94                 // Method hasRenew:()Z
     488: if_icmpne     495
     491: iconst_1
     492: goto          496
     495: iconst_0
     496: istore_3
     497: aload_0
     498: invokevirtual #94                 // Method hasRenew:()Z
     501: ifeq          525
     504: iload_3
     505: ifeq          523
     508: aload_0
     509: invokevirtual #95                 // Method getRenew:()Z
     512: aload_2
     513: invokevirtual #95                 // Method getRenew:()Z
     516: if_icmpne     523
     519: iconst_1
     520: goto          524
     523: iconst_0
     524: istore_3
     525: iload_3
     526: ifeq          544
     529: aload_0
     530: invokevirtual #96                 // Method hasLimitOfRows:()Z
     533: aload_2
     534: invokevirtual #96                 // Method hasLimitOfRows:()Z
     537: if_icmpne     544
     540: iconst_1
     541: goto          545
     544: iconst_0
     545: istore_3
     546: aload_0
     547: invokevirtual #96                 // Method hasLimitOfRows:()Z
     550: ifeq          574
     553: iload_3
     554: ifeq          572
     557: aload_0
     558: invokevirtual #97                 // Method getLimitOfRows:()I
     561: aload_2
     562: invokevirtual #97                 // Method getLimitOfRows:()I
     565: if_icmpne     572
     568: iconst_1
     569: goto          573
     572: iconst_0
     573: istore_3
     574: iload_3
     575: ifeq          596
     578: aload_0
     579: invokevirtual #69                 // Method getUnknownFields:()Lcom/google/protobuf/UnknownFieldSet;
     582: aload_2
     583: invokevirtual #69                 // Method getUnknownFields:()Lcom/google/protobuf/UnknownFieldSet;
     586: invokevirtual #98                 // Method com/google/protobuf/UnknownFieldSet.equals:(Ljava/lang/Object;)Z
     589: ifeq          596
     592: iconst_1
     593: goto          597
     596: iconst_0
     597: istore_3
     598: iload_3
     599: ireturn

  public int hashCode();
    Code:
       0: aload_0
       1: getfield      #19                 // Field memoizedHashCode:I
       4: ifeq          12
       7: aload_0
       8: getfield      #19                 // Field memoizedHashCode:I
      11: ireturn
      12: bipush        41
      14: istore_1
      15: bipush        19
      17: iload_1
      18: imul
      19: aload_0
      20: invokevirtual #99                 // Method getDescriptorForType:()Lcom/google/protobuf/Descriptors$Descriptor;
      23: invokevirtual #100                // Method java/lang/Object.hashCode:()I
      26: iadd
      27: istore_1
      28: aload_0
      29: invokevirtual #58                 // Method hasRegion:()Z
      32: ifeq          55
      35: bipush        37
      37: iload_1
      38: imul
      39: iconst_1
      40: iadd
      41: istore_1
      42: bipush        53
      44: iload_1
      45: imul
      46: aload_0
      47: invokevirtual #59                 // Method getRegion:()Lorg/apache/hadoop/hbase/protobuf/generated/HBaseProtos$RegionSpecifier;
      50: invokevirtual #101                // Method org/apache/hadoop/hbase/protobuf/generated/HBaseProtos$RegionSpecifier.hashCode:()I
      53: iadd
      54: istore_1
      55: aload_0
      56: invokevirtual #61                 // Method hasScan:()Z
      59: ifeq          82
      62: bipush        37
      64: iload_1
      65: imul
      66: iconst_2
      67: iadd
      68: istore_1
      69: bipush        53
      71: iload_1
      72: imul
      73: aload_0
      74: invokevirtual #62                 // Method getScan:()Lorg/apache/hadoop/hbase/protobuf/generated/ClientProtos$Scan;
      77: invokevirtual #102                // Method org/apache/hadoop/hbase/protobuf/generated/ClientProtos$Scan.hashCode:()I
      80: iadd
      81: istore_1
      82: aload_0
      83: invokevirtual #80                 // Method hasScannerId:()Z
      86: ifeq          109
      89: bipush        37
      91: iload_1
      92: imul
      93: iconst_3
      94: iadd
      95: istore_1
      96: bipush        53
      98: iload_1
      99: imul
     100: aload_0
     101: invokevirtual #81                 // Method getScannerId:()J
     104: invokestatic  #103                // Method hashLong:(J)I
     107: iadd
     108: istore_1
     109: aload_0
     110: invokevirtual #82                 // Method hasNumberOfRows:()Z
     113: ifeq          133
     116: bipush        37
     118: iload_1
     119: imul
     120: iconst_4
     121: iadd
     122: istore_1
     123: bipush        53
     125: iload_1
     126: imul
     127: aload_0
     128: invokevirtual #83                 // Method getNumberOfRows:()I
     131: iadd
     132: istore_1
     133: aload_0
     134: invokevirtual #84                 // Method hasCloseScanner:()Z
     137: ifeq          160
     140: bipush        37
     142: iload_1
     143: imul
     144: iconst_5
     145: iadd
     146: istore_1
     147: bipush        53
     149: iload_1
     150: imul
     151: aload_0
     152: invokevirtual #85                 // Method getCloseScanner:()Z
     155: invokestatic  #104                // Method hashBoolean:(Z)I
     158: iadd
     159: istore_1
     160: aload_0
     161: invokevirtual #86                 // Method hasNextCallSeq:()Z
     164: ifeq          188
     167: bipush        37
     169: iload_1
     170: imul
     171: bipush        6
     173: iadd
     174: istore_1
     175: bipush        53
     177: iload_1
     178: imul
     179: aload_0
     180: invokevirtual #87                 // Method getNextCallSeq:()J
     183: invokestatic  #103                // Method hashLong:(J)I
     186: iadd
     187: istore_1
     188: aload_0
     189: invokevirtual #88                 // Method hasClientHandlesPartials:()Z
     192: ifeq          216
     195: bipush        37
     197: iload_1
     198: imul
     199: bipush        7
     201: iadd
     202: istore_1
     203: bipush        53
     205: iload_1
     206: imul
     207: aload_0
     208: invokevirtual #89                 // Method getClientHandlesPartials:()Z
     211: invokestatic  #104                // Method hashBoolean:(Z)I
     214: iadd
     215: istore_1
     216: aload_0
     217: invokevirtual #90                 // Method hasClientHandlesHeartbeats:()Z
     220: ifeq          244
     223: bipush        37
     225: iload_1
     226: imul
     227: bipush        8
     229: iadd
     230: istore_1
     231: bipush        53
     233: iload_1
     234: imul
     235: aload_0
     236: invokevirtual #91                 // Method getClientHandlesHeartbeats:()Z
     239: invokestatic  #104                // Method hashBoolean:(Z)I
     242: iadd
     243: istore_1
     244: aload_0
     245: invokevirtual #92                 // Method hasTrackScanMetrics:()Z
     248: ifeq          272
     251: bipush        37
     253: iload_1
     254: imul
     255: bipush        9
     257: iadd
     258: istore_1
     259: bipush        53
     261: iload_1
     262: imul
     263: aload_0
     264: invokevirtual #93                 // Method getTrackScanMetrics:()Z
     267: invokestatic  #104                // Method hashBoolean:(Z)I
     270: iadd
     271: istore_1
     272: aload_0
     273: invokevirtual #94                 // Method hasRenew:()Z
     276: ifeq          300
     279: bipush        37
     281: iload_1
     282: imul
     283: bipush        10
     285: iadd
     286: istore_1
     287: bipush        53
     289: iload_1
     290: imul
     291: aload_0
     292: invokevirtual #95                 // Method getRenew:()Z
     295: invokestatic  #104                // Method hashBoolean:(Z)I
     298: iadd
     299: istore_1
     300: aload_0
     301: invokevirtual #96                 // Method hasLimitOfRows:()Z
     304: ifeq          325
     307: bipush        37
     309: iload_1
     310: imul
     311: bipush        11
     313: iadd
     314: istore_1
     315: bipush        53
     317: iload_1
     318: imul
     319: aload_0
     320: invokevirtual #97                 // Method getLimitOfRows:()I
     323: iadd
     324: istore_1
     325: bipush        29
     327: iload_1
     328: imul
     329: aload_0
     330: invokevirtual #69                 // Method getUnknownFields:()Lcom/google/protobuf/UnknownFieldSet;
     333: invokevirtual #105                // Method com/google/protobuf/UnknownFieldSet.hashCode:()I
     336: iadd
     337: istore_1
     338: aload_0
     339: iload_1
     340: putfield      #19                 // Field memoizedHashCode:I
     343: iload_1
     344: ireturn

  public static org.apache.hadoop.hbase.protobuf.generated.ClientProtos$ScanRequest parseFrom(com.google.protobuf.ByteString) throws com.google.protobuf.InvalidProtocolBufferException;
    Code:
       0: getstatic     #55                 // Field PARSER:Lcom/google/protobuf/Parser;
       3: aload_0
       4: invokeinterface #106,  2          // InterfaceMethod com/google/protobuf/Parser.parseFrom:(Lcom/google/protobuf/ByteString;)Ljava/lang/Object;
       9: checkcast     #52                 // class org/apache/hadoop/hbase/protobuf/generated/ClientProtos$ScanRequest
      12: areturn

  public static org.apache.hadoop.hbase.protobuf.generated.ClientProtos$ScanRequest parseFrom(com.google.protobuf.ByteString, com.google.protobuf.ExtensionRegistryLite) throws com.google.protobuf.InvalidProtocolBufferException;
    Code:
       0: getstatic     #55                 // Field PARSER:Lcom/google/protobuf/Parser;
       3: aload_0
       4: aload_1
       5: invokeinterface #107,  3          // InterfaceMethod com/google/protobuf/Parser.parseFrom:(Lcom/google/protobuf/ByteString;Lcom/google/protobuf/ExtensionRegistryLite;)Ljava/lang/Object;
      10: checkcast     #52                 // class org/apache/hadoop/hbase/protobuf/generated/ClientProtos$ScanRequest
      13: areturn

  public static org.apache.hadoop.hbase.protobuf.generated.ClientProtos$ScanRequest parseFrom(byte[]) throws com.google.protobuf.InvalidProtocolBufferException;
    Code:
       0: getstatic     #55                 // Field PARSER:Lcom/google/protobuf/Parser;
       3: aload_0
       4: invokeinterface #108,  2          // InterfaceMethod com/google/protobuf/Parser.parseFrom:([B)Ljava/lang/Object;
       9: checkcast     #52                 // class org/apache/hadoop/hbase/protobuf/generated/ClientProtos$ScanRequest
      12: areturn

  public static org.apache.hadoop.hbase.protobuf.generated.ClientProtos$ScanRequest parseFrom(byte[], com.google.protobuf.ExtensionRegistryLite) throws com.google.protobuf.InvalidProtocolBufferException;
    Code:
       0: getstatic     #55                 // Field PARSER:Lcom/google/protobuf/Parser;
       3: aload_0
       4: aload_1
       5: invokeinterface #109,  3          // InterfaceMethod com/google/protobuf/Parser.parseFrom:([BLcom/google/protobuf/ExtensionRegistryLite;)Ljava/lang/Object;
      10: checkcast     #52                 // class org/apache/hadoop/hbase/protobuf/generated/ClientProtos$ScanRequest
      13: areturn

  public static org.apache.hadoop.hbase.protobuf.generated.ClientProtos$ScanRequest parseFrom(java.io.InputStream) throws java.io.IOException;
    Code:
       0: getstatic     #55                 // Field PARSER:Lcom/google/protobuf/Parser;
       3: aload_0
       4: invokeinterface #110,  2          // InterfaceMethod com/google/protobuf/Parser.parseFrom:(Ljava/io/InputStream;)Ljava/lang/Object;
       9: checkcast     #52                 // class org/apache/hadoop/hbase/protobuf/generated/ClientProtos$ScanRequest
      12: areturn

  public static org.apache.hadoop.hbase.protobuf.generated.ClientProtos$ScanRequest parseFrom(java.io.InputStream, com.google.protobuf.ExtensionRegistryLite) throws java.io.IOException;
    Code:
       0: getstatic     #55                 // Field PARSER:Lcom/google/protobuf/Parser;
       3: aload_0
       4: aload_1
       5: invokeinterface #111,  3          // InterfaceMethod com/google/protobuf/Parser.parseFrom:(Ljava/io/InputStream;Lcom/google/protobuf/ExtensionRegistryLite;)Ljava/lang/Object;
      10: checkcast     #52                 // class org/apache/hadoop/hbase/protobuf/generated/ClientProtos$ScanRequest
      13: areturn

  public static org.apache.hadoop.hbase.protobuf.generated.ClientProtos$ScanRequest parseDelimitedFrom(java.io.InputStream) throws java.io.IOException;
    Code:
       0: getstatic     #55                 // Field PARSER:Lcom/google/protobuf/Parser;
       3: aload_0
       4: invokeinterface #112,  2          // InterfaceMethod com/google/protobuf/Parser.parseDelimitedFrom:(Ljava/io/InputStream;)Ljava/lang/Object;
       9: checkcast     #52                 // class org/apache/hadoop/hbase/protobuf/generated/ClientProtos$ScanRequest
      12: areturn

  public static org.apache.hadoop.hbase.protobuf.generated.ClientProtos$ScanRequest parseDelimitedFrom(java.io.InputStream, com.google.protobuf.ExtensionRegistryLite) throws java.io.IOException;
    Code:
       0: getstatic     #55                 // Field PARSER:Lcom/google/protobuf/Parser;
       3: aload_0
       4: aload_1
       5: invokeinterface #113,  3          // InterfaceMethod com/google/protobuf/Parser.parseDelimitedFrom:(Ljava/io/InputStream;Lcom/google/protobuf/ExtensionRegistryLite;)Ljava/lang/Object;
      10: checkcast     #52                 // class org/apache/hadoop/hbase/protobuf/generated/ClientProtos$ScanRequest
      13: areturn

  public static org.apache.hadoop.hbase.protobuf.generated.ClientProtos$ScanRequest parseFrom(com.google.protobuf.CodedInputStream) throws java.io.IOException;
    Code:
       0: getstatic     #55                 // Field PARSER:Lcom/google/protobuf/Parser;
       3: aload_0
       4: invokeinterface #114,  2          // InterfaceMethod com/google/protobuf/Parser.parseFrom:(Lcom/google/protobuf/CodedInputStream;)Ljava/lang/Object;
       9: checkcast     #52                 // class org/apache/hadoop/hbase/protobuf/generated/ClientProtos$ScanRequest
      12: areturn

  public static org.apache.hadoop.hbase.protobuf.generated.ClientProtos$ScanRequest parseFrom(com.google.protobuf.CodedInputStream, com.google.protobuf.ExtensionRegistryLite) throws java.io.IOException;
    Code:
       0: getstatic     #55                 // Field PARSER:Lcom/google/protobuf/Parser;
       3: aload_0
       4: aload_1
       5: invokeinterface #115,  3          // InterfaceMethod com/google/protobuf/Parser.parseFrom:(Lcom/google/protobuf/CodedInputStream;Lcom/google/protobuf/ExtensionRegistryLite;)Ljava/lang/Object;
      10: checkcast     #52                 // class org/apache/hadoop/hbase/protobuf/generated/ClientProtos$ScanRequest
      13: areturn

  public static org.apache.hadoop.hbase.protobuf.generated.ClientProtos$ScanRequest$Builder newBuilder();
    Code:
       0: invokestatic  #116                // Method org/apache/hadoop/hbase/protobuf/generated/ClientProtos$ScanRequest$Builder.access$20200:()Lorg/apache/hadoop/hbase/protobuf/generated/ClientProtos$ScanRequest$Builder;
       3: areturn

  public org.apache.hadoop.hbase.protobuf.generated.ClientProtos$ScanRequest$Builder newBuilderForType();
    Code:
       0: invokestatic  #117                // Method newBuilder:()Lorg/apache/hadoop/hbase/protobuf/generated/ClientProtos$ScanRequest$Builder;
       3: areturn

  public static org.apache.hadoop.hbase.protobuf.generated.ClientProtos$ScanRequest$Builder newBuilder(org.apache.hadoop.hbase.protobuf.generated.ClientProtos$ScanRequest);
    Code:
       0: invokestatic  #117                // Method newBuilder:()Lorg/apache/hadoop/hbase/protobuf/generated/ClientProtos$ScanRequest$Builder;
       3: aload_0
       4: invokevirtual #118                // Method org/apache/hadoop/hbase/protobuf/generated/ClientProtos$ScanRequest$Builder.mergeFrom:(Lorg/apache/hadoop/hbase/protobuf/generated/ClientProtos$ScanRequest;)Lorg/apache/hadoop/hbase/protobuf/generated/ClientProtos$ScanRequest$Builder;
       7: areturn

  public org.apache.hadoop.hbase.protobuf.generated.ClientProtos$ScanRequest$Builder toBuilder();
    Code:
       0: aload_0
       1: invokestatic  #119                // Method newBuilder:(Lorg/apache/hadoop/hbase/protobuf/generated/ClientProtos$ScanRequest;)Lorg/apache/hadoop/hbase/protobuf/generated/ClientProtos$ScanRequest$Builder;
       4: areturn

  protected org.apache.hadoop.hbase.protobuf.generated.ClientProtos$ScanRequest$Builder newBuilderForType(com.google.protobuf.GeneratedMessage$BuilderParent);
    Code:
       0: new           #53                 // class org/apache/hadoop/hbase/protobuf/generated/ClientProtos$ScanRequest$Builder
       3: dup
       4: aload_1
       5: aconst_null
       6: invokespecial #120                // Method org/apache/hadoop/hbase/protobuf/generated/ClientProtos$ScanRequest$Builder."<init>":(Lcom/google/protobuf/GeneratedMessage$BuilderParent;Lorg/apache/hadoop/hbase/protobuf/generated/ClientProtos$1;)V
       9: astore_2
      10: aload_2
      11: areturn

  protected com.google.protobuf.Message$Builder newBuilderForType(com.google.protobuf.GeneratedMessage$BuilderParent);
    Code:
       0: aload_0
       1: aload_1
       2: invokevirtual #121                // Method newBuilderForType:(Lcom/google/protobuf/GeneratedMessage$BuilderParent;)Lorg/apache/hadoop/hbase/protobuf/generated/ClientProtos$ScanRequest$Builder;
       5: areturn

  public com.google.protobuf.Message$Builder toBuilder();
    Code:
       0: aload_0
       1: invokevirtual #122                // Method toBuilder:()Lorg/apache/hadoop/hbase/protobuf/generated/ClientProtos$ScanRequest$Builder;
       4: areturn

  public com.google.protobuf.Message$Builder newBuilderForType();
    Code:
       0: aload_0
       1: invokevirtual #123                // Method newBuilderForType:()Lorg/apache/hadoop/hbase/protobuf/generated/ClientProtos$ScanRequest$Builder;
       4: areturn

  public com.google.protobuf.MessageLite$Builder toBuilder();
    Code:
       0: aload_0
       1: invokevirtual #122                // Method toBuilder:()Lorg/apache/hadoop/hbase/protobuf/generated/ClientProtos$ScanRequest$Builder;
       4: areturn

  public com.google.protobuf.MessageLite$Builder newBuilderForType();
    Code:
       0: aload_0
       1: invokevirtual #123                // Method newBuilderForType:()Lorg/apache/hadoop/hbase/protobuf/generated/ClientProtos$ScanRequest$Builder;
       4: areturn

  public com.google.protobuf.MessageLite getDefaultInstanceForType();
    Code:
       0: aload_0
       1: invokevirtual #124                // Method getDefaultInstanceForType:()Lorg/apache/hadoop/hbase/protobuf/generated/ClientProtos$ScanRequest;
       4: areturn

  public com.google.protobuf.Message getDefaultInstanceForType();
    Code:
       0: aload_0
       1: invokevirtual #124                // Method getDefaultInstanceForType:()Lorg/apache/hadoop/hbase/protobuf/generated/ClientProtos$ScanRequest;
       4: areturn

  org.apache.hadoop.hbase.protobuf.generated.ClientProtos$ScanRequest(com.google.protobuf.CodedInputStream, com.google.protobuf.ExtensionRegistryLite, org.apache.hadoop.hbase.protobuf.generated.ClientProtos$1) throws com.google.protobuf.InvalidProtocolBufferException;
    Code:
       0: aload_0
       1: aload_1
       2: aload_2
       3: invokespecial #15                 // Method "<init>":(Lcom/google/protobuf/CodedInputStream;Lcom/google/protobuf/ExtensionRegistryLite;)V
       6: return

  static boolean access$20400();
    Code:
       0: getstatic     #14                 // Field alwaysUseFieldBuilders:Z
       3: ireturn

  org.apache.hadoop.hbase.protobuf.generated.ClientProtos$ScanRequest(com.google.protobuf.GeneratedMessage$Builder, org.apache.hadoop.hbase.protobuf.generated.ClientProtos$1);
    Code:
       0: aload_0
       1: aload_1
       2: invokespecial #13                 // Method "<init>":(Lcom/google/protobuf/GeneratedMessage$Builder;)V
       5: return

  static org.apache.hadoop.hbase.protobuf.generated.HBaseProtos$RegionSpecifier access$20602(org.apache.hadoop.hbase.protobuf.generated.ClientProtos$ScanRequest, org.apache.hadoop.hbase.protobuf.generated.HBaseProtos$RegionSpecifier);
    Code:
       0: aload_0
       1: aload_1
       2: dup_x1
       3: putfield      #12                 // Field region_:Lorg/apache/hadoop/hbase/protobuf/generated/HBaseProtos$RegionSpecifier;
       6: areturn

  static org.apache.hadoop.hbase.protobuf.generated.ClientProtos$Scan access$20702(org.apache.hadoop.hbase.protobuf.generated.ClientProtos$ScanRequest, org.apache.hadoop.hbase.protobuf.generated.ClientProtos$Scan);
    Code:
       0: aload_0
       1: aload_1
       2: dup_x1
       3: putfield      #11                 // Field scan_:Lorg/apache/hadoop/hbase/protobuf/generated/ClientProtos$Scan;
       6: areturn

  static long access$20802(org.apache.hadoop.hbase.protobuf.generated.ClientProtos$ScanRequest, long);
    Code:
       0: aload_0
       1: lload_1
       2: dup2_x1
       3: putfield      #10                 // Field scannerId_:J
       6: lreturn

  static int access$20902(org.apache.hadoop.hbase.protobuf.generated.ClientProtos$ScanRequest, int);
    Code:
       0: aload_0
       1: iload_1
       2: dup_x1
       3: putfield      #9                  // Field numberOfRows_:I
       6: ireturn

  static boolean access$21002(org.apache.hadoop.hbase.protobuf.generated.ClientProtos$ScanRequest, boolean);
    Code:
       0: aload_0
       1: iload_1
       2: dup_x1
       3: putfield      #8                  // Field closeScanner_:Z
       6: ireturn

  static long access$21102(org.apache.hadoop.hbase.protobuf.generated.ClientProtos$ScanRequest, long);
    Code:
       0: aload_0
       1: lload_1
       2: dup2_x1
       3: putfield      #7                  // Field nextCallSeq_:J
       6: lreturn

  static boolean access$21202(org.apache.hadoop.hbase.protobuf.generated.ClientProtos$ScanRequest, boolean);
    Code:
       0: aload_0
       1: iload_1
       2: dup_x1
       3: putfield      #6                  // Field clientHandlesPartials_:Z
       6: ireturn

  static boolean access$21302(org.apache.hadoop.hbase.protobuf.generated.ClientProtos$ScanRequest, boolean);
    Code:
       0: aload_0
       1: iload_1
       2: dup_x1
       3: putfield      #5                  // Field clientHandlesHeartbeats_:Z
       6: ireturn

  static boolean access$21402(org.apache.hadoop.hbase.protobuf.generated.ClientProtos$ScanRequest, boolean);
    Code:
       0: aload_0
       1: iload_1
       2: dup_x1
       3: putfield      #4                  // Field trackScanMetrics_:Z
       6: ireturn

  static boolean access$21502(org.apache.hadoop.hbase.protobuf.generated.ClientProtos$ScanRequest, boolean);
    Code:
       0: aload_0
       1: iload_1
       2: dup_x1
       3: putfield      #3                  // Field renew_:Z
       6: ireturn

  static int access$21602(org.apache.hadoop.hbase.protobuf.generated.ClientProtos$ScanRequest, int);
    Code:
       0: aload_0
       1: iload_1
       2: dup_x1
       3: putfield      #2                  // Field limitOfRows_:I
       6: ireturn

  static int access$21702(org.apache.hadoop.hbase.protobuf.generated.ClientProtos$ScanRequest, int);
    Code:
       0: aload_0
       1: iload_1
       2: dup_x1
       3: putfield      #1                  // Field bitField0_:I
       6: ireturn

  static {};
    Code:
       0: new           #125                // class org/apache/hadoop/hbase/protobuf/generated/ClientProtos$ScanRequest$1
       3: dup
       4: invokespecial #126                // Method org/apache/hadoop/hbase/protobuf/generated/ClientProtos$ScanRequest$1."<init>":()V
       7: putstatic     #55                 // Field PARSER:Lcom/google/protobuf/Parser;
      10: new           #52                 // class org/apache/hadoop/hbase/protobuf/generated/ClientProtos$ScanRequest
      13: dup
      14: iconst_1
      15: invokespecial #127                // Method "<init>":(Z)V
      18: putstatic     #24                 // Field defaultInstance:Lorg/apache/hadoop/hbase/protobuf/generated/ClientProtos$ScanRequest;
      21: getstatic     #24                 // Field defaultInstance:Lorg/apache/hadoop/hbase/protobuf/generated/ClientProtos$ScanRequest;
      24: invokespecial #25                 // Method initFields:()V
      27: return
}
