Compiled from "ClientProtos.java"
public final class org.apache.hadoop.hbase.protobuf.generated.ClientProtos$ScanResponse$Builder extends com.google.protobuf.GeneratedMessage$Builder<org.apache.hadoop.hbase.protobuf.generated.ClientProtos$ScanResponse$Builder> implements org.apache.hadoop.hbase.protobuf.generated.ClientProtos$ScanResponseOrBuilder {
  public static final com.google.protobuf.Descriptors$Descriptor getDescriptor();
    Code:
       0: invokestatic  #3                  // Method org/apache/hadoop/hbase/protobuf/generated/ClientProtos.access$22700:()Lcom/google/protobuf/Descriptors$Descriptor;
       3: areturn

  protected com.google.protobuf.GeneratedMessage$FieldAccessorTable internalGetFieldAccessorTable();
    Code:
       0: invokestatic  #4                  // Method org/apache/hadoop/hbase/protobuf/generated/ClientProtos.access$22800:()Lcom/google/protobuf/GeneratedMessage$FieldAccessorTable;
       3: ldc           #5                  // class org/apache/hadoop/hbase/protobuf/generated/ClientProtos$ScanResponse
       5: ldc           #6                  // class org/apache/hadoop/hbase/protobuf/generated/ClientProtos$ScanResponse$Builder
       7: invokevirtual #7                  // Method com/google/protobuf/GeneratedMessage$FieldAccessorTable.ensureFieldAccessorsInitialized:(Ljava/lang/Class;Ljava/lang/Class;)Lcom/google/protobuf/GeneratedMessage$FieldAccessorTable;
      10: areturn

  public org.apache.hadoop.hbase.protobuf.generated.ClientProtos$ScanResponse$Builder clear();
    Code:
       0: aload_0
       1: invokespecial #24                 // Method com/google/protobuf/GeneratedMessage$Builder.clear:()Lcom/google/protobuf/GeneratedMessage$Builder;
       4: pop
       5: aload_0
       6: invokestatic  #9                  // Method java/util/Collections.emptyList:()Ljava/util/List;
       9: putfield      #10                 // Field cellsPerResult_:Ljava/util/List;
      12: aload_0
      13: aload_0
      14: getfield      #25                 // Field bitField0_:I
      17: bipush        -2
      19: iand
      20: putfield      #25                 // Field bitField0_:I
      23: aload_0
      24: lconst_0
      25: putfield      #26                 // Field scannerId_:J
      28: aload_0
      29: aload_0
      30: getfield      #25                 // Field bitField0_:I
      33: bipush        -3
      35: iand
      36: putfield      #25                 // Field bitField0_:I
      39: aload_0
      40: iconst_0
      41: putfield      #27                 // Field moreResults_:Z
      44: aload_0
      45: aload_0
      46: getfield      #25                 // Field bitField0_:I
      49: bipush        -5
      51: iand
      52: putfield      #25                 // Field bitField0_:I
      55: aload_0
      56: iconst_0
      57: putfield      #28                 // Field ttl_:I
      60: aload_0
      61: aload_0
      62: getfield      #25                 // Field bitField0_:I
      65: bipush        -9
      67: iand
      68: putfield      #25                 // Field bitField0_:I
      71: aload_0
      72: getfield      #29                 // Field resultsBuilder_:Lcom/google/protobuf/RepeatedFieldBuilder;
      75: ifnonnull     99
      78: aload_0
      79: invokestatic  #9                  // Method java/util/Collections.emptyList:()Ljava/util/List;
      82: putfield      #11                 // Field results_:Ljava/util/List;
      85: aload_0
      86: aload_0
      87: getfield      #25                 // Field bitField0_:I
      90: bipush        -17
      92: iand
      93: putfield      #25                 // Field bitField0_:I
      96: goto          106
      99: aload_0
     100: getfield      #29                 // Field resultsBuilder_:Lcom/google/protobuf/RepeatedFieldBuilder;
     103: invokevirtual #30                 // Method com/google/protobuf/RepeatedFieldBuilder.clear:()V
     106: aload_0
     107: iconst_0
     108: putfield      #31                 // Field stale_:Z
     111: aload_0
     112: aload_0
     113: getfield      #25                 // Field bitField0_:I
     116: bipush        -33
     118: iand
     119: putfield      #25                 // Field bitField0_:I
     122: aload_0
     123: invokestatic  #9                  // Method java/util/Collections.emptyList:()Ljava/util/List;
     126: putfield      #12                 // Field partialFlagPerResult_:Ljava/util/List;
     129: aload_0
     130: aload_0
     131: getfield      #25                 // Field bitField0_:I
     134: bipush        -65
     136: iand
     137: putfield      #25                 // Field bitField0_:I
     140: aload_0
     141: iconst_0
     142: putfield      #32                 // Field moreResultsInRegion_:Z
     145: aload_0
     146: aload_0
     147: getfield      #25                 // Field bitField0_:I
     150: sipush        -129
     153: iand
     154: putfield      #25                 // Field bitField0_:I
     157: aload_0
     158: iconst_0
     159: putfield      #33                 // Field heartbeatMessage_:Z
     162: aload_0
     163: aload_0
     164: getfield      #25                 // Field bitField0_:I
     167: sipush        -257
     170: iand
     171: putfield      #25                 // Field bitField0_:I
     174: aload_0
     175: getfield      #34                 // Field scanMetricsBuilder_:Lcom/google/protobuf/SingleFieldBuilder;
     178: ifnonnull     191
     181: aload_0
     182: invokestatic  #13                 // Method org/apache/hadoop/hbase/protobuf/generated/MapReduceProtos$ScanMetrics.getDefaultInstance:()Lorg/apache/hadoop/hbase/protobuf/generated/MapReduceProtos$ScanMetrics;
     185: putfield      #14                 // Field scanMetrics_:Lorg/apache/hadoop/hbase/protobuf/generated/MapReduceProtos$ScanMetrics;
     188: goto          199
     191: aload_0
     192: getfield      #34                 // Field scanMetricsBuilder_:Lcom/google/protobuf/SingleFieldBuilder;
     195: invokevirtual #35                 // Method com/google/protobuf/SingleFieldBuilder.clear:()Lcom/google/protobuf/SingleFieldBuilder;
     198: pop
     199: aload_0
     200: aload_0
     201: getfield      #25                 // Field bitField0_:I
     204: sipush        -513
     207: iand
     208: putfield      #25                 // Field bitField0_:I
     211: aload_0
     212: lconst_0
     213: putfield      #36                 // Field mvccReadPoint_:J
     216: aload_0
     217: aload_0
     218: getfield      #25                 // Field bitField0_:I
     221: sipush        -1025
     224: iand
     225: putfield      #25                 // Field bitField0_:I
     228: aload_0
     229: getfield      #37                 // Field cursorBuilder_:Lcom/google/protobuf/SingleFieldBuilder;
     232: ifnonnull     245
     235: aload_0
     236: invokestatic  #15                 // Method org/apache/hadoop/hbase/protobuf/generated/ClientProtos$Cursor.getDefaultInstance:()Lorg/apache/hadoop/hbase/protobuf/generated/ClientProtos$Cursor;
     239: putfield      #16                 // Field cursor_:Lorg/apache/hadoop/hbase/protobuf/generated/ClientProtos$Cursor;
     242: goto          253
     245: aload_0
     246: getfield      #37                 // Field cursorBuilder_:Lcom/google/protobuf/SingleFieldBuilder;
     249: invokevirtual #35                 // Method com/google/protobuf/SingleFieldBuilder.clear:()Lcom/google/protobuf/SingleFieldBuilder;
     252: pop
     253: aload_0
     254: aload_0
     255: getfield      #25                 // Field bitField0_:I
     258: sipush        -2049
     261: iand
     262: putfield      #25                 // Field bitField0_:I
     265: aload_0
     266: areturn

  public org.apache.hadoop.hbase.protobuf.generated.ClientProtos$ScanResponse$Builder clone();
    Code:
       0: invokestatic  #2                  // Method create:()Lorg/apache/hadoop/hbase/protobuf/generated/ClientProtos$ScanResponse$Builder;
       3: aload_0
       4: invokevirtual #38                 // Method buildPartial:()Lorg/apache/hadoop/hbase/protobuf/generated/ClientProtos$ScanResponse;
       7: invokevirtual #39                 // Method mergeFrom:(Lorg/apache/hadoop/hbase/protobuf/generated/ClientProtos$ScanResponse;)Lorg/apache/hadoop/hbase/protobuf/generated/ClientProtos$ScanResponse$Builder;
      10: areturn

  public com.google.protobuf.Descriptors$Descriptor getDescriptorForType();
    Code:
       0: invokestatic  #3                  // Method org/apache/hadoop/hbase/protobuf/generated/ClientProtos.access$22700:()Lcom/google/protobuf/Descriptors$Descriptor;
       3: areturn

  public org.apache.hadoop.hbase.protobuf.generated.ClientProtos$ScanResponse getDefaultInstanceForType();
    Code:
       0: invokestatic  #40                 // Method org/apache/hadoop/hbase/protobuf/generated/ClientProtos$ScanResponse.getDefaultInstance:()Lorg/apache/hadoop/hbase/protobuf/generated/ClientProtos$ScanResponse;
       3: areturn

  public org.apache.hadoop.hbase.protobuf.generated.ClientProtos$ScanResponse build();
    Code:
       0: aload_0
       1: invokevirtual #38                 // Method buildPartial:()Lorg/apache/hadoop/hbase/protobuf/generated/ClientProtos$ScanResponse;
       4: astore_1
       5: aload_1
       6: invokevirtual #41                 // Method org/apache/hadoop/hbase/protobuf/generated/ClientProtos$ScanResponse.isInitialized:()Z
       9: ifne          17
      12: aload_1
      13: invokestatic  #42                 // Method newUninitializedMessageException:(Lcom/google/protobuf/Message;)Lcom/google/protobuf/UninitializedMessageException;
      16: athrow
      17: aload_1
      18: areturn

  public org.apache.hadoop.hbase.protobuf.generated.ClientProtos$ScanResponse buildPartial();
    Code:
       0: new           #5                  // class org/apache/hadoop/hbase/protobuf/generated/ClientProtos$ScanResponse
       3: dup
       4: aload_0
       5: aconst_null
       6: invokespecial #43                 // Method org/apache/hadoop/hbase/protobuf/generated/ClientProtos$ScanResponse."<init>":(Lcom/google/protobuf/GeneratedMessage$Builder;Lorg/apache/hadoop/hbase/protobuf/generated/ClientProtos$1;)V
       9: astore_1
      10: aload_0
      11: getfield      #25                 // Field bitField0_:I
      14: istore_2
      15: iconst_0
      16: istore_3
      17: aload_0
      18: getfield      #25                 // Field bitField0_:I
      21: iconst_1
      22: iand
      23: iconst_1
      24: if_icmpne     49
      27: aload_0
      28: aload_0
      29: getfield      #10                 // Field cellsPerResult_:Ljava/util/List;
      32: invokestatic  #44                 // Method java/util/Collections.unmodifiableList:(Ljava/util/List;)Ljava/util/List;
      35: putfield      #10                 // Field cellsPerResult_:Ljava/util/List;
      38: aload_0
      39: aload_0
      40: getfield      #25                 // Field bitField0_:I
      43: bipush        -2
      45: iand
      46: putfield      #25                 // Field bitField0_:I
      49: aload_1
      50: aload_0
      51: getfield      #10                 // Field cellsPerResult_:Ljava/util/List;
      54: invokestatic  #45                 // Method org/apache/hadoop/hbase/protobuf/generated/ClientProtos$ScanResponse.access$23402:(Lorg/apache/hadoop/hbase/protobuf/generated/ClientProtos$ScanResponse;Ljava/util/List;)Ljava/util/List;
      57: pop
      58: iload_2
      59: iconst_2
      60: iand
      61: iconst_2
      62: if_icmpne     69
      65: iload_3
      66: iconst_1
      67: ior
      68: istore_3
      69: aload_1
      70: aload_0
      71: getfield      #26                 // Field scannerId_:J
      74: invokestatic  #46                 // Method org/apache/hadoop/hbase/protobuf/generated/ClientProtos$ScanResponse.access$23502:(Lorg/apache/hadoop/hbase/protobuf/generated/ClientProtos$ScanResponse;J)J
      77: pop2
      78: iload_2
      79: iconst_4
      80: iand
      81: iconst_4
      82: if_icmpne     89
      85: iload_3
      86: iconst_2
      87: ior
      88: istore_3
      89: aload_1
      90: aload_0
      91: getfield      #27                 // Field moreResults_:Z
      94: invokestatic  #47                 // Method org/apache/hadoop/hbase/protobuf/generated/ClientProtos$ScanResponse.access$23602:(Lorg/apache/hadoop/hbase/protobuf/generated/ClientProtos$ScanResponse;Z)Z
      97: pop
      98: iload_2
      99: bipush        8
     101: iand
     102: bipush        8
     104: if_icmpne     111
     107: iload_3
     108: iconst_4
     109: ior
     110: istore_3
     111: aload_1
     112: aload_0
     113: getfield      #28                 // Field ttl_:I
     116: invokestatic  #48                 // Method org/apache/hadoop/hbase/protobuf/generated/ClientProtos$ScanResponse.access$23702:(Lorg/apache/hadoop/hbase/protobuf/generated/ClientProtos$ScanResponse;I)I
     119: pop
     120: aload_0
     121: getfield      #29                 // Field resultsBuilder_:Lcom/google/protobuf/RepeatedFieldBuilder;
     124: ifnonnull     173
     127: aload_0
     128: getfield      #25                 // Field bitField0_:I
     131: bipush        16
     133: iand
     134: bipush        16
     136: if_icmpne     161
     139: aload_0
     140: aload_0
     141: getfield      #11                 // Field results_:Ljava/util/List;
     144: invokestatic  #44                 // Method java/util/Collections.unmodifiableList:(Ljava/util/List;)Ljava/util/List;
     147: putfield      #11                 // Field results_:Ljava/util/List;
     150: aload_0
     151: aload_0
     152: getfield      #25                 // Field bitField0_:I
     155: bipush        -17
     157: iand
     158: putfield      #25                 // Field bitField0_:I
     161: aload_1
     162: aload_0
     163: getfield      #11                 // Field results_:Ljava/util/List;
     166: invokestatic  #49                 // Method org/apache/hadoop/hbase/protobuf/generated/ClientProtos$ScanResponse.access$23802:(Lorg/apache/hadoop/hbase/protobuf/generated/ClientProtos$ScanResponse;Ljava/util/List;)Ljava/util/List;
     169: pop
     170: goto          185
     173: aload_1
     174: aload_0
     175: getfield      #29                 // Field resultsBuilder_:Lcom/google/protobuf/RepeatedFieldBuilder;
     178: invokevirtual #50                 // Method com/google/protobuf/RepeatedFieldBuilder.build:()Ljava/util/List;
     181: invokestatic  #49                 // Method org/apache/hadoop/hbase/protobuf/generated/ClientProtos$ScanResponse.access$23802:(Lorg/apache/hadoop/hbase/protobuf/generated/ClientProtos$ScanResponse;Ljava/util/List;)Ljava/util/List;
     184: pop
     185: iload_2
     186: bipush        32
     188: iand
     189: bipush        32
     191: if_icmpne     199
     194: iload_3
     195: bipush        8
     197: ior
     198: istore_3
     199: aload_1
     200: aload_0
     201: getfield      #31                 // Field stale_:Z
     204: invokestatic  #51                 // Method org/apache/hadoop/hbase/protobuf/generated/ClientProtos$ScanResponse.access$23902:(Lorg/apache/hadoop/hbase/protobuf/generated/ClientProtos$ScanResponse;Z)Z
     207: pop
     208: aload_0
     209: getfield      #25                 // Field bitField0_:I
     212: bipush        64
     214: iand
     215: bipush        64
     217: if_icmpne     242
     220: aload_0
     221: aload_0
     222: getfield      #12                 // Field partialFlagPerResult_:Ljava/util/List;
     225: invokestatic  #44                 // Method java/util/Collections.unmodifiableList:(Ljava/util/List;)Ljava/util/List;
     228: putfield      #12                 // Field partialFlagPerResult_:Ljava/util/List;
     231: aload_0
     232: aload_0
     233: getfield      #25                 // Field bitField0_:I
     236: bipush        -65
     238: iand
     239: putfield      #25                 // Field bitField0_:I
     242: aload_1
     243: aload_0
     244: getfield      #12                 // Field partialFlagPerResult_:Ljava/util/List;
     247: invokestatic  #52                 // Method org/apache/hadoop/hbase/protobuf/generated/ClientProtos$ScanResponse.access$24002:(Lorg/apache/hadoop/hbase/protobuf/generated/ClientProtos$ScanResponse;Ljava/util/List;)Ljava/util/List;
     250: pop
     251: iload_2
     252: sipush        128
     255: iand
     256: sipush        128
     259: if_icmpne     267
     262: iload_3
     263: bipush        16
     265: ior
     266: istore_3
     267: aload_1
     268: aload_0
     269: getfield      #32                 // Field moreResultsInRegion_:Z
     272: invokestatic  #53                 // Method org/apache/hadoop/hbase/protobuf/generated/ClientProtos$ScanResponse.access$24102:(Lorg/apache/hadoop/hbase/protobuf/generated/ClientProtos$ScanResponse;Z)Z
     275: pop
     276: iload_2
     277: sipush        256
     280: iand
     281: sipush        256
     284: if_icmpne     292
     287: iload_3
     288: bipush        32
     290: ior
     291: istore_3
     292: aload_1
     293: aload_0
     294: getfield      #33                 // Field heartbeatMessage_:Z
     297: invokestatic  #54                 // Method org/apache/hadoop/hbase/protobuf/generated/ClientProtos$ScanResponse.access$24202:(Lorg/apache/hadoop/hbase/protobuf/generated/ClientProtos$ScanResponse;Z)Z
     300: pop
     301: iload_2
     302: sipush        512
     305: iand
     306: sipush        512
     309: if_icmpne     317
     312: iload_3
     313: bipush        64
     315: ior
     316: istore_3
     317: aload_0
     318: getfield      #34                 // Field scanMetricsBuilder_:Lcom/google/protobuf/SingleFieldBuilder;
     321: ifnonnull     336
     324: aload_1
     325: aload_0
     326: getfield      #14                 // Field scanMetrics_:Lorg/apache/hadoop/hbase/protobuf/generated/MapReduceProtos$ScanMetrics;
     329: invokestatic  #55                 // Method org/apache/hadoop/hbase/protobuf/generated/ClientProtos$ScanResponse.access$24302:(Lorg/apache/hadoop/hbase/protobuf/generated/ClientProtos$ScanResponse;Lorg/apache/hadoop/hbase/protobuf/generated/MapReduceProtos$ScanMetrics;)Lorg/apache/hadoop/hbase/protobuf/generated/MapReduceProtos$ScanMetrics;
     332: pop
     333: goto          351
     336: aload_1
     337: aload_0
     338: getfield      #34                 // Field scanMetricsBuilder_:Lcom/google/protobuf/SingleFieldBuilder;
     341: invokevirtual #56                 // Method com/google/protobuf/SingleFieldBuilder.build:()Lcom/google/protobuf/GeneratedMessage;
     344: checkcast     #57                 // class org/apache/hadoop/hbase/protobuf/generated/MapReduceProtos$ScanMetrics
     347: invokestatic  #55                 // Method org/apache/hadoop/hbase/protobuf/generated/ClientProtos$ScanResponse.access$24302:(Lorg/apache/hadoop/hbase/protobuf/generated/ClientProtos$ScanResponse;Lorg/apache/hadoop/hbase/protobuf/generated/MapReduceProtos$ScanMetrics;)Lorg/apache/hadoop/hbase/protobuf/generated/MapReduceProtos$ScanMetrics;
     350: pop
     351: iload_2
     352: sipush        1024
     355: iand
     356: sipush        1024
     359: if_icmpne     368
     362: iload_3
     363: sipush        128
     366: ior
     367: istore_3
     368: aload_1
     369: aload_0
     370: getfield      #36                 // Field mvccReadPoint_:J
     373: invokestatic  #58                 // Method org/apache/hadoop/hbase/protobuf/generated/ClientProtos$ScanResponse.access$24402:(Lorg/apache/hadoop/hbase/protobuf/generated/ClientProtos$ScanResponse;J)J
     376: pop2
     377: iload_2
     378: sipush        2048
     381: iand
     382: sipush        2048
     385: if_icmpne     394
     388: iload_3
     389: sipush        256
     392: ior
     393: istore_3
     394: aload_0
     395: getfield      #37                 // Field cursorBuilder_:Lcom/google/protobuf/SingleFieldBuilder;
     398: ifnonnull     413
     401: aload_1
     402: aload_0
     403: getfield      #16                 // Field cursor_:Lorg/apache/hadoop/hbase/protobuf/generated/ClientProtos$Cursor;
     406: invokestatic  #59                 // Method org/apache/hadoop/hbase/protobuf/generated/ClientProtos$ScanResponse.access$24502:(Lorg/apache/hadoop/hbase/protobuf/generated/ClientProtos$ScanResponse;Lorg/apache/hadoop/hbase/protobuf/generated/ClientProtos$Cursor;)Lorg/apache/hadoop/hbase/protobuf/generated/ClientProtos$Cursor;
     409: pop
     410: goto          428
     413: aload_1
     414: aload_0
     415: getfield      #37                 // Field cursorBuilder_:Lcom/google/protobuf/SingleFieldBuilder;
     418: invokevirtual #56                 // Method com/google/protobuf/SingleFieldBuilder.build:()Lcom/google/protobuf/GeneratedMessage;
     421: checkcast     #60                 // class org/apache/hadoop/hbase/protobuf/generated/ClientProtos$Cursor
     424: invokestatic  #59                 // Method org/apache/hadoop/hbase/protobuf/generated/ClientProtos$ScanResponse.access$24502:(Lorg/apache/hadoop/hbase/protobuf/generated/ClientProtos$ScanResponse;Lorg/apache/hadoop/hbase/protobuf/generated/ClientProtos$Cursor;)Lorg/apache/hadoop/hbase/protobuf/generated/ClientProtos$Cursor;
     427: pop
     428: aload_1
     429: iload_3
     430: invokestatic  #61                 // Method org/apache/hadoop/hbase/protobuf/generated/ClientProtos$ScanResponse.access$24602:(Lorg/apache/hadoop/hbase/protobuf/generated/ClientProtos$ScanResponse;I)I
     433: pop
     434: aload_0
     435: invokevirtual #62                 // Method onBuilt:()V
     438: aload_1
     439: areturn

  public org.apache.hadoop.hbase.protobuf.generated.ClientProtos$ScanResponse$Builder mergeFrom(com.google.protobuf.Message);
    Code:
       0: aload_1
       1: instanceof    #5                  // class org/apache/hadoop/hbase/protobuf/generated/ClientProtos$ScanResponse
       4: ifeq          16
       7: aload_0
       8: aload_1
       9: checkcast     #5                  // class org/apache/hadoop/hbase/protobuf/generated/ClientProtos$ScanResponse
      12: invokevirtual #39                 // Method mergeFrom:(Lorg/apache/hadoop/hbase/protobuf/generated/ClientProtos$ScanResponse;)Lorg/apache/hadoop/hbase/protobuf/generated/ClientProtos$ScanResponse$Builder;
      15: areturn
      16: aload_0
      17: aload_1
      18: invokespecial #63                 // Method com/google/protobuf/GeneratedMessage$Builder.mergeFrom:(Lcom/google/protobuf/Message;)Lcom/google/protobuf/AbstractMessage$Builder;
      21: pop
      22: aload_0
      23: areturn

  public org.apache.hadoop.hbase.protobuf.generated.ClientProtos$ScanResponse$Builder mergeFrom(org.apache.hadoop.hbase.protobuf.generated.ClientProtos$ScanResponse);
    Code:
       0: aload_1
       1: invokestatic  #40                 // Method org/apache/hadoop/hbase/protobuf/generated/ClientProtos$ScanResponse.getDefaultInstance:()Lorg/apache/hadoop/hbase/protobuf/generated/ClientProtos$ScanResponse;
       4: if_acmpne     9
       7: aload_0
       8: areturn
       9: aload_1
      10: invokestatic  #64                 // Method org/apache/hadoop/hbase/protobuf/generated/ClientProtos$ScanResponse.access$23400:(Lorg/apache/hadoop/hbase/protobuf/generated/ClientProtos$ScanResponse;)Ljava/util/List;
      13: invokeinterface #65,  1           // InterfaceMethod java/util/List.isEmpty:()Z
      18: ifne          77
      21: aload_0
      22: getfield      #10                 // Field cellsPerResult_:Ljava/util/List;
      25: invokeinterface #65,  1           // InterfaceMethod java/util/List.isEmpty:()Z
      30: ifeq          55
      33: aload_0
      34: aload_1
      35: invokestatic  #64                 // Method org/apache/hadoop/hbase/protobuf/generated/ClientProtos$ScanResponse.access$23400:(Lorg/apache/hadoop/hbase/protobuf/generated/ClientProtos$ScanResponse;)Ljava/util/List;
      38: putfield      #10                 // Field cellsPerResult_:Ljava/util/List;
      41: aload_0
      42: aload_0
      43: getfield      #25                 // Field bitField0_:I
      46: bipush        -2
      48: iand
      49: putfield      #25                 // Field bitField0_:I
      52: goto          73
      55: aload_0
      56: invokespecial #66                 // Method ensureCellsPerResultIsMutable:()V
      59: aload_0
      60: getfield      #10                 // Field cellsPerResult_:Ljava/util/List;
      63: aload_1
      64: invokestatic  #64                 // Method org/apache/hadoop/hbase/protobuf/generated/ClientProtos$ScanResponse.access$23400:(Lorg/apache/hadoop/hbase/protobuf/generated/ClientProtos$ScanResponse;)Ljava/util/List;
      67: invokeinterface #67,  2           // InterfaceMethod java/util/List.addAll:(Ljava/util/Collection;)Z
      72: pop
      73: aload_0
      74: invokevirtual #68                 // Method onChanged:()V
      77: aload_1
      78: invokevirtual #69                 // Method org/apache/hadoop/hbase/protobuf/generated/ClientProtos$ScanResponse.hasScannerId:()Z
      81: ifeq          93
      84: aload_0
      85: aload_1
      86: invokevirtual #70                 // Method org/apache/hadoop/hbase/protobuf/generated/ClientProtos$ScanResponse.getScannerId:()J
      89: invokevirtual #71                 // Method setScannerId:(J)Lorg/apache/hadoop/hbase/protobuf/generated/ClientProtos$ScanResponse$Builder;
      92: pop
      93: aload_1
      94: invokevirtual #72                 // Method org/apache/hadoop/hbase/protobuf/generated/ClientProtos$ScanResponse.hasMoreResults:()Z
      97: ifeq          109
     100: aload_0
     101: aload_1
     102: invokevirtual #73                 // Method org/apache/hadoop/hbase/protobuf/generated/ClientProtos$ScanResponse.getMoreResults:()Z
     105: invokevirtual #74                 // Method setMoreResults:(Z)Lorg/apache/hadoop/hbase/protobuf/generated/ClientProtos$ScanResponse$Builder;
     108: pop
     109: aload_1
     110: invokevirtual #75                 // Method org/apache/hadoop/hbase/protobuf/generated/ClientProtos$ScanResponse.hasTtl:()Z
     113: ifeq          125
     116: aload_0
     117: aload_1
     118: invokevirtual #76                 // Method org/apache/hadoop/hbase/protobuf/generated/ClientProtos$ScanResponse.getTtl:()I
     121: invokevirtual #77                 // Method setTtl:(I)Lorg/apache/hadoop/hbase/protobuf/generated/ClientProtos$ScanResponse$Builder;
     124: pop
     125: aload_0
     126: getfield      #29                 // Field resultsBuilder_:Lcom/google/protobuf/RepeatedFieldBuilder;
     129: ifnonnull     203
     132: aload_1
     133: invokestatic  #78                 // Method org/apache/hadoop/hbase/protobuf/generated/ClientProtos$ScanResponse.access$23800:(Lorg/apache/hadoop/hbase/protobuf/generated/ClientProtos$ScanResponse;)Ljava/util/List;
     136: invokeinterface #65,  1           // InterfaceMethod java/util/List.isEmpty:()Z
     141: ifne          289
     144: aload_0
     145: getfield      #11                 // Field results_:Ljava/util/List;
     148: invokeinterface #65,  1           // InterfaceMethod java/util/List.isEmpty:()Z
     153: ifeq          178
     156: aload_0
     157: aload_1
     158: invokestatic  #78                 // Method org/apache/hadoop/hbase/protobuf/generated/ClientProtos$ScanResponse.access$23800:(Lorg/apache/hadoop/hbase/protobuf/generated/ClientProtos$ScanResponse;)Ljava/util/List;
     161: putfield      #11                 // Field results_:Ljava/util/List;
     164: aload_0
     165: aload_0
     166: getfield      #25                 // Field bitField0_:I
     169: bipush        -17
     171: iand
     172: putfield      #25                 // Field bitField0_:I
     175: goto          196
     178: aload_0
     179: invokespecial #79                 // Method ensureResultsIsMutable:()V
     182: aload_0
     183: getfield      #11                 // Field results_:Ljava/util/List;
     186: aload_1
     187: invokestatic  #78                 // Method org/apache/hadoop/hbase/protobuf/generated/ClientProtos$ScanResponse.access$23800:(Lorg/apache/hadoop/hbase/protobuf/generated/ClientProtos$ScanResponse;)Ljava/util/List;
     190: invokeinterface #67,  2           // InterfaceMethod java/util/List.addAll:(Ljava/util/Collection;)Z
     195: pop
     196: aload_0
     197: invokevirtual #68                 // Method onChanged:()V
     200: goto          289
     203: aload_1
     204: invokestatic  #78                 // Method org/apache/hadoop/hbase/protobuf/generated/ClientProtos$ScanResponse.access$23800:(Lorg/apache/hadoop/hbase/protobuf/generated/ClientProtos$ScanResponse;)Ljava/util/List;
     207: invokeinterface #65,  1           // InterfaceMethod java/util/List.isEmpty:()Z
     212: ifne          289
     215: aload_0
     216: getfield      #29                 // Field resultsBuilder_:Lcom/google/protobuf/RepeatedFieldBuilder;
     219: invokevirtual #80                 // Method com/google/protobuf/RepeatedFieldBuilder.isEmpty:()Z
     222: ifeq          277
     225: aload_0
     226: getfield      #29                 // Field resultsBuilder_:Lcom/google/protobuf/RepeatedFieldBuilder;
     229: invokevirtual #81                 // Method com/google/protobuf/RepeatedFieldBuilder.dispose:()V
     232: aload_0
     233: aconst_null
     234: putfield      #29                 // Field resultsBuilder_:Lcom/google/protobuf/RepeatedFieldBuilder;
     237: aload_0
     238: aload_1
     239: invokestatic  #78                 // Method org/apache/hadoop/hbase/protobuf/generated/ClientProtos$ScanResponse.access$23800:(Lorg/apache/hadoop/hbase/protobuf/generated/ClientProtos$ScanResponse;)Ljava/util/List;
     242: putfield      #11                 // Field results_:Ljava/util/List;
     245: aload_0
     246: aload_0
     247: getfield      #25                 // Field bitField0_:I
     250: bipush        -17
     252: iand
     253: putfield      #25                 // Field bitField0_:I
     256: aload_0
     257: invokestatic  #82                 // Method org/apache/hadoop/hbase/protobuf/generated/ClientProtos$ScanResponse.access$24700:()Z
     260: ifeq          270
     263: aload_0
     264: invokespecial #20                 // Method getResultsFieldBuilder:()Lcom/google/protobuf/RepeatedFieldBuilder;
     267: goto          271
     270: aconst_null
     271: putfield      #29                 // Field resultsBuilder_:Lcom/google/protobuf/RepeatedFieldBuilder;
     274: goto          289
     277: aload_0
     278: getfield      #29                 // Field resultsBuilder_:Lcom/google/protobuf/RepeatedFieldBuilder;
     281: aload_1
     282: invokestatic  #78                 // Method org/apache/hadoop/hbase/protobuf/generated/ClientProtos$ScanResponse.access$23800:(Lorg/apache/hadoop/hbase/protobuf/generated/ClientProtos$ScanResponse;)Ljava/util/List;
     285: invokevirtual #83                 // Method com/google/protobuf/RepeatedFieldBuilder.addAllMessages:(Ljava/lang/Iterable;)Lcom/google/protobuf/RepeatedFieldBuilder;
     288: pop
     289: aload_1
     290: invokevirtual #84                 // Method org/apache/hadoop/hbase/protobuf/generated/ClientProtos$ScanResponse.hasStale:()Z
     293: ifeq          305
     296: aload_0
     297: aload_1
     298: invokevirtual #85                 // Method org/apache/hadoop/hbase/protobuf/generated/ClientProtos$ScanResponse.getStale:()Z
     301: invokevirtual #86                 // Method setStale:(Z)Lorg/apache/hadoop/hbase/protobuf/generated/ClientProtos$ScanResponse$Builder;
     304: pop
     305: aload_1
     306: invokestatic  #87                 // Method org/apache/hadoop/hbase/protobuf/generated/ClientProtos$ScanResponse.access$24000:(Lorg/apache/hadoop/hbase/protobuf/generated/ClientProtos$ScanResponse;)Ljava/util/List;
     309: invokeinterface #65,  1           // InterfaceMethod java/util/List.isEmpty:()Z
     314: ifne          373
     317: aload_0
     318: getfield      #12                 // Field partialFlagPerResult_:Ljava/util/List;
     321: invokeinterface #65,  1           // InterfaceMethod java/util/List.isEmpty:()Z
     326: ifeq          351
     329: aload_0
     330: aload_1
     331: invokestatic  #87                 // Method org/apache/hadoop/hbase/protobuf/generated/ClientProtos$ScanResponse.access$24000:(Lorg/apache/hadoop/hbase/protobuf/generated/ClientProtos$ScanResponse;)Ljava/util/List;
     334: putfield      #12                 // Field partialFlagPerResult_:Ljava/util/List;
     337: aload_0
     338: aload_0
     339: getfield      #25                 // Field bitField0_:I
     342: bipush        -65
     344: iand
     345: putfield      #25                 // Field bitField0_:I
     348: goto          369
     351: aload_0
     352: invokespecial #88                 // Method ensurePartialFlagPerResultIsMutable:()V
     355: aload_0
     356: getfield      #12                 // Field partialFlagPerResult_:Ljava/util/List;
     359: aload_1
     360: invokestatic  #87                 // Method org/apache/hadoop/hbase/protobuf/generated/ClientProtos$ScanResponse.access$24000:(Lorg/apache/hadoop/hbase/protobuf/generated/ClientProtos$ScanResponse;)Ljava/util/List;
     363: invokeinterface #67,  2           // InterfaceMethod java/util/List.addAll:(Ljava/util/Collection;)Z
     368: pop
     369: aload_0
     370: invokevirtual #68                 // Method onChanged:()V
     373: aload_1
     374: invokevirtual #89                 // Method org/apache/hadoop/hbase/protobuf/generated/ClientProtos$ScanResponse.hasMoreResultsInRegion:()Z
     377: ifeq          389
     380: aload_0
     381: aload_1
     382: invokevirtual #90                 // Method org/apache/hadoop/hbase/protobuf/generated/ClientProtos$ScanResponse.getMoreResultsInRegion:()Z
     385: invokevirtual #91                 // Method setMoreResultsInRegion:(Z)Lorg/apache/hadoop/hbase/protobuf/generated/ClientProtos$ScanResponse$Builder;
     388: pop
     389: aload_1
     390: invokevirtual #92                 // Method org/apache/hadoop/hbase/protobuf/generated/ClientProtos$ScanResponse.hasHeartbeatMessage:()Z
     393: ifeq          405
     396: aload_0
     397: aload_1
     398: invokevirtual #93                 // Method org/apache/hadoop/hbase/protobuf/generated/ClientProtos$ScanResponse.getHeartbeatMessage:()Z
     401: invokevirtual #94                 // Method setHeartbeatMessage:(Z)Lorg/apache/hadoop/hbase/protobuf/generated/ClientProtos$ScanResponse$Builder;
     404: pop
     405: aload_1
     406: invokevirtual #95                 // Method org/apache/hadoop/hbase/protobuf/generated/ClientProtos$ScanResponse.hasScanMetrics:()Z
     409: ifeq          421
     412: aload_0
     413: aload_1
     414: invokevirtual #96                 // Method org/apache/hadoop/hbase/protobuf/generated/ClientProtos$ScanResponse.getScanMetrics:()Lorg/apache/hadoop/hbase/protobuf/generated/MapReduceProtos$ScanMetrics;
     417: invokevirtual #97                 // Method mergeScanMetrics:(Lorg/apache/hadoop/hbase/protobuf/generated/MapReduceProtos$ScanMetrics;)Lorg/apache/hadoop/hbase/protobuf/generated/ClientProtos$ScanResponse$Builder;
     420: pop
     421: aload_1
     422: invokevirtual #98                 // Method org/apache/hadoop/hbase/protobuf/generated/ClientProtos$ScanResponse.hasMvccReadPoint:()Z
     425: ifeq          437
     428: aload_0
     429: aload_1
     430: invokevirtual #99                 // Method org/apache/hadoop/hbase/protobuf/generated/ClientProtos$ScanResponse.getMvccReadPoint:()J
     433: invokevirtual #100                // Method setMvccReadPoint:(J)Lorg/apache/hadoop/hbase/protobuf/generated/ClientProtos$ScanResponse$Builder;
     436: pop
     437: aload_1
     438: invokevirtual #101                // Method org/apache/hadoop/hbase/protobuf/generated/ClientProtos$ScanResponse.hasCursor:()Z
     441: ifeq          453
     444: aload_0
     445: aload_1
     446: invokevirtual #102                // Method org/apache/hadoop/hbase/protobuf/generated/ClientProtos$ScanResponse.getCursor:()Lorg/apache/hadoop/hbase/protobuf/generated/ClientProtos$Cursor;
     449: invokevirtual #103                // Method mergeCursor:(Lorg/apache/hadoop/hbase/protobuf/generated/ClientProtos$Cursor;)Lorg/apache/hadoop/hbase/protobuf/generated/ClientProtos$ScanResponse$Builder;
     452: pop
     453: aload_0
     454: aload_1
     455: invokevirtual #104                // Method org/apache/hadoop/hbase/protobuf/generated/ClientProtos$ScanResponse.getUnknownFields:()Lcom/google/protobuf/UnknownFieldSet;
     458: invokevirtual #105                // Method mergeUnknownFields:(Lcom/google/protobuf/UnknownFieldSet;)Lcom/google/protobuf/GeneratedMessage$Builder;
     461: pop
     462: aload_0
     463: areturn

  public final boolean isInitialized();
    Code:
       0: iconst_1
       1: ireturn

  public org.apache.hadoop.hbase.protobuf.generated.ClientProtos$ScanResponse$Builder mergeFrom(com.google.protobuf.CodedInputStream, com.google.protobuf.ExtensionRegistryLite) throws java.io.IOException;
    Code:
       0: aconst_null
       1: astore_3
       2: getstatic     #106                // Field org/apache/hadoop/hbase/protobuf/generated/ClientProtos$ScanResponse.PARSER:Lcom/google/protobuf/Parser;
       5: aload_1
       6: aload_2
       7: invokeinterface #107,  3          // InterfaceMethod com/google/protobuf/Parser.parsePartialFrom:(Lcom/google/protobuf/CodedInputStream;Lcom/google/protobuf/ExtensionRegistryLite;)Ljava/lang/Object;
      12: checkcast     #5                  // class org/apache/hadoop/hbase/protobuf/generated/ClientProtos$ScanResponse
      15: astore_3
      16: aload_3
      17: ifnull        58
      20: aload_0
      21: aload_3
      22: invokevirtual #39                 // Method mergeFrom:(Lorg/apache/hadoop/hbase/protobuf/generated/ClientProtos$ScanResponse;)Lorg/apache/hadoop/hbase/protobuf/generated/ClientProtos$ScanResponse$Builder;
      25: pop
      26: goto          58
      29: astore        4
      31: aload         4
      33: invokevirtual #109                // Method com/google/protobuf/InvalidProtocolBufferException.getUnfinishedMessage:()Lcom/google/protobuf/MessageLite;
      36: checkcast     #5                  // class org/apache/hadoop/hbase/protobuf/generated/ClientProtos$ScanResponse
      39: astore_3
      40: aload         4
      42: athrow
      43: astore        5
      45: aload_3
      46: ifnull        55
      49: aload_0
      50: aload_3
      51: invokevirtual #39                 // Method mergeFrom:(Lorg/apache/hadoop/hbase/protobuf/generated/ClientProtos$ScanResponse;)Lorg/apache/hadoop/hbase/protobuf/generated/ClientProtos$ScanResponse$Builder;
      54: pop
      55: aload         5
      57: athrow
      58: aload_0
      59: areturn
    Exception table:
       from    to  target type
           2    16    29   Class com/google/protobuf/InvalidProtocolBufferException
           2    16    43   any
          29    45    43   any

  public java.util.List<java.lang.Integer> getCellsPerResultList();
    Code:
       0: aload_0
       1: getfield      #10                 // Field cellsPerResult_:Ljava/util/List;
       4: invokestatic  #44                 // Method java/util/Collections.unmodifiableList:(Ljava/util/List;)Ljava/util/List;
       7: areturn

  public int getCellsPerResultCount();
    Code:
       0: aload_0
       1: getfield      #10                 // Field cellsPerResult_:Ljava/util/List;
       4: invokeinterface #112,  1          // InterfaceMethod java/util/List.size:()I
       9: ireturn

  public int getCellsPerResult(int);
    Code:
       0: aload_0
       1: getfield      #10                 // Field cellsPerResult_:Ljava/util/List;
       4: iload_1
       5: invokeinterface #113,  2          // InterfaceMethod java/util/List.get:(I)Ljava/lang/Object;
      10: checkcast     #114                // class java/lang/Integer
      13: invokevirtual #115                // Method java/lang/Integer.intValue:()I
      16: ireturn

  public org.apache.hadoop.hbase.protobuf.generated.ClientProtos$ScanResponse$Builder setCellsPerResult(int, int);
    Code:
       0: aload_0
       1: invokespecial #66                 // Method ensureCellsPerResultIsMutable:()V
       4: aload_0
       5: getfield      #10                 // Field cellsPerResult_:Ljava/util/List;
       8: iload_1
       9: iload_2
      10: invokestatic  #116                // Method java/lang/Integer.valueOf:(I)Ljava/lang/Integer;
      13: invokeinterface #117,  3          // InterfaceMethod java/util/List.set:(ILjava/lang/Object;)Ljava/lang/Object;
      18: pop
      19: aload_0
      20: invokevirtual #68                 // Method onChanged:()V
      23: aload_0
      24: areturn

  public org.apache.hadoop.hbase.protobuf.generated.ClientProtos$ScanResponse$Builder addCellsPerResult(int);
    Code:
       0: aload_0
       1: invokespecial #66                 // Method ensureCellsPerResultIsMutable:()V
       4: aload_0
       5: getfield      #10                 // Field cellsPerResult_:Ljava/util/List;
       8: iload_1
       9: invokestatic  #116                // Method java/lang/Integer.valueOf:(I)Ljava/lang/Integer;
      12: invokeinterface #118,  2          // InterfaceMethod java/util/List.add:(Ljava/lang/Object;)Z
      17: pop
      18: aload_0
      19: invokevirtual #68                 // Method onChanged:()V
      22: aload_0
      23: areturn

  public org.apache.hadoop.hbase.protobuf.generated.ClientProtos$ScanResponse$Builder addAllCellsPerResult(java.lang.Iterable<? extends java.lang.Integer>);
    Code:
       0: aload_0
       1: invokespecial #66                 // Method ensureCellsPerResultIsMutable:()V
       4: aload_1
       5: aload_0
       6: getfield      #10                 // Field cellsPerResult_:Ljava/util/List;
       9: invokestatic  #119                // Method com/google/protobuf/GeneratedMessage$Builder.addAll:(Ljava/lang/Iterable;Ljava/util/Collection;)V
      12: aload_0
      13: invokevirtual #68                 // Method onChanged:()V
      16: aload_0
      17: areturn

  public org.apache.hadoop.hbase.protobuf.generated.ClientProtos$ScanResponse$Builder clearCellsPerResult();
    Code:
       0: aload_0
       1: invokestatic  #9                  // Method java/util/Collections.emptyList:()Ljava/util/List;
       4: putfield      #10                 // Field cellsPerResult_:Ljava/util/List;
       7: aload_0
       8: aload_0
       9: getfield      #25                 // Field bitField0_:I
      12: bipush        -2
      14: iand
      15: putfield      #25                 // Field bitField0_:I
      18: aload_0
      19: invokevirtual #68                 // Method onChanged:()V
      22: aload_0
      23: areturn

  public boolean hasScannerId();
    Code:
       0: aload_0
       1: getfield      #25                 // Field bitField0_:I
       4: iconst_2
       5: iand
       6: iconst_2
       7: if_icmpne     14
      10: iconst_1
      11: goto          15
      14: iconst_0
      15: ireturn

  public long getScannerId();
    Code:
       0: aload_0
       1: getfield      #26                 // Field scannerId_:J
       4: lreturn

  public org.apache.hadoop.hbase.protobuf.generated.ClientProtos$ScanResponse$Builder setScannerId(long);
    Code:
       0: aload_0
       1: dup
       2: getfield      #25                 // Field bitField0_:I
       5: iconst_2
       6: ior
       7: putfield      #25                 // Field bitField0_:I
      10: aload_0
      11: lload_1
      12: putfield      #26                 // Field scannerId_:J
      15: aload_0
      16: invokevirtual #68                 // Method onChanged:()V
      19: aload_0
      20: areturn

  public org.apache.hadoop.hbase.protobuf.generated.ClientProtos$ScanResponse$Builder clearScannerId();
    Code:
       0: aload_0
       1: aload_0
       2: getfield      #25                 // Field bitField0_:I
       5: bipush        -3
       7: iand
       8: putfield      #25                 // Field bitField0_:I
      11: aload_0
      12: lconst_0
      13: putfield      #26                 // Field scannerId_:J
      16: aload_0
      17: invokevirtual #68                 // Method onChanged:()V
      20: aload_0
      21: areturn

  public boolean hasMoreResults();
    Code:
       0: aload_0
       1: getfield      #25                 // Field bitField0_:I
       4: iconst_4
       5: iand
       6: iconst_4
       7: if_icmpne     14
      10: iconst_1
      11: goto          15
      14: iconst_0
      15: ireturn

  public boolean getMoreResults();
    Code:
       0: aload_0
       1: getfield      #27                 // Field moreResults_:Z
       4: ireturn

  public org.apache.hadoop.hbase.protobuf.generated.ClientProtos$ScanResponse$Builder setMoreResults(boolean);
    Code:
       0: aload_0
       1: dup
       2: getfield      #25                 // Field bitField0_:I
       5: iconst_4
       6: ior
       7: putfield      #25                 // Field bitField0_:I
      10: aload_0
      11: iload_1
      12: putfield      #27                 // Field moreResults_:Z
      15: aload_0
      16: invokevirtual #68                 // Method onChanged:()V
      19: aload_0
      20: areturn

  public org.apache.hadoop.hbase.protobuf.generated.ClientProtos$ScanResponse$Builder clearMoreResults();
    Code:
       0: aload_0
       1: aload_0
       2: getfield      #25                 // Field bitField0_:I
       5: bipush        -5
       7: iand
       8: putfield      #25                 // Field bitField0_:I
      11: aload_0
      12: iconst_0
      13: putfield      #27                 // Field moreResults_:Z
      16: aload_0
      17: invokevirtual #68                 // Method onChanged:()V
      20: aload_0
      21: areturn

  public boolean hasTtl();
    Code:
       0: aload_0
       1: getfield      #25                 // Field bitField0_:I
       4: bipush        8
       6: iand
       7: bipush        8
       9: if_icmpne     16
      12: iconst_1
      13: goto          17
      16: iconst_0
      17: ireturn

  public int getTtl();
    Code:
       0: aload_0
       1: getfield      #28                 // Field ttl_:I
       4: ireturn

  public org.apache.hadoop.hbase.protobuf.generated.ClientProtos$ScanResponse$Builder setTtl(int);
    Code:
       0: aload_0
       1: dup
       2: getfield      #25                 // Field bitField0_:I
       5: bipush        8
       7: ior
       8: putfield      #25                 // Field bitField0_:I
      11: aload_0
      12: iload_1
      13: putfield      #28                 // Field ttl_:I
      16: aload_0
      17: invokevirtual #68                 // Method onChanged:()V
      20: aload_0
      21: areturn

  public org.apache.hadoop.hbase.protobuf.generated.ClientProtos$ScanResponse$Builder clearTtl();
    Code:
       0: aload_0
       1: aload_0
       2: getfield      #25                 // Field bitField0_:I
       5: bipush        -9
       7: iand
       8: putfield      #25                 // Field bitField0_:I
      11: aload_0
      12: iconst_0
      13: putfield      #28                 // Field ttl_:I
      16: aload_0
      17: invokevirtual #68                 // Method onChanged:()V
      20: aload_0
      21: areturn

  public java.util.List<org.apache.hadoop.hbase.protobuf.generated.ClientProtos$Result> getResultsList();
    Code:
       0: aload_0
       1: getfield      #29                 // Field resultsBuilder_:Lcom/google/protobuf/RepeatedFieldBuilder;
       4: ifnonnull     15
       7: aload_0
       8: getfield      #11                 // Field results_:Ljava/util/List;
      11: invokestatic  #44                 // Method java/util/Collections.unmodifiableList:(Ljava/util/List;)Ljava/util/List;
      14: areturn
      15: aload_0
      16: getfield      #29                 // Field resultsBuilder_:Lcom/google/protobuf/RepeatedFieldBuilder;
      19: invokevirtual #120                // Method com/google/protobuf/RepeatedFieldBuilder.getMessageList:()Ljava/util/List;
      22: areturn

  public int getResultsCount();
    Code:
       0: aload_0
       1: getfield      #29                 // Field resultsBuilder_:Lcom/google/protobuf/RepeatedFieldBuilder;
       4: ifnonnull     17
       7: aload_0
       8: getfield      #11                 // Field results_:Ljava/util/List;
      11: invokeinterface #112,  1          // InterfaceMethod java/util/List.size:()I
      16: ireturn
      17: aload_0
      18: getfield      #29                 // Field resultsBuilder_:Lcom/google/protobuf/RepeatedFieldBuilder;
      21: invokevirtual #121                // Method com/google/protobuf/RepeatedFieldBuilder.getCount:()I
      24: ireturn

  public org.apache.hadoop.hbase.protobuf.generated.ClientProtos$Result getResults(int);
    Code:
       0: aload_0
       1: getfield      #29                 // Field resultsBuilder_:Lcom/google/protobuf/RepeatedFieldBuilder;
       4: ifnonnull     21
       7: aload_0
       8: getfield      #11                 // Field results_:Ljava/util/List;
      11: iload_1
      12: invokeinterface #113,  2          // InterfaceMethod java/util/List.get:(I)Ljava/lang/Object;
      17: checkcast     #122                // class org/apache/hadoop/hbase/protobuf/generated/ClientProtos$Result
      20: areturn
      21: aload_0
      22: getfield      #29                 // Field resultsBuilder_:Lcom/google/protobuf/RepeatedFieldBuilder;
      25: iload_1
      26: invokevirtual #123                // Method com/google/protobuf/RepeatedFieldBuilder.getMessage:(I)Lcom/google/protobuf/GeneratedMessage;
      29: checkcast     #122                // class org/apache/hadoop/hbase/protobuf/generated/ClientProtos$Result
      32: areturn

  public org.apache.hadoop.hbase.protobuf.generated.ClientProtos$ScanResponse$Builder setResults(int, org.apache.hadoop.hbase.protobuf.generated.ClientProtos$Result);
    Code:
       0: aload_0
       1: getfield      #29                 // Field resultsBuilder_:Lcom/google/protobuf/RepeatedFieldBuilder;
       4: ifnonnull     42
       7: aload_2
       8: ifnonnull     19
      11: new           #124                // class java/lang/NullPointerException
      14: dup
      15: invokespecial #125                // Method java/lang/NullPointerException."<init>":()V
      18: athrow
      19: aload_0
      20: invokespecial #79                 // Method ensureResultsIsMutable:()V
      23: aload_0
      24: getfield      #11                 // Field results_:Ljava/util/List;
      27: iload_1
      28: aload_2
      29: invokeinterface #117,  3          // InterfaceMethod java/util/List.set:(ILjava/lang/Object;)Ljava/lang/Object;
      34: pop
      35: aload_0
      36: invokevirtual #68                 // Method onChanged:()V
      39: goto          52
      42: aload_0
      43: getfield      #29                 // Field resultsBuilder_:Lcom/google/protobuf/RepeatedFieldBuilder;
      46: iload_1
      47: aload_2
      48: invokevirtual #126                // Method com/google/protobuf/RepeatedFieldBuilder.setMessage:(ILcom/google/protobuf/GeneratedMessage;)Lcom/google/protobuf/RepeatedFieldBuilder;
      51: pop
      52: aload_0
      53: areturn

  public org.apache.hadoop.hbase.protobuf.generated.ClientProtos$ScanResponse$Builder setResults(int, org.apache.hadoop.hbase.protobuf.generated.ClientProtos$Result$Builder);
    Code:
       0: aload_0
       1: getfield      #29                 // Field resultsBuilder_:Lcom/google/protobuf/RepeatedFieldBuilder;
       4: ifnonnull     33
       7: aload_0
       8: invokespecial #79                 // Method ensureResultsIsMutable:()V
      11: aload_0
      12: getfield      #11                 // Field results_:Ljava/util/List;
      15: iload_1
      16: aload_2
      17: invokevirtual #127                // Method org/apache/hadoop/hbase/protobuf/generated/ClientProtos$Result$Builder.build:()Lorg/apache/hadoop/hbase/protobuf/generated/ClientProtos$Result;
      20: invokeinterface #117,  3          // InterfaceMethod java/util/List.set:(ILjava/lang/Object;)Ljava/lang/Object;
      25: pop
      26: aload_0
      27: invokevirtual #68                 // Method onChanged:()V
      30: goto          46
      33: aload_0
      34: getfield      #29                 // Field resultsBuilder_:Lcom/google/protobuf/RepeatedFieldBuilder;
      37: iload_1
      38: aload_2
      39: invokevirtual #127                // Method org/apache/hadoop/hbase/protobuf/generated/ClientProtos$Result$Builder.build:()Lorg/apache/hadoop/hbase/protobuf/generated/ClientProtos$Result;
      42: invokevirtual #126                // Method com/google/protobuf/RepeatedFieldBuilder.setMessage:(ILcom/google/protobuf/GeneratedMessage;)Lcom/google/protobuf/RepeatedFieldBuilder;
      45: pop
      46: aload_0
      47: areturn

  public org.apache.hadoop.hbase.protobuf.generated.ClientProtos$ScanResponse$Builder addResults(org.apache.hadoop.hbase.protobuf.generated.ClientProtos$Result);
    Code:
       0: aload_0
       1: getfield      #29                 // Field resultsBuilder_:Lcom/google/protobuf/RepeatedFieldBuilder;
       4: ifnonnull     41
       7: aload_1
       8: ifnonnull     19
      11: new           #124                // class java/lang/NullPointerException
      14: dup
      15: invokespecial #125                // Method java/lang/NullPointerException."<init>":()V
      18: athrow
      19: aload_0
      20: invokespecial #79                 // Method ensureResultsIsMutable:()V
      23: aload_0
      24: getfield      #11                 // Field results_:Ljava/util/List;
      27: aload_1
      28: invokeinterface #118,  2          // InterfaceMethod java/util/List.add:(Ljava/lang/Object;)Z
      33: pop
      34: aload_0
      35: invokevirtual #68                 // Method onChanged:()V
      38: goto          50
      41: aload_0
      42: getfield      #29                 // Field resultsBuilder_:Lcom/google/protobuf/RepeatedFieldBuilder;
      45: aload_1
      46: invokevirtual #128                // Method com/google/protobuf/RepeatedFieldBuilder.addMessage:(Lcom/google/protobuf/GeneratedMessage;)Lcom/google/protobuf/RepeatedFieldBuilder;
      49: pop
      50: aload_0
      51: areturn

  public org.apache.hadoop.hbase.protobuf.generated.ClientProtos$ScanResponse$Builder addResults(int, org.apache.hadoop.hbase.protobuf.generated.ClientProtos$Result);
    Code:
       0: aload_0
       1: getfield      #29                 // Field resultsBuilder_:Lcom/google/protobuf/RepeatedFieldBuilder;
       4: ifnonnull     41
       7: aload_2
       8: ifnonnull     19
      11: new           #124                // class java/lang/NullPointerException
      14: dup
      15: invokespecial #125                // Method java/lang/NullPointerException."<init>":()V
      18: athrow
      19: aload_0
      20: invokespecial #79                 // Method ensureResultsIsMutable:()V
      23: aload_0
      24: getfield      #11                 // Field results_:Ljava/util/List;
      27: iload_1
      28: aload_2
      29: invokeinterface #129,  3          // InterfaceMethod java/util/List.add:(ILjava/lang/Object;)V
      34: aload_0
      35: invokevirtual #68                 // Method onChanged:()V
      38: goto          51
      41: aload_0
      42: getfield      #29                 // Field resultsBuilder_:Lcom/google/protobuf/RepeatedFieldBuilder;
      45: iload_1
      46: aload_2
      47: invokevirtual #130                // Method com/google/protobuf/RepeatedFieldBuilder.addMessage:(ILcom/google/protobuf/GeneratedMessage;)Lcom/google/protobuf/RepeatedFieldBuilder;
      50: pop
      51: aload_0
      52: areturn

  public org.apache.hadoop.hbase.protobuf.generated.ClientProtos$ScanResponse$Builder addResults(org.apache.hadoop.hbase.protobuf.generated.ClientProtos$Result$Builder);
    Code:
       0: aload_0
       1: getfield      #29                 // Field resultsBuilder_:Lcom/google/protobuf/RepeatedFieldBuilder;
       4: ifnonnull     32
       7: aload_0
       8: invokespecial #79                 // Method ensureResultsIsMutable:()V
      11: aload_0
      12: getfield      #11                 // Field results_:Ljava/util/List;
      15: aload_1
      16: invokevirtual #127                // Method org/apache/hadoop/hbase/protobuf/generated/ClientProtos$Result$Builder.build:()Lorg/apache/hadoop/hbase/protobuf/generated/ClientProtos$Result;
      19: invokeinterface #118,  2          // InterfaceMethod java/util/List.add:(Ljava/lang/Object;)Z
      24: pop
      25: aload_0
      26: invokevirtual #68                 // Method onChanged:()V
      29: goto          44
      32: aload_0
      33: getfield      #29                 // Field resultsBuilder_:Lcom/google/protobuf/RepeatedFieldBuilder;
      36: aload_1
      37: invokevirtual #127                // Method org/apache/hadoop/hbase/protobuf/generated/ClientProtos$Result$Builder.build:()Lorg/apache/hadoop/hbase/protobuf/generated/ClientProtos$Result;
      40: invokevirtual #128                // Method com/google/protobuf/RepeatedFieldBuilder.addMessage:(Lcom/google/protobuf/GeneratedMessage;)Lcom/google/protobuf/RepeatedFieldBuilder;
      43: pop
      44: aload_0
      45: areturn

  public org.apache.hadoop.hbase.protobuf.generated.ClientProtos$ScanResponse$Builder addResults(int, org.apache.hadoop.hbase.protobuf.generated.ClientProtos$Result$Builder);
    Code:
       0: aload_0
       1: getfield      #29                 // Field resultsBuilder_:Lcom/google/protobuf/RepeatedFieldBuilder;
       4: ifnonnull     32
       7: aload_0
       8: invokespecial #79                 // Method ensureResultsIsMutable:()V
      11: aload_0
      12: getfield      #11                 // Field results_:Ljava/util/List;
      15: iload_1
      16: aload_2
      17: invokevirtual #127                // Method org/apache/hadoop/hbase/protobuf/generated/ClientProtos$Result$Builder.build:()Lorg/apache/hadoop/hbase/protobuf/generated/ClientProtos$Result;
      20: invokeinterface #129,  3          // InterfaceMethod java/util/List.add:(ILjava/lang/Object;)V
      25: aload_0
      26: invokevirtual #68                 // Method onChanged:()V
      29: goto          45
      32: aload_0
      33: getfield      #29                 // Field resultsBuilder_:Lcom/google/protobuf/RepeatedFieldBuilder;
      36: iload_1
      37: aload_2
      38: invokevirtual #127                // Method org/apache/hadoop/hbase/protobuf/generated/ClientProtos$Result$Builder.build:()Lorg/apache/hadoop/hbase/protobuf/generated/ClientProtos$Result;
      41: invokevirtual #130                // Method com/google/protobuf/RepeatedFieldBuilder.addMessage:(ILcom/google/protobuf/GeneratedMessage;)Lcom/google/protobuf/RepeatedFieldBuilder;
      44: pop
      45: aload_0
      46: areturn

  public org.apache.hadoop.hbase.protobuf.generated.ClientProtos$ScanResponse$Builder addAllResults(java.lang.Iterable<? extends org.apache.hadoop.hbase.protobuf.generated.ClientProtos$Result>);
    Code:
       0: aload_0
       1: getfield      #29                 // Field resultsBuilder_:Lcom/google/protobuf/RepeatedFieldBuilder;
       4: ifnonnull     26
       7: aload_0
       8: invokespecial #79                 // Method ensureResultsIsMutable:()V
      11: aload_1
      12: aload_0
      13: getfield      #11                 // Field results_:Ljava/util/List;
      16: invokestatic  #119                // Method com/google/protobuf/GeneratedMessage$Builder.addAll:(Ljava/lang/Iterable;Ljava/util/Collection;)V
      19: aload_0
      20: invokevirtual #68                 // Method onChanged:()V
      23: goto          35
      26: aload_0
      27: getfield      #29                 // Field resultsBuilder_:Lcom/google/protobuf/RepeatedFieldBuilder;
      30: aload_1
      31: invokevirtual #83                 // Method com/google/protobuf/RepeatedFieldBuilder.addAllMessages:(Ljava/lang/Iterable;)Lcom/google/protobuf/RepeatedFieldBuilder;
      34: pop
      35: aload_0
      36: areturn

  public org.apache.hadoop.hbase.protobuf.generated.ClientProtos$ScanResponse$Builder clearResults();
    Code:
       0: aload_0
       1: getfield      #29                 // Field resultsBuilder_:Lcom/google/protobuf/RepeatedFieldBuilder;
       4: ifnonnull     32
       7: aload_0
       8: invokestatic  #9                  // Method java/util/Collections.emptyList:()Ljava/util/List;
      11: putfield      #11                 // Field results_:Ljava/util/List;
      14: aload_0
      15: aload_0
      16: getfield      #25                 // Field bitField0_:I
      19: bipush        -17
      21: iand
      22: putfield      #25                 // Field bitField0_:I
      25: aload_0
      26: invokevirtual #68                 // Method onChanged:()V
      29: goto          39
      32: aload_0
      33: getfield      #29                 // Field resultsBuilder_:Lcom/google/protobuf/RepeatedFieldBuilder;
      36: invokevirtual #30                 // Method com/google/protobuf/RepeatedFieldBuilder.clear:()V
      39: aload_0
      40: areturn

  public org.apache.hadoop.hbase.protobuf.generated.ClientProtos$ScanResponse$Builder removeResults(int);
    Code:
       0: aload_0
       1: getfield      #29                 // Field resultsBuilder_:Lcom/google/protobuf/RepeatedFieldBuilder;
       4: ifnonnull     29
       7: aload_0
       8: invokespecial #79                 // Method ensureResultsIsMutable:()V
      11: aload_0
      12: getfield      #11                 // Field results_:Ljava/util/List;
      15: iload_1
      16: invokeinterface #131,  2          // InterfaceMethod java/util/List.remove:(I)Ljava/lang/Object;
      21: pop
      22: aload_0
      23: invokevirtual #68                 // Method onChanged:()V
      26: goto          37
      29: aload_0
      30: getfield      #29                 // Field resultsBuilder_:Lcom/google/protobuf/RepeatedFieldBuilder;
      33: iload_1
      34: invokevirtual #132                // Method com/google/protobuf/RepeatedFieldBuilder.remove:(I)V
      37: aload_0
      38: areturn

  public org.apache.hadoop.hbase.protobuf.generated.ClientProtos$Result$Builder getResultsBuilder(int);
    Code:
       0: aload_0
       1: invokespecial #20                 // Method getResultsFieldBuilder:()Lcom/google/protobuf/RepeatedFieldBuilder;
       4: iload_1
       5: invokevirtual #133                // Method com/google/protobuf/RepeatedFieldBuilder.getBuilder:(I)Lcom/google/protobuf/GeneratedMessage$Builder;
       8: checkcast     #134                // class org/apache/hadoop/hbase/protobuf/generated/ClientProtos$Result$Builder
      11: areturn

  public org.apache.hadoop.hbase.protobuf.generated.ClientProtos$ResultOrBuilder getResultsOrBuilder(int);
    Code:
       0: aload_0
       1: getfield      #29                 // Field resultsBuilder_:Lcom/google/protobuf/RepeatedFieldBuilder;
       4: ifnonnull     21
       7: aload_0
       8: getfield      #11                 // Field results_:Ljava/util/List;
      11: iload_1
      12: invokeinterface #113,  2          // InterfaceMethod java/util/List.get:(I)Ljava/lang/Object;
      17: checkcast     #135                // class org/apache/hadoop/hbase/protobuf/generated/ClientProtos$ResultOrBuilder
      20: areturn
      21: aload_0
      22: getfield      #29                 // Field resultsBuilder_:Lcom/google/protobuf/RepeatedFieldBuilder;
      25: iload_1
      26: invokevirtual #136                // Method com/google/protobuf/RepeatedFieldBuilder.getMessageOrBuilder:(I)Lcom/google/protobuf/MessageOrBuilder;
      29: checkcast     #135                // class org/apache/hadoop/hbase/protobuf/generated/ClientProtos$ResultOrBuilder
      32: areturn

  public java.util.List<? extends org.apache.hadoop.hbase.protobuf.generated.ClientProtos$ResultOrBuilder> getResultsOrBuilderList();
    Code:
       0: aload_0
       1: getfield      #29                 // Field resultsBuilder_:Lcom/google/protobuf/RepeatedFieldBuilder;
       4: ifnull        15
       7: aload_0
       8: getfield      #29                 // Field resultsBuilder_:Lcom/google/protobuf/RepeatedFieldBuilder;
      11: invokevirtual #137                // Method com/google/protobuf/RepeatedFieldBuilder.getMessageOrBuilderList:()Ljava/util/List;
      14: areturn
      15: aload_0
      16: getfield      #11                 // Field results_:Ljava/util/List;
      19: invokestatic  #44                 // Method java/util/Collections.unmodifiableList:(Ljava/util/List;)Ljava/util/List;
      22: areturn

  public org.apache.hadoop.hbase.protobuf.generated.ClientProtos$Result$Builder addResultsBuilder();
    Code:
       0: aload_0
       1: invokespecial #20                 // Method getResultsFieldBuilder:()Lcom/google/protobuf/RepeatedFieldBuilder;
       4: invokestatic  #138                // Method org/apache/hadoop/hbase/protobuf/generated/ClientProtos$Result.getDefaultInstance:()Lorg/apache/hadoop/hbase/protobuf/generated/ClientProtos$Result;
       7: invokevirtual #139                // Method com/google/protobuf/RepeatedFieldBuilder.addBuilder:(Lcom/google/protobuf/GeneratedMessage;)Lcom/google/protobuf/GeneratedMessage$Builder;
      10: checkcast     #134                // class org/apache/hadoop/hbase/protobuf/generated/ClientProtos$Result$Builder
      13: areturn

  public org.apache.hadoop.hbase.protobuf.generated.ClientProtos$Result$Builder addResultsBuilder(int);
    Code:
       0: aload_0
       1: invokespecial #20                 // Method getResultsFieldBuilder:()Lcom/google/protobuf/RepeatedFieldBuilder;
       4: iload_1
       5: invokestatic  #138                // Method org/apache/hadoop/hbase/protobuf/generated/ClientProtos$Result.getDefaultInstance:()Lorg/apache/hadoop/hbase/protobuf/generated/ClientProtos$Result;
       8: invokevirtual #140                // Method com/google/protobuf/RepeatedFieldBuilder.addBuilder:(ILcom/google/protobuf/GeneratedMessage;)Lcom/google/protobuf/GeneratedMessage$Builder;
      11: checkcast     #134                // class org/apache/hadoop/hbase/protobuf/generated/ClientProtos$Result$Builder
      14: areturn

  public java.util.List<org.apache.hadoop.hbase.protobuf.generated.ClientProtos$Result$Builder> getResultsBuilderList();
    Code:
       0: aload_0
       1: invokespecial #20                 // Method getResultsFieldBuilder:()Lcom/google/protobuf/RepeatedFieldBuilder;
       4: invokevirtual #141                // Method com/google/protobuf/RepeatedFieldBuilder.getBuilderList:()Ljava/util/List;
       7: areturn

  public boolean hasStale();
    Code:
       0: aload_0
       1: getfield      #25                 // Field bitField0_:I
       4: bipush        32
       6: iand
       7: bipush        32
       9: if_icmpne     16
      12: iconst_1
      13: goto          17
      16: iconst_0
      17: ireturn

  public boolean getStale();
    Code:
       0: aload_0
       1: getfield      #31                 // Field stale_:Z
       4: ireturn

  public org.apache.hadoop.hbase.protobuf.generated.ClientProtos$ScanResponse$Builder setStale(boolean);
    Code:
       0: aload_0
       1: dup
       2: getfield      #25                 // Field bitField0_:I
       5: bipush        32
       7: ior
       8: putfield      #25                 // Field bitField0_:I
      11: aload_0
      12: iload_1
      13: putfield      #31                 // Field stale_:Z
      16: aload_0
      17: invokevirtual #68                 // Method onChanged:()V
      20: aload_0
      21: areturn

  public org.apache.hadoop.hbase.protobuf.generated.ClientProtos$ScanResponse$Builder clearStale();
    Code:
       0: aload_0
       1: aload_0
       2: getfield      #25                 // Field bitField0_:I
       5: bipush        -33
       7: iand
       8: putfield      #25                 // Field bitField0_:I
      11: aload_0
      12: iconst_0
      13: putfield      #31                 // Field stale_:Z
      16: aload_0
      17: invokevirtual #68                 // Method onChanged:()V
      20: aload_0
      21: areturn

  public java.util.List<java.lang.Boolean> getPartialFlagPerResultList();
    Code:
       0: aload_0
       1: getfield      #12                 // Field partialFlagPerResult_:Ljava/util/List;
       4: invokestatic  #44                 // Method java/util/Collections.unmodifiableList:(Ljava/util/List;)Ljava/util/List;
       7: areturn

  public int getPartialFlagPerResultCount();
    Code:
       0: aload_0
       1: getfield      #12                 // Field partialFlagPerResult_:Ljava/util/List;
       4: invokeinterface #112,  1          // InterfaceMethod java/util/List.size:()I
       9: ireturn

  public boolean getPartialFlagPerResult(int);
    Code:
       0: aload_0
       1: getfield      #12                 // Field partialFlagPerResult_:Ljava/util/List;
       4: iload_1
       5: invokeinterface #113,  2          // InterfaceMethod java/util/List.get:(I)Ljava/lang/Object;
      10: checkcast     #146                // class java/lang/Boolean
      13: invokevirtual #147                // Method java/lang/Boolean.booleanValue:()Z
      16: ireturn

  public org.apache.hadoop.hbase.protobuf.generated.ClientProtos$ScanResponse$Builder setPartialFlagPerResult(int, boolean);
    Code:
       0: aload_0
       1: invokespecial #88                 // Method ensurePartialFlagPerResultIsMutable:()V
       4: aload_0
       5: getfield      #12                 // Field partialFlagPerResult_:Ljava/util/List;
       8: iload_1
       9: iload_2
      10: invokestatic  #148                // Method java/lang/Boolean.valueOf:(Z)Ljava/lang/Boolean;
      13: invokeinterface #117,  3          // InterfaceMethod java/util/List.set:(ILjava/lang/Object;)Ljava/lang/Object;
      18: pop
      19: aload_0
      20: invokevirtual #68                 // Method onChanged:()V
      23: aload_0
      24: areturn

  public org.apache.hadoop.hbase.protobuf.generated.ClientProtos$ScanResponse$Builder addPartialFlagPerResult(boolean);
    Code:
       0: aload_0
       1: invokespecial #88                 // Method ensurePartialFlagPerResultIsMutable:()V
       4: aload_0
       5: getfield      #12                 // Field partialFlagPerResult_:Ljava/util/List;
       8: iload_1
       9: invokestatic  #148                // Method java/lang/Boolean.valueOf:(Z)Ljava/lang/Boolean;
      12: invokeinterface #118,  2          // InterfaceMethod java/util/List.add:(Ljava/lang/Object;)Z
      17: pop
      18: aload_0
      19: invokevirtual #68                 // Method onChanged:()V
      22: aload_0
      23: areturn

  public org.apache.hadoop.hbase.protobuf.generated.ClientProtos$ScanResponse$Builder addAllPartialFlagPerResult(java.lang.Iterable<? extends java.lang.Boolean>);
    Code:
       0: aload_0
       1: invokespecial #88                 // Method ensurePartialFlagPerResultIsMutable:()V
       4: aload_1
       5: aload_0
       6: getfield      #12                 // Field partialFlagPerResult_:Ljava/util/List;
       9: invokestatic  #119                // Method com/google/protobuf/GeneratedMessage$Builder.addAll:(Ljava/lang/Iterable;Ljava/util/Collection;)V
      12: aload_0
      13: invokevirtual #68                 // Method onChanged:()V
      16: aload_0
      17: areturn

  public org.apache.hadoop.hbase.protobuf.generated.ClientProtos$ScanResponse$Builder clearPartialFlagPerResult();
    Code:
       0: aload_0
       1: invokestatic  #9                  // Method java/util/Collections.emptyList:()Ljava/util/List;
       4: putfield      #12                 // Field partialFlagPerResult_:Ljava/util/List;
       7: aload_0
       8: aload_0
       9: getfield      #25                 // Field bitField0_:I
      12: bipush        -65
      14: iand
      15: putfield      #25                 // Field bitField0_:I
      18: aload_0
      19: invokevirtual #68                 // Method onChanged:()V
      22: aload_0
      23: areturn

  public boolean hasMoreResultsInRegion();
    Code:
       0: aload_0
       1: getfield      #25                 // Field bitField0_:I
       4: sipush        128
       7: iand
       8: sipush        128
      11: if_icmpne     18
      14: iconst_1
      15: goto          19
      18: iconst_0
      19: ireturn

  public boolean getMoreResultsInRegion();
    Code:
       0: aload_0
       1: getfield      #32                 // Field moreResultsInRegion_:Z
       4: ireturn

  public org.apache.hadoop.hbase.protobuf.generated.ClientProtos$ScanResponse$Builder setMoreResultsInRegion(boolean);
    Code:
       0: aload_0
       1: dup
       2: getfield      #25                 // Field bitField0_:I
       5: sipush        128
       8: ior
       9: putfield      #25                 // Field bitField0_:I
      12: aload_0
      13: iload_1
      14: putfield      #32                 // Field moreResultsInRegion_:Z
      17: aload_0
      18: invokevirtual #68                 // Method onChanged:()V
      21: aload_0
      22: areturn

  public org.apache.hadoop.hbase.protobuf.generated.ClientProtos$ScanResponse$Builder clearMoreResultsInRegion();
    Code:
       0: aload_0
       1: aload_0
       2: getfield      #25                 // Field bitField0_:I
       5: sipush        -129
       8: iand
       9: putfield      #25                 // Field bitField0_:I
      12: aload_0
      13: iconst_0
      14: putfield      #32                 // Field moreResultsInRegion_:Z
      17: aload_0
      18: invokevirtual #68                 // Method onChanged:()V
      21: aload_0
      22: areturn

  public boolean hasHeartbeatMessage();
    Code:
       0: aload_0
       1: getfield      #25                 // Field bitField0_:I
       4: sipush        256
       7: iand
       8: sipush        256
      11: if_icmpne     18
      14: iconst_1
      15: goto          19
      18: iconst_0
      19: ireturn

  public boolean getHeartbeatMessage();
    Code:
       0: aload_0
       1: getfield      #33                 // Field heartbeatMessage_:Z
       4: ireturn

  public org.apache.hadoop.hbase.protobuf.generated.ClientProtos$ScanResponse$Builder setHeartbeatMessage(boolean);
    Code:
       0: aload_0
       1: dup
       2: getfield      #25                 // Field bitField0_:I
       5: sipush        256
       8: ior
       9: putfield      #25                 // Field bitField0_:I
      12: aload_0
      13: iload_1
      14: putfield      #33                 // Field heartbeatMessage_:Z
      17: aload_0
      18: invokevirtual #68                 // Method onChanged:()V
      21: aload_0
      22: areturn

  public org.apache.hadoop.hbase.protobuf.generated.ClientProtos$ScanResponse$Builder clearHeartbeatMessage();
    Code:
       0: aload_0
       1: aload_0
       2: getfield      #25                 // Field bitField0_:I
       5: sipush        -257
       8: iand
       9: putfield      #25                 // Field bitField0_:I
      12: aload_0
      13: iconst_0
      14: putfield      #33                 // Field heartbeatMessage_:Z
      17: aload_0
      18: invokevirtual #68                 // Method onChanged:()V
      21: aload_0
      22: areturn

  public boolean hasScanMetrics();
    Code:
       0: aload_0
       1: getfield      #25                 // Field bitField0_:I
       4: sipush        512
       7: iand
       8: sipush        512
      11: if_icmpne     18
      14: iconst_1
      15: goto          19
      18: iconst_0
      19: ireturn

  public org.apache.hadoop.hbase.protobuf.generated.MapReduceProtos$ScanMetrics getScanMetrics();
    Code:
       0: aload_0
       1: getfield      #34                 // Field scanMetricsBuilder_:Lcom/google/protobuf/SingleFieldBuilder;
       4: ifnonnull     12
       7: aload_0
       8: getfield      #14                 // Field scanMetrics_:Lorg/apache/hadoop/hbase/protobuf/generated/MapReduceProtos$ScanMetrics;
      11: areturn
      12: aload_0
      13: getfield      #34                 // Field scanMetricsBuilder_:Lcom/google/protobuf/SingleFieldBuilder;
      16: invokevirtual #149                // Method com/google/protobuf/SingleFieldBuilder.getMessage:()Lcom/google/protobuf/GeneratedMessage;
      19: checkcast     #57                 // class org/apache/hadoop/hbase/protobuf/generated/MapReduceProtos$ScanMetrics
      22: areturn

  public org.apache.hadoop.hbase.protobuf.generated.ClientProtos$ScanResponse$Builder setScanMetrics(org.apache.hadoop.hbase.protobuf.generated.MapReduceProtos$ScanMetrics);
    Code:
       0: aload_0
       1: getfield      #34                 // Field scanMetricsBuilder_:Lcom/google/protobuf/SingleFieldBuilder;
       4: ifnonnull     31
       7: aload_1
       8: ifnonnull     19
      11: new           #124                // class java/lang/NullPointerException
      14: dup
      15: invokespecial #125                // Method java/lang/NullPointerException."<init>":()V
      18: athrow
      19: aload_0
      20: aload_1
      21: putfield      #14                 // Field scanMetrics_:Lorg/apache/hadoop/hbase/protobuf/generated/MapReduceProtos$ScanMetrics;
      24: aload_0
      25: invokevirtual #68                 // Method onChanged:()V
      28: goto          40
      31: aload_0
      32: getfield      #34                 // Field scanMetricsBuilder_:Lcom/google/protobuf/SingleFieldBuilder;
      35: aload_1
      36: invokevirtual #150                // Method com/google/protobuf/SingleFieldBuilder.setMessage:(Lcom/google/protobuf/GeneratedMessage;)Lcom/google/protobuf/SingleFieldBuilder;
      39: pop
      40: aload_0
      41: dup
      42: getfield      #25                 // Field bitField0_:I
      45: sipush        512
      48: ior
      49: putfield      #25                 // Field bitField0_:I
      52: aload_0
      53: areturn

  public org.apache.hadoop.hbase.protobuf.generated.ClientProtos$ScanResponse$Builder setScanMetrics(org.apache.hadoop.hbase.protobuf.generated.MapReduceProtos$ScanMetrics$Builder);
    Code:
       0: aload_0
       1: getfield      #34                 // Field scanMetricsBuilder_:Lcom/google/protobuf/SingleFieldBuilder;
       4: ifnonnull     22
       7: aload_0
       8: aload_1
       9: invokevirtual #151                // Method org/apache/hadoop/hbase/protobuf/generated/MapReduceProtos$ScanMetrics$Builder.build:()Lorg/apache/hadoop/hbase/protobuf/generated/MapReduceProtos$ScanMetrics;
      12: putfield      #14                 // Field scanMetrics_:Lorg/apache/hadoop/hbase/protobuf/generated/MapReduceProtos$ScanMetrics;
      15: aload_0
      16: invokevirtual #68                 // Method onChanged:()V
      19: goto          34
      22: aload_0
      23: getfield      #34                 // Field scanMetricsBuilder_:Lcom/google/protobuf/SingleFieldBuilder;
      26: aload_1
      27: invokevirtual #151                // Method org/apache/hadoop/hbase/protobuf/generated/MapReduceProtos$ScanMetrics$Builder.build:()Lorg/apache/hadoop/hbase/protobuf/generated/MapReduceProtos$ScanMetrics;
      30: invokevirtual #150                // Method com/google/protobuf/SingleFieldBuilder.setMessage:(Lcom/google/protobuf/GeneratedMessage;)Lcom/google/protobuf/SingleFieldBuilder;
      33: pop
      34: aload_0
      35: dup
      36: getfield      #25                 // Field bitField0_:I
      39: sipush        512
      42: ior
      43: putfield      #25                 // Field bitField0_:I
      46: aload_0
      47: areturn

  public org.apache.hadoop.hbase.protobuf.generated.ClientProtos$ScanResponse$Builder mergeScanMetrics(org.apache.hadoop.hbase.protobuf.generated.MapReduceProtos$ScanMetrics);
    Code:
       0: aload_0
       1: getfield      #34                 // Field scanMetricsBuilder_:Lcom/google/protobuf/SingleFieldBuilder;
       4: ifnonnull     64
       7: aload_0
       8: getfield      #25                 // Field bitField0_:I
      11: sipush        512
      14: iand
      15: sipush        512
      18: if_icmpne     52
      21: aload_0
      22: getfield      #14                 // Field scanMetrics_:Lorg/apache/hadoop/hbase/protobuf/generated/MapReduceProtos$ScanMetrics;
      25: invokestatic  #13                 // Method org/apache/hadoop/hbase/protobuf/generated/MapReduceProtos$ScanMetrics.getDefaultInstance:()Lorg/apache/hadoop/hbase/protobuf/generated/MapReduceProtos$ScanMetrics;
      28: if_acmpeq     52
      31: aload_0
      32: aload_0
      33: getfield      #14                 // Field scanMetrics_:Lorg/apache/hadoop/hbase/protobuf/generated/MapReduceProtos$ScanMetrics;
      36: invokestatic  #152                // Method org/apache/hadoop/hbase/protobuf/generated/MapReduceProtos$ScanMetrics.newBuilder:(Lorg/apache/hadoop/hbase/protobuf/generated/MapReduceProtos$ScanMetrics;)Lorg/apache/hadoop/hbase/protobuf/generated/MapReduceProtos$ScanMetrics$Builder;
      39: aload_1
      40: invokevirtual #153                // Method org/apache/hadoop/hbase/protobuf/generated/MapReduceProtos$ScanMetrics$Builder.mergeFrom:(Lorg/apache/hadoop/hbase/protobuf/generated/MapReduceProtos$ScanMetrics;)Lorg/apache/hadoop/hbase/protobuf/generated/MapReduceProtos$ScanMetrics$Builder;
      43: invokevirtual #154                // Method org/apache/hadoop/hbase/protobuf/generated/MapReduceProtos$ScanMetrics$Builder.buildPartial:()Lorg/apache/hadoop/hbase/protobuf/generated/MapReduceProtos$ScanMetrics;
      46: putfield      #14                 // Field scanMetrics_:Lorg/apache/hadoop/hbase/protobuf/generated/MapReduceProtos$ScanMetrics;
      49: goto          57
      52: aload_0
      53: aload_1
      54: putfield      #14                 // Field scanMetrics_:Lorg/apache/hadoop/hbase/protobuf/generated/MapReduceProtos$ScanMetrics;
      57: aload_0
      58: invokevirtual #68                 // Method onChanged:()V
      61: goto          73
      64: aload_0
      65: getfield      #34                 // Field scanMetricsBuilder_:Lcom/google/protobuf/SingleFieldBuilder;
      68: aload_1
      69: invokevirtual #155                // Method com/google/protobuf/SingleFieldBuilder.mergeFrom:(Lcom/google/protobuf/GeneratedMessage;)Lcom/google/protobuf/SingleFieldBuilder;
      72: pop
      73: aload_0
      74: dup
      75: getfield      #25                 // Field bitField0_:I
      78: sipush        512
      81: ior
      82: putfield      #25                 // Field bitField0_:I
      85: aload_0
      86: areturn

  public org.apache.hadoop.hbase.protobuf.generated.ClientProtos$ScanResponse$Builder clearScanMetrics();
    Code:
       0: aload_0
       1: getfield      #34                 // Field scanMetricsBuilder_:Lcom/google/protobuf/SingleFieldBuilder;
       4: ifnonnull     21
       7: aload_0
       8: invokestatic  #13                 // Method org/apache/hadoop/hbase/protobuf/generated/MapReduceProtos$ScanMetrics.getDefaultInstance:()Lorg/apache/hadoop/hbase/protobuf/generated/MapReduceProtos$ScanMetrics;
      11: putfield      #14                 // Field scanMetrics_:Lorg/apache/hadoop/hbase/protobuf/generated/MapReduceProtos$ScanMetrics;
      14: aload_0
      15: invokevirtual #68                 // Method onChanged:()V
      18: goto          29
      21: aload_0
      22: getfield      #34                 // Field scanMetricsBuilder_:Lcom/google/protobuf/SingleFieldBuilder;
      25: invokevirtual #35                 // Method com/google/protobuf/SingleFieldBuilder.clear:()Lcom/google/protobuf/SingleFieldBuilder;
      28: pop
      29: aload_0
      30: aload_0
      31: getfield      #25                 // Field bitField0_:I
      34: sipush        -513
      37: iand
      38: putfield      #25                 // Field bitField0_:I
      41: aload_0
      42: areturn

  public org.apache.hadoop.hbase.protobuf.generated.MapReduceProtos$ScanMetrics$Builder getScanMetricsBuilder();
    Code:
       0: aload_0
       1: dup
       2: getfield      #25                 // Field bitField0_:I
       5: sipush        512
       8: ior
       9: putfield      #25                 // Field bitField0_:I
      12: aload_0
      13: invokevirtual #68                 // Method onChanged:()V
      16: aload_0
      17: invokespecial #21                 // Method getScanMetricsFieldBuilder:()Lcom/google/protobuf/SingleFieldBuilder;
      20: invokevirtual #156                // Method com/google/protobuf/SingleFieldBuilder.getBuilder:()Lcom/google/protobuf/GeneratedMessage$Builder;
      23: checkcast     #157                // class org/apache/hadoop/hbase/protobuf/generated/MapReduceProtos$ScanMetrics$Builder
      26: areturn

  public org.apache.hadoop.hbase.protobuf.generated.MapReduceProtos$ScanMetricsOrBuilder getScanMetricsOrBuilder();
    Code:
       0: aload_0
       1: getfield      #34                 // Field scanMetricsBuilder_:Lcom/google/protobuf/SingleFieldBuilder;
       4: ifnull        18
       7: aload_0
       8: getfield      #34                 // Field scanMetricsBuilder_:Lcom/google/protobuf/SingleFieldBuilder;
      11: invokevirtual #158                // Method com/google/protobuf/SingleFieldBuilder.getMessageOrBuilder:()Lcom/google/protobuf/MessageOrBuilder;
      14: checkcast     #159                // class org/apache/hadoop/hbase/protobuf/generated/MapReduceProtos$ScanMetricsOrBuilder
      17: areturn
      18: aload_0
      19: getfield      #14                 // Field scanMetrics_:Lorg/apache/hadoop/hbase/protobuf/generated/MapReduceProtos$ScanMetrics;
      22: areturn

  public boolean hasMvccReadPoint();
    Code:
       0: aload_0
       1: getfield      #25                 // Field bitField0_:I
       4: sipush        1024
       7: iand
       8: sipush        1024
      11: if_icmpne     18
      14: iconst_1
      15: goto          19
      18: iconst_0
      19: ireturn

  public long getMvccReadPoint();
    Code:
       0: aload_0
       1: getfield      #36                 // Field mvccReadPoint_:J
       4: lreturn

  public org.apache.hadoop.hbase.protobuf.generated.ClientProtos$ScanResponse$Builder setMvccReadPoint(long);
    Code:
       0: aload_0
       1: dup
       2: getfield      #25                 // Field bitField0_:I
       5: sipush        1024
       8: ior
       9: putfield      #25                 // Field bitField0_:I
      12: aload_0
      13: lload_1
      14: putfield      #36                 // Field mvccReadPoint_:J
      17: aload_0
      18: invokevirtual #68                 // Method onChanged:()V
      21: aload_0
      22: areturn

  public org.apache.hadoop.hbase.protobuf.generated.ClientProtos$ScanResponse$Builder clearMvccReadPoint();
    Code:
       0: aload_0
       1: aload_0
       2: getfield      #25                 // Field bitField0_:I
       5: sipush        -1025
       8: iand
       9: putfield      #25                 // Field bitField0_:I
      12: aload_0
      13: lconst_0
      14: putfield      #36                 // Field mvccReadPoint_:J
      17: aload_0
      18: invokevirtual #68                 // Method onChanged:()V
      21: aload_0
      22: areturn

  public boolean hasCursor();
    Code:
       0: aload_0
       1: getfield      #25                 // Field bitField0_:I
       4: sipush        2048
       7: iand
       8: sipush        2048
      11: if_icmpne     18
      14: iconst_1
      15: goto          19
      18: iconst_0
      19: ireturn

  public org.apache.hadoop.hbase.protobuf.generated.ClientProtos$Cursor getCursor();
    Code:
       0: aload_0
       1: getfield      #37                 // Field cursorBuilder_:Lcom/google/protobuf/SingleFieldBuilder;
       4: ifnonnull     12
       7: aload_0
       8: getfield      #16                 // Field cursor_:Lorg/apache/hadoop/hbase/protobuf/generated/ClientProtos$Cursor;
      11: areturn
      12: aload_0
      13: getfield      #37                 // Field cursorBuilder_:Lcom/google/protobuf/SingleFieldBuilder;
      16: invokevirtual #149                // Method com/google/protobuf/SingleFieldBuilder.getMessage:()Lcom/google/protobuf/GeneratedMessage;
      19: checkcast     #60                 // class org/apache/hadoop/hbase/protobuf/generated/ClientProtos$Cursor
      22: areturn

  public org.apache.hadoop.hbase.protobuf.generated.ClientProtos$ScanResponse$Builder setCursor(org.apache.hadoop.hbase.protobuf.generated.ClientProtos$Cursor);
    Code:
       0: aload_0
       1: getfield      #37                 // Field cursorBuilder_:Lcom/google/protobuf/SingleFieldBuilder;
       4: ifnonnull     31
       7: aload_1
       8: ifnonnull     19
      11: new           #124                // class java/lang/NullPointerException
      14: dup
      15: invokespecial #125                // Method java/lang/NullPointerException."<init>":()V
      18: athrow
      19: aload_0
      20: aload_1
      21: putfield      #16                 // Field cursor_:Lorg/apache/hadoop/hbase/protobuf/generated/ClientProtos$Cursor;
      24: aload_0
      25: invokevirtual #68                 // Method onChanged:()V
      28: goto          40
      31: aload_0
      32: getfield      #37                 // Field cursorBuilder_:Lcom/google/protobuf/SingleFieldBuilder;
      35: aload_1
      36: invokevirtual #150                // Method com/google/protobuf/SingleFieldBuilder.setMessage:(Lcom/google/protobuf/GeneratedMessage;)Lcom/google/protobuf/SingleFieldBuilder;
      39: pop
      40: aload_0
      41: dup
      42: getfield      #25                 // Field bitField0_:I
      45: sipush        2048
      48: ior
      49: putfield      #25                 // Field bitField0_:I
      52: aload_0
      53: areturn

  public org.apache.hadoop.hbase.protobuf.generated.ClientProtos$ScanResponse$Builder setCursor(org.apache.hadoop.hbase.protobuf.generated.ClientProtos$Cursor$Builder);
    Code:
       0: aload_0
       1: getfield      #37                 // Field cursorBuilder_:Lcom/google/protobuf/SingleFieldBuilder;
       4: ifnonnull     22
       7: aload_0
       8: aload_1
       9: invokevirtual #162                // Method org/apache/hadoop/hbase/protobuf/generated/ClientProtos$Cursor$Builder.build:()Lorg/apache/hadoop/hbase/protobuf/generated/ClientProtos$Cursor;
      12: putfield      #16                 // Field cursor_:Lorg/apache/hadoop/hbase/protobuf/generated/ClientProtos$Cursor;
      15: aload_0
      16: invokevirtual #68                 // Method onChanged:()V
      19: goto          34
      22: aload_0
      23: getfield      #37                 // Field cursorBuilder_:Lcom/google/protobuf/SingleFieldBuilder;
      26: aload_1
      27: invokevirtual #162                // Method org/apache/hadoop/hbase/protobuf/generated/ClientProtos$Cursor$Builder.build:()Lorg/apache/hadoop/hbase/protobuf/generated/ClientProtos$Cursor;
      30: invokevirtual #150                // Method com/google/protobuf/SingleFieldBuilder.setMessage:(Lcom/google/protobuf/GeneratedMessage;)Lcom/google/protobuf/SingleFieldBuilder;
      33: pop
      34: aload_0
      35: dup
      36: getfield      #25                 // Field bitField0_:I
      39: sipush        2048
      42: ior
      43: putfield      #25                 // Field bitField0_:I
      46: aload_0
      47: areturn

  public org.apache.hadoop.hbase.protobuf.generated.ClientProtos$ScanResponse$Builder mergeCursor(org.apache.hadoop.hbase.protobuf.generated.ClientProtos$Cursor);
    Code:
       0: aload_0
       1: getfield      #37                 // Field cursorBuilder_:Lcom/google/protobuf/SingleFieldBuilder;
       4: ifnonnull     64
       7: aload_0
       8: getfield      #25                 // Field bitField0_:I
      11: sipush        2048
      14: iand
      15: sipush        2048
      18: if_icmpne     52
      21: aload_0
      22: getfield      #16                 // Field cursor_:Lorg/apache/hadoop/hbase/protobuf/generated/ClientProtos$Cursor;
      25: invokestatic  #15                 // Method org/apache/hadoop/hbase/protobuf/generated/ClientProtos$Cursor.getDefaultInstance:()Lorg/apache/hadoop/hbase/protobuf/generated/ClientProtos$Cursor;
      28: if_acmpeq     52
      31: aload_0
      32: aload_0
      33: getfield      #16                 // Field cursor_:Lorg/apache/hadoop/hbase/protobuf/generated/ClientProtos$Cursor;
      36: invokestatic  #163                // Method org/apache/hadoop/hbase/protobuf/generated/ClientProtos$Cursor.newBuilder:(Lorg/apache/hadoop/hbase/protobuf/generated/ClientProtos$Cursor;)Lorg/apache/hadoop/hbase/protobuf/generated/ClientProtos$Cursor$Builder;
      39: aload_1
      40: invokevirtual #164                // Method org/apache/hadoop/hbase/protobuf/generated/ClientProtos$Cursor$Builder.mergeFrom:(Lorg/apache/hadoop/hbase/protobuf/generated/ClientProtos$Cursor;)Lorg/apache/hadoop/hbase/protobuf/generated/ClientProtos$Cursor$Builder;
      43: invokevirtual #165                // Method org/apache/hadoop/hbase/protobuf/generated/ClientProtos$Cursor$Builder.buildPartial:()Lorg/apache/hadoop/hbase/protobuf/generated/ClientProtos$Cursor;
      46: putfield      #16                 // Field cursor_:Lorg/apache/hadoop/hbase/protobuf/generated/ClientProtos$Cursor;
      49: goto          57
      52: aload_0
      53: aload_1
      54: putfield      #16                 // Field cursor_:Lorg/apache/hadoop/hbase/protobuf/generated/ClientProtos$Cursor;
      57: aload_0
      58: invokevirtual #68                 // Method onChanged:()V
      61: goto          73
      64: aload_0
      65: getfield      #37                 // Field cursorBuilder_:Lcom/google/protobuf/SingleFieldBuilder;
      68: aload_1
      69: invokevirtual #155                // Method com/google/protobuf/SingleFieldBuilder.mergeFrom:(Lcom/google/protobuf/GeneratedMessage;)Lcom/google/protobuf/SingleFieldBuilder;
      72: pop
      73: aload_0
      74: dup
      75: getfield      #25                 // Field bitField0_:I
      78: sipush        2048
      81: ior
      82: putfield      #25                 // Field bitField0_:I
      85: aload_0
      86: areturn

  public org.apache.hadoop.hbase.protobuf.generated.ClientProtos$ScanResponse$Builder clearCursor();
    Code:
       0: aload_0
       1: getfield      #37                 // Field cursorBuilder_:Lcom/google/protobuf/SingleFieldBuilder;
       4: ifnonnull     21
       7: aload_0
       8: invokestatic  #15                 // Method org/apache/hadoop/hbase/protobuf/generated/ClientProtos$Cursor.getDefaultInstance:()Lorg/apache/hadoop/hbase/protobuf/generated/ClientProtos$Cursor;
      11: putfield      #16                 // Field cursor_:Lorg/apache/hadoop/hbase/protobuf/generated/ClientProtos$Cursor;
      14: aload_0
      15: invokevirtual #68                 // Method onChanged:()V
      18: goto          29
      21: aload_0
      22: getfield      #37                 // Field cursorBuilder_:Lcom/google/protobuf/SingleFieldBuilder;
      25: invokevirtual #35                 // Method com/google/protobuf/SingleFieldBuilder.clear:()Lcom/google/protobuf/SingleFieldBuilder;
      28: pop
      29: aload_0
      30: aload_0
      31: getfield      #25                 // Field bitField0_:I
      34: sipush        -2049
      37: iand
      38: putfield      #25                 // Field bitField0_:I
      41: aload_0
      42: areturn

  public org.apache.hadoop.hbase.protobuf.generated.ClientProtos$Cursor$Builder getCursorBuilder();
    Code:
       0: aload_0
       1: dup
       2: getfield      #25                 // Field bitField0_:I
       5: sipush        2048
       8: ior
       9: putfield      #25                 // Field bitField0_:I
      12: aload_0
      13: invokevirtual #68                 // Method onChanged:()V
      16: aload_0
      17: invokespecial #22                 // Method getCursorFieldBuilder:()Lcom/google/protobuf/SingleFieldBuilder;
      20: invokevirtual #156                // Method com/google/protobuf/SingleFieldBuilder.getBuilder:()Lcom/google/protobuf/GeneratedMessage$Builder;
      23: checkcast     #166                // class org/apache/hadoop/hbase/protobuf/generated/ClientProtos$Cursor$Builder
      26: areturn

  public org.apache.hadoop.hbase.protobuf.generated.ClientProtos$CursorOrBuilder getCursorOrBuilder();
    Code:
       0: aload_0
       1: getfield      #37                 // Field cursorBuilder_:Lcom/google/protobuf/SingleFieldBuilder;
       4: ifnull        18
       7: aload_0
       8: getfield      #37                 // Field cursorBuilder_:Lcom/google/protobuf/SingleFieldBuilder;
      11: invokevirtual #158                // Method com/google/protobuf/SingleFieldBuilder.getMessageOrBuilder:()Lcom/google/protobuf/MessageOrBuilder;
      14: checkcast     #167                // class org/apache/hadoop/hbase/protobuf/generated/ClientProtos$CursorOrBuilder
      17: areturn
      18: aload_0
      19: getfield      #16                 // Field cursor_:Lorg/apache/hadoop/hbase/protobuf/generated/ClientProtos$Cursor;
      22: areturn

  public com.google.protobuf.GeneratedMessage$Builder clear();
    Code:
       0: aload_0
       1: invokevirtual #168                // Method clear:()Lorg/apache/hadoop/hbase/protobuf/generated/ClientProtos$ScanResponse$Builder;
       4: areturn

  public com.google.protobuf.GeneratedMessage$Builder clone();
    Code:
       0: aload_0
       1: invokevirtual #169                // Method clone:()Lorg/apache/hadoop/hbase/protobuf/generated/ClientProtos$ScanResponse$Builder;
       4: areturn

  public com.google.protobuf.AbstractMessage$Builder mergeFrom(com.google.protobuf.CodedInputStream, com.google.protobuf.ExtensionRegistryLite) throws java.io.IOException;
    Code:
       0: aload_0
       1: aload_1
       2: aload_2
       3: invokevirtual #170                // Method mergeFrom:(Lcom/google/protobuf/CodedInputStream;Lcom/google/protobuf/ExtensionRegistryLite;)Lorg/apache/hadoop/hbase/protobuf/generated/ClientProtos$ScanResponse$Builder;
       6: areturn

  public com.google.protobuf.AbstractMessage$Builder mergeFrom(com.google.protobuf.Message);
    Code:
       0: aload_0
       1: aload_1
       2: invokevirtual #171                // Method mergeFrom:(Lcom/google/protobuf/Message;)Lorg/apache/hadoop/hbase/protobuf/generated/ClientProtos$ScanResponse$Builder;
       5: areturn

  public com.google.protobuf.AbstractMessage$Builder clear();
    Code:
       0: aload_0
       1: invokevirtual #168                // Method clear:()Lorg/apache/hadoop/hbase/protobuf/generated/ClientProtos$ScanResponse$Builder;
       4: areturn

  public com.google.protobuf.AbstractMessage$Builder clone();
    Code:
       0: aload_0
       1: invokevirtual #169                // Method clone:()Lorg/apache/hadoop/hbase/protobuf/generated/ClientProtos$ScanResponse$Builder;
       4: areturn

  public com.google.protobuf.Message$Builder mergeFrom(com.google.protobuf.CodedInputStream, com.google.protobuf.ExtensionRegistryLite) throws java.io.IOException;
    Code:
       0: aload_0
       1: aload_1
       2: aload_2
       3: invokevirtual #170                // Method mergeFrom:(Lcom/google/protobuf/CodedInputStream;Lcom/google/protobuf/ExtensionRegistryLite;)Lorg/apache/hadoop/hbase/protobuf/generated/ClientProtos$ScanResponse$Builder;
       6: areturn

  public com.google.protobuf.Message$Builder clone();
    Code:
       0: aload_0
       1: invokevirtual #169                // Method clone:()Lorg/apache/hadoop/hbase/protobuf/generated/ClientProtos$ScanResponse$Builder;
       4: areturn

  public com.google.protobuf.Message buildPartial();
    Code:
       0: aload_0
       1: invokevirtual #38                 // Method buildPartial:()Lorg/apache/hadoop/hbase/protobuf/generated/ClientProtos$ScanResponse;
       4: areturn

  public com.google.protobuf.Message build();
    Code:
       0: aload_0
       1: invokevirtual #172                // Method build:()Lorg/apache/hadoop/hbase/protobuf/generated/ClientProtos$ScanResponse;
       4: areturn

  public com.google.protobuf.Message$Builder mergeFrom(com.google.protobuf.Message);
    Code:
       0: aload_0
       1: aload_1
       2: invokevirtual #171                // Method mergeFrom:(Lcom/google/protobuf/Message;)Lorg/apache/hadoop/hbase/protobuf/generated/ClientProtos$ScanResponse$Builder;
       5: areturn

  public com.google.protobuf.Message$Builder clear();
    Code:
       0: aload_0
       1: invokevirtual #168                // Method clear:()Lorg/apache/hadoop/hbase/protobuf/generated/ClientProtos$ScanResponse$Builder;
       4: areturn

  public com.google.protobuf.MessageLite$Builder mergeFrom(com.google.protobuf.CodedInputStream, com.google.protobuf.ExtensionRegistryLite) throws java.io.IOException;
    Code:
       0: aload_0
       1: aload_1
       2: aload_2
       3: invokevirtual #170                // Method mergeFrom:(Lcom/google/protobuf/CodedInputStream;Lcom/google/protobuf/ExtensionRegistryLite;)Lorg/apache/hadoop/hbase/protobuf/generated/ClientProtos$ScanResponse$Builder;
       6: areturn

  public com.google.protobuf.MessageLite$Builder clone();
    Code:
       0: aload_0
       1: invokevirtual #169                // Method clone:()Lorg/apache/hadoop/hbase/protobuf/generated/ClientProtos$ScanResponse$Builder;
       4: areturn

  public com.google.protobuf.MessageLite buildPartial();
    Code:
       0: aload_0
       1: invokevirtual #38                 // Method buildPartial:()Lorg/apache/hadoop/hbase/protobuf/generated/ClientProtos$ScanResponse;
       4: areturn

  public com.google.protobuf.MessageLite build();
    Code:
       0: aload_0
       1: invokevirtual #172                // Method build:()Lorg/apache/hadoop/hbase/protobuf/generated/ClientProtos$ScanResponse;
       4: areturn

  public com.google.protobuf.MessageLite$Builder clear();
    Code:
       0: aload_0
       1: invokevirtual #168                // Method clear:()Lorg/apache/hadoop/hbase/protobuf/generated/ClientProtos$ScanResponse$Builder;
       4: areturn

  public com.google.protobuf.MessageLite getDefaultInstanceForType();
    Code:
       0: aload_0
       1: invokevirtual #173                // Method getDefaultInstanceForType:()Lorg/apache/hadoop/hbase/protobuf/generated/ClientProtos$ScanResponse;
       4: areturn

  public com.google.protobuf.Message getDefaultInstanceForType();
    Code:
       0: aload_0
       1: invokevirtual #173                // Method getDefaultInstanceForType:()Lorg/apache/hadoop/hbase/protobuf/generated/ClientProtos$ScanResponse;
       4: areturn

  public com.google.protobuf.AbstractMessageLite$Builder mergeFrom(com.google.protobuf.CodedInputStream, com.google.protobuf.ExtensionRegistryLite) throws java.io.IOException;
    Code:
       0: aload_0
       1: aload_1
       2: aload_2
       3: invokevirtual #170                // Method mergeFrom:(Lcom/google/protobuf/CodedInputStream;Lcom/google/protobuf/ExtensionRegistryLite;)Lorg/apache/hadoop/hbase/protobuf/generated/ClientProtos$ScanResponse$Builder;
       6: areturn

  public com.google.protobuf.AbstractMessageLite$Builder clone();
    Code:
       0: aload_0
       1: invokevirtual #169                // Method clone:()Lorg/apache/hadoop/hbase/protobuf/generated/ClientProtos$ScanResponse$Builder;
       4: areturn

  public java.lang.Object clone() throws java.lang.CloneNotSupportedException;
    Code:
       0: aload_0
       1: invokevirtual #169                // Method clone:()Lorg/apache/hadoop/hbase/protobuf/generated/ClientProtos$ScanResponse$Builder;
       4: areturn

  static org.apache.hadoop.hbase.protobuf.generated.ClientProtos$ScanResponse$Builder access$23000();
    Code:
       0: invokestatic  #2                  // Method create:()Lorg/apache/hadoop/hbase/protobuf/generated/ClientProtos$ScanResponse$Builder;
       3: areturn

  org.apache.hadoop.hbase.protobuf.generated.ClientProtos$ScanResponse$Builder(com.google.protobuf.GeneratedMessage$BuilderParent, org.apache.hadoop.hbase.protobuf.generated.ClientProtos$1);
    Code:
       0: aload_0
       1: aload_1
       2: invokespecial #1                  // Method "<init>":(Lcom/google/protobuf/GeneratedMessage$BuilderParent;)V
       5: return
}
