Compiled from "ClientUtil.java"
public class org.apache.hadoop.hbase.client.ClientUtil {
  public org.apache.hadoop.hbase.client.ClientUtil();
    Code:
       0: aload_0
       1: invokespecial #1                  // Method java/lang/Object."<init>":()V
       4: return

  public static boolean areScanStartRowAndStopRowEqual(byte[], byte[]);
    Code:
       0: aload_0
       1: ifnull        21
       4: aload_0
       5: arraylength
       6: ifle          21
       9: aload_0
      10: aload_1
      11: invokestatic  #2                  // Method org/apache/hadoop/hbase/util/Bytes.equals:([B[B)Z
      14: ifeq          21
      17: iconst_1
      18: goto          22
      21: iconst_0
      22: ireturn

  public static org.apache.hadoop.hbase.client.Cursor createCursor(byte[]);
    Code:
       0: new           #3                  // class org/apache/hadoop/hbase/client/Cursor
       3: dup
       4: aload_0
       5: invokespecial #4                  // Method org/apache/hadoop/hbase/client/Cursor."<init>":([B)V
       8: areturn
}
