Compiled from "ClusterStatusProtos.java"
public final class org.apache.hadoop.hbase.protobuf.generated.ClusterStatusProtos$RegionState$State extends java.lang.Enum<org.apache.hadoop.hbase.protobuf.generated.ClusterStatusProtos$RegionState$State> implements com.google.protobuf.ProtocolMessageEnum {
  public static final org.apache.hadoop.hbase.protobuf.generated.ClusterStatusProtos$RegionState$State OFFLINE;

  public static final org.apache.hadoop.hbase.protobuf.generated.ClusterStatusProtos$RegionState$State PENDING_OPEN;

  public static final org.apache.hadoop.hbase.protobuf.generated.ClusterStatusProtos$RegionState$State OPENING;

  public static final org.apache.hadoop.hbase.protobuf.generated.ClusterStatusProtos$RegionState$State OPEN;

  public static final org.apache.hadoop.hbase.protobuf.generated.ClusterStatusProtos$RegionState$State PENDING_CLOSE;

  public static final org.apache.hadoop.hbase.protobuf.generated.ClusterStatusProtos$RegionState$State CLOSING;

  public static final org.apache.hadoop.hbase.protobuf.generated.ClusterStatusProtos$RegionState$State CLOSED;

  public static final org.apache.hadoop.hbase.protobuf.generated.ClusterStatusProtos$RegionState$State SPLITTING;

  public static final org.apache.hadoop.hbase.protobuf.generated.ClusterStatusProtos$RegionState$State SPLIT;

  public static final org.apache.hadoop.hbase.protobuf.generated.ClusterStatusProtos$RegionState$State FAILED_OPEN;

  public static final org.apache.hadoop.hbase.protobuf.generated.ClusterStatusProtos$RegionState$State FAILED_CLOSE;

  public static final org.apache.hadoop.hbase.protobuf.generated.ClusterStatusProtos$RegionState$State MERGING;

  public static final org.apache.hadoop.hbase.protobuf.generated.ClusterStatusProtos$RegionState$State MERGED;

  public static final org.apache.hadoop.hbase.protobuf.generated.ClusterStatusProtos$RegionState$State SPLITTING_NEW;

  public static final org.apache.hadoop.hbase.protobuf.generated.ClusterStatusProtos$RegionState$State MERGING_NEW;

  public static final int OFFLINE_VALUE;

  public static final int PENDING_OPEN_VALUE;

  public static final int OPENING_VALUE;

  public static final int OPEN_VALUE;

  public static final int PENDING_CLOSE_VALUE;

  public static final int CLOSING_VALUE;

  public static final int CLOSED_VALUE;

  public static final int SPLITTING_VALUE;

  public static final int SPLIT_VALUE;

  public static final int FAILED_OPEN_VALUE;

  public static final int FAILED_CLOSE_VALUE;

  public static final int MERGING_VALUE;

  public static final int MERGED_VALUE;

  public static final int SPLITTING_NEW_VALUE;

  public static final int MERGING_NEW_VALUE;

  public static org.apache.hadoop.hbase.protobuf.generated.ClusterStatusProtos$RegionState$State[] values();
    Code:
       0: getstatic     #1                  // Field $VALUES:[Lorg/apache/hadoop/hbase/protobuf/generated/ClusterStatusProtos$RegionState$State;
       3: invokevirtual #2                  // Method "[Lorg/apache/hadoop/hbase/protobuf/generated/ClusterStatusProtos$RegionState$State;".clone:()Ljava/lang/Object;
       6: checkcast     #3                  // class "[Lorg/apache/hadoop/hbase/protobuf/generated/ClusterStatusProtos$RegionState$State;"
       9: areturn

  public static org.apache.hadoop.hbase.protobuf.generated.ClusterStatusProtos$RegionState$State valueOf(java.lang.String);
    Code:
       0: ldc           #4                  // class org/apache/hadoop/hbase/protobuf/generated/ClusterStatusProtos$RegionState$State
       2: aload_0
       3: invokestatic  #5                  // Method java/lang/Enum.valueOf:(Ljava/lang/Class;Ljava/lang/String;)Ljava/lang/Enum;
       6: checkcast     #4                  // class org/apache/hadoop/hbase/protobuf/generated/ClusterStatusProtos$RegionState$State
       9: areturn

  public final int getNumber();
    Code:
       0: aload_0
       1: getfield      #6                  // Field value:I
       4: ireturn

  public static org.apache.hadoop.hbase.protobuf.generated.ClusterStatusProtos$RegionState$State valueOf(int);
    Code:
       0: iload_0
       1: tableswitch   { // 0 to 14
                     0: 76
                     1: 80
                     2: 84
                     3: 88
                     4: 92
                     5: 96
                     6: 100
                     7: 104
                     8: 108
                     9: 112
                    10: 116
                    11: 120
                    12: 124
                    13: 128
                    14: 132
               default: 136
          }
      76: getstatic     #7                  // Field OFFLINE:Lorg/apache/hadoop/hbase/protobuf/generated/ClusterStatusProtos$RegionState$State;
      79: areturn
      80: getstatic     #8                  // Field PENDING_OPEN:Lorg/apache/hadoop/hbase/protobuf/generated/ClusterStatusProtos$RegionState$State;
      83: areturn
      84: getstatic     #9                  // Field OPENING:Lorg/apache/hadoop/hbase/protobuf/generated/ClusterStatusProtos$RegionState$State;
      87: areturn
      88: getstatic     #10                 // Field OPEN:Lorg/apache/hadoop/hbase/protobuf/generated/ClusterStatusProtos$RegionState$State;
      91: areturn
      92: getstatic     #11                 // Field PENDING_CLOSE:Lorg/apache/hadoop/hbase/protobuf/generated/ClusterStatusProtos$RegionState$State;
      95: areturn
      96: getstatic     #12                 // Field CLOSING:Lorg/apache/hadoop/hbase/protobuf/generated/ClusterStatusProtos$RegionState$State;
      99: areturn
     100: getstatic     #13                 // Field CLOSED:Lorg/apache/hadoop/hbase/protobuf/generated/ClusterStatusProtos$RegionState$State;
     103: areturn
     104: getstatic     #14                 // Field SPLITTING:Lorg/apache/hadoop/hbase/protobuf/generated/ClusterStatusProtos$RegionState$State;
     107: areturn
     108: getstatic     #15                 // Field SPLIT:Lorg/apache/hadoop/hbase/protobuf/generated/ClusterStatusProtos$RegionState$State;
     111: areturn
     112: getstatic     #16                 // Field FAILED_OPEN:Lorg/apache/hadoop/hbase/protobuf/generated/ClusterStatusProtos$RegionState$State;
     115: areturn
     116: getstatic     #17                 // Field FAILED_CLOSE:Lorg/apache/hadoop/hbase/protobuf/generated/ClusterStatusProtos$RegionState$State;
     119: areturn
     120: getstatic     #18                 // Field MERGING:Lorg/apache/hadoop/hbase/protobuf/generated/ClusterStatusProtos$RegionState$State;
     123: areturn
     124: getstatic     #19                 // Field MERGED:Lorg/apache/hadoop/hbase/protobuf/generated/ClusterStatusProtos$RegionState$State;
     127: areturn
     128: getstatic     #20                 // Field SPLITTING_NEW:Lorg/apache/hadoop/hbase/protobuf/generated/ClusterStatusProtos$RegionState$State;
     131: areturn
     132: getstatic     #21                 // Field MERGING_NEW:Lorg/apache/hadoop/hbase/protobuf/generated/ClusterStatusProtos$RegionState$State;
     135: areturn
     136: aconst_null
     137: areturn

  public static com.google.protobuf.Internal$EnumLiteMap<org.apache.hadoop.hbase.protobuf.generated.ClusterStatusProtos$RegionState$State> internalGetValueMap();
    Code:
       0: getstatic     #22                 // Field internalValueMap:Lcom/google/protobuf/Internal$EnumLiteMap;
       3: areturn

  public final com.google.protobuf.Descriptors$EnumValueDescriptor getValueDescriptor();
    Code:
       0: invokestatic  #23                 // Method getDescriptor:()Lcom/google/protobuf/Descriptors$EnumDescriptor;
       3: invokevirtual #24                 // Method com/google/protobuf/Descriptors$EnumDescriptor.getValues:()Ljava/util/List;
       6: aload_0
       7: getfield      #25                 // Field index:I
      10: invokeinterface #26,  2           // InterfaceMethod java/util/List.get:(I)Ljava/lang/Object;
      15: checkcast     #27                 // class com/google/protobuf/Descriptors$EnumValueDescriptor
      18: areturn

  public final com.google.protobuf.Descriptors$EnumDescriptor getDescriptorForType();
    Code:
       0: invokestatic  #23                 // Method getDescriptor:()Lcom/google/protobuf/Descriptors$EnumDescriptor;
       3: areturn

  public static final com.google.protobuf.Descriptors$EnumDescriptor getDescriptor();
    Code:
       0: invokestatic  #28                 // Method org/apache/hadoop/hbase/protobuf/generated/ClusterStatusProtos$RegionState.getDescriptor:()Lcom/google/protobuf/Descriptors$Descriptor;
       3: invokevirtual #29                 // Method com/google/protobuf/Descriptors$Descriptor.getEnumTypes:()Ljava/util/List;
       6: iconst_0
       7: invokeinterface #26,  2           // InterfaceMethod java/util/List.get:(I)Ljava/lang/Object;
      12: checkcast     #30                 // class com/google/protobuf/Descriptors$EnumDescriptor
      15: areturn

  public static org.apache.hadoop.hbase.protobuf.generated.ClusterStatusProtos$RegionState$State valueOf(com.google.protobuf.Descriptors$EnumValueDescriptor);
    Code:
       0: aload_0
       1: invokevirtual #31                 // Method com/google/protobuf/Descriptors$EnumValueDescriptor.getType:()Lcom/google/protobuf/Descriptors$EnumDescriptor;
       4: invokestatic  #23                 // Method getDescriptor:()Lcom/google/protobuf/Descriptors$EnumDescriptor;
       7: if_acmpeq     20
      10: new           #32                 // class java/lang/IllegalArgumentException
      13: dup
      14: ldc           #33                 // String EnumValueDescriptor is not for this type.
      16: invokespecial #34                 // Method java/lang/IllegalArgumentException."<init>":(Ljava/lang/String;)V
      19: athrow
      20: getstatic     #35                 // Field VALUES:[Lorg/apache/hadoop/hbase/protobuf/generated/ClusterStatusProtos$RegionState$State;
      23: aload_0
      24: invokevirtual #36                 // Method com/google/protobuf/Descriptors$EnumValueDescriptor.getIndex:()I
      27: aaload
      28: areturn

  static {};
    Code:
       0: new           #4                  // class org/apache/hadoop/hbase/protobuf/generated/ClusterStatusProtos$RegionState$State
       3: dup
       4: ldc           #38                 // String OFFLINE
       6: iconst_0
       7: iconst_0
       8: iconst_0
       9: invokespecial #39                 // Method "<init>":(Ljava/lang/String;III)V
      12: putstatic     #7                  // Field OFFLINE:Lorg/apache/hadoop/hbase/protobuf/generated/ClusterStatusProtos$RegionState$State;
      15: new           #4                  // class org/apache/hadoop/hbase/protobuf/generated/ClusterStatusProtos$RegionState$State
      18: dup
      19: ldc           #40                 // String PENDING_OPEN
      21: iconst_1
      22: iconst_1
      23: iconst_1
      24: invokespecial #39                 // Method "<init>":(Ljava/lang/String;III)V
      27: putstatic     #8                  // Field PENDING_OPEN:Lorg/apache/hadoop/hbase/protobuf/generated/ClusterStatusProtos$RegionState$State;
      30: new           #4                  // class org/apache/hadoop/hbase/protobuf/generated/ClusterStatusProtos$RegionState$State
      33: dup
      34: ldc           #41                 // String OPENING
      36: iconst_2
      37: iconst_2
      38: iconst_2
      39: invokespecial #39                 // Method "<init>":(Ljava/lang/String;III)V
      42: putstatic     #9                  // Field OPENING:Lorg/apache/hadoop/hbase/protobuf/generated/ClusterStatusProtos$RegionState$State;
      45: new           #4                  // class org/apache/hadoop/hbase/protobuf/generated/ClusterStatusProtos$RegionState$State
      48: dup
      49: ldc           #42                 // String OPEN
      51: iconst_3
      52: iconst_3
      53: iconst_3
      54: invokespecial #39                 // Method "<init>":(Ljava/lang/String;III)V
      57: putstatic     #10                 // Field OPEN:Lorg/apache/hadoop/hbase/protobuf/generated/ClusterStatusProtos$RegionState$State;
      60: new           #4                  // class org/apache/hadoop/hbase/protobuf/generated/ClusterStatusProtos$RegionState$State
      63: dup
      64: ldc           #43                 // String PENDING_CLOSE
      66: iconst_4
      67: iconst_4
      68: iconst_4
      69: invokespecial #39                 // Method "<init>":(Ljava/lang/String;III)V
      72: putstatic     #11                 // Field PENDING_CLOSE:Lorg/apache/hadoop/hbase/protobuf/generated/ClusterStatusProtos$RegionState$State;
      75: new           #4                  // class org/apache/hadoop/hbase/protobuf/generated/ClusterStatusProtos$RegionState$State
      78: dup
      79: ldc           #44                 // String CLOSING
      81: iconst_5
      82: iconst_5
      83: iconst_5
      84: invokespecial #39                 // Method "<init>":(Ljava/lang/String;III)V
      87: putstatic     #12                 // Field CLOSING:Lorg/apache/hadoop/hbase/protobuf/generated/ClusterStatusProtos$RegionState$State;
      90: new           #4                  // class org/apache/hadoop/hbase/protobuf/generated/ClusterStatusProtos$RegionState$State
      93: dup
      94: ldc           #45                 // String CLOSED
      96: bipush        6
      98: bipush        6
     100: bipush        6
     102: invokespecial #39                 // Method "<init>":(Ljava/lang/String;III)V
     105: putstatic     #13                 // Field CLOSED:Lorg/apache/hadoop/hbase/protobuf/generated/ClusterStatusProtos$RegionState$State;
     108: new           #4                  // class org/apache/hadoop/hbase/protobuf/generated/ClusterStatusProtos$RegionState$State
     111: dup
     112: ldc           #46                 // String SPLITTING
     114: bipush        7
     116: bipush        7
     118: bipush        7
     120: invokespecial #39                 // Method "<init>":(Ljava/lang/String;III)V
     123: putstatic     #14                 // Field SPLITTING:Lorg/apache/hadoop/hbase/protobuf/generated/ClusterStatusProtos$RegionState$State;
     126: new           #4                  // class org/apache/hadoop/hbase/protobuf/generated/ClusterStatusProtos$RegionState$State
     129: dup
     130: ldc           #47                 // String SPLIT
     132: bipush        8
     134: bipush        8
     136: bipush        8
     138: invokespecial #39                 // Method "<init>":(Ljava/lang/String;III)V
     141: putstatic     #15                 // Field SPLIT:Lorg/apache/hadoop/hbase/protobuf/generated/ClusterStatusProtos$RegionState$State;
     144: new           #4                  // class org/apache/hadoop/hbase/protobuf/generated/ClusterStatusProtos$RegionState$State
     147: dup
     148: ldc           #48                 // String FAILED_OPEN
     150: bipush        9
     152: bipush        9
     154: bipush        9
     156: invokespecial #39                 // Method "<init>":(Ljava/lang/String;III)V
     159: putstatic     #16                 // Field FAILED_OPEN:Lorg/apache/hadoop/hbase/protobuf/generated/ClusterStatusProtos$RegionState$State;
     162: new           #4                  // class org/apache/hadoop/hbase/protobuf/generated/ClusterStatusProtos$RegionState$State
     165: dup
     166: ldc           #49                 // String FAILED_CLOSE
     168: bipush        10
     170: bipush        10
     172: bipush        10
     174: invokespecial #39                 // Method "<init>":(Ljava/lang/String;III)V
     177: putstatic     #17                 // Field FAILED_CLOSE:Lorg/apache/hadoop/hbase/protobuf/generated/ClusterStatusProtos$RegionState$State;
     180: new           #4                  // class org/apache/hadoop/hbase/protobuf/generated/ClusterStatusProtos$RegionState$State
     183: dup
     184: ldc           #50                 // String MERGING
     186: bipush        11
     188: bipush        11
     190: bipush        11
     192: invokespecial #39                 // Method "<init>":(Ljava/lang/String;III)V
     195: putstatic     #18                 // Field MERGING:Lorg/apache/hadoop/hbase/protobuf/generated/ClusterStatusProtos$RegionState$State;
     198: new           #4                  // class org/apache/hadoop/hbase/protobuf/generated/ClusterStatusProtos$RegionState$State
     201: dup
     202: ldc           #51                 // String MERGED
     204: bipush        12
     206: bipush        12
     208: bipush        12
     210: invokespecial #39                 // Method "<init>":(Ljava/lang/String;III)V
     213: putstatic     #19                 // Field MERGED:Lorg/apache/hadoop/hbase/protobuf/generated/ClusterStatusProtos$RegionState$State;
     216: new           #4                  // class org/apache/hadoop/hbase/protobuf/generated/ClusterStatusProtos$RegionState$State
     219: dup
     220: ldc           #52                 // String SPLITTING_NEW
     222: bipush        13
     224: bipush        13
     226: bipush        13
     228: invokespecial #39                 // Method "<init>":(Ljava/lang/String;III)V
     231: putstatic     #20                 // Field SPLITTING_NEW:Lorg/apache/hadoop/hbase/protobuf/generated/ClusterStatusProtos$RegionState$State;
     234: new           #4                  // class org/apache/hadoop/hbase/protobuf/generated/ClusterStatusProtos$RegionState$State
     237: dup
     238: ldc           #53                 // String MERGING_NEW
     240: bipush        14
     242: bipush        14
     244: bipush        14
     246: invokespecial #39                 // Method "<init>":(Ljava/lang/String;III)V
     249: putstatic     #21                 // Field MERGING_NEW:Lorg/apache/hadoop/hbase/protobuf/generated/ClusterStatusProtos$RegionState$State;
     252: bipush        15
     254: anewarray     #4                  // class org/apache/hadoop/hbase/protobuf/generated/ClusterStatusProtos$RegionState$State
     257: dup
     258: iconst_0
     259: getstatic     #7                  // Field OFFLINE:Lorg/apache/hadoop/hbase/protobuf/generated/ClusterStatusProtos$RegionState$State;
     262: aastore
     263: dup
     264: iconst_1
     265: getstatic     #8                  // Field PENDING_OPEN:Lorg/apache/hadoop/hbase/protobuf/generated/ClusterStatusProtos$RegionState$State;
     268: aastore
     269: dup
     270: iconst_2
     271: getstatic     #9                  // Field OPENING:Lorg/apache/hadoop/hbase/protobuf/generated/ClusterStatusProtos$RegionState$State;
     274: aastore
     275: dup
     276: iconst_3
     277: getstatic     #10                 // Field OPEN:Lorg/apache/hadoop/hbase/protobuf/generated/ClusterStatusProtos$RegionState$State;
     280: aastore
     281: dup
     282: iconst_4
     283: getstatic     #11                 // Field PENDING_CLOSE:Lorg/apache/hadoop/hbase/protobuf/generated/ClusterStatusProtos$RegionState$State;
     286: aastore
     287: dup
     288: iconst_5
     289: getstatic     #12                 // Field CLOSING:Lorg/apache/hadoop/hbase/protobuf/generated/ClusterStatusProtos$RegionState$State;
     292: aastore
     293: dup
     294: bipush        6
     296: getstatic     #13                 // Field CLOSED:Lorg/apache/hadoop/hbase/protobuf/generated/ClusterStatusProtos$RegionState$State;
     299: aastore
     300: dup
     301: bipush        7
     303: getstatic     #14                 // Field SPLITTING:Lorg/apache/hadoop/hbase/protobuf/generated/ClusterStatusProtos$RegionState$State;
     306: aastore
     307: dup
     308: bipush        8
     310: getstatic     #15                 // Field SPLIT:Lorg/apache/hadoop/hbase/protobuf/generated/ClusterStatusProtos$RegionState$State;
     313: aastore
     314: dup
     315: bipush        9
     317: getstatic     #16                 // Field FAILED_OPEN:Lorg/apache/hadoop/hbase/protobuf/generated/ClusterStatusProtos$RegionState$State;
     320: aastore
     321: dup
     322: bipush        10
     324: getstatic     #17                 // Field FAILED_CLOSE:Lorg/apache/hadoop/hbase/protobuf/generated/ClusterStatusProtos$RegionState$State;
     327: aastore
     328: dup
     329: bipush        11
     331: getstatic     #18                 // Field MERGING:Lorg/apache/hadoop/hbase/protobuf/generated/ClusterStatusProtos$RegionState$State;
     334: aastore
     335: dup
     336: bipush        12
     338: getstatic     #19                 // Field MERGED:Lorg/apache/hadoop/hbase/protobuf/generated/ClusterStatusProtos$RegionState$State;
     341: aastore
     342: dup
     343: bipush        13
     345: getstatic     #20                 // Field SPLITTING_NEW:Lorg/apache/hadoop/hbase/protobuf/generated/ClusterStatusProtos$RegionState$State;
     348: aastore
     349: dup
     350: bipush        14
     352: getstatic     #21                 // Field MERGING_NEW:Lorg/apache/hadoop/hbase/protobuf/generated/ClusterStatusProtos$RegionState$State;
     355: aastore
     356: putstatic     #1                  // Field $VALUES:[Lorg/apache/hadoop/hbase/protobuf/generated/ClusterStatusProtos$RegionState$State;
     359: new           #54                 // class org/apache/hadoop/hbase/protobuf/generated/ClusterStatusProtos$RegionState$State$1
     362: dup
     363: invokespecial #55                 // Method org/apache/hadoop/hbase/protobuf/generated/ClusterStatusProtos$RegionState$State$1."<init>":()V
     366: putstatic     #22                 // Field internalValueMap:Lcom/google/protobuf/Internal$EnumLiteMap;
     369: invokestatic  #56                 // Method values:()[Lorg/apache/hadoop/hbase/protobuf/generated/ClusterStatusProtos$RegionState$State;
     372: putstatic     #35                 // Field VALUES:[Lorg/apache/hadoop/hbase/protobuf/generated/ClusterStatusProtos$RegionState$State;
     375: return
}
