Compiled from "ClusterStatusProtos.java"
public final class org.apache.hadoop.hbase.protobuf.generated.ClusterStatusProtos$Option extends java.lang.Enum<org.apache.hadoop.hbase.protobuf.generated.ClusterStatusProtos$Option> implements com.google.protobuf.ProtocolMessageEnum {
  public static final org.apache.hadoop.hbase.protobuf.generated.ClusterStatusProtos$Option HBASE_VERSION;

  public static final org.apache.hadoop.hbase.protobuf.generated.ClusterStatusProtos$Option CLUSTER_ID;

  public static final org.apache.hadoop.hbase.protobuf.generated.ClusterStatusProtos$Option LIVE_SERVERS;

  public static final org.apache.hadoop.hbase.protobuf.generated.ClusterStatusProtos$Option DEAD_SERVERS;

  public static final org.apache.hadoop.hbase.protobuf.generated.ClusterStatusProtos$Option MASTER;

  public static final org.apache.hadoop.hbase.protobuf.generated.ClusterStatusProtos$Option BACKUP_MASTERS;

  public static final org.apache.hadoop.hbase.protobuf.generated.ClusterStatusProtos$Option MASTER_COPROCESSORS;

  public static final org.apache.hadoop.hbase.protobuf.generated.ClusterStatusProtos$Option REGIONS_IN_TRANSITION;

  public static final org.apache.hadoop.hbase.protobuf.generated.ClusterStatusProtos$Option BALANCER_ON;

  public static final int HBASE_VERSION_VALUE;

  public static final int CLUSTER_ID_VALUE;

  public static final int LIVE_SERVERS_VALUE;

  public static final int DEAD_SERVERS_VALUE;

  public static final int MASTER_VALUE;

  public static final int BACKUP_MASTERS_VALUE;

  public static final int MASTER_COPROCESSORS_VALUE;

  public static final int REGIONS_IN_TRANSITION_VALUE;

  public static final int BALANCER_ON_VALUE;

  public static org.apache.hadoop.hbase.protobuf.generated.ClusterStatusProtos$Option[] values();
    Code:
       0: getstatic     #1                  // Field $VALUES:[Lorg/apache/hadoop/hbase/protobuf/generated/ClusterStatusProtos$Option;
       3: invokevirtual #2                  // Method "[Lorg/apache/hadoop/hbase/protobuf/generated/ClusterStatusProtos$Option;".clone:()Ljava/lang/Object;
       6: checkcast     #3                  // class "[Lorg/apache/hadoop/hbase/protobuf/generated/ClusterStatusProtos$Option;"
       9: areturn

  public static org.apache.hadoop.hbase.protobuf.generated.ClusterStatusProtos$Option valueOf(java.lang.String);
    Code:
       0: ldc           #4                  // class org/apache/hadoop/hbase/protobuf/generated/ClusterStatusProtos$Option
       2: aload_0
       3: invokestatic  #5                  // Method java/lang/Enum.valueOf:(Ljava/lang/Class;Ljava/lang/String;)Ljava/lang/Enum;
       6: checkcast     #4                  // class org/apache/hadoop/hbase/protobuf/generated/ClusterStatusProtos$Option
       9: areturn

  public final int getNumber();
    Code:
       0: aload_0
       1: getfield      #6                  // Field value:I
       4: ireturn

  public static org.apache.hadoop.hbase.protobuf.generated.ClusterStatusProtos$Option valueOf(int);
    Code:
       0: iload_0
       1: tableswitch   { // 0 to 8
                     0: 52
                     1: 56
                     2: 60
                     3: 64
                     4: 68
                     5: 72
                     6: 76
                     7: 80
                     8: 84
               default: 88
          }
      52: getstatic     #7                  // Field HBASE_VERSION:Lorg/apache/hadoop/hbase/protobuf/generated/ClusterStatusProtos$Option;
      55: areturn
      56: getstatic     #8                  // Field CLUSTER_ID:Lorg/apache/hadoop/hbase/protobuf/generated/ClusterStatusProtos$Option;
      59: areturn
      60: getstatic     #9                  // Field LIVE_SERVERS:Lorg/apache/hadoop/hbase/protobuf/generated/ClusterStatusProtos$Option;
      63: areturn
      64: getstatic     #10                 // Field DEAD_SERVERS:Lorg/apache/hadoop/hbase/protobuf/generated/ClusterStatusProtos$Option;
      67: areturn
      68: getstatic     #11                 // Field MASTER:Lorg/apache/hadoop/hbase/protobuf/generated/ClusterStatusProtos$Option;
      71: areturn
      72: getstatic     #12                 // Field BACKUP_MASTERS:Lorg/apache/hadoop/hbase/protobuf/generated/ClusterStatusProtos$Option;
      75: areturn
      76: getstatic     #13                 // Field MASTER_COPROCESSORS:Lorg/apache/hadoop/hbase/protobuf/generated/ClusterStatusProtos$Option;
      79: areturn
      80: getstatic     #14                 // Field REGIONS_IN_TRANSITION:Lorg/apache/hadoop/hbase/protobuf/generated/ClusterStatusProtos$Option;
      83: areturn
      84: getstatic     #15                 // Field BALANCER_ON:Lorg/apache/hadoop/hbase/protobuf/generated/ClusterStatusProtos$Option;
      87: areturn
      88: aconst_null
      89: areturn

  public static com.google.protobuf.Internal$EnumLiteMap<org.apache.hadoop.hbase.protobuf.generated.ClusterStatusProtos$Option> internalGetValueMap();
    Code:
       0: getstatic     #16                 // Field internalValueMap:Lcom/google/protobuf/Internal$EnumLiteMap;
       3: areturn

  public final com.google.protobuf.Descriptors$EnumValueDescriptor getValueDescriptor();
    Code:
       0: invokestatic  #17                 // Method getDescriptor:()Lcom/google/protobuf/Descriptors$EnumDescriptor;
       3: invokevirtual #18                 // Method com/google/protobuf/Descriptors$EnumDescriptor.getValues:()Ljava/util/List;
       6: aload_0
       7: getfield      #19                 // Field index:I
      10: invokeinterface #20,  2           // InterfaceMethod java/util/List.get:(I)Ljava/lang/Object;
      15: checkcast     #21                 // class com/google/protobuf/Descriptors$EnumValueDescriptor
      18: areturn

  public final com.google.protobuf.Descriptors$EnumDescriptor getDescriptorForType();
    Code:
       0: invokestatic  #17                 // Method getDescriptor:()Lcom/google/protobuf/Descriptors$EnumDescriptor;
       3: areturn

  public static final com.google.protobuf.Descriptors$EnumDescriptor getDescriptor();
    Code:
       0: invokestatic  #22                 // Method org/apache/hadoop/hbase/protobuf/generated/ClusterStatusProtos.getDescriptor:()Lcom/google/protobuf/Descriptors$FileDescriptor;
       3: invokevirtual #23                 // Method com/google/protobuf/Descriptors$FileDescriptor.getEnumTypes:()Ljava/util/List;
       6: iconst_0
       7: invokeinterface #20,  2           // InterfaceMethod java/util/List.get:(I)Ljava/lang/Object;
      12: checkcast     #24                 // class com/google/protobuf/Descriptors$EnumDescriptor
      15: areturn

  public static org.apache.hadoop.hbase.protobuf.generated.ClusterStatusProtos$Option valueOf(com.google.protobuf.Descriptors$EnumValueDescriptor);
    Code:
       0: aload_0
       1: invokevirtual #25                 // Method com/google/protobuf/Descriptors$EnumValueDescriptor.getType:()Lcom/google/protobuf/Descriptors$EnumDescriptor;
       4: invokestatic  #17                 // Method getDescriptor:()Lcom/google/protobuf/Descriptors$EnumDescriptor;
       7: if_acmpeq     20
      10: new           #26                 // class java/lang/IllegalArgumentException
      13: dup
      14: ldc           #27                 // String EnumValueDescriptor is not for this type.
      16: invokespecial #28                 // Method java/lang/IllegalArgumentException."<init>":(Ljava/lang/String;)V
      19: athrow
      20: getstatic     #29                 // Field VALUES:[Lorg/apache/hadoop/hbase/protobuf/generated/ClusterStatusProtos$Option;
      23: aload_0
      24: invokevirtual #30                 // Method com/google/protobuf/Descriptors$EnumValueDescriptor.getIndex:()I
      27: aaload
      28: areturn

  static {};
    Code:
       0: new           #4                  // class org/apache/hadoop/hbase/protobuf/generated/ClusterStatusProtos$Option
       3: dup
       4: ldc           #32                 // String HBASE_VERSION
       6: iconst_0
       7: iconst_0
       8: iconst_0
       9: invokespecial #33                 // Method "<init>":(Ljava/lang/String;III)V
      12: putstatic     #7                  // Field HBASE_VERSION:Lorg/apache/hadoop/hbase/protobuf/generated/ClusterStatusProtos$Option;
      15: new           #4                  // class org/apache/hadoop/hbase/protobuf/generated/ClusterStatusProtos$Option
      18: dup
      19: ldc           #34                 // String CLUSTER_ID
      21: iconst_1
      22: iconst_1
      23: iconst_1
      24: invokespecial #33                 // Method "<init>":(Ljava/lang/String;III)V
      27: putstatic     #8                  // Field CLUSTER_ID:Lorg/apache/hadoop/hbase/protobuf/generated/ClusterStatusProtos$Option;
      30: new           #4                  // class org/apache/hadoop/hbase/protobuf/generated/ClusterStatusProtos$Option
      33: dup
      34: ldc           #35                 // String LIVE_SERVERS
      36: iconst_2
      37: iconst_2
      38: iconst_2
      39: invokespecial #33                 // Method "<init>":(Ljava/lang/String;III)V
      42: putstatic     #9                  // Field LIVE_SERVERS:Lorg/apache/hadoop/hbase/protobuf/generated/ClusterStatusProtos$Option;
      45: new           #4                  // class org/apache/hadoop/hbase/protobuf/generated/ClusterStatusProtos$Option
      48: dup
      49: ldc           #36                 // String DEAD_SERVERS
      51: iconst_3
      52: iconst_3
      53: iconst_3
      54: invokespecial #33                 // Method "<init>":(Ljava/lang/String;III)V
      57: putstatic     #10                 // Field DEAD_SERVERS:Lorg/apache/hadoop/hbase/protobuf/generated/ClusterStatusProtos$Option;
      60: new           #4                  // class org/apache/hadoop/hbase/protobuf/generated/ClusterStatusProtos$Option
      63: dup
      64: ldc           #37                 // String MASTER
      66: iconst_4
      67: iconst_4
      68: iconst_4
      69: invokespecial #33                 // Method "<init>":(Ljava/lang/String;III)V
      72: putstatic     #11                 // Field MASTER:Lorg/apache/hadoop/hbase/protobuf/generated/ClusterStatusProtos$Option;
      75: new           #4                  // class org/apache/hadoop/hbase/protobuf/generated/ClusterStatusProtos$Option
      78: dup
      79: ldc           #38                 // String BACKUP_MASTERS
      81: iconst_5
      82: iconst_5
      83: iconst_5
      84: invokespecial #33                 // Method "<init>":(Ljava/lang/String;III)V
      87: putstatic     #12                 // Field BACKUP_MASTERS:Lorg/apache/hadoop/hbase/protobuf/generated/ClusterStatusProtos$Option;
      90: new           #4                  // class org/apache/hadoop/hbase/protobuf/generated/ClusterStatusProtos$Option
      93: dup
      94: ldc           #39                 // String MASTER_COPROCESSORS
      96: bipush        6
      98: bipush        6
     100: bipush        6
     102: invokespecial #33                 // Method "<init>":(Ljava/lang/String;III)V
     105: putstatic     #13                 // Field MASTER_COPROCESSORS:Lorg/apache/hadoop/hbase/protobuf/generated/ClusterStatusProtos$Option;
     108: new           #4                  // class org/apache/hadoop/hbase/protobuf/generated/ClusterStatusProtos$Option
     111: dup
     112: ldc           #40                 // String REGIONS_IN_TRANSITION
     114: bipush        7
     116: bipush        7
     118: bipush        7
     120: invokespecial #33                 // Method "<init>":(Ljava/lang/String;III)V
     123: putstatic     #14                 // Field REGIONS_IN_TRANSITION:Lorg/apache/hadoop/hbase/protobuf/generated/ClusterStatusProtos$Option;
     126: new           #4                  // class org/apache/hadoop/hbase/protobuf/generated/ClusterStatusProtos$Option
     129: dup
     130: ldc           #41                 // String BALANCER_ON
     132: bipush        8
     134: bipush        8
     136: bipush        8
     138: invokespecial #33                 // Method "<init>":(Ljava/lang/String;III)V
     141: putstatic     #15                 // Field BALANCER_ON:Lorg/apache/hadoop/hbase/protobuf/generated/ClusterStatusProtos$Option;
     144: bipush        9
     146: anewarray     #4                  // class org/apache/hadoop/hbase/protobuf/generated/ClusterStatusProtos$Option
     149: dup
     150: iconst_0
     151: getstatic     #7                  // Field HBASE_VERSION:Lorg/apache/hadoop/hbase/protobuf/generated/ClusterStatusProtos$Option;
     154: aastore
     155: dup
     156: iconst_1
     157: getstatic     #8                  // Field CLUSTER_ID:Lorg/apache/hadoop/hbase/protobuf/generated/ClusterStatusProtos$Option;
     160: aastore
     161: dup
     162: iconst_2
     163: getstatic     #9                  // Field LIVE_SERVERS:Lorg/apache/hadoop/hbase/protobuf/generated/ClusterStatusProtos$Option;
     166: aastore
     167: dup
     168: iconst_3
     169: getstatic     #10                 // Field DEAD_SERVERS:Lorg/apache/hadoop/hbase/protobuf/generated/ClusterStatusProtos$Option;
     172: aastore
     173: dup
     174: iconst_4
     175: getstatic     #11                 // Field MASTER:Lorg/apache/hadoop/hbase/protobuf/generated/ClusterStatusProtos$Option;
     178: aastore
     179: dup
     180: iconst_5
     181: getstatic     #12                 // Field BACKUP_MASTERS:Lorg/apache/hadoop/hbase/protobuf/generated/ClusterStatusProtos$Option;
     184: aastore
     185: dup
     186: bipush        6
     188: getstatic     #13                 // Field MASTER_COPROCESSORS:Lorg/apache/hadoop/hbase/protobuf/generated/ClusterStatusProtos$Option;
     191: aastore
     192: dup
     193: bipush        7
     195: getstatic     #14                 // Field REGIONS_IN_TRANSITION:Lorg/apache/hadoop/hbase/protobuf/generated/ClusterStatusProtos$Option;
     198: aastore
     199: dup
     200: bipush        8
     202: getstatic     #15                 // Field BALANCER_ON:Lorg/apache/hadoop/hbase/protobuf/generated/ClusterStatusProtos$Option;
     205: aastore
     206: putstatic     #1                  // Field $VALUES:[Lorg/apache/hadoop/hbase/protobuf/generated/ClusterStatusProtos$Option;
     209: new           #42                 // class org/apache/hadoop/hbase/protobuf/generated/ClusterStatusProtos$Option$1
     212: dup
     213: invokespecial #43                 // Method org/apache/hadoop/hbase/protobuf/generated/ClusterStatusProtos$Option$1."<init>":()V
     216: putstatic     #16                 // Field internalValueMap:Lcom/google/protobuf/Internal$EnumLiteMap;
     219: invokestatic  #44                 // Method values:()[Lorg/apache/hadoop/hbase/protobuf/generated/ClusterStatusProtos$Option;
     222: putstatic     #29                 // Field VALUES:[Lorg/apache/hadoop/hbase/protobuf/generated/ClusterStatusProtos$Option;
     225: return
}
