Compiled from "ClusterId.java"
public class org.apache.hadoop.hbase.ClusterId {
  public org.apache.hadoop.hbase.ClusterId();
    Code:
       0: aload_0
       1: invokestatic  #1                  // Method java/util/UUID.randomUUID:()Ljava/util/UUID;
       4: invokevirtual #2                  // Method java/util/UUID.toString:()Ljava/lang/String;
       7: invokespecial #3                  // Method "<init>":(Ljava/lang/String;)V
      10: return

  public org.apache.hadoop.hbase.ClusterId(java.lang.String);
    Code:
       0: aload_0
       1: invokespecial #4                  // Method java/lang/Object."<init>":()V
       4: aload_0
       5: aload_1
       6: putfield      #5                  // Field id:Ljava/lang/String;
       9: return

  public byte[] toByteArray();
    Code:
       0: aload_0
       1: invokevirtual #6                  // Method convert:()Lorg/apache/hadoop/hbase/shaded/protobuf/generated/ClusterIdProtos$ClusterId;
       4: invokevirtual #7                  // Method org/apache/hadoop/hbase/shaded/protobuf/generated/ClusterIdProtos$ClusterId.toByteArray:()[B
       7: invokestatic  #8                  // Method org/apache/hadoop/hbase/shaded/protobuf/ProtobufUtil.prependPBMagic:([B)[B
      10: areturn

  public static org.apache.hadoop.hbase.ClusterId parseFrom(byte[]) throws org.apache.hadoop.hbase.exceptions.DeserializationException;
    Code:
       0: aload_0
       1: invokestatic  #9                  // Method org/apache/hadoop/hbase/shaded/protobuf/ProtobufUtil.isPBMagicPrefix:([B)Z
       4: ifeq          52
       7: invokestatic  #10                 // Method org/apache/hadoop/hbase/shaded/protobuf/ProtobufUtil.lengthOfPBMagic:()I
      10: istore_1
      11: invokestatic  #11                 // Method org/apache/hadoop/hbase/shaded/protobuf/generated/ClusterIdProtos$ClusterId.newBuilder:()Lorg/apache/hadoop/hbase/shaded/protobuf/generated/ClusterIdProtos$ClusterId$Builder;
      14: astore_2
      15: aconst_null
      16: astore_3
      17: aload_2
      18: aload_0
      19: iload_1
      20: aload_0
      21: arraylength
      22: iload_1
      23: isub
      24: invokestatic  #12                 // Method org/apache/hadoop/hbase/shaded/protobuf/ProtobufUtil.mergeFrom:(Lorg/apache/hbase/thirdparty/com/google/protobuf/Message$Builder;[BII)V
      27: aload_2
      28: invokevirtual #13                 // Method org/apache/hadoop/hbase/shaded/protobuf/generated/ClusterIdProtos$ClusterId$Builder.build:()Lorg/apache/hadoop/hbase/shaded/protobuf/generated/ClusterIdProtos$ClusterId;
      31: astore_3
      32: goto          47
      35: astore        4
      37: new           #15                 // class org/apache/hadoop/hbase/exceptions/DeserializationException
      40: dup
      41: aload         4
      43: invokespecial #16                 // Method org/apache/hadoop/hbase/exceptions/DeserializationException."<init>":(Ljava/lang/Throwable;)V
      46: athrow
      47: aload_3
      48: invokestatic  #17                 // Method convert:(Lorg/apache/hadoop/hbase/shaded/protobuf/generated/ClusterIdProtos$ClusterId;)Lorg/apache/hadoop/hbase/ClusterId;
      51: areturn
      52: new           #18                 // class org/apache/hadoop/hbase/ClusterId
      55: dup
      56: aload_0
      57: invokestatic  #19                 // Method org/apache/hadoop/hbase/util/Bytes.toString:([B)Ljava/lang/String;
      60: invokespecial #3                  // Method "<init>":(Ljava/lang/String;)V
      63: areturn
    Exception table:
       from    to  target type
          17    32    35   Class java/io/IOException

  public org.apache.hadoop.hbase.shaded.protobuf.generated.ClusterIdProtos$ClusterId convert();
    Code:
       0: invokestatic  #11                 // Method org/apache/hadoop/hbase/shaded/protobuf/generated/ClusterIdProtos$ClusterId.newBuilder:()Lorg/apache/hadoop/hbase/shaded/protobuf/generated/ClusterIdProtos$ClusterId$Builder;
       3: astore_1
       4: aload_1
       5: aload_0
       6: getfield      #5                  // Field id:Ljava/lang/String;
       9: invokevirtual #20                 // Method org/apache/hadoop/hbase/shaded/protobuf/generated/ClusterIdProtos$ClusterId$Builder.setClusterId:(Ljava/lang/String;)Lorg/apache/hadoop/hbase/shaded/protobuf/generated/ClusterIdProtos$ClusterId$Builder;
      12: invokevirtual #13                 // Method org/apache/hadoop/hbase/shaded/protobuf/generated/ClusterIdProtos$ClusterId$Builder.build:()Lorg/apache/hadoop/hbase/shaded/protobuf/generated/ClusterIdProtos$ClusterId;
      15: areturn

  public static org.apache.hadoop.hbase.ClusterId convert(org.apache.hadoop.hbase.shaded.protobuf.generated.ClusterIdProtos$ClusterId);
    Code:
       0: new           #18                 // class org/apache/hadoop/hbase/ClusterId
       3: dup
       4: aload_0
       5: invokevirtual #21                 // Method org/apache/hadoop/hbase/shaded/protobuf/generated/ClusterIdProtos$ClusterId.getClusterId:()Ljava/lang/String;
       8: invokespecial #3                  // Method "<init>":(Ljava/lang/String;)V
      11: areturn

  public java.lang.String toString();
    Code:
       0: aload_0
       1: getfield      #5                  // Field id:Ljava/lang/String;
       4: areturn
}
