Compiled from "ClusterStatusProtos.java"
public final class org.apache.hadoop.hbase.protobuf.generated.ClusterStatusProtos$ServerLoad$Builder extends com.google.protobuf.GeneratedMessage$Builder<org.apache.hadoop.hbase.protobuf.generated.ClusterStatusProtos$ServerLoad$Builder> implements org.apache.hadoop.hbase.protobuf.generated.ClusterStatusProtos$ServerLoadOrBuilder {
  public static final com.google.protobuf.Descriptors$Descriptor getDescriptor();
    Code:
       0: invokestatic  #3                  // Method org/apache/hadoop/hbase/protobuf/generated/ClusterStatusProtos.access$9500:()Lcom/google/protobuf/Descriptors$Descriptor;
       3: areturn

  protected com.google.protobuf.GeneratedMessage$FieldAccessorTable internalGetFieldAccessorTable();
    Code:
       0: invokestatic  #4                  // Method org/apache/hadoop/hbase/protobuf/generated/ClusterStatusProtos.access$9600:()Lcom/google/protobuf/GeneratedMessage$FieldAccessorTable;
       3: ldc           #5                  // class org/apache/hadoop/hbase/protobuf/generated/ClusterStatusProtos$ServerLoad
       5: ldc           #6                  // class org/apache/hadoop/hbase/protobuf/generated/ClusterStatusProtos$ServerLoad$Builder
       7: invokevirtual #7                  // Method com/google/protobuf/GeneratedMessage$FieldAccessorTable.ensureFieldAccessorsInitialized:(Ljava/lang/Class;Ljava/lang/Class;)Lcom/google/protobuf/GeneratedMessage$FieldAccessorTable;
      10: areturn

  public org.apache.hadoop.hbase.protobuf.generated.ClusterStatusProtos$ServerLoad$Builder clear();
    Code:
       0: aload_0
       1: invokespecial #23                 // Method com/google/protobuf/GeneratedMessage$Builder.clear:()Lcom/google/protobuf/GeneratedMessage$Builder;
       4: pop
       5: aload_0
       6: lconst_0
       7: putfield      #24                 // Field numberOfRequests_:J
      10: aload_0
      11: aload_0
      12: getfield      #25                 // Field bitField0_:I
      15: bipush        -2
      17: iand
      18: putfield      #25                 // Field bitField0_:I
      21: aload_0
      22: lconst_0
      23: putfield      #26                 // Field totalNumberOfRequests_:J
      26: aload_0
      27: aload_0
      28: getfield      #25                 // Field bitField0_:I
      31: bipush        -3
      33: iand
      34: putfield      #25                 // Field bitField0_:I
      37: aload_0
      38: iconst_0
      39: putfield      #27                 // Field usedHeapMB_:I
      42: aload_0
      43: aload_0
      44: getfield      #25                 // Field bitField0_:I
      47: bipush        -5
      49: iand
      50: putfield      #25                 // Field bitField0_:I
      53: aload_0
      54: iconst_0
      55: putfield      #28                 // Field maxHeapMB_:I
      58: aload_0
      59: aload_0
      60: getfield      #25                 // Field bitField0_:I
      63: bipush        -9
      65: iand
      66: putfield      #25                 // Field bitField0_:I
      69: aload_0
      70: getfield      #29                 // Field regionLoadsBuilder_:Lcom/google/protobuf/RepeatedFieldBuilder;
      73: ifnonnull     97
      76: aload_0
      77: invokestatic  #9                  // Method java/util/Collections.emptyList:()Ljava/util/List;
      80: putfield      #10                 // Field regionLoads_:Ljava/util/List;
      83: aload_0
      84: aload_0
      85: getfield      #25                 // Field bitField0_:I
      88: bipush        -17
      90: iand
      91: putfield      #25                 // Field bitField0_:I
      94: goto          104
      97: aload_0
      98: getfield      #29                 // Field regionLoadsBuilder_:Lcom/google/protobuf/RepeatedFieldBuilder;
     101: invokevirtual #30                 // Method com/google/protobuf/RepeatedFieldBuilder.clear:()V
     104: aload_0
     105: getfield      #31                 // Field coprocessorsBuilder_:Lcom/google/protobuf/RepeatedFieldBuilder;
     108: ifnonnull     132
     111: aload_0
     112: invokestatic  #9                  // Method java/util/Collections.emptyList:()Ljava/util/List;
     115: putfield      #11                 // Field coprocessors_:Ljava/util/List;
     118: aload_0
     119: aload_0
     120: getfield      #25                 // Field bitField0_:I
     123: bipush        -33
     125: iand
     126: putfield      #25                 // Field bitField0_:I
     129: goto          139
     132: aload_0
     133: getfield      #31                 // Field coprocessorsBuilder_:Lcom/google/protobuf/RepeatedFieldBuilder;
     136: invokevirtual #30                 // Method com/google/protobuf/RepeatedFieldBuilder.clear:()V
     139: aload_0
     140: lconst_0
     141: putfield      #32                 // Field reportStartTime_:J
     144: aload_0
     145: aload_0
     146: getfield      #25                 // Field bitField0_:I
     149: bipush        -65
     151: iand
     152: putfield      #25                 // Field bitField0_:I
     155: aload_0
     156: lconst_0
     157: putfield      #33                 // Field reportEndTime_:J
     160: aload_0
     161: aload_0
     162: getfield      #25                 // Field bitField0_:I
     165: sipush        -129
     168: iand
     169: putfield      #25                 // Field bitField0_:I
     172: aload_0
     173: iconst_0
     174: putfield      #34                 // Field infoServerPort_:I
     177: aload_0
     178: aload_0
     179: getfield      #25                 // Field bitField0_:I
     182: sipush        -257
     185: iand
     186: putfield      #25                 // Field bitField0_:I
     189: aload_0
     190: getfield      #35                 // Field replLoadSourceBuilder_:Lcom/google/protobuf/RepeatedFieldBuilder;
     193: ifnonnull     218
     196: aload_0
     197: invokestatic  #9                  // Method java/util/Collections.emptyList:()Ljava/util/List;
     200: putfield      #12                 // Field replLoadSource_:Ljava/util/List;
     203: aload_0
     204: aload_0
     205: getfield      #25                 // Field bitField0_:I
     208: sipush        -513
     211: iand
     212: putfield      #25                 // Field bitField0_:I
     215: goto          225
     218: aload_0
     219: getfield      #35                 // Field replLoadSourceBuilder_:Lcom/google/protobuf/RepeatedFieldBuilder;
     222: invokevirtual #30                 // Method com/google/protobuf/RepeatedFieldBuilder.clear:()V
     225: aload_0
     226: getfield      #36                 // Field replLoadSinkBuilder_:Lcom/google/protobuf/SingleFieldBuilder;
     229: ifnonnull     242
     232: aload_0
     233: invokestatic  #13                 // Method org/apache/hadoop/hbase/protobuf/generated/ClusterStatusProtos$ReplicationLoadSink.getDefaultInstance:()Lorg/apache/hadoop/hbase/protobuf/generated/ClusterStatusProtos$ReplicationLoadSink;
     236: putfield      #14                 // Field replLoadSink_:Lorg/apache/hadoop/hbase/protobuf/generated/ClusterStatusProtos$ReplicationLoadSink;
     239: goto          250
     242: aload_0
     243: getfield      #36                 // Field replLoadSinkBuilder_:Lcom/google/protobuf/SingleFieldBuilder;
     246: invokevirtual #37                 // Method com/google/protobuf/SingleFieldBuilder.clear:()Lcom/google/protobuf/SingleFieldBuilder;
     249: pop
     250: aload_0
     251: aload_0
     252: getfield      #25                 // Field bitField0_:I
     255: sipush        -1025
     258: iand
     259: putfield      #25                 // Field bitField0_:I
     262: aload_0
     263: areturn

  public org.apache.hadoop.hbase.protobuf.generated.ClusterStatusProtos$ServerLoad$Builder clone();
    Code:
       0: invokestatic  #2                  // Method create:()Lorg/apache/hadoop/hbase/protobuf/generated/ClusterStatusProtos$ServerLoad$Builder;
       3: aload_0
       4: invokevirtual #38                 // Method buildPartial:()Lorg/apache/hadoop/hbase/protobuf/generated/ClusterStatusProtos$ServerLoad;
       7: invokevirtual #39                 // Method mergeFrom:(Lorg/apache/hadoop/hbase/protobuf/generated/ClusterStatusProtos$ServerLoad;)Lorg/apache/hadoop/hbase/protobuf/generated/ClusterStatusProtos$ServerLoad$Builder;
      10: areturn

  public com.google.protobuf.Descriptors$Descriptor getDescriptorForType();
    Code:
       0: invokestatic  #3                  // Method org/apache/hadoop/hbase/protobuf/generated/ClusterStatusProtos.access$9500:()Lcom/google/protobuf/Descriptors$Descriptor;
       3: areturn

  public org.apache.hadoop.hbase.protobuf.generated.ClusterStatusProtos$ServerLoad getDefaultInstanceForType();
    Code:
       0: invokestatic  #40                 // Method org/apache/hadoop/hbase/protobuf/generated/ClusterStatusProtos$ServerLoad.getDefaultInstance:()Lorg/apache/hadoop/hbase/protobuf/generated/ClusterStatusProtos$ServerLoad;
       3: areturn

  public org.apache.hadoop.hbase.protobuf.generated.ClusterStatusProtos$ServerLoad build();
    Code:
       0: aload_0
       1: invokevirtual #38                 // Method buildPartial:()Lorg/apache/hadoop/hbase/protobuf/generated/ClusterStatusProtos$ServerLoad;
       4: astore_1
       5: aload_1
       6: invokevirtual #41                 // Method org/apache/hadoop/hbase/protobuf/generated/ClusterStatusProtos$ServerLoad.isInitialized:()Z
       9: ifne          17
      12: aload_1
      13: invokestatic  #42                 // Method newUninitializedMessageException:(Lcom/google/protobuf/Message;)Lcom/google/protobuf/UninitializedMessageException;
      16: athrow
      17: aload_1
      18: areturn

  public org.apache.hadoop.hbase.protobuf.generated.ClusterStatusProtos$ServerLoad buildPartial();
    Code:
       0: new           #5                  // class org/apache/hadoop/hbase/protobuf/generated/ClusterStatusProtos$ServerLoad
       3: dup
       4: aload_0
       5: aconst_null
       6: invokespecial #43                 // Method org/apache/hadoop/hbase/protobuf/generated/ClusterStatusProtos$ServerLoad."<init>":(Lcom/google/protobuf/GeneratedMessage$Builder;Lorg/apache/hadoop/hbase/protobuf/generated/ClusterStatusProtos$1;)V
       9: astore_1
      10: aload_0
      11: getfield      #25                 // Field bitField0_:I
      14: istore_2
      15: iconst_0
      16: istore_3
      17: iload_2
      18: iconst_1
      19: iand
      20: iconst_1
      21: if_icmpne     28
      24: iload_3
      25: iconst_1
      26: ior
      27: istore_3
      28: aload_1
      29: aload_0
      30: getfield      #24                 // Field numberOfRequests_:J
      33: invokestatic  #44                 // Method org/apache/hadoop/hbase/protobuf/generated/ClusterStatusProtos$ServerLoad.access$10202:(Lorg/apache/hadoop/hbase/protobuf/generated/ClusterStatusProtos$ServerLoad;J)J
      36: pop2
      37: iload_2
      38: iconst_2
      39: iand
      40: iconst_2
      41: if_icmpne     48
      44: iload_3
      45: iconst_2
      46: ior
      47: istore_3
      48: aload_1
      49: aload_0
      50: getfield      #26                 // Field totalNumberOfRequests_:J
      53: invokestatic  #45                 // Method org/apache/hadoop/hbase/protobuf/generated/ClusterStatusProtos$ServerLoad.access$10302:(Lorg/apache/hadoop/hbase/protobuf/generated/ClusterStatusProtos$ServerLoad;J)J
      56: pop2
      57: iload_2
      58: iconst_4
      59: iand
      60: iconst_4
      61: if_icmpne     68
      64: iload_3
      65: iconst_4
      66: ior
      67: istore_3
      68: aload_1
      69: aload_0
      70: getfield      #27                 // Field usedHeapMB_:I
      73: invokestatic  #46                 // Method org/apache/hadoop/hbase/protobuf/generated/ClusterStatusProtos$ServerLoad.access$10402:(Lorg/apache/hadoop/hbase/protobuf/generated/ClusterStatusProtos$ServerLoad;I)I
      76: pop
      77: iload_2
      78: bipush        8
      80: iand
      81: bipush        8
      83: if_icmpne     91
      86: iload_3
      87: bipush        8
      89: ior
      90: istore_3
      91: aload_1
      92: aload_0
      93: getfield      #28                 // Field maxHeapMB_:I
      96: invokestatic  #47                 // Method org/apache/hadoop/hbase/protobuf/generated/ClusterStatusProtos$ServerLoad.access$10502:(Lorg/apache/hadoop/hbase/protobuf/generated/ClusterStatusProtos$ServerLoad;I)I
      99: pop
     100: aload_0
     101: getfield      #29                 // Field regionLoadsBuilder_:Lcom/google/protobuf/RepeatedFieldBuilder;
     104: ifnonnull     153
     107: aload_0
     108: getfield      #25                 // Field bitField0_:I
     111: bipush        16
     113: iand
     114: bipush        16
     116: if_icmpne     141
     119: aload_0
     120: aload_0
     121: getfield      #10                 // Field regionLoads_:Ljava/util/List;
     124: invokestatic  #48                 // Method java/util/Collections.unmodifiableList:(Ljava/util/List;)Ljava/util/List;
     127: putfield      #10                 // Field regionLoads_:Ljava/util/List;
     130: aload_0
     131: aload_0
     132: getfield      #25                 // Field bitField0_:I
     135: bipush        -17
     137: iand
     138: putfield      #25                 // Field bitField0_:I
     141: aload_1
     142: aload_0
     143: getfield      #10                 // Field regionLoads_:Ljava/util/List;
     146: invokestatic  #49                 // Method org/apache/hadoop/hbase/protobuf/generated/ClusterStatusProtos$ServerLoad.access$10602:(Lorg/apache/hadoop/hbase/protobuf/generated/ClusterStatusProtos$ServerLoad;Ljava/util/List;)Ljava/util/List;
     149: pop
     150: goto          165
     153: aload_1
     154: aload_0
     155: getfield      #29                 // Field regionLoadsBuilder_:Lcom/google/protobuf/RepeatedFieldBuilder;
     158: invokevirtual #50                 // Method com/google/protobuf/RepeatedFieldBuilder.build:()Ljava/util/List;
     161: invokestatic  #49                 // Method org/apache/hadoop/hbase/protobuf/generated/ClusterStatusProtos$ServerLoad.access$10602:(Lorg/apache/hadoop/hbase/protobuf/generated/ClusterStatusProtos$ServerLoad;Ljava/util/List;)Ljava/util/List;
     164: pop
     165: aload_0
     166: getfield      #31                 // Field coprocessorsBuilder_:Lcom/google/protobuf/RepeatedFieldBuilder;
     169: ifnonnull     218
     172: aload_0
     173: getfield      #25                 // Field bitField0_:I
     176: bipush        32
     178: iand
     179: bipush        32
     181: if_icmpne     206
     184: aload_0
     185: aload_0
     186: getfield      #11                 // Field coprocessors_:Ljava/util/List;
     189: invokestatic  #48                 // Method java/util/Collections.unmodifiableList:(Ljava/util/List;)Ljava/util/List;
     192: putfield      #11                 // Field coprocessors_:Ljava/util/List;
     195: aload_0
     196: aload_0
     197: getfield      #25                 // Field bitField0_:I
     200: bipush        -33
     202: iand
     203: putfield      #25                 // Field bitField0_:I
     206: aload_1
     207: aload_0
     208: getfield      #11                 // Field coprocessors_:Ljava/util/List;
     211: invokestatic  #51                 // Method org/apache/hadoop/hbase/protobuf/generated/ClusterStatusProtos$ServerLoad.access$10702:(Lorg/apache/hadoop/hbase/protobuf/generated/ClusterStatusProtos$ServerLoad;Ljava/util/List;)Ljava/util/List;
     214: pop
     215: goto          230
     218: aload_1
     219: aload_0
     220: getfield      #31                 // Field coprocessorsBuilder_:Lcom/google/protobuf/RepeatedFieldBuilder;
     223: invokevirtual #50                 // Method com/google/protobuf/RepeatedFieldBuilder.build:()Ljava/util/List;
     226: invokestatic  #51                 // Method org/apache/hadoop/hbase/protobuf/generated/ClusterStatusProtos$ServerLoad.access$10702:(Lorg/apache/hadoop/hbase/protobuf/generated/ClusterStatusProtos$ServerLoad;Ljava/util/List;)Ljava/util/List;
     229: pop
     230: iload_2
     231: bipush        64
     233: iand
     234: bipush        64
     236: if_icmpne     244
     239: iload_3
     240: bipush        16
     242: ior
     243: istore_3
     244: aload_1
     245: aload_0
     246: getfield      #32                 // Field reportStartTime_:J
     249: invokestatic  #52                 // Method org/apache/hadoop/hbase/protobuf/generated/ClusterStatusProtos$ServerLoad.access$10802:(Lorg/apache/hadoop/hbase/protobuf/generated/ClusterStatusProtos$ServerLoad;J)J
     252: pop2
     253: iload_2
     254: sipush        128
     257: iand
     258: sipush        128
     261: if_icmpne     269
     264: iload_3
     265: bipush        32
     267: ior
     268: istore_3
     269: aload_1
     270: aload_0
     271: getfield      #33                 // Field reportEndTime_:J
     274: invokestatic  #53                 // Method org/apache/hadoop/hbase/protobuf/generated/ClusterStatusProtos$ServerLoad.access$10902:(Lorg/apache/hadoop/hbase/protobuf/generated/ClusterStatusProtos$ServerLoad;J)J
     277: pop2
     278: iload_2
     279: sipush        256
     282: iand
     283: sipush        256
     286: if_icmpne     294
     289: iload_3
     290: bipush        64
     292: ior
     293: istore_3
     294: aload_1
     295: aload_0
     296: getfield      #34                 // Field infoServerPort_:I
     299: invokestatic  #54                 // Method org/apache/hadoop/hbase/protobuf/generated/ClusterStatusProtos$ServerLoad.access$11002:(Lorg/apache/hadoop/hbase/protobuf/generated/ClusterStatusProtos$ServerLoad;I)I
     302: pop
     303: aload_0
     304: getfield      #35                 // Field replLoadSourceBuilder_:Lcom/google/protobuf/RepeatedFieldBuilder;
     307: ifnonnull     359
     310: aload_0
     311: getfield      #25                 // Field bitField0_:I
     314: sipush        512
     317: iand
     318: sipush        512
     321: if_icmpne     347
     324: aload_0
     325: aload_0
     326: getfield      #12                 // Field replLoadSource_:Ljava/util/List;
     329: invokestatic  #48                 // Method java/util/Collections.unmodifiableList:(Ljava/util/List;)Ljava/util/List;
     332: putfield      #12                 // Field replLoadSource_:Ljava/util/List;
     335: aload_0
     336: aload_0
     337: getfield      #25                 // Field bitField0_:I
     340: sipush        -513
     343: iand
     344: putfield      #25                 // Field bitField0_:I
     347: aload_1
     348: aload_0
     349: getfield      #12                 // Field replLoadSource_:Ljava/util/List;
     352: invokestatic  #55                 // Method org/apache/hadoop/hbase/protobuf/generated/ClusterStatusProtos$ServerLoad.access$11102:(Lorg/apache/hadoop/hbase/protobuf/generated/ClusterStatusProtos$ServerLoad;Ljava/util/List;)Ljava/util/List;
     355: pop
     356: goto          371
     359: aload_1
     360: aload_0
     361: getfield      #35                 // Field replLoadSourceBuilder_:Lcom/google/protobuf/RepeatedFieldBuilder;
     364: invokevirtual #50                 // Method com/google/protobuf/RepeatedFieldBuilder.build:()Ljava/util/List;
     367: invokestatic  #55                 // Method org/apache/hadoop/hbase/protobuf/generated/ClusterStatusProtos$ServerLoad.access$11102:(Lorg/apache/hadoop/hbase/protobuf/generated/ClusterStatusProtos$ServerLoad;Ljava/util/List;)Ljava/util/List;
     370: pop
     371: iload_2
     372: sipush        1024
     375: iand
     376: sipush        1024
     379: if_icmpne     388
     382: iload_3
     383: sipush        128
     386: ior
     387: istore_3
     388: aload_0
     389: getfield      #36                 // Field replLoadSinkBuilder_:Lcom/google/protobuf/SingleFieldBuilder;
     392: ifnonnull     407
     395: aload_1
     396: aload_0
     397: getfield      #14                 // Field replLoadSink_:Lorg/apache/hadoop/hbase/protobuf/generated/ClusterStatusProtos$ReplicationLoadSink;
     400: invokestatic  #56                 // Method org/apache/hadoop/hbase/protobuf/generated/ClusterStatusProtos$ServerLoad.access$11202:(Lorg/apache/hadoop/hbase/protobuf/generated/ClusterStatusProtos$ServerLoad;Lorg/apache/hadoop/hbase/protobuf/generated/ClusterStatusProtos$ReplicationLoadSink;)Lorg/apache/hadoop/hbase/protobuf/generated/ClusterStatusProtos$ReplicationLoadSink;
     403: pop
     404: goto          422
     407: aload_1
     408: aload_0
     409: getfield      #36                 // Field replLoadSinkBuilder_:Lcom/google/protobuf/SingleFieldBuilder;
     412: invokevirtual #57                 // Method com/google/protobuf/SingleFieldBuilder.build:()Lcom/google/protobuf/GeneratedMessage;
     415: checkcast     #58                 // class org/apache/hadoop/hbase/protobuf/generated/ClusterStatusProtos$ReplicationLoadSink
     418: invokestatic  #56                 // Method org/apache/hadoop/hbase/protobuf/generated/ClusterStatusProtos$ServerLoad.access$11202:(Lorg/apache/hadoop/hbase/protobuf/generated/ClusterStatusProtos$ServerLoad;Lorg/apache/hadoop/hbase/protobuf/generated/ClusterStatusProtos$ReplicationLoadSink;)Lorg/apache/hadoop/hbase/protobuf/generated/ClusterStatusProtos$ReplicationLoadSink;
     421: pop
     422: aload_1
     423: iload_3
     424: invokestatic  #59                 // Method org/apache/hadoop/hbase/protobuf/generated/ClusterStatusProtos$ServerLoad.access$11302:(Lorg/apache/hadoop/hbase/protobuf/generated/ClusterStatusProtos$ServerLoad;I)I
     427: pop
     428: aload_0
     429: invokevirtual #60                 // Method onBuilt:()V
     432: aload_1
     433: areturn

  public org.apache.hadoop.hbase.protobuf.generated.ClusterStatusProtos$ServerLoad$Builder mergeFrom(com.google.protobuf.Message);
    Code:
       0: aload_1
       1: instanceof    #5                  // class org/apache/hadoop/hbase/protobuf/generated/ClusterStatusProtos$ServerLoad
       4: ifeq          16
       7: aload_0
       8: aload_1
       9: checkcast     #5                  // class org/apache/hadoop/hbase/protobuf/generated/ClusterStatusProtos$ServerLoad
      12: invokevirtual #39                 // Method mergeFrom:(Lorg/apache/hadoop/hbase/protobuf/generated/ClusterStatusProtos$ServerLoad;)Lorg/apache/hadoop/hbase/protobuf/generated/ClusterStatusProtos$ServerLoad$Builder;
      15: areturn
      16: aload_0
      17: aload_1
      18: invokespecial #61                 // Method com/google/protobuf/GeneratedMessage$Builder.mergeFrom:(Lcom/google/protobuf/Message;)Lcom/google/protobuf/AbstractMessage$Builder;
      21: pop
      22: aload_0
      23: areturn

  public org.apache.hadoop.hbase.protobuf.generated.ClusterStatusProtos$ServerLoad$Builder mergeFrom(org.apache.hadoop.hbase.protobuf.generated.ClusterStatusProtos$ServerLoad);
    Code:
       0: aload_1
       1: invokestatic  #40                 // Method org/apache/hadoop/hbase/protobuf/generated/ClusterStatusProtos$ServerLoad.getDefaultInstance:()Lorg/apache/hadoop/hbase/protobuf/generated/ClusterStatusProtos$ServerLoad;
       4: if_acmpne     9
       7: aload_0
       8: areturn
       9: aload_1
      10: invokevirtual #62                 // Method org/apache/hadoop/hbase/protobuf/generated/ClusterStatusProtos$ServerLoad.hasNumberOfRequests:()Z
      13: ifeq          25
      16: aload_0
      17: aload_1
      18: invokevirtual #63                 // Method org/apache/hadoop/hbase/protobuf/generated/ClusterStatusProtos$ServerLoad.getNumberOfRequests:()J
      21: invokevirtual #64                 // Method setNumberOfRequests:(J)Lorg/apache/hadoop/hbase/protobuf/generated/ClusterStatusProtos$ServerLoad$Builder;
      24: pop
      25: aload_1
      26: invokevirtual #65                 // Method org/apache/hadoop/hbase/protobuf/generated/ClusterStatusProtos$ServerLoad.hasTotalNumberOfRequests:()Z
      29: ifeq          41
      32: aload_0
      33: aload_1
      34: invokevirtual #66                 // Method org/apache/hadoop/hbase/protobuf/generated/ClusterStatusProtos$ServerLoad.getTotalNumberOfRequests:()J
      37: invokevirtual #67                 // Method setTotalNumberOfRequests:(J)Lorg/apache/hadoop/hbase/protobuf/generated/ClusterStatusProtos$ServerLoad$Builder;
      40: pop
      41: aload_1
      42: invokevirtual #68                 // Method org/apache/hadoop/hbase/protobuf/generated/ClusterStatusProtos$ServerLoad.hasUsedHeapMB:()Z
      45: ifeq          57
      48: aload_0
      49: aload_1
      50: invokevirtual #69                 // Method org/apache/hadoop/hbase/protobuf/generated/ClusterStatusProtos$ServerLoad.getUsedHeapMB:()I
      53: invokevirtual #70                 // Method setUsedHeapMB:(I)Lorg/apache/hadoop/hbase/protobuf/generated/ClusterStatusProtos$ServerLoad$Builder;
      56: pop
      57: aload_1
      58: invokevirtual #71                 // Method org/apache/hadoop/hbase/protobuf/generated/ClusterStatusProtos$ServerLoad.hasMaxHeapMB:()Z
      61: ifeq          73
      64: aload_0
      65: aload_1
      66: invokevirtual #72                 // Method org/apache/hadoop/hbase/protobuf/generated/ClusterStatusProtos$ServerLoad.getMaxHeapMB:()I
      69: invokevirtual #73                 // Method setMaxHeapMB:(I)Lorg/apache/hadoop/hbase/protobuf/generated/ClusterStatusProtos$ServerLoad$Builder;
      72: pop
      73: aload_0
      74: getfield      #29                 // Field regionLoadsBuilder_:Lcom/google/protobuf/RepeatedFieldBuilder;
      77: ifnonnull     151
      80: aload_1
      81: invokestatic  #74                 // Method org/apache/hadoop/hbase/protobuf/generated/ClusterStatusProtos$ServerLoad.access$10600:(Lorg/apache/hadoop/hbase/protobuf/generated/ClusterStatusProtos$ServerLoad;)Ljava/util/List;
      84: invokeinterface #75,  1           // InterfaceMethod java/util/List.isEmpty:()Z
      89: ifne          237
      92: aload_0
      93: getfield      #10                 // Field regionLoads_:Ljava/util/List;
      96: invokeinterface #75,  1           // InterfaceMethod java/util/List.isEmpty:()Z
     101: ifeq          126
     104: aload_0
     105: aload_1
     106: invokestatic  #74                 // Method org/apache/hadoop/hbase/protobuf/generated/ClusterStatusProtos$ServerLoad.access$10600:(Lorg/apache/hadoop/hbase/protobuf/generated/ClusterStatusProtos$ServerLoad;)Ljava/util/List;
     109: putfield      #10                 // Field regionLoads_:Ljava/util/List;
     112: aload_0
     113: aload_0
     114: getfield      #25                 // Field bitField0_:I
     117: bipush        -17
     119: iand
     120: putfield      #25                 // Field bitField0_:I
     123: goto          144
     126: aload_0
     127: invokespecial #76                 // Method ensureRegionLoadsIsMutable:()V
     130: aload_0
     131: getfield      #10                 // Field regionLoads_:Ljava/util/List;
     134: aload_1
     135: invokestatic  #74                 // Method org/apache/hadoop/hbase/protobuf/generated/ClusterStatusProtos$ServerLoad.access$10600:(Lorg/apache/hadoop/hbase/protobuf/generated/ClusterStatusProtos$ServerLoad;)Ljava/util/List;
     138: invokeinterface #77,  2           // InterfaceMethod java/util/List.addAll:(Ljava/util/Collection;)Z
     143: pop
     144: aload_0
     145: invokevirtual #78                 // Method onChanged:()V
     148: goto          237
     151: aload_1
     152: invokestatic  #74                 // Method org/apache/hadoop/hbase/protobuf/generated/ClusterStatusProtos$ServerLoad.access$10600:(Lorg/apache/hadoop/hbase/protobuf/generated/ClusterStatusProtos$ServerLoad;)Ljava/util/List;
     155: invokeinterface #75,  1           // InterfaceMethod java/util/List.isEmpty:()Z
     160: ifne          237
     163: aload_0
     164: getfield      #29                 // Field regionLoadsBuilder_:Lcom/google/protobuf/RepeatedFieldBuilder;
     167: invokevirtual #79                 // Method com/google/protobuf/RepeatedFieldBuilder.isEmpty:()Z
     170: ifeq          225
     173: aload_0
     174: getfield      #29                 // Field regionLoadsBuilder_:Lcom/google/protobuf/RepeatedFieldBuilder;
     177: invokevirtual #80                 // Method com/google/protobuf/RepeatedFieldBuilder.dispose:()V
     180: aload_0
     181: aconst_null
     182: putfield      #29                 // Field regionLoadsBuilder_:Lcom/google/protobuf/RepeatedFieldBuilder;
     185: aload_0
     186: aload_1
     187: invokestatic  #74                 // Method org/apache/hadoop/hbase/protobuf/generated/ClusterStatusProtos$ServerLoad.access$10600:(Lorg/apache/hadoop/hbase/protobuf/generated/ClusterStatusProtos$ServerLoad;)Ljava/util/List;
     190: putfield      #10                 // Field regionLoads_:Ljava/util/List;
     193: aload_0
     194: aload_0
     195: getfield      #25                 // Field bitField0_:I
     198: bipush        -17
     200: iand
     201: putfield      #25                 // Field bitField0_:I
     204: aload_0
     205: invokestatic  #81                 // Method org/apache/hadoop/hbase/protobuf/generated/ClusterStatusProtos$ServerLoad.access$11400:()Z
     208: ifeq          218
     211: aload_0
     212: invokespecial #18                 // Method getRegionLoadsFieldBuilder:()Lcom/google/protobuf/RepeatedFieldBuilder;
     215: goto          219
     218: aconst_null
     219: putfield      #29                 // Field regionLoadsBuilder_:Lcom/google/protobuf/RepeatedFieldBuilder;
     222: goto          237
     225: aload_0
     226: getfield      #29                 // Field regionLoadsBuilder_:Lcom/google/protobuf/RepeatedFieldBuilder;
     229: aload_1
     230: invokestatic  #74                 // Method org/apache/hadoop/hbase/protobuf/generated/ClusterStatusProtos$ServerLoad.access$10600:(Lorg/apache/hadoop/hbase/protobuf/generated/ClusterStatusProtos$ServerLoad;)Ljava/util/List;
     233: invokevirtual #82                 // Method com/google/protobuf/RepeatedFieldBuilder.addAllMessages:(Ljava/lang/Iterable;)Lcom/google/protobuf/RepeatedFieldBuilder;
     236: pop
     237: aload_0
     238: getfield      #31                 // Field coprocessorsBuilder_:Lcom/google/protobuf/RepeatedFieldBuilder;
     241: ifnonnull     315
     244: aload_1
     245: invokestatic  #83                 // Method org/apache/hadoop/hbase/protobuf/generated/ClusterStatusProtos$ServerLoad.access$10700:(Lorg/apache/hadoop/hbase/protobuf/generated/ClusterStatusProtos$ServerLoad;)Ljava/util/List;
     248: invokeinterface #75,  1           // InterfaceMethod java/util/List.isEmpty:()Z
     253: ifne          401
     256: aload_0
     257: getfield      #11                 // Field coprocessors_:Ljava/util/List;
     260: invokeinterface #75,  1           // InterfaceMethod java/util/List.isEmpty:()Z
     265: ifeq          290
     268: aload_0
     269: aload_1
     270: invokestatic  #83                 // Method org/apache/hadoop/hbase/protobuf/generated/ClusterStatusProtos$ServerLoad.access$10700:(Lorg/apache/hadoop/hbase/protobuf/generated/ClusterStatusProtos$ServerLoad;)Ljava/util/List;
     273: putfield      #11                 // Field coprocessors_:Ljava/util/List;
     276: aload_0
     277: aload_0
     278: getfield      #25                 // Field bitField0_:I
     281: bipush        -33
     283: iand
     284: putfield      #25                 // Field bitField0_:I
     287: goto          308
     290: aload_0
     291: invokespecial #84                 // Method ensureCoprocessorsIsMutable:()V
     294: aload_0
     295: getfield      #11                 // Field coprocessors_:Ljava/util/List;
     298: aload_1
     299: invokestatic  #83                 // Method org/apache/hadoop/hbase/protobuf/generated/ClusterStatusProtos$ServerLoad.access$10700:(Lorg/apache/hadoop/hbase/protobuf/generated/ClusterStatusProtos$ServerLoad;)Ljava/util/List;
     302: invokeinterface #77,  2           // InterfaceMethod java/util/List.addAll:(Ljava/util/Collection;)Z
     307: pop
     308: aload_0
     309: invokevirtual #78                 // Method onChanged:()V
     312: goto          401
     315: aload_1
     316: invokestatic  #83                 // Method org/apache/hadoop/hbase/protobuf/generated/ClusterStatusProtos$ServerLoad.access$10700:(Lorg/apache/hadoop/hbase/protobuf/generated/ClusterStatusProtos$ServerLoad;)Ljava/util/List;
     319: invokeinterface #75,  1           // InterfaceMethod java/util/List.isEmpty:()Z
     324: ifne          401
     327: aload_0
     328: getfield      #31                 // Field coprocessorsBuilder_:Lcom/google/protobuf/RepeatedFieldBuilder;
     331: invokevirtual #79                 // Method com/google/protobuf/RepeatedFieldBuilder.isEmpty:()Z
     334: ifeq          389
     337: aload_0
     338: getfield      #31                 // Field coprocessorsBuilder_:Lcom/google/protobuf/RepeatedFieldBuilder;
     341: invokevirtual #80                 // Method com/google/protobuf/RepeatedFieldBuilder.dispose:()V
     344: aload_0
     345: aconst_null
     346: putfield      #31                 // Field coprocessorsBuilder_:Lcom/google/protobuf/RepeatedFieldBuilder;
     349: aload_0
     350: aload_1
     351: invokestatic  #83                 // Method org/apache/hadoop/hbase/protobuf/generated/ClusterStatusProtos$ServerLoad.access$10700:(Lorg/apache/hadoop/hbase/protobuf/generated/ClusterStatusProtos$ServerLoad;)Ljava/util/List;
     354: putfield      #11                 // Field coprocessors_:Ljava/util/List;
     357: aload_0
     358: aload_0
     359: getfield      #25                 // Field bitField0_:I
     362: bipush        -33
     364: iand
     365: putfield      #25                 // Field bitField0_:I
     368: aload_0
     369: invokestatic  #85                 // Method org/apache/hadoop/hbase/protobuf/generated/ClusterStatusProtos$ServerLoad.access$11500:()Z
     372: ifeq          382
     375: aload_0
     376: invokespecial #19                 // Method getCoprocessorsFieldBuilder:()Lcom/google/protobuf/RepeatedFieldBuilder;
     379: goto          383
     382: aconst_null
     383: putfield      #31                 // Field coprocessorsBuilder_:Lcom/google/protobuf/RepeatedFieldBuilder;
     386: goto          401
     389: aload_0
     390: getfield      #31                 // Field coprocessorsBuilder_:Lcom/google/protobuf/RepeatedFieldBuilder;
     393: aload_1
     394: invokestatic  #83                 // Method org/apache/hadoop/hbase/protobuf/generated/ClusterStatusProtos$ServerLoad.access$10700:(Lorg/apache/hadoop/hbase/protobuf/generated/ClusterStatusProtos$ServerLoad;)Ljava/util/List;
     397: invokevirtual #82                 // Method com/google/protobuf/RepeatedFieldBuilder.addAllMessages:(Ljava/lang/Iterable;)Lcom/google/protobuf/RepeatedFieldBuilder;
     400: pop
     401: aload_1
     402: invokevirtual #86                 // Method org/apache/hadoop/hbase/protobuf/generated/ClusterStatusProtos$ServerLoad.hasReportStartTime:()Z
     405: ifeq          417
     408: aload_0
     409: aload_1
     410: invokevirtual #87                 // Method org/apache/hadoop/hbase/protobuf/generated/ClusterStatusProtos$ServerLoad.getReportStartTime:()J
     413: invokevirtual #88                 // Method setReportStartTime:(J)Lorg/apache/hadoop/hbase/protobuf/generated/ClusterStatusProtos$ServerLoad$Builder;
     416: pop
     417: aload_1
     418: invokevirtual #89                 // Method org/apache/hadoop/hbase/protobuf/generated/ClusterStatusProtos$ServerLoad.hasReportEndTime:()Z
     421: ifeq          433
     424: aload_0
     425: aload_1
     426: invokevirtual #90                 // Method org/apache/hadoop/hbase/protobuf/generated/ClusterStatusProtos$ServerLoad.getReportEndTime:()J
     429: invokevirtual #91                 // Method setReportEndTime:(J)Lorg/apache/hadoop/hbase/protobuf/generated/ClusterStatusProtos$ServerLoad$Builder;
     432: pop
     433: aload_1
     434: invokevirtual #92                 // Method org/apache/hadoop/hbase/protobuf/generated/ClusterStatusProtos$ServerLoad.hasInfoServerPort:()Z
     437: ifeq          449
     440: aload_0
     441: aload_1
     442: invokevirtual #93                 // Method org/apache/hadoop/hbase/protobuf/generated/ClusterStatusProtos$ServerLoad.getInfoServerPort:()I
     445: invokevirtual #94                 // Method setInfoServerPort:(I)Lorg/apache/hadoop/hbase/protobuf/generated/ClusterStatusProtos$ServerLoad$Builder;
     448: pop
     449: aload_0
     450: getfield      #35                 // Field replLoadSourceBuilder_:Lcom/google/protobuf/RepeatedFieldBuilder;
     453: ifnonnull     528
     456: aload_1
     457: invokestatic  #95                 // Method org/apache/hadoop/hbase/protobuf/generated/ClusterStatusProtos$ServerLoad.access$11100:(Lorg/apache/hadoop/hbase/protobuf/generated/ClusterStatusProtos$ServerLoad;)Ljava/util/List;
     460: invokeinterface #75,  1           // InterfaceMethod java/util/List.isEmpty:()Z
     465: ifne          615
     468: aload_0
     469: getfield      #12                 // Field replLoadSource_:Ljava/util/List;
     472: invokeinterface #75,  1           // InterfaceMethod java/util/List.isEmpty:()Z
     477: ifeq          503
     480: aload_0
     481: aload_1
     482: invokestatic  #95                 // Method org/apache/hadoop/hbase/protobuf/generated/ClusterStatusProtos$ServerLoad.access$11100:(Lorg/apache/hadoop/hbase/protobuf/generated/ClusterStatusProtos$ServerLoad;)Ljava/util/List;
     485: putfield      #12                 // Field replLoadSource_:Ljava/util/List;
     488: aload_0
     489: aload_0
     490: getfield      #25                 // Field bitField0_:I
     493: sipush        -513
     496: iand
     497: putfield      #25                 // Field bitField0_:I
     500: goto          521
     503: aload_0
     504: invokespecial #96                 // Method ensureReplLoadSourceIsMutable:()V
     507: aload_0
     508: getfield      #12                 // Field replLoadSource_:Ljava/util/List;
     511: aload_1
     512: invokestatic  #95                 // Method org/apache/hadoop/hbase/protobuf/generated/ClusterStatusProtos$ServerLoad.access$11100:(Lorg/apache/hadoop/hbase/protobuf/generated/ClusterStatusProtos$ServerLoad;)Ljava/util/List;
     515: invokeinterface #77,  2           // InterfaceMethod java/util/List.addAll:(Ljava/util/Collection;)Z
     520: pop
     521: aload_0
     522: invokevirtual #78                 // Method onChanged:()V
     525: goto          615
     528: aload_1
     529: invokestatic  #95                 // Method org/apache/hadoop/hbase/protobuf/generated/ClusterStatusProtos$ServerLoad.access$11100:(Lorg/apache/hadoop/hbase/protobuf/generated/ClusterStatusProtos$ServerLoad;)Ljava/util/List;
     532: invokeinterface #75,  1           // InterfaceMethod java/util/List.isEmpty:()Z
     537: ifne          615
     540: aload_0
     541: getfield      #35                 // Field replLoadSourceBuilder_:Lcom/google/protobuf/RepeatedFieldBuilder;
     544: invokevirtual #79                 // Method com/google/protobuf/RepeatedFieldBuilder.isEmpty:()Z
     547: ifeq          603
     550: aload_0
     551: getfield      #35                 // Field replLoadSourceBuilder_:Lcom/google/protobuf/RepeatedFieldBuilder;
     554: invokevirtual #80                 // Method com/google/protobuf/RepeatedFieldBuilder.dispose:()V
     557: aload_0
     558: aconst_null
     559: putfield      #35                 // Field replLoadSourceBuilder_:Lcom/google/protobuf/RepeatedFieldBuilder;
     562: aload_0
     563: aload_1
     564: invokestatic  #95                 // Method org/apache/hadoop/hbase/protobuf/generated/ClusterStatusProtos$ServerLoad.access$11100:(Lorg/apache/hadoop/hbase/protobuf/generated/ClusterStatusProtos$ServerLoad;)Ljava/util/List;
     567: putfield      #12                 // Field replLoadSource_:Ljava/util/List;
     570: aload_0
     571: aload_0
     572: getfield      #25                 // Field bitField0_:I
     575: sipush        -513
     578: iand
     579: putfield      #25                 // Field bitField0_:I
     582: aload_0
     583: invokestatic  #97                 // Method org/apache/hadoop/hbase/protobuf/generated/ClusterStatusProtos$ServerLoad.access$11600:()Z
     586: ifeq          596
     589: aload_0
     590: invokespecial #20                 // Method getReplLoadSourceFieldBuilder:()Lcom/google/protobuf/RepeatedFieldBuilder;
     593: goto          597
     596: aconst_null
     597: putfield      #35                 // Field replLoadSourceBuilder_:Lcom/google/protobuf/RepeatedFieldBuilder;
     600: goto          615
     603: aload_0
     604: getfield      #35                 // Field replLoadSourceBuilder_:Lcom/google/protobuf/RepeatedFieldBuilder;
     607: aload_1
     608: invokestatic  #95                 // Method org/apache/hadoop/hbase/protobuf/generated/ClusterStatusProtos$ServerLoad.access$11100:(Lorg/apache/hadoop/hbase/protobuf/generated/ClusterStatusProtos$ServerLoad;)Ljava/util/List;
     611: invokevirtual #82                 // Method com/google/protobuf/RepeatedFieldBuilder.addAllMessages:(Ljava/lang/Iterable;)Lcom/google/protobuf/RepeatedFieldBuilder;
     614: pop
     615: aload_1
     616: invokevirtual #98                 // Method org/apache/hadoop/hbase/protobuf/generated/ClusterStatusProtos$ServerLoad.hasReplLoadSink:()Z
     619: ifeq          631
     622: aload_0
     623: aload_1
     624: invokevirtual #99                 // Method org/apache/hadoop/hbase/protobuf/generated/ClusterStatusProtos$ServerLoad.getReplLoadSink:()Lorg/apache/hadoop/hbase/protobuf/generated/ClusterStatusProtos$ReplicationLoadSink;
     627: invokevirtual #100                // Method mergeReplLoadSink:(Lorg/apache/hadoop/hbase/protobuf/generated/ClusterStatusProtos$ReplicationLoadSink;)Lorg/apache/hadoop/hbase/protobuf/generated/ClusterStatusProtos$ServerLoad$Builder;
     630: pop
     631: aload_0
     632: aload_1
     633: invokevirtual #101                // Method org/apache/hadoop/hbase/protobuf/generated/ClusterStatusProtos$ServerLoad.getUnknownFields:()Lcom/google/protobuf/UnknownFieldSet;
     636: invokevirtual #102                // Method mergeUnknownFields:(Lcom/google/protobuf/UnknownFieldSet;)Lcom/google/protobuf/GeneratedMessage$Builder;
     639: pop
     640: aload_0
     641: areturn

  public final boolean isInitialized();
    Code:
       0: iconst_0
       1: istore_1
       2: iload_1
       3: aload_0
       4: invokevirtual #103                // Method getRegionLoadsCount:()I
       7: if_icmpge     29
      10: aload_0
      11: iload_1
      12: invokevirtual #104                // Method getRegionLoads:(I)Lorg/apache/hadoop/hbase/protobuf/generated/ClusterStatusProtos$RegionLoad;
      15: invokevirtual #105                // Method org/apache/hadoop/hbase/protobuf/generated/ClusterStatusProtos$RegionLoad.isInitialized:()Z
      18: ifne          23
      21: iconst_0
      22: ireturn
      23: iinc          1, 1
      26: goto          2
      29: iconst_0
      30: istore_1
      31: iload_1
      32: aload_0
      33: invokevirtual #106                // Method getCoprocessorsCount:()I
      36: if_icmpge     58
      39: aload_0
      40: iload_1
      41: invokevirtual #107                // Method getCoprocessors:(I)Lorg/apache/hadoop/hbase/protobuf/generated/HBaseProtos$Coprocessor;
      44: invokevirtual #108                // Method org/apache/hadoop/hbase/protobuf/generated/HBaseProtos$Coprocessor.isInitialized:()Z
      47: ifne          52
      50: iconst_0
      51: ireturn
      52: iinc          1, 1
      55: goto          31
      58: iconst_0
      59: istore_1
      60: iload_1
      61: aload_0
      62: invokevirtual #109                // Method getReplLoadSourceCount:()I
      65: if_icmpge     87
      68: aload_0
      69: iload_1
      70: invokevirtual #110                // Method getReplLoadSource:(I)Lorg/apache/hadoop/hbase/protobuf/generated/ClusterStatusProtos$ReplicationLoadSource;
      73: invokevirtual #111                // Method org/apache/hadoop/hbase/protobuf/generated/ClusterStatusProtos$ReplicationLoadSource.isInitialized:()Z
      76: ifne          81
      79: iconst_0
      80: ireturn
      81: iinc          1, 1
      84: goto          60
      87: aload_0
      88: invokevirtual #112                // Method hasReplLoadSink:()Z
      91: ifeq          106
      94: aload_0
      95: invokevirtual #113                // Method getReplLoadSink:()Lorg/apache/hadoop/hbase/protobuf/generated/ClusterStatusProtos$ReplicationLoadSink;
      98: invokevirtual #114                // Method org/apache/hadoop/hbase/protobuf/generated/ClusterStatusProtos$ReplicationLoadSink.isInitialized:()Z
     101: ifne          106
     104: iconst_0
     105: ireturn
     106: iconst_1
     107: ireturn

  public org.apache.hadoop.hbase.protobuf.generated.ClusterStatusProtos$ServerLoad$Builder mergeFrom(com.google.protobuf.CodedInputStream, com.google.protobuf.ExtensionRegistryLite) throws java.io.IOException;
    Code:
       0: aconst_null
       1: astore_3
       2: getstatic     #115                // Field org/apache/hadoop/hbase/protobuf/generated/ClusterStatusProtos$ServerLoad.PARSER:Lcom/google/protobuf/Parser;
       5: aload_1
       6: aload_2
       7: invokeinterface #116,  3          // InterfaceMethod com/google/protobuf/Parser.parsePartialFrom:(Lcom/google/protobuf/CodedInputStream;Lcom/google/protobuf/ExtensionRegistryLite;)Ljava/lang/Object;
      12: checkcast     #5                  // class org/apache/hadoop/hbase/protobuf/generated/ClusterStatusProtos$ServerLoad
      15: astore_3
      16: aload_3
      17: ifnull        58
      20: aload_0
      21: aload_3
      22: invokevirtual #39                 // Method mergeFrom:(Lorg/apache/hadoop/hbase/protobuf/generated/ClusterStatusProtos$ServerLoad;)Lorg/apache/hadoop/hbase/protobuf/generated/ClusterStatusProtos$ServerLoad$Builder;
      25: pop
      26: goto          58
      29: astore        4
      31: aload         4
      33: invokevirtual #118                // Method com/google/protobuf/InvalidProtocolBufferException.getUnfinishedMessage:()Lcom/google/protobuf/MessageLite;
      36: checkcast     #5                  // class org/apache/hadoop/hbase/protobuf/generated/ClusterStatusProtos$ServerLoad
      39: astore_3
      40: aload         4
      42: athrow
      43: astore        5
      45: aload_3
      46: ifnull        55
      49: aload_0
      50: aload_3
      51: invokevirtual #39                 // Method mergeFrom:(Lorg/apache/hadoop/hbase/protobuf/generated/ClusterStatusProtos$ServerLoad;)Lorg/apache/hadoop/hbase/protobuf/generated/ClusterStatusProtos$ServerLoad$Builder;
      54: pop
      55: aload         5
      57: athrow
      58: aload_0
      59: areturn
    Exception table:
       from    to  target type
           2    16    29   Class com/google/protobuf/InvalidProtocolBufferException
           2    16    43   any
          29    45    43   any

  public boolean hasNumberOfRequests();
    Code:
       0: aload_0
       1: getfield      #25                 // Field bitField0_:I
       4: iconst_1
       5: iand
       6: iconst_1
       7: if_icmpne     14
      10: iconst_1
      11: goto          15
      14: iconst_0
      15: ireturn

  public long getNumberOfRequests();
    Code:
       0: aload_0
       1: getfield      #24                 // Field numberOfRequests_:J
       4: lreturn

  public org.apache.hadoop.hbase.protobuf.generated.ClusterStatusProtos$ServerLoad$Builder setNumberOfRequests(long);
    Code:
       0: aload_0
       1: dup
       2: getfield      #25                 // Field bitField0_:I
       5: iconst_1
       6: ior
       7: putfield      #25                 // Field bitField0_:I
      10: aload_0
      11: lload_1
      12: putfield      #24                 // Field numberOfRequests_:J
      15: aload_0
      16: invokevirtual #78                 // Method onChanged:()V
      19: aload_0
      20: areturn

  public org.apache.hadoop.hbase.protobuf.generated.ClusterStatusProtos$ServerLoad$Builder clearNumberOfRequests();
    Code:
       0: aload_0
       1: aload_0
       2: getfield      #25                 // Field bitField0_:I
       5: bipush        -2
       7: iand
       8: putfield      #25                 // Field bitField0_:I
      11: aload_0
      12: lconst_0
      13: putfield      #24                 // Field numberOfRequests_:J
      16: aload_0
      17: invokevirtual #78                 // Method onChanged:()V
      20: aload_0
      21: areturn

  public boolean hasTotalNumberOfRequests();
    Code:
       0: aload_0
       1: getfield      #25                 // Field bitField0_:I
       4: iconst_2
       5: iand
       6: iconst_2
       7: if_icmpne     14
      10: iconst_1
      11: goto          15
      14: iconst_0
      15: ireturn

  public long getTotalNumberOfRequests();
    Code:
       0: aload_0
       1: getfield      #26                 // Field totalNumberOfRequests_:J
       4: lreturn

  public org.apache.hadoop.hbase.protobuf.generated.ClusterStatusProtos$ServerLoad$Builder setTotalNumberOfRequests(long);
    Code:
       0: aload_0
       1: dup
       2: getfield      #25                 // Field bitField0_:I
       5: iconst_2
       6: ior
       7: putfield      #25                 // Field bitField0_:I
      10: aload_0
      11: lload_1
      12: putfield      #26                 // Field totalNumberOfRequests_:J
      15: aload_0
      16: invokevirtual #78                 // Method onChanged:()V
      19: aload_0
      20: areturn

  public org.apache.hadoop.hbase.protobuf.generated.ClusterStatusProtos$ServerLoad$Builder clearTotalNumberOfRequests();
    Code:
       0: aload_0
       1: aload_0
       2: getfield      #25                 // Field bitField0_:I
       5: bipush        -3
       7: iand
       8: putfield      #25                 // Field bitField0_:I
      11: aload_0
      12: lconst_0
      13: putfield      #26                 // Field totalNumberOfRequests_:J
      16: aload_0
      17: invokevirtual #78                 // Method onChanged:()V
      20: aload_0
      21: areturn

  public boolean hasUsedHeapMB();
    Code:
       0: aload_0
       1: getfield      #25                 // Field bitField0_:I
       4: iconst_4
       5: iand
       6: iconst_4
       7: if_icmpne     14
      10: iconst_1
      11: goto          15
      14: iconst_0
      15: ireturn

  public int getUsedHeapMB();
    Code:
       0: aload_0
       1: getfield      #27                 // Field usedHeapMB_:I
       4: ireturn

  public org.apache.hadoop.hbase.protobuf.generated.ClusterStatusProtos$ServerLoad$Builder setUsedHeapMB(int);
    Code:
       0: aload_0
       1: dup
       2: getfield      #25                 // Field bitField0_:I
       5: iconst_4
       6: ior
       7: putfield      #25                 // Field bitField0_:I
      10: aload_0
      11: iload_1
      12: putfield      #27                 // Field usedHeapMB_:I
      15: aload_0
      16: invokevirtual #78                 // Method onChanged:()V
      19: aload_0
      20: areturn

  public org.apache.hadoop.hbase.protobuf.generated.ClusterStatusProtos$ServerLoad$Builder clearUsedHeapMB();
    Code:
       0: aload_0
       1: aload_0
       2: getfield      #25                 // Field bitField0_:I
       5: bipush        -5
       7: iand
       8: putfield      #25                 // Field bitField0_:I
      11: aload_0
      12: iconst_0
      13: putfield      #27                 // Field usedHeapMB_:I
      16: aload_0
      17: invokevirtual #78                 // Method onChanged:()V
      20: aload_0
      21: areturn

  public boolean hasMaxHeapMB();
    Code:
       0: aload_0
       1: getfield      #25                 // Field bitField0_:I
       4: bipush        8
       6: iand
       7: bipush        8
       9: if_icmpne     16
      12: iconst_1
      13: goto          17
      16: iconst_0
      17: ireturn

  public int getMaxHeapMB();
    Code:
       0: aload_0
       1: getfield      #28                 // Field maxHeapMB_:I
       4: ireturn

  public org.apache.hadoop.hbase.protobuf.generated.ClusterStatusProtos$ServerLoad$Builder setMaxHeapMB(int);
    Code:
       0: aload_0
       1: dup
       2: getfield      #25                 // Field bitField0_:I
       5: bipush        8
       7: ior
       8: putfield      #25                 // Field bitField0_:I
      11: aload_0
      12: iload_1
      13: putfield      #28                 // Field maxHeapMB_:I
      16: aload_0
      17: invokevirtual #78                 // Method onChanged:()V
      20: aload_0
      21: areturn

  public org.apache.hadoop.hbase.protobuf.generated.ClusterStatusProtos$ServerLoad$Builder clearMaxHeapMB();
    Code:
       0: aload_0
       1: aload_0
       2: getfield      #25                 // Field bitField0_:I
       5: bipush        -9
       7: iand
       8: putfield      #25                 // Field bitField0_:I
      11: aload_0
      12: iconst_0
      13: putfield      #28                 // Field maxHeapMB_:I
      16: aload_0
      17: invokevirtual #78                 // Method onChanged:()V
      20: aload_0
      21: areturn

  public java.util.List<org.apache.hadoop.hbase.protobuf.generated.ClusterStatusProtos$RegionLoad> getRegionLoadsList();
    Code:
       0: aload_0
       1: getfield      #29                 // Field regionLoadsBuilder_:Lcom/google/protobuf/RepeatedFieldBuilder;
       4: ifnonnull     15
       7: aload_0
       8: getfield      #10                 // Field regionLoads_:Ljava/util/List;
      11: invokestatic  #48                 // Method java/util/Collections.unmodifiableList:(Ljava/util/List;)Ljava/util/List;
      14: areturn
      15: aload_0
      16: getfield      #29                 // Field regionLoadsBuilder_:Lcom/google/protobuf/RepeatedFieldBuilder;
      19: invokevirtual #121                // Method com/google/protobuf/RepeatedFieldBuilder.getMessageList:()Ljava/util/List;
      22: areturn

  public int getRegionLoadsCount();
    Code:
       0: aload_0
       1: getfield      #29                 // Field regionLoadsBuilder_:Lcom/google/protobuf/RepeatedFieldBuilder;
       4: ifnonnull     17
       7: aload_0
       8: getfield      #10                 // Field regionLoads_:Ljava/util/List;
      11: invokeinterface #122,  1          // InterfaceMethod java/util/List.size:()I
      16: ireturn
      17: aload_0
      18: getfield      #29                 // Field regionLoadsBuilder_:Lcom/google/protobuf/RepeatedFieldBuilder;
      21: invokevirtual #123                // Method com/google/protobuf/RepeatedFieldBuilder.getCount:()I
      24: ireturn

  public org.apache.hadoop.hbase.protobuf.generated.ClusterStatusProtos$RegionLoad getRegionLoads(int);
    Code:
       0: aload_0
       1: getfield      #29                 // Field regionLoadsBuilder_:Lcom/google/protobuf/RepeatedFieldBuilder;
       4: ifnonnull     21
       7: aload_0
       8: getfield      #10                 // Field regionLoads_:Ljava/util/List;
      11: iload_1
      12: invokeinterface #124,  2          // InterfaceMethod java/util/List.get:(I)Ljava/lang/Object;
      17: checkcast     #125                // class org/apache/hadoop/hbase/protobuf/generated/ClusterStatusProtos$RegionLoad
      20: areturn
      21: aload_0
      22: getfield      #29                 // Field regionLoadsBuilder_:Lcom/google/protobuf/RepeatedFieldBuilder;
      25: iload_1
      26: invokevirtual #126                // Method com/google/protobuf/RepeatedFieldBuilder.getMessage:(I)Lcom/google/protobuf/GeneratedMessage;
      29: checkcast     #125                // class org/apache/hadoop/hbase/protobuf/generated/ClusterStatusProtos$RegionLoad
      32: areturn

  public org.apache.hadoop.hbase.protobuf.generated.ClusterStatusProtos$ServerLoad$Builder setRegionLoads(int, org.apache.hadoop.hbase.protobuf.generated.ClusterStatusProtos$RegionLoad);
    Code:
       0: aload_0
       1: getfield      #29                 // Field regionLoadsBuilder_:Lcom/google/protobuf/RepeatedFieldBuilder;
       4: ifnonnull     42
       7: aload_2
       8: ifnonnull     19
      11: new           #127                // class java/lang/NullPointerException
      14: dup
      15: invokespecial #128                // Method java/lang/NullPointerException."<init>":()V
      18: athrow
      19: aload_0
      20: invokespecial #76                 // Method ensureRegionLoadsIsMutable:()V
      23: aload_0
      24: getfield      #10                 // Field regionLoads_:Ljava/util/List;
      27: iload_1
      28: aload_2
      29: invokeinterface #129,  3          // InterfaceMethod java/util/List.set:(ILjava/lang/Object;)Ljava/lang/Object;
      34: pop
      35: aload_0
      36: invokevirtual #78                 // Method onChanged:()V
      39: goto          52
      42: aload_0
      43: getfield      #29                 // Field regionLoadsBuilder_:Lcom/google/protobuf/RepeatedFieldBuilder;
      46: iload_1
      47: aload_2
      48: invokevirtual #130                // Method com/google/protobuf/RepeatedFieldBuilder.setMessage:(ILcom/google/protobuf/GeneratedMessage;)Lcom/google/protobuf/RepeatedFieldBuilder;
      51: pop
      52: aload_0
      53: areturn

  public org.apache.hadoop.hbase.protobuf.generated.ClusterStatusProtos$ServerLoad$Builder setRegionLoads(int, org.apache.hadoop.hbase.protobuf.generated.ClusterStatusProtos$RegionLoad$Builder);
    Code:
       0: aload_0
       1: getfield      #29                 // Field regionLoadsBuilder_:Lcom/google/protobuf/RepeatedFieldBuilder;
       4: ifnonnull     33
       7: aload_0
       8: invokespecial #76                 // Method ensureRegionLoadsIsMutable:()V
      11: aload_0
      12: getfield      #10                 // Field regionLoads_:Ljava/util/List;
      15: iload_1
      16: aload_2
      17: invokevirtual #131                // Method org/apache/hadoop/hbase/protobuf/generated/ClusterStatusProtos$RegionLoad$Builder.build:()Lorg/apache/hadoop/hbase/protobuf/generated/ClusterStatusProtos$RegionLoad;
      20: invokeinterface #129,  3          // InterfaceMethod java/util/List.set:(ILjava/lang/Object;)Ljava/lang/Object;
      25: pop
      26: aload_0
      27: invokevirtual #78                 // Method onChanged:()V
      30: goto          46
      33: aload_0
      34: getfield      #29                 // Field regionLoadsBuilder_:Lcom/google/protobuf/RepeatedFieldBuilder;
      37: iload_1
      38: aload_2
      39: invokevirtual #131                // Method org/apache/hadoop/hbase/protobuf/generated/ClusterStatusProtos$RegionLoad$Builder.build:()Lorg/apache/hadoop/hbase/protobuf/generated/ClusterStatusProtos$RegionLoad;
      42: invokevirtual #130                // Method com/google/protobuf/RepeatedFieldBuilder.setMessage:(ILcom/google/protobuf/GeneratedMessage;)Lcom/google/protobuf/RepeatedFieldBuilder;
      45: pop
      46: aload_0
      47: areturn

  public org.apache.hadoop.hbase.protobuf.generated.ClusterStatusProtos$ServerLoad$Builder addRegionLoads(org.apache.hadoop.hbase.protobuf.generated.ClusterStatusProtos$RegionLoad);
    Code:
       0: aload_0
       1: getfield      #29                 // Field regionLoadsBuilder_:Lcom/google/protobuf/RepeatedFieldBuilder;
       4: ifnonnull     41
       7: aload_1
       8: ifnonnull     19
      11: new           #127                // class java/lang/NullPointerException
      14: dup
      15: invokespecial #128                // Method java/lang/NullPointerException."<init>":()V
      18: athrow
      19: aload_0
      20: invokespecial #76                 // Method ensureRegionLoadsIsMutable:()V
      23: aload_0
      24: getfield      #10                 // Field regionLoads_:Ljava/util/List;
      27: aload_1
      28: invokeinterface #132,  2          // InterfaceMethod java/util/List.add:(Ljava/lang/Object;)Z
      33: pop
      34: aload_0
      35: invokevirtual #78                 // Method onChanged:()V
      38: goto          50
      41: aload_0
      42: getfield      #29                 // Field regionLoadsBuilder_:Lcom/google/protobuf/RepeatedFieldBuilder;
      45: aload_1
      46: invokevirtual #133                // Method com/google/protobuf/RepeatedFieldBuilder.addMessage:(Lcom/google/protobuf/GeneratedMessage;)Lcom/google/protobuf/RepeatedFieldBuilder;
      49: pop
      50: aload_0
      51: areturn

  public org.apache.hadoop.hbase.protobuf.generated.ClusterStatusProtos$ServerLoad$Builder addRegionLoads(int, org.apache.hadoop.hbase.protobuf.generated.ClusterStatusProtos$RegionLoad);
    Code:
       0: aload_0
       1: getfield      #29                 // Field regionLoadsBuilder_:Lcom/google/protobuf/RepeatedFieldBuilder;
       4: ifnonnull     41
       7: aload_2
       8: ifnonnull     19
      11: new           #127                // class java/lang/NullPointerException
      14: dup
      15: invokespecial #128                // Method java/lang/NullPointerException."<init>":()V
      18: athrow
      19: aload_0
      20: invokespecial #76                 // Method ensureRegionLoadsIsMutable:()V
      23: aload_0
      24: getfield      #10                 // Field regionLoads_:Ljava/util/List;
      27: iload_1
      28: aload_2
      29: invokeinterface #134,  3          // InterfaceMethod java/util/List.add:(ILjava/lang/Object;)V
      34: aload_0
      35: invokevirtual #78                 // Method onChanged:()V
      38: goto          51
      41: aload_0
      42: getfield      #29                 // Field regionLoadsBuilder_:Lcom/google/protobuf/RepeatedFieldBuilder;
      45: iload_1
      46: aload_2
      47: invokevirtual #135                // Method com/google/protobuf/RepeatedFieldBuilder.addMessage:(ILcom/google/protobuf/GeneratedMessage;)Lcom/google/protobuf/RepeatedFieldBuilder;
      50: pop
      51: aload_0
      52: areturn

  public org.apache.hadoop.hbase.protobuf.generated.ClusterStatusProtos$ServerLoad$Builder addRegionLoads(org.apache.hadoop.hbase.protobuf.generated.ClusterStatusProtos$RegionLoad$Builder);
    Code:
       0: aload_0
       1: getfield      #29                 // Field regionLoadsBuilder_:Lcom/google/protobuf/RepeatedFieldBuilder;
       4: ifnonnull     32
       7: aload_0
       8: invokespecial #76                 // Method ensureRegionLoadsIsMutable:()V
      11: aload_0
      12: getfield      #10                 // Field regionLoads_:Ljava/util/List;
      15: aload_1
      16: invokevirtual #131                // Method org/apache/hadoop/hbase/protobuf/generated/ClusterStatusProtos$RegionLoad$Builder.build:()Lorg/apache/hadoop/hbase/protobuf/generated/ClusterStatusProtos$RegionLoad;
      19: invokeinterface #132,  2          // InterfaceMethod java/util/List.add:(Ljava/lang/Object;)Z
      24: pop
      25: aload_0
      26: invokevirtual #78                 // Method onChanged:()V
      29: goto          44
      32: aload_0
      33: getfield      #29                 // Field regionLoadsBuilder_:Lcom/google/protobuf/RepeatedFieldBuilder;
      36: aload_1
      37: invokevirtual #131                // Method org/apache/hadoop/hbase/protobuf/generated/ClusterStatusProtos$RegionLoad$Builder.build:()Lorg/apache/hadoop/hbase/protobuf/generated/ClusterStatusProtos$RegionLoad;
      40: invokevirtual #133                // Method com/google/protobuf/RepeatedFieldBuilder.addMessage:(Lcom/google/protobuf/GeneratedMessage;)Lcom/google/protobuf/RepeatedFieldBuilder;
      43: pop
      44: aload_0
      45: areturn

  public org.apache.hadoop.hbase.protobuf.generated.ClusterStatusProtos$ServerLoad$Builder addRegionLoads(int, org.apache.hadoop.hbase.protobuf.generated.ClusterStatusProtos$RegionLoad$Builder);
    Code:
       0: aload_0
       1: getfield      #29                 // Field regionLoadsBuilder_:Lcom/google/protobuf/RepeatedFieldBuilder;
       4: ifnonnull     32
       7: aload_0
       8: invokespecial #76                 // Method ensureRegionLoadsIsMutable:()V
      11: aload_0
      12: getfield      #10                 // Field regionLoads_:Ljava/util/List;
      15: iload_1
      16: aload_2
      17: invokevirtual #131                // Method org/apache/hadoop/hbase/protobuf/generated/ClusterStatusProtos$RegionLoad$Builder.build:()Lorg/apache/hadoop/hbase/protobuf/generated/ClusterStatusProtos$RegionLoad;
      20: invokeinterface #134,  3          // InterfaceMethod java/util/List.add:(ILjava/lang/Object;)V
      25: aload_0
      26: invokevirtual #78                 // Method onChanged:()V
      29: goto          45
      32: aload_0
      33: getfield      #29                 // Field regionLoadsBuilder_:Lcom/google/protobuf/RepeatedFieldBuilder;
      36: iload_1
      37: aload_2
      38: invokevirtual #131                // Method org/apache/hadoop/hbase/protobuf/generated/ClusterStatusProtos$RegionLoad$Builder.build:()Lorg/apache/hadoop/hbase/protobuf/generated/ClusterStatusProtos$RegionLoad;
      41: invokevirtual #135                // Method com/google/protobuf/RepeatedFieldBuilder.addMessage:(ILcom/google/protobuf/GeneratedMessage;)Lcom/google/protobuf/RepeatedFieldBuilder;
      44: pop
      45: aload_0
      46: areturn

  public org.apache.hadoop.hbase.protobuf.generated.ClusterStatusProtos$ServerLoad$Builder addAllRegionLoads(java.lang.Iterable<? extends org.apache.hadoop.hbase.protobuf.generated.ClusterStatusProtos$RegionLoad>);
    Code:
       0: aload_0
       1: getfield      #29                 // Field regionLoadsBuilder_:Lcom/google/protobuf/RepeatedFieldBuilder;
       4: ifnonnull     26
       7: aload_0
       8: invokespecial #76                 // Method ensureRegionLoadsIsMutable:()V
      11: aload_1
      12: aload_0
      13: getfield      #10                 // Field regionLoads_:Ljava/util/List;
      16: invokestatic  #136                // Method com/google/protobuf/GeneratedMessage$Builder.addAll:(Ljava/lang/Iterable;Ljava/util/Collection;)V
      19: aload_0
      20: invokevirtual #78                 // Method onChanged:()V
      23: goto          35
      26: aload_0
      27: getfield      #29                 // Field regionLoadsBuilder_:Lcom/google/protobuf/RepeatedFieldBuilder;
      30: aload_1
      31: invokevirtual #82                 // Method com/google/protobuf/RepeatedFieldBuilder.addAllMessages:(Ljava/lang/Iterable;)Lcom/google/protobuf/RepeatedFieldBuilder;
      34: pop
      35: aload_0
      36: areturn

  public org.apache.hadoop.hbase.protobuf.generated.ClusterStatusProtos$ServerLoad$Builder clearRegionLoads();
    Code:
       0: aload_0
       1: getfield      #29                 // Field regionLoadsBuilder_:Lcom/google/protobuf/RepeatedFieldBuilder;
       4: ifnonnull     32
       7: aload_0
       8: invokestatic  #9                  // Method java/util/Collections.emptyList:()Ljava/util/List;
      11: putfield      #10                 // Field regionLoads_:Ljava/util/List;
      14: aload_0
      15: aload_0
      16: getfield      #25                 // Field bitField0_:I
      19: bipush        -17
      21: iand
      22: putfield      #25                 // Field bitField0_:I
      25: aload_0
      26: invokevirtual #78                 // Method onChanged:()V
      29: goto          39
      32: aload_0
      33: getfield      #29                 // Field regionLoadsBuilder_:Lcom/google/protobuf/RepeatedFieldBuilder;
      36: invokevirtual #30                 // Method com/google/protobuf/RepeatedFieldBuilder.clear:()V
      39: aload_0
      40: areturn

  public org.apache.hadoop.hbase.protobuf.generated.ClusterStatusProtos$ServerLoad$Builder removeRegionLoads(int);
    Code:
       0: aload_0
       1: getfield      #29                 // Field regionLoadsBuilder_:Lcom/google/protobuf/RepeatedFieldBuilder;
       4: ifnonnull     29
       7: aload_0
       8: invokespecial #76                 // Method ensureRegionLoadsIsMutable:()V
      11: aload_0
      12: getfield      #10                 // Field regionLoads_:Ljava/util/List;
      15: iload_1
      16: invokeinterface #137,  2          // InterfaceMethod java/util/List.remove:(I)Ljava/lang/Object;
      21: pop
      22: aload_0
      23: invokevirtual #78                 // Method onChanged:()V
      26: goto          37
      29: aload_0
      30: getfield      #29                 // Field regionLoadsBuilder_:Lcom/google/protobuf/RepeatedFieldBuilder;
      33: iload_1
      34: invokevirtual #138                // Method com/google/protobuf/RepeatedFieldBuilder.remove:(I)V
      37: aload_0
      38: areturn

  public org.apache.hadoop.hbase.protobuf.generated.ClusterStatusProtos$RegionLoad$Builder getRegionLoadsBuilder(int);
    Code:
       0: aload_0
       1: invokespecial #18                 // Method getRegionLoadsFieldBuilder:()Lcom/google/protobuf/RepeatedFieldBuilder;
       4: iload_1
       5: invokevirtual #139                // Method com/google/protobuf/RepeatedFieldBuilder.getBuilder:(I)Lcom/google/protobuf/GeneratedMessage$Builder;
       8: checkcast     #140                // class org/apache/hadoop/hbase/protobuf/generated/ClusterStatusProtos$RegionLoad$Builder
      11: areturn

  public org.apache.hadoop.hbase.protobuf.generated.ClusterStatusProtos$RegionLoadOrBuilder getRegionLoadsOrBuilder(int);
    Code:
       0: aload_0
       1: getfield      #29                 // Field regionLoadsBuilder_:Lcom/google/protobuf/RepeatedFieldBuilder;
       4: ifnonnull     21
       7: aload_0
       8: getfield      #10                 // Field regionLoads_:Ljava/util/List;
      11: iload_1
      12: invokeinterface #124,  2          // InterfaceMethod java/util/List.get:(I)Ljava/lang/Object;
      17: checkcast     #141                // class org/apache/hadoop/hbase/protobuf/generated/ClusterStatusProtos$RegionLoadOrBuilder
      20: areturn
      21: aload_0
      22: getfield      #29                 // Field regionLoadsBuilder_:Lcom/google/protobuf/RepeatedFieldBuilder;
      25: iload_1
      26: invokevirtual #142                // Method com/google/protobuf/RepeatedFieldBuilder.getMessageOrBuilder:(I)Lcom/google/protobuf/MessageOrBuilder;
      29: checkcast     #141                // class org/apache/hadoop/hbase/protobuf/generated/ClusterStatusProtos$RegionLoadOrBuilder
      32: areturn

  public java.util.List<? extends org.apache.hadoop.hbase.protobuf.generated.ClusterStatusProtos$RegionLoadOrBuilder> getRegionLoadsOrBuilderList();
    Code:
       0: aload_0
       1: getfield      #29                 // Field regionLoadsBuilder_:Lcom/google/protobuf/RepeatedFieldBuilder;
       4: ifnull        15
       7: aload_0
       8: getfield      #29                 // Field regionLoadsBuilder_:Lcom/google/protobuf/RepeatedFieldBuilder;
      11: invokevirtual #143                // Method com/google/protobuf/RepeatedFieldBuilder.getMessageOrBuilderList:()Ljava/util/List;
      14: areturn
      15: aload_0
      16: getfield      #10                 // Field regionLoads_:Ljava/util/List;
      19: invokestatic  #48                 // Method java/util/Collections.unmodifiableList:(Ljava/util/List;)Ljava/util/List;
      22: areturn

  public org.apache.hadoop.hbase.protobuf.generated.ClusterStatusProtos$RegionLoad$Builder addRegionLoadsBuilder();
    Code:
       0: aload_0
       1: invokespecial #18                 // Method getRegionLoadsFieldBuilder:()Lcom/google/protobuf/RepeatedFieldBuilder;
       4: invokestatic  #144                // Method org/apache/hadoop/hbase/protobuf/generated/ClusterStatusProtos$RegionLoad.getDefaultInstance:()Lorg/apache/hadoop/hbase/protobuf/generated/ClusterStatusProtos$RegionLoad;
       7: invokevirtual #145                // Method com/google/protobuf/RepeatedFieldBuilder.addBuilder:(Lcom/google/protobuf/GeneratedMessage;)Lcom/google/protobuf/GeneratedMessage$Builder;
      10: checkcast     #140                // class org/apache/hadoop/hbase/protobuf/generated/ClusterStatusProtos$RegionLoad$Builder
      13: areturn

  public org.apache.hadoop.hbase.protobuf.generated.ClusterStatusProtos$RegionLoad$Builder addRegionLoadsBuilder(int);
    Code:
       0: aload_0
       1: invokespecial #18                 // Method getRegionLoadsFieldBuilder:()Lcom/google/protobuf/RepeatedFieldBuilder;
       4: iload_1
       5: invokestatic  #144                // Method org/apache/hadoop/hbase/protobuf/generated/ClusterStatusProtos$RegionLoad.getDefaultInstance:()Lorg/apache/hadoop/hbase/protobuf/generated/ClusterStatusProtos$RegionLoad;
       8: invokevirtual #146                // Method com/google/protobuf/RepeatedFieldBuilder.addBuilder:(ILcom/google/protobuf/GeneratedMessage;)Lcom/google/protobuf/GeneratedMessage$Builder;
      11: checkcast     #140                // class org/apache/hadoop/hbase/protobuf/generated/ClusterStatusProtos$RegionLoad$Builder
      14: areturn

  public java.util.List<org.apache.hadoop.hbase.protobuf.generated.ClusterStatusProtos$RegionLoad$Builder> getRegionLoadsBuilderList();
    Code:
       0: aload_0
       1: invokespecial #18                 // Method getRegionLoadsFieldBuilder:()Lcom/google/protobuf/RepeatedFieldBuilder;
       4: invokevirtual #147                // Method com/google/protobuf/RepeatedFieldBuilder.getBuilderList:()Ljava/util/List;
       7: areturn

  public java.util.List<org.apache.hadoop.hbase.protobuf.generated.HBaseProtos$Coprocessor> getCoprocessorsList();
    Code:
       0: aload_0
       1: getfield      #31                 // Field coprocessorsBuilder_:Lcom/google/protobuf/RepeatedFieldBuilder;
       4: ifnonnull     15
       7: aload_0
       8: getfield      #11                 // Field coprocessors_:Ljava/util/List;
      11: invokestatic  #48                 // Method java/util/Collections.unmodifiableList:(Ljava/util/List;)Ljava/util/List;
      14: areturn
      15: aload_0
      16: getfield      #31                 // Field coprocessorsBuilder_:Lcom/google/protobuf/RepeatedFieldBuilder;
      19: invokevirtual #121                // Method com/google/protobuf/RepeatedFieldBuilder.getMessageList:()Ljava/util/List;
      22: areturn

  public int getCoprocessorsCount();
    Code:
       0: aload_0
       1: getfield      #31                 // Field coprocessorsBuilder_:Lcom/google/protobuf/RepeatedFieldBuilder;
       4: ifnonnull     17
       7: aload_0
       8: getfield      #11                 // Field coprocessors_:Ljava/util/List;
      11: invokeinterface #122,  1          // InterfaceMethod java/util/List.size:()I
      16: ireturn
      17: aload_0
      18: getfield      #31                 // Field coprocessorsBuilder_:Lcom/google/protobuf/RepeatedFieldBuilder;
      21: invokevirtual #123                // Method com/google/protobuf/RepeatedFieldBuilder.getCount:()I
      24: ireturn

  public org.apache.hadoop.hbase.protobuf.generated.HBaseProtos$Coprocessor getCoprocessors(int);
    Code:
       0: aload_0
       1: getfield      #31                 // Field coprocessorsBuilder_:Lcom/google/protobuf/RepeatedFieldBuilder;
       4: ifnonnull     21
       7: aload_0
       8: getfield      #11                 // Field coprocessors_:Ljava/util/List;
      11: iload_1
      12: invokeinterface #124,  2          // InterfaceMethod java/util/List.get:(I)Ljava/lang/Object;
      17: checkcast     #152                // class org/apache/hadoop/hbase/protobuf/generated/HBaseProtos$Coprocessor
      20: areturn
      21: aload_0
      22: getfield      #31                 // Field coprocessorsBuilder_:Lcom/google/protobuf/RepeatedFieldBuilder;
      25: iload_1
      26: invokevirtual #126                // Method com/google/protobuf/RepeatedFieldBuilder.getMessage:(I)Lcom/google/protobuf/GeneratedMessage;
      29: checkcast     #152                // class org/apache/hadoop/hbase/protobuf/generated/HBaseProtos$Coprocessor
      32: areturn

  public org.apache.hadoop.hbase.protobuf.generated.ClusterStatusProtos$ServerLoad$Builder setCoprocessors(int, org.apache.hadoop.hbase.protobuf.generated.HBaseProtos$Coprocessor);
    Code:
       0: aload_0
       1: getfield      #31                 // Field coprocessorsBuilder_:Lcom/google/protobuf/RepeatedFieldBuilder;
       4: ifnonnull     42
       7: aload_2
       8: ifnonnull     19
      11: new           #127                // class java/lang/NullPointerException
      14: dup
      15: invokespecial #128                // Method java/lang/NullPointerException."<init>":()V
      18: athrow
      19: aload_0
      20: invokespecial #84                 // Method ensureCoprocessorsIsMutable:()V
      23: aload_0
      24: getfield      #11                 // Field coprocessors_:Ljava/util/List;
      27: iload_1
      28: aload_2
      29: invokeinterface #129,  3          // InterfaceMethod java/util/List.set:(ILjava/lang/Object;)Ljava/lang/Object;
      34: pop
      35: aload_0
      36: invokevirtual #78                 // Method onChanged:()V
      39: goto          52
      42: aload_0
      43: getfield      #31                 // Field coprocessorsBuilder_:Lcom/google/protobuf/RepeatedFieldBuilder;
      46: iload_1
      47: aload_2
      48: invokevirtual #130                // Method com/google/protobuf/RepeatedFieldBuilder.setMessage:(ILcom/google/protobuf/GeneratedMessage;)Lcom/google/protobuf/RepeatedFieldBuilder;
      51: pop
      52: aload_0
      53: areturn

  public org.apache.hadoop.hbase.protobuf.generated.ClusterStatusProtos$ServerLoad$Builder setCoprocessors(int, org.apache.hadoop.hbase.protobuf.generated.HBaseProtos$Coprocessor$Builder);
    Code:
       0: aload_0
       1: getfield      #31                 // Field coprocessorsBuilder_:Lcom/google/protobuf/RepeatedFieldBuilder;
       4: ifnonnull     33
       7: aload_0
       8: invokespecial #84                 // Method ensureCoprocessorsIsMutable:()V
      11: aload_0
      12: getfield      #11                 // Field coprocessors_:Ljava/util/List;
      15: iload_1
      16: aload_2
      17: invokevirtual #153                // Method org/apache/hadoop/hbase/protobuf/generated/HBaseProtos$Coprocessor$Builder.build:()Lorg/apache/hadoop/hbase/protobuf/generated/HBaseProtos$Coprocessor;
      20: invokeinterface #129,  3          // InterfaceMethod java/util/List.set:(ILjava/lang/Object;)Ljava/lang/Object;
      25: pop
      26: aload_0
      27: invokevirtual #78                 // Method onChanged:()V
      30: goto          46
      33: aload_0
      34: getfield      #31                 // Field coprocessorsBuilder_:Lcom/google/protobuf/RepeatedFieldBuilder;
      37: iload_1
      38: aload_2
      39: invokevirtual #153                // Method org/apache/hadoop/hbase/protobuf/generated/HBaseProtos$Coprocessor$Builder.build:()Lorg/apache/hadoop/hbase/protobuf/generated/HBaseProtos$Coprocessor;
      42: invokevirtual #130                // Method com/google/protobuf/RepeatedFieldBuilder.setMessage:(ILcom/google/protobuf/GeneratedMessage;)Lcom/google/protobuf/RepeatedFieldBuilder;
      45: pop
      46: aload_0
      47: areturn

  public org.apache.hadoop.hbase.protobuf.generated.ClusterStatusProtos$ServerLoad$Builder addCoprocessors(org.apache.hadoop.hbase.protobuf.generated.HBaseProtos$Coprocessor);
    Code:
       0: aload_0
       1: getfield      #31                 // Field coprocessorsBuilder_:Lcom/google/protobuf/RepeatedFieldBuilder;
       4: ifnonnull     41
       7: aload_1
       8: ifnonnull     19
      11: new           #127                // class java/lang/NullPointerException
      14: dup
      15: invokespecial #128                // Method java/lang/NullPointerException."<init>":()V
      18: athrow
      19: aload_0
      20: invokespecial #84                 // Method ensureCoprocessorsIsMutable:()V
      23: aload_0
      24: getfield      #11                 // Field coprocessors_:Ljava/util/List;
      27: aload_1
      28: invokeinterface #132,  2          // InterfaceMethod java/util/List.add:(Ljava/lang/Object;)Z
      33: pop
      34: aload_0
      35: invokevirtual #78                 // Method onChanged:()V
      38: goto          50
      41: aload_0
      42: getfield      #31                 // Field coprocessorsBuilder_:Lcom/google/protobuf/RepeatedFieldBuilder;
      45: aload_1
      46: invokevirtual #133                // Method com/google/protobuf/RepeatedFieldBuilder.addMessage:(Lcom/google/protobuf/GeneratedMessage;)Lcom/google/protobuf/RepeatedFieldBuilder;
      49: pop
      50: aload_0
      51: areturn

  public org.apache.hadoop.hbase.protobuf.generated.ClusterStatusProtos$ServerLoad$Builder addCoprocessors(int, org.apache.hadoop.hbase.protobuf.generated.HBaseProtos$Coprocessor);
    Code:
       0: aload_0
       1: getfield      #31                 // Field coprocessorsBuilder_:Lcom/google/protobuf/RepeatedFieldBuilder;
       4: ifnonnull     41
       7: aload_2
       8: ifnonnull     19
      11: new           #127                // class java/lang/NullPointerException
      14: dup
      15: invokespecial #128                // Method java/lang/NullPointerException."<init>":()V
      18: athrow
      19: aload_0
      20: invokespecial #84                 // Method ensureCoprocessorsIsMutable:()V
      23: aload_0
      24: getfield      #11                 // Field coprocessors_:Ljava/util/List;
      27: iload_1
      28: aload_2
      29: invokeinterface #134,  3          // InterfaceMethod java/util/List.add:(ILjava/lang/Object;)V
      34: aload_0
      35: invokevirtual #78                 // Method onChanged:()V
      38: goto          51
      41: aload_0
      42: getfield      #31                 // Field coprocessorsBuilder_:Lcom/google/protobuf/RepeatedFieldBuilder;
      45: iload_1
      46: aload_2
      47: invokevirtual #135                // Method com/google/protobuf/RepeatedFieldBuilder.addMessage:(ILcom/google/protobuf/GeneratedMessage;)Lcom/google/protobuf/RepeatedFieldBuilder;
      50: pop
      51: aload_0
      52: areturn

  public org.apache.hadoop.hbase.protobuf.generated.ClusterStatusProtos$ServerLoad$Builder addCoprocessors(org.apache.hadoop.hbase.protobuf.generated.HBaseProtos$Coprocessor$Builder);
    Code:
       0: aload_0
       1: getfield      #31                 // Field coprocessorsBuilder_:Lcom/google/protobuf/RepeatedFieldBuilder;
       4: ifnonnull     32
       7: aload_0
       8: invokespecial #84                 // Method ensureCoprocessorsIsMutable:()V
      11: aload_0
      12: getfield      #11                 // Field coprocessors_:Ljava/util/List;
      15: aload_1
      16: invokevirtual #153                // Method org/apache/hadoop/hbase/protobuf/generated/HBaseProtos$Coprocessor$Builder.build:()Lorg/apache/hadoop/hbase/protobuf/generated/HBaseProtos$Coprocessor;
      19: invokeinterface #132,  2          // InterfaceMethod java/util/List.add:(Ljava/lang/Object;)Z
      24: pop
      25: aload_0
      26: invokevirtual #78                 // Method onChanged:()V
      29: goto          44
      32: aload_0
      33: getfield      #31                 // Field coprocessorsBuilder_:Lcom/google/protobuf/RepeatedFieldBuilder;
      36: aload_1
      37: invokevirtual #153                // Method org/apache/hadoop/hbase/protobuf/generated/HBaseProtos$Coprocessor$Builder.build:()Lorg/apache/hadoop/hbase/protobuf/generated/HBaseProtos$Coprocessor;
      40: invokevirtual #133                // Method com/google/protobuf/RepeatedFieldBuilder.addMessage:(Lcom/google/protobuf/GeneratedMessage;)Lcom/google/protobuf/RepeatedFieldBuilder;
      43: pop
      44: aload_0
      45: areturn

  public org.apache.hadoop.hbase.protobuf.generated.ClusterStatusProtos$ServerLoad$Builder addCoprocessors(int, org.apache.hadoop.hbase.protobuf.generated.HBaseProtos$Coprocessor$Builder);
    Code:
       0: aload_0
       1: getfield      #31                 // Field coprocessorsBuilder_:Lcom/google/protobuf/RepeatedFieldBuilder;
       4: ifnonnull     32
       7: aload_0
       8: invokespecial #84                 // Method ensureCoprocessorsIsMutable:()V
      11: aload_0
      12: getfield      #11                 // Field coprocessors_:Ljava/util/List;
      15: iload_1
      16: aload_2
      17: invokevirtual #153                // Method org/apache/hadoop/hbase/protobuf/generated/HBaseProtos$Coprocessor$Builder.build:()Lorg/apache/hadoop/hbase/protobuf/generated/HBaseProtos$Coprocessor;
      20: invokeinterface #134,  3          // InterfaceMethod java/util/List.add:(ILjava/lang/Object;)V
      25: aload_0
      26: invokevirtual #78                 // Method onChanged:()V
      29: goto          45
      32: aload_0
      33: getfield      #31                 // Field coprocessorsBuilder_:Lcom/google/protobuf/RepeatedFieldBuilder;
      36: iload_1
      37: aload_2
      38: invokevirtual #153                // Method org/apache/hadoop/hbase/protobuf/generated/HBaseProtos$Coprocessor$Builder.build:()Lorg/apache/hadoop/hbase/protobuf/generated/HBaseProtos$Coprocessor;
      41: invokevirtual #135                // Method com/google/protobuf/RepeatedFieldBuilder.addMessage:(ILcom/google/protobuf/GeneratedMessage;)Lcom/google/protobuf/RepeatedFieldBuilder;
      44: pop
      45: aload_0
      46: areturn

  public org.apache.hadoop.hbase.protobuf.generated.ClusterStatusProtos$ServerLoad$Builder addAllCoprocessors(java.lang.Iterable<? extends org.apache.hadoop.hbase.protobuf.generated.HBaseProtos$Coprocessor>);
    Code:
       0: aload_0
       1: getfield      #31                 // Field coprocessorsBuilder_:Lcom/google/protobuf/RepeatedFieldBuilder;
       4: ifnonnull     26
       7: aload_0
       8: invokespecial #84                 // Method ensureCoprocessorsIsMutable:()V
      11: aload_1
      12: aload_0
      13: getfield      #11                 // Field coprocessors_:Ljava/util/List;
      16: invokestatic  #136                // Method com/google/protobuf/GeneratedMessage$Builder.addAll:(Ljava/lang/Iterable;Ljava/util/Collection;)V
      19: aload_0
      20: invokevirtual #78                 // Method onChanged:()V
      23: goto          35
      26: aload_0
      27: getfield      #31                 // Field coprocessorsBuilder_:Lcom/google/protobuf/RepeatedFieldBuilder;
      30: aload_1
      31: invokevirtual #82                 // Method com/google/protobuf/RepeatedFieldBuilder.addAllMessages:(Ljava/lang/Iterable;)Lcom/google/protobuf/RepeatedFieldBuilder;
      34: pop
      35: aload_0
      36: areturn

  public org.apache.hadoop.hbase.protobuf.generated.ClusterStatusProtos$ServerLoad$Builder clearCoprocessors();
    Code:
       0: aload_0
       1: getfield      #31                 // Field coprocessorsBuilder_:Lcom/google/protobuf/RepeatedFieldBuilder;
       4: ifnonnull     32
       7: aload_0
       8: invokestatic  #9                  // Method java/util/Collections.emptyList:()Ljava/util/List;
      11: putfield      #11                 // Field coprocessors_:Ljava/util/List;
      14: aload_0
      15: aload_0
      16: getfield      #25                 // Field bitField0_:I
      19: bipush        -33
      21: iand
      22: putfield      #25                 // Field bitField0_:I
      25: aload_0
      26: invokevirtual #78                 // Method onChanged:()V
      29: goto          39
      32: aload_0
      33: getfield      #31                 // Field coprocessorsBuilder_:Lcom/google/protobuf/RepeatedFieldBuilder;
      36: invokevirtual #30                 // Method com/google/protobuf/RepeatedFieldBuilder.clear:()V
      39: aload_0
      40: areturn

  public org.apache.hadoop.hbase.protobuf.generated.ClusterStatusProtos$ServerLoad$Builder removeCoprocessors(int);
    Code:
       0: aload_0
       1: getfield      #31                 // Field coprocessorsBuilder_:Lcom/google/protobuf/RepeatedFieldBuilder;
       4: ifnonnull     29
       7: aload_0
       8: invokespecial #84                 // Method ensureCoprocessorsIsMutable:()V
      11: aload_0
      12: getfield      #11                 // Field coprocessors_:Ljava/util/List;
      15: iload_1
      16: invokeinterface #137,  2          // InterfaceMethod java/util/List.remove:(I)Ljava/lang/Object;
      21: pop
      22: aload_0
      23: invokevirtual #78                 // Method onChanged:()V
      26: goto          37
      29: aload_0
      30: getfield      #31                 // Field coprocessorsBuilder_:Lcom/google/protobuf/RepeatedFieldBuilder;
      33: iload_1
      34: invokevirtual #138                // Method com/google/protobuf/RepeatedFieldBuilder.remove:(I)V
      37: aload_0
      38: areturn

  public org.apache.hadoop.hbase.protobuf.generated.HBaseProtos$Coprocessor$Builder getCoprocessorsBuilder(int);
    Code:
       0: aload_0
       1: invokespecial #19                 // Method getCoprocessorsFieldBuilder:()Lcom/google/protobuf/RepeatedFieldBuilder;
       4: iload_1
       5: invokevirtual #139                // Method com/google/protobuf/RepeatedFieldBuilder.getBuilder:(I)Lcom/google/protobuf/GeneratedMessage$Builder;
       8: checkcast     #154                // class org/apache/hadoop/hbase/protobuf/generated/HBaseProtos$Coprocessor$Builder
      11: areturn

  public org.apache.hadoop.hbase.protobuf.generated.HBaseProtos$CoprocessorOrBuilder getCoprocessorsOrBuilder(int);
    Code:
       0: aload_0
       1: getfield      #31                 // Field coprocessorsBuilder_:Lcom/google/protobuf/RepeatedFieldBuilder;
       4: ifnonnull     21
       7: aload_0
       8: getfield      #11                 // Field coprocessors_:Ljava/util/List;
      11: iload_1
      12: invokeinterface #124,  2          // InterfaceMethod java/util/List.get:(I)Ljava/lang/Object;
      17: checkcast     #155                // class org/apache/hadoop/hbase/protobuf/generated/HBaseProtos$CoprocessorOrBuilder
      20: areturn
      21: aload_0
      22: getfield      #31                 // Field coprocessorsBuilder_:Lcom/google/protobuf/RepeatedFieldBuilder;
      25: iload_1
      26: invokevirtual #142                // Method com/google/protobuf/RepeatedFieldBuilder.getMessageOrBuilder:(I)Lcom/google/protobuf/MessageOrBuilder;
      29: checkcast     #155                // class org/apache/hadoop/hbase/protobuf/generated/HBaseProtos$CoprocessorOrBuilder
      32: areturn

  public java.util.List<? extends org.apache.hadoop.hbase.protobuf.generated.HBaseProtos$CoprocessorOrBuilder> getCoprocessorsOrBuilderList();
    Code:
       0: aload_0
       1: getfield      #31                 // Field coprocessorsBuilder_:Lcom/google/protobuf/RepeatedFieldBuilder;
       4: ifnull        15
       7: aload_0
       8: getfield      #31                 // Field coprocessorsBuilder_:Lcom/google/protobuf/RepeatedFieldBuilder;
      11: invokevirtual #143                // Method com/google/protobuf/RepeatedFieldBuilder.getMessageOrBuilderList:()Ljava/util/List;
      14: areturn
      15: aload_0
      16: getfield      #11                 // Field coprocessors_:Ljava/util/List;
      19: invokestatic  #48                 // Method java/util/Collections.unmodifiableList:(Ljava/util/List;)Ljava/util/List;
      22: areturn

  public org.apache.hadoop.hbase.protobuf.generated.HBaseProtos$Coprocessor$Builder addCoprocessorsBuilder();
    Code:
       0: aload_0
       1: invokespecial #19                 // Method getCoprocessorsFieldBuilder:()Lcom/google/protobuf/RepeatedFieldBuilder;
       4: invokestatic  #156                // Method org/apache/hadoop/hbase/protobuf/generated/HBaseProtos$Coprocessor.getDefaultInstance:()Lorg/apache/hadoop/hbase/protobuf/generated/HBaseProtos$Coprocessor;
       7: invokevirtual #145                // Method com/google/protobuf/RepeatedFieldBuilder.addBuilder:(Lcom/google/protobuf/GeneratedMessage;)Lcom/google/protobuf/GeneratedMessage$Builder;
      10: checkcast     #154                // class org/apache/hadoop/hbase/protobuf/generated/HBaseProtos$Coprocessor$Builder
      13: areturn

  public org.apache.hadoop.hbase.protobuf.generated.HBaseProtos$Coprocessor$Builder addCoprocessorsBuilder(int);
    Code:
       0: aload_0
       1: invokespecial #19                 // Method getCoprocessorsFieldBuilder:()Lcom/google/protobuf/RepeatedFieldBuilder;
       4: iload_1
       5: invokestatic  #156                // Method org/apache/hadoop/hbase/protobuf/generated/HBaseProtos$Coprocessor.getDefaultInstance:()Lorg/apache/hadoop/hbase/protobuf/generated/HBaseProtos$Coprocessor;
       8: invokevirtual #146                // Method com/google/protobuf/RepeatedFieldBuilder.addBuilder:(ILcom/google/protobuf/GeneratedMessage;)Lcom/google/protobuf/GeneratedMessage$Builder;
      11: checkcast     #154                // class org/apache/hadoop/hbase/protobuf/generated/HBaseProtos$Coprocessor$Builder
      14: areturn

  public java.util.List<org.apache.hadoop.hbase.protobuf.generated.HBaseProtos$Coprocessor$Builder> getCoprocessorsBuilderList();
    Code:
       0: aload_0
       1: invokespecial #19                 // Method getCoprocessorsFieldBuilder:()Lcom/google/protobuf/RepeatedFieldBuilder;
       4: invokevirtual #147                // Method com/google/protobuf/RepeatedFieldBuilder.getBuilderList:()Ljava/util/List;
       7: areturn

  public boolean hasReportStartTime();
    Code:
       0: aload_0
       1: getfield      #25                 // Field bitField0_:I
       4: bipush        64
       6: iand
       7: bipush        64
       9: if_icmpne     16
      12: iconst_1
      13: goto          17
      16: iconst_0
      17: ireturn

  public long getReportStartTime();
    Code:
       0: aload_0
       1: getfield      #32                 // Field reportStartTime_:J
       4: lreturn

  public org.apache.hadoop.hbase.protobuf.generated.ClusterStatusProtos$ServerLoad$Builder setReportStartTime(long);
    Code:
       0: aload_0
       1: dup
       2: getfield      #25                 // Field bitField0_:I
       5: bipush        64
       7: ior
       8: putfield      #25                 // Field bitField0_:I
      11: aload_0
      12: lload_1
      13: putfield      #32                 // Field reportStartTime_:J
      16: aload_0
      17: invokevirtual #78                 // Method onChanged:()V
      20: aload_0
      21: areturn

  public org.apache.hadoop.hbase.protobuf.generated.ClusterStatusProtos$ServerLoad$Builder clearReportStartTime();
    Code:
       0: aload_0
       1: aload_0
       2: getfield      #25                 // Field bitField0_:I
       5: bipush        -65
       7: iand
       8: putfield      #25                 // Field bitField0_:I
      11: aload_0
      12: lconst_0
      13: putfield      #32                 // Field reportStartTime_:J
      16: aload_0
      17: invokevirtual #78                 // Method onChanged:()V
      20: aload_0
      21: areturn

  public boolean hasReportEndTime();
    Code:
       0: aload_0
       1: getfield      #25                 // Field bitField0_:I
       4: sipush        128
       7: iand
       8: sipush        128
      11: if_icmpne     18
      14: iconst_1
      15: goto          19
      18: iconst_0
      19: ireturn

  public long getReportEndTime();
    Code:
       0: aload_0
       1: getfield      #33                 // Field reportEndTime_:J
       4: lreturn

  public org.apache.hadoop.hbase.protobuf.generated.ClusterStatusProtos$ServerLoad$Builder setReportEndTime(long);
    Code:
       0: aload_0
       1: dup
       2: getfield      #25                 // Field bitField0_:I
       5: sipush        128
       8: ior
       9: putfield      #25                 // Field bitField0_:I
      12: aload_0
      13: lload_1
      14: putfield      #33                 // Field reportEndTime_:J
      17: aload_0
      18: invokevirtual #78                 // Method onChanged:()V
      21: aload_0
      22: areturn

  public org.apache.hadoop.hbase.protobuf.generated.ClusterStatusProtos$ServerLoad$Builder clearReportEndTime();
    Code:
       0: aload_0
       1: aload_0
       2: getfield      #25                 // Field bitField0_:I
       5: sipush        -129
       8: iand
       9: putfield      #25                 // Field bitField0_:I
      12: aload_0
      13: lconst_0
      14: putfield      #33                 // Field reportEndTime_:J
      17: aload_0
      18: invokevirtual #78                 // Method onChanged:()V
      21: aload_0
      22: areturn

  public boolean hasInfoServerPort();
    Code:
       0: aload_0
       1: getfield      #25                 // Field bitField0_:I
       4: sipush        256
       7: iand
       8: sipush        256
      11: if_icmpne     18
      14: iconst_1
      15: goto          19
      18: iconst_0
      19: ireturn

  public int getInfoServerPort();
    Code:
       0: aload_0
       1: getfield      #34                 // Field infoServerPort_:I
       4: ireturn

  public org.apache.hadoop.hbase.protobuf.generated.ClusterStatusProtos$ServerLoad$Builder setInfoServerPort(int);
    Code:
       0: aload_0
       1: dup
       2: getfield      #25                 // Field bitField0_:I
       5: sipush        256
       8: ior
       9: putfield      #25                 // Field bitField0_:I
      12: aload_0
      13: iload_1
      14: putfield      #34                 // Field infoServerPort_:I
      17: aload_0
      18: invokevirtual #78                 // Method onChanged:()V
      21: aload_0
      22: areturn

  public org.apache.hadoop.hbase.protobuf.generated.ClusterStatusProtos$ServerLoad$Builder clearInfoServerPort();
    Code:
       0: aload_0
       1: aload_0
       2: getfield      #25                 // Field bitField0_:I
       5: sipush        -257
       8: iand
       9: putfield      #25                 // Field bitField0_:I
      12: aload_0
      13: iconst_0
      14: putfield      #34                 // Field infoServerPort_:I
      17: aload_0
      18: invokevirtual #78                 // Method onChanged:()V
      21: aload_0
      22: areturn

  public java.util.List<org.apache.hadoop.hbase.protobuf.generated.ClusterStatusProtos$ReplicationLoadSource> getReplLoadSourceList();
    Code:
       0: aload_0
       1: getfield      #35                 // Field replLoadSourceBuilder_:Lcom/google/protobuf/RepeatedFieldBuilder;
       4: ifnonnull     15
       7: aload_0
       8: getfield      #12                 // Field replLoadSource_:Ljava/util/List;
      11: invokestatic  #48                 // Method java/util/Collections.unmodifiableList:(Ljava/util/List;)Ljava/util/List;
      14: areturn
      15: aload_0
      16: getfield      #35                 // Field replLoadSourceBuilder_:Lcom/google/protobuf/RepeatedFieldBuilder;
      19: invokevirtual #121                // Method com/google/protobuf/RepeatedFieldBuilder.getMessageList:()Ljava/util/List;
      22: areturn

  public int getReplLoadSourceCount();
    Code:
       0: aload_0
       1: getfield      #35                 // Field replLoadSourceBuilder_:Lcom/google/protobuf/RepeatedFieldBuilder;
       4: ifnonnull     17
       7: aload_0
       8: getfield      #12                 // Field replLoadSource_:Ljava/util/List;
      11: invokeinterface #122,  1          // InterfaceMethod java/util/List.size:()I
      16: ireturn
      17: aload_0
      18: getfield      #35                 // Field replLoadSourceBuilder_:Lcom/google/protobuf/RepeatedFieldBuilder;
      21: invokevirtual #123                // Method com/google/protobuf/RepeatedFieldBuilder.getCount:()I
      24: ireturn

  public org.apache.hadoop.hbase.protobuf.generated.ClusterStatusProtos$ReplicationLoadSource getReplLoadSource(int);
    Code:
       0: aload_0
       1: getfield      #35                 // Field replLoadSourceBuilder_:Lcom/google/protobuf/RepeatedFieldBuilder;
       4: ifnonnull     21
       7: aload_0
       8: getfield      #12                 // Field replLoadSource_:Ljava/util/List;
      11: iload_1
      12: invokeinterface #124,  2          // InterfaceMethod java/util/List.get:(I)Ljava/lang/Object;
      17: checkcast     #157                // class org/apache/hadoop/hbase/protobuf/generated/ClusterStatusProtos$ReplicationLoadSource
      20: areturn
      21: aload_0
      22: getfield      #35                 // Field replLoadSourceBuilder_:Lcom/google/protobuf/RepeatedFieldBuilder;
      25: iload_1
      26: invokevirtual #126                // Method com/google/protobuf/RepeatedFieldBuilder.getMessage:(I)Lcom/google/protobuf/GeneratedMessage;
      29: checkcast     #157                // class org/apache/hadoop/hbase/protobuf/generated/ClusterStatusProtos$ReplicationLoadSource
      32: areturn

  public org.apache.hadoop.hbase.protobuf.generated.ClusterStatusProtos$ServerLoad$Builder setReplLoadSource(int, org.apache.hadoop.hbase.protobuf.generated.ClusterStatusProtos$ReplicationLoadSource);
    Code:
       0: aload_0
       1: getfield      #35                 // Field replLoadSourceBuilder_:Lcom/google/protobuf/RepeatedFieldBuilder;
       4: ifnonnull     42
       7: aload_2
       8: ifnonnull     19
      11: new           #127                // class java/lang/NullPointerException
      14: dup
      15: invokespecial #128                // Method java/lang/NullPointerException."<init>":()V
      18: athrow
      19: aload_0
      20: invokespecial #96                 // Method ensureReplLoadSourceIsMutable:()V
      23: aload_0
      24: getfield      #12                 // Field replLoadSource_:Ljava/util/List;
      27: iload_1
      28: aload_2
      29: invokeinterface #129,  3          // InterfaceMethod java/util/List.set:(ILjava/lang/Object;)Ljava/lang/Object;
      34: pop
      35: aload_0
      36: invokevirtual #78                 // Method onChanged:()V
      39: goto          52
      42: aload_0
      43: getfield      #35                 // Field replLoadSourceBuilder_:Lcom/google/protobuf/RepeatedFieldBuilder;
      46: iload_1
      47: aload_2
      48: invokevirtual #130                // Method com/google/protobuf/RepeatedFieldBuilder.setMessage:(ILcom/google/protobuf/GeneratedMessage;)Lcom/google/protobuf/RepeatedFieldBuilder;
      51: pop
      52: aload_0
      53: areturn

  public org.apache.hadoop.hbase.protobuf.generated.ClusterStatusProtos$ServerLoad$Builder setReplLoadSource(int, org.apache.hadoop.hbase.protobuf.generated.ClusterStatusProtos$ReplicationLoadSource$Builder);
    Code:
       0: aload_0
       1: getfield      #35                 // Field replLoadSourceBuilder_:Lcom/google/protobuf/RepeatedFieldBuilder;
       4: ifnonnull     33
       7: aload_0
       8: invokespecial #96                 // Method ensureReplLoadSourceIsMutable:()V
      11: aload_0
      12: getfield      #12                 // Field replLoadSource_:Ljava/util/List;
      15: iload_1
      16: aload_2
      17: invokevirtual #158                // Method org/apache/hadoop/hbase/protobuf/generated/ClusterStatusProtos$ReplicationLoadSource$Builder.build:()Lorg/apache/hadoop/hbase/protobuf/generated/ClusterStatusProtos$ReplicationLoadSource;
      20: invokeinterface #129,  3          // InterfaceMethod java/util/List.set:(ILjava/lang/Object;)Ljava/lang/Object;
      25: pop
      26: aload_0
      27: invokevirtual #78                 // Method onChanged:()V
      30: goto          46
      33: aload_0
      34: getfield      #35                 // Field replLoadSourceBuilder_:Lcom/google/protobuf/RepeatedFieldBuilder;
      37: iload_1
      38: aload_2
      39: invokevirtual #158                // Method org/apache/hadoop/hbase/protobuf/generated/ClusterStatusProtos$ReplicationLoadSource$Builder.build:()Lorg/apache/hadoop/hbase/protobuf/generated/ClusterStatusProtos$ReplicationLoadSource;
      42: invokevirtual #130                // Method com/google/protobuf/RepeatedFieldBuilder.setMessage:(ILcom/google/protobuf/GeneratedMessage;)Lcom/google/protobuf/RepeatedFieldBuilder;
      45: pop
      46: aload_0
      47: areturn

  public org.apache.hadoop.hbase.protobuf.generated.ClusterStatusProtos$ServerLoad$Builder addReplLoadSource(org.apache.hadoop.hbase.protobuf.generated.ClusterStatusProtos$ReplicationLoadSource);
    Code:
       0: aload_0
       1: getfield      #35                 // Field replLoadSourceBuilder_:Lcom/google/protobuf/RepeatedFieldBuilder;
       4: ifnonnull     41
       7: aload_1
       8: ifnonnull     19
      11: new           #127                // class java/lang/NullPointerException
      14: dup
      15: invokespecial #128                // Method java/lang/NullPointerException."<init>":()V
      18: athrow
      19: aload_0
      20: invokespecial #96                 // Method ensureReplLoadSourceIsMutable:()V
      23: aload_0
      24: getfield      #12                 // Field replLoadSource_:Ljava/util/List;
      27: aload_1
      28: invokeinterface #132,  2          // InterfaceMethod java/util/List.add:(Ljava/lang/Object;)Z
      33: pop
      34: aload_0
      35: invokevirtual #78                 // Method onChanged:()V
      38: goto          50
      41: aload_0
      42: getfield      #35                 // Field replLoadSourceBuilder_:Lcom/google/protobuf/RepeatedFieldBuilder;
      45: aload_1
      46: invokevirtual #133                // Method com/google/protobuf/RepeatedFieldBuilder.addMessage:(Lcom/google/protobuf/GeneratedMessage;)Lcom/google/protobuf/RepeatedFieldBuilder;
      49: pop
      50: aload_0
      51: areturn

  public org.apache.hadoop.hbase.protobuf.generated.ClusterStatusProtos$ServerLoad$Builder addReplLoadSource(int, org.apache.hadoop.hbase.protobuf.generated.ClusterStatusProtos$ReplicationLoadSource);
    Code:
       0: aload_0
       1: getfield      #35                 // Field replLoadSourceBuilder_:Lcom/google/protobuf/RepeatedFieldBuilder;
       4: ifnonnull     41
       7: aload_2
       8: ifnonnull     19
      11: new           #127                // class java/lang/NullPointerException
      14: dup
      15: invokespecial #128                // Method java/lang/NullPointerException."<init>":()V
      18: athrow
      19: aload_0
      20: invokespecial #96                 // Method ensureReplLoadSourceIsMutable:()V
      23: aload_0
      24: getfield      #12                 // Field replLoadSource_:Ljava/util/List;
      27: iload_1
      28: aload_2
      29: invokeinterface #134,  3          // InterfaceMethod java/util/List.add:(ILjava/lang/Object;)V
      34: aload_0
      35: invokevirtual #78                 // Method onChanged:()V
      38: goto          51
      41: aload_0
      42: getfield      #35                 // Field replLoadSourceBuilder_:Lcom/google/protobuf/RepeatedFieldBuilder;
      45: iload_1
      46: aload_2
      47: invokevirtual #135                // Method com/google/protobuf/RepeatedFieldBuilder.addMessage:(ILcom/google/protobuf/GeneratedMessage;)Lcom/google/protobuf/RepeatedFieldBuilder;
      50: pop
      51: aload_0
      52: areturn

  public org.apache.hadoop.hbase.protobuf.generated.ClusterStatusProtos$ServerLoad$Builder addReplLoadSource(org.apache.hadoop.hbase.protobuf.generated.ClusterStatusProtos$ReplicationLoadSource$Builder);
    Code:
       0: aload_0
       1: getfield      #35                 // Field replLoadSourceBuilder_:Lcom/google/protobuf/RepeatedFieldBuilder;
       4: ifnonnull     32
       7: aload_0
       8: invokespecial #96                 // Method ensureReplLoadSourceIsMutable:()V
      11: aload_0
      12: getfield      #12                 // Field replLoadSource_:Ljava/util/List;
      15: aload_1
      16: invokevirtual #158                // Method org/apache/hadoop/hbase/protobuf/generated/ClusterStatusProtos$ReplicationLoadSource$Builder.build:()Lorg/apache/hadoop/hbase/protobuf/generated/ClusterStatusProtos$ReplicationLoadSource;
      19: invokeinterface #132,  2          // InterfaceMethod java/util/List.add:(Ljava/lang/Object;)Z
      24: pop
      25: aload_0
      26: invokevirtual #78                 // Method onChanged:()V
      29: goto          44
      32: aload_0
      33: getfield      #35                 // Field replLoadSourceBuilder_:Lcom/google/protobuf/RepeatedFieldBuilder;
      36: aload_1
      37: invokevirtual #158                // Method org/apache/hadoop/hbase/protobuf/generated/ClusterStatusProtos$ReplicationLoadSource$Builder.build:()Lorg/apache/hadoop/hbase/protobuf/generated/ClusterStatusProtos$ReplicationLoadSource;
      40: invokevirtual #133                // Method com/google/protobuf/RepeatedFieldBuilder.addMessage:(Lcom/google/protobuf/GeneratedMessage;)Lcom/google/protobuf/RepeatedFieldBuilder;
      43: pop
      44: aload_0
      45: areturn

  public org.apache.hadoop.hbase.protobuf.generated.ClusterStatusProtos$ServerLoad$Builder addReplLoadSource(int, org.apache.hadoop.hbase.protobuf.generated.ClusterStatusProtos$ReplicationLoadSource$Builder);
    Code:
       0: aload_0
       1: getfield      #35                 // Field replLoadSourceBuilder_:Lcom/google/protobuf/RepeatedFieldBuilder;
       4: ifnonnull     32
       7: aload_0
       8: invokespecial #96                 // Method ensureReplLoadSourceIsMutable:()V
      11: aload_0
      12: getfield      #12                 // Field replLoadSource_:Ljava/util/List;
      15: iload_1
      16: aload_2
      17: invokevirtual #158                // Method org/apache/hadoop/hbase/protobuf/generated/ClusterStatusProtos$ReplicationLoadSource$Builder.build:()Lorg/apache/hadoop/hbase/protobuf/generated/ClusterStatusProtos$ReplicationLoadSource;
      20: invokeinterface #134,  3          // InterfaceMethod java/util/List.add:(ILjava/lang/Object;)V
      25: aload_0
      26: invokevirtual #78                 // Method onChanged:()V
      29: goto          45
      32: aload_0
      33: getfield      #35                 // Field replLoadSourceBuilder_:Lcom/google/protobuf/RepeatedFieldBuilder;
      36: iload_1
      37: aload_2
      38: invokevirtual #158                // Method org/apache/hadoop/hbase/protobuf/generated/ClusterStatusProtos$ReplicationLoadSource$Builder.build:()Lorg/apache/hadoop/hbase/protobuf/generated/ClusterStatusProtos$ReplicationLoadSource;
      41: invokevirtual #135                // Method com/google/protobuf/RepeatedFieldBuilder.addMessage:(ILcom/google/protobuf/GeneratedMessage;)Lcom/google/protobuf/RepeatedFieldBuilder;
      44: pop
      45: aload_0
      46: areturn

  public org.apache.hadoop.hbase.protobuf.generated.ClusterStatusProtos$ServerLoad$Builder addAllReplLoadSource(java.lang.Iterable<? extends org.apache.hadoop.hbase.protobuf.generated.ClusterStatusProtos$ReplicationLoadSource>);
    Code:
       0: aload_0
       1: getfield      #35                 // Field replLoadSourceBuilder_:Lcom/google/protobuf/RepeatedFieldBuilder;
       4: ifnonnull     26
       7: aload_0
       8: invokespecial #96                 // Method ensureReplLoadSourceIsMutable:()V
      11: aload_1
      12: aload_0
      13: getfield      #12                 // Field replLoadSource_:Ljava/util/List;
      16: invokestatic  #136                // Method com/google/protobuf/GeneratedMessage$Builder.addAll:(Ljava/lang/Iterable;Ljava/util/Collection;)V
      19: aload_0
      20: invokevirtual #78                 // Method onChanged:()V
      23: goto          35
      26: aload_0
      27: getfield      #35                 // Field replLoadSourceBuilder_:Lcom/google/protobuf/RepeatedFieldBuilder;
      30: aload_1
      31: invokevirtual #82                 // Method com/google/protobuf/RepeatedFieldBuilder.addAllMessages:(Ljava/lang/Iterable;)Lcom/google/protobuf/RepeatedFieldBuilder;
      34: pop
      35: aload_0
      36: areturn

  public org.apache.hadoop.hbase.protobuf.generated.ClusterStatusProtos$ServerLoad$Builder clearReplLoadSource();
    Code:
       0: aload_0
       1: getfield      #35                 // Field replLoadSourceBuilder_:Lcom/google/protobuf/RepeatedFieldBuilder;
       4: ifnonnull     33
       7: aload_0
       8: invokestatic  #9                  // Method java/util/Collections.emptyList:()Ljava/util/List;
      11: putfield      #12                 // Field replLoadSource_:Ljava/util/List;
      14: aload_0
      15: aload_0
      16: getfield      #25                 // Field bitField0_:I
      19: sipush        -513
      22: iand
      23: putfield      #25                 // Field bitField0_:I
      26: aload_0
      27: invokevirtual #78                 // Method onChanged:()V
      30: goto          40
      33: aload_0
      34: getfield      #35                 // Field replLoadSourceBuilder_:Lcom/google/protobuf/RepeatedFieldBuilder;
      37: invokevirtual #30                 // Method com/google/protobuf/RepeatedFieldBuilder.clear:()V
      40: aload_0
      41: areturn

  public org.apache.hadoop.hbase.protobuf.generated.ClusterStatusProtos$ServerLoad$Builder removeReplLoadSource(int);
    Code:
       0: aload_0
       1: getfield      #35                 // Field replLoadSourceBuilder_:Lcom/google/protobuf/RepeatedFieldBuilder;
       4: ifnonnull     29
       7: aload_0
       8: invokespecial #96                 // Method ensureReplLoadSourceIsMutable:()V
      11: aload_0
      12: getfield      #12                 // Field replLoadSource_:Ljava/util/List;
      15: iload_1
      16: invokeinterface #137,  2          // InterfaceMethod java/util/List.remove:(I)Ljava/lang/Object;
      21: pop
      22: aload_0
      23: invokevirtual #78                 // Method onChanged:()V
      26: goto          37
      29: aload_0
      30: getfield      #35                 // Field replLoadSourceBuilder_:Lcom/google/protobuf/RepeatedFieldBuilder;
      33: iload_1
      34: invokevirtual #138                // Method com/google/protobuf/RepeatedFieldBuilder.remove:(I)V
      37: aload_0
      38: areturn

  public org.apache.hadoop.hbase.protobuf.generated.ClusterStatusProtos$ReplicationLoadSource$Builder getReplLoadSourceBuilder(int);
    Code:
       0: aload_0
       1: invokespecial #20                 // Method getReplLoadSourceFieldBuilder:()Lcom/google/protobuf/RepeatedFieldBuilder;
       4: iload_1
       5: invokevirtual #139                // Method com/google/protobuf/RepeatedFieldBuilder.getBuilder:(I)Lcom/google/protobuf/GeneratedMessage$Builder;
       8: checkcast     #159                // class org/apache/hadoop/hbase/protobuf/generated/ClusterStatusProtos$ReplicationLoadSource$Builder
      11: areturn

  public org.apache.hadoop.hbase.protobuf.generated.ClusterStatusProtos$ReplicationLoadSourceOrBuilder getReplLoadSourceOrBuilder(int);
    Code:
       0: aload_0
       1: getfield      #35                 // Field replLoadSourceBuilder_:Lcom/google/protobuf/RepeatedFieldBuilder;
       4: ifnonnull     21
       7: aload_0
       8: getfield      #12                 // Field replLoadSource_:Ljava/util/List;
      11: iload_1
      12: invokeinterface #124,  2          // InterfaceMethod java/util/List.get:(I)Ljava/lang/Object;
      17: checkcast     #160                // class org/apache/hadoop/hbase/protobuf/generated/ClusterStatusProtos$ReplicationLoadSourceOrBuilder
      20: areturn
      21: aload_0
      22: getfield      #35                 // Field replLoadSourceBuilder_:Lcom/google/protobuf/RepeatedFieldBuilder;
      25: iload_1
      26: invokevirtual #142                // Method com/google/protobuf/RepeatedFieldBuilder.getMessageOrBuilder:(I)Lcom/google/protobuf/MessageOrBuilder;
      29: checkcast     #160                // class org/apache/hadoop/hbase/protobuf/generated/ClusterStatusProtos$ReplicationLoadSourceOrBuilder
      32: areturn

  public java.util.List<? extends org.apache.hadoop.hbase.protobuf.generated.ClusterStatusProtos$ReplicationLoadSourceOrBuilder> getReplLoadSourceOrBuilderList();
    Code:
       0: aload_0
       1: getfield      #35                 // Field replLoadSourceBuilder_:Lcom/google/protobuf/RepeatedFieldBuilder;
       4: ifnull        15
       7: aload_0
       8: getfield      #35                 // Field replLoadSourceBuilder_:Lcom/google/protobuf/RepeatedFieldBuilder;
      11: invokevirtual #143                // Method com/google/protobuf/RepeatedFieldBuilder.getMessageOrBuilderList:()Ljava/util/List;
      14: areturn
      15: aload_0
      16: getfield      #12                 // Field replLoadSource_:Ljava/util/List;
      19: invokestatic  #48                 // Method java/util/Collections.unmodifiableList:(Ljava/util/List;)Ljava/util/List;
      22: areturn

  public org.apache.hadoop.hbase.protobuf.generated.ClusterStatusProtos$ReplicationLoadSource$Builder addReplLoadSourceBuilder();
    Code:
       0: aload_0
       1: invokespecial #20                 // Method getReplLoadSourceFieldBuilder:()Lcom/google/protobuf/RepeatedFieldBuilder;
       4: invokestatic  #161                // Method org/apache/hadoop/hbase/protobuf/generated/ClusterStatusProtos$ReplicationLoadSource.getDefaultInstance:()Lorg/apache/hadoop/hbase/protobuf/generated/ClusterStatusProtos$ReplicationLoadSource;
       7: invokevirtual #145                // Method com/google/protobuf/RepeatedFieldBuilder.addBuilder:(Lcom/google/protobuf/GeneratedMessage;)Lcom/google/protobuf/GeneratedMessage$Builder;
      10: checkcast     #159                // class org/apache/hadoop/hbase/protobuf/generated/ClusterStatusProtos$ReplicationLoadSource$Builder
      13: areturn

  public org.apache.hadoop.hbase.protobuf.generated.ClusterStatusProtos$ReplicationLoadSource$Builder addReplLoadSourceBuilder(int);
    Code:
       0: aload_0
       1: invokespecial #20                 // Method getReplLoadSourceFieldBuilder:()Lcom/google/protobuf/RepeatedFieldBuilder;
       4: iload_1
       5: invokestatic  #161                // Method org/apache/hadoop/hbase/protobuf/generated/ClusterStatusProtos$ReplicationLoadSource.getDefaultInstance:()Lorg/apache/hadoop/hbase/protobuf/generated/ClusterStatusProtos$ReplicationLoadSource;
       8: invokevirtual #146                // Method com/google/protobuf/RepeatedFieldBuilder.addBuilder:(ILcom/google/protobuf/GeneratedMessage;)Lcom/google/protobuf/GeneratedMessage$Builder;
      11: checkcast     #159                // class org/apache/hadoop/hbase/protobuf/generated/ClusterStatusProtos$ReplicationLoadSource$Builder
      14: areturn

  public java.util.List<org.apache.hadoop.hbase.protobuf.generated.ClusterStatusProtos$ReplicationLoadSource$Builder> getReplLoadSourceBuilderList();
    Code:
       0: aload_0
       1: invokespecial #20                 // Method getReplLoadSourceFieldBuilder:()Lcom/google/protobuf/RepeatedFieldBuilder;
       4: invokevirtual #147                // Method com/google/protobuf/RepeatedFieldBuilder.getBuilderList:()Ljava/util/List;
       7: areturn

  public boolean hasReplLoadSink();
    Code:
       0: aload_0
       1: getfield      #25                 // Field bitField0_:I
       4: sipush        1024
       7: iand
       8: sipush        1024
      11: if_icmpne     18
      14: iconst_1
      15: goto          19
      18: iconst_0
      19: ireturn

  public org.apache.hadoop.hbase.protobuf.generated.ClusterStatusProtos$ReplicationLoadSink getReplLoadSink();
    Code:
       0: aload_0
       1: getfield      #36                 // Field replLoadSinkBuilder_:Lcom/google/protobuf/SingleFieldBuilder;
       4: ifnonnull     12
       7: aload_0
       8: getfield      #14                 // Field replLoadSink_:Lorg/apache/hadoop/hbase/protobuf/generated/ClusterStatusProtos$ReplicationLoadSink;
      11: areturn
      12: aload_0
      13: getfield      #36                 // Field replLoadSinkBuilder_:Lcom/google/protobuf/SingleFieldBuilder;
      16: invokevirtual #162                // Method com/google/protobuf/SingleFieldBuilder.getMessage:()Lcom/google/protobuf/GeneratedMessage;
      19: checkcast     #58                 // class org/apache/hadoop/hbase/protobuf/generated/ClusterStatusProtos$ReplicationLoadSink
      22: areturn

  public org.apache.hadoop.hbase.protobuf.generated.ClusterStatusProtos$ServerLoad$Builder setReplLoadSink(org.apache.hadoop.hbase.protobuf.generated.ClusterStatusProtos$ReplicationLoadSink);
    Code:
       0: aload_0
       1: getfield      #36                 // Field replLoadSinkBuilder_:Lcom/google/protobuf/SingleFieldBuilder;
       4: ifnonnull     31
       7: aload_1
       8: ifnonnull     19
      11: new           #127                // class java/lang/NullPointerException
      14: dup
      15: invokespecial #128                // Method java/lang/NullPointerException."<init>":()V
      18: athrow
      19: aload_0
      20: aload_1
      21: putfield      #14                 // Field replLoadSink_:Lorg/apache/hadoop/hbase/protobuf/generated/ClusterStatusProtos$ReplicationLoadSink;
      24: aload_0
      25: invokevirtual #78                 // Method onChanged:()V
      28: goto          40
      31: aload_0
      32: getfield      #36                 // Field replLoadSinkBuilder_:Lcom/google/protobuf/SingleFieldBuilder;
      35: aload_1
      36: invokevirtual #163                // Method com/google/protobuf/SingleFieldBuilder.setMessage:(Lcom/google/protobuf/GeneratedMessage;)Lcom/google/protobuf/SingleFieldBuilder;
      39: pop
      40: aload_0
      41: dup
      42: getfield      #25                 // Field bitField0_:I
      45: sipush        1024
      48: ior
      49: putfield      #25                 // Field bitField0_:I
      52: aload_0
      53: areturn

  public org.apache.hadoop.hbase.protobuf.generated.ClusterStatusProtos$ServerLoad$Builder setReplLoadSink(org.apache.hadoop.hbase.protobuf.generated.ClusterStatusProtos$ReplicationLoadSink$Builder);
    Code:
       0: aload_0
       1: getfield      #36                 // Field replLoadSinkBuilder_:Lcom/google/protobuf/SingleFieldBuilder;
       4: ifnonnull     22
       7: aload_0
       8: aload_1
       9: invokevirtual #164                // Method org/apache/hadoop/hbase/protobuf/generated/ClusterStatusProtos$ReplicationLoadSink$Builder.build:()Lorg/apache/hadoop/hbase/protobuf/generated/ClusterStatusProtos$ReplicationLoadSink;
      12: putfield      #14                 // Field replLoadSink_:Lorg/apache/hadoop/hbase/protobuf/generated/ClusterStatusProtos$ReplicationLoadSink;
      15: aload_0
      16: invokevirtual #78                 // Method onChanged:()V
      19: goto          34
      22: aload_0
      23: getfield      #36                 // Field replLoadSinkBuilder_:Lcom/google/protobuf/SingleFieldBuilder;
      26: aload_1
      27: invokevirtual #164                // Method org/apache/hadoop/hbase/protobuf/generated/ClusterStatusProtos$ReplicationLoadSink$Builder.build:()Lorg/apache/hadoop/hbase/protobuf/generated/ClusterStatusProtos$ReplicationLoadSink;
      30: invokevirtual #163                // Method com/google/protobuf/SingleFieldBuilder.setMessage:(Lcom/google/protobuf/GeneratedMessage;)Lcom/google/protobuf/SingleFieldBuilder;
      33: pop
      34: aload_0
      35: dup
      36: getfield      #25                 // Field bitField0_:I
      39: sipush        1024
      42: ior
      43: putfield      #25                 // Field bitField0_:I
      46: aload_0
      47: areturn

  public org.apache.hadoop.hbase.protobuf.generated.ClusterStatusProtos$ServerLoad$Builder mergeReplLoadSink(org.apache.hadoop.hbase.protobuf.generated.ClusterStatusProtos$ReplicationLoadSink);
    Code:
       0: aload_0
       1: getfield      #36                 // Field replLoadSinkBuilder_:Lcom/google/protobuf/SingleFieldBuilder;
       4: ifnonnull     64
       7: aload_0
       8: getfield      #25                 // Field bitField0_:I
      11: sipush        1024
      14: iand
      15: sipush        1024
      18: if_icmpne     52
      21: aload_0
      22: getfield      #14                 // Field replLoadSink_:Lorg/apache/hadoop/hbase/protobuf/generated/ClusterStatusProtos$ReplicationLoadSink;
      25: invokestatic  #13                 // Method org/apache/hadoop/hbase/protobuf/generated/ClusterStatusProtos$ReplicationLoadSink.getDefaultInstance:()Lorg/apache/hadoop/hbase/protobuf/generated/ClusterStatusProtos$ReplicationLoadSink;
      28: if_acmpeq     52
      31: aload_0
      32: aload_0
      33: getfield      #14                 // Field replLoadSink_:Lorg/apache/hadoop/hbase/protobuf/generated/ClusterStatusProtos$ReplicationLoadSink;
      36: invokestatic  #165                // Method org/apache/hadoop/hbase/protobuf/generated/ClusterStatusProtos$ReplicationLoadSink.newBuilder:(Lorg/apache/hadoop/hbase/protobuf/generated/ClusterStatusProtos$ReplicationLoadSink;)Lorg/apache/hadoop/hbase/protobuf/generated/ClusterStatusProtos$ReplicationLoadSink$Builder;
      39: aload_1
      40: invokevirtual #166                // Method org/apache/hadoop/hbase/protobuf/generated/ClusterStatusProtos$ReplicationLoadSink$Builder.mergeFrom:(Lorg/apache/hadoop/hbase/protobuf/generated/ClusterStatusProtos$ReplicationLoadSink;)Lorg/apache/hadoop/hbase/protobuf/generated/ClusterStatusProtos$ReplicationLoadSink$Builder;
      43: invokevirtual #167                // Method org/apache/hadoop/hbase/protobuf/generated/ClusterStatusProtos$ReplicationLoadSink$Builder.buildPartial:()Lorg/apache/hadoop/hbase/protobuf/generated/ClusterStatusProtos$ReplicationLoadSink;
      46: putfield      #14                 // Field replLoadSink_:Lorg/apache/hadoop/hbase/protobuf/generated/ClusterStatusProtos$ReplicationLoadSink;
      49: goto          57
      52: aload_0
      53: aload_1
      54: putfield      #14                 // Field replLoadSink_:Lorg/apache/hadoop/hbase/protobuf/generated/ClusterStatusProtos$ReplicationLoadSink;
      57: aload_0
      58: invokevirtual #78                 // Method onChanged:()V
      61: goto          73
      64: aload_0
      65: getfield      #36                 // Field replLoadSinkBuilder_:Lcom/google/protobuf/SingleFieldBuilder;
      68: aload_1
      69: invokevirtual #168                // Method com/google/protobuf/SingleFieldBuilder.mergeFrom:(Lcom/google/protobuf/GeneratedMessage;)Lcom/google/protobuf/SingleFieldBuilder;
      72: pop
      73: aload_0
      74: dup
      75: getfield      #25                 // Field bitField0_:I
      78: sipush        1024
      81: ior
      82: putfield      #25                 // Field bitField0_:I
      85: aload_0
      86: areturn

  public org.apache.hadoop.hbase.protobuf.generated.ClusterStatusProtos$ServerLoad$Builder clearReplLoadSink();
    Code:
       0: aload_0
       1: getfield      #36                 // Field replLoadSinkBuilder_:Lcom/google/protobuf/SingleFieldBuilder;
       4: ifnonnull     21
       7: aload_0
       8: invokestatic  #13                 // Method org/apache/hadoop/hbase/protobuf/generated/ClusterStatusProtos$ReplicationLoadSink.getDefaultInstance:()Lorg/apache/hadoop/hbase/protobuf/generated/ClusterStatusProtos$ReplicationLoadSink;
      11: putfield      #14                 // Field replLoadSink_:Lorg/apache/hadoop/hbase/protobuf/generated/ClusterStatusProtos$ReplicationLoadSink;
      14: aload_0
      15: invokevirtual #78                 // Method onChanged:()V
      18: goto          29
      21: aload_0
      22: getfield      #36                 // Field replLoadSinkBuilder_:Lcom/google/protobuf/SingleFieldBuilder;
      25: invokevirtual #37                 // Method com/google/protobuf/SingleFieldBuilder.clear:()Lcom/google/protobuf/SingleFieldBuilder;
      28: pop
      29: aload_0
      30: aload_0
      31: getfield      #25                 // Field bitField0_:I
      34: sipush        -1025
      37: iand
      38: putfield      #25                 // Field bitField0_:I
      41: aload_0
      42: areturn

  public org.apache.hadoop.hbase.protobuf.generated.ClusterStatusProtos$ReplicationLoadSink$Builder getReplLoadSinkBuilder();
    Code:
       0: aload_0
       1: dup
       2: getfield      #25                 // Field bitField0_:I
       5: sipush        1024
       8: ior
       9: putfield      #25                 // Field bitField0_:I
      12: aload_0
      13: invokevirtual #78                 // Method onChanged:()V
      16: aload_0
      17: invokespecial #21                 // Method getReplLoadSinkFieldBuilder:()Lcom/google/protobuf/SingleFieldBuilder;
      20: invokevirtual #169                // Method com/google/protobuf/SingleFieldBuilder.getBuilder:()Lcom/google/protobuf/GeneratedMessage$Builder;
      23: checkcast     #170                // class org/apache/hadoop/hbase/protobuf/generated/ClusterStatusProtos$ReplicationLoadSink$Builder
      26: areturn

  public org.apache.hadoop.hbase.protobuf.generated.ClusterStatusProtos$ReplicationLoadSinkOrBuilder getReplLoadSinkOrBuilder();
    Code:
       0: aload_0
       1: getfield      #36                 // Field replLoadSinkBuilder_:Lcom/google/protobuf/SingleFieldBuilder;
       4: ifnull        18
       7: aload_0
       8: getfield      #36                 // Field replLoadSinkBuilder_:Lcom/google/protobuf/SingleFieldBuilder;
      11: invokevirtual #171                // Method com/google/protobuf/SingleFieldBuilder.getMessageOrBuilder:()Lcom/google/protobuf/MessageOrBuilder;
      14: checkcast     #172                // class org/apache/hadoop/hbase/protobuf/generated/ClusterStatusProtos$ReplicationLoadSinkOrBuilder
      17: areturn
      18: aload_0
      19: getfield      #14                 // Field replLoadSink_:Lorg/apache/hadoop/hbase/protobuf/generated/ClusterStatusProtos$ReplicationLoadSink;
      22: areturn

  public com.google.protobuf.GeneratedMessage$Builder clear();
    Code:
       0: aload_0
       1: invokevirtual #175                // Method clear:()Lorg/apache/hadoop/hbase/protobuf/generated/ClusterStatusProtos$ServerLoad$Builder;
       4: areturn

  public com.google.protobuf.GeneratedMessage$Builder clone();
    Code:
       0: aload_0
       1: invokevirtual #176                // Method clone:()Lorg/apache/hadoop/hbase/protobuf/generated/ClusterStatusProtos$ServerLoad$Builder;
       4: areturn

  public com.google.protobuf.AbstractMessage$Builder mergeFrom(com.google.protobuf.CodedInputStream, com.google.protobuf.ExtensionRegistryLite) throws java.io.IOException;
    Code:
       0: aload_0
       1: aload_1
       2: aload_2
       3: invokevirtual #177                // Method mergeFrom:(Lcom/google/protobuf/CodedInputStream;Lcom/google/protobuf/ExtensionRegistryLite;)Lorg/apache/hadoop/hbase/protobuf/generated/ClusterStatusProtos$ServerLoad$Builder;
       6: areturn

  public com.google.protobuf.AbstractMessage$Builder mergeFrom(com.google.protobuf.Message);
    Code:
       0: aload_0
       1: aload_1
       2: invokevirtual #178                // Method mergeFrom:(Lcom/google/protobuf/Message;)Lorg/apache/hadoop/hbase/protobuf/generated/ClusterStatusProtos$ServerLoad$Builder;
       5: areturn

  public com.google.protobuf.AbstractMessage$Builder clear();
    Code:
       0: aload_0
       1: invokevirtual #175                // Method clear:()Lorg/apache/hadoop/hbase/protobuf/generated/ClusterStatusProtos$ServerLoad$Builder;
       4: areturn

  public com.google.protobuf.AbstractMessage$Builder clone();
    Code:
       0: aload_0
       1: invokevirtual #176                // Method clone:()Lorg/apache/hadoop/hbase/protobuf/generated/ClusterStatusProtos$ServerLoad$Builder;
       4: areturn

  public com.google.protobuf.Message$Builder mergeFrom(com.google.protobuf.CodedInputStream, com.google.protobuf.ExtensionRegistryLite) throws java.io.IOException;
    Code:
       0: aload_0
       1: aload_1
       2: aload_2
       3: invokevirtual #177                // Method mergeFrom:(Lcom/google/protobuf/CodedInputStream;Lcom/google/protobuf/ExtensionRegistryLite;)Lorg/apache/hadoop/hbase/protobuf/generated/ClusterStatusProtos$ServerLoad$Builder;
       6: areturn

  public com.google.protobuf.Message$Builder clone();
    Code:
       0: aload_0
       1: invokevirtual #176                // Method clone:()Lorg/apache/hadoop/hbase/protobuf/generated/ClusterStatusProtos$ServerLoad$Builder;
       4: areturn

  public com.google.protobuf.Message buildPartial();
    Code:
       0: aload_0
       1: invokevirtual #38                 // Method buildPartial:()Lorg/apache/hadoop/hbase/protobuf/generated/ClusterStatusProtos$ServerLoad;
       4: areturn

  public com.google.protobuf.Message build();
    Code:
       0: aload_0
       1: invokevirtual #179                // Method build:()Lorg/apache/hadoop/hbase/protobuf/generated/ClusterStatusProtos$ServerLoad;
       4: areturn

  public com.google.protobuf.Message$Builder mergeFrom(com.google.protobuf.Message);
    Code:
       0: aload_0
       1: aload_1
       2: invokevirtual #178                // Method mergeFrom:(Lcom/google/protobuf/Message;)Lorg/apache/hadoop/hbase/protobuf/generated/ClusterStatusProtos$ServerLoad$Builder;
       5: areturn

  public com.google.protobuf.Message$Builder clear();
    Code:
       0: aload_0
       1: invokevirtual #175                // Method clear:()Lorg/apache/hadoop/hbase/protobuf/generated/ClusterStatusProtos$ServerLoad$Builder;
       4: areturn

  public com.google.protobuf.MessageLite$Builder mergeFrom(com.google.protobuf.CodedInputStream, com.google.protobuf.ExtensionRegistryLite) throws java.io.IOException;
    Code:
       0: aload_0
       1: aload_1
       2: aload_2
       3: invokevirtual #177                // Method mergeFrom:(Lcom/google/protobuf/CodedInputStream;Lcom/google/protobuf/ExtensionRegistryLite;)Lorg/apache/hadoop/hbase/protobuf/generated/ClusterStatusProtos$ServerLoad$Builder;
       6: areturn

  public com.google.protobuf.MessageLite$Builder clone();
    Code:
       0: aload_0
       1: invokevirtual #176                // Method clone:()Lorg/apache/hadoop/hbase/protobuf/generated/ClusterStatusProtos$ServerLoad$Builder;
       4: areturn

  public com.google.protobuf.MessageLite buildPartial();
    Code:
       0: aload_0
       1: invokevirtual #38                 // Method buildPartial:()Lorg/apache/hadoop/hbase/protobuf/generated/ClusterStatusProtos$ServerLoad;
       4: areturn

  public com.google.protobuf.MessageLite build();
    Code:
       0: aload_0
       1: invokevirtual #179                // Method build:()Lorg/apache/hadoop/hbase/protobuf/generated/ClusterStatusProtos$ServerLoad;
       4: areturn

  public com.google.protobuf.MessageLite$Builder clear();
    Code:
       0: aload_0
       1: invokevirtual #175                // Method clear:()Lorg/apache/hadoop/hbase/protobuf/generated/ClusterStatusProtos$ServerLoad$Builder;
       4: areturn

  public com.google.protobuf.MessageLite getDefaultInstanceForType();
    Code:
       0: aload_0
       1: invokevirtual #180                // Method getDefaultInstanceForType:()Lorg/apache/hadoop/hbase/protobuf/generated/ClusterStatusProtos$ServerLoad;
       4: areturn

  public com.google.protobuf.Message getDefaultInstanceForType();
    Code:
       0: aload_0
       1: invokevirtual #180                // Method getDefaultInstanceForType:()Lorg/apache/hadoop/hbase/protobuf/generated/ClusterStatusProtos$ServerLoad;
       4: areturn

  public com.google.protobuf.AbstractMessageLite$Builder mergeFrom(com.google.protobuf.CodedInputStream, com.google.protobuf.ExtensionRegistryLite) throws java.io.IOException;
    Code:
       0: aload_0
       1: aload_1
       2: aload_2
       3: invokevirtual #177                // Method mergeFrom:(Lcom/google/protobuf/CodedInputStream;Lcom/google/protobuf/ExtensionRegistryLite;)Lorg/apache/hadoop/hbase/protobuf/generated/ClusterStatusProtos$ServerLoad$Builder;
       6: areturn

  public com.google.protobuf.AbstractMessageLite$Builder clone();
    Code:
       0: aload_0
       1: invokevirtual #176                // Method clone:()Lorg/apache/hadoop/hbase/protobuf/generated/ClusterStatusProtos$ServerLoad$Builder;
       4: areturn

  public java.lang.Object clone() throws java.lang.CloneNotSupportedException;
    Code:
       0: aload_0
       1: invokevirtual #176                // Method clone:()Lorg/apache/hadoop/hbase/protobuf/generated/ClusterStatusProtos$ServerLoad$Builder;
       4: areturn

  static org.apache.hadoop.hbase.protobuf.generated.ClusterStatusProtos$ServerLoad$Builder access$9800();
    Code:
       0: invokestatic  #2                  // Method create:()Lorg/apache/hadoop/hbase/protobuf/generated/ClusterStatusProtos$ServerLoad$Builder;
       3: areturn

  org.apache.hadoop.hbase.protobuf.generated.ClusterStatusProtos$ServerLoad$Builder(com.google.protobuf.GeneratedMessage$BuilderParent, org.apache.hadoop.hbase.protobuf.generated.ClusterStatusProtos$1);
    Code:
       0: aload_0
       1: aload_1
       2: invokespecial #1                  // Method "<init>":(Lcom/google/protobuf/GeneratedMessage$BuilderParent;)V
       5: return
}
