Compiled from "ClusterLoadState.java"
public class org.apache.hadoop.hbase.master.balancer.ClusterLoadState {
  public org.apache.hadoop.hbase.master.balancer.ClusterLoadState(java.util.Map<org.apache.hadoop.hbase.ServerName, java.util.List<org.apache.hadoop.hbase.client.RegionInfo>>);
    Code:
       0: aload_0
       1: invokespecial #1                  // Method java/lang/Object."<init>":()V
       4: aload_0
       5: iconst_0
       6: putfield      #2                  // Field emptyRegionServerPresent:Z
       9: aload_0
      10: iconst_0
      11: putfield      #3                  // Field numRegions:I
      14: aload_0
      15: iconst_0
      16: putfield      #4                  // Field numServers:I
      19: aload_0
      20: iconst_0
      21: putfield      #3                  // Field numRegions:I
      24: aload_0
      25: aload_1
      26: invokeinterface #5,  1            // InterfaceMethod java/util/Map.size:()I
      31: putfield      #4                  // Field numServers:I
      34: aload_0
      35: aload_1
      36: putfield      #6                  // Field clusterState:Ljava/util/Map;
      39: aload_0
      40: new           #7                  // class java/util/TreeMap
      43: dup
      44: invokespecial #8                  // Method java/util/TreeMap."<init>":()V
      47: putfield      #9                  // Field serversByLoad:Ljava/util/NavigableMap;
      50: aload_1
      51: invokeinterface #10,  1           // InterfaceMethod java/util/Map.entrySet:()Ljava/util/Set;
      56: invokeinterface #11,  1           // InterfaceMethod java/util/Set.iterator:()Ljava/util/Iterator;
      61: astore_2
      62: aload_2
      63: invokeinterface #12,  1           // InterfaceMethod java/util/Iterator.hasNext:()Z
      68: ifeq          155
      71: aload_2
      72: invokeinterface #13,  1           // InterfaceMethod java/util/Iterator.next:()Ljava/lang/Object;
      77: checkcast     #14                 // class java/util/Map$Entry
      80: astore_3
      81: aload_3
      82: invokeinterface #15,  1           // InterfaceMethod java/util/Map$Entry.getValue:()Ljava/lang/Object;
      87: checkcast     #16                 // class java/util/List
      90: astore        4
      92: aload         4
      94: invokeinterface #17,  1           // InterfaceMethod java/util/List.size:()I
      99: istore        5
     101: iload         5
     103: ifne          111
     106: aload_0
     107: iconst_1
     108: putfield      #2                  // Field emptyRegionServerPresent:Z
     111: aload_0
     112: dup
     113: getfield      #3                  // Field numRegions:I
     116: iload         5
     118: iadd
     119: putfield      #3                  // Field numRegions:I
     122: aload_0
     123: getfield      #9                  // Field serversByLoad:Ljava/util/NavigableMap;
     126: new           #18                 // class org/apache/hadoop/hbase/master/balancer/ServerAndLoad
     129: dup
     130: aload_3
     131: invokeinterface #19,  1           // InterfaceMethod java/util/Map$Entry.getKey:()Ljava/lang/Object;
     136: checkcast     #20                 // class org/apache/hadoop/hbase/ServerName
     139: iload         5
     141: invokespecial #21                 // Method org/apache/hadoop/hbase/master/balancer/ServerAndLoad."<init>":(Lorg/apache/hadoop/hbase/ServerName;I)V
     144: aload         4
     146: invokeinterface #22,  3           // InterfaceMethod java/util/NavigableMap.put:(Ljava/lang/Object;Ljava/lang/Object;)Ljava/lang/Object;
     151: pop
     152: goto          62
     155: return

  java.util.Map<org.apache.hadoop.hbase.ServerName, java.util.List<org.apache.hadoop.hbase.client.RegionInfo>> getClusterState();
    Code:
       0: aload_0
       1: getfield      #6                  // Field clusterState:Ljava/util/Map;
       4: areturn

  java.util.NavigableMap<org.apache.hadoop.hbase.master.balancer.ServerAndLoad, java.util.List<org.apache.hadoop.hbase.client.RegionInfo>> getServersByLoad();
    Code:
       0: aload_0
       1: getfield      #9                  // Field serversByLoad:Ljava/util/NavigableMap;
       4: areturn

  boolean isEmptyRegionServerPresent();
    Code:
       0: aload_0
       1: getfield      #2                  // Field emptyRegionServerPresent:Z
       4: ireturn

  int getNumRegions();
    Code:
       0: aload_0
       1: getfield      #3                  // Field numRegions:I
       4: ireturn

  int getNumServers();
    Code:
       0: aload_0
       1: getfield      #4                  // Field numServers:I
       4: ireturn

  float getLoadAverage();
    Code:
       0: aload_0
       1: getfield      #3                  // Field numRegions:I
       4: i2f
       5: aload_0
       6: getfield      #4                  // Field numServers:I
       9: i2f
      10: fdiv
      11: freturn

  int getMaxLoad();
    Code:
       0: aload_0
       1: invokevirtual #23                 // Method getServersByLoad:()Ljava/util/NavigableMap;
       4: invokeinterface #24,  1           // InterfaceMethod java/util/NavigableMap.lastKey:()Ljava/lang/Object;
       9: checkcast     #18                 // class org/apache/hadoop/hbase/master/balancer/ServerAndLoad
      12: invokevirtual #25                 // Method org/apache/hadoop/hbase/master/balancer/ServerAndLoad.getLoad:()I
      15: ireturn

  int getMinLoad();
    Code:
       0: aload_0
       1: invokevirtual #23                 // Method getServersByLoad:()Ljava/util/NavigableMap;
       4: invokeinterface #26,  1           // InterfaceMethod java/util/NavigableMap.firstKey:()Ljava/lang/Object;
       9: checkcast     #18                 // class org/apache/hadoop/hbase/master/balancer/ServerAndLoad
      12: invokevirtual #25                 // Method org/apache/hadoop/hbase/master/balancer/ServerAndLoad.getLoad:()I
      15: ireturn
}
