Compiled from "ClusterStatusProtos.java"
public final class org.apache.hadoop.hbase.protobuf.generated.ClusterStatusProtos$ClusterStatus$Builder extends com.google.protobuf.GeneratedMessage$Builder<org.apache.hadoop.hbase.protobuf.generated.ClusterStatusProtos$ClusterStatus$Builder> implements org.apache.hadoop.hbase.protobuf.generated.ClusterStatusProtos$ClusterStatusOrBuilder {
  public static final com.google.protobuf.Descriptors$Descriptor getDescriptor();
    Code:
       0: invokestatic  #3                  // Method org/apache/hadoop/hbase/protobuf/generated/ClusterStatusProtos.access$12700:()Lcom/google/protobuf/Descriptors$Descriptor;
       3: areturn

  protected com.google.protobuf.GeneratedMessage$FieldAccessorTable internalGetFieldAccessorTable();
    Code:
       0: invokestatic  #4                  // Method org/apache/hadoop/hbase/protobuf/generated/ClusterStatusProtos.access$12800:()Lcom/google/protobuf/GeneratedMessage$FieldAccessorTable;
       3: ldc           #5                  // class org/apache/hadoop/hbase/protobuf/generated/ClusterStatusProtos$ClusterStatus
       5: ldc           #6                  // class org/apache/hadoop/hbase/protobuf/generated/ClusterStatusProtos$ClusterStatus$Builder
       7: invokevirtual #7                  // Method com/google/protobuf/GeneratedMessage$FieldAccessorTable.ensureFieldAccessorsInitialized:(Ljava/lang/Class;Ljava/lang/Class;)Lcom/google/protobuf/GeneratedMessage$FieldAccessorTable;
      10: areturn

  public org.apache.hadoop.hbase.protobuf.generated.ClusterStatusProtos$ClusterStatus$Builder clear();
    Code:
       0: aload_0
       1: invokespecial #33                 // Method com/google/protobuf/GeneratedMessage$Builder.clear:()Lcom/google/protobuf/GeneratedMessage$Builder;
       4: pop
       5: aload_0
       6: getfield      #34                 // Field hbaseVersionBuilder_:Lcom/google/protobuf/SingleFieldBuilder;
       9: ifnonnull     22
      12: aload_0
      13: invokestatic  #9                  // Method org/apache/hadoop/hbase/protobuf/generated/FSProtos$HBaseVersionFileContent.getDefaultInstance:()Lorg/apache/hadoop/hbase/protobuf/generated/FSProtos$HBaseVersionFileContent;
      16: putfield      #10                 // Field hbaseVersion_:Lorg/apache/hadoop/hbase/protobuf/generated/FSProtos$HBaseVersionFileContent;
      19: goto          30
      22: aload_0
      23: getfield      #34                 // Field hbaseVersionBuilder_:Lcom/google/protobuf/SingleFieldBuilder;
      26: invokevirtual #35                 // Method com/google/protobuf/SingleFieldBuilder.clear:()Lcom/google/protobuf/SingleFieldBuilder;
      29: pop
      30: aload_0
      31: aload_0
      32: getfield      #36                 // Field bitField0_:I
      35: bipush        -2
      37: iand
      38: putfield      #36                 // Field bitField0_:I
      41: aload_0
      42: getfield      #37                 // Field liveServersBuilder_:Lcom/google/protobuf/RepeatedFieldBuilder;
      45: ifnonnull     69
      48: aload_0
      49: invokestatic  #11                 // Method java/util/Collections.emptyList:()Ljava/util/List;
      52: putfield      #12                 // Field liveServers_:Ljava/util/List;
      55: aload_0
      56: aload_0
      57: getfield      #36                 // Field bitField0_:I
      60: bipush        -3
      62: iand
      63: putfield      #36                 // Field bitField0_:I
      66: goto          76
      69: aload_0
      70: getfield      #37                 // Field liveServersBuilder_:Lcom/google/protobuf/RepeatedFieldBuilder;
      73: invokevirtual #38                 // Method com/google/protobuf/RepeatedFieldBuilder.clear:()V
      76: aload_0
      77: getfield      #39                 // Field deadServersBuilder_:Lcom/google/protobuf/RepeatedFieldBuilder;
      80: ifnonnull     104
      83: aload_0
      84: invokestatic  #11                 // Method java/util/Collections.emptyList:()Ljava/util/List;
      87: putfield      #13                 // Field deadServers_:Ljava/util/List;
      90: aload_0
      91: aload_0
      92: getfield      #36                 // Field bitField0_:I
      95: bipush        -5
      97: iand
      98: putfield      #36                 // Field bitField0_:I
     101: goto          111
     104: aload_0
     105: getfield      #39                 // Field deadServersBuilder_:Lcom/google/protobuf/RepeatedFieldBuilder;
     108: invokevirtual #38                 // Method com/google/protobuf/RepeatedFieldBuilder.clear:()V
     111: aload_0
     112: getfield      #40                 // Field regionsInTransitionBuilder_:Lcom/google/protobuf/RepeatedFieldBuilder;
     115: ifnonnull     139
     118: aload_0
     119: invokestatic  #11                 // Method java/util/Collections.emptyList:()Ljava/util/List;
     122: putfield      #14                 // Field regionsInTransition_:Ljava/util/List;
     125: aload_0
     126: aload_0
     127: getfield      #36                 // Field bitField0_:I
     130: bipush        -9
     132: iand
     133: putfield      #36                 // Field bitField0_:I
     136: goto          146
     139: aload_0
     140: getfield      #40                 // Field regionsInTransitionBuilder_:Lcom/google/protobuf/RepeatedFieldBuilder;
     143: invokevirtual #38                 // Method com/google/protobuf/RepeatedFieldBuilder.clear:()V
     146: aload_0
     147: getfield      #41                 // Field clusterIdBuilder_:Lcom/google/protobuf/SingleFieldBuilder;
     150: ifnonnull     163
     153: aload_0
     154: invokestatic  #15                 // Method org/apache/hadoop/hbase/protobuf/generated/ClusterIdProtos$ClusterId.getDefaultInstance:()Lorg/apache/hadoop/hbase/protobuf/generated/ClusterIdProtos$ClusterId;
     157: putfield      #16                 // Field clusterId_:Lorg/apache/hadoop/hbase/protobuf/generated/ClusterIdProtos$ClusterId;
     160: goto          171
     163: aload_0
     164: getfield      #41                 // Field clusterIdBuilder_:Lcom/google/protobuf/SingleFieldBuilder;
     167: invokevirtual #35                 // Method com/google/protobuf/SingleFieldBuilder.clear:()Lcom/google/protobuf/SingleFieldBuilder;
     170: pop
     171: aload_0
     172: aload_0
     173: getfield      #36                 // Field bitField0_:I
     176: bipush        -17
     178: iand
     179: putfield      #36                 // Field bitField0_:I
     182: aload_0
     183: getfield      #42                 // Field masterCoprocessorsBuilder_:Lcom/google/protobuf/RepeatedFieldBuilder;
     186: ifnonnull     210
     189: aload_0
     190: invokestatic  #11                 // Method java/util/Collections.emptyList:()Ljava/util/List;
     193: putfield      #17                 // Field masterCoprocessors_:Ljava/util/List;
     196: aload_0
     197: aload_0
     198: getfield      #36                 // Field bitField0_:I
     201: bipush        -33
     203: iand
     204: putfield      #36                 // Field bitField0_:I
     207: goto          217
     210: aload_0
     211: getfield      #42                 // Field masterCoprocessorsBuilder_:Lcom/google/protobuf/RepeatedFieldBuilder;
     214: invokevirtual #38                 // Method com/google/protobuf/RepeatedFieldBuilder.clear:()V
     217: aload_0
     218: getfield      #43                 // Field masterBuilder_:Lcom/google/protobuf/SingleFieldBuilder;
     221: ifnonnull     234
     224: aload_0
     225: invokestatic  #18                 // Method org/apache/hadoop/hbase/protobuf/generated/HBaseProtos$ServerName.getDefaultInstance:()Lorg/apache/hadoop/hbase/protobuf/generated/HBaseProtos$ServerName;
     228: putfield      #19                 // Field master_:Lorg/apache/hadoop/hbase/protobuf/generated/HBaseProtos$ServerName;
     231: goto          242
     234: aload_0
     235: getfield      #43                 // Field masterBuilder_:Lcom/google/protobuf/SingleFieldBuilder;
     238: invokevirtual #35                 // Method com/google/protobuf/SingleFieldBuilder.clear:()Lcom/google/protobuf/SingleFieldBuilder;
     241: pop
     242: aload_0
     243: aload_0
     244: getfield      #36                 // Field bitField0_:I
     247: bipush        -65
     249: iand
     250: putfield      #36                 // Field bitField0_:I
     253: aload_0
     254: getfield      #44                 // Field backupMastersBuilder_:Lcom/google/protobuf/RepeatedFieldBuilder;
     257: ifnonnull     282
     260: aload_0
     261: invokestatic  #11                 // Method java/util/Collections.emptyList:()Ljava/util/List;
     264: putfield      #20                 // Field backupMasters_:Ljava/util/List;
     267: aload_0
     268: aload_0
     269: getfield      #36                 // Field bitField0_:I
     272: sipush        -129
     275: iand
     276: putfield      #36                 // Field bitField0_:I
     279: goto          289
     282: aload_0
     283: getfield      #44                 // Field backupMastersBuilder_:Lcom/google/protobuf/RepeatedFieldBuilder;
     286: invokevirtual #38                 // Method com/google/protobuf/RepeatedFieldBuilder.clear:()V
     289: aload_0
     290: iconst_0
     291: putfield      #45                 // Field balancerOn_:Z
     294: aload_0
     295: aload_0
     296: getfield      #36                 // Field bitField0_:I
     299: sipush        -257
     302: iand
     303: putfield      #36                 // Field bitField0_:I
     306: aload_0
     307: areturn

  public org.apache.hadoop.hbase.protobuf.generated.ClusterStatusProtos$ClusterStatus$Builder clone();
    Code:
       0: invokestatic  #2                  // Method create:()Lorg/apache/hadoop/hbase/protobuf/generated/ClusterStatusProtos$ClusterStatus$Builder;
       3: aload_0
       4: invokevirtual #46                 // Method buildPartial:()Lorg/apache/hadoop/hbase/protobuf/generated/ClusterStatusProtos$ClusterStatus;
       7: invokevirtual #47                 // Method mergeFrom:(Lorg/apache/hadoop/hbase/protobuf/generated/ClusterStatusProtos$ClusterStatus;)Lorg/apache/hadoop/hbase/protobuf/generated/ClusterStatusProtos$ClusterStatus$Builder;
      10: areturn

  public com.google.protobuf.Descriptors$Descriptor getDescriptorForType();
    Code:
       0: invokestatic  #3                  // Method org/apache/hadoop/hbase/protobuf/generated/ClusterStatusProtos.access$12700:()Lcom/google/protobuf/Descriptors$Descriptor;
       3: areturn

  public org.apache.hadoop.hbase.protobuf.generated.ClusterStatusProtos$ClusterStatus getDefaultInstanceForType();
    Code:
       0: invokestatic  #48                 // Method org/apache/hadoop/hbase/protobuf/generated/ClusterStatusProtos$ClusterStatus.getDefaultInstance:()Lorg/apache/hadoop/hbase/protobuf/generated/ClusterStatusProtos$ClusterStatus;
       3: areturn

  public org.apache.hadoop.hbase.protobuf.generated.ClusterStatusProtos$ClusterStatus build();
    Code:
       0: aload_0
       1: invokevirtual #46                 // Method buildPartial:()Lorg/apache/hadoop/hbase/protobuf/generated/ClusterStatusProtos$ClusterStatus;
       4: astore_1
       5: aload_1
       6: invokevirtual #49                 // Method org/apache/hadoop/hbase/protobuf/generated/ClusterStatusProtos$ClusterStatus.isInitialized:()Z
       9: ifne          17
      12: aload_1
      13: invokestatic  #50                 // Method newUninitializedMessageException:(Lcom/google/protobuf/Message;)Lcom/google/protobuf/UninitializedMessageException;
      16: athrow
      17: aload_1
      18: areturn

  public org.apache.hadoop.hbase.protobuf.generated.ClusterStatusProtos$ClusterStatus buildPartial();
    Code:
       0: new           #5                  // class org/apache/hadoop/hbase/protobuf/generated/ClusterStatusProtos$ClusterStatus
       3: dup
       4: aload_0
       5: aconst_null
       6: invokespecial #51                 // Method org/apache/hadoop/hbase/protobuf/generated/ClusterStatusProtos$ClusterStatus."<init>":(Lcom/google/protobuf/GeneratedMessage$Builder;Lorg/apache/hadoop/hbase/protobuf/generated/ClusterStatusProtos$1;)V
       9: astore_1
      10: aload_0
      11: getfield      #36                 // Field bitField0_:I
      14: istore_2
      15: iconst_0
      16: istore_3
      17: iload_2
      18: iconst_1
      19: iand
      20: iconst_1
      21: if_icmpne     28
      24: iload_3
      25: iconst_1
      26: ior
      27: istore_3
      28: aload_0
      29: getfield      #34                 // Field hbaseVersionBuilder_:Lcom/google/protobuf/SingleFieldBuilder;
      32: ifnonnull     47
      35: aload_1
      36: aload_0
      37: getfield      #10                 // Field hbaseVersion_:Lorg/apache/hadoop/hbase/protobuf/generated/FSProtos$HBaseVersionFileContent;
      40: invokestatic  #52                 // Method org/apache/hadoop/hbase/protobuf/generated/ClusterStatusProtos$ClusterStatus.access$13402:(Lorg/apache/hadoop/hbase/protobuf/generated/ClusterStatusProtos$ClusterStatus;Lorg/apache/hadoop/hbase/protobuf/generated/FSProtos$HBaseVersionFileContent;)Lorg/apache/hadoop/hbase/protobuf/generated/FSProtos$HBaseVersionFileContent;
      43: pop
      44: goto          62
      47: aload_1
      48: aload_0
      49: getfield      #34                 // Field hbaseVersionBuilder_:Lcom/google/protobuf/SingleFieldBuilder;
      52: invokevirtual #53                 // Method com/google/protobuf/SingleFieldBuilder.build:()Lcom/google/protobuf/GeneratedMessage;
      55: checkcast     #54                 // class org/apache/hadoop/hbase/protobuf/generated/FSProtos$HBaseVersionFileContent
      58: invokestatic  #52                 // Method org/apache/hadoop/hbase/protobuf/generated/ClusterStatusProtos$ClusterStatus.access$13402:(Lorg/apache/hadoop/hbase/protobuf/generated/ClusterStatusProtos$ClusterStatus;Lorg/apache/hadoop/hbase/protobuf/generated/FSProtos$HBaseVersionFileContent;)Lorg/apache/hadoop/hbase/protobuf/generated/FSProtos$HBaseVersionFileContent;
      61: pop
      62: aload_0
      63: getfield      #37                 // Field liveServersBuilder_:Lcom/google/protobuf/RepeatedFieldBuilder;
      66: ifnonnull     113
      69: aload_0
      70: getfield      #36                 // Field bitField0_:I
      73: iconst_2
      74: iand
      75: iconst_2
      76: if_icmpne     101
      79: aload_0
      80: aload_0
      81: getfield      #12                 // Field liveServers_:Ljava/util/List;
      84: invokestatic  #55                 // Method java/util/Collections.unmodifiableList:(Ljava/util/List;)Ljava/util/List;
      87: putfield      #12                 // Field liveServers_:Ljava/util/List;
      90: aload_0
      91: aload_0
      92: getfield      #36                 // Field bitField0_:I
      95: bipush        -3
      97: iand
      98: putfield      #36                 // Field bitField0_:I
     101: aload_1
     102: aload_0
     103: getfield      #12                 // Field liveServers_:Ljava/util/List;
     106: invokestatic  #56                 // Method org/apache/hadoop/hbase/protobuf/generated/ClusterStatusProtos$ClusterStatus.access$13502:(Lorg/apache/hadoop/hbase/protobuf/generated/ClusterStatusProtos$ClusterStatus;Ljava/util/List;)Ljava/util/List;
     109: pop
     110: goto          125
     113: aload_1
     114: aload_0
     115: getfield      #37                 // Field liveServersBuilder_:Lcom/google/protobuf/RepeatedFieldBuilder;
     118: invokevirtual #57                 // Method com/google/protobuf/RepeatedFieldBuilder.build:()Ljava/util/List;
     121: invokestatic  #56                 // Method org/apache/hadoop/hbase/protobuf/generated/ClusterStatusProtos$ClusterStatus.access$13502:(Lorg/apache/hadoop/hbase/protobuf/generated/ClusterStatusProtos$ClusterStatus;Ljava/util/List;)Ljava/util/List;
     124: pop
     125: aload_0
     126: getfield      #39                 // Field deadServersBuilder_:Lcom/google/protobuf/RepeatedFieldBuilder;
     129: ifnonnull     176
     132: aload_0
     133: getfield      #36                 // Field bitField0_:I
     136: iconst_4
     137: iand
     138: iconst_4
     139: if_icmpne     164
     142: aload_0
     143: aload_0
     144: getfield      #13                 // Field deadServers_:Ljava/util/List;
     147: invokestatic  #55                 // Method java/util/Collections.unmodifiableList:(Ljava/util/List;)Ljava/util/List;
     150: putfield      #13                 // Field deadServers_:Ljava/util/List;
     153: aload_0
     154: aload_0
     155: getfield      #36                 // Field bitField0_:I
     158: bipush        -5
     160: iand
     161: putfield      #36                 // Field bitField0_:I
     164: aload_1
     165: aload_0
     166: getfield      #13                 // Field deadServers_:Ljava/util/List;
     169: invokestatic  #58                 // Method org/apache/hadoop/hbase/protobuf/generated/ClusterStatusProtos$ClusterStatus.access$13602:(Lorg/apache/hadoop/hbase/protobuf/generated/ClusterStatusProtos$ClusterStatus;Ljava/util/List;)Ljava/util/List;
     172: pop
     173: goto          188
     176: aload_1
     177: aload_0
     178: getfield      #39                 // Field deadServersBuilder_:Lcom/google/protobuf/RepeatedFieldBuilder;
     181: invokevirtual #57                 // Method com/google/protobuf/RepeatedFieldBuilder.build:()Ljava/util/List;
     184: invokestatic  #58                 // Method org/apache/hadoop/hbase/protobuf/generated/ClusterStatusProtos$ClusterStatus.access$13602:(Lorg/apache/hadoop/hbase/protobuf/generated/ClusterStatusProtos$ClusterStatus;Ljava/util/List;)Ljava/util/List;
     187: pop
     188: aload_0
     189: getfield      #40                 // Field regionsInTransitionBuilder_:Lcom/google/protobuf/RepeatedFieldBuilder;
     192: ifnonnull     241
     195: aload_0
     196: getfield      #36                 // Field bitField0_:I
     199: bipush        8
     201: iand
     202: bipush        8
     204: if_icmpne     229
     207: aload_0
     208: aload_0
     209: getfield      #14                 // Field regionsInTransition_:Ljava/util/List;
     212: invokestatic  #55                 // Method java/util/Collections.unmodifiableList:(Ljava/util/List;)Ljava/util/List;
     215: putfield      #14                 // Field regionsInTransition_:Ljava/util/List;
     218: aload_0
     219: aload_0
     220: getfield      #36                 // Field bitField0_:I
     223: bipush        -9
     225: iand
     226: putfield      #36                 // Field bitField0_:I
     229: aload_1
     230: aload_0
     231: getfield      #14                 // Field regionsInTransition_:Ljava/util/List;
     234: invokestatic  #59                 // Method org/apache/hadoop/hbase/protobuf/generated/ClusterStatusProtos$ClusterStatus.access$13702:(Lorg/apache/hadoop/hbase/protobuf/generated/ClusterStatusProtos$ClusterStatus;Ljava/util/List;)Ljava/util/List;
     237: pop
     238: goto          253
     241: aload_1
     242: aload_0
     243: getfield      #40                 // Field regionsInTransitionBuilder_:Lcom/google/protobuf/RepeatedFieldBuilder;
     246: invokevirtual #57                 // Method com/google/protobuf/RepeatedFieldBuilder.build:()Ljava/util/List;
     249: invokestatic  #59                 // Method org/apache/hadoop/hbase/protobuf/generated/ClusterStatusProtos$ClusterStatus.access$13702:(Lorg/apache/hadoop/hbase/protobuf/generated/ClusterStatusProtos$ClusterStatus;Ljava/util/List;)Ljava/util/List;
     252: pop
     253: iload_2
     254: bipush        16
     256: iand
     257: bipush        16
     259: if_icmpne     266
     262: iload_3
     263: iconst_2
     264: ior
     265: istore_3
     266: aload_0
     267: getfield      #41                 // Field clusterIdBuilder_:Lcom/google/protobuf/SingleFieldBuilder;
     270: ifnonnull     285
     273: aload_1
     274: aload_0
     275: getfield      #16                 // Field clusterId_:Lorg/apache/hadoop/hbase/protobuf/generated/ClusterIdProtos$ClusterId;
     278: invokestatic  #60                 // Method org/apache/hadoop/hbase/protobuf/generated/ClusterStatusProtos$ClusterStatus.access$13802:(Lorg/apache/hadoop/hbase/protobuf/generated/ClusterStatusProtos$ClusterStatus;Lorg/apache/hadoop/hbase/protobuf/generated/ClusterIdProtos$ClusterId;)Lorg/apache/hadoop/hbase/protobuf/generated/ClusterIdProtos$ClusterId;
     281: pop
     282: goto          300
     285: aload_1
     286: aload_0
     287: getfield      #41                 // Field clusterIdBuilder_:Lcom/google/protobuf/SingleFieldBuilder;
     290: invokevirtual #53                 // Method com/google/protobuf/SingleFieldBuilder.build:()Lcom/google/protobuf/GeneratedMessage;
     293: checkcast     #61                 // class org/apache/hadoop/hbase/protobuf/generated/ClusterIdProtos$ClusterId
     296: invokestatic  #60                 // Method org/apache/hadoop/hbase/protobuf/generated/ClusterStatusProtos$ClusterStatus.access$13802:(Lorg/apache/hadoop/hbase/protobuf/generated/ClusterStatusProtos$ClusterStatus;Lorg/apache/hadoop/hbase/protobuf/generated/ClusterIdProtos$ClusterId;)Lorg/apache/hadoop/hbase/protobuf/generated/ClusterIdProtos$ClusterId;
     299: pop
     300: aload_0
     301: getfield      #42                 // Field masterCoprocessorsBuilder_:Lcom/google/protobuf/RepeatedFieldBuilder;
     304: ifnonnull     353
     307: aload_0
     308: getfield      #36                 // Field bitField0_:I
     311: bipush        32
     313: iand
     314: bipush        32
     316: if_icmpne     341
     319: aload_0
     320: aload_0
     321: getfield      #17                 // Field masterCoprocessors_:Ljava/util/List;
     324: invokestatic  #55                 // Method java/util/Collections.unmodifiableList:(Ljava/util/List;)Ljava/util/List;
     327: putfield      #17                 // Field masterCoprocessors_:Ljava/util/List;
     330: aload_0
     331: aload_0
     332: getfield      #36                 // Field bitField0_:I
     335: bipush        -33
     337: iand
     338: putfield      #36                 // Field bitField0_:I
     341: aload_1
     342: aload_0
     343: getfield      #17                 // Field masterCoprocessors_:Ljava/util/List;
     346: invokestatic  #62                 // Method org/apache/hadoop/hbase/protobuf/generated/ClusterStatusProtos$ClusterStatus.access$13902:(Lorg/apache/hadoop/hbase/protobuf/generated/ClusterStatusProtos$ClusterStatus;Ljava/util/List;)Ljava/util/List;
     349: pop
     350: goto          365
     353: aload_1
     354: aload_0
     355: getfield      #42                 // Field masterCoprocessorsBuilder_:Lcom/google/protobuf/RepeatedFieldBuilder;
     358: invokevirtual #57                 // Method com/google/protobuf/RepeatedFieldBuilder.build:()Ljava/util/List;
     361: invokestatic  #62                 // Method org/apache/hadoop/hbase/protobuf/generated/ClusterStatusProtos$ClusterStatus.access$13902:(Lorg/apache/hadoop/hbase/protobuf/generated/ClusterStatusProtos$ClusterStatus;Ljava/util/List;)Ljava/util/List;
     364: pop
     365: iload_2
     366: bipush        64
     368: iand
     369: bipush        64
     371: if_icmpne     378
     374: iload_3
     375: iconst_4
     376: ior
     377: istore_3
     378: aload_0
     379: getfield      #43                 // Field masterBuilder_:Lcom/google/protobuf/SingleFieldBuilder;
     382: ifnonnull     397
     385: aload_1
     386: aload_0
     387: getfield      #19                 // Field master_:Lorg/apache/hadoop/hbase/protobuf/generated/HBaseProtos$ServerName;
     390: invokestatic  #63                 // Method org/apache/hadoop/hbase/protobuf/generated/ClusterStatusProtos$ClusterStatus.access$14002:(Lorg/apache/hadoop/hbase/protobuf/generated/ClusterStatusProtos$ClusterStatus;Lorg/apache/hadoop/hbase/protobuf/generated/HBaseProtos$ServerName;)Lorg/apache/hadoop/hbase/protobuf/generated/HBaseProtos$ServerName;
     393: pop
     394: goto          412
     397: aload_1
     398: aload_0
     399: getfield      #43                 // Field masterBuilder_:Lcom/google/protobuf/SingleFieldBuilder;
     402: invokevirtual #53                 // Method com/google/protobuf/SingleFieldBuilder.build:()Lcom/google/protobuf/GeneratedMessage;
     405: checkcast     #64                 // class org/apache/hadoop/hbase/protobuf/generated/HBaseProtos$ServerName
     408: invokestatic  #63                 // Method org/apache/hadoop/hbase/protobuf/generated/ClusterStatusProtos$ClusterStatus.access$14002:(Lorg/apache/hadoop/hbase/protobuf/generated/ClusterStatusProtos$ClusterStatus;Lorg/apache/hadoop/hbase/protobuf/generated/HBaseProtos$ServerName;)Lorg/apache/hadoop/hbase/protobuf/generated/HBaseProtos$ServerName;
     411: pop
     412: aload_0
     413: getfield      #44                 // Field backupMastersBuilder_:Lcom/google/protobuf/RepeatedFieldBuilder;
     416: ifnonnull     468
     419: aload_0
     420: getfield      #36                 // Field bitField0_:I
     423: sipush        128
     426: iand
     427: sipush        128
     430: if_icmpne     456
     433: aload_0
     434: aload_0
     435: getfield      #20                 // Field backupMasters_:Ljava/util/List;
     438: invokestatic  #55                 // Method java/util/Collections.unmodifiableList:(Ljava/util/List;)Ljava/util/List;
     441: putfield      #20                 // Field backupMasters_:Ljava/util/List;
     444: aload_0
     445: aload_0
     446: getfield      #36                 // Field bitField0_:I
     449: sipush        -129
     452: iand
     453: putfield      #36                 // Field bitField0_:I
     456: aload_1
     457: aload_0
     458: getfield      #20                 // Field backupMasters_:Ljava/util/List;
     461: invokestatic  #65                 // Method org/apache/hadoop/hbase/protobuf/generated/ClusterStatusProtos$ClusterStatus.access$14102:(Lorg/apache/hadoop/hbase/protobuf/generated/ClusterStatusProtos$ClusterStatus;Ljava/util/List;)Ljava/util/List;
     464: pop
     465: goto          480
     468: aload_1
     469: aload_0
     470: getfield      #44                 // Field backupMastersBuilder_:Lcom/google/protobuf/RepeatedFieldBuilder;
     473: invokevirtual #57                 // Method com/google/protobuf/RepeatedFieldBuilder.build:()Ljava/util/List;
     476: invokestatic  #65                 // Method org/apache/hadoop/hbase/protobuf/generated/ClusterStatusProtos$ClusterStatus.access$14102:(Lorg/apache/hadoop/hbase/protobuf/generated/ClusterStatusProtos$ClusterStatus;Ljava/util/List;)Ljava/util/List;
     479: pop
     480: iload_2
     481: sipush        256
     484: iand
     485: sipush        256
     488: if_icmpne     496
     491: iload_3
     492: bipush        8
     494: ior
     495: istore_3
     496: aload_1
     497: aload_0
     498: getfield      #45                 // Field balancerOn_:Z
     501: invokestatic  #66                 // Method org/apache/hadoop/hbase/protobuf/generated/ClusterStatusProtos$ClusterStatus.access$14202:(Lorg/apache/hadoop/hbase/protobuf/generated/ClusterStatusProtos$ClusterStatus;Z)Z
     504: pop
     505: aload_1
     506: iload_3
     507: invokestatic  #67                 // Method org/apache/hadoop/hbase/protobuf/generated/ClusterStatusProtos$ClusterStatus.access$14302:(Lorg/apache/hadoop/hbase/protobuf/generated/ClusterStatusProtos$ClusterStatus;I)I
     510: pop
     511: aload_0
     512: invokevirtual #68                 // Method onBuilt:()V
     515: aload_1
     516: areturn

  public org.apache.hadoop.hbase.protobuf.generated.ClusterStatusProtos$ClusterStatus$Builder mergeFrom(com.google.protobuf.Message);
    Code:
       0: aload_1
       1: instanceof    #5                  // class org/apache/hadoop/hbase/protobuf/generated/ClusterStatusProtos$ClusterStatus
       4: ifeq          16
       7: aload_0
       8: aload_1
       9: checkcast     #5                  // class org/apache/hadoop/hbase/protobuf/generated/ClusterStatusProtos$ClusterStatus
      12: invokevirtual #47                 // Method mergeFrom:(Lorg/apache/hadoop/hbase/protobuf/generated/ClusterStatusProtos$ClusterStatus;)Lorg/apache/hadoop/hbase/protobuf/generated/ClusterStatusProtos$ClusterStatus$Builder;
      15: areturn
      16: aload_0
      17: aload_1
      18: invokespecial #69                 // Method com/google/protobuf/GeneratedMessage$Builder.mergeFrom:(Lcom/google/protobuf/Message;)Lcom/google/protobuf/AbstractMessage$Builder;
      21: pop
      22: aload_0
      23: areturn

  public org.apache.hadoop.hbase.protobuf.generated.ClusterStatusProtos$ClusterStatus$Builder mergeFrom(org.apache.hadoop.hbase.protobuf.generated.ClusterStatusProtos$ClusterStatus);
    Code:
       0: aload_1
       1: invokestatic  #48                 // Method org/apache/hadoop/hbase/protobuf/generated/ClusterStatusProtos$ClusterStatus.getDefaultInstance:()Lorg/apache/hadoop/hbase/protobuf/generated/ClusterStatusProtos$ClusterStatus;
       4: if_acmpne     9
       7: aload_0
       8: areturn
       9: aload_1
      10: invokevirtual #70                 // Method org/apache/hadoop/hbase/protobuf/generated/ClusterStatusProtos$ClusterStatus.hasHbaseVersion:()Z
      13: ifeq          25
      16: aload_0
      17: aload_1
      18: invokevirtual #71                 // Method org/apache/hadoop/hbase/protobuf/generated/ClusterStatusProtos$ClusterStatus.getHbaseVersion:()Lorg/apache/hadoop/hbase/protobuf/generated/FSProtos$HBaseVersionFileContent;
      21: invokevirtual #72                 // Method mergeHbaseVersion:(Lorg/apache/hadoop/hbase/protobuf/generated/FSProtos$HBaseVersionFileContent;)Lorg/apache/hadoop/hbase/protobuf/generated/ClusterStatusProtos$ClusterStatus$Builder;
      24: pop
      25: aload_0
      26: getfield      #37                 // Field liveServersBuilder_:Lcom/google/protobuf/RepeatedFieldBuilder;
      29: ifnonnull     103
      32: aload_1
      33: invokestatic  #73                 // Method org/apache/hadoop/hbase/protobuf/generated/ClusterStatusProtos$ClusterStatus.access$13500:(Lorg/apache/hadoop/hbase/protobuf/generated/ClusterStatusProtos$ClusterStatus;)Ljava/util/List;
      36: invokeinterface #74,  1           // InterfaceMethod java/util/List.isEmpty:()Z
      41: ifne          189
      44: aload_0
      45: getfield      #12                 // Field liveServers_:Ljava/util/List;
      48: invokeinterface #74,  1           // InterfaceMethod java/util/List.isEmpty:()Z
      53: ifeq          78
      56: aload_0
      57: aload_1
      58: invokestatic  #73                 // Method org/apache/hadoop/hbase/protobuf/generated/ClusterStatusProtos$ClusterStatus.access$13500:(Lorg/apache/hadoop/hbase/protobuf/generated/ClusterStatusProtos$ClusterStatus;)Ljava/util/List;
      61: putfield      #12                 // Field liveServers_:Ljava/util/List;
      64: aload_0
      65: aload_0
      66: getfield      #36                 // Field bitField0_:I
      69: bipush        -3
      71: iand
      72: putfield      #36                 // Field bitField0_:I
      75: goto          96
      78: aload_0
      79: invokespecial #75                 // Method ensureLiveServersIsMutable:()V
      82: aload_0
      83: getfield      #12                 // Field liveServers_:Ljava/util/List;
      86: aload_1
      87: invokestatic  #73                 // Method org/apache/hadoop/hbase/protobuf/generated/ClusterStatusProtos$ClusterStatus.access$13500:(Lorg/apache/hadoop/hbase/protobuf/generated/ClusterStatusProtos$ClusterStatus;)Ljava/util/List;
      90: invokeinterface #76,  2           // InterfaceMethod java/util/List.addAll:(Ljava/util/Collection;)Z
      95: pop
      96: aload_0
      97: invokevirtual #77                 // Method onChanged:()V
     100: goto          189
     103: aload_1
     104: invokestatic  #73                 // Method org/apache/hadoop/hbase/protobuf/generated/ClusterStatusProtos$ClusterStatus.access$13500:(Lorg/apache/hadoop/hbase/protobuf/generated/ClusterStatusProtos$ClusterStatus;)Ljava/util/List;
     107: invokeinterface #74,  1           // InterfaceMethod java/util/List.isEmpty:()Z
     112: ifne          189
     115: aload_0
     116: getfield      #37                 // Field liveServersBuilder_:Lcom/google/protobuf/RepeatedFieldBuilder;
     119: invokevirtual #78                 // Method com/google/protobuf/RepeatedFieldBuilder.isEmpty:()Z
     122: ifeq          177
     125: aload_0
     126: getfield      #37                 // Field liveServersBuilder_:Lcom/google/protobuf/RepeatedFieldBuilder;
     129: invokevirtual #79                 // Method com/google/protobuf/RepeatedFieldBuilder.dispose:()V
     132: aload_0
     133: aconst_null
     134: putfield      #37                 // Field liveServersBuilder_:Lcom/google/protobuf/RepeatedFieldBuilder;
     137: aload_0
     138: aload_1
     139: invokestatic  #73                 // Method org/apache/hadoop/hbase/protobuf/generated/ClusterStatusProtos$ClusterStatus.access$13500:(Lorg/apache/hadoop/hbase/protobuf/generated/ClusterStatusProtos$ClusterStatus;)Ljava/util/List;
     142: putfield      #12                 // Field liveServers_:Ljava/util/List;
     145: aload_0
     146: aload_0
     147: getfield      #36                 // Field bitField0_:I
     150: bipush        -3
     152: iand
     153: putfield      #36                 // Field bitField0_:I
     156: aload_0
     157: invokestatic  #80                 // Method org/apache/hadoop/hbase/protobuf/generated/ClusterStatusProtos$ClusterStatus.access$14400:()Z
     160: ifeq          170
     163: aload_0
     164: invokespecial #25                 // Method getLiveServersFieldBuilder:()Lcom/google/protobuf/RepeatedFieldBuilder;
     167: goto          171
     170: aconst_null
     171: putfield      #37                 // Field liveServersBuilder_:Lcom/google/protobuf/RepeatedFieldBuilder;
     174: goto          189
     177: aload_0
     178: getfield      #37                 // Field liveServersBuilder_:Lcom/google/protobuf/RepeatedFieldBuilder;
     181: aload_1
     182: invokestatic  #73                 // Method org/apache/hadoop/hbase/protobuf/generated/ClusterStatusProtos$ClusterStatus.access$13500:(Lorg/apache/hadoop/hbase/protobuf/generated/ClusterStatusProtos$ClusterStatus;)Ljava/util/List;
     185: invokevirtual #81                 // Method com/google/protobuf/RepeatedFieldBuilder.addAllMessages:(Ljava/lang/Iterable;)Lcom/google/protobuf/RepeatedFieldBuilder;
     188: pop
     189: aload_0
     190: getfield      #39                 // Field deadServersBuilder_:Lcom/google/protobuf/RepeatedFieldBuilder;
     193: ifnonnull     267
     196: aload_1
     197: invokestatic  #82                 // Method org/apache/hadoop/hbase/protobuf/generated/ClusterStatusProtos$ClusterStatus.access$13600:(Lorg/apache/hadoop/hbase/protobuf/generated/ClusterStatusProtos$ClusterStatus;)Ljava/util/List;
     200: invokeinterface #74,  1           // InterfaceMethod java/util/List.isEmpty:()Z
     205: ifne          353
     208: aload_0
     209: getfield      #13                 // Field deadServers_:Ljava/util/List;
     212: invokeinterface #74,  1           // InterfaceMethod java/util/List.isEmpty:()Z
     217: ifeq          242
     220: aload_0
     221: aload_1
     222: invokestatic  #82                 // Method org/apache/hadoop/hbase/protobuf/generated/ClusterStatusProtos$ClusterStatus.access$13600:(Lorg/apache/hadoop/hbase/protobuf/generated/ClusterStatusProtos$ClusterStatus;)Ljava/util/List;
     225: putfield      #13                 // Field deadServers_:Ljava/util/List;
     228: aload_0
     229: aload_0
     230: getfield      #36                 // Field bitField0_:I
     233: bipush        -5
     235: iand
     236: putfield      #36                 // Field bitField0_:I
     239: goto          260
     242: aload_0
     243: invokespecial #83                 // Method ensureDeadServersIsMutable:()V
     246: aload_0
     247: getfield      #13                 // Field deadServers_:Ljava/util/List;
     250: aload_1
     251: invokestatic  #82                 // Method org/apache/hadoop/hbase/protobuf/generated/ClusterStatusProtos$ClusterStatus.access$13600:(Lorg/apache/hadoop/hbase/protobuf/generated/ClusterStatusProtos$ClusterStatus;)Ljava/util/List;
     254: invokeinterface #76,  2           // InterfaceMethod java/util/List.addAll:(Ljava/util/Collection;)Z
     259: pop
     260: aload_0
     261: invokevirtual #77                 // Method onChanged:()V
     264: goto          353
     267: aload_1
     268: invokestatic  #82                 // Method org/apache/hadoop/hbase/protobuf/generated/ClusterStatusProtos$ClusterStatus.access$13600:(Lorg/apache/hadoop/hbase/protobuf/generated/ClusterStatusProtos$ClusterStatus;)Ljava/util/List;
     271: invokeinterface #74,  1           // InterfaceMethod java/util/List.isEmpty:()Z
     276: ifne          353
     279: aload_0
     280: getfield      #39                 // Field deadServersBuilder_:Lcom/google/protobuf/RepeatedFieldBuilder;
     283: invokevirtual #78                 // Method com/google/protobuf/RepeatedFieldBuilder.isEmpty:()Z
     286: ifeq          341
     289: aload_0
     290: getfield      #39                 // Field deadServersBuilder_:Lcom/google/protobuf/RepeatedFieldBuilder;
     293: invokevirtual #79                 // Method com/google/protobuf/RepeatedFieldBuilder.dispose:()V
     296: aload_0
     297: aconst_null
     298: putfield      #39                 // Field deadServersBuilder_:Lcom/google/protobuf/RepeatedFieldBuilder;
     301: aload_0
     302: aload_1
     303: invokestatic  #82                 // Method org/apache/hadoop/hbase/protobuf/generated/ClusterStatusProtos$ClusterStatus.access$13600:(Lorg/apache/hadoop/hbase/protobuf/generated/ClusterStatusProtos$ClusterStatus;)Ljava/util/List;
     306: putfield      #13                 // Field deadServers_:Ljava/util/List;
     309: aload_0
     310: aload_0
     311: getfield      #36                 // Field bitField0_:I
     314: bipush        -5
     316: iand
     317: putfield      #36                 // Field bitField0_:I
     320: aload_0
     321: invokestatic  #84                 // Method org/apache/hadoop/hbase/protobuf/generated/ClusterStatusProtos$ClusterStatus.access$14500:()Z
     324: ifeq          334
     327: aload_0
     328: invokespecial #26                 // Method getDeadServersFieldBuilder:()Lcom/google/protobuf/RepeatedFieldBuilder;
     331: goto          335
     334: aconst_null
     335: putfield      #39                 // Field deadServersBuilder_:Lcom/google/protobuf/RepeatedFieldBuilder;
     338: goto          353
     341: aload_0
     342: getfield      #39                 // Field deadServersBuilder_:Lcom/google/protobuf/RepeatedFieldBuilder;
     345: aload_1
     346: invokestatic  #82                 // Method org/apache/hadoop/hbase/protobuf/generated/ClusterStatusProtos$ClusterStatus.access$13600:(Lorg/apache/hadoop/hbase/protobuf/generated/ClusterStatusProtos$ClusterStatus;)Ljava/util/List;
     349: invokevirtual #81                 // Method com/google/protobuf/RepeatedFieldBuilder.addAllMessages:(Ljava/lang/Iterable;)Lcom/google/protobuf/RepeatedFieldBuilder;
     352: pop
     353: aload_0
     354: getfield      #40                 // Field regionsInTransitionBuilder_:Lcom/google/protobuf/RepeatedFieldBuilder;
     357: ifnonnull     431
     360: aload_1
     361: invokestatic  #85                 // Method org/apache/hadoop/hbase/protobuf/generated/ClusterStatusProtos$ClusterStatus.access$13700:(Lorg/apache/hadoop/hbase/protobuf/generated/ClusterStatusProtos$ClusterStatus;)Ljava/util/List;
     364: invokeinterface #74,  1           // InterfaceMethod java/util/List.isEmpty:()Z
     369: ifne          517
     372: aload_0
     373: getfield      #14                 // Field regionsInTransition_:Ljava/util/List;
     376: invokeinterface #74,  1           // InterfaceMethod java/util/List.isEmpty:()Z
     381: ifeq          406
     384: aload_0
     385: aload_1
     386: invokestatic  #85                 // Method org/apache/hadoop/hbase/protobuf/generated/ClusterStatusProtos$ClusterStatus.access$13700:(Lorg/apache/hadoop/hbase/protobuf/generated/ClusterStatusProtos$ClusterStatus;)Ljava/util/List;
     389: putfield      #14                 // Field regionsInTransition_:Ljava/util/List;
     392: aload_0
     393: aload_0
     394: getfield      #36                 // Field bitField0_:I
     397: bipush        -9
     399: iand
     400: putfield      #36                 // Field bitField0_:I
     403: goto          424
     406: aload_0
     407: invokespecial #86                 // Method ensureRegionsInTransitionIsMutable:()V
     410: aload_0
     411: getfield      #14                 // Field regionsInTransition_:Ljava/util/List;
     414: aload_1
     415: invokestatic  #85                 // Method org/apache/hadoop/hbase/protobuf/generated/ClusterStatusProtos$ClusterStatus.access$13700:(Lorg/apache/hadoop/hbase/protobuf/generated/ClusterStatusProtos$ClusterStatus;)Ljava/util/List;
     418: invokeinterface #76,  2           // InterfaceMethod java/util/List.addAll:(Ljava/util/Collection;)Z
     423: pop
     424: aload_0
     425: invokevirtual #77                 // Method onChanged:()V
     428: goto          517
     431: aload_1
     432: invokestatic  #85                 // Method org/apache/hadoop/hbase/protobuf/generated/ClusterStatusProtos$ClusterStatus.access$13700:(Lorg/apache/hadoop/hbase/protobuf/generated/ClusterStatusProtos$ClusterStatus;)Ljava/util/List;
     435: invokeinterface #74,  1           // InterfaceMethod java/util/List.isEmpty:()Z
     440: ifne          517
     443: aload_0
     444: getfield      #40                 // Field regionsInTransitionBuilder_:Lcom/google/protobuf/RepeatedFieldBuilder;
     447: invokevirtual #78                 // Method com/google/protobuf/RepeatedFieldBuilder.isEmpty:()Z
     450: ifeq          505
     453: aload_0
     454: getfield      #40                 // Field regionsInTransitionBuilder_:Lcom/google/protobuf/RepeatedFieldBuilder;
     457: invokevirtual #79                 // Method com/google/protobuf/RepeatedFieldBuilder.dispose:()V
     460: aload_0
     461: aconst_null
     462: putfield      #40                 // Field regionsInTransitionBuilder_:Lcom/google/protobuf/RepeatedFieldBuilder;
     465: aload_0
     466: aload_1
     467: invokestatic  #85                 // Method org/apache/hadoop/hbase/protobuf/generated/ClusterStatusProtos$ClusterStatus.access$13700:(Lorg/apache/hadoop/hbase/protobuf/generated/ClusterStatusProtos$ClusterStatus;)Ljava/util/List;
     470: putfield      #14                 // Field regionsInTransition_:Ljava/util/List;
     473: aload_0
     474: aload_0
     475: getfield      #36                 // Field bitField0_:I
     478: bipush        -9
     480: iand
     481: putfield      #36                 // Field bitField0_:I
     484: aload_0
     485: invokestatic  #87                 // Method org/apache/hadoop/hbase/protobuf/generated/ClusterStatusProtos$ClusterStatus.access$14600:()Z
     488: ifeq          498
     491: aload_0
     492: invokespecial #27                 // Method getRegionsInTransitionFieldBuilder:()Lcom/google/protobuf/RepeatedFieldBuilder;
     495: goto          499
     498: aconst_null
     499: putfield      #40                 // Field regionsInTransitionBuilder_:Lcom/google/protobuf/RepeatedFieldBuilder;
     502: goto          517
     505: aload_0
     506: getfield      #40                 // Field regionsInTransitionBuilder_:Lcom/google/protobuf/RepeatedFieldBuilder;
     509: aload_1
     510: invokestatic  #85                 // Method org/apache/hadoop/hbase/protobuf/generated/ClusterStatusProtos$ClusterStatus.access$13700:(Lorg/apache/hadoop/hbase/protobuf/generated/ClusterStatusProtos$ClusterStatus;)Ljava/util/List;
     513: invokevirtual #81                 // Method com/google/protobuf/RepeatedFieldBuilder.addAllMessages:(Ljava/lang/Iterable;)Lcom/google/protobuf/RepeatedFieldBuilder;
     516: pop
     517: aload_1
     518: invokevirtual #88                 // Method org/apache/hadoop/hbase/protobuf/generated/ClusterStatusProtos$ClusterStatus.hasClusterId:()Z
     521: ifeq          533
     524: aload_0
     525: aload_1
     526: invokevirtual #89                 // Method org/apache/hadoop/hbase/protobuf/generated/ClusterStatusProtos$ClusterStatus.getClusterId:()Lorg/apache/hadoop/hbase/protobuf/generated/ClusterIdProtos$ClusterId;
     529: invokevirtual #90                 // Method mergeClusterId:(Lorg/apache/hadoop/hbase/protobuf/generated/ClusterIdProtos$ClusterId;)Lorg/apache/hadoop/hbase/protobuf/generated/ClusterStatusProtos$ClusterStatus$Builder;
     532: pop
     533: aload_0
     534: getfield      #42                 // Field masterCoprocessorsBuilder_:Lcom/google/protobuf/RepeatedFieldBuilder;
     537: ifnonnull     611
     540: aload_1
     541: invokestatic  #91                 // Method org/apache/hadoop/hbase/protobuf/generated/ClusterStatusProtos$ClusterStatus.access$13900:(Lorg/apache/hadoop/hbase/protobuf/generated/ClusterStatusProtos$ClusterStatus;)Ljava/util/List;
     544: invokeinterface #74,  1           // InterfaceMethod java/util/List.isEmpty:()Z
     549: ifne          697
     552: aload_0
     553: getfield      #17                 // Field masterCoprocessors_:Ljava/util/List;
     556: invokeinterface #74,  1           // InterfaceMethod java/util/List.isEmpty:()Z
     561: ifeq          586
     564: aload_0
     565: aload_1
     566: invokestatic  #91                 // Method org/apache/hadoop/hbase/protobuf/generated/ClusterStatusProtos$ClusterStatus.access$13900:(Lorg/apache/hadoop/hbase/protobuf/generated/ClusterStatusProtos$ClusterStatus;)Ljava/util/List;
     569: putfield      #17                 // Field masterCoprocessors_:Ljava/util/List;
     572: aload_0
     573: aload_0
     574: getfield      #36                 // Field bitField0_:I
     577: bipush        -33
     579: iand
     580: putfield      #36                 // Field bitField0_:I
     583: goto          604
     586: aload_0
     587: invokespecial #92                 // Method ensureMasterCoprocessorsIsMutable:()V
     590: aload_0
     591: getfield      #17                 // Field masterCoprocessors_:Ljava/util/List;
     594: aload_1
     595: invokestatic  #91                 // Method org/apache/hadoop/hbase/protobuf/generated/ClusterStatusProtos$ClusterStatus.access$13900:(Lorg/apache/hadoop/hbase/protobuf/generated/ClusterStatusProtos$ClusterStatus;)Ljava/util/List;
     598: invokeinterface #76,  2           // InterfaceMethod java/util/List.addAll:(Ljava/util/Collection;)Z
     603: pop
     604: aload_0
     605: invokevirtual #77                 // Method onChanged:()V
     608: goto          697
     611: aload_1
     612: invokestatic  #91                 // Method org/apache/hadoop/hbase/protobuf/generated/ClusterStatusProtos$ClusterStatus.access$13900:(Lorg/apache/hadoop/hbase/protobuf/generated/ClusterStatusProtos$ClusterStatus;)Ljava/util/List;
     615: invokeinterface #74,  1           // InterfaceMethod java/util/List.isEmpty:()Z
     620: ifne          697
     623: aload_0
     624: getfield      #42                 // Field masterCoprocessorsBuilder_:Lcom/google/protobuf/RepeatedFieldBuilder;
     627: invokevirtual #78                 // Method com/google/protobuf/RepeatedFieldBuilder.isEmpty:()Z
     630: ifeq          685
     633: aload_0
     634: getfield      #42                 // Field masterCoprocessorsBuilder_:Lcom/google/protobuf/RepeatedFieldBuilder;
     637: invokevirtual #79                 // Method com/google/protobuf/RepeatedFieldBuilder.dispose:()V
     640: aload_0
     641: aconst_null
     642: putfield      #42                 // Field masterCoprocessorsBuilder_:Lcom/google/protobuf/RepeatedFieldBuilder;
     645: aload_0
     646: aload_1
     647: invokestatic  #91                 // Method org/apache/hadoop/hbase/protobuf/generated/ClusterStatusProtos$ClusterStatus.access$13900:(Lorg/apache/hadoop/hbase/protobuf/generated/ClusterStatusProtos$ClusterStatus;)Ljava/util/List;
     650: putfield      #17                 // Field masterCoprocessors_:Ljava/util/List;
     653: aload_0
     654: aload_0
     655: getfield      #36                 // Field bitField0_:I
     658: bipush        -33
     660: iand
     661: putfield      #36                 // Field bitField0_:I
     664: aload_0
     665: invokestatic  #93                 // Method org/apache/hadoop/hbase/protobuf/generated/ClusterStatusProtos$ClusterStatus.access$14700:()Z
     668: ifeq          678
     671: aload_0
     672: invokespecial #29                 // Method getMasterCoprocessorsFieldBuilder:()Lcom/google/protobuf/RepeatedFieldBuilder;
     675: goto          679
     678: aconst_null
     679: putfield      #42                 // Field masterCoprocessorsBuilder_:Lcom/google/protobuf/RepeatedFieldBuilder;
     682: goto          697
     685: aload_0
     686: getfield      #42                 // Field masterCoprocessorsBuilder_:Lcom/google/protobuf/RepeatedFieldBuilder;
     689: aload_1
     690: invokestatic  #91                 // Method org/apache/hadoop/hbase/protobuf/generated/ClusterStatusProtos$ClusterStatus.access$13900:(Lorg/apache/hadoop/hbase/protobuf/generated/ClusterStatusProtos$ClusterStatus;)Ljava/util/List;
     693: invokevirtual #81                 // Method com/google/protobuf/RepeatedFieldBuilder.addAllMessages:(Ljava/lang/Iterable;)Lcom/google/protobuf/RepeatedFieldBuilder;
     696: pop
     697: aload_1
     698: invokevirtual #94                 // Method org/apache/hadoop/hbase/protobuf/generated/ClusterStatusProtos$ClusterStatus.hasMaster:()Z
     701: ifeq          713
     704: aload_0
     705: aload_1
     706: invokevirtual #95                 // Method org/apache/hadoop/hbase/protobuf/generated/ClusterStatusProtos$ClusterStatus.getMaster:()Lorg/apache/hadoop/hbase/protobuf/generated/HBaseProtos$ServerName;
     709: invokevirtual #96                 // Method mergeMaster:(Lorg/apache/hadoop/hbase/protobuf/generated/HBaseProtos$ServerName;)Lorg/apache/hadoop/hbase/protobuf/generated/ClusterStatusProtos$ClusterStatus$Builder;
     712: pop
     713: aload_0
     714: getfield      #44                 // Field backupMastersBuilder_:Lcom/google/protobuf/RepeatedFieldBuilder;
     717: ifnonnull     792
     720: aload_1
     721: invokestatic  #97                 // Method org/apache/hadoop/hbase/protobuf/generated/ClusterStatusProtos$ClusterStatus.access$14100:(Lorg/apache/hadoop/hbase/protobuf/generated/ClusterStatusProtos$ClusterStatus;)Ljava/util/List;
     724: invokeinterface #74,  1           // InterfaceMethod java/util/List.isEmpty:()Z
     729: ifne          879
     732: aload_0
     733: getfield      #20                 // Field backupMasters_:Ljava/util/List;
     736: invokeinterface #74,  1           // InterfaceMethod java/util/List.isEmpty:()Z
     741: ifeq          767
     744: aload_0
     745: aload_1
     746: invokestatic  #97                 // Method org/apache/hadoop/hbase/protobuf/generated/ClusterStatusProtos$ClusterStatus.access$14100:(Lorg/apache/hadoop/hbase/protobuf/generated/ClusterStatusProtos$ClusterStatus;)Ljava/util/List;
     749: putfield      #20                 // Field backupMasters_:Ljava/util/List;
     752: aload_0
     753: aload_0
     754: getfield      #36                 // Field bitField0_:I
     757: sipush        -129
     760: iand
     761: putfield      #36                 // Field bitField0_:I
     764: goto          785
     767: aload_0
     768: invokespecial #98                 // Method ensureBackupMastersIsMutable:()V
     771: aload_0
     772: getfield      #20                 // Field backupMasters_:Ljava/util/List;
     775: aload_1
     776: invokestatic  #97                 // Method org/apache/hadoop/hbase/protobuf/generated/ClusterStatusProtos$ClusterStatus.access$14100:(Lorg/apache/hadoop/hbase/protobuf/generated/ClusterStatusProtos$ClusterStatus;)Ljava/util/List;
     779: invokeinterface #76,  2           // InterfaceMethod java/util/List.addAll:(Ljava/util/Collection;)Z
     784: pop
     785: aload_0
     786: invokevirtual #77                 // Method onChanged:()V
     789: goto          879
     792: aload_1
     793: invokestatic  #97                 // Method org/apache/hadoop/hbase/protobuf/generated/ClusterStatusProtos$ClusterStatus.access$14100:(Lorg/apache/hadoop/hbase/protobuf/generated/ClusterStatusProtos$ClusterStatus;)Ljava/util/List;
     796: invokeinterface #74,  1           // InterfaceMethod java/util/List.isEmpty:()Z
     801: ifne          879
     804: aload_0
     805: getfield      #44                 // Field backupMastersBuilder_:Lcom/google/protobuf/RepeatedFieldBuilder;
     808: invokevirtual #78                 // Method com/google/protobuf/RepeatedFieldBuilder.isEmpty:()Z
     811: ifeq          867
     814: aload_0
     815: getfield      #44                 // Field backupMastersBuilder_:Lcom/google/protobuf/RepeatedFieldBuilder;
     818: invokevirtual #79                 // Method com/google/protobuf/RepeatedFieldBuilder.dispose:()V
     821: aload_0
     822: aconst_null
     823: putfield      #44                 // Field backupMastersBuilder_:Lcom/google/protobuf/RepeatedFieldBuilder;
     826: aload_0
     827: aload_1
     828: invokestatic  #97                 // Method org/apache/hadoop/hbase/protobuf/generated/ClusterStatusProtos$ClusterStatus.access$14100:(Lorg/apache/hadoop/hbase/protobuf/generated/ClusterStatusProtos$ClusterStatus;)Ljava/util/List;
     831: putfield      #20                 // Field backupMasters_:Ljava/util/List;
     834: aload_0
     835: aload_0
     836: getfield      #36                 // Field bitField0_:I
     839: sipush        -129
     842: iand
     843: putfield      #36                 // Field bitField0_:I
     846: aload_0
     847: invokestatic  #99                 // Method org/apache/hadoop/hbase/protobuf/generated/ClusterStatusProtos$ClusterStatus.access$14800:()Z
     850: ifeq          860
     853: aload_0
     854: invokespecial #31                 // Method getBackupMastersFieldBuilder:()Lcom/google/protobuf/RepeatedFieldBuilder;
     857: goto          861
     860: aconst_null
     861: putfield      #44                 // Field backupMastersBuilder_:Lcom/google/protobuf/RepeatedFieldBuilder;
     864: goto          879
     867: aload_0
     868: getfield      #44                 // Field backupMastersBuilder_:Lcom/google/protobuf/RepeatedFieldBuilder;
     871: aload_1
     872: invokestatic  #97                 // Method org/apache/hadoop/hbase/protobuf/generated/ClusterStatusProtos$ClusterStatus.access$14100:(Lorg/apache/hadoop/hbase/protobuf/generated/ClusterStatusProtos$ClusterStatus;)Ljava/util/List;
     875: invokevirtual #81                 // Method com/google/protobuf/RepeatedFieldBuilder.addAllMessages:(Ljava/lang/Iterable;)Lcom/google/protobuf/RepeatedFieldBuilder;
     878: pop
     879: aload_1
     880: invokevirtual #100                // Method org/apache/hadoop/hbase/protobuf/generated/ClusterStatusProtos$ClusterStatus.hasBalancerOn:()Z
     883: ifeq          895
     886: aload_0
     887: aload_1
     888: invokevirtual #101                // Method org/apache/hadoop/hbase/protobuf/generated/ClusterStatusProtos$ClusterStatus.getBalancerOn:()Z
     891: invokevirtual #102                // Method setBalancerOn:(Z)Lorg/apache/hadoop/hbase/protobuf/generated/ClusterStatusProtos$ClusterStatus$Builder;
     894: pop
     895: aload_0
     896: aload_1
     897: invokevirtual #103                // Method org/apache/hadoop/hbase/protobuf/generated/ClusterStatusProtos$ClusterStatus.getUnknownFields:()Lcom/google/protobuf/UnknownFieldSet;
     900: invokevirtual #104                // Method mergeUnknownFields:(Lcom/google/protobuf/UnknownFieldSet;)Lcom/google/protobuf/GeneratedMessage$Builder;
     903: pop
     904: aload_0
     905: areturn

  public final boolean isInitialized();
    Code:
       0: aload_0
       1: invokevirtual #105                // Method hasHbaseVersion:()Z
       4: ifeq          19
       7: aload_0
       8: invokevirtual #106                // Method getHbaseVersion:()Lorg/apache/hadoop/hbase/protobuf/generated/FSProtos$HBaseVersionFileContent;
      11: invokevirtual #107                // Method org/apache/hadoop/hbase/protobuf/generated/FSProtos$HBaseVersionFileContent.isInitialized:()Z
      14: ifne          19
      17: iconst_0
      18: ireturn
      19: iconst_0
      20: istore_1
      21: iload_1
      22: aload_0
      23: invokevirtual #108                // Method getLiveServersCount:()I
      26: if_icmpge     48
      29: aload_0
      30: iload_1
      31: invokevirtual #109                // Method getLiveServers:(I)Lorg/apache/hadoop/hbase/protobuf/generated/ClusterStatusProtos$LiveServerInfo;
      34: invokevirtual #110                // Method org/apache/hadoop/hbase/protobuf/generated/ClusterStatusProtos$LiveServerInfo.isInitialized:()Z
      37: ifne          42
      40: iconst_0
      41: ireturn
      42: iinc          1, 1
      45: goto          21
      48: iconst_0
      49: istore_1
      50: iload_1
      51: aload_0
      52: invokevirtual #111                // Method getDeadServersCount:()I
      55: if_icmpge     77
      58: aload_0
      59: iload_1
      60: invokevirtual #112                // Method getDeadServers:(I)Lorg/apache/hadoop/hbase/protobuf/generated/HBaseProtos$ServerName;
      63: invokevirtual #113                // Method org/apache/hadoop/hbase/protobuf/generated/HBaseProtos$ServerName.isInitialized:()Z
      66: ifne          71
      69: iconst_0
      70: ireturn
      71: iinc          1, 1
      74: goto          50
      77: iconst_0
      78: istore_1
      79: iload_1
      80: aload_0
      81: invokevirtual #114                // Method getRegionsInTransitionCount:()I
      84: if_icmpge     106
      87: aload_0
      88: iload_1
      89: invokevirtual #115                // Method getRegionsInTransition:(I)Lorg/apache/hadoop/hbase/protobuf/generated/ClusterStatusProtos$RegionInTransition;
      92: invokevirtual #116                // Method org/apache/hadoop/hbase/protobuf/generated/ClusterStatusProtos$RegionInTransition.isInitialized:()Z
      95: ifne          100
      98: iconst_0
      99: ireturn
     100: iinc          1, 1
     103: goto          79
     106: aload_0
     107: invokevirtual #117                // Method hasClusterId:()Z
     110: ifeq          125
     113: aload_0
     114: invokevirtual #118                // Method getClusterId:()Lorg/apache/hadoop/hbase/protobuf/generated/ClusterIdProtos$ClusterId;
     117: invokevirtual #119                // Method org/apache/hadoop/hbase/protobuf/generated/ClusterIdProtos$ClusterId.isInitialized:()Z
     120: ifne          125
     123: iconst_0
     124: ireturn
     125: iconst_0
     126: istore_1
     127: iload_1
     128: aload_0
     129: invokevirtual #120                // Method getMasterCoprocessorsCount:()I
     132: if_icmpge     154
     135: aload_0
     136: iload_1
     137: invokevirtual #121                // Method getMasterCoprocessors:(I)Lorg/apache/hadoop/hbase/protobuf/generated/HBaseProtos$Coprocessor;
     140: invokevirtual #122                // Method org/apache/hadoop/hbase/protobuf/generated/HBaseProtos$Coprocessor.isInitialized:()Z
     143: ifne          148
     146: iconst_0
     147: ireturn
     148: iinc          1, 1
     151: goto          127
     154: aload_0
     155: invokevirtual #123                // Method hasMaster:()Z
     158: ifeq          173
     161: aload_0
     162: invokevirtual #124                // Method getMaster:()Lorg/apache/hadoop/hbase/protobuf/generated/HBaseProtos$ServerName;
     165: invokevirtual #113                // Method org/apache/hadoop/hbase/protobuf/generated/HBaseProtos$ServerName.isInitialized:()Z
     168: ifne          173
     171: iconst_0
     172: ireturn
     173: iconst_0
     174: istore_1
     175: iload_1
     176: aload_0
     177: invokevirtual #125                // Method getBackupMastersCount:()I
     180: if_icmpge     202
     183: aload_0
     184: iload_1
     185: invokevirtual #126                // Method getBackupMasters:(I)Lorg/apache/hadoop/hbase/protobuf/generated/HBaseProtos$ServerName;
     188: invokevirtual #113                // Method org/apache/hadoop/hbase/protobuf/generated/HBaseProtos$ServerName.isInitialized:()Z
     191: ifne          196
     194: iconst_0
     195: ireturn
     196: iinc          1, 1
     199: goto          175
     202: iconst_1
     203: ireturn

  public org.apache.hadoop.hbase.protobuf.generated.ClusterStatusProtos$ClusterStatus$Builder mergeFrom(com.google.protobuf.CodedInputStream, com.google.protobuf.ExtensionRegistryLite) throws java.io.IOException;
    Code:
       0: aconst_null
       1: astore_3
       2: getstatic     #127                // Field org/apache/hadoop/hbase/protobuf/generated/ClusterStatusProtos$ClusterStatus.PARSER:Lcom/google/protobuf/Parser;
       5: aload_1
       6: aload_2
       7: invokeinterface #128,  3          // InterfaceMethod com/google/protobuf/Parser.parsePartialFrom:(Lcom/google/protobuf/CodedInputStream;Lcom/google/protobuf/ExtensionRegistryLite;)Ljava/lang/Object;
      12: checkcast     #5                  // class org/apache/hadoop/hbase/protobuf/generated/ClusterStatusProtos$ClusterStatus
      15: astore_3
      16: aload_3
      17: ifnull        58
      20: aload_0
      21: aload_3
      22: invokevirtual #47                 // Method mergeFrom:(Lorg/apache/hadoop/hbase/protobuf/generated/ClusterStatusProtos$ClusterStatus;)Lorg/apache/hadoop/hbase/protobuf/generated/ClusterStatusProtos$ClusterStatus$Builder;
      25: pop
      26: goto          58
      29: astore        4
      31: aload         4
      33: invokevirtual #130                // Method com/google/protobuf/InvalidProtocolBufferException.getUnfinishedMessage:()Lcom/google/protobuf/MessageLite;
      36: checkcast     #5                  // class org/apache/hadoop/hbase/protobuf/generated/ClusterStatusProtos$ClusterStatus
      39: astore_3
      40: aload         4
      42: athrow
      43: astore        5
      45: aload_3
      46: ifnull        55
      49: aload_0
      50: aload_3
      51: invokevirtual #47                 // Method mergeFrom:(Lorg/apache/hadoop/hbase/protobuf/generated/ClusterStatusProtos$ClusterStatus;)Lorg/apache/hadoop/hbase/protobuf/generated/ClusterStatusProtos$ClusterStatus$Builder;
      54: pop
      55: aload         5
      57: athrow
      58: aload_0
      59: areturn
    Exception table:
       from    to  target type
           2    16    29   Class com/google/protobuf/InvalidProtocolBufferException
           2    16    43   any
          29    45    43   any

  public boolean hasHbaseVersion();
    Code:
       0: aload_0
       1: getfield      #36                 // Field bitField0_:I
       4: iconst_1
       5: iand
       6: iconst_1
       7: if_icmpne     14
      10: iconst_1
      11: goto          15
      14: iconst_0
      15: ireturn

  public org.apache.hadoop.hbase.protobuf.generated.FSProtos$HBaseVersionFileContent getHbaseVersion();
    Code:
       0: aload_0
       1: getfield      #34                 // Field hbaseVersionBuilder_:Lcom/google/protobuf/SingleFieldBuilder;
       4: ifnonnull     12
       7: aload_0
       8: getfield      #10                 // Field hbaseVersion_:Lorg/apache/hadoop/hbase/protobuf/generated/FSProtos$HBaseVersionFileContent;
      11: areturn
      12: aload_0
      13: getfield      #34                 // Field hbaseVersionBuilder_:Lcom/google/protobuf/SingleFieldBuilder;
      16: invokevirtual #131                // Method com/google/protobuf/SingleFieldBuilder.getMessage:()Lcom/google/protobuf/GeneratedMessage;
      19: checkcast     #54                 // class org/apache/hadoop/hbase/protobuf/generated/FSProtos$HBaseVersionFileContent
      22: areturn

  public org.apache.hadoop.hbase.protobuf.generated.ClusterStatusProtos$ClusterStatus$Builder setHbaseVersion(org.apache.hadoop.hbase.protobuf.generated.FSProtos$HBaseVersionFileContent);
    Code:
       0: aload_0
       1: getfield      #34                 // Field hbaseVersionBuilder_:Lcom/google/protobuf/SingleFieldBuilder;
       4: ifnonnull     31
       7: aload_1
       8: ifnonnull     19
      11: new           #132                // class java/lang/NullPointerException
      14: dup
      15: invokespecial #133                // Method java/lang/NullPointerException."<init>":()V
      18: athrow
      19: aload_0
      20: aload_1
      21: putfield      #10                 // Field hbaseVersion_:Lorg/apache/hadoop/hbase/protobuf/generated/FSProtos$HBaseVersionFileContent;
      24: aload_0
      25: invokevirtual #77                 // Method onChanged:()V
      28: goto          40
      31: aload_0
      32: getfield      #34                 // Field hbaseVersionBuilder_:Lcom/google/protobuf/SingleFieldBuilder;
      35: aload_1
      36: invokevirtual #134                // Method com/google/protobuf/SingleFieldBuilder.setMessage:(Lcom/google/protobuf/GeneratedMessage;)Lcom/google/protobuf/SingleFieldBuilder;
      39: pop
      40: aload_0
      41: dup
      42: getfield      #36                 // Field bitField0_:I
      45: iconst_1
      46: ior
      47: putfield      #36                 // Field bitField0_:I
      50: aload_0
      51: areturn

  public org.apache.hadoop.hbase.protobuf.generated.ClusterStatusProtos$ClusterStatus$Builder setHbaseVersion(org.apache.hadoop.hbase.protobuf.generated.FSProtos$HBaseVersionFileContent$Builder);
    Code:
       0: aload_0
       1: getfield      #34                 // Field hbaseVersionBuilder_:Lcom/google/protobuf/SingleFieldBuilder;
       4: ifnonnull     22
       7: aload_0
       8: aload_1
       9: invokevirtual #135                // Method org/apache/hadoop/hbase/protobuf/generated/FSProtos$HBaseVersionFileContent$Builder.build:()Lorg/apache/hadoop/hbase/protobuf/generated/FSProtos$HBaseVersionFileContent;
      12: putfield      #10                 // Field hbaseVersion_:Lorg/apache/hadoop/hbase/protobuf/generated/FSProtos$HBaseVersionFileContent;
      15: aload_0
      16: invokevirtual #77                 // Method onChanged:()V
      19: goto          34
      22: aload_0
      23: getfield      #34                 // Field hbaseVersionBuilder_:Lcom/google/protobuf/SingleFieldBuilder;
      26: aload_1
      27: invokevirtual #135                // Method org/apache/hadoop/hbase/protobuf/generated/FSProtos$HBaseVersionFileContent$Builder.build:()Lorg/apache/hadoop/hbase/protobuf/generated/FSProtos$HBaseVersionFileContent;
      30: invokevirtual #134                // Method com/google/protobuf/SingleFieldBuilder.setMessage:(Lcom/google/protobuf/GeneratedMessage;)Lcom/google/protobuf/SingleFieldBuilder;
      33: pop
      34: aload_0
      35: dup
      36: getfield      #36                 // Field bitField0_:I
      39: iconst_1
      40: ior
      41: putfield      #36                 // Field bitField0_:I
      44: aload_0
      45: areturn

  public org.apache.hadoop.hbase.protobuf.generated.ClusterStatusProtos$ClusterStatus$Builder mergeHbaseVersion(org.apache.hadoop.hbase.protobuf.generated.FSProtos$HBaseVersionFileContent);
    Code:
       0: aload_0
       1: getfield      #34                 // Field hbaseVersionBuilder_:Lcom/google/protobuf/SingleFieldBuilder;
       4: ifnonnull     60
       7: aload_0
       8: getfield      #36                 // Field bitField0_:I
      11: iconst_1
      12: iand
      13: iconst_1
      14: if_icmpne     48
      17: aload_0
      18: getfield      #10                 // Field hbaseVersion_:Lorg/apache/hadoop/hbase/protobuf/generated/FSProtos$HBaseVersionFileContent;
      21: invokestatic  #9                  // Method org/apache/hadoop/hbase/protobuf/generated/FSProtos$HBaseVersionFileContent.getDefaultInstance:()Lorg/apache/hadoop/hbase/protobuf/generated/FSProtos$HBaseVersionFileContent;
      24: if_acmpeq     48
      27: aload_0
      28: aload_0
      29: getfield      #10                 // Field hbaseVersion_:Lorg/apache/hadoop/hbase/protobuf/generated/FSProtos$HBaseVersionFileContent;
      32: invokestatic  #136                // Method org/apache/hadoop/hbase/protobuf/generated/FSProtos$HBaseVersionFileContent.newBuilder:(Lorg/apache/hadoop/hbase/protobuf/generated/FSProtos$HBaseVersionFileContent;)Lorg/apache/hadoop/hbase/protobuf/generated/FSProtos$HBaseVersionFileContent$Builder;
      35: aload_1
      36: invokevirtual #137                // Method org/apache/hadoop/hbase/protobuf/generated/FSProtos$HBaseVersionFileContent$Builder.mergeFrom:(Lorg/apache/hadoop/hbase/protobuf/generated/FSProtos$HBaseVersionFileContent;)Lorg/apache/hadoop/hbase/protobuf/generated/FSProtos$HBaseVersionFileContent$Builder;
      39: invokevirtual #138                // Method org/apache/hadoop/hbase/protobuf/generated/FSProtos$HBaseVersionFileContent$Builder.buildPartial:()Lorg/apache/hadoop/hbase/protobuf/generated/FSProtos$HBaseVersionFileContent;
      42: putfield      #10                 // Field hbaseVersion_:Lorg/apache/hadoop/hbase/protobuf/generated/FSProtos$HBaseVersionFileContent;
      45: goto          53
      48: aload_0
      49: aload_1
      50: putfield      #10                 // Field hbaseVersion_:Lorg/apache/hadoop/hbase/protobuf/generated/FSProtos$HBaseVersionFileContent;
      53: aload_0
      54: invokevirtual #77                 // Method onChanged:()V
      57: goto          69
      60: aload_0
      61: getfield      #34                 // Field hbaseVersionBuilder_:Lcom/google/protobuf/SingleFieldBuilder;
      64: aload_1
      65: invokevirtual #139                // Method com/google/protobuf/SingleFieldBuilder.mergeFrom:(Lcom/google/protobuf/GeneratedMessage;)Lcom/google/protobuf/SingleFieldBuilder;
      68: pop
      69: aload_0
      70: dup
      71: getfield      #36                 // Field bitField0_:I
      74: iconst_1
      75: ior
      76: putfield      #36                 // Field bitField0_:I
      79: aload_0
      80: areturn

  public org.apache.hadoop.hbase.protobuf.generated.ClusterStatusProtos$ClusterStatus$Builder clearHbaseVersion();
    Code:
       0: aload_0
       1: getfield      #34                 // Field hbaseVersionBuilder_:Lcom/google/protobuf/SingleFieldBuilder;
       4: ifnonnull     21
       7: aload_0
       8: invokestatic  #9                  // Method org/apache/hadoop/hbase/protobuf/generated/FSProtos$HBaseVersionFileContent.getDefaultInstance:()Lorg/apache/hadoop/hbase/protobuf/generated/FSProtos$HBaseVersionFileContent;
      11: putfield      #10                 // Field hbaseVersion_:Lorg/apache/hadoop/hbase/protobuf/generated/FSProtos$HBaseVersionFileContent;
      14: aload_0
      15: invokevirtual #77                 // Method onChanged:()V
      18: goto          29
      21: aload_0
      22: getfield      #34                 // Field hbaseVersionBuilder_:Lcom/google/protobuf/SingleFieldBuilder;
      25: invokevirtual #35                 // Method com/google/protobuf/SingleFieldBuilder.clear:()Lcom/google/protobuf/SingleFieldBuilder;
      28: pop
      29: aload_0
      30: aload_0
      31: getfield      #36                 // Field bitField0_:I
      34: bipush        -2
      36: iand
      37: putfield      #36                 // Field bitField0_:I
      40: aload_0
      41: areturn

  public org.apache.hadoop.hbase.protobuf.generated.FSProtos$HBaseVersionFileContent$Builder getHbaseVersionBuilder();
    Code:
       0: aload_0
       1: dup
       2: getfield      #36                 // Field bitField0_:I
       5: iconst_1
       6: ior
       7: putfield      #36                 // Field bitField0_:I
      10: aload_0
      11: invokevirtual #77                 // Method onChanged:()V
      14: aload_0
      15: invokespecial #24                 // Method getHbaseVersionFieldBuilder:()Lcom/google/protobuf/SingleFieldBuilder;
      18: invokevirtual #140                // Method com/google/protobuf/SingleFieldBuilder.getBuilder:()Lcom/google/protobuf/GeneratedMessage$Builder;
      21: checkcast     #141                // class org/apache/hadoop/hbase/protobuf/generated/FSProtos$HBaseVersionFileContent$Builder
      24: areturn

  public org.apache.hadoop.hbase.protobuf.generated.FSProtos$HBaseVersionFileContentOrBuilder getHbaseVersionOrBuilder();
    Code:
       0: aload_0
       1: getfield      #34                 // Field hbaseVersionBuilder_:Lcom/google/protobuf/SingleFieldBuilder;
       4: ifnull        18
       7: aload_0
       8: getfield      #34                 // Field hbaseVersionBuilder_:Lcom/google/protobuf/SingleFieldBuilder;
      11: invokevirtual #142                // Method com/google/protobuf/SingleFieldBuilder.getMessageOrBuilder:()Lcom/google/protobuf/MessageOrBuilder;
      14: checkcast     #143                // class org/apache/hadoop/hbase/protobuf/generated/FSProtos$HBaseVersionFileContentOrBuilder
      17: areturn
      18: aload_0
      19: getfield      #10                 // Field hbaseVersion_:Lorg/apache/hadoop/hbase/protobuf/generated/FSProtos$HBaseVersionFileContent;
      22: areturn

  public java.util.List<org.apache.hadoop.hbase.protobuf.generated.ClusterStatusProtos$LiveServerInfo> getLiveServersList();
    Code:
       0: aload_0
       1: getfield      #37                 // Field liveServersBuilder_:Lcom/google/protobuf/RepeatedFieldBuilder;
       4: ifnonnull     15
       7: aload_0
       8: getfield      #12                 // Field liveServers_:Ljava/util/List;
      11: invokestatic  #55                 // Method java/util/Collections.unmodifiableList:(Ljava/util/List;)Ljava/util/List;
      14: areturn
      15: aload_0
      16: getfield      #37                 // Field liveServersBuilder_:Lcom/google/protobuf/RepeatedFieldBuilder;
      19: invokevirtual #150                // Method com/google/protobuf/RepeatedFieldBuilder.getMessageList:()Ljava/util/List;
      22: areturn

  public int getLiveServersCount();
    Code:
       0: aload_0
       1: getfield      #37                 // Field liveServersBuilder_:Lcom/google/protobuf/RepeatedFieldBuilder;
       4: ifnonnull     17
       7: aload_0
       8: getfield      #12                 // Field liveServers_:Ljava/util/List;
      11: invokeinterface #151,  1          // InterfaceMethod java/util/List.size:()I
      16: ireturn
      17: aload_0
      18: getfield      #37                 // Field liveServersBuilder_:Lcom/google/protobuf/RepeatedFieldBuilder;
      21: invokevirtual #152                // Method com/google/protobuf/RepeatedFieldBuilder.getCount:()I
      24: ireturn

  public org.apache.hadoop.hbase.protobuf.generated.ClusterStatusProtos$LiveServerInfo getLiveServers(int);
    Code:
       0: aload_0
       1: getfield      #37                 // Field liveServersBuilder_:Lcom/google/protobuf/RepeatedFieldBuilder;
       4: ifnonnull     21
       7: aload_0
       8: getfield      #12                 // Field liveServers_:Ljava/util/List;
      11: iload_1
      12: invokeinterface #153,  2          // InterfaceMethod java/util/List.get:(I)Ljava/lang/Object;
      17: checkcast     #154                // class org/apache/hadoop/hbase/protobuf/generated/ClusterStatusProtos$LiveServerInfo
      20: areturn
      21: aload_0
      22: getfield      #37                 // Field liveServersBuilder_:Lcom/google/protobuf/RepeatedFieldBuilder;
      25: iload_1
      26: invokevirtual #155                // Method com/google/protobuf/RepeatedFieldBuilder.getMessage:(I)Lcom/google/protobuf/GeneratedMessage;
      29: checkcast     #154                // class org/apache/hadoop/hbase/protobuf/generated/ClusterStatusProtos$LiveServerInfo
      32: areturn

  public org.apache.hadoop.hbase.protobuf.generated.ClusterStatusProtos$ClusterStatus$Builder setLiveServers(int, org.apache.hadoop.hbase.protobuf.generated.ClusterStatusProtos$LiveServerInfo);
    Code:
       0: aload_0
       1: getfield      #37                 // Field liveServersBuilder_:Lcom/google/protobuf/RepeatedFieldBuilder;
       4: ifnonnull     42
       7: aload_2
       8: ifnonnull     19
      11: new           #132                // class java/lang/NullPointerException
      14: dup
      15: invokespecial #133                // Method java/lang/NullPointerException."<init>":()V
      18: athrow
      19: aload_0
      20: invokespecial #75                 // Method ensureLiveServersIsMutable:()V
      23: aload_0
      24: getfield      #12                 // Field liveServers_:Ljava/util/List;
      27: iload_1
      28: aload_2
      29: invokeinterface #156,  3          // InterfaceMethod java/util/List.set:(ILjava/lang/Object;)Ljava/lang/Object;
      34: pop
      35: aload_0
      36: invokevirtual #77                 // Method onChanged:()V
      39: goto          52
      42: aload_0
      43: getfield      #37                 // Field liveServersBuilder_:Lcom/google/protobuf/RepeatedFieldBuilder;
      46: iload_1
      47: aload_2
      48: invokevirtual #157                // Method com/google/protobuf/RepeatedFieldBuilder.setMessage:(ILcom/google/protobuf/GeneratedMessage;)Lcom/google/protobuf/RepeatedFieldBuilder;
      51: pop
      52: aload_0
      53: areturn

  public org.apache.hadoop.hbase.protobuf.generated.ClusterStatusProtos$ClusterStatus$Builder setLiveServers(int, org.apache.hadoop.hbase.protobuf.generated.ClusterStatusProtos$LiveServerInfo$Builder);
    Code:
       0: aload_0
       1: getfield      #37                 // Field liveServersBuilder_:Lcom/google/protobuf/RepeatedFieldBuilder;
       4: ifnonnull     33
       7: aload_0
       8: invokespecial #75                 // Method ensureLiveServersIsMutable:()V
      11: aload_0
      12: getfield      #12                 // Field liveServers_:Ljava/util/List;
      15: iload_1
      16: aload_2
      17: invokevirtual #158                // Method org/apache/hadoop/hbase/protobuf/generated/ClusterStatusProtos$LiveServerInfo$Builder.build:()Lorg/apache/hadoop/hbase/protobuf/generated/ClusterStatusProtos$LiveServerInfo;
      20: invokeinterface #156,  3          // InterfaceMethod java/util/List.set:(ILjava/lang/Object;)Ljava/lang/Object;
      25: pop
      26: aload_0
      27: invokevirtual #77                 // Method onChanged:()V
      30: goto          46
      33: aload_0
      34: getfield      #37                 // Field liveServersBuilder_:Lcom/google/protobuf/RepeatedFieldBuilder;
      37: iload_1
      38: aload_2
      39: invokevirtual #158                // Method org/apache/hadoop/hbase/protobuf/generated/ClusterStatusProtos$LiveServerInfo$Builder.build:()Lorg/apache/hadoop/hbase/protobuf/generated/ClusterStatusProtos$LiveServerInfo;
      42: invokevirtual #157                // Method com/google/protobuf/RepeatedFieldBuilder.setMessage:(ILcom/google/protobuf/GeneratedMessage;)Lcom/google/protobuf/RepeatedFieldBuilder;
      45: pop
      46: aload_0
      47: areturn

  public org.apache.hadoop.hbase.protobuf.generated.ClusterStatusProtos$ClusterStatus$Builder addLiveServers(org.apache.hadoop.hbase.protobuf.generated.ClusterStatusProtos$LiveServerInfo);
    Code:
       0: aload_0
       1: getfield      #37                 // Field liveServersBuilder_:Lcom/google/protobuf/RepeatedFieldBuilder;
       4: ifnonnull     41
       7: aload_1
       8: ifnonnull     19
      11: new           #132                // class java/lang/NullPointerException
      14: dup
      15: invokespecial #133                // Method java/lang/NullPointerException."<init>":()V
      18: athrow
      19: aload_0
      20: invokespecial #75                 // Method ensureLiveServersIsMutable:()V
      23: aload_0
      24: getfield      #12                 // Field liveServers_:Ljava/util/List;
      27: aload_1
      28: invokeinterface #159,  2          // InterfaceMethod java/util/List.add:(Ljava/lang/Object;)Z
      33: pop
      34: aload_0
      35: invokevirtual #77                 // Method onChanged:()V
      38: goto          50
      41: aload_0
      42: getfield      #37                 // Field liveServersBuilder_:Lcom/google/protobuf/RepeatedFieldBuilder;
      45: aload_1
      46: invokevirtual #160                // Method com/google/protobuf/RepeatedFieldBuilder.addMessage:(Lcom/google/protobuf/GeneratedMessage;)Lcom/google/protobuf/RepeatedFieldBuilder;
      49: pop
      50: aload_0
      51: areturn

  public org.apache.hadoop.hbase.protobuf.generated.ClusterStatusProtos$ClusterStatus$Builder addLiveServers(int, org.apache.hadoop.hbase.protobuf.generated.ClusterStatusProtos$LiveServerInfo);
    Code:
       0: aload_0
       1: getfield      #37                 // Field liveServersBuilder_:Lcom/google/protobuf/RepeatedFieldBuilder;
       4: ifnonnull     41
       7: aload_2
       8: ifnonnull     19
      11: new           #132                // class java/lang/NullPointerException
      14: dup
      15: invokespecial #133                // Method java/lang/NullPointerException."<init>":()V
      18: athrow
      19: aload_0
      20: invokespecial #75                 // Method ensureLiveServersIsMutable:()V
      23: aload_0
      24: getfield      #12                 // Field liveServers_:Ljava/util/List;
      27: iload_1
      28: aload_2
      29: invokeinterface #161,  3          // InterfaceMethod java/util/List.add:(ILjava/lang/Object;)V
      34: aload_0
      35: invokevirtual #77                 // Method onChanged:()V
      38: goto          51
      41: aload_0
      42: getfield      #37                 // Field liveServersBuilder_:Lcom/google/protobuf/RepeatedFieldBuilder;
      45: iload_1
      46: aload_2
      47: invokevirtual #162                // Method com/google/protobuf/RepeatedFieldBuilder.addMessage:(ILcom/google/protobuf/GeneratedMessage;)Lcom/google/protobuf/RepeatedFieldBuilder;
      50: pop
      51: aload_0
      52: areturn

  public org.apache.hadoop.hbase.protobuf.generated.ClusterStatusProtos$ClusterStatus$Builder addLiveServers(org.apache.hadoop.hbase.protobuf.generated.ClusterStatusProtos$LiveServerInfo$Builder);
    Code:
       0: aload_0
       1: getfield      #37                 // Field liveServersBuilder_:Lcom/google/protobuf/RepeatedFieldBuilder;
       4: ifnonnull     32
       7: aload_0
       8: invokespecial #75                 // Method ensureLiveServersIsMutable:()V
      11: aload_0
      12: getfield      #12                 // Field liveServers_:Ljava/util/List;
      15: aload_1
      16: invokevirtual #158                // Method org/apache/hadoop/hbase/protobuf/generated/ClusterStatusProtos$LiveServerInfo$Builder.build:()Lorg/apache/hadoop/hbase/protobuf/generated/ClusterStatusProtos$LiveServerInfo;
      19: invokeinterface #159,  2          // InterfaceMethod java/util/List.add:(Ljava/lang/Object;)Z
      24: pop
      25: aload_0
      26: invokevirtual #77                 // Method onChanged:()V
      29: goto          44
      32: aload_0
      33: getfield      #37                 // Field liveServersBuilder_:Lcom/google/protobuf/RepeatedFieldBuilder;
      36: aload_1
      37: invokevirtual #158                // Method org/apache/hadoop/hbase/protobuf/generated/ClusterStatusProtos$LiveServerInfo$Builder.build:()Lorg/apache/hadoop/hbase/protobuf/generated/ClusterStatusProtos$LiveServerInfo;
      40: invokevirtual #160                // Method com/google/protobuf/RepeatedFieldBuilder.addMessage:(Lcom/google/protobuf/GeneratedMessage;)Lcom/google/protobuf/RepeatedFieldBuilder;
      43: pop
      44: aload_0
      45: areturn

  public org.apache.hadoop.hbase.protobuf.generated.ClusterStatusProtos$ClusterStatus$Builder addLiveServers(int, org.apache.hadoop.hbase.protobuf.generated.ClusterStatusProtos$LiveServerInfo$Builder);
    Code:
       0: aload_0
       1: getfield      #37                 // Field liveServersBuilder_:Lcom/google/protobuf/RepeatedFieldBuilder;
       4: ifnonnull     32
       7: aload_0
       8: invokespecial #75                 // Method ensureLiveServersIsMutable:()V
      11: aload_0
      12: getfield      #12                 // Field liveServers_:Ljava/util/List;
      15: iload_1
      16: aload_2
      17: invokevirtual #158                // Method org/apache/hadoop/hbase/protobuf/generated/ClusterStatusProtos$LiveServerInfo$Builder.build:()Lorg/apache/hadoop/hbase/protobuf/generated/ClusterStatusProtos$LiveServerInfo;
      20: invokeinterface #161,  3          // InterfaceMethod java/util/List.add:(ILjava/lang/Object;)V
      25: aload_0
      26: invokevirtual #77                 // Method onChanged:()V
      29: goto          45
      32: aload_0
      33: getfield      #37                 // Field liveServersBuilder_:Lcom/google/protobuf/RepeatedFieldBuilder;
      36: iload_1
      37: aload_2
      38: invokevirtual #158                // Method org/apache/hadoop/hbase/protobuf/generated/ClusterStatusProtos$LiveServerInfo$Builder.build:()Lorg/apache/hadoop/hbase/protobuf/generated/ClusterStatusProtos$LiveServerInfo;
      41: invokevirtual #162                // Method com/google/protobuf/RepeatedFieldBuilder.addMessage:(ILcom/google/protobuf/GeneratedMessage;)Lcom/google/protobuf/RepeatedFieldBuilder;
      44: pop
      45: aload_0
      46: areturn

  public org.apache.hadoop.hbase.protobuf.generated.ClusterStatusProtos$ClusterStatus$Builder addAllLiveServers(java.lang.Iterable<? extends org.apache.hadoop.hbase.protobuf.generated.ClusterStatusProtos$LiveServerInfo>);
    Code:
       0: aload_0
       1: getfield      #37                 // Field liveServersBuilder_:Lcom/google/protobuf/RepeatedFieldBuilder;
       4: ifnonnull     26
       7: aload_0
       8: invokespecial #75                 // Method ensureLiveServersIsMutable:()V
      11: aload_1
      12: aload_0
      13: getfield      #12                 // Field liveServers_:Ljava/util/List;
      16: invokestatic  #163                // Method com/google/protobuf/GeneratedMessage$Builder.addAll:(Ljava/lang/Iterable;Ljava/util/Collection;)V
      19: aload_0
      20: invokevirtual #77                 // Method onChanged:()V
      23: goto          35
      26: aload_0
      27: getfield      #37                 // Field liveServersBuilder_:Lcom/google/protobuf/RepeatedFieldBuilder;
      30: aload_1
      31: invokevirtual #81                 // Method com/google/protobuf/RepeatedFieldBuilder.addAllMessages:(Ljava/lang/Iterable;)Lcom/google/protobuf/RepeatedFieldBuilder;
      34: pop
      35: aload_0
      36: areturn

  public org.apache.hadoop.hbase.protobuf.generated.ClusterStatusProtos$ClusterStatus$Builder clearLiveServers();
    Code:
       0: aload_0
       1: getfield      #37                 // Field liveServersBuilder_:Lcom/google/protobuf/RepeatedFieldBuilder;
       4: ifnonnull     32
       7: aload_0
       8: invokestatic  #11                 // Method java/util/Collections.emptyList:()Ljava/util/List;
      11: putfield      #12                 // Field liveServers_:Ljava/util/List;
      14: aload_0
      15: aload_0
      16: getfield      #36                 // Field bitField0_:I
      19: bipush        -3
      21: iand
      22: putfield      #36                 // Field bitField0_:I
      25: aload_0
      26: invokevirtual #77                 // Method onChanged:()V
      29: goto          39
      32: aload_0
      33: getfield      #37                 // Field liveServersBuilder_:Lcom/google/protobuf/RepeatedFieldBuilder;
      36: invokevirtual #38                 // Method com/google/protobuf/RepeatedFieldBuilder.clear:()V
      39: aload_0
      40: areturn

  public org.apache.hadoop.hbase.protobuf.generated.ClusterStatusProtos$ClusterStatus$Builder removeLiveServers(int);
    Code:
       0: aload_0
       1: getfield      #37                 // Field liveServersBuilder_:Lcom/google/protobuf/RepeatedFieldBuilder;
       4: ifnonnull     29
       7: aload_0
       8: invokespecial #75                 // Method ensureLiveServersIsMutable:()V
      11: aload_0
      12: getfield      #12                 // Field liveServers_:Ljava/util/List;
      15: iload_1
      16: invokeinterface #164,  2          // InterfaceMethod java/util/List.remove:(I)Ljava/lang/Object;
      21: pop
      22: aload_0
      23: invokevirtual #77                 // Method onChanged:()V
      26: goto          37
      29: aload_0
      30: getfield      #37                 // Field liveServersBuilder_:Lcom/google/protobuf/RepeatedFieldBuilder;
      33: iload_1
      34: invokevirtual #165                // Method com/google/protobuf/RepeatedFieldBuilder.remove:(I)V
      37: aload_0
      38: areturn

  public org.apache.hadoop.hbase.protobuf.generated.ClusterStatusProtos$LiveServerInfo$Builder getLiveServersBuilder(int);
    Code:
       0: aload_0
       1: invokespecial #25                 // Method getLiveServersFieldBuilder:()Lcom/google/protobuf/RepeatedFieldBuilder;
       4: iload_1
       5: invokevirtual #166                // Method com/google/protobuf/RepeatedFieldBuilder.getBuilder:(I)Lcom/google/protobuf/GeneratedMessage$Builder;
       8: checkcast     #167                // class org/apache/hadoop/hbase/protobuf/generated/ClusterStatusProtos$LiveServerInfo$Builder
      11: areturn

  public org.apache.hadoop.hbase.protobuf.generated.ClusterStatusProtos$LiveServerInfoOrBuilder getLiveServersOrBuilder(int);
    Code:
       0: aload_0
       1: getfield      #37                 // Field liveServersBuilder_:Lcom/google/protobuf/RepeatedFieldBuilder;
       4: ifnonnull     21
       7: aload_0
       8: getfield      #12                 // Field liveServers_:Ljava/util/List;
      11: iload_1
      12: invokeinterface #153,  2          // InterfaceMethod java/util/List.get:(I)Ljava/lang/Object;
      17: checkcast     #168                // class org/apache/hadoop/hbase/protobuf/generated/ClusterStatusProtos$LiveServerInfoOrBuilder
      20: areturn
      21: aload_0
      22: getfield      #37                 // Field liveServersBuilder_:Lcom/google/protobuf/RepeatedFieldBuilder;
      25: iload_1
      26: invokevirtual #169                // Method com/google/protobuf/RepeatedFieldBuilder.getMessageOrBuilder:(I)Lcom/google/protobuf/MessageOrBuilder;
      29: checkcast     #168                // class org/apache/hadoop/hbase/protobuf/generated/ClusterStatusProtos$LiveServerInfoOrBuilder
      32: areturn

  public java.util.List<? extends org.apache.hadoop.hbase.protobuf.generated.ClusterStatusProtos$LiveServerInfoOrBuilder> getLiveServersOrBuilderList();
    Code:
       0: aload_0
       1: getfield      #37                 // Field liveServersBuilder_:Lcom/google/protobuf/RepeatedFieldBuilder;
       4: ifnull        15
       7: aload_0
       8: getfield      #37                 // Field liveServersBuilder_:Lcom/google/protobuf/RepeatedFieldBuilder;
      11: invokevirtual #170                // Method com/google/protobuf/RepeatedFieldBuilder.getMessageOrBuilderList:()Ljava/util/List;
      14: areturn
      15: aload_0
      16: getfield      #12                 // Field liveServers_:Ljava/util/List;
      19: invokestatic  #55                 // Method java/util/Collections.unmodifiableList:(Ljava/util/List;)Ljava/util/List;
      22: areturn

  public org.apache.hadoop.hbase.protobuf.generated.ClusterStatusProtos$LiveServerInfo$Builder addLiveServersBuilder();
    Code:
       0: aload_0
       1: invokespecial #25                 // Method getLiveServersFieldBuilder:()Lcom/google/protobuf/RepeatedFieldBuilder;
       4: invokestatic  #171                // Method org/apache/hadoop/hbase/protobuf/generated/ClusterStatusProtos$LiveServerInfo.getDefaultInstance:()Lorg/apache/hadoop/hbase/protobuf/generated/ClusterStatusProtos$LiveServerInfo;
       7: invokevirtual #172                // Method com/google/protobuf/RepeatedFieldBuilder.addBuilder:(Lcom/google/protobuf/GeneratedMessage;)Lcom/google/protobuf/GeneratedMessage$Builder;
      10: checkcast     #167                // class org/apache/hadoop/hbase/protobuf/generated/ClusterStatusProtos$LiveServerInfo$Builder
      13: areturn

  public org.apache.hadoop.hbase.protobuf.generated.ClusterStatusProtos$LiveServerInfo$Builder addLiveServersBuilder(int);
    Code:
       0: aload_0
       1: invokespecial #25                 // Method getLiveServersFieldBuilder:()Lcom/google/protobuf/RepeatedFieldBuilder;
       4: iload_1
       5: invokestatic  #171                // Method org/apache/hadoop/hbase/protobuf/generated/ClusterStatusProtos$LiveServerInfo.getDefaultInstance:()Lorg/apache/hadoop/hbase/protobuf/generated/ClusterStatusProtos$LiveServerInfo;
       8: invokevirtual #173                // Method com/google/protobuf/RepeatedFieldBuilder.addBuilder:(ILcom/google/protobuf/GeneratedMessage;)Lcom/google/protobuf/GeneratedMessage$Builder;
      11: checkcast     #167                // class org/apache/hadoop/hbase/protobuf/generated/ClusterStatusProtos$LiveServerInfo$Builder
      14: areturn

  public java.util.List<org.apache.hadoop.hbase.protobuf.generated.ClusterStatusProtos$LiveServerInfo$Builder> getLiveServersBuilderList();
    Code:
       0: aload_0
       1: invokespecial #25                 // Method getLiveServersFieldBuilder:()Lcom/google/protobuf/RepeatedFieldBuilder;
       4: invokevirtual #174                // Method com/google/protobuf/RepeatedFieldBuilder.getBuilderList:()Ljava/util/List;
       7: areturn

  public java.util.List<org.apache.hadoop.hbase.protobuf.generated.HBaseProtos$ServerName> getDeadServersList();
    Code:
       0: aload_0
       1: getfield      #39                 // Field deadServersBuilder_:Lcom/google/protobuf/RepeatedFieldBuilder;
       4: ifnonnull     15
       7: aload_0
       8: getfield      #13                 // Field deadServers_:Ljava/util/List;
      11: invokestatic  #55                 // Method java/util/Collections.unmodifiableList:(Ljava/util/List;)Ljava/util/List;
      14: areturn
      15: aload_0
      16: getfield      #39                 // Field deadServersBuilder_:Lcom/google/protobuf/RepeatedFieldBuilder;
      19: invokevirtual #150                // Method com/google/protobuf/RepeatedFieldBuilder.getMessageList:()Ljava/util/List;
      22: areturn

  public int getDeadServersCount();
    Code:
       0: aload_0
       1: getfield      #39                 // Field deadServersBuilder_:Lcom/google/protobuf/RepeatedFieldBuilder;
       4: ifnonnull     17
       7: aload_0
       8: getfield      #13                 // Field deadServers_:Ljava/util/List;
      11: invokeinterface #151,  1          // InterfaceMethod java/util/List.size:()I
      16: ireturn
      17: aload_0
      18: getfield      #39                 // Field deadServersBuilder_:Lcom/google/protobuf/RepeatedFieldBuilder;
      21: invokevirtual #152                // Method com/google/protobuf/RepeatedFieldBuilder.getCount:()I
      24: ireturn

  public org.apache.hadoop.hbase.protobuf.generated.HBaseProtos$ServerName getDeadServers(int);
    Code:
       0: aload_0
       1: getfield      #39                 // Field deadServersBuilder_:Lcom/google/protobuf/RepeatedFieldBuilder;
       4: ifnonnull     21
       7: aload_0
       8: getfield      #13                 // Field deadServers_:Ljava/util/List;
      11: iload_1
      12: invokeinterface #153,  2          // InterfaceMethod java/util/List.get:(I)Ljava/lang/Object;
      17: checkcast     #64                 // class org/apache/hadoop/hbase/protobuf/generated/HBaseProtos$ServerName
      20: areturn
      21: aload_0
      22: getfield      #39                 // Field deadServersBuilder_:Lcom/google/protobuf/RepeatedFieldBuilder;
      25: iload_1
      26: invokevirtual #155                // Method com/google/protobuf/RepeatedFieldBuilder.getMessage:(I)Lcom/google/protobuf/GeneratedMessage;
      29: checkcast     #64                 // class org/apache/hadoop/hbase/protobuf/generated/HBaseProtos$ServerName
      32: areturn

  public org.apache.hadoop.hbase.protobuf.generated.ClusterStatusProtos$ClusterStatus$Builder setDeadServers(int, org.apache.hadoop.hbase.protobuf.generated.HBaseProtos$ServerName);
    Code:
       0: aload_0
       1: getfield      #39                 // Field deadServersBuilder_:Lcom/google/protobuf/RepeatedFieldBuilder;
       4: ifnonnull     42
       7: aload_2
       8: ifnonnull     19
      11: new           #132                // class java/lang/NullPointerException
      14: dup
      15: invokespecial #133                // Method java/lang/NullPointerException."<init>":()V
      18: athrow
      19: aload_0
      20: invokespecial #83                 // Method ensureDeadServersIsMutable:()V
      23: aload_0
      24: getfield      #13                 // Field deadServers_:Ljava/util/List;
      27: iload_1
      28: aload_2
      29: invokeinterface #156,  3          // InterfaceMethod java/util/List.set:(ILjava/lang/Object;)Ljava/lang/Object;
      34: pop
      35: aload_0
      36: invokevirtual #77                 // Method onChanged:()V
      39: goto          52
      42: aload_0
      43: getfield      #39                 // Field deadServersBuilder_:Lcom/google/protobuf/RepeatedFieldBuilder;
      46: iload_1
      47: aload_2
      48: invokevirtual #157                // Method com/google/protobuf/RepeatedFieldBuilder.setMessage:(ILcom/google/protobuf/GeneratedMessage;)Lcom/google/protobuf/RepeatedFieldBuilder;
      51: pop
      52: aload_0
      53: areturn

  public org.apache.hadoop.hbase.protobuf.generated.ClusterStatusProtos$ClusterStatus$Builder setDeadServers(int, org.apache.hadoop.hbase.protobuf.generated.HBaseProtos$ServerName$Builder);
    Code:
       0: aload_0
       1: getfield      #39                 // Field deadServersBuilder_:Lcom/google/protobuf/RepeatedFieldBuilder;
       4: ifnonnull     33
       7: aload_0
       8: invokespecial #83                 // Method ensureDeadServersIsMutable:()V
      11: aload_0
      12: getfield      #13                 // Field deadServers_:Ljava/util/List;
      15: iload_1
      16: aload_2
      17: invokevirtual #177                // Method org/apache/hadoop/hbase/protobuf/generated/HBaseProtos$ServerName$Builder.build:()Lorg/apache/hadoop/hbase/protobuf/generated/HBaseProtos$ServerName;
      20: invokeinterface #156,  3          // InterfaceMethod java/util/List.set:(ILjava/lang/Object;)Ljava/lang/Object;
      25: pop
      26: aload_0
      27: invokevirtual #77                 // Method onChanged:()V
      30: goto          46
      33: aload_0
      34: getfield      #39                 // Field deadServersBuilder_:Lcom/google/protobuf/RepeatedFieldBuilder;
      37: iload_1
      38: aload_2
      39: invokevirtual #177                // Method org/apache/hadoop/hbase/protobuf/generated/HBaseProtos$ServerName$Builder.build:()Lorg/apache/hadoop/hbase/protobuf/generated/HBaseProtos$ServerName;
      42: invokevirtual #157                // Method com/google/protobuf/RepeatedFieldBuilder.setMessage:(ILcom/google/protobuf/GeneratedMessage;)Lcom/google/protobuf/RepeatedFieldBuilder;
      45: pop
      46: aload_0
      47: areturn

  public org.apache.hadoop.hbase.protobuf.generated.ClusterStatusProtos$ClusterStatus$Builder addDeadServers(org.apache.hadoop.hbase.protobuf.generated.HBaseProtos$ServerName);
    Code:
       0: aload_0
       1: getfield      #39                 // Field deadServersBuilder_:Lcom/google/protobuf/RepeatedFieldBuilder;
       4: ifnonnull     41
       7: aload_1
       8: ifnonnull     19
      11: new           #132                // class java/lang/NullPointerException
      14: dup
      15: invokespecial #133                // Method java/lang/NullPointerException."<init>":()V
      18: athrow
      19: aload_0
      20: invokespecial #83                 // Method ensureDeadServersIsMutable:()V
      23: aload_0
      24: getfield      #13                 // Field deadServers_:Ljava/util/List;
      27: aload_1
      28: invokeinterface #159,  2          // InterfaceMethod java/util/List.add:(Ljava/lang/Object;)Z
      33: pop
      34: aload_0
      35: invokevirtual #77                 // Method onChanged:()V
      38: goto          50
      41: aload_0
      42: getfield      #39                 // Field deadServersBuilder_:Lcom/google/protobuf/RepeatedFieldBuilder;
      45: aload_1
      46: invokevirtual #160                // Method com/google/protobuf/RepeatedFieldBuilder.addMessage:(Lcom/google/protobuf/GeneratedMessage;)Lcom/google/protobuf/RepeatedFieldBuilder;
      49: pop
      50: aload_0
      51: areturn

  public org.apache.hadoop.hbase.protobuf.generated.ClusterStatusProtos$ClusterStatus$Builder addDeadServers(int, org.apache.hadoop.hbase.protobuf.generated.HBaseProtos$ServerName);
    Code:
       0: aload_0
       1: getfield      #39                 // Field deadServersBuilder_:Lcom/google/protobuf/RepeatedFieldBuilder;
       4: ifnonnull     41
       7: aload_2
       8: ifnonnull     19
      11: new           #132                // class java/lang/NullPointerException
      14: dup
      15: invokespecial #133                // Method java/lang/NullPointerException."<init>":()V
      18: athrow
      19: aload_0
      20: invokespecial #83                 // Method ensureDeadServersIsMutable:()V
      23: aload_0
      24: getfield      #13                 // Field deadServers_:Ljava/util/List;
      27: iload_1
      28: aload_2
      29: invokeinterface #161,  3          // InterfaceMethod java/util/List.add:(ILjava/lang/Object;)V
      34: aload_0
      35: invokevirtual #77                 // Method onChanged:()V
      38: goto          51
      41: aload_0
      42: getfield      #39                 // Field deadServersBuilder_:Lcom/google/protobuf/RepeatedFieldBuilder;
      45: iload_1
      46: aload_2
      47: invokevirtual #162                // Method com/google/protobuf/RepeatedFieldBuilder.addMessage:(ILcom/google/protobuf/GeneratedMessage;)Lcom/google/protobuf/RepeatedFieldBuilder;
      50: pop
      51: aload_0
      52: areturn

  public org.apache.hadoop.hbase.protobuf.generated.ClusterStatusProtos$ClusterStatus$Builder addDeadServers(org.apache.hadoop.hbase.protobuf.generated.HBaseProtos$ServerName$Builder);
    Code:
       0: aload_0
       1: getfield      #39                 // Field deadServersBuilder_:Lcom/google/protobuf/RepeatedFieldBuilder;
       4: ifnonnull     32
       7: aload_0
       8: invokespecial #83                 // Method ensureDeadServersIsMutable:()V
      11: aload_0
      12: getfield      #13                 // Field deadServers_:Ljava/util/List;
      15: aload_1
      16: invokevirtual #177                // Method org/apache/hadoop/hbase/protobuf/generated/HBaseProtos$ServerName$Builder.build:()Lorg/apache/hadoop/hbase/protobuf/generated/HBaseProtos$ServerName;
      19: invokeinterface #159,  2          // InterfaceMethod java/util/List.add:(Ljava/lang/Object;)Z
      24: pop
      25: aload_0
      26: invokevirtual #77                 // Method onChanged:()V
      29: goto          44
      32: aload_0
      33: getfield      #39                 // Field deadServersBuilder_:Lcom/google/protobuf/RepeatedFieldBuilder;
      36: aload_1
      37: invokevirtual #177                // Method org/apache/hadoop/hbase/protobuf/generated/HBaseProtos$ServerName$Builder.build:()Lorg/apache/hadoop/hbase/protobuf/generated/HBaseProtos$ServerName;
      40: invokevirtual #160                // Method com/google/protobuf/RepeatedFieldBuilder.addMessage:(Lcom/google/protobuf/GeneratedMessage;)Lcom/google/protobuf/RepeatedFieldBuilder;
      43: pop
      44: aload_0
      45: areturn

  public org.apache.hadoop.hbase.protobuf.generated.ClusterStatusProtos$ClusterStatus$Builder addDeadServers(int, org.apache.hadoop.hbase.protobuf.generated.HBaseProtos$ServerName$Builder);
    Code:
       0: aload_0
       1: getfield      #39                 // Field deadServersBuilder_:Lcom/google/protobuf/RepeatedFieldBuilder;
       4: ifnonnull     32
       7: aload_0
       8: invokespecial #83                 // Method ensureDeadServersIsMutable:()V
      11: aload_0
      12: getfield      #13                 // Field deadServers_:Ljava/util/List;
      15: iload_1
      16: aload_2
      17: invokevirtual #177                // Method org/apache/hadoop/hbase/protobuf/generated/HBaseProtos$ServerName$Builder.build:()Lorg/apache/hadoop/hbase/protobuf/generated/HBaseProtos$ServerName;
      20: invokeinterface #161,  3          // InterfaceMethod java/util/List.add:(ILjava/lang/Object;)V
      25: aload_0
      26: invokevirtual #77                 // Method onChanged:()V
      29: goto          45
      32: aload_0
      33: getfield      #39                 // Field deadServersBuilder_:Lcom/google/protobuf/RepeatedFieldBuilder;
      36: iload_1
      37: aload_2
      38: invokevirtual #177                // Method org/apache/hadoop/hbase/protobuf/generated/HBaseProtos$ServerName$Builder.build:()Lorg/apache/hadoop/hbase/protobuf/generated/HBaseProtos$ServerName;
      41: invokevirtual #162                // Method com/google/protobuf/RepeatedFieldBuilder.addMessage:(ILcom/google/protobuf/GeneratedMessage;)Lcom/google/protobuf/RepeatedFieldBuilder;
      44: pop
      45: aload_0
      46: areturn

  public org.apache.hadoop.hbase.protobuf.generated.ClusterStatusProtos$ClusterStatus$Builder addAllDeadServers(java.lang.Iterable<? extends org.apache.hadoop.hbase.protobuf.generated.HBaseProtos$ServerName>);
    Code:
       0: aload_0
       1: getfield      #39                 // Field deadServersBuilder_:Lcom/google/protobuf/RepeatedFieldBuilder;
       4: ifnonnull     26
       7: aload_0
       8: invokespecial #83                 // Method ensureDeadServersIsMutable:()V
      11: aload_1
      12: aload_0
      13: getfield      #13                 // Field deadServers_:Ljava/util/List;
      16: invokestatic  #163                // Method com/google/protobuf/GeneratedMessage$Builder.addAll:(Ljava/lang/Iterable;Ljava/util/Collection;)V
      19: aload_0
      20: invokevirtual #77                 // Method onChanged:()V
      23: goto          35
      26: aload_0
      27: getfield      #39                 // Field deadServersBuilder_:Lcom/google/protobuf/RepeatedFieldBuilder;
      30: aload_1
      31: invokevirtual #81                 // Method com/google/protobuf/RepeatedFieldBuilder.addAllMessages:(Ljava/lang/Iterable;)Lcom/google/protobuf/RepeatedFieldBuilder;
      34: pop
      35: aload_0
      36: areturn

  public org.apache.hadoop.hbase.protobuf.generated.ClusterStatusProtos$ClusterStatus$Builder clearDeadServers();
    Code:
       0: aload_0
       1: getfield      #39                 // Field deadServersBuilder_:Lcom/google/protobuf/RepeatedFieldBuilder;
       4: ifnonnull     32
       7: aload_0
       8: invokestatic  #11                 // Method java/util/Collections.emptyList:()Ljava/util/List;
      11: putfield      #13                 // Field deadServers_:Ljava/util/List;
      14: aload_0
      15: aload_0
      16: getfield      #36                 // Field bitField0_:I
      19: bipush        -5
      21: iand
      22: putfield      #36                 // Field bitField0_:I
      25: aload_0
      26: invokevirtual #77                 // Method onChanged:()V
      29: goto          39
      32: aload_0
      33: getfield      #39                 // Field deadServersBuilder_:Lcom/google/protobuf/RepeatedFieldBuilder;
      36: invokevirtual #38                 // Method com/google/protobuf/RepeatedFieldBuilder.clear:()V
      39: aload_0
      40: areturn

  public org.apache.hadoop.hbase.protobuf.generated.ClusterStatusProtos$ClusterStatus$Builder removeDeadServers(int);
    Code:
       0: aload_0
       1: getfield      #39                 // Field deadServersBuilder_:Lcom/google/protobuf/RepeatedFieldBuilder;
       4: ifnonnull     29
       7: aload_0
       8: invokespecial #83                 // Method ensureDeadServersIsMutable:()V
      11: aload_0
      12: getfield      #13                 // Field deadServers_:Ljava/util/List;
      15: iload_1
      16: invokeinterface #164,  2          // InterfaceMethod java/util/List.remove:(I)Ljava/lang/Object;
      21: pop
      22: aload_0
      23: invokevirtual #77                 // Method onChanged:()V
      26: goto          37
      29: aload_0
      30: getfield      #39                 // Field deadServersBuilder_:Lcom/google/protobuf/RepeatedFieldBuilder;
      33: iload_1
      34: invokevirtual #165                // Method com/google/protobuf/RepeatedFieldBuilder.remove:(I)V
      37: aload_0
      38: areturn

  public org.apache.hadoop.hbase.protobuf.generated.HBaseProtos$ServerName$Builder getDeadServersBuilder(int);
    Code:
       0: aload_0
       1: invokespecial #26                 // Method getDeadServersFieldBuilder:()Lcom/google/protobuf/RepeatedFieldBuilder;
       4: iload_1
       5: invokevirtual #166                // Method com/google/protobuf/RepeatedFieldBuilder.getBuilder:(I)Lcom/google/protobuf/GeneratedMessage$Builder;
       8: checkcast     #178                // class org/apache/hadoop/hbase/protobuf/generated/HBaseProtos$ServerName$Builder
      11: areturn

  public org.apache.hadoop.hbase.protobuf.generated.HBaseProtos$ServerNameOrBuilder getDeadServersOrBuilder(int);
    Code:
       0: aload_0
       1: getfield      #39                 // Field deadServersBuilder_:Lcom/google/protobuf/RepeatedFieldBuilder;
       4: ifnonnull     21
       7: aload_0
       8: getfield      #13                 // Field deadServers_:Ljava/util/List;
      11: iload_1
      12: invokeinterface #153,  2          // InterfaceMethod java/util/List.get:(I)Ljava/lang/Object;
      17: checkcast     #179                // class org/apache/hadoop/hbase/protobuf/generated/HBaseProtos$ServerNameOrBuilder
      20: areturn
      21: aload_0
      22: getfield      #39                 // Field deadServersBuilder_:Lcom/google/protobuf/RepeatedFieldBuilder;
      25: iload_1
      26: invokevirtual #169                // Method com/google/protobuf/RepeatedFieldBuilder.getMessageOrBuilder:(I)Lcom/google/protobuf/MessageOrBuilder;
      29: checkcast     #179                // class org/apache/hadoop/hbase/protobuf/generated/HBaseProtos$ServerNameOrBuilder
      32: areturn

  public java.util.List<? extends org.apache.hadoop.hbase.protobuf.generated.HBaseProtos$ServerNameOrBuilder> getDeadServersOrBuilderList();
    Code:
       0: aload_0
       1: getfield      #39                 // Field deadServersBuilder_:Lcom/google/protobuf/RepeatedFieldBuilder;
       4: ifnull        15
       7: aload_0
       8: getfield      #39                 // Field deadServersBuilder_:Lcom/google/protobuf/RepeatedFieldBuilder;
      11: invokevirtual #170                // Method com/google/protobuf/RepeatedFieldBuilder.getMessageOrBuilderList:()Ljava/util/List;
      14: areturn
      15: aload_0
      16: getfield      #13                 // Field deadServers_:Ljava/util/List;
      19: invokestatic  #55                 // Method java/util/Collections.unmodifiableList:(Ljava/util/List;)Ljava/util/List;
      22: areturn

  public org.apache.hadoop.hbase.protobuf.generated.HBaseProtos$ServerName$Builder addDeadServersBuilder();
    Code:
       0: aload_0
       1: invokespecial #26                 // Method getDeadServersFieldBuilder:()Lcom/google/protobuf/RepeatedFieldBuilder;
       4: invokestatic  #18                 // Method org/apache/hadoop/hbase/protobuf/generated/HBaseProtos$ServerName.getDefaultInstance:()Lorg/apache/hadoop/hbase/protobuf/generated/HBaseProtos$ServerName;
       7: invokevirtual #172                // Method com/google/protobuf/RepeatedFieldBuilder.addBuilder:(Lcom/google/protobuf/GeneratedMessage;)Lcom/google/protobuf/GeneratedMessage$Builder;
      10: checkcast     #178                // class org/apache/hadoop/hbase/protobuf/generated/HBaseProtos$ServerName$Builder
      13: areturn

  public org.apache.hadoop.hbase.protobuf.generated.HBaseProtos$ServerName$Builder addDeadServersBuilder(int);
    Code:
       0: aload_0
       1: invokespecial #26                 // Method getDeadServersFieldBuilder:()Lcom/google/protobuf/RepeatedFieldBuilder;
       4: iload_1
       5: invokestatic  #18                 // Method org/apache/hadoop/hbase/protobuf/generated/HBaseProtos$ServerName.getDefaultInstance:()Lorg/apache/hadoop/hbase/protobuf/generated/HBaseProtos$ServerName;
       8: invokevirtual #173                // Method com/google/protobuf/RepeatedFieldBuilder.addBuilder:(ILcom/google/protobuf/GeneratedMessage;)Lcom/google/protobuf/GeneratedMessage$Builder;
      11: checkcast     #178                // class org/apache/hadoop/hbase/protobuf/generated/HBaseProtos$ServerName$Builder
      14: areturn

  public java.util.List<org.apache.hadoop.hbase.protobuf.generated.HBaseProtos$ServerName$Builder> getDeadServersBuilderList();
    Code:
       0: aload_0
       1: invokespecial #26                 // Method getDeadServersFieldBuilder:()Lcom/google/protobuf/RepeatedFieldBuilder;
       4: invokevirtual #174                // Method com/google/protobuf/RepeatedFieldBuilder.getBuilderList:()Ljava/util/List;
       7: areturn

  public java.util.List<org.apache.hadoop.hbase.protobuf.generated.ClusterStatusProtos$RegionInTransition> getRegionsInTransitionList();
    Code:
       0: aload_0
       1: getfield      #40                 // Field regionsInTransitionBuilder_:Lcom/google/protobuf/RepeatedFieldBuilder;
       4: ifnonnull     15
       7: aload_0
       8: getfield      #14                 // Field regionsInTransition_:Ljava/util/List;
      11: invokestatic  #55                 // Method java/util/Collections.unmodifiableList:(Ljava/util/List;)Ljava/util/List;
      14: areturn
      15: aload_0
      16: getfield      #40                 // Field regionsInTransitionBuilder_:Lcom/google/protobuf/RepeatedFieldBuilder;
      19: invokevirtual #150                // Method com/google/protobuf/RepeatedFieldBuilder.getMessageList:()Ljava/util/List;
      22: areturn

  public int getRegionsInTransitionCount();
    Code:
       0: aload_0
       1: getfield      #40                 // Field regionsInTransitionBuilder_:Lcom/google/protobuf/RepeatedFieldBuilder;
       4: ifnonnull     17
       7: aload_0
       8: getfield      #14                 // Field regionsInTransition_:Ljava/util/List;
      11: invokeinterface #151,  1          // InterfaceMethod java/util/List.size:()I
      16: ireturn
      17: aload_0
      18: getfield      #40                 // Field regionsInTransitionBuilder_:Lcom/google/protobuf/RepeatedFieldBuilder;
      21: invokevirtual #152                // Method com/google/protobuf/RepeatedFieldBuilder.getCount:()I
      24: ireturn

  public org.apache.hadoop.hbase.protobuf.generated.ClusterStatusProtos$RegionInTransition getRegionsInTransition(int);
    Code:
       0: aload_0
       1: getfield      #40                 // Field regionsInTransitionBuilder_:Lcom/google/protobuf/RepeatedFieldBuilder;
       4: ifnonnull     21
       7: aload_0
       8: getfield      #14                 // Field regionsInTransition_:Ljava/util/List;
      11: iload_1
      12: invokeinterface #153,  2          // InterfaceMethod java/util/List.get:(I)Ljava/lang/Object;
      17: checkcast     #180                // class org/apache/hadoop/hbase/protobuf/generated/ClusterStatusProtos$RegionInTransition
      20: areturn
      21: aload_0
      22: getfield      #40                 // Field regionsInTransitionBuilder_:Lcom/google/protobuf/RepeatedFieldBuilder;
      25: iload_1
      26: invokevirtual #155                // Method com/google/protobuf/RepeatedFieldBuilder.getMessage:(I)Lcom/google/protobuf/GeneratedMessage;
      29: checkcast     #180                // class org/apache/hadoop/hbase/protobuf/generated/ClusterStatusProtos$RegionInTransition
      32: areturn

  public org.apache.hadoop.hbase.protobuf.generated.ClusterStatusProtos$ClusterStatus$Builder setRegionsInTransition(int, org.apache.hadoop.hbase.protobuf.generated.ClusterStatusProtos$RegionInTransition);
    Code:
       0: aload_0
       1: getfield      #40                 // Field regionsInTransitionBuilder_:Lcom/google/protobuf/RepeatedFieldBuilder;
       4: ifnonnull     42
       7: aload_2
       8: ifnonnull     19
      11: new           #132                // class java/lang/NullPointerException
      14: dup
      15: invokespecial #133                // Method java/lang/NullPointerException."<init>":()V
      18: athrow
      19: aload_0
      20: invokespecial #86                 // Method ensureRegionsInTransitionIsMutable:()V
      23: aload_0
      24: getfield      #14                 // Field regionsInTransition_:Ljava/util/List;
      27: iload_1
      28: aload_2
      29: invokeinterface #156,  3          // InterfaceMethod java/util/List.set:(ILjava/lang/Object;)Ljava/lang/Object;
      34: pop
      35: aload_0
      36: invokevirtual #77                 // Method onChanged:()V
      39: goto          52
      42: aload_0
      43: getfield      #40                 // Field regionsInTransitionBuilder_:Lcom/google/protobuf/RepeatedFieldBuilder;
      46: iload_1
      47: aload_2
      48: invokevirtual #157                // Method com/google/protobuf/RepeatedFieldBuilder.setMessage:(ILcom/google/protobuf/GeneratedMessage;)Lcom/google/protobuf/RepeatedFieldBuilder;
      51: pop
      52: aload_0
      53: areturn

  public org.apache.hadoop.hbase.protobuf.generated.ClusterStatusProtos$ClusterStatus$Builder setRegionsInTransition(int, org.apache.hadoop.hbase.protobuf.generated.ClusterStatusProtos$RegionInTransition$Builder);
    Code:
       0: aload_0
       1: getfield      #40                 // Field regionsInTransitionBuilder_:Lcom/google/protobuf/RepeatedFieldBuilder;
       4: ifnonnull     33
       7: aload_0
       8: invokespecial #86                 // Method ensureRegionsInTransitionIsMutable:()V
      11: aload_0
      12: getfield      #14                 // Field regionsInTransition_:Ljava/util/List;
      15: iload_1
      16: aload_2
      17: invokevirtual #181                // Method org/apache/hadoop/hbase/protobuf/generated/ClusterStatusProtos$RegionInTransition$Builder.build:()Lorg/apache/hadoop/hbase/protobuf/generated/ClusterStatusProtos$RegionInTransition;
      20: invokeinterface #156,  3          // InterfaceMethod java/util/List.set:(ILjava/lang/Object;)Ljava/lang/Object;
      25: pop
      26: aload_0
      27: invokevirtual #77                 // Method onChanged:()V
      30: goto          46
      33: aload_0
      34: getfield      #40                 // Field regionsInTransitionBuilder_:Lcom/google/protobuf/RepeatedFieldBuilder;
      37: iload_1
      38: aload_2
      39: invokevirtual #181                // Method org/apache/hadoop/hbase/protobuf/generated/ClusterStatusProtos$RegionInTransition$Builder.build:()Lorg/apache/hadoop/hbase/protobuf/generated/ClusterStatusProtos$RegionInTransition;
      42: invokevirtual #157                // Method com/google/protobuf/RepeatedFieldBuilder.setMessage:(ILcom/google/protobuf/GeneratedMessage;)Lcom/google/protobuf/RepeatedFieldBuilder;
      45: pop
      46: aload_0
      47: areturn

  public org.apache.hadoop.hbase.protobuf.generated.ClusterStatusProtos$ClusterStatus$Builder addRegionsInTransition(org.apache.hadoop.hbase.protobuf.generated.ClusterStatusProtos$RegionInTransition);
    Code:
       0: aload_0
       1: getfield      #40                 // Field regionsInTransitionBuilder_:Lcom/google/protobuf/RepeatedFieldBuilder;
       4: ifnonnull     41
       7: aload_1
       8: ifnonnull     19
      11: new           #132                // class java/lang/NullPointerException
      14: dup
      15: invokespecial #133                // Method java/lang/NullPointerException."<init>":()V
      18: athrow
      19: aload_0
      20: invokespecial #86                 // Method ensureRegionsInTransitionIsMutable:()V
      23: aload_0
      24: getfield      #14                 // Field regionsInTransition_:Ljava/util/List;
      27: aload_1
      28: invokeinterface #159,  2          // InterfaceMethod java/util/List.add:(Ljava/lang/Object;)Z
      33: pop
      34: aload_0
      35: invokevirtual #77                 // Method onChanged:()V
      38: goto          50
      41: aload_0
      42: getfield      #40                 // Field regionsInTransitionBuilder_:Lcom/google/protobuf/RepeatedFieldBuilder;
      45: aload_1
      46: invokevirtual #160                // Method com/google/protobuf/RepeatedFieldBuilder.addMessage:(Lcom/google/protobuf/GeneratedMessage;)Lcom/google/protobuf/RepeatedFieldBuilder;
      49: pop
      50: aload_0
      51: areturn

  public org.apache.hadoop.hbase.protobuf.generated.ClusterStatusProtos$ClusterStatus$Builder addRegionsInTransition(int, org.apache.hadoop.hbase.protobuf.generated.ClusterStatusProtos$RegionInTransition);
    Code:
       0: aload_0
       1: getfield      #40                 // Field regionsInTransitionBuilder_:Lcom/google/protobuf/RepeatedFieldBuilder;
       4: ifnonnull     41
       7: aload_2
       8: ifnonnull     19
      11: new           #132                // class java/lang/NullPointerException
      14: dup
      15: invokespecial #133                // Method java/lang/NullPointerException."<init>":()V
      18: athrow
      19: aload_0
      20: invokespecial #86                 // Method ensureRegionsInTransitionIsMutable:()V
      23: aload_0
      24: getfield      #14                 // Field regionsInTransition_:Ljava/util/List;
      27: iload_1
      28: aload_2
      29: invokeinterface #161,  3          // InterfaceMethod java/util/List.add:(ILjava/lang/Object;)V
      34: aload_0
      35: invokevirtual #77                 // Method onChanged:()V
      38: goto          51
      41: aload_0
      42: getfield      #40                 // Field regionsInTransitionBuilder_:Lcom/google/protobuf/RepeatedFieldBuilder;
      45: iload_1
      46: aload_2
      47: invokevirtual #162                // Method com/google/protobuf/RepeatedFieldBuilder.addMessage:(ILcom/google/protobuf/GeneratedMessage;)Lcom/google/protobuf/RepeatedFieldBuilder;
      50: pop
      51: aload_0
      52: areturn

  public org.apache.hadoop.hbase.protobuf.generated.ClusterStatusProtos$ClusterStatus$Builder addRegionsInTransition(org.apache.hadoop.hbase.protobuf.generated.ClusterStatusProtos$RegionInTransition$Builder);
    Code:
       0: aload_0
       1: getfield      #40                 // Field regionsInTransitionBuilder_:Lcom/google/protobuf/RepeatedFieldBuilder;
       4: ifnonnull     32
       7: aload_0
       8: invokespecial #86                 // Method ensureRegionsInTransitionIsMutable:()V
      11: aload_0
      12: getfield      #14                 // Field regionsInTransition_:Ljava/util/List;
      15: aload_1
      16: invokevirtual #181                // Method org/apache/hadoop/hbase/protobuf/generated/ClusterStatusProtos$RegionInTransition$Builder.build:()Lorg/apache/hadoop/hbase/protobuf/generated/ClusterStatusProtos$RegionInTransition;
      19: invokeinterface #159,  2          // InterfaceMethod java/util/List.add:(Ljava/lang/Object;)Z
      24: pop
      25: aload_0
      26: invokevirtual #77                 // Method onChanged:()V
      29: goto          44
      32: aload_0
      33: getfield      #40                 // Field regionsInTransitionBuilder_:Lcom/google/protobuf/RepeatedFieldBuilder;
      36: aload_1
      37: invokevirtual #181                // Method org/apache/hadoop/hbase/protobuf/generated/ClusterStatusProtos$RegionInTransition$Builder.build:()Lorg/apache/hadoop/hbase/protobuf/generated/ClusterStatusProtos$RegionInTransition;
      40: invokevirtual #160                // Method com/google/protobuf/RepeatedFieldBuilder.addMessage:(Lcom/google/protobuf/GeneratedMessage;)Lcom/google/protobuf/RepeatedFieldBuilder;
      43: pop
      44: aload_0
      45: areturn

  public org.apache.hadoop.hbase.protobuf.generated.ClusterStatusProtos$ClusterStatus$Builder addRegionsInTransition(int, org.apache.hadoop.hbase.protobuf.generated.ClusterStatusProtos$RegionInTransition$Builder);
    Code:
       0: aload_0
       1: getfield      #40                 // Field regionsInTransitionBuilder_:Lcom/google/protobuf/RepeatedFieldBuilder;
       4: ifnonnull     32
       7: aload_0
       8: invokespecial #86                 // Method ensureRegionsInTransitionIsMutable:()V
      11: aload_0
      12: getfield      #14                 // Field regionsInTransition_:Ljava/util/List;
      15: iload_1
      16: aload_2
      17: invokevirtual #181                // Method org/apache/hadoop/hbase/protobuf/generated/ClusterStatusProtos$RegionInTransition$Builder.build:()Lorg/apache/hadoop/hbase/protobuf/generated/ClusterStatusProtos$RegionInTransition;
      20: invokeinterface #161,  3          // InterfaceMethod java/util/List.add:(ILjava/lang/Object;)V
      25: aload_0
      26: invokevirtual #77                 // Method onChanged:()V
      29: goto          45
      32: aload_0
      33: getfield      #40                 // Field regionsInTransitionBuilder_:Lcom/google/protobuf/RepeatedFieldBuilder;
      36: iload_1
      37: aload_2
      38: invokevirtual #181                // Method org/apache/hadoop/hbase/protobuf/generated/ClusterStatusProtos$RegionInTransition$Builder.build:()Lorg/apache/hadoop/hbase/protobuf/generated/ClusterStatusProtos$RegionInTransition;
      41: invokevirtual #162                // Method com/google/protobuf/RepeatedFieldBuilder.addMessage:(ILcom/google/protobuf/GeneratedMessage;)Lcom/google/protobuf/RepeatedFieldBuilder;
      44: pop
      45: aload_0
      46: areturn

  public org.apache.hadoop.hbase.protobuf.generated.ClusterStatusProtos$ClusterStatus$Builder addAllRegionsInTransition(java.lang.Iterable<? extends org.apache.hadoop.hbase.protobuf.generated.ClusterStatusProtos$RegionInTransition>);
    Code:
       0: aload_0
       1: getfield      #40                 // Field regionsInTransitionBuilder_:Lcom/google/protobuf/RepeatedFieldBuilder;
       4: ifnonnull     26
       7: aload_0
       8: invokespecial #86                 // Method ensureRegionsInTransitionIsMutable:()V
      11: aload_1
      12: aload_0
      13: getfield      #14                 // Field regionsInTransition_:Ljava/util/List;
      16: invokestatic  #163                // Method com/google/protobuf/GeneratedMessage$Builder.addAll:(Ljava/lang/Iterable;Ljava/util/Collection;)V
      19: aload_0
      20: invokevirtual #77                 // Method onChanged:()V
      23: goto          35
      26: aload_0
      27: getfield      #40                 // Field regionsInTransitionBuilder_:Lcom/google/protobuf/RepeatedFieldBuilder;
      30: aload_1
      31: invokevirtual #81                 // Method com/google/protobuf/RepeatedFieldBuilder.addAllMessages:(Ljava/lang/Iterable;)Lcom/google/protobuf/RepeatedFieldBuilder;
      34: pop
      35: aload_0
      36: areturn

  public org.apache.hadoop.hbase.protobuf.generated.ClusterStatusProtos$ClusterStatus$Builder clearRegionsInTransition();
    Code:
       0: aload_0
       1: getfield      #40                 // Field regionsInTransitionBuilder_:Lcom/google/protobuf/RepeatedFieldBuilder;
       4: ifnonnull     32
       7: aload_0
       8: invokestatic  #11                 // Method java/util/Collections.emptyList:()Ljava/util/List;
      11: putfield      #14                 // Field regionsInTransition_:Ljava/util/List;
      14: aload_0
      15: aload_0
      16: getfield      #36                 // Field bitField0_:I
      19: bipush        -9
      21: iand
      22: putfield      #36                 // Field bitField0_:I
      25: aload_0
      26: invokevirtual #77                 // Method onChanged:()V
      29: goto          39
      32: aload_0
      33: getfield      #40                 // Field regionsInTransitionBuilder_:Lcom/google/protobuf/RepeatedFieldBuilder;
      36: invokevirtual #38                 // Method com/google/protobuf/RepeatedFieldBuilder.clear:()V
      39: aload_0
      40: areturn

  public org.apache.hadoop.hbase.protobuf.generated.ClusterStatusProtos$ClusterStatus$Builder removeRegionsInTransition(int);
    Code:
       0: aload_0
       1: getfield      #40                 // Field regionsInTransitionBuilder_:Lcom/google/protobuf/RepeatedFieldBuilder;
       4: ifnonnull     29
       7: aload_0
       8: invokespecial #86                 // Method ensureRegionsInTransitionIsMutable:()V
      11: aload_0
      12: getfield      #14                 // Field regionsInTransition_:Ljava/util/List;
      15: iload_1
      16: invokeinterface #164,  2          // InterfaceMethod java/util/List.remove:(I)Ljava/lang/Object;
      21: pop
      22: aload_0
      23: invokevirtual #77                 // Method onChanged:()V
      26: goto          37
      29: aload_0
      30: getfield      #40                 // Field regionsInTransitionBuilder_:Lcom/google/protobuf/RepeatedFieldBuilder;
      33: iload_1
      34: invokevirtual #165                // Method com/google/protobuf/RepeatedFieldBuilder.remove:(I)V
      37: aload_0
      38: areturn

  public org.apache.hadoop.hbase.protobuf.generated.ClusterStatusProtos$RegionInTransition$Builder getRegionsInTransitionBuilder(int);
    Code:
       0: aload_0
       1: invokespecial #27                 // Method getRegionsInTransitionFieldBuilder:()Lcom/google/protobuf/RepeatedFieldBuilder;
       4: iload_1
       5: invokevirtual #166                // Method com/google/protobuf/RepeatedFieldBuilder.getBuilder:(I)Lcom/google/protobuf/GeneratedMessage$Builder;
       8: checkcast     #182                // class org/apache/hadoop/hbase/protobuf/generated/ClusterStatusProtos$RegionInTransition$Builder
      11: areturn

  public org.apache.hadoop.hbase.protobuf.generated.ClusterStatusProtos$RegionInTransitionOrBuilder getRegionsInTransitionOrBuilder(int);
    Code:
       0: aload_0
       1: getfield      #40                 // Field regionsInTransitionBuilder_:Lcom/google/protobuf/RepeatedFieldBuilder;
       4: ifnonnull     21
       7: aload_0
       8: getfield      #14                 // Field regionsInTransition_:Ljava/util/List;
      11: iload_1
      12: invokeinterface #153,  2          // InterfaceMethod java/util/List.get:(I)Ljava/lang/Object;
      17: checkcast     #183                // class org/apache/hadoop/hbase/protobuf/generated/ClusterStatusProtos$RegionInTransitionOrBuilder
      20: areturn
      21: aload_0
      22: getfield      #40                 // Field regionsInTransitionBuilder_:Lcom/google/protobuf/RepeatedFieldBuilder;
      25: iload_1
      26: invokevirtual #169                // Method com/google/protobuf/RepeatedFieldBuilder.getMessageOrBuilder:(I)Lcom/google/protobuf/MessageOrBuilder;
      29: checkcast     #183                // class org/apache/hadoop/hbase/protobuf/generated/ClusterStatusProtos$RegionInTransitionOrBuilder
      32: areturn

  public java.util.List<? extends org.apache.hadoop.hbase.protobuf.generated.ClusterStatusProtos$RegionInTransitionOrBuilder> getRegionsInTransitionOrBuilderList();
    Code:
       0: aload_0
       1: getfield      #40                 // Field regionsInTransitionBuilder_:Lcom/google/protobuf/RepeatedFieldBuilder;
       4: ifnull        15
       7: aload_0
       8: getfield      #40                 // Field regionsInTransitionBuilder_:Lcom/google/protobuf/RepeatedFieldBuilder;
      11: invokevirtual #170                // Method com/google/protobuf/RepeatedFieldBuilder.getMessageOrBuilderList:()Ljava/util/List;
      14: areturn
      15: aload_0
      16: getfield      #14                 // Field regionsInTransition_:Ljava/util/List;
      19: invokestatic  #55                 // Method java/util/Collections.unmodifiableList:(Ljava/util/List;)Ljava/util/List;
      22: areturn

  public org.apache.hadoop.hbase.protobuf.generated.ClusterStatusProtos$RegionInTransition$Builder addRegionsInTransitionBuilder();
    Code:
       0: aload_0
       1: invokespecial #27                 // Method getRegionsInTransitionFieldBuilder:()Lcom/google/protobuf/RepeatedFieldBuilder;
       4: invokestatic  #184                // Method org/apache/hadoop/hbase/protobuf/generated/ClusterStatusProtos$RegionInTransition.getDefaultInstance:()Lorg/apache/hadoop/hbase/protobuf/generated/ClusterStatusProtos$RegionInTransition;
       7: invokevirtual #172                // Method com/google/protobuf/RepeatedFieldBuilder.addBuilder:(Lcom/google/protobuf/GeneratedMessage;)Lcom/google/protobuf/GeneratedMessage$Builder;
      10: checkcast     #182                // class org/apache/hadoop/hbase/protobuf/generated/ClusterStatusProtos$RegionInTransition$Builder
      13: areturn

  public org.apache.hadoop.hbase.protobuf.generated.ClusterStatusProtos$RegionInTransition$Builder addRegionsInTransitionBuilder(int);
    Code:
       0: aload_0
       1: invokespecial #27                 // Method getRegionsInTransitionFieldBuilder:()Lcom/google/protobuf/RepeatedFieldBuilder;
       4: iload_1
       5: invokestatic  #184                // Method org/apache/hadoop/hbase/protobuf/generated/ClusterStatusProtos$RegionInTransition.getDefaultInstance:()Lorg/apache/hadoop/hbase/protobuf/generated/ClusterStatusProtos$RegionInTransition;
       8: invokevirtual #173                // Method com/google/protobuf/RepeatedFieldBuilder.addBuilder:(ILcom/google/protobuf/GeneratedMessage;)Lcom/google/protobuf/GeneratedMessage$Builder;
      11: checkcast     #182                // class org/apache/hadoop/hbase/protobuf/generated/ClusterStatusProtos$RegionInTransition$Builder
      14: areturn

  public java.util.List<org.apache.hadoop.hbase.protobuf.generated.ClusterStatusProtos$RegionInTransition$Builder> getRegionsInTransitionBuilderList();
    Code:
       0: aload_0
       1: invokespecial #27                 // Method getRegionsInTransitionFieldBuilder:()Lcom/google/protobuf/RepeatedFieldBuilder;
       4: invokevirtual #174                // Method com/google/protobuf/RepeatedFieldBuilder.getBuilderList:()Ljava/util/List;
       7: areturn

  public boolean hasClusterId();
    Code:
       0: aload_0
       1: getfield      #36                 // Field bitField0_:I
       4: bipush        16
       6: iand
       7: bipush        16
       9: if_icmpne     16
      12: iconst_1
      13: goto          17
      16: iconst_0
      17: ireturn

  public org.apache.hadoop.hbase.protobuf.generated.ClusterIdProtos$ClusterId getClusterId();
    Code:
       0: aload_0
       1: getfield      #41                 // Field clusterIdBuilder_:Lcom/google/protobuf/SingleFieldBuilder;
       4: ifnonnull     12
       7: aload_0
       8: getfield      #16                 // Field clusterId_:Lorg/apache/hadoop/hbase/protobuf/generated/ClusterIdProtos$ClusterId;
      11: areturn
      12: aload_0
      13: getfield      #41                 // Field clusterIdBuilder_:Lcom/google/protobuf/SingleFieldBuilder;
      16: invokevirtual #131                // Method com/google/protobuf/SingleFieldBuilder.getMessage:()Lcom/google/protobuf/GeneratedMessage;
      19: checkcast     #61                 // class org/apache/hadoop/hbase/protobuf/generated/ClusterIdProtos$ClusterId
      22: areturn

  public org.apache.hadoop.hbase.protobuf.generated.ClusterStatusProtos$ClusterStatus$Builder setClusterId(org.apache.hadoop.hbase.protobuf.generated.ClusterIdProtos$ClusterId);
    Code:
       0: aload_0
       1: getfield      #41                 // Field clusterIdBuilder_:Lcom/google/protobuf/SingleFieldBuilder;
       4: ifnonnull     31
       7: aload_1
       8: ifnonnull     19
      11: new           #132                // class java/lang/NullPointerException
      14: dup
      15: invokespecial #133                // Method java/lang/NullPointerException."<init>":()V
      18: athrow
      19: aload_0
      20: aload_1
      21: putfield      #16                 // Field clusterId_:Lorg/apache/hadoop/hbase/protobuf/generated/ClusterIdProtos$ClusterId;
      24: aload_0
      25: invokevirtual #77                 // Method onChanged:()V
      28: goto          40
      31: aload_0
      32: getfield      #41                 // Field clusterIdBuilder_:Lcom/google/protobuf/SingleFieldBuilder;
      35: aload_1
      36: invokevirtual #134                // Method com/google/protobuf/SingleFieldBuilder.setMessage:(Lcom/google/protobuf/GeneratedMessage;)Lcom/google/protobuf/SingleFieldBuilder;
      39: pop
      40: aload_0
      41: dup
      42: getfield      #36                 // Field bitField0_:I
      45: bipush        16
      47: ior
      48: putfield      #36                 // Field bitField0_:I
      51: aload_0
      52: areturn

  public org.apache.hadoop.hbase.protobuf.generated.ClusterStatusProtos$ClusterStatus$Builder setClusterId(org.apache.hadoop.hbase.protobuf.generated.ClusterIdProtos$ClusterId$Builder);
    Code:
       0: aload_0
       1: getfield      #41                 // Field clusterIdBuilder_:Lcom/google/protobuf/SingleFieldBuilder;
       4: ifnonnull     22
       7: aload_0
       8: aload_1
       9: invokevirtual #185                // Method org/apache/hadoop/hbase/protobuf/generated/ClusterIdProtos$ClusterId$Builder.build:()Lorg/apache/hadoop/hbase/protobuf/generated/ClusterIdProtos$ClusterId;
      12: putfield      #16                 // Field clusterId_:Lorg/apache/hadoop/hbase/protobuf/generated/ClusterIdProtos$ClusterId;
      15: aload_0
      16: invokevirtual #77                 // Method onChanged:()V
      19: goto          34
      22: aload_0
      23: getfield      #41                 // Field clusterIdBuilder_:Lcom/google/protobuf/SingleFieldBuilder;
      26: aload_1
      27: invokevirtual #185                // Method org/apache/hadoop/hbase/protobuf/generated/ClusterIdProtos$ClusterId$Builder.build:()Lorg/apache/hadoop/hbase/protobuf/generated/ClusterIdProtos$ClusterId;
      30: invokevirtual #134                // Method com/google/protobuf/SingleFieldBuilder.setMessage:(Lcom/google/protobuf/GeneratedMessage;)Lcom/google/protobuf/SingleFieldBuilder;
      33: pop
      34: aload_0
      35: dup
      36: getfield      #36                 // Field bitField0_:I
      39: bipush        16
      41: ior
      42: putfield      #36                 // Field bitField0_:I
      45: aload_0
      46: areturn

  public org.apache.hadoop.hbase.protobuf.generated.ClusterStatusProtos$ClusterStatus$Builder mergeClusterId(org.apache.hadoop.hbase.protobuf.generated.ClusterIdProtos$ClusterId);
    Code:
       0: aload_0
       1: getfield      #41                 // Field clusterIdBuilder_:Lcom/google/protobuf/SingleFieldBuilder;
       4: ifnonnull     62
       7: aload_0
       8: getfield      #36                 // Field bitField0_:I
      11: bipush        16
      13: iand
      14: bipush        16
      16: if_icmpne     50
      19: aload_0
      20: getfield      #16                 // Field clusterId_:Lorg/apache/hadoop/hbase/protobuf/generated/ClusterIdProtos$ClusterId;
      23: invokestatic  #15                 // Method org/apache/hadoop/hbase/protobuf/generated/ClusterIdProtos$ClusterId.getDefaultInstance:()Lorg/apache/hadoop/hbase/protobuf/generated/ClusterIdProtos$ClusterId;
      26: if_acmpeq     50
      29: aload_0
      30: aload_0
      31: getfield      #16                 // Field clusterId_:Lorg/apache/hadoop/hbase/protobuf/generated/ClusterIdProtos$ClusterId;
      34: invokestatic  #186                // Method org/apache/hadoop/hbase/protobuf/generated/ClusterIdProtos$ClusterId.newBuilder:(Lorg/apache/hadoop/hbase/protobuf/generated/ClusterIdProtos$ClusterId;)Lorg/apache/hadoop/hbase/protobuf/generated/ClusterIdProtos$ClusterId$Builder;
      37: aload_1
      38: invokevirtual #187                // Method org/apache/hadoop/hbase/protobuf/generated/ClusterIdProtos$ClusterId$Builder.mergeFrom:(Lorg/apache/hadoop/hbase/protobuf/generated/ClusterIdProtos$ClusterId;)Lorg/apache/hadoop/hbase/protobuf/generated/ClusterIdProtos$ClusterId$Builder;
      41: invokevirtual #188                // Method org/apache/hadoop/hbase/protobuf/generated/ClusterIdProtos$ClusterId$Builder.buildPartial:()Lorg/apache/hadoop/hbase/protobuf/generated/ClusterIdProtos$ClusterId;
      44: putfield      #16                 // Field clusterId_:Lorg/apache/hadoop/hbase/protobuf/generated/ClusterIdProtos$ClusterId;
      47: goto          55
      50: aload_0
      51: aload_1
      52: putfield      #16                 // Field clusterId_:Lorg/apache/hadoop/hbase/protobuf/generated/ClusterIdProtos$ClusterId;
      55: aload_0
      56: invokevirtual #77                 // Method onChanged:()V
      59: goto          71
      62: aload_0
      63: getfield      #41                 // Field clusterIdBuilder_:Lcom/google/protobuf/SingleFieldBuilder;
      66: aload_1
      67: invokevirtual #139                // Method com/google/protobuf/SingleFieldBuilder.mergeFrom:(Lcom/google/protobuf/GeneratedMessage;)Lcom/google/protobuf/SingleFieldBuilder;
      70: pop
      71: aload_0
      72: dup
      73: getfield      #36                 // Field bitField0_:I
      76: bipush        16
      78: ior
      79: putfield      #36                 // Field bitField0_:I
      82: aload_0
      83: areturn

  public org.apache.hadoop.hbase.protobuf.generated.ClusterStatusProtos$ClusterStatus$Builder clearClusterId();
    Code:
       0: aload_0
       1: getfield      #41                 // Field clusterIdBuilder_:Lcom/google/protobuf/SingleFieldBuilder;
       4: ifnonnull     21
       7: aload_0
       8: invokestatic  #15                 // Method org/apache/hadoop/hbase/protobuf/generated/ClusterIdProtos$ClusterId.getDefaultInstance:()Lorg/apache/hadoop/hbase/protobuf/generated/ClusterIdProtos$ClusterId;
      11: putfield      #16                 // Field clusterId_:Lorg/apache/hadoop/hbase/protobuf/generated/ClusterIdProtos$ClusterId;
      14: aload_0
      15: invokevirtual #77                 // Method onChanged:()V
      18: goto          29
      21: aload_0
      22: getfield      #41                 // Field clusterIdBuilder_:Lcom/google/protobuf/SingleFieldBuilder;
      25: invokevirtual #35                 // Method com/google/protobuf/SingleFieldBuilder.clear:()Lcom/google/protobuf/SingleFieldBuilder;
      28: pop
      29: aload_0
      30: aload_0
      31: getfield      #36                 // Field bitField0_:I
      34: bipush        -17
      36: iand
      37: putfield      #36                 // Field bitField0_:I
      40: aload_0
      41: areturn

  public org.apache.hadoop.hbase.protobuf.generated.ClusterIdProtos$ClusterId$Builder getClusterIdBuilder();
    Code:
       0: aload_0
       1: dup
       2: getfield      #36                 // Field bitField0_:I
       5: bipush        16
       7: ior
       8: putfield      #36                 // Field bitField0_:I
      11: aload_0
      12: invokevirtual #77                 // Method onChanged:()V
      15: aload_0
      16: invokespecial #28                 // Method getClusterIdFieldBuilder:()Lcom/google/protobuf/SingleFieldBuilder;
      19: invokevirtual #140                // Method com/google/protobuf/SingleFieldBuilder.getBuilder:()Lcom/google/protobuf/GeneratedMessage$Builder;
      22: checkcast     #189                // class org/apache/hadoop/hbase/protobuf/generated/ClusterIdProtos$ClusterId$Builder
      25: areturn

  public org.apache.hadoop.hbase.protobuf.generated.ClusterIdProtos$ClusterIdOrBuilder getClusterIdOrBuilder();
    Code:
       0: aload_0
       1: getfield      #41                 // Field clusterIdBuilder_:Lcom/google/protobuf/SingleFieldBuilder;
       4: ifnull        18
       7: aload_0
       8: getfield      #41                 // Field clusterIdBuilder_:Lcom/google/protobuf/SingleFieldBuilder;
      11: invokevirtual #142                // Method com/google/protobuf/SingleFieldBuilder.getMessageOrBuilder:()Lcom/google/protobuf/MessageOrBuilder;
      14: checkcast     #190                // class org/apache/hadoop/hbase/protobuf/generated/ClusterIdProtos$ClusterIdOrBuilder
      17: areturn
      18: aload_0
      19: getfield      #16                 // Field clusterId_:Lorg/apache/hadoop/hbase/protobuf/generated/ClusterIdProtos$ClusterId;
      22: areturn

  public java.util.List<org.apache.hadoop.hbase.protobuf.generated.HBaseProtos$Coprocessor> getMasterCoprocessorsList();
    Code:
       0: aload_0
       1: getfield      #42                 // Field masterCoprocessorsBuilder_:Lcom/google/protobuf/RepeatedFieldBuilder;
       4: ifnonnull     15
       7: aload_0
       8: getfield      #17                 // Field masterCoprocessors_:Ljava/util/List;
      11: invokestatic  #55                 // Method java/util/Collections.unmodifiableList:(Ljava/util/List;)Ljava/util/List;
      14: areturn
      15: aload_0
      16: getfield      #42                 // Field masterCoprocessorsBuilder_:Lcom/google/protobuf/RepeatedFieldBuilder;
      19: invokevirtual #150                // Method com/google/protobuf/RepeatedFieldBuilder.getMessageList:()Ljava/util/List;
      22: areturn

  public int getMasterCoprocessorsCount();
    Code:
       0: aload_0
       1: getfield      #42                 // Field masterCoprocessorsBuilder_:Lcom/google/protobuf/RepeatedFieldBuilder;
       4: ifnonnull     17
       7: aload_0
       8: getfield      #17                 // Field masterCoprocessors_:Ljava/util/List;
      11: invokeinterface #151,  1          // InterfaceMethod java/util/List.size:()I
      16: ireturn
      17: aload_0
      18: getfield      #42                 // Field masterCoprocessorsBuilder_:Lcom/google/protobuf/RepeatedFieldBuilder;
      21: invokevirtual #152                // Method com/google/protobuf/RepeatedFieldBuilder.getCount:()I
      24: ireturn

  public org.apache.hadoop.hbase.protobuf.generated.HBaseProtos$Coprocessor getMasterCoprocessors(int);
    Code:
       0: aload_0
       1: getfield      #42                 // Field masterCoprocessorsBuilder_:Lcom/google/protobuf/RepeatedFieldBuilder;
       4: ifnonnull     21
       7: aload_0
       8: getfield      #17                 // Field masterCoprocessors_:Ljava/util/List;
      11: iload_1
      12: invokeinterface #153,  2          // InterfaceMethod java/util/List.get:(I)Ljava/lang/Object;
      17: checkcast     #191                // class org/apache/hadoop/hbase/protobuf/generated/HBaseProtos$Coprocessor
      20: areturn
      21: aload_0
      22: getfield      #42                 // Field masterCoprocessorsBuilder_:Lcom/google/protobuf/RepeatedFieldBuilder;
      25: iload_1
      26: invokevirtual #155                // Method com/google/protobuf/RepeatedFieldBuilder.getMessage:(I)Lcom/google/protobuf/GeneratedMessage;
      29: checkcast     #191                // class org/apache/hadoop/hbase/protobuf/generated/HBaseProtos$Coprocessor
      32: areturn

  public org.apache.hadoop.hbase.protobuf.generated.ClusterStatusProtos$ClusterStatus$Builder setMasterCoprocessors(int, org.apache.hadoop.hbase.protobuf.generated.HBaseProtos$Coprocessor);
    Code:
       0: aload_0
       1: getfield      #42                 // Field masterCoprocessorsBuilder_:Lcom/google/protobuf/RepeatedFieldBuilder;
       4: ifnonnull     42
       7: aload_2
       8: ifnonnull     19
      11: new           #132                // class java/lang/NullPointerException
      14: dup
      15: invokespecial #133                // Method java/lang/NullPointerException."<init>":()V
      18: athrow
      19: aload_0
      20: invokespecial #92                 // Method ensureMasterCoprocessorsIsMutable:()V
      23: aload_0
      24: getfield      #17                 // Field masterCoprocessors_:Ljava/util/List;
      27: iload_1
      28: aload_2
      29: invokeinterface #156,  3          // InterfaceMethod java/util/List.set:(ILjava/lang/Object;)Ljava/lang/Object;
      34: pop
      35: aload_0
      36: invokevirtual #77                 // Method onChanged:()V
      39: goto          52
      42: aload_0
      43: getfield      #42                 // Field masterCoprocessorsBuilder_:Lcom/google/protobuf/RepeatedFieldBuilder;
      46: iload_1
      47: aload_2
      48: invokevirtual #157                // Method com/google/protobuf/RepeatedFieldBuilder.setMessage:(ILcom/google/protobuf/GeneratedMessage;)Lcom/google/protobuf/RepeatedFieldBuilder;
      51: pop
      52: aload_0
      53: areturn

  public org.apache.hadoop.hbase.protobuf.generated.ClusterStatusProtos$ClusterStatus$Builder setMasterCoprocessors(int, org.apache.hadoop.hbase.protobuf.generated.HBaseProtos$Coprocessor$Builder);
    Code:
       0: aload_0
       1: getfield      #42                 // Field masterCoprocessorsBuilder_:Lcom/google/protobuf/RepeatedFieldBuilder;
       4: ifnonnull     33
       7: aload_0
       8: invokespecial #92                 // Method ensureMasterCoprocessorsIsMutable:()V
      11: aload_0
      12: getfield      #17                 // Field masterCoprocessors_:Ljava/util/List;
      15: iload_1
      16: aload_2
      17: invokevirtual #192                // Method org/apache/hadoop/hbase/protobuf/generated/HBaseProtos$Coprocessor$Builder.build:()Lorg/apache/hadoop/hbase/protobuf/generated/HBaseProtos$Coprocessor;
      20: invokeinterface #156,  3          // InterfaceMethod java/util/List.set:(ILjava/lang/Object;)Ljava/lang/Object;
      25: pop
      26: aload_0
      27: invokevirtual #77                 // Method onChanged:()V
      30: goto          46
      33: aload_0
      34: getfield      #42                 // Field masterCoprocessorsBuilder_:Lcom/google/protobuf/RepeatedFieldBuilder;
      37: iload_1
      38: aload_2
      39: invokevirtual #192                // Method org/apache/hadoop/hbase/protobuf/generated/HBaseProtos$Coprocessor$Builder.build:()Lorg/apache/hadoop/hbase/protobuf/generated/HBaseProtos$Coprocessor;
      42: invokevirtual #157                // Method com/google/protobuf/RepeatedFieldBuilder.setMessage:(ILcom/google/protobuf/GeneratedMessage;)Lcom/google/protobuf/RepeatedFieldBuilder;
      45: pop
      46: aload_0
      47: areturn

  public org.apache.hadoop.hbase.protobuf.generated.ClusterStatusProtos$ClusterStatus$Builder addMasterCoprocessors(org.apache.hadoop.hbase.protobuf.generated.HBaseProtos$Coprocessor);
    Code:
       0: aload_0
       1: getfield      #42                 // Field masterCoprocessorsBuilder_:Lcom/google/protobuf/RepeatedFieldBuilder;
       4: ifnonnull     41
       7: aload_1
       8: ifnonnull     19
      11: new           #132                // class java/lang/NullPointerException
      14: dup
      15: invokespecial #133                // Method java/lang/NullPointerException."<init>":()V
      18: athrow
      19: aload_0
      20: invokespecial #92                 // Method ensureMasterCoprocessorsIsMutable:()V
      23: aload_0
      24: getfield      #17                 // Field masterCoprocessors_:Ljava/util/List;
      27: aload_1
      28: invokeinterface #159,  2          // InterfaceMethod java/util/List.add:(Ljava/lang/Object;)Z
      33: pop
      34: aload_0
      35: invokevirtual #77                 // Method onChanged:()V
      38: goto          50
      41: aload_0
      42: getfield      #42                 // Field masterCoprocessorsBuilder_:Lcom/google/protobuf/RepeatedFieldBuilder;
      45: aload_1
      46: invokevirtual #160                // Method com/google/protobuf/RepeatedFieldBuilder.addMessage:(Lcom/google/protobuf/GeneratedMessage;)Lcom/google/protobuf/RepeatedFieldBuilder;
      49: pop
      50: aload_0
      51: areturn

  public org.apache.hadoop.hbase.protobuf.generated.ClusterStatusProtos$ClusterStatus$Builder addMasterCoprocessors(int, org.apache.hadoop.hbase.protobuf.generated.HBaseProtos$Coprocessor);
    Code:
       0: aload_0
       1: getfield      #42                 // Field masterCoprocessorsBuilder_:Lcom/google/protobuf/RepeatedFieldBuilder;
       4: ifnonnull     41
       7: aload_2
       8: ifnonnull     19
      11: new           #132                // class java/lang/NullPointerException
      14: dup
      15: invokespecial #133                // Method java/lang/NullPointerException."<init>":()V
      18: athrow
      19: aload_0
      20: invokespecial #92                 // Method ensureMasterCoprocessorsIsMutable:()V
      23: aload_0
      24: getfield      #17                 // Field masterCoprocessors_:Ljava/util/List;
      27: iload_1
      28: aload_2
      29: invokeinterface #161,  3          // InterfaceMethod java/util/List.add:(ILjava/lang/Object;)V
      34: aload_0
      35: invokevirtual #77                 // Method onChanged:()V
      38: goto          51
      41: aload_0
      42: getfield      #42                 // Field masterCoprocessorsBuilder_:Lcom/google/protobuf/RepeatedFieldBuilder;
      45: iload_1
      46: aload_2
      47: invokevirtual #162                // Method com/google/protobuf/RepeatedFieldBuilder.addMessage:(ILcom/google/protobuf/GeneratedMessage;)Lcom/google/protobuf/RepeatedFieldBuilder;
      50: pop
      51: aload_0
      52: areturn

  public org.apache.hadoop.hbase.protobuf.generated.ClusterStatusProtos$ClusterStatus$Builder addMasterCoprocessors(org.apache.hadoop.hbase.protobuf.generated.HBaseProtos$Coprocessor$Builder);
    Code:
       0: aload_0
       1: getfield      #42                 // Field masterCoprocessorsBuilder_:Lcom/google/protobuf/RepeatedFieldBuilder;
       4: ifnonnull     32
       7: aload_0
       8: invokespecial #92                 // Method ensureMasterCoprocessorsIsMutable:()V
      11: aload_0
      12: getfield      #17                 // Field masterCoprocessors_:Ljava/util/List;
      15: aload_1
      16: invokevirtual #192                // Method org/apache/hadoop/hbase/protobuf/generated/HBaseProtos$Coprocessor$Builder.build:()Lorg/apache/hadoop/hbase/protobuf/generated/HBaseProtos$Coprocessor;
      19: invokeinterface #159,  2          // InterfaceMethod java/util/List.add:(Ljava/lang/Object;)Z
      24: pop
      25: aload_0
      26: invokevirtual #77                 // Method onChanged:()V
      29: goto          44
      32: aload_0
      33: getfield      #42                 // Field masterCoprocessorsBuilder_:Lcom/google/protobuf/RepeatedFieldBuilder;
      36: aload_1
      37: invokevirtual #192                // Method org/apache/hadoop/hbase/protobuf/generated/HBaseProtos$Coprocessor$Builder.build:()Lorg/apache/hadoop/hbase/protobuf/generated/HBaseProtos$Coprocessor;
      40: invokevirtual #160                // Method com/google/protobuf/RepeatedFieldBuilder.addMessage:(Lcom/google/protobuf/GeneratedMessage;)Lcom/google/protobuf/RepeatedFieldBuilder;
      43: pop
      44: aload_0
      45: areturn

  public org.apache.hadoop.hbase.protobuf.generated.ClusterStatusProtos$ClusterStatus$Builder addMasterCoprocessors(int, org.apache.hadoop.hbase.protobuf.generated.HBaseProtos$Coprocessor$Builder);
    Code:
       0: aload_0
       1: getfield      #42                 // Field masterCoprocessorsBuilder_:Lcom/google/protobuf/RepeatedFieldBuilder;
       4: ifnonnull     32
       7: aload_0
       8: invokespecial #92                 // Method ensureMasterCoprocessorsIsMutable:()V
      11: aload_0
      12: getfield      #17                 // Field masterCoprocessors_:Ljava/util/List;
      15: iload_1
      16: aload_2
      17: invokevirtual #192                // Method org/apache/hadoop/hbase/protobuf/generated/HBaseProtos$Coprocessor$Builder.build:()Lorg/apache/hadoop/hbase/protobuf/generated/HBaseProtos$Coprocessor;
      20: invokeinterface #161,  3          // InterfaceMethod java/util/List.add:(ILjava/lang/Object;)V
      25: aload_0
      26: invokevirtual #77                 // Method onChanged:()V
      29: goto          45
      32: aload_0
      33: getfield      #42                 // Field masterCoprocessorsBuilder_:Lcom/google/protobuf/RepeatedFieldBuilder;
      36: iload_1
      37: aload_2
      38: invokevirtual #192                // Method org/apache/hadoop/hbase/protobuf/generated/HBaseProtos$Coprocessor$Builder.build:()Lorg/apache/hadoop/hbase/protobuf/generated/HBaseProtos$Coprocessor;
      41: invokevirtual #162                // Method com/google/protobuf/RepeatedFieldBuilder.addMessage:(ILcom/google/protobuf/GeneratedMessage;)Lcom/google/protobuf/RepeatedFieldBuilder;
      44: pop
      45: aload_0
      46: areturn

  public org.apache.hadoop.hbase.protobuf.generated.ClusterStatusProtos$ClusterStatus$Builder addAllMasterCoprocessors(java.lang.Iterable<? extends org.apache.hadoop.hbase.protobuf.generated.HBaseProtos$Coprocessor>);
    Code:
       0: aload_0
       1: getfield      #42                 // Field masterCoprocessorsBuilder_:Lcom/google/protobuf/RepeatedFieldBuilder;
       4: ifnonnull     26
       7: aload_0
       8: invokespecial #92                 // Method ensureMasterCoprocessorsIsMutable:()V
      11: aload_1
      12: aload_0
      13: getfield      #17                 // Field masterCoprocessors_:Ljava/util/List;
      16: invokestatic  #163                // Method com/google/protobuf/GeneratedMessage$Builder.addAll:(Ljava/lang/Iterable;Ljava/util/Collection;)V
      19: aload_0
      20: invokevirtual #77                 // Method onChanged:()V
      23: goto          35
      26: aload_0
      27: getfield      #42                 // Field masterCoprocessorsBuilder_:Lcom/google/protobuf/RepeatedFieldBuilder;
      30: aload_1
      31: invokevirtual #81                 // Method com/google/protobuf/RepeatedFieldBuilder.addAllMessages:(Ljava/lang/Iterable;)Lcom/google/protobuf/RepeatedFieldBuilder;
      34: pop
      35: aload_0
      36: areturn

  public org.apache.hadoop.hbase.protobuf.generated.ClusterStatusProtos$ClusterStatus$Builder clearMasterCoprocessors();
    Code:
       0: aload_0
       1: getfield      #42                 // Field masterCoprocessorsBuilder_:Lcom/google/protobuf/RepeatedFieldBuilder;
       4: ifnonnull     32
       7: aload_0
       8: invokestatic  #11                 // Method java/util/Collections.emptyList:()Ljava/util/List;
      11: putfield      #17                 // Field masterCoprocessors_:Ljava/util/List;
      14: aload_0
      15: aload_0
      16: getfield      #36                 // Field bitField0_:I
      19: bipush        -33
      21: iand
      22: putfield      #36                 // Field bitField0_:I
      25: aload_0
      26: invokevirtual #77                 // Method onChanged:()V
      29: goto          39
      32: aload_0
      33: getfield      #42                 // Field masterCoprocessorsBuilder_:Lcom/google/protobuf/RepeatedFieldBuilder;
      36: invokevirtual #38                 // Method com/google/protobuf/RepeatedFieldBuilder.clear:()V
      39: aload_0
      40: areturn

  public org.apache.hadoop.hbase.protobuf.generated.ClusterStatusProtos$ClusterStatus$Builder removeMasterCoprocessors(int);
    Code:
       0: aload_0
       1: getfield      #42                 // Field masterCoprocessorsBuilder_:Lcom/google/protobuf/RepeatedFieldBuilder;
       4: ifnonnull     29
       7: aload_0
       8: invokespecial #92                 // Method ensureMasterCoprocessorsIsMutable:()V
      11: aload_0
      12: getfield      #17                 // Field masterCoprocessors_:Ljava/util/List;
      15: iload_1
      16: invokeinterface #164,  2          // InterfaceMethod java/util/List.remove:(I)Ljava/lang/Object;
      21: pop
      22: aload_0
      23: invokevirtual #77                 // Method onChanged:()V
      26: goto          37
      29: aload_0
      30: getfield      #42                 // Field masterCoprocessorsBuilder_:Lcom/google/protobuf/RepeatedFieldBuilder;
      33: iload_1
      34: invokevirtual #165                // Method com/google/protobuf/RepeatedFieldBuilder.remove:(I)V
      37: aload_0
      38: areturn

  public org.apache.hadoop.hbase.protobuf.generated.HBaseProtos$Coprocessor$Builder getMasterCoprocessorsBuilder(int);
    Code:
       0: aload_0
       1: invokespecial #29                 // Method getMasterCoprocessorsFieldBuilder:()Lcom/google/protobuf/RepeatedFieldBuilder;
       4: iload_1
       5: invokevirtual #166                // Method com/google/protobuf/RepeatedFieldBuilder.getBuilder:(I)Lcom/google/protobuf/GeneratedMessage$Builder;
       8: checkcast     #193                // class org/apache/hadoop/hbase/protobuf/generated/HBaseProtos$Coprocessor$Builder
      11: areturn

  public org.apache.hadoop.hbase.protobuf.generated.HBaseProtos$CoprocessorOrBuilder getMasterCoprocessorsOrBuilder(int);
    Code:
       0: aload_0
       1: getfield      #42                 // Field masterCoprocessorsBuilder_:Lcom/google/protobuf/RepeatedFieldBuilder;
       4: ifnonnull     21
       7: aload_0
       8: getfield      #17                 // Field masterCoprocessors_:Ljava/util/List;
      11: iload_1
      12: invokeinterface #153,  2          // InterfaceMethod java/util/List.get:(I)Ljava/lang/Object;
      17: checkcast     #194                // class org/apache/hadoop/hbase/protobuf/generated/HBaseProtos$CoprocessorOrBuilder
      20: areturn
      21: aload_0
      22: getfield      #42                 // Field masterCoprocessorsBuilder_:Lcom/google/protobuf/RepeatedFieldBuilder;
      25: iload_1
      26: invokevirtual #169                // Method com/google/protobuf/RepeatedFieldBuilder.getMessageOrBuilder:(I)Lcom/google/protobuf/MessageOrBuilder;
      29: checkcast     #194                // class org/apache/hadoop/hbase/protobuf/generated/HBaseProtos$CoprocessorOrBuilder
      32: areturn

  public java.util.List<? extends org.apache.hadoop.hbase.protobuf.generated.HBaseProtos$CoprocessorOrBuilder> getMasterCoprocessorsOrBuilderList();
    Code:
       0: aload_0
       1: getfield      #42                 // Field masterCoprocessorsBuilder_:Lcom/google/protobuf/RepeatedFieldBuilder;
       4: ifnull        15
       7: aload_0
       8: getfield      #42                 // Field masterCoprocessorsBuilder_:Lcom/google/protobuf/RepeatedFieldBuilder;
      11: invokevirtual #170                // Method com/google/protobuf/RepeatedFieldBuilder.getMessageOrBuilderList:()Ljava/util/List;
      14: areturn
      15: aload_0
      16: getfield      #17                 // Field masterCoprocessors_:Ljava/util/List;
      19: invokestatic  #55                 // Method java/util/Collections.unmodifiableList:(Ljava/util/List;)Ljava/util/List;
      22: areturn

  public org.apache.hadoop.hbase.protobuf.generated.HBaseProtos$Coprocessor$Builder addMasterCoprocessorsBuilder();
    Code:
       0: aload_0
       1: invokespecial #29                 // Method getMasterCoprocessorsFieldBuilder:()Lcom/google/protobuf/RepeatedFieldBuilder;
       4: invokestatic  #195                // Method org/apache/hadoop/hbase/protobuf/generated/HBaseProtos$Coprocessor.getDefaultInstance:()Lorg/apache/hadoop/hbase/protobuf/generated/HBaseProtos$Coprocessor;
       7: invokevirtual #172                // Method com/google/protobuf/RepeatedFieldBuilder.addBuilder:(Lcom/google/protobuf/GeneratedMessage;)Lcom/google/protobuf/GeneratedMessage$Builder;
      10: checkcast     #193                // class org/apache/hadoop/hbase/protobuf/generated/HBaseProtos$Coprocessor$Builder
      13: areturn

  public org.apache.hadoop.hbase.protobuf.generated.HBaseProtos$Coprocessor$Builder addMasterCoprocessorsBuilder(int);
    Code:
       0: aload_0
       1: invokespecial #29                 // Method getMasterCoprocessorsFieldBuilder:()Lcom/google/protobuf/RepeatedFieldBuilder;
       4: iload_1
       5: invokestatic  #195                // Method org/apache/hadoop/hbase/protobuf/generated/HBaseProtos$Coprocessor.getDefaultInstance:()Lorg/apache/hadoop/hbase/protobuf/generated/HBaseProtos$Coprocessor;
       8: invokevirtual #173                // Method com/google/protobuf/RepeatedFieldBuilder.addBuilder:(ILcom/google/protobuf/GeneratedMessage;)Lcom/google/protobuf/GeneratedMessage$Builder;
      11: checkcast     #193                // class org/apache/hadoop/hbase/protobuf/generated/HBaseProtos$Coprocessor$Builder
      14: areturn

  public java.util.List<org.apache.hadoop.hbase.protobuf.generated.HBaseProtos$Coprocessor$Builder> getMasterCoprocessorsBuilderList();
    Code:
       0: aload_0
       1: invokespecial #29                 // Method getMasterCoprocessorsFieldBuilder:()Lcom/google/protobuf/RepeatedFieldBuilder;
       4: invokevirtual #174                // Method com/google/protobuf/RepeatedFieldBuilder.getBuilderList:()Ljava/util/List;
       7: areturn

  public boolean hasMaster();
    Code:
       0: aload_0
       1: getfield      #36                 // Field bitField0_:I
       4: bipush        64
       6: iand
       7: bipush        64
       9: if_icmpne     16
      12: iconst_1
      13: goto          17
      16: iconst_0
      17: ireturn

  public org.apache.hadoop.hbase.protobuf.generated.HBaseProtos$ServerName getMaster();
    Code:
       0: aload_0
       1: getfield      #43                 // Field masterBuilder_:Lcom/google/protobuf/SingleFieldBuilder;
       4: ifnonnull     12
       7: aload_0
       8: getfield      #19                 // Field master_:Lorg/apache/hadoop/hbase/protobuf/generated/HBaseProtos$ServerName;
      11: areturn
      12: aload_0
      13: getfield      #43                 // Field masterBuilder_:Lcom/google/protobuf/SingleFieldBuilder;
      16: invokevirtual #131                // Method com/google/protobuf/SingleFieldBuilder.getMessage:()Lcom/google/protobuf/GeneratedMessage;
      19: checkcast     #64                 // class org/apache/hadoop/hbase/protobuf/generated/HBaseProtos$ServerName
      22: areturn

  public org.apache.hadoop.hbase.protobuf.generated.ClusterStatusProtos$ClusterStatus$Builder setMaster(org.apache.hadoop.hbase.protobuf.generated.HBaseProtos$ServerName);
    Code:
       0: aload_0
       1: getfield      #43                 // Field masterBuilder_:Lcom/google/protobuf/SingleFieldBuilder;
       4: ifnonnull     31
       7: aload_1
       8: ifnonnull     19
      11: new           #132                // class java/lang/NullPointerException
      14: dup
      15: invokespecial #133                // Method java/lang/NullPointerException."<init>":()V
      18: athrow
      19: aload_0
      20: aload_1
      21: putfield      #19                 // Field master_:Lorg/apache/hadoop/hbase/protobuf/generated/HBaseProtos$ServerName;
      24: aload_0
      25: invokevirtual #77                 // Method onChanged:()V
      28: goto          40
      31: aload_0
      32: getfield      #43                 // Field masterBuilder_:Lcom/google/protobuf/SingleFieldBuilder;
      35: aload_1
      36: invokevirtual #134                // Method com/google/protobuf/SingleFieldBuilder.setMessage:(Lcom/google/protobuf/GeneratedMessage;)Lcom/google/protobuf/SingleFieldBuilder;
      39: pop
      40: aload_0
      41: dup
      42: getfield      #36                 // Field bitField0_:I
      45: bipush        64
      47: ior
      48: putfield      #36                 // Field bitField0_:I
      51: aload_0
      52: areturn

  public org.apache.hadoop.hbase.protobuf.generated.ClusterStatusProtos$ClusterStatus$Builder setMaster(org.apache.hadoop.hbase.protobuf.generated.HBaseProtos$ServerName$Builder);
    Code:
       0: aload_0
       1: getfield      #43                 // Field masterBuilder_:Lcom/google/protobuf/SingleFieldBuilder;
       4: ifnonnull     22
       7: aload_0
       8: aload_1
       9: invokevirtual #177                // Method org/apache/hadoop/hbase/protobuf/generated/HBaseProtos$ServerName$Builder.build:()Lorg/apache/hadoop/hbase/protobuf/generated/HBaseProtos$ServerName;
      12: putfield      #19                 // Field master_:Lorg/apache/hadoop/hbase/protobuf/generated/HBaseProtos$ServerName;
      15: aload_0
      16: invokevirtual #77                 // Method onChanged:()V
      19: goto          34
      22: aload_0
      23: getfield      #43                 // Field masterBuilder_:Lcom/google/protobuf/SingleFieldBuilder;
      26: aload_1
      27: invokevirtual #177                // Method org/apache/hadoop/hbase/protobuf/generated/HBaseProtos$ServerName$Builder.build:()Lorg/apache/hadoop/hbase/protobuf/generated/HBaseProtos$ServerName;
      30: invokevirtual #134                // Method com/google/protobuf/SingleFieldBuilder.setMessage:(Lcom/google/protobuf/GeneratedMessage;)Lcom/google/protobuf/SingleFieldBuilder;
      33: pop
      34: aload_0
      35: dup
      36: getfield      #36                 // Field bitField0_:I
      39: bipush        64
      41: ior
      42: putfield      #36                 // Field bitField0_:I
      45: aload_0
      46: areturn

  public org.apache.hadoop.hbase.protobuf.generated.ClusterStatusProtos$ClusterStatus$Builder mergeMaster(org.apache.hadoop.hbase.protobuf.generated.HBaseProtos$ServerName);
    Code:
       0: aload_0
       1: getfield      #43                 // Field masterBuilder_:Lcom/google/protobuf/SingleFieldBuilder;
       4: ifnonnull     62
       7: aload_0
       8: getfield      #36                 // Field bitField0_:I
      11: bipush        64
      13: iand
      14: bipush        64
      16: if_icmpne     50
      19: aload_0
      20: getfield      #19                 // Field master_:Lorg/apache/hadoop/hbase/protobuf/generated/HBaseProtos$ServerName;
      23: invokestatic  #18                 // Method org/apache/hadoop/hbase/protobuf/generated/HBaseProtos$ServerName.getDefaultInstance:()Lorg/apache/hadoop/hbase/protobuf/generated/HBaseProtos$ServerName;
      26: if_acmpeq     50
      29: aload_0
      30: aload_0
      31: getfield      #19                 // Field master_:Lorg/apache/hadoop/hbase/protobuf/generated/HBaseProtos$ServerName;
      34: invokestatic  #196                // Method org/apache/hadoop/hbase/protobuf/generated/HBaseProtos$ServerName.newBuilder:(Lorg/apache/hadoop/hbase/protobuf/generated/HBaseProtos$ServerName;)Lorg/apache/hadoop/hbase/protobuf/generated/HBaseProtos$ServerName$Builder;
      37: aload_1
      38: invokevirtual #197                // Method org/apache/hadoop/hbase/protobuf/generated/HBaseProtos$ServerName$Builder.mergeFrom:(Lorg/apache/hadoop/hbase/protobuf/generated/HBaseProtos$ServerName;)Lorg/apache/hadoop/hbase/protobuf/generated/HBaseProtos$ServerName$Builder;
      41: invokevirtual #198                // Method org/apache/hadoop/hbase/protobuf/generated/HBaseProtos$ServerName$Builder.buildPartial:()Lorg/apache/hadoop/hbase/protobuf/generated/HBaseProtos$ServerName;
      44: putfield      #19                 // Field master_:Lorg/apache/hadoop/hbase/protobuf/generated/HBaseProtos$ServerName;
      47: goto          55
      50: aload_0
      51: aload_1
      52: putfield      #19                 // Field master_:Lorg/apache/hadoop/hbase/protobuf/generated/HBaseProtos$ServerName;
      55: aload_0
      56: invokevirtual #77                 // Method onChanged:()V
      59: goto          71
      62: aload_0
      63: getfield      #43                 // Field masterBuilder_:Lcom/google/protobuf/SingleFieldBuilder;
      66: aload_1
      67: invokevirtual #139                // Method com/google/protobuf/SingleFieldBuilder.mergeFrom:(Lcom/google/protobuf/GeneratedMessage;)Lcom/google/protobuf/SingleFieldBuilder;
      70: pop
      71: aload_0
      72: dup
      73: getfield      #36                 // Field bitField0_:I
      76: bipush        64
      78: ior
      79: putfield      #36                 // Field bitField0_:I
      82: aload_0
      83: areturn

  public org.apache.hadoop.hbase.protobuf.generated.ClusterStatusProtos$ClusterStatus$Builder clearMaster();
    Code:
       0: aload_0
       1: getfield      #43                 // Field masterBuilder_:Lcom/google/protobuf/SingleFieldBuilder;
       4: ifnonnull     21
       7: aload_0
       8: invokestatic  #18                 // Method org/apache/hadoop/hbase/protobuf/generated/HBaseProtos$ServerName.getDefaultInstance:()Lorg/apache/hadoop/hbase/protobuf/generated/HBaseProtos$ServerName;
      11: putfield      #19                 // Field master_:Lorg/apache/hadoop/hbase/protobuf/generated/HBaseProtos$ServerName;
      14: aload_0
      15: invokevirtual #77                 // Method onChanged:()V
      18: goto          29
      21: aload_0
      22: getfield      #43                 // Field masterBuilder_:Lcom/google/protobuf/SingleFieldBuilder;
      25: invokevirtual #35                 // Method com/google/protobuf/SingleFieldBuilder.clear:()Lcom/google/protobuf/SingleFieldBuilder;
      28: pop
      29: aload_0
      30: aload_0
      31: getfield      #36                 // Field bitField0_:I
      34: bipush        -65
      36: iand
      37: putfield      #36                 // Field bitField0_:I
      40: aload_0
      41: areturn

  public org.apache.hadoop.hbase.protobuf.generated.HBaseProtos$ServerName$Builder getMasterBuilder();
    Code:
       0: aload_0
       1: dup
       2: getfield      #36                 // Field bitField0_:I
       5: bipush        64
       7: ior
       8: putfield      #36                 // Field bitField0_:I
      11: aload_0
      12: invokevirtual #77                 // Method onChanged:()V
      15: aload_0
      16: invokespecial #30                 // Method getMasterFieldBuilder:()Lcom/google/protobuf/SingleFieldBuilder;
      19: invokevirtual #140                // Method com/google/protobuf/SingleFieldBuilder.getBuilder:()Lcom/google/protobuf/GeneratedMessage$Builder;
      22: checkcast     #178                // class org/apache/hadoop/hbase/protobuf/generated/HBaseProtos$ServerName$Builder
      25: areturn

  public org.apache.hadoop.hbase.protobuf.generated.HBaseProtos$ServerNameOrBuilder getMasterOrBuilder();
    Code:
       0: aload_0
       1: getfield      #43                 // Field masterBuilder_:Lcom/google/protobuf/SingleFieldBuilder;
       4: ifnull        18
       7: aload_0
       8: getfield      #43                 // Field masterBuilder_:Lcom/google/protobuf/SingleFieldBuilder;
      11: invokevirtual #142                // Method com/google/protobuf/SingleFieldBuilder.getMessageOrBuilder:()Lcom/google/protobuf/MessageOrBuilder;
      14: checkcast     #179                // class org/apache/hadoop/hbase/protobuf/generated/HBaseProtos$ServerNameOrBuilder
      17: areturn
      18: aload_0
      19: getfield      #19                 // Field master_:Lorg/apache/hadoop/hbase/protobuf/generated/HBaseProtos$ServerName;
      22: areturn

  public java.util.List<org.apache.hadoop.hbase.protobuf.generated.HBaseProtos$ServerName> getBackupMastersList();
    Code:
       0: aload_0
       1: getfield      #44                 // Field backupMastersBuilder_:Lcom/google/protobuf/RepeatedFieldBuilder;
       4: ifnonnull     15
       7: aload_0
       8: getfield      #20                 // Field backupMasters_:Ljava/util/List;
      11: invokestatic  #55                 // Method java/util/Collections.unmodifiableList:(Ljava/util/List;)Ljava/util/List;
      14: areturn
      15: aload_0
      16: getfield      #44                 // Field backupMastersBuilder_:Lcom/google/protobuf/RepeatedFieldBuilder;
      19: invokevirtual #150                // Method com/google/protobuf/RepeatedFieldBuilder.getMessageList:()Ljava/util/List;
      22: areturn

  public int getBackupMastersCount();
    Code:
       0: aload_0
       1: getfield      #44                 // Field backupMastersBuilder_:Lcom/google/protobuf/RepeatedFieldBuilder;
       4: ifnonnull     17
       7: aload_0
       8: getfield      #20                 // Field backupMasters_:Ljava/util/List;
      11: invokeinterface #151,  1          // InterfaceMethod java/util/List.size:()I
      16: ireturn
      17: aload_0
      18: getfield      #44                 // Field backupMastersBuilder_:Lcom/google/protobuf/RepeatedFieldBuilder;
      21: invokevirtual #152                // Method com/google/protobuf/RepeatedFieldBuilder.getCount:()I
      24: ireturn

  public org.apache.hadoop.hbase.protobuf.generated.HBaseProtos$ServerName getBackupMasters(int);
    Code:
       0: aload_0
       1: getfield      #44                 // Field backupMastersBuilder_:Lcom/google/protobuf/RepeatedFieldBuilder;
       4: ifnonnull     21
       7: aload_0
       8: getfield      #20                 // Field backupMasters_:Ljava/util/List;
      11: iload_1
      12: invokeinterface #153,  2          // InterfaceMethod java/util/List.get:(I)Ljava/lang/Object;
      17: checkcast     #64                 // class org/apache/hadoop/hbase/protobuf/generated/HBaseProtos$ServerName
      20: areturn
      21: aload_0
      22: getfield      #44                 // Field backupMastersBuilder_:Lcom/google/protobuf/RepeatedFieldBuilder;
      25: iload_1
      26: invokevirtual #155                // Method com/google/protobuf/RepeatedFieldBuilder.getMessage:(I)Lcom/google/protobuf/GeneratedMessage;
      29: checkcast     #64                 // class org/apache/hadoop/hbase/protobuf/generated/HBaseProtos$ServerName
      32: areturn

  public org.apache.hadoop.hbase.protobuf.generated.ClusterStatusProtos$ClusterStatus$Builder setBackupMasters(int, org.apache.hadoop.hbase.protobuf.generated.HBaseProtos$ServerName);
    Code:
       0: aload_0
       1: getfield      #44                 // Field backupMastersBuilder_:Lcom/google/protobuf/RepeatedFieldBuilder;
       4: ifnonnull     42
       7: aload_2
       8: ifnonnull     19
      11: new           #132                // class java/lang/NullPointerException
      14: dup
      15: invokespecial #133                // Method java/lang/NullPointerException."<init>":()V
      18: athrow
      19: aload_0
      20: invokespecial #98                 // Method ensureBackupMastersIsMutable:()V
      23: aload_0
      24: getfield      #20                 // Field backupMasters_:Ljava/util/List;
      27: iload_1
      28: aload_2
      29: invokeinterface #156,  3          // InterfaceMethod java/util/List.set:(ILjava/lang/Object;)Ljava/lang/Object;
      34: pop
      35: aload_0
      36: invokevirtual #77                 // Method onChanged:()V
      39: goto          52
      42: aload_0
      43: getfield      #44                 // Field backupMastersBuilder_:Lcom/google/protobuf/RepeatedFieldBuilder;
      46: iload_1
      47: aload_2
      48: invokevirtual #157                // Method com/google/protobuf/RepeatedFieldBuilder.setMessage:(ILcom/google/protobuf/GeneratedMessage;)Lcom/google/protobuf/RepeatedFieldBuilder;
      51: pop
      52: aload_0
      53: areturn

  public org.apache.hadoop.hbase.protobuf.generated.ClusterStatusProtos$ClusterStatus$Builder setBackupMasters(int, org.apache.hadoop.hbase.protobuf.generated.HBaseProtos$ServerName$Builder);
    Code:
       0: aload_0
       1: getfield      #44                 // Field backupMastersBuilder_:Lcom/google/protobuf/RepeatedFieldBuilder;
       4: ifnonnull     33
       7: aload_0
       8: invokespecial #98                 // Method ensureBackupMastersIsMutable:()V
      11: aload_0
      12: getfield      #20                 // Field backupMasters_:Ljava/util/List;
      15: iload_1
      16: aload_2
      17: invokevirtual #177                // Method org/apache/hadoop/hbase/protobuf/generated/HBaseProtos$ServerName$Builder.build:()Lorg/apache/hadoop/hbase/protobuf/generated/HBaseProtos$ServerName;
      20: invokeinterface #156,  3          // InterfaceMethod java/util/List.set:(ILjava/lang/Object;)Ljava/lang/Object;
      25: pop
      26: aload_0
      27: invokevirtual #77                 // Method onChanged:()V
      30: goto          46
      33: aload_0
      34: getfield      #44                 // Field backupMastersBuilder_:Lcom/google/protobuf/RepeatedFieldBuilder;
      37: iload_1
      38: aload_2
      39: invokevirtual #177                // Method org/apache/hadoop/hbase/protobuf/generated/HBaseProtos$ServerName$Builder.build:()Lorg/apache/hadoop/hbase/protobuf/generated/HBaseProtos$ServerName;
      42: invokevirtual #157                // Method com/google/protobuf/RepeatedFieldBuilder.setMessage:(ILcom/google/protobuf/GeneratedMessage;)Lcom/google/protobuf/RepeatedFieldBuilder;
      45: pop
      46: aload_0
      47: areturn

  public org.apache.hadoop.hbase.protobuf.generated.ClusterStatusProtos$ClusterStatus$Builder addBackupMasters(org.apache.hadoop.hbase.protobuf.generated.HBaseProtos$ServerName);
    Code:
       0: aload_0
       1: getfield      #44                 // Field backupMastersBuilder_:Lcom/google/protobuf/RepeatedFieldBuilder;
       4: ifnonnull     41
       7: aload_1
       8: ifnonnull     19
      11: new           #132                // class java/lang/NullPointerException
      14: dup
      15: invokespecial #133                // Method java/lang/NullPointerException."<init>":()V
      18: athrow
      19: aload_0
      20: invokespecial #98                 // Method ensureBackupMastersIsMutable:()V
      23: aload_0
      24: getfield      #20                 // Field backupMasters_:Ljava/util/List;
      27: aload_1
      28: invokeinterface #159,  2          // InterfaceMethod java/util/List.add:(Ljava/lang/Object;)Z
      33: pop
      34: aload_0
      35: invokevirtual #77                 // Method onChanged:()V
      38: goto          50
      41: aload_0
      42: getfield      #44                 // Field backupMastersBuilder_:Lcom/google/protobuf/RepeatedFieldBuilder;
      45: aload_1
      46: invokevirtual #160                // Method com/google/protobuf/RepeatedFieldBuilder.addMessage:(Lcom/google/protobuf/GeneratedMessage;)Lcom/google/protobuf/RepeatedFieldBuilder;
      49: pop
      50: aload_0
      51: areturn

  public org.apache.hadoop.hbase.protobuf.generated.ClusterStatusProtos$ClusterStatus$Builder addBackupMasters(int, org.apache.hadoop.hbase.protobuf.generated.HBaseProtos$ServerName);
    Code:
       0: aload_0
       1: getfield      #44                 // Field backupMastersBuilder_:Lcom/google/protobuf/RepeatedFieldBuilder;
       4: ifnonnull     41
       7: aload_2
       8: ifnonnull     19
      11: new           #132                // class java/lang/NullPointerException
      14: dup
      15: invokespecial #133                // Method java/lang/NullPointerException."<init>":()V
      18: athrow
      19: aload_0
      20: invokespecial #98                 // Method ensureBackupMastersIsMutable:()V
      23: aload_0
      24: getfield      #20                 // Field backupMasters_:Ljava/util/List;
      27: iload_1
      28: aload_2
      29: invokeinterface #161,  3          // InterfaceMethod java/util/List.add:(ILjava/lang/Object;)V
      34: aload_0
      35: invokevirtual #77                 // Method onChanged:()V
      38: goto          51
      41: aload_0
      42: getfield      #44                 // Field backupMastersBuilder_:Lcom/google/protobuf/RepeatedFieldBuilder;
      45: iload_1
      46: aload_2
      47: invokevirtual #162                // Method com/google/protobuf/RepeatedFieldBuilder.addMessage:(ILcom/google/protobuf/GeneratedMessage;)Lcom/google/protobuf/RepeatedFieldBuilder;
      50: pop
      51: aload_0
      52: areturn

  public org.apache.hadoop.hbase.protobuf.generated.ClusterStatusProtos$ClusterStatus$Builder addBackupMasters(org.apache.hadoop.hbase.protobuf.generated.HBaseProtos$ServerName$Builder);
    Code:
       0: aload_0
       1: getfield      #44                 // Field backupMastersBuilder_:Lcom/google/protobuf/RepeatedFieldBuilder;
       4: ifnonnull     32
       7: aload_0
       8: invokespecial #98                 // Method ensureBackupMastersIsMutable:()V
      11: aload_0
      12: getfield      #20                 // Field backupMasters_:Ljava/util/List;
      15: aload_1
      16: invokevirtual #177                // Method org/apache/hadoop/hbase/protobuf/generated/HBaseProtos$ServerName$Builder.build:()Lorg/apache/hadoop/hbase/protobuf/generated/HBaseProtos$ServerName;
      19: invokeinterface #159,  2          // InterfaceMethod java/util/List.add:(Ljava/lang/Object;)Z
      24: pop
      25: aload_0
      26: invokevirtual #77                 // Method onChanged:()V
      29: goto          44
      32: aload_0
      33: getfield      #44                 // Field backupMastersBuilder_:Lcom/google/protobuf/RepeatedFieldBuilder;
      36: aload_1
      37: invokevirtual #177                // Method org/apache/hadoop/hbase/protobuf/generated/HBaseProtos$ServerName$Builder.build:()Lorg/apache/hadoop/hbase/protobuf/generated/HBaseProtos$ServerName;
      40: invokevirtual #160                // Method com/google/protobuf/RepeatedFieldBuilder.addMessage:(Lcom/google/protobuf/GeneratedMessage;)Lcom/google/protobuf/RepeatedFieldBuilder;
      43: pop
      44: aload_0
      45: areturn

  public org.apache.hadoop.hbase.protobuf.generated.ClusterStatusProtos$ClusterStatus$Builder addBackupMasters(int, org.apache.hadoop.hbase.protobuf.generated.HBaseProtos$ServerName$Builder);
    Code:
       0: aload_0
       1: getfield      #44                 // Field backupMastersBuilder_:Lcom/google/protobuf/RepeatedFieldBuilder;
       4: ifnonnull     32
       7: aload_0
       8: invokespecial #98                 // Method ensureBackupMastersIsMutable:()V
      11: aload_0
      12: getfield      #20                 // Field backupMasters_:Ljava/util/List;
      15: iload_1
      16: aload_2
      17: invokevirtual #177                // Method org/apache/hadoop/hbase/protobuf/generated/HBaseProtos$ServerName$Builder.build:()Lorg/apache/hadoop/hbase/protobuf/generated/HBaseProtos$ServerName;
      20: invokeinterface #161,  3          // InterfaceMethod java/util/List.add:(ILjava/lang/Object;)V
      25: aload_0
      26: invokevirtual #77                 // Method onChanged:()V
      29: goto          45
      32: aload_0
      33: getfield      #44                 // Field backupMastersBuilder_:Lcom/google/protobuf/RepeatedFieldBuilder;
      36: iload_1
      37: aload_2
      38: invokevirtual #177                // Method org/apache/hadoop/hbase/protobuf/generated/HBaseProtos$ServerName$Builder.build:()Lorg/apache/hadoop/hbase/protobuf/generated/HBaseProtos$ServerName;
      41: invokevirtual #162                // Method com/google/protobuf/RepeatedFieldBuilder.addMessage:(ILcom/google/protobuf/GeneratedMessage;)Lcom/google/protobuf/RepeatedFieldBuilder;
      44: pop
      45: aload_0
      46: areturn

  public org.apache.hadoop.hbase.protobuf.generated.ClusterStatusProtos$ClusterStatus$Builder addAllBackupMasters(java.lang.Iterable<? extends org.apache.hadoop.hbase.protobuf.generated.HBaseProtos$ServerName>);
    Code:
       0: aload_0
       1: getfield      #44                 // Field backupMastersBuilder_:Lcom/google/protobuf/RepeatedFieldBuilder;
       4: ifnonnull     26
       7: aload_0
       8: invokespecial #98                 // Method ensureBackupMastersIsMutable:()V
      11: aload_1
      12: aload_0
      13: getfield      #20                 // Field backupMasters_:Ljava/util/List;
      16: invokestatic  #163                // Method com/google/protobuf/GeneratedMessage$Builder.addAll:(Ljava/lang/Iterable;Ljava/util/Collection;)V
      19: aload_0
      20: invokevirtual #77                 // Method onChanged:()V
      23: goto          35
      26: aload_0
      27: getfield      #44                 // Field backupMastersBuilder_:Lcom/google/protobuf/RepeatedFieldBuilder;
      30: aload_1
      31: invokevirtual #81                 // Method com/google/protobuf/RepeatedFieldBuilder.addAllMessages:(Ljava/lang/Iterable;)Lcom/google/protobuf/RepeatedFieldBuilder;
      34: pop
      35: aload_0
      36: areturn

  public org.apache.hadoop.hbase.protobuf.generated.ClusterStatusProtos$ClusterStatus$Builder clearBackupMasters();
    Code:
       0: aload_0
       1: getfield      #44                 // Field backupMastersBuilder_:Lcom/google/protobuf/RepeatedFieldBuilder;
       4: ifnonnull     33
       7: aload_0
       8: invokestatic  #11                 // Method java/util/Collections.emptyList:()Ljava/util/List;
      11: putfield      #20                 // Field backupMasters_:Ljava/util/List;
      14: aload_0
      15: aload_0
      16: getfield      #36                 // Field bitField0_:I
      19: sipush        -129
      22: iand
      23: putfield      #36                 // Field bitField0_:I
      26: aload_0
      27: invokevirtual #77                 // Method onChanged:()V
      30: goto          40
      33: aload_0
      34: getfield      #44                 // Field backupMastersBuilder_:Lcom/google/protobuf/RepeatedFieldBuilder;
      37: invokevirtual #38                 // Method com/google/protobuf/RepeatedFieldBuilder.clear:()V
      40: aload_0
      41: areturn

  public org.apache.hadoop.hbase.protobuf.generated.ClusterStatusProtos$ClusterStatus$Builder removeBackupMasters(int);
    Code:
       0: aload_0
       1: getfield      #44                 // Field backupMastersBuilder_:Lcom/google/protobuf/RepeatedFieldBuilder;
       4: ifnonnull     29
       7: aload_0
       8: invokespecial #98                 // Method ensureBackupMastersIsMutable:()V
      11: aload_0
      12: getfield      #20                 // Field backupMasters_:Ljava/util/List;
      15: iload_1
      16: invokeinterface #164,  2          // InterfaceMethod java/util/List.remove:(I)Ljava/lang/Object;
      21: pop
      22: aload_0
      23: invokevirtual #77                 // Method onChanged:()V
      26: goto          37
      29: aload_0
      30: getfield      #44                 // Field backupMastersBuilder_:Lcom/google/protobuf/RepeatedFieldBuilder;
      33: iload_1
      34: invokevirtual #165                // Method com/google/protobuf/RepeatedFieldBuilder.remove:(I)V
      37: aload_0
      38: areturn

  public org.apache.hadoop.hbase.protobuf.generated.HBaseProtos$ServerName$Builder getBackupMastersBuilder(int);
    Code:
       0: aload_0
       1: invokespecial #31                 // Method getBackupMastersFieldBuilder:()Lcom/google/protobuf/RepeatedFieldBuilder;
       4: iload_1
       5: invokevirtual #166                // Method com/google/protobuf/RepeatedFieldBuilder.getBuilder:(I)Lcom/google/protobuf/GeneratedMessage$Builder;
       8: checkcast     #178                // class org/apache/hadoop/hbase/protobuf/generated/HBaseProtos$ServerName$Builder
      11: areturn

  public org.apache.hadoop.hbase.protobuf.generated.HBaseProtos$ServerNameOrBuilder getBackupMastersOrBuilder(int);
    Code:
       0: aload_0
       1: getfield      #44                 // Field backupMastersBuilder_:Lcom/google/protobuf/RepeatedFieldBuilder;
       4: ifnonnull     21
       7: aload_0
       8: getfield      #20                 // Field backupMasters_:Ljava/util/List;
      11: iload_1
      12: invokeinterface #153,  2          // InterfaceMethod java/util/List.get:(I)Ljava/lang/Object;
      17: checkcast     #179                // class org/apache/hadoop/hbase/protobuf/generated/HBaseProtos$ServerNameOrBuilder
      20: areturn
      21: aload_0
      22: getfield      #44                 // Field backupMastersBuilder_:Lcom/google/protobuf/RepeatedFieldBuilder;
      25: iload_1
      26: invokevirtual #169                // Method com/google/protobuf/RepeatedFieldBuilder.getMessageOrBuilder:(I)Lcom/google/protobuf/MessageOrBuilder;
      29: checkcast     #179                // class org/apache/hadoop/hbase/protobuf/generated/HBaseProtos$ServerNameOrBuilder
      32: areturn

  public java.util.List<? extends org.apache.hadoop.hbase.protobuf.generated.HBaseProtos$ServerNameOrBuilder> getBackupMastersOrBuilderList();
    Code:
       0: aload_0
       1: getfield      #44                 // Field backupMastersBuilder_:Lcom/google/protobuf/RepeatedFieldBuilder;
       4: ifnull        15
       7: aload_0
       8: getfield      #44                 // Field backupMastersBuilder_:Lcom/google/protobuf/RepeatedFieldBuilder;
      11: invokevirtual #170                // Method com/google/protobuf/RepeatedFieldBuilder.getMessageOrBuilderList:()Ljava/util/List;
      14: areturn
      15: aload_0
      16: getfield      #20                 // Field backupMasters_:Ljava/util/List;
      19: invokestatic  #55                 // Method java/util/Collections.unmodifiableList:(Ljava/util/List;)Ljava/util/List;
      22: areturn

  public org.apache.hadoop.hbase.protobuf.generated.HBaseProtos$ServerName$Builder addBackupMastersBuilder();
    Code:
       0: aload_0
       1: invokespecial #31                 // Method getBackupMastersFieldBuilder:()Lcom/google/protobuf/RepeatedFieldBuilder;
       4: invokestatic  #18                 // Method org/apache/hadoop/hbase/protobuf/generated/HBaseProtos$ServerName.getDefaultInstance:()Lorg/apache/hadoop/hbase/protobuf/generated/HBaseProtos$ServerName;
       7: invokevirtual #172                // Method com/google/protobuf/RepeatedFieldBuilder.addBuilder:(Lcom/google/protobuf/GeneratedMessage;)Lcom/google/protobuf/GeneratedMessage$Builder;
      10: checkcast     #178                // class org/apache/hadoop/hbase/protobuf/generated/HBaseProtos$ServerName$Builder
      13: areturn

  public org.apache.hadoop.hbase.protobuf.generated.HBaseProtos$ServerName$Builder addBackupMastersBuilder(int);
    Code:
       0: aload_0
       1: invokespecial #31                 // Method getBackupMastersFieldBuilder:()Lcom/google/protobuf/RepeatedFieldBuilder;
       4: iload_1
       5: invokestatic  #18                 // Method org/apache/hadoop/hbase/protobuf/generated/HBaseProtos$ServerName.getDefaultInstance:()Lorg/apache/hadoop/hbase/protobuf/generated/HBaseProtos$ServerName;
       8: invokevirtual #173                // Method com/google/protobuf/RepeatedFieldBuilder.addBuilder:(ILcom/google/protobuf/GeneratedMessage;)Lcom/google/protobuf/GeneratedMessage$Builder;
      11: checkcast     #178                // class org/apache/hadoop/hbase/protobuf/generated/HBaseProtos$ServerName$Builder
      14: areturn

  public java.util.List<org.apache.hadoop.hbase.protobuf.generated.HBaseProtos$ServerName$Builder> getBackupMastersBuilderList();
    Code:
       0: aload_0
       1: invokespecial #31                 // Method getBackupMastersFieldBuilder:()Lcom/google/protobuf/RepeatedFieldBuilder;
       4: invokevirtual #174                // Method com/google/protobuf/RepeatedFieldBuilder.getBuilderList:()Ljava/util/List;
       7: areturn

  public boolean hasBalancerOn();
    Code:
       0: aload_0
       1: getfield      #36                 // Field bitField0_:I
       4: sipush        256
       7: iand
       8: sipush        256
      11: if_icmpne     18
      14: iconst_1
      15: goto          19
      18: iconst_0
      19: ireturn

  public boolean getBalancerOn();
    Code:
       0: aload_0
       1: getfield      #45                 // Field balancerOn_:Z
       4: ireturn

  public org.apache.hadoop.hbase.protobuf.generated.ClusterStatusProtos$ClusterStatus$Builder setBalancerOn(boolean);
    Code:
       0: aload_0
       1: dup
       2: getfield      #36                 // Field bitField0_:I
       5: sipush        256
       8: ior
       9: putfield      #36                 // Field bitField0_:I
      12: aload_0
      13: iload_1
      14: putfield      #45                 // Field balancerOn_:Z
      17: aload_0
      18: invokevirtual #77                 // Method onChanged:()V
      21: aload_0
      22: areturn

  public org.apache.hadoop.hbase.protobuf.generated.ClusterStatusProtos$ClusterStatus$Builder clearBalancerOn();
    Code:
       0: aload_0
       1: aload_0
       2: getfield      #36                 // Field bitField0_:I
       5: sipush        -257
       8: iand
       9: putfield      #36                 // Field bitField0_:I
      12: aload_0
      13: iconst_0
      14: putfield      #45                 // Field balancerOn_:Z
      17: aload_0
      18: invokevirtual #77                 // Method onChanged:()V
      21: aload_0
      22: areturn

  public com.google.protobuf.GeneratedMessage$Builder clear();
    Code:
       0: aload_0
       1: invokevirtual #199                // Method clear:()Lorg/apache/hadoop/hbase/protobuf/generated/ClusterStatusProtos$ClusterStatus$Builder;
       4: areturn

  public com.google.protobuf.GeneratedMessage$Builder clone();
    Code:
       0: aload_0
       1: invokevirtual #200                // Method clone:()Lorg/apache/hadoop/hbase/protobuf/generated/ClusterStatusProtos$ClusterStatus$Builder;
       4: areturn

  public com.google.protobuf.AbstractMessage$Builder mergeFrom(com.google.protobuf.CodedInputStream, com.google.protobuf.ExtensionRegistryLite) throws java.io.IOException;
    Code:
       0: aload_0
       1: aload_1
       2: aload_2
       3: invokevirtual #201                // Method mergeFrom:(Lcom/google/protobuf/CodedInputStream;Lcom/google/protobuf/ExtensionRegistryLite;)Lorg/apache/hadoop/hbase/protobuf/generated/ClusterStatusProtos$ClusterStatus$Builder;
       6: areturn

  public com.google.protobuf.AbstractMessage$Builder mergeFrom(com.google.protobuf.Message);
    Code:
       0: aload_0
       1: aload_1
       2: invokevirtual #202                // Method mergeFrom:(Lcom/google/protobuf/Message;)Lorg/apache/hadoop/hbase/protobuf/generated/ClusterStatusProtos$ClusterStatus$Builder;
       5: areturn

  public com.google.protobuf.AbstractMessage$Builder clear();
    Code:
       0: aload_0
       1: invokevirtual #199                // Method clear:()Lorg/apache/hadoop/hbase/protobuf/generated/ClusterStatusProtos$ClusterStatus$Builder;
       4: areturn

  public com.google.protobuf.AbstractMessage$Builder clone();
    Code:
       0: aload_0
       1: invokevirtual #200                // Method clone:()Lorg/apache/hadoop/hbase/protobuf/generated/ClusterStatusProtos$ClusterStatus$Builder;
       4: areturn

  public com.google.protobuf.Message$Builder mergeFrom(com.google.protobuf.CodedInputStream, com.google.protobuf.ExtensionRegistryLite) throws java.io.IOException;
    Code:
       0: aload_0
       1: aload_1
       2: aload_2
       3: invokevirtual #201                // Method mergeFrom:(Lcom/google/protobuf/CodedInputStream;Lcom/google/protobuf/ExtensionRegistryLite;)Lorg/apache/hadoop/hbase/protobuf/generated/ClusterStatusProtos$ClusterStatus$Builder;
       6: areturn

  public com.google.protobuf.Message$Builder clone();
    Code:
       0: aload_0
       1: invokevirtual #200                // Method clone:()Lorg/apache/hadoop/hbase/protobuf/generated/ClusterStatusProtos$ClusterStatus$Builder;
       4: areturn

  public com.google.protobuf.Message buildPartial();
    Code:
       0: aload_0
       1: invokevirtual #46                 // Method buildPartial:()Lorg/apache/hadoop/hbase/protobuf/generated/ClusterStatusProtos$ClusterStatus;
       4: areturn

  public com.google.protobuf.Message build();
    Code:
       0: aload_0
       1: invokevirtual #203                // Method build:()Lorg/apache/hadoop/hbase/protobuf/generated/ClusterStatusProtos$ClusterStatus;
       4: areturn

  public com.google.protobuf.Message$Builder mergeFrom(com.google.protobuf.Message);
    Code:
       0: aload_0
       1: aload_1
       2: invokevirtual #202                // Method mergeFrom:(Lcom/google/protobuf/Message;)Lorg/apache/hadoop/hbase/protobuf/generated/ClusterStatusProtos$ClusterStatus$Builder;
       5: areturn

  public com.google.protobuf.Message$Builder clear();
    Code:
       0: aload_0
       1: invokevirtual #199                // Method clear:()Lorg/apache/hadoop/hbase/protobuf/generated/ClusterStatusProtos$ClusterStatus$Builder;
       4: areturn

  public com.google.protobuf.MessageLite$Builder mergeFrom(com.google.protobuf.CodedInputStream, com.google.protobuf.ExtensionRegistryLite) throws java.io.IOException;
    Code:
       0: aload_0
       1: aload_1
       2: aload_2
       3: invokevirtual #201                // Method mergeFrom:(Lcom/google/protobuf/CodedInputStream;Lcom/google/protobuf/ExtensionRegistryLite;)Lorg/apache/hadoop/hbase/protobuf/generated/ClusterStatusProtos$ClusterStatus$Builder;
       6: areturn

  public com.google.protobuf.MessageLite$Builder clone();
    Code:
       0: aload_0
       1: invokevirtual #200                // Method clone:()Lorg/apache/hadoop/hbase/protobuf/generated/ClusterStatusProtos$ClusterStatus$Builder;
       4: areturn

  public com.google.protobuf.MessageLite buildPartial();
    Code:
       0: aload_0
       1: invokevirtual #46                 // Method buildPartial:()Lorg/apache/hadoop/hbase/protobuf/generated/ClusterStatusProtos$ClusterStatus;
       4: areturn

  public com.google.protobuf.MessageLite build();
    Code:
       0: aload_0
       1: invokevirtual #203                // Method build:()Lorg/apache/hadoop/hbase/protobuf/generated/ClusterStatusProtos$ClusterStatus;
       4: areturn

  public com.google.protobuf.MessageLite$Builder clear();
    Code:
       0: aload_0
       1: invokevirtual #199                // Method clear:()Lorg/apache/hadoop/hbase/protobuf/generated/ClusterStatusProtos$ClusterStatus$Builder;
       4: areturn

  public com.google.protobuf.MessageLite getDefaultInstanceForType();
    Code:
       0: aload_0
       1: invokevirtual #204                // Method getDefaultInstanceForType:()Lorg/apache/hadoop/hbase/protobuf/generated/ClusterStatusProtos$ClusterStatus;
       4: areturn

  public com.google.protobuf.Message getDefaultInstanceForType();
    Code:
       0: aload_0
       1: invokevirtual #204                // Method getDefaultInstanceForType:()Lorg/apache/hadoop/hbase/protobuf/generated/ClusterStatusProtos$ClusterStatus;
       4: areturn

  public com.google.protobuf.AbstractMessageLite$Builder mergeFrom(com.google.protobuf.CodedInputStream, com.google.protobuf.ExtensionRegistryLite) throws java.io.IOException;
    Code:
       0: aload_0
       1: aload_1
       2: aload_2
       3: invokevirtual #201                // Method mergeFrom:(Lcom/google/protobuf/CodedInputStream;Lcom/google/protobuf/ExtensionRegistryLite;)Lorg/apache/hadoop/hbase/protobuf/generated/ClusterStatusProtos$ClusterStatus$Builder;
       6: areturn

  public com.google.protobuf.AbstractMessageLite$Builder clone();
    Code:
       0: aload_0
       1: invokevirtual #200                // Method clone:()Lorg/apache/hadoop/hbase/protobuf/generated/ClusterStatusProtos$ClusterStatus$Builder;
       4: areturn

  public java.lang.Object clone() throws java.lang.CloneNotSupportedException;
    Code:
       0: aload_0
       1: invokevirtual #200                // Method clone:()Lorg/apache/hadoop/hbase/protobuf/generated/ClusterStatusProtos$ClusterStatus$Builder;
       4: areturn

  static org.apache.hadoop.hbase.protobuf.generated.ClusterStatusProtos$ClusterStatus$Builder access$13000();
    Code:
       0: invokestatic  #2                  // Method create:()Lorg/apache/hadoop/hbase/protobuf/generated/ClusterStatusProtos$ClusterStatus$Builder;
       3: areturn

  org.apache.hadoop.hbase.protobuf.generated.ClusterStatusProtos$ClusterStatus$Builder(com.google.protobuf.GeneratedMessage$BuilderParent, org.apache.hadoop.hbase.protobuf.generated.ClusterStatusProtos$1);
    Code:
       0: aload_0
       1: aload_1
       2: invokespecial #1                  // Method "<init>":(Lcom/google/protobuf/GeneratedMessage$BuilderParent;)V
       5: return
}
