Compiled from "ClusterCompactionQueues.java"
class org.apache.hadoop.hbase.util.compaction.ClusterCompactionQueues {
  org.apache.hadoop.hbase.util.compaction.ClusterCompactionQueues(int);
    Code:
       0: aload_0
       1: invokespecial #1                  // Method java/lang/Object."<init>":()V
       4: aload_0
       5: iload_1
       6: putfield      #2                  // Field concurrentServers:I
       9: aload_0
      10: invokestatic  #3                  // Method org/apache/hbase/thirdparty/com/google/common/collect/Maps.newHashMap:()Ljava/util/HashMap;
      13: putfield      #4                  // Field compactionQueues:Ljava/util/Map;
      16: aload_0
      17: new           #5                  // class java/util/concurrent/locks/ReentrantReadWriteLock
      20: dup
      21: invokespecial #6                  // Method java/util/concurrent/locks/ReentrantReadWriteLock."<init>":()V
      24: putfield      #7                  // Field lock:Ljava/util/concurrent/locks/ReadWriteLock;
      27: aload_0
      28: invokestatic  #8                  // Method org/apache/hbase/thirdparty/com/google/common/collect/Sets.newHashSet:()Ljava/util/HashSet;
      31: putfield      #9                  // Field compactingServers:Ljava/util/Set;
      34: return

  void addToCompactionQueue(org.apache.hadoop.hbase.ServerName, org.apache.hadoop.hbase.util.compaction.MajorCompactionRequest);
    Code:
       0: aload_0
       1: getfield      #7                  // Field lock:Ljava/util/concurrent/locks/ReadWriteLock;
       4: invokeinterface #10,  1           // InterfaceMethod java/util/concurrent/locks/ReadWriteLock.writeLock:()Ljava/util/concurrent/locks/Lock;
       9: invokeinterface #11,  1           // InterfaceMethod java/util/concurrent/locks/Lock.lock:()V
      14: aload_0
      15: getfield      #4                  // Field compactionQueues:Ljava/util/Map;
      18: aload_1
      19: invokeinterface #12,  2           // InterfaceMethod java/util/Map.get:(Ljava/lang/Object;)Ljava/lang/Object;
      24: checkcast     #13                 // class java/util/List
      27: astore_3
      28: aload_3
      29: ifnonnull     48
      32: invokestatic  #14                 // Method org/apache/hbase/thirdparty/com/google/common/collect/Lists.newArrayList:()Ljava/util/ArrayList;
      35: astore_3
      36: aload_0
      37: getfield      #4                  // Field compactionQueues:Ljava/util/Map;
      40: aload_1
      41: aload_3
      42: invokeinterface #15,  3           // InterfaceMethod java/util/Map.put:(Ljava/lang/Object;Ljava/lang/Object;)Ljava/lang/Object;
      47: pop
      48: aload_3
      49: aload_2
      50: invokeinterface #16,  2           // InterfaceMethod java/util/List.add:(Ljava/lang/Object;)Z
      55: pop
      56: aload_0
      57: getfield      #7                  // Field lock:Ljava/util/concurrent/locks/ReadWriteLock;
      60: invokeinterface #10,  1           // InterfaceMethod java/util/concurrent/locks/ReadWriteLock.writeLock:()Ljava/util/concurrent/locks/Lock;
      65: invokeinterface #17,  1           // InterfaceMethod java/util/concurrent/locks/Lock.unlock:()V
      70: goto          92
      73: astore        4
      75: aload_0
      76: getfield      #7                  // Field lock:Ljava/util/concurrent/locks/ReadWriteLock;
      79: invokeinterface #10,  1           // InterfaceMethod java/util/concurrent/locks/ReadWriteLock.writeLock:()Ljava/util/concurrent/locks/Lock;
      84: invokeinterface #17,  1           // InterfaceMethod java/util/concurrent/locks/Lock.unlock:()V
      89: aload         4
      91: athrow
      92: return
    Exception table:
       from    to  target type
          14    56    73   any
          73    75    73   any

  boolean hasWorkItems();
    Code:
       0: aload_0
       1: getfield      #7                  // Field lock:Ljava/util/concurrent/locks/ReadWriteLock;
       4: invokeinterface #18,  1           // InterfaceMethod java/util/concurrent/locks/ReadWriteLock.readLock:()Ljava/util/concurrent/locks/Lock;
       9: invokeinterface #11,  1           // InterfaceMethod java/util/concurrent/locks/Lock.lock:()V
      14: aload_0
      15: getfield      #4                  // Field compactionQueues:Ljava/util/Map;
      18: invokeinterface #19,  1           // InterfaceMethod java/util/Map.values:()Ljava/util/Collection;
      23: invokeinterface #20,  1           // InterfaceMethod java/util/Collection.stream:()Ljava/util/stream/Stream;
      28: invokedynamic #21,  0             // InvokeDynamic #0:test:()Ljava/util/function/Predicate;
      33: invokeinterface #22,  2           // InterfaceMethod java/util/stream/Stream.allMatch:(Ljava/util/function/Predicate;)Z
      38: ifne          45
      41: iconst_1
      42: goto          46
      45: iconst_0
      46: istore_1
      47: aload_0
      48: getfield      #7                  // Field lock:Ljava/util/concurrent/locks/ReadWriteLock;
      51: invokeinterface #18,  1           // InterfaceMethod java/util/concurrent/locks/ReadWriteLock.readLock:()Ljava/util/concurrent/locks/Lock;
      56: invokeinterface #17,  1           // InterfaceMethod java/util/concurrent/locks/Lock.unlock:()V
      61: iload_1
      62: ireturn
      63: astore_2
      64: aload_0
      65: getfield      #7                  // Field lock:Ljava/util/concurrent/locks/ReadWriteLock;
      68: invokeinterface #18,  1           // InterfaceMethod java/util/concurrent/locks/ReadWriteLock.readLock:()Ljava/util/concurrent/locks/Lock;
      73: invokeinterface #17,  1           // InterfaceMethod java/util/concurrent/locks/Lock.unlock:()V
      78: aload_2
      79: athrow
    Exception table:
       from    to  target type
          14    47    63   any

  int getCompactionRequestsLeftToFinish();
    Code:
       0: aload_0
       1: getfield      #7                  // Field lock:Ljava/util/concurrent/locks/ReadWriteLock;
       4: invokeinterface #18,  1           // InterfaceMethod java/util/concurrent/locks/ReadWriteLock.readLock:()Ljava/util/concurrent/locks/Lock;
       9: invokeinterface #11,  1           // InterfaceMethod java/util/concurrent/locks/Lock.lock:()V
      14: iconst_0
      15: istore_1
      16: aload_0
      17: getfield      #4                  // Field compactionQueues:Ljava/util/Map;
      20: invokeinterface #19,  1           // InterfaceMethod java/util/Map.values:()Ljava/util/Collection;
      25: invokeinterface #23,  1           // InterfaceMethod java/util/Collection.iterator:()Ljava/util/Iterator;
      30: astore_2
      31: aload_2
      32: invokeinterface #24,  1           // InterfaceMethod java/util/Iterator.hasNext:()Z
      37: ifeq          62
      40: aload_2
      41: invokeinterface #25,  1           // InterfaceMethod java/util/Iterator.next:()Ljava/lang/Object;
      46: checkcast     #13                 // class java/util/List
      49: astore_3
      50: iload_1
      51: aload_3
      52: invokeinterface #26,  1           // InterfaceMethod java/util/List.size:()I
      57: iadd
      58: istore_1
      59: goto          31
      62: iload_1
      63: istore_2
      64: aload_0
      65: getfield      #7                  // Field lock:Ljava/util/concurrent/locks/ReadWriteLock;
      68: invokeinterface #18,  1           // InterfaceMethod java/util/concurrent/locks/ReadWriteLock.readLock:()Ljava/util/concurrent/locks/Lock;
      73: invokeinterface #17,  1           // InterfaceMethod java/util/concurrent/locks/Lock.unlock:()V
      78: iload_2
      79: ireturn
      80: astore        4
      82: aload_0
      83: getfield      #7                  // Field lock:Ljava/util/concurrent/locks/ReadWriteLock;
      86: invokeinterface #18,  1           // InterfaceMethod java/util/concurrent/locks/ReadWriteLock.readLock:()Ljava/util/concurrent/locks/Lock;
      91: invokeinterface #17,  1           // InterfaceMethod java/util/concurrent/locks/Lock.unlock:()V
      96: aload         4
      98: athrow
    Exception table:
       from    to  target type
          14    64    80   any
          80    82    80   any

  java.util.List<org.apache.hadoop.hbase.util.compaction.MajorCompactionRequest> getQueue(org.apache.hadoop.hbase.ServerName);
    Code:
       0: aload_0
       1: getfield      #7                  // Field lock:Ljava/util/concurrent/locks/ReadWriteLock;
       4: invokeinterface #18,  1           // InterfaceMethod java/util/concurrent/locks/ReadWriteLock.readLock:()Ljava/util/concurrent/locks/Lock;
       9: invokeinterface #11,  1           // InterfaceMethod java/util/concurrent/locks/Lock.lock:()V
      14: aload_0
      15: getfield      #4                  // Field compactionQueues:Ljava/util/Map;
      18: aload_1
      19: invokeinterface #12,  2           // InterfaceMethod java/util/Map.get:(Ljava/lang/Object;)Ljava/lang/Object;
      24: checkcast     #13                 // class java/util/List
      27: astore_2
      28: aload_0
      29: getfield      #7                  // Field lock:Ljava/util/concurrent/locks/ReadWriteLock;
      32: invokeinterface #18,  1           // InterfaceMethod java/util/concurrent/locks/ReadWriteLock.readLock:()Ljava/util/concurrent/locks/Lock;
      37: invokeinterface #17,  1           // InterfaceMethod java/util/concurrent/locks/Lock.unlock:()V
      42: aload_2
      43: areturn
      44: astore_3
      45: aload_0
      46: getfield      #7                  // Field lock:Ljava/util/concurrent/locks/ReadWriteLock;
      49: invokeinterface #18,  1           // InterfaceMethod java/util/concurrent/locks/ReadWriteLock.readLock:()Ljava/util/concurrent/locks/Lock;
      54: invokeinterface #17,  1           // InterfaceMethod java/util/concurrent/locks/Lock.unlock:()V
      59: aload_3
      60: athrow
    Exception table:
       from    to  target type
          14    28    44   any

  org.apache.hadoop.hbase.util.compaction.MajorCompactionRequest reserveForCompaction(org.apache.hadoop.hbase.ServerName);
    Code:
       0: aload_0
       1: getfield      #7                  // Field lock:Ljava/util/concurrent/locks/ReadWriteLock;
       4: invokeinterface #10,  1           // InterfaceMethod java/util/concurrent/locks/ReadWriteLock.writeLock:()Ljava/util/concurrent/locks/Lock;
       9: invokeinterface #11,  1           // InterfaceMethod java/util/concurrent/locks/Lock.lock:()V
      14: aload_0
      15: getfield      #4                  // Field compactionQueues:Ljava/util/Map;
      18: aload_1
      19: invokeinterface #12,  2           // InterfaceMethod java/util/Map.get:(Ljava/lang/Object;)Ljava/lang/Object;
      24: checkcast     #13                 // class java/util/List
      27: invokeinterface #27,  1           // InterfaceMethod java/util/List.isEmpty:()Z
      32: ifne          85
      35: aload_0
      36: getfield      #9                  // Field compactingServers:Ljava/util/Set;
      39: aload_1
      40: invokeinterface #28,  2           // InterfaceMethod java/util/Set.add:(Ljava/lang/Object;)Z
      45: pop
      46: aload_0
      47: getfield      #4                  // Field compactionQueues:Ljava/util/Map;
      50: aload_1
      51: invokeinterface #12,  2           // InterfaceMethod java/util/Map.get:(Ljava/lang/Object;)Ljava/lang/Object;
      56: checkcast     #13                 // class java/util/List
      59: iconst_0
      60: invokeinterface #29,  2           // InterfaceMethod java/util/List.remove:(I)Ljava/lang/Object;
      65: checkcast     #30                 // class org/apache/hadoop/hbase/util/compaction/MajorCompactionRequest
      68: astore_2
      69: aload_0
      70: getfield      #7                  // Field lock:Ljava/util/concurrent/locks/ReadWriteLock;
      73: invokeinterface #10,  1           // InterfaceMethod java/util/concurrent/locks/ReadWriteLock.writeLock:()Ljava/util/concurrent/locks/Lock;
      78: invokeinterface #17,  1           // InterfaceMethod java/util/concurrent/locks/Lock.unlock:()V
      83: aload_2
      84: areturn
      85: aconst_null
      86: astore_2
      87: aload_0
      88: getfield      #7                  // Field lock:Ljava/util/concurrent/locks/ReadWriteLock;
      91: invokeinterface #10,  1           // InterfaceMethod java/util/concurrent/locks/ReadWriteLock.writeLock:()Ljava/util/concurrent/locks/Lock;
      96: invokeinterface #17,  1           // InterfaceMethod java/util/concurrent/locks/Lock.unlock:()V
     101: aload_2
     102: areturn
     103: astore_3
     104: aload_0
     105: getfield      #7                  // Field lock:Ljava/util/concurrent/locks/ReadWriteLock;
     108: invokeinterface #10,  1           // InterfaceMethod java/util/concurrent/locks/ReadWriteLock.writeLock:()Ljava/util/concurrent/locks/Lock;
     113: invokeinterface #17,  1           // InterfaceMethod java/util/concurrent/locks/Lock.unlock:()V
     118: aload_3
     119: athrow
    Exception table:
       from    to  target type
          14    69   103   any
          85    87   103   any

  void releaseCompaction(org.apache.hadoop.hbase.ServerName);
    Code:
       0: aload_0
       1: getfield      #7                  // Field lock:Ljava/util/concurrent/locks/ReadWriteLock;
       4: invokeinterface #10,  1           // InterfaceMethod java/util/concurrent/locks/ReadWriteLock.writeLock:()Ljava/util/concurrent/locks/Lock;
       9: invokeinterface #11,  1           // InterfaceMethod java/util/concurrent/locks/Lock.lock:()V
      14: aload_0
      15: getfield      #9                  // Field compactingServers:Ljava/util/Set;
      18: aload_1
      19: invokeinterface #31,  2           // InterfaceMethod java/util/Set.remove:(Ljava/lang/Object;)Z
      24: pop
      25: aload_0
      26: getfield      #7                  // Field lock:Ljava/util/concurrent/locks/ReadWriteLock;
      29: invokeinterface #10,  1           // InterfaceMethod java/util/concurrent/locks/ReadWriteLock.writeLock:()Ljava/util/concurrent/locks/Lock;
      34: invokeinterface #17,  1           // InterfaceMethod java/util/concurrent/locks/Lock.unlock:()V
      39: goto          59
      42: astore_2
      43: aload_0
      44: getfield      #7                  // Field lock:Ljava/util/concurrent/locks/ReadWriteLock;
      47: invokeinterface #10,  1           // InterfaceMethod java/util/concurrent/locks/ReadWriteLock.writeLock:()Ljava/util/concurrent/locks/Lock;
      52: invokeinterface #17,  1           // InterfaceMethod java/util/concurrent/locks/Lock.unlock:()V
      57: aload_2
      58: athrow
      59: return
    Exception table:
       from    to  target type
          14    25    42   any

  boolean atCapacity();
    Code:
       0: aload_0
       1: getfield      #7                  // Field lock:Ljava/util/concurrent/locks/ReadWriteLock;
       4: invokeinterface #18,  1           // InterfaceMethod java/util/concurrent/locks/ReadWriteLock.readLock:()Ljava/util/concurrent/locks/Lock;
       9: invokeinterface #11,  1           // InterfaceMethod java/util/concurrent/locks/Lock.lock:()V
      14: aload_0
      15: getfield      #9                  // Field compactingServers:Ljava/util/Set;
      18: invokeinterface #32,  1           // InterfaceMethod java/util/Set.size:()I
      23: aload_0
      24: getfield      #2                  // Field concurrentServers:I
      27: if_icmplt     34
      30: iconst_1
      31: goto          35
      34: iconst_0
      35: istore_1
      36: aload_0
      37: getfield      #7                  // Field lock:Ljava/util/concurrent/locks/ReadWriteLock;
      40: invokeinterface #18,  1           // InterfaceMethod java/util/concurrent/locks/ReadWriteLock.readLock:()Ljava/util/concurrent/locks/Lock;
      45: invokeinterface #17,  1           // InterfaceMethod java/util/concurrent/locks/Lock.unlock:()V
      50: iload_1
      51: ireturn
      52: astore_2
      53: aload_0
      54: getfield      #7                  // Field lock:Ljava/util/concurrent/locks/ReadWriteLock;
      57: invokeinterface #18,  1           // InterfaceMethod java/util/concurrent/locks/ReadWriteLock.readLock:()Ljava/util/concurrent/locks/Lock;
      62: invokeinterface #17,  1           // InterfaceMethod java/util/concurrent/locks/Lock.unlock:()V
      67: aload_2
      68: athrow
    Exception table:
       from    to  target type
          14    36    52   any

  java.util.Optional<org.apache.hadoop.hbase.ServerName> getLargestQueueFromServersNotCompacting();
    Code:
       0: aload_0
       1: getfield      #7                  // Field lock:Ljava/util/concurrent/locks/ReadWriteLock;
       4: invokeinterface #18,  1           // InterfaceMethod java/util/concurrent/locks/ReadWriteLock.readLock:()Ljava/util/concurrent/locks/Lock;
       9: invokeinterface #11,  1           // InterfaceMethod java/util/concurrent/locks/Lock.lock:()V
      14: aload_0
      15: getfield      #4                  // Field compactionQueues:Ljava/util/Map;
      18: invokeinterface #33,  1           // InterfaceMethod java/util/Map.entrySet:()Ljava/util/Set;
      23: invokeinterface #34,  1           // InterfaceMethod java/util/Set.stream:()Ljava/util/stream/Stream;
      28: aload_0
      29: invokedynamic #35,  0             // InvokeDynamic #1:test:(Lorg/apache/hadoop/hbase/util/compaction/ClusterCompactionQueues;)Ljava/util/function/Predicate;
      34: invokeinterface #36,  2           // InterfaceMethod java/util/stream/Stream.filter:(Ljava/util/function/Predicate;)Ljava/util/stream/Stream;
      39: invokedynamic #37,  0             // InvokeDynamic #2:compare:()Ljava/util/Comparator;
      44: invokestatic  #38                 // InterfaceMethod java/util/Map$Entry.comparingByValue:(Ljava/util/Comparator;)Ljava/util/Comparator;
      47: invokeinterface #39,  2           // InterfaceMethod java/util/stream/Stream.max:(Ljava/util/Comparator;)Ljava/util/Optional;
      52: invokedynamic #40,  0             // InvokeDynamic #3:apply:()Ljava/util/function/Function;
      57: invokevirtual #41                 // Method java/util/Optional.map:(Ljava/util/function/Function;)Ljava/util/Optional;
      60: astore_1
      61: aload_0
      62: getfield      #7                  // Field lock:Ljava/util/concurrent/locks/ReadWriteLock;
      65: invokeinterface #18,  1           // InterfaceMethod java/util/concurrent/locks/ReadWriteLock.readLock:()Ljava/util/concurrent/locks/Lock;
      70: invokeinterface #17,  1           // InterfaceMethod java/util/concurrent/locks/Lock.unlock:()V
      75: aload_1
      76: areturn
      77: astore_2
      78: aload_0
      79: getfield      #7                  // Field lock:Ljava/util/concurrent/locks/ReadWriteLock;
      82: invokeinterface #18,  1           // InterfaceMethod java/util/concurrent/locks/ReadWriteLock.readLock:()Ljava/util/concurrent/locks/Lock;
      87: invokeinterface #17,  1           // InterfaceMethod java/util/concurrent/locks/Lock.unlock:()V
      92: aload_2
      93: athrow
    Exception table:
       from    to  target type
          14    61    77   any
}
