Compiled from "ClusterMetrics.java"
public interface org.apache.hadoop.hbase.ClusterMetrics {
  public abstract java.lang.String getHBaseVersion();

  public abstract java.util.List<org.apache.hadoop.hbase.ServerName> getDeadServerNames();

  public abstract java.util.Map<org.apache.hadoop.hbase.ServerName, org.apache.hadoop.hbase.ServerMetrics> getLiveServerMetrics();

  public int getRegionCount();
    Code:
       0: aload_0
       1: invokeinterface #1,  1            // InterfaceMethod getLiveServerMetrics:()Ljava/util/Map;
       6: invokeinterface #2,  1            // InterfaceMethod java/util/Map.entrySet:()Ljava/util/Set;
      11: invokeinterface #3,  1            // InterfaceMethod java/util/Set.stream:()Ljava/util/stream/Stream;
      16: invokedynamic #4,  0              // InvokeDynamic #0:applyAsInt:()Ljava/util/function/ToIntFunction;
      21: invokeinterface #5,  2            // InterfaceMethod java/util/stream/Stream.mapToInt:(Ljava/util/function/ToIntFunction;)Ljava/util/stream/IntStream;
      26: invokeinterface #6,  1            // InterfaceMethod java/util/stream/IntStream.sum:()I
      31: ireturn

  public long getRequestCount();
    Code:
       0: aload_0
       1: invokeinterface #1,  1            // InterfaceMethod getLiveServerMetrics:()Ljava/util/Map;
       6: invokeinterface #2,  1            // InterfaceMethod java/util/Map.entrySet:()Ljava/util/Set;
      11: invokeinterface #3,  1            // InterfaceMethod java/util/Set.stream:()Ljava/util/stream/Stream;
      16: invokedynamic #7,  0              // InvokeDynamic #1:apply:()Ljava/util/function/Function;
      21: invokeinterface #8,  2            // InterfaceMethod java/util/stream/Stream.flatMap:(Ljava/util/function/Function;)Ljava/util/stream/Stream;
      26: invokedynamic #9,  0              // InvokeDynamic #2:applyAsLong:()Ljava/util/function/ToLongFunction;
      31: invokeinterface #10,  2           // InterfaceMethod java/util/stream/Stream.mapToLong:(Ljava/util/function/ToLongFunction;)Ljava/util/stream/LongStream;
      36: invokeinterface #11,  1           // InterfaceMethod java/util/stream/LongStream.sum:()J
      41: lreturn

  public abstract org.apache.hadoop.hbase.ServerName getMasterName();

  public abstract java.util.List<org.apache.hadoop.hbase.ServerName> getBackupMasterNames();

  public abstract java.util.List<org.apache.hadoop.hbase.master.RegionState> getRegionStatesInTransition();

  public abstract java.lang.String getClusterId();

  public abstract java.util.List<java.lang.String> getMasterCoprocessorNames();

  public long getLastMajorCompactionTimestamp(org.apache.hadoop.hbase.TableName);
    Code:
       0: aload_0
       1: invokeinterface #1,  1            // InterfaceMethod getLiveServerMetrics:()Ljava/util/Map;
       6: invokeinterface #12,  1           // InterfaceMethod java/util/Map.values:()Ljava/util/Collection;
      11: invokeinterface #13,  1           // InterfaceMethod java/util/Collection.stream:()Ljava/util/stream/Stream;
      16: invokedynamic #14,  0             // InvokeDynamic #3:apply:()Ljava/util/function/Function;
      21: invokeinterface #8,  2            // InterfaceMethod java/util/stream/Stream.flatMap:(Ljava/util/function/Function;)Ljava/util/stream/Stream;
      26: aload_1
      27: invokedynamic #15,  0             // InvokeDynamic #4:test:(Lorg/apache/hadoop/hbase/TableName;)Ljava/util/function/Predicate;
      32: invokeinterface #16,  2           // InterfaceMethod java/util/stream/Stream.filter:(Ljava/util/function/Predicate;)Ljava/util/stream/Stream;
      37: invokedynamic #17,  0             // InvokeDynamic #5:applyAsLong:()Ljava/util/function/ToLongFunction;
      42: invokeinterface #10,  2           // InterfaceMethod java/util/stream/Stream.mapToLong:(Ljava/util/function/ToLongFunction;)Ljava/util/stream/LongStream;
      47: invokeinterface #18,  1           // InterfaceMethod java/util/stream/LongStream.min:()Ljava/util/OptionalLong;
      52: lconst_0
      53: invokevirtual #19                 // Method java/util/OptionalLong.orElse:(J)J
      56: lreturn

  public long getLastMajorCompactionTimestamp(byte[]);
    Code:
       0: aload_0
       1: invokeinterface #1,  1            // InterfaceMethod getLiveServerMetrics:()Ljava/util/Map;
       6: invokeinterface #12,  1           // InterfaceMethod java/util/Map.values:()Ljava/util/Collection;
      11: invokeinterface #13,  1           // InterfaceMethod java/util/Collection.stream:()Ljava/util/stream/Stream;
      16: aload_1
      17: invokedynamic #20,  0             // InvokeDynamic #6:test:([B)Ljava/util/function/Predicate;
      22: invokeinterface #16,  2           // InterfaceMethod java/util/stream/Stream.filter:(Ljava/util/function/Predicate;)Ljava/util/stream/Stream;
      27: invokeinterface #21,  1           // InterfaceMethod java/util/stream/Stream.findAny:()Ljava/util/Optional;
      32: aload_1
      33: invokedynamic #22,  0             // InvokeDynamic #7:apply:([B)Ljava/util/function/Function;
      38: invokevirtual #23                 // Method java/util/Optional.map:(Ljava/util/function/Function;)Ljava/util/Optional;
      41: lconst_0
      42: invokestatic  #24                 // Method java/lang/Long.valueOf:(J)Ljava/lang/Long;
      45: invokevirtual #25                 // Method java/util/Optional.orElse:(Ljava/lang/Object;)Ljava/lang/Object;
      48: checkcast     #26                 // class java/lang/Long
      51: invokevirtual #27                 // Method java/lang/Long.longValue:()J
      54: lreturn

  public abstract java.lang.Boolean getBalancerOn();

  public abstract int getMasterInfoPort();

  public abstract java.util.List<org.apache.hadoop.hbase.ServerName> getServersName();

  public double getAverageLoad();
    Code:
       0: aload_0
       1: invokeinterface #1,  1            // InterfaceMethod getLiveServerMetrics:()Ljava/util/Map;
       6: invokeinterface #28,  1           // InterfaceMethod java/util/Map.size:()I
      11: istore_1
      12: iload_1
      13: ifne          18
      16: dconst_0
      17: dreturn
      18: aload_0
      19: invokeinterface #29,  1           // InterfaceMethod getRegionCount:()I
      24: i2d
      25: iload_1
      26: i2d
      27: ddiv
      28: dreturn
}
