Compiled from "ClusterStatusProtos.java"
public final class org.apache.hadoop.hbase.protobuf.generated.ClusterStatusProtos$ServerLoad extends com.google.protobuf.GeneratedMessage implements org.apache.hadoop.hbase.protobuf.generated.ClusterStatusProtos$ServerLoadOrBuilder {
  public static com.google.protobuf.Parser<org.apache.hadoop.hbase.protobuf.generated.ClusterStatusProtos$ServerLoad> PARSER;

  public static final int NUMBER_OF_REQUESTS_FIELD_NUMBER;

  public static final int TOTAL_NUMBER_OF_REQUESTS_FIELD_NUMBER;

  public static final int USED_HEAP_MB_FIELD_NUMBER;

  public static final int MAX_HEAP_MB_FIELD_NUMBER;

  public static final int REGION_LOADS_FIELD_NUMBER;

  public static final int COPROCESSORS_FIELD_NUMBER;

  public static final int REPORT_START_TIME_FIELD_NUMBER;

  public static final int REPORT_END_TIME_FIELD_NUMBER;

  public static final int INFO_SERVER_PORT_FIELD_NUMBER;

  public static final int REPLLOADSOURCE_FIELD_NUMBER;

  public static final int REPLLOADSINK_FIELD_NUMBER;

  public static org.apache.hadoop.hbase.protobuf.generated.ClusterStatusProtos$ServerLoad getDefaultInstance();
    Code:
       0: getstatic     #24                 // Field defaultInstance:Lorg/apache/hadoop/hbase/protobuf/generated/ClusterStatusProtos$ServerLoad;
       3: areturn

  public org.apache.hadoop.hbase.protobuf.generated.ClusterStatusProtos$ServerLoad getDefaultInstanceForType();
    Code:
       0: getstatic     #24                 // Field defaultInstance:Lorg/apache/hadoop/hbase/protobuf/generated/ClusterStatusProtos$ServerLoad;
       3: areturn

  public final com.google.protobuf.UnknownFieldSet getUnknownFields();
    Code:
       0: aload_0
       1: getfield      #21                 // Field unknownFields:Lcom/google/protobuf/UnknownFieldSet;
       4: areturn

  public static final com.google.protobuf.Descriptors$Descriptor getDescriptor();
    Code:
       0: invokestatic  #51                 // Method org/apache/hadoop/hbase/protobuf/generated/ClusterStatusProtos.access$9500:()Lcom/google/protobuf/Descriptors$Descriptor;
       3: areturn

  protected com.google.protobuf.GeneratedMessage$FieldAccessorTable internalGetFieldAccessorTable();
    Code:
       0: invokestatic  #52                 // Method org/apache/hadoop/hbase/protobuf/generated/ClusterStatusProtos.access$9600:()Lcom/google/protobuf/GeneratedMessage$FieldAccessorTable;
       3: ldc           #53                 // class org/apache/hadoop/hbase/protobuf/generated/ClusterStatusProtos$ServerLoad
       5: ldc           #54                 // class org/apache/hadoop/hbase/protobuf/generated/ClusterStatusProtos$ServerLoad$Builder
       7: invokevirtual #55                 // Method com/google/protobuf/GeneratedMessage$FieldAccessorTable.ensureFieldAccessorsInitialized:(Ljava/lang/Class;Ljava/lang/Class;)Lcom/google/protobuf/GeneratedMessage$FieldAccessorTable;
      10: areturn

  public com.google.protobuf.Parser<org.apache.hadoop.hbase.protobuf.generated.ClusterStatusProtos$ServerLoad> getParserForType();
    Code:
       0: getstatic     #56                 // Field PARSER:Lcom/google/protobuf/Parser;
       3: areturn

  public boolean hasNumberOfRequests();
    Code:
       0: aload_0
       1: getfield      #2                  // Field bitField0_:I
       4: iconst_1
       5: iand
       6: iconst_1
       7: if_icmpne     14
      10: iconst_1
      11: goto          15
      14: iconst_0
      15: ireturn

  public long getNumberOfRequests();
    Code:
       0: aload_0
       1: getfield      #13                 // Field numberOfRequests_:J
       4: lreturn

  public boolean hasTotalNumberOfRequests();
    Code:
       0: aload_0
       1: getfield      #2                  // Field bitField0_:I
       4: iconst_2
       5: iand
       6: iconst_2
       7: if_icmpne     14
      10: iconst_1
      11: goto          15
      14: iconst_0
      15: ireturn

  public long getTotalNumberOfRequests();
    Code:
       0: aload_0
       1: getfield      #12                 // Field totalNumberOfRequests_:J
       4: lreturn

  public boolean hasUsedHeapMB();
    Code:
       0: aload_0
       1: getfield      #2                  // Field bitField0_:I
       4: iconst_4
       5: iand
       6: iconst_4
       7: if_icmpne     14
      10: iconst_1
      11: goto          15
      14: iconst_0
      15: ireturn

  public int getUsedHeapMB();
    Code:
       0: aload_0
       1: getfield      #11                 // Field usedHeapMB_:I
       4: ireturn

  public boolean hasMaxHeapMB();
    Code:
       0: aload_0
       1: getfield      #2                  // Field bitField0_:I
       4: bipush        8
       6: iand
       7: bipush        8
       9: if_icmpne     16
      12: iconst_1
      13: goto          17
      16: iconst_0
      17: ireturn

  public int getMaxHeapMB();
    Code:
       0: aload_0
       1: getfield      #10                 // Field maxHeapMB_:I
       4: ireturn

  public java.util.List<org.apache.hadoop.hbase.protobuf.generated.ClusterStatusProtos$RegionLoad> getRegionLoadsList();
    Code:
       0: aload_0
       1: getfield      #9                  // Field regionLoads_:Ljava/util/List;
       4: areturn

  public java.util.List<? extends org.apache.hadoop.hbase.protobuf.generated.ClusterStatusProtos$RegionLoadOrBuilder> getRegionLoadsOrBuilderList();
    Code:
       0: aload_0
       1: getfield      #9                  // Field regionLoads_:Ljava/util/List;
       4: areturn

  public int getRegionLoadsCount();
    Code:
       0: aload_0
       1: getfield      #9                  // Field regionLoads_:Ljava/util/List;
       4: invokeinterface #57,  1           // InterfaceMethod java/util/List.size:()I
       9: ireturn

  public org.apache.hadoop.hbase.protobuf.generated.ClusterStatusProtos$RegionLoad getRegionLoads(int);
    Code:
       0: aload_0
       1: getfield      #9                  // Field regionLoads_:Ljava/util/List;
       4: iload_1
       5: invokeinterface #58,  2           // InterfaceMethod java/util/List.get:(I)Ljava/lang/Object;
      10: checkcast     #59                 // class org/apache/hadoop/hbase/protobuf/generated/ClusterStatusProtos$RegionLoad
      13: areturn

  public org.apache.hadoop.hbase.protobuf.generated.ClusterStatusProtos$RegionLoadOrBuilder getRegionLoadsOrBuilder(int);
    Code:
       0: aload_0
       1: getfield      #9                  // Field regionLoads_:Ljava/util/List;
       4: iload_1
       5: invokeinterface #58,  2           // InterfaceMethod java/util/List.get:(I)Ljava/lang/Object;
      10: checkcast     #60                 // class org/apache/hadoop/hbase/protobuf/generated/ClusterStatusProtos$RegionLoadOrBuilder
      13: areturn

  public java.util.List<org.apache.hadoop.hbase.protobuf.generated.HBaseProtos$Coprocessor> getCoprocessorsList();
    Code:
       0: aload_0
       1: getfield      #8                  // Field coprocessors_:Ljava/util/List;
       4: areturn

  public java.util.List<? extends org.apache.hadoop.hbase.protobuf.generated.HBaseProtos$CoprocessorOrBuilder> getCoprocessorsOrBuilderList();
    Code:
       0: aload_0
       1: getfield      #8                  // Field coprocessors_:Ljava/util/List;
       4: areturn

  public int getCoprocessorsCount();
    Code:
       0: aload_0
       1: getfield      #8                  // Field coprocessors_:Ljava/util/List;
       4: invokeinterface #57,  1           // InterfaceMethod java/util/List.size:()I
       9: ireturn

  public org.apache.hadoop.hbase.protobuf.generated.HBaseProtos$Coprocessor getCoprocessors(int);
    Code:
       0: aload_0
       1: getfield      #8                  // Field coprocessors_:Ljava/util/List;
       4: iload_1
       5: invokeinterface #58,  2           // InterfaceMethod java/util/List.get:(I)Ljava/lang/Object;
      10: checkcast     #61                 // class org/apache/hadoop/hbase/protobuf/generated/HBaseProtos$Coprocessor
      13: areturn

  public org.apache.hadoop.hbase.protobuf.generated.HBaseProtos$CoprocessorOrBuilder getCoprocessorsOrBuilder(int);
    Code:
       0: aload_0
       1: getfield      #8                  // Field coprocessors_:Ljava/util/List;
       4: iload_1
       5: invokeinterface #58,  2           // InterfaceMethod java/util/List.get:(I)Ljava/lang/Object;
      10: checkcast     #62                 // class org/apache/hadoop/hbase/protobuf/generated/HBaseProtos$CoprocessorOrBuilder
      13: areturn

  public boolean hasReportStartTime();
    Code:
       0: aload_0
       1: getfield      #2                  // Field bitField0_:I
       4: bipush        16
       6: iand
       7: bipush        16
       9: if_icmpne     16
      12: iconst_1
      13: goto          17
      16: iconst_0
      17: ireturn

  public long getReportStartTime();
    Code:
       0: aload_0
       1: getfield      #7                  // Field reportStartTime_:J
       4: lreturn

  public boolean hasReportEndTime();
    Code:
       0: aload_0
       1: getfield      #2                  // Field bitField0_:I
       4: bipush        32
       6: iand
       7: bipush        32
       9: if_icmpne     16
      12: iconst_1
      13: goto          17
      16: iconst_0
      17: ireturn

  public long getReportEndTime();
    Code:
       0: aload_0
       1: getfield      #6                  // Field reportEndTime_:J
       4: lreturn

  public boolean hasInfoServerPort();
    Code:
       0: aload_0
       1: getfield      #2                  // Field bitField0_:I
       4: bipush        64
       6: iand
       7: bipush        64
       9: if_icmpne     16
      12: iconst_1
      13: goto          17
      16: iconst_0
      17: ireturn

  public int getInfoServerPort();
    Code:
       0: aload_0
       1: getfield      #5                  // Field infoServerPort_:I
       4: ireturn

  public java.util.List<org.apache.hadoop.hbase.protobuf.generated.ClusterStatusProtos$ReplicationLoadSource> getReplLoadSourceList();
    Code:
       0: aload_0
       1: getfield      #4                  // Field replLoadSource_:Ljava/util/List;
       4: areturn

  public java.util.List<? extends org.apache.hadoop.hbase.protobuf.generated.ClusterStatusProtos$ReplicationLoadSourceOrBuilder> getReplLoadSourceOrBuilderList();
    Code:
       0: aload_0
       1: getfield      #4                  // Field replLoadSource_:Ljava/util/List;
       4: areturn

  public int getReplLoadSourceCount();
    Code:
       0: aload_0
       1: getfield      #4                  // Field replLoadSource_:Ljava/util/List;
       4: invokeinterface #57,  1           // InterfaceMethod java/util/List.size:()I
       9: ireturn

  public org.apache.hadoop.hbase.protobuf.generated.ClusterStatusProtos$ReplicationLoadSource getReplLoadSource(int);
    Code:
       0: aload_0
       1: getfield      #4                  // Field replLoadSource_:Ljava/util/List;
       4: iload_1
       5: invokeinterface #58,  2           // InterfaceMethod java/util/List.get:(I)Ljava/lang/Object;
      10: checkcast     #63                 // class org/apache/hadoop/hbase/protobuf/generated/ClusterStatusProtos$ReplicationLoadSource
      13: areturn

  public org.apache.hadoop.hbase.protobuf.generated.ClusterStatusProtos$ReplicationLoadSourceOrBuilder getReplLoadSourceOrBuilder(int);
    Code:
       0: aload_0
       1: getfield      #4                  // Field replLoadSource_:Ljava/util/List;
       4: iload_1
       5: invokeinterface #58,  2           // InterfaceMethod java/util/List.get:(I)Ljava/lang/Object;
      10: checkcast     #64                 // class org/apache/hadoop/hbase/protobuf/generated/ClusterStatusProtos$ReplicationLoadSourceOrBuilder
      13: areturn

  public boolean hasReplLoadSink();
    Code:
       0: aload_0
       1: getfield      #2                  // Field bitField0_:I
       4: sipush        128
       7: iand
       8: sipush        128
      11: if_icmpne     18
      14: iconst_1
      15: goto          19
      18: iconst_0
      19: ireturn

  public org.apache.hadoop.hbase.protobuf.generated.ClusterStatusProtos$ReplicationLoadSink getReplLoadSink();
    Code:
       0: aload_0
       1: getfield      #3                  // Field replLoadSink_:Lorg/apache/hadoop/hbase/protobuf/generated/ClusterStatusProtos$ReplicationLoadSink;
       4: areturn

  public org.apache.hadoop.hbase.protobuf.generated.ClusterStatusProtos$ReplicationLoadSinkOrBuilder getReplLoadSinkOrBuilder();
    Code:
       0: aload_0
       1: getfield      #3                  // Field replLoadSink_:Lorg/apache/hadoop/hbase/protobuf/generated/ClusterStatusProtos$ReplicationLoadSink;
       4: areturn

  public final boolean isInitialized();
    Code:
       0: aload_0
       1: getfield      #17                 // Field memoizedIsInitialized:B
       4: istore_1
       5: iload_1
       6: iconst_m1
       7: if_icmpeq     21
      10: iload_1
      11: iconst_1
      12: if_icmpne     19
      15: iconst_1
      16: goto          20
      19: iconst_0
      20: ireturn
      21: iconst_0
      22: istore_2
      23: iload_2
      24: aload_0
      25: invokevirtual #67                 // Method getRegionLoadsCount:()I
      28: if_icmpge     55
      31: aload_0
      32: iload_2
      33: invokevirtual #68                 // Method getRegionLoads:(I)Lorg/apache/hadoop/hbase/protobuf/generated/ClusterStatusProtos$RegionLoad;
      36: invokevirtual #69                 // Method org/apache/hadoop/hbase/protobuf/generated/ClusterStatusProtos$RegionLoad.isInitialized:()Z
      39: ifne          49
      42: aload_0
      43: iconst_0
      44: putfield      #17                 // Field memoizedIsInitialized:B
      47: iconst_0
      48: ireturn
      49: iinc          2, 1
      52: goto          23
      55: iconst_0
      56: istore_2
      57: iload_2
      58: aload_0
      59: invokevirtual #70                 // Method getCoprocessorsCount:()I
      62: if_icmpge     89
      65: aload_0
      66: iload_2
      67: invokevirtual #71                 // Method getCoprocessors:(I)Lorg/apache/hadoop/hbase/protobuf/generated/HBaseProtos$Coprocessor;
      70: invokevirtual #72                 // Method org/apache/hadoop/hbase/protobuf/generated/HBaseProtos$Coprocessor.isInitialized:()Z
      73: ifne          83
      76: aload_0
      77: iconst_0
      78: putfield      #17                 // Field memoizedIsInitialized:B
      81: iconst_0
      82: ireturn
      83: iinc          2, 1
      86: goto          57
      89: iconst_0
      90: istore_2
      91: iload_2
      92: aload_0
      93: invokevirtual #73                 // Method getReplLoadSourceCount:()I
      96: if_icmpge     123
      99: aload_0
     100: iload_2
     101: invokevirtual #74                 // Method getReplLoadSource:(I)Lorg/apache/hadoop/hbase/protobuf/generated/ClusterStatusProtos$ReplicationLoadSource;
     104: invokevirtual #75                 // Method org/apache/hadoop/hbase/protobuf/generated/ClusterStatusProtos$ReplicationLoadSource.isInitialized:()Z
     107: ifne          117
     110: aload_0
     111: iconst_0
     112: putfield      #17                 // Field memoizedIsInitialized:B
     115: iconst_0
     116: ireturn
     117: iinc          2, 1
     120: goto          91
     123: aload_0
     124: invokevirtual #76                 // Method hasReplLoadSink:()Z
     127: ifeq          147
     130: aload_0
     131: invokevirtual #77                 // Method getReplLoadSink:()Lorg/apache/hadoop/hbase/protobuf/generated/ClusterStatusProtos$ReplicationLoadSink;
     134: invokevirtual #78                 // Method org/apache/hadoop/hbase/protobuf/generated/ClusterStatusProtos$ReplicationLoadSink.isInitialized:()Z
     137: ifne          147
     140: aload_0
     141: iconst_0
     142: putfield      #17                 // Field memoizedIsInitialized:B
     145: iconst_0
     146: ireturn
     147: aload_0
     148: iconst_1
     149: putfield      #17                 // Field memoizedIsInitialized:B
     152: iconst_1
     153: ireturn

  public void writeTo(com.google.protobuf.CodedOutputStream) throws java.io.IOException;
    Code:
       0: aload_0
       1: invokevirtual #79                 // Method getSerializedSize:()I
       4: pop
       5: aload_0
       6: getfield      #2                  // Field bitField0_:I
       9: iconst_1
      10: iand
      11: iconst_1
      12: if_icmpne     24
      15: aload_1
      16: iconst_1
      17: aload_0
      18: getfield      #13                 // Field numberOfRequests_:J
      21: invokevirtual #80                 // Method com/google/protobuf/CodedOutputStream.writeUInt64:(IJ)V
      24: aload_0
      25: getfield      #2                  // Field bitField0_:I
      28: iconst_2
      29: iand
      30: iconst_2
      31: if_icmpne     43
      34: aload_1
      35: iconst_2
      36: aload_0
      37: getfield      #12                 // Field totalNumberOfRequests_:J
      40: invokevirtual #80                 // Method com/google/protobuf/CodedOutputStream.writeUInt64:(IJ)V
      43: aload_0
      44: getfield      #2                  // Field bitField0_:I
      47: iconst_4
      48: iand
      49: iconst_4
      50: if_icmpne     62
      53: aload_1
      54: iconst_3
      55: aload_0
      56: getfield      #11                 // Field usedHeapMB_:I
      59: invokevirtual #81                 // Method com/google/protobuf/CodedOutputStream.writeUInt32:(II)V
      62: aload_0
      63: getfield      #2                  // Field bitField0_:I
      66: bipush        8
      68: iand
      69: bipush        8
      71: if_icmpne     83
      74: aload_1
      75: iconst_4
      76: aload_0
      77: getfield      #10                 // Field maxHeapMB_:I
      80: invokevirtual #81                 // Method com/google/protobuf/CodedOutputStream.writeUInt32:(II)V
      83: iconst_0
      84: istore_2
      85: iload_2
      86: aload_0
      87: getfield      #9                  // Field regionLoads_:Ljava/util/List;
      90: invokeinterface #57,  1           // InterfaceMethod java/util/List.size:()I
      95: if_icmpge     122
      98: aload_1
      99: iconst_5
     100: aload_0
     101: getfield      #9                  // Field regionLoads_:Ljava/util/List;
     104: iload_2
     105: invokeinterface #58,  2           // InterfaceMethod java/util/List.get:(I)Ljava/lang/Object;
     110: checkcast     #82                 // class com/google/protobuf/MessageLite
     113: invokevirtual #83                 // Method com/google/protobuf/CodedOutputStream.writeMessage:(ILcom/google/protobuf/MessageLite;)V
     116: iinc          2, 1
     119: goto          85
     122: iconst_0
     123: istore_2
     124: iload_2
     125: aload_0
     126: getfield      #8                  // Field coprocessors_:Ljava/util/List;
     129: invokeinterface #57,  1           // InterfaceMethod java/util/List.size:()I
     134: if_icmpge     162
     137: aload_1
     138: bipush        6
     140: aload_0
     141: getfield      #8                  // Field coprocessors_:Ljava/util/List;
     144: iload_2
     145: invokeinterface #58,  2           // InterfaceMethod java/util/List.get:(I)Ljava/lang/Object;
     150: checkcast     #82                 // class com/google/protobuf/MessageLite
     153: invokevirtual #83                 // Method com/google/protobuf/CodedOutputStream.writeMessage:(ILcom/google/protobuf/MessageLite;)V
     156: iinc          2, 1
     159: goto          124
     162: aload_0
     163: getfield      #2                  // Field bitField0_:I
     166: bipush        16
     168: iand
     169: bipush        16
     171: if_icmpne     184
     174: aload_1
     175: bipush        7
     177: aload_0
     178: getfield      #7                  // Field reportStartTime_:J
     181: invokevirtual #80                 // Method com/google/protobuf/CodedOutputStream.writeUInt64:(IJ)V
     184: aload_0
     185: getfield      #2                  // Field bitField0_:I
     188: bipush        32
     190: iand
     191: bipush        32
     193: if_icmpne     206
     196: aload_1
     197: bipush        8
     199: aload_0
     200: getfield      #6                  // Field reportEndTime_:J
     203: invokevirtual #80                 // Method com/google/protobuf/CodedOutputStream.writeUInt64:(IJ)V
     206: aload_0
     207: getfield      #2                  // Field bitField0_:I
     210: bipush        64
     212: iand
     213: bipush        64
     215: if_icmpne     228
     218: aload_1
     219: bipush        9
     221: aload_0
     222: getfield      #5                  // Field infoServerPort_:I
     225: invokevirtual #81                 // Method com/google/protobuf/CodedOutputStream.writeUInt32:(II)V
     228: iconst_0
     229: istore_2
     230: iload_2
     231: aload_0
     232: getfield      #4                  // Field replLoadSource_:Ljava/util/List;
     235: invokeinterface #57,  1           // InterfaceMethod java/util/List.size:()I
     240: if_icmpge     268
     243: aload_1
     244: bipush        10
     246: aload_0
     247: getfield      #4                  // Field replLoadSource_:Ljava/util/List;
     250: iload_2
     251: invokeinterface #58,  2           // InterfaceMethod java/util/List.get:(I)Ljava/lang/Object;
     256: checkcast     #82                 // class com/google/protobuf/MessageLite
     259: invokevirtual #83                 // Method com/google/protobuf/CodedOutputStream.writeMessage:(ILcom/google/protobuf/MessageLite;)V
     262: iinc          2, 1
     265: goto          230
     268: aload_0
     269: getfield      #2                  // Field bitField0_:I
     272: sipush        128
     275: iand
     276: sipush        128
     279: if_icmpne     292
     282: aload_1
     283: bipush        11
     285: aload_0
     286: getfield      #3                  // Field replLoadSink_:Lorg/apache/hadoop/hbase/protobuf/generated/ClusterStatusProtos$ReplicationLoadSink;
     289: invokevirtual #83                 // Method com/google/protobuf/CodedOutputStream.writeMessage:(ILcom/google/protobuf/MessageLite;)V
     292: aload_0
     293: invokevirtual #84                 // Method getUnknownFields:()Lcom/google/protobuf/UnknownFieldSet;
     296: aload_1
     297: invokevirtual #85                 // Method com/google/protobuf/UnknownFieldSet.writeTo:(Lcom/google/protobuf/CodedOutputStream;)V
     300: return

  public int getSerializedSize();
    Code:
       0: aload_0
       1: getfield      #18                 // Field memoizedSerializedSize:I
       4: istore_1
       5: iload_1
       6: iconst_m1
       7: if_icmpeq     12
      10: iload_1
      11: ireturn
      12: iconst_0
      13: istore_1
      14: aload_0
      15: getfield      #2                  // Field bitField0_:I
      18: iconst_1
      19: iand
      20: iconst_1
      21: if_icmpne     35
      24: iload_1
      25: iconst_1
      26: aload_0
      27: getfield      #13                 // Field numberOfRequests_:J
      30: invokestatic  #86                 // Method com/google/protobuf/CodedOutputStream.computeUInt64Size:(IJ)I
      33: iadd
      34: istore_1
      35: aload_0
      36: getfield      #2                  // Field bitField0_:I
      39: iconst_2
      40: iand
      41: iconst_2
      42: if_icmpne     56
      45: iload_1
      46: iconst_2
      47: aload_0
      48: getfield      #12                 // Field totalNumberOfRequests_:J
      51: invokestatic  #86                 // Method com/google/protobuf/CodedOutputStream.computeUInt64Size:(IJ)I
      54: iadd
      55: istore_1
      56: aload_0
      57: getfield      #2                  // Field bitField0_:I
      60: iconst_4
      61: iand
      62: iconst_4
      63: if_icmpne     77
      66: iload_1
      67: iconst_3
      68: aload_0
      69: getfield      #11                 // Field usedHeapMB_:I
      72: invokestatic  #87                 // Method com/google/protobuf/CodedOutputStream.computeUInt32Size:(II)I
      75: iadd
      76: istore_1
      77: aload_0
      78: getfield      #2                  // Field bitField0_:I
      81: bipush        8
      83: iand
      84: bipush        8
      86: if_icmpne     100
      89: iload_1
      90: iconst_4
      91: aload_0
      92: getfield      #10                 // Field maxHeapMB_:I
      95: invokestatic  #87                 // Method com/google/protobuf/CodedOutputStream.computeUInt32Size:(II)I
      98: iadd
      99: istore_1
     100: iconst_0
     101: istore_2
     102: iload_2
     103: aload_0
     104: getfield      #9                  // Field regionLoads_:Ljava/util/List;
     107: invokeinterface #57,  1           // InterfaceMethod java/util/List.size:()I
     112: if_icmpge     141
     115: iload_1
     116: iconst_5
     117: aload_0
     118: getfield      #9                  // Field regionLoads_:Ljava/util/List;
     121: iload_2
     122: invokeinterface #58,  2           // InterfaceMethod java/util/List.get:(I)Ljava/lang/Object;
     127: checkcast     #82                 // class com/google/protobuf/MessageLite
     130: invokestatic  #88                 // Method com/google/protobuf/CodedOutputStream.computeMessageSize:(ILcom/google/protobuf/MessageLite;)I
     133: iadd
     134: istore_1
     135: iinc          2, 1
     138: goto          102
     141: iconst_0
     142: istore_2
     143: iload_2
     144: aload_0
     145: getfield      #8                  // Field coprocessors_:Ljava/util/List;
     148: invokeinterface #57,  1           // InterfaceMethod java/util/List.size:()I
     153: if_icmpge     183
     156: iload_1
     157: bipush        6
     159: aload_0
     160: getfield      #8                  // Field coprocessors_:Ljava/util/List;
     163: iload_2
     164: invokeinterface #58,  2           // InterfaceMethod java/util/List.get:(I)Ljava/lang/Object;
     169: checkcast     #82                 // class com/google/protobuf/MessageLite
     172: invokestatic  #88                 // Method com/google/protobuf/CodedOutputStream.computeMessageSize:(ILcom/google/protobuf/MessageLite;)I
     175: iadd
     176: istore_1
     177: iinc          2, 1
     180: goto          143
     183: aload_0
     184: getfield      #2                  // Field bitField0_:I
     187: bipush        16
     189: iand
     190: bipush        16
     192: if_icmpne     207
     195: iload_1
     196: bipush        7
     198: aload_0
     199: getfield      #7                  // Field reportStartTime_:J
     202: invokestatic  #86                 // Method com/google/protobuf/CodedOutputStream.computeUInt64Size:(IJ)I
     205: iadd
     206: istore_1
     207: aload_0
     208: getfield      #2                  // Field bitField0_:I
     211: bipush        32
     213: iand
     214: bipush        32
     216: if_icmpne     231
     219: iload_1
     220: bipush        8
     222: aload_0
     223: getfield      #6                  // Field reportEndTime_:J
     226: invokestatic  #86                 // Method com/google/protobuf/CodedOutputStream.computeUInt64Size:(IJ)I
     229: iadd
     230: istore_1
     231: aload_0
     232: getfield      #2                  // Field bitField0_:I
     235: bipush        64
     237: iand
     238: bipush        64
     240: if_icmpne     255
     243: iload_1
     244: bipush        9
     246: aload_0
     247: getfield      #5                  // Field infoServerPort_:I
     250: invokestatic  #87                 // Method com/google/protobuf/CodedOutputStream.computeUInt32Size:(II)I
     253: iadd
     254: istore_1
     255: iconst_0
     256: istore_2
     257: iload_2
     258: aload_0
     259: getfield      #4                  // Field replLoadSource_:Ljava/util/List;
     262: invokeinterface #57,  1           // InterfaceMethod java/util/List.size:()I
     267: if_icmpge     297
     270: iload_1
     271: bipush        10
     273: aload_0
     274: getfield      #4                  // Field replLoadSource_:Ljava/util/List;
     277: iload_2
     278: invokeinterface #58,  2           // InterfaceMethod java/util/List.get:(I)Ljava/lang/Object;
     283: checkcast     #82                 // class com/google/protobuf/MessageLite
     286: invokestatic  #88                 // Method com/google/protobuf/CodedOutputStream.computeMessageSize:(ILcom/google/protobuf/MessageLite;)I
     289: iadd
     290: istore_1
     291: iinc          2, 1
     294: goto          257
     297: aload_0
     298: getfield      #2                  // Field bitField0_:I
     301: sipush        128
     304: iand
     305: sipush        128
     308: if_icmpne     323
     311: iload_1
     312: bipush        11
     314: aload_0
     315: getfield      #3                  // Field replLoadSink_:Lorg/apache/hadoop/hbase/protobuf/generated/ClusterStatusProtos$ReplicationLoadSink;
     318: invokestatic  #88                 // Method com/google/protobuf/CodedOutputStream.computeMessageSize:(ILcom/google/protobuf/MessageLite;)I
     321: iadd
     322: istore_1
     323: iload_1
     324: aload_0
     325: invokevirtual #84                 // Method getUnknownFields:()Lcom/google/protobuf/UnknownFieldSet;
     328: invokevirtual #89                 // Method com/google/protobuf/UnknownFieldSet.getSerializedSize:()I
     331: iadd
     332: istore_1
     333: aload_0
     334: iload_1
     335: putfield      #18                 // Field memoizedSerializedSize:I
     338: iload_1
     339: ireturn

  protected java.lang.Object writeReplace() throws java.io.ObjectStreamException;
    Code:
       0: aload_0
       1: invokespecial #90                 // Method com/google/protobuf/GeneratedMessage.writeReplace:()Ljava/lang/Object;
       4: areturn

  public boolean equals(java.lang.Object);
    Code:
       0: aload_1
       1: aload_0
       2: if_acmpne     7
       5: iconst_1
       6: ireturn
       7: aload_1
       8: instanceof    #53                 // class org/apache/hadoop/hbase/protobuf/generated/ClusterStatusProtos$ServerLoad
      11: ifne          20
      14: aload_0
      15: aload_1
      16: invokespecial #91                 // Method com/google/protobuf/GeneratedMessage.equals:(Ljava/lang/Object;)Z
      19: ireturn
      20: aload_1
      21: checkcast     #53                 // class org/apache/hadoop/hbase/protobuf/generated/ClusterStatusProtos$ServerLoad
      24: astore_2
      25: iconst_1
      26: istore_3
      27: iload_3
      28: ifeq          46
      31: aload_0
      32: invokevirtual #92                 // Method hasNumberOfRequests:()Z
      35: aload_2
      36: invokevirtual #92                 // Method hasNumberOfRequests:()Z
      39: if_icmpne     46
      42: iconst_1
      43: goto          47
      46: iconst_0
      47: istore_3
      48: aload_0
      49: invokevirtual #92                 // Method hasNumberOfRequests:()Z
      52: ifeq          77
      55: iload_3
      56: ifeq          75
      59: aload_0
      60: invokevirtual #93                 // Method getNumberOfRequests:()J
      63: aload_2
      64: invokevirtual #93                 // Method getNumberOfRequests:()J
      67: lcmp
      68: ifne          75
      71: iconst_1
      72: goto          76
      75: iconst_0
      76: istore_3
      77: iload_3
      78: ifeq          96
      81: aload_0
      82: invokevirtual #94                 // Method hasTotalNumberOfRequests:()Z
      85: aload_2
      86: invokevirtual #94                 // Method hasTotalNumberOfRequests:()Z
      89: if_icmpne     96
      92: iconst_1
      93: goto          97
      96: iconst_0
      97: istore_3
      98: aload_0
      99: invokevirtual #94                 // Method hasTotalNumberOfRequests:()Z
     102: ifeq          127
     105: iload_3
     106: ifeq          125
     109: aload_0
     110: invokevirtual #95                 // Method getTotalNumberOfRequests:()J
     113: aload_2
     114: invokevirtual #95                 // Method getTotalNumberOfRequests:()J
     117: lcmp
     118: ifne          125
     121: iconst_1
     122: goto          126
     125: iconst_0
     126: istore_3
     127: iload_3
     128: ifeq          146
     131: aload_0
     132: invokevirtual #96                 // Method hasUsedHeapMB:()Z
     135: aload_2
     136: invokevirtual #96                 // Method hasUsedHeapMB:()Z
     139: if_icmpne     146
     142: iconst_1
     143: goto          147
     146: iconst_0
     147: istore_3
     148: aload_0
     149: invokevirtual #96                 // Method hasUsedHeapMB:()Z
     152: ifeq          176
     155: iload_3
     156: ifeq          174
     159: aload_0
     160: invokevirtual #97                 // Method getUsedHeapMB:()I
     163: aload_2
     164: invokevirtual #97                 // Method getUsedHeapMB:()I
     167: if_icmpne     174
     170: iconst_1
     171: goto          175
     174: iconst_0
     175: istore_3
     176: iload_3
     177: ifeq          195
     180: aload_0
     181: invokevirtual #98                 // Method hasMaxHeapMB:()Z
     184: aload_2
     185: invokevirtual #98                 // Method hasMaxHeapMB:()Z
     188: if_icmpne     195
     191: iconst_1
     192: goto          196
     195: iconst_0
     196: istore_3
     197: aload_0
     198: invokevirtual #98                 // Method hasMaxHeapMB:()Z
     201: ifeq          225
     204: iload_3
     205: ifeq          223
     208: aload_0
     209: invokevirtual #99                 // Method getMaxHeapMB:()I
     212: aload_2
     213: invokevirtual #99                 // Method getMaxHeapMB:()I
     216: if_icmpne     223
     219: iconst_1
     220: goto          224
     223: iconst_0
     224: istore_3
     225: iload_3
     226: ifeq          249
     229: aload_0
     230: invokevirtual #100                // Method getRegionLoadsList:()Ljava/util/List;
     233: aload_2
     234: invokevirtual #100                // Method getRegionLoadsList:()Ljava/util/List;
     237: invokeinterface #101,  2          // InterfaceMethod java/util/List.equals:(Ljava/lang/Object;)Z
     242: ifeq          249
     245: iconst_1
     246: goto          250
     249: iconst_0
     250: istore_3
     251: iload_3
     252: ifeq          275
     255: aload_0
     256: invokevirtual #102                // Method getCoprocessorsList:()Ljava/util/List;
     259: aload_2
     260: invokevirtual #102                // Method getCoprocessorsList:()Ljava/util/List;
     263: invokeinterface #101,  2          // InterfaceMethod java/util/List.equals:(Ljava/lang/Object;)Z
     268: ifeq          275
     271: iconst_1
     272: goto          276
     275: iconst_0
     276: istore_3
     277: iload_3
     278: ifeq          296
     281: aload_0
     282: invokevirtual #103                // Method hasReportStartTime:()Z
     285: aload_2
     286: invokevirtual #103                // Method hasReportStartTime:()Z
     289: if_icmpne     296
     292: iconst_1
     293: goto          297
     296: iconst_0
     297: istore_3
     298: aload_0
     299: invokevirtual #103                // Method hasReportStartTime:()Z
     302: ifeq          327
     305: iload_3
     306: ifeq          325
     309: aload_0
     310: invokevirtual #104                // Method getReportStartTime:()J
     313: aload_2
     314: invokevirtual #104                // Method getReportStartTime:()J
     317: lcmp
     318: ifne          325
     321: iconst_1
     322: goto          326
     325: iconst_0
     326: istore_3
     327: iload_3
     328: ifeq          346
     331: aload_0
     332: invokevirtual #105                // Method hasReportEndTime:()Z
     335: aload_2
     336: invokevirtual #105                // Method hasReportEndTime:()Z
     339: if_icmpne     346
     342: iconst_1
     343: goto          347
     346: iconst_0
     347: istore_3
     348: aload_0
     349: invokevirtual #105                // Method hasReportEndTime:()Z
     352: ifeq          377
     355: iload_3
     356: ifeq          375
     359: aload_0
     360: invokevirtual #106                // Method getReportEndTime:()J
     363: aload_2
     364: invokevirtual #106                // Method getReportEndTime:()J
     367: lcmp
     368: ifne          375
     371: iconst_1
     372: goto          376
     375: iconst_0
     376: istore_3
     377: iload_3
     378: ifeq          396
     381: aload_0
     382: invokevirtual #107                // Method hasInfoServerPort:()Z
     385: aload_2
     386: invokevirtual #107                // Method hasInfoServerPort:()Z
     389: if_icmpne     396
     392: iconst_1
     393: goto          397
     396: iconst_0
     397: istore_3
     398: aload_0
     399: invokevirtual #107                // Method hasInfoServerPort:()Z
     402: ifeq          426
     405: iload_3
     406: ifeq          424
     409: aload_0
     410: invokevirtual #108                // Method getInfoServerPort:()I
     413: aload_2
     414: invokevirtual #108                // Method getInfoServerPort:()I
     417: if_icmpne     424
     420: iconst_1
     421: goto          425
     424: iconst_0
     425: istore_3
     426: iload_3
     427: ifeq          450
     430: aload_0
     431: invokevirtual #109                // Method getReplLoadSourceList:()Ljava/util/List;
     434: aload_2
     435: invokevirtual #109                // Method getReplLoadSourceList:()Ljava/util/List;
     438: invokeinterface #101,  2          // InterfaceMethod java/util/List.equals:(Ljava/lang/Object;)Z
     443: ifeq          450
     446: iconst_1
     447: goto          451
     450: iconst_0
     451: istore_3
     452: iload_3
     453: ifeq          471
     456: aload_0
     457: invokevirtual #76                 // Method hasReplLoadSink:()Z
     460: aload_2
     461: invokevirtual #76                 // Method hasReplLoadSink:()Z
     464: if_icmpne     471
     467: iconst_1
     468: goto          472
     471: iconst_0
     472: istore_3
     473: aload_0
     474: invokevirtual #76                 // Method hasReplLoadSink:()Z
     477: ifeq          504
     480: iload_3
     481: ifeq          502
     484: aload_0
     485: invokevirtual #77                 // Method getReplLoadSink:()Lorg/apache/hadoop/hbase/protobuf/generated/ClusterStatusProtos$ReplicationLoadSink;
     488: aload_2
     489: invokevirtual #77                 // Method getReplLoadSink:()Lorg/apache/hadoop/hbase/protobuf/generated/ClusterStatusProtos$ReplicationLoadSink;
     492: invokevirtual #110                // Method org/apache/hadoop/hbase/protobuf/generated/ClusterStatusProtos$ReplicationLoadSink.equals:(Ljava/lang/Object;)Z
     495: ifeq          502
     498: iconst_1
     499: goto          503
     502: iconst_0
     503: istore_3
     504: iload_3
     505: ifeq          526
     508: aload_0
     509: invokevirtual #84                 // Method getUnknownFields:()Lcom/google/protobuf/UnknownFieldSet;
     512: aload_2
     513: invokevirtual #84                 // Method getUnknownFields:()Lcom/google/protobuf/UnknownFieldSet;
     516: invokevirtual #111                // Method com/google/protobuf/UnknownFieldSet.equals:(Ljava/lang/Object;)Z
     519: ifeq          526
     522: iconst_1
     523: goto          527
     526: iconst_0
     527: istore_3
     528: iload_3
     529: ireturn

  public int hashCode();
    Code:
       0: aload_0
       1: getfield      #19                 // Field memoizedHashCode:I
       4: ifeq          12
       7: aload_0
       8: getfield      #19                 // Field memoizedHashCode:I
      11: ireturn
      12: bipush        41
      14: istore_1
      15: bipush        19
      17: iload_1
      18: imul
      19: aload_0
      20: invokevirtual #112                // Method getDescriptorForType:()Lcom/google/protobuf/Descriptors$Descriptor;
      23: invokevirtual #113                // Method java/lang/Object.hashCode:()I
      26: iadd
      27: istore_1
      28: aload_0
      29: invokevirtual #92                 // Method hasNumberOfRequests:()Z
      32: ifeq          55
      35: bipush        37
      37: iload_1
      38: imul
      39: iconst_1
      40: iadd
      41: istore_1
      42: bipush        53
      44: iload_1
      45: imul
      46: aload_0
      47: invokevirtual #93                 // Method getNumberOfRequests:()J
      50: invokestatic  #114                // Method hashLong:(J)I
      53: iadd
      54: istore_1
      55: aload_0
      56: invokevirtual #94                 // Method hasTotalNumberOfRequests:()Z
      59: ifeq          82
      62: bipush        37
      64: iload_1
      65: imul
      66: iconst_2
      67: iadd
      68: istore_1
      69: bipush        53
      71: iload_1
      72: imul
      73: aload_0
      74: invokevirtual #95                 // Method getTotalNumberOfRequests:()J
      77: invokestatic  #114                // Method hashLong:(J)I
      80: iadd
      81: istore_1
      82: aload_0
      83: invokevirtual #96                 // Method hasUsedHeapMB:()Z
      86: ifeq          106
      89: bipush        37
      91: iload_1
      92: imul
      93: iconst_3
      94: iadd
      95: istore_1
      96: bipush        53
      98: iload_1
      99: imul
     100: aload_0
     101: invokevirtual #97                 // Method getUsedHeapMB:()I
     104: iadd
     105: istore_1
     106: aload_0
     107: invokevirtual #98                 // Method hasMaxHeapMB:()Z
     110: ifeq          130
     113: bipush        37
     115: iload_1
     116: imul
     117: iconst_4
     118: iadd
     119: istore_1
     120: bipush        53
     122: iload_1
     123: imul
     124: aload_0
     125: invokevirtual #99                 // Method getMaxHeapMB:()I
     128: iadd
     129: istore_1
     130: aload_0
     131: invokevirtual #67                 // Method getRegionLoadsCount:()I
     134: ifle          159
     137: bipush        37
     139: iload_1
     140: imul
     141: iconst_5
     142: iadd
     143: istore_1
     144: bipush        53
     146: iload_1
     147: imul
     148: aload_0
     149: invokevirtual #100                // Method getRegionLoadsList:()Ljava/util/List;
     152: invokeinterface #115,  1          // InterfaceMethod java/util/List.hashCode:()I
     157: iadd
     158: istore_1
     159: aload_0
     160: invokevirtual #70                 // Method getCoprocessorsCount:()I
     163: ifle          189
     166: bipush        37
     168: iload_1
     169: imul
     170: bipush        6
     172: iadd
     173: istore_1
     174: bipush        53
     176: iload_1
     177: imul
     178: aload_0
     179: invokevirtual #102                // Method getCoprocessorsList:()Ljava/util/List;
     182: invokeinterface #115,  1          // InterfaceMethod java/util/List.hashCode:()I
     187: iadd
     188: istore_1
     189: aload_0
     190: invokevirtual #103                // Method hasReportStartTime:()Z
     193: ifeq          217
     196: bipush        37
     198: iload_1
     199: imul
     200: bipush        7
     202: iadd
     203: istore_1
     204: bipush        53
     206: iload_1
     207: imul
     208: aload_0
     209: invokevirtual #104                // Method getReportStartTime:()J
     212: invokestatic  #114                // Method hashLong:(J)I
     215: iadd
     216: istore_1
     217: aload_0
     218: invokevirtual #105                // Method hasReportEndTime:()Z
     221: ifeq          245
     224: bipush        37
     226: iload_1
     227: imul
     228: bipush        8
     230: iadd
     231: istore_1
     232: bipush        53
     234: iload_1
     235: imul
     236: aload_0
     237: invokevirtual #106                // Method getReportEndTime:()J
     240: invokestatic  #114                // Method hashLong:(J)I
     243: iadd
     244: istore_1
     245: aload_0
     246: invokevirtual #107                // Method hasInfoServerPort:()Z
     249: ifeq          270
     252: bipush        37
     254: iload_1
     255: imul
     256: bipush        9
     258: iadd
     259: istore_1
     260: bipush        53
     262: iload_1
     263: imul
     264: aload_0
     265: invokevirtual #108                // Method getInfoServerPort:()I
     268: iadd
     269: istore_1
     270: aload_0
     271: invokevirtual #73                 // Method getReplLoadSourceCount:()I
     274: ifle          300
     277: bipush        37
     279: iload_1
     280: imul
     281: bipush        10
     283: iadd
     284: istore_1
     285: bipush        53
     287: iload_1
     288: imul
     289: aload_0
     290: invokevirtual #109                // Method getReplLoadSourceList:()Ljava/util/List;
     293: invokeinterface #115,  1          // InterfaceMethod java/util/List.hashCode:()I
     298: iadd
     299: istore_1
     300: aload_0
     301: invokevirtual #76                 // Method hasReplLoadSink:()Z
     304: ifeq          328
     307: bipush        37
     309: iload_1
     310: imul
     311: bipush        11
     313: iadd
     314: istore_1
     315: bipush        53
     317: iload_1
     318: imul
     319: aload_0
     320: invokevirtual #77                 // Method getReplLoadSink:()Lorg/apache/hadoop/hbase/protobuf/generated/ClusterStatusProtos$ReplicationLoadSink;
     323: invokevirtual #116                // Method org/apache/hadoop/hbase/protobuf/generated/ClusterStatusProtos$ReplicationLoadSink.hashCode:()I
     326: iadd
     327: istore_1
     328: bipush        29
     330: iload_1
     331: imul
     332: aload_0
     333: invokevirtual #84                 // Method getUnknownFields:()Lcom/google/protobuf/UnknownFieldSet;
     336: invokevirtual #117                // Method com/google/protobuf/UnknownFieldSet.hashCode:()I
     339: iadd
     340: istore_1
     341: aload_0
     342: iload_1
     343: putfield      #19                 // Field memoizedHashCode:I
     346: iload_1
     347: ireturn

  public static org.apache.hadoop.hbase.protobuf.generated.ClusterStatusProtos$ServerLoad parseFrom(com.google.protobuf.ByteString) throws com.google.protobuf.InvalidProtocolBufferException;
    Code:
       0: getstatic     #56                 // Field PARSER:Lcom/google/protobuf/Parser;
       3: aload_0
       4: invokeinterface #118,  2          // InterfaceMethod com/google/protobuf/Parser.parseFrom:(Lcom/google/protobuf/ByteString;)Ljava/lang/Object;
       9: checkcast     #53                 // class org/apache/hadoop/hbase/protobuf/generated/ClusterStatusProtos$ServerLoad
      12: areturn

  public static org.apache.hadoop.hbase.protobuf.generated.ClusterStatusProtos$ServerLoad parseFrom(com.google.protobuf.ByteString, com.google.protobuf.ExtensionRegistryLite) throws com.google.protobuf.InvalidProtocolBufferException;
    Code:
       0: getstatic     #56                 // Field PARSER:Lcom/google/protobuf/Parser;
       3: aload_0
       4: aload_1
       5: invokeinterface #119,  3          // InterfaceMethod com/google/protobuf/Parser.parseFrom:(Lcom/google/protobuf/ByteString;Lcom/google/protobuf/ExtensionRegistryLite;)Ljava/lang/Object;
      10: checkcast     #53                 // class org/apache/hadoop/hbase/protobuf/generated/ClusterStatusProtos$ServerLoad
      13: areturn

  public static org.apache.hadoop.hbase.protobuf.generated.ClusterStatusProtos$ServerLoad parseFrom(byte[]) throws com.google.protobuf.InvalidProtocolBufferException;
    Code:
       0: getstatic     #56                 // Field PARSER:Lcom/google/protobuf/Parser;
       3: aload_0
       4: invokeinterface #120,  2          // InterfaceMethod com/google/protobuf/Parser.parseFrom:([B)Ljava/lang/Object;
       9: checkcast     #53                 // class org/apache/hadoop/hbase/protobuf/generated/ClusterStatusProtos$ServerLoad
      12: areturn

  public static org.apache.hadoop.hbase.protobuf.generated.ClusterStatusProtos$ServerLoad parseFrom(byte[], com.google.protobuf.ExtensionRegistryLite) throws com.google.protobuf.InvalidProtocolBufferException;
    Code:
       0: getstatic     #56                 // Field PARSER:Lcom/google/protobuf/Parser;
       3: aload_0
       4: aload_1
       5: invokeinterface #121,  3          // InterfaceMethod com/google/protobuf/Parser.parseFrom:([BLcom/google/protobuf/ExtensionRegistryLite;)Ljava/lang/Object;
      10: checkcast     #53                 // class org/apache/hadoop/hbase/protobuf/generated/ClusterStatusProtos$ServerLoad
      13: areturn

  public static org.apache.hadoop.hbase.protobuf.generated.ClusterStatusProtos$ServerLoad parseFrom(java.io.InputStream) throws java.io.IOException;
    Code:
       0: getstatic     #56                 // Field PARSER:Lcom/google/protobuf/Parser;
       3: aload_0
       4: invokeinterface #122,  2          // InterfaceMethod com/google/protobuf/Parser.parseFrom:(Ljava/io/InputStream;)Ljava/lang/Object;
       9: checkcast     #53                 // class org/apache/hadoop/hbase/protobuf/generated/ClusterStatusProtos$ServerLoad
      12: areturn

  public static org.apache.hadoop.hbase.protobuf.generated.ClusterStatusProtos$ServerLoad parseFrom(java.io.InputStream, com.google.protobuf.ExtensionRegistryLite) throws java.io.IOException;
    Code:
       0: getstatic     #56                 // Field PARSER:Lcom/google/protobuf/Parser;
       3: aload_0
       4: aload_1
       5: invokeinterface #123,  3          // InterfaceMethod com/google/protobuf/Parser.parseFrom:(Ljava/io/InputStream;Lcom/google/protobuf/ExtensionRegistryLite;)Ljava/lang/Object;
      10: checkcast     #53                 // class org/apache/hadoop/hbase/protobuf/generated/ClusterStatusProtos$ServerLoad
      13: areturn

  public static org.apache.hadoop.hbase.protobuf.generated.ClusterStatusProtos$ServerLoad parseDelimitedFrom(java.io.InputStream) throws java.io.IOException;
    Code:
       0: getstatic     #56                 // Field PARSER:Lcom/google/protobuf/Parser;
       3: aload_0
       4: invokeinterface #124,  2          // InterfaceMethod com/google/protobuf/Parser.parseDelimitedFrom:(Ljava/io/InputStream;)Ljava/lang/Object;
       9: checkcast     #53                 // class org/apache/hadoop/hbase/protobuf/generated/ClusterStatusProtos$ServerLoad
      12: areturn

  public static org.apache.hadoop.hbase.protobuf.generated.ClusterStatusProtos$ServerLoad parseDelimitedFrom(java.io.InputStream, com.google.protobuf.ExtensionRegistryLite) throws java.io.IOException;
    Code:
       0: getstatic     #56                 // Field PARSER:Lcom/google/protobuf/Parser;
       3: aload_0
       4: aload_1
       5: invokeinterface #125,  3          // InterfaceMethod com/google/protobuf/Parser.parseDelimitedFrom:(Ljava/io/InputStream;Lcom/google/protobuf/ExtensionRegistryLite;)Ljava/lang/Object;
      10: checkcast     #53                 // class org/apache/hadoop/hbase/protobuf/generated/ClusterStatusProtos$ServerLoad
      13: areturn

  public static org.apache.hadoop.hbase.protobuf.generated.ClusterStatusProtos$ServerLoad parseFrom(com.google.protobuf.CodedInputStream) throws java.io.IOException;
    Code:
       0: getstatic     #56                 // Field PARSER:Lcom/google/protobuf/Parser;
       3: aload_0
       4: invokeinterface #126,  2          // InterfaceMethod com/google/protobuf/Parser.parseFrom:(Lcom/google/protobuf/CodedInputStream;)Ljava/lang/Object;
       9: checkcast     #53                 // class org/apache/hadoop/hbase/protobuf/generated/ClusterStatusProtos$ServerLoad
      12: areturn

  public static org.apache.hadoop.hbase.protobuf.generated.ClusterStatusProtos$ServerLoad parseFrom(com.google.protobuf.CodedInputStream, com.google.protobuf.ExtensionRegistryLite) throws java.io.IOException;
    Code:
       0: getstatic     #56                 // Field PARSER:Lcom/google/protobuf/Parser;
       3: aload_0
       4: aload_1
       5: invokeinterface #127,  3          // InterfaceMethod com/google/protobuf/Parser.parseFrom:(Lcom/google/protobuf/CodedInputStream;Lcom/google/protobuf/ExtensionRegistryLite;)Ljava/lang/Object;
      10: checkcast     #53                 // class org/apache/hadoop/hbase/protobuf/generated/ClusterStatusProtos$ServerLoad
      13: areturn

  public static org.apache.hadoop.hbase.protobuf.generated.ClusterStatusProtos$ServerLoad$Builder newBuilder();
    Code:
       0: invokestatic  #128                // Method org/apache/hadoop/hbase/protobuf/generated/ClusterStatusProtos$ServerLoad$Builder.access$9800:()Lorg/apache/hadoop/hbase/protobuf/generated/ClusterStatusProtos$ServerLoad$Builder;
       3: areturn

  public org.apache.hadoop.hbase.protobuf.generated.ClusterStatusProtos$ServerLoad$Builder newBuilderForType();
    Code:
       0: invokestatic  #129                // Method newBuilder:()Lorg/apache/hadoop/hbase/protobuf/generated/ClusterStatusProtos$ServerLoad$Builder;
       3: areturn

  public static org.apache.hadoop.hbase.protobuf.generated.ClusterStatusProtos$ServerLoad$Builder newBuilder(org.apache.hadoop.hbase.protobuf.generated.ClusterStatusProtos$ServerLoad);
    Code:
       0: invokestatic  #129                // Method newBuilder:()Lorg/apache/hadoop/hbase/protobuf/generated/ClusterStatusProtos$ServerLoad$Builder;
       3: aload_0
       4: invokevirtual #130                // Method org/apache/hadoop/hbase/protobuf/generated/ClusterStatusProtos$ServerLoad$Builder.mergeFrom:(Lorg/apache/hadoop/hbase/protobuf/generated/ClusterStatusProtos$ServerLoad;)Lorg/apache/hadoop/hbase/protobuf/generated/ClusterStatusProtos$ServerLoad$Builder;
       7: areturn

  public org.apache.hadoop.hbase.protobuf.generated.ClusterStatusProtos$ServerLoad$Builder toBuilder();
    Code:
       0: aload_0
       1: invokestatic  #131                // Method newBuilder:(Lorg/apache/hadoop/hbase/protobuf/generated/ClusterStatusProtos$ServerLoad;)Lorg/apache/hadoop/hbase/protobuf/generated/ClusterStatusProtos$ServerLoad$Builder;
       4: areturn

  protected org.apache.hadoop.hbase.protobuf.generated.ClusterStatusProtos$ServerLoad$Builder newBuilderForType(com.google.protobuf.GeneratedMessage$BuilderParent);
    Code:
       0: new           #54                 // class org/apache/hadoop/hbase/protobuf/generated/ClusterStatusProtos$ServerLoad$Builder
       3: dup
       4: aload_1
       5: aconst_null
       6: invokespecial #132                // Method org/apache/hadoop/hbase/protobuf/generated/ClusterStatusProtos$ServerLoad$Builder."<init>":(Lcom/google/protobuf/GeneratedMessage$BuilderParent;Lorg/apache/hadoop/hbase/protobuf/generated/ClusterStatusProtos$1;)V
       9: astore_2
      10: aload_2
      11: areturn

  protected com.google.protobuf.Message$Builder newBuilderForType(com.google.protobuf.GeneratedMessage$BuilderParent);
    Code:
       0: aload_0
       1: aload_1
       2: invokevirtual #133                // Method newBuilderForType:(Lcom/google/protobuf/GeneratedMessage$BuilderParent;)Lorg/apache/hadoop/hbase/protobuf/generated/ClusterStatusProtos$ServerLoad$Builder;
       5: areturn

  public com.google.protobuf.Message$Builder toBuilder();
    Code:
       0: aload_0
       1: invokevirtual #134                // Method toBuilder:()Lorg/apache/hadoop/hbase/protobuf/generated/ClusterStatusProtos$ServerLoad$Builder;
       4: areturn

  public com.google.protobuf.Message$Builder newBuilderForType();
    Code:
       0: aload_0
       1: invokevirtual #135                // Method newBuilderForType:()Lorg/apache/hadoop/hbase/protobuf/generated/ClusterStatusProtos$ServerLoad$Builder;
       4: areturn

  public com.google.protobuf.MessageLite$Builder toBuilder();
    Code:
       0: aload_0
       1: invokevirtual #134                // Method toBuilder:()Lorg/apache/hadoop/hbase/protobuf/generated/ClusterStatusProtos$ServerLoad$Builder;
       4: areturn

  public com.google.protobuf.MessageLite$Builder newBuilderForType();
    Code:
       0: aload_0
       1: invokevirtual #135                // Method newBuilderForType:()Lorg/apache/hadoop/hbase/protobuf/generated/ClusterStatusProtos$ServerLoad$Builder;
       4: areturn

  public com.google.protobuf.MessageLite getDefaultInstanceForType();
    Code:
       0: aload_0
       1: invokevirtual #136                // Method getDefaultInstanceForType:()Lorg/apache/hadoop/hbase/protobuf/generated/ClusterStatusProtos$ServerLoad;
       4: areturn

  public com.google.protobuf.Message getDefaultInstanceForType();
    Code:
       0: aload_0
       1: invokevirtual #136                // Method getDefaultInstanceForType:()Lorg/apache/hadoop/hbase/protobuf/generated/ClusterStatusProtos$ServerLoad;
       4: areturn

  org.apache.hadoop.hbase.protobuf.generated.ClusterStatusProtos$ServerLoad(com.google.protobuf.CodedInputStream, com.google.protobuf.ExtensionRegistryLite, org.apache.hadoop.hbase.protobuf.generated.ClusterStatusProtos$1) throws com.google.protobuf.InvalidProtocolBufferException;
    Code:
       0: aload_0
       1: aload_1
       2: aload_2
       3: invokespecial #15                 // Method "<init>":(Lcom/google/protobuf/CodedInputStream;Lcom/google/protobuf/ExtensionRegistryLite;)V
       6: return

  static boolean access$10000();
    Code:
       0: getstatic     #1                  // Field alwaysUseFieldBuilders:Z
       3: ireturn

  org.apache.hadoop.hbase.protobuf.generated.ClusterStatusProtos$ServerLoad(com.google.protobuf.GeneratedMessage$Builder, org.apache.hadoop.hbase.protobuf.generated.ClusterStatusProtos$1);
    Code:
       0: aload_0
       1: aload_1
       2: invokespecial #14                 // Method "<init>":(Lcom/google/protobuf/GeneratedMessage$Builder;)V
       5: return

  static long access$10202(org.apache.hadoop.hbase.protobuf.generated.ClusterStatusProtos$ServerLoad, long);
    Code:
       0: aload_0
       1: lload_1
       2: dup2_x1
       3: putfield      #13                 // Field numberOfRequests_:J
       6: lreturn

  static long access$10302(org.apache.hadoop.hbase.protobuf.generated.ClusterStatusProtos$ServerLoad, long);
    Code:
       0: aload_0
       1: lload_1
       2: dup2_x1
       3: putfield      #12                 // Field totalNumberOfRequests_:J
       6: lreturn

  static int access$10402(org.apache.hadoop.hbase.protobuf.generated.ClusterStatusProtos$ServerLoad, int);
    Code:
       0: aload_0
       1: iload_1
       2: dup_x1
       3: putfield      #11                 // Field usedHeapMB_:I
       6: ireturn

  static int access$10502(org.apache.hadoop.hbase.protobuf.generated.ClusterStatusProtos$ServerLoad, int);
    Code:
       0: aload_0
       1: iload_1
       2: dup_x1
       3: putfield      #10                 // Field maxHeapMB_:I
       6: ireturn

  static java.util.List access$10602(org.apache.hadoop.hbase.protobuf.generated.ClusterStatusProtos$ServerLoad, java.util.List);
    Code:
       0: aload_0
       1: aload_1
       2: dup_x1
       3: putfield      #9                  // Field regionLoads_:Ljava/util/List;
       6: areturn

  static java.util.List access$10702(org.apache.hadoop.hbase.protobuf.generated.ClusterStatusProtos$ServerLoad, java.util.List);
    Code:
       0: aload_0
       1: aload_1
       2: dup_x1
       3: putfield      #8                  // Field coprocessors_:Ljava/util/List;
       6: areturn

  static long access$10802(org.apache.hadoop.hbase.protobuf.generated.ClusterStatusProtos$ServerLoad, long);
    Code:
       0: aload_0
       1: lload_1
       2: dup2_x1
       3: putfield      #7                  // Field reportStartTime_:J
       6: lreturn

  static long access$10902(org.apache.hadoop.hbase.protobuf.generated.ClusterStatusProtos$ServerLoad, long);
    Code:
       0: aload_0
       1: lload_1
       2: dup2_x1
       3: putfield      #6                  // Field reportEndTime_:J
       6: lreturn

  static int access$11002(org.apache.hadoop.hbase.protobuf.generated.ClusterStatusProtos$ServerLoad, int);
    Code:
       0: aload_0
       1: iload_1
       2: dup_x1
       3: putfield      #5                  // Field infoServerPort_:I
       6: ireturn

  static java.util.List access$11102(org.apache.hadoop.hbase.protobuf.generated.ClusterStatusProtos$ServerLoad, java.util.List);
    Code:
       0: aload_0
       1: aload_1
       2: dup_x1
       3: putfield      #4                  // Field replLoadSource_:Ljava/util/List;
       6: areturn

  static org.apache.hadoop.hbase.protobuf.generated.ClusterStatusProtos$ReplicationLoadSink access$11202(org.apache.hadoop.hbase.protobuf.generated.ClusterStatusProtos$ServerLoad, org.apache.hadoop.hbase.protobuf.generated.ClusterStatusProtos$ReplicationLoadSink);
    Code:
       0: aload_0
       1: aload_1
       2: dup_x1
       3: putfield      #3                  // Field replLoadSink_:Lorg/apache/hadoop/hbase/protobuf/generated/ClusterStatusProtos$ReplicationLoadSink;
       6: areturn

  static int access$11302(org.apache.hadoop.hbase.protobuf.generated.ClusterStatusProtos$ServerLoad, int);
    Code:
       0: aload_0
       1: iload_1
       2: dup_x1
       3: putfield      #2                  // Field bitField0_:I
       6: ireturn

  static java.util.List access$10600(org.apache.hadoop.hbase.protobuf.generated.ClusterStatusProtos$ServerLoad);
    Code:
       0: aload_0
       1: getfield      #9                  // Field regionLoads_:Ljava/util/List;
       4: areturn

  static boolean access$11400();
    Code:
       0: getstatic     #1                  // Field alwaysUseFieldBuilders:Z
       3: ireturn

  static java.util.List access$10700(org.apache.hadoop.hbase.protobuf.generated.ClusterStatusProtos$ServerLoad);
    Code:
       0: aload_0
       1: getfield      #8                  // Field coprocessors_:Ljava/util/List;
       4: areturn

  static boolean access$11500();
    Code:
       0: getstatic     #1                  // Field alwaysUseFieldBuilders:Z
       3: ireturn

  static java.util.List access$11100(org.apache.hadoop.hbase.protobuf.generated.ClusterStatusProtos$ServerLoad);
    Code:
       0: aload_0
       1: getfield      #4                  // Field replLoadSource_:Ljava/util/List;
       4: areturn

  static boolean access$11600();
    Code:
       0: getstatic     #1                  // Field alwaysUseFieldBuilders:Z
       3: ireturn

  static {};
    Code:
       0: new           #137                // class org/apache/hadoop/hbase/protobuf/generated/ClusterStatusProtos$ServerLoad$1
       3: dup
       4: invokespecial #138                // Method org/apache/hadoop/hbase/protobuf/generated/ClusterStatusProtos$ServerLoad$1."<init>":()V
       7: putstatic     #56                 // Field PARSER:Lcom/google/protobuf/Parser;
      10: new           #53                 // class org/apache/hadoop/hbase/protobuf/generated/ClusterStatusProtos$ServerLoad
      13: dup
      14: iconst_1
      15: invokespecial #139                // Method "<init>":(Z)V
      18: putstatic     #24                 // Field defaultInstance:Lorg/apache/hadoop/hbase/protobuf/generated/ClusterStatusProtos$ServerLoad;
      21: getstatic     #24                 // Field defaultInstance:Lorg/apache/hadoop/hbase/protobuf/generated/ClusterStatusProtos$ServerLoad;
      24: invokespecial #25                 // Method initFields:()V
      27: return
}
