Compiled from "CollectionBackedScanner.java"
public class org.apache.hadoop.hbase.util.CollectionBackedScanner extends org.apache.hadoop.hbase.regionserver.NonReversedNonLazyKeyValueScanner {
  final org.apache.hadoop.hbase.CellComparator comparator;

  public org.apache.hadoop.hbase.util.CollectionBackedScanner(java.util.SortedSet<org.apache.hadoop.hbase.Cell>);
    Code:
       0: aload_0
       1: aload_1
       2: invokestatic  #1                  // InterfaceMethod org/apache/hadoop/hbase/CellComparator.getInstance:()Lorg/apache/hadoop/hbase/CellComparator;
       5: invokespecial #2                  // Method "<init>":(Ljava/util/SortedSet;Lorg/apache/hadoop/hbase/CellComparator;)V
       8: return

  public org.apache.hadoop.hbase.util.CollectionBackedScanner(java.util.SortedSet<org.apache.hadoop.hbase.Cell>, org.apache.hadoop.hbase.CellComparator);
    Code:
       0: aload_0
       1: invokespecial #3                  // Method org/apache/hadoop/hbase/regionserver/NonReversedNonLazyKeyValueScanner."<init>":()V
       4: aload_0
       5: aload_2
       6: putfield      #4                  // Field comparator:Lorg/apache/hadoop/hbase/CellComparator;
       9: aload_0
      10: aload_1
      11: putfield      #5                  // Field data:Ljava/lang/Iterable;
      14: aload_0
      15: invokespecial #6                  // Method init:()V
      18: return

  public org.apache.hadoop.hbase.util.CollectionBackedScanner(java.util.List<org.apache.hadoop.hbase.Cell>);
    Code:
       0: aload_0
       1: aload_1
       2: invokestatic  #1                  // InterfaceMethod org/apache/hadoop/hbase/CellComparator.getInstance:()Lorg/apache/hadoop/hbase/CellComparator;
       5: invokespecial #7                  // Method "<init>":(Ljava/util/List;Lorg/apache/hadoop/hbase/CellComparator;)V
       8: return

  public org.apache.hadoop.hbase.util.CollectionBackedScanner(java.util.List<org.apache.hadoop.hbase.Cell>, org.apache.hadoop.hbase.CellComparator);
    Code:
       0: aload_0
       1: invokespecial #3                  // Method org/apache/hadoop/hbase/regionserver/NonReversedNonLazyKeyValueScanner."<init>":()V
       4: aload_1
       5: aload_2
       6: invokestatic  #8                  // Method java/util/Collections.sort:(Ljava/util/List;Ljava/util/Comparator;)V
       9: aload_0
      10: aload_2
      11: putfield      #4                  // Field comparator:Lorg/apache/hadoop/hbase/CellComparator;
      14: aload_0
      15: aload_1
      16: putfield      #5                  // Field data:Ljava/lang/Iterable;
      19: aload_0
      20: invokespecial #6                  // Method init:()V
      23: return

  public org.apache.hadoop.hbase.util.CollectionBackedScanner(org.apache.hadoop.hbase.CellComparator, org.apache.hadoop.hbase.Cell...);
    Code:
       0: aload_0
       1: invokespecial #3                  // Method org/apache/hadoop/hbase/regionserver/NonReversedNonLazyKeyValueScanner."<init>":()V
       4: aload_0
       5: aload_1
       6: putfield      #4                  // Field comparator:Lorg/apache/hadoop/hbase/CellComparator;
       9: new           #9                  // class java/util/ArrayList
      12: dup
      13: aload_2
      14: arraylength
      15: invokespecial #10                 // Method java/util/ArrayList."<init>":(I)V
      18: astore_3
      19: aload_3
      20: aload_2
      21: invokestatic  #11                 // Method java/util/Collections.addAll:(Ljava/util/Collection;[Ljava/lang/Object;)Z
      24: pop
      25: aload_3
      26: aload_1
      27: invokestatic  #8                  // Method java/util/Collections.sort:(Ljava/util/List;Ljava/util/Comparator;)V
      30: aload_0
      31: aload_3
      32: putfield      #5                  // Field data:Ljava/lang/Iterable;
      35: aload_0
      36: invokespecial #6                  // Method init:()V
      39: return

  public org.apache.hadoop.hbase.Cell peek();
    Code:
       0: aload_0
       1: getfield      #17                 // Field current:Lorg/apache/hadoop/hbase/Cell;
       4: areturn

  public org.apache.hadoop.hbase.Cell next();
    Code:
       0: aload_0
       1: getfield      #17                 // Field current:Lorg/apache/hadoop/hbase/Cell;
       4: astore_1
       5: aload_0
       6: getfield      #13                 // Field iter:Ljava/util/Iterator;
       9: invokeinterface #14,  1           // InterfaceMethod java/util/Iterator.hasNext:()Z
      14: ifeq          36
      17: aload_0
      18: aload_0
      19: getfield      #13                 // Field iter:Ljava/util/Iterator;
      22: invokeinterface #15,  1           // InterfaceMethod java/util/Iterator.next:()Ljava/lang/Object;
      27: checkcast     #16                 // class org/apache/hadoop/hbase/Cell
      30: putfield      #17                 // Field current:Lorg/apache/hadoop/hbase/Cell;
      33: goto          41
      36: aload_0
      37: aconst_null
      38: putfield      #17                 // Field current:Lorg/apache/hadoop/hbase/Cell;
      41: aload_1
      42: areturn

  public boolean seek(org.apache.hadoop.hbase.Cell);
    Code:
       0: aload_0
       1: aload_0
       2: getfield      #5                  // Field data:Ljava/lang/Iterable;
       5: invokeinterface #12,  1           // InterfaceMethod java/lang/Iterable.iterator:()Ljava/util/Iterator;
      10: putfield      #13                 // Field iter:Ljava/util/Iterator;
      13: aload_0
      14: aload_1
      15: invokevirtual #18                 // Method reseek:(Lorg/apache/hadoop/hbase/Cell;)Z
      18: ireturn

  public boolean reseek(org.apache.hadoop.hbase.Cell);
    Code:
       0: aload_0
       1: getfield      #13                 // Field iter:Ljava/util/Iterator;
       4: invokeinterface #14,  1           // InterfaceMethod java/util/Iterator.hasNext:()Z
       9: ifeq          51
      12: aload_0
      13: getfield      #13                 // Field iter:Ljava/util/Iterator;
      16: invokeinterface #15,  1           // InterfaceMethod java/util/Iterator.next:()Ljava/lang/Object;
      21: checkcast     #16                 // class org/apache/hadoop/hbase/Cell
      24: astore_2
      25: aload_0
      26: getfield      #4                  // Field comparator:Lorg/apache/hadoop/hbase/CellComparator;
      29: aload_2
      30: aload_1
      31: invokeinterface #19,  3           // InterfaceMethod org/apache/hadoop/hbase/CellComparator.compare:(Lorg/apache/hadoop/hbase/Cell;Lorg/apache/hadoop/hbase/Cell;)I
      36: istore_3
      37: iload_3
      38: iflt          48
      41: aload_0
      42: aload_2
      43: putfield      #17                 // Field current:Lorg/apache/hadoop/hbase/Cell;
      46: iconst_1
      47: ireturn
      48: goto          0
      51: iconst_0
      52: ireturn

  public void close();
    Code:
       0: return
}
