Compiled from "ColumnValueFilter.java"
public class org.apache.hadoop.hbase.filter.ColumnValueFilter extends org.apache.hadoop.hbase.filter.FilterBase {
  public org.apache.hadoop.hbase.filter.ColumnValueFilter(byte[], byte[], org.apache.hadoop.hbase.CompareOperator, byte[]);
    Code:
       0: aload_0
       1: aload_1
       2: aload_2
       3: aload_3
       4: new           #1                  // class org/apache/hadoop/hbase/filter/BinaryComparator
       7: dup
       8: aload         4
      10: invokespecial #2                  // Method org/apache/hadoop/hbase/filter/BinaryComparator."<init>":([B)V
      13: invokespecial #3                  // Method "<init>":([B[BLorg/apache/hadoop/hbase/CompareOperator;Lorg/apache/hadoop/hbase/filter/ByteArrayComparable;)V
      16: return

  public org.apache.hadoop.hbase.filter.ColumnValueFilter(byte[], byte[], org.apache.hadoop.hbase.CompareOperator, org.apache.hadoop.hbase.filter.ByteArrayComparable);
    Code:
       0: aload_0
       1: invokespecial #4                  // Method org/apache/hadoop/hbase/filter/FilterBase."<init>":()V
       4: aload_0
       5: iconst_0
       6: putfield      #5                  // Field columnFound:Z
       9: aload_0
      10: aload_1
      11: ldc           #6                  // String family should not be null.
      13: invokestatic  #7                  // Method org/apache/hbase/thirdparty/com/google/common/base/Preconditions.checkNotNull:(Ljava/lang/Object;Ljava/lang/Object;)Ljava/lang/Object;
      16: checkcast     #8                  // class "[B"
      19: putfield      #9                  // Field family:[B
      22: aload_0
      23: aload_2
      24: ifnonnull     33
      27: iconst_0
      28: newarray       byte
      30: goto          34
      33: aload_2
      34: putfield      #10                 // Field qualifier:[B
      37: aload_0
      38: aload_3
      39: ldc           #11                 // String CompareOperator should not be null
      41: invokestatic  #7                  // Method org/apache/hbase/thirdparty/com/google/common/base/Preconditions.checkNotNull:(Ljava/lang/Object;Ljava/lang/Object;)Ljava/lang/Object;
      44: checkcast     #12                 // class org/apache/hadoop/hbase/CompareOperator
      47: putfield      #13                 // Field op:Lorg/apache/hadoop/hbase/CompareOperator;
      50: aload_0
      51: aload         4
      53: ldc           #14                 // String Comparator should not be null
      55: invokestatic  #7                  // Method org/apache/hbase/thirdparty/com/google/common/base/Preconditions.checkNotNull:(Ljava/lang/Object;Ljava/lang/Object;)Ljava/lang/Object;
      58: checkcast     #15                 // class org/apache/hadoop/hbase/filter/ByteArrayComparable
      61: putfield      #16                 // Field comparator:Lorg/apache/hadoop/hbase/filter/ByteArrayComparable;
      64: return

  public org.apache.hadoop.hbase.CompareOperator getCompareOperator();
    Code:
       0: aload_0
       1: getfield      #13                 // Field op:Lorg/apache/hadoop/hbase/CompareOperator;
       4: areturn

  public org.apache.hadoop.hbase.filter.ByteArrayComparable getComparator();
    Code:
       0: aload_0
       1: getfield      #16                 // Field comparator:Lorg/apache/hadoop/hbase/filter/ByteArrayComparable;
       4: areturn

  public byte[] getFamily();
    Code:
       0: aload_0
       1: getfield      #9                  // Field family:[B
       4: areturn

  public byte[] getQualifier();
    Code:
       0: aload_0
       1: getfield      #10                 // Field qualifier:[B
       4: areturn

  public void reset() throws java.io.IOException;
    Code:
       0: aload_0
       1: iconst_0
       2: putfield      #5                  // Field columnFound:Z
       5: return

  public boolean filterRowKey(org.apache.hadoop.hbase.Cell) throws java.io.IOException;
    Code:
       0: iconst_0
       1: ireturn

  public org.apache.hadoop.hbase.filter.Filter$ReturnCode filterCell(org.apache.hadoop.hbase.Cell) throws java.io.IOException;
    Code:
       0: aload_1
       1: aload_0
       2: getfield      #9                  // Field family:[B
       5: aload_0
       6: getfield      #10                 // Field qualifier:[B
       9: invokestatic  #17                 // Method org/apache/hadoop/hbase/CellUtil.matchingColumn:(Lorg/apache/hadoop/hbase/Cell;[B[B)Z
      12: ifne          32
      15: aload_0
      16: getfield      #5                  // Field columnFound:Z
      19: ifeq          28
      22: getstatic     #18                 // Field org/apache/hadoop/hbase/filter/Filter$ReturnCode.NEXT_ROW:Lorg/apache/hadoop/hbase/filter/Filter$ReturnCode;
      25: goto          31
      28: getstatic     #19                 // Field org/apache/hadoop/hbase/filter/Filter$ReturnCode.NEXT_COL:Lorg/apache/hadoop/hbase/filter/Filter$ReturnCode;
      31: areturn
      32: aload_0
      33: iconst_1
      34: putfield      #5                  // Field columnFound:Z
      37: aload_0
      38: aload_0
      39: invokevirtual #20                 // Method getCompareOperator:()Lorg/apache/hadoop/hbase/CompareOperator;
      42: aload_0
      43: invokevirtual #21                 // Method getComparator:()Lorg/apache/hadoop/hbase/filter/ByteArrayComparable;
      46: aload_1
      47: invokespecial #22                 // Method compareValue:(Lorg/apache/hadoop/hbase/CompareOperator;Lorg/apache/hadoop/hbase/filter/ByteArrayComparable;Lorg/apache/hadoop/hbase/Cell;)Z
      50: ifeq          59
      53: getstatic     #23                 // Field org/apache/hadoop/hbase/filter/Filter$ReturnCode.SKIP:Lorg/apache/hadoop/hbase/filter/Filter$ReturnCode;
      56: goto          62
      59: getstatic     #24                 // Field org/apache/hadoop/hbase/filter/Filter$ReturnCode.INCLUDE:Lorg/apache/hadoop/hbase/filter/Filter$ReturnCode;
      62: areturn

  public static org.apache.hadoop.hbase.filter.Filter createFilterFromArguments(java.util.ArrayList<byte[]>);
    Code:
       0: aload_0
       1: invokevirtual #28                 // Method java/util/ArrayList.size:()I
       4: iconst_4
       5: if_icmpne     12
       8: iconst_1
       9: goto          13
      12: iconst_0
      13: ldc           #29                 // String Expect 4 arguments: %s
      15: aload_0
      16: invokevirtual #28                 // Method java/util/ArrayList.size:()I
      19: invokestatic  #30                 // Method org/apache/hbase/thirdparty/com/google/common/base/Preconditions.checkArgument:(ZLjava/lang/String;I)V
      22: aload_0
      23: iconst_0
      24: invokevirtual #31                 // Method java/util/ArrayList.get:(I)Ljava/lang/Object;
      27: checkcast     #8                  // class "[B"
      30: invokestatic  #32                 // Method org/apache/hadoop/hbase/filter/ParseFilter.removeQuotesFromByteArray:([B)[B
      33: astore_1
      34: aload_0
      35: iconst_1
      36: invokevirtual #31                 // Method java/util/ArrayList.get:(I)Ljava/lang/Object;
      39: checkcast     #8                  // class "[B"
      42: invokestatic  #32                 // Method org/apache/hadoop/hbase/filter/ParseFilter.removeQuotesFromByteArray:([B)[B
      45: astore_2
      46: aload_0
      47: iconst_2
      48: invokevirtual #31                 // Method java/util/ArrayList.get:(I)Ljava/lang/Object;
      51: checkcast     #8                  // class "[B"
      54: invokestatic  #33                 // Method org/apache/hadoop/hbase/filter/ParseFilter.createCompareOperator:([B)Lorg/apache/hadoop/hbase/CompareOperator;
      57: astore_3
      58: aload_0
      59: iconst_3
      60: invokevirtual #31                 // Method java/util/ArrayList.get:(I)Ljava/lang/Object;
      63: checkcast     #8                  // class "[B"
      66: invokestatic  #32                 // Method org/apache/hadoop/hbase/filter/ParseFilter.removeQuotesFromByteArray:([B)[B
      69: invokestatic  #34                 // Method org/apache/hadoop/hbase/filter/ParseFilter.createComparator:([B)Lorg/apache/hadoop/hbase/filter/ByteArrayComparable;
      72: astore        4
      74: aload         4
      76: instanceof    #35                 // class org/apache/hadoop/hbase/filter/RegexStringComparator
      79: ifne          90
      82: aload         4
      84: instanceof    #36                 // class org/apache/hadoop/hbase/filter/SubstringComparator
      87: ifeq          114
      90: aload_3
      91: getstatic     #37                 // Field org/apache/hadoop/hbase/CompareOperator.EQUAL:Lorg/apache/hadoop/hbase/CompareOperator;
      94: if_acmpeq     114
      97: aload_3
      98: getstatic     #38                 // Field org/apache/hadoop/hbase/CompareOperator.NOT_EQUAL:Lorg/apache/hadoop/hbase/CompareOperator;
     101: if_acmpeq     114
     104: new           #39                 // class java/lang/IllegalArgumentException
     107: dup
     108: ldc           #40                 // String A regexstring comparator and substring comparator can only be used with EQUAL and NOT_EQUAL
     110: invokespecial #41                 // Method java/lang/IllegalArgumentException."<init>":(Ljava/lang/String;)V
     113: athrow
     114: new           #42                 // class org/apache/hadoop/hbase/filter/ColumnValueFilter
     117: dup
     118: aload_1
     119: aload_2
     120: aload_3
     121: aload         4
     123: invokespecial #3                  // Method "<init>":([B[BLorg/apache/hadoop/hbase/CompareOperator;Lorg/apache/hadoop/hbase/filter/ByteArrayComparable;)V
     126: areturn

  org.apache.hadoop.hbase.shaded.protobuf.generated.FilterProtos$ColumnValueFilter convert();
    Code:
       0: invokestatic  #43                 // Method org/apache/hadoop/hbase/shaded/protobuf/generated/FilterProtos$ColumnValueFilter.newBuilder:()Lorg/apache/hadoop/hbase/shaded/protobuf/generated/FilterProtos$ColumnValueFilter$Builder;
       3: astore_1
       4: aload_1
       5: aload_0
       6: getfield      #9                  // Field family:[B
       9: invokestatic  #44                 // Method org/apache/hbase/thirdparty/com/google/protobuf/UnsafeByteOperations.unsafeWrap:([B)Lorg/apache/hbase/thirdparty/com/google/protobuf/ByteString;
      12: invokevirtual #45                 // Method org/apache/hadoop/hbase/shaded/protobuf/generated/FilterProtos$ColumnValueFilter$Builder.setFamily:(Lorg/apache/hbase/thirdparty/com/google/protobuf/ByteString;)Lorg/apache/hadoop/hbase/shaded/protobuf/generated/FilterProtos$ColumnValueFilter$Builder;
      15: pop
      16: aload_1
      17: aload_0
      18: getfield      #10                 // Field qualifier:[B
      21: invokestatic  #44                 // Method org/apache/hbase/thirdparty/com/google/protobuf/UnsafeByteOperations.unsafeWrap:([B)Lorg/apache/hbase/thirdparty/com/google/protobuf/ByteString;
      24: invokevirtual #46                 // Method org/apache/hadoop/hbase/shaded/protobuf/generated/FilterProtos$ColumnValueFilter$Builder.setQualifier:(Lorg/apache/hbase/thirdparty/com/google/protobuf/ByteString;)Lorg/apache/hadoop/hbase/shaded/protobuf/generated/FilterProtos$ColumnValueFilter$Builder;
      27: pop
      28: aload_1
      29: aload_0
      30: getfield      #13                 // Field op:Lorg/apache/hadoop/hbase/CompareOperator;
      33: invokevirtual #47                 // Method org/apache/hadoop/hbase/CompareOperator.name:()Ljava/lang/String;
      36: invokestatic  #48                 // Method org/apache/hadoop/hbase/shaded/protobuf/generated/HBaseProtos$CompareType.valueOf:(Ljava/lang/String;)Lorg/apache/hadoop/hbase/shaded/protobuf/generated/HBaseProtos$CompareType;
      39: invokevirtual #49                 // Method org/apache/hadoop/hbase/shaded/protobuf/generated/FilterProtos$ColumnValueFilter$Builder.setCompareOp:(Lorg/apache/hadoop/hbase/shaded/protobuf/generated/HBaseProtos$CompareType;)Lorg/apache/hadoop/hbase/shaded/protobuf/generated/FilterProtos$ColumnValueFilter$Builder;
      42: pop
      43: aload_1
      44: aload_0
      45: getfield      #16                 // Field comparator:Lorg/apache/hadoop/hbase/filter/ByteArrayComparable;
      48: invokestatic  #50                 // Method org/apache/hadoop/hbase/shaded/protobuf/ProtobufUtil.toComparator:(Lorg/apache/hadoop/hbase/filter/ByteArrayComparable;)Lorg/apache/hadoop/hbase/shaded/protobuf/generated/ComparatorProtos$Comparator;
      51: invokevirtual #51                 // Method org/apache/hadoop/hbase/shaded/protobuf/generated/FilterProtos$ColumnValueFilter$Builder.setComparator:(Lorg/apache/hadoop/hbase/shaded/protobuf/generated/ComparatorProtos$Comparator;)Lorg/apache/hadoop/hbase/shaded/protobuf/generated/FilterProtos$ColumnValueFilter$Builder;
      54: pop
      55: aload_1
      56: invokevirtual #52                 // Method org/apache/hadoop/hbase/shaded/protobuf/generated/FilterProtos$ColumnValueFilter$Builder.build:()Lorg/apache/hadoop/hbase/shaded/protobuf/generated/FilterProtos$ColumnValueFilter;
      59: areturn

  public static org.apache.hadoop.hbase.filter.ColumnValueFilter parseFrom(byte[]) throws org.apache.hadoop.hbase.exceptions.DeserializationException;
    Code:
       0: aload_0
       1: invokestatic  #53                 // Method org/apache/hadoop/hbase/shaded/protobuf/generated/FilterProtos$ColumnValueFilter.parseFrom:([B)Lorg/apache/hadoop/hbase/shaded/protobuf/generated/FilterProtos$ColumnValueFilter;
       4: astore_1
       5: goto          18
       8: astore_2
       9: new           #55                 // class org/apache/hadoop/hbase/exceptions/DeserializationException
      12: dup
      13: aload_2
      14: invokespecial #56                 // Method org/apache/hadoop/hbase/exceptions/DeserializationException."<init>":(Ljava/lang/Throwable;)V
      17: athrow
      18: aload_1
      19: invokevirtual #57                 // Method org/apache/hadoop/hbase/shaded/protobuf/generated/FilterProtos$ColumnValueFilter.getCompareOp:()Lorg/apache/hadoop/hbase/shaded/protobuf/generated/HBaseProtos$CompareType;
      22: invokevirtual #58                 // Method org/apache/hadoop/hbase/shaded/protobuf/generated/HBaseProtos$CompareType.name:()Ljava/lang/String;
      25: invokestatic  #59                 // Method org/apache/hadoop/hbase/CompareOperator.valueOf:(Ljava/lang/String;)Lorg/apache/hadoop/hbase/CompareOperator;
      28: astore_2
      29: aload_1
      30: invokevirtual #60                 // Method org/apache/hadoop/hbase/shaded/protobuf/generated/FilterProtos$ColumnValueFilter.getComparator:()Lorg/apache/hadoop/hbase/shaded/protobuf/generated/ComparatorProtos$Comparator;
      33: invokestatic  #61                 // Method org/apache/hadoop/hbase/shaded/protobuf/ProtobufUtil.toComparator:(Lorg/apache/hadoop/hbase/shaded/protobuf/generated/ComparatorProtos$Comparator;)Lorg/apache/hadoop/hbase/filter/ByteArrayComparable;
      36: astore_3
      37: goto          52
      40: astore        4
      42: new           #55                 // class org/apache/hadoop/hbase/exceptions/DeserializationException
      45: dup
      46: aload         4
      48: invokespecial #56                 // Method org/apache/hadoop/hbase/exceptions/DeserializationException."<init>":(Ljava/lang/Throwable;)V
      51: athrow
      52: new           #42                 // class org/apache/hadoop/hbase/filter/ColumnValueFilter
      55: dup
      56: aload_1
      57: invokevirtual #63                 // Method org/apache/hadoop/hbase/shaded/protobuf/generated/FilterProtos$ColumnValueFilter.getFamily:()Lorg/apache/hbase/thirdparty/com/google/protobuf/ByteString;
      60: invokevirtual #64                 // Method org/apache/hbase/thirdparty/com/google/protobuf/ByteString.toByteArray:()[B
      63: aload_1
      64: invokevirtual #65                 // Method org/apache/hadoop/hbase/shaded/protobuf/generated/FilterProtos$ColumnValueFilter.getQualifier:()Lorg/apache/hbase/thirdparty/com/google/protobuf/ByteString;
      67: invokevirtual #64                 // Method org/apache/hbase/thirdparty/com/google/protobuf/ByteString.toByteArray:()[B
      70: aload_2
      71: aload_3
      72: invokespecial #3                  // Method "<init>":([B[BLorg/apache/hadoop/hbase/CompareOperator;Lorg/apache/hadoop/hbase/filter/ByteArrayComparable;)V
      75: areturn
    Exception table:
       from    to  target type
           0     5     8   Class org/apache/hbase/thirdparty/com/google/protobuf/InvalidProtocolBufferException
          29    37    40   Class java/io/IOException

  public byte[] toByteArray() throws java.io.IOException;
    Code:
       0: aload_0
       1: invokevirtual #66                 // Method convert:()Lorg/apache/hadoop/hbase/shaded/protobuf/generated/FilterProtos$ColumnValueFilter;
       4: invokevirtual #67                 // Method org/apache/hadoop/hbase/shaded/protobuf/generated/FilterProtos$ColumnValueFilter.toByteArray:()[B
       7: areturn

  boolean areSerializedFieldsEqual(org.apache.hadoop.hbase.filter.Filter);
    Code:
       0: aload_1
       1: aload_0
       2: if_acmpne     7
       5: iconst_1
       6: ireturn
       7: aload_1
       8: instanceof    #42                 // class org/apache/hadoop/hbase/filter/ColumnValueFilter
      11: ifne          16
      14: iconst_0
      15: ireturn
      16: aload_1
      17: checkcast     #42                 // class org/apache/hadoop/hbase/filter/ColumnValueFilter
      20: astore_2
      21: aload_0
      22: invokevirtual #68                 // Method getFamily:()[B
      25: aload_2
      26: invokevirtual #68                 // Method getFamily:()[B
      29: invokestatic  #69                 // Method org/apache/hadoop/hbase/util/Bytes.equals:([B[B)Z
      32: ifeq          81
      35: aload_0
      36: invokevirtual #70                 // Method getQualifier:()[B
      39: aload_2
      40: invokevirtual #70                 // Method getQualifier:()[B
      43: invokestatic  #69                 // Method org/apache/hadoop/hbase/util/Bytes.equals:([B[B)Z
      46: ifeq          81
      49: aload_0
      50: invokevirtual #20                 // Method getCompareOperator:()Lorg/apache/hadoop/hbase/CompareOperator;
      53: aload_2
      54: invokevirtual #20                 // Method getCompareOperator:()Lorg/apache/hadoop/hbase/CompareOperator;
      57: invokevirtual #71                 // Method org/apache/hadoop/hbase/CompareOperator.equals:(Ljava/lang/Object;)Z
      60: ifeq          81
      63: aload_0
      64: invokevirtual #21                 // Method getComparator:()Lorg/apache/hadoop/hbase/filter/ByteArrayComparable;
      67: aload_2
      68: invokevirtual #21                 // Method getComparator:()Lorg/apache/hadoop/hbase/filter/ByteArrayComparable;
      71: invokevirtual #72                 // Method org/apache/hadoop/hbase/filter/ByteArrayComparable.areSerializedFieldsEqual:(Lorg/apache/hadoop/hbase/filter/ByteArrayComparable;)Z
      74: ifeq          81
      77: iconst_1
      78: goto          82
      81: iconst_0
      82: ireturn

  public boolean isFamilyEssential(byte[]) throws java.io.IOException;
    Code:
       0: aload_1
       1: aload_0
       2: getfield      #9                  // Field family:[B
       5: invokestatic  #69                 // Method org/apache/hadoop/hbase/util/Bytes.equals:([B[B)Z
       8: ireturn

  public java.lang.String toString();
    Code:
       0: ldc           #73                 // String %s (%s, %s, %s, %s)
       2: iconst_5
       3: anewarray     #74                 // class java/lang/Object
       6: dup
       7: iconst_0
       8: aload_0
       9: invokevirtual #75                 // Method java/lang/Object.getClass:()Ljava/lang/Class;
      12: invokevirtual #76                 // Method java/lang/Class.getSimpleName:()Ljava/lang/String;
      15: aastore
      16: dup
      17: iconst_1
      18: aload_0
      19: getfield      #9                  // Field family:[B
      22: invokestatic  #77                 // Method org/apache/hadoop/hbase/util/Bytes.toStringBinary:([B)Ljava/lang/String;
      25: aastore
      26: dup
      27: iconst_2
      28: aload_0
      29: getfield      #10                 // Field qualifier:[B
      32: invokestatic  #77                 // Method org/apache/hadoop/hbase/util/Bytes.toStringBinary:([B)Ljava/lang/String;
      35: aastore
      36: dup
      37: iconst_3
      38: aload_0
      39: getfield      #13                 // Field op:Lorg/apache/hadoop/hbase/CompareOperator;
      42: invokevirtual #47                 // Method org/apache/hadoop/hbase/CompareOperator.name:()Ljava/lang/String;
      45: aastore
      46: dup
      47: iconst_4
      48: aload_0
      49: getfield      #16                 // Field comparator:Lorg/apache/hadoop/hbase/filter/ByteArrayComparable;
      52: invokevirtual #78                 // Method org/apache/hadoop/hbase/filter/ByteArrayComparable.getValue:()[B
      55: invokestatic  #77                 // Method org/apache/hadoop/hbase/util/Bytes.toStringBinary:([B)Ljava/lang/String;
      58: aastore
      59: invokestatic  #79                 // Method java/lang/String.format:(Ljava/lang/String;[Ljava/lang/Object;)Ljava/lang/String;
      62: areturn

  public boolean equals(java.lang.Object);
    Code:
       0: aload_1
       1: instanceof    #80                 // class org/apache/hadoop/hbase/filter/Filter
       4: ifeq          22
       7: aload_0
       8: aload_1
       9: checkcast     #80                 // class org/apache/hadoop/hbase/filter/Filter
      12: invokevirtual #81                 // Method areSerializedFieldsEqual:(Lorg/apache/hadoop/hbase/filter/Filter;)Z
      15: ifeq          22
      18: iconst_1
      19: goto          23
      22: iconst_0
      23: ireturn

  public int hashCode();
    Code:
       0: iconst_4
       1: anewarray     #74                 // class java/lang/Object
       4: dup
       5: iconst_0
       6: aload_0
       7: invokevirtual #68                 // Method getFamily:()[B
      10: invokestatic  #82                 // Method org/apache/hadoop/hbase/util/Bytes.hashCode:([B)I
      13: invokestatic  #83                 // Method java/lang/Integer.valueOf:(I)Ljava/lang/Integer;
      16: aastore
      17: dup
      18: iconst_1
      19: aload_0
      20: invokevirtual #70                 // Method getQualifier:()[B
      23: invokestatic  #82                 // Method org/apache/hadoop/hbase/util/Bytes.hashCode:([B)I
      26: invokestatic  #83                 // Method java/lang/Integer.valueOf:(I)Ljava/lang/Integer;
      29: aastore
      30: dup
      31: iconst_2
      32: aload_0
      33: invokevirtual #20                 // Method getCompareOperator:()Lorg/apache/hadoop/hbase/CompareOperator;
      36: aastore
      37: dup
      38: iconst_3
      39: aload_0
      40: invokevirtual #21                 // Method getComparator:()Lorg/apache/hadoop/hbase/filter/ByteArrayComparable;
      43: aastore
      44: invokestatic  #84                 // Method java/util/Objects.hash:([Ljava/lang/Object;)I
      47: ireturn
}
