Compiled from "CombinedBlockCache.java"
public class org.apache.hadoop.hbase.io.hfile.CombinedBlockCache$CombinedCacheStats extends org.apache.hadoop.hbase.io.hfile.CacheStats {
  org.apache.hadoop.hbase.io.hfile.CombinedBlockCache$CombinedCacheStats(org.apache.hadoop.hbase.io.hfile.CacheStats, org.apache.hadoop.hbase.io.hfile.CacheStats);
    Code:
       0: aload_0
       1: ldc           #1                  // String CombinedBlockCache
       3: invokespecial #2                  // Method org/apache/hadoop/hbase/io/hfile/CacheStats."<init>":(Ljava/lang/String;)V
       6: aload_0
       7: aload_1
       8: putfield      #3                  // Field lruCacheStats:Lorg/apache/hadoop/hbase/io/hfile/CacheStats;
      11: aload_0
      12: aload_2
      13: putfield      #4                  // Field bucketCacheStats:Lorg/apache/hadoop/hbase/io/hfile/CacheStats;
      16: return

  public org.apache.hadoop.hbase.io.hfile.CacheStats getLruCacheStats();
    Code:
       0: aload_0
       1: getfield      #3                  // Field lruCacheStats:Lorg/apache/hadoop/hbase/io/hfile/CacheStats;
       4: areturn

  public org.apache.hadoop.hbase.io.hfile.CacheStats getBucketCacheStats();
    Code:
       0: aload_0
       1: getfield      #4                  // Field bucketCacheStats:Lorg/apache/hadoop/hbase/io/hfile/CacheStats;
       4: areturn

  public long getDataMissCount();
    Code:
       0: aload_0
       1: getfield      #3                  // Field lruCacheStats:Lorg/apache/hadoop/hbase/io/hfile/CacheStats;
       4: invokevirtual #5                  // Method org/apache/hadoop/hbase/io/hfile/CacheStats.getDataMissCount:()J
       7: aload_0
       8: getfield      #4                  // Field bucketCacheStats:Lorg/apache/hadoop/hbase/io/hfile/CacheStats;
      11: invokevirtual #5                  // Method org/apache/hadoop/hbase/io/hfile/CacheStats.getDataMissCount:()J
      14: ladd
      15: lreturn

  public long getLeafIndexMissCount();
    Code:
       0: aload_0
       1: getfield      #3                  // Field lruCacheStats:Lorg/apache/hadoop/hbase/io/hfile/CacheStats;
       4: invokevirtual #6                  // Method org/apache/hadoop/hbase/io/hfile/CacheStats.getLeafIndexMissCount:()J
       7: aload_0
       8: getfield      #4                  // Field bucketCacheStats:Lorg/apache/hadoop/hbase/io/hfile/CacheStats;
      11: invokevirtual #6                  // Method org/apache/hadoop/hbase/io/hfile/CacheStats.getLeafIndexMissCount:()J
      14: ladd
      15: lreturn

  public long getBloomChunkMissCount();
    Code:
       0: aload_0
       1: getfield      #3                  // Field lruCacheStats:Lorg/apache/hadoop/hbase/io/hfile/CacheStats;
       4: invokevirtual #7                  // Method org/apache/hadoop/hbase/io/hfile/CacheStats.getBloomChunkMissCount:()J
       7: aload_0
       8: getfield      #4                  // Field bucketCacheStats:Lorg/apache/hadoop/hbase/io/hfile/CacheStats;
      11: invokevirtual #7                  // Method org/apache/hadoop/hbase/io/hfile/CacheStats.getBloomChunkMissCount:()J
      14: ladd
      15: lreturn

  public long getMetaMissCount();
    Code:
       0: aload_0
       1: getfield      #3                  // Field lruCacheStats:Lorg/apache/hadoop/hbase/io/hfile/CacheStats;
       4: invokevirtual #8                  // Method org/apache/hadoop/hbase/io/hfile/CacheStats.getMetaMissCount:()J
       7: aload_0
       8: getfield      #4                  // Field bucketCacheStats:Lorg/apache/hadoop/hbase/io/hfile/CacheStats;
      11: invokevirtual #8                  // Method org/apache/hadoop/hbase/io/hfile/CacheStats.getMetaMissCount:()J
      14: ladd
      15: lreturn

  public long getRootIndexMissCount();
    Code:
       0: aload_0
       1: getfield      #3                  // Field lruCacheStats:Lorg/apache/hadoop/hbase/io/hfile/CacheStats;
       4: invokevirtual #9                  // Method org/apache/hadoop/hbase/io/hfile/CacheStats.getRootIndexMissCount:()J
       7: aload_0
       8: getfield      #4                  // Field bucketCacheStats:Lorg/apache/hadoop/hbase/io/hfile/CacheStats;
      11: invokevirtual #9                  // Method org/apache/hadoop/hbase/io/hfile/CacheStats.getRootIndexMissCount:()J
      14: ladd
      15: lreturn

  public long getIntermediateIndexMissCount();
    Code:
       0: aload_0
       1: getfield      #3                  // Field lruCacheStats:Lorg/apache/hadoop/hbase/io/hfile/CacheStats;
       4: invokevirtual #10                 // Method org/apache/hadoop/hbase/io/hfile/CacheStats.getIntermediateIndexMissCount:()J
       7: aload_0
       8: getfield      #4                  // Field bucketCacheStats:Lorg/apache/hadoop/hbase/io/hfile/CacheStats;
      11: invokevirtual #10                 // Method org/apache/hadoop/hbase/io/hfile/CacheStats.getIntermediateIndexMissCount:()J
      14: ladd
      15: lreturn

  public long getFileInfoMissCount();
    Code:
       0: aload_0
       1: getfield      #3                  // Field lruCacheStats:Lorg/apache/hadoop/hbase/io/hfile/CacheStats;
       4: invokevirtual #11                 // Method org/apache/hadoop/hbase/io/hfile/CacheStats.getFileInfoMissCount:()J
       7: aload_0
       8: getfield      #4                  // Field bucketCacheStats:Lorg/apache/hadoop/hbase/io/hfile/CacheStats;
      11: invokevirtual #11                 // Method org/apache/hadoop/hbase/io/hfile/CacheStats.getFileInfoMissCount:()J
      14: ladd
      15: lreturn

  public long getGeneralBloomMetaMissCount();
    Code:
       0: aload_0
       1: getfield      #3                  // Field lruCacheStats:Lorg/apache/hadoop/hbase/io/hfile/CacheStats;
       4: invokevirtual #12                 // Method org/apache/hadoop/hbase/io/hfile/CacheStats.getGeneralBloomMetaMissCount:()J
       7: aload_0
       8: getfield      #4                  // Field bucketCacheStats:Lorg/apache/hadoop/hbase/io/hfile/CacheStats;
      11: invokevirtual #12                 // Method org/apache/hadoop/hbase/io/hfile/CacheStats.getGeneralBloomMetaMissCount:()J
      14: ladd
      15: lreturn

  public long getDeleteFamilyBloomMissCount();
    Code:
       0: aload_0
       1: getfield      #3                  // Field lruCacheStats:Lorg/apache/hadoop/hbase/io/hfile/CacheStats;
       4: invokevirtual #13                 // Method org/apache/hadoop/hbase/io/hfile/CacheStats.getDeleteFamilyBloomMissCount:()J
       7: aload_0
       8: getfield      #4                  // Field bucketCacheStats:Lorg/apache/hadoop/hbase/io/hfile/CacheStats;
      11: invokevirtual #13                 // Method org/apache/hadoop/hbase/io/hfile/CacheStats.getDeleteFamilyBloomMissCount:()J
      14: ladd
      15: lreturn

  public long getTrailerMissCount();
    Code:
       0: aload_0
       1: getfield      #3                  // Field lruCacheStats:Lorg/apache/hadoop/hbase/io/hfile/CacheStats;
       4: invokevirtual #14                 // Method org/apache/hadoop/hbase/io/hfile/CacheStats.getTrailerMissCount:()J
       7: aload_0
       8: getfield      #4                  // Field bucketCacheStats:Lorg/apache/hadoop/hbase/io/hfile/CacheStats;
      11: invokevirtual #14                 // Method org/apache/hadoop/hbase/io/hfile/CacheStats.getTrailerMissCount:()J
      14: ladd
      15: lreturn

  public long getDataHitCount();
    Code:
       0: aload_0
       1: getfield      #3                  // Field lruCacheStats:Lorg/apache/hadoop/hbase/io/hfile/CacheStats;
       4: invokevirtual #15                 // Method org/apache/hadoop/hbase/io/hfile/CacheStats.getDataHitCount:()J
       7: aload_0
       8: getfield      #4                  // Field bucketCacheStats:Lorg/apache/hadoop/hbase/io/hfile/CacheStats;
      11: invokevirtual #15                 // Method org/apache/hadoop/hbase/io/hfile/CacheStats.getDataHitCount:()J
      14: ladd
      15: lreturn

  public long getLeafIndexHitCount();
    Code:
       0: aload_0
       1: getfield      #3                  // Field lruCacheStats:Lorg/apache/hadoop/hbase/io/hfile/CacheStats;
       4: invokevirtual #16                 // Method org/apache/hadoop/hbase/io/hfile/CacheStats.getLeafIndexHitCount:()J
       7: aload_0
       8: getfield      #4                  // Field bucketCacheStats:Lorg/apache/hadoop/hbase/io/hfile/CacheStats;
      11: invokevirtual #16                 // Method org/apache/hadoop/hbase/io/hfile/CacheStats.getLeafIndexHitCount:()J
      14: ladd
      15: lreturn

  public long getBloomChunkHitCount();
    Code:
       0: aload_0
       1: getfield      #3                  // Field lruCacheStats:Lorg/apache/hadoop/hbase/io/hfile/CacheStats;
       4: invokevirtual #17                 // Method org/apache/hadoop/hbase/io/hfile/CacheStats.getBloomChunkHitCount:()J
       7: aload_0
       8: getfield      #4                  // Field bucketCacheStats:Lorg/apache/hadoop/hbase/io/hfile/CacheStats;
      11: invokevirtual #17                 // Method org/apache/hadoop/hbase/io/hfile/CacheStats.getBloomChunkHitCount:()J
      14: ladd
      15: lreturn

  public long getMetaHitCount();
    Code:
       0: aload_0
       1: getfield      #3                  // Field lruCacheStats:Lorg/apache/hadoop/hbase/io/hfile/CacheStats;
       4: invokevirtual #18                 // Method org/apache/hadoop/hbase/io/hfile/CacheStats.getMetaHitCount:()J
       7: aload_0
       8: getfield      #4                  // Field bucketCacheStats:Lorg/apache/hadoop/hbase/io/hfile/CacheStats;
      11: invokevirtual #18                 // Method org/apache/hadoop/hbase/io/hfile/CacheStats.getMetaHitCount:()J
      14: ladd
      15: lreturn

  public long getRootIndexHitCount();
    Code:
       0: aload_0
       1: getfield      #3                  // Field lruCacheStats:Lorg/apache/hadoop/hbase/io/hfile/CacheStats;
       4: invokevirtual #19                 // Method org/apache/hadoop/hbase/io/hfile/CacheStats.getRootIndexHitCount:()J
       7: aload_0
       8: getfield      #4                  // Field bucketCacheStats:Lorg/apache/hadoop/hbase/io/hfile/CacheStats;
      11: invokevirtual #19                 // Method org/apache/hadoop/hbase/io/hfile/CacheStats.getRootIndexHitCount:()J
      14: ladd
      15: lreturn

  public long getIntermediateIndexHitCount();
    Code:
       0: aload_0
       1: getfield      #3                  // Field lruCacheStats:Lorg/apache/hadoop/hbase/io/hfile/CacheStats;
       4: invokevirtual #20                 // Method org/apache/hadoop/hbase/io/hfile/CacheStats.getIntermediateIndexHitCount:()J
       7: aload_0
       8: getfield      #4                  // Field bucketCacheStats:Lorg/apache/hadoop/hbase/io/hfile/CacheStats;
      11: invokevirtual #20                 // Method org/apache/hadoop/hbase/io/hfile/CacheStats.getIntermediateIndexHitCount:()J
      14: ladd
      15: lreturn

  public long getFileInfoHitCount();
    Code:
       0: aload_0
       1: getfield      #3                  // Field lruCacheStats:Lorg/apache/hadoop/hbase/io/hfile/CacheStats;
       4: invokevirtual #21                 // Method org/apache/hadoop/hbase/io/hfile/CacheStats.getFileInfoHitCount:()J
       7: aload_0
       8: getfield      #4                  // Field bucketCacheStats:Lorg/apache/hadoop/hbase/io/hfile/CacheStats;
      11: invokevirtual #21                 // Method org/apache/hadoop/hbase/io/hfile/CacheStats.getFileInfoHitCount:()J
      14: ladd
      15: lreturn

  public long getGeneralBloomMetaHitCount();
    Code:
       0: aload_0
       1: getfield      #3                  // Field lruCacheStats:Lorg/apache/hadoop/hbase/io/hfile/CacheStats;
       4: invokevirtual #22                 // Method org/apache/hadoop/hbase/io/hfile/CacheStats.getGeneralBloomMetaHitCount:()J
       7: aload_0
       8: getfield      #4                  // Field bucketCacheStats:Lorg/apache/hadoop/hbase/io/hfile/CacheStats;
      11: invokevirtual #22                 // Method org/apache/hadoop/hbase/io/hfile/CacheStats.getGeneralBloomMetaHitCount:()J
      14: ladd
      15: lreturn

  public long getDeleteFamilyBloomHitCount();
    Code:
       0: aload_0
       1: getfield      #3                  // Field lruCacheStats:Lorg/apache/hadoop/hbase/io/hfile/CacheStats;
       4: invokevirtual #23                 // Method org/apache/hadoop/hbase/io/hfile/CacheStats.getDeleteFamilyBloomHitCount:()J
       7: aload_0
       8: getfield      #4                  // Field bucketCacheStats:Lorg/apache/hadoop/hbase/io/hfile/CacheStats;
      11: invokevirtual #23                 // Method org/apache/hadoop/hbase/io/hfile/CacheStats.getDeleteFamilyBloomHitCount:()J
      14: ladd
      15: lreturn

  public long getTrailerHitCount();
    Code:
       0: aload_0
       1: getfield      #3                  // Field lruCacheStats:Lorg/apache/hadoop/hbase/io/hfile/CacheStats;
       4: invokevirtual #24                 // Method org/apache/hadoop/hbase/io/hfile/CacheStats.getTrailerHitCount:()J
       7: aload_0
       8: getfield      #4                  // Field bucketCacheStats:Lorg/apache/hadoop/hbase/io/hfile/CacheStats;
      11: invokevirtual #24                 // Method org/apache/hadoop/hbase/io/hfile/CacheStats.getTrailerHitCount:()J
      14: ladd
      15: lreturn

  public long getRequestCount();
    Code:
       0: aload_0
       1: getfield      #3                  // Field lruCacheStats:Lorg/apache/hadoop/hbase/io/hfile/CacheStats;
       4: invokevirtual #25                 // Method org/apache/hadoop/hbase/io/hfile/CacheStats.getRequestCount:()J
       7: aload_0
       8: getfield      #4                  // Field bucketCacheStats:Lorg/apache/hadoop/hbase/io/hfile/CacheStats;
      11: invokevirtual #25                 // Method org/apache/hadoop/hbase/io/hfile/CacheStats.getRequestCount:()J
      14: ladd
      15: lreturn

  public long getRequestCachingCount();
    Code:
       0: aload_0
       1: getfield      #3                  // Field lruCacheStats:Lorg/apache/hadoop/hbase/io/hfile/CacheStats;
       4: invokevirtual #26                 // Method org/apache/hadoop/hbase/io/hfile/CacheStats.getRequestCachingCount:()J
       7: aload_0
       8: getfield      #4                  // Field bucketCacheStats:Lorg/apache/hadoop/hbase/io/hfile/CacheStats;
      11: invokevirtual #26                 // Method org/apache/hadoop/hbase/io/hfile/CacheStats.getRequestCachingCount:()J
      14: ladd
      15: lreturn

  public long getMissCount();
    Code:
       0: aload_0
       1: getfield      #3                  // Field lruCacheStats:Lorg/apache/hadoop/hbase/io/hfile/CacheStats;
       4: invokevirtual #27                 // Method org/apache/hadoop/hbase/io/hfile/CacheStats.getMissCount:()J
       7: aload_0
       8: getfield      #4                  // Field bucketCacheStats:Lorg/apache/hadoop/hbase/io/hfile/CacheStats;
      11: invokevirtual #27                 // Method org/apache/hadoop/hbase/io/hfile/CacheStats.getMissCount:()J
      14: ladd
      15: lreturn

  public long getPrimaryMissCount();
    Code:
       0: aload_0
       1: getfield      #3                  // Field lruCacheStats:Lorg/apache/hadoop/hbase/io/hfile/CacheStats;
       4: invokevirtual #28                 // Method org/apache/hadoop/hbase/io/hfile/CacheStats.getPrimaryMissCount:()J
       7: aload_0
       8: getfield      #4                  // Field bucketCacheStats:Lorg/apache/hadoop/hbase/io/hfile/CacheStats;
      11: invokevirtual #28                 // Method org/apache/hadoop/hbase/io/hfile/CacheStats.getPrimaryMissCount:()J
      14: ladd
      15: lreturn

  public long getMissCachingCount();
    Code:
       0: aload_0
       1: getfield      #3                  // Field lruCacheStats:Lorg/apache/hadoop/hbase/io/hfile/CacheStats;
       4: invokevirtual #29                 // Method org/apache/hadoop/hbase/io/hfile/CacheStats.getMissCachingCount:()J
       7: aload_0
       8: getfield      #4                  // Field bucketCacheStats:Lorg/apache/hadoop/hbase/io/hfile/CacheStats;
      11: invokevirtual #29                 // Method org/apache/hadoop/hbase/io/hfile/CacheStats.getMissCachingCount:()J
      14: ladd
      15: lreturn

  public long getHitCount();
    Code:
       0: aload_0
       1: getfield      #3                  // Field lruCacheStats:Lorg/apache/hadoop/hbase/io/hfile/CacheStats;
       4: invokevirtual #30                 // Method org/apache/hadoop/hbase/io/hfile/CacheStats.getHitCount:()J
       7: aload_0
       8: getfield      #4                  // Field bucketCacheStats:Lorg/apache/hadoop/hbase/io/hfile/CacheStats;
      11: invokevirtual #30                 // Method org/apache/hadoop/hbase/io/hfile/CacheStats.getHitCount:()J
      14: ladd
      15: lreturn

  public long getPrimaryHitCount();
    Code:
       0: aload_0
       1: getfield      #3                  // Field lruCacheStats:Lorg/apache/hadoop/hbase/io/hfile/CacheStats;
       4: invokevirtual #31                 // Method org/apache/hadoop/hbase/io/hfile/CacheStats.getPrimaryHitCount:()J
       7: aload_0
       8: getfield      #4                  // Field bucketCacheStats:Lorg/apache/hadoop/hbase/io/hfile/CacheStats;
      11: invokevirtual #31                 // Method org/apache/hadoop/hbase/io/hfile/CacheStats.getPrimaryHitCount:()J
      14: ladd
      15: lreturn

  public long getHitCachingCount();
    Code:
       0: aload_0
       1: getfield      #3                  // Field lruCacheStats:Lorg/apache/hadoop/hbase/io/hfile/CacheStats;
       4: invokevirtual #32                 // Method org/apache/hadoop/hbase/io/hfile/CacheStats.getHitCachingCount:()J
       7: aload_0
       8: getfield      #4                  // Field bucketCacheStats:Lorg/apache/hadoop/hbase/io/hfile/CacheStats;
      11: invokevirtual #32                 // Method org/apache/hadoop/hbase/io/hfile/CacheStats.getHitCachingCount:()J
      14: ladd
      15: lreturn

  public long getEvictionCount();
    Code:
       0: aload_0
       1: getfield      #3                  // Field lruCacheStats:Lorg/apache/hadoop/hbase/io/hfile/CacheStats;
       4: invokevirtual #33                 // Method org/apache/hadoop/hbase/io/hfile/CacheStats.getEvictionCount:()J
       7: aload_0
       8: getfield      #4                  // Field bucketCacheStats:Lorg/apache/hadoop/hbase/io/hfile/CacheStats;
      11: invokevirtual #33                 // Method org/apache/hadoop/hbase/io/hfile/CacheStats.getEvictionCount:()J
      14: ladd
      15: lreturn

  public long getEvictedCount();
    Code:
       0: aload_0
       1: getfield      #3                  // Field lruCacheStats:Lorg/apache/hadoop/hbase/io/hfile/CacheStats;
       4: invokevirtual #34                 // Method org/apache/hadoop/hbase/io/hfile/CacheStats.getEvictedCount:()J
       7: aload_0
       8: getfield      #4                  // Field bucketCacheStats:Lorg/apache/hadoop/hbase/io/hfile/CacheStats;
      11: invokevirtual #34                 // Method org/apache/hadoop/hbase/io/hfile/CacheStats.getEvictedCount:()J
      14: ladd
      15: lreturn

  public long getPrimaryEvictedCount();
    Code:
       0: aload_0
       1: getfield      #3                  // Field lruCacheStats:Lorg/apache/hadoop/hbase/io/hfile/CacheStats;
       4: invokevirtual #35                 // Method org/apache/hadoop/hbase/io/hfile/CacheStats.getPrimaryEvictedCount:()J
       7: aload_0
       8: getfield      #4                  // Field bucketCacheStats:Lorg/apache/hadoop/hbase/io/hfile/CacheStats;
      11: invokevirtual #35                 // Method org/apache/hadoop/hbase/io/hfile/CacheStats.getPrimaryEvictedCount:()J
      14: ladd
      15: lreturn

  public void rollMetricsPeriod();
    Code:
       0: aload_0
       1: getfield      #3                  // Field lruCacheStats:Lorg/apache/hadoop/hbase/io/hfile/CacheStats;
       4: invokevirtual #36                 // Method org/apache/hadoop/hbase/io/hfile/CacheStats.rollMetricsPeriod:()V
       7: aload_0
       8: getfield      #4                  // Field bucketCacheStats:Lorg/apache/hadoop/hbase/io/hfile/CacheStats;
      11: invokevirtual #36                 // Method org/apache/hadoop/hbase/io/hfile/CacheStats.rollMetricsPeriod:()V
      14: return

  public long getFailedInserts();
    Code:
       0: aload_0
       1: getfield      #3                  // Field lruCacheStats:Lorg/apache/hadoop/hbase/io/hfile/CacheStats;
       4: invokevirtual #37                 // Method org/apache/hadoop/hbase/io/hfile/CacheStats.getFailedInserts:()J
       7: aload_0
       8: getfield      #4                  // Field bucketCacheStats:Lorg/apache/hadoop/hbase/io/hfile/CacheStats;
      11: invokevirtual #37                 // Method org/apache/hadoop/hbase/io/hfile/CacheStats.getFailedInserts:()J
      14: ladd
      15: lreturn

  public long getSumHitCountsPastNPeriods();
    Code:
       0: aload_0
       1: getfield      #3                  // Field lruCacheStats:Lorg/apache/hadoop/hbase/io/hfile/CacheStats;
       4: invokevirtual #38                 // Method org/apache/hadoop/hbase/io/hfile/CacheStats.getSumHitCountsPastNPeriods:()J
       7: aload_0
       8: getfield      #4                  // Field bucketCacheStats:Lorg/apache/hadoop/hbase/io/hfile/CacheStats;
      11: invokevirtual #38                 // Method org/apache/hadoop/hbase/io/hfile/CacheStats.getSumHitCountsPastNPeriods:()J
      14: ladd
      15: lreturn

  public long getSumRequestCountsPastNPeriods();
    Code:
       0: aload_0
       1: getfield      #3                  // Field lruCacheStats:Lorg/apache/hadoop/hbase/io/hfile/CacheStats;
       4: invokevirtual #39                 // Method org/apache/hadoop/hbase/io/hfile/CacheStats.getSumRequestCountsPastNPeriods:()J
       7: aload_0
       8: getfield      #4                  // Field bucketCacheStats:Lorg/apache/hadoop/hbase/io/hfile/CacheStats;
      11: invokevirtual #39                 // Method org/apache/hadoop/hbase/io/hfile/CacheStats.getSumRequestCountsPastNPeriods:()J
      14: ladd
      15: lreturn

  public long getSumHitCachingCountsPastNPeriods();
    Code:
       0: aload_0
       1: getfield      #3                  // Field lruCacheStats:Lorg/apache/hadoop/hbase/io/hfile/CacheStats;
       4: invokevirtual #40                 // Method org/apache/hadoop/hbase/io/hfile/CacheStats.getSumHitCachingCountsPastNPeriods:()J
       7: aload_0
       8: getfield      #4                  // Field bucketCacheStats:Lorg/apache/hadoop/hbase/io/hfile/CacheStats;
      11: invokevirtual #40                 // Method org/apache/hadoop/hbase/io/hfile/CacheStats.getSumHitCachingCountsPastNPeriods:()J
      14: ladd
      15: lreturn

  public long getSumRequestCachingCountsPastNPeriods();
    Code:
       0: aload_0
       1: getfield      #3                  // Field lruCacheStats:Lorg/apache/hadoop/hbase/io/hfile/CacheStats;
       4: invokevirtual #41                 // Method org/apache/hadoop/hbase/io/hfile/CacheStats.getSumRequestCachingCountsPastNPeriods:()J
       7: aload_0
       8: getfield      #4                  // Field bucketCacheStats:Lorg/apache/hadoop/hbase/io/hfile/CacheStats;
      11: invokevirtual #41                 // Method org/apache/hadoop/hbase/io/hfile/CacheStats.getSumRequestCachingCountsPastNPeriods:()J
      14: ladd
      15: lreturn
}
