Compiled from "CompleteScanResultCache.java"
class org.apache.hadoop.hbase.client.CompleteScanResultCache implements org.apache.hadoop.hbase.client.ScanResultCache {
  org.apache.hadoop.hbase.client.CompleteScanResultCache();
    Code:
       0: aload_0
       1: invokespecial #1                  // Method java/lang/Object."<init>":()V
       4: aload_0
       5: new           #2                  // class java/util/ArrayList
       8: dup
       9: invokespecial #3                  // Method java/util/ArrayList."<init>":()V
      12: putfield      #4                  // Field partialResults:Ljava/util/List;
      15: return

  public org.apache.hadoop.hbase.client.Result[] addAndGet(org.apache.hadoop.hbase.client.Result[], boolean) throws java.io.IOException;
    Code:
       0: aload_1
       1: arraylength
       2: ifne          41
       5: aload_0
       6: getfield      #4                  // Field partialResults:Ljava/util/List;
       9: invokeinterface #15,  1           // InterfaceMethod java/util/List.isEmpty:()Z
      14: ifne          37
      17: iload_2
      18: ifne          37
      21: aload_0
      22: iconst_1
      23: anewarray     #7                  // class org/apache/hadoop/hbase/client/Result
      26: dup
      27: iconst_0
      28: aload_0
      29: invokespecial #8                  // Method combine:()Lorg/apache/hadoop/hbase/client/Result;
      32: aastore
      33: invokespecial #16                 // Method updateNumberOfCompleteResultsAndReturn:([Lorg/apache/hadoop/hbase/client/Result;)[Lorg/apache/hadoop/hbase/client/Result;
      36: areturn
      37: getstatic     #17                 // Field EMPTY_RESULT_ARRAY:[Lorg/apache/hadoop/hbase/client/Result;
      40: areturn
      41: aload_1
      42: aload_1
      43: arraylength
      44: iconst_1
      45: isub
      46: aaload
      47: astore_3
      48: aload_3
      49: invokevirtual #18                 // Method org/apache/hadoop/hbase/client/Result.mayHaveMoreCellsInRow:()Z
      52: ifeq          201
      55: aload_0
      56: getfield      #4                  // Field partialResults:Ljava/util/List;
      59: invokeinterface #15,  1           // InterfaceMethod java/util/List.isEmpty:()Z
      64: ifeq          94
      67: aload_0
      68: getfield      #4                  // Field partialResults:Ljava/util/List;
      71: aload_3
      72: invokeinterface #12,  2           // InterfaceMethod java/util/List.add:(Ljava/lang/Object;)Z
      77: pop
      78: aload_0
      79: aload_1
      80: aload_1
      81: arraylength
      82: iconst_1
      83: isub
      84: invokestatic  #19                 // Method java/util/Arrays.copyOf:([Ljava/lang/Object;I)[Ljava/lang/Object;
      87: checkcast     #20                 // class "[Lorg/apache/hadoop/hbase/client/Result;"
      90: invokespecial #16                 // Method updateNumberOfCompleteResultsAndReturn:([Lorg/apache/hadoop/hbase/client/Result;)[Lorg/apache/hadoop/hbase/client/Result;
      93: areturn
      94: aload_1
      95: arraylength
      96: iconst_1
      97: if_icmpne     172
     100: aload_0
     101: getfield      #4                  // Field partialResults:Ljava/util/List;
     104: iconst_0
     105: invokeinterface #9,  2            // InterfaceMethod java/util/List.get:(I)Ljava/lang/Object;
     110: checkcast     #7                  // class org/apache/hadoop/hbase/client/Result
     113: invokevirtual #10                 // Method org/apache/hadoop/hbase/client/Result.getRow:()[B
     116: aload_3
     117: invokevirtual #10                 // Method org/apache/hadoop/hbase/client/Result.getRow:()[B
     120: invokestatic  #11                 // Method org/apache/hadoop/hbase/util/Bytes.equals:([B[B)Z
     123: ifeq          141
     126: aload_0
     127: getfield      #4                  // Field partialResults:Ljava/util/List;
     130: aload_3
     131: invokeinterface #12,  2           // InterfaceMethod java/util/List.add:(Ljava/lang/Object;)Z
     136: pop
     137: getstatic     #17                 // Field EMPTY_RESULT_ARRAY:[Lorg/apache/hadoop/hbase/client/Result;
     140: areturn
     141: aload_0
     142: invokespecial #8                  // Method combine:()Lorg/apache/hadoop/hbase/client/Result;
     145: astore        4
     147: aload_0
     148: getfield      #4                  // Field partialResults:Ljava/util/List;
     151: aload_3
     152: invokeinterface #12,  2           // InterfaceMethod java/util/List.add:(Ljava/lang/Object;)Z
     157: pop
     158: aload_0
     159: iconst_1
     160: anewarray     #7                  // class org/apache/hadoop/hbase/client/Result
     163: dup
     164: iconst_0
     165: aload         4
     167: aastore
     168: invokespecial #16                 // Method updateNumberOfCompleteResultsAndReturn:([Lorg/apache/hadoop/hbase/client/Result;)[Lorg/apache/hadoop/hbase/client/Result;
     171: areturn
     172: aload_0
     173: aload_1
     174: aload_1
     175: arraylength
     176: iconst_1
     177: isub
     178: invokespecial #21                 // Method prependCombined:([Lorg/apache/hadoop/hbase/client/Result;I)[Lorg/apache/hadoop/hbase/client/Result;
     181: astore        4
     183: aload_0
     184: getfield      #4                  // Field partialResults:Ljava/util/List;
     187: aload_3
     188: invokeinterface #12,  2           // InterfaceMethod java/util/List.add:(Ljava/lang/Object;)Z
     193: pop
     194: aload_0
     195: aload         4
     197: invokespecial #16                 // Method updateNumberOfCompleteResultsAndReturn:([Lorg/apache/hadoop/hbase/client/Result;)[Lorg/apache/hadoop/hbase/client/Result;
     200: areturn
     201: aload_0
     202: getfield      #4                  // Field partialResults:Ljava/util/List;
     205: invokeinterface #15,  1           // InterfaceMethod java/util/List.isEmpty:()Z
     210: ifne          225
     213: aload_0
     214: aload_0
     215: aload_1
     216: aload_1
     217: arraylength
     218: invokespecial #21                 // Method prependCombined:([Lorg/apache/hadoop/hbase/client/Result;I)[Lorg/apache/hadoop/hbase/client/Result;
     221: invokespecial #16                 // Method updateNumberOfCompleteResultsAndReturn:([Lorg/apache/hadoop/hbase/client/Result;)[Lorg/apache/hadoop/hbase/client/Result;
     224: areturn
     225: aload_0
     226: aload_1
     227: invokespecial #16                 // Method updateNumberOfCompleteResultsAndReturn:([Lorg/apache/hadoop/hbase/client/Result;)[Lorg/apache/hadoop/hbase/client/Result;
     230: areturn

  public void clear();
    Code:
       0: aload_0
       1: getfield      #4                  // Field partialResults:Ljava/util/List;
       4: invokeinterface #6,  1            // InterfaceMethod java/util/List.clear:()V
       9: return

  public int numberOfCompleteRows();
    Code:
       0: aload_0
       1: getfield      #14                 // Field numberOfCompleteRows:I
       4: ireturn
}
