Compiled from "CompoundBloomFilterBase.java"
public class org.apache.hadoop.hbase.io.hfile.CompoundBloomFilterBase implements org.apache.hadoop.hbase.util.BloomFilterBase {
  protected int numChunks;

  public static final int VERSION;

  protected float errorRate;

  protected long totalKeyCount;

  protected long totalByteSize;

  protected long totalMaxKeys;

  protected int hashType;

  protected org.apache.hadoop.hbase.CellComparator comparator;

  public org.apache.hadoop.hbase.io.hfile.CompoundBloomFilterBase();
    Code:
       0: aload_0
       1: invokespecial #1                  // Method java/lang/Object."<init>":()V
       4: return

  public long getMaxKeys();
    Code:
       0: aload_0
       1: getfield      #2                  // Field totalMaxKeys:J
       4: lreturn

  public long getKeyCount();
    Code:
       0: aload_0
       1: getfield      #3                  // Field totalKeyCount:J
       4: lreturn

  public long getByteSize();
    Code:
       0: aload_0
       1: getfield      #4                  // Field totalByteSize:J
       4: lreturn
}
