Compiled from "CompactSplit.java"
class org.apache.hadoop.hbase.regionserver.CompactSplit$Rejection implements java.util.concurrent.RejectedExecutionHandler {
  public void rejectedExecution(java.lang.Runnable, java.util.concurrent.ThreadPoolExecutor);
    Code:
       0: aload_1
       1: instanceof    #3                  // class org/apache/hadoop/hbase/regionserver/CompactSplit$CompactionRunner
       4: ifeq          57
       7: aload_1
       8: checkcast     #3                  // class org/apache/hadoop/hbase/regionserver/CompactSplit$CompactionRunner
      11: astore_3
      12: invokestatic  #4                  // Method org/apache/hadoop/hbase/regionserver/CompactSplit.access$400:()Lorg/slf4j/Logger;
      15: new           #5                  // class java/lang/StringBuilder
      18: dup
      19: invokespecial #6                  // Method java/lang/StringBuilder."<init>":()V
      22: ldc           #7                  // String Compaction Rejected:
      24: invokevirtual #8                  // Method java/lang/StringBuilder.append:(Ljava/lang/String;)Ljava/lang/StringBuilder;
      27: aload_3
      28: invokevirtual #9                  // Method java/lang/StringBuilder.append:(Ljava/lang/Object;)Ljava/lang/StringBuilder;
      31: invokevirtual #10                 // Method java/lang/StringBuilder.toString:()Ljava/lang/String;
      34: invokeinterface #11,  2           // InterfaceMethod org/slf4j/Logger.debug:(Ljava/lang/String;)V
      39: aload_3
      40: invokestatic  #12                 // Method org/apache/hadoop/hbase/regionserver/CompactSplit$CompactionRunner.access$200:(Lorg/apache/hadoop/hbase/regionserver/CompactSplit$CompactionRunner;)Lorg/apache/hadoop/hbase/regionserver/compactions/CompactionContext;
      43: ifnull        57
      46: aload_3
      47: invokestatic  #13                 // Method org/apache/hadoop/hbase/regionserver/CompactSplit$CompactionRunner.access$900:(Lorg/apache/hadoop/hbase/regionserver/CompactSplit$CompactionRunner;)Lorg/apache/hadoop/hbase/regionserver/HStore;
      50: aload_3
      51: invokestatic  #12                 // Method org/apache/hadoop/hbase/regionserver/CompactSplit$CompactionRunner.access$200:(Lorg/apache/hadoop/hbase/regionserver/CompactSplit$CompactionRunner;)Lorg/apache/hadoop/hbase/regionserver/compactions/CompactionContext;
      54: invokevirtual #14                 // Method org/apache/hadoop/hbase/regionserver/HStore.cancelRequestedCompaction:(Lorg/apache/hadoop/hbase/regionserver/compactions/CompactionContext;)V
      57: return

  org.apache.hadoop.hbase.regionserver.CompactSplit$Rejection(org.apache.hadoop.hbase.regionserver.CompactSplit$1);
    Code:
       0: aload_0
       1: invokespecial #1                  // Method "<init>":()V
       4: return
}
