Compiled from "CompactSplit.java"
final class org.apache.hadoop.hbase.regionserver.CompactSplit$CompactionRunner implements java.lang.Runnable {
  static final boolean $assertionsDisabled;

  final org.apache.hadoop.hbase.regionserver.CompactSplit this$0;

  public org.apache.hadoop.hbase.regionserver.CompactSplit$CompactionRunner(org.apache.hadoop.hbase.regionserver.CompactSplit, org.apache.hadoop.hbase.regionserver.HStore, org.apache.hadoop.hbase.regionserver.HRegion, org.apache.hadoop.hbase.regionserver.compactions.CompactionContext, org.apache.hadoop.hbase.regionserver.compactions.CompactionLifeCycleTracker, org.apache.hadoop.hbase.regionserver.CompactSplit$CompactionCompleteTracker, java.util.concurrent.ThreadPoolExecutor, org.apache.hadoop.hbase.security.User);
    Code:
       0: aload_0
       1: aload_1
       2: putfield      #4                  // Field this$0:Lorg/apache/hadoop/hbase/regionserver/CompactSplit;
       5: aload_0
       6: invokespecial #5                  // Method java/lang/Object."<init>":()V
       9: aload_0
      10: aload_2
      11: putfield      #1                  // Field store:Lorg/apache/hadoop/hbase/regionserver/HStore;
      14: aload_0
      15: aload_3
      16: putfield      #6                  // Field region:Lorg/apache/hadoop/hbase/regionserver/HRegion;
      19: aload_0
      20: aload         4
      22: putfield      #2                  // Field compaction:Lorg/apache/hadoop/hbase/regionserver/compactions/CompactionContext;
      25: aload_0
      26: aload         5
      28: putfield      #7                  // Field tracker:Lorg/apache/hadoop/hbase/regionserver/compactions/CompactionLifeCycleTracker;
      31: aload_0
      32: aload         6
      34: putfield      #8                  // Field completeTracker:Lorg/apache/hadoop/hbase/regionserver/CompactSplit$CompactionCompleteTracker;
      37: aload_0
      38: aload         4
      40: ifnull        54
      43: aload         4
      45: invokevirtual #9                  // Method org/apache/hadoop/hbase/regionserver/compactions/CompactionContext.getRequest:()Lorg/apache/hadoop/hbase/regionserver/compactions/CompactionRequestImpl;
      48: invokevirtual #10                 // Method org/apache/hadoop/hbase/regionserver/compactions/CompactionRequestImpl.getPriority:()I
      51: goto          58
      54: aload_2
      55: invokevirtual #11                 // Method org/apache/hadoop/hbase/regionserver/HStore.getCompactPriority:()I
      58: putfield      #3                  // Field queuedPriority:I
      61: aload_0
      62: aload         7
      64: putfield      #12                 // Field parent:Ljava/util/concurrent/ThreadPoolExecutor;
      67: aload_0
      68: aload         8
      70: putfield      #13                 // Field user:Lorg/apache/hadoop/hbase/security/User;
      73: aload_0
      74: invokestatic  #14                 // Method org/apache/hadoop/hbase/util/EnvironmentEdgeManager.currentTime:()J
      77: putfield      #15                 // Field time:J
      80: return

  public java.lang.String toString();
    Code:
       0: aload_0
       1: getfield      #2                  // Field compaction:Lorg/apache/hadoop/hbase/regionserver/compactions/CompactionContext;
       4: ifnull        33
       7: new           #16                 // class java/lang/StringBuilder
      10: dup
      11: invokespecial #17                 // Method java/lang/StringBuilder."<init>":()V
      14: ldc           #18                 // String Request=
      16: invokevirtual #19                 // Method java/lang/StringBuilder.append:(Ljava/lang/String;)Ljava/lang/StringBuilder;
      19: aload_0
      20: getfield      #2                  // Field compaction:Lorg/apache/hadoop/hbase/regionserver/compactions/CompactionContext;
      23: invokevirtual #9                  // Method org/apache/hadoop/hbase/regionserver/compactions/CompactionContext.getRequest:()Lorg/apache/hadoop/hbase/regionserver/compactions/CompactionRequestImpl;
      26: invokevirtual #20                 // Method java/lang/StringBuilder.append:(Ljava/lang/Object;)Ljava/lang/StringBuilder;
      29: invokevirtual #21                 // Method java/lang/StringBuilder.toString:()Ljava/lang/String;
      32: areturn
      33: new           #16                 // class java/lang/StringBuilder
      36: dup
      37: invokespecial #17                 // Method java/lang/StringBuilder."<init>":()V
      40: ldc           #22                 // String region=
      42: invokevirtual #19                 // Method java/lang/StringBuilder.append:(Ljava/lang/String;)Ljava/lang/StringBuilder;
      45: aload_0
      46: getfield      #6                  // Field region:Lorg/apache/hadoop/hbase/regionserver/HRegion;
      49: invokevirtual #23                 // Method org/apache/hadoop/hbase/regionserver/HRegion.toString:()Ljava/lang/String;
      52: invokevirtual #19                 // Method java/lang/StringBuilder.append:(Ljava/lang/String;)Ljava/lang/StringBuilder;
      55: ldc           #24                 // String , storeName=
      57: invokevirtual #19                 // Method java/lang/StringBuilder.append:(Ljava/lang/String;)Ljava/lang/StringBuilder;
      60: aload_0
      61: getfield      #1                  // Field store:Lorg/apache/hadoop/hbase/regionserver/HStore;
      64: invokevirtual #25                 // Method org/apache/hadoop/hbase/regionserver/HStore.toString:()Ljava/lang/String;
      67: invokevirtual #19                 // Method java/lang/StringBuilder.append:(Ljava/lang/String;)Ljava/lang/StringBuilder;
      70: ldc           #26                 // String , priority=
      72: invokevirtual #19                 // Method java/lang/StringBuilder.append:(Ljava/lang/String;)Ljava/lang/StringBuilder;
      75: aload_0
      76: getfield      #3                  // Field queuedPriority:I
      79: invokevirtual #27                 // Method java/lang/StringBuilder.append:(I)Ljava/lang/StringBuilder;
      82: ldc           #28                 // String , startTime=
      84: invokevirtual #19                 // Method java/lang/StringBuilder.append:(Ljava/lang/String;)Ljava/lang/StringBuilder;
      87: aload_0
      88: getfield      #15                 // Field time:J
      91: invokevirtual #29                 // Method java/lang/StringBuilder.append:(J)Ljava/lang/StringBuilder;
      94: invokevirtual #21                 // Method java/lang/StringBuilder.toString:()Ljava/lang/String;
      97: areturn

  public void run();
    Code:
       0: aload_0
       1: getfield      #4                  // Field this$0:Lorg/apache/hadoop/hbase/regionserver/CompactSplit;
       4: invokestatic  #36                 // Method org/apache/hadoop/hbase/regionserver/CompactSplit.access$500:(Lorg/apache/hadoop/hbase/regionserver/CompactSplit;)Lorg/apache/hadoop/hbase/regionserver/HRegionServer;
       7: invokestatic  #74                 // Method org/apache/hbase/thirdparty/com/google/common/base/Preconditions.checkNotNull:(Ljava/lang/Object;)Ljava/lang/Object;
      10: pop
      11: aload_0
      12: getfield      #4                  // Field this$0:Lorg/apache/hadoop/hbase/regionserver/CompactSplit;
      15: invokestatic  #36                 // Method org/apache/hadoop/hbase/regionserver/CompactSplit.access$500:(Lorg/apache/hadoop/hbase/regionserver/CompactSplit;)Lorg/apache/hadoop/hbase/regionserver/HRegionServer;
      18: invokevirtual #75                 // Method org/apache/hadoop/hbase/regionserver/HRegionServer.isStopped:()Z
      21: ifne          49
      24: aload_0
      25: getfield      #6                  // Field region:Lorg/apache/hadoop/hbase/regionserver/HRegion;
      28: invokevirtual #76                 // Method org/apache/hadoop/hbase/regionserver/HRegion.getTableDescriptor:()Lorg/apache/hadoop/hbase/client/TableDescriptor;
      31: ifnull        57
      34: aload_0
      35: getfield      #6                  // Field region:Lorg/apache/hadoop/hbase/regionserver/HRegion;
      38: invokevirtual #76                 // Method org/apache/hadoop/hbase/regionserver/HRegion.getTableDescriptor:()Lorg/apache/hadoop/hbase/client/TableDescriptor;
      41: invokeinterface #77,  1           // InterfaceMethod org/apache/hadoop/hbase/client/TableDescriptor.isCompactionEnabled:()Z
      46: ifne          57
      49: aload_0
      50: getfield      #6                  // Field region:Lorg/apache/hadoop/hbase/regionserver/HRegion;
      53: invokevirtual #38                 // Method org/apache/hadoop/hbase/regionserver/HRegion.decrementCompactionsQueuedCount:()V
      56: return
      57: aload_0
      58: aload_0
      59: getfield      #13                 // Field user:Lorg/apache/hadoop/hbase/security/User;
      62: invokespecial #78                 // Method doCompaction:(Lorg/apache/hadoop/hbase/security/User;)V
      65: return

  static int access$100(org.apache.hadoop.hbase.regionserver.CompactSplit$CompactionRunner);
    Code:
       0: aload_0
       1: getfield      #3                  // Field queuedPriority:I
       4: ireturn

  static org.apache.hadoop.hbase.regionserver.compactions.CompactionContext access$200(org.apache.hadoop.hbase.regionserver.CompactSplit$CompactionRunner);
    Code:
       0: aload_0
       1: getfield      #2                  // Field compaction:Lorg/apache/hadoop/hbase/regionserver/compactions/CompactionContext;
       4: areturn

  static org.apache.hadoop.hbase.regionserver.HStore access$900(org.apache.hadoop.hbase.regionserver.CompactSplit$CompactionRunner);
    Code:
       0: aload_0
       1: getfield      #1                  // Field store:Lorg/apache/hadoop/hbase/regionserver/HStore;
       4: areturn

  static {};
    Code:
       0: ldc           #86                 // class org/apache/hadoop/hbase/regionserver/CompactSplit
       2: invokevirtual #87                 // Method java/lang/Class.desiredAssertionStatus:()Z
       5: ifne          12
       8: iconst_1
       9: goto          13
      12: iconst_0
      13: putstatic     #42                 // Field $assertionsDisabled:Z
      16: return
}
