Compiled from "CompactionState.java"
public final class org.apache.hadoop.hbase.client.CompactionState extends java.lang.Enum<org.apache.hadoop.hbase.client.CompactionState> {
  public static final org.apache.hadoop.hbase.client.CompactionState NONE;

  public static final org.apache.hadoop.hbase.client.CompactionState MINOR;

  public static final org.apache.hadoop.hbase.client.CompactionState MAJOR;

  public static final org.apache.hadoop.hbase.client.CompactionState MAJOR_AND_MINOR;

  public static org.apache.hadoop.hbase.client.CompactionState[] values();
    Code:
       0: getstatic     #1                  // Field $VALUES:[Lorg/apache/hadoop/hbase/client/CompactionState;
       3: invokevirtual #2                  // Method "[Lorg/apache/hadoop/hbase/client/CompactionState;".clone:()Ljava/lang/Object;
       6: checkcast     #3                  // class "[Lorg/apache/hadoop/hbase/client/CompactionState;"
       9: areturn

  public static org.apache.hadoop.hbase.client.CompactionState valueOf(java.lang.String);
    Code:
       0: ldc           #4                  // class org/apache/hadoop/hbase/client/CompactionState
       2: aload_0
       3: invokestatic  #5                  // Method java/lang/Enum.valueOf:(Ljava/lang/Class;Ljava/lang/String;)Ljava/lang/Enum;
       6: checkcast     #4                  // class org/apache/hadoop/hbase/client/CompactionState
       9: areturn

  static {};
    Code:
       0: new           #4                  // class org/apache/hadoop/hbase/client/CompactionState
       3: dup
       4: ldc           #7                  // String NONE
       6: iconst_0
       7: invokespecial #8                  // Method "<init>":(Ljava/lang/String;I)V
      10: putstatic     #9                  // Field NONE:Lorg/apache/hadoop/hbase/client/CompactionState;
      13: new           #4                  // class org/apache/hadoop/hbase/client/CompactionState
      16: dup
      17: ldc           #10                 // String MINOR
      19: iconst_1
      20: invokespecial #8                  // Method "<init>":(Ljava/lang/String;I)V
      23: putstatic     #11                 // Field MINOR:Lorg/apache/hadoop/hbase/client/CompactionState;
      26: new           #4                  // class org/apache/hadoop/hbase/client/CompactionState
      29: dup
      30: ldc           #12                 // String MAJOR
      32: iconst_2
      33: invokespecial #8                  // Method "<init>":(Ljava/lang/String;I)V
      36: putstatic     #13                 // Field MAJOR:Lorg/apache/hadoop/hbase/client/CompactionState;
      39: new           #4                  // class org/apache/hadoop/hbase/client/CompactionState
      42: dup
      43: ldc           #14                 // String MAJOR_AND_MINOR
      45: iconst_3
      46: invokespecial #8                  // Method "<init>":(Ljava/lang/String;I)V
      49: putstatic     #15                 // Field MAJOR_AND_MINOR:Lorg/apache/hadoop/hbase/client/CompactionState;
      52: iconst_4
      53: anewarray     #4                  // class org/apache/hadoop/hbase/client/CompactionState
      56: dup
      57: iconst_0
      58: getstatic     #9                  // Field NONE:Lorg/apache/hadoop/hbase/client/CompactionState;
      61: aastore
      62: dup
      63: iconst_1
      64: getstatic     #11                 // Field MINOR:Lorg/apache/hadoop/hbase/client/CompactionState;
      67: aastore
      68: dup
      69: iconst_2
      70: getstatic     #13                 // Field MAJOR:Lorg/apache/hadoop/hbase/client/CompactionState;
      73: aastore
      74: dup
      75: iconst_3
      76: getstatic     #15                 // Field MAJOR_AND_MINOR:Lorg/apache/hadoop/hbase/client/CompactionState;
      79: aastore
      80: putstatic     #1                  // Field $VALUES:[Lorg/apache/hadoop/hbase/client/CompactionState;
      83: return
}
