Compiled from "CompoundConfiguration.java"
class org.apache.hadoop.hbase.CompoundConfiguration$ImmutableConfWrapper implements org.apache.hadoop.hbase.CompoundConfiguration$ImmutableConfigMap {
  org.apache.hadoop.hbase.CompoundConfiguration$ImmutableConfWrapper(org.apache.hadoop.conf.Configuration);
    Code:
       0: aload_0
       1: invokespecial #1                  // Method java/lang/Object."<init>":()V
       4: aload_0
       5: aload_1
       6: putfield      #2                  // Field c:Lorg/apache/hadoop/conf/Configuration;
       9: return

  public java.util.Iterator<java.util.Map$Entry<java.lang.String, java.lang.String>> iterator();
    Code:
       0: aload_0
       1: getfield      #2                  // Field c:Lorg/apache/hadoop/conf/Configuration;
       4: invokevirtual #3                  // Method org/apache/hadoop/conf/Configuration.iterator:()Ljava/util/Iterator;
       7: areturn

  public java.lang.String get(java.lang.String);
    Code:
       0: aload_0
       1: getfield      #2                  // Field c:Lorg/apache/hadoop/conf/Configuration;
       4: aload_1
       5: invokevirtual #4                  // Method org/apache/hadoop/conf/Configuration.get:(Ljava/lang/String;)Ljava/lang/String;
       8: areturn

  public java.lang.String getRaw(java.lang.String);
    Code:
       0: aload_0
       1: getfield      #2                  // Field c:Lorg/apache/hadoop/conf/Configuration;
       4: aload_1
       5: invokevirtual #5                  // Method org/apache/hadoop/conf/Configuration.getRaw:(Ljava/lang/String;)Ljava/lang/String;
       8: areturn

  public java.lang.Class<?> getClassByName(java.lang.String) throws java.lang.ClassNotFoundException;
    Code:
       0: aload_0
       1: getfield      #2                  // Field c:Lorg/apache/hadoop/conf/Configuration;
       4: aload_1
       5: invokevirtual #6                  // Method org/apache/hadoop/conf/Configuration.getClassByName:(Ljava/lang/String;)Ljava/lang/Class;
       8: areturn

  public int size();
    Code:
       0: aload_0
       1: getfield      #2                  // Field c:Lorg/apache/hadoop/conf/Configuration;
       4: invokevirtual #7                  // Method org/apache/hadoop/conf/Configuration.size:()I
       7: ireturn

  public java.lang.String toString();
    Code:
       0: aload_0
       1: getfield      #2                  // Field c:Lorg/apache/hadoop/conf/Configuration;
       4: invokevirtual #8                  // Method org/apache/hadoop/conf/Configuration.toString:()Ljava/lang/String;
       7: areturn
}
