Compiled from "CompoundBloomFilter.java"
public class org.apache.hadoop.hbase.io.hfile.CompoundBloomFilter extends org.apache.hadoop.hbase.io.hfile.CompoundBloomFilterBase implements org.apache.hadoop.hbase.util.BloomFilter {
  public org.apache.hadoop.hbase.io.hfile.CompoundBloomFilter(java.io.DataInput, org.apache.hadoop.hbase.io.hfile.HFile$Reader) throws java.io.IOException;
    Code:
       0: aload_0
       1: invokespecial #1                  // Method org/apache/hadoop/hbase/io/hfile/CompoundBloomFilterBase."<init>":()V
       4: aload_0
       5: aload_2
       6: putfield      #2                  // Field reader:Lorg/apache/hadoop/hbase/io/hfile/HFile$Reader;
       9: aload_0
      10: aload_1
      11: invokeinterface #3,  1            // InterfaceMethod java/io/DataInput.readLong:()J
      16: putfield      #4                  // Field totalByteSize:J
      19: aload_0
      20: aload_1
      21: invokeinterface #5,  1            // InterfaceMethod java/io/DataInput.readInt:()I
      26: putfield      #6                  // Field hashCount:I
      29: aload_0
      30: aload_1
      31: invokeinterface #5,  1            // InterfaceMethod java/io/DataInput.readInt:()I
      36: putfield      #7                  // Field hashType:I
      39: aload_0
      40: aload_1
      41: invokeinterface #3,  1            // InterfaceMethod java/io/DataInput.readLong:()J
      46: putfield      #8                  // Field totalKeyCount:J
      49: aload_0
      50: aload_1
      51: invokeinterface #3,  1            // InterfaceMethod java/io/DataInput.readLong:()J
      56: putfield      #9                  // Field totalMaxKeys:J
      59: aload_0
      60: aload_1
      61: invokeinterface #5,  1            // InterfaceMethod java/io/DataInput.readInt:()I
      66: putfield      #10                 // Field numChunks:I
      69: aload_1
      70: invokestatic  #11                 // Method org/apache/hadoop/hbase/util/Bytes.readByteArray:(Ljava/io/DataInput;)[B
      73: astore_3
      74: aload_3
      75: arraylength
      76: ifeq          90
      79: aload_0
      80: aload_3
      81: invokestatic  #12                 // Method org/apache/hadoop/hbase/util/Bytes.toString:([B)Ljava/lang/String;
      84: invokestatic  #13                 // Method org/apache/hadoop/hbase/io/hfile/FixedFileTrailer.createComparator:(Ljava/lang/String;)Lorg/apache/hadoop/hbase/CellComparator;
      87: putfield      #14                 // Field comparator:Lorg/apache/hadoop/hbase/CellComparator;
      90: aload_0
      91: aload_0
      92: getfield      #7                  // Field hashType:I
      95: invokestatic  #15                 // Method org/apache/hadoop/hbase/util/Hash.getInstance:(I)Lorg/apache/hadoop/hbase/util/Hash;
      98: putfield      #16                 // Field hash:Lorg/apache/hadoop/hbase/util/Hash;
     101: aload_0
     102: getfield      #16                 // Field hash:Lorg/apache/hadoop/hbase/util/Hash;
     105: ifnonnull     138
     108: new           #17                 // class java/lang/IllegalArgumentException
     111: dup
     112: new           #18                 // class java/lang/StringBuilder
     115: dup
     116: invokespecial #19                 // Method java/lang/StringBuilder."<init>":()V
     119: ldc           #20                 // String Invalid hash type:
     121: invokevirtual #21                 // Method java/lang/StringBuilder.append:(Ljava/lang/String;)Ljava/lang/StringBuilder;
     124: aload_0
     125: getfield      #7                  // Field hashType:I
     128: invokevirtual #22                 // Method java/lang/StringBuilder.append:(I)Ljava/lang/StringBuilder;
     131: invokevirtual #23                 // Method java/lang/StringBuilder.toString:()Ljava/lang/String;
     134: invokespecial #24                 // Method java/lang/IllegalArgumentException."<init>":(Ljava/lang/String;)V
     137: athrow
     138: aload_0
     139: getfield      #14                 // Field comparator:Lorg/apache/hadoop/hbase/CellComparator;
     142: ifnonnull     160
     145: aload_0
     146: new           #25                 // class org/apache/hadoop/hbase/io/hfile/HFileBlockIndex$ByteArrayKeyBlockIndexReader
     149: dup
     150: iconst_1
     151: invokespecial #26                 // Method org/apache/hadoop/hbase/io/hfile/HFileBlockIndex$ByteArrayKeyBlockIndexReader."<init>":(I)V
     154: putfield      #27                 // Field index:Lorg/apache/hadoop/hbase/io/hfile/HFileBlockIndex$BlockIndexReader;
     157: goto          176
     160: aload_0
     161: new           #28                 // class org/apache/hadoop/hbase/io/hfile/HFileBlockIndex$CellBasedKeyBlockIndexReader
     164: dup
     165: aload_0
     166: getfield      #14                 // Field comparator:Lorg/apache/hadoop/hbase/CellComparator;
     169: iconst_1
     170: invokespecial #29                 // Method org/apache/hadoop/hbase/io/hfile/HFileBlockIndex$CellBasedKeyBlockIndexReader."<init>":(Lorg/apache/hadoop/hbase/CellComparator;I)V
     173: putfield      #27                 // Field index:Lorg/apache/hadoop/hbase/io/hfile/HFileBlockIndex$BlockIndexReader;
     176: aload_0
     177: getfield      #27                 // Field index:Lorg/apache/hadoop/hbase/io/hfile/HFileBlockIndex$BlockIndexReader;
     180: aload_1
     181: aload_0
     182: getfield      #10                 // Field numChunks:I
     185: invokevirtual #30                 // Method org/apache/hadoop/hbase/io/hfile/HFileBlockIndex$BlockIndexReader.readRootIndex:(Ljava/io/DataInput;I)V
     188: return

  public boolean contains(byte[], int, int, org.apache.hadoop.hbase.nio.ByteBuff);
    Code:
       0: aload_0
       1: getfield      #27                 // Field index:Lorg/apache/hadoop/hbase/io/hfile/HFileBlockIndex$BlockIndexReader;
       4: aload_1
       5: iload_2
       6: iload_3
       7: invokevirtual #31                 // Method org/apache/hadoop/hbase/io/hfile/HFileBlockIndex$BlockIndexReader.rootBlockContainingKey:([BII)I
      10: istore        5
      12: iload         5
      14: ifge          19
      17: iconst_0
      18: ireturn
      19: aload_0
      20: iload         5
      22: invokespecial #32                 // Method getBloomBlock:(I)Lorg/apache/hadoop/hbase/io/hfile/HFileBlock;
      25: astore        7
      27: aload         7
      29: invokevirtual #33                 // Method org/apache/hadoop/hbase/io/hfile/HFileBlock.getBufferReadOnly:()Lorg/apache/hadoop/hbase/nio/ByteBuff;
      32: astore        8
      34: aload_1
      35: iload_2
      36: iload_3
      37: aload         8
      39: aload         7
      41: invokevirtual #34                 // Method org/apache/hadoop/hbase/io/hfile/HFileBlock.headerSize:()I
      44: aload         7
      46: invokevirtual #35                 // Method org/apache/hadoop/hbase/io/hfile/HFileBlock.getUncompressedSizeWithoutHeader:()I
      49: aload_0
      50: getfield      #16                 // Field hash:Lorg/apache/hadoop/hbase/util/Hash;
      53: aload_0
      54: getfield      #6                  // Field hashCount:I
      57: invokestatic  #36                 // Method org/apache/hadoop/hbase/util/BloomFilterUtil.contains:([BIILorg/apache/hadoop/hbase/nio/ByteBuff;IILorg/apache/hadoop/hbase/util/Hash;I)Z
      60: istore        6
      62: aload_0
      63: getfield      #2                  // Field reader:Lorg/apache/hadoop/hbase/io/hfile/HFile$Reader;
      66: aload         7
      68: invokeinterface #37,  2           // InterfaceMethod org/apache/hadoop/hbase/io/hfile/HFile$Reader.returnBlock:(Lorg/apache/hadoop/hbase/io/hfile/HFileBlock;)V
      73: goto          92
      76: astore        9
      78: aload_0
      79: getfield      #2                  // Field reader:Lorg/apache/hadoop/hbase/io/hfile/HFile$Reader;
      82: aload         7
      84: invokeinterface #37,  2           // InterfaceMethod org/apache/hadoop/hbase/io/hfile/HFile$Reader.returnBlock:(Lorg/apache/hadoop/hbase/io/hfile/HFileBlock;)V
      89: aload         9
      91: athrow
      92: aload_0
      93: getfield      #38                 // Field numPositivesPerChunk:[J
      96: ifnull        115
      99: iload         6
     101: ifeq          115
     104: aload_0
     105: getfield      #38                 // Field numPositivesPerChunk:[J
     108: iload         5
     110: dup2
     111: laload
     112: lconst_1
     113: ladd
     114: lastore
     115: iload         6
     117: ireturn
    Exception table:
       from    to  target type
          27    62    76   any
          76    78    76   any

  public boolean contains(org.apache.hadoop.hbase.Cell, org.apache.hadoop.hbase.nio.ByteBuff, org.apache.hadoop.hbase.regionserver.BloomType);
    Code:
       0: aload_0
       1: getfield      #27                 // Field index:Lorg/apache/hadoop/hbase/io/hfile/HFileBlockIndex$BlockIndexReader;
       4: aload_1
       5: invokevirtual #47                 // Method org/apache/hadoop/hbase/io/hfile/HFileBlockIndex$BlockIndexReader.rootBlockContainingKey:(Lorg/apache/hadoop/hbase/Cell;)I
       8: istore        4
      10: iload         4
      12: ifge          17
      15: iconst_0
      16: ireturn
      17: aload_0
      18: iload         4
      20: invokespecial #32                 // Method getBloomBlock:(I)Lorg/apache/hadoop/hbase/io/hfile/HFileBlock;
      23: astore        6
      25: aload         6
      27: invokevirtual #33                 // Method org/apache/hadoop/hbase/io/hfile/HFileBlock.getBufferReadOnly:()Lorg/apache/hadoop/hbase/nio/ByteBuff;
      30: astore        7
      32: aload_1
      33: aload         7
      35: aload         6
      37: invokevirtual #34                 // Method org/apache/hadoop/hbase/io/hfile/HFileBlock.headerSize:()I
      40: aload         6
      42: invokevirtual #35                 // Method org/apache/hadoop/hbase/io/hfile/HFileBlock.getUncompressedSizeWithoutHeader:()I
      45: aload_0
      46: getfield      #16                 // Field hash:Lorg/apache/hadoop/hbase/util/Hash;
      49: aload_0
      50: getfield      #6                  // Field hashCount:I
      53: aload_3
      54: invokestatic  #48                 // Method org/apache/hadoop/hbase/util/BloomFilterUtil.contains:(Lorg/apache/hadoop/hbase/Cell;Lorg/apache/hadoop/hbase/nio/ByteBuff;IILorg/apache/hadoop/hbase/util/Hash;ILorg/apache/hadoop/hbase/regionserver/BloomType;)Z
      57: istore        5
      59: aload_0
      60: getfield      #2                  // Field reader:Lorg/apache/hadoop/hbase/io/hfile/HFile$Reader;
      63: aload         6
      65: invokeinterface #37,  2           // InterfaceMethod org/apache/hadoop/hbase/io/hfile/HFile$Reader.returnBlock:(Lorg/apache/hadoop/hbase/io/hfile/HFileBlock;)V
      70: goto          89
      73: astore        8
      75: aload_0
      76: getfield      #2                  // Field reader:Lorg/apache/hadoop/hbase/io/hfile/HFile$Reader;
      79: aload         6
      81: invokeinterface #37,  2           // InterfaceMethod org/apache/hadoop/hbase/io/hfile/HFile$Reader.returnBlock:(Lorg/apache/hadoop/hbase/io/hfile/HFileBlock;)V
      86: aload         8
      88: athrow
      89: aload_0
      90: getfield      #38                 // Field numPositivesPerChunk:[J
      93: ifnull        112
      96: iload         5
      98: ifeq          112
     101: aload_0
     102: getfield      #38                 // Field numPositivesPerChunk:[J
     105: iload         4
     107: dup2
     108: laload
     109: lconst_1
     110: ladd
     111: lastore
     112: iload         5
     114: ireturn
    Exception table:
       from    to  target type
          25    59    73   any
          73    75    73   any

  public boolean supportsAutoLoading();
    Code:
       0: iconst_1
       1: ireturn

  public int getNumChunks();
    Code:
       0: aload_0
       1: getfield      #10                 // Field numChunks:I
       4: ireturn

  public void enableTestingStats();
    Code:
       0: aload_0
       1: aload_0
       2: getfield      #10                 // Field numChunks:I
       5: newarray       long
       7: putfield      #46                 // Field numQueriesPerChunk:[J
      10: aload_0
      11: aload_0
      12: getfield      #10                 // Field numChunks:I
      15: newarray       long
      17: putfield      #38                 // Field numPositivesPerChunk:[J
      20: return

  public java.lang.String formatTestingStats();
    Code:
       0: new           #18                 // class java/lang/StringBuilder
       3: dup
       4: invokespecial #19                 // Method java/lang/StringBuilder."<init>":()V
       7: astore_1
       8: iconst_0
       9: istore_2
      10: iload_2
      11: aload_0
      12: getfield      #10                 // Field numChunks:I
      15: if_icmpge     109
      18: aload_1
      19: ldc           #49                 // String chunk #
      21: invokevirtual #21                 // Method java/lang/StringBuilder.append:(Ljava/lang/String;)Ljava/lang/StringBuilder;
      24: pop
      25: aload_1
      26: iload_2
      27: invokevirtual #22                 // Method java/lang/StringBuilder.append:(I)Ljava/lang/StringBuilder;
      30: pop
      31: aload_1
      32: ldc           #50                 // String : queries=
      34: invokevirtual #21                 // Method java/lang/StringBuilder.append:(Ljava/lang/String;)Ljava/lang/StringBuilder;
      37: pop
      38: aload_1
      39: aload_0
      40: getfield      #46                 // Field numQueriesPerChunk:[J
      43: iload_2
      44: laload
      45: invokevirtual #51                 // Method java/lang/StringBuilder.append:(J)Ljava/lang/StringBuilder;
      48: pop
      49: aload_1
      50: ldc           #52                 // String , positives=
      52: invokevirtual #21                 // Method java/lang/StringBuilder.append:(Ljava/lang/String;)Ljava/lang/StringBuilder;
      55: pop
      56: aload_1
      57: aload_0
      58: getfield      #38                 // Field numPositivesPerChunk:[J
      61: iload_2
      62: laload
      63: invokevirtual #51                 // Method java/lang/StringBuilder.append:(J)Ljava/lang/StringBuilder;
      66: pop
      67: aload_1
      68: ldc           #53                 // String , positiveRatio=
      70: invokevirtual #21                 // Method java/lang/StringBuilder.append:(Ljava/lang/String;)Ljava/lang/StringBuilder;
      73: pop
      74: aload_1
      75: aload_0
      76: getfield      #38                 // Field numPositivesPerChunk:[J
      79: iload_2
      80: laload
      81: l2d
      82: dconst_1
      83: dmul
      84: aload_0
      85: getfield      #46                 // Field numQueriesPerChunk:[J
      88: iload_2
      89: laload
      90: l2d
      91: ddiv
      92: invokevirtual #54                 // Method java/lang/StringBuilder.append:(D)Ljava/lang/StringBuilder;
      95: pop
      96: aload_1
      97: ldc           #55                 // String ;\n
      99: invokevirtual #21                 // Method java/lang/StringBuilder.append:(Ljava/lang/String;)Ljava/lang/StringBuilder;
     102: pop
     103: iinc          2, 1
     106: goto          10
     109: aload_1
     110: invokevirtual #23                 // Method java/lang/StringBuilder.toString:()Ljava/lang/String;
     113: areturn

  public long getNumQueriesForTesting(int);
    Code:
       0: aload_0
       1: getfield      #46                 // Field numQueriesPerChunk:[J
       4: iload_1
       5: laload
       6: lreturn

  public long getNumPositivesForTesting(int);
    Code:
       0: aload_0
       1: getfield      #38                 // Field numPositivesPerChunk:[J
       4: iload_1
       5: laload
       6: lreturn

  public java.lang.String toString();
    Code:
       0: new           #18                 // class java/lang/StringBuilder
       3: dup
       4: invokespecial #19                 // Method java/lang/StringBuilder."<init>":()V
       7: astore_1
       8: aload_1
       9: aload_0
      10: invokestatic  #56                 // Method org/apache/hadoop/hbase/util/BloomFilterUtil.formatStats:(Lorg/apache/hadoop/hbase/util/BloomFilterBase;)Ljava/lang/String;
      13: invokevirtual #21                 // Method java/lang/StringBuilder.append:(Ljava/lang/String;)Ljava/lang/StringBuilder;
      16: pop
      17: aload_1
      18: new           #18                 // class java/lang/StringBuilder
      21: dup
      22: invokespecial #19                 // Method java/lang/StringBuilder."<init>":()V
      25: ldc           #58                 // String ; Number of chunks:
      27: invokevirtual #21                 // Method java/lang/StringBuilder.append:(Ljava/lang/String;)Ljava/lang/StringBuilder;
      30: aload_0
      31: getfield      #10                 // Field numChunks:I
      34: invokevirtual #22                 // Method java/lang/StringBuilder.append:(I)Ljava/lang/StringBuilder;
      37: invokevirtual #23                 // Method java/lang/StringBuilder.toString:()Ljava/lang/String;
      40: invokevirtual #21                 // Method java/lang/StringBuilder.append:(Ljava/lang/String;)Ljava/lang/StringBuilder;
      43: pop
      44: aload_1
      45: new           #18                 // class java/lang/StringBuilder
      48: dup
      49: invokespecial #19                 // Method java/lang/StringBuilder."<init>":()V
      52: ldc           #59                 // String ;
      54: invokevirtual #21                 // Method java/lang/StringBuilder.append:(Ljava/lang/String;)Ljava/lang/StringBuilder;
      57: aload_0
      58: getfield      #14                 // Field comparator:Lorg/apache/hadoop/hbase/CellComparator;
      61: ifnull        95
      64: new           #18                 // class java/lang/StringBuilder
      67: dup
      68: invokespecial #19                 // Method java/lang/StringBuilder."<init>":()V
      71: ldc           #60                 // String Comparator:
      73: invokevirtual #21                 // Method java/lang/StringBuilder.append:(Ljava/lang/String;)Ljava/lang/StringBuilder;
      76: aload_0
      77: getfield      #14                 // Field comparator:Lorg/apache/hadoop/hbase/CellComparator;
      80: invokevirtual #61                 // Method java/lang/Object.getClass:()Ljava/lang/Class;
      83: invokevirtual #62                 // Method java/lang/Class.getSimpleName:()Ljava/lang/String;
      86: invokevirtual #21                 // Method java/lang/StringBuilder.append:(Ljava/lang/String;)Ljava/lang/StringBuilder;
      89: invokevirtual #23                 // Method java/lang/StringBuilder.toString:()Ljava/lang/String;
      92: goto          122
      95: new           #18                 // class java/lang/StringBuilder
      98: dup
      99: invokespecial #19                 // Method java/lang/StringBuilder."<init>":()V
     102: ldc           #60                 // String Comparator:
     104: invokevirtual #21                 // Method java/lang/StringBuilder.append:(Ljava/lang/String;)Ljava/lang/StringBuilder;
     107: getstatic     #63                 // Field org/apache/hadoop/hbase/util/Bytes.BYTES_RAWCOMPARATOR:Lorg/apache/hadoop/io/RawComparator;
     110: invokevirtual #61                 // Method java/lang/Object.getClass:()Ljava/lang/Class;
     113: invokevirtual #62                 // Method java/lang/Class.getSimpleName:()Ljava/lang/String;
     116: invokevirtual #21                 // Method java/lang/StringBuilder.append:(Ljava/lang/String;)Ljava/lang/StringBuilder;
     119: invokevirtual #23                 // Method java/lang/StringBuilder.toString:()Ljava/lang/String;
     122: invokevirtual #21                 // Method java/lang/StringBuilder.append:(Ljava/lang/String;)Ljava/lang/StringBuilder;
     125: invokevirtual #23                 // Method java/lang/StringBuilder.toString:()Ljava/lang/String;
     128: invokevirtual #21                 // Method java/lang/StringBuilder.append:(Ljava/lang/String;)Ljava/lang/StringBuilder;
     131: pop
     132: aload_1
     133: invokevirtual #23                 // Method java/lang/StringBuilder.toString:()Ljava/lang/String;
     136: areturn
}
