Compiled from "CompactionContext.java"
public abstract class org.apache.hadoop.hbase.regionserver.compactions.CompactionContext {
  protected org.apache.hadoop.hbase.regionserver.compactions.CompactionRequestImpl request;

  static final boolean $assertionsDisabled;

  public org.apache.hadoop.hbase.regionserver.compactions.CompactionContext();
    Code:
       0: aload_0
       1: invokespecial #1                  // Method java/lang/Object."<init>":()V
       4: aload_0
       5: aconst_null
       6: putfield      #2                  // Field request:Lorg/apache/hadoop/hbase/regionserver/compactions/CompactionRequestImpl;
       9: return

  public abstract java.util.List<org.apache.hadoop.hbase.regionserver.HStoreFile> preSelect(java.util.List<org.apache.hadoop.hbase.regionserver.HStoreFile>);

  public abstract boolean select(java.util.List<org.apache.hadoop.hbase.regionserver.HStoreFile>, boolean, boolean, boolean) throws java.io.IOException;

  public void forceSelect(org.apache.hadoop.hbase.regionserver.compactions.CompactionRequestImpl);
    Code:
       0: aload_0
       1: aload_1
       2: putfield      #2                  // Field request:Lorg/apache/hadoop/hbase/regionserver/compactions/CompactionRequestImpl;
       5: return

  public abstract java.util.List<org.apache.hadoop.fs.Path> compact(org.apache.hadoop.hbase.regionserver.throttle.ThroughputController, org.apache.hadoop.hbase.security.User) throws java.io.IOException;

  public org.apache.hadoop.hbase.regionserver.compactions.CompactionRequestImpl getRequest();
    Code:
       0: getstatic     #3                  // Field $assertionsDisabled:Z
       3: ifne          21
       6: aload_0
       7: invokevirtual #4                  // Method hasSelection:()Z
      10: ifne          21
      13: new           #5                  // class java/lang/AssertionError
      16: dup
      17: invokespecial #6                  // Method java/lang/AssertionError."<init>":()V
      20: athrow
      21: aload_0
      22: getfield      #2                  // Field request:Lorg/apache/hadoop/hbase/regionserver/compactions/CompactionRequestImpl;
      25: areturn

  public boolean hasSelection();
    Code:
       0: aload_0
       1: getfield      #2                  // Field request:Lorg/apache/hadoop/hbase/regionserver/compactions/CompactionRequestImpl;
       4: ifnull        11
       7: iconst_1
       8: goto          12
      11: iconst_0
      12: ireturn

  static {};
    Code:
       0: ldc           #7                  // class org/apache/hadoop/hbase/regionserver/compactions/CompactionContext
       2: invokevirtual #8                  // Method java/lang/Class.desiredAssertionStatus:()Z
       5: ifne          12
       8: iconst_1
       9: goto          13
      12: iconst_0
      13: putstatic     #3                  // Field $assertionsDisabled:Z
      16: return
}
