Compiled from "CompareOperator.java"
public final class org.apache.hadoop.hbase.CompareOperator extends java.lang.Enum<org.apache.hadoop.hbase.CompareOperator> {
  public static final org.apache.hadoop.hbase.CompareOperator LESS;

  public static final org.apache.hadoop.hbase.CompareOperator LESS_OR_EQUAL;

  public static final org.apache.hadoop.hbase.CompareOperator EQUAL;

  public static final org.apache.hadoop.hbase.CompareOperator NOT_EQUAL;

  public static final org.apache.hadoop.hbase.CompareOperator GREATER_OR_EQUAL;

  public static final org.apache.hadoop.hbase.CompareOperator GREATER;

  public static final org.apache.hadoop.hbase.CompareOperator NO_OP;

  public static org.apache.hadoop.hbase.CompareOperator[] values();
    Code:
       0: getstatic     #1                  // Field $VALUES:[Lorg/apache/hadoop/hbase/CompareOperator;
       3: invokevirtual #2                  // Method "[Lorg/apache/hadoop/hbase/CompareOperator;".clone:()Ljava/lang/Object;
       6: checkcast     #3                  // class "[Lorg/apache/hadoop/hbase/CompareOperator;"
       9: areturn

  public static org.apache.hadoop.hbase.CompareOperator valueOf(java.lang.String);
    Code:
       0: ldc           #4                  // class org/apache/hadoop/hbase/CompareOperator
       2: aload_0
       3: invokestatic  #5                  // Method java/lang/Enum.valueOf:(Ljava/lang/Class;Ljava/lang/String;)Ljava/lang/Enum;
       6: checkcast     #4                  // class org/apache/hadoop/hbase/CompareOperator
       9: areturn

  static {};
    Code:
       0: new           #4                  // class org/apache/hadoop/hbase/CompareOperator
       3: dup
       4: ldc           #7                  // String LESS
       6: iconst_0
       7: invokespecial #8                  // Method "<init>":(Ljava/lang/String;I)V
      10: putstatic     #9                  // Field LESS:Lorg/apache/hadoop/hbase/CompareOperator;
      13: new           #4                  // class org/apache/hadoop/hbase/CompareOperator
      16: dup
      17: ldc           #10                 // String LESS_OR_EQUAL
      19: iconst_1
      20: invokespecial #8                  // Method "<init>":(Ljava/lang/String;I)V
      23: putstatic     #11                 // Field LESS_OR_EQUAL:Lorg/apache/hadoop/hbase/CompareOperator;
      26: new           #4                  // class org/apache/hadoop/hbase/CompareOperator
      29: dup
      30: ldc           #12                 // String EQUAL
      32: iconst_2
      33: invokespecial #8                  // Method "<init>":(Ljava/lang/String;I)V
      36: putstatic     #13                 // Field EQUAL:Lorg/apache/hadoop/hbase/CompareOperator;
      39: new           #4                  // class org/apache/hadoop/hbase/CompareOperator
      42: dup
      43: ldc           #14                 // String NOT_EQUAL
      45: iconst_3
      46: invokespecial #8                  // Method "<init>":(Ljava/lang/String;I)V
      49: putstatic     #15                 // Field NOT_EQUAL:Lorg/apache/hadoop/hbase/CompareOperator;
      52: new           #4                  // class org/apache/hadoop/hbase/CompareOperator
      55: dup
      56: ldc           #16                 // String GREATER_OR_EQUAL
      58: iconst_4
      59: invokespecial #8                  // Method "<init>":(Ljava/lang/String;I)V
      62: putstatic     #17                 // Field GREATER_OR_EQUAL:Lorg/apache/hadoop/hbase/CompareOperator;
      65: new           #4                  // class org/apache/hadoop/hbase/CompareOperator
      68: dup
      69: ldc           #18                 // String GREATER
      71: iconst_5
      72: invokespecial #8                  // Method "<init>":(Ljava/lang/String;I)V
      75: putstatic     #19                 // Field GREATER:Lorg/apache/hadoop/hbase/CompareOperator;
      78: new           #4                  // class org/apache/hadoop/hbase/CompareOperator
      81: dup
      82: ldc           #20                 // String NO_OP
      84: bipush        6
      86: invokespecial #8                  // Method "<init>":(Ljava/lang/String;I)V
      89: putstatic     #21                 // Field NO_OP:Lorg/apache/hadoop/hbase/CompareOperator;
      92: bipush        7
      94: anewarray     #4                  // class org/apache/hadoop/hbase/CompareOperator
      97: dup
      98: iconst_0
      99: getstatic     #9                  // Field LESS:Lorg/apache/hadoop/hbase/CompareOperator;
     102: aastore
     103: dup
     104: iconst_1
     105: getstatic     #11                 // Field LESS_OR_EQUAL:Lorg/apache/hadoop/hbase/CompareOperator;
     108: aastore
     109: dup
     110: iconst_2
     111: getstatic     #13                 // Field EQUAL:Lorg/apache/hadoop/hbase/CompareOperator;
     114: aastore
     115: dup
     116: iconst_3
     117: getstatic     #15                 // Field NOT_EQUAL:Lorg/apache/hadoop/hbase/CompareOperator;
     120: aastore
     121: dup
     122: iconst_4
     123: getstatic     #17                 // Field GREATER_OR_EQUAL:Lorg/apache/hadoop/hbase/CompareOperator;
     126: aastore
     127: dup
     128: iconst_5
     129: getstatic     #19                 // Field GREATER:Lorg/apache/hadoop/hbase/CompareOperator;
     132: aastore
     133: dup
     134: bipush        6
     136: getstatic     #21                 // Field NO_OP:Lorg/apache/hadoop/hbase/CompareOperator;
     139: aastore
     140: putstatic     #1                  // Field $VALUES:[Lorg/apache/hadoop/hbase/CompareOperator;
     143: return
}
