Compiled from "Compactor.java"
public abstract class org.apache.hadoop.hbase.regionserver.compactions.Compactor<T extends org.apache.hadoop.hbase.regionserver.CellSink> {
  protected static final long COMPACTION_PROGRESS_LOG_INTERVAL;

  protected volatile org.apache.hadoop.hbase.regionserver.compactions.CompactionProgress progress;

  protected final org.apache.hadoop.conf.Configuration conf;

  protected final org.apache.hadoop.hbase.regionserver.HStore store;

  protected final int compactionKVMax;

  protected final org.apache.hadoop.hbase.io.compress.Compression$Algorithm compactionCompression;

  protected int keepSeqIdPeriod;

  protected static final java.lang.String MAJOR_COMPACTION_DROP_CACHE;

  protected static final java.lang.String MINOR_COMPACTION_DROP_CACHE;

  protected final org.apache.hadoop.hbase.regionserver.compactions.Compactor$InternalScannerFactory defaultScannerFactory;

  static final boolean $assertionsDisabled;

  org.apache.hadoop.hbase.regionserver.compactions.Compactor(org.apache.hadoop.conf.Configuration, org.apache.hadoop.hbase.regionserver.HStore);
    Code:
       0: aload_0
       1: invokespecial #1                  // Method java/lang/Object."<init>":()V
       4: aload_0
       5: new           #2                  // class org/apache/hadoop/hbase/regionserver/compactions/Compactor$1
       8: dup
       9: aload_0
      10: invokespecial #3                  // Method org/apache/hadoop/hbase/regionserver/compactions/Compactor$1."<init>":(Lorg/apache/hadoop/hbase/regionserver/compactions/Compactor;)V
      13: putfield      #4                  // Field defaultScannerFactory:Lorg/apache/hadoop/hbase/regionserver/compactions/Compactor$InternalScannerFactory;
      16: aload_0
      17: aload_1
      18: putfield      #5                  // Field conf:Lorg/apache/hadoop/conf/Configuration;
      21: aload_0
      22: aload_2
      23: putfield      #6                  // Field store:Lorg/apache/hadoop/hbase/regionserver/HStore;
      26: aload_0
      27: aload_0
      28: getfield      #5                  // Field conf:Lorg/apache/hadoop/conf/Configuration;
      31: ldc           #8                  // String hbase.hstore.compaction.kv.max
      33: bipush        10
      35: invokevirtual #9                  // Method org/apache/hadoop/conf/Configuration.getInt:(Ljava/lang/String;I)I
      38: putfield      #10                 // Field compactionKVMax:I
      41: aload_0
      42: aload_0
      43: getfield      #6                  // Field store:Lorg/apache/hadoop/hbase/regionserver/HStore;
      46: invokevirtual #11                 // Method org/apache/hadoop/hbase/regionserver/HStore.getColumnFamilyDescriptor:()Lorg/apache/hadoop/hbase/client/ColumnFamilyDescriptor;
      49: ifnonnull     58
      52: getstatic     #12                 // Field org/apache/hadoop/hbase/io/compress/Compression$Algorithm.NONE:Lorg/apache/hadoop/hbase/io/compress/Compression$Algorithm;
      55: goto          70
      58: aload_0
      59: getfield      #6                  // Field store:Lorg/apache/hadoop/hbase/regionserver/HStore;
      62: invokevirtual #11                 // Method org/apache/hadoop/hbase/regionserver/HStore.getColumnFamilyDescriptor:()Lorg/apache/hadoop/hbase/client/ColumnFamilyDescriptor;
      65: invokeinterface #13,  1           // InterfaceMethod org/apache/hadoop/hbase/client/ColumnFamilyDescriptor.getCompactionCompressionType:()Lorg/apache/hadoop/hbase/io/compress/Compression$Algorithm;
      70: putfield      #14                 // Field compactionCompression:Lorg/apache/hadoop/hbase/io/compress/Compression$Algorithm;
      73: aload_0
      74: aload_0
      75: getfield      #5                  // Field conf:Lorg/apache/hadoop/conf/Configuration;
      78: ldc           #15                 // String hbase.hstore.compaction.keep.seqId.period
      80: iconst_5
      81: invokevirtual #9                  // Method org/apache/hadoop/conf/Configuration.getInt:(Ljava/lang/String;I)I
      84: iconst_5
      85: invokestatic  #16                 // Method java/lang/Math.max:(II)I
      88: putfield      #17                 // Field keepSeqIdPeriod:I
      91: aload_0
      92: aload_1
      93: ldc           #19                 // String hbase.regionserver.majorcompaction.pagecache.drop
      95: iconst_1
      96: invokevirtual #20                 // Method org/apache/hadoop/conf/Configuration.getBoolean:(Ljava/lang/String;Z)Z
      99: putfield      #21                 // Field dropCacheMajor:Z
     102: aload_0
     103: aload_1
     104: ldc           #22                 // String hbase.regionserver.minorcompaction.pagecache.drop
     106: iconst_1
     107: invokevirtual #20                 // Method org/apache/hadoop/conf/Configuration.getBoolean:(Ljava/lang/String;Z)Z
     110: putfield      #23                 // Field dropCacheMinor:Z
     113: return

  public org.apache.hadoop.hbase.regionserver.compactions.CompactionProgress getProgress();
    Code:
       0: aload_0
       1: getfield      #24                 // Field progress:Lorg/apache/hadoop/hbase/regionserver/compactions/CompactionProgress;
       4: areturn

  protected final org.apache.hadoop.hbase.regionserver.StoreFileWriter createTmpWriter(org.apache.hadoop.hbase.regionserver.compactions.Compactor$FileDetails, boolean) throws java.io.IOException;
    Code:
       0: aload_0
       1: getfield      #6                  // Field store:Lorg/apache/hadoop/hbase/regionserver/HStore;
       4: aload_1
       5: getfield      #51                 // Field org/apache/hadoop/hbase/regionserver/compactions/Compactor$FileDetails.maxKeyCount:J
       8: aload_0
       9: getfield      #14                 // Field compactionCompression:Lorg/apache/hadoop/hbase/io/compress/Compression$Algorithm;
      12: iconst_1
      13: aload_1
      14: getfield      #54                 // Field org/apache/hadoop/hbase/regionserver/compactions/Compactor$FileDetails.maxMVCCReadpoint:J
      17: lconst_0
      18: lcmp
      19: ifle          26
      22: iconst_1
      23: goto          27
      26: iconst_0
      27: aload_1
      28: getfield      #61                 // Field org/apache/hadoop/hbase/regionserver/compactions/Compactor$FileDetails.maxTagsLength:I
      31: ifle          38
      34: iconst_1
      35: goto          39
      38: iconst_0
      39: iload_2
      40: invokevirtual #90                 // Method org/apache/hadoop/hbase/regionserver/HStore.createWriterInTmp:(JLorg/apache/hadoop/hbase/io/compress/Compression$Algorithm;ZZZZ)Lorg/apache/hadoop/hbase/regionserver/StoreFileWriter;
      43: areturn

  protected final java.util.List<org.apache.hadoop.fs.Path> compact(org.apache.hadoop.hbase.regionserver.compactions.CompactionRequestImpl, org.apache.hadoop.hbase.regionserver.compactions.Compactor$InternalScannerFactory, org.apache.hadoop.hbase.regionserver.compactions.Compactor$CellSinkFactory<T>, org.apache.hadoop.hbase.regionserver.throttle.ThroughputController, org.apache.hadoop.hbase.security.User) throws java.io.IOException;
    Code:
       0: aload_0
       1: aload_1
       2: invokevirtual #96                 // Method org/apache/hadoop/hbase/regionserver/compactions/CompactionRequestImpl.getFiles:()Ljava/util/Collection;
       5: aload_1
       6: invokevirtual #97                 // Method org/apache/hadoop/hbase/regionserver/compactions/CompactionRequestImpl.isAllFiles:()Z
       9: invokespecial #98                 // Method getFileDetails:(Ljava/util/Collection;Z)Lorg/apache/hadoop/hbase/regionserver/compactions/Compactor$FileDetails;
      12: astore        6
      14: aload_0
      15: new           #99                 // class org/apache/hadoop/hbase/regionserver/compactions/CompactionProgress
      18: dup
      19: aload         6
      21: getfield      #51                 // Field org/apache/hadoop/hbase/regionserver/compactions/Compactor$FileDetails.maxKeyCount:J
      24: invokespecial #100                // Method org/apache/hadoop/hbase/regionserver/compactions/CompactionProgress."<init>":(J)V
      27: putfield      #24                 // Field progress:Lorg/apache/hadoop/hbase/regionserver/compactions/CompactionProgress;
      30: aload_0
      31: invokespecial #101                // Method getSmallestReadPoint:()J
      34: lstore        7
      36: aconst_null
      37: astore        9
      39: aload_1
      40: invokevirtual #102                // Method org/apache/hadoop/hbase/regionserver/compactions/CompactionRequestImpl.isMajor:()Z
      43: ifne          53
      46: aload_1
      47: invokevirtual #97                 // Method org/apache/hadoop/hbase/regionserver/compactions/CompactionRequestImpl.isAllFiles:()Z
      50: ifeq          62
      53: aload_0
      54: getfield      #21                 // Field dropCacheMajor:Z
      57: istore        10
      59: goto          68
      62: aload_0
      63: getfield      #23                 // Field dropCacheMinor:Z
      66: istore        10
      68: aload_0
      69: aload_1
      70: invokevirtual #96                 // Method org/apache/hadoop/hbase/regionserver/compactions/CompactionRequestImpl.getFiles:()Ljava/util/Collection;
      73: lload         7
      75: iload         10
      77: invokespecial #103                // Method createFileScanners:(Ljava/util/Collection;JZ)Ljava/util/List;
      80: astore        11
      82: aconst_null
      83: astore        12
      85: iconst_0
      86: istore        13
      88: aload_2
      89: aload_1
      90: invokeinterface #104,  2          // InterfaceMethod org/apache/hadoop/hbase/regionserver/compactions/Compactor$InternalScannerFactory.getScanType:(Lorg/apache/hadoop/hbase/regionserver/compactions/CompactionRequestImpl;)Lorg/apache/hadoop/hbase/regionserver/ScanType;
      95: astore        14
      97: aload_0
      98: aload_1
      99: aload         14
     101: aload         5
     103: invokespecial #105                // Method preCompactScannerOpen:(Lorg/apache/hadoop/hbase/regionserver/compactions/CompactionRequestImpl;Lorg/apache/hadoop/hbase/regionserver/ScanType;Lorg/apache/hadoop/hbase/security/User;)Lorg/apache/hadoop/hbase/regionserver/ScanInfo;
     106: astore        15
     108: aload_0
     109: aload_1
     110: aload         14
     112: aload_2
     113: aload         15
     115: aload         11
     117: aload         14
     119: aload         6
     121: lload         7
     123: invokeinterface #106,  7          // InterfaceMethod org/apache/hadoop/hbase/regionserver/compactions/Compactor$InternalScannerFactory.createScanner:(Lorg/apache/hadoop/hbase/regionserver/ScanInfo;Ljava/util/List;Lorg/apache/hadoop/hbase/regionserver/ScanType;Lorg/apache/hadoop/hbase/regionserver/compactions/Compactor$FileDetails;J)Lorg/apache/hadoop/hbase/regionserver/InternalScanner;
     128: aload         5
     130: invokespecial #107                // Method postCompactScannerOpen:(Lorg/apache/hadoop/hbase/regionserver/compactions/CompactionRequestImpl;Lorg/apache/hadoop/hbase/regionserver/ScanType;Lorg/apache/hadoop/hbase/regionserver/InternalScanner;Lorg/apache/hadoop/hbase/security/User;)Lorg/apache/hadoop/hbase/regionserver/InternalScanner;
     133: astore        12
     135: iconst_0
     136: istore        16
     138: aload         6
     140: getfield      #35                 // Field org/apache/hadoop/hbase/regionserver/compactions/Compactor$FileDetails.minSeqIdToKeep:J
     143: lconst_0
     144: lcmp
     145: ifle          178
     148: aload_0
     149: getfield      #6                  // Field store:Lorg/apache/hadoop/hbase/regionserver/HStore;
     152: invokevirtual #11                 // Method org/apache/hadoop/hbase/regionserver/HStore.getColumnFamilyDescriptor:()Lorg/apache/hadoop/hbase/client/ColumnFamilyDescriptor;
     155: invokeinterface #108,  1          // InterfaceMethod org/apache/hadoop/hbase/client/ColumnFamilyDescriptor.isNewVersionBehavior:()Z
     160: ifne          178
     163: aload         6
     165: getfield      #35                 // Field org/apache/hadoop/hbase/regionserver/compactions/Compactor$FileDetails.minSeqIdToKeep:J
     168: lload         7
     170: invokestatic  #67                 // Method java/lang/Math.min:(JJ)J
     173: lstore        7
     175: iconst_1
     176: istore        16
     178: aload_3
     179: aload         12
     181: aload         6
     183: iload         10
     185: invokeinterface #109,  4          // InterfaceMethod org/apache/hadoop/hbase/regionserver/compactions/Compactor$CellSinkFactory.createWriter:(Lorg/apache/hadoop/hbase/regionserver/InternalScanner;Lorg/apache/hadoop/hbase/regionserver/compactions/Compactor$FileDetails;Z)Ljava/lang/Object;
     190: checkcast     #110                // class org/apache/hadoop/hbase/regionserver/CellSink
     193: astore        9
     195: aload_0
     196: aload         6
     198: aload         12
     200: aload         9
     202: lload         7
     204: iload         16
     206: aload         4
     208: aload_1
     209: invokevirtual #97                 // Method org/apache/hadoop/hbase/regionserver/compactions/CompactionRequestImpl.isAllFiles:()Z
     212: aload_1
     213: invokevirtual #96                 // Method org/apache/hadoop/hbase/regionserver/compactions/CompactionRequestImpl.getFiles:()Ljava/util/Collection;
     216: invokeinterface #111,  1          // InterfaceMethod java/util/Collection.size:()I
     221: invokevirtual #112                // Method performCompaction:(Lorg/apache/hadoop/hbase/regionserver/compactions/Compactor$FileDetails;Lorg/apache/hadoop/hbase/regionserver/InternalScanner;Lorg/apache/hadoop/hbase/regionserver/CellSink;JZLorg/apache/hadoop/hbase/regionserver/throttle/ThroughputController;ZI)Z
     224: istore        13
     226: iload         13
     228: ifne          286
     231: new           #113                // class java/io/InterruptedIOException
     234: dup
     235: new           #42                 // class java/lang/StringBuilder
     238: dup
     239: invokespecial #43                 // Method java/lang/StringBuilder."<init>":()V
     242: ldc           #114                // String Aborting compaction of store
     244: invokevirtual #45                 // Method java/lang/StringBuilder.append:(Ljava/lang/String;)Ljava/lang/StringBuilder;
     247: aload_0
     248: getfield      #6                  // Field store:Lorg/apache/hadoop/hbase/regionserver/HStore;
     251: invokevirtual #47                 // Method java/lang/StringBuilder.append:(Ljava/lang/Object;)Ljava/lang/StringBuilder;
     254: ldc           #115                // String  in region
     256: invokevirtual #45                 // Method java/lang/StringBuilder.append:(Ljava/lang/String;)Ljava/lang/StringBuilder;
     259: aload_0
     260: getfield      #6                  // Field store:Lorg/apache/hadoop/hbase/regionserver/HStore;
     263: invokevirtual #116                // Method org/apache/hadoop/hbase/regionserver/HStore.getRegionInfo:()Lorg/apache/hadoop/hbase/client/RegionInfo;
     266: invokeinterface #117,  1          // InterfaceMethod org/apache/hadoop/hbase/client/RegionInfo.getRegionNameAsString:()Ljava/lang/String;
     271: invokevirtual #45                 // Method java/lang/StringBuilder.append:(Ljava/lang/String;)Ljava/lang/StringBuilder;
     274: ldc           #118                // String  because it was interrupted.
     276: invokevirtual #45                 // Method java/lang/StringBuilder.append:(Ljava/lang/String;)Ljava/lang/StringBuilder;
     279: invokevirtual #48                 // Method java/lang/StringBuilder.toString:()Ljava/lang/String;
     282: invokespecial #119                // Method java/io/InterruptedIOException."<init>":(Ljava/lang/String;)V
     285: athrow
     286: aload         12
     288: iconst_1
     289: invokestatic  #120                // Method org/apache/hbase/thirdparty/com/google/common/io/Closeables.close:(Ljava/io/Closeable;Z)V
     292: iload         13
     294: ifne          338
     297: aload         9
     299: ifnull        338
     302: aload_0
     303: aload         9
     305: invokevirtual #121                // Method abortWriter:(Lorg/apache/hadoop/hbase/regionserver/CellSink;)V
     308: goto          338
     311: astore        17
     313: aload         12
     315: iconst_1
     316: invokestatic  #120                // Method org/apache/hbase/thirdparty/com/google/common/io/Closeables.close:(Ljava/io/Closeable;Z)V
     319: iload         13
     321: ifne          335
     324: aload         9
     326: ifnull        335
     329: aload_0
     330: aload         9
     332: invokevirtual #121                // Method abortWriter:(Lorg/apache/hadoop/hbase/regionserver/CellSink;)V
     335: aload         17
     337: athrow
     338: getstatic     #122                // Field $assertionsDisabled:Z
     341: ifne          359
     344: iload         13
     346: ifne          359
     349: new           #123                // class java/lang/AssertionError
     352: dup
     353: ldc           #124                // String We should have exited the method on all error paths
     355: invokespecial #125                // Method java/lang/AssertionError."<init>":(Ljava/lang/Object;)V
     358: athrow
     359: getstatic     #122                // Field $assertionsDisabled:Z
     362: ifne          380
     365: aload         9
     367: ifnonnull     380
     370: new           #123                // class java/lang/AssertionError
     373: dup
     374: ldc           #126                // String Writer should be non-null if no error
     376: invokespecial #125                // Method java/lang/AssertionError."<init>":(Ljava/lang/Object;)V
     379: athrow
     380: aload_0
     381: aload         9
     383: aload         6
     385: aload_1
     386: invokevirtual #127                // Method commitWriter:(Lorg/apache/hadoop/hbase/regionserver/CellSink;Lorg/apache/hadoop/hbase/regionserver/compactions/Compactor$FileDetails;Lorg/apache/hadoop/hbase/regionserver/compactions/CompactionRequestImpl;)Ljava/util/List;
     389: areturn
    Exception table:
       from    to  target type
          88   286   311   any
         311   313   311   any

  protected abstract java.util.List<org.apache.hadoop.fs.Path> commitWriter(T, org.apache.hadoop.hbase.regionserver.compactions.Compactor$FileDetails, org.apache.hadoop.hbase.regionserver.compactions.CompactionRequestImpl) throws java.io.IOException;

  protected abstract void abortWriter(T) throws java.io.IOException;

  protected boolean performCompaction(org.apache.hadoop.hbase.regionserver.compactions.Compactor$FileDetails, org.apache.hadoop.hbase.regionserver.InternalScanner, org.apache.hadoop.hbase.regionserver.CellSink, long, boolean, org.apache.hadoop.hbase.regionserver.throttle.ThroughputController, boolean, int) throws java.io.IOException;
    Code:
       0: getstatic     #122                // Field $assertionsDisabled:Z
       3: ifne          21
       6: aload_3
       7: instanceof    #128                // class org/apache/hadoop/hbase/regionserver/ShipperListener
      10: ifne          21
      13: new           #123                // class java/lang/AssertionError
      16: dup
      17: invokespecial #129                // Method java/lang/AssertionError."<init>":()V
      20: athrow
      21: lconst_0
      22: lstore        10
      24: lconst_0
      25: lstore        12
      27: lconst_0
      28: lstore        14
      30: new           #130                // class java/util/ArrayList
      33: dup
      34: invokespecial #131                // Method java/util/ArrayList."<init>":()V
      37: astore        16
      39: invokestatic  #132                // Method org/apache/hadoop/hbase/regionserver/HStore.getCloseCheckInterval:()I
      42: i2l
      43: lstore        17
      45: lconst_0
      46: lstore        19
      48: getstatic     #41                 // Field LOG:Lorg/slf4j/Logger;
      51: invokeinterface #133,  1          // InterfaceMethod org/slf4j/Logger.isDebugEnabled:()Z
      56: ifeq          64
      59: invokestatic  #134                // Method org/apache/hadoop/hbase/util/EnvironmentEdgeManager.currentTime:()J
      62: lstore        19
      64: aload_0
      65: getfield      #6                  // Field store:Lorg/apache/hadoop/hbase/regionserver/HStore;
      68: ldc           #135                // String compaction
      70: invokestatic  #136                // Method org/apache/hadoop/hbase/regionserver/throttle/ThroughputControlUtil.getNameForThrottling:(Lorg/apache/hadoop/hbase/regionserver/HStore;Ljava/lang/String;)Ljava/lang/String;
      73: astore        21
      75: lconst_0
      76: lstore        22
      78: invokestatic  #137                // Method org/apache/hadoop/hbase/regionserver/ScannerContext.newBuilder:()Lorg/apache/hadoop/hbase/regionserver/ScannerContext$Builder;
      81: aload_0
      82: getfield      #10                 // Field compactionKVMax:I
      85: invokevirtual #138                // Method org/apache/hadoop/hbase/regionserver/ScannerContext$Builder.setBatchLimit:(I)Lorg/apache/hadoop/hbase/regionserver/ScannerContext$Builder;
      88: invokevirtual #139                // Method org/apache/hadoop/hbase/regionserver/ScannerContext$Builder.build:()Lorg/apache/hadoop/hbase/regionserver/ScannerContext;
      91: astore        25
      93: aload         7
      95: aload         21
      97: invokeinterface #140,  2          // InterfaceMethod org/apache/hadoop/hbase/regionserver/throttle/ThroughputController.start:(Ljava/lang/String;)V
     102: aload_2
     103: instanceof    #141                // class org/apache/hadoop/hbase/regionserver/KeyValueScanner
     106: ifeq          116
     109: aload_2
     110: checkcast     #141                // class org/apache/hadoop/hbase/regionserver/KeyValueScanner
     113: goto          117
     116: aconst_null
     117: astore        26
     119: iload         9
     121: i2l
     122: aload_0
     123: getfield      #6                  // Field store:Lorg/apache/hadoop/hbase/regionserver/HStore;
     126: invokevirtual #11                 // Method org/apache/hadoop/hbase/regionserver/HStore.getColumnFamilyDescriptor:()Lorg/apache/hadoop/hbase/client/ColumnFamilyDescriptor;
     129: invokeinterface #142,  1          // InterfaceMethod org/apache/hadoop/hbase/client/ColumnFamilyDescriptor.getBlocksize:()I
     134: i2l
     135: lmul
     136: lstore        27
     138: aload_2
     139: aload         16
     141: aload         25
     143: invokeinterface #143,  3          // InterfaceMethod org/apache/hadoop/hbase/regionserver/InternalScanner.next:(Ljava/util/List;Lorg/apache/hadoop/hbase/regionserver/ScannerContext;)Z
     148: istore        24
     150: getstatic     #41                 // Field LOG:Lorg/slf4j/Logger;
     153: invokeinterface #133,  1          // InterfaceMethod org/slf4j/Logger.isDebugEnabled:()Z
     158: ifeq          166
     161: invokestatic  #134                // Method org/apache/hadoop/hbase/util/EnvironmentEdgeManager.currentTime:()J
     164: lstore        22
     166: aconst_null
     167: astore        29
     169: lconst_0
     170: lstore        30
     172: aload         16
     174: invokeinterface #144,  1          // InterfaceMethod java/util/List.iterator:()Ljava/util/Iterator;
     179: astore        32
     181: aload         32
     183: invokeinterface #31,  1           // InterfaceMethod java/util/Iterator.hasNext:()Z
     188: ifeq          439
     191: aload         32
     193: invokeinterface #32,  1           // InterfaceMethod java/util/Iterator.next:()Ljava/lang/Object;
     198: checkcast     #145                // class org/apache/hadoop/hbase/Cell
     201: astore        33
     203: iload         6
     205: ifeq          243
     208: aload         33
     210: invokeinterface #146,  1          // InterfaceMethod org/apache/hadoop/hbase/Cell.getSequenceId:()J
     215: lload         4
     217: lcmp
     218: ifgt          243
     221: aload         33
     223: astore        29
     225: aload         33
     227: invokeinterface #146,  1          // InterfaceMethod org/apache/hadoop/hbase/Cell.getSequenceId:()J
     232: lstore        30
     234: aload         33
     236: lconst_0
     237: invokestatic  #147                // Method org/apache/hadoop/hbase/PrivateCellUtil.setSequenceId:(Lorg/apache/hadoop/hbase/Cell;J)V
     240: goto          249
     243: aconst_null
     244: astore        29
     246: lconst_0
     247: lstore        30
     249: aload_3
     250: aload         33
     252: invokeinterface #148,  2          // InterfaceMethod org/apache/hadoop/hbase/regionserver/CellSink.append:(Lorg/apache/hadoop/hbase/Cell;)V
     257: aload         33
     259: invokeinterface #149,  1          // InterfaceMethod org/apache/hadoop/hbase/Cell.getSerializedSize:()I
     264: istore        34
     266: aload_0
     267: getfield      #24                 // Field progress:Lorg/apache/hadoop/hbase/regionserver/compactions/CompactionProgress;
     270: dup
     271: getfield      #150                // Field org/apache/hadoop/hbase/regionserver/compactions/CompactionProgress.currentCompactedKVs:J
     274: lconst_1
     275: ladd
     276: putfield      #150                // Field org/apache/hadoop/hbase/regionserver/compactions/CompactionProgress.currentCompactedKVs:J
     279: aload_0
     280: getfield      #24                 // Field progress:Lorg/apache/hadoop/hbase/regionserver/compactions/CompactionProgress;
     283: dup
     284: getfield      #151                // Field org/apache/hadoop/hbase/regionserver/compactions/CompactionProgress.totalCompactedSize:J
     287: iload         34
     289: i2l
     290: ladd
     291: putfield      #151                // Field org/apache/hadoop/hbase/regionserver/compactions/CompactionProgress.totalCompactedSize:J
     294: lload         14
     296: iload         34
     298: i2l
     299: ladd
     300: lstore        14
     302: getstatic     #41                 // Field LOG:Lorg/slf4j/Logger;
     305: invokeinterface #133,  1          // InterfaceMethod org/slf4j/Logger.isDebugEnabled:()Z
     310: ifeq          321
     313: lload         12
     315: iload         34
     317: i2l
     318: ladd
     319: lstore        12
     321: aload         7
     323: aload         21
     325: iload         34
     327: i2l
     328: invokeinterface #152,  4          // InterfaceMethod org/apache/hadoop/hbase/regionserver/throttle/ThroughputController.control:(Ljava/lang/String;J)J
     333: pop2
     334: lload         17
     336: lconst_0
     337: lcmp
     338: ifle          392
     341: lload         10
     343: iload         34
     345: i2l
     346: ladd
     347: lstore        10
     349: lload         10
     351: lload         17
     353: lcmp
     354: ifle          392
     357: lconst_0
     358: lstore        10
     360: aload_0
     361: getfield      #6                  // Field store:Lorg/apache/hadoop/hbase/regionserver/HStore;
     364: invokevirtual #153                // Method org/apache/hadoop/hbase/regionserver/HStore.areWritesEnabled:()Z
     367: ifne          392
     370: aload_0
     371: getfield      #24                 // Field progress:Lorg/apache/hadoop/hbase/regionserver/compactions/CompactionProgress;
     374: invokevirtual #154                // Method org/apache/hadoop/hbase/regionserver/compactions/CompactionProgress.cancel:()V
     377: iconst_0
     378: istore        35
     380: aload         7
     382: aload         21
     384: invokeinterface #155,  2          // InterfaceMethod org/apache/hadoop/hbase/regionserver/throttle/ThroughputController.finish:(Ljava/lang/String;)V
     389: iload         35
     391: ireturn
     392: aload         26
     394: ifnull        436
     397: lload         14
     399: lload         27
     401: lcmp
     402: ifle          436
     405: aload         29
     407: ifnull        417
     410: aload         29
     412: lload         30
     414: invokestatic  #147                // Method org/apache/hadoop/hbase/PrivateCellUtil.setSequenceId:(Lorg/apache/hadoop/hbase/Cell;J)V
     417: aload_3
     418: checkcast     #128                // class org/apache/hadoop/hbase/regionserver/ShipperListener
     421: invokeinterface #156,  1          // InterfaceMethod org/apache/hadoop/hbase/regionserver/ShipperListener.beforeShipped:()V
     426: aload         26
     428: invokeinterface #157,  1          // InterfaceMethod org/apache/hadoop/hbase/regionserver/KeyValueScanner.shipped:()V
     433: lconst_0
     434: lstore        14
     436: goto          181
     439: aload         29
     441: ifnull        451
     444: aload         29
     446: lload         30
     448: invokestatic  #147                // Method org/apache/hadoop/hbase/PrivateCellUtil.setSequenceId:(Lorg/apache/hadoop/hbase/Cell;J)V
     451: getstatic     #41                 // Field LOG:Lorg/slf4j/Logger;
     454: invokeinterface #133,  1          // InterfaceMethod org/slf4j/Logger.isDebugEnabled:()Z
     459: ifeq          567
     462: lload         22
     464: lload         19
     466: lsub
     467: ldc2_w        #158                // long 60000l
     470: lcmp
     471: iflt          567
     474: getstatic     #41                 // Field LOG:Lorg/slf4j/Logger;
     477: new           #42                 // class java/lang/StringBuilder
     480: dup
     481: invokespecial #43                 // Method java/lang/StringBuilder."<init>":()V
     484: ldc           #160                // String Compaction progress:
     486: invokevirtual #45                 // Method java/lang/StringBuilder.append:(Ljava/lang/String;)Ljava/lang/StringBuilder;
     489: aload         21
     491: invokevirtual #45                 // Method java/lang/StringBuilder.append:(Ljava/lang/String;)Ljava/lang/StringBuilder;
     494: ldc           #161                // String
     496: invokevirtual #45                 // Method java/lang/StringBuilder.append:(Ljava/lang/String;)Ljava/lang/StringBuilder;
     499: aload_0
     500: getfield      #24                 // Field progress:Lorg/apache/hadoop/hbase/regionserver/compactions/CompactionProgress;
     503: invokevirtual #47                 // Method java/lang/StringBuilder.append:(Ljava/lang/Object;)Ljava/lang/StringBuilder;
     506: ldc           #162                // String , rate=%.2f kB/sec
     508: iconst_1
     509: anewarray     #75                 // class java/lang/Object
     512: dup
     513: iconst_0
     514: lload         12
     516: l2d
     517: ldc2_w        #163                // double 1024.0d
     520: ddiv
     521: lload         22
     523: lload         19
     525: lsub
     526: l2d
     527: ldc2_w        #165                // double 1000.0d
     530: ddiv
     531: ddiv
     532: invokestatic  #167                // Method java/lang/Double.valueOf:(D)Ljava/lang/Double;
     535: aastore
     536: invokestatic  #168                // Method java/lang/String.format:(Ljava/lang/String;[Ljava/lang/Object;)Ljava/lang/String;
     539: invokevirtual #45                 // Method java/lang/StringBuilder.append:(Ljava/lang/String;)Ljava/lang/StringBuilder;
     542: ldc           #169                // String , throughputController is
     544: invokevirtual #45                 // Method java/lang/StringBuilder.append:(Ljava/lang/String;)Ljava/lang/StringBuilder;
     547: aload         7
     549: invokevirtual #47                 // Method java/lang/StringBuilder.append:(Ljava/lang/Object;)Ljava/lang/StringBuilder;
     552: invokevirtual #48                 // Method java/lang/StringBuilder.toString:()Ljava/lang/String;
     555: invokeinterface #170,  2          // InterfaceMethod org/slf4j/Logger.debug:(Ljava/lang/String;)V
     560: lload         22
     562: lstore        19
     564: lconst_0
     565: lstore        12
     567: aload         16
     569: invokeinterface #171,  1          // InterfaceMethod java/util/List.clear:()V
     574: iload         24
     576: ifne          138
     579: aload         7
     581: aload         21
     583: invokeinterface #155,  2          // InterfaceMethod org/apache/hadoop/hbase/regionserver/throttle/ThroughputController.finish:(Ljava/lang/String;)V
     588: goto          642
     591: astore        29
     593: aload_0
     594: getfield      #24                 // Field progress:Lorg/apache/hadoop/hbase/regionserver/compactions/CompactionProgress;
     597: invokevirtual #154                // Method org/apache/hadoop/hbase/regionserver/compactions/CompactionProgress.cancel:()V
     600: new           #113                // class java/io/InterruptedIOException
     603: dup
     604: new           #42                 // class java/lang/StringBuilder
     607: dup
     608: invokespecial #43                 // Method java/lang/StringBuilder."<init>":()V
     611: ldc           #173                // String Interrupted while control throughput of compacting
     613: invokevirtual #45                 // Method java/lang/StringBuilder.append:(Ljava/lang/String;)Ljava/lang/StringBuilder;
     616: aload         21
     618: invokevirtual #45                 // Method java/lang/StringBuilder.append:(Ljava/lang/String;)Ljava/lang/StringBuilder;
     621: invokevirtual #48                 // Method java/lang/StringBuilder.toString:()Ljava/lang/String;
     624: invokespecial #119                // Method java/io/InterruptedIOException."<init>":(Ljava/lang/String;)V
     627: athrow
     628: astore        36
     630: aload         7
     632: aload         21
     634: invokeinterface #155,  2          // InterfaceMethod org/apache/hadoop/hbase/regionserver/throttle/ThroughputController.finish:(Ljava/lang/String;)V
     639: aload         36
     641: athrow
     642: aload_0
     643: getfield      #24                 // Field progress:Lorg/apache/hadoop/hbase/regionserver/compactions/CompactionProgress;
     646: invokevirtual #174                // Method org/apache/hadoop/hbase/regionserver/compactions/CompactionProgress.complete:()V
     649: iconst_1
     650: ireturn
    Exception table:
       from    to  target type
         138   380   591   Class java/lang/InterruptedException
         392   579   591   Class java/lang/InterruptedException
         138   380   628   any
         392   579   628   any
         591   630   628   any

  protected org.apache.hadoop.hbase.regionserver.InternalScanner createScanner(org.apache.hadoop.hbase.regionserver.HStore, org.apache.hadoop.hbase.regionserver.ScanInfo, java.util.List<org.apache.hadoop.hbase.regionserver.StoreFileScanner>, org.apache.hadoop.hbase.regionserver.ScanType, long, long) throws java.io.IOException;
    Code:
       0: new           #175                // class org/apache/hadoop/hbase/regionserver/StoreScanner
       3: dup
       4: aload_1
       5: aload_2
       6: aload_3
       7: aload         4
       9: lload         5
      11: lload         7
      13: invokespecial #176                // Method org/apache/hadoop/hbase/regionserver/StoreScanner."<init>":(Lorg/apache/hadoop/hbase/regionserver/HStore;Lorg/apache/hadoop/hbase/regionserver/ScanInfo;Ljava/util/List;Lorg/apache/hadoop/hbase/regionserver/ScanType;JJ)V
      16: areturn

  protected org.apache.hadoop.hbase.regionserver.InternalScanner createScanner(org.apache.hadoop.hbase.regionserver.HStore, org.apache.hadoop.hbase.regionserver.ScanInfo, java.util.List<org.apache.hadoop.hbase.regionserver.StoreFileScanner>, long, long, byte[], byte[]) throws java.io.IOException;
    Code:
       0: new           #175                // class org/apache/hadoop/hbase/regionserver/StoreScanner
       3: dup
       4: aload_1
       5: aload_2
       6: aload_3
       7: lload         4
       9: lload         6
      11: aload         8
      13: aload         9
      15: invokespecial #177                // Method org/apache/hadoop/hbase/regionserver/StoreScanner."<init>":(Lorg/apache/hadoop/hbase/regionserver/HStore;Lorg/apache/hadoop/hbase/regionserver/ScanInfo;Ljava/util/List;JJ[B[B)V
      18: areturn

  static {};
    Code:
       0: ldc           #18                 // class org/apache/hadoop/hbase/regionserver/compactions/Compactor
       2: invokevirtual #178                // Method java/lang/Class.desiredAssertionStatus:()Z
       5: ifne          12
       8: iconst_1
       9: goto          13
      12: iconst_0
      13: putstatic     #122                // Field $assertionsDisabled:Z
      16: ldc           #18                 // class org/apache/hadoop/hbase/regionserver/compactions/Compactor
      18: invokestatic  #179                // Method org/slf4j/LoggerFactory.getLogger:(Ljava/lang/Class;)Lorg/slf4j/Logger;
      21: putstatic     #41                 // Field LOG:Lorg/slf4j/Logger;
      24: return
}
