Compiled from "CompletedProcedureRetainer.java"
class org.apache.hadoop.hbase.procedure2.CompletedProcedureRetainer<TEnvironment> {
  public org.apache.hadoop.hbase.procedure2.CompletedProcedureRetainer(org.apache.hadoop.hbase.procedure2.Procedure<TEnvironment>);
    Code:
       0: aload_0
       1: invokespecial #1                  // Method java/lang/Object."<init>":()V
       4: aload_0
       5: aload_1
       6: putfield      #2                  // Field procedure:Lorg/apache/hadoop/hbase/procedure2/Procedure;
       9: aload_0
      10: ldc2_w        #3                  // long -1l
      13: putfield      #5                  // Field clientAckTime:J
      16: return

  public org.apache.hadoop.hbase.procedure2.Procedure<TEnvironment> getProcedure();
    Code:
       0: aload_0
       1: getfield      #2                  // Field procedure:Lorg/apache/hadoop/hbase/procedure2/Procedure;
       4: areturn

  public boolean hasClientAckTime();
    Code:
       0: aload_0
       1: getfield      #5                  // Field clientAckTime:J
       4: ldc2_w        #3                  // long -1l
       7: lcmp
       8: ifeq          15
      11: iconst_1
      12: goto          16
      15: iconst_0
      16: ireturn

  public long getClientAckTime();
    Code:
       0: aload_0
       1: getfield      #5                  // Field clientAckTime:J
       4: lreturn

  public void setClientAckTime(long);
    Code:
       0: aload_0
       1: lload_1
       2: putfield      #5                  // Field clientAckTime:J
       5: return

  public boolean isExpired(long, long, long);
    Code:
       0: aload_0
       1: invokevirtual #6                  // Method hasClientAckTime:()Z
       4: ifeq          19
       7: lload_1
       8: aload_0
       9: invokevirtual #7                  // Method getClientAckTime:()J
      12: lsub
      13: lload         5
      15: lcmp
      16: ifge          33
      19: lload_1
      20: aload_0
      21: getfield      #2                  // Field procedure:Lorg/apache/hadoop/hbase/procedure2/Procedure;
      24: invokevirtual #8                  // Method org/apache/hadoop/hbase/procedure2/Procedure.getLastUpdate:()J
      27: lsub
      28: lload_3
      29: lcmp
      30: iflt          37
      33: iconst_1
      34: goto          38
      37: iconst_0
      38: ireturn
}
