Compiled from "Compactor.java"
public class org.apache.hadoop.hbase.regionserver.compactions.Compactor$FileDetails {
  public long maxKeyCount;

  public long earliestPutTs;

  public long latestPutTs;

  public long maxSeqId;

  public long maxMVCCReadpoint;

  public int maxTagsLength;

  public long minSeqIdToKeep;

  protected org.apache.hadoop.hbase.regionserver.compactions.Compactor$FileDetails();
    Code:
       0: aload_0
       1: invokespecial #1                  // Method java/lang/Object."<init>":()V
       4: aload_0
       5: lconst_0
       6: putfield      #2                  // Field maxKeyCount:J
       9: aload_0
      10: ldc2_w        #4                  // long 9223372036854775807l
      13: putfield      #6                  // Field earliestPutTs:J
      16: aload_0
      17: ldc2_w        #4                  // long 9223372036854775807l
      20: putfield      #7                  // Field latestPutTs:J
      23: aload_0
      24: lconst_0
      25: putfield      #8                  // Field maxSeqId:J
      28: aload_0
      29: lconst_0
      30: putfield      #9                  // Field maxMVCCReadpoint:J
      33: aload_0
      34: iconst_0
      35: putfield      #10                 // Field maxTagsLength:I
      38: aload_0
      39: lconst_0
      40: putfield      #11                 // Field minSeqIdToKeep:J
      43: return
}
