Compiled from "CompactionRequestImpl.java"
public class org.apache.hadoop.hbase.regionserver.compactions.CompactionRequestImpl implements org.apache.hadoop.hbase.regionserver.compactions.CompactionRequest {
  static final boolean $assertionsDisabled;

  public org.apache.hadoop.hbase.regionserver.compactions.CompactionRequestImpl(java.util.Collection<org.apache.hadoop.hbase.regionserver.HStoreFile>);
    Code:
       0: aload_0
       1: invokespecial #2                  // Method java/lang/Object."<init>":()V
       4: aload_0
       5: iconst_0
       6: putfield      #3                  // Field isOffPeak:Z
       9: aload_0
      10: getstatic     #4                  // Field org/apache/hadoop/hbase/regionserver/compactions/CompactionRequestImpl$DisplayCompactionType.MINOR:Lorg/apache/hadoop/hbase/regionserver/compactions/CompactionRequestImpl$DisplayCompactionType;
      13: putfield      #5                  // Field isMajor:Lorg/apache/hadoop/hbase/regionserver/compactions/CompactionRequestImpl$DisplayCompactionType;
      16: aload_0
      17: ldc           #6                  // int -2147483648
      19: putfield      #7                  // Field priority:I
      22: aload_0
      23: ldc           #8                  // String
      25: putfield      #9                  // Field regionName:Ljava/lang/String;
      28: aload_0
      29: ldc           #8                  // String
      31: putfield      #10                 // Field storeName:Ljava/lang/String;
      34: aload_0
      35: ldc2_w        #11                 // long -1l
      38: putfield      #13                 // Field totalSize:J
      41: aload_0
      42: getstatic     #14                 // Field org/apache/hadoop/hbase/regionserver/compactions/CompactionLifeCycleTracker.DUMMY:Lorg/apache/hadoop/hbase/regionserver/compactions/CompactionLifeCycleTracker;
      45: putfield      #15                 // Field tracker:Lorg/apache/hadoop/hbase/regionserver/compactions/CompactionLifeCycleTracker;
      48: aload_0
      49: invokestatic  #16                 // Method org/apache/hadoop/hbase/util/EnvironmentEdgeManager.currentTime:()J
      52: putfield      #17                 // Field selectionTime:J
      55: aload_0
      56: aload_1
      57: ldc           #18                 // String files for compaction can not null
      59: invokestatic  #19                 // Method org/apache/hbase/thirdparty/com/google/common/base/Preconditions.checkNotNull:(Ljava/lang/Object;Ljava/lang/Object;)Ljava/lang/Object;
      62: checkcast     #20                 // class java/util/Collection
      65: putfield      #21                 // Field filesToCompact:Ljava/util/Collection;
      68: aload_0
      69: invokespecial #22                 // Method recalculateSize:()V
      72: return

  public void updateFiles(java.util.Collection<org.apache.hadoop.hbase.regionserver.HStoreFile>);
    Code:
       0: aload_0
       1: aload_1
       2: ldc           #18                 // String files for compaction can not null
       4: invokestatic  #19                 // Method org/apache/hbase/thirdparty/com/google/common/base/Preconditions.checkNotNull:(Ljava/lang/Object;Ljava/lang/Object;)Ljava/lang/Object;
       7: checkcast     #20                 // class java/util/Collection
      10: putfield      #21                 // Field filesToCompact:Ljava/util/Collection;
      13: aload_0
      14: invokespecial #22                 // Method recalculateSize:()V
      17: return

  public java.util.Collection<org.apache.hadoop.hbase.regionserver.HStoreFile> getFiles();
    Code:
       0: aload_0
       1: getfield      #21                 // Field filesToCompact:Ljava/util/Collection;
       4: invokestatic  #23                 // Method java/util/Collections.unmodifiableCollection:(Ljava/util/Collection;)Ljava/util/Collection;
       7: areturn

  public void setDescription(java.lang.String, java.lang.String);
    Code:
       0: aload_0
       1: aload_1
       2: putfield      #9                  // Field regionName:Ljava/lang/String;
       5: aload_0
       6: aload_2
       7: putfield      #10                 // Field storeName:Ljava/lang/String;
      10: return

  public long getSize();
    Code:
       0: aload_0
       1: getfield      #13                 // Field totalSize:J
       4: lreturn

  public boolean isAllFiles();
    Code:
       0: aload_0
       1: getfield      #5                  // Field isMajor:Lorg/apache/hadoop/hbase/regionserver/compactions/CompactionRequestImpl$DisplayCompactionType;
       4: getstatic     #24                 // Field org/apache/hadoop/hbase/regionserver/compactions/CompactionRequestImpl$DisplayCompactionType.MAJOR:Lorg/apache/hadoop/hbase/regionserver/compactions/CompactionRequestImpl$DisplayCompactionType;
       7: if_acmpeq     20
      10: aload_0
      11: getfield      #5                  // Field isMajor:Lorg/apache/hadoop/hbase/regionserver/compactions/CompactionRequestImpl$DisplayCompactionType;
      14: getstatic     #25                 // Field org/apache/hadoop/hbase/regionserver/compactions/CompactionRequestImpl$DisplayCompactionType.ALL_FILES:Lorg/apache/hadoop/hbase/regionserver/compactions/CompactionRequestImpl$DisplayCompactionType;
      17: if_acmpne     24
      20: iconst_1
      21: goto          25
      24: iconst_0
      25: ireturn

  public boolean isMajor();
    Code:
       0: aload_0
       1: getfield      #5                  // Field isMajor:Lorg/apache/hadoop/hbase/regionserver/compactions/CompactionRequestImpl$DisplayCompactionType;
       4: getstatic     #24                 // Field org/apache/hadoop/hbase/regionserver/compactions/CompactionRequestImpl$DisplayCompactionType.MAJOR:Lorg/apache/hadoop/hbase/regionserver/compactions/CompactionRequestImpl$DisplayCompactionType;
       7: if_acmpne     14
      10: iconst_1
      11: goto          15
      14: iconst_0
      15: ireturn

  public int getPriority();
    Code:
       0: aload_0
       1: getfield      #7                  // Field priority:I
       4: ireturn

  public void setPriority(int);
    Code:
       0: aload_0
       1: iload_1
       2: putfield      #7                  // Field priority:I
       5: return

  public boolean isOffPeak();
    Code:
       0: aload_0
       1: getfield      #3                  // Field isOffPeak:Z
       4: ireturn

  public void setOffPeak(boolean);
    Code:
       0: aload_0
       1: iload_1
       2: putfield      #3                  // Field isOffPeak:Z
       5: return

  public long getSelectionTime();
    Code:
       0: aload_0
       1: getfield      #17                 // Field selectionTime:J
       4: lreturn

  public void setIsMajor(boolean, boolean);
    Code:
       0: getstatic     #26                 // Field $assertionsDisabled:Z
       3: ifne          22
       6: iload_2
       7: ifne          22
      10: iload_1
      11: ifeq          22
      14: new           #27                 // class java/lang/AssertionError
      17: dup
      18: invokespecial #28                 // Method java/lang/AssertionError."<init>":()V
      21: athrow
      22: aload_0
      23: iload_2
      24: ifne          33
      27: getstatic     #4                  // Field org/apache/hadoop/hbase/regionserver/compactions/CompactionRequestImpl$DisplayCompactionType.MINOR:Lorg/apache/hadoop/hbase/regionserver/compactions/CompactionRequestImpl$DisplayCompactionType;
      30: goto          46
      33: iload_1
      34: ifeq          43
      37: getstatic     #24                 // Field org/apache/hadoop/hbase/regionserver/compactions/CompactionRequestImpl$DisplayCompactionType.MAJOR:Lorg/apache/hadoop/hbase/regionserver/compactions/CompactionRequestImpl$DisplayCompactionType;
      40: goto          46
      43: getstatic     #25                 // Field org/apache/hadoop/hbase/regionserver/compactions/CompactionRequestImpl$DisplayCompactionType.ALL_FILES:Lorg/apache/hadoop/hbase/regionserver/compactions/CompactionRequestImpl$DisplayCompactionType;
      46: putfield      #5                  // Field isMajor:Lorg/apache/hadoop/hbase/regionserver/compactions/CompactionRequestImpl$DisplayCompactionType;
      49: return

  public void setTracker(org.apache.hadoop.hbase.regionserver.compactions.CompactionLifeCycleTracker);
    Code:
       0: aload_0
       1: aload_1
       2: putfield      #15                 // Field tracker:Lorg/apache/hadoop/hbase/regionserver/compactions/CompactionLifeCycleTracker;
       5: return

  public org.apache.hadoop.hbase.regionserver.compactions.CompactionLifeCycleTracker getTracker();
    Code:
       0: aload_0
       1: getfield      #15                 // Field tracker:Lorg/apache/hadoop/hbase/regionserver/compactions/CompactionLifeCycleTracker;
       4: areturn

  public int hashCode();
    Code:
       0: bipush        31
       2: istore_1
       3: iconst_1
       4: istore_2
       5: bipush        31
       7: iload_2
       8: imul
       9: aload_0
      10: getfield      #21                 // Field filesToCompact:Ljava/util/Collection;
      13: ifnonnull     20
      16: iconst_0
      17: goto          29
      20: aload_0
      21: getfield      #21                 // Field filesToCompact:Ljava/util/Collection;
      24: invokeinterface #29,  1           // InterfaceMethod java/util/Collection.hashCode:()I
      29: iadd
      30: istore_2
      31: bipush        31
      33: iload_2
      34: imul
      35: aload_0
      36: getfield      #5                  // Field isMajor:Lorg/apache/hadoop/hbase/regionserver/compactions/CompactionRequestImpl$DisplayCompactionType;
      39: ifnonnull     46
      42: iconst_0
      43: goto          53
      46: aload_0
      47: getfield      #5                  // Field isMajor:Lorg/apache/hadoop/hbase/regionserver/compactions/CompactionRequestImpl$DisplayCompactionType;
      50: invokevirtual #30                 // Method org/apache/hadoop/hbase/regionserver/compactions/CompactionRequestImpl$DisplayCompactionType.hashCode:()I
      53: iadd
      54: istore_2
      55: bipush        31
      57: iload_2
      58: imul
      59: aload_0
      60: getfield      #3                  // Field isOffPeak:Z
      63: ifeq          72
      66: sipush        1231
      69: goto          75
      72: sipush        1237
      75: iadd
      76: istore_2
      77: bipush        31
      79: iload_2
      80: imul
      81: aload_0
      82: getfield      #7                  // Field priority:I
      85: iadd
      86: istore_2
      87: bipush        31
      89: iload_2
      90: imul
      91: aload_0
      92: getfield      #9                  // Field regionName:Ljava/lang/String;
      95: ifnonnull     102
      98: iconst_0
      99: goto          109
     102: aload_0
     103: getfield      #9                  // Field regionName:Ljava/lang/String;
     106: invokevirtual #31                 // Method java/lang/String.hashCode:()I
     109: iadd
     110: istore_2
     111: bipush        31
     113: iload_2
     114: imul
     115: aload_0
     116: getfield      #17                 // Field selectionTime:J
     119: aload_0
     120: getfield      #17                 // Field selectionTime:J
     123: bipush        32
     125: lushr
     126: lxor
     127: l2i
     128: iadd
     129: istore_2
     130: bipush        31
     132: iload_2
     133: imul
     134: aload_0
     135: getfield      #10                 // Field storeName:Ljava/lang/String;
     138: ifnonnull     145
     141: iconst_0
     142: goto          152
     145: aload_0
     146: getfield      #10                 // Field storeName:Ljava/lang/String;
     149: invokevirtual #31                 // Method java/lang/String.hashCode:()I
     152: iadd
     153: istore_2
     154: bipush        31
     156: iload_2
     157: imul
     158: aload_0
     159: getfield      #13                 // Field totalSize:J
     162: aload_0
     163: getfield      #13                 // Field totalSize:J
     166: bipush        32
     168: lushr
     169: lxor
     170: l2i
     171: iadd
     172: istore_2
     173: bipush        31
     175: iload_2
     176: imul
     177: aload_0
     178: getfield      #15                 // Field tracker:Lorg/apache/hadoop/hbase/regionserver/compactions/CompactionLifeCycleTracker;
     181: ifnonnull     188
     184: iconst_0
     185: goto          195
     188: aload_0
     189: getfield      #15                 // Field tracker:Lorg/apache/hadoop/hbase/regionserver/compactions/CompactionLifeCycleTracker;
     192: invokevirtual #32                 // Method java/lang/Object.hashCode:()I
     195: iadd
     196: istore_2
     197: iload_2
     198: ireturn

  public boolean equals(java.lang.Object);
    Code:
       0: aload_0
       1: aload_1
       2: if_acmpne     7
       5: iconst_1
       6: ireturn
       7: aload_1
       8: ifnonnull     13
      11: iconst_0
      12: ireturn
      13: aload_0
      14: invokevirtual #33                 // Method java/lang/Object.getClass:()Ljava/lang/Class;
      17: aload_1
      18: invokevirtual #33                 // Method java/lang/Object.getClass:()Ljava/lang/Class;
      21: if_acmpeq     26
      24: iconst_0
      25: ireturn
      26: aload_1
      27: checkcast     #34                 // class org/apache/hadoop/hbase/regionserver/compactions/CompactionRequestImpl
      30: astore_2
      31: aload_0
      32: getfield      #21                 // Field filesToCompact:Ljava/util/Collection;
      35: ifnonnull     47
      38: aload_2
      39: getfield      #21                 // Field filesToCompact:Ljava/util/Collection;
      42: ifnull        65
      45: iconst_0
      46: ireturn
      47: aload_0
      48: getfield      #21                 // Field filesToCompact:Ljava/util/Collection;
      51: aload_2
      52: getfield      #21                 // Field filesToCompact:Ljava/util/Collection;
      55: invokeinterface #35,  2           // InterfaceMethod java/util/Collection.equals:(Ljava/lang/Object;)Z
      60: ifne          65
      63: iconst_0
      64: ireturn
      65: aload_0
      66: getfield      #5                  // Field isMajor:Lorg/apache/hadoop/hbase/regionserver/compactions/CompactionRequestImpl$DisplayCompactionType;
      69: aload_2
      70: getfield      #5                  // Field isMajor:Lorg/apache/hadoop/hbase/regionserver/compactions/CompactionRequestImpl$DisplayCompactionType;
      73: if_acmpeq     78
      76: iconst_0
      77: ireturn
      78: aload_0
      79: getfield      #3                  // Field isOffPeak:Z
      82: aload_2
      83: getfield      #3                  // Field isOffPeak:Z
      86: if_icmpeq     91
      89: iconst_0
      90: ireturn
      91: aload_0
      92: getfield      #7                  // Field priority:I
      95: aload_2
      96: getfield      #7                  // Field priority:I
      99: if_icmpeq     104
     102: iconst_0
     103: ireturn
     104: aload_0
     105: getfield      #9                  // Field regionName:Ljava/lang/String;
     108: ifnonnull     120
     111: aload_2
     112: getfield      #9                  // Field regionName:Ljava/lang/String;
     115: ifnull        136
     118: iconst_0
     119: ireturn
     120: aload_0
     121: getfield      #9                  // Field regionName:Ljava/lang/String;
     124: aload_2
     125: getfield      #9                  // Field regionName:Ljava/lang/String;
     128: invokevirtual #36                 // Method java/lang/String.equals:(Ljava/lang/Object;)Z
     131: ifne          136
     134: iconst_0
     135: ireturn
     136: aload_0
     137: getfield      #17                 // Field selectionTime:J
     140: aload_2
     141: getfield      #17                 // Field selectionTime:J
     144: lcmp
     145: ifeq          150
     148: iconst_0
     149: ireturn
     150: aload_0
     151: getfield      #10                 // Field storeName:Ljava/lang/String;
     154: ifnonnull     166
     157: aload_2
     158: getfield      #10                 // Field storeName:Ljava/lang/String;
     161: ifnull        182
     164: iconst_0
     165: ireturn
     166: aload_0
     167: getfield      #10                 // Field storeName:Ljava/lang/String;
     170: aload_2
     171: getfield      #10                 // Field storeName:Ljava/lang/String;
     174: invokevirtual #36                 // Method java/lang/String.equals:(Ljava/lang/Object;)Z
     177: ifne          182
     180: iconst_0
     181: ireturn
     182: aload_0
     183: getfield      #13                 // Field totalSize:J
     186: aload_2
     187: getfield      #13                 // Field totalSize:J
     190: lcmp
     191: ifeq          196
     194: iconst_0
     195: ireturn
     196: aload_0
     197: getfield      #15                 // Field tracker:Lorg/apache/hadoop/hbase/regionserver/compactions/CompactionLifeCycleTracker;
     200: ifnonnull     212
     203: aload_2
     204: getfield      #15                 // Field tracker:Lorg/apache/hadoop/hbase/regionserver/compactions/CompactionLifeCycleTracker;
     207: ifnull        228
     210: iconst_0
     211: ireturn
     212: aload_0
     213: getfield      #15                 // Field tracker:Lorg/apache/hadoop/hbase/regionserver/compactions/CompactionLifeCycleTracker;
     216: aload_2
     217: getfield      #15                 // Field tracker:Lorg/apache/hadoop/hbase/regionserver/compactions/CompactionLifeCycleTracker;
     220: invokevirtual #37                 // Method java/lang/Object.equals:(Ljava/lang/Object;)Z
     223: ifne          228
     226: iconst_0
     227: ireturn
     228: iconst_1
     229: ireturn

  public java.lang.String toString();
    Code:
       0: aload_0
       1: getfield      #21                 // Field filesToCompact:Ljava/util/Collection;
       4: invokeinterface #38,  1           // InterfaceMethod java/util/Collection.stream:()Ljava/util/stream/Stream;
       9: invokedynamic #39,  0             // InvokeDynamic #0:test:()Ljava/util/function/Predicate;
      14: invokeinterface #40,  2           // InterfaceMethod java/util/stream/Stream.filter:(Ljava/util/function/Predicate;)Ljava/util/stream/Stream;
      19: invokedynamic #41,  0             // InvokeDynamic #1:apply:()Ljava/util/function/Function;
      24: invokeinterface #42,  2           // InterfaceMethod java/util/stream/Stream.map:(Ljava/util/function/Function;)Ljava/util/stream/Stream;
      29: ldc           #43                 // String ,
      31: invokestatic  #44                 // Method java/util/stream/Collectors.joining:(Ljava/lang/CharSequence;)Ljava/util/stream/Collector;
      34: invokeinterface #45,  2           // InterfaceMethod java/util/stream/Stream.collect:(Ljava/util/stream/Collector;)Ljava/lang/Object;
      39: checkcast     #46                 // class java/lang/String
      42: astore_1
      43: new           #47                 // class java/lang/StringBuilder
      46: dup
      47: invokespecial #48                 // Method java/lang/StringBuilder."<init>":()V
      50: ldc           #49                 // String regionName=
      52: invokevirtual #50                 // Method java/lang/StringBuilder.append:(Ljava/lang/String;)Ljava/lang/StringBuilder;
      55: aload_0
      56: getfield      #9                  // Field regionName:Ljava/lang/String;
      59: invokevirtual #50                 // Method java/lang/StringBuilder.append:(Ljava/lang/String;)Ljava/lang/StringBuilder;
      62: ldc           #51                 // String , storeName=
      64: invokevirtual #50                 // Method java/lang/StringBuilder.append:(Ljava/lang/String;)Ljava/lang/StringBuilder;
      67: aload_0
      68: getfield      #10                 // Field storeName:Ljava/lang/String;
      71: invokevirtual #50                 // Method java/lang/StringBuilder.append:(Ljava/lang/String;)Ljava/lang/StringBuilder;
      74: ldc           #52                 // String , fileCount=
      76: invokevirtual #50                 // Method java/lang/StringBuilder.append:(Ljava/lang/String;)Ljava/lang/StringBuilder;
      79: aload_0
      80: invokevirtual #53                 // Method getFiles:()Ljava/util/Collection;
      83: invokeinterface #54,  1           // InterfaceMethod java/util/Collection.size:()I
      88: invokevirtual #55                 // Method java/lang/StringBuilder.append:(I)Ljava/lang/StringBuilder;
      91: ldc           #56                 // String , fileSize=
      93: invokevirtual #50                 // Method java/lang/StringBuilder.append:(Ljava/lang/String;)Ljava/lang/StringBuilder;
      96: aload_0
      97: getfield      #13                 // Field totalSize:J
     100: ldc           #8                  // String
     102: iconst_1
     103: invokestatic  #57                 // Method org/apache/hadoop/util/StringUtils$TraditionalBinaryPrefix.long2String:(JLjava/lang/String;I)Ljava/lang/String;
     106: invokevirtual #50                 // Method java/lang/StringBuilder.append:(Ljava/lang/String;)Ljava/lang/StringBuilder;
     109: aload_1
     110: invokevirtual #58                 // Method java/lang/String.isEmpty:()Z
     113: ifeq          121
     116: ldc           #8                  // String
     118: goto          145
     121: new           #47                 // class java/lang/StringBuilder
     124: dup
     125: invokespecial #48                 // Method java/lang/StringBuilder."<init>":()V
     128: ldc           #59                 // String  (
     130: invokevirtual #50                 // Method java/lang/StringBuilder.append:(Ljava/lang/String;)Ljava/lang/StringBuilder;
     133: aload_1
     134: invokevirtual #50                 // Method java/lang/StringBuilder.append:(Ljava/lang/String;)Ljava/lang/StringBuilder;
     137: ldc           #60                 // String )
     139: invokevirtual #50                 // Method java/lang/StringBuilder.append:(Ljava/lang/String;)Ljava/lang/StringBuilder;
     142: invokevirtual #61                 // Method java/lang/StringBuilder.toString:()Ljava/lang/String;
     145: invokevirtual #50                 // Method java/lang/StringBuilder.append:(Ljava/lang/String;)Ljava/lang/StringBuilder;
     148: ldc           #62                 // String , priority=
     150: invokevirtual #50                 // Method java/lang/StringBuilder.append:(Ljava/lang/String;)Ljava/lang/StringBuilder;
     153: aload_0
     154: getfield      #7                  // Field priority:I
     157: invokevirtual #55                 // Method java/lang/StringBuilder.append:(I)Ljava/lang/StringBuilder;
     160: ldc           #63                 // String , time=
     162: invokevirtual #50                 // Method java/lang/StringBuilder.append:(Ljava/lang/String;)Ljava/lang/StringBuilder;
     165: aload_0
     166: getfield      #17                 // Field selectionTime:J
     169: invokevirtual #64                 // Method java/lang/StringBuilder.append:(J)Ljava/lang/StringBuilder;
     172: invokevirtual #61                 // Method java/lang/StringBuilder.toString:()Ljava/lang/String;
     175: areturn

  static {};
    Code:
       0: ldc           #34                 // class org/apache/hadoop/hbase/regionserver/compactions/CompactionRequestImpl
       2: invokevirtual #71                 // Method java/lang/Class.desiredAssertionStatus:()Z
       5: ifne          12
       8: iconst_1
       9: goto          13
      12: iconst_0
      13: putstatic     #26                 // Field $assertionsDisabled:Z
      16: return
}
