Compiled from "CompactedHFilesDischarger.java"
public class org.apache.hadoop.hbase.regionserver.CompactedHFilesDischarger extends org.apache.hadoop.hbase.ScheduledChore {
  public org.apache.hadoop.hbase.regionserver.CompactedHFilesDischarger(int, org.apache.hadoop.hbase.Stoppable, org.apache.hadoop.hbase.regionserver.RegionServerServices);
    Code:
       0: aload_0
       1: ldc           #1                  // String CompactedHFilesCleaner
       3: aload_2
       4: iload_1
       5: invokespecial #2                  // Method org/apache/hadoop/hbase/ScheduledChore."<init>":(Ljava/lang/String;Lorg/apache/hadoop/hbase/Stoppable;I)V
       8: aload_0
       9: iconst_1
      10: putfield      #3                  // Field useExecutor:Z
      13: aload_0
      14: aload_3
      15: putfield      #4                  // Field regionServerServices:Lorg/apache/hadoop/hbase/regionserver/RegionServerServices;
      18: return

  public org.apache.hadoop.hbase.regionserver.CompactedHFilesDischarger(int, org.apache.hadoop.hbase.Stoppable, org.apache.hadoop.hbase.regionserver.RegionServerServices, boolean);
    Code:
       0: aload_0
       1: iload_1
       2: aload_2
       3: aload_3
       4: invokespecial #5                  // Method "<init>":(ILorg/apache/hadoop/hbase/Stoppable;Lorg/apache/hadoop/hbase/regionserver/RegionServerServices;)V
       7: aload_0
       8: iload         4
      10: putfield      #3                  // Field useExecutor:Z
      13: return

  boolean setUseExecutor(boolean);
    Code:
       0: aload_0
       1: getfield      #3                  // Field useExecutor:Z
       4: istore_2
       5: aload_0
       6: iload_1
       7: putfield      #3                  // Field useExecutor:Z
      10: iload_2
      11: ireturn

  public void chore();
    Code:
       0: aload_0
       1: getfield      #4                  // Field regionServerServices:Lorg/apache/hadoop/hbase/regionserver/RegionServerServices;
       4: ifnonnull     8
       7: return
       8: aload_0
       9: getfield      #4                  // Field regionServerServices:Lorg/apache/hadoop/hbase/regionserver/RegionServerServices;
      12: invokeinterface #6,  1            // InterfaceMethod org/apache/hadoop/hbase/regionserver/RegionServerServices.getRegions:()Ljava/util/List;
      17: astore_1
      18: aload_1
      19: ifnonnull     23
      22: return
      23: aload_1
      24: invokeinterface #7,  1            // InterfaceMethod java/util/List.iterator:()Ljava/util/Iterator;
      29: astore_2
      30: aload_2
      31: invokeinterface #8,  1            // InterfaceMethod java/util/Iterator.hasNext:()Z
      36: ifeq          328
      39: aload_2
      40: invokeinterface #9,  1            // InterfaceMethod java/util/Iterator.next:()Ljava/lang/Object;
      45: checkcast     #10                 // class org/apache/hadoop/hbase/regionserver/HRegion
      48: astore_3
      49: getstatic     #11                 // Field LOG:Lorg/slf4j/Logger;
      52: invokeinterface #12,  1           // InterfaceMethod org/slf4j/Logger.isTraceEnabled:()Z
      57: ifeq          90
      60: getstatic     #11                 // Field LOG:Lorg/slf4j/Logger;
      63: new           #13                 // class java/lang/StringBuilder
      66: dup
      67: invokespecial #14                 // Method java/lang/StringBuilder."<init>":()V
      70: ldc           #15                 // String Started compacted hfiles cleaner on
      72: invokevirtual #16                 // Method java/lang/StringBuilder.append:(Ljava/lang/String;)Ljava/lang/StringBuilder;
      75: aload_3
      76: invokevirtual #17                 // Method org/apache/hadoop/hbase/regionserver/HRegion.getRegionInfo:()Lorg/apache/hadoop/hbase/client/RegionInfo;
      79: invokevirtual #18                 // Method java/lang/StringBuilder.append:(Ljava/lang/Object;)Ljava/lang/StringBuilder;
      82: invokevirtual #19                 // Method java/lang/StringBuilder.toString:()Ljava/lang/String;
      85: invokeinterface #20,  2           // InterfaceMethod org/slf4j/Logger.trace:(Ljava/lang/String;)V
      90: aload_3
      91: invokevirtual #21                 // Method org/apache/hadoop/hbase/regionserver/HRegion.getStores:()Ljava/util/List;
      94: invokeinterface #7,  1            // InterfaceMethod java/util/List.iterator:()Ljava/util/Iterator;
      99: astore        4
     101: aload         4
     103: invokeinterface #8,  1            // InterfaceMethod java/util/Iterator.hasNext:()Z
     108: ifeq          284
     111: aload         4
     113: invokeinterface #9,  1            // InterfaceMethod java/util/Iterator.next:()Ljava/lang/Object;
     118: checkcast     #22                 // class org/apache/hadoop/hbase/regionserver/HStore
     121: astore        5
     123: aload_0
     124: getfield      #3                  // Field useExecutor:Z
     127: ifeq          172
     130: aload_0
     131: getfield      #4                  // Field regionServerServices:Lorg/apache/hadoop/hbase/regionserver/RegionServerServices;
     134: ifnull        172
     137: new           #23                 // class org/apache/hadoop/hbase/regionserver/CompactedHFilesDischargeHandler
     140: dup
     141: aload_0
     142: getfield      #4                  // Field regionServerServices:Lorg/apache/hadoop/hbase/regionserver/RegionServerServices;
     145: getstatic     #24                 // Field org/apache/hadoop/hbase/executor/EventType.RS_COMPACTED_FILES_DISCHARGER:Lorg/apache/hadoop/hbase/executor/EventType;
     148: aload         5
     150: invokespecial #25                 // Method org/apache/hadoop/hbase/regionserver/CompactedHFilesDischargeHandler."<init>":(Lorg/apache/hadoop/hbase/Server;Lorg/apache/hadoop/hbase/executor/EventType;Lorg/apache/hadoop/hbase/regionserver/HStore;)V
     153: astore        6
     155: aload_0
     156: getfield      #4                  // Field regionServerServices:Lorg/apache/hadoop/hbase/regionserver/RegionServerServices;
     159: invokeinterface #26,  1           // InterfaceMethod org/apache/hadoop/hbase/regionserver/RegionServerServices.getExecutorService:()Lorg/apache/hadoop/hbase/executor/ExecutorService;
     164: aload         6
     166: invokevirtual #27                 // Method org/apache/hadoop/hbase/executor/ExecutorService.submit:(Lorg/apache/hadoop/hbase/executor/EventHandler;)V
     169: goto          177
     172: aload         5
     174: invokevirtual #28                 // Method org/apache/hadoop/hbase/regionserver/HStore.closeAndArchiveCompactedFiles:()V
     177: getstatic     #11                 // Field LOG:Lorg/slf4j/Logger;
     180: invokeinterface #12,  1           // InterfaceMethod org/slf4j/Logger.isTraceEnabled:()Z
     185: ifeq          231
     188: getstatic     #11                 // Field LOG:Lorg/slf4j/Logger;
     191: new           #13                 // class java/lang/StringBuilder
     194: dup
     195: invokespecial #14                 // Method java/lang/StringBuilder."<init>":()V
     198: ldc           #29                 // String Completed archiving the compacted files for the region
     200: invokevirtual #16                 // Method java/lang/StringBuilder.append:(Ljava/lang/String;)Ljava/lang/StringBuilder;
     203: aload_3
     204: invokevirtual #17                 // Method org/apache/hadoop/hbase/regionserver/HRegion.getRegionInfo:()Lorg/apache/hadoop/hbase/client/RegionInfo;
     207: invokevirtual #18                 // Method java/lang/StringBuilder.append:(Ljava/lang/Object;)Ljava/lang/StringBuilder;
     210: ldc           #30                 // String  under the store
     212: invokevirtual #16                 // Method java/lang/StringBuilder.append:(Ljava/lang/String;)Ljava/lang/StringBuilder;
     215: aload         5
     217: invokevirtual #31                 // Method org/apache/hadoop/hbase/regionserver/HStore.getColumnFamilyName:()Ljava/lang/String;
     220: invokevirtual #16                 // Method java/lang/StringBuilder.append:(Ljava/lang/String;)Ljava/lang/StringBuilder;
     223: invokevirtual #19                 // Method java/lang/StringBuilder.toString:()Ljava/lang/String;
     226: invokeinterface #20,  2           // InterfaceMethod org/slf4j/Logger.trace:(Ljava/lang/String;)V
     231: goto          281
     234: astore        6
     236: getstatic     #11                 // Field LOG:Lorg/slf4j/Logger;
     239: new           #13                 // class java/lang/StringBuilder
     242: dup
     243: invokespecial #14                 // Method java/lang/StringBuilder."<init>":()V
     246: ldc           #33                 // String Exception while trying to close and archive the compacted store files of the store
     248: invokevirtual #16                 // Method java/lang/StringBuilder.append:(Ljava/lang/String;)Ljava/lang/StringBuilder;
     251: aload         5
     253: invokevirtual #31                 // Method org/apache/hadoop/hbase/regionserver/HStore.getColumnFamilyName:()Ljava/lang/String;
     256: invokevirtual #16                 // Method java/lang/StringBuilder.append:(Ljava/lang/String;)Ljava/lang/StringBuilder;
     259: ldc           #34                 // String  in the region
     261: invokevirtual #16                 // Method java/lang/StringBuilder.append:(Ljava/lang/String;)Ljava/lang/StringBuilder;
     264: aload_3
     265: invokevirtual #17                 // Method org/apache/hadoop/hbase/regionserver/HRegion.getRegionInfo:()Lorg/apache/hadoop/hbase/client/RegionInfo;
     268: invokevirtual #18                 // Method java/lang/StringBuilder.append:(Ljava/lang/Object;)Ljava/lang/StringBuilder;
     271: invokevirtual #19                 // Method java/lang/StringBuilder.toString:()Ljava/lang/String;
     274: aload         6
     276: invokeinterface #35,  3           // InterfaceMethod org/slf4j/Logger.error:(Ljava/lang/String;Ljava/lang/Throwable;)V
     281: goto          101
     284: getstatic     #11                 // Field LOG:Lorg/slf4j/Logger;
     287: invokeinterface #12,  1           // InterfaceMethod org/slf4j/Logger.isTraceEnabled:()Z
     292: ifeq          325
     295: getstatic     #11                 // Field LOG:Lorg/slf4j/Logger;
     298: new           #13                 // class java/lang/StringBuilder
     301: dup
     302: invokespecial #14                 // Method java/lang/StringBuilder."<init>":()V
     305: ldc           #36                 // String Completed the compacted hfiles cleaner for the region
     307: invokevirtual #16                 // Method java/lang/StringBuilder.append:(Ljava/lang/String;)Ljava/lang/StringBuilder;
     310: aload_3
     311: invokevirtual #17                 // Method org/apache/hadoop/hbase/regionserver/HRegion.getRegionInfo:()Lorg/apache/hadoop/hbase/client/RegionInfo;
     314: invokevirtual #18                 // Method java/lang/StringBuilder.append:(Ljava/lang/Object;)Ljava/lang/StringBuilder;
     317: invokevirtual #19                 // Method java/lang/StringBuilder.toString:()Ljava/lang/String;
     320: invokeinterface #20,  2           // InterfaceMethod org/slf4j/Logger.trace:(Ljava/lang/String;)V
     325: goto          30
     328: return
    Exception table:
       from    to  target type
         123   231   234   Class java/lang/Exception

  static {};
    Code:
       0: ldc           #37                 // class org/apache/hadoop/hbase/regionserver/CompactedHFilesDischarger
       2: invokestatic  #38                 // Method org/slf4j/LoggerFactory.getLogger:(Ljava/lang/Class;)Lorg/slf4j/Logger;
       5: putstatic     #11                 // Field LOG:Lorg/slf4j/Logger;
       8: return
}
