Compiled from "ConnectionId.java"
class org.apache.hadoop.hbase.ipc.ConnectionId {
  final org.apache.hadoop.hbase.security.User ticket;

  final java.lang.String serviceName;

  final java.net.InetSocketAddress address;

  public org.apache.hadoop.hbase.ipc.ConnectionId(org.apache.hadoop.hbase.security.User, java.lang.String, java.net.InetSocketAddress);
    Code:
       0: aload_0
       1: invokespecial #1                  // Method java/lang/Object."<init>":()V
       4: aload_0
       5: aload_3
       6: putfield      #2                  // Field address:Ljava/net/InetSocketAddress;
       9: aload_0
      10: aload_1
      11: putfield      #3                  // Field ticket:Lorg/apache/hadoop/hbase/security/User;
      14: aload_0
      15: aload_2
      16: putfield      #4                  // Field serviceName:Ljava/lang/String;
      19: return

  public java.lang.String getServiceName();
    Code:
       0: aload_0
       1: getfield      #4                  // Field serviceName:Ljava/lang/String;
       4: areturn

  public java.net.InetSocketAddress getAddress();
    Code:
       0: aload_0
       1: getfield      #2                  // Field address:Ljava/net/InetSocketAddress;
       4: areturn

  public org.apache.hadoop.hbase.security.User getTicket();
    Code:
       0: aload_0
       1: getfield      #3                  // Field ticket:Lorg/apache/hadoop/hbase/security/User;
       4: areturn

  public java.lang.String toString();
    Code:
       0: new           #5                  // class java/lang/StringBuilder
       3: dup
       4: invokespecial #6                  // Method java/lang/StringBuilder."<init>":()V
       7: aload_0
       8: getfield      #2                  // Field address:Ljava/net/InetSocketAddress;
      11: invokevirtual #7                  // Method java/net/InetSocketAddress.toString:()Ljava/lang/String;
      14: invokevirtual #8                  // Method java/lang/StringBuilder.append:(Ljava/lang/String;)Ljava/lang/StringBuilder;
      17: ldc           #9                  // String /
      19: invokevirtual #8                  // Method java/lang/StringBuilder.append:(Ljava/lang/String;)Ljava/lang/StringBuilder;
      22: aload_0
      23: getfield      #4                  // Field serviceName:Ljava/lang/String;
      26: invokevirtual #8                  // Method java/lang/StringBuilder.append:(Ljava/lang/String;)Ljava/lang/StringBuilder;
      29: ldc           #9                  // String /
      31: invokevirtual #8                  // Method java/lang/StringBuilder.append:(Ljava/lang/String;)Ljava/lang/StringBuilder;
      34: aload_0
      35: getfield      #3                  // Field ticket:Lorg/apache/hadoop/hbase/security/User;
      38: invokevirtual #10                 // Method java/lang/StringBuilder.append:(Ljava/lang/Object;)Ljava/lang/StringBuilder;
      41: invokevirtual #11                 // Method java/lang/StringBuilder.toString:()Ljava/lang/String;
      44: areturn

  public boolean equals(java.lang.Object);
    Code:
       0: aload_1
       1: instanceof    #12                 // class org/apache/hadoop/hbase/ipc/ConnectionId
       4: ifeq          78
       7: aload_1
       8: checkcast     #12                 // class org/apache/hadoop/hbase/ipc/ConnectionId
      11: astore_2
      12: aload_0
      13: getfield      #2                  // Field address:Ljava/net/InetSocketAddress;
      16: aload_2
      17: getfield      #2                  // Field address:Ljava/net/InetSocketAddress;
      20: invokevirtual #13                 // Method java/net/InetSocketAddress.equals:(Ljava/lang/Object;)Z
      23: ifeq          76
      26: aload_0
      27: getfield      #3                  // Field ticket:Lorg/apache/hadoop/hbase/security/User;
      30: ifnull        47
      33: aload_0
      34: getfield      #3                  // Field ticket:Lorg/apache/hadoop/hbase/security/User;
      37: aload_2
      38: getfield      #3                  // Field ticket:Lorg/apache/hadoop/hbase/security/User;
      41: invokevirtual #14                 // Method org/apache/hadoop/hbase/security/User.equals:(Ljava/lang/Object;)Z
      44: ifne          58
      47: aload_0
      48: getfield      #3                  // Field ticket:Lorg/apache/hadoop/hbase/security/User;
      51: aload_2
      52: getfield      #3                  // Field ticket:Lorg/apache/hadoop/hbase/security/User;
      55: if_acmpne     76
      58: aload_0
      59: getfield      #4                  // Field serviceName:Ljava/lang/String;
      62: aload_2
      63: getfield      #4                  // Field serviceName:Ljava/lang/String;
      66: invokestatic  #15                 // Method java/util/Objects.equals:(Ljava/lang/Object;Ljava/lang/Object;)Z
      69: ifeq          76
      72: iconst_1
      73: goto          77
      76: iconst_0
      77: ireturn
      78: iconst_0
      79: ireturn

  public int hashCode();
    Code:
       0: aload_0
       1: getfield      #3                  // Field ticket:Lorg/apache/hadoop/hbase/security/User;
       4: aload_0
       5: getfield      #4                  // Field serviceName:Ljava/lang/String;
       8: aload_0
       9: getfield      #2                  // Field address:Ljava/net/InetSocketAddress;
      12: invokestatic  #16                 // Method hashCode:(Lorg/apache/hadoop/hbase/security/User;Ljava/lang/String;Ljava/net/InetSocketAddress;)I
      15: ireturn

  public static int hashCode(org.apache.hadoop.hbase.security.User, java.lang.String, java.net.InetSocketAddress);
    Code:
       0: aload_2
       1: invokevirtual #17                 // Method java/net/InetSocketAddress.hashCode:()I
       4: ldc           #18                 // int 16777619
       6: ldc           #18                 // int 16777619
       8: aload_1
       9: invokevirtual #19                 // Method java/lang/String.hashCode:()I
      12: imul
      13: aload_0
      14: ifnonnull     21
      17: iconst_0
      18: goto          25
      21: aload_0
      22: invokevirtual #20                 // Method org/apache/hadoop/hbase/security/User.hashCode:()I
      25: ixor
      26: imul
      27: iadd
      28: ireturn
}
