Compiled from "ConnectionUtils.java"
public final class org.apache.hadoop.hbase.client.ConnectionUtils {
  static final org.apache.hadoop.hbase.client.NonceGenerator NO_NONCE_GENERATOR;

  static final byte[] MAX_BYTE_ARRAY;

  static final long SLEEP_DELTA_NS;

  public static long getPauseTime(long, int);
    Code:
       0: iload_2
       1: istore_3
       2: iload_3
       3: getstatic     #2                  // Field org/apache/hadoop/hbase/HConstants.RETRY_BACKOFF:[I
       6: arraylength
       7: if_icmplt     17
      10: getstatic     #2                  // Field org/apache/hadoop/hbase/HConstants.RETRY_BACKOFF:[I
      13: arraylength
      14: iconst_1
      15: isub
      16: istore_3
      17: iload_3
      18: ifge          23
      21: iconst_0
      22: istore_3
      23: lload_0
      24: getstatic     #2                  // Field org/apache/hadoop/hbase/HConstants.RETRY_BACKOFF:[I
      27: iload_3
      28: iaload
      29: i2l
      30: lmul
      31: lstore        4
      33: lload         4
      35: l2f
      36: invokestatic  #3                  // Method java/util/concurrent/ThreadLocalRandom.current:()Ljava/util/concurrent/ThreadLocalRandom;
      39: invokevirtual #4                  // Method java/util/concurrent/ThreadLocalRandom.nextFloat:()F
      42: fmul
      43: ldc           #5                  // float 0.01f
      45: fmul
      46: f2l
      47: lstore        6
      49: lload         4
      51: lload         6
      53: ladd
      54: lreturn

  public static org.apache.hadoop.hbase.client.NonceGenerator injectNonceGeneratorForTesting(org.apache.hadoop.hbase.client.ClusterConnection, org.apache.hadoop.hbase.client.NonceGenerator);
    Code:
       0: aload_0
       1: aload_1
       2: invokestatic  #6                  // Method org/apache/hadoop/hbase/client/ConnectionImplementation.injectNonceGeneratorForTesting:(Lorg/apache/hadoop/hbase/client/ClusterConnection;Lorg/apache/hadoop/hbase/client/NonceGenerator;)Lorg/apache/hadoop/hbase/client/NonceGenerator;
       5: areturn

  public static void setServerSideHConnectionRetriesConfig(org.apache.hadoop.conf.Configuration, java.lang.String, org.slf4j.Logger);
    Code:
       0: aload_0
       1: ldc           #8                  // String hbase.client.retries.number
       3: bipush        15
       5: invokevirtual #9                  // Method org/apache/hadoop/conf/Configuration.getInt:(Ljava/lang/String;I)I
       8: istore_3
       9: aload_0
      10: ldc           #10                 // String hbase.client.serverside.retries.multiplier
      12: iconst_3
      13: invokevirtual #9                  // Method org/apache/hadoop/conf/Configuration.getInt:(Ljava/lang/String;I)I
      16: istore        4
      18: iload_3
      19: iload         4
      21: imul
      22: istore        5
      24: aload_0
      25: ldc           #8                  // String hbase.client.retries.number
      27: iload         5
      29: invokevirtual #11                 // Method org/apache/hadoop/conf/Configuration.setInt:(Ljava/lang/String;I)V
      32: aload_2
      33: new           #12                 // class java/lang/StringBuilder
      36: dup
      37: invokespecial #13                 // Method java/lang/StringBuilder."<init>":()V
      40: aload_1
      41: invokevirtual #14                 // Method java/lang/StringBuilder.append:(Ljava/lang/String;)Ljava/lang/StringBuilder;
      44: ldc           #15                 // String  server-side Connection retries=
      46: invokevirtual #14                 // Method java/lang/StringBuilder.append:(Ljava/lang/String;)Ljava/lang/StringBuilder;
      49: iload         5
      51: invokevirtual #16                 // Method java/lang/StringBuilder.append:(I)Ljava/lang/StringBuilder;
      54: invokevirtual #17                 // Method java/lang/StringBuilder.toString:()Ljava/lang/String;
      57: invokeinterface #18,  2           // InterfaceMethod org/slf4j/Logger.info:(Ljava/lang/String;)V
      62: return

  public static org.apache.hadoop.hbase.client.ClusterConnection createShortCircuitConnection(org.apache.hadoop.conf.Configuration, java.util.concurrent.ExecutorService, org.apache.hadoop.hbase.security.User, org.apache.hadoop.hbase.ServerName, org.apache.hadoop.hbase.shaded.protobuf.generated.AdminProtos$AdminService$BlockingInterface, org.apache.hadoop.hbase.shaded.protobuf.generated.ClientProtos$ClientService$BlockingInterface) throws java.io.IOException;
    Code:
       0: aload_2
       1: ifnonnull     12
       4: aload_0
       5: invokestatic  #19                 // Method org/apache/hadoop/hbase/security/UserProvider.instantiate:(Lorg/apache/hadoop/conf/Configuration;)Lorg/apache/hadoop/hbase/security/UserProvider;
       8: invokevirtual #20                 // Method org/apache/hadoop/hbase/security/UserProvider.getCurrent:()Lorg/apache/hadoop/hbase/security/User;
      11: astore_2
      12: new           #21                 // class org/apache/hadoop/hbase/client/ConnectionUtils$ShortCircuitingClusterConnection
      15: dup
      16: aload_0
      17: aload_1
      18: aload_2
      19: aload_3
      20: aload         4
      22: aload         5
      24: aconst_null
      25: invokespecial #22                 // Method org/apache/hadoop/hbase/client/ConnectionUtils$ShortCircuitingClusterConnection."<init>":(Lorg/apache/hadoop/conf/Configuration;Ljava/util/concurrent/ExecutorService;Lorg/apache/hadoop/hbase/security/User;Lorg/apache/hadoop/hbase/ServerName;Lorg/apache/hadoop/hbase/shaded/protobuf/generated/AdminProtos$AdminService$BlockingInterface;Lorg/apache/hadoop/hbase/shaded/protobuf/generated/ClientProtos$ClientService$BlockingInterface;Lorg/apache/hadoop/hbase/client/ConnectionUtils$1;)V
      28: areturn

  public static void setupMasterlessConnection(org.apache.hadoop.conf.Configuration);
    Code:
       0: aload_0
       1: ldc           #24                 // String hbase.client.connection.impl
       3: ldc           #25                 // class org/apache/hadoop/hbase/client/ConnectionUtils$MasterlessConnection
       5: invokevirtual #26                 // Method java/lang/Class.getName:()Ljava/lang/String;
       8: invokevirtual #27                 // Method org/apache/hadoop/conf/Configuration.set:(Ljava/lang/String;Ljava/lang/String;)V
      11: return

  static int retries2Attempts(int);
    Code:
       0: iconst_1
       1: iload_0
       2: ldc           #29                 // int 2147483647
       4: if_icmpne     12
       7: ldc           #29                 // int 2147483647
       9: goto          15
      12: iload_0
      13: iconst_1
      14: iadd
      15: invokestatic  #30                 // Method java/lang/Math.max:(II)I
      18: ireturn

  static java.lang.String getStubKey(java.lang.String, org.apache.hadoop.hbase.ServerName, boolean);
    Code:
       0: aload_1
       1: invokevirtual #31                 // Method org/apache/hadoop/hbase/ServerName.getHostname:()Ljava/lang/String;
       4: astore_3
       5: aload_1
       6: invokevirtual #32                 // Method org/apache/hadoop/hbase/ServerName.getPort:()I
       9: istore        4
      11: iload_2
      12: ifeq          104
      15: aload_3
      16: invokestatic  #33                 // Method java/net/InetAddress.getByName:(Ljava/lang/String;)Ljava/net/InetAddress;
      19: astore        5
      21: new           #12                 // class java/lang/StringBuilder
      24: dup
      25: invokespecial #13                 // Method java/lang/StringBuilder."<init>":()V
      28: aload_0
      29: invokevirtual #14                 // Method java/lang/StringBuilder.append:(Ljava/lang/String;)Ljava/lang/StringBuilder;
      32: ldc           #34                 // String @
      34: invokevirtual #14                 // Method java/lang/StringBuilder.append:(Ljava/lang/String;)Ljava/lang/StringBuilder;
      37: aload_3
      38: invokevirtual #14                 // Method java/lang/StringBuilder.append:(Ljava/lang/String;)Ljava/lang/StringBuilder;
      41: ldc           #35                 // String -
      43: invokevirtual #14                 // Method java/lang/StringBuilder.append:(Ljava/lang/String;)Ljava/lang/StringBuilder;
      46: aload         5
      48: invokevirtual #36                 // Method java/net/InetAddress.getHostAddress:()Ljava/lang/String;
      51: invokevirtual #14                 // Method java/lang/StringBuilder.append:(Ljava/lang/String;)Ljava/lang/StringBuilder;
      54: ldc           #37                 // String :
      56: invokevirtual #14                 // Method java/lang/StringBuilder.append:(Ljava/lang/String;)Ljava/lang/StringBuilder;
      59: iload         4
      61: invokevirtual #16                 // Method java/lang/StringBuilder.append:(I)Ljava/lang/StringBuilder;
      64: invokevirtual #17                 // Method java/lang/StringBuilder.toString:()Ljava/lang/String;
      67: areturn
      68: astore        5
      70: getstatic     #39                 // Field LOG:Lorg/slf4j/Logger;
      73: new           #12                 // class java/lang/StringBuilder
      76: dup
      77: invokespecial #13                 // Method java/lang/StringBuilder."<init>":()V
      80: ldc           #40                 // String Can not resolve
      82: invokevirtual #14                 // Method java/lang/StringBuilder.append:(Ljava/lang/String;)Ljava/lang/StringBuilder;
      85: aload_3
      86: invokevirtual #14                 // Method java/lang/StringBuilder.append:(Ljava/lang/String;)Ljava/lang/StringBuilder;
      89: ldc           #41                 // String , please check your network
      91: invokevirtual #14                 // Method java/lang/StringBuilder.append:(Ljava/lang/String;)Ljava/lang/StringBuilder;
      94: invokevirtual #17                 // Method java/lang/StringBuilder.toString:()Ljava/lang/String;
      97: aload         5
      99: invokeinterface #42,  3           // InterfaceMethod org/slf4j/Logger.warn:(Ljava/lang/String;Ljava/lang/Throwable;)V
     104: new           #12                 // class java/lang/StringBuilder
     107: dup
     108: invokespecial #13                 // Method java/lang/StringBuilder."<init>":()V
     111: aload_0
     112: invokevirtual #14                 // Method java/lang/StringBuilder.append:(Ljava/lang/String;)Ljava/lang/StringBuilder;
     115: ldc           #34                 // String @
     117: invokevirtual #14                 // Method java/lang/StringBuilder.append:(Ljava/lang/String;)Ljava/lang/StringBuilder;
     120: aload_3
     121: invokevirtual #14                 // Method java/lang/StringBuilder.append:(Ljava/lang/String;)Ljava/lang/StringBuilder;
     124: ldc           #37                 // String :
     126: invokevirtual #14                 // Method java/lang/StringBuilder.append:(Ljava/lang/String;)Ljava/lang/StringBuilder;
     129: iload         4
     131: invokevirtual #16                 // Method java/lang/StringBuilder.append:(I)Ljava/lang/StringBuilder;
     134: invokevirtual #17                 // Method java/lang/StringBuilder.toString:()Ljava/lang/String;
     137: areturn
    Exception table:
       from    to  target type
          15    67    68   Class java/net/UnknownHostException

  static void checkHasFamilies(org.apache.hadoop.hbase.client.Mutation);
    Code:
       0: aload_0
       1: invokevirtual #43                 // Method org/apache/hadoop/hbase/client/Mutation.numFamilies:()I
       4: ifle          11
       7: iconst_1
       8: goto          12
      11: iconst_0
      12: ldc           #44                 // String Invalid arguments to %s, zero columns specified
      14: aload_0
      15: invokevirtual #45                 // Method org/apache/hadoop/hbase/client/Mutation.toString:()Ljava/lang/String;
      18: invokestatic  #46                 // Method org/apache/hbase/thirdparty/com/google/common/base/Preconditions.checkArgument:(ZLjava/lang/String;Ljava/lang/Object;)V
      21: return

  static byte[] createClosestRowAfter(byte[]);
    Code:
       0: aload_0
       1: aload_0
       2: arraylength
       3: iconst_1
       4: iadd
       5: invokestatic  #47                 // Method java/util/Arrays.copyOf:([BI)[B
       8: areturn

  static byte[] createCloseRowBefore(byte[]);
    Code:
       0: aload_0
       1: arraylength
       2: ifne          9
       5: getstatic     #48                 // Field MAX_BYTE_ARRAY:[B
       8: areturn
       9: aload_0
      10: aload_0
      11: arraylength
      12: iconst_1
      13: isub
      14: baload
      15: ifne          27
      18: aload_0
      19: aload_0
      20: arraylength
      21: iconst_1
      22: isub
      23: invokestatic  #47                 // Method java/util/Arrays.copyOf:([BI)[B
      26: areturn
      27: aload_0
      28: arraylength
      29: getstatic     #48                 // Field MAX_BYTE_ARRAY:[B
      32: arraylength
      33: iadd
      34: newarray       byte
      36: astore_1
      37: aload_0
      38: iconst_0
      39: aload_1
      40: iconst_0
      41: aload_0
      42: arraylength
      43: iconst_1
      44: isub
      45: invokestatic  #49                 // Method java/lang/System.arraycopy:(Ljava/lang/Object;ILjava/lang/Object;II)V
      48: aload_1
      49: aload_0
      50: arraylength
      51: iconst_1
      52: isub
      53: aload_0
      54: aload_0
      55: arraylength
      56: iconst_1
      57: isub
      58: baload
      59: sipush        255
      62: iand
      63: iconst_1
      64: isub
      65: i2b
      66: bastore
      67: getstatic     #48                 // Field MAX_BYTE_ARRAY:[B
      70: iconst_0
      71: aload_1
      72: aload_0
      73: arraylength
      74: getstatic     #48                 // Field MAX_BYTE_ARRAY:[B
      77: arraylength
      78: invokestatic  #49                 // Method java/lang/System.arraycopy:(Ljava/lang/Object;ILjava/lang/Object;II)V
      81: aload_1
      82: areturn

  static boolean isEmptyStartRow(byte[]);
    Code:
       0: aload_0
       1: getstatic     #50                 // Field org/apache/hadoop/hbase/HConstants.EMPTY_START_ROW:[B
       4: invokestatic  #51                 // Method org/apache/hadoop/hbase/util/Bytes.equals:([B[B)Z
       7: ireturn

  static boolean isEmptyStopRow(byte[]);
    Code:
       0: aload_0
       1: getstatic     #52                 // Field org/apache/hadoop/hbase/HConstants.EMPTY_END_ROW:[B
       4: invokestatic  #51                 // Method org/apache/hadoop/hbase/util/Bytes.equals:([B[B)Z
       7: ireturn

  static void resetController(org.apache.hadoop.hbase.ipc.HBaseRpcController, long, int);
    Code:
       0: aload_0
       1: invokeinterface #53,  1           // InterfaceMethod org/apache/hadoop/hbase/ipc/HBaseRpcController.reset:()V
       6: lload_1
       7: lconst_0
       8: lcmp
       9: iflt          32
      12: aload_0
      13: ldc2_w        #54                 // long 2147483647l
      16: getstatic     #56                 // Field java/util/concurrent/TimeUnit.NANOSECONDS:Ljava/util/concurrent/TimeUnit;
      19: lload_1
      20: invokevirtual #57                 // Method java/util/concurrent/TimeUnit.toMillis:(J)J
      23: invokestatic  #58                 // Method java/lang/Math.min:(JJ)J
      26: l2i
      27: invokeinterface #59,  2           // InterfaceMethod org/apache/hadoop/hbase/ipc/HBaseRpcController.setCallTimeout:(I)V
      32: aload_0
      33: iload_3
      34: invokeinterface #60,  2           // InterfaceMethod org/apache/hadoop/hbase/ipc/HBaseRpcController.setPriority:(I)V
      39: return

  static java.lang.Throwable translateException(java.lang.Throwable);
    Code:
       0: aload_0
       1: instanceof    #61                 // class java/lang/reflect/UndeclaredThrowableException
       4: ifeq          19
       7: aload_0
       8: invokevirtual #62                 // Method java/lang/Throwable.getCause:()Ljava/lang/Throwable;
      11: ifnull        19
      14: aload_0
      15: invokevirtual #62                 // Method java/lang/Throwable.getCause:()Ljava/lang/Throwable;
      18: astore_0
      19: aload_0
      20: instanceof    #63                 // class org/apache/hadoop/ipc/RemoteException
      23: ifeq          34
      26: aload_0
      27: checkcast     #63                 // class org/apache/hadoop/ipc/RemoteException
      30: invokevirtual #64                 // Method org/apache/hadoop/ipc/RemoteException.unwrapRemoteException:()Ljava/io/IOException;
      33: astore_0
      34: aload_0
      35: instanceof    #65                 // class org/apache/hbase/thirdparty/com/google/protobuf/ServiceException
      38: ifeq          56
      41: aload_0
      42: invokevirtual #62                 // Method java/lang/Throwable.getCause:()Ljava/lang/Throwable;
      45: ifnull        56
      48: aload_0
      49: invokevirtual #62                 // Method java/lang/Throwable.getCause:()Ljava/lang/Throwable;
      52: invokestatic  #66                 // Method translateException:(Ljava/lang/Throwable;)Ljava/lang/Throwable;
      55: astore_0
      56: aload_0
      57: areturn

  static long calcEstimatedSize(org.apache.hadoop.hbase.client.Result);
    Code:
       0: lconst_0
       1: lstore_1
       2: aload_0
       3: invokevirtual #67                 // Method org/apache/hadoop/hbase/client/Result.rawCells:()[Lorg/apache/hadoop/hbase/Cell;
       6: astore_3
       7: aload_3
       8: arraylength
       9: istore        4
      11: iconst_0
      12: istore        5
      14: iload         5
      16: iload         4
      18: if_icmpge     43
      21: aload_3
      22: iload         5
      24: aaload
      25: astore        6
      27: lload_1
      28: aload         6
      30: invokeinterface #68,  1           // InterfaceMethod org/apache/hadoop/hbase/Cell.heapSize:()J
      35: ladd
      36: lstore_1
      37: iinc          5, 1
      40: goto          14
      43: lload_1
      44: lreturn

  static org.apache.hadoop.hbase.client.Result filterCells(org.apache.hadoop.hbase.client.Result, org.apache.hadoop.hbase.Cell);
    Code:
       0: aload_1
       1: ifnonnull     6
       4: aload_0
       5: areturn
       6: aload_1
       7: aload_0
       8: invokevirtual #69                 // Method org/apache/hadoop/hbase/client/Result.getRow:()[B
      11: iconst_0
      12: aload_0
      13: invokevirtual #69                 // Method org/apache/hadoop/hbase/client/Result.getRow:()[B
      16: arraylength
      17: invokestatic  #70                 // Method org/apache/hadoop/hbase/PrivateCellUtil.matchingRows:(Lorg/apache/hadoop/hbase/Cell;[BII)Z
      20: ifne          25
      23: aload_0
      24: areturn
      25: aload_0
      26: invokevirtual #67                 // Method org/apache/hadoop/hbase/client/Result.rawCells:()[Lorg/apache/hadoop/hbase/Cell;
      29: astore_2
      30: aload_2
      31: aload_1
      32: invokestatic  #71                 // InterfaceMethod org/apache/hadoop/hbase/CellComparator.getInstance:()Lorg/apache/hadoop/hbase/CellComparator;
      35: dup
      36: invokevirtual #72                 // Method java/lang/Object.getClass:()Ljava/lang/Class;
      39: pop
      40: invokedynamic #73,  0             // InvokeDynamic #0:compare:(Lorg/apache/hadoop/hbase/CellComparator;)Ljava/util/Comparator;
      45: invokestatic  #74                 // Method java/util/Arrays.binarySearch:([Ljava/lang/Object;Ljava/lang/Object;Ljava/util/Comparator;)I
      48: istore_3
      49: iload_3
      50: ifge          61
      53: iload_3
      54: ineg
      55: iconst_1
      56: isub
      57: istore_3
      58: goto          64
      61: iinc          3, 1
      64: iload_3
      65: ifne          70
      68: aload_0
      69: areturn
      70: iload_3
      71: aload_2
      72: arraylength
      73: if_icmpne     78
      76: aconst_null
      77: areturn
      78: aload_2
      79: iload_3
      80: aload_2
      81: arraylength
      82: invokestatic  #75                 // Method java/util/Arrays.copyOfRange:([Ljava/lang/Object;II)[Ljava/lang/Object;
      85: checkcast     #76                 // class "[Lorg/apache/hadoop/hbase/Cell;"
      88: aconst_null
      89: aload_0
      90: invokevirtual #77                 // Method org/apache/hadoop/hbase/client/Result.isStale:()Z
      93: aload_0
      94: invokevirtual #78                 // Method org/apache/hadoop/hbase/client/Result.mayHaveMoreCellsInRow:()Z
      97: invokestatic  #79                 // Method org/apache/hadoop/hbase/client/Result.create:([Lorg/apache/hadoop/hbase/Cell;Ljava/lang/Boolean;ZZ)Lorg/apache/hadoop/hbase/client/Result;
     100: areturn

  static org.apache.hadoop.hbase.client.Get toCheckExistenceOnly(org.apache.hadoop.hbase.client.Get);
    Code:
       0: aload_0
       1: invokevirtual #80                 // Method org/apache/hadoop/hbase/client/Get.isCheckExistenceOnly:()Z
       4: ifeq          9
       7: aload_0
       8: areturn
       9: aload_0
      10: invokevirtual #72                 // Method java/lang/Object.getClass:()Ljava/lang/Class;
      13: iconst_1
      14: anewarray     #81                 // class java/lang/Object
      17: dup
      18: iconst_0
      19: aload_0
      20: aastore
      21: invokestatic  #82                 // Method org/apache/hadoop/hbase/util/ReflectionUtils.newInstance:(Ljava/lang/Class;[Ljava/lang/Object;)Ljava/lang/Object;
      24: checkcast     #83                 // class org/apache/hadoop/hbase/client/Get
      27: iconst_1
      28: invokevirtual #84                 // Method org/apache/hadoop/hbase/client/Get.setCheckExistenceOnly:(Z)Lorg/apache/hadoop/hbase/client/Get;
      31: areturn

  static java.util.List<org.apache.hadoop.hbase.client.Get> toCheckExistenceOnly(java.util.List<org.apache.hadoop.hbase.client.Get>);
    Code:
       0: aload_0
       1: invokeinterface #85,  1           // InterfaceMethod java/util/List.stream:()Ljava/util/stream/Stream;
       6: invokedynamic #86,  0             // InvokeDynamic #1:apply:()Ljava/util/function/Function;
      11: invokeinterface #87,  2           // InterfaceMethod java/util/stream/Stream.map:(Ljava/util/function/Function;)Ljava/util/stream/Stream;
      16: invokestatic  #88                 // Method java/util/stream/Collectors.toList:()Ljava/util/stream/Collector;
      19: invokeinterface #89,  2           // InterfaceMethod java/util/stream/Stream.collect:(Ljava/util/stream/Collector;)Ljava/lang/Object;
      24: checkcast     #90                 // class java/util/List
      27: areturn

  static org.apache.hadoop.hbase.client.RegionLocateType getLocateType(org.apache.hadoop.hbase.client.Scan);
    Code:
       0: aload_0
       1: invokevirtual #91                 // Method org/apache/hadoop/hbase/client/Scan.isReversed:()Z
       4: ifeq          38
       7: aload_0
       8: invokevirtual #92                 // Method org/apache/hadoop/hbase/client/Scan.getStartRow:()[B
      11: invokestatic  #93                 // Method isEmptyStartRow:([B)Z
      14: ifeq          21
      17: getstatic     #94                 // Field org/apache/hadoop/hbase/client/RegionLocateType.BEFORE:Lorg/apache/hadoop/hbase/client/RegionLocateType;
      20: areturn
      21: aload_0
      22: invokevirtual #95                 // Method org/apache/hadoop/hbase/client/Scan.includeStartRow:()Z
      25: ifeq          34
      28: getstatic     #96                 // Field org/apache/hadoop/hbase/client/RegionLocateType.CURRENT:Lorg/apache/hadoop/hbase/client/RegionLocateType;
      31: goto          37
      34: getstatic     #94                 // Field org/apache/hadoop/hbase/client/RegionLocateType.BEFORE:Lorg/apache/hadoop/hbase/client/RegionLocateType;
      37: areturn
      38: aload_0
      39: invokevirtual #95                 // Method org/apache/hadoop/hbase/client/Scan.includeStartRow:()Z
      42: ifeq          51
      45: getstatic     #96                 // Field org/apache/hadoop/hbase/client/RegionLocateType.CURRENT:Lorg/apache/hadoop/hbase/client/RegionLocateType;
      48: goto          54
      51: getstatic     #97                 // Field org/apache/hadoop/hbase/client/RegionLocateType.AFTER:Lorg/apache/hadoop/hbase/client/RegionLocateType;
      54: areturn

  static boolean noMoreResultsForScan(org.apache.hadoop.hbase.client.Scan, org.apache.hadoop.hbase.client.RegionInfo);
    Code:
       0: aload_1
       1: invokeinterface #98,  1           // InterfaceMethod org/apache/hadoop/hbase/client/RegionInfo.getEndKey:()[B
       6: invokestatic  #99                 // Method isEmptyStopRow:([B)Z
       9: ifeq          14
      12: iconst_1
      13: ireturn
      14: aload_0
      15: invokevirtual #100                // Method org/apache/hadoop/hbase/client/Scan.getStopRow:()[B
      18: invokestatic  #99                 // Method isEmptyStopRow:([B)Z
      21: ifeq          26
      24: iconst_0
      25: ireturn
      26: aload_1
      27: invokeinterface #98,  1           // InterfaceMethod org/apache/hadoop/hbase/client/RegionInfo.getEndKey:()[B
      32: aload_0
      33: invokevirtual #100                // Method org/apache/hadoop/hbase/client/Scan.getStopRow:()[B
      36: invokestatic  #101                // Method org/apache/hadoop/hbase/util/Bytes.compareTo:([B[B)I
      39: istore_2
      40: iload_2
      41: ifgt          55
      44: iload_2
      45: ifne          59
      48: aload_0
      49: invokevirtual #102                // Method org/apache/hadoop/hbase/client/Scan.includeStopRow:()Z
      52: ifne          59
      55: iconst_1
      56: goto          60
      59: iconst_0
      60: ireturn

  static boolean noMoreResultsForReverseScan(org.apache.hadoop.hbase.client.Scan, org.apache.hadoop.hbase.client.RegionInfo);
    Code:
       0: aload_1
       1: invokeinterface #103,  1          // InterfaceMethod org/apache/hadoop/hbase/client/RegionInfo.getStartKey:()[B
       6: invokestatic  #93                 // Method isEmptyStartRow:([B)Z
       9: ifeq          14
      12: iconst_1
      13: ireturn
      14: aload_0
      15: invokevirtual #100                // Method org/apache/hadoop/hbase/client/Scan.getStopRow:()[B
      18: invokestatic  #99                 // Method isEmptyStopRow:([B)Z
      21: ifeq          26
      24: iconst_0
      25: ireturn
      26: aload_1
      27: invokeinterface #103,  1          // InterfaceMethod org/apache/hadoop/hbase/client/RegionInfo.getStartKey:()[B
      32: aload_0
      33: invokevirtual #100                // Method org/apache/hadoop/hbase/client/Scan.getStopRow:()[B
      36: invokestatic  #101                // Method org/apache/hadoop/hbase/util/Bytes.compareTo:([B[B)I
      39: ifgt          46
      42: iconst_1
      43: goto          47
      46: iconst_0
      47: ireturn

  static <T> java.util.concurrent.CompletableFuture<java.util.List<T>> allOf(java.util.List<java.util.concurrent.CompletableFuture<T>>);
    Code:
       0: aload_0
       1: iconst_0
       2: anewarray     #104                // class java/util/concurrent/CompletableFuture
       5: invokeinterface #105,  2          // InterfaceMethod java/util/List.toArray:([Ljava/lang/Object;)[Ljava/lang/Object;
      10: checkcast     #106                // class "[Ljava/util/concurrent/CompletableFuture;"
      13: invokestatic  #107                // Method java/util/concurrent/CompletableFuture.allOf:([Ljava/util/concurrent/CompletableFuture;)Ljava/util/concurrent/CompletableFuture;
      16: aload_0
      17: invokedynamic #108,  0            // InvokeDynamic #2:apply:(Ljava/util/List;)Ljava/util/function/Function;
      22: invokevirtual #109                // Method java/util/concurrent/CompletableFuture.thenApply:(Ljava/util/function/Function;)Ljava/util/concurrent/CompletableFuture;
      25: areturn

  public static org.apache.hadoop.hbase.client.ScanResultCache createScanResultCache(org.apache.hadoop.hbase.client.Scan);
    Code:
       0: aload_0
       1: invokevirtual #110                // Method org/apache/hadoop/hbase/client/Scan.getAllowPartialResults:()Z
       4: ifeq          15
       7: new           #111                // class org/apache/hadoop/hbase/client/AllowPartialScanResultCache
      10: dup
      11: invokespecial #112                // Method org/apache/hadoop/hbase/client/AllowPartialScanResultCache."<init>":()V
      14: areturn
      15: aload_0
      16: invokevirtual #113                // Method org/apache/hadoop/hbase/client/Scan.getBatch:()I
      19: ifle          34
      22: new           #114                // class org/apache/hadoop/hbase/client/BatchScanResultCache
      25: dup
      26: aload_0
      27: invokevirtual #113                // Method org/apache/hadoop/hbase/client/Scan.getBatch:()I
      30: invokespecial #115                // Method org/apache/hadoop/hbase/client/BatchScanResultCache."<init>":(I)V
      33: areturn
      34: new           #116                // class org/apache/hadoop/hbase/client/CompleteScanResultCache
      37: dup
      38: invokespecial #117                // Method org/apache/hadoop/hbase/client/CompleteScanResultCache."<init>":()V
      41: areturn

  static boolean isRemote(java.lang.String);
    Code:
       0: aload_0
       1: getstatic     #122                // Field MY_ADDRESS:Ljava/lang/String;
       4: invokevirtual #123                // Method java/lang/String.equalsIgnoreCase:(Ljava/lang/String;)Z
       7: ifne          14
      10: iconst_1
      11: goto          15
      14: iconst_0
      15: ireturn

  static void incRPCCallsMetrics(org.apache.hadoop.hbase.client.metrics.ScanMetrics, boolean);
    Code:
       0: aload_0
       1: ifnonnull     5
       4: return
       5: aload_0
       6: getfield      #124                // Field org/apache/hadoop/hbase/client/metrics/ScanMetrics.countOfRPCcalls:Ljava/util/concurrent/atomic/AtomicLong;
       9: invokevirtual #125                // Method java/util/concurrent/atomic/AtomicLong.incrementAndGet:()J
      12: pop2
      13: iload_1
      14: ifeq          25
      17: aload_0
      18: getfield      #126                // Field org/apache/hadoop/hbase/client/metrics/ScanMetrics.countOfRemoteRPCcalls:Ljava/util/concurrent/atomic/AtomicLong;
      21: invokevirtual #125                // Method java/util/concurrent/atomic/AtomicLong.incrementAndGet:()J
      24: pop2
      25: return

  static void incRPCRetriesMetrics(org.apache.hadoop.hbase.client.metrics.ScanMetrics, boolean);
    Code:
       0: aload_0
       1: ifnonnull     5
       4: return
       5: aload_0
       6: getfield      #127                // Field org/apache/hadoop/hbase/client/metrics/ScanMetrics.countOfRPCRetries:Ljava/util/concurrent/atomic/AtomicLong;
       9: invokevirtual #125                // Method java/util/concurrent/atomic/AtomicLong.incrementAndGet:()J
      12: pop2
      13: iload_1
      14: ifeq          25
      17: aload_0
      18: getfield      #128                // Field org/apache/hadoop/hbase/client/metrics/ScanMetrics.countOfRemoteRPCRetries:Ljava/util/concurrent/atomic/AtomicLong;
      21: invokevirtual #125                // Method java/util/concurrent/atomic/AtomicLong.incrementAndGet:()J
      24: pop2
      25: return

  static void updateResultsMetrics(org.apache.hadoop.hbase.client.metrics.ScanMetrics, org.apache.hadoop.hbase.client.Result[], boolean);
    Code:
       0: aload_0
       1: ifnull        13
       4: aload_1
       5: ifnull        13
       8: aload_1
       9: arraylength
      10: ifne          14
      13: return
      14: lconst_0
      15: lstore_3
      16: aload_1
      17: astore        5
      19: aload         5
      21: arraylength
      22: istore        6
      24: iconst_0
      25: istore        7
      27: iload         7
      29: iload         6
      31: if_icmpge     91
      34: aload         5
      36: iload         7
      38: aaload
      39: astore        8
      41: aload         8
      43: invokevirtual #67                 // Method org/apache/hadoop/hbase/client/Result.rawCells:()[Lorg/apache/hadoop/hbase/Cell;
      46: astore        9
      48: aload         9
      50: arraylength
      51: istore        10
      53: iconst_0
      54: istore        11
      56: iload         11
      58: iload         10
      60: if_icmpge     85
      63: aload         9
      65: iload         11
      67: aaload
      68: astore        12
      70: lload_3
      71: aload         12
      73: invokestatic  #129                // Method org/apache/hadoop/hbase/PrivateCellUtil.estimatedSerializedSizeOf:(Lorg/apache/hadoop/hbase/Cell;)I
      76: i2l
      77: ladd
      78: lstore_3
      79: iinc          11, 1
      82: goto          56
      85: iinc          7, 1
      88: goto          27
      91: aload_0
      92: getfield      #130                // Field org/apache/hadoop/hbase/client/metrics/ScanMetrics.countOfBytesInResults:Ljava/util/concurrent/atomic/AtomicLong;
      95: lload_3
      96: invokevirtual #131                // Method java/util/concurrent/atomic/AtomicLong.addAndGet:(J)J
      99: pop2
     100: iload_2
     101: ifeq          113
     104: aload_0
     105: getfield      #132                // Field org/apache/hadoop/hbase/client/metrics/ScanMetrics.countOfBytesInRemoteResults:Ljava/util/concurrent/atomic/AtomicLong;
     108: lload_3
     109: invokevirtual #131                // Method java/util/concurrent/atomic/AtomicLong.addAndGet:(J)J
     112: pop2
     113: return

  static void updateServerSideMetrics(org.apache.hadoop.hbase.client.metrics.ScanMetrics, org.apache.hadoop.hbase.shaded.protobuf.generated.ClientProtos$ScanResponse);
    Code:
       0: aload_0
       1: ifnull        15
       4: aload_1
       5: ifnull        15
       8: aload_1
       9: invokevirtual #133                // Method org/apache/hadoop/hbase/shaded/protobuf/generated/ClientProtos$ScanResponse.hasScanMetrics:()Z
      12: ifne          16
      15: return
      16: aload_1
      17: invokestatic  #134                // Method org/apache/hadoop/hbase/shaded/protobuf/ResponseConverter.getScanMetrics:(Lorg/apache/hadoop/hbase/shaded/protobuf/generated/ClientProtos$ScanResponse;)Ljava/util/Map;
      20: aload_0
      21: dup
      22: invokevirtual #72                 // Method java/lang/Object.getClass:()Ljava/lang/Class;
      25: pop
      26: invokedynamic #135,  0            // InvokeDynamic #3:accept:(Lorg/apache/hadoop/hbase/client/metrics/ScanMetrics;)Ljava/util/function/BiConsumer;
      31: invokeinterface #136,  2          // InterfaceMethod java/util/Map.forEach:(Ljava/util/function/BiConsumer;)V
      36: return

  static void incRegionCountMetrics(org.apache.hadoop.hbase.client.metrics.ScanMetrics);
    Code:
       0: aload_0
       1: ifnonnull     5
       4: return
       5: aload_0
       6: getfield      #137                // Field org/apache/hadoop/hbase/client/metrics/ScanMetrics.countOfRegions:Ljava/util/concurrent/atomic/AtomicLong;
       9: invokevirtual #125                // Method java/util/concurrent/atomic/AtomicLong.incrementAndGet:()J
      12: pop2
      13: return

  static <T> java.util.concurrent.CompletableFuture<T> timelineConsistentRead(org.apache.hadoop.hbase.client.AsyncRegionLocator, org.apache.hadoop.hbase.TableName, org.apache.hadoop.hbase.client.Query, byte[], org.apache.hadoop.hbase.client.RegionLocateType, java.util.function.Function<java.lang.Integer, java.util.concurrent.CompletableFuture<T>>, long, long, org.apache.hbase.thirdparty.io.netty.util.Timer, java.util.Optional<org.apache.hadoop.hbase.client.MetricsConnection>);
    Code:
       0: aload_2
       1: invokevirtual #148                // Method org/apache/hadoop/hbase/client/Query.getConsistency:()Lorg/apache/hadoop/hbase/client/Consistency;
       4: getstatic     #149                // Field org/apache/hadoop/hbase/client/Consistency.STRONG:Lorg/apache/hadoop/hbase/client/Consistency;
       7: if_acmpne     25
      10: aload         5
      12: iconst_0
      13: invokestatic  #143                // Method java/lang/Integer.valueOf:(I)Ljava/lang/Integer;
      16: invokeinterface #144,  2          // InterfaceMethod java/util/function/Function.apply:(Ljava/lang/Object;)Ljava/lang/Object;
      21: checkcast     #104                // class java/util/concurrent/CompletableFuture
      24: areturn
      25: aload_2
      26: invokevirtual #151                // Method org/apache/hadoop/hbase/client/Query.getReplicaId:()I
      29: iflt          50
      32: aload         5
      34: aload_2
      35: invokevirtual #151                // Method org/apache/hadoop/hbase/client/Query.getReplicaId:()I
      38: invokestatic  #143                // Method java/lang/Integer.valueOf:(I)Ljava/lang/Integer;
      41: invokeinterface #144,  2          // InterfaceMethod java/util/function/Function.apply:(Ljava/lang/Object;)Ljava/lang/Object;
      46: checkcast     #104                // class java/util/concurrent/CompletableFuture
      49: areturn
      50: aload         5
      52: iconst_0
      53: invokestatic  #143                // Method java/lang/Integer.valueOf:(I)Ljava/lang/Integer;
      56: invokeinterface #144,  2          // InterfaceMethod java/util/function/Function.apply:(Ljava/lang/Object;)Ljava/lang/Object;
      61: checkcast     #104                // class java/util/concurrent/CompletableFuture
      64: astore        12
      66: new           #104                // class java/util/concurrent/CompletableFuture
      69: dup
      70: invokespecial #152                // Method java/util/concurrent/CompletableFuture."<init>":()V
      73: astore        13
      75: aload         12
      77: aload         13
      79: invokestatic  #153                // Method java/util/Optional.empty:()Ljava/util/Optional;
      82: invokestatic  #147                // Method connect:(Ljava/util/concurrent/CompletableFuture;Ljava/util/concurrent/CompletableFuture;Ljava/util/Optional;)V
      85: invokestatic  #154                // Method java/lang/System.nanoTime:()J
      88: lstore        14
      90: aload_0
      91: aload_1
      92: aload_3
      93: aload         4
      95: iconst_0
      96: lload         6
      98: invokevirtual #155                // Method org/apache/hadoop/hbase/client/AsyncRegionLocator.getRegionLocations:(Lorg/apache/hadoop/hbase/TableName;[BLorg/apache/hadoop/hbase/client/RegionLocateType;ZJ)Ljava/util/concurrent/CompletableFuture;
     101: aload_1
     102: aload_3
     103: aload         4
     105: lload         8
     107: lload         14
     109: aload         5
     111: aload         13
     113: aload         11
     115: aload         10
     117: invokedynamic #156,  0            // InvokeDynamic #7:accept:(Lorg/apache/hadoop/hbase/TableName;[BLorg/apache/hadoop/hbase/client/RegionLocateType;JJLjava/util/function/Function;Ljava/util/concurrent/CompletableFuture;Ljava/util/Optional;Lorg/apache/hbase/thirdparty/io/netty/util/Timer;)Ljava/util/function/BiConsumer;
     122: invokestatic  #139                // Method org/apache/hadoop/hbase/util/FutureUtils.addListener:(Ljava/util/concurrent/CompletableFuture;Ljava/util/function/BiConsumer;)V
     125: aload         13
     127: areturn

  static void validatePut(org.apache.hadoop.hbase.client.Put, int) throws java.lang.IllegalArgumentException;
    Code:
       0: aload_0
       1: invokevirtual #157                // Method org/apache/hadoop/hbase/client/Put.isEmpty:()Z
       4: ifeq          17
       7: new           #158                // class java/lang/IllegalArgumentException
      10: dup
      11: ldc           #159                // String No columns to insert
      13: invokespecial #160                // Method java/lang/IllegalArgumentException."<init>":(Ljava/lang/String;)V
      16: athrow
      17: iload_1
      18: ifle          112
      21: aload_0
      22: invokevirtual #161                // Method org/apache/hadoop/hbase/client/Put.getFamilyCellMap:()Ljava/util/NavigableMap;
      25: invokeinterface #162,  1          // InterfaceMethod java/util/NavigableMap.values:()Ljava/util/Collection;
      30: invokeinterface #163,  1          // InterfaceMethod java/util/Collection.iterator:()Ljava/util/Iterator;
      35: astore_2
      36: aload_2
      37: invokeinterface #164,  1          // InterfaceMethod java/util/Iterator.hasNext:()Z
      42: ifeq          112
      45: aload_2
      46: invokeinterface #165,  1          // InterfaceMethod java/util/Iterator.next:()Ljava/lang/Object;
      51: checkcast     #90                 // class java/util/List
      54: astore_3
      55: aload_3
      56: invokeinterface #166,  1          // InterfaceMethod java/util/List.iterator:()Ljava/util/Iterator;
      61: astore        4
      63: aload         4
      65: invokeinterface #164,  1          // InterfaceMethod java/util/Iterator.hasNext:()Z
      70: ifeq          109
      73: aload         4
      75: invokeinterface #165,  1          // InterfaceMethod java/util/Iterator.next:()Ljava/lang/Object;
      80: checkcast     #167                // class org/apache/hadoop/hbase/Cell
      83: astore        5
      85: aload         5
      87: invokeinterface #168,  1          // InterfaceMethod org/apache/hadoop/hbase/Cell.getSerializedSize:()I
      92: iload_1
      93: if_icmple     106
      96: new           #158                // class java/lang/IllegalArgumentException
      99: dup
     100: ldc           #169                // String KeyValue size too large
     102: invokespecial #160                // Method java/lang/IllegalArgumentException."<init>":(Ljava/lang/String;)V
     105: athrow
     106: goto          63
     109: goto          36
     112: return

  static int calcPriority(int, org.apache.hadoop.hbase.TableName);
    Code:
       0: iload_0
       1: iconst_m1
       2: if_icmpeq     7
       5: iload_0
       6: ireturn
       7: aload_1
       8: invokestatic  #170                // Method getPriority:(Lorg/apache/hadoop/hbase/TableName;)I
      11: ireturn

  static int getPriority(org.apache.hadoop.hbase.TableName);
    Code:
       0: aload_0
       1: invokevirtual #171                // Method org/apache/hadoop/hbase/TableName.isSystemTable:()Z
       4: ifeq          11
       7: sipush        200
      10: ireturn
      11: iconst_0
      12: ireturn

  static <T> java.util.concurrent.CompletableFuture<T> getOrFetch(java.util.concurrent.atomic.AtomicReference<T>, java.util.concurrent.atomic.AtomicReference<java.util.concurrent.CompletableFuture<T>>, boolean, java.util.function.Supplier<java.util.concurrent.CompletableFuture<T>>, java.util.function.Predicate<T>, java.lang.String);
    Code:
       0: iload_2
       1: ifne          33
       4: aload_0
       5: invokevirtual #172                // Method java/util/concurrent/atomic/AtomicReference.get:()Ljava/lang/Object;
       8: astore        6
      10: aload         6
      12: ifnull        33
      15: aload         4
      17: aload         6
      19: invokeinterface #173,  2          // InterfaceMethod java/util/function/Predicate.test:(Ljava/lang/Object;)Z
      24: ifeq          33
      27: aload         6
      29: invokestatic  #174                // Method java/util/concurrent/CompletableFuture.completedFuture:(Ljava/lang/Object;)Ljava/util/concurrent/CompletableFuture;
      32: areturn
      33: getstatic     #39                 // Field LOG:Lorg/slf4j/Logger;
      36: ldc           #175                // String {} cache is null, try fetching from registry
      38: aload         5
      40: invokeinterface #176,  3          // InterfaceMethod org/slf4j/Logger.trace:(Ljava/lang/String;Ljava/lang/Object;)V
      45: aload_1
      46: aconst_null
      47: new           #104                // class java/util/concurrent/CompletableFuture
      50: dup
      51: invokespecial #152                // Method java/util/concurrent/CompletableFuture."<init>":()V
      54: invokevirtual #177                // Method java/util/concurrent/atomic/AtomicReference.compareAndSet:(Ljava/lang/Object;Ljava/lang/Object;)Z
      57: ifeq          107
      60: getstatic     #39                 // Field LOG:Lorg/slf4j/Logger;
      63: ldc           #178                // String Start fetching{} from registry
      65: aload         5
      67: invokeinterface #179,  3          // InterfaceMethod org/slf4j/Logger.debug:(Ljava/lang/String;Ljava/lang/Object;)V
      72: aload_1
      73: invokevirtual #172                // Method java/util/concurrent/atomic/AtomicReference.get:()Ljava/lang/Object;
      76: checkcast     #104                // class java/util/concurrent/CompletableFuture
      79: astore        6
      81: aload_3
      82: invokeinterface #180,  1          // InterfaceMethod java/util/function/Supplier.get:()Ljava/lang/Object;
      87: checkcast     #104                // class java/util/concurrent/CompletableFuture
      90: aload         5
      92: aload_1
      93: aload_0
      94: aload         6
      96: invokedynamic #181,  0            // InvokeDynamic #8:accept:(Ljava/lang/String;Ljava/util/concurrent/atomic/AtomicReference;Ljava/util/concurrent/atomic/AtomicReference;Ljava/util/concurrent/CompletableFuture;)Ljava/util/function/BiConsumer;
     101: invokestatic  #139                // Method org/apache/hadoop/hbase/util/FutureUtils.addListener:(Ljava/util/concurrent/CompletableFuture;Ljava/util/function/BiConsumer;)V
     104: aload         6
     106: areturn
     107: aload_1
     108: invokevirtual #172                // Method java/util/concurrent/atomic/AtomicReference.get:()Ljava/lang/Object;
     111: checkcast     #104                // class java/util/concurrent/CompletableFuture
     114: astore        6
     116: aload         6
     118: ifnull        124
     121: aload         6
     123: areturn
     124: goto          0

  static void updateStats(java.util.Optional<org.apache.hadoop.hbase.client.ServerStatisticTracker>, java.util.Optional<org.apache.hadoop.hbase.client.MetricsConnection>, org.apache.hadoop.hbase.ServerName, org.apache.hadoop.hbase.client.MultiResponse);
    Code:
       0: aload_0
       1: invokevirtual #182                // Method java/util/Optional.isPresent:()Z
       4: ifne          15
       7: aload_1
       8: invokevirtual #182                // Method java/util/Optional.isPresent:()Z
      11: ifne          15
      14: return
      15: aload_3
      16: invokevirtual #183                // Method org/apache/hadoop/hbase/client/MultiResponse.getResults:()Ljava/util/Map;
      19: aload_2
      20: aload_0
      21: aload_1
      22: invokedynamic #184,  0            // InvokeDynamic #9:accept:(Lorg/apache/hadoop/hbase/ServerName;Ljava/util/Optional;Ljava/util/Optional;)Ljava/util/function/BiConsumer;
      27: invokeinterface #136,  2          // InterfaceMethod java/util/Map.forEach:(Ljava/util/function/BiConsumer;)V
      32: return

  static {};
    Code:
       0: ldc           #213                // class org/apache/hadoop/hbase/client/ConnectionUtils
       2: invokestatic  #214                // Method org/slf4j/LoggerFactory.getLogger:(Ljava/lang/Class;)Lorg/slf4j/Logger;
       5: putstatic     #39                 // Field LOG:Lorg/slf4j/Logger;
       8: new           #215                // class org/apache/hadoop/hbase/client/ConnectionUtils$1
      11: dup
      12: invokespecial #216                // Method org/apache/hadoop/hbase/client/ConnectionUtils$1."<init>":()V
      15: putstatic     #217                // Field NO_NONCE_GENERATOR:Lorg/apache/hadoop/hbase/client/NonceGenerator;
      18: bipush        9
      20: invokestatic  #218                // Method org/apache/hadoop/hbase/util/Bytes.createMaxByteArray:(I)[B
      23: putstatic     #48                 // Field MAX_BYTE_ARRAY:[B
      26: getstatic     #219                // Field java/util/concurrent/TimeUnit.MILLISECONDS:Ljava/util/concurrent/TimeUnit;
      29: lconst_1
      30: invokevirtual #220                // Method java/util/concurrent/TimeUnit.toNanos:(J)J
      33: putstatic     #221                // Field SLEEP_DELTA_NS:J
      36: invokestatic  #222                // Method getMyAddress:()Ljava/lang/String;
      39: putstatic     #122                // Field MY_ADDRESS:Ljava/lang/String;
      42: return
}
