Compiled from "ConnectionCache.java"
class org.apache.hadoop.hbase.util.ConnectionCache$3 extends org.apache.hadoop.hbase.ScheduledChore {
  final int val$maxIdleTime;

  final org.apache.hadoop.hbase.util.ConnectionCache this$0;

  org.apache.hadoop.hbase.util.ConnectionCache$3(org.apache.hadoop.hbase.util.ConnectionCache, java.lang.String, org.apache.hadoop.hbase.Stoppable, int, int);
    Code:
       0: aload_0
       1: aload_1
       2: putfield      #1                  // Field this$0:Lorg/apache/hadoop/hbase/util/ConnectionCache;
       5: aload_0
       6: iload         5
       8: putfield      #2                  // Field val$maxIdleTime:I
      11: aload_0
      12: aload_2
      13: aload_3
      14: iload         4
      16: invokespecial #3                  // Method org/apache/hadoop/hbase/ScheduledChore."<init>":(Ljava/lang/String;Lorg/apache/hadoop/hbase/Stoppable;I)V
      19: return

  protected void chore();
    Code:
       0: aload_0
       1: getfield      #1                  // Field this$0:Lorg/apache/hadoop/hbase/util/ConnectionCache;
       4: invokestatic  #4                  // Method org/apache/hadoop/hbase/util/ConnectionCache.access$100:(Lorg/apache/hadoop/hbase/util/ConnectionCache;)Ljava/util/Map;
       7: invokeinterface #5,  1            // InterfaceMethod java/util/Map.entrySet:()Ljava/util/Set;
      12: invokeinterface #6,  1            // InterfaceMethod java/util/Set.iterator:()Ljava/util/Iterator;
      17: astore_1
      18: aload_1
      19: invokeinterface #7,  1            // InterfaceMethod java/util/Iterator.hasNext:()Z
      24: ifeq          120
      27: aload_1
      28: invokeinterface #8,  1            // InterfaceMethod java/util/Iterator.next:()Ljava/lang/Object;
      33: checkcast     #9                  // class java/util/Map$Entry
      36: astore_2
      37: aload_2
      38: invokeinterface #10,  1           // InterfaceMethod java/util/Map$Entry.getValue:()Ljava/lang/Object;
      43: checkcast     #11                 // class org/apache/hadoop/hbase/util/ConnectionCache$ConnectionInfo
      46: astore_3
      47: aload_3
      48: aload_0
      49: getfield      #2                  // Field val$maxIdleTime:I
      52: invokevirtual #12                 // Method org/apache/hadoop/hbase/util/ConnectionCache$ConnectionInfo.timedOut:(I)Z
      55: ifeq          117
      58: aload_3
      59: getfield      #13                 // Field org/apache/hadoop/hbase/util/ConnectionCache$ConnectionInfo.admin:Lorg/apache/hadoop/hbase/client/Admin;
      62: ifnull        91
      65: aload_3
      66: getfield      #13                 // Field org/apache/hadoop/hbase/util/ConnectionCache$ConnectionInfo.admin:Lorg/apache/hadoop/hbase/client/Admin;
      69: invokeinterface #14,  1           // InterfaceMethod org/apache/hadoop/hbase/client/Admin.close:()V
      74: goto          91
      77: astore        4
      79: invokestatic  #16                 // Method org/apache/hadoop/hbase/util/ConnectionCache.access$200:()Lorg/slf4j/Logger;
      82: ldc           #17                 // String Got exception in closing idle admin
      84: aload         4
      86: invokeinterface #18,  3           // InterfaceMethod org/slf4j/Logger.info:(Ljava/lang/String;Ljava/lang/Throwable;)V
      91: aload_3
      92: getfield      #19                 // Field org/apache/hadoop/hbase/util/ConnectionCache$ConnectionInfo.connection:Lorg/apache/hadoop/hbase/client/Connection;
      95: invokeinterface #20,  1           // InterfaceMethod org/apache/hadoop/hbase/client/Connection.close:()V
     100: goto          117
     103: astore        4
     105: invokestatic  #16                 // Method org/apache/hadoop/hbase/util/ConnectionCache.access$200:()Lorg/slf4j/Logger;
     108: ldc           #21                 // String Got exception in closing idle connection
     110: aload         4
     112: invokeinterface #18,  3           // InterfaceMethod org/slf4j/Logger.info:(Ljava/lang/String;Ljava/lang/Throwable;)V
     117: goto          18
     120: return
    Exception table:
       from    to  target type
          65    74    77   Class java/lang/Throwable
          91   100   103   Class java/lang/Throwable
}
