Compiled from "CoprocessorServiceBackwardCompatiblity.java"
public class org.apache.hadoop.hbase.coprocessor.CoprocessorServiceBackwardCompatiblity$RegionServerCoprocessorService implements org.apache.hadoop.hbase.coprocessor.RegionServerCoprocessor {
  org.apache.hadoop.hbase.coprocessor.SingletonCoprocessorService service;

  public org.apache.hadoop.hbase.coprocessor.CoprocessorServiceBackwardCompatiblity$RegionServerCoprocessorService(org.apache.hadoop.hbase.coprocessor.SingletonCoprocessorService);
    Code:
       0: aload_0
       1: invokespecial #1                  // Method java/lang/Object."<init>":()V
       4: aload_0
       5: aload_1
       6: putfield      #2                  // Field service:Lorg/apache/hadoop/hbase/coprocessor/SingletonCoprocessorService;
       9: return

  public java.lang.Iterable<com.google.protobuf.Service> getServices();
    Code:
       0: aload_0
       1: getfield      #2                  // Field service:Lorg/apache/hadoop/hbase/coprocessor/SingletonCoprocessorService;
       4: invokeinterface #3,  1            // InterfaceMethod org/apache/hadoop/hbase/coprocessor/SingletonCoprocessorService.getService:()Lcom/google/protobuf/Service;
       9: invokestatic  #4                  // Method java/util/Collections.singleton:(Ljava/lang/Object;)Ljava/util/Set;
      12: areturn
}
