Compiled from "CoprocessorWhitelistMasterObserver.java"
public class org.apache.hadoop.hbase.security.access.CoprocessorWhitelistMasterObserver implements org.apache.hadoop.hbase.coprocessor.MasterCoprocessor,org.apache.hadoop.hbase.coprocessor.MasterObserver {
  public static final java.lang.String CP_COPROCESSOR_WHITELIST_PATHS_KEY;

  public org.apache.hadoop.hbase.security.access.CoprocessorWhitelistMasterObserver();
    Code:
       0: aload_0
       1: invokespecial #1                  // Method java/lang/Object."<init>":()V
       4: return

  public java.util.Optional<org.apache.hadoop.hbase.coprocessor.MasterObserver> getMasterObserver();
    Code:
       0: aload_0
       1: invokestatic  #2                  // Method java/util/Optional.of:(Ljava/lang/Object;)Ljava/util/Optional;
       4: areturn

  public org.apache.hadoop.hbase.client.TableDescriptor preModifyTable(org.apache.hadoop.hbase.coprocessor.ObserverContext<org.apache.hadoop.hbase.coprocessor.MasterCoprocessorEnvironment>, org.apache.hadoop.hbase.TableName, org.apache.hadoop.hbase.client.TableDescriptor, org.apache.hadoop.hbase.client.TableDescriptor) throws java.io.IOException;
    Code:
       0: aload_1
       1: aload         4
       3: invokestatic  #3                  // Method verifyCoprocessors:(Lorg/apache/hadoop/hbase/coprocessor/ObserverContext;Lorg/apache/hadoop/hbase/client/TableDescriptor;)V
       6: aload         4
       8: areturn

  public void preCreateTable(org.apache.hadoop.hbase.coprocessor.ObserverContext<org.apache.hadoop.hbase.coprocessor.MasterCoprocessorEnvironment>, org.apache.hadoop.hbase.client.TableDescriptor, org.apache.hadoop.hbase.client.RegionInfo[]) throws java.io.IOException;
    Code:
       0: aload_1
       1: aload_2
       2: invokestatic  #3                  // Method verifyCoprocessors:(Lorg/apache/hadoop/hbase/coprocessor/ObserverContext;Lorg/apache/hadoop/hbase/client/TableDescriptor;)V
       5: return

  static {};
    Code:
       0: ldc           #20                 // class org/apache/hadoop/hbase/security/access/CoprocessorWhitelistMasterObserver
       2: invokestatic  #47                 // Method org/slf4j/LoggerFactory.getLogger:(Ljava/lang/Class;)Lorg/slf4j/Logger;
       5: putstatic     #44                 // Field LOG:Lorg/slf4j/Logger;
       8: return
}
