Compiled from "CoprocessorValidator.java"
final class org.apache.hadoop.hbase.tool.coprocessor.CoprocessorValidator$ResolverUrlClassLoader extends java.net.URLClassLoader {
  public java.lang.Class<?> loadClass(java.lang.String) throws java.lang.ClassNotFoundException;
    Code:
       0: aload_0
       1: aload_1
       2: iconst_1
       3: invokevirtual #3                  // Method loadClass:(Ljava/lang/String;Z)Ljava/lang/Class;
       6: areturn

  org.apache.hadoop.hbase.tool.coprocessor.CoprocessorValidator$ResolverUrlClassLoader(java.net.URL[], java.lang.ClassLoader, org.apache.hadoop.hbase.tool.coprocessor.CoprocessorValidator$1);
    Code:
       0: aload_0
       1: aload_1
       2: aload_2
       3: invokespecial #1                  // Method "<init>":([Ljava/net/URL;Ljava/lang/ClassLoader;)V
       6: return
}
