Compiled from "CoprocessorValidatorTest.java"
public class org.apache.hadoop.hbase.tool.coprocessor.CoprocessorValidatorTest {
  public static final org.apache.hadoop.hbase.HBaseClassTestRule CLASS_RULE;

  public org.apache.hadoop.hbase.tool.coprocessor.CoprocessorValidatorTest();
    Code:
       0: aload_0
       1: invokespecial #3                  // Method java/lang/Object."<init>":()V
       4: aload_0
       5: new           #4                  // class org/apache/hadoop/hbase/tool/coprocessor/CoprocessorValidator
       8: dup
       9: invokespecial #5                  // Method org/apache/hadoop/hbase/tool/coprocessor/CoprocessorValidator."<init>":()V
      12: putfield      #6                  // Field validator:Lorg/apache/hadoop/hbase/tool/coprocessor/CoprocessorValidator;
      15: aload_0
      16: getfield      #6                  // Field validator:Lorg/apache/hadoop/hbase/tool/coprocessor/CoprocessorValidator;
      19: invokestatic  #7                  // Method org/apache/hadoop/hbase/HBaseConfiguration.create:()Lorg/apache/hadoop/conf/Configuration;
      22: invokevirtual #8                  // Method org/apache/hadoop/hbase/tool/coprocessor/CoprocessorValidator.setConf:(Lorg/apache/hadoop/conf/Configuration;)V
      25: return

  public void testNoSuchClass() throws java.io.IOException;
    Code:
       0: aload_0
       1: ldc           #24                 // String NoSuchClass
       3: invokespecial #25                 // Method validateClass:(Ljava/lang/String;)Ljava/util/List;
       6: astore_1
       7: lconst_1
       8: aload_1
       9: invokeinterface #26,  1           // InterfaceMethod java/util/List.size:()I
      14: i2l
      15: invokestatic  #27                 // Method org/junit/Assert.assertEquals:(JJ)V
      18: aload_1
      19: iconst_0
      20: invokeinterface #28,  2           // InterfaceMethod java/util/List.get:(I)Ljava/lang/Object;
      25: checkcast     #29                 // class org/apache/hadoop/hbase/tool/coprocessor/CoprocessorViolation
      28: astore_2
      29: ldc           #24                 // String NoSuchClass
      31: invokestatic  #1                  // Method getFullClassName:(Ljava/lang/String;)Ljava/lang/String;
      34: aload_2
      35: invokevirtual #30                 // Method org/apache/hadoop/hbase/tool/coprocessor/CoprocessorViolation.getClassName:()Ljava/lang/String;
      38: invokestatic  #31                 // Method org/junit/Assert.assertEquals:(Ljava/lang/Object;Ljava/lang/Object;)V
      41: getstatic     #32                 // Field org/apache/hadoop/hbase/tool/coprocessor/CoprocessorViolation$Severity.ERROR:Lorg/apache/hadoop/hbase/tool/coprocessor/CoprocessorViolation$Severity;
      44: aload_2
      45: invokevirtual #33                 // Method org/apache/hadoop/hbase/tool/coprocessor/CoprocessorViolation.getSeverity:()Lorg/apache/hadoop/hbase/tool/coprocessor/CoprocessorViolation$Severity;
      48: invokestatic  #31                 // Method org/junit/Assert.assertEquals:(Ljava/lang/Object;Ljava/lang/Object;)V
      51: aload_2
      52: invokevirtual #34                 // Method org/apache/hadoop/hbase/tool/coprocessor/CoprocessorViolation.getThrowable:()Ljava/lang/Throwable;
      55: invokestatic  #35                 // Method org/apache/hbase/thirdparty/com/google/common/base/Throwables.getStackTraceAsString:(Ljava/lang/Throwable;)Ljava/lang/String;
      58: astore_3
      59: aload_3
      60: ldc           #36                 // String java.lang.ClassNotFoundException: org.apache.hadoop.hbase.tool.coprocessor.CoprocessorValidatorTest$NoSuchClass
      62: invokevirtual #37                 // Method java/lang/String.contains:(Ljava/lang/CharSequence;)Z
      65: invokestatic  #38                 // Method org/junit/Assert.assertTrue:(Z)V
      68: return

  public void testMissingClass() throws java.io.IOException;
    Code:
       0: new           #39                 // class org/apache/hadoop/hbase/tool/coprocessor/CoprocessorValidatorTest$MissingClassClassLoader
       3: dup
       4: invokespecial #40                 // Method org/apache/hadoop/hbase/tool/coprocessor/CoprocessorValidatorTest$MissingClassClassLoader."<init>":()V
       7: astore_1
       8: aload_0
       9: aload_1
      10: ldc           #41                 // String MissingClassObserver
      12: invokespecial #18                 // Method validateClass:(Ljava/lang/ClassLoader;Ljava/lang/String;)Ljava/util/List;
      15: astore_2
      16: lconst_1
      17: aload_2
      18: invokeinterface #26,  1           // InterfaceMethod java/util/List.size:()I
      23: i2l
      24: invokestatic  #27                 // Method org/junit/Assert.assertEquals:(JJ)V
      27: aload_2
      28: iconst_0
      29: invokeinterface #28,  2           // InterfaceMethod java/util/List.get:(I)Ljava/lang/Object;
      34: checkcast     #29                 // class org/apache/hadoop/hbase/tool/coprocessor/CoprocessorViolation
      37: astore_3
      38: ldc           #41                 // String MissingClassObserver
      40: invokestatic  #1                  // Method getFullClassName:(Ljava/lang/String;)Ljava/lang/String;
      43: aload_3
      44: invokevirtual #30                 // Method org/apache/hadoop/hbase/tool/coprocessor/CoprocessorViolation.getClassName:()Ljava/lang/String;
      47: invokestatic  #31                 // Method org/junit/Assert.assertEquals:(Ljava/lang/Object;Ljava/lang/Object;)V
      50: getstatic     #32                 // Field org/apache/hadoop/hbase/tool/coprocessor/CoprocessorViolation$Severity.ERROR:Lorg/apache/hadoop/hbase/tool/coprocessor/CoprocessorViolation$Severity;
      53: aload_3
      54: invokevirtual #33                 // Method org/apache/hadoop/hbase/tool/coprocessor/CoprocessorViolation.getSeverity:()Lorg/apache/hadoop/hbase/tool/coprocessor/CoprocessorViolation$Severity;
      57: invokestatic  #31                 // Method org/junit/Assert.assertEquals:(Ljava/lang/Object;Ljava/lang/Object;)V
      60: aload_3
      61: invokevirtual #34                 // Method org/apache/hadoop/hbase/tool/coprocessor/CoprocessorViolation.getThrowable:()Ljava/lang/Throwable;
      64: invokestatic  #35                 // Method org/apache/hbase/thirdparty/com/google/common/base/Throwables.getStackTraceAsString:(Ljava/lang/Throwable;)Ljava/lang/String;
      67: astore        4
      69: aload         4
      71: ldc           #42                 // String java.lang.ClassNotFoundException: org.apache.hadoop.hbase.tool.coprocessor.CoprocessorValidatorTest$MissingClass
      73: invokevirtual #37                 // Method java/lang/String.contains:(Ljava/lang/CharSequence;)Z
      76: invokestatic  #38                 // Method org/junit/Assert.assertTrue:(Z)V
      79: return

  public void testObsoleteMethod() throws java.io.IOException;
    Code:
       0: aload_0
       1: ldc           #43                 // String ObsoleteMethodObserver
       3: invokespecial #25                 // Method validateClass:(Ljava/lang/String;)Ljava/util/List;
       6: astore_1
       7: lconst_1
       8: aload_1
       9: invokeinterface #26,  1           // InterfaceMethod java/util/List.size:()I
      14: i2l
      15: invokestatic  #27                 // Method org/junit/Assert.assertEquals:(JJ)V
      18: aload_1
      19: iconst_0
      20: invokeinterface #28,  2           // InterfaceMethod java/util/List.get:(I)Ljava/lang/Object;
      25: checkcast     #29                 // class org/apache/hadoop/hbase/tool/coprocessor/CoprocessorViolation
      28: astore_2
      29: getstatic     #44                 // Field org/apache/hadoop/hbase/tool/coprocessor/CoprocessorViolation$Severity.WARNING:Lorg/apache/hadoop/hbase/tool/coprocessor/CoprocessorViolation$Severity;
      32: aload_2
      33: invokevirtual #33                 // Method org/apache/hadoop/hbase/tool/coprocessor/CoprocessorViolation.getSeverity:()Lorg/apache/hadoop/hbase/tool/coprocessor/CoprocessorViolation$Severity;
      36: invokestatic  #31                 // Method org/junit/Assert.assertEquals:(Ljava/lang/Object;Ljava/lang/Object;)V
      39: ldc           #43                 // String ObsoleteMethodObserver
      41: invokestatic  #1                  // Method getFullClassName:(Ljava/lang/String;)Ljava/lang/String;
      44: aload_2
      45: invokevirtual #30                 // Method org/apache/hadoop/hbase/tool/coprocessor/CoprocessorViolation.getClassName:()Ljava/lang/String;
      48: invokestatic  #31                 // Method org/junit/Assert.assertEquals:(Ljava/lang/Object;Ljava/lang/Object;)V
      51: aload_2
      52: invokevirtual #45                 // Method org/apache/hadoop/hbase/tool/coprocessor/CoprocessorViolation.getMessage:()Ljava/lang/String;
      55: ldc           #46                 // String was removed from new coprocessor API
      57: invokevirtual #37                 // Method java/lang/String.contains:(Ljava/lang/CharSequence;)Z
      60: invokestatic  #38                 // Method org/junit/Assert.assertTrue:(Z)V
      63: return

  public void testTableNoSuchClass() throws java.io.IOException;
    Code:
       0: aload_0
       1: aconst_null
       2: ldc           #24                 // String NoSuchClass
       4: invokespecial #61                 // Method validateTable:(Ljava/lang/String;Ljava/lang/String;)Ljava/util/List;
       7: astore_1
       8: lconst_1
       9: aload_1
      10: invokeinterface #26,  1           // InterfaceMethod java/util/List.size:()I
      15: i2l
      16: invokestatic  #27                 // Method org/junit/Assert.assertEquals:(JJ)V
      19: aload_1
      20: iconst_0
      21: invokeinterface #28,  2           // InterfaceMethod java/util/List.get:(I)Ljava/lang/Object;
      26: checkcast     #29                 // class org/apache/hadoop/hbase/tool/coprocessor/CoprocessorViolation
      29: astore_2
      30: ldc           #24                 // String NoSuchClass
      32: invokestatic  #1                  // Method getFullClassName:(Ljava/lang/String;)Ljava/lang/String;
      35: aload_2
      36: invokevirtual #30                 // Method org/apache/hadoop/hbase/tool/coprocessor/CoprocessorViolation.getClassName:()Ljava/lang/String;
      39: invokestatic  #31                 // Method org/junit/Assert.assertEquals:(Ljava/lang/Object;Ljava/lang/Object;)V
      42: getstatic     #32                 // Field org/apache/hadoop/hbase/tool/coprocessor/CoprocessorViolation$Severity.ERROR:Lorg/apache/hadoop/hbase/tool/coprocessor/CoprocessorViolation$Severity;
      45: aload_2
      46: invokevirtual #33                 // Method org/apache/hadoop/hbase/tool/coprocessor/CoprocessorViolation.getSeverity:()Lorg/apache/hadoop/hbase/tool/coprocessor/CoprocessorViolation$Severity;
      49: invokestatic  #31                 // Method org/junit/Assert.assertEquals:(Ljava/lang/Object;Ljava/lang/Object;)V
      52: aload_2
      53: invokevirtual #34                 // Method org/apache/hadoop/hbase/tool/coprocessor/CoprocessorViolation.getThrowable:()Ljava/lang/Throwable;
      56: invokestatic  #35                 // Method org/apache/hbase/thirdparty/com/google/common/base/Throwables.getStackTraceAsString:(Ljava/lang/Throwable;)Ljava/lang/String;
      59: astore_3
      60: aload_3
      61: ldc           #36                 // String java.lang.ClassNotFoundException: org.apache.hadoop.hbase.tool.coprocessor.CoprocessorValidatorTest$NoSuchClass
      63: invokevirtual #37                 // Method java/lang/String.contains:(Ljava/lang/CharSequence;)Z
      66: invokestatic  #38                 // Method org/junit/Assert.assertTrue:(Z)V
      69: return

  public void testTableMissingJar() throws java.io.IOException;
    Code:
       0: aload_0
       1: ldc           #62                 // String no such file
       3: ldc           #24                 // String NoSuchClass
       5: invokespecial #61                 // Method validateTable:(Ljava/lang/String;Ljava/lang/String;)Ljava/util/List;
       8: astore_1
       9: lconst_1
      10: aload_1
      11: invokeinterface #26,  1           // InterfaceMethod java/util/List.size:()I
      16: i2l
      17: invokestatic  #27                 // Method org/junit/Assert.assertEquals:(JJ)V
      20: aload_1
      21: iconst_0
      22: invokeinterface #28,  2           // InterfaceMethod java/util/List.get:(I)Ljava/lang/Object;
      27: checkcast     #29                 // class org/apache/hadoop/hbase/tool/coprocessor/CoprocessorViolation
      30: astore_2
      31: ldc           #24                 // String NoSuchClass
      33: invokestatic  #1                  // Method getFullClassName:(Ljava/lang/String;)Ljava/lang/String;
      36: aload_2
      37: invokevirtual #30                 // Method org/apache/hadoop/hbase/tool/coprocessor/CoprocessorViolation.getClassName:()Ljava/lang/String;
      40: invokestatic  #31                 // Method org/junit/Assert.assertEquals:(Ljava/lang/Object;Ljava/lang/Object;)V
      43: getstatic     #32                 // Field org/apache/hadoop/hbase/tool/coprocessor/CoprocessorViolation$Severity.ERROR:Lorg/apache/hadoop/hbase/tool/coprocessor/CoprocessorViolation$Severity;
      46: aload_2
      47: invokevirtual #33                 // Method org/apache/hadoop/hbase/tool/coprocessor/CoprocessorViolation.getSeverity:()Lorg/apache/hadoop/hbase/tool/coprocessor/CoprocessorViolation$Severity;
      50: invokestatic  #31                 // Method org/junit/Assert.assertEquals:(Ljava/lang/Object;Ljava/lang/Object;)V
      53: aload_2
      54: invokevirtual #45                 // Method org/apache/hadoop/hbase/tool/coprocessor/CoprocessorViolation.getMessage:()Ljava/lang/String;
      57: ldc           #63                 // String could not validate jar file 'no such file'
      59: invokevirtual #37                 // Method java/lang/String.contains:(Ljava/lang/CharSequence;)Z
      62: invokestatic  #38                 // Method org/junit/Assert.assertTrue:(Z)V
      65: return

  public void testTableValidJar() throws java.io.IOException;
    Code:
       0: ldc           #64                 // String target
       2: iconst_1
       3: anewarray     #19                 // class java/lang/String
       6: dup
       7: iconst_0
       8: ldc           #65                 // String test-classes
      10: aastore
      11: invokestatic  #66                 // Method java/nio/file/Paths.get:(Ljava/lang/String;[Ljava/lang/String;)Ljava/nio/file/Path;
      14: astore_1
      15: ldc           #43                 // String ObsoleteMethodObserver
      17: invokestatic  #1                  // Method getFullClassName:(Ljava/lang/String;)Ljava/lang/String;
      20: astore_2
      21: new           #11                 // class java/lang/StringBuilder
      24: dup
      25: invokespecial #12                 // Method java/lang/StringBuilder."<init>":()V
      28: aload_2
      29: bipush        46
      31: bipush        47
      33: invokevirtual #67                 // Method java/lang/String.replace:(CC)Ljava/lang/String;
      36: invokevirtual #14                 // Method java/lang/StringBuilder.append:(Ljava/lang/String;)Ljava/lang/StringBuilder;
      39: ldc           #68                 // String .class
      41: invokevirtual #14                 // Method java/lang/StringBuilder.append:(Ljava/lang/String;)Ljava/lang/StringBuilder;
      44: invokevirtual #16                 // Method java/lang/StringBuilder.toString:()Ljava/lang/String;
      47: iconst_0
      48: anewarray     #19                 // class java/lang/String
      51: invokestatic  #66                 // Method java/nio/file/Paths.get:(Ljava/lang/String;[Ljava/lang/String;)Ljava/nio/file/Path;
      54: astore_3
      55: aload_1
      56: aload_3
      57: invokeinterface #69,  2           // InterfaceMethod java/nio/file/Path.resolve:(Ljava/nio/file/Path;)Ljava/nio/file/Path;
      62: astore        4
      64: ldc           #70                 // String coprocessor-validator-test-
      66: ldc           #71                 // String .jar
      68: iconst_0
      69: anewarray     #72                 // class java/nio/file/attribute/FileAttribute
      72: invokestatic  #73                 // Method java/nio/file/Files.createTempFile:(Ljava/lang/String;Ljava/lang/String;[Ljava/nio/file/attribute/FileAttribute;)Ljava/nio/file/Path;
      75: astore        5
      77: aload         5
      79: iconst_0
      80: anewarray     #74                 // class java/nio/file/OpenOption
      83: invokestatic  #75                 // Method java/nio/file/Files.newOutputStream:(Ljava/nio/file/Path;[Ljava/nio/file/OpenOption;)Ljava/io/OutputStream;
      86: astore        6
      88: aconst_null
      89: astore        7
      91: new           #76                 // class java/util/jar/JarOutputStream
      94: dup
      95: aload         6
      97: invokespecial #77                 // Method java/util/jar/JarOutputStream."<init>":(Ljava/io/OutputStream;)V
     100: astore        8
     102: aconst_null
     103: astore        9
     105: aload         4
     107: iconst_0
     108: anewarray     #74                 // class java/nio/file/OpenOption
     111: invokestatic  #78                 // Method java/nio/file/Files.newInputStream:(Ljava/nio/file/Path;[Ljava/nio/file/OpenOption;)Ljava/io/InputStream;
     114: astore        10
     116: aconst_null
     117: astore        11
     119: new           #79                 // class java/util/zip/ZipEntry
     122: dup
     123: aload_3
     124: invokeinterface #80,  1           // InterfaceMethod java/nio/file/Path.toString:()Ljava/lang/String;
     129: invokespecial #81                 // Method java/util/zip/ZipEntry."<init>":(Ljava/lang/String;)V
     132: astore        12
     134: aload         8
     136: aload         12
     138: invokevirtual #82                 // Method java/util/jar/JarOutputStream.putNextEntry:(Ljava/util/zip/ZipEntry;)V
     141: aload         10
     143: aload         8
     145: invokestatic  #83                 // Method org/apache/hbase/thirdparty/com/google/common/io/ByteStreams.copy:(Ljava/io/InputStream;Ljava/io/OutputStream;)J
     148: pop2
     149: aload         10
     151: ifnull        236
     154: aload         11
     156: ifnull        179
     159: aload         10
     161: invokevirtual #84                 // Method java/io/InputStream.close:()V
     164: goto          236
     167: astore        12
     169: aload         11
     171: aload         12
     173: invokevirtual #86                 // Method java/lang/Throwable.addSuppressed:(Ljava/lang/Throwable;)V
     176: goto          236
     179: aload         10
     181: invokevirtual #84                 // Method java/io/InputStream.close:()V
     184: goto          236
     187: astore        12
     189: aload         12
     191: astore        11
     193: aload         12
     195: athrow
     196: astore        13
     198: aload         10
     200: ifnull        233
     203: aload         11
     205: ifnull        228
     208: aload         10
     210: invokevirtual #84                 // Method java/io/InputStream.close:()V
     213: goto          233
     216: astore        14
     218: aload         11
     220: aload         14
     222: invokevirtual #86                 // Method java/lang/Throwable.addSuppressed:(Ljava/lang/Throwable;)V
     225: goto          233
     228: aload         10
     230: invokevirtual #84                 // Method java/io/InputStream.close:()V
     233: aload         13
     235: athrow
     236: aload         8
     238: ifnull        323
     241: aload         9
     243: ifnull        266
     246: aload         8
     248: invokevirtual #87                 // Method java/util/jar/JarOutputStream.close:()V
     251: goto          323
     254: astore        10
     256: aload         9
     258: aload         10
     260: invokevirtual #86                 // Method java/lang/Throwable.addSuppressed:(Ljava/lang/Throwable;)V
     263: goto          323
     266: aload         8
     268: invokevirtual #87                 // Method java/util/jar/JarOutputStream.close:()V
     271: goto          323
     274: astore        10
     276: aload         10
     278: astore        9
     280: aload         10
     282: athrow
     283: astore        15
     285: aload         8
     287: ifnull        320
     290: aload         9
     292: ifnull        315
     295: aload         8
     297: invokevirtual #87                 // Method java/util/jar/JarOutputStream.close:()V
     300: goto          320
     303: astore        16
     305: aload         9
     307: aload         16
     309: invokevirtual #86                 // Method java/lang/Throwable.addSuppressed:(Ljava/lang/Throwable;)V
     312: goto          320
     315: aload         8
     317: invokevirtual #87                 // Method java/util/jar/JarOutputStream.close:()V
     320: aload         15
     322: athrow
     323: aload         6
     325: ifnull        410
     328: aload         7
     330: ifnull        353
     333: aload         6
     335: invokevirtual #88                 // Method java/io/OutputStream.close:()V
     338: goto          410
     341: astore        8
     343: aload         7
     345: aload         8
     347: invokevirtual #86                 // Method java/lang/Throwable.addSuppressed:(Ljava/lang/Throwable;)V
     350: goto          410
     353: aload         6
     355: invokevirtual #88                 // Method java/io/OutputStream.close:()V
     358: goto          410
     361: astore        8
     363: aload         8
     365: astore        7
     367: aload         8
     369: athrow
     370: astore        17
     372: aload         6
     374: ifnull        407
     377: aload         7
     379: ifnull        402
     382: aload         6
     384: invokevirtual #88                 // Method java/io/OutputStream.close:()V
     387: goto          407
     390: astore        18
     392: aload         7
     394: aload         18
     396: invokevirtual #86                 // Method java/lang/Throwable.addSuppressed:(Ljava/lang/Throwable;)V
     399: goto          407
     402: aload         6
     404: invokevirtual #88                 // Method java/io/OutputStream.close:()V
     407: aload         17
     409: athrow
     410: aload         5
     412: invokeinterface #89,  1           // InterfaceMethod java/nio/file/Path.toUri:()Ljava/net/URI;
     417: invokevirtual #90                 // Method java/net/URI.toString:()Ljava/lang/String;
     420: astore        6
     422: aload_0
     423: aload         6
     425: ldc           #43                 // String ObsoleteMethodObserver
     427: invokespecial #61                 // Method validateTable:(Ljava/lang/String;Ljava/lang/String;)Ljava/util/List;
     430: astore        7
     432: lconst_1
     433: aload         7
     435: invokeinterface #26,  1           // InterfaceMethod java/util/List.size:()I
     440: i2l
     441: invokestatic  #27                 // Method org/junit/Assert.assertEquals:(JJ)V
     444: aload         7
     446: iconst_0
     447: invokeinterface #28,  2           // InterfaceMethod java/util/List.get:(I)Ljava/lang/Object;
     452: checkcast     #29                 // class org/apache/hadoop/hbase/tool/coprocessor/CoprocessorViolation
     455: astore        8
     457: ldc           #43                 // String ObsoleteMethodObserver
     459: invokestatic  #1                  // Method getFullClassName:(Ljava/lang/String;)Ljava/lang/String;
     462: aload         8
     464: invokevirtual #30                 // Method org/apache/hadoop/hbase/tool/coprocessor/CoprocessorViolation.getClassName:()Ljava/lang/String;
     467: invokestatic  #31                 // Method org/junit/Assert.assertEquals:(Ljava/lang/Object;Ljava/lang/Object;)V
     470: getstatic     #44                 // Field org/apache/hadoop/hbase/tool/coprocessor/CoprocessorViolation$Severity.WARNING:Lorg/apache/hadoop/hbase/tool/coprocessor/CoprocessorViolation$Severity;
     473: aload         8
     475: invokevirtual #33                 // Method org/apache/hadoop/hbase/tool/coprocessor/CoprocessorViolation.getSeverity:()Lorg/apache/hadoop/hbase/tool/coprocessor/CoprocessorViolation$Severity;
     478: invokestatic  #31                 // Method org/junit/Assert.assertEquals:(Ljava/lang/Object;Ljava/lang/Object;)V
     481: aload         8
     483: invokevirtual #45                 // Method org/apache/hadoop/hbase/tool/coprocessor/CoprocessorViolation.getMessage:()Ljava/lang/String;
     486: ldc           #46                 // String was removed from new coprocessor API
     488: invokevirtual #37                 // Method java/lang/String.contains:(Ljava/lang/CharSequence;)Z
     491: invokestatic  #38                 // Method org/junit/Assert.assertTrue:(Z)V
     494: aload         5
     496: invokestatic  #91                 // Method java/nio/file/Files.delete:(Ljava/nio/file/Path;)V
     499: goto          512
     502: astore        19
     504: aload         5
     506: invokestatic  #91                 // Method java/nio/file/Files.delete:(Ljava/nio/file/Path;)V
     509: aload         19
     511: athrow
     512: return
    Exception table:
       from    to  target type
         159   164   167   Class java/lang/Throwable
         119   149   187   Class java/lang/Throwable
         119   149   196   any
         208   213   216   Class java/lang/Throwable
         187   198   196   any
         246   251   254   Class java/lang/Throwable
         105   236   274   Class java/lang/Throwable
         105   236   283   any
         295   300   303   Class java/lang/Throwable
         274   285   283   any
         333   338   341   Class java/lang/Throwable
          91   323   361   Class java/lang/Throwable
          91   323   370   any
         382   387   390   Class java/lang/Throwable
         361   372   370   any
          77   494   502   any
         502   504   502   any

  static java.lang.ClassLoader access$000();
    Code:
       0: invokestatic  #2                  // Method getClassLoader:()Ljava/lang/ClassLoader;
       3: areturn

  static java.lang.String access$100(java.lang.String);
    Code:
       0: aload_0
       1: invokestatic  #1                  // Method getFullClassName:(Ljava/lang/String;)Ljava/lang/String;
       4: areturn

  static {};
    Code:
       0: ldc           #9                  // class org/apache/hadoop/hbase/tool/coprocessor/CoprocessorValidatorTest
       2: invokestatic  #92                 // Method org/apache/hadoop/hbase/HBaseClassTestRule.forClass:(Ljava/lang/Class;)Lorg/apache/hadoop/hbase/HBaseClassTestRule;
       5: putstatic     #93                 // Field CLASS_RULE:Lorg/apache/hadoop/hbase/HBaseClassTestRule;
       8: return
}
