Compiled from "CoprocessorHost.java"
final class org.apache.hadoop.hbase.coprocessor.CoprocessorHost$1 implements java.util.Comparator<java.lang.Class<? extends org.apache.hadoop.hbase.Coprocessor>> {
  org.apache.hadoop.hbase.coprocessor.CoprocessorHost$1();
    Code:
       0: aload_0
       1: invokespecial #1                  // Method java/lang/Object."<init>":()V
       4: return

  public int compare(java.lang.Class<? extends org.apache.hadoop.hbase.Coprocessor>, java.lang.Class<? extends org.apache.hadoop.hbase.Coprocessor>);
    Code:
       0: aload_1
       1: aload_2
       2: invokevirtual #2                  // Method java/lang/Object.equals:(Ljava/lang/Object;)Z
       5: ifeq          10
       8: iconst_0
       9: ireturn
      10: aload_1
      11: invokevirtual #3                  // Method java/lang/Class.getName:()Ljava/lang/String;
      14: aload_2
      15: invokevirtual #3                  // Method java/lang/Class.getName:()Ljava/lang/String;
      18: invokevirtual #4                  // Method java/lang/String.compareTo:(Ljava/lang/String;)I
      21: ireturn

  public int compare(java.lang.Object, java.lang.Object);
    Code:
       0: aload_0
       1: aload_1
       2: checkcast     #5                  // class java/lang/Class
       5: aload_2
       6: checkcast     #5                  // class java/lang/Class
       9: invokevirtual #6                  // Method compare:(Ljava/lang/Class;Ljava/lang/Class;)I
      12: ireturn
}
