Compiled from "CoprocessorHost.java"
public abstract class org.apache.hadoop.hbase.coprocessor.CoprocessorHost$ObserverOperationWithoutResult<O> extends org.apache.hadoop.hbase.coprocessor.CoprocessorHost<C, E>.ObserverOperation<O> {
  final org.apache.hadoop.hbase.coprocessor.CoprocessorHost this$0;

  protected abstract void call(O) throws java.io.IOException;

  public org.apache.hadoop.hbase.coprocessor.CoprocessorHost$ObserverOperationWithoutResult(org.apache.hadoop.hbase.coprocessor.CoprocessorHost$ObserverGetter<C, O>);
    Code:
       0: aload_0
       1: aload_1
       2: putfield      #1                  // Field this$0:Lorg/apache/hadoop/hbase/coprocessor/CoprocessorHost;
       5: aload_0
       6: aload_1
       7: aload_2
       8: invokespecial #2                  // Method org/apache/hadoop/hbase/coprocessor/CoprocessorHost$ObserverOperation."<init>":(Lorg/apache/hadoop/hbase/coprocessor/CoprocessorHost;Lorg/apache/hadoop/hbase/coprocessor/CoprocessorHost$ObserverGetter;)V
      11: return

  public org.apache.hadoop.hbase.coprocessor.CoprocessorHost$ObserverOperationWithoutResult(org.apache.hadoop.hbase.coprocessor.CoprocessorHost$ObserverGetter<C, O>, org.apache.hadoop.hbase.security.User);
    Code:
       0: aload_0
       1: aload_1
       2: putfield      #1                  // Field this$0:Lorg/apache/hadoop/hbase/coprocessor/CoprocessorHost;
       5: aload_0
       6: aload_1
       7: aload_2
       8: aload_3
       9: invokespecial #3                  // Method org/apache/hadoop/hbase/coprocessor/CoprocessorHost$ObserverOperation."<init>":(Lorg/apache/hadoop/hbase/coprocessor/CoprocessorHost;Lorg/apache/hadoop/hbase/coprocessor/CoprocessorHost$ObserverGetter;Lorg/apache/hadoop/hbase/security/User;)V
      12: return

  public org.apache.hadoop.hbase.coprocessor.CoprocessorHost$ObserverOperationWithoutResult(org.apache.hadoop.hbase.coprocessor.CoprocessorHost$ObserverGetter<C, O>, org.apache.hadoop.hbase.security.User, boolean);
    Code:
       0: aload_0
       1: aload_1
       2: putfield      #1                  // Field this$0:Lorg/apache/hadoop/hbase/coprocessor/CoprocessorHost;
       5: aload_0
       6: aload_1
       7: aload_2
       8: aload_3
       9: iload         4
      11: invokespecial #4                  // Method org/apache/hadoop/hbase/coprocessor/CoprocessorHost$ObserverOperation."<init>":(Lorg/apache/hadoop/hbase/coprocessor/CoprocessorHost;Lorg/apache/hadoop/hbase/coprocessor/CoprocessorHost$ObserverGetter;Lorg/apache/hadoop/hbase/security/User;Z)V
      14: return

  void callObserver() throws java.io.IOException;
    Code:
       0: aload_0
       1: getfield      #5                  // Field observerGetter:Lorg/apache/hadoop/hbase/coprocessor/CoprocessorHost$ObserverGetter;
       4: aload_0
       5: invokevirtual #6                  // Method getEnvironment:()Lorg/apache/hadoop/hbase/CoprocessorEnvironment;
       8: invokeinterface #7,  1            // InterfaceMethod org/apache/hadoop/hbase/CoprocessorEnvironment.getInstance:()Lorg/apache/hadoop/hbase/Coprocessor;
      13: invokeinterface #8,  2            // InterfaceMethod org/apache/hadoop/hbase/coprocessor/CoprocessorHost$ObserverGetter.apply:(Ljava/lang/Object;)Ljava/lang/Object;
      18: checkcast     #9                  // class java/util/Optional
      21: astore_1
      22: aload_1
      23: invokevirtual #10                 // Method java/util/Optional.isPresent:()Z
      26: ifeq          37
      29: aload_0
      30: aload_1
      31: invokevirtual #11                 // Method java/util/Optional.get:()Ljava/lang/Object;
      34: invokevirtual #12                 // Method call:(Ljava/lang/Object;)V
      37: return
}
