Compiled from "CopyOnWriteArrayMap.java"
final class org.apache.hadoop.hbase.types.CopyOnWriteArrayMap$ArrayEntryIterator<K, V> implements java.util.Iterator<java.util.Map$Entry<K, V>> {
  int index;

  public boolean hasNext();
    Code:
       0: aload_0
       1: getfield      #5                  // Field index:I
       4: aload_0
       5: getfield      #3                  // Field holder:Lorg/apache/hadoop/hbase/types/CopyOnWriteArrayMap$ArrayHolder;
       8: invokestatic  #6                  // Method org/apache/hadoop/hbase/types/CopyOnWriteArrayMap$ArrayHolder.access$200:(Lorg/apache/hadoop/hbase/types/CopyOnWriteArrayMap$ArrayHolder;)I
      11: if_icmpge     18
      14: iconst_1
      15: goto          19
      18: iconst_0
      19: ireturn

  public java.util.Map$Entry<K, V> next();
    Code:
       0: aload_0
       1: invokevirtual #7                  // Method hasNext:()Z
       4: ifne          15
       7: new           #8                  // class java/util/NoSuchElementException
      10: dup
      11: invokespecial #9                  // Method java/util/NoSuchElementException."<init>":()V
      14: athrow
      15: aload_0
      16: getfield      #3                  // Field holder:Lorg/apache/hadoop/hbase/types/CopyOnWriteArrayMap$ArrayHolder;
      19: invokestatic  #10                 // Method org/apache/hadoop/hbase/types/CopyOnWriteArrayMap$ArrayHolder.access$100:(Lorg/apache/hadoop/hbase/types/CopyOnWriteArrayMap$ArrayHolder;)[Lorg/apache/hadoop/hbase/types/CopyOnWriteArrayMap$COWEntry;
      22: aload_0
      23: dup
      24: getfield      #5                  // Field index:I
      27: dup_x1
      28: iconst_1
      29: iadd
      30: putfield      #5                  // Field index:I
      33: aaload
      34: areturn

  public void remove();
    Code:
       0: new           #11                 // class java/lang/UnsupportedOperationException
       3: dup
       4: ldc           #12                 // String remove
       6: invokespecial #13                 // Method java/lang/UnsupportedOperationException."<init>":(Ljava/lang/String;)V
       9: athrow

  public java.lang.Object next();
    Code:
       0: aload_0
       1: invokevirtual #14                 // Method next:()Ljava/util/Map$Entry;
       4: areturn

  org.apache.hadoop.hbase.types.CopyOnWriteArrayMap$ArrayEntryIterator(org.apache.hadoop.hbase.types.CopyOnWriteArrayMap$ArrayHolder, org.apache.hadoop.hbase.types.CopyOnWriteArrayMap$1);
    Code:
       0: aload_0
       1: aload_1
       2: invokespecial #1                  // Method "<init>":(Lorg/apache/hadoop/hbase/types/CopyOnWriteArrayMap$ArrayHolder;)V
       5: return
}
