Compiled from "Counter.java"
class org.apache.hadoop.hbase.util.Counter$Cell {
  volatile long p0;

  volatile long p1;

  volatile long p2;

  volatile long p3;

  volatile long p4;

  volatile long p5;

  volatile long p6;

  volatile long value;

  volatile long q0;

  volatile long q1;

  volatile long q2;

  volatile long q3;

  volatile long q4;

  volatile long q5;

  volatile long q6;

  static final java.util.concurrent.atomic.AtomicLongFieldUpdater<org.apache.hadoop.hbase.util.Counter$Cell> valueUpdater;

  org.apache.hadoop.hbase.util.Counter$Cell();
    Code:
       0: aload_0
       1: invokespecial #1                  // Method java/lang/Object."<init>":()V
       4: return

  org.apache.hadoop.hbase.util.Counter$Cell(long);
    Code:
       0: aload_0
       1: invokespecial #1                  // Method java/lang/Object."<init>":()V
       4: aload_0
       5: lload_1
       6: putfield      #2                  // Field value:J
       9: return

  long get();
    Code:
       0: aload_0
       1: getfield      #2                  // Field value:J
       4: lreturn

  boolean add(long);
    Code:
       0: aload_0
       1: getfield      #2                  // Field value:J
       4: lstore_3
       5: getstatic     #3                  // Field valueUpdater:Ljava/util/concurrent/atomic/AtomicLongFieldUpdater;
       8: aload_0
       9: lload_3
      10: lload_3
      11: lload_1
      12: ladd
      13: invokevirtual #4                  // Method java/util/concurrent/atomic/AtomicLongFieldUpdater.compareAndSet:(Ljava/lang/Object;JJ)Z
      16: ireturn

  static {};
    Code:
       0: ldc           #5                  // class org/apache/hadoop/hbase/util/Counter$Cell
       2: ldc           #6                  // String value
       4: invokestatic  #7                  // Method java/util/concurrent/atomic/AtomicLongFieldUpdater.newUpdater:(Ljava/lang/Class;Ljava/lang/String;)Ljava/util/concurrent/atomic/AtomicLongFieldUpdater;
       7: putstatic     #3                  // Field valueUpdater:Ljava/util/concurrent/atomic/AtomicLongFieldUpdater;
      10: return
}
