Compiled from "Counter.java"
class org.apache.hadoop.hbase.util.Counter$Container {
  final org.apache.hadoop.hbase.util.Counter$Cell[] cells;

  final java.util.concurrent.atomic.AtomicBoolean demoted;

  org.apache.hadoop.hbase.util.Counter$Container(org.apache.hadoop.hbase.util.Counter$Cell);
    Code:
       0: aload_0
       1: iconst_1
       2: anewarray     #1                  // class org/apache/hadoop/hbase/util/Counter$Cell
       5: dup
       6: iconst_0
       7: aload_1
       8: aastore
       9: invokespecial #2                  // Method "<init>":([Lorg/apache/hadoop/hbase/util/Counter$Cell;)V
      12: return

  org.apache.hadoop.hbase.util.Counter$Container(org.apache.hadoop.hbase.util.Counter$Cell[]);
    Code:
       0: aload_0
       1: invokespecial #3                  // Method java/lang/Object."<init>":()V
       4: aload_0
       5: new           #4                  // class java/util/concurrent/atomic/AtomicBoolean
       8: dup
       9: invokespecial #5                  // Method java/util/concurrent/atomic/AtomicBoolean."<init>":()V
      12: putfield      #6                  // Field demoted:Ljava/util/concurrent/atomic/AtomicBoolean;
      15: aload_0
      16: aload_1
      17: putfield      #7                  // Field cells:[Lorg/apache/hadoop/hbase/util/Counter$Cell;
      20: return
}
