Compiled from "CreateTableProcedure.java"
final class org.apache.hadoop.hbase.master.procedure.CreateTableProcedure$1 implements org.apache.hadoop.hbase.master.procedure.CreateTableProcedure$CreateHdfsRegions {
  final org.apache.hadoop.hbase.client.TableDescriptor val$tableDescriptor;

  org.apache.hadoop.hbase.master.procedure.CreateTableProcedure$1(org.apache.hadoop.hbase.client.TableDescriptor);
    Code:
       0: aload_0
       1: aload_1
       2: putfield      #1                  // Field val$tableDescriptor:Lorg/apache/hadoop/hbase/client/TableDescriptor;
       5: aload_0
       6: invokespecial #2                  // Method java/lang/Object."<init>":()V
       9: return

  public java.util.List<org.apache.hadoop.hbase.client.RegionInfo> createHdfsRegions(org.apache.hadoop.hbase.master.procedure.MasterProcedureEnv, org.apache.hadoop.fs.Path, org.apache.hadoop.hbase.TableName, java.util.List<org.apache.hadoop.hbase.client.RegionInfo>) throws java.io.IOException;
    Code:
       0: aload         4
       2: ifnull        28
       5: aload         4
       7: aload         4
       9: invokeinterface #3,  1            // InterfaceMethod java/util/List.size:()I
      14: anewarray     #4                  // class org/apache/hadoop/hbase/client/RegionInfo
      17: invokeinterface #5,  2            // InterfaceMethod java/util/List.toArray:([Ljava/lang/Object;)[Ljava/lang/Object;
      22: checkcast     #6                  // class "[Lorg/apache/hadoop/hbase/client/RegionInfo;"
      25: goto          29
      28: aconst_null
      29: astore        5
      31: aload_1
      32: invokevirtual #7                  // Method org/apache/hadoop/hbase/master/procedure/MasterProcedureEnv.getMasterConfiguration:()Lorg/apache/hadoop/conf/Configuration;
      35: aload_2
      36: aload_0
      37: getfield      #1                  // Field val$tableDescriptor:Lorg/apache/hadoop/hbase/client/TableDescriptor;
      40: aload         5
      42: aconst_null
      43: invokestatic  #8                  // Method org/apache/hadoop/hbase/util/ModifyRegionUtils.createRegions:(Lorg/apache/hadoop/conf/Configuration;Lorg/apache/hadoop/fs/Path;Lorg/apache/hadoop/hbase/client/TableDescriptor;[Lorg/apache/hadoop/hbase/client/RegionInfo;Lorg/apache/hadoop/hbase/util/ModifyRegionUtils$RegionFillTask;)Ljava/util/List;
      46: areturn
}
