Compiled from "CryptoAES.java"
public class org.apache.hadoop.hbase.io.crypto.aes.CryptoAES {
  public org.apache.hadoop.hbase.io.crypto.aes.CryptoAES(java.lang.String, java.util.Properties, byte[], byte[], byte[], byte[]) throws java.io.IOException;
    Code:
       0: aload_0
       1: invokespecial #1                  // Method java/lang/Object."<init>":()V
       4: aload_0
       5: aload_1
       6: invokespecial #2                  // Method checkTransformation:(Ljava/lang/String;)V
       9: aload_0
      10: aload_1
      11: aload_2
      12: invokestatic  #3                  // Method org/apache/commons/crypto/utils/Utils.getCipherInstance:(Ljava/lang/String;Ljava/util/Properties;)Lorg/apache/commons/crypto/cipher/CryptoCipher;
      15: putfield      #4                  // Field encryptor:Lorg/apache/commons/crypto/cipher/CryptoCipher;
      18: new           #5                  // class javax/crypto/spec/SecretKeySpec
      21: dup
      22: aload         4
      24: ldc           #6                  // String AES
      26: invokespecial #7                  // Method javax/crypto/spec/SecretKeySpec."<init>":([BLjava/lang/String;)V
      29: astore        7
      31: new           #8                  // class javax/crypto/spec/IvParameterSpec
      34: dup
      35: aload         6
      37: invokespecial #9                  // Method javax/crypto/spec/IvParameterSpec."<init>":([B)V
      40: astore        8
      42: aload_0
      43: getfield      #4                  // Field encryptor:Lorg/apache/commons/crypto/cipher/CryptoCipher;
      46: iconst_1
      47: aload         7
      49: aload         8
      51: invokeinterface #11,  4           // InterfaceMethod org/apache/commons/crypto/cipher/CryptoCipher.init:(ILjava/security/Key;Ljava/security/spec/AlgorithmParameterSpec;)V
      56: goto          73
      59: astore        7
      61: new           #14                 // class java/io/IOException
      64: dup
      65: ldc           #15                 // String Failed to initialize encryptor
      67: aload         7
      69: invokespecial #16                 // Method java/io/IOException."<init>":(Ljava/lang/String;Ljava/lang/Throwable;)V
      72: athrow
      73: aload_0
      74: aload_1
      75: aload_2
      76: invokestatic  #3                  // Method org/apache/commons/crypto/utils/Utils.getCipherInstance:(Ljava/lang/String;Ljava/util/Properties;)Lorg/apache/commons/crypto/cipher/CryptoCipher;
      79: putfield      #17                 // Field decryptor:Lorg/apache/commons/crypto/cipher/CryptoCipher;
      82: new           #5                  // class javax/crypto/spec/SecretKeySpec
      85: dup
      86: aload_3
      87: ldc           #6                  // String AES
      89: invokespecial #7                  // Method javax/crypto/spec/SecretKeySpec."<init>":([BLjava/lang/String;)V
      92: astore        7
      94: new           #8                  // class javax/crypto/spec/IvParameterSpec
      97: dup
      98: aload         5
     100: invokespecial #9                  // Method javax/crypto/spec/IvParameterSpec."<init>":([B)V
     103: astore        8
     105: aload_0
     106: getfield      #17                 // Field decryptor:Lorg/apache/commons/crypto/cipher/CryptoCipher;
     109: iconst_2
     110: aload         7
     112: aload         8
     114: invokeinterface #11,  4           // InterfaceMethod org/apache/commons/crypto/cipher/CryptoCipher.init:(ILjava/security/Key;Ljava/security/spec/AlgorithmParameterSpec;)V
     119: goto          136
     122: astore        7
     124: new           #14                 // class java/io/IOException
     127: dup
     128: ldc           #18                 // String Failed to initialize decryptor
     130: aload         7
     132: invokespecial #16                 // Method java/io/IOException."<init>":(Ljava/lang/String;Ljava/lang/Throwable;)V
     135: athrow
     136: aload_0
     137: new           #19                 // class org/apache/hadoop/hbase/io/crypto/aes/CryptoAES$Integrity
     140: dup
     141: aload         4
     143: aload_3
     144: invokespecial #20                 // Method org/apache/hadoop/hbase/io/crypto/aes/CryptoAES$Integrity."<init>":([B[B)V
     147: putfield      #21                 // Field integrity:Lorg/apache/hadoop/hbase/io/crypto/aes/CryptoAES$Integrity;
     150: return
    Exception table:
       from    to  target type
          18    56    59   Class java/security/InvalidKeyException
          18    56    59   Class java/security/InvalidAlgorithmParameterException
          82   119   122   Class java/security/InvalidKeyException
          82   119   122   Class java/security/InvalidAlgorithmParameterException

  public byte[] wrap(byte[], int, int) throws javax.security.sasl.SaslException;
    Code:
       0: aload_0
       1: getfield      #21                 // Field integrity:Lorg/apache/hadoop/hbase/io/crypto/aes/CryptoAES$Integrity;
       4: aload_1
       5: iload_2
       6: iload_3
       7: invokevirtual #22                 // Method org/apache/hadoop/hbase/io/crypto/aes/CryptoAES$Integrity.getHMAC:([BII)[B
      10: astore        4
      12: aload_0
      13: getfield      #21                 // Field integrity:Lorg/apache/hadoop/hbase/io/crypto/aes/CryptoAES$Integrity;
      16: invokevirtual #23                 // Method org/apache/hadoop/hbase/io/crypto/aes/CryptoAES$Integrity.incMySeqNum:()V
      19: iload_3
      20: bipush        10
      22: iadd
      23: newarray       byte
      25: astore        5
      27: aload_0
      28: getfield      #4                  // Field encryptor:Lorg/apache/commons/crypto/cipher/CryptoCipher;
      31: aload_1
      32: iload_2
      33: iload_3
      34: aload         5
      36: iconst_0
      37: invokeinterface #24,  6           // InterfaceMethod org/apache/commons/crypto/cipher/CryptoCipher.update:([BII[BI)I
      42: istore        6
      44: aload_0
      45: getfield      #4                  // Field encryptor:Lorg/apache/commons/crypto/cipher/CryptoCipher;
      48: aload         4
      50: iconst_0
      51: bipush        10
      53: aload         5
      55: iload         6
      57: invokeinterface #24,  6           // InterfaceMethod org/apache/commons/crypto/cipher/CryptoCipher.update:([BII[BI)I
      62: pop
      63: goto          80
      66: astore        6
      68: new           #26                 // class javax/security/sasl/SaslException
      71: dup
      72: ldc           #27                 // String Error happens during encrypt data
      74: aload         6
      76: invokespecial #28                 // Method javax/security/sasl/SaslException."<init>":(Ljava/lang/String;Ljava/lang/Throwable;)V
      79: athrow
      80: aload         5
      82: arraylength
      83: iconst_4
      84: iadd
      85: newarray       byte
      87: astore        6
      89: aload         5
      91: iconst_0
      92: aload         6
      94: iconst_0
      95: aload         5
      97: arraylength
      98: invokestatic  #29                 // Method java/lang/System.arraycopy:(Ljava/lang/Object;ILjava/lang/Object;II)V
     101: aload_0
     102: getfield      #21                 // Field integrity:Lorg/apache/hadoop/hbase/io/crypto/aes/CryptoAES$Integrity;
     105: invokevirtual #30                 // Method org/apache/hadoop/hbase/io/crypto/aes/CryptoAES$Integrity.getSeqNum:()[B
     108: iconst_0
     109: aload         6
     111: aload         5
     113: arraylength
     114: iconst_4
     115: invokestatic  #29                 // Method java/lang/System.arraycopy:(Ljava/lang/Object;ILjava/lang/Object;II)V
     118: aload         6
     120: areturn
    Exception table:
       from    to  target type
          27    63    66   Class javax/crypto/ShortBufferException

  public byte[] unwrap(byte[], int, int) throws javax.security.sasl.SaslException;
    Code:
       0: iload_3
       1: iconst_4
       2: isub
       3: newarray       byte
       5: astore        4
       7: iconst_4
       8: newarray       byte
      10: astore        5
      12: aload_0
      13: getfield      #17                 // Field decryptor:Lorg/apache/commons/crypto/cipher/CryptoCipher;
      16: aload_1
      17: iload_2
      18: iload_3
      19: iconst_4
      20: isub
      21: aload         4
      23: iconst_0
      24: invokeinterface #24,  6           // InterfaceMethod org/apache/commons/crypto/cipher/CryptoCipher.update:([BII[BI)I
      29: pop
      30: goto          47
      33: astore        6
      35: new           #26                 // class javax/security/sasl/SaslException
      38: dup
      39: ldc           #31                 // String Error happens during decrypt data
      41: aload         6
      43: invokespecial #28                 // Method javax/security/sasl/SaslException."<init>":(Ljava/lang/String;Ljava/lang/Throwable;)V
      46: athrow
      47: aload_1
      48: iload_2
      49: aload         4
      51: arraylength
      52: iadd
      53: aload         5
      55: iconst_0
      56: iconst_4
      57: invokestatic  #29                 // Method java/lang/System.arraycopy:(Ljava/lang/Object;ILjava/lang/Object;II)V
      60: aload         4
      62: arraylength
      63: bipush        10
      65: isub
      66: newarray       byte
      68: astore        6
      70: bipush        10
      72: newarray       byte
      74: astore        7
      76: aload         4
      78: iconst_0
      79: aload         6
      81: iconst_0
      82: aload         6
      84: arraylength
      85: invokestatic  #29                 // Method java/lang/System.arraycopy:(Ljava/lang/Object;ILjava/lang/Object;II)V
      88: aload         4
      90: aload         6
      92: arraylength
      93: aload         7
      95: iconst_0
      96: bipush        10
      98: invokestatic  #29                 // Method java/lang/System.arraycopy:(Ljava/lang/Object;ILjava/lang/Object;II)V
     101: aload_0
     102: getfield      #21                 // Field integrity:Lorg/apache/hadoop/hbase/io/crypto/aes/CryptoAES$Integrity;
     105: aload         7
     107: aload         5
     109: aload         6
     111: iconst_0
     112: aload         6
     114: arraylength
     115: invokevirtual #32                 // Method org/apache/hadoop/hbase/io/crypto/aes/CryptoAES$Integrity.compareHMAC:([B[B[BII)Z
     118: ifne          131
     121: new           #26                 // class javax/security/sasl/SaslException
     124: dup
     125: ldc           #33                 // String Unmatched MAC
     127: invokespecial #34                 // Method javax/security/sasl/SaslException."<init>":(Ljava/lang/String;)V
     130: athrow
     131: aload_0
     132: getfield      #21                 // Field integrity:Lorg/apache/hadoop/hbase/io/crypto/aes/CryptoAES$Integrity;
     135: aload         5
     137: invokevirtual #35                 // Method org/apache/hadoop/hbase/io/crypto/aes/CryptoAES$Integrity.comparePeerSeqNum:([B)Z
     140: ifne          193
     143: new           #26                 // class javax/security/sasl/SaslException
     146: dup
     147: new           #36                 // class java/lang/StringBuilder
     150: dup
     151: invokespecial #37                 // Method java/lang/StringBuilder."<init>":()V
     154: ldc           #38                 // String Out of order sequencing of messages. Got:
     156: invokevirtual #39                 // Method java/lang/StringBuilder.append:(Ljava/lang/String;)Ljava/lang/StringBuilder;
     159: aload_0
     160: getfield      #21                 // Field integrity:Lorg/apache/hadoop/hbase/io/crypto/aes/CryptoAES$Integrity;
     163: aload         5
     165: invokestatic  #40                 // Method org/apache/hadoop/hbase/io/crypto/aes/CryptoAES$Integrity.access$000:(Lorg/apache/hadoop/hbase/io/crypto/aes/CryptoAES$Integrity;[B)I
     168: invokevirtual #41                 // Method java/lang/StringBuilder.append:(I)Ljava/lang/StringBuilder;
     171: ldc           #42                 // String  Expected:
     173: invokevirtual #39                 // Method java/lang/StringBuilder.append:(Ljava/lang/String;)Ljava/lang/StringBuilder;
     176: aload_0
     177: getfield      #21                 // Field integrity:Lorg/apache/hadoop/hbase/io/crypto/aes/CryptoAES$Integrity;
     180: invokestatic  #43                 // Method org/apache/hadoop/hbase/io/crypto/aes/CryptoAES$Integrity.access$100:(Lorg/apache/hadoop/hbase/io/crypto/aes/CryptoAES$Integrity;)I
     183: invokevirtual #41                 // Method java/lang/StringBuilder.append:(I)Ljava/lang/StringBuilder;
     186: invokevirtual #44                 // Method java/lang/StringBuilder.toString:()Ljava/lang/String;
     189: invokespecial #34                 // Method javax/security/sasl/SaslException."<init>":(Ljava/lang/String;)V
     192: athrow
     193: aload_0
     194: getfield      #21                 // Field integrity:Lorg/apache/hadoop/hbase/io/crypto/aes/CryptoAES$Integrity;
     197: invokevirtual #45                 // Method org/apache/hadoop/hbase/io/crypto/aes/CryptoAES$Integrity.incPeerSeqNum:()V
     200: aload         6
     202: areturn
    Exception table:
       from    to  target type
          12    30    33   Class javax/crypto/ShortBufferException
}
