Compiled from "CurrentHourProvider.java"
public class org.apache.hadoop.hbase.regionserver.compactions.CurrentHourProvider {
  public static int getCurrentHour();
    Code:
       0: getstatic     #14                 // Field tick:Lorg/apache/hadoop/hbase/regionserver/compactions/CurrentHourProvider$Tick;
       3: astore_0
       4: invokestatic  #15                 // Method java/lang/System.currentTimeMillis:()J
       7: aload_0
       8: getfield      #16                 // Field org/apache/hadoop/hbase/regionserver/compactions/CurrentHourProvider$Tick.expirationTimeInMillis:J
      11: lcmp
      12: ifge          20
      15: aload_0
      16: getfield      #17                 // Field org/apache/hadoop/hbase/regionserver/compactions/CurrentHourProvider$Tick.currentHour:I
      19: ireturn
      20: invokestatic  #18                 // Method nextTick:()Lorg/apache/hadoop/hbase/regionserver/compactions/CurrentHourProvider$Tick;
      23: dup
      24: astore_0
      25: putstatic     #14                 // Field tick:Lorg/apache/hadoop/hbase/regionserver/compactions/CurrentHourProvider$Tick;
      28: aload_0
      29: getfield      #17                 // Field org/apache/hadoop/hbase/regionserver/compactions/CurrentHourProvider$Tick.currentHour:I
      32: ireturn

  static {};
    Code:
       0: invokestatic  #18                 // Method nextTick:()Lorg/apache/hadoop/hbase/regionserver/compactions/CurrentHourProvider$Tick;
       3: putstatic     #14                 // Field tick:Lorg/apache/hadoop/hbase/regionserver/compactions/CurrentHourProvider$Tick;
       6: return
}
