Compiled from "DataBlockEncoding.java"
public final class org.apache.hadoop.hbase.io.encoding.DataBlockEncoding extends java.lang.Enum<org.apache.hadoop.hbase.io.encoding.DataBlockEncoding> {
  public static final org.apache.hadoop.hbase.io.encoding.DataBlockEncoding NONE;

  public static final org.apache.hadoop.hbase.io.encoding.DataBlockEncoding PREFIX;

  public static final org.apache.hadoop.hbase.io.encoding.DataBlockEncoding DIFF;

  public static final org.apache.hadoop.hbase.io.encoding.DataBlockEncoding FAST_DIFF;

  public static final org.apache.hadoop.hbase.io.encoding.DataBlockEncoding ROW_INDEX_V1;

  public static final int ID_SIZE;

  public static org.apache.hadoop.hbase.io.encoding.DataBlockEncoding[] values();
    Code:
       0: getstatic     #2                  // Field $VALUES:[Lorg/apache/hadoop/hbase/io/encoding/DataBlockEncoding;
       3: invokevirtual #3                  // Method "[Lorg/apache/hadoop/hbase/io/encoding/DataBlockEncoding;".clone:()Ljava/lang/Object;
       6: checkcast     #4                  // class "[Lorg/apache/hadoop/hbase/io/encoding/DataBlockEncoding;"
       9: areturn

  public static org.apache.hadoop.hbase.io.encoding.DataBlockEncoding valueOf(java.lang.String);
    Code:
       0: ldc           #5                  // class org/apache/hadoop/hbase/io/encoding/DataBlockEncoding
       2: aload_0
       3: invokestatic  #6                  // Method java/lang/Enum.valueOf:(Ljava/lang/Class;Ljava/lang/String;)Ljava/lang/Enum;
       6: checkcast     #5                  // class org/apache/hadoop/hbase/io/encoding/DataBlockEncoding
       9: areturn

  public byte[] getNameInBytes();
    Code:
       0: aload_0
       1: invokevirtual #25                 // Method toString:()Ljava/lang/String;
       4: invokestatic  #26                 // Method org/apache/hadoop/hbase/util/Bytes.toBytes:(Ljava/lang/String;)[B
       7: areturn

  public short getId();
    Code:
       0: aload_0
       1: getfield      #17                 // Field id:S
       4: ireturn

  public void writeIdInBytes(java.io.OutputStream) throws java.io.IOException;
    Code:
       0: aload_1
       1: aload_0
       2: getfield      #19                 // Field idInBytes:[B
       5: invokevirtual #27                 // Method java/io/OutputStream.write:([B)V
       8: return

  public void writeIdInBytes(byte[], int) throws java.io.IOException;
    Code:
       0: aload_0
       1: getfield      #19                 // Field idInBytes:[B
       4: iconst_0
       5: aload_1
       6: iload_2
       7: iconst_2
       8: invokestatic  #28                 // Method java/lang/System.arraycopy:(Ljava/lang/Object;ILjava/lang/Object;II)V
      11: return

  public org.apache.hadoop.hbase.io.encoding.DataBlockEncoder getEncoder();
    Code:
       0: aload_0
       1: getfield      #29                 // Field encoder:Lorg/apache/hadoop/hbase/io/encoding/DataBlockEncoder;
       4: ifnonnull     25
       7: aload_0
       8: getfield      #17                 // Field id:S
      11: ifeq          25
      14: aload_0
      15: aload_0
      16: getfield      #24                 // Field encoderCls:Ljava/lang/String;
      19: invokestatic  #30                 // Method createEncoder:(Ljava/lang/String;)Lorg/apache/hadoop/hbase/io/encoding/DataBlockEncoder;
      22: putfield      #29                 // Field encoder:Lorg/apache/hadoop/hbase/io/encoding/DataBlockEncoder;
      25: aload_0
      26: getfield      #29                 // Field encoder:Lorg/apache/hadoop/hbase/io/encoding/DataBlockEncoder;
      29: areturn

  public static org.apache.hadoop.hbase.io.encoding.DataBlockEncoder getDataBlockEncoderById(short);
    Code:
       0: iload_0
       1: invokestatic  #31                 // Method getEncodingById:(S)Lorg/apache/hadoop/hbase/io/encoding/DataBlockEncoding;
       4: invokevirtual #32                 // Method getEncoder:()Lorg/apache/hadoop/hbase/io/encoding/DataBlockEncoder;
       7: areturn

  public static java.lang.String getNameFromId(short);
    Code:
       0: iload_0
       1: invokestatic  #31                 // Method getEncodingById:(S)Lorg/apache/hadoop/hbase/io/encoding/DataBlockEncoding;
       4: invokevirtual #25                 // Method toString:()Ljava/lang/String;
       7: areturn

  public static boolean isCorrectEncoder(org.apache.hadoop.hbase.io.encoding.DataBlockEncoder, short);
    Code:
       0: iload_1
       1: invokestatic  #31                 // Method getEncodingById:(S)Lorg/apache/hadoop/hbase/io/encoding/DataBlockEncoding;
       4: astore_2
       5: aload_0
       6: invokevirtual #33                 // Method java/lang/Object.getClass:()Ljava/lang/Class;
       9: invokevirtual #34                 // Method java/lang/Class.getName:()Ljava/lang/String;
      12: astore_3
      13: aload_3
      14: aload_2
      15: getfield      #24                 // Field encoderCls:Ljava/lang/String;
      18: invokevirtual #35                 // Method java/lang/String.equals:(Ljava/lang/Object;)Z
      21: ireturn

  public static org.apache.hadoop.hbase.io.encoding.DataBlockEncoding getEncodingById(short);
    Code:
       0: aconst_null
       1: astore_1
       2: iload_0
       3: iflt          18
       6: iload_0
       7: bipush        127
       9: if_icmpgt     18
      12: getstatic     #36                 // Field idArray:[Lorg/apache/hadoop/hbase/io/encoding/DataBlockEncoding;
      15: iload_0
      16: aaload
      17: astore_1
      18: aload_1
      19: ifnonnull     46
      22: new           #37                 // class java/lang/IllegalArgumentException
      25: dup
      26: ldc           #38                 // String There is no data block encoder for given id '%d'
      28: iconst_1
      29: anewarray     #39                 // class java/lang/Object
      32: dup
      33: iconst_0
      34: iload_0
      35: invokestatic  #40                 // Method java/lang/Integer.valueOf:(I)Ljava/lang/Integer;
      38: aastore
      39: invokestatic  #41                 // Method java/lang/String.format:(Ljava/lang/String;[Ljava/lang/Object;)Ljava/lang/String;
      42: invokespecial #42                 // Method java/lang/IllegalArgumentException."<init>":(Ljava/lang/String;)V
      45: athrow
      46: aload_1
      47: areturn

  protected static org.apache.hadoop.hbase.io.encoding.DataBlockEncoder createEncoder(java.lang.String);
    Code:
       0: aload_0
       1: invokestatic  #43                 // Method java/lang/Class.forName:(Ljava/lang/String;)Ljava/lang/Class;
       4: iconst_0
       5: anewarray     #44                 // class java/lang/Class
       8: invokevirtual #45                 // Method java/lang/Class.getDeclaredConstructor:([Ljava/lang/Class;)Ljava/lang/reflect/Constructor;
      11: iconst_0
      12: anewarray     #39                 // class java/lang/Object
      15: invokevirtual #46                 // Method java/lang/reflect/Constructor.newInstance:([Ljava/lang/Object;)Ljava/lang/Object;
      18: checkcast     #47                 // class org/apache/hadoop/hbase/io/encoding/DataBlockEncoder
      21: areturn
      22: astore_1
      23: new           #20                 // class java/lang/RuntimeException
      26: dup
      27: aload_1
      28: invokespecial #49                 // Method java/lang/RuntimeException."<init>":(Ljava/lang/Throwable;)V
      31: athrow
    Exception table:
       from    to  target type
           0    21    22   Class java/lang/Exception

  static {};
    Code:
       0: new           #5                  // class org/apache/hadoop/hbase/io/encoding/DataBlockEncoding
       3: dup
       4: ldc           #50                 // String NONE
       6: iconst_0
       7: iconst_0
       8: aconst_null
       9: invokespecial #51                 // Method "<init>":(Ljava/lang/String;IILjava/lang/String;)V
      12: putstatic     #52                 // Field NONE:Lorg/apache/hadoop/hbase/io/encoding/DataBlockEncoding;
      15: new           #5                  // class org/apache/hadoop/hbase/io/encoding/DataBlockEncoding
      18: dup
      19: ldc           #53                 // String PREFIX
      21: iconst_1
      22: iconst_2
      23: ldc           #54                 // String org.apache.hadoop.hbase.io.encoding.PrefixKeyDeltaEncoder
      25: invokespecial #51                 // Method "<init>":(Ljava/lang/String;IILjava/lang/String;)V
      28: putstatic     #55                 // Field PREFIX:Lorg/apache/hadoop/hbase/io/encoding/DataBlockEncoding;
      31: new           #5                  // class org/apache/hadoop/hbase/io/encoding/DataBlockEncoding
      34: dup
      35: ldc           #56                 // String DIFF
      37: iconst_2
      38: iconst_3
      39: ldc           #57                 // String org.apache.hadoop.hbase.io.encoding.DiffKeyDeltaEncoder
      41: invokespecial #51                 // Method "<init>":(Ljava/lang/String;IILjava/lang/String;)V
      44: putstatic     #58                 // Field DIFF:Lorg/apache/hadoop/hbase/io/encoding/DataBlockEncoding;
      47: new           #5                  // class org/apache/hadoop/hbase/io/encoding/DataBlockEncoding
      50: dup
      51: ldc           #59                 // String FAST_DIFF
      53: iconst_3
      54: iconst_4
      55: ldc           #60                 // String org.apache.hadoop.hbase.io.encoding.FastDiffDeltaEncoder
      57: invokespecial #51                 // Method "<init>":(Ljava/lang/String;IILjava/lang/String;)V
      60: putstatic     #61                 // Field FAST_DIFF:Lorg/apache/hadoop/hbase/io/encoding/DataBlockEncoding;
      63: new           #5                  // class org/apache/hadoop/hbase/io/encoding/DataBlockEncoding
      66: dup
      67: ldc           #62                 // String ROW_INDEX_V1
      69: iconst_4
      70: bipush        7
      72: ldc           #63                 // String org.apache.hadoop.hbase.io.encoding.RowIndexCodecV1
      74: invokespecial #51                 // Method "<init>":(Ljava/lang/String;IILjava/lang/String;)V
      77: putstatic     #64                 // Field ROW_INDEX_V1:Lorg/apache/hadoop/hbase/io/encoding/DataBlockEncoding;
      80: iconst_5
      81: anewarray     #5                  // class org/apache/hadoop/hbase/io/encoding/DataBlockEncoding
      84: dup
      85: iconst_0
      86: getstatic     #52                 // Field NONE:Lorg/apache/hadoop/hbase/io/encoding/DataBlockEncoding;
      89: aastore
      90: dup
      91: iconst_1
      92: getstatic     #55                 // Field PREFIX:Lorg/apache/hadoop/hbase/io/encoding/DataBlockEncoding;
      95: aastore
      96: dup
      97: iconst_2
      98: getstatic     #58                 // Field DIFF:Lorg/apache/hadoop/hbase/io/encoding/DataBlockEncoding;
     101: aastore
     102: dup
     103: iconst_3
     104: getstatic     #61                 // Field FAST_DIFF:Lorg/apache/hadoop/hbase/io/encoding/DataBlockEncoding;
     107: aastore
     108: dup
     109: iconst_4
     110: getstatic     #64                 // Field ROW_INDEX_V1:Lorg/apache/hadoop/hbase/io/encoding/DataBlockEncoding;
     113: aastore
     114: putstatic     #2                  // Field $VALUES:[Lorg/apache/hadoop/hbase/io/encoding/DataBlockEncoding;
     117: sipush        128
     120: anewarray     #5                  // class org/apache/hadoop/hbase/io/encoding/DataBlockEncoding
     123: putstatic     #36                 // Field idArray:[Lorg/apache/hadoop/hbase/io/encoding/DataBlockEncoding;
     126: invokestatic  #65                 // Method values:()[Lorg/apache/hadoop/hbase/io/encoding/DataBlockEncoding;
     129: astore_0
     130: aload_0
     131: arraylength
     132: istore_1
     133: iconst_0
     134: istore_2
     135: iload_2
     136: iload_1
     137: if_icmpge     218
     140: aload_0
     141: iload_2
     142: aaload
     143: astore_3
     144: getstatic     #36                 // Field idArray:[Lorg/apache/hadoop/hbase/io/encoding/DataBlockEncoding;
     147: aload_3
     148: getfield      #17                 // Field id:S
     151: aaload
     152: ifnull        203
     155: new           #20                 // class java/lang/RuntimeException
     158: dup
     159: ldc           #66                 // String Two data block encoder algorithms '%s' and '%s' have the same id %d
     161: iconst_3
     162: anewarray     #39                 // class java/lang/Object
     165: dup
     166: iconst_0
     167: getstatic     #36                 // Field idArray:[Lorg/apache/hadoop/hbase/io/encoding/DataBlockEncoding;
     170: aload_3
     171: getfield      #17                 // Field id:S
     174: aaload
     175: invokevirtual #25                 // Method toString:()Ljava/lang/String;
     178: aastore
     179: dup
     180: iconst_1
     181: aload_3
     182: invokevirtual #25                 // Method toString:()Ljava/lang/String;
     185: aastore
     186: dup
     187: iconst_2
     188: aload_3
     189: getfield      #17                 // Field id:S
     192: invokestatic  #40                 // Method java/lang/Integer.valueOf:(I)Ljava/lang/Integer;
     195: aastore
     196: invokestatic  #41                 // Method java/lang/String.format:(Ljava/lang/String;[Ljava/lang/Object;)Ljava/lang/String;
     199: invokespecial #23                 // Method java/lang/RuntimeException."<init>":(Ljava/lang/String;)V
     202: athrow
     203: getstatic     #36                 // Field idArray:[Lorg/apache/hadoop/hbase/io/encoding/DataBlockEncoding;
     206: aload_3
     207: getfield      #17                 // Field id:S
     210: aload_3
     211: aastore
     212: iinc          2, 1
     215: goto          135
     218: return
}
