Compiled from "DataBlockEncodingTool.java"
public class org.apache.hadoop.hbase.regionserver.DataBlockEncodingTool {
  public org.apache.hadoop.hbase.regionserver.DataBlockEncodingTool(java.lang.String);
    Code:
       0: aload_0
       1: invokespecial #2                  // Method java/lang/Object."<init>":()V
       4: aload_0
       5: new           #3                  // class java/util/ArrayList
       8: dup
       9: invokespecial #4                  // Method java/util/ArrayList."<init>":()V
      12: putfield      #5                  // Field codecs:Ljava/util/List;
      15: aload_0
      16: lconst_0
      17: putfield      #6                  // Field totalPrefixLength:J
      20: aload_0
      21: lconst_0
      22: putfield      #7                  // Field totalKeyLength:J
      25: aload_0
      26: lconst_0
      27: putfield      #8                  // Field totalValueLength:J
      30: aload_0
      31: lconst_0
      32: putfield      #9                  // Field totalKeyRedundancyLength:J
      35: aload_0
      36: lconst_0
      37: putfield      #10                 // Field totalCFLength:J
      40: aload_0
      41: iconst_0
      42: putfield      #11                 // Field useHBaseChecksum:Z
      45: aload_0
      46: aload_1
      47: putfield      #12                 // Field compressionAlgorithmName:Ljava/lang/String;
      50: aload_0
      51: aload_1
      52: invokestatic  #13                 // Method org/apache/hadoop/hbase/io/compress/Compression.getCompressionAlgorithmByName:(Ljava/lang/String;)Lorg/apache/hadoop/hbase/io/compress/Compression$Algorithm;
      55: putfield      #14                 // Field compressionAlgorithm:Lorg/apache/hadoop/hbase/io/compress/Compression$Algorithm;
      58: aload_0
      59: aload_0
      60: getfield      #14                 // Field compressionAlgorithm:Lorg/apache/hadoop/hbase/io/compress/Compression$Algorithm;
      63: invokevirtual #15                 // Method org/apache/hadoop/hbase/io/compress/Compression$Algorithm.getCompressor:()Lorg/apache/hadoop/io/compress/Compressor;
      66: putfield      #16                 // Field compressor:Lorg/apache/hadoop/io/compress/Compressor;
      69: aload_0
      70: aload_0
      71: getfield      #14                 // Field compressionAlgorithm:Lorg/apache/hadoop/hbase/io/compress/Compression$Algorithm;
      74: invokevirtual #17                 // Method org/apache/hadoop/hbase/io/compress/Compression$Algorithm.getDecompressor:()Lorg/apache/hadoop/io/compress/Decompressor;
      77: putfield      #18                 // Field decompressor:Lorg/apache/hadoop/io/compress/Decompressor;
      80: return

  public void checkStatistics(org.apache.hadoop.hbase.regionserver.KeyValueScanner, int) throws java.io.IOException;
    Code:
       0: aload_1
       1: getstatic     #19                 // Field org/apache/hadoop/hbase/KeyValue.LOWESTKEY:Lorg/apache/hadoop/hbase/KeyValue;
       4: invokeinterface #20,  2           // InterfaceMethod org/apache/hadoop/hbase/regionserver/KeyValueScanner.seek:(Lorg/apache/hadoop/hbase/Cell;)Z
       9: pop
      10: aconst_null
      11: astore        4
      13: invokestatic  #21                 // Method org/apache/hadoop/hbase/io/encoding/DataBlockEncoding.values:()[Lorg/apache/hadoop/hbase/io/encoding/DataBlockEncoding;
      16: astore        6
      18: new           #22                 // class java/io/ByteArrayOutputStream
      21: dup
      22: invokespecial #23                 // Method java/io/ByteArrayOutputStream."<init>":()V
      25: astore        7
      27: iconst_0
      28: istore        8
      30: aload_1
      31: invokeinterface #24,  1           // InterfaceMethod org/apache/hadoop/hbase/regionserver/KeyValueScanner.next:()Lorg/apache/hadoop/hbase/Cell;
      36: invokestatic  #25                 // Method org/apache/hadoop/hbase/KeyValueUtil.ensureKeyValue:(Lorg/apache/hadoop/hbase/Cell;)Lorg/apache/hadoop/hbase/KeyValue;
      39: dup
      40: astore_3
      41: ifnull        276
      44: iload         8
      46: iload_2
      47: if_icmpge     276
      50: iinc          8, 1
      53: aload_3
      54: invokevirtual #26                 // Method org/apache/hadoop/hbase/KeyValue.getKey:()[B
      57: astore        5
      59: aload         4
      61: ifnull        112
      64: iconst_0
      65: istore        9
      67: iload         9
      69: aload         4
      71: arraylength
      72: if_icmpge     112
      75: iload         9
      77: aload         5
      79: arraylength
      80: if_icmpge     112
      83: aload         4
      85: iload         9
      87: baload
      88: aload         5
      90: iload         9
      92: baload
      93: if_icmpne     112
      96: aload_0
      97: dup
      98: getfield      #9                  // Field totalKeyRedundancyLength:J
     101: lconst_1
     102: ladd
     103: putfield      #9                  // Field totalKeyRedundancyLength:J
     106: iinc          9, 1
     109: goto          67
     112: getstatic     #27                 // Field USE_TAG:Z
     115: ifeq          154
     118: aload_3
     119: invokevirtual #28                 // Method org/apache/hadoop/hbase/KeyValue.getTagsLength:()I
     122: ifne          154
     125: aload         7
     127: aload_3
     128: invokevirtual #29                 // Method org/apache/hadoop/hbase/KeyValue.getBuffer:()[B
     131: aload_3
     132: invokevirtual #30                 // Method org/apache/hadoop/hbase/KeyValue.getOffset:()I
     135: aload_3
     136: invokevirtual #31                 // Method org/apache/hadoop/hbase/KeyValue.getLength:()I
     139: invokevirtual #32                 // Method java/io/ByteArrayOutputStream.write:([BII)V
     142: aload         7
     144: iconst_0
     145: invokestatic  #33                 // Method org/apache/hadoop/hbase/util/Bytes.toBytes:(S)[B
     148: invokevirtual #34                 // Method java/io/ByteArrayOutputStream.write:([B)V
     151: goto          171
     154: aload         7
     156: aload_3
     157: invokevirtual #29                 // Method org/apache/hadoop/hbase/KeyValue.getBuffer:()[B
     160: aload_3
     161: invokevirtual #30                 // Method org/apache/hadoop/hbase/KeyValue.getOffset:()I
     164: aload_3
     165: invokevirtual #31                 // Method org/apache/hadoop/hbase/KeyValue.getLength:()I
     168: invokevirtual #32                 // Method java/io/ByteArrayOutputStream.write:([BII)V
     171: new           #35                 // class java/io/DataOutputStream
     174: dup
     175: aload         7
     177: invokespecial #36                 // Method java/io/DataOutputStream."<init>":(Ljava/io/OutputStream;)V
     180: aload_3
     181: invokevirtual #37                 // Method org/apache/hadoop/hbase/KeyValue.getSequenceId:()J
     184: invokestatic  #38                 // Method org/apache/hadoop/io/WritableUtils.writeVLong:(Ljava/io/DataOutput;J)V
     187: aload         5
     189: astore        4
     191: aload_3
     192: invokevirtual #39                 // Method org/apache/hadoop/hbase/KeyValue.getKeyLength:()I
     195: istore        9
     197: aload_3
     198: invokevirtual #40                 // Method org/apache/hadoop/hbase/KeyValue.getValueLength:()I
     201: istore        10
     203: aload_3
     204: aload_3
     205: invokevirtual #41                 // Method org/apache/hadoop/hbase/KeyValue.getFamilyOffset:()I
     208: invokevirtual #42                 // Method org/apache/hadoop/hbase/KeyValue.getFamilyLength:(I)B
     211: istore        11
     213: aload_3
     214: invokevirtual #31                 // Method org/apache/hadoop/hbase/KeyValue.getLength:()I
     217: iload         9
     219: isub
     220: iload         10
     222: isub
     223: istore        12
     225: aload_0
     226: dup
     227: getfield      #7                  // Field totalKeyLength:J
     230: iload         9
     232: i2l
     233: ladd
     234: putfield      #7                  // Field totalKeyLength:J
     237: aload_0
     238: dup
     239: getfield      #8                  // Field totalValueLength:J
     242: iload         10
     244: i2l
     245: ladd
     246: putfield      #8                  // Field totalValueLength:J
     249: aload_0
     250: dup
     251: getfield      #6                  // Field totalPrefixLength:J
     254: iload         12
     256: i2l
     257: ladd
     258: putfield      #6                  // Field totalPrefixLength:J
     261: aload_0
     262: dup
     263: getfield      #10                 // Field totalCFLength:J
     266: iload         11
     268: i2l
     269: ladd
     270: putfield      #10                 // Field totalCFLength:J
     273: goto          30
     276: aload_0
     277: aload         7
     279: invokevirtual #43                 // Method java/io/ByteArrayOutputStream.toByteArray:()[B
     282: putfield      #44                 // Field rawKVs:[B
     285: aload         6
     287: astore        9
     289: aload         9
     291: arraylength
     292: istore        10
     294: iconst_0
     295: istore        11
     297: iload         11
     299: iload         10
     301: if_icmpge     395
     304: aload         9
     306: iload         11
     308: aaload
     309: astore        12
     311: aload         12
     313: getstatic     #45                 // Field org/apache/hadoop/hbase/io/encoding/DataBlockEncoding.NONE:Lorg/apache/hadoop/hbase/io/encoding/DataBlockEncoding;
     316: if_acmpne     322
     319: goto          389
     322: aload         12
     324: invokevirtual #46                 // Method org/apache/hadoop/hbase/io/encoding/DataBlockEncoding.getEncoder:()Lorg/apache/hadoop/hbase/io/encoding/DataBlockEncoder;
     327: astore        13
     329: new           #47                 // class org/apache/hadoop/hbase/io/hfile/HFileContextBuilder
     332: dup
     333: invokespecial #48                 // Method org/apache/hadoop/hbase/io/hfile/HFileContextBuilder."<init>":()V
     336: aload         12
     338: invokevirtual #49                 // Method org/apache/hadoop/hbase/io/hfile/HFileContextBuilder.withDataBlockEncoding:(Lorg/apache/hadoop/hbase/io/encoding/DataBlockEncoding;)Lorg/apache/hadoop/hbase/io/hfile/HFileContextBuilder;
     341: getstatic     #50                 // Field org/apache/hadoop/hbase/io/compress/Compression$Algorithm.NONE:Lorg/apache/hadoop/hbase/io/compress/Compression$Algorithm;
     344: invokevirtual #51                 // Method org/apache/hadoop/hbase/io/hfile/HFileContextBuilder.withCompression:(Lorg/apache/hadoop/hbase/io/compress/Compression$Algorithm;)Lorg/apache/hadoop/hbase/io/hfile/HFileContextBuilder;
     347: iconst_1
     348: invokevirtual #52                 // Method org/apache/hadoop/hbase/io/hfile/HFileContextBuilder.withIncludesMvcc:(Z)Lorg/apache/hadoop/hbase/io/hfile/HFileContextBuilder;
     351: getstatic     #27                 // Field USE_TAG:Z
     354: invokevirtual #53                 // Method org/apache/hadoop/hbase/io/hfile/HFileContextBuilder.withIncludesTags:(Z)Lorg/apache/hadoop/hbase/io/hfile/HFileContextBuilder;
     357: invokevirtual #54                 // Method org/apache/hadoop/hbase/io/hfile/HFileContextBuilder.build:()Lorg/apache/hadoop/hbase/io/hfile/HFileContext;
     360: astore        14
     362: aload_0
     363: getfield      #5                  // Field codecs:Ljava/util/List;
     366: new           #55                 // class org/apache/hadoop/hbase/io/encoding/EncodedDataBlock
     369: dup
     370: aload         13
     372: aload         12
     374: aload_0
     375: getfield      #44                 // Field rawKVs:[B
     378: aload         14
     380: invokespecial #56                 // Method org/apache/hadoop/hbase/io/encoding/EncodedDataBlock."<init>":(Lorg/apache/hadoop/hbase/io/encoding/DataBlockEncoder;Lorg/apache/hadoop/hbase/io/encoding/DataBlockEncoding;[BLorg/apache/hadoop/hbase/io/hfile/HFileContext;)V
     383: invokeinterface #57,  2           // InterfaceMethod java/util/List.add:(Ljava/lang/Object;)Z
     388: pop
     389: iinc          11, 1
     392: goto          297
     395: return

  public boolean verifyCodecs(org.apache.hadoop.hbase.regionserver.KeyValueScanner, int) throws java.io.IOException;
    Code:
       0: aload_1
       1: getstatic     #19                 // Field org/apache/hadoop/hbase/KeyValue.LOWESTKEY:Lorg/apache/hadoop/hbase/KeyValue;
       4: invokeinterface #20,  2           // InterfaceMethod org/apache/hadoop/hbase/regionserver/KeyValueScanner.seek:(Lorg/apache/hadoop/hbase/Cell;)Z
       9: pop
      10: new           #3                  // class java/util/ArrayList
      13: dup
      14: invokespecial #4                  // Method java/util/ArrayList."<init>":()V
      17: astore        4
      19: aload_0
      20: getfield      #5                  // Field codecs:Ljava/util/List;
      23: invokeinterface #58,  1           // InterfaceMethod java/util/List.iterator:()Ljava/util/Iterator;
      28: astore        5
      30: aload         5
      32: invokeinterface #59,  1           // InterfaceMethod java/util/Iterator.hasNext:()Z
      37: ifeq          75
      40: aload         5
      42: invokeinterface #60,  1           // InterfaceMethod java/util/Iterator.next:()Ljava/lang/Object;
      47: checkcast     #55                 // class org/apache/hadoop/hbase/io/encoding/EncodedDataBlock
      50: astore        6
      52: aload         4
      54: aload         6
      56: aload_0
      57: getfield      #11                 // Field useHBaseChecksum:Z
      60: invokestatic  #61                 // Method org/apache/hadoop/hbase/io/hfile/HFileBlock.headerSize:(Z)I
      63: invokevirtual #62                 // Method org/apache/hadoop/hbase/io/encoding/EncodedDataBlock.getIterator:(I)Ljava/util/Iterator;
      66: invokeinterface #57,  2           // InterfaceMethod java/util/List.add:(Ljava/lang/Object;)Z
      71: pop
      72: goto          30
      75: iconst_0
      76: istore        5
      78: aload_1
      79: invokeinterface #24,  1           // InterfaceMethod org/apache/hadoop/hbase/regionserver/KeyValueScanner.next:()Lorg/apache/hadoop/hbase/Cell;
      84: invokestatic  #25                 // Method org/apache/hadoop/hbase/KeyValueUtil.ensureKeyValue:(Lorg/apache/hadoop/hbase/Cell;)Lorg/apache/hadoop/hbase/KeyValue;
      87: dup
      88: astore_3
      89: ifnull        573
      92: iload         5
      94: iload_2
      95: if_icmpge     573
      98: iinc          5, 1
     101: aload         4
     103: invokeinterface #58,  1           // InterfaceMethod java/util/List.iterator:()Ljava/util/Iterator;
     108: astore        6
     110: aload         6
     112: invokeinterface #59,  1           // InterfaceMethod java/util/Iterator.hasNext:()Z
     117: ifeq          570
     120: aload         6
     122: invokeinterface #60,  1           // InterfaceMethod java/util/Iterator.next:()Ljava/lang/Object;
     127: checkcast     #63                 // class java/util/Iterator
     130: astore        7
     132: aload         7
     134: invokeinterface #60,  1           // InterfaceMethod java/util/Iterator.next:()Ljava/lang/Object;
     139: checkcast     #64                 // class org/apache/hadoop/hbase/Cell
     142: astore        8
     144: aload         8
     146: invokestatic  #25                 // Method org/apache/hadoop/hbase/KeyValueUtil.ensureKeyValue:(Lorg/apache/hadoop/hbase/Cell;)Lorg/apache/hadoop/hbase/KeyValue;
     149: astore        9
     151: aload         9
     153: ifnull        190
     156: iconst_0
     157: aload         9
     159: invokevirtual #29                 // Method org/apache/hadoop/hbase/KeyValue.getBuffer:()[B
     162: aload         9
     164: invokevirtual #30                 // Method org/apache/hadoop/hbase/KeyValue.getOffset:()I
     167: aload         9
     169: invokevirtual #31                 // Method org/apache/hadoop/hbase/KeyValue.getLength:()I
     172: aload_3
     173: invokevirtual #29                 // Method org/apache/hadoop/hbase/KeyValue.getBuffer:()[B
     176: aload_3
     177: invokevirtual #30                 // Method org/apache/hadoop/hbase/KeyValue.getOffset:()I
     180: aload_3
     181: invokevirtual #31                 // Method org/apache/hadoop/hbase/KeyValue.getLength:()I
     184: invokestatic  #65                 // Method org/apache/hadoop/hbase/util/Bytes.compareTo:([BII[BII)I
     187: if_icmpeq     567
     190: aload         9
     192: ifnonnull     231
     195: getstatic     #66                 // Field LOG:Lorg/slf4j/Logger;
     198: new           #67                 // class java/lang/StringBuilder
     201: dup
     202: invokespecial #68                 // Method java/lang/StringBuilder."<init>":()V
     205: ldc           #69                 // String There is a bug in codec
     207: invokevirtual #70                 // Method java/lang/StringBuilder.append:(Ljava/lang/String;)Ljava/lang/StringBuilder;
     210: aload         7
     212: invokevirtual #71                 // Method java/lang/StringBuilder.append:(Ljava/lang/Object;)Ljava/lang/StringBuilder;
     215: ldc           #72                 // String  it returned null KeyValue,
     217: invokevirtual #70                 // Method java/lang/StringBuilder.append:(Ljava/lang/String;)Ljava/lang/StringBuilder;
     220: invokevirtual #73                 // Method java/lang/StringBuilder.toString:()Ljava/lang/String;
     223: invokeinterface #74,  2           // InterfaceMethod org/slf4j/Logger.error:(Ljava/lang/String;)V
     228: goto          565
     231: iconst_0
     232: istore        10
     234: bipush        8
     236: aload         9
     238: invokevirtual #31                 // Method org/apache/hadoop/hbase/KeyValue.getLength:()I
     241: aload_3
     242: invokevirtual #31                 // Method org/apache/hadoop/hbase/KeyValue.getLength:()I
     245: invokestatic  #76                 // Method java/lang/Math.min:(II)I
     248: iadd
     249: istore        11
     251: iload         10
     253: iload         11
     255: if_icmpge     293
     258: aload         9
     260: invokevirtual #29                 // Method org/apache/hadoop/hbase/KeyValue.getBuffer:()[B
     263: iload         10
     265: aload         9
     267: invokevirtual #30                 // Method org/apache/hadoop/hbase/KeyValue.getOffset:()I
     270: iadd
     271: baload
     272: aload_3
     273: invokevirtual #29                 // Method org/apache/hadoop/hbase/KeyValue.getBuffer:()[B
     276: iload         10
     278: aload_3
     279: invokevirtual #30                 // Method org/apache/hadoop/hbase/KeyValue.getOffset:()I
     282: iadd
     283: baload
     284: if_icmpne     293
     287: iinc          10, 1
     290: goto          251
     293: getstatic     #66                 // Field LOG:Lorg/slf4j/Logger;
     296: new           #67                 // class java/lang/StringBuilder
     299: dup
     300: invokespecial #68                 // Method java/lang/StringBuilder."<init>":()V
     303: ldc           #77                 // String There is bug in codec
     305: invokevirtual #70                 // Method java/lang/StringBuilder.append:(Ljava/lang/String;)Ljava/lang/StringBuilder;
     308: aload         7
     310: invokevirtual #78                 // Method java/lang/Object.toString:()Ljava/lang/String;
     313: invokevirtual #70                 // Method java/lang/StringBuilder.append:(Ljava/lang/String;)Ljava/lang/StringBuilder;
     316: ldc           #79                 // String \n on element
     318: invokevirtual #70                 // Method java/lang/StringBuilder.append:(Ljava/lang/String;)Ljava/lang/StringBuilder;
     321: iload         5
     323: invokevirtual #80                 // Method java/lang/StringBuilder.append:(I)Ljava/lang/StringBuilder;
     326: ldc           #81                 // String \n codecKv.getKeyLength()
     328: invokevirtual #70                 // Method java/lang/StringBuilder.append:(Ljava/lang/String;)Ljava/lang/StringBuilder;
     331: aload         9
     333: invokevirtual #39                 // Method org/apache/hadoop/hbase/KeyValue.getKeyLength:()I
     336: invokevirtual #80                 // Method java/lang/StringBuilder.append:(I)Ljava/lang/StringBuilder;
     339: ldc           #82                 // String \n codecKv.getValueLength()
     341: invokevirtual #70                 // Method java/lang/StringBuilder.append:(Ljava/lang/String;)Ljava/lang/StringBuilder;
     344: aload         9
     346: invokevirtual #40                 // Method org/apache/hadoop/hbase/KeyValue.getValueLength:()I
     349: invokevirtual #80                 // Method java/lang/StringBuilder.append:(I)Ljava/lang/StringBuilder;
     352: ldc           #83                 // String \n codecKv.getLength()
     354: invokevirtual #70                 // Method java/lang/StringBuilder.append:(Ljava/lang/String;)Ljava/lang/StringBuilder;
     357: aload         9
     359: invokevirtual #31                 // Method org/apache/hadoop/hbase/KeyValue.getLength:()I
     362: invokevirtual #80                 // Method java/lang/StringBuilder.append:(I)Ljava/lang/StringBuilder;
     365: ldc           #84                 // String \n currentKv.getKeyLength()
     367: invokevirtual #70                 // Method java/lang/StringBuilder.append:(Ljava/lang/String;)Ljava/lang/StringBuilder;
     370: aload_3
     371: invokevirtual #39                 // Method org/apache/hadoop/hbase/KeyValue.getKeyLength:()I
     374: invokevirtual #80                 // Method java/lang/StringBuilder.append:(I)Ljava/lang/StringBuilder;
     377: ldc           #85                 // String \n currentKv.getValueLength()
     379: invokevirtual #70                 // Method java/lang/StringBuilder.append:(Ljava/lang/String;)Ljava/lang/StringBuilder;
     382: aload_3
     383: invokevirtual #40                 // Method org/apache/hadoop/hbase/KeyValue.getValueLength:()I
     386: invokevirtual #80                 // Method java/lang/StringBuilder.append:(I)Ljava/lang/StringBuilder;
     389: ldc           #83                 // String \n codecKv.getLength()
     391: invokevirtual #70                 // Method java/lang/StringBuilder.append:(Ljava/lang/String;)Ljava/lang/StringBuilder;
     394: aload_3
     395: invokevirtual #31                 // Method org/apache/hadoop/hbase/KeyValue.getLength:()I
     398: invokevirtual #80                 // Method java/lang/StringBuilder.append:(I)Ljava/lang/StringBuilder;
     401: ldc           #86                 // String \n currentKV rowLength
     403: invokevirtual #70                 // Method java/lang/StringBuilder.append:(Ljava/lang/String;)Ljava/lang/StringBuilder;
     406: aload_3
     407: invokevirtual #87                 // Method org/apache/hadoop/hbase/KeyValue.getRowLength:()S
     410: invokevirtual #80                 // Method java/lang/StringBuilder.append:(I)Ljava/lang/StringBuilder;
     413: ldc           #88                 // String  familyName
     415: invokevirtual #70                 // Method java/lang/StringBuilder.append:(Ljava/lang/String;)Ljava/lang/StringBuilder;
     418: aload_3
     419: invokevirtual #89                 // Method org/apache/hadoop/hbase/KeyValue.getFamilyLength:()B
     422: invokevirtual #80                 // Method java/lang/StringBuilder.append:(I)Ljava/lang/StringBuilder;
     425: ldc           #90                 // String  qualifier
     427: invokevirtual #70                 // Method java/lang/StringBuilder.append:(Ljava/lang/String;)Ljava/lang/StringBuilder;
     430: aload_3
     431: invokevirtual #91                 // Method org/apache/hadoop/hbase/KeyValue.getQualifierLength:()I
     434: invokevirtual #80                 // Method java/lang/StringBuilder.append:(I)Ljava/lang/StringBuilder;
     437: ldc           #92                 // String \n prefix
     439: invokevirtual #70                 // Method java/lang/StringBuilder.append:(Ljava/lang/String;)Ljava/lang/StringBuilder;
     442: iload         10
     444: invokevirtual #80                 // Method java/lang/StringBuilder.append:(I)Ljava/lang/StringBuilder;
     447: ldc           #93                 // String \n codecKv   '
     449: invokevirtual #70                 // Method java/lang/StringBuilder.append:(Ljava/lang/String;)Ljava/lang/StringBuilder;
     452: aload         9
     454: invokevirtual #29                 // Method org/apache/hadoop/hbase/KeyValue.getBuffer:()[B
     457: aload         9
     459: invokevirtual #30                 // Method org/apache/hadoop/hbase/KeyValue.getOffset:()I
     462: iload         10
     464: invokestatic  #94                 // Method org/apache/hadoop/hbase/util/Bytes.toStringBinary:([BII)Ljava/lang/String;
     467: invokevirtual #70                 // Method java/lang/StringBuilder.append:(Ljava/lang/String;)Ljava/lang/StringBuilder;
     470: ldc           #95                 // String ' diff '
     472: invokevirtual #70                 // Method java/lang/StringBuilder.append:(Ljava/lang/String;)Ljava/lang/StringBuilder;
     475: aload         9
     477: invokevirtual #29                 // Method org/apache/hadoop/hbase/KeyValue.getBuffer:()[B
     480: aload         9
     482: invokevirtual #30                 // Method org/apache/hadoop/hbase/KeyValue.getOffset:()I
     485: iload         10
     487: iadd
     488: aload         9
     490: invokevirtual #31                 // Method org/apache/hadoop/hbase/KeyValue.getLength:()I
     493: iload         10
     495: isub
     496: invokestatic  #94                 // Method org/apache/hadoop/hbase/util/Bytes.toStringBinary:([BII)Ljava/lang/String;
     499: invokevirtual #70                 // Method java/lang/StringBuilder.append:(Ljava/lang/String;)Ljava/lang/StringBuilder;
     502: ldc           #96                 // String '\n currentKv '
     504: invokevirtual #70                 // Method java/lang/StringBuilder.append:(Ljava/lang/String;)Ljava/lang/StringBuilder;
     507: aload_3
     508: invokevirtual #29                 // Method org/apache/hadoop/hbase/KeyValue.getBuffer:()[B
     511: aload_3
     512: invokevirtual #30                 // Method org/apache/hadoop/hbase/KeyValue.getOffset:()I
     515: iload         10
     517: invokestatic  #94                 // Method org/apache/hadoop/hbase/util/Bytes.toStringBinary:([BII)Ljava/lang/String;
     520: invokevirtual #70                 // Method java/lang/StringBuilder.append:(Ljava/lang/String;)Ljava/lang/StringBuilder;
     523: ldc           #95                 // String ' diff '
     525: invokevirtual #70                 // Method java/lang/StringBuilder.append:(Ljava/lang/String;)Ljava/lang/StringBuilder;
     528: aload_3
     529: invokevirtual #29                 // Method org/apache/hadoop/hbase/KeyValue.getBuffer:()[B
     532: aload_3
     533: invokevirtual #30                 // Method org/apache/hadoop/hbase/KeyValue.getOffset:()I
     536: iload         10
     538: iadd
     539: aload_3
     540: invokevirtual #31                 // Method org/apache/hadoop/hbase/KeyValue.getLength:()I
     543: iload         10
     545: isub
     546: invokestatic  #94                 // Method org/apache/hadoop/hbase/util/Bytes.toStringBinary:([BII)Ljava/lang/String;
     549: invokevirtual #70                 // Method java/lang/StringBuilder.append:(Ljava/lang/String;)Ljava/lang/StringBuilder;
     552: ldc           #97                 // String '
     554: invokevirtual #70                 // Method java/lang/StringBuilder.append:(Ljava/lang/String;)Ljava/lang/StringBuilder;
     557: invokevirtual #73                 // Method java/lang/StringBuilder.toString:()Ljava/lang/String;
     560: invokeinterface #74,  2           // InterfaceMethod org/slf4j/Logger.error:(Ljava/lang/String;)V
     565: iconst_0
     566: ireturn
     567: goto          110
     570: goto          78
     573: getstatic     #66                 // Field LOG:Lorg/slf4j/Logger;
     576: ldc           #98                 // String Verification was successful!
     578: invokeinterface #99,  2           // InterfaceMethod org/slf4j/Logger.info:(Ljava/lang/String;)V
     583: iconst_1
     584: ireturn

  public void benchmarkCodecs() throws java.io.IOException;
    Code:
       0: getstatic     #66                 // Field LOG:Lorg/slf4j/Logger;
       3: ldc           #100                // String Starting a throughput benchmark for data block encoding codecs
       5: invokeinterface #99,  2           // InterfaceMethod org/slf4j/Logger.info:(Ljava/lang/String;)V
      10: iconst_m1
      11: istore_1
      12: aload_0
      13: getfield      #5                  // Field codecs:Ljava/util/List;
      16: invokeinterface #58,  1           // InterfaceMethod java/util/List.iterator:()Ljava/util/Iterator;
      21: astore_2
      22: aload_2
      23: invokeinterface #59,  1           // InterfaceMethod java/util/Iterator.hasNext:()Z
      28: ifeq          51
      31: aload_2
      32: invokeinterface #60,  1           // InterfaceMethod java/util/Iterator.next:()Ljava/lang/Object;
      37: checkcast     #55                 // class org/apache/hadoop/hbase/io/encoding/EncodedDataBlock
      40: astore_3
      41: aload_0
      42: iload_1
      43: aload_3
      44: invokespecial #101                // Method benchmarkEncoder:(ILorg/apache/hadoop/hbase/io/encoding/EncodedDataBlock;)I
      47: istore_1
      48: goto          22
      51: aload_0
      52: iload_1
      53: aload_0
      54: getfield      #44                 // Field rawKVs:[B
      57: invokespecial #102                // Method benchmarkDefaultCompression:(I[B)V
      60: return

  public void benchmarkAlgorithm(org.apache.hadoop.hbase.io.compress.Compression$Algorithm, java.lang.String, byte[], int, int) throws java.io.IOException;
    Code:
       0: getstatic     #114                // Field java/lang/System.out:Ljava/io/PrintStream;
       3: new           #67                 // class java/lang/StringBuilder
       6: dup
       7: invokespecial #68                 // Method java/lang/StringBuilder."<init>":()V
      10: aload_2
      11: invokevirtual #70                 // Method java/lang/StringBuilder.append:(Ljava/lang/String;)Ljava/lang/StringBuilder;
      14: ldc           #115                // String :
      16: invokevirtual #70                 // Method java/lang/StringBuilder.append:(Ljava/lang/String;)Ljava/lang/StringBuilder;
      19: invokevirtual #73                 // Method java/lang/StringBuilder.toString:()Ljava/lang/String;
      22: invokevirtual #116                // Method java/io/PrintStream.println:(Ljava/lang/String;)V
      25: new           #3                  // class java/util/ArrayList
      28: dup
      29: invokespecial #4                  // Method java/util/ArrayList."<init>":()V
      32: astore        6
      34: new           #22                 // class java/io/ByteArrayOutputStream
      37: dup
      38: invokespecial #23                 // Method java/io/ByteArrayOutputStream."<init>":()V
      41: astore        7
      43: aload_1
      44: aload         7
      46: aload_0
      47: getfield      #16                 // Field compressor:Lorg/apache/hadoop/io/compress/Compressor;
      50: invokevirtual #124                // Method org/apache/hadoop/hbase/io/compress/Compression$Algorithm.createPlainCompressionStream:(Ljava/io/OutputStream;Lorg/apache/hadoop/io/compress/Compressor;)Lorg/apache/hadoop/io/compress/CompressionOutputStream;
      53: astore        8
      55: iconst_0
      56: istore        9
      58: iload         9
      60: getstatic     #103                // Field benchmarkNTimes:I
      63: if_icmpge     137
      66: invokestatic  #104                // Method java/lang/System.nanoTime:()J
      69: lstore        10
      71: aload         7
      73: invokevirtual #125                // Method java/io/ByteArrayOutputStream.reset:()V
      76: aload         8
      78: invokevirtual #126                // Method org/apache/hadoop/io/compress/CompressionOutputStream.resetState:()V
      81: aload         8
      83: aload_3
      84: iload         4
      86: iload         5
      88: invokevirtual #127                // Method org/apache/hadoop/io/compress/CompressionOutputStream.write:([BII)V
      91: aload         8
      93: invokevirtual #128                // Method org/apache/hadoop/io/compress/CompressionOutputStream.flush:()V
      96: aload         7
      98: invokevirtual #43                 // Method java/io/ByteArrayOutputStream.toByteArray:()[B
     101: pop
     102: invokestatic  #104                // Method java/lang/System.nanoTime:()J
     105: lstore        12
     107: iload         9
     109: getstatic     #105                // Field benchmarkNOmit:I
     112: if_icmplt     131
     115: aload         6
     117: lload         12
     119: lload         10
     121: lsub
     122: invokestatic  #106                // Method java/lang/Long.valueOf:(J)Ljava/lang/Long;
     125: invokeinterface #57,  2           // InterfaceMethod java/util/List.add:(Ljava/lang/Object;)Z
     130: pop
     131: iinc          9, 1
     134: goto          58
     137: goto          165
     140: astore        9
     142: new           #130                // class java/lang/RuntimeException
     145: dup
     146: ldc           #131                // String Benchmark, or encoding algorithm '%s' cause some stream problems
     148: iconst_1
     149: anewarray     #109                // class java/lang/Object
     152: dup
     153: iconst_0
     154: aload_2
     155: aastore
     156: invokestatic  #111                // Method java/lang/String.format:(Ljava/lang/String;[Ljava/lang/Object;)Ljava/lang/String;
     159: aload         9
     161: invokespecial #132                // Method java/lang/RuntimeException."<init>":(Ljava/lang/String;Ljava/lang/Throwable;)V
     164: athrow
     165: aload         8
     167: invokevirtual #133                // Method org/apache/hadoop/io/compress/CompressionOutputStream.close:()V
     170: iload         5
     172: aload         6
     174: getstatic     #134                // Field org/apache/hadoop/hbase/regionserver/DataBlockEncodingTool$Manipulation.COMPRESSION:Lorg/apache/hadoop/hbase/regionserver/DataBlockEncodingTool$Manipulation;
     177: invokestatic  #118                // Method printBenchmarkResult:(ILjava/util/List;Lorg/apache/hadoop/hbase/regionserver/DataBlockEncodingTool$Manipulation;)V
     180: aload         7
     182: invokevirtual #43                 // Method java/io/ByteArrayOutputStream.toByteArray:()[B
     185: astore        9
     187: new           #3                  // class java/util/ArrayList
     190: dup
     191: invokespecial #4                  // Method java/util/ArrayList."<init>":()V
     194: astore        10
     196: iconst_0
     197: istore        11
     199: iload         11
     201: getstatic     #103                // Field benchmarkNTimes:I
     204: if_icmpge     425
     207: invokestatic  #104                // Method java/lang/System.nanoTime:()J
     210: lstore        12
     212: iload         5
     214: iconst_1
     215: iadd
     216: newarray       byte
     218: astore        14
     220: new           #135                // class java/io/ByteArrayInputStream
     223: dup
     224: aload         9
     226: iconst_0
     227: aload         9
     229: arraylength
     230: invokespecial #136                // Method java/io/ByteArrayInputStream."<init>":([BII)V
     233: astore        15
     235: aload_1
     236: aload         15
     238: aload_0
     239: getfield      #18                 // Field decompressor:Lorg/apache/hadoop/io/compress/Decompressor;
     242: iconst_0
     243: invokevirtual #137                // Method org/apache/hadoop/hbase/io/compress/Compression$Algorithm.createDecompressionStream:(Ljava/io/InputStream;Lorg/apache/hadoop/io/compress/Decompressor;I)Ljava/io/InputStream;
     246: astore        16
     248: iconst_0
     249: istore        17
     251: aload         16
     253: invokevirtual #138                // Method java/io/InputStream.available:()I
     256: dup
     257: istore        18
     259: ifle          281
     262: iload         17
     264: aload         16
     266: aload         14
     268: iload         17
     270: iload         18
     272: invokevirtual #139                // Method java/io/InputStream.read:([BII)I
     275: iadd
     276: istore        17
     278: goto          251
     281: aload         16
     283: invokevirtual #140                // Method java/io/InputStream.close:()V
     286: goto          314
     289: astore        15
     291: new           #130                // class java/lang/RuntimeException
     294: dup
     295: ldc           #141                // String Decoding path in '%s' algorithm cause exception
     297: iconst_1
     298: anewarray     #109                // class java/lang/Object
     301: dup
     302: iconst_0
     303: aload_2
     304: aastore
     305: invokestatic  #111                // Method java/lang/String.format:(Ljava/lang/String;[Ljava/lang/Object;)Ljava/lang/String;
     308: aload         15
     310: invokespecial #132                // Method java/lang/RuntimeException."<init>":(Ljava/lang/String;Ljava/lang/Throwable;)V
     313: athrow
     314: invokestatic  #104                // Method java/lang/System.nanoTime:()J
     317: lstore        15
     319: iconst_0
     320: aload_3
     321: iconst_0
     322: iload         5
     324: aload         14
     326: iconst_0
     327: iload         5
     329: invokestatic  #65                 // Method org/apache/hadoop/hbase/util/Bytes.compareTo:([BII[BII)I
     332: if_icmpeq     395
     335: iconst_0
     336: istore        17
     338: iload         17
     340: aload_3
     341: arraylength
     342: if_icmpge     374
     345: iload         17
     347: aload         14
     349: arraylength
     350: if_icmpge     374
     353: aload_3
     354: iload         17
     356: baload
     357: aload         14
     359: iload         17
     361: baload
     362: if_icmpeq     368
     365: goto          374
     368: iinc          17, 1
     371: goto          338
     374: new           #130                // class java/lang/RuntimeException
     377: dup
     378: ldc           #142                // String Algorithm '%s' is corrupting the data
     380: iconst_1
     381: anewarray     #109                // class java/lang/Object
     384: dup
     385: iconst_0
     386: aload_2
     387: aastore
     388: invokestatic  #111                // Method java/lang/String.format:(Ljava/lang/String;[Ljava/lang/Object;)Ljava/lang/String;
     391: invokespecial #143                // Method java/lang/RuntimeException."<init>":(Ljava/lang/String;)V
     394: athrow
     395: iload         11
     397: getstatic     #105                // Field benchmarkNOmit:I
     400: if_icmplt     419
     403: aload         10
     405: lload         15
     407: lload         12
     409: lsub
     410: invokestatic  #106                // Method java/lang/Long.valueOf:(J)Ljava/lang/Long;
     413: invokeinterface #57,  2           // InterfaceMethod java/util/List.add:(Ljava/lang/Object;)Z
     418: pop
     419: iinc          11, 1
     422: goto          199
     425: iload         5
     427: aload         10
     429: getstatic     #144                // Field org/apache/hadoop/hbase/regionserver/DataBlockEncodingTool$Manipulation.DECOMPRESSION:Lorg/apache/hadoop/hbase/regionserver/DataBlockEncodingTool$Manipulation;
     432: invokestatic  #118                // Method printBenchmarkResult:(ILjava/util/List;Lorg/apache/hadoop/hbase/regionserver/DataBlockEncodingTool$Manipulation;)V
     435: getstatic     #114                // Field java/lang/System.out:Ljava/io/PrintStream;
     438: invokevirtual #120                // Method java/io/PrintStream.println:()V
     441: return
    Exception table:
       from    to  target type
          55   137   140   Class java/io/IOException
         220   286   289   Class java/io/IOException

  public void displayStatistics() throws java.io.IOException;
    Code:
       0: aload_0
       1: getfield      #12                 // Field compressionAlgorithmName:Ljava/lang/String;
       4: getstatic     #121                // Field java/util/Locale.ROOT:Ljava/util/Locale;
       7: invokevirtual #122                // Method java/lang/String.toUpperCase:(Ljava/util/Locale;)Ljava/lang/String;
      10: astore_1
      11: aload_0
      12: getfield      #7                  // Field totalKeyLength:J
      15: aload_0
      16: getfield      #6                  // Field totalPrefixLength:J
      19: ladd
      20: aload_0
      21: getfield      #8                  // Field totalValueLength:J
      24: ladd
      25: lstore_2
      26: getstatic     #114                // Field java/lang/System.out:Ljava/io/PrintStream;
      29: ldc           #166                // String Raw data size:
      31: invokevirtual #116                // Method java/io/PrintStream.println:(Ljava/lang/String;)V
      34: ldc           #167                // String Raw bytes
      36: ldc           #155                // String %d
      38: iconst_1
      39: anewarray     #109                // class java/lang/Object
      42: dup
      43: iconst_0
      44: lload_2
      45: invokestatic  #106                // Method java/lang/Long.valueOf:(J)Ljava/lang/Long;
      48: aastore
      49: invokestatic  #154                // Method outputTuple:(Ljava/lang/String;Ljava/lang/String;[Ljava/lang/Object;)V
      52: aload_0
      53: ldc           #168                // String Key bytes
      55: aload_0
      56: getfield      #7                  // Field totalKeyLength:J
      59: invokespecial #169                // Method outputTuplePct:(Ljava/lang/String;J)V
      62: aload_0
      63: ldc           #170                // String Value bytes
      65: aload_0
      66: getfield      #8                  // Field totalValueLength:J
      69: invokespecial #169                // Method outputTuplePct:(Ljava/lang/String;J)V
      72: aload_0
      73: ldc           #171                // String KV infrastructure
      75: aload_0
      76: getfield      #6                  // Field totalPrefixLength:J
      79: invokespecial #169                // Method outputTuplePct:(Ljava/lang/String;J)V
      82: aload_0
      83: ldc           #172                // String CF overhead
      85: aload_0
      86: getfield      #10                 // Field totalCFLength:J
      89: invokespecial #169                // Method outputTuplePct:(Ljava/lang/String;J)V
      92: aload_0
      93: ldc           #173                // String Total key redundancy
      95: aload_0
      96: getfield      #9                  // Field totalKeyRedundancyLength:J
      99: invokespecial #169                // Method outputTuplePct:(Ljava/lang/String;J)V
     102: aload_0
     103: getfield      #14                 // Field compressionAlgorithm:Lorg/apache/hadoop/hbase/io/compress/Compression$Algorithm;
     106: aload_0
     107: getfield      #16                 // Field compressor:Lorg/apache/hadoop/io/compress/Compressor;
     110: aload_0
     111: getfield      #44                 // Field rawKVs:[B
     114: iconst_0
     115: aload_0
     116: getfield      #44                 // Field rawKVs:[B
     119: arraylength
     120: invokestatic  #174                // Method org/apache/hadoop/hbase/io/encoding/EncodedDataBlock.getCompressedSize:(Lorg/apache/hadoop/hbase/io/compress/Compression$Algorithm;Lorg/apache/hadoop/io/compress/Compressor;[BII)I
     123: istore        4
     125: new           #67                 // class java/lang/StringBuilder
     128: dup
     129: invokespecial #68                 // Method java/lang/StringBuilder."<init>":()V
     132: aload_1
     133: invokevirtual #70                 // Method java/lang/StringBuilder.append:(Ljava/lang/String;)Ljava/lang/StringBuilder;
     136: ldc           #175                // String  only size
     138: invokevirtual #70                 // Method java/lang/StringBuilder.append:(Ljava/lang/String;)Ljava/lang/StringBuilder;
     141: invokevirtual #73                 // Method java/lang/StringBuilder.toString:()Ljava/lang/String;
     144: ldc           #155                // String %d
     146: iconst_1
     147: anewarray     #109                // class java/lang/Object
     150: dup
     151: iconst_0
     152: iload         4
     154: invokestatic  #176                // Method java/lang/Integer.valueOf:(I)Ljava/lang/Integer;
     157: aastore
     158: invokestatic  #154                // Method outputTuple:(Ljava/lang/String;Ljava/lang/String;[Ljava/lang/Object;)V
     161: aload_0
     162: new           #67                 // class java/lang/StringBuilder
     165: dup
     166: invokespecial #68                 // Method java/lang/StringBuilder."<init>":()V
     169: aload_1
     170: invokevirtual #70                 // Method java/lang/StringBuilder.append:(Ljava/lang/String;)Ljava/lang/StringBuilder;
     173: ldc           #177                // String  only
     175: invokevirtual #70                 // Method java/lang/StringBuilder.append:(Ljava/lang/String;)Ljava/lang/StringBuilder;
     178: invokevirtual #73                 // Method java/lang/StringBuilder.toString:()Ljava/lang/String;
     181: iload         4
     183: i2l
     184: lload_2
     185: invokespecial #178                // Method outputSavings:(Ljava/lang/String;JJ)V
     188: getstatic     #114                // Field java/lang/System.out:Ljava/io/PrintStream;
     191: invokevirtual #120                // Method java/io/PrintStream.println:()V
     194: aload_0
     195: getfield      #5                  // Field codecs:Ljava/util/List;
     198: invokeinterface #58,  1           // InterfaceMethod java/util/List.iterator:()Ljava/util/Iterator;
     203: astore        5
     205: aload         5
     207: invokeinterface #59,  1           // InterfaceMethod java/util/Iterator.hasNext:()Z
     212: ifeq          414
     215: aload         5
     217: invokeinterface #60,  1           // InterfaceMethod java/util/Iterator.next:()Ljava/lang/Object;
     222: checkcast     #55                 // class org/apache/hadoop/hbase/io/encoding/EncodedDataBlock
     225: astore        6
     227: getstatic     #114                // Field java/lang/System.out:Ljava/io/PrintStream;
     230: aload         6
     232: invokevirtual #110                // Method org/apache/hadoop/hbase/io/encoding/EncodedDataBlock.toString:()Ljava/lang/String;
     235: invokevirtual #116                // Method java/io/PrintStream.println:(Ljava/lang/String;)V
     238: aload         6
     240: invokevirtual #179                // Method org/apache/hadoop/hbase/io/encoding/EncodedDataBlock.getSize:()I
     243: i2l
     244: lstore        7
     246: ldc           #180                // String Encoded bytes
     248: ldc           #155                // String %d
     250: iconst_1
     251: anewarray     #109                // class java/lang/Object
     254: dup
     255: iconst_0
     256: lload         7
     258: invokestatic  #106                // Method java/lang/Long.valueOf:(J)Ljava/lang/Long;
     261: aastore
     262: invokestatic  #154                // Method outputTuple:(Ljava/lang/String;Ljava/lang/String;[Ljava/lang/Object;)V
     265: aload_0
     266: ldc           #181                // String Key encoding
     268: lload         7
     270: aload_0
     271: getfield      #8                  // Field totalValueLength:J
     274: lsub
     275: lload_2
     276: aload_0
     277: getfield      #8                  // Field totalValueLength:J
     280: lsub
     281: invokespecial #178                // Method outputSavings:(Ljava/lang/String;JJ)V
     284: aload_0
     285: ldc           #182                // String Total encoding
     287: lload         7
     289: lload_2
     290: invokespecial #178                // Method outputSavings:(Ljava/lang/String;JJ)V
     293: aload         6
     295: aload_0
     296: getfield      #14                 // Field compressionAlgorithm:Lorg/apache/hadoop/hbase/io/compress/Compression$Algorithm;
     299: aload_0
     300: getfield      #16                 // Field compressor:Lorg/apache/hadoop/io/compress/Compressor;
     303: invokevirtual #183                // Method org/apache/hadoop/hbase/io/encoding/EncodedDataBlock.getEncodedCompressedSize:(Lorg/apache/hadoop/hbase/io/compress/Compression$Algorithm;Lorg/apache/hadoop/io/compress/Compressor;)I
     306: istore        9
     308: new           #67                 // class java/lang/StringBuilder
     311: dup
     312: invokespecial #68                 // Method java/lang/StringBuilder."<init>":()V
     315: ldc           #184                // String Encoding +
     317: invokevirtual #70                 // Method java/lang/StringBuilder.append:(Ljava/lang/String;)Ljava/lang/StringBuilder;
     320: aload_1
     321: invokevirtual #70                 // Method java/lang/StringBuilder.append:(Ljava/lang/String;)Ljava/lang/StringBuilder;
     324: ldc           #185                // String  size
     326: invokevirtual #70                 // Method java/lang/StringBuilder.append:(Ljava/lang/String;)Ljava/lang/StringBuilder;
     329: invokevirtual #73                 // Method java/lang/StringBuilder.toString:()Ljava/lang/String;
     332: ldc           #155                // String %d
     334: iconst_1
     335: anewarray     #109                // class java/lang/Object
     338: dup
     339: iconst_0
     340: iload         9
     342: invokestatic  #176                // Method java/lang/Integer.valueOf:(I)Ljava/lang/Integer;
     345: aastore
     346: invokestatic  #154                // Method outputTuple:(Ljava/lang/String;Ljava/lang/String;[Ljava/lang/Object;)V
     349: aload_0
     350: new           #67                 // class java/lang/StringBuilder
     353: dup
     354: invokespecial #68                 // Method java/lang/StringBuilder."<init>":()V
     357: ldc           #184                // String Encoding +
     359: invokevirtual #70                 // Method java/lang/StringBuilder.append:(Ljava/lang/String;)Ljava/lang/StringBuilder;
     362: aload_1
     363: invokevirtual #70                 // Method java/lang/StringBuilder.append:(Ljava/lang/String;)Ljava/lang/StringBuilder;
     366: invokevirtual #73                 // Method java/lang/StringBuilder.toString:()Ljava/lang/String;
     369: iload         9
     371: i2l
     372: lload_2
     373: invokespecial #178                // Method outputSavings:(Ljava/lang/String;JJ)V
     376: aload_0
     377: new           #67                 // class java/lang/StringBuilder
     380: dup
     381: invokespecial #68                 // Method java/lang/StringBuilder."<init>":()V
     384: ldc           #186                // String Encoding with
     386: invokevirtual #70                 // Method java/lang/StringBuilder.append:(Ljava/lang/String;)Ljava/lang/StringBuilder;
     389: aload_1
     390: invokevirtual #70                 // Method java/lang/StringBuilder.append:(Ljava/lang/String;)Ljava/lang/StringBuilder;
     393: invokevirtual #73                 // Method java/lang/StringBuilder.toString:()Ljava/lang/String;
     396: iload         9
     398: i2l
     399: iload         4
     401: i2l
     402: invokespecial #178                // Method outputSavings:(Ljava/lang/String;JJ)V
     405: getstatic     #114                // Field java/lang/System.out:Ljava/io/PrintStream;
     408: invokevirtual #120                // Method java/io/PrintStream.println:()V
     411: goto          205
     414: return

  public static void testCodecs(org.apache.hadoop.conf.Configuration, int, java.lang.String, java.lang.String, boolean, boolean) throws java.io.IOException;
    Code:
       0: new           #192                // class org/apache/hadoop/fs/Path
       3: dup
       4: aload_2
       5: invokespecial #193                // Method org/apache/hadoop/fs/Path."<init>":(Ljava/lang/String;)V
       8: astore        6
      10: new           #194                // class org/apache/hadoop/hbase/io/hfile/CacheConfig
      13: dup
      14: aload_0
      15: invokespecial #195                // Method org/apache/hadoop/hbase/io/hfile/CacheConfig."<init>":(Lorg/apache/hadoop/conf/Configuration;)V
      18: astore        7
      20: aload_0
      21: invokestatic  #196                // Method org/apache/hadoop/fs/FileSystem.get:(Lorg/apache/hadoop/conf/Configuration;)Lorg/apache/hadoop/fs/FileSystem;
      24: astore        8
      26: new           #197                // class org/apache/hadoop/hbase/regionserver/HStoreFile
      29: dup
      30: aload         8
      32: aload         6
      34: aload_0
      35: aload         7
      37: getstatic     #198                // Field org/apache/hadoop/hbase/regionserver/BloomType.NONE:Lorg/apache/hadoop/hbase/regionserver/BloomType;
      40: iconst_1
      41: invokespecial #199                // Method org/apache/hadoop/hbase/regionserver/HStoreFile."<init>":(Lorg/apache/hadoop/fs/FileSystem;Lorg/apache/hadoop/fs/Path;Lorg/apache/hadoop/conf/Configuration;Lorg/apache/hadoop/hbase/io/hfile/CacheConfig;Lorg/apache/hadoop/hbase/regionserver/BloomType;Z)V
      44: astore        9
      46: aload         9
      48: invokevirtual #200                // Method org/apache/hadoop/hbase/regionserver/HStoreFile.initReader:()V
      51: aload         9
      53: invokevirtual #201                // Method org/apache/hadoop/hbase/regionserver/HStoreFile.getReader:()Lorg/apache/hadoop/hbase/regionserver/StoreFileReader;
      56: astore        10
      58: aload         10
      60: invokevirtual #202                // Method org/apache/hadoop/hbase/regionserver/StoreFileReader.loadFileInfo:()Ljava/util/Map;
      63: pop
      64: aload         10
      66: iconst_1
      67: iconst_1
      68: iconst_0
      69: aload         9
      71: invokevirtual #203                // Method org/apache/hadoop/hbase/regionserver/HStoreFile.getMaxMemStoreTS:()J
      74: lconst_0
      75: iconst_0
      76: invokevirtual #204                // Method org/apache/hadoop/hbase/regionserver/StoreFileReader.getStoreFileScanner:(ZZZJJZ)Lorg/apache/hadoop/hbase/regionserver/StoreFileScanner;
      79: astore        11
      81: aload         10
      83: invokevirtual #205                // Method org/apache/hadoop/hbase/regionserver/StoreFileReader.getHFileReader:()Lorg/apache/hadoop/hbase/io/hfile/HFile$Reader;
      86: invokeinterface #206,  1          // InterfaceMethod org/apache/hadoop/hbase/io/hfile/HFile$Reader.getFileContext:()Lorg/apache/hadoop/hbase/io/hfile/HFileContext;
      91: invokevirtual #207                // Method org/apache/hadoop/hbase/io/hfile/HFileContext.isIncludesTags:()Z
      94: putstatic     #27                 // Field USE_TAG:Z
      97: new           #1                  // class org/apache/hadoop/hbase/regionserver/DataBlockEncodingTool
     100: dup
     101: aload_3
     102: invokespecial #208                // Method "<init>":(Ljava/lang/String;)V
     105: astore        12
     107: aload         10
     109: invokevirtual #209                // Method org/apache/hadoop/hbase/regionserver/StoreFileReader.getHFileVersion:()I
     112: istore        13
     114: aload         12
     116: iload         13
     118: iconst_2
     119: if_icmpgt     137
     122: iload         13
     124: iconst_2
     125: if_icmpne     141
     128: aload         10
     130: invokevirtual #210                // Method org/apache/hadoop/hbase/regionserver/StoreFileReader.getHFileMinorVersion:()I
     133: iconst_1
     134: if_icmplt     141
     137: iconst_1
     138: goto          142
     141: iconst_0
     142: putfield      #11                 // Field useHBaseChecksum:Z
     145: aload         12
     147: aload         11
     149: iload_1
     150: invokevirtual #212                // Method checkStatistics:(Lorg/apache/hadoop/hbase/regionserver/KeyValueScanner;I)V
     153: iload         5
     155: ifeq          167
     158: aload         12
     160: aload         11
     162: iload_1
     163: invokevirtual #213                // Method verifyCodecs:(Lorg/apache/hadoop/hbase/regionserver/KeyValueScanner;I)Z
     166: pop
     167: iload         4
     169: ifeq          177
     172: aload         12
     174: invokevirtual #214                // Method benchmarkCodecs:()V
     177: aload         12
     179: invokevirtual #215                // Method displayStatistics:()V
     182: aload         11
     184: invokeinterface #216,  1          // InterfaceMethod org/apache/hadoop/hbase/regionserver/KeyValueScanner.close:()V
     189: aload         10
     191: aload         7
     193: invokevirtual #217                // Method org/apache/hadoop/hbase/io/hfile/CacheConfig.shouldEvictOnClose:()Z
     196: invokevirtual #218                // Method org/apache/hadoop/hbase/regionserver/StoreFileReader.close:(Z)V
     199: return

  public static void main(java.lang.String[]) throws java.io.IOException;
    Code:
       0: new           #233                // class org/apache/hbase/thirdparty/org/apache/commons/cli/Options
       3: dup
       4: invokespecial #234                // Method org/apache/hbase/thirdparty/org/apache/commons/cli/Options."<init>":()V
       7: astore_1
       8: aload_1
       9: ldc           #235                // String f
      11: iconst_1
      12: ldc           #236                // String HFile to analyse (REQUIRED)
      14: invokevirtual #237                // Method org/apache/hbase/thirdparty/org/apache/commons/cli/Options.addOption:(Ljava/lang/String;ZLjava/lang/String;)Lorg/apache/hbase/thirdparty/org/apache/commons/cli/Options;
      17: pop
      18: aload_1
      19: ldc           #235                // String f
      21: invokevirtual #238                // Method org/apache/hbase/thirdparty/org/apache/commons/cli/Options.getOption:(Ljava/lang/String;)Lorg/apache/hbase/thirdparty/org/apache/commons/cli/Option;
      24: ldc           #239                // String FILENAME
      26: invokevirtual #240                // Method org/apache/hbase/thirdparty/org/apache/commons/cli/Option.setArgName:(Ljava/lang/String;)V
      29: aload_1
      30: ldc           #241                // String n
      32: iconst_1
      33: ldc           #242                // String Maximum number of KeyValues to process. A benchmark stops running after iterating over this many KV pairs.
      35: invokevirtual #237                // Method org/apache/hbase/thirdparty/org/apache/commons/cli/Options.addOption:(Ljava/lang/String;ZLjava/lang/String;)Lorg/apache/hbase/thirdparty/org/apache/commons/cli/Options;
      38: pop
      39: aload_1
      40: ldc           #241                // String n
      42: invokevirtual #238                // Method org/apache/hbase/thirdparty/org/apache/commons/cli/Options.getOption:(Ljava/lang/String;)Lorg/apache/hbase/thirdparty/org/apache/commons/cli/Option;
      45: ldc           #243                // String NUMBER
      47: invokevirtual #240                // Method org/apache/hbase/thirdparty/org/apache/commons/cli/Option.setArgName:(Ljava/lang/String;)V
      50: aload_1
      51: ldc           #244                // String b
      53: iconst_0
      54: ldc           #245                // String Measure read throughput
      56: invokevirtual #237                // Method org/apache/hbase/thirdparty/org/apache/commons/cli/Options.addOption:(Ljava/lang/String;ZLjava/lang/String;)Lorg/apache/hbase/thirdparty/org/apache/commons/cli/Options;
      59: pop
      60: aload_1
      61: ldc           #246                // String c
      63: iconst_0
      64: ldc           #247                // String Omit corectness tests.
      66: invokevirtual #237                // Method org/apache/hbase/thirdparty/org/apache/commons/cli/Options.addOption:(Ljava/lang/String;ZLjava/lang/String;)Lorg/apache/hbase/thirdparty/org/apache/commons/cli/Options;
      69: pop
      70: aload_1
      71: ldc           #248                // String a
      73: iconst_1
      74: ldc           #249                // String What kind of compression algorithm use for comparison.
      76: invokevirtual #237                // Method org/apache/hbase/thirdparty/org/apache/commons/cli/Options.addOption:(Ljava/lang/String;ZLjava/lang/String;)Lorg/apache/hbase/thirdparty/org/apache/commons/cli/Options;
      79: pop
      80: aload_1
      81: ldc           #250                // String t
      83: iconst_1
      84: ldc           #251                // String Number of times to run each benchmark. Default value: 12
      86: invokevirtual #237                // Method org/apache/hbase/thirdparty/org/apache/commons/cli/Options.addOption:(Ljava/lang/String;ZLjava/lang/String;)Lorg/apache/hbase/thirdparty/org/apache/commons/cli/Options;
      89: pop
      90: aload_1
      91: ldc           #252                // String omit
      93: iconst_1
      94: ldc           #253                // String Number of first runs of every benchmark to exclude from statistics (2 by default, so that only the last 10 times are included in statistics.)
      96: invokevirtual #237                // Method org/apache/hbase/thirdparty/org/apache/commons/cli/Options.addOption:(Ljava/lang/String;ZLjava/lang/String;)Lorg/apache/hbase/thirdparty/org/apache/commons/cli/Options;
      99: pop
     100: new           #254                // class org/apache/hbase/thirdparty/org/apache/commons/cli/PosixParser
     103: dup
     104: invokespecial #255                // Method org/apache/hbase/thirdparty/org/apache/commons/cli/PosixParser."<init>":()V
     107: astore_2
     108: aconst_null
     109: astore_3
     110: aload_2
     111: aload_1
     112: aload_0
     113: invokeinterface #256,  3          // InterfaceMethod org/apache/hbase/thirdparty/org/apache/commons/cli/CommandLineParser.parse:(Lorg/apache/hbase/thirdparty/org/apache/commons/cli/Options;[Ljava/lang/String;)Lorg/apache/hbase/thirdparty/org/apache/commons/cli/CommandLine;
     118: astore_3
     119: goto          138
     122: astore        4
     124: getstatic     #219                // Field java/lang/System.err:Ljava/io/PrintStream;
     127: ldc_w         #258                // String Could not parse arguments!
     130: invokevirtual #116                // Method java/io/PrintStream.println:(Ljava/lang/String;)V
     133: iconst_m1
     134: invokestatic  #259                // Method java/lang/System.exit:(I)V
     137: return
     138: ldc_w         #261                // int 2147483647
     141: istore        4
     143: aload_3
     144: ldc           #241                // String n
     146: invokevirtual #262                // Method org/apache/hbase/thirdparty/org/apache/commons/cli/CommandLine.hasOption:(Ljava/lang/String;)Z
     149: ifeq          179
     152: aload_3
     153: ldc           #241                // String n
     155: invokevirtual #263                // Method org/apache/hbase/thirdparty/org/apache/commons/cli/CommandLine.getOptionValue:(Ljava/lang/String;)Ljava/lang/String;
     158: invokestatic  #264                // Method java/lang/Integer.parseInt:(Ljava/lang/String;)I
     161: istore        4
     163: iload         4
     165: ifgt          179
     168: getstatic     #66                 // Field LOG:Lorg/slf4j/Logger;
     171: ldc_w         #265                // String KV_LIMIT should not less than 1.
     174: invokeinterface #74,  2           // InterfaceMethod org/slf4j/Logger.error:(Ljava/lang/String;)V
     179: aload_3
     180: ldc           #235                // String f
     182: invokevirtual #262                // Method org/apache/hbase/thirdparty/org/apache/commons/cli/CommandLine.hasOption:(Ljava/lang/String;)Z
     185: ifne          207
     188: getstatic     #66                 // Field LOG:Lorg/slf4j/Logger;
     191: ldc_w         #266                // String Please specify HFile name using the f option
     194: invokeinterface #74,  2           // InterfaceMethod org/slf4j/Logger.error:(Ljava/lang/String;)V
     199: aload_1
     200: invokestatic  #267                // Method printUsage:(Lorg/apache/hbase/thirdparty/org/apache/commons/cli/Options;)V
     203: iconst_m1
     204: invokestatic  #259                // Method java/lang/System.exit:(I)V
     207: aload_3
     208: ldc           #235                // String f
     210: invokevirtual #263                // Method org/apache/hbase/thirdparty/org/apache/commons/cli/CommandLine.getOptionValue:(Ljava/lang/String;)Ljava/lang/String;
     213: astore        5
     215: getstatic     #268                // Field DEFAULT_COMPRESSION:Lorg/apache/hadoop/hbase/io/compress/Compression$Algorithm;
     218: invokevirtual #269                // Method org/apache/hadoop/hbase/io/compress/Compression$Algorithm.getName:()Ljava/lang/String;
     221: astore        6
     223: aload_3
     224: ldc           #248                // String a
     226: invokevirtual #262                // Method org/apache/hbase/thirdparty/org/apache/commons/cli/CommandLine.hasOption:(Ljava/lang/String;)Z
     229: ifeq          246
     232: aload_3
     233: ldc           #248                // String a
     235: invokevirtual #263                // Method org/apache/hbase/thirdparty/org/apache/commons/cli/CommandLine.getOptionValue:(Ljava/lang/String;)Ljava/lang/String;
     238: getstatic     #121                // Field java/util/Locale.ROOT:Ljava/util/Locale;
     241: invokevirtual #270                // Method java/lang/String.toLowerCase:(Ljava/util/Locale;)Ljava/lang/String;
     244: astore        6
     246: aload_3
     247: ldc           #244                // String b
     249: invokevirtual #262                // Method org/apache/hbase/thirdparty/org/apache/commons/cli/CommandLine.hasOption:(Ljava/lang/String;)Z
     252: istore        7
     254: aload_3
     255: ldc           #246                // String c
     257: invokevirtual #262                // Method org/apache/hbase/thirdparty/org/apache/commons/cli/CommandLine.hasOption:(Ljava/lang/String;)Z
     260: ifne          267
     263: iconst_1
     264: goto          268
     267: iconst_0
     268: istore        8
     270: aload_3
     271: ldc           #250                // String t
     273: invokevirtual #262                // Method org/apache/hbase/thirdparty/org/apache/commons/cli/CommandLine.hasOption:(Ljava/lang/String;)Z
     276: ifeq          294
     279: aload_3
     280: ldc           #250                // String t
     282: invokevirtual #263                // Method org/apache/hbase/thirdparty/org/apache/commons/cli/CommandLine.getOptionValue:(Ljava/lang/String;)Ljava/lang/String;
     285: invokestatic  #271                // Method java/lang/Integer.valueOf:(Ljava/lang/String;)Ljava/lang/Integer;
     288: invokevirtual #272                // Method java/lang/Integer.intValue:()I
     291: putstatic     #103                // Field benchmarkNTimes:I
     294: aload_3
     295: ldc           #252                // String omit
     297: invokevirtual #262                // Method org/apache/hbase/thirdparty/org/apache/commons/cli/CommandLine.hasOption:(Ljava/lang/String;)Z
     300: ifeq          318
     303: aload_3
     304: ldc           #252                // String omit
     306: invokevirtual #263                // Method org/apache/hbase/thirdparty/org/apache/commons/cli/CommandLine.getOptionValue:(Ljava/lang/String;)Ljava/lang/String;
     309: invokestatic  #271                // Method java/lang/Integer.valueOf:(Ljava/lang/String;)Ljava/lang/Integer;
     312: invokevirtual #272                // Method java/lang/Integer.intValue:()I
     315: putstatic     #105                // Field benchmarkNOmit:I
     318: getstatic     #103                // Field benchmarkNTimes:I
     321: getstatic     #105                // Field benchmarkNOmit:I
     324: if_icmpge     379
     327: getstatic     #66                 // Field LOG:Lorg/slf4j/Logger;
     330: new           #67                 // class java/lang/StringBuilder
     333: dup
     334: invokespecial #68                 // Method java/lang/StringBuilder."<init>":()V
     337: ldc_w         #273                // String The number of times to run each benchmark (
     340: invokevirtual #70                 // Method java/lang/StringBuilder.append:(Ljava/lang/String;)Ljava/lang/StringBuilder;
     343: getstatic     #103                // Field benchmarkNTimes:I
     346: invokevirtual #80                 // Method java/lang/StringBuilder.append:(I)Ljava/lang/StringBuilder;
     349: ldc_w         #274                // String ) must be greater than the number of benchmark runs to exclude from statistics (
     352: invokevirtual #70                 // Method java/lang/StringBuilder.append:(Ljava/lang/String;)Ljava/lang/StringBuilder;
     355: getstatic     #105                // Field benchmarkNOmit:I
     358: invokevirtual #80                 // Method java/lang/StringBuilder.append:(I)Ljava/lang/StringBuilder;
     361: ldc_w         #275                // String )
     364: invokevirtual #70                 // Method java/lang/StringBuilder.append:(Ljava/lang/String;)Ljava/lang/StringBuilder;
     367: invokevirtual #73                 // Method java/lang/StringBuilder.toString:()Ljava/lang/String;
     370: invokeinterface #74,  2           // InterfaceMethod org/slf4j/Logger.error:(Ljava/lang/String;)V
     375: iconst_1
     376: invokestatic  #259                // Method java/lang/System.exit:(I)V
     379: getstatic     #66                 // Field LOG:Lorg/slf4j/Logger;
     382: new           #67                 // class java/lang/StringBuilder
     385: dup
     386: invokespecial #68                 // Method java/lang/StringBuilder."<init>":()V
     389: ldc_w         #276                // String Running benchmark
     392: invokevirtual #70                 // Method java/lang/StringBuilder.append:(Ljava/lang/String;)Ljava/lang/StringBuilder;
     395: getstatic     #103                // Field benchmarkNTimes:I
     398: invokevirtual #80                 // Method java/lang/StringBuilder.append:(I)Ljava/lang/StringBuilder;
     401: ldc_w         #277                // String  times. Excluding the first
     404: invokevirtual #70                 // Method java/lang/StringBuilder.append:(Ljava/lang/String;)Ljava/lang/StringBuilder;
     407: getstatic     #105                // Field benchmarkNOmit:I
     410: invokevirtual #80                 // Method java/lang/StringBuilder.append:(I)Ljava/lang/StringBuilder;
     413: ldc_w         #278                // String  times from statistics.
     416: invokevirtual #70                 // Method java/lang/StringBuilder.append:(Ljava/lang/String;)Ljava/lang/StringBuilder;
     419: invokevirtual #73                 // Method java/lang/StringBuilder.toString:()Ljava/lang/String;
     422: invokeinterface #99,  2           // InterfaceMethod org/slf4j/Logger.info:(Ljava/lang/String;)V
     427: invokestatic  #279                // Method org/apache/hadoop/hbase/HBaseConfiguration.create:()Lorg/apache/hadoop/conf/Configuration;
     430: astore        9
     432: aload         9
     434: iload         4
     436: aload         5
     438: aload         6
     440: iload         7
     442: iload         8
     444: invokestatic  #280                // Method testCodecs:(Lorg/apache/hadoop/conf/Configuration;ILjava/lang/String;Ljava/lang/String;ZZ)V
     447: return
    Exception table:
       from    to  target type
         110   119   122   Class org/apache/hbase/thirdparty/org/apache/commons/cli/ParseException

  static {};
    Code:
       0: ldc           #1                  // class org/apache/hadoop/hbase/regionserver/DataBlockEncodingTool
       2: invokestatic  #281                // Method org/slf4j/LoggerFactory.getLogger:(Ljava/lang/Class;)Lorg/slf4j/Logger;
       5: putstatic     #66                 // Field LOG:Lorg/slf4j/Logger;
       8: getstatic     #282                // Field org/apache/hadoop/hbase/io/compress/Compression$Algorithm.GZ:Lorg/apache/hadoop/hbase/io/compress/Compression$Algorithm;
      11: putstatic     #268                // Field DEFAULT_COMPRESSION:Lorg/apache/hadoop/hbase/io/compress/Compression$Algorithm;
      14: new           #283                // class java/text/DecimalFormat
      17: dup
      18: invokespecial #284                // Method java/text/DecimalFormat."<init>":()V
      21: putstatic     #160                // Field DELIMITED_DECIMAL_FORMAT:Ljava/text/DecimalFormat;
      24: getstatic     #160                // Field DELIMITED_DECIMAL_FORMAT:Ljava/text/DecimalFormat;
      27: iconst_3
      28: invokevirtual #285                // Method java/text/DecimalFormat.setGroupingSize:(I)V
      31: bipush        12
      33: putstatic     #103                // Field benchmarkNTimes:I
      36: iconst_2
      37: putstatic     #105                // Field benchmarkNOmit:I
      40: iconst_0
      41: putstatic     #27                 // Field USE_TAG:Z
      44: return
}
