Compiled from "DateTieredCompactor.java"
public class org.apache.hadoop.hbase.regionserver.compactions.DateTieredCompactor extends org.apache.hadoop.hbase.regionserver.compactions.AbstractMultiOutputCompactor<org.apache.hadoop.hbase.regionserver.DateTieredMultiFileWriter> {
  public org.apache.hadoop.hbase.regionserver.compactions.DateTieredCompactor(org.apache.hadoop.conf.Configuration, org.apache.hadoop.hbase.regionserver.HStore);
    Code:
       0: aload_0
       1: aload_1
       2: aload_2
       3: invokespecial #2                  // Method org/apache/hadoop/hbase/regionserver/compactions/AbstractMultiOutputCompactor."<init>":(Lorg/apache/hadoop/conf/Configuration;Lorg/apache/hadoop/hbase/regionserver/HStore;)V
       6: return

  public java.util.List<org.apache.hadoop.fs.Path> compact(org.apache.hadoop.hbase.regionserver.compactions.CompactionRequestImpl, java.util.List<java.lang.Long>, org.apache.hadoop.hbase.regionserver.throttle.ThroughputController, org.apache.hadoop.hbase.security.User) throws java.io.IOException;
    Code:
       0: getstatic     #9                  // Field LOG:Lorg/slf4j/Logger;
       3: invokeinterface #10,  1           // InterfaceMethod org/slf4j/Logger.isDebugEnabled:()Z
       8: ifeq          52
      11: getstatic     #9                  // Field LOG:Lorg/slf4j/Logger;
      14: new           #11                 // class java/lang/StringBuilder
      17: dup
      18: invokespecial #12                 // Method java/lang/StringBuilder."<init>":()V
      21: ldc           #13                 // String Executing compaction with
      23: invokevirtual #14                 // Method java/lang/StringBuilder.append:(Ljava/lang/String;)Ljava/lang/StringBuilder;
      26: aload_2
      27: invokeinterface #15,  1           // InterfaceMethod java/util/List.size:()I
      32: invokevirtual #16                 // Method java/lang/StringBuilder.append:(I)Ljava/lang/StringBuilder;
      35: ldc           #17                 // String windows, lower boundaries:
      37: invokevirtual #14                 // Method java/lang/StringBuilder.append:(Ljava/lang/String;)Ljava/lang/StringBuilder;
      40: aload_2
      41: invokevirtual #18                 // Method java/lang/StringBuilder.append:(Ljava/lang/Object;)Ljava/lang/StringBuilder;
      44: invokevirtual #19                 // Method java/lang/StringBuilder.toString:()Ljava/lang/String;
      47: invokeinterface #20,  2           // InterfaceMethod org/slf4j/Logger.debug:(Ljava/lang/String;)V
      52: aload_0
      53: aload_1
      54: aload_0
      55: getfield      #21                 // Field defaultScannerFactory:Lorg/apache/hadoop/hbase/regionserver/compactions/Compactor$InternalScannerFactory;
      58: new           #22                 // class org/apache/hadoop/hbase/regionserver/compactions/DateTieredCompactor$1
      61: dup
      62: aload_0
      63: aload_2
      64: aload_1
      65: invokespecial #23                 // Method org/apache/hadoop/hbase/regionserver/compactions/DateTieredCompactor$1."<init>":(Lorg/apache/hadoop/hbase/regionserver/compactions/DateTieredCompactor;Ljava/util/List;Lorg/apache/hadoop/hbase/regionserver/compactions/CompactionRequestImpl;)V
      68: aload_3
      69: aload         4
      71: invokevirtual #24                 // Method compact:(Lorg/apache/hadoop/hbase/regionserver/compactions/CompactionRequestImpl;Lorg/apache/hadoop/hbase/regionserver/compactions/Compactor$InternalScannerFactory;Lorg/apache/hadoop/hbase/regionserver/compactions/Compactor$CellSinkFactory;Lorg/apache/hadoop/hbase/regionserver/throttle/ThroughputController;Lorg/apache/hadoop/hbase/security/User;)Ljava/util/List;
      74: areturn

  protected java.util.List<org.apache.hadoop.fs.Path> commitWriter(org.apache.hadoop.hbase.regionserver.DateTieredMultiFileWriter, org.apache.hadoop.hbase.regionserver.compactions.Compactor$FileDetails, org.apache.hadoop.hbase.regionserver.compactions.CompactionRequestImpl) throws java.io.IOException;
    Code:
       0: aload_1
       1: aload_2
       2: getfield      #25                 // Field org/apache/hadoop/hbase/regionserver/compactions/Compactor$FileDetails.maxSeqId:J
       5: aload_3
       6: invokevirtual #26                 // Method org/apache/hadoop/hbase/regionserver/compactions/CompactionRequestImpl.isAllFiles:()Z
       9: aload_3
      10: invokevirtual #3                  // Method org/apache/hadoop/hbase/regionserver/compactions/CompactionRequestImpl.getFiles:()Ljava/util/Collection;
      13: invokevirtual #27                 // Method org/apache/hadoop/hbase/regionserver/DateTieredMultiFileWriter.commitWriters:(JZLjava/util/Collection;)Ljava/util/List;
      16: areturn

  protected java.util.List commitWriter(org.apache.hadoop.hbase.regionserver.CellSink, org.apache.hadoop.hbase.regionserver.compactions.Compactor$FileDetails, org.apache.hadoop.hbase.regionserver.compactions.CompactionRequestImpl) throws java.io.IOException;
    Code:
       0: aload_0
       1: aload_1
       2: checkcast     #28                 // class org/apache/hadoop/hbase/regionserver/DateTieredMultiFileWriter
       5: aload_2
       6: aload_3
       7: invokevirtual #29                 // Method commitWriter:(Lorg/apache/hadoop/hbase/regionserver/DateTieredMultiFileWriter;Lorg/apache/hadoop/hbase/regionserver/compactions/Compactor$FileDetails;Lorg/apache/hadoop/hbase/regionserver/compactions/CompactionRequestImpl;)Ljava/util/List;
      10: areturn

  static boolean access$000(org.apache.hadoop.hbase.regionserver.compactions.DateTieredCompactor, org.apache.hadoop.hbase.regionserver.compactions.CompactionRequestImpl);
    Code:
       0: aload_0
       1: aload_1
       2: invokespecial #1                  // Method needEmptyFile:(Lorg/apache/hadoop/hbase/regionserver/compactions/CompactionRequestImpl;)Z
       5: ireturn

  static {};
    Code:
       0: ldc           #30                 // class org/apache/hadoop/hbase/regionserver/compactions/DateTieredCompactor
       2: invokestatic  #31                 // Method org/slf4j/LoggerFactory.getLogger:(Ljava/lang/Class;)Lorg/slf4j/Logger;
       5: putstatic     #9                  // Field LOG:Lorg/slf4j/Logger;
       8: return
}
