Compiled from "DeadServer.java"
final class org.apache.hadoop.hbase.master.DeadServer$1 implements java.util.Comparator<org.apache.hadoop.hbase.util.Pair<org.apache.hadoop.hbase.ServerName, java.lang.Long>> {
  org.apache.hadoop.hbase.master.DeadServer$1();
    Code:
       0: aload_0
       1: invokespecial #1                  // Method java/lang/Object."<init>":()V
       4: return

  public int compare(org.apache.hadoop.hbase.util.Pair<org.apache.hadoop.hbase.ServerName, java.lang.Long>, org.apache.hadoop.hbase.util.Pair<org.apache.hadoop.hbase.ServerName, java.lang.Long>);
    Code:
       0: aload_1
       1: invokevirtual #2                  // Method org/apache/hadoop/hbase/util/Pair.getSecond:()Ljava/lang/Object;
       4: checkcast     #3                  // class java/lang/Long
       7: aload_2
       8: invokevirtual #2                  // Method org/apache/hadoop/hbase/util/Pair.getSecond:()Ljava/lang/Object;
      11: checkcast     #3                  // class java/lang/Long
      14: invokevirtual #4                  // Method java/lang/Long.compareTo:(Ljava/lang/Long;)I
      17: ireturn

  public int compare(java.lang.Object, java.lang.Object);
    Code:
       0: aload_0
       1: aload_1
       2: checkcast     #5                  // class org/apache/hadoop/hbase/util/Pair
       5: aload_2
       6: checkcast     #5                  // class org/apache/hadoop/hbase/util/Pair
       9: invokevirtual #6                  // Method compare:(Lorg/apache/hadoop/hbase/util/Pair;Lorg/apache/hadoop/hbase/util/Pair;)I
      12: ireturn
}
