Compiled from "DefaultMemStore.java"
public class org.apache.hadoop.hbase.regionserver.DefaultMemStore extends org.apache.hadoop.hbase.regionserver.AbstractMemStore {
  public static final long DEEP_OVERHEAD;

  public static final long FIXED_OVERHEAD;

  public org.apache.hadoop.hbase.regionserver.DefaultMemStore();
    Code:
       0: aload_0
       1: invokestatic  #1                  // Method org/apache/hadoop/hbase/HBaseConfiguration.create:()Lorg/apache/hadoop/conf/Configuration;
       4: invokestatic  #2                  // InterfaceMethod org/apache/hadoop/hbase/CellComparator.getInstance:()Lorg/apache/hadoop/hbase/CellComparator;
       7: aconst_null
       8: invokespecial #3                  // Method "<init>":(Lorg/apache/hadoop/conf/Configuration;Lorg/apache/hadoop/hbase/CellComparator;Lorg/apache/hadoop/hbase/regionserver/RegionServicesForStores;)V
      11: return

  public org.apache.hadoop.hbase.regionserver.DefaultMemStore(org.apache.hadoop.conf.Configuration, org.apache.hadoop.hbase.CellComparator);
    Code:
       0: aload_0
       1: aload_1
       2: aload_2
       3: aconst_null
       4: invokespecial #4                  // Method org/apache/hadoop/hbase/regionserver/AbstractMemStore."<init>":(Lorg/apache/hadoop/conf/Configuration;Lorg/apache/hadoop/hbase/CellComparator;Lorg/apache/hadoop/hbase/regionserver/RegionServicesForStores;)V
       7: return

  public org.apache.hadoop.hbase.regionserver.DefaultMemStore(org.apache.hadoop.conf.Configuration, org.apache.hadoop.hbase.CellComparator, org.apache.hadoop.hbase.regionserver.RegionServicesForStores);
    Code:
       0: aload_0
       1: aload_1
       2: aload_2
       3: aload_3
       4: invokespecial #4                  // Method org/apache/hadoop/hbase/regionserver/AbstractMemStore."<init>":(Lorg/apache/hadoop/conf/Configuration;Lorg/apache/hadoop/hbase/CellComparator;Lorg/apache/hadoop/hbase/regionserver/RegionServicesForStores;)V
       7: return

  public org.apache.hadoop.hbase.regionserver.MemStoreSnapshot snapshot();
    Code:
       0: aload_0
       1: getfield      #5                  // Field snapshot:Lorg/apache/hadoop/hbase/regionserver/ImmutableSegment;
       4: invokevirtual #6                  // Method org/apache/hadoop/hbase/regionserver/ImmutableSegment.isEmpty:()Z
       7: ifne          23
      10: getstatic     #7                  // Field LOG:Lorg/slf4j/Logger;
      13: ldc           #8                  // String Snapshot called again without clearing previous. Doing nothing. Another ongoing flush or did we fail last attempt?
      15: invokeinterface #9,  2            // InterfaceMethod org/slf4j/Logger.warn:(Ljava/lang/String;)V
      20: goto          107
      23: aload_0
      24: invokestatic  #10                 // Method org/apache/hadoop/hbase/util/EnvironmentEdgeManager.currentTime:()J
      27: putfield      #11                 // Field snapshotId:J
      30: aload_0
      31: invokevirtual #12                 // Method getActive:()Lorg/apache/hadoop/hbase/regionserver/MutableSegment;
      34: invokevirtual #13                 // Method org/apache/hadoop/hbase/regionserver/MutableSegment.isEmpty:()Z
      37: ifne          107
      40: new           #14                 // class org/apache/hadoop/hbase/regionserver/NonThreadSafeMemStoreSizing
      43: dup
      44: invokespecial #15                 // Method org/apache/hadoop/hbase/regionserver/NonThreadSafeMemStoreSizing."<init>":()V
      47: astore_1
      48: invokestatic  #16                 // Method org/apache/hadoop/hbase/regionserver/SegmentFactory.instance:()Lorg/apache/hadoop/hbase/regionserver/SegmentFactory;
      51: aload_0
      52: invokevirtual #12                 // Method getActive:()Lorg/apache/hadoop/hbase/regionserver/MutableSegment;
      55: aload_1
      56: invokevirtual #17                 // Method org/apache/hadoop/hbase/regionserver/SegmentFactory.createImmutableSegment:(Lorg/apache/hadoop/hbase/regionserver/MutableSegment;Lorg/apache/hadoop/hbase/regionserver/MemStoreSizing;)Lorg/apache/hadoop/hbase/regionserver/ImmutableSegment;
      59: astore_2
      60: aload_0
      61: getfield      #18                 // Field regionServices:Lorg/apache/hadoop/hbase/regionserver/RegionServicesForStores;
      64: ifnull        98
      67: aload_0
      68: getfield      #18                 // Field regionServices:Lorg/apache/hadoop/hbase/regionserver/RegionServicesForStores;
      71: aload_1
      72: invokeinterface #19,  1           // InterfaceMethod org/apache/hadoop/hbase/regionserver/MemStoreSizing.getDataSize:()J
      77: aload_1
      78: invokeinterface #20,  1           // InterfaceMethod org/apache/hadoop/hbase/regionserver/MemStoreSizing.getHeapSize:()J
      83: aload_1
      84: invokeinterface #21,  1           // InterfaceMethod org/apache/hadoop/hbase/regionserver/MemStoreSizing.getOffHeapSize:()J
      89: aload_1
      90: invokeinterface #22,  1           // InterfaceMethod org/apache/hadoop/hbase/regionserver/MemStoreSizing.getCellsCount:()I
      95: invokevirtual #23                 // Method org/apache/hadoop/hbase/regionserver/RegionServicesForStores.addMemStoreSize:(JJJI)V
      98: aload_0
      99: aload_2
     100: putfield      #5                  // Field snapshot:Lorg/apache/hadoop/hbase/regionserver/ImmutableSegment;
     103: aload_0
     104: invokevirtual #24                 // Method resetActive:()V
     107: new           #25                 // class org/apache/hadoop/hbase/regionserver/MemStoreSnapshot
     110: dup
     111: aload_0
     112: getfield      #11                 // Field snapshotId:J
     115: aload_0
     116: getfield      #5                  // Field snapshot:Lorg/apache/hadoop/hbase/regionserver/ImmutableSegment;
     119: invokespecial #26                 // Method org/apache/hadoop/hbase/regionserver/MemStoreSnapshot."<init>":(JLorg/apache/hadoop/hbase/regionserver/ImmutableSegment;)V
     122: areturn

  public org.apache.hadoop.hbase.regionserver.MemStoreSize getFlushableSize();
    Code:
       0: aload_0
       1: invokevirtual #27                 // Method getSnapshotSize:()Lorg/apache/hadoop/hbase/regionserver/MemStoreSize;
       4: astore_1
       5: aload_1
       6: invokevirtual #28                 // Method org/apache/hadoop/hbase/regionserver/MemStoreSize.getDataSize:()J
       9: lconst_0
      10: lcmp
      11: ifle          18
      14: aload_1
      15: goto          25
      18: aload_0
      19: invokevirtual #12                 // Method getActive:()Lorg/apache/hadoop/hbase/regionserver/MutableSegment;
      22: invokevirtual #29                 // Method org/apache/hadoop/hbase/regionserver/MutableSegment.getMemStoreSize:()Lorg/apache/hadoop/hbase/regionserver/MemStoreSize;
      25: areturn

  protected long keySize();
    Code:
       0: aload_0
       1: invokevirtual #12                 // Method getActive:()Lorg/apache/hadoop/hbase/regionserver/MutableSegment;
       4: invokevirtual #30                 // Method org/apache/hadoop/hbase/regionserver/MutableSegment.getDataSize:()J
       7: lreturn

  protected long heapSize();
    Code:
       0: aload_0
       1: invokevirtual #12                 // Method getActive:()Lorg/apache/hadoop/hbase/regionserver/MutableSegment;
       4: invokevirtual #31                 // Method org/apache/hadoop/hbase/regionserver/MutableSegment.getHeapSize:()J
       7: lreturn

  public java.util.List<org.apache.hadoop.hbase.regionserver.KeyValueScanner> getScanners(long) throws java.io.IOException;
    Code:
       0: new           #32                 // class java/util/ArrayList
       3: dup
       4: invokespecial #33                 // Method java/util/ArrayList."<init>":()V
       7: astore_3
       8: aload_0
       9: invokevirtual #12                 // Method getActive:()Lorg/apache/hadoop/hbase/regionserver/MutableSegment;
      12: lload_1
      13: aload_3
      14: invokestatic  #34                 // Method addToScanners:(Lorg/apache/hadoop/hbase/regionserver/Segment;JLjava/util/List;)V
      17: aload_0
      18: getfield      #5                  // Field snapshot:Lorg/apache/hadoop/hbase/regionserver/ImmutableSegment;
      21: invokevirtual #35                 // Method org/apache/hadoop/hbase/regionserver/ImmutableSegment.getAllSegments:()Ljava/util/List;
      24: lload_1
      25: aload_3
      26: invokestatic  #36                 // Method addToScanners:(Ljava/util/List;JLjava/util/List;)V
      29: aload_3
      30: areturn

  protected java.util.List<org.apache.hadoop.hbase.regionserver.Segment> getSegments() throws java.io.IOException;
    Code:
       0: new           #32                 // class java/util/ArrayList
       3: dup
       4: iconst_2
       5: invokespecial #37                 // Method java/util/ArrayList."<init>":(I)V
       8: astore_1
       9: aload_1
      10: aload_0
      11: invokevirtual #12                 // Method getActive:()Lorg/apache/hadoop/hbase/regionserver/MutableSegment;
      14: invokeinterface #38,  2           // InterfaceMethod java/util/List.add:(Ljava/lang/Object;)Z
      19: pop
      20: aload_1
      21: aload_0
      22: getfield      #5                  // Field snapshot:Lorg/apache/hadoop/hbase/regionserver/ImmutableSegment;
      25: invokeinterface #38,  2           // InterfaceMethod java/util/List.add:(Ljava/lang/Object;)Z
      30: pop
      31: aload_1
      32: areturn

  org.apache.hadoop.hbase.Cell getNextRow(org.apache.hadoop.hbase.Cell);
    Code:
       0: aload_0
       1: aload_0
       2: aload_1
       3: aload_0
       4: invokevirtual #12                 // Method getActive:()Lorg/apache/hadoop/hbase/regionserver/MutableSegment;
       7: invokevirtual #39                 // Method org/apache/hadoop/hbase/regionserver/MutableSegment.getCellSet:()Lorg/apache/hadoop/hbase/regionserver/CellSet;
      10: invokevirtual #40                 // Method getNextRow:(Lorg/apache/hadoop/hbase/Cell;Ljava/util/NavigableSet;)Lorg/apache/hadoop/hbase/Cell;
      13: aload_0
      14: aload_1
      15: aload_0
      16: getfield      #5                  // Field snapshot:Lorg/apache/hadoop/hbase/regionserver/ImmutableSegment;
      19: invokevirtual #41                 // Method org/apache/hadoop/hbase/regionserver/ImmutableSegment.getCellSet:()Lorg/apache/hadoop/hbase/regionserver/CellSet;
      22: invokevirtual #40                 // Method getNextRow:(Lorg/apache/hadoop/hbase/Cell;Ljava/util/NavigableSet;)Lorg/apache/hadoop/hbase/Cell;
      25: invokevirtual #42                 // Method getLowest:(Lorg/apache/hadoop/hbase/Cell;Lorg/apache/hadoop/hbase/Cell;)Lorg/apache/hadoop/hbase/Cell;
      28: areturn

  public void updateLowestUnflushedSequenceIdInWAL(boolean);
    Code:
       0: return

  protected boolean preUpdate(org.apache.hadoop.hbase.regionserver.MutableSegment, org.apache.hadoop.hbase.Cell, org.apache.hadoop.hbase.regionserver.MemStoreSizing);
    Code:
       0: iconst_1
       1: ireturn

  protected void postUpdate(org.apache.hadoop.hbase.regionserver.MutableSegment);
    Code:
       0: return

  protected boolean sizeAddedPreOperation();
    Code:
       0: iconst_0
       1: ireturn

  public org.apache.hadoop.hbase.regionserver.MemStoreSize size();
    Code:
       0: aload_0
       1: invokevirtual #12                 // Method getActive:()Lorg/apache/hadoop/hbase/regionserver/MutableSegment;
       4: invokevirtual #29                 // Method org/apache/hadoop/hbase/regionserver/MutableSegment.getMemStoreSize:()Lorg/apache/hadoop/hbase/regionserver/MemStoreSize;
       7: areturn

  public long preFlushSeqIDEstimation();
    Code:
       0: ldc2_w        #44                 // long -1l
       3: lreturn

  public boolean isSloppy();
    Code:
       0: iconst_0
       1: ireturn

  public static void main(java.lang.String[]);
    Code:
       0: invokestatic  #46                 // Method java/lang/management/ManagementFactory.getRuntimeMXBean:()Ljava/lang/management/RuntimeMXBean;
       3: astore_1
       4: getstatic     #7                  // Field LOG:Lorg/slf4j/Logger;
       7: new           #47                 // class java/lang/StringBuilder
      10: dup
      11: invokespecial #48                 // Method java/lang/StringBuilder."<init>":()V
      14: ldc           #49                 // String vmName=
      16: invokevirtual #50                 // Method java/lang/StringBuilder.append:(Ljava/lang/String;)Ljava/lang/StringBuilder;
      19: aload_1
      20: invokeinterface #51,  1           // InterfaceMethod java/lang/management/RuntimeMXBean.getVmName:()Ljava/lang/String;
      25: invokevirtual #50                 // Method java/lang/StringBuilder.append:(Ljava/lang/String;)Ljava/lang/StringBuilder;
      28: ldc           #52                 // String , vmVendor=
      30: invokevirtual #50                 // Method java/lang/StringBuilder.append:(Ljava/lang/String;)Ljava/lang/StringBuilder;
      33: aload_1
      34: invokeinterface #53,  1           // InterfaceMethod java/lang/management/RuntimeMXBean.getVmVendor:()Ljava/lang/String;
      39: invokevirtual #50                 // Method java/lang/StringBuilder.append:(Ljava/lang/String;)Ljava/lang/StringBuilder;
      42: ldc           #54                 // String , vmVersion=
      44: invokevirtual #50                 // Method java/lang/StringBuilder.append:(Ljava/lang/String;)Ljava/lang/StringBuilder;
      47: aload_1
      48: invokeinterface #55,  1           // InterfaceMethod java/lang/management/RuntimeMXBean.getVmVersion:()Ljava/lang/String;
      53: invokevirtual #50                 // Method java/lang/StringBuilder.append:(Ljava/lang/String;)Ljava/lang/StringBuilder;
      56: invokevirtual #56                 // Method java/lang/StringBuilder.toString:()Ljava/lang/String;
      59: invokeinterface #57,  2           // InterfaceMethod org/slf4j/Logger.info:(Ljava/lang/String;)V
      64: getstatic     #7                  // Field LOG:Lorg/slf4j/Logger;
      67: new           #47                 // class java/lang/StringBuilder
      70: dup
      71: invokespecial #48                 // Method java/lang/StringBuilder."<init>":()V
      74: ldc           #58                 // String vmInputArguments=
      76: invokevirtual #50                 // Method java/lang/StringBuilder.append:(Ljava/lang/String;)Ljava/lang/StringBuilder;
      79: aload_1
      80: invokeinterface #59,  1           // InterfaceMethod java/lang/management/RuntimeMXBean.getInputArguments:()Ljava/util/List;
      85: invokevirtual #60                 // Method java/lang/StringBuilder.append:(Ljava/lang/Object;)Ljava/lang/StringBuilder;
      88: invokevirtual #56                 // Method java/lang/StringBuilder.toString:()Ljava/lang/String;
      91: invokeinterface #57,  2           // InterfaceMethod org/slf4j/Logger.info:(Ljava/lang/String;)V
      96: new           #61                 // class org/apache/hadoop/hbase/regionserver/DefaultMemStore
      99: dup
     100: invokespecial #62                 // Method "<init>":()V
     103: astore_2
     104: sipush        10000
     107: istore_3
     108: ldc           #63                 // String col
     110: invokestatic  #64                 // Method org/apache/hadoop/hbase/util/Bytes.toBytes:(Ljava/lang/String;)[B
     113: astore        4
     115: ldc           #65                 // String umn
     117: invokestatic  #64                 // Method org/apache/hadoop/hbase/util/Bytes.toBytes:(Ljava/lang/String;)[B
     120: astore        5
     122: iconst_0
     123: newarray       byte
     125: astore        6
     127: new           #14                 // class org/apache/hadoop/hbase/regionserver/NonThreadSafeMemStoreSizing
     130: dup
     131: invokespecial #15                 // Method org/apache/hadoop/hbase/regionserver/NonThreadSafeMemStoreSizing."<init>":()V
     134: astore        7
     136: iconst_0
     137: istore        8
     139: iload         8
     141: sipush        10000
     144: if_icmpge     180
     147: aload_2
     148: new           #66                 // class org/apache/hadoop/hbase/KeyValue
     151: dup
     152: iload         8
     154: invokestatic  #67                 // Method org/apache/hadoop/hbase/util/Bytes.toBytes:(I)[B
     157: aload         4
     159: aload         5
     161: iload         8
     163: i2l
     164: aload         6
     166: invokespecial #68                 // Method org/apache/hadoop/hbase/KeyValue."<init>":([B[B[BJ[B)V
     169: aload         7
     171: invokevirtual #69                 // Method add:(Lorg/apache/hadoop/hbase/Cell;Lorg/apache/hadoop/hbase/regionserver/MemStoreSizing;)V
     174: iinc          8, 1
     177: goto          139
     180: getstatic     #7                  // Field LOG:Lorg/slf4j/Logger;
     183: ldc           #70                 // String memstore1 estimated size={}
     185: aload         7
     187: invokeinterface #71,  1           // InterfaceMethod org/apache/hadoop/hbase/regionserver/MemStoreSizing.getMemStoreSize:()Lorg/apache/hadoop/hbase/regionserver/MemStoreSize;
     192: invokevirtual #28                 // Method org/apache/hadoop/hbase/regionserver/MemStoreSize.getDataSize:()J
     195: aload         7
     197: invokeinterface #71,  1           // InterfaceMethod org/apache/hadoop/hbase/regionserver/MemStoreSizing.getMemStoreSize:()Lorg/apache/hadoop/hbase/regionserver/MemStoreSize;
     202: invokevirtual #72                 // Method org/apache/hadoop/hbase/regionserver/MemStoreSize.getHeapSize:()J
     205: ladd
     206: invokestatic  #73                 // Method java/lang/Long.valueOf:(J)Ljava/lang/Long;
     209: invokeinterface #74,  3           // InterfaceMethod org/slf4j/Logger.info:(Ljava/lang/String;Ljava/lang/Object;)V
     214: iconst_0
     215: istore        8
     217: iload         8
     219: sipush        10000
     222: if_icmpge     258
     225: aload_2
     226: new           #66                 // class org/apache/hadoop/hbase/KeyValue
     229: dup
     230: iload         8
     232: invokestatic  #67                 // Method org/apache/hadoop/hbase/util/Bytes.toBytes:(I)[B
     235: aload         4
     237: aload         5
     239: iload         8
     241: i2l
     242: aload         6
     244: invokespecial #68                 // Method org/apache/hadoop/hbase/KeyValue."<init>":([B[B[BJ[B)V
     247: aload         7
     249: invokevirtual #69                 // Method add:(Lorg/apache/hadoop/hbase/Cell;Lorg/apache/hadoop/hbase/regionserver/MemStoreSizing;)V
     252: iinc          8, 1
     255: goto          217
     258: getstatic     #7                  // Field LOG:Lorg/slf4j/Logger;
     261: ldc           #75                 // String memstore1 estimated size (2nd loading of same data)={}
     263: aload         7
     265: invokeinterface #71,  1           // InterfaceMethod org/apache/hadoop/hbase/regionserver/MemStoreSizing.getMemStoreSize:()Lorg/apache/hadoop/hbase/regionserver/MemStoreSize;
     270: invokevirtual #28                 // Method org/apache/hadoop/hbase/regionserver/MemStoreSize.getDataSize:()J
     273: aload         7
     275: invokeinterface #71,  1           // InterfaceMethod org/apache/hadoop/hbase/regionserver/MemStoreSizing.getMemStoreSize:()Lorg/apache/hadoop/hbase/regionserver/MemStoreSize;
     280: invokevirtual #72                 // Method org/apache/hadoop/hbase/regionserver/MemStoreSize.getHeapSize:()J
     283: ladd
     284: invokestatic  #73                 // Method java/lang/Long.valueOf:(J)Ljava/lang/Long;
     287: invokeinterface #74,  3           // InterfaceMethod org/slf4j/Logger.info:(Ljava/lang/String;Ljava/lang/Object;)V
     292: new           #61                 // class org/apache/hadoop/hbase/regionserver/DefaultMemStore
     295: dup
     296: invokespecial #62                 // Method "<init>":()V
     299: astore        8
     301: new           #14                 // class org/apache/hadoop/hbase/regionserver/NonThreadSafeMemStoreSizing
     304: dup
     305: invokespecial #15                 // Method org/apache/hadoop/hbase/regionserver/NonThreadSafeMemStoreSizing."<init>":()V
     308: astore        7
     310: iconst_0
     311: istore        9
     313: iload         9
     315: sipush        10000
     318: if_icmpge     357
     321: aload         8
     323: new           #66                 // class org/apache/hadoop/hbase/KeyValue
     326: dup
     327: iload         9
     329: invokestatic  #67                 // Method org/apache/hadoop/hbase/util/Bytes.toBytes:(I)[B
     332: aload         4
     334: aload         5
     336: iload         9
     338: i2l
     339: iload         9
     341: newarray       byte
     343: invokespecial #68                 // Method org/apache/hadoop/hbase/KeyValue."<init>":([B[B[BJ[B)V
     346: aload         7
     348: invokevirtual #69                 // Method add:(Lorg/apache/hadoop/hbase/Cell;Lorg/apache/hadoop/hbase/regionserver/MemStoreSizing;)V
     351: iinc          9, 1
     354: goto          313
     357: getstatic     #7                  // Field LOG:Lorg/slf4j/Logger;
     360: ldc           #76                 // String memstore2 estimated size={}
     362: aload         7
     364: invokeinterface #71,  1           // InterfaceMethod org/apache/hadoop/hbase/regionserver/MemStoreSizing.getMemStoreSize:()Lorg/apache/hadoop/hbase/regionserver/MemStoreSize;
     369: invokevirtual #28                 // Method org/apache/hadoop/hbase/regionserver/MemStoreSize.getDataSize:()J
     372: aload         7
     374: invokeinterface #71,  1           // InterfaceMethod org/apache/hadoop/hbase/regionserver/MemStoreSizing.getMemStoreSize:()Lorg/apache/hadoop/hbase/regionserver/MemStoreSize;
     379: invokevirtual #72                 // Method org/apache/hadoop/hbase/regionserver/MemStoreSize.getHeapSize:()J
     382: ladd
     383: invokestatic  #73                 // Method java/lang/Long.valueOf:(J)Ljava/lang/Long;
     386: invokeinterface #74,  3           // InterfaceMethod org/slf4j/Logger.info:(Ljava/lang/String;Ljava/lang/Object;)V
     391: bipush        30
     393: istore        9
     395: getstatic     #7                  // Field LOG:Lorg/slf4j/Logger;
     398: ldc           #77                 // String Waiting 30 seconds while heap dump is taken
     400: invokeinterface #57,  2           // InterfaceMethod org/slf4j/Logger.info:(Ljava/lang/String;)V
     405: getstatic     #7                  // Field LOG:Lorg/slf4j/Logger;
     408: ldc           #78                 // String Exiting.
     410: invokeinterface #57,  2           // InterfaceMethod org/slf4j/Logger.info:(Ljava/lang/String;)V
     415: return

  static {};
    Code:
       0: ldc           #61                 // class org/apache/hadoop/hbase/regionserver/DefaultMemStore
       2: invokestatic  #79                 // Method org/slf4j/LoggerFactory.getLogger:(Ljava/lang/Class;)Lorg/slf4j/Logger;
       5: putstatic     #7                  // Field LOG:Lorg/slf4j/Logger;
       8: getstatic     #80                 // Field org/apache/hadoop/hbase/regionserver/AbstractMemStore.DEEP_OVERHEAD:J
      11: invokestatic  #81                 // Method org/apache/hadoop/hbase/util/ClassSize.align:(J)J
      14: putstatic     #82                 // Field DEEP_OVERHEAD:J
      17: getstatic     #83                 // Field org/apache/hadoop/hbase/regionserver/AbstractMemStore.FIXED_OVERHEAD:J
      20: invokestatic  #81                 // Method org/apache/hadoop/hbase/util/ClassSize.align:(J)J
      23: putstatic     #84                 // Field FIXED_OVERHEAD:J
      26: return
}
