Compiled from "DefaultStoreFlusher.java"
public class org.apache.hadoop.hbase.regionserver.DefaultStoreFlusher extends org.apache.hadoop.hbase.regionserver.StoreFlusher {
  public org.apache.hadoop.hbase.regionserver.DefaultStoreFlusher(org.apache.hadoop.conf.Configuration, org.apache.hadoop.hbase.regionserver.HStore);
    Code:
       0: aload_0
       1: aload_1
       2: aload_2
       3: invokespecial #1                  // Method org/apache/hadoop/hbase/regionserver/StoreFlusher."<init>":(Lorg/apache/hadoop/conf/Configuration;Lorg/apache/hadoop/hbase/regionserver/HStore;)V
       6: aload_0
       7: new           #2                  // class java/lang/Object
      10: dup
      11: invokespecial #3                  // Method java/lang/Object."<init>":()V
      14: putfield      #4                  // Field flushLock:Ljava/lang/Object;
      17: return

  public java.util.List<org.apache.hadoop.fs.Path> flushSnapshot(org.apache.hadoop.hbase.regionserver.MemStoreSnapshot, long, org.apache.hadoop.hbase.monitoring.MonitoredTask, org.apache.hadoop.hbase.regionserver.throttle.ThroughputController, org.apache.hadoop.hbase.regionserver.FlushLifeCycleTracker) throws java.io.IOException;
    Code:
       0: new           #5                  // class java/util/ArrayList
       3: dup
       4: invokespecial #6                  // Method java/util/ArrayList."<init>":()V
       7: astore        7
       9: aload_1
      10: invokevirtual #7                  // Method org/apache/hadoop/hbase/regionserver/MemStoreSnapshot.getCellsCount:()I
      13: istore        8
      15: iload         8
      17: ifne          23
      20: aload         7
      22: areturn
      23: aload_0
      24: getfield      #8                  // Field store:Lorg/apache/hadoop/hbase/regionserver/HStore;
      27: invokevirtual #9                  // Method org/apache/hadoop/hbase/regionserver/HStore.getSmallestReadPoint:()J
      30: lstore        9
      32: aload_0
      33: aload_1
      34: invokevirtual #10                 // Method org/apache/hadoop/hbase/regionserver/MemStoreSnapshot.getScanners:()Ljava/util/List;
      37: lload         9
      39: aload         6
      41: invokevirtual #11                 // Method createScanner:(Ljava/util/List;JLorg/apache/hadoop/hbase/regionserver/FlushLifeCycleTracker;)Lorg/apache/hadoop/hbase/regionserver/InternalScanner;
      44: astore        11
      46: aload_0
      47: getfield      #4                  // Field flushLock:Ljava/lang/Object;
      50: dup
      51: astore        13
      53: monitorenter
      54: aload         4
      56: new           #12                 // class java/lang/StringBuilder
      59: dup
      60: invokespecial #13                 // Method java/lang/StringBuilder."<init>":()V
      63: ldc           #14                 // String Flushing
      65: invokevirtual #15                 // Method java/lang/StringBuilder.append:(Ljava/lang/String;)Ljava/lang/StringBuilder;
      68: aload_0
      69: getfield      #8                  // Field store:Lorg/apache/hadoop/hbase/regionserver/HStore;
      72: invokevirtual #16                 // Method java/lang/StringBuilder.append:(Ljava/lang/Object;)Ljava/lang/StringBuilder;
      75: ldc           #17                 // String : creating writer
      77: invokevirtual #15                 // Method java/lang/StringBuilder.append:(Ljava/lang/String;)Ljava/lang/StringBuilder;
      80: invokevirtual #18                 // Method java/lang/StringBuilder.toString:()Ljava/lang/String;
      83: invokeinterface #19,  2           // InterfaceMethod org/apache/hadoop/hbase/monitoring/MonitoredTask.setStatus:(Ljava/lang/String;)V
      88: aload_0
      89: getfield      #8                  // Field store:Lorg/apache/hadoop/hbase/regionserver/HStore;
      92: iload         8
      94: i2l
      95: aload_0
      96: getfield      #8                  // Field store:Lorg/apache/hadoop/hbase/regionserver/HStore;
      99: invokevirtual #20                 // Method org/apache/hadoop/hbase/regionserver/HStore.getColumnFamilyDescriptor:()Lorg/apache/hadoop/hbase/client/ColumnFamilyDescriptor;
     102: invokeinterface #21,  1           // InterfaceMethod org/apache/hadoop/hbase/client/ColumnFamilyDescriptor.getCompressionType:()Lorg/apache/hadoop/hbase/io/compress/Compression$Algorithm;
     107: iconst_0
     108: iconst_1
     109: aload_1
     110: invokevirtual #22                 // Method org/apache/hadoop/hbase/regionserver/MemStoreSnapshot.isTagsPresent:()Z
     113: iconst_0
     114: invokevirtual #23                 // Method org/apache/hadoop/hbase/regionserver/HStore.createWriterInTmp:(JLorg/apache/hadoop/hbase/io/compress/Compression$Algorithm;ZZZZ)Lorg/apache/hadoop/hbase/regionserver/StoreFileWriter;
     117: astore        12
     119: aconst_null
     120: astore        14
     122: aload_0
     123: aload         11
     125: aload         12
     127: lload         9
     129: aload         5
     131: invokevirtual #24                 // Method performFlush:(Lorg/apache/hadoop/hbase/regionserver/InternalScanner;Lorg/apache/hadoop/hbase/regionserver/CellSink;JLorg/apache/hadoop/hbase/regionserver/throttle/ThroughputController;)V
     134: aload         14
     136: ifnull        147
     139: aload         12
     141: invokevirtual #25                 // Method org/apache/hadoop/hbase/regionserver/StoreFileWriter.close:()V
     144: goto          195
     147: aload_0
     148: aload         12
     150: lload_2
     151: aload         4
     153: invokevirtual #26                 // Method finalizeWriter:(Lorg/apache/hadoop/hbase/regionserver/StoreFileWriter;JLorg/apache/hadoop/hbase/monitoring/MonitoredTask;)V
     156: goto          195
     159: astore        15
     161: aload         15
     163: astore        14
     165: aload         15
     167: athrow
     168: astore        16
     170: aload         14
     172: ifnull        183
     175: aload         12
     177: invokevirtual #25                 // Method org/apache/hadoop/hbase/regionserver/StoreFileWriter.close:()V
     180: goto          192
     183: aload_0
     184: aload         12
     186: lload_2
     187: aload         4
     189: invokevirtual #26                 // Method finalizeWriter:(Lorg/apache/hadoop/hbase/regionserver/StoreFileWriter;JLorg/apache/hadoop/hbase/monitoring/MonitoredTask;)V
     192: aload         16
     194: athrow
     195: aload         13
     197: monitorexit
     198: goto          209
     201: astore        17
     203: aload         13
     205: monitorexit
     206: aload         17
     208: athrow
     209: aload         11
     211: invokeinterface #28,  1           // InterfaceMethod org/apache/hadoop/hbase/regionserver/InternalScanner.close:()V
     216: goto          231
     219: astore        18
     221: aload         11
     223: invokeinterface #28,  1           // InterfaceMethod org/apache/hadoop/hbase/regionserver/InternalScanner.close:()V
     228: aload         18
     230: athrow
     231: getstatic     #29                 // Field LOG:Lorg/slf4j/Logger;
     234: ldc           #30                 // String Flushed memstore data size={} at sequenceid={} (bloomFilter={}), to={}
     236: iconst_4
     237: anewarray     #2                  // class java/lang/Object
     240: dup
     241: iconst_0
     242: aload_1
     243: invokevirtual #31                 // Method org/apache/hadoop/hbase/regionserver/MemStoreSnapshot.getDataSize:()J
     246: invokestatic  #32                 // Method org/apache/hadoop/util/StringUtils.byteDesc:(J)Ljava/lang/String;
     249: aastore
     250: dup
     251: iconst_1
     252: lload_2
     253: invokestatic  #33                 // Method java/lang/Long.valueOf:(J)Ljava/lang/Long;
     256: aastore
     257: dup
     258: iconst_2
     259: aload         12
     261: invokevirtual #34                 // Method org/apache/hadoop/hbase/regionserver/StoreFileWriter.hasGeneralBloom:()Z
     264: invokestatic  #35                 // Method java/lang/Boolean.valueOf:(Z)Ljava/lang/Boolean;
     267: aastore
     268: dup
     269: iconst_3
     270: aload         12
     272: invokevirtual #36                 // Method org/apache/hadoop/hbase/regionserver/StoreFileWriter.getPath:()Lorg/apache/hadoop/fs/Path;
     275: aastore
     276: invokeinterface #37,  3           // InterfaceMethod org/slf4j/Logger.info:(Ljava/lang/String;[Ljava/lang/Object;)V
     281: aload         7
     283: aload         12
     285: invokevirtual #36                 // Method org/apache/hadoop/hbase/regionserver/StoreFileWriter.getPath:()Lorg/apache/hadoop/fs/Path;
     288: invokevirtual #38                 // Method java/util/ArrayList.add:(Ljava/lang/Object;)Z
     291: pop
     292: aload         7
     294: areturn
    Exception table:
       from    to  target type
         122   134   159   Class java/io/IOException
         122   134   168   any
         159   170   168   any
          54   198   201   any
         201   206   201   any
          46   209   219   any
         219   221   219   any

  static {};
    Code:
       0: ldc           #39                 // class org/apache/hadoop/hbase/regionserver/DefaultStoreFlusher
       2: invokestatic  #40                 // Method org/slf4j/LoggerFactory.getLogger:(Ljava/lang/Class;)Lorg/slf4j/Logger;
       5: putstatic     #29                 // Field LOG:Lorg/slf4j/Logger;
       8: return
}
