Compiled from "DefaultHeapMemoryTuner.java"
final class org.apache.hadoop.hbase.regionserver.DefaultHeapMemoryTuner$StepDirection extends java.lang.Enum<org.apache.hadoop.hbase.regionserver.DefaultHeapMemoryTuner$StepDirection> {
  public static final org.apache.hadoop.hbase.regionserver.DefaultHeapMemoryTuner$StepDirection INCREASE_BLOCK_CACHE_SIZE;

  public static final org.apache.hadoop.hbase.regionserver.DefaultHeapMemoryTuner$StepDirection INCREASE_MEMSTORE_SIZE;

  public static final org.apache.hadoop.hbase.regionserver.DefaultHeapMemoryTuner$StepDirection NEUTRAL;

  public static org.apache.hadoop.hbase.regionserver.DefaultHeapMemoryTuner$StepDirection[] values();
    Code:
       0: getstatic     #1                  // Field $VALUES:[Lorg/apache/hadoop/hbase/regionserver/DefaultHeapMemoryTuner$StepDirection;
       3: invokevirtual #2                  // Method "[Lorg/apache/hadoop/hbase/regionserver/DefaultHeapMemoryTuner$StepDirection;".clone:()Ljava/lang/Object;
       6: checkcast     #3                  // class "[Lorg/apache/hadoop/hbase/regionserver/DefaultHeapMemoryTuner$StepDirection;"
       9: areturn

  public static org.apache.hadoop.hbase.regionserver.DefaultHeapMemoryTuner$StepDirection valueOf(java.lang.String);
    Code:
       0: ldc           #4                  // class org/apache/hadoop/hbase/regionserver/DefaultHeapMemoryTuner$StepDirection
       2: aload_0
       3: invokestatic  #5                  // Method java/lang/Enum.valueOf:(Ljava/lang/Class;Ljava/lang/String;)Ljava/lang/Enum;
       6: checkcast     #4                  // class org/apache/hadoop/hbase/regionserver/DefaultHeapMemoryTuner$StepDirection
       9: areturn

  static {};
    Code:
       0: new           #4                  // class org/apache/hadoop/hbase/regionserver/DefaultHeapMemoryTuner$StepDirection
       3: dup
       4: ldc           #7                  // String INCREASE_BLOCK_CACHE_SIZE
       6: iconst_0
       7: invokespecial #8                  // Method "<init>":(Ljava/lang/String;I)V
      10: putstatic     #9                  // Field INCREASE_BLOCK_CACHE_SIZE:Lorg/apache/hadoop/hbase/regionserver/DefaultHeapMemoryTuner$StepDirection;
      13: new           #4                  // class org/apache/hadoop/hbase/regionserver/DefaultHeapMemoryTuner$StepDirection
      16: dup
      17: ldc           #10                 // String INCREASE_MEMSTORE_SIZE
      19: iconst_1
      20: invokespecial #8                  // Method "<init>":(Ljava/lang/String;I)V
      23: putstatic     #11                 // Field INCREASE_MEMSTORE_SIZE:Lorg/apache/hadoop/hbase/regionserver/DefaultHeapMemoryTuner$StepDirection;
      26: new           #4                  // class org/apache/hadoop/hbase/regionserver/DefaultHeapMemoryTuner$StepDirection
      29: dup
      30: ldc           #12                 // String NEUTRAL
      32: iconst_2
      33: invokespecial #8                  // Method "<init>":(Ljava/lang/String;I)V
      36: putstatic     #13                 // Field NEUTRAL:Lorg/apache/hadoop/hbase/regionserver/DefaultHeapMemoryTuner$StepDirection;
      39: iconst_3
      40: anewarray     #4                  // class org/apache/hadoop/hbase/regionserver/DefaultHeapMemoryTuner$StepDirection
      43: dup
      44: iconst_0
      45: getstatic     #9                  // Field INCREASE_BLOCK_CACHE_SIZE:Lorg/apache/hadoop/hbase/regionserver/DefaultHeapMemoryTuner$StepDirection;
      48: aastore
      49: dup
      50: iconst_1
      51: getstatic     #11                 // Field INCREASE_MEMSTORE_SIZE:Lorg/apache/hadoop/hbase/regionserver/DefaultHeapMemoryTuner$StepDirection;
      54: aastore
      55: dup
      56: iconst_2
      57: getstatic     #13                 // Field NEUTRAL:Lorg/apache/hadoop/hbase/regionserver/DefaultHeapMemoryTuner$StepDirection;
      60: aastore
      61: putstatic     #1                  // Field $VALUES:[Lorg/apache/hadoop/hbase/regionserver/DefaultHeapMemoryTuner$StepDirection;
      64: return
}
