Compiled from "DelayedUtil.java"
public final class org.apache.hadoop.hbase.procedure2.util.DelayedUtil {
  public static final org.apache.hadoop.hbase.procedure2.util.DelayedUtil$DelayedWithTimeout DELAYED_POISON;

  static final boolean $assertionsDisabled;

  public static <E extends java.util.concurrent.Delayed> E takeWithoutInterrupt(java.util.concurrent.DelayQueue<E>);
    Code:
       0: aload_0
       1: invokevirtual #3                  // Method java/util/concurrent/DelayQueue.take:()Ljava/util/concurrent/Delayed;
       4: areturn
       5: astore_1
       6: invokestatic  #5                  // Method java/lang/Thread.currentThread:()Ljava/lang/Thread;
       9: invokevirtual #6                  // Method java/lang/Thread.interrupt:()V
      12: aconst_null
      13: areturn
    Exception table:
       from    to  target type
           0     4     5   Class java/lang/InterruptedException

  public static long getRemainingTime(java.util.concurrent.TimeUnit, long);
    Code:
       0: invokestatic  #7                  // Method org/apache/hadoop/hbase/util/EnvironmentEdgeManager.currentTime:()J
       3: lstore_3
       4: lload_3
       5: lload_1
       6: lcmp
       7: iflt          12
      10: lconst_0
      11: lreturn
      12: aload_0
      13: lload_1
      14: lload_3
      15: lsub
      16: getstatic     #8                  // Field java/util/concurrent/TimeUnit.MILLISECONDS:Ljava/util/concurrent/TimeUnit;
      19: invokevirtual #9                  // Method java/util/concurrent/TimeUnit.convert:(JLjava/util/concurrent/TimeUnit;)J
      22: lreturn

  public static int compareDelayed(java.util.concurrent.Delayed, java.util.concurrent.Delayed);
    Code:
       0: aload_0
       1: invokestatic  #1                  // Method getTimeout:(Ljava/util/concurrent/Delayed;)J
       4: aload_1
       5: invokestatic  #1                  // Method getTimeout:(Ljava/util/concurrent/Delayed;)J
       8: invokestatic  #10                 // Method java/lang/Long.compare:(JJ)I
      11: ireturn

  static long access$000(java.util.concurrent.Delayed);
    Code:
       0: aload_0
       1: invokestatic  #1                  // Method getTimeout:(Ljava/util/concurrent/Delayed;)J
       4: lreturn

  static {};
    Code:
       0: ldc           #22                 // class org/apache/hadoop/hbase/procedure2/util/DelayedUtil
       2: invokevirtual #23                 // Method java/lang/Class.desiredAssertionStatus:()Z
       5: ifne          12
       8: iconst_1
       9: goto          13
      12: iconst_0
      13: putstatic     #11                 // Field $assertionsDisabled:Z
      16: new           #24                 // class org/apache/hadoop/hbase/procedure2/util/DelayedUtil$1
      19: dup
      20: invokespecial #25                 // Method org/apache/hadoop/hbase/procedure2/util/DelayedUtil$1."<init>":()V
      23: putstatic     #26                 // Field DELAYED_POISON:Lorg/apache/hadoop/hbase/procedure2/util/DelayedUtil$DelayedWithTimeout;
      26: return
}
