Compiled from "DeletionListener.java"
public class org.apache.hadoop.hbase.zookeeper.DeletionListener extends org.apache.hadoop.hbase.zookeeper.ZKListener {
  public org.apache.hadoop.hbase.zookeeper.DeletionListener(org.apache.hadoop.hbase.zookeeper.ZKWatcher, java.lang.String, java.util.concurrent.CountDownLatch);
    Code:
       0: aload_0
       1: aload_1
       2: invokespecial #1                  // Method org/apache/hadoop/hbase/zookeeper/ZKListener."<init>":(Lorg/apache/hadoop/hbase/zookeeper/ZKWatcher;)V
       5: aload_0
       6: aload_2
       7: putfield      #2                  // Field pathToWatch:Ljava/lang/String;
      10: aload_0
      11: aload_3
      12: putfield      #3                  // Field deletedLatch:Ljava/util/concurrent/CountDownLatch;
      15: aload_0
      16: aconst_null
      17: putfield      #4                  // Field exception:Ljava/lang/Throwable;
      20: return

  public boolean hasException();
    Code:
       0: aload_0
       1: getfield      #4                  // Field exception:Ljava/lang/Throwable;
       4: ifnull        11
       7: iconst_1
       8: goto          12
      11: iconst_0
      12: ireturn

  public java.lang.Throwable getException();
    Code:
       0: aload_0
       1: getfield      #4                  // Field exception:Ljava/lang/Throwable;
       4: areturn

  public void nodeDataChanged(java.lang.String);
    Code:
       0: aload_1
       1: aload_0
       2: getfield      #2                  // Field pathToWatch:Ljava/lang/String;
       5: invokevirtual #5                  // Method java/lang/String.equals:(Ljava/lang/Object;)Z
       8: ifne          12
      11: return
      12: aload_0
      13: getfield      #6                  // Field watcher:Lorg/apache/hadoop/hbase/zookeeper/ZKWatcher;
      16: aload_0
      17: getfield      #2                  // Field pathToWatch:Ljava/lang/String;
      20: invokestatic  #7                  // Method org/apache/hadoop/hbase/zookeeper/ZKUtil.setWatchIfNodeExists:(Lorg/apache/hadoop/hbase/zookeeper/ZKWatcher;Ljava/lang/String;)Z
      23: ifne          33
      26: aload_0
      27: getfield      #3                  // Field deletedLatch:Ljava/util/concurrent/CountDownLatch;
      30: invokevirtual #8                  // Method java/util/concurrent/CountDownLatch.countDown:()V
      33: goto          80
      36: astore_2
      37: aload_0
      38: aload_2
      39: putfield      #4                  // Field exception:Ljava/lang/Throwable;
      42: aload_0
      43: getfield      #3                  // Field deletedLatch:Ljava/util/concurrent/CountDownLatch;
      46: invokevirtual #8                  // Method java/util/concurrent/CountDownLatch.countDown:()V
      49: getstatic     #10                 // Field LOG:Lorg/slf4j/Logger;
      52: new           #11                 // class java/lang/StringBuilder
      55: dup
      56: invokespecial #12                 // Method java/lang/StringBuilder."<init>":()V
      59: ldc           #13                 // String Error when re-setting the watch on
      61: invokevirtual #14                 // Method java/lang/StringBuilder.append:(Ljava/lang/String;)Ljava/lang/StringBuilder;
      64: aload_0
      65: getfield      #2                  // Field pathToWatch:Ljava/lang/String;
      68: invokevirtual #14                 // Method java/lang/StringBuilder.append:(Ljava/lang/String;)Ljava/lang/StringBuilder;
      71: invokevirtual #15                 // Method java/lang/StringBuilder.toString:()Ljava/lang/String;
      74: aload_2
      75: invokeinterface #16,  3           // InterfaceMethod org/slf4j/Logger.error:(Ljava/lang/String;Ljava/lang/Throwable;)V
      80: return
    Exception table:
       from    to  target type
          12    33    36   Class org/apache/zookeeper/KeeperException

  public void nodeDeleted(java.lang.String);
    Code:
       0: aload_1
       1: aload_0
       2: getfield      #2                  // Field pathToWatch:Ljava/lang/String;
       5: invokevirtual #5                  // Method java/lang/String.equals:(Ljava/lang/Object;)Z
       8: ifne          12
      11: return
      12: getstatic     #10                 // Field LOG:Lorg/slf4j/Logger;
      15: invokeinterface #17,  1           // InterfaceMethod org/slf4j/Logger.isDebugEnabled:()Z
      20: ifeq          53
      23: getstatic     #10                 // Field LOG:Lorg/slf4j/Logger;
      26: new           #11                 // class java/lang/StringBuilder
      29: dup
      30: invokespecial #12                 // Method java/lang/StringBuilder."<init>":()V
      33: ldc           #18                 // String Processing delete on
      35: invokevirtual #14                 // Method java/lang/StringBuilder.append:(Ljava/lang/String;)Ljava/lang/StringBuilder;
      38: aload_0
      39: getfield      #2                  // Field pathToWatch:Ljava/lang/String;
      42: invokevirtual #14                 // Method java/lang/StringBuilder.append:(Ljava/lang/String;)Ljava/lang/StringBuilder;
      45: invokevirtual #15                 // Method java/lang/StringBuilder.toString:()Ljava/lang/String;
      48: invokeinterface #19,  2           // InterfaceMethod org/slf4j/Logger.debug:(Ljava/lang/String;)V
      53: aload_0
      54: getfield      #3                  // Field deletedLatch:Ljava/util/concurrent/CountDownLatch;
      57: invokevirtual #8                  // Method java/util/concurrent/CountDownLatch.countDown:()V
      60: return

  static {};
    Code:
       0: ldc           #20                 // class org/apache/hadoop/hbase/zookeeper/DeletionListener
       2: invokestatic  #21                 // Method org/slf4j/LoggerFactory.getLogger:(Ljava/lang/Class;)Lorg/slf4j/Logger;
       5: putstatic     #10                 // Field LOG:Lorg/slf4j/Logger;
       8: return
}
