Compiled from "DiffKeyDeltaEncoder.java"
class org.apache.hadoop.hbase.io.encoding.DiffKeyDeltaEncoder$1 extends org.apache.hadoop.hbase.io.encoding.BufferedDataBlockEncoder$BufferedEncodedSeeker<org.apache.hadoop.hbase.io.encoding.DiffKeyDeltaEncoder$DiffSeekerState> {
  final org.apache.hadoop.hbase.io.encoding.DiffKeyDeltaEncoder this$0;

  org.apache.hadoop.hbase.io.encoding.DiffKeyDeltaEncoder$1(org.apache.hadoop.hbase.io.encoding.DiffKeyDeltaEncoder, org.apache.hadoop.hbase.CellComparator, org.apache.hadoop.hbase.io.encoding.HFileBlockDecodingContext);
    Code:
       0: aload_0
       1: aload_1
       2: putfield      #3                  // Field this$0:Lorg/apache/hadoop/hbase/io/encoding/DiffKeyDeltaEncoder;
       5: aload_0
       6: aload_2
       7: aload_3
       8: invokespecial #4                  // Method org/apache/hadoop/hbase/io/encoding/BufferedDataBlockEncoder$BufferedEncodedSeeker."<init>":(Lorg/apache/hadoop/hbase/CellComparator;Lorg/apache/hadoop/hbase/io/encoding/HFileBlockDecodingContext;)V
      11: return

  protected void decodeFirst();
    Code:
       0: aload_0
       1: getfield      #5                  // Field currentBuffer:Lorg/apache/hadoop/hbase/nio/ByteBuff;
       4: iconst_4
       5: invokevirtual #28                 // Method org/apache/hadoop/hbase/nio/ByteBuff.skip:(I)Lorg/apache/hadoop/hbase/nio/ByteBuff;
       8: pop
       9: aload_0
      10: getfield      #5                  // Field currentBuffer:Lorg/apache/hadoop/hbase/nio/ByteBuff;
      13: invokevirtual #6                  // Method org/apache/hadoop/hbase/nio/ByteBuff.get:()B
      16: istore_1
      17: aload_0
      18: iload_1
      19: iconst_1
      20: iadd
      21: newarray       byte
      23: putfield      #19                 // Field familyNameWithSize:[B
      26: aload_0
      27: getfield      #19                 // Field familyNameWithSize:[B
      30: iconst_0
      31: iload_1
      32: bastore
      33: aload_0
      34: getfield      #5                  // Field currentBuffer:Lorg/apache/hadoop/hbase/nio/ByteBuff;
      37: aload_0
      38: getfield      #19                 // Field familyNameWithSize:[B
      41: iconst_1
      42: iload_1
      43: invokevirtual #15                 // Method org/apache/hadoop/hbase/nio/ByteBuff.get:([BII)V
      46: aload_0
      47: iconst_1
      48: invokespecial #35                 // Method decode:(Z)V
      51: return

  protected void decodeNext();
    Code:
       0: aload_0
       1: iconst_0
       2: invokespecial #35                 // Method decode:(Z)V
       5: return

  protected org.apache.hadoop.hbase.io.encoding.DiffKeyDeltaEncoder$DiffSeekerState createSeekerState();
    Code:
       0: new           #8                  // class org/apache/hadoop/hbase/io/encoding/DiffKeyDeltaEncoder$DiffSeekerState
       3: dup
       4: aload_0
       5: getfield      #36                 // Field tmpPair:Lorg/apache/hadoop/hbase/util/ObjectIntPair;
       8: aload_0
       9: invokevirtual #29                 // Method includesTags:()Z
      12: invokespecial #37                 // Method org/apache/hadoop/hbase/io/encoding/DiffKeyDeltaEncoder$DiffSeekerState."<init>":(Lorg/apache/hadoop/hbase/util/ObjectIntPair;Z)V
      15: areturn

  protected org.apache.hadoop.hbase.io.encoding.BufferedDataBlockEncoder$SeekerState createSeekerState();
    Code:
       0: aload_0
       1: invokevirtual #38                 // Method createSeekerState:()Lorg/apache/hadoop/hbase/io/encoding/DiffKeyDeltaEncoder$DiffSeekerState;
       4: areturn
}
