Compiled from "DisableTableViolationPolicyEnforcement.java"
public class org.apache.hadoop.hbase.quotas.policies.DisableTableViolationPolicyEnforcement extends org.apache.hadoop.hbase.quotas.policies.DefaultViolationPolicyEnforcement {
  public org.apache.hadoop.hbase.quotas.policies.DisableTableViolationPolicyEnforcement();
    Code:
       0: aload_0
       1: invokespecial #1                  // Method org/apache/hadoop/hbase/quotas/policies/DefaultViolationPolicyEnforcement."<init>":()V
       4: return

  public void enable() throws java.io.IOException;
    Code:
       0: return

  public void disable() throws java.io.IOException;
    Code:
       0: return

  public void check(org.apache.hadoop.hbase.client.Mutation) throws org.apache.hadoop.hbase.quotas.SpaceLimitingException;
    Code:
       0: new           #2                  // class org/apache/hadoop/hbase/quotas/SpaceLimitingException
       3: dup
       4: aload_0
       5: invokevirtual #3                  // Method getPolicyName:()Ljava/lang/String;
       8: ldc           #4                  // String This table is disabled due to violating a space quota.
      10: invokespecial #5                  // Method org/apache/hadoop/hbase/quotas/SpaceLimitingException."<init>":(Ljava/lang/String;Ljava/lang/String;)V
      13: athrow

  public java.lang.String getPolicyName();
    Code:
       0: getstatic     #6                  // Field org/apache/hadoop/hbase/quotas/SpaceViolationPolicy.DISABLE:Lorg/apache/hadoop/hbase/quotas/SpaceViolationPolicy;
       3: invokevirtual #7                  // Method org/apache/hadoop/hbase/quotas/SpaceViolationPolicy.name:()Ljava/lang/String;
       6: areturn
}
