Compiled from "DoNothingAsyncRegistry.java"
class org.apache.hadoop.hbase.client.DoNothingAsyncRegistry implements org.apache.hadoop.hbase.client.AsyncRegistry {
  public org.apache.hadoop.hbase.client.DoNothingAsyncRegistry(org.apache.hadoop.conf.Configuration);
    Code:
       0: aload_0
       1: invokespecial #1                  // Method java/lang/Object."<init>":()V
       4: return

  public java.util.concurrent.CompletableFuture<org.apache.hadoop.hbase.RegionLocations> getMetaRegionLocation();
    Code:
       0: aconst_null
       1: invokestatic  #2                  // Method java/util/concurrent/CompletableFuture.completedFuture:(Ljava/lang/Object;)Ljava/util/concurrent/CompletableFuture;
       4: areturn

  public java.util.concurrent.CompletableFuture<java.lang.String> getClusterId();
    Code:
       0: aconst_null
       1: invokestatic  #2                  // Method java/util/concurrent/CompletableFuture.completedFuture:(Ljava/lang/Object;)Ljava/util/concurrent/CompletableFuture;
       4: areturn

  public java.util.concurrent.CompletableFuture<java.lang.Integer> getCurrentNrHRS();
    Code:
       0: iconst_0
       1: invokestatic  #3                  // Method java/lang/Integer.valueOf:(I)Ljava/lang/Integer;
       4: invokestatic  #2                  // Method java/util/concurrent/CompletableFuture.completedFuture:(Ljava/lang/Object;)Ljava/util/concurrent/CompletableFuture;
       7: areturn

  public java.util.concurrent.CompletableFuture<org.apache.hadoop.hbase.ServerName> getMasterAddress();
    Code:
       0: aconst_null
       1: invokestatic  #2                  // Method java/util/concurrent/CompletableFuture.completedFuture:(Ljava/lang/Object;)Ljava/util/concurrent/CompletableFuture;
       4: areturn

  public java.util.concurrent.CompletableFuture<java.lang.Integer> getMasterInfoPort();
    Code:
       0: iconst_0
       1: invokestatic  #3                  // Method java/lang/Integer.valueOf:(I)Ljava/lang/Integer;
       4: invokestatic  #2                  // Method java/util/concurrent/CompletableFuture.completedFuture:(Ljava/lang/Object;)Ljava/util/concurrent/CompletableFuture;
       7: areturn

  public void close();
    Code:
       0: return
}
