Compiled from "DropDeletesCompactionScanQueryMatcher.java"
public abstract class org.apache.hadoop.hbase.regionserver.querymatcher.DropDeletesCompactionScanQueryMatcher extends org.apache.hadoop.hbase.regionserver.querymatcher.CompactionScanQueryMatcher {
  protected final long timeToPurgeDeletes;

  protected final long earliestPutTs;

  protected org.apache.hadoop.hbase.regionserver.querymatcher.DropDeletesCompactionScanQueryMatcher(org.apache.hadoop.hbase.regionserver.ScanInfo, org.apache.hadoop.hbase.regionserver.querymatcher.DeleteTracker, org.apache.hadoop.hbase.regionserver.querymatcher.ColumnTracker, long, long, long, long);
    Code:
       0: aload_0
       1: aload_1
       2: aload_2
       3: aload_3
       4: lload         4
       6: lload         8
       8: lload         10
      10: invokespecial #1                  // Method org/apache/hadoop/hbase/regionserver/querymatcher/CompactionScanQueryMatcher."<init>":(Lorg/apache/hadoop/hbase/regionserver/ScanInfo;Lorg/apache/hadoop/hbase/regionserver/querymatcher/DeleteTracker;Lorg/apache/hadoop/hbase/regionserver/querymatcher/ColumnTracker;JJJ)V
      13: aload_0
      14: aload_1
      15: invokevirtual #2                  // Method org/apache/hadoop/hbase/regionserver/ScanInfo.getTimeToPurgeDeletes:()J
      18: putfield      #3                  // Field timeToPurgeDeletes:J
      21: aload_0
      22: lload         6
      24: putfield      #4                  // Field earliestPutTs:J
      27: return

  protected final org.apache.hadoop.hbase.regionserver.querymatcher.ScanQueryMatcher$MatchCode tryDropDelete(org.apache.hadoop.hbase.Cell);
    Code:
       0: aload_1
       1: invokeinterface #5,  1            // InterfaceMethod org/apache/hadoop/hbase/Cell.getTimestamp:()J
       6: lstore_2
       7: aload_0
       8: getfield      #3                  // Field timeToPurgeDeletes:J
      11: lconst_0
      12: lcmp
      13: ifle          34
      16: aload_0
      17: getfield      #6                  // Field now:J
      20: lload_2
      21: lsub
      22: aload_0
      23: getfield      #3                  // Field timeToPurgeDeletes:J
      26: lcmp
      27: ifgt          34
      30: getstatic     #7                  // Field org/apache/hadoop/hbase/regionserver/querymatcher/ScanQueryMatcher$MatchCode.INCLUDE:Lorg/apache/hadoop/hbase/regionserver/querymatcher/ScanQueryMatcher$MatchCode;
      33: areturn
      34: aload_0
      35: getfield      #8                  // Field keepDeletedCells:Lorg/apache/hadoop/hbase/KeepDeletedCells;
      38: getstatic     #9                  // Field org/apache/hadoop/hbase/KeepDeletedCells.TRUE:Lorg/apache/hadoop/hbase/KeepDeletedCells;
      41: if_acmpeq     63
      44: aload_0
      45: getfield      #8                  // Field keepDeletedCells:Lorg/apache/hadoop/hbase/KeepDeletedCells;
      48: getstatic     #10                 // Field org/apache/hadoop/hbase/KeepDeletedCells.TTL:Lorg/apache/hadoop/hbase/KeepDeletedCells;
      51: if_acmpne     85
      54: lload_2
      55: aload_0
      56: getfield      #11                 // Field oldestUnexpiredTS:J
      59: lcmp
      60: iflt          85
      63: lload_2
      64: aload_0
      65: getfield      #4                  // Field earliestPutTs:J
      68: lcmp
      69: ifge          83
      72: aload_0
      73: getfield      #12                 // Field columns:Lorg/apache/hadoop/hbase/regionserver/querymatcher/ColumnTracker;
      76: aload_1
      77: invokeinterface #13,  2           // InterfaceMethod org/apache/hadoop/hbase/regionserver/querymatcher/ColumnTracker.getNextRowOrNextColumn:(Lorg/apache/hadoop/hbase/Cell;)Lorg/apache/hadoop/hbase/regionserver/querymatcher/ScanQueryMatcher$MatchCode;
      82: areturn
      83: aconst_null
      84: areturn
      85: getstatic     #14                 // Field org/apache/hadoop/hbase/regionserver/querymatcher/ScanQueryMatcher$MatchCode.SKIP:Lorg/apache/hadoop/hbase/regionserver/querymatcher/ScanQueryMatcher$MatchCode;
      88: areturn
}
