Compiled from "DumpRegionServerMetrics.java"
public final class org.apache.hadoop.hbase.regionserver.DumpRegionServerMetrics {
  public static java.lang.String dumpMetrics() throws javax.management.MalformedObjectNameException, java.io.IOException;
    Code:
       0: new           #1                  // class java/io/StringWriter
       3: dup
       4: ldc           #2                  // int 102400
       6: invokespecial #3                  // Method java/io/StringWriter."<init>":(I)V
       9: astore_0
      10: new           #4                  // class java/io/PrintWriter
      13: dup
      14: aload_0
      15: invokespecial #5                  // Method java/io/PrintWriter."<init>":(Ljava/io/Writer;)V
      18: astore_1
      19: aconst_null
      20: astore_2
      21: new           #6                  // class org/apache/hadoop/hbase/util/JSONBean
      24: dup
      25: invokespecial #7                  // Method org/apache/hadoop/hbase/util/JSONBean."<init>":()V
      28: astore_3
      29: aload_3
      30: aload_1
      31: invokevirtual #8                  // Method org/apache/hadoop/hbase/util/JSONBean.open:(Ljava/io/PrintWriter;)Lorg/apache/hadoop/hbase/util/JSONBean$Writer;
      34: astore        4
      36: aconst_null
      37: astore        5
      39: invokestatic  #9                  // Method java/lang/management/ManagementFactory.getPlatformMBeanServer:()Ljavax/management/MBeanServer;
      42: astore        6
      44: aload         4
      46: aload         6
      48: new           #10                 // class javax/management/ObjectName
      51: dup
      52: ldc           #11                 // String java.lang:type=Memory
      54: invokespecial #12                 // Method javax/management/ObjectName."<init>":(Ljava/lang/String;)V
      57: aconst_null
      58: iconst_0
      59: invokeinterface #13,  5           // InterfaceMethod org/apache/hadoop/hbase/util/JSONBean$Writer.write:(Ljavax/management/MBeanServer;Ljavax/management/ObjectName;Ljava/lang/String;Z)I
      64: pop
      65: aload         4
      67: aload         6
      69: new           #10                 // class javax/management/ObjectName
      72: dup
      73: ldc           #14                 // String Hadoop:service=HBase,name=RegionServer,sub=IPC
      75: invokespecial #12                 // Method javax/management/ObjectName."<init>":(Ljava/lang/String;)V
      78: aconst_null
      79: iconst_0
      80: invokeinterface #13,  5           // InterfaceMethod org/apache/hadoop/hbase/util/JSONBean$Writer.write:(Ljavax/management/MBeanServer;Ljavax/management/ObjectName;Ljava/lang/String;Z)I
      85: pop
      86: aload         4
      88: aload         6
      90: new           #10                 // class javax/management/ObjectName
      93: dup
      94: ldc           #15                 // String Hadoop:service=HBase,name=RegionServer,sub=Replication
      96: invokespecial #12                 // Method javax/management/ObjectName."<init>":(Ljava/lang/String;)V
      99: aconst_null
     100: iconst_0
     101: invokeinterface #13,  5           // InterfaceMethod org/apache/hadoop/hbase/util/JSONBean$Writer.write:(Ljavax/management/MBeanServer;Ljavax/management/ObjectName;Ljava/lang/String;Z)I
     106: pop
     107: aload         4
     109: aload         6
     111: new           #10                 // class javax/management/ObjectName
     114: dup
     115: ldc           #16                 // String Hadoop:service=HBase,name=RegionServer,sub=Server
     117: invokespecial #12                 // Method javax/management/ObjectName."<init>":(Ljava/lang/String;)V
     120: aconst_null
     121: iconst_0
     122: invokeinterface #13,  5           // InterfaceMethod org/apache/hadoop/hbase/util/JSONBean$Writer.write:(Ljavax/management/MBeanServer;Ljavax/management/ObjectName;Ljava/lang/String;Z)I
     127: pop
     128: aload         4
     130: ifnull        223
     133: aload         5
     135: ifnull        160
     138: aload         4
     140: invokeinterface #17,  1           // InterfaceMethod org/apache/hadoop/hbase/util/JSONBean$Writer.close:()V
     145: goto          223
     148: astore        6
     150: aload         5
     152: aload         6
     154: invokevirtual #19                 // Method java/lang/Throwable.addSuppressed:(Ljava/lang/Throwable;)V
     157: goto          223
     160: aload         4
     162: invokeinterface #17,  1           // InterfaceMethod org/apache/hadoop/hbase/util/JSONBean$Writer.close:()V
     167: goto          223
     170: astore        6
     172: aload         6
     174: astore        5
     176: aload         6
     178: athrow
     179: astore        7
     181: aload         4
     183: ifnull        220
     186: aload         5
     188: ifnull        213
     191: aload         4
     193: invokeinterface #17,  1           // InterfaceMethod org/apache/hadoop/hbase/util/JSONBean$Writer.close:()V
     198: goto          220
     201: astore        8
     203: aload         5
     205: aload         8
     207: invokevirtual #19                 // Method java/lang/Throwable.addSuppressed:(Ljava/lang/Throwable;)V
     210: goto          220
     213: aload         4
     215: invokeinterface #17,  1           // InterfaceMethod org/apache/hadoop/hbase/util/JSONBean$Writer.close:()V
     220: aload         7
     222: athrow
     223: aload_1
     224: ifnull        294
     227: aload_2
     228: ifnull        247
     231: aload_1
     232: invokevirtual #20                 // Method java/io/PrintWriter.close:()V
     235: goto          294
     238: astore_3
     239: aload_2
     240: aload_3
     241: invokevirtual #19                 // Method java/lang/Throwable.addSuppressed:(Ljava/lang/Throwable;)V
     244: goto          294
     247: aload_1
     248: invokevirtual #20                 // Method java/io/PrintWriter.close:()V
     251: goto          294
     254: astore_3
     255: aload_3
     256: astore_2
     257: aload_3
     258: athrow
     259: astore        9
     261: aload_1
     262: ifnull        291
     265: aload_2
     266: ifnull        287
     269: aload_1
     270: invokevirtual #20                 // Method java/io/PrintWriter.close:()V
     273: goto          291
     276: astore        10
     278: aload_2
     279: aload         10
     281: invokevirtual #19                 // Method java/lang/Throwable.addSuppressed:(Ljava/lang/Throwable;)V
     284: goto          291
     287: aload_1
     288: invokevirtual #20                 // Method java/io/PrintWriter.close:()V
     291: aload         9
     293: athrow
     294: aload_0
     295: invokevirtual #21                 // Method java/io/StringWriter.close:()V
     298: aload_0
     299: invokevirtual #22                 // Method java/io/StringWriter.toString:()Ljava/lang/String;
     302: areturn
    Exception table:
       from    to  target type
         138   145   148   Class java/lang/Throwable
          39   128   170   Class java/lang/Throwable
          39   128   179   any
         191   198   201   Class java/lang/Throwable
         170   181   179   any
         231   235   238   Class java/lang/Throwable
          21   223   254   Class java/lang/Throwable
          21   223   259   any
         269   273   276   Class java/lang/Throwable
         254   261   259   any

  public static void main(java.lang.String[]) throws java.io.IOException, javax.management.MalformedObjectNameException;
    Code:
       0: invokestatic  #23                 // Method dumpMetrics:()Ljava/lang/String;
       3: astore_1
       4: getstatic     #24                 // Field java/lang/System.out:Ljava/io/PrintStream;
       7: aload_1
       8: invokevirtual #25                 // Method java/io/PrintStream.println:(Ljava/lang/String;)V
      11: return
}
