Compiled from "DumpReplicationQueues.java"
class org.apache.hadoop.hbase.replication.regionserver.DumpReplicationQueues$DumpOptions {
  boolean hdfs;

  boolean distributed;

  public org.apache.hadoop.hbase.replication.regionserver.DumpReplicationQueues$DumpOptions();
    Code:
       0: aload_0
       1: invokespecial #1                  // Method java/lang/Object."<init>":()V
       4: aload_0
       5: iconst_0
       6: putfield      #2                  // Field hdfs:Z
       9: aload_0
      10: iconst_0
      11: putfield      #3                  // Field distributed:Z
      14: return

  public org.apache.hadoop.hbase.replication.regionserver.DumpReplicationQueues$DumpOptions(org.apache.hadoop.hbase.replication.regionserver.DumpReplicationQueues$DumpOptions);
    Code:
       0: aload_0
       1: invokespecial #1                  // Method java/lang/Object."<init>":()V
       4: aload_0
       5: iconst_0
       6: putfield      #2                  // Field hdfs:Z
       9: aload_0
      10: iconst_0
      11: putfield      #3                  // Field distributed:Z
      14: aload_0
      15: aload_1
      16: getfield      #2                  // Field hdfs:Z
      19: putfield      #2                  // Field hdfs:Z
      22: aload_0
      23: aload_1
      24: getfield      #3                  // Field distributed:Z
      27: putfield      #3                  // Field distributed:Z
      30: return

  boolean isHdfs();
    Code:
       0: aload_0
       1: getfield      #2                  // Field hdfs:Z
       4: ireturn

  boolean isDistributed();
    Code:
       0: aload_0
       1: getfield      #3                  // Field distributed:Z
       4: ireturn

  void setHdfs(boolean);
    Code:
       0: aload_0
       1: iload_1
       2: putfield      #2                  // Field hdfs:Z
       5: return

  void setDistributed(boolean);
    Code:
       0: aload_0
       1: iload_1
       2: putfield      #3                  // Field distributed:Z
       5: return
}
