Compiled from "DumpReplicationQueues.java"
public class org.apache.hadoop.hbase.replication.regionserver.DumpReplicationQueues extends org.apache.hadoop.conf.Configured implements org.apache.hadoop.util.Tool {
  public org.apache.hadoop.hbase.replication.regionserver.DumpReplicationQueues();
    Code:
       0: aload_0
       1: invokespecial #2                  // Method org/apache/hadoop/conf/Configured."<init>":()V
       4: aload_0
       5: new           #3                  // class java/util/ArrayList
       8: dup
       9: invokespecial #4                  // Method java/util/ArrayList."<init>":()V
      12: putfield      #5                  // Field deadRegionServers:Ljava/util/List;
      15: aload_0
      16: new           #3                  // class java/util/ArrayList
      19: dup
      20: invokespecial #4                  // Method java/util/ArrayList."<init>":()V
      23: putfield      #6                  // Field deletedQueues:Ljava/util/List;
      26: aload_0
      27: invokestatic  #7                  // Method org/apache/hbase/thirdparty/com/google/common/util/concurrent/AtomicLongMap.create:()Lorg/apache/hbase/thirdparty/com/google/common/util/concurrent/AtomicLongMap;
      30: putfield      #8                  // Field peersQueueSize:Lorg/apache/hbase/thirdparty/com/google/common/util/concurrent/AtomicLongMap;
      33: aload_0
      34: lconst_0
      35: putfield      #9                  // Field totalSizeOfWALs:J
      38: aload_0
      39: lconst_0
      40: putfield      #10                 // Field numWalsNotFound:J
      43: return

  static org.apache.hadoop.hbase.replication.regionserver.DumpReplicationQueues$DumpOptions parseOpts(java.util.Queue<java.lang.String>);
    Code:
       0: new           #11                 // class org/apache/hadoop/hbase/replication/regionserver/DumpReplicationQueues$DumpOptions
       3: dup
       4: invokespecial #12                 // Method org/apache/hadoop/hbase/replication/regionserver/DumpReplicationQueues$DumpOptions."<init>":()V
       7: astore_1
       8: aconst_null
       9: astore_2
      10: aload_0
      11: invokeinterface #13,  1           // InterfaceMethod java/util/Queue.poll:()Ljava/lang/Object;
      16: checkcast     #14                 // class java/lang/String
      19: dup
      20: astore_2
      21: ifnull        166
      24: aload_2
      25: ldc           #15                 // String -h
      27: invokevirtual #16                 // Method java/lang/String.equals:(Ljava/lang/Object;)Z
      30: ifne          51
      33: aload_2
      34: ldc           #17                 // String --h
      36: invokevirtual #16                 // Method java/lang/String.equals:(Ljava/lang/Object;)Z
      39: ifne          51
      42: aload_2
      43: ldc           #18                 // String --help
      45: invokevirtual #16                 // Method java/lang/String.equals:(Ljava/lang/Object;)Z
      48: ifeq          62
      51: aload_0
      52: aload_2
      53: invokeinterface #19,  2           // InterfaceMethod java/util/Queue.add:(Ljava/lang/Object;)Z
      58: pop
      59: goto          166
      62: ldc           #20                 // String --hdfs
      64: astore_3
      65: aload_2
      66: ldc           #20                 // String --hdfs
      68: invokevirtual #16                 // Method java/lang/String.equals:(Ljava/lang/Object;)Z
      71: ifeq          82
      74: aload_1
      75: iconst_1
      76: invokevirtual #21                 // Method org/apache/hadoop/hbase/replication/regionserver/DumpReplicationQueues$DumpOptions.setHdfs:(Z)V
      79: goto          10
      82: ldc           #22                 // String --distributed
      84: astore        4
      86: aload_2
      87: ldc           #22                 // String --distributed
      89: invokevirtual #16                 // Method java/lang/String.equals:(Ljava/lang/Object;)Z
      92: ifeq          103
      95: aload_1
      96: iconst_1
      97: invokevirtual #23                 // Method org/apache/hadoop/hbase/replication/regionserver/DumpReplicationQueues$DumpOptions.setDistributed:(Z)V
     100: goto          10
     103: new           #24                 // class java/lang/StringBuilder
     106: dup
     107: invokespecial #25                 // Method java/lang/StringBuilder."<init>":()V
     110: ldc           #26                 // String ERROR: Unrecognized option/command:
     112: invokevirtual #27                 // Method java/lang/StringBuilder.append:(Ljava/lang/String;)Ljava/lang/StringBuilder;
     115: aload_2
     116: invokevirtual #27                 // Method java/lang/StringBuilder.append:(Ljava/lang/String;)Ljava/lang/StringBuilder;
     119: invokevirtual #28                 // Method java/lang/StringBuilder.toString:()Ljava/lang/String;
     122: iconst_m1
     123: invokestatic  #29                 // Method printUsageAndExit:(Ljava/lang/String;I)V
     126: aload_1
     127: invokevirtual #30                 // Method org/apache/hadoop/hbase/replication/regionserver/DumpReplicationQueues$DumpOptions.isDistributed:()Z
     130: ifne          163
     133: aload_1
     134: invokevirtual #31                 // Method org/apache/hadoop/hbase/replication/regionserver/DumpReplicationQueues$DumpOptions.isHdfs:()Z
     137: ifeq          163
     140: new           #24                 // class java/lang/StringBuilder
     143: dup
     144: invokespecial #25                 // Method java/lang/StringBuilder."<init>":()V
     147: ldc           #32                 // String ERROR: --hdfs option can only be used with --distributed:
     149: invokevirtual #27                 // Method java/lang/StringBuilder.append:(Ljava/lang/String;)Ljava/lang/StringBuilder;
     152: aload_2
     153: invokevirtual #27                 // Method java/lang/StringBuilder.append:(Ljava/lang/String;)Ljava/lang/StringBuilder;
     156: invokevirtual #28                 // Method java/lang/StringBuilder.toString:()Ljava/lang/String;
     159: iconst_m1
     160: invokestatic  #29                 // Method printUsageAndExit:(Ljava/lang/String;I)V
     163: goto          10
     166: aload_1
     167: areturn

  public static void main(java.lang.String[]) throws java.lang.Exception;
    Code:
       0: invokestatic  #33                 // Method org/apache/hadoop/hbase/HBaseConfiguration.create:()Lorg/apache/hadoop/conf/Configuration;
       3: astore_1
       4: aload_1
       5: new           #34                 // class org/apache/hadoop/hbase/replication/regionserver/DumpReplicationQueues
       8: dup
       9: invokespecial #35                 // Method "<init>":()V
      12: aload_0
      13: invokestatic  #36                 // Method org/apache/hadoop/util/ToolRunner.run:(Lorg/apache/hadoop/conf/Configuration;Lorg/apache/hadoop/util/Tool;[Ljava/lang/String;)I
      16: istore_2
      17: iload_2
      18: invokestatic  #37                 // Method java/lang/System.exit:(I)V
      21: return

  public int run(java.lang.String[]) throws java.lang.Exception;
    Code:
       0: iconst_m1
       1: istore_2
       2: new           #38                 // class java/util/LinkedList
       5: dup
       6: invokespecial #39                 // Method java/util/LinkedList."<init>":()V
       9: astore_3
      10: aload_3
      11: aload_1
      12: invokestatic  #40                 // Method java/util/Arrays.asList:([Ljava/lang/Object;)Ljava/util/List;
      15: invokevirtual #41                 // Method java/util/LinkedList.addAll:(Ljava/util/Collection;)Z
      18: pop
      19: aload_3
      20: invokestatic  #42                 // Method parseOpts:(Ljava/util/Queue;)Lorg/apache/hadoop/hbase/replication/regionserver/DumpReplicationQueues$DumpOptions;
      23: astore        4
      25: aload_3
      26: invokevirtual #43                 // Method java/util/LinkedList.isEmpty:()Z
      29: ifne          40
      32: iconst_0
      33: istore_2
      34: aload_0
      35: invokevirtual #44                 // Method printUsage:()V
      38: iload_2
      39: ireturn
      40: aload_0
      41: aload         4
      43: invokespecial #45                 // Method dumpReplicationQueues:(Lorg/apache/hadoop/hbase/replication/regionserver/DumpReplicationQueues$DumpOptions;)I
      46: ireturn

  protected void printUsage();
    Code:
       0: aload_0
       1: invokevirtual #46                 // Method java/lang/Object.getClass:()Ljava/lang/Class;
       4: invokevirtual #47                 // Method java/lang/Class.getName:()Ljava/lang/String;
       7: aconst_null
       8: invokestatic  #48                 // Method printUsage:(Ljava/lang/String;Ljava/lang/String;)V
      11: return

  protected static void printUsage(java.lang.String);
    Code:
       0: ldc           #34                 // class org/apache/hadoop/hbase/replication/regionserver/DumpReplicationQueues
       2: invokevirtual #47                 // Method java/lang/Class.getName:()Ljava/lang/String;
       5: aload_0
       6: invokestatic  #48                 // Method printUsage:(Ljava/lang/String;Ljava/lang/String;)V
       9: return

  protected static void printUsage(java.lang.String, java.lang.String);
    Code:
       0: aload_1
       1: ifnull        18
       4: aload_1
       5: invokevirtual #49                 // Method java/lang/String.length:()I
       8: ifle          18
      11: getstatic     #50                 // Field java/lang/System.err:Ljava/io/PrintStream;
      14: aload_1
      15: invokevirtual #51                 // Method java/io/PrintStream.println:(Ljava/lang/String;)V
      18: getstatic     #50                 // Field java/lang/System.err:Ljava/io/PrintStream;
      21: new           #24                 // class java/lang/StringBuilder
      24: dup
      25: invokespecial #25                 // Method java/lang/StringBuilder."<init>":()V
      28: ldc           #52                 // String Usage: hbase
      30: invokevirtual #27                 // Method java/lang/StringBuilder.append:(Ljava/lang/String;)Ljava/lang/StringBuilder;
      33: aload_0
      34: invokevirtual #27                 // Method java/lang/StringBuilder.append:(Ljava/lang/String;)Ljava/lang/StringBuilder;
      37: ldc           #53                 // String  \
      39: invokevirtual #27                 // Method java/lang/StringBuilder.append:(Ljava/lang/String;)Ljava/lang/StringBuilder;
      42: invokevirtual #28                 // Method java/lang/StringBuilder.toString:()Ljava/lang/String;
      45: invokevirtual #51                 // Method java/io/PrintStream.println:(Ljava/lang/String;)V
      48: getstatic     #50                 // Field java/lang/System.err:Ljava/io/PrintStream;
      51: ldc           #54                 // String   <OPTIONS> [-D<property=value>]*
      53: invokevirtual #51                 // Method java/io/PrintStream.println:(Ljava/lang/String;)V
      56: getstatic     #50                 // Field java/lang/System.err:Ljava/io/PrintStream;
      59: invokevirtual #55                 // Method java/io/PrintStream.println:()V
      62: getstatic     #50                 // Field java/lang/System.err:Ljava/io/PrintStream;
      65: ldc           #56                 // String General Options:
      67: invokevirtual #51                 // Method java/io/PrintStream.println:(Ljava/lang/String;)V
      70: getstatic     #50                 // Field java/lang/System.err:Ljava/io/PrintStream;
      73: ldc           #57                 // String  -h|--h|--help  Show this help and exit.
      75: invokevirtual #51                 // Method java/io/PrintStream.println:(Ljava/lang/String;)V
      78: getstatic     #50                 // Field java/lang/System.err:Ljava/io/PrintStream;
      81: ldc           #58                 // String  --distributed  Poll each RS and print its own replication queue. Default only polls ZooKeeper
      83: invokevirtual #51                 // Method java/io/PrintStream.println:(Ljava/lang/String;)V
      86: getstatic     #50                 // Field java/lang/System.err:Ljava/io/PrintStream;
      89: ldc           #59                 // String  --hdfs         Use HDFS to calculate usage of WALs by replication. It could be overestimated if replicating to multiple peers. --distributed flag is also needed.
      91: invokevirtual #51                 // Method java/io/PrintStream.println:(Ljava/lang/String;)V
      94: return

  protected static void printUsageAndExit(java.lang.String, int);
    Code:
       0: aload_0
       1: invokestatic  #60                 // Method printUsage:(Ljava/lang/String;)V
       4: iload_1
       5: invokestatic  #37                 // Method java/lang/System.exit:(I)V
       8: return

  public java.lang.String dumpReplicationSummary();
    Code:
       0: new           #24                 // class java/lang/StringBuilder
       3: dup
       4: invokespecial #25                 // Method java/lang/StringBuilder."<init>":()V
       7: astore_1
       8: aload_0
       9: getfield      #6                  // Field deletedQueues:Ljava/util/List;
      12: invokeinterface #77,  1           // InterfaceMethod java/util/List.isEmpty:()Z
      17: ifne          118
      20: aload_1
      21: new           #24                 // class java/lang/StringBuilder
      24: dup
      25: invokespecial #25                 // Method java/lang/StringBuilder."<init>":()V
      28: ldc           #100                // String Found
      30: invokevirtual #27                 // Method java/lang/StringBuilder.append:(Ljava/lang/String;)Ljava/lang/StringBuilder;
      33: aload_0
      34: getfield      #6                  // Field deletedQueues:Ljava/util/List;
      37: invokeinterface #101,  1          // InterfaceMethod java/util/List.size:()I
      42: invokevirtual #102                // Method java/lang/StringBuilder.append:(I)Ljava/lang/StringBuilder;
      45: ldc           #103                // String  deleted queues, run hbck -fixReplication in order to remove the deleted replication queues\n
      47: invokevirtual #27                 // Method java/lang/StringBuilder.append:(Ljava/lang/String;)Ljava/lang/StringBuilder;
      50: invokevirtual #28                 // Method java/lang/StringBuilder.toString:()Ljava/lang/String;
      53: invokevirtual #27                 // Method java/lang/StringBuilder.append:(Ljava/lang/String;)Ljava/lang/StringBuilder;
      56: pop
      57: aload_0
      58: getfield      #6                  // Field deletedQueues:Ljava/util/List;
      61: invokeinterface #104,  1          // InterfaceMethod java/util/List.iterator:()Ljava/util/Iterator;
      66: astore_2
      67: aload_2
      68: invokeinterface #105,  1          // InterfaceMethod java/util/Iterator.hasNext:()Z
      73: ifeq          118
      76: aload_2
      77: invokeinterface #106,  1          // InterfaceMethod java/util/Iterator.next:()Ljava/lang/Object;
      82: checkcast     #14                 // class java/lang/String
      85: astore_3
      86: aload_1
      87: new           #24                 // class java/lang/StringBuilder
      90: dup
      91: invokespecial #25                 // Method java/lang/StringBuilder."<init>":()V
      94: ldc           #107                // String
      96: invokevirtual #27                 // Method java/lang/StringBuilder.append:(Ljava/lang/String;)Ljava/lang/StringBuilder;
      99: aload_3
     100: invokevirtual #27                 // Method java/lang/StringBuilder.append:(Ljava/lang/String;)Ljava/lang/StringBuilder;
     103: ldc           #108                // String \n
     105: invokevirtual #27                 // Method java/lang/StringBuilder.append:(Ljava/lang/String;)Ljava/lang/StringBuilder;
     108: invokevirtual #28                 // Method java/lang/StringBuilder.toString:()Ljava/lang/String;
     111: invokevirtual #27                 // Method java/lang/StringBuilder.append:(Ljava/lang/String;)Ljava/lang/StringBuilder;
     114: pop
     115: goto          67
     118: aload_0
     119: getfield      #5                  // Field deadRegionServers:Ljava/util/List;
     122: invokeinterface #77,  1           // InterfaceMethod java/util/List.isEmpty:()Z
     127: ifne          228
     130: aload_1
     131: new           #24                 // class java/lang/StringBuilder
     134: dup
     135: invokespecial #25                 // Method java/lang/StringBuilder."<init>":()V
     138: ldc           #100                // String Found
     140: invokevirtual #27                 // Method java/lang/StringBuilder.append:(Ljava/lang/String;)Ljava/lang/StringBuilder;
     143: aload_0
     144: getfield      #5                  // Field deadRegionServers:Ljava/util/List;
     147: invokeinterface #101,  1          // InterfaceMethod java/util/List.size:()I
     152: invokevirtual #102                // Method java/lang/StringBuilder.append:(I)Ljava/lang/StringBuilder;
     155: ldc           #109                // String  dead regionservers, restart one regionserver to transfer the queues of dead regionservers\n
     157: invokevirtual #27                 // Method java/lang/StringBuilder.append:(Ljava/lang/String;)Ljava/lang/StringBuilder;
     160: invokevirtual #28                 // Method java/lang/StringBuilder.toString:()Ljava/lang/String;
     163: invokevirtual #27                 // Method java/lang/StringBuilder.append:(Ljava/lang/String;)Ljava/lang/StringBuilder;
     166: pop
     167: aload_0
     168: getfield      #5                  // Field deadRegionServers:Ljava/util/List;
     171: invokeinterface #104,  1          // InterfaceMethod java/util/List.iterator:()Ljava/util/Iterator;
     176: astore_2
     177: aload_2
     178: invokeinterface #105,  1          // InterfaceMethod java/util/Iterator.hasNext:()Z
     183: ifeq          228
     186: aload_2
     187: invokeinterface #106,  1          // InterfaceMethod java/util/Iterator.next:()Ljava/lang/Object;
     192: checkcast     #14                 // class java/lang/String
     195: astore_3
     196: aload_1
     197: new           #24                 // class java/lang/StringBuilder
     200: dup
     201: invokespecial #25                 // Method java/lang/StringBuilder."<init>":()V
     204: ldc           #107                // String
     206: invokevirtual #27                 // Method java/lang/StringBuilder.append:(Ljava/lang/String;)Ljava/lang/StringBuilder;
     209: aload_3
     210: invokevirtual #27                 // Method java/lang/StringBuilder.append:(Ljava/lang/String;)Ljava/lang/StringBuilder;
     213: ldc           #108                // String \n
     215: invokevirtual #27                 // Method java/lang/StringBuilder.append:(Ljava/lang/String;)Ljava/lang/StringBuilder;
     218: invokevirtual #28                 // Method java/lang/StringBuilder.toString:()Ljava/lang/String;
     221: invokevirtual #27                 // Method java/lang/StringBuilder.append:(Ljava/lang/String;)Ljava/lang/StringBuilder;
     224: pop
     225: goto          177
     228: aload_0
     229: getfield      #8                  // Field peersQueueSize:Lorg/apache/hbase/thirdparty/com/google/common/util/concurrent/AtomicLongMap;
     232: invokevirtual #110                // Method org/apache/hbase/thirdparty/com/google/common/util/concurrent/AtomicLongMap.isEmpty:()Z
     235: ifne          336
     238: aload_1
     239: ldc           #111                // String Dumping all peers's number of WALs in replication queue\n
     241: invokevirtual #27                 // Method java/lang/StringBuilder.append:(Ljava/lang/String;)Ljava/lang/StringBuilder;
     244: pop
     245: aload_0
     246: getfield      #8                  // Field peersQueueSize:Lorg/apache/hbase/thirdparty/com/google/common/util/concurrent/AtomicLongMap;
     249: invokevirtual #112                // Method org/apache/hbase/thirdparty/com/google/common/util/concurrent/AtomicLongMap.asMap:()Ljava/util/Map;
     252: invokeinterface #113,  1          // InterfaceMethod java/util/Map.entrySet:()Ljava/util/Set;
     257: invokeinterface #114,  1          // InterfaceMethod java/util/Set.iterator:()Ljava/util/Iterator;
     262: astore_2
     263: aload_2
     264: invokeinterface #105,  1          // InterfaceMethod java/util/Iterator.hasNext:()Z
     269: ifeq          336
     272: aload_2
     273: invokeinterface #106,  1          // InterfaceMethod java/util/Iterator.next:()Ljava/lang/Object;
     278: checkcast     #115                // class java/util/Map$Entry
     281: astore_3
     282: aload_1
     283: new           #24                 // class java/lang/StringBuilder
     286: dup
     287: invokespecial #25                 // Method java/lang/StringBuilder."<init>":()V
     290: ldc           #116                // String     PeerId:
     292: invokevirtual #27                 // Method java/lang/StringBuilder.append:(Ljava/lang/String;)Ljava/lang/StringBuilder;
     295: aload_3
     296: invokeinterface #117,  1          // InterfaceMethod java/util/Map$Entry.getKey:()Ljava/lang/Object;
     301: checkcast     #14                 // class java/lang/String
     304: invokevirtual #27                 // Method java/lang/StringBuilder.append:(Ljava/lang/String;)Ljava/lang/StringBuilder;
     307: ldc           #118                // String  , sizeOfLogQueue:
     309: invokevirtual #27                 // Method java/lang/StringBuilder.append:(Ljava/lang/String;)Ljava/lang/StringBuilder;
     312: aload_3
     313: invokeinterface #119,  1          // InterfaceMethod java/util/Map$Entry.getValue:()Ljava/lang/Object;
     318: invokevirtual #81                 // Method java/lang/StringBuilder.append:(Ljava/lang/Object;)Ljava/lang/StringBuilder;
     321: ldc           #108                // String \n
     323: invokevirtual #27                 // Method java/lang/StringBuilder.append:(Ljava/lang/String;)Ljava/lang/StringBuilder;
     326: invokevirtual #28                 // Method java/lang/StringBuilder.toString:()Ljava/lang/String;
     329: invokevirtual #27                 // Method java/lang/StringBuilder.append:(Ljava/lang/String;)Ljava/lang/StringBuilder;
     332: pop
     333: goto          263
     336: aload_1
     337: new           #24                 // class java/lang/StringBuilder
     340: dup
     341: invokespecial #25                 // Method java/lang/StringBuilder."<init>":()V
     344: ldc           #120                // String     Total size of WALs on HDFS:
     346: invokevirtual #27                 // Method java/lang/StringBuilder.append:(Ljava/lang/String;)Ljava/lang/StringBuilder;
     349: aload_0
     350: getfield      #9                  // Field totalSizeOfWALs:J
     353: l2d
     354: invokestatic  #121                // Method org/apache/hadoop/hbase/procedure2/util/StringUtils.humanSize:(D)Ljava/lang/String;
     357: invokevirtual #27                 // Method java/lang/StringBuilder.append:(Ljava/lang/String;)Ljava/lang/StringBuilder;
     360: ldc           #108                // String \n
     362: invokevirtual #27                 // Method java/lang/StringBuilder.append:(Ljava/lang/String;)Ljava/lang/StringBuilder;
     365: invokevirtual #28                 // Method java/lang/StringBuilder.toString:()Ljava/lang/String;
     368: invokevirtual #27                 // Method java/lang/StringBuilder.append:(Ljava/lang/String;)Ljava/lang/StringBuilder;
     371: pop
     372: aload_0
     373: getfield      #10                 // Field numWalsNotFound:J
     376: lconst_0
     377: lcmp
     378: ifle          413
     381: aload_1
     382: new           #24                 // class java/lang/StringBuilder
     385: dup
     386: invokespecial #25                 // Method java/lang/StringBuilder."<init>":()V
     389: ldc           #122                // String     ERROR: There are
     391: invokevirtual #27                 // Method java/lang/StringBuilder.append:(Ljava/lang/String;)Ljava/lang/StringBuilder;
     394: aload_0
     395: getfield      #10                 // Field numWalsNotFound:J
     398: invokevirtual #69                 // Method java/lang/StringBuilder.append:(J)Ljava/lang/StringBuilder;
     401: ldc           #123                // String  WALs not found!!!\n
     403: invokevirtual #27                 // Method java/lang/StringBuilder.append:(Ljava/lang/String;)Ljava/lang/StringBuilder;
     406: invokevirtual #28                 // Method java/lang/StringBuilder.toString:()Ljava/lang/String;
     409: invokevirtual #27                 // Method java/lang/StringBuilder.append:(Ljava/lang/String;)Ljava/lang/StringBuilder;
     412: pop
     413: aload_1
     414: invokevirtual #28                 // Method java/lang/StringBuilder.toString:()Ljava/lang/String;
     417: areturn

  public java.lang.String dumpPeersState(java.util.List<org.apache.hadoop.hbase.replication.ReplicationPeerDescription>) throws java.lang.Exception;
    Code:
       0: new           #24                 // class java/lang/StringBuilder
       3: dup
       4: invokespecial #25                 // Method java/lang/StringBuilder."<init>":()V
       7: astore_3
       8: aload_1
       9: invokeinterface #104,  1          // InterfaceMethod java/util/List.iterator:()Ljava/util/Iterator;
      14: astore        4
      16: aload         4
      18: invokeinterface #105,  1          // InterfaceMethod java/util/Iterator.hasNext:()Z
      23: ifeq          301
      26: aload         4
      28: invokeinterface #106,  1          // InterfaceMethod java/util/Iterator.next:()Ljava/lang/Object;
      33: checkcast     #124                // class org/apache/hadoop/hbase/replication/ReplicationPeerDescription
      36: astore        5
      38: aload         5
      40: invokevirtual #125                // Method org/apache/hadoop/hbase/replication/ReplicationPeerDescription.getPeerConfig:()Lorg/apache/hadoop/hbase/replication/ReplicationPeerConfig;
      43: astore        6
      45: aload_3
      46: new           #24                 // class java/lang/StringBuilder
      49: dup
      50: invokespecial #25                 // Method java/lang/StringBuilder."<init>":()V
      53: ldc           #126                // String Peer:
      55: invokevirtual #27                 // Method java/lang/StringBuilder.append:(Ljava/lang/String;)Ljava/lang/StringBuilder;
      58: aload         5
      60: invokevirtual #127                // Method org/apache/hadoop/hbase/replication/ReplicationPeerDescription.getPeerId:()Ljava/lang/String;
      63: invokevirtual #27                 // Method java/lang/StringBuilder.append:(Ljava/lang/String;)Ljava/lang/StringBuilder;
      66: ldc           #108                // String \n
      68: invokevirtual #27                 // Method java/lang/StringBuilder.append:(Ljava/lang/String;)Ljava/lang/StringBuilder;
      71: invokevirtual #28                 // Method java/lang/StringBuilder.toString:()Ljava/lang/String;
      74: invokevirtual #27                 // Method java/lang/StringBuilder.append:(Ljava/lang/String;)Ljava/lang/StringBuilder;
      77: pop
      78: aload_3
      79: new           #24                 // class java/lang/StringBuilder
      82: dup
      83: invokespecial #25                 // Method java/lang/StringBuilder."<init>":()V
      86: ldc           #128                // String     State:
      88: invokevirtual #27                 // Method java/lang/StringBuilder.append:(Ljava/lang/String;)Ljava/lang/StringBuilder;
      91: aload         5
      93: invokevirtual #129                // Method org/apache/hadoop/hbase/replication/ReplicationPeerDescription.isEnabled:()Z
      96: ifeq          104
      99: ldc           #130                // String ENABLED
     101: goto          106
     104: ldc           #131                // String DISABLED
     106: invokevirtual #27                 // Method java/lang/StringBuilder.append:(Ljava/lang/String;)Ljava/lang/StringBuilder;
     109: ldc           #108                // String \n
     111: invokevirtual #27                 // Method java/lang/StringBuilder.append:(Ljava/lang/String;)Ljava/lang/StringBuilder;
     114: invokevirtual #28                 // Method java/lang/StringBuilder.toString:()Ljava/lang/String;
     117: invokevirtual #27                 // Method java/lang/StringBuilder.append:(Ljava/lang/String;)Ljava/lang/StringBuilder;
     120: pop
     121: aload_3
     122: new           #24                 // class java/lang/StringBuilder
     125: dup
     126: invokespecial #25                 // Method java/lang/StringBuilder."<init>":()V
     129: ldc           #132                // String     Cluster Name:
     131: invokevirtual #27                 // Method java/lang/StringBuilder.append:(Ljava/lang/String;)Ljava/lang/StringBuilder;
     134: aload         6
     136: invokevirtual #133                // Method org/apache/hadoop/hbase/replication/ReplicationPeerConfig.getClusterKey:()Ljava/lang/String;
     139: invokevirtual #27                 // Method java/lang/StringBuilder.append:(Ljava/lang/String;)Ljava/lang/StringBuilder;
     142: ldc           #108                // String \n
     144: invokevirtual #27                 // Method java/lang/StringBuilder.append:(Ljava/lang/String;)Ljava/lang/StringBuilder;
     147: invokevirtual #28                 // Method java/lang/StringBuilder.toString:()Ljava/lang/String;
     150: invokevirtual #27                 // Method java/lang/StringBuilder.append:(Ljava/lang/String;)Ljava/lang/StringBuilder;
     153: pop
     154: aload_3
     155: new           #24                 // class java/lang/StringBuilder
     158: dup
     159: invokespecial #25                 // Method java/lang/StringBuilder."<init>":()V
     162: ldc           #134                // String     Replication Endpoint:
     164: invokevirtual #27                 // Method java/lang/StringBuilder.append:(Ljava/lang/String;)Ljava/lang/StringBuilder;
     167: aload         6
     169: invokevirtual #135                // Method org/apache/hadoop/hbase/replication/ReplicationPeerConfig.getReplicationEndpointImpl:()Ljava/lang/String;
     172: invokevirtual #27                 // Method java/lang/StringBuilder.append:(Ljava/lang/String;)Ljava/lang/StringBuilder;
     175: ldc           #108                // String \n
     177: invokevirtual #27                 // Method java/lang/StringBuilder.append:(Ljava/lang/String;)Ljava/lang/StringBuilder;
     180: invokevirtual #28                 // Method java/lang/StringBuilder.toString:()Ljava/lang/String;
     183: invokevirtual #27                 // Method java/lang/StringBuilder.append:(Ljava/lang/String;)Ljava/lang/StringBuilder;
     186: pop
     187: aload         6
     189: invokevirtual #136                // Method org/apache/hadoop/hbase/replication/ReplicationPeerConfig.getConfiguration:()Ljava/util/Map;
     192: astore_2
     193: aload_2
     194: invokeinterface #137,  1          // InterfaceMethod java/util/Map.size:()I
     199: iconst_1
     200: if_icmple     232
     203: aload_3
     204: new           #24                 // class java/lang/StringBuilder
     207: dup
     208: invokespecial #25                 // Method java/lang/StringBuilder."<init>":()V
     211: ldc           #138                // String     Peer Configuration:
     213: invokevirtual #27                 // Method java/lang/StringBuilder.append:(Ljava/lang/String;)Ljava/lang/StringBuilder;
     216: aload_2
     217: invokevirtual #81                 // Method java/lang/StringBuilder.append:(Ljava/lang/Object;)Ljava/lang/StringBuilder;
     220: ldc           #108                // String \n
     222: invokevirtual #27                 // Method java/lang/StringBuilder.append:(Ljava/lang/String;)Ljava/lang/StringBuilder;
     225: invokevirtual #28                 // Method java/lang/StringBuilder.toString:()Ljava/lang/String;
     228: invokevirtual #27                 // Method java/lang/StringBuilder.append:(Ljava/lang/String;)Ljava/lang/StringBuilder;
     231: pop
     232: aload_3
     233: new           #24                 // class java/lang/StringBuilder
     236: dup
     237: invokespecial #25                 // Method java/lang/StringBuilder."<init>":()V
     240: ldc           #139                // String     Peer Table CFs:
     242: invokevirtual #27                 // Method java/lang/StringBuilder.append:(Ljava/lang/String;)Ljava/lang/StringBuilder;
     245: aload         6
     247: invokevirtual #140                // Method org/apache/hadoop/hbase/replication/ReplicationPeerConfig.getTableCFsMap:()Ljava/util/Map;
     250: invokevirtual #81                 // Method java/lang/StringBuilder.append:(Ljava/lang/Object;)Ljava/lang/StringBuilder;
     253: ldc           #108                // String \n
     255: invokevirtual #27                 // Method java/lang/StringBuilder.append:(Ljava/lang/String;)Ljava/lang/StringBuilder;
     258: invokevirtual #28                 // Method java/lang/StringBuilder.toString:()Ljava/lang/String;
     261: invokevirtual #27                 // Method java/lang/StringBuilder.append:(Ljava/lang/String;)Ljava/lang/StringBuilder;
     264: pop
     265: aload_3
     266: new           #24                 // class java/lang/StringBuilder
     269: dup
     270: invokespecial #25                 // Method java/lang/StringBuilder."<init>":()V
     273: ldc           #141                // String     Peer Namespaces:
     275: invokevirtual #27                 // Method java/lang/StringBuilder.append:(Ljava/lang/String;)Ljava/lang/StringBuilder;
     278: aload         6
     280: invokevirtual #142                // Method org/apache/hadoop/hbase/replication/ReplicationPeerConfig.getNamespaces:()Ljava/util/Set;
     283: invokevirtual #81                 // Method java/lang/StringBuilder.append:(Ljava/lang/Object;)Ljava/lang/StringBuilder;
     286: ldc           #108                // String \n
     288: invokevirtual #27                 // Method java/lang/StringBuilder.append:(Ljava/lang/String;)Ljava/lang/StringBuilder;
     291: invokevirtual #28                 // Method java/lang/StringBuilder.toString:()Ljava/lang/String;
     294: invokevirtual #27                 // Method java/lang/StringBuilder.append:(Ljava/lang/String;)Ljava/lang/StringBuilder;
     297: pop
     298: goto          16
     301: aload_3
     302: invokevirtual #28                 // Method java/lang/StringBuilder.toString:()Ljava/lang/String;
     305: areturn

  public java.lang.String dumpQueues(org.apache.hadoop.hbase.zookeeper.ZKWatcher, java.util.Set<java.lang.String>, boolean) throws java.lang.Exception;
    Code:
       0: new           #24                 // class java/lang/StringBuilder
       3: dup
       4: invokespecial #25                 // Method java/lang/StringBuilder."<init>":()V
       7: astore        6
       9: aload_1
      10: aload_0
      11: invokevirtual #61                 // Method getConf:()Lorg/apache/hadoop/conf/Configuration;
      14: invokestatic  #143                // Method org/apache/hadoop/hbase/replication/ReplicationStorageFactory.getReplicationQueueStorage:(Lorg/apache/hadoop/hbase/zookeeper/ZKWatcher;Lorg/apache/hadoop/conf/Configuration;)Lorg/apache/hadoop/hbase/replication/ReplicationQueueStorage;
      17: astore        4
      19: aload_1
      20: new           #70                 // class org/apache/hadoop/hbase/replication/regionserver/DumpReplicationQueues$WarnOnlyAbortable
      23: dup
      24: aconst_null
      25: invokespecial #71                 // Method org/apache/hadoop/hbase/replication/regionserver/DumpReplicationQueues$WarnOnlyAbortable."<init>":(Lorg/apache/hadoop/hbase/replication/regionserver/DumpReplicationQueues$1;)V
      28: new           #144                // class org/apache/hadoop/hbase/replication/regionserver/DumpReplicationQueues$WarnOnlyStoppable
      31: dup
      32: aconst_null
      33: invokespecial #145                // Method org/apache/hadoop/hbase/replication/regionserver/DumpReplicationQueues$WarnOnlyStoppable."<init>":(Lorg/apache/hadoop/hbase/replication/regionserver/DumpReplicationQueues$1;)V
      36: invokestatic  #146                // Method org/apache/hadoop/hbase/replication/ReplicationFactory.getReplicationTracker:(Lorg/apache/hadoop/hbase/zookeeper/ZKWatcher;Lorg/apache/hadoop/hbase/Abortable;Lorg/apache/hadoop/hbase/Stoppable;)Lorg/apache/hadoop/hbase/replication/ReplicationTracker;
      39: astore        5
      41: new           #147                // class java/util/HashSet
      44: dup
      45: aload         5
      47: invokeinterface #148,  1          // InterfaceMethod org/apache/hadoop/hbase/replication/ReplicationTracker.getListOfRegionServers:()Ljava/util/List;
      52: invokespecial #149                // Method java/util/HashSet."<init>":(Ljava/util/Collection;)V
      55: astore        7
      57: aload         4
      59: invokeinterface #150,  1          // InterfaceMethod org/apache/hadoop/hbase/replication/ReplicationQueueStorage.getListOfReplicators:()Ljava/util/List;
      64: astore        8
      66: aload         8
      68: ifnull        81
      71: aload         8
      73: invokeinterface #77,  1           // InterfaceMethod java/util/List.isEmpty:()Z
      78: ifeq          87
      81: aload         6
      83: invokevirtual #28                 // Method java/lang/StringBuilder.toString:()Ljava/lang/String;
      86: areturn
      87: aload         8
      89: invokeinterface #104,  1          // InterfaceMethod java/util/List.iterator:()Ljava/util/Iterator;
      94: astore        9
      96: aload         9
      98: invokeinterface #105,  1          // InterfaceMethod java/util/Iterator.hasNext:()Z
     103: ifeq          321
     106: aload         9
     108: invokeinterface #106,  1          // InterfaceMethod java/util/Iterator.next:()Ljava/lang/Object;
     113: checkcast     #151                // class org/apache/hadoop/hbase/ServerName
     116: astore        10
     118: aload         4
     120: aload         10
     122: invokeinterface #152,  2          // InterfaceMethod org/apache/hadoop/hbase/replication/ReplicationQueueStorage.getAllQueues:(Lorg/apache/hadoop/hbase/ServerName;)Ljava/util/List;
     127: astore        11
     129: aload         7
     131: aload         10
     133: invokevirtual #153                // Method org/apache/hadoop/hbase/ServerName.getServerName:()Ljava/lang/String;
     136: invokeinterface #154,  2          // InterfaceMethod java/util/Set.contains:(Ljava/lang/Object;)Z
     141: ifne          159
     144: aload_0
     145: getfield      #5                  // Field deadRegionServers:Ljava/util/List;
     148: aload         10
     150: invokevirtual #153                // Method org/apache/hadoop/hbase/ServerName.getServerName:()Ljava/lang/String;
     153: invokeinterface #155,  2          // InterfaceMethod java/util/List.add:(Ljava/lang/Object;)Z
     158: pop
     159: aload         11
     161: invokeinterface #104,  1          // InterfaceMethod java/util/List.iterator:()Ljava/util/Iterator;
     166: astore        12
     168: aload         12
     170: invokeinterface #105,  1          // InterfaceMethod java/util/Iterator.hasNext:()Z
     175: ifeq          318
     178: aload         12
     180: invokeinterface #106,  1          // InterfaceMethod java/util/Iterator.next:()Ljava/lang/Object;
     185: checkcast     #14                 // class java/lang/String
     188: astore        13
     190: new           #156                // class org/apache/hadoop/hbase/replication/ReplicationQueueInfo
     193: dup
     194: aload         13
     196: invokespecial #157                // Method org/apache/hadoop/hbase/replication/ReplicationQueueInfo."<init>":(Ljava/lang/String;)V
     199: astore        14
     201: aload         4
     203: aload         10
     205: aload         13
     207: invokeinterface #158,  3          // InterfaceMethod org/apache/hadoop/hbase/replication/ReplicationQueueStorage.getWALsInQueue:(Lorg/apache/hadoop/hbase/ServerName;Ljava/lang/String;)Ljava/util/List;
     212: astore        15
     214: aload         15
     216: invokestatic  #159                // Method java/util/Collections.sort:(Ljava/util/List;)V
     219: aload_2
     220: aload         14
     222: invokevirtual #160                // Method org/apache/hadoop/hbase/replication/ReplicationQueueInfo.getPeerId:()Ljava/lang/String;
     225: invokeinterface #154,  2          // InterfaceMethod java/util/Set.contains:(Ljava/lang/Object;)Z
     230: ifne          293
     233: aload_0
     234: getfield      #6                  // Field deletedQueues:Ljava/util/List;
     237: new           #24                 // class java/lang/StringBuilder
     240: dup
     241: invokespecial #25                 // Method java/lang/StringBuilder."<init>":()V
     244: aload         10
     246: invokevirtual #81                 // Method java/lang/StringBuilder.append:(Ljava/lang/Object;)Ljava/lang/StringBuilder;
     249: ldc           #161                // String /
     251: invokevirtual #27                 // Method java/lang/StringBuilder.append:(Ljava/lang/String;)Ljava/lang/StringBuilder;
     254: aload         13
     256: invokevirtual #27                 // Method java/lang/StringBuilder.append:(Ljava/lang/String;)Ljava/lang/StringBuilder;
     259: invokevirtual #28                 // Method java/lang/StringBuilder.toString:()Ljava/lang/String;
     262: invokeinterface #155,  2          // InterfaceMethod java/util/List.add:(Ljava/lang/Object;)Z
     267: pop
     268: aload         6
     270: aload_0
     271: aload         10
     273: aload         4
     275: aload         14
     277: aload         13
     279: aload         15
     281: iconst_1
     282: iload_3
     283: invokespecial #162                // Method formatQueue:(Lorg/apache/hadoop/hbase/ServerName;Lorg/apache/hadoop/hbase/replication/ReplicationQueueStorage;Lorg/apache/hadoop/hbase/replication/ReplicationQueueInfo;Ljava/lang/String;Ljava/util/List;ZZ)Ljava/lang/String;
     286: invokevirtual #27                 // Method java/lang/StringBuilder.append:(Ljava/lang/String;)Ljava/lang/StringBuilder;
     289: pop
     290: goto          315
     293: aload         6
     295: aload_0
     296: aload         10
     298: aload         4
     300: aload         14
     302: aload         13
     304: aload         15
     306: iconst_0
     307: iload_3
     308: invokespecial #162                // Method formatQueue:(Lorg/apache/hadoop/hbase/ServerName;Lorg/apache/hadoop/hbase/replication/ReplicationQueueStorage;Lorg/apache/hadoop/hbase/replication/ReplicationQueueInfo;Ljava/lang/String;Ljava/util/List;ZZ)Ljava/lang/String;
     311: invokevirtual #27                 // Method java/lang/StringBuilder.append:(Ljava/lang/String;)Ljava/lang/StringBuilder;
     314: pop
     315: goto          168
     318: goto          96
     321: aload         6
     323: invokevirtual #28                 // Method java/lang/StringBuilder.toString:()Ljava/lang/String;
     326: areturn

  static org.slf4j.Logger access$200();
    Code:
       0: getstatic     #1                  // Field LOG:Lorg/slf4j/Logger;
       3: areturn

  static {};
    Code:
       0: ldc           #34                 // class org/apache/hadoop/hbase/replication/regionserver/DumpReplicationQueues
       2: invokevirtual #47                 // Method java/lang/Class.getName:()Ljava/lang/String;
       5: invokestatic  #194                // Method org/slf4j/LoggerFactory.getLogger:(Ljava/lang/String;)Lorg/slf4j/Logger;
       8: putstatic     #1                  // Field LOG:Lorg/slf4j/Logger;
      11: return
}
