Compiled from "Durability.java"
public final class org.apache.hadoop.hbase.client.Durability extends java.lang.Enum<org.apache.hadoop.hbase.client.Durability> {
  public static final org.apache.hadoop.hbase.client.Durability USE_DEFAULT;

  public static final org.apache.hadoop.hbase.client.Durability SKIP_WAL;

  public static final org.apache.hadoop.hbase.client.Durability ASYNC_WAL;

  public static final org.apache.hadoop.hbase.client.Durability SYNC_WAL;

  public static final org.apache.hadoop.hbase.client.Durability FSYNC_WAL;

  public static org.apache.hadoop.hbase.client.Durability[] values();
    Code:
       0: getstatic     #1                  // Field $VALUES:[Lorg/apache/hadoop/hbase/client/Durability;
       3: invokevirtual #2                  // Method "[Lorg/apache/hadoop/hbase/client/Durability;".clone:()Ljava/lang/Object;
       6: checkcast     #3                  // class "[Lorg/apache/hadoop/hbase/client/Durability;"
       9: areturn

  public static org.apache.hadoop.hbase.client.Durability valueOf(java.lang.String);
    Code:
       0: ldc           #4                  // class org/apache/hadoop/hbase/client/Durability
       2: aload_0
       3: invokestatic  #5                  // Method java/lang/Enum.valueOf:(Ljava/lang/Class;Ljava/lang/String;)Ljava/lang/Enum;
       6: checkcast     #4                  // class org/apache/hadoop/hbase/client/Durability
       9: areturn

  static {};
    Code:
       0: new           #4                  // class org/apache/hadoop/hbase/client/Durability
       3: dup
       4: ldc           #7                  // String USE_DEFAULT
       6: iconst_0
       7: invokespecial #8                  // Method "<init>":(Ljava/lang/String;I)V
      10: putstatic     #9                  // Field USE_DEFAULT:Lorg/apache/hadoop/hbase/client/Durability;
      13: new           #4                  // class org/apache/hadoop/hbase/client/Durability
      16: dup
      17: ldc           #10                 // String SKIP_WAL
      19: iconst_1
      20: invokespecial #8                  // Method "<init>":(Ljava/lang/String;I)V
      23: putstatic     #11                 // Field SKIP_WAL:Lorg/apache/hadoop/hbase/client/Durability;
      26: new           #4                  // class org/apache/hadoop/hbase/client/Durability
      29: dup
      30: ldc           #12                 // String ASYNC_WAL
      32: iconst_2
      33: invokespecial #8                  // Method "<init>":(Ljava/lang/String;I)V
      36: putstatic     #13                 // Field ASYNC_WAL:Lorg/apache/hadoop/hbase/client/Durability;
      39: new           #4                  // class org/apache/hadoop/hbase/client/Durability
      42: dup
      43: ldc           #14                 // String SYNC_WAL
      45: iconst_3
      46: invokespecial #8                  // Method "<init>":(Ljava/lang/String;I)V
      49: putstatic     #15                 // Field SYNC_WAL:Lorg/apache/hadoop/hbase/client/Durability;
      52: new           #4                  // class org/apache/hadoop/hbase/client/Durability
      55: dup
      56: ldc           #16                 // String FSYNC_WAL
      58: iconst_4
      59: invokespecial #8                  // Method "<init>":(Ljava/lang/String;I)V
      62: putstatic     #17                 // Field FSYNC_WAL:Lorg/apache/hadoop/hbase/client/Durability;
      65: iconst_5
      66: anewarray     #4                  // class org/apache/hadoop/hbase/client/Durability
      69: dup
      70: iconst_0
      71: getstatic     #9                  // Field USE_DEFAULT:Lorg/apache/hadoop/hbase/client/Durability;
      74: aastore
      75: dup
      76: iconst_1
      77: getstatic     #11                 // Field SKIP_WAL:Lorg/apache/hadoop/hbase/client/Durability;
      80: aastore
      81: dup
      82: iconst_2
      83: getstatic     #13                 // Field ASYNC_WAL:Lorg/apache/hadoop/hbase/client/Durability;
      86: aastore
      87: dup
      88: iconst_3
      89: getstatic     #15                 // Field SYNC_WAL:Lorg/apache/hadoop/hbase/client/Durability;
      92: aastore
      93: dup
      94: iconst_4
      95: getstatic     #17                 // Field FSYNC_WAL:Lorg/apache/hadoop/hbase/client/Durability;
      98: aastore
      99: putstatic     #1                  // Field $VALUES:[Lorg/apache/hadoop/hbase/client/Durability;
     102: return
}
