Compiled from "DynamicMetricsRegistry.java"
public class org.apache.hadoop.metrics2.lib.DynamicMetricsRegistry {
  public org.apache.hadoop.metrics2.lib.DynamicMetricsRegistry(java.lang.String);
    Code:
       0: aload_0
       1: aload_1
       2: aload_1
       3: invokestatic  #1                  // Method org/apache/hadoop/hbase/metrics/Interns.info:(Ljava/lang/String;Ljava/lang/String;)Lorg/apache/hadoop/metrics2/MetricsInfo;
       6: invokespecial #2                  // Method "<init>":(Lorg/apache/hadoop/metrics2/MetricsInfo;)V
       9: return

  public org.apache.hadoop.metrics2.lib.DynamicMetricsRegistry(org.apache.hadoop.metrics2.MetricsInfo);
    Code:
       0: aload_0
       1: invokespecial #3                  // Method java/lang/Object."<init>":()V
       4: aload_0
       5: invokestatic  #4                  // Method org/apache/hbase/thirdparty/com/google/common/collect/Maps.newConcurrentMap:()Ljava/util/concurrent/ConcurrentMap;
       8: putfield      #5                  // Field metricsMap:Ljava/util/concurrent/ConcurrentMap;
      11: aload_0
      12: invokestatic  #4                  // Method org/apache/hbase/thirdparty/com/google/common/collect/Maps.newConcurrentMap:()Ljava/util/concurrent/ConcurrentMap;
      15: putfield      #6                  // Field tagsMap:Ljava/util/concurrent/ConcurrentMap;
      18: aload_0
      19: new           #7                  // class org/apache/hadoop/metrics2/lib/DefaultMetricsSystemHelper
      22: dup
      23: invokespecial #8                  // Method org/apache/hadoop/metrics2/lib/DefaultMetricsSystemHelper."<init>":()V
      26: putfield      #9                  // Field helper:Lorg/apache/hadoop/metrics2/lib/DefaultMetricsSystemHelper;
      29: aload_0
      30: aload_1
      31: putfield      #10                 // Field metricsInfo:Lorg/apache/hadoop/metrics2/MetricsInfo;
      34: return

  public org.apache.hadoop.metrics2.MetricsInfo info();
    Code:
       0: aload_0
       1: getfield      #10                 // Field metricsInfo:Lorg/apache/hadoop/metrics2/MetricsInfo;
       4: areturn

  public org.apache.hadoop.metrics2.lib.MutableMetric get(java.lang.String);
    Code:
       0: aload_0
       1: getfield      #5                  // Field metricsMap:Ljava/util/concurrent/ConcurrentMap;
       4: aload_1
       5: invokeinterface #11,  2           // InterfaceMethod java/util/concurrent/ConcurrentMap.get:(Ljava/lang/Object;)Ljava/lang/Object;
      10: checkcast     #12                 // class org/apache/hadoop/metrics2/lib/MutableMetric
      13: areturn

  public org.apache.hadoop.metrics2.MetricsTag getTag(java.lang.String);
    Code:
       0: aload_0
       1: getfield      #6                  // Field tagsMap:Ljava/util/concurrent/ConcurrentMap;
       4: aload_1
       5: invokeinterface #11,  2           // InterfaceMethod java/util/concurrent/ConcurrentMap.get:(Ljava/lang/Object;)Ljava/lang/Object;
      10: checkcast     #13                 // class org/apache/hadoop/metrics2/MetricsTag
      13: areturn

  public org.apache.hadoop.metrics2.lib.MutableFastCounter newCounter(java.lang.String, java.lang.String, long);
    Code:
       0: aload_0
       1: new           #14                 // class org/apache/hadoop/metrics2/lib/MetricsInfoImpl
       4: dup
       5: aload_1
       6: aload_2
       7: invokespecial #15                 // Method org/apache/hadoop/metrics2/lib/MetricsInfoImpl."<init>":(Ljava/lang/String;Ljava/lang/String;)V
      10: lload_3
      11: invokevirtual #16                 // Method newCounter:(Lorg/apache/hadoop/metrics2/MetricsInfo;J)Lorg/apache/hadoop/metrics2/lib/MutableFastCounter;
      14: areturn

  public org.apache.hadoop.metrics2.lib.MutableFastCounter newCounter(org.apache.hadoop.metrics2.MetricsInfo, long);
    Code:
       0: new           #17                 // class org/apache/hadoop/metrics2/lib/MutableFastCounter
       3: dup
       4: aload_1
       5: lload_2
       6: invokespecial #18                 // Method org/apache/hadoop/metrics2/lib/MutableFastCounter."<init>":(Lorg/apache/hadoop/metrics2/MetricsInfo;J)V
       9: astore        4
      11: aload_0
      12: aload_1
      13: invokeinterface #19,  1           // InterfaceMethod org/apache/hadoop/metrics2/MetricsInfo.name:()Ljava/lang/String;
      18: aload         4
      20: ldc           #17                 // class org/apache/hadoop/metrics2/lib/MutableFastCounter
      22: invokespecial #20                 // Method addNewMetricIfAbsent:(Ljava/lang/String;Lorg/apache/hadoop/metrics2/lib/MutableMetric;Ljava/lang/Class;)Lorg/apache/hadoop/metrics2/lib/MutableMetric;
      25: checkcast     #17                 // class org/apache/hadoop/metrics2/lib/MutableFastCounter
      28: areturn

  public org.apache.hadoop.metrics2.lib.MutableGaugeLong newGauge(java.lang.String, java.lang.String, long);
    Code:
       0: aload_0
       1: new           #14                 // class org/apache/hadoop/metrics2/lib/MetricsInfoImpl
       4: dup
       5: aload_1
       6: aload_2
       7: invokespecial #15                 // Method org/apache/hadoop/metrics2/lib/MetricsInfoImpl."<init>":(Ljava/lang/String;Ljava/lang/String;)V
      10: lload_3
      11: invokevirtual #21                 // Method newGauge:(Lorg/apache/hadoop/metrics2/MetricsInfo;J)Lorg/apache/hadoop/metrics2/lib/MutableGaugeLong;
      14: areturn

  public org.apache.hadoop.metrics2.lib.MutableGaugeLong newGauge(org.apache.hadoop.metrics2.MetricsInfo, long);
    Code:
       0: new           #22                 // class org/apache/hadoop/metrics2/lib/MutableGaugeLong
       3: dup
       4: aload_1
       5: lload_2
       6: invokespecial #23                 // Method org/apache/hadoop/metrics2/lib/MutableGaugeLong."<init>":(Lorg/apache/hadoop/metrics2/MetricsInfo;J)V
       9: astore        4
      11: aload_0
      12: aload_1
      13: invokeinterface #19,  1           // InterfaceMethod org/apache/hadoop/metrics2/MetricsInfo.name:()Ljava/lang/String;
      18: aload         4
      20: ldc           #22                 // class org/apache/hadoop/metrics2/lib/MutableGaugeLong
      22: invokespecial #20                 // Method addNewMetricIfAbsent:(Ljava/lang/String;Lorg/apache/hadoop/metrics2/lib/MutableMetric;Ljava/lang/Class;)Lorg/apache/hadoop/metrics2/lib/MutableMetric;
      25: checkcast     #22                 // class org/apache/hadoop/metrics2/lib/MutableGaugeLong
      28: areturn

  public org.apache.hadoop.metrics2.lib.MutableStat newStat(java.lang.String, java.lang.String, java.lang.String, java.lang.String, boolean);
    Code:
       0: new           #24                 // class org/apache/hadoop/metrics2/lib/MutableStat
       3: dup
       4: aload_1
       5: aload_2
       6: aload_3
       7: aload         4
       9: iload         5
      11: invokespecial #25                 // Method org/apache/hadoop/metrics2/lib/MutableStat."<init>":(Ljava/lang/String;Ljava/lang/String;Ljava/lang/String;Ljava/lang/String;Z)V
      14: astore        6
      16: aload_0
      17: aload_1
      18: aload         6
      20: ldc           #24                 // class org/apache/hadoop/metrics2/lib/MutableStat
      22: invokespecial #20                 // Method addNewMetricIfAbsent:(Ljava/lang/String;Lorg/apache/hadoop/metrics2/lib/MutableMetric;Ljava/lang/Class;)Lorg/apache/hadoop/metrics2/lib/MutableMetric;
      25: checkcast     #24                 // class org/apache/hadoop/metrics2/lib/MutableStat
      28: areturn

  public org.apache.hadoop.metrics2.lib.MutableStat newStat(java.lang.String, java.lang.String, java.lang.String, java.lang.String);
    Code:
       0: aload_0
       1: aload_1
       2: aload_2
       3: aload_3
       4: aload         4
       6: iconst_0
       7: invokevirtual #26                 // Method newStat:(Ljava/lang/String;Ljava/lang/String;Ljava/lang/String;Ljava/lang/String;Z)Lorg/apache/hadoop/metrics2/lib/MutableStat;
      10: areturn

  public org.apache.hadoop.metrics2.lib.MutableRate newRate(java.lang.String);
    Code:
       0: aload_0
       1: aload_1
       2: aload_1
       3: iconst_0
       4: invokevirtual #27                 // Method newRate:(Ljava/lang/String;Ljava/lang/String;Z)Lorg/apache/hadoop/metrics2/lib/MutableRate;
       7: areturn

  public org.apache.hadoop.metrics2.lib.MutableRate newRate(java.lang.String, java.lang.String);
    Code:
       0: aload_0
       1: aload_1
       2: aload_2
       3: iconst_0
       4: invokevirtual #27                 // Method newRate:(Ljava/lang/String;Ljava/lang/String;Z)Lorg/apache/hadoop/metrics2/lib/MutableRate;
       7: areturn

  public org.apache.hadoop.metrics2.lib.MutableRate newRate(java.lang.String, java.lang.String, boolean);
    Code:
       0: aload_0
       1: aload_1
       2: aload_2
       3: iload_3
       4: iconst_1
       5: invokevirtual #28                 // Method newRate:(Ljava/lang/String;Ljava/lang/String;ZZ)Lorg/apache/hadoop/metrics2/lib/MutableRate;
       8: areturn

  public org.apache.hadoop.metrics2.lib.MutableRate newRate(java.lang.String, java.lang.String, boolean, boolean);
    Code:
       0: iload         4
       2: ifeq          79
       5: aload_0
       6: getfield      #5                  // Field metricsMap:Ljava/util/concurrent/ConcurrentMap;
       9: aload_1
      10: invokeinterface #11,  2           // InterfaceMethod java/util/concurrent/ConcurrentMap.get:(Ljava/lang/Object;)Ljava/lang/Object;
      15: checkcast     #12                 // class org/apache/hadoop/metrics2/lib/MutableMetric
      18: astore        5
      20: aload         5
      22: ifnull        79
      25: aload         5
      27: instanceof    #29                 // class org/apache/hadoop/metrics2/lib/MutableRate
      30: ifeq          39
      33: aload         5
      35: checkcast     #29                 // class org/apache/hadoop/metrics2/lib/MutableRate
      38: areturn
      39: new           #30                 // class org/apache/hadoop/metrics2/MetricsException
      42: dup
      43: new           #31                 // class java/lang/StringBuilder
      46: dup
      47: invokespecial #32                 // Method java/lang/StringBuilder."<init>":()V
      50: ldc           #33                 // String Unexpected metrics type
      52: invokevirtual #34                 // Method java/lang/StringBuilder.append:(Ljava/lang/String;)Ljava/lang/StringBuilder;
      55: aload         5
      57: invokevirtual #35                 // Method java/lang/Object.getClass:()Ljava/lang/Class;
      60: invokevirtual #36                 // Method java/lang/StringBuilder.append:(Ljava/lang/Object;)Ljava/lang/StringBuilder;
      63: ldc           #37                 // String  for
      65: invokevirtual #34                 // Method java/lang/StringBuilder.append:(Ljava/lang/String;)Ljava/lang/StringBuilder;
      68: aload_1
      69: invokevirtual #34                 // Method java/lang/StringBuilder.append:(Ljava/lang/String;)Ljava/lang/StringBuilder;
      72: invokevirtual #38                 // Method java/lang/StringBuilder.toString:()Ljava/lang/String;
      75: invokespecial #39                 // Method org/apache/hadoop/metrics2/MetricsException."<init>":(Ljava/lang/String;)V
      78: athrow
      79: new           #29                 // class org/apache/hadoop/metrics2/lib/MutableRate
      82: dup
      83: aload_1
      84: aload_2
      85: iload_3
      86: invokespecial #40                 // Method org/apache/hadoop/metrics2/lib/MutableRate."<init>":(Ljava/lang/String;Ljava/lang/String;Z)V
      89: astore        5
      91: aload_0
      92: aload_1
      93: aload         5
      95: ldc           #29                 // class org/apache/hadoop/metrics2/lib/MutableRate
      97: invokespecial #20                 // Method addNewMetricIfAbsent:(Ljava/lang/String;Lorg/apache/hadoop/metrics2/lib/MutableMetric;Ljava/lang/Class;)Lorg/apache/hadoop/metrics2/lib/MutableMetric;
     100: checkcast     #29                 // class org/apache/hadoop/metrics2/lib/MutableRate
     103: areturn

  public org.apache.hadoop.metrics2.lib.MutableHistogram newHistogram(java.lang.String);
    Code:
       0: aload_0
       1: aload_1
       2: ldc           #41                 // String
       4: invokevirtual #42                 // Method newHistogram:(Ljava/lang/String;Ljava/lang/String;)Lorg/apache/hadoop/metrics2/lib/MutableHistogram;
       7: areturn

  public org.apache.hadoop.metrics2.lib.MutableHistogram newHistogram(java.lang.String, java.lang.String);
    Code:
       0: new           #43                 // class org/apache/hadoop/metrics2/lib/MutableHistogram
       3: dup
       4: aload_1
       5: aload_2
       6: invokespecial #44                 // Method org/apache/hadoop/metrics2/lib/MutableHistogram."<init>":(Ljava/lang/String;Ljava/lang/String;)V
       9: astore_3
      10: aload_0
      11: aload_1
      12: aload_3
      13: ldc           #43                 // class org/apache/hadoop/metrics2/lib/MutableHistogram
      15: invokespecial #20                 // Method addNewMetricIfAbsent:(Ljava/lang/String;Lorg/apache/hadoop/metrics2/lib/MutableMetric;Ljava/lang/Class;)Lorg/apache/hadoop/metrics2/lib/MutableMetric;
      18: checkcast     #43                 // class org/apache/hadoop/metrics2/lib/MutableHistogram
      21: areturn

  public org.apache.hadoop.metrics2.lib.MutableTimeHistogram newTimeHistogram(java.lang.String);
    Code:
       0: aload_0
       1: aload_1
       2: ldc           #41                 // String
       4: invokevirtual #45                 // Method newTimeHistogram:(Ljava/lang/String;Ljava/lang/String;)Lorg/apache/hadoop/metrics2/lib/MutableTimeHistogram;
       7: areturn

  public org.apache.hadoop.metrics2.lib.MutableTimeHistogram newTimeHistogram(java.lang.String, java.lang.String);
    Code:
       0: new           #46                 // class org/apache/hadoop/metrics2/lib/MutableTimeHistogram
       3: dup
       4: aload_1
       5: aload_2
       6: invokespecial #47                 // Method org/apache/hadoop/metrics2/lib/MutableTimeHistogram."<init>":(Ljava/lang/String;Ljava/lang/String;)V
       9: astore_3
      10: aload_0
      11: aload_1
      12: aload_3
      13: ldc           #46                 // class org/apache/hadoop/metrics2/lib/MutableTimeHistogram
      15: invokespecial #20                 // Method addNewMetricIfAbsent:(Ljava/lang/String;Lorg/apache/hadoop/metrics2/lib/MutableMetric;Ljava/lang/Class;)Lorg/apache/hadoop/metrics2/lib/MutableMetric;
      18: checkcast     #46                 // class org/apache/hadoop/metrics2/lib/MutableTimeHistogram
      21: areturn

  public org.apache.hadoop.metrics2.lib.MutableSizeHistogram newSizeHistogram(java.lang.String);
    Code:
       0: aload_0
       1: aload_1
       2: ldc           #41                 // String
       4: invokevirtual #48                 // Method newSizeHistogram:(Ljava/lang/String;Ljava/lang/String;)Lorg/apache/hadoop/metrics2/lib/MutableSizeHistogram;
       7: areturn

  public org.apache.hadoop.metrics2.lib.MutableSizeHistogram newSizeHistogram(java.lang.String, java.lang.String);
    Code:
       0: new           #49                 // class org/apache/hadoop/metrics2/lib/MutableSizeHistogram
       3: dup
       4: aload_1
       5: aload_2
       6: invokespecial #50                 // Method org/apache/hadoop/metrics2/lib/MutableSizeHistogram."<init>":(Ljava/lang/String;Ljava/lang/String;)V
       9: astore_3
      10: aload_0
      11: aload_1
      12: aload_3
      13: ldc           #49                 // class org/apache/hadoop/metrics2/lib/MutableSizeHistogram
      15: invokespecial #20                 // Method addNewMetricIfAbsent:(Ljava/lang/String;Lorg/apache/hadoop/metrics2/lib/MutableMetric;Ljava/lang/Class;)Lorg/apache/hadoop/metrics2/lib/MutableMetric;
      18: checkcast     #49                 // class org/apache/hadoop/metrics2/lib/MutableSizeHistogram
      21: areturn

  synchronized void add(java.lang.String, org.apache.hadoop.metrics2.lib.MutableMetric);
    Code:
       0: aload_0
       1: aload_1
       2: aload_2
       3: ldc           #12                 // class org/apache/hadoop/metrics2/lib/MutableMetric
       5: invokespecial #20                 // Method addNewMetricIfAbsent:(Ljava/lang/String;Lorg/apache/hadoop/metrics2/lib/MutableMetric;Ljava/lang/Class;)Lorg/apache/hadoop/metrics2/lib/MutableMetric;
       8: pop
       9: return

  public void add(java.lang.String, long);
    Code:
       0: aload_0
       1: getfield      #5                  // Field metricsMap:Ljava/util/concurrent/ConcurrentMap;
       4: aload_1
       5: invokeinterface #11,  2           // InterfaceMethod java/util/concurrent/ConcurrentMap.get:(Ljava/lang/Object;)Ljava/lang/Object;
      10: checkcast     #12                 // class org/apache/hadoop/metrics2/lib/MutableMetric
      13: astore        4
      15: aload         4
      17: ifnull        67
      20: aload         4
      22: instanceof    #24                 // class org/apache/hadoop/metrics2/lib/MutableStat
      25: ifeq          40
      28: aload         4
      30: checkcast     #24                 // class org/apache/hadoop/metrics2/lib/MutableStat
      33: lload_2
      34: invokevirtual #51                 // Method org/apache/hadoop/metrics2/lib/MutableStat.add:(J)V
      37: goto          89
      40: new           #30                 // class org/apache/hadoop/metrics2/MetricsException
      43: dup
      44: new           #31                 // class java/lang/StringBuilder
      47: dup
      48: invokespecial #32                 // Method java/lang/StringBuilder."<init>":()V
      51: ldc           #52                 // String Unsupported add(value) for metric
      53: invokevirtual #34                 // Method java/lang/StringBuilder.append:(Ljava/lang/String;)Ljava/lang/StringBuilder;
      56: aload_1
      57: invokevirtual #34                 // Method java/lang/StringBuilder.append:(Ljava/lang/String;)Ljava/lang/StringBuilder;
      60: invokevirtual #38                 // Method java/lang/StringBuilder.toString:()Ljava/lang/String;
      63: invokespecial #39                 // Method org/apache/hadoop/metrics2/MetricsException."<init>":(Ljava/lang/String;)V
      66: athrow
      67: aload_0
      68: getfield      #5                  // Field metricsMap:Ljava/util/concurrent/ConcurrentMap;
      71: aload_1
      72: aload_0
      73: aload_1
      74: invokevirtual #53                 // Method newRate:(Ljava/lang/String;)Lorg/apache/hadoop/metrics2/lib/MutableRate;
      77: invokeinterface #54,  3           // InterfaceMethod java/util/concurrent/ConcurrentMap.put:(Ljava/lang/Object;Ljava/lang/Object;)Ljava/lang/Object;
      82: pop
      83: aload_0
      84: aload_1
      85: lload_2
      86: invokevirtual #55                 // Method add:(Ljava/lang/String;J)V
      89: return

  public org.apache.hadoop.metrics2.lib.DynamicMetricsRegistry setContext(java.lang.String);
    Code:
       0: aload_0
       1: getstatic     #56                 // Field org/apache/hadoop/metrics2/impl/MsInfo.Context:Lorg/apache/hadoop/metrics2/impl/MsInfo;
       4: aload_1
       5: iconst_1
       6: invokevirtual #57                 // Method tag:(Lorg/apache/hadoop/metrics2/MetricsInfo;Ljava/lang/String;Z)Lorg/apache/hadoop/metrics2/lib/DynamicMetricsRegistry;
       9: areturn

  public org.apache.hadoop.metrics2.lib.DynamicMetricsRegistry tag(java.lang.String, java.lang.String, java.lang.String);
    Code:
       0: aload_0
       1: aload_1
       2: aload_2
       3: aload_3
       4: iconst_0
       5: invokevirtual #58                 // Method tag:(Ljava/lang/String;Ljava/lang/String;Ljava/lang/String;Z)Lorg/apache/hadoop/metrics2/lib/DynamicMetricsRegistry;
       8: areturn

  public org.apache.hadoop.metrics2.lib.DynamicMetricsRegistry tag(java.lang.String, java.lang.String, java.lang.String, boolean);
    Code:
       0: aload_0
       1: new           #14                 // class org/apache/hadoop/metrics2/lib/MetricsInfoImpl
       4: dup
       5: aload_1
       6: aload_2
       7: invokespecial #15                 // Method org/apache/hadoop/metrics2/lib/MetricsInfoImpl."<init>":(Ljava/lang/String;Ljava/lang/String;)V
      10: aload_3
      11: iload         4
      13: invokevirtual #57                 // Method tag:(Lorg/apache/hadoop/metrics2/MetricsInfo;Ljava/lang/String;Z)Lorg/apache/hadoop/metrics2/lib/DynamicMetricsRegistry;
      16: areturn

  public org.apache.hadoop.metrics2.lib.DynamicMetricsRegistry tag(org.apache.hadoop.metrics2.MetricsInfo, java.lang.String, boolean);
    Code:
       0: aload_1
       1: aload_2
       2: invokestatic  #59                 // Method org/apache/hadoop/hbase/metrics/Interns.tag:(Lorg/apache/hadoop/metrics2/MetricsInfo;Ljava/lang/String;)Lorg/apache/hadoop/metrics2/MetricsTag;
       5: astore        4
       7: iload_3
       8: ifne          77
      11: aload_0
      12: getfield      #6                  // Field tagsMap:Ljava/util/concurrent/ConcurrentMap;
      15: aload_1
      16: invokeinterface #19,  1           // InterfaceMethod org/apache/hadoop/metrics2/MetricsInfo.name:()Ljava/lang/String;
      21: aload         4
      23: invokeinterface #60,  3           // InterfaceMethod java/util/concurrent/ConcurrentMap.putIfAbsent:(Ljava/lang/Object;Ljava/lang/Object;)Ljava/lang/Object;
      28: checkcast     #13                 // class org/apache/hadoop/metrics2/MetricsTag
      31: astore        5
      33: aload         5
      35: ifnull        75
      38: new           #30                 // class org/apache/hadoop/metrics2/MetricsException
      41: dup
      42: new           #31                 // class java/lang/StringBuilder
      45: dup
      46: invokespecial #32                 // Method java/lang/StringBuilder."<init>":()V
      49: ldc           #61                 // String Tag
      51: invokevirtual #34                 // Method java/lang/StringBuilder.append:(Ljava/lang/String;)Ljava/lang/StringBuilder;
      54: aload_1
      55: invokeinterface #19,  1           // InterfaceMethod org/apache/hadoop/metrics2/MetricsInfo.name:()Ljava/lang/String;
      60: invokevirtual #34                 // Method java/lang/StringBuilder.append:(Ljava/lang/String;)Ljava/lang/StringBuilder;
      63: ldc           #62                 // String  already exists!
      65: invokevirtual #34                 // Method java/lang/StringBuilder.append:(Ljava/lang/String;)Ljava/lang/StringBuilder;
      68: invokevirtual #38                 // Method java/lang/StringBuilder.toString:()Ljava/lang/String;
      71: invokespecial #39                 // Method org/apache/hadoop/metrics2/MetricsException."<init>":(Ljava/lang/String;)V
      74: athrow
      75: aload_0
      76: areturn
      77: aload_0
      78: getfield      #6                  // Field tagsMap:Ljava/util/concurrent/ConcurrentMap;
      81: aload_1
      82: invokeinterface #19,  1           // InterfaceMethod org/apache/hadoop/metrics2/MetricsInfo.name:()Ljava/lang/String;
      87: aload         4
      89: invokeinterface #54,  3           // InterfaceMethod java/util/concurrent/ConcurrentMap.put:(Ljava/lang/Object;Ljava/lang/Object;)Ljava/lang/Object;
      94: pop
      95: aload_0
      96: areturn

  public org.apache.hadoop.metrics2.lib.DynamicMetricsRegistry tag(org.apache.hadoop.metrics2.MetricsInfo, java.lang.String);
    Code:
       0: aload_0
       1: aload_1
       2: aload_2
       3: iconst_0
       4: invokevirtual #57                 // Method tag:(Lorg/apache/hadoop/metrics2/MetricsInfo;Ljava/lang/String;Z)Lorg/apache/hadoop/metrics2/lib/DynamicMetricsRegistry;
       7: areturn

  java.util.Collection<org.apache.hadoop.metrics2.MetricsTag> tags();
    Code:
       0: aload_0
       1: getfield      #6                  // Field tagsMap:Ljava/util/concurrent/ConcurrentMap;
       4: invokeinterface #63,  1           // InterfaceMethod java/util/concurrent/ConcurrentMap.values:()Ljava/util/Collection;
       9: areturn

  java.util.Collection<org.apache.hadoop.metrics2.lib.MutableMetric> metrics();
    Code:
       0: aload_0
       1: getfield      #5                  // Field metricsMap:Ljava/util/concurrent/ConcurrentMap;
       4: invokeinterface #63,  1           // InterfaceMethod java/util/concurrent/ConcurrentMap.values:()Ljava/util/Collection;
       9: areturn

  public void snapshot(org.apache.hadoop.metrics2.MetricsRecordBuilder, boolean);
    Code:
       0: aload_0
       1: invokevirtual #64                 // Method tags:()Ljava/util/Collection;
       4: invokeinterface #65,  1           // InterfaceMethod java/util/Collection.iterator:()Ljava/util/Iterator;
       9: astore_3
      10: aload_3
      11: invokeinterface #66,  1           // InterfaceMethod java/util/Iterator.hasNext:()Z
      16: ifeq          40
      19: aload_3
      20: invokeinterface #67,  1           // InterfaceMethod java/util/Iterator.next:()Ljava/lang/Object;
      25: checkcast     #13                 // class org/apache/hadoop/metrics2/MetricsTag
      28: astore        4
      30: aload_1
      31: aload         4
      33: invokevirtual #68                 // Method org/apache/hadoop/metrics2/MetricsRecordBuilder.add:(Lorg/apache/hadoop/metrics2/MetricsTag;)Lorg/apache/hadoop/metrics2/MetricsRecordBuilder;
      36: pop
      37: goto          10
      40: aload_0
      41: invokevirtual #69                 // Method metrics:()Ljava/util/Collection;
      44: invokeinterface #65,  1           // InterfaceMethod java/util/Collection.iterator:()Ljava/util/Iterator;
      49: astore_3
      50: aload_3
      51: invokeinterface #66,  1           // InterfaceMethod java/util/Iterator.hasNext:()Z
      56: ifeq          80
      59: aload_3
      60: invokeinterface #67,  1           // InterfaceMethod java/util/Iterator.next:()Ljava/lang/Object;
      65: checkcast     #12                 // class org/apache/hadoop/metrics2/lib/MutableMetric
      68: astore        4
      70: aload         4
      72: aload_1
      73: iload_2
      74: invokevirtual #70                 // Method org/apache/hadoop/metrics2/lib/MutableMetric.snapshot:(Lorg/apache/hadoop/metrics2/MetricsRecordBuilder;Z)V
      77: goto          50
      80: return

  public java.lang.String toString();
    Code:
       0: aload_0
       1: invokestatic  #71                 // Method org/apache/hbase/thirdparty/com/google/common/base/MoreObjects.toStringHelper:(Ljava/lang/Object;)Lorg/apache/hbase/thirdparty/com/google/common/base/MoreObjects$ToStringHelper;
       4: ldc           #72                 // String info
       6: aload_0
       7: getfield      #10                 // Field metricsInfo:Lorg/apache/hadoop/metrics2/MetricsInfo;
      10: invokevirtual #73                 // Method org/apache/hbase/thirdparty/com/google/common/base/MoreObjects$ToStringHelper.add:(Ljava/lang/String;Ljava/lang/Object;)Lorg/apache/hbase/thirdparty/com/google/common/base/MoreObjects$ToStringHelper;
      13: ldc           #74                 // String tags
      15: aload_0
      16: invokevirtual #64                 // Method tags:()Ljava/util/Collection;
      19: invokevirtual #73                 // Method org/apache/hbase/thirdparty/com/google/common/base/MoreObjects$ToStringHelper.add:(Ljava/lang/String;Ljava/lang/Object;)Lorg/apache/hbase/thirdparty/com/google/common/base/MoreObjects$ToStringHelper;
      22: ldc           #75                 // String metrics
      24: aload_0
      25: invokevirtual #69                 // Method metrics:()Ljava/util/Collection;
      28: invokevirtual #73                 // Method org/apache/hbase/thirdparty/com/google/common/base/MoreObjects$ToStringHelper.add:(Ljava/lang/String;Ljava/lang/Object;)Lorg/apache/hbase/thirdparty/com/google/common/base/MoreObjects$ToStringHelper;
      31: invokevirtual #76                 // Method org/apache/hbase/thirdparty/com/google/common/base/MoreObjects$ToStringHelper.toString:()Ljava/lang/String;
      34: areturn

  public void removeMetric(java.lang.String);
    Code:
       0: aload_0
       1: getfield      #9                  // Field helper:Lorg/apache/hadoop/metrics2/lib/DefaultMetricsSystemHelper;
       4: aload_1
       5: invokevirtual #77                 // Method org/apache/hadoop/metrics2/lib/DefaultMetricsSystemHelper.removeObjectName:(Ljava/lang/String;)Z
       8: pop
       9: aload_0
      10: getfield      #5                  // Field metricsMap:Ljava/util/concurrent/ConcurrentMap;
      13: aload_1
      14: invokeinterface #78,  2           // InterfaceMethod java/util/concurrent/ConcurrentMap.remove:(Ljava/lang/Object;)Ljava/lang/Object;
      19: pop
      20: return

  public void removeHistogramMetrics(java.lang.String);
    Code:
       0: getstatic     #79                 // Field histogramSuffixes:[Ljava/lang/String;
       3: astore_2
       4: aload_2
       5: arraylength
       6: istore_3
       7: iconst_0
       8: istore        4
      10: iload         4
      12: iload_3
      13: if_icmpge     51
      16: aload_2
      17: iload         4
      19: aaload
      20: astore        5
      22: aload_0
      23: new           #31                 // class java/lang/StringBuilder
      26: dup
      27: invokespecial #32                 // Method java/lang/StringBuilder."<init>":()V
      30: aload_1
      31: invokevirtual #34                 // Method java/lang/StringBuilder.append:(Ljava/lang/String;)Ljava/lang/StringBuilder;
      34: aload         5
      36: invokevirtual #34                 // Method java/lang/StringBuilder.append:(Ljava/lang/String;)Ljava/lang/StringBuilder;
      39: invokevirtual #38                 // Method java/lang/StringBuilder.toString:()Ljava/lang/String;
      42: invokevirtual #80                 // Method removeMetric:(Ljava/lang/String;)V
      45: iinc          4, 1
      48: goto          10
      51: return

  public org.apache.hadoop.metrics2.lib.MutableGaugeLong getGauge(java.lang.String, long);
    Code:
       0: aload_0
       1: getfield      #5                  // Field metricsMap:Ljava/util/concurrent/ConcurrentMap;
       4: aload_1
       5: invokeinterface #11,  2           // InterfaceMethod java/util/concurrent/ConcurrentMap.get:(Ljava/lang/Object;)Ljava/lang/Object;
      10: checkcast     #12                 // class org/apache/hadoop/metrics2/lib/MutableMetric
      13: astore        4
      15: aload         4
      17: ifnonnull     65
      20: new           #22                 // class org/apache/hadoop/metrics2/lib/MutableGaugeLong
      23: dup
      24: new           #14                 // class org/apache/hadoop/metrics2/lib/MetricsInfoImpl
      27: dup
      28: aload_1
      29: ldc           #41                 // String
      31: invokespecial #15                 // Method org/apache/hadoop/metrics2/lib/MetricsInfoImpl."<init>":(Ljava/lang/String;Ljava/lang/String;)V
      34: lload_2
      35: invokespecial #23                 // Method org/apache/hadoop/metrics2/lib/MutableGaugeLong."<init>":(Lorg/apache/hadoop/metrics2/MetricsInfo;J)V
      38: astore        5
      40: aload_0
      41: getfield      #5                  // Field metricsMap:Ljava/util/concurrent/ConcurrentMap;
      44: aload_1
      45: aload         5
      47: invokeinterface #60,  3           // InterfaceMethod java/util/concurrent/ConcurrentMap.putIfAbsent:(Ljava/lang/Object;Ljava/lang/Object;)Ljava/lang/Object;
      52: checkcast     #12                 // class org/apache/hadoop/metrics2/lib/MutableMetric
      55: astore        4
      57: aload         4
      59: ifnonnull     65
      62: aload         5
      64: areturn
      65: aload         4
      67: instanceof    #22                 // class org/apache/hadoop/metrics2/lib/MutableGaugeLong
      70: ifne          105
      73: new           #30                 // class org/apache/hadoop/metrics2/MetricsException
      76: dup
      77: new           #31                 // class java/lang/StringBuilder
      80: dup
      81: invokespecial #32                 // Method java/lang/StringBuilder."<init>":()V
      84: ldc           #81                 // String Metric already exists in registry for metric name:
      86: invokevirtual #34                 // Method java/lang/StringBuilder.append:(Ljava/lang/String;)Ljava/lang/StringBuilder;
      89: aload_1
      90: invokevirtual #34                 // Method java/lang/StringBuilder.append:(Ljava/lang/String;)Ljava/lang/StringBuilder;
      93: ldc           #82                 // String  and not of type MetricMutableGaugeLong
      95: invokevirtual #34                 // Method java/lang/StringBuilder.append:(Ljava/lang/String;)Ljava/lang/StringBuilder;
      98: invokevirtual #38                 // Method java/lang/StringBuilder.toString:()Ljava/lang/String;
     101: invokespecial #39                 // Method org/apache/hadoop/metrics2/MetricsException."<init>":(Ljava/lang/String;)V
     104: athrow
     105: aload         4
     107: checkcast     #22                 // class org/apache/hadoop/metrics2/lib/MutableGaugeLong
     110: areturn

  public org.apache.hadoop.metrics2.lib.MutableFastCounter getCounter(java.lang.String, long);
    Code:
       0: aload_0
       1: getfield      #5                  // Field metricsMap:Ljava/util/concurrent/ConcurrentMap;
       4: aload_1
       5: invokeinterface #11,  2           // InterfaceMethod java/util/concurrent/ConcurrentMap.get:(Ljava/lang/Object;)Ljava/lang/Object;
      10: checkcast     #12                 // class org/apache/hadoop/metrics2/lib/MutableMetric
      13: astore        4
      15: aload         4
      17: ifnonnull     65
      20: new           #17                 // class org/apache/hadoop/metrics2/lib/MutableFastCounter
      23: dup
      24: new           #14                 // class org/apache/hadoop/metrics2/lib/MetricsInfoImpl
      27: dup
      28: aload_1
      29: ldc           #41                 // String
      31: invokespecial #15                 // Method org/apache/hadoop/metrics2/lib/MetricsInfoImpl."<init>":(Ljava/lang/String;Ljava/lang/String;)V
      34: lload_2
      35: invokespecial #18                 // Method org/apache/hadoop/metrics2/lib/MutableFastCounter."<init>":(Lorg/apache/hadoop/metrics2/MetricsInfo;J)V
      38: astore        5
      40: aload_0
      41: getfield      #5                  // Field metricsMap:Ljava/util/concurrent/ConcurrentMap;
      44: aload_1
      45: aload         5
      47: invokeinterface #60,  3           // InterfaceMethod java/util/concurrent/ConcurrentMap.putIfAbsent:(Ljava/lang/Object;Ljava/lang/Object;)Ljava/lang/Object;
      52: checkcast     #12                 // class org/apache/hadoop/metrics2/lib/MutableMetric
      55: astore        4
      57: aload         4
      59: ifnonnull     65
      62: aload         5
      64: areturn
      65: aload         4
      67: instanceof    #83                 // class org/apache/hadoop/metrics2/lib/MutableCounter
      70: ifne          105
      73: new           #30                 // class org/apache/hadoop/metrics2/MetricsException
      76: dup
      77: new           #31                 // class java/lang/StringBuilder
      80: dup
      81: invokespecial #32                 // Method java/lang/StringBuilder."<init>":()V
      84: ldc           #81                 // String Metric already exists in registry for metric name:
      86: invokevirtual #34                 // Method java/lang/StringBuilder.append:(Ljava/lang/String;)Ljava/lang/StringBuilder;
      89: aload_1
      90: invokevirtual #34                 // Method java/lang/StringBuilder.append:(Ljava/lang/String;)Ljava/lang/StringBuilder;
      93: ldc           #84                 // String  and not of type MutableCounter
      95: invokevirtual #34                 // Method java/lang/StringBuilder.append:(Ljava/lang/String;)Ljava/lang/StringBuilder;
      98: invokevirtual #38                 // Method java/lang/StringBuilder.toString:()Ljava/lang/String;
     101: invokespecial #39                 // Method org/apache/hadoop/metrics2/MetricsException."<init>":(Ljava/lang/String;)V
     104: athrow
     105: aload         4
     107: checkcast     #17                 // class org/apache/hadoop/metrics2/lib/MutableFastCounter
     110: areturn

  public org.apache.hadoop.metrics2.lib.MutableHistogram getHistogram(java.lang.String);
    Code:
       0: aload_0
       1: getfield      #5                  // Field metricsMap:Ljava/util/concurrent/ConcurrentMap;
       4: aload_1
       5: invokeinterface #11,  2           // InterfaceMethod java/util/concurrent/ConcurrentMap.get:(Ljava/lang/Object;)Ljava/lang/Object;
      10: checkcast     #12                 // class org/apache/hadoop/metrics2/lib/MutableMetric
      13: astore_2
      14: aload_2
      15: ifnonnull     57
      18: new           #43                 // class org/apache/hadoop/metrics2/lib/MutableHistogram
      21: dup
      22: new           #14                 // class org/apache/hadoop/metrics2/lib/MetricsInfoImpl
      25: dup
      26: aload_1
      27: ldc           #41                 // String
      29: invokespecial #15                 // Method org/apache/hadoop/metrics2/lib/MetricsInfoImpl."<init>":(Ljava/lang/String;Ljava/lang/String;)V
      32: invokespecial #85                 // Method org/apache/hadoop/metrics2/lib/MutableHistogram."<init>":(Lorg/apache/hadoop/metrics2/MetricsInfo;)V
      35: astore_3
      36: aload_0
      37: getfield      #5                  // Field metricsMap:Ljava/util/concurrent/ConcurrentMap;
      40: aload_1
      41: aload_3
      42: invokeinterface #60,  3           // InterfaceMethod java/util/concurrent/ConcurrentMap.putIfAbsent:(Ljava/lang/Object;Ljava/lang/Object;)Ljava/lang/Object;
      47: checkcast     #12                 // class org/apache/hadoop/metrics2/lib/MutableMetric
      50: astore_2
      51: aload_2
      52: ifnonnull     57
      55: aload_3
      56: areturn
      57: aload_2
      58: instanceof    #43                 // class org/apache/hadoop/metrics2/lib/MutableHistogram
      61: ifne          96
      64: new           #30                 // class org/apache/hadoop/metrics2/MetricsException
      67: dup
      68: new           #31                 // class java/lang/StringBuilder
      71: dup
      72: invokespecial #32                 // Method java/lang/StringBuilder."<init>":()V
      75: ldc           #81                 // String Metric already exists in registry for metric name:
      77: invokevirtual #34                 // Method java/lang/StringBuilder.append:(Ljava/lang/String;)Ljava/lang/StringBuilder;
      80: aload_1
      81: invokevirtual #34                 // Method java/lang/StringBuilder.append:(Ljava/lang/String;)Ljava/lang/StringBuilder;
      84: ldc           #86                 // String  and not of type MutableHistogram
      86: invokevirtual #34                 // Method java/lang/StringBuilder.append:(Ljava/lang/String;)Ljava/lang/StringBuilder;
      89: invokevirtual #38                 // Method java/lang/StringBuilder.toString:()Ljava/lang/String;
      92: invokespecial #39                 // Method org/apache/hadoop/metrics2/MetricsException."<init>":(Ljava/lang/String;)V
      95: athrow
      96: aload_2
      97: checkcast     #43                 // class org/apache/hadoop/metrics2/lib/MutableHistogram
     100: areturn

  public void clearMetrics();
    Code:
       0: aload_0
       1: getfield      #5                  // Field metricsMap:Ljava/util/concurrent/ConcurrentMap;
       4: invokeinterface #91,  1           // InterfaceMethod java/util/concurrent/ConcurrentMap.keySet:()Ljava/util/Set;
       9: invokeinterface #92,  1           // InterfaceMethod java/util/Set.iterator:()Ljava/util/Iterator;
      14: astore_1
      15: aload_1
      16: invokeinterface #66,  1           // InterfaceMethod java/util/Iterator.hasNext:()Z
      21: ifeq          46
      24: aload_1
      25: invokeinterface #67,  1           // InterfaceMethod java/util/Iterator.next:()Ljava/lang/Object;
      30: checkcast     #93                 // class java/lang/String
      33: astore_2
      34: aload_0
      35: getfield      #9                  // Field helper:Lorg/apache/hadoop/metrics2/lib/DefaultMetricsSystemHelper;
      38: aload_2
      39: invokevirtual #77                 // Method org/apache/hadoop/metrics2/lib/DefaultMetricsSystemHelper.removeObjectName:(Ljava/lang/String;)Z
      42: pop
      43: goto          15
      46: aload_0
      47: getfield      #5                  // Field metricsMap:Ljava/util/concurrent/ConcurrentMap;
      50: invokeinterface #94,  1           // InterfaceMethod java/util/concurrent/ConcurrentMap.clear:()V
      55: return

  static {};
    Code:
       0: ldc           #95                 // class org/apache/hadoop/metrics2/lib/DynamicMetricsRegistry
       2: invokestatic  #96                 // Method org/slf4j/LoggerFactory.getLogger:(Ljava/lang/Class;)Lorg/slf4j/Logger;
       5: putstatic     #97                 // Field LOG:Lorg/slf4j/Logger;
       8: bipush        8
      10: anewarray     #93                 // class java/lang/String
      13: dup
      14: iconst_0
      15: ldc           #98                 // String _num_ops
      17: aastore
      18: dup
      19: iconst_1
      20: ldc           #99                 // String _min
      22: aastore
      23: dup
      24: iconst_2
      25: ldc           #100                // String _max
      27: aastore
      28: dup
      29: iconst_3
      30: ldc           #101                // String _median
      32: aastore
      33: dup
      34: iconst_4
      35: ldc           #102                // String _75th_percentile
      37: aastore
      38: dup
      39: iconst_5
      40: ldc           #103                // String _90th_percentile
      42: aastore
      43: dup
      44: bipush        6
      46: ldc           #104                // String _95th_percentile
      48: aastore
      49: dup
      50: bipush        7
      52: ldc           #105                // String _99th_percentile
      54: aastore
      55: putstatic     #79                 // Field histogramSuffixes:[Ljava/lang/String;
      58: return
}
