Compiled from "EmptyNormalizationPlan.java"
public final class org.apache.hadoop.hbase.master.normalizer.EmptyNormalizationPlan implements org.apache.hadoop.hbase.master.normalizer.NormalizationPlan {
  public static org.apache.hadoop.hbase.master.normalizer.EmptyNormalizationPlan getInstance();
    Code:
       0: getstatic     #2                  // Field instance:Lorg/apache/hadoop/hbase/master/normalizer/EmptyNormalizationPlan;
       3: areturn

  public void execute(org.apache.hadoop.hbase.client.Admin);
    Code:
       0: return

  public org.apache.hadoop.hbase.master.normalizer.NormalizationPlan$PlanType getType();
    Code:
       0: getstatic     #3                  // Field org/apache/hadoop/hbase/master/normalizer/NormalizationPlan$PlanType.NONE:Lorg/apache/hadoop/hbase/master/normalizer/NormalizationPlan$PlanType;
       3: areturn

  static {};
    Code:
       0: new           #4                  // class org/apache/hadoop/hbase/master/normalizer/EmptyNormalizationPlan
       3: dup
       4: invokespecial #5                  // Method "<init>":()V
       7: putstatic     #2                  // Field instance:Lorg/apache/hadoop/hbase/master/normalizer/EmptyNormalizationPlan;
      10: return
}
