Compiled from "EnableTableProcedure.java"
public class org.apache.hadoop.hbase.master.procedure.EnableTableProcedure extends org.apache.hadoop.hbase.master.procedure.AbstractStateMachineTableProcedure<org.apache.hadoop.hbase.shaded.protobuf.generated.MasterProcedureProtos$EnableTableState> {
  static final boolean $assertionsDisabled;

  public org.apache.hadoop.hbase.master.procedure.EnableTableProcedure();
    Code:
       0: aload_0
       1: invokespecial #1                  // Method org/apache/hadoop/hbase/master/procedure/AbstractStateMachineTableProcedure."<init>":()V
       4: aload_0
       5: aconst_null
       6: putfield      #2                  // Field traceEnabled:Ljava/lang/Boolean;
       9: return

  public org.apache.hadoop.hbase.master.procedure.EnableTableProcedure(org.apache.hadoop.hbase.master.procedure.MasterProcedureEnv, org.apache.hadoop.hbase.TableName);
    Code:
       0: aload_0
       1: aload_1
       2: aload_2
       3: aconst_null
       4: invokespecial #3                  // Method "<init>":(Lorg/apache/hadoop/hbase/master/procedure/MasterProcedureEnv;Lorg/apache/hadoop/hbase/TableName;Lorg/apache/hadoop/hbase/master/procedure/ProcedurePrepareLatch;)V
       7: return

  public org.apache.hadoop.hbase.master.procedure.EnableTableProcedure(org.apache.hadoop.hbase.master.procedure.MasterProcedureEnv, org.apache.hadoop.hbase.TableName, org.apache.hadoop.hbase.master.procedure.ProcedurePrepareLatch);
    Code:
       0: aload_0
       1: aload_1
       2: aload_3
       3: invokespecial #4                  // Method org/apache/hadoop/hbase/master/procedure/AbstractStateMachineTableProcedure."<init>":(Lorg/apache/hadoop/hbase/master/procedure/MasterProcedureEnv;Lorg/apache/hadoop/hbase/master/procedure/ProcedurePrepareLatch;)V
       6: aload_0
       7: aconst_null
       8: putfield      #2                  // Field traceEnabled:Ljava/lang/Boolean;
      11: aload_0
      12: aload_2
      13: putfield      #5                  // Field tableName:Lorg/apache/hadoop/hbase/TableName;
      16: return

  protected org.apache.hadoop.hbase.procedure2.StateMachineProcedure$Flow executeFromState(org.apache.hadoop.hbase.master.procedure.MasterProcedureEnv, org.apache.hadoop.hbase.shaded.protobuf.generated.MasterProcedureProtos$EnableTableState) throws java.lang.InterruptedException;
    Code:
       0: aload_0
       1: invokespecial #6                  // Method isTraceEnabled:()Ljava/lang/Boolean;
       4: invokevirtual #7                  // Method java/lang/Boolean.booleanValue:()Z
       7: ifeq          41
      10: getstatic     #8                  // Field LOG:Lorg/slf4j/Logger;
      13: new           #9                  // class java/lang/StringBuilder
      16: dup
      17: invokespecial #10                 // Method java/lang/StringBuilder."<init>":()V
      20: aload_0
      21: invokevirtual #11                 // Method java/lang/StringBuilder.append:(Ljava/lang/Object;)Ljava/lang/StringBuilder;
      24: ldc           #12                 // String  execute state=
      26: invokevirtual #13                 // Method java/lang/StringBuilder.append:(Ljava/lang/String;)Ljava/lang/StringBuilder;
      29: aload_2
      30: invokevirtual #11                 // Method java/lang/StringBuilder.append:(Ljava/lang/Object;)Ljava/lang/StringBuilder;
      33: invokevirtual #14                 // Method java/lang/StringBuilder.toString:()Ljava/lang/String;
      36: invokeinterface #15,  2           // InterfaceMethod org/slf4j/Logger.trace:(Ljava/lang/String;)V
      41: getstatic     #16                 // Field org/apache/hadoop/hbase/master/procedure/EnableTableProcedure$1.$SwitchMap$org$apache$hadoop$hbase$shaded$protobuf$generated$MasterProcedureProtos$EnableTableState:[I
      44: aload_2
      45: invokevirtual #17                 // Method org/apache/hadoop/hbase/shaded/protobuf/generated/MasterProcedureProtos$EnableTableState.ordinal:()I
      48: iaload
      49: tableswitch   { // 1 to 6
                     1: 88
                     2: 133
                     3: 149
                     4: 167
                     5: 668
                     6: 686
               default: 696
          }
      88: aload_0
      89: aload_1
      90: invokespecial #18                 // Method prepareEnable:(Lorg/apache/hadoop/hbase/master/procedure/MasterProcedureEnv;)Z
      93: ifeq          106
      96: aload_0
      97: getstatic     #19                 // Field org/apache/hadoop/hbase/shaded/protobuf/generated/MasterProcedureProtos$EnableTableState.ENABLE_TABLE_PRE_OPERATION:Lorg/apache/hadoop/hbase/shaded/protobuf/generated/MasterProcedureProtos$EnableTableState;
     100: invokevirtual #20                 // Method setNextState:(Ljava/lang/Object;)V
     103: goto          723
     106: getstatic     #21                 // Field $assertionsDisabled:Z
     109: ifne          129
     112: aload_0
     113: invokevirtual #22                 // Method isFailed:()Z
     116: ifne          129
     119: new           #23                 // class java/lang/AssertionError
     122: dup
     123: ldc           #24                 // String enable should have an exception here
     125: invokespecial #25                 // Method java/lang/AssertionError."<init>":(Ljava/lang/Object;)V
     128: athrow
     129: getstatic     #26                 // Field org/apache/hadoop/hbase/procedure2/StateMachineProcedure$Flow.NO_MORE_STATE:Lorg/apache/hadoop/hbase/procedure2/StateMachineProcedure$Flow;
     132: areturn
     133: aload_0
     134: aload_1
     135: aload_2
     136: invokespecial #27                 // Method preEnable:(Lorg/apache/hadoop/hbase/master/procedure/MasterProcedureEnv;Lorg/apache/hadoop/hbase/shaded/protobuf/generated/MasterProcedureProtos$EnableTableState;)V
     139: aload_0
     140: getstatic     #28                 // Field org/apache/hadoop/hbase/shaded/protobuf/generated/MasterProcedureProtos$EnableTableState.ENABLE_TABLE_SET_ENABLING_TABLE_STATE:Lorg/apache/hadoop/hbase/shaded/protobuf/generated/MasterProcedureProtos$EnableTableState;
     143: invokevirtual #20                 // Method setNextState:(Ljava/lang/Object;)V
     146: goto          723
     149: aload_1
     150: aload_0
     151: getfield      #5                  // Field tableName:Lorg/apache/hadoop/hbase/TableName;
     154: invokestatic  #29                 // Method setTableStateToEnabling:(Lorg/apache/hadoop/hbase/master/procedure/MasterProcedureEnv;Lorg/apache/hadoop/hbase/TableName;)V
     157: aload_0
     158: getstatic     #30                 // Field org/apache/hadoop/hbase/shaded/protobuf/generated/MasterProcedureProtos$EnableTableState.ENABLE_TABLE_MARK_REGIONS_ONLINE:Lorg/apache/hadoop/hbase/shaded/protobuf/generated/MasterProcedureProtos$EnableTableState;
     161: invokevirtual #20                 // Method setNextState:(Ljava/lang/Object;)V
     164: goto          723
     167: aload_1
     168: invokevirtual #31                 // Method org/apache/hadoop/hbase/master/procedure/MasterProcedureEnv.getMasterServices:()Lorg/apache/hadoop/hbase/master/MasterServices;
     171: invokeinterface #32,  1           // InterfaceMethod org/apache/hadoop/hbase/master/MasterServices.getConnection:()Lorg/apache/hadoop/hbase/client/Connection;
     176: astore_3
     177: aload_1
     178: invokevirtual #31                 // Method org/apache/hadoop/hbase/master/procedure/MasterProcedureEnv.getMasterServices:()Lorg/apache/hadoop/hbase/master/MasterServices;
     181: invokeinterface #33,  1           // InterfaceMethod org/apache/hadoop/hbase/master/MasterServices.getTableDescriptors:()Lorg/apache/hadoop/hbase/TableDescriptors;
     186: aload_0
     187: getfield      #5                  // Field tableName:Lorg/apache/hadoop/hbase/TableName;
     190: invokeinterface #34,  2           // InterfaceMethod org/apache/hadoop/hbase/TableDescriptors.get:(Lorg/apache/hadoop/hbase/TableName;)Lorg/apache/hadoop/hbase/client/TableDescriptor;
     195: astore        4
     197: aload         4
     199: invokeinterface #35,  1           // InterfaceMethod org/apache/hadoop/hbase/client/TableDescriptor.getRegionReplication:()I
     204: istore        5
     206: aload_1
     207: invokevirtual #36                 // Method org/apache/hadoop/hbase/master/procedure/MasterProcedureEnv.getAssignmentManager:()Lorg/apache/hadoop/hbase/master/assignment/AssignmentManager;
     210: invokevirtual #37                 // Method org/apache/hadoop/hbase/master/assignment/AssignmentManager.getRegionStates:()Lorg/apache/hadoop/hbase/master/assignment/RegionStates;
     213: aload_0
     214: getfield      #5                  // Field tableName:Lorg/apache/hadoop/hbase/TableName;
     217: iconst_1
     218: invokevirtual #38                 // Method org/apache/hadoop/hbase/master/assignment/RegionStates.getRegionsOfTable:(Lorg/apache/hadoop/hbase/TableName;Z)Ljava/util/List;
     221: astore        6
     223: iconst_0
     224: istore        7
     226: aload         6
     228: invokeinterface #39,  1           // InterfaceMethod java/util/List.iterator:()Ljava/util/Iterator;
     233: astore        8
     235: aload         8
     237: invokeinterface #40,  1           // InterfaceMethod java/util/Iterator.hasNext:()Z
     242: ifeq          281
     245: aload         8
     247: invokeinterface #41,  1           // InterfaceMethod java/util/Iterator.next:()Ljava/lang/Object;
     252: checkcast     #42                 // class org/apache/hadoop/hbase/client/RegionInfo
     255: astore        9
     257: aload         9
     259: invokeinterface #43,  1           // InterfaceMethod org/apache/hadoop/hbase/client/RegionInfo.getReplicaId:()I
     264: iload         7
     266: if_icmple     278
     269: aload         9
     271: invokeinterface #43,  1           // InterfaceMethod org/apache/hadoop/hbase/client/RegionInfo.getReplicaId:()I
     276: istore        7
     278: goto          235
     281: aload_0
     282: aload_3
     283: iload         5
     285: aload         6
     287: invokespecial #44                 // Method getNumberOfReplicasFromMeta:(Lorg/apache/hadoop/hbase/client/Connection;ILjava/util/List;)I
     290: istore        8
     292: getstatic     #21                 // Field $assertionsDisabled:Z
     295: ifne          315
     298: iload         5
     300: iconst_1
     301: isub
     302: iload         8
     304: if_icmpeq     315
     307: new           #23                 // class java/lang/AssertionError
     310: dup
     311: invokespecial #45                 // Method java/lang/AssertionError."<init>":()V
     314: athrow
     315: getstatic     #8                  // Field LOG:Lorg/slf4j/Logger;
     318: new           #9                  // class java/lang/StringBuilder
     321: dup
     322: invokespecial #10                 // Method java/lang/StringBuilder."<init>":()V
     325: iload         8
     327: invokevirtual #46                 // Method java/lang/StringBuilder.append:(I)Ljava/lang/StringBuilder;
     330: ldc           #47                 // String  META entries added for the given regionReplicaCount
     332: invokevirtual #13                 // Method java/lang/StringBuilder.append:(Ljava/lang/String;)Ljava/lang/StringBuilder;
     335: iload         5
     337: invokevirtual #46                 // Method java/lang/StringBuilder.append:(I)Ljava/lang/StringBuilder;
     340: ldc           #48                 // String  for the table
     342: invokevirtual #13                 // Method java/lang/StringBuilder.append:(Ljava/lang/String;)Ljava/lang/StringBuilder;
     345: aload_0
     346: getfield      #5                  // Field tableName:Lorg/apache/hadoop/hbase/TableName;
     349: invokevirtual #49                 // Method org/apache/hadoop/hbase/TableName.getNameAsString:()Ljava/lang/String;
     352: invokevirtual #13                 // Method java/lang/StringBuilder.append:(Ljava/lang/String;)Ljava/lang/StringBuilder;
     355: invokevirtual #14                 // Method java/lang/StringBuilder.toString:()Ljava/lang/String;
     358: invokeinterface #50,  2           // InterfaceMethod org/slf4j/Logger.info:(Ljava/lang/String;)V
     363: iload         7
     365: iload         5
     367: iconst_1
     368: isub
     369: if_icmpne     414
     372: getstatic     #8                  // Field LOG:Lorg/slf4j/Logger;
     375: invokeinterface #51,  1           // InterfaceMethod org/slf4j/Logger.isDebugEnabled:()Z
     380: ifeq          645
     383: getstatic     #8                  // Field LOG:Lorg/slf4j/Logger;
     386: new           #9                  // class java/lang/StringBuilder
     389: dup
     390: invokespecial #10                 // Method java/lang/StringBuilder."<init>":()V
     393: ldc           #52                 // String There is no change to the number of region replicas. Assigning the available regions. Current and previousreplica count is
     395: invokevirtual #13                 // Method java/lang/StringBuilder.append:(Ljava/lang/String;)Ljava/lang/StringBuilder;
     398: iload         5
     400: invokevirtual #46                 // Method java/lang/StringBuilder.append:(I)Ljava/lang/StringBuilder;
     403: invokevirtual #14                 // Method java/lang/StringBuilder.toString:()Ljava/lang/String;
     406: invokeinterface #53,  2           // InterfaceMethod org/slf4j/Logger.debug:(Ljava/lang/String;)V
     411: goto          645
     414: iload         7
     416: iload         5
     418: iconst_1
     419: isub
     420: if_icmple     590
     423: getstatic     #8                  // Field LOG:Lorg/slf4j/Logger;
     426: new           #9                  // class java/lang/StringBuilder
     429: dup
     430: invokespecial #10                 // Method java/lang/StringBuilder."<init>":()V
     433: ldc           #54                 // String The number of replicas
     435: invokevirtual #13                 // Method java/lang/StringBuilder.append:(Ljava/lang/String;)Ljava/lang/StringBuilder;
     438: iload         7
     440: iconst_1
     441: iadd
     442: invokevirtual #46                 // Method java/lang/StringBuilder.append:(I)Ljava/lang/StringBuilder;
     445: ldc           #55                 // String   is more than the region replica count
     447: invokevirtual #13                 // Method java/lang/StringBuilder.append:(Ljava/lang/String;)Ljava/lang/StringBuilder;
     450: iload         5
     452: invokevirtual #46                 // Method java/lang/StringBuilder.append:(I)Ljava/lang/StringBuilder;
     455: invokevirtual #14                 // Method java/lang/StringBuilder.toString:()Ljava/lang/String;
     458: invokeinterface #50,  2           // InterfaceMethod org/slf4j/Logger.info:(Ljava/lang/String;)V
     463: new           #56                 // class java/util/ArrayList
     466: dup
     467: aload         6
     469: invokespecial #57                 // Method java/util/ArrayList."<init>":(Ljava/util/Collection;)V
     472: astore        9
     474: aload         9
     476: invokeinterface #39,  1           // InterfaceMethod java/util/List.iterator:()Ljava/util/Iterator;
     481: astore        10
     483: aload         10
     485: invokeinterface #40,  1           // InterfaceMethod java/util/Iterator.hasNext:()Z
     490: ifeq          587
     493: aload         10
     495: invokeinterface #41,  1           // InterfaceMethod java/util/Iterator.next:()Ljava/lang/Object;
     500: checkcast     #42                 // class org/apache/hadoop/hbase/client/RegionInfo
     503: astore        11
     505: aload         11
     507: invokeinterface #43,  1           // InterfaceMethod org/apache/hadoop/hbase/client/RegionInfo.getReplicaId:()I
     512: iload         5
     514: iconst_1
     515: isub
     516: if_icmple     584
     519: aload_1
     520: invokevirtual #36                 // Method org/apache/hadoop/hbase/master/procedure/MasterProcedureEnv.getAssignmentManager:()Lorg/apache/hadoop/hbase/master/assignment/AssignmentManager;
     523: invokevirtual #37                 // Method org/apache/hadoop/hbase/master/assignment/AssignmentManager.getRegionStates:()Lorg/apache/hadoop/hbase/master/assignment/RegionStates;
     526: aload         11
     528: invokevirtual #58                 // Method org/apache/hadoop/hbase/master/assignment/RegionStates.deleteRegion:(Lorg/apache/hadoop/hbase/client/RegionInfo;)V
     531: getstatic     #8                  // Field LOG:Lorg/slf4j/Logger;
     534: new           #9                  // class java/lang/StringBuilder
     537: dup
     538: invokespecial #10                 // Method java/lang/StringBuilder."<init>":()V
     541: ldc           #59                 // String The regioninfo being removed is
     543: invokevirtual #13                 // Method java/lang/StringBuilder.append:(Ljava/lang/String;)Ljava/lang/StringBuilder;
     546: aload         11
     548: invokevirtual #11                 // Method java/lang/StringBuilder.append:(Ljava/lang/Object;)Ljava/lang/StringBuilder;
     551: ldc           #60                 // String
     553: invokevirtual #13                 // Method java/lang/StringBuilder.append:(Ljava/lang/String;)Ljava/lang/StringBuilder;
     556: aload         11
     558: invokeinterface #43,  1           // InterfaceMethod org/apache/hadoop/hbase/client/RegionInfo.getReplicaId:()I
     563: invokevirtual #46                 // Method java/lang/StringBuilder.append:(I)Ljava/lang/StringBuilder;
     566: invokevirtual #14                 // Method java/lang/StringBuilder.toString:()Ljava/lang/String;
     569: invokeinterface #50,  2           // InterfaceMethod org/slf4j/Logger.info:(Ljava/lang/String;)V
     574: aload         6
     576: aload         11
     578: invokeinterface #61,  2           // InterfaceMethod java/util/List.remove:(Ljava/lang/Object;)Z
     583: pop
     584: goto          483
     587: goto          645
     590: getstatic     #8                  // Field LOG:Lorg/slf4j/Logger;
     593: new           #9                  // class java/lang/StringBuilder
     596: dup
     597: invokespecial #10                 // Method java/lang/StringBuilder."<init>":()V
     600: ldc           #62                 // String The number of replicas has been changed(increased). Lets assign the new region replicas. The previous replica count was
     602: invokevirtual #13                 // Method java/lang/StringBuilder.append:(Ljava/lang/String;)Ljava/lang/StringBuilder;
     605: iload         7
     607: iconst_1
     608: iadd
     609: invokevirtual #46                 // Method java/lang/StringBuilder.append:(I)Ljava/lang/StringBuilder;
     612: ldc           #63                 // String . The current replica count is
     614: invokevirtual #13                 // Method java/lang/StringBuilder.append:(Ljava/lang/String;)Ljava/lang/StringBuilder;
     617: iload         5
     619: invokevirtual #46                 // Method java/lang/StringBuilder.append:(I)Ljava/lang/StringBuilder;
     622: invokevirtual #14                 // Method java/lang/StringBuilder.toString:()Ljava/lang/String;
     625: invokeinterface #50,  2           // InterfaceMethod org/slf4j/Logger.info:(Ljava/lang/String;)V
     630: aload         4
     632: aload         6
     634: iload         7
     636: iconst_1
     637: iadd
     638: iload         5
     640: invokestatic  #64                 // Method org/apache/hadoop/hbase/client/RegionReplicaUtil.addReplicas:(Lorg/apache/hadoop/hbase/client/TableDescriptor;Ljava/util/List;II)Ljava/util/List;
     643: astore        6
     645: aload_0
     646: aload_1
     647: invokevirtual #36                 // Method org/apache/hadoop/hbase/master/procedure/MasterProcedureEnv.getAssignmentManager:()Lorg/apache/hadoop/hbase/master/assignment/AssignmentManager;
     650: aload         6
     652: invokevirtual #65                 // Method org/apache/hadoop/hbase/master/assignment/AssignmentManager.createAssignProcedures:(Ljava/util/List;)[Lorg/apache/hadoop/hbase/master/assignment/TransitRegionStateProcedure;
     655: invokevirtual #66                 // Method addChildProcedure:([Lorg/apache/hadoop/hbase/procedure2/Procedure;)V
     658: aload_0
     659: getstatic     #67                 // Field org/apache/hadoop/hbase/shaded/protobuf/generated/MasterProcedureProtos$EnableTableState.ENABLE_TABLE_SET_ENABLED_TABLE_STATE:Lorg/apache/hadoop/hbase/shaded/protobuf/generated/MasterProcedureProtos$EnableTableState;
     662: invokevirtual #20                 // Method setNextState:(Ljava/lang/Object;)V
     665: goto          723
     668: aload_1
     669: aload_0
     670: getfield      #5                  // Field tableName:Lorg/apache/hadoop/hbase/TableName;
     673: invokestatic  #68                 // Method setTableStateToEnabled:(Lorg/apache/hadoop/hbase/master/procedure/MasterProcedureEnv;Lorg/apache/hadoop/hbase/TableName;)V
     676: aload_0
     677: getstatic     #69                 // Field org/apache/hadoop/hbase/shaded/protobuf/generated/MasterProcedureProtos$EnableTableState.ENABLE_TABLE_POST_OPERATION:Lorg/apache/hadoop/hbase/shaded/protobuf/generated/MasterProcedureProtos$EnableTableState;
     680: invokevirtual #20                 // Method setNextState:(Ljava/lang/Object;)V
     683: goto          723
     686: aload_0
     687: aload_1
     688: aload_2
     689: invokespecial #70                 // Method postEnable:(Lorg/apache/hadoop/hbase/master/procedure/MasterProcedureEnv;Lorg/apache/hadoop/hbase/shaded/protobuf/generated/MasterProcedureProtos$EnableTableState;)V
     692: getstatic     #26                 // Field org/apache/hadoop/hbase/procedure2/StateMachineProcedure$Flow.NO_MORE_STATE:Lorg/apache/hadoop/hbase/procedure2/StateMachineProcedure$Flow;
     695: areturn
     696: new           #71                 // class java/lang/UnsupportedOperationException
     699: dup
     700: new           #9                  // class java/lang/StringBuilder
     703: dup
     704: invokespecial #10                 // Method java/lang/StringBuilder."<init>":()V
     707: ldc           #72                 // String unhandled state=
     709: invokevirtual #13                 // Method java/lang/StringBuilder.append:(Ljava/lang/String;)Ljava/lang/StringBuilder;
     712: aload_2
     713: invokevirtual #11                 // Method java/lang/StringBuilder.append:(Ljava/lang/Object;)Ljava/lang/StringBuilder;
     716: invokevirtual #14                 // Method java/lang/StringBuilder.toString:()Ljava/lang/String;
     719: invokespecial #73                 // Method java/lang/UnsupportedOperationException."<init>":(Ljava/lang/String;)V
     722: athrow
     723: goto          790
     726: astore_3
     727: aload_0
     728: aload_2
     729: invokevirtual #75                 // Method isRollbackSupported:(Lorg/apache/hadoop/hbase/shaded/protobuf/generated/MasterProcedureProtos$EnableTableState;)Z
     732: ifeq          745
     735: aload_0
     736: ldc           #76                 // String master-enable-table
     738: aload_3
     739: invokevirtual #77                 // Method setFailure:(Ljava/lang/String;Ljava/lang/Throwable;)V
     742: goto          790
     745: getstatic     #8                  // Field LOG:Lorg/slf4j/Logger;
     748: new           #9                  // class java/lang/StringBuilder
     751: dup
     752: invokespecial #10                 // Method java/lang/StringBuilder."<init>":()V
     755: ldc           #78                 // String Retriable error trying to enable table=
     757: invokevirtual #13                 // Method java/lang/StringBuilder.append:(Ljava/lang/String;)Ljava/lang/StringBuilder;
     760: aload_0
     761: getfield      #5                  // Field tableName:Lorg/apache/hadoop/hbase/TableName;
     764: invokevirtual #11                 // Method java/lang/StringBuilder.append:(Ljava/lang/Object;)Ljava/lang/StringBuilder;
     767: ldc           #79                 // String  (in state=
     769: invokevirtual #13                 // Method java/lang/StringBuilder.append:(Ljava/lang/String;)Ljava/lang/StringBuilder;
     772: aload_2
     773: invokevirtual #11                 // Method java/lang/StringBuilder.append:(Ljava/lang/Object;)Ljava/lang/StringBuilder;
     776: ldc           #80                 // String )
     778: invokevirtual #13                 // Method java/lang/StringBuilder.append:(Ljava/lang/String;)Ljava/lang/StringBuilder;
     781: invokevirtual #14                 // Method java/lang/StringBuilder.toString:()Ljava/lang/String;
     784: aload_3
     785: invokeinterface #81,  3           // InterfaceMethod org/slf4j/Logger.warn:(Ljava/lang/String;Ljava/lang/Throwable;)V
     790: getstatic     #82                 // Field org/apache/hadoop/hbase/procedure2/StateMachineProcedure$Flow.HAS_MORE_STATE:Lorg/apache/hadoop/hbase/procedure2/StateMachineProcedure$Flow;
     793: areturn
    Exception table:
       from    to  target type
          41   132   726   Class java/io/IOException
         133   695   726   Class java/io/IOException
         696   723   726   Class java/io/IOException

  protected void rollbackState(org.apache.hadoop.hbase.master.procedure.MasterProcedureEnv, org.apache.hadoop.hbase.shaded.protobuf.generated.MasterProcedureProtos$EnableTableState) throws java.io.IOException;
    Code:
       0: getstatic     #16                 // Field org/apache/hadoop/hbase/master/procedure/EnableTableProcedure$1.$SwitchMap$org$apache$hadoop$hbase$shaded$protobuf$generated$MasterProcedureProtos$EnableTableState:[I
       3: aload_2
       4: invokevirtual #17                 // Method org/apache/hadoop/hbase/shaded/protobuf/generated/MasterProcedureProtos$EnableTableState.ordinal:()I
       7: iaload
       8: lookupswitch  { // 2
                     1: 37
                     2: 36
               default: 42
          }
      36: return
      37: aload_0
      38: invokevirtual #95                 // Method releaseSyncLatch:()V
      41: return
      42: new           #71                 // class java/lang/UnsupportedOperationException
      45: dup
      46: new           #9                  // class java/lang/StringBuilder
      49: dup
      50: invokespecial #10                 // Method java/lang/StringBuilder."<init>":()V
      53: ldc           #72                 // String unhandled state=
      55: invokevirtual #13                 // Method java/lang/StringBuilder.append:(Ljava/lang/String;)Ljava/lang/StringBuilder;
      58: aload_2
      59: invokevirtual #11                 // Method java/lang/StringBuilder.append:(Ljava/lang/Object;)Ljava/lang/StringBuilder;
      62: invokevirtual #14                 // Method java/lang/StringBuilder.toString:()Ljava/lang/String;
      65: invokespecial #73                 // Method java/lang/UnsupportedOperationException."<init>":(Ljava/lang/String;)V
      68: athrow

  protected boolean isRollbackSupported(org.apache.hadoop.hbase.shaded.protobuf.generated.MasterProcedureProtos$EnableTableState);
    Code:
       0: getstatic     #16                 // Field org/apache/hadoop/hbase/master/procedure/EnableTableProcedure$1.$SwitchMap$org$apache$hadoop$hbase$shaded$protobuf$generated$MasterProcedureProtos$EnableTableState:[I
       3: aload_1
       4: invokevirtual #17                 // Method org/apache/hadoop/hbase/shaded/protobuf/generated/MasterProcedureProtos$EnableTableState.ordinal:()I
       7: iaload
       8: lookupswitch  { // 2
                     1: 36
                     2: 36
               default: 38
          }
      36: iconst_1
      37: ireturn
      38: iconst_0
      39: ireturn

  protected org.apache.hadoop.hbase.shaded.protobuf.generated.MasterProcedureProtos$EnableTableState getState(int);
    Code:
       0: iload_1
       1: invokestatic  #96                 // Method org/apache/hadoop/hbase/shaded/protobuf/generated/MasterProcedureProtos$EnableTableState.forNumber:(I)Lorg/apache/hadoop/hbase/shaded/protobuf/generated/MasterProcedureProtos$EnableTableState;
       4: areturn

  protected int getStateId(org.apache.hadoop.hbase.shaded.protobuf.generated.MasterProcedureProtos$EnableTableState);
    Code:
       0: aload_1
       1: invokevirtual #97                 // Method org/apache/hadoop/hbase/shaded/protobuf/generated/MasterProcedureProtos$EnableTableState.getNumber:()I
       4: ireturn

  protected org.apache.hadoop.hbase.shaded.protobuf.generated.MasterProcedureProtos$EnableTableState getInitialState();
    Code:
       0: getstatic     #98                 // Field org/apache/hadoop/hbase/shaded/protobuf/generated/MasterProcedureProtos$EnableTableState.ENABLE_TABLE_PREPARE:Lorg/apache/hadoop/hbase/shaded/protobuf/generated/MasterProcedureProtos$EnableTableState;
       3: areturn

  protected void serializeStateData(org.apache.hadoop.hbase.procedure2.ProcedureStateSerializer) throws java.io.IOException;
    Code:
       0: aload_0
       1: aload_1
       2: invokespecial #99                 // Method org/apache/hadoop/hbase/master/procedure/AbstractStateMachineTableProcedure.serializeStateData:(Lorg/apache/hadoop/hbase/procedure2/ProcedureStateSerializer;)V
       5: invokestatic  #100                // Method org/apache/hadoop/hbase/shaded/protobuf/generated/MasterProcedureProtos$EnableTableStateData.newBuilder:()Lorg/apache/hadoop/hbase/shaded/protobuf/generated/MasterProcedureProtos$EnableTableStateData$Builder;
       8: aload_0
       9: invokevirtual #101                // Method getUser:()Lorg/apache/hadoop/hbase/security/User;
      12: invokestatic  #102                // Method org/apache/hadoop/hbase/master/procedure/MasterProcedureUtil.toProtoUserInfo:(Lorg/apache/hadoop/hbase/security/User;)Lorg/apache/hadoop/hbase/shaded/protobuf/generated/RPCProtos$UserInformation;
      15: invokevirtual #103                // Method org/apache/hadoop/hbase/shaded/protobuf/generated/MasterProcedureProtos$EnableTableStateData$Builder.setUserInfo:(Lorg/apache/hadoop/hbase/shaded/protobuf/generated/RPCProtos$UserInformation;)Lorg/apache/hadoop/hbase/shaded/protobuf/generated/MasterProcedureProtos$EnableTableStateData$Builder;
      18: aload_0
      19: getfield      #5                  // Field tableName:Lorg/apache/hadoop/hbase/TableName;
      22: invokestatic  #104                // Method org/apache/hadoop/hbase/shaded/protobuf/ProtobufUtil.toProtoTableName:(Lorg/apache/hadoop/hbase/TableName;)Lorg/apache/hadoop/hbase/shaded/protobuf/generated/HBaseProtos$TableName;
      25: invokevirtual #105                // Method org/apache/hadoop/hbase/shaded/protobuf/generated/MasterProcedureProtos$EnableTableStateData$Builder.setTableName:(Lorg/apache/hadoop/hbase/shaded/protobuf/generated/HBaseProtos$TableName;)Lorg/apache/hadoop/hbase/shaded/protobuf/generated/MasterProcedureProtos$EnableTableStateData$Builder;
      28: iconst_0
      29: invokevirtual #106                // Method org/apache/hadoop/hbase/shaded/protobuf/generated/MasterProcedureProtos$EnableTableStateData$Builder.setSkipTableStateCheck:(Z)Lorg/apache/hadoop/hbase/shaded/protobuf/generated/MasterProcedureProtos$EnableTableStateData$Builder;
      32: astore_2
      33: aload_1
      34: aload_2
      35: invokevirtual #107                // Method org/apache/hadoop/hbase/shaded/protobuf/generated/MasterProcedureProtos$EnableTableStateData$Builder.build:()Lorg/apache/hadoop/hbase/shaded/protobuf/generated/MasterProcedureProtos$EnableTableStateData;
      38: invokeinterface #108,  2          // InterfaceMethod org/apache/hadoop/hbase/procedure2/ProcedureStateSerializer.serialize:(Lorg/apache/hbase/thirdparty/com/google/protobuf/Message;)V
      43: return

  protected void deserializeStateData(org.apache.hadoop.hbase.procedure2.ProcedureStateSerializer) throws java.io.IOException;
    Code:
       0: aload_0
       1: aload_1
       2: invokespecial #109                // Method org/apache/hadoop/hbase/master/procedure/AbstractStateMachineTableProcedure.deserializeStateData:(Lorg/apache/hadoop/hbase/procedure2/ProcedureStateSerializer;)V
       5: aload_1
       6: ldc           #110                // class org/apache/hadoop/hbase/shaded/protobuf/generated/MasterProcedureProtos$EnableTableStateData
       8: invokeinterface #111,  2          // InterfaceMethod org/apache/hadoop/hbase/procedure2/ProcedureStateSerializer.deserialize:(Ljava/lang/Class;)Lorg/apache/hbase/thirdparty/com/google/protobuf/Message;
      13: checkcast     #110                // class org/apache/hadoop/hbase/shaded/protobuf/generated/MasterProcedureProtos$EnableTableStateData
      16: astore_2
      17: aload_0
      18: aload_2
      19: invokevirtual #112                // Method org/apache/hadoop/hbase/shaded/protobuf/generated/MasterProcedureProtos$EnableTableStateData.getUserInfo:()Lorg/apache/hadoop/hbase/shaded/protobuf/generated/RPCProtos$UserInformation;
      22: invokestatic  #113                // Method org/apache/hadoop/hbase/master/procedure/MasterProcedureUtil.toUserInfo:(Lorg/apache/hadoop/hbase/shaded/protobuf/generated/RPCProtos$UserInformation;)Lorg/apache/hadoop/hbase/security/User;
      25: invokevirtual #114                // Method setUser:(Lorg/apache/hadoop/hbase/security/User;)V
      28: aload_0
      29: aload_2
      30: invokevirtual #115                // Method org/apache/hadoop/hbase/shaded/protobuf/generated/MasterProcedureProtos$EnableTableStateData.getTableName:()Lorg/apache/hadoop/hbase/shaded/protobuf/generated/HBaseProtos$TableName;
      33: invokestatic  #116                // Method org/apache/hadoop/hbase/shaded/protobuf/ProtobufUtil.toTableName:(Lorg/apache/hadoop/hbase/shaded/protobuf/generated/HBaseProtos$TableName;)Lorg/apache/hadoop/hbase/TableName;
      36: putfield      #5                  // Field tableName:Lorg/apache/hadoop/hbase/TableName;
      39: return

  public org.apache.hadoop.hbase.TableName getTableName();
    Code:
       0: aload_0
       1: getfield      #5                  // Field tableName:Lorg/apache/hadoop/hbase/TableName;
       4: areturn

  public org.apache.hadoop.hbase.master.procedure.TableProcedureInterface$TableOperationType getTableOperationType();
    Code:
       0: getstatic     #117                // Field org/apache/hadoop/hbase/master/procedure/TableProcedureInterface$TableOperationType.ENABLE:Lorg/apache/hadoop/hbase/master/procedure/TableProcedureInterface$TableOperationType;
       3: areturn

  protected static void setTableStateToEnabling(org.apache.hadoop.hbase.master.procedure.MasterProcedureEnv, org.apache.hadoop.hbase.TableName) throws java.io.IOException;
    Code:
       0: getstatic     #8                  // Field LOG:Lorg/slf4j/Logger;
       3: new           #9                  // class java/lang/StringBuilder
       6: dup
       7: invokespecial #10                 // Method java/lang/StringBuilder."<init>":()V
      10: ldc           #131                // String Attempting to enable the table
      12: invokevirtual #13                 // Method java/lang/StringBuilder.append:(Ljava/lang/String;)Ljava/lang/StringBuilder;
      15: aload_1
      16: invokevirtual #11                 // Method java/lang/StringBuilder.append:(Ljava/lang/Object;)Ljava/lang/StringBuilder;
      19: invokevirtual #14                 // Method java/lang/StringBuilder.toString:()Ljava/lang/String;
      22: invokeinterface #50,  2           // InterfaceMethod org/slf4j/Logger.info:(Ljava/lang/String;)V
      27: aload_0
      28: invokevirtual #31                 // Method org/apache/hadoop/hbase/master/procedure/MasterProcedureEnv.getMasterServices:()Lorg/apache/hadoop/hbase/master/MasterServices;
      31: invokeinterface #121,  1          // InterfaceMethod org/apache/hadoop/hbase/master/MasterServices.getTableStateManager:()Lorg/apache/hadoop/hbase/master/TableStateManager;
      36: aload_1
      37: getstatic     #132                // Field org/apache/hadoop/hbase/client/TableState$State.ENABLING:Lorg/apache/hadoop/hbase/client/TableState$State;
      40: invokevirtual #133                // Method org/apache/hadoop/hbase/master/TableStateManager.setTableState:(Lorg/apache/hadoop/hbase/TableName;Lorg/apache/hadoop/hbase/client/TableState$State;)V
      43: return

  protected static void setTableStateToEnabled(org.apache.hadoop.hbase.master.procedure.MasterProcedureEnv, org.apache.hadoop.hbase.TableName) throws java.io.IOException;
    Code:
       0: aload_0
       1: invokevirtual #31                 // Method org/apache/hadoop/hbase/master/procedure/MasterProcedureEnv.getMasterServices:()Lorg/apache/hadoop/hbase/master/MasterServices;
       4: invokeinterface #121,  1          // InterfaceMethod org/apache/hadoop/hbase/master/MasterServices.getTableStateManager:()Lorg/apache/hadoop/hbase/master/TableStateManager;
       9: aload_1
      10: getstatic     #134                // Field org/apache/hadoop/hbase/client/TableState$State.ENABLED:Lorg/apache/hadoop/hbase/client/TableState$State;
      13: invokevirtual #133                // Method org/apache/hadoop/hbase/master/TableStateManager.setTableState:(Lorg/apache/hadoop/hbase/TableName;Lorg/apache/hadoop/hbase/client/TableState$State;)V
      16: getstatic     #8                  // Field LOG:Lorg/slf4j/Logger;
      19: new           #9                  // class java/lang/StringBuilder
      22: dup
      23: invokespecial #10                 // Method java/lang/StringBuilder."<init>":()V
      26: ldc           #135                // String Table '
      28: invokevirtual #13                 // Method java/lang/StringBuilder.append:(Ljava/lang/String;)Ljava/lang/StringBuilder;
      31: aload_1
      32: invokevirtual #11                 // Method java/lang/StringBuilder.append:(Ljava/lang/Object;)Ljava/lang/StringBuilder;
      35: ldc           #136                // String ' was successfully enabled.
      37: invokevirtual #13                 // Method java/lang/StringBuilder.append:(Ljava/lang/String;)Ljava/lang/StringBuilder;
      40: invokevirtual #14                 // Method java/lang/StringBuilder.toString:()Ljava/lang/String;
      43: invokeinterface #50,  2           // InterfaceMethod org/slf4j/Logger.info:(Ljava/lang/String;)V
      48: return

  protected boolean isRollbackSupported(java.lang.Object);
    Code:
       0: aload_0
       1: aload_1
       2: checkcast     #144                // class org/apache/hadoop/hbase/shaded/protobuf/generated/MasterProcedureProtos$EnableTableState
       5: invokevirtual #75                 // Method isRollbackSupported:(Lorg/apache/hadoop/hbase/shaded/protobuf/generated/MasterProcedureProtos$EnableTableState;)Z
       8: ireturn

  protected java.lang.Object getInitialState();
    Code:
       0: aload_0
       1: invokevirtual #145                // Method getInitialState:()Lorg/apache/hadoop/hbase/shaded/protobuf/generated/MasterProcedureProtos$EnableTableState;
       4: areturn

  protected int getStateId(java.lang.Object);
    Code:
       0: aload_0
       1: aload_1
       2: checkcast     #144                // class org/apache/hadoop/hbase/shaded/protobuf/generated/MasterProcedureProtos$EnableTableState
       5: invokevirtual #146                // Method getStateId:(Lorg/apache/hadoop/hbase/shaded/protobuf/generated/MasterProcedureProtos$EnableTableState;)I
       8: ireturn

  protected java.lang.Object getState(int);
    Code:
       0: aload_0
       1: iload_1
       2: invokevirtual #147                // Method getState:(I)Lorg/apache/hadoop/hbase/shaded/protobuf/generated/MasterProcedureProtos$EnableTableState;
       5: areturn

  protected void rollbackState(java.lang.Object, java.lang.Object) throws java.io.IOException, java.lang.InterruptedException;
    Code:
       0: aload_0
       1: aload_1
       2: checkcast     #148                // class org/apache/hadoop/hbase/master/procedure/MasterProcedureEnv
       5: aload_2
       6: checkcast     #144                // class org/apache/hadoop/hbase/shaded/protobuf/generated/MasterProcedureProtos$EnableTableState
       9: invokevirtual #149                // Method rollbackState:(Lorg/apache/hadoop/hbase/master/procedure/MasterProcedureEnv;Lorg/apache/hadoop/hbase/shaded/protobuf/generated/MasterProcedureProtos$EnableTableState;)V
      12: return

  protected org.apache.hadoop.hbase.procedure2.StateMachineProcedure$Flow executeFromState(java.lang.Object, java.lang.Object) throws org.apache.hadoop.hbase.procedure2.ProcedureSuspendedException, org.apache.hadoop.hbase.procedure2.ProcedureYieldException, java.lang.InterruptedException;
    Code:
       0: aload_0
       1: aload_1
       2: checkcast     #148                // class org/apache/hadoop/hbase/master/procedure/MasterProcedureEnv
       5: aload_2
       6: checkcast     #144                // class org/apache/hadoop/hbase/shaded/protobuf/generated/MasterProcedureProtos$EnableTableState
       9: invokevirtual #150                // Method executeFromState:(Lorg/apache/hadoop/hbase/master/procedure/MasterProcedureEnv;Lorg/apache/hadoop/hbase/shaded/protobuf/generated/MasterProcedureProtos$EnableTableState;)Lorg/apache/hadoop/hbase/procedure2/StateMachineProcedure$Flow;
      12: areturn

  static {};
    Code:
       0: ldc           #151                // class org/apache/hadoop/hbase/master/procedure/EnableTableProcedure
       2: invokevirtual #152                // Method java/lang/Class.desiredAssertionStatus:()Z
       5: ifne          12
       8: iconst_1
       9: goto          13
      12: iconst_0
      13: putstatic     #21                 // Field $assertionsDisabled:Z
      16: ldc           #151                // class org/apache/hadoop/hbase/master/procedure/EnableTableProcedure
      18: invokestatic  #153                // Method org/slf4j/LoggerFactory.getLogger:(Ljava/lang/Class;)Lorg/slf4j/Logger;
      21: putstatic     #8                  // Field LOG:Lorg/slf4j/Logger;
      24: return
}
