Compiled from "EncodedSeekPerformanceTest.java"
public class org.apache.hadoop.hbase.regionserver.EncodedSeekPerformanceTest {
  public static int DEFAULT_NUMBER_OF_SEEKS;

  public org.apache.hadoop.hbase.regionserver.EncodedSeekPerformanceTest();
    Code:
       0: aload_0
       1: invokespecial #1                  // Method java/lang/Object."<init>":()V
       4: aload_0
       5: new           #2                  // class org/apache/hadoop/hbase/HBaseTestingUtility
       8: dup
       9: invokespecial #3                  // Method org/apache/hadoop/hbase/HBaseTestingUtility."<init>":()V
      12: putfield      #4                  // Field testingUtility:Lorg/apache/hadoop/hbase/HBaseTestingUtility;
      15: aload_0
      16: aload_0
      17: getfield      #4                  // Field testingUtility:Lorg/apache/hadoop/hbase/HBaseTestingUtility;
      20: invokevirtual #5                  // Method org/apache/hadoop/hbase/HBaseTestingUtility.getConfiguration:()Lorg/apache/hadoop/conf/Configuration;
      23: putfield      #6                  // Field configuration:Lorg/apache/hadoop/conf/Configuration;
      26: aload_0
      27: new           #7                  // class org/apache/hadoop/hbase/io/hfile/CacheConfig
      30: dup
      31: aload_0
      32: getfield      #6                  // Field configuration:Lorg/apache/hadoop/conf/Configuration;
      35: invokespecial #8                  // Method org/apache/hadoop/hbase/io/hfile/CacheConfig."<init>":(Lorg/apache/hadoop/conf/Configuration;)V
      38: putfield      #9                  // Field cacheConf:Lorg/apache/hadoop/hbase/io/hfile/CacheConfig;
      41: aload_0
      42: getfield      #6                  // Field configuration:Lorg/apache/hadoop/conf/Configuration;
      45: ldc           #11                 // String hfile.block.cache.size
      47: ldc           #12                 // float 0.5f
      49: invokevirtual #13                 // Method org/apache/hadoop/conf/Configuration.setFloat:(Ljava/lang/String;F)V
      52: aload_0
      53: new           #14                 // class java/util/Random
      56: dup
      57: ldc2_w        #15                 // long 42l
      60: invokespecial #17                 // Method java/util/Random."<init>":(J)V
      63: putfield      #18                 // Field randomizer:Ljava/util/Random;
      66: aload_0
      67: getstatic     #19                 // Field DEFAULT_NUMBER_OF_SEEKS:I
      70: putfield      #20                 // Field numberOfSeeks:I
      73: return

  public void runTests(org.apache.hadoop.fs.Path, org.apache.hadoop.hbase.io.encoding.DataBlockEncoding[]) throws java.io.IOException;
    Code:
       0: aload_0
       1: aload_1
       2: invokespecial #79                 // Method prepareListOfTestSeeks:(Lorg/apache/hadoop/fs/Path;)Ljava/util/List;
       5: astore_3
       6: aload_2
       7: astore        4
       9: aload         4
      11: arraylength
      12: istore        5
      14: iconst_0
      15: istore        6
      17: iload         6
      19: iload         5
      21: if_icmpge     45
      24: aload         4
      26: iload         6
      28: aaload
      29: astore        7
      31: aload_0
      32: aload_1
      33: aload         7
      35: aload_3
      36: invokespecial #80                 // Method runTest:(Lorg/apache/hadoop/fs/Path;Lorg/apache/hadoop/hbase/io/encoding/DataBlockEncoding;Ljava/util/List;)V
      39: iinc          6, 1
      42: goto          17
      45: return

  public static void main(java.lang.String[]) throws java.io.IOException;
    Code:
       0: aload_0
       1: arraylength
       2: iconst_1
       3: if_icmpge     13
       6: invokestatic  #81                 // Method printUsage:()V
       9: iconst_m1
      10: invokestatic  #82                 // Method java/lang/System.exit:(I)V
      13: new           #83                 // class org/apache/hadoop/fs/Path
      16: dup
      17: aload_0
      18: iconst_0
      19: aaload
      20: invokespecial #84                 // Method org/apache/hadoop/fs/Path."<init>":(Ljava/lang/String;)V
      23: astore_1
      24: new           #67                 // class org/apache/hadoop/hbase/regionserver/EncodedSeekPerformanceTest
      27: dup
      28: invokespecial #85                 // Method "<init>":()V
      31: astore_2
      32: aload_2
      33: aload_1
      34: invokestatic  #86                 // Method org/apache/hadoop/hbase/io/encoding/DataBlockEncoding.values:()[Lorg/apache/hadoop/hbase/io/encoding/DataBlockEncoding;
      37: invokevirtual #87                 // Method runTests:(Lorg/apache/hadoop/fs/Path;[Lorg/apache/hadoop/hbase/io/encoding/DataBlockEncoding;)V
      40: iconst_0
      41: invokestatic  #82                 // Method java/lang/System.exit:(I)V
      44: return

  static {};
    Code:
       0: sipush        10000
       3: putstatic     #19                 // Field DEFAULT_NUMBER_OF_SEEKS:I
       6: return
}
