Compiled from "EntityLock.java"
public class org.apache.hadoop.hbase.client.locking.EntityLock$LockHeartbeatWorker extends java.lang.Thread {
  final org.apache.hadoop.hbase.client.locking.EntityLock this$0;

  public org.apache.hadoop.hbase.client.locking.EntityLock$LockHeartbeatWorker(org.apache.hadoop.hbase.client.locking.EntityLock, java.lang.String);
    Code:
       0: aload_0
       1: aload_1
       2: putfield      #1                  // Field this$0:Lorg/apache/hadoop/hbase/client/locking/EntityLock;
       5: aload_0
       6: new           #2                  // class java/lang/StringBuilder
       9: dup
      10: invokespecial #3                  // Method java/lang/StringBuilder."<init>":()V
      13: ldc           #4                  // String LockHeartbeatWorker(
      15: invokevirtual #5                  // Method java/lang/StringBuilder.append:(Ljava/lang/String;)Ljava/lang/StringBuilder;
      18: aload_2
      19: invokevirtual #5                  // Method java/lang/StringBuilder.append:(Ljava/lang/String;)Ljava/lang/StringBuilder;
      22: ldc           #6                  // String )
      24: invokevirtual #5                  // Method java/lang/StringBuilder.append:(Ljava/lang/String;)Ljava/lang/StringBuilder;
      27: invokevirtual #7                  // Method java/lang/StringBuilder.toString:()Ljava/lang/String;
      30: invokespecial #8                  // Method java/lang/Thread."<init>":(Ljava/lang/String;)V
      33: aload_0
      34: iconst_0
      35: putfield      #9                  // Field shutdown:Z
      38: aload_0
      39: iconst_1
      40: invokevirtual #10                 // Method setDaemon:(Z)V
      43: return

  java.lang.Thread shutdown();
    Code:
       0: aload_0
       1: iconst_1
       2: putfield      #9                  // Field shutdown:Z
       5: aload_0
       6: invokevirtual #11                 // Method interrupt:()V
       9: aload_0
      10: areturn

  public void run();
    Code:
       0: invokestatic  #12                 // Method org/apache/hadoop/hbase/shaded/protobuf/generated/LockServiceProtos$LockHeartbeatRequest.newBuilder:()Lorg/apache/hadoop/hbase/shaded/protobuf/generated/LockServiceProtos$LockHeartbeatRequest$Builder;
       3: aload_0
       4: getfield      #1                  // Field this$0:Lorg/apache/hadoop/hbase/client/locking/EntityLock;
       7: invokestatic  #13                 // Method org/apache/hadoop/hbase/client/locking/EntityLock.access$000:(Lorg/apache/hadoop/hbase/client/locking/EntityLock;)Ljava/lang/Long;
      10: invokevirtual #14                 // Method java/lang/Long.longValue:()J
      13: invokevirtual #15                 // Method org/apache/hadoop/hbase/shaded/protobuf/generated/LockServiceProtos$LockHeartbeatRequest$Builder.setProcId:(J)Lorg/apache/hadoop/hbase/shaded/protobuf/generated/LockServiceProtos$LockHeartbeatRequest$Builder;
      16: invokevirtual #16                 // Method org/apache/hadoop/hbase/shaded/protobuf/generated/LockServiceProtos$LockHeartbeatRequest$Builder.build:()Lorg/apache/hadoop/hbase/shaded/protobuf/generated/LockServiceProtos$LockHeartbeatRequest;
      19: astore_1
      20: aload_0
      21: getfield      #1                  // Field this$0:Lorg/apache/hadoop/hbase/client/locking/EntityLock;
      24: invokestatic  #17                 // Method org/apache/hadoop/hbase/client/locking/EntityLock.access$100:(Lorg/apache/hadoop/hbase/client/locking/EntityLock;)Lorg/apache/hadoop/hbase/shaded/protobuf/generated/LockServiceProtos$LockService$BlockingInterface;
      27: aconst_null
      28: aload_1
      29: invokeinterface #18,  3           // InterfaceMethod org/apache/hadoop/hbase/shaded/protobuf/generated/LockServiceProtos$LockService$BlockingInterface.lockHeartbeat:(Lorg/apache/hbase/thirdparty/com/google/protobuf/RpcController;Lorg/apache/hadoop/hbase/shaded/protobuf/generated/LockServiceProtos$LockHeartbeatRequest;)Lorg/apache/hadoop/hbase/shaded/protobuf/generated/LockServiceProtos$LockHeartbeatResponse;
      34: astore_2
      35: goto          102
      38: astore_3
      39: aload_3
      40: invokestatic  #20                 // Method org/apache/hadoop/hbase/shaded/protobuf/ProtobufUtil.handleRemoteException:(Ljava/lang/Exception;)Ljava/io/IOException;
      43: astore_3
      44: aload_0
      45: getfield      #1                  // Field this$0:Lorg/apache/hadoop/hbase/client/locking/EntityLock;
      48: invokestatic  #21                 // Method org/apache/hadoop/hbase/client/locking/EntityLock.access$200:(Lorg/apache/hadoop/hbase/client/locking/EntityLock;)Ljava/util/concurrent/atomic/AtomicBoolean;
      51: iconst_0
      52: invokevirtual #22                 // Method java/util/concurrent/atomic/AtomicBoolean.set:(Z)V
      55: invokestatic  #23                 // Method org/apache/hadoop/hbase/client/locking/EntityLock.access$300:()Lorg/slf4j/Logger;
      58: new           #2                  // class java/lang/StringBuilder
      61: dup
      62: invokespecial #3                  // Method java/lang/StringBuilder."<init>":()V
      65: ldc           #24                 // String Heartbeat failed, releasing
      67: invokevirtual #5                  // Method java/lang/StringBuilder.append:(Ljava/lang/String;)Ljava/lang/StringBuilder;
      70: aload_0
      71: getfield      #1                  // Field this$0:Lorg/apache/hadoop/hbase/client/locking/EntityLock;
      74: invokevirtual #25                 // Method java/lang/StringBuilder.append:(Ljava/lang/Object;)Ljava/lang/StringBuilder;
      77: invokevirtual #7                  // Method java/lang/StringBuilder.toString:()Ljava/lang/String;
      80: aload_3
      81: invokeinterface #26,  3           // InterfaceMethod org/slf4j/Logger.error:(Ljava/lang/String;Ljava/lang/Throwable;)V
      86: aload_0
      87: getfield      #1                  // Field this$0:Lorg/apache/hadoop/hbase/client/locking/EntityLock;
      90: invokestatic  #27                 // Method org/apache/hadoop/hbase/client/locking/EntityLock.access$400:(Lorg/apache/hadoop/hbase/client/locking/EntityLock;)Lorg/apache/hadoop/hbase/Abortable;
      93: ldc           #28                 // String Heartbeat failed
      95: aload_3
      96: invokeinterface #29,  3           // InterfaceMethod org/apache/hadoop/hbase/Abortable.abort:(Ljava/lang/String;Ljava/lang/Throwable;)V
     101: return
     102: aload_0
     103: getfield      #1                  // Field this$0:Lorg/apache/hadoop/hbase/client/locking/EntityLock;
     106: invokevirtual #30                 // Method org/apache/hadoop/hbase/client/locking/EntityLock.isLocked:()Z
     109: ifne          146
     112: aload_2
     113: invokevirtual #31                 // Method org/apache/hadoop/hbase/shaded/protobuf/generated/LockServiceProtos$LockHeartbeatResponse.getLockStatus:()Lorg/apache/hadoop/hbase/shaded/protobuf/generated/LockServiceProtos$LockHeartbeatResponse$LockStatus;
     116: getstatic     #32                 // Field org/apache/hadoop/hbase/shaded/protobuf/generated/LockServiceProtos$LockHeartbeatResponse$LockStatus.LOCKED:Lorg/apache/hadoop/hbase/shaded/protobuf/generated/LockServiceProtos$LockHeartbeatResponse$LockStatus;
     119: if_acmpne     146
     122: aload_0
     123: getfield      #1                  // Field this$0:Lorg/apache/hadoop/hbase/client/locking/EntityLock;
     126: invokestatic  #21                 // Method org/apache/hadoop/hbase/client/locking/EntityLock.access$200:(Lorg/apache/hadoop/hbase/client/locking/EntityLock;)Ljava/util/concurrent/atomic/AtomicBoolean;
     129: iconst_1
     130: invokevirtual #22                 // Method java/util/concurrent/atomic/AtomicBoolean.set:(Z)V
     133: aload_0
     134: getfield      #1                  // Field this$0:Lorg/apache/hadoop/hbase/client/locking/EntityLock;
     137: invokestatic  #33                 // Method org/apache/hadoop/hbase/client/locking/EntityLock.access$500:(Lorg/apache/hadoop/hbase/client/locking/EntityLock;)Ljava/util/concurrent/CountDownLatch;
     140: invokevirtual #34                 // Method java/util/concurrent/CountDownLatch.countDown:()V
     143: goto          193
     146: aload_0
     147: getfield      #1                  // Field this$0:Lorg/apache/hadoop/hbase/client/locking/EntityLock;
     150: invokevirtual #30                 // Method org/apache/hadoop/hbase/client/locking/EntityLock.isLocked:()Z
     153: ifeq          193
     156: aload_2
     157: invokevirtual #31                 // Method org/apache/hadoop/hbase/shaded/protobuf/generated/LockServiceProtos$LockHeartbeatResponse.getLockStatus:()Lorg/apache/hadoop/hbase/shaded/protobuf/generated/LockServiceProtos$LockHeartbeatResponse$LockStatus;
     160: getstatic     #35                 // Field org/apache/hadoop/hbase/shaded/protobuf/generated/LockServiceProtos$LockHeartbeatResponse$LockStatus.UNLOCKED:Lorg/apache/hadoop/hbase/shaded/protobuf/generated/LockServiceProtos$LockHeartbeatResponse$LockStatus;
     163: if_acmpne     193
     166: aload_0
     167: getfield      #1                  // Field this$0:Lorg/apache/hadoop/hbase/client/locking/EntityLock;
     170: invokestatic  #21                 // Method org/apache/hadoop/hbase/client/locking/EntityLock.access$200:(Lorg/apache/hadoop/hbase/client/locking/EntityLock;)Ljava/util/concurrent/atomic/AtomicBoolean;
     173: iconst_0
     174: invokevirtual #22                 // Method java/util/concurrent/atomic/AtomicBoolean.set:(Z)V
     177: aload_0
     178: getfield      #1                  // Field this$0:Lorg/apache/hadoop/hbase/client/locking/EntityLock;
     181: invokestatic  #27                 // Method org/apache/hadoop/hbase/client/locking/EntityLock.access$400:(Lorg/apache/hadoop/hbase/client/locking/EntityLock;)Lorg/apache/hadoop/hbase/Abortable;
     184: ldc           #36                 // String Lock timed out.
     186: aconst_null
     187: invokeinterface #29,  3           // InterfaceMethod org/apache/hadoop/hbase/Abortable.abort:(Ljava/lang/String;Ljava/lang/Throwable;)V
     192: return
     193: ldc2_w        #37                 // long 1000l
     196: lstore_3
     197: aload_0
     198: getfield      #1                  // Field this$0:Lorg/apache/hadoop/hbase/client/locking/EntityLock;
     201: invokevirtual #30                 // Method org/apache/hadoop/hbase/client/locking/EntityLock.isLocked:()Z
     204: ifeq          225
     207: aload_2
     208: invokevirtual #39                 // Method org/apache/hadoop/hbase/shaded/protobuf/generated/LockServiceProtos$LockHeartbeatResponse.getTimeoutMs:()I
     211: aload_0
     212: getfield      #1                  // Field this$0:Lorg/apache/hadoop/hbase/client/locking/EntityLock;
     215: invokestatic  #40                 // Method org/apache/hadoop/hbase/client/locking/EntityLock.access$600:(Lorg/apache/hadoop/hbase/client/locking/EntityLock;)I
     218: isub
     219: iconst_1
     220: invokestatic  #41                 // Method java/lang/Math.max:(II)I
     223: i2l
     224: lstore_3
     225: aload_0
     226: getfield      #1                  // Field this$0:Lorg/apache/hadoop/hbase/client/locking/EntityLock;
     229: invokestatic  #42                 // Method org/apache/hadoop/hbase/client/locking/EntityLock.access$700:(Lorg/apache/hadoop/hbase/client/locking/EntityLock;)J
     232: lconst_0
     233: lcmp
     234: ifeq          245
     237: aload_0
     238: getfield      #1                  // Field this$0:Lorg/apache/hadoop/hbase/client/locking/EntityLock;
     241: invokestatic  #42                 // Method org/apache/hadoop/hbase/client/locking/EntityLock.access$700:(Lorg/apache/hadoop/hbase/client/locking/EntityLock;)J
     244: lstore_3
     245: lload_3
     246: invokestatic  #43                 // Method java/lang/Thread.sleep:(J)V
     249: goto          20
     252: astore_3
     253: aload_0
     254: getfield      #1                  // Field this$0:Lorg/apache/hadoop/hbase/client/locking/EntityLock;
     257: invokestatic  #21                 // Method org/apache/hadoop/hbase/client/locking/EntityLock.access$200:(Lorg/apache/hadoop/hbase/client/locking/EntityLock;)Ljava/util/concurrent/atomic/AtomicBoolean;
     260: iconst_0
     261: invokevirtual #22                 // Method java/util/concurrent/atomic/AtomicBoolean.set:(Z)V
     264: aload_0
     265: getfield      #9                  // Field shutdown:Z
     268: ifne          314
     271: invokestatic  #23                 // Method org/apache/hadoop/hbase/client/locking/EntityLock.access$300:()Lorg/slf4j/Logger;
     274: new           #2                  // class java/lang/StringBuilder
     277: dup
     278: invokespecial #3                  // Method java/lang/StringBuilder."<init>":()V
     281: ldc           #45                 // String Interrupted, releasing
     283: invokevirtual #5                  // Method java/lang/StringBuilder.append:(Ljava/lang/String;)Ljava/lang/StringBuilder;
     286: aload_0
     287: invokevirtual #25                 // Method java/lang/StringBuilder.append:(Ljava/lang/Object;)Ljava/lang/StringBuilder;
     290: invokevirtual #7                  // Method java/lang/StringBuilder.toString:()Ljava/lang/String;
     293: aload_3
     294: invokeinterface #26,  3           // InterfaceMethod org/slf4j/Logger.error:(Ljava/lang/String;Ljava/lang/Throwable;)V
     299: aload_0
     300: getfield      #1                  // Field this$0:Lorg/apache/hadoop/hbase/client/locking/EntityLock;
     303: invokestatic  #27                 // Method org/apache/hadoop/hbase/client/locking/EntityLock.access$400:(Lorg/apache/hadoop/hbase/client/locking/EntityLock;)Lorg/apache/hadoop/hbase/Abortable;
     306: ldc           #46                 // String Worker thread interrupted
     308: aload_3
     309: invokeinterface #29,  3           // InterfaceMethod org/apache/hadoop/hbase/Abortable.abort:(Ljava/lang/String;Ljava/lang/Throwable;)V
     314: return
    Exception table:
       from    to  target type
          20    35    38   Class java/lang/Exception
         193   249   252   Class java/lang/InterruptedException
}
