Compiled from "EventHandler.java"
public abstract class org.apache.hadoop.hbase.executor.EventHandler implements java.lang.Runnable, java.lang.Comparable<java.lang.Runnable> {
  protected org.apache.hadoop.hbase.executor.EventType eventType;

  protected org.apache.hadoop.hbase.Server server;

  protected static final java.util.concurrent.atomic.AtomicLong seqids;

  protected int waitingTimeForEvents;

  public org.apache.hadoop.hbase.executor.EventHandler(org.apache.hadoop.hbase.Server, org.apache.hadoop.hbase.executor.EventType);
    Code:
       0: aload_0
       1: invokespecial #1                  // Method java/lang/Object."<init>":()V
       4: aload_0
       5: invokestatic  #2                  // Method org/apache/htrace/core/Tracer.getCurrentSpan:()Lorg/apache/htrace/core/Span;
       8: putfield      #3                  // Field parent:Lorg/apache/htrace/core/Span;
      11: aload_0
      12: aload_1
      13: putfield      #4                  // Field server:Lorg/apache/hadoop/hbase/Server;
      16: aload_0
      17: aload_2
      18: putfield      #5                  // Field eventType:Lorg/apache/hadoop/hbase/executor/EventType;
      21: aload_0
      22: getstatic     #6                  // Field seqids:Ljava/util/concurrent/atomic/AtomicLong;
      25: invokevirtual #7                  // Method java/util/concurrent/atomic/AtomicLong.incrementAndGet:()J
      28: putfield      #8                  // Field seqid:J
      31: aload_1
      32: ifnull        53
      35: aload_0
      36: aload_1
      37: invokeinterface #9,  1            // InterfaceMethod org/apache/hadoop/hbase/Server.getConfiguration:()Lorg/apache/hadoop/conf/Configuration;
      42: ldc           #10                 // String hbase.master.event.waiting.time
      44: sipush        1000
      47: invokevirtual #11                 // Method org/apache/hadoop/conf/Configuration.getInt:(Ljava/lang/String;I)I
      50: putfield      #12                 // Field waitingTimeForEvents:I
      53: return

  public org.apache.hadoop.hbase.executor.EventHandler prepare() throws java.lang.Exception;
    Code:
       0: aload_0
       1: areturn

  public void run();
    Code:
       0: aload_0
       1: invokevirtual #13                 // Method java/lang/Object.getClass:()Ljava/lang/Class;
       4: invokevirtual #14                 // Method java/lang/Class.getSimpleName:()Ljava/lang/String;
       7: aload_0
       8: getfield      #3                  // Field parent:Lorg/apache/htrace/core/Span;
      11: invokestatic  #15                 // Method org/apache/hadoop/hbase/trace/TraceUtil.createTrace:(Ljava/lang/String;Lorg/apache/htrace/core/Span;)Lorg/apache/htrace/core/TraceScope;
      14: astore_1
      15: aconst_null
      16: astore_2
      17: aload_0
      18: invokevirtual #16                 // Method process:()V
      21: aload_1
      22: ifnull        92
      25: aload_2
      26: ifnull        45
      29: aload_1
      30: invokevirtual #17                 // Method org/apache/htrace/core/TraceScope.close:()V
      33: goto          92
      36: astore_3
      37: aload_2
      38: aload_3
      39: invokevirtual #19                 // Method java/lang/Throwable.addSuppressed:(Ljava/lang/Throwable;)V
      42: goto          92
      45: aload_1
      46: invokevirtual #17                 // Method org/apache/htrace/core/TraceScope.close:()V
      49: goto          92
      52: astore_3
      53: aload_3
      54: astore_2
      55: aload_3
      56: athrow
      57: astore        4
      59: aload_1
      60: ifnull        89
      63: aload_2
      64: ifnull        85
      67: aload_1
      68: invokevirtual #17                 // Method org/apache/htrace/core/TraceScope.close:()V
      71: goto          89
      74: astore        5
      76: aload_2
      77: aload         5
      79: invokevirtual #19                 // Method java/lang/Throwable.addSuppressed:(Ljava/lang/Throwable;)V
      82: goto          89
      85: aload_1
      86: invokevirtual #17                 // Method org/apache/htrace/core/TraceScope.close:()V
      89: aload         4
      91: athrow
      92: goto          101
      95: astore_1
      96: aload_0
      97: aload_1
      98: invokevirtual #20                 // Method handleException:(Ljava/lang/Throwable;)V
     101: return
    Exception table:
       from    to  target type
          29    33    36   Class java/lang/Throwable
          17    21    52   Class java/lang/Throwable
          17    21    57   any
          67    71    74   Class java/lang/Throwable
          52    59    57   any
           0    92    95   Class java/lang/Throwable

  public abstract void process() throws java.io.IOException;

  public org.apache.hadoop.hbase.executor.EventType getEventType();
    Code:
       0: aload_0
       1: getfield      #5                  // Field eventType:Lorg/apache/hadoop/hbase/executor/EventType;
       4: areturn

  public int getPriority();
    Code:
       0: ldc           #22                 // int 2147483647
       2: ireturn

  public long getSeqid();
    Code:
       0: aload_0
       1: getfield      #8                  // Field seqid:J
       4: lreturn

  public int compareTo(java.lang.Runnable);
    Code:
       0: aload_1
       1: checkcast     #23                 // class org/apache/hadoop/hbase/executor/EventHandler
       4: astore_2
       5: aload_0
       6: invokevirtual #24                 // Method getPriority:()I
       9: aload_2
      10: invokevirtual #24                 // Method getPriority:()I
      13: if_icmpeq     33
      16: aload_0
      17: invokevirtual #24                 // Method getPriority:()I
      20: aload_2
      21: invokevirtual #24                 // Method getPriority:()I
      24: if_icmpge     31
      27: iconst_m1
      28: goto          32
      31: iconst_1
      32: ireturn
      33: aload_0
      34: getfield      #8                  // Field seqid:J
      37: aload_2
      38: getfield      #8                  // Field seqid:J
      41: lcmp
      42: ifge          49
      45: iconst_m1
      46: goto          50
      49: iconst_1
      50: ireturn

  public java.lang.String toString();
    Code:
       0: new           #25                 // class java/lang/StringBuilder
       3: dup
       4: invokespecial #26                 // Method java/lang/StringBuilder."<init>":()V
       7: ldc           #27                 // String Event #
       9: invokevirtual #28                 // Method java/lang/StringBuilder.append:(Ljava/lang/String;)Ljava/lang/StringBuilder;
      12: aload_0
      13: invokevirtual #29                 // Method getSeqid:()J
      16: invokevirtual #30                 // Method java/lang/StringBuilder.append:(J)Ljava/lang/StringBuilder;
      19: ldc           #31                 // String  of type
      21: invokevirtual #28                 // Method java/lang/StringBuilder.append:(Ljava/lang/String;)Ljava/lang/StringBuilder;
      24: aload_0
      25: getfield      #5                  // Field eventType:Lorg/apache/hadoop/hbase/executor/EventType;
      28: invokevirtual #32                 // Method java/lang/StringBuilder.append:(Ljava/lang/Object;)Ljava/lang/StringBuilder;
      31: ldc           #33                 // String  (
      33: invokevirtual #28                 // Method java/lang/StringBuilder.append:(Ljava/lang/String;)Ljava/lang/StringBuilder;
      36: aload_0
      37: invokevirtual #34                 // Method getInformativeName:()Ljava/lang/String;
      40: invokevirtual #28                 // Method java/lang/StringBuilder.append:(Ljava/lang/String;)Ljava/lang/StringBuilder;
      43: ldc           #35                 // String )
      45: invokevirtual #28                 // Method java/lang/StringBuilder.append:(Ljava/lang/String;)Ljava/lang/StringBuilder;
      48: invokevirtual #36                 // Method java/lang/StringBuilder.toString:()Ljava/lang/String;
      51: areturn

  public java.lang.String getInformativeName();
    Code:
       0: aload_0
       1: invokevirtual #13                 // Method java/lang/Object.getClass:()Ljava/lang/Class;
       4: invokevirtual #37                 // Method java/lang/Class.toString:()Ljava/lang/String;
       7: areturn

  protected void handleException(java.lang.Throwable);
    Code:
       0: new           #25                 // class java/lang/StringBuilder
       3: dup
       4: invokespecial #26                 // Method java/lang/StringBuilder."<init>":()V
       7: ldc           #38                 // String Caught throwable while processing event
       9: invokevirtual #28                 // Method java/lang/StringBuilder.append:(Ljava/lang/String;)Ljava/lang/StringBuilder;
      12: aload_0
      13: getfield      #5                  // Field eventType:Lorg/apache/hadoop/hbase/executor/EventType;
      16: invokevirtual #32                 // Method java/lang/StringBuilder.append:(Ljava/lang/Object;)Ljava/lang/StringBuilder;
      19: invokevirtual #36                 // Method java/lang/StringBuilder.toString:()Ljava/lang/String;
      22: astore_2
      23: getstatic     #39                 // Field LOG:Lorg/slf4j/Logger;
      26: aload_2
      27: aload_1
      28: invokeinterface #40,  3           // InterfaceMethod org/slf4j/Logger.error:(Ljava/lang/String;Ljava/lang/Throwable;)V
      33: aload_0
      34: getfield      #4                  // Field server:Lorg/apache/hadoop/hbase/Server;
      37: ifnull        65
      40: aload_1
      41: instanceof    #41                 // class java/lang/Error
      44: ifne          54
      47: aload_1
      48: instanceof    #42                 // class java/lang/RuntimeException
      51: ifeq          65
      54: aload_0
      55: getfield      #4                  // Field server:Lorg/apache/hadoop/hbase/Server;
      58: aload_2
      59: aload_1
      60: invokeinterface #43,  3           // InterfaceMethod org/apache/hadoop/hbase/Server.abort:(Ljava/lang/String;Ljava/lang/Throwable;)V
      65: return

  public int compareTo(java.lang.Object);
    Code:
       0: aload_0
       1: aload_1
       2: checkcast     #44                 // class java/lang/Runnable
       5: invokevirtual #45                 // Method compareTo:(Ljava/lang/Runnable;)I
       8: ireturn

  static {};
    Code:
       0: ldc           #23                 // class org/apache/hadoop/hbase/executor/EventHandler
       2: invokestatic  #46                 // Method org/slf4j/LoggerFactory.getLogger:(Ljava/lang/Class;)Lorg/slf4j/Logger;
       5: putstatic     #39                 // Field LOG:Lorg/slf4j/Logger;
       8: new           #47                 // class java/util/concurrent/atomic/AtomicLong
      11: dup
      12: lconst_0
      13: invokespecial #48                 // Method java/util/concurrent/atomic/AtomicLong."<init>":(J)V
      16: putstatic     #6                  // Field seqids:Ljava/util/concurrent/atomic/AtomicLong;
      19: return
}
