Compiled from "ExclusiveMemoryMmapIOEngine.java"
public class org.apache.hadoop.hbase.io.hfile.bucket.ExclusiveMemoryMmapIOEngine extends org.apache.hadoop.hbase.io.hfile.bucket.FileMmapIOEngine {
  static final org.slf4j.Logger LOG;

  public org.apache.hadoop.hbase.io.hfile.bucket.ExclusiveMemoryMmapIOEngine(java.lang.String, long) throws java.io.IOException;
    Code:
       0: aload_0
       1: aload_1
       2: lload_2
       3: invokespecial #1                  // Method org/apache/hadoop/hbase/io/hfile/bucket/FileMmapIOEngine."<init>":(Ljava/lang/String;J)V
       6: return

  public org.apache.hadoop.hbase.io.hfile.Cacheable read(long, int, org.apache.hadoop.hbase.io.hfile.CacheableDeserializer<org.apache.hadoop.hbase.io.hfile.Cacheable>) throws java.io.IOException;
    Code:
       0: iload_3
       1: newarray       byte
       3: astore        5
       5: aload_0
       6: getfield      #2                  // Field bufferArray:Lorg/apache/hadoop/hbase/util/ByteBufferArray;
       9: lload_1
      10: iload_3
      11: aload         5
      13: invokevirtual #3                  // Method org/apache/hadoop/hbase/util/ByteBufferArray.getMultiple:(JI[B)I
      16: pop
      17: aload         4
      19: new           #4                  // class org/apache/hadoop/hbase/nio/SingleByteBuff
      22: dup
      23: aload         5
      25: invokestatic  #5                  // Method java/nio/ByteBuffer.wrap:([B)Ljava/nio/ByteBuffer;
      28: invokespecial #6                  // Method org/apache/hadoop/hbase/nio/SingleByteBuff."<init>":(Ljava/nio/ByteBuffer;)V
      31: iconst_1
      32: getstatic     #7                  // Field org/apache/hadoop/hbase/io/hfile/Cacheable$MemoryType.EXCLUSIVE:Lorg/apache/hadoop/hbase/io/hfile/Cacheable$MemoryType;
      35: invokeinterface #8,  4            // InterfaceMethod org/apache/hadoop/hbase/io/hfile/CacheableDeserializer.deserialize:(Lorg/apache/hadoop/hbase/nio/ByteBuff;ZLorg/apache/hadoop/hbase/io/hfile/Cacheable$MemoryType;)Lorg/apache/hadoop/hbase/io/hfile/Cacheable;
      40: areturn

  static {};
    Code:
       0: ldc           #9                  // class org/apache/hadoop/hbase/io/hfile/bucket/ExclusiveMemoryMmapIOEngine
       2: invokestatic  #10                 // Method org/slf4j/LoggerFactory.getLogger:(Ljava/lang/Class;)Lorg/slf4j/Logger;
       5: putstatic     #11                 // Field LOG:Lorg/slf4j/Logger;
       8: return
}
