Compiled from "ExecutorService.java"
public class org.apache.hadoop.hbase.executor.ExecutorService$ExecutorStatus {
  final org.apache.hadoop.hbase.executor.ExecutorService$Executor executor;

  final java.util.List<org.apache.hadoop.hbase.executor.EventHandler> queuedEvents;

  final java.util.List<org.apache.hadoop.hbase.executor.ExecutorService$RunningEventStatus> running;

  org.apache.hadoop.hbase.executor.ExecutorService$ExecutorStatus(org.apache.hadoop.hbase.executor.ExecutorService$Executor, java.util.List<org.apache.hadoop.hbase.executor.EventHandler>, java.util.List<org.apache.hadoop.hbase.executor.ExecutorService$RunningEventStatus>);
    Code:
       0: aload_0
       1: invokespecial #1                  // Method java/lang/Object."<init>":()V
       4: aload_0
       5: aload_1
       6: putfield      #2                  // Field executor:Lorg/apache/hadoop/hbase/executor/ExecutorService$Executor;
       9: aload_0
      10: aload_2
      11: putfield      #3                  // Field queuedEvents:Ljava/util/List;
      14: aload_0
      15: aload_3
      16: putfield      #4                  // Field running:Ljava/util/List;
      19: return

  public void dumpTo(java.io.Writer, java.lang.String) throws java.io.IOException;
    Code:
       0: aload_1
       1: new           #5                  // class java/lang/StringBuilder
       4: dup
       5: invokespecial #6                  // Method java/lang/StringBuilder."<init>":()V
       8: aload_2
       9: invokevirtual #7                  // Method java/lang/StringBuilder.append:(Ljava/lang/String;)Ljava/lang/StringBuilder;
      12: ldc           #8                  // String Status for executor:
      14: invokevirtual #7                  // Method java/lang/StringBuilder.append:(Ljava/lang/String;)Ljava/lang/StringBuilder;
      17: aload_0
      18: getfield      #2                  // Field executor:Lorg/apache/hadoop/hbase/executor/ExecutorService$Executor;
      21: invokevirtual #9                  // Method java/lang/StringBuilder.append:(Ljava/lang/Object;)Ljava/lang/StringBuilder;
      24: ldc           #10                 // String \n
      26: invokevirtual #7                  // Method java/lang/StringBuilder.append:(Ljava/lang/String;)Ljava/lang/StringBuilder;
      29: invokevirtual #11                 // Method java/lang/StringBuilder.toString:()Ljava/lang/String;
      32: invokevirtual #12                 // Method java/io/Writer.write:(Ljava/lang/String;)V
      35: aload_1
      36: new           #5                  // class java/lang/StringBuilder
      39: dup
      40: invokespecial #6                  // Method java/lang/StringBuilder."<init>":()V
      43: aload_2
      44: invokevirtual #7                  // Method java/lang/StringBuilder.append:(Ljava/lang/String;)Ljava/lang/StringBuilder;
      47: ldc           #13                 // String =======================================\n
      49: invokevirtual #7                  // Method java/lang/StringBuilder.append:(Ljava/lang/String;)Ljava/lang/StringBuilder;
      52: invokevirtual #11                 // Method java/lang/StringBuilder.toString:()Ljava/lang/String;
      55: invokevirtual #12                 // Method java/io/Writer.write:(Ljava/lang/String;)V
      58: aload_1
      59: new           #5                  // class java/lang/StringBuilder
      62: dup
      63: invokespecial #6                  // Method java/lang/StringBuilder."<init>":()V
      66: aload_2
      67: invokevirtual #7                  // Method java/lang/StringBuilder.append:(Ljava/lang/String;)Ljava/lang/StringBuilder;
      70: aload_0
      71: getfield      #3                  // Field queuedEvents:Ljava/util/List;
      74: invokeinterface #14,  1           // InterfaceMethod java/util/List.size:()I
      79: invokevirtual #15                 // Method java/lang/StringBuilder.append:(I)Ljava/lang/StringBuilder;
      82: ldc           #16                 // String  events queued,
      84: invokevirtual #7                  // Method java/lang/StringBuilder.append:(Ljava/lang/String;)Ljava/lang/StringBuilder;
      87: aload_0
      88: getfield      #4                  // Field running:Ljava/util/List;
      91: invokeinterface #14,  1           // InterfaceMethod java/util/List.size:()I
      96: invokevirtual #15                 // Method java/lang/StringBuilder.append:(I)Ljava/lang/StringBuilder;
      99: ldc           #17                 // String  running\n
     101: invokevirtual #7                  // Method java/lang/StringBuilder.append:(Ljava/lang/String;)Ljava/lang/StringBuilder;
     104: invokevirtual #11                 // Method java/lang/StringBuilder.toString:()Ljava/lang/String;
     107: invokevirtual #12                 // Method java/io/Writer.write:(Ljava/lang/String;)V
     110: aload_0
     111: getfield      #3                  // Field queuedEvents:Ljava/util/List;
     114: invokeinterface #18,  1           // InterfaceMethod java/util/List.isEmpty:()Z
     119: ifne          217
     122: aload_1
     123: new           #5                  // class java/lang/StringBuilder
     126: dup
     127: invokespecial #6                  // Method java/lang/StringBuilder."<init>":()V
     130: aload_2
     131: invokevirtual #7                  // Method java/lang/StringBuilder.append:(Ljava/lang/String;)Ljava/lang/StringBuilder;
     134: ldc           #19                 // String Queued:\n
     136: invokevirtual #7                  // Method java/lang/StringBuilder.append:(Ljava/lang/String;)Ljava/lang/StringBuilder;
     139: invokevirtual #11                 // Method java/lang/StringBuilder.toString:()Ljava/lang/String;
     142: invokevirtual #12                 // Method java/io/Writer.write:(Ljava/lang/String;)V
     145: aload_0
     146: getfield      #3                  // Field queuedEvents:Ljava/util/List;
     149: invokeinterface #20,  1           // InterfaceMethod java/util/List.iterator:()Ljava/util/Iterator;
     154: astore_3
     155: aload_3
     156: invokeinterface #21,  1           // InterfaceMethod java/util/Iterator.hasNext:()Z
     161: ifeq          211
     164: aload_3
     165: invokeinterface #22,  1           // InterfaceMethod java/util/Iterator.next:()Ljava/lang/Object;
     170: checkcast     #23                 // class org/apache/hadoop/hbase/executor/EventHandler
     173: astore        4
     175: aload_1
     176: new           #5                  // class java/lang/StringBuilder
     179: dup
     180: invokespecial #6                  // Method java/lang/StringBuilder."<init>":()V
     183: aload_2
     184: invokevirtual #7                  // Method java/lang/StringBuilder.append:(Ljava/lang/String;)Ljava/lang/StringBuilder;
     187: ldc           #24                 // String
     189: invokevirtual #7                  // Method java/lang/StringBuilder.append:(Ljava/lang/String;)Ljava/lang/StringBuilder;
     192: aload         4
     194: invokevirtual #9                  // Method java/lang/StringBuilder.append:(Ljava/lang/Object;)Ljava/lang/StringBuilder;
     197: ldc           #10                 // String \n
     199: invokevirtual #7                  // Method java/lang/StringBuilder.append:(Ljava/lang/String;)Ljava/lang/StringBuilder;
     202: invokevirtual #11                 // Method java/lang/StringBuilder.toString:()Ljava/lang/String;
     205: invokevirtual #12                 // Method java/io/Writer.write:(Ljava/lang/String;)V
     208: goto          155
     211: aload_1
     212: ldc           #10                 // String \n
     214: invokevirtual #12                 // Method java/io/Writer.write:(Ljava/lang/String;)V
     217: aload_0
     218: getfield      #4                  // Field running:Ljava/util/List;
     221: invokeinterface #18,  1           // InterfaceMethod java/util/List.isEmpty:()Z
     226: ifne          374
     229: aload_1
     230: new           #5                  // class java/lang/StringBuilder
     233: dup
     234: invokespecial #6                  // Method java/lang/StringBuilder."<init>":()V
     237: aload_2
     238: invokevirtual #7                  // Method java/lang/StringBuilder.append:(Ljava/lang/String;)Ljava/lang/StringBuilder;
     241: ldc           #25                 // String Running:\n
     243: invokevirtual #7                  // Method java/lang/StringBuilder.append:(Ljava/lang/String;)Ljava/lang/StringBuilder;
     246: invokevirtual #11                 // Method java/lang/StringBuilder.toString:()Ljava/lang/String;
     249: invokevirtual #12                 // Method java/io/Writer.write:(Ljava/lang/String;)V
     252: aload_0
     253: getfield      #4                  // Field running:Ljava/util/List;
     256: invokeinterface #20,  1           // InterfaceMethod java/util/List.iterator:()Ljava/util/Iterator;
     261: astore_3
     262: aload_3
     263: invokeinterface #21,  1           // InterfaceMethod java/util/Iterator.hasNext:()Z
     268: ifeq          374
     271: aload_3
     272: invokeinterface #22,  1           // InterfaceMethod java/util/Iterator.next:()Ljava/lang/Object;
     277: checkcast     #26                 // class org/apache/hadoop/hbase/executor/ExecutorService$RunningEventStatus
     280: astore        4
     282: aload_1
     283: new           #5                  // class java/lang/StringBuilder
     286: dup
     287: invokespecial #6                  // Method java/lang/StringBuilder."<init>":()V
     290: aload_2
     291: invokevirtual #7                  // Method java/lang/StringBuilder.append:(Ljava/lang/String;)Ljava/lang/StringBuilder;
     294: ldc           #27                 // String   Running on thread '
     296: invokevirtual #7                  // Method java/lang/StringBuilder.append:(Ljava/lang/String;)Ljava/lang/StringBuilder;
     299: aload         4
     301: getfield      #28                 // Field org/apache/hadoop/hbase/executor/ExecutorService$RunningEventStatus.threadInfo:Ljava/lang/management/ThreadInfo;
     304: invokevirtual #29                 // Method java/lang/management/ThreadInfo.getThreadName:()Ljava/lang/String;
     307: invokevirtual #7                  // Method java/lang/StringBuilder.append:(Ljava/lang/String;)Ljava/lang/StringBuilder;
     310: ldc           #30                 // String ':
     312: invokevirtual #7                  // Method java/lang/StringBuilder.append:(Ljava/lang/String;)Ljava/lang/StringBuilder;
     315: aload         4
     317: getfield      #31                 // Field org/apache/hadoop/hbase/executor/ExecutorService$RunningEventStatus.event:Lorg/apache/hadoop/hbase/executor/EventHandler;
     320: invokevirtual #9                  // Method java/lang/StringBuilder.append:(Ljava/lang/Object;)Ljava/lang/StringBuilder;
     323: ldc           #10                 // String \n
     325: invokevirtual #7                  // Method java/lang/StringBuilder.append:(Ljava/lang/String;)Ljava/lang/StringBuilder;
     328: invokevirtual #11                 // Method java/lang/StringBuilder.toString:()Ljava/lang/String;
     331: invokevirtual #12                 // Method java/io/Writer.write:(Ljava/lang/String;)V
     334: aload_1
     335: aload         4
     337: getfield      #28                 // Field org/apache/hadoop/hbase/executor/ExecutorService$RunningEventStatus.threadInfo:Ljava/lang/management/ThreadInfo;
     340: new           #5                  // class java/lang/StringBuilder
     343: dup
     344: invokespecial #6                  // Method java/lang/StringBuilder."<init>":()V
     347: aload_2
     348: invokevirtual #7                  // Method java/lang/StringBuilder.append:(Ljava/lang/String;)Ljava/lang/StringBuilder;
     351: ldc           #24                 // String
     353: invokevirtual #7                  // Method java/lang/StringBuilder.append:(Ljava/lang/String;)Ljava/lang/StringBuilder;
     356: invokevirtual #11                 // Method java/lang/StringBuilder.toString:()Ljava/lang/String;
     359: invokestatic  #32                 // Method org/apache/hadoop/hbase/monitoring/ThreadMonitoring.formatThreadInfo:(Ljava/lang/management/ThreadInfo;Ljava/lang/String;)Ljava/lang/String;
     362: invokevirtual #12                 // Method java/io/Writer.write:(Ljava/lang/String;)V
     365: aload_1
     366: ldc           #10                 // String \n
     368: invokevirtual #12                 // Method java/io/Writer.write:(Ljava/lang/String;)V
     371: goto          262
     374: aload_1
     375: invokevirtual #33                 // Method java/io/Writer.flush:()V
     378: return
}
