Compiled from "ExecutorService.java"
class org.apache.hadoop.hbase.executor.ExecutorService$Executor {
  static final long keepAliveTimeInMillis;

  final org.apache.hadoop.hbase.executor.ExecutorService$TrackingThreadPoolExecutor threadPoolExecutor;

  final java.util.concurrent.BlockingQueue<java.lang.Runnable> q;

  protected org.apache.hadoop.hbase.executor.ExecutorService$Executor(java.lang.String, int);
    Code:
       0: aload_0
       1: invokespecial #1                  // Method java/lang/Object."<init>":()V
       4: aload_0
       5: new           #2                  // class java/util/concurrent/LinkedBlockingQueue
       8: dup
       9: invokespecial #3                  // Method java/util/concurrent/LinkedBlockingQueue."<init>":()V
      12: putfield      #4                  // Field q:Ljava/util/concurrent/BlockingQueue;
      15: aload_0
      16: getstatic     #5                  // Field seqids:Ljava/util/concurrent/atomic/AtomicLong;
      19: invokevirtual #6                  // Method java/util/concurrent/atomic/AtomicLong.incrementAndGet:()J
      22: putfield      #7                  // Field id:J
      25: aload_0
      26: aload_1
      27: putfield      #8                  // Field name:Ljava/lang/String;
      30: aload_0
      31: new           #9                  // class org/apache/hadoop/hbase/executor/ExecutorService$TrackingThreadPoolExecutor
      34: dup
      35: iload_2
      36: iload_2
      37: ldc2_w        #11                 // long 1000l
      40: getstatic     #13                 // Field java/util/concurrent/TimeUnit.MILLISECONDS:Ljava/util/concurrent/TimeUnit;
      43: aload_0
      44: getfield      #4                  // Field q:Ljava/util/concurrent/BlockingQueue;
      47: invokespecial #14                 // Method org/apache/hadoop/hbase/executor/ExecutorService$TrackingThreadPoolExecutor."<init>":(IIJLjava/util/concurrent/TimeUnit;Ljava/util/concurrent/BlockingQueue;)V
      50: putfield      #15                 // Field threadPoolExecutor:Lorg/apache/hadoop/hbase/executor/ExecutorService$TrackingThreadPoolExecutor;
      53: new           #16                 // class org/apache/hbase/thirdparty/com/google/common/util/concurrent/ThreadFactoryBuilder
      56: dup
      57: invokespecial #17                 // Method org/apache/hbase/thirdparty/com/google/common/util/concurrent/ThreadFactoryBuilder."<init>":()V
      60: astore_3
      61: aload_3
      62: new           #18                 // class java/lang/StringBuilder
      65: dup
      66: invokespecial #19                 // Method java/lang/StringBuilder."<init>":()V
      69: aload_0
      70: getfield      #8                  // Field name:Ljava/lang/String;
      73: invokevirtual #20                 // Method java/lang/StringBuilder.append:(Ljava/lang/String;)Ljava/lang/StringBuilder;
      76: ldc           #21                 // String -%d
      78: invokevirtual #20                 // Method java/lang/StringBuilder.append:(Ljava/lang/String;)Ljava/lang/StringBuilder;
      81: invokevirtual #22                 // Method java/lang/StringBuilder.toString:()Ljava/lang/String;
      84: invokevirtual #23                 // Method org/apache/hbase/thirdparty/com/google/common/util/concurrent/ThreadFactoryBuilder.setNameFormat:(Ljava/lang/String;)Lorg/apache/hbase/thirdparty/com/google/common/util/concurrent/ThreadFactoryBuilder;
      87: pop
      88: aload_3
      89: iconst_1
      90: invokevirtual #24                 // Method org/apache/hbase/thirdparty/com/google/common/util/concurrent/ThreadFactoryBuilder.setDaemon:(Z)Lorg/apache/hbase/thirdparty/com/google/common/util/concurrent/ThreadFactoryBuilder;
      93: pop
      94: aload_0
      95: getfield      #15                 // Field threadPoolExecutor:Lorg/apache/hadoop/hbase/executor/ExecutorService$TrackingThreadPoolExecutor;
      98: aload_3
      99: invokevirtual #25                 // Method org/apache/hbase/thirdparty/com/google/common/util/concurrent/ThreadFactoryBuilder.build:()Ljava/util/concurrent/ThreadFactory;
     102: invokevirtual #26                 // Method org/apache/hadoop/hbase/executor/ExecutorService$TrackingThreadPoolExecutor.setThreadFactory:(Ljava/util/concurrent/ThreadFactory;)V
     105: return

  void submit(org.apache.hadoop.hbase.executor.EventHandler);
    Code:
       0: aload_0
       1: getfield      #15                 // Field threadPoolExecutor:Lorg/apache/hadoop/hbase/executor/ExecutorService$TrackingThreadPoolExecutor;
       4: aload_1
       5: invokevirtual #27                 // Method org/apache/hadoop/hbase/executor/ExecutorService$TrackingThreadPoolExecutor.execute:(Ljava/lang/Runnable;)V
       8: return

  org.apache.hadoop.hbase.executor.ExecutorService$TrackingThreadPoolExecutor getThreadPoolExecutor();
    Code:
       0: aload_0
       1: getfield      #15                 // Field threadPoolExecutor:Lorg/apache/hadoop/hbase/executor/ExecutorService$TrackingThreadPoolExecutor;
       4: areturn

  public java.lang.String toString();
    Code:
       0: new           #18                 // class java/lang/StringBuilder
       3: dup
       4: invokespecial #19                 // Method java/lang/StringBuilder."<init>":()V
       7: aload_0
       8: invokevirtual #28                 // Method java/lang/Object.getClass:()Ljava/lang/Class;
      11: invokevirtual #29                 // Method java/lang/Class.getSimpleName:()Ljava/lang/String;
      14: invokevirtual #20                 // Method java/lang/StringBuilder.append:(Ljava/lang/String;)Ljava/lang/StringBuilder;
      17: ldc           #30                 // String -
      19: invokevirtual #20                 // Method java/lang/StringBuilder.append:(Ljava/lang/String;)Ljava/lang/StringBuilder;
      22: aload_0
      23: getfield      #7                  // Field id:J
      26: invokevirtual #31                 // Method java/lang/StringBuilder.append:(J)Ljava/lang/StringBuilder;
      29: ldc           #30                 // String -
      31: invokevirtual #20                 // Method java/lang/StringBuilder.append:(Ljava/lang/String;)Ljava/lang/StringBuilder;
      34: aload_0
      35: getfield      #8                  // Field name:Ljava/lang/String;
      38: invokevirtual #20                 // Method java/lang/StringBuilder.append:(Ljava/lang/String;)Ljava/lang/StringBuilder;
      41: invokevirtual #22                 // Method java/lang/StringBuilder.toString:()Ljava/lang/String;
      44: areturn

  public org.apache.hadoop.hbase.executor.ExecutorService$ExecutorStatus getStatus();
    Code:
       0: invokestatic  #32                 // Method org/apache/hbase/thirdparty/com/google/common/collect/Lists.newArrayList:()Ljava/util/ArrayList;
       3: astore_1
       4: aload_0
       5: getfield      #4                  // Field q:Ljava/util/concurrent/BlockingQueue;
       8: invokeinterface #33,  1           // InterfaceMethod java/util/concurrent/BlockingQueue.iterator:()Ljava/util/Iterator;
      13: astore_2
      14: aload_2
      15: invokeinterface #34,  1           // InterfaceMethod java/util/Iterator.hasNext:()Z
      20: ifeq          96
      23: aload_2
      24: invokeinterface #35,  1           // InterfaceMethod java/util/Iterator.next:()Ljava/lang/Object;
      29: checkcast     #36                 // class java/lang/Runnable
      32: astore_3
      33: aload_3
      34: instanceof    #37                 // class org/apache/hadoop/hbase/executor/EventHandler
      37: ifne          82
      40: invokestatic  #38                 // Method org/apache/hadoop/hbase/executor/ExecutorService.access$000:()Lorg/slf4j/Logger;
      43: new           #18                 // class java/lang/StringBuilder
      46: dup
      47: invokespecial #19                 // Method java/lang/StringBuilder."<init>":()V
      50: ldc           #39                 // String Non-EventHandler
      52: invokevirtual #20                 // Method java/lang/StringBuilder.append:(Ljava/lang/String;)Ljava/lang/StringBuilder;
      55: aload_3
      56: invokevirtual #40                 // Method java/lang/StringBuilder.append:(Ljava/lang/Object;)Ljava/lang/StringBuilder;
      59: ldc           #41                 // String  queued in
      61: invokevirtual #20                 // Method java/lang/StringBuilder.append:(Ljava/lang/String;)Ljava/lang/StringBuilder;
      64: aload_0
      65: getfield      #8                  // Field name:Ljava/lang/String;
      68: invokevirtual #20                 // Method java/lang/StringBuilder.append:(Ljava/lang/String;)Ljava/lang/StringBuilder;
      71: invokevirtual #22                 // Method java/lang/StringBuilder.toString:()Ljava/lang/String;
      74: invokeinterface #42,  2           // InterfaceMethod org/slf4j/Logger.warn:(Ljava/lang/String;)V
      79: goto          14
      82: aload_1
      83: aload_3
      84: checkcast     #37                 // class org/apache/hadoop/hbase/executor/EventHandler
      87: invokeinterface #43,  2           // InterfaceMethod java/util/List.add:(Ljava/lang/Object;)Z
      92: pop
      93: goto          14
      96: invokestatic  #32                 // Method org/apache/hbase/thirdparty/com/google/common/collect/Lists.newArrayList:()Ljava/util/ArrayList;
      99: astore_2
     100: aload_0
     101: getfield      #15                 // Field threadPoolExecutor:Lorg/apache/hadoop/hbase/executor/ExecutorService$TrackingThreadPoolExecutor;
     104: invokevirtual #44                 // Method org/apache/hadoop/hbase/executor/ExecutorService$TrackingThreadPoolExecutor.getRunningTasks:()Ljava/util/concurrent/ConcurrentMap;
     107: invokeinterface #45,  1           // InterfaceMethod java/util/concurrent/ConcurrentMap.entrySet:()Ljava/util/Set;
     112: invokeinterface #46,  1           // InterfaceMethod java/util/Set.iterator:()Ljava/util/Iterator;
     117: astore_3
     118: aload_3
     119: invokeinterface #34,  1           // InterfaceMethod java/util/Iterator.hasNext:()Z
     124: ifeq          233
     127: aload_3
     128: invokeinterface #35,  1           // InterfaceMethod java/util/Iterator.next:()Ljava/lang/Object;
     133: checkcast     #47                 // class java/util/Map$Entry
     136: astore        4
     138: aload         4
     140: invokeinterface #48,  1           // InterfaceMethod java/util/Map$Entry.getValue:()Ljava/lang/Object;
     145: checkcast     #36                 // class java/lang/Runnable
     148: astore        5
     150: aload         5
     152: instanceof    #37                 // class org/apache/hadoop/hbase/executor/EventHandler
     155: ifne          201
     158: invokestatic  #38                 // Method org/apache/hadoop/hbase/executor/ExecutorService.access$000:()Lorg/slf4j/Logger;
     161: new           #18                 // class java/lang/StringBuilder
     164: dup
     165: invokespecial #19                 // Method java/lang/StringBuilder."<init>":()V
     168: ldc           #39                 // String Non-EventHandler
     170: invokevirtual #20                 // Method java/lang/StringBuilder.append:(Ljava/lang/String;)Ljava/lang/StringBuilder;
     173: aload         5
     175: invokevirtual #40                 // Method java/lang/StringBuilder.append:(Ljava/lang/Object;)Ljava/lang/StringBuilder;
     178: ldc           #49                 // String  running in
     180: invokevirtual #20                 // Method java/lang/StringBuilder.append:(Ljava/lang/String;)Ljava/lang/StringBuilder;
     183: aload_0
     184: getfield      #8                  // Field name:Ljava/lang/String;
     187: invokevirtual #20                 // Method java/lang/StringBuilder.append:(Ljava/lang/String;)Ljava/lang/StringBuilder;
     190: invokevirtual #22                 // Method java/lang/StringBuilder.toString:()Ljava/lang/String;
     193: invokeinterface #42,  2           // InterfaceMethod org/slf4j/Logger.warn:(Ljava/lang/String;)V
     198: goto          118
     201: aload_2
     202: new           #50                 // class org/apache/hadoop/hbase/executor/ExecutorService$RunningEventStatus
     205: dup
     206: aload         4
     208: invokeinterface #51,  1           // InterfaceMethod java/util/Map$Entry.getKey:()Ljava/lang/Object;
     213: checkcast     #52                 // class java/lang/Thread
     216: aload         5
     218: checkcast     #37                 // class org/apache/hadoop/hbase/executor/EventHandler
     221: invokespecial #53                 // Method org/apache/hadoop/hbase/executor/ExecutorService$RunningEventStatus."<init>":(Ljava/lang/Thread;Lorg/apache/hadoop/hbase/executor/EventHandler;)V
     224: invokeinterface #43,  2           // InterfaceMethod java/util/List.add:(Ljava/lang/Object;)Z
     229: pop
     230: goto          118
     233: new           #54                 // class org/apache/hadoop/hbase/executor/ExecutorService$ExecutorStatus
     236: dup
     237: aload_0
     238: aload_1
     239: aload_2
     240: invokespecial #55                 // Method org/apache/hadoop/hbase/executor/ExecutorService$ExecutorStatus."<init>":(Lorg/apache/hadoop/hbase/executor/ExecutorService$Executor;Ljava/util/List;Ljava/util/List;)V
     243: areturn

  static {};
    Code:
       0: new           #56                 // class java/util/concurrent/atomic/AtomicLong
       3: dup
       4: lconst_0
       5: invokespecial #57                 // Method java/util/concurrent/atomic/AtomicLong."<init>":(J)V
       8: putstatic     #5                  // Field seqids:Ljava/util/concurrent/atomic/AtomicLong;
      11: return
}
