Compiled from "ExpressionExpander.java"
public class org.apache.hadoop.hbase.security.visibility.ExpressionExpander {
  static final boolean $assertionsDisabled;

  public org.apache.hadoop.hbase.security.visibility.ExpressionExpander();
    Code:
       0: aload_0
       1: invokespecial #1                  // Method java/lang/Object."<init>":()V
       4: return

  public org.apache.hadoop.hbase.security.visibility.expression.ExpressionNode expand(org.apache.hadoop.hbase.security.visibility.expression.ExpressionNode);
    Code:
       0: aload_1
       1: invokeinterface #2,  1            // InterfaceMethod org/apache/hadoop/hbase/security/visibility/expression/ExpressionNode.isSingleNode:()Z
       6: ifne          121
       9: aload_1
      10: checkcast     #3                  // class org/apache/hadoop/hbase/security/visibility/expression/NonLeafExpressionNode
      13: astore_2
      14: aload_2
      15: invokevirtual #4                  // Method org/apache/hadoop/hbase/security/visibility/expression/NonLeafExpressionNode.getChildExps:()Ljava/util/List;
      18: astore_3
      19: aload_2
      20: invokevirtual #5                  // Method org/apache/hadoop/hbase/security/visibility/expression/NonLeafExpressionNode.getOperator:()Lorg/apache/hadoop/hbase/security/visibility/expression/Operator;
      23: astore        4
      25: aload_0
      26: aload_3
      27: invokespecial #6                  // Method isToBeExpanded:(Ljava/util/List;)Z
      30: ifeq          119
      33: new           #3                  // class org/apache/hadoop/hbase/security/visibility/expression/NonLeafExpressionNode
      36: dup
      37: aload_2
      38: invokevirtual #5                  // Method org/apache/hadoop/hbase/security/visibility/expression/NonLeafExpressionNode.getOperator:()Lorg/apache/hadoop/hbase/security/visibility/expression/Operator;
      41: invokespecial #7                  // Method org/apache/hadoop/hbase/security/visibility/expression/NonLeafExpressionNode."<init>":(Lorg/apache/hadoop/hbase/security/visibility/expression/Operator;)V
      44: astore        5
      46: aload_3
      47: invokeinterface #8,  1            // InterfaceMethod java/util/List.iterator:()Ljava/util/Iterator;
      52: astore        6
      54: aload         6
      56: invokeinterface #9,  1            // InterfaceMethod java/util/Iterator.hasNext:()Z
      61: ifeq          110
      64: aload         6
      66: invokeinterface #10,  1           // InterfaceMethod java/util/Iterator.next:()Ljava/lang/Object;
      71: checkcast     #11                 // class org/apache/hadoop/hbase/security/visibility/expression/ExpressionNode
      74: astore        7
      76: aload         7
      78: invokeinterface #2,  1            // InterfaceMethod org/apache/hadoop/hbase/security/visibility/expression/ExpressionNode.isSingleNode:()Z
      83: ifeq          96
      86: aload         5
      88: aload         7
      90: invokevirtual #12                 // Method org/apache/hadoop/hbase/security/visibility/expression/NonLeafExpressionNode.addChildExp:(Lorg/apache/hadoop/hbase/security/visibility/expression/ExpressionNode;)V
      93: goto          107
      96: aload         5
      98: aload_0
      99: aload         7
     101: invokevirtual #13                 // Method expand:(Lorg/apache/hadoop/hbase/security/visibility/expression/ExpressionNode;)Lorg/apache/hadoop/hbase/security/visibility/expression/ExpressionNode;
     104: invokevirtual #12                 // Method org/apache/hadoop/hbase/security/visibility/expression/NonLeafExpressionNode.addChildExp:(Lorg/apache/hadoop/hbase/security/visibility/expression/ExpressionNode;)V
     107: goto          54
     110: aload_0
     111: aload         5
     113: aload         4
     115: invokespecial #14                 // Method expandNonLeaf:(Lorg/apache/hadoop/hbase/security/visibility/expression/NonLeafExpressionNode;Lorg/apache/hadoop/hbase/security/visibility/expression/Operator;)Lorg/apache/hadoop/hbase/security/visibility/expression/NonLeafExpressionNode;
     118: astore_2
     119: aload_2
     120: areturn
     121: aload_1
     122: instanceof    #3                  // class org/apache/hadoop/hbase/security/visibility/expression/NonLeafExpressionNode
     125: ifeq          150
     128: aload_1
     129: checkcast     #3                  // class org/apache/hadoop/hbase/security/visibility/expression/NonLeafExpressionNode
     132: invokevirtual #5                  // Method org/apache/hadoop/hbase/security/visibility/expression/NonLeafExpressionNode.getOperator:()Lorg/apache/hadoop/hbase/security/visibility/expression/Operator;
     135: getstatic     #15                 // Field org/apache/hadoop/hbase/security/visibility/expression/Operator.NOT:Lorg/apache/hadoop/hbase/security/visibility/expression/Operator;
     138: if_acmpne     150
     141: aload_0
     142: aload_1
     143: checkcast     #3                  // class org/apache/hadoop/hbase/security/visibility/expression/NonLeafExpressionNode
     146: invokespecial #16                 // Method negate:(Lorg/apache/hadoop/hbase/security/visibility/expression/NonLeafExpressionNode;)Lorg/apache/hadoop/hbase/security/visibility/expression/ExpressionNode;
     149: areturn
     150: aload_1
     151: areturn

  static {};
    Code:
       0: ldc           #30                 // class org/apache/hadoop/hbase/security/visibility/ExpressionExpander
       2: invokevirtual #31                 // Method java/lang/Class.desiredAssertionStatus:()Z
       5: ifne          12
       8: iconst_1
       9: goto          13
      12: iconst_0
      13: putstatic     #22                 // Field $assertionsDisabled:Z
      16: return
}
