Compiled from "FailedServers.java"
public class org.apache.hadoop.hbase.ipc.FailedServers {
  public org.apache.hadoop.hbase.ipc.FailedServers(org.apache.hadoop.conf.Configuration);
    Code:
       0: aload_0
       1: invokespecial #1                  // Method java/lang/Object."<init>":()V
       4: aload_0
       5: new           #2                  // class java/util/HashMap
       8: dup
       9: invokespecial #3                  // Method java/util/HashMap."<init>":()V
      12: putfield      #4                  // Field failedServers:Ljava/util/Map;
      15: aload_0
      16: lconst_0
      17: putfield      #5                  // Field latestExpiry:J
      20: aload_0
      21: aload_1
      22: ldc           #7                  // String hbase.ipc.client.failed.servers.expiry
      24: sipush        2000
      27: invokevirtual #8                  // Method org/apache/hadoop/conf/Configuration.getInt:(Ljava/lang/String;I)I
      30: putfield      #9                  // Field recheckServersTimeout:I
      33: return

  public synchronized void addToFailedServers(java.net.InetSocketAddress, java.lang.Throwable);
    Code:
       0: invokestatic  #10                 // Method org/apache/hadoop/hbase/util/EnvironmentEdgeManager.currentTime:()J
       3: aload_0
       4: getfield      #9                  // Field recheckServersTimeout:I
       7: i2l
       8: ladd
       9: lstore_3
      10: aload_0
      11: getfield      #4                  // Field failedServers:Ljava/util/Map;
      14: aload_1
      15: invokevirtual #11                 // Method java/net/InetSocketAddress.toString:()Ljava/lang/String;
      18: lload_3
      19: invokestatic  #12                 // Method java/lang/Long.valueOf:(J)Ljava/lang/Long;
      22: invokeinterface #13,  3           // InterfaceMethod java/util/Map.put:(Ljava/lang/Object;Ljava/lang/Object;)Ljava/lang/Object;
      27: pop
      28: aload_0
      29: lload_3
      30: putfield      #5                  // Field latestExpiry:J
      33: getstatic     #14                 // Field LOG:Lorg/slf4j/Logger;
      36: invokeinterface #15,  1           // InterfaceMethod org/slf4j/Logger.isDebugEnabled:()Z
      41: ifeq          86
      44: getstatic     #14                 // Field LOG:Lorg/slf4j/Logger;
      47: new           #16                 // class java/lang/StringBuilder
      50: dup
      51: invokespecial #17                 // Method java/lang/StringBuilder."<init>":()V
      54: ldc           #18                 // String Added failed server with address
      56: invokevirtual #19                 // Method java/lang/StringBuilder.append:(Ljava/lang/String;)Ljava/lang/StringBuilder;
      59: aload_1
      60: invokevirtual #11                 // Method java/net/InetSocketAddress.toString:()Ljava/lang/String;
      63: invokevirtual #19                 // Method java/lang/StringBuilder.append:(Ljava/lang/String;)Ljava/lang/StringBuilder;
      66: ldc           #20                 // String  to list caused by
      68: invokevirtual #19                 // Method java/lang/StringBuilder.append:(Ljava/lang/String;)Ljava/lang/StringBuilder;
      71: aload_2
      72: invokevirtual #21                 // Method java/lang/Throwable.toString:()Ljava/lang/String;
      75: invokevirtual #19                 // Method java/lang/StringBuilder.append:(Ljava/lang/String;)Ljava/lang/StringBuilder;
      78: invokevirtual #22                 // Method java/lang/StringBuilder.toString:()Ljava/lang/String;
      81: invokeinterface #23,  2           // InterfaceMethod org/slf4j/Logger.debug:(Ljava/lang/String;)V
      86: return

  public synchronized boolean isFailedServer(java.net.InetSocketAddress);
    Code:
       0: aload_0
       1: getfield      #4                  // Field failedServers:Ljava/util/Map;
       4: invokeinterface #24,  1           // InterfaceMethod java/util/Map.isEmpty:()Z
       9: ifeq          14
      12: iconst_0
      13: ireturn
      14: invokestatic  #10                 // Method org/apache/hadoop/hbase/util/EnvironmentEdgeManager.currentTime:()J
      17: lstore_2
      18: lload_2
      19: aload_0
      20: getfield      #5                  // Field latestExpiry:J
      23: lcmp
      24: ifle          38
      27: aload_0
      28: getfield      #4                  // Field failedServers:Ljava/util/Map;
      31: invokeinterface #25,  1           // InterfaceMethod java/util/Map.clear:()V
      36: iconst_0
      37: ireturn
      38: aload_1
      39: invokevirtual #11                 // Method java/net/InetSocketAddress.toString:()Ljava/lang/String;
      42: astore        4
      44: aload_0
      45: getfield      #4                  // Field failedServers:Ljava/util/Map;
      48: aload         4
      50: invokeinterface #26,  2           // InterfaceMethod java/util/Map.get:(Ljava/lang/Object;)Ljava/lang/Object;
      55: checkcast     #27                 // class java/lang/Long
      58: astore        5
      60: aload         5
      62: ifnonnull     67
      65: iconst_0
      66: ireturn
      67: aload         5
      69: invokevirtual #28                 // Method java/lang/Long.longValue:()J
      72: lload_2
      73: lcmp
      74: iflt          79
      77: iconst_1
      78: ireturn
      79: aload_0
      80: getfield      #4                  // Field failedServers:Ljava/util/Map;
      83: aload         4
      85: invokeinterface #29,  2           // InterfaceMethod java/util/Map.remove:(Ljava/lang/Object;)Ljava/lang/Object;
      90: pop
      91: iconst_0
      92: ireturn

  static {};
    Code:
       0: ldc           #30                 // class org/apache/hadoop/hbase/ipc/FailedServers
       2: invokestatic  #31                 // Method org/slf4j/LoggerFactory.getLogger:(Ljava/lang/Class;)Lorg/slf4j/Logger;
       5: putstatic     #14                 // Field LOG:Lorg/slf4j/Logger;
       8: return
}
