Compiled from "FanOutOneBlockAsyncDFSOutputHelper.java"
final class org.apache.hadoop.hbase.io.asyncfs.FanOutOneBlockAsyncDFSOutputHelper$3 extends org.apache.hbase.thirdparty.io.netty.channel.SimpleChannelInboundHandler<org.apache.hadoop.hdfs.protocol.proto.DataTransferProtos$BlockOpResponseProto> {
  final org.apache.hadoop.hdfs.protocol.DatanodeInfo val$dnInfo;

  final org.apache.hbase.thirdparty.io.netty.util.concurrent.Promise val$promise;

  final int val$timeoutMs;

  org.apache.hadoop.hbase.io.asyncfs.FanOutOneBlockAsyncDFSOutputHelper$3(org.apache.hadoop.hdfs.protocol.DatanodeInfo, org.apache.hbase.thirdparty.io.netty.util.concurrent.Promise, int);
    Code:
       0: aload_0
       1: aload_1
       2: putfield      #1                  // Field val$dnInfo:Lorg/apache/hadoop/hdfs/protocol/DatanodeInfo;
       5: aload_0
       6: aload_2
       7: putfield      #2                  // Field val$promise:Lorg/apache/hbase/thirdparty/io/netty/util/concurrent/Promise;
      10: aload_0
      11: iload_3
      12: putfield      #3                  // Field val$timeoutMs:I
      15: aload_0
      16: invokespecial #4                  // Method org/apache/hbase/thirdparty/io/netty/channel/SimpleChannelInboundHandler."<init>":()V
      19: return

  protected void channelRead0(org.apache.hbase.thirdparty.io.netty.channel.ChannelHandlerContext, org.apache.hadoop.hdfs.protocol.proto.DataTransferProtos$BlockOpResponseProto) throws java.lang.Exception;
    Code:
       0: aload_2
       1: invokevirtual #5                  // Method org/apache/hadoop/hdfs/protocol/proto/DataTransferProtos$BlockOpResponseProto.getStatus:()Lorg/apache/hadoop/hdfs/protocol/proto/DataTransferProtos$Status;
       4: astore_3
       5: aload_3
       6: invokestatic  #6                  // Method org/apache/hadoop/hdfs/protocol/datatransfer/PipelineAck.isRestartOOBStatus:(Lorg/apache/hadoop/hdfs/protocol/proto/DataTransferProtos$Status;)Z
       9: ifeq          47
      12: new           #7                  // class java/io/IOException
      15: dup
      16: new           #8                  // class java/lang/StringBuilder
      19: dup
      20: invokespecial #9                  // Method java/lang/StringBuilder."<init>":()V
      23: ldc           #10                 // String datanode
      25: invokevirtual #11                 // Method java/lang/StringBuilder.append:(Ljava/lang/String;)Ljava/lang/StringBuilder;
      28: aload_0
      29: getfield      #1                  // Field val$dnInfo:Lorg/apache/hadoop/hdfs/protocol/DatanodeInfo;
      32: invokevirtual #12                 // Method java/lang/StringBuilder.append:(Ljava/lang/Object;)Ljava/lang/StringBuilder;
      35: ldc           #13                 // String  is restarting
      37: invokevirtual #11                 // Method java/lang/StringBuilder.append:(Ljava/lang/String;)Ljava/lang/StringBuilder;
      40: invokevirtual #14                 // Method java/lang/StringBuilder.toString:()Ljava/lang/String;
      43: invokespecial #15                 // Method java/io/IOException."<init>":(Ljava/lang/String;)V
      46: athrow
      47: new           #8                  // class java/lang/StringBuilder
      50: dup
      51: invokespecial #9                  // Method java/lang/StringBuilder."<init>":()V
      54: ldc           #16                 // String ack with firstBadLink as
      56: invokevirtual #11                 // Method java/lang/StringBuilder.append:(Ljava/lang/String;)Ljava/lang/StringBuilder;
      59: aload_2
      60: invokevirtual #17                 // Method org/apache/hadoop/hdfs/protocol/proto/DataTransferProtos$BlockOpResponseProto.getFirstBadLink:()Ljava/lang/String;
      63: invokevirtual #11                 // Method java/lang/StringBuilder.append:(Ljava/lang/String;)Ljava/lang/StringBuilder;
      66: invokevirtual #14                 // Method java/lang/StringBuilder.toString:()Ljava/lang/String;
      69: astore        4
      71: aload_2
      72: invokevirtual #5                  // Method org/apache/hadoop/hdfs/protocol/proto/DataTransferProtos$BlockOpResponseProto.getStatus:()Lorg/apache/hadoop/hdfs/protocol/proto/DataTransferProtos$Status;
      75: getstatic     #18                 // Field org/apache/hadoop/hdfs/protocol/proto/DataTransferProtos$Status.SUCCESS:Lorg/apache/hadoop/hdfs/protocol/proto/DataTransferProtos$Status;
      78: if_acmpeq     186
      81: aload_2
      82: invokevirtual #5                  // Method org/apache/hadoop/hdfs/protocol/proto/DataTransferProtos$BlockOpResponseProto.getStatus:()Lorg/apache/hadoop/hdfs/protocol/proto/DataTransferProtos$Status;
      85: getstatic     #19                 // Field org/apache/hadoop/hdfs/protocol/proto/DataTransferProtos$Status.ERROR_ACCESS_TOKEN:Lorg/apache/hadoop/hdfs/protocol/proto/DataTransferProtos$Status;
      88: if_acmpne     131
      91: new           #20                 // class org/apache/hadoop/hdfs/security/token/block/InvalidBlockTokenException
      94: dup
      95: new           #8                  // class java/lang/StringBuilder
      98: dup
      99: invokespecial #9                  // Method java/lang/StringBuilder."<init>":()V
     102: ldc           #21                 // String Got access token error, status message
     104: invokevirtual #11                 // Method java/lang/StringBuilder.append:(Ljava/lang/String;)Ljava/lang/StringBuilder;
     107: aload_2
     108: invokevirtual #22                 // Method org/apache/hadoop/hdfs/protocol/proto/DataTransferProtos$BlockOpResponseProto.getMessage:()Ljava/lang/String;
     111: invokevirtual #11                 // Method java/lang/StringBuilder.append:(Ljava/lang/String;)Ljava/lang/StringBuilder;
     114: ldc           #23                 // String ,
     116: invokevirtual #11                 // Method java/lang/StringBuilder.append:(Ljava/lang/String;)Ljava/lang/StringBuilder;
     119: aload         4
     121: invokevirtual #11                 // Method java/lang/StringBuilder.append:(Ljava/lang/String;)Ljava/lang/StringBuilder;
     124: invokevirtual #14                 // Method java/lang/StringBuilder.toString:()Ljava/lang/String;
     127: invokespecial #24                 // Method org/apache/hadoop/hdfs/security/token/block/InvalidBlockTokenException."<init>":(Ljava/lang/String;)V
     130: athrow
     131: new           #7                  // class java/io/IOException
     134: dup
     135: new           #8                  // class java/lang/StringBuilder
     138: dup
     139: invokespecial #9                  // Method java/lang/StringBuilder."<init>":()V
     142: ldc           #25                 // String Got error, status=
     144: invokevirtual #11                 // Method java/lang/StringBuilder.append:(Ljava/lang/String;)Ljava/lang/StringBuilder;
     147: aload_2
     148: invokevirtual #5                  // Method org/apache/hadoop/hdfs/protocol/proto/DataTransferProtos$BlockOpResponseProto.getStatus:()Lorg/apache/hadoop/hdfs/protocol/proto/DataTransferProtos$Status;
     151: invokevirtual #26                 // Method org/apache/hadoop/hdfs/protocol/proto/DataTransferProtos$Status.name:()Ljava/lang/String;
     154: invokevirtual #11                 // Method java/lang/StringBuilder.append:(Ljava/lang/String;)Ljava/lang/StringBuilder;
     157: ldc           #27                 // String , status message
     159: invokevirtual #11                 // Method java/lang/StringBuilder.append:(Ljava/lang/String;)Ljava/lang/StringBuilder;
     162: aload_2
     163: invokevirtual #22                 // Method org/apache/hadoop/hdfs/protocol/proto/DataTransferProtos$BlockOpResponseProto.getMessage:()Ljava/lang/String;
     166: invokevirtual #11                 // Method java/lang/StringBuilder.append:(Ljava/lang/String;)Ljava/lang/StringBuilder;
     169: ldc           #23                 // String ,
     171: invokevirtual #11                 // Method java/lang/StringBuilder.append:(Ljava/lang/String;)Ljava/lang/StringBuilder;
     174: aload         4
     176: invokevirtual #11                 // Method java/lang/StringBuilder.append:(Ljava/lang/String;)Ljava/lang/StringBuilder;
     179: invokevirtual #14                 // Method java/lang/StringBuilder.toString:()Ljava/lang/String;
     182: invokespecial #15                 // Method java/io/IOException."<init>":(Ljava/lang/String;)V
     185: athrow
     186: aload_1
     187: invokeinterface #28,  1           // InterfaceMethod org/apache/hbase/thirdparty/io/netty/channel/ChannelHandlerContext.pipeline:()Lorg/apache/hbase/thirdparty/io/netty/channel/ChannelPipeline;
     192: astore        5
     194: aload         5
     196: invokeinterface #29,  1           // InterfaceMethod org/apache/hbase/thirdparty/io/netty/channel/ChannelPipeline.removeLast:()Lorg/apache/hbase/thirdparty/io/netty/channel/ChannelHandler;
     201: dup
     202: astore        6
     204: ifnull        218
     207: aload         6
     209: instanceof    #30                 // class org/apache/hbase/thirdparty/io/netty/handler/timeout/IdleStateHandler
     212: ifeq          194
     215: goto          218
     218: aload_1
     219: invokeinterface #31,  1           // InterfaceMethod org/apache/hbase/thirdparty/io/netty/channel/ChannelHandlerContext.channel:()Lorg/apache/hbase/thirdparty/io/netty/channel/Channel;
     224: invokeinterface #32,  1           // InterfaceMethod org/apache/hbase/thirdparty/io/netty/channel/Channel.config:()Lorg/apache/hbase/thirdparty/io/netty/channel/ChannelConfig;
     229: iconst_0
     230: invokeinterface #33,  2           // InterfaceMethod org/apache/hbase/thirdparty/io/netty/channel/ChannelConfig.setAutoRead:(Z)Lorg/apache/hbase/thirdparty/io/netty/channel/ChannelConfig;
     235: pop
     236: aload_0
     237: getfield      #2                  // Field val$promise:Lorg/apache/hbase/thirdparty/io/netty/util/concurrent/Promise;
     240: aload_1
     241: invokeinterface #31,  1           // InterfaceMethod org/apache/hbase/thirdparty/io/netty/channel/ChannelHandlerContext.channel:()Lorg/apache/hbase/thirdparty/io/netty/channel/Channel;
     246: invokeinterface #34,  2           // InterfaceMethod org/apache/hbase/thirdparty/io/netty/util/concurrent/Promise.trySuccess:(Ljava/lang/Object;)Z
     251: pop
     252: return

  public void channelInactive(org.apache.hbase.thirdparty.io.netty.channel.ChannelHandlerContext) throws java.lang.Exception;
    Code:
       0: aload_0
       1: getfield      #2                  // Field val$promise:Lorg/apache/hbase/thirdparty/io/netty/util/concurrent/Promise;
       4: new           #7                  // class java/io/IOException
       7: dup
       8: new           #8                  // class java/lang/StringBuilder
      11: dup
      12: invokespecial #9                  // Method java/lang/StringBuilder."<init>":()V
      15: ldc           #35                 // String connection to
      17: invokevirtual #11                 // Method java/lang/StringBuilder.append:(Ljava/lang/String;)Ljava/lang/StringBuilder;
      20: aload_0
      21: getfield      #1                  // Field val$dnInfo:Lorg/apache/hadoop/hdfs/protocol/DatanodeInfo;
      24: invokevirtual #12                 // Method java/lang/StringBuilder.append:(Ljava/lang/Object;)Ljava/lang/StringBuilder;
      27: ldc           #36                 // String  is closed
      29: invokevirtual #11                 // Method java/lang/StringBuilder.append:(Ljava/lang/String;)Ljava/lang/StringBuilder;
      32: invokevirtual #14                 // Method java/lang/StringBuilder.toString:()Ljava/lang/String;
      35: invokespecial #15                 // Method java/io/IOException."<init>":(Ljava/lang/String;)V
      38: invokeinterface #37,  2           // InterfaceMethod org/apache/hbase/thirdparty/io/netty/util/concurrent/Promise.tryFailure:(Ljava/lang/Throwable;)Z
      43: pop
      44: return

  public void userEventTriggered(org.apache.hbase.thirdparty.io.netty.channel.ChannelHandlerContext, java.lang.Object) throws java.lang.Exception;
    Code:
       0: aload_2
       1: instanceof    #38                 // class org/apache/hbase/thirdparty/io/netty/handler/timeout/IdleStateEvent
       4: ifeq          67
       7: aload_2
       8: checkcast     #38                 // class org/apache/hbase/thirdparty/io/netty/handler/timeout/IdleStateEvent
      11: invokevirtual #39                 // Method org/apache/hbase/thirdparty/io/netty/handler/timeout/IdleStateEvent.state:()Lorg/apache/hbase/thirdparty/io/netty/handler/timeout/IdleState;
      14: getstatic     #40                 // Field org/apache/hbase/thirdparty/io/netty/handler/timeout/IdleState.READER_IDLE:Lorg/apache/hbase/thirdparty/io/netty/handler/timeout/IdleState;
      17: if_acmpne     67
      20: aload_0
      21: getfield      #2                  // Field val$promise:Lorg/apache/hbase/thirdparty/io/netty/util/concurrent/Promise;
      24: new           #7                  // class java/io/IOException
      27: dup
      28: new           #8                  // class java/lang/StringBuilder
      31: dup
      32: invokespecial #9                  // Method java/lang/StringBuilder."<init>":()V
      35: ldc           #41                 // String Timeout(
      37: invokevirtual #11                 // Method java/lang/StringBuilder.append:(Ljava/lang/String;)Ljava/lang/StringBuilder;
      40: aload_0
      41: getfield      #3                  // Field val$timeoutMs:I
      44: invokevirtual #42                 // Method java/lang/StringBuilder.append:(I)Ljava/lang/StringBuilder;
      47: ldc           #43                 // String ms) waiting for response
      49: invokevirtual #11                 // Method java/lang/StringBuilder.append:(Ljava/lang/String;)Ljava/lang/StringBuilder;
      52: invokevirtual #14                 // Method java/lang/StringBuilder.toString:()Ljava/lang/String;
      55: invokespecial #15                 // Method java/io/IOException."<init>":(Ljava/lang/String;)V
      58: invokeinterface #37,  2           // InterfaceMethod org/apache/hbase/thirdparty/io/netty/util/concurrent/Promise.tryFailure:(Ljava/lang/Throwable;)Z
      63: pop
      64: goto          73
      67: aload_0
      68: aload_1
      69: aload_2
      70: invokespecial #44                 // Method org/apache/hbase/thirdparty/io/netty/channel/SimpleChannelInboundHandler.userEventTriggered:(Lorg/apache/hbase/thirdparty/io/netty/channel/ChannelHandlerContext;Ljava/lang/Object;)V
      73: return

  public void exceptionCaught(org.apache.hbase.thirdparty.io.netty.channel.ChannelHandlerContext, java.lang.Throwable) throws java.lang.Exception;
    Code:
       0: aload_0
       1: getfield      #2                  // Field val$promise:Lorg/apache/hbase/thirdparty/io/netty/util/concurrent/Promise;
       4: aload_2
       5: invokeinterface #37,  2           // InterfaceMethod org/apache/hbase/thirdparty/io/netty/util/concurrent/Promise.tryFailure:(Ljava/lang/Throwable;)Z
      10: pop
      11: return

  protected void channelRead0(org.apache.hbase.thirdparty.io.netty.channel.ChannelHandlerContext, java.lang.Object) throws java.lang.Exception;
    Code:
       0: aload_0
       1: aload_1
       2: aload_2
       3: checkcast     #45                 // class org/apache/hadoop/hdfs/protocol/proto/DataTransferProtos$BlockOpResponseProto
       6: invokevirtual #46                 // Method channelRead0:(Lorg/apache/hbase/thirdparty/io/netty/channel/ChannelHandlerContext;Lorg/apache/hadoop/hdfs/protocol/proto/DataTransferProtos$BlockOpResponseProto;)V
       9: return
}
