Compiled from "FanOutOneBlockAsyncDFSOutput.java"
final class org.apache.hadoop.hbase.io.asyncfs.FanOutOneBlockAsyncDFSOutput$State extends java.lang.Enum<org.apache.hadoop.hbase.io.asyncfs.FanOutOneBlockAsyncDFSOutput$State> {
  public static final org.apache.hadoop.hbase.io.asyncfs.FanOutOneBlockAsyncDFSOutput$State STREAMING;

  public static final org.apache.hadoop.hbase.io.asyncfs.FanOutOneBlockAsyncDFSOutput$State CLOSING;

  public static final org.apache.hadoop.hbase.io.asyncfs.FanOutOneBlockAsyncDFSOutput$State BROKEN;

  public static final org.apache.hadoop.hbase.io.asyncfs.FanOutOneBlockAsyncDFSOutput$State CLOSED;

  public static org.apache.hadoop.hbase.io.asyncfs.FanOutOneBlockAsyncDFSOutput$State[] values();
    Code:
       0: getstatic     #1                  // Field $VALUES:[Lorg/apache/hadoop/hbase/io/asyncfs/FanOutOneBlockAsyncDFSOutput$State;
       3: invokevirtual #2                  // Method "[Lorg/apache/hadoop/hbase/io/asyncfs/FanOutOneBlockAsyncDFSOutput$State;".clone:()Ljava/lang/Object;
       6: checkcast     #3                  // class "[Lorg/apache/hadoop/hbase/io/asyncfs/FanOutOneBlockAsyncDFSOutput$State;"
       9: areturn

  public static org.apache.hadoop.hbase.io.asyncfs.FanOutOneBlockAsyncDFSOutput$State valueOf(java.lang.String);
    Code:
       0: ldc           #4                  // class org/apache/hadoop/hbase/io/asyncfs/FanOutOneBlockAsyncDFSOutput$State
       2: aload_0
       3: invokestatic  #5                  // Method java/lang/Enum.valueOf:(Ljava/lang/Class;Ljava/lang/String;)Ljava/lang/Enum;
       6: checkcast     #4                  // class org/apache/hadoop/hbase/io/asyncfs/FanOutOneBlockAsyncDFSOutput$State
       9: areturn

  static {};
    Code:
       0: new           #4                  // class org/apache/hadoop/hbase/io/asyncfs/FanOutOneBlockAsyncDFSOutput$State
       3: dup
       4: ldc           #7                  // String STREAMING
       6: iconst_0
       7: invokespecial #8                  // Method "<init>":(Ljava/lang/String;I)V
      10: putstatic     #9                  // Field STREAMING:Lorg/apache/hadoop/hbase/io/asyncfs/FanOutOneBlockAsyncDFSOutput$State;
      13: new           #4                  // class org/apache/hadoop/hbase/io/asyncfs/FanOutOneBlockAsyncDFSOutput$State
      16: dup
      17: ldc           #10                 // String CLOSING
      19: iconst_1
      20: invokespecial #8                  // Method "<init>":(Ljava/lang/String;I)V
      23: putstatic     #11                 // Field CLOSING:Lorg/apache/hadoop/hbase/io/asyncfs/FanOutOneBlockAsyncDFSOutput$State;
      26: new           #4                  // class org/apache/hadoop/hbase/io/asyncfs/FanOutOneBlockAsyncDFSOutput$State
      29: dup
      30: ldc           #12                 // String BROKEN
      32: iconst_2
      33: invokespecial #8                  // Method "<init>":(Ljava/lang/String;I)V
      36: putstatic     #13                 // Field BROKEN:Lorg/apache/hadoop/hbase/io/asyncfs/FanOutOneBlockAsyncDFSOutput$State;
      39: new           #4                  // class org/apache/hadoop/hbase/io/asyncfs/FanOutOneBlockAsyncDFSOutput$State
      42: dup
      43: ldc           #14                 // String CLOSED
      45: iconst_3
      46: invokespecial #8                  // Method "<init>":(Ljava/lang/String;I)V
      49: putstatic     #15                 // Field CLOSED:Lorg/apache/hadoop/hbase/io/asyncfs/FanOutOneBlockAsyncDFSOutput$State;
      52: iconst_4
      53: anewarray     #4                  // class org/apache/hadoop/hbase/io/asyncfs/FanOutOneBlockAsyncDFSOutput$State
      56: dup
      57: iconst_0
      58: getstatic     #9                  // Field STREAMING:Lorg/apache/hadoop/hbase/io/asyncfs/FanOutOneBlockAsyncDFSOutput$State;
      61: aastore
      62: dup
      63: iconst_1
      64: getstatic     #11                 // Field CLOSING:Lorg/apache/hadoop/hbase/io/asyncfs/FanOutOneBlockAsyncDFSOutput$State;
      67: aastore
      68: dup
      69: iconst_2
      70: getstatic     #13                 // Field BROKEN:Lorg/apache/hadoop/hbase/io/asyncfs/FanOutOneBlockAsyncDFSOutput$State;
      73: aastore
      74: dup
      75: iconst_3
      76: getstatic     #15                 // Field CLOSED:Lorg/apache/hadoop/hbase/io/asyncfs/FanOutOneBlockAsyncDFSOutput$State;
      79: aastore
      80: putstatic     #1                  // Field $VALUES:[Lorg/apache/hadoop/hbase/io/asyncfs/FanOutOneBlockAsyncDFSOutput$State;
      83: return
}
