Compiled from "FanOutOneBlockAsyncDFSOutputHelper.java"
final class org.apache.hadoop.hbase.io.asyncfs.FanOutOneBlockAsyncDFSOutputHelper$8 extends org.apache.hadoop.fs.FileSystemLinkResolver<org.apache.hadoop.hbase.io.asyncfs.FanOutOneBlockAsyncDFSOutput> {
  final org.apache.hadoop.hdfs.DistributedFileSystem val$dfs;

  final boolean val$overwrite;

  final boolean val$createParent;

  final short val$replication;

  final long val$blockSize;

  final org.apache.hbase.thirdparty.io.netty.channel.EventLoopGroup val$eventLoopGroup;

  final java.lang.Class val$channelClass;

  org.apache.hadoop.hbase.io.asyncfs.FanOutOneBlockAsyncDFSOutputHelper$8(org.apache.hadoop.hdfs.DistributedFileSystem, boolean, boolean, short, long, org.apache.hbase.thirdparty.io.netty.channel.EventLoopGroup, java.lang.Class);
    Code:
       0: aload_0
       1: aload_1
       2: putfield      #1                  // Field val$dfs:Lorg/apache/hadoop/hdfs/DistributedFileSystem;
       5: aload_0
       6: iload_2
       7: putfield      #2                  // Field val$overwrite:Z
      10: aload_0
      11: iload_3
      12: putfield      #3                  // Field val$createParent:Z
      15: aload_0
      16: iload         4
      18: putfield      #4                  // Field val$replication:S
      21: aload_0
      22: lload         5
      24: putfield      #5                  // Field val$blockSize:J
      27: aload_0
      28: aload         7
      30: putfield      #6                  // Field val$eventLoopGroup:Lorg/apache/hbase/thirdparty/io/netty/channel/EventLoopGroup;
      33: aload_0
      34: aload         8
      36: putfield      #7                  // Field val$channelClass:Ljava/lang/Class;
      39: aload_0
      40: invokespecial #8                  // Method org/apache/hadoop/fs/FileSystemLinkResolver."<init>":()V
      43: return

  public org.apache.hadoop.hbase.io.asyncfs.FanOutOneBlockAsyncDFSOutput doCall(org.apache.hadoop.fs.Path) throws java.io.IOException, org.apache.hadoop.fs.UnresolvedLinkException;
    Code:
       0: aload_0
       1: getfield      #1                  // Field val$dfs:Lorg/apache/hadoop/hdfs/DistributedFileSystem;
       4: aload_1
       5: invokevirtual #9                  // Method org/apache/hadoop/fs/Path.toUri:()Ljava/net/URI;
       8: invokevirtual #10                 // Method java/net/URI.getPath:()Ljava/lang/String;
      11: aload_0
      12: getfield      #2                  // Field val$overwrite:Z
      15: aload_0
      16: getfield      #3                  // Field val$createParent:Z
      19: aload_0
      20: getfield      #4                  // Field val$replication:S
      23: aload_0
      24: getfield      #5                  // Field val$blockSize:J
      27: aload_0
      28: getfield      #6                  // Field val$eventLoopGroup:Lorg/apache/hbase/thirdparty/io/netty/channel/EventLoopGroup;
      31: aload_0
      32: getfield      #7                  // Field val$channelClass:Ljava/lang/Class;
      35: invokestatic  #11                 // Method org/apache/hadoop/hbase/io/asyncfs/FanOutOneBlockAsyncDFSOutputHelper.access$400:(Lorg/apache/hadoop/hdfs/DistributedFileSystem;Ljava/lang/String;ZZSJLorg/apache/hbase/thirdparty/io/netty/channel/EventLoopGroup;Ljava/lang/Class;)Lorg/apache/hadoop/hbase/io/asyncfs/FanOutOneBlockAsyncDFSOutput;
      38: areturn

  public org.apache.hadoop.hbase.io.asyncfs.FanOutOneBlockAsyncDFSOutput next(org.apache.hadoop.fs.FileSystem, org.apache.hadoop.fs.Path) throws java.io.IOException;
    Code:
       0: new           #12                 // class java/lang/UnsupportedOperationException
       3: dup
       4: invokespecial #13                 // Method java/lang/UnsupportedOperationException."<init>":()V
       7: athrow

  public java.lang.Object next(org.apache.hadoop.fs.FileSystem, org.apache.hadoop.fs.Path) throws java.io.IOException;
    Code:
       0: aload_0
       1: aload_1
       2: aload_2
       3: invokevirtual #14                 // Method next:(Lorg/apache/hadoop/fs/FileSystem;Lorg/apache/hadoop/fs/Path;)Lorg/apache/hadoop/hbase/io/asyncfs/FanOutOneBlockAsyncDFSOutput;
       6: areturn

  public java.lang.Object doCall(org.apache.hadoop.fs.Path) throws java.io.IOException, org.apache.hadoop.fs.UnresolvedLinkException;
    Code:
       0: aload_0
       1: aload_1
       2: invokevirtual #15                 // Method doCall:(Lorg/apache/hadoop/fs/Path;)Lorg/apache/hadoop/hbase/io/asyncfs/FanOutOneBlockAsyncDFSOutput;
       5: areturn
}
