Compiled from "FanOutOneBlockAsyncDFSOutputSaslHelper.java"
public final class org.apache.hadoop.hbase.io.asyncfs.FanOutOneBlockAsyncDFSOutputSaslHelper {
  static void trySaslNegotiate(org.apache.hadoop.conf.Configuration, org.apache.hbase.thirdparty.io.netty.channel.Channel, org.apache.hadoop.hdfs.protocol.DatanodeInfo, int, org.apache.hadoop.hdfs.DFSClient, org.apache.hadoop.security.token.Token<org.apache.hadoop.hdfs.security.token.block.BlockTokenIdentifier>, org.apache.hbase.thirdparty.io.netty.util.concurrent.Promise<java.lang.Void>) throws java.io.IOException;
    Code:
       0: aload         4
       2: invokevirtual #70                 // Method org/apache/hadoop/hdfs/DFSClient.getSaslDataTransferClient:()Lorg/apache/hadoop/hdfs/protocol/datatransfer/sasl/SaslDataTransferClient;
       5: astore        7
       7: getstatic     #71                 // Field SASL_ADAPTOR:Lorg/apache/hadoop/hbase/io/asyncfs/FanOutOneBlockAsyncDFSOutputSaslHelper$SaslAdaptor;
      10: aload         7
      12: invokeinterface #72,  2           // InterfaceMethod org/apache/hadoop/hbase/io/asyncfs/FanOutOneBlockAsyncDFSOutputSaslHelper$SaslAdaptor.getSaslPropsResolver:(Lorg/apache/hadoop/hdfs/protocol/datatransfer/sasl/SaslDataTransferClient;)Lorg/apache/hadoop/security/SaslPropertiesResolver;
      17: astore        8
      19: getstatic     #71                 // Field SASL_ADAPTOR:Lorg/apache/hadoop/hbase/io/asyncfs/FanOutOneBlockAsyncDFSOutputSaslHelper$SaslAdaptor;
      22: aload         7
      24: invokeinterface #73,  2           // InterfaceMethod org/apache/hadoop/hbase/io/asyncfs/FanOutOneBlockAsyncDFSOutputSaslHelper$SaslAdaptor.getTrustedChannelResolver:(Lorg/apache/hadoop/hdfs/protocol/datatransfer/sasl/SaslDataTransferClient;)Lorg/apache/hadoop/hdfs/protocol/datatransfer/TrustedChannelResolver;
      29: astore        9
      31: getstatic     #71                 // Field SASL_ADAPTOR:Lorg/apache/hadoop/hbase/io/asyncfs/FanOutOneBlockAsyncDFSOutputSaslHelper$SaslAdaptor;
      34: aload         7
      36: invokeinterface #74,  2           // InterfaceMethod org/apache/hadoop/hbase/io/asyncfs/FanOutOneBlockAsyncDFSOutputSaslHelper$SaslAdaptor.getFallbackToSimpleAuth:(Lorg/apache/hadoop/hdfs/protocol/datatransfer/sasl/SaslDataTransferClient;)Ljava/util/concurrent/atomic/AtomicBoolean;
      41: astore        10
      43: aload_1
      44: invokeinterface #75,  1           // InterfaceMethod org/apache/hbase/thirdparty/io/netty/channel/Channel.remoteAddress:()Ljava/net/SocketAddress;
      49: checkcast     #76                 // class java/net/InetSocketAddress
      52: invokevirtual #77                 // Method java/net/InetSocketAddress.getAddress:()Ljava/net/InetAddress;
      55: astore        11
      57: aload         9
      59: invokevirtual #78                 // Method org/apache/hadoop/hdfs/protocol/datatransfer/TrustedChannelResolver.isTrusted:()Z
      62: ifne          75
      65: aload         9
      67: aload         11
      69: invokevirtual #79                 // Method org/apache/hadoop/hdfs/protocol/datatransfer/TrustedChannelResolver.isTrusted:(Ljava/net/InetAddress;)Z
      72: ifeq          85
      75: aload         6
      77: aconst_null
      78: invokeinterface #80,  2           // InterfaceMethod org/apache/hbase/thirdparty/io/netty/util/concurrent/Promise.trySuccess:(Ljava/lang/Object;)Z
      83: pop
      84: return
      85: aload         4
      87: invokevirtual #81                 // Method org/apache/hadoop/hdfs/DFSClient.newDataEncryptionKey:()Lorg/apache/hadoop/hdfs/security/token/block/DataEncryptionKey;
      90: astore        12
      92: aload         12
      94: ifnull        179
      97: getstatic     #1                  // Field LOG:Lorg/slf4j/Logger;
     100: invokeinterface #82,  1           // InterfaceMethod org/slf4j/Logger.isDebugEnabled:()Z
     105: ifeq          145
     108: getstatic     #1                  // Field LOG:Lorg/slf4j/Logger;
     111: new           #29                 // class java/lang/StringBuilder
     114: dup
     115: invokespecial #30                 // Method java/lang/StringBuilder."<init>":()V
     118: ldc           #83                 // String SASL client doing encrypted handshake for addr =
     120: invokevirtual #35                 // Method java/lang/StringBuilder.append:(Ljava/lang/String;)Ljava/lang/StringBuilder;
     123: aload         11
     125: invokevirtual #84                 // Method java/lang/StringBuilder.append:(Ljava/lang/Object;)Ljava/lang/StringBuilder;
     128: ldc           #85                 // String , datanodeId =
     130: invokevirtual #35                 // Method java/lang/StringBuilder.append:(Ljava/lang/String;)Ljava/lang/StringBuilder;
     133: aload_2
     134: invokevirtual #84                 // Method java/lang/StringBuilder.append:(Ljava/lang/Object;)Ljava/lang/StringBuilder;
     137: invokevirtual #42                 // Method java/lang/StringBuilder.toString:()Ljava/lang/String;
     140: invokeinterface #86,  2           // InterfaceMethod org/slf4j/Logger.debug:(Ljava/lang/String;)V
     145: aload_0
     146: aload_1
     147: iload_3
     148: aload         12
     150: invokestatic  #87                 // Method getUserNameFromEncryptionKey:(Lorg/apache/hadoop/hdfs/security/token/block/DataEncryptionKey;)Ljava/lang/String;
     153: aload         12
     155: getfield      #88                 // Field org/apache/hadoop/hdfs/security/token/block/DataEncryptionKey.encryptionKey:[B
     158: invokestatic  #89                 // Method encryptionKeyToPassword:([B)[C
     161: aload         12
     163: getfield      #90                 // Field org/apache/hadoop/hdfs/security/token/block/DataEncryptionKey.encryptionAlgorithm:Ljava/lang/String;
     166: invokestatic  #91                 // Method createSaslPropertiesForEncryption:(Ljava/lang/String;)Ljava/util/Map;
     169: aload         6
     171: aload         4
     173: invokestatic  #92                 // Method doSaslNegotiation:(Lorg/apache/hadoop/conf/Configuration;Lorg/apache/hbase/thirdparty/io/netty/channel/Channel;ILjava/lang/String;[CLjava/util/Map;Lorg/apache/hbase/thirdparty/io/netty/util/concurrent/Promise;Lorg/apache/hadoop/hdfs/DFSClient;)V
     176: goto          528
     179: invokestatic  #93                 // Method org/apache/hadoop/security/UserGroupInformation.isSecurityEnabled:()Z
     182: ifne          245
     185: getstatic     #1                  // Field LOG:Lorg/slf4j/Logger;
     188: invokeinterface #82,  1           // InterfaceMethod org/slf4j/Logger.isDebugEnabled:()Z
     193: ifeq          233
     196: getstatic     #1                  // Field LOG:Lorg/slf4j/Logger;
     199: new           #29                 // class java/lang/StringBuilder
     202: dup
     203: invokespecial #30                 // Method java/lang/StringBuilder."<init>":()V
     206: ldc           #94                 // String SASL client skipping handshake in unsecured configuration for addr =
     208: invokevirtual #35                 // Method java/lang/StringBuilder.append:(Ljava/lang/String;)Ljava/lang/StringBuilder;
     211: aload         11
     213: invokevirtual #84                 // Method java/lang/StringBuilder.append:(Ljava/lang/Object;)Ljava/lang/StringBuilder;
     216: ldc           #85                 // String , datanodeId =
     218: invokevirtual #35                 // Method java/lang/StringBuilder.append:(Ljava/lang/String;)Ljava/lang/StringBuilder;
     221: aload_2
     222: invokevirtual #84                 // Method java/lang/StringBuilder.append:(Ljava/lang/Object;)Ljava/lang/StringBuilder;
     225: invokevirtual #42                 // Method java/lang/StringBuilder.toString:()Ljava/lang/String;
     228: invokeinterface #86,  2           // InterfaceMethod org/slf4j/Logger.debug:(Ljava/lang/String;)V
     233: aload         6
     235: aconst_null
     236: invokeinterface #80,  2           // InterfaceMethod org/apache/hbase/thirdparty/io/netty/util/concurrent/Promise.trySuccess:(Ljava/lang/Object;)Z
     241: pop
     242: goto          528
     245: aload_2
     246: invokevirtual #95                 // Method org/apache/hadoop/hdfs/protocol/DatanodeInfo.getXferPort:()I
     249: sipush        1024
     252: if_icmpge     315
     255: getstatic     #1                  // Field LOG:Lorg/slf4j/Logger;
     258: invokeinterface #82,  1           // InterfaceMethod org/slf4j/Logger.isDebugEnabled:()Z
     263: ifeq          303
     266: getstatic     #1                  // Field LOG:Lorg/slf4j/Logger;
     269: new           #29                 // class java/lang/StringBuilder
     272: dup
     273: invokespecial #30                 // Method java/lang/StringBuilder."<init>":()V
     276: ldc           #96                 // String SASL client skipping handshake in secured configuration with privileged port for addr =
     278: invokevirtual #35                 // Method java/lang/StringBuilder.append:(Ljava/lang/String;)Ljava/lang/StringBuilder;
     281: aload         11
     283: invokevirtual #84                 // Method java/lang/StringBuilder.append:(Ljava/lang/Object;)Ljava/lang/StringBuilder;
     286: ldc           #85                 // String , datanodeId =
     288: invokevirtual #35                 // Method java/lang/StringBuilder.append:(Ljava/lang/String;)Ljava/lang/StringBuilder;
     291: aload_2
     292: invokevirtual #84                 // Method java/lang/StringBuilder.append:(Ljava/lang/Object;)Ljava/lang/StringBuilder;
     295: invokevirtual #42                 // Method java/lang/StringBuilder.toString:()Ljava/lang/String;
     298: invokeinterface #86,  2           // InterfaceMethod org/slf4j/Logger.debug:(Ljava/lang/String;)V
     303: aload         6
     305: aconst_null
     306: invokeinterface #80,  2           // InterfaceMethod org/apache/hbase/thirdparty/io/netty/util/concurrent/Promise.trySuccess:(Ljava/lang/Object;)Z
     311: pop
     312: goto          528
     315: aload         10
     317: ifnull        388
     320: aload         10
     322: invokevirtual #97                 // Method java/util/concurrent/atomic/AtomicBoolean.get:()Z
     325: ifeq          388
     328: getstatic     #1                  // Field LOG:Lorg/slf4j/Logger;
     331: invokeinterface #82,  1           // InterfaceMethod org/slf4j/Logger.isDebugEnabled:()Z
     336: ifeq          376
     339: getstatic     #1                  // Field LOG:Lorg/slf4j/Logger;
     342: new           #29                 // class java/lang/StringBuilder
     345: dup
     346: invokespecial #30                 // Method java/lang/StringBuilder."<init>":()V
     349: ldc           #98                 // String SASL client skipping handshake in secured configuration with unsecured cluster for addr =
     351: invokevirtual #35                 // Method java/lang/StringBuilder.append:(Ljava/lang/String;)Ljava/lang/StringBuilder;
     354: aload         11
     356: invokevirtual #84                 // Method java/lang/StringBuilder.append:(Ljava/lang/Object;)Ljava/lang/StringBuilder;
     359: ldc           #85                 // String , datanodeId =
     361: invokevirtual #35                 // Method java/lang/StringBuilder.append:(Ljava/lang/String;)Ljava/lang/StringBuilder;
     364: aload_2
     365: invokevirtual #84                 // Method java/lang/StringBuilder.append:(Ljava/lang/Object;)Ljava/lang/StringBuilder;
     368: invokevirtual #42                 // Method java/lang/StringBuilder.toString:()Ljava/lang/String;
     371: invokeinterface #86,  2           // InterfaceMethod org/slf4j/Logger.debug:(Ljava/lang/String;)V
     376: aload         6
     378: aconst_null
     379: invokeinterface #80,  2           // InterfaceMethod org/apache/hbase/thirdparty/io/netty/util/concurrent/Promise.trySuccess:(Ljava/lang/Object;)Z
     384: pop
     385: goto          528
     388: aload         8
     390: ifnull        471
     393: getstatic     #1                  // Field LOG:Lorg/slf4j/Logger;
     396: invokeinterface #82,  1           // InterfaceMethod org/slf4j/Logger.isDebugEnabled:()Z
     401: ifeq          441
     404: getstatic     #1                  // Field LOG:Lorg/slf4j/Logger;
     407: new           #29                 // class java/lang/StringBuilder
     410: dup
     411: invokespecial #30                 // Method java/lang/StringBuilder."<init>":()V
     414: ldc           #99                 // String SASL client doing general handshake for addr =
     416: invokevirtual #35                 // Method java/lang/StringBuilder.append:(Ljava/lang/String;)Ljava/lang/StringBuilder;
     419: aload         11
     421: invokevirtual #84                 // Method java/lang/StringBuilder.append:(Ljava/lang/Object;)Ljava/lang/StringBuilder;
     424: ldc           #85                 // String , datanodeId =
     426: invokevirtual #35                 // Method java/lang/StringBuilder.append:(Ljava/lang/String;)Ljava/lang/StringBuilder;
     429: aload_2
     430: invokevirtual #84                 // Method java/lang/StringBuilder.append:(Ljava/lang/Object;)Ljava/lang/StringBuilder;
     433: invokevirtual #42                 // Method java/lang/StringBuilder.toString:()Ljava/lang/String;
     436: invokeinterface #86,  2           // InterfaceMethod org/slf4j/Logger.debug:(Ljava/lang/String;)V
     441: aload_0
     442: aload_1
     443: iload_3
     444: aload         5
     446: invokestatic  #100                // Method buildUsername:(Lorg/apache/hadoop/security/token/Token;)Ljava/lang/String;
     449: aload         5
     451: invokestatic  #101                // Method buildClientPassword:(Lorg/apache/hadoop/security/token/Token;)[C
     454: aload         8
     456: aload         11
     458: invokevirtual #102                // Method org/apache/hadoop/security/SaslPropertiesResolver.getClientProperties:(Ljava/net/InetAddress;)Ljava/util/Map;
     461: aload         6
     463: aload         4
     465: invokestatic  #92                 // Method doSaslNegotiation:(Lorg/apache/hadoop/conf/Configuration;Lorg/apache/hbase/thirdparty/io/netty/channel/Channel;ILjava/lang/String;[CLjava/util/Map;Lorg/apache/hbase/thirdparty/io/netty/util/concurrent/Promise;Lorg/apache/hadoop/hdfs/DFSClient;)V
     468: goto          528
     471: getstatic     #1                  // Field LOG:Lorg/slf4j/Logger;
     474: invokeinterface #82,  1           // InterfaceMethod org/slf4j/Logger.isDebugEnabled:()Z
     479: ifeq          519
     482: getstatic     #1                  // Field LOG:Lorg/slf4j/Logger;
     485: new           #29                 // class java/lang/StringBuilder
     488: dup
     489: invokespecial #30                 // Method java/lang/StringBuilder."<init>":()V
     492: ldc           #103                // String SASL client skipping handshake in secured configuration with no SASL protection configured for addr =
     494: invokevirtual #35                 // Method java/lang/StringBuilder.append:(Ljava/lang/String;)Ljava/lang/StringBuilder;
     497: aload         11
     499: invokevirtual #84                 // Method java/lang/StringBuilder.append:(Ljava/lang/Object;)Ljava/lang/StringBuilder;
     502: ldc           #85                 // String , datanodeId =
     504: invokevirtual #35                 // Method java/lang/StringBuilder.append:(Ljava/lang/String;)Ljava/lang/StringBuilder;
     507: aload_2
     508: invokevirtual #84                 // Method java/lang/StringBuilder.append:(Ljava/lang/Object;)Ljava/lang/StringBuilder;
     511: invokevirtual #42                 // Method java/lang/StringBuilder.toString:()Ljava/lang/String;
     514: invokeinterface #86,  2           // InterfaceMethod org/slf4j/Logger.debug:(Ljava/lang/String;)V
     519: aload         6
     521: aconst_null
     522: invokeinterface #80,  2           // InterfaceMethod org/apache/hbase/thirdparty/io/netty/util/concurrent/Promise.trySuccess:(Ljava/lang/Object;)Z
     527: pop
     528: return

  static org.apache.hadoop.crypto.Encryptor createEncryptor(org.apache.hadoop.conf.Configuration, org.apache.hadoop.hdfs.protocol.HdfsFileStatus, org.apache.hadoop.hdfs.DFSClient) throws java.io.IOException;
    Code:
       0: aload_1
       1: invokevirtual #104                // Method org/apache/hadoop/hdfs/protocol/HdfsFileStatus.getFileEncryptionInfo:()Lorg/apache/hadoop/fs/FileEncryptionInfo;
       4: astore_3
       5: aload_3
       6: ifnonnull     11
       9: aconst_null
      10: areturn
      11: getstatic     #105                // Field TRANSPARENT_CRYPTO_HELPER:Lorg/apache/hadoop/hbase/io/asyncfs/FanOutOneBlockAsyncDFSOutputSaslHelper$TransparentCryptoHelper;
      14: aload_0
      15: aload_3
      16: aload_2
      17: invokeinterface #106,  4          // InterfaceMethod org/apache/hadoop/hbase/io/asyncfs/FanOutOneBlockAsyncDFSOutputSaslHelper$TransparentCryptoHelper.createEncryptor:(Lorg/apache/hadoop/conf/Configuration;Lorg/apache/hadoop/fs/FileEncryptionInfo;Lorg/apache/hadoop/hdfs/DFSClient;)Lorg/apache/hadoop/crypto/Encryptor;
      22: areturn

  static org.slf4j.Logger access$000();
    Code:
       0: getstatic     #1                  // Field LOG:Lorg/slf4j/Logger;
       3: areturn

  static {};
    Code:
       0: ldc           #33                 // class org/apache/hadoop/hbase/io/asyncfs/FanOutOneBlockAsyncDFSOutputSaslHelper
       2: invokestatic  #107                // Method org/slf4j/LoggerFactory.getLogger:(Ljava/lang/Class;)Lorg/slf4j/Logger;
       5: putstatic     #1                  // Field LOG:Lorg/slf4j/Logger;
       8: invokestatic  #108                // Method createSaslAdaptor:()Lorg/apache/hadoop/hbase/io/asyncfs/FanOutOneBlockAsyncDFSOutputSaslHelper$SaslAdaptor;
      11: putstatic     #71                 // Field SASL_ADAPTOR:Lorg/apache/hadoop/hbase/io/asyncfs/FanOutOneBlockAsyncDFSOutputSaslHelper$SaslAdaptor;
      14: invokestatic  #109                // Method createTransparentCryptoHelper:()Lorg/apache/hadoop/hbase/io/asyncfs/FanOutOneBlockAsyncDFSOutputSaslHelper$TransparentCryptoHelper;
      17: putstatic     #105                // Field TRANSPARENT_CRYPTO_HELPER:Lorg/apache/hadoop/hbase/io/asyncfs/FanOutOneBlockAsyncDFSOutputSaslHelper$TransparentCryptoHelper;
      20: goto          47
      23: astore_0
      24: ldc           #111                // String Couldn't properly initialize access to HDFS internals. Please update your WAL Provider to not make use of the 'asyncfs' provider. See HBASE-16110 for more information.
      26: astore_1
      27: getstatic     #1                  // Field LOG:Lorg/slf4j/Logger;
      30: aload_1
      31: aload_0
      32: invokeinterface #112,  3          // InterfaceMethod org/slf4j/Logger.error:(Ljava/lang/String;Ljava/lang/Throwable;)V
      37: new           #113                // class java/lang/Error
      40: dup
      41: aload_1
      42: aload_0
      43: invokespecial #114                // Method java/lang/Error."<init>":(Ljava/lang/String;Ljava/lang/Throwable;)V
      46: athrow
      47: return
    Exception table:
       from    to  target type
           8    20    23   Class java/lang/Exception
}
