Compiled from "FaultyProtobufLogReader.java"
public class org.apache.hadoop.hbase.regionserver.wal.FaultyProtobufLogReader extends org.apache.hadoop.hbase.regionserver.wal.ProtobufLogReader {
  java.util.Queue<org.apache.hadoop.hbase.wal.WAL$Entry> nextQueue;

  int numberOfFileEntries;

  public org.apache.hadoop.hbase.regionserver.wal.FaultyProtobufLogReader();
    Code:
       0: aload_0
       1: invokespecial #1                  // Method org/apache/hadoop/hbase/regionserver/wal/ProtobufLogReader."<init>":()V
       4: aload_0
       5: new           #2                  // class java/util/LinkedList
       8: dup
       9: invokespecial #3                  // Method java/util/LinkedList."<init>":()V
      12: putfield      #4                  // Field nextQueue:Ljava/util/Queue;
      15: aload_0
      16: iconst_0
      17: putfield      #5                  // Field numberOfFileEntries:I
      20: return

  org.apache.hadoop.hbase.regionserver.wal.FaultyProtobufLogReader$FailureType getFailureType();
    Code:
       0: aload_0
       1: getfield      #6                  // Field conf:Lorg/apache/hadoop/conf/Configuration;
       4: ldc           #7                  // String faultyprotobuflogreader.failuretype
       6: ldc           #8                  // String NONE
       8: invokevirtual #9                  // Method org/apache/hadoop/conf/Configuration.get:(Ljava/lang/String;Ljava/lang/String;)Ljava/lang/String;
      11: invokestatic  #10                 // Method org/apache/hadoop/hbase/regionserver/wal/FaultyProtobufLogReader$FailureType.valueOf:(Ljava/lang/String;)Lorg/apache/hadoop/hbase/regionserver/wal/FaultyProtobufLogReader$FailureType;
      14: areturn

  public org.apache.hadoop.hbase.wal.WAL$Entry next(org.apache.hadoop.hbase.wal.WAL$Entry) throws java.io.IOException;
    Code:
       0: aload_0
       1: getfield      #4                  // Field nextQueue:Ljava/util/Queue;
       4: invokeinterface #11,  1           // InterfaceMethod java/util/Queue.isEmpty:()Z
       9: ifeq          51
      12: new           #12                 // class org/apache/hadoop/hbase/wal/WAL$Entry
      15: dup
      16: invokespecial #13                 // Method org/apache/hadoop/hbase/wal/WAL$Entry."<init>":()V
      19: astore_3
      20: aload_0
      21: aload_3
      22: invokevirtual #14                 // Method readNext:(Lorg/apache/hadoop/hbase/wal/WAL$Entry;)Z
      25: istore_2
      26: aload_0
      27: getfield      #4                  // Field nextQueue:Ljava/util/Queue;
      30: aload_3
      31: invokeinterface #15,  2           // InterfaceMethod java/util/Queue.offer:(Ljava/lang/Object;)Z
      36: pop
      37: aload_0
      38: dup
      39: getfield      #5                  // Field numberOfFileEntries:I
      42: iconst_1
      43: iadd
      44: putfield      #5                  // Field numberOfFileEntries:I
      47: iload_2
      48: ifne          12
      51: aload_0
      52: getfield      #4                  // Field nextQueue:Ljava/util/Queue;
      55: invokeinterface #16,  1           // InterfaceMethod java/util/Queue.size:()I
      60: aload_0
      61: getfield      #5                  // Field numberOfFileEntries:I
      64: if_icmpne     87
      67: aload_0
      68: invokevirtual #17                 // Method getFailureType:()Lorg/apache/hadoop/hbase/regionserver/wal/FaultyProtobufLogReader$FailureType;
      71: getstatic     #18                 // Field org/apache/hadoop/hbase/regionserver/wal/FaultyProtobufLogReader$FailureType.BEGINNING:Lorg/apache/hadoop/hbase/regionserver/wal/FaultyProtobufLogReader$FailureType;
      74: if_acmpne     87
      77: new           #19                 // class java/io/IOException
      80: dup
      81: ldc           #20                 // String fake Exception
      83: invokespecial #21                 // Method java/io/IOException."<init>":(Ljava/lang/String;)V
      86: athrow
      87: aload_0
      88: getfield      #4                  // Field nextQueue:Ljava/util/Queue;
      91: invokeinterface #16,  1           // InterfaceMethod java/util/Queue.size:()I
      96: aload_0
      97: getfield      #5                  // Field numberOfFileEntries:I
     100: iconst_2
     101: idiv
     102: if_icmpne     125
     105: aload_0
     106: invokevirtual #17                 // Method getFailureType:()Lorg/apache/hadoop/hbase/regionserver/wal/FaultyProtobufLogReader$FailureType;
     109: getstatic     #22                 // Field org/apache/hadoop/hbase/regionserver/wal/FaultyProtobufLogReader$FailureType.MIDDLE:Lorg/apache/hadoop/hbase/regionserver/wal/FaultyProtobufLogReader$FailureType;
     112: if_acmpne     125
     115: new           #19                 // class java/io/IOException
     118: dup
     119: ldc           #20                 // String fake Exception
     121: invokespecial #21                 // Method java/io/IOException."<init>":(Ljava/lang/String;)V
     124: athrow
     125: aload_0
     126: getfield      #4                  // Field nextQueue:Ljava/util/Queue;
     129: invokeinterface #16,  1           // InterfaceMethod java/util/Queue.size:()I
     134: iconst_1
     135: if_icmpne     158
     138: aload_0
     139: invokevirtual #17                 // Method getFailureType:()Lorg/apache/hadoop/hbase/regionserver/wal/FaultyProtobufLogReader$FailureType;
     142: getstatic     #23                 // Field org/apache/hadoop/hbase/regionserver/wal/FaultyProtobufLogReader$FailureType.END:Lorg/apache/hadoop/hbase/regionserver/wal/FaultyProtobufLogReader$FailureType;
     145: if_acmpne     158
     148: new           #19                 // class java/io/IOException
     151: dup
     152: ldc           #20                 // String fake Exception
     154: invokespecial #21                 // Method java/io/IOException."<init>":(Ljava/lang/String;)V
     157: athrow
     158: aload_0
     159: getfield      #4                  // Field nextQueue:Ljava/util/Queue;
     162: invokeinterface #24,  1           // InterfaceMethod java/util/Queue.peek:()Ljava/lang/Object;
     167: ifnull        180
     170: aload_0
     171: dup
     172: getfield      #25                 // Field edit:J
     175: lconst_1
     176: ladd
     177: putfield      #25                 // Field edit:J
     180: aload_0
     181: getfield      #4                  // Field nextQueue:Ljava/util/Queue;
     184: invokeinterface #26,  1           // InterfaceMethod java/util/Queue.poll:()Ljava/lang/Object;
     189: checkcast     #12                 // class org/apache/hadoop/hbase/wal/WAL$Entry
     192: astore_2
     193: aload_2
     194: invokevirtual #27                 // Method org/apache/hadoop/hbase/wal/WAL$Entry.getEdit:()Lorg/apache/hadoop/hbase/wal/WALEdit;
     197: invokevirtual #28                 // Method org/apache/hadoop/hbase/wal/WALEdit.isEmpty:()Z
     200: ifeq          205
     203: aconst_null
     204: areturn
     205: aload_2
     206: areturn
}
