Compiled from "FavoredNodesManager.java"
public class org.apache.hadoop.hbase.favored.FavoredNodesManager {
  public org.apache.hadoop.hbase.favored.FavoredNodesManager(org.apache.hadoop.hbase.master.MasterServices);
    Code:
       0: aload_0
       1: invokespecial #3                  // Method java/lang/Object."<init>":()V
       4: aload_0
       5: aload_1
       6: putfield      #4                  // Field masterServices:Lorg/apache/hadoop/hbase/master/MasterServices;
       9: aload_0
      10: new           #5                  // class org/apache/hadoop/hbase/favored/FavoredNodesPlan
      13: dup
      14: invokespecial #6                  // Method org/apache/hadoop/hbase/favored/FavoredNodesPlan."<init>":()V
      17: putfield      #7                  // Field globalFavoredNodesAssignmentPlan:Lorg/apache/hadoop/hbase/favored/FavoredNodesPlan;
      20: aload_0
      21: new           #8                  // class java/util/HashMap
      24: dup
      25: invokespecial #9                  // Method java/util/HashMap."<init>":()V
      28: putfield      #10                 // Field primaryRSToRegionMap:Ljava/util/Map;
      31: aload_0
      32: new           #8                  // class java/util/HashMap
      35: dup
      36: invokespecial #9                  // Method java/util/HashMap."<init>":()V
      39: putfield      #11                 // Field secondaryRSToRegionMap:Ljava/util/Map;
      42: aload_0
      43: new           #8                  // class java/util/HashMap
      46: dup
      47: invokespecial #9                  // Method java/util/HashMap."<init>":()V
      50: putfield      #12                 // Field teritiaryRSToRegionMap:Ljava/util/Map;
      53: aload_0
      54: new           #13                 // class org/apache/hadoop/hbase/master/RackManager
      57: dup
      58: aload_1
      59: invokeinterface #14,  1           // InterfaceMethod org/apache/hadoop/hbase/master/MasterServices.getConfiguration:()Lorg/apache/hadoop/conf/Configuration;
      64: invokespecial #15                 // Method org/apache/hadoop/hbase/master/RackManager."<init>":(Lorg/apache/hadoop/conf/Configuration;)V
      67: putfield      #16                 // Field rackManager:Lorg/apache/hadoop/hbase/master/RackManager;
      70: return

  public void initialize(org.apache.hadoop.hbase.master.SnapshotOfRegionAssignmentFromMeta) throws org.apache.hadoop.hbase.HBaseIOException;
    Code:
       0: aload_0
       1: aload_1
       2: invokevirtual #17                 // Method org/apache/hadoop/hbase/master/SnapshotOfRegionAssignmentFromMeta.getExistingAssignmentPlan:()Lorg/apache/hadoop/hbase/favored/FavoredNodesPlan;
       5: putfield      #7                  // Field globalFavoredNodesAssignmentPlan:Lorg/apache/hadoop/hbase/favored/FavoredNodesPlan;
       8: aload_0
       9: aload_1
      10: invokevirtual #18                 // Method org/apache/hadoop/hbase/master/SnapshotOfRegionAssignmentFromMeta.getPrimaryToRegionInfoMap:()Ljava/util/Map;
      13: putfield      #10                 // Field primaryRSToRegionMap:Ljava/util/Map;
      16: aload_0
      17: aload_1
      18: invokevirtual #19                 // Method org/apache/hadoop/hbase/master/SnapshotOfRegionAssignmentFromMeta.getSecondaryToRegionInfoMap:()Ljava/util/Map;
      21: putfield      #11                 // Field secondaryRSToRegionMap:Ljava/util/Map;
      24: aload_0
      25: aload_1
      26: invokevirtual #20                 // Method org/apache/hadoop/hbase/master/SnapshotOfRegionAssignmentFromMeta.getTertiaryToRegionInfoMap:()Ljava/util/Map;
      29: putfield      #12                 // Field teritiaryRSToRegionMap:Ljava/util/Map;
      32: aload_0
      33: aload_0
      34: invokevirtual #21                 // Method getDataNodePort:()I
      37: putfield      #22                 // Field datanodeDataTransferPort:I
      40: return

  public int getDataNodePort();
    Code:
       0: invokestatic  #23                 // Method org/apache/hadoop/hdfs/HdfsConfiguration.init:()V
       3: new           #24                 // class org/apache/hadoop/hdfs/HdfsConfiguration
       6: dup
       7: aload_0
       8: getfield      #4                  // Field masterServices:Lorg/apache/hadoop/hbase/master/MasterServices;
      11: invokeinterface #14,  1           // InterfaceMethod org/apache/hadoop/hbase/master/MasterServices.getConfiguration:()Lorg/apache/hadoop/conf/Configuration;
      16: invokespecial #25                 // Method org/apache/hadoop/hdfs/HdfsConfiguration."<init>":(Lorg/apache/hadoop/conf/Configuration;)V
      19: astore_1
      20: aload_1
      21: ldc           #27                 // String dfs.datanode.address
      23: ldc           #28                 // String 0.0.0.0:50010
      25: invokevirtual #29                 // Method org/apache/hadoop/conf/Configuration.get:(Ljava/lang/String;Ljava/lang/String;)Ljava/lang/String;
      28: invokestatic  #30                 // Method org/apache/hadoop/net/NetUtils.createSocketAddr:(Ljava/lang/String;)Ljava/net/InetSocketAddress;
      31: invokevirtual #31                 // Method java/net/InetSocketAddress.getPort:()I
      34: istore_2
      35: getstatic     #32                 // Field LOG:Lorg/slf4j/Logger;
      38: new           #33                 // class java/lang/StringBuilder
      41: dup
      42: invokespecial #34                 // Method java/lang/StringBuilder."<init>":()V
      45: ldc           #35                 // String Loaded default datanode port for FN:
      47: invokevirtual #36                 // Method java/lang/StringBuilder.append:(Ljava/lang/String;)Ljava/lang/StringBuilder;
      50: aload_0
      51: getfield      #22                 // Field datanodeDataTransferPort:I
      54: invokevirtual #37                 // Method java/lang/StringBuilder.append:(I)Ljava/lang/StringBuilder;
      57: invokevirtual #38                 // Method java/lang/StringBuilder.toString:()Ljava/lang/String;
      60: invokeinterface #39,  2           // InterfaceMethod org/slf4j/Logger.debug:(Ljava/lang/String;)V
      65: iload_2
      66: ireturn

  public synchronized java.util.List<org.apache.hadoop.hbase.ServerName> getFavoredNodes(org.apache.hadoop.hbase.client.RegionInfo);
    Code:
       0: aload_0
       1: getfield      #7                  // Field globalFavoredNodesAssignmentPlan:Lorg/apache/hadoop/hbase/favored/FavoredNodesPlan;
       4: aload_1
       5: invokevirtual #40                 // Method org/apache/hadoop/hbase/favored/FavoredNodesPlan.getFavoredNodes:(Lorg/apache/hadoop/hbase/client/RegionInfo;)Ljava/util/List;
       8: areturn

  public static boolean isFavoredNodeApplicable(org.apache.hadoop.hbase.client.RegionInfo);
    Code:
       0: aload_0
       1: invokeinterface #41,  1           // InterfaceMethod org/apache/hadoop/hbase/client/RegionInfo.getTable:()Lorg/apache/hadoop/hbase/TableName;
       6: invokevirtual #42                 // Method org/apache/hadoop/hbase/TableName.isSystemTable:()Z
       9: ifne          16
      12: iconst_1
      13: goto          17
      16: iconst_0
      17: ireturn

  public static java.util.Set<org.apache.hadoop.hbase.client.RegionInfo> filterNonFNApplicableRegions(java.util.Collection<org.apache.hadoop.hbase.client.RegionInfo>);
    Code:
       0: invokestatic  #43                 // Method org/apache/hbase/thirdparty/com/google/common/collect/Sets.newHashSet:()Ljava/util/HashSet;
       3: astore_1
       4: aload_0
       5: invokeinterface #44,  1           // InterfaceMethod java/util/Collection.iterator:()Ljava/util/Iterator;
      10: astore_2
      11: aload_2
      12: invokeinterface #45,  1           // InterfaceMethod java/util/Iterator.hasNext:()Z
      17: ifeq          48
      20: aload_2
      21: invokeinterface #46,  1           // InterfaceMethod java/util/Iterator.next:()Ljava/lang/Object;
      26: checkcast     #47                 // class org/apache/hadoop/hbase/client/RegionInfo
      29: astore_3
      30: aload_3
      31: invokestatic  #48                 // Method isFavoredNodeApplicable:(Lorg/apache/hadoop/hbase/client/RegionInfo;)Z
      34: ifne          45
      37: aload_1
      38: aload_3
      39: invokeinterface #49,  2           // InterfaceMethod java/util/Set.add:(Ljava/lang/Object;)Z
      44: pop
      45: goto          11
      48: aload_1
      49: areturn

  public synchronized java.util.List<org.apache.hadoop.hbase.ServerName> getFavoredNodesWithDNPort(org.apache.hadoop.hbase.client.RegionInfo);
    Code:
       0: aload_0
       1: aload_1
       2: invokevirtual #50                 // Method getFavoredNodes:(Lorg/apache/hadoop/hbase/client/RegionInfo;)Ljava/util/List;
       5: ifnonnull     10
       8: aconst_null
       9: areturn
      10: invokestatic  #51                 // Method org/apache/hbase/thirdparty/com/google/common/collect/Lists.newArrayList:()Ljava/util/ArrayList;
      13: astore_2
      14: aload_0
      15: aload_1
      16: invokevirtual #50                 // Method getFavoredNodes:(Lorg/apache/hadoop/hbase/client/RegionInfo;)Ljava/util/List;
      19: invokeinterface #52,  1           // InterfaceMethod java/util/List.iterator:()Ljava/util/Iterator;
      24: astore_3
      25: aload_3
      26: invokeinterface #45,  1           // InterfaceMethod java/util/Iterator.hasNext:()Z
      31: ifeq          70
      34: aload_3
      35: invokeinterface #46,  1           // InterfaceMethod java/util/Iterator.next:()Ljava/lang/Object;
      40: checkcast     #1                  // class org/apache/hadoop/hbase/ServerName
      43: astore        4
      45: aload_2
      46: aload         4
      48: invokevirtual #53                 // Method org/apache/hadoop/hbase/ServerName.getHostname:()Ljava/lang/String;
      51: aload_0
      52: getfield      #22                 // Field datanodeDataTransferPort:I
      55: ldc2_w        #54                 // long -1l
      58: invokestatic  #56                 // Method org/apache/hadoop/hbase/ServerName.valueOf:(Ljava/lang/String;IJ)Lorg/apache/hadoop/hbase/ServerName;
      61: invokeinterface #57,  2           // InterfaceMethod java/util/List.add:(Ljava/lang/Object;)Z
      66: pop
      67: goto          25
      70: aload_2
      71: areturn

  public synchronized void updateFavoredNodes(java.util.Map<org.apache.hadoop.hbase.client.RegionInfo, java.util.List<org.apache.hadoop.hbase.ServerName>>) throws java.io.IOException;
    Code:
       0: new           #8                  // class java/util/HashMap
       3: dup
       4: invokespecial #9                  // Method java/util/HashMap."<init>":()V
       7: astore_2
       8: aload_1
       9: invokeinterface #58,  1           // InterfaceMethod java/util/Map.entrySet:()Ljava/util/Set;
      14: invokeinterface #59,  1           // InterfaceMethod java/util/Set.iterator:()Ljava/util/Iterator;
      19: astore_3
      20: aload_3
      21: invokeinterface #45,  1           // InterfaceMethod java/util/Iterator.hasNext:()Z
      26: ifeq          317
      29: aload_3
      30: invokeinterface #46,  1           // InterfaceMethod java/util/Iterator.next:()Ljava/lang/Object;
      35: checkcast     #60                 // class java/util/Map$Entry
      38: astore        4
      40: aload         4
      42: invokeinterface #61,  1           // InterfaceMethod java/util/Map$Entry.getKey:()Ljava/lang/Object;
      47: checkcast     #47                 // class org/apache/hadoop/hbase/client/RegionInfo
      50: astore        5
      52: aload         4
      54: invokeinterface #62,  1           // InterfaceMethod java/util/Map$Entry.getValue:()Ljava/lang/Object;
      59: checkcast     #63                 // class java/util/List
      62: astore        6
      64: aload         6
      66: invokeinterface #64,  1           // InterfaceMethod java/util/List.size:()I
      71: aload         6
      73: invokestatic  #65                 // Method org/apache/hbase/thirdparty/com/google/common/collect/Sets.newHashSet:(Ljava/lang/Iterable;)Ljava/util/HashSet;
      76: invokevirtual #66                 // Method java/util/HashSet.size:()I
      79: if_icmpeq     110
      82: new           #67                 // class java/io/IOException
      85: dup
      86: new           #33                 // class java/lang/StringBuilder
      89: dup
      90: invokespecial #34                 // Method java/lang/StringBuilder."<init>":()V
      93: ldc           #68                 // String Duplicates found:
      95: invokevirtual #36                 // Method java/lang/StringBuilder.append:(Ljava/lang/String;)Ljava/lang/StringBuilder;
      98: aload         6
     100: invokevirtual #69                 // Method java/lang/StringBuilder.append:(Ljava/lang/Object;)Ljava/lang/StringBuilder;
     103: invokevirtual #38                 // Method java/lang/StringBuilder.toString:()Ljava/lang/String;
     106: invokespecial #70                 // Method java/io/IOException."<init>":(Ljava/lang/String;)V
     109: athrow
     110: aload         5
     112: invokestatic  #48                 // Method isFavoredNodeApplicable:(Lorg/apache/hadoop/hbase/client/RegionInfo;)Z
     115: ifne          161
     118: new           #67                 // class java/io/IOException
     121: dup
     122: new           #33                 // class java/lang/StringBuilder
     125: dup
     126: invokespecial #34                 // Method java/lang/StringBuilder."<init>":()V
     129: ldc           #71                 // String Can't update FN for a un-applicable region:
     131: invokevirtual #36                 // Method java/lang/StringBuilder.append:(Ljava/lang/String;)Ljava/lang/StringBuilder;
     134: aload         5
     136: invokeinterface #72,  1           // InterfaceMethod org/apache/hadoop/hbase/client/RegionInfo.getRegionNameAsString:()Ljava/lang/String;
     141: invokevirtual #36                 // Method java/lang/StringBuilder.append:(Ljava/lang/String;)Ljava/lang/StringBuilder;
     144: ldc           #73                 // String  with
     146: invokevirtual #36                 // Method java/lang/StringBuilder.append:(Ljava/lang/String;)Ljava/lang/StringBuilder;
     149: aload         6
     151: invokevirtual #69                 // Method java/lang/StringBuilder.append:(Ljava/lang/Object;)Ljava/lang/StringBuilder;
     154: invokevirtual #38                 // Method java/lang/StringBuilder.toString:()Ljava/lang/String;
     157: invokespecial #70                 // Method java/io/IOException."<init>":(Ljava/lang/String;)V
     160: athrow
     161: aload         6
     163: invokeinterface #64,  1           // InterfaceMethod java/util/List.size:()I
     168: iconst_3
     169: if_icmpeq     215
     172: new           #67                 // class java/io/IOException
     175: dup
     176: new           #33                 // class java/lang/StringBuilder
     179: dup
     180: invokespecial #34                 // Method java/lang/StringBuilder."<init>":()V
     183: ldc           #74                 // String At least 3 favored nodes should be present for region :
     185: invokevirtual #36                 // Method java/lang/StringBuilder.append:(Ljava/lang/String;)Ljava/lang/StringBuilder;
     188: aload         5
     190: invokeinterface #75,  1           // InterfaceMethod org/apache/hadoop/hbase/client/RegionInfo.getEncodedName:()Ljava/lang/String;
     195: invokevirtual #36                 // Method java/lang/StringBuilder.append:(Ljava/lang/String;)Ljava/lang/StringBuilder;
     198: ldc           #76                 // String  current FN servers:
     200: invokevirtual #36                 // Method java/lang/StringBuilder.append:(Ljava/lang/String;)Ljava/lang/StringBuilder;
     203: aload         6
     205: invokevirtual #69                 // Method java/lang/StringBuilder.append:(Ljava/lang/Object;)Ljava/lang/StringBuilder;
     208: invokevirtual #38                 // Method java/lang/StringBuilder.toString:()Ljava/lang/String;
     211: invokespecial #70                 // Method java/io/IOException."<init>":(Ljava/lang/String;)V
     214: athrow
     215: invokestatic  #51                 // Method org/apache/hbase/thirdparty/com/google/common/collect/Lists.newArrayList:()Ljava/util/ArrayList;
     218: astore        7
     220: aload         6
     222: invokeinterface #52,  1           // InterfaceMethod java/util/List.iterator:()Ljava/util/Iterator;
     227: astore        8
     229: aload         8
     231: invokeinterface #45,  1           // InterfaceMethod java/util/Iterator.hasNext:()Z
     236: ifeq          303
     239: aload         8
     241: invokeinterface #46,  1           // InterfaceMethod java/util/Iterator.next:()Ljava/lang/Object;
     246: checkcast     #1                  // class org/apache/hadoop/hbase/ServerName
     249: astore        9
     251: aload         9
     253: invokevirtual #77                 // Method org/apache/hadoop/hbase/ServerName.getStartcode:()J
     256: ldc2_w        #54                 // long -1l
     259: lcmp
     260: ifne          276
     263: aload         7
     265: aload         9
     267: invokeinterface #57,  2           // InterfaceMethod java/util/List.add:(Ljava/lang/Object;)Z
     272: pop
     273: goto          300
     276: aload         7
     278: aload         9
     280: invokevirtual #53                 // Method org/apache/hadoop/hbase/ServerName.getHostname:()Ljava/lang/String;
     283: aload         9
     285: invokevirtual #78                 // Method org/apache/hadoop/hbase/ServerName.getPort:()I
     288: ldc2_w        #54                 // long -1l
     291: invokestatic  #56                 // Method org/apache/hadoop/hbase/ServerName.valueOf:(Ljava/lang/String;IJ)Lorg/apache/hadoop/hbase/ServerName;
     294: invokeinterface #57,  2           // InterfaceMethod java/util/List.add:(Ljava/lang/Object;)Z
     299: pop
     300: goto          229
     303: aload_2
     304: aload         5
     306: aload         7
     308: invokeinterface #79,  3           // InterfaceMethod java/util/Map.put:(Ljava/lang/Object;Ljava/lang/Object;)Ljava/lang/Object;
     313: pop
     314: goto          20
     317: aload_2
     318: aload_0
     319: getfield      #4                  // Field masterServices:Lorg/apache/hadoop/hbase/master/MasterServices;
     322: invokeinterface #80,  1           // InterfaceMethod org/apache/hadoop/hbase/master/MasterServices.getConnection:()Lorg/apache/hadoop/hbase/client/Connection;
     327: invokestatic  #81                 // Method org/apache/hadoop/hbase/favored/FavoredNodeAssignmentHelper.updateMetaWithFavoredNodesInfo:(Ljava/util/Map;Lorg/apache/hadoop/hbase/client/Connection;)V
     330: aload_0
     331: aload_2
     332: invokeinterface #82,  1           // InterfaceMethod java/util/Map.keySet:()Ljava/util/Set;
     337: invokevirtual #83                 // Method deleteFavoredNodesForRegions:(Ljava/util/Collection;)V
     340: aload_2
     341: invokeinterface #58,  1           // InterfaceMethod java/util/Map.entrySet:()Ljava/util/Set;
     346: invokeinterface #59,  1           // InterfaceMethod java/util/Set.iterator:()Ljava/util/Iterator;
     351: astore_3
     352: aload_3
     353: invokeinterface #45,  1           // InterfaceMethod java/util/Iterator.hasNext:()Z
     358: ifeq          418
     361: aload_3
     362: invokeinterface #46,  1           // InterfaceMethod java/util/Iterator.next:()Ljava/lang/Object;
     367: checkcast     #60                 // class java/util/Map$Entry
     370: astore        4
     372: aload         4
     374: invokeinterface #61,  1           // InterfaceMethod java/util/Map$Entry.getKey:()Ljava/lang/Object;
     379: checkcast     #47                 // class org/apache/hadoop/hbase/client/RegionInfo
     382: astore        5
     384: aload         4
     386: invokeinterface #62,  1           // InterfaceMethod java/util/Map$Entry.getValue:()Ljava/lang/Object;
     391: checkcast     #63                 // class java/util/List
     394: astore        6
     396: aload_0
     397: getfield      #7                  // Field globalFavoredNodesAssignmentPlan:Lorg/apache/hadoop/hbase/favored/FavoredNodesPlan;
     400: aload         5
     402: aload         6
     404: invokevirtual #84                 // Method org/apache/hadoop/hbase/favored/FavoredNodesPlan.updateFavoredNodesMap:(Lorg/apache/hadoop/hbase/client/RegionInfo;Ljava/util/List;)V
     407: aload_0
     408: aload         5
     410: aload         6
     412: invokespecial #85                 // Method addToReplicaLoad:(Lorg/apache/hadoop/hbase/client/RegionInfo;Ljava/util/List;)V
     415: goto          352
     418: return

  public synchronized java.util.Map<org.apache.hadoop.hbase.ServerName, java.util.List<java.lang.Integer>> getReplicaLoad(java.util.List<org.apache.hadoop.hbase.ServerName>);
    Code:
       0: invokestatic  #96                 // Method org/apache/hbase/thirdparty/com/google/common/collect/Maps.newHashMap:()Ljava/util/HashMap;
       3: astore_2
       4: aload_1
       5: invokeinterface #52,  1           // InterfaceMethod java/util/List.iterator:()Ljava/util/Iterator;
      10: astore_3
      11: aload_3
      12: invokeinterface #45,  1           // InterfaceMethod java/util/Iterator.hasNext:()Z
      17: ifeq          240
      20: aload_3
      21: invokeinterface #46,  1           // InterfaceMethod java/util/Iterator.next:()Ljava/lang/Object;
      26: checkcast     #1                  // class org/apache/hadoop/hbase/ServerName
      29: astore        4
      31: aload         4
      33: invokevirtual #89                 // Method org/apache/hadoop/hbase/ServerName.getHostAndPort:()Ljava/lang/String;
      36: ldc2_w        #54                 // long -1l
      39: invokestatic  #90                 // Method org/apache/hadoop/hbase/ServerName.valueOf:(Ljava/lang/String;J)Lorg/apache/hadoop/hbase/ServerName;
      42: astore        5
      44: invokestatic  #51                 // Method org/apache/hbase/thirdparty/com/google/common/collect/Lists.newArrayList:()Ljava/util/ArrayList;
      47: astore        6
      49: aload_0
      50: getfield      #10                 // Field primaryRSToRegionMap:Ljava/util/Map;
      53: aload         5
      55: invokeinterface #97,  2           // InterfaceMethod java/util/Map.containsKey:(Ljava/lang/Object;)Z
      60: ifeq          96
      63: aload         6
      65: aload_0
      66: getfield      #10                 // Field primaryRSToRegionMap:Ljava/util/Map;
      69: aload         5
      71: invokeinterface #91,  2           // InterfaceMethod java/util/Map.get:(Ljava/lang/Object;)Ljava/lang/Object;
      76: checkcast     #63                 // class java/util/List
      79: invokeinterface #64,  1           // InterfaceMethod java/util/List.size:()I
      84: invokestatic  #98                 // Method java/lang/Integer.valueOf:(I)Ljava/lang/Integer;
      87: invokeinterface #57,  2           // InterfaceMethod java/util/List.add:(Ljava/lang/Object;)Z
      92: pop
      93: goto          108
      96: aload         6
      98: iconst_0
      99: invokestatic  #98                 // Method java/lang/Integer.valueOf:(I)Ljava/lang/Integer;
     102: invokeinterface #57,  2           // InterfaceMethod java/util/List.add:(Ljava/lang/Object;)Z
     107: pop
     108: aload_0
     109: getfield      #11                 // Field secondaryRSToRegionMap:Ljava/util/Map;
     112: aload         5
     114: invokeinterface #97,  2           // InterfaceMethod java/util/Map.containsKey:(Ljava/lang/Object;)Z
     119: ifeq          155
     122: aload         6
     124: aload_0
     125: getfield      #11                 // Field secondaryRSToRegionMap:Ljava/util/Map;
     128: aload         5
     130: invokeinterface #91,  2           // InterfaceMethod java/util/Map.get:(Ljava/lang/Object;)Ljava/lang/Object;
     135: checkcast     #63                 // class java/util/List
     138: invokeinterface #64,  1           // InterfaceMethod java/util/List.size:()I
     143: invokestatic  #98                 // Method java/lang/Integer.valueOf:(I)Ljava/lang/Integer;
     146: invokeinterface #57,  2           // InterfaceMethod java/util/List.add:(Ljava/lang/Object;)Z
     151: pop
     152: goto          167
     155: aload         6
     157: iconst_0
     158: invokestatic  #98                 // Method java/lang/Integer.valueOf:(I)Ljava/lang/Integer;
     161: invokeinterface #57,  2           // InterfaceMethod java/util/List.add:(Ljava/lang/Object;)Z
     166: pop
     167: aload_0
     168: getfield      #12                 // Field teritiaryRSToRegionMap:Ljava/util/Map;
     171: aload         5
     173: invokeinterface #97,  2           // InterfaceMethod java/util/Map.containsKey:(Ljava/lang/Object;)Z
     178: ifeq          214
     181: aload         6
     183: aload_0
     184: getfield      #12                 // Field teritiaryRSToRegionMap:Ljava/util/Map;
     187: aload         5
     189: invokeinterface #91,  2           // InterfaceMethod java/util/Map.get:(Ljava/lang/Object;)Ljava/lang/Object;
     194: checkcast     #63                 // class java/util/List
     197: invokeinterface #64,  1           // InterfaceMethod java/util/List.size:()I
     202: invokestatic  #98                 // Method java/lang/Integer.valueOf:(I)Ljava/lang/Integer;
     205: invokeinterface #57,  2           // InterfaceMethod java/util/List.add:(Ljava/lang/Object;)Z
     210: pop
     211: goto          226
     214: aload         6
     216: iconst_0
     217: invokestatic  #98                 // Method java/lang/Integer.valueOf:(I)Ljava/lang/Integer;
     220: invokeinterface #57,  2           // InterfaceMethod java/util/List.add:(Ljava/lang/Object;)Z
     225: pop
     226: aload_2
     227: aload         4
     229: aload         6
     231: invokeinterface #79,  3           // InterfaceMethod java/util/Map.put:(Ljava/lang/Object;Ljava/lang/Object;)Ljava/lang/Object;
     236: pop
     237: goto          11
     240: aload_2
     241: areturn

  public synchronized void deleteFavoredNodesForRegion(org.apache.hadoop.hbase.client.RegionInfo);
    Code:
       0: aload_0
       1: aload_1
       2: invokevirtual #50                 // Method getFavoredNodes:(Lorg/apache/hadoop/hbase/client/RegionInfo;)Ljava/util/List;
       5: astore_2
       6: aload_2
       7: ifnull        184
      10: aload_0
      11: getfield      #10                 // Field primaryRSToRegionMap:Ljava/util/Map;
      14: aload_2
      15: getstatic     #86                 // Field org/apache/hadoop/hbase/favored/FavoredNodesPlan$Position.PRIMARY:Lorg/apache/hadoop/hbase/favored/FavoredNodesPlan$Position;
      18: invokevirtual #87                 // Method org/apache/hadoop/hbase/favored/FavoredNodesPlan$Position.ordinal:()I
      21: invokeinterface #88,  2           // InterfaceMethod java/util/List.get:(I)Ljava/lang/Object;
      26: invokeinterface #97,  2           // InterfaceMethod java/util/Map.containsKey:(Ljava/lang/Object;)Z
      31: ifeq          65
      34: aload_0
      35: getfield      #10                 // Field primaryRSToRegionMap:Ljava/util/Map;
      38: aload_2
      39: getstatic     #86                 // Field org/apache/hadoop/hbase/favored/FavoredNodesPlan$Position.PRIMARY:Lorg/apache/hadoop/hbase/favored/FavoredNodesPlan$Position;
      42: invokevirtual #87                 // Method org/apache/hadoop/hbase/favored/FavoredNodesPlan$Position.ordinal:()I
      45: invokeinterface #88,  2           // InterfaceMethod java/util/List.get:(I)Ljava/lang/Object;
      50: invokeinterface #91,  2           // InterfaceMethod java/util/Map.get:(Ljava/lang/Object;)Ljava/lang/Object;
      55: checkcast     #63                 // class java/util/List
      58: aload_1
      59: invokeinterface #99,  2           // InterfaceMethod java/util/List.remove:(Ljava/lang/Object;)Z
      64: pop
      65: aload_0
      66: getfield      #11                 // Field secondaryRSToRegionMap:Ljava/util/Map;
      69: aload_2
      70: getstatic     #94                 // Field org/apache/hadoop/hbase/favored/FavoredNodesPlan$Position.SECONDARY:Lorg/apache/hadoop/hbase/favored/FavoredNodesPlan$Position;
      73: invokevirtual #87                 // Method org/apache/hadoop/hbase/favored/FavoredNodesPlan$Position.ordinal:()I
      76: invokeinterface #88,  2           // InterfaceMethod java/util/List.get:(I)Ljava/lang/Object;
      81: invokeinterface #97,  2           // InterfaceMethod java/util/Map.containsKey:(Ljava/lang/Object;)Z
      86: ifeq          120
      89: aload_0
      90: getfield      #11                 // Field secondaryRSToRegionMap:Ljava/util/Map;
      93: aload_2
      94: getstatic     #94                 // Field org/apache/hadoop/hbase/favored/FavoredNodesPlan$Position.SECONDARY:Lorg/apache/hadoop/hbase/favored/FavoredNodesPlan$Position;
      97: invokevirtual #87                 // Method org/apache/hadoop/hbase/favored/FavoredNodesPlan$Position.ordinal:()I
     100: invokeinterface #88,  2           // InterfaceMethod java/util/List.get:(I)Ljava/lang/Object;
     105: invokeinterface #91,  2           // InterfaceMethod java/util/Map.get:(Ljava/lang/Object;)Ljava/lang/Object;
     110: checkcast     #63                 // class java/util/List
     113: aload_1
     114: invokeinterface #99,  2           // InterfaceMethod java/util/List.remove:(Ljava/lang/Object;)Z
     119: pop
     120: aload_0
     121: getfield      #12                 // Field teritiaryRSToRegionMap:Ljava/util/Map;
     124: aload_2
     125: getstatic     #95                 // Field org/apache/hadoop/hbase/favored/FavoredNodesPlan$Position.TERTIARY:Lorg/apache/hadoop/hbase/favored/FavoredNodesPlan$Position;
     128: invokevirtual #87                 // Method org/apache/hadoop/hbase/favored/FavoredNodesPlan$Position.ordinal:()I
     131: invokeinterface #88,  2           // InterfaceMethod java/util/List.get:(I)Ljava/lang/Object;
     136: invokeinterface #97,  2           // InterfaceMethod java/util/Map.containsKey:(Ljava/lang/Object;)Z
     141: ifeq          175
     144: aload_0
     145: getfield      #12                 // Field teritiaryRSToRegionMap:Ljava/util/Map;
     148: aload_2
     149: getstatic     #95                 // Field org/apache/hadoop/hbase/favored/FavoredNodesPlan$Position.TERTIARY:Lorg/apache/hadoop/hbase/favored/FavoredNodesPlan$Position;
     152: invokevirtual #87                 // Method org/apache/hadoop/hbase/favored/FavoredNodesPlan$Position.ordinal:()I
     155: invokeinterface #88,  2           // InterfaceMethod java/util/List.get:(I)Ljava/lang/Object;
     160: invokeinterface #91,  2           // InterfaceMethod java/util/Map.get:(Ljava/lang/Object;)Ljava/lang/Object;
     165: checkcast     #63                 // class java/util/List
     168: aload_1
     169: invokeinterface #99,  2           // InterfaceMethod java/util/List.remove:(Ljava/lang/Object;)Z
     174: pop
     175: aload_0
     176: getfield      #7                  // Field globalFavoredNodesAssignmentPlan:Lorg/apache/hadoop/hbase/favored/FavoredNodesPlan;
     179: aload_1
     180: invokevirtual #100                // Method org/apache/hadoop/hbase/favored/FavoredNodesPlan.removeFavoredNodes:(Lorg/apache/hadoop/hbase/client/RegionInfo;)Ljava/util/List;
     183: pop
     184: return

  public synchronized void deleteFavoredNodesForRegions(java.util.Collection<org.apache.hadoop.hbase.client.RegionInfo>);
    Code:
       0: aload_1
       1: invokeinterface #44,  1           // InterfaceMethod java/util/Collection.iterator:()Ljava/util/Iterator;
       6: astore_2
       7: aload_2
       8: invokeinterface #45,  1           // InterfaceMethod java/util/Iterator.hasNext:()Z
      13: ifeq          34
      16: aload_2
      17: invokeinterface #46,  1           // InterfaceMethod java/util/Iterator.next:()Ljava/lang/Object;
      22: checkcast     #47                 // class org/apache/hadoop/hbase/client/RegionInfo
      25: astore_3
      26: aload_0
      27: aload_3
      28: invokevirtual #101                // Method deleteFavoredNodesForRegion:(Lorg/apache/hadoop/hbase/client/RegionInfo;)V
      31: goto          7
      34: return

  public synchronized java.util.Set<org.apache.hadoop.hbase.client.RegionInfo> getRegionsOfFavoredNode(org.apache.hadoop.hbase.ServerName);
    Code:
       0: invokestatic  #43                 // Method org/apache/hbase/thirdparty/com/google/common/collect/Sets.newHashSet:()Ljava/util/HashSet;
       3: astore_2
       4: aload_1
       5: invokevirtual #89                 // Method org/apache/hadoop/hbase/ServerName.getHostAndPort:()Ljava/lang/String;
       8: ldc2_w        #54                 // long -1l
      11: invokestatic  #90                 // Method org/apache/hadoop/hbase/ServerName.valueOf:(Ljava/lang/String;J)Lorg/apache/hadoop/hbase/ServerName;
      14: astore_3
      15: aload_0
      16: getfield      #10                 // Field primaryRSToRegionMap:Ljava/util/Map;
      19: aload_3
      20: invokeinterface #97,  2           // InterfaceMethod java/util/Map.containsKey:(Ljava/lang/Object;)Z
      25: ifeq          48
      28: aload_2
      29: aload_0
      30: getfield      #10                 // Field primaryRSToRegionMap:Ljava/util/Map;
      33: aload_3
      34: invokeinterface #91,  2           // InterfaceMethod java/util/Map.get:(Ljava/lang/Object;)Ljava/lang/Object;
      39: checkcast     #102                // class java/util/Collection
      42: invokeinterface #103,  2          // InterfaceMethod java/util/Set.addAll:(Ljava/util/Collection;)Z
      47: pop
      48: aload_0
      49: getfield      #11                 // Field secondaryRSToRegionMap:Ljava/util/Map;
      52: aload_3
      53: invokeinterface #97,  2           // InterfaceMethod java/util/Map.containsKey:(Ljava/lang/Object;)Z
      58: ifeq          81
      61: aload_2
      62: aload_0
      63: getfield      #11                 // Field secondaryRSToRegionMap:Ljava/util/Map;
      66: aload_3
      67: invokeinterface #91,  2           // InterfaceMethod java/util/Map.get:(Ljava/lang/Object;)Ljava/lang/Object;
      72: checkcast     #102                // class java/util/Collection
      75: invokeinterface #103,  2          // InterfaceMethod java/util/Set.addAll:(Ljava/util/Collection;)Z
      80: pop
      81: aload_0
      82: getfield      #12                 // Field teritiaryRSToRegionMap:Ljava/util/Map;
      85: aload_3
      86: invokeinterface #97,  2           // InterfaceMethod java/util/Map.containsKey:(Ljava/lang/Object;)Z
      91: ifeq          114
      94: aload_2
      95: aload_0
      96: getfield      #12                 // Field teritiaryRSToRegionMap:Ljava/util/Map;
      99: aload_3
     100: invokeinterface #91,  2           // InterfaceMethod java/util/Map.get:(Ljava/lang/Object;)Ljava/lang/Object;
     105: checkcast     #102                // class java/util/Collection
     108: invokeinterface #103,  2          // InterfaceMethod java/util/Set.addAll:(Ljava/util/Collection;)Z
     113: pop
     114: aload_2
     115: areturn

  public org.apache.hadoop.hbase.master.RackManager getRackManager();
    Code:
       0: aload_0
       1: getfield      #16                 // Field rackManager:Lorg/apache/hadoop/hbase/master/RackManager;
       4: areturn

  static {};
    Code:
       0: ldc           #104                // class org/apache/hadoop/hbase/favored/FavoredNodesManager
       2: invokestatic  #105                // Method org/slf4j/LoggerFactory.getLogger:(Ljava/lang/Class;)Lorg/slf4j/Logger;
       5: putstatic     #32                 // Field LOG:Lorg/slf4j/Logger;
       8: return
}
