Compiled from "FavoredStochasticBalancer.java"
public class org.apache.hadoop.hbase.master.balancer.FavoredStochasticBalancer extends org.apache.hadoop.hbase.master.balancer.StochasticLoadBalancer implements org.apache.hadoop.hbase.favored.FavoredNodesPromoter {
  public org.apache.hadoop.hbase.master.balancer.FavoredStochasticBalancer();
    Code:
       0: aload_0
       1: invokespecial #5                  // Method org/apache/hadoop/hbase/master/balancer/StochasticLoadBalancer."<init>":()V
       4: return

  public void initialize() throws org.apache.hadoop.hbase.HBaseIOException;
    Code:
       0: aload_0
       1: invokevirtual #6                  // Method configureGenerators:()V
       4: aload_0
       5: invokespecial #7                  // Method org/apache/hadoop/hbase/master/balancer/StochasticLoadBalancer.initialize:()V
       8: return

  protected void configureGenerators();
    Code:
       0: new           #8                  // class java/util/ArrayList
       3: dup
       4: iconst_2
       5: invokespecial #9                  // Method java/util/ArrayList."<init>":(I)V
       8: astore_1
       9: aload_1
      10: new           #10                 // class org/apache/hadoop/hbase/master/balancer/FavoredStochasticBalancer$FavoredNodeLoadPicker
      13: dup
      14: aload_0
      15: invokespecial #11                 // Method org/apache/hadoop/hbase/master/balancer/FavoredStochasticBalancer$FavoredNodeLoadPicker."<init>":(Lorg/apache/hadoop/hbase/master/balancer/FavoredStochasticBalancer;)V
      18: invokeinterface #12,  2           // InterfaceMethod java/util/List.add:(Ljava/lang/Object;)Z
      23: pop
      24: aload_1
      25: new           #13                 // class org/apache/hadoop/hbase/master/balancer/FavoredStochasticBalancer$FavoredNodeLocalityPicker
      28: dup
      29: aload_0
      30: aconst_null
      31: invokespecial #14                 // Method org/apache/hadoop/hbase/master/balancer/FavoredStochasticBalancer$FavoredNodeLocalityPicker."<init>":(Lorg/apache/hadoop/hbase/master/balancer/FavoredStochasticBalancer;Lorg/apache/hadoop/hbase/master/balancer/FavoredStochasticBalancer$1;)V
      34: invokeinterface #12,  2           // InterfaceMethod java/util/List.add:(Ljava/lang/Object;)Z
      39: pop
      40: aload_0
      41: aload_1
      42: invokevirtual #15                 // Method setCandidateGenerators:(Ljava/util/List;)V
      45: return

  public synchronized void setMasterServices(org.apache.hadoop.hbase.master.MasterServices);
    Code:
       0: aload_0
       1: aload_1
       2: invokespecial #16                 // Method org/apache/hadoop/hbase/master/balancer/StochasticLoadBalancer.setMasterServices:(Lorg/apache/hadoop/hbase/master/MasterServices;)V
       5: aload_0
       6: aload_1
       7: invokeinterface #17,  1           // InterfaceMethod org/apache/hadoop/hbase/master/MasterServices.getFavoredNodesManager:()Lorg/apache/hadoop/hbase/favored/FavoredNodesManager;
      12: putfield      #3                  // Field fnm:Lorg/apache/hadoop/hbase/favored/FavoredNodesManager;
      15: return

  public java.util.Map<org.apache.hadoop.hbase.ServerName, java.util.List<org.apache.hadoop.hbase.client.RegionInfo>> roundRobinAssignment(java.util.List<org.apache.hadoop.hbase.client.RegionInfo>, java.util.List<org.apache.hadoop.hbase.ServerName>) throws org.apache.hadoop.hbase.HBaseIOException;
    Code:
       0: aload_0
       1: getfield      #18                 // Field metricsBalancer:Lorg/apache/hadoop/hbase/master/balancer/MetricsBalancer;
       4: invokevirtual #19                 // Method org/apache/hadoop/hbase/master/balancer/MetricsBalancer.incrMiscInvocations:()V
       7: aload_1
       8: invokestatic  #20                 // Method org/apache/hbase/thirdparty/com/google/common/collect/Sets.newHashSet:(Ljava/lang/Iterable;)Ljava/util/HashSet;
      11: astore_3
      12: aload_0
      13: aload_1
      14: aload_2
      15: invokevirtual #21                 // Method assignMasterSystemRegions:(Ljava/util/Collection;Ljava/util/List;)Ljava/util/Map;
      18: astore        4
      20: aload         4
      22: ifnull        124
      25: aload         4
      27: invokeinterface #22,  1           // InterfaceMethod java/util/Map.isEmpty:()Z
      32: ifne          124
      35: new           #8                  // class java/util/ArrayList
      38: dup
      39: aload_2
      40: invokespecial #23                 // Method java/util/ArrayList."<init>":(Ljava/util/Collection;)V
      43: astore_2
      44: aload_2
      45: aload_0
      46: getfield      #24                 // Field masterServerName:Lorg/apache/hadoop/hbase/ServerName;
      49: invokeinterface #25,  2           // InterfaceMethod java/util/List.remove:(Ljava/lang/Object;)Z
      54: pop
      55: aload         4
      57: aload_0
      58: getfield      #24                 // Field masterServerName:Lorg/apache/hadoop/hbase/ServerName;
      61: invokeinterface #26,  2           // InterfaceMethod java/util/Map.get:(Ljava/lang/Object;)Ljava/lang/Object;
      66: checkcast     #27                 // class java/util/List
      69: astore        5
      71: aload         5
      73: invokeinterface #28,  1           // InterfaceMethod java/util/List.isEmpty:()Z
      78: ifne          124
      81: aload         5
      83: invokeinterface #29,  1           // InterfaceMethod java/util/List.iterator:()Ljava/util/Iterator;
      88: astore        6
      90: aload         6
      92: invokeinterface #30,  1           // InterfaceMethod java/util/Iterator.hasNext:()Z
      97: ifeq          124
     100: aload         6
     102: invokeinterface #31,  1           // InterfaceMethod java/util/Iterator.next:()Ljava/lang/Object;
     107: checkcast     #32                 // class org/apache/hadoop/hbase/client/RegionInfo
     110: astore        7
     112: aload_3
     113: aload         7
     115: invokeinterface #33,  2           // InterfaceMethod java/util/Set.remove:(Ljava/lang/Object;)Z
     120: pop
     121: goto          90
     124: aload_3
     125: invokeinterface #34,  1           // InterfaceMethod java/util/Set.isEmpty:()Z
     130: ifeq          136
     133: aload         4
     135: areturn
     136: new           #1                  // class org/apache/hadoop/hbase/favored/FavoredNodeAssignmentHelper
     139: dup
     140: aload_2
     141: aload_0
     142: getfield      #3                  // Field fnm:Lorg/apache/hadoop/hbase/favored/FavoredNodesManager;
     145: invokevirtual #35                 // Method org/apache/hadoop/hbase/favored/FavoredNodesManager.getRackManager:()Lorg/apache/hadoop/hbase/master/RackManager;
     148: invokespecial #36                 // Method org/apache/hadoop/hbase/favored/FavoredNodeAssignmentHelper."<init>":(Ljava/util/List;Lorg/apache/hadoop/hbase/master/RackManager;)V
     151: astore        5
     153: aload         5
     155: invokevirtual #37                 // Method org/apache/hadoop/hbase/favored/FavoredNodeAssignmentHelper.initialize:()V
     158: aload_3
     159: invokestatic  #38                 // Method org/apache/hadoop/hbase/favored/FavoredNodesManager.filterNonFNApplicableRegions:(Ljava/util/Collection;)Ljava/util/Set;
     162: astore        6
     164: aload_3
     165: aload         6
     167: invokeinterface #39,  2           // InterfaceMethod java/util/Set.removeAll:(Ljava/util/Collection;)Z
     172: pop
     173: aload_0
     174: aload         6
     176: invokestatic  #40                 // Method org/apache/hbase/thirdparty/com/google/common/collect/Lists.newArrayList:(Ljava/lang/Iterable;)Ljava/util/ArrayList;
     179: aload_2
     180: invokespecial #41                 // Method org/apache/hadoop/hbase/master/balancer/StochasticLoadBalancer.roundRobinAssignment:(Ljava/util/List;Ljava/util/List;)Ljava/util/Map;
     183: astore        7
     185: aload_0
     186: aload_3
     187: aload_2
     188: invokespecial #42                 // Method segregateRegionsAndAssignRegionsWithFavoredNodes:(Ljava/util/Collection;Ljava/util/List;)Lorg/apache/hadoop/hbase/util/Pair;
     191: astore        8
     193: aload         8
     195: invokevirtual #43                 // Method org/apache/hadoop/hbase/util/Pair.getFirst:()Ljava/lang/Object;
     198: checkcast     #44                 // class java/util/Map
     201: astore        9
     203: aload_0
     204: aload         5
     206: aload         8
     208: invokevirtual #45                 // Method org/apache/hadoop/hbase/util/Pair.getSecond:()Ljava/lang/Object;
     211: checkcast     #27                 // class java/util/List
     214: invokespecial #46                 // Method generateFNForRegionsWithoutFN:(Lorg/apache/hadoop/hbase/favored/FavoredNodeAssignmentHelper;Ljava/util/List;)Ljava/util/Map;
     217: astore        10
     219: aload_0
     220: aload         4
     222: aload         7
     224: invokespecial #47                 // Method mergeAssignmentMaps:(Ljava/util/Map;Ljava/util/Map;)V
     227: aload_0
     228: aload         4
     230: aload         9
     232: invokespecial #47                 // Method mergeAssignmentMaps:(Ljava/util/Map;Ljava/util/Map;)V
     235: aload_0
     236: aload         4
     238: aload         10
     240: invokespecial #47                 // Method mergeAssignmentMaps:(Ljava/util/Map;Ljava/util/Map;)V
     243: goto          283
     246: astore        5
     248: new           #49                 // class org/apache/hadoop/hbase/HBaseIOException
     251: dup
     252: new           #50                 // class java/lang/StringBuilder
     255: dup
     256: invokespecial #51                 // Method java/lang/StringBuilder."<init>":()V
     259: ldc           #52                 // String Encountered exception while doing favored-nodes assignment
     261: invokevirtual #53                 // Method java/lang/StringBuilder.append:(Ljava/lang/String;)Ljava/lang/StringBuilder;
     264: aload         5
     266: invokevirtual #54                 // Method java/lang/StringBuilder.append:(Ljava/lang/Object;)Ljava/lang/StringBuilder;
     269: ldc           #55                 // String  Falling back to regular assignment
     271: invokevirtual #53                 // Method java/lang/StringBuilder.append:(Ljava/lang/String;)Ljava/lang/StringBuilder;
     274: invokevirtual #56                 // Method java/lang/StringBuilder.toString:()Ljava/lang/String;
     277: aload         5
     279: invokespecial #57                 // Method org/apache/hadoop/hbase/HBaseIOException."<init>":(Ljava/lang/String;Ljava/lang/Throwable;)V
     282: athrow
     283: aload         4
     285: areturn
    Exception table:
       from    to  target type
         136   243   246   Class java/lang/Exception

  public org.apache.hadoop.hbase.ServerName randomAssignment(org.apache.hadoop.hbase.client.RegionInfo, java.util.List<org.apache.hadoop.hbase.ServerName>) throws org.apache.hadoop.hbase.HBaseIOException;
    Code:
       0: aload_2
       1: ifnull        67
       4: aload_2
       5: aload_0
       6: getfield      #24                 // Field masterServerName:Lorg/apache/hadoop/hbase/ServerName;
       9: invokeinterface #94,  2           // InterfaceMethod java/util/List.contains:(Ljava/lang/Object;)Z
      14: ifeq          67
      17: aload_0
      18: aload_1
      19: invokevirtual #95                 // Method shouldBeOnMaster:(Lorg/apache/hadoop/hbase/client/RegionInfo;)Z
      22: ifeq          37
      25: aload_0
      26: getfield      #18                 // Field metricsBalancer:Lorg/apache/hadoop/hbase/master/balancer/MetricsBalancer;
      29: invokevirtual #19                 // Method org/apache/hadoop/hbase/master/balancer/MetricsBalancer.incrMiscInvocations:()V
      32: aload_0
      33: getfield      #24                 // Field masterServerName:Lorg/apache/hadoop/hbase/ServerName;
      36: areturn
      37: aload_0
      38: invokevirtual #96                 // Method getConf:()Lorg/apache/hadoop/conf/Configuration;
      41: invokestatic  #97                 // InterfaceMethod org/apache/hadoop/hbase/master/LoadBalancer.isTablesOnMaster:(Lorg/apache/hadoop/conf/Configuration;)Z
      44: ifne          67
      47: new           #8                  // class java/util/ArrayList
      50: dup
      51: aload_2
      52: invokespecial #23                 // Method java/util/ArrayList."<init>":(Ljava/util/Collection;)V
      55: astore_2
      56: aload_2
      57: aload_0
      58: getfield      #24                 // Field masterServerName:Lorg/apache/hadoop/hbase/ServerName;
      61: invokeinterface #25,  2           // InterfaceMethod java/util/List.remove:(Ljava/lang/Object;)Z
      66: pop
      67: aconst_null
      68: astore_3
      69: aload_1
      70: invokestatic  #98                 // Method org/apache/hadoop/hbase/favored/FavoredNodesManager.isFavoredNodeApplicable:(Lorg/apache/hadoop/hbase/client/RegionInfo;)Z
      73: ifne          83
      76: aload_0
      77: aload_1
      78: aload_2
      79: invokespecial #99                 // Method org/apache/hadoop/hbase/master/balancer/StochasticLoadBalancer.randomAssignment:(Lorg/apache/hadoop/hbase/client/RegionInfo;Ljava/util/List;)Lorg/apache/hadoop/hbase/ServerName;
      82: areturn
      83: aload_0
      84: getfield      #18                 // Field metricsBalancer:Lorg/apache/hadoop/hbase/master/balancer/MetricsBalancer;
      87: invokevirtual #19                 // Method org/apache/hadoop/hbase/master/balancer/MetricsBalancer.incrMiscInvocations:()V
      90: aload_0
      91: getfield      #3                  // Field fnm:Lorg/apache/hadoop/hbase/favored/FavoredNodesManager;
      94: aload_1
      95: invokevirtual #73                 // Method org/apache/hadoop/hbase/favored/FavoredNodesManager.getFavoredNodes:(Lorg/apache/hadoop/hbase/client/RegionInfo;)Ljava/util/List;
      98: astore        4
     100: aload         4
     102: ifnull        115
     105: aload         4
     107: invokeinterface #28,  1           // InterfaceMethod java/util/List.isEmpty:()Z
     112: ifeq          192
     115: new           #1                  // class org/apache/hadoop/hbase/favored/FavoredNodeAssignmentHelper
     118: dup
     119: aload_2
     120: aload_0
     121: invokevirtual #96                 // Method getConf:()Lorg/apache/hadoop/conf/Configuration;
     124: invokespecial #100                // Method org/apache/hadoop/hbase/favored/FavoredNodeAssignmentHelper."<init>":(Ljava/util/List;Lorg/apache/hadoop/conf/Configuration;)V
     127: astore        5
     129: aload         5
     131: invokevirtual #37                 // Method org/apache/hadoop/hbase/favored/FavoredNodeAssignmentHelper.initialize:()V
     134: aload         5
     136: aload_1
     137: invokevirtual #101                // Method org/apache/hadoop/hbase/favored/FavoredNodeAssignmentHelper.generateFavoredNodes:(Lorg/apache/hadoop/hbase/client/RegionInfo;)Ljava/util/List;
     140: astore        4
     142: aload_0
     143: aload_1
     144: aload         4
     146: invokespecial #102                // Method updateFavoredNodesForRegion:(Lorg/apache/hadoop/hbase/client/RegionInfo;Ljava/util/List;)V
     149: goto          192
     152: astore        6
     154: getstatic     #4                  // Field LOG:Lorg/slf4j/Logger;
     157: new           #50                 // class java/lang/StringBuilder
     160: dup
     161: invokespecial #51                 // Method java/lang/StringBuilder."<init>":()V
     164: ldc           #104                // String Encountered exception while doing favored-nodes (random)assignment
     166: invokevirtual #53                 // Method java/lang/StringBuilder.append:(Ljava/lang/String;)Ljava/lang/StringBuilder;
     169: aload         6
     171: invokevirtual #54                 // Method java/lang/StringBuilder.append:(Ljava/lang/Object;)Ljava/lang/StringBuilder;
     174: invokevirtual #56                 // Method java/lang/StringBuilder.toString:()Ljava/lang/String;
     177: invokeinterface #105,  2          // InterfaceMethod org/slf4j/Logger.warn:(Ljava/lang/String;)V
     182: new           #49                 // class org/apache/hadoop/hbase/HBaseIOException
     185: dup
     186: aload         6
     188: invokespecial #106                // Method org/apache/hadoop/hbase/HBaseIOException."<init>":(Ljava/lang/Throwable;)V
     191: athrow
     192: aload_0
     193: aload_2
     194: aload         4
     196: invokespecial #107                // Method getOnlineFavoredNodes:(Ljava/util/List;Ljava/util/List;)Ljava/util/List;
     199: astore        5
     201: aload         5
     203: invokeinterface #66,  1           // InterfaceMethod java/util/List.size:()I
     208: ifle          235
     211: aload         5
     213: getstatic     #91                 // Field RANDOM:Ljava/util/Random;
     216: aload         5
     218: invokeinterface #66,  1           // InterfaceMethod java/util/List.size:()I
     223: invokevirtual #108                // Method java/util/Random.nextInt:(I)I
     226: invokeinterface #109,  2          // InterfaceMethod java/util/List.get:(I)Ljava/lang/Object;
     231: checkcast     #2                  // class org/apache/hadoop/hbase/ServerName
     234: astore_3
     235: aload_0
     236: invokevirtual #96                 // Method getConf:()Lorg/apache/hadoop/conf/Configuration;
     239: ldc           #111                // String hbase.favored.assignment.always.assign
     241: iconst_1
     242: invokevirtual #112                // Method org/apache/hadoop/conf/Configuration.getBoolean:(Ljava/lang/String;Z)Z
     245: istore        6
     247: aload_3
     248: ifnonnull     295
     251: iload         6
     253: ifeq          295
     256: getstatic     #4                  // Field LOG:Lorg/slf4j/Logger;
     259: new           #50                 // class java/lang/StringBuilder
     262: dup
     263: invokespecial #51                 // Method java/lang/StringBuilder."<init>":()V
     266: ldc           #113                // String Can't generate FN for region:
     268: invokevirtual #53                 // Method java/lang/StringBuilder.append:(Ljava/lang/String;)Ljava/lang/StringBuilder;
     271: aload_1
     272: invokevirtual #54                 // Method java/lang/StringBuilder.append:(Ljava/lang/Object;)Ljava/lang/StringBuilder;
     275: ldc           #114                // String  falling back
     277: invokevirtual #53                 // Method java/lang/StringBuilder.append:(Ljava/lang/String;)Ljava/lang/StringBuilder;
     280: invokevirtual #56                 // Method java/lang/StringBuilder.toString:()Ljava/lang/String;
     283: invokeinterface #105,  2          // InterfaceMethod org/slf4j/Logger.warn:(Ljava/lang/String;)V
     288: aload_0
     289: aload_1
     290: aload_2
     291: invokespecial #99                 // Method org/apache/hadoop/hbase/master/balancer/StochasticLoadBalancer.randomAssignment:(Lorg/apache/hadoop/hbase/client/RegionInfo;Ljava/util/List;)Lorg/apache/hadoop/hbase/ServerName;
     294: astore_3
     295: aload_3
     296: areturn
    Exception table:
       from    to  target type
         134   149   152   Class java/io/IOException

  public java.util.Map<org.apache.hadoop.hbase.ServerName, java.util.List<org.apache.hadoop.hbase.client.RegionInfo>> retainAssignment(java.util.Map<org.apache.hadoop.hbase.client.RegionInfo, org.apache.hadoop.hbase.ServerName>, java.util.List<org.apache.hadoop.hbase.ServerName>) throws org.apache.hadoop.hbase.HBaseIOException;
    Code:
       0: invokestatic  #65                 // Method org/apache/hbase/thirdparty/com/google/common/collect/Maps.newHashMap:()Ljava/util/HashMap;
       3: astore_3
       4: aload_0
       5: aload_1
       6: aload_2
       7: invokespecial #115                // Method org/apache/hadoop/hbase/master/balancer/StochasticLoadBalancer.retainAssignment:(Ljava/util/Map;Ljava/util/List;)Ljava/util/Map;
      10: astore        4
      12: aload         4
      14: ifnull        27
      17: aload         4
      19: invokeinterface #22,  1           // InterfaceMethod java/util/Map.isEmpty:()Z
      24: ifeq          39
      27: getstatic     #4                  // Field LOG:Lorg/slf4j/Logger;
      30: ldc           #116                // String Nothing to assign to, probably no servers or no regions
      32: invokeinterface #105,  2          // InterfaceMethod org/slf4j/Logger.warn:(Ljava/lang/String;)V
      37: aconst_null
      38: areturn
      39: aload_2
      40: ifnull        76
      43: aload_2
      44: aload_0
      45: getfield      #24                 // Field masterServerName:Lorg/apache/hadoop/hbase/ServerName;
      48: invokeinterface #94,  2           // InterfaceMethod java/util/List.contains:(Ljava/lang/Object;)Z
      53: ifeq          76
      56: new           #8                  // class java/util/ArrayList
      59: dup
      60: aload_2
      61: invokespecial #23                 // Method java/util/ArrayList."<init>":(Ljava/util/Collection;)V
      64: astore_2
      65: aload_2
      66: aload_0
      67: getfield      #24                 // Field masterServerName:Lorg/apache/hadoop/hbase/ServerName;
      70: invokeinterface #25,  2           // InterfaceMethod java/util/List.remove:(Ljava/lang/Object;)Z
      75: pop
      76: new           #1                  // class org/apache/hadoop/hbase/favored/FavoredNodeAssignmentHelper
      79: dup
      80: aload_2
      81: aload_0
      82: invokevirtual #96                 // Method getConf:()Lorg/apache/hadoop/conf/Configuration;
      85: invokespecial #100                // Method org/apache/hadoop/hbase/favored/FavoredNodeAssignmentHelper."<init>":(Ljava/util/List;Lorg/apache/hadoop/conf/Configuration;)V
      88: astore        5
      90: aload         5
      92: invokevirtual #37                 // Method org/apache/hadoop/hbase/favored/FavoredNodeAssignmentHelper.initialize:()V
      95: getstatic     #4                  // Field LOG:Lorg/slf4j/Logger;
      98: ldc           #117                // String Generating favored nodes for regions missing them.
     100: invokeinterface #118,  2          // InterfaceMethod org/slf4j/Logger.debug:(Ljava/lang/String;)V
     105: invokestatic  #65                 // Method org/apache/hbase/thirdparty/com/google/common/collect/Maps.newHashMap:()Ljava/util/HashMap;
     108: astore        6
     110: aload         4
     112: invokeinterface #58,  1           // InterfaceMethod java/util/Map.entrySet:()Ljava/util/Set;
     117: invokeinterface #59,  1           // InterfaceMethod java/util/Set.iterator:()Ljava/util/Iterator;
     122: astore        7
     124: aload         7
     126: invokeinterface #30,  1           // InterfaceMethod java/util/Iterator.hasNext:()Z
     131: ifeq          621
     134: aload         7
     136: invokeinterface #31,  1           // InterfaceMethod java/util/Iterator.next:()Ljava/lang/Object;
     141: checkcast     #60                 // class java/util/Map$Entry
     144: astore        8
     146: aload         8
     148: invokeinterface #61,  1           // InterfaceMethod java/util/Map$Entry.getKey:()Ljava/lang/Object;
     153: checkcast     #2                  // class org/apache/hadoop/hbase/ServerName
     156: astore        9
     158: aload         9
     160: invokevirtual #119                // Method org/apache/hadoop/hbase/ServerName.getHostname:()Ljava/lang/String;
     163: aload         9
     165: invokevirtual #120                // Method org/apache/hadoop/hbase/ServerName.getPort:()I
     168: ldc2_w        #121                // long -1l
     171: invokestatic  #123                // Method org/apache/hadoop/hbase/ServerName.valueOf:(Ljava/lang/String;IJ)Lorg/apache/hadoop/hbase/ServerName;
     174: astore        10
     176: aload         8
     178: invokeinterface #62,  1           // InterfaceMethod java/util/Map$Entry.getValue:()Ljava/lang/Object;
     183: checkcast     #27                 // class java/util/List
     186: invokeinterface #29,  1           // InterfaceMethod java/util/List.iterator:()Ljava/util/Iterator;
     191: astore        11
     193: aload         11
     195: invokeinterface #30,  1           // InterfaceMethod java/util/Iterator.hasNext:()Z
     200: ifeq          618
     203: aload         11
     205: invokeinterface #31,  1           // InterfaceMethod java/util/Iterator.next:()Ljava/lang/Object;
     210: checkcast     #32                 // class org/apache/hadoop/hbase/client/RegionInfo
     213: astore        12
     215: aload         12
     217: invokestatic  #98                 // Method org/apache/hadoop/hbase/favored/FavoredNodesManager.isFavoredNodeApplicable:(Lorg/apache/hadoop/hbase/client/RegionInfo;)Z
     220: ifeq          606
     223: aload_0
     224: getfield      #3                  // Field fnm:Lorg/apache/hadoop/hbase/favored/FavoredNodesManager;
     227: aload         12
     229: invokevirtual #73                 // Method org/apache/hadoop/hbase/favored/FavoredNodesManager.getFavoredNodes:(Lorg/apache/hadoop/hbase/client/RegionInfo;)Ljava/util/List;
     232: astore        13
     234: aload         13
     236: ifnull        250
     239: aload         13
     241: invokeinterface #66,  1           // InterfaceMethod java/util/List.size:()I
     246: iconst_3
     247: if_icmpge     457
     250: getstatic     #4                  // Field LOG:Lorg/slf4j/Logger;
     253: new           #50                 // class java/lang/StringBuilder
     256: dup
     257: invokespecial #51                 // Method java/lang/StringBuilder."<init>":()V
     260: ldc           #124                // String Generating favored nodes for:
     262: invokevirtual #53                 // Method java/lang/StringBuilder.append:(Ljava/lang/String;)Ljava/lang/StringBuilder;
     265: aload         12
     267: invokevirtual #54                 // Method java/lang/StringBuilder.append:(Ljava/lang/Object;)Ljava/lang/StringBuilder;
     270: ldc           #125                // String  with primary:
     272: invokevirtual #53                 // Method java/lang/StringBuilder.append:(Ljava/lang/String;)Ljava/lang/StringBuilder;
     275: aload         10
     277: invokevirtual #54                 // Method java/lang/StringBuilder.append:(Ljava/lang/Object;)Ljava/lang/StringBuilder;
     280: invokevirtual #56                 // Method java/lang/StringBuilder.toString:()Ljava/lang/String;
     283: invokeinterface #118,  2          // InterfaceMethod org/slf4j/Logger.debug:(Ljava/lang/String;)V
     288: aload         5
     290: aload         12
     292: aload         10
     294: invokevirtual #126                // Method org/apache/hadoop/hbase/favored/FavoredNodeAssignmentHelper.getSecondaryAndTertiary:(Lorg/apache/hadoop/hbase/client/RegionInfo;Lorg/apache/hadoop/hbase/ServerName;)[Lorg/apache/hadoop/hbase/ServerName;
     297: astore        14
     299: aload         14
     301: ifnull        406
     304: aload         14
     306: arraylength
     307: iconst_2
     308: if_icmpne     406
     311: invokestatic  #83                 // Method org/apache/hbase/thirdparty/com/google/common/collect/Lists.newArrayList:()Ljava/util/ArrayList;
     314: astore        15
     316: aload         15
     318: aload         10
     320: invokeinterface #12,  2           // InterfaceMethod java/util/List.add:(Ljava/lang/Object;)Z
     325: pop
     326: aload         15
     328: aload         14
     330: iconst_0
     331: aaload
     332: invokevirtual #119                // Method org/apache/hadoop/hbase/ServerName.getHostname:()Ljava/lang/String;
     335: aload         14
     337: iconst_0
     338: aaload
     339: invokevirtual #120                // Method org/apache/hadoop/hbase/ServerName.getPort:()I
     342: ldc2_w        #121                // long -1l
     345: invokestatic  #123                // Method org/apache/hadoop/hbase/ServerName.valueOf:(Ljava/lang/String;IJ)Lorg/apache/hadoop/hbase/ServerName;
     348: invokeinterface #12,  2           // InterfaceMethod java/util/List.add:(Ljava/lang/Object;)Z
     353: pop
     354: aload         15
     356: aload         14
     358: iconst_1
     359: aaload
     360: invokevirtual #119                // Method org/apache/hadoop/hbase/ServerName.getHostname:()Ljava/lang/String;
     363: aload         14
     365: iconst_1
     366: aaload
     367: invokevirtual #120                // Method org/apache/hadoop/hbase/ServerName.getPort:()I
     370: ldc2_w        #121                // long -1l
     373: invokestatic  #123                // Method org/apache/hadoop/hbase/ServerName.valueOf:(Ljava/lang/String;IJ)Lorg/apache/hadoop/hbase/ServerName;
     376: invokeinterface #12,  2           // InterfaceMethod java/util/List.add:(Ljava/lang/Object;)Z
     381: pop
     382: aload         6
     384: aload         12
     386: aload         15
     388: invokeinterface #63,  3           // InterfaceMethod java/util/Map.put:(Ljava/lang/Object;Ljava/lang/Object;)Ljava/lang/Object;
     393: pop
     394: aload_0
     395: aload_3
     396: aload         12
     398: aload         9
     400: invokespecial #85                 // Method addRegionToMap:(Ljava/util/Map;Lorg/apache/hadoop/hbase/client/RegionInfo;Lorg/apache/hadoop/hbase/ServerName;)V
     403: goto          454
     406: new           #49                 // class org/apache/hadoop/hbase/HBaseIOException
     409: dup
     410: new           #50                 // class java/lang/StringBuilder
     413: dup
     414: invokespecial #51                 // Method java/lang/StringBuilder."<init>":()V
     417: ldc           #127                // String Cannot generate secondary/tertiary FN for
     419: invokevirtual #53                 // Method java/lang/StringBuilder.append:(Ljava/lang/String;)Ljava/lang/StringBuilder;
     422: aload         12
     424: invokevirtual #54                 // Method java/lang/StringBuilder.append:(Ljava/lang/Object;)Ljava/lang/StringBuilder;
     427: ldc           #128                // String  generated
     429: invokevirtual #53                 // Method java/lang/StringBuilder.append:(Ljava/lang/String;)Ljava/lang/StringBuilder;
     432: aload         14
     434: ifnull        442
     437: aload         14
     439: goto          444
     442: ldc           #129                // String  nothing
     444: invokevirtual #54                 // Method java/lang/StringBuilder.append:(Ljava/lang/Object;)Ljava/lang/StringBuilder;
     447: invokevirtual #56                 // Method java/lang/StringBuilder.toString:()Ljava/lang/String;
     450: invokespecial #130                // Method org/apache/hadoop/hbase/HBaseIOException."<init>":(Ljava/lang/String;)V
     453: athrow
     454: goto          603
     457: aload_0
     458: aload_2
     459: aload         13
     461: invokespecial #107                // Method getOnlineFavoredNodes:(Ljava/util/List;Ljava/util/List;)Ljava/util/List;
     464: astore        14
     466: aload         14
     468: invokeinterface #28,  1           // InterfaceMethod java/util/List.isEmpty:()Z
     473: ifeq          489
     476: aload_0
     477: aload_3
     478: aload         12
     480: getstatic     #93                 // Field BOGUS_SERVER_NAME:Lorg/apache/hadoop/hbase/ServerName;
     483: invokespecial #85                 // Method addRegionToMap:(Ljava/util/Map;Lorg/apache/hadoop/hbase/client/RegionInfo;Lorg/apache/hadoop/hbase/ServerName;)V
     486: goto          603
     489: aload         13
     491: aload         9
     493: invokestatic  #75                 // Method org/apache/hadoop/hbase/favored/FavoredNodesPlan.getFavoredServerPosition:(Ljava/util/List;Lorg/apache/hadoop/hbase/ServerName;)Lorg/apache/hadoop/hbase/favored/FavoredNodesPlan$Position;
     496: ifnull        511
     499: aload_0
     500: aload_3
     501: aload         12
     503: aload         9
     505: invokespecial #85                 // Method addRegionToMap:(Ljava/util/Map;Lorg/apache/hadoop/hbase/client/RegionInfo;Lorg/apache/hadoop/hbase/ServerName;)V
     508: goto          603
     511: aload         14
     513: getstatic     #91                 // Field RANDOM:Ljava/util/Random;
     516: aload         14
     518: invokeinterface #66,  1           // InterfaceMethod java/util/List.size:()I
     523: invokevirtual #108                // Method java/util/Random.nextInt:(I)I
     526: invokeinterface #109,  2          // InterfaceMethod java/util/List.get:(I)Ljava/lang/Object;
     531: checkcast     #2                  // class org/apache/hadoop/hbase/ServerName
     534: astore        15
     536: getstatic     #4                  // Field LOG:Lorg/slf4j/Logger;
     539: new           #50                 // class java/lang/StringBuilder
     542: dup
     543: invokespecial #51                 // Method java/lang/StringBuilder."<init>":()V
     546: ldc           #131                // String Region:
     548: invokevirtual #53                 // Method java/lang/StringBuilder.append:(Ljava/lang/String;)Ljava/lang/StringBuilder;
     551: aload         12
     553: invokevirtual #54                 // Method java/lang/StringBuilder.append:(Ljava/lang/Object;)Ljava/lang/StringBuilder;
     556: ldc           #132                // String  not hosted on favored nodes:
     558: invokevirtual #53                 // Method java/lang/StringBuilder.append:(Ljava/lang/String;)Ljava/lang/StringBuilder;
     561: aload         13
     563: invokevirtual #54                 // Method java/lang/StringBuilder.append:(Ljava/lang/Object;)Ljava/lang/StringBuilder;
     566: ldc           #133                // String  current:
     568: invokevirtual #53                 // Method java/lang/StringBuilder.append:(Ljava/lang/String;)Ljava/lang/StringBuilder;
     571: aload         9
     573: invokevirtual #54                 // Method java/lang/StringBuilder.append:(Ljava/lang/Object;)Ljava/lang/StringBuilder;
     576: ldc           #134                // String  moving to:
     578: invokevirtual #53                 // Method java/lang/StringBuilder.append:(Ljava/lang/String;)Ljava/lang/StringBuilder;
     581: aload         15
     583: invokevirtual #54                 // Method java/lang/StringBuilder.append:(Ljava/lang/Object;)Ljava/lang/StringBuilder;
     586: invokevirtual #56                 // Method java/lang/StringBuilder.toString:()Ljava/lang/String;
     589: invokeinterface #105,  2          // InterfaceMethod org/slf4j/Logger.warn:(Ljava/lang/String;)V
     594: aload_0
     595: aload_3
     596: aload         12
     598: aload         15
     600: invokespecial #85                 // Method addRegionToMap:(Ljava/util/Map;Lorg/apache/hadoop/hbase/client/RegionInfo;Lorg/apache/hadoop/hbase/ServerName;)V
     603: goto          615
     606: aload_0
     607: aload_3
     608: aload         12
     610: aload         9
     612: invokespecial #85                 // Method addRegionToMap:(Ljava/util/Map;Lorg/apache/hadoop/hbase/client/RegionInfo;Lorg/apache/hadoop/hbase/ServerName;)V
     615: goto          193
     618: goto          124
     621: aload         6
     623: invokeinterface #22,  1           // InterfaceMethod java/util/Map.isEmpty:()Z
     628: ifne          673
     631: getstatic     #4                  // Field LOG:Lorg/slf4j/Logger;
     634: new           #50                 // class java/lang/StringBuilder
     637: dup
     638: invokespecial #51                 // Method java/lang/StringBuilder."<init>":()V
     641: ldc           #135                // String Updating FN in meta for missing regions, count:
     643: invokevirtual #53                 // Method java/lang/StringBuilder.append:(Ljava/lang/String;)Ljava/lang/StringBuilder;
     646: aload         6
     648: invokeinterface #90,  1           // InterfaceMethod java/util/Map.size:()I
     653: invokevirtual #136                // Method java/lang/StringBuilder.append:(I)Ljava/lang/StringBuilder;
     656: invokevirtual #56                 // Method java/lang/StringBuilder.toString:()Ljava/lang/String;
     659: invokeinterface #118,  2          // InterfaceMethod org/slf4j/Logger.debug:(Ljava/lang/String;)V
     664: aload_0
     665: getfield      #3                  // Field fnm:Lorg/apache/hadoop/hbase/favored/FavoredNodesManager;
     668: aload         6
     670: invokevirtual #68                 // Method org/apache/hadoop/hbase/favored/FavoredNodesManager.updateFavoredNodes:(Ljava/util/Map;)V
     673: goto          711
     676: astore        7
     678: new           #49                 // class org/apache/hadoop/hbase/HBaseIOException
     681: dup
     682: new           #50                 // class java/lang/StringBuilder
     685: dup
     686: invokespecial #51                 // Method java/lang/StringBuilder."<init>":()V
     689: ldc           #137                // String Cannot generate/update FN for regions:
     691: invokevirtual #53                 // Method java/lang/StringBuilder.append:(Ljava/lang/String;)Ljava/lang/StringBuilder;
     694: aload         6
     696: invokeinterface #138,  1          // InterfaceMethod java/util/Map.keySet:()Ljava/util/Set;
     701: invokevirtual #54                 // Method java/lang/StringBuilder.append:(Ljava/lang/Object;)Ljava/lang/StringBuilder;
     704: invokevirtual #56                 // Method java/lang/StringBuilder.toString:()Ljava/lang/String;
     707: invokespecial #130                // Method org/apache/hadoop/hbase/HBaseIOException."<init>":(Ljava/lang/String;)V
     710: athrow
     711: aload_3
     712: areturn
    Exception table:
       from    to  target type
         110   673   676   Class java/io/IOException

  public synchronized java.util.List<org.apache.hadoop.hbase.ServerName> getFavoredNodes(org.apache.hadoop.hbase.client.RegionInfo);
    Code:
       0: aload_0
       1: getfield      #3                  // Field fnm:Lorg/apache/hadoop/hbase/favored/FavoredNodesManager;
       4: aload_1
       5: invokevirtual #73                 // Method org/apache/hadoop/hbase/favored/FavoredNodesManager.getFavoredNodes:(Lorg/apache/hadoop/hbase/client/RegionInfo;)Ljava/util/List;
       8: areturn

  public void generateFavoredNodesForDaughter(java.util.List<org.apache.hadoop.hbase.ServerName>, org.apache.hadoop.hbase.client.RegionInfo, org.apache.hadoop.hbase.client.RegionInfo, org.apache.hadoop.hbase.client.RegionInfo) throws java.io.IOException;
    Code:
       0: new           #69                 // class java/util/HashMap
       3: dup
       4: invokespecial #139                // Method java/util/HashMap."<init>":()V
       7: astore        5
       9: new           #1                  // class org/apache/hadoop/hbase/favored/FavoredNodeAssignmentHelper
      12: dup
      13: aload_1
      14: aload_0
      15: getfield      #140                // Field rackManager:Lorg/apache/hadoop/hbase/master/RackManager;
      18: invokespecial #36                 // Method org/apache/hadoop/hbase/favored/FavoredNodeAssignmentHelper."<init>":(Ljava/util/List;Lorg/apache/hadoop/hbase/master/RackManager;)V
      21: astore        6
      23: aload         6
      25: invokevirtual #37                 // Method org/apache/hadoop/hbase/favored/FavoredNodeAssignmentHelper.initialize:()V
      28: aload_0
      29: getfield      #3                  // Field fnm:Lorg/apache/hadoop/hbase/favored/FavoredNodesManager;
      32: aload_2
      33: invokevirtual #73                 // Method org/apache/hadoop/hbase/favored/FavoredNodesManager.getFavoredNodes:(Lorg/apache/hadoop/hbase/client/RegionInfo;)Ljava/util/List;
      36: astore        7
      38: aload         7
      40: ifnonnull     110
      43: getstatic     #4                  // Field LOG:Lorg/slf4j/Logger;
      46: new           #50                 // class java/lang/StringBuilder
      49: dup
      50: invokespecial #51                 // Method java/lang/StringBuilder."<init>":()V
      53: ldc           #141                // String Unable to find favored nodes for parent,
      55: invokevirtual #53                 // Method java/lang/StringBuilder.append:(Ljava/lang/String;)Ljava/lang/StringBuilder;
      58: aload_2
      59: invokevirtual #54                 // Method java/lang/StringBuilder.append:(Ljava/lang/Object;)Ljava/lang/StringBuilder;
      62: ldc           #142                // String  generating new favored nodes for daughter
      64: invokevirtual #53                 // Method java/lang/StringBuilder.append:(Ljava/lang/String;)Ljava/lang/StringBuilder;
      67: invokevirtual #56                 // Method java/lang/StringBuilder.toString:()Ljava/lang/String;
      70: invokeinterface #118,  2          // InterfaceMethod org/slf4j/Logger.debug:(Ljava/lang/String;)V
      75: aload         5
      77: aload_3
      78: aload         6
      80: aload_3
      81: invokevirtual #101                // Method org/apache/hadoop/hbase/favored/FavoredNodeAssignmentHelper.generateFavoredNodes:(Lorg/apache/hadoop/hbase/client/RegionInfo;)Ljava/util/List;
      84: invokeinterface #63,  3           // InterfaceMethod java/util/Map.put:(Ljava/lang/Object;Ljava/lang/Object;)Ljava/lang/Object;
      89: pop
      90: aload         5
      92: aload         4
      94: aload         6
      96: aload         4
      98: invokevirtual #101                // Method org/apache/hadoop/hbase/favored/FavoredNodeAssignmentHelper.generateFavoredNodes:(Lorg/apache/hadoop/hbase/client/RegionInfo;)Ljava/util/List;
     101: invokeinterface #63,  3           // InterfaceMethod java/util/Map.put:(Ljava/lang/Object;Ljava/lang/Object;)Ljava/lang/Object;
     106: pop
     107: goto          171
     110: aload_0
     111: aload         6
     113: aload         7
     115: getstatic     #76                 // Field org/apache/hadoop/hbase/favored/FavoredNodesPlan$Position.PRIMARY:Lorg/apache/hadoop/hbase/favored/FavoredNodesPlan$Position;
     118: getstatic     #78                 // Field org/apache/hadoop/hbase/favored/FavoredNodesPlan$Position.SECONDARY:Lorg/apache/hadoop/hbase/favored/FavoredNodesPlan$Position;
     121: invokespecial #143                // Method getInheritedFNForDaughter:(Lorg/apache/hadoop/hbase/favored/FavoredNodeAssignmentHelper;Ljava/util/List;Lorg/apache/hadoop/hbase/favored/FavoredNodesPlan$Position;Lorg/apache/hadoop/hbase/favored/FavoredNodesPlan$Position;)Ljava/util/Set;
     124: astore        8
     126: aload         5
     128: aload_3
     129: aload         8
     131: invokestatic  #40                 // Method org/apache/hbase/thirdparty/com/google/common/collect/Lists.newArrayList:(Ljava/lang/Iterable;)Ljava/util/ArrayList;
     134: invokeinterface #63,  3           // InterfaceMethod java/util/Map.put:(Ljava/lang/Object;Ljava/lang/Object;)Ljava/lang/Object;
     139: pop
     140: aload_0
     141: aload         6
     143: aload         7
     145: getstatic     #76                 // Field org/apache/hadoop/hbase/favored/FavoredNodesPlan$Position.PRIMARY:Lorg/apache/hadoop/hbase/favored/FavoredNodesPlan$Position;
     148: getstatic     #79                 // Field org/apache/hadoop/hbase/favored/FavoredNodesPlan$Position.TERTIARY:Lorg/apache/hadoop/hbase/favored/FavoredNodesPlan$Position;
     151: invokespecial #143                // Method getInheritedFNForDaughter:(Lorg/apache/hadoop/hbase/favored/FavoredNodeAssignmentHelper;Ljava/util/List;Lorg/apache/hadoop/hbase/favored/FavoredNodesPlan$Position;Lorg/apache/hadoop/hbase/favored/FavoredNodesPlan$Position;)Ljava/util/Set;
     154: astore        9
     156: aload         5
     158: aload         4
     160: aload         9
     162: invokestatic  #40                 // Method org/apache/hbase/thirdparty/com/google/common/collect/Lists.newArrayList:(Ljava/lang/Iterable;)Ljava/util/ArrayList;
     165: invokeinterface #63,  3           // InterfaceMethod java/util/Map.put:(Ljava/lang/Object;Ljava/lang/Object;)Ljava/lang/Object;
     170: pop
     171: aload_0
     172: getfield      #3                  // Field fnm:Lorg/apache/hadoop/hbase/favored/FavoredNodesManager;
     175: aload         5
     177: invokevirtual #68                 // Method org/apache/hadoop/hbase/favored/FavoredNodesManager.updateFavoredNodes:(Ljava/util/Map;)V
     180: return

  public void generateFavoredNodesForMergedRegion(org.apache.hadoop.hbase.client.RegionInfo, org.apache.hadoop.hbase.client.RegionInfo, org.apache.hadoop.hbase.client.RegionInfo) throws java.io.IOException;
    Code:
       0: aload_0
       1: aload_1
       2: aload_0
       3: getfield      #3                  // Field fnm:Lorg/apache/hadoop/hbase/favored/FavoredNodesManager;
       6: aload_2
       7: invokevirtual #73                 // Method org/apache/hadoop/hbase/favored/FavoredNodesManager.getFavoredNodes:(Lorg/apache/hadoop/hbase/client/RegionInfo;)Ljava/util/List;
      10: invokespecial #102                // Method updateFavoredNodesForRegion:(Lorg/apache/hadoop/hbase/client/RegionInfo;Ljava/util/List;)V
      13: return

  public synchronized java.util.List<org.apache.hadoop.hbase.master.RegionPlan> balanceCluster(java.util.Map<org.apache.hadoop.hbase.ServerName, java.util.List<org.apache.hadoop.hbase.client.RegionInfo>>);
    Code:
       0: aload_0
       1: getfield      #149                // Field services:Lorg/apache/hadoop/hbase/master/MasterServices;
       4: ifnull        336
       7: invokestatic  #83                 // Method org/apache/hbase/thirdparty/com/google/common/collect/Lists.newArrayList:()Ljava/util/ArrayList;
      10: astore_2
      11: new           #69                 // class java/util/HashMap
      14: dup
      15: invokespecial #139                // Method java/util/HashMap."<init>":()V
      18: astore_3
      19: iconst_0
      20: istore        4
      22: aload_1
      23: invokeinterface #58,  1           // InterfaceMethod java/util/Map.entrySet:()Ljava/util/Set;
      28: invokeinterface #59,  1           // InterfaceMethod java/util/Set.iterator:()Ljava/util/Iterator;
      33: astore        5
      35: aload         5
      37: invokeinterface #30,  1           // InterfaceMethod java/util/Iterator.hasNext:()Z
      42: ifeq          280
      45: aload         5
      47: invokeinterface #31,  1           // InterfaceMethod java/util/Iterator.next:()Ljava/lang/Object;
      52: checkcast     #60                 // class java/util/Map$Entry
      55: astore        6
      57: aload         6
      59: invokeinterface #61,  1           // InterfaceMethod java/util/Map$Entry.getKey:()Ljava/lang/Object;
      64: checkcast     #2                  // class org/apache/hadoop/hbase/ServerName
      67: astore        7
      69: invokestatic  #83                 // Method org/apache/hbase/thirdparty/com/google/common/collect/Lists.newArrayList:()Ljava/util/ArrayList;
      72: astore        8
      74: aload_3
      75: aload         7
      77: aload         8
      79: invokeinterface #63,  3           // InterfaceMethod java/util/Map.put:(Ljava/lang/Object;Ljava/lang/Object;)Ljava/lang/Object;
      84: pop
      85: aload         6
      87: invokeinterface #62,  1           // InterfaceMethod java/util/Map$Entry.getValue:()Ljava/lang/Object;
      92: checkcast     #27                 // class java/util/List
      95: invokeinterface #29,  1           // InterfaceMethod java/util/List.iterator:()Ljava/util/Iterator;
     100: astore        9
     102: aload         9
     104: invokeinterface #30,  1           // InterfaceMethod java/util/Iterator.hasNext:()Z
     109: ifeq          277
     112: aload         9
     114: invokeinterface #31,  1           // InterfaceMethod java/util/Iterator.next:()Ljava/lang/Object;
     119: checkcast     #32                 // class org/apache/hadoop/hbase/client/RegionInfo
     122: astore        10
     124: aload_0
     125: getfield      #3                  // Field fnm:Lorg/apache/hadoop/hbase/favored/FavoredNodesManager;
     128: aload         10
     130: invokevirtual #73                 // Method org/apache/hadoop/hbase/favored/FavoredNodesManager.getFavoredNodes:(Lorg/apache/hadoop/hbase/client/RegionInfo;)Ljava/util/List;
     133: astore        11
     135: aload         11
     137: aload         7
     139: invokestatic  #75                 // Method org/apache/hadoop/hbase/favored/FavoredNodesPlan.getFavoredServerPosition:(Ljava/util/List;Lorg/apache/hadoop/hbase/ServerName;)Lorg/apache/hadoop/hbase/favored/FavoredNodesPlan$Position;
     142: ifnonnull     153
     145: aload         10
     147: invokestatic  #98                 // Method org/apache/hadoop/hbase/favored/FavoredNodesManager.isFavoredNodeApplicable:(Lorg/apache/hadoop/hbase/client/RegionInfo;)Z
     150: ifne          166
     153: aload         8
     155: aload         10
     157: invokeinterface #12,  2           // InterfaceMethod java/util/List.add:(Ljava/lang/Object;)Z
     162: pop
     163: goto          274
     166: getstatic     #4                  // Field LOG:Lorg/slf4j/Logger;
     169: new           #50                 // class java/lang/StringBuilder
     172: dup
     173: invokespecial #51                 // Method java/lang/StringBuilder."<init>":()V
     176: ldc           #150                // String Region not on favored nodes, unassign. Region:
     178: invokevirtual #53                 // Method java/lang/StringBuilder.append:(Ljava/lang/String;)Ljava/lang/StringBuilder;
     181: aload         10
     183: invokevirtual #54                 // Method java/lang/StringBuilder.append:(Ljava/lang/Object;)Ljava/lang/StringBuilder;
     186: ldc           #133                // String  current:
     188: invokevirtual #53                 // Method java/lang/StringBuilder.append:(Ljava/lang/String;)Ljava/lang/StringBuilder;
     191: aload         7
     193: invokevirtual #54                 // Method java/lang/StringBuilder.append:(Ljava/lang/Object;)Ljava/lang/StringBuilder;
     196: ldc           #151                // String  favored nodes:
     198: invokevirtual #53                 // Method java/lang/StringBuilder.append:(Ljava/lang/String;)Ljava/lang/StringBuilder;
     201: aload         11
     203: invokevirtual #54                 // Method java/lang/StringBuilder.append:(Ljava/lang/Object;)Ljava/lang/StringBuilder;
     206: invokevirtual #56                 // Method java/lang/StringBuilder.toString:()Ljava/lang/String;
     209: invokeinterface #105,  2          // InterfaceMethod org/slf4j/Logger.warn:(Ljava/lang/String;)V
     214: aload_0
     215: getfield      #149                // Field services:Lorg/apache/hadoop/hbase/master/MasterServices;
     218: invokeinterface #152,  1          // InterfaceMethod org/apache/hadoop/hbase/master/MasterServices.getAssignmentManager:()Lorg/apache/hadoop/hbase/master/assignment/AssignmentManager;
     223: aload         10
     225: invokevirtual #153                // Method org/apache/hadoop/hbase/master/assignment/AssignmentManager.unassign:(Lorg/apache/hadoop/hbase/client/RegionInfo;)J
     228: pop2
     229: goto          249
     232: astore        12
     234: getstatic     #4                  // Field LOG:Lorg/slf4j/Logger;
     237: ldc           #154                // String Failed unassign
     239: aload         12
     241: invokeinterface #155,  3          // InterfaceMethod org/slf4j/Logger.warn:(Ljava/lang/String;Ljava/lang/Throwable;)V
     246: goto          102
     249: new           #156                // class org/apache/hadoop/hbase/master/RegionPlan
     252: dup
     253: aload         10
     255: aconst_null
     256: aconst_null
     257: invokespecial #157                // Method org/apache/hadoop/hbase/master/RegionPlan."<init>":(Lorg/apache/hadoop/hbase/client/RegionInfo;Lorg/apache/hadoop/hbase/ServerName;Lorg/apache/hadoop/hbase/ServerName;)V
     260: astore        12
     262: aload_2
     263: aload         12
     265: invokeinterface #12,  2           // InterfaceMethod java/util/List.add:(Ljava/lang/Object;)Z
     270: pop
     271: iinc          4, 1
     274: goto          102
     277: goto          35
     280: getstatic     #4                  // Field LOG:Lorg/slf4j/Logger;
     283: new           #50                 // class java/lang/StringBuilder
     286: dup
     287: invokespecial #51                 // Method java/lang/StringBuilder."<init>":()V
     290: ldc           #158                // String Found misplaced regions:
     292: invokevirtual #53                 // Method java/lang/StringBuilder.append:(Ljava/lang/String;)Ljava/lang/StringBuilder;
     295: iload         4
     297: invokevirtual #136                // Method java/lang/StringBuilder.append:(I)Ljava/lang/StringBuilder;
     300: ldc           #159                // String , not on favored nodes.
     302: invokevirtual #53                 // Method java/lang/StringBuilder.append:(Ljava/lang/String;)Ljava/lang/StringBuilder;
     305: invokevirtual #56                 // Method java/lang/StringBuilder.toString:()Ljava/lang/String;
     308: invokeinterface #118,  2          // InterfaceMethod org/slf4j/Logger.debug:(Ljava/lang/String;)V
     313: aload_0
     314: aload_3
     315: invokespecial #160                // Method org/apache/hadoop/hbase/master/balancer/StochasticLoadBalancer.balanceCluster:(Ljava/util/Map;)Ljava/util/List;
     318: astore        5
     320: aload         5
     322: ifnull        334
     325: aload_2
     326: aload         5
     328: invokeinterface #64,  2           // InterfaceMethod java/util/List.addAll:(Ljava/util/Collection;)Z
     333: pop
     334: aload_2
     335: areturn
     336: aload_0
     337: aload_1
     338: invokespecial #160                // Method org/apache/hadoop/hbase/master/balancer/StochasticLoadBalancer.balanceCluster:(Ljava/util/Map;)Ljava/util/List;
     341: areturn
    Exception table:
       from    to  target type
         214   229   232   Class java/io/IOException

  static org.slf4j.Logger access$100();
    Code:
       0: getstatic     #4                  // Field LOG:Lorg/slf4j/Logger;
       3: areturn

  static org.apache.hadoop.hbase.favored.FavoredNodesManager access$200(org.apache.hadoop.hbase.master.balancer.FavoredStochasticBalancer);
    Code:
       0: aload_0
       1: getfield      #3                  // Field fnm:Lorg/apache/hadoop/hbase/favored/FavoredNodesManager;
       4: areturn

  static {};
    Code:
       0: ldc           #161                // class org/apache/hadoop/hbase/master/balancer/FavoredStochasticBalancer
       2: invokestatic  #162                // Method org/slf4j/LoggerFactory.getLogger:(Ljava/lang/Class;)Lorg/slf4j/Logger;
       5: putstatic     #4                  // Field LOG:Lorg/slf4j/Logger;
       8: return
}
