Compiled from "FavoredStochasticBalancer.java"
class org.apache.hadoop.hbase.master.balancer.FavoredStochasticBalancer$FavoredNodeLocalityPicker extends org.apache.hadoop.hbase.master.balancer.StochasticLoadBalancer$CandidateGenerator {
  final org.apache.hadoop.hbase.master.balancer.FavoredStochasticBalancer this$0;

  protected org.apache.hadoop.hbase.master.balancer.BaseLoadBalancer$Cluster$Action generate(org.apache.hadoop.hbase.master.balancer.BaseLoadBalancer$Cluster);
    Code:
       0: aload_0
       1: aload_1
       2: invokevirtual #4                  // Method pickRandomServer:(Lorg/apache/hadoop/hbase/master/balancer/BaseLoadBalancer$Cluster;)I
       5: istore_2
       6: iload_2
       7: iconst_m1
       8: if_icmpne     25
      11: invokestatic  #5                  // Method org/apache/hadoop/hbase/master/balancer/FavoredStochasticBalancer.access$100:()Lorg/slf4j/Logger;
      14: ldc           #6                  // String Could not pick lowest local region server
      16: invokeinterface #7,  2            // InterfaceMethod org/slf4j/Logger.trace:(Ljava/lang/String;)V
      21: getstatic     #8                  // Field org/apache/hadoop/hbase/master/balancer/BaseLoadBalancer$Cluster.NullAction:Lorg/apache/hadoop/hbase/master/balancer/BaseLoadBalancer$Cluster$Action;
      24: areturn
      25: aload_0
      26: aload_1
      27: iload_2
      28: invokespecial #9                  // Method pickLowestLocalRegionOnServer:(Lorg/apache/hadoop/hbase/master/balancer/BaseLoadBalancer$Cluster;I)I
      31: istore_3
      32: iload_3
      33: iconst_m1
      34: if_icmpne     89
      37: aload_1
      38: getfield      #10                 // Field org/apache/hadoop/hbase/master/balancer/BaseLoadBalancer$Cluster.regionsPerServer:[[I
      41: iload_2
      42: aaload
      43: arraylength
      44: ifle          85
      47: invokestatic  #5                  // Method org/apache/hadoop/hbase/master/balancer/FavoredStochasticBalancer.access$100:()Lorg/slf4j/Logger;
      50: new           #11                 // class java/lang/StringBuilder
      53: dup
      54: invokespecial #12                 // Method java/lang/StringBuilder."<init>":()V
      57: ldc           #13                 // String Could not pick lowest local region even when region server held
      59: invokevirtual #14                 // Method java/lang/StringBuilder.append:(Ljava/lang/String;)Ljava/lang/StringBuilder;
      62: aload_1
      63: getfield      #10                 // Field org/apache/hadoop/hbase/master/balancer/BaseLoadBalancer$Cluster.regionsPerServer:[[I
      66: iload_2
      67: aaload
      68: arraylength
      69: invokevirtual #15                 // Method java/lang/StringBuilder.append:(I)Ljava/lang/StringBuilder;
      72: ldc           #16                 // String  regions
      74: invokevirtual #14                 // Method java/lang/StringBuilder.append:(Ljava/lang/String;)Ljava/lang/StringBuilder;
      77: invokevirtual #17                 // Method java/lang/StringBuilder.toString:()Ljava/lang/String;
      80: invokeinterface #7,  2            // InterfaceMethod org/slf4j/Logger.trace:(Ljava/lang/String;)V
      85: getstatic     #8                  // Field org/apache/hadoop/hbase/master/balancer/BaseLoadBalancer$Cluster.NullAction:Lorg/apache/hadoop/hbase/master/balancer/BaseLoadBalancer$Cluster$Action;
      88: areturn
      89: aload_1
      90: getfield      #18                 // Field org/apache/hadoop/hbase/master/balancer/BaseLoadBalancer$Cluster.regions:[Lorg/apache/hadoop/hbase/client/RegionInfo;
      93: iload_3
      94: aaload
      95: astore        4
      97: aload_0
      98: getfield      #2                  // Field this$0:Lorg/apache/hadoop/hbase/master/balancer/FavoredStochasticBalancer;
     101: invokestatic  #19                 // Method org/apache/hadoop/hbase/master/balancer/FavoredStochasticBalancer.access$200:(Lorg/apache/hadoop/hbase/master/balancer/FavoredStochasticBalancer;)Lorg/apache/hadoop/hbase/favored/FavoredNodesManager;
     104: aload         4
     106: invokevirtual #20                 // Method org/apache/hadoop/hbase/favored/FavoredNodesManager.getFavoredNodes:(Lorg/apache/hadoop/hbase/client/RegionInfo;)Ljava/util/List;
     109: astore        5
     111: aload         5
     113: ifnonnull     167
     116: aload         4
     118: invokestatic  #21                 // Method org/apache/hadoop/hbase/favored/FavoredNodesManager.isFavoredNodeApplicable:(Lorg/apache/hadoop/hbase/client/RegionInfo;)Z
     121: ifne          135
     124: aload_0
     125: aload_1
     126: iload_2
     127: invokevirtual #22                 // Method pickOtherRandomServer:(Lorg/apache/hadoop/hbase/master/balancer/BaseLoadBalancer$Cluster;I)I
     130: istore        6
     132: goto          177
     135: invokestatic  #5                  // Method org/apache/hadoop/hbase/master/balancer/FavoredStochasticBalancer.access$100:()Lorg/slf4j/Logger;
     138: new           #11                 // class java/lang/StringBuilder
     141: dup
     142: invokespecial #12                 // Method java/lang/StringBuilder."<init>":()V
     145: ldc           #23                 // String Ignoring, no favored nodes for region:
     147: invokevirtual #14                 // Method java/lang/StringBuilder.append:(Ljava/lang/String;)Ljava/lang/StringBuilder;
     150: aload         4
     152: invokevirtual #24                 // Method java/lang/StringBuilder.append:(Ljava/lang/Object;)Ljava/lang/StringBuilder;
     155: invokevirtual #17                 // Method java/lang/StringBuilder.toString:()Ljava/lang/String;
     158: invokeinterface #7,  2            // InterfaceMethod org/slf4j/Logger.trace:(Ljava/lang/String;)V
     163: getstatic     #8                  // Field org/apache/hadoop/hbase/master/balancer/BaseLoadBalancer$Cluster.NullAction:Lorg/apache/hadoop/hbase/master/balancer/BaseLoadBalancer$Cluster$Action;
     166: areturn
     167: aload_0
     168: aload_1
     169: aload         5
     171: iload_2
     172: invokespecial #25                 // Method getDifferentFavoredNode:(Lorg/apache/hadoop/hbase/master/balancer/BaseLoadBalancer$Cluster;Ljava/util/List;I)I
     175: istore        6
     177: aload_0
     178: iload_2
     179: iload_3
     180: iload         6
     182: iconst_m1
     183: invokevirtual #26                 // Method getAction:(IIII)Lorg/apache/hadoop/hbase/master/balancer/BaseLoadBalancer$Cluster$Action;
     186: areturn

  org.apache.hadoop.hbase.master.balancer.FavoredStochasticBalancer$FavoredNodeLocalityPicker(org.apache.hadoop.hbase.master.balancer.FavoredStochasticBalancer, org.apache.hadoop.hbase.master.balancer.FavoredStochasticBalancer$1);
    Code:
       0: aload_0
       1: aload_1
       2: invokespecial #1                  // Method "<init>":(Lorg/apache/hadoop/hbase/master/balancer/FavoredStochasticBalancer;)V
       5: return
}
