Compiled from "FileMmapIOEngine.java"
class org.apache.hadoop.hbase.io.hfile.bucket.FileMmapIOEngine$1 implements org.apache.hadoop.hbase.util.ByteBufferAllocator {
  java.util.concurrent.atomic.AtomicInteger pos;

  final org.apache.hadoop.hbase.io.hfile.bucket.FileMmapIOEngine this$0;

  org.apache.hadoop.hbase.io.hfile.bucket.FileMmapIOEngine$1(org.apache.hadoop.hbase.io.hfile.bucket.FileMmapIOEngine);
    Code:
       0: aload_0
       1: aload_1
       2: putfield      #1                  // Field this$0:Lorg/apache/hadoop/hbase/io/hfile/bucket/FileMmapIOEngine;
       5: aload_0
       6: invokespecial #2                  // Method java/lang/Object."<init>":()V
       9: aload_0
      10: new           #3                  // class java/util/concurrent/atomic/AtomicInteger
      13: dup
      14: iconst_0
      15: invokespecial #4                  // Method java/util/concurrent/atomic/AtomicInteger."<init>":(I)V
      18: putfield      #5                  // Field pos:Ljava/util/concurrent/atomic/AtomicInteger;
      21: return

  public java.nio.ByteBuffer allocate(long) throws java.io.IOException;
    Code:
       0: aload_0
       1: getfield      #1                  // Field this$0:Lorg/apache/hadoop/hbase/io/hfile/bucket/FileMmapIOEngine;
       4: invokestatic  #6                  // Method org/apache/hadoop/hbase/io/hfile/bucket/FileMmapIOEngine.access$000:(Lorg/apache/hadoop/hbase/io/hfile/bucket/FileMmapIOEngine;)Ljava/nio/channels/FileChannel;
       7: getstatic     #7                  // Field java/nio/channels/FileChannel$MapMode.READ_WRITE:Ljava/nio/channels/FileChannel$MapMode;
      10: aload_0
      11: getfield      #5                  // Field pos:Ljava/util/concurrent/atomic/AtomicInteger;
      14: invokevirtual #8                  // Method java/util/concurrent/atomic/AtomicInteger.getAndIncrement:()I
      17: i2l
      18: lload_1
      19: lmul
      20: lload_1
      21: invokevirtual #9                  // Method java/nio/channels/FileChannel.map:(Ljava/nio/channels/FileChannel$MapMode;JJ)Ljava/nio/MappedByteBuffer;
      24: astore_3
      25: aload_3
      26: areturn
}
