Compiled from "FilterWrapper.java"
public final class org.apache.hadoop.hbase.filter.FilterWrapper$FilterRowRetCode extends java.lang.Enum<org.apache.hadoop.hbase.filter.FilterWrapper$FilterRowRetCode> {
  public static final org.apache.hadoop.hbase.filter.FilterWrapper$FilterRowRetCode NOT_CALLED;

  public static final org.apache.hadoop.hbase.filter.FilterWrapper$FilterRowRetCode INCLUDE;

  public static final org.apache.hadoop.hbase.filter.FilterWrapper$FilterRowRetCode EXCLUDE;

  public static final org.apache.hadoop.hbase.filter.FilterWrapper$FilterRowRetCode INCLUDE_THIS_FAMILY;

  public static org.apache.hadoop.hbase.filter.FilterWrapper$FilterRowRetCode[] values();
    Code:
       0: getstatic     #1                  // Field $VALUES:[Lorg/apache/hadoop/hbase/filter/FilterWrapper$FilterRowRetCode;
       3: invokevirtual #2                  // Method "[Lorg/apache/hadoop/hbase/filter/FilterWrapper$FilterRowRetCode;".clone:()Ljava/lang/Object;
       6: checkcast     #3                  // class "[Lorg/apache/hadoop/hbase/filter/FilterWrapper$FilterRowRetCode;"
       9: areturn

  public static org.apache.hadoop.hbase.filter.FilterWrapper$FilterRowRetCode valueOf(java.lang.String);
    Code:
       0: ldc           #4                  // class org/apache/hadoop/hbase/filter/FilterWrapper$FilterRowRetCode
       2: aload_0
       3: invokestatic  #5                  // Method java/lang/Enum.valueOf:(Ljava/lang/Class;Ljava/lang/String;)Ljava/lang/Enum;
       6: checkcast     #4                  // class org/apache/hadoop/hbase/filter/FilterWrapper$FilterRowRetCode
       9: areturn

  static {};
    Code:
       0: new           #4                  // class org/apache/hadoop/hbase/filter/FilterWrapper$FilterRowRetCode
       3: dup
       4: ldc           #7                  // String NOT_CALLED
       6: iconst_0
       7: invokespecial #8                  // Method "<init>":(Ljava/lang/String;I)V
      10: putstatic     #9                  // Field NOT_CALLED:Lorg/apache/hadoop/hbase/filter/FilterWrapper$FilterRowRetCode;
      13: new           #4                  // class org/apache/hadoop/hbase/filter/FilterWrapper$FilterRowRetCode
      16: dup
      17: ldc           #10                 // String INCLUDE
      19: iconst_1
      20: invokespecial #8                  // Method "<init>":(Ljava/lang/String;I)V
      23: putstatic     #11                 // Field INCLUDE:Lorg/apache/hadoop/hbase/filter/FilterWrapper$FilterRowRetCode;
      26: new           #4                  // class org/apache/hadoop/hbase/filter/FilterWrapper$FilterRowRetCode
      29: dup
      30: ldc           #12                 // String EXCLUDE
      32: iconst_2
      33: invokespecial #8                  // Method "<init>":(Ljava/lang/String;I)V
      36: putstatic     #13                 // Field EXCLUDE:Lorg/apache/hadoop/hbase/filter/FilterWrapper$FilterRowRetCode;
      39: new           #4                  // class org/apache/hadoop/hbase/filter/FilterWrapper$FilterRowRetCode
      42: dup
      43: ldc           #14                 // String INCLUDE_THIS_FAMILY
      45: iconst_3
      46: invokespecial #8                  // Method "<init>":(Ljava/lang/String;I)V
      49: putstatic     #15                 // Field INCLUDE_THIS_FAMILY:Lorg/apache/hadoop/hbase/filter/FilterWrapper$FilterRowRetCode;
      52: iconst_4
      53: anewarray     #4                  // class org/apache/hadoop/hbase/filter/FilterWrapper$FilterRowRetCode
      56: dup
      57: iconst_0
      58: getstatic     #9                  // Field NOT_CALLED:Lorg/apache/hadoop/hbase/filter/FilterWrapper$FilterRowRetCode;
      61: aastore
      62: dup
      63: iconst_1
      64: getstatic     #11                 // Field INCLUDE:Lorg/apache/hadoop/hbase/filter/FilterWrapper$FilterRowRetCode;
      67: aastore
      68: dup
      69: iconst_2
      70: getstatic     #13                 // Field EXCLUDE:Lorg/apache/hadoop/hbase/filter/FilterWrapper$FilterRowRetCode;
      73: aastore
      74: dup
      75: iconst_3
      76: getstatic     #15                 // Field INCLUDE_THIS_FAMILY:Lorg/apache/hadoop/hbase/filter/FilterWrapper$FilterRowRetCode;
      79: aastore
      80: putstatic     #1                  // Field $VALUES:[Lorg/apache/hadoop/hbase/filter/FilterWrapper$FilterRowRetCode;
      83: return
}
