Compiled from "FilterProtos.java"
final class org.apache.hadoop.hbase.protobuf.generated.FilterProtos$1 implements com.google.protobuf.Descriptors$FileDescriptor$InternalDescriptorAssigner {
  org.apache.hadoop.hbase.protobuf.generated.FilterProtos$1();
    Code:
       0: aload_0
       1: invokespecial #1                  // Method java/lang/Object."<init>":()V
       4: return

  public com.google.protobuf.ExtensionRegistry assignDescriptors(com.google.protobuf.Descriptors$FileDescriptor);
    Code:
       0: aload_1
       1: invokestatic  #2                  // Method org/apache/hadoop/hbase/protobuf/generated/FilterProtos.access$29702:(Lcom/google/protobuf/Descriptors$FileDescriptor;)Lcom/google/protobuf/Descriptors$FileDescriptor;
       4: pop
       5: invokestatic  #3                  // Method org/apache/hadoop/hbase/protobuf/generated/FilterProtos.getDescriptor:()Lcom/google/protobuf/Descriptors$FileDescriptor;
       8: invokevirtual #4                  // Method com/google/protobuf/Descriptors$FileDescriptor.getMessageTypes:()Ljava/util/List;
      11: iconst_0
      12: invokeinterface #5,  2            // InterfaceMethod java/util/List.get:(I)Ljava/lang/Object;
      17: checkcast     #6                  // class com/google/protobuf/Descriptors$Descriptor
      20: invokestatic  #7                  // Method org/apache/hadoop/hbase/protobuf/generated/FilterProtos.access$002:(Lcom/google/protobuf/Descriptors$Descriptor;)Lcom/google/protobuf/Descriptors$Descriptor;
      23: pop
      24: new           #8                  // class com/google/protobuf/GeneratedMessage$FieldAccessorTable
      27: dup
      28: invokestatic  #9                  // Method org/apache/hadoop/hbase/protobuf/generated/FilterProtos.access$000:()Lcom/google/protobuf/Descriptors$Descriptor;
      31: iconst_2
      32: anewarray     #10                 // class java/lang/String
      35: dup
      36: iconst_0
      37: ldc           #11                 // String Name
      39: aastore
      40: dup
      41: iconst_1
      42: ldc           #12                 // String SerializedFilter
      44: aastore
      45: invokespecial #13                 // Method com/google/protobuf/GeneratedMessage$FieldAccessorTable."<init>":(Lcom/google/protobuf/Descriptors$Descriptor;[Ljava/lang/String;)V
      48: invokestatic  #14                 // Method org/apache/hadoop/hbase/protobuf/generated/FilterProtos.access$102:(Lcom/google/protobuf/GeneratedMessage$FieldAccessorTable;)Lcom/google/protobuf/GeneratedMessage$FieldAccessorTable;
      51: pop
      52: invokestatic  #3                  // Method org/apache/hadoop/hbase/protobuf/generated/FilterProtos.getDescriptor:()Lcom/google/protobuf/Descriptors$FileDescriptor;
      55: invokevirtual #4                  // Method com/google/protobuf/Descriptors$FileDescriptor.getMessageTypes:()Ljava/util/List;
      58: iconst_1
      59: invokeinterface #5,  2            // InterfaceMethod java/util/List.get:(I)Ljava/lang/Object;
      64: checkcast     #6                  // class com/google/protobuf/Descriptors$Descriptor
      67: invokestatic  #15                 // Method org/apache/hadoop/hbase/protobuf/generated/FilterProtos.access$1002:(Lcom/google/protobuf/Descriptors$Descriptor;)Lcom/google/protobuf/Descriptors$Descriptor;
      70: pop
      71: new           #8                  // class com/google/protobuf/GeneratedMessage$FieldAccessorTable
      74: dup
      75: invokestatic  #16                 // Method org/apache/hadoop/hbase/protobuf/generated/FilterProtos.access$1000:()Lcom/google/protobuf/Descriptors$Descriptor;
      78: iconst_1
      79: anewarray     #10                 // class java/lang/String
      82: dup
      83: iconst_0
      84: ldc           #17                 // String Limit
      86: aastore
      87: invokespecial #13                 // Method com/google/protobuf/GeneratedMessage$FieldAccessorTable."<init>":(Lcom/google/protobuf/Descriptors$Descriptor;[Ljava/lang/String;)V
      90: invokestatic  #18                 // Method org/apache/hadoop/hbase/protobuf/generated/FilterProtos.access$1102:(Lcom/google/protobuf/GeneratedMessage$FieldAccessorTable;)Lcom/google/protobuf/GeneratedMessage$FieldAccessorTable;
      93: pop
      94: invokestatic  #3                  // Method org/apache/hadoop/hbase/protobuf/generated/FilterProtos.getDescriptor:()Lcom/google/protobuf/Descriptors$FileDescriptor;
      97: invokevirtual #4                  // Method com/google/protobuf/Descriptors$FileDescriptor.getMessageTypes:()Ljava/util/List;
     100: iconst_2
     101: invokeinterface #5,  2            // InterfaceMethod java/util/List.get:(I)Ljava/lang/Object;
     106: checkcast     #6                  // class com/google/protobuf/Descriptors$Descriptor
     109: invokestatic  #19                 // Method org/apache/hadoop/hbase/protobuf/generated/FilterProtos.access$1902:(Lcom/google/protobuf/Descriptors$Descriptor;)Lcom/google/protobuf/Descriptors$Descriptor;
     112: pop
     113: new           #8                  // class com/google/protobuf/GeneratedMessage$FieldAccessorTable
     116: dup
     117: invokestatic  #20                 // Method org/apache/hadoop/hbase/protobuf/generated/FilterProtos.access$1900:()Lcom/google/protobuf/Descriptors$Descriptor;
     120: iconst_3
     121: anewarray     #10                 // class java/lang/String
     124: dup
     125: iconst_0
     126: ldc           #17                 // String Limit
     128: aastore
     129: dup
     130: iconst_1
     131: ldc           #21                 // String Offset
     133: aastore
     134: dup
     135: iconst_2
     136: ldc           #22                 // String ColumnOffset
     138: aastore
     139: invokespecial #13                 // Method com/google/protobuf/GeneratedMessage$FieldAccessorTable."<init>":(Lcom/google/protobuf/Descriptors$Descriptor;[Ljava/lang/String;)V
     142: invokestatic  #23                 // Method org/apache/hadoop/hbase/protobuf/generated/FilterProtos.access$2002:(Lcom/google/protobuf/GeneratedMessage$FieldAccessorTable;)Lcom/google/protobuf/GeneratedMessage$FieldAccessorTable;
     145: pop
     146: invokestatic  #3                  // Method org/apache/hadoop/hbase/protobuf/generated/FilterProtos.getDescriptor:()Lcom/google/protobuf/Descriptors$FileDescriptor;
     149: invokevirtual #4                  // Method com/google/protobuf/Descriptors$FileDescriptor.getMessageTypes:()Ljava/util/List;
     152: iconst_3
     153: invokeinterface #5,  2            // InterfaceMethod java/util/List.get:(I)Ljava/lang/Object;
     158: checkcast     #6                  // class com/google/protobuf/Descriptors$Descriptor
     161: invokestatic  #24                 // Method org/apache/hadoop/hbase/protobuf/generated/FilterProtos.access$3002:(Lcom/google/protobuf/Descriptors$Descriptor;)Lcom/google/protobuf/Descriptors$Descriptor;
     164: pop
     165: new           #8                  // class com/google/protobuf/GeneratedMessage$FieldAccessorTable
     168: dup
     169: invokestatic  #25                 // Method org/apache/hadoop/hbase/protobuf/generated/FilterProtos.access$3000:()Lcom/google/protobuf/Descriptors$Descriptor;
     172: iconst_1
     173: anewarray     #10                 // class java/lang/String
     176: dup
     177: iconst_0
     178: ldc           #26                 // String Prefix
     180: aastore
     181: invokespecial #13                 // Method com/google/protobuf/GeneratedMessage$FieldAccessorTable."<init>":(Lcom/google/protobuf/Descriptors$Descriptor;[Ljava/lang/String;)V
     184: invokestatic  #27                 // Method org/apache/hadoop/hbase/protobuf/generated/FilterProtos.access$3102:(Lcom/google/protobuf/GeneratedMessage$FieldAccessorTable;)Lcom/google/protobuf/GeneratedMessage$FieldAccessorTable;
     187: pop
     188: invokestatic  #3                  // Method org/apache/hadoop/hbase/protobuf/generated/FilterProtos.getDescriptor:()Lcom/google/protobuf/Descriptors$FileDescriptor;
     191: invokevirtual #4                  // Method com/google/protobuf/Descriptors$FileDescriptor.getMessageTypes:()Ljava/util/List;
     194: iconst_4
     195: invokeinterface #5,  2            // InterfaceMethod java/util/List.get:(I)Ljava/lang/Object;
     200: checkcast     #6                  // class com/google/protobuf/Descriptors$Descriptor
     203: invokestatic  #28                 // Method org/apache/hadoop/hbase/protobuf/generated/FilterProtos.access$3902:(Lcom/google/protobuf/Descriptors$Descriptor;)Lcom/google/protobuf/Descriptors$Descriptor;
     206: pop
     207: new           #8                  // class com/google/protobuf/GeneratedMessage$FieldAccessorTable
     210: dup
     211: invokestatic  #29                 // Method org/apache/hadoop/hbase/protobuf/generated/FilterProtos.access$3900:()Lcom/google/protobuf/Descriptors$Descriptor;
     214: iconst_4
     215: anewarray     #10                 // class java/lang/String
     218: dup
     219: iconst_0
     220: ldc           #30                 // String MinColumn
     222: aastore
     223: dup
     224: iconst_1
     225: ldc           #31                 // String MinColumnInclusive
     227: aastore
     228: dup
     229: iconst_2
     230: ldc           #32                 // String MaxColumn
     232: aastore
     233: dup
     234: iconst_3
     235: ldc           #33                 // String MaxColumnInclusive
     237: aastore
     238: invokespecial #13                 // Method com/google/protobuf/GeneratedMessage$FieldAccessorTable."<init>":(Lcom/google/protobuf/Descriptors$Descriptor;[Ljava/lang/String;)V
     241: invokestatic  #34                 // Method org/apache/hadoop/hbase/protobuf/generated/FilterProtos.access$4002:(Lcom/google/protobuf/GeneratedMessage$FieldAccessorTable;)Lcom/google/protobuf/GeneratedMessage$FieldAccessorTable;
     244: pop
     245: invokestatic  #3                  // Method org/apache/hadoop/hbase/protobuf/generated/FilterProtos.getDescriptor:()Lcom/google/protobuf/Descriptors$FileDescriptor;
     248: invokevirtual #4                  // Method com/google/protobuf/Descriptors$FileDescriptor.getMessageTypes:()Ljava/util/List;
     251: iconst_5
     252: invokeinterface #5,  2            // InterfaceMethod java/util/List.get:(I)Ljava/lang/Object;
     257: checkcast     #6                  // class com/google/protobuf/Descriptors$Descriptor
     260: invokestatic  #35                 // Method org/apache/hadoop/hbase/protobuf/generated/FilterProtos.access$5102:(Lcom/google/protobuf/Descriptors$Descriptor;)Lcom/google/protobuf/Descriptors$Descriptor;
     263: pop
     264: new           #8                  // class com/google/protobuf/GeneratedMessage$FieldAccessorTable
     267: dup
     268: invokestatic  #36                 // Method org/apache/hadoop/hbase/protobuf/generated/FilterProtos.access$5100:()Lcom/google/protobuf/Descriptors$Descriptor;
     271: iconst_2
     272: anewarray     #10                 // class java/lang/String
     275: dup
     276: iconst_0
     277: ldc           #37                 // String CompareOp
     279: aastore
     280: dup
     281: iconst_1
     282: ldc           #38                 // String Comparator
     284: aastore
     285: invokespecial #13                 // Method com/google/protobuf/GeneratedMessage$FieldAccessorTable."<init>":(Lcom/google/protobuf/Descriptors$Descriptor;[Ljava/lang/String;)V
     288: invokestatic  #39                 // Method org/apache/hadoop/hbase/protobuf/generated/FilterProtos.access$5202:(Lcom/google/protobuf/GeneratedMessage$FieldAccessorTable;)Lcom/google/protobuf/GeneratedMessage$FieldAccessorTable;
     291: pop
     292: invokestatic  #3                  // Method org/apache/hadoop/hbase/protobuf/generated/FilterProtos.getDescriptor:()Lcom/google/protobuf/Descriptors$FileDescriptor;
     295: invokevirtual #4                  // Method com/google/protobuf/Descriptors$FileDescriptor.getMessageTypes:()Ljava/util/List;
     298: bipush        6
     300: invokeinterface #5,  2            // InterfaceMethod java/util/List.get:(I)Ljava/lang/Object;
     305: checkcast     #6                  // class com/google/protobuf/Descriptors$Descriptor
     308: invokestatic  #40                 // Method org/apache/hadoop/hbase/protobuf/generated/FilterProtos.access$6102:(Lcom/google/protobuf/Descriptors$Descriptor;)Lcom/google/protobuf/Descriptors$Descriptor;
     311: pop
     312: new           #8                  // class com/google/protobuf/GeneratedMessage$FieldAccessorTable
     315: dup
     316: invokestatic  #41                 // Method org/apache/hadoop/hbase/protobuf/generated/FilterProtos.access$6100:()Lcom/google/protobuf/Descriptors$Descriptor;
     319: iconst_4
     320: anewarray     #10                 // class java/lang/String
     323: dup
     324: iconst_0
     325: ldc           #42                 // String CompareFilter
     327: aastore
     328: dup
     329: iconst_1
     330: ldc           #43                 // String ColumnFamily
     332: aastore
     333: dup
     334: iconst_2
     335: ldc           #44                 // String ColumnQualifier
     337: aastore
     338: dup
     339: iconst_3
     340: ldc           #45                 // String DropDependentColumn
     342: aastore
     343: invokespecial #13                 // Method com/google/protobuf/GeneratedMessage$FieldAccessorTable."<init>":(Lcom/google/protobuf/Descriptors$Descriptor;[Ljava/lang/String;)V
     346: invokestatic  #46                 // Method org/apache/hadoop/hbase/protobuf/generated/FilterProtos.access$6202:(Lcom/google/protobuf/GeneratedMessage$FieldAccessorTable;)Lcom/google/protobuf/GeneratedMessage$FieldAccessorTable;
     349: pop
     350: invokestatic  #3                  // Method org/apache/hadoop/hbase/protobuf/generated/FilterProtos.getDescriptor:()Lcom/google/protobuf/Descriptors$FileDescriptor;
     353: invokevirtual #4                  // Method com/google/protobuf/Descriptors$FileDescriptor.getMessageTypes:()Ljava/util/List;
     356: bipush        7
     358: invokeinterface #5,  2            // InterfaceMethod java/util/List.get:(I)Ljava/lang/Object;
     363: checkcast     #6                  // class com/google/protobuf/Descriptors$Descriptor
     366: invokestatic  #47                 // Method org/apache/hadoop/hbase/protobuf/generated/FilterProtos.access$7302:(Lcom/google/protobuf/Descriptors$Descriptor;)Lcom/google/protobuf/Descriptors$Descriptor;
     369: pop
     370: new           #8                  // class com/google/protobuf/GeneratedMessage$FieldAccessorTable
     373: dup
     374: invokestatic  #48                 // Method org/apache/hadoop/hbase/protobuf/generated/FilterProtos.access$7300:()Lcom/google/protobuf/Descriptors$Descriptor;
     377: iconst_1
     378: anewarray     #10                 // class java/lang/String
     381: dup
     382: iconst_0
     383: ldc           #42                 // String CompareFilter
     385: aastore
     386: invokespecial #13                 // Method com/google/protobuf/GeneratedMessage$FieldAccessorTable."<init>":(Lcom/google/protobuf/Descriptors$Descriptor;[Ljava/lang/String;)V
     389: invokestatic  #49                 // Method org/apache/hadoop/hbase/protobuf/generated/FilterProtos.access$7402:(Lcom/google/protobuf/GeneratedMessage$FieldAccessorTable;)Lcom/google/protobuf/GeneratedMessage$FieldAccessorTable;
     392: pop
     393: invokestatic  #3                  // Method org/apache/hadoop/hbase/protobuf/generated/FilterProtos.getDescriptor:()Lcom/google/protobuf/Descriptors$FileDescriptor;
     396: invokevirtual #4                  // Method com/google/protobuf/Descriptors$FileDescriptor.getMessageTypes:()Ljava/util/List;
     399: bipush        8
     401: invokeinterface #5,  2            // InterfaceMethod java/util/List.get:(I)Ljava/lang/Object;
     406: checkcast     #6                  // class com/google/protobuf/Descriptors$Descriptor
     409: invokestatic  #50                 // Method org/apache/hadoop/hbase/protobuf/generated/FilterProtos.access$8202:(Lcom/google/protobuf/Descriptors$Descriptor;)Lcom/google/protobuf/Descriptors$Descriptor;
     412: pop
     413: new           #8                  // class com/google/protobuf/GeneratedMessage$FieldAccessorTable
     416: dup
     417: invokestatic  #51                 // Method org/apache/hadoop/hbase/protobuf/generated/FilterProtos.access$8200:()Lcom/google/protobuf/Descriptors$Descriptor;
     420: iconst_2
     421: anewarray     #10                 // class java/lang/String
     424: dup
     425: iconst_0
     426: ldc           #52                 // String Operator
     428: aastore
     429: dup
     430: iconst_1
     431: ldc           #53                 // String Filters
     433: aastore
     434: invokespecial #13                 // Method com/google/protobuf/GeneratedMessage$FieldAccessorTable."<init>":(Lcom/google/protobuf/Descriptors$Descriptor;[Ljava/lang/String;)V
     437: invokestatic  #54                 // Method org/apache/hadoop/hbase/protobuf/generated/FilterProtos.access$8302:(Lcom/google/protobuf/GeneratedMessage$FieldAccessorTable;)Lcom/google/protobuf/GeneratedMessage$FieldAccessorTable;
     440: pop
     441: invokestatic  #3                  // Method org/apache/hadoop/hbase/protobuf/generated/FilterProtos.getDescriptor:()Lcom/google/protobuf/Descriptors$FileDescriptor;
     444: invokevirtual #4                  // Method com/google/protobuf/Descriptors$FileDescriptor.getMessageTypes:()Ljava/util/List;
     447: bipush        9
     449: invokeinterface #5,  2            // InterfaceMethod java/util/List.get:(I)Ljava/lang/Object;
     454: checkcast     #6                  // class com/google/protobuf/Descriptors$Descriptor
     457: invokestatic  #55                 // Method org/apache/hadoop/hbase/protobuf/generated/FilterProtos.access$9302:(Lcom/google/protobuf/Descriptors$Descriptor;)Lcom/google/protobuf/Descriptors$Descriptor;
     460: pop
     461: new           #8                  // class com/google/protobuf/GeneratedMessage$FieldAccessorTable
     464: dup
     465: invokestatic  #56                 // Method org/apache/hadoop/hbase/protobuf/generated/FilterProtos.access$9300:()Lcom/google/protobuf/Descriptors$Descriptor;
     468: iconst_1
     469: anewarray     #10                 // class java/lang/String
     472: dup
     473: iconst_0
     474: ldc           #57                 // String Filter
     476: aastore
     477: invokespecial #13                 // Method com/google/protobuf/GeneratedMessage$FieldAccessorTable."<init>":(Lcom/google/protobuf/Descriptors$Descriptor;[Ljava/lang/String;)V
     480: invokestatic  #58                 // Method org/apache/hadoop/hbase/protobuf/generated/FilterProtos.access$9402:(Lcom/google/protobuf/GeneratedMessage$FieldAccessorTable;)Lcom/google/protobuf/GeneratedMessage$FieldAccessorTable;
     483: pop
     484: invokestatic  #3                  // Method org/apache/hadoop/hbase/protobuf/generated/FilterProtos.getDescriptor:()Lcom/google/protobuf/Descriptors$FileDescriptor;
     487: invokevirtual #4                  // Method com/google/protobuf/Descriptors$FileDescriptor.getMessageTypes:()Ljava/util/List;
     490: bipush        10
     492: invokeinterface #5,  2            // InterfaceMethod java/util/List.get:(I)Ljava/lang/Object;
     497: checkcast     #6                  // class com/google/protobuf/Descriptors$Descriptor
     500: invokestatic  #59                 // Method org/apache/hadoop/hbase/protobuf/generated/FilterProtos.access$10202:(Lcom/google/protobuf/Descriptors$Descriptor;)Lcom/google/protobuf/Descriptors$Descriptor;
     503: pop
     504: new           #8                  // class com/google/protobuf/GeneratedMessage$FieldAccessorTable
     507: dup
     508: invokestatic  #60                 // Method org/apache/hadoop/hbase/protobuf/generated/FilterProtos.access$10200:()Lcom/google/protobuf/Descriptors$Descriptor;
     511: iconst_0
     512: anewarray     #10                 // class java/lang/String
     515: invokespecial #13                 // Method com/google/protobuf/GeneratedMessage$FieldAccessorTable."<init>":(Lcom/google/protobuf/Descriptors$Descriptor;[Ljava/lang/String;)V
     518: invokestatic  #61                 // Method org/apache/hadoop/hbase/protobuf/generated/FilterProtos.access$10302:(Lcom/google/protobuf/GeneratedMessage$FieldAccessorTable;)Lcom/google/protobuf/GeneratedMessage$FieldAccessorTable;
     521: pop
     522: invokestatic  #3                  // Method org/apache/hadoop/hbase/protobuf/generated/FilterProtos.getDescriptor:()Lcom/google/protobuf/Descriptors$FileDescriptor;
     525: invokevirtual #4                  // Method com/google/protobuf/Descriptors$FileDescriptor.getMessageTypes:()Ljava/util/List;
     528: bipush        11
     530: invokeinterface #5,  2            // InterfaceMethod java/util/List.get:(I)Ljava/lang/Object;
     535: checkcast     #6                  // class com/google/protobuf/Descriptors$Descriptor
     538: invokestatic  #62                 // Method org/apache/hadoop/hbase/protobuf/generated/FilterProtos.access$10902:(Lcom/google/protobuf/Descriptors$Descriptor;)Lcom/google/protobuf/Descriptors$Descriptor;
     541: pop
     542: new           #8                  // class com/google/protobuf/GeneratedMessage$FieldAccessorTable
     545: dup
     546: invokestatic  #63                 // Method org/apache/hadoop/hbase/protobuf/generated/FilterProtos.access$10900:()Lcom/google/protobuf/Descriptors$Descriptor;
     549: iconst_1
     550: anewarray     #10                 // class java/lang/String
     553: dup
     554: iconst_0
     555: ldc           #64                 // String Qualifiers
     557: aastore
     558: invokespecial #13                 // Method com/google/protobuf/GeneratedMessage$FieldAccessorTable."<init>":(Lcom/google/protobuf/Descriptors$Descriptor;[Ljava/lang/String;)V
     561: invokestatic  #65                 // Method org/apache/hadoop/hbase/protobuf/generated/FilterProtos.access$11002:(Lcom/google/protobuf/GeneratedMessage$FieldAccessorTable;)Lcom/google/protobuf/GeneratedMessage$FieldAccessorTable;
     564: pop
     565: invokestatic  #3                  // Method org/apache/hadoop/hbase/protobuf/generated/FilterProtos.getDescriptor:()Lcom/google/protobuf/Descriptors$FileDescriptor;
     568: invokevirtual #4                  // Method com/google/protobuf/Descriptors$FileDescriptor.getMessageTypes:()Ljava/util/List;
     571: bipush        12
     573: invokeinterface #5,  2            // InterfaceMethod java/util/List.get:(I)Ljava/lang/Object;
     578: checkcast     #6                  // class com/google/protobuf/Descriptors$Descriptor
     581: invokestatic  #66                 // Method org/apache/hadoop/hbase/protobuf/generated/FilterProtos.access$11702:(Lcom/google/protobuf/Descriptors$Descriptor;)Lcom/google/protobuf/Descriptors$Descriptor;
     584: pop
     585: new           #8                  // class com/google/protobuf/GeneratedMessage$FieldAccessorTable
     588: dup
     589: invokestatic  #67                 // Method org/apache/hadoop/hbase/protobuf/generated/FilterProtos.access$11700:()Lcom/google/protobuf/Descriptors$Descriptor;
     592: iconst_1
     593: anewarray     #10                 // class java/lang/String
     596: dup
     597: iconst_0
     598: ldc           #68                 // String FuzzyKeysData
     600: aastore
     601: invokespecial #13                 // Method com/google/protobuf/GeneratedMessage$FieldAccessorTable."<init>":(Lcom/google/protobuf/Descriptors$Descriptor;[Ljava/lang/String;)V
     604: invokestatic  #69                 // Method org/apache/hadoop/hbase/protobuf/generated/FilterProtos.access$11802:(Lcom/google/protobuf/GeneratedMessage$FieldAccessorTable;)Lcom/google/protobuf/GeneratedMessage$FieldAccessorTable;
     607: pop
     608: invokestatic  #3                  // Method org/apache/hadoop/hbase/protobuf/generated/FilterProtos.getDescriptor:()Lcom/google/protobuf/Descriptors$FileDescriptor;
     611: invokevirtual #4                  // Method com/google/protobuf/Descriptors$FileDescriptor.getMessageTypes:()Ljava/util/List;
     614: bipush        13
     616: invokeinterface #5,  2            // InterfaceMethod java/util/List.get:(I)Ljava/lang/Object;
     621: checkcast     #6                  // class com/google/protobuf/Descriptors$Descriptor
     624: invokestatic  #70                 // Method org/apache/hadoop/hbase/protobuf/generated/FilterProtos.access$12602:(Lcom/google/protobuf/Descriptors$Descriptor;)Lcom/google/protobuf/Descriptors$Descriptor;
     627: pop
     628: new           #8                  // class com/google/protobuf/GeneratedMessage$FieldAccessorTable
     631: dup
     632: invokestatic  #71                 // Method org/apache/hadoop/hbase/protobuf/generated/FilterProtos.access$12600:()Lcom/google/protobuf/Descriptors$Descriptor;
     635: iconst_1
     636: anewarray     #10                 // class java/lang/String
     639: dup
     640: iconst_0
     641: ldc           #72                 // String StopRowKey
     643: aastore
     644: invokespecial #13                 // Method com/google/protobuf/GeneratedMessage$FieldAccessorTable."<init>":(Lcom/google/protobuf/Descriptors$Descriptor;[Ljava/lang/String;)V
     647: invokestatic  #73                 // Method org/apache/hadoop/hbase/protobuf/generated/FilterProtos.access$12702:(Lcom/google/protobuf/GeneratedMessage$FieldAccessorTable;)Lcom/google/protobuf/GeneratedMessage$FieldAccessorTable;
     650: pop
     651: invokestatic  #3                  // Method org/apache/hadoop/hbase/protobuf/generated/FilterProtos.getDescriptor:()Lcom/google/protobuf/Descriptors$FileDescriptor;
     654: invokevirtual #4                  // Method com/google/protobuf/Descriptors$FileDescriptor.getMessageTypes:()Ljava/util/List;
     657: bipush        14
     659: invokeinterface #5,  2            // InterfaceMethod java/util/List.get:(I)Ljava/lang/Object;
     664: checkcast     #6                  // class com/google/protobuf/Descriptors$Descriptor
     667: invokestatic  #74                 // Method org/apache/hadoop/hbase/protobuf/generated/FilterProtos.access$13502:(Lcom/google/protobuf/Descriptors$Descriptor;)Lcom/google/protobuf/Descriptors$Descriptor;
     670: pop
     671: new           #8                  // class com/google/protobuf/GeneratedMessage$FieldAccessorTable
     674: dup
     675: invokestatic  #75                 // Method org/apache/hadoop/hbase/protobuf/generated/FilterProtos.access$13500:()Lcom/google/protobuf/Descriptors$Descriptor;
     678: iconst_1
     679: anewarray     #10                 // class java/lang/String
     682: dup
     683: iconst_0
     684: ldc           #76                 // String LenAsVal
     686: aastore
     687: invokespecial #13                 // Method com/google/protobuf/GeneratedMessage$FieldAccessorTable."<init>":(Lcom/google/protobuf/Descriptors$Descriptor;[Ljava/lang/String;)V
     690: invokestatic  #77                 // Method org/apache/hadoop/hbase/protobuf/generated/FilterProtos.access$13602:(Lcom/google/protobuf/GeneratedMessage$FieldAccessorTable;)Lcom/google/protobuf/GeneratedMessage$FieldAccessorTable;
     693: pop
     694: invokestatic  #3                  // Method org/apache/hadoop/hbase/protobuf/generated/FilterProtos.getDescriptor:()Lcom/google/protobuf/Descriptors$FileDescriptor;
     697: invokevirtual #4                  // Method com/google/protobuf/Descriptors$FileDescriptor.getMessageTypes:()Ljava/util/List;
     700: bipush        15
     702: invokeinterface #5,  2            // InterfaceMethod java/util/List.get:(I)Ljava/lang/Object;
     707: checkcast     #6                  // class com/google/protobuf/Descriptors$Descriptor
     710: invokestatic  #78                 // Method org/apache/hadoop/hbase/protobuf/generated/FilterProtos.access$14402:(Lcom/google/protobuf/Descriptors$Descriptor;)Lcom/google/protobuf/Descriptors$Descriptor;
     713: pop
     714: new           #8                  // class com/google/protobuf/GeneratedMessage$FieldAccessorTable
     717: dup
     718: invokestatic  #79                 // Method org/apache/hadoop/hbase/protobuf/generated/FilterProtos.access$14400:()Lcom/google/protobuf/Descriptors$Descriptor;
     721: iconst_1
     722: anewarray     #10                 // class java/lang/String
     725: dup
     726: iconst_0
     727: ldc           #80                 // String SortedPrefixes
     729: aastore
     730: invokespecial #13                 // Method com/google/protobuf/GeneratedMessage$FieldAccessorTable."<init>":(Lcom/google/protobuf/Descriptors$Descriptor;[Ljava/lang/String;)V
     733: invokestatic  #81                 // Method org/apache/hadoop/hbase/protobuf/generated/FilterProtos.access$14502:(Lcom/google/protobuf/GeneratedMessage$FieldAccessorTable;)Lcom/google/protobuf/GeneratedMessage$FieldAccessorTable;
     736: pop
     737: invokestatic  #3                  // Method org/apache/hadoop/hbase/protobuf/generated/FilterProtos.getDescriptor:()Lcom/google/protobuf/Descriptors$FileDescriptor;
     740: invokevirtual #4                  // Method com/google/protobuf/Descriptors$FileDescriptor.getMessageTypes:()Ljava/util/List;
     743: bipush        16
     745: invokeinterface #5,  2            // InterfaceMethod java/util/List.get:(I)Ljava/lang/Object;
     750: checkcast     #6                  // class com/google/protobuf/Descriptors$Descriptor
     753: invokestatic  #82                 // Method org/apache/hadoop/hbase/protobuf/generated/FilterProtos.access$15202:(Lcom/google/protobuf/Descriptors$Descriptor;)Lcom/google/protobuf/Descriptors$Descriptor;
     756: pop
     757: new           #8                  // class com/google/protobuf/GeneratedMessage$FieldAccessorTable
     760: dup
     761: invokestatic  #83                 // Method org/apache/hadoop/hbase/protobuf/generated/FilterProtos.access$15200:()Lcom/google/protobuf/Descriptors$Descriptor;
     764: iconst_1
     765: anewarray     #10                 // class java/lang/String
     768: dup
     769: iconst_0
     770: ldc           #84                 // String PageSize
     772: aastore
     773: invokespecial #13                 // Method com/google/protobuf/GeneratedMessage$FieldAccessorTable."<init>":(Lcom/google/protobuf/Descriptors$Descriptor;[Ljava/lang/String;)V
     776: invokestatic  #85                 // Method org/apache/hadoop/hbase/protobuf/generated/FilterProtos.access$15302:(Lcom/google/protobuf/GeneratedMessage$FieldAccessorTable;)Lcom/google/protobuf/GeneratedMessage$FieldAccessorTable;
     779: pop
     780: invokestatic  #3                  // Method org/apache/hadoop/hbase/protobuf/generated/FilterProtos.getDescriptor:()Lcom/google/protobuf/Descriptors$FileDescriptor;
     783: invokevirtual #4                  // Method com/google/protobuf/Descriptors$FileDescriptor.getMessageTypes:()Ljava/util/List;
     786: bipush        17
     788: invokeinterface #5,  2            // InterfaceMethod java/util/List.get:(I)Ljava/lang/Object;
     793: checkcast     #6                  // class com/google/protobuf/Descriptors$Descriptor
     796: invokestatic  #86                 // Method org/apache/hadoop/hbase/protobuf/generated/FilterProtos.access$16102:(Lcom/google/protobuf/Descriptors$Descriptor;)Lcom/google/protobuf/Descriptors$Descriptor;
     799: pop
     800: new           #8                  // class com/google/protobuf/GeneratedMessage$FieldAccessorTable
     803: dup
     804: invokestatic  #87                 // Method org/apache/hadoop/hbase/protobuf/generated/FilterProtos.access$16100:()Lcom/google/protobuf/Descriptors$Descriptor;
     807: iconst_1
     808: anewarray     #10                 // class java/lang/String
     811: dup
     812: iconst_0
     813: ldc           #26                 // String Prefix
     815: aastore
     816: invokespecial #13                 // Method com/google/protobuf/GeneratedMessage$FieldAccessorTable."<init>":(Lcom/google/protobuf/Descriptors$Descriptor;[Ljava/lang/String;)V
     819: invokestatic  #88                 // Method org/apache/hadoop/hbase/protobuf/generated/FilterProtos.access$16202:(Lcom/google/protobuf/GeneratedMessage$FieldAccessorTable;)Lcom/google/protobuf/GeneratedMessage$FieldAccessorTable;
     822: pop
     823: invokestatic  #3                  // Method org/apache/hadoop/hbase/protobuf/generated/FilterProtos.getDescriptor:()Lcom/google/protobuf/Descriptors$FileDescriptor;
     826: invokevirtual #4                  // Method com/google/protobuf/Descriptors$FileDescriptor.getMessageTypes:()Ljava/util/List;
     829: bipush        18
     831: invokeinterface #5,  2            // InterfaceMethod java/util/List.get:(I)Ljava/lang/Object;
     836: checkcast     #6                  // class com/google/protobuf/Descriptors$Descriptor
     839: invokestatic  #89                 // Method org/apache/hadoop/hbase/protobuf/generated/FilterProtos.access$17002:(Lcom/google/protobuf/Descriptors$Descriptor;)Lcom/google/protobuf/Descriptors$Descriptor;
     842: pop
     843: new           #8                  // class com/google/protobuf/GeneratedMessage$FieldAccessorTable
     846: dup
     847: invokestatic  #90                 // Method org/apache/hadoop/hbase/protobuf/generated/FilterProtos.access$17000:()Lcom/google/protobuf/Descriptors$Descriptor;
     850: iconst_1
     851: anewarray     #10                 // class java/lang/String
     854: dup
     855: iconst_0
     856: ldc           #42                 // String CompareFilter
     858: aastore
     859: invokespecial #13                 // Method com/google/protobuf/GeneratedMessage$FieldAccessorTable."<init>":(Lcom/google/protobuf/Descriptors$Descriptor;[Ljava/lang/String;)V
     862: invokestatic  #91                 // Method org/apache/hadoop/hbase/protobuf/generated/FilterProtos.access$17102:(Lcom/google/protobuf/GeneratedMessage$FieldAccessorTable;)Lcom/google/protobuf/GeneratedMessage$FieldAccessorTable;
     865: pop
     866: invokestatic  #3                  // Method org/apache/hadoop/hbase/protobuf/generated/FilterProtos.getDescriptor:()Lcom/google/protobuf/Descriptors$FileDescriptor;
     869: invokevirtual #4                  // Method com/google/protobuf/Descriptors$FileDescriptor.getMessageTypes:()Ljava/util/List;
     872: bipush        19
     874: invokeinterface #5,  2            // InterfaceMethod java/util/List.get:(I)Ljava/lang/Object;
     879: checkcast     #6                  // class com/google/protobuf/Descriptors$Descriptor
     882: invokestatic  #92                 // Method org/apache/hadoop/hbase/protobuf/generated/FilterProtos.access$17902:(Lcom/google/protobuf/Descriptors$Descriptor;)Lcom/google/protobuf/Descriptors$Descriptor;
     885: pop
     886: new           #8                  // class com/google/protobuf/GeneratedMessage$FieldAccessorTable
     889: dup
     890: invokestatic  #93                 // Method org/apache/hadoop/hbase/protobuf/generated/FilterProtos.access$17900:()Lcom/google/protobuf/Descriptors$Descriptor;
     893: iconst_1
     894: anewarray     #10                 // class java/lang/String
     897: dup
     898: iconst_0
     899: ldc           #94                 // String Chance
     901: aastore
     902: invokespecial #13                 // Method com/google/protobuf/GeneratedMessage$FieldAccessorTable."<init>":(Lcom/google/protobuf/Descriptors$Descriptor;[Ljava/lang/String;)V
     905: invokestatic  #95                 // Method org/apache/hadoop/hbase/protobuf/generated/FilterProtos.access$18002:(Lcom/google/protobuf/GeneratedMessage$FieldAccessorTable;)Lcom/google/protobuf/GeneratedMessage$FieldAccessorTable;
     908: pop
     909: invokestatic  #3                  // Method org/apache/hadoop/hbase/protobuf/generated/FilterProtos.getDescriptor:()Lcom/google/protobuf/Descriptors$FileDescriptor;
     912: invokevirtual #4                  // Method com/google/protobuf/Descriptors$FileDescriptor.getMessageTypes:()Ljava/util/List;
     915: bipush        20
     917: invokeinterface #5,  2            // InterfaceMethod java/util/List.get:(I)Ljava/lang/Object;
     922: checkcast     #6                  // class com/google/protobuf/Descriptors$Descriptor
     925: invokestatic  #96                 // Method org/apache/hadoop/hbase/protobuf/generated/FilterProtos.access$18802:(Lcom/google/protobuf/Descriptors$Descriptor;)Lcom/google/protobuf/Descriptors$Descriptor;
     928: pop
     929: new           #8                  // class com/google/protobuf/GeneratedMessage$FieldAccessorTable
     932: dup
     933: invokestatic  #97                 // Method org/apache/hadoop/hbase/protobuf/generated/FilterProtos.access$18800:()Lcom/google/protobuf/Descriptors$Descriptor;
     936: iconst_1
     937: anewarray     #10                 // class java/lang/String
     940: dup
     941: iconst_0
     942: ldc           #42                 // String CompareFilter
     944: aastore
     945: invokespecial #13                 // Method com/google/protobuf/GeneratedMessage$FieldAccessorTable."<init>":(Lcom/google/protobuf/Descriptors$Descriptor;[Ljava/lang/String;)V
     948: invokestatic  #98                 // Method org/apache/hadoop/hbase/protobuf/generated/FilterProtos.access$18902:(Lcom/google/protobuf/GeneratedMessage$FieldAccessorTable;)Lcom/google/protobuf/GeneratedMessage$FieldAccessorTable;
     951: pop
     952: invokestatic  #3                  // Method org/apache/hadoop/hbase/protobuf/generated/FilterProtos.getDescriptor:()Lcom/google/protobuf/Descriptors$FileDescriptor;
     955: invokevirtual #4                  // Method com/google/protobuf/Descriptors$FileDescriptor.getMessageTypes:()Ljava/util/List;
     958: bipush        21
     960: invokeinterface #5,  2            // InterfaceMethod java/util/List.get:(I)Ljava/lang/Object;
     965: checkcast     #6                  // class com/google/protobuf/Descriptors$Descriptor
     968: invokestatic  #99                 // Method org/apache/hadoop/hbase/protobuf/generated/FilterProtos.access$19702:(Lcom/google/protobuf/Descriptors$Descriptor;)Lcom/google/protobuf/Descriptors$Descriptor;
     971: pop
     972: new           #8                  // class com/google/protobuf/GeneratedMessage$FieldAccessorTable
     975: dup
     976: invokestatic  #100                // Method org/apache/hadoop/hbase/protobuf/generated/FilterProtos.access$19700:()Lcom/google/protobuf/Descriptors$Descriptor;
     979: iconst_1
     980: anewarray     #10                 // class java/lang/String
     983: dup
     984: iconst_0
     985: ldc           #101                // String SingleColumnValueFilter
     987: aastore
     988: invokespecial #13                 // Method com/google/protobuf/GeneratedMessage$FieldAccessorTable."<init>":(Lcom/google/protobuf/Descriptors$Descriptor;[Ljava/lang/String;)V
     991: invokestatic  #102                // Method org/apache/hadoop/hbase/protobuf/generated/FilterProtos.access$19802:(Lcom/google/protobuf/GeneratedMessage$FieldAccessorTable;)Lcom/google/protobuf/GeneratedMessage$FieldAccessorTable;
     994: pop
     995: invokestatic  #3                  // Method org/apache/hadoop/hbase/protobuf/generated/FilterProtos.getDescriptor:()Lcom/google/protobuf/Descriptors$FileDescriptor;
     998: invokevirtual #4                  // Method com/google/protobuf/Descriptors$FileDescriptor.getMessageTypes:()Ljava/util/List;
    1001: bipush        22
    1003: invokeinterface #5,  2            // InterfaceMethod java/util/List.get:(I)Ljava/lang/Object;
    1008: checkcast     #6                  // class com/google/protobuf/Descriptors$Descriptor
    1011: invokestatic  #103                // Method org/apache/hadoop/hbase/protobuf/generated/FilterProtos.access$20602:(Lcom/google/protobuf/Descriptors$Descriptor;)Lcom/google/protobuf/Descriptors$Descriptor;
    1014: pop
    1015: new           #8                  // class com/google/protobuf/GeneratedMessage$FieldAccessorTable
    1018: dup
    1019: invokestatic  #104                // Method org/apache/hadoop/hbase/protobuf/generated/FilterProtos.access$20600:()Lcom/google/protobuf/Descriptors$Descriptor;
    1022: bipush        6
    1024: anewarray     #10                 // class java/lang/String
    1027: dup
    1028: iconst_0
    1029: ldc           #43                 // String ColumnFamily
    1031: aastore
    1032: dup
    1033: iconst_1
    1034: ldc           #44                 // String ColumnQualifier
    1036: aastore
    1037: dup
    1038: iconst_2
    1039: ldc           #37                 // String CompareOp
    1041: aastore
    1042: dup
    1043: iconst_3
    1044: ldc           #38                 // String Comparator
    1046: aastore
    1047: dup
    1048: iconst_4
    1049: ldc           #105                // String FilterIfMissing
    1051: aastore
    1052: dup
    1053: iconst_5
    1054: ldc           #106                // String LatestVersionOnly
    1056: aastore
    1057: invokespecial #13                 // Method com/google/protobuf/GeneratedMessage$FieldAccessorTable."<init>":(Lcom/google/protobuf/Descriptors$Descriptor;[Ljava/lang/String;)V
    1060: invokestatic  #107                // Method org/apache/hadoop/hbase/protobuf/generated/FilterProtos.access$20702:(Lcom/google/protobuf/GeneratedMessage$FieldAccessorTable;)Lcom/google/protobuf/GeneratedMessage$FieldAccessorTable;
    1063: pop
    1064: invokestatic  #3                  // Method org/apache/hadoop/hbase/protobuf/generated/FilterProtos.getDescriptor:()Lcom/google/protobuf/Descriptors$FileDescriptor;
    1067: invokevirtual #4                  // Method com/google/protobuf/Descriptors$FileDescriptor.getMessageTypes:()Ljava/util/List;
    1070: bipush        23
    1072: invokeinterface #5,  2            // InterfaceMethod java/util/List.get:(I)Ljava/lang/Object;
    1077: checkcast     #6                  // class com/google/protobuf/Descriptors$Descriptor
    1080: invokestatic  #108                // Method org/apache/hadoop/hbase/protobuf/generated/FilterProtos.access$22002:(Lcom/google/protobuf/Descriptors$Descriptor;)Lcom/google/protobuf/Descriptors$Descriptor;
    1083: pop
    1084: new           #8                  // class com/google/protobuf/GeneratedMessage$FieldAccessorTable
    1087: dup
    1088: invokestatic  #109                // Method org/apache/hadoop/hbase/protobuf/generated/FilterProtos.access$22000:()Lcom/google/protobuf/Descriptors$Descriptor;
    1091: iconst_1
    1092: anewarray     #10                 // class java/lang/String
    1095: dup
    1096: iconst_0
    1097: ldc           #57                 // String Filter
    1099: aastore
    1100: invokespecial #13                 // Method com/google/protobuf/GeneratedMessage$FieldAccessorTable."<init>":(Lcom/google/protobuf/Descriptors$Descriptor;[Ljava/lang/String;)V
    1103: invokestatic  #110                // Method org/apache/hadoop/hbase/protobuf/generated/FilterProtos.access$22102:(Lcom/google/protobuf/GeneratedMessage$FieldAccessorTable;)Lcom/google/protobuf/GeneratedMessage$FieldAccessorTable;
    1106: pop
    1107: invokestatic  #3                  // Method org/apache/hadoop/hbase/protobuf/generated/FilterProtos.getDescriptor:()Lcom/google/protobuf/Descriptors$FileDescriptor;
    1110: invokevirtual #4                  // Method com/google/protobuf/Descriptors$FileDescriptor.getMessageTypes:()Ljava/util/List;
    1113: bipush        24
    1115: invokeinterface #5,  2            // InterfaceMethod java/util/List.get:(I)Ljava/lang/Object;
    1120: checkcast     #6                  // class com/google/protobuf/Descriptors$Descriptor
    1123: invokestatic  #111                // Method org/apache/hadoop/hbase/protobuf/generated/FilterProtos.access$22902:(Lcom/google/protobuf/Descriptors$Descriptor;)Lcom/google/protobuf/Descriptors$Descriptor;
    1126: pop
    1127: new           #8                  // class com/google/protobuf/GeneratedMessage$FieldAccessorTable
    1130: dup
    1131: invokestatic  #112                // Method org/apache/hadoop/hbase/protobuf/generated/FilterProtos.access$22900:()Lcom/google/protobuf/Descriptors$Descriptor;
    1134: iconst_2
    1135: anewarray     #10                 // class java/lang/String
    1138: dup
    1139: iconst_0
    1140: ldc           #113                // String Timestamps
    1142: aastore
    1143: dup
    1144: iconst_1
    1145: ldc           #114                // String CanHint
    1147: aastore
    1148: invokespecial #13                 // Method com/google/protobuf/GeneratedMessage$FieldAccessorTable."<init>":(Lcom/google/protobuf/Descriptors$Descriptor;[Ljava/lang/String;)V
    1151: invokestatic  #115                // Method org/apache/hadoop/hbase/protobuf/generated/FilterProtos.access$23002:(Lcom/google/protobuf/GeneratedMessage$FieldAccessorTable;)Lcom/google/protobuf/GeneratedMessage$FieldAccessorTable;
    1154: pop
    1155: invokestatic  #3                  // Method org/apache/hadoop/hbase/protobuf/generated/FilterProtos.getDescriptor:()Lcom/google/protobuf/Descriptors$FileDescriptor;
    1158: invokevirtual #4                  // Method com/google/protobuf/Descriptors$FileDescriptor.getMessageTypes:()Ljava/util/List;
    1161: bipush        25
    1163: invokeinterface #5,  2            // InterfaceMethod java/util/List.get:(I)Ljava/lang/Object;
    1168: checkcast     #6                  // class com/google/protobuf/Descriptors$Descriptor
    1171: invokestatic  #116                // Method org/apache/hadoop/hbase/protobuf/generated/FilterProtos.access$23902:(Lcom/google/protobuf/Descriptors$Descriptor;)Lcom/google/protobuf/Descriptors$Descriptor;
    1174: pop
    1175: new           #8                  // class com/google/protobuf/GeneratedMessage$FieldAccessorTable
    1178: dup
    1179: invokestatic  #117                // Method org/apache/hadoop/hbase/protobuf/generated/FilterProtos.access$23900:()Lcom/google/protobuf/Descriptors$Descriptor;
    1182: iconst_1
    1183: anewarray     #10                 // class java/lang/String
    1186: dup
    1187: iconst_0
    1188: ldc           #42                 // String CompareFilter
    1190: aastore
    1191: invokespecial #13                 // Method com/google/protobuf/GeneratedMessage$FieldAccessorTable."<init>":(Lcom/google/protobuf/Descriptors$Descriptor;[Ljava/lang/String;)V
    1194: invokestatic  #118                // Method org/apache/hadoop/hbase/protobuf/generated/FilterProtos.access$24002:(Lcom/google/protobuf/GeneratedMessage$FieldAccessorTable;)Lcom/google/protobuf/GeneratedMessage$FieldAccessorTable;
    1197: pop
    1198: invokestatic  #3                  // Method org/apache/hadoop/hbase/protobuf/generated/FilterProtos.getDescriptor:()Lcom/google/protobuf/Descriptors$FileDescriptor;
    1201: invokevirtual #4                  // Method com/google/protobuf/Descriptors$FileDescriptor.getMessageTypes:()Ljava/util/List;
    1204: bipush        26
    1206: invokeinterface #5,  2            // InterfaceMethod java/util/List.get:(I)Ljava/lang/Object;
    1211: checkcast     #6                  // class com/google/protobuf/Descriptors$Descriptor
    1214: invokestatic  #119                // Method org/apache/hadoop/hbase/protobuf/generated/FilterProtos.access$24802:(Lcom/google/protobuf/Descriptors$Descriptor;)Lcom/google/protobuf/Descriptors$Descriptor;
    1217: pop
    1218: new           #8                  // class com/google/protobuf/GeneratedMessage$FieldAccessorTable
    1221: dup
    1222: invokestatic  #120                // Method org/apache/hadoop/hbase/protobuf/generated/FilterProtos.access$24800:()Lcom/google/protobuf/Descriptors$Descriptor;
    1225: iconst_1
    1226: anewarray     #10                 // class java/lang/String
    1229: dup
    1230: iconst_0
    1231: ldc           #57                 // String Filter
    1233: aastore
    1234: invokespecial #13                 // Method com/google/protobuf/GeneratedMessage$FieldAccessorTable."<init>":(Lcom/google/protobuf/Descriptors$Descriptor;[Ljava/lang/String;)V
    1237: invokestatic  #121                // Method org/apache/hadoop/hbase/protobuf/generated/FilterProtos.access$24902:(Lcom/google/protobuf/GeneratedMessage$FieldAccessorTable;)Lcom/google/protobuf/GeneratedMessage$FieldAccessorTable;
    1240: pop
    1241: invokestatic  #3                  // Method org/apache/hadoop/hbase/protobuf/generated/FilterProtos.getDescriptor:()Lcom/google/protobuf/Descriptors$FileDescriptor;
    1244: invokevirtual #4                  // Method com/google/protobuf/Descriptors$FileDescriptor.getMessageTypes:()Ljava/util/List;
    1247: bipush        27
    1249: invokeinterface #5,  2            // InterfaceMethod java/util/List.get:(I)Ljava/lang/Object;
    1254: checkcast     #6                  // class com/google/protobuf/Descriptors$Descriptor
    1257: invokestatic  #122                // Method org/apache/hadoop/hbase/protobuf/generated/FilterProtos.access$25702:(Lcom/google/protobuf/Descriptors$Descriptor;)Lcom/google/protobuf/Descriptors$Descriptor;
    1260: pop
    1261: new           #8                  // class com/google/protobuf/GeneratedMessage$FieldAccessorTable
    1264: dup
    1265: invokestatic  #123                // Method org/apache/hadoop/hbase/protobuf/generated/FilterProtos.access$25700:()Lcom/google/protobuf/Descriptors$Descriptor;
    1268: iconst_0
    1269: anewarray     #10                 // class java/lang/String
    1272: invokespecial #13                 // Method com/google/protobuf/GeneratedMessage$FieldAccessorTable."<init>":(Lcom/google/protobuf/Descriptors$Descriptor;[Ljava/lang/String;)V
    1275: invokestatic  #124                // Method org/apache/hadoop/hbase/protobuf/generated/FilterProtos.access$25802:(Lcom/google/protobuf/GeneratedMessage$FieldAccessorTable;)Lcom/google/protobuf/GeneratedMessage$FieldAccessorTable;
    1278: pop
    1279: invokestatic  #3                  // Method org/apache/hadoop/hbase/protobuf/generated/FilterProtos.getDescriptor:()Lcom/google/protobuf/Descriptors$FileDescriptor;
    1282: invokevirtual #4                  // Method com/google/protobuf/Descriptors$FileDescriptor.getMessageTypes:()Ljava/util/List;
    1285: bipush        28
    1287: invokeinterface #5,  2            // InterfaceMethod java/util/List.get:(I)Ljava/lang/Object;
    1292: checkcast     #6                  // class com/google/protobuf/Descriptors$Descriptor
    1295: invokestatic  #125                // Method org/apache/hadoop/hbase/protobuf/generated/FilterProtos.access$26402:(Lcom/google/protobuf/Descriptors$Descriptor;)Lcom/google/protobuf/Descriptors$Descriptor;
    1298: pop
    1299: new           #8                  // class com/google/protobuf/GeneratedMessage$FieldAccessorTable
    1302: dup
    1303: invokestatic  #126                // Method org/apache/hadoop/hbase/protobuf/generated/FilterProtos.access$26400:()Lcom/google/protobuf/Descriptors$Descriptor;
    1306: iconst_4
    1307: anewarray     #10                 // class java/lang/String
    1310: dup
    1311: iconst_0
    1312: ldc           #127                // String StartRow
    1314: aastore
    1315: dup
    1316: iconst_1
    1317: ldc           #128                // String StartRowInclusive
    1319: aastore
    1320: dup
    1321: iconst_2
    1322: ldc           #129                // String StopRow
    1324: aastore
    1325: dup
    1326: iconst_3
    1327: ldc           #130                // String StopRowInclusive
    1329: aastore
    1330: invokespecial #13                 // Method com/google/protobuf/GeneratedMessage$FieldAccessorTable."<init>":(Lcom/google/protobuf/Descriptors$Descriptor;[Ljava/lang/String;)V
    1333: invokestatic  #131                // Method org/apache/hadoop/hbase/protobuf/generated/FilterProtos.access$26502:(Lcom/google/protobuf/GeneratedMessage$FieldAccessorTable;)Lcom/google/protobuf/GeneratedMessage$FieldAccessorTable;
    1336: pop
    1337: invokestatic  #3                  // Method org/apache/hadoop/hbase/protobuf/generated/FilterProtos.getDescriptor:()Lcom/google/protobuf/Descriptors$FileDescriptor;
    1340: invokevirtual #4                  // Method com/google/protobuf/Descriptors$FileDescriptor.getMessageTypes:()Ljava/util/List;
    1343: bipush        29
    1345: invokeinterface #5,  2            // InterfaceMethod java/util/List.get:(I)Ljava/lang/Object;
    1350: checkcast     #6                  // class com/google/protobuf/Descriptors$Descriptor
    1353: invokestatic  #132                // Method org/apache/hadoop/hbase/protobuf/generated/FilterProtos.access$27602:(Lcom/google/protobuf/Descriptors$Descriptor;)Lcom/google/protobuf/Descriptors$Descriptor;
    1356: pop
    1357: new           #8                  // class com/google/protobuf/GeneratedMessage$FieldAccessorTable
    1360: dup
    1361: invokestatic  #133                // Method org/apache/hadoop/hbase/protobuf/generated/FilterProtos.access$27600:()Lcom/google/protobuf/Descriptors$Descriptor;
    1364: iconst_1
    1365: anewarray     #10                 // class java/lang/String
    1368: dup
    1369: iconst_0
    1370: ldc           #134                // String RowRangeList
    1372: aastore
    1373: invokespecial #13                 // Method com/google/protobuf/GeneratedMessage$FieldAccessorTable."<init>":(Lcom/google/protobuf/Descriptors$Descriptor;[Ljava/lang/String;)V
    1376: invokestatic  #135                // Method org/apache/hadoop/hbase/protobuf/generated/FilterProtos.access$27702:(Lcom/google/protobuf/GeneratedMessage$FieldAccessorTable;)Lcom/google/protobuf/GeneratedMessage$FieldAccessorTable;
    1379: pop
    1380: invokestatic  #3                  // Method org/apache/hadoop/hbase/protobuf/generated/FilterProtos.getDescriptor:()Lcom/google/protobuf/Descriptors$FileDescriptor;
    1383: invokevirtual #4                  // Method com/google/protobuf/Descriptors$FileDescriptor.getMessageTypes:()Ljava/util/List;
    1386: bipush        30
    1388: invokeinterface #5,  2            // InterfaceMethod java/util/List.get:(I)Ljava/lang/Object;
    1393: checkcast     #6                  // class com/google/protobuf/Descriptors$Descriptor
    1396: invokestatic  #136                // Method org/apache/hadoop/hbase/protobuf/generated/FilterProtos.access$28502:(Lcom/google/protobuf/Descriptors$Descriptor;)Lcom/google/protobuf/Descriptors$Descriptor;
    1399: pop
    1400: new           #8                  // class com/google/protobuf/GeneratedMessage$FieldAccessorTable
    1403: dup
    1404: invokestatic  #137                // Method org/apache/hadoop/hbase/protobuf/generated/FilterProtos.access$28500:()Lcom/google/protobuf/Descriptors$Descriptor;
    1407: iconst_4
    1408: anewarray     #10                 // class java/lang/String
    1411: dup
    1412: iconst_0
    1413: ldc           #138                // String Family
    1415: aastore
    1416: dup
    1417: iconst_1
    1418: ldc           #139                // String Qualifier
    1420: aastore
    1421: dup
    1422: iconst_2
    1423: ldc           #37                 // String CompareOp
    1425: aastore
    1426: dup
    1427: iconst_3
    1428: ldc           #38                 // String Comparator
    1430: aastore
    1431: invokespecial #13                 // Method com/google/protobuf/GeneratedMessage$FieldAccessorTable."<init>":(Lcom/google/protobuf/Descriptors$Descriptor;[Ljava/lang/String;)V
    1434: invokestatic  #140                // Method org/apache/hadoop/hbase/protobuf/generated/FilterProtos.access$28602:(Lcom/google/protobuf/GeneratedMessage$FieldAccessorTable;)Lcom/google/protobuf/GeneratedMessage$FieldAccessorTable;
    1437: pop
    1438: aconst_null
    1439: areturn
}
