Compiled from "FilterList.java"
public final class org.apache.hadoop.hbase.filter.FilterList$Operator extends java.lang.Enum<org.apache.hadoop.hbase.filter.FilterList$Operator> {
  public static final org.apache.hadoop.hbase.filter.FilterList$Operator MUST_PASS_ALL;

  public static final org.apache.hadoop.hbase.filter.FilterList$Operator MUST_PASS_ONE;

  public static org.apache.hadoop.hbase.filter.FilterList$Operator[] values();
    Code:
       0: getstatic     #1                  // Field $VALUES:[Lorg/apache/hadoop/hbase/filter/FilterList$Operator;
       3: invokevirtual #2                  // Method "[Lorg/apache/hadoop/hbase/filter/FilterList$Operator;".clone:()Ljava/lang/Object;
       6: checkcast     #3                  // class "[Lorg/apache/hadoop/hbase/filter/FilterList$Operator;"
       9: areturn

  public static org.apache.hadoop.hbase.filter.FilterList$Operator valueOf(java.lang.String);
    Code:
       0: ldc           #4                  // class org/apache/hadoop/hbase/filter/FilterList$Operator
       2: aload_0
       3: invokestatic  #5                  // Method java/lang/Enum.valueOf:(Ljava/lang/Class;Ljava/lang/String;)Ljava/lang/Enum;
       6: checkcast     #4                  // class org/apache/hadoop/hbase/filter/FilterList$Operator
       9: areturn

  static {};
    Code:
       0: new           #4                  // class org/apache/hadoop/hbase/filter/FilterList$Operator
       3: dup
       4: ldc           #7                  // String MUST_PASS_ALL
       6: iconst_0
       7: invokespecial #8                  // Method "<init>":(Ljava/lang/String;I)V
      10: putstatic     #9                  // Field MUST_PASS_ALL:Lorg/apache/hadoop/hbase/filter/FilterList$Operator;
      13: new           #4                  // class org/apache/hadoop/hbase/filter/FilterList$Operator
      16: dup
      17: ldc           #10                 // String MUST_PASS_ONE
      19: iconst_1
      20: invokespecial #8                  // Method "<init>":(Ljava/lang/String;I)V
      23: putstatic     #11                 // Field MUST_PASS_ONE:Lorg/apache/hadoop/hbase/filter/FilterList$Operator;
      26: iconst_2
      27: anewarray     #4                  // class org/apache/hadoop/hbase/filter/FilterList$Operator
      30: dup
      31: iconst_0
      32: getstatic     #9                  // Field MUST_PASS_ALL:Lorg/apache/hadoop/hbase/filter/FilterList$Operator;
      35: aastore
      36: dup
      37: iconst_1
      38: getstatic     #11                 // Field MUST_PASS_ONE:Lorg/apache/hadoop/hbase/filter/FilterList$Operator;
      41: aastore
      42: putstatic     #1                  // Field $VALUES:[Lorg/apache/hadoop/hbase/filter/FilterList$Operator;
      45: return
}
