Compiled from "FilterListBase.java"
public abstract class org.apache.hadoop.hbase.filter.FilterListBase extends org.apache.hadoop.hbase.filter.FilterBase {
  protected final java.util.ArrayList<org.apache.hadoop.hbase.filter.Filter> filters;

  protected java.util.ArrayList<java.lang.Boolean> subFiltersIncludedCell;

  public org.apache.hadoop.hbase.filter.FilterListBase(java.util.List<org.apache.hadoop.hbase.filter.Filter>);
    Code:
       0: aload_0
       1: invokespecial #1                  // Method org/apache/hadoop/hbase/filter/FilterBase."<init>":()V
       4: aload_0
       5: aload_1
       6: aload_0
       7: getfield      #2                  // Field reversed:Z
      10: invokestatic  #3                  // Method checkAndGetReversed:(Ljava/util/List;Z)Z
      13: putfield      #2                  // Field reversed:Z
      16: aload_0
      17: new           #4                  // class java/util/ArrayList
      20: dup
      21: aload_1
      22: invokespecial #5                  // Method java/util/ArrayList."<init>":(Ljava/util/Collection;)V
      25: putfield      #6                  // Field filters:Ljava/util/ArrayList;
      28: return

  protected static boolean isInReturnCodes(org.apache.hadoop.hbase.filter.Filter$ReturnCode, org.apache.hadoop.hbase.filter.Filter$ReturnCode...);
    Code:
       0: aload_1
       1: astore_2
       2: aload_2
       3: arraylength
       4: istore_3
       5: iconst_0
       6: istore        4
       8: iload         4
      10: iload_3
      11: if_icmpge     34
      14: aload_2
      15: iload         4
      17: aaload
      18: astore        5
      20: aload_0
      21: aload         5
      23: if_acmpne     28
      26: iconst_1
      27: ireturn
      28: iinc          4, 1
      31: goto          8
      34: iconst_0
      35: ireturn

  protected static boolean checkAndGetReversed(java.util.List<org.apache.hadoop.hbase.filter.Filter>, boolean);
    Code:
       0: aload_0
       1: invokeinterface #7,  1            // InterfaceMethod java/util/List.isEmpty:()Z
       6: ifeq          11
       9: iload_1
      10: ireturn
      11: aload_0
      12: iconst_0
      13: invokeinterface #8,  2            // InterfaceMethod java/util/List.get:(I)Ljava/lang/Object;
      18: checkcast     #9                  // class org/apache/hadoop/hbase/filter/Filter
      21: invokevirtual #10                 // Method org/apache/hadoop/hbase/filter/Filter.isReversed:()Z
      24: istore_2
      25: iconst_1
      26: istore_3
      27: aload_0
      28: invokeinterface #11,  1           // InterfaceMethod java/util/List.size:()I
      33: istore        4
      35: iload_3
      36: iload         4
      38: if_icmpge     74
      41: aload_0
      42: iload_3
      43: invokeinterface #8,  2            // InterfaceMethod java/util/List.get:(I)Ljava/lang/Object;
      48: checkcast     #9                  // class org/apache/hadoop/hbase/filter/Filter
      51: invokevirtual #10                 // Method org/apache/hadoop/hbase/filter/Filter.isReversed:()Z
      54: iload_2
      55: if_icmpeq     68
      58: new           #12                 // class java/lang/IllegalArgumentException
      61: dup
      62: ldc           #13                 // String Filters in the list must have the same reversed flag
      64: invokespecial #14                 // Method java/lang/IllegalArgumentException."<init>":(Ljava/lang/String;)V
      67: athrow
      68: iinc          3, 1
      71: goto          35
      74: iload_2
      75: ireturn

  public abstract void addFilterLists(java.util.List<org.apache.hadoop.hbase.filter.Filter>);

  public int size();
    Code:
       0: aload_0
       1: getfield      #6                  // Field filters:Ljava/util/ArrayList;
       4: invokevirtual #15                 // Method java/util/ArrayList.size:()I
       7: ireturn

  public boolean isEmpty();
    Code:
       0: aload_0
       1: getfield      #6                  // Field filters:Ljava/util/ArrayList;
       4: invokevirtual #16                 // Method java/util/ArrayList.isEmpty:()Z
       7: ireturn

  public java.util.ArrayList<org.apache.hadoop.hbase.filter.Filter> getFilters();
    Code:
       0: aload_0
       1: getfield      #6                  // Field filters:Ljava/util/ArrayList;
       4: areturn

  protected int compareCell(org.apache.hadoop.hbase.Cell, org.apache.hadoop.hbase.Cell);
    Code:
       0: invokestatic  #17                 // InterfaceMethod org/apache/hadoop/hbase/CellComparator.getInstance:()Lorg/apache/hadoop/hbase/CellComparator;
       3: aload_1
       4: aload_2
       5: invokeinterface #18,  3           // InterfaceMethod org/apache/hadoop/hbase/CellComparator.compare:(Lorg/apache/hadoop/hbase/Cell;Lorg/apache/hadoop/hbase/Cell;)I
      10: istore_3
      11: aload_0
      12: getfield      #2                  // Field reversed:Z
      15: ifeq          24
      18: iconst_m1
      19: iload_3
      20: imul
      21: goto          25
      24: iload_3
      25: ireturn

  public org.apache.hadoop.hbase.Cell transformCell(org.apache.hadoop.hbase.Cell) throws java.io.IOException;
    Code:
       0: aload_0
       1: invokevirtual #19                 // Method isEmpty:()Z
       4: ifeq          13
       7: aload_0
       8: aload_1
       9: invokespecial #20                 // Method org/apache/hadoop/hbase/filter/FilterBase.transformCell:(Lorg/apache/hadoop/hbase/Cell;)Lorg/apache/hadoop/hbase/Cell;
      12: areturn
      13: aload_1
      14: astore_2
      15: iconst_0
      16: istore_3
      17: aload_0
      18: getfield      #6                  // Field filters:Ljava/util/ArrayList;
      21: invokevirtual #15                 // Method java/util/ArrayList.size:()I
      24: istore        4
      26: iload_3
      27: iload         4
      29: if_icmpge     71
      32: aload_0
      33: getfield      #21                 // Field subFiltersIncludedCell:Ljava/util/ArrayList;
      36: iload_3
      37: invokevirtual #22                 // Method java/util/ArrayList.get:(I)Ljava/lang/Object;
      40: checkcast     #23                 // class java/lang/Boolean
      43: invokevirtual #24                 // Method java/lang/Boolean.booleanValue:()Z
      46: ifeq          65
      49: aload_0
      50: getfield      #6                  // Field filters:Ljava/util/ArrayList;
      53: iload_3
      54: invokevirtual #22                 // Method java/util/ArrayList.get:(I)Ljava/lang/Object;
      57: checkcast     #9                  // class org/apache/hadoop/hbase/filter/Filter
      60: aload_2
      61: invokevirtual #25                 // Method org/apache/hadoop/hbase/filter/Filter.transformCell:(Lorg/apache/hadoop/hbase/Cell;)Lorg/apache/hadoop/hbase/Cell;
      64: astore_2
      65: iinc          3, 1
      68: goto          26
      71: aload_2
      72: areturn

  public org.apache.hadoop.hbase.filter.Filter$ReturnCode filterKeyValue(org.apache.hadoop.hbase.Cell) throws java.io.IOException;
    Code:
       0: aload_0
       1: aload_1
       2: invokevirtual #26                 // Method filterCell:(Lorg/apache/hadoop/hbase/Cell;)Lorg/apache/hadoop/hbase/filter/Filter$ReturnCode;
       5: areturn

  public void filterRowCells(java.util.List<org.apache.hadoop.hbase.Cell>) throws java.io.IOException;
    Code:
       0: iconst_0
       1: istore_2
       2: aload_0
       3: getfield      #6                  // Field filters:Ljava/util/ArrayList;
       6: invokevirtual #15                 // Method java/util/ArrayList.size:()I
       9: istore_3
      10: iload_2
      11: iload_3
      12: if_icmpge     36
      15: aload_0
      16: getfield      #6                  // Field filters:Ljava/util/ArrayList;
      19: iload_2
      20: invokevirtual #22                 // Method java/util/ArrayList.get:(I)Ljava/lang/Object;
      23: checkcast     #9                  // class org/apache/hadoop/hbase/filter/Filter
      26: aload_1
      27: invokevirtual #27                 // Method org/apache/hadoop/hbase/filter/Filter.filterRowCells:(Ljava/util/List;)V
      30: iinc          2, 1
      33: goto          10
      36: return

  public boolean hasFilterRow();
    Code:
       0: iconst_0
       1: istore_1
       2: aload_0
       3: getfield      #6                  // Field filters:Ljava/util/ArrayList;
       6: invokevirtual #15                 // Method java/util/ArrayList.size:()I
       9: istore_2
      10: iload_1
      11: iload_2
      12: if_icmpge     40
      15: aload_0
      16: getfield      #6                  // Field filters:Ljava/util/ArrayList;
      19: iload_1
      20: invokevirtual #22                 // Method java/util/ArrayList.get:(I)Ljava/lang/Object;
      23: checkcast     #9                  // class org/apache/hadoop/hbase/filter/Filter
      26: invokevirtual #28                 // Method org/apache/hadoop/hbase/filter/Filter.hasFilterRow:()Z
      29: ifeq          34
      32: iconst_1
      33: ireturn
      34: iinc          1, 1
      37: goto          10
      40: iconst_0
      41: ireturn

  public boolean isFamilyEssential(byte[]) throws java.io.IOException;
    Code:
       0: aload_0
       1: getfield      #6                  // Field filters:Ljava/util/ArrayList;
       4: invokevirtual #16                 // Method java/util/ArrayList.isEmpty:()Z
       7: ifeq          16
      10: aload_0
      11: aload_1
      12: invokespecial #29                 // Method org/apache/hadoop/hbase/filter/FilterBase.isFamilyEssential:([B)Z
      15: ireturn
      16: iconst_0
      17: istore_2
      18: aload_0
      19: getfield      #6                  // Field filters:Ljava/util/ArrayList;
      22: invokevirtual #15                 // Method java/util/ArrayList.size:()I
      25: istore_3
      26: iload_2
      27: iload_3
      28: if_icmpge     57
      31: aload_0
      32: getfield      #6                  // Field filters:Ljava/util/ArrayList;
      35: iload_2
      36: invokevirtual #22                 // Method java/util/ArrayList.get:(I)Ljava/lang/Object;
      39: checkcast     #9                  // class org/apache/hadoop/hbase/filter/Filter
      42: aload_1
      43: invokevirtual #30                 // Method org/apache/hadoop/hbase/filter/Filter.isFamilyEssential:([B)Z
      46: ifeq          51
      49: iconst_1
      50: ireturn
      51: iinc          2, 1
      54: goto          26
      57: iconst_0
      58: ireturn

  public void setReversed(boolean);
    Code:
       0: iconst_0
       1: istore_2
       2: aload_0
       3: getfield      #6                  // Field filters:Ljava/util/ArrayList;
       6: invokevirtual #15                 // Method java/util/ArrayList.size:()I
       9: istore_3
      10: iload_2
      11: iload_3
      12: if_icmpge     36
      15: aload_0
      16: getfield      #6                  // Field filters:Ljava/util/ArrayList;
      19: iload_2
      20: invokevirtual #22                 // Method java/util/ArrayList.get:(I)Ljava/lang/Object;
      23: checkcast     #9                  // class org/apache/hadoop/hbase/filter/Filter
      26: iload_1
      27: invokevirtual #31                 // Method org/apache/hadoop/hbase/filter/Filter.setReversed:(Z)V
      30: iinc          2, 1
      33: goto          10
      36: aload_0
      37: iload_1
      38: putfield      #2                  // Field reversed:Z
      41: return

  public java.lang.String toString();
    Code:
       0: aload_0
       1: invokevirtual #32                 // Method size:()I
       4: iconst_5
       5: if_icmpge     15
       8: aload_0
       9: invokevirtual #32                 // Method size:()I
      12: goto          16
      15: iconst_5
      16: istore_1
      17: aload_0
      18: aload_0
      19: getfield      #6                  // Field filters:Ljava/util/ArrayList;
      22: iconst_0
      23: iload_1
      24: invokevirtual #34                 // Method java/util/ArrayList.subList:(II)Ljava/util/List;
      27: invokevirtual #35                 // Method formatLogFilters:(Ljava/util/List;)Ljava/lang/String;
      30: areturn

  protected abstract java.lang.String formatLogFilters(java.util.List<org.apache.hadoop.hbase.filter.Filter>);
}
