Compiled from "FilterProtos.java"
public final class org.apache.hadoop.hbase.protobuf.generated.FilterProtos$RowRange$Builder extends com.google.protobuf.GeneratedMessage$Builder<org.apache.hadoop.hbase.protobuf.generated.FilterProtos$RowRange$Builder> implements org.apache.hadoop.hbase.protobuf.generated.FilterProtos$RowRangeOrBuilder {
  public static final com.google.protobuf.Descriptors$Descriptor getDescriptor();
    Code:
       0: invokestatic  #3                  // Method org/apache/hadoop/hbase/protobuf/generated/FilterProtos.access$26400:()Lcom/google/protobuf/Descriptors$Descriptor;
       3: areturn

  protected com.google.protobuf.GeneratedMessage$FieldAccessorTable internalGetFieldAccessorTable();
    Code:
       0: invokestatic  #4                  // Method org/apache/hadoop/hbase/protobuf/generated/FilterProtos.access$26500:()Lcom/google/protobuf/GeneratedMessage$FieldAccessorTable;
       3: ldc           #5                  // class org/apache/hadoop/hbase/protobuf/generated/FilterProtos$RowRange
       5: ldc           #6                  // class org/apache/hadoop/hbase/protobuf/generated/FilterProtos$RowRange$Builder
       7: invokevirtual #7                  // Method com/google/protobuf/GeneratedMessage$FieldAccessorTable.ensureFieldAccessorsInitialized:(Ljava/lang/Class;Ljava/lang/Class;)Lcom/google/protobuf/GeneratedMessage$FieldAccessorTable;
      10: areturn

  public org.apache.hadoop.hbase.protobuf.generated.FilterProtos$RowRange$Builder clear();
    Code:
       0: aload_0
       1: invokespecial #16                 // Method com/google/protobuf/GeneratedMessage$Builder.clear:()Lcom/google/protobuf/GeneratedMessage$Builder;
       4: pop
       5: aload_0
       6: getstatic     #9                  // Field com/google/protobuf/ByteString.EMPTY:Lcom/google/protobuf/ByteString;
       9: putfield      #10                 // Field startRow_:Lcom/google/protobuf/ByteString;
      12: aload_0
      13: aload_0
      14: getfield      #17                 // Field bitField0_:I
      17: bipush        -2
      19: iand
      20: putfield      #17                 // Field bitField0_:I
      23: aload_0
      24: iconst_0
      25: putfield      #18                 // Field startRowInclusive_:Z
      28: aload_0
      29: aload_0
      30: getfield      #17                 // Field bitField0_:I
      33: bipush        -3
      35: iand
      36: putfield      #17                 // Field bitField0_:I
      39: aload_0
      40: getstatic     #9                  // Field com/google/protobuf/ByteString.EMPTY:Lcom/google/protobuf/ByteString;
      43: putfield      #11                 // Field stopRow_:Lcom/google/protobuf/ByteString;
      46: aload_0
      47: aload_0
      48: getfield      #17                 // Field bitField0_:I
      51: bipush        -5
      53: iand
      54: putfield      #17                 // Field bitField0_:I
      57: aload_0
      58: iconst_0
      59: putfield      #19                 // Field stopRowInclusive_:Z
      62: aload_0
      63: aload_0
      64: getfield      #17                 // Field bitField0_:I
      67: bipush        -9
      69: iand
      70: putfield      #17                 // Field bitField0_:I
      73: aload_0
      74: areturn

  public org.apache.hadoop.hbase.protobuf.generated.FilterProtos$RowRange$Builder clone();
    Code:
       0: invokestatic  #2                  // Method create:()Lorg/apache/hadoop/hbase/protobuf/generated/FilterProtos$RowRange$Builder;
       3: aload_0
       4: invokevirtual #20                 // Method buildPartial:()Lorg/apache/hadoop/hbase/protobuf/generated/FilterProtos$RowRange;
       7: invokevirtual #21                 // Method mergeFrom:(Lorg/apache/hadoop/hbase/protobuf/generated/FilterProtos$RowRange;)Lorg/apache/hadoop/hbase/protobuf/generated/FilterProtos$RowRange$Builder;
      10: areturn

  public com.google.protobuf.Descriptors$Descriptor getDescriptorForType();
    Code:
       0: invokestatic  #3                  // Method org/apache/hadoop/hbase/protobuf/generated/FilterProtos.access$26400:()Lcom/google/protobuf/Descriptors$Descriptor;
       3: areturn

  public org.apache.hadoop.hbase.protobuf.generated.FilterProtos$RowRange getDefaultInstanceForType();
    Code:
       0: invokestatic  #22                 // Method org/apache/hadoop/hbase/protobuf/generated/FilterProtos$RowRange.getDefaultInstance:()Lorg/apache/hadoop/hbase/protobuf/generated/FilterProtos$RowRange;
       3: areturn

  public org.apache.hadoop.hbase.protobuf.generated.FilterProtos$RowRange build();
    Code:
       0: aload_0
       1: invokevirtual #20                 // Method buildPartial:()Lorg/apache/hadoop/hbase/protobuf/generated/FilterProtos$RowRange;
       4: astore_1
       5: aload_1
       6: invokevirtual #23                 // Method org/apache/hadoop/hbase/protobuf/generated/FilterProtos$RowRange.isInitialized:()Z
       9: ifne          17
      12: aload_1
      13: invokestatic  #24                 // Method newUninitializedMessageException:(Lcom/google/protobuf/Message;)Lcom/google/protobuf/UninitializedMessageException;
      16: athrow
      17: aload_1
      18: areturn

  public org.apache.hadoop.hbase.protobuf.generated.FilterProtos$RowRange buildPartial();
    Code:
       0: new           #5                  // class org/apache/hadoop/hbase/protobuf/generated/FilterProtos$RowRange
       3: dup
       4: aload_0
       5: aconst_null
       6: invokespecial #25                 // Method org/apache/hadoop/hbase/protobuf/generated/FilterProtos$RowRange."<init>":(Lcom/google/protobuf/GeneratedMessage$Builder;Lorg/apache/hadoop/hbase/protobuf/generated/FilterProtos$1;)V
       9: astore_1
      10: aload_0
      11: getfield      #17                 // Field bitField0_:I
      14: istore_2
      15: iconst_0
      16: istore_3
      17: iload_2
      18: iconst_1
      19: iand
      20: iconst_1
      21: if_icmpne     28
      24: iload_3
      25: iconst_1
      26: ior
      27: istore_3
      28: aload_1
      29: aload_0
      30: getfield      #10                 // Field startRow_:Lcom/google/protobuf/ByteString;
      33: invokestatic  #26                 // Method org/apache/hadoop/hbase/protobuf/generated/FilterProtos$RowRange.access$27102:(Lorg/apache/hadoop/hbase/protobuf/generated/FilterProtos$RowRange;Lcom/google/protobuf/ByteString;)Lcom/google/protobuf/ByteString;
      36: pop
      37: iload_2
      38: iconst_2
      39: iand
      40: iconst_2
      41: if_icmpne     48
      44: iload_3
      45: iconst_2
      46: ior
      47: istore_3
      48: aload_1
      49: aload_0
      50: getfield      #18                 // Field startRowInclusive_:Z
      53: invokestatic  #27                 // Method org/apache/hadoop/hbase/protobuf/generated/FilterProtos$RowRange.access$27202:(Lorg/apache/hadoop/hbase/protobuf/generated/FilterProtos$RowRange;Z)Z
      56: pop
      57: iload_2
      58: iconst_4
      59: iand
      60: iconst_4
      61: if_icmpne     68
      64: iload_3
      65: iconst_4
      66: ior
      67: istore_3
      68: aload_1
      69: aload_0
      70: getfield      #11                 // Field stopRow_:Lcom/google/protobuf/ByteString;
      73: invokestatic  #28                 // Method org/apache/hadoop/hbase/protobuf/generated/FilterProtos$RowRange.access$27302:(Lorg/apache/hadoop/hbase/protobuf/generated/FilterProtos$RowRange;Lcom/google/protobuf/ByteString;)Lcom/google/protobuf/ByteString;
      76: pop
      77: iload_2
      78: bipush        8
      80: iand
      81: bipush        8
      83: if_icmpne     91
      86: iload_3
      87: bipush        8
      89: ior
      90: istore_3
      91: aload_1
      92: aload_0
      93: getfield      #19                 // Field stopRowInclusive_:Z
      96: invokestatic  #29                 // Method org/apache/hadoop/hbase/protobuf/generated/FilterProtos$RowRange.access$27402:(Lorg/apache/hadoop/hbase/protobuf/generated/FilterProtos$RowRange;Z)Z
      99: pop
     100: aload_1
     101: iload_3
     102: invokestatic  #30                 // Method org/apache/hadoop/hbase/protobuf/generated/FilterProtos$RowRange.access$27502:(Lorg/apache/hadoop/hbase/protobuf/generated/FilterProtos$RowRange;I)I
     105: pop
     106: aload_0
     107: invokevirtual #31                 // Method onBuilt:()V
     110: aload_1
     111: areturn

  public org.apache.hadoop.hbase.protobuf.generated.FilterProtos$RowRange$Builder mergeFrom(com.google.protobuf.Message);
    Code:
       0: aload_1
       1: instanceof    #5                  // class org/apache/hadoop/hbase/protobuf/generated/FilterProtos$RowRange
       4: ifeq          16
       7: aload_0
       8: aload_1
       9: checkcast     #5                  // class org/apache/hadoop/hbase/protobuf/generated/FilterProtos$RowRange
      12: invokevirtual #21                 // Method mergeFrom:(Lorg/apache/hadoop/hbase/protobuf/generated/FilterProtos$RowRange;)Lorg/apache/hadoop/hbase/protobuf/generated/FilterProtos$RowRange$Builder;
      15: areturn
      16: aload_0
      17: aload_1
      18: invokespecial #32                 // Method com/google/protobuf/GeneratedMessage$Builder.mergeFrom:(Lcom/google/protobuf/Message;)Lcom/google/protobuf/AbstractMessage$Builder;
      21: pop
      22: aload_0
      23: areturn

  public org.apache.hadoop.hbase.protobuf.generated.FilterProtos$RowRange$Builder mergeFrom(org.apache.hadoop.hbase.protobuf.generated.FilterProtos$RowRange);
    Code:
       0: aload_1
       1: invokestatic  #22                 // Method org/apache/hadoop/hbase/protobuf/generated/FilterProtos$RowRange.getDefaultInstance:()Lorg/apache/hadoop/hbase/protobuf/generated/FilterProtos$RowRange;
       4: if_acmpne     9
       7: aload_0
       8: areturn
       9: aload_1
      10: invokevirtual #33                 // Method org/apache/hadoop/hbase/protobuf/generated/FilterProtos$RowRange.hasStartRow:()Z
      13: ifeq          25
      16: aload_0
      17: aload_1
      18: invokevirtual #34                 // Method org/apache/hadoop/hbase/protobuf/generated/FilterProtos$RowRange.getStartRow:()Lcom/google/protobuf/ByteString;
      21: invokevirtual #35                 // Method setStartRow:(Lcom/google/protobuf/ByteString;)Lorg/apache/hadoop/hbase/protobuf/generated/FilterProtos$RowRange$Builder;
      24: pop
      25: aload_1
      26: invokevirtual #36                 // Method org/apache/hadoop/hbase/protobuf/generated/FilterProtos$RowRange.hasStartRowInclusive:()Z
      29: ifeq          41
      32: aload_0
      33: aload_1
      34: invokevirtual #37                 // Method org/apache/hadoop/hbase/protobuf/generated/FilterProtos$RowRange.getStartRowInclusive:()Z
      37: invokevirtual #38                 // Method setStartRowInclusive:(Z)Lorg/apache/hadoop/hbase/protobuf/generated/FilterProtos$RowRange$Builder;
      40: pop
      41: aload_1
      42: invokevirtual #39                 // Method org/apache/hadoop/hbase/protobuf/generated/FilterProtos$RowRange.hasStopRow:()Z
      45: ifeq          57
      48: aload_0
      49: aload_1
      50: invokevirtual #40                 // Method org/apache/hadoop/hbase/protobuf/generated/FilterProtos$RowRange.getStopRow:()Lcom/google/protobuf/ByteString;
      53: invokevirtual #41                 // Method setStopRow:(Lcom/google/protobuf/ByteString;)Lorg/apache/hadoop/hbase/protobuf/generated/FilterProtos$RowRange$Builder;
      56: pop
      57: aload_1
      58: invokevirtual #42                 // Method org/apache/hadoop/hbase/protobuf/generated/FilterProtos$RowRange.hasStopRowInclusive:()Z
      61: ifeq          73
      64: aload_0
      65: aload_1
      66: invokevirtual #43                 // Method org/apache/hadoop/hbase/protobuf/generated/FilterProtos$RowRange.getStopRowInclusive:()Z
      69: invokevirtual #44                 // Method setStopRowInclusive:(Z)Lorg/apache/hadoop/hbase/protobuf/generated/FilterProtos$RowRange$Builder;
      72: pop
      73: aload_0
      74: aload_1
      75: invokevirtual #45                 // Method org/apache/hadoop/hbase/protobuf/generated/FilterProtos$RowRange.getUnknownFields:()Lcom/google/protobuf/UnknownFieldSet;
      78: invokevirtual #46                 // Method mergeUnknownFields:(Lcom/google/protobuf/UnknownFieldSet;)Lcom/google/protobuf/GeneratedMessage$Builder;
      81: pop
      82: aload_0
      83: areturn

  public final boolean isInitialized();
    Code:
       0: iconst_1
       1: ireturn

  public org.apache.hadoop.hbase.protobuf.generated.FilterProtos$RowRange$Builder mergeFrom(com.google.protobuf.CodedInputStream, com.google.protobuf.ExtensionRegistryLite) throws java.io.IOException;
    Code:
       0: aconst_null
       1: astore_3
       2: getstatic     #47                 // Field org/apache/hadoop/hbase/protobuf/generated/FilterProtos$RowRange.PARSER:Lcom/google/protobuf/Parser;
       5: aload_1
       6: aload_2
       7: invokeinterface #48,  3           // InterfaceMethod com/google/protobuf/Parser.parsePartialFrom:(Lcom/google/protobuf/CodedInputStream;Lcom/google/protobuf/ExtensionRegistryLite;)Ljava/lang/Object;
      12: checkcast     #5                  // class org/apache/hadoop/hbase/protobuf/generated/FilterProtos$RowRange
      15: astore_3
      16: aload_3
      17: ifnull        58
      20: aload_0
      21: aload_3
      22: invokevirtual #21                 // Method mergeFrom:(Lorg/apache/hadoop/hbase/protobuf/generated/FilterProtos$RowRange;)Lorg/apache/hadoop/hbase/protobuf/generated/FilterProtos$RowRange$Builder;
      25: pop
      26: goto          58
      29: astore        4
      31: aload         4
      33: invokevirtual #50                 // Method com/google/protobuf/InvalidProtocolBufferException.getUnfinishedMessage:()Lcom/google/protobuf/MessageLite;
      36: checkcast     #5                  // class org/apache/hadoop/hbase/protobuf/generated/FilterProtos$RowRange
      39: astore_3
      40: aload         4
      42: athrow
      43: astore        5
      45: aload_3
      46: ifnull        55
      49: aload_0
      50: aload_3
      51: invokevirtual #21                 // Method mergeFrom:(Lorg/apache/hadoop/hbase/protobuf/generated/FilterProtos$RowRange;)Lorg/apache/hadoop/hbase/protobuf/generated/FilterProtos$RowRange$Builder;
      54: pop
      55: aload         5
      57: athrow
      58: aload_0
      59: areturn
    Exception table:
       from    to  target type
           2    16    29   Class com/google/protobuf/InvalidProtocolBufferException
           2    16    43   any
          29    45    43   any

  public boolean hasStartRow();
    Code:
       0: aload_0
       1: getfield      #17                 // Field bitField0_:I
       4: iconst_1
       5: iand
       6: iconst_1
       7: if_icmpne     14
      10: iconst_1
      11: goto          15
      14: iconst_0
      15: ireturn

  public com.google.protobuf.ByteString getStartRow();
    Code:
       0: aload_0
       1: getfield      #10                 // Field startRow_:Lcom/google/protobuf/ByteString;
       4: areturn

  public org.apache.hadoop.hbase.protobuf.generated.FilterProtos$RowRange$Builder setStartRow(com.google.protobuf.ByteString);
    Code:
       0: aload_1
       1: ifnonnull     12
       4: new           #51                 // class java/lang/NullPointerException
       7: dup
       8: invokespecial #52                 // Method java/lang/NullPointerException."<init>":()V
      11: athrow
      12: aload_0
      13: dup
      14: getfield      #17                 // Field bitField0_:I
      17: iconst_1
      18: ior
      19: putfield      #17                 // Field bitField0_:I
      22: aload_0
      23: aload_1
      24: putfield      #10                 // Field startRow_:Lcom/google/protobuf/ByteString;
      27: aload_0
      28: invokevirtual #53                 // Method onChanged:()V
      31: aload_0
      32: areturn

  public org.apache.hadoop.hbase.protobuf.generated.FilterProtos$RowRange$Builder clearStartRow();
    Code:
       0: aload_0
       1: aload_0
       2: getfield      #17                 // Field bitField0_:I
       5: bipush        -2
       7: iand
       8: putfield      #17                 // Field bitField0_:I
      11: aload_0
      12: invokestatic  #22                 // Method org/apache/hadoop/hbase/protobuf/generated/FilterProtos$RowRange.getDefaultInstance:()Lorg/apache/hadoop/hbase/protobuf/generated/FilterProtos$RowRange;
      15: invokevirtual #34                 // Method org/apache/hadoop/hbase/protobuf/generated/FilterProtos$RowRange.getStartRow:()Lcom/google/protobuf/ByteString;
      18: putfield      #10                 // Field startRow_:Lcom/google/protobuf/ByteString;
      21: aload_0
      22: invokevirtual #53                 // Method onChanged:()V
      25: aload_0
      26: areturn

  public boolean hasStartRowInclusive();
    Code:
       0: aload_0
       1: getfield      #17                 // Field bitField0_:I
       4: iconst_2
       5: iand
       6: iconst_2
       7: if_icmpne     14
      10: iconst_1
      11: goto          15
      14: iconst_0
      15: ireturn

  public boolean getStartRowInclusive();
    Code:
       0: aload_0
       1: getfield      #18                 // Field startRowInclusive_:Z
       4: ireturn

  public org.apache.hadoop.hbase.protobuf.generated.FilterProtos$RowRange$Builder setStartRowInclusive(boolean);
    Code:
       0: aload_0
       1: dup
       2: getfield      #17                 // Field bitField0_:I
       5: iconst_2
       6: ior
       7: putfield      #17                 // Field bitField0_:I
      10: aload_0
      11: iload_1
      12: putfield      #18                 // Field startRowInclusive_:Z
      15: aload_0
      16: invokevirtual #53                 // Method onChanged:()V
      19: aload_0
      20: areturn

  public org.apache.hadoop.hbase.protobuf.generated.FilterProtos$RowRange$Builder clearStartRowInclusive();
    Code:
       0: aload_0
       1: aload_0
       2: getfield      #17                 // Field bitField0_:I
       5: bipush        -3
       7: iand
       8: putfield      #17                 // Field bitField0_:I
      11: aload_0
      12: iconst_0
      13: putfield      #18                 // Field startRowInclusive_:Z
      16: aload_0
      17: invokevirtual #53                 // Method onChanged:()V
      20: aload_0
      21: areturn

  public boolean hasStopRow();
    Code:
       0: aload_0
       1: getfield      #17                 // Field bitField0_:I
       4: iconst_4
       5: iand
       6: iconst_4
       7: if_icmpne     14
      10: iconst_1
      11: goto          15
      14: iconst_0
      15: ireturn

  public com.google.protobuf.ByteString getStopRow();
    Code:
       0: aload_0
       1: getfield      #11                 // Field stopRow_:Lcom/google/protobuf/ByteString;
       4: areturn

  public org.apache.hadoop.hbase.protobuf.generated.FilterProtos$RowRange$Builder setStopRow(com.google.protobuf.ByteString);
    Code:
       0: aload_1
       1: ifnonnull     12
       4: new           #51                 // class java/lang/NullPointerException
       7: dup
       8: invokespecial #52                 // Method java/lang/NullPointerException."<init>":()V
      11: athrow
      12: aload_0
      13: dup
      14: getfield      #17                 // Field bitField0_:I
      17: iconst_4
      18: ior
      19: putfield      #17                 // Field bitField0_:I
      22: aload_0
      23: aload_1
      24: putfield      #11                 // Field stopRow_:Lcom/google/protobuf/ByteString;
      27: aload_0
      28: invokevirtual #53                 // Method onChanged:()V
      31: aload_0
      32: areturn

  public org.apache.hadoop.hbase.protobuf.generated.FilterProtos$RowRange$Builder clearStopRow();
    Code:
       0: aload_0
       1: aload_0
       2: getfield      #17                 // Field bitField0_:I
       5: bipush        -5
       7: iand
       8: putfield      #17                 // Field bitField0_:I
      11: aload_0
      12: invokestatic  #22                 // Method org/apache/hadoop/hbase/protobuf/generated/FilterProtos$RowRange.getDefaultInstance:()Lorg/apache/hadoop/hbase/protobuf/generated/FilterProtos$RowRange;
      15: invokevirtual #40                 // Method org/apache/hadoop/hbase/protobuf/generated/FilterProtos$RowRange.getStopRow:()Lcom/google/protobuf/ByteString;
      18: putfield      #11                 // Field stopRow_:Lcom/google/protobuf/ByteString;
      21: aload_0
      22: invokevirtual #53                 // Method onChanged:()V
      25: aload_0
      26: areturn

  public boolean hasStopRowInclusive();
    Code:
       0: aload_0
       1: getfield      #17                 // Field bitField0_:I
       4: bipush        8
       6: iand
       7: bipush        8
       9: if_icmpne     16
      12: iconst_1
      13: goto          17
      16: iconst_0
      17: ireturn

  public boolean getStopRowInclusive();
    Code:
       0: aload_0
       1: getfield      #19                 // Field stopRowInclusive_:Z
       4: ireturn

  public org.apache.hadoop.hbase.protobuf.generated.FilterProtos$RowRange$Builder setStopRowInclusive(boolean);
    Code:
       0: aload_0
       1: dup
       2: getfield      #17                 // Field bitField0_:I
       5: bipush        8
       7: ior
       8: putfield      #17                 // Field bitField0_:I
      11: aload_0
      12: iload_1
      13: putfield      #19                 // Field stopRowInclusive_:Z
      16: aload_0
      17: invokevirtual #53                 // Method onChanged:()V
      20: aload_0
      21: areturn

  public org.apache.hadoop.hbase.protobuf.generated.FilterProtos$RowRange$Builder clearStopRowInclusive();
    Code:
       0: aload_0
       1: aload_0
       2: getfield      #17                 // Field bitField0_:I
       5: bipush        -9
       7: iand
       8: putfield      #17                 // Field bitField0_:I
      11: aload_0
      12: iconst_0
      13: putfield      #19                 // Field stopRowInclusive_:Z
      16: aload_0
      17: invokevirtual #53                 // Method onChanged:()V
      20: aload_0
      21: areturn

  public com.google.protobuf.GeneratedMessage$Builder clear();
    Code:
       0: aload_0
       1: invokevirtual #54                 // Method clear:()Lorg/apache/hadoop/hbase/protobuf/generated/FilterProtos$RowRange$Builder;
       4: areturn

  public com.google.protobuf.GeneratedMessage$Builder clone();
    Code:
       0: aload_0
       1: invokevirtual #55                 // Method clone:()Lorg/apache/hadoop/hbase/protobuf/generated/FilterProtos$RowRange$Builder;
       4: areturn

  public com.google.protobuf.AbstractMessage$Builder mergeFrom(com.google.protobuf.CodedInputStream, com.google.protobuf.ExtensionRegistryLite) throws java.io.IOException;
    Code:
       0: aload_0
       1: aload_1
       2: aload_2
       3: invokevirtual #56                 // Method mergeFrom:(Lcom/google/protobuf/CodedInputStream;Lcom/google/protobuf/ExtensionRegistryLite;)Lorg/apache/hadoop/hbase/protobuf/generated/FilterProtos$RowRange$Builder;
       6: areturn

  public com.google.protobuf.AbstractMessage$Builder mergeFrom(com.google.protobuf.Message);
    Code:
       0: aload_0
       1: aload_1
       2: invokevirtual #57                 // Method mergeFrom:(Lcom/google/protobuf/Message;)Lorg/apache/hadoop/hbase/protobuf/generated/FilterProtos$RowRange$Builder;
       5: areturn

  public com.google.protobuf.AbstractMessage$Builder clear();
    Code:
       0: aload_0
       1: invokevirtual #54                 // Method clear:()Lorg/apache/hadoop/hbase/protobuf/generated/FilterProtos$RowRange$Builder;
       4: areturn

  public com.google.protobuf.AbstractMessage$Builder clone();
    Code:
       0: aload_0
       1: invokevirtual #55                 // Method clone:()Lorg/apache/hadoop/hbase/protobuf/generated/FilterProtos$RowRange$Builder;
       4: areturn

  public com.google.protobuf.Message$Builder mergeFrom(com.google.protobuf.CodedInputStream, com.google.protobuf.ExtensionRegistryLite) throws java.io.IOException;
    Code:
       0: aload_0
       1: aload_1
       2: aload_2
       3: invokevirtual #56                 // Method mergeFrom:(Lcom/google/protobuf/CodedInputStream;Lcom/google/protobuf/ExtensionRegistryLite;)Lorg/apache/hadoop/hbase/protobuf/generated/FilterProtos$RowRange$Builder;
       6: areturn

  public com.google.protobuf.Message$Builder clone();
    Code:
       0: aload_0
       1: invokevirtual #55                 // Method clone:()Lorg/apache/hadoop/hbase/protobuf/generated/FilterProtos$RowRange$Builder;
       4: areturn

  public com.google.protobuf.Message buildPartial();
    Code:
       0: aload_0
       1: invokevirtual #20                 // Method buildPartial:()Lorg/apache/hadoop/hbase/protobuf/generated/FilterProtos$RowRange;
       4: areturn

  public com.google.protobuf.Message build();
    Code:
       0: aload_0
       1: invokevirtual #58                 // Method build:()Lorg/apache/hadoop/hbase/protobuf/generated/FilterProtos$RowRange;
       4: areturn

  public com.google.protobuf.Message$Builder mergeFrom(com.google.protobuf.Message);
    Code:
       0: aload_0
       1: aload_1
       2: invokevirtual #57                 // Method mergeFrom:(Lcom/google/protobuf/Message;)Lorg/apache/hadoop/hbase/protobuf/generated/FilterProtos$RowRange$Builder;
       5: areturn

  public com.google.protobuf.Message$Builder clear();
    Code:
       0: aload_0
       1: invokevirtual #54                 // Method clear:()Lorg/apache/hadoop/hbase/protobuf/generated/FilterProtos$RowRange$Builder;
       4: areturn

  public com.google.protobuf.MessageLite$Builder mergeFrom(com.google.protobuf.CodedInputStream, com.google.protobuf.ExtensionRegistryLite) throws java.io.IOException;
    Code:
       0: aload_0
       1: aload_1
       2: aload_2
       3: invokevirtual #56                 // Method mergeFrom:(Lcom/google/protobuf/CodedInputStream;Lcom/google/protobuf/ExtensionRegistryLite;)Lorg/apache/hadoop/hbase/protobuf/generated/FilterProtos$RowRange$Builder;
       6: areturn

  public com.google.protobuf.MessageLite$Builder clone();
    Code:
       0: aload_0
       1: invokevirtual #55                 // Method clone:()Lorg/apache/hadoop/hbase/protobuf/generated/FilterProtos$RowRange$Builder;
       4: areturn

  public com.google.protobuf.MessageLite buildPartial();
    Code:
       0: aload_0
       1: invokevirtual #20                 // Method buildPartial:()Lorg/apache/hadoop/hbase/protobuf/generated/FilterProtos$RowRange;
       4: areturn

  public com.google.protobuf.MessageLite build();
    Code:
       0: aload_0
       1: invokevirtual #58                 // Method build:()Lorg/apache/hadoop/hbase/protobuf/generated/FilterProtos$RowRange;
       4: areturn

  public com.google.protobuf.MessageLite$Builder clear();
    Code:
       0: aload_0
       1: invokevirtual #54                 // Method clear:()Lorg/apache/hadoop/hbase/protobuf/generated/FilterProtos$RowRange$Builder;
       4: areturn

  public com.google.protobuf.MessageLite getDefaultInstanceForType();
    Code:
       0: aload_0
       1: invokevirtual #59                 // Method getDefaultInstanceForType:()Lorg/apache/hadoop/hbase/protobuf/generated/FilterProtos$RowRange;
       4: areturn

  public com.google.protobuf.Message getDefaultInstanceForType();
    Code:
       0: aload_0
       1: invokevirtual #59                 // Method getDefaultInstanceForType:()Lorg/apache/hadoop/hbase/protobuf/generated/FilterProtos$RowRange;
       4: areturn

  public com.google.protobuf.AbstractMessageLite$Builder mergeFrom(com.google.protobuf.CodedInputStream, com.google.protobuf.ExtensionRegistryLite) throws java.io.IOException;
    Code:
       0: aload_0
       1: aload_1
       2: aload_2
       3: invokevirtual #56                 // Method mergeFrom:(Lcom/google/protobuf/CodedInputStream;Lcom/google/protobuf/ExtensionRegistryLite;)Lorg/apache/hadoop/hbase/protobuf/generated/FilterProtos$RowRange$Builder;
       6: areturn

  public com.google.protobuf.AbstractMessageLite$Builder clone();
    Code:
       0: aload_0
       1: invokevirtual #55                 // Method clone:()Lorg/apache/hadoop/hbase/protobuf/generated/FilterProtos$RowRange$Builder;
       4: areturn

  public java.lang.Object clone() throws java.lang.CloneNotSupportedException;
    Code:
       0: aload_0
       1: invokevirtual #55                 // Method clone:()Lorg/apache/hadoop/hbase/protobuf/generated/FilterProtos$RowRange$Builder;
       4: areturn

  static org.apache.hadoop.hbase.protobuf.generated.FilterProtos$RowRange$Builder access$26700();
    Code:
       0: invokestatic  #2                  // Method create:()Lorg/apache/hadoop/hbase/protobuf/generated/FilterProtos$RowRange$Builder;
       3: areturn

  org.apache.hadoop.hbase.protobuf.generated.FilterProtos$RowRange$Builder(com.google.protobuf.GeneratedMessage$BuilderParent, org.apache.hadoop.hbase.protobuf.generated.FilterProtos$1);
    Code:
       0: aload_0
       1: aload_1
       2: invokespecial #1                  // Method "<init>":(Lcom/google/protobuf/GeneratedMessage$BuilderParent;)V
       5: return
}
