Compiled from "FixedFileTrailer.java"
public class org.apache.hadoop.hbase.io.hfile.FixedFileTrailer {
  org.apache.hadoop.hbase.io.hfile.FixedFileTrailer(int, int);
    Code:
       0: aload_0
       1: invokespecial #3                  // Method java/lang/Object."<init>":()V
       4: aload_0
       5: getstatic     #4                  // Field org/apache/hadoop/hbase/io/compress/Compression$Algorithm.NONE:Lorg/apache/hadoop/hbase/io/compress/Compression$Algorithm;
       8: putfield      #5                  // Field compressionCodec:Lorg/apache/hadoop/hbase/io/compress/Compression$Algorithm;
      11: aload_0
      12: invokestatic  #6                  // InterfaceMethod org/apache/hadoop/hbase/CellComparator.getInstance:()Lorg/apache/hadoop/hbase/CellComparator;
      15: invokevirtual #7                  // Method java/lang/Object.getClass:()Ljava/lang/Class;
      18: invokevirtual #8                  // Method java/lang/Class.getName:()Ljava/lang/String;
      21: putfield      #9                  // Field comparatorClassName:Ljava/lang/String;
      24: aload_0
      25: iload_1
      26: putfield      #10                 // Field majorVersion:I
      29: aload_0
      30: iload_2
      31: putfield      #11                 // Field minorVersion:I
      34: iload_1
      35: invokestatic  #12                 // Method org/apache/hadoop/hbase/io/hfile/HFile.checkFormatVersion:(I)V
      38: return

  static int getTrailerSize(int);
    Code:
       0: getstatic     #16                 // Field TRAILER_SIZE:[I
       3: iload_0
       4: iaload
       5: ireturn

  public int getTrailerSize();
    Code:
       0: aload_0
       1: getfield      #10                 // Field majorVersion:I
       4: invokestatic  #14                 // Method getTrailerSize:(I)I
       7: ireturn

  void serialize(java.io.DataOutputStream) throws java.io.IOException;
    Code:
       0: aload_0
       1: getfield      #10                 // Field majorVersion:I
       4: invokestatic  #12                 // Method org/apache/hadoop/hbase/io/hfile/HFile.checkFormatVersion:(I)V
       7: new           #17                 // class java/io/ByteArrayOutputStream
      10: dup
      11: invokespecial #18                 // Method java/io/ByteArrayOutputStream."<init>":()V
      14: astore_2
      15: new           #19                 // class java/io/DataOutputStream
      18: dup
      19: aload_2
      20: invokespecial #20                 // Method java/io/DataOutputStream."<init>":(Ljava/io/OutputStream;)V
      23: astore_3
      24: getstatic     #21                 // Field org/apache/hadoop/hbase/io/hfile/BlockType.TRAILER:Lorg/apache/hadoop/hbase/io/hfile/BlockType;
      27: aload_3
      28: invokevirtual #22                 // Method org/apache/hadoop/hbase/io/hfile/BlockType.write:(Ljava/io/DataOutput;)V
      31: aload_0
      32: aload_3
      33: invokevirtual #23                 // Method serializeAsPB:(Ljava/io/DataOutputStream;)V
      36: aload_3
      37: aload_0
      38: getfield      #10                 // Field majorVersion:I
      41: aload_0
      42: getfield      #11                 // Field minorVersion:I
      45: invokestatic  #24                 // Method materializeVersion:(II)I
      48: invokevirtual #25                 // Method java/io/DataOutputStream.writeInt:(I)V
      51: aload_2
      52: aload_1
      53: invokevirtual #26                 // Method java/io/ByteArrayOutputStream.writeTo:(Ljava/io/OutputStream;)V
      56: return

  org.apache.hadoop.hbase.shaded.protobuf.generated.HFileProtos$FileTrailerProto toProtobuf();
    Code:
       0: invokestatic  #27                 // Method org/apache/hadoop/hbase/shaded/protobuf/generated/HFileProtos$FileTrailerProto.newBuilder:()Lorg/apache/hadoop/hbase/shaded/protobuf/generated/HFileProtos$FileTrailerProto$Builder;
       3: aload_0
       4: getfield      #28                 // Field fileInfoOffset:J
       7: invokevirtual #29                 // Method org/apache/hadoop/hbase/shaded/protobuf/generated/HFileProtos$FileTrailerProto$Builder.setFileInfoOffset:(J)Lorg/apache/hadoop/hbase/shaded/protobuf/generated/HFileProtos$FileTrailerProto$Builder;
      10: aload_0
      11: getfield      #30                 // Field loadOnOpenDataOffset:J
      14: invokevirtual #31                 // Method org/apache/hadoop/hbase/shaded/protobuf/generated/HFileProtos$FileTrailerProto$Builder.setLoadOnOpenDataOffset:(J)Lorg/apache/hadoop/hbase/shaded/protobuf/generated/HFileProtos$FileTrailerProto$Builder;
      17: aload_0
      18: getfield      #32                 // Field uncompressedDataIndexSize:J
      21: invokevirtual #33                 // Method org/apache/hadoop/hbase/shaded/protobuf/generated/HFileProtos$FileTrailerProto$Builder.setUncompressedDataIndexSize:(J)Lorg/apache/hadoop/hbase/shaded/protobuf/generated/HFileProtos$FileTrailerProto$Builder;
      24: aload_0
      25: getfield      #34                 // Field totalUncompressedBytes:J
      28: invokevirtual #35                 // Method org/apache/hadoop/hbase/shaded/protobuf/generated/HFileProtos$FileTrailerProto$Builder.setTotalUncompressedBytes:(J)Lorg/apache/hadoop/hbase/shaded/protobuf/generated/HFileProtos$FileTrailerProto$Builder;
      31: aload_0
      32: getfield      #36                 // Field dataIndexCount:I
      35: invokevirtual #37                 // Method org/apache/hadoop/hbase/shaded/protobuf/generated/HFileProtos$FileTrailerProto$Builder.setDataIndexCount:(I)Lorg/apache/hadoop/hbase/shaded/protobuf/generated/HFileProtos$FileTrailerProto$Builder;
      38: aload_0
      39: getfield      #38                 // Field metaIndexCount:I
      42: invokevirtual #39                 // Method org/apache/hadoop/hbase/shaded/protobuf/generated/HFileProtos$FileTrailerProto$Builder.setMetaIndexCount:(I)Lorg/apache/hadoop/hbase/shaded/protobuf/generated/HFileProtos$FileTrailerProto$Builder;
      45: aload_0
      46: getfield      #40                 // Field entryCount:J
      49: invokevirtual #41                 // Method org/apache/hadoop/hbase/shaded/protobuf/generated/HFileProtos$FileTrailerProto$Builder.setEntryCount:(J)Lorg/apache/hadoop/hbase/shaded/protobuf/generated/HFileProtos$FileTrailerProto$Builder;
      52: aload_0
      53: getfield      #42                 // Field numDataIndexLevels:I
      56: invokevirtual #43                 // Method org/apache/hadoop/hbase/shaded/protobuf/generated/HFileProtos$FileTrailerProto$Builder.setNumDataIndexLevels:(I)Lorg/apache/hadoop/hbase/shaded/protobuf/generated/HFileProtos$FileTrailerProto$Builder;
      59: aload_0
      60: getfield      #44                 // Field firstDataBlockOffset:J
      63: invokevirtual #45                 // Method org/apache/hadoop/hbase/shaded/protobuf/generated/HFileProtos$FileTrailerProto$Builder.setFirstDataBlockOffset:(J)Lorg/apache/hadoop/hbase/shaded/protobuf/generated/HFileProtos$FileTrailerProto$Builder;
      66: aload_0
      67: getfield      #46                 // Field lastDataBlockOffset:J
      70: invokevirtual #47                 // Method org/apache/hadoop/hbase/shaded/protobuf/generated/HFileProtos$FileTrailerProto$Builder.setLastDataBlockOffset:(J)Lorg/apache/hadoop/hbase/shaded/protobuf/generated/HFileProtos$FileTrailerProto$Builder;
      73: aload_0
      74: aload_0
      75: getfield      #9                  // Field comparatorClassName:Ljava/lang/String;
      78: invokespecial #48                 // Method getHBase1CompatibleName:(Ljava/lang/String;)Ljava/lang/String;
      81: invokevirtual #49                 // Method org/apache/hadoop/hbase/shaded/protobuf/generated/HFileProtos$FileTrailerProto$Builder.setComparatorClassName:(Ljava/lang/String;)Lorg/apache/hadoop/hbase/shaded/protobuf/generated/HFileProtos$FileTrailerProto$Builder;
      84: aload_0
      85: getfield      #5                  // Field compressionCodec:Lorg/apache/hadoop/hbase/io/compress/Compression$Algorithm;
      88: invokevirtual #50                 // Method org/apache/hadoop/hbase/io/compress/Compression$Algorithm.ordinal:()I
      91: invokevirtual #51                 // Method org/apache/hadoop/hbase/shaded/protobuf/generated/HFileProtos$FileTrailerProto$Builder.setCompressionCodec:(I)Lorg/apache/hadoop/hbase/shaded/protobuf/generated/HFileProtos$FileTrailerProto$Builder;
      94: astore_1
      95: aload_0
      96: getfield      #52                 // Field encryptionKey:[B
      99: ifnull        114
     102: aload_1
     103: aload_0
     104: getfield      #52                 // Field encryptionKey:[B
     107: invokestatic  #53                 // Method org/apache/hbase/thirdparty/com/google/protobuf/UnsafeByteOperations.unsafeWrap:([B)Lorg/apache/hbase/thirdparty/com/google/protobuf/ByteString;
     110: invokevirtual #54                 // Method org/apache/hadoop/hbase/shaded/protobuf/generated/HFileProtos$FileTrailerProto$Builder.setEncryptionKey:(Lorg/apache/hbase/thirdparty/com/google/protobuf/ByteString;)Lorg/apache/hadoop/hbase/shaded/protobuf/generated/HFileProtos$FileTrailerProto$Builder;
     113: pop
     114: aload_1
     115: invokevirtual #55                 // Method org/apache/hadoop/hbase/shaded/protobuf/generated/HFileProtos$FileTrailerProto$Builder.build:()Lorg/apache/hadoop/hbase/shaded/protobuf/generated/HFileProtos$FileTrailerProto;
     118: areturn

  void serializeAsPB(java.io.DataOutputStream) throws java.io.IOException;
    Code:
       0: new           #17                 // class java/io/ByteArrayOutputStream
       3: dup
       4: invokespecial #18                 // Method java/io/ByteArrayOutputStream."<init>":()V
       7: astore_2
       8: aload_0
       9: invokevirtual #56                 // Method toProtobuf:()Lorg/apache/hadoop/hbase/shaded/protobuf/generated/HFileProtos$FileTrailerProto;
      12: aload_2
      13: invokevirtual #57                 // Method org/apache/hadoop/hbase/shaded/protobuf/generated/HFileProtos$FileTrailerProto.writeDelimitedTo:(Ljava/io/OutputStream;)V
      16: aload_2
      17: aload_1
      18: invokevirtual #26                 // Method java/io/ByteArrayOutputStream.writeTo:(Ljava/io/OutputStream;)V
      21: aload_0
      22: invokevirtual #58                 // Method getTrailerSize:()I
      25: bipush        12
      27: isub
      28: aload_2
      29: invokevirtual #60                 // Method java/io/ByteArrayOutputStream.size:()I
      32: isub
      33: istore_3
      34: iload_3
      35: ifge          48
      38: new           #61                 // class java/io/IOException
      41: dup
      42: ldc           #62                 // String Pbuf encoding size exceeded fixed trailer size limit
      44: invokespecial #63                 // Method java/io/IOException."<init>":(Ljava/lang/String;)V
      47: athrow
      48: iconst_0
      49: istore        4
      51: iload         4
      53: iload_3
      54: if_icmpge     68
      57: aload_1
      58: iconst_0
      59: invokevirtual #64                 // Method java/io/DataOutputStream.write:(I)V
      62: iinc          4, 1
      65: goto          51
      68: return

  void deserialize(java.io.DataInputStream) throws java.io.IOException;
    Code:
       0: aload_0
       1: getfield      #10                 // Field majorVersion:I
       4: invokestatic  #12                 // Method org/apache/hadoop/hbase/io/hfile/HFile.checkFormatVersion:(I)V
       7: getstatic     #21                 // Field org/apache/hadoop/hbase/io/hfile/BlockType.TRAILER:Lorg/apache/hadoop/hbase/io/hfile/BlockType;
      10: aload_1
      11: invokevirtual #65                 // Method org/apache/hadoop/hbase/io/hfile/BlockType.readAndCheck:(Ljava/io/DataInputStream;)V
      14: aload_0
      15: getfield      #10                 // Field majorVersion:I
      18: iconst_2
      19: if_icmpgt     38
      22: aload_0
      23: getfield      #10                 // Field majorVersion:I
      26: iconst_2
      27: if_icmpne     46
      30: aload_0
      31: getfield      #11                 // Field minorVersion:I
      34: iconst_2
      35: if_icmplt     46
      38: aload_0
      39: aload_1
      40: invokevirtual #67                 // Method deserializeFromPB:(Ljava/io/DataInputStream;)V
      43: goto          51
      46: aload_0
      47: aload_1
      48: invokevirtual #68                 // Method deserializeFromWritable:(Ljava/io/DataInput;)V
      51: aload_1
      52: invokevirtual #69                 // Method java/io/DataInputStream.readInt:()I
      55: istore_2
      56: aload_0
      57: iload_2
      58: invokestatic  #70                 // Method extractMajorVersion:(I)I
      61: invokevirtual #71                 // Method expectMajorVersion:(I)V
      64: aload_0
      65: iload_2
      66: invokestatic  #72                 // Method extractMinorVersion:(I)I
      69: invokevirtual #73                 // Method expectMinorVersion:(I)V
      72: return

  void deserializeFromPB(java.io.DataInputStream) throws java.io.IOException;
    Code:
       0: aload_1
       1: invokevirtual #74                 // Method java/io/DataInputStream.available:()I
       4: istore_2
       5: getstatic     #75                 // Field org/apache/hadoop/hbase/shaded/protobuf/generated/HFileProtos$FileTrailerProto.PARSER:Lorg/apache/hbase/thirdparty/com/google/protobuf/Parser;
       8: aload_1
       9: invokeinterface #76,  2           // InterfaceMethod org/apache/hbase/thirdparty/com/google/protobuf/Parser.parseDelimitedFrom:(Ljava/io/InputStream;)Ljava/lang/Object;
      14: checkcast     #77                 // class org/apache/hadoop/hbase/shaded/protobuf/generated/HFileProtos$FileTrailerProto
      17: astore_3
      18: iload_2
      19: aload_1
      20: invokevirtual #74                 // Method java/io/DataInputStream.available:()I
      23: isub
      24: istore        4
      26: aload_1
      27: aload_0
      28: invokevirtual #58                 // Method getTrailerSize:()I
      31: bipush        12
      33: isub
      34: iload         4
      36: isub
      37: i2l
      38: invokevirtual #78                 // Method java/io/DataInputStream.skip:(J)J
      41: pop2
      42: aload_3
      43: invokevirtual #79                 // Method org/apache/hadoop/hbase/shaded/protobuf/generated/HFileProtos$FileTrailerProto.hasFileInfoOffset:()Z
      46: ifeq          57
      49: aload_0
      50: aload_3
      51: invokevirtual #80                 // Method org/apache/hadoop/hbase/shaded/protobuf/generated/HFileProtos$FileTrailerProto.getFileInfoOffset:()J
      54: putfield      #28                 // Field fileInfoOffset:J
      57: aload_3
      58: invokevirtual #81                 // Method org/apache/hadoop/hbase/shaded/protobuf/generated/HFileProtos$FileTrailerProto.hasLoadOnOpenDataOffset:()Z
      61: ifeq          72
      64: aload_0
      65: aload_3
      66: invokevirtual #82                 // Method org/apache/hadoop/hbase/shaded/protobuf/generated/HFileProtos$FileTrailerProto.getLoadOnOpenDataOffset:()J
      69: putfield      #30                 // Field loadOnOpenDataOffset:J
      72: aload_3
      73: invokevirtual #83                 // Method org/apache/hadoop/hbase/shaded/protobuf/generated/HFileProtos$FileTrailerProto.hasUncompressedDataIndexSize:()Z
      76: ifeq          87
      79: aload_0
      80: aload_3
      81: invokevirtual #84                 // Method org/apache/hadoop/hbase/shaded/protobuf/generated/HFileProtos$FileTrailerProto.getUncompressedDataIndexSize:()J
      84: putfield      #32                 // Field uncompressedDataIndexSize:J
      87: aload_3
      88: invokevirtual #85                 // Method org/apache/hadoop/hbase/shaded/protobuf/generated/HFileProtos$FileTrailerProto.hasTotalUncompressedBytes:()Z
      91: ifeq          102
      94: aload_0
      95: aload_3
      96: invokevirtual #86                 // Method org/apache/hadoop/hbase/shaded/protobuf/generated/HFileProtos$FileTrailerProto.getTotalUncompressedBytes:()J
      99: putfield      #34                 // Field totalUncompressedBytes:J
     102: aload_3
     103: invokevirtual #87                 // Method org/apache/hadoop/hbase/shaded/protobuf/generated/HFileProtos$FileTrailerProto.hasDataIndexCount:()Z
     106: ifeq          117
     109: aload_0
     110: aload_3
     111: invokevirtual #88                 // Method org/apache/hadoop/hbase/shaded/protobuf/generated/HFileProtos$FileTrailerProto.getDataIndexCount:()I
     114: putfield      #36                 // Field dataIndexCount:I
     117: aload_3
     118: invokevirtual #89                 // Method org/apache/hadoop/hbase/shaded/protobuf/generated/HFileProtos$FileTrailerProto.hasMetaIndexCount:()Z
     121: ifeq          132
     124: aload_0
     125: aload_3
     126: invokevirtual #90                 // Method org/apache/hadoop/hbase/shaded/protobuf/generated/HFileProtos$FileTrailerProto.getMetaIndexCount:()I
     129: putfield      #38                 // Field metaIndexCount:I
     132: aload_3
     133: invokevirtual #91                 // Method org/apache/hadoop/hbase/shaded/protobuf/generated/HFileProtos$FileTrailerProto.hasEntryCount:()Z
     136: ifeq          147
     139: aload_0
     140: aload_3
     141: invokevirtual #92                 // Method org/apache/hadoop/hbase/shaded/protobuf/generated/HFileProtos$FileTrailerProto.getEntryCount:()J
     144: putfield      #40                 // Field entryCount:J
     147: aload_3
     148: invokevirtual #93                 // Method org/apache/hadoop/hbase/shaded/protobuf/generated/HFileProtos$FileTrailerProto.hasNumDataIndexLevels:()Z
     151: ifeq          162
     154: aload_0
     155: aload_3
     156: invokevirtual #94                 // Method org/apache/hadoop/hbase/shaded/protobuf/generated/HFileProtos$FileTrailerProto.getNumDataIndexLevels:()I
     159: putfield      #42                 // Field numDataIndexLevels:I
     162: aload_3
     163: invokevirtual #95                 // Method org/apache/hadoop/hbase/shaded/protobuf/generated/HFileProtos$FileTrailerProto.hasFirstDataBlockOffset:()Z
     166: ifeq          177
     169: aload_0
     170: aload_3
     171: invokevirtual #96                 // Method org/apache/hadoop/hbase/shaded/protobuf/generated/HFileProtos$FileTrailerProto.getFirstDataBlockOffset:()J
     174: putfield      #44                 // Field firstDataBlockOffset:J
     177: aload_3
     178: invokevirtual #97                 // Method org/apache/hadoop/hbase/shaded/protobuf/generated/HFileProtos$FileTrailerProto.hasLastDataBlockOffset:()Z
     181: ifeq          192
     184: aload_0
     185: aload_3
     186: invokevirtual #98                 // Method org/apache/hadoop/hbase/shaded/protobuf/generated/HFileProtos$FileTrailerProto.getLastDataBlockOffset:()J
     189: putfield      #46                 // Field lastDataBlockOffset:J
     192: aload_3
     193: invokevirtual #99                 // Method org/apache/hadoop/hbase/shaded/protobuf/generated/HFileProtos$FileTrailerProto.hasComparatorClassName:()Z
     196: ifeq          210
     199: aload_0
     200: aload_3
     201: invokevirtual #100                // Method org/apache/hadoop/hbase/shaded/protobuf/generated/HFileProtos$FileTrailerProto.getComparatorClassName:()Ljava/lang/String;
     204: invokestatic  #101                // Method getComparatorClass:(Ljava/lang/String;)Ljava/lang/Class;
     207: invokevirtual #102                // Method setComparatorClass:(Ljava/lang/Class;)V
     210: aload_3
     211: invokevirtual #103                // Method org/apache/hadoop/hbase/shaded/protobuf/generated/HFileProtos$FileTrailerProto.hasCompressionCodec:()Z
     214: ifeq          232
     217: aload_0
     218: invokestatic  #104                // Method org/apache/hadoop/hbase/io/compress/Compression$Algorithm.values:()[Lorg/apache/hadoop/hbase/io/compress/Compression$Algorithm;
     221: aload_3
     222: invokevirtual #105                // Method org/apache/hadoop/hbase/shaded/protobuf/generated/HFileProtos$FileTrailerProto.getCompressionCodec:()I
     225: aaload
     226: putfield      #5                  // Field compressionCodec:Lorg/apache/hadoop/hbase/io/compress/Compression$Algorithm;
     229: goto          239
     232: aload_0
     233: getstatic     #4                  // Field org/apache/hadoop/hbase/io/compress/Compression$Algorithm.NONE:Lorg/apache/hadoop/hbase/io/compress/Compression$Algorithm;
     236: putfield      #5                  // Field compressionCodec:Lorg/apache/hadoop/hbase/io/compress/Compression$Algorithm;
     239: aload_3
     240: invokevirtual #106                // Method org/apache/hadoop/hbase/shaded/protobuf/generated/HFileProtos$FileTrailerProto.hasEncryptionKey:()Z
     243: ifeq          257
     246: aload_0
     247: aload_3
     248: invokevirtual #107                // Method org/apache/hadoop/hbase/shaded/protobuf/generated/HFileProtos$FileTrailerProto.getEncryptionKey:()Lorg/apache/hbase/thirdparty/com/google/protobuf/ByteString;
     251: invokevirtual #108                // Method org/apache/hbase/thirdparty/com/google/protobuf/ByteString.toByteArray:()[B
     254: putfield      #52                 // Field encryptionKey:[B
     257: return

  void deserializeFromWritable(java.io.DataInput) throws java.io.IOException;
    Code:
       0: aload_0
       1: aload_1
       2: invokeinterface #109,  1          // InterfaceMethod java/io/DataInput.readLong:()J
       7: putfield      #28                 // Field fileInfoOffset:J
      10: aload_0
      11: aload_1
      12: invokeinterface #109,  1          // InterfaceMethod java/io/DataInput.readLong:()J
      17: putfield      #30                 // Field loadOnOpenDataOffset:J
      20: aload_0
      21: aload_1
      22: invokeinterface #110,  1          // InterfaceMethod java/io/DataInput.readInt:()I
      27: putfield      #36                 // Field dataIndexCount:I
      30: aload_0
      31: aload_1
      32: invokeinterface #109,  1          // InterfaceMethod java/io/DataInput.readLong:()J
      37: putfield      #32                 // Field uncompressedDataIndexSize:J
      40: aload_0
      41: aload_1
      42: invokeinterface #110,  1          // InterfaceMethod java/io/DataInput.readInt:()I
      47: putfield      #38                 // Field metaIndexCount:I
      50: aload_0
      51: aload_1
      52: invokeinterface #109,  1          // InterfaceMethod java/io/DataInput.readLong:()J
      57: putfield      #34                 // Field totalUncompressedBytes:J
      60: aload_0
      61: aload_1
      62: invokeinterface #109,  1          // InterfaceMethod java/io/DataInput.readLong:()J
      67: putfield      #40                 // Field entryCount:J
      70: aload_0
      71: invokestatic  #104                // Method org/apache/hadoop/hbase/io/compress/Compression$Algorithm.values:()[Lorg/apache/hadoop/hbase/io/compress/Compression$Algorithm;
      74: aload_1
      75: invokeinterface #110,  1          // InterfaceMethod java/io/DataInput.readInt:()I
      80: aaload
      81: putfield      #5                  // Field compressionCodec:Lorg/apache/hadoop/hbase/io/compress/Compression$Algorithm;
      84: aload_0
      85: aload_1
      86: invokeinterface #110,  1          // InterfaceMethod java/io/DataInput.readInt:()I
      91: putfield      #42                 // Field numDataIndexLevels:I
      94: aload_0
      95: aload_1
      96: invokeinterface #109,  1          // InterfaceMethod java/io/DataInput.readLong:()J
     101: putfield      #44                 // Field firstDataBlockOffset:J
     104: aload_0
     105: aload_1
     106: invokeinterface #109,  1          // InterfaceMethod java/io/DataInput.readLong:()J
     111: putfield      #46                 // Field lastDataBlockOffset:J
     114: aload_0
     115: aload_1
     116: sipush        128
     119: invokestatic  #111                // Method org/apache/hadoop/hbase/util/Bytes.readStringFixedSize:(Ljava/io/DataInput;I)Ljava/lang/String;
     122: invokestatic  #101                // Method getComparatorClass:(Ljava/lang/String;)Ljava/lang/Class;
     125: invokevirtual #102                // Method setComparatorClass:(Ljava/lang/Class;)V
     128: return

  public java.lang.String toString();
    Code:
       0: new           #115                // class java/lang/StringBuilder
       3: dup
       4: invokespecial #116                // Method java/lang/StringBuilder."<init>":()V
       7: astore_1
       8: aload_0
       9: aload_1
      10: new           #115                // class java/lang/StringBuilder
      13: dup
      14: invokespecial #116                // Method java/lang/StringBuilder."<init>":()V
      17: ldc           #117                // String fileinfoOffset=
      19: invokevirtual #114                // Method java/lang/StringBuilder.append:(Ljava/lang/String;)Ljava/lang/StringBuilder;
      22: aload_0
      23: getfield      #28                 // Field fileInfoOffset:J
      26: invokevirtual #118                // Method java/lang/StringBuilder.append:(J)Ljava/lang/StringBuilder;
      29: invokevirtual #119                // Method java/lang/StringBuilder.toString:()Ljava/lang/String;
      32: invokespecial #120                // Method append:(Ljava/lang/StringBuilder;Ljava/lang/String;)V
      35: aload_0
      36: aload_1
      37: new           #115                // class java/lang/StringBuilder
      40: dup
      41: invokespecial #116                // Method java/lang/StringBuilder."<init>":()V
      44: ldc           #121                // String loadOnOpenDataOffset=
      46: invokevirtual #114                // Method java/lang/StringBuilder.append:(Ljava/lang/String;)Ljava/lang/StringBuilder;
      49: aload_0
      50: getfield      #30                 // Field loadOnOpenDataOffset:J
      53: invokevirtual #118                // Method java/lang/StringBuilder.append:(J)Ljava/lang/StringBuilder;
      56: invokevirtual #119                // Method java/lang/StringBuilder.toString:()Ljava/lang/String;
      59: invokespecial #120                // Method append:(Ljava/lang/StringBuilder;Ljava/lang/String;)V
      62: aload_0
      63: aload_1
      64: new           #115                // class java/lang/StringBuilder
      67: dup
      68: invokespecial #116                // Method java/lang/StringBuilder."<init>":()V
      71: ldc           #122                // String dataIndexCount=
      73: invokevirtual #114                // Method java/lang/StringBuilder.append:(Ljava/lang/String;)Ljava/lang/StringBuilder;
      76: aload_0
      77: getfield      #36                 // Field dataIndexCount:I
      80: invokevirtual #123                // Method java/lang/StringBuilder.append:(I)Ljava/lang/StringBuilder;
      83: invokevirtual #119                // Method java/lang/StringBuilder.toString:()Ljava/lang/String;
      86: invokespecial #120                // Method append:(Ljava/lang/StringBuilder;Ljava/lang/String;)V
      89: aload_0
      90: aload_1
      91: new           #115                // class java/lang/StringBuilder
      94: dup
      95: invokespecial #116                // Method java/lang/StringBuilder."<init>":()V
      98: ldc           #124                // String metaIndexCount=
     100: invokevirtual #114                // Method java/lang/StringBuilder.append:(Ljava/lang/String;)Ljava/lang/StringBuilder;
     103: aload_0
     104: getfield      #38                 // Field metaIndexCount:I
     107: invokevirtual #123                // Method java/lang/StringBuilder.append:(I)Ljava/lang/StringBuilder;
     110: invokevirtual #119                // Method java/lang/StringBuilder.toString:()Ljava/lang/String;
     113: invokespecial #120                // Method append:(Ljava/lang/StringBuilder;Ljava/lang/String;)V
     116: aload_0
     117: aload_1
     118: new           #115                // class java/lang/StringBuilder
     121: dup
     122: invokespecial #116                // Method java/lang/StringBuilder."<init>":()V
     125: ldc           #125                // String totalUncomressedBytes=
     127: invokevirtual #114                // Method java/lang/StringBuilder.append:(Ljava/lang/String;)Ljava/lang/StringBuilder;
     130: aload_0
     131: getfield      #34                 // Field totalUncompressedBytes:J
     134: invokevirtual #118                // Method java/lang/StringBuilder.append:(J)Ljava/lang/StringBuilder;
     137: invokevirtual #119                // Method java/lang/StringBuilder.toString:()Ljava/lang/String;
     140: invokespecial #120                // Method append:(Ljava/lang/StringBuilder;Ljava/lang/String;)V
     143: aload_0
     144: aload_1
     145: new           #115                // class java/lang/StringBuilder
     148: dup
     149: invokespecial #116                // Method java/lang/StringBuilder."<init>":()V
     152: ldc           #126                // String entryCount=
     154: invokevirtual #114                // Method java/lang/StringBuilder.append:(Ljava/lang/String;)Ljava/lang/StringBuilder;
     157: aload_0
     158: getfield      #40                 // Field entryCount:J
     161: invokevirtual #118                // Method java/lang/StringBuilder.append:(J)Ljava/lang/StringBuilder;
     164: invokevirtual #119                // Method java/lang/StringBuilder.toString:()Ljava/lang/String;
     167: invokespecial #120                // Method append:(Ljava/lang/StringBuilder;Ljava/lang/String;)V
     170: aload_0
     171: aload_1
     172: new           #115                // class java/lang/StringBuilder
     175: dup
     176: invokespecial #116                // Method java/lang/StringBuilder."<init>":()V
     179: ldc           #127                // String compressionCodec=
     181: invokevirtual #114                // Method java/lang/StringBuilder.append:(Ljava/lang/String;)Ljava/lang/StringBuilder;
     184: aload_0
     185: getfield      #5                  // Field compressionCodec:Lorg/apache/hadoop/hbase/io/compress/Compression$Algorithm;
     188: invokevirtual #128                // Method java/lang/StringBuilder.append:(Ljava/lang/Object;)Ljava/lang/StringBuilder;
     191: invokevirtual #119                // Method java/lang/StringBuilder.toString:()Ljava/lang/String;
     194: invokespecial #120                // Method append:(Ljava/lang/StringBuilder;Ljava/lang/String;)V
     197: aload_0
     198: aload_1
     199: new           #115                // class java/lang/StringBuilder
     202: dup
     203: invokespecial #116                // Method java/lang/StringBuilder."<init>":()V
     206: ldc           #129                // String uncompressedDataIndexSize=
     208: invokevirtual #114                // Method java/lang/StringBuilder.append:(Ljava/lang/String;)Ljava/lang/StringBuilder;
     211: aload_0
     212: getfield      #32                 // Field uncompressedDataIndexSize:J
     215: invokevirtual #118                // Method java/lang/StringBuilder.append:(J)Ljava/lang/StringBuilder;
     218: invokevirtual #119                // Method java/lang/StringBuilder.toString:()Ljava/lang/String;
     221: invokespecial #120                // Method append:(Ljava/lang/StringBuilder;Ljava/lang/String;)V
     224: aload_0
     225: aload_1
     226: new           #115                // class java/lang/StringBuilder
     229: dup
     230: invokespecial #116                // Method java/lang/StringBuilder."<init>":()V
     233: ldc           #130                // String numDataIndexLevels=
     235: invokevirtual #114                // Method java/lang/StringBuilder.append:(Ljava/lang/String;)Ljava/lang/StringBuilder;
     238: aload_0
     239: getfield      #42                 // Field numDataIndexLevels:I
     242: invokevirtual #123                // Method java/lang/StringBuilder.append:(I)Ljava/lang/StringBuilder;
     245: invokevirtual #119                // Method java/lang/StringBuilder.toString:()Ljava/lang/String;
     248: invokespecial #120                // Method append:(Ljava/lang/StringBuilder;Ljava/lang/String;)V
     251: aload_0
     252: aload_1
     253: new           #115                // class java/lang/StringBuilder
     256: dup
     257: invokespecial #116                // Method java/lang/StringBuilder."<init>":()V
     260: ldc           #131                // String firstDataBlockOffset=
     262: invokevirtual #114                // Method java/lang/StringBuilder.append:(Ljava/lang/String;)Ljava/lang/StringBuilder;
     265: aload_0
     266: getfield      #44                 // Field firstDataBlockOffset:J
     269: invokevirtual #118                // Method java/lang/StringBuilder.append:(J)Ljava/lang/StringBuilder;
     272: invokevirtual #119                // Method java/lang/StringBuilder.toString:()Ljava/lang/String;
     275: invokespecial #120                // Method append:(Ljava/lang/StringBuilder;Ljava/lang/String;)V
     278: aload_0
     279: aload_1
     280: new           #115                // class java/lang/StringBuilder
     283: dup
     284: invokespecial #116                // Method java/lang/StringBuilder."<init>":()V
     287: ldc           #132                // String lastDataBlockOffset=
     289: invokevirtual #114                // Method java/lang/StringBuilder.append:(Ljava/lang/String;)Ljava/lang/StringBuilder;
     292: aload_0
     293: getfield      #46                 // Field lastDataBlockOffset:J
     296: invokevirtual #118                // Method java/lang/StringBuilder.append:(J)Ljava/lang/StringBuilder;
     299: invokevirtual #119                // Method java/lang/StringBuilder.toString:()Ljava/lang/String;
     302: invokespecial #120                // Method append:(Ljava/lang/StringBuilder;Ljava/lang/String;)V
     305: aload_0
     306: aload_1
     307: new           #115                // class java/lang/StringBuilder
     310: dup
     311: invokespecial #116                // Method java/lang/StringBuilder."<init>":()V
     314: ldc           #133                // String comparatorClassName=
     316: invokevirtual #114                // Method java/lang/StringBuilder.append:(Ljava/lang/String;)Ljava/lang/StringBuilder;
     319: aload_0
     320: getfield      #9                  // Field comparatorClassName:Ljava/lang/String;
     323: invokevirtual #114                // Method java/lang/StringBuilder.append:(Ljava/lang/String;)Ljava/lang/StringBuilder;
     326: invokevirtual #119                // Method java/lang/StringBuilder.toString:()Ljava/lang/String;
     329: invokespecial #120                // Method append:(Ljava/lang/StringBuilder;Ljava/lang/String;)V
     332: aload_0
     333: getfield      #10                 // Field majorVersion:I
     336: iconst_3
     337: if_icmplt     377
     340: aload_0
     341: aload_1
     342: new           #115                // class java/lang/StringBuilder
     345: dup
     346: invokespecial #116                // Method java/lang/StringBuilder."<init>":()V
     349: ldc           #134                // String encryptionKey=
     351: invokevirtual #114                // Method java/lang/StringBuilder.append:(Ljava/lang/String;)Ljava/lang/StringBuilder;
     354: aload_0
     355: getfield      #52                 // Field encryptionKey:[B
     358: ifnull        366
     361: ldc           #135                // String PRESENT
     363: goto          368
     366: ldc           #136                // String NONE
     368: invokevirtual #114                // Method java/lang/StringBuilder.append:(Ljava/lang/String;)Ljava/lang/StringBuilder;
     371: invokevirtual #119                // Method java/lang/StringBuilder.toString:()Ljava/lang/String;
     374: invokespecial #120                // Method append:(Ljava/lang/StringBuilder;Ljava/lang/String;)V
     377: aload_0
     378: aload_1
     379: new           #115                // class java/lang/StringBuilder
     382: dup
     383: invokespecial #116                // Method java/lang/StringBuilder."<init>":()V
     386: ldc           #137                // String majorVersion=
     388: invokevirtual #114                // Method java/lang/StringBuilder.append:(Ljava/lang/String;)Ljava/lang/StringBuilder;
     391: aload_0
     392: getfield      #10                 // Field majorVersion:I
     395: invokevirtual #123                // Method java/lang/StringBuilder.append:(I)Ljava/lang/StringBuilder;
     398: invokevirtual #119                // Method java/lang/StringBuilder.toString:()Ljava/lang/String;
     401: invokespecial #120                // Method append:(Ljava/lang/StringBuilder;Ljava/lang/String;)V
     404: aload_0
     405: aload_1
     406: new           #115                // class java/lang/StringBuilder
     409: dup
     410: invokespecial #116                // Method java/lang/StringBuilder."<init>":()V
     413: ldc           #138                // String minorVersion=
     415: invokevirtual #114                // Method java/lang/StringBuilder.append:(Ljava/lang/String;)Ljava/lang/StringBuilder;
     418: aload_0
     419: getfield      #11                 // Field minorVersion:I
     422: invokevirtual #123                // Method java/lang/StringBuilder.append:(I)Ljava/lang/StringBuilder;
     425: invokevirtual #119                // Method java/lang/StringBuilder.toString:()Ljava/lang/String;
     428: invokespecial #120                // Method append:(Ljava/lang/StringBuilder;Ljava/lang/String;)V
     431: aload_1
     432: invokevirtual #119                // Method java/lang/StringBuilder.toString:()Ljava/lang/String;
     435: areturn

  public static org.apache.hadoop.hbase.io.hfile.FixedFileTrailer readFromStream(org.apache.hadoop.fs.FSDataInputStream, long) throws java.io.IOException;
    Code:
       0: getstatic     #139                // Field MAX_TRAILER_SIZE:I
       3: istore_3
       4: lload_1
       5: iload_3
       6: i2l
       7: lsub
       8: lstore        4
      10: lload         4
      12: lconst_0
      13: lcmp
      14: ifge          23
      17: lconst_0
      18: lstore        4
      20: lload_1
      21: l2i
      22: istore_3
      23: aload_0
      24: lload         4
      26: invokestatic  #140                // Method org/apache/hadoop/hbase/io/hfile/HFileUtil.seekOnMultipleSources:(Lorg/apache/hadoop/fs/FSDataInputStream;J)V
      29: iload_3
      30: invokestatic  #141                // Method java/nio/ByteBuffer.allocate:(I)Ljava/nio/ByteBuffer;
      33: astore        6
      35: aload_0
      36: aload         6
      38: invokevirtual #142                // Method java/nio/ByteBuffer.array:()[B
      41: aload         6
      43: invokevirtual #143                // Method java/nio/ByteBuffer.arrayOffset:()I
      46: aload         6
      48: invokevirtual #143                // Method java/nio/ByteBuffer.arrayOffset:()I
      51: aload         6
      53: invokevirtual #144                // Method java/nio/ByteBuffer.limit:()I
      56: iadd
      57: invokevirtual #145                // Method org/apache/hadoop/fs/FSDataInputStream.readFully:([BII)V
      60: aload         6
      62: aload         6
      64: invokevirtual #144                // Method java/nio/ByteBuffer.limit:()I
      67: iconst_4
      68: isub
      69: invokevirtual #146                // Method java/nio/ByteBuffer.position:(I)Ljava/nio/Buffer;
      72: pop
      73: aload         6
      75: invokevirtual #147                // Method java/nio/ByteBuffer.getInt:()I
      78: istore        7
      80: iload         7
      82: invokestatic  #70                 // Method extractMajorVersion:(I)I
      85: istore        8
      87: iload         7
      89: invokestatic  #72                 // Method extractMinorVersion:(I)I
      92: istore        9
      94: iload         8
      96: invokestatic  #12                 // Method org/apache/hadoop/hbase/io/hfile/HFile.checkFormatVersion:(I)V
      99: iload         8
     101: invokestatic  #14                 // Method getTrailerSize:(I)I
     104: istore        10
     106: new           #59                 // class org/apache/hadoop/hbase/io/hfile/FixedFileTrailer
     109: dup
     110: iload         8
     112: iload         9
     114: invokespecial #148                // Method "<init>":(II)V
     117: astore        11
     119: aload         11
     121: new           #149                // class java/io/DataInputStream
     124: dup
     125: new           #150                // class java/io/ByteArrayInputStream
     128: dup
     129: aload         6
     131: invokevirtual #142                // Method java/nio/ByteBuffer.array:()[B
     134: aload         6
     136: invokevirtual #143                // Method java/nio/ByteBuffer.arrayOffset:()I
     139: iload_3
     140: iadd
     141: iload         10
     143: isub
     144: iload         10
     146: invokespecial #151                // Method java/io/ByteArrayInputStream."<init>":([BII)V
     149: invokespecial #152                // Method java/io/DataInputStream."<init>":(Ljava/io/InputStream;)V
     152: invokevirtual #153                // Method deserialize:(Ljava/io/DataInputStream;)V
     155: aload         11
     157: areturn

  public void expectMajorVersion(int);
    Code:
       0: aload_0
       1: getfield      #10                 // Field majorVersion:I
       4: iload_1
       5: if_icmpeq     52
       8: new           #154                // class java/lang/IllegalArgumentException
      11: dup
      12: new           #115                // class java/lang/StringBuilder
      15: dup
      16: invokespecial #116                // Method java/lang/StringBuilder."<init>":()V
      19: ldc           #155                // String Invalid HFile major version:
      21: invokevirtual #114                // Method java/lang/StringBuilder.append:(Ljava/lang/String;)Ljava/lang/StringBuilder;
      24: aload_0
      25: getfield      #10                 // Field majorVersion:I
      28: invokevirtual #123                // Method java/lang/StringBuilder.append:(I)Ljava/lang/StringBuilder;
      31: ldc           #156                // String  (expected:
      33: invokevirtual #114                // Method java/lang/StringBuilder.append:(Ljava/lang/String;)Ljava/lang/StringBuilder;
      36: iload_1
      37: invokevirtual #123                // Method java/lang/StringBuilder.append:(I)Ljava/lang/StringBuilder;
      40: ldc           #157                // String )
      42: invokevirtual #114                // Method java/lang/StringBuilder.append:(Ljava/lang/String;)Ljava/lang/StringBuilder;
      45: invokevirtual #119                // Method java/lang/StringBuilder.toString:()Ljava/lang/String;
      48: invokespecial #158                // Method java/lang/IllegalArgumentException."<init>":(Ljava/lang/String;)V
      51: athrow
      52: return

  public void expectMinorVersion(int);
    Code:
       0: aload_0
       1: getfield      #11                 // Field minorVersion:I
       4: iload_1
       5: if_icmpeq     52
       8: new           #154                // class java/lang/IllegalArgumentException
      11: dup
      12: new           #115                // class java/lang/StringBuilder
      15: dup
      16: invokespecial #116                // Method java/lang/StringBuilder."<init>":()V
      19: ldc           #159                // String Invalid HFile minor version:
      21: invokevirtual #114                // Method java/lang/StringBuilder.append:(Ljava/lang/String;)Ljava/lang/StringBuilder;
      24: aload_0
      25: getfield      #11                 // Field minorVersion:I
      28: invokevirtual #123                // Method java/lang/StringBuilder.append:(I)Ljava/lang/StringBuilder;
      31: ldc           #156                // String  (expected:
      33: invokevirtual #114                // Method java/lang/StringBuilder.append:(Ljava/lang/String;)Ljava/lang/StringBuilder;
      36: iload_1
      37: invokevirtual #123                // Method java/lang/StringBuilder.append:(I)Ljava/lang/StringBuilder;
      40: ldc           #157                // String )
      42: invokevirtual #114                // Method java/lang/StringBuilder.append:(Ljava/lang/String;)Ljava/lang/StringBuilder;
      45: invokevirtual #119                // Method java/lang/StringBuilder.toString:()Ljava/lang/String;
      48: invokespecial #158                // Method java/lang/IllegalArgumentException."<init>":(Ljava/lang/String;)V
      51: athrow
      52: return

  public void expectAtLeastMajorVersion(int);
    Code:
       0: aload_0
       1: getfield      #10                 // Field majorVersion:I
       4: iload_1
       5: if_icmpge     52
       8: new           #154                // class java/lang/IllegalArgumentException
      11: dup
      12: new           #115                // class java/lang/StringBuilder
      15: dup
      16: invokespecial #116                // Method java/lang/StringBuilder."<init>":()V
      19: ldc           #155                // String Invalid HFile major version:
      21: invokevirtual #114                // Method java/lang/StringBuilder.append:(Ljava/lang/String;)Ljava/lang/StringBuilder;
      24: aload_0
      25: getfield      #10                 // Field majorVersion:I
      28: invokevirtual #123                // Method java/lang/StringBuilder.append:(I)Ljava/lang/StringBuilder;
      31: ldc           #156                // String  (expected:
      33: invokevirtual #114                // Method java/lang/StringBuilder.append:(Ljava/lang/String;)Ljava/lang/StringBuilder;
      36: iload_1
      37: invokevirtual #123                // Method java/lang/StringBuilder.append:(I)Ljava/lang/StringBuilder;
      40: ldc           #160                // String  or higher).
      42: invokevirtual #114                // Method java/lang/StringBuilder.append:(Ljava/lang/String;)Ljava/lang/StringBuilder;
      45: invokevirtual #119                // Method java/lang/StringBuilder.toString:()Ljava/lang/String;
      48: invokespecial #158                // Method java/lang/IllegalArgumentException."<init>":(Ljava/lang/String;)V
      51: athrow
      52: return

  public long getFileInfoOffset();
    Code:
       0: aload_0
       1: getfield      #28                 // Field fileInfoOffset:J
       4: lreturn

  public void setFileInfoOffset(long);
    Code:
       0: aload_0
       1: lload_1
       2: putfield      #28                 // Field fileInfoOffset:J
       5: return

  public long getLoadOnOpenDataOffset();
    Code:
       0: aload_0
       1: getfield      #30                 // Field loadOnOpenDataOffset:J
       4: lreturn

  public void setLoadOnOpenOffset(long);
    Code:
       0: aload_0
       1: lload_1
       2: putfield      #30                 // Field loadOnOpenDataOffset:J
       5: return

  public int getDataIndexCount();
    Code:
       0: aload_0
       1: getfield      #36                 // Field dataIndexCount:I
       4: ireturn

  public void setDataIndexCount(int);
    Code:
       0: aload_0
       1: iload_1
       2: putfield      #36                 // Field dataIndexCount:I
       5: return

  public int getMetaIndexCount();
    Code:
       0: aload_0
       1: getfield      #38                 // Field metaIndexCount:I
       4: ireturn

  public void setMetaIndexCount(int);
    Code:
       0: aload_0
       1: iload_1
       2: putfield      #38                 // Field metaIndexCount:I
       5: return

  public long getTotalUncompressedBytes();
    Code:
       0: aload_0
       1: getfield      #34                 // Field totalUncompressedBytes:J
       4: lreturn

  public void setTotalUncompressedBytes(long);
    Code:
       0: aload_0
       1: lload_1
       2: putfield      #34                 // Field totalUncompressedBytes:J
       5: return

  public long getEntryCount();
    Code:
       0: aload_0
       1: getfield      #40                 // Field entryCount:J
       4: lreturn

  public void setEntryCount(long);
    Code:
       0: aload_0
       1: lload_1
       2: putfield      #40                 // Field entryCount:J
       5: return

  public org.apache.hadoop.hbase.io.compress.Compression$Algorithm getCompressionCodec();
    Code:
       0: aload_0
       1: getfield      #5                  // Field compressionCodec:Lorg/apache/hadoop/hbase/io/compress/Compression$Algorithm;
       4: areturn

  public void setCompressionCodec(org.apache.hadoop.hbase.io.compress.Compression$Algorithm);
    Code:
       0: aload_0
       1: aload_1
       2: putfield      #5                  // Field compressionCodec:Lorg/apache/hadoop/hbase/io/compress/Compression$Algorithm;
       5: return

  public int getNumDataIndexLevels();
    Code:
       0: aload_0
       1: iconst_2
       2: invokevirtual #161                // Method expectAtLeastMajorVersion:(I)V
       5: aload_0
       6: getfield      #42                 // Field numDataIndexLevels:I
       9: ireturn

  public void setNumDataIndexLevels(int);
    Code:
       0: aload_0
       1: iconst_2
       2: invokevirtual #161                // Method expectAtLeastMajorVersion:(I)V
       5: aload_0
       6: iload_1
       7: putfield      #42                 // Field numDataIndexLevels:I
      10: return

  public long getLastDataBlockOffset();
    Code:
       0: aload_0
       1: iconst_2
       2: invokevirtual #161                // Method expectAtLeastMajorVersion:(I)V
       5: aload_0
       6: getfield      #46                 // Field lastDataBlockOffset:J
       9: lreturn

  public void setLastDataBlockOffset(long);
    Code:
       0: aload_0
       1: iconst_2
       2: invokevirtual #161                // Method expectAtLeastMajorVersion:(I)V
       5: aload_0
       6: lload_1
       7: putfield      #46                 // Field lastDataBlockOffset:J
      10: return

  public long getFirstDataBlockOffset();
    Code:
       0: aload_0
       1: iconst_2
       2: invokevirtual #161                // Method expectAtLeastMajorVersion:(I)V
       5: aload_0
       6: getfield      #44                 // Field firstDataBlockOffset:J
       9: lreturn

  public void setFirstDataBlockOffset(long);
    Code:
       0: aload_0
       1: iconst_2
       2: invokevirtual #161                // Method expectAtLeastMajorVersion:(I)V
       5: aload_0
       6: lload_1
       7: putfield      #44                 // Field firstDataBlockOffset:J
      10: return

  public java.lang.String getComparatorClassName();
    Code:
       0: aload_0
       1: getfield      #9                  // Field comparatorClassName:Ljava/lang/String;
       4: areturn

  public int getMajorVersion();
    Code:
       0: aload_0
       1: getfield      #10                 // Field majorVersion:I
       4: ireturn

  public int getMinorVersion();
    Code:
       0: aload_0
       1: getfield      #11                 // Field minorVersion:I
       4: ireturn

  public void setComparatorClass(java.lang.Class<? extends org.apache.hadoop.hbase.CellComparator>);
    Code:
       0: aload_1
       1: ifnull        31
       4: aload_1
       5: iconst_0
       6: anewarray     #162                // class java/lang/Class
       9: invokevirtual #163                // Method java/lang/Class.getDeclaredConstructor:([Ljava/lang/Class;)Ljava/lang/reflect/Constructor;
      12: iconst_0
      13: anewarray     #164                // class java/lang/Object
      16: invokevirtual #165                // Method java/lang/reflect/Constructor.newInstance:([Ljava/lang/Object;)Ljava/lang/Object;
      19: checkcast     #166                // class org/apache/hadoop/hbase/CellComparator
      22: astore_2
      23: aload_0
      24: aload_1
      25: invokevirtual #8                  // Method java/lang/Class.getName:()Ljava/lang/String;
      28: putfield      #9                  // Field comparatorClassName:Ljava/lang/String;
      31: goto          71
      34: astore_2
      35: new           #168                // class java/lang/RuntimeException
      38: dup
      39: new           #115                // class java/lang/StringBuilder
      42: dup
      43: invokespecial #116                // Method java/lang/StringBuilder."<init>":()V
      46: ldc           #169                // String Comparator class
      48: invokevirtual #114                // Method java/lang/StringBuilder.append:(Ljava/lang/String;)Ljava/lang/StringBuilder;
      51: aload_1
      52: invokevirtual #8                  // Method java/lang/Class.getName:()Ljava/lang/String;
      55: invokevirtual #114                // Method java/lang/StringBuilder.append:(Ljava/lang/String;)Ljava/lang/StringBuilder;
      58: ldc           #170                // String  is not instantiable
      60: invokevirtual #114                // Method java/lang/StringBuilder.append:(Ljava/lang/String;)Ljava/lang/StringBuilder;
      63: invokevirtual #119                // Method java/lang/StringBuilder.toString:()Ljava/lang/String;
      66: aload_2
      67: invokespecial #171                // Method java/lang/RuntimeException."<init>":(Ljava/lang/String;Ljava/lang/Throwable;)V
      70: athrow
      71: return
    Exception table:
       from    to  target type
           0    31    34   Class java/lang/Exception

  public static org.apache.hadoop.hbase.CellComparator createComparator(java.lang.String) throws java.io.IOException;
    Code:
       0: aload_0
       1: invokestatic  #101                // Method getComparatorClass:(Ljava/lang/String;)Ljava/lang/Class;
       4: astore_1
       5: aload_1
       6: ifnull        28
       9: aload_1
      10: iconst_0
      11: anewarray     #162                // class java/lang/Class
      14: invokevirtual #163                // Method java/lang/Class.getDeclaredConstructor:([Ljava/lang/Class;)Ljava/lang/reflect/Constructor;
      17: iconst_0
      18: anewarray     #164                // class java/lang/Object
      21: invokevirtual #165                // Method java/lang/reflect/Constructor.newInstance:([Ljava/lang/Object;)Ljava/lang/Object;
      24: checkcast     #166                // class org/apache/hadoop/hbase/CellComparator
      27: areturn
      28: getstatic     #185                // Field LOG:Lorg/slf4j/Logger;
      31: new           #115                // class java/lang/StringBuilder
      34: dup
      35: invokespecial #116                // Method java/lang/StringBuilder."<init>":()V
      38: ldc           #186                // String No Comparator class for
      40: invokevirtual #114                // Method java/lang/StringBuilder.append:(Ljava/lang/String;)Ljava/lang/StringBuilder;
      43: aload_0
      44: invokevirtual #114                // Method java/lang/StringBuilder.append:(Ljava/lang/String;)Ljava/lang/StringBuilder;
      47: ldc           #187                // String . Returning Null.
      49: invokevirtual #114                // Method java/lang/StringBuilder.append:(Ljava/lang/String;)Ljava/lang/StringBuilder;
      52: invokevirtual #119                // Method java/lang/StringBuilder.toString:()Ljava/lang/String;
      55: invokeinterface #188,  2          // InterfaceMethod org/slf4j/Logger.warn:(Ljava/lang/String;)V
      60: aconst_null
      61: areturn
      62: astore_1
      63: new           #61                 // class java/io/IOException
      66: dup
      67: new           #115                // class java/lang/StringBuilder
      70: dup
      71: invokespecial #116                // Method java/lang/StringBuilder."<init>":()V
      74: ldc           #169                // String Comparator class
      76: invokevirtual #114                // Method java/lang/StringBuilder.append:(Ljava/lang/String;)Ljava/lang/StringBuilder;
      79: aload_0
      80: invokevirtual #114                // Method java/lang/StringBuilder.append:(Ljava/lang/String;)Ljava/lang/StringBuilder;
      83: ldc           #170                // String  is not instantiable
      85: invokevirtual #114                // Method java/lang/StringBuilder.append:(Ljava/lang/String;)Ljava/lang/StringBuilder;
      88: invokevirtual #119                // Method java/lang/StringBuilder.toString:()Ljava/lang/String;
      91: aload_1
      92: invokespecial #189                // Method java/io/IOException."<init>":(Ljava/lang/String;Ljava/lang/Throwable;)V
      95: athrow
    Exception table:
       from    to  target type
           0    27    62   Class java/lang/Exception
          28    61    62   Class java/lang/Exception

  org.apache.hadoop.hbase.CellComparator createComparator() throws java.io.IOException;
    Code:
       0: aload_0
       1: iconst_2
       2: invokevirtual #161                // Method expectAtLeastMajorVersion:(I)V
       5: aload_0
       6: getfield      #9                  // Field comparatorClassName:Ljava/lang/String;
       9: invokestatic  #190                // Method createComparator:(Ljava/lang/String;)Lorg/apache/hadoop/hbase/CellComparator;
      12: areturn

  public long getUncompressedDataIndexSize();
    Code:
       0: aload_0
       1: getfield      #32                 // Field uncompressedDataIndexSize:J
       4: lreturn

  public void setUncompressedDataIndexSize(long);
    Code:
       0: aload_0
       1: iconst_2
       2: invokevirtual #161                // Method expectAtLeastMajorVersion:(I)V
       5: aload_0
       6: lload_1
       7: putfield      #32                 // Field uncompressedDataIndexSize:J
      10: return

  public byte[] getEncryptionKey();
    Code:
       0: aload_0
       1: iconst_2
       2: invokevirtual #161                // Method expectAtLeastMajorVersion:(I)V
       5: aload_0
       6: getfield      #52                 // Field encryptionKey:[B
       9: areturn

  public void setEncryptionKey(byte[]);
    Code:
       0: aload_0
       1: aload_1
       2: putfield      #52                 // Field encryptionKey:[B
       5: return

  static int materializeVersion(int, int);
    Code:
       0: iload_0
       1: ldc           #191                // int 16777215
       3: iand
       4: iload_1
       5: bipush        24
       7: ishl
       8: ior
       9: ireturn

  static {};
    Code:
       0: ldc           #59                 // class org/apache/hadoop/hbase/io/hfile/FixedFileTrailer
       2: invokestatic  #192                // Method org/slf4j/LoggerFactory.getLogger:(Ljava/lang/Class;)Lorg/slf4j/Logger;
       5: putstatic     #185                // Field LOG:Lorg/slf4j/Logger;
       8: invokestatic  #193                // Method computeTrailerSizeByVersion:()[I
      11: putstatic     #16                 // Field TRAILER_SIZE:[I
      14: invokestatic  #194                // Method getMaxTrailerSize:()I
      17: putstatic     #139                // Field MAX_TRAILER_SIZE:I
      20: return
}
