Compiled from "FlushType.java"
final class org.apache.hadoop.hbase.regionserver.FlushType extends java.lang.Enum<org.apache.hadoop.hbase.regionserver.FlushType> {
  public static final org.apache.hadoop.hbase.regionserver.FlushType NORMAL;

  public static final org.apache.hadoop.hbase.regionserver.FlushType ABOVE_ONHEAP_LOWER_MARK;

  public static final org.apache.hadoop.hbase.regionserver.FlushType ABOVE_ONHEAP_HIGHER_MARK;

  public static final org.apache.hadoop.hbase.regionserver.FlushType ABOVE_OFFHEAP_LOWER_MARK;

  public static final org.apache.hadoop.hbase.regionserver.FlushType ABOVE_OFFHEAP_HIGHER_MARK;

  public static org.apache.hadoop.hbase.regionserver.FlushType[] values();
    Code:
       0: getstatic     #1                  // Field $VALUES:[Lorg/apache/hadoop/hbase/regionserver/FlushType;
       3: invokevirtual #2                  // Method "[Lorg/apache/hadoop/hbase/regionserver/FlushType;".clone:()Ljava/lang/Object;
       6: checkcast     #3                  // class "[Lorg/apache/hadoop/hbase/regionserver/FlushType;"
       9: areturn

  public static org.apache.hadoop.hbase.regionserver.FlushType valueOf(java.lang.String);
    Code:
       0: ldc           #4                  // class org/apache/hadoop/hbase/regionserver/FlushType
       2: aload_0
       3: invokestatic  #5                  // Method java/lang/Enum.valueOf:(Ljava/lang/Class;Ljava/lang/String;)Ljava/lang/Enum;
       6: checkcast     #4                  // class org/apache/hadoop/hbase/regionserver/FlushType
       9: areturn

  static {};
    Code:
       0: new           #4                  // class org/apache/hadoop/hbase/regionserver/FlushType
       3: dup
       4: ldc           #7                  // String NORMAL
       6: iconst_0
       7: invokespecial #8                  // Method "<init>":(Ljava/lang/String;I)V
      10: putstatic     #9                  // Field NORMAL:Lorg/apache/hadoop/hbase/regionserver/FlushType;
      13: new           #4                  // class org/apache/hadoop/hbase/regionserver/FlushType
      16: dup
      17: ldc           #10                 // String ABOVE_ONHEAP_LOWER_MARK
      19: iconst_1
      20: invokespecial #8                  // Method "<init>":(Ljava/lang/String;I)V
      23: putstatic     #11                 // Field ABOVE_ONHEAP_LOWER_MARK:Lorg/apache/hadoop/hbase/regionserver/FlushType;
      26: new           #4                  // class org/apache/hadoop/hbase/regionserver/FlushType
      29: dup
      30: ldc           #12                 // String ABOVE_ONHEAP_HIGHER_MARK
      32: iconst_2
      33: invokespecial #8                  // Method "<init>":(Ljava/lang/String;I)V
      36: putstatic     #13                 // Field ABOVE_ONHEAP_HIGHER_MARK:Lorg/apache/hadoop/hbase/regionserver/FlushType;
      39: new           #4                  // class org/apache/hadoop/hbase/regionserver/FlushType
      42: dup
      43: ldc           #14                 // String ABOVE_OFFHEAP_LOWER_MARK
      45: iconst_3
      46: invokespecial #8                  // Method "<init>":(Ljava/lang/String;I)V
      49: putstatic     #15                 // Field ABOVE_OFFHEAP_LOWER_MARK:Lorg/apache/hadoop/hbase/regionserver/FlushType;
      52: new           #4                  // class org/apache/hadoop/hbase/regionserver/FlushType
      55: dup
      56: ldc           #16                 // String ABOVE_OFFHEAP_HIGHER_MARK
      58: iconst_4
      59: invokespecial #8                  // Method "<init>":(Ljava/lang/String;I)V
      62: putstatic     #17                 // Field ABOVE_OFFHEAP_HIGHER_MARK:Lorg/apache/hadoop/hbase/regionserver/FlushType;
      65: iconst_5
      66: anewarray     #4                  // class org/apache/hadoop/hbase/regionserver/FlushType
      69: dup
      70: iconst_0
      71: getstatic     #9                  // Field NORMAL:Lorg/apache/hadoop/hbase/regionserver/FlushType;
      74: aastore
      75: dup
      76: iconst_1
      77: getstatic     #11                 // Field ABOVE_ONHEAP_LOWER_MARK:Lorg/apache/hadoop/hbase/regionserver/FlushType;
      80: aastore
      81: dup
      82: iconst_2
      83: getstatic     #13                 // Field ABOVE_ONHEAP_HIGHER_MARK:Lorg/apache/hadoop/hbase/regionserver/FlushType;
      86: aastore
      87: dup
      88: iconst_3
      89: getstatic     #15                 // Field ABOVE_OFFHEAP_LOWER_MARK:Lorg/apache/hadoop/hbase/regionserver/FlushType;
      92: aastore
      93: dup
      94: iconst_4
      95: getstatic     #17                 // Field ABOVE_OFFHEAP_HIGHER_MARK:Lorg/apache/hadoop/hbase/regionserver/FlushType;
      98: aastore
      99: putstatic     #1                  // Field $VALUES:[Lorg/apache/hadoop/hbase/regionserver/FlushType;
     102: return
}
