Compiled from "ForeignExceptionDispatcher.java"
public class org.apache.hadoop.hbase.errorhandling.ForeignExceptionDispatcher implements org.apache.hadoop.hbase.errorhandling.ForeignExceptionListener,org.apache.hadoop.hbase.errorhandling.ForeignExceptionSnare {
  protected final java.lang.String name;

  protected final java.util.List<org.apache.hadoop.hbase.errorhandling.ForeignExceptionListener> listeners;

  public org.apache.hadoop.hbase.errorhandling.ForeignExceptionDispatcher(java.lang.String);
    Code:
       0: aload_0
       1: invokespecial #1                  // Method java/lang/Object."<init>":()V
       4: aload_0
       5: new           #2                  // class java/util/ArrayList
       8: dup
       9: invokespecial #3                  // Method java/util/ArrayList."<init>":()V
      12: putfield      #4                  // Field listeners:Ljava/util/List;
      15: aload_0
      16: aload_1
      17: putfield      #5                  // Field name:Ljava/lang/String;
      20: return

  public org.apache.hadoop.hbase.errorhandling.ForeignExceptionDispatcher();
    Code:
       0: aload_0
       1: ldc           #6                  // String
       3: invokespecial #7                  // Method "<init>":(Ljava/lang/String;)V
       6: return

  public java.lang.String getName();
    Code:
       0: aload_0
       1: getfield      #5                  // Field name:Ljava/lang/String;
       4: areturn

  public synchronized void receive(org.apache.hadoop.hbase.errorhandling.ForeignException);
    Code:
       0: aload_0
       1: getfield      #8                  // Field exception:Lorg/apache/hadoop/hbase/errorhandling/ForeignException;
       4: ifnull        8
       7: return
       8: getstatic     #9                  // Field LOG:Lorg/slf4j/Logger;
      11: new           #10                 // class java/lang/StringBuilder
      14: dup
      15: invokespecial #11                 // Method java/lang/StringBuilder."<init>":()V
      18: aload_0
      19: getfield      #5                  // Field name:Ljava/lang/String;
      22: invokevirtual #12                 // Method java/lang/StringBuilder.append:(Ljava/lang/String;)Ljava/lang/StringBuilder;
      25: ldc           #13                 // String  accepting received exception
      27: invokevirtual #12                 // Method java/lang/StringBuilder.append:(Ljava/lang/String;)Ljava/lang/StringBuilder;
      30: invokevirtual #14                 // Method java/lang/StringBuilder.toString:()Ljava/lang/String;
      33: aload_1
      34: invokeinterface #15,  3           // InterfaceMethod org/slf4j/Logger.debug:(Ljava/lang/String;Ljava/lang/Throwable;)V
      39: aload_1
      40: ifnull        51
      43: aload_0
      44: aload_1
      45: putfield      #8                  // Field exception:Lorg/apache/hadoop/hbase/errorhandling/ForeignException;
      48: goto          68
      51: aload_0
      52: new           #16                 // class org/apache/hadoop/hbase/errorhandling/ForeignException
      55: dup
      56: aload_0
      57: getfield      #5                  // Field name:Ljava/lang/String;
      60: ldc           #6                  // String
      62: invokespecial #17                 // Method org/apache/hadoop/hbase/errorhandling/ForeignException."<init>":(Ljava/lang/String;Ljava/lang/String;)V
      65: putfield      #8                  // Field exception:Lorg/apache/hadoop/hbase/errorhandling/ForeignException;
      68: aload_0
      69: aload_1
      70: invokespecial #18                 // Method dispatch:(Lorg/apache/hadoop/hbase/errorhandling/ForeignException;)V
      73: return

  public synchronized void rethrowException() throws org.apache.hadoop.hbase.errorhandling.ForeignException;
    Code:
       0: aload_0
       1: getfield      #8                  // Field exception:Lorg/apache/hadoop/hbase/errorhandling/ForeignException;
       4: ifnull        29
       7: new           #16                 // class org/apache/hadoop/hbase/errorhandling/ForeignException
      10: dup
      11: aload_0
      12: getfield      #8                  // Field exception:Lorg/apache/hadoop/hbase/errorhandling/ForeignException;
      15: invokevirtual #19                 // Method org/apache/hadoop/hbase/errorhandling/ForeignException.getSource:()Ljava/lang/String;
      18: aload_0
      19: getfield      #8                  // Field exception:Lorg/apache/hadoop/hbase/errorhandling/ForeignException;
      22: invokevirtual #20                 // Method org/apache/hadoop/hbase/errorhandling/ForeignException.getCause:()Ljava/lang/Throwable;
      25: invokespecial #21                 // Method org/apache/hadoop/hbase/errorhandling/ForeignException."<init>":(Ljava/lang/String;Ljava/lang/Throwable;)V
      28: athrow
      29: return

  public synchronized boolean hasException();
    Code:
       0: aload_0
       1: getfield      #8                  // Field exception:Lorg/apache/hadoop/hbase/errorhandling/ForeignException;
       4: ifnull        11
       7: iconst_1
       8: goto          12
      11: iconst_0
      12: ireturn

  public synchronized org.apache.hadoop.hbase.errorhandling.ForeignException getException();
    Code:
       0: aload_0
       1: getfield      #8                  // Field exception:Lorg/apache/hadoop/hbase/errorhandling/ForeignException;
       4: areturn

  public synchronized void addListener(org.apache.hadoop.hbase.errorhandling.ForeignExceptionListener);
    Code:
       0: aload_0
       1: getfield      #4                  // Field listeners:Ljava/util/List;
       4: aload_1
       5: invokeinterface #27,  2           // InterfaceMethod java/util/List.add:(Ljava/lang/Object;)Z
      10: pop
      11: return

  static {};
    Code:
       0: ldc           #28                 // class org/apache/hadoop/hbase/errorhandling/ForeignExceptionDispatcher
       2: invokestatic  #29                 // Method org/slf4j/LoggerFactory.getLogger:(Ljava/lang/Class;)Lorg/slf4j/Logger;
       5: putstatic     #9                  // Field LOG:Lorg/slf4j/Logger;
       8: return
}
