Compiled from "FSHLog.java"
class org.apache.hadoop.hbase.regionserver.wal.FSHLog$RingBufferExceptionHandler implements com.lmax.disruptor.ExceptionHandler<org.apache.hadoop.hbase.regionserver.wal.RingBufferTruck> {
  org.apache.hadoop.hbase.regionserver.wal.FSHLog$RingBufferExceptionHandler();
    Code:
       0: aload_0
       1: invokespecial #1                  // Method java/lang/Object."<init>":()V
       4: return

  public void handleEventException(java.lang.Throwable, long, org.apache.hadoop.hbase.regionserver.wal.RingBufferTruck);
    Code:
       0: invokestatic  #2                  // Method org/apache/hadoop/hbase/regionserver/wal/FSHLog.access$000:()Lorg/slf4j/Logger;
       3: new           #3                  // class java/lang/StringBuilder
       6: dup
       7: invokespecial #4                  // Method java/lang/StringBuilder."<init>":()V
      10: ldc           #5                  // String Sequence=
      12: invokevirtual #6                  // Method java/lang/StringBuilder.append:(Ljava/lang/String;)Ljava/lang/StringBuilder;
      15: lload_2
      16: invokevirtual #7                  // Method java/lang/StringBuilder.append:(J)Ljava/lang/StringBuilder;
      19: ldc           #8                  // String , event=
      21: invokevirtual #6                  // Method java/lang/StringBuilder.append:(Ljava/lang/String;)Ljava/lang/StringBuilder;
      24: aload         4
      26: invokevirtual #9                  // Method java/lang/StringBuilder.append:(Ljava/lang/Object;)Ljava/lang/StringBuilder;
      29: invokevirtual #10                 // Method java/lang/StringBuilder.toString:()Ljava/lang/String;
      32: aload_1
      33: invokeinterface #11,  3           // InterfaceMethod org/slf4j/Logger.error:(Ljava/lang/String;Ljava/lang/Throwable;)V
      38: new           #12                 // class java/lang/RuntimeException
      41: dup
      42: aload_1
      43: invokespecial #13                 // Method java/lang/RuntimeException."<init>":(Ljava/lang/Throwable;)V
      46: athrow

  public void handleOnStartException(java.lang.Throwable);
    Code:
       0: invokestatic  #2                  // Method org/apache/hadoop/hbase/regionserver/wal/FSHLog.access$000:()Lorg/slf4j/Logger;
       3: aload_1
       4: invokevirtual #14                 // Method java/lang/Throwable.toString:()Ljava/lang/String;
       7: aload_1
       8: invokeinterface #11,  3           // InterfaceMethod org/slf4j/Logger.error:(Ljava/lang/String;Ljava/lang/Throwable;)V
      13: new           #12                 // class java/lang/RuntimeException
      16: dup
      17: aload_1
      18: invokespecial #13                 // Method java/lang/RuntimeException."<init>":(Ljava/lang/Throwable;)V
      21: athrow

  public void handleOnShutdownException(java.lang.Throwable);
    Code:
       0: invokestatic  #2                  // Method org/apache/hadoop/hbase/regionserver/wal/FSHLog.access$000:()Lorg/slf4j/Logger;
       3: aload_1
       4: invokevirtual #14                 // Method java/lang/Throwable.toString:()Ljava/lang/String;
       7: aload_1
       8: invokeinterface #11,  3           // InterfaceMethod org/slf4j/Logger.error:(Ljava/lang/String;Ljava/lang/Throwable;)V
      13: new           #12                 // class java/lang/RuntimeException
      16: dup
      17: aload_1
      18: invokespecial #13                 // Method java/lang/RuntimeException."<init>":(Ljava/lang/Throwable;)V
      21: athrow

  public void handleEventException(java.lang.Throwable, long, java.lang.Object);
    Code:
       0: aload_0
       1: aload_1
       2: lload_2
       3: aload         4
       5: checkcast     #15                 // class org/apache/hadoop/hbase/regionserver/wal/RingBufferTruck
       8: invokevirtual #16                 // Method handleEventException:(Ljava/lang/Throwable;JLorg/apache/hadoop/hbase/regionserver/wal/RingBufferTruck;)V
      11: return
}
