Compiled from "FSRegionScanner.java"
class org.apache.hadoop.hbase.util.FSRegionScanner implements java.lang.Runnable {
  org.apache.hadoop.hbase.util.FSRegionScanner(org.apache.hadoop.fs.FileSystem, org.apache.hadoop.fs.Path, java.util.Map<java.lang.String, java.lang.String>, java.util.Map<java.lang.String, java.util.Map<java.lang.String, java.lang.Float>>);
    Code:
       0: aload_0
       1: invokespecial #1                  // Method java/lang/Object."<init>":()V
       4: aload_0
       5: aload_1
       6: putfield      #2                  // Field fs:Lorg/apache/hadoop/fs/FileSystem;
       9: aload_0
      10: aload_2
      11: putfield      #3                  // Field regionPath:Lorg/apache/hadoop/fs/Path;
      14: aload_0
      15: aload_3
      16: putfield      #4                  // Field regionToBestLocalityRSMapping:Ljava/util/Map;
      19: aload_0
      20: aload         4
      22: putfield      #5                  // Field regionDegreeLocalityMapping:Ljava/util/Map;
      25: return

  public void run();
    Code:
       0: new           #6                  // class java/util/HashMap
       3: dup
       4: invokespecial #7                  // Method java/util/HashMap."<init>":()V
       7: astore_1
       8: aload_0
       9: getfield      #3                  // Field regionPath:Lorg/apache/hadoop/fs/Path;
      12: invokevirtual #8                  // Method org/apache/hadoop/fs/Path.getParent:()Lorg/apache/hadoop/fs/Path;
      15: invokevirtual #9                  // Method org/apache/hadoop/fs/Path.getName:()Ljava/lang/String;
      18: astore_2
      19: iconst_0
      20: istore_3
      21: aload_0
      22: getfield      #2                  // Field fs:Lorg/apache/hadoop/fs/FileSystem;
      25: aload_0
      26: getfield      #3                  // Field regionPath:Lorg/apache/hadoop/fs/Path;
      29: new           #10                 // class org/apache/hadoop/hbase/util/FSUtils$FamilyDirFilter
      32: dup
      33: aload_0
      34: getfield      #2                  // Field fs:Lorg/apache/hadoop/fs/FileSystem;
      37: invokespecial #11                 // Method org/apache/hadoop/hbase/util/FSUtils$FamilyDirFilter."<init>":(Lorg/apache/hadoop/fs/FileSystem;)V
      40: invokevirtual #12                 // Method org/apache/hadoop/fs/FileSystem.listStatus:(Lorg/apache/hadoop/fs/Path;Lorg/apache/hadoop/fs/PathFilter;)[Lorg/apache/hadoop/fs/FileStatus;
      43: astore        4
      45: aconst_null
      46: aload         4
      48: if_acmpne     52
      51: return
      52: aload         4
      54: astore        5
      56: aload         5
      58: arraylength
      59: istore        6
      61: iconst_0
      62: istore        7
      64: iload         7
      66: iload         6
      68: if_icmpge     294
      71: aload         5
      73: iload         7
      75: aaload
      76: astore        8
      78: aload         8
      80: invokevirtual #13                 // Method org/apache/hadoop/fs/FileStatus.isDirectory:()Z
      83: ifne          89
      86: goto          288
      89: aload_0
      90: getfield      #2                  // Field fs:Lorg/apache/hadoop/fs/FileSystem;
      93: aload         8
      95: invokevirtual #14                 // Method org/apache/hadoop/fs/FileStatus.getPath:()Lorg/apache/hadoop/fs/Path;
      98: invokevirtual #15                 // Method org/apache/hadoop/fs/FileSystem.listStatus:(Lorg/apache/hadoop/fs/Path;)[Lorg/apache/hadoop/fs/FileStatus;
     101: astore        9
     103: aconst_null
     104: aload         9
     106: if_acmpne     112
     109: goto          288
     112: aload         9
     114: astore        10
     116: aload         10
     118: arraylength
     119: istore        11
     121: iconst_0
     122: istore        12
     124: iload         12
     126: iload         11
     128: if_icmpge     288
     131: aload         10
     133: iload         12
     135: aaload
     136: astore        13
     138: aload_0
     139: getfield      #2                  // Field fs:Lorg/apache/hadoop/fs/FileSystem;
     142: aload         13
     144: lconst_0
     145: aload         13
     147: invokevirtual #16                 // Method org/apache/hadoop/fs/FileStatus.getLen:()J
     150: invokevirtual #17                 // Method org/apache/hadoop/fs/FileSystem.getFileBlockLocations:(Lorg/apache/hadoop/fs/FileStatus;JJ)[Lorg/apache/hadoop/fs/BlockLocation;
     153: astore        14
     155: aconst_null
     156: aload         14
     158: if_acmpne     164
     161: goto          282
     164: iload_3
     165: aload         14
     167: arraylength
     168: iadd
     169: istore_3
     170: aload         14
     172: astore        15
     174: aload         15
     176: arraylength
     177: istore        16
     179: iconst_0
     180: istore        17
     182: iload         17
     184: iload         16
     186: if_icmpge     282
     189: aload         15
     191: iload         17
     193: aaload
     194: astore        18
     196: aload         18
     198: invokevirtual #18                 // Method org/apache/hadoop/fs/BlockLocation.getHosts:()[Ljava/lang/String;
     201: astore        19
     203: aload         19
     205: arraylength
     206: istore        20
     208: iconst_0
     209: istore        21
     211: iload         21
     213: iload         20
     215: if_icmpge     276
     218: aload         19
     220: iload         21
     222: aaload
     223: astore        22
     225: aload_1
     226: aload         22
     228: invokeinterface #19,  2           // InterfaceMethod java/util/Map.get:(Ljava/lang/Object;)Ljava/lang/Object;
     233: checkcast     #20                 // class java/util/concurrent/atomic/AtomicInteger
     236: astore        23
     238: aload         23
     240: ifnonnull     264
     243: new           #20                 // class java/util/concurrent/atomic/AtomicInteger
     246: dup
     247: iconst_0
     248: invokespecial #21                 // Method java/util/concurrent/atomic/AtomicInteger."<init>":(I)V
     251: astore        23
     253: aload_1
     254: aload         22
     256: aload         23
     258: invokeinterface #22,  3           // InterfaceMethod java/util/Map.put:(Ljava/lang/Object;Ljava/lang/Object;)Ljava/lang/Object;
     263: pop
     264: aload         23
     266: invokevirtual #23                 // Method java/util/concurrent/atomic/AtomicInteger.incrementAndGet:()I
     269: pop
     270: iinc          21, 1
     273: goto          211
     276: iinc          17, 1
     279: goto          182
     282: iinc          12, 1
     285: goto          124
     288: iinc          7, 1
     291: goto          64
     294: aload_0
     295: getfield      #4                  // Field regionToBestLocalityRSMapping:Ljava/util/Map;
     298: ifnull        486
     301: iconst_0
     302: istore        5
     304: aconst_null
     305: astore        6
     307: aload_1
     308: invokeinterface #24,  1           // InterfaceMethod java/util/Map.entrySet:()Ljava/util/Set;
     313: invokeinterface #25,  1           // InterfaceMethod java/util/Set.iterator:()Ljava/util/Iterator;
     318: astore        7
     320: aload         7
     322: invokeinterface #26,  1           // InterfaceMethod java/util/Iterator.hasNext:()Z
     327: ifeq          387
     330: aload         7
     332: invokeinterface #27,  1           // InterfaceMethod java/util/Iterator.next:()Ljava/lang/Object;
     337: checkcast     #28                 // class java/util/Map$Entry
     340: astore        8
     342: aload         8
     344: invokeinterface #29,  1           // InterfaceMethod java/util/Map$Entry.getKey:()Ljava/lang/Object;
     349: checkcast     #30                 // class java/lang/String
     352: astore        9
     354: aload         8
     356: invokeinterface #31,  1           // InterfaceMethod java/util/Map$Entry.getValue:()Ljava/lang/Object;
     361: checkcast     #20                 // class java/util/concurrent/atomic/AtomicInteger
     364: invokevirtual #32                 // Method java/util/concurrent/atomic/AtomicInteger.get:()I
     367: istore        10
     369: iload         10
     371: iload         5
     373: if_icmple     384
     376: iload         10
     378: istore        5
     380: aload         9
     382: astore        6
     384: goto          320
     387: aconst_null
     388: aload         6
     390: if_acmpne     394
     393: return
     394: aload         6
     396: ldc           #33                 // String .
     398: invokevirtual #34                 // Method java/lang/String.endsWith:(Ljava/lang/String;)Z
     401: ifeq          419
     404: aload         6
     406: iconst_0
     407: aload         6
     409: invokevirtual #35                 // Method java/lang/String.length:()I
     412: iconst_1
     413: isub
     414: invokevirtual #36                 // Method java/lang/String.substring:(II)Ljava/lang/String;
     417: astore        6
     419: new           #37                 // class java/lang/StringBuilder
     422: dup
     423: invokespecial #38                 // Method java/lang/StringBuilder."<init>":()V
     426: aload_2
     427: invokevirtual #39                 // Method java/lang/StringBuilder.append:(Ljava/lang/String;)Ljava/lang/StringBuilder;
     430: ldc           #40                 // String :
     432: invokevirtual #39                 // Method java/lang/StringBuilder.append:(Ljava/lang/String;)Ljava/lang/StringBuilder;
     435: aload_0
     436: getfield      #3                  // Field regionPath:Lorg/apache/hadoop/fs/Path;
     439: invokevirtual #9                  // Method org/apache/hadoop/fs/Path.getName:()Ljava/lang/String;
     442: invokevirtual #39                 // Method java/lang/StringBuilder.append:(Ljava/lang/String;)Ljava/lang/StringBuilder;
     445: invokevirtual #41                 // Method java/lang/StringBuilder.toString:()Ljava/lang/String;
     448: astore        7
     450: aload_0
     451: getfield      #4                  // Field regionToBestLocalityRSMapping:Ljava/util/Map;
     454: dup
     455: astore        8
     457: monitorenter
     458: aload_0
     459: getfield      #4                  // Field regionToBestLocalityRSMapping:Ljava/util/Map;
     462: aload         7
     464: aload         6
     466: invokeinterface #22,  3           // InterfaceMethod java/util/Map.put:(Ljava/lang/Object;Ljava/lang/Object;)Ljava/lang/Object;
     471: pop
     472: aload         8
     474: monitorexit
     475: goto          486
     478: astore        24
     480: aload         8
     482: monitorexit
     483: aload         24
     485: athrow
     486: aload_0
     487: getfield      #5                  // Field regionDegreeLocalityMapping:Ljava/util/Map;
     490: ifnull        634
     493: iload_3
     494: ifle          634
     497: new           #6                  // class java/util/HashMap
     500: dup
     501: invokespecial #7                  // Method java/util/HashMap."<init>":()V
     504: astore        5
     506: aload_1
     507: invokeinterface #24,  1           // InterfaceMethod java/util/Map.entrySet:()Ljava/util/Set;
     512: invokeinterface #25,  1           // InterfaceMethod java/util/Set.iterator:()Ljava/util/Iterator;
     517: astore        6
     519: aload         6
     521: invokeinterface #26,  1           // InterfaceMethod java/util/Iterator.hasNext:()Z
     526: ifeq          615
     529: aload         6
     531: invokeinterface #27,  1           // InterfaceMethod java/util/Iterator.next:()Ljava/lang/Object;
     536: checkcast     #28                 // class java/util/Map$Entry
     539: astore        7
     541: aload         7
     543: invokeinterface #29,  1           // InterfaceMethod java/util/Map$Entry.getKey:()Ljava/lang/Object;
     548: checkcast     #30                 // class java/lang/String
     551: astore        8
     553: aload         8
     555: ldc           #33                 // String .
     557: invokevirtual #34                 // Method java/lang/String.endsWith:(Ljava/lang/String;)Z
     560: ifeq          578
     563: aload         8
     565: iconst_0
     566: aload         8
     568: invokevirtual #35                 // Method java/lang/String.length:()I
     571: iconst_1
     572: isub
     573: invokevirtual #36                 // Method java/lang/String.substring:(II)Ljava/lang/String;
     576: astore        8
     578: aload         7
     580: invokeinterface #31,  1           // InterfaceMethod java/util/Map$Entry.getValue:()Ljava/lang/Object;
     585: checkcast     #20                 // class java/util/concurrent/atomic/AtomicInteger
     588: invokevirtual #32                 // Method java/util/concurrent/atomic/AtomicInteger.get:()I
     591: i2f
     592: iload_3
     593: i2f
     594: fdiv
     595: fstore        9
     597: aload         5
     599: aload         8
     601: fload         9
     603: invokestatic  #42                 // Method java/lang/Float.valueOf:(F)Ljava/lang/Float;
     606: invokeinterface #22,  3           // InterfaceMethod java/util/Map.put:(Ljava/lang/Object;Ljava/lang/Object;)Ljava/lang/Object;
     611: pop
     612: goto          519
     615: aload_0
     616: getfield      #5                  // Field regionDegreeLocalityMapping:Ljava/util/Map;
     619: aload_0
     620: getfield      #3                  // Field regionPath:Lorg/apache/hadoop/fs/Path;
     623: invokevirtual #9                  // Method org/apache/hadoop/fs/Path.getName:()Ljava/lang/String;
     626: aload         5
     628: invokeinterface #22,  3           // InterfaceMethod java/util/Map.put:(Ljava/lang/Object;Ljava/lang/Object;)Ljava/lang/Object;
     633: pop
     634: goto          664
     637: astore_1
     638: getstatic     #44                 // Field LOG:Lorg/slf4j/Logger;
     641: ldc           #45                 // String Problem scanning file system
     643: aload_1
     644: invokeinterface #46,  3           // InterfaceMethod org/slf4j/Logger.warn:(Ljava/lang/String;Ljava/lang/Throwable;)V
     649: goto          664
     652: astore_1
     653: getstatic     #44                 // Field LOG:Lorg/slf4j/Logger;
     656: ldc           #45                 // String Problem scanning file system
     658: aload_1
     659: invokeinterface #46,  3           // InterfaceMethod org/slf4j/Logger.warn:(Ljava/lang/String;Ljava/lang/Throwable;)V
     664: return
    Exception table:
       from    to  target type
         458   475   478   any
         478   483   478   any
           0    51   637   Class java/io/IOException
          52   393   637   Class java/io/IOException
         394   634   637   Class java/io/IOException
           0    51   652   Class java/lang/RuntimeException
          52   393   652   Class java/lang/RuntimeException
         394   634   652   Class java/lang/RuntimeException

  static {};
    Code:
       0: ldc           #48                 // class org/apache/hadoop/hbase/util/FSRegionScanner
       2: invokestatic  #49                 // Method org/slf4j/LoggerFactory.getLogger:(Ljava/lang/Class;)Lorg/slf4j/Logger;
       5: putstatic     #44                 // Field LOG:Lorg/slf4j/Logger;
       8: return
}
