Compiled from "FSTableDescriptors.java"
final class org.apache.hadoop.hbase.util.FSTableDescriptors$1 implements java.util.Comparator<org.apache.hadoop.fs.FileStatus> {
  org.apache.hadoop.hbase.util.FSTableDescriptors$1();
    Code:
       0: aload_0
       1: invokespecial #1                  // Method java/lang/Object."<init>":()V
       4: return

  public int compare(org.apache.hadoop.fs.FileStatus, org.apache.hadoop.fs.FileStatus);
    Code:
       0: aload_2
       1: aload_1
       2: invokevirtual #2                  // Method org/apache/hadoop/fs/FileStatus.compareTo:(Lorg/apache/hadoop/fs/FileStatus;)I
       5: ireturn

  public int compare(java.lang.Object, java.lang.Object);
    Code:
       0: aload_0
       1: aload_1
       2: checkcast     #3                  // class org/apache/hadoop/fs/FileStatus
       5: aload_2
       6: checkcast     #3                  // class org/apache/hadoop/fs/FileStatus
       9: invokevirtual #4                  // Method compare:(Lorg/apache/hadoop/fs/FileStatus;Lorg/apache/hadoop/fs/FileStatus;)I
      12: ireturn
}
