Compiled from "FSUtils.java"
public class org.apache.hadoop.hbase.util.FSUtils$RegionDirFilter extends org.apache.hadoop.hbase.util.AbstractFileStatusFilter {
  public static final java.util.regex.Pattern regionDirPattern;

  final org.apache.hadoop.fs.FileSystem fs;

  public org.apache.hadoop.hbase.util.FSUtils$RegionDirFilter(org.apache.hadoop.fs.FileSystem);
    Code:
       0: aload_0
       1: invokespecial #1                  // Method org/apache/hadoop/hbase/util/AbstractFileStatusFilter."<init>":()V
       4: aload_0
       5: aload_1
       6: putfield      #2                  // Field fs:Lorg/apache/hadoop/fs/FileSystem;
       9: return

  protected boolean accept(org.apache.hadoop.fs.Path, java.lang.Boolean);
    Code:
       0: getstatic     #3                  // Field regionDirPattern:Ljava/util/regex/Pattern;
       3: aload_1
       4: invokevirtual #4                  // Method org/apache/hadoop/fs/Path.getName:()Ljava/lang/String;
       7: invokevirtual #5                  // Method java/util/regex/Pattern.matcher:(Ljava/lang/CharSequence;)Ljava/util/regex/Matcher;
      10: invokevirtual #6                  // Method java/util/regex/Matcher.matches:()Z
      13: ifne          18
      16: iconst_0
      17: ireturn
      18: aload_0
      19: aload_0
      20: getfield      #2                  // Field fs:Lorg/apache/hadoop/fs/FileSystem;
      23: aload_2
      24: aload_1
      25: invokevirtual #7                  // Method isDirectory:(Lorg/apache/hadoop/fs/FileSystem;Ljava/lang/Boolean;Lorg/apache/hadoop/fs/Path;)Z
      28: ireturn
      29: astore_3
      30: invokestatic  #9                  // Method org/apache/hadoop/hbase/util/FSUtils.access$000:()Lorg/slf4j/Logger;
      33: new           #10                 // class java/lang/StringBuilder
      36: dup
      37: invokespecial #11                 // Method java/lang/StringBuilder."<init>":()V
      40: ldc           #12                 // String Skipping file
      42: invokevirtual #13                 // Method java/lang/StringBuilder.append:(Ljava/lang/String;)Ljava/lang/StringBuilder;
      45: aload_1
      46: invokevirtual #14                 // Method java/lang/StringBuilder.append:(Ljava/lang/Object;)Ljava/lang/StringBuilder;
      49: ldc           #15                 // String  due to IOException
      51: invokevirtual #13                 // Method java/lang/StringBuilder.append:(Ljava/lang/String;)Ljava/lang/StringBuilder;
      54: invokevirtual #16                 // Method java/lang/StringBuilder.toString:()Ljava/lang/String;
      57: aload_3
      58: invokeinterface #17,  3           // InterfaceMethod org/slf4j/Logger.warn:(Ljava/lang/String;Ljava/lang/Throwable;)V
      63: iconst_0
      64: ireturn
    Exception table:
       from    to  target type
          18    28    29   Class java/io/IOException

  static {};
    Code:
       0: ldc           #18                 // String ^[0-9a-f]*$
       2: invokestatic  #19                 // Method java/util/regex/Pattern.compile:(Ljava/lang/String;)Ljava/util/regex/Pattern;
       5: putstatic     #3                  // Field regionDirPattern:Ljava/util/regex/Pattern;
       8: return
}
