Compiled from "FSUtils.java"
final class org.apache.hadoop.hbase.util.FSUtils$1 implements java.lang.Runnable {
  final org.apache.hadoop.fs.FileSystem val$fs;

  final org.apache.hadoop.fs.Path val$dd;

  final org.apache.hadoop.hbase.util.FSUtils$FamilyDirFilter val$familyFilter;

  final org.apache.hadoop.hbase.util.HBaseFsck$ErrorReporter val$errors;

  final org.apache.hadoop.fs.PathFilter val$sfFilter;

  final java.util.Map val$finalResultMap;

  final java.util.Vector val$exceptions;

  org.apache.hadoop.hbase.util.FSUtils$1(org.apache.hadoop.fs.FileSystem, org.apache.hadoop.fs.Path, org.apache.hadoop.hbase.util.FSUtils$FamilyDirFilter, org.apache.hadoop.hbase.util.HBaseFsck$ErrorReporter, org.apache.hadoop.fs.PathFilter, java.util.Map, java.util.Vector);
    Code:
       0: aload_0
       1: aload_1
       2: putfield      #1                  // Field val$fs:Lorg/apache/hadoop/fs/FileSystem;
       5: aload_0
       6: aload_2
       7: putfield      #2                  // Field val$dd:Lorg/apache/hadoop/fs/Path;
      10: aload_0
      11: aload_3
      12: putfield      #3                  // Field val$familyFilter:Lorg/apache/hadoop/hbase/util/FSUtils$FamilyDirFilter;
      15: aload_0
      16: aload         4
      18: putfield      #4                  // Field val$errors:Lorg/apache/hadoop/hbase/util/HBaseFsck$ErrorReporter;
      21: aload_0
      22: aload         5
      24: putfield      #5                  // Field val$sfFilter:Lorg/apache/hadoop/fs/PathFilter;
      27: aload_0
      28: aload         6
      30: putfield      #6                  // Field val$finalResultMap:Ljava/util/Map;
      33: aload_0
      34: aload         7
      36: putfield      #7                  // Field val$exceptions:Ljava/util/Vector;
      39: aload_0
      40: invokespecial #8                  // Method java/lang/Object."<init>":()V
      43: return

  public void run();
    Code:
       0: new           #9                  // class java/util/HashMap
       3: dup
       4: invokespecial #10                 // Method java/util/HashMap."<init>":()V
       7: astore_1
       8: aload_0
       9: getfield      #1                  // Field val$fs:Lorg/apache/hadoop/fs/FileSystem;
      12: aload_0
      13: getfield      #2                  // Field val$dd:Lorg/apache/hadoop/fs/Path;
      16: aload_0
      17: getfield      #3                  // Field val$familyFilter:Lorg/apache/hadoop/hbase/util/FSUtils$FamilyDirFilter;
      20: invokestatic  #11                 // Method org/apache/hadoop/hbase/util/FSUtils.listStatusWithStatusFilter:(Lorg/apache/hadoop/fs/FileSystem;Lorg/apache/hadoop/fs/Path;Lorg/apache/hadoop/hbase/util/FileStatusFilter;)Ljava/util/List;
      23: astore_2
      24: aload_2
      25: ifnonnull     106
      28: aload_0
      29: getfield      #1                  // Field val$fs:Lorg/apache/hadoop/fs/FileSystem;
      32: aload_0
      33: getfield      #2                  // Field val$dd:Lorg/apache/hadoop/fs/Path;
      36: invokevirtual #12                 // Method org/apache/hadoop/fs/FileSystem.exists:(Lorg/apache/hadoop/fs/Path;)Z
      39: ifne          75
      42: invokestatic  #13                 // Method org/apache/hadoop/hbase/util/FSUtils.access$000:()Lorg/slf4j/Logger;
      45: new           #14                 // class java/lang/StringBuilder
      48: dup
      49: invokespecial #15                 // Method java/lang/StringBuilder."<init>":()V
      52: ldc           #16                 // String Skipping region because it no longer exists:
      54: invokevirtual #17                 // Method java/lang/StringBuilder.append:(Ljava/lang/String;)Ljava/lang/StringBuilder;
      57: aload_0
      58: getfield      #2                  // Field val$dd:Lorg/apache/hadoop/fs/Path;
      61: invokevirtual #18                 // Method java/lang/StringBuilder.append:(Ljava/lang/Object;)Ljava/lang/StringBuilder;
      64: invokevirtual #19                 // Method java/lang/StringBuilder.toString:()Ljava/lang/String;
      67: invokeinterface #20,  2           // InterfaceMethod org/slf4j/Logger.warn:(Ljava/lang/String;)V
      72: goto          105
      75: invokestatic  #13                 // Method org/apache/hadoop/hbase/util/FSUtils.access$000:()Lorg/slf4j/Logger;
      78: new           #14                 // class java/lang/StringBuilder
      81: dup
      82: invokespecial #15                 // Method java/lang/StringBuilder."<init>":()V
      85: ldc           #21                 // String Skipping region because it has no family dirs:
      87: invokevirtual #17                 // Method java/lang/StringBuilder.append:(Ljava/lang/String;)Ljava/lang/StringBuilder;
      90: aload_0
      91: getfield      #2                  // Field val$dd:Lorg/apache/hadoop/fs/Path;
      94: invokevirtual #18                 // Method java/lang/StringBuilder.append:(Ljava/lang/Object;)Ljava/lang/StringBuilder;
      97: invokevirtual #19                 // Method java/lang/StringBuilder.toString:()Ljava/lang/String;
     100: invokeinterface #20,  2           // InterfaceMethod org/slf4j/Logger.warn:(Ljava/lang/String;)V
     105: return
     106: aload_2
     107: invokeinterface #22,  1           // InterfaceMethod java/util/List.iterator:()Ljava/util/Iterator;
     112: astore_3
     113: aload_3
     114: invokeinterface #23,  1           // InterfaceMethod java/util/Iterator.hasNext:()Z
     119: ifeq          276
     122: aload_3
     123: invokeinterface #24,  1           // InterfaceMethod java/util/Iterator.next:()Ljava/lang/Object;
     128: checkcast     #25                 // class org/apache/hadoop/fs/FileStatus
     131: astore        4
     133: aconst_null
     134: aload_0
     135: getfield      #4                  // Field val$errors:Lorg/apache/hadoop/hbase/util/HBaseFsck$ErrorReporter;
     138: if_acmpeq     150
     141: aload_0
     142: getfield      #4                  // Field val$errors:Lorg/apache/hadoop/hbase/util/HBaseFsck$ErrorReporter;
     145: invokeinterface #26,  1           // InterfaceMethod org/apache/hadoop/hbase/util/HBaseFsck$ErrorReporter.progress:()V
     150: aload         4
     152: invokevirtual #27                 // Method org/apache/hadoop/fs/FileStatus.getPath:()Lorg/apache/hadoop/fs/Path;
     155: astore        5
     157: aload         5
     159: invokevirtual #28                 // Method org/apache/hadoop/fs/Path.getName:()Ljava/lang/String;
     162: ldc           #30                 // String recovered.edits
     164: invokevirtual #31                 // Method java/lang/String.equals:(Ljava/lang/Object;)Z
     167: ifeq          173
     170: goto          113
     173: aload_0
     174: getfield      #1                  // Field val$fs:Lorg/apache/hadoop/fs/FileSystem;
     177: aload         5
     179: invokevirtual #32                 // Method org/apache/hadoop/fs/FileSystem.listStatus:(Lorg/apache/hadoop/fs/Path;)[Lorg/apache/hadoop/fs/FileStatus;
     182: astore        6
     184: aload         6
     186: astore        7
     188: aload         7
     190: arraylength
     191: istore        8
     193: iconst_0
     194: istore        9
     196: iload         9
     198: iload         8
     200: if_icmpge     273
     203: aload         7
     205: iload         9
     207: aaload
     208: astore        10
     210: aconst_null
     211: aload_0
     212: getfield      #4                  // Field val$errors:Lorg/apache/hadoop/hbase/util/HBaseFsck$ErrorReporter;
     215: if_acmpeq     227
     218: aload_0
     219: getfield      #4                  // Field val$errors:Lorg/apache/hadoop/hbase/util/HBaseFsck$ErrorReporter;
     222: invokeinterface #26,  1           // InterfaceMethod org/apache/hadoop/hbase/util/HBaseFsck$ErrorReporter.progress:()V
     227: aload         10
     229: invokevirtual #27                 // Method org/apache/hadoop/fs/FileStatus.getPath:()Lorg/apache/hadoop/fs/Path;
     232: astore        11
     234: aload_0
     235: getfield      #5                  // Field val$sfFilter:Lorg/apache/hadoop/fs/PathFilter;
     238: ifnull        255
     241: aload_0
     242: getfield      #5                  // Field val$sfFilter:Lorg/apache/hadoop/fs/PathFilter;
     245: aload         11
     247: invokeinterface #33,  2           // InterfaceMethod org/apache/hadoop/fs/PathFilter.accept:(Lorg/apache/hadoop/fs/Path;)Z
     252: ifeq          267
     255: aload_1
     256: aload         11
     258: invokevirtual #28                 // Method org/apache/hadoop/fs/Path.getName:()Ljava/lang/String;
     261: aload         11
     263: invokevirtual #34                 // Method java/util/HashMap.put:(Ljava/lang/Object;Ljava/lang/Object;)Ljava/lang/Object;
     266: pop
     267: iinc          9, 1
     270: goto          196
     273: goto          113
     276: aload_0
     277: getfield      #6                  // Field val$finalResultMap:Ljava/util/Map;
     280: aload_1
     281: invokeinterface #35,  2           // InterfaceMethod java/util/Map.putAll:(Ljava/util/Map;)V
     286: goto          330
     289: astore_1
     290: invokestatic  #13                 // Method org/apache/hadoop/hbase/util/FSUtils.access$000:()Lorg/slf4j/Logger;
     293: new           #14                 // class java/lang/StringBuilder
     296: dup
     297: invokespecial #15                 // Method java/lang/StringBuilder."<init>":()V
     300: ldc           #37                 // String Could not get region store file map for region:
     302: invokevirtual #17                 // Method java/lang/StringBuilder.append:(Ljava/lang/String;)Ljava/lang/StringBuilder;
     305: aload_0
     306: getfield      #2                  // Field val$dd:Lorg/apache/hadoop/fs/Path;
     309: invokevirtual #18                 // Method java/lang/StringBuilder.append:(Ljava/lang/Object;)Ljava/lang/StringBuilder;
     312: invokevirtual #19                 // Method java/lang/StringBuilder.toString:()Ljava/lang/String;
     315: aload_1
     316: invokeinterface #38,  3           // InterfaceMethod org/slf4j/Logger.error:(Ljava/lang/String;Ljava/lang/Throwable;)V
     321: aload_0
     322: getfield      #7                  // Field val$exceptions:Ljava/util/Vector;
     325: aload_1
     326: invokevirtual #39                 // Method java/util/Vector.add:(Ljava/lang/Object;)Z
     329: pop
     330: return
    Exception table:
       from    to  target type
           0   105   289   Class java/lang/Exception
         106   286   289   Class java/lang/Exception
}
