Compiled from "FSVisitor.java"
public final class org.apache.hadoop.hbase.util.FSVisitor {
  public static void visitTableStoreFiles(org.apache.hadoop.fs.FileSystem, org.apache.hadoop.fs.Path, org.apache.hadoop.hbase.util.FSVisitor$StoreFileVisitor) throws java.io.IOException;
    Code:
       0: aload_0
       1: aload_1
       2: new           #2                  // class org/apache/hadoop/hbase/util/FSUtils$RegionDirFilter
       5: dup
       6: aload_0
       7: invokespecial #3                  // Method org/apache/hadoop/hbase/util/FSUtils$RegionDirFilter."<init>":(Lorg/apache/hadoop/fs/FileSystem;)V
      10: invokestatic  #4                  // Method org/apache/hadoop/hbase/util/FSUtils.listStatusWithStatusFilter:(Lorg/apache/hadoop/fs/FileSystem;Lorg/apache/hadoop/fs/Path;Lorg/apache/hadoop/hbase/util/FileStatusFilter;)Ljava/util/List;
      13: astore_3
      14: aload_3
      15: ifnonnull     57
      18: getstatic     #5                  // Field LOG:Lorg/slf4j/Logger;
      21: invokeinterface #6,  1            // InterfaceMethod org/slf4j/Logger.isTraceEnabled:()Z
      26: ifeq          56
      29: getstatic     #5                  // Field LOG:Lorg/slf4j/Logger;
      32: new           #7                  // class java/lang/StringBuilder
      35: dup
      36: invokespecial #8                  // Method java/lang/StringBuilder."<init>":()V
      39: ldc           #9                  // String No regions under directory:
      41: invokevirtual #10                 // Method java/lang/StringBuilder.append:(Ljava/lang/String;)Ljava/lang/StringBuilder;
      44: aload_1
      45: invokevirtual #11                 // Method java/lang/StringBuilder.append:(Ljava/lang/Object;)Ljava/lang/StringBuilder;
      48: invokevirtual #12                 // Method java/lang/StringBuilder.toString:()Ljava/lang/String;
      51: invokeinterface #13,  2           // InterfaceMethod org/slf4j/Logger.trace:(Ljava/lang/String;)V
      56: return
      57: aload_3
      58: invokeinterface #14,  1           // InterfaceMethod java/util/List.iterator:()Ljava/util/Iterator;
      63: astore        4
      65: aload         4
      67: invokeinterface #15,  1           // InterfaceMethod java/util/Iterator.hasNext:()Z
      72: ifeq          100
      75: aload         4
      77: invokeinterface #16,  1           // InterfaceMethod java/util/Iterator.next:()Ljava/lang/Object;
      82: checkcast     #17                 // class org/apache/hadoop/fs/FileStatus
      85: astore        5
      87: aload_0
      88: aload         5
      90: invokevirtual #18                 // Method org/apache/hadoop/fs/FileStatus.getPath:()Lorg/apache/hadoop/fs/Path;
      93: aload_2
      94: invokestatic  #19                 // Method visitRegionStoreFiles:(Lorg/apache/hadoop/fs/FileSystem;Lorg/apache/hadoop/fs/Path;Lorg/apache/hadoop/hbase/util/FSVisitor$StoreFileVisitor;)V
      97: goto          65
     100: return

  public static void visitRegionStoreFiles(org.apache.hadoop.fs.FileSystem, org.apache.hadoop.fs.Path, org.apache.hadoop.hbase.util.FSVisitor$StoreFileVisitor) throws java.io.IOException;
    Code:
       0: aload_0
       1: aload_1
       2: new           #20                 // class org/apache/hadoop/hbase/util/FSUtils$FamilyDirFilter
       5: dup
       6: aload_0
       7: invokespecial #21                 // Method org/apache/hadoop/hbase/util/FSUtils$FamilyDirFilter."<init>":(Lorg/apache/hadoop/fs/FileSystem;)V
      10: invokestatic  #4                  // Method org/apache/hadoop/hbase/util/FSUtils.listStatusWithStatusFilter:(Lorg/apache/hadoop/fs/FileSystem;Lorg/apache/hadoop/fs/Path;Lorg/apache/hadoop/hbase/util/FileStatusFilter;)Ljava/util/List;
      13: astore_3
      14: aload_3
      15: ifnonnull     57
      18: getstatic     #5                  // Field LOG:Lorg/slf4j/Logger;
      21: invokeinterface #6,  1            // InterfaceMethod org/slf4j/Logger.isTraceEnabled:()Z
      26: ifeq          56
      29: getstatic     #5                  // Field LOG:Lorg/slf4j/Logger;
      32: new           #7                  // class java/lang/StringBuilder
      35: dup
      36: invokespecial #8                  // Method java/lang/StringBuilder."<init>":()V
      39: ldc           #22                 // String No families under region directory:
      41: invokevirtual #10                 // Method java/lang/StringBuilder.append:(Ljava/lang/String;)Ljava/lang/StringBuilder;
      44: aload_1
      45: invokevirtual #11                 // Method java/lang/StringBuilder.append:(Ljava/lang/Object;)Ljava/lang/StringBuilder;
      48: invokevirtual #12                 // Method java/lang/StringBuilder.toString:()Ljava/lang/String;
      51: invokeinterface #13,  2           // InterfaceMethod org/slf4j/Logger.trace:(Ljava/lang/String;)V
      56: return
      57: new           #23                 // class org/apache/hadoop/hbase/util/FSUtils$FileFilter
      60: dup
      61: aload_0
      62: invokespecial #24                 // Method org/apache/hadoop/hbase/util/FSUtils$FileFilter."<init>":(Lorg/apache/hadoop/fs/FileSystem;)V
      65: astore        4
      67: aload_3
      68: invokeinterface #14,  1           // InterfaceMethod java/util/List.iterator:()Ljava/util/Iterator;
      73: astore        5
      75: aload         5
      77: invokeinterface #15,  1           // InterfaceMethod java/util/Iterator.hasNext:()Z
      82: ifeq          232
      85: aload         5
      87: invokeinterface #16,  1           // InterfaceMethod java/util/Iterator.next:()Ljava/lang/Object;
      92: checkcast     #17                 // class org/apache/hadoop/fs/FileStatus
      95: astore        6
      97: aload         6
      99: invokevirtual #18                 // Method org/apache/hadoop/fs/FileStatus.getPath:()Lorg/apache/hadoop/fs/Path;
     102: astore        7
     104: aload         7
     106: invokevirtual #25                 // Method org/apache/hadoop/fs/Path.getName:()Ljava/lang/String;
     109: astore        8
     111: aload_0
     112: aload         7
     114: aload         4
     116: invokestatic  #26                 // Method org/apache/hadoop/hbase/util/FSUtils.listStatus:(Lorg/apache/hadoop/fs/FileSystem;Lorg/apache/hadoop/fs/Path;Lorg/apache/hadoop/fs/PathFilter;)[Lorg/apache/hadoop/fs/FileStatus;
     119: astore        9
     121: aload         9
     123: ifnonnull     173
     126: getstatic     #5                  // Field LOG:Lorg/slf4j/Logger;
     129: invokeinterface #6,  1            // InterfaceMethod org/slf4j/Logger.isTraceEnabled:()Z
     134: ifeq          75
     137: getstatic     #5                  // Field LOG:Lorg/slf4j/Logger;
     140: new           #7                  // class java/lang/StringBuilder
     143: dup
     144: invokespecial #8                  // Method java/lang/StringBuilder."<init>":()V
     147: ldc           #27                 // String No hfiles found for family:
     149: invokevirtual #10                 // Method java/lang/StringBuilder.append:(Ljava/lang/String;)Ljava/lang/StringBuilder;
     152: aload         7
     154: invokevirtual #11                 // Method java/lang/StringBuilder.append:(Ljava/lang/Object;)Ljava/lang/StringBuilder;
     157: ldc           #28                 // String , skipping.
     159: invokevirtual #10                 // Method java/lang/StringBuilder.append:(Ljava/lang/String;)Ljava/lang/StringBuilder;
     162: invokevirtual #12                 // Method java/lang/StringBuilder.toString:()Ljava/lang/String;
     165: invokeinterface #13,  2           // InterfaceMethod org/slf4j/Logger.trace:(Ljava/lang/String;)V
     170: goto          75
     173: aload         9
     175: astore        10
     177: aload         10
     179: arraylength
     180: istore        11
     182: iconst_0
     183: istore        12
     185: iload         12
     187: iload         11
     189: if_icmpge     229
     192: aload         10
     194: iload         12
     196: aaload
     197: astore        13
     199: aload         13
     201: invokevirtual #18                 // Method org/apache/hadoop/fs/FileStatus.getPath:()Lorg/apache/hadoop/fs/Path;
     204: astore        14
     206: aload_2
     207: aload_1
     208: invokevirtual #25                 // Method org/apache/hadoop/fs/Path.getName:()Ljava/lang/String;
     211: aload         8
     213: aload         14
     215: invokevirtual #25                 // Method org/apache/hadoop/fs/Path.getName:()Ljava/lang/String;
     218: invokeinterface #29,  4           // InterfaceMethod org/apache/hadoop/hbase/util/FSVisitor$StoreFileVisitor.storeFile:(Ljava/lang/String;Ljava/lang/String;Ljava/lang/String;)V
     223: iinc          12, 1
     226: goto          185
     229: goto          75
     232: return

  static {};
    Code:
       0: ldc           #30                 // class org/apache/hadoop/hbase/util/FSVisitor
       2: invokestatic  #31                 // Method org/slf4j/LoggerFactory.getLogger:(Ljava/lang/Class;)Lorg/slf4j/Logger;
       5: putstatic     #5                  // Field LOG:Lorg/slf4j/Logger;
       8: return
}
