Compiled from "FuzzyRowFilter.java"
public class org.apache.hadoop.hbase.filter.FuzzyRowFilter extends org.apache.hadoop.hbase.filter.FilterBase {
  public org.apache.hadoop.hbase.filter.FuzzyRowFilter(java.util.List<org.apache.hadoop.hbase.util.Pair<byte[], byte[]>>);
    Code:
       0: aload_0
       1: invokespecial #2                  // Method org/apache/hadoop/hbase/filter/FilterBase."<init>":()V
       4: aload_0
       5: iconst_0
       6: putfield      #3                  // Field done:Z
       9: aload_0
      10: iconst_m1
      11: putfield      #4                  // Field lastFoundIndex:I
      14: new           #5                  // class java/util/ArrayList
      17: dup
      18: aload_1
      19: invokeinterface #6,  1            // InterfaceMethod java/util/List.size:()I
      24: invokespecial #7                  // Method java/util/ArrayList."<init>":(I)V
      27: astore_2
      28: aload_1
      29: invokeinterface #8,  1            // InterfaceMethod java/util/List.iterator:()Ljava/util/Iterator;
      34: astore_3
      35: aload_3
      36: invokeinterface #9,  1            // InterfaceMethod java/util/Iterator.hasNext:()Z
      41: ifeq          229
      44: aload_3
      45: invokeinterface #10,  1           // InterfaceMethod java/util/Iterator.next:()Ljava/lang/Object;
      50: checkcast     #11                 // class org/apache/hadoop/hbase/util/Pair
      53: astore        4
      55: aload         4
      57: invokevirtual #12                 // Method org/apache/hadoop/hbase/util/Pair.getFirst:()Ljava/lang/Object;
      60: checkcast     #13                 // class "[B"
      63: arraylength
      64: aload         4
      66: invokevirtual #14                 // Method org/apache/hadoop/hbase/util/Pair.getSecond:()Ljava/lang/Object;
      69: checkcast     #13                 // class "[B"
      72: arraylength
      73: if_icmpeq     135
      76: new           #11                 // class org/apache/hadoop/hbase/util/Pair
      79: dup
      80: aload         4
      82: invokevirtual #12                 // Method org/apache/hadoop/hbase/util/Pair.getFirst:()Ljava/lang/Object;
      85: checkcast     #13                 // class "[B"
      88: invokestatic  #15                 // Method org/apache/hadoop/hbase/util/Bytes.toStringBinary:([B)Ljava/lang/String;
      91: aload         4
      93: invokevirtual #14                 // Method org/apache/hadoop/hbase/util/Pair.getSecond:()Ljava/lang/Object;
      96: checkcast     #13                 // class "[B"
      99: invokestatic  #15                 // Method org/apache/hadoop/hbase/util/Bytes.toStringBinary:([B)Ljava/lang/String;
     102: invokespecial #16                 // Method org/apache/hadoop/hbase/util/Pair."<init>":(Ljava/lang/Object;Ljava/lang/Object;)V
     105: astore        5
     107: new           #17                 // class java/lang/IllegalArgumentException
     110: dup
     111: new           #18                 // class java/lang/StringBuilder
     114: dup
     115: invokespecial #19                 // Method java/lang/StringBuilder."<init>":()V
     118: ldc           #20                 // String Fuzzy pair lengths do not match:
     120: invokevirtual #21                 // Method java/lang/StringBuilder.append:(Ljava/lang/String;)Ljava/lang/StringBuilder;
     123: aload         5
     125: invokevirtual #22                 // Method java/lang/StringBuilder.append:(Ljava/lang/Object;)Ljava/lang/StringBuilder;
     128: invokevirtual #23                 // Method java/lang/StringBuilder.toString:()Ljava/lang/String;
     131: invokespecial #24                 // Method java/lang/IllegalArgumentException."<init>":(Ljava/lang/String;)V
     134: athrow
     135: new           #11                 // class org/apache/hadoop/hbase/util/Pair
     138: dup
     139: invokespecial #25                 // Method org/apache/hadoop/hbase/util/Pair."<init>":()V
     142: astore        5
     144: aload         5
     146: aload         4
     148: invokevirtual #12                 // Method org/apache/hadoop/hbase/util/Pair.getFirst:()Ljava/lang/Object;
     151: checkcast     #13                 // class "[B"
     154: aload         4
     156: invokevirtual #12                 // Method org/apache/hadoop/hbase/util/Pair.getFirst:()Ljava/lang/Object;
     159: checkcast     #13                 // class "[B"
     162: arraylength
     163: invokestatic  #26                 // Method java/util/Arrays.copyOf:([BI)[B
     166: invokevirtual #27                 // Method org/apache/hadoop/hbase/util/Pair.setFirst:(Ljava/lang/Object;)V
     169: aload         5
     171: aload         4
     173: invokevirtual #14                 // Method org/apache/hadoop/hbase/util/Pair.getSecond:()Ljava/lang/Object;
     176: checkcast     #13                 // class "[B"
     179: aload         4
     181: invokevirtual #14                 // Method org/apache/hadoop/hbase/util/Pair.getSecond:()Ljava/lang/Object;
     184: checkcast     #13                 // class "[B"
     187: arraylength
     188: invokestatic  #26                 // Method java/util/Arrays.copyOf:([BI)[B
     191: invokevirtual #28                 // Method org/apache/hadoop/hbase/util/Pair.setSecond:(Ljava/lang/Object;)V
     194: aload         5
     196: aload_0
     197: aload         5
     199: invokevirtual #14                 // Method org/apache/hadoop/hbase/util/Pair.getSecond:()Ljava/lang/Object;
     202: checkcast     #13                 // class "[B"
     205: invokespecial #29                 // Method preprocessMask:([B)[B
     208: invokevirtual #28                 // Method org/apache/hadoop/hbase/util/Pair.setSecond:(Ljava/lang/Object;)V
     211: aload_0
     212: aload         5
     214: invokespecial #30                 // Method preprocessSearchKey:(Lorg/apache/hadoop/hbase/util/Pair;)V
     217: aload_2
     218: aload         5
     220: invokeinterface #31,  2           // InterfaceMethod java/util/List.add:(Ljava/lang/Object;)Z
     225: pop
     226: goto          35
     229: aload_0
     230: aload_2
     231: putfield      #1                  // Field fuzzyKeysData:Ljava/util/List;
     234: aload_0
     235: new           #32                 // class org/apache/hadoop/hbase/filter/FuzzyRowFilter$RowTracker
     238: dup
     239: aload_0
     240: invokespecial #33                 // Method org/apache/hadoop/hbase/filter/FuzzyRowFilter$RowTracker."<init>":(Lorg/apache/hadoop/hbase/filter/FuzzyRowFilter;)V
     243: putfield      #34                 // Field tracker:Lorg/apache/hadoop/hbase/filter/FuzzyRowFilter$RowTracker;
     246: return

  public org.apache.hadoop.hbase.filter.Filter$ReturnCode filterKeyValue(org.apache.hadoop.hbase.Cell);
    Code:
       0: aload_0
       1: aload_1
       2: invokevirtual #37                 // Method filterCell:(Lorg/apache/hadoop/hbase/Cell;)Lorg/apache/hadoop/hbase/filter/Filter$ReturnCode;
       5: areturn

  public org.apache.hadoop.hbase.filter.Filter$ReturnCode filterCell(org.apache.hadoop.hbase.Cell);
    Code:
       0: aload_0
       1: getfield      #4                  // Field lastFoundIndex:I
       4: iflt          14
       7: aload_0
       8: getfield      #4                  // Field lastFoundIndex:I
      11: goto          15
      14: iconst_0
      15: istore_2
      16: aload_0
      17: getfield      #1                  // Field fuzzyKeysData:Ljava/util/List;
      20: invokeinterface #6,  1            // InterfaceMethod java/util/List.size:()I
      25: istore_3
      26: iload_2
      27: istore        4
      29: iload         4
      31: iload_3
      32: iload_2
      33: iadd
      34: if_icmpge     165
      37: iload         4
      39: iload_3
      40: irem
      41: istore        5
      43: aload_0
      44: getfield      #1                  // Field fuzzyKeysData:Ljava/util/List;
      47: iload         5
      49: invokeinterface #38,  2           // InterfaceMethod java/util/List.get:(I)Ljava/lang/Object;
      54: checkcast     #11                 // class org/apache/hadoop/hbase/util/Pair
      57: astore        6
      59: iconst_0
      60: istore        7
      62: iload         7
      64: aload         6
      66: invokevirtual #14                 // Method org/apache/hadoop/hbase/util/Pair.getSecond:()Ljava/lang/Object;
      69: checkcast     #13                 // class "[B"
      72: arraylength
      73: if_icmpge     98
      76: aload         6
      78: invokevirtual #14                 // Method org/apache/hadoop/hbase/util/Pair.getSecond:()Ljava/lang/Object;
      81: checkcast     #13                 // class "[B"
      84: iload         7
      86: dup2
      87: baload
      88: iconst_2
      89: ishr
      90: i2b
      91: bastore
      92: iinc          7, 1
      95: goto          62
      98: aload_0
      99: invokevirtual #39                 // Method isReversed:()Z
     102: aload_1
     103: invokeinterface #40,  1           // InterfaceMethod org/apache/hadoop/hbase/Cell.getRowArray:()[B
     108: aload_1
     109: invokeinterface #41,  1           // InterfaceMethod org/apache/hadoop/hbase/Cell.getRowOffset:()I
     114: aload_1
     115: invokeinterface #42,  1           // InterfaceMethod org/apache/hadoop/hbase/Cell.getRowLength:()S
     120: aload         6
     122: invokevirtual #12                 // Method org/apache/hadoop/hbase/util/Pair.getFirst:()Ljava/lang/Object;
     125: checkcast     #13                 // class "[B"
     128: aload         6
     130: invokevirtual #14                 // Method org/apache/hadoop/hbase/util/Pair.getSecond:()Ljava/lang/Object;
     133: checkcast     #13                 // class "[B"
     136: invokestatic  #43                 // Method satisfies:(Z[BII[B[B)Lorg/apache/hadoop/hbase/filter/FuzzyRowFilter$SatisfiesCode;
     139: astore        7
     141: aload         7
     143: getstatic     #44                 // Field org/apache/hadoop/hbase/filter/FuzzyRowFilter$SatisfiesCode.YES:Lorg/apache/hadoop/hbase/filter/FuzzyRowFilter$SatisfiesCode;
     146: if_acmpne     159
     149: aload_0
     150: iload         5
     152: putfield      #4                  // Field lastFoundIndex:I
     155: getstatic     #45                 // Field org/apache/hadoop/hbase/filter/Filter$ReturnCode.INCLUDE:Lorg/apache/hadoop/hbase/filter/Filter$ReturnCode;
     158: areturn
     159: iinc          4, 1
     162: goto          29
     165: aload_0
     166: iconst_m1
     167: putfield      #4                  // Field lastFoundIndex:I
     170: getstatic     #46                 // Field org/apache/hadoop/hbase/filter/Filter$ReturnCode.SEEK_NEXT_USING_HINT:Lorg/apache/hadoop/hbase/filter/Filter$ReturnCode;
     173: areturn

  public org.apache.hadoop.hbase.Cell getNextCellHint(org.apache.hadoop.hbase.Cell);
    Code:
       0: aload_0
       1: getfield      #34                 // Field tracker:Lorg/apache/hadoop/hbase/filter/FuzzyRowFilter$RowTracker;
       4: aload_1
       5: invokevirtual #47                 // Method org/apache/hadoop/hbase/filter/FuzzyRowFilter$RowTracker.updateTracker:(Lorg/apache/hadoop/hbase/Cell;)Z
       8: istore_2
       9: iload_2
      10: ifne          20
      13: aload_0
      14: iconst_1
      15: putfield      #3                  // Field done:Z
      18: aconst_null
      19: areturn
      20: aload_0
      21: getfield      #34                 // Field tracker:Lorg/apache/hadoop/hbase/filter/FuzzyRowFilter$RowTracker;
      24: invokevirtual #48                 // Method org/apache/hadoop/hbase/filter/FuzzyRowFilter$RowTracker.nextRow:()[B
      27: astore_3
      28: aload_3
      29: iconst_0
      30: aload_3
      31: arraylength
      32: i2s
      33: invokestatic  #49                 // Method org/apache/hadoop/hbase/PrivateCellUtil.createFirstOnRow:([BIS)Lorg/apache/hadoop/hbase/Cell;
      36: areturn

  public boolean filterAllRemaining();
    Code:
       0: aload_0
       1: getfield      #3                  // Field done:Z
       4: ireturn

  public byte[] toByteArray();
    Code:
       0: invokestatic  #50                 // Method org/apache/hadoop/hbase/shaded/protobuf/generated/FilterProtos$FuzzyRowFilter.newBuilder:()Lorg/apache/hadoop/hbase/shaded/protobuf/generated/FilterProtos$FuzzyRowFilter$Builder;
       3: astore_1
       4: aload_0
       5: getfield      #1                  // Field fuzzyKeysData:Ljava/util/List;
       8: invokeinterface #8,  1            // InterfaceMethod java/util/List.iterator:()Ljava/util/Iterator;
      13: astore_2
      14: aload_2
      15: invokeinterface #9,  1            // InterfaceMethod java/util/Iterator.hasNext:()Z
      20: ifeq          80
      23: aload_2
      24: invokeinterface #10,  1           // InterfaceMethod java/util/Iterator.next:()Ljava/lang/Object;
      29: checkcast     #11                 // class org/apache/hadoop/hbase/util/Pair
      32: astore_3
      33: invokestatic  #51                 // Method org/apache/hadoop/hbase/shaded/protobuf/generated/HBaseProtos$BytesBytesPair.newBuilder:()Lorg/apache/hadoop/hbase/shaded/protobuf/generated/HBaseProtos$BytesBytesPair$Builder;
      36: astore        4
      38: aload         4
      40: aload_3
      41: invokevirtual #12                 // Method org/apache/hadoop/hbase/util/Pair.getFirst:()Ljava/lang/Object;
      44: checkcast     #13                 // class "[B"
      47: invokestatic  #52                 // Method org/apache/hbase/thirdparty/com/google/protobuf/UnsafeByteOperations.unsafeWrap:([B)Lorg/apache/hbase/thirdparty/com/google/protobuf/ByteString;
      50: invokevirtual #53                 // Method org/apache/hadoop/hbase/shaded/protobuf/generated/HBaseProtos$BytesBytesPair$Builder.setFirst:(Lorg/apache/hbase/thirdparty/com/google/protobuf/ByteString;)Lorg/apache/hadoop/hbase/shaded/protobuf/generated/HBaseProtos$BytesBytesPair$Builder;
      53: pop
      54: aload         4
      56: aload_3
      57: invokevirtual #14                 // Method org/apache/hadoop/hbase/util/Pair.getSecond:()Ljava/lang/Object;
      60: checkcast     #13                 // class "[B"
      63: invokestatic  #52                 // Method org/apache/hbase/thirdparty/com/google/protobuf/UnsafeByteOperations.unsafeWrap:([B)Lorg/apache/hbase/thirdparty/com/google/protobuf/ByteString;
      66: invokevirtual #54                 // Method org/apache/hadoop/hbase/shaded/protobuf/generated/HBaseProtos$BytesBytesPair$Builder.setSecond:(Lorg/apache/hbase/thirdparty/com/google/protobuf/ByteString;)Lorg/apache/hadoop/hbase/shaded/protobuf/generated/HBaseProtos$BytesBytesPair$Builder;
      69: pop
      70: aload_1
      71: aload         4
      73: invokevirtual #55                 // Method org/apache/hadoop/hbase/shaded/protobuf/generated/FilterProtos$FuzzyRowFilter$Builder.addFuzzyKeysData:(Lorg/apache/hadoop/hbase/shaded/protobuf/generated/HBaseProtos$BytesBytesPair$Builder;)Lorg/apache/hadoop/hbase/shaded/protobuf/generated/FilterProtos$FuzzyRowFilter$Builder;
      76: pop
      77: goto          14
      80: aload_1
      81: invokevirtual #56                 // Method org/apache/hadoop/hbase/shaded/protobuf/generated/FilterProtos$FuzzyRowFilter$Builder.build:()Lorg/apache/hadoop/hbase/shaded/protobuf/generated/FilterProtos$FuzzyRowFilter;
      84: invokevirtual #57                 // Method org/apache/hadoop/hbase/shaded/protobuf/generated/FilterProtos$FuzzyRowFilter.toByteArray:()[B
      87: areturn

  public static org.apache.hadoop.hbase.filter.FuzzyRowFilter parseFrom(byte[]) throws org.apache.hadoop.hbase.exceptions.DeserializationException;
    Code:
       0: aload_0
       1: invokestatic  #58                 // Method org/apache/hadoop/hbase/shaded/protobuf/generated/FilterProtos$FuzzyRowFilter.parseFrom:([B)Lorg/apache/hadoop/hbase/shaded/protobuf/generated/FilterProtos$FuzzyRowFilter;
       4: astore_1
       5: goto          18
       8: astore_2
       9: new           #60                 // class org/apache/hadoop/hbase/exceptions/DeserializationException
      12: dup
      13: aload_2
      14: invokespecial #61                 // Method org/apache/hadoop/hbase/exceptions/DeserializationException."<init>":(Ljava/lang/Throwable;)V
      17: athrow
      18: aload_1
      19: invokevirtual #62                 // Method org/apache/hadoop/hbase/shaded/protobuf/generated/FilterProtos$FuzzyRowFilter.getFuzzyKeysDataCount:()I
      22: istore_2
      23: new           #5                  // class java/util/ArrayList
      26: dup
      27: iload_2
      28: invokespecial #7                  // Method java/util/ArrayList."<init>":(I)V
      31: astore_3
      32: iconst_0
      33: istore        4
      35: iload         4
      37: iload_2
      38: if_icmpge     91
      41: aload_1
      42: iload         4
      44: invokevirtual #63                 // Method org/apache/hadoop/hbase/shaded/protobuf/generated/FilterProtos$FuzzyRowFilter.getFuzzyKeysData:(I)Lorg/apache/hadoop/hbase/shaded/protobuf/generated/HBaseProtos$BytesBytesPair;
      47: astore        5
      49: aload         5
      51: invokevirtual #64                 // Method org/apache/hadoop/hbase/shaded/protobuf/generated/HBaseProtos$BytesBytesPair.getFirst:()Lorg/apache/hbase/thirdparty/com/google/protobuf/ByteString;
      54: invokevirtual #65                 // Method org/apache/hbase/thirdparty/com/google/protobuf/ByteString.toByteArray:()[B
      57: astore        6
      59: aload         5
      61: invokevirtual #66                 // Method org/apache/hadoop/hbase/shaded/protobuf/generated/HBaseProtos$BytesBytesPair.getSecond:()Lorg/apache/hbase/thirdparty/com/google/protobuf/ByteString;
      64: invokevirtual #65                 // Method org/apache/hbase/thirdparty/com/google/protobuf/ByteString.toByteArray:()[B
      67: astore        7
      69: aload_3
      70: new           #11                 // class org/apache/hadoop/hbase/util/Pair
      73: dup
      74: aload         6
      76: aload         7
      78: invokespecial #16                 // Method org/apache/hadoop/hbase/util/Pair."<init>":(Ljava/lang/Object;Ljava/lang/Object;)V
      81: invokevirtual #67                 // Method java/util/ArrayList.add:(Ljava/lang/Object;)Z
      84: pop
      85: iinc          4, 1
      88: goto          35
      91: new           #68                 // class org/apache/hadoop/hbase/filter/FuzzyRowFilter
      94: dup
      95: aload_3
      96: invokespecial #69                 // Method "<init>":(Ljava/util/List;)V
      99: areturn
    Exception table:
       from    to  target type
           0     5     8   Class org/apache/hbase/thirdparty/com/google/protobuf/InvalidProtocolBufferException

  public java.lang.String toString();
    Code:
       0: new           #18                 // class java/lang/StringBuilder
       3: dup
       4: invokespecial #19                 // Method java/lang/StringBuilder."<init>":()V
       7: astore_1
       8: aload_1
       9: ldc           #70                 // String FuzzyRowFilter
      11: invokevirtual #21                 // Method java/lang/StringBuilder.append:(Ljava/lang/String;)Ljava/lang/StringBuilder;
      14: pop
      15: aload_1
      16: ldc           #71                 // String {fuzzyKeysData=
      18: invokevirtual #21                 // Method java/lang/StringBuilder.append:(Ljava/lang/String;)Ljava/lang/StringBuilder;
      21: pop
      22: aload_0
      23: getfield      #1                  // Field fuzzyKeysData:Ljava/util/List;
      26: invokeinterface #8,  1            // InterfaceMethod java/util/List.iterator:()Ljava/util/Iterator;
      31: astore_2
      32: aload_2
      33: invokeinterface #9,  1            // InterfaceMethod java/util/Iterator.hasNext:()Z
      38: ifeq          99
      41: aload_2
      42: invokeinterface #10,  1           // InterfaceMethod java/util/Iterator.next:()Ljava/lang/Object;
      47: checkcast     #11                 // class org/apache/hadoop/hbase/util/Pair
      50: astore_3
      51: aload_1
      52: bipush        123
      54: invokevirtual #72                 // Method java/lang/StringBuilder.append:(C)Ljava/lang/StringBuilder;
      57: aload_3
      58: invokevirtual #12                 // Method org/apache/hadoop/hbase/util/Pair.getFirst:()Ljava/lang/Object;
      61: checkcast     #13                 // class "[B"
      64: invokestatic  #15                 // Method org/apache/hadoop/hbase/util/Bytes.toStringBinary:([B)Ljava/lang/String;
      67: invokevirtual #21                 // Method java/lang/StringBuilder.append:(Ljava/lang/String;)Ljava/lang/StringBuilder;
      70: ldc           #73                 // String :
      72: invokevirtual #21                 // Method java/lang/StringBuilder.append:(Ljava/lang/String;)Ljava/lang/StringBuilder;
      75: pop
      76: aload_1
      77: aload_3
      78: invokevirtual #14                 // Method org/apache/hadoop/hbase/util/Pair.getSecond:()Ljava/lang/Object;
      81: checkcast     #13                 // class "[B"
      84: invokestatic  #15                 // Method org/apache/hadoop/hbase/util/Bytes.toStringBinary:([B)Ljava/lang/String;
      87: invokevirtual #21                 // Method java/lang/StringBuilder.append:(Ljava/lang/String;)Ljava/lang/StringBuilder;
      90: bipush        125
      92: invokevirtual #72                 // Method java/lang/StringBuilder.append:(C)Ljava/lang/StringBuilder;
      95: pop
      96: goto          32
      99: aload_1
     100: ldc           #74                 // String },
     102: invokevirtual #21                 // Method java/lang/StringBuilder.append:(Ljava/lang/String;)Ljava/lang/StringBuilder;
     105: pop
     106: aload_1
     107: invokevirtual #23                 // Method java/lang/StringBuilder.toString:()Ljava/lang/String;
     110: areturn

  static org.apache.hadoop.hbase.filter.FuzzyRowFilter$SatisfiesCode satisfies(byte[], byte[], byte[]);
    Code:
       0: iconst_0
       1: aload_0
       2: iconst_0
       3: aload_0
       4: arraylength
       5: aload_1
       6: aload_2
       7: invokestatic  #43                 // Method satisfies:(Z[BII[B[B)Lorg/apache/hadoop/hbase/filter/FuzzyRowFilter$SatisfiesCode;
      10: areturn

  static org.apache.hadoop.hbase.filter.FuzzyRowFilter$SatisfiesCode satisfies(boolean, byte[], byte[], byte[]);
    Code:
       0: iload_0
       1: aload_1
       2: iconst_0
       3: aload_1
       4: arraylength
       5: aload_2
       6: aload_3
       7: invokestatic  #43                 // Method satisfies:(Z[BII[B[B)Lorg/apache/hadoop/hbase/filter/FuzzyRowFilter$SatisfiesCode;
      10: areturn

  static org.apache.hadoop.hbase.filter.FuzzyRowFilter$SatisfiesCode satisfies(boolean, byte[], int, int, byte[], byte[]);
    Code:
       0: getstatic     #35                 // Field UNSAFE_UNALIGNED:Z
       3: ifne          18
       6: iload_0
       7: aload_1
       8: iload_2
       9: iload_3
      10: aload         4
      12: aload         5
      14: invokestatic  #75                 // Method satisfiesNoUnsafe:(Z[BII[B[B)Lorg/apache/hadoop/hbase/filter/FuzzyRowFilter$SatisfiesCode;
      17: areturn
      18: aload_1
      19: ifnonnull     26
      22: getstatic     #44                 // Field org/apache/hadoop/hbase/filter/FuzzyRowFilter$SatisfiesCode.YES:Lorg/apache/hadoop/hbase/filter/FuzzyRowFilter$SatisfiesCode;
      25: areturn
      26: iload_3
      27: aload         4
      29: arraylength
      30: invokestatic  #76                 // Method java/lang/Math.min:(II)I
      33: istore_3
      34: iload_3
      35: bipush        8
      37: idiv
      38: istore        6
      40: iload         6
      42: iconst_3
      43: ishl
      44: istore        7
      46: iconst_0
      47: istore        8
      49: iload         8
      51: iload         7
      53: if_icmpge     105
      56: aload         4
      58: iload         8
      60: invokestatic  #78                 // Method org/apache/hadoop/hbase/util/Bytes.toLong:([BI)J
      63: lstore        9
      65: aload         5
      67: iload         8
      69: invokestatic  #78                 // Method org/apache/hadoop/hbase/util/Bytes.toLong:([BI)J
      72: lstore        11
      74: aload_1
      75: iload_2
      76: iload         8
      78: iadd
      79: invokestatic  #78                 // Method org/apache/hadoop/hbase/util/Bytes.toLong:([BI)J
      82: lstore        13
      84: lload         13
      86: lload         11
      88: land
      89: lload         9
      91: lcmp
      92: ifeq          99
      95: getstatic     #79                 // Field org/apache/hadoop/hbase/filter/FuzzyRowFilter$SatisfiesCode.NEXT_EXISTS:Lorg/apache/hadoop/hbase/filter/FuzzyRowFilter$SatisfiesCode;
      98: areturn
      99: iinc          8, 8
     102: goto          49
     105: iload         7
     107: istore        8
     109: iload_3
     110: iload         8
     112: isub
     113: iconst_4
     114: if_icmplt     162
     117: aload         4
     119: iload         8
     121: invokestatic  #80                 // Method org/apache/hadoop/hbase/util/Bytes.toInt:([BI)I
     124: istore        9
     126: aload         5
     128: iload         8
     130: invokestatic  #80                 // Method org/apache/hadoop/hbase/util/Bytes.toInt:([BI)I
     133: istore        10
     135: aload_1
     136: iload_2
     137: iload         8
     139: iadd
     140: invokestatic  #80                 // Method org/apache/hadoop/hbase/util/Bytes.toInt:([BI)I
     143: istore        11
     145: iload         11
     147: iload         10
     149: iand
     150: iload         9
     152: if_icmpeq     159
     155: getstatic     #79                 // Field org/apache/hadoop/hbase/filter/FuzzyRowFilter$SatisfiesCode.NEXT_EXISTS:Lorg/apache/hadoop/hbase/filter/FuzzyRowFilter$SatisfiesCode;
     158: areturn
     159: iinc          8, 4
     162: iload_3
     163: iload         8
     165: isub
     166: iconst_2
     167: if_icmplt     215
     170: aload         4
     172: iload         8
     174: invokestatic  #81                 // Method org/apache/hadoop/hbase/util/Bytes.toShort:([BI)S
     177: istore        9
     179: aload         5
     181: iload         8
     183: invokestatic  #81                 // Method org/apache/hadoop/hbase/util/Bytes.toShort:([BI)S
     186: istore        10
     188: aload_1
     189: iload_2
     190: iload         8
     192: iadd
     193: invokestatic  #81                 // Method org/apache/hadoop/hbase/util/Bytes.toShort:([BI)S
     196: istore        11
     198: iload         11
     200: iload         10
     202: iand
     203: iload         9
     205: if_icmpeq     212
     208: getstatic     #79                 // Field org/apache/hadoop/hbase/filter/FuzzyRowFilter$SatisfiesCode.NEXT_EXISTS:Lorg/apache/hadoop/hbase/filter/FuzzyRowFilter$SatisfiesCode;
     211: areturn
     212: iinc          8, 2
     215: iload_3
     216: iload         8
     218: isub
     219: iconst_1
     220: if_icmplt     271
     223: aload         4
     225: iload         8
     227: baload
     228: sipush        255
     231: iand
     232: istore        9
     234: aload         5
     236: iload         8
     238: baload
     239: sipush        255
     242: iand
     243: istore        10
     245: aload_1
     246: iload_2
     247: iload         8
     249: iadd
     250: baload
     251: sipush        255
     254: iand
     255: istore        11
     257: iload         11
     259: iload         10
     261: iand
     262: iload         9
     264: if_icmpeq     271
     267: getstatic     #79                 // Field org/apache/hadoop/hbase/filter/FuzzyRowFilter$SatisfiesCode.NEXT_EXISTS:Lorg/apache/hadoop/hbase/filter/FuzzyRowFilter$SatisfiesCode;
     270: areturn
     271: getstatic     #44                 // Field org/apache/hadoop/hbase/filter/FuzzyRowFilter$SatisfiesCode.YES:Lorg/apache/hadoop/hbase/filter/FuzzyRowFilter$SatisfiesCode;
     274: areturn

  static org.apache.hadoop.hbase.filter.FuzzyRowFilter$SatisfiesCode satisfiesNoUnsafe(boolean, byte[], int, int, byte[], byte[]);
    Code:
       0: aload_1
       1: ifnonnull     8
       4: getstatic     #44                 // Field org/apache/hadoop/hbase/filter/FuzzyRowFilter$SatisfiesCode.YES:Lorg/apache/hadoop/hbase/filter/FuzzyRowFilter$SatisfiesCode;
       7: areturn
       8: iload_0
       9: invokestatic  #82                 // Method org/apache/hadoop/hbase/filter/FuzzyRowFilter$Order.orderFor:(Z)Lorg/apache/hadoop/hbase/filter/FuzzyRowFilter$Order;
      12: astore        6
      14: iconst_0
      15: istore        7
      17: iconst_0
      18: istore        8
      20: iload         8
      22: aload         5
      24: arraylength
      25: if_icmpge     179
      28: iload         8
      30: iload_3
      31: if_icmpge     179
      34: aload         5
      36: iload         8
      38: baload
      39: ifne          46
      42: iconst_1
      43: goto          47
      46: iconst_0
      47: istore        9
      49: iload         9
      51: ifeq          72
      54: aload         4
      56: iload         8
      58: baload
      59: aload_1
      60: iload         8
      62: iload_2
      63: iadd
      64: baload
      65: if_icmpeq     72
      68: iconst_1
      69: goto          73
      72: iconst_0
      73: istore        10
      75: iload         10
      77: ifeq          148
      80: iload         7
      82: ifeq          89
      85: getstatic     #79                 // Field org/apache/hadoop/hbase/filter/FuzzyRowFilter$SatisfiesCode.NEXT_EXISTS:Lorg/apache/hadoop/hbase/filter/FuzzyRowFilter$SatisfiesCode;
      88: areturn
      89: aload_1
      90: iload         8
      92: iload_2
      93: iadd
      94: baload
      95: sipush        255
      98: iand
      99: aload         4
     101: iload         8
     103: baload
     104: sipush        255
     107: iand
     108: if_icmpge     115
     111: iconst_1
     112: goto          116
     115: iconst_0
     116: istore        11
     118: iload         11
     120: ifeq          131
     123: iload_0
     124: ifne          131
     127: getstatic     #79                 // Field org/apache/hadoop/hbase/filter/FuzzyRowFilter$SatisfiesCode.NEXT_EXISTS:Lorg/apache/hadoop/hbase/filter/FuzzyRowFilter$SatisfiesCode;
     130: areturn
     131: iload         11
     133: ifne          144
     136: iload_0
     137: ifeq          144
     140: getstatic     #79                 // Field org/apache/hadoop/hbase/filter/FuzzyRowFilter$SatisfiesCode.NEXT_EXISTS:Lorg/apache/hadoop/hbase/filter/FuzzyRowFilter$SatisfiesCode;
     143: areturn
     144: getstatic     #83                 // Field org/apache/hadoop/hbase/filter/FuzzyRowFilter$SatisfiesCode.NO_NEXT:Lorg/apache/hadoop/hbase/filter/FuzzyRowFilter$SatisfiesCode;
     147: areturn
     148: aload         5
     150: iload         8
     152: baload
     153: iconst_1
     154: if_icmpne     173
     157: aload         6
     159: aload         4
     161: iload         8
     163: baload
     164: invokevirtual #84                 // Method org/apache/hadoop/hbase/filter/FuzzyRowFilter$Order.isMax:(B)Z
     167: ifne          173
     170: iconst_1
     171: istore        7
     173: iinc          8, 1
     176: goto          20
     179: getstatic     #44                 // Field org/apache/hadoop/hbase/filter/FuzzyRowFilter$SatisfiesCode.YES:Lorg/apache/hadoop/hbase/filter/FuzzyRowFilter$SatisfiesCode;
     182: areturn

  static byte[] getNextForFuzzyRule(byte[], byte[], byte[]);
    Code:
       0: iconst_0
       1: aload_0
       2: iconst_0
       3: aload_0
       4: arraylength
       5: aload_1
       6: aload_2
       7: invokestatic  #85                 // Method getNextForFuzzyRule:(Z[BII[B[B)[B
      10: areturn

  static byte[] getNextForFuzzyRule(boolean, byte[], byte[], byte[]);
    Code:
       0: iload_0
       1: aload_1
       2: iconst_0
       3: aload_1
       4: arraylength
       5: aload_2
       6: aload_3
       7: invokestatic  #85                 // Method getNextForFuzzyRule:(Z[BII[B[B)[B
      10: areturn

  static byte[] getNextForFuzzyRule(boolean, byte[], int, int, byte[], byte[]);
    Code:
       0: aload         4
       2: iload_3
       3: aload         4
       5: arraylength
       6: if_icmple     13
       9: iload_3
      10: goto          16
      13: aload         4
      15: arraylength
      16: invokestatic  #26                 // Method java/util/Arrays.copyOf:([BI)[B
      19: astore        6
      21: iload_0
      22: ifeq          57
      25: iload_3
      26: aload         4
      28: arraylength
      29: if_icmple     57
      32: aload         4
      34: arraylength
      35: istore        7
      37: iload         7
      39: aload         6
      41: arraylength
      42: if_icmpge     57
      45: aload         6
      47: iload         7
      49: iconst_m1
      50: bastore
      51: iinc          7, 1
      54: goto          37
      57: iconst_m1
      58: istore        7
      60: iload_0
      61: invokestatic  #82                 // Method org/apache/hadoop/hbase/filter/FuzzyRowFilter$Order.orderFor:(Z)Lorg/apache/hadoop/hbase/filter/FuzzyRowFilter$Order;
      64: astore        8
      66: iconst_0
      67: istore        9
      69: iconst_0
      70: istore        10
      72: iload         10
      74: aload         6
      76: arraylength
      77: if_icmpge     214
      80: iload         10
      82: aload         5
      84: arraylength
      85: if_icmpge     96
      88: aload         5
      90: iload         10
      92: baload
      93: ifne          128
      96: aload         6
      98: iload         10
     100: aload_1
     101: iload_2
     102: iload         10
     104: iadd
     105: baload
     106: bastore
     107: aload         8
     109: aload_1
     110: iload_2
     111: iload         10
     113: iadd
     114: baload
     115: invokevirtual #84                 // Method org/apache/hadoop/hbase/filter/FuzzyRowFilter$Order.isMax:(B)Z
     118: ifne          208
     121: iload         10
     123: istore        7
     125: goto          208
     128: iload         10
     130: aload         5
     132: arraylength
     133: if_icmpge     208
     136: aload         5
     138: iload         10
     140: baload
     141: iconst_m1
     142: if_icmpne     208
     145: aload         8
     147: aload_1
     148: iload         10
     150: iload_2
     151: iadd
     152: baload
     153: sipush        255
     156: iand
     157: aload         4
     159: iload         10
     161: baload
     162: sipush        255
     165: iand
     166: invokevirtual #86                 // Method org/apache/hadoop/hbase/filter/FuzzyRowFilter$Order.lt:(II)Z
     169: ifeq          178
     172: iconst_1
     173: istore        9
     175: goto          214
     178: aload         8
     180: aload_1
     181: iload         10
     183: iload_2
     184: iadd
     185: baload
     186: sipush        255
     189: iand
     190: aload         4
     192: iload         10
     194: baload
     195: sipush        255
     198: iand
     199: invokevirtual #87                 // Method org/apache/hadoop/hbase/filter/FuzzyRowFilter$Order.gt:(II)Z
     202: ifeq          208
     205: goto          214
     208: iinc          10, 1
     211: goto          72
     214: iload         9
     216: ifne          287
     219: iload         7
     221: ifge          226
     224: aconst_null
     225: areturn
     226: aload         6
     228: iload         7
     230: aload         8
     232: aload         6
     234: iload         7
     236: baload
     237: invokevirtual #88                 // Method org/apache/hadoop/hbase/filter/FuzzyRowFilter$Order.inc:(B)B
     240: bastore
     241: iload         7
     243: iconst_1
     244: iadd
     245: istore        10
     247: iload         10
     249: aload         6
     251: arraylength
     252: if_icmpge     287
     255: iload         10
     257: aload         5
     259: arraylength
     260: if_icmpge     271
     263: aload         5
     265: iload         10
     267: baload
     268: ifne          281
     271: aload         6
     273: iload         10
     275: aload         8
     277: invokevirtual #89                 // Method org/apache/hadoop/hbase/filter/FuzzyRowFilter$Order.min:()B
     280: bastore
     281: iinc          10, 1
     284: goto          247
     287: iload_0
     288: ifeq          296
     291: aload         6
     293: goto          305
     296: aload         6
     298: aload         5
     300: iload         7
     302: invokestatic  #90                 // Method trimTrailingZeroes:([B[BI)[B
     305: areturn

  boolean areSerializedFieldsEqual(org.apache.hadoop.hbase.filter.Filter);
    Code:
       0: aload_1
       1: aload_0
       2: if_acmpne     7
       5: iconst_1
       6: ireturn
       7: aload_1
       8: instanceof    #68                 // class org/apache/hadoop/hbase/filter/FuzzyRowFilter
      11: ifne          16
      14: iconst_0
      15: ireturn
      16: aload_1
      17: checkcast     #68                 // class org/apache/hadoop/hbase/filter/FuzzyRowFilter
      20: astore_2
      21: aload_0
      22: getfield      #1                  // Field fuzzyKeysData:Ljava/util/List;
      25: invokeinterface #6,  1            // InterfaceMethod java/util/List.size:()I
      30: aload_2
      31: getfield      #1                  // Field fuzzyKeysData:Ljava/util/List;
      34: invokeinterface #6,  1            // InterfaceMethod java/util/List.size:()I
      39: if_icmpeq     44
      42: iconst_0
      43: ireturn
      44: iconst_0
      45: istore_3
      46: iload_3
      47: aload_0
      48: getfield      #1                  // Field fuzzyKeysData:Ljava/util/List;
      51: invokeinterface #6,  1            // InterfaceMethod java/util/List.size:()I
      56: if_icmpge     141
      59: aload_0
      60: getfield      #1                  // Field fuzzyKeysData:Ljava/util/List;
      63: iload_3
      64: invokeinterface #38,  2           // InterfaceMethod java/util/List.get:(I)Ljava/lang/Object;
      69: checkcast     #11                 // class org/apache/hadoop/hbase/util/Pair
      72: astore        4
      74: aload_2
      75: getfield      #1                  // Field fuzzyKeysData:Ljava/util/List;
      78: iload_3
      79: invokeinterface #38,  2           // InterfaceMethod java/util/List.get:(I)Ljava/lang/Object;
      84: checkcast     #11                 // class org/apache/hadoop/hbase/util/Pair
      87: astore        5
      89: aload         4
      91: invokevirtual #12                 // Method org/apache/hadoop/hbase/util/Pair.getFirst:()Ljava/lang/Object;
      94: checkcast     #13                 // class "[B"
      97: aload         5
      99: invokevirtual #12                 // Method org/apache/hadoop/hbase/util/Pair.getFirst:()Ljava/lang/Object;
     102: checkcast     #13                 // class "[B"
     105: invokestatic  #92                 // Method org/apache/hadoop/hbase/util/Bytes.equals:([B[B)Z
     108: ifeq          133
     111: aload         4
     113: invokevirtual #14                 // Method org/apache/hadoop/hbase/util/Pair.getSecond:()Ljava/lang/Object;
     116: checkcast     #13                 // class "[B"
     119: aload         5
     121: invokevirtual #14                 // Method org/apache/hadoop/hbase/util/Pair.getSecond:()Ljava/lang/Object;
     124: checkcast     #13                 // class "[B"
     127: invokestatic  #92                 // Method org/apache/hadoop/hbase/util/Bytes.equals:([B[B)Z
     130: ifne          135
     133: iconst_0
     134: ireturn
     135: iinc          3, 1
     138: goto          46
     141: iconst_1
     142: ireturn

  public boolean equals(java.lang.Object);
    Code:
       0: aload_1
       1: instanceof    #93                 // class org/apache/hadoop/hbase/filter/Filter
       4: ifeq          22
       7: aload_0
       8: aload_1
       9: checkcast     #93                 // class org/apache/hadoop/hbase/filter/Filter
      12: invokevirtual #94                 // Method areSerializedFieldsEqual:(Lorg/apache/hadoop/hbase/filter/Filter;)Z
      15: ifeq          22
      18: iconst_1
      19: goto          23
      22: iconst_0
      23: ireturn

  public int hashCode();
    Code:
       0: iconst_1
       1: anewarray     #95                 // class java/lang/Object
       4: dup
       5: iconst_0
       6: aload_0
       7: getfield      #1                  // Field fuzzyKeysData:Ljava/util/List;
      10: aastore
      11: invokestatic  #96                 // Method java/util/Objects.hash:([Ljava/lang/Object;)I
      14: ireturn

  static java.util.List access$000(org.apache.hadoop.hbase.filter.FuzzyRowFilter);
    Code:
       0: aload_0
       1: getfield      #1                  // Field fuzzyKeysData:Ljava/util/List;
       4: areturn

  static {};
    Code:
       0: invokestatic  #97                 // Method org/apache/hadoop/hbase/util/UnsafeAvailChecker.unaligned:()Z
       3: putstatic     #35                 // Field UNSAFE_UNALIGNED:Z
       6: return
}
