Compiled from "GlobalQuotaSettings.java"
public abstract class org.apache.hadoop.hbase.quotas.GlobalQuotaSettings extends org.apache.hadoop.hbase.quotas.QuotaSettings {
  protected org.apache.hadoop.hbase.quotas.GlobalQuotaSettings(java.lang.String, org.apache.hadoop.hbase.TableName, java.lang.String, java.lang.String);
    Code:
       0: aload_0
       1: aload_1
       2: aload_2
       3: aload_3
       4: aload         4
       6: invokespecial #1                  // Method org/apache/hadoop/hbase/quotas/QuotaSettings."<init>":(Ljava/lang/String;Lorg/apache/hadoop/hbase/TableName;Ljava/lang/String;Ljava/lang/String;)V
       9: return

  public abstract java.util.List<org.apache.hadoop.hbase.quotas.QuotaSettings> getQuotaSettings();

  public org.apache.hadoop.hbase.quotas.QuotaType getQuotaType();
    Code:
       0: new           #2                  // class java/lang/UnsupportedOperationException
       3: dup
       4: invokespecial #3                  // Method java/lang/UnsupportedOperationException."<init>":()V
       7: athrow

  protected void setupSetQuotaRequest(org.apache.hadoop.hbase.shaded.protobuf.generated.MasterProtos$SetQuotaRequest$Builder);
    Code:
       0: new           #2                  // class java/lang/UnsupportedOperationException
       3: dup
       4: ldc           #4                  // String This class should not be used to generate a SetQuotaRequest.
       6: invokespecial #5                  // Method java/lang/UnsupportedOperationException."<init>":(Ljava/lang/String;)V
       9: athrow
}
