Compiled from "HalfStoreFileReader.java"
class org.apache.hadoop.hbase.io.HalfStoreFileReader$1 implements org.apache.hadoop.hbase.io.hfile.HFileScanner {
  final org.apache.hadoop.hbase.io.hfile.HFileScanner delegate;

  public boolean atEnd;

  final org.apache.hadoop.hbase.io.hfile.HFileScanner val$s;

  final org.apache.hadoop.hbase.io.HalfStoreFileReader this$0;

  org.apache.hadoop.hbase.io.HalfStoreFileReader$1(org.apache.hadoop.hbase.io.HalfStoreFileReader, org.apache.hadoop.hbase.io.hfile.HFileScanner);
    Code:
       0: aload_0
       1: aload_1
       2: putfield      #1                  // Field this$0:Lorg/apache/hadoop/hbase/io/HalfStoreFileReader;
       5: aload_0
       6: aload_2
       7: putfield      #2                  // Field val$s:Lorg/apache/hadoop/hbase/io/hfile/HFileScanner;
      10: aload_0
      11: invokespecial #3                  // Method java/lang/Object."<init>":()V
      14: aload_0
      15: aload_0
      16: getfield      #2                  // Field val$s:Lorg/apache/hadoop/hbase/io/hfile/HFileScanner;
      19: putfield      #4                  // Field delegate:Lorg/apache/hadoop/hbase/io/hfile/HFileScanner;
      22: aload_0
      23: iconst_0
      24: putfield      #5                  // Field atEnd:Z
      27: return

  public org.apache.hadoop.hbase.Cell getKey();
    Code:
       0: aload_0
       1: getfield      #5                  // Field atEnd:Z
       4: ifeq          9
       7: aconst_null
       8: areturn
       9: aload_0
      10: getfield      #4                  // Field delegate:Lorg/apache/hadoop/hbase/io/hfile/HFileScanner;
      13: invokeinterface #6,  1            // InterfaceMethod org/apache/hadoop/hbase/io/hfile/HFileScanner.getKey:()Lorg/apache/hadoop/hbase/Cell;
      18: areturn

  public java.lang.String getKeyString();
    Code:
       0: aload_0
       1: getfield      #5                  // Field atEnd:Z
       4: ifeq          9
       7: aconst_null
       8: areturn
       9: aload_0
      10: getfield      #4                  // Field delegate:Lorg/apache/hadoop/hbase/io/hfile/HFileScanner;
      13: invokeinterface #7,  1            // InterfaceMethod org/apache/hadoop/hbase/io/hfile/HFileScanner.getKeyString:()Ljava/lang/String;
      18: areturn

  public java.nio.ByteBuffer getValue();
    Code:
       0: aload_0
       1: getfield      #5                  // Field atEnd:Z
       4: ifeq          9
       7: aconst_null
       8: areturn
       9: aload_0
      10: getfield      #4                  // Field delegate:Lorg/apache/hadoop/hbase/io/hfile/HFileScanner;
      13: invokeinterface #8,  1            // InterfaceMethod org/apache/hadoop/hbase/io/hfile/HFileScanner.getValue:()Ljava/nio/ByteBuffer;
      18: areturn

  public java.lang.String getValueString();
    Code:
       0: aload_0
       1: getfield      #5                  // Field atEnd:Z
       4: ifeq          9
       7: aconst_null
       8: areturn
       9: aload_0
      10: getfield      #4                  // Field delegate:Lorg/apache/hadoop/hbase/io/hfile/HFileScanner;
      13: invokeinterface #9,  1            // InterfaceMethod org/apache/hadoop/hbase/io/hfile/HFileScanner.getValueString:()Ljava/lang/String;
      18: areturn

  public org.apache.hadoop.hbase.Cell getCell();
    Code:
       0: aload_0
       1: getfield      #5                  // Field atEnd:Z
       4: ifeq          9
       7: aconst_null
       8: areturn
       9: aload_0
      10: getfield      #4                  // Field delegate:Lorg/apache/hadoop/hbase/io/hfile/HFileScanner;
      13: invokeinterface #10,  1           // InterfaceMethod org/apache/hadoop/hbase/io/hfile/HFileScanner.getCell:()Lorg/apache/hadoop/hbase/Cell;
      18: areturn

  public boolean next() throws java.io.IOException;
    Code:
       0: aload_0
       1: getfield      #5                  // Field atEnd:Z
       4: ifeq          9
       7: iconst_0
       8: ireturn
       9: aload_0
      10: getfield      #4                  // Field delegate:Lorg/apache/hadoop/hbase/io/hfile/HFileScanner;
      13: invokeinterface #11,  1           // InterfaceMethod org/apache/hadoop/hbase/io/hfile/HFileScanner.next:()Z
      18: istore_1
      19: iload_1
      20: ifne          25
      23: iload_1
      24: ireturn
      25: aload_0
      26: getfield      #1                  // Field this$0:Lorg/apache/hadoop/hbase/io/HalfStoreFileReader;
      29: getfield      #12                 // Field org/apache/hadoop/hbase/io/HalfStoreFileReader.top:Z
      32: ifne          68
      35: aload_0
      36: getfield      #1                  // Field this$0:Lorg/apache/hadoop/hbase/io/HalfStoreFileReader;
      39: invokevirtual #13                 // Method org/apache/hadoop/hbase/io/HalfStoreFileReader.getComparator:()Lorg/apache/hadoop/hbase/CellComparator;
      42: aload_0
      43: getfield      #1                  // Field this$0:Lorg/apache/hadoop/hbase/io/HalfStoreFileReader;
      46: invokestatic  #14                 // Method org/apache/hadoop/hbase/io/HalfStoreFileReader.access$000:(Lorg/apache/hadoop/hbase/io/HalfStoreFileReader;)Lorg/apache/hadoop/hbase/Cell;
      49: aload_0
      50: invokevirtual #15                 // Method getKey:()Lorg/apache/hadoop/hbase/Cell;
      53: invokeinterface #16,  3           // InterfaceMethod org/apache/hadoop/hbase/CellComparator.compare:(Lorg/apache/hadoop/hbase/Cell;Lorg/apache/hadoop/hbase/Cell;)I
      58: ifgt          68
      61: aload_0
      62: iconst_1
      63: putfield      #5                  // Field atEnd:Z
      66: iconst_0
      67: ireturn
      68: iconst_1
      69: ireturn

  public boolean seekTo() throws java.io.IOException;
    Code:
       0: aload_0
       1: getfield      #1                  // Field this$0:Lorg/apache/hadoop/hbase/io/HalfStoreFileReader;
       4: getfield      #12                 // Field org/apache/hadoop/hbase/io/HalfStoreFileReader.top:Z
       7: ifeq          65
      10: aload_0
      11: getfield      #4                  // Field delegate:Lorg/apache/hadoop/hbase/io/hfile/HFileScanner;
      14: aload_0
      15: getfield      #1                  // Field this$0:Lorg/apache/hadoop/hbase/io/HalfStoreFileReader;
      18: invokestatic  #14                 // Method org/apache/hadoop/hbase/io/HalfStoreFileReader.access$000:(Lorg/apache/hadoop/hbase/io/HalfStoreFileReader;)Lorg/apache/hadoop/hbase/Cell;
      21: invokeinterface #17,  2           // InterfaceMethod org/apache/hadoop/hbase/io/hfile/HFileScanner.seekTo:(Lorg/apache/hadoop/hbase/Cell;)I
      26: istore_1
      27: iload_1
      28: bipush        -2
      30: if_icmpne     35
      33: iconst_1
      34: ireturn
      35: iload_1
      36: ifge          49
      39: aload_0
      40: getfield      #4                  // Field delegate:Lorg/apache/hadoop/hbase/io/hfile/HFileScanner;
      43: invokeinterface #19,  1           // InterfaceMethod org/apache/hadoop/hbase/io/hfile/HFileScanner.seekTo:()Z
      48: ireturn
      49: iload_1
      50: ifle          63
      53: aload_0
      54: getfield      #4                  // Field delegate:Lorg/apache/hadoop/hbase/io/hfile/HFileScanner;
      57: invokeinterface #11,  1           // InterfaceMethod org/apache/hadoop/hbase/io/hfile/HFileScanner.next:()Z
      62: ireturn
      63: iconst_1
      64: ireturn
      65: aload_0
      66: getfield      #4                  // Field delegate:Lorg/apache/hadoop/hbase/io/hfile/HFileScanner;
      69: invokeinterface #19,  1           // InterfaceMethod org/apache/hadoop/hbase/io/hfile/HFileScanner.seekTo:()Z
      74: istore_1
      75: iload_1
      76: ifne          81
      79: iload_1
      80: ireturn
      81: aload_0
      82: getfield      #4                  // Field delegate:Lorg/apache/hadoop/hbase/io/hfile/HFileScanner;
      85: invokeinterface #20,  1           // InterfaceMethod org/apache/hadoop/hbase/io/hfile/HFileScanner.getReader:()Lorg/apache/hadoop/hbase/io/hfile/HFile$Reader;
      90: invokeinterface #21,  1           // InterfaceMethod org/apache/hadoop/hbase/io/hfile/HFile$Reader.getComparator:()Lorg/apache/hadoop/hbase/CellComparator;
      95: aload_0
      96: getfield      #1                  // Field this$0:Lorg/apache/hadoop/hbase/io/HalfStoreFileReader;
      99: invokestatic  #14                 // Method org/apache/hadoop/hbase/io/HalfStoreFileReader.access$000:(Lorg/apache/hadoop/hbase/io/HalfStoreFileReader;)Lorg/apache/hadoop/hbase/Cell;
     102: aload_0
     103: invokevirtual #15                 // Method getKey:()Lorg/apache/hadoop/hbase/Cell;
     106: invokeinterface #16,  3           // InterfaceMethod org/apache/hadoop/hbase/CellComparator.compare:(Lorg/apache/hadoop/hbase/Cell;Lorg/apache/hadoop/hbase/Cell;)I
     111: ifle          118
     114: iconst_1
     115: goto          119
     118: iconst_0
     119: ireturn

  public org.apache.hadoop.hbase.io.hfile.HFile$Reader getReader();
    Code:
       0: aload_0
       1: getfield      #4                  // Field delegate:Lorg/apache/hadoop/hbase/io/hfile/HFileScanner;
       4: invokeinterface #20,  1           // InterfaceMethod org/apache/hadoop/hbase/io/hfile/HFileScanner.getReader:()Lorg/apache/hadoop/hbase/io/hfile/HFile$Reader;
       9: areturn

  public boolean isSeeked();
    Code:
       0: aload_0
       1: getfield      #4                  // Field delegate:Lorg/apache/hadoop/hbase/io/hfile/HFileScanner;
       4: invokeinterface #22,  1           // InterfaceMethod org/apache/hadoop/hbase/io/hfile/HFileScanner.isSeeked:()Z
       9: ireturn

  public int seekTo(org.apache.hadoop.hbase.Cell) throws java.io.IOException;
    Code:
       0: aload_0
       1: getfield      #1                  // Field this$0:Lorg/apache/hadoop/hbase/io/HalfStoreFileReader;
       4: getfield      #12                 // Field org/apache/hadoop/hbase/io/HalfStoreFileReader.top:Z
       7: ifeq          33
      10: aload_0
      11: getfield      #1                  // Field this$0:Lorg/apache/hadoop/hbase/io/HalfStoreFileReader;
      14: invokevirtual #13                 // Method org/apache/hadoop/hbase/io/HalfStoreFileReader.getComparator:()Lorg/apache/hadoop/hbase/CellComparator;
      17: aload_1
      18: aload_0
      19: getfield      #1                  // Field this$0:Lorg/apache/hadoop/hbase/io/HalfStoreFileReader;
      22: invokestatic  #14                 // Method org/apache/hadoop/hbase/io/HalfStoreFileReader.access$000:(Lorg/apache/hadoop/hbase/io/HalfStoreFileReader;)Lorg/apache/hadoop/hbase/Cell;
      25: invokestatic  #23                 // Method org/apache/hadoop/hbase/PrivateCellUtil.compareKeyIgnoresMvcc:(Lorg/apache/hadoop/hbase/CellComparator;Lorg/apache/hadoop/hbase/Cell;Lorg/apache/hadoop/hbase/Cell;)I
      28: ifge          87
      31: iconst_m1
      32: ireturn
      33: aload_0
      34: getfield      #1                  // Field this$0:Lorg/apache/hadoop/hbase/io/HalfStoreFileReader;
      37: invokevirtual #13                 // Method org/apache/hadoop/hbase/io/HalfStoreFileReader.getComparator:()Lorg/apache/hadoop/hbase/CellComparator;
      40: aload_1
      41: aload_0
      42: getfield      #1                  // Field this$0:Lorg/apache/hadoop/hbase/io/HalfStoreFileReader;
      45: invokestatic  #14                 // Method org/apache/hadoop/hbase/io/HalfStoreFileReader.access$000:(Lorg/apache/hadoop/hbase/io/HalfStoreFileReader;)Lorg/apache/hadoop/hbase/Cell;
      48: invokestatic  #23                 // Method org/apache/hadoop/hbase/PrivateCellUtil.compareKeyIgnoresMvcc:(Lorg/apache/hadoop/hbase/CellComparator;Lorg/apache/hadoop/hbase/Cell;Lorg/apache/hadoop/hbase/Cell;)I
      51: iflt          87
      54: aload_0
      55: getfield      #4                  // Field delegate:Lorg/apache/hadoop/hbase/io/hfile/HFileScanner;
      58: aload_0
      59: getfield      #1                  // Field this$0:Lorg/apache/hadoop/hbase/io/HalfStoreFileReader;
      62: invokestatic  #14                 // Method org/apache/hadoop/hbase/io/HalfStoreFileReader.access$000:(Lorg/apache/hadoop/hbase/io/HalfStoreFileReader;)Lorg/apache/hadoop/hbase/Cell;
      65: invokeinterface #24,  2           // InterfaceMethod org/apache/hadoop/hbase/io/hfile/HFileScanner.seekBefore:(Lorg/apache/hadoop/hbase/Cell;)Z
      70: istore_2
      71: iload_2
      72: ifne          85
      75: new           #25                 // class java/io/IOException
      78: dup
      79: ldc           #26                 // String Seeking for a key in bottom of file, but key exists in top of file, failed on seekBefore(midkey)
      81: invokespecial #27                 // Method java/io/IOException."<init>":(Ljava/lang/String;)V
      84: athrow
      85: iconst_1
      86: ireturn
      87: aload_0
      88: getfield      #4                  // Field delegate:Lorg/apache/hadoop/hbase/io/hfile/HFileScanner;
      91: aload_1
      92: invokeinterface #17,  2           // InterfaceMethod org/apache/hadoop/hbase/io/hfile/HFileScanner.seekTo:(Lorg/apache/hadoop/hbase/Cell;)I
      97: ireturn

  public int reseekTo(org.apache.hadoop.hbase.Cell) throws java.io.IOException;
    Code:
       0: aload_0
       1: getfield      #1                  // Field this$0:Lorg/apache/hadoop/hbase/io/HalfStoreFileReader;
       4: getfield      #12                 // Field org/apache/hadoop/hbase/io/HalfStoreFileReader.top:Z
       7: ifeq          33
      10: aload_0
      11: getfield      #1                  // Field this$0:Lorg/apache/hadoop/hbase/io/HalfStoreFileReader;
      14: invokevirtual #13                 // Method org/apache/hadoop/hbase/io/HalfStoreFileReader.getComparator:()Lorg/apache/hadoop/hbase/CellComparator;
      17: aload_1
      18: aload_0
      19: getfield      #1                  // Field this$0:Lorg/apache/hadoop/hbase/io/HalfStoreFileReader;
      22: invokestatic  #14                 // Method org/apache/hadoop/hbase/io/HalfStoreFileReader.access$000:(Lorg/apache/hadoop/hbase/io/HalfStoreFileReader;)Lorg/apache/hadoop/hbase/Cell;
      25: invokestatic  #23                 // Method org/apache/hadoop/hbase/PrivateCellUtil.compareKeyIgnoresMvcc:(Lorg/apache/hadoop/hbase/CellComparator;Lorg/apache/hadoop/hbase/Cell;Lorg/apache/hadoop/hbase/Cell;)I
      28: ifge          87
      31: iconst_m1
      32: ireturn
      33: aload_0
      34: getfield      #1                  // Field this$0:Lorg/apache/hadoop/hbase/io/HalfStoreFileReader;
      37: invokevirtual #13                 // Method org/apache/hadoop/hbase/io/HalfStoreFileReader.getComparator:()Lorg/apache/hadoop/hbase/CellComparator;
      40: aload_1
      41: aload_0
      42: getfield      #1                  // Field this$0:Lorg/apache/hadoop/hbase/io/HalfStoreFileReader;
      45: invokestatic  #14                 // Method org/apache/hadoop/hbase/io/HalfStoreFileReader.access$000:(Lorg/apache/hadoop/hbase/io/HalfStoreFileReader;)Lorg/apache/hadoop/hbase/Cell;
      48: invokestatic  #23                 // Method org/apache/hadoop/hbase/PrivateCellUtil.compareKeyIgnoresMvcc:(Lorg/apache/hadoop/hbase/CellComparator;Lorg/apache/hadoop/hbase/Cell;Lorg/apache/hadoop/hbase/Cell;)I
      51: iflt          87
      54: aload_0
      55: getfield      #4                  // Field delegate:Lorg/apache/hadoop/hbase/io/hfile/HFileScanner;
      58: aload_0
      59: getfield      #1                  // Field this$0:Lorg/apache/hadoop/hbase/io/HalfStoreFileReader;
      62: invokestatic  #14                 // Method org/apache/hadoop/hbase/io/HalfStoreFileReader.access$000:(Lorg/apache/hadoop/hbase/io/HalfStoreFileReader;)Lorg/apache/hadoop/hbase/Cell;
      65: invokeinterface #24,  2           // InterfaceMethod org/apache/hadoop/hbase/io/hfile/HFileScanner.seekBefore:(Lorg/apache/hadoop/hbase/Cell;)Z
      70: istore_2
      71: iload_2
      72: ifne          85
      75: new           #25                 // class java/io/IOException
      78: dup
      79: ldc           #26                 // String Seeking for a key in bottom of file, but key exists in top of file, failed on seekBefore(midkey)
      81: invokespecial #27                 // Method java/io/IOException."<init>":(Ljava/lang/String;)V
      84: athrow
      85: iconst_1
      86: ireturn
      87: aload_0
      88: getfield      #5                  // Field atEnd:Z
      91: ifeq          96
      94: iconst_1
      95: ireturn
      96: aload_0
      97: getfield      #4                  // Field delegate:Lorg/apache/hadoop/hbase/io/hfile/HFileScanner;
     100: aload_1
     101: invokeinterface #28,  2           // InterfaceMethod org/apache/hadoop/hbase/io/hfile/HFileScanner.reseekTo:(Lorg/apache/hadoop/hbase/Cell;)I
     106: ireturn

  public boolean seekBefore(org.apache.hadoop.hbase.Cell) throws java.io.IOException;
    Code:
       0: aload_0
       1: getfield      #1                  // Field this$0:Lorg/apache/hadoop/hbase/io/HalfStoreFileReader;
       4: getfield      #12                 // Field org/apache/hadoop/hbase/io/HalfStoreFileReader.top:Z
       7: ifeq          51
      10: aload_0
      11: getfield      #1                  // Field this$0:Lorg/apache/hadoop/hbase/io/HalfStoreFileReader;
      14: invokevirtual #29                 // Method org/apache/hadoop/hbase/io/HalfStoreFileReader.getFirstKey:()Ljava/util/Optional;
      17: astore_2
      18: aload_2
      19: invokevirtual #30                 // Method java/util/Optional.isPresent:()Z
      22: ifeq          48
      25: aload_0
      26: getfield      #1                  // Field this$0:Lorg/apache/hadoop/hbase/io/HalfStoreFileReader;
      29: invokevirtual #13                 // Method org/apache/hadoop/hbase/io/HalfStoreFileReader.getComparator:()Lorg/apache/hadoop/hbase/CellComparator;
      32: aload_1
      33: aload_2
      34: invokevirtual #31                 // Method java/util/Optional.get:()Ljava/lang/Object;
      37: checkcast     #32                 // class org/apache/hadoop/hbase/Cell
      40: invokestatic  #23                 // Method org/apache/hadoop/hbase/PrivateCellUtil.compareKeyIgnoresMvcc:(Lorg/apache/hadoop/hbase/CellComparator;Lorg/apache/hadoop/hbase/Cell;Lorg/apache/hadoop/hbase/Cell;)I
      43: ifgt          48
      46: iconst_0
      47: ireturn
      48: goto          100
      51: aload_0
      52: getfield      #1                  // Field this$0:Lorg/apache/hadoop/hbase/io/HalfStoreFileReader;
      55: invokevirtual #13                 // Method org/apache/hadoop/hbase/io/HalfStoreFileReader.getComparator:()Lorg/apache/hadoop/hbase/CellComparator;
      58: aload_1
      59: aload_0
      60: getfield      #1                  // Field this$0:Lorg/apache/hadoop/hbase/io/HalfStoreFileReader;
      63: invokestatic  #14                 // Method org/apache/hadoop/hbase/io/HalfStoreFileReader.access$000:(Lorg/apache/hadoop/hbase/io/HalfStoreFileReader;)Lorg/apache/hadoop/hbase/Cell;
      66: invokestatic  #23                 // Method org/apache/hadoop/hbase/PrivateCellUtil.compareKeyIgnoresMvcc:(Lorg/apache/hadoop/hbase/CellComparator;Lorg/apache/hadoop/hbase/Cell;Lorg/apache/hadoop/hbase/Cell;)I
      69: iflt          100
      72: aload_0
      73: getfield      #4                  // Field delegate:Lorg/apache/hadoop/hbase/io/hfile/HFileScanner;
      76: aload_0
      77: getfield      #1                  // Field this$0:Lorg/apache/hadoop/hbase/io/HalfStoreFileReader;
      80: invokestatic  #14                 // Method org/apache/hadoop/hbase/io/HalfStoreFileReader.access$000:(Lorg/apache/hadoop/hbase/io/HalfStoreFileReader;)Lorg/apache/hadoop/hbase/Cell;
      83: invokeinterface #24,  2           // InterfaceMethod org/apache/hadoop/hbase/io/hfile/HFileScanner.seekBefore:(Lorg/apache/hadoop/hbase/Cell;)Z
      88: istore_2
      89: iload_2
      90: ifeq          98
      93: aload_0
      94: iconst_0
      95: putfield      #5                  // Field atEnd:Z
      98: iload_2
      99: ireturn
     100: aload_0
     101: getfield      #4                  // Field delegate:Lorg/apache/hadoop/hbase/io/hfile/HFileScanner;
     104: aload_1
     105: invokeinterface #24,  2           // InterfaceMethod org/apache/hadoop/hbase/io/hfile/HFileScanner.seekBefore:(Lorg/apache/hadoop/hbase/Cell;)Z
     110: istore_2
     111: iload_2
     112: ifeq          120
     115: aload_0
     116: iconst_0
     117: putfield      #5                  // Field atEnd:Z
     120: iload_2
     121: ireturn

  public org.apache.hadoop.hbase.Cell getNextIndexedKey();
    Code:
       0: aconst_null
       1: areturn

  public void close();
    Code:
       0: aload_0
       1: getfield      #4                  // Field delegate:Lorg/apache/hadoop/hbase/io/hfile/HFileScanner;
       4: invokeinterface #33,  1           // InterfaceMethod org/apache/hadoop/hbase/io/hfile/HFileScanner.close:()V
       9: return

  public void shipped() throws java.io.IOException;
    Code:
       0: aload_0
       1: getfield      #4                  // Field delegate:Lorg/apache/hadoop/hbase/io/hfile/HFileScanner;
       4: invokeinterface #34,  1           // InterfaceMethod org/apache/hadoop/hbase/io/hfile/HFileScanner.shipped:()V
       9: return
}
