Compiled from "HalfStoreFileReader.java"
public class org.apache.hadoop.hbase.io.HalfStoreFileReader extends org.apache.hadoop.hbase.regionserver.StoreFileReader {
  final boolean top;

  protected final byte[] splitkey;

  public org.apache.hadoop.hbase.io.HalfStoreFileReader(org.apache.hadoop.fs.FileSystem, org.apache.hadoop.fs.Path, org.apache.hadoop.hbase.io.hfile.CacheConfig, org.apache.hadoop.hbase.io.Reference, boolean, java.util.concurrent.atomic.AtomicInteger, boolean, org.apache.hadoop.conf.Configuration) throws java.io.IOException;
    Code:
       0: aload_0
       1: aload_1
       2: aload_2
       3: aload_3
       4: iload         5
       6: aload         6
       8: iload         7
      10: aload         8
      12: invokespecial #2                  // Method org/apache/hadoop/hbase/regionserver/StoreFileReader."<init>":(Lorg/apache/hadoop/fs/FileSystem;Lorg/apache/hadoop/fs/Path;Lorg/apache/hadoop/hbase/io/hfile/CacheConfig;ZLjava/util/concurrent/atomic/AtomicInteger;ZLorg/apache/hadoop/conf/Configuration;)V
      15: aload_0
      16: invokestatic  #3                  // Method java/util/Optional.empty:()Ljava/util/Optional;
      19: putfield      #4                  // Field firstKey:Ljava/util/Optional;
      22: aload_0
      23: iconst_0
      24: putfield      #5                  // Field firstKeySeeked:Z
      27: aload_0
      28: aload         4
      30: invokevirtual #6                  // Method org/apache/hadoop/hbase/io/Reference.getSplitKey:()[B
      33: putfield      #7                  // Field splitkey:[B
      36: aload_0
      37: new           #8                  // class org/apache/hadoop/hbase/KeyValue$KeyOnlyKeyValue
      40: dup
      41: aload_0
      42: getfield      #7                  // Field splitkey:[B
      45: iconst_0
      46: aload_0
      47: getfield      #7                  // Field splitkey:[B
      50: arraylength
      51: invokespecial #9                  // Method org/apache/hadoop/hbase/KeyValue$KeyOnlyKeyValue."<init>":([BII)V
      54: putfield      #1                  // Field splitCell:Lorg/apache/hadoop/hbase/Cell;
      57: aload_0
      58: aload         4
      60: invokevirtual #10                 // Method org/apache/hadoop/hbase/io/Reference.getFileRegion:()Lorg/apache/hadoop/hbase/io/Reference$Range;
      63: invokestatic  #11                 // Method org/apache/hadoop/hbase/io/Reference.isTopFileRegion:(Lorg/apache/hadoop/hbase/io/Reference$Range;)Z
      66: putfield      #12                 // Field top:Z
      69: return

  public org.apache.hadoop.hbase.io.HalfStoreFileReader(org.apache.hadoop.fs.FileSystem, org.apache.hadoop.fs.Path, org.apache.hadoop.hbase.io.FSDataInputStreamWrapper, long, org.apache.hadoop.hbase.io.hfile.CacheConfig, org.apache.hadoop.hbase.io.Reference, boolean, java.util.concurrent.atomic.AtomicInteger, boolean, org.apache.hadoop.conf.Configuration) throws java.io.IOException;
    Code:
       0: aload_0
       1: aload_1
       2: aload_2
       3: aload_3
       4: lload         4
       6: aload         6
       8: iload         8
      10: aload         9
      12: iload         10
      14: aload         11
      16: invokespecial #13                 // Method org/apache/hadoop/hbase/regionserver/StoreFileReader."<init>":(Lorg/apache/hadoop/fs/FileSystem;Lorg/apache/hadoop/fs/Path;Lorg/apache/hadoop/hbase/io/FSDataInputStreamWrapper;JLorg/apache/hadoop/hbase/io/hfile/CacheConfig;ZLjava/util/concurrent/atomic/AtomicInteger;ZLorg/apache/hadoop/conf/Configuration;)V
      19: aload_0
      20: invokestatic  #3                  // Method java/util/Optional.empty:()Ljava/util/Optional;
      23: putfield      #4                  // Field firstKey:Ljava/util/Optional;
      26: aload_0
      27: iconst_0
      28: putfield      #5                  // Field firstKeySeeked:Z
      31: aload_0
      32: aload         7
      34: invokevirtual #6                  // Method org/apache/hadoop/hbase/io/Reference.getSplitKey:()[B
      37: putfield      #7                  // Field splitkey:[B
      40: aload_0
      41: new           #8                  // class org/apache/hadoop/hbase/KeyValue$KeyOnlyKeyValue
      44: dup
      45: aload_0
      46: getfield      #7                  // Field splitkey:[B
      49: iconst_0
      50: aload_0
      51: getfield      #7                  // Field splitkey:[B
      54: arraylength
      55: invokespecial #9                  // Method org/apache/hadoop/hbase/KeyValue$KeyOnlyKeyValue."<init>":([BII)V
      58: putfield      #1                  // Field splitCell:Lorg/apache/hadoop/hbase/Cell;
      61: aload_0
      62: aload         7
      64: invokevirtual #10                 // Method org/apache/hadoop/hbase/io/Reference.getFileRegion:()Lorg/apache/hadoop/hbase/io/Reference$Range;
      67: invokestatic  #11                 // Method org/apache/hadoop/hbase/io/Reference.isTopFileRegion:(Lorg/apache/hadoop/hbase/io/Reference$Range;)Z
      70: putfield      #12                 // Field top:Z
      73: return

  protected boolean isTop();
    Code:
       0: aload_0
       1: getfield      #12                 // Field top:Z
       4: ireturn

  public org.apache.hadoop.hbase.io.hfile.HFileScanner getScanner(boolean, boolean, boolean);
    Code:
       0: aload_0
       1: iload_1
       2: iload_2
       3: iload_3
       4: invokespecial #14                 // Method org/apache/hadoop/hbase/regionserver/StoreFileReader.getScanner:(ZZZ)Lorg/apache/hadoop/hbase/io/hfile/HFileScanner;
       7: astore        4
       9: new           #15                 // class org/apache/hadoop/hbase/io/HalfStoreFileReader$1
      12: dup
      13: aload_0
      14: aload         4
      16: invokespecial #16                 // Method org/apache/hadoop/hbase/io/HalfStoreFileReader$1."<init>":(Lorg/apache/hadoop/hbase/io/HalfStoreFileReader;Lorg/apache/hadoop/hbase/io/hfile/HFileScanner;)V
      19: areturn

  public boolean passesKeyRangeFilter(org.apache.hadoop.hbase.client.Scan);
    Code:
       0: iconst_1
       1: ireturn

  public java.util.Optional<org.apache.hadoop.hbase.Cell> getLastKey();
    Code:
       0: aload_0
       1: getfield      #12                 // Field top:Z
       4: ifeq          12
       7: aload_0
       8: invokespecial #17                 // Method org/apache/hadoop/hbase/regionserver/StoreFileReader.getLastKey:()Ljava/util/Optional;
      11: areturn
      12: aload_0
      13: iconst_1
      14: iconst_1
      15: invokevirtual #18                 // Method getScanner:(ZZ)Lorg/apache/hadoop/hbase/io/hfile/HFileScanner;
      18: astore_1
      19: aload_1
      20: aload_0
      21: getfield      #1                  // Field splitCell:Lorg/apache/hadoop/hbase/Cell;
      24: invokeinterface #19,  2           // InterfaceMethod org/apache/hadoop/hbase/io/hfile/HFileScanner.seekBefore:(Lorg/apache/hadoop/hbase/Cell;)Z
      29: ifeq          54
      32: aload_1
      33: invokeinterface #20,  1           // InterfaceMethod org/apache/hadoop/hbase/io/hfile/HFileScanner.getKey:()Lorg/apache/hadoop/hbase/Cell;
      38: invokestatic  #21                 // Method java/util/Optional.ofNullable:(Ljava/lang/Object;)Ljava/util/Optional;
      41: astore_2
      42: aload_1
      43: ifnull        52
      46: aload_1
      47: invokeinterface #22,  1           // InterfaceMethod org/apache/hadoop/hbase/io/hfile/HFileScanner.close:()V
      52: aload_2
      53: areturn
      54: aload_1
      55: ifnull        128
      58: aload_1
      59: invokeinterface #22,  1           // InterfaceMethod org/apache/hadoop/hbase/io/hfile/HFileScanner.close:()V
      64: goto          128
      67: astore_2
      68: getstatic     #24                 // Field LOG:Lorg/slf4j/Logger;
      71: new           #25                 // class java/lang/StringBuilder
      74: dup
      75: invokespecial #26                 // Method java/lang/StringBuilder."<init>":()V
      78: ldc           #27                 // String Failed seekBefore
      80: invokevirtual #28                 // Method java/lang/StringBuilder.append:(Ljava/lang/String;)Ljava/lang/StringBuilder;
      83: aload_0
      84: getfield      #7                  // Field splitkey:[B
      87: invokestatic  #29                 // Method org/apache/hadoop/hbase/util/Bytes.toStringBinary:([B)Ljava/lang/String;
      90: invokevirtual #28                 // Method java/lang/StringBuilder.append:(Ljava/lang/String;)Ljava/lang/StringBuilder;
      93: invokevirtual #30                 // Method java/lang/StringBuilder.toString:()Ljava/lang/String;
      96: aload_2
      97: invokeinterface #31,  3           // InterfaceMethod org/slf4j/Logger.warn:(Ljava/lang/String;Ljava/lang/Throwable;)V
     102: aload_1
     103: ifnull        128
     106: aload_1
     107: invokeinterface #22,  1           // InterfaceMethod org/apache/hadoop/hbase/io/hfile/HFileScanner.close:()V
     112: goto          128
     115: astore_3
     116: aload_1
     117: ifnull        126
     120: aload_1
     121: invokeinterface #22,  1           // InterfaceMethod org/apache/hadoop/hbase/io/hfile/HFileScanner.close:()V
     126: aload_3
     127: athrow
     128: invokestatic  #3                  // Method java/util/Optional.empty:()Ljava/util/Optional;
     131: areturn
    Exception table:
       from    to  target type
          19    42    67   Class java/io/IOException
          19    42   115   any
          67   102   115   any

  public java.util.Optional<org.apache.hadoop.hbase.Cell> midKey() throws java.io.IOException;
    Code:
       0: invokestatic  #3                  // Method java/util/Optional.empty:()Ljava/util/Optional;
       3: areturn

  public java.util.Optional<org.apache.hadoop.hbase.Cell> getFirstKey();
    Code:
       0: aload_0
       1: getfield      #5                  // Field firstKeySeeked:Z
       4: ifne          93
       7: aload_0
       8: iconst_1
       9: iconst_1
      10: iconst_0
      11: invokevirtual #32                 // Method getScanner:(ZZZ)Lorg/apache/hadoop/hbase/io/hfile/HFileScanner;
      14: astore_1
      15: aload_1
      16: invokeinterface #33,  1           // InterfaceMethod org/apache/hadoop/hbase/io/hfile/HFileScanner.seekTo:()Z
      21: ifeq          37
      24: aload_0
      25: aload_1
      26: invokeinterface #20,  1           // InterfaceMethod org/apache/hadoop/hbase/io/hfile/HFileScanner.getKey:()Lorg/apache/hadoop/hbase/Cell;
      31: invokestatic  #21                 // Method java/util/Optional.ofNullable:(Ljava/lang/Object;)Ljava/util/Optional;
      34: putfield      #4                  // Field firstKey:Ljava/util/Optional;
      37: aload_0
      38: iconst_1
      39: putfield      #5                  // Field firstKeySeeked:Z
      42: aload_1
      43: ifnull        93
      46: aload_1
      47: invokeinterface #22,  1           // InterfaceMethod org/apache/hadoop/hbase/io/hfile/HFileScanner.close:()V
      52: goto          93
      55: astore_2
      56: getstatic     #24                 // Field LOG:Lorg/slf4j/Logger;
      59: ldc           #34                 // String Failed seekTo first KV in the file
      61: aload_2
      62: invokeinterface #31,  3           // InterfaceMethod org/slf4j/Logger.warn:(Ljava/lang/String;Ljava/lang/Throwable;)V
      67: aload_1
      68: ifnull        93
      71: aload_1
      72: invokeinterface #22,  1           // InterfaceMethod org/apache/hadoop/hbase/io/hfile/HFileScanner.close:()V
      77: goto          93
      80: astore_3
      81: aload_1
      82: ifnull        91
      85: aload_1
      86: invokeinterface #22,  1           // InterfaceMethod org/apache/hadoop/hbase/io/hfile/HFileScanner.close:()V
      91: aload_3
      92: athrow
      93: aload_0
      94: getfield      #4                  // Field firstKey:Ljava/util/Optional;
      97: areturn
    Exception table:
       from    to  target type
          15    42    55   Class java/io/IOException
          15    42    80   any
          55    67    80   any

  public long getEntries();
    Code:
       0: aload_0
       1: invokespecial #35                 // Method org/apache/hadoop/hbase/regionserver/StoreFileReader.getEntries:()J
       4: ldc2_w        #36                 // long 2l
       7: ldiv
       8: lreturn

  public long getFilterEntries();
    Code:
       0: aload_0
       1: invokespecial #38                 // Method org/apache/hadoop/hbase/regionserver/StoreFileReader.getFilterEntries:()J
       4: ldc2_w        #36                 // long 2l
       7: ldiv
       8: lreturn

  static org.apache.hadoop.hbase.Cell access$000(org.apache.hadoop.hbase.io.HalfStoreFileReader);
    Code:
       0: aload_0
       1: getfield      #1                  // Field splitCell:Lorg/apache/hadoop/hbase/Cell;
       4: areturn

  static {};
    Code:
       0: ldc           #39                 // class org/apache/hadoop/hbase/io/HalfStoreFileReader
       2: invokestatic  #40                 // Method org/slf4j/LoggerFactory.getLogger:(Ljava/lang/Class;)Lorg/slf4j/Logger;
       5: putstatic     #24                 // Field LOG:Lorg/slf4j/Logger;
       8: return
}
