Compiled from "HandlerUtil.java"
final class org.apache.hadoop.hbase.regionserver.handler.HandlerUtil {
  public static org.apache.hadoop.hbase.util.RetryCounter getRetryCounter();
    Code:
       0: new           #2                  // class org/apache/hadoop/hbase/util/RetryCounterFactory
       3: dup
       4: new           #3                  // class org/apache/hadoop/hbase/util/RetryCounter$RetryConfig
       7: dup
       8: invokespecial #4                  // Method org/apache/hadoop/hbase/util/RetryCounter$RetryConfig."<init>":()V
      11: new           #5                  // class org/apache/hadoop/hbase/util/RetryCounter$ExponentialBackoffPolicy
      14: dup
      15: invokespecial #6                  // Method org/apache/hadoop/hbase/util/RetryCounter$ExponentialBackoffPolicy."<init>":()V
      18: invokevirtual #7                  // Method org/apache/hadoop/hbase/util/RetryCounter$RetryConfig.setBackoffPolicy:(Lorg/apache/hadoop/hbase/util/RetryCounter$BackoffPolicy;)Lorg/apache/hadoop/hbase/util/RetryCounter$RetryConfig;
      21: ldc2_w        #8                  // long 100l
      24: invokevirtual #10                 // Method org/apache/hadoop/hbase/util/RetryCounter$RetryConfig.setSleepInterval:(J)Lorg/apache/hadoop/hbase/util/RetryCounter$RetryConfig;
      27: ldc2_w        #11                 // long 30000l
      30: invokevirtual #13                 // Method org/apache/hadoop/hbase/util/RetryCounter$RetryConfig.setMaxSleepTime:(J)Lorg/apache/hadoop/hbase/util/RetryCounter$RetryConfig;
      33: ldc           #15                 // int 2147483647
      35: invokevirtual #16                 // Method org/apache/hadoop/hbase/util/RetryCounter$RetryConfig.setMaxAttempts:(I)Lorg/apache/hadoop/hbase/util/RetryCounter$RetryConfig;
      38: getstatic     #17                 // Field java/util/concurrent/TimeUnit.MILLISECONDS:Ljava/util/concurrent/TimeUnit;
      41: invokevirtual #18                 // Method org/apache/hadoop/hbase/util/RetryCounter$RetryConfig.setTimeUnit:(Ljava/util/concurrent/TimeUnit;)Lorg/apache/hadoop/hbase/util/RetryCounter$RetryConfig;
      44: ldc           #19                 // float 0.01f
      46: invokevirtual #20                 // Method org/apache/hadoop/hbase/util/RetryCounter$RetryConfig.setJitter:(F)Lorg/apache/hadoop/hbase/util/RetryCounter$RetryConfig;
      49: invokespecial #21                 // Method org/apache/hadoop/hbase/util/RetryCounterFactory."<init>":(Lorg/apache/hadoop/hbase/util/RetryCounter$RetryConfig;)V
      52: invokevirtual #22                 // Method org/apache/hadoop/hbase/util/RetryCounterFactory.create:()Lorg/apache/hadoop/hbase/util/RetryCounter;
      55: areturn
}
