Compiled from "HasThread.java"
public abstract class org.apache.hadoop.hbase.util.HasThread implements java.lang.Runnable {
  public org.apache.hadoop.hbase.util.HasThread();
    Code:
       0: aload_0
       1: invokespecial #1                  // Method java/lang/Object."<init>":()V
       4: aload_0
       5: new           #2                  // class java/lang/Thread
       8: dup
       9: aload_0
      10: invokespecial #3                  // Method java/lang/Thread."<init>":(Ljava/lang/Runnable;)V
      13: putfield      #4                  // Field thread:Ljava/lang/Thread;
      16: aload_0
      17: getfield      #4                  // Field thread:Ljava/lang/Thread;
      20: iconst_1
      21: invokevirtual #5                  // Method java/lang/Thread.setDaemon:(Z)V
      24: return

  public org.apache.hadoop.hbase.util.HasThread(java.lang.String);
    Code:
       0: aload_0
       1: invokespecial #1                  // Method java/lang/Object."<init>":()V
       4: aload_0
       5: new           #2                  // class java/lang/Thread
       8: dup
       9: aload_0
      10: aload_1
      11: invokespecial #6                  // Method java/lang/Thread."<init>":(Ljava/lang/Runnable;Ljava/lang/String;)V
      14: putfield      #4                  // Field thread:Ljava/lang/Thread;
      17: aload_0
      18: getfield      #4                  // Field thread:Ljava/lang/Thread;
      21: iconst_1
      22: invokevirtual #5                  // Method java/lang/Thread.setDaemon:(Z)V
      25: return

  public java.lang.Thread getThread();
    Code:
       0: aload_0
       1: getfield      #4                  // Field thread:Ljava/lang/Thread;
       4: areturn

  public abstract void run();

  public final java.lang.String getName();
    Code:
       0: aload_0
       1: getfield      #4                  // Field thread:Ljava/lang/Thread;
       4: invokevirtual #7                  // Method java/lang/Thread.getName:()Ljava/lang/String;
       7: areturn

  public void interrupt();
    Code:
       0: aload_0
       1: getfield      #4                  // Field thread:Ljava/lang/Thread;
       4: invokevirtual #8                  // Method java/lang/Thread.interrupt:()V
       7: return

  public final boolean isAlive();
    Code:
       0: aload_0
       1: getfield      #4                  // Field thread:Ljava/lang/Thread;
       4: invokevirtual #9                  // Method java/lang/Thread.isAlive:()Z
       7: ireturn

  public boolean isInterrupted();
    Code:
       0: aload_0
       1: getfield      #4                  // Field thread:Ljava/lang/Thread;
       4: invokevirtual #10                 // Method java/lang/Thread.isInterrupted:()Z
       7: ireturn

  public final void setDaemon(boolean);
    Code:
       0: aload_0
       1: getfield      #4                  // Field thread:Ljava/lang/Thread;
       4: iload_1
       5: invokevirtual #5                  // Method java/lang/Thread.setDaemon:(Z)V
       8: return

  public final void setName(java.lang.String);
    Code:
       0: aload_0
       1: getfield      #4                  // Field thread:Ljava/lang/Thread;
       4: aload_1
       5: invokevirtual #11                 // Method java/lang/Thread.setName:(Ljava/lang/String;)V
       8: return

  public final void setPriority(int);
    Code:
       0: aload_0
       1: getfield      #4                  // Field thread:Ljava/lang/Thread;
       4: iload_1
       5: invokevirtual #12                 // Method java/lang/Thread.setPriority:(I)V
       8: return

  public void setUncaughtExceptionHandler(java.lang.Thread$UncaughtExceptionHandler);
    Code:
       0: aload_0
       1: getfield      #4                  // Field thread:Ljava/lang/Thread;
       4: aload_1
       5: invokevirtual #13                 // Method java/lang/Thread.setUncaughtExceptionHandler:(Ljava/lang/Thread$UncaughtExceptionHandler;)V
       8: return

  public void start();
    Code:
       0: aload_0
       1: getfield      #4                  // Field thread:Ljava/lang/Thread;
       4: invokevirtual #14                 // Method java/lang/Thread.start:()V
       7: return

  public final void join() throws java.lang.InterruptedException;
    Code:
       0: aload_0
       1: getfield      #4                  // Field thread:Ljava/lang/Thread;
       4: invokevirtual #15                 // Method java/lang/Thread.join:()V
       7: return

  public final void join(long, int) throws java.lang.InterruptedException;
    Code:
       0: aload_0
       1: getfield      #4                  // Field thread:Ljava/lang/Thread;
       4: lload_1
       5: iload_3
       6: invokevirtual #16                 // Method java/lang/Thread.join:(JI)V
       9: return

  public final void join(long) throws java.lang.InterruptedException;
    Code:
       0: aload_0
       1: getfield      #4                  // Field thread:Ljava/lang/Thread;
       4: lload_1
       5: invokevirtual #17                 // Method java/lang/Thread.join:(J)V
       8: return
}
