Compiled from "HBaseFsck.java"
public final class org.apache.hadoop.hbase.util.HBaseFsck$ErrorReporter$ERROR_CODE extends java.lang.Enum<org.apache.hadoop.hbase.util.HBaseFsck$ErrorReporter$ERROR_CODE> {
  public static final org.apache.hadoop.hbase.util.HBaseFsck$ErrorReporter$ERROR_CODE UNKNOWN;

  public static final org.apache.hadoop.hbase.util.HBaseFsck$ErrorReporter$ERROR_CODE NO_META_REGION;

  public static final org.apache.hadoop.hbase.util.HBaseFsck$ErrorReporter$ERROR_CODE NULL_META_REGION;

  public static final org.apache.hadoop.hbase.util.HBaseFsck$ErrorReporter$ERROR_CODE NO_VERSION_FILE;

  public static final org.apache.hadoop.hbase.util.HBaseFsck$ErrorReporter$ERROR_CODE NOT_IN_META_HDFS;

  public static final org.apache.hadoop.hbase.util.HBaseFsck$ErrorReporter$ERROR_CODE NOT_IN_META;

  public static final org.apache.hadoop.hbase.util.HBaseFsck$ErrorReporter$ERROR_CODE NOT_IN_META_OR_DEPLOYED;

  public static final org.apache.hadoop.hbase.util.HBaseFsck$ErrorReporter$ERROR_CODE NOT_IN_HDFS_OR_DEPLOYED;

  public static final org.apache.hadoop.hbase.util.HBaseFsck$ErrorReporter$ERROR_CODE NOT_IN_HDFS;

  public static final org.apache.hadoop.hbase.util.HBaseFsck$ErrorReporter$ERROR_CODE SERVER_DOES_NOT_MATCH_META;

  public static final org.apache.hadoop.hbase.util.HBaseFsck$ErrorReporter$ERROR_CODE NOT_DEPLOYED;

  public static final org.apache.hadoop.hbase.util.HBaseFsck$ErrorReporter$ERROR_CODE MULTI_DEPLOYED;

  public static final org.apache.hadoop.hbase.util.HBaseFsck$ErrorReporter$ERROR_CODE SHOULD_NOT_BE_DEPLOYED;

  public static final org.apache.hadoop.hbase.util.HBaseFsck$ErrorReporter$ERROR_CODE MULTI_META_REGION;

  public static final org.apache.hadoop.hbase.util.HBaseFsck$ErrorReporter$ERROR_CODE RS_CONNECT_FAILURE;

  public static final org.apache.hadoop.hbase.util.HBaseFsck$ErrorReporter$ERROR_CODE FIRST_REGION_STARTKEY_NOT_EMPTY;

  public static final org.apache.hadoop.hbase.util.HBaseFsck$ErrorReporter$ERROR_CODE LAST_REGION_ENDKEY_NOT_EMPTY;

  public static final org.apache.hadoop.hbase.util.HBaseFsck$ErrorReporter$ERROR_CODE DUPE_STARTKEYS;

  public static final org.apache.hadoop.hbase.util.HBaseFsck$ErrorReporter$ERROR_CODE HOLE_IN_REGION_CHAIN;

  public static final org.apache.hadoop.hbase.util.HBaseFsck$ErrorReporter$ERROR_CODE OVERLAP_IN_REGION_CHAIN;

  public static final org.apache.hadoop.hbase.util.HBaseFsck$ErrorReporter$ERROR_CODE REGION_CYCLE;

  public static final org.apache.hadoop.hbase.util.HBaseFsck$ErrorReporter$ERROR_CODE DEGENERATE_REGION;

  public static final org.apache.hadoop.hbase.util.HBaseFsck$ErrorReporter$ERROR_CODE ORPHAN_HDFS_REGION;

  public static final org.apache.hadoop.hbase.util.HBaseFsck$ErrorReporter$ERROR_CODE LINGERING_SPLIT_PARENT;

  public static final org.apache.hadoop.hbase.util.HBaseFsck$ErrorReporter$ERROR_CODE NO_TABLEINFO_FILE;

  public static final org.apache.hadoop.hbase.util.HBaseFsck$ErrorReporter$ERROR_CODE LINGERING_REFERENCE_HFILE;

  public static final org.apache.hadoop.hbase.util.HBaseFsck$ErrorReporter$ERROR_CODE LINGERING_HFILELINK;

  public static final org.apache.hadoop.hbase.util.HBaseFsck$ErrorReporter$ERROR_CODE WRONG_USAGE;

  public static final org.apache.hadoop.hbase.util.HBaseFsck$ErrorReporter$ERROR_CODE EMPTY_META_CELL;

  public static final org.apache.hadoop.hbase.util.HBaseFsck$ErrorReporter$ERROR_CODE EXPIRED_TABLE_LOCK;

  public static final org.apache.hadoop.hbase.util.HBaseFsck$ErrorReporter$ERROR_CODE BOUNDARIES_ERROR;

  public static final org.apache.hadoop.hbase.util.HBaseFsck$ErrorReporter$ERROR_CODE ORPHAN_TABLE_STATE;

  public static final org.apache.hadoop.hbase.util.HBaseFsck$ErrorReporter$ERROR_CODE NO_TABLE_STATE;

  public static final org.apache.hadoop.hbase.util.HBaseFsck$ErrorReporter$ERROR_CODE UNDELETED_REPLICATION_QUEUE;

  public static final org.apache.hadoop.hbase.util.HBaseFsck$ErrorReporter$ERROR_CODE DUPE_ENDKEYS;

  public static final org.apache.hadoop.hbase.util.HBaseFsck$ErrorReporter$ERROR_CODE UNSUPPORTED_OPTION;

  public static final org.apache.hadoop.hbase.util.HBaseFsck$ErrorReporter$ERROR_CODE INVALID_TABLE;

  public static org.apache.hadoop.hbase.util.HBaseFsck$ErrorReporter$ERROR_CODE[] values();
    Code:
       0: getstatic     #1                  // Field $VALUES:[Lorg/apache/hadoop/hbase/util/HBaseFsck$ErrorReporter$ERROR_CODE;
       3: invokevirtual #2                  // Method "[Lorg/apache/hadoop/hbase/util/HBaseFsck$ErrorReporter$ERROR_CODE;".clone:()Ljava/lang/Object;
       6: checkcast     #3                  // class "[Lorg/apache/hadoop/hbase/util/HBaseFsck$ErrorReporter$ERROR_CODE;"
       9: areturn

  public static org.apache.hadoop.hbase.util.HBaseFsck$ErrorReporter$ERROR_CODE valueOf(java.lang.String);
    Code:
       0: ldc           #4                  // class org/apache/hadoop/hbase/util/HBaseFsck$ErrorReporter$ERROR_CODE
       2: aload_0
       3: invokestatic  #5                  // Method java/lang/Enum.valueOf:(Ljava/lang/Class;Ljava/lang/String;)Ljava/lang/Enum;
       6: checkcast     #4                  // class org/apache/hadoop/hbase/util/HBaseFsck$ErrorReporter$ERROR_CODE
       9: areturn

  static {};
    Code:
       0: new           #4                  // class org/apache/hadoop/hbase/util/HBaseFsck$ErrorReporter$ERROR_CODE
       3: dup
       4: ldc           #7                  // String UNKNOWN
       6: iconst_0
       7: invokespecial #8                  // Method "<init>":(Ljava/lang/String;I)V
      10: putstatic     #9                  // Field UNKNOWN:Lorg/apache/hadoop/hbase/util/HBaseFsck$ErrorReporter$ERROR_CODE;
      13: new           #4                  // class org/apache/hadoop/hbase/util/HBaseFsck$ErrorReporter$ERROR_CODE
      16: dup
      17: ldc           #10                 // String NO_META_REGION
      19: iconst_1
      20: invokespecial #8                  // Method "<init>":(Ljava/lang/String;I)V
      23: putstatic     #11                 // Field NO_META_REGION:Lorg/apache/hadoop/hbase/util/HBaseFsck$ErrorReporter$ERROR_CODE;
      26: new           #4                  // class org/apache/hadoop/hbase/util/HBaseFsck$ErrorReporter$ERROR_CODE
      29: dup
      30: ldc           #12                 // String NULL_META_REGION
      32: iconst_2
      33: invokespecial #8                  // Method "<init>":(Ljava/lang/String;I)V
      36: putstatic     #13                 // Field NULL_META_REGION:Lorg/apache/hadoop/hbase/util/HBaseFsck$ErrorReporter$ERROR_CODE;
      39: new           #4                  // class org/apache/hadoop/hbase/util/HBaseFsck$ErrorReporter$ERROR_CODE
      42: dup
      43: ldc           #14                 // String NO_VERSION_FILE
      45: iconst_3
      46: invokespecial #8                  // Method "<init>":(Ljava/lang/String;I)V
      49: putstatic     #15                 // Field NO_VERSION_FILE:Lorg/apache/hadoop/hbase/util/HBaseFsck$ErrorReporter$ERROR_CODE;
      52: new           #4                  // class org/apache/hadoop/hbase/util/HBaseFsck$ErrorReporter$ERROR_CODE
      55: dup
      56: ldc           #16                 // String NOT_IN_META_HDFS
      58: iconst_4
      59: invokespecial #8                  // Method "<init>":(Ljava/lang/String;I)V
      62: putstatic     #17                 // Field NOT_IN_META_HDFS:Lorg/apache/hadoop/hbase/util/HBaseFsck$ErrorReporter$ERROR_CODE;
      65: new           #4                  // class org/apache/hadoop/hbase/util/HBaseFsck$ErrorReporter$ERROR_CODE
      68: dup
      69: ldc           #18                 // String NOT_IN_META
      71: iconst_5
      72: invokespecial #8                  // Method "<init>":(Ljava/lang/String;I)V
      75: putstatic     #19                 // Field NOT_IN_META:Lorg/apache/hadoop/hbase/util/HBaseFsck$ErrorReporter$ERROR_CODE;
      78: new           #4                  // class org/apache/hadoop/hbase/util/HBaseFsck$ErrorReporter$ERROR_CODE
      81: dup
      82: ldc           #20                 // String NOT_IN_META_OR_DEPLOYED
      84: bipush        6
      86: invokespecial #8                  // Method "<init>":(Ljava/lang/String;I)V
      89: putstatic     #21                 // Field NOT_IN_META_OR_DEPLOYED:Lorg/apache/hadoop/hbase/util/HBaseFsck$ErrorReporter$ERROR_CODE;
      92: new           #4                  // class org/apache/hadoop/hbase/util/HBaseFsck$ErrorReporter$ERROR_CODE
      95: dup
      96: ldc           #22                 // String NOT_IN_HDFS_OR_DEPLOYED
      98: bipush        7
     100: invokespecial #8                  // Method "<init>":(Ljava/lang/String;I)V
     103: putstatic     #23                 // Field NOT_IN_HDFS_OR_DEPLOYED:Lorg/apache/hadoop/hbase/util/HBaseFsck$ErrorReporter$ERROR_CODE;
     106: new           #4                  // class org/apache/hadoop/hbase/util/HBaseFsck$ErrorReporter$ERROR_CODE
     109: dup
     110: ldc           #24                 // String NOT_IN_HDFS
     112: bipush        8
     114: invokespecial #8                  // Method "<init>":(Ljava/lang/String;I)V
     117: putstatic     #25                 // Field NOT_IN_HDFS:Lorg/apache/hadoop/hbase/util/HBaseFsck$ErrorReporter$ERROR_CODE;
     120: new           #4                  // class org/apache/hadoop/hbase/util/HBaseFsck$ErrorReporter$ERROR_CODE
     123: dup
     124: ldc           #26                 // String SERVER_DOES_NOT_MATCH_META
     126: bipush        9
     128: invokespecial #8                  // Method "<init>":(Ljava/lang/String;I)V
     131: putstatic     #27                 // Field SERVER_DOES_NOT_MATCH_META:Lorg/apache/hadoop/hbase/util/HBaseFsck$ErrorReporter$ERROR_CODE;
     134: new           #4                  // class org/apache/hadoop/hbase/util/HBaseFsck$ErrorReporter$ERROR_CODE
     137: dup
     138: ldc           #28                 // String NOT_DEPLOYED
     140: bipush        10
     142: invokespecial #8                  // Method "<init>":(Ljava/lang/String;I)V
     145: putstatic     #29                 // Field NOT_DEPLOYED:Lorg/apache/hadoop/hbase/util/HBaseFsck$ErrorReporter$ERROR_CODE;
     148: new           #4                  // class org/apache/hadoop/hbase/util/HBaseFsck$ErrorReporter$ERROR_CODE
     151: dup
     152: ldc           #30                 // String MULTI_DEPLOYED
     154: bipush        11
     156: invokespecial #8                  // Method "<init>":(Ljava/lang/String;I)V
     159: putstatic     #31                 // Field MULTI_DEPLOYED:Lorg/apache/hadoop/hbase/util/HBaseFsck$ErrorReporter$ERROR_CODE;
     162: new           #4                  // class org/apache/hadoop/hbase/util/HBaseFsck$ErrorReporter$ERROR_CODE
     165: dup
     166: ldc           #32                 // String SHOULD_NOT_BE_DEPLOYED
     168: bipush        12
     170: invokespecial #8                  // Method "<init>":(Ljava/lang/String;I)V
     173: putstatic     #33                 // Field SHOULD_NOT_BE_DEPLOYED:Lorg/apache/hadoop/hbase/util/HBaseFsck$ErrorReporter$ERROR_CODE;
     176: new           #4                  // class org/apache/hadoop/hbase/util/HBaseFsck$ErrorReporter$ERROR_CODE
     179: dup
     180: ldc           #34                 // String MULTI_META_REGION
     182: bipush        13
     184: invokespecial #8                  // Method "<init>":(Ljava/lang/String;I)V
     187: putstatic     #35                 // Field MULTI_META_REGION:Lorg/apache/hadoop/hbase/util/HBaseFsck$ErrorReporter$ERROR_CODE;
     190: new           #4                  // class org/apache/hadoop/hbase/util/HBaseFsck$ErrorReporter$ERROR_CODE
     193: dup
     194: ldc           #36                 // String RS_CONNECT_FAILURE
     196: bipush        14
     198: invokespecial #8                  // Method "<init>":(Ljava/lang/String;I)V
     201: putstatic     #37                 // Field RS_CONNECT_FAILURE:Lorg/apache/hadoop/hbase/util/HBaseFsck$ErrorReporter$ERROR_CODE;
     204: new           #4                  // class org/apache/hadoop/hbase/util/HBaseFsck$ErrorReporter$ERROR_CODE
     207: dup
     208: ldc           #38                 // String FIRST_REGION_STARTKEY_NOT_EMPTY
     210: bipush        15
     212: invokespecial #8                  // Method "<init>":(Ljava/lang/String;I)V
     215: putstatic     #39                 // Field FIRST_REGION_STARTKEY_NOT_EMPTY:Lorg/apache/hadoop/hbase/util/HBaseFsck$ErrorReporter$ERROR_CODE;
     218: new           #4                  // class org/apache/hadoop/hbase/util/HBaseFsck$ErrorReporter$ERROR_CODE
     221: dup
     222: ldc           #40                 // String LAST_REGION_ENDKEY_NOT_EMPTY
     224: bipush        16
     226: invokespecial #8                  // Method "<init>":(Ljava/lang/String;I)V
     229: putstatic     #41                 // Field LAST_REGION_ENDKEY_NOT_EMPTY:Lorg/apache/hadoop/hbase/util/HBaseFsck$ErrorReporter$ERROR_CODE;
     232: new           #4                  // class org/apache/hadoop/hbase/util/HBaseFsck$ErrorReporter$ERROR_CODE
     235: dup
     236: ldc           #42                 // String DUPE_STARTKEYS
     238: bipush        17
     240: invokespecial #8                  // Method "<init>":(Ljava/lang/String;I)V
     243: putstatic     #43                 // Field DUPE_STARTKEYS:Lorg/apache/hadoop/hbase/util/HBaseFsck$ErrorReporter$ERROR_CODE;
     246: new           #4                  // class org/apache/hadoop/hbase/util/HBaseFsck$ErrorReporter$ERROR_CODE
     249: dup
     250: ldc           #44                 // String HOLE_IN_REGION_CHAIN
     252: bipush        18
     254: invokespecial #8                  // Method "<init>":(Ljava/lang/String;I)V
     257: putstatic     #45                 // Field HOLE_IN_REGION_CHAIN:Lorg/apache/hadoop/hbase/util/HBaseFsck$ErrorReporter$ERROR_CODE;
     260: new           #4                  // class org/apache/hadoop/hbase/util/HBaseFsck$ErrorReporter$ERROR_CODE
     263: dup
     264: ldc           #46                 // String OVERLAP_IN_REGION_CHAIN
     266: bipush        19
     268: invokespecial #8                  // Method "<init>":(Ljava/lang/String;I)V
     271: putstatic     #47                 // Field OVERLAP_IN_REGION_CHAIN:Lorg/apache/hadoop/hbase/util/HBaseFsck$ErrorReporter$ERROR_CODE;
     274: new           #4                  // class org/apache/hadoop/hbase/util/HBaseFsck$ErrorReporter$ERROR_CODE
     277: dup
     278: ldc           #48                 // String REGION_CYCLE
     280: bipush        20
     282: invokespecial #8                  // Method "<init>":(Ljava/lang/String;I)V
     285: putstatic     #49                 // Field REGION_CYCLE:Lorg/apache/hadoop/hbase/util/HBaseFsck$ErrorReporter$ERROR_CODE;
     288: new           #4                  // class org/apache/hadoop/hbase/util/HBaseFsck$ErrorReporter$ERROR_CODE
     291: dup
     292: ldc           #50                 // String DEGENERATE_REGION
     294: bipush        21
     296: invokespecial #8                  // Method "<init>":(Ljava/lang/String;I)V
     299: putstatic     #51                 // Field DEGENERATE_REGION:Lorg/apache/hadoop/hbase/util/HBaseFsck$ErrorReporter$ERROR_CODE;
     302: new           #4                  // class org/apache/hadoop/hbase/util/HBaseFsck$ErrorReporter$ERROR_CODE
     305: dup
     306: ldc           #52                 // String ORPHAN_HDFS_REGION
     308: bipush        22
     310: invokespecial #8                  // Method "<init>":(Ljava/lang/String;I)V
     313: putstatic     #53                 // Field ORPHAN_HDFS_REGION:Lorg/apache/hadoop/hbase/util/HBaseFsck$ErrorReporter$ERROR_CODE;
     316: new           #4                  // class org/apache/hadoop/hbase/util/HBaseFsck$ErrorReporter$ERROR_CODE
     319: dup
     320: ldc           #54                 // String LINGERING_SPLIT_PARENT
     322: bipush        23
     324: invokespecial #8                  // Method "<init>":(Ljava/lang/String;I)V
     327: putstatic     #55                 // Field LINGERING_SPLIT_PARENT:Lorg/apache/hadoop/hbase/util/HBaseFsck$ErrorReporter$ERROR_CODE;
     330: new           #4                  // class org/apache/hadoop/hbase/util/HBaseFsck$ErrorReporter$ERROR_CODE
     333: dup
     334: ldc           #56                 // String NO_TABLEINFO_FILE
     336: bipush        24
     338: invokespecial #8                  // Method "<init>":(Ljava/lang/String;I)V
     341: putstatic     #57                 // Field NO_TABLEINFO_FILE:Lorg/apache/hadoop/hbase/util/HBaseFsck$ErrorReporter$ERROR_CODE;
     344: new           #4                  // class org/apache/hadoop/hbase/util/HBaseFsck$ErrorReporter$ERROR_CODE
     347: dup
     348: ldc           #58                 // String LINGERING_REFERENCE_HFILE
     350: bipush        25
     352: invokespecial #8                  // Method "<init>":(Ljava/lang/String;I)V
     355: putstatic     #59                 // Field LINGERING_REFERENCE_HFILE:Lorg/apache/hadoop/hbase/util/HBaseFsck$ErrorReporter$ERROR_CODE;
     358: new           #4                  // class org/apache/hadoop/hbase/util/HBaseFsck$ErrorReporter$ERROR_CODE
     361: dup
     362: ldc           #60                 // String LINGERING_HFILELINK
     364: bipush        26
     366: invokespecial #8                  // Method "<init>":(Ljava/lang/String;I)V
     369: putstatic     #61                 // Field LINGERING_HFILELINK:Lorg/apache/hadoop/hbase/util/HBaseFsck$ErrorReporter$ERROR_CODE;
     372: new           #4                  // class org/apache/hadoop/hbase/util/HBaseFsck$ErrorReporter$ERROR_CODE
     375: dup
     376: ldc           #62                 // String WRONG_USAGE
     378: bipush        27
     380: invokespecial #8                  // Method "<init>":(Ljava/lang/String;I)V
     383: putstatic     #63                 // Field WRONG_USAGE:Lorg/apache/hadoop/hbase/util/HBaseFsck$ErrorReporter$ERROR_CODE;
     386: new           #4                  // class org/apache/hadoop/hbase/util/HBaseFsck$ErrorReporter$ERROR_CODE
     389: dup
     390: ldc           #64                 // String EMPTY_META_CELL
     392: bipush        28
     394: invokespecial #8                  // Method "<init>":(Ljava/lang/String;I)V
     397: putstatic     #65                 // Field EMPTY_META_CELL:Lorg/apache/hadoop/hbase/util/HBaseFsck$ErrorReporter$ERROR_CODE;
     400: new           #4                  // class org/apache/hadoop/hbase/util/HBaseFsck$ErrorReporter$ERROR_CODE
     403: dup
     404: ldc           #66                 // String EXPIRED_TABLE_LOCK
     406: bipush        29
     408: invokespecial #8                  // Method "<init>":(Ljava/lang/String;I)V
     411: putstatic     #67                 // Field EXPIRED_TABLE_LOCK:Lorg/apache/hadoop/hbase/util/HBaseFsck$ErrorReporter$ERROR_CODE;
     414: new           #4                  // class org/apache/hadoop/hbase/util/HBaseFsck$ErrorReporter$ERROR_CODE
     417: dup
     418: ldc           #68                 // String BOUNDARIES_ERROR
     420: bipush        30
     422: invokespecial #8                  // Method "<init>":(Ljava/lang/String;I)V
     425: putstatic     #69                 // Field BOUNDARIES_ERROR:Lorg/apache/hadoop/hbase/util/HBaseFsck$ErrorReporter$ERROR_CODE;
     428: new           #4                  // class org/apache/hadoop/hbase/util/HBaseFsck$ErrorReporter$ERROR_CODE
     431: dup
     432: ldc           #70                 // String ORPHAN_TABLE_STATE
     434: bipush        31
     436: invokespecial #8                  // Method "<init>":(Ljava/lang/String;I)V
     439: putstatic     #71                 // Field ORPHAN_TABLE_STATE:Lorg/apache/hadoop/hbase/util/HBaseFsck$ErrorReporter$ERROR_CODE;
     442: new           #4                  // class org/apache/hadoop/hbase/util/HBaseFsck$ErrorReporter$ERROR_CODE
     445: dup
     446: ldc           #72                 // String NO_TABLE_STATE
     448: bipush        32
     450: invokespecial #8                  // Method "<init>":(Ljava/lang/String;I)V
     453: putstatic     #73                 // Field NO_TABLE_STATE:Lorg/apache/hadoop/hbase/util/HBaseFsck$ErrorReporter$ERROR_CODE;
     456: new           #4                  // class org/apache/hadoop/hbase/util/HBaseFsck$ErrorReporter$ERROR_CODE
     459: dup
     460: ldc           #74                 // String UNDELETED_REPLICATION_QUEUE
     462: bipush        33
     464: invokespecial #8                  // Method "<init>":(Ljava/lang/String;I)V
     467: putstatic     #75                 // Field UNDELETED_REPLICATION_QUEUE:Lorg/apache/hadoop/hbase/util/HBaseFsck$ErrorReporter$ERROR_CODE;
     470: new           #4                  // class org/apache/hadoop/hbase/util/HBaseFsck$ErrorReporter$ERROR_CODE
     473: dup
     474: ldc           #76                 // String DUPE_ENDKEYS
     476: bipush        34
     478: invokespecial #8                  // Method "<init>":(Ljava/lang/String;I)V
     481: putstatic     #77                 // Field DUPE_ENDKEYS:Lorg/apache/hadoop/hbase/util/HBaseFsck$ErrorReporter$ERROR_CODE;
     484: new           #4                  // class org/apache/hadoop/hbase/util/HBaseFsck$ErrorReporter$ERROR_CODE
     487: dup
     488: ldc           #78                 // String UNSUPPORTED_OPTION
     490: bipush        35
     492: invokespecial #8                  // Method "<init>":(Ljava/lang/String;I)V
     495: putstatic     #79                 // Field UNSUPPORTED_OPTION:Lorg/apache/hadoop/hbase/util/HBaseFsck$ErrorReporter$ERROR_CODE;
     498: new           #4                  // class org/apache/hadoop/hbase/util/HBaseFsck$ErrorReporter$ERROR_CODE
     501: dup
     502: ldc           #80                 // String INVALID_TABLE
     504: bipush        36
     506: invokespecial #8                  // Method "<init>":(Ljava/lang/String;I)V
     509: putstatic     #81                 // Field INVALID_TABLE:Lorg/apache/hadoop/hbase/util/HBaseFsck$ErrorReporter$ERROR_CODE;
     512: bipush        37
     514: anewarray     #4                  // class org/apache/hadoop/hbase/util/HBaseFsck$ErrorReporter$ERROR_CODE
     517: dup
     518: iconst_0
     519: getstatic     #9                  // Field UNKNOWN:Lorg/apache/hadoop/hbase/util/HBaseFsck$ErrorReporter$ERROR_CODE;
     522: aastore
     523: dup
     524: iconst_1
     525: getstatic     #11                 // Field NO_META_REGION:Lorg/apache/hadoop/hbase/util/HBaseFsck$ErrorReporter$ERROR_CODE;
     528: aastore
     529: dup
     530: iconst_2
     531: getstatic     #13                 // Field NULL_META_REGION:Lorg/apache/hadoop/hbase/util/HBaseFsck$ErrorReporter$ERROR_CODE;
     534: aastore
     535: dup
     536: iconst_3
     537: getstatic     #15                 // Field NO_VERSION_FILE:Lorg/apache/hadoop/hbase/util/HBaseFsck$ErrorReporter$ERROR_CODE;
     540: aastore
     541: dup
     542: iconst_4
     543: getstatic     #17                 // Field NOT_IN_META_HDFS:Lorg/apache/hadoop/hbase/util/HBaseFsck$ErrorReporter$ERROR_CODE;
     546: aastore
     547: dup
     548: iconst_5
     549: getstatic     #19                 // Field NOT_IN_META:Lorg/apache/hadoop/hbase/util/HBaseFsck$ErrorReporter$ERROR_CODE;
     552: aastore
     553: dup
     554: bipush        6
     556: getstatic     #21                 // Field NOT_IN_META_OR_DEPLOYED:Lorg/apache/hadoop/hbase/util/HBaseFsck$ErrorReporter$ERROR_CODE;
     559: aastore
     560: dup
     561: bipush        7
     563: getstatic     #23                 // Field NOT_IN_HDFS_OR_DEPLOYED:Lorg/apache/hadoop/hbase/util/HBaseFsck$ErrorReporter$ERROR_CODE;
     566: aastore
     567: dup
     568: bipush        8
     570: getstatic     #25                 // Field NOT_IN_HDFS:Lorg/apache/hadoop/hbase/util/HBaseFsck$ErrorReporter$ERROR_CODE;
     573: aastore
     574: dup
     575: bipush        9
     577: getstatic     #27                 // Field SERVER_DOES_NOT_MATCH_META:Lorg/apache/hadoop/hbase/util/HBaseFsck$ErrorReporter$ERROR_CODE;
     580: aastore
     581: dup
     582: bipush        10
     584: getstatic     #29                 // Field NOT_DEPLOYED:Lorg/apache/hadoop/hbase/util/HBaseFsck$ErrorReporter$ERROR_CODE;
     587: aastore
     588: dup
     589: bipush        11
     591: getstatic     #31                 // Field MULTI_DEPLOYED:Lorg/apache/hadoop/hbase/util/HBaseFsck$ErrorReporter$ERROR_CODE;
     594: aastore
     595: dup
     596: bipush        12
     598: getstatic     #33                 // Field SHOULD_NOT_BE_DEPLOYED:Lorg/apache/hadoop/hbase/util/HBaseFsck$ErrorReporter$ERROR_CODE;
     601: aastore
     602: dup
     603: bipush        13
     605: getstatic     #35                 // Field MULTI_META_REGION:Lorg/apache/hadoop/hbase/util/HBaseFsck$ErrorReporter$ERROR_CODE;
     608: aastore
     609: dup
     610: bipush        14
     612: getstatic     #37                 // Field RS_CONNECT_FAILURE:Lorg/apache/hadoop/hbase/util/HBaseFsck$ErrorReporter$ERROR_CODE;
     615: aastore
     616: dup
     617: bipush        15
     619: getstatic     #39                 // Field FIRST_REGION_STARTKEY_NOT_EMPTY:Lorg/apache/hadoop/hbase/util/HBaseFsck$ErrorReporter$ERROR_CODE;
     622: aastore
     623: dup
     624: bipush        16
     626: getstatic     #41                 // Field LAST_REGION_ENDKEY_NOT_EMPTY:Lorg/apache/hadoop/hbase/util/HBaseFsck$ErrorReporter$ERROR_CODE;
     629: aastore
     630: dup
     631: bipush        17
     633: getstatic     #43                 // Field DUPE_STARTKEYS:Lorg/apache/hadoop/hbase/util/HBaseFsck$ErrorReporter$ERROR_CODE;
     636: aastore
     637: dup
     638: bipush        18
     640: getstatic     #45                 // Field HOLE_IN_REGION_CHAIN:Lorg/apache/hadoop/hbase/util/HBaseFsck$ErrorReporter$ERROR_CODE;
     643: aastore
     644: dup
     645: bipush        19
     647: getstatic     #47                 // Field OVERLAP_IN_REGION_CHAIN:Lorg/apache/hadoop/hbase/util/HBaseFsck$ErrorReporter$ERROR_CODE;
     650: aastore
     651: dup
     652: bipush        20
     654: getstatic     #49                 // Field REGION_CYCLE:Lorg/apache/hadoop/hbase/util/HBaseFsck$ErrorReporter$ERROR_CODE;
     657: aastore
     658: dup
     659: bipush        21
     661: getstatic     #51                 // Field DEGENERATE_REGION:Lorg/apache/hadoop/hbase/util/HBaseFsck$ErrorReporter$ERROR_CODE;
     664: aastore
     665: dup
     666: bipush        22
     668: getstatic     #53                 // Field ORPHAN_HDFS_REGION:Lorg/apache/hadoop/hbase/util/HBaseFsck$ErrorReporter$ERROR_CODE;
     671: aastore
     672: dup
     673: bipush        23
     675: getstatic     #55                 // Field LINGERING_SPLIT_PARENT:Lorg/apache/hadoop/hbase/util/HBaseFsck$ErrorReporter$ERROR_CODE;
     678: aastore
     679: dup
     680: bipush        24
     682: getstatic     #57                 // Field NO_TABLEINFO_FILE:Lorg/apache/hadoop/hbase/util/HBaseFsck$ErrorReporter$ERROR_CODE;
     685: aastore
     686: dup
     687: bipush        25
     689: getstatic     #59                 // Field LINGERING_REFERENCE_HFILE:Lorg/apache/hadoop/hbase/util/HBaseFsck$ErrorReporter$ERROR_CODE;
     692: aastore
     693: dup
     694: bipush        26
     696: getstatic     #61                 // Field LINGERING_HFILELINK:Lorg/apache/hadoop/hbase/util/HBaseFsck$ErrorReporter$ERROR_CODE;
     699: aastore
     700: dup
     701: bipush        27
     703: getstatic     #63                 // Field WRONG_USAGE:Lorg/apache/hadoop/hbase/util/HBaseFsck$ErrorReporter$ERROR_CODE;
     706: aastore
     707: dup
     708: bipush        28
     710: getstatic     #65                 // Field EMPTY_META_CELL:Lorg/apache/hadoop/hbase/util/HBaseFsck$ErrorReporter$ERROR_CODE;
     713: aastore
     714: dup
     715: bipush        29
     717: getstatic     #67                 // Field EXPIRED_TABLE_LOCK:Lorg/apache/hadoop/hbase/util/HBaseFsck$ErrorReporter$ERROR_CODE;
     720: aastore
     721: dup
     722: bipush        30
     724: getstatic     #69                 // Field BOUNDARIES_ERROR:Lorg/apache/hadoop/hbase/util/HBaseFsck$ErrorReporter$ERROR_CODE;
     727: aastore
     728: dup
     729: bipush        31
     731: getstatic     #71                 // Field ORPHAN_TABLE_STATE:Lorg/apache/hadoop/hbase/util/HBaseFsck$ErrorReporter$ERROR_CODE;
     734: aastore
     735: dup
     736: bipush        32
     738: getstatic     #73                 // Field NO_TABLE_STATE:Lorg/apache/hadoop/hbase/util/HBaseFsck$ErrorReporter$ERROR_CODE;
     741: aastore
     742: dup
     743: bipush        33
     745: getstatic     #75                 // Field UNDELETED_REPLICATION_QUEUE:Lorg/apache/hadoop/hbase/util/HBaseFsck$ErrorReporter$ERROR_CODE;
     748: aastore
     749: dup
     750: bipush        34
     752: getstatic     #77                 // Field DUPE_ENDKEYS:Lorg/apache/hadoop/hbase/util/HBaseFsck$ErrorReporter$ERROR_CODE;
     755: aastore
     756: dup
     757: bipush        35
     759: getstatic     #79                 // Field UNSUPPORTED_OPTION:Lorg/apache/hadoop/hbase/util/HBaseFsck$ErrorReporter$ERROR_CODE;
     762: aastore
     763: dup
     764: bipush        36
     766: getstatic     #81                 // Field INVALID_TABLE:Lorg/apache/hadoop/hbase/util/HBaseFsck$ErrorReporter$ERROR_CODE;
     769: aastore
     770: putstatic     #1                  // Field $VALUES:[Lorg/apache/hadoop/hbase/util/HBaseFsck$ErrorReporter$ERROR_CODE;
     773: return
}
