Compiled from "HBaseKerberosUtils.java"
public class org.apache.hadoop.hbase.security.HBaseKerberosUtils {
  public static final java.lang.String KRB_PRINCIPAL;

  public static final java.lang.String MASTER_KRB_PRINCIPAL;

  public static final java.lang.String KRB_KEYTAB_FILE;

  public static final java.lang.String CLIENT_PRINCIPAL;

  public static final java.lang.String CLIENT_KEYTAB;

  public org.apache.hadoop.hbase.security.HBaseKerberosUtils();
    Code:
       0: aload_0
       1: invokespecial #3                  // Method java/lang/Object."<init>":()V
       4: return

  public static boolean isKerberosPropertySetted();
    Code:
       0: ldc           #5                  // String hbase.regionserver.kerberos.principal
       2: invokestatic  #6                  // Method java/lang/System.getProperty:(Ljava/lang/String;)Ljava/lang/String;
       5: astore_0
       6: ldc           #7                  // String hbase.regionserver.keytab.file
       8: invokestatic  #6                  // Method java/lang/System.getProperty:(Ljava/lang/String;)Ljava/lang/String;
      11: astore_1
      12: aload_0
      13: invokestatic  #8                  // Method org/apache/hbase/thirdparty/com/google/common/base/Strings.isNullOrEmpty:(Ljava/lang/String;)Z
      16: ifne          26
      19: aload_1
      20: invokestatic  #8                  // Method org/apache/hbase/thirdparty/com/google/common/base/Strings.isNullOrEmpty:(Ljava/lang/String;)Z
      23: ifeq          28
      26: iconst_0
      27: ireturn
      28: iconst_1
      29: ireturn

  public static void setPrincipalForTesting(java.lang.String);
    Code:
       0: ldc           #5                  // String hbase.regionserver.kerberos.principal
       2: aload_0
       3: invokestatic  #9                  // Method setSystemProperty:(Ljava/lang/String;Ljava/lang/String;)V
       6: return

  public static void setKeytabFileForTesting(java.lang.String);
    Code:
       0: ldc           #7                  // String hbase.regionserver.keytab.file
       2: aload_0
       3: invokestatic  #9                  // Method setSystemProperty:(Ljava/lang/String;Ljava/lang/String;)V
       6: return

  public static void setClientPrincipalForTesting(java.lang.String);
    Code:
       0: ldc           #10                 // String hbase.client.keytab.principal
       2: aload_0
       3: invokestatic  #9                  // Method setSystemProperty:(Ljava/lang/String;Ljava/lang/String;)V
       6: return

  public static void setClientKeytabForTesting(java.lang.String);
    Code:
       0: ldc           #11                 // String hbase.client.keytab.file
       2: aload_0
       3: invokestatic  #9                  // Method setSystemProperty:(Ljava/lang/String;Ljava/lang/String;)V
       6: return

  public static void setSystemProperty(java.lang.String, java.lang.String);
    Code:
       0: aload_0
       1: aload_1
       2: invokestatic  #12                 // Method java/lang/System.setProperty:(Ljava/lang/String;Ljava/lang/String;)Ljava/lang/String;
       5: pop
       6: return

  public static java.lang.String getKeytabFileForTesting();
    Code:
       0: ldc           #7                  // String hbase.regionserver.keytab.file
       2: invokestatic  #6                  // Method java/lang/System.getProperty:(Ljava/lang/String;)Ljava/lang/String;
       5: areturn

  public static java.lang.String getPrincipalForTesting();
    Code:
       0: ldc           #5                  // String hbase.regionserver.kerberos.principal
       2: invokestatic  #6                  // Method java/lang/System.getProperty:(Ljava/lang/String;)Ljava/lang/String;
       5: areturn

  public static java.lang.String getClientPrincipalForTesting();
    Code:
       0: ldc           #10                 // String hbase.client.keytab.principal
       2: invokestatic  #6                  // Method java/lang/System.getProperty:(Ljava/lang/String;)Ljava/lang/String;
       5: areturn

  public static java.lang.String getClientKeytabForTesting();
    Code:
       0: ldc           #11                 // String hbase.client.keytab.file
       2: invokestatic  #6                  // Method java/lang/System.getProperty:(Ljava/lang/String;)Ljava/lang/String;
       5: areturn

  public static org.apache.hadoop.conf.Configuration getConfigurationWoPrincipal();
    Code:
       0: invokestatic  #13                 // Method org/apache/hadoop/hbase/HBaseConfiguration.create:()Lorg/apache/hadoop/conf/Configuration;
       3: astore_0
       4: aload_0
       5: ldc           #15                 // String hadoop.security.authentication
       7: ldc           #16                 // String kerberos
       9: invokevirtual #17                 // Method org/apache/hadoop/conf/Configuration.set:(Ljava/lang/String;Ljava/lang/String;)V
      12: aload_0
      13: ldc           #19                 // String hbase.security.authentication
      15: ldc           #16                 // String kerberos
      17: invokevirtual #17                 // Method org/apache/hadoop/conf/Configuration.set:(Ljava/lang/String;Ljava/lang/String;)V
      20: aload_0
      21: ldc           #20                 // String hbase.security.authorization
      23: iconst_1
      24: invokevirtual #21                 // Method org/apache/hadoop/conf/Configuration.setBoolean:(Ljava/lang/String;Z)V
      27: aload_0
      28: areturn

  public static org.apache.hadoop.conf.Configuration getSecuredConfiguration();
    Code:
       0: invokestatic  #13                 // Method org/apache/hadoop/hbase/HBaseConfiguration.create:()Lorg/apache/hadoop/conf/Configuration;
       3: astore_0
       4: aload_0
       5: invokestatic  #22                 // Method setSecuredConfiguration:(Lorg/apache/hadoop/conf/Configuration;)V
       8: aload_0
       9: areturn

  public static void setSecuredConfiguration(org.apache.hadoop.conf.Configuration, java.lang.String, java.lang.String);
    Code:
       0: aload_1
       1: invokestatic  #23                 // Method setPrincipalForTesting:(Ljava/lang/String;)V
       4: aload_0
       5: invokestatic  #22                 // Method setSecuredConfiguration:(Lorg/apache/hadoop/conf/Configuration;)V
       8: aload_0
       9: aload_2
      10: invokestatic  #24                 // Method setSecuredHadoopConfiguration:(Lorg/apache/hadoop/conf/Configuration;Ljava/lang/String;)V
      13: return

  public static void setSecuredConfiguration(org.apache.hadoop.conf.Configuration);
    Code:
       0: aload_0
       1: ldc           #15                 // String hadoop.security.authentication
       3: ldc           #16                 // String kerberos
       5: invokevirtual #17                 // Method org/apache/hadoop/conf/Configuration.set:(Ljava/lang/String;Ljava/lang/String;)V
       8: aload_0
       9: ldc           #19                 // String hbase.security.authentication
      11: ldc           #16                 // String kerberos
      13: invokevirtual #17                 // Method org/apache/hadoop/conf/Configuration.set:(Ljava/lang/String;Ljava/lang/String;)V
      16: aload_0
      17: ldc           #20                 // String hbase.security.authorization
      19: iconst_1
      20: invokevirtual #21                 // Method org/apache/hadoop/conf/Configuration.setBoolean:(Ljava/lang/String;Z)V
      23: aload_0
      24: ldc           #7                  // String hbase.regionserver.keytab.file
      26: ldc           #7                  // String hbase.regionserver.keytab.file
      28: invokestatic  #6                  // Method java/lang/System.getProperty:(Ljava/lang/String;)Ljava/lang/String;
      31: invokevirtual #17                 // Method org/apache/hadoop/conf/Configuration.set:(Ljava/lang/String;Ljava/lang/String;)V
      34: aload_0
      35: ldc           #5                  // String hbase.regionserver.kerberos.principal
      37: ldc           #5                  // String hbase.regionserver.kerberos.principal
      39: invokestatic  #6                  // Method java/lang/System.getProperty:(Ljava/lang/String;)Ljava/lang/String;
      42: invokevirtual #17                 // Method org/apache/hadoop/conf/Configuration.set:(Ljava/lang/String;Ljava/lang/String;)V
      45: aload_0
      46: ldc           #25                 // String hbase.master.kerberos.principal
      48: ldc           #5                  // String hbase.regionserver.kerberos.principal
      50: invokestatic  #6                  // Method java/lang/System.getProperty:(Ljava/lang/String;)Ljava/lang/String;
      53: invokevirtual #17                 // Method org/apache/hadoop/conf/Configuration.set:(Ljava/lang/String;Ljava/lang/String;)V
      56: return

  public static void setSSLConfiguration(org.apache.hadoop.hbase.HBaseTestingUtility, java.lang.Class) throws java.lang.Exception;
    Code:
       0: aload_0
       1: invokevirtual #38                 // Method org/apache/hadoop/hbase/HBaseTestingUtility.getConfiguration:()Lorg/apache/hadoop/conf/Configuration;
       4: astore_2
       5: aload_2
       6: ldc           #39                 // String dfs.http.policy
       8: getstatic     #40                 // Field org/apache/hadoop/http/HttpConfig$Policy.HTTPS_ONLY:Lorg/apache/hadoop/http/HttpConfig$Policy;
      11: invokevirtual #41                 // Method org/apache/hadoop/http/HttpConfig$Policy.name:()Ljava/lang/String;
      14: invokevirtual #17                 // Method org/apache/hadoop/conf/Configuration.set:(Ljava/lang/String;Ljava/lang/String;)V
      17: aload_2
      18: ldc           #42                 // String dfs.namenode.https-address
      20: ldc           #43                 // String localhost:0
      22: invokevirtual #17                 // Method org/apache/hadoop/conf/Configuration.set:(Ljava/lang/String;Ljava/lang/String;)V
      25: aload_2
      26: ldc           #44                 // String dfs.datanode.https.address
      28: ldc           #43                 // String localhost:0
      30: invokevirtual #17                 // Method org/apache/hadoop/conf/Configuration.set:(Ljava/lang/String;Ljava/lang/String;)V
      33: new           #45                 // class java/io/File
      36: dup
      37: aload_0
      38: ldc           #46                 // String keystore
      40: invokevirtual #47                 // Method org/apache/hadoop/hbase/HBaseTestingUtility.getDataTestDir:(Ljava/lang/String;)Lorg/apache/hadoop/fs/Path;
      43: invokevirtual #48                 // Method org/apache/hadoop/fs/Path.toUri:()Ljava/net/URI;
      46: invokevirtual #49                 // Method java/net/URI.getPath:()Ljava/lang/String;
      49: invokespecial #50                 // Method java/io/File."<init>":(Ljava/lang/String;)V
      52: astore_3
      53: aload_3
      54: invokevirtual #51                 // Method java/io/File.mkdirs:()Z
      57: pop
      58: aload_1
      59: invokestatic  #52                 // Method org/apache/hadoop/hbase/http/ssl/KeyStoreTestUtil.getClasspathDir:(Ljava/lang/Class;)Ljava/lang/String;
      62: astore        4
      64: aload_3
      65: invokevirtual #53                 // Method java/io/File.getAbsolutePath:()Ljava/lang/String;
      68: aload         4
      70: aload_2
      71: iconst_0
      72: invokestatic  #54                 // Method org/apache/hadoop/hbase/http/ssl/KeyStoreTestUtil.setupSSLConfig:(Ljava/lang/String;Ljava/lang/String;Lorg/apache/hadoop/conf/Configuration;Z)V
      75: return

  public static org.apache.hadoop.security.UserGroupInformation loginAndReturnUGI(org.apache.hadoop.conf.Configuration, java.lang.String) throws java.io.IOException;
    Code:
       0: invokestatic  #55                 // Method java/net/InetAddress.getLocalHost:()Ljava/net/InetAddress;
       3: invokevirtual #56                 // Method java/net/InetAddress.getHostName:()Ljava/lang/String;
       6: astore_2
       7: new           #57                 // class java/lang/StringBuilder
      10: dup
      11: invokespecial #58                 // Method java/lang/StringBuilder."<init>":()V
      14: ldc           #59                 // String hbase.
      16: invokevirtual #60                 // Method java/lang/StringBuilder.append:(Ljava/lang/String;)Ljava/lang/StringBuilder;
      19: aload_1
      20: invokevirtual #60                 // Method java/lang/StringBuilder.append:(Ljava/lang/String;)Ljava/lang/StringBuilder;
      23: ldc           #61                 // String .keytab.file
      25: invokevirtual #60                 // Method java/lang/StringBuilder.append:(Ljava/lang/String;)Ljava/lang/StringBuilder;
      28: invokevirtual #62                 // Method java/lang/StringBuilder.toString:()Ljava/lang/String;
      31: astore_3
      32: aload_0
      33: aload_3
      34: invokevirtual #63                 // Method org/apache/hadoop/conf/Configuration.get:(Ljava/lang/String;)Ljava/lang/String;
      37: astore        4
      39: new           #57                 // class java/lang/StringBuilder
      42: dup
      43: invokespecial #58                 // Method java/lang/StringBuilder."<init>":()V
      46: ldc           #59                 // String hbase.
      48: invokevirtual #60                 // Method java/lang/StringBuilder.append:(Ljava/lang/String;)Ljava/lang/StringBuilder;
      51: aload_1
      52: invokevirtual #60                 // Method java/lang/StringBuilder.append:(Ljava/lang/String;)Ljava/lang/StringBuilder;
      55: ldc           #64                 // String .kerberos.principal
      57: invokevirtual #60                 // Method java/lang/StringBuilder.append:(Ljava/lang/String;)Ljava/lang/StringBuilder;
      60: invokevirtual #62                 // Method java/lang/StringBuilder.toString:()Ljava/lang/String;
      63: astore        5
      65: aload_0
      66: aload         5
      68: invokevirtual #63                 // Method org/apache/hadoop/conf/Configuration.get:(Ljava/lang/String;)Ljava/lang/String;
      71: aload_2
      72: invokestatic  #65                 // Method org/apache/hadoop/security/SecurityUtil.getServerPrincipal:(Ljava/lang/String;Ljava/lang/String;)Ljava/lang/String;
      75: astore        6
      77: aload         4
      79: ifnull        87
      82: aload         6
      84: ifnonnull     124
      87: getstatic     #66                 // Field LOG:Lorg/slf4j/Logger;
      90: new           #57                 // class java/lang/StringBuilder
      93: dup
      94: invokespecial #58                 // Method java/lang/StringBuilder."<init>":()V
      97: ldc           #67                 // String Principal or key tab file null for :
      99: invokevirtual #60                 // Method java/lang/StringBuilder.append:(Ljava/lang/String;)Ljava/lang/StringBuilder;
     102: aload         5
     104: invokevirtual #60                 // Method java/lang/StringBuilder.append:(Ljava/lang/String;)Ljava/lang/StringBuilder;
     107: ldc           #68                 // String ,
     109: invokevirtual #60                 // Method java/lang/StringBuilder.append:(Ljava/lang/String;)Ljava/lang/StringBuilder;
     112: aload_3
     113: invokevirtual #60                 // Method java/lang/StringBuilder.append:(Ljava/lang/String;)Ljava/lang/StringBuilder;
     116: invokevirtual #62                 // Method java/lang/StringBuilder.toString:()Ljava/lang/String;
     119: invokeinterface #69,  2           // InterfaceMethod org/slf4j/Logger.warn:(Ljava/lang/String;)V
     124: aload         6
     126: aload         4
     128: invokestatic  #70                 // Method org/apache/hadoop/security/UserGroupInformation.loginUserFromKeytabAndReturnUGI:(Ljava/lang/String;Ljava/lang/String;)Lorg/apache/hadoop/security/UserGroupInformation;
     131: astore        7
     133: aload         7
     135: areturn

  static {};
    Code:
       0: ldc           #4                  // class org/apache/hadoop/hbase/security/HBaseKerberosUtils
       2: invokestatic  #71                 // Method org/slf4j/LoggerFactory.getLogger:(Ljava/lang/Class;)Lorg/slf4j/Logger;
       5: putstatic     #66                 // Field LOG:Lorg/slf4j/Logger;
       8: return
}
