Compiled from "HBaseConfTool.java"
public class org.apache.hadoop.hbase.util.HBaseConfTool {
  public org.apache.hadoop.hbase.util.HBaseConfTool();
    Code:
       0: aload_0
       1: invokespecial #1                  // Method java/lang/Object."<init>":()V
       4: return

  public static void main(java.lang.String[]);
    Code:
       0: aload_0
       1: arraylength
       2: iconst_1
       3: if_icmpge     19
       6: getstatic     #2                  // Field java/lang/System.err:Ljava/io/PrintStream;
       9: ldc           #3                  // String Usage: HBaseConfTool <CONFIGURATION_KEY>
      11: invokevirtual #4                  // Method java/io/PrintStream.println:(Ljava/lang/String;)V
      14: iconst_1
      15: invokestatic  #5                  // Method java/lang/System.exit:(I)V
      18: return
      19: invokestatic  #6                  // Method org/apache/hadoop/hbase/HBaseConfiguration.create:()Lorg/apache/hadoop/conf/Configuration;
      22: astore_1
      23: getstatic     #7                  // Field java/lang/System.out:Ljava/io/PrintStream;
      26: aload_1
      27: aload_0
      28: iconst_0
      29: aaload
      30: invokevirtual #8                  // Method org/apache/hadoop/conf/Configuration.get:(Ljava/lang/String;)Ljava/lang/String;
      33: invokevirtual #4                  // Method java/io/PrintStream.println:(Ljava/lang/String;)V
      36: return
}
