Compiled from "HBaseAdmin.java"
class org.apache.hadoop.hbase.client.HBaseAdmin$92 extends org.apache.hadoop.hbase.client.MasterCallable<java.util.List<org.apache.hadoop.hbase.ServerName>> {
  final java.util.List val$servers;

  final org.apache.hadoop.hbase.client.HBaseAdmin this$0;

  org.apache.hadoop.hbase.client.HBaseAdmin$92(org.apache.hadoop.hbase.client.HBaseAdmin, org.apache.hadoop.hbase.client.Connection, org.apache.hadoop.hbase.ipc.RpcControllerFactory, java.util.List);
    Code:
       0: aload_0
       1: aload_1
       2: putfield      #1                  // Field this$0:Lorg/apache/hadoop/hbase/client/HBaseAdmin;
       5: aload_0
       6: aload         4
       8: putfield      #2                  // Field val$servers:Ljava/util/List;
      11: aload_0
      12: aload_2
      13: aload_3
      14: invokespecial #3                  // Method org/apache/hadoop/hbase/client/MasterCallable."<init>":(Lorg/apache/hadoop/hbase/client/Connection;Lorg/apache/hadoop/hbase/ipc/RpcControllerFactory;)V
      17: return

  protected java.util.List<org.apache.hadoop.hbase.ServerName> rpcCall() throws java.lang.Exception;
    Code:
       0: aload_0
       1: getfield      #2                  // Field val$servers:Ljava/util/List;
       4: ifnonnull     13
       7: invokestatic  #4                  // Method java/util/Collections.emptyList:()Ljava/util/List;
      10: goto          17
      13: aload_0
      14: getfield      #2                  // Field val$servers:Ljava/util/List;
      17: invokestatic  #5                  // Method org/apache/hadoop/hbase/shaded/protobuf/RequestConverter.buildClearDeadServersRequest:(Ljava/util/Collection;)Lorg/apache/hadoop/hbase/shaded/protobuf/generated/MasterProtos$ClearDeadServersRequest;
      20: astore_1
      21: aload_0
      22: getfield      #6                  // Field master:Lorg/apache/hadoop/hbase/client/MasterKeepAliveConnection;
      25: aload_0
      26: invokevirtual #7                  // Method getRpcController:()Lorg/apache/hadoop/hbase/ipc/HBaseRpcController;
      29: aload_1
      30: invokeinterface #8,  3            // InterfaceMethod org/apache/hadoop/hbase/client/MasterKeepAliveConnection.clearDeadServers:(Lorg/apache/hbase/thirdparty/com/google/protobuf/RpcController;Lorg/apache/hadoop/hbase/shaded/protobuf/generated/MasterProtos$ClearDeadServersRequest;)Lorg/apache/hadoop/hbase/shaded/protobuf/generated/MasterProtos$ClearDeadServersResponse;
      35: invokevirtual #9                  // Method org/apache/hadoop/hbase/shaded/protobuf/generated/MasterProtos$ClearDeadServersResponse.getServerNameList:()Ljava/util/List;
      38: invokestatic  #10                 // Method org/apache/hadoop/hbase/shaded/protobuf/ProtobufUtil.toServerNameList:(Ljava/util/List;)Ljava/util/List;
      41: areturn

  protected java.lang.Object rpcCall() throws java.lang.Exception;
    Code:
       0: aload_0
       1: invokevirtual #11                 // Method rpcCall:()Ljava/util/List;
       4: areturn
}
