Compiled from "HBaseProtos.java"
public final class org.apache.hadoop.hbase.protobuf.generated.HBaseProtos$CompareType extends java.lang.Enum<org.apache.hadoop.hbase.protobuf.generated.HBaseProtos$CompareType> implements com.google.protobuf.ProtocolMessageEnum {
  public static final org.apache.hadoop.hbase.protobuf.generated.HBaseProtos$CompareType LESS;

  public static final org.apache.hadoop.hbase.protobuf.generated.HBaseProtos$CompareType LESS_OR_EQUAL;

  public static final org.apache.hadoop.hbase.protobuf.generated.HBaseProtos$CompareType EQUAL;

  public static final org.apache.hadoop.hbase.protobuf.generated.HBaseProtos$CompareType NOT_EQUAL;

  public static final org.apache.hadoop.hbase.protobuf.generated.HBaseProtos$CompareType GREATER_OR_EQUAL;

  public static final org.apache.hadoop.hbase.protobuf.generated.HBaseProtos$CompareType GREATER;

  public static final org.apache.hadoop.hbase.protobuf.generated.HBaseProtos$CompareType NO_OP;

  public static final int LESS_VALUE;

  public static final int LESS_OR_EQUAL_VALUE;

  public static final int EQUAL_VALUE;

  public static final int NOT_EQUAL_VALUE;

  public static final int GREATER_OR_EQUAL_VALUE;

  public static final int GREATER_VALUE;

  public static final int NO_OP_VALUE;

  public static org.apache.hadoop.hbase.protobuf.generated.HBaseProtos$CompareType[] values();
    Code:
       0: getstatic     #1                  // Field $VALUES:[Lorg/apache/hadoop/hbase/protobuf/generated/HBaseProtos$CompareType;
       3: invokevirtual #2                  // Method "[Lorg/apache/hadoop/hbase/protobuf/generated/HBaseProtos$CompareType;".clone:()Ljava/lang/Object;
       6: checkcast     #3                  // class "[Lorg/apache/hadoop/hbase/protobuf/generated/HBaseProtos$CompareType;"
       9: areturn

  public static org.apache.hadoop.hbase.protobuf.generated.HBaseProtos$CompareType valueOf(java.lang.String);
    Code:
       0: ldc           #4                  // class org/apache/hadoop/hbase/protobuf/generated/HBaseProtos$CompareType
       2: aload_0
       3: invokestatic  #5                  // Method java/lang/Enum.valueOf:(Ljava/lang/Class;Ljava/lang/String;)Ljava/lang/Enum;
       6: checkcast     #4                  // class org/apache/hadoop/hbase/protobuf/generated/HBaseProtos$CompareType
       9: areturn

  public final int getNumber();
    Code:
       0: aload_0
       1: getfield      #6                  // Field value:I
       4: ireturn

  public static org.apache.hadoop.hbase.protobuf.generated.HBaseProtos$CompareType valueOf(int);
    Code:
       0: iload_0
       1: tableswitch   { // 0 to 6
                     0: 44
                     1: 48
                     2: 52
                     3: 56
                     4: 60
                     5: 64
                     6: 68
               default: 72
          }
      44: getstatic     #7                  // Field LESS:Lorg/apache/hadoop/hbase/protobuf/generated/HBaseProtos$CompareType;
      47: areturn
      48: getstatic     #8                  // Field LESS_OR_EQUAL:Lorg/apache/hadoop/hbase/protobuf/generated/HBaseProtos$CompareType;
      51: areturn
      52: getstatic     #9                  // Field EQUAL:Lorg/apache/hadoop/hbase/protobuf/generated/HBaseProtos$CompareType;
      55: areturn
      56: getstatic     #10                 // Field NOT_EQUAL:Lorg/apache/hadoop/hbase/protobuf/generated/HBaseProtos$CompareType;
      59: areturn
      60: getstatic     #11                 // Field GREATER_OR_EQUAL:Lorg/apache/hadoop/hbase/protobuf/generated/HBaseProtos$CompareType;
      63: areturn
      64: getstatic     #12                 // Field GREATER:Lorg/apache/hadoop/hbase/protobuf/generated/HBaseProtos$CompareType;
      67: areturn
      68: getstatic     #13                 // Field NO_OP:Lorg/apache/hadoop/hbase/protobuf/generated/HBaseProtos$CompareType;
      71: areturn
      72: aconst_null
      73: areturn

  public static com.google.protobuf.Internal$EnumLiteMap<org.apache.hadoop.hbase.protobuf.generated.HBaseProtos$CompareType> internalGetValueMap();
    Code:
       0: getstatic     #14                 // Field internalValueMap:Lcom/google/protobuf/Internal$EnumLiteMap;
       3: areturn

  public final com.google.protobuf.Descriptors$EnumValueDescriptor getValueDescriptor();
    Code:
       0: invokestatic  #15                 // Method getDescriptor:()Lcom/google/protobuf/Descriptors$EnumDescriptor;
       3: invokevirtual #16                 // Method com/google/protobuf/Descriptors$EnumDescriptor.getValues:()Ljava/util/List;
       6: aload_0
       7: getfield      #17                 // Field index:I
      10: invokeinterface #18,  2           // InterfaceMethod java/util/List.get:(I)Ljava/lang/Object;
      15: checkcast     #19                 // class com/google/protobuf/Descriptors$EnumValueDescriptor
      18: areturn

  public final com.google.protobuf.Descriptors$EnumDescriptor getDescriptorForType();
    Code:
       0: invokestatic  #15                 // Method getDescriptor:()Lcom/google/protobuf/Descriptors$EnumDescriptor;
       3: areturn

  public static final com.google.protobuf.Descriptors$EnumDescriptor getDescriptor();
    Code:
       0: invokestatic  #20                 // Method org/apache/hadoop/hbase/protobuf/generated/HBaseProtos.getDescriptor:()Lcom/google/protobuf/Descriptors$FileDescriptor;
       3: invokevirtual #21                 // Method com/google/protobuf/Descriptors$FileDescriptor.getEnumTypes:()Ljava/util/List;
       6: iconst_0
       7: invokeinterface #18,  2           // InterfaceMethod java/util/List.get:(I)Ljava/lang/Object;
      12: checkcast     #22                 // class com/google/protobuf/Descriptors$EnumDescriptor
      15: areturn

  public static org.apache.hadoop.hbase.protobuf.generated.HBaseProtos$CompareType valueOf(com.google.protobuf.Descriptors$EnumValueDescriptor);
    Code:
       0: aload_0
       1: invokevirtual #23                 // Method com/google/protobuf/Descriptors$EnumValueDescriptor.getType:()Lcom/google/protobuf/Descriptors$EnumDescriptor;
       4: invokestatic  #15                 // Method getDescriptor:()Lcom/google/protobuf/Descriptors$EnumDescriptor;
       7: if_acmpeq     20
      10: new           #24                 // class java/lang/IllegalArgumentException
      13: dup
      14: ldc           #25                 // String EnumValueDescriptor is not for this type.
      16: invokespecial #26                 // Method java/lang/IllegalArgumentException."<init>":(Ljava/lang/String;)V
      19: athrow
      20: getstatic     #27                 // Field VALUES:[Lorg/apache/hadoop/hbase/protobuf/generated/HBaseProtos$CompareType;
      23: aload_0
      24: invokevirtual #28                 // Method com/google/protobuf/Descriptors$EnumValueDescriptor.getIndex:()I
      27: aaload
      28: areturn

  static {};
    Code:
       0: new           #4                  // class org/apache/hadoop/hbase/protobuf/generated/HBaseProtos$CompareType
       3: dup
       4: ldc           #30                 // String LESS
       6: iconst_0
       7: iconst_0
       8: iconst_0
       9: invokespecial #31                 // Method "<init>":(Ljava/lang/String;III)V
      12: putstatic     #7                  // Field LESS:Lorg/apache/hadoop/hbase/protobuf/generated/HBaseProtos$CompareType;
      15: new           #4                  // class org/apache/hadoop/hbase/protobuf/generated/HBaseProtos$CompareType
      18: dup
      19: ldc           #32                 // String LESS_OR_EQUAL
      21: iconst_1
      22: iconst_1
      23: iconst_1
      24: invokespecial #31                 // Method "<init>":(Ljava/lang/String;III)V
      27: putstatic     #8                  // Field LESS_OR_EQUAL:Lorg/apache/hadoop/hbase/protobuf/generated/HBaseProtos$CompareType;
      30: new           #4                  // class org/apache/hadoop/hbase/protobuf/generated/HBaseProtos$CompareType
      33: dup
      34: ldc           #33                 // String EQUAL
      36: iconst_2
      37: iconst_2
      38: iconst_2
      39: invokespecial #31                 // Method "<init>":(Ljava/lang/String;III)V
      42: putstatic     #9                  // Field EQUAL:Lorg/apache/hadoop/hbase/protobuf/generated/HBaseProtos$CompareType;
      45: new           #4                  // class org/apache/hadoop/hbase/protobuf/generated/HBaseProtos$CompareType
      48: dup
      49: ldc           #34                 // String NOT_EQUAL
      51: iconst_3
      52: iconst_3
      53: iconst_3
      54: invokespecial #31                 // Method "<init>":(Ljava/lang/String;III)V
      57: putstatic     #10                 // Field NOT_EQUAL:Lorg/apache/hadoop/hbase/protobuf/generated/HBaseProtos$CompareType;
      60: new           #4                  // class org/apache/hadoop/hbase/protobuf/generated/HBaseProtos$CompareType
      63: dup
      64: ldc           #35                 // String GREATER_OR_EQUAL
      66: iconst_4
      67: iconst_4
      68: iconst_4
      69: invokespecial #31                 // Method "<init>":(Ljava/lang/String;III)V
      72: putstatic     #11                 // Field GREATER_OR_EQUAL:Lorg/apache/hadoop/hbase/protobuf/generated/HBaseProtos$CompareType;
      75: new           #4                  // class org/apache/hadoop/hbase/protobuf/generated/HBaseProtos$CompareType
      78: dup
      79: ldc           #36                 // String GREATER
      81: iconst_5
      82: iconst_5
      83: iconst_5
      84: invokespecial #31                 // Method "<init>":(Ljava/lang/String;III)V
      87: putstatic     #12                 // Field GREATER:Lorg/apache/hadoop/hbase/protobuf/generated/HBaseProtos$CompareType;
      90: new           #4                  // class org/apache/hadoop/hbase/protobuf/generated/HBaseProtos$CompareType
      93: dup
      94: ldc           #37                 // String NO_OP
      96: bipush        6
      98: bipush        6
     100: bipush        6
     102: invokespecial #31                 // Method "<init>":(Ljava/lang/String;III)V
     105: putstatic     #13                 // Field NO_OP:Lorg/apache/hadoop/hbase/protobuf/generated/HBaseProtos$CompareType;
     108: bipush        7
     110: anewarray     #4                  // class org/apache/hadoop/hbase/protobuf/generated/HBaseProtos$CompareType
     113: dup
     114: iconst_0
     115: getstatic     #7                  // Field LESS:Lorg/apache/hadoop/hbase/protobuf/generated/HBaseProtos$CompareType;
     118: aastore
     119: dup
     120: iconst_1
     121: getstatic     #8                  // Field LESS_OR_EQUAL:Lorg/apache/hadoop/hbase/protobuf/generated/HBaseProtos$CompareType;
     124: aastore
     125: dup
     126: iconst_2
     127: getstatic     #9                  // Field EQUAL:Lorg/apache/hadoop/hbase/protobuf/generated/HBaseProtos$CompareType;
     130: aastore
     131: dup
     132: iconst_3
     133: getstatic     #10                 // Field NOT_EQUAL:Lorg/apache/hadoop/hbase/protobuf/generated/HBaseProtos$CompareType;
     136: aastore
     137: dup
     138: iconst_4
     139: getstatic     #11                 // Field GREATER_OR_EQUAL:Lorg/apache/hadoop/hbase/protobuf/generated/HBaseProtos$CompareType;
     142: aastore
     143: dup
     144: iconst_5
     145: getstatic     #12                 // Field GREATER:Lorg/apache/hadoop/hbase/protobuf/generated/HBaseProtos$CompareType;
     148: aastore
     149: dup
     150: bipush        6
     152: getstatic     #13                 // Field NO_OP:Lorg/apache/hadoop/hbase/protobuf/generated/HBaseProtos$CompareType;
     155: aastore
     156: putstatic     #1                  // Field $VALUES:[Lorg/apache/hadoop/hbase/protobuf/generated/HBaseProtos$CompareType;
     159: new           #38                 // class org/apache/hadoop/hbase/protobuf/generated/HBaseProtos$CompareType$1
     162: dup
     163: invokespecial #39                 // Method org/apache/hadoop/hbase/protobuf/generated/HBaseProtos$CompareType$1."<init>":()V
     166: putstatic     #14                 // Field internalValueMap:Lcom/google/protobuf/Internal$EnumLiteMap;
     169: invokestatic  #40                 // Method values:()[Lorg/apache/hadoop/hbase/protobuf/generated/HBaseProtos$CompareType;
     172: putstatic     #27                 // Field VALUES:[Lorg/apache/hadoop/hbase/protobuf/generated/HBaseProtos$CompareType;
     175: return
}
