Compiled from "HBaseTestCase.java"
public abstract class org.apache.hadoop.hbase.HBaseTestCase extends junit.framework.TestCase {
  protected static final byte[] fam1;

  protected static final byte[] fam2;

  protected static final byte[] fam3;

  protected static final byte[][] COLUMNS;

  protected static org.apache.hadoop.fs.Path testDir;

  protected org.apache.hadoop.fs.FileSystem fs;

  protected org.apache.hadoop.hbase.regionserver.HRegion meta;

  protected static final char FIRST_CHAR;

  protected static final char LAST_CHAR;

  protected static final java.lang.String PUNCTUATION;

  protected static final byte[] START_KEY_BYTES;

  protected java.lang.String START_KEY;

  protected static final int MAXVERSIONS;

  protected final org.apache.hadoop.hbase.HBaseTestingUtility testUtil;

  public volatile org.apache.hadoop.conf.Configuration conf;

  public final org.apache.hadoop.hbase.util.FSTableDescriptors fsTableDescriptors;

  public org.apache.hadoop.hbase.HBaseTestCase();
    Code:
       0: aload_0
       1: invokespecial #1                  // Method junit/framework/TestCase."<init>":()V
       4: aload_0
       5: iconst_0
       6: putfield      #2                  // Field localfs:Z
       9: aload_0
      10: aconst_null
      11: putfield      #3                  // Field fs:Lorg/apache/hadoop/fs/FileSystem;
      14: aload_0
      15: aconst_null
      16: putfield      #4                  // Field meta:Lorg/apache/hadoop/hbase/regionserver/HRegion;
      19: aload_0
      20: new           #5                  // class java/lang/String
      23: dup
      24: getstatic     #6                  // Field START_KEY_BYTES:[B
      27: getstatic     #7                  // Field org/apache/hadoop/hbase/HConstants.UTF8_CHARSET:Ljava/nio/charset/Charset;
      30: invokespecial #8                  // Method java/lang/String."<init>":([BLjava/nio/charset/Charset;)V
      33: putfield      #9                  // Field START_KEY:Ljava/lang/String;
      36: aload_0
      37: new           #10                 // class org/apache/hadoop/hbase/HBaseTestingUtility
      40: dup
      41: invokespecial #11                 // Method org/apache/hadoop/hbase/HBaseTestingUtility."<init>":()V
      44: putfield      #12                 // Field testUtil:Lorg/apache/hadoop/hbase/HBaseTestingUtility;
      47: aload_0
      48: aload_0
      49: getfield      #12                 // Field testUtil:Lorg/apache/hadoop/hbase/HBaseTestingUtility;
      52: invokevirtual #13                 // Method org/apache/hadoop/hbase/HBaseTestingUtility.getConfiguration:()Lorg/apache/hadoop/conf/Configuration;
      55: putfield      #14                 // Field conf:Lorg/apache/hadoop/conf/Configuration;
      58: aload_0
      59: new           #15                 // class org/apache/hadoop/hbase/util/FSTableDescriptors
      62: dup
      63: aload_0
      64: getfield      #14                 // Field conf:Lorg/apache/hadoop/conf/Configuration;
      67: invokespecial #16                 // Method org/apache/hadoop/hbase/util/FSTableDescriptors."<init>":(Lorg/apache/hadoop/conf/Configuration;)V
      70: putfield      #17                 // Field fsTableDescriptors:Lorg/apache/hadoop/hbase/util/FSTableDescriptors;
      73: goto          88
      76: astore_1
      77: new           #19                 // class java/lang/RuntimeException
      80: dup
      81: ldc           #20                 // String Failed to init descriptors
      83: aload_1
      84: invokespecial #21                 // Method java/lang/RuntimeException."<init>":(Ljava/lang/String;Ljava/lang/Throwable;)V
      87: athrow
      88: return
    Exception table:
       from    to  target type
          58    73    76   Class java/io/IOException

  public org.apache.hadoop.hbase.HBaseTestCase(java.lang.String);
    Code:
       0: aload_0
       1: aload_1
       2: invokespecial #22                 // Method junit/framework/TestCase."<init>":(Ljava/lang/String;)V
       5: aload_0
       6: iconst_0
       7: putfield      #2                  // Field localfs:Z
      10: aload_0
      11: aconst_null
      12: putfield      #3                  // Field fs:Lorg/apache/hadoop/fs/FileSystem;
      15: aload_0
      16: aconst_null
      17: putfield      #4                  // Field meta:Lorg/apache/hadoop/hbase/regionserver/HRegion;
      20: aload_0
      21: new           #5                  // class java/lang/String
      24: dup
      25: getstatic     #6                  // Field START_KEY_BYTES:[B
      28: getstatic     #7                  // Field org/apache/hadoop/hbase/HConstants.UTF8_CHARSET:Ljava/nio/charset/Charset;
      31: invokespecial #8                  // Method java/lang/String."<init>":([BLjava/nio/charset/Charset;)V
      34: putfield      #9                  // Field START_KEY:Ljava/lang/String;
      37: aload_0
      38: new           #10                 // class org/apache/hadoop/hbase/HBaseTestingUtility
      41: dup
      42: invokespecial #11                 // Method org/apache/hadoop/hbase/HBaseTestingUtility."<init>":()V
      45: putfield      #12                 // Field testUtil:Lorg/apache/hadoop/hbase/HBaseTestingUtility;
      48: aload_0
      49: aload_0
      50: getfield      #12                 // Field testUtil:Lorg/apache/hadoop/hbase/HBaseTestingUtility;
      53: invokevirtual #13                 // Method org/apache/hadoop/hbase/HBaseTestingUtility.getConfiguration:()Lorg/apache/hadoop/conf/Configuration;
      56: putfield      #14                 // Field conf:Lorg/apache/hadoop/conf/Configuration;
      59: aload_0
      60: new           #15                 // class org/apache/hadoop/hbase/util/FSTableDescriptors
      63: dup
      64: aload_0
      65: getfield      #14                 // Field conf:Lorg/apache/hadoop/conf/Configuration;
      68: invokespecial #16                 // Method org/apache/hadoop/hbase/util/FSTableDescriptors."<init>":(Lorg/apache/hadoop/conf/Configuration;)V
      71: putfield      #17                 // Field fsTableDescriptors:Lorg/apache/hadoop/hbase/util/FSTableDescriptors;
      74: goto          89
      77: astore_2
      78: new           #19                 // class java/lang/RuntimeException
      81: dup
      82: ldc           #20                 // String Failed to init descriptors
      84: aload_2
      85: invokespecial #21                 // Method java/lang/RuntimeException."<init>":(Ljava/lang/String;Ljava/lang/Throwable;)V
      88: athrow
      89: return
    Exception table:
       from    to  target type
          59    74    77   Class java/io/IOException

  protected void setUp() throws java.lang.Exception;
    Code:
       0: aload_0
       1: invokespecial #23                 // Method junit/framework/TestCase.setUp:()V
       4: aload_0
       5: aload_0
       6: getfield      #14                 // Field conf:Lorg/apache/hadoop/conf/Configuration;
       9: ldc           #24                 // String fs.defaultFS
      11: ldc           #25                 // String file:///
      13: invokevirtual #26                 // Method org/apache/hadoop/conf/Configuration.get:(Ljava/lang/String;Ljava/lang/String;)Ljava/lang/String;
      16: ldc           #25                 // String file:///
      18: invokevirtual #27                 // Method java/lang/String.compareTo:(Ljava/lang/String;)I
      21: ifne          28
      24: iconst_1
      25: goto          29
      28: iconst_0
      29: putfield      #2                  // Field localfs:Z
      32: aload_0
      33: getfield      #3                  // Field fs:Lorg/apache/hadoop/fs/FileSystem;
      36: ifnonnull     50
      39: aload_0
      40: aload_0
      41: getfield      #14                 // Field conf:Lorg/apache/hadoop/conf/Configuration;
      44: invokestatic  #28                 // Method org/apache/hadoop/fs/FileSystem.get:(Lorg/apache/hadoop/conf/Configuration;)Lorg/apache/hadoop/fs/FileSystem;
      47: putfield      #3                  // Field fs:Lorg/apache/hadoop/fs/FileSystem;
      50: aload_0
      51: getfield      #2                  // Field localfs:Z
      54: ifeq          96
      57: aload_0
      58: aload_0
      59: invokevirtual #29                 // Method getName:()Ljava/lang/String;
      62: invokevirtual #30                 // Method getUnitTestdir:(Ljava/lang/String;)Lorg/apache/hadoop/fs/Path;
      65: putstatic     #31                 // Field testDir:Lorg/apache/hadoop/fs/Path;
      68: aload_0
      69: getfield      #3                  // Field fs:Lorg/apache/hadoop/fs/FileSystem;
      72: getstatic     #31                 // Field testDir:Lorg/apache/hadoop/fs/Path;
      75: invokevirtual #32                 // Method org/apache/hadoop/fs/FileSystem.exists:(Lorg/apache/hadoop/fs/Path;)Z
      78: ifeq          106
      81: aload_0
      82: getfield      #3                  // Field fs:Lorg/apache/hadoop/fs/FileSystem;
      85: getstatic     #31                 // Field testDir:Lorg/apache/hadoop/fs/Path;
      88: iconst_1
      89: invokevirtual #33                 // Method org/apache/hadoop/fs/FileSystem.delete:(Lorg/apache/hadoop/fs/Path;Z)Z
      92: pop
      93: goto          106
      96: aload_0
      97: getfield      #14                 // Field conf:Lorg/apache/hadoop/conf/Configuration;
     100: invokestatic  #34                 // Method org/apache/hadoop/hbase/util/FSUtils.getRootDir:(Lorg/apache/hadoop/conf/Configuration;)Lorg/apache/hadoop/fs/Path;
     103: putstatic     #31                 // Field testDir:Lorg/apache/hadoop/fs/Path;
     106: goto          126
     109: astore_1
     110: getstatic     #36                 // Field LOG:Lorg/slf4j/Logger;
     113: getstatic     #37                 // Field org/apache/hadoop/hbase/log/HBaseMarkers.FATAL:Lorg/slf4j/Marker;
     116: ldc           #38                 // String error during setup
     118: aload_1
     119: invokeinterface #39,  4           // InterfaceMethod org/slf4j/Logger.error:(Lorg/slf4j/Marker;Ljava/lang/String;Ljava/lang/Throwable;)V
     124: aload_1
     125: athrow
     126: return
    Exception table:
       from    to  target type
          50   106   109   Class java/lang/Exception

  protected void tearDown() throws java.lang.Exception;
    Code:
       0: aload_0
       1: getfield      #2                  // Field localfs:Z
       4: ifeq          32
       7: aload_0
       8: getfield      #3                  // Field fs:Lorg/apache/hadoop/fs/FileSystem;
      11: getstatic     #31                 // Field testDir:Lorg/apache/hadoop/fs/Path;
      14: invokevirtual #32                 // Method org/apache/hadoop/fs/FileSystem.exists:(Lorg/apache/hadoop/fs/Path;)Z
      17: ifeq          32
      20: aload_0
      21: getfield      #3                  // Field fs:Lorg/apache/hadoop/fs/FileSystem;
      24: getstatic     #31                 // Field testDir:Lorg/apache/hadoop/fs/Path;
      27: iconst_1
      28: invokevirtual #33                 // Method org/apache/hadoop/fs/FileSystem.delete:(Lorg/apache/hadoop/fs/Path;Z)Z
      31: pop
      32: goto          50
      35: astore_1
      36: getstatic     #36                 // Field LOG:Lorg/slf4j/Logger;
      39: getstatic     #37                 // Field org/apache/hadoop/hbase/log/HBaseMarkers.FATAL:Lorg/slf4j/Marker;
      42: ldc           #40                 // String error during tear down
      44: aload_1
      45: invokeinterface #39,  4           // InterfaceMethod org/slf4j/Logger.error:(Lorg/slf4j/Marker;Ljava/lang/String;Ljava/lang/Throwable;)V
      50: aload_0
      51: invokespecial #41                 // Method junit/framework/TestCase.tearDown:()V
      54: return
    Exception table:
       from    to  target type
           0    32    35   Class java/lang/Exception

  protected org.apache.hadoop.fs.Path getUnitTestdir(java.lang.String);
    Code:
       0: aload_0
       1: getfield      #12                 // Field testUtil:Lorg/apache/hadoop/hbase/HBaseTestingUtility;
       4: aload_1
       5: invokevirtual #42                 // Method org/apache/hadoop/hbase/HBaseTestingUtility.getDataTestDir:(Ljava/lang/String;)Lorg/apache/hadoop/fs/Path;
       8: areturn

  public org.apache.hadoop.hbase.regionserver.HRegion createNewHRegion(org.apache.hadoop.hbase.HTableDescriptor, byte[], byte[]) throws java.io.IOException;
    Code:
       0: aload_0
       1: aload_1
       2: aload_2
       3: aload_3
       4: aload_0
       5: getfield      #14                 // Field conf:Lorg/apache/hadoop/conf/Configuration;
       8: invokevirtual #43                 // Method createNewHRegion:(Lorg/apache/hadoop/hbase/HTableDescriptor;[B[BLorg/apache/hadoop/conf/Configuration;)Lorg/apache/hadoop/hbase/regionserver/HRegion;
      11: areturn

  public org.apache.hadoop.hbase.regionserver.HRegion createNewHRegion(org.apache.hadoop.hbase.HTableDescriptor, byte[], byte[], org.apache.hadoop.conf.Configuration) throws java.io.IOException;
    Code:
       0: new           #44                 // class org/apache/hadoop/hbase/HRegionInfo
       3: dup
       4: aload_1
       5: invokevirtual #45                 // Method org/apache/hadoop/hbase/HTableDescriptor.getTableName:()Lorg/apache/hadoop/hbase/TableName;
       8: aload_2
       9: aload_3
      10: invokespecial #46                 // Method org/apache/hadoop/hbase/HRegionInfo."<init>":(Lorg/apache/hadoop/hbase/TableName;[B[B)V
      13: astore        5
      15: aload         5
      17: getstatic     #31                 // Field testDir:Lorg/apache/hadoop/fs/Path;
      20: aload         4
      22: aload_1
      23: invokestatic  #47                 // Method org/apache/hadoop/hbase/HBaseTestingUtility.createRegionAndWAL:(Lorg/apache/hadoop/hbase/client/RegionInfo;Lorg/apache/hadoop/fs/Path;Lorg/apache/hadoop/conf/Configuration;Lorg/apache/hadoop/hbase/client/TableDescriptor;)Lorg/apache/hadoop/hbase/regionserver/HRegion;
      26: areturn

  protected org.apache.hadoop.hbase.regionserver.HRegion openClosedRegion(org.apache.hadoop.hbase.regionserver.HRegion) throws java.io.IOException;
    Code:
       0: aload_1
       1: aconst_null
       2: invokestatic  #48                 // Method org/apache/hadoop/hbase/regionserver/HRegion.openHRegion:(Lorg/apache/hadoop/hbase/regionserver/HRegion;Lorg/apache/hadoop/hbase/util/CancelableProgressable;)Lorg/apache/hadoop/hbase/regionserver/HRegion;
       5: areturn

  protected org.apache.hadoop.hbase.HTableDescriptor createTableDescriptor(java.lang.String);
    Code:
       0: aload_0
       1: aload_1
       2: iconst_3
       3: invokevirtual #50                 // Method createTableDescriptor:(Ljava/lang/String;I)Lorg/apache/hadoop/hbase/HTableDescriptor;
       6: areturn

  protected org.apache.hadoop.hbase.HTableDescriptor createTableDescriptor(java.lang.String, int);
    Code:
       0: aload_0
       1: aload_1
       2: iconst_0
       3: iload_2
       4: ldc           #53                 // int 2147483647
       6: getstatic     #54                 // Field org/apache/hadoop/hbase/HColumnDescriptor.DEFAULT_KEEP_DELETED:Lorg/apache/hadoop/hbase/KeepDeletedCells;
       9: invokevirtual #55                 // Method createTableDescriptor:(Ljava/lang/String;IIILorg/apache/hadoop/hbase/KeepDeletedCells;)Lorg/apache/hadoop/hbase/HTableDescriptor;
      12: areturn

  protected org.apache.hadoop.hbase.HTableDescriptor createTableDescriptor(java.lang.String, int, int, int, org.apache.hadoop.hbase.KeepDeletedCells);
    Code:
       0: new           #56                 // class org/apache/hadoop/hbase/HTableDescriptor
       3: dup
       4: aload_1
       5: invokestatic  #57                 // Method org/apache/hadoop/hbase/TableName.valueOf:(Ljava/lang/String;)Lorg/apache/hadoop/hbase/TableName;
       8: invokespecial #58                 // Method org/apache/hadoop/hbase/HTableDescriptor."<init>":(Lorg/apache/hadoop/hbase/TableName;)V
      11: astore        6
      13: iconst_3
      14: anewarray     #59                 // class "[B"
      17: dup
      18: iconst_0
      19: getstatic     #60                 // Field fam1:[B
      22: aastore
      23: dup
      24: iconst_1
      25: getstatic     #61                 // Field fam2:[B
      28: aastore
      29: dup
      30: iconst_2
      31: getstatic     #62                 // Field fam3:[B
      34: aastore
      35: astore        7
      37: aload         7
      39: arraylength
      40: istore        8
      42: iconst_0
      43: istore        9
      45: iload         9
      47: iload         8
      49: if_icmpge     102
      52: aload         7
      54: iload         9
      56: aaload
      57: astore        10
      59: aload         6
      61: new           #51                 // class org/apache/hadoop/hbase/HColumnDescriptor
      64: dup
      65: aload         10
      67: invokespecial #63                 // Method org/apache/hadoop/hbase/HColumnDescriptor."<init>":([B)V
      70: iload_2
      71: invokevirtual #64                 // Method org/apache/hadoop/hbase/HColumnDescriptor.setMinVersions:(I)Lorg/apache/hadoop/hbase/HColumnDescriptor;
      74: iload_3
      75: invokevirtual #65                 // Method org/apache/hadoop/hbase/HColumnDescriptor.setMaxVersions:(I)Lorg/apache/hadoop/hbase/HColumnDescriptor;
      78: aload         5
      80: invokevirtual #66                 // Method org/apache/hadoop/hbase/HColumnDescriptor.setKeepDeletedCells:(Lorg/apache/hadoop/hbase/KeepDeletedCells;)Lorg/apache/hadoop/hbase/HColumnDescriptor;
      83: iconst_0
      84: invokevirtual #67                 // Method org/apache/hadoop/hbase/HColumnDescriptor.setBlockCacheEnabled:(Z)Lorg/apache/hadoop/hbase/HColumnDescriptor;
      87: iload         4
      89: invokevirtual #68                 // Method org/apache/hadoop/hbase/HColumnDescriptor.setTimeToLive:(I)Lorg/apache/hadoop/hbase/HColumnDescriptor;
      92: invokevirtual #69                 // Method org/apache/hadoop/hbase/HTableDescriptor.addFamily:(Lorg/apache/hadoop/hbase/HColumnDescriptor;)Lorg/apache/hadoop/hbase/HTableDescriptor;
      95: pop
      96: iinc          9, 1
      99: goto          45
     102: aload         6
     104: areturn

  public static long addContent(org.apache.hadoop.hbase.regionserver.Region, byte[], byte[]) throws java.io.IOException;
    Code:
       0: aload_0
       1: invokeinterface #70,  1           // InterfaceMethod org/apache/hadoop/hbase/regionserver/Region.getRegionInfo:()Lorg/apache/hadoop/hbase/client/RegionInfo;
       6: invokeinterface #71,  1           // InterfaceMethod org/apache/hadoop/hbase/client/RegionInfo.getStartKey:()[B
      11: astore_3
      12: aload_0
      13: invokeinterface #70,  1           // InterfaceMethod org/apache/hadoop/hbase/regionserver/Region.getRegionInfo:()Lorg/apache/hadoop/hbase/client/RegionInfo;
      18: invokeinterface #72,  1           // InterfaceMethod org/apache/hadoop/hbase/client/RegionInfo.getEndKey:()[B
      23: astore        4
      25: aload_3
      26: astore        5
      28: aload         5
      30: ifnull        39
      33: aload         5
      35: arraylength
      36: ifne          44
      39: getstatic     #6                  // Field START_KEY_BYTES:[B
      42: astore        5
      44: new           #73                 // class org/apache/hadoop/hbase/regionserver/RegionAsTable
      47: dup
      48: aload_0
      49: invokespecial #74                 // Method org/apache/hadoop/hbase/regionserver/RegionAsTable."<init>":(Lorg/apache/hadoop/hbase/regionserver/Region;)V
      52: aload_1
      53: invokestatic  #75                 // Method org/apache/hadoop/hbase/util/Bytes.toString:([B)Ljava/lang/String;
      56: aload_2
      57: invokestatic  #75                 // Method org/apache/hadoop/hbase/util/Bytes.toString:([B)Ljava/lang/String;
      60: aload         5
      62: aload         4
      64: ldc2_w        #76                 // long -1l
      67: invokestatic  #78                 // Method addContent:(Lorg/apache/hadoop/hbase/client/Table;Ljava/lang/String;Ljava/lang/String;[B[BJ)J
      70: lreturn

  public static long addContent(org.apache.hadoop.hbase.regionserver.Region, byte[]) throws java.io.IOException;
    Code:
       0: aload_0
       1: aload_1
       2: aconst_null
       3: invokestatic  #79                 // Method addContent:(Lorg/apache/hadoop/hbase/regionserver/Region;[B[B)J
       6: lreturn

  public static long addContent(org.apache.hadoop.hbase.client.Table, java.lang.String) throws java.io.IOException;
    Code:
       0: aload_0
       1: aload_1
       2: getstatic     #6                  // Field START_KEY_BYTES:[B
       5: aconst_null
       6: invokestatic  #80                 // Method addContent:(Lorg/apache/hadoop/hbase/client/Table;Ljava/lang/String;[B[B)J
       9: lreturn

  public static long addContent(org.apache.hadoop.hbase.client.Table, java.lang.String, java.lang.String) throws java.io.IOException;
    Code:
       0: aload_0
       1: aload_1
       2: aload_2
       3: getstatic     #6                  // Field START_KEY_BYTES:[B
       6: aconst_null
       7: invokestatic  #81                 // Method addContent:(Lorg/apache/hadoop/hbase/client/Table;Ljava/lang/String;Ljava/lang/String;[B[B)J
      10: lreturn

  public static long addContent(org.apache.hadoop.hbase.client.Table, java.lang.String, byte[], byte[]) throws java.io.IOException;
    Code:
       0: aload_0
       1: aload_1
       2: aconst_null
       3: aload_2
       4: aload_3
       5: ldc2_w        #76                 // long -1l
       8: invokestatic  #78                 // Method addContent:(Lorg/apache/hadoop/hbase/client/Table;Ljava/lang/String;Ljava/lang/String;[B[BJ)J
      11: lreturn

  public static long addContent(org.apache.hadoop.hbase.client.Table, java.lang.String, java.lang.String, byte[], byte[]) throws java.io.IOException;
    Code:
       0: aload_0
       1: aload_1
       2: aload_2
       3: aload_3
       4: aload         4
       6: ldc2_w        #76                 // long -1l
       9: invokestatic  #78                 // Method addContent:(Lorg/apache/hadoop/hbase/client/Table;Ljava/lang/String;Ljava/lang/String;[B[BJ)J
      12: lreturn

  public static long addContent(org.apache.hadoop.hbase.client.Table, java.lang.String, java.lang.String, byte[], byte[], long) throws java.io.IOException;
    Code:
       0: lconst_0
       1: lstore        7
       3: aload_3
       4: iconst_1
       5: baload
       6: i2c
       7: istore        9
       9: aload_3
      10: iconst_2
      11: baload
      12: i2c
      13: istore        10
      15: aload_3
      16: iconst_0
      17: baload
      18: i2c
      19: istore        11
      21: iload         11
      23: bipush        122
      25: if_icmpgt     369
      28: iload         9
      30: istore        12
      32: iload         12
      34: bipush        122
      36: if_icmpgt     355
      39: iload         10
      41: istore        13
      43: iload         13
      45: bipush        122
      47: if_icmpgt     341
      50: iconst_3
      51: newarray       byte
      53: dup
      54: iconst_0
      55: iload         11
      57: i2b
      58: bastore
      59: dup
      60: iconst_1
      61: iload         12
      63: i2b
      64: bastore
      65: dup
      66: iconst_2
      67: iload         13
      69: i2b
      70: bastore
      71: astore        14
      73: aload         4
      75: ifnull        97
      78: aload         4
      80: arraylength
      81: ifle          97
      84: aload         4
      86: aload         14
      88: invokestatic  #82                 // Method org/apache/hadoop/hbase/util/Bytes.compareTo:([B[B)I
      91: ifgt          97
      94: goto          369
      97: lload         5
      99: ldc2_w        #76                 // long -1l
     102: lcmp
     103: ifeq          122
     106: new           #83                 // class org/apache/hadoop/hbase/client/Put
     109: dup
     110: aload         14
     112: lload         5
     114: invokespecial #84                 // Method org/apache/hadoop/hbase/client/Put."<init>":([BJ)V
     117: astore        15
     119: goto          133
     122: new           #83                 // class org/apache/hadoop/hbase/client/Put
     125: dup
     126: aload         14
     128: invokespecial #85                 // Method org/apache/hadoop/hbase/client/Put."<init>":([B)V
     131: astore        15
     133: new           #86                 // class java/lang/StringBuilder
     136: dup
     137: invokespecial #87                 // Method java/lang/StringBuilder."<init>":()V
     140: astore        16
     142: aload_2
     143: ifnull        165
     146: aload_2
     147: ldc           #88                 // String :
     149: invokevirtual #89                 // Method java/lang/String.contains:(Ljava/lang/CharSequence;)Z
     152: ifeq          165
     155: aload         16
     157: aload_2
     158: invokevirtual #90                 // Method java/lang/StringBuilder.append:(Ljava/lang/String;)Ljava/lang/StringBuilder;
     161: pop
     162: goto          204
     165: aload_1
     166: ifnull        204
     169: aload         16
     171: aload_1
     172: invokevirtual #90                 // Method java/lang/StringBuilder.append:(Ljava/lang/String;)Ljava/lang/StringBuilder;
     175: pop
     176: aload_1
     177: ldc           #88                 // String :
     179: invokevirtual #91                 // Method java/lang/String.endsWith:(Ljava/lang/String;)Z
     182: ifne          193
     185: aload         16
     187: ldc           #88                 // String :
     189: invokevirtual #90                 // Method java/lang/StringBuilder.append:(Ljava/lang/String;)Ljava/lang/StringBuilder;
     192: pop
     193: aload_2
     194: ifnull        204
     197: aload         16
     199: aload_2
     200: invokevirtual #90                 // Method java/lang/StringBuilder.append:(Ljava/lang/String;)Ljava/lang/StringBuilder;
     203: pop
     204: aload         16
     206: invokevirtual #92                 // Method java/lang/StringBuilder.toString:()Ljava/lang/String;
     209: invokestatic  #93                 // Method org/apache/hadoop/hbase/util/Bytes.toBytes:(Ljava/lang/String;)[B
     212: invokestatic  #94                 // Method org/apache/hadoop/hbase/CellUtil.parseColumn:([B)[[B
     215: astore        17
     217: aload         17
     219: arraylength
     220: iconst_1
     221: if_icmpne     246
     224: iconst_0
     225: newarray       byte
     227: astore        18
     229: aload         15
     231: aload         17
     233: iconst_0
     234: aaload
     235: aload         18
     237: aload         14
     239: invokevirtual #95                 // Method org/apache/hadoop/hbase/client/Put.addColumn:([B[B[B)Lorg/apache/hadoop/hbase/client/Put;
     242: pop
     243: goto          262
     246: aload         15
     248: aload         17
     250: iconst_0
     251: aaload
     252: aload         17
     254: iconst_1
     255: aaload
     256: aload         14
     258: invokevirtual #95                 // Method org/apache/hadoop/hbase/client/Put.addColumn:([B[B[B)Lorg/apache/hadoop/hbase/client/Put;
     261: pop
     262: aload         15
     264: getstatic     #96                 // Field org/apache/hadoop/hbase/client/Durability.SKIP_WAL:Lorg/apache/hadoop/hbase/client/Durability;
     267: invokevirtual #97                 // Method org/apache/hadoop/hbase/client/Put.setDurability:(Lorg/apache/hadoop/hbase/client/Durability;)Lorg/apache/hadoop/hbase/client/Put;
     270: pop
     271: aload_0
     272: aload         15
     274: invokeinterface #98,  2           // InterfaceMethod org/apache/hadoop/hbase/client/Table.put:(Lorg/apache/hadoop/hbase/client/Put;)V
     279: lload         7
     281: lconst_1
     282: ladd
     283: lstore        7
     285: goto          308
     288: astore        16
     290: aload         16
     292: invokevirtual #99                 // Method java/lang/RuntimeException.printStackTrace:()V
     295: aload         16
     297: athrow
     298: astore        16
     300: aload         16
     302: invokevirtual #100                // Method java/io/IOException.printStackTrace:()V
     305: aload         16
     307: athrow
     308: goto          331
     311: astore        15
     313: aload         15
     315: invokevirtual #99                 // Method java/lang/RuntimeException.printStackTrace:()V
     318: aload         15
     320: athrow
     321: astore        15
     323: aload         15
     325: invokevirtual #100                // Method java/io/IOException.printStackTrace:()V
     328: aload         15
     330: athrow
     331: iload         13
     333: iconst_1
     334: iadd
     335: i2c
     336: istore        13
     338: goto          43
     341: bipush        97
     343: istore        10
     345: iload         12
     347: iconst_1
     348: iadd
     349: i2c
     350: istore        12
     352: goto          32
     355: bipush        97
     357: istore        9
     359: iload         11
     361: iconst_1
     362: iadd
     363: i2c
     364: istore        11
     366: goto          21
     369: lload         7
     371: lreturn
    Exception table:
       from    to  target type
         133   285   288   Class java/lang/RuntimeException
         133   285   298   Class java/io/IOException
          97   308   311   Class java/lang/RuntimeException
          97   308   321   Class java/io/IOException

  protected void assertResultEquals(org.apache.hadoop.hbase.regionserver.HRegion, byte[], byte[], byte[], long, byte[]) throws java.io.IOException;
    Code:
       0: new           #101                // class org/apache/hadoop/hbase/client/Get
       3: dup
       4: aload_2
       5: invokespecial #102                // Method org/apache/hadoop/hbase/client/Get."<init>":([B)V
       8: astore        8
      10: aload         8
      12: lload         5
      14: invokevirtual #103                // Method org/apache/hadoop/hbase/client/Get.setTimestamp:(J)Lorg/apache/hadoop/hbase/client/Get;
      17: pop
      18: aload_1
      19: aload         8
      21: invokevirtual #104                // Method org/apache/hadoop/hbase/regionserver/HRegion.get:(Lorg/apache/hadoop/hbase/client/Get;)Lorg/apache/hadoop/hbase/client/Result;
      24: astore        9
      26: aload         9
      28: invokevirtual #105                // Method org/apache/hadoop/hbase/client/Result.getMap:()Ljava/util/NavigableMap;
      31: astore        10
      33: aload         10
      35: aload_3
      36: invokeinterface #106,  2          // InterfaceMethod java/util/NavigableMap.get:(Ljava/lang/Object;)Ljava/lang/Object;
      41: checkcast     #107                // class java/util/NavigableMap
      44: aload         4
      46: invokeinterface #106,  2          // InterfaceMethod java/util/NavigableMap.get:(Ljava/lang/Object;)Ljava/lang/Object;
      51: checkcast     #107                // class java/util/NavigableMap
      54: lload         5
      56: invokestatic  #108                // Method java/lang/Long.valueOf:(J)Ljava/lang/Long;
      59: invokeinterface #106,  2          // InterfaceMethod java/util/NavigableMap.get:(Ljava/lang/Object;)Ljava/lang/Object;
      64: checkcast     #59                 // class "[B"
      67: astore        11
      69: aload         7
      71: ifnonnull     123
      74: new           #86                 // class java/lang/StringBuilder
      77: dup
      78: invokespecial #87                 // Method java/lang/StringBuilder."<init>":()V
      81: aload_3
      82: invokestatic  #75                 // Method org/apache/hadoop/hbase/util/Bytes.toString:([B)Ljava/lang/String;
      85: invokevirtual #90                 // Method java/lang/StringBuilder.append:(Ljava/lang/String;)Ljava/lang/StringBuilder;
      88: ldc           #109                // String
      90: invokevirtual #90                 // Method java/lang/StringBuilder.append:(Ljava/lang/String;)Ljava/lang/StringBuilder;
      93: aload         4
      95: invokestatic  #75                 // Method org/apache/hadoop/hbase/util/Bytes.toString:([B)Ljava/lang/String;
      98: invokevirtual #90                 // Method java/lang/StringBuilder.append:(Ljava/lang/String;)Ljava/lang/StringBuilder;
     101: ldc           #110                // String  at timestamp
     103: invokevirtual #90                 // Method java/lang/StringBuilder.append:(Ljava/lang/String;)Ljava/lang/StringBuilder;
     106: lload         5
     108: invokevirtual #111                // Method java/lang/StringBuilder.append:(J)Ljava/lang/StringBuilder;
     111: invokevirtual #92                 // Method java/lang/StringBuilder.toString:()Ljava/lang/String;
     114: aconst_null
     115: aload         11
     117: invokestatic  #112                // Method assertEquals:(Ljava/lang/String;Ljava/lang/Object;Ljava/lang/Object;)V
     120: goto          251
     123: aload         11
     125: ifnonnull     189
     128: new           #86                 // class java/lang/StringBuilder
     131: dup
     132: invokespecial #87                 // Method java/lang/StringBuilder."<init>":()V
     135: aload_3
     136: invokestatic  #75                 // Method org/apache/hadoop/hbase/util/Bytes.toString:([B)Ljava/lang/String;
     139: invokevirtual #90                 // Method java/lang/StringBuilder.append:(Ljava/lang/String;)Ljava/lang/StringBuilder;
     142: ldc           #109                // String
     144: invokevirtual #90                 // Method java/lang/StringBuilder.append:(Ljava/lang/String;)Ljava/lang/StringBuilder;
     147: aload         4
     149: invokestatic  #75                 // Method org/apache/hadoop/hbase/util/Bytes.toString:([B)Ljava/lang/String;
     152: invokevirtual #90                 // Method java/lang/StringBuilder.append:(Ljava/lang/String;)Ljava/lang/StringBuilder;
     155: ldc           #110                // String  at timestamp
     157: invokevirtual #90                 // Method java/lang/StringBuilder.append:(Ljava/lang/String;)Ljava/lang/StringBuilder;
     160: lload         5
     162: invokevirtual #111                // Method java/lang/StringBuilder.append:(J)Ljava/lang/StringBuilder;
     165: ldc           #113                // String \" was expected to be \"
     167: invokevirtual #90                 // Method java/lang/StringBuilder.append:(Ljava/lang/String;)Ljava/lang/StringBuilder;
     170: aload         7
     172: invokestatic  #114                // Method org/apache/hadoop/hbase/util/Bytes.toStringBinary:([B)Ljava/lang/String;
     175: invokevirtual #90                 // Method java/lang/StringBuilder.append:(Ljava/lang/String;)Ljava/lang/StringBuilder;
     178: ldc           #115                // String  but was null
     180: invokevirtual #90                 // Method java/lang/StringBuilder.append:(Ljava/lang/String;)Ljava/lang/StringBuilder;
     183: invokevirtual #92                 // Method java/lang/StringBuilder.toString:()Ljava/lang/String;
     186: invokestatic  #116                // Method fail:(Ljava/lang/String;)V
     189: aload         11
     191: ifnull        251
     194: new           #86                 // class java/lang/StringBuilder
     197: dup
     198: invokespecial #87                 // Method java/lang/StringBuilder."<init>":()V
     201: aload_3
     202: invokestatic  #75                 // Method org/apache/hadoop/hbase/util/Bytes.toString:([B)Ljava/lang/String;
     205: invokevirtual #90                 // Method java/lang/StringBuilder.append:(Ljava/lang/String;)Ljava/lang/StringBuilder;
     208: ldc           #109                // String
     210: invokevirtual #90                 // Method java/lang/StringBuilder.append:(Ljava/lang/String;)Ljava/lang/StringBuilder;
     213: aload         4
     215: invokestatic  #75                 // Method org/apache/hadoop/hbase/util/Bytes.toString:([B)Ljava/lang/String;
     218: invokevirtual #90                 // Method java/lang/StringBuilder.append:(Ljava/lang/String;)Ljava/lang/StringBuilder;
     221: ldc           #110                // String  at timestamp
     223: invokevirtual #90                 // Method java/lang/StringBuilder.append:(Ljava/lang/String;)Ljava/lang/StringBuilder;
     226: lload         5
     228: invokevirtual #111                // Method java/lang/StringBuilder.append:(J)Ljava/lang/StringBuilder;
     231: invokevirtual #92                 // Method java/lang/StringBuilder.toString:()Ljava/lang/String;
     234: aload         7
     236: new           #5                  // class java/lang/String
     239: dup
     240: aload         11
     242: getstatic     #117                // Field java/nio/charset/StandardCharsets.UTF_8:Ljava/nio/charset/Charset;
     245: invokespecial #8                  // Method java/lang/String."<init>":([BLjava/nio/charset/Charset;)V
     248: invokestatic  #112                // Method assertEquals:(Ljava/lang/String;Ljava/lang/Object;Ljava/lang/Object;)V
     251: return

  public static void shutdownDfs(org.apache.hadoop.hdfs.MiniDFSCluster);
    Code:
       0: aload_0
       1: ifnull        63
       4: getstatic     #36                 // Field LOG:Lorg/slf4j/Logger;
       7: ldc           #118                // String Shutting down Mini DFS
       9: invokeinterface #119,  2          // InterfaceMethod org/slf4j/Logger.info:(Ljava/lang/String;)V
      14: aload_0
      15: invokevirtual #120                // Method org/apache/hadoop/hdfs/MiniDFSCluster.shutdown:()V
      18: goto          22
      21: astore_1
      22: aload_0
      23: invokevirtual #121                // Method org/apache/hadoop/hdfs/MiniDFSCluster.getFileSystem:()Lorg/apache/hadoop/hdfs/DistributedFileSystem;
      26: astore_1
      27: aload_1
      28: ifnull        45
      31: getstatic     #36                 // Field LOG:Lorg/slf4j/Logger;
      34: ldc           #122                // String Shutting down FileSystem
      36: invokeinterface #119,  2          // InterfaceMethod org/slf4j/Logger.info:(Ljava/lang/String;)V
      41: aload_1
      42: invokevirtual #123                // Method org/apache/hadoop/fs/FileSystem.close:()V
      45: invokestatic  #124                // Method org/apache/hadoop/fs/FileSystem.closeAll:()V
      48: goto          63
      51: astore_1
      52: getstatic     #36                 // Field LOG:Lorg/slf4j/Logger;
      55: ldc           #125                // String error closing file system
      57: aload_1
      58: invokeinterface #126,  3          // InterfaceMethod org/slf4j/Logger.error:(Ljava/lang/String;Ljava/lang/Throwable;)V
      63: return
    Exception table:
       from    to  target type
          14    18    21   Class java/lang/Exception
          22    48    51   Class java/io/IOException

  protected void createMetaRegion() throws java.io.IOException;
    Code:
       0: new           #15                 // class org/apache/hadoop/hbase/util/FSTableDescriptors
       3: dup
       4: aload_0
       5: getfield      #14                 // Field conf:Lorg/apache/hadoop/conf/Configuration;
       8: invokespecial #16                 // Method org/apache/hadoop/hbase/util/FSTableDescriptors."<init>":(Lorg/apache/hadoop/conf/Configuration;)V
      11: astore_1
      12: aload_0
      13: getstatic     #127                // Field org/apache/hadoop/hbase/HRegionInfo.FIRST_META_REGIONINFO:Lorg/apache/hadoop/hbase/HRegionInfo;
      16: getstatic     #31                 // Field testDir:Lorg/apache/hadoop/fs/Path;
      19: aload_0
      20: getfield      #14                 // Field conf:Lorg/apache/hadoop/conf/Configuration;
      23: aload_1
      24: getstatic     #128                // Field org/apache/hadoop/hbase/TableName.META_TABLE_NAME:Lorg/apache/hadoop/hbase/TableName;
      27: invokevirtual #129                // Method org/apache/hadoop/hbase/util/FSTableDescriptors.get:(Lorg/apache/hadoop/hbase/TableName;)Lorg/apache/hadoop/hbase/client/TableDescriptor;
      30: invokestatic  #47                 // Method org/apache/hadoop/hbase/HBaseTestingUtility.createRegionAndWAL:(Lorg/apache/hadoop/hbase/client/RegionInfo;Lorg/apache/hadoop/fs/Path;Lorg/apache/hadoop/conf/Configuration;Lorg/apache/hadoop/hbase/client/TableDescriptor;)Lorg/apache/hadoop/hbase/regionserver/HRegion;
      33: putfield      #4                  // Field meta:Lorg/apache/hadoop/hbase/regionserver/HRegion;
      36: return

  protected void closeRootAndMeta() throws java.io.IOException;
    Code:
       0: aload_0
       1: getfield      #4                  // Field meta:Lorg/apache/hadoop/hbase/regionserver/HRegion;
       4: invokestatic  #130                // Method org/apache/hadoop/hbase/HBaseTestingUtility.closeRegionAndWAL:(Lorg/apache/hadoop/hbase/regionserver/HRegion;)V
       7: return

  public static void assertByteEquals(byte[], byte[]);
    Code:
       0: aload_0
       1: aload_1
       2: invokestatic  #82                 // Method org/apache/hadoop/hbase/util/Bytes.compareTo:([B[B)I
       5: ifeq          55
       8: new           #131                // class junit/framework/AssertionFailedError
      11: dup
      12: new           #86                 // class java/lang/StringBuilder
      15: dup
      16: invokespecial #87                 // Method java/lang/StringBuilder."<init>":()V
      19: ldc           #132                // String expected:<
      21: invokevirtual #90                 // Method java/lang/StringBuilder.append:(Ljava/lang/String;)Ljava/lang/StringBuilder;
      24: aload_0
      25: invokestatic  #75                 // Method org/apache/hadoop/hbase/util/Bytes.toString:([B)Ljava/lang/String;
      28: invokevirtual #90                 // Method java/lang/StringBuilder.append:(Ljava/lang/String;)Ljava/lang/StringBuilder;
      31: ldc           #133                // String > but was:<
      33: invokevirtual #90                 // Method java/lang/StringBuilder.append:(Ljava/lang/String;)Ljava/lang/StringBuilder;
      36: aload_1
      37: invokestatic  #75                 // Method org/apache/hadoop/hbase/util/Bytes.toString:([B)Ljava/lang/String;
      40: invokevirtual #90                 // Method java/lang/StringBuilder.append:(Ljava/lang/String;)Ljava/lang/StringBuilder;
      43: ldc           #134                // String >
      45: invokevirtual #90                 // Method java/lang/StringBuilder.append:(Ljava/lang/String;)Ljava/lang/StringBuilder;
      48: invokevirtual #92                 // Method java/lang/StringBuilder.toString:()Ljava/lang/String;
      51: invokespecial #135                // Method junit/framework/AssertionFailedError."<init>":(Ljava/lang/String;)V
      54: athrow
      55: return

  public static void assertEquals(byte[], byte[]);
    Code:
       0: aload_0
       1: aload_1
       2: invokestatic  #82                 // Method org/apache/hadoop/hbase/util/Bytes.compareTo:([B[B)I
       5: ifeq          55
       8: new           #131                // class junit/framework/AssertionFailedError
      11: dup
      12: new           #86                 // class java/lang/StringBuilder
      15: dup
      16: invokespecial #87                 // Method java/lang/StringBuilder."<init>":()V
      19: ldc           #132                // String expected:<
      21: invokevirtual #90                 // Method java/lang/StringBuilder.append:(Ljava/lang/String;)Ljava/lang/StringBuilder;
      24: aload_0
      25: invokestatic  #114                // Method org/apache/hadoop/hbase/util/Bytes.toStringBinary:([B)Ljava/lang/String;
      28: invokevirtual #90                 // Method java/lang/StringBuilder.append:(Ljava/lang/String;)Ljava/lang/StringBuilder;
      31: ldc           #133                // String > but was:<
      33: invokevirtual #90                 // Method java/lang/StringBuilder.append:(Ljava/lang/String;)Ljava/lang/StringBuilder;
      36: aload_1
      37: invokestatic  #114                // Method org/apache/hadoop/hbase/util/Bytes.toStringBinary:([B)Ljava/lang/String;
      40: invokevirtual #90                 // Method java/lang/StringBuilder.append:(Ljava/lang/String;)Ljava/lang/StringBuilder;
      43: ldc           #134                // String >
      45: invokevirtual #90                 // Method java/lang/StringBuilder.append:(Ljava/lang/String;)Ljava/lang/StringBuilder;
      48: invokevirtual #92                 // Method java/lang/StringBuilder.toString:()Ljava/lang/String;
      51: invokespecial #135                // Method junit/framework/AssertionFailedError."<init>":(Ljava/lang/String;)V
      54: athrow
      55: return

  static {};
    Code:
       0: ldc           #49                 // class org/apache/hadoop/hbase/HBaseTestCase
       2: invokestatic  #136                // Method org/slf4j/LoggerFactory.getLogger:(Ljava/lang/Class;)Lorg/slf4j/Logger;
       5: putstatic     #36                 // Field LOG:Lorg/slf4j/Logger;
       8: ldc           #137                // String colfamily11
      10: invokestatic  #93                 // Method org/apache/hadoop/hbase/util/Bytes.toBytes:(Ljava/lang/String;)[B
      13: putstatic     #60                 // Field fam1:[B
      16: ldc           #138                // String colfamily21
      18: invokestatic  #93                 // Method org/apache/hadoop/hbase/util/Bytes.toBytes:(Ljava/lang/String;)[B
      21: putstatic     #61                 // Field fam2:[B
      24: ldc           #139                // String colfamily31
      26: invokestatic  #93                 // Method org/apache/hadoop/hbase/util/Bytes.toBytes:(Ljava/lang/String;)[B
      29: putstatic     #62                 // Field fam3:[B
      32: iconst_3
      33: anewarray     #59                 // class "[B"
      36: dup
      37: iconst_0
      38: getstatic     #60                 // Field fam1:[B
      41: aastore
      42: dup
      43: iconst_1
      44: getstatic     #61                 // Field fam2:[B
      47: aastore
      48: dup
      49: iconst_2
      50: getstatic     #62                 // Field fam3:[B
      53: aastore
      54: putstatic     #140                // Field COLUMNS:[[B
      57: aconst_null
      58: putstatic     #31                 // Field testDir:Lorg/apache/hadoop/fs/Path;
      61: iconst_3
      62: newarray       byte
      64: dup
      65: iconst_0
      66: bipush        97
      68: bastore
      69: dup
      70: iconst_1
      71: bipush        97
      73: bastore
      74: dup
      75: iconst_2
      76: bipush        97
      78: bastore
      79: putstatic     #6                  // Field START_KEY_BYTES:[B
      82: return
}
