Compiled from "HBaseRpcControllerImpl.java"
public class org.apache.hadoop.hbase.ipc.HBaseRpcControllerImpl implements org.apache.hadoop.hbase.ipc.HBaseRpcController {
  public org.apache.hadoop.hbase.ipc.HBaseRpcControllerImpl();
    Code:
       0: aload_0
       1: aconst_null
       2: checkcast     #1                  // class org/apache/hadoop/hbase/CellScanner
       5: invokespecial #2                  // Method "<init>":(Lorg/apache/hadoop/hbase/CellScanner;)V
       8: return

  public org.apache.hadoop.hbase.ipc.HBaseRpcControllerImpl(org.apache.hadoop.hbase.CellScanner);
    Code:
       0: aload_0
       1: invokespecial #3                  // Method java/lang/Object."<init>":()V
       4: aload_0
       5: iconst_0
       6: putfield      #4                  // Field done:Z
       9: aload_0
      10: iconst_0
      11: putfield      #5                  // Field cancelled:Z
      14: aload_0
      15: new           #6                  // class java/util/ArrayList
      18: dup
      19: invokespecial #7                  // Method java/util/ArrayList."<init>":()V
      22: putfield      #8                  // Field cancellationCbs:Ljava/util/List;
      25: aload_0
      26: iconst_m1
      27: putfield      #10                 // Field priority:I
      30: aload_0
      31: aload_1
      32: putfield      #11                 // Field cellScanner:Lorg/apache/hadoop/hbase/CellScanner;
      35: return

  public org.apache.hadoop.hbase.ipc.HBaseRpcControllerImpl(java.util.List<org.apache.hadoop.hbase.CellScannable>);
    Code:
       0: aload_0
       1: invokespecial #3                  // Method java/lang/Object."<init>":()V
       4: aload_0
       5: iconst_0
       6: putfield      #4                  // Field done:Z
       9: aload_0
      10: iconst_0
      11: putfield      #5                  // Field cancelled:Z
      14: aload_0
      15: new           #6                  // class java/util/ArrayList
      18: dup
      19: invokespecial #7                  // Method java/util/ArrayList."<init>":()V
      22: putfield      #8                  // Field cancellationCbs:Ljava/util/List;
      25: aload_0
      26: iconst_m1
      27: putfield      #10                 // Field priority:I
      30: aload_0
      31: aload_1
      32: ifnonnull     39
      35: aconst_null
      36: goto          43
      39: aload_1
      40: invokestatic  #12                 // Method org/apache/hadoop/hbase/CellUtil.createCellScanner:(Ljava/util/List;)Lorg/apache/hadoop/hbase/CellScanner;
      43: putfield      #11                 // Field cellScanner:Lorg/apache/hadoop/hbase/CellScanner;
      46: return

  public org.apache.hadoop.hbase.CellScanner cellScanner();
    Code:
       0: aload_0
       1: getfield      #11                 // Field cellScanner:Lorg/apache/hadoop/hbase/CellScanner;
       4: areturn

  public void setCellScanner(org.apache.hadoop.hbase.CellScanner);
    Code:
       0: aload_0
       1: aload_1
       2: putfield      #11                 // Field cellScanner:Lorg/apache/hadoop/hbase/CellScanner;
       5: return

  public void setPriority(int);
    Code:
       0: aload_0
       1: aload_0
       2: getfield      #10                 // Field priority:I
       5: iload_1
       6: invokestatic  #13                 // Method java/lang/Math.max:(II)I
       9: putfield      #10                 // Field priority:I
      12: return

  public void setPriority(org.apache.hadoop.hbase.TableName);
    Code:
       0: aload_0
       1: aload_1
       2: ifnull        18
       5: aload_1
       6: invokevirtual #14                 // Method org/apache/hadoop/hbase/TableName.isSystemTable:()Z
       9: ifeq          18
      12: sipush        200
      15: goto          19
      18: iconst_0
      19: invokevirtual #15                 // Method setPriority:(I)V
      22: return

  public int getPriority();
    Code:
       0: aload_0
       1: getfield      #10                 // Field priority:I
       4: ifge          11
       7: iconst_0
       8: goto          15
      11: aload_0
      12: getfield      #10                 // Field priority:I
      15: ireturn

  public void reset();
    Code:
       0: aload_0
       1: iconst_0
       2: putfield      #10                 // Field priority:I
       5: aload_0
       6: aconst_null
       7: putfield      #11                 // Field cellScanner:Lorg/apache/hadoop/hbase/CellScanner;
      10: aload_0
      11: aconst_null
      12: putfield      #16                 // Field exception:Ljava/io/IOException;
      15: aload_0
      16: aconst_null
      17: putfield      #17                 // Field callTimeout:Ljava/lang/Integer;
      20: aload_0
      21: dup
      22: astore_1
      23: monitorenter
      24: aload_0
      25: iconst_0
      26: putfield      #4                  // Field done:Z
      29: aload_0
      30: iconst_0
      31: putfield      #5                  // Field cancelled:Z
      34: aload_0
      35: getfield      #8                  // Field cancellationCbs:Ljava/util/List;
      38: invokeinterface #18,  1           // InterfaceMethod java/util/List.clear:()V
      43: aload_1
      44: monitorexit
      45: goto          53
      48: astore_2
      49: aload_1
      50: monitorexit
      51: aload_2
      52: athrow
      53: return
    Exception table:
       from    to  target type
          24    45    48   any
          48    51    48   any

  public int getCallTimeout();
    Code:
       0: aload_0
       1: getfield      #17                 // Field callTimeout:Ljava/lang/Integer;
       4: ifnull        15
       7: aload_0
       8: getfield      #17                 // Field callTimeout:Ljava/lang/Integer;
      11: invokevirtual #19                 // Method java/lang/Integer.intValue:()I
      14: ireturn
      15: iconst_0
      16: ireturn

  public void setCallTimeout(int);
    Code:
       0: aload_0
       1: iload_1
       2: invokestatic  #20                 // Method java/lang/Integer.valueOf:(I)Ljava/lang/Integer;
       5: putfield      #17                 // Field callTimeout:Ljava/lang/Integer;
       8: return

  public boolean hasCallTimeout();
    Code:
       0: aload_0
       1: getfield      #17                 // Field callTimeout:Ljava/lang/Integer;
       4: ifnull        11
       7: iconst_1
       8: goto          12
      11: iconst_0
      12: ireturn

  public synchronized java.lang.String errorText();
    Code:
       0: aload_0
       1: getfield      #4                  // Field done:Z
       4: ifeq          14
       7: aload_0
       8: getfield      #16                 // Field exception:Ljava/io/IOException;
      11: ifnonnull     16
      14: aconst_null
      15: areturn
      16: aload_0
      17: getfield      #16                 // Field exception:Ljava/io/IOException;
      20: invokevirtual #21                 // Method java/io/IOException.getMessage:()Ljava/lang/String;
      23: areturn

  public synchronized boolean failed();
    Code:
       0: aload_0
       1: getfield      #4                  // Field done:Z
       4: ifeq          18
       7: aload_0
       8: getfield      #16                 // Field exception:Ljava/io/IOException;
      11: ifnull        18
      14: iconst_1
      15: goto          19
      18: iconst_0
      19: ireturn

  public synchronized boolean isCanceled();
    Code:
       0: aload_0
       1: getfield      #5                  // Field cancelled:Z
       4: ireturn

  public void notifyOnCancel(org.apache.hbase.thirdparty.com.google.protobuf.RpcCallback<java.lang.Object>);
    Code:
       0: aload_0
       1: dup
       2: astore_2
       3: monitorenter
       4: aload_0
       5: getfield      #4                  // Field done:Z
       8: ifeq          14
      11: aload_2
      12: monitorexit
      13: return
      14: aload_0
      15: getfield      #5                  // Field cancelled:Z
      18: ifne          35
      21: aload_0
      22: getfield      #8                  // Field cancellationCbs:Ljava/util/List;
      25: aload_1
      26: invokeinterface #22,  2           // InterfaceMethod java/util/List.add:(Ljava/lang/Object;)Z
      31: pop
      32: aload_2
      33: monitorexit
      34: return
      35: aload_2
      36: monitorexit
      37: goto          45
      40: astore_3
      41: aload_2
      42: monitorexit
      43: aload_3
      44: athrow
      45: aload_1
      46: aconst_null
      47: invokeinterface #23,  2           // InterfaceMethod org/apache/hbase/thirdparty/com/google/protobuf/RpcCallback.run:(Ljava/lang/Object;)V
      52: return
    Exception table:
       from    to  target type
           4    13    40   any
          14    34    40   any
          35    37    40   any
          40    43    40   any

  public synchronized void setFailed(java.lang.String);
    Code:
       0: aload_0
       1: getfield      #4                  // Field done:Z
       4: ifeq          8
       7: return
       8: aload_0
       9: iconst_1
      10: putfield      #4                  // Field done:Z
      13: aload_0
      14: new           #24                 // class java/io/IOException
      17: dup
      18: aload_1
      19: invokespecial #25                 // Method java/io/IOException."<init>":(Ljava/lang/String;)V
      22: putfield      #16                 // Field exception:Ljava/io/IOException;
      25: return

  public synchronized void setFailed(java.io.IOException);
    Code:
       0: aload_0
       1: getfield      #4                  // Field done:Z
       4: ifeq          8
       7: return
       8: aload_0
       9: iconst_1
      10: putfield      #4                  // Field done:Z
      13: aload_0
      14: aload_1
      15: putfield      #16                 // Field exception:Ljava/io/IOException;
      18: return

  public synchronized java.io.IOException getFailed();
    Code:
       0: aload_0
       1: getfield      #4                  // Field done:Z
       4: ifeq          14
       7: aload_0
       8: getfield      #16                 // Field exception:Ljava/io/IOException;
      11: goto          15
      14: aconst_null
      15: areturn

  public synchronized void setDone(org.apache.hadoop.hbase.CellScanner);
    Code:
       0: aload_0
       1: getfield      #4                  // Field done:Z
       4: ifeq          8
       7: return
       8: aload_0
       9: iconst_1
      10: putfield      #4                  // Field done:Z
      13: aload_0
      14: aload_1
      15: putfield      #11                 // Field cellScanner:Lorg/apache/hadoop/hbase/CellScanner;
      18: return

  public void startCancel();
    Code:
       0: aload_0
       1: dup
       2: astore_2
       3: monitorenter
       4: aload_0
       5: getfield      #4                  // Field done:Z
       8: ifeq          14
      11: aload_2
      12: monitorexit
      13: return
      14: aload_0
      15: iconst_1
      16: putfield      #4                  // Field done:Z
      19: aload_0
      20: iconst_1
      21: putfield      #5                  // Field cancelled:Z
      24: new           #6                  // class java/util/ArrayList
      27: dup
      28: aload_0
      29: getfield      #8                  // Field cancellationCbs:Ljava/util/List;
      32: invokespecial #26                 // Method java/util/ArrayList."<init>":(Ljava/util/Collection;)V
      35: astore_1
      36: aload_2
      37: monitorexit
      38: goto          46
      41: astore_3
      42: aload_2
      43: monitorexit
      44: aload_3
      45: athrow
      46: aload_1
      47: invokeinterface #27,  1           // InterfaceMethod java/util/List.iterator:()Ljava/util/Iterator;
      52: astore_2
      53: aload_2
      54: invokeinterface #28,  1           // InterfaceMethod java/util/Iterator.hasNext:()Z
      59: ifeq          82
      62: aload_2
      63: invokeinterface #29,  1           // InterfaceMethod java/util/Iterator.next:()Ljava/lang/Object;
      68: checkcast     #30                 // class org/apache/hbase/thirdparty/com/google/protobuf/RpcCallback
      71: astore_3
      72: aload_3
      73: aconst_null
      74: invokeinterface #23,  2           // InterfaceMethod org/apache/hbase/thirdparty/com/google/protobuf/RpcCallback.run:(Ljava/lang/Object;)V
      79: goto          53
      82: return
    Exception table:
       from    to  target type
           4    13    41   any
          14    38    41   any
          41    44    41   any

  public synchronized void notifyOnCancel(org.apache.hbase.thirdparty.com.google.protobuf.RpcCallback<java.lang.Object>, org.apache.hadoop.hbase.ipc.HBaseRpcController$CancellationCallback) throws java.io.IOException;
    Code:
       0: aload_0
       1: getfield      #5                  // Field cancelled:Z
       4: ifeq          17
       7: aload_2
       8: iconst_1
       9: invokeinterface #31,  2           // InterfaceMethod org/apache/hadoop/hbase/ipc/HBaseRpcController$CancellationCallback.run:(Z)V
      14: goto          35
      17: aload_0
      18: getfield      #8                  // Field cancellationCbs:Ljava/util/List;
      21: aload_1
      22: invokeinterface #22,  2           // InterfaceMethod java/util/List.add:(Ljava/lang/Object;)Z
      27: pop
      28: aload_2
      29: iconst_0
      30: invokeinterface #31,  2           // InterfaceMethod org/apache/hadoop/hbase/ipc/HBaseRpcController$CancellationCallback.run:(Z)V
      35: return
}
