Compiled from "HBaseAdmin.java"
class org.apache.hadoop.hbase.client.HBaseAdmin$14 extends org.apache.hadoop.hbase.client.RpcRetryingCallable<java.lang.Boolean> {
  final org.apache.hadoop.hbase.TableName val$tableName;

  final org.apache.hadoop.hbase.client.HBaseAdmin this$0;

  org.apache.hadoop.hbase.client.HBaseAdmin$14(org.apache.hadoop.hbase.client.HBaseAdmin, org.apache.hadoop.hbase.TableName);
    Code:
       0: aload_0
       1: aload_1
       2: putfield      #1                  // Field this$0:Lorg/apache/hadoop/hbase/client/HBaseAdmin;
       5: aload_0
       6: aload_2
       7: putfield      #2                  // Field val$tableName:Lorg/apache/hadoop/hbase/TableName;
      10: aload_0
      11: invokespecial #3                  // Method org/apache/hadoop/hbase/client/RpcRetryingCallable."<init>":()V
      14: return

  protected java.lang.Boolean rpcCall(int) throws java.lang.Exception;
    Code:
       0: aload_0
       1: getfield      #1                  // Field this$0:Lorg/apache/hadoop/hbase/client/HBaseAdmin;
       4: invokevirtual #4                  // Method org/apache/hadoop/hbase/client/HBaseAdmin.getConnection:()Lorg/apache/hadoop/hbase/client/Connection;
       7: aload_0
       8: getfield      #2                  // Field val$tableName:Lorg/apache/hadoop/hbase/TableName;
      11: invokestatic  #5                  // Method org/apache/hadoop/hbase/MetaTableAccessor.getTableState:(Lorg/apache/hadoop/hbase/client/Connection;Lorg/apache/hadoop/hbase/TableName;)Lorg/apache/hadoop/hbase/client/TableState;
      14: astore_2
      15: aload_2
      16: ifnonnull     31
      19: new           #6                  // class org/apache/hadoop/hbase/TableNotFoundException
      22: dup
      23: aload_0
      24: getfield      #2                  // Field val$tableName:Lorg/apache/hadoop/hbase/TableName;
      27: invokespecial #7                  // Method org/apache/hadoop/hbase/TableNotFoundException."<init>":(Lorg/apache/hadoop/hbase/TableName;)V
      30: athrow
      31: aload_2
      32: getstatic     #8                  // Field org/apache/hadoop/hbase/client/TableState$State.ENABLED:Lorg/apache/hadoop/hbase/client/TableState$State;
      35: invokevirtual #9                  // Method org/apache/hadoop/hbase/client/TableState.inStates:(Lorg/apache/hadoop/hbase/client/TableState$State;)Z
      38: invokestatic  #10                 // Method java/lang/Boolean.valueOf:(Z)Ljava/lang/Boolean;
      41: areturn

  protected java.lang.Object rpcCall(int) throws java.lang.Exception;
    Code:
       0: aload_0
       1: iload_1
       2: invokevirtual #11                 // Method rpcCall:(I)Ljava/lang/Boolean;
       5: areturn
}
