Compiled from "HBaseTestingUtility.java"
class org.apache.hadoop.hbase.HBaseTestingUtility$5 implements org.apache.hadoop.hbase.Waiter$ExplainingPredicate<java.io.IOException> {
  final org.apache.hadoop.hbase.HBaseTestingUtility this$0;

  org.apache.hadoop.hbase.HBaseTestingUtility$5(org.apache.hadoop.hbase.HBaseTestingUtility);
    Code:
       0: aload_0
       1: aload_1
       2: putfield      #1                  // Field this$0:Lorg/apache/hadoop/hbase/HBaseTestingUtility;
       5: aload_0
       6: invokespecial #2                  // Method java/lang/Object."<init>":()V
       9: return

  public java.lang.String explainFailure() throws java.io.IOException;
    Code:
       0: aload_0
       1: getfield      #1                  // Field this$0:Lorg/apache/hadoop/hbase/HBaseTestingUtility;
       4: invokevirtual #3                  // Method org/apache/hadoop/hbase/HBaseTestingUtility.getMiniHBaseCluster:()Lorg/apache/hadoop/hbase/MiniHBaseCluster;
       7: invokevirtual #4                  // Method org/apache/hadoop/hbase/MiniHBaseCluster.getMaster:()Lorg/apache/hadoop/hbase/master/HMaster;
      10: invokevirtual #5                  // Method org/apache/hadoop/hbase/master/HMaster.getAssignmentManager:()Lorg/apache/hadoop/hbase/master/assignment/AssignmentManager;
      13: invokevirtual #6                  // Method org/apache/hadoop/hbase/master/assignment/AssignmentManager.getRegionStates:()Lorg/apache/hadoop/hbase/master/assignment/RegionStates;
      16: astore_1
      17: new           #7                  // class java/lang/StringBuilder
      20: dup
      21: invokespecial #8                  // Method java/lang/StringBuilder."<init>":()V
      24: ldc           #9                  // String found in transition:
      26: invokevirtual #10                 // Method java/lang/StringBuilder.append:(Ljava/lang/String;)Ljava/lang/StringBuilder;
      29: aload_1
      30: invokevirtual #11                 // Method org/apache/hadoop/hbase/master/assignment/RegionStates.getRegionsInTransition:()Ljava/util/List;
      33: invokevirtual #12                 // Method java/lang/Object.toString:()Ljava/lang/String;
      36: invokevirtual #10                 // Method java/lang/StringBuilder.append:(Ljava/lang/String;)Ljava/lang/StringBuilder;
      39: invokevirtual #13                 // Method java/lang/StringBuilder.toString:()Ljava/lang/String;
      42: areturn

  public boolean evaluate() throws java.io.IOException;
    Code:
       0: aload_0
       1: getfield      #1                  // Field this$0:Lorg/apache/hadoop/hbase/HBaseTestingUtility;
       4: invokevirtual #3                  // Method org/apache/hadoop/hbase/HBaseTestingUtility.getMiniHBaseCluster:()Lorg/apache/hadoop/hbase/MiniHBaseCluster;
       7: invokevirtual #4                  // Method org/apache/hadoop/hbase/MiniHBaseCluster.getMaster:()Lorg/apache/hadoop/hbase/master/HMaster;
      10: astore_1
      11: aload_1
      12: ifnonnull     17
      15: iconst_0
      16: ireturn
      17: aload_1
      18: invokevirtual #5                  // Method org/apache/hadoop/hbase/master/HMaster.getAssignmentManager:()Lorg/apache/hadoop/hbase/master/assignment/AssignmentManager;
      21: astore_2
      22: aload_2
      23: ifnonnull     28
      26: iconst_0
      27: ireturn
      28: aload_2
      29: invokevirtual #14                 // Method org/apache/hadoop/hbase/master/assignment/AssignmentManager.hasRegionsInTransition:()Z
      32: ifne          39
      35: iconst_1
      36: goto          40
      39: iconst_0
      40: ireturn
}
