Compiled from "HBaseAdmin.java"
class org.apache.hadoop.hbase.client.HBaseAdmin$TableFuture$4 implements org.apache.hadoop.hbase.MetaTableAccessor$Visitor {
  final org.apache.hadoop.hbase.client.TableDescriptor val$desc;

  final java.util.concurrent.atomic.AtomicInteger val$actualRegCount;

  final org.apache.hadoop.hbase.client.HBaseAdmin$TableFuture this$0;

  org.apache.hadoop.hbase.client.HBaseAdmin$TableFuture$4(org.apache.hadoop.hbase.client.HBaseAdmin$TableFuture, org.apache.hadoop.hbase.client.TableDescriptor, java.util.concurrent.atomic.AtomicInteger);
    Code:
       0: aload_0
       1: aload_1
       2: putfield      #1                  // Field this$0:Lorg/apache/hadoop/hbase/client/HBaseAdmin$TableFuture;
       5: aload_0
       6: aload_2
       7: putfield      #2                  // Field val$desc:Lorg/apache/hadoop/hbase/client/TableDescriptor;
      10: aload_0
      11: aload_3
      12: putfield      #3                  // Field val$actualRegCount:Ljava/util/concurrent/atomic/AtomicInteger;
      15: aload_0
      16: invokespecial #4                  // Method java/lang/Object."<init>":()V
      19: return

  public boolean visit(org.apache.hadoop.hbase.client.Result) throws java.io.IOException;
    Code:
       0: aload_1
       1: invokestatic  #5                  // Method org/apache/hadoop/hbase/MetaTableAccessor.getRegionLocations:(Lorg/apache/hadoop/hbase/client/Result;)Lorg/apache/hadoop/hbase/RegionLocations;
       4: astore_2
       5: aload_2
       6: ifnonnull     38
       9: invokestatic  #6                  // Method org/apache/hadoop/hbase/client/HBaseAdmin.access$200:()Lorg/slf4j/Logger;
      12: new           #7                  // class java/lang/StringBuilder
      15: dup
      16: invokespecial #8                  // Method java/lang/StringBuilder."<init>":()V
      19: ldc           #9                  // String No serialized HRegionInfo in
      21: invokevirtual #10                 // Method java/lang/StringBuilder.append:(Ljava/lang/String;)Ljava/lang/StringBuilder;
      24: aload_1
      25: invokevirtual #11                 // Method java/lang/StringBuilder.append:(Ljava/lang/Object;)Ljava/lang/StringBuilder;
      28: invokevirtual #12                 // Method java/lang/StringBuilder.toString:()Ljava/lang/String;
      31: invokeinterface #13,  2           // InterfaceMethod org/slf4j/Logger.warn:(Ljava/lang/String;)V
      36: iconst_1
      37: ireturn
      38: aload_2
      39: invokevirtual #14                 // Method org/apache/hadoop/hbase/RegionLocations.getRegionLocation:()Lorg/apache/hadoop/hbase/HRegionLocation;
      42: astore_3
      43: aload_3
      44: ifnonnull     49
      47: iconst_1
      48: ireturn
      49: aload_3
      50: invokevirtual #15                 // Method org/apache/hadoop/hbase/HRegionLocation.getRegion:()Lorg/apache/hadoop/hbase/client/RegionInfo;
      53: invokeinterface #16,  1           // InterfaceMethod org/apache/hadoop/hbase/client/RegionInfo.getTable:()Lorg/apache/hadoop/hbase/TableName;
      58: aload_0
      59: getfield      #2                  // Field val$desc:Lorg/apache/hadoop/hbase/client/TableDescriptor;
      62: invokeinterface #17,  1           // InterfaceMethod org/apache/hadoop/hbase/client/TableDescriptor.getTableName:()Lorg/apache/hadoop/hbase/TableName;
      67: invokevirtual #18                 // Method org/apache/hadoop/hbase/TableName.equals:(Ljava/lang/Object;)Z
      70: ifne          75
      73: iconst_0
      74: ireturn
      75: aload_3
      76: invokevirtual #15                 // Method org/apache/hadoop/hbase/HRegionLocation.getRegion:()Lorg/apache/hadoop/hbase/client/RegionInfo;
      79: invokeinterface #19,  1           // InterfaceMethod org/apache/hadoop/hbase/client/RegionInfo.isOffline:()Z
      84: ifne          99
      87: aload_3
      88: invokevirtual #15                 // Method org/apache/hadoop/hbase/HRegionLocation.getRegion:()Lorg/apache/hadoop/hbase/client/RegionInfo;
      91: invokeinterface #20,  1           // InterfaceMethod org/apache/hadoop/hbase/client/RegionInfo.isSplit:()Z
      96: ifeq          101
      99: iconst_1
     100: ireturn
     101: aload_2
     102: invokevirtual #21                 // Method org/apache/hadoop/hbase/RegionLocations.getRegionLocations:()[Lorg/apache/hadoop/hbase/HRegionLocation;
     105: astore        4
     107: aload         4
     109: astore        5
     111: aload         5
     113: arraylength
     114: istore        6
     116: iconst_0
     117: istore        7
     119: iload         7
     121: iload         6
     123: if_icmpge     175
     126: aload         5
     128: iload         7
     130: aaload
     131: astore        8
     133: aload         8
     135: ifnonnull     141
     138: goto          169
     141: aload         8
     143: invokevirtual #22                 // Method org/apache/hadoop/hbase/HRegionLocation.getServerName:()Lorg/apache/hadoop/hbase/ServerName;
     146: astore        9
     148: aload         9
     150: ifnull        169
     153: aload         9
     155: invokevirtual #23                 // Method org/apache/hadoop/hbase/ServerName.getAddress:()Lorg/apache/hadoop/hbase/net/Address;
     158: ifnull        169
     161: aload_0
     162: getfield      #3                  // Field val$actualRegCount:Ljava/util/concurrent/atomic/AtomicInteger;
     165: invokevirtual #24                 // Method java/util/concurrent/atomic/AtomicInteger.incrementAndGet:()I
     168: pop
     169: iinc          7, 1
     172: goto          119
     175: iconst_1
     176: ireturn
}
