Compiled from "HBaseAdmin.java"
class org.apache.hadoop.hbase.client.HBaseAdmin$69 extends org.apache.hadoop.hbase.client.SyncCoprocessorRpcChannel {
  final org.apache.hadoop.hbase.client.HBaseAdmin this$0;

  org.apache.hadoop.hbase.client.HBaseAdmin$69(org.apache.hadoop.hbase.client.HBaseAdmin);
    Code:
       0: aload_0
       1: aload_1
       2: putfield      #1                  // Field this$0:Lorg/apache/hadoop/hbase/client/HBaseAdmin;
       5: aload_0
       6: invokespecial #2                  // Method org/apache/hadoop/hbase/client/SyncCoprocessorRpcChannel."<init>":()V
       9: return

  protected com.google.protobuf.Message callExecService(com.google.protobuf.RpcController, com.google.protobuf.Descriptors$MethodDescriptor, com.google.protobuf.Message, com.google.protobuf.Message) throws java.io.IOException;
    Code:
       0: invokestatic  #3                  // Method org/apache/hadoop/hbase/client/HBaseAdmin.access$200:()Lorg/slf4j/Logger;
       3: invokeinterface #4,  1            // InterfaceMethod org/slf4j/Logger.isTraceEnabled:()Z
       8: ifeq          55
      11: invokestatic  #3                  // Method org/apache/hadoop/hbase/client/HBaseAdmin.access$200:()Lorg/slf4j/Logger;
      14: new           #5                  // class java/lang/StringBuilder
      17: dup
      18: invokespecial #6                  // Method java/lang/StringBuilder."<init>":()V
      21: ldc           #7                  // String Call:
      23: invokevirtual #8                  // Method java/lang/StringBuilder.append:(Ljava/lang/String;)Ljava/lang/StringBuilder;
      26: aload_2
      27: invokevirtual #9                  // Method com/google/protobuf/Descriptors$MethodDescriptor.getName:()Ljava/lang/String;
      30: invokevirtual #8                  // Method java/lang/StringBuilder.append:(Ljava/lang/String;)Ljava/lang/StringBuilder;
      33: ldc           #10                 // String ,
      35: invokevirtual #8                  // Method java/lang/StringBuilder.append:(Ljava/lang/String;)Ljava/lang/StringBuilder;
      38: aload_3
      39: invokeinterface #11,  1           // InterfaceMethod com/google/protobuf/Message.toString:()Ljava/lang/String;
      44: invokevirtual #8                  // Method java/lang/StringBuilder.append:(Ljava/lang/String;)Ljava/lang/StringBuilder;
      47: invokevirtual #12                 // Method java/lang/StringBuilder.toString:()Ljava/lang/String;
      50: invokeinterface #13,  2           // InterfaceMethod org/slf4j/Logger.trace:(Ljava/lang/String;)V
      55: new           #14                 // class org/apache/hadoop/hbase/client/HBaseAdmin$69$1
      58: dup
      59: aload_0
      60: aload_0
      61: getfield      #1                  // Field this$0:Lorg/apache/hadoop/hbase/client/HBaseAdmin;
      64: invokestatic  #15                 // Method org/apache/hadoop/hbase/client/HBaseAdmin.access$100:(Lorg/apache/hadoop/hbase/client/HBaseAdmin;)Lorg/apache/hadoop/hbase/client/ClusterConnection;
      67: aload_0
      68: getfield      #1                  // Field this$0:Lorg/apache/hadoop/hbase/client/HBaseAdmin;
      71: invokestatic  #15                 // Method org/apache/hadoop/hbase/client/HBaseAdmin.access$100:(Lorg/apache/hadoop/hbase/client/HBaseAdmin;)Lorg/apache/hadoop/hbase/client/ClusterConnection;
      74: invokeinterface #16,  1           // InterfaceMethod org/apache/hadoop/hbase/client/ClusterConnection.getRpcControllerFactory:()Lorg/apache/hadoop/hbase/ipc/RpcControllerFactory;
      79: aload_2
      80: aload_3
      81: invokespecial #17                 // Method org/apache/hadoop/hbase/client/HBaseAdmin$69$1."<init>":(Lorg/apache/hadoop/hbase/client/HBaseAdmin$69;Lorg/apache/hadoop/hbase/client/Connection;Lorg/apache/hadoop/hbase/ipc/RpcControllerFactory;Lcom/google/protobuf/Descriptors$MethodDescriptor;Lcom/google/protobuf/Message;)V
      84: astore        5
      86: aconst_null
      87: astore        6
      89: aload         5
      91: iconst_0
      92: invokevirtual #18                 // Method org/apache/hadoop/hbase/client/MasterCallable.prepare:(Z)V
      95: aload_0
      96: getfield      #1                  // Field this$0:Lorg/apache/hadoop/hbase/client/HBaseAdmin;
      99: invokestatic  #15                 // Method org/apache/hadoop/hbase/client/HBaseAdmin.access$100:(Lorg/apache/hadoop/hbase/client/HBaseAdmin;)Lorg/apache/hadoop/hbase/client/ClusterConnection;
     102: invokeinterface #19,  1           // InterfaceMethod org/apache/hadoop/hbase/client/ClusterConnection.getConnectionConfiguration:()Lorg/apache/hadoop/hbase/client/ConnectionConfiguration;
     107: invokevirtual #20                 // Method org/apache/hadoop/hbase/client/ConnectionConfiguration.getOperationTimeout:()I
     110: istore        7
     112: aload         5
     114: iload         7
     116: invokevirtual #21                 // Method org/apache/hadoop/hbase/client/MasterCallable.call:(I)Ljava/lang/Object;
     119: checkcast     #22                 // class org/apache/hadoop/hbase/shaded/protobuf/generated/ClientProtos$CoprocessorServiceResponse
     122: astore        8
     124: aload         8
     126: aload         4
     128: invokestatic  #23                 // Method org/apache/hadoop/hbase/ipc/CoprocessorRpcUtils.getResponse:(Lorg/apache/hadoop/hbase/shaded/protobuf/generated/ClientProtos$CoprocessorServiceResponse;Lcom/google/protobuf/Message;)Lcom/google/protobuf/Message;
     131: astore        9
     133: aload         5
     135: ifnull        168
     138: aload         6
     140: ifnull        163
     143: aload         5
     145: invokevirtual #24                 // Method org/apache/hadoop/hbase/client/MasterCallable.close:()V
     148: goto          168
     151: astore        10
     153: aload         6
     155: aload         10
     157: invokevirtual #26                 // Method java/lang/Throwable.addSuppressed:(Ljava/lang/Throwable;)V
     160: goto          168
     163: aload         5
     165: invokevirtual #24                 // Method org/apache/hadoop/hbase/client/MasterCallable.close:()V
     168: aload         9
     170: areturn
     171: astore        7
     173: aload         7
     175: astore        6
     177: aload         7
     179: athrow
     180: astore        11
     182: aload         5
     184: ifnull        217
     187: aload         6
     189: ifnull        212
     192: aload         5
     194: invokevirtual #24                 // Method org/apache/hadoop/hbase/client/MasterCallable.close:()V
     197: goto          217
     200: astore        12
     202: aload         6
     204: aload         12
     206: invokevirtual #26                 // Method java/lang/Throwable.addSuppressed:(Ljava/lang/Throwable;)V
     209: goto          217
     212: aload         5
     214: invokevirtual #24                 // Method org/apache/hadoop/hbase/client/MasterCallable.close:()V
     217: aload         11
     219: athrow
    Exception table:
       from    to  target type
         143   148   151   Class java/lang/Throwable
          89   133   171   Class java/lang/Throwable
          89   133   180   any
         192   197   200   Class java/lang/Throwable
         171   182   180   any
}
