Compiled from "HBaseTestingUtility.java"
class org.apache.hadoop.hbase.HBaseTestingUtility$7 implements org.apache.hadoop.hbase.Waiter$ExplainingPredicate<java.io.IOException> {
  final org.apache.hadoop.hbase.TableName val$tableName;

  final org.apache.hadoop.hbase.HBaseTestingUtility this$0;

  org.apache.hadoop.hbase.HBaseTestingUtility$7(org.apache.hadoop.hbase.HBaseTestingUtility, org.apache.hadoop.hbase.TableName);
    Code:
       0: aload_0
       1: aload_1
       2: putfield      #1                  // Field this$0:Lorg/apache/hadoop/hbase/HBaseTestingUtility;
       5: aload_0
       6: aload_2
       7: putfield      #2                  // Field val$tableName:Lorg/apache/hadoop/hbase/TableName;
      10: aload_0
      11: invokespecial #3                  // Method java/lang/Object."<init>":()V
      14: return

  public java.lang.String explainFailure() throws java.io.IOException;
    Code:
       0: aload_0
       1: getfield      #1                  // Field this$0:Lorg/apache/hadoop/hbase/HBaseTestingUtility;
       4: aload_0
       5: getfield      #2                  // Field val$tableName:Lorg/apache/hadoop/hbase/TableName;
       8: getstatic     #4                  // Field org/apache/hadoop/hbase/client/TableState$State.DISABLED:Lorg/apache/hadoop/hbase/client/TableState$State;
      11: invokevirtual #5                  // Method org/apache/hadoop/hbase/HBaseTestingUtility.explainTableState:(Lorg/apache/hadoop/hbase/TableName;Lorg/apache/hadoop/hbase/client/TableState$State;)Ljava/lang/String;
      14: areturn

  public boolean evaluate() throws java.io.IOException;
    Code:
       0: aload_0
       1: getfield      #1                  // Field this$0:Lorg/apache/hadoop/hbase/HBaseTestingUtility;
       4: invokevirtual #6                  // Method org/apache/hadoop/hbase/HBaseTestingUtility.getAdmin:()Lorg/apache/hadoop/hbase/client/Admin;
       7: aload_0
       8: getfield      #2                  // Field val$tableName:Lorg/apache/hadoop/hbase/TableName;
      11: invokeinterface #7,  2            // InterfaceMethod org/apache/hadoop/hbase/client/Admin.isTableDisabled:(Lorg/apache/hadoop/hbase/TableName;)Z
      16: ireturn
}
