Compiled from "HBaseZeroCopyByteString.java"
public final class com.google.protobuf.HBaseZeroCopyByteString extends com.google.protobuf.LiteralByteString {
  public static com.google.protobuf.ByteString wrap(byte[]);
    Code:
       0: new           #5                  // class com/google/protobuf/LiteralByteString
       3: dup
       4: aload_0
       5: invokespecial #1                  // Method com/google/protobuf/LiteralByteString."<init>":([B)V
       8: areturn

  public static com.google.protobuf.ByteString wrap(byte[], int, int);
    Code:
       0: new           #6                  // class com/google/protobuf/BoundedByteString
       3: dup
       4: aload_0
       5: iload_1
       6: iload_2
       7: invokespecial #7                  // Method com/google/protobuf/BoundedByteString."<init>":([BII)V
      10: areturn

  public static byte[] zeroCopyGetBytes(com.google.protobuf.ByteString);
    Code:
       0: aload_0
       1: instanceof    #5                  // class com/google/protobuf/LiteralByteString
       4: ifeq          15
       7: aload_0
       8: checkcast     #5                  // class com/google/protobuf/LiteralByteString
      11: getfield      #8                  // Field com/google/protobuf/LiteralByteString.bytes:[B
      14: areturn
      15: new           #2                  // class java/lang/UnsupportedOperationException
      18: dup
      19: new           #9                  // class java/lang/StringBuilder
      22: dup
      23: invokespecial #10                 // Method java/lang/StringBuilder."<init>":()V
      26: ldc           #11                 // String Need a LiteralByteString, got a
      28: invokevirtual #12                 // Method java/lang/StringBuilder.append:(Ljava/lang/String;)Ljava/lang/StringBuilder;
      31: aload_0
      32: invokevirtual #13                 // Method java/lang/Object.getClass:()Ljava/lang/Class;
      35: invokevirtual #14                 // Method java/lang/Class.getName:()Ljava/lang/String;
      38: invokevirtual #12                 // Method java/lang/StringBuilder.append:(Ljava/lang/String;)Ljava/lang/StringBuilder;
      41: invokevirtual #15                 // Method java/lang/StringBuilder.toString:()Ljava/lang/String;
      44: invokespecial #4                  // Method java/lang/UnsupportedOperationException."<init>":(Ljava/lang/String;)V
      47: athrow

  public com.google.protobuf.ByteString$ByteIterator iterator();
    Code:
       0: aload_0
       1: invokespecial #16                 // Method com/google/protobuf/LiteralByteString.iterator:()Lcom/google/protobuf/ByteString$ByteIterator;
       4: areturn

  public com.google.protobuf.CodedInputStream newCodedInput();
    Code:
       0: aload_0
       1: invokespecial #17                 // Method com/google/protobuf/LiteralByteString.newCodedInput:()Lcom/google/protobuf/CodedInputStream;
       4: areturn

  public java.io.InputStream newInput();
    Code:
       0: aload_0
       1: invokespecial #18                 // Method com/google/protobuf/LiteralByteString.newInput:()Ljava/io/InputStream;
       4: areturn

  public int hashCode();
    Code:
       0: aload_0
       1: invokespecial #19                 // Method com/google/protobuf/LiteralByteString.hashCode:()I
       4: ireturn

  public boolean equals(java.lang.Object);
    Code:
       0: aload_0
       1: aload_1
       2: invokespecial #20                 // Method com/google/protobuf/LiteralByteString.equals:(Ljava/lang/Object;)Z
       5: ireturn

  public boolean isValidUtf8();
    Code:
       0: aload_0
       1: invokespecial #21                 // Method com/google/protobuf/LiteralByteString.isValidUtf8:()Z
       4: ireturn

  public java.lang.String toString(java.lang.String) throws java.io.UnsupportedEncodingException;
    Code:
       0: aload_0
       1: aload_1
       2: invokespecial #22                 // Method com/google/protobuf/LiteralByteString.toString:(Ljava/lang/String;)Ljava/lang/String;
       5: areturn

  public void writeTo(java.io.OutputStream) throws java.io.IOException;
    Code:
       0: aload_0
       1: aload_1
       2: invokespecial #23                 // Method com/google/protobuf/LiteralByteString.writeTo:(Ljava/io/OutputStream;)V
       5: return

  public java.util.List asReadOnlyByteBufferList();
    Code:
       0: aload_0
       1: invokespecial #24                 // Method com/google/protobuf/LiteralByteString.asReadOnlyByteBufferList:()Ljava/util/List;
       4: areturn

  public java.nio.ByteBuffer asReadOnlyByteBuffer();
    Code:
       0: aload_0
       1: invokespecial #25                 // Method com/google/protobuf/LiteralByteString.asReadOnlyByteBuffer:()Ljava/nio/ByteBuffer;
       4: areturn

  public void copyTo(java.nio.ByteBuffer);
    Code:
       0: aload_0
       1: aload_1
       2: invokespecial #26                 // Method com/google/protobuf/LiteralByteString.copyTo:(Ljava/nio/ByteBuffer;)V
       5: return

  public com.google.protobuf.ByteString substring(int, int);
    Code:
       0: aload_0
       1: iload_1
       2: iload_2
       3: invokespecial #27                 // Method com/google/protobuf/LiteralByteString.substring:(II)Lcom/google/protobuf/ByteString;
       6: areturn

  public int size();
    Code:
       0: aload_0
       1: invokespecial #28                 // Method com/google/protobuf/LiteralByteString.size:()I
       4: ireturn

  public byte byteAt(int);
    Code:
       0: aload_0
       1: iload_1
       2: invokespecial #29                 // Method com/google/protobuf/LiteralByteString.byteAt:(I)B
       5: ireturn
}
