Compiled from "HBaseProtos.java"
public final class org.apache.hadoop.hbase.protobuf.generated.HBaseProtos$SnapshotDescription$Builder extends com.google.protobuf.GeneratedMessage$Builder<org.apache.hadoop.hbase.protobuf.generated.HBaseProtos$SnapshotDescription$Builder> implements org.apache.hadoop.hbase.protobuf.generated.HBaseProtos$SnapshotDescriptionOrBuilder {
  public static final com.google.protobuf.Descriptors$Descriptor getDescriptor();
    Code:
       0: invokestatic  #3                  // Method org/apache/hadoop/hbase/protobuf/generated/HBaseProtos.access$16100:()Lcom/google/protobuf/Descriptors$Descriptor;
       3: areturn

  protected com.google.protobuf.GeneratedMessage$FieldAccessorTable internalGetFieldAccessorTable();
    Code:
       0: invokestatic  #4                  // Method org/apache/hadoop/hbase/protobuf/generated/HBaseProtos.access$16200:()Lcom/google/protobuf/GeneratedMessage$FieldAccessorTable;
       3: ldc           #5                  // class org/apache/hadoop/hbase/protobuf/generated/HBaseProtos$SnapshotDescription
       5: ldc           #6                  // class org/apache/hadoop/hbase/protobuf/generated/HBaseProtos$SnapshotDescription$Builder
       7: invokevirtual #7                  // Method com/google/protobuf/GeneratedMessage$FieldAccessorTable.ensureFieldAccessorsInitialized:(Ljava/lang/Class;Ljava/lang/Class;)Lcom/google/protobuf/GeneratedMessage$FieldAccessorTable;
      10: areturn

  public org.apache.hadoop.hbase.protobuf.generated.HBaseProtos$SnapshotDescription$Builder clear();
    Code:
       0: aload_0
       1: invokespecial #19                 // Method com/google/protobuf/GeneratedMessage$Builder.clear:()Lcom/google/protobuf/GeneratedMessage$Builder;
       4: pop
       5: aload_0
       6: ldc           #9                  // String
       8: putfield      #10                 // Field name_:Ljava/lang/Object;
      11: aload_0
      12: aload_0
      13: getfield      #20                 // Field bitField0_:I
      16: bipush        -2
      18: iand
      19: putfield      #20                 // Field bitField0_:I
      22: aload_0
      23: ldc           #9                  // String
      25: putfield      #11                 // Field table_:Ljava/lang/Object;
      28: aload_0
      29: aload_0
      30: getfield      #20                 // Field bitField0_:I
      33: bipush        -3
      35: iand
      36: putfield      #20                 // Field bitField0_:I
      39: aload_0
      40: lconst_0
      41: putfield      #21                 // Field creationTime_:J
      44: aload_0
      45: aload_0
      46: getfield      #20                 // Field bitField0_:I
      49: bipush        -5
      51: iand
      52: putfield      #20                 // Field bitField0_:I
      55: aload_0
      56: getstatic     #12                 // Field org/apache/hadoop/hbase/protobuf/generated/HBaseProtos$SnapshotDescription$Type.FLUSH:Lorg/apache/hadoop/hbase/protobuf/generated/HBaseProtos$SnapshotDescription$Type;
      59: putfield      #13                 // Field type_:Lorg/apache/hadoop/hbase/protobuf/generated/HBaseProtos$SnapshotDescription$Type;
      62: aload_0
      63: aload_0
      64: getfield      #20                 // Field bitField0_:I
      67: bipush        -9
      69: iand
      70: putfield      #20                 // Field bitField0_:I
      73: aload_0
      74: iconst_0
      75: putfield      #22                 // Field version_:I
      78: aload_0
      79: aload_0
      80: getfield      #20                 // Field bitField0_:I
      83: bipush        -17
      85: iand
      86: putfield      #20                 // Field bitField0_:I
      89: aload_0
      90: ldc           #9                  // String
      92: putfield      #14                 // Field owner_:Ljava/lang/Object;
      95: aload_0
      96: aload_0
      97: getfield      #20                 // Field bitField0_:I
     100: bipush        -33
     102: iand
     103: putfield      #20                 // Field bitField0_:I
     106: aload_0
     107: areturn

  public org.apache.hadoop.hbase.protobuf.generated.HBaseProtos$SnapshotDescription$Builder clone();
    Code:
       0: invokestatic  #2                  // Method create:()Lorg/apache/hadoop/hbase/protobuf/generated/HBaseProtos$SnapshotDescription$Builder;
       3: aload_0
       4: invokevirtual #23                 // Method buildPartial:()Lorg/apache/hadoop/hbase/protobuf/generated/HBaseProtos$SnapshotDescription;
       7: invokevirtual #24                 // Method mergeFrom:(Lorg/apache/hadoop/hbase/protobuf/generated/HBaseProtos$SnapshotDescription;)Lorg/apache/hadoop/hbase/protobuf/generated/HBaseProtos$SnapshotDescription$Builder;
      10: areturn

  public com.google.protobuf.Descriptors$Descriptor getDescriptorForType();
    Code:
       0: invokestatic  #3                  // Method org/apache/hadoop/hbase/protobuf/generated/HBaseProtos.access$16100:()Lcom/google/protobuf/Descriptors$Descriptor;
       3: areturn

  public org.apache.hadoop.hbase.protobuf.generated.HBaseProtos$SnapshotDescription getDefaultInstanceForType();
    Code:
       0: invokestatic  #25                 // Method org/apache/hadoop/hbase/protobuf/generated/HBaseProtos$SnapshotDescription.getDefaultInstance:()Lorg/apache/hadoop/hbase/protobuf/generated/HBaseProtos$SnapshotDescription;
       3: areturn

  public org.apache.hadoop.hbase.protobuf.generated.HBaseProtos$SnapshotDescription build();
    Code:
       0: aload_0
       1: invokevirtual #23                 // Method buildPartial:()Lorg/apache/hadoop/hbase/protobuf/generated/HBaseProtos$SnapshotDescription;
       4: astore_1
       5: aload_1
       6: invokevirtual #26                 // Method org/apache/hadoop/hbase/protobuf/generated/HBaseProtos$SnapshotDescription.isInitialized:()Z
       9: ifne          17
      12: aload_1
      13: invokestatic  #27                 // Method newUninitializedMessageException:(Lcom/google/protobuf/Message;)Lcom/google/protobuf/UninitializedMessageException;
      16: athrow
      17: aload_1
      18: areturn

  public org.apache.hadoop.hbase.protobuf.generated.HBaseProtos$SnapshotDescription buildPartial();
    Code:
       0: new           #5                  // class org/apache/hadoop/hbase/protobuf/generated/HBaseProtos$SnapshotDescription
       3: dup
       4: aload_0
       5: aconst_null
       6: invokespecial #28                 // Method org/apache/hadoop/hbase/protobuf/generated/HBaseProtos$SnapshotDescription."<init>":(Lcom/google/protobuf/GeneratedMessage$Builder;Lorg/apache/hadoop/hbase/protobuf/generated/HBaseProtos$1;)V
       9: astore_1
      10: aload_0
      11: getfield      #20                 // Field bitField0_:I
      14: istore_2
      15: iconst_0
      16: istore_3
      17: iload_2
      18: iconst_1
      19: iand
      20: iconst_1
      21: if_icmpne     28
      24: iload_3
      25: iconst_1
      26: ior
      27: istore_3
      28: aload_1
      29: aload_0
      30: getfield      #10                 // Field name_:Ljava/lang/Object;
      33: invokestatic  #29                 // Method org/apache/hadoop/hbase/protobuf/generated/HBaseProtos$SnapshotDescription.access$16802:(Lorg/apache/hadoop/hbase/protobuf/generated/HBaseProtos$SnapshotDescription;Ljava/lang/Object;)Ljava/lang/Object;
      36: pop
      37: iload_2
      38: iconst_2
      39: iand
      40: iconst_2
      41: if_icmpne     48
      44: iload_3
      45: iconst_2
      46: ior
      47: istore_3
      48: aload_1
      49: aload_0
      50: getfield      #11                 // Field table_:Ljava/lang/Object;
      53: invokestatic  #30                 // Method org/apache/hadoop/hbase/protobuf/generated/HBaseProtos$SnapshotDescription.access$16902:(Lorg/apache/hadoop/hbase/protobuf/generated/HBaseProtos$SnapshotDescription;Ljava/lang/Object;)Ljava/lang/Object;
      56: pop
      57: iload_2
      58: iconst_4
      59: iand
      60: iconst_4
      61: if_icmpne     68
      64: iload_3
      65: iconst_4
      66: ior
      67: istore_3
      68: aload_1
      69: aload_0
      70: getfield      #21                 // Field creationTime_:J
      73: invokestatic  #31                 // Method org/apache/hadoop/hbase/protobuf/generated/HBaseProtos$SnapshotDescription.access$17002:(Lorg/apache/hadoop/hbase/protobuf/generated/HBaseProtos$SnapshotDescription;J)J
      76: pop2
      77: iload_2
      78: bipush        8
      80: iand
      81: bipush        8
      83: if_icmpne     91
      86: iload_3
      87: bipush        8
      89: ior
      90: istore_3
      91: aload_1
      92: aload_0
      93: getfield      #13                 // Field type_:Lorg/apache/hadoop/hbase/protobuf/generated/HBaseProtos$SnapshotDescription$Type;
      96: invokestatic  #32                 // Method org/apache/hadoop/hbase/protobuf/generated/HBaseProtos$SnapshotDescription.access$17102:(Lorg/apache/hadoop/hbase/protobuf/generated/HBaseProtos$SnapshotDescription;Lorg/apache/hadoop/hbase/protobuf/generated/HBaseProtos$SnapshotDescription$Type;)Lorg/apache/hadoop/hbase/protobuf/generated/HBaseProtos$SnapshotDescription$Type;
      99: pop
     100: iload_2
     101: bipush        16
     103: iand
     104: bipush        16
     106: if_icmpne     114
     109: iload_3
     110: bipush        16
     112: ior
     113: istore_3
     114: aload_1
     115: aload_0
     116: getfield      #22                 // Field version_:I
     119: invokestatic  #33                 // Method org/apache/hadoop/hbase/protobuf/generated/HBaseProtos$SnapshotDescription.access$17202:(Lorg/apache/hadoop/hbase/protobuf/generated/HBaseProtos$SnapshotDescription;I)I
     122: pop
     123: iload_2
     124: bipush        32
     126: iand
     127: bipush        32
     129: if_icmpne     137
     132: iload_3
     133: bipush        32
     135: ior
     136: istore_3
     137: aload_1
     138: aload_0
     139: getfield      #14                 // Field owner_:Ljava/lang/Object;
     142: invokestatic  #34                 // Method org/apache/hadoop/hbase/protobuf/generated/HBaseProtos$SnapshotDescription.access$17302:(Lorg/apache/hadoop/hbase/protobuf/generated/HBaseProtos$SnapshotDescription;Ljava/lang/Object;)Ljava/lang/Object;
     145: pop
     146: aload_1
     147: iload_3
     148: invokestatic  #35                 // Method org/apache/hadoop/hbase/protobuf/generated/HBaseProtos$SnapshotDescription.access$17402:(Lorg/apache/hadoop/hbase/protobuf/generated/HBaseProtos$SnapshotDescription;I)I
     151: pop
     152: aload_0
     153: invokevirtual #36                 // Method onBuilt:()V
     156: aload_1
     157: areturn

  public org.apache.hadoop.hbase.protobuf.generated.HBaseProtos$SnapshotDescription$Builder mergeFrom(com.google.protobuf.Message);
    Code:
       0: aload_1
       1: instanceof    #5                  // class org/apache/hadoop/hbase/protobuf/generated/HBaseProtos$SnapshotDescription
       4: ifeq          16
       7: aload_0
       8: aload_1
       9: checkcast     #5                  // class org/apache/hadoop/hbase/protobuf/generated/HBaseProtos$SnapshotDescription
      12: invokevirtual #24                 // Method mergeFrom:(Lorg/apache/hadoop/hbase/protobuf/generated/HBaseProtos$SnapshotDescription;)Lorg/apache/hadoop/hbase/protobuf/generated/HBaseProtos$SnapshotDescription$Builder;
      15: areturn
      16: aload_0
      17: aload_1
      18: invokespecial #37                 // Method com/google/protobuf/GeneratedMessage$Builder.mergeFrom:(Lcom/google/protobuf/Message;)Lcom/google/protobuf/AbstractMessage$Builder;
      21: pop
      22: aload_0
      23: areturn

  public org.apache.hadoop.hbase.protobuf.generated.HBaseProtos$SnapshotDescription$Builder mergeFrom(org.apache.hadoop.hbase.protobuf.generated.HBaseProtos$SnapshotDescription);
    Code:
       0: aload_1
       1: invokestatic  #25                 // Method org/apache/hadoop/hbase/protobuf/generated/HBaseProtos$SnapshotDescription.getDefaultInstance:()Lorg/apache/hadoop/hbase/protobuf/generated/HBaseProtos$SnapshotDescription;
       4: if_acmpne     9
       7: aload_0
       8: areturn
       9: aload_1
      10: invokevirtual #38                 // Method org/apache/hadoop/hbase/protobuf/generated/HBaseProtos$SnapshotDescription.hasName:()Z
      13: ifeq          38
      16: aload_0
      17: dup
      18: getfield      #20                 // Field bitField0_:I
      21: iconst_1
      22: ior
      23: putfield      #20                 // Field bitField0_:I
      26: aload_0
      27: aload_1
      28: invokestatic  #39                 // Method org/apache/hadoop/hbase/protobuf/generated/HBaseProtos$SnapshotDescription.access$16800:(Lorg/apache/hadoop/hbase/protobuf/generated/HBaseProtos$SnapshotDescription;)Ljava/lang/Object;
      31: putfield      #10                 // Field name_:Ljava/lang/Object;
      34: aload_0
      35: invokevirtual #40                 // Method onChanged:()V
      38: aload_1
      39: invokevirtual #41                 // Method org/apache/hadoop/hbase/protobuf/generated/HBaseProtos$SnapshotDescription.hasTable:()Z
      42: ifeq          67
      45: aload_0
      46: dup
      47: getfield      #20                 // Field bitField0_:I
      50: iconst_2
      51: ior
      52: putfield      #20                 // Field bitField0_:I
      55: aload_0
      56: aload_1
      57: invokestatic  #42                 // Method org/apache/hadoop/hbase/protobuf/generated/HBaseProtos$SnapshotDescription.access$16900:(Lorg/apache/hadoop/hbase/protobuf/generated/HBaseProtos$SnapshotDescription;)Ljava/lang/Object;
      60: putfield      #11                 // Field table_:Ljava/lang/Object;
      63: aload_0
      64: invokevirtual #40                 // Method onChanged:()V
      67: aload_1
      68: invokevirtual #43                 // Method org/apache/hadoop/hbase/protobuf/generated/HBaseProtos$SnapshotDescription.hasCreationTime:()Z
      71: ifeq          83
      74: aload_0
      75: aload_1
      76: invokevirtual #44                 // Method org/apache/hadoop/hbase/protobuf/generated/HBaseProtos$SnapshotDescription.getCreationTime:()J
      79: invokevirtual #45                 // Method setCreationTime:(J)Lorg/apache/hadoop/hbase/protobuf/generated/HBaseProtos$SnapshotDescription$Builder;
      82: pop
      83: aload_1
      84: invokevirtual #46                 // Method org/apache/hadoop/hbase/protobuf/generated/HBaseProtos$SnapshotDescription.hasType:()Z
      87: ifeq          99
      90: aload_0
      91: aload_1
      92: invokevirtual #47                 // Method org/apache/hadoop/hbase/protobuf/generated/HBaseProtos$SnapshotDescription.getType:()Lorg/apache/hadoop/hbase/protobuf/generated/HBaseProtos$SnapshotDescription$Type;
      95: invokevirtual #48                 // Method setType:(Lorg/apache/hadoop/hbase/protobuf/generated/HBaseProtos$SnapshotDescription$Type;)Lorg/apache/hadoop/hbase/protobuf/generated/HBaseProtos$SnapshotDescription$Builder;
      98: pop
      99: aload_1
     100: invokevirtual #49                 // Method org/apache/hadoop/hbase/protobuf/generated/HBaseProtos$SnapshotDescription.hasVersion:()Z
     103: ifeq          115
     106: aload_0
     107: aload_1
     108: invokevirtual #50                 // Method org/apache/hadoop/hbase/protobuf/generated/HBaseProtos$SnapshotDescription.getVersion:()I
     111: invokevirtual #51                 // Method setVersion:(I)Lorg/apache/hadoop/hbase/protobuf/generated/HBaseProtos$SnapshotDescription$Builder;
     114: pop
     115: aload_1
     116: invokevirtual #52                 // Method org/apache/hadoop/hbase/protobuf/generated/HBaseProtos$SnapshotDescription.hasOwner:()Z
     119: ifeq          145
     122: aload_0
     123: dup
     124: getfield      #20                 // Field bitField0_:I
     127: bipush        32
     129: ior
     130: putfield      #20                 // Field bitField0_:I
     133: aload_0
     134: aload_1
     135: invokestatic  #53                 // Method org/apache/hadoop/hbase/protobuf/generated/HBaseProtos$SnapshotDescription.access$17300:(Lorg/apache/hadoop/hbase/protobuf/generated/HBaseProtos$SnapshotDescription;)Ljava/lang/Object;
     138: putfield      #14                 // Field owner_:Ljava/lang/Object;
     141: aload_0
     142: invokevirtual #40                 // Method onChanged:()V
     145: aload_0
     146: aload_1
     147: invokevirtual #54                 // Method org/apache/hadoop/hbase/protobuf/generated/HBaseProtos$SnapshotDescription.getUnknownFields:()Lcom/google/protobuf/UnknownFieldSet;
     150: invokevirtual #55                 // Method mergeUnknownFields:(Lcom/google/protobuf/UnknownFieldSet;)Lcom/google/protobuf/GeneratedMessage$Builder;
     153: pop
     154: aload_0
     155: areturn

  public final boolean isInitialized();
    Code:
       0: aload_0
       1: invokevirtual #56                 // Method hasName:()Z
       4: ifne          9
       7: iconst_0
       8: ireturn
       9: iconst_1
      10: ireturn

  public org.apache.hadoop.hbase.protobuf.generated.HBaseProtos$SnapshotDescription$Builder mergeFrom(com.google.protobuf.CodedInputStream, com.google.protobuf.ExtensionRegistryLite) throws java.io.IOException;
    Code:
       0: aconst_null
       1: astore_3
       2: getstatic     #57                 // Field org/apache/hadoop/hbase/protobuf/generated/HBaseProtos$SnapshotDescription.PARSER:Lcom/google/protobuf/Parser;
       5: aload_1
       6: aload_2
       7: invokeinterface #58,  3           // InterfaceMethod com/google/protobuf/Parser.parsePartialFrom:(Lcom/google/protobuf/CodedInputStream;Lcom/google/protobuf/ExtensionRegistryLite;)Ljava/lang/Object;
      12: checkcast     #5                  // class org/apache/hadoop/hbase/protobuf/generated/HBaseProtos$SnapshotDescription
      15: astore_3
      16: aload_3
      17: ifnull        58
      20: aload_0
      21: aload_3
      22: invokevirtual #24                 // Method mergeFrom:(Lorg/apache/hadoop/hbase/protobuf/generated/HBaseProtos$SnapshotDescription;)Lorg/apache/hadoop/hbase/protobuf/generated/HBaseProtos$SnapshotDescription$Builder;
      25: pop
      26: goto          58
      29: astore        4
      31: aload         4
      33: invokevirtual #60                 // Method com/google/protobuf/InvalidProtocolBufferException.getUnfinishedMessage:()Lcom/google/protobuf/MessageLite;
      36: checkcast     #5                  // class org/apache/hadoop/hbase/protobuf/generated/HBaseProtos$SnapshotDescription
      39: astore_3
      40: aload         4
      42: athrow
      43: astore        5
      45: aload_3
      46: ifnull        55
      49: aload_0
      50: aload_3
      51: invokevirtual #24                 // Method mergeFrom:(Lorg/apache/hadoop/hbase/protobuf/generated/HBaseProtos$SnapshotDescription;)Lorg/apache/hadoop/hbase/protobuf/generated/HBaseProtos$SnapshotDescription$Builder;
      54: pop
      55: aload         5
      57: athrow
      58: aload_0
      59: areturn
    Exception table:
       from    to  target type
           2    16    29   Class com/google/protobuf/InvalidProtocolBufferException
           2    16    43   any
          29    45    43   any

  public boolean hasName();
    Code:
       0: aload_0
       1: getfield      #20                 // Field bitField0_:I
       4: iconst_1
       5: iand
       6: iconst_1
       7: if_icmpne     14
      10: iconst_1
      11: goto          15
      14: iconst_0
      15: ireturn

  public java.lang.String getName();
    Code:
       0: aload_0
       1: getfield      #10                 // Field name_:Ljava/lang/Object;
       4: astore_1
       5: aload_1
       6: instanceof    #61                 // class java/lang/String
       9: ifne          27
      12: aload_1
      13: checkcast     #62                 // class com/google/protobuf/ByteString
      16: invokevirtual #63                 // Method com/google/protobuf/ByteString.toStringUtf8:()Ljava/lang/String;
      19: astore_2
      20: aload_0
      21: aload_2
      22: putfield      #10                 // Field name_:Ljava/lang/Object;
      25: aload_2
      26: areturn
      27: aload_1
      28: checkcast     #61                 // class java/lang/String
      31: areturn

  public com.google.protobuf.ByteString getNameBytes();
    Code:
       0: aload_0
       1: getfield      #10                 // Field name_:Ljava/lang/Object;
       4: astore_1
       5: aload_1
       6: instanceof    #61                 // class java/lang/String
       9: ifeq          27
      12: aload_1
      13: checkcast     #61                 // class java/lang/String
      16: invokestatic  #64                 // Method com/google/protobuf/ByteString.copyFromUtf8:(Ljava/lang/String;)Lcom/google/protobuf/ByteString;
      19: astore_2
      20: aload_0
      21: aload_2
      22: putfield      #10                 // Field name_:Ljava/lang/Object;
      25: aload_2
      26: areturn
      27: aload_1
      28: checkcast     #62                 // class com/google/protobuf/ByteString
      31: areturn

  public org.apache.hadoop.hbase.protobuf.generated.HBaseProtos$SnapshotDescription$Builder setName(java.lang.String);
    Code:
       0: aload_1
       1: ifnonnull     12
       4: new           #65                 // class java/lang/NullPointerException
       7: dup
       8: invokespecial #66                 // Method java/lang/NullPointerException."<init>":()V
      11: athrow
      12: aload_0
      13: dup
      14: getfield      #20                 // Field bitField0_:I
      17: iconst_1
      18: ior
      19: putfield      #20                 // Field bitField0_:I
      22: aload_0
      23: aload_1
      24: putfield      #10                 // Field name_:Ljava/lang/Object;
      27: aload_0
      28: invokevirtual #40                 // Method onChanged:()V
      31: aload_0
      32: areturn

  public org.apache.hadoop.hbase.protobuf.generated.HBaseProtos$SnapshotDescription$Builder clearName();
    Code:
       0: aload_0
       1: aload_0
       2: getfield      #20                 // Field bitField0_:I
       5: bipush        -2
       7: iand
       8: putfield      #20                 // Field bitField0_:I
      11: aload_0
      12: invokestatic  #25                 // Method org/apache/hadoop/hbase/protobuf/generated/HBaseProtos$SnapshotDescription.getDefaultInstance:()Lorg/apache/hadoop/hbase/protobuf/generated/HBaseProtos$SnapshotDescription;
      15: invokevirtual #67                 // Method org/apache/hadoop/hbase/protobuf/generated/HBaseProtos$SnapshotDescription.getName:()Ljava/lang/String;
      18: putfield      #10                 // Field name_:Ljava/lang/Object;
      21: aload_0
      22: invokevirtual #40                 // Method onChanged:()V
      25: aload_0
      26: areturn

  public org.apache.hadoop.hbase.protobuf.generated.HBaseProtos$SnapshotDescription$Builder setNameBytes(com.google.protobuf.ByteString);
    Code:
       0: aload_1
       1: ifnonnull     12
       4: new           #65                 // class java/lang/NullPointerException
       7: dup
       8: invokespecial #66                 // Method java/lang/NullPointerException."<init>":()V
      11: athrow
      12: aload_0
      13: dup
      14: getfield      #20                 // Field bitField0_:I
      17: iconst_1
      18: ior
      19: putfield      #20                 // Field bitField0_:I
      22: aload_0
      23: aload_1
      24: putfield      #10                 // Field name_:Ljava/lang/Object;
      27: aload_0
      28: invokevirtual #40                 // Method onChanged:()V
      31: aload_0
      32: areturn

  public boolean hasTable();
    Code:
       0: aload_0
       1: getfield      #20                 // Field bitField0_:I
       4: iconst_2
       5: iand
       6: iconst_2
       7: if_icmpne     14
      10: iconst_1
      11: goto          15
      14: iconst_0
      15: ireturn

  public java.lang.String getTable();
    Code:
       0: aload_0
       1: getfield      #11                 // Field table_:Ljava/lang/Object;
       4: astore_1
       5: aload_1
       6: instanceof    #61                 // class java/lang/String
       9: ifne          27
      12: aload_1
      13: checkcast     #62                 // class com/google/protobuf/ByteString
      16: invokevirtual #63                 // Method com/google/protobuf/ByteString.toStringUtf8:()Ljava/lang/String;
      19: astore_2
      20: aload_0
      21: aload_2
      22: putfield      #11                 // Field table_:Ljava/lang/Object;
      25: aload_2
      26: areturn
      27: aload_1
      28: checkcast     #61                 // class java/lang/String
      31: areturn

  public com.google.protobuf.ByteString getTableBytes();
    Code:
       0: aload_0
       1: getfield      #11                 // Field table_:Ljava/lang/Object;
       4: astore_1
       5: aload_1
       6: instanceof    #61                 // class java/lang/String
       9: ifeq          27
      12: aload_1
      13: checkcast     #61                 // class java/lang/String
      16: invokestatic  #64                 // Method com/google/protobuf/ByteString.copyFromUtf8:(Ljava/lang/String;)Lcom/google/protobuf/ByteString;
      19: astore_2
      20: aload_0
      21: aload_2
      22: putfield      #11                 // Field table_:Ljava/lang/Object;
      25: aload_2
      26: areturn
      27: aload_1
      28: checkcast     #62                 // class com/google/protobuf/ByteString
      31: areturn

  public org.apache.hadoop.hbase.protobuf.generated.HBaseProtos$SnapshotDescription$Builder setTable(java.lang.String);
    Code:
       0: aload_1
       1: ifnonnull     12
       4: new           #65                 // class java/lang/NullPointerException
       7: dup
       8: invokespecial #66                 // Method java/lang/NullPointerException."<init>":()V
      11: athrow
      12: aload_0
      13: dup
      14: getfield      #20                 // Field bitField0_:I
      17: iconst_2
      18: ior
      19: putfield      #20                 // Field bitField0_:I
      22: aload_0
      23: aload_1
      24: putfield      #11                 // Field table_:Ljava/lang/Object;
      27: aload_0
      28: invokevirtual #40                 // Method onChanged:()V
      31: aload_0
      32: areturn

  public org.apache.hadoop.hbase.protobuf.generated.HBaseProtos$SnapshotDescription$Builder clearTable();
    Code:
       0: aload_0
       1: aload_0
       2: getfield      #20                 // Field bitField0_:I
       5: bipush        -3
       7: iand
       8: putfield      #20                 // Field bitField0_:I
      11: aload_0
      12: invokestatic  #25                 // Method org/apache/hadoop/hbase/protobuf/generated/HBaseProtos$SnapshotDescription.getDefaultInstance:()Lorg/apache/hadoop/hbase/protobuf/generated/HBaseProtos$SnapshotDescription;
      15: invokevirtual #68                 // Method org/apache/hadoop/hbase/protobuf/generated/HBaseProtos$SnapshotDescription.getTable:()Ljava/lang/String;
      18: putfield      #11                 // Field table_:Ljava/lang/Object;
      21: aload_0
      22: invokevirtual #40                 // Method onChanged:()V
      25: aload_0
      26: areturn

  public org.apache.hadoop.hbase.protobuf.generated.HBaseProtos$SnapshotDescription$Builder setTableBytes(com.google.protobuf.ByteString);
    Code:
       0: aload_1
       1: ifnonnull     12
       4: new           #65                 // class java/lang/NullPointerException
       7: dup
       8: invokespecial #66                 // Method java/lang/NullPointerException."<init>":()V
      11: athrow
      12: aload_0
      13: dup
      14: getfield      #20                 // Field bitField0_:I
      17: iconst_2
      18: ior
      19: putfield      #20                 // Field bitField0_:I
      22: aload_0
      23: aload_1
      24: putfield      #11                 // Field table_:Ljava/lang/Object;
      27: aload_0
      28: invokevirtual #40                 // Method onChanged:()V
      31: aload_0
      32: areturn

  public boolean hasCreationTime();
    Code:
       0: aload_0
       1: getfield      #20                 // Field bitField0_:I
       4: iconst_4
       5: iand
       6: iconst_4
       7: if_icmpne     14
      10: iconst_1
      11: goto          15
      14: iconst_0
      15: ireturn

  public long getCreationTime();
    Code:
       0: aload_0
       1: getfield      #21                 // Field creationTime_:J
       4: lreturn

  public org.apache.hadoop.hbase.protobuf.generated.HBaseProtos$SnapshotDescription$Builder setCreationTime(long);
    Code:
       0: aload_0
       1: dup
       2: getfield      #20                 // Field bitField0_:I
       5: iconst_4
       6: ior
       7: putfield      #20                 // Field bitField0_:I
      10: aload_0
      11: lload_1
      12: putfield      #21                 // Field creationTime_:J
      15: aload_0
      16: invokevirtual #40                 // Method onChanged:()V
      19: aload_0
      20: areturn

  public org.apache.hadoop.hbase.protobuf.generated.HBaseProtos$SnapshotDescription$Builder clearCreationTime();
    Code:
       0: aload_0
       1: aload_0
       2: getfield      #20                 // Field bitField0_:I
       5: bipush        -5
       7: iand
       8: putfield      #20                 // Field bitField0_:I
      11: aload_0
      12: lconst_0
      13: putfield      #21                 // Field creationTime_:J
      16: aload_0
      17: invokevirtual #40                 // Method onChanged:()V
      20: aload_0
      21: areturn

  public boolean hasType();
    Code:
       0: aload_0
       1: getfield      #20                 // Field bitField0_:I
       4: bipush        8
       6: iand
       7: bipush        8
       9: if_icmpne     16
      12: iconst_1
      13: goto          17
      16: iconst_0
      17: ireturn

  public org.apache.hadoop.hbase.protobuf.generated.HBaseProtos$SnapshotDescription$Type getType();
    Code:
       0: aload_0
       1: getfield      #13                 // Field type_:Lorg/apache/hadoop/hbase/protobuf/generated/HBaseProtos$SnapshotDescription$Type;
       4: areturn

  public org.apache.hadoop.hbase.protobuf.generated.HBaseProtos$SnapshotDescription$Builder setType(org.apache.hadoop.hbase.protobuf.generated.HBaseProtos$SnapshotDescription$Type);
    Code:
       0: aload_1
       1: ifnonnull     12
       4: new           #65                 // class java/lang/NullPointerException
       7: dup
       8: invokespecial #66                 // Method java/lang/NullPointerException."<init>":()V
      11: athrow
      12: aload_0
      13: dup
      14: getfield      #20                 // Field bitField0_:I
      17: bipush        8
      19: ior
      20: putfield      #20                 // Field bitField0_:I
      23: aload_0
      24: aload_1
      25: putfield      #13                 // Field type_:Lorg/apache/hadoop/hbase/protobuf/generated/HBaseProtos$SnapshotDescription$Type;
      28: aload_0
      29: invokevirtual #40                 // Method onChanged:()V
      32: aload_0
      33: areturn

  public org.apache.hadoop.hbase.protobuf.generated.HBaseProtos$SnapshotDescription$Builder clearType();
    Code:
       0: aload_0
       1: aload_0
       2: getfield      #20                 // Field bitField0_:I
       5: bipush        -9
       7: iand
       8: putfield      #20                 // Field bitField0_:I
      11: aload_0
      12: getstatic     #12                 // Field org/apache/hadoop/hbase/protobuf/generated/HBaseProtos$SnapshotDescription$Type.FLUSH:Lorg/apache/hadoop/hbase/protobuf/generated/HBaseProtos$SnapshotDescription$Type;
      15: putfield      #13                 // Field type_:Lorg/apache/hadoop/hbase/protobuf/generated/HBaseProtos$SnapshotDescription$Type;
      18: aload_0
      19: invokevirtual #40                 // Method onChanged:()V
      22: aload_0
      23: areturn

  public boolean hasVersion();
    Code:
       0: aload_0
       1: getfield      #20                 // Field bitField0_:I
       4: bipush        16
       6: iand
       7: bipush        16
       9: if_icmpne     16
      12: iconst_1
      13: goto          17
      16: iconst_0
      17: ireturn

  public int getVersion();
    Code:
       0: aload_0
       1: getfield      #22                 // Field version_:I
       4: ireturn

  public org.apache.hadoop.hbase.protobuf.generated.HBaseProtos$SnapshotDescription$Builder setVersion(int);
    Code:
       0: aload_0
       1: dup
       2: getfield      #20                 // Field bitField0_:I
       5: bipush        16
       7: ior
       8: putfield      #20                 // Field bitField0_:I
      11: aload_0
      12: iload_1
      13: putfield      #22                 // Field version_:I
      16: aload_0
      17: invokevirtual #40                 // Method onChanged:()V
      20: aload_0
      21: areturn

  public org.apache.hadoop.hbase.protobuf.generated.HBaseProtos$SnapshotDescription$Builder clearVersion();
    Code:
       0: aload_0
       1: aload_0
       2: getfield      #20                 // Field bitField0_:I
       5: bipush        -17
       7: iand
       8: putfield      #20                 // Field bitField0_:I
      11: aload_0
      12: iconst_0
      13: putfield      #22                 // Field version_:I
      16: aload_0
      17: invokevirtual #40                 // Method onChanged:()V
      20: aload_0
      21: areturn

  public boolean hasOwner();
    Code:
       0: aload_0
       1: getfield      #20                 // Field bitField0_:I
       4: bipush        32
       6: iand
       7: bipush        32
       9: if_icmpne     16
      12: iconst_1
      13: goto          17
      16: iconst_0
      17: ireturn

  public java.lang.String getOwner();
    Code:
       0: aload_0
       1: getfield      #14                 // Field owner_:Ljava/lang/Object;
       4: astore_1
       5: aload_1
       6: instanceof    #61                 // class java/lang/String
       9: ifne          27
      12: aload_1
      13: checkcast     #62                 // class com/google/protobuf/ByteString
      16: invokevirtual #63                 // Method com/google/protobuf/ByteString.toStringUtf8:()Ljava/lang/String;
      19: astore_2
      20: aload_0
      21: aload_2
      22: putfield      #14                 // Field owner_:Ljava/lang/Object;
      25: aload_2
      26: areturn
      27: aload_1
      28: checkcast     #61                 // class java/lang/String
      31: areturn

  public com.google.protobuf.ByteString getOwnerBytes();
    Code:
       0: aload_0
       1: getfield      #14                 // Field owner_:Ljava/lang/Object;
       4: astore_1
       5: aload_1
       6: instanceof    #61                 // class java/lang/String
       9: ifeq          27
      12: aload_1
      13: checkcast     #61                 // class java/lang/String
      16: invokestatic  #64                 // Method com/google/protobuf/ByteString.copyFromUtf8:(Ljava/lang/String;)Lcom/google/protobuf/ByteString;
      19: astore_2
      20: aload_0
      21: aload_2
      22: putfield      #14                 // Field owner_:Ljava/lang/Object;
      25: aload_2
      26: areturn
      27: aload_1
      28: checkcast     #62                 // class com/google/protobuf/ByteString
      31: areturn

  public org.apache.hadoop.hbase.protobuf.generated.HBaseProtos$SnapshotDescription$Builder setOwner(java.lang.String);
    Code:
       0: aload_1
       1: ifnonnull     12
       4: new           #65                 // class java/lang/NullPointerException
       7: dup
       8: invokespecial #66                 // Method java/lang/NullPointerException."<init>":()V
      11: athrow
      12: aload_0
      13: dup
      14: getfield      #20                 // Field bitField0_:I
      17: bipush        32
      19: ior
      20: putfield      #20                 // Field bitField0_:I
      23: aload_0
      24: aload_1
      25: putfield      #14                 // Field owner_:Ljava/lang/Object;
      28: aload_0
      29: invokevirtual #40                 // Method onChanged:()V
      32: aload_0
      33: areturn

  public org.apache.hadoop.hbase.protobuf.generated.HBaseProtos$SnapshotDescription$Builder clearOwner();
    Code:
       0: aload_0
       1: aload_0
       2: getfield      #20                 // Field bitField0_:I
       5: bipush        -33
       7: iand
       8: putfield      #20                 // Field bitField0_:I
      11: aload_0
      12: invokestatic  #25                 // Method org/apache/hadoop/hbase/protobuf/generated/HBaseProtos$SnapshotDescription.getDefaultInstance:()Lorg/apache/hadoop/hbase/protobuf/generated/HBaseProtos$SnapshotDescription;
      15: invokevirtual #69                 // Method org/apache/hadoop/hbase/protobuf/generated/HBaseProtos$SnapshotDescription.getOwner:()Ljava/lang/String;
      18: putfield      #14                 // Field owner_:Ljava/lang/Object;
      21: aload_0
      22: invokevirtual #40                 // Method onChanged:()V
      25: aload_0
      26: areturn

  public org.apache.hadoop.hbase.protobuf.generated.HBaseProtos$SnapshotDescription$Builder setOwnerBytes(com.google.protobuf.ByteString);
    Code:
       0: aload_1
       1: ifnonnull     12
       4: new           #65                 // class java/lang/NullPointerException
       7: dup
       8: invokespecial #66                 // Method java/lang/NullPointerException."<init>":()V
      11: athrow
      12: aload_0
      13: dup
      14: getfield      #20                 // Field bitField0_:I
      17: bipush        32
      19: ior
      20: putfield      #20                 // Field bitField0_:I
      23: aload_0
      24: aload_1
      25: putfield      #14                 // Field owner_:Ljava/lang/Object;
      28: aload_0
      29: invokevirtual #40                 // Method onChanged:()V
      32: aload_0
      33: areturn

  public com.google.protobuf.GeneratedMessage$Builder clear();
    Code:
       0: aload_0
       1: invokevirtual #70                 // Method clear:()Lorg/apache/hadoop/hbase/protobuf/generated/HBaseProtos$SnapshotDescription$Builder;
       4: areturn

  public com.google.protobuf.GeneratedMessage$Builder clone();
    Code:
       0: aload_0
       1: invokevirtual #71                 // Method clone:()Lorg/apache/hadoop/hbase/protobuf/generated/HBaseProtos$SnapshotDescription$Builder;
       4: areturn

  public com.google.protobuf.AbstractMessage$Builder mergeFrom(com.google.protobuf.CodedInputStream, com.google.protobuf.ExtensionRegistryLite) throws java.io.IOException;
    Code:
       0: aload_0
       1: aload_1
       2: aload_2
       3: invokevirtual #72                 // Method mergeFrom:(Lcom/google/protobuf/CodedInputStream;Lcom/google/protobuf/ExtensionRegistryLite;)Lorg/apache/hadoop/hbase/protobuf/generated/HBaseProtos$SnapshotDescription$Builder;
       6: areturn

  public com.google.protobuf.AbstractMessage$Builder mergeFrom(com.google.protobuf.Message);
    Code:
       0: aload_0
       1: aload_1
       2: invokevirtual #73                 // Method mergeFrom:(Lcom/google/protobuf/Message;)Lorg/apache/hadoop/hbase/protobuf/generated/HBaseProtos$SnapshotDescription$Builder;
       5: areturn

  public com.google.protobuf.AbstractMessage$Builder clear();
    Code:
       0: aload_0
       1: invokevirtual #70                 // Method clear:()Lorg/apache/hadoop/hbase/protobuf/generated/HBaseProtos$SnapshotDescription$Builder;
       4: areturn

  public com.google.protobuf.AbstractMessage$Builder clone();
    Code:
       0: aload_0
       1: invokevirtual #71                 // Method clone:()Lorg/apache/hadoop/hbase/protobuf/generated/HBaseProtos$SnapshotDescription$Builder;
       4: areturn

  public com.google.protobuf.Message$Builder mergeFrom(com.google.protobuf.CodedInputStream, com.google.protobuf.ExtensionRegistryLite) throws java.io.IOException;
    Code:
       0: aload_0
       1: aload_1
       2: aload_2
       3: invokevirtual #72                 // Method mergeFrom:(Lcom/google/protobuf/CodedInputStream;Lcom/google/protobuf/ExtensionRegistryLite;)Lorg/apache/hadoop/hbase/protobuf/generated/HBaseProtos$SnapshotDescription$Builder;
       6: areturn

  public com.google.protobuf.Message$Builder clone();
    Code:
       0: aload_0
       1: invokevirtual #71                 // Method clone:()Lorg/apache/hadoop/hbase/protobuf/generated/HBaseProtos$SnapshotDescription$Builder;
       4: areturn

  public com.google.protobuf.Message buildPartial();
    Code:
       0: aload_0
       1: invokevirtual #23                 // Method buildPartial:()Lorg/apache/hadoop/hbase/protobuf/generated/HBaseProtos$SnapshotDescription;
       4: areturn

  public com.google.protobuf.Message build();
    Code:
       0: aload_0
       1: invokevirtual #74                 // Method build:()Lorg/apache/hadoop/hbase/protobuf/generated/HBaseProtos$SnapshotDescription;
       4: areturn

  public com.google.protobuf.Message$Builder mergeFrom(com.google.protobuf.Message);
    Code:
       0: aload_0
       1: aload_1
       2: invokevirtual #73                 // Method mergeFrom:(Lcom/google/protobuf/Message;)Lorg/apache/hadoop/hbase/protobuf/generated/HBaseProtos$SnapshotDescription$Builder;
       5: areturn

  public com.google.protobuf.Message$Builder clear();
    Code:
       0: aload_0
       1: invokevirtual #70                 // Method clear:()Lorg/apache/hadoop/hbase/protobuf/generated/HBaseProtos$SnapshotDescription$Builder;
       4: areturn

  public com.google.protobuf.MessageLite$Builder mergeFrom(com.google.protobuf.CodedInputStream, com.google.protobuf.ExtensionRegistryLite) throws java.io.IOException;
    Code:
       0: aload_0
       1: aload_1
       2: aload_2
       3: invokevirtual #72                 // Method mergeFrom:(Lcom/google/protobuf/CodedInputStream;Lcom/google/protobuf/ExtensionRegistryLite;)Lorg/apache/hadoop/hbase/protobuf/generated/HBaseProtos$SnapshotDescription$Builder;
       6: areturn

  public com.google.protobuf.MessageLite$Builder clone();
    Code:
       0: aload_0
       1: invokevirtual #71                 // Method clone:()Lorg/apache/hadoop/hbase/protobuf/generated/HBaseProtos$SnapshotDescription$Builder;
       4: areturn

  public com.google.protobuf.MessageLite buildPartial();
    Code:
       0: aload_0
       1: invokevirtual #23                 // Method buildPartial:()Lorg/apache/hadoop/hbase/protobuf/generated/HBaseProtos$SnapshotDescription;
       4: areturn

  public com.google.protobuf.MessageLite build();
    Code:
       0: aload_0
       1: invokevirtual #74                 // Method build:()Lorg/apache/hadoop/hbase/protobuf/generated/HBaseProtos$SnapshotDescription;
       4: areturn

  public com.google.protobuf.MessageLite$Builder clear();
    Code:
       0: aload_0
       1: invokevirtual #70                 // Method clear:()Lorg/apache/hadoop/hbase/protobuf/generated/HBaseProtos$SnapshotDescription$Builder;
       4: areturn

  public com.google.protobuf.MessageLite getDefaultInstanceForType();
    Code:
       0: aload_0
       1: invokevirtual #75                 // Method getDefaultInstanceForType:()Lorg/apache/hadoop/hbase/protobuf/generated/HBaseProtos$SnapshotDescription;
       4: areturn

  public com.google.protobuf.Message getDefaultInstanceForType();
    Code:
       0: aload_0
       1: invokevirtual #75                 // Method getDefaultInstanceForType:()Lorg/apache/hadoop/hbase/protobuf/generated/HBaseProtos$SnapshotDescription;
       4: areturn

  public com.google.protobuf.AbstractMessageLite$Builder mergeFrom(com.google.protobuf.CodedInputStream, com.google.protobuf.ExtensionRegistryLite) throws java.io.IOException;
    Code:
       0: aload_0
       1: aload_1
       2: aload_2
       3: invokevirtual #72                 // Method mergeFrom:(Lcom/google/protobuf/CodedInputStream;Lcom/google/protobuf/ExtensionRegistryLite;)Lorg/apache/hadoop/hbase/protobuf/generated/HBaseProtos$SnapshotDescription$Builder;
       6: areturn

  public com.google.protobuf.AbstractMessageLite$Builder clone();
    Code:
       0: aload_0
       1: invokevirtual #71                 // Method clone:()Lorg/apache/hadoop/hbase/protobuf/generated/HBaseProtos$SnapshotDescription$Builder;
       4: areturn

  public java.lang.Object clone() throws java.lang.CloneNotSupportedException;
    Code:
       0: aload_0
       1: invokevirtual #71                 // Method clone:()Lorg/apache/hadoop/hbase/protobuf/generated/HBaseProtos$SnapshotDescription$Builder;
       4: areturn

  static org.apache.hadoop.hbase.protobuf.generated.HBaseProtos$SnapshotDescription$Builder access$16400();
    Code:
       0: invokestatic  #2                  // Method create:()Lorg/apache/hadoop/hbase/protobuf/generated/HBaseProtos$SnapshotDescription$Builder;
       3: areturn

  org.apache.hadoop.hbase.protobuf.generated.HBaseProtos$SnapshotDescription$Builder(com.google.protobuf.GeneratedMessage$BuilderParent, org.apache.hadoop.hbase.protobuf.generated.HBaseProtos$1);
    Code:
       0: aload_0
       1: aload_1
       2: invokespecial #1                  // Method "<init>":(Lcom/google/protobuf/GeneratedMessage$BuilderParent;)V
       5: return
}
