Compiled from "HBaseAdmin.java"
class org.apache.hadoop.hbase.client.HBaseAdmin$91 implements java.util.concurrent.Callable<java.lang.Void> {
  final java.util.Set val$queues;

  final org.apache.hadoop.hbase.shaded.protobuf.generated.AdminProtos$AdminService$BlockingInterface val$admin;

  final org.apache.hadoop.hbase.client.HBaseAdmin this$0;

  org.apache.hadoop.hbase.client.HBaseAdmin$91(org.apache.hadoop.hbase.client.HBaseAdmin, java.util.Set, org.apache.hadoop.hbase.shaded.protobuf.generated.AdminProtos$AdminService$BlockingInterface);
    Code:
       0: aload_0
       1: aload_1
       2: putfield      #1                  // Field this$0:Lorg/apache/hadoop/hbase/client/HBaseAdmin;
       5: aload_0
       6: aload_2
       7: putfield      #2                  // Field val$queues:Ljava/util/Set;
      10: aload_0
      11: aload_3
      12: putfield      #3                  // Field val$admin:Lorg/apache/hadoop/hbase/shaded/protobuf/generated/AdminProtos$AdminService$BlockingInterface;
      15: aload_0
      16: invokespecial #4                  // Method java/lang/Object."<init>":()V
      19: return

  public java.lang.Void call() throws java.lang.Exception;
    Code:
       0: aload_0
       1: getfield      #1                  // Field this$0:Lorg/apache/hadoop/hbase/client/HBaseAdmin;
       4: invokestatic  #5                  // Method org/apache/hadoop/hbase/client/HBaseAdmin.access$400:(Lorg/apache/hadoop/hbase/client/HBaseAdmin;)Lorg/apache/hadoop/hbase/ipc/RpcControllerFactory;
       7: invokevirtual #6                  // Method org/apache/hadoop/hbase/ipc/RpcControllerFactory.newController:()Lorg/apache/hadoop/hbase/ipc/HBaseRpcController;
      10: astore_1
      11: aload_0
      12: getfield      #2                  // Field val$queues:Ljava/util/Set;
      15: invokestatic  #7                  // Method org/apache/hadoop/hbase/shaded/protobuf/RequestConverter.buildClearCompactionQueuesRequest:(Ljava/util/Set;)Lorg/apache/hadoop/hbase/shaded/protobuf/generated/AdminProtos$ClearCompactionQueuesRequest;
      18: astore_2
      19: aload_0
      20: getfield      #3                  // Field val$admin:Lorg/apache/hadoop/hbase/shaded/protobuf/generated/AdminProtos$AdminService$BlockingInterface;
      23: aload_1
      24: aload_2
      25: invokeinterface #8,  3            // InterfaceMethod org/apache/hadoop/hbase/shaded/protobuf/generated/AdminProtos$AdminService$BlockingInterface.clearCompactionQueues:(Lorg/apache/hbase/thirdparty/com/google/protobuf/RpcController;Lorg/apache/hadoop/hbase/shaded/protobuf/generated/AdminProtos$ClearCompactionQueuesRequest;)Lorg/apache/hadoop/hbase/shaded/protobuf/generated/AdminProtos$ClearCompactionQueuesResponse;
      30: pop
      31: aconst_null
      32: areturn

  public java.lang.Object call() throws java.lang.Exception;
    Code:
       0: aload_0
       1: invokevirtual #9                  // Method call:()Ljava/lang/Void;
       4: areturn
}
