Compiled from "HBaseAdmin.java"
class org.apache.hadoop.hbase.client.HBaseAdmin$75 implements java.util.concurrent.Callable<org.apache.hadoop.hbase.shaded.protobuf.generated.AdminProtos$GetRegionInfoResponse> {
  final byte[] val$regionName;

  final org.apache.hadoop.hbase.shaded.protobuf.generated.AdminProtos$AdminService$BlockingInterface val$snAdmin;

  final org.apache.hadoop.hbase.ipc.HBaseRpcController val$rpcController;

  final org.apache.hadoop.hbase.client.HBaseAdmin this$0;

  org.apache.hadoop.hbase.client.HBaseAdmin$75(org.apache.hadoop.hbase.client.HBaseAdmin, byte[], org.apache.hadoop.hbase.shaded.protobuf.generated.AdminProtos$AdminService$BlockingInterface, org.apache.hadoop.hbase.ipc.HBaseRpcController);
    Code:
       0: aload_0
       1: aload_1
       2: putfield      #1                  // Field this$0:Lorg/apache/hadoop/hbase/client/HBaseAdmin;
       5: aload_0
       6: aload_2
       7: putfield      #2                  // Field val$regionName:[B
      10: aload_0
      11: aload_3
      12: putfield      #3                  // Field val$snAdmin:Lorg/apache/hadoop/hbase/shaded/protobuf/generated/AdminProtos$AdminService$BlockingInterface;
      15: aload_0
      16: aload         4
      18: putfield      #4                  // Field val$rpcController:Lorg/apache/hadoop/hbase/ipc/HBaseRpcController;
      21: aload_0
      22: invokespecial #5                  // Method java/lang/Object."<init>":()V
      25: return

  public org.apache.hadoop.hbase.shaded.protobuf.generated.AdminProtos$GetRegionInfoResponse call() throws java.lang.Exception;
    Code:
       0: aload_0
       1: getfield      #2                  // Field val$regionName:[B
       4: iconst_1
       5: invokestatic  #6                  // Method org/apache/hadoop/hbase/shaded/protobuf/RequestConverter.buildGetRegionInfoRequest:([BZ)Lorg/apache/hadoop/hbase/shaded/protobuf/generated/AdminProtos$GetRegionInfoRequest;
       8: astore_1
       9: aload_0
      10: getfield      #3                  // Field val$snAdmin:Lorg/apache/hadoop/hbase/shaded/protobuf/generated/AdminProtos$AdminService$BlockingInterface;
      13: aload_0
      14: getfield      #4                  // Field val$rpcController:Lorg/apache/hadoop/hbase/ipc/HBaseRpcController;
      17: aload_1
      18: invokeinterface #7,  3            // InterfaceMethod org/apache/hadoop/hbase/shaded/protobuf/generated/AdminProtos$AdminService$BlockingInterface.getRegionInfo:(Lorg/apache/hbase/thirdparty/com/google/protobuf/RpcController;Lorg/apache/hadoop/hbase/shaded/protobuf/generated/AdminProtos$GetRegionInfoRequest;)Lorg/apache/hadoop/hbase/shaded/protobuf/generated/AdminProtos$GetRegionInfoResponse;
      23: areturn

  public java.lang.Object call() throws java.lang.Exception;
    Code:
       0: aload_0
       1: invokevirtual #8                  // Method call:()Lorg/apache/hadoop/hbase/shaded/protobuf/generated/AdminProtos$GetRegionInfoResponse;
       4: areturn
}
