Compiled from "HBaseFsck.java"
class org.apache.hadoop.hbase.util.HBaseFsck$TableInfo$HDFSIntegrityFixer extends org.apache.hadoop.hbase.util.HBaseFsck$TableInfo$IntegrityFixSuggester {
  org.apache.hadoop.conf.Configuration conf;

  boolean fixOverlaps;

  final org.apache.hadoop.hbase.util.HBaseFsck$TableInfo this$1;

  org.apache.hadoop.hbase.util.HBaseFsck$TableInfo$HDFSIntegrityFixer(org.apache.hadoop.hbase.util.HBaseFsck$TableInfo, org.apache.hadoop.hbase.util.HBaseFsck$TableInfo, org.apache.hadoop.hbase.util.HBaseFsck$ErrorReporter, org.apache.hadoop.conf.Configuration, boolean, boolean);
    Code:
       0: aload_0
       1: aload_1
       2: putfield      #2                  // Field this$1:Lorg/apache/hadoop/hbase/util/HBaseFsck$TableInfo;
       5: aload_0
       6: aload_1
       7: aload_2
       8: aload_3
       9: invokespecial #3                  // Method org/apache/hadoop/hbase/util/HBaseFsck$TableInfo$IntegrityFixSuggester."<init>":(Lorg/apache/hadoop/hbase/util/HBaseFsck$TableInfo;Lorg/apache/hadoop/hbase/util/HBaseFsck$TableInfo;Lorg/apache/hadoop/hbase/util/HBaseFsck$ErrorReporter;)V
      12: aload_0
      13: iconst_1
      14: putfield      #4                  // Field fixOverlaps:Z
      17: aload_0
      18: aload         4
      20: putfield      #5                  // Field conf:Lorg/apache/hadoop/conf/Configuration;
      23: aload_0
      24: iload         6
      26: putfield      #4                  // Field fixOverlaps:Z
      29: return

  public void handleRegionStartKeyNotEmpty(org.apache.hadoop.hbase.util.HBaseFsck$HbckInfo) throws java.io.IOException;
    Code:
       0: aload_0
       1: getfield      #6                  // Field errors:Lorg/apache/hadoop/hbase/util/HBaseFsck$ErrorReporter;
       4: getstatic     #7                  // Field org/apache/hadoop/hbase/util/HBaseFsck$ErrorReporter$ERROR_CODE.FIRST_REGION_STARTKEY_NOT_EMPTY:Lorg/apache/hadoop/hbase/util/HBaseFsck$ErrorReporter$ERROR_CODE;
       7: ldc           #8                  // String First region should start with an empty key.  Creating a new region and regioninfo in HDFS to plug the hole.
       9: aload_0
      10: invokevirtual #9                  // Method getTableInfo:()Lorg/apache/hadoop/hbase/util/HBaseFsck$TableInfo;
      13: aload_1
      14: invokeinterface #10,  5           // InterfaceMethod org/apache/hadoop/hbase/util/HBaseFsck$ErrorReporter.reportError:(Lorg/apache/hadoop/hbase/util/HBaseFsck$ErrorReporter$ERROR_CODE;Ljava/lang/String;Lorg/apache/hadoop/hbase/util/HBaseFsck$TableInfo;Lorg/apache/hadoop/hbase/util/HBaseFsck$HbckInfo;)V
      19: aload_0
      20: invokevirtual #9                  // Method getTableInfo:()Lorg/apache/hadoop/hbase/util/HBaseFsck$TableInfo;
      23: invokestatic  #11                 // Method org/apache/hadoop/hbase/util/HBaseFsck$TableInfo.access$400:(Lorg/apache/hadoop/hbase/util/HBaseFsck$TableInfo;)Lorg/apache/hadoop/hbase/client/TableDescriptor;
      26: astore_2
      27: aload_2
      28: invokeinterface #12,  1           // InterfaceMethod org/apache/hadoop/hbase/client/TableDescriptor.getTableName:()Lorg/apache/hadoop/hbase/TableName;
      33: invokestatic  #13                 // Method org/apache/hadoop/hbase/client/RegionInfoBuilder.newBuilder:(Lorg/apache/hadoop/hbase/TableName;)Lorg/apache/hadoop/hbase/client/RegionInfoBuilder;
      36: getstatic     #14                 // Field org/apache/hadoop/hbase/HConstants.EMPTY_START_ROW:[B
      39: invokevirtual #15                 // Method org/apache/hadoop/hbase/client/RegionInfoBuilder.setStartKey:([B)Lorg/apache/hadoop/hbase/client/RegionInfoBuilder;
      42: aload_1
      43: invokevirtual #16                 // Method org/apache/hadoop/hbase/util/HBaseFsck$HbckInfo.getStartKey:()[B
      46: invokevirtual #17                 // Method org/apache/hadoop/hbase/client/RegionInfoBuilder.setEndKey:([B)Lorg/apache/hadoop/hbase/client/RegionInfoBuilder;
      49: invokevirtual #18                 // Method org/apache/hadoop/hbase/client/RegionInfoBuilder.build:()Lorg/apache/hadoop/hbase/client/RegionInfo;
      52: astore_3
      53: aload_0
      54: getfield      #5                  // Field conf:Lorg/apache/hadoop/conf/Configuration;
      57: aload_3
      58: aload_2
      59: invokestatic  #19                 // Method org/apache/hadoop/hbase/util/HBaseFsckRepair.createHDFSRegionDir:(Lorg/apache/hadoop/conf/Configuration;Lorg/apache/hadoop/hbase/client/RegionInfo;Lorg/apache/hadoop/hbase/client/TableDescriptor;)Lorg/apache/hadoop/hbase/regionserver/HRegion;
      62: astore        4
      64: invokestatic  #20                 // Method org/apache/hadoop/hbase/util/HBaseFsck.access$000:()Lorg/slf4j/Logger;
      67: new           #21                 // class java/lang/StringBuilder
      70: dup
      71: invokespecial #22                 // Method java/lang/StringBuilder."<init>":()V
      74: ldc           #23                 // String Table region start key was not empty.  Created new empty region:
      76: invokevirtual #24                 // Method java/lang/StringBuilder.append:(Ljava/lang/String;)Ljava/lang/StringBuilder;
      79: aload_3
      80: invokevirtual #25                 // Method java/lang/StringBuilder.append:(Ljava/lang/Object;)Ljava/lang/StringBuilder;
      83: ldc           #26                 // String
      85: invokevirtual #24                 // Method java/lang/StringBuilder.append:(Ljava/lang/String;)Ljava/lang/StringBuilder;
      88: aload         4
      90: invokevirtual #25                 // Method java/lang/StringBuilder.append:(Ljava/lang/Object;)Ljava/lang/StringBuilder;
      93: invokevirtual #27                 // Method java/lang/StringBuilder.toString:()Ljava/lang/String;
      96: invokeinterface #28,  2           // InterfaceMethod org/slf4j/Logger.info:(Ljava/lang/String;)V
     101: aload_0
     102: getfield      #2                  // Field this$1:Lorg/apache/hadoop/hbase/util/HBaseFsck$TableInfo;
     105: getfield      #29                 // Field org/apache/hadoop/hbase/util/HBaseFsck$TableInfo.this$0:Lorg/apache/hadoop/hbase/util/HBaseFsck;
     108: dup
     109: getfield      #30                 // Field org/apache/hadoop/hbase/util/HBaseFsck.fixes:I
     112: iconst_1
     113: iadd
     114: putfield      #30                 // Field org/apache/hadoop/hbase/util/HBaseFsck.fixes:I
     117: return

  public void handleRegionEndKeyNotEmpty(byte[]) throws java.io.IOException;
    Code:
       0: aload_0
       1: getfield      #6                  // Field errors:Lorg/apache/hadoop/hbase/util/HBaseFsck$ErrorReporter;
       4: getstatic     #31                 // Field org/apache/hadoop/hbase/util/HBaseFsck$ErrorReporter$ERROR_CODE.LAST_REGION_ENDKEY_NOT_EMPTY:Lorg/apache/hadoop/hbase/util/HBaseFsck$ErrorReporter$ERROR_CODE;
       7: ldc           #32                 // String Last region should end with an empty key.  Creating a new region and regioninfo in HDFS to plug the hole.
       9: aload_0
      10: invokevirtual #9                  // Method getTableInfo:()Lorg/apache/hadoop/hbase/util/HBaseFsck$TableInfo;
      13: invokeinterface #33,  4           // InterfaceMethod org/apache/hadoop/hbase/util/HBaseFsck$ErrorReporter.reportError:(Lorg/apache/hadoop/hbase/util/HBaseFsck$ErrorReporter$ERROR_CODE;Ljava/lang/String;Lorg/apache/hadoop/hbase/util/HBaseFsck$TableInfo;)V
      18: aload_0
      19: invokevirtual #9                  // Method getTableInfo:()Lorg/apache/hadoop/hbase/util/HBaseFsck$TableInfo;
      22: invokestatic  #11                 // Method org/apache/hadoop/hbase/util/HBaseFsck$TableInfo.access$400:(Lorg/apache/hadoop/hbase/util/HBaseFsck$TableInfo;)Lorg/apache/hadoop/hbase/client/TableDescriptor;
      25: astore_2
      26: aload_2
      27: invokeinterface #12,  1           // InterfaceMethod org/apache/hadoop/hbase/client/TableDescriptor.getTableName:()Lorg/apache/hadoop/hbase/TableName;
      32: invokestatic  #13                 // Method org/apache/hadoop/hbase/client/RegionInfoBuilder.newBuilder:(Lorg/apache/hadoop/hbase/TableName;)Lorg/apache/hadoop/hbase/client/RegionInfoBuilder;
      35: aload_1
      36: invokevirtual #15                 // Method org/apache/hadoop/hbase/client/RegionInfoBuilder.setStartKey:([B)Lorg/apache/hadoop/hbase/client/RegionInfoBuilder;
      39: getstatic     #14                 // Field org/apache/hadoop/hbase/HConstants.EMPTY_START_ROW:[B
      42: invokevirtual #17                 // Method org/apache/hadoop/hbase/client/RegionInfoBuilder.setEndKey:([B)Lorg/apache/hadoop/hbase/client/RegionInfoBuilder;
      45: invokevirtual #18                 // Method org/apache/hadoop/hbase/client/RegionInfoBuilder.build:()Lorg/apache/hadoop/hbase/client/RegionInfo;
      48: astore_3
      49: aload_0
      50: getfield      #5                  // Field conf:Lorg/apache/hadoop/conf/Configuration;
      53: aload_3
      54: aload_2
      55: invokestatic  #19                 // Method org/apache/hadoop/hbase/util/HBaseFsckRepair.createHDFSRegionDir:(Lorg/apache/hadoop/conf/Configuration;Lorg/apache/hadoop/hbase/client/RegionInfo;Lorg/apache/hadoop/hbase/client/TableDescriptor;)Lorg/apache/hadoop/hbase/regionserver/HRegion;
      58: astore        4
      60: invokestatic  #20                 // Method org/apache/hadoop/hbase/util/HBaseFsck.access$000:()Lorg/slf4j/Logger;
      63: new           #21                 // class java/lang/StringBuilder
      66: dup
      67: invokespecial #22                 // Method java/lang/StringBuilder."<init>":()V
      70: ldc           #34                 // String Table region end key was not empty.  Created new empty region:
      72: invokevirtual #24                 // Method java/lang/StringBuilder.append:(Ljava/lang/String;)Ljava/lang/StringBuilder;
      75: aload_3
      76: invokevirtual #25                 // Method java/lang/StringBuilder.append:(Ljava/lang/Object;)Ljava/lang/StringBuilder;
      79: ldc           #26                 // String
      81: invokevirtual #24                 // Method java/lang/StringBuilder.append:(Ljava/lang/String;)Ljava/lang/StringBuilder;
      84: aload         4
      86: invokevirtual #25                 // Method java/lang/StringBuilder.append:(Ljava/lang/Object;)Ljava/lang/StringBuilder;
      89: invokevirtual #27                 // Method java/lang/StringBuilder.toString:()Ljava/lang/String;
      92: invokeinterface #28,  2           // InterfaceMethod org/slf4j/Logger.info:(Ljava/lang/String;)V
      97: aload_0
      98: getfield      #2                  // Field this$1:Lorg/apache/hadoop/hbase/util/HBaseFsck$TableInfo;
     101: getfield      #29                 // Field org/apache/hadoop/hbase/util/HBaseFsck$TableInfo.this$0:Lorg/apache/hadoop/hbase/util/HBaseFsck;
     104: dup
     105: getfield      #30                 // Field org/apache/hadoop/hbase/util/HBaseFsck.fixes:I
     108: iconst_1
     109: iadd
     110: putfield      #30                 // Field org/apache/hadoop/hbase/util/HBaseFsck.fixes:I
     113: return

  public void handleHoleInRegionChain(byte[], byte[]) throws java.io.IOException;
    Code:
       0: aload_0
       1: getfield      #6                  // Field errors:Lorg/apache/hadoop/hbase/util/HBaseFsck$ErrorReporter;
       4: getstatic     #35                 // Field org/apache/hadoop/hbase/util/HBaseFsck$ErrorReporter$ERROR_CODE.HOLE_IN_REGION_CHAIN:Lorg/apache/hadoop/hbase/util/HBaseFsck$ErrorReporter$ERROR_CODE;
       7: new           #21                 // class java/lang/StringBuilder
      10: dup
      11: invokespecial #22                 // Method java/lang/StringBuilder."<init>":()V
      14: ldc           #36                 // String There is a hole in the region chain between
      16: invokevirtual #24                 // Method java/lang/StringBuilder.append:(Ljava/lang/String;)Ljava/lang/StringBuilder;
      19: aload_1
      20: invokestatic  #37                 // Method org/apache/hadoop/hbase/util/Bytes.toStringBinary:([B)Ljava/lang/String;
      23: invokevirtual #24                 // Method java/lang/StringBuilder.append:(Ljava/lang/String;)Ljava/lang/StringBuilder;
      26: ldc           #38                 // String  and
      28: invokevirtual #24                 // Method java/lang/StringBuilder.append:(Ljava/lang/String;)Ljava/lang/StringBuilder;
      31: aload_2
      32: invokestatic  #37                 // Method org/apache/hadoop/hbase/util/Bytes.toStringBinary:([B)Ljava/lang/String;
      35: invokevirtual #24                 // Method java/lang/StringBuilder.append:(Ljava/lang/String;)Ljava/lang/StringBuilder;
      38: ldc           #39                 // String .  Creating a new regioninfo and region dir in hdfs to plug the hole.
      40: invokevirtual #24                 // Method java/lang/StringBuilder.append:(Ljava/lang/String;)Ljava/lang/StringBuilder;
      43: invokevirtual #27                 // Method java/lang/StringBuilder.toString:()Ljava/lang/String;
      46: invokeinterface #40,  3           // InterfaceMethod org/apache/hadoop/hbase/util/HBaseFsck$ErrorReporter.reportError:(Lorg/apache/hadoop/hbase/util/HBaseFsck$ErrorReporter$ERROR_CODE;Ljava/lang/String;)V
      51: aload_0
      52: invokevirtual #9                  // Method getTableInfo:()Lorg/apache/hadoop/hbase/util/HBaseFsck$TableInfo;
      55: invokestatic  #11                 // Method org/apache/hadoop/hbase/util/HBaseFsck$TableInfo.access$400:(Lorg/apache/hadoop/hbase/util/HBaseFsck$TableInfo;)Lorg/apache/hadoop/hbase/client/TableDescriptor;
      58: astore_3
      59: aload_3
      60: invokeinterface #12,  1           // InterfaceMethod org/apache/hadoop/hbase/client/TableDescriptor.getTableName:()Lorg/apache/hadoop/hbase/TableName;
      65: invokestatic  #13                 // Method org/apache/hadoop/hbase/client/RegionInfoBuilder.newBuilder:(Lorg/apache/hadoop/hbase/TableName;)Lorg/apache/hadoop/hbase/client/RegionInfoBuilder;
      68: aload_1
      69: invokevirtual #15                 // Method org/apache/hadoop/hbase/client/RegionInfoBuilder.setStartKey:([B)Lorg/apache/hadoop/hbase/client/RegionInfoBuilder;
      72: aload_2
      73: invokevirtual #17                 // Method org/apache/hadoop/hbase/client/RegionInfoBuilder.setEndKey:([B)Lorg/apache/hadoop/hbase/client/RegionInfoBuilder;
      76: invokevirtual #18                 // Method org/apache/hadoop/hbase/client/RegionInfoBuilder.build:()Lorg/apache/hadoop/hbase/client/RegionInfo;
      79: astore        4
      81: aload_0
      82: getfield      #5                  // Field conf:Lorg/apache/hadoop/conf/Configuration;
      85: aload         4
      87: aload_3
      88: invokestatic  #19                 // Method org/apache/hadoop/hbase/util/HBaseFsckRepair.createHDFSRegionDir:(Lorg/apache/hadoop/conf/Configuration;Lorg/apache/hadoop/hbase/client/RegionInfo;Lorg/apache/hadoop/hbase/client/TableDescriptor;)Lorg/apache/hadoop/hbase/regionserver/HRegion;
      91: astore        5
      93: invokestatic  #20                 // Method org/apache/hadoop/hbase/util/HBaseFsck.access$000:()Lorg/slf4j/Logger;
      96: new           #21                 // class java/lang/StringBuilder
      99: dup
     100: invokespecial #22                 // Method java/lang/StringBuilder."<init>":()V
     103: ldc           #41                 // String Plugged hole by creating new empty region:
     105: invokevirtual #24                 // Method java/lang/StringBuilder.append:(Ljava/lang/String;)Ljava/lang/StringBuilder;
     108: aload         4
     110: invokevirtual #25                 // Method java/lang/StringBuilder.append:(Ljava/lang/Object;)Ljava/lang/StringBuilder;
     113: ldc           #26                 // String
     115: invokevirtual #24                 // Method java/lang/StringBuilder.append:(Ljava/lang/String;)Ljava/lang/StringBuilder;
     118: aload         5
     120: invokevirtual #25                 // Method java/lang/StringBuilder.append:(Ljava/lang/Object;)Ljava/lang/StringBuilder;
     123: invokevirtual #27                 // Method java/lang/StringBuilder.toString:()Ljava/lang/String;
     126: invokeinterface #28,  2           // InterfaceMethod org/slf4j/Logger.info:(Ljava/lang/String;)V
     131: aload_0
     132: getfield      #2                  // Field this$1:Lorg/apache/hadoop/hbase/util/HBaseFsck$TableInfo;
     135: getfield      #29                 // Field org/apache/hadoop/hbase/util/HBaseFsck$TableInfo.this$0:Lorg/apache/hadoop/hbase/util/HBaseFsck;
     138: dup
     139: getfield      #30                 // Field org/apache/hadoop/hbase/util/HBaseFsck.fixes:I
     142: iconst_1
     143: iadd
     144: putfield      #30                 // Field org/apache/hadoop/hbase/util/HBaseFsck.fixes:I
     147: return

  public void handleOverlapGroup(java.util.Collection<org.apache.hadoop.hbase.util.HBaseFsck$HbckInfo>) throws java.io.IOException;
    Code:
       0: aload_1
       1: invokestatic  #42                 // Method org/apache/hbase/thirdparty/com/google/common/base/Preconditions.checkNotNull:(Ljava/lang/Object;)Ljava/lang/Object;
       4: pop
       5: aload_1
       6: invokeinterface #43,  1           // InterfaceMethod java/util/Collection.size:()I
      11: ifle          18
      14: iconst_1
      15: goto          19
      18: iconst_0
      19: invokestatic  #44                 // Method org/apache/hbase/thirdparty/com/google/common/base/Preconditions.checkArgument:(Z)V
      22: aload_0
      23: getfield      #4                  // Field fixOverlaps:Z
      26: ifne          40
      29: invokestatic  #20                 // Method org/apache/hadoop/hbase/util/HBaseFsck.access$000:()Lorg/slf4j/Logger;
      32: ldc           #45                 // String Not attempting to repair overlaps.
      34: invokeinterface #46,  2           // InterfaceMethod org/slf4j/Logger.warn:(Ljava/lang/String;)V
      39: return
      40: aload_1
      41: invokeinterface #43,  1           // InterfaceMethod java/util/Collection.size:()I
      46: aload_0
      47: getfield      #2                  // Field this$1:Lorg/apache/hadoop/hbase/util/HBaseFsck$TableInfo;
      50: getfield      #29                 // Field org/apache/hadoop/hbase/util/HBaseFsck$TableInfo.this$0:Lorg/apache/hadoop/hbase/util/HBaseFsck;
      53: invokestatic  #47                 // Method org/apache/hadoop/hbase/util/HBaseFsck.access$1500:(Lorg/apache/hadoop/hbase/util/HBaseFsck;)I
      56: if_icmple     133
      59: invokestatic  #20                 // Method org/apache/hadoop/hbase/util/HBaseFsck.access$000:()Lorg/slf4j/Logger;
      62: new           #21                 // class java/lang/StringBuilder
      65: dup
      66: invokespecial #22                 // Method java/lang/StringBuilder."<init>":()V
      69: ldc           #48                 // String Overlap group has
      71: invokevirtual #24                 // Method java/lang/StringBuilder.append:(Ljava/lang/String;)Ljava/lang/StringBuilder;
      74: aload_1
      75: invokeinterface #43,  1           // InterfaceMethod java/util/Collection.size:()I
      80: invokevirtual #49                 // Method java/lang/StringBuilder.append:(I)Ljava/lang/StringBuilder;
      83: ldc           #50                 // String  overlapping regions which is greater than
      85: invokevirtual #24                 // Method java/lang/StringBuilder.append:(Ljava/lang/String;)Ljava/lang/StringBuilder;
      88: aload_0
      89: getfield      #2                  // Field this$1:Lorg/apache/hadoop/hbase/util/HBaseFsck$TableInfo;
      92: getfield      #29                 // Field org/apache/hadoop/hbase/util/HBaseFsck$TableInfo.this$0:Lorg/apache/hadoop/hbase/util/HBaseFsck;
      95: invokestatic  #47                 // Method org/apache/hadoop/hbase/util/HBaseFsck.access$1500:(Lorg/apache/hadoop/hbase/util/HBaseFsck;)I
      98: invokevirtual #49                 // Method java/lang/StringBuilder.append:(I)Ljava/lang/StringBuilder;
     101: ldc           #51                 // String , the max number of regions to merge
     103: invokevirtual #24                 // Method java/lang/StringBuilder.append:(Ljava/lang/String;)Ljava/lang/StringBuilder;
     106: invokevirtual #27                 // Method java/lang/StringBuilder.toString:()Ljava/lang/String;
     109: invokeinterface #46,  2           // InterfaceMethod org/slf4j/Logger.warn:(Ljava/lang/String;)V
     114: aload_0
     115: getfield      #2                  // Field this$1:Lorg/apache/hadoop/hbase/util/HBaseFsck$TableInfo;
     118: getfield      #29                 // Field org/apache/hadoop/hbase/util/HBaseFsck$TableInfo.this$0:Lorg/apache/hadoop/hbase/util/HBaseFsck;
     121: invokestatic  #52                 // Method org/apache/hadoop/hbase/util/HBaseFsck.access$1600:(Lorg/apache/hadoop/hbase/util/HBaseFsck;)Z
     124: ifeq          132
     127: aload_0
     128: aload_1
     129: invokevirtual #53                 // Method sidelineBigOverlaps:(Ljava/util/Collection;)V
     132: return
     133: aload_0
     134: getfield      #2                  // Field this$1:Lorg/apache/hadoop/hbase/util/HBaseFsck$TableInfo;
     137: getfield      #29                 // Field org/apache/hadoop/hbase/util/HBaseFsck$TableInfo.this$0:Lorg/apache/hadoop/hbase/util/HBaseFsck;
     140: invokevirtual #54                 // Method org/apache/hadoop/hbase/util/HBaseFsck.shouldRemoveParents:()Z
     143: ifeq          151
     146: aload_0
     147: aload_1
     148: invokevirtual #55                 // Method removeParentsAndFixSplits:(Ljava/util/Collection;)V
     151: aload_0
     152: aload_1
     153: invokevirtual #56                 // Method mergeOverlaps:(Ljava/util/Collection;)V
     156: return

  void removeParentsAndFixSplits(java.util.Collection<org.apache.hadoop.hbase.util.HBaseFsck$HbckInfo>) throws java.io.IOException;
    Code:
       0: aconst_null
       1: astore_2
       2: aconst_null
       3: astore_3
       4: aconst_null
       5: astore        4
       7: aconst_null
       8: astore        5
      10: new           #57                 // class java/util/ArrayList
      13: dup
      14: aload_1
      15: invokespecial #58                 // Method java/util/ArrayList."<init>":(Ljava/util/Collection;)V
      18: astore        6
      20: invokestatic  #59                 // Method java/lang/Thread.currentThread:()Ljava/lang/Thread;
      23: invokevirtual #60                 // Method java/lang/Thread.getName:()Ljava/lang/String;
      26: astore        7
      28: invokestatic  #20                 // Method org/apache/hadoop/hbase/util/HBaseFsck.access$000:()Lorg/slf4j/Logger;
      31: new           #21                 // class java/lang/StringBuilder
      34: dup
      35: invokespecial #22                 // Method java/lang/StringBuilder."<init>":()V
      38: ldc           #61                 // String == [
      40: invokevirtual #24                 // Method java/lang/StringBuilder.append:(Ljava/lang/String;)Ljava/lang/StringBuilder;
      43: aload         7
      45: invokevirtual #24                 // Method java/lang/StringBuilder.append:(Ljava/lang/String;)Ljava/lang/StringBuilder;
      48: ldc           #62                 // String ] Attempting fix splits in overlap state.
      50: invokevirtual #24                 // Method java/lang/StringBuilder.append:(Ljava/lang/String;)Ljava/lang/StringBuilder;
      53: invokevirtual #27                 // Method java/lang/StringBuilder.toString:()Ljava/lang/String;
      56: invokeinterface #28,  2           // InterfaceMethod org/slf4j/Logger.info:(Ljava/lang/String;)V
      61: aload_1
      62: invokeinterface #43,  1           // InterfaceMethod java/util/Collection.size:()I
      67: iconst_3
      68: if_icmple     82
      71: invokestatic  #20                 // Method org/apache/hadoop/hbase/util/HBaseFsck.access$000:()Lorg/slf4j/Logger;
      74: ldc           #63                 // String Too many overlaps were found on this group, falling back to regular merge.
      76: invokeinterface #28,  2           // InterfaceMethod org/slf4j/Logger.info:(Ljava/lang/String;)V
      81: return
      82: aload_1
      83: invokeinterface #64,  1           // InterfaceMethod java/util/Collection.iterator:()Ljava/util/Iterator;
      88: astore        8
      90: aload         8
      92: invokeinterface #65,  1           // InterfaceMethod java/util/Iterator.hasNext:()Z
      97: ifeq          198
     100: aload         8
     102: invokeinterface #66,  1           // InterfaceMethod java/util/Iterator.next:()Ljava/lang/Object;
     107: checkcast     #67                 // class org/apache/hadoop/hbase/util/HBaseFsck$HbckInfo
     110: astore        9
     112: aload_2
     113: ifnonnull     137
     116: new           #68                 // class org/apache/hadoop/hbase/util/Pair
     119: dup
     120: aload         9
     122: invokevirtual #16                 // Method org/apache/hadoop/hbase/util/HBaseFsck$HbckInfo.getStartKey:()[B
     125: aload         9
     127: invokevirtual #69                 // Method org/apache/hadoop/hbase/util/HBaseFsck$HbckInfo.getEndKey:()[B
     130: invokespecial #70                 // Method org/apache/hadoop/hbase/util/Pair."<init>":(Ljava/lang/Object;Ljava/lang/Object;)V
     133: astore_2
     134: goto          195
     137: getstatic     #71                 // Field org/apache/hadoop/hbase/util/RegionSplitCalculator.BYTES_COMPARATOR:Ljava/util/Comparator;
     140: aload         9
     142: invokevirtual #16                 // Method org/apache/hadoop/hbase/util/HBaseFsck$HbckInfo.getStartKey:()[B
     145: aload_2
     146: invokevirtual #72                 // Method org/apache/hadoop/hbase/util/Pair.getFirst:()Ljava/lang/Object;
     149: invokeinterface #73,  3           // InterfaceMethod java/util/Comparator.compare:(Ljava/lang/Object;Ljava/lang/Object;)I
     154: ifge          166
     157: aload_2
     158: aload         9
     160: invokevirtual #16                 // Method org/apache/hadoop/hbase/util/HBaseFsck$HbckInfo.getStartKey:()[B
     163: invokevirtual #74                 // Method org/apache/hadoop/hbase/util/Pair.setFirst:(Ljava/lang/Object;)V
     166: getstatic     #71                 // Field org/apache/hadoop/hbase/util/RegionSplitCalculator.BYTES_COMPARATOR:Ljava/util/Comparator;
     169: aload         9
     171: invokevirtual #69                 // Method org/apache/hadoop/hbase/util/HBaseFsck$HbckInfo.getEndKey:()[B
     174: aload_2
     175: invokevirtual #75                 // Method org/apache/hadoop/hbase/util/Pair.getSecond:()Ljava/lang/Object;
     178: invokeinterface #73,  3           // InterfaceMethod java/util/Comparator.compare:(Ljava/lang/Object;Ljava/lang/Object;)I
     183: ifle          195
     186: aload_2
     187: aload         9
     189: invokevirtual #69                 // Method org/apache/hadoop/hbase/util/HBaseFsck$HbckInfo.getEndKey:()[B
     192: invokevirtual #76                 // Method org/apache/hadoop/hbase/util/Pair.setSecond:(Ljava/lang/Object;)V
     195: goto          90
     198: invokestatic  #20                 // Method org/apache/hadoop/hbase/util/HBaseFsck.access$000:()Lorg/slf4j/Logger;
     201: new           #21                 // class java/lang/StringBuilder
     204: dup
     205: invokespecial #22                 // Method java/lang/StringBuilder."<init>":()V
     208: ldc           #77                 // String This group range is [
     210: invokevirtual #24                 // Method java/lang/StringBuilder.append:(Ljava/lang/String;)Ljava/lang/StringBuilder;
     213: aload_2
     214: invokevirtual #72                 // Method org/apache/hadoop/hbase/util/Pair.getFirst:()Ljava/lang/Object;
     217: checkcast     #78                 // class "[B"
     220: invokestatic  #37                 // Method org/apache/hadoop/hbase/util/Bytes.toStringBinary:([B)Ljava/lang/String;
     223: invokevirtual #24                 // Method java/lang/StringBuilder.append:(Ljava/lang/String;)Ljava/lang/StringBuilder;
     226: ldc           #79                 // String ,
     228: invokevirtual #24                 // Method java/lang/StringBuilder.append:(Ljava/lang/String;)Ljava/lang/StringBuilder;
     231: aload_2
     232: invokevirtual #75                 // Method org/apache/hadoop/hbase/util/Pair.getSecond:()Ljava/lang/Object;
     235: checkcast     #78                 // class "[B"
     238: invokestatic  #37                 // Method org/apache/hadoop/hbase/util/Bytes.toStringBinary:([B)Ljava/lang/String;
     241: invokevirtual #24                 // Method java/lang/StringBuilder.append:(Ljava/lang/String;)Ljava/lang/StringBuilder;
     244: ldc           #80                 // String ]
     246: invokevirtual #24                 // Method java/lang/StringBuilder.append:(Ljava/lang/String;)Ljava/lang/StringBuilder;
     249: invokevirtual #27                 // Method java/lang/StringBuilder.toString:()Ljava/lang/String;
     252: invokeinterface #28,  2           // InterfaceMethod org/slf4j/Logger.info:(Ljava/lang/String;)V
     257: aload_1
     258: invokeinterface #64,  1           // InterfaceMethod java/util/Collection.iterator:()Ljava/util/Iterator;
     263: astore        8
     265: aload         8
     267: invokeinterface #65,  1           // InterfaceMethod java/util/Iterator.hasNext:()Z
     272: ifeq          370
     275: aload         8
     277: invokeinterface #66,  1           // InterfaceMethod java/util/Iterator.next:()Ljava/lang/Object;
     282: checkcast     #67                 // class org/apache/hadoop/hbase/util/HBaseFsck$HbckInfo
     285: astore        9
     287: aload         9
     289: invokevirtual #81                 // Method org/apache/hadoop/hbase/util/HBaseFsck$HbckInfo.getHdfsHRI:()Lorg/apache/hadoop/hbase/client/RegionInfo;
     292: invokeinterface #82,  1           // InterfaceMethod org/apache/hadoop/hbase/client/RegionInfo.getStartKey:()[B
     297: aload_2
     298: invokevirtual #72                 // Method org/apache/hadoop/hbase/util/Pair.getFirst:()Ljava/lang/Object;
     301: checkcast     #78                 // class "[B"
     304: invokestatic  #83                 // Method org/apache/hadoop/hbase/util/Bytes.compareTo:([B[B)I
     307: ifne          367
     310: aload         9
     312: invokevirtual #81                 // Method org/apache/hadoop/hbase/util/HBaseFsck$HbckInfo.getHdfsHRI:()Lorg/apache/hadoop/hbase/client/RegionInfo;
     315: invokeinterface #84,  1           // InterfaceMethod org/apache/hadoop/hbase/client/RegionInfo.getEndKey:()[B
     320: aload_2
     321: invokevirtual #75                 // Method org/apache/hadoop/hbase/util/Pair.getSecond:()Ljava/lang/Object;
     324: checkcast     #78                 // class "[B"
     327: invokestatic  #83                 // Method org/apache/hadoop/hbase/util/Bytes.compareTo:([B[B)I
     330: ifne          367
     333: invokestatic  #20                 // Method org/apache/hadoop/hbase/util/HBaseFsck.access$000:()Lorg/slf4j/Logger;
     336: new           #21                 // class java/lang/StringBuilder
     339: dup
     340: invokespecial #22                 // Method java/lang/StringBuilder."<init>":()V
     343: ldc           #85                 // String This is a parent for this group:
     345: invokevirtual #24                 // Method java/lang/StringBuilder.append:(Ljava/lang/String;)Ljava/lang/StringBuilder;
     348: aload         9
     350: invokevirtual #86                 // Method org/apache/hadoop/hbase/util/HBaseFsck$HbckInfo.toString:()Ljava/lang/String;
     353: invokevirtual #24                 // Method java/lang/StringBuilder.append:(Ljava/lang/String;)Ljava/lang/StringBuilder;
     356: invokevirtual #27                 // Method java/lang/StringBuilder.toString:()Ljava/lang/String;
     359: invokeinterface #28,  2           // InterfaceMethod org/slf4j/Logger.info:(Ljava/lang/String;)V
     364: aload         9
     366: astore_3
     367: goto          265
     370: aload_3
     371: ifnull        383
     374: aload         6
     376: aload_3
     377: invokeinterface #87,  2           // InterfaceMethod java/util/Collection.remove:(Ljava/lang/Object;)Z
     382: pop
     383: aload         6
     385: invokeinterface #64,  1           // InterfaceMethod java/util/Collection.iterator:()Ljava/util/Iterator;
     390: astore        8
     392: aload         8
     394: invokeinterface #65,  1           // InterfaceMethod java/util/Iterator.hasNext:()Z
     399: ifeq          517
     402: aload         8
     404: invokeinterface #66,  1           // InterfaceMethod java/util/Iterator.next:()Ljava/lang/Object;
     409: checkcast     #67                 // class org/apache/hadoop/hbase/util/HBaseFsck$HbckInfo
     412: astore        9
     414: aload         9
     416: invokevirtual #81                 // Method org/apache/hadoop/hbase/util/HBaseFsck$HbckInfo.getHdfsHRI:()Lorg/apache/hadoop/hbase/client/RegionInfo;
     419: invokeinterface #82,  1           // InterfaceMethod org/apache/hadoop/hbase/client/RegionInfo.getStartKey:()[B
     424: aload_2
     425: invokevirtual #72                 // Method org/apache/hadoop/hbase/util/Pair.getFirst:()Ljava/lang/Object;
     428: checkcast     #78                 // class "[B"
     431: invokestatic  #83                 // Method org/apache/hadoop/hbase/util/Bytes.compareTo:([B[B)I
     434: ifne          464
     437: aload_3
     438: invokevirtual #81                 // Method org/apache/hadoop/hbase/util/HBaseFsck$HbckInfo.getHdfsHRI:()Lorg/apache/hadoop/hbase/client/RegionInfo;
     441: invokeinterface #88,  1           // InterfaceMethod org/apache/hadoop/hbase/client/RegionInfo.getRegionId:()J
     446: aload         9
     448: invokevirtual #81                 // Method org/apache/hadoop/hbase/util/HBaseFsck$HbckInfo.getHdfsHRI:()Lorg/apache/hadoop/hbase/client/RegionInfo;
     451: invokeinterface #88,  1           // InterfaceMethod org/apache/hadoop/hbase/client/RegionInfo.getRegionId:()J
     456: lcmp
     457: ifge          464
     460: aload         9
     462: astore        4
     464: aload         9
     466: invokevirtual #81                 // Method org/apache/hadoop/hbase/util/HBaseFsck$HbckInfo.getHdfsHRI:()Lorg/apache/hadoop/hbase/client/RegionInfo;
     469: invokeinterface #84,  1           // InterfaceMethod org/apache/hadoop/hbase/client/RegionInfo.getEndKey:()[B
     474: aload_2
     475: invokevirtual #75                 // Method org/apache/hadoop/hbase/util/Pair.getSecond:()Ljava/lang/Object;
     478: checkcast     #78                 // class "[B"
     481: invokestatic  #83                 // Method org/apache/hadoop/hbase/util/Bytes.compareTo:([B[B)I
     484: ifne          514
     487: aload_3
     488: invokevirtual #81                 // Method org/apache/hadoop/hbase/util/HBaseFsck$HbckInfo.getHdfsHRI:()Lorg/apache/hadoop/hbase/client/RegionInfo;
     491: invokeinterface #88,  1           // InterfaceMethod org/apache/hadoop/hbase/client/RegionInfo.getRegionId:()J
     496: aload         9
     498: invokevirtual #81                 // Method org/apache/hadoop/hbase/util/HBaseFsck$HbckInfo.getHdfsHRI:()Lorg/apache/hadoop/hbase/client/RegionInfo;
     501: invokeinterface #88,  1           // InterfaceMethod org/apache/hadoop/hbase/client/RegionInfo.getRegionId:()J
     506: lcmp
     507: ifge          514
     510: aload         9
     512: astore        5
     514: goto          392
     517: aload         4
     519: invokevirtual #81                 // Method org/apache/hadoop/hbase/util/HBaseFsck$HbckInfo.getHdfsHRI:()Lorg/apache/hadoop/hbase/client/RegionInfo;
     522: invokeinterface #88,  1           // InterfaceMethod org/apache/hadoop/hbase/client/RegionInfo.getRegionId:()J
     527: aload         5
     529: invokevirtual #81                 // Method org/apache/hadoop/hbase/util/HBaseFsck$HbckInfo.getHdfsHRI:()Lorg/apache/hadoop/hbase/client/RegionInfo;
     532: invokeinterface #88,  1           // InterfaceMethod org/apache/hadoop/hbase/client/RegionInfo.getRegionId:()J
     537: lcmp
     538: ifne          545
     541: aload_3
     542: ifnonnull     546
     545: return
     546: aload_0
     547: getfield      #5                  // Field conf:Lorg/apache/hadoop/conf/Configuration;
     550: invokestatic  #89                 // Method org/apache/hadoop/fs/FileSystem.get:(Lorg/apache/hadoop/conf/Configuration;)Lorg/apache/hadoop/fs/FileSystem;
     553: astore        8
     555: invokestatic  #20                 // Method org/apache/hadoop/hbase/util/HBaseFsck.access$000:()Lorg/slf4j/Logger;
     558: new           #21                 // class java/lang/StringBuilder
     561: dup
     562: invokespecial #22                 // Method java/lang/StringBuilder."<init>":()V
     565: ldc           #90                 // String Found parent:
     567: invokevirtual #24                 // Method java/lang/StringBuilder.append:(Ljava/lang/String;)Ljava/lang/StringBuilder;
     570: aload_3
     571: invokevirtual #91                 // Method org/apache/hadoop/hbase/util/HBaseFsck$HbckInfo.getRegionNameAsString:()Ljava/lang/String;
     574: invokevirtual #24                 // Method java/lang/StringBuilder.append:(Ljava/lang/String;)Ljava/lang/StringBuilder;
     577: invokevirtual #27                 // Method java/lang/StringBuilder.toString:()Ljava/lang/String;
     580: invokeinterface #28,  2           // InterfaceMethod org/slf4j/Logger.info:(Ljava/lang/String;)V
     585: invokestatic  #20                 // Method org/apache/hadoop/hbase/util/HBaseFsck.access$000:()Lorg/slf4j/Logger;
     588: new           #21                 // class java/lang/StringBuilder
     591: dup
     592: invokespecial #22                 // Method java/lang/StringBuilder."<init>":()V
     595: ldc           #92                 // String Found potential daughter a:
     597: invokevirtual #24                 // Method java/lang/StringBuilder.append:(Ljava/lang/String;)Ljava/lang/StringBuilder;
     600: aload         4
     602: invokevirtual #91                 // Method org/apache/hadoop/hbase/util/HBaseFsck$HbckInfo.getRegionNameAsString:()Ljava/lang/String;
     605: invokevirtual #24                 // Method java/lang/StringBuilder.append:(Ljava/lang/String;)Ljava/lang/StringBuilder;
     608: invokevirtual #27                 // Method java/lang/StringBuilder.toString:()Ljava/lang/String;
     611: invokeinterface #28,  2           // InterfaceMethod org/slf4j/Logger.info:(Ljava/lang/String;)V
     616: invokestatic  #20                 // Method org/apache/hadoop/hbase/util/HBaseFsck.access$000:()Lorg/slf4j/Logger;
     619: new           #21                 // class java/lang/StringBuilder
     622: dup
     623: invokespecial #22                 // Method java/lang/StringBuilder."<init>":()V
     626: ldc           #93                 // String Found potential daughter b:
     628: invokevirtual #24                 // Method java/lang/StringBuilder.append:(Ljava/lang/String;)Ljava/lang/StringBuilder;
     631: aload         5
     633: invokevirtual #91                 // Method org/apache/hadoop/hbase/util/HBaseFsck$HbckInfo.getRegionNameAsString:()Ljava/lang/String;
     636: invokevirtual #24                 // Method java/lang/StringBuilder.append:(Ljava/lang/String;)Ljava/lang/StringBuilder;
     639: invokevirtual #27                 // Method java/lang/StringBuilder.toString:()Ljava/lang/String;
     642: invokeinterface #28,  2           // InterfaceMethod org/slf4j/Logger.info:(Ljava/lang/String;)V
     647: invokestatic  #20                 // Method org/apache/hadoop/hbase/util/HBaseFsck.access$000:()Lorg/slf4j/Logger;
     650: ldc           #94                 // String Trying to fix parent in overlap by removing the parent.
     652: invokeinterface #28,  2           // InterfaceMethod org/slf4j/Logger.info:(Ljava/lang/String;)V
     657: aload_0
     658: getfield      #2                  // Field this$1:Lorg/apache/hadoop/hbase/util/HBaseFsck$TableInfo;
     661: getfield      #29                 // Field org/apache/hadoop/hbase/util/HBaseFsck$TableInfo.this$0:Lorg/apache/hadoop/hbase/util/HBaseFsck;
     664: aload_3
     665: invokestatic  #95                 // Method org/apache/hadoop/hbase/util/HBaseFsck.access$1700:(Lorg/apache/hadoop/hbase/util/HBaseFsck;Lorg/apache/hadoop/hbase/util/HBaseFsck$HbckInfo;)V
     668: goto          701
     671: astore        9
     673: invokestatic  #20                 // Method org/apache/hadoop/hbase/util/HBaseFsck.access$000:()Lorg/slf4j/Logger;
     676: ldc           #97                 // String Parent region could not be closed, continuing with regular merge...
     678: aload         9
     680: invokeinterface #98,  3           // InterfaceMethod org/slf4j/Logger.warn:(Ljava/lang/String;Ljava/lang/Throwable;)V
     685: return
     686: astore        9
     688: invokestatic  #20                 // Method org/apache/hadoop/hbase/util/HBaseFsck.access$000:()Lorg/slf4j/Logger;
     691: ldc           #97                 // String Parent region could not be closed, continuing with regular merge...
     693: aload         9
     695: invokeinterface #98,  3           // InterfaceMethod org/slf4j/Logger.warn:(Ljava/lang/String;Ljava/lang/Throwable;)V
     700: return
     701: aload_0
     702: getfield      #2                  // Field this$1:Lorg/apache/hadoop/hbase/util/HBaseFsck$TableInfo;
     705: getfield      #29                 // Field org/apache/hadoop/hbase/util/HBaseFsck$TableInfo.this$0:Lorg/apache/hadoop/hbase/util/HBaseFsck;
     708: aload_3
     709: invokevirtual #100                // Method org/apache/hadoop/hbase/util/HBaseFsck$HbckInfo.getRegionName:()[B
     712: invokestatic  #101                // Method org/apache/hadoop/hbase/util/HBaseFsck.access$1800:(Lorg/apache/hadoop/hbase/util/HBaseFsck;[B)V
     715: goto          758
     718: astore        9
     720: invokestatic  #20                 // Method org/apache/hadoop/hbase/util/HBaseFsck.access$000:()Lorg/slf4j/Logger;
     723: new           #21                 // class java/lang/StringBuilder
     726: dup
     727: invokespecial #22                 // Method java/lang/StringBuilder."<init>":()V
     730: ldc           #102                // String Unable to offline parent region:
     732: invokevirtual #24                 // Method java/lang/StringBuilder.append:(Ljava/lang/String;)Ljava/lang/StringBuilder;
     735: aload_3
     736: invokevirtual #91                 // Method org/apache/hadoop/hbase/util/HBaseFsck$HbckInfo.getRegionNameAsString:()Ljava/lang/String;
     739: invokevirtual #24                 // Method java/lang/StringBuilder.append:(Ljava/lang/String;)Ljava/lang/StringBuilder;
     742: ldc           #103                // String .  Just continuing with regular merge...
     744: invokevirtual #24                 // Method java/lang/StringBuilder.append:(Ljava/lang/String;)Ljava/lang/StringBuilder;
     747: invokevirtual #27                 // Method java/lang/StringBuilder.toString:()Ljava/lang/String;
     750: aload         9
     752: invokeinterface #98,  3           // InterfaceMethod org/slf4j/Logger.warn:(Ljava/lang/String;Ljava/lang/Throwable;)V
     757: return
     758: aload_0
     759: getfield      #5                  // Field conf:Lorg/apache/hadoop/conf/Configuration;
     762: aload_3
     763: invokevirtual #81                 // Method org/apache/hadoop/hbase/util/HBaseFsck$HbckInfo.getHdfsHRI:()Lorg/apache/hadoop/hbase/client/RegionInfo;
     766: invokestatic  #104                // Method org/apache/hadoop/hbase/util/HBaseFsckRepair.removeParentInMeta:(Lorg/apache/hadoop/conf/Configuration;Lorg/apache/hadoop/hbase/client/RegionInfo;)V
     769: goto          812
     772: astore        9
     774: invokestatic  #20                 // Method org/apache/hadoop/hbase/util/HBaseFsck.access$000:()Lorg/slf4j/Logger;
     777: new           #21                 // class java/lang/StringBuilder
     780: dup
     781: invokespecial #22                 // Method java/lang/StringBuilder."<init>":()V
     784: ldc           #105                // String Unable to remove parent region in META:
     786: invokevirtual #24                 // Method java/lang/StringBuilder.append:(Ljava/lang/String;)Ljava/lang/StringBuilder;
     789: aload_3
     790: invokevirtual #91                 // Method org/apache/hadoop/hbase/util/HBaseFsck$HbckInfo.getRegionNameAsString:()Ljava/lang/String;
     793: invokevirtual #24                 // Method java/lang/StringBuilder.append:(Ljava/lang/String;)Ljava/lang/StringBuilder;
     796: ldc           #103                // String .  Just continuing with regular merge...
     798: invokevirtual #24                 // Method java/lang/StringBuilder.append:(Ljava/lang/String;)Ljava/lang/StringBuilder;
     801: invokevirtual #27                 // Method java/lang/StringBuilder.toString:()Ljava/lang/String;
     804: aload         9
     806: invokeinterface #98,  3           // InterfaceMethod org/slf4j/Logger.warn:(Ljava/lang/String;Ljava/lang/Throwable;)V
     811: return
     812: aload_0
     813: getfield      #2                  // Field this$1:Lorg/apache/hadoop/hbase/util/HBaseFsck$TableInfo;
     816: getfield      #29                 // Field org/apache/hadoop/hbase/util/HBaseFsck$TableInfo.this$0:Lorg/apache/hadoop/hbase/util/HBaseFsck;
     819: aload         8
     821: aload_3
     822: invokevirtual #106                // Method org/apache/hadoop/hbase/util/HBaseFsck.sidelineRegionDir:(Lorg/apache/hadoop/fs/FileSystem;Lorg/apache/hadoop/hbase/util/HBaseFsck$HbckInfo;)Lorg/apache/hadoop/fs/Path;
     825: pop
     826: invokestatic  #20                 // Method org/apache/hadoop/hbase/util/HBaseFsck.access$000:()Lorg/slf4j/Logger;
     829: new           #21                 // class java/lang/StringBuilder
     832: dup
     833: invokespecial #22                 // Method java/lang/StringBuilder."<init>":()V
     836: ldc           #107                // String [
     838: invokevirtual #24                 // Method java/lang/StringBuilder.append:(Ljava/lang/String;)Ljava/lang/StringBuilder;
     841: aload         7
     843: invokevirtual #24                 // Method java/lang/StringBuilder.append:(Ljava/lang/String;)Ljava/lang/StringBuilder;
     846: ldc           #108                // String ] Sidelined parent region dir
     848: invokevirtual #24                 // Method java/lang/StringBuilder.append:(Ljava/lang/String;)Ljava/lang/StringBuilder;
     851: aload_3
     852: invokevirtual #109                // Method org/apache/hadoop/hbase/util/HBaseFsck$HbckInfo.getHdfsRegionDir:()Lorg/apache/hadoop/fs/Path;
     855: invokevirtual #25                 // Method java/lang/StringBuilder.append:(Ljava/lang/Object;)Ljava/lang/StringBuilder;
     858: ldc           #110                // String  into
     860: invokevirtual #24                 // Method java/lang/StringBuilder.append:(Ljava/lang/String;)Ljava/lang/StringBuilder;
     863: aload_0
     864: getfield      #2                  // Field this$1:Lorg/apache/hadoop/hbase/util/HBaseFsck$TableInfo;
     867: getfield      #29                 // Field org/apache/hadoop/hbase/util/HBaseFsck$TableInfo.this$0:Lorg/apache/hadoop/hbase/util/HBaseFsck;
     870: invokestatic  #111                // Method org/apache/hadoop/hbase/util/HBaseFsck.access$1900:(Lorg/apache/hadoop/hbase/util/HBaseFsck;)Lorg/apache/hadoop/fs/Path;
     873: invokevirtual #25                 // Method java/lang/StringBuilder.append:(Ljava/lang/Object;)Ljava/lang/StringBuilder;
     876: invokevirtual #27                 // Method java/lang/StringBuilder.toString:()Ljava/lang/String;
     879: invokeinterface #28,  2           // InterfaceMethod org/slf4j/Logger.info:(Ljava/lang/String;)V
     884: aload_0
     885: getfield      #2                  // Field this$1:Lorg/apache/hadoop/hbase/util/HBaseFsck$TableInfo;
     888: getfield      #29                 // Field org/apache/hadoop/hbase/util/HBaseFsck$TableInfo.this$0:Lorg/apache/hadoop/hbase/util/HBaseFsck;
     891: aload_3
     892: invokevirtual #109                // Method org/apache/hadoop/hbase/util/HBaseFsck$HbckInfo.getHdfsRegionDir:()Lorg/apache/hadoop/fs/Path;
     895: invokevirtual #112                // Method org/apache/hadoop/hbase/util/HBaseFsck.debugLsr:(Lorg/apache/hadoop/fs/Path;)V
     898: aload_1
     899: aload_3
     900: invokeinterface #87,  2           // InterfaceMethod java/util/Collection.remove:(Ljava/lang/Object;)Z
     905: pop
     906: aload_1
     907: aload         4
     909: invokeinterface #87,  2           // InterfaceMethod java/util/Collection.remove:(Ljava/lang/Object;)Z
     914: pop
     915: aload_1
     916: aload         5
     918: invokeinterface #87,  2           // InterfaceMethod java/util/Collection.remove:(Ljava/lang/Object;)Z
     923: pop
     924: invokestatic  #20                 // Method org/apache/hadoop/hbase/util/HBaseFsck.access$000:()Lorg/slf4j/Logger;
     927: ldc           #113                // String Done fixing split.
     929: invokeinterface #28,  2           // InterfaceMethod org/slf4j/Logger.info:(Ljava/lang/String;)V
     934: return
    Exception table:
       from    to  target type
         657   668   671   Class java/io/IOException
         657   668   686   Class java/lang/InterruptedException
         701   715   718   Class java/io/IOException
         758   769   772   Class java/io/IOException

  void mergeOverlaps(java.util.Collection<org.apache.hadoop.hbase.util.HBaseFsck$HbckInfo>) throws java.io.IOException;
    Code:
       0: invokestatic  #59                 // Method java/lang/Thread.currentThread:()Ljava/lang/Thread;
       3: invokevirtual #60                 // Method java/lang/Thread.getName:()Ljava/lang/String;
       6: astore_2
       7: invokestatic  #20                 // Method org/apache/hadoop/hbase/util/HBaseFsck.access$000:()Lorg/slf4j/Logger;
      10: new           #21                 // class java/lang/StringBuilder
      13: dup
      14: invokespecial #22                 // Method java/lang/StringBuilder."<init>":()V
      17: ldc           #61                 // String == [
      19: invokevirtual #24                 // Method java/lang/StringBuilder.append:(Ljava/lang/String;)Ljava/lang/StringBuilder;
      22: aload_2
      23: invokevirtual #24                 // Method java/lang/StringBuilder.append:(Ljava/lang/String;)Ljava/lang/StringBuilder;
      26: ldc           #114                // String ] Merging regions into one region:
      28: invokevirtual #24                 // Method java/lang/StringBuilder.append:(Ljava/lang/String;)Ljava/lang/StringBuilder;
      31: ldc           #115                // String ,
      33: invokestatic  #116                // Method org/apache/hbase/thirdparty/com/google/common/base/Joiner.on:(Ljava/lang/String;)Lorg/apache/hbase/thirdparty/com/google/common/base/Joiner;
      36: aload_1
      37: invokevirtual #117                // Method org/apache/hbase/thirdparty/com/google/common/base/Joiner.join:(Ljava/lang/Iterable;)Ljava/lang/String;
      40: invokevirtual #24                 // Method java/lang/StringBuilder.append:(Ljava/lang/String;)Ljava/lang/StringBuilder;
      43: invokevirtual #27                 // Method java/lang/StringBuilder.toString:()Ljava/lang/String;
      46: invokeinterface #28,  2           // InterfaceMethod org/slf4j/Logger.info:(Ljava/lang/String;)V
      51: aconst_null
      52: astore_3
      53: aload_1
      54: invokeinterface #64,  1           // InterfaceMethod java/util/Collection.iterator:()Ljava/util/Iterator;
      59: astore        4
      61: aload         4
      63: invokeinterface #65,  1           // InterfaceMethod java/util/Iterator.hasNext:()Z
      68: ifeq          501
      71: aload         4
      73: invokeinterface #66,  1           // InterfaceMethod java/util/Iterator.next:()Ljava/lang/Object;
      78: checkcast     #67                 // class org/apache/hadoop/hbase/util/HBaseFsck$HbckInfo
      81: astore        5
      83: aload_3
      84: ifnonnull     108
      87: new           #68                 // class org/apache/hadoop/hbase/util/Pair
      90: dup
      91: aload         5
      93: invokevirtual #16                 // Method org/apache/hadoop/hbase/util/HBaseFsck$HbckInfo.getStartKey:()[B
      96: aload         5
      98: invokevirtual #69                 // Method org/apache/hadoop/hbase/util/HBaseFsck$HbckInfo.getEndKey:()[B
     101: invokespecial #70                 // Method org/apache/hadoop/hbase/util/Pair."<init>":(Ljava/lang/Object;Ljava/lang/Object;)V
     104: astore_3
     105: goto          166
     108: getstatic     #71                 // Field org/apache/hadoop/hbase/util/RegionSplitCalculator.BYTES_COMPARATOR:Ljava/util/Comparator;
     111: aload         5
     113: invokevirtual #16                 // Method org/apache/hadoop/hbase/util/HBaseFsck$HbckInfo.getStartKey:()[B
     116: aload_3
     117: invokevirtual #72                 // Method org/apache/hadoop/hbase/util/Pair.getFirst:()Ljava/lang/Object;
     120: invokeinterface #73,  3           // InterfaceMethod java/util/Comparator.compare:(Ljava/lang/Object;Ljava/lang/Object;)I
     125: ifge          137
     128: aload_3
     129: aload         5
     131: invokevirtual #16                 // Method org/apache/hadoop/hbase/util/HBaseFsck$HbckInfo.getStartKey:()[B
     134: invokevirtual #74                 // Method org/apache/hadoop/hbase/util/Pair.setFirst:(Ljava/lang/Object;)V
     137: getstatic     #71                 // Field org/apache/hadoop/hbase/util/RegionSplitCalculator.BYTES_COMPARATOR:Ljava/util/Comparator;
     140: aload         5
     142: invokevirtual #69                 // Method org/apache/hadoop/hbase/util/HBaseFsck$HbckInfo.getEndKey:()[B
     145: aload_3
     146: invokevirtual #75                 // Method org/apache/hadoop/hbase/util/Pair.getSecond:()Ljava/lang/Object;
     149: invokeinterface #73,  3           // InterfaceMethod java/util/Comparator.compare:(Ljava/lang/Object;Ljava/lang/Object;)I
     154: ifle          166
     157: aload_3
     158: aload         5
     160: invokevirtual #69                 // Method org/apache/hadoop/hbase/util/HBaseFsck$HbckInfo.getEndKey:()[B
     163: invokevirtual #76                 // Method org/apache/hadoop/hbase/util/Pair.setSecond:(Ljava/lang/Object;)V
     166: invokestatic  #20                 // Method org/apache/hadoop/hbase/util/HBaseFsck.access$000:()Lorg/slf4j/Logger;
     169: new           #21                 // class java/lang/StringBuilder
     172: dup
     173: invokespecial #22                 // Method java/lang/StringBuilder."<init>":()V
     176: ldc           #107                // String [
     178: invokevirtual #24                 // Method java/lang/StringBuilder.append:(Ljava/lang/String;)Ljava/lang/StringBuilder;
     181: aload_2
     182: invokevirtual #24                 // Method java/lang/StringBuilder.append:(Ljava/lang/String;)Ljava/lang/StringBuilder;
     185: ldc           #118                // String ] Closing region before moving data around:
     187: invokevirtual #24                 // Method java/lang/StringBuilder.append:(Ljava/lang/String;)Ljava/lang/StringBuilder;
     190: aload         5
     192: invokevirtual #25                 // Method java/lang/StringBuilder.append:(Ljava/lang/Object;)Ljava/lang/StringBuilder;
     195: invokevirtual #27                 // Method java/lang/StringBuilder.toString:()Ljava/lang/String;
     198: invokeinterface #119,  2          // InterfaceMethod org/slf4j/Logger.debug:(Ljava/lang/String;)V
     203: invokestatic  #20                 // Method org/apache/hadoop/hbase/util/HBaseFsck.access$000:()Lorg/slf4j/Logger;
     206: new           #21                 // class java/lang/StringBuilder
     209: dup
     210: invokespecial #22                 // Method java/lang/StringBuilder."<init>":()V
     213: ldc           #107                // String [
     215: invokevirtual #24                 // Method java/lang/StringBuilder.append:(Ljava/lang/String;)Ljava/lang/StringBuilder;
     218: aload_2
     219: invokevirtual #24                 // Method java/lang/StringBuilder.append:(Ljava/lang/String;)Ljava/lang/StringBuilder;
     222: ldc           #120                // String ] Contained region dir before close
     224: invokevirtual #24                 // Method java/lang/StringBuilder.append:(Ljava/lang/String;)Ljava/lang/StringBuilder;
     227: invokevirtual #27                 // Method java/lang/StringBuilder.toString:()Ljava/lang/String;
     230: invokeinterface #119,  2          // InterfaceMethod org/slf4j/Logger.debug:(Ljava/lang/String;)V
     235: aload_0
     236: getfield      #2                  // Field this$1:Lorg/apache/hadoop/hbase/util/HBaseFsck$TableInfo;
     239: getfield      #29                 // Field org/apache/hadoop/hbase/util/HBaseFsck$TableInfo.this$0:Lorg/apache/hadoop/hbase/util/HBaseFsck;
     242: aload         5
     244: invokevirtual #109                // Method org/apache/hadoop/hbase/util/HBaseFsck$HbckInfo.getHdfsRegionDir:()Lorg/apache/hadoop/fs/Path;
     247: invokevirtual #112                // Method org/apache/hadoop/hbase/util/HBaseFsck.debugLsr:(Lorg/apache/hadoop/fs/Path;)V
     250: invokestatic  #20                 // Method org/apache/hadoop/hbase/util/HBaseFsck.access$000:()Lorg/slf4j/Logger;
     253: new           #21                 // class java/lang/StringBuilder
     256: dup
     257: invokespecial #22                 // Method java/lang/StringBuilder."<init>":()V
     260: ldc           #107                // String [
     262: invokevirtual #24                 // Method java/lang/StringBuilder.append:(Ljava/lang/String;)Ljava/lang/StringBuilder;
     265: aload_2
     266: invokevirtual #24                 // Method java/lang/StringBuilder.append:(Ljava/lang/String;)Ljava/lang/StringBuilder;
     269: ldc           #121                // String ] Closing region:
     271: invokevirtual #24                 // Method java/lang/StringBuilder.append:(Ljava/lang/String;)Ljava/lang/StringBuilder;
     274: aload         5
     276: invokevirtual #25                 // Method java/lang/StringBuilder.append:(Ljava/lang/Object;)Ljava/lang/StringBuilder;
     279: invokevirtual #27                 // Method java/lang/StringBuilder.toString:()Ljava/lang/String;
     282: invokeinterface #28,  2           // InterfaceMethod org/slf4j/Logger.info:(Ljava/lang/String;)V
     287: aload_0
     288: getfield      #2                  // Field this$1:Lorg/apache/hadoop/hbase/util/HBaseFsck$TableInfo;
     291: getfield      #29                 // Field org/apache/hadoop/hbase/util/HBaseFsck$TableInfo.this$0:Lorg/apache/hadoop/hbase/util/HBaseFsck;
     294: aload         5
     296: invokestatic  #95                 // Method org/apache/hadoop/hbase/util/HBaseFsck.access$1700:(Lorg/apache/hadoop/hbase/util/HBaseFsck;Lorg/apache/hadoop/hbase/util/HBaseFsck$HbckInfo;)V
     299: goto          397
     302: astore        6
     304: invokestatic  #20                 // Method org/apache/hadoop/hbase/util/HBaseFsck.access$000:()Lorg/slf4j/Logger;
     307: new           #21                 // class java/lang/StringBuilder
     310: dup
     311: invokespecial #22                 // Method java/lang/StringBuilder."<init>":()V
     314: ldc           #107                // String [
     316: invokevirtual #24                 // Method java/lang/StringBuilder.append:(Ljava/lang/String;)Ljava/lang/StringBuilder;
     319: aload_2
     320: invokevirtual #24                 // Method java/lang/StringBuilder.append:(Ljava/lang/String;)Ljava/lang/StringBuilder;
     323: ldc           #122                // String ] Was unable to close region
     325: invokevirtual #24                 // Method java/lang/StringBuilder.append:(Ljava/lang/String;)Ljava/lang/StringBuilder;
     328: aload         5
     330: invokevirtual #25                 // Method java/lang/StringBuilder.append:(Ljava/lang/Object;)Ljava/lang/StringBuilder;
     333: ldc           #123                // String .  Just continuing...
     335: invokevirtual #24                 // Method java/lang/StringBuilder.append:(Ljava/lang/String;)Ljava/lang/StringBuilder;
     338: invokevirtual #27                 // Method java/lang/StringBuilder.toString:()Ljava/lang/String;
     341: aload         6
     343: invokeinterface #98,  3           // InterfaceMethod org/slf4j/Logger.warn:(Ljava/lang/String;Ljava/lang/Throwable;)V
     348: goto          397
     351: astore        6
     353: invokestatic  #20                 // Method org/apache/hadoop/hbase/util/HBaseFsck.access$000:()Lorg/slf4j/Logger;
     356: new           #21                 // class java/lang/StringBuilder
     359: dup
     360: invokespecial #22                 // Method java/lang/StringBuilder."<init>":()V
     363: ldc           #107                // String [
     365: invokevirtual #24                 // Method java/lang/StringBuilder.append:(Ljava/lang/String;)Ljava/lang/StringBuilder;
     368: aload_2
     369: invokevirtual #24                 // Method java/lang/StringBuilder.append:(Ljava/lang/String;)Ljava/lang/StringBuilder;
     372: ldc           #122                // String ] Was unable to close region
     374: invokevirtual #24                 // Method java/lang/StringBuilder.append:(Ljava/lang/String;)Ljava/lang/StringBuilder;
     377: aload         5
     379: invokevirtual #25                 // Method java/lang/StringBuilder.append:(Ljava/lang/Object;)Ljava/lang/StringBuilder;
     382: ldc           #123                // String .  Just continuing...
     384: invokevirtual #24                 // Method java/lang/StringBuilder.append:(Ljava/lang/String;)Ljava/lang/StringBuilder;
     387: invokevirtual #27                 // Method java/lang/StringBuilder.toString:()Ljava/lang/String;
     390: aload         6
     392: invokeinterface #98,  3           // InterfaceMethod org/slf4j/Logger.warn:(Ljava/lang/String;Ljava/lang/Throwable;)V
     397: invokestatic  #20                 // Method org/apache/hadoop/hbase/util/HBaseFsck.access$000:()Lorg/slf4j/Logger;
     400: new           #21                 // class java/lang/StringBuilder
     403: dup
     404: invokespecial #22                 // Method java/lang/StringBuilder."<init>":()V
     407: ldc           #107                // String [
     409: invokevirtual #24                 // Method java/lang/StringBuilder.append:(Ljava/lang/String;)Ljava/lang/StringBuilder;
     412: aload_2
     413: invokevirtual #24                 // Method java/lang/StringBuilder.append:(Ljava/lang/String;)Ljava/lang/StringBuilder;
     416: ldc           #124                // String ] Offlining region:
     418: invokevirtual #24                 // Method java/lang/StringBuilder.append:(Ljava/lang/String;)Ljava/lang/StringBuilder;
     421: aload         5
     423: invokevirtual #25                 // Method java/lang/StringBuilder.append:(Ljava/lang/Object;)Ljava/lang/StringBuilder;
     426: invokevirtual #27                 // Method java/lang/StringBuilder.toString:()Ljava/lang/String;
     429: invokeinterface #28,  2           // InterfaceMethod org/slf4j/Logger.info:(Ljava/lang/String;)V
     434: aload_0
     435: getfield      #2                  // Field this$1:Lorg/apache/hadoop/hbase/util/HBaseFsck$TableInfo;
     438: getfield      #29                 // Field org/apache/hadoop/hbase/util/HBaseFsck$TableInfo.this$0:Lorg/apache/hadoop/hbase/util/HBaseFsck;
     441: aload         5
     443: invokevirtual #100                // Method org/apache/hadoop/hbase/util/HBaseFsck$HbckInfo.getRegionName:()[B
     446: invokestatic  #101                // Method org/apache/hadoop/hbase/util/HBaseFsck.access$1800:(Lorg/apache/hadoop/hbase/util/HBaseFsck;[B)V
     449: goto          498
     452: astore        6
     454: invokestatic  #20                 // Method org/apache/hadoop/hbase/util/HBaseFsck.access$000:()Lorg/slf4j/Logger;
     457: new           #21                 // class java/lang/StringBuilder
     460: dup
     461: invokespecial #22                 // Method java/lang/StringBuilder."<init>":()V
     464: ldc           #107                // String [
     466: invokevirtual #24                 // Method java/lang/StringBuilder.append:(Ljava/lang/String;)Ljava/lang/StringBuilder;
     469: aload_2
     470: invokevirtual #24                 // Method java/lang/StringBuilder.append:(Ljava/lang/String;)Ljava/lang/StringBuilder;
     473: ldc           #125                // String ] Unable to offline region from master:
     475: invokevirtual #24                 // Method java/lang/StringBuilder.append:(Ljava/lang/String;)Ljava/lang/StringBuilder;
     478: aload         5
     480: invokevirtual #25                 // Method java/lang/StringBuilder.append:(Ljava/lang/Object;)Ljava/lang/StringBuilder;
     483: ldc           #123                // String .  Just continuing...
     485: invokevirtual #24                 // Method java/lang/StringBuilder.append:(Ljava/lang/String;)Ljava/lang/StringBuilder;
     488: invokevirtual #27                 // Method java/lang/StringBuilder.toString:()Ljava/lang/String;
     491: aload         6
     493: invokeinterface #98,  3           // InterfaceMethod org/slf4j/Logger.warn:(Ljava/lang/String;Ljava/lang/Throwable;)V
     498: goto          61
     501: aload_0
     502: invokevirtual #9                  // Method getTableInfo:()Lorg/apache/hadoop/hbase/util/HBaseFsck$TableInfo;
     505: invokestatic  #11                 // Method org/apache/hadoop/hbase/util/HBaseFsck$TableInfo.access$400:(Lorg/apache/hadoop/hbase/util/HBaseFsck$TableInfo;)Lorg/apache/hadoop/hbase/client/TableDescriptor;
     508: astore        4
     510: aload         4
     512: invokeinterface #12,  1           // InterfaceMethod org/apache/hadoop/hbase/client/TableDescriptor.getTableName:()Lorg/apache/hadoop/hbase/TableName;
     517: invokestatic  #13                 // Method org/apache/hadoop/hbase/client/RegionInfoBuilder.newBuilder:(Lorg/apache/hadoop/hbase/TableName;)Lorg/apache/hadoop/hbase/client/RegionInfoBuilder;
     520: aload_3
     521: invokevirtual #72                 // Method org/apache/hadoop/hbase/util/Pair.getFirst:()Ljava/lang/Object;
     524: checkcast     #78                 // class "[B"
     527: invokevirtual #15                 // Method org/apache/hadoop/hbase/client/RegionInfoBuilder.setStartKey:([B)Lorg/apache/hadoop/hbase/client/RegionInfoBuilder;
     530: aload_3
     531: invokevirtual #75                 // Method org/apache/hadoop/hbase/util/Pair.getSecond:()Ljava/lang/Object;
     534: checkcast     #78                 // class "[B"
     537: invokevirtual #17                 // Method org/apache/hadoop/hbase/client/RegionInfoBuilder.setEndKey:([B)Lorg/apache/hadoop/hbase/client/RegionInfoBuilder;
     540: invokevirtual #18                 // Method org/apache/hadoop/hbase/client/RegionInfoBuilder.build:()Lorg/apache/hadoop/hbase/client/RegionInfo;
     543: astore        5
     545: aload_0
     546: getfield      #5                  // Field conf:Lorg/apache/hadoop/conf/Configuration;
     549: aload         5
     551: aload         4
     553: invokestatic  #19                 // Method org/apache/hadoop/hbase/util/HBaseFsckRepair.createHDFSRegionDir:(Lorg/apache/hadoop/conf/Configuration;Lorg/apache/hadoop/hbase/client/RegionInfo;Lorg/apache/hadoop/hbase/client/TableDescriptor;)Lorg/apache/hadoop/hbase/regionserver/HRegion;
     556: astore        6
     558: invokestatic  #20                 // Method org/apache/hadoop/hbase/util/HBaseFsck.access$000:()Lorg/slf4j/Logger;
     561: new           #21                 // class java/lang/StringBuilder
     564: dup
     565: invokespecial #22                 // Method java/lang/StringBuilder."<init>":()V
     568: ldc           #107                // String [
     570: invokevirtual #24                 // Method java/lang/StringBuilder.append:(Ljava/lang/String;)Ljava/lang/StringBuilder;
     573: aload_2
     574: invokevirtual #24                 // Method java/lang/StringBuilder.append:(Ljava/lang/String;)Ljava/lang/StringBuilder;
     577: ldc           #126                // String ] Created new empty container region:
     579: invokevirtual #24                 // Method java/lang/StringBuilder.append:(Ljava/lang/String;)Ljava/lang/StringBuilder;
     582: aload         5
     584: invokevirtual #25                 // Method java/lang/StringBuilder.append:(Ljava/lang/Object;)Ljava/lang/StringBuilder;
     587: ldc           #127                // String  to contain regions:
     589: invokevirtual #24                 // Method java/lang/StringBuilder.append:(Ljava/lang/String;)Ljava/lang/StringBuilder;
     592: ldc           #115                // String ,
     594: invokestatic  #116                // Method org/apache/hbase/thirdparty/com/google/common/base/Joiner.on:(Ljava/lang/String;)Lorg/apache/hbase/thirdparty/com/google/common/base/Joiner;
     597: aload_1
     598: invokevirtual #117                // Method org/apache/hbase/thirdparty/com/google/common/base/Joiner.join:(Ljava/lang/Iterable;)Ljava/lang/String;
     601: invokevirtual #24                 // Method java/lang/StringBuilder.append:(Ljava/lang/String;)Ljava/lang/StringBuilder;
     604: invokevirtual #27                 // Method java/lang/StringBuilder.toString:()Ljava/lang/String;
     607: invokeinterface #28,  2           // InterfaceMethod org/slf4j/Logger.info:(Ljava/lang/String;)V
     612: aload_0
     613: getfield      #2                  // Field this$1:Lorg/apache/hadoop/hbase/util/HBaseFsck$TableInfo;
     616: getfield      #29                 // Field org/apache/hadoop/hbase/util/HBaseFsck$TableInfo.this$0:Lorg/apache/hadoop/hbase/util/HBaseFsck;
     619: aload         6
     621: invokevirtual #128                // Method org/apache/hadoop/hbase/regionserver/HRegion.getRegionFileSystem:()Lorg/apache/hadoop/hbase/regionserver/HRegionFileSystem;
     624: invokevirtual #129                // Method org/apache/hadoop/hbase/regionserver/HRegionFileSystem.getRegionDir:()Lorg/apache/hadoop/fs/Path;
     627: invokevirtual #112                // Method org/apache/hadoop/hbase/util/HBaseFsck.debugLsr:(Lorg/apache/hadoop/fs/Path;)V
     630: iconst_0
     631: istore        7
     633: aload         6
     635: invokevirtual #128                // Method org/apache/hadoop/hbase/regionserver/HRegion.getRegionFileSystem:()Lorg/apache/hadoop/hbase/regionserver/HRegionFileSystem;
     638: invokevirtual #129                // Method org/apache/hadoop/hbase/regionserver/HRegionFileSystem.getRegionDir:()Lorg/apache/hadoop/fs/Path;
     641: astore        8
     643: aload_1
     644: invokeinterface #64,  1           // InterfaceMethod java/util/Collection.iterator:()Ljava/util/Iterator;
     649: astore        9
     651: aload         9
     653: invokeinterface #65,  1           // InterfaceMethod java/util/Iterator.hasNext:()Z
     658: ifeq          747
     661: aload         9
     663: invokeinterface #66,  1           // InterfaceMethod java/util/Iterator.next:()Ljava/lang/Object;
     668: checkcast     #67                 // class org/apache/hadoop/hbase/util/HBaseFsck$HbckInfo
     671: astore        10
     673: invokestatic  #20                 // Method org/apache/hadoop/hbase/util/HBaseFsck.access$000:()Lorg/slf4j/Logger;
     676: new           #21                 // class java/lang/StringBuilder
     679: dup
     680: invokespecial #22                 // Method java/lang/StringBuilder."<init>":()V
     683: ldc           #107                // String [
     685: invokevirtual #24                 // Method java/lang/StringBuilder.append:(Ljava/lang/String;)Ljava/lang/StringBuilder;
     688: aload_2
     689: invokevirtual #24                 // Method java/lang/StringBuilder.append:(Ljava/lang/String;)Ljava/lang/StringBuilder;
     692: ldc           #130                // String ] Merging
     694: invokevirtual #24                 // Method java/lang/StringBuilder.append:(Ljava/lang/String;)Ljava/lang/StringBuilder;
     697: aload         10
     699: invokevirtual #25                 // Method java/lang/StringBuilder.append:(Ljava/lang/Object;)Ljava/lang/StringBuilder;
     702: ldc           #110                // String  into
     704: invokevirtual #24                 // Method java/lang/StringBuilder.append:(Ljava/lang/String;)Ljava/lang/StringBuilder;
     707: aload         8
     709: invokevirtual #25                 // Method java/lang/StringBuilder.append:(Ljava/lang/Object;)Ljava/lang/StringBuilder;
     712: invokevirtual #27                 // Method java/lang/StringBuilder.toString:()Ljava/lang/String;
     715: invokeinterface #28,  2           // InterfaceMethod org/slf4j/Logger.info:(Ljava/lang/String;)V
     720: aload_0
     721: getfield      #2                  // Field this$1:Lorg/apache/hadoop/hbase/util/HBaseFsck$TableInfo;
     724: getfield      #29                 // Field org/apache/hadoop/hbase/util/HBaseFsck$TableInfo.this$0:Lorg/apache/hadoop/hbase/util/HBaseFsck;
     727: aload         8
     729: aload         10
     731: invokevirtual #131                // Method org/apache/hadoop/hbase/util/HBaseFsck.mergeRegionDirs:(Lorg/apache/hadoop/fs/Path;Lorg/apache/hadoop/hbase/util/HBaseFsck$HbckInfo;)I
     734: istore        11
     736: iload         11
     738: ifle          744
     741: iconst_1
     742: istore        7
     744: goto          651
     747: iload         7
     749: ifeq          768
     752: aload_0
     753: getfield      #2                  // Field this$1:Lorg/apache/hadoop/hbase/util/HBaseFsck$TableInfo;
     756: getfield      #29                 // Field org/apache/hadoop/hbase/util/HBaseFsck$TableInfo.this$0:Lorg/apache/hadoop/hbase/util/HBaseFsck;
     759: dup
     760: getfield      #30                 // Field org/apache/hadoop/hbase/util/HBaseFsck.fixes:I
     763: iconst_1
     764: iadd
     765: putfield      #30                 // Field org/apache/hadoop/hbase/util/HBaseFsck.fixes:I
     768: return
    Exception table:
       from    to  target type
         250   299   302   Class java/io/IOException
         250   299   351   Class java/lang/InterruptedException
         397   449   452   Class java/io/IOException

  void sidelineBigOverlaps(java.util.Collection<org.apache.hadoop.hbase.util.HBaseFsck$HbckInfo>) throws java.io.IOException;
    Code:
       0: aload_1
       1: invokeinterface #43,  1           // InterfaceMethod java/util/Collection.size:()I
       6: aload_0
       7: getfield      #2                  // Field this$1:Lorg/apache/hadoop/hbase/util/HBaseFsck$TableInfo;
      10: getfield      #29                 // Field org/apache/hadoop/hbase/util/HBaseFsck$TableInfo.this$0:Lorg/apache/hadoop/hbase/util/HBaseFsck;
      13: invokestatic  #47                 // Method org/apache/hadoop/hbase/util/HBaseFsck.access$1500:(Lorg/apache/hadoop/hbase/util/HBaseFsck;)I
      16: isub
      17: istore_2
      18: iload_2
      19: aload_0
      20: getfield      #2                  // Field this$1:Lorg/apache/hadoop/hbase/util/HBaseFsck$TableInfo;
      23: getfield      #29                 // Field org/apache/hadoop/hbase/util/HBaseFsck$TableInfo.this$0:Lorg/apache/hadoop/hbase/util/HBaseFsck;
      26: invokestatic  #132                // Method org/apache/hadoop/hbase/util/HBaseFsck.access$2000:(Lorg/apache/hadoop/hbase/util/HBaseFsck;)I
      29: if_icmple     43
      32: aload_0
      33: getfield      #2                  // Field this$1:Lorg/apache/hadoop/hbase/util/HBaseFsck$TableInfo;
      36: getfield      #29                 // Field org/apache/hadoop/hbase/util/HBaseFsck$TableInfo.this$0:Lorg/apache/hadoop/hbase/util/HBaseFsck;
      39: invokestatic  #132                // Method org/apache/hadoop/hbase/util/HBaseFsck.access$2000:(Lorg/apache/hadoop/hbase/util/HBaseFsck;)I
      42: istore_2
      43: aload_1
      44: iload_2
      45: invokestatic  #133                // Method org/apache/hadoop/hbase/util/RegionSplitCalculator.findBigRanges:(Ljava/util/Collection;I)Ljava/util/List;
      48: astore_3
      49: aload_0
      50: getfield      #5                  // Field conf:Lorg/apache/hadoop/conf/Configuration;
      53: invokestatic  #89                 // Method org/apache/hadoop/fs/FileSystem.get:(Lorg/apache/hadoop/conf/Configuration;)Lorg/apache/hadoop/fs/FileSystem;
      56: astore        4
      58: aload_3
      59: invokeinterface #134,  1          // InterfaceMethod java/util/List.iterator:()Ljava/util/Iterator;
      64: astore        5
      66: aload         5
      68: invokeinterface #65,  1           // InterfaceMethod java/util/Iterator.hasNext:()Z
      73: ifeq          425
      76: aload         5
      78: invokeinterface #66,  1           // InterfaceMethod java/util/Iterator.next:()Ljava/lang/Object;
      83: checkcast     #67                 // class org/apache/hadoop/hbase/util/HBaseFsck$HbckInfo
      86: astore        6
      88: invokestatic  #20                 // Method org/apache/hadoop/hbase/util/HBaseFsck.access$000:()Lorg/slf4j/Logger;
      91: new           #21                 // class java/lang/StringBuilder
      94: dup
      95: invokespecial #22                 // Method java/lang/StringBuilder."<init>":()V
      98: ldc           #135                // String Closing region:
     100: invokevirtual #24                 // Method java/lang/StringBuilder.append:(Ljava/lang/String;)Ljava/lang/StringBuilder;
     103: aload         6
     105: invokevirtual #25                 // Method java/lang/StringBuilder.append:(Ljava/lang/Object;)Ljava/lang/StringBuilder;
     108: invokevirtual #27                 // Method java/lang/StringBuilder.toString:()Ljava/lang/String;
     111: invokeinterface #28,  2           // InterfaceMethod org/slf4j/Logger.info:(Ljava/lang/String;)V
     116: aload_0
     117: getfield      #2                  // Field this$1:Lorg/apache/hadoop/hbase/util/HBaseFsck$TableInfo;
     120: getfield      #29                 // Field org/apache/hadoop/hbase/util/HBaseFsck$TableInfo.this$0:Lorg/apache/hadoop/hbase/util/HBaseFsck;
     123: aload         6
     125: invokestatic  #95                 // Method org/apache/hadoop/hbase/util/HBaseFsck.access$1700:(Lorg/apache/hadoop/hbase/util/HBaseFsck;Lorg/apache/hadoop/hbase/util/HBaseFsck$HbckInfo;)V
     128: goto          208
     131: astore        7
     133: invokestatic  #20                 // Method org/apache/hadoop/hbase/util/HBaseFsck.access$000:()Lorg/slf4j/Logger;
     136: new           #21                 // class java/lang/StringBuilder
     139: dup
     140: invokespecial #22                 // Method java/lang/StringBuilder."<init>":()V
     143: ldc           #136                // String Was unable to close region
     145: invokevirtual #24                 // Method java/lang/StringBuilder.append:(Ljava/lang/String;)Ljava/lang/StringBuilder;
     148: aload         6
     150: invokevirtual #25                 // Method java/lang/StringBuilder.append:(Ljava/lang/Object;)Ljava/lang/StringBuilder;
     153: ldc           #123                // String .  Just continuing...
     155: invokevirtual #24                 // Method java/lang/StringBuilder.append:(Ljava/lang/String;)Ljava/lang/StringBuilder;
     158: invokevirtual #27                 // Method java/lang/StringBuilder.toString:()Ljava/lang/String;
     161: aload         7
     163: invokeinterface #98,  3           // InterfaceMethod org/slf4j/Logger.warn:(Ljava/lang/String;Ljava/lang/Throwable;)V
     168: goto          208
     171: astore        7
     173: invokestatic  #20                 // Method org/apache/hadoop/hbase/util/HBaseFsck.access$000:()Lorg/slf4j/Logger;
     176: new           #21                 // class java/lang/StringBuilder
     179: dup
     180: invokespecial #22                 // Method java/lang/StringBuilder."<init>":()V
     183: ldc           #136                // String Was unable to close region
     185: invokevirtual #24                 // Method java/lang/StringBuilder.append:(Ljava/lang/String;)Ljava/lang/StringBuilder;
     188: aload         6
     190: invokevirtual #25                 // Method java/lang/StringBuilder.append:(Ljava/lang/Object;)Ljava/lang/StringBuilder;
     193: ldc           #123                // String .  Just continuing...
     195: invokevirtual #24                 // Method java/lang/StringBuilder.append:(Ljava/lang/String;)Ljava/lang/StringBuilder;
     198: invokevirtual #27                 // Method java/lang/StringBuilder.toString:()Ljava/lang/String;
     201: aload         7
     203: invokeinterface #98,  3           // InterfaceMethod org/slf4j/Logger.warn:(Ljava/lang/String;Ljava/lang/Throwable;)V
     208: invokestatic  #20                 // Method org/apache/hadoop/hbase/util/HBaseFsck.access$000:()Lorg/slf4j/Logger;
     211: new           #21                 // class java/lang/StringBuilder
     214: dup
     215: invokespecial #22                 // Method java/lang/StringBuilder."<init>":()V
     218: ldc           #137                // String Offlining region:
     220: invokevirtual #24                 // Method java/lang/StringBuilder.append:(Ljava/lang/String;)Ljava/lang/StringBuilder;
     223: aload         6
     225: invokevirtual #25                 // Method java/lang/StringBuilder.append:(Ljava/lang/Object;)Ljava/lang/StringBuilder;
     228: invokevirtual #27                 // Method java/lang/StringBuilder.toString:()Ljava/lang/String;
     231: invokeinterface #28,  2           // InterfaceMethod org/slf4j/Logger.info:(Ljava/lang/String;)V
     236: aload_0
     237: getfield      #2                  // Field this$1:Lorg/apache/hadoop/hbase/util/HBaseFsck$TableInfo;
     240: getfield      #29                 // Field org/apache/hadoop/hbase/util/HBaseFsck$TableInfo.this$0:Lorg/apache/hadoop/hbase/util/HBaseFsck;
     243: aload         6
     245: invokevirtual #100                // Method org/apache/hadoop/hbase/util/HBaseFsck$HbckInfo.getRegionName:()[B
     248: invokestatic  #101                // Method org/apache/hadoop/hbase/util/HBaseFsck.access$1800:(Lorg/apache/hadoop/hbase/util/HBaseFsck;[B)V
     251: goto          291
     254: astore        7
     256: invokestatic  #20                 // Method org/apache/hadoop/hbase/util/HBaseFsck.access$000:()Lorg/slf4j/Logger;
     259: new           #21                 // class java/lang/StringBuilder
     262: dup
     263: invokespecial #22                 // Method java/lang/StringBuilder."<init>":()V
     266: ldc           #138                // String Unable to offline region from master:
     268: invokevirtual #24                 // Method java/lang/StringBuilder.append:(Ljava/lang/String;)Ljava/lang/StringBuilder;
     271: aload         6
     273: invokevirtual #25                 // Method java/lang/StringBuilder.append:(Ljava/lang/Object;)Ljava/lang/StringBuilder;
     276: ldc           #123                // String .  Just continuing...
     278: invokevirtual #24                 // Method java/lang/StringBuilder.append:(Ljava/lang/String;)Ljava/lang/StringBuilder;
     281: invokevirtual #27                 // Method java/lang/StringBuilder.toString:()Ljava/lang/String;
     284: aload         7
     286: invokeinterface #98,  3           // InterfaceMethod org/slf4j/Logger.warn:(Ljava/lang/String;Ljava/lang/Throwable;)V
     291: invokestatic  #20                 // Method org/apache/hadoop/hbase/util/HBaseFsck.access$000:()Lorg/slf4j/Logger;
     294: new           #21                 // class java/lang/StringBuilder
     297: dup
     298: invokespecial #22                 // Method java/lang/StringBuilder."<init>":()V
     301: ldc           #139                // String Before sideline big overlapped region:
     303: invokevirtual #24                 // Method java/lang/StringBuilder.append:(Ljava/lang/String;)Ljava/lang/StringBuilder;
     306: aload         6
     308: invokevirtual #86                 // Method org/apache/hadoop/hbase/util/HBaseFsck$HbckInfo.toString:()Ljava/lang/String;
     311: invokevirtual #24                 // Method java/lang/StringBuilder.append:(Ljava/lang/String;)Ljava/lang/StringBuilder;
     314: invokevirtual #27                 // Method java/lang/StringBuilder.toString:()Ljava/lang/String;
     317: invokeinterface #28,  2           // InterfaceMethod org/slf4j/Logger.info:(Ljava/lang/String;)V
     322: aload_0
     323: getfield      #2                  // Field this$1:Lorg/apache/hadoop/hbase/util/HBaseFsck$TableInfo;
     326: getfield      #29                 // Field org/apache/hadoop/hbase/util/HBaseFsck$TableInfo.this$0:Lorg/apache/hadoop/hbase/util/HBaseFsck;
     329: aload         4
     331: ldc           #140                // String to_be_loaded
     333: aload         6
     335: invokevirtual #141                // Method org/apache/hadoop/hbase/util/HBaseFsck.sidelineRegionDir:(Lorg/apache/hadoop/fs/FileSystem;Ljava/lang/String;Lorg/apache/hadoop/hbase/util/HBaseFsck$HbckInfo;)Lorg/apache/hadoop/fs/Path;
     338: astore        7
     340: aload         7
     342: ifnull        422
     345: aload_0
     346: getfield      #2                  // Field this$1:Lorg/apache/hadoop/hbase/util/HBaseFsck$TableInfo;
     349: getfield      #142                // Field org/apache/hadoop/hbase/util/HBaseFsck$TableInfo.sidelinedRegions:Ljava/util/Map;
     352: aload         7
     354: aload         6
     356: invokeinterface #143,  3          // InterfaceMethod java/util/Map.put:(Ljava/lang/Object;Ljava/lang/Object;)Ljava/lang/Object;
     361: pop
     362: invokestatic  #20                 // Method org/apache/hadoop/hbase/util/HBaseFsck.access$000:()Lorg/slf4j/Logger;
     365: new           #21                 // class java/lang/StringBuilder
     368: dup
     369: invokespecial #22                 // Method java/lang/StringBuilder."<init>":()V
     372: ldc           #144                // String After sidelined big overlapped region:
     374: invokevirtual #24                 // Method java/lang/StringBuilder.append:(Ljava/lang/String;)Ljava/lang/StringBuilder;
     377: aload         6
     379: invokevirtual #91                 // Method org/apache/hadoop/hbase/util/HBaseFsck$HbckInfo.getRegionNameAsString:()Ljava/lang/String;
     382: invokevirtual #24                 // Method java/lang/StringBuilder.append:(Ljava/lang/String;)Ljava/lang/StringBuilder;
     385: ldc           #145                // String  to
     387: invokevirtual #24                 // Method java/lang/StringBuilder.append:(Ljava/lang/String;)Ljava/lang/StringBuilder;
     390: aload         7
     392: invokevirtual #146                // Method org/apache/hadoop/fs/Path.toString:()Ljava/lang/String;
     395: invokevirtual #24                 // Method java/lang/StringBuilder.append:(Ljava/lang/String;)Ljava/lang/StringBuilder;
     398: invokevirtual #27                 // Method java/lang/StringBuilder.toString:()Ljava/lang/String;
     401: invokeinterface #28,  2           // InterfaceMethod org/slf4j/Logger.info:(Ljava/lang/String;)V
     406: aload_0
     407: getfield      #2                  // Field this$1:Lorg/apache/hadoop/hbase/util/HBaseFsck$TableInfo;
     410: getfield      #29                 // Field org/apache/hadoop/hbase/util/HBaseFsck$TableInfo.this$0:Lorg/apache/hadoop/hbase/util/HBaseFsck;
     413: dup
     414: getfield      #30                 // Field org/apache/hadoop/hbase/util/HBaseFsck.fixes:I
     417: iconst_1
     418: iadd
     419: putfield      #30                 // Field org/apache/hadoop/hbase/util/HBaseFsck.fixes:I
     422: goto          66
     425: return
    Exception table:
       from    to  target type
          88   128   131   Class java/io/IOException
          88   128   171   Class java/lang/InterruptedException
         208   251   254   Class java/io/IOException
}
