Compiled from "HBaseAdmin.java"
class org.apache.hadoop.hbase.client.HBaseAdmin$66 extends org.apache.hadoop.hbase.client.MasterCallable<java.lang.Void> {
  final java.lang.String val$snapshotName;

  final org.apache.hadoop.hbase.client.HBaseAdmin this$0;

  org.apache.hadoop.hbase.client.HBaseAdmin$66(org.apache.hadoop.hbase.client.HBaseAdmin, org.apache.hadoop.hbase.client.Connection, org.apache.hadoop.hbase.ipc.RpcControllerFactory, java.lang.String);
    Code:
       0: aload_0
       1: aload_1
       2: putfield      #1                  // Field this$0:Lorg/apache/hadoop/hbase/client/HBaseAdmin;
       5: aload_0
       6: aload         4
       8: putfield      #2                  // Field val$snapshotName:Ljava/lang/String;
      11: aload_0
      12: aload_2
      13: aload_3
      14: invokespecial #3                  // Method org/apache/hadoop/hbase/client/MasterCallable."<init>":(Lorg/apache/hadoop/hbase/client/Connection;Lorg/apache/hadoop/hbase/ipc/RpcControllerFactory;)V
      17: return

  protected java.lang.Void rpcCall() throws java.lang.Exception;
    Code:
       0: aload_0
       1: getfield      #4                  // Field master:Lorg/apache/hadoop/hbase/client/MasterKeepAliveConnection;
       4: aload_0
       5: invokevirtual #5                  // Method getRpcController:()Lorg/apache/hadoop/hbase/ipc/HBaseRpcController;
       8: invokestatic  #6                  // Method org/apache/hadoop/hbase/shaded/protobuf/generated/MasterProtos$DeleteSnapshotRequest.newBuilder:()Lorg/apache/hadoop/hbase/shaded/protobuf/generated/MasterProtos$DeleteSnapshotRequest$Builder;
      11: invokestatic  #7                  // Method org/apache/hadoop/hbase/shaded/protobuf/generated/SnapshotProtos$SnapshotDescription.newBuilder:()Lorg/apache/hadoop/hbase/shaded/protobuf/generated/SnapshotProtos$SnapshotDescription$Builder;
      14: aload_0
      15: getfield      #2                  // Field val$snapshotName:Ljava/lang/String;
      18: invokevirtual #8                  // Method org/apache/hadoop/hbase/shaded/protobuf/generated/SnapshotProtos$SnapshotDescription$Builder.setName:(Ljava/lang/String;)Lorg/apache/hadoop/hbase/shaded/protobuf/generated/SnapshotProtos$SnapshotDescription$Builder;
      21: invokevirtual #9                  // Method org/apache/hadoop/hbase/shaded/protobuf/generated/SnapshotProtos$SnapshotDescription$Builder.build:()Lorg/apache/hadoop/hbase/shaded/protobuf/generated/SnapshotProtos$SnapshotDescription;
      24: invokevirtual #10                 // Method org/apache/hadoop/hbase/shaded/protobuf/generated/MasterProtos$DeleteSnapshotRequest$Builder.setSnapshot:(Lorg/apache/hadoop/hbase/shaded/protobuf/generated/SnapshotProtos$SnapshotDescription;)Lorg/apache/hadoop/hbase/shaded/protobuf/generated/MasterProtos$DeleteSnapshotRequest$Builder;
      27: invokevirtual #11                 // Method org/apache/hadoop/hbase/shaded/protobuf/generated/MasterProtos$DeleteSnapshotRequest$Builder.build:()Lorg/apache/hadoop/hbase/shaded/protobuf/generated/MasterProtos$DeleteSnapshotRequest;
      30: invokeinterface #12,  3           // InterfaceMethod org/apache/hadoop/hbase/client/MasterKeepAliveConnection.deleteSnapshot:(Lorg/apache/hbase/thirdparty/com/google/protobuf/RpcController;Lorg/apache/hadoop/hbase/shaded/protobuf/generated/MasterProtos$DeleteSnapshotRequest;)Lorg/apache/hadoop/hbase/shaded/protobuf/generated/MasterProtos$DeleteSnapshotResponse;
      35: pop
      36: aconst_null
      37: areturn

  protected java.lang.Object rpcCall() throws java.lang.Exception;
    Code:
       0: aload_0
       1: invokevirtual #13                 // Method rpcCall:()Ljava/lang/Void;
       4: areturn
}
