Compiled from "HBaseAdmin.java"
class org.apache.hadoop.hbase.client.HBaseAdmin$64 extends org.apache.hadoop.hbase.client.MasterCallable<org.apache.hadoop.hbase.shaded.protobuf.generated.MasterProtos$RestoreSnapshotResponse> {
  java.lang.Long nonceGroup;

  java.lang.Long nonce;

  final org.apache.hadoop.hbase.shaded.protobuf.generated.SnapshotProtos$SnapshotDescription val$snapshot;

  final boolean val$restoreAcl;

  final org.apache.hadoop.hbase.client.HBaseAdmin this$0;

  org.apache.hadoop.hbase.client.HBaseAdmin$64(org.apache.hadoop.hbase.client.HBaseAdmin, org.apache.hadoop.hbase.client.Connection, org.apache.hadoop.hbase.ipc.RpcControllerFactory, org.apache.hadoop.hbase.shaded.protobuf.generated.SnapshotProtos$SnapshotDescription, boolean);
    Code:
       0: aload_0
       1: aload_1
       2: putfield      #1                  // Field this$0:Lorg/apache/hadoop/hbase/client/HBaseAdmin;
       5: aload_0
       6: aload         4
       8: putfield      #2                  // Field val$snapshot:Lorg/apache/hadoop/hbase/shaded/protobuf/generated/SnapshotProtos$SnapshotDescription;
      11: aload_0
      12: iload         5
      14: putfield      #3                  // Field val$restoreAcl:Z
      17: aload_0
      18: aload_2
      19: aload_3
      20: invokespecial #4                  // Method org/apache/hadoop/hbase/client/MasterCallable."<init>":(Lorg/apache/hadoop/hbase/client/Connection;Lorg/apache/hadoop/hbase/ipc/RpcControllerFactory;)V
      23: aload_0
      24: aload_0
      25: getfield      #1                  // Field this$0:Lorg/apache/hadoop/hbase/client/HBaseAdmin;
      28: invokestatic  #5                  // Method org/apache/hadoop/hbase/client/HBaseAdmin.access$000:(Lorg/apache/hadoop/hbase/client/HBaseAdmin;)Lorg/apache/hadoop/hbase/client/NonceGenerator;
      31: invokeinterface #6,  1            // InterfaceMethod org/apache/hadoop/hbase/client/NonceGenerator.getNonceGroup:()J
      36: invokestatic  #7                  // Method java/lang/Long.valueOf:(J)Ljava/lang/Long;
      39: putfield      #8                  // Field nonceGroup:Ljava/lang/Long;
      42: aload_0
      43: aload_0
      44: getfield      #1                  // Field this$0:Lorg/apache/hadoop/hbase/client/HBaseAdmin;
      47: invokestatic  #5                  // Method org/apache/hadoop/hbase/client/HBaseAdmin.access$000:(Lorg/apache/hadoop/hbase/client/HBaseAdmin;)Lorg/apache/hadoop/hbase/client/NonceGenerator;
      50: invokeinterface #9,  1            // InterfaceMethod org/apache/hadoop/hbase/client/NonceGenerator.newNonce:()J
      55: invokestatic  #7                  // Method java/lang/Long.valueOf:(J)Ljava/lang/Long;
      58: putfield      #10                 // Field nonce:Ljava/lang/Long;
      61: return

  protected org.apache.hadoop.hbase.shaded.protobuf.generated.MasterProtos$RestoreSnapshotResponse rpcCall() throws java.lang.Exception;
    Code:
       0: invokestatic  #11                 // Method org/apache/hadoop/hbase/shaded/protobuf/generated/MasterProtos$RestoreSnapshotRequest.newBuilder:()Lorg/apache/hadoop/hbase/shaded/protobuf/generated/MasterProtos$RestoreSnapshotRequest$Builder;
       3: aload_0
       4: getfield      #2                  // Field val$snapshot:Lorg/apache/hadoop/hbase/shaded/protobuf/generated/SnapshotProtos$SnapshotDescription;
       7: invokevirtual #12                 // Method org/apache/hadoop/hbase/shaded/protobuf/generated/MasterProtos$RestoreSnapshotRequest$Builder.setSnapshot:(Lorg/apache/hadoop/hbase/shaded/protobuf/generated/SnapshotProtos$SnapshotDescription;)Lorg/apache/hadoop/hbase/shaded/protobuf/generated/MasterProtos$RestoreSnapshotRequest$Builder;
      10: aload_0
      11: getfield      #8                  // Field nonceGroup:Ljava/lang/Long;
      14: invokevirtual #13                 // Method java/lang/Long.longValue:()J
      17: invokevirtual #14                 // Method org/apache/hadoop/hbase/shaded/protobuf/generated/MasterProtos$RestoreSnapshotRequest$Builder.setNonceGroup:(J)Lorg/apache/hadoop/hbase/shaded/protobuf/generated/MasterProtos$RestoreSnapshotRequest$Builder;
      20: aload_0
      21: getfield      #10                 // Field nonce:Ljava/lang/Long;
      24: invokevirtual #13                 // Method java/lang/Long.longValue:()J
      27: invokevirtual #15                 // Method org/apache/hadoop/hbase/shaded/protobuf/generated/MasterProtos$RestoreSnapshotRequest$Builder.setNonce:(J)Lorg/apache/hadoop/hbase/shaded/protobuf/generated/MasterProtos$RestoreSnapshotRequest$Builder;
      30: aload_0
      31: getfield      #3                  // Field val$restoreAcl:Z
      34: invokevirtual #16                 // Method org/apache/hadoop/hbase/shaded/protobuf/generated/MasterProtos$RestoreSnapshotRequest$Builder.setRestoreACL:(Z)Lorg/apache/hadoop/hbase/shaded/protobuf/generated/MasterProtos$RestoreSnapshotRequest$Builder;
      37: invokevirtual #17                 // Method org/apache/hadoop/hbase/shaded/protobuf/generated/MasterProtos$RestoreSnapshotRequest$Builder.build:()Lorg/apache/hadoop/hbase/shaded/protobuf/generated/MasterProtos$RestoreSnapshotRequest;
      40: astore_1
      41: aload_0
      42: getfield      #18                 // Field master:Lorg/apache/hadoop/hbase/client/MasterKeepAliveConnection;
      45: aload_0
      46: invokevirtual #19                 // Method getRpcController:()Lorg/apache/hadoop/hbase/ipc/HBaseRpcController;
      49: aload_1
      50: invokeinterface #20,  3           // InterfaceMethod org/apache/hadoop/hbase/client/MasterKeepAliveConnection.restoreSnapshot:(Lorg/apache/hbase/thirdparty/com/google/protobuf/RpcController;Lorg/apache/hadoop/hbase/shaded/protobuf/generated/MasterProtos$RestoreSnapshotRequest;)Lorg/apache/hadoop/hbase/shaded/protobuf/generated/MasterProtos$RestoreSnapshotResponse;
      55: areturn

  protected java.lang.Object rpcCall() throws java.lang.Exception;
    Code:
       0: aload_0
       1: invokevirtual #21                 // Method rpcCall:()Lorg/apache/hadoop/hbase/shaded/protobuf/generated/MasterProtos$RestoreSnapshotResponse;
       4: areturn
}
