Compiled from "HBaseInterClusterReplicationEndpoint.java"
public class org.apache.hadoop.hbase.replication.regionserver.HBaseInterClusterReplicationEndpoint extends org.apache.hadoop.hbase.replication.HBaseReplicationEndpoint {
  public org.apache.hadoop.hbase.replication.regionserver.HBaseInterClusterReplicationEndpoint();
    Code:
       0: aload_0
       1: invokespecial #1                  // Method org/apache/hadoop/hbase/replication/HBaseReplicationEndpoint."<init>":()V
       4: aload_0
       5: iconst_0
       6: putfield      #2                  // Field peersSelected:Z
       9: aload_0
      10: ldc           #3                  // String
      12: putfield      #4                  // Field replicationClusterId:Ljava/lang/String;
      15: aload_0
      16: iconst_0
      17: putfield      #5                  // Field isSerial:Z
      20: return

  public void init(org.apache.hadoop.hbase.replication.ReplicationEndpoint$Context) throws java.io.IOException;
    Code:
       0: aload_0
       1: aload_1
       2: invokespecial #6                  // Method org/apache/hadoop/hbase/replication/HBaseReplicationEndpoint.init:(Lorg/apache/hadoop/hbase/replication/ReplicationEndpoint$Context;)V
       5: aload_0
       6: aload_0
       7: getfield      #7                  // Field ctx:Lorg/apache/hadoop/hbase/replication/ReplicationEndpoint$Context;
      10: invokevirtual #8                  // Method org/apache/hadoop/hbase/replication/ReplicationEndpoint$Context.getConfiguration:()Lorg/apache/hadoop/conf/Configuration;
      13: invokestatic  #9                  // Method org/apache/hadoop/hbase/HBaseConfiguration.create:(Lorg/apache/hadoop/conf/Configuration;)Lorg/apache/hadoop/conf/Configuration;
      16: putfield      #10                 // Field conf:Lorg/apache/hadoop/conf/Configuration;
      19: aload_0
      20: aload_0
      21: getfield      #7                  // Field ctx:Lorg/apache/hadoop/hbase/replication/ReplicationEndpoint$Context;
      24: invokevirtual #11                 // Method org/apache/hadoop/hbase/replication/ReplicationEndpoint$Context.getLocalConfiguration:()Lorg/apache/hadoop/conf/Configuration;
      27: invokestatic  #9                  // Method org/apache/hadoop/hbase/HBaseConfiguration.create:(Lorg/apache/hadoop/conf/Configuration;)Lorg/apache/hadoop/conf/Configuration;
      30: putfield      #12                 // Field localConf:Lorg/apache/hadoop/conf/Configuration;
      33: aload_0
      34: invokespecial #13                 // Method decorateConf:()V
      37: aload_0
      38: aload_0
      39: getfield      #10                 // Field conf:Lorg/apache/hadoop/conf/Configuration;
      42: ldc           #14                 // String replication.source.maxretriesmultiplier
      44: sipush        300
      47: invokevirtual #15                 // Method org/apache/hadoop/conf/Configuration.getInt:(Ljava/lang/String;I)I
      50: putfield      #16                 // Field maxRetriesMultiplier:I
      53: aload_0
      54: aload_0
      55: getfield      #10                 // Field conf:Lorg/apache/hadoop/conf/Configuration;
      58: ldc           #17                 // String replication.source.socketTimeoutMultiplier
      60: aload_0
      61: getfield      #16                 // Field maxRetriesMultiplier:I
      64: invokevirtual #15                 // Method org/apache/hadoop/conf/Configuration.getInt:(Ljava/lang/String;I)I
      67: putfield      #18                 // Field socketTimeoutMultiplier:I
      70: aload_0
      71: getfield      #10                 // Field conf:Lorg/apache/hadoop/conf/Configuration;
      74: ldc           #19                 // String replication.source.maxterminationmultiplier
      76: ldc2_w        #21                 // long 2l
      79: invokevirtual #23                 // Method org/apache/hadoop/conf/Configuration.getLong:(Ljava/lang/String;J)J
      82: lstore_2
      83: aload_0
      84: lload_2
      85: aload_0
      86: getfield      #10                 // Field conf:Lorg/apache/hadoop/conf/Configuration;
      89: ldc           #25                 // String hbase.rpc.timeout
      91: ldc2_w        #26                 // long 60000l
      94: invokevirtual #23                 // Method org/apache/hadoop/conf/Configuration.getLong:(Ljava/lang/String;J)J
      97: lmul
      98: putfield      #28                 // Field maxTerminationWait:J
     101: aload_0
     102: aload_0
     103: getfield      #10                 // Field conf:Lorg/apache/hadoop/conf/Configuration;
     106: invokestatic  #29                 // Method org/apache/hadoop/hbase/client/ConnectionFactory.createConnection:(Lorg/apache/hadoop/conf/Configuration;)Lorg/apache/hadoop/hbase/client/Connection;
     109: checkcast     #30                 // class org/apache/hadoop/hbase/client/ClusterConnection
     112: putfield      #31                 // Field conn:Lorg/apache/hadoop/hbase/client/ClusterConnection;
     115: aload_0
     116: aload_0
     117: getfield      #10                 // Field conf:Lorg/apache/hadoop/conf/Configuration;
     120: ldc           #32                 // String replication.source.sleepforretries
     122: ldc2_w        #33                 // long 1000l
     125: invokevirtual #23                 // Method org/apache/hadoop/conf/Configuration.getLong:(Ljava/lang/String;J)J
     128: putfield      #35                 // Field sleepForRetries:J
     131: aload_0
     132: aload_1
     133: invokevirtual #36                 // Method org/apache/hadoop/hbase/replication/ReplicationEndpoint$Context.getMetrics:()Lorg/apache/hadoop/hbase/replication/regionserver/MetricsSource;
     136: putfield      #37                 // Field metrics:Lorg/apache/hadoop/hbase/replication/regionserver/MetricsSource;
     139: aload_0
     140: new           #38                 // class org/apache/hadoop/hbase/replication/regionserver/ReplicationSinkManager
     143: dup
     144: aload_0
     145: getfield      #31                 // Field conn:Lorg/apache/hadoop/hbase/client/ClusterConnection;
     148: aload_0
     149: getfield      #7                  // Field ctx:Lorg/apache/hadoop/hbase/replication/ReplicationEndpoint$Context;
     152: invokevirtual #39                 // Method org/apache/hadoop/hbase/replication/ReplicationEndpoint$Context.getPeerId:()Ljava/lang/String;
     155: aload_0
     156: aload_0
     157: getfield      #10                 // Field conf:Lorg/apache/hadoop/conf/Configuration;
     160: invokespecial #40                 // Method org/apache/hadoop/hbase/replication/regionserver/ReplicationSinkManager."<init>":(Lorg/apache/hadoop/hbase/client/ClusterConnection;Ljava/lang/String;Lorg/apache/hadoop/hbase/replication/HBaseReplicationEndpoint;Lorg/apache/hadoop/conf/Configuration;)V
     163: putfield      #41                 // Field replicationSinkMgr:Lorg/apache/hadoop/hbase/replication/regionserver/ReplicationSinkManager;
     166: aload_0
     167: aload_0
     168: getfield      #10                 // Field conf:Lorg/apache/hadoop/conf/Configuration;
     171: ldc           #42                 // String hbase.replication.source.maxthreads
     173: bipush        10
     175: invokevirtual #15                 // Method org/apache/hadoop/conf/Configuration.getInt:(Ljava/lang/String;I)I
     178: putfield      #43                 // Field maxThreads:I
     181: aload_0
     182: new           #44                 // class java/util/concurrent/ThreadPoolExecutor
     185: dup
     186: aload_0
     187: getfield      #43                 // Field maxThreads:I
     190: aload_0
     191: getfield      #43                 // Field maxThreads:I
     194: ldc2_w        #45                 // long 60l
     197: getstatic     #47                 // Field java/util/concurrent/TimeUnit.SECONDS:Ljava/util/concurrent/TimeUnit;
     200: new           #48                 // class java/util/concurrent/LinkedBlockingQueue
     203: dup
     204: invokespecial #49                 // Method java/util/concurrent/LinkedBlockingQueue."<init>":()V
     207: invokespecial #50                 // Method java/util/concurrent/ThreadPoolExecutor."<init>":(IIJLjava/util/concurrent/TimeUnit;Ljava/util/concurrent/BlockingQueue;)V
     210: putfield      #51                 // Field exec:Ljava/util/concurrent/ThreadPoolExecutor;
     213: aload_0
     214: getfield      #51                 // Field exec:Ljava/util/concurrent/ThreadPoolExecutor;
     217: iconst_1
     218: invokevirtual #52                 // Method java/util/concurrent/ThreadPoolExecutor.allowCoreThreadTimeOut:(Z)V
     221: aload_0
     222: aload_0
     223: getfield      #7                  // Field ctx:Lorg/apache/hadoop/hbase/replication/ReplicationEndpoint$Context;
     226: invokevirtual #53                 // Method org/apache/hadoop/hbase/replication/ReplicationEndpoint$Context.getAbortable:()Lorg/apache/hadoop/hbase/Abortable;
     229: putfield      #54                 // Field abortable:Lorg/apache/hadoop/hbase/Abortable;
     232: aload_0
     233: ldc2_w        #55                 // double 0.95d
     236: aload_0
     237: getfield      #10                 // Field conf:Lorg/apache/hadoop/conf/Configuration;
     240: ldc           #58                 // String hbase.ipc.max.request.size
     242: ldc2_w        #59                 // long 268435456l
     245: invokevirtual #23                 // Method org/apache/hadoop/conf/Configuration.getLong:(Ljava/lang/String;J)J
     248: l2d
     249: dmul
     250: d2i
     251: putfield      #61                 // Field replicationRpcLimit:I
     254: aload_0
     255: aload_0
     256: getfield      #10                 // Field conf:Lorg/apache/hadoop/conf/Configuration;
     259: ldc           #62                 // String hbase.replication.drop.on.deleted.table
     261: iconst_0
     262: invokevirtual #63                 // Method org/apache/hadoop/conf/Configuration.getBoolean:(Ljava/lang/String;Z)Z
     265: putfield      #64                 // Field dropOnDeletedTables:Z
     268: aload_0
     269: aload_0
     270: getfield      #10                 // Field conf:Lorg/apache/hadoop/conf/Configuration;
     273: ldc           #65                 // String hbase.replication.bulkload.enabled
     275: iconst_0
     276: invokevirtual #63                 // Method org/apache/hadoop/conf/Configuration.getBoolean:(Ljava/lang/String;Z)Z
     279: putfield      #66                 // Field replicationBulkLoadDataEnabled:Z
     282: aload_0
     283: getfield      #66                 // Field replicationBulkLoadDataEnabled:Z
     286: ifeq          302
     289: aload_0
     290: aload_0
     291: getfield      #10                 // Field conf:Lorg/apache/hadoop/conf/Configuration;
     294: ldc           #67                 // String hbase.replication.cluster.id
     296: invokevirtual #68                 // Method org/apache/hadoop/conf/Configuration.get:(Ljava/lang/String;)Ljava/lang/String;
     299: putfield      #4                  // Field replicationClusterId:Ljava/lang/String;
     302: aload_0
     303: getfield      #10                 // Field conf:Lorg/apache/hadoop/conf/Configuration;
     306: invokestatic  #69                 // Method org/apache/hadoop/hbase/util/FSUtils.getRootDir:(Lorg/apache/hadoop/conf/Configuration;)Lorg/apache/hadoop/fs/Path;
     309: astore        4
     311: new           #70                 // class org/apache/hadoop/fs/Path
     314: dup
     315: ldc           #71                 // String data
     317: invokespecial #72                 // Method org/apache/hadoop/fs/Path."<init>":(Ljava/lang/String;)V
     320: astore        5
     322: aload_0
     323: new           #70                 // class org/apache/hadoop/fs/Path
     326: dup
     327: aload         4
     329: aload         5
     331: invokespecial #73                 // Method org/apache/hadoop/fs/Path."<init>":(Lorg/apache/hadoop/fs/Path;Lorg/apache/hadoop/fs/Path;)V
     334: putfield      #74                 // Field baseNamespaceDir:Lorg/apache/hadoop/fs/Path;
     337: aload_0
     338: new           #70                 // class org/apache/hadoop/fs/Path
     341: dup
     342: aload         4
     344: new           #70                 // class org/apache/hadoop/fs/Path
     347: dup
     348: ldc           #75                 // String archive
     350: aload         5
     352: invokespecial #76                 // Method org/apache/hadoop/fs/Path."<init>":(Ljava/lang/String;Lorg/apache/hadoop/fs/Path;)V
     355: invokespecial #73                 // Method org/apache/hadoop/fs/Path."<init>":(Lorg/apache/hadoop/fs/Path;Lorg/apache/hadoop/fs/Path;)V
     358: putfield      #77                 // Field hfileArchiveDir:Lorg/apache/hadoop/fs/Path;
     361: aload_0
     362: aload_1
     363: invokevirtual #78                 // Method org/apache/hadoop/hbase/replication/ReplicationEndpoint$Context.getPeerConfig:()Lorg/apache/hadoop/hbase/replication/ReplicationPeerConfig;
     366: invokevirtual #79                 // Method org/apache/hadoop/hbase/replication/ReplicationPeerConfig.isSerial:()Z
     369: putfield      #5                  // Field isSerial:Z
     372: return

  protected boolean sleepForRetries(java.lang.String, int);
    Code:
       0: getstatic     #90                 // Field LOG:Lorg/slf4j/Logger;
       3: invokeinterface #91,  1           // InterfaceMethod org/slf4j/Logger.isTraceEnabled:()Z
       8: ifeq          54
      11: getstatic     #90                 // Field LOG:Lorg/slf4j/Logger;
      14: new           #92                 // class java/lang/StringBuilder
      17: dup
      18: invokespecial #93                 // Method java/lang/StringBuilder."<init>":()V
      21: aload_1
      22: invokevirtual #94                 // Method java/lang/StringBuilder.append:(Ljava/lang/String;)Ljava/lang/StringBuilder;
      25: ldc           #95                 // String , sleeping
      27: invokevirtual #94                 // Method java/lang/StringBuilder.append:(Ljava/lang/String;)Ljava/lang/StringBuilder;
      30: aload_0
      31: getfield      #35                 // Field sleepForRetries:J
      34: invokevirtual #96                 // Method java/lang/StringBuilder.append:(J)Ljava/lang/StringBuilder;
      37: ldc           #97                 // String  times
      39: invokevirtual #94                 // Method java/lang/StringBuilder.append:(Ljava/lang/String;)Ljava/lang/StringBuilder;
      42: iload_2
      43: invokevirtual #98                 // Method java/lang/StringBuilder.append:(I)Ljava/lang/StringBuilder;
      46: invokevirtual #99                 // Method java/lang/StringBuilder.toString:()Ljava/lang/String;
      49: invokeinterface #100,  2          // InterfaceMethod org/slf4j/Logger.trace:(Ljava/lang/String;)V
      54: aload_0
      55: getfield      #35                 // Field sleepForRetries:J
      58: iload_2
      59: i2l
      60: lmul
      61: invokestatic  #101                // Method java/lang/Thread.sleep:(J)V
      64: goto          78
      67: astore_3
      68: getstatic     #90                 // Field LOG:Lorg/slf4j/Logger;
      71: ldc           #103                // String Interrupted while sleeping between retries
      73: invokeinterface #104,  2          // InterfaceMethod org/slf4j/Logger.debug:(Ljava/lang/String;)V
      78: iload_2
      79: aload_0
      80: getfield      #16                 // Field maxRetriesMultiplier:I
      83: if_icmpge     90
      86: iconst_1
      87: goto          91
      90: iconst_0
      91: ireturn
    Exception table:
       from    to  target type
           0    64    67   Class java/lang/InterruptedException

  public boolean replicate(org.apache.hadoop.hbase.replication.ReplicationEndpoint$ReplicateContext);
    Code:
       0: new           #172                // class java/util/concurrent/ExecutorCompletionService
       3: dup
       4: aload_0
       5: getfield      #51                 // Field exec:Ljava/util/concurrent/ThreadPoolExecutor;
       8: invokespecial #173                // Method java/util/concurrent/ExecutorCompletionService."<init>":(Ljava/util/concurrent/Executor;)V
      11: astore_2
      12: iconst_1
      13: istore_3
      14: aload_0
      15: getfield      #2                  // Field peersSelected:Z
      18: ifne          37
      21: aload_0
      22: invokevirtual #85                 // Method isRunning:()Z
      25: ifeq          37
      28: aload_0
      29: invokespecial #174                // Method connectToPeers:()V
      32: aload_0
      33: iconst_1
      34: putfield      #2                  // Field peersSelected:Z
      37: aload_0
      38: getfield      #41                 // Field replicationSinkMgr:Lorg/apache/hadoop/hbase/replication/regionserver/ReplicationSinkManager;
      41: invokevirtual #86                 // Method org/apache/hadoop/hbase/replication/regionserver/ReplicationSinkManager.getNumSinks:()I
      44: istore        4
      46: iload         4
      48: ifne          63
      51: getstatic     #90                 // Field LOG:Lorg/slf4j/Logger;
      54: ldc           #175                // String No replication sinks found, returning without replicating. The source should retry with the same set of edits.
      56: invokeinterface #176,  2          // InterfaceMethod org/slf4j/Logger.warn:(Ljava/lang/String;)V
      61: iconst_0
      62: ireturn
      63: aload_0
      64: aload_1
      65: invokevirtual #177                // Method org/apache/hadoop/hbase/replication/ReplicationEndpoint$ReplicateContext.getEntries:()Ljava/util/List;
      68: invokespecial #178                // Method createBatches:(Ljava/util/List;)Ljava/util/List;
      71: astore        5
      73: aload_0
      74: invokevirtual #85                 // Method isRunning:()Z
      77: ifeq          552
      80: aload_0
      81: getfield      #51                 // Field exec:Ljava/util/concurrent/ThreadPoolExecutor;
      84: invokevirtual #179                // Method java/util/concurrent/ThreadPoolExecutor.isShutdown:()Z
      87: ifne          552
      90: aload_0
      91: invokevirtual #180                // Method isPeerEnabled:()Z
      94: ifne          113
      97: aload_0
      98: ldc           #181                // String Replication is disabled
     100: iload_3
     101: invokevirtual #89                 // Method sleepForRetries:(Ljava/lang/String;I)Z
     104: ifeq          73
     107: iinc          3, 1
     110: goto          73
     113: aload_0
     114: getfield      #31                 // Field conn:Lorg/apache/hadoop/hbase/client/ClusterConnection;
     117: ifnull        132
     120: aload_0
     121: getfield      #31                 // Field conn:Lorg/apache/hadoop/hbase/client/ClusterConnection;
     124: invokeinterface #182,  1          // InterfaceMethod org/apache/hadoop/hbase/client/ClusterConnection.isClosed:()Z
     129: ifeq          136
     132: aload_0
     133: invokespecial #183                // Method reconnectToPeerCluster:()V
     136: aload_0
     137: aload_2
     138: aload_1
     139: aload         5
     141: invokespecial #184                // Method parallelReplicate:(Ljava/util/concurrent/CompletionService;Lorg/apache/hadoop/hbase/replication/ReplicationEndpoint$ReplicateContext;Ljava/util/List;)J
     144: pop2
     145: iconst_1
     146: ireturn
     147: astore        6
     149: aload         6
     151: instanceof    #185                // class org/apache/hadoop/ipc/RemoteException
     154: ifeq          464
     157: aload         6
     159: checkcast     #185                // class org/apache/hadoop/ipc/RemoteException
     162: invokevirtual #186                // Method org/apache/hadoop/ipc/RemoteException.unwrapRemoteException:()Ljava/io/IOException;
     165: astore        6
     167: getstatic     #90                 // Field LOG:Lorg/slf4j/Logger;
     170: ldc           #187                // String Can't replicate because of an error on the remote cluster:
     172: aload         6
     174: invokeinterface #155,  3          // InterfaceMethod org/slf4j/Logger.warn:(Ljava/lang/String;Ljava/lang/Throwable;)V
     179: aload         6
     181: instanceof    #188                // class org/apache/hadoop/hbase/TableNotFoundException
     184: ifeq          442
     187: aload_0
     188: getfield      #64                 // Field dropOnDeletedTables:Z
     191: ifeq          536
     194: aload_0
     195: aload         6
     197: invokevirtual #189                // Method java/io/IOException.getMessage:()Ljava/lang/String;
     200: invokespecial #190                // Method parseTable:(Ljava/lang/String;)Lorg/apache/hadoop/hbase/TableName;
     203: astore        7
     205: aload         7
     207: ifnull        439
     210: aload_0
     211: getfield      #7                  // Field ctx:Lorg/apache/hadoop/hbase/replication/ReplicationEndpoint$Context;
     214: invokevirtual #11                 // Method org/apache/hadoop/hbase/replication/ReplicationEndpoint$Context.getLocalConfiguration:()Lorg/apache/hadoop/conf/Configuration;
     217: invokestatic  #29                 // Method org/apache/hadoop/hbase/client/ConnectionFactory.createConnection:(Lorg/apache/hadoop/conf/Configuration;)Lorg/apache/hadoop/hbase/client/Connection;
     220: astore        8
     222: aconst_null
     223: astore        9
     225: aload         8
     227: invokeinterface #191,  1          // InterfaceMethod org/apache/hadoop/hbase/client/Connection.getAdmin:()Lorg/apache/hadoop/hbase/client/Admin;
     232: aload         7
     234: invokeinterface #192,  2          // InterfaceMethod org/apache/hadoop/hbase/client/Admin.tableExists:(Lorg/apache/hadoop/hbase/TableName;)Z
     239: ifne          327
     242: getstatic     #90                 // Field LOG:Lorg/slf4j/Logger;
     245: new           #92                 // class java/lang/StringBuilder
     248: dup
     249: invokespecial #93                 // Method java/lang/StringBuilder."<init>":()V
     252: ldc           #193                // String Missing table detected at sink, local table also does not exist, filtering edits for '
     254: invokevirtual #94                 // Method java/lang/StringBuilder.append:(Ljava/lang/String;)Ljava/lang/StringBuilder;
     257: aload         7
     259: invokevirtual #194                // Method java/lang/StringBuilder.append:(Ljava/lang/Object;)Ljava/lang/StringBuilder;
     262: ldc           #195                // String '
     264: invokevirtual #94                 // Method java/lang/StringBuilder.append:(Ljava/lang/String;)Ljava/lang/StringBuilder;
     267: invokevirtual #99                 // Method java/lang/StringBuilder.toString:()Ljava/lang/String;
     270: invokeinterface #196,  2          // InterfaceMethod org/slf4j/Logger.info:(Ljava/lang/String;)V
     275: aload_0
     276: aload         5
     278: aload         7
     280: invokespecial #197                // Method filterBatches:(Ljava/util/List;Lorg/apache/hadoop/hbase/TableName;)Ljava/util/List;
     283: astore        5
     285: aload         8
     287: ifnull        324
     290: aload         9
     292: ifnull        317
     295: aload         8
     297: invokeinterface #198,  1          // InterfaceMethod org/apache/hadoop/hbase/client/Connection.close:()V
     302: goto          324
     305: astore        10
     307: aload         9
     309: aload         10
     311: invokevirtual #200                // Method java/lang/Throwable.addSuppressed:(Ljava/lang/Throwable;)V
     314: goto          324
     317: aload         8
     319: invokeinterface #198,  1          // InterfaceMethod org/apache/hadoop/hbase/client/Connection.close:()V
     324: goto          73
     327: aload         8
     329: ifnull        422
     332: aload         9
     334: ifnull        359
     337: aload         8
     339: invokeinterface #198,  1          // InterfaceMethod org/apache/hadoop/hbase/client/Connection.close:()V
     344: goto          422
     347: astore        10
     349: aload         9
     351: aload         10
     353: invokevirtual #200                // Method java/lang/Throwable.addSuppressed:(Ljava/lang/Throwable;)V
     356: goto          422
     359: aload         8
     361: invokeinterface #198,  1          // InterfaceMethod org/apache/hadoop/hbase/client/Connection.close:()V
     366: goto          422
     369: astore        10
     371: aload         10
     373: astore        9
     375: aload         10
     377: athrow
     378: astore        11
     380: aload         8
     382: ifnull        419
     385: aload         9
     387: ifnull        412
     390: aload         8
     392: invokeinterface #198,  1          // InterfaceMethod org/apache/hadoop/hbase/client/Connection.close:()V
     397: goto          419
     400: astore        12
     402: aload         9
     404: aload         12
     406: invokevirtual #200                // Method java/lang/Throwable.addSuppressed:(Ljava/lang/Throwable;)V
     409: goto          419
     412: aload         8
     414: invokeinterface #198,  1          // InterfaceMethod org/apache/hadoop/hbase/client/Connection.close:()V
     419: aload         11
     421: athrow
     422: goto          439
     425: astore        8
     427: getstatic     #90                 // Field LOG:Lorg/slf4j/Logger;
     430: ldc           #201                // String Exception checking for local table:
     432: aload         8
     434: invokeinterface #155,  3          // InterfaceMethod org/slf4j/Logger.warn:(Ljava/lang/String;Ljava/lang/Throwable;)V
     439: goto          536
     442: getstatic     #90                 // Field LOG:Lorg/slf4j/Logger;
     445: ldc           #202                // String Peer encountered RemoteException, rechecking all sinks:
     447: aload         6
     449: invokeinterface #155,  3          // InterfaceMethod org/slf4j/Logger.warn:(Ljava/lang/String;Ljava/lang/Throwable;)V
     454: aload_0
     455: getfield      #41                 // Field replicationSinkMgr:Lorg/apache/hadoop/hbase/replication/regionserver/ReplicationSinkManager;
     458: invokevirtual #87                 // Method org/apache/hadoop/hbase/replication/regionserver/ReplicationSinkManager.chooseSinks:()V
     461: goto          536
     464: aload         6
     466: instanceof    #203                // class java/net/SocketTimeoutException
     469: ifeq          486
     472: aload_0
     473: ldc           #204                // String Encountered a SocketTimeoutException. Since the call to the remote cluster timed out, which is usually caused by a machine failure or a massive slowdown
     475: aload_0
     476: getfield      #18                 // Field socketTimeoutMultiplier:I
     479: invokevirtual #89                 // Method sleepForRetries:(Ljava/lang/String;I)Z
     482: pop
     483: goto          536
     486: aload         6
     488: instanceof    #205                // class java/net/ConnectException
     491: ifne          502
     494: aload         6
     496: instanceof    #206                // class java/net/UnknownHostException
     499: ifeq          524
     502: getstatic     #90                 // Field LOG:Lorg/slf4j/Logger;
     505: ldc           #207                // String Peer is unavailable, rechecking all sinks:
     507: aload         6
     509: invokeinterface #155,  3          // InterfaceMethod org/slf4j/Logger.warn:(Ljava/lang/String;Ljava/lang/Throwable;)V
     514: aload_0
     515: getfield      #41                 // Field replicationSinkMgr:Lorg/apache/hadoop/hbase/replication/regionserver/ReplicationSinkManager;
     518: invokevirtual #87                 // Method org/apache/hadoop/hbase/replication/regionserver/ReplicationSinkManager.chooseSinks:()V
     521: goto          536
     524: getstatic     #90                 // Field LOG:Lorg/slf4j/Logger;
     527: ldc           #208                // String Can't replicate because of a local or network error:
     529: aload         6
     531: invokeinterface #155,  3          // InterfaceMethod org/slf4j/Logger.warn:(Ljava/lang/String;Ljava/lang/Throwable;)V
     536: aload_0
     537: ldc           #209                // String Since we are unable to replicate
     539: iload_3
     540: invokevirtual #89                 // Method sleepForRetries:(Ljava/lang/String;I)Z
     543: ifeq          549
     546: iinc          3, 1
     549: goto          73
     552: iconst_0
     553: ireturn
    Exception table:
       from    to  target type
         136   146   147   Class java/io/IOException
         295   302   305   Class java/lang/Throwable
         337   344   347   Class java/lang/Throwable
         225   285   369   Class java/lang/Throwable
         225   285   378   any
         390   397   400   Class java/lang/Throwable
         369   380   378   any
         210   324   425   Class java/io/IOException
         327   422   425   Class java/io/IOException

  protected boolean isPeerEnabled();
    Code:
       0: aload_0
       1: getfield      #7                  // Field ctx:Lorg/apache/hadoop/hbase/replication/ReplicationEndpoint$Context;
       4: invokevirtual #210                // Method org/apache/hadoop/hbase/replication/ReplicationEndpoint$Context.getReplicationPeer:()Lorg/apache/hadoop/hbase/replication/ReplicationPeer;
       7: invokeinterface #211,  1          // InterfaceMethod org/apache/hadoop/hbase/replication/ReplicationPeer.isPeerEnabled:()Z
      12: ireturn

  protected void doStop();
    Code:
       0: aload_0
       1: invokevirtual #212                // Method disconnect:()V
       4: aload_0
       5: getfield      #31                 // Field conn:Lorg/apache/hadoop/hbase/client/ClusterConnection;
       8: ifnull        39
      11: aload_0
      12: getfield      #31                 // Field conn:Lorg/apache/hadoop/hbase/client/ClusterConnection;
      15: invokeinterface #213,  1          // InterfaceMethod org/apache/hadoop/hbase/client/ClusterConnection.close:()V
      20: aload_0
      21: aconst_null
      22: putfield      #31                 // Field conn:Lorg/apache/hadoop/hbase/client/ClusterConnection;
      25: goto          39
      28: astore_1
      29: getstatic     #90                 // Field LOG:Lorg/slf4j/Logger;
      32: ldc           #214                // String Failed to close the connection
      34: invokeinterface #176,  2          // InterfaceMethod org/slf4j/Logger.warn:(Ljava/lang/String;)V
      39: aload_0
      40: getfield      #51                 // Field exec:Ljava/util/concurrent/ThreadPoolExecutor;
      43: invokevirtual #215                // Method java/util/concurrent/ThreadPoolExecutor.shutdown:()V
      46: aload_0
      47: getfield      #51                 // Field exec:Ljava/util/concurrent/ThreadPoolExecutor;
      50: aload_0
      51: getfield      #28                 // Field maxTerminationWait:J
      54: getstatic     #216                // Field java/util/concurrent/TimeUnit.MILLISECONDS:Ljava/util/concurrent/TimeUnit;
      57: invokevirtual #217                // Method java/util/concurrent/ThreadPoolExecutor.awaitTermination:(JLjava/util/concurrent/TimeUnit;)Z
      60: pop
      61: goto          65
      64: astore_1
      65: aload_0
      66: getfield      #51                 // Field exec:Ljava/util/concurrent/ThreadPoolExecutor;
      69: invokevirtual #218                // Method java/util/concurrent/ThreadPoolExecutor.isTerminated:()Z
      72: ifne          121
      75: new           #92                 // class java/lang/StringBuilder
      78: dup
      79: invokespecial #93                 // Method java/lang/StringBuilder."<init>":()V
      82: ldc           #219                // String HBaseInterClusterReplicationEndpoint termination failed. The ThreadPoolExecutor failed to finish all tasks within
      84: invokevirtual #94                 // Method java/lang/StringBuilder.append:(Ljava/lang/String;)Ljava/lang/StringBuilder;
      87: aload_0
      88: getfield      #28                 // Field maxTerminationWait:J
      91: invokevirtual #96                 // Method java/lang/StringBuilder.append:(J)Ljava/lang/StringBuilder;
      94: ldc           #220                // String ms. Aborting to prevent Replication from deadlocking. See HBASE-16081.
      96: invokevirtual #94                 // Method java/lang/StringBuilder.append:(Ljava/lang/String;)Ljava/lang/StringBuilder;
      99: invokevirtual #99                 // Method java/lang/StringBuilder.toString:()Ljava/lang/String;
     102: astore_1
     103: aload_0
     104: getfield      #54                 // Field abortable:Lorg/apache/hadoop/hbase/Abortable;
     107: aload_1
     108: new           #153                // class java/io/IOException
     111: dup
     112: aload_1
     113: invokespecial #221                // Method java/io/IOException."<init>":(Ljava/lang/String;)V
     116: invokeinterface #222,  3          // InterfaceMethod org/apache/hadoop/hbase/Abortable.abort:(Ljava/lang/String;Ljava/lang/Throwable;)V
     121: aload_0
     122: invokevirtual #223                // Method notifyStopped:()V
     125: return
    Exception table:
       from    to  target type
          11    25    28   Class java/io/IOException
          46    61    64   Class java/lang/InterruptedException

  protected int replicateEntries(java.util.List<org.apache.hadoop.hbase.wal.WAL$Entry>, int) throws java.io.IOException;
    Code:
       0: aconst_null
       1: astore_3
       2: aload_1
       3: invokestatic  #224                // Method java/lang/System.identityHashCode:(Ljava/lang/Object;)I
       6: istore        4
       8: getstatic     #90                 // Field LOG:Lorg/slf4j/Logger;
      11: invokeinterface #91,  1           // InterfaceMethod org/slf4j/Logger.isTraceEnabled:()Z
      16: ifeq          92
      19: aload_1
      20: invokeinterface #150,  1          // InterfaceMethod java/util/List.stream:()Ljava/util/stream/Stream;
      25: aload_0
      26: invokedynamic #225,  0            // InvokeDynamic #3:applyAsLong:(Lorg/apache/hadoop/hbase/replication/regionserver/HBaseInterClusterReplicationEndpoint;)Ljava/util/function/ToLongFunction;
      31: invokeinterface #226,  2          // InterfaceMethod java/util/stream/Stream.mapToLong:(Ljava/util/function/ToLongFunction;)Ljava/util/stream/LongStream;
      36: invokeinterface #227,  1          // InterfaceMethod java/util/stream/LongStream.sum:()J
      41: lstore        5
      43: getstatic     #90                 // Field LOG:Lorg/slf4j/Logger;
      46: ldc           #228                // String Replicating batch {} of {} entries with total size {} bytes to {}
      48: iconst_4
      49: anewarray     #229                // class java/lang/Object
      52: dup
      53: iconst_0
      54: iload         4
      56: invokestatic  #158                // Method java/lang/Integer.valueOf:(I)Ljava/lang/Integer;
      59: aastore
      60: dup
      61: iconst_1
      62: aload_1
      63: invokeinterface #110,  1          // InterfaceMethod java/util/List.size:()I
      68: invokestatic  #158                // Method java/lang/Integer.valueOf:(I)Ljava/lang/Integer;
      71: aastore
      72: dup
      73: iconst_2
      74: lload         5
      76: invokestatic  #230                // Method java/lang/Long.valueOf:(J)Ljava/lang/Long;
      79: aastore
      80: dup
      81: iconst_3
      82: aload_0
      83: getfield      #4                  // Field replicationClusterId:Ljava/lang/String;
      86: aastore
      87: invokeinterface #231,  3          // InterfaceMethod org/slf4j/Logger.trace:(Ljava/lang/String;[Ljava/lang/Object;)V
      92: aload_0
      93: getfield      #41                 // Field replicationSinkMgr:Lorg/apache/hadoop/hbase/replication/regionserver/ReplicationSinkManager;
      96: invokevirtual #232                // Method org/apache/hadoop/hbase/replication/regionserver/ReplicationSinkManager.getReplicationSink:()Lorg/apache/hadoop/hbase/replication/regionserver/ReplicationSinkManager$SinkPeer;
      99: astore_3
     100: aload_3
     101: invokevirtual #233                // Method org/apache/hadoop/hbase/replication/regionserver/ReplicationSinkManager$SinkPeer.getRegionServer:()Lorg/apache/hadoop/hbase/shaded/protobuf/generated/AdminProtos$AdminService$BlockingInterface;
     104: astore        5
     106: aload         5
     108: aload_1
     109: aload_1
     110: invokeinterface #110,  1          // InterfaceMethod java/util/List.size:()I
     115: anewarray     #121                // class org/apache/hadoop/hbase/wal/WAL$Entry
     118: invokeinterface #234,  2          // InterfaceMethod java/util/List.toArray:([Ljava/lang/Object;)[Ljava/lang/Object;
     123: checkcast     #235                // class "[Lorg/apache/hadoop/hbase/wal/WAL$Entry;"
     126: aload_0
     127: getfield      #4                  // Field replicationClusterId:Ljava/lang/String;
     130: aload_0
     131: getfield      #74                 // Field baseNamespaceDir:Lorg/apache/hadoop/fs/Path;
     134: aload_0
     135: getfield      #77                 // Field hfileArchiveDir:Lorg/apache/hadoop/fs/Path;
     138: invokestatic  #236                // Method org/apache/hadoop/hbase/protobuf/ReplicationProtbufUtil.replicateWALEntry:(Lorg/apache/hadoop/hbase/shaded/protobuf/generated/AdminProtos$AdminService$BlockingInterface;[Lorg/apache/hadoop/hbase/wal/WAL$Entry;Ljava/lang/String;Lorg/apache/hadoop/fs/Path;Lorg/apache/hadoop/fs/Path;)V
     141: getstatic     #90                 // Field LOG:Lorg/slf4j/Logger;
     144: ldc           #237                // String Completed replicating batch {}
     146: iload         4
     148: invokestatic  #158                // Method java/lang/Integer.valueOf:(I)Ljava/lang/Integer;
     151: invokeinterface #238,  3          // InterfaceMethod org/slf4j/Logger.trace:(Ljava/lang/String;Ljava/lang/Object;)V
     156: goto          181
     159: astore        6
     161: getstatic     #90                 // Field LOG:Lorg/slf4j/Logger;
     164: ldc           #239                // String Failed replicating batch {}
     166: iload         4
     168: invokestatic  #158                // Method java/lang/Integer.valueOf:(I)Ljava/lang/Integer;
     171: aload         6
     173: invokeinterface #160,  4          // InterfaceMethod org/slf4j/Logger.trace:(Ljava/lang/String;Ljava/lang/Object;Ljava/lang/Object;)V
     178: aload         6
     180: athrow
     181: aload_0
     182: getfield      #41                 // Field replicationSinkMgr:Lorg/apache/hadoop/hbase/replication/regionserver/ReplicationSinkManager;
     185: aload_3
     186: invokevirtual #240                // Method org/apache/hadoop/hbase/replication/regionserver/ReplicationSinkManager.reportSinkSuccess:(Lorg/apache/hadoop/hbase/replication/regionserver/ReplicationSinkManager$SinkPeer;)V
     189: goto          209
     192: astore        4
     194: aload_3
     195: ifnull        206
     198: aload_0
     199: getfield      #41                 // Field replicationSinkMgr:Lorg/apache/hadoop/hbase/replication/regionserver/ReplicationSinkManager;
     202: aload_3
     203: invokevirtual #241                // Method org/apache/hadoop/hbase/replication/regionserver/ReplicationSinkManager.reportBadSink:(Lorg/apache/hadoop/hbase/replication/regionserver/ReplicationSinkManager$SinkPeer;)V
     206: aload         4
     208: athrow
     209: iload_2
     210: ireturn
    Exception table:
       from    to  target type
         106   156   159   Class java/io/IOException
           2   189   192   Class java/io/IOException

  protected java.util.concurrent.Callable<java.lang.Integer> createReplicator(java.util.List<org.apache.hadoop.hbase.wal.WAL$Entry>, int);
    Code:
       0: aload_0
       1: getfield      #5                  // Field isSerial:Z
       4: ifeq          18
       7: aload_0
       8: aload_1
       9: iload_2
      10: invokedynamic #244,  0            // InvokeDynamic #4:call:(Lorg/apache/hadoop/hbase/replication/regionserver/HBaseInterClusterReplicationEndpoint;Ljava/util/List;I)Ljava/util/concurrent/Callable;
      15: goto          26
      18: aload_0
      19: aload_1
      20: iload_2
      21: invokedynamic #245,  0            // InvokeDynamic #5:call:(Lorg/apache/hadoop/hbase/replication/regionserver/HBaseInterClusterReplicationEndpoint;Ljava/util/List;I)Ljava/util/concurrent/Callable;
      26: areturn

  static {};
    Code:
       0: ldc           #20                 // class org/apache/hadoop/hbase/replication/regionserver/HBaseInterClusterReplicationEndpoint
       2: invokestatic  #251                // Method org/slf4j/LoggerFactory.getLogger:(Ljava/lang/Class;)Lorg/slf4j/Logger;
       5: putstatic     #90                 // Field LOG:Lorg/slf4j/Logger;
       8: return
}
