Compiled from "HBaseAdmin.java"
class org.apache.hadoop.hbase.client.HBaseAdmin$46 extends org.apache.hadoop.hbase.client.HBaseAdmin$NamespaceFuture {
  final org.apache.hadoop.hbase.client.HBaseAdmin this$0;

  org.apache.hadoop.hbase.client.HBaseAdmin$46(org.apache.hadoop.hbase.client.HBaseAdmin, org.apache.hadoop.hbase.client.HBaseAdmin, java.lang.String, java.lang.Long);
    Code:
       0: aload_0
       1: aload_1
       2: putfield      #1                  // Field this$0:Lorg/apache/hadoop/hbase/client/HBaseAdmin;
       5: aload_0
       6: aload_2
       7: aload_3
       8: aload         4
      10: invokespecial #2                  // Method org/apache/hadoop/hbase/client/HBaseAdmin$NamespaceFuture."<init>":(Lorg/apache/hadoop/hbase/client/HBaseAdmin;Ljava/lang/String;Ljava/lang/Long;)V
      13: return

  public java.lang.String getOperationType();
    Code:
       0: ldc           #3                  // String CREATE_NAMESPACE
       2: areturn
}
