Compiled from "HBaseFsck.java"
class org.apache.hadoop.hbase.util.HBaseFsck$3$1 implements java.util.Comparator<org.apache.hadoop.hbase.Cell> {
  final org.apache.hadoop.hbase.util.HBaseFsck$3 this$1;

  org.apache.hadoop.hbase.util.HBaseFsck$3$1(org.apache.hadoop.hbase.util.HBaseFsck$3);
    Code:
       0: aload_0
       1: aload_1
       2: putfield      #1                  // Field this$1:Lorg/apache/hadoop/hbase/util/HBaseFsck$3;
       5: aload_0
       6: invokespecial #2                  // Method java/lang/Object."<init>":()V
       9: return

  public int compare(org.apache.hadoop.hbase.Cell, org.apache.hadoop.hbase.Cell);
    Code:
       0: aload_1
       1: invokeinterface #3,  1            // InterfaceMethod org/apache/hadoop/hbase/Cell.getTimestamp:()J
       6: aload_2
       7: invokeinterface #3,  1            // InterfaceMethod org/apache/hadoop/hbase/Cell.getTimestamp:()J
      12: invokestatic  #4                  // Method java/lang/Long.compare:(JJ)I
      15: ireturn

  public int compare(java.lang.Object, java.lang.Object);
    Code:
       0: aload_0
       1: aload_1
       2: checkcast     #5                  // class org/apache/hadoop/hbase/Cell
       5: aload_2
       6: checkcast     #5                  // class org/apache/hadoop/hbase/Cell
       9: invokevirtual #6                  // Method compare:(Lorg/apache/hadoop/hbase/Cell;Lorg/apache/hadoop/hbase/Cell;)I
      12: ireturn
}
