Compiled from "HBaseFsck.java"
class org.apache.hadoop.hbase.util.HBaseFsck$WorkItemHdfsDir implements java.util.concurrent.Callable<java.lang.Void> {
  final org.apache.hadoop.hbase.util.HBaseFsck this$0;

  org.apache.hadoop.hbase.util.HBaseFsck$WorkItemHdfsDir(org.apache.hadoop.hbase.util.HBaseFsck, org.apache.hadoop.fs.FileSystem, org.apache.hadoop.hbase.util.HBaseFsck$ErrorReporter, org.apache.hadoop.fs.FileStatus);
    Code:
       0: aload_0
       1: aload_1
       2: putfield      #3                  // Field this$0:Lorg/apache/hadoop/hbase/util/HBaseFsck;
       5: aload_0
       6: invokespecial #4                  // Method java/lang/Object."<init>":()V
       9: aload_0
      10: aload_2
      11: putfield      #2                  // Field fs:Lorg/apache/hadoop/fs/FileSystem;
      14: aload_0
      15: aload         4
      17: putfield      #5                  // Field tableDir:Lorg/apache/hadoop/fs/FileStatus;
      20: aload_0
      21: aload_3
      22: putfield      #1                  // Field errors:Lorg/apache/hadoop/hbase/util/HBaseFsck$ErrorReporter;
      25: return

  public synchronized java.lang.Void call() throws java.lang.InterruptedException, java.util.concurrent.ExecutionException;
    Code:
       0: new           #6                  // class java/util/Vector
       3: dup
       4: invokespecial #7                  // Method java/util/Vector."<init>":()V
       7: astore_1
       8: aload_0
       9: getfield      #2                  // Field fs:Lorg/apache/hadoop/fs/FileSystem;
      12: aload_0
      13: getfield      #5                  // Field tableDir:Lorg/apache/hadoop/fs/FileStatus;
      16: invokevirtual #8                  // Method org/apache/hadoop/fs/FileStatus.getPath:()Lorg/apache/hadoop/fs/Path;
      19: invokevirtual #9                  // Method org/apache/hadoop/fs/FileSystem.listStatus:(Lorg/apache/hadoop/fs/Path;)[Lorg/apache/hadoop/fs/FileStatus;
      22: astore_2
      23: new           #10                 // class java/util/ArrayList
      26: dup
      27: aload_2
      28: arraylength
      29: invokespecial #11                 // Method java/util/ArrayList."<init>":(I)V
      32: astore_3
      33: aload_2
      34: astore        4
      36: aload         4
      38: arraylength
      39: istore        5
      41: iconst_0
      42: istore        6
      44: iload         6
      46: iload         5
      48: if_icmpge     144
      51: aload         4
      53: iload         6
      55: aaload
      56: astore        7
      58: aload_0
      59: getfield      #1                  // Field errors:Lorg/apache/hadoop/hbase/util/HBaseFsck$ErrorReporter;
      62: invokeinterface #12,  1           // InterfaceMethod org/apache/hadoop/hbase/util/HBaseFsck$ErrorReporter.progress:()V
      67: aload         7
      69: invokevirtual #8                  // Method org/apache/hadoop/fs/FileStatus.getPath:()Lorg/apache/hadoop/fs/Path;
      72: invokevirtual #13                 // Method org/apache/hadoop/fs/Path.getName:()Ljava/lang/String;
      75: astore        8
      77: aload         8
      79: getstatic     #14                 // Field java/util/Locale.ROOT:Ljava/util/Locale;
      82: invokevirtual #15                 // Method java/lang/String.toLowerCase:(Ljava/util/Locale;)Ljava/lang/String;
      85: ldc           #16                 // String [0-9a-f]+
      87: invokevirtual #17                 // Method java/lang/String.matches:(Ljava/lang/String;)Z
      90: ifne          96
      93: goto          138
      96: aload_1
      97: invokevirtual #18                 // Method java/util/Vector.isEmpty:()Z
     100: ifne          106
     103: goto          144
     106: aload_3
     107: aload_0
     108: getfield      #3                  // Field this$0:Lorg/apache/hadoop/hbase/util/HBaseFsck;
     111: getfield      #19                 // Field org/apache/hadoop/hbase/util/HBaseFsck.executor:Ljava/util/concurrent/ExecutorService;
     114: new           #20                 // class org/apache/hadoop/hbase/util/HBaseFsck$WorkItemHdfsDir$1
     117: dup
     118: aload_0
     119: aload         7
     121: aload         8
     123: aload_1
     124: invokespecial #21                 // Method org/apache/hadoop/hbase/util/HBaseFsck$WorkItemHdfsDir$1."<init>":(Lorg/apache/hadoop/hbase/util/HBaseFsck$WorkItemHdfsDir;Lorg/apache/hadoop/fs/FileStatus;Ljava/lang/String;Ljava/util/Vector;)V
     127: invokeinterface #22,  2           // InterfaceMethod java/util/concurrent/ExecutorService.submit:(Ljava/lang/Runnable;)Ljava/util/concurrent/Future;
     132: invokeinterface #23,  2           // InterfaceMethod java/util/List.add:(Ljava/lang/Object;)Z
     137: pop
     138: iinc          6, 1
     141: goto          44
     144: aload_3
     145: invokeinterface #24,  1           // InterfaceMethod java/util/List.iterator:()Ljava/util/Iterator;
     150: astore        4
     152: aload         4
     154: invokeinterface #25,  1           // InterfaceMethod java/util/Iterator.hasNext:()Z
     159: ifeq          212
     162: aload         4
     164: invokeinterface #26,  1           // InterfaceMethod java/util/Iterator.next:()Ljava/lang/Object;
     169: checkcast     #27                 // class java/util/concurrent/Future
     172: astore        5
     174: aload_1
     175: invokevirtual #18                 // Method java/util/Vector.isEmpty:()Z
     178: ifne          184
     181: goto          212
     184: aload         5
     186: invokeinterface #28,  1           // InterfaceMethod java/util/concurrent/Future.get:()Ljava/lang/Object;
     191: pop
     192: goto          209
     195: astore        6
     197: invokestatic  #30                 // Method org/apache/hadoop/hbase/util/HBaseFsck.access$000:()Lorg/slf4j/Logger;
     200: ldc           #31                 // String Unexpected exec exception!  Should've been caught already.  (Bug?)
     202: aload         6
     204: invokeinterface #32,  3           // InterfaceMethod org/slf4j/Logger.error:(Ljava/lang/String;Ljava/lang/Throwable;)V
     209: goto          152
     212: aload_1
     213: invokevirtual #18                 // Method java/util/Vector.isEmpty:()Z
     216: ifne          462
     219: aload_0
     220: getfield      #1                  // Field errors:Lorg/apache/hadoop/hbase/util/HBaseFsck$ErrorReporter;
     223: getstatic     #33                 // Field org/apache/hadoop/hbase/util/HBaseFsck$ErrorReporter$ERROR_CODE.RS_CONNECT_FAILURE:Lorg/apache/hadoop/hbase/util/HBaseFsck$ErrorReporter$ERROR_CODE;
     226: new           #34                 // class java/lang/StringBuilder
     229: dup
     230: invokespecial #35                 // Method java/lang/StringBuilder."<init>":()V
     233: ldc           #36                 // String Table Directory:
     235: invokevirtual #37                 // Method java/lang/StringBuilder.append:(Ljava/lang/String;)Ljava/lang/StringBuilder;
     238: aload_0
     239: getfield      #5                  // Field tableDir:Lorg/apache/hadoop/fs/FileStatus;
     242: invokevirtual #8                  // Method org/apache/hadoop/fs/FileStatus.getPath:()Lorg/apache/hadoop/fs/Path;
     245: invokevirtual #13                 // Method org/apache/hadoop/fs/Path.getName:()Ljava/lang/String;
     248: invokevirtual #37                 // Method java/lang/StringBuilder.append:(Ljava/lang/String;)Ljava/lang/StringBuilder;
     251: ldc           #38                 // String  Unable to fetch all HDFS region information.
     253: invokevirtual #37                 // Method java/lang/StringBuilder.append:(Ljava/lang/String;)Ljava/lang/StringBuilder;
     256: invokevirtual #39                 // Method java/lang/StringBuilder.toString:()Ljava/lang/String;
     259: invokeinterface #40,  3           // InterfaceMethod org/apache/hadoop/hbase/util/HBaseFsck$ErrorReporter.reportError:(Lorg/apache/hadoop/hbase/util/HBaseFsck$ErrorReporter$ERROR_CODE;Ljava/lang/String;)V
     264: new           #29                 // class java/util/concurrent/ExecutionException
     267: dup
     268: ldc           #41                 // String First exception in WorkItemHdfsDir
     270: aload_1
     271: invokevirtual #42                 // Method java/util/Vector.firstElement:()Ljava/lang/Object;
     274: checkcast     #43                 // class java/lang/Throwable
     277: invokespecial #44                 // Method java/util/concurrent/ExecutionException."<init>":(Ljava/lang/String;Ljava/lang/Throwable;)V
     280: athrow
     281: astore_2
     282: invokestatic  #30                 // Method org/apache/hadoop/hbase/util/HBaseFsck.access$000:()Lorg/slf4j/Logger;
     285: new           #34                 // class java/lang/StringBuilder
     288: dup
     289: invokespecial #35                 // Method java/lang/StringBuilder."<init>":()V
     292: ldc           #46                 // String Cannot execute WorkItemHdfsDir for
     294: invokevirtual #37                 // Method java/lang/StringBuilder.append:(Ljava/lang/String;)Ljava/lang/StringBuilder;
     297: aload_0
     298: getfield      #5                  // Field tableDir:Lorg/apache/hadoop/fs/FileStatus;
     301: invokevirtual #47                 // Method java/lang/StringBuilder.append:(Ljava/lang/Object;)Ljava/lang/StringBuilder;
     304: invokevirtual #39                 // Method java/lang/StringBuilder.toString:()Ljava/lang/String;
     307: aload_2
     308: invokeinterface #32,  3           // InterfaceMethod org/slf4j/Logger.error:(Ljava/lang/String;Ljava/lang/Throwable;)V
     313: aload_1
     314: aload_2
     315: invokevirtual #48                 // Method java/util/Vector.add:(Ljava/lang/Object;)Z
     318: pop
     319: aload_1
     320: invokevirtual #18                 // Method java/util/Vector.isEmpty:()Z
     323: ifne          462
     326: aload_0
     327: getfield      #1                  // Field errors:Lorg/apache/hadoop/hbase/util/HBaseFsck$ErrorReporter;
     330: getstatic     #33                 // Field org/apache/hadoop/hbase/util/HBaseFsck$ErrorReporter$ERROR_CODE.RS_CONNECT_FAILURE:Lorg/apache/hadoop/hbase/util/HBaseFsck$ErrorReporter$ERROR_CODE;
     333: new           #34                 // class java/lang/StringBuilder
     336: dup
     337: invokespecial #35                 // Method java/lang/StringBuilder."<init>":()V
     340: ldc           #36                 // String Table Directory:
     342: invokevirtual #37                 // Method java/lang/StringBuilder.append:(Ljava/lang/String;)Ljava/lang/StringBuilder;
     345: aload_0
     346: getfield      #5                  // Field tableDir:Lorg/apache/hadoop/fs/FileStatus;
     349: invokevirtual #8                  // Method org/apache/hadoop/fs/FileStatus.getPath:()Lorg/apache/hadoop/fs/Path;
     352: invokevirtual #13                 // Method org/apache/hadoop/fs/Path.getName:()Ljava/lang/String;
     355: invokevirtual #37                 // Method java/lang/StringBuilder.append:(Ljava/lang/String;)Ljava/lang/StringBuilder;
     358: ldc           #38                 // String  Unable to fetch all HDFS region information.
     360: invokevirtual #37                 // Method java/lang/StringBuilder.append:(Ljava/lang/String;)Ljava/lang/StringBuilder;
     363: invokevirtual #39                 // Method java/lang/StringBuilder.toString:()Ljava/lang/String;
     366: invokeinterface #40,  3           // InterfaceMethod org/apache/hadoop/hbase/util/HBaseFsck$ErrorReporter.reportError:(Lorg/apache/hadoop/hbase/util/HBaseFsck$ErrorReporter$ERROR_CODE;Ljava/lang/String;)V
     371: new           #29                 // class java/util/concurrent/ExecutionException
     374: dup
     375: ldc           #41                 // String First exception in WorkItemHdfsDir
     377: aload_1
     378: invokevirtual #42                 // Method java/util/Vector.firstElement:()Ljava/lang/Object;
     381: checkcast     #43                 // class java/lang/Throwable
     384: invokespecial #44                 // Method java/util/concurrent/ExecutionException."<init>":(Ljava/lang/String;Ljava/lang/Throwable;)V
     387: athrow
     388: astore        9
     390: aload_1
     391: invokevirtual #18                 // Method java/util/Vector.isEmpty:()Z
     394: ifne          459
     397: aload_0
     398: getfield      #1                  // Field errors:Lorg/apache/hadoop/hbase/util/HBaseFsck$ErrorReporter;
     401: getstatic     #33                 // Field org/apache/hadoop/hbase/util/HBaseFsck$ErrorReporter$ERROR_CODE.RS_CONNECT_FAILURE:Lorg/apache/hadoop/hbase/util/HBaseFsck$ErrorReporter$ERROR_CODE;
     404: new           #34                 // class java/lang/StringBuilder
     407: dup
     408: invokespecial #35                 // Method java/lang/StringBuilder."<init>":()V
     411: ldc           #36                 // String Table Directory:
     413: invokevirtual #37                 // Method java/lang/StringBuilder.append:(Ljava/lang/String;)Ljava/lang/StringBuilder;
     416: aload_0
     417: getfield      #5                  // Field tableDir:Lorg/apache/hadoop/fs/FileStatus;
     420: invokevirtual #8                  // Method org/apache/hadoop/fs/FileStatus.getPath:()Lorg/apache/hadoop/fs/Path;
     423: invokevirtual #13                 // Method org/apache/hadoop/fs/Path.getName:()Ljava/lang/String;
     426: invokevirtual #37                 // Method java/lang/StringBuilder.append:(Ljava/lang/String;)Ljava/lang/StringBuilder;
     429: ldc           #38                 // String  Unable to fetch all HDFS region information.
     431: invokevirtual #37                 // Method java/lang/StringBuilder.append:(Ljava/lang/String;)Ljava/lang/StringBuilder;
     434: invokevirtual #39                 // Method java/lang/StringBuilder.toString:()Ljava/lang/String;
     437: invokeinterface #40,  3           // InterfaceMethod org/apache/hadoop/hbase/util/HBaseFsck$ErrorReporter.reportError:(Lorg/apache/hadoop/hbase/util/HBaseFsck$ErrorReporter$ERROR_CODE;Ljava/lang/String;)V
     442: new           #29                 // class java/util/concurrent/ExecutionException
     445: dup
     446: ldc           #41                 // String First exception in WorkItemHdfsDir
     448: aload_1
     449: invokevirtual #42                 // Method java/util/Vector.firstElement:()Ljava/lang/Object;
     452: checkcast     #43                 // class java/lang/Throwable
     455: invokespecial #44                 // Method java/util/concurrent/ExecutionException."<init>":(Ljava/lang/String;Ljava/lang/Throwable;)V
     458: athrow
     459: aload         9
     461: athrow
     462: aconst_null
     463: areturn
    Exception table:
       from    to  target type
         184   192   195   Class java/util/concurrent/ExecutionException
           8   212   281   Class java/io/IOException
           8   212   388   any
         281   319   388   any
         388   390   388   any

  public java.lang.Object call() throws java.lang.Exception;
    Code:
       0: aload_0
       1: invokevirtual #49                 // Method call:()Ljava/lang/Void;
       4: areturn

  static org.apache.hadoop.fs.FileSystem access$2700(org.apache.hadoop.hbase.util.HBaseFsck$WorkItemHdfsDir);
    Code:
       0: aload_0
       1: getfield      #2                  // Field fs:Lorg/apache/hadoop/fs/FileSystem;
       4: areturn

  static org.apache.hadoop.hbase.util.HBaseFsck$ErrorReporter access$2800(org.apache.hadoop.hbase.util.HBaseFsck$WorkItemHdfsDir);
    Code:
       0: aload_0
       1: getfield      #1                  // Field errors:Lorg/apache/hadoop/hbase/util/HBaseFsck$ErrorReporter;
       4: areturn
}
