Compiled from "HBaseAdmin.java"
public abstract class org.apache.hadoop.hbase.client.HBaseAdmin$NamespaceFuture extends org.apache.hadoop.hbase.client.HBaseAdmin$ProcedureFuture<java.lang.Void> {
  public org.apache.hadoop.hbase.client.HBaseAdmin$NamespaceFuture(org.apache.hadoop.hbase.client.HBaseAdmin, java.lang.String, java.lang.Long);
    Code:
       0: aload_0
       1: aload_1
       2: aload_3
       3: invokespecial #1                  // Method org/apache/hadoop/hbase/client/HBaseAdmin$ProcedureFuture."<init>":(Lorg/apache/hadoop/hbase/client/HBaseAdmin;Ljava/lang/Long;)V
       6: aload_0
       7: aload_2
       8: putfield      #2                  // Field namespaceName:Ljava/lang/String;
      11: return

  protected java.lang.String getNamespaceName();
    Code:
       0: aload_0
       1: getfield      #2                  // Field namespaceName:Ljava/lang/String;
       4: areturn

  public abstract java.lang.String getOperationType();

  public java.lang.String toString();
    Code:
       0: new           #3                  // class java/lang/StringBuilder
       3: dup
       4: invokespecial #4                  // Method java/lang/StringBuilder."<init>":()V
       7: ldc           #5                  // String Operation:
       9: invokevirtual #6                  // Method java/lang/StringBuilder.append:(Ljava/lang/String;)Ljava/lang/StringBuilder;
      12: aload_0
      13: invokevirtual #7                  // Method getOperationType:()Ljava/lang/String;
      16: invokevirtual #6                  // Method java/lang/StringBuilder.append:(Ljava/lang/String;)Ljava/lang/StringBuilder;
      19: ldc           #8                  // String , Namespace:
      21: invokevirtual #6                  // Method java/lang/StringBuilder.append:(Ljava/lang/String;)Ljava/lang/StringBuilder;
      24: aload_0
      25: invokevirtual #9                  // Method getNamespaceName:()Ljava/lang/String;
      28: invokevirtual #6                  // Method java/lang/StringBuilder.append:(Ljava/lang/String;)Ljava/lang/StringBuilder;
      31: invokevirtual #10                 // Method java/lang/StringBuilder.toString:()Ljava/lang/String;
      34: areturn
}
