Compiled from "HBaseAdmin.java"
class org.apache.hadoop.hbase.client.HBaseAdmin$51 extends org.apache.hadoop.hbase.client.MasterCallable<org.apache.hadoop.hbase.NamespaceDescriptor> {
  final java.lang.String val$name;

  final org.apache.hadoop.hbase.client.HBaseAdmin this$0;

  org.apache.hadoop.hbase.client.HBaseAdmin$51(org.apache.hadoop.hbase.client.HBaseAdmin, org.apache.hadoop.hbase.client.Connection, org.apache.hadoop.hbase.ipc.RpcControllerFactory, java.lang.String);
    Code:
       0: aload_0
       1: aload_1
       2: putfield      #1                  // Field this$0:Lorg/apache/hadoop/hbase/client/HBaseAdmin;
       5: aload_0
       6: aload         4
       8: putfield      #2                  // Field val$name:Ljava/lang/String;
      11: aload_0
      12: aload_2
      13: aload_3
      14: invokespecial #3                  // Method org/apache/hadoop/hbase/client/MasterCallable."<init>":(Lorg/apache/hadoop/hbase/client/Connection;Lorg/apache/hadoop/hbase/ipc/RpcControllerFactory;)V
      17: return

  protected org.apache.hadoop.hbase.NamespaceDescriptor rpcCall() throws java.lang.Exception;
    Code:
       0: aload_0
       1: getfield      #4                  // Field master:Lorg/apache/hadoop/hbase/client/MasterKeepAliveConnection;
       4: aload_0
       5: invokevirtual #5                  // Method getRpcController:()Lorg/apache/hadoop/hbase/ipc/HBaseRpcController;
       8: invokestatic  #6                  // Method org/apache/hadoop/hbase/shaded/protobuf/generated/MasterProtos$GetNamespaceDescriptorRequest.newBuilder:()Lorg/apache/hadoop/hbase/shaded/protobuf/generated/MasterProtos$GetNamespaceDescriptorRequest$Builder;
      11: aload_0
      12: getfield      #2                  // Field val$name:Ljava/lang/String;
      15: invokevirtual #7                  // Method org/apache/hadoop/hbase/shaded/protobuf/generated/MasterProtos$GetNamespaceDescriptorRequest$Builder.setNamespaceName:(Ljava/lang/String;)Lorg/apache/hadoop/hbase/shaded/protobuf/generated/MasterProtos$GetNamespaceDescriptorRequest$Builder;
      18: invokevirtual #8                  // Method org/apache/hadoop/hbase/shaded/protobuf/generated/MasterProtos$GetNamespaceDescriptorRequest$Builder.build:()Lorg/apache/hadoop/hbase/shaded/protobuf/generated/MasterProtos$GetNamespaceDescriptorRequest;
      21: invokeinterface #9,  3            // InterfaceMethod org/apache/hadoop/hbase/client/MasterKeepAliveConnection.getNamespaceDescriptor:(Lorg/apache/hbase/thirdparty/com/google/protobuf/RpcController;Lorg/apache/hadoop/hbase/shaded/protobuf/generated/MasterProtos$GetNamespaceDescriptorRequest;)Lorg/apache/hadoop/hbase/shaded/protobuf/generated/MasterProtos$GetNamespaceDescriptorResponse;
      26: invokevirtual #10                 // Method org/apache/hadoop/hbase/shaded/protobuf/generated/MasterProtos$GetNamespaceDescriptorResponse.getNamespaceDescriptor:()Lorg/apache/hadoop/hbase/shaded/protobuf/generated/HBaseProtos$NamespaceDescriptor;
      29: invokestatic  #11                 // Method org/apache/hadoop/hbase/shaded/protobuf/ProtobufUtil.toNamespaceDescriptor:(Lorg/apache/hadoop/hbase/shaded/protobuf/generated/HBaseProtos$NamespaceDescriptor;)Lorg/apache/hadoop/hbase/NamespaceDescriptor;
      32: areturn

  protected java.lang.Object rpcCall() throws java.lang.Exception;
    Code:
       0: aload_0
       1: invokevirtual #12                 // Method rpcCall:()Lorg/apache/hadoop/hbase/NamespaceDescriptor;
       4: areturn
}
