Compiled from "HBaseZKTestingUtility.java"
public class org.apache.hadoop.hbase.HBaseZKTestingUtility extends org.apache.hadoop.hbase.HBaseCommonTestingUtility {
  protected org.apache.hadoop.hbase.zookeeper.ZKWatcher zooKeeperWatcher;

  protected java.io.File clusterTestDir;

  public org.apache.hadoop.hbase.HBaseZKTestingUtility();
    Code:
       0: aload_0
       1: invokestatic  #1                  // Method org/apache/hadoop/hbase/HBaseConfiguration.create:()Lorg/apache/hadoop/conf/Configuration;
       4: invokespecial #2                  // Method "<init>":(Lorg/apache/hadoop/conf/Configuration;)V
       7: return

  public org.apache.hadoop.hbase.HBaseZKTestingUtility(org.apache.hadoop.conf.Configuration);
    Code:
       0: aload_0
       1: aload_1
       2: invokespecial #3                  // Method org/apache/hadoop/hbase/HBaseCommonTestingUtility."<init>":(Lorg/apache/hadoop/conf/Configuration;)V
       5: return

  org.apache.hadoop.fs.Path getClusterTestDir();
    Code:
       0: aload_0
       1: getfield      #4                  // Field clusterTestDir:Ljava/io/File;
       4: ifnonnull     11
       7: aload_0
       8: invokevirtual #5                  // Method setupClusterTestDir:()V
      11: new           #6                  // class org/apache/hadoop/fs/Path
      14: dup
      15: aload_0
      16: getfield      #4                  // Field clusterTestDir:Ljava/io/File;
      19: invokevirtual #7                  // Method java/io/File.getAbsolutePath:()Ljava/lang/String;
      22: invokespecial #8                  // Method org/apache/hadoop/fs/Path."<init>":(Ljava/lang/String;)V
      25: areturn

  protected void setupClusterTestDir();
    Code:
       0: aload_0
       1: getfield      #4                  // Field clusterTestDir:Ljava/io/File;
       4: ifnull        8
       7: return
       8: aload_0
       9: new           #9                  // class java/lang/StringBuilder
      12: dup
      13: invokespecial #10                 // Method java/lang/StringBuilder."<init>":()V
      16: ldc           #11                 // String cluster_
      18: invokevirtual #12                 // Method java/lang/StringBuilder.append:(Ljava/lang/String;)Ljava/lang/StringBuilder;
      21: aload_0
      22: invokevirtual #13                 // Method getRandomUUID:()Ljava/util/UUID;
      25: invokevirtual #14                 // Method java/util/UUID.toString:()Ljava/lang/String;
      28: invokevirtual #12                 // Method java/lang/StringBuilder.append:(Ljava/lang/String;)Ljava/lang/StringBuilder;
      31: invokevirtual #15                 // Method java/lang/StringBuilder.toString:()Ljava/lang/String;
      34: invokevirtual #16                 // Method getDataTestDir:(Ljava/lang/String;)Lorg/apache/hadoop/fs/Path;
      37: astore_1
      38: aload_0
      39: new           #17                 // class java/io/File
      42: dup
      43: aload_1
      44: invokevirtual #18                 // Method org/apache/hadoop/fs/Path.toString:()Ljava/lang/String;
      47: invokespecial #19                 // Method java/io/File."<init>":(Ljava/lang/String;)V
      50: invokevirtual #20                 // Method java/io/File.getAbsoluteFile:()Ljava/io/File;
      53: putfield      #4                  // Field clusterTestDir:Ljava/io/File;
      56: aload_0
      57: invokevirtual #21                 // Method deleteOnExit:()Z
      60: istore_2
      61: iload_2
      62: ifeq          72
      65: aload_0
      66: getfield      #4                  // Field clusterTestDir:Ljava/io/File;
      69: invokevirtual #22                 // Method java/io/File.deleteOnExit:()V
      72: getstatic     #23                 // Field LOG:Lorg/slf4j/Logger;
      75: new           #9                  // class java/lang/StringBuilder
      78: dup
      79: invokespecial #10                 // Method java/lang/StringBuilder."<init>":()V
      82: ldc           #24                 // String Created new mini-cluster data directory:
      84: invokevirtual #12                 // Method java/lang/StringBuilder.append:(Ljava/lang/String;)Ljava/lang/StringBuilder;
      87: aload_0
      88: getfield      #4                  // Field clusterTestDir:Ljava/io/File;
      91: invokevirtual #25                 // Method java/lang/StringBuilder.append:(Ljava/lang/Object;)Ljava/lang/StringBuilder;
      94: ldc           #26                 // String , deleteOnExit=
      96: invokevirtual #12                 // Method java/lang/StringBuilder.append:(Ljava/lang/String;)Ljava/lang/StringBuilder;
      99: iload_2
     100: invokevirtual #27                 // Method java/lang/StringBuilder.append:(Z)Ljava/lang/StringBuilder;
     103: invokevirtual #15                 // Method java/lang/StringBuilder.toString:()Ljava/lang/String;
     106: invokeinterface #28,  2           // InterfaceMethod org/slf4j/Logger.info:(Ljava/lang/String;)V
     111: return

  public org.apache.hadoop.hbase.zookeeper.MiniZooKeeperCluster startMiniZKCluster() throws java.lang.Exception;
    Code:
       0: aload_0
       1: iconst_1
       2: iconst_0
       3: newarray       int
       5: invokevirtual #29                 // Method startMiniZKCluster:(I[I)Lorg/apache/hadoop/hbase/zookeeper/MiniZooKeeperCluster;
       8: areturn

  public org.apache.hadoop.hbase.zookeeper.MiniZooKeeperCluster startMiniZKCluster(int, int...) throws java.lang.Exception;
    Code:
       0: aload_0
       1: invokevirtual #5                  // Method setupClusterTestDir:()V
       4: aload_0
       5: aload_0
       6: getfield      #4                  // Field clusterTestDir:Ljava/io/File;
       9: iload_1
      10: aload_2
      11: invokespecial #30                 // Method startMiniZKCluster:(Ljava/io/File;I[I)Lorg/apache/hadoop/hbase/zookeeper/MiniZooKeeperCluster;
      14: areturn

  public org.apache.hadoop.hbase.zookeeper.MiniZooKeeperCluster getZkCluster();
    Code:
       0: aload_0
       1: getfield      #31                 // Field zkCluster:Lorg/apache/hadoop/hbase/zookeeper/MiniZooKeeperCluster;
       4: areturn

  public void setZkCluster(org.apache.hadoop.hbase.zookeeper.MiniZooKeeperCluster);
    Code:
       0: aload_0
       1: iconst_1
       2: putfield      #35                 // Field passedZkCluster:Z
       5: aload_0
       6: aload_1
       7: putfield      #31                 // Field zkCluster:Lorg/apache/hadoop/hbase/zookeeper/MiniZooKeeperCluster;
      10: aload_0
      11: getfield      #39                 // Field conf:Lorg/apache/hadoop/conf/Configuration;
      14: ldc           #46                 // String hbase.zookeeper.property.clientPort
      16: aload_1
      17: invokevirtual #49                 // Method org/apache/hadoop/hbase/zookeeper/MiniZooKeeperCluster.getClientPort:()I
      20: invokevirtual #50                 // Method org/apache/hadoop/conf/Configuration.setInt:(Ljava/lang/String;I)V
      23: return

  public void shutdownMiniZKCluster() throws java.io.IOException;
    Code:
       0: aload_0
       1: getfield      #35                 // Field passedZkCluster:Z
       4: ifne          26
       7: aload_0
       8: getfield      #31                 // Field zkCluster:Lorg/apache/hadoop/hbase/zookeeper/MiniZooKeeperCluster;
      11: ifnull        26
      14: aload_0
      15: getfield      #31                 // Field zkCluster:Lorg/apache/hadoop/hbase/zookeeper/MiniZooKeeperCluster;
      18: invokevirtual #51                 // Method org/apache/hadoop/hbase/zookeeper/MiniZooKeeperCluster.shutdown:()V
      21: aload_0
      22: aconst_null
      23: putfield      #31                 // Field zkCluster:Lorg/apache/hadoop/hbase/zookeeper/MiniZooKeeperCluster;
      26: return

  public synchronized org.apache.hadoop.hbase.zookeeper.ZKWatcher getZooKeeperWatcher() throws java.io.IOException;
    Code:
       0: aload_0
       1: getfield      #52                 // Field zooKeeperWatcher:Lorg/apache/hadoop/hbase/zookeeper/ZKWatcher;
       4: ifnonnull     32
       7: aload_0
       8: new           #53                 // class org/apache/hadoop/hbase/zookeeper/ZKWatcher
      11: dup
      12: aload_0
      13: getfield      #39                 // Field conf:Lorg/apache/hadoop/conf/Configuration;
      16: ldc           #54                 // String testing utility
      18: new           #55                 // class org/apache/hadoop/hbase/HBaseZKTestingUtility$1
      21: dup
      22: aload_0
      23: invokespecial #56                 // Method org/apache/hadoop/hbase/HBaseZKTestingUtility$1."<init>":(Lorg/apache/hadoop/hbase/HBaseZKTestingUtility;)V
      26: invokespecial #57                 // Method org/apache/hadoop/hbase/zookeeper/ZKWatcher."<init>":(Lorg/apache/hadoop/conf/Configuration;Ljava/lang/String;Lorg/apache/hadoop/hbase/Abortable;)V
      29: putfield      #52                 // Field zooKeeperWatcher:Lorg/apache/hadoop/hbase/zookeeper/ZKWatcher;
      32: aload_0
      33: getfield      #52                 // Field zooKeeperWatcher:Lorg/apache/hadoop/hbase/zookeeper/ZKWatcher;
      36: areturn

  public static org.apache.hadoop.hbase.zookeeper.ZKWatcher getZooKeeperWatcher(org.apache.hadoop.hbase.HBaseZKTestingUtility) throws java.io.IOException;
    Code:
       0: new           #53                 // class org/apache/hadoop/hbase/zookeeper/ZKWatcher
       3: dup
       4: aload_0
       5: invokevirtual #37                 // Method getConfiguration:()Lorg/apache/hadoop/conf/Configuration;
       8: ldc           #58                 // String unittest
      10: new           #59                 // class org/apache/hadoop/hbase/HBaseZKTestingUtility$2
      13: dup
      14: invokespecial #60                 // Method org/apache/hadoop/hbase/HBaseZKTestingUtility$2."<init>":()V
      17: invokespecial #57                 // Method org/apache/hadoop/hbase/zookeeper/ZKWatcher."<init>":(Lorg/apache/hadoop/conf/Configuration;Ljava/lang/String;Lorg/apache/hadoop/hbase/Abortable;)V
      20: astore_1
      21: aload_1
      22: areturn

  public boolean cleanupTestDir() throws java.io.IOException;
    Code:
       0: aload_0
       1: invokespecial #61                 // Method org/apache/hadoop/hbase/HBaseCommonTestingUtility.cleanupTestDir:()Z
       4: istore_1
       5: aload_0
       6: aload_0
       7: getfield      #4                  // Field clusterTestDir:Ljava/io/File;
      10: invokevirtual #62                 // Method deleteDir:(Ljava/io/File;)Z
      13: ifeq          25
      16: aload_0
      17: aconst_null
      18: putfield      #4                  // Field clusterTestDir:Ljava/io/File;
      21: iload_1
      22: iconst_1
      23: iand
      24: ireturn
      25: iconst_0
      26: ireturn
}
