Compiled from "HBaseClassTestRuleChecker.java"
public class org.apache.hadoop.hbase.HBaseClassTestRuleChecker extends org.junit.runner.notification.RunListener {
  public org.apache.hadoop.hbase.HBaseClassTestRuleChecker();
    Code:
       0: aload_0
       1: invokespecial #1                  // Method org/junit/runner/notification/RunListener."<init>":()V
       4: return

  public void testStarted(org.junit.runner.Description) throws java.lang.Exception;
    Code:
       0: aload_1
       1: invokevirtual #2                  // Method org/junit/runner/Description.getTestClass:()Ljava/lang/Class;
       4: ldc           #3                  // class org/junit/experimental/categories/Category
       6: invokevirtual #4                  // Method java/lang/Class.getAnnotationsByType:(Ljava/lang/Class;)[Ljava/lang/annotation/Annotation;
       9: checkcast     #5                  // class "[Lorg/junit/experimental/categories/Category;"
      12: astore_2
      13: aload_2
      14: iconst_0
      15: aaload
      16: invokeinterface #6,  1            // InterfaceMethod org/junit/experimental/categories/Category.value:()[Ljava/lang/Class;
      21: astore_3
      22: aload_3
      23: arraylength
      24: istore        4
      26: iconst_0
      27: istore        5
      29: iload         5
      31: iload         4
      33: if_icmpge     56
      36: aload_3
      37: iload         5
      39: aaload
      40: astore        6
      42: aload         6
      44: ldc           #7                  // class org/apache/hadoop/hbase/testclassification/IntegrationTests
      46: if_acmpne     50
      49: return
      50: iinc          5, 1
      53: goto          29
      56: aload_1
      57: invokevirtual #2                  // Method org/junit/runner/Description.getTestClass:()Ljava/lang/Class;
      60: invokevirtual #8                  // Method java/lang/Class.getFields:()[Ljava/lang/reflect/Field;
      63: astore_3
      64: aload_3
      65: arraylength
      66: istore        4
      68: iconst_0
      69: istore        5
      71: iload         5
      73: iload         4
      75: if_icmpge     186
      78: aload_3
      79: iload         5
      81: aaload
      82: astore        6
      84: aload         6
      86: invokevirtual #9                  // Method java/lang/reflect/Field.getModifiers:()I
      89: invokestatic  #10                 // Method java/lang/reflect/Modifier.isStatic:(I)Z
      92: ifeq          180
      95: aload         6
      97: invokevirtual #11                 // Method java/lang/reflect/Field.getType:()Ljava/lang/Class;
     100: ldc           #12                 // class org/apache/hadoop/hbase/HBaseClassTestRule
     102: if_acmpne     180
     105: aload         6
     107: ldc           #13                 // class org/junit/ClassRule
     109: invokevirtual #14                 // Method java/lang/reflect/Field.isAnnotationPresent:(Ljava/lang/Class;)Z
     112: ifeq          180
     115: aload         6
     117: aconst_null
     118: invokevirtual #15                 // Method java/lang/reflect/Field.get:(Ljava/lang/Object;)Ljava/lang/Object;
     121: checkcast     #12                 // class org/apache/hadoop/hbase/HBaseClassTestRule
     124: astore        7
     126: new           #16                 // class java/lang/StringBuilder
     129: dup
     130: invokespecial #17                 // Method java/lang/StringBuilder."<init>":()V
     133: ldc           #18                 // String The HBaseClassTestRule ClassRule in
     135: invokevirtual #19                 // Method java/lang/StringBuilder.append:(Ljava/lang/String;)Ljava/lang/StringBuilder;
     138: aload_1
     139: invokevirtual #2                  // Method org/junit/runner/Description.getTestClass:()Ljava/lang/Class;
     142: invokevirtual #20                 // Method java/lang/Class.getName:()Ljava/lang/String;
     145: invokevirtual #19                 // Method java/lang/StringBuilder.append:(Ljava/lang/String;)Ljava/lang/StringBuilder;
     148: ldc           #21                 // String  is for
     150: invokevirtual #19                 // Method java/lang/StringBuilder.append:(Ljava/lang/String;)Ljava/lang/StringBuilder;
     153: aload         7
     155: invokevirtual #22                 // Method org/apache/hadoop/hbase/HBaseClassTestRule.getClazz:()Ljava/lang/Class;
     158: invokevirtual #20                 // Method java/lang/Class.getName:()Ljava/lang/String;
     161: invokevirtual #19                 // Method java/lang/StringBuilder.append:(Ljava/lang/String;)Ljava/lang/StringBuilder;
     164: invokevirtual #23                 // Method java/lang/StringBuilder.toString:()Ljava/lang/String;
     167: aload_1
     168: invokevirtual #2                  // Method org/junit/runner/Description.getTestClass:()Ljava/lang/Class;
     171: aload         7
     173: invokevirtual #22                 // Method org/apache/hadoop/hbase/HBaseClassTestRule.getClazz:()Ljava/lang/Class;
     176: invokestatic  #24                 // Method org/junit/Assert.assertEquals:(Ljava/lang/String;Ljava/lang/Object;Ljava/lang/Object;)V
     179: return
     180: iinc          5, 1
     183: goto          71
     186: new           #16                 // class java/lang/StringBuilder
     189: dup
     190: invokespecial #17                 // Method java/lang/StringBuilder."<init>":()V
     193: ldc           #25                 // String No HBaseClassTestRule ClassRule for
     195: invokevirtual #19                 // Method java/lang/StringBuilder.append:(Ljava/lang/String;)Ljava/lang/StringBuilder;
     198: aload_1
     199: invokevirtual #2                  // Method org/junit/runner/Description.getTestClass:()Ljava/lang/Class;
     202: invokevirtual #20                 // Method java/lang/Class.getName:()Ljava/lang/String;
     205: invokevirtual #19                 // Method java/lang/StringBuilder.append:(Ljava/lang/String;)Ljava/lang/StringBuilder;
     208: invokevirtual #23                 // Method java/lang/StringBuilder.toString:()Ljava/lang/String;
     211: invokestatic  #26                 // Method org/junit/Assert.fail:(Ljava/lang/String;)V
     214: return
}
