Compiled from "HBaseHbck.java"
public class org.apache.hadoop.hbase.client.HBaseHbck implements org.apache.hadoop.hbase.client.Hbck {
  org.apache.hadoop.hbase.client.HBaseHbck(org.apache.hadoop.hbase.shaded.protobuf.generated.MasterProtos$HbckService$BlockingInterface, org.apache.hadoop.hbase.ipc.RpcControllerFactory);
    Code:
       0: aload_0
       1: invokespecial #4                  // Method java/lang/Object."<init>":()V
       4: aload_0
       5: aload_1
       6: putfield      #2                  // Field hbck:Lorg/apache/hadoop/hbase/shaded/protobuf/generated/MasterProtos$HbckService$BlockingInterface;
       9: aload_0
      10: aload_2
      11: putfield      #3                  // Field rpcControllerFactory:Lorg/apache/hadoop/hbase/ipc/RpcControllerFactory;
      14: return

  public void close() throws java.io.IOException;
    Code:
       0: return

  public void abort(java.lang.String, java.lang.Throwable);
    Code:
       0: aload_0
       1: iconst_1
       2: putfield      #5                  // Field aborted:Z
       5: new           #6                  // class java/lang/RuntimeException
       8: dup
       9: aload_1
      10: aload_2
      11: invokespecial #7                  // Method java/lang/RuntimeException."<init>":(Ljava/lang/String;Ljava/lang/Throwable;)V
      14: athrow

  public boolean isAborted();
    Code:
       0: aload_0
       1: getfield      #5                  // Field aborted:Z
       4: ireturn

  public org.apache.hadoop.hbase.client.TableState setTableStateInMeta(org.apache.hadoop.hbase.client.TableState) throws java.io.IOException;
    Code:
       0: aload_0
       1: getfield      #2                  // Field hbck:Lorg/apache/hadoop/hbase/shaded/protobuf/generated/MasterProtos$HbckService$BlockingInterface;
       4: aload_0
       5: getfield      #3                  // Field rpcControllerFactory:Lorg/apache/hadoop/hbase/ipc/RpcControllerFactory;
       8: invokevirtual #8                  // Method org/apache/hadoop/hbase/ipc/RpcControllerFactory.newController:()Lorg/apache/hadoop/hbase/ipc/HBaseRpcController;
      11: aload_1
      12: invokestatic  #9                  // Method org/apache/hadoop/hbase/shaded/protobuf/RequestConverter.buildSetTableStateInMetaRequest:(Lorg/apache/hadoop/hbase/client/TableState;)Lorg/apache/hadoop/hbase/shaded/protobuf/generated/MasterProtos$SetTableStateInMetaRequest;
      15: invokeinterface #10,  3           // InterfaceMethod org/apache/hadoop/hbase/shaded/protobuf/generated/MasterProtos$HbckService$BlockingInterface.setTableStateInMeta:(Lorg/apache/hbase/thirdparty/com/google/protobuf/RpcController;Lorg/apache/hadoop/hbase/shaded/protobuf/generated/MasterProtos$SetTableStateInMetaRequest;)Lorg/apache/hadoop/hbase/shaded/protobuf/generated/MasterProtos$GetTableStateResponse;
      20: astore_2
      21: aload_1
      22: invokevirtual #11                 // Method org/apache/hadoop/hbase/client/TableState.getTableName:()Lorg/apache/hadoop/hbase/TableName;
      25: aload_2
      26: invokevirtual #12                 // Method org/apache/hadoop/hbase/shaded/protobuf/generated/MasterProtos$GetTableStateResponse.getTableState:()Lorg/apache/hadoop/hbase/shaded/protobuf/generated/HBaseProtos$TableState;
      29: invokestatic  #13                 // Method org/apache/hadoop/hbase/client/TableState.convert:(Lorg/apache/hadoop/hbase/TableName;Lorg/apache/hadoop/hbase/shaded/protobuf/generated/HBaseProtos$TableState;)Lorg/apache/hadoop/hbase/client/TableState;
      32: areturn
      33: astore_2
      34: getstatic     #1                  // Field LOG:Lorg/slf4j/Logger;
      37: ldc           #15                 // String table={}, state={}
      39: iconst_3
      40: anewarray     #16                 // class java/lang/Object
      43: dup
      44: iconst_0
      45: aload_1
      46: invokevirtual #11                 // Method org/apache/hadoop/hbase/client/TableState.getTableName:()Lorg/apache/hadoop/hbase/TableName;
      49: aastore
      50: dup
      51: iconst_1
      52: aload_1
      53: invokevirtual #17                 // Method org/apache/hadoop/hbase/client/TableState.getState:()Lorg/apache/hadoop/hbase/client/TableState$State;
      56: aastore
      57: dup
      58: iconst_2
      59: aload_2
      60: aastore
      61: invokeinterface #18,  3           // InterfaceMethod org/slf4j/Logger.debug:(Ljava/lang/String;[Ljava/lang/Object;)V
      66: new           #19                 // class java/io/IOException
      69: dup
      70: aload_2
      71: invokespecial #20                 // Method java/io/IOException."<init>":(Ljava/lang/Throwable;)V
      74: athrow
    Exception table:
       from    to  target type
           0    32    33   Class org/apache/hbase/thirdparty/com/google/protobuf/ServiceException

  public java.util.List<java.lang.Long> assigns(java.util.List<java.lang.String>, boolean) throws java.io.IOException;
    Code:
       0: aload_0
       1: getfield      #2                  // Field hbck:Lorg/apache/hadoop/hbase/shaded/protobuf/generated/MasterProtos$HbckService$BlockingInterface;
       4: aload_0
       5: getfield      #3                  // Field rpcControllerFactory:Lorg/apache/hadoop/hbase/ipc/RpcControllerFactory;
       8: invokevirtual #8                  // Method org/apache/hadoop/hbase/ipc/RpcControllerFactory.newController:()Lorg/apache/hadoop/hbase/ipc/HBaseRpcController;
      11: aload_1
      12: iload_2
      13: invokestatic  #21                 // Method org/apache/hadoop/hbase/shaded/protobuf/RequestConverter.toAssignRegionsRequest:(Ljava/util/List;Z)Lorg/apache/hadoop/hbase/shaded/protobuf/generated/MasterProtos$AssignsRequest;
      16: invokeinterface #22,  3           // InterfaceMethod org/apache/hadoop/hbase/shaded/protobuf/generated/MasterProtos$HbckService$BlockingInterface.assigns:(Lorg/apache/hbase/thirdparty/com/google/protobuf/RpcController;Lorg/apache/hadoop/hbase/shaded/protobuf/generated/MasterProtos$AssignsRequest;)Lorg/apache/hadoop/hbase/shaded/protobuf/generated/MasterProtos$AssignsResponse;
      21: astore_3
      22: aload_3
      23: invokevirtual #23                 // Method org/apache/hadoop/hbase/shaded/protobuf/generated/MasterProtos$AssignsResponse.getPidList:()Ljava/util/List;
      26: areturn
      27: astore_3
      28: getstatic     #1                  // Field LOG:Lorg/slf4j/Logger;
      31: aload_1
      32: invokestatic  #24                 // Method toCommaDelimitedString:(Ljava/util/List;)Ljava/lang/String;
      35: aload_3
      36: invokeinterface #25,  3           // InterfaceMethod org/slf4j/Logger.debug:(Ljava/lang/String;Ljava/lang/Throwable;)V
      41: new           #19                 // class java/io/IOException
      44: dup
      45: aload_3
      46: invokespecial #20                 // Method java/io/IOException."<init>":(Ljava/lang/Throwable;)V
      49: athrow
    Exception table:
       from    to  target type
           0    26    27   Class org/apache/hbase/thirdparty/com/google/protobuf/ServiceException

  public java.util.List<java.lang.Long> unassigns(java.util.List<java.lang.String>, boolean) throws java.io.IOException;
    Code:
       0: aload_0
       1: getfield      #2                  // Field hbck:Lorg/apache/hadoop/hbase/shaded/protobuf/generated/MasterProtos$HbckService$BlockingInterface;
       4: aload_0
       5: getfield      #3                  // Field rpcControllerFactory:Lorg/apache/hadoop/hbase/ipc/RpcControllerFactory;
       8: invokevirtual #8                  // Method org/apache/hadoop/hbase/ipc/RpcControllerFactory.newController:()Lorg/apache/hadoop/hbase/ipc/HBaseRpcController;
      11: aload_1
      12: iload_2
      13: invokestatic  #26                 // Method org/apache/hadoop/hbase/shaded/protobuf/RequestConverter.toUnassignRegionsRequest:(Ljava/util/List;Z)Lorg/apache/hadoop/hbase/shaded/protobuf/generated/MasterProtos$UnassignsRequest;
      16: invokeinterface #27,  3           // InterfaceMethod org/apache/hadoop/hbase/shaded/protobuf/generated/MasterProtos$HbckService$BlockingInterface.unassigns:(Lorg/apache/hbase/thirdparty/com/google/protobuf/RpcController;Lorg/apache/hadoop/hbase/shaded/protobuf/generated/MasterProtos$UnassignsRequest;)Lorg/apache/hadoop/hbase/shaded/protobuf/generated/MasterProtos$UnassignsResponse;
      21: astore_3
      22: aload_3
      23: invokevirtual #28                 // Method org/apache/hadoop/hbase/shaded/protobuf/generated/MasterProtos$UnassignsResponse.getPidList:()Ljava/util/List;
      26: areturn
      27: astore_3
      28: getstatic     #1                  // Field LOG:Lorg/slf4j/Logger;
      31: aload_1
      32: invokestatic  #24                 // Method toCommaDelimitedString:(Ljava/util/List;)Ljava/lang/String;
      35: aload_3
      36: invokeinterface #25,  3           // InterfaceMethod org/slf4j/Logger.debug:(Ljava/lang/String;Ljava/lang/Throwable;)V
      41: new           #19                 // class java/io/IOException
      44: dup
      45: aload_3
      46: invokespecial #20                 // Method java/io/IOException."<init>":(Ljava/lang/Throwable;)V
      49: athrow
    Exception table:
       from    to  target type
           0    26    27   Class org/apache/hbase/thirdparty/com/google/protobuf/ServiceException

  public java.util.List<java.lang.Boolean> bypassProcedure(java.util.List<java.lang.Long>, long, boolean, boolean) throws java.io.IOException;
    Code:
       0: new           #34                 // class org/apache/hadoop/hbase/client/HBaseHbck$1
       3: dup
       4: aload_0
       5: aload_1
       6: lload_2
       7: iload         4
       9: iload         5
      11: invokespecial #35                 // Method org/apache/hadoop/hbase/client/HBaseHbck$1."<init>":(Lorg/apache/hadoop/hbase/client/HBaseHbck;Ljava/util/List;JZZ)V
      14: invokestatic  #36                 // Method org/apache/hadoop/hbase/shaded/protobuf/ProtobufUtil.call:(Ljava/util/concurrent/Callable;)Ljava/lang/Object;
      17: checkcast     #37                 // class org/apache/hadoop/hbase/shaded/protobuf/generated/MasterProtos$BypassProcedureResponse
      20: astore        6
      22: aload         6
      24: invokevirtual #38                 // Method org/apache/hadoop/hbase/shaded/protobuf/generated/MasterProtos$BypassProcedureResponse.getBypassedList:()Ljava/util/List;
      27: areturn

  public java.util.List<java.lang.Long> scheduleServerCrashProcedure(java.util.List<org.apache.hadoop.hbase.shaded.protobuf.generated.HBaseProtos$ServerName>) throws java.io.IOException;
    Code:
       0: aload_0
       1: getfield      #2                  // Field hbck:Lorg/apache/hadoop/hbase/shaded/protobuf/generated/MasterProtos$HbckService$BlockingInterface;
       4: aload_0
       5: getfield      #3                  // Field rpcControllerFactory:Lorg/apache/hadoop/hbase/ipc/RpcControllerFactory;
       8: invokevirtual #8                  // Method org/apache/hadoop/hbase/ipc/RpcControllerFactory.newController:()Lorg/apache/hadoop/hbase/ipc/HBaseRpcController;
      11: aload_1
      12: invokestatic  #39                 // Method org/apache/hadoop/hbase/shaded/protobuf/RequestConverter.toScheduleServerCrashProcedureRequest:(Ljava/util/List;)Lorg/apache/hadoop/hbase/shaded/protobuf/generated/MasterProtos$ScheduleServerCrashProcedureRequest;
      15: invokeinterface #40,  3           // InterfaceMethod org/apache/hadoop/hbase/shaded/protobuf/generated/MasterProtos$HbckService$BlockingInterface.scheduleServerCrashProcedure:(Lorg/apache/hbase/thirdparty/com/google/protobuf/RpcController;Lorg/apache/hadoop/hbase/shaded/protobuf/generated/MasterProtos$ScheduleServerCrashProcedureRequest;)Lorg/apache/hadoop/hbase/shaded/protobuf/generated/MasterProtos$ScheduleServerCrashProcedureResponse;
      20: astore_2
      21: aload_2
      22: invokevirtual #41                 // Method org/apache/hadoop/hbase/shaded/protobuf/generated/MasterProtos$ScheduleServerCrashProcedureResponse.getPidList:()Ljava/util/List;
      25: areturn
      26: astore_2
      27: getstatic     #1                  // Field LOG:Lorg/slf4j/Logger;
      30: aload_1
      31: invokeinterface #29,  1           // InterfaceMethod java/util/List.stream:()Ljava/util/stream/Stream;
      36: invokedynamic #42,  0             // InvokeDynamic #0:apply:()Ljava/util/function/Function;
      41: invokeinterface #43,  2           // InterfaceMethod java/util/stream/Stream.map:(Ljava/util/function/Function;)Ljava/util/stream/Stream;
      46: invokestatic  #44                 // Method java/util/stream/Collectors.toList:()Ljava/util/stream/Collector;
      49: invokeinterface #32,  2           // InterfaceMethod java/util/stream/Stream.collect:(Ljava/util/stream/Collector;)Ljava/lang/Object;
      54: checkcast     #45                 // class java/util/List
      57: invokestatic  #24                 // Method toCommaDelimitedString:(Ljava/util/List;)Ljava/lang/String;
      60: aload_2
      61: invokeinterface #25,  3           // InterfaceMethod org/slf4j/Logger.debug:(Ljava/lang/String;Ljava/lang/Throwable;)V
      66: new           #19                 // class java/io/IOException
      69: dup
      70: aload_2
      71: invokespecial #20                 // Method java/io/IOException."<init>":(Ljava/lang/Throwable;)V
      74: athrow
    Exception table:
       from    to  target type
           0    25    26   Class org/apache/hbase/thirdparty/com/google/protobuf/ServiceException

  public java.util.Map<java.lang.String, org.apache.hadoop.hbase.shaded.protobuf.generated.MasterProtos$RegionErrorType> getFailedSplitMergeLegacyRegions(java.util.List<org.apache.hadoop.hbase.TableName>) throws java.io.IOException;
    Code:
       0: aload_0
       1: getfield      #2                  // Field hbck:Lorg/apache/hadoop/hbase/shaded/protobuf/generated/MasterProtos$HbckService$BlockingInterface;
       4: aload_0
       5: getfield      #3                  // Field rpcControllerFactory:Lorg/apache/hadoop/hbase/ipc/RpcControllerFactory;
       8: invokevirtual #8                  // Method org/apache/hadoop/hbase/ipc/RpcControllerFactory.newController:()Lorg/apache/hadoop/hbase/ipc/HBaseRpcController;
      11: aload_1
      12: invokestatic  #46                 // Method org/apache/hadoop/hbase/shaded/protobuf/RequestConverter.toGetFailedSplitMergeLegacyRegionsRequest:(Ljava/util/List;)Lorg/apache/hadoop/hbase/shaded/protobuf/generated/MasterProtos$GetFailedSplitMergeLegacyRegionsRequest;
      15: invokeinterface #47,  3           // InterfaceMethod org/apache/hadoop/hbase/shaded/protobuf/generated/MasterProtos$HbckService$BlockingInterface.getFailedSplitMergeLegacyRegions:(Lorg/apache/hbase/thirdparty/com/google/protobuf/RpcController;Lorg/apache/hadoop/hbase/shaded/protobuf/generated/MasterProtos$GetFailedSplitMergeLegacyRegionsRequest;)Lorg/apache/hadoop/hbase/shaded/protobuf/generated/MasterProtos$GetFailedSplitMergeLegacyRegionsResponse;
      20: astore_2
      21: aload_2
      22: invokevirtual #48                 // Method org/apache/hadoop/hbase/shaded/protobuf/generated/MasterProtos$GetFailedSplitMergeLegacyRegionsResponse.getErrorsMap:()Ljava/util/Map;
      25: areturn
      26: astore_2
      27: getstatic     #1                  // Field LOG:Lorg/slf4j/Logger;
      30: ldc           #49                 // String get failed split/merge legacy regions failed
      32: aload_2
      33: invokeinterface #25,  3           // InterfaceMethod org/slf4j/Logger.debug:(Ljava/lang/String;Ljava/lang/Throwable;)V
      38: new           #19                 // class java/io/IOException
      41: dup
      42: aload_2
      43: invokespecial #20                 // Method java/io/IOException."<init>":(Ljava/lang/Throwable;)V
      46: athrow
    Exception table:
       from    to  target type
           0    25    26   Class org/apache/hbase/thirdparty/com/google/protobuf/ServiceException

  static org.apache.hadoop.hbase.ipc.RpcControllerFactory access$000(org.apache.hadoop.hbase.client.HBaseHbck);
    Code:
       0: aload_0
       1: getfield      #3                  // Field rpcControllerFactory:Lorg/apache/hadoop/hbase/ipc/RpcControllerFactory;
       4: areturn

  static org.apache.hadoop.hbase.shaded.protobuf.generated.MasterProtos$HbckService$BlockingInterface access$100(org.apache.hadoop.hbase.client.HBaseHbck);
    Code:
       0: aload_0
       1: getfield      #2                  // Field hbck:Lorg/apache/hadoop/hbase/shaded/protobuf/generated/MasterProtos$HbckService$BlockingInterface;
       4: areturn

  static org.slf4j.Logger access$200();
    Code:
       0: getstatic     #1                  // Field LOG:Lorg/slf4j/Logger;
       3: areturn

  static {};
    Code:
       0: ldc           #52                 // class org/apache/hadoop/hbase/client/HBaseHbck
       2: invokestatic  #53                 // Method org/slf4j/LoggerFactory.getLogger:(Ljava/lang/Class;)Lorg/slf4j/Logger;
       5: putstatic     #1                  // Field LOG:Lorg/slf4j/Logger;
       8: return
}
