Compiled from "HBaseHbck.java"
class org.apache.hadoop.hbase.client.HBaseHbck$1 implements java.util.concurrent.Callable<org.apache.hadoop.hbase.shaded.protobuf.generated.MasterProtos$BypassProcedureResponse> {
  final java.util.List val$pids;

  final long val$waitTime;

  final boolean val$override;

  final boolean val$recursive;

  final org.apache.hadoop.hbase.client.HBaseHbck this$0;

  org.apache.hadoop.hbase.client.HBaseHbck$1(org.apache.hadoop.hbase.client.HBaseHbck, java.util.List, long, boolean, boolean);
    Code:
       0: aload_0
       1: aload_1
       2: putfield      #1                  // Field this$0:Lorg/apache/hadoop/hbase/client/HBaseHbck;
       5: aload_0
       6: aload_2
       7: putfield      #2                  // Field val$pids:Ljava/util/List;
      10: aload_0
      11: lload_3
      12: putfield      #3                  // Field val$waitTime:J
      15: aload_0
      16: iload         5
      18: putfield      #4                  // Field val$override:Z
      21: aload_0
      22: iload         6
      24: putfield      #5                  // Field val$recursive:Z
      27: aload_0
      28: invokespecial #6                  // Method java/lang/Object."<init>":()V
      31: return

  public org.apache.hadoop.hbase.shaded.protobuf.generated.MasterProtos$BypassProcedureResponse call() throws java.lang.Exception;
    Code:
       0: aload_0
       1: getfield      #1                  // Field this$0:Lorg/apache/hadoop/hbase/client/HBaseHbck;
       4: invokestatic  #7                  // Method org/apache/hadoop/hbase/client/HBaseHbck.access$100:(Lorg/apache/hadoop/hbase/client/HBaseHbck;)Lorg/apache/hadoop/hbase/shaded/protobuf/generated/MasterProtos$HbckService$BlockingInterface;
       7: aload_0
       8: getfield      #1                  // Field this$0:Lorg/apache/hadoop/hbase/client/HBaseHbck;
      11: invokestatic  #8                  // Method org/apache/hadoop/hbase/client/HBaseHbck.access$000:(Lorg/apache/hadoop/hbase/client/HBaseHbck;)Lorg/apache/hadoop/hbase/ipc/RpcControllerFactory;
      14: invokevirtual #9                  // Method org/apache/hadoop/hbase/ipc/RpcControllerFactory.newController:()Lorg/apache/hadoop/hbase/ipc/HBaseRpcController;
      17: invokestatic  #10                 // Method org/apache/hadoop/hbase/shaded/protobuf/generated/MasterProtos$BypassProcedureRequest.newBuilder:()Lorg/apache/hadoop/hbase/shaded/protobuf/generated/MasterProtos$BypassProcedureRequest$Builder;
      20: aload_0
      21: getfield      #2                  // Field val$pids:Ljava/util/List;
      24: invokevirtual #11                 // Method org/apache/hadoop/hbase/shaded/protobuf/generated/MasterProtos$BypassProcedureRequest$Builder.addAllProcId:(Ljava/lang/Iterable;)Lorg/apache/hadoop/hbase/shaded/protobuf/generated/MasterProtos$BypassProcedureRequest$Builder;
      27: aload_0
      28: getfield      #3                  // Field val$waitTime:J
      31: invokevirtual #12                 // Method org/apache/hadoop/hbase/shaded/protobuf/generated/MasterProtos$BypassProcedureRequest$Builder.setWaitTime:(J)Lorg/apache/hadoop/hbase/shaded/protobuf/generated/MasterProtos$BypassProcedureRequest$Builder;
      34: aload_0
      35: getfield      #4                  // Field val$override:Z
      38: invokevirtual #13                 // Method org/apache/hadoop/hbase/shaded/protobuf/generated/MasterProtos$BypassProcedureRequest$Builder.setOverride:(Z)Lorg/apache/hadoop/hbase/shaded/protobuf/generated/MasterProtos$BypassProcedureRequest$Builder;
      41: aload_0
      42: getfield      #5                  // Field val$recursive:Z
      45: invokevirtual #14                 // Method org/apache/hadoop/hbase/shaded/protobuf/generated/MasterProtos$BypassProcedureRequest$Builder.setRecursive:(Z)Lorg/apache/hadoop/hbase/shaded/protobuf/generated/MasterProtos$BypassProcedureRequest$Builder;
      48: invokevirtual #15                 // Method org/apache/hadoop/hbase/shaded/protobuf/generated/MasterProtos$BypassProcedureRequest$Builder.build:()Lorg/apache/hadoop/hbase/shaded/protobuf/generated/MasterProtos$BypassProcedureRequest;
      51: invokeinterface #16,  3           // InterfaceMethod org/apache/hadoop/hbase/shaded/protobuf/generated/MasterProtos$HbckService$BlockingInterface.bypassProcedure:(Lorg/apache/hbase/thirdparty/com/google/protobuf/RpcController;Lorg/apache/hadoop/hbase/shaded/protobuf/generated/MasterProtos$BypassProcedureRequest;)Lorg/apache/hadoop/hbase/shaded/protobuf/generated/MasterProtos$BypassProcedureResponse;
      56: areturn
      57: astore_1
      58: invokestatic  #18                 // Method org/apache/hadoop/hbase/client/HBaseHbck.access$200:()Lorg/slf4j/Logger;
      61: aload_0
      62: getfield      #2                  // Field val$pids:Ljava/util/List;
      65: invokeinterface #19,  1           // InterfaceMethod java/util/List.stream:()Ljava/util/stream/Stream;
      70: invokedynamic #20,  0             // InvokeDynamic #0:apply:()Ljava/util/function/Function;
      75: invokeinterface #21,  2           // InterfaceMethod java/util/stream/Stream.map:(Ljava/util/function/Function;)Ljava/util/stream/Stream;
      80: ldc           #22                 // String ,
      82: invokestatic  #23                 // Method java/util/stream/Collectors.joining:(Ljava/lang/CharSequence;)Ljava/util/stream/Collector;
      85: invokeinterface #24,  2           // InterfaceMethod java/util/stream/Stream.collect:(Ljava/util/stream/Collector;)Ljava/lang/Object;
      90: checkcast     #25                 // class java/lang/String
      93: aload_1
      94: invokeinterface #26,  3           // InterfaceMethod org/slf4j/Logger.error:(Ljava/lang/String;Ljava/lang/Throwable;)V
      99: aload_1
     100: athrow
    Exception table:
       from    to  target type
           0    56    57   Class java/lang/Throwable

  public java.lang.Object call() throws java.lang.Exception;
    Code:
       0: aload_0
       1: invokevirtual #27                 // Method call:()Lorg/apache/hadoop/hbase/shaded/protobuf/generated/MasterProtos$BypassProcedureResponse;
       4: areturn
}
