Compiled from "Hbck.java"
public interface org.apache.hadoop.hbase.client.Hbck extends org.apache.hadoop.hbase.Abortable,java.io.Closeable {
  public abstract org.apache.hadoop.hbase.client.TableState setTableStateInMeta(org.apache.hadoop.hbase.client.TableState) throws java.io.IOException;

  public abstract java.util.List<java.lang.Long> assigns(java.util.List<java.lang.String>, boolean) throws java.io.IOException;

  public java.util.List<java.lang.Long> assigns(java.util.List<java.lang.String>) throws java.io.IOException;
    Code:
       0: aload_0
       1: aload_1
       2: iconst_0
       3: invokeinterface #1,  3            // InterfaceMethod assigns:(Ljava/util/List;Z)Ljava/util/List;
       8: areturn

  public abstract java.util.List<java.lang.Long> unassigns(java.util.List<java.lang.String>, boolean) throws java.io.IOException;

  public java.util.List<java.lang.Long> unassigns(java.util.List<java.lang.String>) throws java.io.IOException;
    Code:
       0: aload_0
       1: aload_1
       2: iconst_0
       3: invokeinterface #2,  3            // InterfaceMethod unassigns:(Ljava/util/List;Z)Ljava/util/List;
       8: areturn

  public abstract java.util.List<java.lang.Boolean> bypassProcedure(java.util.List<java.lang.Long>, long, boolean, boolean) throws java.io.IOException;

  public abstract java.util.List<java.lang.Long> scheduleServerCrashProcedure(java.util.List<org.apache.hadoop.hbase.shaded.protobuf.generated.HBaseProtos$ServerName>) throws java.io.IOException;

  public abstract java.util.Map<java.lang.String, org.apache.hadoop.hbase.shaded.protobuf.generated.MasterProtos$RegionErrorType> getFailedSplitMergeLegacyRegions(java.util.List<org.apache.hadoop.hbase.TableName>) throws java.io.IOException;
}
