Compiled from "HbckTestingUtil.java"
public class org.apache.hadoop.hbase.util.hbck.HbckTestingUtil {
  public org.apache.hadoop.hbase.util.hbck.HbckTestingUtil();
    Code:
       0: aload_0
       1: invokespecial #1                  // Method java/lang/Object."<init>":()V
       4: return

  public static org.apache.hadoop.hbase.util.HBaseFsck doFsck(org.apache.hadoop.conf.Configuration, boolean) throws java.lang.Exception;
    Code:
       0: aload_0
       1: iload_1
       2: aconst_null
       3: invokestatic  #2                  // Method doFsck:(Lorg/apache/hadoop/conf/Configuration;ZLorg/apache/hadoop/hbase/TableName;)Lorg/apache/hadoop/hbase/util/HBaseFsck;
       6: areturn

  public static org.apache.hadoop.hbase.util.HBaseFsck doFsck(org.apache.hadoop.conf.Configuration, boolean, org.apache.hadoop.hbase.TableName) throws java.lang.Exception;
    Code:
       0: aload_0
       1: iload_1
       2: iload_1
       3: iload_1
       4: iload_1
       5: iload_1
       6: iload_1
       7: iload_1
       8: iload_1
       9: iload_1
      10: iload_1
      11: iload_1
      12: iload_1
      13: iload_1
      14: aload_2
      15: invokestatic  #3                  // Method doFsck:(Lorg/apache/hadoop/conf/Configuration;ZZZZZZZZZZZZZLorg/apache/hadoop/hbase/TableName;)Lorg/apache/hadoop/hbase/util/HBaseFsck;
      18: areturn

  public static org.apache.hadoop.hbase.util.HBaseFsck doFsck(org.apache.hadoop.conf.Configuration, boolean, boolean, boolean, boolean, boolean, boolean, boolean, boolean, boolean, boolean, boolean, boolean, boolean, org.apache.hadoop.hbase.TableName) throws java.lang.Exception;
    Code:
       0: new           #4                  // class org/apache/hadoop/hbase/util/HBaseFsck
       3: dup
       4: aload_0
       5: getstatic     #5                  // Field exec:Ljava/util/concurrent/ExecutorService;
       8: invokespecial #6                  // Method org/apache/hadoop/hbase/util/HBaseFsck."<init>":(Lorg/apache/hadoop/conf/Configuration;Ljava/util/concurrent/ExecutorService;)V
      11: astore        15
      13: invokestatic  #7                  // Method org/apache/hadoop/hbase/util/HBaseFsck.setDisplayFullReport:()V
      16: aload         15
      18: lconst_0
      19: invokevirtual #8                  // Method org/apache/hadoop/hbase/util/HBaseFsck.setTimeLag:(J)V
      22: aload         15
      24: iload_1
      25: invokevirtual #9                  // Method org/apache/hadoop/hbase/util/HBaseFsck.setFixAssignments:(Z)V
      28: aload         15
      30: iload_2
      31: invokevirtual #10                 // Method org/apache/hadoop/hbase/util/HBaseFsck.setFixMeta:(Z)V
      34: aload         15
      36: iload_3
      37: invokevirtual #11                 // Method org/apache/hadoop/hbase/util/HBaseFsck.setFixHdfsHoles:(Z)V
      40: aload         15
      42: iload         4
      44: invokevirtual #12                 // Method org/apache/hadoop/hbase/util/HBaseFsck.setFixHdfsOverlaps:(Z)V
      47: aload         15
      49: iload         5
      51: invokevirtual #13                 // Method org/apache/hadoop/hbase/util/HBaseFsck.setFixHdfsOrphans:(Z)V
      54: aload         15
      56: iload         6
      58: invokevirtual #14                 // Method org/apache/hadoop/hbase/util/HBaseFsck.setFixTableOrphans:(Z)V
      61: aload         15
      63: iload         7
      65: invokevirtual #15                 // Method org/apache/hadoop/hbase/util/HBaseFsck.setFixVersionFile:(Z)V
      68: aload         15
      70: iload         8
      72: invokevirtual #16                 // Method org/apache/hadoop/hbase/util/HBaseFsck.setFixReferenceFiles:(Z)V
      75: aload         15
      77: iload         9
      79: invokevirtual #17                 // Method org/apache/hadoop/hbase/util/HBaseFsck.setFixHFileLinks:(Z)V
      82: aload         15
      84: iload         10
      86: invokevirtual #18                 // Method org/apache/hadoop/hbase/util/HBaseFsck.setFixEmptyMetaCells:(Z)V
      89: aload         15
      91: iload         12
      93: invokevirtual #19                 // Method org/apache/hadoop/hbase/util/HBaseFsck.setFixReplication:(Z)V
      96: aload         15
      98: iload         13
     100: invokevirtual #20                 // Method org/apache/hadoop/hbase/util/HBaseFsck.setCleanReplicationBarrier:(Z)V
     103: aload         14
     105: ifnull        115
     108: aload         15
     110: aload         14
     112: invokevirtual #21                 // Method org/apache/hadoop/hbase/util/HBaseFsck.includeTable:(Lorg/apache/hadoop/hbase/TableName;)V
     115: aload         15
     117: invokevirtual #22                 // Method org/apache/hadoop/hbase/util/HBaseFsck.connect:()V
     120: aload         15
     122: invokevirtual #23                 // Method org/apache/hadoop/hbase/util/HBaseFsck.onlineHbck:()I
     125: pop
     126: aload         15
     128: invokevirtual #24                 // Method org/apache/hadoop/hbase/util/HBaseFsck.close:()V
     131: goto          144
     134: astore        16
     136: aload         15
     138: invokevirtual #24                 // Method org/apache/hadoop/hbase/util/HBaseFsck.close:()V
     141: aload         16
     143: athrow
     144: aload         15
     146: areturn
    Exception table:
       from    to  target type
          13   126   134   any
         134   136   134   any

  public static org.apache.hadoop.hbase.util.HBaseFsck doHFileQuarantine(org.apache.hadoop.conf.Configuration, org.apache.hadoop.hbase.TableName) throws java.lang.Exception;
    Code:
       0: iconst_3
       1: anewarray     #25                 // class java/lang/String
       4: dup
       5: iconst_0
       6: ldc           #26                 // String -sidelineCorruptHFiles
       8: aastore
       9: dup
      10: iconst_1
      11: ldc           #27                 // String -ignorePreCheckPermission
      13: aastore
      14: dup
      15: iconst_2
      16: aload_1
      17: invokevirtual #28                 // Method org/apache/hadoop/hbase/TableName.getNameAsString:()Ljava/lang/String;
      20: aastore
      21: astore_2
      22: new           #4                  // class org/apache/hadoop/hbase/util/HBaseFsck
      25: dup
      26: aload_0
      27: getstatic     #5                  // Field exec:Ljava/util/concurrent/ExecutorService;
      30: invokespecial #6                  // Method org/apache/hadoop/hbase/util/HBaseFsck."<init>":(Lorg/apache/hadoop/conf/Configuration;Ljava/util/concurrent/ExecutorService;)V
      33: astore_3
      34: aload_3
      35: getstatic     #5                  // Field exec:Ljava/util/concurrent/ExecutorService;
      38: aload_2
      39: invokevirtual #29                 // Method org/apache/hadoop/hbase/util/HBaseFsck.exec:(Ljava/util/concurrent/ExecutorService;[Ljava/lang/String;)Lorg/apache/hadoop/hbase/util/HBaseFsck;
      42: pop
      43: aload_3
      44: areturn

  public static boolean cleanReplicationBarrier(org.apache.hadoop.conf.Configuration, org.apache.hadoop.hbase.TableName) throws java.io.IOException, java.lang.ClassNotFoundException;
    Code:
       0: new           #4                  // class org/apache/hadoop/hbase/util/HBaseFsck
       3: dup
       4: aload_0
       5: aconst_null
       6: invokespecial #6                  // Method org/apache/hadoop/hbase/util/HBaseFsck."<init>":(Lorg/apache/hadoop/conf/Configuration;Ljava/util/concurrent/ExecutorService;)V
       9: astore_2
      10: aload_2
      11: aload_1
      12: invokevirtual #28                 // Method org/apache/hadoop/hbase/TableName.getNameAsString:()Ljava/lang/String;
      15: invokevirtual #30                 // Method org/apache/hadoop/hbase/util/HBaseFsck.setCleanReplicationBarrierTable:(Ljava/lang/String;)V
      18: aload_2
      19: iconst_1
      20: invokevirtual #20                 // Method org/apache/hadoop/hbase/util/HBaseFsck.setCleanReplicationBarrier:(Z)V
      23: aload_2
      24: invokevirtual #22                 // Method org/apache/hadoop/hbase/util/HBaseFsck.connect:()V
      27: aload_2
      28: invokevirtual #31                 // Method org/apache/hadoop/hbase/util/HBaseFsck.cleanReplicationBarrier:()V
      31: aload_2
      32: invokevirtual #32                 // Method org/apache/hadoop/hbase/util/HBaseFsck.shouldRerun:()Z
      35: ireturn

  public static boolean inconsistencyFound(org.apache.hadoop.hbase.util.HBaseFsck) throws java.lang.Exception;
    Code:
       0: aload_0
       1: invokevirtual #33                 // Method org/apache/hadoop/hbase/util/HBaseFsck.getErrors:()Lorg/apache/hadoop/hbase/util/HBaseFsck$ErrorReporter;
       4: invokeinterface #34,  1           // InterfaceMethod org/apache/hadoop/hbase/util/HBaseFsck$ErrorReporter.getErrorList:()Ljava/util/ArrayList;
       9: astore_1
      10: aload_1
      11: ifnull        27
      14: aload_1
      15: invokeinterface #35,  1           // InterfaceMethod java/util/List.isEmpty:()Z
      20: ifne          27
      23: iconst_1
      24: goto          28
      27: iconst_0
      28: ireturn

  public static void assertNoErrors(org.apache.hadoop.hbase.util.HBaseFsck) throws java.lang.Exception;
    Code:
       0: aload_0
       1: invokevirtual #33                 // Method org/apache/hadoop/hbase/util/HBaseFsck.getErrors:()Lorg/apache/hadoop/hbase/util/HBaseFsck$ErrorReporter;
       4: invokeinterface #34,  1           // InterfaceMethod org/apache/hadoop/hbase/util/HBaseFsck$ErrorReporter.getErrorList:()Ljava/util/ArrayList;
       9: astore_1
      10: new           #36                 // class java/util/ArrayList
      13: dup
      14: invokespecial #37                 // Method java/util/ArrayList."<init>":()V
      17: aload_1
      18: invokestatic  #38                 // Method org/junit/Assert.assertEquals:(Ljava/lang/Object;Ljava/lang/Object;)V
      21: return

  public static void assertErrors(org.apache.hadoop.hbase.util.HBaseFsck, org.apache.hadoop.hbase.util.HBaseFsck$ErrorReporter$ERROR_CODE[]);
    Code:
       0: aload_0
       1: invokevirtual #33                 // Method org/apache/hadoop/hbase/util/HBaseFsck.getErrors:()Lorg/apache/hadoop/hbase/util/HBaseFsck$ErrorReporter;
       4: invokeinterface #34,  1           // InterfaceMethod org/apache/hadoop/hbase/util/HBaseFsck$ErrorReporter.getErrorList:()Ljava/util/ArrayList;
       9: astore_2
      10: aload_2
      11: invokestatic  #39                 // Method java/util/Collections.sort:(Ljava/util/List;)V
      14: aload_1
      15: invokestatic  #40                 // Method org/apache/hbase/thirdparty/com/google/common/collect/Lists.newArrayList:([Ljava/lang/Object;)Ljava/util/ArrayList;
      18: astore_3
      19: aload_3
      20: invokestatic  #39                 // Method java/util/Collections.sort:(Ljava/util/List;)V
      23: aload_3
      24: aload_2
      25: invokestatic  #38                 // Method org/junit/Assert.assertEquals:(Ljava/lang/Object;Ljava/lang/Object;)V
      28: return

  static {};
    Code:
       0: new           #41                 // class java/util/concurrent/ScheduledThreadPoolExecutor
       3: dup
       4: bipush        10
       6: invokespecial #42                 // Method java/util/concurrent/ScheduledThreadPoolExecutor."<init>":(I)V
       9: putstatic     #5                  // Field exec:Ljava/util/concurrent/ExecutorService;
      12: return
}
