Compiled from "HealthReport.java"
class org.apache.hadoop.hbase.HealthReport {
  org.apache.hadoop.hbase.HealthReport(org.apache.hadoop.hbase.HealthChecker$HealthCheckerExitStatus, java.lang.String);
    Code:
       0: aload_0
       1: invokespecial #1                  // Method java/lang/Object."<init>":()V
       4: aload_0
       5: aload_1
       6: putfield      #2                  // Field status:Lorg/apache/hadoop/hbase/HealthChecker$HealthCheckerExitStatus;
       9: aload_0
      10: aload_2
      11: putfield      #3                  // Field healthReport:Ljava/lang/String;
      14: return

  org.apache.hadoop.hbase.HealthChecker$HealthCheckerExitStatus getStatus();
    Code:
       0: aload_0
       1: getfield      #2                  // Field status:Lorg/apache/hadoop/hbase/HealthChecker$HealthCheckerExitStatus;
       4: areturn

  public java.lang.String toString();
    Code:
       0: new           #4                  // class java/lang/StringBuilder
       3: dup
       4: invokespecial #5                  // Method java/lang/StringBuilder."<init>":()V
       7: aload_0
       8: getfield      #2                  // Field status:Lorg/apache/hadoop/hbase/HealthChecker$HealthCheckerExitStatus;
      11: invokevirtual #6                  // Method java/lang/StringBuilder.append:(Ljava/lang/Object;)Ljava/lang/StringBuilder;
      14: ldc           #7                  // String
      16: invokevirtual #8                  // Method java/lang/StringBuilder.append:(Ljava/lang/String;)Ljava/lang/StringBuilder;
      19: aload_0
      20: getfield      #3                  // Field healthReport:Ljava/lang/String;
      23: invokevirtual #8                  // Method java/lang/StringBuilder.append:(Ljava/lang/String;)Ljava/lang/StringBuilder;
      26: invokevirtual #9                  // Method java/lang/StringBuilder.toString:()Ljava/lang/String;
      29: areturn

  java.lang.String getHealthReport();
    Code:
       0: aload_0
       1: getfield      #3                  // Field healthReport:Ljava/lang/String;
       4: areturn

  public int hashCode();
    Code:
       0: bipush        31
       2: istore_1
       3: iconst_1
       4: istore_2
       5: bipush        31
       7: iload_2
       8: imul
       9: aload_0
      10: getfield      #3                  // Field healthReport:Ljava/lang/String;
      13: ifnonnull     20
      16: iconst_0
      17: goto          27
      20: aload_0
      21: getfield      #3                  // Field healthReport:Ljava/lang/String;
      24: invokevirtual #10                 // Method java/lang/String.hashCode:()I
      27: iadd
      28: istore_2
      29: bipush        31
      31: iload_2
      32: imul
      33: aload_0
      34: getfield      #2                  // Field status:Lorg/apache/hadoop/hbase/HealthChecker$HealthCheckerExitStatus;
      37: ifnonnull     44
      40: iconst_0
      41: goto          51
      44: aload_0
      45: getfield      #2                  // Field status:Lorg/apache/hadoop/hbase/HealthChecker$HealthCheckerExitStatus;
      48: invokevirtual #11                 // Method org/apache/hadoop/hbase/HealthChecker$HealthCheckerExitStatus.hashCode:()I
      51: iadd
      52: istore_2
      53: iload_2
      54: ireturn

  public boolean equals(java.lang.Object);
    Code:
       0: aload_0
       1: aload_1
       2: if_acmpne     7
       5: iconst_1
       6: ireturn
       7: aload_1
       8: ifnonnull     13
      11: iconst_0
      12: ireturn
      13: aload_1
      14: instanceof    #12                 // class org/apache/hadoop/hbase/HealthReport
      17: ifne          22
      20: iconst_0
      21: ireturn
      22: aload_1
      23: checkcast     #12                 // class org/apache/hadoop/hbase/HealthReport
      26: astore_2
      27: aload_0
      28: getfield      #3                  // Field healthReport:Ljava/lang/String;
      31: ifnonnull     43
      34: aload_2
      35: getfield      #3                  // Field healthReport:Ljava/lang/String;
      38: ifnull        59
      41: iconst_0
      42: ireturn
      43: aload_0
      44: getfield      #3                  // Field healthReport:Ljava/lang/String;
      47: aload_2
      48: getfield      #3                  // Field healthReport:Ljava/lang/String;
      51: invokevirtual #13                 // Method java/lang/String.equals:(Ljava/lang/Object;)Z
      54: ifne          59
      57: iconst_0
      58: ireturn
      59: aload_0
      60: getfield      #2                  // Field status:Lorg/apache/hadoop/hbase/HealthChecker$HealthCheckerExitStatus;
      63: aload_2
      64: getfield      #2                  // Field status:Lorg/apache/hadoop/hbase/HealthChecker$HealthCheckerExitStatus;
      67: if_acmpeq     72
      70: iconst_0
      71: ireturn
      72: iconst_1
      73: ireturn
}
