Compiled from "HFileArchiveManager.java"
class org.apache.hadoop.hbase.backup.example.HFileArchiveManager {
  public org.apache.hadoop.hbase.backup.example.HFileArchiveManager(org.apache.hadoop.hbase.client.Connection, org.apache.hadoop.conf.Configuration) throws org.apache.hadoop.hbase.ZooKeeperConnectionException, java.io.IOException;
    Code:
       0: aload_0
       1: invokespecial #1                  // Method java/lang/Object."<init>":()V
       4: aload_0
       5: iconst_0
       6: putfield      #2                  // Field stopped:Z
       9: aload_0
      10: new           #3                  // class org/apache/hadoop/hbase/zookeeper/ZKWatcher
      13: dup
      14: aload_2
      15: new           #4                  // class java/lang/StringBuilder
      18: dup
      19: invokespecial #5                  // Method java/lang/StringBuilder."<init>":()V
      22: ldc           #6                  // String hfileArchiveManager-on-
      24: invokevirtual #7                  // Method java/lang/StringBuilder.append:(Ljava/lang/String;)Ljava/lang/StringBuilder;
      27: aload_1
      28: invokevirtual #8                  // Method java/lang/Object.toString:()Ljava/lang/String;
      31: invokevirtual #7                  // Method java/lang/StringBuilder.append:(Ljava/lang/String;)Ljava/lang/StringBuilder;
      34: invokevirtual #9                  // Method java/lang/StringBuilder.toString:()Ljava/lang/String;
      37: aload_1
      38: invokespecial #10                 // Method org/apache/hadoop/hbase/zookeeper/ZKWatcher."<init>":(Lorg/apache/hadoop/conf/Configuration;Ljava/lang/String;Lorg/apache/hadoop/hbase/Abortable;)V
      41: putfield      #11                 // Field zooKeeper:Lorg/apache/hadoop/hbase/zookeeper/ZKWatcher;
      44: aload_0
      45: aload_0
      46: getfield      #11                 // Field zooKeeper:Lorg/apache/hadoop/hbase/zookeeper/ZKWatcher;
      49: invokevirtual #12                 // Method org/apache/hadoop/hbase/zookeeper/ZKWatcher.getConfiguration:()Lorg/apache/hadoop/conf/Configuration;
      52: aload_0
      53: getfield      #11                 // Field zooKeeper:Lorg/apache/hadoop/hbase/zookeeper/ZKWatcher;
      56: invokestatic  #13                 // Method org/apache/hadoop/hbase/backup/example/ZKTableArchiveClient.getArchiveZNode:(Lorg/apache/hadoop/conf/Configuration;Lorg/apache/hadoop/hbase/zookeeper/ZKWatcher;)Ljava/lang/String;
      59: putfield      #14                 // Field archiveZnode:Ljava/lang/String;
      62: return

  public org.apache.hadoop.hbase.backup.example.HFileArchiveManager enableHFileBackup(byte[]) throws org.apache.zookeeper.KeeperException;
    Code:
       0: aload_0
       1: aload_0
       2: getfield      #11                 // Field zooKeeper:Lorg/apache/hadoop/hbase/zookeeper/ZKWatcher;
       5: aload_1
       6: invokespecial #15                 // Method enable:(Lorg/apache/hadoop/hbase/zookeeper/ZKWatcher;[B)V
       9: aload_0
      10: areturn

  public org.apache.hadoop.hbase.backup.example.HFileArchiveManager disableHFileBackup(byte[]) throws org.apache.zookeeper.KeeperException;
    Code:
       0: aload_0
       1: aload_0
       2: getfield      #11                 // Field zooKeeper:Lorg/apache/hadoop/hbase/zookeeper/ZKWatcher;
       5: aload_1
       6: invokespecial #16                 // Method disable:(Lorg/apache/hadoop/hbase/zookeeper/ZKWatcher;[B)V
       9: aload_0
      10: areturn

  public org.apache.hadoop.hbase.backup.example.HFileArchiveManager disableHFileBackup() throws java.io.IOException;
    Code:
       0: getstatic     #17                 // Field LOG:Lorg/slf4j/Logger;
       3: ldc           #18                 // String Disabling backups on all tables.
       5: invokeinterface #19,  2           // InterfaceMethod org/slf4j/Logger.debug:(Ljava/lang/String;)V
      10: aload_0
      11: getfield      #11                 // Field zooKeeper:Lorg/apache/hadoop/hbase/zookeeper/ZKWatcher;
      14: aload_0
      15: getfield      #14                 // Field archiveZnode:Ljava/lang/String;
      18: invokestatic  #20                 // Method org/apache/hadoop/hbase/zookeeper/ZKUtil.deleteNodeRecursively:(Lorg/apache/hadoop/hbase/zookeeper/ZKWatcher;Ljava/lang/String;)V
      21: aload_0
      22: areturn
      23: astore_1
      24: new           #22                 // class java/io/IOException
      27: dup
      28: ldc           #23                 // String Unexpected ZK exception!
      30: aload_1
      31: invokespecial #24                 // Method java/io/IOException."<init>":(Ljava/lang/String;Ljava/lang/Throwable;)V
      34: athrow
    Exception table:
       from    to  target type
          10    22    23   Class org/apache/zookeeper/KeeperException

  public void stop();
    Code:
       0: aload_0
       1: getfield      #2                  // Field stopped:Z
       4: ifne          29
       7: aload_0
       8: iconst_1
       9: putfield      #2                  // Field stopped:Z
      12: getstatic     #17                 // Field LOG:Lorg/slf4j/Logger;
      15: ldc           #34                 // String Stopping HFileArchiveManager...
      17: invokeinterface #19,  2           // InterfaceMethod org/slf4j/Logger.debug:(Ljava/lang/String;)V
      22: aload_0
      23: getfield      #11                 // Field zooKeeper:Lorg/apache/hadoop/hbase/zookeeper/ZKWatcher;
      26: invokevirtual #35                 // Method org/apache/hadoop/hbase/zookeeper/ZKWatcher.close:()V
      29: return

  public boolean isArchivingEnabled(byte[]) throws org.apache.zookeeper.KeeperException;
    Code:
       0: aload_0
       1: aload_1
       2: invokespecial #27                 // Method getTableNode:([B)Ljava/lang/String;
       5: astore_2
       6: aload_0
       7: getfield      #11                 // Field zooKeeper:Lorg/apache/hadoop/hbase/zookeeper/ZKWatcher;
      10: aload_2
      11: invokestatic  #32                 // Method org/apache/hadoop/hbase/zookeeper/ZKUtil.checkExists:(Lorg/apache/hadoop/hbase/zookeeper/ZKWatcher;Ljava/lang/String;)I
      14: iflt          21
      17: iconst_1
      18: goto          22
      21: iconst_0
      22: ireturn

  static {};
    Code:
       0: ldc           #38                 // class org/apache/hadoop/hbase/backup/example/HFileArchiveManager
       2: invokestatic  #39                 // Method org/slf4j/LoggerFactory.getLogger:(Ljava/lang/Class;)Lorg/slf4j/Logger;
       5: putstatic     #17                 // Field LOG:Lorg/slf4j/Logger;
       8: return
}
