Compiled from "HFileReaderImpl.java"
public class org.apache.hadoop.hbase.io.hfile.HFileReaderImpl$BlockIndexNotLoadedException extends java.lang.IllegalStateException {
  public org.apache.hadoop.hbase.io.hfile.HFileReaderImpl$BlockIndexNotLoadedException(org.apache.hadoop.fs.Path);
    Code:
       0: aload_0
       1: new           #1                  // class java/lang/StringBuilder
       4: dup
       5: invokespecial #2                  // Method java/lang/StringBuilder."<init>":()V
       8: aload_1
       9: invokevirtual #3                  // Method java/lang/StringBuilder.append:(Ljava/lang/Object;)Ljava/lang/StringBuilder;
      12: ldc           #4                  // String  block index not loaded
      14: invokevirtual #5                  // Method java/lang/StringBuilder.append:(Ljava/lang/String;)Ljava/lang/StringBuilder;
      17: invokevirtual #6                  // Method java/lang/StringBuilder.toString:()Ljava/lang/String;
      20: invokespecial #7                  // Method java/lang/IllegalStateException."<init>":(Ljava/lang/String;)V
      23: return
}
