Compiled from "HFile.java"
public class org.apache.hadoop.hbase.io.hfile.HFile$FileInfo implements java.util.SortedMap<byte[], byte[]> {
  static final java.lang.String RESERVED_PREFIX;

  static final byte[] RESERVED_PREFIX_BYTES;

  static final byte[] LASTKEY;

  static final byte[] AVG_KEY_LEN;

  static final byte[] AVG_VALUE_LEN;

  static final byte[] CREATE_TIME_TS;

  static final byte[] COMPARATOR;

  static final byte[] TAGS_COMPRESSED;

  public static final byte[] MAX_TAGS_LEN;

  public org.apache.hadoop.hbase.io.hfile.HFile$FileInfo();
    Code:
       0: aload_0
       1: invokespecial #1                  // Method java/lang/Object."<init>":()V
       4: aload_0
       5: new           #2                  // class java/util/TreeMap
       8: dup
       9: getstatic     #3                  // Field org/apache/hadoop/hbase/util/Bytes.BYTES_COMPARATOR:Ljava/util/Comparator;
      12: invokespecial #4                  // Method java/util/TreeMap."<init>":(Ljava/util/Comparator;)V
      15: putfield      #5                  // Field map:Ljava/util/SortedMap;
      18: return

  public org.apache.hadoop.hbase.io.hfile.HFile$FileInfo append(byte[], byte[], boolean) throws java.io.IOException;
    Code:
       0: aload_1
       1: ifnull        8
       4: aload_2
       5: ifnonnull     18
       8: new           #6                  // class java/lang/NullPointerException
      11: dup
      12: ldc           #7                  // String Key nor value may be null
      14: invokespecial #8                  // Method java/lang/NullPointerException."<init>":(Ljava/lang/String;)V
      17: athrow
      18: iload_3
      19: ifeq          39
      22: aload_1
      23: invokestatic  #9                  // Method org/apache/hadoop/hbase/io/hfile/HFile.isReservedFileInfoKey:([B)Z
      26: ifeq          39
      29: new           #10                 // class java/io/IOException
      32: dup
      33: ldc           #12                 // String Keys with a hfile. are reserved
      35: invokespecial #13                 // Method java/io/IOException."<init>":(Ljava/lang/String;)V
      38: athrow
      39: aload_0
      40: aload_1
      41: aload_2
      42: invokevirtual #14                 // Method put:([B[B)[B
      45: pop
      46: aload_0
      47: areturn

  public void clear();
    Code:
       0: aload_0
       1: getfield      #5                  // Field map:Ljava/util/SortedMap;
       4: invokeinterface #15,  1           // InterfaceMethod java/util/SortedMap.clear:()V
       9: return

  public java.util.Comparator<? super byte[]> comparator();
    Code:
       0: aload_0
       1: getfield      #5                  // Field map:Ljava/util/SortedMap;
       4: invokeinterface #16,  1           // InterfaceMethod java/util/SortedMap.comparator:()Ljava/util/Comparator;
       9: areturn

  public boolean containsKey(java.lang.Object);
    Code:
       0: aload_0
       1: getfield      #5                  // Field map:Ljava/util/SortedMap;
       4: aload_1
       5: invokeinterface #17,  2           // InterfaceMethod java/util/SortedMap.containsKey:(Ljava/lang/Object;)Z
      10: ireturn

  public boolean containsValue(java.lang.Object);
    Code:
       0: aload_0
       1: getfield      #5                  // Field map:Ljava/util/SortedMap;
       4: aload_1
       5: invokeinterface #18,  2           // InterfaceMethod java/util/SortedMap.containsValue:(Ljava/lang/Object;)Z
      10: ireturn

  public java.util.Set<java.util.Map$Entry<byte[], byte[]>> entrySet();
    Code:
       0: aload_0
       1: getfield      #5                  // Field map:Ljava/util/SortedMap;
       4: invokeinterface #19,  1           // InterfaceMethod java/util/SortedMap.entrySet:()Ljava/util/Set;
       9: areturn

  public boolean equals(java.lang.Object);
    Code:
       0: aload_0
       1: getfield      #5                  // Field map:Ljava/util/SortedMap;
       4: aload_1
       5: invokevirtual #20                 // Method java/lang/Object.equals:(Ljava/lang/Object;)Z
       8: ireturn

  public byte[] firstKey();
    Code:
       0: aload_0
       1: getfield      #5                  // Field map:Ljava/util/SortedMap;
       4: invokeinterface #21,  1           // InterfaceMethod java/util/SortedMap.firstKey:()Ljava/lang/Object;
       9: checkcast     #22                 // class "[B"
      12: areturn

  public byte[] get(java.lang.Object);
    Code:
       0: aload_0
       1: getfield      #5                  // Field map:Ljava/util/SortedMap;
       4: aload_1
       5: invokeinterface #23,  2           // InterfaceMethod java/util/SortedMap.get:(Ljava/lang/Object;)Ljava/lang/Object;
      10: checkcast     #22                 // class "[B"
      13: areturn

  public int hashCode();
    Code:
       0: aload_0
       1: getfield      #5                  // Field map:Ljava/util/SortedMap;
       4: invokevirtual #24                 // Method java/lang/Object.hashCode:()I
       7: ireturn

  public java.util.SortedMap<byte[], byte[]> headMap(byte[]);
    Code:
       0: aload_0
       1: getfield      #5                  // Field map:Ljava/util/SortedMap;
       4: aload_1
       5: invokeinterface #25,  2           // InterfaceMethod java/util/SortedMap.headMap:(Ljava/lang/Object;)Ljava/util/SortedMap;
      10: areturn

  public boolean isEmpty();
    Code:
       0: aload_0
       1: getfield      #5                  // Field map:Ljava/util/SortedMap;
       4: invokeinterface #26,  1           // InterfaceMethod java/util/SortedMap.isEmpty:()Z
       9: ireturn

  public java.util.Set<byte[]> keySet();
    Code:
       0: aload_0
       1: getfield      #5                  // Field map:Ljava/util/SortedMap;
       4: invokeinterface #27,  1           // InterfaceMethod java/util/SortedMap.keySet:()Ljava/util/Set;
       9: areturn

  public byte[] lastKey();
    Code:
       0: aload_0
       1: getfield      #5                  // Field map:Ljava/util/SortedMap;
       4: invokeinterface #28,  1           // InterfaceMethod java/util/SortedMap.lastKey:()Ljava/lang/Object;
       9: checkcast     #22                 // class "[B"
      12: areturn

  public byte[] put(byte[], byte[]);
    Code:
       0: aload_0
       1: getfield      #5                  // Field map:Ljava/util/SortedMap;
       4: aload_1
       5: aload_2
       6: invokeinterface #29,  3           // InterfaceMethod java/util/SortedMap.put:(Ljava/lang/Object;Ljava/lang/Object;)Ljava/lang/Object;
      11: checkcast     #22                 // class "[B"
      14: areturn

  public void putAll(java.util.Map<? extends byte[], ? extends byte[]>);
    Code:
       0: aload_0
       1: getfield      #5                  // Field map:Ljava/util/SortedMap;
       4: aload_1
       5: invokeinterface #30,  2           // InterfaceMethod java/util/SortedMap.putAll:(Ljava/util/Map;)V
      10: return

  public byte[] remove(java.lang.Object);
    Code:
       0: aload_0
       1: getfield      #5                  // Field map:Ljava/util/SortedMap;
       4: aload_1
       5: invokeinterface #31,  2           // InterfaceMethod java/util/SortedMap.remove:(Ljava/lang/Object;)Ljava/lang/Object;
      10: checkcast     #22                 // class "[B"
      13: areturn

  public int size();
    Code:
       0: aload_0
       1: getfield      #5                  // Field map:Ljava/util/SortedMap;
       4: invokeinterface #32,  1           // InterfaceMethod java/util/SortedMap.size:()I
       9: ireturn

  public java.util.SortedMap<byte[], byte[]> subMap(byte[], byte[]);
    Code:
       0: aload_0
       1: getfield      #5                  // Field map:Ljava/util/SortedMap;
       4: aload_1
       5: aload_2
       6: invokeinterface #33,  3           // InterfaceMethod java/util/SortedMap.subMap:(Ljava/lang/Object;Ljava/lang/Object;)Ljava/util/SortedMap;
      11: areturn

  public java.util.SortedMap<byte[], byte[]> tailMap(byte[]);
    Code:
       0: aload_0
       1: getfield      #5                  // Field map:Ljava/util/SortedMap;
       4: aload_1
       5: invokeinterface #34,  2           // InterfaceMethod java/util/SortedMap.tailMap:(Ljava/lang/Object;)Ljava/util/SortedMap;
      10: areturn

  public java.util.Collection<byte[]> values();
    Code:
       0: aload_0
       1: getfield      #5                  // Field map:Ljava/util/SortedMap;
       4: invokeinterface #35,  1           // InterfaceMethod java/util/SortedMap.values:()Ljava/util/Collection;
       9: areturn

  void write(java.io.DataOutputStream) throws java.io.IOException;
    Code:
       0: invokestatic  #36                 // Method org/apache/hadoop/hbase/shaded/protobuf/generated/HFileProtos$FileInfoProto.newBuilder:()Lorg/apache/hadoop/hbase/shaded/protobuf/generated/HFileProtos$FileInfoProto$Builder;
       3: astore_2
       4: aload_0
       5: getfield      #5                  // Field map:Ljava/util/SortedMap;
       8: invokeinterface #19,  1           // InterfaceMethod java/util/SortedMap.entrySet:()Ljava/util/Set;
      13: invokeinterface #37,  1           // InterfaceMethod java/util/Set.iterator:()Ljava/util/Iterator;
      18: astore_3
      19: aload_3
      20: invokeinterface #38,  1           // InterfaceMethod java/util/Iterator.hasNext:()Z
      25: ifeq          95
      28: aload_3
      29: invokeinterface #39,  1           // InterfaceMethod java/util/Iterator.next:()Ljava/lang/Object;
      34: checkcast     #40                 // class java/util/Map$Entry
      37: astore        4
      39: invokestatic  #41                 // Method org/apache/hadoop/hbase/shaded/protobuf/generated/HBaseProtos$BytesBytesPair.newBuilder:()Lorg/apache/hadoop/hbase/shaded/protobuf/generated/HBaseProtos$BytesBytesPair$Builder;
      42: astore        5
      44: aload         5
      46: aload         4
      48: invokeinterface #42,  1           // InterfaceMethod java/util/Map$Entry.getKey:()Ljava/lang/Object;
      53: checkcast     #22                 // class "[B"
      56: invokestatic  #43                 // Method org/apache/hbase/thirdparty/com/google/protobuf/UnsafeByteOperations.unsafeWrap:([B)Lorg/apache/hbase/thirdparty/com/google/protobuf/ByteString;
      59: invokevirtual #44                 // Method org/apache/hadoop/hbase/shaded/protobuf/generated/HBaseProtos$BytesBytesPair$Builder.setFirst:(Lorg/apache/hbase/thirdparty/com/google/protobuf/ByteString;)Lorg/apache/hadoop/hbase/shaded/protobuf/generated/HBaseProtos$BytesBytesPair$Builder;
      62: pop
      63: aload         5
      65: aload         4
      67: invokeinterface #45,  1           // InterfaceMethod java/util/Map$Entry.getValue:()Ljava/lang/Object;
      72: checkcast     #22                 // class "[B"
      75: invokestatic  #43                 // Method org/apache/hbase/thirdparty/com/google/protobuf/UnsafeByteOperations.unsafeWrap:([B)Lorg/apache/hbase/thirdparty/com/google/protobuf/ByteString;
      78: invokevirtual #46                 // Method org/apache/hadoop/hbase/shaded/protobuf/generated/HBaseProtos$BytesBytesPair$Builder.setSecond:(Lorg/apache/hbase/thirdparty/com/google/protobuf/ByteString;)Lorg/apache/hadoop/hbase/shaded/protobuf/generated/HBaseProtos$BytesBytesPair$Builder;
      81: pop
      82: aload_2
      83: aload         5
      85: invokevirtual #47                 // Method org/apache/hadoop/hbase/shaded/protobuf/generated/HBaseProtos$BytesBytesPair$Builder.build:()Lorg/apache/hadoop/hbase/shaded/protobuf/generated/HBaseProtos$BytesBytesPair;
      88: invokevirtual #48                 // Method org/apache/hadoop/hbase/shaded/protobuf/generated/HFileProtos$FileInfoProto$Builder.addMapEntry:(Lorg/apache/hadoop/hbase/shaded/protobuf/generated/HBaseProtos$BytesBytesPair;)Lorg/apache/hadoop/hbase/shaded/protobuf/generated/HFileProtos$FileInfoProto$Builder;
      91: pop
      92: goto          19
      95: aload_1
      96: getstatic     #49                 // Field org/apache/hadoop/hbase/protobuf/ProtobufMagic.PB_MAGIC:[B
      99: invokevirtual #50                 // Method java/io/DataOutputStream.write:([B)V
     102: aload_2
     103: invokevirtual #51                 // Method org/apache/hadoop/hbase/shaded/protobuf/generated/HFileProtos$FileInfoProto$Builder.build:()Lorg/apache/hadoop/hbase/shaded/protobuf/generated/HFileProtos$FileInfoProto;
     106: aload_1
     107: invokevirtual #52                 // Method org/apache/hadoop/hbase/shaded/protobuf/generated/HFileProtos$FileInfoProto.writeDelimitedTo:(Ljava/io/OutputStream;)V
     110: return

  void read(java.io.DataInputStream) throws java.io.IOException;
    Code:
       0: invokestatic  #53                 // Method org/apache/hadoop/hbase/shaded/protobuf/ProtobufUtil.lengthOfPBMagic:()I
       3: istore_2
       4: iload_2
       5: newarray       byte
       7: astore_3
       8: aload_1
       9: invokevirtual #54                 // Method java/io/DataInputStream.markSupported:()Z
      12: ifeq          20
      15: aload_1
      16: iload_2
      17: invokevirtual #55                 // Method java/io/DataInputStream.mark:(I)V
      20: aload_1
      21: aload_3
      22: invokevirtual #56                 // Method java/io/DataInputStream.read:([B)I
      25: istore        4
      27: iload         4
      29: iload_2
      30: if_icmpeq     70
      33: new           #10                 // class java/io/IOException
      36: dup
      37: new           #57                 // class java/lang/StringBuilder
      40: dup
      41: invokespecial #58                 // Method java/lang/StringBuilder."<init>":()V
      44: ldc           #59                 // String read=
      46: invokevirtual #60                 // Method java/lang/StringBuilder.append:(Ljava/lang/String;)Ljava/lang/StringBuilder;
      49: iload         4
      51: invokevirtual #61                 // Method java/lang/StringBuilder.append:(I)Ljava/lang/StringBuilder;
      54: ldc           #62                 // String , wanted=
      56: invokevirtual #60                 // Method java/lang/StringBuilder.append:(Ljava/lang/String;)Ljava/lang/StringBuilder;
      59: iload_2
      60: invokevirtual #61                 // Method java/lang/StringBuilder.append:(I)Ljava/lang/StringBuilder;
      63: invokevirtual #63                 // Method java/lang/StringBuilder.toString:()Ljava/lang/String;
      66: invokespecial #13                 // Method java/io/IOException."<init>":(Ljava/lang/String;)V
      69: athrow
      70: aload_3
      71: invokestatic  #64                 // Method org/apache/hadoop/hbase/shaded/protobuf/ProtobufUtil.isPBMagicPrefix:([B)Z
      74: ifeq          88
      77: aload_0
      78: aload_1
      79: invokestatic  #65                 // Method org/apache/hadoop/hbase/shaded/protobuf/generated/HFileProtos$FileInfoProto.parseDelimitedFrom:(Ljava/io/InputStream;)Lorg/apache/hadoop/hbase/shaded/protobuf/generated/HFileProtos$FileInfoProto;
      82: invokevirtual #66                 // Method parsePB:(Lorg/apache/hadoop/hbase/shaded/protobuf/generated/HFileProtos$FileInfoProto;)V
      85: goto          142
      88: aload_1
      89: invokevirtual #54                 // Method java/io/DataInputStream.markSupported:()Z
      92: ifeq          107
      95: aload_1
      96: invokevirtual #67                 // Method java/io/DataInputStream.reset:()V
      99: aload_0
     100: aload_1
     101: invokevirtual #68                 // Method parseWritable:(Ljava/io/DataInputStream;)V
     104: goto          142
     107: new           #69                 // class java/io/ByteArrayInputStream
     110: dup
     111: aload_3
     112: invokespecial #70                 // Method java/io/ByteArrayInputStream."<init>":([B)V
     115: astore        5
     117: new           #71                 // class java/io/SequenceInputStream
     120: dup
     121: aload         5
     123: aload_1
     124: invokespecial #72                 // Method java/io/SequenceInputStream."<init>":(Ljava/io/InputStream;Ljava/io/InputStream;)V
     127: astore        6
     129: aload_0
     130: new           #73                 // class java/io/DataInputStream
     133: dup
     134: aload         6
     136: invokespecial #74                 // Method java/io/DataInputStream."<init>":(Ljava/io/InputStream;)V
     139: invokevirtual #68                 // Method parseWritable:(Ljava/io/DataInputStream;)V
     142: return

  void parseWritable(java.io.DataInputStream) throws java.io.IOException;
    Code:
       0: aload_0
       1: getfield      #5                  // Field map:Ljava/util/SortedMap;
       4: invokeinterface #15,  1           // InterfaceMethod java/util/SortedMap.clear:()V
       9: aload_1
      10: invokevirtual #75                 // Method java/io/DataInputStream.readInt:()I
      13: istore_2
      14: iconst_0
      15: istore_3
      16: iload_3
      17: iload_2
      18: if_icmpge     58
      21: aload_1
      22: invokestatic  #76                 // Method org/apache/hadoop/hbase/util/Bytes.readByteArray:(Ljava/io/DataInput;)[B
      25: astore        4
      27: aload_1
      28: invokevirtual #77                 // Method java/io/DataInputStream.readByte:()B
      31: pop
      32: aload_1
      33: invokestatic  #76                 // Method org/apache/hadoop/hbase/util/Bytes.readByteArray:(Ljava/io/DataInput;)[B
      36: astore        5
      38: aload_0
      39: getfield      #5                  // Field map:Ljava/util/SortedMap;
      42: aload         4
      44: aload         5
      46: invokeinterface #29,  3           // InterfaceMethod java/util/SortedMap.put:(Ljava/lang/Object;Ljava/lang/Object;)Ljava/lang/Object;
      51: pop
      52: iinc          3, 1
      55: goto          16
      58: return

  void parsePB(org.apache.hadoop.hbase.shaded.protobuf.generated.HFileProtos$FileInfoProto);
    Code:
       0: aload_0
       1: getfield      #5                  // Field map:Ljava/util/SortedMap;
       4: invokeinterface #15,  1           // InterfaceMethod java/util/SortedMap.clear:()V
       9: aload_1
      10: invokevirtual #78                 // Method org/apache/hadoop/hbase/shaded/protobuf/generated/HFileProtos$FileInfoProto.getMapEntryList:()Ljava/util/List;
      13: invokeinterface #79,  1           // InterfaceMethod java/util/List.iterator:()Ljava/util/Iterator;
      18: astore_2
      19: aload_2
      20: invokeinterface #38,  1           // InterfaceMethod java/util/Iterator.hasNext:()Z
      25: ifeq          65
      28: aload_2
      29: invokeinterface #39,  1           // InterfaceMethod java/util/Iterator.next:()Ljava/lang/Object;
      34: checkcast     #80                 // class org/apache/hadoop/hbase/shaded/protobuf/generated/HBaseProtos$BytesBytesPair
      37: astore_3
      38: aload_0
      39: getfield      #5                  // Field map:Ljava/util/SortedMap;
      42: aload_3
      43: invokevirtual #81                 // Method org/apache/hadoop/hbase/shaded/protobuf/generated/HBaseProtos$BytesBytesPair.getFirst:()Lorg/apache/hbase/thirdparty/com/google/protobuf/ByteString;
      46: invokevirtual #82                 // Method org/apache/hbase/thirdparty/com/google/protobuf/ByteString.toByteArray:()[B
      49: aload_3
      50: invokevirtual #83                 // Method org/apache/hadoop/hbase/shaded/protobuf/generated/HBaseProtos$BytesBytesPair.getSecond:()Lorg/apache/hbase/thirdparty/com/google/protobuf/ByteString;
      53: invokevirtual #82                 // Method org/apache/hbase/thirdparty/com/google/protobuf/ByteString.toByteArray:()[B
      56: invokeinterface #29,  3           // InterfaceMethod java/util/SortedMap.put:(Ljava/lang/Object;Ljava/lang/Object;)Ljava/lang/Object;
      61: pop
      62: goto          19
      65: return

  public java.lang.Object lastKey();
    Code:
       0: aload_0
       1: invokevirtual #84                 // Method lastKey:()[B
       4: areturn

  public java.lang.Object firstKey();
    Code:
       0: aload_0
       1: invokevirtual #85                 // Method firstKey:()[B
       4: areturn

  public java.util.SortedMap tailMap(java.lang.Object);
    Code:
       0: aload_0
       1: aload_1
       2: checkcast     #22                 // class "[B"
       5: invokevirtual #86                 // Method tailMap:([B)Ljava/util/SortedMap;
       8: areturn

  public java.util.SortedMap headMap(java.lang.Object);
    Code:
       0: aload_0
       1: aload_1
       2: checkcast     #22                 // class "[B"
       5: invokevirtual #87                 // Method headMap:([B)Ljava/util/SortedMap;
       8: areturn

  public java.util.SortedMap subMap(java.lang.Object, java.lang.Object);
    Code:
       0: aload_0
       1: aload_1
       2: checkcast     #22                 // class "[B"
       5: aload_2
       6: checkcast     #22                 // class "[B"
       9: invokevirtual #88                 // Method subMap:([B[B)Ljava/util/SortedMap;
      12: areturn

  public java.lang.Object remove(java.lang.Object);
    Code:
       0: aload_0
       1: aload_1
       2: invokevirtual #89                 // Method remove:(Ljava/lang/Object;)[B
       5: areturn

  public java.lang.Object put(java.lang.Object, java.lang.Object);
    Code:
       0: aload_0
       1: aload_1
       2: checkcast     #22                 // class "[B"
       5: aload_2
       6: checkcast     #22                 // class "[B"
       9: invokevirtual #14                 // Method put:([B[B)[B
      12: areturn

  public java.lang.Object get(java.lang.Object);
    Code:
       0: aload_0
       1: aload_1
       2: invokevirtual #90                 // Method get:(Ljava/lang/Object;)[B
       5: areturn

  static {};
    Code:
       0: ldc           #91                 // String hfile.
       2: invokestatic  #92                 // Method org/apache/hadoop/hbase/util/Bytes.toBytes:(Ljava/lang/String;)[B
       5: putstatic     #93                 // Field RESERVED_PREFIX_BYTES:[B
       8: ldc           #94                 // String hfile.LASTKEY
      10: invokestatic  #92                 // Method org/apache/hadoop/hbase/util/Bytes.toBytes:(Ljava/lang/String;)[B
      13: putstatic     #95                 // Field LASTKEY:[B
      16: ldc           #96                 // String hfile.AVG_KEY_LEN
      18: invokestatic  #92                 // Method org/apache/hadoop/hbase/util/Bytes.toBytes:(Ljava/lang/String;)[B
      21: putstatic     #97                 // Field AVG_KEY_LEN:[B
      24: ldc           #98                 // String hfile.AVG_VALUE_LEN
      26: invokestatic  #92                 // Method org/apache/hadoop/hbase/util/Bytes.toBytes:(Ljava/lang/String;)[B
      29: putstatic     #99                 // Field AVG_VALUE_LEN:[B
      32: ldc           #100                // String hfile.CREATE_TIME_TS
      34: invokestatic  #92                 // Method org/apache/hadoop/hbase/util/Bytes.toBytes:(Ljava/lang/String;)[B
      37: putstatic     #101                // Field CREATE_TIME_TS:[B
      40: ldc           #102                // String hfile.COMPARATOR
      42: invokestatic  #92                 // Method org/apache/hadoop/hbase/util/Bytes.toBytes:(Ljava/lang/String;)[B
      45: putstatic     #103                // Field COMPARATOR:[B
      48: ldc           #104                // String hfile.TAGS_COMPRESSED
      50: invokestatic  #92                 // Method org/apache/hadoop/hbase/util/Bytes.toBytes:(Ljava/lang/String;)[B
      53: putstatic     #105                // Field TAGS_COMPRESSED:[B
      56: ldc           #106                // String hfile.MAX_TAGS_LEN
      58: invokestatic  #92                 // Method org/apache/hadoop/hbase/util/Bytes.toBytes:(Ljava/lang/String;)[B
      61: putstatic     #107                // Field MAX_TAGS_LEN:[B
      64: return
}
