Compiled from "HFileArchiver.java"
class org.apache.hadoop.hbase.backup.HFileArchiver$FileableStoreFile extends org.apache.hadoop.hbase.backup.HFileArchiver$File {
  org.apache.hadoop.hbase.regionserver.HStoreFile file;

  public org.apache.hadoop.hbase.backup.HFileArchiver$FileableStoreFile(org.apache.hadoop.fs.FileSystem, org.apache.hadoop.hbase.regionserver.HStoreFile);
    Code:
       0: aload_0
       1: aload_1
       2: invokespecial #1                  // Method org/apache/hadoop/hbase/backup/HFileArchiver$File."<init>":(Lorg/apache/hadoop/fs/FileSystem;)V
       5: aload_0
       6: aload_2
       7: putfield      #2                  // Field file:Lorg/apache/hadoop/hbase/regionserver/HStoreFile;
      10: return

  public void delete() throws java.io.IOException;
    Code:
       0: aload_0
       1: getfield      #2                  // Field file:Lorg/apache/hadoop/hbase/regionserver/HStoreFile;
       4: invokevirtual #3                  // Method org/apache/hadoop/hbase/regionserver/HStoreFile.deleteStoreFile:()V
       7: return

  public java.lang.String getName();
    Code:
       0: aload_0
       1: getfield      #2                  // Field file:Lorg/apache/hadoop/hbase/regionserver/HStoreFile;
       4: invokevirtual #4                  // Method org/apache/hadoop/hbase/regionserver/HStoreFile.getPath:()Lorg/apache/hadoop/fs/Path;
       7: invokevirtual #5                  // Method org/apache/hadoop/fs/Path.getName:()Ljava/lang/String;
      10: areturn

  public boolean isFile();
    Code:
       0: iconst_1
       1: ireturn

  public java.util.Collection<org.apache.hadoop.hbase.backup.HFileArchiver$File> getChildren() throws java.io.IOException;
    Code:
       0: invokestatic  #6                  // Method java/util/Collections.emptyList:()Ljava/util/List;
       3: areturn

  public void close() throws java.io.IOException;
    Code:
       0: aload_0
       1: getfield      #2                  // Field file:Lorg/apache/hadoop/hbase/regionserver/HStoreFile;
       4: iconst_1
       5: invokevirtual #7                  // Method org/apache/hadoop/hbase/regionserver/HStoreFile.closeStoreFile:(Z)V
       8: return

  org.apache.hadoop.fs.Path getPath();
    Code:
       0: aload_0
       1: getfield      #2                  // Field file:Lorg/apache/hadoop/hbase/regionserver/HStoreFile;
       4: invokevirtual #4                  // Method org/apache/hadoop/hbase/regionserver/HStoreFile.getPath:()Lorg/apache/hadoop/fs/Path;
       7: areturn
}
