Compiled from "HFileProtos.java"
public final class org.apache.hadoop.hbase.protobuf.generated.HFileProtos$FileTrailerProto extends com.google.protobuf.GeneratedMessage implements org.apache.hadoop.hbase.protobuf.generated.HFileProtos$FileTrailerProtoOrBuilder {
  public static com.google.protobuf.Parser<org.apache.hadoop.hbase.protobuf.generated.HFileProtos$FileTrailerProto> PARSER;

  public static final int FILE_INFO_OFFSET_FIELD_NUMBER;

  public static final int LOAD_ON_OPEN_DATA_OFFSET_FIELD_NUMBER;

  public static final int UNCOMPRESSED_DATA_INDEX_SIZE_FIELD_NUMBER;

  public static final int TOTAL_UNCOMPRESSED_BYTES_FIELD_NUMBER;

  public static final int DATA_INDEX_COUNT_FIELD_NUMBER;

  public static final int META_INDEX_COUNT_FIELD_NUMBER;

  public static final int ENTRY_COUNT_FIELD_NUMBER;

  public static final int NUM_DATA_INDEX_LEVELS_FIELD_NUMBER;

  public static final int FIRST_DATA_BLOCK_OFFSET_FIELD_NUMBER;

  public static final int LAST_DATA_BLOCK_OFFSET_FIELD_NUMBER;

  public static final int COMPARATOR_CLASS_NAME_FIELD_NUMBER;

  public static final int COMPRESSION_CODEC_FIELD_NUMBER;

  public static final int ENCRYPTION_KEY_FIELD_NUMBER;

  public static org.apache.hadoop.hbase.protobuf.generated.HFileProtos$FileTrailerProto getDefaultInstance();
    Code:
       0: getstatic     #26                 // Field defaultInstance:Lorg/apache/hadoop/hbase/protobuf/generated/HFileProtos$FileTrailerProto;
       3: areturn

  public org.apache.hadoop.hbase.protobuf.generated.HFileProtos$FileTrailerProto getDefaultInstanceForType();
    Code:
       0: getstatic     #26                 // Field defaultInstance:Lorg/apache/hadoop/hbase/protobuf/generated/HFileProtos$FileTrailerProto;
       3: areturn

  public final com.google.protobuf.UnknownFieldSet getUnknownFields();
    Code:
       0: aload_0
       1: getfield      #23                 // Field unknownFields:Lcom/google/protobuf/UnknownFieldSet;
       4: areturn

  public static final com.google.protobuf.Descriptors$Descriptor getDescriptor();
    Code:
       0: invokestatic  #41                 // Method org/apache/hadoop/hbase/protobuf/generated/HFileProtos.access$900:()Lcom/google/protobuf/Descriptors$Descriptor;
       3: areturn

  protected com.google.protobuf.GeneratedMessage$FieldAccessorTable internalGetFieldAccessorTable();
    Code:
       0: invokestatic  #42                 // Method org/apache/hadoop/hbase/protobuf/generated/HFileProtos.access$1000:()Lcom/google/protobuf/GeneratedMessage$FieldAccessorTable;
       3: ldc           #43                 // class org/apache/hadoop/hbase/protobuf/generated/HFileProtos$FileTrailerProto
       5: ldc           #44                 // class org/apache/hadoop/hbase/protobuf/generated/HFileProtos$FileTrailerProto$Builder
       7: invokevirtual #45                 // Method com/google/protobuf/GeneratedMessage$FieldAccessorTable.ensureFieldAccessorsInitialized:(Ljava/lang/Class;Ljava/lang/Class;)Lcom/google/protobuf/GeneratedMessage$FieldAccessorTable;
      10: areturn

  public com.google.protobuf.Parser<org.apache.hadoop.hbase.protobuf.generated.HFileProtos$FileTrailerProto> getParserForType();
    Code:
       0: getstatic     #46                 // Field PARSER:Lcom/google/protobuf/Parser;
       3: areturn

  public boolean hasFileInfoOffset();
    Code:
       0: aload_0
       1: getfield      #1                  // Field bitField0_:I
       4: iconst_1
       5: iand
       6: iconst_1
       7: if_icmpne     14
      10: iconst_1
      11: goto          15
      14: iconst_0
      15: ireturn

  public long getFileInfoOffset();
    Code:
       0: aload_0
       1: getfield      #14                 // Field fileInfoOffset_:J
       4: lreturn

  public boolean hasLoadOnOpenDataOffset();
    Code:
       0: aload_0
       1: getfield      #1                  // Field bitField0_:I
       4: iconst_2
       5: iand
       6: iconst_2
       7: if_icmpne     14
      10: iconst_1
      11: goto          15
      14: iconst_0
      15: ireturn

  public long getLoadOnOpenDataOffset();
    Code:
       0: aload_0
       1: getfield      #13                 // Field loadOnOpenDataOffset_:J
       4: lreturn

  public boolean hasUncompressedDataIndexSize();
    Code:
       0: aload_0
       1: getfield      #1                  // Field bitField0_:I
       4: iconst_4
       5: iand
       6: iconst_4
       7: if_icmpne     14
      10: iconst_1
      11: goto          15
      14: iconst_0
      15: ireturn

  public long getUncompressedDataIndexSize();
    Code:
       0: aload_0
       1: getfield      #12                 // Field uncompressedDataIndexSize_:J
       4: lreturn

  public boolean hasTotalUncompressedBytes();
    Code:
       0: aload_0
       1: getfield      #1                  // Field bitField0_:I
       4: bipush        8
       6: iand
       7: bipush        8
       9: if_icmpne     16
      12: iconst_1
      13: goto          17
      16: iconst_0
      17: ireturn

  public long getTotalUncompressedBytes();
    Code:
       0: aload_0
       1: getfield      #11                 // Field totalUncompressedBytes_:J
       4: lreturn

  public boolean hasDataIndexCount();
    Code:
       0: aload_0
       1: getfield      #1                  // Field bitField0_:I
       4: bipush        16
       6: iand
       7: bipush        16
       9: if_icmpne     16
      12: iconst_1
      13: goto          17
      16: iconst_0
      17: ireturn

  public int getDataIndexCount();
    Code:
       0: aload_0
       1: getfield      #10                 // Field dataIndexCount_:I
       4: ireturn

  public boolean hasMetaIndexCount();
    Code:
       0: aload_0
       1: getfield      #1                  // Field bitField0_:I
       4: bipush        32
       6: iand
       7: bipush        32
       9: if_icmpne     16
      12: iconst_1
      13: goto          17
      16: iconst_0
      17: ireturn

  public int getMetaIndexCount();
    Code:
       0: aload_0
       1: getfield      #9                  // Field metaIndexCount_:I
       4: ireturn

  public boolean hasEntryCount();
    Code:
       0: aload_0
       1: getfield      #1                  // Field bitField0_:I
       4: bipush        64
       6: iand
       7: bipush        64
       9: if_icmpne     16
      12: iconst_1
      13: goto          17
      16: iconst_0
      17: ireturn

  public long getEntryCount();
    Code:
       0: aload_0
       1: getfield      #8                  // Field entryCount_:J
       4: lreturn

  public boolean hasNumDataIndexLevels();
    Code:
       0: aload_0
       1: getfield      #1                  // Field bitField0_:I
       4: sipush        128
       7: iand
       8: sipush        128
      11: if_icmpne     18
      14: iconst_1
      15: goto          19
      18: iconst_0
      19: ireturn

  public int getNumDataIndexLevels();
    Code:
       0: aload_0
       1: getfield      #7                  // Field numDataIndexLevels_:I
       4: ireturn

  public boolean hasFirstDataBlockOffset();
    Code:
       0: aload_0
       1: getfield      #1                  // Field bitField0_:I
       4: sipush        256
       7: iand
       8: sipush        256
      11: if_icmpne     18
      14: iconst_1
      15: goto          19
      18: iconst_0
      19: ireturn

  public long getFirstDataBlockOffset();
    Code:
       0: aload_0
       1: getfield      #6                  // Field firstDataBlockOffset_:J
       4: lreturn

  public boolean hasLastDataBlockOffset();
    Code:
       0: aload_0
       1: getfield      #1                  // Field bitField0_:I
       4: sipush        512
       7: iand
       8: sipush        512
      11: if_icmpne     18
      14: iconst_1
      15: goto          19
      18: iconst_0
      19: ireturn

  public long getLastDataBlockOffset();
    Code:
       0: aload_0
       1: getfield      #5                  // Field lastDataBlockOffset_:J
       4: lreturn

  public boolean hasComparatorClassName();
    Code:
       0: aload_0
       1: getfield      #1                  // Field bitField0_:I
       4: sipush        1024
       7: iand
       8: sipush        1024
      11: if_icmpne     18
      14: iconst_1
      15: goto          19
      18: iconst_0
      19: ireturn

  public java.lang.String getComparatorClassName();
    Code:
       0: aload_0
       1: getfield      #4                  // Field comparatorClassName_:Ljava/lang/Object;
       4: astore_1
       5: aload_1
       6: instanceof    #47                 // class java/lang/String
       9: ifeq          17
      12: aload_1
      13: checkcast     #47                 // class java/lang/String
      16: areturn
      17: aload_1
      18: checkcast     #48                 // class com/google/protobuf/ByteString
      21: astore_2
      22: aload_2
      23: invokevirtual #49                 // Method com/google/protobuf/ByteString.toStringUtf8:()Ljava/lang/String;
      26: astore_3
      27: aload_2
      28: invokevirtual #50                 // Method com/google/protobuf/ByteString.isValidUtf8:()Z
      31: ifeq          39
      34: aload_0
      35: aload_3
      36: putfield      #4                  // Field comparatorClassName_:Ljava/lang/Object;
      39: aload_3
      40: areturn

  public com.google.protobuf.ByteString getComparatorClassNameBytes();
    Code:
       0: aload_0
       1: getfield      #4                  // Field comparatorClassName_:Ljava/lang/Object;
       4: astore_1
       5: aload_1
       6: instanceof    #47                 // class java/lang/String
       9: ifeq          27
      12: aload_1
      13: checkcast     #47                 // class java/lang/String
      16: invokestatic  #51                 // Method com/google/protobuf/ByteString.copyFromUtf8:(Ljava/lang/String;)Lcom/google/protobuf/ByteString;
      19: astore_2
      20: aload_0
      21: aload_2
      22: putfield      #4                  // Field comparatorClassName_:Ljava/lang/Object;
      25: aload_2
      26: areturn
      27: aload_1
      28: checkcast     #48                 // class com/google/protobuf/ByteString
      31: areturn

  public boolean hasCompressionCodec();
    Code:
       0: aload_0
       1: getfield      #1                  // Field bitField0_:I
       4: sipush        2048
       7: iand
       8: sipush        2048
      11: if_icmpne     18
      14: iconst_1
      15: goto          19
      18: iconst_0
      19: ireturn

  public int getCompressionCodec();
    Code:
       0: aload_0
       1: getfield      #3                  // Field compressionCodec_:I
       4: ireturn

  public boolean hasEncryptionKey();
    Code:
       0: aload_0
       1: getfield      #1                  // Field bitField0_:I
       4: sipush        4096
       7: iand
       8: sipush        4096
      11: if_icmpne     18
      14: iconst_1
      15: goto          19
      18: iconst_0
      19: ireturn

  public com.google.protobuf.ByteString getEncryptionKey();
    Code:
       0: aload_0
       1: getfield      #2                  // Field encryptionKey_:Lcom/google/protobuf/ByteString;
       4: areturn

  public final boolean isInitialized();
    Code:
       0: aload_0
       1: getfield      #19                 // Field memoizedIsInitialized:B
       4: istore_1
       5: iload_1
       6: iconst_m1
       7: if_icmpeq     21
      10: iload_1
      11: iconst_1
      12: if_icmpne     19
      15: iconst_1
      16: goto          20
      19: iconst_0
      20: ireturn
      21: aload_0
      22: iconst_1
      23: putfield      #19                 // Field memoizedIsInitialized:B
      26: iconst_1
      27: ireturn

  public void writeTo(com.google.protobuf.CodedOutputStream) throws java.io.IOException;
    Code:
       0: aload_0
       1: invokevirtual #54                 // Method getSerializedSize:()I
       4: pop
       5: aload_0
       6: getfield      #1                  // Field bitField0_:I
       9: iconst_1
      10: iand
      11: iconst_1
      12: if_icmpne     24
      15: aload_1
      16: iconst_1
      17: aload_0
      18: getfield      #14                 // Field fileInfoOffset_:J
      21: invokevirtual #55                 // Method com/google/protobuf/CodedOutputStream.writeUInt64:(IJ)V
      24: aload_0
      25: getfield      #1                  // Field bitField0_:I
      28: iconst_2
      29: iand
      30: iconst_2
      31: if_icmpne     43
      34: aload_1
      35: iconst_2
      36: aload_0
      37: getfield      #13                 // Field loadOnOpenDataOffset_:J
      40: invokevirtual #55                 // Method com/google/protobuf/CodedOutputStream.writeUInt64:(IJ)V
      43: aload_0
      44: getfield      #1                  // Field bitField0_:I
      47: iconst_4
      48: iand
      49: iconst_4
      50: if_icmpne     62
      53: aload_1
      54: iconst_3
      55: aload_0
      56: getfield      #12                 // Field uncompressedDataIndexSize_:J
      59: invokevirtual #55                 // Method com/google/protobuf/CodedOutputStream.writeUInt64:(IJ)V
      62: aload_0
      63: getfield      #1                  // Field bitField0_:I
      66: bipush        8
      68: iand
      69: bipush        8
      71: if_icmpne     83
      74: aload_1
      75: iconst_4
      76: aload_0
      77: getfield      #11                 // Field totalUncompressedBytes_:J
      80: invokevirtual #55                 // Method com/google/protobuf/CodedOutputStream.writeUInt64:(IJ)V
      83: aload_0
      84: getfield      #1                  // Field bitField0_:I
      87: bipush        16
      89: iand
      90: bipush        16
      92: if_icmpne     104
      95: aload_1
      96: iconst_5
      97: aload_0
      98: getfield      #10                 // Field dataIndexCount_:I
     101: invokevirtual #56                 // Method com/google/protobuf/CodedOutputStream.writeUInt32:(II)V
     104: aload_0
     105: getfield      #1                  // Field bitField0_:I
     108: bipush        32
     110: iand
     111: bipush        32
     113: if_icmpne     126
     116: aload_1
     117: bipush        6
     119: aload_0
     120: getfield      #9                  // Field metaIndexCount_:I
     123: invokevirtual #56                 // Method com/google/protobuf/CodedOutputStream.writeUInt32:(II)V
     126: aload_0
     127: getfield      #1                  // Field bitField0_:I
     130: bipush        64
     132: iand
     133: bipush        64
     135: if_icmpne     148
     138: aload_1
     139: bipush        7
     141: aload_0
     142: getfield      #8                  // Field entryCount_:J
     145: invokevirtual #55                 // Method com/google/protobuf/CodedOutputStream.writeUInt64:(IJ)V
     148: aload_0
     149: getfield      #1                  // Field bitField0_:I
     152: sipush        128
     155: iand
     156: sipush        128
     159: if_icmpne     172
     162: aload_1
     163: bipush        8
     165: aload_0
     166: getfield      #7                  // Field numDataIndexLevels_:I
     169: invokevirtual #56                 // Method com/google/protobuf/CodedOutputStream.writeUInt32:(II)V
     172: aload_0
     173: getfield      #1                  // Field bitField0_:I
     176: sipush        256
     179: iand
     180: sipush        256
     183: if_icmpne     196
     186: aload_1
     187: bipush        9
     189: aload_0
     190: getfield      #6                  // Field firstDataBlockOffset_:J
     193: invokevirtual #55                 // Method com/google/protobuf/CodedOutputStream.writeUInt64:(IJ)V
     196: aload_0
     197: getfield      #1                  // Field bitField0_:I
     200: sipush        512
     203: iand
     204: sipush        512
     207: if_icmpne     220
     210: aload_1
     211: bipush        10
     213: aload_0
     214: getfield      #5                  // Field lastDataBlockOffset_:J
     217: invokevirtual #55                 // Method com/google/protobuf/CodedOutputStream.writeUInt64:(IJ)V
     220: aload_0
     221: getfield      #1                  // Field bitField0_:I
     224: sipush        1024
     227: iand
     228: sipush        1024
     231: if_icmpne     244
     234: aload_1
     235: bipush        11
     237: aload_0
     238: invokevirtual #57                 // Method getComparatorClassNameBytes:()Lcom/google/protobuf/ByteString;
     241: invokevirtual #58                 // Method com/google/protobuf/CodedOutputStream.writeBytes:(ILcom/google/protobuf/ByteString;)V
     244: aload_0
     245: getfield      #1                  // Field bitField0_:I
     248: sipush        2048
     251: iand
     252: sipush        2048
     255: if_icmpne     268
     258: aload_1
     259: bipush        12
     261: aload_0
     262: getfield      #3                  // Field compressionCodec_:I
     265: invokevirtual #56                 // Method com/google/protobuf/CodedOutputStream.writeUInt32:(II)V
     268: aload_0
     269: getfield      #1                  // Field bitField0_:I
     272: sipush        4096
     275: iand
     276: sipush        4096
     279: if_icmpne     292
     282: aload_1
     283: bipush        13
     285: aload_0
     286: getfield      #2                  // Field encryptionKey_:Lcom/google/protobuf/ByteString;
     289: invokevirtual #58                 // Method com/google/protobuf/CodedOutputStream.writeBytes:(ILcom/google/protobuf/ByteString;)V
     292: aload_0
     293: invokevirtual #59                 // Method getUnknownFields:()Lcom/google/protobuf/UnknownFieldSet;
     296: aload_1
     297: invokevirtual #60                 // Method com/google/protobuf/UnknownFieldSet.writeTo:(Lcom/google/protobuf/CodedOutputStream;)V
     300: return

  public int getSerializedSize();
    Code:
       0: aload_0
       1: getfield      #20                 // Field memoizedSerializedSize:I
       4: istore_1
       5: iload_1
       6: iconst_m1
       7: if_icmpeq     12
      10: iload_1
      11: ireturn
      12: iconst_0
      13: istore_1
      14: aload_0
      15: getfield      #1                  // Field bitField0_:I
      18: iconst_1
      19: iand
      20: iconst_1
      21: if_icmpne     35
      24: iload_1
      25: iconst_1
      26: aload_0
      27: getfield      #14                 // Field fileInfoOffset_:J
      30: invokestatic  #61                 // Method com/google/protobuf/CodedOutputStream.computeUInt64Size:(IJ)I
      33: iadd
      34: istore_1
      35: aload_0
      36: getfield      #1                  // Field bitField0_:I
      39: iconst_2
      40: iand
      41: iconst_2
      42: if_icmpne     56
      45: iload_1
      46: iconst_2
      47: aload_0
      48: getfield      #13                 // Field loadOnOpenDataOffset_:J
      51: invokestatic  #61                 // Method com/google/protobuf/CodedOutputStream.computeUInt64Size:(IJ)I
      54: iadd
      55: istore_1
      56: aload_0
      57: getfield      #1                  // Field bitField0_:I
      60: iconst_4
      61: iand
      62: iconst_4
      63: if_icmpne     77
      66: iload_1
      67: iconst_3
      68: aload_0
      69: getfield      #12                 // Field uncompressedDataIndexSize_:J
      72: invokestatic  #61                 // Method com/google/protobuf/CodedOutputStream.computeUInt64Size:(IJ)I
      75: iadd
      76: istore_1
      77: aload_0
      78: getfield      #1                  // Field bitField0_:I
      81: bipush        8
      83: iand
      84: bipush        8
      86: if_icmpne     100
      89: iload_1
      90: iconst_4
      91: aload_0
      92: getfield      #11                 // Field totalUncompressedBytes_:J
      95: invokestatic  #61                 // Method com/google/protobuf/CodedOutputStream.computeUInt64Size:(IJ)I
      98: iadd
      99: istore_1
     100: aload_0
     101: getfield      #1                  // Field bitField0_:I
     104: bipush        16
     106: iand
     107: bipush        16
     109: if_icmpne     123
     112: iload_1
     113: iconst_5
     114: aload_0
     115: getfield      #10                 // Field dataIndexCount_:I
     118: invokestatic  #62                 // Method com/google/protobuf/CodedOutputStream.computeUInt32Size:(II)I
     121: iadd
     122: istore_1
     123: aload_0
     124: getfield      #1                  // Field bitField0_:I
     127: bipush        32
     129: iand
     130: bipush        32
     132: if_icmpne     147
     135: iload_1
     136: bipush        6
     138: aload_0
     139: getfield      #9                  // Field metaIndexCount_:I
     142: invokestatic  #62                 // Method com/google/protobuf/CodedOutputStream.computeUInt32Size:(II)I
     145: iadd
     146: istore_1
     147: aload_0
     148: getfield      #1                  // Field bitField0_:I
     151: bipush        64
     153: iand
     154: bipush        64
     156: if_icmpne     171
     159: iload_1
     160: bipush        7
     162: aload_0
     163: getfield      #8                  // Field entryCount_:J
     166: invokestatic  #61                 // Method com/google/protobuf/CodedOutputStream.computeUInt64Size:(IJ)I
     169: iadd
     170: istore_1
     171: aload_0
     172: getfield      #1                  // Field bitField0_:I
     175: sipush        128
     178: iand
     179: sipush        128
     182: if_icmpne     197
     185: iload_1
     186: bipush        8
     188: aload_0
     189: getfield      #7                  // Field numDataIndexLevels_:I
     192: invokestatic  #62                 // Method com/google/protobuf/CodedOutputStream.computeUInt32Size:(II)I
     195: iadd
     196: istore_1
     197: aload_0
     198: getfield      #1                  // Field bitField0_:I
     201: sipush        256
     204: iand
     205: sipush        256
     208: if_icmpne     223
     211: iload_1
     212: bipush        9
     214: aload_0
     215: getfield      #6                  // Field firstDataBlockOffset_:J
     218: invokestatic  #61                 // Method com/google/protobuf/CodedOutputStream.computeUInt64Size:(IJ)I
     221: iadd
     222: istore_1
     223: aload_0
     224: getfield      #1                  // Field bitField0_:I
     227: sipush        512
     230: iand
     231: sipush        512
     234: if_icmpne     249
     237: iload_1
     238: bipush        10
     240: aload_0
     241: getfield      #5                  // Field lastDataBlockOffset_:J
     244: invokestatic  #61                 // Method com/google/protobuf/CodedOutputStream.computeUInt64Size:(IJ)I
     247: iadd
     248: istore_1
     249: aload_0
     250: getfield      #1                  // Field bitField0_:I
     253: sipush        1024
     256: iand
     257: sipush        1024
     260: if_icmpne     275
     263: iload_1
     264: bipush        11
     266: aload_0
     267: invokevirtual #57                 // Method getComparatorClassNameBytes:()Lcom/google/protobuf/ByteString;
     270: invokestatic  #63                 // Method com/google/protobuf/CodedOutputStream.computeBytesSize:(ILcom/google/protobuf/ByteString;)I
     273: iadd
     274: istore_1
     275: aload_0
     276: getfield      #1                  // Field bitField0_:I
     279: sipush        2048
     282: iand
     283: sipush        2048
     286: if_icmpne     301
     289: iload_1
     290: bipush        12
     292: aload_0
     293: getfield      #3                  // Field compressionCodec_:I
     296: invokestatic  #62                 // Method com/google/protobuf/CodedOutputStream.computeUInt32Size:(II)I
     299: iadd
     300: istore_1
     301: aload_0
     302: getfield      #1                  // Field bitField0_:I
     305: sipush        4096
     308: iand
     309: sipush        4096
     312: if_icmpne     327
     315: iload_1
     316: bipush        13
     318: aload_0
     319: getfield      #2                  // Field encryptionKey_:Lcom/google/protobuf/ByteString;
     322: invokestatic  #63                 // Method com/google/protobuf/CodedOutputStream.computeBytesSize:(ILcom/google/protobuf/ByteString;)I
     325: iadd
     326: istore_1
     327: iload_1
     328: aload_0
     329: invokevirtual #59                 // Method getUnknownFields:()Lcom/google/protobuf/UnknownFieldSet;
     332: invokevirtual #64                 // Method com/google/protobuf/UnknownFieldSet.getSerializedSize:()I
     335: iadd
     336: istore_1
     337: aload_0
     338: iload_1
     339: putfield      #20                 // Field memoizedSerializedSize:I
     342: iload_1
     343: ireturn

  protected java.lang.Object writeReplace() throws java.io.ObjectStreamException;
    Code:
       0: aload_0
       1: invokespecial #65                 // Method com/google/protobuf/GeneratedMessage.writeReplace:()Ljava/lang/Object;
       4: areturn

  public boolean equals(java.lang.Object);
    Code:
       0: aload_1
       1: aload_0
       2: if_acmpne     7
       5: iconst_1
       6: ireturn
       7: aload_1
       8: instanceof    #43                 // class org/apache/hadoop/hbase/protobuf/generated/HFileProtos$FileTrailerProto
      11: ifne          20
      14: aload_0
      15: aload_1
      16: invokespecial #66                 // Method com/google/protobuf/GeneratedMessage.equals:(Ljava/lang/Object;)Z
      19: ireturn
      20: aload_1
      21: checkcast     #43                 // class org/apache/hadoop/hbase/protobuf/generated/HFileProtos$FileTrailerProto
      24: astore_2
      25: iconst_1
      26: istore_3
      27: iload_3
      28: ifeq          46
      31: aload_0
      32: invokevirtual #67                 // Method hasFileInfoOffset:()Z
      35: aload_2
      36: invokevirtual #67                 // Method hasFileInfoOffset:()Z
      39: if_icmpne     46
      42: iconst_1
      43: goto          47
      46: iconst_0
      47: istore_3
      48: aload_0
      49: invokevirtual #67                 // Method hasFileInfoOffset:()Z
      52: ifeq          77
      55: iload_3
      56: ifeq          75
      59: aload_0
      60: invokevirtual #68                 // Method getFileInfoOffset:()J
      63: aload_2
      64: invokevirtual #68                 // Method getFileInfoOffset:()J
      67: lcmp
      68: ifne          75
      71: iconst_1
      72: goto          76
      75: iconst_0
      76: istore_3
      77: iload_3
      78: ifeq          96
      81: aload_0
      82: invokevirtual #69                 // Method hasLoadOnOpenDataOffset:()Z
      85: aload_2
      86: invokevirtual #69                 // Method hasLoadOnOpenDataOffset:()Z
      89: if_icmpne     96
      92: iconst_1
      93: goto          97
      96: iconst_0
      97: istore_3
      98: aload_0
      99: invokevirtual #69                 // Method hasLoadOnOpenDataOffset:()Z
     102: ifeq          127
     105: iload_3
     106: ifeq          125
     109: aload_0
     110: invokevirtual #70                 // Method getLoadOnOpenDataOffset:()J
     113: aload_2
     114: invokevirtual #70                 // Method getLoadOnOpenDataOffset:()J
     117: lcmp
     118: ifne          125
     121: iconst_1
     122: goto          126
     125: iconst_0
     126: istore_3
     127: iload_3
     128: ifeq          146
     131: aload_0
     132: invokevirtual #71                 // Method hasUncompressedDataIndexSize:()Z
     135: aload_2
     136: invokevirtual #71                 // Method hasUncompressedDataIndexSize:()Z
     139: if_icmpne     146
     142: iconst_1
     143: goto          147
     146: iconst_0
     147: istore_3
     148: aload_0
     149: invokevirtual #71                 // Method hasUncompressedDataIndexSize:()Z
     152: ifeq          177
     155: iload_3
     156: ifeq          175
     159: aload_0
     160: invokevirtual #72                 // Method getUncompressedDataIndexSize:()J
     163: aload_2
     164: invokevirtual #72                 // Method getUncompressedDataIndexSize:()J
     167: lcmp
     168: ifne          175
     171: iconst_1
     172: goto          176
     175: iconst_0
     176: istore_3
     177: iload_3
     178: ifeq          196
     181: aload_0
     182: invokevirtual #73                 // Method hasTotalUncompressedBytes:()Z
     185: aload_2
     186: invokevirtual #73                 // Method hasTotalUncompressedBytes:()Z
     189: if_icmpne     196
     192: iconst_1
     193: goto          197
     196: iconst_0
     197: istore_3
     198: aload_0
     199: invokevirtual #73                 // Method hasTotalUncompressedBytes:()Z
     202: ifeq          227
     205: iload_3
     206: ifeq          225
     209: aload_0
     210: invokevirtual #74                 // Method getTotalUncompressedBytes:()J
     213: aload_2
     214: invokevirtual #74                 // Method getTotalUncompressedBytes:()J
     217: lcmp
     218: ifne          225
     221: iconst_1
     222: goto          226
     225: iconst_0
     226: istore_3
     227: iload_3
     228: ifeq          246
     231: aload_0
     232: invokevirtual #75                 // Method hasDataIndexCount:()Z
     235: aload_2
     236: invokevirtual #75                 // Method hasDataIndexCount:()Z
     239: if_icmpne     246
     242: iconst_1
     243: goto          247
     246: iconst_0
     247: istore_3
     248: aload_0
     249: invokevirtual #75                 // Method hasDataIndexCount:()Z
     252: ifeq          276
     255: iload_3
     256: ifeq          274
     259: aload_0
     260: invokevirtual #76                 // Method getDataIndexCount:()I
     263: aload_2
     264: invokevirtual #76                 // Method getDataIndexCount:()I
     267: if_icmpne     274
     270: iconst_1
     271: goto          275
     274: iconst_0
     275: istore_3
     276: iload_3
     277: ifeq          295
     280: aload_0
     281: invokevirtual #77                 // Method hasMetaIndexCount:()Z
     284: aload_2
     285: invokevirtual #77                 // Method hasMetaIndexCount:()Z
     288: if_icmpne     295
     291: iconst_1
     292: goto          296
     295: iconst_0
     296: istore_3
     297: aload_0
     298: invokevirtual #77                 // Method hasMetaIndexCount:()Z
     301: ifeq          325
     304: iload_3
     305: ifeq          323
     308: aload_0
     309: invokevirtual #78                 // Method getMetaIndexCount:()I
     312: aload_2
     313: invokevirtual #78                 // Method getMetaIndexCount:()I
     316: if_icmpne     323
     319: iconst_1
     320: goto          324
     323: iconst_0
     324: istore_3
     325: iload_3
     326: ifeq          344
     329: aload_0
     330: invokevirtual #79                 // Method hasEntryCount:()Z
     333: aload_2
     334: invokevirtual #79                 // Method hasEntryCount:()Z
     337: if_icmpne     344
     340: iconst_1
     341: goto          345
     344: iconst_0
     345: istore_3
     346: aload_0
     347: invokevirtual #79                 // Method hasEntryCount:()Z
     350: ifeq          375
     353: iload_3
     354: ifeq          373
     357: aload_0
     358: invokevirtual #80                 // Method getEntryCount:()J
     361: aload_2
     362: invokevirtual #80                 // Method getEntryCount:()J
     365: lcmp
     366: ifne          373
     369: iconst_1
     370: goto          374
     373: iconst_0
     374: istore_3
     375: iload_3
     376: ifeq          394
     379: aload_0
     380: invokevirtual #81                 // Method hasNumDataIndexLevels:()Z
     383: aload_2
     384: invokevirtual #81                 // Method hasNumDataIndexLevels:()Z
     387: if_icmpne     394
     390: iconst_1
     391: goto          395
     394: iconst_0
     395: istore_3
     396: aload_0
     397: invokevirtual #81                 // Method hasNumDataIndexLevels:()Z
     400: ifeq          424
     403: iload_3
     404: ifeq          422
     407: aload_0
     408: invokevirtual #82                 // Method getNumDataIndexLevels:()I
     411: aload_2
     412: invokevirtual #82                 // Method getNumDataIndexLevels:()I
     415: if_icmpne     422
     418: iconst_1
     419: goto          423
     422: iconst_0
     423: istore_3
     424: iload_3
     425: ifeq          443
     428: aload_0
     429: invokevirtual #83                 // Method hasFirstDataBlockOffset:()Z
     432: aload_2
     433: invokevirtual #83                 // Method hasFirstDataBlockOffset:()Z
     436: if_icmpne     443
     439: iconst_1
     440: goto          444
     443: iconst_0
     444: istore_3
     445: aload_0
     446: invokevirtual #83                 // Method hasFirstDataBlockOffset:()Z
     449: ifeq          474
     452: iload_3
     453: ifeq          472
     456: aload_0
     457: invokevirtual #84                 // Method getFirstDataBlockOffset:()J
     460: aload_2
     461: invokevirtual #84                 // Method getFirstDataBlockOffset:()J
     464: lcmp
     465: ifne          472
     468: iconst_1
     469: goto          473
     472: iconst_0
     473: istore_3
     474: iload_3
     475: ifeq          493
     478: aload_0
     479: invokevirtual #85                 // Method hasLastDataBlockOffset:()Z
     482: aload_2
     483: invokevirtual #85                 // Method hasLastDataBlockOffset:()Z
     486: if_icmpne     493
     489: iconst_1
     490: goto          494
     493: iconst_0
     494: istore_3
     495: aload_0
     496: invokevirtual #85                 // Method hasLastDataBlockOffset:()Z
     499: ifeq          524
     502: iload_3
     503: ifeq          522
     506: aload_0
     507: invokevirtual #86                 // Method getLastDataBlockOffset:()J
     510: aload_2
     511: invokevirtual #86                 // Method getLastDataBlockOffset:()J
     514: lcmp
     515: ifne          522
     518: iconst_1
     519: goto          523
     522: iconst_0
     523: istore_3
     524: iload_3
     525: ifeq          543
     528: aload_0
     529: invokevirtual #87                 // Method hasComparatorClassName:()Z
     532: aload_2
     533: invokevirtual #87                 // Method hasComparatorClassName:()Z
     536: if_icmpne     543
     539: iconst_1
     540: goto          544
     543: iconst_0
     544: istore_3
     545: aload_0
     546: invokevirtual #87                 // Method hasComparatorClassName:()Z
     549: ifeq          576
     552: iload_3
     553: ifeq          574
     556: aload_0
     557: invokevirtual #88                 // Method getComparatorClassName:()Ljava/lang/String;
     560: aload_2
     561: invokevirtual #88                 // Method getComparatorClassName:()Ljava/lang/String;
     564: invokevirtual #89                 // Method java/lang/String.equals:(Ljava/lang/Object;)Z
     567: ifeq          574
     570: iconst_1
     571: goto          575
     574: iconst_0
     575: istore_3
     576: iload_3
     577: ifeq          595
     580: aload_0
     581: invokevirtual #90                 // Method hasCompressionCodec:()Z
     584: aload_2
     585: invokevirtual #90                 // Method hasCompressionCodec:()Z
     588: if_icmpne     595
     591: iconst_1
     592: goto          596
     595: iconst_0
     596: istore_3
     597: aload_0
     598: invokevirtual #90                 // Method hasCompressionCodec:()Z
     601: ifeq          625
     604: iload_3
     605: ifeq          623
     608: aload_0
     609: invokevirtual #91                 // Method getCompressionCodec:()I
     612: aload_2
     613: invokevirtual #91                 // Method getCompressionCodec:()I
     616: if_icmpne     623
     619: iconst_1
     620: goto          624
     623: iconst_0
     624: istore_3
     625: iload_3
     626: ifeq          644
     629: aload_0
     630: invokevirtual #92                 // Method hasEncryptionKey:()Z
     633: aload_2
     634: invokevirtual #92                 // Method hasEncryptionKey:()Z
     637: if_icmpne     644
     640: iconst_1
     641: goto          645
     644: iconst_0
     645: istore_3
     646: aload_0
     647: invokevirtual #92                 // Method hasEncryptionKey:()Z
     650: ifeq          677
     653: iload_3
     654: ifeq          675
     657: aload_0
     658: invokevirtual #93                 // Method getEncryptionKey:()Lcom/google/protobuf/ByteString;
     661: aload_2
     662: invokevirtual #93                 // Method getEncryptionKey:()Lcom/google/protobuf/ByteString;
     665: invokevirtual #94                 // Method com/google/protobuf/ByteString.equals:(Ljava/lang/Object;)Z
     668: ifeq          675
     671: iconst_1
     672: goto          676
     675: iconst_0
     676: istore_3
     677: iload_3
     678: ifeq          699
     681: aload_0
     682: invokevirtual #59                 // Method getUnknownFields:()Lcom/google/protobuf/UnknownFieldSet;
     685: aload_2
     686: invokevirtual #59                 // Method getUnknownFields:()Lcom/google/protobuf/UnknownFieldSet;
     689: invokevirtual #95                 // Method com/google/protobuf/UnknownFieldSet.equals:(Ljava/lang/Object;)Z
     692: ifeq          699
     695: iconst_1
     696: goto          700
     699: iconst_0
     700: istore_3
     701: iload_3
     702: ireturn

  public int hashCode();
    Code:
       0: aload_0
       1: getfield      #21                 // Field memoizedHashCode:I
       4: ifeq          12
       7: aload_0
       8: getfield      #21                 // Field memoizedHashCode:I
      11: ireturn
      12: bipush        41
      14: istore_1
      15: bipush        19
      17: iload_1
      18: imul
      19: aload_0
      20: invokevirtual #96                 // Method getDescriptorForType:()Lcom/google/protobuf/Descriptors$Descriptor;
      23: invokevirtual #97                 // Method java/lang/Object.hashCode:()I
      26: iadd
      27: istore_1
      28: aload_0
      29: invokevirtual #67                 // Method hasFileInfoOffset:()Z
      32: ifeq          55
      35: bipush        37
      37: iload_1
      38: imul
      39: iconst_1
      40: iadd
      41: istore_1
      42: bipush        53
      44: iload_1
      45: imul
      46: aload_0
      47: invokevirtual #68                 // Method getFileInfoOffset:()J
      50: invokestatic  #98                 // Method hashLong:(J)I
      53: iadd
      54: istore_1
      55: aload_0
      56: invokevirtual #69                 // Method hasLoadOnOpenDataOffset:()Z
      59: ifeq          82
      62: bipush        37
      64: iload_1
      65: imul
      66: iconst_2
      67: iadd
      68: istore_1
      69: bipush        53
      71: iload_1
      72: imul
      73: aload_0
      74: invokevirtual #70                 // Method getLoadOnOpenDataOffset:()J
      77: invokestatic  #98                 // Method hashLong:(J)I
      80: iadd
      81: istore_1
      82: aload_0
      83: invokevirtual #71                 // Method hasUncompressedDataIndexSize:()Z
      86: ifeq          109
      89: bipush        37
      91: iload_1
      92: imul
      93: iconst_3
      94: iadd
      95: istore_1
      96: bipush        53
      98: iload_1
      99: imul
     100: aload_0
     101: invokevirtual #72                 // Method getUncompressedDataIndexSize:()J
     104: invokestatic  #98                 // Method hashLong:(J)I
     107: iadd
     108: istore_1
     109: aload_0
     110: invokevirtual #73                 // Method hasTotalUncompressedBytes:()Z
     113: ifeq          136
     116: bipush        37
     118: iload_1
     119: imul
     120: iconst_4
     121: iadd
     122: istore_1
     123: bipush        53
     125: iload_1
     126: imul
     127: aload_0
     128: invokevirtual #74                 // Method getTotalUncompressedBytes:()J
     131: invokestatic  #98                 // Method hashLong:(J)I
     134: iadd
     135: istore_1
     136: aload_0
     137: invokevirtual #75                 // Method hasDataIndexCount:()Z
     140: ifeq          160
     143: bipush        37
     145: iload_1
     146: imul
     147: iconst_5
     148: iadd
     149: istore_1
     150: bipush        53
     152: iload_1
     153: imul
     154: aload_0
     155: invokevirtual #76                 // Method getDataIndexCount:()I
     158: iadd
     159: istore_1
     160: aload_0
     161: invokevirtual #77                 // Method hasMetaIndexCount:()Z
     164: ifeq          185
     167: bipush        37
     169: iload_1
     170: imul
     171: bipush        6
     173: iadd
     174: istore_1
     175: bipush        53
     177: iload_1
     178: imul
     179: aload_0
     180: invokevirtual #78                 // Method getMetaIndexCount:()I
     183: iadd
     184: istore_1
     185: aload_0
     186: invokevirtual #79                 // Method hasEntryCount:()Z
     189: ifeq          213
     192: bipush        37
     194: iload_1
     195: imul
     196: bipush        7
     198: iadd
     199: istore_1
     200: bipush        53
     202: iload_1
     203: imul
     204: aload_0
     205: invokevirtual #80                 // Method getEntryCount:()J
     208: invokestatic  #98                 // Method hashLong:(J)I
     211: iadd
     212: istore_1
     213: aload_0
     214: invokevirtual #81                 // Method hasNumDataIndexLevels:()Z
     217: ifeq          238
     220: bipush        37
     222: iload_1
     223: imul
     224: bipush        8
     226: iadd
     227: istore_1
     228: bipush        53
     230: iload_1
     231: imul
     232: aload_0
     233: invokevirtual #82                 // Method getNumDataIndexLevels:()I
     236: iadd
     237: istore_1
     238: aload_0
     239: invokevirtual #83                 // Method hasFirstDataBlockOffset:()Z
     242: ifeq          266
     245: bipush        37
     247: iload_1
     248: imul
     249: bipush        9
     251: iadd
     252: istore_1
     253: bipush        53
     255: iload_1
     256: imul
     257: aload_0
     258: invokevirtual #84                 // Method getFirstDataBlockOffset:()J
     261: invokestatic  #98                 // Method hashLong:(J)I
     264: iadd
     265: istore_1
     266: aload_0
     267: invokevirtual #85                 // Method hasLastDataBlockOffset:()Z
     270: ifeq          294
     273: bipush        37
     275: iload_1
     276: imul
     277: bipush        10
     279: iadd
     280: istore_1
     281: bipush        53
     283: iload_1
     284: imul
     285: aload_0
     286: invokevirtual #86                 // Method getLastDataBlockOffset:()J
     289: invokestatic  #98                 // Method hashLong:(J)I
     292: iadd
     293: istore_1
     294: aload_0
     295: invokevirtual #87                 // Method hasComparatorClassName:()Z
     298: ifeq          322
     301: bipush        37
     303: iload_1
     304: imul
     305: bipush        11
     307: iadd
     308: istore_1
     309: bipush        53
     311: iload_1
     312: imul
     313: aload_0
     314: invokevirtual #88                 // Method getComparatorClassName:()Ljava/lang/String;
     317: invokevirtual #99                 // Method java/lang/String.hashCode:()I
     320: iadd
     321: istore_1
     322: aload_0
     323: invokevirtual #90                 // Method hasCompressionCodec:()Z
     326: ifeq          347
     329: bipush        37
     331: iload_1
     332: imul
     333: bipush        12
     335: iadd
     336: istore_1
     337: bipush        53
     339: iload_1
     340: imul
     341: aload_0
     342: invokevirtual #91                 // Method getCompressionCodec:()I
     345: iadd
     346: istore_1
     347: aload_0
     348: invokevirtual #92                 // Method hasEncryptionKey:()Z
     351: ifeq          375
     354: bipush        37
     356: iload_1
     357: imul
     358: bipush        13
     360: iadd
     361: istore_1
     362: bipush        53
     364: iload_1
     365: imul
     366: aload_0
     367: invokevirtual #93                 // Method getEncryptionKey:()Lcom/google/protobuf/ByteString;
     370: invokevirtual #100                // Method com/google/protobuf/ByteString.hashCode:()I
     373: iadd
     374: istore_1
     375: bipush        29
     377: iload_1
     378: imul
     379: aload_0
     380: invokevirtual #59                 // Method getUnknownFields:()Lcom/google/protobuf/UnknownFieldSet;
     383: invokevirtual #101                // Method com/google/protobuf/UnknownFieldSet.hashCode:()I
     386: iadd
     387: istore_1
     388: aload_0
     389: iload_1
     390: putfield      #21                 // Field memoizedHashCode:I
     393: iload_1
     394: ireturn

  public static org.apache.hadoop.hbase.protobuf.generated.HFileProtos$FileTrailerProto parseFrom(com.google.protobuf.ByteString) throws com.google.protobuf.InvalidProtocolBufferException;
    Code:
       0: getstatic     #46                 // Field PARSER:Lcom/google/protobuf/Parser;
       3: aload_0
       4: invokeinterface #102,  2          // InterfaceMethod com/google/protobuf/Parser.parseFrom:(Lcom/google/protobuf/ByteString;)Ljava/lang/Object;
       9: checkcast     #43                 // class org/apache/hadoop/hbase/protobuf/generated/HFileProtos$FileTrailerProto
      12: areturn

  public static org.apache.hadoop.hbase.protobuf.generated.HFileProtos$FileTrailerProto parseFrom(com.google.protobuf.ByteString, com.google.protobuf.ExtensionRegistryLite) throws com.google.protobuf.InvalidProtocolBufferException;
    Code:
       0: getstatic     #46                 // Field PARSER:Lcom/google/protobuf/Parser;
       3: aload_0
       4: aload_1
       5: invokeinterface #103,  3          // InterfaceMethod com/google/protobuf/Parser.parseFrom:(Lcom/google/protobuf/ByteString;Lcom/google/protobuf/ExtensionRegistryLite;)Ljava/lang/Object;
      10: checkcast     #43                 // class org/apache/hadoop/hbase/protobuf/generated/HFileProtos$FileTrailerProto
      13: areturn

  public static org.apache.hadoop.hbase.protobuf.generated.HFileProtos$FileTrailerProto parseFrom(byte[]) throws com.google.protobuf.InvalidProtocolBufferException;
    Code:
       0: getstatic     #46                 // Field PARSER:Lcom/google/protobuf/Parser;
       3: aload_0
       4: invokeinterface #104,  2          // InterfaceMethod com/google/protobuf/Parser.parseFrom:([B)Ljava/lang/Object;
       9: checkcast     #43                 // class org/apache/hadoop/hbase/protobuf/generated/HFileProtos$FileTrailerProto
      12: areturn

  public static org.apache.hadoop.hbase.protobuf.generated.HFileProtos$FileTrailerProto parseFrom(byte[], com.google.protobuf.ExtensionRegistryLite) throws com.google.protobuf.InvalidProtocolBufferException;
    Code:
       0: getstatic     #46                 // Field PARSER:Lcom/google/protobuf/Parser;
       3: aload_0
       4: aload_1
       5: invokeinterface #105,  3          // InterfaceMethod com/google/protobuf/Parser.parseFrom:([BLcom/google/protobuf/ExtensionRegistryLite;)Ljava/lang/Object;
      10: checkcast     #43                 // class org/apache/hadoop/hbase/protobuf/generated/HFileProtos$FileTrailerProto
      13: areturn

  public static org.apache.hadoop.hbase.protobuf.generated.HFileProtos$FileTrailerProto parseFrom(java.io.InputStream) throws java.io.IOException;
    Code:
       0: getstatic     #46                 // Field PARSER:Lcom/google/protobuf/Parser;
       3: aload_0
       4: invokeinterface #106,  2          // InterfaceMethod com/google/protobuf/Parser.parseFrom:(Ljava/io/InputStream;)Ljava/lang/Object;
       9: checkcast     #43                 // class org/apache/hadoop/hbase/protobuf/generated/HFileProtos$FileTrailerProto
      12: areturn

  public static org.apache.hadoop.hbase.protobuf.generated.HFileProtos$FileTrailerProto parseFrom(java.io.InputStream, com.google.protobuf.ExtensionRegistryLite) throws java.io.IOException;
    Code:
       0: getstatic     #46                 // Field PARSER:Lcom/google/protobuf/Parser;
       3: aload_0
       4: aload_1
       5: invokeinterface #107,  3          // InterfaceMethod com/google/protobuf/Parser.parseFrom:(Ljava/io/InputStream;Lcom/google/protobuf/ExtensionRegistryLite;)Ljava/lang/Object;
      10: checkcast     #43                 // class org/apache/hadoop/hbase/protobuf/generated/HFileProtos$FileTrailerProto
      13: areturn

  public static org.apache.hadoop.hbase.protobuf.generated.HFileProtos$FileTrailerProto parseDelimitedFrom(java.io.InputStream) throws java.io.IOException;
    Code:
       0: getstatic     #46                 // Field PARSER:Lcom/google/protobuf/Parser;
       3: aload_0
       4: invokeinterface #108,  2          // InterfaceMethod com/google/protobuf/Parser.parseDelimitedFrom:(Ljava/io/InputStream;)Ljava/lang/Object;
       9: checkcast     #43                 // class org/apache/hadoop/hbase/protobuf/generated/HFileProtos$FileTrailerProto
      12: areturn

  public static org.apache.hadoop.hbase.protobuf.generated.HFileProtos$FileTrailerProto parseDelimitedFrom(java.io.InputStream, com.google.protobuf.ExtensionRegistryLite) throws java.io.IOException;
    Code:
       0: getstatic     #46                 // Field PARSER:Lcom/google/protobuf/Parser;
       3: aload_0
       4: aload_1
       5: invokeinterface #109,  3          // InterfaceMethod com/google/protobuf/Parser.parseDelimitedFrom:(Ljava/io/InputStream;Lcom/google/protobuf/ExtensionRegistryLite;)Ljava/lang/Object;
      10: checkcast     #43                 // class org/apache/hadoop/hbase/protobuf/generated/HFileProtos$FileTrailerProto
      13: areturn

  public static org.apache.hadoop.hbase.protobuf.generated.HFileProtos$FileTrailerProto parseFrom(com.google.protobuf.CodedInputStream) throws java.io.IOException;
    Code:
       0: getstatic     #46                 // Field PARSER:Lcom/google/protobuf/Parser;
       3: aload_0
       4: invokeinterface #110,  2          // InterfaceMethod com/google/protobuf/Parser.parseFrom:(Lcom/google/protobuf/CodedInputStream;)Ljava/lang/Object;
       9: checkcast     #43                 // class org/apache/hadoop/hbase/protobuf/generated/HFileProtos$FileTrailerProto
      12: areturn

  public static org.apache.hadoop.hbase.protobuf.generated.HFileProtos$FileTrailerProto parseFrom(com.google.protobuf.CodedInputStream, com.google.protobuf.ExtensionRegistryLite) throws java.io.IOException;
    Code:
       0: getstatic     #46                 // Field PARSER:Lcom/google/protobuf/Parser;
       3: aload_0
       4: aload_1
       5: invokeinterface #111,  3          // InterfaceMethod com/google/protobuf/Parser.parseFrom:(Lcom/google/protobuf/CodedInputStream;Lcom/google/protobuf/ExtensionRegistryLite;)Ljava/lang/Object;
      10: checkcast     #43                 // class org/apache/hadoop/hbase/protobuf/generated/HFileProtos$FileTrailerProto
      13: areturn

  public static org.apache.hadoop.hbase.protobuf.generated.HFileProtos$FileTrailerProto$Builder newBuilder();
    Code:
       0: invokestatic  #112                // Method org/apache/hadoop/hbase/protobuf/generated/HFileProtos$FileTrailerProto$Builder.access$1200:()Lorg/apache/hadoop/hbase/protobuf/generated/HFileProtos$FileTrailerProto$Builder;
       3: areturn

  public org.apache.hadoop.hbase.protobuf.generated.HFileProtos$FileTrailerProto$Builder newBuilderForType();
    Code:
       0: invokestatic  #113                // Method newBuilder:()Lorg/apache/hadoop/hbase/protobuf/generated/HFileProtos$FileTrailerProto$Builder;
       3: areturn

  public static org.apache.hadoop.hbase.protobuf.generated.HFileProtos$FileTrailerProto$Builder newBuilder(org.apache.hadoop.hbase.protobuf.generated.HFileProtos$FileTrailerProto);
    Code:
       0: invokestatic  #113                // Method newBuilder:()Lorg/apache/hadoop/hbase/protobuf/generated/HFileProtos$FileTrailerProto$Builder;
       3: aload_0
       4: invokevirtual #114                // Method org/apache/hadoop/hbase/protobuf/generated/HFileProtos$FileTrailerProto$Builder.mergeFrom:(Lorg/apache/hadoop/hbase/protobuf/generated/HFileProtos$FileTrailerProto;)Lorg/apache/hadoop/hbase/protobuf/generated/HFileProtos$FileTrailerProto$Builder;
       7: areturn

  public org.apache.hadoop.hbase.protobuf.generated.HFileProtos$FileTrailerProto$Builder toBuilder();
    Code:
       0: aload_0
       1: invokestatic  #115                // Method newBuilder:(Lorg/apache/hadoop/hbase/protobuf/generated/HFileProtos$FileTrailerProto;)Lorg/apache/hadoop/hbase/protobuf/generated/HFileProtos$FileTrailerProto$Builder;
       4: areturn

  protected org.apache.hadoop.hbase.protobuf.generated.HFileProtos$FileTrailerProto$Builder newBuilderForType(com.google.protobuf.GeneratedMessage$BuilderParent);
    Code:
       0: new           #44                 // class org/apache/hadoop/hbase/protobuf/generated/HFileProtos$FileTrailerProto$Builder
       3: dup
       4: aload_1
       5: aconst_null
       6: invokespecial #116                // Method org/apache/hadoop/hbase/protobuf/generated/HFileProtos$FileTrailerProto$Builder."<init>":(Lcom/google/protobuf/GeneratedMessage$BuilderParent;Lorg/apache/hadoop/hbase/protobuf/generated/HFileProtos$1;)V
       9: astore_2
      10: aload_2
      11: areturn

  protected com.google.protobuf.Message$Builder newBuilderForType(com.google.protobuf.GeneratedMessage$BuilderParent);
    Code:
       0: aload_0
       1: aload_1
       2: invokevirtual #117                // Method newBuilderForType:(Lcom/google/protobuf/GeneratedMessage$BuilderParent;)Lorg/apache/hadoop/hbase/protobuf/generated/HFileProtos$FileTrailerProto$Builder;
       5: areturn

  public com.google.protobuf.Message$Builder toBuilder();
    Code:
       0: aload_0
       1: invokevirtual #118                // Method toBuilder:()Lorg/apache/hadoop/hbase/protobuf/generated/HFileProtos$FileTrailerProto$Builder;
       4: areturn

  public com.google.protobuf.Message$Builder newBuilderForType();
    Code:
       0: aload_0
       1: invokevirtual #119                // Method newBuilderForType:()Lorg/apache/hadoop/hbase/protobuf/generated/HFileProtos$FileTrailerProto$Builder;
       4: areturn

  public com.google.protobuf.MessageLite$Builder toBuilder();
    Code:
       0: aload_0
       1: invokevirtual #118                // Method toBuilder:()Lorg/apache/hadoop/hbase/protobuf/generated/HFileProtos$FileTrailerProto$Builder;
       4: areturn

  public com.google.protobuf.MessageLite$Builder newBuilderForType();
    Code:
       0: aload_0
       1: invokevirtual #119                // Method newBuilderForType:()Lorg/apache/hadoop/hbase/protobuf/generated/HFileProtos$FileTrailerProto$Builder;
       4: areturn

  public com.google.protobuf.MessageLite getDefaultInstanceForType();
    Code:
       0: aload_0
       1: invokevirtual #120                // Method getDefaultInstanceForType:()Lorg/apache/hadoop/hbase/protobuf/generated/HFileProtos$FileTrailerProto;
       4: areturn

  public com.google.protobuf.Message getDefaultInstanceForType();
    Code:
       0: aload_0
       1: invokevirtual #120                // Method getDefaultInstanceForType:()Lorg/apache/hadoop/hbase/protobuf/generated/HFileProtos$FileTrailerProto;
       4: areturn

  org.apache.hadoop.hbase.protobuf.generated.HFileProtos$FileTrailerProto(com.google.protobuf.CodedInputStream, com.google.protobuf.ExtensionRegistryLite, org.apache.hadoop.hbase.protobuf.generated.HFileProtos$1) throws com.google.protobuf.InvalidProtocolBufferException;
    Code:
       0: aload_0
       1: aload_1
       2: aload_2
       3: invokespecial #17                 // Method "<init>":(Lcom/google/protobuf/CodedInputStream;Lcom/google/protobuf/ExtensionRegistryLite;)V
       6: return

  static boolean access$1400();
    Code:
       0: getstatic     #16                 // Field alwaysUseFieldBuilders:Z
       3: ireturn

  org.apache.hadoop.hbase.protobuf.generated.HFileProtos$FileTrailerProto(com.google.protobuf.GeneratedMessage$Builder, org.apache.hadoop.hbase.protobuf.generated.HFileProtos$1);
    Code:
       0: aload_0
       1: aload_1
       2: invokespecial #15                 // Method "<init>":(Lcom/google/protobuf/GeneratedMessage$Builder;)V
       5: return

  static long access$1602(org.apache.hadoop.hbase.protobuf.generated.HFileProtos$FileTrailerProto, long);
    Code:
       0: aload_0
       1: lload_1
       2: dup2_x1
       3: putfield      #14                 // Field fileInfoOffset_:J
       6: lreturn

  static long access$1702(org.apache.hadoop.hbase.protobuf.generated.HFileProtos$FileTrailerProto, long);
    Code:
       0: aload_0
       1: lload_1
       2: dup2_x1
       3: putfield      #13                 // Field loadOnOpenDataOffset_:J
       6: lreturn

  static long access$1802(org.apache.hadoop.hbase.protobuf.generated.HFileProtos$FileTrailerProto, long);
    Code:
       0: aload_0
       1: lload_1
       2: dup2_x1
       3: putfield      #12                 // Field uncompressedDataIndexSize_:J
       6: lreturn

  static long access$1902(org.apache.hadoop.hbase.protobuf.generated.HFileProtos$FileTrailerProto, long);
    Code:
       0: aload_0
       1: lload_1
       2: dup2_x1
       3: putfield      #11                 // Field totalUncompressedBytes_:J
       6: lreturn

  static int access$2002(org.apache.hadoop.hbase.protobuf.generated.HFileProtos$FileTrailerProto, int);
    Code:
       0: aload_0
       1: iload_1
       2: dup_x1
       3: putfield      #10                 // Field dataIndexCount_:I
       6: ireturn

  static int access$2102(org.apache.hadoop.hbase.protobuf.generated.HFileProtos$FileTrailerProto, int);
    Code:
       0: aload_0
       1: iload_1
       2: dup_x1
       3: putfield      #9                  // Field metaIndexCount_:I
       6: ireturn

  static long access$2202(org.apache.hadoop.hbase.protobuf.generated.HFileProtos$FileTrailerProto, long);
    Code:
       0: aload_0
       1: lload_1
       2: dup2_x1
       3: putfield      #8                  // Field entryCount_:J
       6: lreturn

  static int access$2302(org.apache.hadoop.hbase.protobuf.generated.HFileProtos$FileTrailerProto, int);
    Code:
       0: aload_0
       1: iload_1
       2: dup_x1
       3: putfield      #7                  // Field numDataIndexLevels_:I
       6: ireturn

  static long access$2402(org.apache.hadoop.hbase.protobuf.generated.HFileProtos$FileTrailerProto, long);
    Code:
       0: aload_0
       1: lload_1
       2: dup2_x1
       3: putfield      #6                  // Field firstDataBlockOffset_:J
       6: lreturn

  static long access$2502(org.apache.hadoop.hbase.protobuf.generated.HFileProtos$FileTrailerProto, long);
    Code:
       0: aload_0
       1: lload_1
       2: dup2_x1
       3: putfield      #5                  // Field lastDataBlockOffset_:J
       6: lreturn

  static java.lang.Object access$2602(org.apache.hadoop.hbase.protobuf.generated.HFileProtos$FileTrailerProto, java.lang.Object);
    Code:
       0: aload_0
       1: aload_1
       2: dup_x1
       3: putfield      #4                  // Field comparatorClassName_:Ljava/lang/Object;
       6: areturn

  static int access$2702(org.apache.hadoop.hbase.protobuf.generated.HFileProtos$FileTrailerProto, int);
    Code:
       0: aload_0
       1: iload_1
       2: dup_x1
       3: putfield      #3                  // Field compressionCodec_:I
       6: ireturn

  static com.google.protobuf.ByteString access$2802(org.apache.hadoop.hbase.protobuf.generated.HFileProtos$FileTrailerProto, com.google.protobuf.ByteString);
    Code:
       0: aload_0
       1: aload_1
       2: dup_x1
       3: putfield      #2                  // Field encryptionKey_:Lcom/google/protobuf/ByteString;
       6: areturn

  static int access$2902(org.apache.hadoop.hbase.protobuf.generated.HFileProtos$FileTrailerProto, int);
    Code:
       0: aload_0
       1: iload_1
       2: dup_x1
       3: putfield      #1                  // Field bitField0_:I
       6: ireturn

  static java.lang.Object access$2600(org.apache.hadoop.hbase.protobuf.generated.HFileProtos$FileTrailerProto);
    Code:
       0: aload_0
       1: getfield      #4                  // Field comparatorClassName_:Ljava/lang/Object;
       4: areturn

  static {};
    Code:
       0: new           #121                // class org/apache/hadoop/hbase/protobuf/generated/HFileProtos$FileTrailerProto$1
       3: dup
       4: invokespecial #122                // Method org/apache/hadoop/hbase/protobuf/generated/HFileProtos$FileTrailerProto$1."<init>":()V
       7: putstatic     #46                 // Field PARSER:Lcom/google/protobuf/Parser;
      10: new           #43                 // class org/apache/hadoop/hbase/protobuf/generated/HFileProtos$FileTrailerProto
      13: dup
      14: iconst_1
      15: invokespecial #123                // Method "<init>":(Z)V
      18: putstatic     #26                 // Field defaultInstance:Lorg/apache/hadoop/hbase/protobuf/generated/HFileProtos$FileTrailerProto;
      21: getstatic     #26                 // Field defaultInstance:Lorg/apache/hadoop/hbase/protobuf/generated/HFileProtos$FileTrailerProto;
      24: invokespecial #27                 // Method initFields:()V
      27: return
}
