Compiled from "HFileSystem.java"
final class org.apache.hadoop.hbase.fs.HFileSystem$1 implements java.lang.reflect.InvocationHandler {
  final org.apache.hadoop.hdfs.protocol.ClientProtocol val$cp;

  final org.apache.hadoop.hbase.fs.HFileSystem$ReorderBlocks val$lrb;

  final org.apache.hadoop.conf.Configuration val$conf;

  org.apache.hadoop.hbase.fs.HFileSystem$1(org.apache.hadoop.hdfs.protocol.ClientProtocol, org.apache.hadoop.hbase.fs.HFileSystem$ReorderBlocks, org.apache.hadoop.conf.Configuration);
    Code:
       0: aload_0
       1: aload_1
       2: putfield      #1                  // Field val$cp:Lorg/apache/hadoop/hdfs/protocol/ClientProtocol;
       5: aload_0
       6: aload_2
       7: putfield      #2                  // Field val$lrb:Lorg/apache/hadoop/hbase/fs/HFileSystem$ReorderBlocks;
      10: aload_0
      11: aload_3
      12: putfield      #3                  // Field val$conf:Lorg/apache/hadoop/conf/Configuration;
      15: aload_0
      16: invokespecial #4                  // Method java/lang/Object."<init>":()V
      19: return

  public java.lang.Object invoke(java.lang.Object, java.lang.reflect.Method, java.lang.Object[]) throws java.lang.Throwable;
    Code:
       0: aload_3
       1: ifnull        9
       4: aload_3
       5: arraylength
       6: ifne          30
       9: ldc           #5                  // String close
      11: aload_2
      12: invokevirtual #6                  // Method java/lang/reflect/Method.getName:()Ljava/lang/String;
      15: invokevirtual #7                  // Method java/lang/String.equals:(Ljava/lang/Object;)Z
      18: ifeq          30
      21: aload_0
      22: getfield      #1                  // Field val$cp:Lorg/apache/hadoop/hdfs/protocol/ClientProtocol;
      25: invokestatic  #8                  // Method org/apache/hadoop/ipc/RPC.stopProxy:(Ljava/lang/Object;)V
      28: aconst_null
      29: areturn
      30: aload_2
      31: aload_0
      32: getfield      #1                  // Field val$cp:Lorg/apache/hadoop/hdfs/protocol/ClientProtocol;
      35: aload_3
      36: invokevirtual #9                  // Method java/lang/reflect/Method.invoke:(Ljava/lang/Object;[Ljava/lang/Object;)Ljava/lang/Object;
      39: astore        4
      41: aload         4
      43: ifnull        115
      46: aload_3
      47: ifnull        115
      50: aload_3
      51: arraylength
      52: iconst_3
      53: if_icmpne     115
      56: ldc           #10                 // String getBlockLocations
      58: aload_2
      59: invokevirtual #6                  // Method java/lang/reflect/Method.getName:()Ljava/lang/String;
      62: invokevirtual #7                  // Method java/lang/String.equals:(Ljava/lang/Object;)Z
      65: ifeq          115
      68: aload         4
      70: instanceof    #11                 // class org/apache/hadoop/hdfs/protocol/LocatedBlocks
      73: ifeq          115
      76: aload_3
      77: iconst_0
      78: aaload
      79: instanceof    #12                 // class java/lang/String
      82: ifeq          115
      85: aload_3
      86: iconst_0
      87: aaload
      88: ifnull        115
      91: aload_0
      92: getfield      #2                  // Field val$lrb:Lorg/apache/hadoop/hbase/fs/HFileSystem$ReorderBlocks;
      95: aload_0
      96: getfield      #3                  // Field val$conf:Lorg/apache/hadoop/conf/Configuration;
      99: aload         4
     101: checkcast     #11                 // class org/apache/hadoop/hdfs/protocol/LocatedBlocks
     104: aload_3
     105: iconst_0
     106: aaload
     107: checkcast     #12                 // class java/lang/String
     110: invokeinterface #13,  4           // InterfaceMethod org/apache/hadoop/hbase/fs/HFileSystem$ReorderBlocks.reorderBlocks:(Lorg/apache/hadoop/conf/Configuration;Lorg/apache/hadoop/hdfs/protocol/LocatedBlocks;Ljava/lang/String;)V
     115: aload         4
     117: areturn
     118: astore        4
     120: aload         4
     122: invokevirtual #15                 // Method java/lang/reflect/InvocationTargetException.getCause:()Ljava/lang/Throwable;
     125: astore        5
     127: aload         5
     129: ifnonnull     144
     132: new           #16                 // class java/lang/RuntimeException
     135: dup
     136: ldc           #17                 // String Proxy invocation failed and getCause is null
     138: aload         4
     140: invokespecial #18                 // Method java/lang/RuntimeException."<init>":(Ljava/lang/String;Ljava/lang/Throwable;)V
     143: athrow
     144: aload         5
     146: instanceof    #19                 // class java/lang/reflect/UndeclaredThrowableException
     149: ifeq          181
     152: aload         5
     154: invokevirtual #20                 // Method java/lang/Throwable.getCause:()Ljava/lang/Throwable;
     157: astore        6
     159: aload         6
     161: ifnonnull     174
     164: new           #16                 // class java/lang/RuntimeException
     167: dup
     168: ldc           #21                 // String UndeclaredThrowableException had null cause!
     170: invokespecial #22                 // Method java/lang/RuntimeException."<init>":(Ljava/lang/String;)V
     173: athrow
     174: aload         5
     176: invokevirtual #20                 // Method java/lang/Throwable.getCause:()Ljava/lang/Throwable;
     179: astore        5
     181: aload         5
     183: athrow
    Exception table:
       from    to  target type
           0    29   118   Class java/lang/reflect/InvocationTargetException
          30   117   118   Class java/lang/reflect/InvocationTargetException
}
