Compiled from "HFileCleaner.java"
class org.apache.hadoop.hbase.master.cleaner.HFileCleaner$2 extends java.lang.Thread {
  final org.apache.hadoop.hbase.master.cleaner.HFileCleaner this$0;

  org.apache.hadoop.hbase.master.cleaner.HFileCleaner$2(org.apache.hadoop.hbase.master.cleaner.HFileCleaner);
    Code:
       0: aload_0
       1: aload_1
       2: putfield      #1                  // Field this$0:Lorg/apache/hadoop/hbase/master/cleaner/HFileCleaner;
       5: aload_0
       6: invokespecial #2                  // Method java/lang/Thread."<init>":()V
       9: return

  public void run();
    Code:
       0: aload_0
       1: getfield      #1                  // Field this$0:Lorg/apache/hadoop/hbase/master/cleaner/HFileCleaner;
       4: aload_0
       5: getfield      #1                  // Field this$0:Lorg/apache/hadoop/hbase/master/cleaner/HFileCleaner;
       8: getfield      #3                  // Field org/apache/hadoop/hbase/master/cleaner/HFileCleaner.smallFileQueue:Ljava/util/concurrent/BlockingQueue;
      11: invokevirtual #4                  // Method org/apache/hadoop/hbase/master/cleaner/HFileCleaner.consumerLoop:(Ljava/util/concurrent/BlockingQueue;)V
      14: return
}
