Compiled from "HFileLink.java"
public class org.apache.hadoop.hbase.io.HFileLink extends org.apache.hadoop.hbase.io.FileLink {
  public static final java.lang.String LINK_NAME_REGEX;

  static final java.util.regex.Pattern LINK_NAME_PATTERN;

  public org.apache.hadoop.hbase.io.HFileLink(org.apache.hadoop.fs.Path, org.apache.hadoop.fs.Path, org.apache.hadoop.fs.Path, org.apache.hadoop.fs.Path);
    Code:
       0: aload_0
       1: invokespecial #1                  // Method org/apache/hadoop/hbase/io/FileLink."<init>":()V
       4: aload_0
       5: aload_2
       6: putfield      #2                  // Field tempPath:Lorg/apache/hadoop/fs/Path;
       9: aload_0
      10: aload_1
      11: putfield      #3                  // Field originPath:Lorg/apache/hadoop/fs/Path;
      14: aload_0
      15: aload_3
      16: putfield      #4                  // Field mobPath:Lorg/apache/hadoop/fs/Path;
      19: aload_0
      20: aload         4
      22: putfield      #5                  // Field archivePath:Lorg/apache/hadoop/fs/Path;
      25: aload_0
      26: aload_1
      27: iconst_3
      28: anewarray     #6                  // class org/apache/hadoop/fs/Path
      31: dup
      32: iconst_0
      33: aload_2
      34: aastore
      35: dup
      36: iconst_1
      37: aload_3
      38: aastore
      39: dup
      40: iconst_2
      41: aload         4
      43: aastore
      44: invokevirtual #7                  // Method setLocations:(Lorg/apache/hadoop/fs/Path;[Lorg/apache/hadoop/fs/Path;)V
      47: return

  public static final org.apache.hadoop.hbase.io.HFileLink buildFromHFileLinkPattern(org.apache.hadoop.conf.Configuration, org.apache.hadoop.fs.Path) throws java.io.IOException;
    Code:
       0: aload_0
       1: invokestatic  #8                  // Method org/apache/hadoop/hbase/util/FSUtils.getRootDir:(Lorg/apache/hadoop/conf/Configuration;)Lorg/apache/hadoop/fs/Path;
       4: aload_0
       5: invokestatic  #9                  // Method org/apache/hadoop/hbase/util/HFileArchiveUtil.getArchivePath:(Lorg/apache/hadoop/conf/Configuration;)Lorg/apache/hadoop/fs/Path;
       8: aload_1
       9: invokestatic  #10                 // Method buildFromHFileLinkPattern:(Lorg/apache/hadoop/fs/Path;Lorg/apache/hadoop/fs/Path;Lorg/apache/hadoop/fs/Path;)Lorg/apache/hadoop/hbase/io/HFileLink;
      12: areturn

  public static final org.apache.hadoop.hbase.io.HFileLink buildFromHFileLinkPattern(org.apache.hadoop.fs.Path, org.apache.hadoop.fs.Path, org.apache.hadoop.fs.Path);
    Code:
       0: aload_2
       1: invokestatic  #11                 // Method getHFileLinkPatternRelativePath:(Lorg/apache/hadoop/fs/Path;)Lorg/apache/hadoop/fs/Path;
       4: astore_3
       5: new           #6                  // class org/apache/hadoop/fs/Path
       8: dup
       9: new           #6                  // class org/apache/hadoop/fs/Path
      12: dup
      13: aload_0
      14: ldc           #13                 // String .tmp
      16: invokespecial #14                 // Method org/apache/hadoop/fs/Path."<init>":(Lorg/apache/hadoop/fs/Path;Ljava/lang/String;)V
      19: aload_3
      20: invokespecial #15                 // Method org/apache/hadoop/fs/Path."<init>":(Lorg/apache/hadoop/fs/Path;Lorg/apache/hadoop/fs/Path;)V
      23: astore        4
      25: new           #6                  // class org/apache/hadoop/fs/Path
      28: dup
      29: aload_0
      30: aload_3
      31: invokespecial #15                 // Method org/apache/hadoop/fs/Path."<init>":(Lorg/apache/hadoop/fs/Path;Lorg/apache/hadoop/fs/Path;)V
      34: astore        5
      36: new           #6                  // class org/apache/hadoop/fs/Path
      39: dup
      40: new           #6                  // class org/apache/hadoop/fs/Path
      43: dup
      44: aload_0
      45: ldc           #17                 // String mobdir
      47: invokespecial #14                 // Method org/apache/hadoop/fs/Path."<init>":(Lorg/apache/hadoop/fs/Path;Ljava/lang/String;)V
      50: aload_3
      51: invokespecial #15                 // Method org/apache/hadoop/fs/Path."<init>":(Lorg/apache/hadoop/fs/Path;Lorg/apache/hadoop/fs/Path;)V
      54: astore        6
      56: new           #6                  // class org/apache/hadoop/fs/Path
      59: dup
      60: aload_1
      61: aload_3
      62: invokespecial #15                 // Method org/apache/hadoop/fs/Path."<init>":(Lorg/apache/hadoop/fs/Path;Lorg/apache/hadoop/fs/Path;)V
      65: astore        7
      67: new           #18                 // class org/apache/hadoop/hbase/io/HFileLink
      70: dup
      71: aload         5
      73: aload         4
      75: aload         6
      77: aload         7
      79: invokespecial #19                 // Method "<init>":(Lorg/apache/hadoop/fs/Path;Lorg/apache/hadoop/fs/Path;Lorg/apache/hadoop/fs/Path;Lorg/apache/hadoop/fs/Path;)V
      82: areturn

  public static org.apache.hadoop.fs.Path createPath(org.apache.hadoop.hbase.TableName, java.lang.String, java.lang.String, java.lang.String);
    Code:
       0: aload_3
       1: invokestatic  #20                 // Method isHFileLink:(Ljava/lang/String;)Z
       4: ifeq          17
       7: new           #6                  // class org/apache/hadoop/fs/Path
      10: dup
      11: aload_2
      12: aload_3
      13: invokespecial #21                 // Method org/apache/hadoop/fs/Path."<init>":(Ljava/lang/String;Ljava/lang/String;)V
      16: areturn
      17: new           #6                  // class org/apache/hadoop/fs/Path
      20: dup
      21: aload_2
      22: aload_0
      23: aload_1
      24: aload_3
      25: invokestatic  #22                 // Method createHFileLinkName:(Lorg/apache/hadoop/hbase/TableName;Ljava/lang/String;Ljava/lang/String;)Ljava/lang/String;
      28: invokespecial #21                 // Method org/apache/hadoop/fs/Path."<init>":(Ljava/lang/String;Ljava/lang/String;)V
      31: areturn

  public static org.apache.hadoop.hbase.io.HFileLink build(org.apache.hadoop.conf.Configuration, org.apache.hadoop.hbase.TableName, java.lang.String, java.lang.String, java.lang.String) throws java.io.IOException;
    Code:
       0: aload_0
       1: aload_1
       2: aload_2
       3: aload_3
       4: aload         4
       6: invokestatic  #23                 // Method createPath:(Lorg/apache/hadoop/hbase/TableName;Ljava/lang/String;Ljava/lang/String;Ljava/lang/String;)Lorg/apache/hadoop/fs/Path;
       9: invokestatic  #24                 // Method buildFromHFileLinkPattern:(Lorg/apache/hadoop/conf/Configuration;Lorg/apache/hadoop/fs/Path;)Lorg/apache/hadoop/hbase/io/HFileLink;
      12: areturn

  public org.apache.hadoop.fs.Path getOriginPath();
    Code:
       0: aload_0
       1: getfield      #3                  // Field originPath:Lorg/apache/hadoop/fs/Path;
       4: areturn

  public org.apache.hadoop.fs.Path getArchivePath();
    Code:
       0: aload_0
       1: getfield      #5                  // Field archivePath:Lorg/apache/hadoop/fs/Path;
       4: areturn

  public org.apache.hadoop.fs.Path getMobPath();
    Code:
       0: aload_0
       1: getfield      #4                  // Field mobPath:Lorg/apache/hadoop/fs/Path;
       4: areturn

  public static boolean isHFileLink(org.apache.hadoop.fs.Path);
    Code:
       0: aload_0
       1: invokevirtual #25                 // Method org/apache/hadoop/fs/Path.getName:()Ljava/lang/String;
       4: invokestatic  #20                 // Method isHFileLink:(Ljava/lang/String;)Z
       7: ireturn

  public static boolean isHFileLink(java.lang.String);
    Code:
       0: getstatic     #26                 // Field LINK_NAME_PATTERN:Ljava/util/regex/Pattern;
       3: aload_0
       4: invokevirtual #27                 // Method java/util/regex/Pattern.matcher:(Ljava/lang/CharSequence;)Ljava/util/regex/Matcher;
       7: astore_1
       8: aload_1
       9: invokevirtual #28                 // Method java/util/regex/Matcher.matches:()Z
      12: ifne          17
      15: iconst_0
      16: ireturn
      17: aload_1
      18: invokevirtual #29                 // Method java/util/regex/Matcher.groupCount:()I
      21: iconst_2
      22: if_icmple     53
      25: aload_1
      26: iconst_4
      27: invokevirtual #30                 // Method java/util/regex/Matcher.group:(I)Ljava/lang/String;
      30: ifnull        53
      33: aload_1
      34: iconst_3
      35: invokevirtual #30                 // Method java/util/regex/Matcher.group:(I)Ljava/lang/String;
      38: ifnull        53
      41: aload_1
      42: iconst_2
      43: invokevirtual #30                 // Method java/util/regex/Matcher.group:(I)Ljava/lang/String;
      46: ifnull        53
      49: iconst_1
      50: goto          54
      53: iconst_0
      54: ireturn

  public static java.lang.String getReferencedHFileName(java.lang.String);
    Code:
       0: getstatic     #31                 // Field REF_OR_HFILE_LINK_PATTERN:Ljava/util/regex/Pattern;
       3: aload_0
       4: invokevirtual #27                 // Method java/util/regex/Pattern.matcher:(Ljava/lang/CharSequence;)Ljava/util/regex/Matcher;
       7: astore_1
       8: aload_1
       9: invokevirtual #28                 // Method java/util/regex/Matcher.matches:()Z
      12: ifne          42
      15: new           #32                 // class java/lang/IllegalArgumentException
      18: dup
      19: new           #33                 // class java/lang/StringBuilder
      22: dup
      23: invokespecial #34                 // Method java/lang/StringBuilder."<init>":()V
      26: aload_0
      27: invokevirtual #35                 // Method java/lang/StringBuilder.append:(Ljava/lang/String;)Ljava/lang/StringBuilder;
      30: ldc           #45                 // String  is not a valid HFileLink name!
      32: invokevirtual #35                 // Method java/lang/StringBuilder.append:(Ljava/lang/String;)Ljava/lang/StringBuilder;
      35: invokevirtual #37                 // Method java/lang/StringBuilder.toString:()Ljava/lang/String;
      38: invokespecial #38                 // Method java/lang/IllegalArgumentException."<init>":(Ljava/lang/String;)V
      41: athrow
      42: aload_1
      43: iconst_4
      44: invokevirtual #30                 // Method java/util/regex/Matcher.group:(I)Ljava/lang/String;
      47: areturn

  public static java.lang.String getReferencedRegionName(java.lang.String);
    Code:
       0: getstatic     #31                 // Field REF_OR_HFILE_LINK_PATTERN:Ljava/util/regex/Pattern;
       3: aload_0
       4: invokevirtual #27                 // Method java/util/regex/Pattern.matcher:(Ljava/lang/CharSequence;)Ljava/util/regex/Matcher;
       7: astore_1
       8: aload_1
       9: invokevirtual #28                 // Method java/util/regex/Matcher.matches:()Z
      12: ifne          42
      15: new           #32                 // class java/lang/IllegalArgumentException
      18: dup
      19: new           #33                 // class java/lang/StringBuilder
      22: dup
      23: invokespecial #34                 // Method java/lang/StringBuilder."<init>":()V
      26: aload_0
      27: invokevirtual #35                 // Method java/lang/StringBuilder.append:(Ljava/lang/String;)Ljava/lang/StringBuilder;
      30: ldc           #45                 // String  is not a valid HFileLink name!
      32: invokevirtual #35                 // Method java/lang/StringBuilder.append:(Ljava/lang/String;)Ljava/lang/StringBuilder;
      35: invokevirtual #37                 // Method java/lang/StringBuilder.toString:()Ljava/lang/String;
      38: invokespecial #38                 // Method java/lang/IllegalArgumentException."<init>":(Ljava/lang/String;)V
      41: athrow
      42: aload_1
      43: iconst_3
      44: invokevirtual #30                 // Method java/util/regex/Matcher.group:(I)Ljava/lang/String;
      47: areturn

  public static org.apache.hadoop.hbase.TableName getReferencedTableName(java.lang.String);
    Code:
       0: getstatic     #31                 // Field REF_OR_HFILE_LINK_PATTERN:Ljava/util/regex/Pattern;
       3: aload_0
       4: invokevirtual #27                 // Method java/util/regex/Pattern.matcher:(Ljava/lang/CharSequence;)Ljava/util/regex/Matcher;
       7: astore_1
       8: aload_1
       9: invokevirtual #28                 // Method java/util/regex/Matcher.matches:()Z
      12: ifne          42
      15: new           #32                 // class java/lang/IllegalArgumentException
      18: dup
      19: new           #33                 // class java/lang/StringBuilder
      22: dup
      23: invokespecial #34                 // Method java/lang/StringBuilder."<init>":()V
      26: aload_0
      27: invokevirtual #35                 // Method java/lang/StringBuilder.append:(Ljava/lang/String;)Ljava/lang/StringBuilder;
      30: ldc           #45                 // String  is not a valid HFileLink name!
      32: invokevirtual #35                 // Method java/lang/StringBuilder.append:(Ljava/lang/String;)Ljava/lang/StringBuilder;
      35: invokevirtual #37                 // Method java/lang/StringBuilder.toString:()Ljava/lang/String;
      38: invokespecial #38                 // Method java/lang/IllegalArgumentException."<init>":(Ljava/lang/String;)V
      41: athrow
      42: aload_1
      43: iconst_1
      44: invokevirtual #30                 // Method java/util/regex/Matcher.group:(I)Ljava/lang/String;
      47: aload_1
      48: iconst_2
      49: invokevirtual #30                 // Method java/util/regex/Matcher.group:(I)Ljava/lang/String;
      52: invokestatic  #39                 // Method org/apache/hadoop/hbase/TableName.valueOf:(Ljava/lang/String;Ljava/lang/String;)Lorg/apache/hadoop/hbase/TableName;
      55: areturn

  public static java.lang.String createHFileLinkName(org.apache.hadoop.hbase.client.RegionInfo, java.lang.String);
    Code:
       0: aload_0
       1: invokeinterface #46,  1           // InterfaceMethod org/apache/hadoop/hbase/client/RegionInfo.getTable:()Lorg/apache/hadoop/hbase/TableName;
       6: aload_0
       7: invokeinterface #47,  1           // InterfaceMethod org/apache/hadoop/hbase/client/RegionInfo.getEncodedName:()Ljava/lang/String;
      12: aload_1
      13: invokestatic  #22                 // Method createHFileLinkName:(Lorg/apache/hadoop/hbase/TableName;Ljava/lang/String;Ljava/lang/String;)Ljava/lang/String;
      16: areturn

  public static java.lang.String createHFileLinkName(org.apache.hadoop.hbase.TableName, java.lang.String, java.lang.String);
    Code:
       0: ldc           #48                 // String %s=%s-%s
       2: iconst_3
       3: anewarray     #49                 // class java/lang/Object
       6: dup
       7: iconst_0
       8: aload_0
       9: invokevirtual #50                 // Method org/apache/hadoop/hbase/TableName.getNameAsString:()Ljava/lang/String;
      12: bipush        58
      14: bipush        61
      16: invokevirtual #52                 // Method java/lang/String.replace:(CC)Ljava/lang/String;
      19: aastore
      20: dup
      21: iconst_1
      22: aload_1
      23: aastore
      24: dup
      25: iconst_2
      26: aload_2
      27: aastore
      28: invokestatic  #53                 // Method java/lang/String.format:(Ljava/lang/String;[Ljava/lang/Object;)Ljava/lang/String;
      31: astore_3
      32: aload_3
      33: areturn

  public static boolean create(org.apache.hadoop.conf.Configuration, org.apache.hadoop.fs.FileSystem, org.apache.hadoop.fs.Path, org.apache.hadoop.hbase.client.RegionInfo, java.lang.String) throws java.io.IOException;
    Code:
       0: aload_0
       1: aload_1
       2: aload_2
       3: aload_3
       4: aload         4
       6: iconst_1
       7: invokestatic  #54                 // Method create:(Lorg/apache/hadoop/conf/Configuration;Lorg/apache/hadoop/fs/FileSystem;Lorg/apache/hadoop/fs/Path;Lorg/apache/hadoop/hbase/client/RegionInfo;Ljava/lang/String;Z)Z
      10: ireturn

  public static boolean create(org.apache.hadoop.conf.Configuration, org.apache.hadoop.fs.FileSystem, org.apache.hadoop.fs.Path, org.apache.hadoop.hbase.client.RegionInfo, java.lang.String, boolean) throws java.io.IOException;
    Code:
       0: aload_3
       1: invokeinterface #46,  1           // InterfaceMethod org/apache/hadoop/hbase/client/RegionInfo.getTable:()Lorg/apache/hadoop/hbase/TableName;
       6: astore        6
       8: aload_3
       9: invokeinterface #47,  1           // InterfaceMethod org/apache/hadoop/hbase/client/RegionInfo.getEncodedName:()Ljava/lang/String;
      14: astore        7
      16: aload_0
      17: aload_1
      18: aload_2
      19: aload         6
      21: aload         7
      23: aload         4
      25: iload         5
      27: invokestatic  #55                 // Method create:(Lorg/apache/hadoop/conf/Configuration;Lorg/apache/hadoop/fs/FileSystem;Lorg/apache/hadoop/fs/Path;Lorg/apache/hadoop/hbase/TableName;Ljava/lang/String;Ljava/lang/String;Z)Z
      30: ireturn

  public static boolean create(org.apache.hadoop.conf.Configuration, org.apache.hadoop.fs.FileSystem, org.apache.hadoop.fs.Path, org.apache.hadoop.hbase.TableName, java.lang.String, java.lang.String) throws java.io.IOException;
    Code:
       0: aload_0
       1: aload_1
       2: aload_2
       3: aload_3
       4: aload         4
       6: aload         5
       8: iconst_1
       9: invokestatic  #55                 // Method create:(Lorg/apache/hadoop/conf/Configuration;Lorg/apache/hadoop/fs/FileSystem;Lorg/apache/hadoop/fs/Path;Lorg/apache/hadoop/hbase/TableName;Ljava/lang/String;Ljava/lang/String;Z)Z
      12: ireturn

  public static boolean create(org.apache.hadoop.conf.Configuration, org.apache.hadoop.fs.FileSystem, org.apache.hadoop.fs.Path, org.apache.hadoop.hbase.TableName, java.lang.String, java.lang.String, boolean) throws java.io.IOException;
    Code:
       0: aload_2
       1: invokevirtual #25                 // Method org/apache/hadoop/fs/Path.getName:()Ljava/lang/String;
       4: astore        7
       6: aload_2
       7: invokevirtual #40                 // Method org/apache/hadoop/fs/Path.getParent:()Lorg/apache/hadoop/fs/Path;
      10: invokevirtual #25                 // Method org/apache/hadoop/fs/Path.getName:()Ljava/lang/String;
      13: astore        8
      15: aload_2
      16: invokevirtual #40                 // Method org/apache/hadoop/fs/Path.getParent:()Lorg/apache/hadoop/fs/Path;
      19: invokevirtual #40                 // Method org/apache/hadoop/fs/Path.getParent:()Lorg/apache/hadoop/fs/Path;
      22: invokestatic  #56                 // Method org/apache/hadoop/hbase/util/FSUtils.getTableName:(Lorg/apache/hadoop/fs/Path;)Lorg/apache/hadoop/hbase/TableName;
      25: invokevirtual #50                 // Method org/apache/hadoop/hbase/TableName.getNameAsString:()Ljava/lang/String;
      28: astore        9
      30: aload_3
      31: aload         4
      33: aload         5
      35: invokestatic  #22                 // Method createHFileLinkName:(Lorg/apache/hadoop/hbase/TableName;Ljava/lang/String;Ljava/lang/String;)Ljava/lang/String;
      38: astore        10
      40: aload         9
      42: aload         8
      44: invokestatic  #57                 // Method createBackReferenceName:(Ljava/lang/String;Ljava/lang/String;)Ljava/lang/String;
      47: astore        11
      49: aload_1
      50: aload_2
      51: invokevirtual #58                 // Method org/apache/hadoop/fs/FileSystem.mkdirs:(Lorg/apache/hadoop/fs/Path;)Z
      54: pop
      55: aload_0
      56: aload_3
      57: aload         4
      59: aload         7
      61: invokestatic  #59                 // Method org/apache/hadoop/hbase/util/HFileArchiveUtil.getStoreArchivePath:(Lorg/apache/hadoop/conf/Configuration;Lorg/apache/hadoop/hbase/TableName;Ljava/lang/String;Ljava/lang/String;)Lorg/apache/hadoop/fs/Path;
      64: astore        12
      66: aconst_null
      67: astore        13
      69: iload         6
      71: ifeq          110
      74: aload         12
      76: aload         5
      78: invokestatic  #60                 // Method getBackReferencesDir:(Lorg/apache/hadoop/fs/Path;Ljava/lang/String;)Lorg/apache/hadoop/fs/Path;
      81: astore        14
      83: aload_1
      84: aload         14
      86: invokevirtual #58                 // Method org/apache/hadoop/fs/FileSystem.mkdirs:(Lorg/apache/hadoop/fs/Path;)Z
      89: pop
      90: new           #6                  // class org/apache/hadoop/fs/Path
      93: dup
      94: aload         14
      96: aload         11
      98: invokespecial #14                 // Method org/apache/hadoop/fs/Path."<init>":(Lorg/apache/hadoop/fs/Path;Ljava/lang/String;)V
     101: astore        13
     103: aload_1
     104: aload         13
     106: invokevirtual #61                 // Method org/apache/hadoop/fs/FileSystem.createNewFile:(Lorg/apache/hadoop/fs/Path;)Z
     109: pop
     110: aload_1
     111: new           #6                  // class org/apache/hadoop/fs/Path
     114: dup
     115: aload_2
     116: aload         10
     118: invokespecial #14                 // Method org/apache/hadoop/fs/Path."<init>":(Lorg/apache/hadoop/fs/Path;Ljava/lang/String;)V
     121: invokevirtual #61                 // Method org/apache/hadoop/fs/FileSystem.createNewFile:(Lorg/apache/hadoop/fs/Path;)Z
     124: ireturn
     125: astore        14
     127: getstatic     #63                 // Field LOG:Lorg/slf4j/Logger;
     130: new           #33                 // class java/lang/StringBuilder
     133: dup
     134: invokespecial #34                 // Method java/lang/StringBuilder."<init>":()V
     137: ldc           #64                 // String couldn't create the link=
     139: invokevirtual #35                 // Method java/lang/StringBuilder.append:(Ljava/lang/String;)Ljava/lang/StringBuilder;
     142: aload         10
     144: invokevirtual #35                 // Method java/lang/StringBuilder.append:(Ljava/lang/String;)Ljava/lang/StringBuilder;
     147: ldc           #65                 // String  for
     149: invokevirtual #35                 // Method java/lang/StringBuilder.append:(Ljava/lang/String;)Ljava/lang/StringBuilder;
     152: aload_2
     153: invokevirtual #66                 // Method java/lang/StringBuilder.append:(Ljava/lang/Object;)Ljava/lang/StringBuilder;
     156: invokevirtual #37                 // Method java/lang/StringBuilder.toString:()Ljava/lang/String;
     159: aload         14
     161: invokeinterface #67,  3           // InterfaceMethod org/slf4j/Logger.error:(Ljava/lang/String;Ljava/lang/Throwable;)V
     166: iload         6
     168: ifeq          179
     171: aload_1
     172: aload         13
     174: iconst_0
     175: invokevirtual #68                 // Method org/apache/hadoop/fs/FileSystem.delete:(Lorg/apache/hadoop/fs/Path;Z)Z
     178: pop
     179: aload         14
     181: athrow
    Exception table:
       from    to  target type
         110   124   125   Class java/io/IOException

  public static boolean createFromHFileLink(org.apache.hadoop.conf.Configuration, org.apache.hadoop.fs.FileSystem, org.apache.hadoop.fs.Path, java.lang.String) throws java.io.IOException;
    Code:
       0: aload_0
       1: aload_1
       2: aload_2
       3: aload_3
       4: iconst_1
       5: invokestatic  #69                 // Method createFromHFileLink:(Lorg/apache/hadoop/conf/Configuration;Lorg/apache/hadoop/fs/FileSystem;Lorg/apache/hadoop/fs/Path;Ljava/lang/String;Z)Z
       8: ireturn

  public static boolean createFromHFileLink(org.apache.hadoop.conf.Configuration, org.apache.hadoop.fs.FileSystem, org.apache.hadoop.fs.Path, java.lang.String, boolean) throws java.io.IOException;
    Code:
       0: getstatic     #26                 // Field LINK_NAME_PATTERN:Ljava/util/regex/Pattern;
       3: aload_3
       4: invokevirtual #27                 // Method java/util/regex/Pattern.matcher:(Ljava/lang/CharSequence;)Ljava/util/regex/Matcher;
       7: astore        5
       9: aload         5
      11: invokevirtual #28                 // Method java/util/regex/Matcher.matches:()Z
      14: ifne          44
      17: new           #32                 // class java/lang/IllegalArgumentException
      20: dup
      21: new           #33                 // class java/lang/StringBuilder
      24: dup
      25: invokespecial #34                 // Method java/lang/StringBuilder."<init>":()V
      28: aload_3
      29: invokevirtual #35                 // Method java/lang/StringBuilder.append:(Ljava/lang/String;)Ljava/lang/StringBuilder;
      32: ldc           #45                 // String  is not a valid HFileLink name!
      34: invokevirtual #35                 // Method java/lang/StringBuilder.append:(Ljava/lang/String;)Ljava/lang/StringBuilder;
      37: invokevirtual #37                 // Method java/lang/StringBuilder.toString:()Ljava/lang/String;
      40: invokespecial #38                 // Method java/lang/IllegalArgumentException."<init>":(Ljava/lang/String;)V
      43: athrow
      44: aload_0
      45: aload_1
      46: aload_2
      47: aload         5
      49: iconst_1
      50: invokevirtual #30                 // Method java/util/regex/Matcher.group:(I)Ljava/lang/String;
      53: aload         5
      55: iconst_2
      56: invokevirtual #30                 // Method java/util/regex/Matcher.group:(I)Ljava/lang/String;
      59: invokestatic  #39                 // Method org/apache/hadoop/hbase/TableName.valueOf:(Ljava/lang/String;Ljava/lang/String;)Lorg/apache/hadoop/hbase/TableName;
      62: aload         5
      64: iconst_3
      65: invokevirtual #30                 // Method java/util/regex/Matcher.group:(I)Ljava/lang/String;
      68: aload         5
      70: iconst_4
      71: invokevirtual #30                 // Method java/util/regex/Matcher.group:(I)Ljava/lang/String;
      74: iload         4
      76: invokestatic  #55                 // Method create:(Lorg/apache/hadoop/conf/Configuration;Lorg/apache/hadoop/fs/FileSystem;Lorg/apache/hadoop/fs/Path;Lorg/apache/hadoop/hbase/TableName;Ljava/lang/String;Ljava/lang/String;Z)Z
      79: ireturn

  static java.lang.String createBackReferenceName(java.lang.String, java.lang.String);
    Code:
       0: new           #33                 // class java/lang/StringBuilder
       3: dup
       4: invokespecial #34                 // Method java/lang/StringBuilder."<init>":()V
       7: aload_1
       8: invokevirtual #35                 // Method java/lang/StringBuilder.append:(Ljava/lang/String;)Ljava/lang/StringBuilder;
      11: ldc           #70                 // String .
      13: invokevirtual #35                 // Method java/lang/StringBuilder.append:(Ljava/lang/String;)Ljava/lang/StringBuilder;
      16: aload_0
      17: bipush        58
      19: bipush        61
      21: invokevirtual #52                 // Method java/lang/String.replace:(CC)Ljava/lang/String;
      24: invokevirtual #35                 // Method java/lang/StringBuilder.append:(Ljava/lang/String;)Ljava/lang/StringBuilder;
      27: invokevirtual #37                 // Method java/lang/StringBuilder.toString:()Ljava/lang/String;
      30: areturn

  public static org.apache.hadoop.fs.Path getHFileFromBackReference(org.apache.hadoop.fs.Path, org.apache.hadoop.fs.Path);
    Code:
       0: aload_1
       1: invokevirtual #25                 // Method org/apache/hadoop/fs/Path.getName:()Ljava/lang/String;
       4: invokestatic  #71                 // Method parseBackReferenceName:(Ljava/lang/String;)Lorg/apache/hadoop/hbase/util/Pair;
       7: astore_2
       8: aload_2
       9: invokevirtual #72                 // Method org/apache/hadoop/hbase/util/Pair.getFirst:()Ljava/lang/Object;
      12: checkcast     #51                 // class org/apache/hadoop/hbase/TableName
      15: astore_3
      16: aload_2
      17: invokevirtual #73                 // Method org/apache/hadoop/hbase/util/Pair.getSecond:()Ljava/lang/Object;
      20: checkcast     #74                 // class java/lang/String
      23: astore        4
      25: aload_1
      26: invokevirtual #40                 // Method org/apache/hadoop/fs/Path.getParent:()Lorg/apache/hadoop/fs/Path;
      29: invokestatic  #75                 // Method getBackReferenceFileName:(Lorg/apache/hadoop/fs/Path;)Ljava/lang/String;
      32: astore        5
      34: aload_1
      35: invokevirtual #40                 // Method org/apache/hadoop/fs/Path.getParent:()Lorg/apache/hadoop/fs/Path;
      38: invokevirtual #40                 // Method org/apache/hadoop/fs/Path.getParent:()Lorg/apache/hadoop/fs/Path;
      41: astore        6
      43: aload         6
      45: invokevirtual #40                 // Method org/apache/hadoop/fs/Path.getParent:()Lorg/apache/hadoop/fs/Path;
      48: astore        7
      50: aload         7
      52: invokevirtual #40                 // Method org/apache/hadoop/fs/Path.getParent:()Lorg/apache/hadoop/fs/Path;
      55: astore        8
      57: aload         8
      59: invokestatic  #56                 // Method org/apache/hadoop/hbase/util/FSUtils.getTableName:(Lorg/apache/hadoop/fs/Path;)Lorg/apache/hadoop/hbase/TableName;
      62: aload         7
      64: invokevirtual #25                 // Method org/apache/hadoop/fs/Path.getName:()Ljava/lang/String;
      67: aload         5
      69: invokestatic  #22                 // Method createHFileLinkName:(Lorg/apache/hadoop/hbase/TableName;Ljava/lang/String;Ljava/lang/String;)Ljava/lang/String;
      72: astore        9
      74: aload_0
      75: aload_3
      76: invokestatic  #43                 // Method org/apache/hadoop/hbase/util/FSUtils.getTableDir:(Lorg/apache/hadoop/fs/Path;Lorg/apache/hadoop/hbase/TableName;)Lorg/apache/hadoop/fs/Path;
      79: astore        10
      81: aload         10
      83: aload         4
      85: invokestatic  #76                 // Method org/apache/hadoop/hbase/regionserver/HRegion.getRegionDir:(Lorg/apache/hadoop/fs/Path;Ljava/lang/String;)Lorg/apache/hadoop/fs/Path;
      88: astore        11
      90: new           #6                  // class org/apache/hadoop/fs/Path
      93: dup
      94: new           #6                  // class org/apache/hadoop/fs/Path
      97: dup
      98: aload         11
     100: aload         6
     102: invokevirtual #25                 // Method org/apache/hadoop/fs/Path.getName:()Ljava/lang/String;
     105: invokespecial #14                 // Method org/apache/hadoop/fs/Path."<init>":(Lorg/apache/hadoop/fs/Path;Ljava/lang/String;)V
     108: aload         9
     110: invokespecial #14                 // Method org/apache/hadoop/fs/Path."<init>":(Lorg/apache/hadoop/fs/Path;Ljava/lang/String;)V
     113: areturn

  static org.apache.hadoop.hbase.util.Pair<org.apache.hadoop.hbase.TableName, java.lang.String> parseBackReferenceName(java.lang.String);
    Code:
       0: aload_0
       1: bipush        46
       3: invokevirtual #77                 // Method java/lang/String.indexOf:(I)I
       6: istore_1
       7: aload_0
       8: iconst_0
       9: iload_1
      10: invokevirtual #78                 // Method java/lang/String.substring:(II)Ljava/lang/String;
      13: astore_2
      14: aload_0
      15: iload_1
      16: iconst_1
      17: iadd
      18: invokevirtual #79                 // Method java/lang/String.substring:(I)Ljava/lang/String;
      21: bipush        61
      23: bipush        58
      25: invokevirtual #52                 // Method java/lang/String.replace:(CC)Ljava/lang/String;
      28: astore_3
      29: aload_3
      30: invokestatic  #80                 // Method org/apache/hadoop/hbase/TableName.valueOf:(Ljava/lang/String;)Lorg/apache/hadoop/hbase/TableName;
      33: astore        4
      35: new           #81                 // class org/apache/hadoop/hbase/util/Pair
      38: dup
      39: aload         4
      41: aload_2
      42: invokespecial #82                 // Method org/apache/hadoop/hbase/util/Pair."<init>":(Ljava/lang/Object;Ljava/lang/Object;)V
      45: areturn

  public static org.apache.hadoop.fs.Path getHFileFromBackReference(org.apache.hadoop.conf.Configuration, org.apache.hadoop.fs.Path) throws java.io.IOException;
    Code:
       0: aload_0
       1: invokestatic  #8                  // Method org/apache/hadoop/hbase/util/FSUtils.getRootDir:(Lorg/apache/hadoop/conf/Configuration;)Lorg/apache/hadoop/fs/Path;
       4: aload_1
       5: invokestatic  #83                 // Method getHFileFromBackReference:(Lorg/apache/hadoop/fs/Path;Lorg/apache/hadoop/fs/Path;)Lorg/apache/hadoop/fs/Path;
       8: areturn

  static {};
    Code:
       0: ldc           #18                 // class org/apache/hadoop/hbase/io/HFileLink
       2: invokestatic  #84                 // Method org/slf4j/LoggerFactory.getLogger:(Ljava/lang/Class;)Lorg/slf4j/Logger;
       5: putstatic     #63                 // Field LOG:Lorg/slf4j/Logger;
       8: ldc           #85                 // String (?:(?:%s=)?)%s=%s-%s
      10: iconst_4
      11: anewarray     #49                 // class java/lang/Object
      14: dup
      15: iconst_0
      16: ldc           #86                 // String (?:[_\p{Digit}\p{IsAlphabetic}]+)
      18: aastore
      19: dup
      20: iconst_1
      21: ldc           #87                 // String (?:[_\p{Digit}\p{IsAlphabetic}][-_.\p{Digit}\p{IsAlphabetic}]*)
      23: aastore
      24: dup
      25: iconst_2
      26: ldc           #89                 // String (?:[a-f0-9]+)
      28: aastore
      29: dup
      30: iconst_3
      31: ldc           #91                 // String [0-9a-f]+(?:(?:_SeqId_[0-9]+_)|(?:_del))?
      33: aastore
      34: invokestatic  #53                 // Method java/lang/String.format:(Ljava/lang/String;[Ljava/lang/Object;)Ljava/lang/String;
      37: putstatic     #92                 // Field LINK_NAME_REGEX:Ljava/lang/String;
      40: ldc           #93                 // String ^(?:(%s)(?:\=))?(%s)=(%s)-(%s)$
      42: iconst_4
      43: anewarray     #49                 // class java/lang/Object
      46: dup
      47: iconst_0
      48: ldc           #86                 // String (?:[_\p{Digit}\p{IsAlphabetic}]+)
      50: aastore
      51: dup
      52: iconst_1
      53: ldc           #87                 // String (?:[_\p{Digit}\p{IsAlphabetic}][-_.\p{Digit}\p{IsAlphabetic}]*)
      55: aastore
      56: dup
      57: iconst_2
      58: ldc           #89                 // String (?:[a-f0-9]+)
      60: aastore
      61: dup
      62: iconst_3
      63: ldc           #91                 // String [0-9a-f]+(?:(?:_SeqId_[0-9]+_)|(?:_del))?
      65: aastore
      66: invokestatic  #53                 // Method java/lang/String.format:(Ljava/lang/String;[Ljava/lang/Object;)Ljava/lang/String;
      69: invokestatic  #94                 // Method java/util/regex/Pattern.compile:(Ljava/lang/String;)Ljava/util/regex/Pattern;
      72: putstatic     #26                 // Field LINK_NAME_PATTERN:Ljava/util/regex/Pattern;
      75: ldc           #95                 // String ^(?:(%s)(?:=))?(%s)=(%s)-(.+)$
      77: iconst_3
      78: anewarray     #49                 // class java/lang/Object
      81: dup
      82: iconst_0
      83: ldc           #86                 // String (?:[_\p{Digit}\p{IsAlphabetic}]+)
      85: aastore
      86: dup
      87: iconst_1
      88: ldc           #87                 // String (?:[_\p{Digit}\p{IsAlphabetic}][-_.\p{Digit}\p{IsAlphabetic}]*)
      90: aastore
      91: dup
      92: iconst_2
      93: ldc           #89                 // String (?:[a-f0-9]+)
      95: aastore
      96: invokestatic  #53                 // Method java/lang/String.format:(Ljava/lang/String;[Ljava/lang/Object;)Ljava/lang/String;
      99: invokestatic  #94                 // Method java/util/regex/Pattern.compile:(Ljava/lang/String;)Ljava/util/regex/Pattern;
     102: putstatic     #31                 // Field REF_OR_HFILE_LINK_PATTERN:Ljava/util/regex/Pattern;
     105: return
}
