Compiled from "HFileBlockIndex.java"
class org.apache.hadoop.hbase.io.hfile.HFileBlockIndex$BlockIndexChunk {
  org.apache.hadoop.hbase.io.hfile.HFileBlockIndex$BlockIndexChunk();
    Code:
       0: aload_0
       1: invokespecial #2                  // Method java/lang/Object."<init>":()V
       4: aload_0
       5: new           #3                  // class java/util/ArrayList
       8: dup
       9: invokespecial #4                  // Method java/util/ArrayList."<init>":()V
      12: putfield      #5                  // Field blockKeys:Ljava/util/List;
      15: aload_0
      16: new           #3                  // class java/util/ArrayList
      19: dup
      20: invokespecial #4                  // Method java/util/ArrayList."<init>":()V
      23: putfield      #6                  // Field blockOffsets:Ljava/util/List;
      26: aload_0
      27: new           #3                  // class java/util/ArrayList
      30: dup
      31: invokespecial #4                  // Method java/util/ArrayList."<init>":()V
      34: putfield      #7                  // Field onDiskDataSizes:Ljava/util/List;
      37: aload_0
      38: new           #3                  // class java/util/ArrayList
      41: dup
      42: invokespecial #4                  // Method java/util/ArrayList."<init>":()V
      45: putfield      #8                  // Field numSubEntriesAt:Ljava/util/List;
      48: aload_0
      49: iconst_0
      50: putfield      #9                  // Field curTotalNonRootEntrySize:I
      53: aload_0
      54: iconst_0
      55: putfield      #10                 // Field curTotalRootSize:I
      58: aload_0
      59: new           #3                  // class java/util/ArrayList
      62: dup
      63: invokespecial #4                  // Method java/util/ArrayList."<init>":()V
      66: putfield      #11                 // Field secondaryIndexOffsetMarks:Ljava/util/List;
      69: return

  void add(byte[], long, int, long);
    Code:
       0: aload_0
       1: getfield      #11                 // Field secondaryIndexOffsetMarks:Ljava/util/List;
       4: aload_0
       5: getfield      #9                  // Field curTotalNonRootEntrySize:I
       8: invokestatic  #12                 // Method java/lang/Integer.valueOf:(I)Ljava/lang/Integer;
      11: invokeinterface #13,  2           // InterfaceMethod java/util/List.add:(Ljava/lang/Object;)Z
      16: pop
      17: aload_0
      18: dup
      19: getfield      #9                  // Field curTotalNonRootEntrySize:I
      22: bipush        12
      24: aload_1
      25: arraylength
      26: iadd
      27: iadd
      28: putfield      #9                  // Field curTotalNonRootEntrySize:I
      31: aload_0
      32: dup
      33: getfield      #10                 // Field curTotalRootSize:I
      36: bipush        12
      38: aload_1
      39: arraylength
      40: i2l
      41: invokestatic  #15                 // Method org/apache/hadoop/io/WritableUtils.getVIntSize:(J)I
      44: iadd
      45: aload_1
      46: arraylength
      47: iadd
      48: iadd
      49: putfield      #10                 // Field curTotalRootSize:I
      52: aload_0
      53: getfield      #5                  // Field blockKeys:Ljava/util/List;
      56: aload_1
      57: invokeinterface #13,  2           // InterfaceMethod java/util/List.add:(Ljava/lang/Object;)Z
      62: pop
      63: aload_0
      64: getfield      #6                  // Field blockOffsets:Ljava/util/List;
      67: lload_2
      68: invokestatic  #16                 // Method java/lang/Long.valueOf:(J)Ljava/lang/Long;
      71: invokeinterface #13,  2           // InterfaceMethod java/util/List.add:(Ljava/lang/Object;)Z
      76: pop
      77: aload_0
      78: getfield      #7                  // Field onDiskDataSizes:Ljava/util/List;
      81: iload         4
      83: invokestatic  #12                 // Method java/lang/Integer.valueOf:(I)Ljava/lang/Integer;
      86: invokeinterface #13,  2           // InterfaceMethod java/util/List.add:(Ljava/lang/Object;)Z
      91: pop
      92: lload         5
      94: ldc2_w        #17                 // long -1l
      97: lcmp
      98: ifeq          189
     101: aload_0
     102: getfield      #8                  // Field numSubEntriesAt:Ljava/util/List;
     105: lload         5
     107: invokestatic  #16                 // Method java/lang/Long.valueOf:(J)Ljava/lang/Long;
     110: invokeinterface #13,  2           // InterfaceMethod java/util/List.add:(Ljava/lang/Object;)Z
     115: pop
     116: aload_0
     117: getfield      #8                  // Field numSubEntriesAt:Ljava/util/List;
     120: invokeinterface #19,  1           // InterfaceMethod java/util/List.size:()I
     125: aload_0
     126: getfield      #5                  // Field blockKeys:Ljava/util/List;
     129: invokeinterface #19,  1           // InterfaceMethod java/util/List.size:()I
     134: if_icmpeq     189
     137: new           #20                 // class java/lang/IllegalStateException
     140: dup
     141: new           #21                 // class java/lang/StringBuilder
     144: dup
     145: invokespecial #22                 // Method java/lang/StringBuilder."<init>":()V
     148: ldc           #23                 // String Only have key/value count stats for
     150: invokevirtual #24                 // Method java/lang/StringBuilder.append:(Ljava/lang/String;)Ljava/lang/StringBuilder;
     153: aload_0
     154: getfield      #8                  // Field numSubEntriesAt:Ljava/util/List;
     157: invokeinterface #19,  1           // InterfaceMethod java/util/List.size:()I
     162: invokevirtual #25                 // Method java/lang/StringBuilder.append:(I)Ljava/lang/StringBuilder;
     165: ldc           #26                 // String  block index entries out of
     167: invokevirtual #24                 // Method java/lang/StringBuilder.append:(Ljava/lang/String;)Ljava/lang/StringBuilder;
     170: aload_0
     171: getfield      #5                  // Field blockKeys:Ljava/util/List;
     174: invokeinterface #19,  1           // InterfaceMethod java/util/List.size:()I
     179: invokevirtual #25                 // Method java/lang/StringBuilder.append:(I)Ljava/lang/StringBuilder;
     182: invokevirtual #27                 // Method java/lang/StringBuilder.toString:()Ljava/lang/String;
     185: invokespecial #28                 // Method java/lang/IllegalStateException."<init>":(Ljava/lang/String;)V
     188: athrow
     189: return

  public void add(byte[], long, int);
    Code:
       0: aload_0
       1: aload_1
       2: lload_2
       3: iload         4
       5: ldc2_w        #17                 // long -1l
       8: invokevirtual #29                 // Method add:([BJIJ)V
      11: return

  public void clear();
    Code:
       0: aload_0
       1: getfield      #5                  // Field blockKeys:Ljava/util/List;
       4: invokeinterface #30,  1           // InterfaceMethod java/util/List.clear:()V
       9: aload_0
      10: getfield      #6                  // Field blockOffsets:Ljava/util/List;
      13: invokeinterface #30,  1           // InterfaceMethod java/util/List.clear:()V
      18: aload_0
      19: getfield      #7                  // Field onDiskDataSizes:Ljava/util/List;
      22: invokeinterface #30,  1           // InterfaceMethod java/util/List.clear:()V
      27: aload_0
      28: getfield      #11                 // Field secondaryIndexOffsetMarks:Ljava/util/List;
      31: invokeinterface #30,  1           // InterfaceMethod java/util/List.clear:()V
      36: aload_0
      37: getfield      #8                  // Field numSubEntriesAt:Ljava/util/List;
      40: invokeinterface #30,  1           // InterfaceMethod java/util/List.clear:()V
      45: aload_0
      46: iconst_0
      47: putfield      #9                  // Field curTotalNonRootEntrySize:I
      50: aload_0
      51: iconst_0
      52: putfield      #10                 // Field curTotalRootSize:I
      55: return

  public int getEntryBySubEntry(long);
    Code:
       0: aload_0
       1: getfield      #8                  // Field numSubEntriesAt:Ljava/util/List;
       4: lload_1
       5: invokestatic  #16                 // Method java/lang/Long.valueOf:(J)Ljava/lang/Long;
       8: invokestatic  #31                 // Method java/util/Collections.binarySearch:(Ljava/util/List;Ljava/lang/Object;)I
      11: istore_3
      12: iload_3
      13: iflt          20
      16: iload_3
      17: iconst_1
      18: iadd
      19: ireturn
      20: iload_3
      21: ineg
      22: iconst_1
      23: isub
      24: ireturn

  public byte[] getMidKeyMetadata() throws java.io.IOException;
    Code:
       0: new           #32                 // class java/io/ByteArrayOutputStream
       3: dup
       4: bipush        16
       6: invokespecial #33                 // Method java/io/ByteArrayOutputStream."<init>":(I)V
       9: astore_1
      10: new           #34                 // class java/io/DataOutputStream
      13: dup
      14: aload_1
      15: invokespecial #35                 // Method java/io/DataOutputStream."<init>":(Ljava/io/OutputStream;)V
      18: astore_2
      19: aload_0
      20: getfield      #8                  // Field numSubEntriesAt:Ljava/util/List;
      23: aload_0
      24: getfield      #5                  // Field blockKeys:Ljava/util/List;
      27: invokeinterface #19,  1           // InterfaceMethod java/util/List.size:()I
      32: iconst_1
      33: isub
      34: invokeinterface #36,  2           // InterfaceMethod java/util/List.get:(I)Ljava/lang/Object;
      39: checkcast     #37                 // class java/lang/Long
      42: invokevirtual #38                 // Method java/lang/Long.longValue:()J
      45: lstore_3
      46: lload_3
      47: lconst_0
      48: lcmp
      49: ifne          62
      52: new           #39                 // class java/io/IOException
      55: dup
      56: ldc           #40                 // String No leaf-level entries, mid-key unavailable
      58: invokespecial #41                 // Method java/io/IOException."<init>":(Ljava/lang/String;)V
      61: athrow
      62: lload_3
      63: lconst_1
      64: lsub
      65: ldc2_w        #42                 // long 2l
      68: ldiv
      69: lstore        5
      71: aload_0
      72: lload         5
      74: invokevirtual #44                 // Method getEntryBySubEntry:(J)I
      77: istore        7
      79: aload_2
      80: aload_0
      81: getfield      #6                  // Field blockOffsets:Ljava/util/List;
      84: iload         7
      86: invokeinterface #36,  2           // InterfaceMethod java/util/List.get:(I)Ljava/lang/Object;
      91: checkcast     #37                 // class java/lang/Long
      94: invokevirtual #38                 // Method java/lang/Long.longValue:()J
      97: invokevirtual #45                 // Method java/io/DataOutputStream.writeLong:(J)V
     100: aload_2
     101: aload_0
     102: getfield      #7                  // Field onDiskDataSizes:Ljava/util/List;
     105: iload         7
     107: invokeinterface #36,  2           // InterfaceMethod java/util/List.get:(I)Ljava/lang/Object;
     112: checkcast     #46                 // class java/lang/Integer
     115: invokevirtual #47                 // Method java/lang/Integer.intValue:()I
     118: invokevirtual #48                 // Method java/io/DataOutputStream.writeInt:(I)V
     121: iload         7
     123: ifle          148
     126: aload_0
     127: getfield      #8                  // Field numSubEntriesAt:Ljava/util/List;
     130: iload         7
     132: iconst_1
     133: isub
     134: invokeinterface #36,  2           // InterfaceMethod java/util/List.get:(I)Ljava/lang/Object;
     139: checkcast     #37                 // class java/lang/Long
     142: invokevirtual #38                 // Method java/lang/Long.longValue:()J
     145: goto          149
     148: lconst_0
     149: lstore        8
     151: lload         5
     153: lload         8
     155: lsub
     156: lstore        10
     158: lload         10
     160: lconst_0
     161: lcmp
     162: iflt          174
     165: lload         10
     167: ldc2_w        #49                 // long 2147483647l
     170: lcmp
     171: ifle          227
     174: new           #39                 // class java/io/IOException
     177: dup
     178: new           #21                 // class java/lang/StringBuilder
     181: dup
     182: invokespecial #22                 // Method java/lang/StringBuilder."<init>":()V
     185: ldc           #51                 // String Could not identify mid-key index within the leaf-level block containing mid-key: out of range (
     187: invokevirtual #24                 // Method java/lang/StringBuilder.append:(Ljava/lang/String;)Ljava/lang/StringBuilder;
     190: lload         10
     192: invokevirtual #52                 // Method java/lang/StringBuilder.append:(J)Ljava/lang/StringBuilder;
     195: ldc           #53                 // String , numSubEntriesBefore=
     197: invokevirtual #24                 // Method java/lang/StringBuilder.append:(Ljava/lang/String;)Ljava/lang/StringBuilder;
     200: lload         8
     202: invokevirtual #52                 // Method java/lang/StringBuilder.append:(J)Ljava/lang/StringBuilder;
     205: ldc           #54                 // String , midKeySubEntry=
     207: invokevirtual #24                 // Method java/lang/StringBuilder.append:(Ljava/lang/String;)Ljava/lang/StringBuilder;
     210: lload         5
     212: invokevirtual #52                 // Method java/lang/StringBuilder.append:(J)Ljava/lang/StringBuilder;
     215: ldc           #55                 // String )
     217: invokevirtual #24                 // Method java/lang/StringBuilder.append:(Ljava/lang/String;)Ljava/lang/StringBuilder;
     220: invokevirtual #27                 // Method java/lang/StringBuilder.toString:()Ljava/lang/String;
     223: invokespecial #41                 // Method java/io/IOException."<init>":(Ljava/lang/String;)V
     226: athrow
     227: aload_2
     228: lload         10
     230: l2i
     231: invokevirtual #48                 // Method java/io/DataOutputStream.writeInt:(I)V
     234: aload_2
     235: invokevirtual #56                 // Method java/io/DataOutputStream.size:()I
     238: bipush        16
     240: if_icmpeq     283
     243: new           #39                 // class java/io/IOException
     246: dup
     247: new           #21                 // class java/lang/StringBuilder
     250: dup
     251: invokespecial #22                 // Method java/lang/StringBuilder."<init>":()V
     254: ldc           #57                 // String Could not write mid-key metadata: size=
     256: invokevirtual #24                 // Method java/lang/StringBuilder.append:(Ljava/lang/String;)Ljava/lang/StringBuilder;
     259: aload_2
     260: invokevirtual #56                 // Method java/io/DataOutputStream.size:()I
     263: invokevirtual #25                 // Method java/lang/StringBuilder.append:(I)Ljava/lang/StringBuilder;
     266: ldc           #58                 // String , correct size:
     268: invokevirtual #24                 // Method java/lang/StringBuilder.append:(Ljava/lang/String;)Ljava/lang/StringBuilder;
     271: bipush        16
     273: invokevirtual #25                 // Method java/lang/StringBuilder.append:(I)Ljava/lang/StringBuilder;
     276: invokevirtual #27                 // Method java/lang/StringBuilder.toString:()Ljava/lang/String;
     279: invokespecial #41                 // Method java/io/IOException."<init>":(Ljava/lang/String;)V
     282: athrow
     283: aload_1
     284: invokevirtual #59                 // Method java/io/ByteArrayOutputStream.close:()V
     287: aload_1
     288: invokevirtual #60                 // Method java/io/ByteArrayOutputStream.toByteArray:()[B
     291: areturn

  void writeNonRoot(java.io.DataOutput) throws java.io.IOException;
    Code:
       0: aload_1
       1: aload_0
       2: getfield      #5                  // Field blockKeys:Ljava/util/List;
       5: invokeinterface #19,  1           // InterfaceMethod java/util/List.size:()I
      10: invokeinterface #61,  2           // InterfaceMethod java/io/DataOutput.writeInt:(I)V
      15: aload_0
      16: getfield      #11                 // Field secondaryIndexOffsetMarks:Ljava/util/List;
      19: invokeinterface #19,  1           // InterfaceMethod java/util/List.size:()I
      24: aload_0
      25: getfield      #5                  // Field blockKeys:Ljava/util/List;
      28: invokeinterface #19,  1           // InterfaceMethod java/util/List.size:()I
      33: if_icmpeq     93
      36: new           #39                 // class java/io/IOException
      39: dup
      40: new           #21                 // class java/lang/StringBuilder
      43: dup
      44: invokespecial #22                 // Method java/lang/StringBuilder."<init>":()V
      47: ldc           #62                 // String Corrupted block index chunk writer:
      49: invokevirtual #24                 // Method java/lang/StringBuilder.append:(Ljava/lang/String;)Ljava/lang/StringBuilder;
      52: aload_0
      53: getfield      #5                  // Field blockKeys:Ljava/util/List;
      56: invokeinterface #19,  1           // InterfaceMethod java/util/List.size:()I
      61: invokevirtual #25                 // Method java/lang/StringBuilder.append:(I)Ljava/lang/StringBuilder;
      64: ldc           #63                 // String  entries but
      66: invokevirtual #24                 // Method java/lang/StringBuilder.append:(Ljava/lang/String;)Ljava/lang/StringBuilder;
      69: aload_0
      70: getfield      #11                 // Field secondaryIndexOffsetMarks:Ljava/util/List;
      73: invokeinterface #19,  1           // InterfaceMethod java/util/List.size:()I
      78: invokevirtual #25                 // Method java/lang/StringBuilder.append:(I)Ljava/lang/StringBuilder;
      81: ldc           #64                 // String  secondary index items
      83: invokevirtual #24                 // Method java/lang/StringBuilder.append:(Ljava/lang/String;)Ljava/lang/StringBuilder;
      86: invokevirtual #27                 // Method java/lang/StringBuilder.toString:()Ljava/lang/String;
      89: invokespecial #41                 // Method java/io/IOException."<init>":(Ljava/lang/String;)V
      92: athrow
      93: aload_0
      94: getfield      #11                 // Field secondaryIndexOffsetMarks:Ljava/util/List;
      97: invokeinterface #65,  1           // InterfaceMethod java/util/List.iterator:()Ljava/util/Iterator;
     102: astore_2
     103: aload_2
     104: invokeinterface #66,  1           // InterfaceMethod java/util/Iterator.hasNext:()Z
     109: ifeq          135
     112: aload_2
     113: invokeinterface #67,  1           // InterfaceMethod java/util/Iterator.next:()Ljava/lang/Object;
     118: checkcast     #46                 // class java/lang/Integer
     121: invokevirtual #47                 // Method java/lang/Integer.intValue:()I
     124: istore_3
     125: aload_1
     126: iload_3
     127: invokeinterface #61,  2           // InterfaceMethod java/io/DataOutput.writeInt:(I)V
     132: goto          103
     135: aload_1
     136: aload_0
     137: getfield      #9                  // Field curTotalNonRootEntrySize:I
     140: invokeinterface #61,  2           // InterfaceMethod java/io/DataOutput.writeInt:(I)V
     145: iconst_0
     146: istore_2
     147: iload_2
     148: aload_0
     149: getfield      #5                  // Field blockKeys:Ljava/util/List;
     152: invokeinterface #19,  1           // InterfaceMethod java/util/List.size:()I
     157: if_icmpge     229
     160: aload_1
     161: aload_0
     162: getfield      #6                  // Field blockOffsets:Ljava/util/List;
     165: iload_2
     166: invokeinterface #36,  2           // InterfaceMethod java/util/List.get:(I)Ljava/lang/Object;
     171: checkcast     #37                 // class java/lang/Long
     174: invokevirtual #38                 // Method java/lang/Long.longValue:()J
     177: invokeinterface #68,  3           // InterfaceMethod java/io/DataOutput.writeLong:(J)V
     182: aload_1
     183: aload_0
     184: getfield      #7                  // Field onDiskDataSizes:Ljava/util/List;
     187: iload_2
     188: invokeinterface #36,  2           // InterfaceMethod java/util/List.get:(I)Ljava/lang/Object;
     193: checkcast     #46                 // class java/lang/Integer
     196: invokevirtual #47                 // Method java/lang/Integer.intValue:()I
     199: invokeinterface #61,  2           // InterfaceMethod java/io/DataOutput.writeInt:(I)V
     204: aload_1
     205: aload_0
     206: getfield      #5                  // Field blockKeys:Ljava/util/List;
     209: iload_2
     210: invokeinterface #36,  2           // InterfaceMethod java/util/List.get:(I)Ljava/lang/Object;
     215: checkcast     #69                 // class "[B"
     218: invokeinterface #70,  2           // InterfaceMethod java/io/DataOutput.write:([B)V
     223: iinc          2, 1
     226: goto          147
     229: return

  int getNonRootSize();
    Code:
       0: iconst_4
       1: iconst_4
       2: aload_0
       3: getfield      #5                  // Field blockKeys:Ljava/util/List;
       6: invokeinterface #19,  1           // InterfaceMethod java/util/List.size:()I
      11: iconst_1
      12: iadd
      13: imul
      14: iadd
      15: aload_0
      16: getfield      #9                  // Field curTotalNonRootEntrySize:I
      19: iadd
      20: ireturn

  void writeRoot(java.io.DataOutput) throws java.io.IOException;
    Code:
       0: iconst_0
       1: istore_2
       2: iload_2
       3: aload_0
       4: getfield      #5                  // Field blockKeys:Ljava/util/List;
       7: invokeinterface #19,  1           // InterfaceMethod java/util/List.size:()I
      12: if_icmpge     82
      15: aload_1
      16: aload_0
      17: getfield      #6                  // Field blockOffsets:Ljava/util/List;
      20: iload_2
      21: invokeinterface #36,  2           // InterfaceMethod java/util/List.get:(I)Ljava/lang/Object;
      26: checkcast     #37                 // class java/lang/Long
      29: invokevirtual #38                 // Method java/lang/Long.longValue:()J
      32: invokeinterface #68,  3           // InterfaceMethod java/io/DataOutput.writeLong:(J)V
      37: aload_1
      38: aload_0
      39: getfield      #7                  // Field onDiskDataSizes:Ljava/util/List;
      42: iload_2
      43: invokeinterface #36,  2           // InterfaceMethod java/util/List.get:(I)Ljava/lang/Object;
      48: checkcast     #46                 // class java/lang/Integer
      51: invokevirtual #47                 // Method java/lang/Integer.intValue:()I
      54: invokeinterface #61,  2           // InterfaceMethod java/io/DataOutput.writeInt:(I)V
      59: aload_1
      60: aload_0
      61: getfield      #5                  // Field blockKeys:Ljava/util/List;
      64: iload_2
      65: invokeinterface #36,  2           // InterfaceMethod java/util/List.get:(I)Ljava/lang/Object;
      70: checkcast     #69                 // class "[B"
      73: invokestatic  #71                 // Method org/apache/hadoop/hbase/util/Bytes.writeByteArray:(Ljava/io/DataOutput;[B)V
      76: iinc          2, 1
      79: goto          2
      82: return

  int getRootSize();
    Code:
       0: aload_0
       1: getfield      #10                 // Field curTotalRootSize:I
       4: ireturn

  public int getNumEntries();
    Code:
       0: aload_0
       1: getfield      #5                  // Field blockKeys:Ljava/util/List;
       4: invokeinterface #19,  1           // InterfaceMethod java/util/List.size:()I
       9: ireturn

  public byte[] getBlockKey(int);
    Code:
       0: aload_0
       1: getfield      #5                  // Field blockKeys:Ljava/util/List;
       4: iload_1
       5: invokeinterface #36,  2           // InterfaceMethod java/util/List.get:(I)Ljava/lang/Object;
      10: checkcast     #69                 // class "[B"
      13: areturn

  public long getBlockOffset(int);
    Code:
       0: aload_0
       1: getfield      #6                  // Field blockOffsets:Ljava/util/List;
       4: iload_1
       5: invokeinterface #36,  2           // InterfaceMethod java/util/List.get:(I)Ljava/lang/Object;
      10: checkcast     #37                 // class java/lang/Long
      13: invokevirtual #38                 // Method java/lang/Long.longValue:()J
      16: lreturn

  public int getOnDiskDataSize(int);
    Code:
       0: aload_0
       1: getfield      #7                  // Field onDiskDataSizes:Ljava/util/List;
       4: iload_1
       5: invokeinterface #36,  2           // InterfaceMethod java/util/List.get:(I)Ljava/lang/Object;
      10: checkcast     #46                 // class java/lang/Integer
      13: invokevirtual #47                 // Method java/lang/Integer.intValue:()I
      16: ireturn

  public long getCumulativeNumKV(int);
    Code:
       0: iload_1
       1: ifge          6
       4: lconst_0
       5: lreturn
       6: aload_0
       7: getfield      #8                  // Field numSubEntriesAt:Ljava/util/List;
      10: iload_1
      11: invokeinterface #36,  2           // InterfaceMethod java/util/List.get:(I)Ljava/lang/Object;
      16: checkcast     #37                 // class java/lang/Long
      19: invokevirtual #38                 // Method java/lang/Long.longValue:()J
      22: lreturn
}
