Compiled from "HFileBlock.java"
public final class org.apache.hadoop.hbase.io.hfile.HFileBlock$BlockDeserializer implements org.apache.hadoop.hbase.io.hfile.CacheableDeserializer<org.apache.hadoop.hbase.io.hfile.Cacheable> {
  public org.apache.hadoop.hbase.io.hfile.HFileBlock deserialize(org.apache.hadoop.hbase.nio.ByteBuff, boolean, org.apache.hadoop.hbase.io.hfile.Cacheable$MemoryType) throws java.io.IOException;
    Code:
       0: aload_1
       1: aload_1
       2: invokevirtual #4                  // Method org/apache/hadoop/hbase/nio/ByteBuff.limit:()I
       5: bipush        13
       7: isub
       8: invokevirtual #5                  // Method org/apache/hadoop/hbase/nio/ByteBuff.limit:(I)Lorg/apache/hadoop/hbase/nio/ByteBuff;
      11: invokevirtual #6                  // Method org/apache/hadoop/hbase/nio/ByteBuff.rewind:()Lorg/apache/hadoop/hbase/nio/ByteBuff;
      14: pop
      15: iload_2
      16: ifeq          28
      19: aload_1
      20: invokevirtual #7                  // Method org/apache/hadoop/hbase/nio/ByteBuff.slice:()Lorg/apache/hadoop/hbase/nio/ByteBuff;
      23: astore        4
      25: goto          62
      28: aload_1
      29: invokevirtual #4                  // Method org/apache/hadoop/hbase/nio/ByteBuff.limit:()I
      32: istore        5
      34: new           #8                  // class org/apache/hadoop/hbase/nio/SingleByteBuff
      37: dup
      38: iload         5
      40: invokestatic  #9                  // Method java/nio/ByteBuffer.allocate:(I)Ljava/nio/ByteBuffer;
      43: invokespecial #10                 // Method org/apache/hadoop/hbase/nio/SingleByteBuff."<init>":(Ljava/nio/ByteBuffer;)V
      46: astore        4
      48: aload         4
      50: iconst_0
      51: aload_1
      52: aload_1
      53: invokevirtual #11                 // Method org/apache/hadoop/hbase/nio/ByteBuff.position:()I
      56: iload         5
      58: invokevirtual #12                 // Method org/apache/hadoop/hbase/nio/ByteBuff.put:(ILorg/apache/hadoop/hbase/nio/ByteBuff;II)Lorg/apache/hadoop/hbase/nio/ByteBuff;
      61: pop
      62: aload_1
      63: aload_1
      64: invokevirtual #4                  // Method org/apache/hadoop/hbase/nio/ByteBuff.limit:()I
      67: invokevirtual #13                 // Method org/apache/hadoop/hbase/nio/ByteBuff.position:(I)Lorg/apache/hadoop/hbase/nio/ByteBuff;
      70: pop
      71: aload_1
      72: aload_1
      73: invokevirtual #4                  // Method org/apache/hadoop/hbase/nio/ByteBuff.limit:()I
      76: bipush        13
      78: iadd
      79: invokevirtual #5                  // Method org/apache/hadoop/hbase/nio/ByteBuff.limit:(I)Lorg/apache/hadoop/hbase/nio/ByteBuff;
      82: pop
      83: aload_1
      84: invokevirtual #14                 // Method org/apache/hadoop/hbase/nio/ByteBuff.get:()B
      87: iconst_1
      88: if_icmpne     95
      91: iconst_1
      92: goto          96
      95: iconst_0
      96: istore        5
      98: aload_1
      99: invokevirtual #15                 // Method org/apache/hadoop/hbase/nio/ByteBuff.getLong:()J
     102: lstore        6
     104: aload_1
     105: invokevirtual #16                 // Method org/apache/hadoop/hbase/nio/ByteBuff.getInt:()I
     108: istore        8
     110: new           #1                  // class org/apache/hadoop/hbase/io/hfile/HFileBlock
     113: dup
     114: aload         4
     116: iload         5
     118: aload_3
     119: lload         6
     121: iload         8
     123: aconst_null
     124: invokespecial #17                 // Method org/apache/hadoop/hbase/io/hfile/HFileBlock."<init>":(Lorg/apache/hadoop/hbase/nio/ByteBuff;ZLorg/apache/hadoop/hbase/io/hfile/Cacheable$MemoryType;JILorg/apache/hadoop/hbase/io/hfile/HFileContext;)V
     127: astore        9
     129: aload         9
     131: areturn

  public int getDeserialiserIdentifier();
    Code:
       0: invokestatic  #18                 // Method org/apache/hadoop/hbase/io/hfile/HFileBlock.access$100:()I
       3: ireturn

  public org.apache.hadoop.hbase.io.hfile.HFileBlock deserialize(org.apache.hadoop.hbase.nio.ByteBuff) throws java.io.IOException;
    Code:
       0: aload_0
       1: aload_1
       2: iconst_0
       3: getstatic     #19                 // Field org/apache/hadoop/hbase/io/hfile/Cacheable$MemoryType.EXCLUSIVE:Lorg/apache/hadoop/hbase/io/hfile/Cacheable$MemoryType;
       6: invokevirtual #20                 // Method deserialize:(Lorg/apache/hadoop/hbase/nio/ByteBuff;ZLorg/apache/hadoop/hbase/io/hfile/Cacheable$MemoryType;)Lorg/apache/hadoop/hbase/io/hfile/HFileBlock;
       9: areturn

  public org.apache.hadoop.hbase.io.hfile.Cacheable deserialize(org.apache.hadoop.hbase.nio.ByteBuff, boolean, org.apache.hadoop.hbase.io.hfile.Cacheable$MemoryType) throws java.io.IOException;
    Code:
       0: aload_0
       1: aload_1
       2: iload_2
       3: aload_3
       4: invokevirtual #20                 // Method deserialize:(Lorg/apache/hadoop/hbase/nio/ByteBuff;ZLorg/apache/hadoop/hbase/io/hfile/Cacheable$MemoryType;)Lorg/apache/hadoop/hbase/io/hfile/HFileBlock;
       7: areturn

  public org.apache.hadoop.hbase.io.hfile.Cacheable deserialize(org.apache.hadoop.hbase.nio.ByteBuff) throws java.io.IOException;
    Code:
       0: aload_0
       1: aload_1
       2: invokevirtual #21                 // Method deserialize:(Lorg/apache/hadoop/hbase/nio/ByteBuff;)Lorg/apache/hadoop/hbase/io/hfile/HFileBlock;
       5: areturn

  org.apache.hadoop.hbase.io.hfile.HFileBlock$BlockDeserializer(org.apache.hadoop.hbase.io.hfile.HFileBlock$1);
    Code:
       0: aload_0
       1: invokespecial #2                  // Method "<init>":()V
       4: return
}
