Compiled from "HFileReaderImpl.java"
public class org.apache.hadoop.hbase.io.hfile.HFileReaderImpl$HFileScannerImpl implements org.apache.hadoop.hbase.io.hfile.HFileScanner {
  protected final boolean cacheBlocks;

  protected final boolean pread;

  protected final boolean isCompaction;

  protected java.util.concurrent.atomic.AtomicInteger blockFetches;

  protected final org.apache.hadoop.hbase.io.hfile.HFile$Reader reader;

  final org.apache.hadoop.hbase.util.ObjectIntPair<java.nio.ByteBuffer> pair;

  protected org.apache.hadoop.hbase.Cell nextIndexedKey;

  protected org.apache.hadoop.hbase.io.hfile.HFileBlock curBlock;

  protected final java.util.ArrayList<org.apache.hadoop.hbase.io.hfile.HFileBlock> prevBlocks;

  public org.apache.hadoop.hbase.io.hfile.HFileReaderImpl$HFileScannerImpl(org.apache.hadoop.hbase.io.hfile.HFile$Reader, boolean, boolean, boolean);
    Code:
       0: aload_0
       1: invokespecial #2                  // Method java/lang/Object."<init>":()V
       4: aload_0
       5: new           #3                  // class java/util/concurrent/atomic/AtomicInteger
       8: dup
       9: iconst_0
      10: invokespecial #4                  // Method java/util/concurrent/atomic/AtomicInteger."<init>":(I)V
      13: putfield      #5                  // Field blockFetches:Ljava/util/concurrent/atomic/AtomicInteger;
      16: aload_0
      17: new           #6                  // class org/apache/hadoop/hbase/ByteBufferKeyOnlyKeyValue
      20: dup
      21: invokespecial #7                  // Method org/apache/hadoop/hbase/ByteBufferKeyOnlyKeyValue."<init>":()V
      24: putfield      #8                  // Field bufBackedKeyOnlyKv:Lorg/apache/hadoop/hbase/ByteBufferKeyOnlyKeyValue;
      27: aload_0
      28: new           #9                  // class org/apache/hadoop/hbase/util/ObjectIntPair
      31: dup
      32: invokespecial #10                 // Method org/apache/hadoop/hbase/util/ObjectIntPair."<init>":()V
      35: putfield      #11                 // Field pair:Lorg/apache/hadoop/hbase/util/ObjectIntPair;
      38: aload_0
      39: new           #12                 // class java/util/ArrayList
      42: dup
      43: invokespecial #13                 // Method java/util/ArrayList."<init>":()V
      46: putfield      #14                 // Field prevBlocks:Ljava/util/ArrayList;
      49: aload_0
      50: aload_1
      51: putfield      #15                 // Field reader:Lorg/apache/hadoop/hbase/io/hfile/HFile$Reader;
      54: aload_0
      55: iload_2
      56: putfield      #16                 // Field cacheBlocks:Z
      59: aload_0
      60: iload_3
      61: putfield      #17                 // Field pread:Z
      64: aload_0
      65: iload         4
      67: putfield      #18                 // Field isCompaction:Z
      70: return

  void updateCurrBlockRef(org.apache.hadoop.hbase.io.hfile.HFileBlock);
    Code:
       0: aload_1
       1: ifnull        27
       4: aload_0
       5: getfield      #19                 // Field curBlock:Lorg/apache/hadoop/hbase/io/hfile/HFileBlock;
       8: ifnull        27
      11: aload_1
      12: invokevirtual #20                 // Method org/apache/hadoop/hbase/io/hfile/HFileBlock.getOffset:()J
      15: aload_0
      16: getfield      #19                 // Field curBlock:Lorg/apache/hadoop/hbase/io/hfile/HFileBlock;
      19: invokevirtual #20                 // Method org/apache/hadoop/hbase/io/hfile/HFileBlock.getOffset:()J
      22: lcmp
      23: ifne          27
      26: return
      27: aload_0
      28: getfield      #19                 // Field curBlock:Lorg/apache/hadoop/hbase/io/hfile/HFileBlock;
      31: ifnull        56
      34: aload_0
      35: getfield      #19                 // Field curBlock:Lorg/apache/hadoop/hbase/io/hfile/HFileBlock;
      38: invokevirtual #21                 // Method org/apache/hadoop/hbase/io/hfile/HFileBlock.usesSharedMemory:()Z
      41: ifeq          56
      44: aload_0
      45: getfield      #14                 // Field prevBlocks:Ljava/util/ArrayList;
      48: aload_0
      49: getfield      #19                 // Field curBlock:Lorg/apache/hadoop/hbase/io/hfile/HFileBlock;
      52: invokevirtual #22                 // Method java/util/ArrayList.add:(Ljava/lang/Object;)Z
      55: pop
      56: aload_0
      57: aload_1
      58: putfield      #19                 // Field curBlock:Lorg/apache/hadoop/hbase/io/hfile/HFileBlock;
      61: return

  void reset();
    Code:
       0: aload_0
       1: getfield      #19                 // Field curBlock:Lorg/apache/hadoop/hbase/io/hfile/HFileBlock;
       4: ifnull        29
       7: aload_0
       8: getfield      #19                 // Field curBlock:Lorg/apache/hadoop/hbase/io/hfile/HFileBlock;
      11: invokevirtual #21                 // Method org/apache/hadoop/hbase/io/hfile/HFileBlock.usesSharedMemory:()Z
      14: ifeq          29
      17: aload_0
      18: getfield      #14                 // Field prevBlocks:Ljava/util/ArrayList;
      21: aload_0
      22: getfield      #19                 // Field curBlock:Lorg/apache/hadoop/hbase/io/hfile/HFileBlock;
      25: invokevirtual #22                 // Method java/util/ArrayList.add:(Ljava/lang/Object;)Z
      28: pop
      29: aload_0
      30: aconst_null
      31: putfield      #19                 // Field curBlock:Lorg/apache/hadoop/hbase/io/hfile/HFileBlock;
      34: return

  public boolean isSeeked();
    Code:
       0: aload_0
       1: getfield      #38                 // Field blockBuffer:Lorg/apache/hadoop/hbase/nio/ByteBuff;
       4: ifnull        11
       7: iconst_1
       8: goto          12
      11: iconst_0
      12: ireturn

  public java.lang.String toString();
    Code:
       0: new           #25                 // class java/lang/StringBuilder
       3: dup
       4: invokespecial #26                 // Method java/lang/StringBuilder."<init>":()V
       7: ldc           #39                 // String HFileScanner for reader
       9: invokevirtual #28                 // Method java/lang/StringBuilder.append:(Ljava/lang/String;)Ljava/lang/StringBuilder;
      12: aload_0
      13: invokevirtual #40                 // Method getReader:()Lorg/apache/hadoop/hbase/io/hfile/HFile$Reader;
      16: invokestatic  #41                 // Method java/lang/String.valueOf:(Ljava/lang/Object;)Ljava/lang/String;
      19: invokevirtual #28                 // Method java/lang/StringBuilder.append:(Ljava/lang/String;)Ljava/lang/StringBuilder;
      22: invokevirtual #30                 // Method java/lang/StringBuilder.toString:()Ljava/lang/String;
      25: areturn

  protected void assertSeeked();
    Code:
       0: aload_0
       1: invokevirtual #42                 // Method isSeeked:()Z
       4: ifne          24
       7: new           #43                 // class org/apache/hadoop/hbase/io/hfile/HFileReaderImpl$NotSeekedException
      10: dup
      11: aload_0
      12: getfield      #15                 // Field reader:Lorg/apache/hadoop/hbase/io/hfile/HFile$Reader;
      15: invokeinterface #44,  1           // InterfaceMethod org/apache/hadoop/hbase/io/hfile/HFile$Reader.getPath:()Lorg/apache/hadoop/fs/Path;
      20: invokespecial #45                 // Method org/apache/hadoop/hbase/io/hfile/HFileReaderImpl$NotSeekedException."<init>":(Lorg/apache/hadoop/fs/Path;)V
      23: athrow
      24: return

  public org.apache.hadoop.hbase.io.hfile.HFile$Reader getReader();
    Code:
       0: aload_0
       1: getfield      #15                 // Field reader:Lorg/apache/hadoop/hbase/io/hfile/HFile$Reader;
       4: areturn

  public void close();
    Code:
       0: aload_0
       1: getfield      #17                 // Field pread:Z
       4: ifne          16
       7: aload_0
       8: getfield      #15                 // Field reader:Lorg/apache/hadoop/hbase/io/hfile/HFile$Reader;
      11: invokeinterface #50,  1           // InterfaceMethod org/apache/hadoop/hbase/io/hfile/HFile$Reader.unbufferStream:()V
      16: aload_0
      17: iconst_1
      18: invokespecial #51                 // Method returnBlocks:(Z)V
      21: return

  protected void readKeyValueLen();
    Code:
       0: aload_0
       1: getfield      #38                 // Field blockBuffer:Lorg/apache/hadoop/hbase/nio/ByteBuff;
       4: iconst_0
       5: invokevirtual #55                 // Method org/apache/hadoop/hbase/nio/ByteBuff.getLongAfterPosition:(I)J
       8: lstore_1
       9: aload_0
      10: lload_1
      11: bipush        32
      13: lshr
      14: l2i
      15: putfield      #46                 // Field currKeyLen:I
      18: aload_0
      19: ldc2_w        #57                 // long -4294967296l
      22: lload_1
      23: lxor
      24: l2i
      25: putfield      #47                 // Field currValueLen:I
      28: aload_0
      29: invokevirtual #59                 // Method checkKeyValueLen:()V
      32: bipush        8
      34: aload_0
      35: getfield      #46                 // Field currKeyLen:I
      38: iadd
      39: aload_0
      40: getfield      #47                 // Field currValueLen:I
      43: iadd
      44: istore_3
      45: aload_0
      46: getfield      #15                 // Field reader:Lorg/apache/hadoop/hbase/io/hfile/HFile$Reader;
      49: invokeinterface #53,  1           // InterfaceMethod org/apache/hadoop/hbase/io/hfile/HFile$Reader.getFileContext:()Lorg/apache/hadoop/hbase/io/hfile/HFileContext;
      54: invokevirtual #54                 // Method org/apache/hadoop/hbase/io/hfile/HFileContext.isIncludesTags:()Z
      57: ifeq          85
      60: aload_0
      61: aload_0
      62: getfield      #38                 // Field blockBuffer:Lorg/apache/hadoop/hbase/nio/ByteBuff;
      65: iload_3
      66: invokevirtual #60                 // Method org/apache/hadoop/hbase/nio/ByteBuff.getShortAfterPosition:(I)S
      69: putfield      #48                 // Field currTagsLen:I
      72: aload_0
      73: invokespecial #61                 // Method checkTagsLen:()V
      76: iload_3
      77: iconst_2
      78: aload_0
      79: getfield      #48                 // Field currTagsLen:I
      82: iadd
      83: iadd
      84: istore_3
      85: aload_0
      86: iload_3
      87: invokevirtual #62                 // Method readMvccVersion:(I)V
      90: return

  protected void readMvccVersion(int);
    Code:
       0: aload_0
       1: getfield      #15                 // Field reader:Lorg/apache/hadoop/hbase/io/hfile/HFile$Reader;
       4: invokeinterface #75,  1           // InterfaceMethod org/apache/hadoop/hbase/io/hfile/HFile$Reader.shouldIncludeMemStoreTS:()Z
       9: ifne          13
      12: return
      13: aload_0
      14: getfield      #15                 // Field reader:Lorg/apache/hadoop/hbase/io/hfile/HFile$Reader;
      17: invokeinterface #76,  1           // InterfaceMethod org/apache/hadoop/hbase/io/hfile/HFile$Reader.isDecodeMemStoreTS:()Z
      22: ifne          36
      25: aload_0
      26: lconst_0
      27: putfield      #77                 // Field currMemstoreTS:J
      30: aload_0
      31: iconst_1
      32: putfield      #52                 // Field currMemstoreTSLen:I
      35: return
      36: aload_0
      37: iload_1
      38: invokespecial #78                 // Method _readMvccVersion:(I)V
      41: return

  protected int blockSeek(org.apache.hadoop.hbase.Cell, boolean);
    Code:
       0: iconst_0
       1: istore        5
       3: iconst_m1
       4: istore        6
       6: iconst_0
       7: istore        7
       9: aload_0
      10: getfield      #38                 // Field blockBuffer:Lorg/apache/hadoop/hbase/nio/ByteBuff;
      13: iload         7
      15: invokevirtual #55                 // Method org/apache/hadoop/hbase/nio/ByteBuff.getLongAfterPosition:(I)J
      18: lstore        8
      20: lload         8
      22: bipush        32
      24: lshr
      25: l2i
      26: istore_3
      27: ldc2_w        #57                 // long -4294967296l
      30: lload         8
      32: lxor
      33: l2i
      34: istore        4
      36: aload_0
      37: iload_3
      38: invokevirtual #88                 // Method checkKeyLen:(I)Z
      41: ifne          53
      44: aload_0
      45: iload         4
      47: invokevirtual #63                 // Method checkLen:(I)Z
      50: ifeq          152
      53: new           #64                 // class java/lang/IllegalStateException
      56: dup
      57: new           #25                 // class java/lang/StringBuilder
      60: dup
      61: invokespecial #26                 // Method java/lang/StringBuilder."<init>":()V
      64: ldc           #89                 // String Invalid klen
      66: invokevirtual #28                 // Method java/lang/StringBuilder.append:(Ljava/lang/String;)Ljava/lang/StringBuilder;
      69: iload_3
      70: invokevirtual #66                 // Method java/lang/StringBuilder.append:(I)Ljava/lang/StringBuilder;
      73: ldc           #90                 // String  or vlen
      75: invokevirtual #28                 // Method java/lang/StringBuilder.append:(Ljava/lang/String;)Ljava/lang/StringBuilder;
      78: iload         4
      80: invokevirtual #66                 // Method java/lang/StringBuilder.append:(I)Ljava/lang/StringBuilder;
      83: ldc           #67                 // String . Block offset:
      85: invokevirtual #28                 // Method java/lang/StringBuilder.append:(Ljava/lang/String;)Ljava/lang/StringBuilder;
      88: aload_0
      89: getfield      #19                 // Field curBlock:Lorg/apache/hadoop/hbase/io/hfile/HFileBlock;
      92: invokevirtual #20                 // Method org/apache/hadoop/hbase/io/hfile/HFileBlock.getOffset:()J
      95: invokevirtual #68                 // Method java/lang/StringBuilder.append:(J)Ljava/lang/StringBuilder;
      98: ldc           #69                 // String , block length:
     100: invokevirtual #28                 // Method java/lang/StringBuilder.append:(Ljava/lang/String;)Ljava/lang/StringBuilder;
     103: aload_0
     104: getfield      #38                 // Field blockBuffer:Lorg/apache/hadoop/hbase/nio/ByteBuff;
     107: invokevirtual #70                 // Method org/apache/hadoop/hbase/nio/ByteBuff.limit:()I
     110: invokevirtual #66                 // Method java/lang/StringBuilder.append:(I)Ljava/lang/StringBuilder;
     113: ldc           #71                 // String , position:
     115: invokevirtual #28                 // Method java/lang/StringBuilder.append:(Ljava/lang/String;)Ljava/lang/StringBuilder;
     118: aload_0
     119: getfield      #38                 // Field blockBuffer:Lorg/apache/hadoop/hbase/nio/ByteBuff;
     122: invokevirtual #72                 // Method org/apache/hadoop/hbase/nio/ByteBuff.position:()I
     125: invokevirtual #66                 // Method java/lang/StringBuilder.append:(I)Ljava/lang/StringBuilder;
     128: ldc           #73                 // String  (without header). path=
     130: invokevirtual #28                 // Method java/lang/StringBuilder.append:(Ljava/lang/String;)Ljava/lang/StringBuilder;
     133: aload_0
     134: getfield      #15                 // Field reader:Lorg/apache/hadoop/hbase/io/hfile/HFile$Reader;
     137: invokeinterface #44,  1           // InterfaceMethod org/apache/hadoop/hbase/io/hfile/HFile$Reader.getPath:()Lorg/apache/hadoop/fs/Path;
     142: invokevirtual #29                 // Method java/lang/StringBuilder.append:(Ljava/lang/Object;)Ljava/lang/StringBuilder;
     145: invokevirtual #30                 // Method java/lang/StringBuilder.toString:()Ljava/lang/String;
     148: invokespecial #74                 // Method java/lang/IllegalStateException."<init>":(Ljava/lang/String;)V
     151: athrow
     152: iinc          7, 8
     155: aload_0
     156: getfield      #38                 // Field blockBuffer:Lorg/apache/hadoop/hbase/nio/ByteBuff;
     159: aload_0
     160: getfield      #38                 // Field blockBuffer:Lorg/apache/hadoop/hbase/nio/ByteBuff;
     163: invokevirtual #72                 // Method org/apache/hadoop/hbase/nio/ByteBuff.position:()I
     166: iload         7
     168: iadd
     169: iload_3
     170: aload_0
     171: getfield      #11                 // Field pair:Lorg/apache/hadoop/hbase/util/ObjectIntPair;
     174: invokevirtual #91                 // Method org/apache/hadoop/hbase/nio/ByteBuff.asSubByteBuffer:(IILorg/apache/hadoop/hbase/util/ObjectIntPair;)V
     177: aload_0
     178: getfield      #8                  // Field bufBackedKeyOnlyKv:Lorg/apache/hadoop/hbase/ByteBufferKeyOnlyKeyValue;
     181: aload_0
     182: getfield      #11                 // Field pair:Lorg/apache/hadoop/hbase/util/ObjectIntPair;
     185: invokevirtual #92                 // Method org/apache/hadoop/hbase/util/ObjectIntPair.getFirst:()Ljava/lang/Object;
     188: checkcast     #93                 // class java/nio/ByteBuffer
     191: aload_0
     192: getfield      #11                 // Field pair:Lorg/apache/hadoop/hbase/util/ObjectIntPair;
     195: invokevirtual #94                 // Method org/apache/hadoop/hbase/util/ObjectIntPair.getSecond:()I
     198: iload_3
     199: invokevirtual #95                 // Method org/apache/hadoop/hbase/ByteBufferKeyOnlyKeyValue.setKey:(Ljava/nio/ByteBuffer;II)V
     202: aload_0
     203: getfield      #15                 // Field reader:Lorg/apache/hadoop/hbase/io/hfile/HFile$Reader;
     206: invokeinterface #96,  1           // InterfaceMethod org/apache/hadoop/hbase/io/hfile/HFile$Reader.getComparator:()Lorg/apache/hadoop/hbase/CellComparator;
     211: aload_1
     212: aload_0
     213: getfield      #8                  // Field bufBackedKeyOnlyKv:Lorg/apache/hadoop/hbase/ByteBufferKeyOnlyKeyValue;
     216: invokestatic  #97                 // Method org/apache/hadoop/hbase/PrivateCellUtil.compareKeyIgnoresMvcc:(Lorg/apache/hadoop/hbase/CellComparator;Lorg/apache/hadoop/hbase/Cell;Lorg/apache/hadoop/hbase/Cell;)I
     219: istore        10
     221: iload         7
     223: iload_3
     224: iload         4
     226: iadd
     227: iadd
     228: istore        7
     230: aload_0
     231: getfield      #15                 // Field reader:Lorg/apache/hadoop/hbase/io/hfile/HFile$Reader;
     234: invokeinterface #53,  1           // InterfaceMethod org/apache/hadoop/hbase/io/hfile/HFile$Reader.getFileContext:()Lorg/apache/hadoop/hbase/io/hfile/HFileContext;
     239: invokevirtual #54                 // Method org/apache/hadoop/hbase/io/hfile/HFileContext.isIncludesTags:()Z
     242: ifeq          387
     245: aload_0
     246: getfield      #38                 // Field blockBuffer:Lorg/apache/hadoop/hbase/nio/ByteBuff;
     249: iload         7
     251: invokevirtual #79                 // Method org/apache/hadoop/hbase/nio/ByteBuff.getByteAfterPosition:(I)B
     254: sipush        255
     257: iand
     258: bipush        8
     260: ishl
     261: aload_0
     262: getfield      #38                 // Field blockBuffer:Lorg/apache/hadoop/hbase/nio/ByteBuff;
     265: iload         7
     267: iconst_1
     268: iadd
     269: invokevirtual #79                 // Method org/apache/hadoop/hbase/nio/ByteBuff.getByteAfterPosition:(I)B
     272: sipush        255
     275: iand
     276: ixor
     277: istore        5
     279: aload_0
     280: iload         5
     282: invokevirtual #63                 // Method checkLen:(I)Z
     285: ifeq          378
     288: new           #64                 // class java/lang/IllegalStateException
     291: dup
     292: new           #25                 // class java/lang/StringBuilder
     295: dup
     296: invokespecial #26                 // Method java/lang/StringBuilder."<init>":()V
     299: ldc           #98                 // String Invalid tlen
     301: invokevirtual #28                 // Method java/lang/StringBuilder.append:(Ljava/lang/String;)Ljava/lang/StringBuilder;
     304: iload         5
     306: invokevirtual #66                 // Method java/lang/StringBuilder.append:(I)Ljava/lang/StringBuilder;
     309: ldc           #67                 // String . Block offset:
     311: invokevirtual #28                 // Method java/lang/StringBuilder.append:(Ljava/lang/String;)Ljava/lang/StringBuilder;
     314: aload_0
     315: getfield      #19                 // Field curBlock:Lorg/apache/hadoop/hbase/io/hfile/HFileBlock;
     318: invokevirtual #20                 // Method org/apache/hadoop/hbase/io/hfile/HFileBlock.getOffset:()J
     321: invokevirtual #68                 // Method java/lang/StringBuilder.append:(J)Ljava/lang/StringBuilder;
     324: ldc           #69                 // String , block length:
     326: invokevirtual #28                 // Method java/lang/StringBuilder.append:(Ljava/lang/String;)Ljava/lang/StringBuilder;
     329: aload_0
     330: getfield      #38                 // Field blockBuffer:Lorg/apache/hadoop/hbase/nio/ByteBuff;
     333: invokevirtual #70                 // Method org/apache/hadoop/hbase/nio/ByteBuff.limit:()I
     336: invokevirtual #66                 // Method java/lang/StringBuilder.append:(I)Ljava/lang/StringBuilder;
     339: ldc           #71                 // String , position:
     341: invokevirtual #28                 // Method java/lang/StringBuilder.append:(Ljava/lang/String;)Ljava/lang/StringBuilder;
     344: aload_0
     345: getfield      #38                 // Field blockBuffer:Lorg/apache/hadoop/hbase/nio/ByteBuff;
     348: invokevirtual #72                 // Method org/apache/hadoop/hbase/nio/ByteBuff.position:()I
     351: invokevirtual #66                 // Method java/lang/StringBuilder.append:(I)Ljava/lang/StringBuilder;
     354: ldc           #73                 // String  (without header). path=
     356: invokevirtual #28                 // Method java/lang/StringBuilder.append:(Ljava/lang/String;)Ljava/lang/StringBuilder;
     359: aload_0
     360: getfield      #15                 // Field reader:Lorg/apache/hadoop/hbase/io/hfile/HFile$Reader;
     363: invokeinterface #44,  1           // InterfaceMethod org/apache/hadoop/hbase/io/hfile/HFile$Reader.getPath:()Lorg/apache/hadoop/fs/Path;
     368: invokevirtual #29                 // Method java/lang/StringBuilder.append:(Ljava/lang/Object;)Ljava/lang/StringBuilder;
     371: invokevirtual #30                 // Method java/lang/StringBuilder.toString:()Ljava/lang/String;
     374: invokespecial #74                 // Method java/lang/IllegalStateException."<init>":(Ljava/lang/String;)V
     377: athrow
     378: iload         7
     380: iload         5
     382: iconst_2
     383: iadd
     384: iadd
     385: istore        7
     387: aload_0
     388: getfield      #15                 // Field reader:Lorg/apache/hadoop/hbase/io/hfile/HFile$Reader;
     391: invokeinterface #75,  1           // InterfaceMethod org/apache/hadoop/hbase/io/hfile/HFile$Reader.shouldIncludeMemStoreTS:()Z
     396: ifeq          405
     399: aload_0
     400: iload         7
     402: invokevirtual #62                 // Method readMvccVersion:(I)V
     405: iload         10
     407: ifne          531
     410: iload_2
     411: ifeq          512
     414: iload         6
     416: ifge          496
     419: new           #64                 // class java/lang/IllegalStateException
     422: dup
     423: new           #25                 // class java/lang/StringBuilder
     426: dup
     427: invokespecial #26                 // Method java/lang/StringBuilder."<init>":()V
     430: ldc           #99                 // String blockSeek with seekBefore at the first key of the block: key=
     432: invokevirtual #28                 // Method java/lang/StringBuilder.append:(Ljava/lang/String;)Ljava/lang/StringBuilder;
     435: aload_1
     436: invokestatic  #100                // Method org/apache/hadoop/hbase/CellUtil.getCellKeyAsString:(Lorg/apache/hadoop/hbase/Cell;)Ljava/lang/String;
     439: invokevirtual #28                 // Method java/lang/StringBuilder.append:(Ljava/lang/String;)Ljava/lang/StringBuilder;
     442: ldc           #101                // String , blockOffset=
     444: invokevirtual #28                 // Method java/lang/StringBuilder.append:(Ljava/lang/String;)Ljava/lang/StringBuilder;
     447: aload_0
     448: getfield      #19                 // Field curBlock:Lorg/apache/hadoop/hbase/io/hfile/HFileBlock;
     451: invokevirtual #20                 // Method org/apache/hadoop/hbase/io/hfile/HFileBlock.getOffset:()J
     454: invokevirtual #68                 // Method java/lang/StringBuilder.append:(J)Ljava/lang/StringBuilder;
     457: ldc           #102                // String , onDiskSize=
     459: invokevirtual #28                 // Method java/lang/StringBuilder.append:(Ljava/lang/String;)Ljava/lang/StringBuilder;
     462: aload_0
     463: getfield      #19                 // Field curBlock:Lorg/apache/hadoop/hbase/io/hfile/HFileBlock;
     466: invokevirtual #103                // Method org/apache/hadoop/hbase/io/hfile/HFileBlock.getOnDiskSizeWithHeader:()I
     469: invokevirtual #66                 // Method java/lang/StringBuilder.append:(I)Ljava/lang/StringBuilder;
     472: ldc           #104                // String , path=
     474: invokevirtual #28                 // Method java/lang/StringBuilder.append:(Ljava/lang/String;)Ljava/lang/StringBuilder;
     477: aload_0
     478: getfield      #15                 // Field reader:Lorg/apache/hadoop/hbase/io/hfile/HFile$Reader;
     481: invokeinterface #44,  1           // InterfaceMethod org/apache/hadoop/hbase/io/hfile/HFile$Reader.getPath:()Lorg/apache/hadoop/fs/Path;
     486: invokevirtual #29                 // Method java/lang/StringBuilder.append:(Ljava/lang/Object;)Ljava/lang/StringBuilder;
     489: invokevirtual #30                 // Method java/lang/StringBuilder.toString:()Ljava/lang/String;
     492: invokespecial #74                 // Method java/lang/IllegalStateException."<init>":(Ljava/lang/String;)V
     495: athrow
     496: aload_0
     497: getfield      #38                 // Field blockBuffer:Lorg/apache/hadoop/hbase/nio/ByteBuff;
     500: iload         6
     502: invokevirtual #105                // Method org/apache/hadoop/hbase/nio/ByteBuff.moveBack:(I)Lorg/apache/hadoop/hbase/nio/ByteBuff;
     505: pop
     506: aload_0
     507: invokevirtual #106                // Method readKeyValueLen:()V
     510: iconst_1
     511: ireturn
     512: aload_0
     513: iload_3
     514: putfield      #46                 // Field currKeyLen:I
     517: aload_0
     518: iload         4
     520: putfield      #47                 // Field currValueLen:I
     523: aload_0
     524: iload         5
     526: putfield      #48                 // Field currTagsLen:I
     529: iconst_0
     530: ireturn
     531: iload         10
     533: ifge          576
     536: iload         6
     538: ifle          551
     541: aload_0
     542: getfield      #38                 // Field blockBuffer:Lorg/apache/hadoop/hbase/nio/ByteBuff;
     545: iload         6
     547: invokevirtual #105                // Method org/apache/hadoop/hbase/nio/ByteBuff.moveBack:(I)Lorg/apache/hadoop/hbase/nio/ByteBuff;
     550: pop
     551: aload_0
     552: invokevirtual #106                // Method readKeyValueLen:()V
     555: iload         6
     557: iconst_m1
     558: if_icmpne     574
     561: aload_0
     562: getfield      #38                 // Field blockBuffer:Lorg/apache/hadoop/hbase/nio/ByteBuff;
     565: invokevirtual #72                 // Method org/apache/hadoop/hbase/nio/ByteBuff.position:()I
     568: ifne          574
     571: bipush        -2
     573: ireturn
     574: iconst_1
     575: ireturn
     576: iload_3
     577: iload         4
     579: iadd
     580: aload_0
     581: getfield      #52                 // Field currMemstoreTSLen:I
     584: iadd
     585: bipush        8
     587: iadd
     588: istore        6
     590: aload_0
     591: getfield      #15                 // Field reader:Lorg/apache/hadoop/hbase/io/hfile/HFile$Reader;
     594: invokeinterface #53,  1           // InterfaceMethod org/apache/hadoop/hbase/io/hfile/HFile$Reader.getFileContext:()Lorg/apache/hadoop/hbase/io/hfile/HFileContext;
     599: invokevirtual #54                 // Method org/apache/hadoop/hbase/io/hfile/HFileContext.isIncludesTags:()Z
     602: ifeq          614
     605: iload         6
     607: iload         5
     609: iconst_2
     610: iadd
     611: iadd
     612: istore        6
     614: aload_0
     615: getfield      #38                 // Field blockBuffer:Lorg/apache/hadoop/hbase/nio/ByteBuff;
     618: iload         6
     620: invokevirtual #108                // Method org/apache/hadoop/hbase/nio/ByteBuff.skip:(I)Lorg/apache/hadoop/hbase/nio/ByteBuff;
     623: pop
     624: aload_0
     625: getfield      #38                 // Field blockBuffer:Lorg/apache/hadoop/hbase/nio/ByteBuff;
     628: invokevirtual #109                // Method org/apache/hadoop/hbase/nio/ByteBuff.hasRemaining:()Z
     631: ifne          6
     634: aload_0
     635: getfield      #38                 // Field blockBuffer:Lorg/apache/hadoop/hbase/nio/ByteBuff;
     638: iload         6
     640: invokevirtual #105                // Method org/apache/hadoop/hbase/nio/ByteBuff.moveBack:(I)Lorg/apache/hadoop/hbase/nio/ByteBuff;
     643: pop
     644: aload_0
     645: invokevirtual #106                // Method readKeyValueLen:()V
     648: iconst_1
     649: ireturn

  public org.apache.hadoop.hbase.Cell getNextIndexedKey();
    Code:
       0: aload_0
       1: getfield      #110                // Field nextIndexedKey:Lorg/apache/hadoop/hbase/Cell;
       4: areturn

  public int seekTo(org.apache.hadoop.hbase.Cell) throws java.io.IOException;
    Code:
       0: aload_0
       1: aload_1
       2: iconst_1
       3: invokevirtual #111                // Method seekTo:(Lorg/apache/hadoop/hbase/Cell;Z)I
       6: ireturn

  public int reseekTo(org.apache.hadoop.hbase.Cell) throws java.io.IOException;
    Code:
       0: aload_0
       1: invokevirtual #42                 // Method isSeeked:()Z
       4: ifeq          82
       7: aload_0
       8: aload_0
       9: getfield      #15                 // Field reader:Lorg/apache/hadoop/hbase/io/hfile/HFile$Reader;
      12: invokeinterface #96,  1           // InterfaceMethod org/apache/hadoop/hbase/io/hfile/HFile$Reader.getComparator:()Lorg/apache/hadoop/hbase/CellComparator;
      17: aload_1
      18: invokevirtual #112                // Method compareKey:(Lorg/apache/hadoop/hbase/CellComparator;Lorg/apache/hadoop/hbase/Cell;)I
      21: istore_2
      22: iload_2
      23: iconst_1
      24: if_icmpge     29
      27: iload_2
      28: ireturn
      29: aload_0
      30: getfield      #110                // Field nextIndexedKey:Lorg/apache/hadoop/hbase/Cell;
      33: ifnull        82
      36: aload_0
      37: getfield      #110                // Field nextIndexedKey:Lorg/apache/hadoop/hbase/Cell;
      40: getstatic     #113                // Field org/apache/hadoop/hbase/regionserver/KeyValueScanner.NO_NEXT_INDEXED_KEY:Lorg/apache/hadoop/hbase/Cell;
      43: if_acmpeq     66
      46: aload_0
      47: getfield      #15                 // Field reader:Lorg/apache/hadoop/hbase/io/hfile/HFile$Reader;
      50: invokeinterface #96,  1           // InterfaceMethod org/apache/hadoop/hbase/io/hfile/HFile$Reader.getComparator:()Lorg/apache/hadoop/hbase/CellComparator;
      55: aload_1
      56: aload_0
      57: getfield      #110                // Field nextIndexedKey:Lorg/apache/hadoop/hbase/Cell;
      60: invokestatic  #97                 // Method org/apache/hadoop/hbase/PrivateCellUtil.compareKeyIgnoresMvcc:(Lorg/apache/hadoop/hbase/CellComparator;Lorg/apache/hadoop/hbase/Cell;Lorg/apache/hadoop/hbase/Cell;)I
      63: ifge          82
      66: aload_0
      67: aload_0
      68: getfield      #19                 // Field curBlock:Lorg/apache/hadoop/hbase/io/hfile/HFileBlock;
      71: aload_0
      72: getfield      #110                // Field nextIndexedKey:Lorg/apache/hadoop/hbase/Cell;
      75: iconst_0
      76: aload_1
      77: iconst_0
      78: invokevirtual #114                // Method loadBlockAndSeekToKey:(Lorg/apache/hadoop/hbase/io/hfile/HFileBlock;Lorg/apache/hadoop/hbase/Cell;ZLorg/apache/hadoop/hbase/Cell;Z)I
      81: ireturn
      82: aload_0
      83: aload_1
      84: iconst_0
      85: invokevirtual #111                // Method seekTo:(Lorg/apache/hadoop/hbase/Cell;Z)I
      88: ireturn

  public int seekTo(org.apache.hadoop.hbase.Cell, boolean) throws java.io.IOException;
    Code:
       0: aload_0
       1: getfield      #15                 // Field reader:Lorg/apache/hadoop/hbase/io/hfile/HFile$Reader;
       4: invokeinterface #115,  1          // InterfaceMethod org/apache/hadoop/hbase/io/hfile/HFile$Reader.getDataBlockIndexReader:()Lorg/apache/hadoop/hbase/io/hfile/HFileBlockIndex$BlockIndexReader;
       9: astore_3
      10: aload_3
      11: aload_1
      12: aload_0
      13: getfield      #19                 // Field curBlock:Lorg/apache/hadoop/hbase/io/hfile/HFileBlock;
      16: aload_0
      17: getfield      #16                 // Field cacheBlocks:Z
      20: aload_0
      21: getfield      #17                 // Field pread:Z
      24: aload_0
      25: getfield      #18                 // Field isCompaction:Z
      28: aload_0
      29: invokevirtual #116                // Method getEffectiveDataBlockEncoding:()Lorg/apache/hadoop/hbase/io/encoding/DataBlockEncoding;
      32: invokevirtual #117                // Method org/apache/hadoop/hbase/io/hfile/HFileBlockIndex$BlockIndexReader.loadDataBlockWithScanInfo:(Lorg/apache/hadoop/hbase/Cell;Lorg/apache/hadoop/hbase/io/hfile/HFileBlock;ZZZLorg/apache/hadoop/hbase/io/encoding/DataBlockEncoding;)Lorg/apache/hadoop/hbase/io/hfile/BlockWithScanInfo;
      35: astore        4
      37: aload         4
      39: ifnull        50
      42: aload         4
      44: invokevirtual #118                // Method org/apache/hadoop/hbase/io/hfile/BlockWithScanInfo.getHFileBlock:()Lorg/apache/hadoop/hbase/io/hfile/HFileBlock;
      47: ifnonnull     52
      50: iconst_m1
      51: ireturn
      52: aload_0
      53: aload         4
      55: invokevirtual #118                // Method org/apache/hadoop/hbase/io/hfile/BlockWithScanInfo.getHFileBlock:()Lorg/apache/hadoop/hbase/io/hfile/HFileBlock;
      58: aload         4
      60: invokevirtual #119                // Method org/apache/hadoop/hbase/io/hfile/BlockWithScanInfo.getNextIndexedKey:()Lorg/apache/hadoop/hbase/Cell;
      63: iload_2
      64: aload_1
      65: iconst_0
      66: invokevirtual #114                // Method loadBlockAndSeekToKey:(Lorg/apache/hadoop/hbase/io/hfile/HFileBlock;Lorg/apache/hadoop/hbase/Cell;ZLorg/apache/hadoop/hbase/Cell;Z)I
      69: ireturn

  public boolean seekBefore(org.apache.hadoop.hbase.Cell) throws java.io.IOException;
    Code:
       0: aload_0
       1: getfield      #15                 // Field reader:Lorg/apache/hadoop/hbase/io/hfile/HFile$Reader;
       4: invokeinterface #115,  1          // InterfaceMethod org/apache/hadoop/hbase/io/hfile/HFile$Reader.getDataBlockIndexReader:()Lorg/apache/hadoop/hbase/io/hfile/HFileBlockIndex$BlockIndexReader;
       9: aload_1
      10: aload_0
      11: getfield      #19                 // Field curBlock:Lorg/apache/hadoop/hbase/io/hfile/HFileBlock;
      14: aload_0
      15: getfield      #16                 // Field cacheBlocks:Z
      18: aload_0
      19: getfield      #17                 // Field pread:Z
      22: aload_0
      23: getfield      #18                 // Field isCompaction:Z
      26: aload_0
      27: getfield      #15                 // Field reader:Lorg/apache/hadoop/hbase/io/hfile/HFile$Reader;
      30: aload_0
      31: getfield      #18                 // Field isCompaction:Z
      34: invokeinterface #120,  2          // InterfaceMethod org/apache/hadoop/hbase/io/hfile/HFile$Reader.getEffectiveEncodingInCache:(Z)Lorg/apache/hadoop/hbase/io/encoding/DataBlockEncoding;
      39: invokevirtual #121                // Method org/apache/hadoop/hbase/io/hfile/HFileBlockIndex$BlockIndexReader.seekToDataBlock:(Lorg/apache/hadoop/hbase/Cell;Lorg/apache/hadoop/hbase/io/hfile/HFileBlock;ZZZLorg/apache/hadoop/hbase/io/encoding/DataBlockEncoding;)Lorg/apache/hadoop/hbase/io/hfile/HFileBlock;
      42: astore_2
      43: aload_2
      44: ifnonnull     49
      47: iconst_0
      48: ireturn
      49: aload_0
      50: aload_2
      51: invokevirtual #122                // Method getFirstKeyCellInBlock:(Lorg/apache/hadoop/hbase/io/hfile/HFileBlock;)Lorg/apache/hadoop/hbase/Cell;
      54: astore_3
      55: aload_0
      56: getfield      #15                 // Field reader:Lorg/apache/hadoop/hbase/io/hfile/HFile$Reader;
      59: invokeinterface #96,  1           // InterfaceMethod org/apache/hadoop/hbase/io/hfile/HFile$Reader.getComparator:()Lorg/apache/hadoop/hbase/CellComparator;
      64: aload_3
      65: aload_1
      66: invokestatic  #97                 // Method org/apache/hadoop/hbase/PrivateCellUtil.compareKeyIgnoresMvcc:(Lorg/apache/hadoop/hbase/CellComparator;Lorg/apache/hadoop/hbase/Cell;Lorg/apache/hadoop/hbase/Cell;)I
      69: iflt          137
      72: aload_2
      73: invokevirtual #123                // Method org/apache/hadoop/hbase/io/hfile/HFileBlock.getPrevBlockOffset:()J
      76: lstore        4
      78: lload         4
      80: ldc2_w        #86                 // long -1l
      83: lcmp
      84: ifne          89
      87: iconst_0
      88: ireturn
      89: aload_0
      90: getfield      #15                 // Field reader:Lorg/apache/hadoop/hbase/io/hfile/HFile$Reader;
      93: aload_2
      94: invokeinterface #32,  2           // InterfaceMethod org/apache/hadoop/hbase/io/hfile/HFile$Reader.returnBlock:(Lorg/apache/hadoop/hbase/io/hfile/HFileBlock;)V
      99: iconst_m1
     100: istore        6
     102: aload_0
     103: getfield      #15                 // Field reader:Lorg/apache/hadoop/hbase/io/hfile/HFile$Reader;
     106: lload         4
     108: iload         6
     110: i2l
     111: aload_0
     112: getfield      #16                 // Field cacheBlocks:Z
     115: aload_0
     116: getfield      #17                 // Field pread:Z
     119: aload_0
     120: getfield      #18                 // Field isCompaction:Z
     123: iconst_1
     124: getstatic     #124                // Field org/apache/hadoop/hbase/io/hfile/BlockType.DATA:Lorg/apache/hadoop/hbase/io/hfile/BlockType;
     127: aload_0
     128: invokevirtual #116                // Method getEffectiveDataBlockEncoding:()Lorg/apache/hadoop/hbase/io/encoding/DataBlockEncoding;
     131: invokeinterface #125,  11         // InterfaceMethod org/apache/hadoop/hbase/io/hfile/HFile$Reader.readBlock:(JJZZZZLorg/apache/hadoop/hbase/io/hfile/BlockType;Lorg/apache/hadoop/hbase/io/encoding/DataBlockEncoding;)Lorg/apache/hadoop/hbase/io/hfile/HFileBlock;
     136: astore_2
     137: aload_0
     138: aload_2
     139: aload_3
     140: iconst_1
     141: aload_1
     142: iconst_1
     143: invokevirtual #114                // Method loadBlockAndSeekToKey:(Lorg/apache/hadoop/hbase/io/hfile/HFileBlock;Lorg/apache/hadoop/hbase/Cell;ZLorg/apache/hadoop/hbase/Cell;Z)I
     146: pop
     147: iconst_1
     148: ireturn

  protected org.apache.hadoop.hbase.io.hfile.HFileBlock readNextDataBlock() throws java.io.IOException;
    Code:
       0: aload_0
       1: getfield      #15                 // Field reader:Lorg/apache/hadoop/hbase/io/hfile/HFile$Reader;
       4: invokeinterface #126,  1          // InterfaceMethod org/apache/hadoop/hbase/io/hfile/HFile$Reader.getTrailer:()Lorg/apache/hadoop/hbase/io/hfile/FixedFileTrailer;
       9: invokevirtual #127                // Method org/apache/hadoop/hbase/io/hfile/FixedFileTrailer.getLastDataBlockOffset:()J
      12: lstore_1
      13: aload_0
      14: getfield      #19                 // Field curBlock:Lorg/apache/hadoop/hbase/io/hfile/HFileBlock;
      17: ifnonnull     22
      20: aconst_null
      21: areturn
      22: aload_0
      23: getfield      #19                 // Field curBlock:Lorg/apache/hadoop/hbase/io/hfile/HFileBlock;
      26: astore_3
      27: aload_3
      28: invokevirtual #20                 // Method org/apache/hadoop/hbase/io/hfile/HFileBlock.getOffset:()J
      31: lload_1
      32: lcmp
      33: iflt          38
      36: aconst_null
      37: areturn
      38: aload_3
      39: invokevirtual #20                 // Method org/apache/hadoop/hbase/io/hfile/HFileBlock.getOffset:()J
      42: lconst_0
      43: lcmp
      44: ifge          91
      47: new           #128                // class java/io/IOException
      50: dup
      51: new           #25                 // class java/lang/StringBuilder
      54: dup
      55: invokespecial #26                 // Method java/lang/StringBuilder."<init>":()V
      58: ldc           #129                // String Invalid block file offset:
      60: invokevirtual #28                 // Method java/lang/StringBuilder.append:(Ljava/lang/String;)Ljava/lang/StringBuilder;
      63: aload_3
      64: invokevirtual #29                 // Method java/lang/StringBuilder.append:(Ljava/lang/Object;)Ljava/lang/StringBuilder;
      67: ldc           #104                // String , path=
      69: invokevirtual #28                 // Method java/lang/StringBuilder.append:(Ljava/lang/String;)Ljava/lang/StringBuilder;
      72: aload_0
      73: getfield      #15                 // Field reader:Lorg/apache/hadoop/hbase/io/hfile/HFile$Reader;
      76: invokeinterface #44,  1           // InterfaceMethod org/apache/hadoop/hbase/io/hfile/HFile$Reader.getPath:()Lorg/apache/hadoop/fs/Path;
      81: invokevirtual #29                 // Method java/lang/StringBuilder.append:(Ljava/lang/Object;)Ljava/lang/StringBuilder;
      84: invokevirtual #30                 // Method java/lang/StringBuilder.toString:()Ljava/lang/String;
      87: invokespecial #130                // Method java/io/IOException."<init>":(Ljava/lang/String;)V
      90: athrow
      91: aload_0
      92: getfield      #15                 // Field reader:Lorg/apache/hadoop/hbase/io/hfile/HFile$Reader;
      95: aload_3
      96: invokevirtual #20                 // Method org/apache/hadoop/hbase/io/hfile/HFileBlock.getOffset:()J
      99: aload_3
     100: invokevirtual #103                // Method org/apache/hadoop/hbase/io/hfile/HFileBlock.getOnDiskSizeWithHeader:()I
     103: i2l
     104: ladd
     105: aload_3
     106: invokevirtual #131                // Method org/apache/hadoop/hbase/io/hfile/HFileBlock.getNextBlockOnDiskSize:()I
     109: i2l
     110: aload_0
     111: getfield      #16                 // Field cacheBlocks:Z
     114: aload_0
     115: getfield      #17                 // Field pread:Z
     118: aload_0
     119: getfield      #18                 // Field isCompaction:Z
     122: iconst_1
     123: aconst_null
     124: aload_0
     125: invokevirtual #116                // Method getEffectiveDataBlockEncoding:()Lorg/apache/hadoop/hbase/io/encoding/DataBlockEncoding;
     128: invokeinterface #125,  11         // InterfaceMethod org/apache/hadoop/hbase/io/hfile/HFile$Reader.readBlock:(JJZZZZLorg/apache/hadoop/hbase/io/hfile/BlockType;Lorg/apache/hadoop/hbase/io/encoding/DataBlockEncoding;)Lorg/apache/hadoop/hbase/io/hfile/HFileBlock;
     133: astore_3
     134: aload_3
     135: ifnull        158
     138: aload_3
     139: invokevirtual #132                // Method org/apache/hadoop/hbase/io/hfile/HFileBlock.getBlockType:()Lorg/apache/hadoop/hbase/io/hfile/BlockType;
     142: invokevirtual #133                // Method org/apache/hadoop/hbase/io/hfile/BlockType.isData:()Z
     145: ifne          158
     148: aload_0
     149: getfield      #15                 // Field reader:Lorg/apache/hadoop/hbase/io/hfile/HFile$Reader;
     152: aload_3
     153: invokeinterface #32,  2           // InterfaceMethod org/apache/hadoop/hbase/io/hfile/HFile$Reader.returnBlock:(Lorg/apache/hadoop/hbase/io/hfile/HFileBlock;)V
     158: aload_3
     159: invokevirtual #132                // Method org/apache/hadoop/hbase/io/hfile/HFileBlock.getBlockType:()Lorg/apache/hadoop/hbase/io/hfile/BlockType;
     162: invokevirtual #133                // Method org/apache/hadoop/hbase/io/hfile/BlockType.isData:()Z
     165: ifeq          27
     168: aload_3
     169: areturn

  public org.apache.hadoop.hbase.io.encoding.DataBlockEncoding getEffectiveDataBlockEncoding();
    Code:
       0: aload_0
       1: getfield      #15                 // Field reader:Lorg/apache/hadoop/hbase/io/hfile/HFile$Reader;
       4: aload_0
       5: getfield      #18                 // Field isCompaction:Z
       8: invokeinterface #120,  2          // InterfaceMethod org/apache/hadoop/hbase/io/hfile/HFile$Reader.getEffectiveEncodingInCache:(Z)Lorg/apache/hadoop/hbase/io/encoding/DataBlockEncoding;
      13: areturn

  public org.apache.hadoop.hbase.Cell getCell();
    Code:
       0: aload_0
       1: invokevirtual #42                 // Method isSeeked:()Z
       4: ifne          9
       7: aconst_null
       8: areturn
       9: aload_0
      10: invokespecial #134                // Method getKVBufSize:()I
      13: istore_2
      14: lconst_0
      15: lstore_3
      16: aload_0
      17: getfield      #15                 // Field reader:Lorg/apache/hadoop/hbase/io/hfile/HFile$Reader;
      20: invokeinterface #75,  1           // InterfaceMethod org/apache/hadoop/hbase/io/hfile/HFile$Reader.shouldIncludeMemStoreTS:()Z
      25: ifeq          33
      28: aload_0
      29: getfield      #77                 // Field currMemstoreTS:J
      32: lstore_3
      33: aload_0
      34: getfield      #38                 // Field blockBuffer:Lorg/apache/hadoop/hbase/nio/ByteBuff;
      37: invokevirtual #135                // Method org/apache/hadoop/hbase/nio/ByteBuff.hasArray:()Z
      40: ifeq          120
      43: aload_0
      44: getfield      #48                 // Field currTagsLen:I
      47: ifle          85
      50: new           #136                // class org/apache/hadoop/hbase/SizeCachedKeyValue
      53: dup
      54: aload_0
      55: getfield      #38                 // Field blockBuffer:Lorg/apache/hadoop/hbase/nio/ByteBuff;
      58: invokevirtual #137                // Method org/apache/hadoop/hbase/nio/ByteBuff.array:()[B
      61: aload_0
      62: getfield      #38                 // Field blockBuffer:Lorg/apache/hadoop/hbase/nio/ByteBuff;
      65: invokevirtual #138                // Method org/apache/hadoop/hbase/nio/ByteBuff.arrayOffset:()I
      68: aload_0
      69: getfield      #38                 // Field blockBuffer:Lorg/apache/hadoop/hbase/nio/ByteBuff;
      72: invokevirtual #72                 // Method org/apache/hadoop/hbase/nio/ByteBuff.position:()I
      75: iadd
      76: iload_2
      77: lload_3
      78: invokespecial #139                // Method org/apache/hadoop/hbase/SizeCachedKeyValue."<init>":([BIIJ)V
      81: astore_1
      82: goto          246
      85: new           #140                // class org/apache/hadoop/hbase/SizeCachedNoTagsKeyValue
      88: dup
      89: aload_0
      90: getfield      #38                 // Field blockBuffer:Lorg/apache/hadoop/hbase/nio/ByteBuff;
      93: invokevirtual #137                // Method org/apache/hadoop/hbase/nio/ByteBuff.array:()[B
      96: aload_0
      97: getfield      #38                 // Field blockBuffer:Lorg/apache/hadoop/hbase/nio/ByteBuff;
     100: invokevirtual #138                // Method org/apache/hadoop/hbase/nio/ByteBuff.arrayOffset:()I
     103: aload_0
     104: getfield      #38                 // Field blockBuffer:Lorg/apache/hadoop/hbase/nio/ByteBuff;
     107: invokevirtual #72                 // Method org/apache/hadoop/hbase/nio/ByteBuff.position:()I
     110: iadd
     111: iload_2
     112: lload_3
     113: invokespecial #141                // Method org/apache/hadoop/hbase/SizeCachedNoTagsKeyValue."<init>":([BIIJ)V
     116: astore_1
     117: goto          246
     120: aload_0
     121: getfield      #38                 // Field blockBuffer:Lorg/apache/hadoop/hbase/nio/ByteBuff;
     124: iload_2
     125: invokevirtual #142                // Method org/apache/hadoop/hbase/nio/ByteBuff.asSubByteBuffer:(I)Ljava/nio/ByteBuffer;
     128: astore        5
     130: aload         5
     132: invokevirtual #143                // Method java/nio/ByteBuffer.isDirect:()Z
     135: ifeq          184
     138: aload_0
     139: getfield      #48                 // Field currTagsLen:I
     142: ifle          164
     145: new           #144                // class org/apache/hadoop/hbase/ByteBufferKeyValue
     148: dup
     149: aload         5
     151: aload         5
     153: invokevirtual #145                // Method java/nio/ByteBuffer.position:()I
     156: iload_2
     157: lload_3
     158: invokespecial #146                // Method org/apache/hadoop/hbase/ByteBufferKeyValue."<init>":(Ljava/nio/ByteBuffer;IIJ)V
     161: goto          180
     164: new           #147                // class org/apache/hadoop/hbase/NoTagsByteBufferKeyValue
     167: dup
     168: aload         5
     170: aload         5
     172: invokevirtual #145                // Method java/nio/ByteBuffer.position:()I
     175: iload_2
     176: lload_3
     177: invokespecial #148                // Method org/apache/hadoop/hbase/NoTagsByteBufferKeyValue."<init>":(Ljava/nio/ByteBuffer;IIJ)V
     180: astore_1
     181: goto          246
     184: aload_0
     185: getfield      #48                 // Field currTagsLen:I
     188: ifle          220
     191: new           #136                // class org/apache/hadoop/hbase/SizeCachedKeyValue
     194: dup
     195: aload         5
     197: invokevirtual #149                // Method java/nio/ByteBuffer.array:()[B
     200: aload         5
     202: invokevirtual #150                // Method java/nio/ByteBuffer.arrayOffset:()I
     205: aload         5
     207: invokevirtual #145                // Method java/nio/ByteBuffer.position:()I
     210: iadd
     211: iload_2
     212: lload_3
     213: invokespecial #139                // Method org/apache/hadoop/hbase/SizeCachedKeyValue."<init>":([BIIJ)V
     216: astore_1
     217: goto          246
     220: new           #140                // class org/apache/hadoop/hbase/SizeCachedNoTagsKeyValue
     223: dup
     224: aload         5
     226: invokevirtual #149                // Method java/nio/ByteBuffer.array:()[B
     229: aload         5
     231: invokevirtual #150                // Method java/nio/ByteBuffer.arrayOffset:()I
     234: aload         5
     236: invokevirtual #145                // Method java/nio/ByteBuffer.position:()I
     239: iadd
     240: iload_2
     241: lload_3
     242: invokespecial #141                // Method org/apache/hadoop/hbase/SizeCachedNoTagsKeyValue."<init>":([BIIJ)V
     245: astore_1
     246: aload_1
     247: areturn

  public org.apache.hadoop.hbase.Cell getKey();
    Code:
       0: aload_0
       1: invokevirtual #151                // Method assertSeeked:()V
       4: new           #9                  // class org/apache/hadoop/hbase/util/ObjectIntPair
       7: dup
       8: invokespecial #10                 // Method org/apache/hadoop/hbase/util/ObjectIntPair."<init>":()V
      11: astore_1
      12: aload_0
      13: getfield      #38                 // Field blockBuffer:Lorg/apache/hadoop/hbase/nio/ByteBuff;
      16: aload_0
      17: getfield      #38                 // Field blockBuffer:Lorg/apache/hadoop/hbase/nio/ByteBuff;
      20: invokevirtual #72                 // Method org/apache/hadoop/hbase/nio/ByteBuff.position:()I
      23: bipush        8
      25: iadd
      26: aload_0
      27: getfield      #46                 // Field currKeyLen:I
      30: aload_1
      31: invokevirtual #91                 // Method org/apache/hadoop/hbase/nio/ByteBuff.asSubByteBuffer:(IILorg/apache/hadoop/hbase/util/ObjectIntPair;)V
      34: aload_1
      35: invokevirtual #92                 // Method org/apache/hadoop/hbase/util/ObjectIntPair.getFirst:()Ljava/lang/Object;
      38: checkcast     #93                 // class java/nio/ByteBuffer
      41: astore_2
      42: aload_2
      43: invokevirtual #152                // Method java/nio/ByteBuffer.hasArray:()Z
      46: ifeq          74
      49: new           #153                // class org/apache/hadoop/hbase/KeyValue$KeyOnlyKeyValue
      52: dup
      53: aload_2
      54: invokevirtual #149                // Method java/nio/ByteBuffer.array:()[B
      57: aload_2
      58: invokevirtual #150                // Method java/nio/ByteBuffer.arrayOffset:()I
      61: aload_1
      62: invokevirtual #94                 // Method org/apache/hadoop/hbase/util/ObjectIntPair.getSecond:()I
      65: iadd
      66: aload_0
      67: getfield      #46                 // Field currKeyLen:I
      70: invokespecial #154                // Method org/apache/hadoop/hbase/KeyValue$KeyOnlyKeyValue."<init>":([BII)V
      73: areturn
      74: aload_0
      75: getfield      #46                 // Field currKeyLen:I
      78: newarray       byte
      80: astore_3
      81: aload_3
      82: aload_2
      83: aload_1
      84: invokevirtual #94                 // Method org/apache/hadoop/hbase/util/ObjectIntPair.getSecond:()I
      87: iconst_0
      88: aload_0
      89: getfield      #46                 // Field currKeyLen:I
      92: invokestatic  #155                // Method org/apache/hadoop/hbase/util/ByteBufferUtils.copyFromBufferToArray:([BLjava/nio/ByteBuffer;III)V
      95: new           #153                // class org/apache/hadoop/hbase/KeyValue$KeyOnlyKeyValue
      98: dup
      99: aload_3
     100: iconst_0
     101: aload_0
     102: getfield      #46                 // Field currKeyLen:I
     105: invokespecial #154                // Method org/apache/hadoop/hbase/KeyValue$KeyOnlyKeyValue."<init>":([BII)V
     108: areturn

  public java.nio.ByteBuffer getValue();
    Code:
       0: aload_0
       1: invokevirtual #151                // Method assertSeeked:()V
       4: new           #9                  // class org/apache/hadoop/hbase/util/ObjectIntPair
       7: dup
       8: invokespecial #10                 // Method org/apache/hadoop/hbase/util/ObjectIntPair."<init>":()V
      11: astore_1
      12: aload_0
      13: getfield      #38                 // Field blockBuffer:Lorg/apache/hadoop/hbase/nio/ByteBuff;
      16: aload_0
      17: getfield      #38                 // Field blockBuffer:Lorg/apache/hadoop/hbase/nio/ByteBuff;
      20: invokevirtual #72                 // Method org/apache/hadoop/hbase/nio/ByteBuff.position:()I
      23: bipush        8
      25: iadd
      26: aload_0
      27: getfield      #46                 // Field currKeyLen:I
      30: iadd
      31: aload_0
      32: getfield      #47                 // Field currValueLen:I
      35: aload_1
      36: invokevirtual #91                 // Method org/apache/hadoop/hbase/nio/ByteBuff.asSubByteBuffer:(IILorg/apache/hadoop/hbase/util/ObjectIntPair;)V
      39: aload_1
      40: invokevirtual #92                 // Method org/apache/hadoop/hbase/util/ObjectIntPair.getFirst:()Ljava/lang/Object;
      43: checkcast     #93                 // class java/nio/ByteBuffer
      46: invokevirtual #156                // Method java/nio/ByteBuffer.duplicate:()Ljava/nio/ByteBuffer;
      49: astore_2
      50: aload_2
      51: aload_1
      52: invokevirtual #94                 // Method org/apache/hadoop/hbase/util/ObjectIntPair.getSecond:()I
      55: invokevirtual #157                // Method java/nio/ByteBuffer.position:(I)Ljava/nio/Buffer;
      58: pop
      59: aload_2
      60: aload_0
      61: getfield      #47                 // Field currValueLen:I
      64: aload_1
      65: invokevirtual #94                 // Method org/apache/hadoop/hbase/util/ObjectIntPair.getSecond:()I
      68: iadd
      69: invokevirtual #158                // Method java/nio/ByteBuffer.limit:(I)Ljava/nio/Buffer;
      72: pop
      73: aload_2
      74: invokevirtual #159                // Method java/nio/ByteBuffer.slice:()Ljava/nio/ByteBuffer;
      77: areturn

  protected void setNonSeekedState();
    Code:
       0: aload_0
       1: invokevirtual #160                // Method reset:()V
       4: aload_0
       5: aconst_null
       6: putfield      #38                 // Field blockBuffer:Lorg/apache/hadoop/hbase/nio/ByteBuff;
       9: aload_0
      10: iconst_0
      11: putfield      #46                 // Field currKeyLen:I
      14: aload_0
      15: iconst_0
      16: putfield      #47                 // Field currValueLen:I
      19: aload_0
      20: lconst_0
      21: putfield      #77                 // Field currMemstoreTS:J
      24: aload_0
      25: iconst_0
      26: putfield      #52                 // Field currMemstoreTSLen:I
      29: aload_0
      30: iconst_0
      31: putfield      #48                 // Field currTagsLen:I
      34: return

  public boolean next() throws java.io.IOException;
    Code:
       0: aload_0
       1: invokevirtual #151                // Method assertSeeked:()V
       4: aload_0
       5: invokespecial #176                // Method positionThisBlockBuffer:()V
       8: aload_0
       9: invokespecial #177                // Method _next:()Z
      12: ireturn

  public boolean seekTo() throws java.io.IOException;
    Code:
       0: aload_0
       1: getfield      #15                 // Field reader:Lorg/apache/hadoop/hbase/io/hfile/HFile$Reader;
       4: ifnonnull     9
       7: iconst_0
       8: ireturn
       9: aload_0
      10: getfield      #15                 // Field reader:Lorg/apache/hadoop/hbase/io/hfile/HFile$Reader;
      13: invokeinterface #126,  1          // InterfaceMethod org/apache/hadoop/hbase/io/hfile/HFile$Reader.getTrailer:()Lorg/apache/hadoop/hbase/io/hfile/FixedFileTrailer;
      18: invokevirtual #178                // Method org/apache/hadoop/hbase/io/hfile/FixedFileTrailer.getEntryCount:()J
      21: lconst_0
      22: lcmp
      23: ifne          28
      26: iconst_0
      27: ireturn
      28: aload_0
      29: getfield      #15                 // Field reader:Lorg/apache/hadoop/hbase/io/hfile/HFile$Reader;
      32: invokeinterface #126,  1          // InterfaceMethod org/apache/hadoop/hbase/io/hfile/HFile$Reader.getTrailer:()Lorg/apache/hadoop/hbase/io/hfile/FixedFileTrailer;
      37: invokevirtual #179                // Method org/apache/hadoop/hbase/io/hfile/FixedFileTrailer.getFirstDataBlockOffset:()J
      40: lstore_1
      41: aload_0
      42: getfield      #19                 // Field curBlock:Lorg/apache/hadoop/hbase/io/hfile/HFileBlock;
      45: ifnull        65
      48: aload_0
      49: getfield      #19                 // Field curBlock:Lorg/apache/hadoop/hbase/io/hfile/HFileBlock;
      52: invokevirtual #20                 // Method org/apache/hadoop/hbase/io/hfile/HFileBlock.getOffset:()J
      55: lload_1
      56: lcmp
      57: ifne          65
      60: aload_0
      61: invokevirtual #180                // Method processFirstDataBlock:()Z
      64: ireturn
      65: aload_0
      66: lload_1
      67: invokevirtual #181                // Method readAndUpdateNewBlock:(J)V
      70: iconst_1
      71: ireturn

  protected boolean processFirstDataBlock() throws java.io.IOException;
    Code:
       0: aload_0
       1: getfield      #38                 // Field blockBuffer:Lorg/apache/hadoop/hbase/nio/ByteBuff;
       4: invokevirtual #182                // Method org/apache/hadoop/hbase/nio/ByteBuff.rewind:()Lorg/apache/hadoop/hbase/nio/ByteBuff;
       7: pop
       8: aload_0
       9: invokevirtual #106                // Method readKeyValueLen:()V
      12: iconst_1
      13: ireturn

  protected void readAndUpdateNewBlock(long) throws java.io.IOException, org.apache.hadoop.hbase.io.hfile.CorruptHFileException;
    Code:
       0: aload_0
       1: getfield      #15                 // Field reader:Lorg/apache/hadoop/hbase/io/hfile/HFile$Reader;
       4: lload_1
       5: ldc2_w        #86                 // long -1l
       8: aload_0
       9: getfield      #16                 // Field cacheBlocks:Z
      12: aload_0
      13: getfield      #17                 // Field pread:Z
      16: aload_0
      17: getfield      #18                 // Field isCompaction:Z
      20: iconst_1
      21: getstatic     #124                // Field org/apache/hadoop/hbase/io/hfile/BlockType.DATA:Lorg/apache/hadoop/hbase/io/hfile/BlockType;
      24: aload_0
      25: invokevirtual #116                // Method getEffectiveDataBlockEncoding:()Lorg/apache/hadoop/hbase/io/encoding/DataBlockEncoding;
      28: invokeinterface #125,  11         // InterfaceMethod org/apache/hadoop/hbase/io/hfile/HFile$Reader.readBlock:(JJZZZZLorg/apache/hadoop/hbase/io/hfile/BlockType;Lorg/apache/hadoop/hbase/io/encoding/DataBlockEncoding;)Lorg/apache/hadoop/hbase/io/hfile/HFileBlock;
      33: astore_3
      34: aload_3
      35: invokevirtual #20                 // Method org/apache/hadoop/hbase/io/hfile/HFileBlock.getOffset:()J
      38: lconst_0
      39: lcmp
      40: ifge          90
      43: new           #128                // class java/io/IOException
      46: dup
      47: new           #25                 // class java/lang/StringBuilder
      50: dup
      51: invokespecial #26                 // Method java/lang/StringBuilder."<init>":()V
      54: ldc           #183                // String Invalid block offset:
      56: invokevirtual #28                 // Method java/lang/StringBuilder.append:(Ljava/lang/String;)Ljava/lang/StringBuilder;
      59: aload_3
      60: invokevirtual #20                 // Method org/apache/hadoop/hbase/io/hfile/HFileBlock.getOffset:()J
      63: invokevirtual #68                 // Method java/lang/StringBuilder.append:(J)Ljava/lang/StringBuilder;
      66: ldc           #104                // String , path=
      68: invokevirtual #28                 // Method java/lang/StringBuilder.append:(Ljava/lang/String;)Ljava/lang/StringBuilder;
      71: aload_0
      72: getfield      #15                 // Field reader:Lorg/apache/hadoop/hbase/io/hfile/HFile$Reader;
      75: invokeinterface #44,  1           // InterfaceMethod org/apache/hadoop/hbase/io/hfile/HFile$Reader.getPath:()Lorg/apache/hadoop/fs/Path;
      80: invokevirtual #29                 // Method java/lang/StringBuilder.append:(Ljava/lang/Object;)Ljava/lang/StringBuilder;
      83: invokevirtual #30                 // Method java/lang/StringBuilder.toString:()Ljava/lang/String;
      86: invokespecial #130                // Method java/io/IOException."<init>":(Ljava/lang/String;)V
      89: athrow
      90: aload_0
      91: aload_3
      92: invokevirtual #173                // Method updateCurrentBlock:(Lorg/apache/hadoop/hbase/io/hfile/HFileBlock;)V
      95: return

  protected int loadBlockAndSeekToKey(org.apache.hadoop.hbase.io.hfile.HFileBlock, org.apache.hadoop.hbase.Cell, boolean, org.apache.hadoop.hbase.Cell, boolean) throws java.io.IOException;
    Code:
       0: aload_0
       1: getfield      #19                 // Field curBlock:Lorg/apache/hadoop/hbase/io/hfile/HFileBlock;
       4: ifnull        22
       7: aload_0
       8: getfield      #19                 // Field curBlock:Lorg/apache/hadoop/hbase/io/hfile/HFileBlock;
      11: invokevirtual #20                 // Method org/apache/hadoop/hbase/io/hfile/HFileBlock.getOffset:()J
      14: aload_1
      15: invokevirtual #20                 // Method org/apache/hadoop/hbase/io/hfile/HFileBlock.getOffset:()J
      18: lcmp
      19: ifeq          30
      22: aload_0
      23: aload_1
      24: invokevirtual #173                // Method updateCurrentBlock:(Lorg/apache/hadoop/hbase/io/hfile/HFileBlock;)V
      27: goto          42
      30: iload_3
      31: ifeq          42
      34: aload_0
      35: getfield      #38                 // Field blockBuffer:Lorg/apache/hadoop/hbase/nio/ByteBuff;
      38: invokevirtual #182                // Method org/apache/hadoop/hbase/nio/ByteBuff.rewind:()Lorg/apache/hadoop/hbase/nio/ByteBuff;
      41: pop
      42: aload_0
      43: aload_2
      44: putfield      #110                // Field nextIndexedKey:Lorg/apache/hadoop/hbase/Cell;
      47: aload_0
      48: aload         4
      50: iload         5
      52: invokevirtual #184                // Method blockSeek:(Lorg/apache/hadoop/hbase/Cell;Z)I
      55: ireturn

  protected final boolean checkKeyLen(int);
    Code:
       0: iload_1
       1: ifle          15
       4: iload_1
       5: aload_0
       6: getfield      #38                 // Field blockBuffer:Lorg/apache/hadoop/hbase/nio/ByteBuff;
       9: invokevirtual #70                 // Method org/apache/hadoop/hbase/nio/ByteBuff.limit:()I
      12: if_icmple     19
      15: iconst_1
      16: goto          20
      19: iconst_0
      20: ireturn

  protected final boolean checkLen(int);
    Code:
       0: iload_1
       1: iflt          15
       4: iload_1
       5: aload_0
       6: getfield      #38                 // Field blockBuffer:Lorg/apache/hadoop/hbase/nio/ByteBuff;
       9: invokevirtual #70                 // Method org/apache/hadoop/hbase/nio/ByteBuff.limit:()I
      12: if_icmple     19
      15: iconst_1
      16: goto          20
      19: iconst_0
      20: ireturn

  protected final void checkKeyValueLen();
    Code:
       0: aload_0
       1: aload_0
       2: getfield      #46                 // Field currKeyLen:I
       5: invokevirtual #88                 // Method checkKeyLen:(I)Z
       8: ifne          22
      11: aload_0
      12: aload_0
      13: getfield      #47                 // Field currValueLen:I
      16: invokevirtual #63                 // Method checkLen:(I)Z
      19: ifeq          126
      22: new           #64                 // class java/lang/IllegalStateException
      25: dup
      26: new           #25                 // class java/lang/StringBuilder
      29: dup
      30: invokespecial #26                 // Method java/lang/StringBuilder."<init>":()V
      33: ldc           #185                // String Invalid currKeyLen
      35: invokevirtual #28                 // Method java/lang/StringBuilder.append:(Ljava/lang/String;)Ljava/lang/StringBuilder;
      38: aload_0
      39: getfield      #46                 // Field currKeyLen:I
      42: invokevirtual #66                 // Method java/lang/StringBuilder.append:(I)Ljava/lang/StringBuilder;
      45: ldc           #186                // String  or currValueLen
      47: invokevirtual #28                 // Method java/lang/StringBuilder.append:(Ljava/lang/String;)Ljava/lang/StringBuilder;
      50: aload_0
      51: getfield      #47                 // Field currValueLen:I
      54: invokevirtual #66                 // Method java/lang/StringBuilder.append:(I)Ljava/lang/StringBuilder;
      57: ldc           #67                 // String . Block offset:
      59: invokevirtual #28                 // Method java/lang/StringBuilder.append:(Ljava/lang/String;)Ljava/lang/StringBuilder;
      62: aload_0
      63: getfield      #19                 // Field curBlock:Lorg/apache/hadoop/hbase/io/hfile/HFileBlock;
      66: invokevirtual #20                 // Method org/apache/hadoop/hbase/io/hfile/HFileBlock.getOffset:()J
      69: invokevirtual #68                 // Method java/lang/StringBuilder.append:(J)Ljava/lang/StringBuilder;
      72: ldc           #69                 // String , block length:
      74: invokevirtual #28                 // Method java/lang/StringBuilder.append:(Ljava/lang/String;)Ljava/lang/StringBuilder;
      77: aload_0
      78: getfield      #38                 // Field blockBuffer:Lorg/apache/hadoop/hbase/nio/ByteBuff;
      81: invokevirtual #70                 // Method org/apache/hadoop/hbase/nio/ByteBuff.limit:()I
      84: invokevirtual #66                 // Method java/lang/StringBuilder.append:(I)Ljava/lang/StringBuilder;
      87: ldc           #71                 // String , position:
      89: invokevirtual #28                 // Method java/lang/StringBuilder.append:(Ljava/lang/String;)Ljava/lang/StringBuilder;
      92: aload_0
      93: getfield      #38                 // Field blockBuffer:Lorg/apache/hadoop/hbase/nio/ByteBuff;
      96: invokevirtual #72                 // Method org/apache/hadoop/hbase/nio/ByteBuff.position:()I
      99: invokevirtual #66                 // Method java/lang/StringBuilder.append:(I)Ljava/lang/StringBuilder;
     102: ldc           #187                // String  (without header)., path=
     104: invokevirtual #28                 // Method java/lang/StringBuilder.append:(Ljava/lang/String;)Ljava/lang/StringBuilder;
     107: aload_0
     108: getfield      #15                 // Field reader:Lorg/apache/hadoop/hbase/io/hfile/HFile$Reader;
     111: invokeinterface #44,  1           // InterfaceMethod org/apache/hadoop/hbase/io/hfile/HFile$Reader.getPath:()Lorg/apache/hadoop/fs/Path;
     116: invokevirtual #29                 // Method java/lang/StringBuilder.append:(Ljava/lang/Object;)Ljava/lang/StringBuilder;
     119: invokevirtual #30                 // Method java/lang/StringBuilder.toString:()Ljava/lang/String;
     122: invokespecial #74                 // Method java/lang/IllegalStateException."<init>":(Ljava/lang/String;)V
     125: athrow
     126: return

  protected void updateCurrentBlock(org.apache.hadoop.hbase.io.hfile.HFileBlock) throws java.io.IOException;
    Code:
       0: aload_1
       1: invokevirtual #132                // Method org/apache/hadoop/hbase/io/hfile/HFileBlock.getBlockType:()Lorg/apache/hadoop/hbase/io/hfile/BlockType;
       4: getstatic     #124                // Field org/apache/hadoop/hbase/io/hfile/BlockType.DATA:Lorg/apache/hadoop/hbase/io/hfile/BlockType;
       7: if_acmpeq     86
      10: new           #64                 // class java/lang/IllegalStateException
      13: dup
      14: new           #25                 // class java/lang/StringBuilder
      17: dup
      18: invokespecial #26                 // Method java/lang/StringBuilder."<init>":()V
      21: ldc           #188                // String ScannerV2 works only on data blocks, got
      23: invokevirtual #28                 // Method java/lang/StringBuilder.append:(Ljava/lang/String;)Ljava/lang/StringBuilder;
      26: aload_1
      27: invokevirtual #132                // Method org/apache/hadoop/hbase/io/hfile/HFileBlock.getBlockType:()Lorg/apache/hadoop/hbase/io/hfile/BlockType;
      30: invokevirtual #29                 // Method java/lang/StringBuilder.append:(Ljava/lang/Object;)Ljava/lang/StringBuilder;
      33: ldc           #189                // String ; HFileName=
      35: invokevirtual #28                 // Method java/lang/StringBuilder.append:(Ljava/lang/String;)Ljava/lang/StringBuilder;
      38: aload_0
      39: getfield      #15                 // Field reader:Lorg/apache/hadoop/hbase/io/hfile/HFile$Reader;
      42: invokeinterface #44,  1           // InterfaceMethod org/apache/hadoop/hbase/io/hfile/HFile$Reader.getPath:()Lorg/apache/hadoop/fs/Path;
      47: invokevirtual #29                 // Method java/lang/StringBuilder.append:(Ljava/lang/Object;)Ljava/lang/StringBuilder;
      50: ldc           #190                // String , dataBlockEncoder=
      52: invokevirtual #28                 // Method java/lang/StringBuilder.append:(Ljava/lang/String;)Ljava/lang/StringBuilder;
      55: aload_0
      56: getfield      #15                 // Field reader:Lorg/apache/hadoop/hbase/io/hfile/HFile$Reader;
      59: invokeinterface #191,  1          // InterfaceMethod org/apache/hadoop/hbase/io/hfile/HFile$Reader.getDataBlockEncoding:()Lorg/apache/hadoop/hbase/io/encoding/DataBlockEncoding;
      64: invokevirtual #29                 // Method java/lang/StringBuilder.append:(Ljava/lang/Object;)Ljava/lang/StringBuilder;
      67: ldc           #192                // String , isCompaction=
      69: invokevirtual #28                 // Method java/lang/StringBuilder.append:(Ljava/lang/String;)Ljava/lang/StringBuilder;
      72: aload_0
      73: getfield      #18                 // Field isCompaction:Z
      76: invokevirtual #193                // Method java/lang/StringBuilder.append:(Z)Ljava/lang/StringBuilder;
      79: invokevirtual #30                 // Method java/lang/StringBuilder.toString:()Ljava/lang/String;
      82: invokespecial #74                 // Method java/lang/IllegalStateException."<init>":(Ljava/lang/String;)V
      85: athrow
      86: aload_0
      87: aload_1
      88: invokevirtual #194                // Method updateCurrBlockRef:(Lorg/apache/hadoop/hbase/io/hfile/HFileBlock;)V
      91: aload_0
      92: aload_1
      93: invokevirtual #195                // Method org/apache/hadoop/hbase/io/hfile/HFileBlock.getBufferWithoutHeader:()Lorg/apache/hadoop/hbase/nio/ByteBuff;
      96: putfield      #38                 // Field blockBuffer:Lorg/apache/hadoop/hbase/nio/ByteBuff;
      99: aload_0
     100: invokevirtual #106                // Method readKeyValueLen:()V
     103: aload_0
     104: getfield      #5                  // Field blockFetches:Ljava/util/concurrent/atomic/AtomicInteger;
     107: invokevirtual #196                // Method java/util/concurrent/atomic/AtomicInteger.incrementAndGet:()I
     110: pop
     111: aload_0
     112: aconst_null
     113: putfield      #110                // Field nextIndexedKey:Lorg/apache/hadoop/hbase/Cell;
     116: return

  protected org.apache.hadoop.hbase.Cell getFirstKeyCellInBlock(org.apache.hadoop.hbase.io.hfile.HFileBlock);
    Code:
       0: aload_1
       1: invokevirtual #195                // Method org/apache/hadoop/hbase/io/hfile/HFileBlock.getBufferWithoutHeader:()Lorg/apache/hadoop/hbase/nio/ByteBuff;
       4: astore_2
       5: aload_2
       6: invokevirtual #182                // Method org/apache/hadoop/hbase/nio/ByteBuff.rewind:()Lorg/apache/hadoop/hbase/nio/ByteBuff;
       9: pop
      10: aload_2
      11: invokevirtual #197                // Method org/apache/hadoop/hbase/nio/ByteBuff.getInt:()I
      14: istore_3
      15: aload_2
      16: iconst_4
      17: invokevirtual #108                // Method org/apache/hadoop/hbase/nio/ByteBuff.skip:(I)Lorg/apache/hadoop/hbase/nio/ByteBuff;
      20: pop
      21: aload_2
      22: iload_3
      23: invokevirtual #142                // Method org/apache/hadoop/hbase/nio/ByteBuff.asSubByteBuffer:(I)Ljava/nio/ByteBuffer;
      26: astore        4
      28: aload         4
      30: invokevirtual #152                // Method java/nio/ByteBuffer.hasArray:()Z
      33: ifeq          61
      36: new           #153                // class org/apache/hadoop/hbase/KeyValue$KeyOnlyKeyValue
      39: dup
      40: aload         4
      42: invokevirtual #149                // Method java/nio/ByteBuffer.array:()[B
      45: aload         4
      47: invokevirtual #150                // Method java/nio/ByteBuffer.arrayOffset:()I
      50: aload         4
      52: invokevirtual #145                // Method java/nio/ByteBuffer.position:()I
      55: iadd
      56: iload_3
      57: invokespecial #154                // Method org/apache/hadoop/hbase/KeyValue$KeyOnlyKeyValue."<init>":([BII)V
      60: areturn
      61: new           #6                  // class org/apache/hadoop/hbase/ByteBufferKeyOnlyKeyValue
      64: dup
      65: aload         4
      67: aload         4
      69: invokevirtual #145                // Method java/nio/ByteBuffer.position:()I
      72: iload_3
      73: invokespecial #198                // Method org/apache/hadoop/hbase/ByteBufferKeyOnlyKeyValue."<init>":(Ljava/nio/ByteBuffer;II)V
      76: areturn

  public java.lang.String getKeyString();
    Code:
       0: aload_0
       1: invokevirtual #199                // Method getKey:()Lorg/apache/hadoop/hbase/Cell;
       4: iconst_0
       5: invokestatic  #200                // Method org/apache/hadoop/hbase/CellUtil.toString:(Lorg/apache/hadoop/hbase/Cell;Z)Ljava/lang/String;
       8: areturn

  public java.lang.String getValueString();
    Code:
       0: aload_0
       1: invokevirtual #201                // Method getValue:()Ljava/nio/ByteBuffer;
       4: invokestatic  #202                // Method org/apache/hadoop/hbase/util/ByteBufferUtils.toStringBinary:(Ljava/nio/ByteBuffer;)Ljava/lang/String;
       7: areturn

  public int compareKey(org.apache.hadoop.hbase.CellComparator, org.apache.hadoop.hbase.Cell);
    Code:
       0: aload_0
       1: getfield      #38                 // Field blockBuffer:Lorg/apache/hadoop/hbase/nio/ByteBuff;
       4: aload_0
       5: getfield      #38                 // Field blockBuffer:Lorg/apache/hadoop/hbase/nio/ByteBuff;
       8: invokevirtual #72                 // Method org/apache/hadoop/hbase/nio/ByteBuff.position:()I
      11: bipush        8
      13: iadd
      14: aload_0
      15: getfield      #46                 // Field currKeyLen:I
      18: aload_0
      19: getfield      #11                 // Field pair:Lorg/apache/hadoop/hbase/util/ObjectIntPair;
      22: invokevirtual #91                 // Method org/apache/hadoop/hbase/nio/ByteBuff.asSubByteBuffer:(IILorg/apache/hadoop/hbase/util/ObjectIntPair;)V
      25: aload_0
      26: getfield      #8                  // Field bufBackedKeyOnlyKv:Lorg/apache/hadoop/hbase/ByteBufferKeyOnlyKeyValue;
      29: aload_0
      30: getfield      #11                 // Field pair:Lorg/apache/hadoop/hbase/util/ObjectIntPair;
      33: invokevirtual #92                 // Method org/apache/hadoop/hbase/util/ObjectIntPair.getFirst:()Ljava/lang/Object;
      36: checkcast     #93                 // class java/nio/ByteBuffer
      39: aload_0
      40: getfield      #11                 // Field pair:Lorg/apache/hadoop/hbase/util/ObjectIntPair;
      43: invokevirtual #94                 // Method org/apache/hadoop/hbase/util/ObjectIntPair.getSecond:()I
      46: aload_0
      47: getfield      #46                 // Field currKeyLen:I
      50: invokevirtual #95                 // Method org/apache/hadoop/hbase/ByteBufferKeyOnlyKeyValue.setKey:(Ljava/nio/ByteBuffer;II)V
      53: aload_1
      54: aload_2
      55: aload_0
      56: getfield      #8                  // Field bufBackedKeyOnlyKv:Lorg/apache/hadoop/hbase/ByteBufferKeyOnlyKeyValue;
      59: invokestatic  #97                 // Method org/apache/hadoop/hbase/PrivateCellUtil.compareKeyIgnoresMvcc:(Lorg/apache/hadoop/hbase/CellComparator;Lorg/apache/hadoop/hbase/Cell;Lorg/apache/hadoop/hbase/Cell;)I
      62: ireturn

  public void shipped() throws java.io.IOException;
    Code:
       0: aload_0
       1: iconst_0
       2: invokespecial #51                 // Method returnBlocks:(Z)V
       5: return
}
