Compiled from "HFileBlock.java"
class org.apache.hadoop.hbase.io.hfile.HFileBlock$FSReaderImpl$1 implements org.apache.hadoop.hbase.io.hfile.HFileBlock$BlockIterator {
  final long val$startOffset;

  final long val$endOffset;

  final org.apache.hadoop.hbase.io.hfile.HFileBlock$FSReader val$owner;

  final org.apache.hadoop.hbase.io.hfile.HFileBlock$FSReaderImpl this$0;

  org.apache.hadoop.hbase.io.hfile.HFileBlock$FSReaderImpl$1(org.apache.hadoop.hbase.io.hfile.HFileBlock$FSReaderImpl, long, long, org.apache.hadoop.hbase.io.hfile.HFileBlock$FSReader);
    Code:
       0: aload_0
       1: aload_1
       2: putfield      #1                  // Field this$0:Lorg/apache/hadoop/hbase/io/hfile/HFileBlock$FSReaderImpl;
       5: aload_0
       6: lload_2
       7: putfield      #2                  // Field val$startOffset:J
      10: aload_0
      11: lload         4
      13: putfield      #3                  // Field val$endOffset:J
      16: aload_0
      17: aload         6
      19: putfield      #4                  // Field val$owner:Lorg/apache/hadoop/hbase/io/hfile/HFileBlock$FSReader;
      22: aload_0
      23: invokespecial #5                  // Method java/lang/Object."<init>":()V
      26: aload_0
      27: aload_0
      28: getfield      #2                  // Field val$startOffset:J
      31: putfield      #6                  // Field offset:J
      34: aload_0
      35: ldc2_w        #7                  // long -1l
      38: putfield      #9                  // Field length:J
      41: return

  public org.apache.hadoop.hbase.io.hfile.HFileBlock nextBlock() throws java.io.IOException;
    Code:
       0: aload_0
       1: getfield      #6                  // Field offset:J
       4: aload_0
       5: getfield      #3                  // Field val$endOffset:J
       8: lcmp
       9: iflt          14
      12: aconst_null
      13: areturn
      14: aload_0
      15: getfield      #1                  // Field this$0:Lorg/apache/hadoop/hbase/io/hfile/HFileBlock$FSReaderImpl;
      18: aload_0
      19: getfield      #6                  // Field offset:J
      22: aload_0
      23: getfield      #9                  // Field length:J
      26: iconst_0
      27: iconst_0
      28: invokevirtual #10                 // Method org/apache/hadoop/hbase/io/hfile/HFileBlock$FSReaderImpl.readBlockData:(JJZZ)Lorg/apache/hadoop/hbase/io/hfile/HFileBlock;
      31: astore_1
      32: aload_0
      33: dup
      34: getfield      #6                  // Field offset:J
      37: aload_1
      38: invokevirtual #11                 // Method org/apache/hadoop/hbase/io/hfile/HFileBlock.getOnDiskSizeWithHeader:()I
      41: i2l
      42: ladd
      43: putfield      #6                  // Field offset:J
      46: aload_0
      47: aload_1
      48: invokevirtual #12                 // Method org/apache/hadoop/hbase/io/hfile/HFileBlock.getNextBlockOnDiskSize:()I
      51: i2l
      52: putfield      #9                  // Field length:J
      55: aload_1
      56: aload_0
      57: getfield      #1                  // Field this$0:Lorg/apache/hadoop/hbase/io/hfile/HFileBlock$FSReaderImpl;
      60: invokestatic  #13                 // Method org/apache/hadoop/hbase/io/hfile/HFileBlock$FSReaderImpl.access$400:(Lorg/apache/hadoop/hbase/io/hfile/HFileBlock$FSReaderImpl;)Lorg/apache/hadoop/hbase/io/hfile/HFileContext;
      63: aload_0
      64: getfield      #4                  // Field val$owner:Lorg/apache/hadoop/hbase/io/hfile/HFileBlock$FSReader;
      67: invokevirtual #14                 // Method org/apache/hadoop/hbase/io/hfile/HFileBlock.unpack:(Lorg/apache/hadoop/hbase/io/hfile/HFileContext;Lorg/apache/hadoop/hbase/io/hfile/HFileBlock$FSReader;)Lorg/apache/hadoop/hbase/io/hfile/HFileBlock;
      70: areturn

  public org.apache.hadoop.hbase.io.hfile.HFileBlock nextBlockWithBlockType(org.apache.hadoop.hbase.io.hfile.BlockType) throws java.io.IOException;
    Code:
       0: aload_0
       1: invokevirtual #15                 // Method nextBlock:()Lorg/apache/hadoop/hbase/io/hfile/HFileBlock;
       4: astore_2
       5: aload_2
       6: invokevirtual #16                 // Method org/apache/hadoop/hbase/io/hfile/HFileBlock.getBlockType:()Lorg/apache/hadoop/hbase/io/hfile/BlockType;
       9: aload_1
      10: if_acmpeq     52
      13: new           #17                 // class java/io/IOException
      16: dup
      17: new           #18                 // class java/lang/StringBuilder
      20: dup
      21: invokespecial #19                 // Method java/lang/StringBuilder."<init>":()V
      24: ldc           #20                 // String Expected block of type
      26: invokevirtual #21                 // Method java/lang/StringBuilder.append:(Ljava/lang/String;)Ljava/lang/StringBuilder;
      29: aload_1
      30: invokevirtual #22                 // Method java/lang/StringBuilder.append:(Ljava/lang/Object;)Ljava/lang/StringBuilder;
      33: ldc           #23                 // String  but found
      35: invokevirtual #21                 // Method java/lang/StringBuilder.append:(Ljava/lang/String;)Ljava/lang/StringBuilder;
      38: aload_2
      39: invokevirtual #16                 // Method org/apache/hadoop/hbase/io/hfile/HFileBlock.getBlockType:()Lorg/apache/hadoop/hbase/io/hfile/BlockType;
      42: invokevirtual #22                 // Method java/lang/StringBuilder.append:(Ljava/lang/Object;)Ljava/lang/StringBuilder;
      45: invokevirtual #24                 // Method java/lang/StringBuilder.toString:()Ljava/lang/String;
      48: invokespecial #25                 // Method java/io/IOException."<init>":(Ljava/lang/String;)V
      51: athrow
      52: aload_2
      53: areturn
}
