Compiled from "HFileWriterImpl.java"
class org.apache.hadoop.hbase.io.hfile.HFileWriterImpl$1 implements org.apache.hadoop.hbase.io.hfile.HFileBlock$BlockWritable {
  final org.apache.hadoop.hbase.io.hfile.BlockType val$blockType;

  final org.apache.hadoop.hbase.util.BloomFilterWriter val$bfw;

  final org.apache.hadoop.hbase.io.hfile.HFileWriterImpl this$0;

  org.apache.hadoop.hbase.io.hfile.HFileWriterImpl$1(org.apache.hadoop.hbase.io.hfile.HFileWriterImpl, org.apache.hadoop.hbase.io.hfile.BlockType, org.apache.hadoop.hbase.util.BloomFilterWriter);
    Code:
       0: aload_0
       1: aload_1
       2: putfield      #1                  // Field this$0:Lorg/apache/hadoop/hbase/io/hfile/HFileWriterImpl;
       5: aload_0
       6: aload_2
       7: putfield      #2                  // Field val$blockType:Lorg/apache/hadoop/hbase/io/hfile/BlockType;
      10: aload_0
      11: aload_3
      12: putfield      #3                  // Field val$bfw:Lorg/apache/hadoop/hbase/util/BloomFilterWriter;
      15: aload_0
      16: invokespecial #4                  // Method java/lang/Object."<init>":()V
      19: return

  public org.apache.hadoop.hbase.io.hfile.BlockType getBlockType();
    Code:
       0: aload_0
       1: getfield      #2                  // Field val$blockType:Lorg/apache/hadoop/hbase/io/hfile/BlockType;
       4: areturn

  public void writeToBlock(java.io.DataOutput) throws java.io.IOException;
    Code:
       0: aload_0
       1: getfield      #3                  // Field val$bfw:Lorg/apache/hadoop/hbase/util/BloomFilterWriter;
       4: invokeinterface #5,  1            // InterfaceMethod org/apache/hadoop/hbase/util/BloomFilterWriter.getMetaWriter:()Lorg/apache/hadoop/io/Writable;
       9: aload_1
      10: invokeinterface #6,  2            // InterfaceMethod org/apache/hadoop/io/Writable.write:(Ljava/io/DataOutput;)V
      15: aload_0
      16: getfield      #3                  // Field val$bfw:Lorg/apache/hadoop/hbase/util/BloomFilterWriter;
      19: invokeinterface #7,  1            // InterfaceMethod org/apache/hadoop/hbase/util/BloomFilterWriter.getDataWriter:()Lorg/apache/hadoop/io/Writable;
      24: astore_2
      25: aload_2
      26: ifnull        36
      29: aload_2
      30: aload_1
      31: invokeinterface #6,  2            // InterfaceMethod org/apache/hadoop/io/Writable.write:(Ljava/io/DataOutput;)V
      36: return
}
