Compiled from "HFilePrettyPrinter.java"
public class org.apache.hadoop.hbase.io.hfile.HFilePrettyPrinter extends org.apache.hadoop.conf.Configured implements org.apache.hadoop.util.Tool {
  public org.apache.hadoop.hbase.io.hfile.HFilePrettyPrinter();
    Code:
       0: aload_0
       1: invokespecial #1                  // Method org/apache/hadoop/conf/Configured."<init>":()V
       4: aload_0
       5: new           #2                  // class org/apache/hbase/thirdparty/org/apache/commons/cli/Options
       8: dup
       9: invokespecial #3                  // Method org/apache/hbase/thirdparty/org/apache/commons/cli/Options."<init>":()V
      12: putfield      #4                  // Field options:Lorg/apache/hbase/thirdparty/org/apache/commons/cli/Options;
      15: aload_0
      16: iconst_0
      17: putfield      #5                  // Field isSeekToRow:Z
      20: aload_0
      21: iconst_0
      22: putfield      #6                  // Field checkMobIntegrity:Z
      25: aload_0
      26: getstatic     #7                  // Field java/lang/System.out:Ljava/io/PrintStream;
      29: putfield      #8                  // Field out:Ljava/io/PrintStream;
      32: aload_0
      33: getstatic     #9                  // Field java/lang/System.err:Ljava/io/PrintStream;
      36: putfield      #10                 // Field err:Ljava/io/PrintStream;
      39: aload_0
      40: aconst_null
      41: putfield      #11                 // Field row:[B
      44: aload_0
      45: new           #12                 // class java/util/ArrayList
      48: dup
      49: invokespecial #13                 // Method java/util/ArrayList."<init>":()V
      52: putfield      #14                 // Field files:Ljava/util/List;
      55: aload_0
      56: invokespecial #15                 // Method init:()V
      59: return

  public org.apache.hadoop.hbase.io.hfile.HFilePrettyPrinter(org.apache.hadoop.conf.Configuration);
    Code:
       0: aload_0
       1: aload_1
       2: invokespecial #16                 // Method org/apache/hadoop/conf/Configured."<init>":(Lorg/apache/hadoop/conf/Configuration;)V
       5: aload_0
       6: new           #2                  // class org/apache/hbase/thirdparty/org/apache/commons/cli/Options
       9: dup
      10: invokespecial #3                  // Method org/apache/hbase/thirdparty/org/apache/commons/cli/Options."<init>":()V
      13: putfield      #4                  // Field options:Lorg/apache/hbase/thirdparty/org/apache/commons/cli/Options;
      16: aload_0
      17: iconst_0
      18: putfield      #5                  // Field isSeekToRow:Z
      21: aload_0
      22: iconst_0
      23: putfield      #6                  // Field checkMobIntegrity:Z
      26: aload_0
      27: getstatic     #7                  // Field java/lang/System.out:Ljava/io/PrintStream;
      30: putfield      #8                  // Field out:Ljava/io/PrintStream;
      33: aload_0
      34: getstatic     #9                  // Field java/lang/System.err:Ljava/io/PrintStream;
      37: putfield      #10                 // Field err:Ljava/io/PrintStream;
      40: aload_0
      41: aconst_null
      42: putfield      #11                 // Field row:[B
      45: aload_0
      46: new           #12                 // class java/util/ArrayList
      49: dup
      50: invokespecial #13                 // Method java/util/ArrayList."<init>":()V
      53: putfield      #14                 // Field files:Ljava/util/List;
      56: aload_0
      57: invokespecial #15                 // Method init:()V
      60: return

  public void setPrintStreams(java.io.PrintStream, java.io.PrintStream);
    Code:
       0: aload_0
       1: aload_1
       2: putfield      #8                  // Field out:Ljava/io/PrintStream;
       5: aload_0
       6: aload_2
       7: putfield      #10                 // Field err:Ljava/io/PrintStream;
      10: return

  public boolean parseOptions(java.lang.String[]) throws org.apache.hbase.thirdparty.org.apache.commons.cli.ParseException, java.io.IOException;
    Code:
       0: aload_1
       1: arraylength
       2: ifne          26
       5: new           #63                 // class org/apache/hbase/thirdparty/org/apache/commons/cli/HelpFormatter
       8: dup
       9: invokespecial #64                 // Method org/apache/hbase/thirdparty/org/apache/commons/cli/HelpFormatter."<init>":()V
      12: astore_2
      13: aload_2
      14: ldc           #65                 // String HFile
      16: aload_0
      17: getfield      #4                  // Field options:Lorg/apache/hbase/thirdparty/org/apache/commons/cli/Options;
      20: iconst_1
      21: invokevirtual #66                 // Method org/apache/hbase/thirdparty/org/apache/commons/cli/HelpFormatter.printHelp:(Ljava/lang/String;Lorg/apache/hbase/thirdparty/org/apache/commons/cli/Options;Z)V
      24: iconst_0
      25: ireturn
      26: new           #67                 // class org/apache/hbase/thirdparty/org/apache/commons/cli/PosixParser
      29: dup
      30: invokespecial #68                 // Method org/apache/hbase/thirdparty/org/apache/commons/cli/PosixParser."<init>":()V
      33: astore_2
      34: aload_2
      35: aload_0
      36: getfield      #4                  // Field options:Lorg/apache/hbase/thirdparty/org/apache/commons/cli/Options;
      39: aload_1
      40: invokeinterface #69,  3           // InterfaceMethod org/apache/hbase/thirdparty/org/apache/commons/cli/CommandLineParser.parse:(Lorg/apache/hbase/thirdparty/org/apache/commons/cli/Options;[Ljava/lang/String;)Lorg/apache/hbase/thirdparty/org/apache/commons/cli/CommandLine;
      45: astore_3
      46: aload_0
      47: aload_3
      48: ldc           #17                 // String v
      50: invokevirtual #70                 // Method org/apache/hbase/thirdparty/org/apache/commons/cli/CommandLine.hasOption:(Ljava/lang/String;)Z
      53: putfield      #71                 // Field verbose:Z
      56: aload_0
      57: aload_3
      58: ldc           #21                 // String p
      60: invokevirtual #70                 // Method org/apache/hbase/thirdparty/org/apache/commons/cli/CommandLine.hasOption:(Ljava/lang/String;)Z
      63: putfield      #72                 // Field printValue:Z
      66: aload_0
      67: aload_3
      68: ldc           #24                 // String e
      70: invokevirtual #70                 // Method org/apache/hbase/thirdparty/org/apache/commons/cli/CommandLine.hasOption:(Ljava/lang/String;)Z
      73: ifne          83
      76: aload_0
      77: getfield      #72                 // Field printValue:Z
      80: ifeq          87
      83: iconst_1
      84: goto          88
      87: iconst_0
      88: putfield      #73                 // Field printKey:Z
      91: aload_0
      92: aload_3
      93: ldc           #27                 // String m
      95: invokevirtual #70                 // Method org/apache/hbase/thirdparty/org/apache/commons/cli/CommandLine.hasOption:(Ljava/lang/String;)Z
      98: putfield      #74                 // Field shouldPrintMeta:Z
     101: aload_0
     102: aload_3
     103: ldc           #30                 // String b
     105: invokevirtual #70                 // Method org/apache/hbase/thirdparty/org/apache/commons/cli/CommandLine.hasOption:(Ljava/lang/String;)Z
     108: putfield      #75                 // Field printBlockIndex:Z
     111: aload_0
     112: aload_3
     113: ldc           #33                 // String h
     115: invokevirtual #70                 // Method org/apache/hbase/thirdparty/org/apache/commons/cli/CommandLine.hasOption:(Ljava/lang/String;)Z
     118: putfield      #76                 // Field printBlockHeaders:Z
     121: aload_0
     122: aload_3
     123: ldc           #45                 // String s
     125: invokevirtual #70                 // Method org/apache/hbase/thirdparty/org/apache/commons/cli/CommandLine.hasOption:(Ljava/lang/String;)Z
     128: putfield      #77                 // Field printStats:Z
     131: aload_0
     132: aload_3
     133: ldc           #36                 // String k
     135: invokevirtual #70                 // Method org/apache/hbase/thirdparty/org/apache/commons/cli/CommandLine.hasOption:(Ljava/lang/String;)Z
     138: putfield      #78                 // Field checkRow:Z
     141: aload_0
     142: aload_3
     143: ldc           #39                 // String a
     145: invokevirtual #70                 // Method org/apache/hbase/thirdparty/org/apache/commons/cli/CommandLine.hasOption:(Ljava/lang/String;)Z
     148: putfield      #79                 // Field checkFamily:Z
     151: aload_0
     152: aload_3
     153: ldc           #48                 // String i
     155: invokevirtual #70                 // Method org/apache/hbase/thirdparty/org/apache/commons/cli/CommandLine.hasOption:(Ljava/lang/String;)Z
     158: putfield      #6                  // Field checkMobIntegrity:Z
     161: aload_3
     162: ldc           #54                 // String f
     164: invokevirtual #70                 // Method org/apache/hbase/thirdparty/org/apache/commons/cli/CommandLine.hasOption:(Ljava/lang/String;)Z
     167: ifeq          193
     170: aload_0
     171: getfield      #14                 // Field files:Ljava/util/List;
     174: new           #80                 // class org/apache/hadoop/fs/Path
     177: dup
     178: aload_3
     179: ldc           #54                 // String f
     181: invokevirtual #81                 // Method org/apache/hbase/thirdparty/org/apache/commons/cli/CommandLine.getOptionValue:(Ljava/lang/String;)Ljava/lang/String;
     184: invokespecial #82                 // Method org/apache/hadoop/fs/Path."<init>":(Ljava/lang/String;)V
     187: invokeinterface #83,  2           // InterfaceMethod java/util/List.add:(Ljava/lang/Object;)Z
     192: pop
     193: aload_3
     194: ldc           #42                 // String w
     196: invokevirtual #70                 // Method org/apache/hbase/thirdparty/org/apache/commons/cli/CommandLine.hasOption:(Ljava/lang/String;)Z
     199: ifeq          253
     202: aload_3
     203: ldc           #42                 // String w
     205: invokevirtual #81                 // Method org/apache/hbase/thirdparty/org/apache/commons/cli/CommandLine.getOptionValue:(Ljava/lang/String;)Ljava/lang/String;
     208: astore        4
     210: aload         4
     212: ifnull        240
     215: aload         4
     217: invokevirtual #84                 // Method java/lang/String.length:()I
     220: ifeq          240
     223: aload_0
     224: aload         4
     226: invokestatic  #85                 // Method org/apache/hadoop/hbase/util/Bytes.toBytesBinary:(Ljava/lang/String;)[B
     229: putfield      #11                 // Field row:[B
     232: aload_0
     233: iconst_1
     234: putfield      #5                  // Field isSeekToRow:Z
     237: goto          253
     240: aload_0
     241: getfield      #10                 // Field err:Ljava/io/PrintStream;
     244: ldc           #86                 // String Invalid row is specified.
     246: invokevirtual #87                 // Method java/io/PrintStream.println:(Ljava/lang/String;)V
     249: iconst_m1
     250: invokestatic  #88                 // Method java/lang/System.exit:(I)V
     253: aload_3
     254: ldc           #59                 // String r
     256: invokevirtual #70                 // Method org/apache/hbase/thirdparty/org/apache/commons/cli/CommandLine.hasOption:(Ljava/lang/String;)Z
     259: ifeq          517
     262: aload_3
     263: ldc           #59                 // String r
     265: invokevirtual #81                 // Method org/apache/hbase/thirdparty/org/apache/commons/cli/CommandLine.getOptionValue:(Ljava/lang/String;)Ljava/lang/String;
     268: astore        4
     270: aload         4
     272: invokestatic  #89                 // Method org/apache/hadoop/hbase/util/Bytes.toBytes:(Ljava/lang/String;)[B
     275: astore        5
     277: aload         5
     279: invokestatic  #90                 // Method org/apache/hadoop/hbase/HRegionInfo.parseRegionName:([B)[[B
     282: astore        6
     284: aload_0
     285: invokevirtual #91                 // Method getConf:()Lorg/apache/hadoop/conf/Configuration;
     288: invokestatic  #92                 // Method org/apache/hadoop/hbase/util/FSUtils.getRootDir:(Lorg/apache/hadoop/conf/Configuration;)Lorg/apache/hadoop/fs/Path;
     291: astore        7
     293: aload         7
     295: aload         6
     297: iconst_0
     298: aaload
     299: invokestatic  #93                 // Method org/apache/hadoop/hbase/TableName.valueOf:([B)Lorg/apache/hadoop/hbase/TableName;
     302: invokestatic  #94                 // Method org/apache/hadoop/hbase/util/FSUtils.getTableDir:(Lorg/apache/hadoop/fs/Path;Lorg/apache/hadoop/hbase/TableName;)Lorg/apache/hadoop/fs/Path;
     305: astore        8
     307: aload         5
     309: invokestatic  #95                 // Method org/apache/hadoop/hbase/HRegionInfo.encodeRegionName:([B)Ljava/lang/String;
     312: astore        9
     314: new           #80                 // class org/apache/hadoop/fs/Path
     317: dup
     318: aload         8
     320: aload         9
     322: invokespecial #96                 // Method org/apache/hadoop/fs/Path."<init>":(Lorg/apache/hadoop/fs/Path;Ljava/lang/String;)V
     325: astore        10
     327: aload_0
     328: getfield      #71                 // Field verbose:Z
     331: ifeq          361
     334: aload_0
     335: getfield      #8                  // Field out:Ljava/io/PrintStream;
     338: new           #97                 // class java/lang/StringBuilder
     341: dup
     342: invokespecial #98                 // Method java/lang/StringBuilder."<init>":()V
     345: ldc           #99                 // String region dir ->
     347: invokevirtual #100                // Method java/lang/StringBuilder.append:(Ljava/lang/String;)Ljava/lang/StringBuilder;
     350: aload         10
     352: invokevirtual #101                // Method java/lang/StringBuilder.append:(Ljava/lang/Object;)Ljava/lang/StringBuilder;
     355: invokevirtual #102                // Method java/lang/StringBuilder.toString:()Ljava/lang/String;
     358: invokevirtual #87                 // Method java/io/PrintStream.println:(Ljava/lang/String;)V
     361: aload_0
     362: invokevirtual #91                 // Method getConf:()Lorg/apache/hadoop/conf/Configuration;
     365: invokestatic  #103                // Method org/apache/hadoop/fs/FileSystem.get:(Lorg/apache/hadoop/conf/Configuration;)Lorg/apache/hadoop/fs/FileSystem;
     368: aload         10
     370: invokestatic  #104                // Method org/apache/hadoop/hbase/io/hfile/HFile.getStoreFiles:(Lorg/apache/hadoop/fs/FileSystem;Lorg/apache/hadoop/fs/Path;)Ljava/util/List;
     373: astore        11
     375: aload_0
     376: getfield      #71                 // Field verbose:Z
     379: ifeq          414
     382: aload_0
     383: getfield      #8                  // Field out:Ljava/io/PrintStream;
     386: new           #97                 // class java/lang/StringBuilder
     389: dup
     390: invokespecial #98                 // Method java/lang/StringBuilder."<init>":()V
     393: ldc           #105                // String Number of region files found ->
     395: invokevirtual #100                // Method java/lang/StringBuilder.append:(Ljava/lang/String;)Ljava/lang/StringBuilder;
     398: aload         11
     400: invokeinterface #106,  1          // InterfaceMethod java/util/List.size:()I
     405: invokevirtual #107                // Method java/lang/StringBuilder.append:(I)Ljava/lang/StringBuilder;
     408: invokevirtual #102                // Method java/lang/StringBuilder.toString:()Ljava/lang/String;
     411: invokevirtual #87                 // Method java/io/PrintStream.println:(Ljava/lang/String;)V
     414: aload_0
     415: getfield      #71                 // Field verbose:Z
     418: ifeq          505
     421: iconst_1
     422: istore        12
     424: aload         11
     426: invokeinterface #108,  1          // InterfaceMethod java/util/List.iterator:()Ljava/util/Iterator;
     431: astore        13
     433: aload         13
     435: invokeinterface #109,  1          // InterfaceMethod java/util/Iterator.hasNext:()Z
     440: ifeq          505
     443: aload         13
     445: invokeinterface #110,  1          // InterfaceMethod java/util/Iterator.next:()Ljava/lang/Object;
     450: checkcast     #80                 // class org/apache/hadoop/fs/Path
     453: astore        14
     455: aload_0
     456: getfield      #71                 // Field verbose:Z
     459: ifeq          502
     462: aload_0
     463: getfield      #8                  // Field out:Ljava/io/PrintStream;
     466: new           #97                 // class java/lang/StringBuilder
     469: dup
     470: invokespecial #98                 // Method java/lang/StringBuilder."<init>":()V
     473: ldc           #111                // String Found file[
     475: invokevirtual #100                // Method java/lang/StringBuilder.append:(Ljava/lang/String;)Ljava/lang/StringBuilder;
     478: iload         12
     480: iinc          12, 1
     483: invokevirtual #107                // Method java/lang/StringBuilder.append:(I)Ljava/lang/StringBuilder;
     486: ldc           #112                // String ] ->
     488: invokevirtual #100                // Method java/lang/StringBuilder.append:(Ljava/lang/String;)Ljava/lang/StringBuilder;
     491: aload         14
     493: invokevirtual #101                // Method java/lang/StringBuilder.append:(Ljava/lang/Object;)Ljava/lang/StringBuilder;
     496: invokevirtual #102                // Method java/lang/StringBuilder.toString:()Ljava/lang/String;
     499: invokevirtual #87                 // Method java/io/PrintStream.println:(Ljava/lang/String;)V
     502: goto          433
     505: aload_0
     506: getfield      #14                 // Field files:Ljava/util/List;
     509: aload         11
     511: invokeinterface #113,  2          // InterfaceMethod java/util/List.addAll:(Ljava/util/Collection;)Z
     516: pop
     517: aload_0
     518: getfield      #6                  // Field checkMobIntegrity:Z
     521: ifeq          550
     524: aload_0
     525: getfield      #71                 // Field verbose:Z
     528: ifeq          539
     531: getstatic     #7                  // Field java/lang/System.out:Ljava/io/PrintStream;
     534: ldc           #114                // String checkMobIntegrity is enabled
     536: invokevirtual #87                 // Method java/io/PrintStream.println:(Ljava/lang/String;)V
     539: aload_0
     540: new           #115                // class java/util/HashMap
     543: dup
     544: invokespecial #116                // Method java/util/HashMap."<init>":()V
     547: putfield      #117                // Field mobFileLocations:Ljava/util/Map;
     550: aload_3
     551: invokevirtual #118                // Method org/apache/hbase/thirdparty/org/apache/commons/cli/CommandLine.getArgList:()Ljava/util/List;
     554: aload_0
     555: invokedynamic #119,  0            // InvokeDynamic #0:accept:(Lorg/apache/hadoop/hbase/io/hfile/HFilePrettyPrinter;)Ljava/util/function/Consumer;
     560: invokeinterface #120,  2          // InterfaceMethod java/util/List.forEach:(Ljava/util/function/Consumer;)V
     565: iconst_1
     566: ireturn

  public int run(java.lang.String[]);
    Code:
       0: aload_0
       1: invokevirtual #91                 // Method getConf:()Lorg/apache/hadoop/conf/Configuration;
       4: ifnonnull     17
       7: new           #121                // class java/lang/RuntimeException
      10: dup
      11: ldc           #122                // String A Configuration instance must be provided.
      13: invokespecial #123                // Method java/lang/RuntimeException."<init>":(Ljava/lang/String;)V
      16: athrow
      17: aload_0
      18: invokevirtual #91                 // Method getConf:()Lorg/apache/hadoop/conf/Configuration;
      21: aload_0
      22: invokevirtual #91                 // Method getConf:()Lorg/apache/hadoop/conf/Configuration;
      25: invokestatic  #92                 // Method org/apache/hadoop/hbase/util/FSUtils.getRootDir:(Lorg/apache/hadoop/conf/Configuration;)Lorg/apache/hadoop/fs/Path;
      28: invokestatic  #124                // Method org/apache/hadoop/hbase/util/FSUtils.setFsDefault:(Lorg/apache/hadoop/conf/Configuration;Lorg/apache/hadoop/fs/Path;)V
      31: aload_0
      32: aload_1
      33: invokevirtual #125                // Method parseOptions:([Ljava/lang/String;)Z
      36: ifne          41
      39: iconst_1
      40: ireturn
      41: goto          72
      44: astore_2
      45: getstatic     #127                // Field LOG:Lorg/slf4j/Logger;
      48: ldc           #128                // String Error parsing command-line options
      50: aload_2
      51: invokeinterface #129,  3          // InterfaceMethod org/slf4j/Logger.error:(Ljava/lang/String;Ljava/lang/Throwable;)V
      56: iconst_1
      57: ireturn
      58: astore_2
      59: getstatic     #127                // Field LOG:Lorg/slf4j/Logger;
      62: ldc           #128                // String Error parsing command-line options
      64: aload_2
      65: invokeinterface #129,  3          // InterfaceMethod org/slf4j/Logger.error:(Ljava/lang/String;Ljava/lang/Throwable;)V
      70: iconst_1
      71: ireturn
      72: aload_0
      73: getfield      #14                 // Field files:Ljava/util/List;
      76: invokeinterface #108,  1          // InterfaceMethod java/util/List.iterator:()Ljava/util/Iterator;
      81: astore_2
      82: aload_2
      83: invokeinterface #109,  1          // InterfaceMethod java/util/Iterator.hasNext:()Z
      88: ifeq          156
      91: aload_2
      92: invokeinterface #110,  1          // InterfaceMethod java/util/Iterator.next:()Ljava/lang/Object;
      97: checkcast     #80                 // class org/apache/hadoop/fs/Path
     100: astore_3
     101: aload_0
     102: aload_3
     103: invokevirtual #131                // Method processFile:(Lorg/apache/hadoop/fs/Path;)I
     106: istore        4
     108: iload         4
     110: ifeq          116
     113: iload         4
     115: ireturn
     116: goto          153
     119: astore        4
     121: getstatic     #127                // Field LOG:Lorg/slf4j/Logger;
     124: new           #97                 // class java/lang/StringBuilder
     127: dup
     128: invokespecial #98                 // Method java/lang/StringBuilder."<init>":()V
     131: ldc           #132                // String Error reading
     133: invokevirtual #100                // Method java/lang/StringBuilder.append:(Ljava/lang/String;)Ljava/lang/StringBuilder;
     136: aload_3
     137: invokevirtual #101                // Method java/lang/StringBuilder.append:(Ljava/lang/Object;)Ljava/lang/StringBuilder;
     140: invokevirtual #102                // Method java/lang/StringBuilder.toString:()Ljava/lang/String;
     143: aload         4
     145: invokeinterface #129,  3          // InterfaceMethod org/slf4j/Logger.error:(Ljava/lang/String;Ljava/lang/Throwable;)V
     150: bipush        -2
     152: ireturn
     153: goto          82
     156: aload_0
     157: getfield      #71                 // Field verbose:Z
     160: ifne          170
     163: aload_0
     164: getfield      #73                 // Field printKey:Z
     167: ifeq          199
     170: aload_0
     171: getfield      #8                  // Field out:Ljava/io/PrintStream;
     174: new           #97                 // class java/lang/StringBuilder
     177: dup
     178: invokespecial #98                 // Method java/lang/StringBuilder."<init>":()V
     181: ldc           #133                // String Scanned kv count ->
     183: invokevirtual #100                // Method java/lang/StringBuilder.append:(Ljava/lang/String;)Ljava/lang/StringBuilder;
     186: aload_0
     187: getfield      #134                // Field count:I
     190: invokevirtual #107                // Method java/lang/StringBuilder.append:(I)Ljava/lang/StringBuilder;
     193: invokevirtual #102                // Method java/lang/StringBuilder.toString:()Ljava/lang/String;
     196: invokevirtual #87                 // Method java/io/PrintStream.println:(Ljava/lang/String;)V
     199: iconst_0
     200: ireturn
    Exception table:
       from    to  target type
          17    40    44   Class java/io/IOException
          17    40    58   Class org/apache/hbase/thirdparty/org/apache/commons/cli/ParseException
         101   115   119   Class java/io/IOException

  public int processFile(org.apache.hadoop.fs.Path) throws java.io.IOException;
    Code:
       0: aload_0
       1: getfield      #71                 // Field verbose:Z
       4: ifeq          33
       7: aload_0
       8: getfield      #8                  // Field out:Ljava/io/PrintStream;
      11: new           #97                 // class java/lang/StringBuilder
      14: dup
      15: invokespecial #98                 // Method java/lang/StringBuilder."<init>":()V
      18: ldc           #135                // String Scanning ->
      20: invokevirtual #100                // Method java/lang/StringBuilder.append:(Ljava/lang/String;)Ljava/lang/StringBuilder;
      23: aload_1
      24: invokevirtual #101                // Method java/lang/StringBuilder.append:(Ljava/lang/Object;)Ljava/lang/StringBuilder;
      27: invokevirtual #102                // Method java/lang/StringBuilder.toString:()Ljava/lang/String;
      30: invokevirtual #87                 // Method java/io/PrintStream.println:(Ljava/lang/String;)V
      33: aload_0
      34: invokevirtual #91                 // Method getConf:()Lorg/apache/hadoop/conf/Configuration;
      37: invokestatic  #92                 // Method org/apache/hadoop/hbase/util/FSUtils.getRootDir:(Lorg/apache/hadoop/conf/Configuration;)Lorg/apache/hadoop/fs/Path;
      40: astore_2
      41: new           #97                 // class java/lang/StringBuilder
      44: dup
      45: invokespecial #98                 // Method java/lang/StringBuilder."<init>":()V
      48: aload_2
      49: invokevirtual #101                // Method java/lang/StringBuilder.append:(Ljava/lang/Object;)Ljava/lang/StringBuilder;
      52: aload_2
      53: pop
      54: ldc           #136                // String /
      56: invokevirtual #100                // Method java/lang/StringBuilder.append:(Ljava/lang/String;)Ljava/lang/StringBuilder;
      59: invokevirtual #102                // Method java/lang/StringBuilder.toString:()Ljava/lang/String;
      62: astore_3
      63: aload_1
      64: invokevirtual #137                // Method org/apache/hadoop/fs/Path.toString:()Ljava/lang/String;
      67: aload_3
      68: invokevirtual #138                // Method java/lang/String.startsWith:(Ljava/lang/String;)Z
      71: ifne          166
      74: aload_2
      75: aload_0
      76: invokevirtual #91                 // Method getConf:()Lorg/apache/hadoop/conf/Configuration;
      79: invokevirtual #139                // Method org/apache/hadoop/fs/Path.getFileSystem:(Lorg/apache/hadoop/conf/Configuration;)Lorg/apache/hadoop/fs/FileSystem;
      82: astore        4
      84: new           #97                 // class java/lang/StringBuilder
      87: dup
      88: invokespecial #98                 // Method java/lang/StringBuilder."<init>":()V
      91: aload         4
      93: invokevirtual #140                // Method org/apache/hadoop/fs/FileSystem.getUri:()Ljava/net/URI;
      96: invokevirtual #141                // Method java/net/URI.toString:()Ljava/lang/String;
      99: invokevirtual #100                // Method java/lang/StringBuilder.append:(Ljava/lang/String;)Ljava/lang/StringBuilder;
     102: aload_1
     103: invokevirtual #137                // Method org/apache/hadoop/fs/Path.toString:()Ljava/lang/String;
     106: invokevirtual #100                // Method java/lang/StringBuilder.append:(Ljava/lang/String;)Ljava/lang/StringBuilder;
     109: invokevirtual #102                // Method java/lang/StringBuilder.toString:()Ljava/lang/String;
     112: astore        5
     114: aload         5
     116: aload_3
     117: invokevirtual #138                // Method java/lang/String.startsWith:(Ljava/lang/String;)Z
     120: ifne          166
     123: aload_0
     124: getfield      #10                 // Field err:Ljava/io/PrintStream;
     127: new           #97                 // class java/lang/StringBuilder
     130: dup
     131: invokespecial #98                 // Method java/lang/StringBuilder."<init>":()V
     134: ldc           #142                // String ERROR, file (
     136: invokevirtual #100                // Method java/lang/StringBuilder.append:(Ljava/lang/String;)Ljava/lang/StringBuilder;
     139: aload_1
     140: invokevirtual #101                // Method java/lang/StringBuilder.append:(Ljava/lang/Object;)Ljava/lang/StringBuilder;
     143: ldc           #143                // String ) is not in HBase's root directory (
     145: invokevirtual #100                // Method java/lang/StringBuilder.append:(Ljava/lang/String;)Ljava/lang/StringBuilder;
     148: aload_3
     149: invokevirtual #100                // Method java/lang/StringBuilder.append:(Ljava/lang/String;)Ljava/lang/StringBuilder;
     152: ldc           #144                // String )
     154: invokevirtual #100                // Method java/lang/StringBuilder.append:(Ljava/lang/String;)Ljava/lang/StringBuilder;
     157: invokevirtual #102                // Method java/lang/StringBuilder.toString:()Ljava/lang/String;
     160: invokevirtual #87                 // Method java/io/PrintStream.println:(Ljava/lang/String;)V
     163: bipush        -2
     165: ireturn
     166: aload_1
     167: aload_0
     168: invokevirtual #91                 // Method getConf:()Lorg/apache/hadoop/conf/Configuration;
     171: invokevirtual #139                // Method org/apache/hadoop/fs/Path.getFileSystem:(Lorg/apache/hadoop/conf/Configuration;)Lorg/apache/hadoop/fs/FileSystem;
     174: astore        4
     176: aload         4
     178: aload_1
     179: invokevirtual #145                // Method org/apache/hadoop/fs/FileSystem.exists:(Lorg/apache/hadoop/fs/Path;)Z
     182: ifne          214
     185: aload_0
     186: getfield      #10                 // Field err:Ljava/io/PrintStream;
     189: new           #97                 // class java/lang/StringBuilder
     192: dup
     193: invokespecial #98                 // Method java/lang/StringBuilder."<init>":()V
     196: ldc           #146                // String ERROR, file doesnt exist:
     198: invokevirtual #100                // Method java/lang/StringBuilder.append:(Ljava/lang/String;)Ljava/lang/StringBuilder;
     201: aload_1
     202: invokevirtual #101                // Method java/lang/StringBuilder.append:(Ljava/lang/Object;)Ljava/lang/StringBuilder;
     205: invokevirtual #102                // Method java/lang/StringBuilder.toString:()Ljava/lang/String;
     208: invokevirtual #87                 // Method java/io/PrintStream.println:(Ljava/lang/String;)V
     211: bipush        -2
     213: ireturn
     214: aload         4
     216: aload_1
     217: getstatic     #147                // Field org/apache/hadoop/hbase/io/hfile/CacheConfig.DISABLED:Lorg/apache/hadoop/hbase/io/hfile/CacheConfig;
     220: iconst_1
     221: aload_0
     222: invokevirtual #91                 // Method getConf:()Lorg/apache/hadoop/conf/Configuration;
     225: invokestatic  #148                // Method org/apache/hadoop/hbase/io/hfile/HFile.createReader:(Lorg/apache/hadoop/fs/FileSystem;Lorg/apache/hadoop/fs/Path;Lorg/apache/hadoop/hbase/io/hfile/CacheConfig;ZLorg/apache/hadoop/conf/Configuration;)Lorg/apache/hadoop/hbase/io/hfile/HFile$Reader;
     228: astore        5
     230: aload         5
     232: invokeinterface #149,  1          // InterfaceMethod org/apache/hadoop/hbase/io/hfile/HFile$Reader.loadFileInfo:()Ljava/util/Map;
     237: astore        6
     239: aconst_null
     240: astore        7
     242: aload_0
     243: getfield      #71                 // Field verbose:Z
     246: ifne          284
     249: aload_0
     250: getfield      #73                 // Field printKey:Z
     253: ifne          284
     256: aload_0
     257: getfield      #78                 // Field checkRow:Z
     260: ifne          284
     263: aload_0
     264: getfield      #79                 // Field checkFamily:Z
     267: ifne          284
     270: aload_0
     271: getfield      #77                 // Field printStats:Z
     274: ifne          284
     277: aload_0
     278: getfield      #6                  // Field checkMobIntegrity:Z
     281: ifeq          371
     284: aload         5
     286: iconst_0
     287: iconst_0
     288: iconst_0
     289: invokeinterface #150,  4          // InterfaceMethod org/apache/hadoop/hbase/io/hfile/HFile$Reader.getScanner:(ZZZ)Lorg/apache/hadoop/hbase/io/hfile/HFileScanner;
     294: astore        8
     296: new           #151                // class org/apache/hadoop/hbase/io/hfile/HFilePrettyPrinter$KeyValueStatsCollector
     299: dup
     300: aconst_null
     301: invokespecial #152                // Method org/apache/hadoop/hbase/io/hfile/HFilePrettyPrinter$KeyValueStatsCollector."<init>":(Lorg/apache/hadoop/hbase/io/hfile/HFilePrettyPrinter$1;)V
     304: astore        7
     306: iconst_0
     307: istore        9
     309: aload_0
     310: getfield      #5                  // Field isSeekToRow:Z
     313: ifeq          344
     316: aload         8
     318: aload_0
     319: getfield      #11                 // Field row:[B
     322: invokestatic  #153                // Method org/apache/hadoop/hbase/PrivateCellUtil.createFirstOnRow:([B)Lorg/apache/hadoop/hbase/Cell;
     325: invokeinterface #154,  2          // InterfaceMethod org/apache/hadoop/hbase/io/hfile/HFileScanner.seekTo:(Lorg/apache/hadoop/hbase/Cell;)I
     330: iconst_m1
     331: if_icmpeq     338
     334: iconst_1
     335: goto          339
     338: iconst_0
     339: istore        9
     341: goto          353
     344: aload         8
     346: invokeinterface #155,  1          // InterfaceMethod org/apache/hadoop/hbase/io/hfile/HFileScanner.seekTo:()Z
     351: istore        9
     353: iload         9
     355: ifeq          371
     358: aload_0
     359: aload_1
     360: aload         7
     362: aload         8
     364: aload_0
     365: getfield      #11                 // Field row:[B
     368: invokespecial #156                // Method scanKeysValues:(Lorg/apache/hadoop/fs/Path;Lorg/apache/hadoop/hbase/io/hfile/HFilePrettyPrinter$KeyValueStatsCollector;Lorg/apache/hadoop/hbase/io/hfile/HFileScanner;[B)V
     371: aload_0
     372: getfield      #74                 // Field shouldPrintMeta:Z
     375: ifeq          386
     378: aload_0
     379: aload         5
     381: aload         6
     383: invokespecial #157                // Method printMeta:(Lorg/apache/hadoop/hbase/io/hfile/HFile$Reader;Ljava/util/Map;)V
     386: aload_0
     387: getfield      #75                 // Field printBlockIndex:Z
     390: ifeq          416
     393: aload_0
     394: getfield      #8                  // Field out:Ljava/io/PrintStream;
     397: ldc           #158                // String Block Index:
     399: invokevirtual #87                 // Method java/io/PrintStream.println:(Ljava/lang/String;)V
     402: aload_0
     403: getfield      #8                  // Field out:Ljava/io/PrintStream;
     406: aload         5
     408: invokeinterface #159,  1          // InterfaceMethod org/apache/hadoop/hbase/io/hfile/HFile$Reader.getDataBlockIndexReader:()Lorg/apache/hadoop/hbase/io/hfile/HFileBlockIndex$BlockIndexReader;
     413: invokevirtual #160                // Method java/io/PrintStream.println:(Ljava/lang/Object;)V
     416: aload_0
     417: getfield      #76                 // Field printBlockHeaders:Z
     420: ifeq          533
     423: aload_0
     424: getfield      #8                  // Field out:Ljava/io/PrintStream;
     427: ldc           #161                // String Block Headers:
     429: invokevirtual #87                 // Method java/io/PrintStream.println:(Ljava/lang/String;)V
     432: new           #162                // class org/apache/hadoop/hbase/io/FSDataInputStreamWrapper
     435: dup
     436: aload         4
     438: aload_1
     439: invokespecial #163                // Method org/apache/hadoop/hbase/io/FSDataInputStreamWrapper."<init>":(Lorg/apache/hadoop/fs/FileSystem;Lorg/apache/hadoop/fs/Path;)V
     442: astore        8
     444: aload         4
     446: aload_1
     447: invokevirtual #164                // Method org/apache/hadoop/fs/FileSystem.getFileStatus:(Lorg/apache/hadoop/fs/Path;)Lorg/apache/hadoop/fs/FileStatus;
     450: invokevirtual #165                // Method org/apache/hadoop/fs/FileStatus.getLen:()J
     453: lstore        9
     455: aload         8
     457: iconst_0
     458: invokevirtual #166                // Method org/apache/hadoop/hbase/io/FSDataInputStreamWrapper.getStream:(Z)Lorg/apache/hadoop/fs/FSDataInputStream;
     461: lload         9
     463: invokestatic  #167                // Method org/apache/hadoop/hbase/io/hfile/FixedFileTrailer.readFromStream:(Lorg/apache/hadoop/fs/FSDataInputStream;J)Lorg/apache/hadoop/hbase/io/hfile/FixedFileTrailer;
     466: astore        11
     468: aload         11
     470: invokevirtual #168                // Method org/apache/hadoop/hbase/io/hfile/FixedFileTrailer.getFirstDataBlockOffset:()J
     473: lstore        12
     475: aload         11
     477: invokevirtual #169                // Method org/apache/hadoop/hbase/io/hfile/FixedFileTrailer.getLastDataBlockOffset:()J
     480: lstore        14
     482: lload         12
     484: lload         14
     486: lcmp
     487: ifgt          533
     490: aload         5
     492: lload         12
     494: ldc2_w        #170                // long -1l
     497: iconst_0
     498: iconst_0
     499: iconst_0
     500: iconst_0
     501: aconst_null
     502: aconst_null
     503: invokeinterface #172,  11         // InterfaceMethod org/apache/hadoop/hbase/io/hfile/HFile$Reader.readBlock:(JJZZZZLorg/apache/hadoop/hbase/io/hfile/BlockType;Lorg/apache/hadoop/hbase/io/encoding/DataBlockEncoding;)Lorg/apache/hadoop/hbase/io/hfile/HFileBlock;
     508: astore        16
     510: lload         12
     512: aload         16
     514: invokevirtual #173                // Method org/apache/hadoop/hbase/io/hfile/HFileBlock.getOnDiskSizeWithHeader:()I
     517: i2l
     518: ladd
     519: lstore        12
     521: aload_0
     522: getfield      #8                  // Field out:Ljava/io/PrintStream;
     525: aload         16
     527: invokevirtual #160                // Method java/io/PrintStream.println:(Ljava/lang/Object;)V
     530: goto          482
     533: aload_0
     534: getfield      #77                 // Field printStats:Z
     537: ifeq          572
     540: aload         7
     542: invokevirtual #174                // Method org/apache/hadoop/hbase/io/hfile/HFilePrettyPrinter$KeyValueStatsCollector.finish:()V
     545: aload_0
     546: getfield      #8                  // Field out:Ljava/io/PrintStream;
     549: new           #97                 // class java/lang/StringBuilder
     552: dup
     553: invokespecial #98                 // Method java/lang/StringBuilder."<init>":()V
     556: ldc           #175                // String Stats:\n
     558: invokevirtual #100                // Method java/lang/StringBuilder.append:(Ljava/lang/String;)Ljava/lang/StringBuilder;
     561: aload         7
     563: invokevirtual #101                // Method java/lang/StringBuilder.append:(Ljava/lang/Object;)Ljava/lang/StringBuilder;
     566: invokevirtual #102                // Method java/lang/StringBuilder.toString:()Ljava/lang/String;
     569: invokevirtual #87                 // Method java/io/PrintStream.println:(Ljava/lang/String;)V
     572: aload         5
     574: invokeinterface #176,  1          // InterfaceMethod org/apache/hadoop/hbase/io/hfile/HFile$Reader.close:()V
     579: iconst_0
     580: ireturn

  public static void main(java.lang.String[]) throws java.lang.Exception;
    Code:
       0: invokestatic  #304                // Method org/apache/hadoop/hbase/HBaseConfiguration.create:()Lorg/apache/hadoop/conf/Configuration;
       3: astore_1
       4: aload_1
       5: ldc_w         #306                // String hfile.block.cache.size
       8: fconst_0
       9: invokevirtual #307                // Method org/apache/hadoop/conf/Configuration.setFloat:(Ljava/lang/String;F)V
      12: aload_1
      13: new           #178                // class org/apache/hadoop/hbase/io/hfile/HFilePrettyPrinter
      16: dup
      17: invokespecial #308                // Method "<init>":()V
      20: aload_0
      21: invokestatic  #309                // Method org/apache/hadoop/util/ToolRunner.run:(Lorg/apache/hadoop/conf/Configuration;Lorg/apache/hadoop/util/Tool;[Ljava/lang/String;)I
      24: istore_2
      25: iload_2
      26: invokestatic  #88                 // Method java/lang/System.exit:(I)V
      29: return

  static {};
    Code:
       0: ldc           #178                // class org/apache/hadoop/hbase/io/hfile/HFilePrettyPrinter
       2: invokestatic  #310                // Method org/slf4j/LoggerFactory.getLogger:(Ljava/lang/Class;)Lorg/slf4j/Logger;
       5: putstatic     #127                // Field LOG:Lorg/slf4j/Logger;
       8: return
}
