Compiled from "HQuorumPeer.java"
public final class org.apache.hadoop.hbase.zookeeper.HQuorumPeer {
  public static void main(java.lang.String[]);
    Code:
       0: invokestatic  #2                  // Method org/apache/hadoop/hbase/HBaseConfiguration.create:()Lorg/apache/hadoop/conf/Configuration;
       3: astore_1
       4: aload_1
       5: invokestatic  #3                  // Method org/apache/hadoop/hbase/zookeeper/ZKConfig.makeZKProps:(Lorg/apache/hadoop/conf/Configuration;)Ljava/util/Properties;
       8: astore_2
       9: aload_2
      10: invokestatic  #4                  // Method writeMyID:(Ljava/util/Properties;)V
      13: new           #5                  // class org/apache/zookeeper/server/quorum/QuorumPeerConfig
      16: dup
      17: invokespecial #6                  // Method org/apache/zookeeper/server/quorum/QuorumPeerConfig."<init>":()V
      20: astore_3
      21: aload_3
      22: aload_2
      23: invokevirtual #7                  // Method org/apache/zookeeper/server/quorum/QuorumPeerConfig.parseProperties:(Ljava/util/Properties;)V
      26: aload_1
      27: ldc           #9                  // String hbase.zookeeper.server.keytab.file
      29: ldc           #10                 // String hbase.zookeeper.server.kerberos.principal
      31: aload_3
      32: invokevirtual #11                 // Method org/apache/zookeeper/server/quorum/QuorumPeerConfig.getClientPortAddress:()Ljava/net/InetSocketAddress;
      35: invokevirtual #12                 // Method java/net/InetSocketAddress.getHostName:()Ljava/lang/String;
      38: invokestatic  #13                 // Method org/apache/hadoop/hbase/zookeeper/ZKUtil.loginServer:(Lorg/apache/hadoop/conf/Configuration;Ljava/lang/String;Ljava/lang/String;Ljava/lang/String;)V
      41: aload_3
      42: invokestatic  #14                 // Method runZKServer:(Lorg/apache/zookeeper/server/quorum/QuorumPeerConfig;)V
      45: goto          64
      48: astore_2
      49: getstatic     #16                 // Field LOG:Lorg/slf4j/Logger;
      52: ldc           #17                 // String Failed to start ZKServer
      54: aload_2
      55: invokeinterface #18,  3           // InterfaceMethod org/slf4j/Logger.error:(Ljava/lang/String;Ljava/lang/Throwable;)V
      60: iconst_m1
      61: invokestatic  #19                 // Method java/lang/System.exit:(I)V
      64: return
    Exception table:
       from    to  target type
           4    45    48   Class java/lang/Exception

  static void writeMyID(java.util.Properties) throws java.io.IOException;
    Code:
       0: ldc2_w        #33                 // long -1l
       3: lstore_1
       4: invokestatic  #2                  // Method org/apache/hadoop/hbase/HBaseConfiguration.create:()Lorg/apache/hadoop/conf/Configuration;
       7: astore_3
       8: aload_3
       9: ldc           #35                 // String hbase.zookeeper.dns.interface
      11: ldc           #36                 // String default
      13: invokevirtual #37                 // Method org/apache/hadoop/conf/Configuration.get:(Ljava/lang/String;Ljava/lang/String;)Ljava/lang/String;
      16: aload_3
      17: ldc           #38                 // String hbase.zookeeper.dns.nameserver
      19: ldc           #36                 // String default
      21: invokevirtual #37                 // Method org/apache/hadoop/conf/Configuration.get:(Ljava/lang/String;Ljava/lang/String;)Ljava/lang/String;
      24: invokestatic  #39                 // Method org/apache/hadoop/hbase/util/DNS.getDefaultHost:(Ljava/lang/String;Ljava/lang/String;)Ljava/lang/String;
      27: invokestatic  #40                 // Method org/apache/hadoop/hbase/util/Strings.domainNamePointerToHostName:(Ljava/lang/String;)Ljava/lang/String;
      30: astore        4
      32: new           #41                 // class java/util/ArrayList
      35: dup
      36: invokespecial #42                 // Method java/util/ArrayList."<init>":()V
      39: astore        5
      41: aload         5
      43: aload         4
      45: ldc           #43                 // String .
      47: invokevirtual #44                 // Method java/lang/String.contains:(Ljava/lang/CharSequence;)Z
      50: ifeq          58
      53: aload         4
      55: goto          63
      58: aload         4
      60: invokestatic  #45                 // Method org/apache/hadoop/util/StringUtils.simpleHostname:(Ljava/lang/String;)Ljava/lang/String;
      63: invokeinterface #46,  2           // InterfaceMethod java/util/List.add:(Ljava/lang/Object;)Z
      68: pop
      69: invokestatic  #47                 // Method java/net/NetworkInterface.getNetworkInterfaces:()Ljava/util/Enumeration;
      72: astore        6
      74: aload         6
      76: invokeinterface #48,  1           // InterfaceMethod java/util/Enumeration.hasMoreElements:()Z
      81: ifeq          156
      84: aload         6
      86: invokeinterface #49,  1           // InterfaceMethod java/util/Enumeration.nextElement:()Ljava/lang/Object;
      91: checkcast     #50                 // class java/net/NetworkInterface
      94: invokevirtual #51                 // Method java/net/NetworkInterface.getInetAddresses:()Ljava/util/Enumeration;
      97: astore        7
      99: aload         7
     101: invokeinterface #48,  1           // InterfaceMethod java/util/Enumeration.hasMoreElements:()Z
     106: ifeq          153
     109: aload         7
     111: invokeinterface #49,  1           // InterfaceMethod java/util/Enumeration.nextElement:()Ljava/lang/Object;
     116: checkcast     #52                 // class java/net/InetAddress
     119: astore        8
     121: aload         5
     123: aload         8
     125: invokevirtual #53                 // Method java/net/InetAddress.getHostName:()Ljava/lang/String;
     128: invokestatic  #45                 // Method org/apache/hadoop/util/StringUtils.simpleHostname:(Ljava/lang/String;)Ljava/lang/String;
     131: invokeinterface #46,  2           // InterfaceMethod java/util/List.add:(Ljava/lang/Object;)Z
     136: pop
     137: aload         5
     139: aload         8
     141: invokevirtual #54                 // Method java/net/InetAddress.getHostAddress:()Ljava/lang/String;
     144: invokeinterface #46,  2           // InterfaceMethod java/util/List.add:(Ljava/lang/Object;)Z
     149: pop
     150: goto          99
     153: goto          74
     156: aload_0
     157: invokevirtual #55                 // Method java/util/Properties.entrySet:()Ljava/util/Set;
     160: invokeinterface #56,  1           // InterfaceMethod java/util/Set.iterator:()Ljava/util/Iterator;
     165: astore        7
     167: aload         7
     169: invokeinterface #57,  1           // InterfaceMethod java/util/Iterator.hasNext:()Z
     174: ifeq          296
     177: aload         7
     179: invokeinterface #58,  1           // InterfaceMethod java/util/Iterator.next:()Ljava/lang/Object;
     184: checkcast     #59                 // class java/util/Map$Entry
     187: astore        8
     189: aload         8
     191: invokeinterface #60,  1           // InterfaceMethod java/util/Map$Entry.getKey:()Ljava/lang/Object;
     196: invokevirtual #61                 // Method java/lang/Object.toString:()Ljava/lang/String;
     199: invokevirtual #62                 // Method java/lang/String.trim:()Ljava/lang/String;
     202: astore        9
     204: aload         8
     206: invokeinterface #63,  1           // InterfaceMethod java/util/Map$Entry.getValue:()Ljava/lang/Object;
     211: invokevirtual #61                 // Method java/lang/Object.toString:()Ljava/lang/String;
     214: invokevirtual #62                 // Method java/lang/String.trim:()Ljava/lang/String;
     217: astore        10
     219: aload         9
     221: ldc           #64                 // String server.
     223: invokevirtual #65                 // Method java/lang/String.startsWith:(Ljava/lang/String;)Z
     226: ifeq          293
     229: aload         9
     231: bipush        46
     233: invokevirtual #66                 // Method java/lang/String.indexOf:(I)I
     236: istore        11
     238: aload         9
     240: iload         11
     242: iconst_1
     243: iadd
     244: invokevirtual #67                 // Method java/lang/String.substring:(I)Ljava/lang/String;
     247: invokestatic  #68                 // Method java/lang/Long.parseLong:(Ljava/lang/String;)J
     250: lstore        12
     252: aload         10
     254: ldc           #69                 // String :
     256: invokevirtual #70                 // Method java/lang/String.split:(Ljava/lang/String;)[Ljava/lang/String;
     259: astore        14
     261: aload         14
     263: iconst_0
     264: aaload
     265: astore        15
     267: aload         15
     269: invokestatic  #71                 // Method addressIsLocalHost:(Ljava/lang/String;)Z
     272: ifne          287
     275: aload         5
     277: aload         15
     279: invokeinterface #72,  2           // InterfaceMethod java/util/List.contains:(Ljava/lang/Object;)Z
     284: ifeq          293
     287: lload         12
     289: lstore_1
     290: goto          296
     293: goto          167
     296: aload_0
     297: ldc           #73                 // String maxSessionTimeout
     299: aload_3
     300: ldc           #74                 // String zookeeper.session.timeout
     302: ldc           #75                 // int 90000
     304: invokestatic  #76                 // Method java/lang/Integer.toString:(I)Ljava/lang/String;
     307: invokevirtual #37                 // Method org/apache/hadoop/conf/Configuration.get:(Ljava/lang/String;Ljava/lang/String;)Ljava/lang/String;
     310: invokevirtual #77                 // Method java/util/Properties.setProperty:(Ljava/lang/String;Ljava/lang/String;)Ljava/lang/Object;
     313: pop
     314: lload_1
     315: ldc2_w        #33                 // long -1l
     318: lcmp
     319: ifne          355
     322: new           #78                 // class java/io/IOException
     325: dup
     326: new           #79                 // class java/lang/StringBuilder
     329: dup
     330: invokespecial #80                 // Method java/lang/StringBuilder."<init>":()V
     333: ldc           #81                 // String Could not find my address:
     335: invokevirtual #82                 // Method java/lang/StringBuilder.append:(Ljava/lang/String;)Ljava/lang/StringBuilder;
     338: aload         4
     340: invokevirtual #82                 // Method java/lang/StringBuilder.append:(Ljava/lang/String;)Ljava/lang/StringBuilder;
     343: ldc           #83                 // String  in list of ZooKeeper quorum servers
     345: invokevirtual #82                 // Method java/lang/StringBuilder.append:(Ljava/lang/String;)Ljava/lang/StringBuilder;
     348: invokevirtual #84                 // Method java/lang/StringBuilder.toString:()Ljava/lang/String;
     351: invokespecial #85                 // Method java/io/IOException."<init>":(Ljava/lang/String;)V
     354: athrow
     355: aload_0
     356: ldc           #86                 // String dataDir
     358: invokevirtual #87                 // Method java/util/Properties.get:(Ljava/lang/Object;)Ljava/lang/Object;
     361: invokevirtual #61                 // Method java/lang/Object.toString:()Ljava/lang/String;
     364: invokevirtual #62                 // Method java/lang/String.trim:()Ljava/lang/String;
     367: astore        7
     369: new           #88                 // class java/io/File
     372: dup
     373: aload         7
     375: invokespecial #89                 // Method java/io/File."<init>":(Ljava/lang/String;)V
     378: astore        8
     380: aload         8
     382: invokevirtual #90                 // Method java/io/File.isDirectory:()Z
     385: ifne          424
     388: aload         8
     390: invokevirtual #91                 // Method java/io/File.mkdirs:()Z
     393: ifne          424
     396: new           #78                 // class java/io/IOException
     399: dup
     400: new           #79                 // class java/lang/StringBuilder
     403: dup
     404: invokespecial #80                 // Method java/lang/StringBuilder."<init>":()V
     407: ldc           #92                 // String Unable to create data dir
     409: invokevirtual #82                 // Method java/lang/StringBuilder.append:(Ljava/lang/String;)Ljava/lang/StringBuilder;
     412: aload         8
     414: invokevirtual #93                 // Method java/lang/StringBuilder.append:(Ljava/lang/Object;)Ljava/lang/StringBuilder;
     417: invokevirtual #84                 // Method java/lang/StringBuilder.toString:()Ljava/lang/String;
     420: invokespecial #85                 // Method java/io/IOException."<init>":(Ljava/lang/String;)V
     423: athrow
     424: new           #88                 // class java/io/File
     427: dup
     428: aload         8
     430: ldc           #94                 // String myid
     432: invokespecial #95                 // Method java/io/File."<init>":(Ljava/io/File;Ljava/lang/String;)V
     435: astore        9
     437: new           #96                 // class java/io/PrintWriter
     440: dup
     441: aload         9
     443: getstatic     #97                 // Field java/nio/charset/StandardCharsets.UTF_8:Ljava/nio/charset/Charset;
     446: invokevirtual #98                 // Method java/nio/charset/Charset.name:()Ljava/lang/String;
     449: invokespecial #99                 // Method java/io/PrintWriter."<init>":(Ljava/io/File;Ljava/lang/String;)V
     452: astore        10
     454: aload         10
     456: lload_1
     457: invokevirtual #100                // Method java/io/PrintWriter.println:(J)V
     460: aload         10
     462: invokevirtual #101                // Method java/io/PrintWriter.close:()V
     465: return

  static {};
    Code:
       0: ldc           #102                // class org/apache/hadoop/hbase/zookeeper/HQuorumPeer
       2: invokestatic  #103                // Method org/slf4j/LoggerFactory.getLogger:(Ljava/lang/Class;)Lorg/slf4j/Logger;
       5: putstatic     #16                 // Field LOG:Lorg/slf4j/Logger;
       8: return
}
