Compiled from "HRegionServer.java"
class org.apache.hadoop.hbase.regionserver.HRegionServer$SystemExitWhenAbortTimeout extends java.util.TimerTask {
  public org.apache.hadoop.hbase.regionserver.HRegionServer$SystemExitWhenAbortTimeout();
    Code:
       0: aload_0
       1: invokespecial #1                  // Method java/util/TimerTask."<init>":()V
       4: return

  public void run();
    Code:
       0: invokestatic  #2                  // Method org/apache/hadoop/hbase/regionserver/HRegionServer.access$000:()Lorg/slf4j/Logger;
       3: ldc           #3                  // String Aborting region server timed out, terminating forcibly and does not wait for any running shutdown hooks or finalizers to finish their work. Thread dump to stdout.
       5: invokeinterface #4,  2            // InterfaceMethod org/slf4j/Logger.warn:(Ljava/lang/String;)V
      10: getstatic     #5                  // Field java/lang/System.out:Ljava/io/PrintStream;
      13: ldc           #6                  // String Zombie HRegionServer
      15: invokestatic  #7                  // Method org/apache/hadoop/hbase/util/Threads.printThreadInfo:(Ljava/io/PrintStream;Ljava/lang/String;)V
      18: invokestatic  #8                  // Method java/lang/Runtime.getRuntime:()Ljava/lang/Runtime;
      21: iconst_1
      22: invokevirtual #9                  // Method java/lang/Runtime.halt:(I)V
      25: return
}
