Compiled from "HRegion.java"
class org.apache.hadoop.hbase.regionserver.HRegion$4 extends org.apache.hadoop.hbase.regionserver.HRegion$MutationBatchOperation {
  final java.util.Collection val$rowsToLock;

  final org.apache.hadoop.hbase.regionserver.HRegion this$0;

  org.apache.hadoop.hbase.regionserver.HRegion$4(org.apache.hadoop.hbase.regionserver.HRegion, org.apache.hadoop.hbase.regionserver.HRegion, org.apache.hadoop.hbase.client.Mutation[], boolean, long, long, java.util.Collection);
    Code:
       0: aload_0
       1: aload_1
       2: putfield      #1                  // Field this$0:Lorg/apache/hadoop/hbase/regionserver/HRegion;
       5: aload_0
       6: aload         9
       8: putfield      #2                  // Field val$rowsToLock:Ljava/util/Collection;
      11: aload_0
      12: aload_2
      13: aload_3
      14: iload         4
      16: lload         5
      18: lload         7
      20: invokespecial #3                  // Method org/apache/hadoop/hbase/regionserver/HRegion$MutationBatchOperation."<init>":(Lorg/apache/hadoop/hbase/regionserver/HRegion;[Lorg/apache/hadoop/hbase/client/Mutation;ZJJ)V
      23: return

  public org.apache.hadoop.hbase.regionserver.MiniBatchOperationInProgress<org.apache.hadoop.hbase.client.Mutation> lockRowsAndBuildMiniBatch(java.util.List<org.apache.hadoop.hbase.regionserver.Region$RowLock>) throws java.io.IOException;
    Code:
       0: aconst_null
       1: astore_2
       2: aload_0
       3: getfield      #2                  // Field val$rowsToLock:Ljava/util/Collection;
       6: invokeinterface #4,  1            // InterfaceMethod java/util/Collection.iterator:()Ljava/util/Iterator;
      11: astore_3
      12: aload_3
      13: invokeinterface #5,  1            // InterfaceMethod java/util/Iterator.hasNext:()Z
      18: ifeq          107
      21: aload_3
      22: invokeinterface #6,  1            // InterfaceMethod java/util/Iterator.next:()Ljava/lang/Object;
      27: checkcast     #7                  // class "[B"
      30: astore        4
      32: aload_0
      33: getfield      #8                  // Field region:Lorg/apache/hadoop/hbase/regionserver/HRegion;
      36: aload         4
      38: iconst_0
      39: aload_2
      40: invokevirtual #9                  // Method org/apache/hadoop/hbase/regionserver/HRegion.getRowLockInternal:([BZLorg/apache/hadoop/hbase/regionserver/Region$RowLock;)Lorg/apache/hadoop/hbase/regionserver/Region$RowLock;
      43: astore        5
      45: aload         5
      47: aload_2
      48: if_acmpeq     63
      51: aload_1
      52: aload         5
      54: invokeinterface #10,  2           // InterfaceMethod java/util/List.add:(Ljava/lang/Object;)Z
      59: pop
      60: aload         5
      62: astore_2
      63: goto          104
      66: astore        5
      68: invokestatic  #12                 // Method org/apache/hadoop/hbase/regionserver/HRegion.access$000:()Lorg/slf4j/Logger;
      71: new           #13                 // class java/lang/StringBuilder
      74: dup
      75: invokespecial #14                 // Method java/lang/StringBuilder."<init>":()V
      78: ldc           #15                 // String Failed getting lock, row=
      80: invokevirtual #16                 // Method java/lang/StringBuilder.append:(Ljava/lang/String;)Ljava/lang/StringBuilder;
      83: aload         4
      85: invokestatic  #17                 // Method org/apache/hadoop/hbase/util/Bytes.toStringBinary:([B)Ljava/lang/String;
      88: invokevirtual #16                 // Method java/lang/StringBuilder.append:(Ljava/lang/String;)Ljava/lang/StringBuilder;
      91: invokevirtual #18                 // Method java/lang/StringBuilder.toString:()Ljava/lang/String;
      94: aload         5
      96: invokeinterface #19,  3           // InterfaceMethod org/slf4j/Logger.warn:(Ljava/lang/String;Ljava/lang/Throwable;)V
     101: aload         5
     103: athrow
     104: goto          12
     107: aload_0
     108: aload_0
     109: invokevirtual #20                 // Method size:()I
     112: aload_0
     113: invokevirtual #20                 // Method size:()I
     116: invokevirtual #21                 // Method createMiniBatch:(II)Lorg/apache/hadoop/hbase/regionserver/MiniBatchOperationInProgress;
     119: areturn
    Exception table:
       from    to  target type
          32    63    66   Class java/io/IOException
}
