Compiled from "HRegion.java"
class org.apache.hadoop.hbase.regionserver.HRegion$RowLockContext {
  final java.util.concurrent.locks.ReadWriteLock readWriteLock;

  final java.util.concurrent.atomic.AtomicBoolean usable;

  final java.util.concurrent.atomic.AtomicInteger count;

  final java.lang.Object lock;

  static final boolean $assertionsDisabled;

  final org.apache.hadoop.hbase.regionserver.HRegion this$0;

  org.apache.hadoop.hbase.regionserver.HRegion$RowLockContext(org.apache.hadoop.hbase.regionserver.HRegion, org.apache.hadoop.hbase.util.HashedBytes);
    Code:
       0: aload_0
       1: aload_1
       2: putfield      #1                  // Field this$0:Lorg/apache/hadoop/hbase/regionserver/HRegion;
       5: aload_0
       6: invokespecial #2                  // Method java/lang/Object."<init>":()V
       9: aload_0
      10: new           #3                  // class java/util/concurrent/locks/ReentrantReadWriteLock
      13: dup
      14: iconst_1
      15: invokespecial #4                  // Method java/util/concurrent/locks/ReentrantReadWriteLock."<init>":(Z)V
      18: putfield      #5                  // Field readWriteLock:Ljava/util/concurrent/locks/ReadWriteLock;
      21: aload_0
      22: new           #6                  // class java/util/concurrent/atomic/AtomicBoolean
      25: dup
      26: iconst_1
      27: invokespecial #7                  // Method java/util/concurrent/atomic/AtomicBoolean."<init>":(Z)V
      30: putfield      #8                  // Field usable:Ljava/util/concurrent/atomic/AtomicBoolean;
      33: aload_0
      34: new           #9                  // class java/util/concurrent/atomic/AtomicInteger
      37: dup
      38: iconst_0
      39: invokespecial #10                 // Method java/util/concurrent/atomic/AtomicInteger."<init>":(I)V
      42: putfield      #11                 // Field count:Ljava/util/concurrent/atomic/AtomicInteger;
      45: aload_0
      46: new           #12                 // class java/lang/Object
      49: dup
      50: invokespecial #2                  // Method java/lang/Object."<init>":()V
      53: putfield      #13                 // Field lock:Ljava/lang/Object;
      56: aload_0
      57: aload_2
      58: putfield      #14                 // Field row:Lorg/apache/hadoop/hbase/util/HashedBytes;
      61: return

  org.apache.hadoop.hbase.regionserver.HRegion$RowLockImpl newWriteLock();
    Code:
       0: aload_0
       1: getfield      #5                  // Field readWriteLock:Ljava/util/concurrent/locks/ReadWriteLock;
       4: invokeinterface #15,  1           // InterfaceMethod java/util/concurrent/locks/ReadWriteLock.writeLock:()Ljava/util/concurrent/locks/Lock;
       9: astore_1
      10: aload_0
      11: aload_1
      12: invokespecial #16                 // Method getRowLock:(Ljava/util/concurrent/locks/Lock;)Lorg/apache/hadoop/hbase/regionserver/HRegion$RowLockImpl;
      15: areturn

  org.apache.hadoop.hbase.regionserver.HRegion$RowLockImpl newReadLock();
    Code:
       0: aload_0
       1: getfield      #5                  // Field readWriteLock:Ljava/util/concurrent/locks/ReadWriteLock;
       4: invokeinterface #17,  1           // InterfaceMethod java/util/concurrent/locks/ReadWriteLock.readLock:()Ljava/util/concurrent/locks/Lock;
       9: astore_1
      10: aload_0
      11: aload_1
      12: invokespecial #16                 // Method getRowLock:(Ljava/util/concurrent/locks/Lock;)Lorg/apache/hadoop/hbase/regionserver/HRegion$RowLockImpl;
      15: areturn

  void cleanUp();
    Code:
       0: aload_0
       1: getfield      #11                 // Field count:Ljava/util/concurrent/atomic/AtomicInteger;
       4: invokevirtual #22                 // Method java/util/concurrent/atomic/AtomicInteger.decrementAndGet:()I
       7: i2l
       8: lstore_1
       9: lload_1
      10: lconst_0
      11: lcmp
      12: ifgt          103
      15: aload_0
      16: getfield      #13                 // Field lock:Ljava/lang/Object;
      19: dup
      20: astore_3
      21: monitorenter
      22: aload_0
      23: getfield      #11                 // Field count:Ljava/util/concurrent/atomic/AtomicInteger;
      26: invokevirtual #23                 // Method java/util/concurrent/atomic/AtomicInteger.get:()I
      29: ifgt          91
      32: aload_0
      33: getfield      #8                  // Field usable:Ljava/util/concurrent/atomic/AtomicBoolean;
      36: invokevirtual #19                 // Method java/util/concurrent/atomic/AtomicBoolean.get:()Z
      39: ifeq          91
      42: aload_0
      43: getfield      #8                  // Field usable:Ljava/util/concurrent/atomic/AtomicBoolean;
      46: iconst_0
      47: invokevirtual #24                 // Method java/util/concurrent/atomic/AtomicBoolean.set:(Z)V
      50: aload_0
      51: getfield      #1                  // Field this$0:Lorg/apache/hadoop/hbase/regionserver/HRegion;
      54: invokestatic  #25                 // Method org/apache/hadoop/hbase/regionserver/HRegion.access$1300:(Lorg/apache/hadoop/hbase/regionserver/HRegion;)Ljava/util/concurrent/ConcurrentHashMap;
      57: aload_0
      58: getfield      #14                 // Field row:Lorg/apache/hadoop/hbase/util/HashedBytes;
      61: invokevirtual #26                 // Method java/util/concurrent/ConcurrentHashMap.remove:(Ljava/lang/Object;)Ljava/lang/Object;
      64: checkcast     #27                 // class org/apache/hadoop/hbase/regionserver/HRegion$RowLockContext
      67: astore        4
      69: getstatic     #28                 // Field $assertionsDisabled:Z
      72: ifne          91
      75: aload         4
      77: aload_0
      78: if_acmpeq     91
      81: new           #29                 // class java/lang/AssertionError
      84: dup
      85: ldc           #30                 // String we should never remove a different context
      87: invokespecial #31                 // Method java/lang/AssertionError."<init>":(Ljava/lang/Object;)V
      90: athrow
      91: aload_3
      92: monitorexit
      93: goto          103
      96: astore        5
      98: aload_3
      99: monitorexit
     100: aload         5
     102: athrow
     103: return
    Exception table:
       from    to  target type
          22    93    96   any
          96   100    96   any

  public void setThreadName(java.lang.String);
    Code:
       0: aload_0
       1: aload_1
       2: putfield      #32                 // Field threadName:Ljava/lang/String;
       5: return

  public java.lang.String toString();
    Code:
       0: new           #33                 // class java/lang/StringBuilder
       3: dup
       4: invokespecial #34                 // Method java/lang/StringBuilder."<init>":()V
       7: ldc           #35                 // String RowLockContext{row=
       9: invokevirtual #36                 // Method java/lang/StringBuilder.append:(Ljava/lang/String;)Ljava/lang/StringBuilder;
      12: aload_0
      13: getfield      #14                 // Field row:Lorg/apache/hadoop/hbase/util/HashedBytes;
      16: invokevirtual #37                 // Method java/lang/StringBuilder.append:(Ljava/lang/Object;)Ljava/lang/StringBuilder;
      19: ldc           #38                 // String , readWriteLock=
      21: invokevirtual #36                 // Method java/lang/StringBuilder.append:(Ljava/lang/String;)Ljava/lang/StringBuilder;
      24: aload_0
      25: getfield      #5                  // Field readWriteLock:Ljava/util/concurrent/locks/ReadWriteLock;
      28: invokevirtual #37                 // Method java/lang/StringBuilder.append:(Ljava/lang/Object;)Ljava/lang/StringBuilder;
      31: ldc           #39                 // String , count=
      33: invokevirtual #36                 // Method java/lang/StringBuilder.append:(Ljava/lang/String;)Ljava/lang/StringBuilder;
      36: aload_0
      37: getfield      #11                 // Field count:Ljava/util/concurrent/atomic/AtomicInteger;
      40: invokevirtual #37                 // Method java/lang/StringBuilder.append:(Ljava/lang/Object;)Ljava/lang/StringBuilder;
      43: ldc           #40                 // String , threadName=
      45: invokevirtual #36                 // Method java/lang/StringBuilder.append:(Ljava/lang/String;)Ljava/lang/StringBuilder;
      48: aload_0
      49: getfield      #32                 // Field threadName:Ljava/lang/String;
      52: invokevirtual #36                 // Method java/lang/StringBuilder.append:(Ljava/lang/String;)Ljava/lang/StringBuilder;
      55: bipush        125
      57: invokevirtual #41                 // Method java/lang/StringBuilder.append:(C)Ljava/lang/StringBuilder;
      60: invokevirtual #42                 // Method java/lang/StringBuilder.toString:()Ljava/lang/String;
      63: areturn

  static {};
    Code:
       0: ldc           #43                 // class org/apache/hadoop/hbase/regionserver/HRegion
       2: invokevirtual #44                 // Method java/lang/Class.desiredAssertionStatus:()Z
       5: ifne          12
       8: iconst_1
       9: goto          13
      12: iconst_0
      13: putstatic     #28                 // Field $assertionsDisabled:Z
      16: return
}
