Compiled from "HRegion.java"
public class org.apache.hadoop.hbase.regionserver.HRegion$RowLockImpl implements org.apache.hadoop.hbase.regionserver.Region$RowLock {
  public org.apache.hadoop.hbase.regionserver.HRegion$RowLockImpl(org.apache.hadoop.hbase.regionserver.HRegion$RowLockContext, java.util.concurrent.locks.Lock);
    Code:
       0: aload_0
       1: invokespecial #1                  // Method java/lang/Object."<init>":()V
       4: aload_0
       5: aload_1
       6: putfield      #2                  // Field context:Lorg/apache/hadoop/hbase/regionserver/HRegion$RowLockContext;
       9: aload_0
      10: aload_2
      11: putfield      #3                  // Field lock:Ljava/util/concurrent/locks/Lock;
      14: return

  public java.util.concurrent.locks.Lock getLock();
    Code:
       0: aload_0
       1: getfield      #3                  // Field lock:Ljava/util/concurrent/locks/Lock;
       4: areturn

  public org.apache.hadoop.hbase.regionserver.HRegion$RowLockContext getContext();
    Code:
       0: aload_0
       1: getfield      #2                  // Field context:Lorg/apache/hadoop/hbase/regionserver/HRegion$RowLockContext;
       4: areturn

  public void release();
    Code:
       0: aload_0
       1: getfield      #3                  // Field lock:Ljava/util/concurrent/locks/Lock;
       4: invokeinterface #4,  1            // InterfaceMethod java/util/concurrent/locks/Lock.unlock:()V
       9: aload_0
      10: getfield      #2                  // Field context:Lorg/apache/hadoop/hbase/regionserver/HRegion$RowLockContext;
      13: invokevirtual #5                  // Method org/apache/hadoop/hbase/regionserver/HRegion$RowLockContext.cleanUp:()V
      16: return

  public java.lang.String toString();
    Code:
       0: new           #6                  // class java/lang/StringBuilder
       3: dup
       4: invokespecial #7                  // Method java/lang/StringBuilder."<init>":()V
       7: ldc           #8                  // String RowLockImpl{context=
       9: invokevirtual #9                  // Method java/lang/StringBuilder.append:(Ljava/lang/String;)Ljava/lang/StringBuilder;
      12: aload_0
      13: getfield      #2                  // Field context:Lorg/apache/hadoop/hbase/regionserver/HRegion$RowLockContext;
      16: invokevirtual #10                 // Method java/lang/StringBuilder.append:(Ljava/lang/Object;)Ljava/lang/StringBuilder;
      19: ldc           #11                 // String , lock=
      21: invokevirtual #9                  // Method java/lang/StringBuilder.append:(Ljava/lang/String;)Ljava/lang/StringBuilder;
      24: aload_0
      25: getfield      #3                  // Field lock:Ljava/util/concurrent/locks/Lock;
      28: invokevirtual #10                 // Method java/lang/StringBuilder.append:(Ljava/lang/Object;)Ljava/lang/StringBuilder;
      31: bipush        125
      33: invokevirtual #12                 // Method java/lang/StringBuilder.append:(C)Ljava/lang/StringBuilder;
      36: invokevirtual #13                 // Method java/lang/StringBuilder.toString:()Ljava/lang/String;
      39: areturn
}
