Compiled from "HRegion.java"
class org.apache.hadoop.hbase.regionserver.HRegion$8 {
  static final int[] $SwitchMap$org$apache$hadoop$hbase$HConstants$OperationStatusCode;

  static final int[] $SwitchMap$org$apache$hadoop$hbase$CompareOperator;

  static final int[] $SwitchMap$org$apache$hadoop$hbase$shaded$protobuf$generated$WALProtos$FlushDescriptor$FlushAction;

  static final int[] $SwitchMap$org$apache$hadoop$hbase$regionserver$Region$Operation;

  static final int[] $SwitchMap$org$apache$hadoop$hbase$client$Durability;

  static {};
    Code:
       0: invokestatic  #1                  // Method org/apache/hadoop/hbase/client/Durability.values:()[Lorg/apache/hadoop/hbase/client/Durability;
       3: arraylength
       4: newarray       int
       6: putstatic     #2                  // Field $SwitchMap$org$apache$hadoop$hbase$client$Durability:[I
       9: getstatic     #2                  // Field $SwitchMap$org$apache$hadoop$hbase$client$Durability:[I
      12: getstatic     #3                  // Field org/apache/hadoop/hbase/client/Durability.USE_DEFAULT:Lorg/apache/hadoop/hbase/client/Durability;
      15: invokevirtual #4                  // Method org/apache/hadoop/hbase/client/Durability.ordinal:()I
      18: iconst_1
      19: iastore
      20: goto          24
      23: astore_0
      24: getstatic     #2                  // Field $SwitchMap$org$apache$hadoop$hbase$client$Durability:[I
      27: getstatic     #6                  // Field org/apache/hadoop/hbase/client/Durability.SKIP_WAL:Lorg/apache/hadoop/hbase/client/Durability;
      30: invokevirtual #4                  // Method org/apache/hadoop/hbase/client/Durability.ordinal:()I
      33: iconst_2
      34: iastore
      35: goto          39
      38: astore_0
      39: getstatic     #2                  // Field $SwitchMap$org$apache$hadoop$hbase$client$Durability:[I
      42: getstatic     #7                  // Field org/apache/hadoop/hbase/client/Durability.ASYNC_WAL:Lorg/apache/hadoop/hbase/client/Durability;
      45: invokevirtual #4                  // Method org/apache/hadoop/hbase/client/Durability.ordinal:()I
      48: iconst_3
      49: iastore
      50: goto          54
      53: astore_0
      54: getstatic     #2                  // Field $SwitchMap$org$apache$hadoop$hbase$client$Durability:[I
      57: getstatic     #8                  // Field org/apache/hadoop/hbase/client/Durability.SYNC_WAL:Lorg/apache/hadoop/hbase/client/Durability;
      60: invokevirtual #4                  // Method org/apache/hadoop/hbase/client/Durability.ordinal:()I
      63: iconst_4
      64: iastore
      65: goto          69
      68: astore_0
      69: getstatic     #2                  // Field $SwitchMap$org$apache$hadoop$hbase$client$Durability:[I
      72: getstatic     #9                  // Field org/apache/hadoop/hbase/client/Durability.FSYNC_WAL:Lorg/apache/hadoop/hbase/client/Durability;
      75: invokevirtual #4                  // Method org/apache/hadoop/hbase/client/Durability.ordinal:()I
      78: iconst_5
      79: iastore
      80: goto          84
      83: astore_0
      84: invokestatic  #10                 // Method org/apache/hadoop/hbase/regionserver/Region$Operation.values:()[Lorg/apache/hadoop/hbase/regionserver/Region$Operation;
      87: arraylength
      88: newarray       int
      90: putstatic     #11                 // Field $SwitchMap$org$apache$hadoop$hbase$regionserver$Region$Operation:[I
      93: getstatic     #11                 // Field $SwitchMap$org$apache$hadoop$hbase$regionserver$Region$Operation:[I
      96: getstatic     #12                 // Field org/apache/hadoop/hbase/regionserver/Region$Operation.INCREMENT:Lorg/apache/hadoop/hbase/regionserver/Region$Operation;
      99: invokevirtual #13                 // Method org/apache/hadoop/hbase/regionserver/Region$Operation.ordinal:()I
     102: iconst_1
     103: iastore
     104: goto          108
     107: astore_0
     108: getstatic     #11                 // Field $SwitchMap$org$apache$hadoop$hbase$regionserver$Region$Operation:[I
     111: getstatic     #14                 // Field org/apache/hadoop/hbase/regionserver/Region$Operation.APPEND:Lorg/apache/hadoop/hbase/regionserver/Region$Operation;
     114: invokevirtual #13                 // Method org/apache/hadoop/hbase/regionserver/Region$Operation.ordinal:()I
     117: iconst_2
     118: iastore
     119: goto          123
     122: astore_0
     123: getstatic     #11                 // Field $SwitchMap$org$apache$hadoop$hbase$regionserver$Region$Operation:[I
     126: getstatic     #15                 // Field org/apache/hadoop/hbase/regionserver/Region$Operation.GET:Lorg/apache/hadoop/hbase/regionserver/Region$Operation;
     129: invokevirtual #13                 // Method org/apache/hadoop/hbase/regionserver/Region$Operation.ordinal:()I
     132: iconst_3
     133: iastore
     134: goto          138
     137: astore_0
     138: getstatic     #11                 // Field $SwitchMap$org$apache$hadoop$hbase$regionserver$Region$Operation:[I
     141: getstatic     #16                 // Field org/apache/hadoop/hbase/regionserver/Region$Operation.SCAN:Lorg/apache/hadoop/hbase/regionserver/Region$Operation;
     144: invokevirtual #13                 // Method org/apache/hadoop/hbase/regionserver/Region$Operation.ordinal:()I
     147: iconst_4
     148: iastore
     149: goto          153
     152: astore_0
     153: invokestatic  #17                 // Method org/apache/hadoop/hbase/shaded/protobuf/generated/WALProtos$FlushDescriptor$FlushAction.values:()[Lorg/apache/hadoop/hbase/shaded/protobuf/generated/WALProtos$FlushDescriptor$FlushAction;
     156: arraylength
     157: newarray       int
     159: putstatic     #18                 // Field $SwitchMap$org$apache$hadoop$hbase$shaded$protobuf$generated$WALProtos$FlushDescriptor$FlushAction:[I
     162: getstatic     #18                 // Field $SwitchMap$org$apache$hadoop$hbase$shaded$protobuf$generated$WALProtos$FlushDescriptor$FlushAction:[I
     165: getstatic     #19                 // Field org/apache/hadoop/hbase/shaded/protobuf/generated/WALProtos$FlushDescriptor$FlushAction.START_FLUSH:Lorg/apache/hadoop/hbase/shaded/protobuf/generated/WALProtos$FlushDescriptor$FlushAction;
     168: invokevirtual #20                 // Method org/apache/hadoop/hbase/shaded/protobuf/generated/WALProtos$FlushDescriptor$FlushAction.ordinal:()I
     171: iconst_1
     172: iastore
     173: goto          177
     176: astore_0
     177: getstatic     #18                 // Field $SwitchMap$org$apache$hadoop$hbase$shaded$protobuf$generated$WALProtos$FlushDescriptor$FlushAction:[I
     180: getstatic     #21                 // Field org/apache/hadoop/hbase/shaded/protobuf/generated/WALProtos$FlushDescriptor$FlushAction.COMMIT_FLUSH:Lorg/apache/hadoop/hbase/shaded/protobuf/generated/WALProtos$FlushDescriptor$FlushAction;
     183: invokevirtual #20                 // Method org/apache/hadoop/hbase/shaded/protobuf/generated/WALProtos$FlushDescriptor$FlushAction.ordinal:()I
     186: iconst_2
     187: iastore
     188: goto          192
     191: astore_0
     192: getstatic     #18                 // Field $SwitchMap$org$apache$hadoop$hbase$shaded$protobuf$generated$WALProtos$FlushDescriptor$FlushAction:[I
     195: getstatic     #22                 // Field org/apache/hadoop/hbase/shaded/protobuf/generated/WALProtos$FlushDescriptor$FlushAction.ABORT_FLUSH:Lorg/apache/hadoop/hbase/shaded/protobuf/generated/WALProtos$FlushDescriptor$FlushAction;
     198: invokevirtual #20                 // Method org/apache/hadoop/hbase/shaded/protobuf/generated/WALProtos$FlushDescriptor$FlushAction.ordinal:()I
     201: iconst_3
     202: iastore
     203: goto          207
     206: astore_0
     207: getstatic     #18                 // Field $SwitchMap$org$apache$hadoop$hbase$shaded$protobuf$generated$WALProtos$FlushDescriptor$FlushAction:[I
     210: getstatic     #23                 // Field org/apache/hadoop/hbase/shaded/protobuf/generated/WALProtos$FlushDescriptor$FlushAction.CANNOT_FLUSH:Lorg/apache/hadoop/hbase/shaded/protobuf/generated/WALProtos$FlushDescriptor$FlushAction;
     213: invokevirtual #20                 // Method org/apache/hadoop/hbase/shaded/protobuf/generated/WALProtos$FlushDescriptor$FlushAction.ordinal:()I
     216: iconst_4
     217: iastore
     218: goto          222
     221: astore_0
     222: invokestatic  #24                 // Method org/apache/hadoop/hbase/CompareOperator.values:()[Lorg/apache/hadoop/hbase/CompareOperator;
     225: arraylength
     226: newarray       int
     228: putstatic     #25                 // Field $SwitchMap$org$apache$hadoop$hbase$CompareOperator:[I
     231: getstatic     #25                 // Field $SwitchMap$org$apache$hadoop$hbase$CompareOperator:[I
     234: getstatic     #26                 // Field org/apache/hadoop/hbase/CompareOperator.LESS:Lorg/apache/hadoop/hbase/CompareOperator;
     237: invokevirtual #27                 // Method org/apache/hadoop/hbase/CompareOperator.ordinal:()I
     240: iconst_1
     241: iastore
     242: goto          246
     245: astore_0
     246: getstatic     #25                 // Field $SwitchMap$org$apache$hadoop$hbase$CompareOperator:[I
     249: getstatic     #28                 // Field org/apache/hadoop/hbase/CompareOperator.LESS_OR_EQUAL:Lorg/apache/hadoop/hbase/CompareOperator;
     252: invokevirtual #27                 // Method org/apache/hadoop/hbase/CompareOperator.ordinal:()I
     255: iconst_2
     256: iastore
     257: goto          261
     260: astore_0
     261: getstatic     #25                 // Field $SwitchMap$org$apache$hadoop$hbase$CompareOperator:[I
     264: getstatic     #29                 // Field org/apache/hadoop/hbase/CompareOperator.EQUAL:Lorg/apache/hadoop/hbase/CompareOperator;
     267: invokevirtual #27                 // Method org/apache/hadoop/hbase/CompareOperator.ordinal:()I
     270: iconst_3
     271: iastore
     272: goto          276
     275: astore_0
     276: getstatic     #25                 // Field $SwitchMap$org$apache$hadoop$hbase$CompareOperator:[I
     279: getstatic     #30                 // Field org/apache/hadoop/hbase/CompareOperator.NOT_EQUAL:Lorg/apache/hadoop/hbase/CompareOperator;
     282: invokevirtual #27                 // Method org/apache/hadoop/hbase/CompareOperator.ordinal:()I
     285: iconst_4
     286: iastore
     287: goto          291
     290: astore_0
     291: getstatic     #25                 // Field $SwitchMap$org$apache$hadoop$hbase$CompareOperator:[I
     294: getstatic     #31                 // Field org/apache/hadoop/hbase/CompareOperator.GREATER_OR_EQUAL:Lorg/apache/hadoop/hbase/CompareOperator;
     297: invokevirtual #27                 // Method org/apache/hadoop/hbase/CompareOperator.ordinal:()I
     300: iconst_5
     301: iastore
     302: goto          306
     305: astore_0
     306: getstatic     #25                 // Field $SwitchMap$org$apache$hadoop$hbase$CompareOperator:[I
     309: getstatic     #32                 // Field org/apache/hadoop/hbase/CompareOperator.GREATER:Lorg/apache/hadoop/hbase/CompareOperator;
     312: invokevirtual #27                 // Method org/apache/hadoop/hbase/CompareOperator.ordinal:()I
     315: bipush        6
     317: iastore
     318: goto          322
     321: astore_0
     322: invokestatic  #33                 // Method org/apache/hadoop/hbase/HConstants$OperationStatusCode.values:()[Lorg/apache/hadoop/hbase/HConstants$OperationStatusCode;
     325: arraylength
     326: newarray       int
     328: putstatic     #34                 // Field $SwitchMap$org$apache$hadoop$hbase$HConstants$OperationStatusCode:[I
     331: getstatic     #34                 // Field $SwitchMap$org$apache$hadoop$hbase$HConstants$OperationStatusCode:[I
     334: getstatic     #35                 // Field org/apache/hadoop/hbase/HConstants$OperationStatusCode.SUCCESS:Lorg/apache/hadoop/hbase/HConstants$OperationStatusCode;
     337: invokevirtual #36                 // Method org/apache/hadoop/hbase/HConstants$OperationStatusCode.ordinal:()I
     340: iconst_1
     341: iastore
     342: goto          346
     345: astore_0
     346: getstatic     #34                 // Field $SwitchMap$org$apache$hadoop$hbase$HConstants$OperationStatusCode:[I
     349: getstatic     #37                 // Field org/apache/hadoop/hbase/HConstants$OperationStatusCode.FAILURE:Lorg/apache/hadoop/hbase/HConstants$OperationStatusCode;
     352: invokevirtual #36                 // Method org/apache/hadoop/hbase/HConstants$OperationStatusCode.ordinal:()I
     355: iconst_2
     356: iastore
     357: goto          361
     360: astore_0
     361: return
    Exception table:
       from    to  target type
           9    20    23   Class java/lang/NoSuchFieldError
          24    35    38   Class java/lang/NoSuchFieldError
          39    50    53   Class java/lang/NoSuchFieldError
          54    65    68   Class java/lang/NoSuchFieldError
          69    80    83   Class java/lang/NoSuchFieldError
          93   104   107   Class java/lang/NoSuchFieldError
         108   119   122   Class java/lang/NoSuchFieldError
         123   134   137   Class java/lang/NoSuchFieldError
         138   149   152   Class java/lang/NoSuchFieldError
         162   173   176   Class java/lang/NoSuchFieldError
         177   188   191   Class java/lang/NoSuchFieldError
         192   203   206   Class java/lang/NoSuchFieldError
         207   218   221   Class java/lang/NoSuchFieldError
         231   242   245   Class java/lang/NoSuchFieldError
         246   257   260   Class java/lang/NoSuchFieldError
         261   272   275   Class java/lang/NoSuchFieldError
         276   287   290   Class java/lang/NoSuchFieldError
         291   302   305   Class java/lang/NoSuchFieldError
         306   318   321   Class java/lang/NoSuchFieldError
         331   342   345   Class java/lang/NoSuchFieldError
         346   357   360   Class java/lang/NoSuchFieldError
}
