Compiled from "HStore.java"
final class org.apache.hadoop.hbase.regionserver.HStore$StoreFlusherImpl implements org.apache.hadoop.hbase.regionserver.StoreFlushContext {
  final org.apache.hadoop.hbase.regionserver.HStore this$0;

  public org.apache.hadoop.hbase.regionserver.MemStoreSize prepare();
    Code:
       0: aload_0
       1: aload_0
       2: getfield      #2                  // Field this$0:Lorg/apache/hadoop/hbase/regionserver/HStore;
       5: getfield      #6                  // Field org/apache/hadoop/hbase/regionserver/HStore.memstore:Lorg/apache/hadoop/hbase/regionserver/MemStore;
       8: invokeinterface #7,  1            // InterfaceMethod org/apache/hadoop/hbase/regionserver/MemStore.snapshot:()Lorg/apache/hadoop/hbase/regionserver/MemStoreSnapshot;
      13: putfield      #8                  // Field snapshot:Lorg/apache/hadoop/hbase/regionserver/MemStoreSnapshot;
      16: aload_0
      17: aload_0
      18: getfield      #8                  // Field snapshot:Lorg/apache/hadoop/hbase/regionserver/MemStoreSnapshot;
      21: invokevirtual #9                  // Method org/apache/hadoop/hbase/regionserver/MemStoreSnapshot.getCellsCount:()I
      24: i2l
      25: putfield      #10                 // Field cacheFlushCount:J
      28: aload_0
      29: aload_0
      30: getfield      #8                  // Field snapshot:Lorg/apache/hadoop/hbase/regionserver/MemStoreSnapshot;
      33: invokevirtual #11                 // Method org/apache/hadoop/hbase/regionserver/MemStoreSnapshot.getDataSize:()J
      36: putfield      #12                 // Field cacheFlushSize:J
      39: aload_0
      40: new           #13                 // class java/util/ArrayList
      43: dup
      44: iconst_1
      45: invokespecial #14                 // Method java/util/ArrayList."<init>":(I)V
      48: putfield      #15                 // Field committedFiles:Ljava/util/List;
      51: aload_0
      52: getfield      #8                  // Field snapshot:Lorg/apache/hadoop/hbase/regionserver/MemStoreSnapshot;
      55: invokevirtual #16                 // Method org/apache/hadoop/hbase/regionserver/MemStoreSnapshot.getMemStoreSize:()Lorg/apache/hadoop/hbase/regionserver/MemStoreSize;
      58: areturn

  public void flushCache(org.apache.hadoop.hbase.monitoring.MonitoredTask) throws java.io.IOException;
    Code:
       0: aload_0
       1: getfield      #2                  // Field this$0:Lorg/apache/hadoop/hbase/regionserver/HStore;
       4: getfield      #17                 // Field org/apache/hadoop/hbase/regionserver/HStore.region:Lorg/apache/hadoop/hbase/regionserver/HRegion;
       7: invokevirtual #18                 // Method org/apache/hadoop/hbase/regionserver/HRegion.getRegionServerServices:()Lorg/apache/hadoop/hbase/regionserver/RegionServerServices;
      10: astore_2
      11: aload_2
      12: ifnonnull     19
      15: aconst_null
      16: goto          25
      19: aload_2
      20: invokeinterface #19,  1           // InterfaceMethod org/apache/hadoop/hbase/regionserver/RegionServerServices.getFlushThroughputController:()Lorg/apache/hadoop/hbase/regionserver/throttle/ThroughputController;
      25: astore_3
      26: aload_0
      27: aload_0
      28: getfield      #2                  // Field this$0:Lorg/apache/hadoop/hbase/regionserver/HStore;
      31: aload_0
      32: getfield      #4                  // Field cacheFlushSeqNum:J
      35: aload_0
      36: getfield      #8                  // Field snapshot:Lorg/apache/hadoop/hbase/regionserver/MemStoreSnapshot;
      39: aload_1
      40: aload_3
      41: aload_0
      42: getfield      #5                  // Field tracker:Lorg/apache/hadoop/hbase/regionserver/FlushLifeCycleTracker;
      45: invokevirtual #20                 // Method org/apache/hadoop/hbase/regionserver/HStore.flushCache:(JLorg/apache/hadoop/hbase/regionserver/MemStoreSnapshot;Lorg/apache/hadoop/hbase/monitoring/MonitoredTask;Lorg/apache/hadoop/hbase/regionserver/throttle/ThroughputController;Lorg/apache/hadoop/hbase/regionserver/FlushLifeCycleTracker;)Ljava/util/List;
      48: putfield      #21                 // Field tempFiles:Ljava/util/List;
      51: return

  public boolean commit(org.apache.hadoop.hbase.monitoring.MonitoredTask) throws java.io.IOException;
    Code:
       0: aload_0
       1: getfield      #21                 // Field tempFiles:Ljava/util/List;
       4: invokestatic  #22                 // Method org/apache/hbase/thirdparty/org/apache/commons/collections4/CollectionUtils.isEmpty:(Ljava/util/Collection;)Z
       7: ifeq          12
      10: iconst_0
      11: ireturn
      12: new           #13                 // class java/util/ArrayList
      15: dup
      16: aload_0
      17: getfield      #21                 // Field tempFiles:Ljava/util/List;
      20: invokeinterface #23,  1           // InterfaceMethod java/util/List.size:()I
      25: invokespecial #14                 // Method java/util/ArrayList."<init>":(I)V
      28: astore_2
      29: aload_0
      30: getfield      #21                 // Field tempFiles:Ljava/util/List;
      33: invokeinterface #24,  1           // InterfaceMethod java/util/List.iterator:()Ljava/util/Iterator;
      38: astore_3
      39: aload_3
      40: invokeinterface #25,  1           // InterfaceMethod java/util/Iterator.hasNext:()Z
      45: ifeq          209
      48: aload_3
      49: invokeinterface #26,  1           // InterfaceMethod java/util/Iterator.next:()Ljava/lang/Object;
      54: checkcast     #27                 // class org/apache/hadoop/fs/Path
      57: astore        4
      59: aload_0
      60: getfield      #2                  // Field this$0:Lorg/apache/hadoop/hbase/regionserver/HStore;
      63: aload         4
      65: aload_0
      66: getfield      #4                  // Field cacheFlushSeqNum:J
      69: aload_1
      70: invokestatic  #28                 // Method org/apache/hadoop/hbase/regionserver/HStore.access$100:(Lorg/apache/hadoop/hbase/regionserver/HStore;Lorg/apache/hadoop/fs/Path;JLorg/apache/hadoop/hbase/monitoring/MonitoredTask;)Lorg/apache/hadoop/hbase/regionserver/HStoreFile;
      73: astore        5
      75: aload_0
      76: dup
      77: getfield      #29                 // Field outputFileSize:J
      80: aload         5
      82: invokevirtual #30                 // Method org/apache/hadoop/hbase/regionserver/HStoreFile.getReader:()Lorg/apache/hadoop/hbase/regionserver/StoreFileReader;
      85: invokevirtual #31                 // Method org/apache/hadoop/hbase/regionserver/StoreFileReader.length:()J
      88: ladd
      89: putfield      #29                 // Field outputFileSize:J
      92: aload_2
      93: aload         5
      95: invokeinterface #32,  2           // InterfaceMethod java/util/List.add:(Ljava/lang/Object;)Z
     100: pop
     101: goto          206
     104: astore        5
     106: invokestatic  #34                 // Method org/apache/hadoop/hbase/regionserver/HStore.access$200:()Lorg/slf4j/Logger;
     109: ldc           #35                 // String Failed to commit store file {}
     111: aload         4
     113: aload         5
     115: invokeinterface #36,  4           // InterfaceMethod org/slf4j/Logger.error:(Ljava/lang/String;Ljava/lang/Object;Ljava/lang/Object;)V
     120: aload_2
     121: invokeinterface #24,  1           // InterfaceMethod java/util/List.iterator:()Ljava/util/Iterator;
     126: astore        6
     128: aload         6
     130: invokeinterface #25,  1           // InterfaceMethod java/util/Iterator.hasNext:()Z
     135: ifeq          194
     138: aload         6
     140: invokeinterface #26,  1           // InterfaceMethod java/util/Iterator.next:()Ljava/lang/Object;
     145: checkcast     #37                 // class org/apache/hadoop/hbase/regionserver/HStoreFile
     148: astore        7
     150: aload         7
     152: invokevirtual #38                 // Method org/apache/hadoop/hbase/regionserver/HStoreFile.getPath:()Lorg/apache/hadoop/fs/Path;
     155: astore        8
     157: aload         7
     159: invokevirtual #39                 // Method org/apache/hadoop/hbase/regionserver/HStoreFile.deleteStoreFile:()V
     162: goto          191
     165: astore        9
     167: invokestatic  #34                 // Method org/apache/hadoop/hbase/regionserver/HStore.access$200:()Lorg/slf4j/Logger;
     170: getstatic     #40                 // Field org/apache/hadoop/hbase/log/HBaseMarkers.FATAL:Lorg/slf4j/Marker;
     173: ldc           #41                 // String Failed to delete store file we committed, halting {}
     175: aload         8
     177: aload         5
     179: invokeinterface #42,  5           // InterfaceMethod org/slf4j/Logger.error:(Lorg/slf4j/Marker;Ljava/lang/String;Ljava/lang/Object;Ljava/lang/Object;)V
     184: invokestatic  #43                 // Method java/lang/Runtime.getRuntime:()Ljava/lang/Runtime;
     187: iconst_1
     188: invokevirtual #44                 // Method java/lang/Runtime.halt:(I)V
     191: goto          128
     194: new           #33                 // class java/io/IOException
     197: dup
     198: ldc           #45                 // String Failed to commit the flush
     200: aload         5
     202: invokespecial #46                 // Method java/io/IOException."<init>":(Ljava/lang/String;Ljava/lang/Throwable;)V
     205: athrow
     206: goto          39
     209: aload_2
     210: invokeinterface #24,  1           // InterfaceMethod java/util/List.iterator:()Ljava/util/Iterator;
     215: astore_3
     216: aload_3
     217: invokeinterface #25,  1           // InterfaceMethod java/util/Iterator.hasNext:()Z
     222: ifeq          284
     225: aload_3
     226: invokeinterface #26,  1           // InterfaceMethod java/util/Iterator.next:()Ljava/lang/Object;
     231: checkcast     #37                 // class org/apache/hadoop/hbase/regionserver/HStoreFile
     234: astore        4
     236: aload_0
     237: getfield      #2                  // Field this$0:Lorg/apache/hadoop/hbase/regionserver/HStore;
     240: invokevirtual #47                 // Method org/apache/hadoop/hbase/regionserver/HStore.getCoprocessorHost:()Lorg/apache/hadoop/hbase/regionserver/RegionCoprocessorHost;
     243: ifnull        266
     246: aload_0
     247: getfield      #2                  // Field this$0:Lorg/apache/hadoop/hbase/regionserver/HStore;
     250: invokevirtual #47                 // Method org/apache/hadoop/hbase/regionserver/HStore.getCoprocessorHost:()Lorg/apache/hadoop/hbase/regionserver/RegionCoprocessorHost;
     253: aload_0
     254: getfield      #2                  // Field this$0:Lorg/apache/hadoop/hbase/regionserver/HStore;
     257: aload         4
     259: aload_0
     260: getfield      #5                  // Field tracker:Lorg/apache/hadoop/hbase/regionserver/FlushLifeCycleTracker;
     263: invokevirtual #48                 // Method org/apache/hadoop/hbase/regionserver/RegionCoprocessorHost.postFlush:(Lorg/apache/hadoop/hbase/regionserver/HStore;Lorg/apache/hadoop/hbase/regionserver/HStoreFile;Lorg/apache/hadoop/hbase/regionserver/FlushLifeCycleTracker;)V
     266: aload_0
     267: getfield      #15                 // Field committedFiles:Ljava/util/List;
     270: aload         4
     272: invokevirtual #38                 // Method org/apache/hadoop/hbase/regionserver/HStoreFile.getPath:()Lorg/apache/hadoop/fs/Path;
     275: invokeinterface #32,  2           // InterfaceMethod java/util/List.add:(Ljava/lang/Object;)Z
     280: pop
     281: goto          216
     284: aload_0
     285: getfield      #2                  // Field this$0:Lorg/apache/hadoop/hbase/regionserver/HStore;
     288: invokestatic  #49                 // Method org/apache/hadoop/hbase/regionserver/HStore.access$300:(Lorg/apache/hadoop/hbase/regionserver/HStore;)Ljava/util/concurrent/atomic/AtomicLong;
     291: aload_0
     292: getfield      #10                 // Field cacheFlushCount:J
     295: invokevirtual #50                 // Method java/util/concurrent/atomic/AtomicLong.addAndGet:(J)J
     298: pop2
     299: aload_0
     300: getfield      #2                  // Field this$0:Lorg/apache/hadoop/hbase/regionserver/HStore;
     303: invokestatic  #51                 // Method org/apache/hadoop/hbase/regionserver/HStore.access$400:(Lorg/apache/hadoop/hbase/regionserver/HStore;)Ljava/util/concurrent/atomic/AtomicLong;
     306: aload_0
     307: getfield      #12                 // Field cacheFlushSize:J
     310: invokevirtual #50                 // Method java/util/concurrent/atomic/AtomicLong.addAndGet:(J)J
     313: pop2
     314: aload_0
     315: getfield      #2                  // Field this$0:Lorg/apache/hadoop/hbase/regionserver/HStore;
     318: invokestatic  #52                 // Method org/apache/hadoop/hbase/regionserver/HStore.access$500:(Lorg/apache/hadoop/hbase/regionserver/HStore;)Ljava/util/concurrent/atomic/AtomicLong;
     321: aload_0
     322: getfield      #29                 // Field outputFileSize:J
     325: invokevirtual #50                 // Method java/util/concurrent/atomic/AtomicLong.addAndGet:(J)J
     328: pop2
     329: aload_0
     330: getfield      #2                  // Field this$0:Lorg/apache/hadoop/hbase/regionserver/HStore;
     333: aload_2
     334: aload_0
     335: getfield      #8                  // Field snapshot:Lorg/apache/hadoop/hbase/regionserver/MemStoreSnapshot;
     338: invokevirtual #53                 // Method org/apache/hadoop/hbase/regionserver/MemStoreSnapshot.getId:()J
     341: invokestatic  #54                 // Method org/apache/hadoop/hbase/regionserver/HStore.access$600:(Lorg/apache/hadoop/hbase/regionserver/HStore;Ljava/util/List;J)Z
     344: ireturn
    Exception table:
       from    to  target type
          59   101   104   Class java/io/IOException
         157   162   165   Class java/io/IOException

  public long getOutputFileSize();
    Code:
       0: aload_0
       1: getfield      #29                 // Field outputFileSize:J
       4: lreturn

  public java.util.List<org.apache.hadoop.fs.Path> getCommittedFiles();
    Code:
       0: aload_0
       1: getfield      #15                 // Field committedFiles:Ljava/util/List;
       4: areturn

  public void replayFlush(java.util.List<java.lang.String>, boolean) throws java.io.IOException;
    Code:
       0: new           #13                 // class java/util/ArrayList
       3: dup
       4: aload_1
       5: invokeinterface #23,  1           // InterfaceMethod java/util/List.size:()I
      10: invokespecial #14                 // Method java/util/ArrayList."<init>":(I)V
      13: astore_3
      14: aload_1
      15: invokeinterface #24,  1           // InterfaceMethod java/util/List.iterator:()Ljava/util/Iterator;
      20: astore        4
      22: aload         4
      24: invokeinterface #25,  1           // InterfaceMethod java/util/Iterator.hasNext:()Z
      29: ifeq          239
      32: aload         4
      34: invokeinterface #26,  1           // InterfaceMethod java/util/Iterator.next:()Ljava/lang/Object;
      39: checkcast     #55                 // class java/lang/String
      42: astore        5
      44: aload_0
      45: getfield      #2                  // Field this$0:Lorg/apache/hadoop/hbase/regionserver/HStore;
      48: invokestatic  #56                 // Method org/apache/hadoop/hbase/regionserver/HStore.access$700:(Lorg/apache/hadoop/hbase/regionserver/HStore;)Lorg/apache/hadoop/hbase/regionserver/HRegionFileSystem;
      51: aload_0
      52: getfield      #2                  // Field this$0:Lorg/apache/hadoop/hbase/regionserver/HStore;
      55: invokevirtual #57                 // Method org/apache/hadoop/hbase/regionserver/HStore.getColumnFamilyName:()Ljava/lang/String;
      58: aload         5
      60: invokevirtual #58                 // Method org/apache/hadoop/hbase/regionserver/HRegionFileSystem.getStoreFileInfo:(Ljava/lang/String;Ljava/lang/String;)Lorg/apache/hadoop/hbase/regionserver/StoreFileInfo;
      63: astore        6
      65: aload_0
      66: getfield      #2                  // Field this$0:Lorg/apache/hadoop/hbase/regionserver/HStore;
      69: aload         6
      71: invokestatic  #59                 // Method org/apache/hadoop/hbase/regionserver/HStore.access$800:(Lorg/apache/hadoop/hbase/regionserver/HStore;Lorg/apache/hadoop/hbase/regionserver/StoreFileInfo;)Lorg/apache/hadoop/hbase/regionserver/HStoreFile;
      74: astore        7
      76: aload_3
      77: aload         7
      79: invokeinterface #32,  2           // InterfaceMethod java/util/List.add:(Ljava/lang/Object;)Z
      84: pop
      85: aload_0
      86: getfield      #2                  // Field this$0:Lorg/apache/hadoop/hbase/regionserver/HStore;
      89: invokestatic  #60                 // Method org/apache/hadoop/hbase/regionserver/HStore.access$900:(Lorg/apache/hadoop/hbase/regionserver/HStore;)Ljava/util/concurrent/atomic/AtomicLong;
      92: aload         7
      94: invokevirtual #30                 // Method org/apache/hadoop/hbase/regionserver/HStoreFile.getReader:()Lorg/apache/hadoop/hbase/regionserver/StoreFileReader;
      97: invokevirtual #31                 // Method org/apache/hadoop/hbase/regionserver/StoreFileReader.length:()J
     100: invokevirtual #50                 // Method java/util/concurrent/atomic/AtomicLong.addAndGet:(J)J
     103: pop2
     104: aload_0
     105: getfield      #2                  // Field this$0:Lorg/apache/hadoop/hbase/regionserver/HStore;
     108: invokestatic  #61                 // Method org/apache/hadoop/hbase/regionserver/HStore.access$1000:(Lorg/apache/hadoop/hbase/regionserver/HStore;)Ljava/util/concurrent/atomic/AtomicLong;
     111: aload         7
     113: invokevirtual #30                 // Method org/apache/hadoop/hbase/regionserver/HStoreFile.getReader:()Lorg/apache/hadoop/hbase/regionserver/StoreFileReader;
     116: invokevirtual #62                 // Method org/apache/hadoop/hbase/regionserver/StoreFileReader.getTotalUncompressedBytes:()J
     119: invokevirtual #50                 // Method java/util/concurrent/atomic/AtomicLong.addAndGet:(J)J
     122: pop2
     123: invokestatic  #34                 // Method org/apache/hadoop/hbase/regionserver/HStore.access$200:()Lorg/slf4j/Logger;
     126: invokeinterface #63,  1           // InterfaceMethod org/slf4j/Logger.isInfoEnabled:()Z
     131: ifeq          236
     134: invokestatic  #34                 // Method org/apache/hadoop/hbase/regionserver/HStore.access$200:()Lorg/slf4j/Logger;
     137: new           #64                 // class java/lang/StringBuilder
     140: dup
     141: invokespecial #65                 // Method java/lang/StringBuilder."<init>":()V
     144: ldc           #66                 // String Region:
     146: invokevirtual #67                 // Method java/lang/StringBuilder.append:(Ljava/lang/String;)Ljava/lang/StringBuilder;
     149: aload_0
     150: getfield      #2                  // Field this$0:Lorg/apache/hadoop/hbase/regionserver/HStore;
     153: invokevirtual #68                 // Method org/apache/hadoop/hbase/regionserver/HStore.getRegionInfo:()Lorg/apache/hadoop/hbase/client/RegionInfo;
     156: invokeinterface #69,  1           // InterfaceMethod org/apache/hadoop/hbase/client/RegionInfo.getEncodedName:()Ljava/lang/String;
     161: invokevirtual #67                 // Method java/lang/StringBuilder.append:(Ljava/lang/String;)Ljava/lang/StringBuilder;
     164: ldc           #70                 // String  added
     166: invokevirtual #67                 // Method java/lang/StringBuilder.append:(Ljava/lang/String;)Ljava/lang/StringBuilder;
     169: aload         7
     171: invokevirtual #71                 // Method java/lang/StringBuilder.append:(Ljava/lang/Object;)Ljava/lang/StringBuilder;
     174: ldc           #72                 // String , entries=
     176: invokevirtual #67                 // Method java/lang/StringBuilder.append:(Ljava/lang/String;)Ljava/lang/StringBuilder;
     179: aload         7
     181: invokevirtual #30                 // Method org/apache/hadoop/hbase/regionserver/HStoreFile.getReader:()Lorg/apache/hadoop/hbase/regionserver/StoreFileReader;
     184: invokevirtual #73                 // Method org/apache/hadoop/hbase/regionserver/StoreFileReader.getEntries:()J
     187: invokevirtual #74                 // Method java/lang/StringBuilder.append:(J)Ljava/lang/StringBuilder;
     190: ldc           #75                 // String , sequenceid=
     192: invokevirtual #67                 // Method java/lang/StringBuilder.append:(Ljava/lang/String;)Ljava/lang/StringBuilder;
     195: aload         7
     197: invokevirtual #30                 // Method org/apache/hadoop/hbase/regionserver/HStoreFile.getReader:()Lorg/apache/hadoop/hbase/regionserver/StoreFileReader;
     200: invokevirtual #76                 // Method org/apache/hadoop/hbase/regionserver/StoreFileReader.getSequenceID:()J
     203: invokevirtual #74                 // Method java/lang/StringBuilder.append:(J)Ljava/lang/StringBuilder;
     206: ldc           #77                 // String , filesize=
     208: invokevirtual #67                 // Method java/lang/StringBuilder.append:(Ljava/lang/String;)Ljava/lang/StringBuilder;
     211: aload         7
     213: invokevirtual #30                 // Method org/apache/hadoop/hbase/regionserver/HStoreFile.getReader:()Lorg/apache/hadoop/hbase/regionserver/StoreFileReader;
     216: invokevirtual #31                 // Method org/apache/hadoop/hbase/regionserver/StoreFileReader.length:()J
     219: ldc           #78                 // String
     221: iconst_1
     222: invokestatic  #79                 // Method org/apache/hadoop/util/StringUtils$TraditionalBinaryPrefix.long2String:(JLjava/lang/String;I)Ljava/lang/String;
     225: invokevirtual #67                 // Method java/lang/StringBuilder.append:(Ljava/lang/String;)Ljava/lang/StringBuilder;
     228: invokevirtual #80                 // Method java/lang/StringBuilder.toString:()Ljava/lang/String;
     231: invokeinterface #81,  2           // InterfaceMethod org/slf4j/Logger.info:(Ljava/lang/String;)V
     236: goto          22
     239: ldc2_w        #82                 // long -1l
     242: lstore        4
     244: iload_2
     245: ifeq          271
     248: aload_0
     249: getfield      #8                  // Field snapshot:Lorg/apache/hadoop/hbase/regionserver/MemStoreSnapshot;
     252: ifnull        271
     255: aload_0
     256: getfield      #8                  // Field snapshot:Lorg/apache/hadoop/hbase/regionserver/MemStoreSnapshot;
     259: invokevirtual #53                 // Method org/apache/hadoop/hbase/regionserver/MemStoreSnapshot.getId:()J
     262: lstore        4
     264: aload_0
     265: getfield      #8                  // Field snapshot:Lorg/apache/hadoop/hbase/regionserver/MemStoreSnapshot;
     268: invokevirtual #84                 // Method org/apache/hadoop/hbase/regionserver/MemStoreSnapshot.close:()V
     271: aload_0
     272: getfield      #2                  // Field this$0:Lorg/apache/hadoop/hbase/regionserver/HStore;
     275: aload_3
     276: lload         4
     278: invokestatic  #54                 // Method org/apache/hadoop/hbase/regionserver/HStore.access$600:(Lorg/apache/hadoop/hbase/regionserver/HStore;Ljava/util/List;J)Z
     281: pop
     282: return

  public void abort() throws java.io.IOException;
    Code:
       0: aload_0
       1: getfield      #8                  // Field snapshot:Lorg/apache/hadoop/hbase/regionserver/MemStoreSnapshot;
       4: ifnull        32
       7: aload_0
       8: getfield      #8                  // Field snapshot:Lorg/apache/hadoop/hbase/regionserver/MemStoreSnapshot;
      11: invokevirtual #84                 // Method org/apache/hadoop/hbase/regionserver/MemStoreSnapshot.close:()V
      14: aload_0
      15: getfield      #2                  // Field this$0:Lorg/apache/hadoop/hbase/regionserver/HStore;
      18: invokestatic  #85                 // Method java/util/Collections.emptyList:()Ljava/util/List;
      21: aload_0
      22: getfield      #8                  // Field snapshot:Lorg/apache/hadoop/hbase/regionserver/MemStoreSnapshot;
      25: invokevirtual #53                 // Method org/apache/hadoop/hbase/regionserver/MemStoreSnapshot.getId:()J
      28: invokestatic  #54                 // Method org/apache/hadoop/hbase/regionserver/HStore.access$600:(Lorg/apache/hadoop/hbase/regionserver/HStore;Ljava/util/List;J)Z
      31: pop
      32: return

  org.apache.hadoop.hbase.regionserver.HStore$StoreFlusherImpl(org.apache.hadoop.hbase.regionserver.HStore, long, org.apache.hadoop.hbase.regionserver.FlushLifeCycleTracker, org.apache.hadoop.hbase.regionserver.HStore$1);
    Code:
       0: aload_0
       1: aload_1
       2: lload_2
       3: aload         4
       5: invokespecial #1                  // Method "<init>":(Lorg/apache/hadoop/hbase/regionserver/HStore;JLorg/apache/hadoop/hbase/regionserver/FlushLifeCycleTracker;)V
       8: return
}
