Compiled from "HTable.java"
class org.apache.hadoop.hbase.client.HTable$9 extends org.apache.hadoop.hbase.client.CancellableRegionServerCallable<org.apache.hadoop.hbase.client.SingleResponse> {
  final java.lang.String val$opName;

  final byte[] val$row;

  final byte[] val$family;

  final byte[] val$qualifier;

  final byte[] val$value;

  final org.apache.hadoop.hbase.io.TimeRange val$timeRange;

  final org.apache.hadoop.hbase.client.Delete val$delete;

  final org.apache.hadoop.hbase.client.HTable this$0;

  org.apache.hadoop.hbase.client.HTable$9(org.apache.hadoop.hbase.client.HTable, org.apache.hadoop.hbase.client.Connection, org.apache.hadoop.hbase.TableName, byte[], org.apache.hbase.thirdparty.com.google.protobuf.RpcController, int, org.apache.hadoop.hbase.client.RetryingTimeTracker, int, java.lang.String, byte[], byte[], byte[], byte[], org.apache.hadoop.hbase.io.TimeRange, org.apache.hadoop.hbase.client.Delete);
    Code:
       0: aload_0
       1: aload_1
       2: putfield      #1                  // Field this$0:Lorg/apache/hadoop/hbase/client/HTable;
       5: aload_0
       6: aload         9
       8: putfield      #2                  // Field val$opName:Ljava/lang/String;
      11: aload_0
      12: aload         10
      14: putfield      #3                  // Field val$row:[B
      17: aload_0
      18: aload         11
      20: putfield      #4                  // Field val$family:[B
      23: aload_0
      24: aload         12
      26: putfield      #5                  // Field val$qualifier:[B
      29: aload_0
      30: aload         13
      32: putfield      #6                  // Field val$value:[B
      35: aload_0
      36: aload         14
      38: putfield      #7                  // Field val$timeRange:Lorg/apache/hadoop/hbase/io/TimeRange;
      41: aload_0
      42: aload         15
      44: putfield      #8                  // Field val$delete:Lorg/apache/hadoop/hbase/client/Delete;
      47: aload_0
      48: aload_2
      49: aload_3
      50: aload         4
      52: aload         5
      54: iload         6
      56: aload         7
      58: iload         8
      60: invokespecial #9                  // Method org/apache/hadoop/hbase/client/CancellableRegionServerCallable."<init>":(Lorg/apache/hadoop/hbase/client/Connection;Lorg/apache/hadoop/hbase/TableName;[BLorg/apache/hbase/thirdparty/com/google/protobuf/RpcController;ILorg/apache/hadoop/hbase/client/RetryingTimeTracker;I)V
      63: return

  protected org.apache.hadoop.hbase.client.SingleResponse rpcCall() throws java.lang.Exception;
    Code:
       0: aload_0
       1: getfield      #2                  // Field val$opName:Ljava/lang/String;
       4: invokestatic  #10                 // Method org/apache/hadoop/hbase/shaded/protobuf/generated/HBaseProtos$CompareType.valueOf:(Ljava/lang/String;)Lorg/apache/hadoop/hbase/shaded/protobuf/generated/HBaseProtos$CompareType;
       7: astore_1
       8: aload_0
       9: invokevirtual #11                 // Method getLocation:()Lorg/apache/hadoop/hbase/HRegionLocation;
      12: invokevirtual #12                 // Method org/apache/hadoop/hbase/HRegionLocation.getRegionInfo:()Lorg/apache/hadoop/hbase/HRegionInfo;
      15: invokevirtual #13                 // Method org/apache/hadoop/hbase/HRegionInfo.getRegionName:()[B
      18: aload_0
      19: getfield      #3                  // Field val$row:[B
      22: aload_0
      23: getfield      #4                  // Field val$family:[B
      26: aload_0
      27: getfield      #5                  // Field val$qualifier:[B
      30: new           #14                 // class org/apache/hadoop/hbase/filter/BinaryComparator
      33: dup
      34: aload_0
      35: getfield      #6                  // Field val$value:[B
      38: invokespecial #15                 // Method org/apache/hadoop/hbase/filter/BinaryComparator."<init>":([B)V
      41: aload_1
      42: aload_0
      43: getfield      #7                  // Field val$timeRange:Lorg/apache/hadoop/hbase/io/TimeRange;
      46: aload_0
      47: getfield      #8                  // Field val$delete:Lorg/apache/hadoop/hbase/client/Delete;
      50: invokestatic  #16                 // Method org/apache/hadoop/hbase/shaded/protobuf/RequestConverter.buildMutateRequest:([B[B[B[BLorg/apache/hadoop/hbase/filter/ByteArrayComparable;Lorg/apache/hadoop/hbase/shaded/protobuf/generated/HBaseProtos$CompareType;Lorg/apache/hadoop/hbase/io/TimeRange;Lorg/apache/hadoop/hbase/client/Delete;)Lorg/apache/hadoop/hbase/shaded/protobuf/generated/ClientProtos$MutateRequest;
      53: astore_2
      54: aload_0
      55: aload_2
      56: invokevirtual #17                 // Method doMutate:(Lorg/apache/hadoop/hbase/shaded/protobuf/generated/ClientProtos$MutateRequest;)Lorg/apache/hadoop/hbase/shaded/protobuf/generated/ClientProtos$MutateResponse;
      59: astore_3
      60: aload_2
      61: aload_3
      62: aload_0
      63: invokevirtual #18                 // Method getRpcControllerCellScanner:()Lorg/apache/hadoop/hbase/CellScanner;
      66: invokestatic  #19                 // Method org/apache/hadoop/hbase/shaded/protobuf/ResponseConverter.getResult:(Lorg/apache/hadoop/hbase/shaded/protobuf/generated/ClientProtos$MutateRequest;Lorg/apache/hadoop/hbase/shaded/protobuf/generated/ClientProtos$MutateResponse;Lorg/apache/hadoop/hbase/CellScanner;)Lorg/apache/hadoop/hbase/client/SingleResponse;
      69: areturn

  protected java.lang.Object rpcCall() throws java.lang.Exception;
    Code:
       0: aload_0
       1: invokevirtual #20                 // Method rpcCall:()Lorg/apache/hadoop/hbase/client/SingleResponse;
       4: areturn
}
