Compiled from "HTable.java"
class org.apache.hadoop.hbase.client.HTable$13 implements org.apache.hadoop.hbase.client.coprocessor.Batch$Callback<R> {
  final java.util.Map val$results;

  final org.apache.hadoop.hbase.client.HTable this$0;

  org.apache.hadoop.hbase.client.HTable$13(org.apache.hadoop.hbase.client.HTable, java.util.Map);
    Code:
       0: aload_0
       1: aload_1
       2: putfield      #1                  // Field this$0:Lorg/apache/hadoop/hbase/client/HTable;
       5: aload_0
       6: aload_2
       7: putfield      #2                  // Field val$results:Ljava/util/Map;
      10: aload_0
      11: invokespecial #3                  // Method java/lang/Object."<init>":()V
      14: return

  public void update(byte[], byte[], R);
    Code:
       0: aload_1
       1: ifnull        16
       4: aload_0
       5: getfield      #2                  // Field val$results:Ljava/util/Map;
       8: aload_1
       9: aload_3
      10: invokeinterface #4,  3            // InterfaceMethod java/util/Map.put:(Ljava/lang/Object;Ljava/lang/Object;)Ljava/lang/Object;
      15: pop
      16: return

  public void update(byte[], byte[], java.lang.Object);
    Code:
       0: aload_0
       1: aload_1
       2: aload_2
       3: aload_3
       4: checkcast     #5                  // class com/google/protobuf/Message
       7: invokevirtual #6                  // Method update:([B[BLcom/google/protobuf/Message;)V
      10: return
}
