Compiled from "IdReadWriteLock.java"
class org.apache.hadoop.hbase.util.IdReadWriteLock$2 implements org.apache.hadoop.hbase.util.ObjectPool$ObjectFactory<T, java.util.concurrent.locks.ReentrantReadWriteLock> {
  final org.apache.hadoop.hbase.util.IdReadWriteLock this$0;

  org.apache.hadoop.hbase.util.IdReadWriteLock$2(org.apache.hadoop.hbase.util.IdReadWriteLock);
    Code:
       0: aload_0
       1: aload_1
       2: putfield      #1                  // Field this$0:Lorg/apache/hadoop/hbase/util/IdReadWriteLock;
       5: aload_0
       6: invokespecial #2                  // Method java/lang/Object."<init>":()V
       9: return

  public java.util.concurrent.locks.ReentrantReadWriteLock createObject(T);
    Code:
       0: new           #3                  // class java/util/concurrent/locks/ReentrantReadWriteLock
       3: dup
       4: invokespecial #4                  // Method java/util/concurrent/locks/ReentrantReadWriteLock."<init>":()V
       7: areturn

  public java.lang.Object createObject(java.lang.Object);
    Code:
       0: aload_0
       1: aload_1
       2: invokevirtual #5                  // Method createObject:(Ljava/lang/Object;)Ljava/util/concurrent/locks/ReentrantReadWriteLock;
       5: areturn
}
