Compiled from "ImmutableHColumnDescriptor.java"
public class org.apache.hadoop.hbase.client.ImmutableHColumnDescriptor extends org.apache.hadoop.hbase.HColumnDescriptor {
  org.apache.hadoop.hbase.client.ImmutableHColumnDescriptor(org.apache.hadoop.hbase.HColumnDescriptor);
    Code:
       0: aload_0
       1: aload_1
       2: iconst_0
       3: invokespecial #1                  // Method org/apache/hadoop/hbase/HColumnDescriptor."<init>":(Lorg/apache/hadoop/hbase/HColumnDescriptor;Z)V
       6: return

  public org.apache.hadoop.hbase.client.ImmutableHColumnDescriptor(org.apache.hadoop.hbase.client.ColumnFamilyDescriptor);
    Code:
       0: aload_0
       1: aload_1
       2: instanceof    #2                  // class org/apache/hadoop/hbase/client/ColumnFamilyDescriptorBuilder$ModifyableColumnFamilyDescriptor
       5: ifeq          15
       8: aload_1
       9: checkcast     #2                  // class org/apache/hadoop/hbase/client/ColumnFamilyDescriptorBuilder$ModifyableColumnFamilyDescriptor
      12: goto          23
      15: new           #2                  // class org/apache/hadoop/hbase/client/ColumnFamilyDescriptorBuilder$ModifyableColumnFamilyDescriptor
      18: dup
      19: aload_1
      20: invokespecial #3                  // Method org/apache/hadoop/hbase/client/ColumnFamilyDescriptorBuilder$ModifyableColumnFamilyDescriptor."<init>":(Lorg/apache/hadoop/hbase/client/ColumnFamilyDescriptor;)V
      23: invokespecial #4                  // Method org/apache/hadoop/hbase/HColumnDescriptor."<init>":(Lorg/apache/hadoop/hbase/client/ColumnFamilyDescriptorBuilder$ModifyableColumnFamilyDescriptor;)V
      26: return

  protected org.apache.hadoop.hbase.client.ColumnFamilyDescriptorBuilder$ModifyableColumnFamilyDescriptor getDelegateeForModification();
    Code:
       0: new           #5                  // class java/lang/UnsupportedOperationException
       3: dup
       4: ldc           #6                  // String HColumnDescriptor is read-only
       6: invokespecial #7                  // Method java/lang/UnsupportedOperationException."<init>":(Ljava/lang/String;)V
       9: athrow
}
