Compiled from "ImmutableHTableDescriptor.java"
public class org.apache.hadoop.hbase.client.ImmutableHTableDescriptor extends org.apache.hadoop.hbase.HTableDescriptor {
  protected org.apache.hadoop.hbase.HColumnDescriptor toHColumnDescriptor(org.apache.hadoop.hbase.client.ColumnFamilyDescriptor);
    Code:
       0: aload_1
       1: ifnonnull     6
       4: aconst_null
       5: areturn
       6: aload_1
       7: instanceof    #1                  // class org/apache/hadoop/hbase/HColumnDescriptor
      10: ifeq          25
      13: new           #2                  // class org/apache/hadoop/hbase/client/ImmutableHColumnDescriptor
      16: dup
      17: aload_1
      18: checkcast     #1                  // class org/apache/hadoop/hbase/HColumnDescriptor
      21: invokespecial #3                  // Method org/apache/hadoop/hbase/client/ImmutableHColumnDescriptor."<init>":(Lorg/apache/hadoop/hbase/HColumnDescriptor;)V
      24: areturn
      25: new           #2                  // class org/apache/hadoop/hbase/client/ImmutableHColumnDescriptor
      28: dup
      29: aload_1
      30: invokespecial #4                  // Method org/apache/hadoop/hbase/client/ImmutableHColumnDescriptor."<init>":(Lorg/apache/hadoop/hbase/client/ColumnFamilyDescriptor;)V
      33: areturn

  public org.apache.hadoop.hbase.client.ImmutableHTableDescriptor(org.apache.hadoop.hbase.HTableDescriptor);
    Code:
       0: aload_0
       1: aload_1
       2: iconst_0
       3: invokespecial #5                  // Method org/apache/hadoop/hbase/HTableDescriptor."<init>":(Lorg/apache/hadoop/hbase/HTableDescriptor;Z)V
       6: return

  public org.apache.hadoop.hbase.client.ImmutableHTableDescriptor(org.apache.hadoop.hbase.client.TableDescriptor);
    Code:
       0: aload_0
       1: aload_1
       2: instanceof    #6                  // class org/apache/hadoop/hbase/client/TableDescriptorBuilder$ModifyableTableDescriptor
       5: ifeq          15
       8: aload_1
       9: checkcast     #6                  // class org/apache/hadoop/hbase/client/TableDescriptorBuilder$ModifyableTableDescriptor
      12: goto          29
      15: new           #6                  // class org/apache/hadoop/hbase/client/TableDescriptorBuilder$ModifyableTableDescriptor
      18: dup
      19: aload_1
      20: invokeinterface #7,  1            // InterfaceMethod org/apache/hadoop/hbase/client/TableDescriptor.getTableName:()Lorg/apache/hadoop/hbase/TableName;
      25: aload_1
      26: invokespecial #8                  // Method org/apache/hadoop/hbase/client/TableDescriptorBuilder$ModifyableTableDescriptor."<init>":(Lorg/apache/hadoop/hbase/TableName;Lorg/apache/hadoop/hbase/client/TableDescriptor;)V
      29: invokespecial #9                  // Method org/apache/hadoop/hbase/HTableDescriptor."<init>":(Lorg/apache/hadoop/hbase/client/TableDescriptorBuilder$ModifyableTableDescriptor;)V
      32: return

  protected org.apache.hadoop.hbase.client.TableDescriptorBuilder$ModifyableTableDescriptor getDelegateeForModification();
    Code:
       0: new           #10                 // class java/lang/UnsupportedOperationException
       3: dup
       4: ldc           #11                 // String HTableDescriptor is read-only
       6: invokespecial #12                 // Method java/lang/UnsupportedOperationException."<init>":(Ljava/lang/String;)V
       9: athrow
}
