Compiled from "ImmutableHRegionInfo.java"
public class org.apache.hadoop.hbase.client.ImmutableHRegionInfo extends org.apache.hadoop.hbase.HRegionInfo {
  public org.apache.hadoop.hbase.client.ImmutableHRegionInfo(org.apache.hadoop.hbase.client.RegionInfo);
    Code:
       0: aload_0
       1: aload_1
       2: invokespecial #1                  // Method org/apache/hadoop/hbase/HRegionInfo."<init>":(Lorg/apache/hadoop/hbase/client/RegionInfo;)V
       5: return

  public void setSplit(boolean);
    Code:
       0: new           #2                  // class java/lang/UnsupportedOperationException
       3: dup
       4: ldc           #3                  // String HRegionInfo is read-only
       6: invokespecial #4                  // Method java/lang/UnsupportedOperationException."<init>":(Ljava/lang/String;)V
       9: athrow

  public void setOffline(boolean);
    Code:
       0: new           #2                  // class java/lang/UnsupportedOperationException
       3: dup
       4: ldc           #3                  // String HRegionInfo is read-only
       6: invokespecial #4                  // Method java/lang/UnsupportedOperationException."<init>":(Ljava/lang/String;)V
       9: athrow
}
