Compiled from "InclusiveCombinedBlockCache.java"
public class org.apache.hadoop.hbase.io.hfile.InclusiveCombinedBlockCache extends org.apache.hadoop.hbase.io.hfile.CombinedBlockCache {
  public org.apache.hadoop.hbase.io.hfile.InclusiveCombinedBlockCache(org.apache.hadoop.hbase.io.hfile.FirstLevelBlockCache, org.apache.hadoop.hbase.io.hfile.BlockCache);
    Code:
       0: aload_0
       1: aload_1
       2: aload_2
       3: invokespecial #1                  // Method org/apache/hadoop/hbase/io/hfile/CombinedBlockCache."<init>":(Lorg/apache/hadoop/hbase/io/hfile/FirstLevelBlockCache;Lorg/apache/hadoop/hbase/io/hfile/BlockCache;)V
       6: aload_1
       7: aload_2
       8: invokeinterface #2,  2            // InterfaceMethod org/apache/hadoop/hbase/io/hfile/FirstLevelBlockCache.setVictimCache:(Lorg/apache/hadoop/hbase/io/hfile/BlockCache;)V
      13: return

  public org.apache.hadoop.hbase.io.hfile.Cacheable getBlock(org.apache.hadoop.hbase.io.hfile.BlockCacheKey, boolean, boolean, boolean);
    Code:
       0: aload_0
       1: getfield      #3                  // Field l1Cache:Lorg/apache/hadoop/hbase/io/hfile/FirstLevelBlockCache;
       4: aload_1
       5: iload_2
       6: iload_3
       7: iload         4
       9: invokeinterface #4,  5            // InterfaceMethod org/apache/hadoop/hbase/io/hfile/FirstLevelBlockCache.getBlock:(Lorg/apache/hadoop/hbase/io/hfile/BlockCacheKey;ZZZ)Lorg/apache/hadoop/hbase/io/hfile/Cacheable;
      14: areturn

  public void cacheBlock(org.apache.hadoop.hbase.io.hfile.BlockCacheKey, org.apache.hadoop.hbase.io.hfile.Cacheable, boolean);
    Code:
       0: aload_0
       1: getfield      #3                  // Field l1Cache:Lorg/apache/hadoop/hbase/io/hfile/FirstLevelBlockCache;
       4: aload_1
       5: aload_2
       6: iload_3
       7: invokeinterface #5,  4            // InterfaceMethod org/apache/hadoop/hbase/io/hfile/FirstLevelBlockCache.cacheBlock:(Lorg/apache/hadoop/hbase/io/hfile/BlockCacheKey;Lorg/apache/hadoop/hbase/io/hfile/Cacheable;Z)V
      12: aload_0
      13: getfield      #6                  // Field l2Cache:Lorg/apache/hadoop/hbase/io/hfile/BlockCache;
      16: aload_1
      17: aload_2
      18: iload_3
      19: invokeinterface #7,  4            // InterfaceMethod org/apache/hadoop/hbase/io/hfile/BlockCache.cacheBlock:(Lorg/apache/hadoop/hbase/io/hfile/BlockCacheKey;Lorg/apache/hadoop/hbase/io/hfile/Cacheable;Z)V
      24: return

  public boolean evictBlock(org.apache.hadoop.hbase.io.hfile.BlockCacheKey);
    Code:
       0: aload_0
       1: getfield      #3                  // Field l1Cache:Lorg/apache/hadoop/hbase/io/hfile/FirstLevelBlockCache;
       4: aload_1
       5: invokeinterface #8,  2            // InterfaceMethod org/apache/hadoop/hbase/io/hfile/FirstLevelBlockCache.evictBlock:(Lorg/apache/hadoop/hbase/io/hfile/BlockCacheKey;)Z
      10: istore_2
      11: aload_0
      12: getfield      #6                  // Field l2Cache:Lorg/apache/hadoop/hbase/io/hfile/BlockCache;
      15: aload_1
      16: invokeinterface #9,  2            // InterfaceMethod org/apache/hadoop/hbase/io/hfile/BlockCache.evictBlock:(Lorg/apache/hadoop/hbase/io/hfile/BlockCacheKey;)Z
      21: istore_3
      22: iload_2
      23: ifne          30
      26: iload_3
      27: ifeq          34
      30: iconst_1
      31: goto          35
      34: iconst_0
      35: ireturn
}
