Compiled from "InitMetaProcedure.java"
public class org.apache.hadoop.hbase.master.procedure.InitMetaProcedure extends org.apache.hadoop.hbase.master.procedure.AbstractStateMachineTableProcedure<org.apache.hadoop.hbase.shaded.protobuf.generated.MasterProcedureProtos$InitMetaState> {
  public org.apache.hadoop.hbase.master.procedure.InitMetaProcedure();
    Code:
       0: aload_0
       1: invokespecial #1                  // Method org/apache/hadoop/hbase/master/procedure/AbstractStateMachineTableProcedure."<init>":()V
       4: aload_0
       5: new           #2                  // class java/util/concurrent/CountDownLatch
       8: dup
       9: iconst_1
      10: invokespecial #3                  // Method java/util/concurrent/CountDownLatch."<init>":(I)V
      13: putfield      #4                  // Field latch:Ljava/util/concurrent/CountDownLatch;
      16: return

  public org.apache.hadoop.hbase.TableName getTableName();
    Code:
       0: getstatic     #5                  // Field org/apache/hadoop/hbase/TableName.META_TABLE_NAME:Lorg/apache/hadoop/hbase/TableName;
       3: areturn

  public org.apache.hadoop.hbase.master.procedure.TableProcedureInterface$TableOperationType getTableOperationType();
    Code:
       0: getstatic     #6                  // Field org/apache/hadoop/hbase/master/procedure/TableProcedureInterface$TableOperationType.CREATE:Lorg/apache/hadoop/hbase/master/procedure/TableProcedureInterface$TableOperationType;
       3: areturn

  protected org.apache.hadoop.hbase.procedure2.StateMachineProcedure$Flow executeFromState(org.apache.hadoop.hbase.master.procedure.MasterProcedureEnv, org.apache.hadoop.hbase.shaded.protobuf.generated.MasterProcedureProtos$InitMetaState) throws org.apache.hadoop.hbase.procedure2.ProcedureSuspendedException, org.apache.hadoop.hbase.procedure2.ProcedureYieldException, java.lang.InterruptedException;
    Code:
       0: getstatic     #7                  // Field LOG:Lorg/slf4j/Logger;
       3: ldc           #8                  // String Execute {}
       5: aload_0
       6: invokeinterface #9,  3            // InterfaceMethod org/slf4j/Logger.debug:(Ljava/lang/String;Ljava/lang/Object;)V
      11: getstatic     #10                 // Field org/apache/hadoop/hbase/master/procedure/InitMetaProcedure$1.$SwitchMap$org$apache$hadoop$hbase$shaded$protobuf$generated$MasterProcedureProtos$InitMetaState:[I
      14: aload_2
      15: invokevirtual #11                 // Method org/apache/hadoop/hbase/shaded/protobuf/generated/MasterProcedureProtos$InitMetaState.ordinal:()I
      18: iaload
      19: lookupswitch  { // 2
                     1: 44
                     2: 89
               default: 228
          }
      44: getstatic     #7                  // Field LOG:Lorg/slf4j/Logger;
      47: ldc           #12                 // String Going to assign meta
      49: invokeinterface #13,  2           // InterfaceMethod org/slf4j/Logger.info:(Ljava/lang/String;)V
      54: aload_0
      55: aload_1
      56: invokevirtual #14                 // Method org/apache/hadoop/hbase/master/procedure/MasterProcedureEnv.getAssignmentManager:()Lorg/apache/hadoop/hbase/master/assignment/AssignmentManager;
      59: iconst_1
      60: anewarray     #15                 // class org/apache/hadoop/hbase/client/RegionInfo
      63: dup
      64: iconst_0
      65: getstatic     #16                 // Field org/apache/hadoop/hbase/client/RegionInfoBuilder.FIRST_META_REGIONINFO:Lorg/apache/hadoop/hbase/client/RegionInfo;
      68: aastore
      69: invokestatic  #17                 // Method java/util/Arrays.asList:([Ljava/lang/Object;)Ljava/util/List;
      72: invokevirtual #18                 // Method org/apache/hadoop/hbase/master/assignment/AssignmentManager.createAssignProcedures:(Ljava/util/List;)[Lorg/apache/hadoop/hbase/master/assignment/TransitRegionStateProcedure;
      75: invokevirtual #19                 // Method addChildProcedure:([Lorg/apache/hadoop/hbase/procedure2/Procedure;)V
      78: aload_0
      79: getstatic     #20                 // Field org/apache/hadoop/hbase/shaded/protobuf/generated/MasterProcedureProtos$InitMetaState.INIT_META_CREATE_NAMESPACES:Lorg/apache/hadoop/hbase/shaded/protobuf/generated/MasterProcedureProtos$InitMetaState;
      82: invokevirtual #21                 // Method setNextState:(Ljava/lang/Object;)V
      85: getstatic     #22                 // Field org/apache/hadoop/hbase/procedure2/StateMachineProcedure$Flow.HAS_MORE_STATE:Lorg/apache/hadoop/hbase/procedure2/StateMachineProcedure$Flow;
      88: areturn
      89: getstatic     #7                  // Field LOG:Lorg/slf4j/Logger;
      92: ldc           #23                 // String Going to create {} and {} namespaces
      94: getstatic     #24                 // Field org/apache/hadoop/hbase/NamespaceDescriptor.DEFAULT_NAMESPACE:Lorg/apache/hadoop/hbase/NamespaceDescriptor;
      97: getstatic     #25                 // Field org/apache/hadoop/hbase/NamespaceDescriptor.SYSTEM_NAMESPACE:Lorg/apache/hadoop/hbase/NamespaceDescriptor;
     100: invokeinterface #26,  4           // InterfaceMethod org/slf4j/Logger.info:(Ljava/lang/String;Ljava/lang/Object;Ljava/lang/Object;)V
     105: aload_1
     106: getstatic     #24                 // Field org/apache/hadoop/hbase/NamespaceDescriptor.DEFAULT_NAMESPACE:Lorg/apache/hadoop/hbase/NamespaceDescriptor;
     109: invokestatic  #27                 // Method org/apache/hadoop/hbase/master/procedure/AbstractStateMachineNamespaceProcedure.createDirectory:(Lorg/apache/hadoop/hbase/master/procedure/MasterProcedureEnv;Lorg/apache/hadoop/hbase/NamespaceDescriptor;)V
     112: aload_1
     113: getstatic     #25                 // Field org/apache/hadoop/hbase/NamespaceDescriptor.SYSTEM_NAMESPACE:Lorg/apache/hadoop/hbase/NamespaceDescriptor;
     116: invokestatic  #27                 // Method org/apache/hadoop/hbase/master/procedure/AbstractStateMachineNamespaceProcedure.createDirectory:(Lorg/apache/hadoop/hbase/master/procedure/MasterProcedureEnv;Lorg/apache/hadoop/hbase/NamespaceDescriptor;)V
     119: aload_1
     120: invokevirtual #28                 // Method org/apache/hadoop/hbase/master/procedure/MasterProcedureEnv.getMasterServices:()Lorg/apache/hadoop/hbase/master/MasterServices;
     123: invokeinterface #29,  1           // InterfaceMethod org/apache/hadoop/hbase/master/MasterServices.getConnection:()Lorg/apache/hadoop/hbase/client/Connection;
     128: getstatic     #24                 // Field org/apache/hadoop/hbase/NamespaceDescriptor.DEFAULT_NAMESPACE:Lorg/apache/hadoop/hbase/NamespaceDescriptor;
     131: invokestatic  #30                 // Method org/apache/hadoop/hbase/master/TableNamespaceManager.insertNamespaceToMeta:(Lorg/apache/hadoop/hbase/client/Connection;Lorg/apache/hadoop/hbase/NamespaceDescriptor;)V
     134: aload_1
     135: invokevirtual #28                 // Method org/apache/hadoop/hbase/master/procedure/MasterProcedureEnv.getMasterServices:()Lorg/apache/hadoop/hbase/master/MasterServices;
     138: invokeinterface #29,  1           // InterfaceMethod org/apache/hadoop/hbase/master/MasterServices.getConnection:()Lorg/apache/hadoop/hbase/client/Connection;
     143: getstatic     #25                 // Field org/apache/hadoop/hbase/NamespaceDescriptor.SYSTEM_NAMESPACE:Lorg/apache/hadoop/hbase/NamespaceDescriptor;
     146: invokestatic  #30                 // Method org/apache/hadoop/hbase/master/TableNamespaceManager.insertNamespaceToMeta:(Lorg/apache/hadoop/hbase/client/Connection;Lorg/apache/hadoop/hbase/NamespaceDescriptor;)V
     149: goto          224
     152: astore_3
     153: aload_0
     154: getfield      #32                 // Field retryCounter:Lorg/apache/hadoop/hbase/util/RetryCounter;
     157: ifnonnull     171
     160: aload_0
     161: aload_1
     162: invokevirtual #33                 // Method org/apache/hadoop/hbase/master/procedure/MasterProcedureEnv.getMasterConfiguration:()Lorg/apache/hadoop/conf/Configuration;
     165: invokestatic  #34                 // Method org/apache/hadoop/hbase/procedure2/ProcedureUtil.createRetryCounter:(Lorg/apache/hadoop/conf/Configuration;)Lorg/apache/hadoop/hbase/util/RetryCounter;
     168: putfield      #32                 // Field retryCounter:Lorg/apache/hadoop/hbase/util/RetryCounter;
     171: aload_0
     172: getfield      #32                 // Field retryCounter:Lorg/apache/hadoop/hbase/util/RetryCounter;
     175: invokevirtual #35                 // Method org/apache/hadoop/hbase/util/RetryCounter.getBackoffTimeAndIncrementAttempts:()J
     178: lstore        4
     180: getstatic     #7                  // Field LOG:Lorg/slf4j/Logger;
     183: ldc           #36                 // String Failed to init default and system namespaces, suspend {}secs
     185: lload         4
     187: invokestatic  #37                 // Method java/lang/Long.valueOf:(J)Ljava/lang/Long;
     190: aload_3
     191: invokeinterface #38,  4           // InterfaceMethod org/slf4j/Logger.warn:(Ljava/lang/String;Ljava/lang/Object;Ljava/lang/Object;)V
     196: aload_0
     197: lload         4
     199: invokestatic  #39                 // Method java/lang/Math.toIntExact:(J)I
     202: invokevirtual #40                 // Method setTimeout:(I)V
     205: aload_0
     206: getstatic     #41                 // Field org/apache/hadoop/hbase/shaded/protobuf/generated/ProcedureProtos$ProcedureState.WAITING_TIMEOUT:Lorg/apache/hadoop/hbase/shaded/protobuf/generated/ProcedureProtos$ProcedureState;
     209: invokevirtual #42                 // Method setState:(Lorg/apache/hadoop/hbase/shaded/protobuf/generated/ProcedureProtos$ProcedureState;)V
     212: aload_0
     213: invokevirtual #43                 // Method skipPersistence:()V
     216: new           #44                 // class org/apache/hadoop/hbase/procedure2/ProcedureSuspendedException
     219: dup
     220: invokespecial #45                 // Method org/apache/hadoop/hbase/procedure2/ProcedureSuspendedException."<init>":()V
     223: athrow
     224: getstatic     #46                 // Field org/apache/hadoop/hbase/procedure2/StateMachineProcedure$Flow.NO_MORE_STATE:Lorg/apache/hadoop/hbase/procedure2/StateMachineProcedure$Flow;
     227: areturn
     228: new           #47                 // class java/lang/UnsupportedOperationException
     231: dup
     232: new           #48                 // class java/lang/StringBuilder
     235: dup
     236: invokespecial #49                 // Method java/lang/StringBuilder."<init>":()V
     239: ldc           #50                 // String unhandled state=
     241: invokevirtual #51                 // Method java/lang/StringBuilder.append:(Ljava/lang/String;)Ljava/lang/StringBuilder;
     244: aload_2
     245: invokevirtual #52                 // Method java/lang/StringBuilder.append:(Ljava/lang/Object;)Ljava/lang/StringBuilder;
     248: invokevirtual #53                 // Method java/lang/StringBuilder.toString:()Ljava/lang/String;
     251: invokespecial #54                 // Method java/lang/UnsupportedOperationException."<init>":(Ljava/lang/String;)V
     254: athrow
    Exception table:
       from    to  target type
         105   149   152   Class java/io/IOException

  protected boolean waitInitialized(org.apache.hadoop.hbase.master.procedure.MasterProcedureEnv);
    Code:
       0: iconst_0
       1: ireturn

  protected synchronized boolean setTimeoutFailure(org.apache.hadoop.hbase.master.procedure.MasterProcedureEnv);
    Code:
       0: aload_0
       1: getstatic     #55                 // Field org/apache/hadoop/hbase/shaded/protobuf/generated/ProcedureProtos$ProcedureState.RUNNABLE:Lorg/apache/hadoop/hbase/shaded/protobuf/generated/ProcedureProtos$ProcedureState;
       4: invokevirtual #42                 // Method setState:(Lorg/apache/hadoop/hbase/shaded/protobuf/generated/ProcedureProtos$ProcedureState;)V
       7: aload_1
       8: invokevirtual #56                 // Method org/apache/hadoop/hbase/master/procedure/MasterProcedureEnv.getProcedureScheduler:()Lorg/apache/hadoop/hbase/master/procedure/MasterProcedureScheduler;
      11: aload_0
      12: invokevirtual #57                 // Method org/apache/hadoop/hbase/master/procedure/MasterProcedureScheduler.addFront:(Lorg/apache/hadoop/hbase/procedure2/Procedure;)V
      15: iconst_0
      16: ireturn

  protected org.apache.hadoop.hbase.procedure2.Procedure$LockState acquireLock(org.apache.hadoop.hbase.master.procedure.MasterProcedureEnv);
    Code:
       0: aload_1
       1: invokevirtual #56                 // Method org/apache/hadoop/hbase/master/procedure/MasterProcedureEnv.getProcedureScheduler:()Lorg/apache/hadoop/hbase/master/procedure/MasterProcedureScheduler;
       4: aload_0
       5: aload_0
       6: invokevirtual #58                 // Method getTableName:()Lorg/apache/hadoop/hbase/TableName;
       9: invokevirtual #59                 // Method org/apache/hadoop/hbase/master/procedure/MasterProcedureScheduler.waitTableExclusiveLock:(Lorg/apache/hadoop/hbase/procedure2/Procedure;Lorg/apache/hadoop/hbase/TableName;)Z
      12: ifeq          19
      15: getstatic     #60                 // Field org/apache/hadoop/hbase/procedure2/Procedure$LockState.LOCK_EVENT_WAIT:Lorg/apache/hadoop/hbase/procedure2/Procedure$LockState;
      18: areturn
      19: getstatic     #61                 // Field org/apache/hadoop/hbase/procedure2/Procedure$LockState.LOCK_ACQUIRED:Lorg/apache/hadoop/hbase/procedure2/Procedure$LockState;
      22: areturn

  protected void rollbackState(org.apache.hadoop.hbase.master.procedure.MasterProcedureEnv, org.apache.hadoop.hbase.shaded.protobuf.generated.MasterProcedureProtos$InitMetaState) throws java.io.IOException, java.lang.InterruptedException;
    Code:
       0: new           #47                 // class java/lang/UnsupportedOperationException
       3: dup
       4: invokespecial #62                 // Method java/lang/UnsupportedOperationException."<init>":()V
       7: athrow

  protected org.apache.hadoop.hbase.shaded.protobuf.generated.MasterProcedureProtos$InitMetaState getState(int);
    Code:
       0: iload_1
       1: invokestatic  #63                 // Method org/apache/hadoop/hbase/shaded/protobuf/generated/MasterProcedureProtos$InitMetaState.forNumber:(I)Lorg/apache/hadoop/hbase/shaded/protobuf/generated/MasterProcedureProtos$InitMetaState;
       4: areturn

  protected int getStateId(org.apache.hadoop.hbase.shaded.protobuf.generated.MasterProcedureProtos$InitMetaState);
    Code:
       0: aload_1
       1: invokevirtual #64                 // Method org/apache/hadoop/hbase/shaded/protobuf/generated/MasterProcedureProtos$InitMetaState.getNumber:()I
       4: ireturn

  protected org.apache.hadoop.hbase.shaded.protobuf.generated.MasterProcedureProtos$InitMetaState getInitialState();
    Code:
       0: getstatic     #65                 // Field org/apache/hadoop/hbase/shaded/protobuf/generated/MasterProcedureProtos$InitMetaState.INIT_META_ASSIGN_META:Lorg/apache/hadoop/hbase/shaded/protobuf/generated/MasterProcedureProtos$InitMetaState;
       3: areturn

  protected void serializeStateData(org.apache.hadoop.hbase.procedure2.ProcedureStateSerializer) throws java.io.IOException;
    Code:
       0: aload_0
       1: aload_1
       2: invokespecial #66                 // Method org/apache/hadoop/hbase/master/procedure/AbstractStateMachineTableProcedure.serializeStateData:(Lorg/apache/hadoop/hbase/procedure2/ProcedureStateSerializer;)V
       5: aload_1
       6: invokestatic  #67                 // Method org/apache/hadoop/hbase/shaded/protobuf/generated/MasterProcedureProtos$InitMetaStateData.getDefaultInstance:()Lorg/apache/hadoop/hbase/shaded/protobuf/generated/MasterProcedureProtos$InitMetaStateData;
       9: invokeinterface #68,  2           // InterfaceMethod org/apache/hadoop/hbase/procedure2/ProcedureStateSerializer.serialize:(Lorg/apache/hbase/thirdparty/com/google/protobuf/Message;)V
      14: return

  protected void deserializeStateData(org.apache.hadoop.hbase.procedure2.ProcedureStateSerializer) throws java.io.IOException;
    Code:
       0: aload_0
       1: aload_1
       2: invokespecial #69                 // Method org/apache/hadoop/hbase/master/procedure/AbstractStateMachineTableProcedure.deserializeStateData:(Lorg/apache/hadoop/hbase/procedure2/ProcedureStateSerializer;)V
       5: aload_1
       6: ldc           #70                 // class org/apache/hadoop/hbase/shaded/protobuf/generated/MasterProcedureProtos$InitMetaStateData
       8: invokeinterface #71,  2           // InterfaceMethod org/apache/hadoop/hbase/procedure2/ProcedureStateSerializer.deserialize:(Ljava/lang/Class;)Lorg/apache/hbase/thirdparty/com/google/protobuf/Message;
      13: pop
      14: return

  protected void completionCleanup(org.apache.hadoop.hbase.master.procedure.MasterProcedureEnv);
    Code:
       0: aload_0
       1: getfield      #4                  // Field latch:Ljava/util/concurrent/CountDownLatch;
       4: invokevirtual #72                 // Method java/util/concurrent/CountDownLatch.countDown:()V
       7: return

  public void await() throws java.lang.InterruptedException;
    Code:
       0: aload_0
       1: getfield      #4                  // Field latch:Ljava/util/concurrent/CountDownLatch;
       4: invokevirtual #73                 // Method java/util/concurrent/CountDownLatch.await:()V
       7: return

  protected java.lang.Object getInitialState();
    Code:
       0: aload_0
       1: invokevirtual #74                 // Method getInitialState:()Lorg/apache/hadoop/hbase/shaded/protobuf/generated/MasterProcedureProtos$InitMetaState;
       4: areturn

  protected int getStateId(java.lang.Object);
    Code:
       0: aload_0
       1: aload_1
       2: checkcast     #75                 // class org/apache/hadoop/hbase/shaded/protobuf/generated/MasterProcedureProtos$InitMetaState
       5: invokevirtual #76                 // Method getStateId:(Lorg/apache/hadoop/hbase/shaded/protobuf/generated/MasterProcedureProtos$InitMetaState;)I
       8: ireturn

  protected java.lang.Object getState(int);
    Code:
       0: aload_0
       1: iload_1
       2: invokevirtual #77                 // Method getState:(I)Lorg/apache/hadoop/hbase/shaded/protobuf/generated/MasterProcedureProtos$InitMetaState;
       5: areturn

  protected void rollbackState(java.lang.Object, java.lang.Object) throws java.io.IOException, java.lang.InterruptedException;
    Code:
       0: aload_0
       1: aload_1
       2: checkcast     #78                 // class org/apache/hadoop/hbase/master/procedure/MasterProcedureEnv
       5: aload_2
       6: checkcast     #75                 // class org/apache/hadoop/hbase/shaded/protobuf/generated/MasterProcedureProtos$InitMetaState
       9: invokevirtual #79                 // Method rollbackState:(Lorg/apache/hadoop/hbase/master/procedure/MasterProcedureEnv;Lorg/apache/hadoop/hbase/shaded/protobuf/generated/MasterProcedureProtos$InitMetaState;)V
      12: return

  protected org.apache.hadoop.hbase.procedure2.StateMachineProcedure$Flow executeFromState(java.lang.Object, java.lang.Object) throws org.apache.hadoop.hbase.procedure2.ProcedureSuspendedException, org.apache.hadoop.hbase.procedure2.ProcedureYieldException, java.lang.InterruptedException;
    Code:
       0: aload_0
       1: aload_1
       2: checkcast     #78                 // class org/apache/hadoop/hbase/master/procedure/MasterProcedureEnv
       5: aload_2
       6: checkcast     #75                 // class org/apache/hadoop/hbase/shaded/protobuf/generated/MasterProcedureProtos$InitMetaState
       9: invokevirtual #80                 // Method executeFromState:(Lorg/apache/hadoop/hbase/master/procedure/MasterProcedureEnv;Lorg/apache/hadoop/hbase/shaded/protobuf/generated/MasterProcedureProtos$InitMetaState;)Lorg/apache/hadoop/hbase/procedure2/StateMachineProcedure$Flow;
      12: areturn

  protected boolean setTimeoutFailure(java.lang.Object);
    Code:
       0: aload_0
       1: aload_1
       2: checkcast     #78                 // class org/apache/hadoop/hbase/master/procedure/MasterProcedureEnv
       5: invokevirtual #81                 // Method setTimeoutFailure:(Lorg/apache/hadoop/hbase/master/procedure/MasterProcedureEnv;)Z
       8: ireturn

  protected void completionCleanup(java.lang.Object);
    Code:
       0: aload_0
       1: aload_1
       2: checkcast     #78                 // class org/apache/hadoop/hbase/master/procedure/MasterProcedureEnv
       5: invokevirtual #82                 // Method completionCleanup:(Lorg/apache/hadoop/hbase/master/procedure/MasterProcedureEnv;)V
       8: return

  protected org.apache.hadoop.hbase.procedure2.Procedure$LockState acquireLock(java.lang.Object);
    Code:
       0: aload_0
       1: aload_1
       2: checkcast     #78                 // class org/apache/hadoop/hbase/master/procedure/MasterProcedureEnv
       5: invokevirtual #83                 // Method acquireLock:(Lorg/apache/hadoop/hbase/master/procedure/MasterProcedureEnv;)Lorg/apache/hadoop/hbase/procedure2/Procedure$LockState;
       8: areturn

  protected boolean waitInitialized(java.lang.Object);
    Code:
       0: aload_0
       1: aload_1
       2: checkcast     #78                 // class org/apache/hadoop/hbase/master/procedure/MasterProcedureEnv
       5: invokevirtual #84                 // Method waitInitialized:(Lorg/apache/hadoop/hbase/master/procedure/MasterProcedureEnv;)Z
       8: ireturn

  static {};
    Code:
       0: ldc           #85                 // class org/apache/hadoop/hbase/master/procedure/InitMetaProcedure
       2: invokestatic  #86                 // Method org/slf4j/LoggerFactory.getLogger:(Ljava/lang/Class;)Lorg/slf4j/Logger;
       5: putstatic     #7                  // Field LOG:Lorg/slf4j/Logger;
       8: return
}
