Compiled from "InstancePending.java"
class org.apache.hadoop.hbase.zookeeper.InstancePending<T> {
  static final boolean $assertionsDisabled;

  org.apache.hadoop.hbase.zookeeper.InstancePending();
    Code:
       0: aload_0
       1: invokespecial #1                  // Method java/lang/Object."<init>":()V
       4: aload_0
       5: new           #2                  // class java/util/concurrent/CountDownLatch
       8: dup
       9: iconst_1
      10: invokespecial #3                  // Method java/util/concurrent/CountDownLatch."<init>":(I)V
      13: putfield      #4                  // Field pendingLatch:Ljava/util/concurrent/CountDownLatch;
      16: return

  T get();
    Code:
       0: iconst_0
       1: istore_2
       2: aload_0
       3: getfield      #5                  // Field instanceHolder:Lorg/apache/hadoop/hbase/zookeeper/InstancePending$InstanceHolder;
       6: dup
       7: astore_1
       8: ifnonnull     27
      11: aload_0
      12: getfield      #4                  // Field pendingLatch:Ljava/util/concurrent/CountDownLatch;
      15: invokevirtual #6                  // Method java/util/concurrent/CountDownLatch.await:()V
      18: goto          2
      21: astore_3
      22: iconst_1
      23: istore_2
      24: goto          2
      27: iload_2
      28: ifeq          37
      31: invokestatic  #8                  // Method java/lang/Thread.currentThread:()Ljava/lang/Thread;
      34: invokevirtual #9                  // Method java/lang/Thread.interrupt:()V
      37: aload_1
      38: getfield      #10                 // Field org/apache/hadoop/hbase/zookeeper/InstancePending$InstanceHolder.instance:Ljava/lang/Object;
      41: areturn
    Exception table:
       from    to  target type
          11    18    21   Class java/lang/InterruptedException

  void prepare(T);
    Code:
       0: getstatic     #11                 // Field $assertionsDisabled:Z
       3: ifne          18
       6: aload_1
       7: ifnonnull     18
      10: new           #12                 // class java/lang/AssertionError
      13: dup
      14: invokespecial #13                 // Method java/lang/AssertionError."<init>":()V
      17: athrow
      18: aload_0
      19: new           #14                 // class org/apache/hadoop/hbase/zookeeper/InstancePending$InstanceHolder
      22: dup
      23: aload_1
      24: invokespecial #15                 // Method org/apache/hadoop/hbase/zookeeper/InstancePending$InstanceHolder."<init>":(Ljava/lang/Object;)V
      27: putfield      #5                  // Field instanceHolder:Lorg/apache/hadoop/hbase/zookeeper/InstancePending$InstanceHolder;
      30: aload_0
      31: getfield      #4                  // Field pendingLatch:Ljava/util/concurrent/CountDownLatch;
      34: invokevirtual #16                 // Method java/util/concurrent/CountDownLatch.countDown:()V
      37: return

  static {};
    Code:
       0: ldc           #17                 // class org/apache/hadoop/hbase/zookeeper/InstancePending
       2: invokevirtual #18                 // Method java/lang/Class.desiredAssertionStatus:()Z
       5: ifne          12
       8: iconst_1
       9: goto          13
      12: iconst_0
      13: putstatic     #11                 // Field $assertionsDisabled:Z
      16: return
}
