Compiled from "JMXJsonServlet.java"
public class org.apache.hadoop.hbase.http.jmx.JMXJsonServlet extends javax.servlet.http.HttpServlet {
  protected transient javax.management.MBeanServer mBeanServer;

  protected transient org.apache.hadoop.hbase.util.JSONBean jsonBeanWriter;

  public org.apache.hadoop.hbase.http.jmx.JMXJsonServlet();
    Code:
       0: aload_0
       1: invokespecial #1                  // Method javax/servlet/http/HttpServlet."<init>":()V
       4: return

  public void init() throws javax.servlet.ServletException;
    Code:
       0: aload_0
       1: invokestatic  #2                  // Method java/lang/management/ManagementFactory.getPlatformMBeanServer:()Ljavax/management/MBeanServer;
       4: putfield      #3                  // Field mBeanServer:Ljavax/management/MBeanServer;
       7: aload_0
       8: new           #4                  // class org/apache/hadoop/hbase/util/JSONBean
      11: dup
      12: invokespecial #5                  // Method org/apache/hadoop/hbase/util/JSONBean."<init>":()V
      15: putfield      #6                  // Field jsonBeanWriter:Lorg/apache/hadoop/hbase/util/JSONBean;
      18: return

  public void doGet(javax.servlet.http.HttpServletRequest, javax.servlet.http.HttpServletResponse) throws java.io.IOException;
    Code:
       0: aload_0
       1: invokevirtual #7                  // Method getServletContext:()Ljavax/servlet/ServletContext;
       4: aload_1
       5: aload_2
       6: invokestatic  #8                  // Method org/apache/hadoop/hbase/http/HttpServer.isInstrumentationAccessAllowed:(Ljavax/servlet/ServletContext;Ljavax/servlet/http/HttpServletRequest;Ljavax/servlet/http/HttpServletResponse;)Z
       9: ifne          13
      12: return
      13: aconst_null
      14: astore_3
      15: aconst_null
      16: astore        4
      18: aconst_null
      19: astore        5
      21: aload_0
      22: aload_1
      23: ldc           #10                 // String callback
      25: invokeinterface #11,  2           // InterfaceMethod javax/servlet/http/HttpServletRequest.getParameter:(Ljava/lang/String;)Ljava/lang/String;
      30: invokespecial #12                 // Method checkCallbackName:(Ljava/lang/String;)Ljava/lang/String;
      33: astore_3
      34: aload_2
      35: invokeinterface #13,  1           // InterfaceMethod javax/servlet/http/HttpServletResponse.getWriter:()Ljava/io/PrintWriter;
      40: astore        4
      42: aload_3
      43: ifnull        81
      46: aload_2
      47: ldc           #14                 // String application/javascript; charset=utf8
      49: invokeinterface #15,  2           // InterfaceMethod javax/servlet/http/HttpServletResponse.setContentType:(Ljava/lang/String;)V
      54: aload         4
      56: new           #16                 // class java/lang/StringBuilder
      59: dup
      60: invokespecial #17                 // Method java/lang/StringBuilder."<init>":()V
      63: aload_3
      64: invokevirtual #18                 // Method java/lang/StringBuilder.append:(Ljava/lang/String;)Ljava/lang/StringBuilder;
      67: ldc           #19                 // String (
      69: invokevirtual #18                 // Method java/lang/StringBuilder.append:(Ljava/lang/String;)Ljava/lang/StringBuilder;
      72: invokevirtual #20                 // Method java/lang/StringBuilder.toString:()Ljava/lang/String;
      75: invokevirtual #21                 // Method java/io/PrintWriter.write:(Ljava/lang/String;)V
      78: goto          89
      81: aload_2
      82: ldc           #22                 // String application/json; charset=utf8
      84: invokeinterface #15,  2           // InterfaceMethod javax/servlet/http/HttpServletResponse.setContentType:(Ljava/lang/String;)V
      89: aload_0
      90: getfield      #6                  // Field jsonBeanWriter:Lorg/apache/hadoop/hbase/util/JSONBean;
      93: aload         4
      95: invokevirtual #23                 // Method org/apache/hadoop/hbase/util/JSONBean.open:(Ljava/io/PrintWriter;)Lorg/apache/hadoop/hbase/util/JSONBean$Writer;
      98: astore        5
     100: aload_1
     101: ldc           #24                 // String description
     103: invokeinterface #11,  2           // InterfaceMethod javax/servlet/http/HttpServletRequest.getParameter:(Ljava/lang/String;)Ljava/lang/String;
     108: astore        6
     110: aload         6
     112: ifnull        127
     115: aload         6
     117: invokevirtual #25                 // Method java/lang/String.length:()I
     120: ifle          127
     123: iconst_1
     124: goto          128
     127: iconst_0
     128: istore        7
     130: aload_1
     131: ldc           #26                 // String get
     133: invokeinterface #11,  2           // InterfaceMethod javax/servlet/http/HttpServletRequest.getParameter:(Ljava/lang/String;)Ljava/lang/String;
     138: astore        8
     140: aload         8
     142: ifnull        314
     145: aload         8
     147: ldc           #27                 // String \:\:
     149: invokevirtual #28                 // Method java/lang/String.split:(Ljava/lang/String;)[Ljava/lang/String;
     152: astore        9
     154: aload         9
     156: arraylength
     157: iconst_2
     158: if_icmpeq     233
     161: aload         5
     163: ldc           #29                 // String result
     165: ldc           #30                 // String ERROR
     167: invokeinterface #31,  3           // InterfaceMethod org/apache/hadoop/hbase/util/JSONBean$Writer.write:(Ljava/lang/String;Ljava/lang/String;)V
     172: aload         5
     174: ldc           #32                 // String message
     176: ldc           #33                 // String query format is not as expected.
     178: invokeinterface #31,  3           // InterfaceMethod org/apache/hadoop/hbase/util/JSONBean$Writer.write:(Ljava/lang/String;Ljava/lang/String;)V
     183: aload         5
     185: invokeinterface #34,  1           // InterfaceMethod org/apache/hadoop/hbase/util/JSONBean$Writer.flush:()V
     190: aload_2
     191: sipush        400
     194: invokeinterface #36,  2           // InterfaceMethod javax/servlet/http/HttpServletResponse.setStatus:(I)V
     199: aload         5
     201: ifnull        211
     204: aload         5
     206: invokeinterface #37,  1           // InterfaceMethod org/apache/hadoop/hbase/util/JSONBean$Writer.close:()V
     211: aload_3
     212: ifnull        222
     215: aload         4
     217: ldc           #38                 // String );
     219: invokevirtual #21                 // Method java/io/PrintWriter.write:(Ljava/lang/String;)V
     222: aload         4
     224: ifnull        232
     227: aload         4
     229: invokevirtual #39                 // Method java/io/PrintWriter.close:()V
     232: return
     233: aload         5
     235: aload_0
     236: getfield      #3                  // Field mBeanServer:Ljavax/management/MBeanServer;
     239: new           #40                 // class javax/management/ObjectName
     242: dup
     243: aload         9
     245: iconst_0
     246: aaload
     247: invokespecial #41                 // Method javax/management/ObjectName."<init>":(Ljava/lang/String;)V
     250: aload         9
     252: iconst_1
     253: aaload
     254: iload         7
     256: invokeinterface #42,  5           // InterfaceMethod org/apache/hadoop/hbase/util/JSONBean$Writer.write:(Ljavax/management/MBeanServer;Ljavax/management/ObjectName;Ljava/lang/String;Z)I
     261: ifeq          280
     264: aload         5
     266: invokeinterface #34,  1           // InterfaceMethod org/apache/hadoop/hbase/util/JSONBean$Writer.flush:()V
     271: aload_2
     272: sipush        400
     275: invokeinterface #36,  2           // InterfaceMethod javax/servlet/http/HttpServletResponse.setStatus:(I)V
     280: aload         5
     282: ifnull        292
     285: aload         5
     287: invokeinterface #37,  1           // InterfaceMethod org/apache/hadoop/hbase/util/JSONBean$Writer.close:()V
     292: aload_3
     293: ifnull        303
     296: aload         4
     298: ldc           #38                 // String );
     300: invokevirtual #21                 // Method java/io/PrintWriter.write:(Ljava/lang/String;)V
     303: aload         4
     305: ifnull        313
     308: aload         4
     310: invokevirtual #39                 // Method java/io/PrintWriter.close:()V
     313: return
     314: aload_1
     315: ldc           #43                 // String qry
     317: invokeinterface #11,  2           // InterfaceMethod javax/servlet/http/HttpServletRequest.getParameter:(Ljava/lang/String;)Ljava/lang/String;
     322: astore        9
     324: aload         9
     326: ifnonnull     333
     329: ldc           #44                 // String *:*
     331: astore        9
     333: aload         5
     335: aload_0
     336: getfield      #3                  // Field mBeanServer:Ljavax/management/MBeanServer;
     339: new           #40                 // class javax/management/ObjectName
     342: dup
     343: aload         9
     345: invokespecial #41                 // Method javax/management/ObjectName."<init>":(Ljava/lang/String;)V
     348: aconst_null
     349: iload         7
     351: invokeinterface #42,  5           // InterfaceMethod org/apache/hadoop/hbase/util/JSONBean$Writer.write:(Ljavax/management/MBeanServer;Ljavax/management/ObjectName;Ljava/lang/String;Z)I
     356: ifeq          375
     359: aload         5
     361: invokeinterface #34,  1           // InterfaceMethod org/apache/hadoop/hbase/util/JSONBean$Writer.flush:()V
     366: aload_2
     367: sipush        400
     370: invokeinterface #36,  2           // InterfaceMethod javax/servlet/http/HttpServletResponse.setStatus:(I)V
     375: aload         5
     377: ifnull        387
     380: aload         5
     382: invokeinterface #37,  1           // InterfaceMethod org/apache/hadoop/hbase/util/JSONBean$Writer.close:()V
     387: aload_3
     388: ifnull        398
     391: aload         4
     393: ldc           #38                 // String );
     395: invokevirtual #21                 // Method java/io/PrintWriter.write:(Ljava/lang/String;)V
     398: aload         4
     400: ifnull        449
     403: aload         4
     405: invokevirtual #39                 // Method java/io/PrintWriter.close:()V
     408: goto          449
     411: astore        10
     413: aload         5
     415: ifnull        425
     418: aload         5
     420: invokeinterface #37,  1           // InterfaceMethod org/apache/hadoop/hbase/util/JSONBean$Writer.close:()V
     425: aload_3
     426: ifnull        436
     429: aload         4
     431: ldc           #38                 // String );
     433: invokevirtual #21                 // Method java/io/PrintWriter.write:(Ljava/lang/String;)V
     436: aload         4
     438: ifnull        446
     441: aload         4
     443: invokevirtual #39                 // Method java/io/PrintWriter.close:()V
     446: aload         10
     448: athrow
     449: goto          497
     452: astore_3
     453: getstatic     #46                 // Field LOG:Lorg/slf4j/Logger;
     456: ldc           #47                 // String Caught an exception while processing JMX request
     458: aload_3
     459: invokeinterface #48,  3           // InterfaceMethod org/slf4j/Logger.error:(Ljava/lang/String;Ljava/lang/Throwable;)V
     464: aload_2
     465: sipush        500
     468: invokeinterface #49,  2           // InterfaceMethod javax/servlet/http/HttpServletResponse.sendError:(I)V
     473: goto          497
     476: astore_3
     477: getstatic     #46                 // Field LOG:Lorg/slf4j/Logger;
     480: ldc           #47                 // String Caught an exception while processing JMX request
     482: aload_3
     483: invokeinterface #48,  3           // InterfaceMethod org/slf4j/Logger.error:(Ljava/lang/String;Ljava/lang/Throwable;)V
     488: aload_2
     489: sipush        400
     492: invokeinterface #49,  2           // InterfaceMethod javax/servlet/http/HttpServletResponse.sendError:(I)V
     497: return
    Exception table:
       from    to  target type
          21   199   411   any
         233   280   411   any
         314   375   411   any
         411   413   411   any
           0    12   452   Class java/io/IOException
          13   232   452   Class java/io/IOException
         233   313   452   Class java/io/IOException
         314   449   452   Class java/io/IOException
           0    12   476   Class javax/management/MalformedObjectNameException
          13   232   476   Class javax/management/MalformedObjectNameException
         233   313   476   Class javax/management/MalformedObjectNameException
         314   449   476   Class javax/management/MalformedObjectNameException

  static {};
    Code:
       0: ldc           #9                  // class org/apache/hadoop/hbase/http/jmx/JMXJsonServlet
       2: invokestatic  #55                 // Method org/slf4j/LoggerFactory.getLogger:(Ljava/lang/Class;)Lorg/slf4j/Logger;
       5: putstatic     #46                 // Field LOG:Lorg/slf4j/Logger;
       8: return
}
