Compiled from "JobUtil.java"
public abstract class org.apache.hadoop.hbase.mapreduce.JobUtil {
  protected org.apache.hadoop.hbase.mapreduce.JobUtil();
    Code:
       0: aload_0
       1: invokespecial #1                  // Method java/lang/Object."<init>":()V
       4: return

  public static org.apache.hadoop.fs.Path getStagingDir(org.apache.hadoop.conf.Configuration) throws java.io.IOException, java.lang.InterruptedException;
    Code:
       0: new           #2                  // class org/apache/hadoop/mapreduce/Cluster
       3: dup
       4: aload_0
       5: invokespecial #3                  // Method org/apache/hadoop/mapreduce/Cluster."<init>":(Lorg/apache/hadoop/conf/Configuration;)V
       8: aload_0
       9: invokestatic  #4                  // Method org/apache/hadoop/mapreduce/JobSubmissionFiles.getStagingDir:(Lorg/apache/hadoop/mapreduce/Cluster;Lorg/apache/hadoop/conf/Configuration;)Lorg/apache/hadoop/fs/Path;
      12: areturn

  static {};
    Code:
       0: ldc           #5                  // class org/apache/hadoop/hbase/mapreduce/JobUtil
       2: invokestatic  #6                  // Method org/slf4j/LoggerFactory.getLogger:(Ljava/lang/Class;)Lorg/slf4j/Logger;
       5: putstatic     #7                  // Field LOG:Lorg/slf4j/Logger;
       8: return
}
