Compiled from "JsonMapper.java"
public final class org.apache.hadoop.hbase.util.JsonMapper {
  public static java.lang.String writeMapAsString(java.util.Map<java.lang.String, java.lang.Object>) throws java.io.IOException;
    Code:
       0: aload_0
       1: invokestatic  #2                  // Method writeObjectAsString:(Ljava/lang/Object;)Ljava/lang/String;
       4: areturn

  public static java.lang.String writeObjectAsString(java.lang.Object) throws java.io.IOException;
    Code:
       0: getstatic     #3                  // Field GSON:Lorg/apache/hbase/thirdparty/com/google/gson/Gson;
       3: aload_0
       4: invokevirtual #4                  // Method org/apache/hbase/thirdparty/com/google/gson/Gson.toJson:(Ljava/lang/Object;)Ljava/lang/String;
       7: areturn

  static {};
    Code:
       0: invokestatic  #5                  // Method org/apache/hadoop/hbase/util/GsonUtil.createGson:()Lorg/apache/hbase/thirdparty/com/google/gson/GsonBuilder;
       3: invokevirtual #6                  // Method org/apache/hbase/thirdparty/com/google/gson/GsonBuilder.create:()Lorg/apache/hbase/thirdparty/com/google/gson/Gson;
       6: putstatic     #3                  // Field GSON:Lorg/apache/hbase/thirdparty/com/google/gson/Gson;
       9: return
}
