Compiled from "KeepDeletedCells.java"
public final class org.apache.hadoop.hbase.KeepDeletedCells extends java.lang.Enum<org.apache.hadoop.hbase.KeepDeletedCells> {
  public static final org.apache.hadoop.hbase.KeepDeletedCells FALSE;

  public static final org.apache.hadoop.hbase.KeepDeletedCells TRUE;

  public static final org.apache.hadoop.hbase.KeepDeletedCells TTL;

  public static org.apache.hadoop.hbase.KeepDeletedCells[] values();
    Code:
       0: getstatic     #1                  // Field $VALUES:[Lorg/apache/hadoop/hbase/KeepDeletedCells;
       3: invokevirtual #2                  // Method "[Lorg/apache/hadoop/hbase/KeepDeletedCells;".clone:()Ljava/lang/Object;
       6: checkcast     #3                  // class "[Lorg/apache/hadoop/hbase/KeepDeletedCells;"
       9: areturn

  public static org.apache.hadoop.hbase.KeepDeletedCells valueOf(java.lang.String);
    Code:
       0: ldc           #4                  // class org/apache/hadoop/hbase/KeepDeletedCells
       2: aload_0
       3: invokestatic  #5                  // Method java/lang/Enum.valueOf:(Ljava/lang/Class;Ljava/lang/String;)Ljava/lang/Enum;
       6: checkcast     #4                  // class org/apache/hadoop/hbase/KeepDeletedCells
       9: areturn

  public static org.apache.hadoop.hbase.KeepDeletedCells getValue(java.lang.String);
    Code:
       0: aload_0
       1: invokevirtual #7                  // Method java/lang/String.toUpperCase:()Ljava/lang/String;
       4: invokestatic  #8                  // Method valueOf:(Ljava/lang/String;)Lorg/apache/hadoop/hbase/KeepDeletedCells;
       7: areturn

  static {};
    Code:
       0: new           #4                  // class org/apache/hadoop/hbase/KeepDeletedCells
       3: dup
       4: ldc           #9                  // String FALSE
       6: iconst_0
       7: invokespecial #10                 // Method "<init>":(Ljava/lang/String;I)V
      10: putstatic     #11                 // Field FALSE:Lorg/apache/hadoop/hbase/KeepDeletedCells;
      13: new           #4                  // class org/apache/hadoop/hbase/KeepDeletedCells
      16: dup
      17: ldc           #12                 // String TRUE
      19: iconst_1
      20: invokespecial #10                 // Method "<init>":(Ljava/lang/String;I)V
      23: putstatic     #13                 // Field TRUE:Lorg/apache/hadoop/hbase/KeepDeletedCells;
      26: new           #4                  // class org/apache/hadoop/hbase/KeepDeletedCells
      29: dup
      30: ldc           #14                 // String TTL
      32: iconst_2
      33: invokespecial #10                 // Method "<init>":(Ljava/lang/String;I)V
      36: putstatic     #15                 // Field TTL:Lorg/apache/hadoop/hbase/KeepDeletedCells;
      39: iconst_3
      40: anewarray     #4                  // class org/apache/hadoop/hbase/KeepDeletedCells
      43: dup
      44: iconst_0
      45: getstatic     #11                 // Field FALSE:Lorg/apache/hadoop/hbase/KeepDeletedCells;
      48: aastore
      49: dup
      50: iconst_1
      51: getstatic     #13                 // Field TRUE:Lorg/apache/hadoop/hbase/KeepDeletedCells;
      54: aastore
      55: dup
      56: iconst_2
      57: getstatic     #15                 // Field TTL:Lorg/apache/hadoop/hbase/KeepDeletedCells;
      60: aastore
      61: putstatic     #1                  // Field $VALUES:[Lorg/apache/hadoop/hbase/KeepDeletedCells;
      64: return
}
