Compiled from "KeyValueScanFixture.java"
public class org.apache.hadoop.hbase.regionserver.KeyValueScanFixture extends org.apache.hadoop.hbase.util.CollectionBackedScanner {
  public org.apache.hadoop.hbase.regionserver.KeyValueScanFixture(org.apache.hadoop.hbase.CellComparator, org.apache.hadoop.hbase.Cell...);
    Code:
       0: aload_0
       1: aload_1
       2: aload_2
       3: invokespecial #1                  // Method org/apache/hadoop/hbase/util/CollectionBackedScanner."<init>":(Lorg/apache/hadoop/hbase/CellComparator;[Lorg/apache/hadoop/hbase/Cell;)V
       6: return

  public static java.util.List<org.apache.hadoop.hbase.regionserver.KeyValueScanner> scanFixture(org.apache.hadoop.hbase.KeyValue[]...);
    Code:
       0: new           #2                  // class java/util/ArrayList
       3: dup
       4: invokespecial #3                  // Method java/util/ArrayList."<init>":()V
       7: astore_1
       8: aload_0
       9: astore_2
      10: aload_2
      11: arraylength
      12: istore_3
      13: iconst_0
      14: istore        4
      16: iload         4
      18: iload_3
      19: if_icmpge     51
      22: aload_2
      23: iload         4
      25: aaload
      26: astore        5
      28: aload_1
      29: new           #4                  // class org/apache/hadoop/hbase/regionserver/KeyValueScanFixture
      32: dup
      33: invokestatic  #5                  // InterfaceMethod org/apache/hadoop/hbase/CellComparator.getInstance:()Lorg/apache/hadoop/hbase/CellComparator;
      36: aload         5
      38: invokespecial #6                  // Method "<init>":(Lorg/apache/hadoop/hbase/CellComparator;[Lorg/apache/hadoop/hbase/Cell;)V
      41: invokevirtual #7                  // Method java/util/ArrayList.add:(Ljava/lang/Object;)Z
      44: pop
      45: iinc          4, 1
      48: goto          16
      51: aload_1
      52: areturn
}
