Compiled from "KeyValue.java"
public final class org.apache.hadoop.hbase.KeyValue$Type extends java.lang.Enum<org.apache.hadoop.hbase.KeyValue$Type> {
  public static final org.apache.hadoop.hbase.KeyValue$Type Minimum;

  public static final org.apache.hadoop.hbase.KeyValue$Type Put;

  public static final org.apache.hadoop.hbase.KeyValue$Type Delete;

  public static final org.apache.hadoop.hbase.KeyValue$Type DeleteFamilyVersion;

  public static final org.apache.hadoop.hbase.KeyValue$Type DeleteColumn;

  public static final org.apache.hadoop.hbase.KeyValue$Type DeleteFamily;

  public static final org.apache.hadoop.hbase.KeyValue$Type Maximum;

  public static org.apache.hadoop.hbase.KeyValue$Type[] values();
    Code:
       0: getstatic     #1                  // Field $VALUES:[Lorg/apache/hadoop/hbase/KeyValue$Type;
       3: invokevirtual #2                  // Method "[Lorg/apache/hadoop/hbase/KeyValue$Type;".clone:()Ljava/lang/Object;
       6: checkcast     #3                  // class "[Lorg/apache/hadoop/hbase/KeyValue$Type;"
       9: areturn

  public static org.apache.hadoop.hbase.KeyValue$Type valueOf(java.lang.String);
    Code:
       0: ldc           #4                  // class org/apache/hadoop/hbase/KeyValue$Type
       2: aload_0
       3: invokestatic  #5                  // Method java/lang/Enum.valueOf:(Ljava/lang/Class;Ljava/lang/String;)Ljava/lang/Enum;
       6: checkcast     #4                  // class org/apache/hadoop/hbase/KeyValue$Type
       9: areturn

  public byte getCode();
    Code:
       0: aload_0
       1: getfield      #7                  // Field code:B
       4: ireturn

  static boolean isValidType(byte);
    Code:
       0: getstatic     #8                  // Field codeArray:[Lorg/apache/hadoop/hbase/KeyValue$Type;
       3: iload_0
       4: sipush        255
       7: iand
       8: aaload
       9: ifnull        16
      12: iconst_1
      13: goto          17
      16: iconst_0
      17: ireturn

  public static org.apache.hadoop.hbase.KeyValue$Type codeToType(byte);
    Code:
       0: getstatic     #8                  // Field codeArray:[Lorg/apache/hadoop/hbase/KeyValue$Type;
       3: iload_0
       4: sipush        255
       7: iand
       8: aaload
       9: astore_1
      10: aload_1
      11: ifnull        16
      14: aload_1
      15: areturn
      16: new           #9                  // class java/lang/RuntimeException
      19: dup
      20: new           #10                 // class java/lang/StringBuilder
      23: dup
      24: invokespecial #11                 // Method java/lang/StringBuilder."<init>":()V
      27: ldc           #12                 // String Unknown code
      29: invokevirtual #13                 // Method java/lang/StringBuilder.append:(Ljava/lang/String;)Ljava/lang/StringBuilder;
      32: iload_0
      33: invokevirtual #14                 // Method java/lang/StringBuilder.append:(I)Ljava/lang/StringBuilder;
      36: invokevirtual #15                 // Method java/lang/StringBuilder.toString:()Ljava/lang/String;
      39: invokespecial #16                 // Method java/lang/RuntimeException."<init>":(Ljava/lang/String;)V
      42: athrow

  static {};
    Code:
       0: new           #4                  // class org/apache/hadoop/hbase/KeyValue$Type
       3: dup
       4: ldc           #17                 // String Minimum
       6: iconst_0
       7: iconst_0
       8: invokespecial #18                 // Method "<init>":(Ljava/lang/String;IB)V
      11: putstatic     #19                 // Field Minimum:Lorg/apache/hadoop/hbase/KeyValue$Type;
      14: new           #4                  // class org/apache/hadoop/hbase/KeyValue$Type
      17: dup
      18: ldc           #20                 // String Put
      20: iconst_1
      21: iconst_4
      22: invokespecial #18                 // Method "<init>":(Ljava/lang/String;IB)V
      25: putstatic     #21                 // Field Put:Lorg/apache/hadoop/hbase/KeyValue$Type;
      28: new           #4                  // class org/apache/hadoop/hbase/KeyValue$Type
      31: dup
      32: ldc           #22                 // String Delete
      34: iconst_2
      35: bipush        8
      37: invokespecial #18                 // Method "<init>":(Ljava/lang/String;IB)V
      40: putstatic     #23                 // Field Delete:Lorg/apache/hadoop/hbase/KeyValue$Type;
      43: new           #4                  // class org/apache/hadoop/hbase/KeyValue$Type
      46: dup
      47: ldc           #24                 // String DeleteFamilyVersion
      49: iconst_3
      50: bipush        10
      52: invokespecial #18                 // Method "<init>":(Ljava/lang/String;IB)V
      55: putstatic     #25                 // Field DeleteFamilyVersion:Lorg/apache/hadoop/hbase/KeyValue$Type;
      58: new           #4                  // class org/apache/hadoop/hbase/KeyValue$Type
      61: dup
      62: ldc           #26                 // String DeleteColumn
      64: iconst_4
      65: bipush        12
      67: invokespecial #18                 // Method "<init>":(Ljava/lang/String;IB)V
      70: putstatic     #27                 // Field DeleteColumn:Lorg/apache/hadoop/hbase/KeyValue$Type;
      73: new           #4                  // class org/apache/hadoop/hbase/KeyValue$Type
      76: dup
      77: ldc           #28                 // String DeleteFamily
      79: iconst_5
      80: bipush        14
      82: invokespecial #18                 // Method "<init>":(Ljava/lang/String;IB)V
      85: putstatic     #29                 // Field DeleteFamily:Lorg/apache/hadoop/hbase/KeyValue$Type;
      88: new           #4                  // class org/apache/hadoop/hbase/KeyValue$Type
      91: dup
      92: ldc           #30                 // String Maximum
      94: bipush        6
      96: iconst_m1
      97: invokespecial #18                 // Method "<init>":(Ljava/lang/String;IB)V
     100: putstatic     #31                 // Field Maximum:Lorg/apache/hadoop/hbase/KeyValue$Type;
     103: bipush        7
     105: anewarray     #4                  // class org/apache/hadoop/hbase/KeyValue$Type
     108: dup
     109: iconst_0
     110: getstatic     #19                 // Field Minimum:Lorg/apache/hadoop/hbase/KeyValue$Type;
     113: aastore
     114: dup
     115: iconst_1
     116: getstatic     #21                 // Field Put:Lorg/apache/hadoop/hbase/KeyValue$Type;
     119: aastore
     120: dup
     121: iconst_2
     122: getstatic     #23                 // Field Delete:Lorg/apache/hadoop/hbase/KeyValue$Type;
     125: aastore
     126: dup
     127: iconst_3
     128: getstatic     #25                 // Field DeleteFamilyVersion:Lorg/apache/hadoop/hbase/KeyValue$Type;
     131: aastore
     132: dup
     133: iconst_4
     134: getstatic     #27                 // Field DeleteColumn:Lorg/apache/hadoop/hbase/KeyValue$Type;
     137: aastore
     138: dup
     139: iconst_5
     140: getstatic     #29                 // Field DeleteFamily:Lorg/apache/hadoop/hbase/KeyValue$Type;
     143: aastore
     144: dup
     145: bipush        6
     147: getstatic     #31                 // Field Maximum:Lorg/apache/hadoop/hbase/KeyValue$Type;
     150: aastore
     151: putstatic     #1                  // Field $VALUES:[Lorg/apache/hadoop/hbase/KeyValue$Type;
     154: sipush        256
     157: anewarray     #4                  // class org/apache/hadoop/hbase/KeyValue$Type
     160: putstatic     #8                  // Field codeArray:[Lorg/apache/hadoop/hbase/KeyValue$Type;
     163: invokestatic  #32                 // Method values:()[Lorg/apache/hadoop/hbase/KeyValue$Type;
     166: astore_0
     167: aload_0
     168: arraylength
     169: istore_1
     170: iconst_0
     171: istore_2
     172: iload_2
     173: iload_1
     174: if_icmpge     200
     177: aload_0
     178: iload_2
     179: aaload
     180: astore_3
     181: getstatic     #8                  // Field codeArray:[Lorg/apache/hadoop/hbase/KeyValue$Type;
     184: aload_3
     185: getfield      #7                  // Field code:B
     188: sipush        255
     191: iand
     192: aload_3
     193: aastore
     194: iinc          2, 1
     197: goto          172
     200: return
}
