Compiled from "KeyValueCodecWithTags.java"
public class org.apache.hadoop.hbase.codec.KeyValueCodecWithTags$ByteBuffKeyValueDecoder extends org.apache.hadoop.hbase.codec.KeyValueCodec$ByteBuffKeyValueDecoder {
  public org.apache.hadoop.hbase.codec.KeyValueCodecWithTags$ByteBuffKeyValueDecoder(org.apache.hadoop.hbase.nio.ByteBuff);
    Code:
       0: aload_0
       1: aload_1
       2: invokespecial #1                  // Method org/apache/hadoop/hbase/codec/KeyValueCodec$ByteBuffKeyValueDecoder."<init>":(Lorg/apache/hadoop/hbase/nio/ByteBuff;)V
       5: return

  protected org.apache.hadoop.hbase.Cell createCell(byte[], int, int);
    Code:
       0: new           #2                  // class org/apache/hadoop/hbase/KeyValue
       3: dup
       4: aload_1
       5: iload_2
       6: iload_3
       7: invokespecial #3                  // Method org/apache/hadoop/hbase/KeyValue."<init>":([BII)V
      10: areturn

  protected org.apache.hadoop.hbase.Cell createCell(java.nio.ByteBuffer, int, int);
    Code:
       0: new           #4                  // class org/apache/hadoop/hbase/ByteBufferKeyValue
       3: dup
       4: aload_1
       5: iload_2
       6: iload_3
       7: invokespecial #5                  // Method org/apache/hadoop/hbase/ByteBufferKeyValue."<init>":(Ljava/nio/ByteBuffer;II)V
      10: areturn
}
