Compiled from "Leases.java"
public class org.apache.hadoop.hbase.regionserver.Leases extends org.apache.hadoop.hbase.util.HasThread {
  public static final int MIN_WAIT_TIME;

  protected final int leaseCheckFrequency;

  protected volatile boolean stopRequested;

  public org.apache.hadoop.hbase.regionserver.Leases(int);
    Code:
       0: aload_0
       1: ldc           #1                  // String RegionServerLeases
       3: invokespecial #2                  // Method org/apache/hadoop/hbase/util/HasThread."<init>":(Ljava/lang/String;)V
       6: aload_0
       7: new           #3                  // class java/util/concurrent/ConcurrentHashMap
      10: dup
      11: invokespecial #4                  // Method java/util/concurrent/ConcurrentHashMap."<init>":()V
      14: putfield      #5                  // Field leases:Ljava/util/Map;
      17: aload_0
      18: iconst_0
      19: putfield      #6                  // Field stopRequested:Z
      22: aload_0
      23: iload_1
      24: putfield      #7                  // Field leaseCheckFrequency:I
      27: aload_0
      28: iconst_1
      29: invokevirtual #8                  // Method setDaemon:(Z)V
      32: return

  public void run();
    Code:
       0: aload_0
       1: getfield      #7                  // Field leaseCheckFrequency:I
       4: i2l
       5: lstore_1
       6: aconst_null
       7: astore_3
       8: ldc2_w        #10                 // long 9223372036854775807l
      11: lstore        4
      13: aload_0
      14: getfield      #6                  // Field stopRequested:Z
      17: ifeq          39
      20: aload_0
      21: getfield      #6                  // Field stopRequested:Z
      24: ifeq          267
      27: aload_0
      28: getfield      #5                  // Field leases:Ljava/util/Map;
      31: invokeinterface #12,  1           // InterfaceMethod java/util/Map.isEmpty:()Z
      36: ifne          267
      39: aload_3
      40: ifnull        51
      43: aload_3
      44: getstatic     #13                 // Field java/util/concurrent/TimeUnit.MILLISECONDS:Ljava/util/concurrent/TimeUnit;
      47: invokevirtual #14                 // Method org/apache/hadoop/hbase/regionserver/Leases$Lease.getDelay:(Ljava/util/concurrent/TimeUnit;)J
      50: lstore_1
      51: aload_0
      52: getfield      #7                  // Field leaseCheckFrequency:I
      55: i2l
      56: lload_1
      57: invokestatic  #15                 // Method java/lang/Math.min:(JJ)J
      60: lstore_1
      61: ldc2_w        #17                 // long 100l
      64: lload_1
      65: invokestatic  #19                 // Method java/lang/Math.max:(JJ)J
      68: lstore_1
      69: lload_1
      70: invokestatic  #20                 // Method java/lang/Thread.sleep:(J)V
      73: goto          106
      76: astore        6
      78: goto          13
      81: astore        6
      83: goto          13
      86: astore        6
      88: getstatic     #24                 // Field LOG:Lorg/slf4j/Logger;
      91: getstatic     #25                 // Field org/apache/hadoop/hbase/log/HBaseMarkers.FATAL:Lorg/slf4j/Marker;
      94: ldc           #26                 // String Unexpected exception killed leases thread
      96: aload         6
      98: invokeinterface #27,  4           // InterfaceMethod org/slf4j/Logger.error:(Lorg/slf4j/Marker;Ljava/lang/String;Ljava/lang/Throwable;)V
     103: goto          267
     106: aconst_null
     107: astore_3
     108: ldc2_w        #10                 // long 9223372036854775807l
     111: lstore        4
     113: aload_0
     114: getfield      #5                  // Field leases:Ljava/util/Map;
     117: invokeinterface #28,  1           // InterfaceMethod java/util/Map.entrySet:()Ljava/util/Set;
     122: invokeinterface #29,  1           // InterfaceMethod java/util/Set.iterator:()Ljava/util/Iterator;
     127: astore        6
     129: aload         6
     131: invokeinterface #30,  1           // InterfaceMethod java/util/Iterator.hasNext:()Z
     136: ifeq          264
     139: aload         6
     141: invokeinterface #31,  1           // InterfaceMethod java/util/Iterator.next:()Ljava/lang/Object;
     146: checkcast     #32                 // class java/util/Map$Entry
     149: astore        7
     151: aload         7
     153: invokeinterface #33,  1           // InterfaceMethod java/util/Map$Entry.getValue:()Ljava/lang/Object;
     158: checkcast     #34                 // class org/apache/hadoop/hbase/regionserver/Leases$Lease
     161: astore        8
     163: aload         8
     165: getstatic     #13                 // Field java/util/concurrent/TimeUnit.MILLISECONDS:Ljava/util/concurrent/TimeUnit;
     168: invokevirtual #14                 // Method org/apache/hadoop/hbase/regionserver/Leases$Lease.getDelay:(Ljava/util/concurrent/TimeUnit;)J
     171: lstore        9
     173: lload         9
     175: lconst_0
     176: lcmp
     177: ifle          202
     180: aload_3
     181: ifnull        192
     184: lload         9
     186: lload         4
     188: lcmp
     189: ifge          261
     192: aload         8
     194: astore_3
     195: lload         9
     197: lstore        4
     199: goto          261
     202: aload         8
     204: invokevirtual #35                 // Method org/apache/hadoop/hbase/regionserver/Leases$Lease.getListener:()Lorg/apache/hadoop/hbase/regionserver/LeaseListener;
     207: ifnonnull     244
     210: getstatic     #24                 // Field LOG:Lorg/slf4j/Logger;
     213: new           #36                 // class java/lang/StringBuilder
     216: dup
     217: invokespecial #37                 // Method java/lang/StringBuilder."<init>":()V
     220: ldc           #38                 // String lease listener is null for lease
     222: invokevirtual #39                 // Method java/lang/StringBuilder.append:(Ljava/lang/String;)Ljava/lang/StringBuilder;
     225: aload         8
     227: invokevirtual #40                 // Method org/apache/hadoop/hbase/regionserver/Leases$Lease.getLeaseName:()Ljava/lang/String;
     230: invokevirtual #39                 // Method java/lang/StringBuilder.append:(Ljava/lang/String;)Ljava/lang/StringBuilder;
     233: invokevirtual #41                 // Method java/lang/StringBuilder.toString:()Ljava/lang/String;
     236: invokeinterface #42,  2           // InterfaceMethod org/slf4j/Logger.error:(Ljava/lang/String;)V
     241: goto          254
     244: aload         8
     246: invokevirtual #35                 // Method org/apache/hadoop/hbase/regionserver/Leases$Lease.getListener:()Lorg/apache/hadoop/hbase/regionserver/LeaseListener;
     249: invokeinterface #43,  1           // InterfaceMethod org/apache/hadoop/hbase/regionserver/LeaseListener.leaseExpired:()V
     254: aload         6
     256: invokeinterface #44,  1           // InterfaceMethod java/util/Iterator.remove:()V
     261: goto          129
     264: goto          13
     267: aload_0
     268: invokevirtual #45                 // Method close:()V
     271: return
    Exception table:
       from    to  target type
          39    73    76   Class java/lang/InterruptedException
          39    73    81   Class java/util/ConcurrentModificationException
          39    73    86   Class java/lang/Throwable

  public void closeAfterLeasesExpire();
    Code:
       0: aload_0
       1: iconst_1
       2: putfield      #6                  // Field stopRequested:Z
       5: return

  public void close();
    Code:
       0: aload_0
       1: iconst_1
       2: putfield      #6                  // Field stopRequested:Z
       5: aload_0
       6: getfield      #5                  // Field leases:Ljava/util/Map;
       9: invokeinterface #46,  1           // InterfaceMethod java/util/Map.clear:()V
      14: getstatic     #24                 // Field LOG:Lorg/slf4j/Logger;
      17: ldc           #47                 // String Closed leases
      19: invokeinterface #48,  2           // InterfaceMethod org/slf4j/Logger.info:(Ljava/lang/String;)V
      24: return

  public org.apache.hadoop.hbase.regionserver.Leases$Lease createLease(java.lang.String, int, org.apache.hadoop.hbase.regionserver.LeaseListener) throws org.apache.hadoop.hbase.regionserver.Leases$LeaseStillHeldException;
    Code:
       0: new           #34                 // class org/apache/hadoop/hbase/regionserver/Leases$Lease
       3: dup
       4: aload_1
       5: iload_2
       6: aload_3
       7: invokespecial #49                 // Method org/apache/hadoop/hbase/regionserver/Leases$Lease."<init>":(Ljava/lang/String;ILorg/apache/hadoop/hbase/regionserver/LeaseListener;)V
      10: astore        4
      12: aload_0
      13: aload         4
      15: invokevirtual #50                 // Method addLease:(Lorg/apache/hadoop/hbase/regionserver/Leases$Lease;)V
      18: aload         4
      20: areturn

  public void addLease(org.apache.hadoop.hbase.regionserver.Leases$Lease) throws org.apache.hadoop.hbase.regionserver.Leases$LeaseStillHeldException;
    Code:
       0: aload_0
       1: getfield      #6                  // Field stopRequested:Z
       4: ifeq          8
       7: return
       8: aload_0
       9: getfield      #5                  // Field leases:Ljava/util/Map;
      12: aload_1
      13: invokevirtual #40                 // Method org/apache/hadoop/hbase/regionserver/Leases$Lease.getLeaseName:()Ljava/lang/String;
      16: invokeinterface #51,  2           // InterfaceMethod java/util/Map.containsKey:(Ljava/lang/Object;)Z
      21: ifeq          36
      24: new           #52                 // class org/apache/hadoop/hbase/regionserver/Leases$LeaseStillHeldException
      27: dup
      28: aload_1
      29: invokevirtual #40                 // Method org/apache/hadoop/hbase/regionserver/Leases$Lease.getLeaseName:()Ljava/lang/String;
      32: invokespecial #53                 // Method org/apache/hadoop/hbase/regionserver/Leases$LeaseStillHeldException."<init>":(Ljava/lang/String;)V
      35: athrow
      36: aload_1
      37: invokevirtual #54                 // Method org/apache/hadoop/hbase/regionserver/Leases$Lease.resetExpirationTime:()V
      40: aload_0
      41: getfield      #5                  // Field leases:Ljava/util/Map;
      44: aload_1
      45: invokevirtual #40                 // Method org/apache/hadoop/hbase/regionserver/Leases$Lease.getLeaseName:()Ljava/lang/String;
      48: aload_1
      49: invokeinterface #55,  3           // InterfaceMethod java/util/Map.put:(Ljava/lang/Object;Ljava/lang/Object;)Ljava/lang/Object;
      54: pop
      55: return

  public void renewLease(java.lang.String) throws org.apache.hadoop.hbase.regionserver.LeaseException;
    Code:
       0: aload_0
       1: getfield      #6                  // Field stopRequested:Z
       4: ifeq          8
       7: return
       8: aload_0
       9: getfield      #5                  // Field leases:Ljava/util/Map;
      12: aload_1
      13: invokeinterface #56,  2           // InterfaceMethod java/util/Map.get:(Ljava/lang/Object;)Ljava/lang/Object;
      18: checkcast     #34                 // class org/apache/hadoop/hbase/regionserver/Leases$Lease
      21: astore_2
      22: aload_2
      23: ifnonnull     58
      26: new           #57                 // class org/apache/hadoop/hbase/regionserver/LeaseException
      29: dup
      30: new           #36                 // class java/lang/StringBuilder
      33: dup
      34: invokespecial #37                 // Method java/lang/StringBuilder."<init>":()V
      37: ldc           #58                 // String lease '
      39: invokevirtual #39                 // Method java/lang/StringBuilder.append:(Ljava/lang/String;)Ljava/lang/StringBuilder;
      42: aload_1
      43: invokevirtual #39                 // Method java/lang/StringBuilder.append:(Ljava/lang/String;)Ljava/lang/StringBuilder;
      46: ldc           #59                 // String ' does not exist or has already expired
      48: invokevirtual #39                 // Method java/lang/StringBuilder.append:(Ljava/lang/String;)Ljava/lang/StringBuilder;
      51: invokevirtual #41                 // Method java/lang/StringBuilder.toString:()Ljava/lang/String;
      54: invokespecial #60                 // Method org/apache/hadoop/hbase/regionserver/LeaseException."<init>":(Ljava/lang/String;)V
      57: athrow
      58: aload_2
      59: invokevirtual #54                 // Method org/apache/hadoop/hbase/regionserver/Leases$Lease.resetExpirationTime:()V
      62: return

  public void cancelLease(java.lang.String) throws org.apache.hadoop.hbase.regionserver.LeaseException;
    Code:
       0: aload_0
       1: aload_1
       2: invokevirtual #61                 // Method removeLease:(Ljava/lang/String;)Lorg/apache/hadoop/hbase/regionserver/Leases$Lease;
       5: pop
       6: return

  org.apache.hadoop.hbase.regionserver.Leases$Lease removeLease(java.lang.String) throws org.apache.hadoop.hbase.regionserver.LeaseException;
    Code:
       0: aload_0
       1: getfield      #5                  // Field leases:Ljava/util/Map;
       4: aload_1
       5: invokeinterface #62,  2           // InterfaceMethod java/util/Map.remove:(Ljava/lang/Object;)Ljava/lang/Object;
      10: checkcast     #34                 // class org/apache/hadoop/hbase/regionserver/Leases$Lease
      13: astore_2
      14: aload_2
      15: ifnonnull     50
      18: new           #57                 // class org/apache/hadoop/hbase/regionserver/LeaseException
      21: dup
      22: new           #36                 // class java/lang/StringBuilder
      25: dup
      26: invokespecial #37                 // Method java/lang/StringBuilder."<init>":()V
      29: ldc           #58                 // String lease '
      31: invokevirtual #39                 // Method java/lang/StringBuilder.append:(Ljava/lang/String;)Ljava/lang/StringBuilder;
      34: aload_1
      35: invokevirtual #39                 // Method java/lang/StringBuilder.append:(Ljava/lang/String;)Ljava/lang/StringBuilder;
      38: ldc           #63                 // String ' does not exist
      40: invokevirtual #39                 // Method java/lang/StringBuilder.append:(Ljava/lang/String;)Ljava/lang/StringBuilder;
      43: invokevirtual #41                 // Method java/lang/StringBuilder.toString:()Ljava/lang/String;
      46: invokespecial #60                 // Method org/apache/hadoop/hbase/regionserver/LeaseException."<init>":(Ljava/lang/String;)V
      49: athrow
      50: aload_2
      51: areturn

  static {};
    Code:
       0: ldc           #16                 // class org/apache/hadoop/hbase/regionserver/Leases
       2: invokevirtual #64                 // Method java/lang/Class.getName:()Ljava/lang/String;
       5: invokestatic  #65                 // Method org/slf4j/LoggerFactory.getLogger:(Ljava/lang/String;)Lorg/slf4j/Logger;
       8: putstatic     #24                 // Field LOG:Lorg/slf4j/Logger;
      11: return
}
