Compiled from "LoadBalancerPerformanceEvaluation.java"
public class org.apache.hadoop.hbase.master.balancer.LoadBalancerPerformanceEvaluation extends org.apache.hadoop.hbase.util.AbstractHBaseTool {
  protected static final org.apache.hadoop.hbase.HBaseCommonTestingUtility UTIL;

  public org.apache.hadoop.hbase.master.balancer.LoadBalancerPerformanceEvaluation();
    Code:
       0: aload_0
       1: invokespecial #1                  // Method org/apache/hadoop/hbase/util/AbstractHBaseTool."<init>":()V
       4: return

  protected void addOptions();
    Code:
       0: aload_0
       1: getstatic     #39                 // Field NUM_REGIONS_OPT:Lorg/apache/hbase/thirdparty/org/apache/commons/cli/Option;
       4: invokevirtual #40                 // Method addOption:(Lorg/apache/hbase/thirdparty/org/apache/commons/cli/Option;)V
       7: aload_0
       8: getstatic     #41                 // Field NUM_SERVERS_OPT:Lorg/apache/hbase/thirdparty/org/apache/commons/cli/Option;
      11: invokevirtual #40                 // Method addOption:(Lorg/apache/hbase/thirdparty/org/apache/commons/cli/Option;)V
      14: aload_0
      15: getstatic     #42                 // Field LOAD_BALANCER_OPT:Lorg/apache/hbase/thirdparty/org/apache/commons/cli/Option;
      18: invokevirtual #40                 // Method addOption:(Lorg/apache/hbase/thirdparty/org/apache/commons/cli/Option;)V
      21: return

  protected void processOptions(org.apache.hbase.thirdparty.org.apache.commons.cli.CommandLine);
    Code:
       0: aload_0
       1: aload_0
       2: aload_1
       3: getstatic     #39                 // Field NUM_REGIONS_OPT:Lorg/apache/hbase/thirdparty/org/apache/commons/cli/Option;
       6: invokevirtual #43                 // Method org/apache/hbase/thirdparty/org/apache/commons/cli/Option.getOpt:()Ljava/lang/String;
       9: ldc           #45                 // int 1000000
      11: invokevirtual #46                 // Method getOptionAsInt:(Lorg/apache/hbase/thirdparty/org/apache/commons/cli/CommandLine;Ljava/lang/String;I)I
      14: putfield      #11                 // Field numRegions:I
      17: aload_0
      18: getfield      #11                 // Field numRegions:I
      21: ifle          28
      24: iconst_1
      25: goto          29
      28: iconst_0
      29: ldc           #47                 // String Invalid number of regions!
      31: invokestatic  #48                 // Method org/apache/hbase/thirdparty/com/google/common/base/Preconditions.checkArgument:(ZLjava/lang/Object;)V
      34: aload_0
      35: aload_0
      36: aload_1
      37: getstatic     #41                 // Field NUM_SERVERS_OPT:Lorg/apache/hbase/thirdparty/org/apache/commons/cli/Option;
      40: invokevirtual #43                 // Method org/apache/hbase/thirdparty/org/apache/commons/cli/Option.getOpt:()Ljava/lang/String;
      43: sipush        1000
      46: invokevirtual #46                 // Method getOptionAsInt:(Lorg/apache/hbase/thirdparty/org/apache/commons/cli/CommandLine;Ljava/lang/String;I)I
      49: putfield      #28                 // Field numServers:I
      52: aload_0
      53: getfield      #28                 // Field numServers:I
      56: ifle          63
      59: iconst_1
      60: goto          64
      63: iconst_0
      64: ldc           #49                 // String Invalid number of servers!
      66: invokestatic  #48                 // Method org/apache/hbase/thirdparty/com/google/common/base/Preconditions.checkArgument:(ZLjava/lang/Object;)V
      69: aload_0
      70: aload_1
      71: getstatic     #42                 // Field LOAD_BALANCER_OPT:Lorg/apache/hbase/thirdparty/org/apache/commons/cli/Option;
      74: invokevirtual #43                 // Method org/apache/hbase/thirdparty/org/apache/commons/cli/Option.getOpt:()Ljava/lang/String;
      77: ldc           #50                 // String org.apache.hadoop.hbase.master.balancer.StochasticLoadBalancer
      79: invokevirtual #51                 // Method org/apache/hbase/thirdparty/org/apache/commons/cli/CommandLine.getOptionValue:(Ljava/lang/String;Ljava/lang/String;)Ljava/lang/String;
      82: putfield      #52                 // Field loadBalancerType:Ljava/lang/String;
      85: aload_0
      86: getfield      #52                 // Field loadBalancerType:Ljava/lang/String;
      89: invokevirtual #53                 // Method java/lang/String.isEmpty:()Z
      92: ifne          99
      95: iconst_1
      96: goto          100
      99: iconst_0
     100: ldc           #54                 // String Invalid load balancer type!
     102: invokestatic  #48                 // Method org/apache/hbase/thirdparty/com/google/common/base/Preconditions.checkArgument:(ZLjava/lang/Object;)V
     105: aload_0
     106: aload_0
     107: getfield      #52                 // Field loadBalancerType:Ljava/lang/String;
     110: invokestatic  #55                 // Method java/lang/Class.forName:(Ljava/lang/String;)Ljava/lang/Class;
     113: putfield      #5                  // Field loadBalancerClazz:Ljava/lang/Class;
     116: goto          157
     119: astore_2
     120: getstatic     #57                 // Field java/lang/System.err:Ljava/io/PrintStream;
     123: new           #31                 // class java/lang/StringBuilder
     126: dup
     127: invokespecial #32                 // Method java/lang/StringBuilder."<init>":()V
     130: ldc           #58                 // String Class '
     132: invokevirtual #34                 // Method java/lang/StringBuilder.append:(Ljava/lang/String;)Ljava/lang/StringBuilder;
     135: aload_0
     136: getfield      #52                 // Field loadBalancerType:Ljava/lang/String;
     139: invokevirtual #34                 // Method java/lang/StringBuilder.append:(Ljava/lang/String;)Ljava/lang/StringBuilder;
     142: ldc           #59                 // String ' not found!
     144: invokevirtual #34                 // Method java/lang/StringBuilder.append:(Ljava/lang/String;)Ljava/lang/StringBuilder;
     147: invokevirtual #36                 // Method java/lang/StringBuilder.toString:()Ljava/lang/String;
     150: invokevirtual #60                 // Method java/io/PrintStream.println:(Ljava/lang/String;)V
     153: iconst_1
     154: invokestatic  #61                 // Method java/lang/System.exit:(I)V
     157: aload_0
     158: invokespecial #62                 // Method setupConf:()V
     161: return
    Exception table:
       from    to  target type
         105   116   119   Class java/lang/ClassNotFoundException

  protected int doWork() throws java.lang.Exception;
    Code:
       0: aload_0
       1: invokespecial #67                 // Method generateRegionsAndServers:()V
       4: ldc           #68                 // String roundRobinAssignment
       6: astore_1
       7: getstatic     #69                 // Field LOG:Lorg/slf4j/Logger;
      10: new           #31                 // class java/lang/StringBuilder
      13: dup
      14: invokespecial #32                 // Method java/lang/StringBuilder."<init>":()V
      17: ldc           #70                 // String Calling
      19: invokevirtual #34                 // Method java/lang/StringBuilder.append:(Ljava/lang/String;)Ljava/lang/StringBuilder;
      22: aload_1
      23: invokevirtual #34                 // Method java/lang/StringBuilder.append:(Ljava/lang/String;)Ljava/lang/StringBuilder;
      26: invokevirtual #36                 // Method java/lang/StringBuilder.toString:()Ljava/lang/String;
      29: invokeinterface #71,  2           // InterfaceMethod org/slf4j/Logger.info:(Ljava/lang/String;)V
      34: invokestatic  #72                 // Method org/apache/hbase/thirdparty/com/google/common/base/Stopwatch.createStarted:()Lorg/apache/hbase/thirdparty/com/google/common/base/Stopwatch;
      37: astore_2
      38: aload_0
      39: getfield      #9                  // Field loadBalancer:Lorg/apache/hadoop/hbase/master/LoadBalancer;
      42: aload_0
      43: getfield      #13                 // Field regions:Ljava/util/List;
      46: aload_0
      47: getfield      #29                 // Field servers:Ljava/util/List;
      50: invokeinterface #73,  3           // InterfaceMethod org/apache/hadoop/hbase/master/LoadBalancer.roundRobinAssignment:(Ljava/util/List;Ljava/util/List;)Ljava/util/Map;
      55: pop
      56: getstatic     #74                 // Field java/lang/System.out:Ljava/io/PrintStream;
      59: aload_0
      60: aload_1
      61: aload_2
      62: getstatic     #75                 // Field java/util/concurrent/TimeUnit.MILLISECONDS:Ljava/util/concurrent/TimeUnit;
      65: invokevirtual #76                 // Method org/apache/hbase/thirdparty/com/google/common/base/Stopwatch.elapsed:(Ljava/util/concurrent/TimeUnit;)J
      68: invokespecial #77                 // Method formatResults:(Ljava/lang/String;J)Ljava/lang/String;
      71: invokevirtual #78                 // Method java/io/PrintStream.print:(Ljava/lang/String;)V
      74: ldc           #79                 // String retainAssignment
      76: astore_1
      77: getstatic     #69                 // Field LOG:Lorg/slf4j/Logger;
      80: new           #31                 // class java/lang/StringBuilder
      83: dup
      84: invokespecial #32                 // Method java/lang/StringBuilder."<init>":()V
      87: ldc           #70                 // String Calling
      89: invokevirtual #34                 // Method java/lang/StringBuilder.append:(Ljava/lang/String;)Ljava/lang/StringBuilder;
      92: aload_1
      93: invokevirtual #34                 // Method java/lang/StringBuilder.append:(Ljava/lang/String;)Ljava/lang/StringBuilder;
      96: invokevirtual #36                 // Method java/lang/StringBuilder.toString:()Ljava/lang/String;
      99: invokeinterface #71,  2           // InterfaceMethod org/slf4j/Logger.info:(Ljava/lang/String;)V
     104: aload_2
     105: invokevirtual #80                 // Method org/apache/hbase/thirdparty/com/google/common/base/Stopwatch.reset:()Lorg/apache/hbase/thirdparty/com/google/common/base/Stopwatch;
     108: invokevirtual #81                 // Method org/apache/hbase/thirdparty/com/google/common/base/Stopwatch.start:()Lorg/apache/hbase/thirdparty/com/google/common/base/Stopwatch;
     111: pop
     112: aload_0
     113: getfield      #9                  // Field loadBalancer:Lorg/apache/hadoop/hbase/master/LoadBalancer;
     116: aload_0
     117: getfield      #16                 // Field regionServerMap:Ljava/util/Map;
     120: aload_0
     121: getfield      #29                 // Field servers:Ljava/util/List;
     124: invokeinterface #82,  3           // InterfaceMethod org/apache/hadoop/hbase/master/LoadBalancer.retainAssignment:(Ljava/util/Map;Ljava/util/List;)Ljava/util/Map;
     129: pop
     130: getstatic     #74                 // Field java/lang/System.out:Ljava/io/PrintStream;
     133: aload_0
     134: aload_1
     135: aload_2
     136: getstatic     #75                 // Field java/util/concurrent/TimeUnit.MILLISECONDS:Ljava/util/concurrent/TimeUnit;
     139: invokevirtual #76                 // Method org/apache/hbase/thirdparty/com/google/common/base/Stopwatch.elapsed:(Ljava/util/concurrent/TimeUnit;)J
     142: invokespecial #77                 // Method formatResults:(Ljava/lang/String;J)Ljava/lang/String;
     145: invokevirtual #78                 // Method java/io/PrintStream.print:(Ljava/lang/String;)V
     148: ldc           #83                 // String balanceCluster
     150: astore_1
     151: getstatic     #69                 // Field LOG:Lorg/slf4j/Logger;
     154: new           #31                 // class java/lang/StringBuilder
     157: dup
     158: invokespecial #32                 // Method java/lang/StringBuilder."<init>":()V
     161: ldc           #70                 // String Calling
     163: invokevirtual #34                 // Method java/lang/StringBuilder.append:(Ljava/lang/String;)Ljava/lang/StringBuilder;
     166: aload_1
     167: invokevirtual #34                 // Method java/lang/StringBuilder.append:(Ljava/lang/String;)Ljava/lang/StringBuilder;
     170: invokevirtual #36                 // Method java/lang/StringBuilder.toString:()Ljava/lang/String;
     173: invokeinterface #71,  2           // InterfaceMethod org/slf4j/Logger.info:(Ljava/lang/String;)V
     178: aload_2
     179: invokevirtual #80                 // Method org/apache/hbase/thirdparty/com/google/common/base/Stopwatch.reset:()Lorg/apache/hbase/thirdparty/com/google/common/base/Stopwatch;
     182: invokevirtual #81                 // Method org/apache/hbase/thirdparty/com/google/common/base/Stopwatch.start:()Lorg/apache/hbase/thirdparty/com/google/common/base/Stopwatch;
     185: pop
     186: aload_0
     187: getfield      #9                  // Field loadBalancer:Lorg/apache/hadoop/hbase/master/LoadBalancer;
     190: aload_0
     191: getfield      #30                 // Field serverRegionMap:Ljava/util/Map;
     194: invokeinterface #84,  2           // InterfaceMethod org/apache/hadoop/hbase/master/LoadBalancer.balanceCluster:(Ljava/util/Map;)Ljava/util/List;
     199: pop
     200: getstatic     #74                 // Field java/lang/System.out:Ljava/io/PrintStream;
     203: aload_0
     204: aload_1
     205: aload_2
     206: getstatic     #75                 // Field java/util/concurrent/TimeUnit.MILLISECONDS:Ljava/util/concurrent/TimeUnit;
     209: invokevirtual #76                 // Method org/apache/hbase/thirdparty/com/google/common/base/Stopwatch.elapsed:(Ljava/util/concurrent/TimeUnit;)J
     212: invokespecial #77                 // Method formatResults:(Ljava/lang/String;J)Ljava/lang/String;
     215: invokevirtual #78                 // Method java/io/PrintStream.print:(Ljava/lang/String;)V
     218: iconst_0
     219: ireturn

  public static void main(java.lang.String[]) throws java.io.IOException;
    Code:
       0: new           #44                 // class org/apache/hadoop/hbase/master/balancer/LoadBalancerPerformanceEvaluation
       3: dup
       4: invokespecial #86                 // Method "<init>":()V
       7: astore_1
       8: aload_1
       9: getstatic     #87                 // Field UTIL:Lorg/apache/hadoop/hbase/HBaseCommonTestingUtility;
      12: invokevirtual #88                 // Method org/apache/hadoop/hbase/HBaseCommonTestingUtility.getConfiguration:()Lorg/apache/hadoop/conf/Configuration;
      15: invokevirtual #89                 // Method setConf:(Lorg/apache/hadoop/conf/Configuration;)V
      18: aload_1
      19: aload_0
      20: invokevirtual #90                 // Method run:([Ljava/lang/String;)I
      23: pop
      24: return

  static {};
    Code:
       0: ldc           #44                 // class org/apache/hadoop/hbase/master/balancer/LoadBalancerPerformanceEvaluation
       2: invokevirtual #91                 // Method java/lang/Class.getName:()Ljava/lang/String;
       5: invokestatic  #92                 // Method org/slf4j/LoggerFactory.getLogger:(Ljava/lang/String;)Lorg/slf4j/Logger;
       8: putstatic     #69                 // Field LOG:Lorg/slf4j/Logger;
      11: new           #93                 // class org/apache/hadoop/hbase/HBaseCommonTestingUtility
      14: dup
      15: invokespecial #94                 // Method org/apache/hadoop/hbase/HBaseCommonTestingUtility."<init>":()V
      18: putstatic     #87                 // Field UTIL:Lorg/apache/hadoop/hbase/HBaseCommonTestingUtility;
      21: new           #95                 // class org/apache/hbase/thirdparty/org/apache/commons/cli/Option
      24: dup
      25: ldc           #96                 // String regions
      27: iconst_1
      28: ldc           #97                 // String Number of regions to consider by load balancer. Default: 1000000
      30: invokespecial #98                 // Method org/apache/hbase/thirdparty/org/apache/commons/cli/Option."<init>":(Ljava/lang/String;ZLjava/lang/String;)V
      33: putstatic     #39                 // Field NUM_REGIONS_OPT:Lorg/apache/hbase/thirdparty/org/apache/commons/cli/Option;
      36: new           #95                 // class org/apache/hbase/thirdparty/org/apache/commons/cli/Option
      39: dup
      40: ldc           #99                 // String servers
      42: iconst_1
      43: ldc           #100                // String Number of servers to consider by load balancer. Default: 1000
      45: invokespecial #98                 // Method org/apache/hbase/thirdparty/org/apache/commons/cli/Option."<init>":(Ljava/lang/String;ZLjava/lang/String;)V
      48: putstatic     #41                 // Field NUM_SERVERS_OPT:Lorg/apache/hbase/thirdparty/org/apache/commons/cli/Option;
      51: new           #95                 // class org/apache/hbase/thirdparty/org/apache/commons/cli/Option
      54: dup
      55: ldc           #101                // String load_balancer
      57: iconst_1
      58: ldc           #102                // String Type of Load Balancer to use. Default: org.apache.hadoop.hbase.master.balancer.StochasticLoadBalancer
      60: invokespecial #98                 // Method org/apache/hbase/thirdparty/org/apache/commons/cli/Option."<init>":(Ljava/lang/String;ZLjava/lang/String;)V
      63: putstatic     #42                 // Field LOAD_BALANCER_OPT:Lorg/apache/hbase/thirdparty/org/apache/commons/cli/Option;
      66: return
}
