Compiled from "LoadBalancer.java"
public interface org.apache.hadoop.hbase.master.LoadBalancer extends org.apache.hadoop.conf.Configurable,org.apache.hadoop.hbase.Stoppable,org.apache.hadoop.hbase.conf.ConfigurationObserver {
  public static final java.lang.String TABLES_ON_MASTER;

  public static final java.lang.String SYSTEM_TABLES_ON_MASTER;

  public static final org.apache.hadoop.hbase.ServerName BOGUS_SERVER_NAME;

  public abstract void setClusterMetrics(org.apache.hadoop.hbase.ClusterMetrics);

  public abstract void setClusterLoad(java.util.Map<org.apache.hadoop.hbase.TableName, java.util.Map<org.apache.hadoop.hbase.ServerName, java.util.List<org.apache.hadoop.hbase.client.RegionInfo>>>);

  public abstract void setMasterServices(org.apache.hadoop.hbase.master.MasterServices);

  public abstract java.util.List<org.apache.hadoop.hbase.master.RegionPlan> balanceCluster(org.apache.hadoop.hbase.TableName, java.util.Map<org.apache.hadoop.hbase.ServerName, java.util.List<org.apache.hadoop.hbase.client.RegionInfo>>) throws org.apache.hadoop.hbase.HBaseIOException;

  public abstract java.util.List<org.apache.hadoop.hbase.master.RegionPlan> balanceCluster(java.util.Map<org.apache.hadoop.hbase.ServerName, java.util.List<org.apache.hadoop.hbase.client.RegionInfo>>) throws org.apache.hadoop.hbase.HBaseIOException;

  public abstract java.util.Map<org.apache.hadoop.hbase.ServerName, java.util.List<org.apache.hadoop.hbase.client.RegionInfo>> roundRobinAssignment(java.util.List<org.apache.hadoop.hbase.client.RegionInfo>, java.util.List<org.apache.hadoop.hbase.ServerName>) throws org.apache.hadoop.hbase.HBaseIOException;

  public abstract java.util.Map<org.apache.hadoop.hbase.ServerName, java.util.List<org.apache.hadoop.hbase.client.RegionInfo>> retainAssignment(java.util.Map<org.apache.hadoop.hbase.client.RegionInfo, org.apache.hadoop.hbase.ServerName>, java.util.List<org.apache.hadoop.hbase.ServerName>) throws org.apache.hadoop.hbase.HBaseIOException;

  public abstract org.apache.hadoop.hbase.ServerName randomAssignment(org.apache.hadoop.hbase.client.RegionInfo, java.util.List<org.apache.hadoop.hbase.ServerName>) throws org.apache.hadoop.hbase.HBaseIOException;

  public abstract void initialize() throws org.apache.hadoop.hbase.HBaseIOException;

  public abstract void regionOnline(org.apache.hadoop.hbase.client.RegionInfo, org.apache.hadoop.hbase.ServerName);

  public abstract void regionOffline(org.apache.hadoop.hbase.client.RegionInfo);

  public abstract void onConfigurationChange(org.apache.hadoop.conf.Configuration);

  public abstract void postMasterStartupInitialize();

  public abstract void updateBalancerStatus(boolean);

  public static boolean isTablesOnMaster(org.apache.hadoop.conf.Configuration);
    Code:
       0: aload_0
       1: ldc           #2                  // String hbase.balancer.tablesOnMaster
       3: iconst_0
       4: invokevirtual #3                  // Method org/apache/hadoop/conf/Configuration.getBoolean:(Ljava/lang/String;Z)Z
       7: ireturn

  public static boolean isSystemTablesOnlyOnMaster(org.apache.hadoop.conf.Configuration);
    Code:
       0: aload_0
       1: ldc           #4                  // String hbase.balancer.tablesOnMaster.systemTablesOnly
       3: iconst_0
       4: invokevirtual #3                  // Method org/apache/hadoop/conf/Configuration.getBoolean:(Ljava/lang/String;Z)Z
       7: ireturn

  public static boolean isMasterCanHostUserRegions(org.apache.hadoop.conf.Configuration);
    Code:
       0: aload_0
       1: invokestatic  #5                  // InterfaceMethod isTablesOnMaster:(Lorg/apache/hadoop/conf/Configuration;)Z
       4: ifeq          18
       7: aload_0
       8: invokestatic  #6                  // InterfaceMethod isSystemTablesOnlyOnMaster:(Lorg/apache/hadoop/conf/Configuration;)Z
      11: ifne          18
      14: iconst_1
      15: goto          19
      18: iconst_0
      19: ireturn

  static {};
    Code:
       0: ldc           #7                  // String localhost,1,1
       2: invokestatic  #8                  // Method org/apache/hadoop/hbase/ServerName.valueOf:(Ljava/lang/String;)Lorg/apache/hadoop/hbase/ServerName;
       5: putstatic     #9                  // Field BOGUS_SERVER_NAME:Lorg/apache/hadoop/hbase/ServerName;
       8: return
}
