Compiled from "LocalHBaseCluster.java"
class org.apache.hadoop.hbase.LocalHBaseCluster$1 implements java.security.PrivilegedExceptionAction<org.apache.hadoop.hbase.util.JVMClusterUtil$RegionServerThread> {
  final org.apache.hadoop.conf.Configuration val$config;

  final int val$index;

  final org.apache.hadoop.hbase.LocalHBaseCluster this$0;

  org.apache.hadoop.hbase.LocalHBaseCluster$1(org.apache.hadoop.hbase.LocalHBaseCluster, org.apache.hadoop.conf.Configuration, int);
    Code:
       0: aload_0
       1: aload_1
       2: putfield      #1                  // Field this$0:Lorg/apache/hadoop/hbase/LocalHBaseCluster;
       5: aload_0
       6: aload_2
       7: putfield      #2                  // Field val$config:Lorg/apache/hadoop/conf/Configuration;
      10: aload_0
      11: iload_3
      12: putfield      #3                  // Field val$index:I
      15: aload_0
      16: invokespecial #4                  // Method java/lang/Object."<init>":()V
      19: return

  public org.apache.hadoop.hbase.util.JVMClusterUtil$RegionServerThread run() throws java.lang.Exception;
    Code:
       0: aload_0
       1: getfield      #1                  // Field this$0:Lorg/apache/hadoop/hbase/LocalHBaseCluster;
       4: aload_0
       5: getfield      #2                  // Field val$config:Lorg/apache/hadoop/conf/Configuration;
       8: aload_0
       9: getfield      #3                  // Field val$index:I
      12: invokevirtual #5                  // Method org/apache/hadoop/hbase/LocalHBaseCluster.addRegionServer:(Lorg/apache/hadoop/conf/Configuration;I)Lorg/apache/hadoop/hbase/util/JVMClusterUtil$RegionServerThread;
      15: areturn

  public java.lang.Object run() throws java.lang.Exception;
    Code:
       0: aload_0
       1: invokevirtual #6                  // Method run:()Lorg/apache/hadoop/hbase/util/JVMClusterUtil$RegionServerThread;
       4: areturn
}
