Compiled from "LockServiceProtos.java"
public final class org.apache.hadoop.hbase.shaded.protobuf.generated.LockServiceProtos$LockService$Stub extends org.apache.hadoop.hbase.shaded.protobuf.generated.LockServiceProtos$LockService implements org.apache.hadoop.hbase.shaded.protobuf.generated.LockServiceProtos$LockService$Interface {
  public org.apache.hbase.thirdparty.com.google.protobuf.RpcChannel getChannel();
    Code:
       0: aload_0
       1: getfield      #3                  // Field channel:Lorg/apache/hbase/thirdparty/com/google/protobuf/RpcChannel;
       4: areturn

  public void requestLock(org.apache.hbase.thirdparty.com.google.protobuf.RpcController, org.apache.hadoop.hbase.shaded.protobuf.generated.LockServiceProtos$LockRequest, org.apache.hbase.thirdparty.com.google.protobuf.RpcCallback<org.apache.hadoop.hbase.shaded.protobuf.generated.LockServiceProtos$LockResponse>);
    Code:
       0: aload_0
       1: getfield      #3                  // Field channel:Lorg/apache/hbase/thirdparty/com/google/protobuf/RpcChannel;
       4: invokestatic  #4                  // Method getDescriptor:()Lorg/apache/hbase/thirdparty/com/google/protobuf/Descriptors$ServiceDescriptor;
       7: invokevirtual #5                  // Method org/apache/hbase/thirdparty/com/google/protobuf/Descriptors$ServiceDescriptor.getMethods:()Ljava/util/List;
      10: iconst_0
      11: invokeinterface #6,  2            // InterfaceMethod java/util/List.get:(I)Ljava/lang/Object;
      16: checkcast     #7                  // class org/apache/hbase/thirdparty/com/google/protobuf/Descriptors$MethodDescriptor
      19: aload_1
      20: aload_2
      21: invokestatic  #8                  // Method org/apache/hadoop/hbase/shaded/protobuf/generated/LockServiceProtos$LockResponse.getDefaultInstance:()Lorg/apache/hadoop/hbase/shaded/protobuf/generated/LockServiceProtos$LockResponse;
      24: aload_3
      25: ldc           #9                  // class org/apache/hadoop/hbase/shaded/protobuf/generated/LockServiceProtos$LockResponse
      27: invokestatic  #8                  // Method org/apache/hadoop/hbase/shaded/protobuf/generated/LockServiceProtos$LockResponse.getDefaultInstance:()Lorg/apache/hadoop/hbase/shaded/protobuf/generated/LockServiceProtos$LockResponse;
      30: invokestatic  #10                 // Method org/apache/hbase/thirdparty/com/google/protobuf/RpcUtil.generalizeCallback:(Lorg/apache/hbase/thirdparty/com/google/protobuf/RpcCallback;Ljava/lang/Class;Lorg/apache/hbase/thirdparty/com/google/protobuf/Message;)Lorg/apache/hbase/thirdparty/com/google/protobuf/RpcCallback;
      33: invokeinterface #11,  6           // InterfaceMethod org/apache/hbase/thirdparty/com/google/protobuf/RpcChannel.callMethod:(Lorg/apache/hbase/thirdparty/com/google/protobuf/Descriptors$MethodDescriptor;Lorg/apache/hbase/thirdparty/com/google/protobuf/RpcController;Lorg/apache/hbase/thirdparty/com/google/protobuf/Message;Lorg/apache/hbase/thirdparty/com/google/protobuf/Message;Lorg/apache/hbase/thirdparty/com/google/protobuf/RpcCallback;)V
      38: return

  public void lockHeartbeat(org.apache.hbase.thirdparty.com.google.protobuf.RpcController, org.apache.hadoop.hbase.shaded.protobuf.generated.LockServiceProtos$LockHeartbeatRequest, org.apache.hbase.thirdparty.com.google.protobuf.RpcCallback<org.apache.hadoop.hbase.shaded.protobuf.generated.LockServiceProtos$LockHeartbeatResponse>);
    Code:
       0: aload_0
       1: getfield      #3                  // Field channel:Lorg/apache/hbase/thirdparty/com/google/protobuf/RpcChannel;
       4: invokestatic  #4                  // Method getDescriptor:()Lorg/apache/hbase/thirdparty/com/google/protobuf/Descriptors$ServiceDescriptor;
       7: invokevirtual #5                  // Method org/apache/hbase/thirdparty/com/google/protobuf/Descriptors$ServiceDescriptor.getMethods:()Ljava/util/List;
      10: iconst_1
      11: invokeinterface #6,  2            // InterfaceMethod java/util/List.get:(I)Ljava/lang/Object;
      16: checkcast     #7                  // class org/apache/hbase/thirdparty/com/google/protobuf/Descriptors$MethodDescriptor
      19: aload_1
      20: aload_2
      21: invokestatic  #12                 // Method org/apache/hadoop/hbase/shaded/protobuf/generated/LockServiceProtos$LockHeartbeatResponse.getDefaultInstance:()Lorg/apache/hadoop/hbase/shaded/protobuf/generated/LockServiceProtos$LockHeartbeatResponse;
      24: aload_3
      25: ldc           #13                 // class org/apache/hadoop/hbase/shaded/protobuf/generated/LockServiceProtos$LockHeartbeatResponse
      27: invokestatic  #12                 // Method org/apache/hadoop/hbase/shaded/protobuf/generated/LockServiceProtos$LockHeartbeatResponse.getDefaultInstance:()Lorg/apache/hadoop/hbase/shaded/protobuf/generated/LockServiceProtos$LockHeartbeatResponse;
      30: invokestatic  #10                 // Method org/apache/hbase/thirdparty/com/google/protobuf/RpcUtil.generalizeCallback:(Lorg/apache/hbase/thirdparty/com/google/protobuf/RpcCallback;Ljava/lang/Class;Lorg/apache/hbase/thirdparty/com/google/protobuf/Message;)Lorg/apache/hbase/thirdparty/com/google/protobuf/RpcCallback;
      33: invokeinterface #11,  6           // InterfaceMethod org/apache/hbase/thirdparty/com/google/protobuf/RpcChannel.callMethod:(Lorg/apache/hbase/thirdparty/com/google/protobuf/Descriptors$MethodDescriptor;Lorg/apache/hbase/thirdparty/com/google/protobuf/RpcController;Lorg/apache/hbase/thirdparty/com/google/protobuf/Message;Lorg/apache/hbase/thirdparty/com/google/protobuf/Message;Lorg/apache/hbase/thirdparty/com/google/protobuf/RpcCallback;)V
      38: return

  org.apache.hadoop.hbase.shaded.protobuf.generated.LockServiceProtos$LockService$Stub(org.apache.hbase.thirdparty.com.google.protobuf.RpcChannel, org.apache.hadoop.hbase.shaded.protobuf.generated.LockServiceProtos$1);
    Code:
       0: aload_0
       1: aload_1
       2: invokespecial #1                  // Method "<init>":(Lorg/apache/hbase/thirdparty/com/google/protobuf/RpcChannel;)V
       5: return
}
