Compiled from "LockServiceProtos.java"
public final class org.apache.hadoop.hbase.shaded.protobuf.generated.LockServiceProtos$LockedResource$Builder extends org.apache.hbase.thirdparty.com.google.protobuf.GeneratedMessageV3$Builder<org.apache.hadoop.hbase.shaded.protobuf.generated.LockServiceProtos$LockedResource$Builder> implements org.apache.hadoop.hbase.shaded.protobuf.generated.LockServiceProtos$LockedResourceOrBuilder {
  public static final org.apache.hbase.thirdparty.com.google.protobuf.Descriptors$Descriptor getDescriptor();
    Code:
       0: invokestatic  #3                  // Method org/apache/hadoop/hbase/shaded/protobuf/generated/LockServiceProtos.access$6500:()Lorg/apache/hbase/thirdparty/com/google/protobuf/Descriptors$Descriptor;
       3: areturn

  protected org.apache.hbase.thirdparty.com.google.protobuf.GeneratedMessageV3$FieldAccessorTable internalGetFieldAccessorTable();
    Code:
       0: invokestatic  #4                  // Method org/apache/hadoop/hbase/shaded/protobuf/generated/LockServiceProtos.access$6600:()Lorg/apache/hbase/thirdparty/com/google/protobuf/GeneratedMessageV3$FieldAccessorTable;
       3: ldc           #5                  // class org/apache/hadoop/hbase/shaded/protobuf/generated/LockServiceProtos$LockedResource
       5: ldc           #6                  // class org/apache/hadoop/hbase/shaded/protobuf/generated/LockServiceProtos$LockedResource$Builder
       7: invokevirtual #7                  // Method org/apache/hbase/thirdparty/com/google/protobuf/GeneratedMessageV3$FieldAccessorTable.ensureFieldAccessorsInitialized:(Ljava/lang/Class;Ljava/lang/Class;)Lorg/apache/hbase/thirdparty/com/google/protobuf/GeneratedMessageV3$FieldAccessorTable;
      10: areturn

  public org.apache.hadoop.hbase.shaded.protobuf.generated.LockServiceProtos$LockedResource$Builder clear();
    Code:
       0: aload_0
       1: invokespecial #21                 // Method org/apache/hbase/thirdparty/com/google/protobuf/GeneratedMessageV3$Builder.clear:()Lorg/apache/hbase/thirdparty/com/google/protobuf/GeneratedMessageV3$Builder;
       4: pop
       5: aload_0
       6: iconst_1
       7: putfield      #9                  // Field resourceType_:I
      10: aload_0
      11: aload_0
      12: getfield      #22                 // Field bitField0_:I
      15: bipush        -2
      17: iand
      18: putfield      #22                 // Field bitField0_:I
      21: aload_0
      22: ldc           #10                 // String
      24: putfield      #11                 // Field resourceName_:Ljava/lang/Object;
      27: aload_0
      28: aload_0
      29: getfield      #22                 // Field bitField0_:I
      32: bipush        -3
      34: iand
      35: putfield      #22                 // Field bitField0_:I
      38: aload_0
      39: iconst_1
      40: putfield      #12                 // Field lockType_:I
      43: aload_0
      44: aload_0
      45: getfield      #22                 // Field bitField0_:I
      48: bipush        -5
      50: iand
      51: putfield      #22                 // Field bitField0_:I
      54: aload_0
      55: getfield      #23                 // Field exclusiveLockOwnerProcedureBuilder_:Lorg/apache/hbase/thirdparty/com/google/protobuf/SingleFieldBuilderV3;
      58: ifnonnull     69
      61: aload_0
      62: aconst_null
      63: putfield      #13                 // Field exclusiveLockOwnerProcedure_:Lorg/apache/hadoop/hbase/shaded/protobuf/generated/ProcedureProtos$Procedure;
      66: goto          77
      69: aload_0
      70: getfield      #23                 // Field exclusiveLockOwnerProcedureBuilder_:Lorg/apache/hbase/thirdparty/com/google/protobuf/SingleFieldBuilderV3;
      73: invokevirtual #24                 // Method org/apache/hbase/thirdparty/com/google/protobuf/SingleFieldBuilderV3.clear:()Lorg/apache/hbase/thirdparty/com/google/protobuf/SingleFieldBuilderV3;
      76: pop
      77: aload_0
      78: aload_0
      79: getfield      #22                 // Field bitField0_:I
      82: bipush        -9
      84: iand
      85: putfield      #22                 // Field bitField0_:I
      88: aload_0
      89: iconst_0
      90: putfield      #25                 // Field sharedLockCount_:I
      93: aload_0
      94: aload_0
      95: getfield      #22                 // Field bitField0_:I
      98: bipush        -17
     100: iand
     101: putfield      #22                 // Field bitField0_:I
     104: aload_0
     105: getfield      #26                 // Field waitingProceduresBuilder_:Lorg/apache/hbase/thirdparty/com/google/protobuf/RepeatedFieldBuilderV3;
     108: ifnonnull     132
     111: aload_0
     112: invokestatic  #14                 // Method java/util/Collections.emptyList:()Ljava/util/List;
     115: putfield      #15                 // Field waitingProcedures_:Ljava/util/List;
     118: aload_0
     119: aload_0
     120: getfield      #22                 // Field bitField0_:I
     123: bipush        -33
     125: iand
     126: putfield      #22                 // Field bitField0_:I
     129: goto          139
     132: aload_0
     133: getfield      #26                 // Field waitingProceduresBuilder_:Lorg/apache/hbase/thirdparty/com/google/protobuf/RepeatedFieldBuilderV3;
     136: invokevirtual #27                 // Method org/apache/hbase/thirdparty/com/google/protobuf/RepeatedFieldBuilderV3.clear:()V
     139: aload_0
     140: areturn

  public org.apache.hbase.thirdparty.com.google.protobuf.Descriptors$Descriptor getDescriptorForType();
    Code:
       0: invokestatic  #3                  // Method org/apache/hadoop/hbase/shaded/protobuf/generated/LockServiceProtos.access$6500:()Lorg/apache/hbase/thirdparty/com/google/protobuf/Descriptors$Descriptor;
       3: areturn

  public org.apache.hadoop.hbase.shaded.protobuf.generated.LockServiceProtos$LockedResource getDefaultInstanceForType();
    Code:
       0: invokestatic  #28                 // Method org/apache/hadoop/hbase/shaded/protobuf/generated/LockServiceProtos$LockedResource.getDefaultInstance:()Lorg/apache/hadoop/hbase/shaded/protobuf/generated/LockServiceProtos$LockedResource;
       3: areturn

  public org.apache.hadoop.hbase.shaded.protobuf.generated.LockServiceProtos$LockedResource build();
    Code:
       0: aload_0
       1: invokevirtual #29                 // Method buildPartial:()Lorg/apache/hadoop/hbase/shaded/protobuf/generated/LockServiceProtos$LockedResource;
       4: astore_1
       5: aload_1
       6: invokevirtual #30                 // Method org/apache/hadoop/hbase/shaded/protobuf/generated/LockServiceProtos$LockedResource.isInitialized:()Z
       9: ifne          17
      12: aload_1
      13: invokestatic  #31                 // Method newUninitializedMessageException:(Lorg/apache/hbase/thirdparty/com/google/protobuf/Message;)Lorg/apache/hbase/thirdparty/com/google/protobuf/UninitializedMessageException;
      16: athrow
      17: aload_1
      18: areturn

  public org.apache.hadoop.hbase.shaded.protobuf.generated.LockServiceProtos$LockedResource buildPartial();
    Code:
       0: new           #5                  // class org/apache/hadoop/hbase/shaded/protobuf/generated/LockServiceProtos$LockedResource
       3: dup
       4: aload_0
       5: aconst_null
       6: invokespecial #32                 // Method org/apache/hadoop/hbase/shaded/protobuf/generated/LockServiceProtos$LockedResource."<init>":(Lorg/apache/hbase/thirdparty/com/google/protobuf/GeneratedMessageV3$Builder;Lorg/apache/hadoop/hbase/shaded/protobuf/generated/LockServiceProtos$1;)V
       9: astore_1
      10: aload_0
      11: getfield      #22                 // Field bitField0_:I
      14: istore_2
      15: iconst_0
      16: istore_3
      17: iload_2
      18: iconst_1
      19: iand
      20: iconst_1
      21: if_icmpne     28
      24: iload_3
      25: iconst_1
      26: ior
      27: istore_3
      28: aload_1
      29: aload_0
      30: getfield      #9                  // Field resourceType_:I
      33: invokestatic  #33                 // Method org/apache/hadoop/hbase/shaded/protobuf/generated/LockServiceProtos$LockedResource.access$7102:(Lorg/apache/hadoop/hbase/shaded/protobuf/generated/LockServiceProtos$LockedResource;I)I
      36: pop
      37: iload_2
      38: iconst_2
      39: iand
      40: iconst_2
      41: if_icmpne     48
      44: iload_3
      45: iconst_2
      46: ior
      47: istore_3
      48: aload_1
      49: aload_0
      50: getfield      #11                 // Field resourceName_:Ljava/lang/Object;
      53: invokestatic  #34                 // Method org/apache/hadoop/hbase/shaded/protobuf/generated/LockServiceProtos$LockedResource.access$7202:(Lorg/apache/hadoop/hbase/shaded/protobuf/generated/LockServiceProtos$LockedResource;Ljava/lang/Object;)Ljava/lang/Object;
      56: pop
      57: iload_2
      58: iconst_4
      59: iand
      60: iconst_4
      61: if_icmpne     68
      64: iload_3
      65: iconst_4
      66: ior
      67: istore_3
      68: aload_1
      69: aload_0
      70: getfield      #12                 // Field lockType_:I
      73: invokestatic  #35                 // Method org/apache/hadoop/hbase/shaded/protobuf/generated/LockServiceProtos$LockedResource.access$7302:(Lorg/apache/hadoop/hbase/shaded/protobuf/generated/LockServiceProtos$LockedResource;I)I
      76: pop
      77: iload_2
      78: bipush        8
      80: iand
      81: bipush        8
      83: if_icmpne     91
      86: iload_3
      87: bipush        8
      89: ior
      90: istore_3
      91: aload_0
      92: getfield      #23                 // Field exclusiveLockOwnerProcedureBuilder_:Lorg/apache/hbase/thirdparty/com/google/protobuf/SingleFieldBuilderV3;
      95: ifnonnull     110
      98: aload_1
      99: aload_0
     100: getfield      #13                 // Field exclusiveLockOwnerProcedure_:Lorg/apache/hadoop/hbase/shaded/protobuf/generated/ProcedureProtos$Procedure;
     103: invokestatic  #36                 // Method org/apache/hadoop/hbase/shaded/protobuf/generated/LockServiceProtos$LockedResource.access$7402:(Lorg/apache/hadoop/hbase/shaded/protobuf/generated/LockServiceProtos$LockedResource;Lorg/apache/hadoop/hbase/shaded/protobuf/generated/ProcedureProtos$Procedure;)Lorg/apache/hadoop/hbase/shaded/protobuf/generated/ProcedureProtos$Procedure;
     106: pop
     107: goto          125
     110: aload_1
     111: aload_0
     112: getfield      #23                 // Field exclusiveLockOwnerProcedureBuilder_:Lorg/apache/hbase/thirdparty/com/google/protobuf/SingleFieldBuilderV3;
     115: invokevirtual #37                 // Method org/apache/hbase/thirdparty/com/google/protobuf/SingleFieldBuilderV3.build:()Lorg/apache/hbase/thirdparty/com/google/protobuf/AbstractMessage;
     118: checkcast     #38                 // class org/apache/hadoop/hbase/shaded/protobuf/generated/ProcedureProtos$Procedure
     121: invokestatic  #36                 // Method org/apache/hadoop/hbase/shaded/protobuf/generated/LockServiceProtos$LockedResource.access$7402:(Lorg/apache/hadoop/hbase/shaded/protobuf/generated/LockServiceProtos$LockedResource;Lorg/apache/hadoop/hbase/shaded/protobuf/generated/ProcedureProtos$Procedure;)Lorg/apache/hadoop/hbase/shaded/protobuf/generated/ProcedureProtos$Procedure;
     124: pop
     125: iload_2
     126: bipush        16
     128: iand
     129: bipush        16
     131: if_icmpne     139
     134: iload_3
     135: bipush        16
     137: ior
     138: istore_3
     139: aload_1
     140: aload_0
     141: getfield      #25                 // Field sharedLockCount_:I
     144: invokestatic  #39                 // Method org/apache/hadoop/hbase/shaded/protobuf/generated/LockServiceProtos$LockedResource.access$7502:(Lorg/apache/hadoop/hbase/shaded/protobuf/generated/LockServiceProtos$LockedResource;I)I
     147: pop
     148: aload_0
     149: getfield      #26                 // Field waitingProceduresBuilder_:Lorg/apache/hbase/thirdparty/com/google/protobuf/RepeatedFieldBuilderV3;
     152: ifnonnull     201
     155: aload_0
     156: getfield      #22                 // Field bitField0_:I
     159: bipush        32
     161: iand
     162: bipush        32
     164: if_icmpne     189
     167: aload_0
     168: aload_0
     169: getfield      #15                 // Field waitingProcedures_:Ljava/util/List;
     172: invokestatic  #40                 // Method java/util/Collections.unmodifiableList:(Ljava/util/List;)Ljava/util/List;
     175: putfield      #15                 // Field waitingProcedures_:Ljava/util/List;
     178: aload_0
     179: aload_0
     180: getfield      #22                 // Field bitField0_:I
     183: bipush        -33
     185: iand
     186: putfield      #22                 // Field bitField0_:I
     189: aload_1
     190: aload_0
     191: getfield      #15                 // Field waitingProcedures_:Ljava/util/List;
     194: invokestatic  #41                 // Method org/apache/hadoop/hbase/shaded/protobuf/generated/LockServiceProtos$LockedResource.access$7602:(Lorg/apache/hadoop/hbase/shaded/protobuf/generated/LockServiceProtos$LockedResource;Ljava/util/List;)Ljava/util/List;
     197: pop
     198: goto          213
     201: aload_1
     202: aload_0
     203: getfield      #26                 // Field waitingProceduresBuilder_:Lorg/apache/hbase/thirdparty/com/google/protobuf/RepeatedFieldBuilderV3;
     206: invokevirtual #42                 // Method org/apache/hbase/thirdparty/com/google/protobuf/RepeatedFieldBuilderV3.build:()Ljava/util/List;
     209: invokestatic  #41                 // Method org/apache/hadoop/hbase/shaded/protobuf/generated/LockServiceProtos$LockedResource.access$7602:(Lorg/apache/hadoop/hbase/shaded/protobuf/generated/LockServiceProtos$LockedResource;Ljava/util/List;)Ljava/util/List;
     212: pop
     213: aload_1
     214: iload_3
     215: invokestatic  #43                 // Method org/apache/hadoop/hbase/shaded/protobuf/generated/LockServiceProtos$LockedResource.access$7702:(Lorg/apache/hadoop/hbase/shaded/protobuf/generated/LockServiceProtos$LockedResource;I)I
     218: pop
     219: aload_0
     220: invokevirtual #44                 // Method onBuilt:()V
     223: aload_1
     224: areturn

  public org.apache.hadoop.hbase.shaded.protobuf.generated.LockServiceProtos$LockedResource$Builder clone();
    Code:
       0: aload_0
       1: invokespecial #45                 // Method org/apache/hbase/thirdparty/com/google/protobuf/GeneratedMessageV3$Builder.clone:()Lorg/apache/hbase/thirdparty/com/google/protobuf/GeneratedMessageV3$Builder;
       4: checkcast     #6                  // class org/apache/hadoop/hbase/shaded/protobuf/generated/LockServiceProtos$LockedResource$Builder
       7: areturn

  public org.apache.hadoop.hbase.shaded.protobuf.generated.LockServiceProtos$LockedResource$Builder setField(org.apache.hbase.thirdparty.com.google.protobuf.Descriptors$FieldDescriptor, java.lang.Object);
    Code:
       0: aload_0
       1: aload_1
       2: aload_2
       3: invokespecial #46                 // Method org/apache/hbase/thirdparty/com/google/protobuf/GeneratedMessageV3$Builder.setField:(Lorg/apache/hbase/thirdparty/com/google/protobuf/Descriptors$FieldDescriptor;Ljava/lang/Object;)Lorg/apache/hbase/thirdparty/com/google/protobuf/GeneratedMessageV3$Builder;
       6: checkcast     #6                  // class org/apache/hadoop/hbase/shaded/protobuf/generated/LockServiceProtos$LockedResource$Builder
       9: areturn

  public org.apache.hadoop.hbase.shaded.protobuf.generated.LockServiceProtos$LockedResource$Builder clearField(org.apache.hbase.thirdparty.com.google.protobuf.Descriptors$FieldDescriptor);
    Code:
       0: aload_0
       1: aload_1
       2: invokespecial #47                 // Method org/apache/hbase/thirdparty/com/google/protobuf/GeneratedMessageV3$Builder.clearField:(Lorg/apache/hbase/thirdparty/com/google/protobuf/Descriptors$FieldDescriptor;)Lorg/apache/hbase/thirdparty/com/google/protobuf/GeneratedMessageV3$Builder;
       5: checkcast     #6                  // class org/apache/hadoop/hbase/shaded/protobuf/generated/LockServiceProtos$LockedResource$Builder
       8: areturn

  public org.apache.hadoop.hbase.shaded.protobuf.generated.LockServiceProtos$LockedResource$Builder clearOneof(org.apache.hbase.thirdparty.com.google.protobuf.Descriptors$OneofDescriptor);
    Code:
       0: aload_0
       1: aload_1
       2: invokespecial #48                 // Method org/apache/hbase/thirdparty/com/google/protobuf/GeneratedMessageV3$Builder.clearOneof:(Lorg/apache/hbase/thirdparty/com/google/protobuf/Descriptors$OneofDescriptor;)Lorg/apache/hbase/thirdparty/com/google/protobuf/GeneratedMessageV3$Builder;
       5: checkcast     #6                  // class org/apache/hadoop/hbase/shaded/protobuf/generated/LockServiceProtos$LockedResource$Builder
       8: areturn

  public org.apache.hadoop.hbase.shaded.protobuf.generated.LockServiceProtos$LockedResource$Builder setRepeatedField(org.apache.hbase.thirdparty.com.google.protobuf.Descriptors$FieldDescriptor, int, java.lang.Object);
    Code:
       0: aload_0
       1: aload_1
       2: iload_2
       3: aload_3
       4: invokespecial #49                 // Method org/apache/hbase/thirdparty/com/google/protobuf/GeneratedMessageV3$Builder.setRepeatedField:(Lorg/apache/hbase/thirdparty/com/google/protobuf/Descriptors$FieldDescriptor;ILjava/lang/Object;)Lorg/apache/hbase/thirdparty/com/google/protobuf/GeneratedMessageV3$Builder;
       7: checkcast     #6                  // class org/apache/hadoop/hbase/shaded/protobuf/generated/LockServiceProtos$LockedResource$Builder
      10: areturn

  public org.apache.hadoop.hbase.shaded.protobuf.generated.LockServiceProtos$LockedResource$Builder addRepeatedField(org.apache.hbase.thirdparty.com.google.protobuf.Descriptors$FieldDescriptor, java.lang.Object);
    Code:
       0: aload_0
       1: aload_1
       2: aload_2
       3: invokespecial #50                 // Method org/apache/hbase/thirdparty/com/google/protobuf/GeneratedMessageV3$Builder.addRepeatedField:(Lorg/apache/hbase/thirdparty/com/google/protobuf/Descriptors$FieldDescriptor;Ljava/lang/Object;)Lorg/apache/hbase/thirdparty/com/google/protobuf/GeneratedMessageV3$Builder;
       6: checkcast     #6                  // class org/apache/hadoop/hbase/shaded/protobuf/generated/LockServiceProtos$LockedResource$Builder
       9: areturn

  public org.apache.hadoop.hbase.shaded.protobuf.generated.LockServiceProtos$LockedResource$Builder mergeFrom(org.apache.hbase.thirdparty.com.google.protobuf.Message);
    Code:
       0: aload_1
       1: instanceof    #5                  // class org/apache/hadoop/hbase/shaded/protobuf/generated/LockServiceProtos$LockedResource
       4: ifeq          16
       7: aload_0
       8: aload_1
       9: checkcast     #5                  // class org/apache/hadoop/hbase/shaded/protobuf/generated/LockServiceProtos$LockedResource
      12: invokevirtual #51                 // Method mergeFrom:(Lorg/apache/hadoop/hbase/shaded/protobuf/generated/LockServiceProtos$LockedResource;)Lorg/apache/hadoop/hbase/shaded/protobuf/generated/LockServiceProtos$LockedResource$Builder;
      15: areturn
      16: aload_0
      17: aload_1
      18: invokespecial #52                 // Method org/apache/hbase/thirdparty/com/google/protobuf/GeneratedMessageV3$Builder.mergeFrom:(Lorg/apache/hbase/thirdparty/com/google/protobuf/Message;)Lorg/apache/hbase/thirdparty/com/google/protobuf/AbstractMessage$Builder;
      21: pop
      22: aload_0
      23: areturn

  public org.apache.hadoop.hbase.shaded.protobuf.generated.LockServiceProtos$LockedResource$Builder mergeFrom(org.apache.hadoop.hbase.shaded.protobuf.generated.LockServiceProtos$LockedResource);
    Code:
       0: aload_1
       1: invokestatic  #28                 // Method org/apache/hadoop/hbase/shaded/protobuf/generated/LockServiceProtos$LockedResource.getDefaultInstance:()Lorg/apache/hadoop/hbase/shaded/protobuf/generated/LockServiceProtos$LockedResource;
       4: if_acmpne     9
       7: aload_0
       8: areturn
       9: aload_1
      10: invokevirtual #53                 // Method org/apache/hadoop/hbase/shaded/protobuf/generated/LockServiceProtos$LockedResource.hasResourceType:()Z
      13: ifeq          25
      16: aload_0
      17: aload_1
      18: invokevirtual #54                 // Method org/apache/hadoop/hbase/shaded/protobuf/generated/LockServiceProtos$LockedResource.getResourceType:()Lorg/apache/hadoop/hbase/shaded/protobuf/generated/LockServiceProtos$LockedResourceType;
      21: invokevirtual #55                 // Method setResourceType:(Lorg/apache/hadoop/hbase/shaded/protobuf/generated/LockServiceProtos$LockedResourceType;)Lorg/apache/hadoop/hbase/shaded/protobuf/generated/LockServiceProtos$LockedResource$Builder;
      24: pop
      25: aload_1
      26: invokevirtual #56                 // Method org/apache/hadoop/hbase/shaded/protobuf/generated/LockServiceProtos$LockedResource.hasResourceName:()Z
      29: ifeq          54
      32: aload_0
      33: dup
      34: getfield      #22                 // Field bitField0_:I
      37: iconst_2
      38: ior
      39: putfield      #22                 // Field bitField0_:I
      42: aload_0
      43: aload_1
      44: invokestatic  #57                 // Method org/apache/hadoop/hbase/shaded/protobuf/generated/LockServiceProtos$LockedResource.access$7200:(Lorg/apache/hadoop/hbase/shaded/protobuf/generated/LockServiceProtos$LockedResource;)Ljava/lang/Object;
      47: putfield      #11                 // Field resourceName_:Ljava/lang/Object;
      50: aload_0
      51: invokevirtual #58                 // Method onChanged:()V
      54: aload_1
      55: invokevirtual #59                 // Method org/apache/hadoop/hbase/shaded/protobuf/generated/LockServiceProtos$LockedResource.hasLockType:()Z
      58: ifeq          70
      61: aload_0
      62: aload_1
      63: invokevirtual #60                 // Method org/apache/hadoop/hbase/shaded/protobuf/generated/LockServiceProtos$LockedResource.getLockType:()Lorg/apache/hadoop/hbase/shaded/protobuf/generated/LockServiceProtos$LockType;
      66: invokevirtual #61                 // Method setLockType:(Lorg/apache/hadoop/hbase/shaded/protobuf/generated/LockServiceProtos$LockType;)Lorg/apache/hadoop/hbase/shaded/protobuf/generated/LockServiceProtos$LockedResource$Builder;
      69: pop
      70: aload_1
      71: invokevirtual #62                 // Method org/apache/hadoop/hbase/shaded/protobuf/generated/LockServiceProtos$LockedResource.hasExclusiveLockOwnerProcedure:()Z
      74: ifeq          86
      77: aload_0
      78: aload_1
      79: invokevirtual #63                 // Method org/apache/hadoop/hbase/shaded/protobuf/generated/LockServiceProtos$LockedResource.getExclusiveLockOwnerProcedure:()Lorg/apache/hadoop/hbase/shaded/protobuf/generated/ProcedureProtos$Procedure;
      82: invokevirtual #64                 // Method mergeExclusiveLockOwnerProcedure:(Lorg/apache/hadoop/hbase/shaded/protobuf/generated/ProcedureProtos$Procedure;)Lorg/apache/hadoop/hbase/shaded/protobuf/generated/LockServiceProtos$LockedResource$Builder;
      85: pop
      86: aload_1
      87: invokevirtual #65                 // Method org/apache/hadoop/hbase/shaded/protobuf/generated/LockServiceProtos$LockedResource.hasSharedLockCount:()Z
      90: ifeq          102
      93: aload_0
      94: aload_1
      95: invokevirtual #66                 // Method org/apache/hadoop/hbase/shaded/protobuf/generated/LockServiceProtos$LockedResource.getSharedLockCount:()I
      98: invokevirtual #67                 // Method setSharedLockCount:(I)Lorg/apache/hadoop/hbase/shaded/protobuf/generated/LockServiceProtos$LockedResource$Builder;
     101: pop
     102: aload_0
     103: getfield      #26                 // Field waitingProceduresBuilder_:Lorg/apache/hbase/thirdparty/com/google/protobuf/RepeatedFieldBuilderV3;
     106: ifnonnull     180
     109: aload_1
     110: invokestatic  #68                 // Method org/apache/hadoop/hbase/shaded/protobuf/generated/LockServiceProtos$LockedResource.access$7600:(Lorg/apache/hadoop/hbase/shaded/protobuf/generated/LockServiceProtos$LockedResource;)Ljava/util/List;
     113: invokeinterface #69,  1           // InterfaceMethod java/util/List.isEmpty:()Z
     118: ifne          266
     121: aload_0
     122: getfield      #15                 // Field waitingProcedures_:Ljava/util/List;
     125: invokeinterface #69,  1           // InterfaceMethod java/util/List.isEmpty:()Z
     130: ifeq          155
     133: aload_0
     134: aload_1
     135: invokestatic  #68                 // Method org/apache/hadoop/hbase/shaded/protobuf/generated/LockServiceProtos$LockedResource.access$7600:(Lorg/apache/hadoop/hbase/shaded/protobuf/generated/LockServiceProtos$LockedResource;)Ljava/util/List;
     138: putfield      #15                 // Field waitingProcedures_:Ljava/util/List;
     141: aload_0
     142: aload_0
     143: getfield      #22                 // Field bitField0_:I
     146: bipush        -33
     148: iand
     149: putfield      #22                 // Field bitField0_:I
     152: goto          173
     155: aload_0
     156: invokespecial #70                 // Method ensureWaitingProceduresIsMutable:()V
     159: aload_0
     160: getfield      #15                 // Field waitingProcedures_:Ljava/util/List;
     163: aload_1
     164: invokestatic  #68                 // Method org/apache/hadoop/hbase/shaded/protobuf/generated/LockServiceProtos$LockedResource.access$7600:(Lorg/apache/hadoop/hbase/shaded/protobuf/generated/LockServiceProtos$LockedResource;)Ljava/util/List;
     167: invokeinterface #71,  2           // InterfaceMethod java/util/List.addAll:(Ljava/util/Collection;)Z
     172: pop
     173: aload_0
     174: invokevirtual #58                 // Method onChanged:()V
     177: goto          266
     180: aload_1
     181: invokestatic  #68                 // Method org/apache/hadoop/hbase/shaded/protobuf/generated/LockServiceProtos$LockedResource.access$7600:(Lorg/apache/hadoop/hbase/shaded/protobuf/generated/LockServiceProtos$LockedResource;)Ljava/util/List;
     184: invokeinterface #69,  1           // InterfaceMethod java/util/List.isEmpty:()Z
     189: ifne          266
     192: aload_0
     193: getfield      #26                 // Field waitingProceduresBuilder_:Lorg/apache/hbase/thirdparty/com/google/protobuf/RepeatedFieldBuilderV3;
     196: invokevirtual #72                 // Method org/apache/hbase/thirdparty/com/google/protobuf/RepeatedFieldBuilderV3.isEmpty:()Z
     199: ifeq          254
     202: aload_0
     203: getfield      #26                 // Field waitingProceduresBuilder_:Lorg/apache/hbase/thirdparty/com/google/protobuf/RepeatedFieldBuilderV3;
     206: invokevirtual #73                 // Method org/apache/hbase/thirdparty/com/google/protobuf/RepeatedFieldBuilderV3.dispose:()V
     209: aload_0
     210: aconst_null
     211: putfield      #26                 // Field waitingProceduresBuilder_:Lorg/apache/hbase/thirdparty/com/google/protobuf/RepeatedFieldBuilderV3;
     214: aload_0
     215: aload_1
     216: invokestatic  #68                 // Method org/apache/hadoop/hbase/shaded/protobuf/generated/LockServiceProtos$LockedResource.access$7600:(Lorg/apache/hadoop/hbase/shaded/protobuf/generated/LockServiceProtos$LockedResource;)Ljava/util/List;
     219: putfield      #15                 // Field waitingProcedures_:Ljava/util/List;
     222: aload_0
     223: aload_0
     224: getfield      #22                 // Field bitField0_:I
     227: bipush        -33
     229: iand
     230: putfield      #22                 // Field bitField0_:I
     233: aload_0
     234: invokestatic  #74                 // Method org/apache/hadoop/hbase/shaded/protobuf/generated/LockServiceProtos$LockedResource.access$7800:()Z
     237: ifeq          247
     240: aload_0
     241: invokespecial #20                 // Method getWaitingProceduresFieldBuilder:()Lorg/apache/hbase/thirdparty/com/google/protobuf/RepeatedFieldBuilderV3;
     244: goto          248
     247: aconst_null
     248: putfield      #26                 // Field waitingProceduresBuilder_:Lorg/apache/hbase/thirdparty/com/google/protobuf/RepeatedFieldBuilderV3;
     251: goto          266
     254: aload_0
     255: getfield      #26                 // Field waitingProceduresBuilder_:Lorg/apache/hbase/thirdparty/com/google/protobuf/RepeatedFieldBuilderV3;
     258: aload_1
     259: invokestatic  #68                 // Method org/apache/hadoop/hbase/shaded/protobuf/generated/LockServiceProtos$LockedResource.access$7600:(Lorg/apache/hadoop/hbase/shaded/protobuf/generated/LockServiceProtos$LockedResource;)Ljava/util/List;
     262: invokevirtual #75                 // Method org/apache/hbase/thirdparty/com/google/protobuf/RepeatedFieldBuilderV3.addAllMessages:(Ljava/lang/Iterable;)Lorg/apache/hbase/thirdparty/com/google/protobuf/RepeatedFieldBuilderV3;
     265: pop
     266: aload_0
     267: aload_1
     268: invokestatic  #76                 // Method org/apache/hadoop/hbase/shaded/protobuf/generated/LockServiceProtos$LockedResource.access$7900:(Lorg/apache/hadoop/hbase/shaded/protobuf/generated/LockServiceProtos$LockedResource;)Lorg/apache/hbase/thirdparty/com/google/protobuf/UnknownFieldSet;
     271: invokevirtual #77                 // Method mergeUnknownFields:(Lorg/apache/hbase/thirdparty/com/google/protobuf/UnknownFieldSet;)Lorg/apache/hadoop/hbase/shaded/protobuf/generated/LockServiceProtos$LockedResource$Builder;
     274: pop
     275: aload_0
     276: invokevirtual #58                 // Method onChanged:()V
     279: aload_0
     280: areturn

  public final boolean isInitialized();
    Code:
       0: aload_0
       1: invokevirtual #78                 // Method hasResourceType:()Z
       4: ifne          9
       7: iconst_0
       8: ireturn
       9: aload_0
      10: invokevirtual #79                 // Method hasLockType:()Z
      13: ifne          18
      16: iconst_0
      17: ireturn
      18: aload_0
      19: invokevirtual #80                 // Method hasExclusiveLockOwnerProcedure:()Z
      22: ifeq          37
      25: aload_0
      26: invokevirtual #81                 // Method getExclusiveLockOwnerProcedure:()Lorg/apache/hadoop/hbase/shaded/protobuf/generated/ProcedureProtos$Procedure;
      29: invokevirtual #82                 // Method org/apache/hadoop/hbase/shaded/protobuf/generated/ProcedureProtos$Procedure.isInitialized:()Z
      32: ifne          37
      35: iconst_0
      36: ireturn
      37: iconst_0
      38: istore_1
      39: iload_1
      40: aload_0
      41: invokevirtual #83                 // Method getWaitingProceduresCount:()I
      44: if_icmpge     66
      47: aload_0
      48: iload_1
      49: invokevirtual #84                 // Method getWaitingProcedures:(I)Lorg/apache/hadoop/hbase/shaded/protobuf/generated/ProcedureProtos$Procedure;
      52: invokevirtual #82                 // Method org/apache/hadoop/hbase/shaded/protobuf/generated/ProcedureProtos$Procedure.isInitialized:()Z
      55: ifne          60
      58: iconst_0
      59: ireturn
      60: iinc          1, 1
      63: goto          39
      66: iconst_1
      67: ireturn

  public org.apache.hadoop.hbase.shaded.protobuf.generated.LockServiceProtos$LockedResource$Builder mergeFrom(org.apache.hbase.thirdparty.com.google.protobuf.CodedInputStream, org.apache.hbase.thirdparty.com.google.protobuf.ExtensionRegistryLite) throws java.io.IOException;
    Code:
       0: aconst_null
       1: astore_3
       2: getstatic     #85                 // Field org/apache/hadoop/hbase/shaded/protobuf/generated/LockServiceProtos$LockedResource.PARSER:Lorg/apache/hbase/thirdparty/com/google/protobuf/Parser;
       5: aload_1
       6: aload_2
       7: invokeinterface #86,  3           // InterfaceMethod org/apache/hbase/thirdparty/com/google/protobuf/Parser.parsePartialFrom:(Lorg/apache/hbase/thirdparty/com/google/protobuf/CodedInputStream;Lorg/apache/hbase/thirdparty/com/google/protobuf/ExtensionRegistryLite;)Ljava/lang/Object;
      12: checkcast     #5                  // class org/apache/hadoop/hbase/shaded/protobuf/generated/LockServiceProtos$LockedResource
      15: astore_3
      16: aload_3
      17: ifnull        61
      20: aload_0
      21: aload_3
      22: invokevirtual #51                 // Method mergeFrom:(Lorg/apache/hadoop/hbase/shaded/protobuf/generated/LockServiceProtos$LockedResource;)Lorg/apache/hadoop/hbase/shaded/protobuf/generated/LockServiceProtos$LockedResource$Builder;
      25: pop
      26: goto          61
      29: astore        4
      31: aload         4
      33: invokevirtual #88                 // Method org/apache/hbase/thirdparty/com/google/protobuf/InvalidProtocolBufferException.getUnfinishedMessage:()Lorg/apache/hbase/thirdparty/com/google/protobuf/MessageLite;
      36: checkcast     #5                  // class org/apache/hadoop/hbase/shaded/protobuf/generated/LockServiceProtos$LockedResource
      39: astore_3
      40: aload         4
      42: invokevirtual #89                 // Method org/apache/hbase/thirdparty/com/google/protobuf/InvalidProtocolBufferException.unwrapIOException:()Ljava/io/IOException;
      45: athrow
      46: astore        5
      48: aload_3
      49: ifnull        58
      52: aload_0
      53: aload_3
      54: invokevirtual #51                 // Method mergeFrom:(Lorg/apache/hadoop/hbase/shaded/protobuf/generated/LockServiceProtos$LockedResource;)Lorg/apache/hadoop/hbase/shaded/protobuf/generated/LockServiceProtos$LockedResource$Builder;
      57: pop
      58: aload         5
      60: athrow
      61: aload_0
      62: areturn
    Exception table:
       from    to  target type
           2    16    29   Class org/apache/hbase/thirdparty/com/google/protobuf/InvalidProtocolBufferException
           2    16    46   any
          29    48    46   any

  public boolean hasResourceType();
    Code:
       0: aload_0
       1: getfield      #22                 // Field bitField0_:I
       4: iconst_1
       5: iand
       6: iconst_1
       7: if_icmpne     14
      10: iconst_1
      11: goto          15
      14: iconst_0
      15: ireturn

  public org.apache.hadoop.hbase.shaded.protobuf.generated.LockServiceProtos$LockedResourceType getResourceType();
    Code:
       0: aload_0
       1: getfield      #9                  // Field resourceType_:I
       4: invokestatic  #90                 // Method org/apache/hadoop/hbase/shaded/protobuf/generated/LockServiceProtos$LockedResourceType.valueOf:(I)Lorg/apache/hadoop/hbase/shaded/protobuf/generated/LockServiceProtos$LockedResourceType;
       7: astore_1
       8: aload_1
       9: ifnonnull     18
      12: getstatic     #91                 // Field org/apache/hadoop/hbase/shaded/protobuf/generated/LockServiceProtos$LockedResourceType.SERVER:Lorg/apache/hadoop/hbase/shaded/protobuf/generated/LockServiceProtos$LockedResourceType;
      15: goto          19
      18: aload_1
      19: areturn

  public org.apache.hadoop.hbase.shaded.protobuf.generated.LockServiceProtos$LockedResource$Builder setResourceType(org.apache.hadoop.hbase.shaded.protobuf.generated.LockServiceProtos$LockedResourceType);
    Code:
       0: aload_1
       1: ifnonnull     12
       4: new           #92                 // class java/lang/NullPointerException
       7: dup
       8: invokespecial #93                 // Method java/lang/NullPointerException."<init>":()V
      11: athrow
      12: aload_0
      13: dup
      14: getfield      #22                 // Field bitField0_:I
      17: iconst_1
      18: ior
      19: putfield      #22                 // Field bitField0_:I
      22: aload_0
      23: aload_1
      24: invokevirtual #94                 // Method org/apache/hadoop/hbase/shaded/protobuf/generated/LockServiceProtos$LockedResourceType.getNumber:()I
      27: putfield      #9                  // Field resourceType_:I
      30: aload_0
      31: invokevirtual #58                 // Method onChanged:()V
      34: aload_0
      35: areturn

  public org.apache.hadoop.hbase.shaded.protobuf.generated.LockServiceProtos$LockedResource$Builder clearResourceType();
    Code:
       0: aload_0
       1: aload_0
       2: getfield      #22                 // Field bitField0_:I
       5: bipush        -2
       7: iand
       8: putfield      #22                 // Field bitField0_:I
      11: aload_0
      12: iconst_1
      13: putfield      #9                  // Field resourceType_:I
      16: aload_0
      17: invokevirtual #58                 // Method onChanged:()V
      20: aload_0
      21: areturn

  public boolean hasResourceName();
    Code:
       0: aload_0
       1: getfield      #22                 // Field bitField0_:I
       4: iconst_2
       5: iand
       6: iconst_2
       7: if_icmpne     14
      10: iconst_1
      11: goto          15
      14: iconst_0
      15: ireturn

  public java.lang.String getResourceName();
    Code:
       0: aload_0
       1: getfield      #11                 // Field resourceName_:Ljava/lang/Object;
       4: astore_1
       5: aload_1
       6: instanceof    #95                 // class java/lang/String
       9: ifne          36
      12: aload_1
      13: checkcast     #96                 // class org/apache/hbase/thirdparty/com/google/protobuf/ByteString
      16: astore_2
      17: aload_2
      18: invokevirtual #97                 // Method org/apache/hbase/thirdparty/com/google/protobuf/ByteString.toStringUtf8:()Ljava/lang/String;
      21: astore_3
      22: aload_2
      23: invokevirtual #98                 // Method org/apache/hbase/thirdparty/com/google/protobuf/ByteString.isValidUtf8:()Z
      26: ifeq          34
      29: aload_0
      30: aload_3
      31: putfield      #11                 // Field resourceName_:Ljava/lang/Object;
      34: aload_3
      35: areturn
      36: aload_1
      37: checkcast     #95                 // class java/lang/String
      40: areturn

  public org.apache.hbase.thirdparty.com.google.protobuf.ByteString getResourceNameBytes();
    Code:
       0: aload_0
       1: getfield      #11                 // Field resourceName_:Ljava/lang/Object;
       4: astore_1
       5: aload_1
       6: instanceof    #95                 // class java/lang/String
       9: ifeq          27
      12: aload_1
      13: checkcast     #95                 // class java/lang/String
      16: invokestatic  #99                 // Method org/apache/hbase/thirdparty/com/google/protobuf/ByteString.copyFromUtf8:(Ljava/lang/String;)Lorg/apache/hbase/thirdparty/com/google/protobuf/ByteString;
      19: astore_2
      20: aload_0
      21: aload_2
      22: putfield      #11                 // Field resourceName_:Ljava/lang/Object;
      25: aload_2
      26: areturn
      27: aload_1
      28: checkcast     #96                 // class org/apache/hbase/thirdparty/com/google/protobuf/ByteString
      31: areturn

  public org.apache.hadoop.hbase.shaded.protobuf.generated.LockServiceProtos$LockedResource$Builder setResourceName(java.lang.String);
    Code:
       0: aload_1
       1: ifnonnull     12
       4: new           #92                 // class java/lang/NullPointerException
       7: dup
       8: invokespecial #93                 // Method java/lang/NullPointerException."<init>":()V
      11: athrow
      12: aload_0
      13: dup
      14: getfield      #22                 // Field bitField0_:I
      17: iconst_2
      18: ior
      19: putfield      #22                 // Field bitField0_:I
      22: aload_0
      23: aload_1
      24: putfield      #11                 // Field resourceName_:Ljava/lang/Object;
      27: aload_0
      28: invokevirtual #58                 // Method onChanged:()V
      31: aload_0
      32: areturn

  public org.apache.hadoop.hbase.shaded.protobuf.generated.LockServiceProtos$LockedResource$Builder clearResourceName();
    Code:
       0: aload_0
       1: aload_0
       2: getfield      #22                 // Field bitField0_:I
       5: bipush        -3
       7: iand
       8: putfield      #22                 // Field bitField0_:I
      11: aload_0
      12: invokestatic  #28                 // Method org/apache/hadoop/hbase/shaded/protobuf/generated/LockServiceProtos$LockedResource.getDefaultInstance:()Lorg/apache/hadoop/hbase/shaded/protobuf/generated/LockServiceProtos$LockedResource;
      15: invokevirtual #100                // Method org/apache/hadoop/hbase/shaded/protobuf/generated/LockServiceProtos$LockedResource.getResourceName:()Ljava/lang/String;
      18: putfield      #11                 // Field resourceName_:Ljava/lang/Object;
      21: aload_0
      22: invokevirtual #58                 // Method onChanged:()V
      25: aload_0
      26: areturn

  public org.apache.hadoop.hbase.shaded.protobuf.generated.LockServiceProtos$LockedResource$Builder setResourceNameBytes(org.apache.hbase.thirdparty.com.google.protobuf.ByteString);
    Code:
       0: aload_1
       1: ifnonnull     12
       4: new           #92                 // class java/lang/NullPointerException
       7: dup
       8: invokespecial #93                 // Method java/lang/NullPointerException."<init>":()V
      11: athrow
      12: aload_0
      13: dup
      14: getfield      #22                 // Field bitField0_:I
      17: iconst_2
      18: ior
      19: putfield      #22                 // Field bitField0_:I
      22: aload_0
      23: aload_1
      24: putfield      #11                 // Field resourceName_:Ljava/lang/Object;
      27: aload_0
      28: invokevirtual #58                 // Method onChanged:()V
      31: aload_0
      32: areturn

  public boolean hasLockType();
    Code:
       0: aload_0
       1: getfield      #22                 // Field bitField0_:I
       4: iconst_4
       5: iand
       6: iconst_4
       7: if_icmpne     14
      10: iconst_1
      11: goto          15
      14: iconst_0
      15: ireturn

  public org.apache.hadoop.hbase.shaded.protobuf.generated.LockServiceProtos$LockType getLockType();
    Code:
       0: aload_0
       1: getfield      #12                 // Field lockType_:I
       4: invokestatic  #101                // Method org/apache/hadoop/hbase/shaded/protobuf/generated/LockServiceProtos$LockType.valueOf:(I)Lorg/apache/hadoop/hbase/shaded/protobuf/generated/LockServiceProtos$LockType;
       7: astore_1
       8: aload_1
       9: ifnonnull     18
      12: getstatic     #102                // Field org/apache/hadoop/hbase/shaded/protobuf/generated/LockServiceProtos$LockType.EXCLUSIVE:Lorg/apache/hadoop/hbase/shaded/protobuf/generated/LockServiceProtos$LockType;
      15: goto          19
      18: aload_1
      19: areturn

  public org.apache.hadoop.hbase.shaded.protobuf.generated.LockServiceProtos$LockedResource$Builder setLockType(org.apache.hadoop.hbase.shaded.protobuf.generated.LockServiceProtos$LockType);
    Code:
       0: aload_1
       1: ifnonnull     12
       4: new           #92                 // class java/lang/NullPointerException
       7: dup
       8: invokespecial #93                 // Method java/lang/NullPointerException."<init>":()V
      11: athrow
      12: aload_0
      13: dup
      14: getfield      #22                 // Field bitField0_:I
      17: iconst_4
      18: ior
      19: putfield      #22                 // Field bitField0_:I
      22: aload_0
      23: aload_1
      24: invokevirtual #103                // Method org/apache/hadoop/hbase/shaded/protobuf/generated/LockServiceProtos$LockType.getNumber:()I
      27: putfield      #12                 // Field lockType_:I
      30: aload_0
      31: invokevirtual #58                 // Method onChanged:()V
      34: aload_0
      35: areturn

  public org.apache.hadoop.hbase.shaded.protobuf.generated.LockServiceProtos$LockedResource$Builder clearLockType();
    Code:
       0: aload_0
       1: aload_0
       2: getfield      #22                 // Field bitField0_:I
       5: bipush        -5
       7: iand
       8: putfield      #22                 // Field bitField0_:I
      11: aload_0
      12: iconst_1
      13: putfield      #12                 // Field lockType_:I
      16: aload_0
      17: invokevirtual #58                 // Method onChanged:()V
      20: aload_0
      21: areturn

  public boolean hasExclusiveLockOwnerProcedure();
    Code:
       0: aload_0
       1: getfield      #22                 // Field bitField0_:I
       4: bipush        8
       6: iand
       7: bipush        8
       9: if_icmpne     16
      12: iconst_1
      13: goto          17
      16: iconst_0
      17: ireturn

  public org.apache.hadoop.hbase.shaded.protobuf.generated.ProcedureProtos$Procedure getExclusiveLockOwnerProcedure();
    Code:
       0: aload_0
       1: getfield      #23                 // Field exclusiveLockOwnerProcedureBuilder_:Lorg/apache/hbase/thirdparty/com/google/protobuf/SingleFieldBuilderV3;
       4: ifnonnull     25
       7: aload_0
       8: getfield      #13                 // Field exclusiveLockOwnerProcedure_:Lorg/apache/hadoop/hbase/shaded/protobuf/generated/ProcedureProtos$Procedure;
      11: ifnonnull     20
      14: invokestatic  #104                // Method org/apache/hadoop/hbase/shaded/protobuf/generated/ProcedureProtos$Procedure.getDefaultInstance:()Lorg/apache/hadoop/hbase/shaded/protobuf/generated/ProcedureProtos$Procedure;
      17: goto          24
      20: aload_0
      21: getfield      #13                 // Field exclusiveLockOwnerProcedure_:Lorg/apache/hadoop/hbase/shaded/protobuf/generated/ProcedureProtos$Procedure;
      24: areturn
      25: aload_0
      26: getfield      #23                 // Field exclusiveLockOwnerProcedureBuilder_:Lorg/apache/hbase/thirdparty/com/google/protobuf/SingleFieldBuilderV3;
      29: invokevirtual #105                // Method org/apache/hbase/thirdparty/com/google/protobuf/SingleFieldBuilderV3.getMessage:()Lorg/apache/hbase/thirdparty/com/google/protobuf/AbstractMessage;
      32: checkcast     #38                 // class org/apache/hadoop/hbase/shaded/protobuf/generated/ProcedureProtos$Procedure
      35: areturn

  public org.apache.hadoop.hbase.shaded.protobuf.generated.LockServiceProtos$LockedResource$Builder setExclusiveLockOwnerProcedure(org.apache.hadoop.hbase.shaded.protobuf.generated.ProcedureProtos$Procedure);
    Code:
       0: aload_0
       1: getfield      #23                 // Field exclusiveLockOwnerProcedureBuilder_:Lorg/apache/hbase/thirdparty/com/google/protobuf/SingleFieldBuilderV3;
       4: ifnonnull     31
       7: aload_1
       8: ifnonnull     19
      11: new           #92                 // class java/lang/NullPointerException
      14: dup
      15: invokespecial #93                 // Method java/lang/NullPointerException."<init>":()V
      18: athrow
      19: aload_0
      20: aload_1
      21: putfield      #13                 // Field exclusiveLockOwnerProcedure_:Lorg/apache/hadoop/hbase/shaded/protobuf/generated/ProcedureProtos$Procedure;
      24: aload_0
      25: invokevirtual #58                 // Method onChanged:()V
      28: goto          40
      31: aload_0
      32: getfield      #23                 // Field exclusiveLockOwnerProcedureBuilder_:Lorg/apache/hbase/thirdparty/com/google/protobuf/SingleFieldBuilderV3;
      35: aload_1
      36: invokevirtual #106                // Method org/apache/hbase/thirdparty/com/google/protobuf/SingleFieldBuilderV3.setMessage:(Lorg/apache/hbase/thirdparty/com/google/protobuf/AbstractMessage;)Lorg/apache/hbase/thirdparty/com/google/protobuf/SingleFieldBuilderV3;
      39: pop
      40: aload_0
      41: dup
      42: getfield      #22                 // Field bitField0_:I
      45: bipush        8
      47: ior
      48: putfield      #22                 // Field bitField0_:I
      51: aload_0
      52: areturn

  public org.apache.hadoop.hbase.shaded.protobuf.generated.LockServiceProtos$LockedResource$Builder setExclusiveLockOwnerProcedure(org.apache.hadoop.hbase.shaded.protobuf.generated.ProcedureProtos$Procedure$Builder);
    Code:
       0: aload_0
       1: getfield      #23                 // Field exclusiveLockOwnerProcedureBuilder_:Lorg/apache/hbase/thirdparty/com/google/protobuf/SingleFieldBuilderV3;
       4: ifnonnull     22
       7: aload_0
       8: aload_1
       9: invokevirtual #107                // Method org/apache/hadoop/hbase/shaded/protobuf/generated/ProcedureProtos$Procedure$Builder.build:()Lorg/apache/hadoop/hbase/shaded/protobuf/generated/ProcedureProtos$Procedure;
      12: putfield      #13                 // Field exclusiveLockOwnerProcedure_:Lorg/apache/hadoop/hbase/shaded/protobuf/generated/ProcedureProtos$Procedure;
      15: aload_0
      16: invokevirtual #58                 // Method onChanged:()V
      19: goto          34
      22: aload_0
      23: getfield      #23                 // Field exclusiveLockOwnerProcedureBuilder_:Lorg/apache/hbase/thirdparty/com/google/protobuf/SingleFieldBuilderV3;
      26: aload_1
      27: invokevirtual #107                // Method org/apache/hadoop/hbase/shaded/protobuf/generated/ProcedureProtos$Procedure$Builder.build:()Lorg/apache/hadoop/hbase/shaded/protobuf/generated/ProcedureProtos$Procedure;
      30: invokevirtual #106                // Method org/apache/hbase/thirdparty/com/google/protobuf/SingleFieldBuilderV3.setMessage:(Lorg/apache/hbase/thirdparty/com/google/protobuf/AbstractMessage;)Lorg/apache/hbase/thirdparty/com/google/protobuf/SingleFieldBuilderV3;
      33: pop
      34: aload_0
      35: dup
      36: getfield      #22                 // Field bitField0_:I
      39: bipush        8
      41: ior
      42: putfield      #22                 // Field bitField0_:I
      45: aload_0
      46: areturn

  public org.apache.hadoop.hbase.shaded.protobuf.generated.LockServiceProtos$LockedResource$Builder mergeExclusiveLockOwnerProcedure(org.apache.hadoop.hbase.shaded.protobuf.generated.ProcedureProtos$Procedure);
    Code:
       0: aload_0
       1: getfield      #23                 // Field exclusiveLockOwnerProcedureBuilder_:Lorg/apache/hbase/thirdparty/com/google/protobuf/SingleFieldBuilderV3;
       4: ifnonnull     69
       7: aload_0
       8: getfield      #22                 // Field bitField0_:I
      11: bipush        8
      13: iand
      14: bipush        8
      16: if_icmpne     57
      19: aload_0
      20: getfield      #13                 // Field exclusiveLockOwnerProcedure_:Lorg/apache/hadoop/hbase/shaded/protobuf/generated/ProcedureProtos$Procedure;
      23: ifnull        57
      26: aload_0
      27: getfield      #13                 // Field exclusiveLockOwnerProcedure_:Lorg/apache/hadoop/hbase/shaded/protobuf/generated/ProcedureProtos$Procedure;
      30: invokestatic  #104                // Method org/apache/hadoop/hbase/shaded/protobuf/generated/ProcedureProtos$Procedure.getDefaultInstance:()Lorg/apache/hadoop/hbase/shaded/protobuf/generated/ProcedureProtos$Procedure;
      33: if_acmpeq     57
      36: aload_0
      37: aload_0
      38: getfield      #13                 // Field exclusiveLockOwnerProcedure_:Lorg/apache/hadoop/hbase/shaded/protobuf/generated/ProcedureProtos$Procedure;
      41: invokestatic  #108                // Method org/apache/hadoop/hbase/shaded/protobuf/generated/ProcedureProtos$Procedure.newBuilder:(Lorg/apache/hadoop/hbase/shaded/protobuf/generated/ProcedureProtos$Procedure;)Lorg/apache/hadoop/hbase/shaded/protobuf/generated/ProcedureProtos$Procedure$Builder;
      44: aload_1
      45: invokevirtual #109                // Method org/apache/hadoop/hbase/shaded/protobuf/generated/ProcedureProtos$Procedure$Builder.mergeFrom:(Lorg/apache/hadoop/hbase/shaded/protobuf/generated/ProcedureProtos$Procedure;)Lorg/apache/hadoop/hbase/shaded/protobuf/generated/ProcedureProtos$Procedure$Builder;
      48: invokevirtual #110                // Method org/apache/hadoop/hbase/shaded/protobuf/generated/ProcedureProtos$Procedure$Builder.buildPartial:()Lorg/apache/hadoop/hbase/shaded/protobuf/generated/ProcedureProtos$Procedure;
      51: putfield      #13                 // Field exclusiveLockOwnerProcedure_:Lorg/apache/hadoop/hbase/shaded/protobuf/generated/ProcedureProtos$Procedure;
      54: goto          62
      57: aload_0
      58: aload_1
      59: putfield      #13                 // Field exclusiveLockOwnerProcedure_:Lorg/apache/hadoop/hbase/shaded/protobuf/generated/ProcedureProtos$Procedure;
      62: aload_0
      63: invokevirtual #58                 // Method onChanged:()V
      66: goto          78
      69: aload_0
      70: getfield      #23                 // Field exclusiveLockOwnerProcedureBuilder_:Lorg/apache/hbase/thirdparty/com/google/protobuf/SingleFieldBuilderV3;
      73: aload_1
      74: invokevirtual #111                // Method org/apache/hbase/thirdparty/com/google/protobuf/SingleFieldBuilderV3.mergeFrom:(Lorg/apache/hbase/thirdparty/com/google/protobuf/AbstractMessage;)Lorg/apache/hbase/thirdparty/com/google/protobuf/SingleFieldBuilderV3;
      77: pop
      78: aload_0
      79: dup
      80: getfield      #22                 // Field bitField0_:I
      83: bipush        8
      85: ior
      86: putfield      #22                 // Field bitField0_:I
      89: aload_0
      90: areturn

  public org.apache.hadoop.hbase.shaded.protobuf.generated.LockServiceProtos$LockedResource$Builder clearExclusiveLockOwnerProcedure();
    Code:
       0: aload_0
       1: getfield      #23                 // Field exclusiveLockOwnerProcedureBuilder_:Lorg/apache/hbase/thirdparty/com/google/protobuf/SingleFieldBuilderV3;
       4: ifnonnull     19
       7: aload_0
       8: aconst_null
       9: putfield      #13                 // Field exclusiveLockOwnerProcedure_:Lorg/apache/hadoop/hbase/shaded/protobuf/generated/ProcedureProtos$Procedure;
      12: aload_0
      13: invokevirtual #58                 // Method onChanged:()V
      16: goto          27
      19: aload_0
      20: getfield      #23                 // Field exclusiveLockOwnerProcedureBuilder_:Lorg/apache/hbase/thirdparty/com/google/protobuf/SingleFieldBuilderV3;
      23: invokevirtual #24                 // Method org/apache/hbase/thirdparty/com/google/protobuf/SingleFieldBuilderV3.clear:()Lorg/apache/hbase/thirdparty/com/google/protobuf/SingleFieldBuilderV3;
      26: pop
      27: aload_0
      28: aload_0
      29: getfield      #22                 // Field bitField0_:I
      32: bipush        -9
      34: iand
      35: putfield      #22                 // Field bitField0_:I
      38: aload_0
      39: areturn

  public org.apache.hadoop.hbase.shaded.protobuf.generated.ProcedureProtos$Procedure$Builder getExclusiveLockOwnerProcedureBuilder();
    Code:
       0: aload_0
       1: dup
       2: getfield      #22                 // Field bitField0_:I
       5: bipush        8
       7: ior
       8: putfield      #22                 // Field bitField0_:I
      11: aload_0
      12: invokevirtual #58                 // Method onChanged:()V
      15: aload_0
      16: invokespecial #19                 // Method getExclusiveLockOwnerProcedureFieldBuilder:()Lorg/apache/hbase/thirdparty/com/google/protobuf/SingleFieldBuilderV3;
      19: invokevirtual #112                // Method org/apache/hbase/thirdparty/com/google/protobuf/SingleFieldBuilderV3.getBuilder:()Lorg/apache/hbase/thirdparty/com/google/protobuf/AbstractMessage$Builder;
      22: checkcast     #113                // class org/apache/hadoop/hbase/shaded/protobuf/generated/ProcedureProtos$Procedure$Builder
      25: areturn

  public org.apache.hadoop.hbase.shaded.protobuf.generated.ProcedureProtos$ProcedureOrBuilder getExclusiveLockOwnerProcedureOrBuilder();
    Code:
       0: aload_0
       1: getfield      #23                 // Field exclusiveLockOwnerProcedureBuilder_:Lorg/apache/hbase/thirdparty/com/google/protobuf/SingleFieldBuilderV3;
       4: ifnull        18
       7: aload_0
       8: getfield      #23                 // Field exclusiveLockOwnerProcedureBuilder_:Lorg/apache/hbase/thirdparty/com/google/protobuf/SingleFieldBuilderV3;
      11: invokevirtual #114                // Method org/apache/hbase/thirdparty/com/google/protobuf/SingleFieldBuilderV3.getMessageOrBuilder:()Lorg/apache/hbase/thirdparty/com/google/protobuf/MessageOrBuilder;
      14: checkcast     #115                // class org/apache/hadoop/hbase/shaded/protobuf/generated/ProcedureProtos$ProcedureOrBuilder
      17: areturn
      18: aload_0
      19: getfield      #13                 // Field exclusiveLockOwnerProcedure_:Lorg/apache/hadoop/hbase/shaded/protobuf/generated/ProcedureProtos$Procedure;
      22: ifnonnull     31
      25: invokestatic  #104                // Method org/apache/hadoop/hbase/shaded/protobuf/generated/ProcedureProtos$Procedure.getDefaultInstance:()Lorg/apache/hadoop/hbase/shaded/protobuf/generated/ProcedureProtos$Procedure;
      28: goto          35
      31: aload_0
      32: getfield      #13                 // Field exclusiveLockOwnerProcedure_:Lorg/apache/hadoop/hbase/shaded/protobuf/generated/ProcedureProtos$Procedure;
      35: areturn

  public boolean hasSharedLockCount();
    Code:
       0: aload_0
       1: getfield      #22                 // Field bitField0_:I
       4: bipush        16
       6: iand
       7: bipush        16
       9: if_icmpne     16
      12: iconst_1
      13: goto          17
      16: iconst_0
      17: ireturn

  public int getSharedLockCount();
    Code:
       0: aload_0
       1: getfield      #25                 // Field sharedLockCount_:I
       4: ireturn

  public org.apache.hadoop.hbase.shaded.protobuf.generated.LockServiceProtos$LockedResource$Builder setSharedLockCount(int);
    Code:
       0: aload_0
       1: dup
       2: getfield      #22                 // Field bitField0_:I
       5: bipush        16
       7: ior
       8: putfield      #22                 // Field bitField0_:I
      11: aload_0
      12: iload_1
      13: putfield      #25                 // Field sharedLockCount_:I
      16: aload_0
      17: invokevirtual #58                 // Method onChanged:()V
      20: aload_0
      21: areturn

  public org.apache.hadoop.hbase.shaded.protobuf.generated.LockServiceProtos$LockedResource$Builder clearSharedLockCount();
    Code:
       0: aload_0
       1: aload_0
       2: getfield      #22                 // Field bitField0_:I
       5: bipush        -17
       7: iand
       8: putfield      #22                 // Field bitField0_:I
      11: aload_0
      12: iconst_0
      13: putfield      #25                 // Field sharedLockCount_:I
      16: aload_0
      17: invokevirtual #58                 // Method onChanged:()V
      20: aload_0
      21: areturn

  public java.util.List<org.apache.hadoop.hbase.shaded.protobuf.generated.ProcedureProtos$Procedure> getWaitingProceduresList();
    Code:
       0: aload_0
       1: getfield      #26                 // Field waitingProceduresBuilder_:Lorg/apache/hbase/thirdparty/com/google/protobuf/RepeatedFieldBuilderV3;
       4: ifnonnull     15
       7: aload_0
       8: getfield      #15                 // Field waitingProcedures_:Ljava/util/List;
      11: invokestatic  #40                 // Method java/util/Collections.unmodifiableList:(Ljava/util/List;)Ljava/util/List;
      14: areturn
      15: aload_0
      16: getfield      #26                 // Field waitingProceduresBuilder_:Lorg/apache/hbase/thirdparty/com/google/protobuf/RepeatedFieldBuilderV3;
      19: invokevirtual #122                // Method org/apache/hbase/thirdparty/com/google/protobuf/RepeatedFieldBuilderV3.getMessageList:()Ljava/util/List;
      22: areturn

  public int getWaitingProceduresCount();
    Code:
       0: aload_0
       1: getfield      #26                 // Field waitingProceduresBuilder_:Lorg/apache/hbase/thirdparty/com/google/protobuf/RepeatedFieldBuilderV3;
       4: ifnonnull     17
       7: aload_0
       8: getfield      #15                 // Field waitingProcedures_:Ljava/util/List;
      11: invokeinterface #123,  1          // InterfaceMethod java/util/List.size:()I
      16: ireturn
      17: aload_0
      18: getfield      #26                 // Field waitingProceduresBuilder_:Lorg/apache/hbase/thirdparty/com/google/protobuf/RepeatedFieldBuilderV3;
      21: invokevirtual #124                // Method org/apache/hbase/thirdparty/com/google/protobuf/RepeatedFieldBuilderV3.getCount:()I
      24: ireturn

  public org.apache.hadoop.hbase.shaded.protobuf.generated.ProcedureProtos$Procedure getWaitingProcedures(int);
    Code:
       0: aload_0
       1: getfield      #26                 // Field waitingProceduresBuilder_:Lorg/apache/hbase/thirdparty/com/google/protobuf/RepeatedFieldBuilderV3;
       4: ifnonnull     21
       7: aload_0
       8: getfield      #15                 // Field waitingProcedures_:Ljava/util/List;
      11: iload_1
      12: invokeinterface #125,  2          // InterfaceMethod java/util/List.get:(I)Ljava/lang/Object;
      17: checkcast     #38                 // class org/apache/hadoop/hbase/shaded/protobuf/generated/ProcedureProtos$Procedure
      20: areturn
      21: aload_0
      22: getfield      #26                 // Field waitingProceduresBuilder_:Lorg/apache/hbase/thirdparty/com/google/protobuf/RepeatedFieldBuilderV3;
      25: iload_1
      26: invokevirtual #126                // Method org/apache/hbase/thirdparty/com/google/protobuf/RepeatedFieldBuilderV3.getMessage:(I)Lorg/apache/hbase/thirdparty/com/google/protobuf/AbstractMessage;
      29: checkcast     #38                 // class org/apache/hadoop/hbase/shaded/protobuf/generated/ProcedureProtos$Procedure
      32: areturn

  public org.apache.hadoop.hbase.shaded.protobuf.generated.LockServiceProtos$LockedResource$Builder setWaitingProcedures(int, org.apache.hadoop.hbase.shaded.protobuf.generated.ProcedureProtos$Procedure);
    Code:
       0: aload_0
       1: getfield      #26                 // Field waitingProceduresBuilder_:Lorg/apache/hbase/thirdparty/com/google/protobuf/RepeatedFieldBuilderV3;
       4: ifnonnull     42
       7: aload_2
       8: ifnonnull     19
      11: new           #92                 // class java/lang/NullPointerException
      14: dup
      15: invokespecial #93                 // Method java/lang/NullPointerException."<init>":()V
      18: athrow
      19: aload_0
      20: invokespecial #70                 // Method ensureWaitingProceduresIsMutable:()V
      23: aload_0
      24: getfield      #15                 // Field waitingProcedures_:Ljava/util/List;
      27: iload_1
      28: aload_2
      29: invokeinterface #127,  3          // InterfaceMethod java/util/List.set:(ILjava/lang/Object;)Ljava/lang/Object;
      34: pop
      35: aload_0
      36: invokevirtual #58                 // Method onChanged:()V
      39: goto          52
      42: aload_0
      43: getfield      #26                 // Field waitingProceduresBuilder_:Lorg/apache/hbase/thirdparty/com/google/protobuf/RepeatedFieldBuilderV3;
      46: iload_1
      47: aload_2
      48: invokevirtual #128                // Method org/apache/hbase/thirdparty/com/google/protobuf/RepeatedFieldBuilderV3.setMessage:(ILorg/apache/hbase/thirdparty/com/google/protobuf/AbstractMessage;)Lorg/apache/hbase/thirdparty/com/google/protobuf/RepeatedFieldBuilderV3;
      51: pop
      52: aload_0
      53: areturn

  public org.apache.hadoop.hbase.shaded.protobuf.generated.LockServiceProtos$LockedResource$Builder setWaitingProcedures(int, org.apache.hadoop.hbase.shaded.protobuf.generated.ProcedureProtos$Procedure$Builder);
    Code:
       0: aload_0
       1: getfield      #26                 // Field waitingProceduresBuilder_:Lorg/apache/hbase/thirdparty/com/google/protobuf/RepeatedFieldBuilderV3;
       4: ifnonnull     33
       7: aload_0
       8: invokespecial #70                 // Method ensureWaitingProceduresIsMutable:()V
      11: aload_0
      12: getfield      #15                 // Field waitingProcedures_:Ljava/util/List;
      15: iload_1
      16: aload_2
      17: invokevirtual #107                // Method org/apache/hadoop/hbase/shaded/protobuf/generated/ProcedureProtos$Procedure$Builder.build:()Lorg/apache/hadoop/hbase/shaded/protobuf/generated/ProcedureProtos$Procedure;
      20: invokeinterface #127,  3          // InterfaceMethod java/util/List.set:(ILjava/lang/Object;)Ljava/lang/Object;
      25: pop
      26: aload_0
      27: invokevirtual #58                 // Method onChanged:()V
      30: goto          46
      33: aload_0
      34: getfield      #26                 // Field waitingProceduresBuilder_:Lorg/apache/hbase/thirdparty/com/google/protobuf/RepeatedFieldBuilderV3;
      37: iload_1
      38: aload_2
      39: invokevirtual #107                // Method org/apache/hadoop/hbase/shaded/protobuf/generated/ProcedureProtos$Procedure$Builder.build:()Lorg/apache/hadoop/hbase/shaded/protobuf/generated/ProcedureProtos$Procedure;
      42: invokevirtual #128                // Method org/apache/hbase/thirdparty/com/google/protobuf/RepeatedFieldBuilderV3.setMessage:(ILorg/apache/hbase/thirdparty/com/google/protobuf/AbstractMessage;)Lorg/apache/hbase/thirdparty/com/google/protobuf/RepeatedFieldBuilderV3;
      45: pop
      46: aload_0
      47: areturn

  public org.apache.hadoop.hbase.shaded.protobuf.generated.LockServiceProtos$LockedResource$Builder addWaitingProcedures(org.apache.hadoop.hbase.shaded.protobuf.generated.ProcedureProtos$Procedure);
    Code:
       0: aload_0
       1: getfield      #26                 // Field waitingProceduresBuilder_:Lorg/apache/hbase/thirdparty/com/google/protobuf/RepeatedFieldBuilderV3;
       4: ifnonnull     41
       7: aload_1
       8: ifnonnull     19
      11: new           #92                 // class java/lang/NullPointerException
      14: dup
      15: invokespecial #93                 // Method java/lang/NullPointerException."<init>":()V
      18: athrow
      19: aload_0
      20: invokespecial #70                 // Method ensureWaitingProceduresIsMutable:()V
      23: aload_0
      24: getfield      #15                 // Field waitingProcedures_:Ljava/util/List;
      27: aload_1
      28: invokeinterface #129,  2          // InterfaceMethod java/util/List.add:(Ljava/lang/Object;)Z
      33: pop
      34: aload_0
      35: invokevirtual #58                 // Method onChanged:()V
      38: goto          50
      41: aload_0
      42: getfield      #26                 // Field waitingProceduresBuilder_:Lorg/apache/hbase/thirdparty/com/google/protobuf/RepeatedFieldBuilderV3;
      45: aload_1
      46: invokevirtual #130                // Method org/apache/hbase/thirdparty/com/google/protobuf/RepeatedFieldBuilderV3.addMessage:(Lorg/apache/hbase/thirdparty/com/google/protobuf/AbstractMessage;)Lorg/apache/hbase/thirdparty/com/google/protobuf/RepeatedFieldBuilderV3;
      49: pop
      50: aload_0
      51: areturn

  public org.apache.hadoop.hbase.shaded.protobuf.generated.LockServiceProtos$LockedResource$Builder addWaitingProcedures(int, org.apache.hadoop.hbase.shaded.protobuf.generated.ProcedureProtos$Procedure);
    Code:
       0: aload_0
       1: getfield      #26                 // Field waitingProceduresBuilder_:Lorg/apache/hbase/thirdparty/com/google/protobuf/RepeatedFieldBuilderV3;
       4: ifnonnull     41
       7: aload_2
       8: ifnonnull     19
      11: new           #92                 // class java/lang/NullPointerException
      14: dup
      15: invokespecial #93                 // Method java/lang/NullPointerException."<init>":()V
      18: athrow
      19: aload_0
      20: invokespecial #70                 // Method ensureWaitingProceduresIsMutable:()V
      23: aload_0
      24: getfield      #15                 // Field waitingProcedures_:Ljava/util/List;
      27: iload_1
      28: aload_2
      29: invokeinterface #131,  3          // InterfaceMethod java/util/List.add:(ILjava/lang/Object;)V
      34: aload_0
      35: invokevirtual #58                 // Method onChanged:()V
      38: goto          51
      41: aload_0
      42: getfield      #26                 // Field waitingProceduresBuilder_:Lorg/apache/hbase/thirdparty/com/google/protobuf/RepeatedFieldBuilderV3;
      45: iload_1
      46: aload_2
      47: invokevirtual #132                // Method org/apache/hbase/thirdparty/com/google/protobuf/RepeatedFieldBuilderV3.addMessage:(ILorg/apache/hbase/thirdparty/com/google/protobuf/AbstractMessage;)Lorg/apache/hbase/thirdparty/com/google/protobuf/RepeatedFieldBuilderV3;
      50: pop
      51: aload_0
      52: areturn

  public org.apache.hadoop.hbase.shaded.protobuf.generated.LockServiceProtos$LockedResource$Builder addWaitingProcedures(org.apache.hadoop.hbase.shaded.protobuf.generated.ProcedureProtos$Procedure$Builder);
    Code:
       0: aload_0
       1: getfield      #26                 // Field waitingProceduresBuilder_:Lorg/apache/hbase/thirdparty/com/google/protobuf/RepeatedFieldBuilderV3;
       4: ifnonnull     32
       7: aload_0
       8: invokespecial #70                 // Method ensureWaitingProceduresIsMutable:()V
      11: aload_0
      12: getfield      #15                 // Field waitingProcedures_:Ljava/util/List;
      15: aload_1
      16: invokevirtual #107                // Method org/apache/hadoop/hbase/shaded/protobuf/generated/ProcedureProtos$Procedure$Builder.build:()Lorg/apache/hadoop/hbase/shaded/protobuf/generated/ProcedureProtos$Procedure;
      19: invokeinterface #129,  2          // InterfaceMethod java/util/List.add:(Ljava/lang/Object;)Z
      24: pop
      25: aload_0
      26: invokevirtual #58                 // Method onChanged:()V
      29: goto          44
      32: aload_0
      33: getfield      #26                 // Field waitingProceduresBuilder_:Lorg/apache/hbase/thirdparty/com/google/protobuf/RepeatedFieldBuilderV3;
      36: aload_1
      37: invokevirtual #107                // Method org/apache/hadoop/hbase/shaded/protobuf/generated/ProcedureProtos$Procedure$Builder.build:()Lorg/apache/hadoop/hbase/shaded/protobuf/generated/ProcedureProtos$Procedure;
      40: invokevirtual #130                // Method org/apache/hbase/thirdparty/com/google/protobuf/RepeatedFieldBuilderV3.addMessage:(Lorg/apache/hbase/thirdparty/com/google/protobuf/AbstractMessage;)Lorg/apache/hbase/thirdparty/com/google/protobuf/RepeatedFieldBuilderV3;
      43: pop
      44: aload_0
      45: areturn

  public org.apache.hadoop.hbase.shaded.protobuf.generated.LockServiceProtos$LockedResource$Builder addWaitingProcedures(int, org.apache.hadoop.hbase.shaded.protobuf.generated.ProcedureProtos$Procedure$Builder);
    Code:
       0: aload_0
       1: getfield      #26                 // Field waitingProceduresBuilder_:Lorg/apache/hbase/thirdparty/com/google/protobuf/RepeatedFieldBuilderV3;
       4: ifnonnull     32
       7: aload_0
       8: invokespecial #70                 // Method ensureWaitingProceduresIsMutable:()V
      11: aload_0
      12: getfield      #15                 // Field waitingProcedures_:Ljava/util/List;
      15: iload_1
      16: aload_2
      17: invokevirtual #107                // Method org/apache/hadoop/hbase/shaded/protobuf/generated/ProcedureProtos$Procedure$Builder.build:()Lorg/apache/hadoop/hbase/shaded/protobuf/generated/ProcedureProtos$Procedure;
      20: invokeinterface #131,  3          // InterfaceMethod java/util/List.add:(ILjava/lang/Object;)V
      25: aload_0
      26: invokevirtual #58                 // Method onChanged:()V
      29: goto          45
      32: aload_0
      33: getfield      #26                 // Field waitingProceduresBuilder_:Lorg/apache/hbase/thirdparty/com/google/protobuf/RepeatedFieldBuilderV3;
      36: iload_1
      37: aload_2
      38: invokevirtual #107                // Method org/apache/hadoop/hbase/shaded/protobuf/generated/ProcedureProtos$Procedure$Builder.build:()Lorg/apache/hadoop/hbase/shaded/protobuf/generated/ProcedureProtos$Procedure;
      41: invokevirtual #132                // Method org/apache/hbase/thirdparty/com/google/protobuf/RepeatedFieldBuilderV3.addMessage:(ILorg/apache/hbase/thirdparty/com/google/protobuf/AbstractMessage;)Lorg/apache/hbase/thirdparty/com/google/protobuf/RepeatedFieldBuilderV3;
      44: pop
      45: aload_0
      46: areturn

  public org.apache.hadoop.hbase.shaded.protobuf.generated.LockServiceProtos$LockedResource$Builder addAllWaitingProcedures(java.lang.Iterable<? extends org.apache.hadoop.hbase.shaded.protobuf.generated.ProcedureProtos$Procedure>);
    Code:
       0: aload_0
       1: getfield      #26                 // Field waitingProceduresBuilder_:Lorg/apache/hbase/thirdparty/com/google/protobuf/RepeatedFieldBuilderV3;
       4: ifnonnull     26
       7: aload_0
       8: invokespecial #70                 // Method ensureWaitingProceduresIsMutable:()V
      11: aload_1
      12: aload_0
      13: getfield      #15                 // Field waitingProcedures_:Ljava/util/List;
      16: invokestatic  #133                // Method org/apache/hbase/thirdparty/com/google/protobuf/AbstractMessageLite$Builder.addAll:(Ljava/lang/Iterable;Ljava/util/List;)V
      19: aload_0
      20: invokevirtual #58                 // Method onChanged:()V
      23: goto          35
      26: aload_0
      27: getfield      #26                 // Field waitingProceduresBuilder_:Lorg/apache/hbase/thirdparty/com/google/protobuf/RepeatedFieldBuilderV3;
      30: aload_1
      31: invokevirtual #75                 // Method org/apache/hbase/thirdparty/com/google/protobuf/RepeatedFieldBuilderV3.addAllMessages:(Ljava/lang/Iterable;)Lorg/apache/hbase/thirdparty/com/google/protobuf/RepeatedFieldBuilderV3;
      34: pop
      35: aload_0
      36: areturn

  public org.apache.hadoop.hbase.shaded.protobuf.generated.LockServiceProtos$LockedResource$Builder clearWaitingProcedures();
    Code:
       0: aload_0
       1: getfield      #26                 // Field waitingProceduresBuilder_:Lorg/apache/hbase/thirdparty/com/google/protobuf/RepeatedFieldBuilderV3;
       4: ifnonnull     32
       7: aload_0
       8: invokestatic  #14                 // Method java/util/Collections.emptyList:()Ljava/util/List;
      11: putfield      #15                 // Field waitingProcedures_:Ljava/util/List;
      14: aload_0
      15: aload_0
      16: getfield      #22                 // Field bitField0_:I
      19: bipush        -33
      21: iand
      22: putfield      #22                 // Field bitField0_:I
      25: aload_0
      26: invokevirtual #58                 // Method onChanged:()V
      29: goto          39
      32: aload_0
      33: getfield      #26                 // Field waitingProceduresBuilder_:Lorg/apache/hbase/thirdparty/com/google/protobuf/RepeatedFieldBuilderV3;
      36: invokevirtual #27                 // Method org/apache/hbase/thirdparty/com/google/protobuf/RepeatedFieldBuilderV3.clear:()V
      39: aload_0
      40: areturn

  public org.apache.hadoop.hbase.shaded.protobuf.generated.LockServiceProtos$LockedResource$Builder removeWaitingProcedures(int);
    Code:
       0: aload_0
       1: getfield      #26                 // Field waitingProceduresBuilder_:Lorg/apache/hbase/thirdparty/com/google/protobuf/RepeatedFieldBuilderV3;
       4: ifnonnull     29
       7: aload_0
       8: invokespecial #70                 // Method ensureWaitingProceduresIsMutable:()V
      11: aload_0
      12: getfield      #15                 // Field waitingProcedures_:Ljava/util/List;
      15: iload_1
      16: invokeinterface #134,  2          // InterfaceMethod java/util/List.remove:(I)Ljava/lang/Object;
      21: pop
      22: aload_0
      23: invokevirtual #58                 // Method onChanged:()V
      26: goto          37
      29: aload_0
      30: getfield      #26                 // Field waitingProceduresBuilder_:Lorg/apache/hbase/thirdparty/com/google/protobuf/RepeatedFieldBuilderV3;
      33: iload_1
      34: invokevirtual #135                // Method org/apache/hbase/thirdparty/com/google/protobuf/RepeatedFieldBuilderV3.remove:(I)V
      37: aload_0
      38: areturn

  public org.apache.hadoop.hbase.shaded.protobuf.generated.ProcedureProtos$Procedure$Builder getWaitingProceduresBuilder(int);
    Code:
       0: aload_0
       1: invokespecial #20                 // Method getWaitingProceduresFieldBuilder:()Lorg/apache/hbase/thirdparty/com/google/protobuf/RepeatedFieldBuilderV3;
       4: iload_1
       5: invokevirtual #136                // Method org/apache/hbase/thirdparty/com/google/protobuf/RepeatedFieldBuilderV3.getBuilder:(I)Lorg/apache/hbase/thirdparty/com/google/protobuf/AbstractMessage$Builder;
       8: checkcast     #113                // class org/apache/hadoop/hbase/shaded/protobuf/generated/ProcedureProtos$Procedure$Builder
      11: areturn

  public org.apache.hadoop.hbase.shaded.protobuf.generated.ProcedureProtos$ProcedureOrBuilder getWaitingProceduresOrBuilder(int);
    Code:
       0: aload_0
       1: getfield      #26                 // Field waitingProceduresBuilder_:Lorg/apache/hbase/thirdparty/com/google/protobuf/RepeatedFieldBuilderV3;
       4: ifnonnull     21
       7: aload_0
       8: getfield      #15                 // Field waitingProcedures_:Ljava/util/List;
      11: iload_1
      12: invokeinterface #125,  2          // InterfaceMethod java/util/List.get:(I)Ljava/lang/Object;
      17: checkcast     #115                // class org/apache/hadoop/hbase/shaded/protobuf/generated/ProcedureProtos$ProcedureOrBuilder
      20: areturn
      21: aload_0
      22: getfield      #26                 // Field waitingProceduresBuilder_:Lorg/apache/hbase/thirdparty/com/google/protobuf/RepeatedFieldBuilderV3;
      25: iload_1
      26: invokevirtual #137                // Method org/apache/hbase/thirdparty/com/google/protobuf/RepeatedFieldBuilderV3.getMessageOrBuilder:(I)Lorg/apache/hbase/thirdparty/com/google/protobuf/MessageOrBuilder;
      29: checkcast     #115                // class org/apache/hadoop/hbase/shaded/protobuf/generated/ProcedureProtos$ProcedureOrBuilder
      32: areturn

  public java.util.List<? extends org.apache.hadoop.hbase.shaded.protobuf.generated.ProcedureProtos$ProcedureOrBuilder> getWaitingProceduresOrBuilderList();
    Code:
       0: aload_0
       1: getfield      #26                 // Field waitingProceduresBuilder_:Lorg/apache/hbase/thirdparty/com/google/protobuf/RepeatedFieldBuilderV3;
       4: ifnull        15
       7: aload_0
       8: getfield      #26                 // Field waitingProceduresBuilder_:Lorg/apache/hbase/thirdparty/com/google/protobuf/RepeatedFieldBuilderV3;
      11: invokevirtual #138                // Method org/apache/hbase/thirdparty/com/google/protobuf/RepeatedFieldBuilderV3.getMessageOrBuilderList:()Ljava/util/List;
      14: areturn
      15: aload_0
      16: getfield      #15                 // Field waitingProcedures_:Ljava/util/List;
      19: invokestatic  #40                 // Method java/util/Collections.unmodifiableList:(Ljava/util/List;)Ljava/util/List;
      22: areturn

  public org.apache.hadoop.hbase.shaded.protobuf.generated.ProcedureProtos$Procedure$Builder addWaitingProceduresBuilder();
    Code:
       0: aload_0
       1: invokespecial #20                 // Method getWaitingProceduresFieldBuilder:()Lorg/apache/hbase/thirdparty/com/google/protobuf/RepeatedFieldBuilderV3;
       4: invokestatic  #104                // Method org/apache/hadoop/hbase/shaded/protobuf/generated/ProcedureProtos$Procedure.getDefaultInstance:()Lorg/apache/hadoop/hbase/shaded/protobuf/generated/ProcedureProtos$Procedure;
       7: invokevirtual #139                // Method org/apache/hbase/thirdparty/com/google/protobuf/RepeatedFieldBuilderV3.addBuilder:(Lorg/apache/hbase/thirdparty/com/google/protobuf/AbstractMessage;)Lorg/apache/hbase/thirdparty/com/google/protobuf/AbstractMessage$Builder;
      10: checkcast     #113                // class org/apache/hadoop/hbase/shaded/protobuf/generated/ProcedureProtos$Procedure$Builder
      13: areturn

  public org.apache.hadoop.hbase.shaded.protobuf.generated.ProcedureProtos$Procedure$Builder addWaitingProceduresBuilder(int);
    Code:
       0: aload_0
       1: invokespecial #20                 // Method getWaitingProceduresFieldBuilder:()Lorg/apache/hbase/thirdparty/com/google/protobuf/RepeatedFieldBuilderV3;
       4: iload_1
       5: invokestatic  #104                // Method org/apache/hadoop/hbase/shaded/protobuf/generated/ProcedureProtos$Procedure.getDefaultInstance:()Lorg/apache/hadoop/hbase/shaded/protobuf/generated/ProcedureProtos$Procedure;
       8: invokevirtual #140                // Method org/apache/hbase/thirdparty/com/google/protobuf/RepeatedFieldBuilderV3.addBuilder:(ILorg/apache/hbase/thirdparty/com/google/protobuf/AbstractMessage;)Lorg/apache/hbase/thirdparty/com/google/protobuf/AbstractMessage$Builder;
      11: checkcast     #113                // class org/apache/hadoop/hbase/shaded/protobuf/generated/ProcedureProtos$Procedure$Builder
      14: areturn

  public java.util.List<org.apache.hadoop.hbase.shaded.protobuf.generated.ProcedureProtos$Procedure$Builder> getWaitingProceduresBuilderList();
    Code:
       0: aload_0
       1: invokespecial #20                 // Method getWaitingProceduresFieldBuilder:()Lorg/apache/hbase/thirdparty/com/google/protobuf/RepeatedFieldBuilderV3;
       4: invokevirtual #141                // Method org/apache/hbase/thirdparty/com/google/protobuf/RepeatedFieldBuilderV3.getBuilderList:()Ljava/util/List;
       7: areturn

  public final org.apache.hadoop.hbase.shaded.protobuf.generated.LockServiceProtos$LockedResource$Builder setUnknownFields(org.apache.hbase.thirdparty.com.google.protobuf.UnknownFieldSet);
    Code:
       0: aload_0
       1: aload_1
       2: invokespecial #144                // Method org/apache/hbase/thirdparty/com/google/protobuf/GeneratedMessageV3$Builder.setUnknownFields:(Lorg/apache/hbase/thirdparty/com/google/protobuf/UnknownFieldSet;)Lorg/apache/hbase/thirdparty/com/google/protobuf/GeneratedMessageV3$Builder;
       5: checkcast     #6                  // class org/apache/hadoop/hbase/shaded/protobuf/generated/LockServiceProtos$LockedResource$Builder
       8: areturn

  public final org.apache.hadoop.hbase.shaded.protobuf.generated.LockServiceProtos$LockedResource$Builder mergeUnknownFields(org.apache.hbase.thirdparty.com.google.protobuf.UnknownFieldSet);
    Code:
       0: aload_0
       1: aload_1
       2: invokespecial #145                // Method org/apache/hbase/thirdparty/com/google/protobuf/GeneratedMessageV3$Builder.mergeUnknownFields:(Lorg/apache/hbase/thirdparty/com/google/protobuf/UnknownFieldSet;)Lorg/apache/hbase/thirdparty/com/google/protobuf/GeneratedMessageV3$Builder;
       5: checkcast     #6                  // class org/apache/hadoop/hbase/shaded/protobuf/generated/LockServiceProtos$LockedResource$Builder
       8: areturn

  public org.apache.hbase.thirdparty.com.google.protobuf.GeneratedMessageV3$Builder mergeUnknownFields(org.apache.hbase.thirdparty.com.google.protobuf.UnknownFieldSet);
    Code:
       0: aload_0
       1: aload_1
       2: invokevirtual #77                 // Method mergeUnknownFields:(Lorg/apache/hbase/thirdparty/com/google/protobuf/UnknownFieldSet;)Lorg/apache/hadoop/hbase/shaded/protobuf/generated/LockServiceProtos$LockedResource$Builder;
       5: areturn

  public org.apache.hbase.thirdparty.com.google.protobuf.GeneratedMessageV3$Builder setUnknownFields(org.apache.hbase.thirdparty.com.google.protobuf.UnknownFieldSet);
    Code:
       0: aload_0
       1: aload_1
       2: invokevirtual #146                // Method setUnknownFields:(Lorg/apache/hbase/thirdparty/com/google/protobuf/UnknownFieldSet;)Lorg/apache/hadoop/hbase/shaded/protobuf/generated/LockServiceProtos$LockedResource$Builder;
       5: areturn

  public org.apache.hbase.thirdparty.com.google.protobuf.GeneratedMessageV3$Builder addRepeatedField(org.apache.hbase.thirdparty.com.google.protobuf.Descriptors$FieldDescriptor, java.lang.Object);
    Code:
       0: aload_0
       1: aload_1
       2: aload_2
       3: invokevirtual #147                // Method addRepeatedField:(Lorg/apache/hbase/thirdparty/com/google/protobuf/Descriptors$FieldDescriptor;Ljava/lang/Object;)Lorg/apache/hadoop/hbase/shaded/protobuf/generated/LockServiceProtos$LockedResource$Builder;
       6: areturn

  public org.apache.hbase.thirdparty.com.google.protobuf.GeneratedMessageV3$Builder setRepeatedField(org.apache.hbase.thirdparty.com.google.protobuf.Descriptors$FieldDescriptor, int, java.lang.Object);
    Code:
       0: aload_0
       1: aload_1
       2: iload_2
       3: aload_3
       4: invokevirtual #148                // Method setRepeatedField:(Lorg/apache/hbase/thirdparty/com/google/protobuf/Descriptors$FieldDescriptor;ILjava/lang/Object;)Lorg/apache/hadoop/hbase/shaded/protobuf/generated/LockServiceProtos$LockedResource$Builder;
       7: areturn

  public org.apache.hbase.thirdparty.com.google.protobuf.GeneratedMessageV3$Builder clearOneof(org.apache.hbase.thirdparty.com.google.protobuf.Descriptors$OneofDescriptor);
    Code:
       0: aload_0
       1: aload_1
       2: invokevirtual #149                // Method clearOneof:(Lorg/apache/hbase/thirdparty/com/google/protobuf/Descriptors$OneofDescriptor;)Lorg/apache/hadoop/hbase/shaded/protobuf/generated/LockServiceProtos$LockedResource$Builder;
       5: areturn

  public org.apache.hbase.thirdparty.com.google.protobuf.GeneratedMessageV3$Builder clearField(org.apache.hbase.thirdparty.com.google.protobuf.Descriptors$FieldDescriptor);
    Code:
       0: aload_0
       1: aload_1
       2: invokevirtual #150                // Method clearField:(Lorg/apache/hbase/thirdparty/com/google/protobuf/Descriptors$FieldDescriptor;)Lorg/apache/hadoop/hbase/shaded/protobuf/generated/LockServiceProtos$LockedResource$Builder;
       5: areturn

  public org.apache.hbase.thirdparty.com.google.protobuf.GeneratedMessageV3$Builder setField(org.apache.hbase.thirdparty.com.google.protobuf.Descriptors$FieldDescriptor, java.lang.Object);
    Code:
       0: aload_0
       1: aload_1
       2: aload_2
       3: invokevirtual #151                // Method setField:(Lorg/apache/hbase/thirdparty/com/google/protobuf/Descriptors$FieldDescriptor;Ljava/lang/Object;)Lorg/apache/hadoop/hbase/shaded/protobuf/generated/LockServiceProtos$LockedResource$Builder;
       6: areturn

  public org.apache.hbase.thirdparty.com.google.protobuf.GeneratedMessageV3$Builder clear();
    Code:
       0: aload_0
       1: invokevirtual #152                // Method clear:()Lorg/apache/hadoop/hbase/shaded/protobuf/generated/LockServiceProtos$LockedResource$Builder;
       4: areturn

  public org.apache.hbase.thirdparty.com.google.protobuf.GeneratedMessageV3$Builder clone();
    Code:
       0: aload_0
       1: invokevirtual #153                // Method clone:()Lorg/apache/hadoop/hbase/shaded/protobuf/generated/LockServiceProtos$LockedResource$Builder;
       4: areturn

  public org.apache.hbase.thirdparty.com.google.protobuf.AbstractMessage$Builder mergeUnknownFields(org.apache.hbase.thirdparty.com.google.protobuf.UnknownFieldSet);
    Code:
       0: aload_0
       1: aload_1
       2: invokevirtual #77                 // Method mergeUnknownFields:(Lorg/apache/hbase/thirdparty/com/google/protobuf/UnknownFieldSet;)Lorg/apache/hadoop/hbase/shaded/protobuf/generated/LockServiceProtos$LockedResource$Builder;
       5: areturn

  public org.apache.hbase.thirdparty.com.google.protobuf.AbstractMessage$Builder mergeFrom(org.apache.hbase.thirdparty.com.google.protobuf.CodedInputStream, org.apache.hbase.thirdparty.com.google.protobuf.ExtensionRegistryLite) throws java.io.IOException;
    Code:
       0: aload_0
       1: aload_1
       2: aload_2
       3: invokevirtual #154                // Method mergeFrom:(Lorg/apache/hbase/thirdparty/com/google/protobuf/CodedInputStream;Lorg/apache/hbase/thirdparty/com/google/protobuf/ExtensionRegistryLite;)Lorg/apache/hadoop/hbase/shaded/protobuf/generated/LockServiceProtos$LockedResource$Builder;
       6: areturn

  public org.apache.hbase.thirdparty.com.google.protobuf.AbstractMessage$Builder mergeFrom(org.apache.hbase.thirdparty.com.google.protobuf.Message);
    Code:
       0: aload_0
       1: aload_1
       2: invokevirtual #155                // Method mergeFrom:(Lorg/apache/hbase/thirdparty/com/google/protobuf/Message;)Lorg/apache/hadoop/hbase/shaded/protobuf/generated/LockServiceProtos$LockedResource$Builder;
       5: areturn

  public org.apache.hbase.thirdparty.com.google.protobuf.AbstractMessage$Builder clear();
    Code:
       0: aload_0
       1: invokevirtual #152                // Method clear:()Lorg/apache/hadoop/hbase/shaded/protobuf/generated/LockServiceProtos$LockedResource$Builder;
       4: areturn

  public org.apache.hbase.thirdparty.com.google.protobuf.AbstractMessage$Builder clearOneof(org.apache.hbase.thirdparty.com.google.protobuf.Descriptors$OneofDescriptor);
    Code:
       0: aload_0
       1: aload_1
       2: invokevirtual #149                // Method clearOneof:(Lorg/apache/hbase/thirdparty/com/google/protobuf/Descriptors$OneofDescriptor;)Lorg/apache/hadoop/hbase/shaded/protobuf/generated/LockServiceProtos$LockedResource$Builder;
       5: areturn

  public org.apache.hbase.thirdparty.com.google.protobuf.AbstractMessage$Builder clone();
    Code:
       0: aload_0
       1: invokevirtual #153                // Method clone:()Lorg/apache/hadoop/hbase/shaded/protobuf/generated/LockServiceProtos$LockedResource$Builder;
       4: areturn

  public org.apache.hbase.thirdparty.com.google.protobuf.Message$Builder mergeUnknownFields(org.apache.hbase.thirdparty.com.google.protobuf.UnknownFieldSet);
    Code:
       0: aload_0
       1: aload_1
       2: invokevirtual #77                 // Method mergeUnknownFields:(Lorg/apache/hbase/thirdparty/com/google/protobuf/UnknownFieldSet;)Lorg/apache/hadoop/hbase/shaded/protobuf/generated/LockServiceProtos$LockedResource$Builder;
       5: areturn

  public org.apache.hbase.thirdparty.com.google.protobuf.Message$Builder setUnknownFields(org.apache.hbase.thirdparty.com.google.protobuf.UnknownFieldSet);
    Code:
       0: aload_0
       1: aload_1
       2: invokevirtual #146                // Method setUnknownFields:(Lorg/apache/hbase/thirdparty/com/google/protobuf/UnknownFieldSet;)Lorg/apache/hadoop/hbase/shaded/protobuf/generated/LockServiceProtos$LockedResource$Builder;
       5: areturn

  public org.apache.hbase.thirdparty.com.google.protobuf.Message$Builder addRepeatedField(org.apache.hbase.thirdparty.com.google.protobuf.Descriptors$FieldDescriptor, java.lang.Object);
    Code:
       0: aload_0
       1: aload_1
       2: aload_2
       3: invokevirtual #147                // Method addRepeatedField:(Lorg/apache/hbase/thirdparty/com/google/protobuf/Descriptors$FieldDescriptor;Ljava/lang/Object;)Lorg/apache/hadoop/hbase/shaded/protobuf/generated/LockServiceProtos$LockedResource$Builder;
       6: areturn

  public org.apache.hbase.thirdparty.com.google.protobuf.Message$Builder setRepeatedField(org.apache.hbase.thirdparty.com.google.protobuf.Descriptors$FieldDescriptor, int, java.lang.Object);
    Code:
       0: aload_0
       1: aload_1
       2: iload_2
       3: aload_3
       4: invokevirtual #148                // Method setRepeatedField:(Lorg/apache/hbase/thirdparty/com/google/protobuf/Descriptors$FieldDescriptor;ILjava/lang/Object;)Lorg/apache/hadoop/hbase/shaded/protobuf/generated/LockServiceProtos$LockedResource$Builder;
       7: areturn

  public org.apache.hbase.thirdparty.com.google.protobuf.Message$Builder clearOneof(org.apache.hbase.thirdparty.com.google.protobuf.Descriptors$OneofDescriptor);
    Code:
       0: aload_0
       1: aload_1
       2: invokevirtual #149                // Method clearOneof:(Lorg/apache/hbase/thirdparty/com/google/protobuf/Descriptors$OneofDescriptor;)Lorg/apache/hadoop/hbase/shaded/protobuf/generated/LockServiceProtos$LockedResource$Builder;
       5: areturn

  public org.apache.hbase.thirdparty.com.google.protobuf.Message$Builder clearField(org.apache.hbase.thirdparty.com.google.protobuf.Descriptors$FieldDescriptor);
    Code:
       0: aload_0
       1: aload_1
       2: invokevirtual #150                // Method clearField:(Lorg/apache/hbase/thirdparty/com/google/protobuf/Descriptors$FieldDescriptor;)Lorg/apache/hadoop/hbase/shaded/protobuf/generated/LockServiceProtos$LockedResource$Builder;
       5: areturn

  public org.apache.hbase.thirdparty.com.google.protobuf.Message$Builder setField(org.apache.hbase.thirdparty.com.google.protobuf.Descriptors$FieldDescriptor, java.lang.Object);
    Code:
       0: aload_0
       1: aload_1
       2: aload_2
       3: invokevirtual #151                // Method setField:(Lorg/apache/hbase/thirdparty/com/google/protobuf/Descriptors$FieldDescriptor;Ljava/lang/Object;)Lorg/apache/hadoop/hbase/shaded/protobuf/generated/LockServiceProtos$LockedResource$Builder;
       6: areturn

  public org.apache.hbase.thirdparty.com.google.protobuf.Message$Builder mergeFrom(org.apache.hbase.thirdparty.com.google.protobuf.CodedInputStream, org.apache.hbase.thirdparty.com.google.protobuf.ExtensionRegistryLite) throws java.io.IOException;
    Code:
       0: aload_0
       1: aload_1
       2: aload_2
       3: invokevirtual #154                // Method mergeFrom:(Lorg/apache/hbase/thirdparty/com/google/protobuf/CodedInputStream;Lorg/apache/hbase/thirdparty/com/google/protobuf/ExtensionRegistryLite;)Lorg/apache/hadoop/hbase/shaded/protobuf/generated/LockServiceProtos$LockedResource$Builder;
       6: areturn

  public org.apache.hbase.thirdparty.com.google.protobuf.Message$Builder clone();
    Code:
       0: aload_0
       1: invokevirtual #153                // Method clone:()Lorg/apache/hadoop/hbase/shaded/protobuf/generated/LockServiceProtos$LockedResource$Builder;
       4: areturn

  public org.apache.hbase.thirdparty.com.google.protobuf.Message buildPartial();
    Code:
       0: aload_0
       1: invokevirtual #29                 // Method buildPartial:()Lorg/apache/hadoop/hbase/shaded/protobuf/generated/LockServiceProtos$LockedResource;
       4: areturn

  public org.apache.hbase.thirdparty.com.google.protobuf.Message build();
    Code:
       0: aload_0
       1: invokevirtual #156                // Method build:()Lorg/apache/hadoop/hbase/shaded/protobuf/generated/LockServiceProtos$LockedResource;
       4: areturn

  public org.apache.hbase.thirdparty.com.google.protobuf.Message$Builder mergeFrom(org.apache.hbase.thirdparty.com.google.protobuf.Message);
    Code:
       0: aload_0
       1: aload_1
       2: invokevirtual #155                // Method mergeFrom:(Lorg/apache/hbase/thirdparty/com/google/protobuf/Message;)Lorg/apache/hadoop/hbase/shaded/protobuf/generated/LockServiceProtos$LockedResource$Builder;
       5: areturn

  public org.apache.hbase.thirdparty.com.google.protobuf.Message$Builder clear();
    Code:
       0: aload_0
       1: invokevirtual #152                // Method clear:()Lorg/apache/hadoop/hbase/shaded/protobuf/generated/LockServiceProtos$LockedResource$Builder;
       4: areturn

  public org.apache.hbase.thirdparty.com.google.protobuf.MessageLite$Builder mergeFrom(org.apache.hbase.thirdparty.com.google.protobuf.CodedInputStream, org.apache.hbase.thirdparty.com.google.protobuf.ExtensionRegistryLite) throws java.io.IOException;
    Code:
       0: aload_0
       1: aload_1
       2: aload_2
       3: invokevirtual #154                // Method mergeFrom:(Lorg/apache/hbase/thirdparty/com/google/protobuf/CodedInputStream;Lorg/apache/hbase/thirdparty/com/google/protobuf/ExtensionRegistryLite;)Lorg/apache/hadoop/hbase/shaded/protobuf/generated/LockServiceProtos$LockedResource$Builder;
       6: areturn

  public org.apache.hbase.thirdparty.com.google.protobuf.MessageLite$Builder clone();
    Code:
       0: aload_0
       1: invokevirtual #153                // Method clone:()Lorg/apache/hadoop/hbase/shaded/protobuf/generated/LockServiceProtos$LockedResource$Builder;
       4: areturn

  public org.apache.hbase.thirdparty.com.google.protobuf.MessageLite buildPartial();
    Code:
       0: aload_0
       1: invokevirtual #29                 // Method buildPartial:()Lorg/apache/hadoop/hbase/shaded/protobuf/generated/LockServiceProtos$LockedResource;
       4: areturn

  public org.apache.hbase.thirdparty.com.google.protobuf.MessageLite build();
    Code:
       0: aload_0
       1: invokevirtual #156                // Method build:()Lorg/apache/hadoop/hbase/shaded/protobuf/generated/LockServiceProtos$LockedResource;
       4: areturn

  public org.apache.hbase.thirdparty.com.google.protobuf.MessageLite$Builder clear();
    Code:
       0: aload_0
       1: invokevirtual #152                // Method clear:()Lorg/apache/hadoop/hbase/shaded/protobuf/generated/LockServiceProtos$LockedResource$Builder;
       4: areturn

  public org.apache.hbase.thirdparty.com.google.protobuf.MessageLite getDefaultInstanceForType();
    Code:
       0: aload_0
       1: invokevirtual #157                // Method getDefaultInstanceForType:()Lorg/apache/hadoop/hbase/shaded/protobuf/generated/LockServiceProtos$LockedResource;
       4: areturn

  public org.apache.hbase.thirdparty.com.google.protobuf.Message getDefaultInstanceForType();
    Code:
       0: aload_0
       1: invokevirtual #157                // Method getDefaultInstanceForType:()Lorg/apache/hadoop/hbase/shaded/protobuf/generated/LockServiceProtos$LockedResource;
       4: areturn

  public org.apache.hbase.thirdparty.com.google.protobuf.AbstractMessageLite$Builder mergeFrom(org.apache.hbase.thirdparty.com.google.protobuf.CodedInputStream, org.apache.hbase.thirdparty.com.google.protobuf.ExtensionRegistryLite) throws java.io.IOException;
    Code:
       0: aload_0
       1: aload_1
       2: aload_2
       3: invokevirtual #154                // Method mergeFrom:(Lorg/apache/hbase/thirdparty/com/google/protobuf/CodedInputStream;Lorg/apache/hbase/thirdparty/com/google/protobuf/ExtensionRegistryLite;)Lorg/apache/hadoop/hbase/shaded/protobuf/generated/LockServiceProtos$LockedResource$Builder;
       6: areturn

  public org.apache.hbase.thirdparty.com.google.protobuf.AbstractMessageLite$Builder clone();
    Code:
       0: aload_0
       1: invokevirtual #153                // Method clone:()Lorg/apache/hadoop/hbase/shaded/protobuf/generated/LockServiceProtos$LockedResource$Builder;
       4: areturn

  public java.lang.Object clone() throws java.lang.CloneNotSupportedException;
    Code:
       0: aload_0
       1: invokevirtual #153                // Method clone:()Lorg/apache/hadoop/hbase/shaded/protobuf/generated/LockServiceProtos$LockedResource$Builder;
       4: areturn

  org.apache.hadoop.hbase.shaded.protobuf.generated.LockServiceProtos$LockedResource$Builder(org.apache.hadoop.hbase.shaded.protobuf.generated.LockServiceProtos$1);
    Code:
       0: aload_0
       1: invokespecial #2                  // Method "<init>":()V
       4: return

  org.apache.hadoop.hbase.shaded.protobuf.generated.LockServiceProtos$LockedResource$Builder(org.apache.hbase.thirdparty.com.google.protobuf.GeneratedMessageV3$BuilderParent, org.apache.hadoop.hbase.shaded.protobuf.generated.LockServiceProtos$1);
    Code:
       0: aload_0
       1: aload_1
       2: invokespecial #1                  // Method "<init>":(Lorg/apache/hbase/thirdparty/com/google/protobuf/GeneratedMessageV3$BuilderParent;)V
       5: return
}
