Compiled from "LockStatus.java"
public interface org.apache.hadoop.hbase.procedure2.LockStatus {
  public boolean isLocked();
    Code:
       0: aload_0
       1: invokeinterface #1,  1            // InterfaceMethod hasExclusiveLock:()Z
       6: ifne          18
       9: aload_0
      10: invokeinterface #2,  1            // InterfaceMethod getSharedLockCount:()I
      15: ifle          22
      18: iconst_1
      19: goto          23
      22: iconst_0
      23: ireturn

  public abstract boolean hasExclusiveLock();

  public abstract boolean hasLockAccess(org.apache.hadoop.hbase.procedure2.Procedure<?>);

  public abstract org.apache.hadoop.hbase.procedure2.Procedure<?> getExclusiveLockOwnerProcedure();

  public long getExclusiveLockProcIdOwner();
    Code:
       0: aload_0
       1: invokeinterface #3,  1            // InterfaceMethod getExclusiveLockOwnerProcedure:()Lorg/apache/hadoop/hbase/procedure2/Procedure;
       6: astore_1
       7: aload_1
       8: ifnull        18
      11: aload_1
      12: invokevirtual #4                  // Method org/apache/hadoop/hbase/procedure2/Procedure.getProcId:()J
      15: goto          21
      18: ldc2_w        #5                  // long -1l
      21: lreturn

  public abstract int getSharedLockCount();
}
