Compiled from "LockManager.java"
public class org.apache.hadoop.hbase.master.locking.LockManager$RemoteLocks {
  final org.apache.hadoop.hbase.master.locking.LockManager this$0;

  public org.apache.hadoop.hbase.master.locking.LockManager$RemoteLocks(org.apache.hadoop.hbase.master.locking.LockManager);
    Code:
       0: aload_0
       1: aload_1
       2: putfield      #1                  // Field this$0:Lorg/apache/hadoop/hbase/master/locking/LockManager;
       5: aload_0
       6: invokespecial #2                  // Method java/lang/Object."<init>":()V
       9: return

  public long requestNamespaceLock(java.lang.String, org.apache.hadoop.hbase.procedure2.LockType, java.lang.String, org.apache.hadoop.hbase.util.NonceKey) throws java.lang.IllegalArgumentException, java.io.IOException;
    Code:
       0: aload_0
       1: getfield      #1                  // Field this$0:Lorg/apache/hadoop/hbase/master/locking/LockManager;
       4: invokestatic  #3                  // Method org/apache/hadoop/hbase/master/locking/LockManager.access$000:(Lorg/apache/hadoop/hbase/master/locking/LockManager;)Lorg/apache/hadoop/hbase/master/HMaster;
       7: invokevirtual #4                  // Method org/apache/hadoop/hbase/master/HMaster.getMasterCoprocessorHost:()Lorg/apache/hadoop/hbase/master/MasterCoprocessorHost;
      10: aload_1
      11: aconst_null
      12: aconst_null
      13: aload_2
      14: aload_3
      15: invokevirtual #5                  // Method org/apache/hadoop/hbase/master/MasterCoprocessorHost.preRequestLock:(Ljava/lang/String;Lorg/apache/hadoop/hbase/TableName;[Lorg/apache/hadoop/hbase/client/RegionInfo;Lorg/apache/hadoop/hbase/procedure2/LockType;Ljava/lang/String;)V
      18: new           #6                  // class org/apache/hadoop/hbase/master/locking/LockProcedure
      21: dup
      22: aload_0
      23: getfield      #1                  // Field this$0:Lorg/apache/hadoop/hbase/master/locking/LockManager;
      26: invokestatic  #3                  // Method org/apache/hadoop/hbase/master/locking/LockManager.access$000:(Lorg/apache/hadoop/hbase/master/locking/LockManager;)Lorg/apache/hadoop/hbase/master/HMaster;
      29: invokevirtual #7                  // Method org/apache/hadoop/hbase/master/HMaster.getConfiguration:()Lorg/apache/hadoop/conf/Configuration;
      32: aload_1
      33: aload_2
      34: aload_3
      35: aconst_null
      36: invokespecial #8                  // Method org/apache/hadoop/hbase/master/locking/LockProcedure."<init>":(Lorg/apache/hadoop/conf/Configuration;Ljava/lang/String;Lorg/apache/hadoop/hbase/procedure2/LockType;Ljava/lang/String;Ljava/util/concurrent/CountDownLatch;)V
      39: astore        5
      41: aload_0
      42: getfield      #1                  // Field this$0:Lorg/apache/hadoop/hbase/master/locking/LockManager;
      45: aload         5
      47: aload         4
      49: invokestatic  #9                  // Method org/apache/hadoop/hbase/master/locking/LockManager.access$200:(Lorg/apache/hadoop/hbase/master/locking/LockManager;Lorg/apache/hadoop/hbase/master/locking/LockProcedure;Lorg/apache/hadoop/hbase/util/NonceKey;)V
      52: aload_0
      53: getfield      #1                  // Field this$0:Lorg/apache/hadoop/hbase/master/locking/LockManager;
      56: invokestatic  #3                  // Method org/apache/hadoop/hbase/master/locking/LockManager.access$000:(Lorg/apache/hadoop/hbase/master/locking/LockManager;)Lorg/apache/hadoop/hbase/master/HMaster;
      59: invokevirtual #4                  // Method org/apache/hadoop/hbase/master/HMaster.getMasterCoprocessorHost:()Lorg/apache/hadoop/hbase/master/MasterCoprocessorHost;
      62: aload_1
      63: aconst_null
      64: aconst_null
      65: aload_2
      66: aload_3
      67: invokevirtual #10                 // Method org/apache/hadoop/hbase/master/MasterCoprocessorHost.postRequestLock:(Ljava/lang/String;Lorg/apache/hadoop/hbase/TableName;[Lorg/apache/hadoop/hbase/client/RegionInfo;Lorg/apache/hadoop/hbase/procedure2/LockType;Ljava/lang/String;)V
      70: aload         5
      72: invokevirtual #11                 // Method org/apache/hadoop/hbase/master/locking/LockProcedure.getProcId:()J
      75: lreturn

  public long requestTableLock(org.apache.hadoop.hbase.TableName, org.apache.hadoop.hbase.procedure2.LockType, java.lang.String, org.apache.hadoop.hbase.util.NonceKey) throws java.lang.IllegalArgumentException, java.io.IOException;
    Code:
       0: aload_0
       1: getfield      #1                  // Field this$0:Lorg/apache/hadoop/hbase/master/locking/LockManager;
       4: invokestatic  #3                  // Method org/apache/hadoop/hbase/master/locking/LockManager.access$000:(Lorg/apache/hadoop/hbase/master/locking/LockManager;)Lorg/apache/hadoop/hbase/master/HMaster;
       7: invokevirtual #4                  // Method org/apache/hadoop/hbase/master/HMaster.getMasterCoprocessorHost:()Lorg/apache/hadoop/hbase/master/MasterCoprocessorHost;
      10: aconst_null
      11: aload_1
      12: aconst_null
      13: aload_2
      14: aload_3
      15: invokevirtual #5                  // Method org/apache/hadoop/hbase/master/MasterCoprocessorHost.preRequestLock:(Ljava/lang/String;Lorg/apache/hadoop/hbase/TableName;[Lorg/apache/hadoop/hbase/client/RegionInfo;Lorg/apache/hadoop/hbase/procedure2/LockType;Ljava/lang/String;)V
      18: new           #6                  // class org/apache/hadoop/hbase/master/locking/LockProcedure
      21: dup
      22: aload_0
      23: getfield      #1                  // Field this$0:Lorg/apache/hadoop/hbase/master/locking/LockManager;
      26: invokestatic  #3                  // Method org/apache/hadoop/hbase/master/locking/LockManager.access$000:(Lorg/apache/hadoop/hbase/master/locking/LockManager;)Lorg/apache/hadoop/hbase/master/HMaster;
      29: invokevirtual #7                  // Method org/apache/hadoop/hbase/master/HMaster.getConfiguration:()Lorg/apache/hadoop/conf/Configuration;
      32: aload_1
      33: aload_2
      34: aload_3
      35: aconst_null
      36: invokespecial #12                 // Method org/apache/hadoop/hbase/master/locking/LockProcedure."<init>":(Lorg/apache/hadoop/conf/Configuration;Lorg/apache/hadoop/hbase/TableName;Lorg/apache/hadoop/hbase/procedure2/LockType;Ljava/lang/String;Ljava/util/concurrent/CountDownLatch;)V
      39: astore        5
      41: aload_0
      42: getfield      #1                  // Field this$0:Lorg/apache/hadoop/hbase/master/locking/LockManager;
      45: aload         5
      47: aload         4
      49: invokestatic  #9                  // Method org/apache/hadoop/hbase/master/locking/LockManager.access$200:(Lorg/apache/hadoop/hbase/master/locking/LockManager;Lorg/apache/hadoop/hbase/master/locking/LockProcedure;Lorg/apache/hadoop/hbase/util/NonceKey;)V
      52: aload_0
      53: getfield      #1                  // Field this$0:Lorg/apache/hadoop/hbase/master/locking/LockManager;
      56: invokestatic  #3                  // Method org/apache/hadoop/hbase/master/locking/LockManager.access$000:(Lorg/apache/hadoop/hbase/master/locking/LockManager;)Lorg/apache/hadoop/hbase/master/HMaster;
      59: invokevirtual #4                  // Method org/apache/hadoop/hbase/master/HMaster.getMasterCoprocessorHost:()Lorg/apache/hadoop/hbase/master/MasterCoprocessorHost;
      62: aconst_null
      63: aload_1
      64: aconst_null
      65: aload_2
      66: aload_3
      67: invokevirtual #10                 // Method org/apache/hadoop/hbase/master/MasterCoprocessorHost.postRequestLock:(Ljava/lang/String;Lorg/apache/hadoop/hbase/TableName;[Lorg/apache/hadoop/hbase/client/RegionInfo;Lorg/apache/hadoop/hbase/procedure2/LockType;Ljava/lang/String;)V
      70: aload         5
      72: invokevirtual #11                 // Method org/apache/hadoop/hbase/master/locking/LockProcedure.getProcId:()J
      75: lreturn

  public long requestRegionsLock(org.apache.hadoop.hbase.client.RegionInfo[], java.lang.String, org.apache.hadoop.hbase.util.NonceKey) throws java.lang.IllegalArgumentException, java.io.IOException;
    Code:
       0: aload_0
       1: getfield      #1                  // Field this$0:Lorg/apache/hadoop/hbase/master/locking/LockManager;
       4: invokestatic  #3                  // Method org/apache/hadoop/hbase/master/locking/LockManager.access$000:(Lorg/apache/hadoop/hbase/master/locking/LockManager;)Lorg/apache/hadoop/hbase/master/HMaster;
       7: invokevirtual #4                  // Method org/apache/hadoop/hbase/master/HMaster.getMasterCoprocessorHost:()Lorg/apache/hadoop/hbase/master/MasterCoprocessorHost;
      10: aconst_null
      11: aconst_null
      12: aload_1
      13: getstatic     #13                 // Field org/apache/hadoop/hbase/procedure2/LockType.EXCLUSIVE:Lorg/apache/hadoop/hbase/procedure2/LockType;
      16: aload_2
      17: invokevirtual #5                  // Method org/apache/hadoop/hbase/master/MasterCoprocessorHost.preRequestLock:(Ljava/lang/String;Lorg/apache/hadoop/hbase/TableName;[Lorg/apache/hadoop/hbase/client/RegionInfo;Lorg/apache/hadoop/hbase/procedure2/LockType;Ljava/lang/String;)V
      20: new           #6                  // class org/apache/hadoop/hbase/master/locking/LockProcedure
      23: dup
      24: aload_0
      25: getfield      #1                  // Field this$0:Lorg/apache/hadoop/hbase/master/locking/LockManager;
      28: invokestatic  #3                  // Method org/apache/hadoop/hbase/master/locking/LockManager.access$000:(Lorg/apache/hadoop/hbase/master/locking/LockManager;)Lorg/apache/hadoop/hbase/master/HMaster;
      31: invokevirtual #7                  // Method org/apache/hadoop/hbase/master/HMaster.getConfiguration:()Lorg/apache/hadoop/conf/Configuration;
      34: aload_1
      35: getstatic     #13                 // Field org/apache/hadoop/hbase/procedure2/LockType.EXCLUSIVE:Lorg/apache/hadoop/hbase/procedure2/LockType;
      38: aload_2
      39: aconst_null
      40: invokespecial #14                 // Method org/apache/hadoop/hbase/master/locking/LockProcedure."<init>":(Lorg/apache/hadoop/conf/Configuration;[Lorg/apache/hadoop/hbase/client/RegionInfo;Lorg/apache/hadoop/hbase/procedure2/LockType;Ljava/lang/String;Ljava/util/concurrent/CountDownLatch;)V
      43: astore        4
      45: aload_0
      46: getfield      #1                  // Field this$0:Lorg/apache/hadoop/hbase/master/locking/LockManager;
      49: aload         4
      51: aload_3
      52: invokestatic  #9                  // Method org/apache/hadoop/hbase/master/locking/LockManager.access$200:(Lorg/apache/hadoop/hbase/master/locking/LockManager;Lorg/apache/hadoop/hbase/master/locking/LockProcedure;Lorg/apache/hadoop/hbase/util/NonceKey;)V
      55: aload_0
      56: getfield      #1                  // Field this$0:Lorg/apache/hadoop/hbase/master/locking/LockManager;
      59: invokestatic  #3                  // Method org/apache/hadoop/hbase/master/locking/LockManager.access$000:(Lorg/apache/hadoop/hbase/master/locking/LockManager;)Lorg/apache/hadoop/hbase/master/HMaster;
      62: invokevirtual #4                  // Method org/apache/hadoop/hbase/master/HMaster.getMasterCoprocessorHost:()Lorg/apache/hadoop/hbase/master/MasterCoprocessorHost;
      65: aconst_null
      66: aconst_null
      67: aload_1
      68: getstatic     #13                 // Field org/apache/hadoop/hbase/procedure2/LockType.EXCLUSIVE:Lorg/apache/hadoop/hbase/procedure2/LockType;
      71: aload_2
      72: invokevirtual #10                 // Method org/apache/hadoop/hbase/master/MasterCoprocessorHost.postRequestLock:(Ljava/lang/String;Lorg/apache/hadoop/hbase/TableName;[Lorg/apache/hadoop/hbase/client/RegionInfo;Lorg/apache/hadoop/hbase/procedure2/LockType;Ljava/lang/String;)V
      75: aload         4
      77: invokevirtual #11                 // Method org/apache/hadoop/hbase/master/locking/LockProcedure.getProcId:()J
      80: lreturn

  public boolean lockHeartbeat(long, boolean) throws java.io.IOException;
    Code:
       0: aload_0
       1: getfield      #1                  // Field this$0:Lorg/apache/hadoop/hbase/master/locking/LockManager;
       4: invokestatic  #3                  // Method org/apache/hadoop/hbase/master/locking/LockManager.access$000:(Lorg/apache/hadoop/hbase/master/locking/LockManager;)Lorg/apache/hadoop/hbase/master/HMaster;
       7: invokevirtual #15                 // Method org/apache/hadoop/hbase/master/HMaster.getMasterProcedureExecutor:()Lorg/apache/hadoop/hbase/procedure2/ProcedureExecutor;
      10: ldc           #6                  // class org/apache/hadoop/hbase/master/locking/LockProcedure
      12: lload_1
      13: invokevirtual #16                 // Method org/apache/hadoop/hbase/procedure2/ProcedureExecutor.getProcedure:(Ljava/lang/Class;J)Lorg/apache/hadoop/hbase/procedure2/Procedure;
      16: checkcast     #6                  // class org/apache/hadoop/hbase/master/locking/LockProcedure
      19: astore        4
      21: aload         4
      23: ifnonnull     28
      26: iconst_0
      27: ireturn
      28: aload_0
      29: getfield      #1                  // Field this$0:Lorg/apache/hadoop/hbase/master/locking/LockManager;
      32: invokestatic  #3                  // Method org/apache/hadoop/hbase/master/locking/LockManager.access$000:(Lorg/apache/hadoop/hbase/master/locking/LockManager;)Lorg/apache/hadoop/hbase/master/HMaster;
      35: invokevirtual #4                  // Method org/apache/hadoop/hbase/master/HMaster.getMasterCoprocessorHost:()Lorg/apache/hadoop/hbase/master/MasterCoprocessorHost;
      38: aload         4
      40: iload_3
      41: invokevirtual #17                 // Method org/apache/hadoop/hbase/master/MasterCoprocessorHost.preLockHeartbeat:(Lorg/apache/hadoop/hbase/master/locking/LockProcedure;Z)V
      44: aload         4
      46: invokevirtual #18                 // Method org/apache/hadoop/hbase/master/locking/LockProcedure.updateHeartBeat:()V
      49: iload_3
      50: ifne          74
      53: aload         4
      55: aload_0
      56: getfield      #1                  // Field this$0:Lorg/apache/hadoop/hbase/master/locking/LockManager;
      59: invokestatic  #3                  // Method org/apache/hadoop/hbase/master/locking/LockManager.access$000:(Lorg/apache/hadoop/hbase/master/locking/LockManager;)Lorg/apache/hadoop/hbase/master/HMaster;
      62: invokevirtual #15                 // Method org/apache/hadoop/hbase/master/HMaster.getMasterProcedureExecutor:()Lorg/apache/hadoop/hbase/procedure2/ProcedureExecutor;
      65: invokevirtual #19                 // Method org/apache/hadoop/hbase/procedure2/ProcedureExecutor.getEnvironment:()Ljava/lang/Object;
      68: checkcast     #20                 // class org/apache/hadoop/hbase/master/procedure/MasterProcedureEnv
      71: invokevirtual #21                 // Method org/apache/hadoop/hbase/master/locking/LockProcedure.unlock:(Lorg/apache/hadoop/hbase/master/procedure/MasterProcedureEnv;)V
      74: aload_0
      75: getfield      #1                  // Field this$0:Lorg/apache/hadoop/hbase/master/locking/LockManager;
      78: invokestatic  #3                  // Method org/apache/hadoop/hbase/master/locking/LockManager.access$000:(Lorg/apache/hadoop/hbase/master/locking/LockManager;)Lorg/apache/hadoop/hbase/master/HMaster;
      81: invokevirtual #4                  // Method org/apache/hadoop/hbase/master/HMaster.getMasterCoprocessorHost:()Lorg/apache/hadoop/hbase/master/MasterCoprocessorHost;
      84: aload         4
      86: iload_3
      87: invokevirtual #22                 // Method org/apache/hadoop/hbase/master/MasterCoprocessorHost.postLockHeartbeat:(Lorg/apache/hadoop/hbase/master/locking/LockProcedure;Z)V
      90: aload         4
      92: invokevirtual #23                 // Method org/apache/hadoop/hbase/master/locking/LockProcedure.isLocked:()Z
      95: ireturn
}
