Compiled from "MajorCompactor.java"
public class org.apache.hadoop.hbase.util.compaction.MajorCompactor extends org.apache.hadoop.conf.Configured implements org.apache.hadoop.util.Tool {
  protected static final java.util.Set<org.apache.hadoop.hbase.util.compaction.MajorCompactionRequest> ERRORS;

  protected org.apache.hadoop.hbase.util.compaction.ClusterCompactionQueues clusterCompactionQueues;

  protected java.util.Set<java.lang.String> storesToCompact;

  protected java.util.concurrent.ExecutorService executor;

  protected long sleepForMs;

  protected org.apache.hadoop.hbase.client.Connection connection;

  protected org.apache.hadoop.hbase.TableName tableName;

  org.apache.hadoop.hbase.util.compaction.MajorCompactor();
    Code:
       0: aload_0
       1: invokespecial #5                  // Method org/apache/hadoop/conf/Configured."<init>":()V
       4: aload_0
       5: iconst_m1
       6: putfield      #6                  // Field numServers:I
       9: aload_0
      10: iconst_m1
      11: putfield      #7                  // Field numRegions:I
      14: aload_0
      15: iconst_0
      16: putfield      #1                  // Field skipWait:Z
      19: return

  public org.apache.hadoop.hbase.util.compaction.MajorCompactor(org.apache.hadoop.conf.Configuration, org.apache.hadoop.hbase.TableName, java.util.Set<java.lang.String>, int, long, long) throws java.io.IOException;
    Code:
       0: aload_0
       1: invokespecial #5                  // Method org/apache/hadoop/conf/Configured."<init>":()V
       4: aload_0
       5: iconst_m1
       6: putfield      #6                  // Field numServers:I
       9: aload_0
      10: iconst_m1
      11: putfield      #7                  // Field numRegions:I
      14: aload_0
      15: iconst_0
      16: putfield      #1                  // Field skipWait:Z
      19: aload_0
      20: aload_1
      21: invokestatic  #8                  // Method org/apache/hadoop/hbase/client/ConnectionFactory.createConnection:(Lorg/apache/hadoop/conf/Configuration;)Lorg/apache/hadoop/hbase/client/Connection;
      24: putfield      #9                  // Field connection:Lorg/apache/hadoop/hbase/client/Connection;
      27: aload_0
      28: aload_2
      29: putfield      #10                 // Field tableName:Lorg/apache/hadoop/hbase/TableName;
      32: aload_0
      33: lload         5
      35: putfield      #11                 // Field timestamp:J
      38: aload_0
      39: aload_3
      40: putfield      #12                 // Field storesToCompact:Ljava/util/Set;
      43: aload_0
      44: iload         4
      46: invokestatic  #13                 // Method java/util/concurrent/Executors.newFixedThreadPool:(I)Ljava/util/concurrent/ExecutorService;
      49: putfield      #14                 // Field executor:Ljava/util/concurrent/ExecutorService;
      52: aload_0
      53: new           #15                 // class org/apache/hadoop/hbase/util/compaction/ClusterCompactionQueues
      56: dup
      57: iload         4
      59: invokespecial #16                 // Method org/apache/hadoop/hbase/util/compaction/ClusterCompactionQueues."<init>":(I)V
      62: putfield      #17                 // Field clusterCompactionQueues:Lorg/apache/hadoop/hbase/util/compaction/ClusterCompactionQueues;
      65: aload_0
      66: lload         7
      68: putfield      #18                 // Field sleepForMs:J
      71: return

  public void compactAllRegions() throws java.lang.Exception;
    Code:
       0: invokestatic  #19                 // Method org/apache/hbase/thirdparty/com/google/common/collect/Lists.newArrayList:()Ljava/util/ArrayList;
       3: astore_1
       4: aload_0
       5: getfield      #17                 // Field clusterCompactionQueues:Lorg/apache/hadoop/hbase/util/compaction/ClusterCompactionQueues;
       8: invokevirtual #20                 // Method org/apache/hadoop/hbase/util/compaction/ClusterCompactionQueues.hasWorkItems:()Z
      11: ifne          22
      14: aload_0
      15: aload_1
      16: invokespecial #21                 // Method futuresComplete:(Ljava/util/List;)Z
      19: ifne          311
      22: aload_0
      23: getfield      #17                 // Field clusterCompactionQueues:Lorg/apache/hadoop/hbase/util/compaction/ClusterCompactionQueues;
      26: invokevirtual #22                 // Method org/apache/hadoop/hbase/util/compaction/ClusterCompactionQueues.atCapacity:()Z
      29: ifeq          52
      32: getstatic     #4                  // Field LOG:Lorg/slf4j/Logger;
      35: ldc           #23                 // String Waiting for servers to complete Compactions
      37: invokeinterface #24,  2           // InterfaceMethod org/slf4j/Logger.debug:(Ljava/lang/String;)V
      42: aload_0
      43: getfield      #18                 // Field sleepForMs:J
      46: invokestatic  #25                 // Method java/lang/Thread.sleep:(J)V
      49: goto          22
      52: aload_0
      53: getfield      #17                 // Field clusterCompactionQueues:Lorg/apache/hadoop/hbase/util/compaction/ClusterCompactionQueues;
      56: invokevirtual #26                 // Method org/apache/hadoop/hbase/util/compaction/ClusterCompactionQueues.getLargestQueueFromServersNotCompacting:()Ljava/util/Optional;
      59: astore_2
      60: aload_2
      61: invokevirtual #27                 // Method java/util/Optional.isPresent:()Z
      64: ifeq          301
      67: aload_0
      68: getfield      #17                 // Field clusterCompactionQueues:Lorg/apache/hadoop/hbase/util/compaction/ClusterCompactionQueues;
      71: invokevirtual #20                 // Method org/apache/hadoop/hbase/util/compaction/ClusterCompactionQueues.hasWorkItems:()Z
      74: ifeq          301
      77: aload_2
      78: invokevirtual #28                 // Method java/util/Optional.get:()Ljava/lang/Object;
      81: checkcast     #29                 // class org/apache/hadoop/hbase/ServerName
      84: astore_3
      85: aload_0
      86: getfield      #17                 // Field clusterCompactionQueues:Lorg/apache/hadoop/hbase/util/compaction/ClusterCompactionQueues;
      89: aload_3
      90: invokevirtual #30                 // Method org/apache/hadoop/hbase/util/compaction/ClusterCompactionQueues.reserveForCompaction:(Lorg/apache/hadoop/hbase/ServerName;)Lorg/apache/hadoop/hbase/util/compaction/MajorCompactionRequest;
      93: astore        4
      95: aload_0
      96: getfield      #9                  // Field connection:Lorg/apache/hadoop/hbase/client/Connection;
      99: aload_0
     100: getfield      #10                 // Field tableName:Lorg/apache/hadoop/hbase/TableName;
     103: invokeinterface #31,  2           // InterfaceMethod org/apache/hadoop/hbase/client/Connection.getRegionLocator:(Lorg/apache/hadoop/hbase/TableName;)Lorg/apache/hadoop/hbase/client/RegionLocator;
     108: aload         4
     110: invokevirtual #32                 // Method org/apache/hadoop/hbase/util/compaction/MajorCompactionRequest.getRegion:()Lorg/apache/hadoop/hbase/client/RegionInfo;
     113: invokeinterface #33,  1           // InterfaceMethod org/apache/hadoop/hbase/client/RegionInfo.getStartKey:()[B
     118: invokeinterface #34,  2           // InterfaceMethod org/apache/hadoop/hbase/client/RegionLocator.getRegionLocation:([B)Lorg/apache/hadoop/hbase/HRegionLocation;
     123: invokevirtual #35                 // Method org/apache/hadoop/hbase/HRegionLocation.getServerName:()Lorg/apache/hadoop/hbase/ServerName;
     126: astore        5
     128: aload         5
     130: aload_3
     131: invokevirtual #36                 // Method org/apache/hadoop/hbase/ServerName.equals:(Ljava/lang/Object;)Z
     134: ifne          219
     137: getstatic     #4                  // Field LOG:Lorg/slf4j/Logger;
     140: new           #37                 // class java/lang/StringBuilder
     143: dup
     144: invokespecial #38                 // Method java/lang/StringBuilder."<init>":()V
     147: ldc           #39                 // String Server changed for region:
     149: invokevirtual #40                 // Method java/lang/StringBuilder.append:(Ljava/lang/String;)Ljava/lang/StringBuilder;
     152: aload         4
     154: invokevirtual #32                 // Method org/apache/hadoop/hbase/util/compaction/MajorCompactionRequest.getRegion:()Lorg/apache/hadoop/hbase/client/RegionInfo;
     157: invokeinterface #41,  1           // InterfaceMethod org/apache/hadoop/hbase/client/RegionInfo.getEncodedName:()Ljava/lang/String;
     162: invokevirtual #40                 // Method java/lang/StringBuilder.append:(Ljava/lang/String;)Ljava/lang/StringBuilder;
     165: ldc           #42                 // String  from:
     167: invokevirtual #40                 // Method java/lang/StringBuilder.append:(Ljava/lang/String;)Ljava/lang/StringBuilder;
     170: aload_3
     171: invokevirtual #43                 // Method java/lang/StringBuilder.append:(Ljava/lang/Object;)Ljava/lang/StringBuilder;
     174: ldc           #44                 // String  to:
     176: invokevirtual #40                 // Method java/lang/StringBuilder.append:(Ljava/lang/String;)Ljava/lang/StringBuilder;
     179: aload         5
     181: invokevirtual #43                 // Method java/lang/StringBuilder.append:(Ljava/lang/Object;)Ljava/lang/StringBuilder;
     184: ldc           #45                 // String  re-queuing request
     186: invokevirtual #40                 // Method java/lang/StringBuilder.append:(Ljava/lang/String;)Ljava/lang/StringBuilder;
     189: invokevirtual #46                 // Method java/lang/StringBuilder.toString:()Ljava/lang/String;
     192: invokeinterface #47,  2           // InterfaceMethod org/slf4j/Logger.info:(Ljava/lang/String;)V
     197: aload_0
     198: getfield      #17                 // Field clusterCompactionQueues:Lorg/apache/hadoop/hbase/util/compaction/ClusterCompactionQueues;
     201: aload         5
     203: aload         4
     205: invokevirtual #48                 // Method org/apache/hadoop/hbase/util/compaction/ClusterCompactionQueues.addToCompactionQueue:(Lorg/apache/hadoop/hbase/ServerName;Lorg/apache/hadoop/hbase/util/compaction/MajorCompactionRequest;)V
     208: aload_0
     209: getfield      #17                 // Field clusterCompactionQueues:Lorg/apache/hadoop/hbase/util/compaction/ClusterCompactionQueues;
     212: aload_3
     213: invokevirtual #49                 // Method org/apache/hadoop/hbase/util/compaction/ClusterCompactionQueues.releaseCompaction:(Lorg/apache/hadoop/hbase/ServerName;)V
     216: goto          298
     219: getstatic     #4                  // Field LOG:Lorg/slf4j/Logger;
     222: new           #37                 // class java/lang/StringBuilder
     225: dup
     226: invokespecial #38                 // Method java/lang/StringBuilder."<init>":()V
     229: ldc           #50                 // String Firing off compaction request for server:
     231: invokevirtual #40                 // Method java/lang/StringBuilder.append:(Ljava/lang/String;)Ljava/lang/StringBuilder;
     234: aload_3
     235: invokevirtual #43                 // Method java/lang/StringBuilder.append:(Ljava/lang/Object;)Ljava/lang/StringBuilder;
     238: ldc           #51                 // String ,
     240: invokevirtual #40                 // Method java/lang/StringBuilder.append:(Ljava/lang/String;)Ljava/lang/StringBuilder;
     243: aload         4
     245: invokevirtual #43                 // Method java/lang/StringBuilder.append:(Ljava/lang/Object;)Ljava/lang/StringBuilder;
     248: ldc           #52                 // String  total queue size left:
     250: invokevirtual #40                 // Method java/lang/StringBuilder.append:(Ljava/lang/String;)Ljava/lang/StringBuilder;
     253: aload_0
     254: getfield      #17                 // Field clusterCompactionQueues:Lorg/apache/hadoop/hbase/util/compaction/ClusterCompactionQueues;
     257: invokevirtual #53                 // Method org/apache/hadoop/hbase/util/compaction/ClusterCompactionQueues.getCompactionRequestsLeftToFinish:()I
     260: invokevirtual #54                 // Method java/lang/StringBuilder.append:(I)Ljava/lang/StringBuilder;
     263: invokevirtual #46                 // Method java/lang/StringBuilder.toString:()Ljava/lang/String;
     266: invokeinterface #47,  2           // InterfaceMethod org/slf4j/Logger.info:(Ljava/lang/String;)V
     271: aload_1
     272: aload_0
     273: getfield      #14                 // Field executor:Ljava/util/concurrent/ExecutorService;
     276: new           #55                 // class org/apache/hadoop/hbase/util/compaction/MajorCompactor$Compact
     279: dup
     280: aload_0
     281: aload_3
     282: aload         4
     284: invokespecial #56                 // Method org/apache/hadoop/hbase/util/compaction/MajorCompactor$Compact."<init>":(Lorg/apache/hadoop/hbase/util/compaction/MajorCompactor;Lorg/apache/hadoop/hbase/ServerName;Lorg/apache/hadoop/hbase/util/compaction/MajorCompactionRequest;)V
     287: invokeinterface #57,  2           // InterfaceMethod java/util/concurrent/ExecutorService.submit:(Ljava/lang/Runnable;)Ljava/util/concurrent/Future;
     292: invokeinterface #58,  2           // InterfaceMethod java/util/List.add:(Ljava/lang/Object;)Z
     297: pop
     298: goto          308
     301: aload_0
     302: getfield      #18                 // Field sleepForMs:J
     305: invokestatic  #25                 // Method java/lang/Thread.sleep:(J)V
     308: goto          4
     311: getstatic     #4                  // Field LOG:Lorg/slf4j/Logger;
     314: ldc           #59                 // String All compactions have completed
     316: invokeinterface #47,  2           // InterfaceMethod org/slf4j/Logger.info:(Ljava/lang/String;)V
     321: return

  public void shutdown() throws java.lang.Exception;
    Code:
       0: aload_0
       1: getfield      #14                 // Field executor:Ljava/util/concurrent/ExecutorService;
       4: invokeinterface #63,  1           // InterfaceMethod java/util/concurrent/ExecutorService.shutdown:()V
       9: aload_0
      10: getfield      #14                 // Field executor:Ljava/util/concurrent/ExecutorService;
      13: ldc2_w        #65                 // long 9223372036854775807l
      16: getstatic     #67                 // Field java/util/concurrent/TimeUnit.MILLISECONDS:Ljava/util/concurrent/TimeUnit;
      19: invokeinterface #68,  4           // InterfaceMethod java/util/concurrent/ExecutorService.awaitTermination:(JLjava/util/concurrent/TimeUnit;)Z
      24: pop
      25: getstatic     #69                 // Field ERRORS:Ljava/util/Set;
      28: invokeinterface #70,  1           // InterfaceMethod java/util/Set.isEmpty:()Z
      33: ifne          101
      36: new           #37                 // class java/lang/StringBuilder
      39: dup
      40: invokespecial #38                 // Method java/lang/StringBuilder."<init>":()V
      43: ldc           #71                 // String Major compaction failed, there were:
      45: invokevirtual #40                 // Method java/lang/StringBuilder.append:(Ljava/lang/String;)Ljava/lang/StringBuilder;
      48: getstatic     #69                 // Field ERRORS:Ljava/util/Set;
      51: invokeinterface #72,  1           // InterfaceMethod java/util/Set.size:()I
      56: invokevirtual #54                 // Method java/lang/StringBuilder.append:(I)Ljava/lang/StringBuilder;
      59: ldc           #73                 // String  regions / stores that failed compacting\n
      61: invokevirtual #40                 // Method java/lang/StringBuilder.append:(Ljava/lang/String;)Ljava/lang/StringBuilder;
      64: ldc           #74                 // String Failed compaction requests\n
      66: invokevirtual #40                 // Method java/lang/StringBuilder.append:(Ljava/lang/String;)Ljava/lang/StringBuilder;
      69: ldc           #75                 // String --------------------------\n
      71: invokevirtual #40                 // Method java/lang/StringBuilder.append:(Ljava/lang/String;)Ljava/lang/StringBuilder;
      74: ldc           #76                 // String \n
      76: invokestatic  #77                 // Method org/apache/hbase/thirdparty/com/google/common/base/Joiner.on:(Ljava/lang/String;)Lorg/apache/hbase/thirdparty/com/google/common/base/Joiner;
      79: getstatic     #69                 // Field ERRORS:Ljava/util/Set;
      82: invokevirtual #78                 // Method org/apache/hbase/thirdparty/com/google/common/base/Joiner.join:(Ljava/lang/Iterable;)Ljava/lang/String;
      85: invokevirtual #40                 // Method java/lang/StringBuilder.append:(Ljava/lang/String;)Ljava/lang/StringBuilder;
      88: astore_1
      89: getstatic     #4                  // Field LOG:Lorg/slf4j/Logger;
      92: aload_1
      93: invokevirtual #46                 // Method java/lang/StringBuilder.toString:()Ljava/lang/String;
      96: invokeinterface #79,  2           // InterfaceMethod org/slf4j/Logger.error:(Ljava/lang/String;)V
     101: aload_0
     102: getfield      #9                  // Field connection:Lorg/apache/hadoop/hbase/client/Connection;
     105: ifnull        117
     108: aload_0
     109: getfield      #9                  // Field connection:Lorg/apache/hadoop/hbase/client/Connection;
     112: invokeinterface #80,  1           // InterfaceMethod org/apache/hadoop/hbase/client/Connection.close:()V
     117: getstatic     #4                  // Field LOG:Lorg/slf4j/Logger;
     120: ldc           #81                 // String All regions major compacted successfully
     122: invokeinterface #47,  2           // InterfaceMethod org/slf4j/Logger.info:(Ljava/lang/String;)V
     127: return

  void initializeWorkQueues() throws java.io.IOException;
    Code:
       0: aload_0
       1: getfield      #12                 // Field storesToCompact:Ljava/util/Set;
       4: invokeinterface #70,  1           // InterfaceMethod java/util/Set.isEmpty:()Z
       9: ifeq          56
      12: aload_0
      13: getfield      #9                  // Field connection:Lorg/apache/hadoop/hbase/client/Connection;
      16: aload_0
      17: getfield      #10                 // Field tableName:Lorg/apache/hadoop/hbase/TableName;
      20: invokeinterface #82,  2           // InterfaceMethod org/apache/hadoop/hbase/client/Connection.getTable:(Lorg/apache/hadoop/hbase/TableName;)Lorg/apache/hadoop/hbase/client/Table;
      25: invokeinterface #83,  1           // InterfaceMethod org/apache/hadoop/hbase/client/Table.getDescriptor:()Lorg/apache/hadoop/hbase/client/TableDescriptor;
      30: invokeinterface #84,  1           // InterfaceMethod org/apache/hadoop/hbase/client/TableDescriptor.getColumnFamilyNames:()Ljava/util/Set;
      35: aload_0
      36: invokedynamic #85,  0             // InvokeDynamic #1:accept:(Lorg/apache/hadoop/hbase/util/compaction/MajorCompactor;)Ljava/util/function/Consumer;
      41: invokeinterface #86,  2           // InterfaceMethod java/util/Set.forEach:(Ljava/util/function/Consumer;)V
      46: getstatic     #4                  // Field LOG:Lorg/slf4j/Logger;
      49: ldc           #87                 // String No family specified, will execute for all families
      51: invokeinterface #47,  2           // InterfaceMethod org/slf4j/Logger.info:(Ljava/lang/String;)V
      56: getstatic     #4                  // Field LOG:Lorg/slf4j/Logger;
      59: new           #37                 // class java/lang/StringBuilder
      62: dup
      63: invokespecial #38                 // Method java/lang/StringBuilder."<init>":()V
      66: ldc           #88                 // String Initializing compaction queues for table:
      68: invokevirtual #40                 // Method java/lang/StringBuilder.append:(Ljava/lang/String;)Ljava/lang/StringBuilder;
      71: aload_0
      72: getfield      #10                 // Field tableName:Lorg/apache/hadoop/hbase/TableName;
      75: invokevirtual #43                 // Method java/lang/StringBuilder.append:(Ljava/lang/Object;)Ljava/lang/StringBuilder;
      78: ldc           #89                 // String  with cf:
      80: invokevirtual #40                 // Method java/lang/StringBuilder.append:(Ljava/lang/String;)Ljava/lang/StringBuilder;
      83: aload_0
      84: getfield      #12                 // Field storesToCompact:Ljava/util/Set;
      87: invokevirtual #43                 // Method java/lang/StringBuilder.append:(Ljava/lang/Object;)Ljava/lang/StringBuilder;
      90: invokevirtual #46                 // Method java/lang/StringBuilder.toString:()Ljava/lang/String;
      93: invokeinterface #47,  2           // InterfaceMethod org/slf4j/Logger.info:(Ljava/lang/String;)V
      98: aload_0
      99: invokespecial #90                 // Method getServerRegionsMap:()Ljava/util/Map;
     102: astore_1
     103: aload_0
     104: aload_1
     105: invokeinterface #91,  1           // InterfaceMethod java/util/Map.keySet:()Ljava/util/Set;
     110: invokespecial #92                 // Method getServersToCompact:(Ljava/util/Set;)Ljava/util/Collection;
     113: invokeinterface #93,  1           // InterfaceMethod java/util/Collection.iterator:()Ljava/util/Iterator;
     118: astore_2
     119: aload_2
     120: invokeinterface #94,  1           // InterfaceMethod java/util/Iterator.hasNext:()Z
     125: ifeq          378
     128: aload_2
     129: invokeinterface #95,  1           // InterfaceMethod java/util/Iterator.next:()Ljava/lang/Object;
     134: checkcast     #29                 // class org/apache/hadoop/hbase/ServerName
     137: astore_3
     138: aload_1
     139: aload_3
     140: invokeinterface #96,  2           // InterfaceMethod java/util/Map.get:(Ljava/lang/Object;)Ljava/lang/Object;
     145: checkcast     #97                 // class java/util/List
     148: astore        4
     150: getstatic     #4                  // Field LOG:Lorg/slf4j/Logger;
     153: new           #37                 // class java/lang/StringBuilder
     156: dup
     157: invokespecial #38                 // Method java/lang/StringBuilder."<init>":()V
     160: ldc           #98                 // String Table:
     162: invokevirtual #40                 // Method java/lang/StringBuilder.append:(Ljava/lang/String;)Ljava/lang/StringBuilder;
     165: aload_0
     166: getfield      #10                 // Field tableName:Lorg/apache/hadoop/hbase/TableName;
     169: invokevirtual #43                 // Method java/lang/StringBuilder.append:(Ljava/lang/Object;)Ljava/lang/StringBuilder;
     172: ldc           #99                 // String  Server:
     174: invokevirtual #40                 // Method java/lang/StringBuilder.append:(Ljava/lang/String;)Ljava/lang/StringBuilder;
     177: aload_3
     178: invokevirtual #43                 // Method java/lang/StringBuilder.append:(Ljava/lang/Object;)Ljava/lang/StringBuilder;
     181: ldc           #100                // String  No of regions:
     183: invokevirtual #40                 // Method java/lang/StringBuilder.append:(Ljava/lang/String;)Ljava/lang/StringBuilder;
     186: aload         4
     188: invokeinterface #101,  1          // InterfaceMethod java/util/List.size:()I
     193: invokevirtual #54                 // Method java/lang/StringBuilder.append:(I)Ljava/lang/StringBuilder;
     196: invokevirtual #46                 // Method java/lang/StringBuilder.toString:()Ljava/lang/String;
     199: invokeinterface #24,  2           // InterfaceMethod org/slf4j/Logger.debug:(Ljava/lang/String;)V
     204: aload         4
     206: invokestatic  #102                // Method java/util/Collections.shuffle:(Ljava/util/List;)V
     209: aload_0
     210: getfield      #7                  // Field numRegions:I
     213: istore        5
     215: aload         4
     217: invokeinterface #103,  1          // InterfaceMethod java/util/List.iterator:()Ljava/util/Iterator;
     222: astore        6
     224: aload         6
     226: invokeinterface #94,  1           // InterfaceMethod java/util/Iterator.hasNext:()Z
     231: ifeq          375
     234: aload         6
     236: invokeinterface #95,  1           // InterfaceMethod java/util/Iterator.next:()Ljava/lang/Object;
     241: checkcast     #104                // class org/apache/hadoop/hbase/client/RegionInfo
     244: astore        7
     246: aload_0
     247: getfield      #7                  // Field numRegions:I
     250: ifle          288
     253: iload         5
     255: ifgt          288
     258: getstatic     #4                  // Field LOG:Lorg/slf4j/Logger;
     261: new           #37                 // class java/lang/StringBuilder
     264: dup
     265: invokespecial #38                 // Method java/lang/StringBuilder."<init>":()V
     268: ldc           #105                // String Reached region limit for server:
     270: invokevirtual #40                 // Method java/lang/StringBuilder.append:(Ljava/lang/String;)Ljava/lang/StringBuilder;
     273: aload_3
     274: invokevirtual #43                 // Method java/lang/StringBuilder.append:(Ljava/lang/Object;)Ljava/lang/StringBuilder;
     277: invokevirtual #46                 // Method java/lang/StringBuilder.toString:()Ljava/lang/String;
     280: invokeinterface #24,  2           // InterfaceMethod org/slf4j/Logger.debug:(Ljava/lang/String;)V
     285: goto          375
     288: aload_0
     289: aload         7
     291: invokevirtual #106                // Method getMajorCompactionRequest:(Lorg/apache/hadoop/hbase/client/RegionInfo;)Ljava/util/Optional;
     294: astore        8
     296: aload         8
     298: invokevirtual #27                 // Method java/util/Optional.isPresent:()Z
     301: ifeq          372
     304: getstatic     #4                  // Field LOG:Lorg/slf4j/Logger;
     307: new           #37                 // class java/lang/StringBuilder
     310: dup
     311: invokespecial #38                 // Method java/lang/StringBuilder."<init>":()V
     314: ldc           #107                // String Adding region
     316: invokevirtual #40                 // Method java/lang/StringBuilder.append:(Ljava/lang/String;)Ljava/lang/StringBuilder;
     319: aload         7
     321: invokevirtual #43                 // Method java/lang/StringBuilder.append:(Ljava/lang/Object;)Ljava/lang/StringBuilder;
     324: ldc           #108                // String  to queue
     326: invokevirtual #40                 // Method java/lang/StringBuilder.append:(Ljava/lang/String;)Ljava/lang/StringBuilder;
     329: aload_3
     330: invokevirtual #43                 // Method java/lang/StringBuilder.append:(Ljava/lang/Object;)Ljava/lang/StringBuilder;
     333: ldc           #109                // String  for compaction
     335: invokevirtual #40                 // Method java/lang/StringBuilder.append:(Ljava/lang/String;)Ljava/lang/StringBuilder;
     338: invokevirtual #46                 // Method java/lang/StringBuilder.toString:()Ljava/lang/String;
     341: invokeinterface #24,  2           // InterfaceMethod org/slf4j/Logger.debug:(Ljava/lang/String;)V
     346: aload_0
     347: getfield      #17                 // Field clusterCompactionQueues:Lorg/apache/hadoop/hbase/util/compaction/ClusterCompactionQueues;
     350: aload_3
     351: aload         8
     353: invokevirtual #28                 // Method java/util/Optional.get:()Ljava/lang/Object;
     356: checkcast     #110                // class org/apache/hadoop/hbase/util/compaction/MajorCompactionRequest
     359: invokevirtual #48                 // Method org/apache/hadoop/hbase/util/compaction/ClusterCompactionQueues.addToCompactionQueue:(Lorg/apache/hadoop/hbase/ServerName;Lorg/apache/hadoop/hbase/util/compaction/MajorCompactionRequest;)V
     362: aload_0
     363: getfield      #7                  // Field numRegions:I
     366: ifle          372
     369: iinc          5, -1
     372: goto          224
     375: goto          119
     378: return

  protected java.util.Optional<org.apache.hadoop.hbase.util.compaction.MajorCompactionRequest> getMajorCompactionRequest(org.apache.hadoop.hbase.client.RegionInfo) throws java.io.IOException;
    Code:
       0: aload_0
       1: getfield      #9                  // Field connection:Lorg/apache/hadoop/hbase/client/Connection;
       4: invokeinterface #111,  1          // InterfaceMethod org/apache/hadoop/hbase/client/Connection.getConfiguration:()Lorg/apache/hadoop/conf/Configuration;
       9: aload_1
      10: aload_0
      11: getfield      #12                 // Field storesToCompact:Ljava/util/Set;
      14: aload_0
      15: getfield      #11                 // Field timestamp:J
      18: invokestatic  #112                // Method org/apache/hadoop/hbase/util/compaction/MajorCompactionRequest.newRequest:(Lorg/apache/hadoop/conf/Configuration;Lorg/apache/hadoop/hbase/client/RegionInfo;Ljava/util/Set;J)Ljava/util/Optional;
      21: areturn

  public void setNumServers(int);
    Code:
       0: aload_0
       1: iload_1
       2: putfield      #6                  // Field numServers:I
       5: return

  public void setNumRegions(int);
    Code:
       0: aload_0
       1: iload_1
       2: putfield      #7                  // Field numRegions:I
       5: return

  public void setSkipWait(boolean);
    Code:
       0: aload_0
       1: iload_1
       2: putfield      #1                  // Field skipWait:Z
       5: return

  protected java.util.Set<java.lang.String> getStoresRequiringCompaction(org.apache.hadoop.hbase.util.compaction.MajorCompactionRequest) throws java.io.IOException;
    Code:
       0: aload_1
       1: aload_0
       2: getfield      #12                 // Field storesToCompact:Ljava/util/Set;
       5: aload_0
       6: getfield      #11                 // Field timestamp:J
       9: invokevirtual #133                // Method org/apache/hadoop/hbase/util/compaction/MajorCompactionRequest.getStoresRequiringCompaction:(Ljava/util/Set;J)Ljava/util/Set;
      12: areturn

  protected org.apache.hbase.thirdparty.org.apache.commons.cli.Options getCommonOptions();
    Code:
       0: new           #134                // class org/apache/hbase/thirdparty/org/apache/commons/cli/Options
       3: dup
       4: invokespecial #135                // Method org/apache/hbase/thirdparty/org/apache/commons/cli/Options."<init>":()V
       7: astore_1
       8: aload_1
       9: ldc           #136                // String servers
      11: invokestatic  #137                // Method org/apache/hbase/thirdparty/org/apache/commons/cli/Option.builder:(Ljava/lang/String;)Lorg/apache/hbase/thirdparty/org/apache/commons/cli/Option$Builder;
      14: invokevirtual #138                // Method org/apache/hbase/thirdparty/org/apache/commons/cli/Option$Builder.required:()Lorg/apache/hbase/thirdparty/org/apache/commons/cli/Option$Builder;
      17: ldc           #139                // String Concurrent servers compacting
      19: invokevirtual #140                // Method org/apache/hbase/thirdparty/org/apache/commons/cli/Option$Builder.desc:(Ljava/lang/String;)Lorg/apache/hbase/thirdparty/org/apache/commons/cli/Option$Builder;
      22: invokevirtual #141                // Method org/apache/hbase/thirdparty/org/apache/commons/cli/Option$Builder.hasArg:()Lorg/apache/hbase/thirdparty/org/apache/commons/cli/Option$Builder;
      25: invokevirtual #142                // Method org/apache/hbase/thirdparty/org/apache/commons/cli/Option$Builder.build:()Lorg/apache/hbase/thirdparty/org/apache/commons/cli/Option;
      28: invokevirtual #143                // Method org/apache/hbase/thirdparty/org/apache/commons/cli/Options.addOption:(Lorg/apache/hbase/thirdparty/org/apache/commons/cli/Option;)Lorg/apache/hbase/thirdparty/org/apache/commons/cli/Options;
      31: pop
      32: aload_1
      33: ldc           #144                // String minModTime
      35: invokestatic  #137                // Method org/apache/hbase/thirdparty/org/apache/commons/cli/Option.builder:(Ljava/lang/String;)Lorg/apache/hbase/thirdparty/org/apache/commons/cli/Option$Builder;
      38: ldc           #145                // String Compact if store files have modification time < minModTime
      40: invokevirtual #140                // Method org/apache/hbase/thirdparty/org/apache/commons/cli/Option$Builder.desc:(Ljava/lang/String;)Lorg/apache/hbase/thirdparty/org/apache/commons/cli/Option$Builder;
      43: invokevirtual #141                // Method org/apache/hbase/thirdparty/org/apache/commons/cli/Option$Builder.hasArg:()Lorg/apache/hbase/thirdparty/org/apache/commons/cli/Option$Builder;
      46: invokevirtual #142                // Method org/apache/hbase/thirdparty/org/apache/commons/cli/Option$Builder.build:()Lorg/apache/hbase/thirdparty/org/apache/commons/cli/Option;
      49: invokevirtual #143                // Method org/apache/hbase/thirdparty/org/apache/commons/cli/Options.addOption:(Lorg/apache/hbase/thirdparty/org/apache/commons/cli/Option;)Lorg/apache/hbase/thirdparty/org/apache/commons/cli/Options;
      52: pop
      53: aload_1
      54: ldc           #146                // String zk
      56: invokestatic  #137                // Method org/apache/hbase/thirdparty/org/apache/commons/cli/Option.builder:(Ljava/lang/String;)Lorg/apache/hbase/thirdparty/org/apache/commons/cli/Option$Builder;
      59: iconst_1
      60: invokevirtual #147                // Method org/apache/hbase/thirdparty/org/apache/commons/cli/Option$Builder.optionalArg:(Z)Lorg/apache/hbase/thirdparty/org/apache/commons/cli/Option$Builder;
      63: ldc           #148                // String zk quorum
      65: invokevirtual #140                // Method org/apache/hbase/thirdparty/org/apache/commons/cli/Option$Builder.desc:(Ljava/lang/String;)Lorg/apache/hbase/thirdparty/org/apache/commons/cli/Option$Builder;
      68: invokevirtual #141                // Method org/apache/hbase/thirdparty/org/apache/commons/cli/Option$Builder.hasArg:()Lorg/apache/hbase/thirdparty/org/apache/commons/cli/Option$Builder;
      71: invokevirtual #142                // Method org/apache/hbase/thirdparty/org/apache/commons/cli/Option$Builder.build:()Lorg/apache/hbase/thirdparty/org/apache/commons/cli/Option;
      74: invokevirtual #143                // Method org/apache/hbase/thirdparty/org/apache/commons/cli/Options.addOption:(Lorg/apache/hbase/thirdparty/org/apache/commons/cli/Option;)Lorg/apache/hbase/thirdparty/org/apache/commons/cli/Options;
      77: pop
      78: aload_1
      79: ldc           #149                // String rootDir
      81: invokestatic  #137                // Method org/apache/hbase/thirdparty/org/apache/commons/cli/Option.builder:(Ljava/lang/String;)Lorg/apache/hbase/thirdparty/org/apache/commons/cli/Option$Builder;
      84: iconst_1
      85: invokevirtual #147                // Method org/apache/hbase/thirdparty/org/apache/commons/cli/Option$Builder.optionalArg:(Z)Lorg/apache/hbase/thirdparty/org/apache/commons/cli/Option$Builder;
      88: ldc           #150                // String hbase.rootDir
      90: invokevirtual #140                // Method org/apache/hbase/thirdparty/org/apache/commons/cli/Option$Builder.desc:(Ljava/lang/String;)Lorg/apache/hbase/thirdparty/org/apache/commons/cli/Option$Builder;
      93: invokevirtual #141                // Method org/apache/hbase/thirdparty/org/apache/commons/cli/Option$Builder.hasArg:()Lorg/apache/hbase/thirdparty/org/apache/commons/cli/Option$Builder;
      96: invokevirtual #142                // Method org/apache/hbase/thirdparty/org/apache/commons/cli/Option$Builder.build:()Lorg/apache/hbase/thirdparty/org/apache/commons/cli/Option;
      99: invokevirtual #143                // Method org/apache/hbase/thirdparty/org/apache/commons/cli/Options.addOption:(Lorg/apache/hbase/thirdparty/org/apache/commons/cli/Option;)Lorg/apache/hbase/thirdparty/org/apache/commons/cli/Options;
     102: pop
     103: aload_1
     104: ldc           #151                // String sleep
     106: invokestatic  #137                // Method org/apache/hbase/thirdparty/org/apache/commons/cli/Option.builder:(Ljava/lang/String;)Lorg/apache/hbase/thirdparty/org/apache/commons/cli/Option$Builder;
     109: ldc           #152                // String Time to sleepForMs (ms) for checking compaction status per region and available work queues: default 30s
     111: invokevirtual #140                // Method org/apache/hbase/thirdparty/org/apache/commons/cli/Option$Builder.desc:(Ljava/lang/String;)Lorg/apache/hbase/thirdparty/org/apache/commons/cli/Option$Builder;
     114: invokevirtual #141                // Method org/apache/hbase/thirdparty/org/apache/commons/cli/Option$Builder.hasArg:()Lorg/apache/hbase/thirdparty/org/apache/commons/cli/Option$Builder;
     117: invokevirtual #142                // Method org/apache/hbase/thirdparty/org/apache/commons/cli/Option$Builder.build:()Lorg/apache/hbase/thirdparty/org/apache/commons/cli/Option;
     120: invokevirtual #143                // Method org/apache/hbase/thirdparty/org/apache/commons/cli/Options.addOption:(Lorg/apache/hbase/thirdparty/org/apache/commons/cli/Option;)Lorg/apache/hbase/thirdparty/org/apache/commons/cli/Options;
     123: pop
     124: aload_1
     125: ldc           #153                // String retries
     127: invokestatic  #137                // Method org/apache/hbase/thirdparty/org/apache/commons/cli/Option.builder:(Ljava/lang/String;)Lorg/apache/hbase/thirdparty/org/apache/commons/cli/Option$Builder;
     130: ldc           #154                // String Max # of retries for a compaction request, defaults to 3
     132: invokevirtual #140                // Method org/apache/hbase/thirdparty/org/apache/commons/cli/Option$Builder.desc:(Ljava/lang/String;)Lorg/apache/hbase/thirdparty/org/apache/commons/cli/Option$Builder;
     135: invokevirtual #141                // Method org/apache/hbase/thirdparty/org/apache/commons/cli/Option$Builder.hasArg:()Lorg/apache/hbase/thirdparty/org/apache/commons/cli/Option$Builder;
     138: invokevirtual #142                // Method org/apache/hbase/thirdparty/org/apache/commons/cli/Option$Builder.build:()Lorg/apache/hbase/thirdparty/org/apache/commons/cli/Option;
     141: invokevirtual #143                // Method org/apache/hbase/thirdparty/org/apache/commons/cli/Options.addOption:(Lorg/apache/hbase/thirdparty/org/apache/commons/cli/Option;)Lorg/apache/hbase/thirdparty/org/apache/commons/cli/Options;
     144: pop
     145: aload_1
     146: ldc           #155                // String dryRun
     148: invokestatic  #137                // Method org/apache/hbase/thirdparty/org/apache/commons/cli/Option.builder:(Ljava/lang/String;)Lorg/apache/hbase/thirdparty/org/apache/commons/cli/Option$Builder;
     151: ldc           #156                // String Dry run, will just output a list of regions that require compaction based on parameters passed
     153: invokevirtual #140                // Method org/apache/hbase/thirdparty/org/apache/commons/cli/Option$Builder.desc:(Ljava/lang/String;)Lorg/apache/hbase/thirdparty/org/apache/commons/cli/Option$Builder;
     156: iconst_0
     157: invokevirtual #157                // Method org/apache/hbase/thirdparty/org/apache/commons/cli/Option$Builder.hasArg:(Z)Lorg/apache/hbase/thirdparty/org/apache/commons/cli/Option$Builder;
     160: invokevirtual #142                // Method org/apache/hbase/thirdparty/org/apache/commons/cli/Option$Builder.build:()Lorg/apache/hbase/thirdparty/org/apache/commons/cli/Option;
     163: invokevirtual #143                // Method org/apache/hbase/thirdparty/org/apache/commons/cli/Options.addOption:(Lorg/apache/hbase/thirdparty/org/apache/commons/cli/Option;)Lorg/apache/hbase/thirdparty/org/apache/commons/cli/Options;
     166: pop
     167: aload_1
     168: ldc           #158                // String skipWait
     170: invokestatic  #137                // Method org/apache/hbase/thirdparty/org/apache/commons/cli/Option.builder:(Ljava/lang/String;)Lorg/apache/hbase/thirdparty/org/apache/commons/cli/Option$Builder;
     173: ldc           #159                // String Skip waiting after triggering compaction.
     175: invokevirtual #140                // Method org/apache/hbase/thirdparty/org/apache/commons/cli/Option$Builder.desc:(Ljava/lang/String;)Lorg/apache/hbase/thirdparty/org/apache/commons/cli/Option$Builder;
     178: iconst_0
     179: invokevirtual #157                // Method org/apache/hbase/thirdparty/org/apache/commons/cli/Option$Builder.hasArg:(Z)Lorg/apache/hbase/thirdparty/org/apache/commons/cli/Option$Builder;
     182: invokevirtual #142                // Method org/apache/hbase/thirdparty/org/apache/commons/cli/Option$Builder.build:()Lorg/apache/hbase/thirdparty/org/apache/commons/cli/Option;
     185: invokevirtual #143                // Method org/apache/hbase/thirdparty/org/apache/commons/cli/Options.addOption:(Lorg/apache/hbase/thirdparty/org/apache/commons/cli/Option;)Lorg/apache/hbase/thirdparty/org/apache/commons/cli/Options;
     188: pop
     189: aload_1
     190: ldc           #160                // String numservers
     192: invokestatic  #137                // Method org/apache/hbase/thirdparty/org/apache/commons/cli/Option.builder:(Ljava/lang/String;)Lorg/apache/hbase/thirdparty/org/apache/commons/cli/Option$Builder;
     195: iconst_1
     196: invokevirtual #147                // Method org/apache/hbase/thirdparty/org/apache/commons/cli/Option$Builder.optionalArg:(Z)Lorg/apache/hbase/thirdparty/org/apache/commons/cli/Option$Builder;
     199: ldc           #161                // String Number of servers to compact in this run, defaults to all
     201: invokevirtual #140                // Method org/apache/hbase/thirdparty/org/apache/commons/cli/Option$Builder.desc:(Ljava/lang/String;)Lorg/apache/hbase/thirdparty/org/apache/commons/cli/Option$Builder;
     204: invokevirtual #141                // Method org/apache/hbase/thirdparty/org/apache/commons/cli/Option$Builder.hasArg:()Lorg/apache/hbase/thirdparty/org/apache/commons/cli/Option$Builder;
     207: invokevirtual #142                // Method org/apache/hbase/thirdparty/org/apache/commons/cli/Option$Builder.build:()Lorg/apache/hbase/thirdparty/org/apache/commons/cli/Option;
     210: invokevirtual #143                // Method org/apache/hbase/thirdparty/org/apache/commons/cli/Options.addOption:(Lorg/apache/hbase/thirdparty/org/apache/commons/cli/Option;)Lorg/apache/hbase/thirdparty/org/apache/commons/cli/Options;
     213: pop
     214: aload_1
     215: ldc           #162                // String numregions
     217: invokestatic  #137                // Method org/apache/hbase/thirdparty/org/apache/commons/cli/Option.builder:(Ljava/lang/String;)Lorg/apache/hbase/thirdparty/org/apache/commons/cli/Option$Builder;
     220: iconst_1
     221: invokevirtual #147                // Method org/apache/hbase/thirdparty/org/apache/commons/cli/Option$Builder.optionalArg:(Z)Lorg/apache/hbase/thirdparty/org/apache/commons/cli/Option$Builder;
     224: ldc           #163                // String Number of regions to compact per server, defaults to all
     226: invokevirtual #140                // Method org/apache/hbase/thirdparty/org/apache/commons/cli/Option$Builder.desc:(Ljava/lang/String;)Lorg/apache/hbase/thirdparty/org/apache/commons/cli/Option$Builder;
     229: invokevirtual #141                // Method org/apache/hbase/thirdparty/org/apache/commons/cli/Option$Builder.hasArg:()Lorg/apache/hbase/thirdparty/org/apache/commons/cli/Option$Builder;
     232: invokevirtual #142                // Method org/apache/hbase/thirdparty/org/apache/commons/cli/Option$Builder.build:()Lorg/apache/hbase/thirdparty/org/apache/commons/cli/Option;
     235: invokevirtual #143                // Method org/apache/hbase/thirdparty/org/apache/commons/cli/Options.addOption:(Lorg/apache/hbase/thirdparty/org/apache/commons/cli/Option;)Lorg/apache/hbase/thirdparty/org/apache/commons/cli/Options;
     238: pop
     239: aload_1
     240: areturn

  public int run(java.lang.String[]) throws java.lang.Exception;
    Code:
       0: aload_0
       1: invokevirtual #164                // Method getCommonOptions:()Lorg/apache/hbase/thirdparty/org/apache/commons/cli/Options;
       4: astore_2
       5: aload_2
       6: ldc           #165                // String table
       8: invokestatic  #137                // Method org/apache/hbase/thirdparty/org/apache/commons/cli/Option.builder:(Ljava/lang/String;)Lorg/apache/hbase/thirdparty/org/apache/commons/cli/Option$Builder;
      11: invokevirtual #138                // Method org/apache/hbase/thirdparty/org/apache/commons/cli/Option$Builder.required:()Lorg/apache/hbase/thirdparty/org/apache/commons/cli/Option$Builder;
      14: ldc           #166                // String table name
      16: invokevirtual #140                // Method org/apache/hbase/thirdparty/org/apache/commons/cli/Option$Builder.desc:(Ljava/lang/String;)Lorg/apache/hbase/thirdparty/org/apache/commons/cli/Option$Builder;
      19: invokevirtual #141                // Method org/apache/hbase/thirdparty/org/apache/commons/cli/Option$Builder.hasArg:()Lorg/apache/hbase/thirdparty/org/apache/commons/cli/Option$Builder;
      22: invokevirtual #142                // Method org/apache/hbase/thirdparty/org/apache/commons/cli/Option$Builder.build:()Lorg/apache/hbase/thirdparty/org/apache/commons/cli/Option;
      25: invokevirtual #143                // Method org/apache/hbase/thirdparty/org/apache/commons/cli/Options.addOption:(Lorg/apache/hbase/thirdparty/org/apache/commons/cli/Option;)Lorg/apache/hbase/thirdparty/org/apache/commons/cli/Options;
      28: pop
      29: aload_2
      30: ldc           #167                // String cf
      32: invokestatic  #137                // Method org/apache/hbase/thirdparty/org/apache/commons/cli/Option.builder:(Ljava/lang/String;)Lorg/apache/hbase/thirdparty/org/apache/commons/cli/Option$Builder;
      35: iconst_1
      36: invokevirtual #147                // Method org/apache/hbase/thirdparty/org/apache/commons/cli/Option$Builder.optionalArg:(Z)Lorg/apache/hbase/thirdparty/org/apache/commons/cli/Option$Builder;
      39: ldc           #168                // String column families: comma separated eg: a,b,c
      41: invokevirtual #140                // Method org/apache/hbase/thirdparty/org/apache/commons/cli/Option$Builder.desc:(Ljava/lang/String;)Lorg/apache/hbase/thirdparty/org/apache/commons/cli/Option$Builder;
      44: invokevirtual #141                // Method org/apache/hbase/thirdparty/org/apache/commons/cli/Option$Builder.hasArg:()Lorg/apache/hbase/thirdparty/org/apache/commons/cli/Option$Builder;
      47: invokevirtual #142                // Method org/apache/hbase/thirdparty/org/apache/commons/cli/Option$Builder.build:()Lorg/apache/hbase/thirdparty/org/apache/commons/cli/Option;
      50: invokevirtual #143                // Method org/apache/hbase/thirdparty/org/apache/commons/cli/Options.addOption:(Lorg/apache/hbase/thirdparty/org/apache/commons/cli/Option;)Lorg/apache/hbase/thirdparty/org/apache/commons/cli/Options;
      53: pop
      54: new           #169                // class org/apache/hbase/thirdparty/org/apache/commons/cli/DefaultParser
      57: dup
      58: invokespecial #170                // Method org/apache/hbase/thirdparty/org/apache/commons/cli/DefaultParser."<init>":()V
      61: astore_3
      62: aconst_null
      63: astore        4
      65: aload_3
      66: aload_2
      67: aload_1
      68: invokeinterface #171,  3          // InterfaceMethod org/apache/hbase/thirdparty/org/apache/commons/cli/CommandLineParser.parse:(Lorg/apache/hbase/thirdparty/org/apache/commons/cli/Options;[Ljava/lang/String;)Lorg/apache/hbase/thirdparty/org/apache/commons/cli/CommandLine;
      73: astore        4
      75: goto          124
      78: astore        5
      80: getstatic     #173                // Field java/lang/System.out:Ljava/io/PrintStream;
      83: new           #37                 // class java/lang/StringBuilder
      86: dup
      87: invokespecial #38                 // Method java/lang/StringBuilder."<init>":()V
      90: ldc           #174                // String ERROR: Unable to parse command-line arguments
      92: invokevirtual #40                 // Method java/lang/StringBuilder.append:(Ljava/lang/String;)Ljava/lang/StringBuilder;
      95: aload_1
      96: invokestatic  #175                // Method java/util/Arrays.toString:([Ljava/lang/Object;)Ljava/lang/String;
      99: invokevirtual #40                 // Method java/lang/StringBuilder.append:(Ljava/lang/String;)Ljava/lang/StringBuilder;
     102: ldc           #176                // String  due to:
     104: invokevirtual #40                 // Method java/lang/StringBuilder.append:(Ljava/lang/String;)Ljava/lang/StringBuilder;
     107: aload         5
     109: invokevirtual #43                 // Method java/lang/StringBuilder.append:(Ljava/lang/Object;)Ljava/lang/StringBuilder;
     112: invokevirtual #46                 // Method java/lang/StringBuilder.toString:()Ljava/lang/String;
     115: invokevirtual #177                // Method java/io/PrintStream.println:(Ljava/lang/String;)V
     118: aload_2
     119: invokestatic  #178                // Method printUsage:(Lorg/apache/hbase/thirdparty/org/apache/commons/cli/Options;)V
     122: iconst_m1
     123: ireturn
     124: aload         4
     126: ifnonnull     163
     129: getstatic     #173                // Field java/lang/System.out:Ljava/io/PrintStream;
     132: new           #37                 // class java/lang/StringBuilder
     135: dup
     136: invokespecial #38                 // Method java/lang/StringBuilder."<init>":()V
     139: ldc           #179                // String ERROR: Failed parse, empty commandLine;
     141: invokevirtual #40                 // Method java/lang/StringBuilder.append:(Ljava/lang/String;)Ljava/lang/StringBuilder;
     144: aload_1
     145: invokestatic  #175                // Method java/util/Arrays.toString:([Ljava/lang/Object;)Ljava/lang/String;
     148: invokevirtual #40                 // Method java/lang/StringBuilder.append:(Ljava/lang/String;)Ljava/lang/StringBuilder;
     151: invokevirtual #46                 // Method java/lang/StringBuilder.toString:()Ljava/lang/String;
     154: invokevirtual #177                // Method java/io/PrintStream.println:(Ljava/lang/String;)V
     157: aload_2
     158: invokestatic  #178                // Method printUsage:(Lorg/apache/hbase/thirdparty/org/apache/commons/cli/Options;)V
     161: iconst_m1
     162: ireturn
     163: aload         4
     165: ldc           #165                // String table
     167: invokevirtual #180                // Method org/apache/hbase/thirdparty/org/apache/commons/cli/CommandLine.getOptionValue:(Ljava/lang/String;)Ljava/lang/String;
     170: astore        5
     172: aload         4
     174: ldc           #167                // String cf
     176: aconst_null
     177: invokevirtual #181                // Method org/apache/hbase/thirdparty/org/apache/commons/cli/CommandLine.getOptionValue:(Ljava/lang/String;Ljava/lang/String;)Ljava/lang/String;
     180: astore        6
     182: invokestatic  #182                // Method org/apache/hbase/thirdparty/com/google/common/collect/Sets.newHashSet:()Ljava/util/HashSet;
     185: astore        7
     187: aload         6
     189: ifnull        208
     192: aload         7
     194: ldc           #183                // String ,
     196: invokestatic  #184                // Method org/apache/hbase/thirdparty/com/google/common/base/Splitter.on:(Ljava/lang/String;)Lorg/apache/hbase/thirdparty/com/google/common/base/Splitter;
     199: aload         6
     201: invokevirtual #185                // Method org/apache/hbase/thirdparty/com/google/common/base/Splitter.split:(Ljava/lang/CharSequence;)Ljava/lang/Iterable;
     204: invokestatic  #186                // Method org/apache/hbase/thirdparty/com/google/common/collect/Iterables.addAll:(Ljava/util/Collection;Ljava/lang/Iterable;)Z
     207: pop
     208: aload_0
     209: invokevirtual #187                // Method getConf:()Lorg/apache/hadoop/conf/Configuration;
     212: astore        8
     214: aload         4
     216: ldc           #136                // String servers
     218: invokevirtual #180                // Method org/apache/hbase/thirdparty/org/apache/commons/cli/CommandLine.getOptionValue:(Ljava/lang/String;)Ljava/lang/String;
     221: invokestatic  #188                // Method java/lang/Integer.parseInt:(Ljava/lang/String;)I
     224: istore        9
     226: aload         4
     228: ldc           #144                // String minModTime
     230: invokestatic  #189                // Method java/lang/System.currentTimeMillis:()J
     233: invokestatic  #190                // Method java/lang/String.valueOf:(J)Ljava/lang/String;
     236: invokevirtual #181                // Method org/apache/hbase/thirdparty/org/apache/commons/cli/CommandLine.getOptionValue:(Ljava/lang/String;Ljava/lang/String;)Ljava/lang/String;
     239: invokestatic  #191                // Method java/lang/Long.parseLong:(Ljava/lang/String;)J
     242: lstore        10
     244: aload         4
     246: ldc           #146                // String zk
     248: aload         8
     250: ldc           #193                // String hbase.zookeeper.quorum
     252: invokevirtual #194                // Method org/apache/hadoop/conf/Configuration.get:(Ljava/lang/String;)Ljava/lang/String;
     255: invokevirtual #181                // Method org/apache/hbase/thirdparty/org/apache/commons/cli/CommandLine.getOptionValue:(Ljava/lang/String;Ljava/lang/String;)Ljava/lang/String;
     258: astore        12
     260: aload         4
     262: ldc           #149                // String rootDir
     264: aload         8
     266: ldc           #195                // String hbase.rootdir
     268: invokevirtual #194                // Method org/apache/hadoop/conf/Configuration.get:(Ljava/lang/String;)Ljava/lang/String;
     271: invokevirtual #181                // Method org/apache/hbase/thirdparty/org/apache/commons/cli/CommandLine.getOptionValue:(Ljava/lang/String;Ljava/lang/String;)Ljava/lang/String;
     274: astore        13
     276: aload         4
     278: ldc           #151                // String sleep
     280: ldc2_w        #196                // long 30000l
     283: invokestatic  #198                // Method java/lang/Long.toString:(J)Ljava/lang/String;
     286: invokevirtual #181                // Method org/apache/hbase/thirdparty/org/apache/commons/cli/CommandLine.getOptionValue:(Ljava/lang/String;Ljava/lang/String;)Ljava/lang/String;
     289: invokestatic  #191                // Method java/lang/Long.parseLong:(Ljava/lang/String;)J
     292: lstore        14
     294: aload         4
     296: ldc           #160                // String numservers
     298: ldc           #199                // String -1
     300: invokevirtual #181                // Method org/apache/hbase/thirdparty/org/apache/commons/cli/CommandLine.getOptionValue:(Ljava/lang/String;Ljava/lang/String;)Ljava/lang/String;
     303: invokestatic  #188                // Method java/lang/Integer.parseInt:(Ljava/lang/String;)I
     306: istore        16
     308: aload         4
     310: ldc           #162                // String numregions
     312: ldc           #199                // String -1
     314: invokevirtual #181                // Method org/apache/hbase/thirdparty/org/apache/commons/cli/CommandLine.getOptionValue:(Ljava/lang/String;Ljava/lang/String;)Ljava/lang/String;
     317: invokestatic  #188                // Method java/lang/Integer.parseInt:(Ljava/lang/String;)I
     320: istore        17
     322: aload         8
     324: ldc           #195                // String hbase.rootdir
     326: aload         13
     328: invokevirtual #200                // Method org/apache/hadoop/conf/Configuration.set:(Ljava/lang/String;Ljava/lang/String;)V
     331: aload         8
     333: ldc           #193                // String hbase.zookeeper.quorum
     335: aload         12
     337: invokevirtual #200                // Method org/apache/hadoop/conf/Configuration.set:(Ljava/lang/String;Ljava/lang/String;)V
     340: new           #201                // class org/apache/hadoop/hbase/util/compaction/MajorCompactor
     343: dup
     344: aload         8
     346: aload         5
     348: invokestatic  #202                // Method org/apache/hadoop/hbase/TableName.valueOf:(Ljava/lang/String;)Lorg/apache/hadoop/hbase/TableName;
     351: aload         7
     353: iload         9
     355: lload         10
     357: lload         14
     359: invokespecial #203                // Method "<init>":(Lorg/apache/hadoop/conf/Configuration;Lorg/apache/hadoop/hbase/TableName;Ljava/util/Set;IJJ)V
     362: astore        18
     364: aload         18
     366: iload         16
     368: invokevirtual #204                // Method setNumServers:(I)V
     371: aload         18
     373: iload         17
     375: invokevirtual #205                // Method setNumRegions:(I)V
     378: aload         18
     380: aload         4
     382: ldc           #158                // String skipWait
     384: invokevirtual #206                // Method org/apache/hbase/thirdparty/org/apache/commons/cli/CommandLine.hasOption:(Ljava/lang/String;)Z
     387: invokevirtual #207                // Method setSkipWait:(Z)V
     390: aload         18
     392: invokevirtual #208                // Method initializeWorkQueues:()V
     395: aload         4
     397: ldc           #155                // String dryRun
     399: invokevirtual #206                // Method org/apache/hbase/thirdparty/org/apache/commons/cli/CommandLine.hasOption:(Ljava/lang/String;)Z
     402: ifne          410
     405: aload         18
     407: invokevirtual #209                // Method compactAllRegions:()V
     410: aload         18
     412: invokevirtual #210                // Method shutdown:()V
     415: getstatic     #69                 // Field ERRORS:Ljava/util/Set;
     418: invokeinterface #72,  1           // InterfaceMethod java/util/Set.size:()I
     423: ireturn
    Exception table:
       from    to  target type
          65    75    78   Class org/apache/hbase/thirdparty/org/apache/commons/cli/ParseException

  protected static void printUsage(org.apache.hbase.thirdparty.org.apache.commons.cli.Options);
    Code:
       0: ldc           #211                // String \nUsage instructions\n\n
       2: astore_1
       3: ldc           #76                 // String \n
       5: astore_2
       6: new           #212                // class org/apache/hbase/thirdparty/org/apache/commons/cli/HelpFormatter
       9: dup
      10: invokespecial #213                // Method org/apache/hbase/thirdparty/org/apache/commons/cli/HelpFormatter."<init>":()V
      13: astore_3
      14: aload_3
      15: ldc           #201                // class org/apache/hadoop/hbase/util/compaction/MajorCompactor
      17: invokevirtual #214                // Method java/lang/Class.getSimpleName:()Ljava/lang/String;
      20: aload_1
      21: aload_0
      22: aload_2
      23: iconst_1
      24: invokevirtual #215                // Method org/apache/hbase/thirdparty/org/apache/commons/cli/HelpFormatter.printHelp:(Ljava/lang/String;Ljava/lang/String;Lorg/apache/hbase/thirdparty/org/apache/commons/cli/Options;Ljava/lang/String;Z)V
      27: return

  public static void main(java.lang.String[]) throws java.lang.Exception;
    Code:
       0: invokestatic  #216                // Method org/apache/hadoop/hbase/HBaseConfiguration.create:()Lorg/apache/hadoop/conf/Configuration;
       3: new           #201                // class org/apache/hadoop/hbase/util/compaction/MajorCompactor
       6: dup
       7: invokespecial #217                // Method "<init>":()V
      10: aload_0
      11: invokestatic  #218                // Method org/apache/hadoop/util/ToolRunner.run:(Lorg/apache/hadoop/conf/Configuration;Lorg/apache/hadoop/util/Tool;[Ljava/lang/String;)I
      14: pop
      15: return

  static org.slf4j.Logger access$000();
    Code:
       0: getstatic     #4                  // Field LOG:Lorg/slf4j/Logger;
       3: areturn

  static void access$100(org.apache.hadoop.hbase.util.compaction.MajorCompactor);
    Code:
       0: aload_0
       1: invokespecial #3                  // Method addNewRegions:()V
       4: return

  static boolean access$200(org.apache.hadoop.hbase.util.compaction.MajorCompactor, org.apache.hadoop.hbase.util.compaction.MajorCompactionRequest) throws java.lang.Exception;
    Code:
       0: aload_0
       1: aload_1
       2: invokespecial #2                  // Method isCompacting:(Lorg/apache/hadoop/hbase/util/compaction/MajorCompactionRequest;)Z
       5: ireturn

  static boolean access$300(org.apache.hadoop.hbase.util.compaction.MajorCompactor);
    Code:
       0: aload_0
       1: getfield      #1                  // Field skipWait:Z
       4: ireturn

  static {};
    Code:
       0: ldc           #201                // class org/apache/hadoop/hbase/util/compaction/MajorCompactor
       2: invokestatic  #221                // Method org/slf4j/LoggerFactory.getLogger:(Ljava/lang/Class;)Lorg/slf4j/Logger;
       5: putstatic     #4                  // Field LOG:Lorg/slf4j/Logger;
       8: invokestatic  #222                // Method java/util/concurrent/ConcurrentHashMap.newKeySet:()Ljava/util/concurrent/ConcurrentHashMap$KeySetView;
      11: putstatic     #69                 // Field ERRORS:Ljava/util/Set;
      14: return
}
