Compiled from "ManualEnvironmentEdge.java"
public class org.apache.hadoop.hbase.util.ManualEnvironmentEdge implements org.apache.hadoop.hbase.util.EnvironmentEdge {
  protected long value;

  public org.apache.hadoop.hbase.util.ManualEnvironmentEdge();
    Code:
       0: aload_0
       1: invokespecial #1                  // Method java/lang/Object."<init>":()V
       4: aload_0
       5: lconst_1
       6: putfield      #2                  // Field value:J
       9: return

  public void setValue(long);
    Code:
       0: aload_0
       1: lload_1
       2: putfield      #2                  // Field value:J
       5: return

  public void incValue(long);
    Code:
       0: aload_0
       1: dup
       2: getfield      #2                  // Field value:J
       5: lload_1
       6: ladd
       7: putfield      #2                  // Field value:J
      10: return

  public long currentTime();
    Code:
       0: aload_0
       1: getfield      #2                  // Field value:J
       4: lreturn
}
