Compiled from "MapReduceProtos.java"
public final class org.apache.hadoop.hbase.protobuf.generated.MapReduceProtos$TableSnapshotRegionSplit$Builder extends com.google.protobuf.GeneratedMessage$Builder<org.apache.hadoop.hbase.protobuf.generated.MapReduceProtos$TableSnapshotRegionSplit$Builder> implements org.apache.hadoop.hbase.protobuf.generated.MapReduceProtos$TableSnapshotRegionSplitOrBuilder {
  public static final com.google.protobuf.Descriptors$Descriptor getDescriptor();
    Code:
       0: invokestatic  #3                  // Method org/apache/hadoop/hbase/protobuf/generated/MapReduceProtos.access$900:()Lcom/google/protobuf/Descriptors$Descriptor;
       3: areturn

  protected com.google.protobuf.GeneratedMessage$FieldAccessorTable internalGetFieldAccessorTable();
    Code:
       0: invokestatic  #4                  // Method org/apache/hadoop/hbase/protobuf/generated/MapReduceProtos.access$1000:()Lcom/google/protobuf/GeneratedMessage$FieldAccessorTable;
       3: ldc           #5                  // class org/apache/hadoop/hbase/protobuf/generated/MapReduceProtos$TableSnapshotRegionSplit
       5: ldc           #6                  // class org/apache/hadoop/hbase/protobuf/generated/MapReduceProtos$TableSnapshotRegionSplit$Builder
       7: invokevirtual #7                  // Method com/google/protobuf/GeneratedMessage$FieldAccessorTable.ensureFieldAccessorsInitialized:(Ljava/lang/Class;Ljava/lang/Class;)Lcom/google/protobuf/GeneratedMessage$FieldAccessorTable;
      10: areturn

  public org.apache.hadoop.hbase.protobuf.generated.MapReduceProtos$TableSnapshotRegionSplit$Builder clear();
    Code:
       0: aload_0
       1: invokespecial #21                 // Method com/google/protobuf/GeneratedMessage$Builder.clear:()Lcom/google/protobuf/GeneratedMessage$Builder;
       4: pop
       5: aload_0
       6: getstatic     #9                  // Field com/google/protobuf/LazyStringArrayList.EMPTY:Lcom/google/protobuf/LazyStringList;
       9: putfield      #10                 // Field locations_:Lcom/google/protobuf/LazyStringList;
      12: aload_0
      13: aload_0
      14: getfield      #22                 // Field bitField0_:I
      17: bipush        -2
      19: iand
      20: putfield      #22                 // Field bitField0_:I
      23: aload_0
      24: getfield      #23                 // Field tableBuilder_:Lcom/google/protobuf/SingleFieldBuilder;
      27: ifnonnull     40
      30: aload_0
      31: invokestatic  #11                 // Method org/apache/hadoop/hbase/protobuf/generated/HBaseProtos$TableSchema.getDefaultInstance:()Lorg/apache/hadoop/hbase/protobuf/generated/HBaseProtos$TableSchema;
      34: putfield      #12                 // Field table_:Lorg/apache/hadoop/hbase/protobuf/generated/HBaseProtos$TableSchema;
      37: goto          48
      40: aload_0
      41: getfield      #23                 // Field tableBuilder_:Lcom/google/protobuf/SingleFieldBuilder;
      44: invokevirtual #24                 // Method com/google/protobuf/SingleFieldBuilder.clear:()Lcom/google/protobuf/SingleFieldBuilder;
      47: pop
      48: aload_0
      49: aload_0
      50: getfield      #22                 // Field bitField0_:I
      53: bipush        -3
      55: iand
      56: putfield      #22                 // Field bitField0_:I
      59: aload_0
      60: getfield      #25                 // Field regionBuilder_:Lcom/google/protobuf/SingleFieldBuilder;
      63: ifnonnull     76
      66: aload_0
      67: invokestatic  #13                 // Method org/apache/hadoop/hbase/protobuf/generated/HBaseProtos$RegionInfo.getDefaultInstance:()Lorg/apache/hadoop/hbase/protobuf/generated/HBaseProtos$RegionInfo;
      70: putfield      #14                 // Field region_:Lorg/apache/hadoop/hbase/protobuf/generated/HBaseProtos$RegionInfo;
      73: goto          84
      76: aload_0
      77: getfield      #25                 // Field regionBuilder_:Lcom/google/protobuf/SingleFieldBuilder;
      80: invokevirtual #24                 // Method com/google/protobuf/SingleFieldBuilder.clear:()Lcom/google/protobuf/SingleFieldBuilder;
      83: pop
      84: aload_0
      85: aload_0
      86: getfield      #22                 // Field bitField0_:I
      89: bipush        -5
      91: iand
      92: putfield      #22                 // Field bitField0_:I
      95: aload_0
      96: areturn

  public org.apache.hadoop.hbase.protobuf.generated.MapReduceProtos$TableSnapshotRegionSplit$Builder clone();
    Code:
       0: invokestatic  #2                  // Method create:()Lorg/apache/hadoop/hbase/protobuf/generated/MapReduceProtos$TableSnapshotRegionSplit$Builder;
       3: aload_0
       4: invokevirtual #26                 // Method buildPartial:()Lorg/apache/hadoop/hbase/protobuf/generated/MapReduceProtos$TableSnapshotRegionSplit;
       7: invokevirtual #27                 // Method mergeFrom:(Lorg/apache/hadoop/hbase/protobuf/generated/MapReduceProtos$TableSnapshotRegionSplit;)Lorg/apache/hadoop/hbase/protobuf/generated/MapReduceProtos$TableSnapshotRegionSplit$Builder;
      10: areturn

  public com.google.protobuf.Descriptors$Descriptor getDescriptorForType();
    Code:
       0: invokestatic  #3                  // Method org/apache/hadoop/hbase/protobuf/generated/MapReduceProtos.access$900:()Lcom/google/protobuf/Descriptors$Descriptor;
       3: areturn

  public org.apache.hadoop.hbase.protobuf.generated.MapReduceProtos$TableSnapshotRegionSplit getDefaultInstanceForType();
    Code:
       0: invokestatic  #28                 // Method org/apache/hadoop/hbase/protobuf/generated/MapReduceProtos$TableSnapshotRegionSplit.getDefaultInstance:()Lorg/apache/hadoop/hbase/protobuf/generated/MapReduceProtos$TableSnapshotRegionSplit;
       3: areturn

  public org.apache.hadoop.hbase.protobuf.generated.MapReduceProtos$TableSnapshotRegionSplit build();
    Code:
       0: aload_0
       1: invokevirtual #26                 // Method buildPartial:()Lorg/apache/hadoop/hbase/protobuf/generated/MapReduceProtos$TableSnapshotRegionSplit;
       4: astore_1
       5: aload_1
       6: invokevirtual #29                 // Method org/apache/hadoop/hbase/protobuf/generated/MapReduceProtos$TableSnapshotRegionSplit.isInitialized:()Z
       9: ifne          17
      12: aload_1
      13: invokestatic  #30                 // Method newUninitializedMessageException:(Lcom/google/protobuf/Message;)Lcom/google/protobuf/UninitializedMessageException;
      16: athrow
      17: aload_1
      18: areturn

  public org.apache.hadoop.hbase.protobuf.generated.MapReduceProtos$TableSnapshotRegionSplit buildPartial();
    Code:
       0: new           #5                  // class org/apache/hadoop/hbase/protobuf/generated/MapReduceProtos$TableSnapshotRegionSplit
       3: dup
       4: aload_0
       5: aconst_null
       6: invokespecial #31                 // Method org/apache/hadoop/hbase/protobuf/generated/MapReduceProtos$TableSnapshotRegionSplit."<init>":(Lcom/google/protobuf/GeneratedMessage$Builder;Lorg/apache/hadoop/hbase/protobuf/generated/MapReduceProtos$1;)V
       9: astore_1
      10: aload_0
      11: getfield      #22                 // Field bitField0_:I
      14: istore_2
      15: iconst_0
      16: istore_3
      17: aload_0
      18: getfield      #22                 // Field bitField0_:I
      21: iconst_1
      22: iand
      23: iconst_1
      24: if_icmpne     53
      27: aload_0
      28: new           #32                 // class com/google/protobuf/UnmodifiableLazyStringList
      31: dup
      32: aload_0
      33: getfield      #10                 // Field locations_:Lcom/google/protobuf/LazyStringList;
      36: invokespecial #33                 // Method com/google/protobuf/UnmodifiableLazyStringList."<init>":(Lcom/google/protobuf/LazyStringList;)V
      39: putfield      #10                 // Field locations_:Lcom/google/protobuf/LazyStringList;
      42: aload_0
      43: aload_0
      44: getfield      #22                 // Field bitField0_:I
      47: bipush        -2
      49: iand
      50: putfield      #22                 // Field bitField0_:I
      53: aload_1
      54: aload_0
      55: getfield      #10                 // Field locations_:Lcom/google/protobuf/LazyStringList;
      58: invokestatic  #34                 // Method org/apache/hadoop/hbase/protobuf/generated/MapReduceProtos$TableSnapshotRegionSplit.access$1602:(Lorg/apache/hadoop/hbase/protobuf/generated/MapReduceProtos$TableSnapshotRegionSplit;Lcom/google/protobuf/LazyStringList;)Lcom/google/protobuf/LazyStringList;
      61: pop
      62: iload_2
      63: iconst_2
      64: iand
      65: iconst_2
      66: if_icmpne     73
      69: iload_3
      70: iconst_1
      71: ior
      72: istore_3
      73: aload_0
      74: getfield      #23                 // Field tableBuilder_:Lcom/google/protobuf/SingleFieldBuilder;
      77: ifnonnull     92
      80: aload_1
      81: aload_0
      82: getfield      #12                 // Field table_:Lorg/apache/hadoop/hbase/protobuf/generated/HBaseProtos$TableSchema;
      85: invokestatic  #35                 // Method org/apache/hadoop/hbase/protobuf/generated/MapReduceProtos$TableSnapshotRegionSplit.access$1702:(Lorg/apache/hadoop/hbase/protobuf/generated/MapReduceProtos$TableSnapshotRegionSplit;Lorg/apache/hadoop/hbase/protobuf/generated/HBaseProtos$TableSchema;)Lorg/apache/hadoop/hbase/protobuf/generated/HBaseProtos$TableSchema;
      88: pop
      89: goto          107
      92: aload_1
      93: aload_0
      94: getfield      #23                 // Field tableBuilder_:Lcom/google/protobuf/SingleFieldBuilder;
      97: invokevirtual #36                 // Method com/google/protobuf/SingleFieldBuilder.build:()Lcom/google/protobuf/GeneratedMessage;
     100: checkcast     #37                 // class org/apache/hadoop/hbase/protobuf/generated/HBaseProtos$TableSchema
     103: invokestatic  #35                 // Method org/apache/hadoop/hbase/protobuf/generated/MapReduceProtos$TableSnapshotRegionSplit.access$1702:(Lorg/apache/hadoop/hbase/protobuf/generated/MapReduceProtos$TableSnapshotRegionSplit;Lorg/apache/hadoop/hbase/protobuf/generated/HBaseProtos$TableSchema;)Lorg/apache/hadoop/hbase/protobuf/generated/HBaseProtos$TableSchema;
     106: pop
     107: iload_2
     108: iconst_4
     109: iand
     110: iconst_4
     111: if_icmpne     118
     114: iload_3
     115: iconst_2
     116: ior
     117: istore_3
     118: aload_0
     119: getfield      #25                 // Field regionBuilder_:Lcom/google/protobuf/SingleFieldBuilder;
     122: ifnonnull     137
     125: aload_1
     126: aload_0
     127: getfield      #14                 // Field region_:Lorg/apache/hadoop/hbase/protobuf/generated/HBaseProtos$RegionInfo;
     130: invokestatic  #38                 // Method org/apache/hadoop/hbase/protobuf/generated/MapReduceProtos$TableSnapshotRegionSplit.access$1802:(Lorg/apache/hadoop/hbase/protobuf/generated/MapReduceProtos$TableSnapshotRegionSplit;Lorg/apache/hadoop/hbase/protobuf/generated/HBaseProtos$RegionInfo;)Lorg/apache/hadoop/hbase/protobuf/generated/HBaseProtos$RegionInfo;
     133: pop
     134: goto          152
     137: aload_1
     138: aload_0
     139: getfield      #25                 // Field regionBuilder_:Lcom/google/protobuf/SingleFieldBuilder;
     142: invokevirtual #36                 // Method com/google/protobuf/SingleFieldBuilder.build:()Lcom/google/protobuf/GeneratedMessage;
     145: checkcast     #39                 // class org/apache/hadoop/hbase/protobuf/generated/HBaseProtos$RegionInfo
     148: invokestatic  #38                 // Method org/apache/hadoop/hbase/protobuf/generated/MapReduceProtos$TableSnapshotRegionSplit.access$1802:(Lorg/apache/hadoop/hbase/protobuf/generated/MapReduceProtos$TableSnapshotRegionSplit;Lorg/apache/hadoop/hbase/protobuf/generated/HBaseProtos$RegionInfo;)Lorg/apache/hadoop/hbase/protobuf/generated/HBaseProtos$RegionInfo;
     151: pop
     152: aload_1
     153: iload_3
     154: invokestatic  #40                 // Method org/apache/hadoop/hbase/protobuf/generated/MapReduceProtos$TableSnapshotRegionSplit.access$1902:(Lorg/apache/hadoop/hbase/protobuf/generated/MapReduceProtos$TableSnapshotRegionSplit;I)I
     157: pop
     158: aload_0
     159: invokevirtual #41                 // Method onBuilt:()V
     162: aload_1
     163: areturn

  public org.apache.hadoop.hbase.protobuf.generated.MapReduceProtos$TableSnapshotRegionSplit$Builder mergeFrom(com.google.protobuf.Message);
    Code:
       0: aload_1
       1: instanceof    #5                  // class org/apache/hadoop/hbase/protobuf/generated/MapReduceProtos$TableSnapshotRegionSplit
       4: ifeq          16
       7: aload_0
       8: aload_1
       9: checkcast     #5                  // class org/apache/hadoop/hbase/protobuf/generated/MapReduceProtos$TableSnapshotRegionSplit
      12: invokevirtual #27                 // Method mergeFrom:(Lorg/apache/hadoop/hbase/protobuf/generated/MapReduceProtos$TableSnapshotRegionSplit;)Lorg/apache/hadoop/hbase/protobuf/generated/MapReduceProtos$TableSnapshotRegionSplit$Builder;
      15: areturn
      16: aload_0
      17: aload_1
      18: invokespecial #42                 // Method com/google/protobuf/GeneratedMessage$Builder.mergeFrom:(Lcom/google/protobuf/Message;)Lcom/google/protobuf/AbstractMessage$Builder;
      21: pop
      22: aload_0
      23: areturn

  public org.apache.hadoop.hbase.protobuf.generated.MapReduceProtos$TableSnapshotRegionSplit$Builder mergeFrom(org.apache.hadoop.hbase.protobuf.generated.MapReduceProtos$TableSnapshotRegionSplit);
    Code:
       0: aload_1
       1: invokestatic  #28                 // Method org/apache/hadoop/hbase/protobuf/generated/MapReduceProtos$TableSnapshotRegionSplit.getDefaultInstance:()Lorg/apache/hadoop/hbase/protobuf/generated/MapReduceProtos$TableSnapshotRegionSplit;
       4: if_acmpne     9
       7: aload_0
       8: areturn
       9: aload_1
      10: invokestatic  #43                 // Method org/apache/hadoop/hbase/protobuf/generated/MapReduceProtos$TableSnapshotRegionSplit.access$1600:(Lorg/apache/hadoop/hbase/protobuf/generated/MapReduceProtos$TableSnapshotRegionSplit;)Lcom/google/protobuf/LazyStringList;
      13: invokeinterface #44,  1           // InterfaceMethod com/google/protobuf/LazyStringList.isEmpty:()Z
      18: ifne          77
      21: aload_0
      22: getfield      #10                 // Field locations_:Lcom/google/protobuf/LazyStringList;
      25: invokeinterface #44,  1           // InterfaceMethod com/google/protobuf/LazyStringList.isEmpty:()Z
      30: ifeq          55
      33: aload_0
      34: aload_1
      35: invokestatic  #43                 // Method org/apache/hadoop/hbase/protobuf/generated/MapReduceProtos$TableSnapshotRegionSplit.access$1600:(Lorg/apache/hadoop/hbase/protobuf/generated/MapReduceProtos$TableSnapshotRegionSplit;)Lcom/google/protobuf/LazyStringList;
      38: putfield      #10                 // Field locations_:Lcom/google/protobuf/LazyStringList;
      41: aload_0
      42: aload_0
      43: getfield      #22                 // Field bitField0_:I
      46: bipush        -2
      48: iand
      49: putfield      #22                 // Field bitField0_:I
      52: goto          73
      55: aload_0
      56: invokespecial #45                 // Method ensureLocationsIsMutable:()V
      59: aload_0
      60: getfield      #10                 // Field locations_:Lcom/google/protobuf/LazyStringList;
      63: aload_1
      64: invokestatic  #43                 // Method org/apache/hadoop/hbase/protobuf/generated/MapReduceProtos$TableSnapshotRegionSplit.access$1600:(Lorg/apache/hadoop/hbase/protobuf/generated/MapReduceProtos$TableSnapshotRegionSplit;)Lcom/google/protobuf/LazyStringList;
      67: invokeinterface #46,  2           // InterfaceMethod com/google/protobuf/LazyStringList.addAll:(Ljava/util/Collection;)Z
      72: pop
      73: aload_0
      74: invokevirtual #47                 // Method onChanged:()V
      77: aload_1
      78: invokevirtual #48                 // Method org/apache/hadoop/hbase/protobuf/generated/MapReduceProtos$TableSnapshotRegionSplit.hasTable:()Z
      81: ifeq          93
      84: aload_0
      85: aload_1
      86: invokevirtual #49                 // Method org/apache/hadoop/hbase/protobuf/generated/MapReduceProtos$TableSnapshotRegionSplit.getTable:()Lorg/apache/hadoop/hbase/protobuf/generated/HBaseProtos$TableSchema;
      89: invokevirtual #50                 // Method mergeTable:(Lorg/apache/hadoop/hbase/protobuf/generated/HBaseProtos$TableSchema;)Lorg/apache/hadoop/hbase/protobuf/generated/MapReduceProtos$TableSnapshotRegionSplit$Builder;
      92: pop
      93: aload_1
      94: invokevirtual #51                 // Method org/apache/hadoop/hbase/protobuf/generated/MapReduceProtos$TableSnapshotRegionSplit.hasRegion:()Z
      97: ifeq          109
     100: aload_0
     101: aload_1
     102: invokevirtual #52                 // Method org/apache/hadoop/hbase/protobuf/generated/MapReduceProtos$TableSnapshotRegionSplit.getRegion:()Lorg/apache/hadoop/hbase/protobuf/generated/HBaseProtos$RegionInfo;
     105: invokevirtual #53                 // Method mergeRegion:(Lorg/apache/hadoop/hbase/protobuf/generated/HBaseProtos$RegionInfo;)Lorg/apache/hadoop/hbase/protobuf/generated/MapReduceProtos$TableSnapshotRegionSplit$Builder;
     108: pop
     109: aload_0
     110: aload_1
     111: invokevirtual #54                 // Method org/apache/hadoop/hbase/protobuf/generated/MapReduceProtos$TableSnapshotRegionSplit.getUnknownFields:()Lcom/google/protobuf/UnknownFieldSet;
     114: invokevirtual #55                 // Method mergeUnknownFields:(Lcom/google/protobuf/UnknownFieldSet;)Lcom/google/protobuf/GeneratedMessage$Builder;
     117: pop
     118: aload_0
     119: areturn

  public final boolean isInitialized();
    Code:
       0: aload_0
       1: invokevirtual #56                 // Method hasTable:()Z
       4: ifeq          19
       7: aload_0
       8: invokevirtual #57                 // Method getTable:()Lorg/apache/hadoop/hbase/protobuf/generated/HBaseProtos$TableSchema;
      11: invokevirtual #58                 // Method org/apache/hadoop/hbase/protobuf/generated/HBaseProtos$TableSchema.isInitialized:()Z
      14: ifne          19
      17: iconst_0
      18: ireturn
      19: aload_0
      20: invokevirtual #59                 // Method hasRegion:()Z
      23: ifeq          38
      26: aload_0
      27: invokevirtual #60                 // Method getRegion:()Lorg/apache/hadoop/hbase/protobuf/generated/HBaseProtos$RegionInfo;
      30: invokevirtual #61                 // Method org/apache/hadoop/hbase/protobuf/generated/HBaseProtos$RegionInfo.isInitialized:()Z
      33: ifne          38
      36: iconst_0
      37: ireturn
      38: iconst_1
      39: ireturn

  public org.apache.hadoop.hbase.protobuf.generated.MapReduceProtos$TableSnapshotRegionSplit$Builder mergeFrom(com.google.protobuf.CodedInputStream, com.google.protobuf.ExtensionRegistryLite) throws java.io.IOException;
    Code:
       0: aconst_null
       1: astore_3
       2: getstatic     #62                 // Field org/apache/hadoop/hbase/protobuf/generated/MapReduceProtos$TableSnapshotRegionSplit.PARSER:Lcom/google/protobuf/Parser;
       5: aload_1
       6: aload_2
       7: invokeinterface #63,  3           // InterfaceMethod com/google/protobuf/Parser.parsePartialFrom:(Lcom/google/protobuf/CodedInputStream;Lcom/google/protobuf/ExtensionRegistryLite;)Ljava/lang/Object;
      12: checkcast     #5                  // class org/apache/hadoop/hbase/protobuf/generated/MapReduceProtos$TableSnapshotRegionSplit
      15: astore_3
      16: aload_3
      17: ifnull        58
      20: aload_0
      21: aload_3
      22: invokevirtual #27                 // Method mergeFrom:(Lorg/apache/hadoop/hbase/protobuf/generated/MapReduceProtos$TableSnapshotRegionSplit;)Lorg/apache/hadoop/hbase/protobuf/generated/MapReduceProtos$TableSnapshotRegionSplit$Builder;
      25: pop
      26: goto          58
      29: astore        4
      31: aload         4
      33: invokevirtual #65                 // Method com/google/protobuf/InvalidProtocolBufferException.getUnfinishedMessage:()Lcom/google/protobuf/MessageLite;
      36: checkcast     #5                  // class org/apache/hadoop/hbase/protobuf/generated/MapReduceProtos$TableSnapshotRegionSplit
      39: astore_3
      40: aload         4
      42: athrow
      43: astore        5
      45: aload_3
      46: ifnull        55
      49: aload_0
      50: aload_3
      51: invokevirtual #27                 // Method mergeFrom:(Lorg/apache/hadoop/hbase/protobuf/generated/MapReduceProtos$TableSnapshotRegionSplit;)Lorg/apache/hadoop/hbase/protobuf/generated/MapReduceProtos$TableSnapshotRegionSplit$Builder;
      54: pop
      55: aload         5
      57: athrow
      58: aload_0
      59: areturn
    Exception table:
       from    to  target type
           2    16    29   Class com/google/protobuf/InvalidProtocolBufferException
           2    16    43   any
          29    45    43   any

  public java.util.List<java.lang.String> getLocationsList();
    Code:
       0: aload_0
       1: getfield      #10                 // Field locations_:Lcom/google/protobuf/LazyStringList;
       4: invokestatic  #68                 // Method java/util/Collections.unmodifiableList:(Ljava/util/List;)Ljava/util/List;
       7: areturn

  public int getLocationsCount();
    Code:
       0: aload_0
       1: getfield      #10                 // Field locations_:Lcom/google/protobuf/LazyStringList;
       4: invokeinterface #69,  1           // InterfaceMethod com/google/protobuf/LazyStringList.size:()I
       9: ireturn

  public java.lang.String getLocations(int);
    Code:
       0: aload_0
       1: getfield      #10                 // Field locations_:Lcom/google/protobuf/LazyStringList;
       4: iload_1
       5: invokeinterface #70,  2           // InterfaceMethod com/google/protobuf/LazyStringList.get:(I)Ljava/lang/Object;
      10: checkcast     #71                 // class java/lang/String
      13: areturn

  public com.google.protobuf.ByteString getLocationsBytes(int);
    Code:
       0: aload_0
       1: getfield      #10                 // Field locations_:Lcom/google/protobuf/LazyStringList;
       4: iload_1
       5: invokeinterface #72,  2           // InterfaceMethod com/google/protobuf/LazyStringList.getByteString:(I)Lcom/google/protobuf/ByteString;
      10: areturn

  public org.apache.hadoop.hbase.protobuf.generated.MapReduceProtos$TableSnapshotRegionSplit$Builder setLocations(int, java.lang.String);
    Code:
       0: aload_2
       1: ifnonnull     12
       4: new           #73                 // class java/lang/NullPointerException
       7: dup
       8: invokespecial #74                 // Method java/lang/NullPointerException."<init>":()V
      11: athrow
      12: aload_0
      13: invokespecial #45                 // Method ensureLocationsIsMutable:()V
      16: aload_0
      17: getfield      #10                 // Field locations_:Lcom/google/protobuf/LazyStringList;
      20: iload_1
      21: aload_2
      22: invokeinterface #75,  3           // InterfaceMethod com/google/protobuf/LazyStringList.set:(ILjava/lang/Object;)Ljava/lang/Object;
      27: pop
      28: aload_0
      29: invokevirtual #47                 // Method onChanged:()V
      32: aload_0
      33: areturn

  public org.apache.hadoop.hbase.protobuf.generated.MapReduceProtos$TableSnapshotRegionSplit$Builder addLocations(java.lang.String);
    Code:
       0: aload_1
       1: ifnonnull     12
       4: new           #73                 // class java/lang/NullPointerException
       7: dup
       8: invokespecial #74                 // Method java/lang/NullPointerException."<init>":()V
      11: athrow
      12: aload_0
      13: invokespecial #45                 // Method ensureLocationsIsMutable:()V
      16: aload_0
      17: getfield      #10                 // Field locations_:Lcom/google/protobuf/LazyStringList;
      20: aload_1
      21: invokeinterface #76,  2           // InterfaceMethod com/google/protobuf/LazyStringList.add:(Ljava/lang/Object;)Z
      26: pop
      27: aload_0
      28: invokevirtual #47                 // Method onChanged:()V
      31: aload_0
      32: areturn

  public org.apache.hadoop.hbase.protobuf.generated.MapReduceProtos$TableSnapshotRegionSplit$Builder addAllLocations(java.lang.Iterable<java.lang.String>);
    Code:
       0: aload_0
       1: invokespecial #45                 // Method ensureLocationsIsMutable:()V
       4: aload_1
       5: aload_0
       6: getfield      #10                 // Field locations_:Lcom/google/protobuf/LazyStringList;
       9: invokestatic  #77                 // Method com/google/protobuf/GeneratedMessage$Builder.addAll:(Ljava/lang/Iterable;Ljava/util/Collection;)V
      12: aload_0
      13: invokevirtual #47                 // Method onChanged:()V
      16: aload_0
      17: areturn

  public org.apache.hadoop.hbase.protobuf.generated.MapReduceProtos$TableSnapshotRegionSplit$Builder clearLocations();
    Code:
       0: aload_0
       1: getstatic     #9                  // Field com/google/protobuf/LazyStringArrayList.EMPTY:Lcom/google/protobuf/LazyStringList;
       4: putfield      #10                 // Field locations_:Lcom/google/protobuf/LazyStringList;
       7: aload_0
       8: aload_0
       9: getfield      #22                 // Field bitField0_:I
      12: bipush        -2
      14: iand
      15: putfield      #22                 // Field bitField0_:I
      18: aload_0
      19: invokevirtual #47                 // Method onChanged:()V
      22: aload_0
      23: areturn

  public org.apache.hadoop.hbase.protobuf.generated.MapReduceProtos$TableSnapshotRegionSplit$Builder addLocationsBytes(com.google.protobuf.ByteString);
    Code:
       0: aload_1
       1: ifnonnull     12
       4: new           #73                 // class java/lang/NullPointerException
       7: dup
       8: invokespecial #74                 // Method java/lang/NullPointerException."<init>":()V
      11: athrow
      12: aload_0
      13: invokespecial #45                 // Method ensureLocationsIsMutable:()V
      16: aload_0
      17: getfield      #10                 // Field locations_:Lcom/google/protobuf/LazyStringList;
      20: aload_1
      21: invokeinterface #78,  2           // InterfaceMethod com/google/protobuf/LazyStringList.add:(Lcom/google/protobuf/ByteString;)V
      26: aload_0
      27: invokevirtual #47                 // Method onChanged:()V
      30: aload_0
      31: areturn

  public boolean hasTable();
    Code:
       0: aload_0
       1: getfield      #22                 // Field bitField0_:I
       4: iconst_2
       5: iand
       6: iconst_2
       7: if_icmpne     14
      10: iconst_1
      11: goto          15
      14: iconst_0
      15: ireturn

  public org.apache.hadoop.hbase.protobuf.generated.HBaseProtos$TableSchema getTable();
    Code:
       0: aload_0
       1: getfield      #23                 // Field tableBuilder_:Lcom/google/protobuf/SingleFieldBuilder;
       4: ifnonnull     12
       7: aload_0
       8: getfield      #12                 // Field table_:Lorg/apache/hadoop/hbase/protobuf/generated/HBaseProtos$TableSchema;
      11: areturn
      12: aload_0
      13: getfield      #23                 // Field tableBuilder_:Lcom/google/protobuf/SingleFieldBuilder;
      16: invokevirtual #79                 // Method com/google/protobuf/SingleFieldBuilder.getMessage:()Lcom/google/protobuf/GeneratedMessage;
      19: checkcast     #37                 // class org/apache/hadoop/hbase/protobuf/generated/HBaseProtos$TableSchema
      22: areturn

  public org.apache.hadoop.hbase.protobuf.generated.MapReduceProtos$TableSnapshotRegionSplit$Builder setTable(org.apache.hadoop.hbase.protobuf.generated.HBaseProtos$TableSchema);
    Code:
       0: aload_0
       1: getfield      #23                 // Field tableBuilder_:Lcom/google/protobuf/SingleFieldBuilder;
       4: ifnonnull     31
       7: aload_1
       8: ifnonnull     19
      11: new           #73                 // class java/lang/NullPointerException
      14: dup
      15: invokespecial #74                 // Method java/lang/NullPointerException."<init>":()V
      18: athrow
      19: aload_0
      20: aload_1
      21: putfield      #12                 // Field table_:Lorg/apache/hadoop/hbase/protobuf/generated/HBaseProtos$TableSchema;
      24: aload_0
      25: invokevirtual #47                 // Method onChanged:()V
      28: goto          40
      31: aload_0
      32: getfield      #23                 // Field tableBuilder_:Lcom/google/protobuf/SingleFieldBuilder;
      35: aload_1
      36: invokevirtual #80                 // Method com/google/protobuf/SingleFieldBuilder.setMessage:(Lcom/google/protobuf/GeneratedMessage;)Lcom/google/protobuf/SingleFieldBuilder;
      39: pop
      40: aload_0
      41: dup
      42: getfield      #22                 // Field bitField0_:I
      45: iconst_2
      46: ior
      47: putfield      #22                 // Field bitField0_:I
      50: aload_0
      51: areturn

  public org.apache.hadoop.hbase.protobuf.generated.MapReduceProtos$TableSnapshotRegionSplit$Builder setTable(org.apache.hadoop.hbase.protobuf.generated.HBaseProtos$TableSchema$Builder);
    Code:
       0: aload_0
       1: getfield      #23                 // Field tableBuilder_:Lcom/google/protobuf/SingleFieldBuilder;
       4: ifnonnull     22
       7: aload_0
       8: aload_1
       9: invokevirtual #81                 // Method org/apache/hadoop/hbase/protobuf/generated/HBaseProtos$TableSchema$Builder.build:()Lorg/apache/hadoop/hbase/protobuf/generated/HBaseProtos$TableSchema;
      12: putfield      #12                 // Field table_:Lorg/apache/hadoop/hbase/protobuf/generated/HBaseProtos$TableSchema;
      15: aload_0
      16: invokevirtual #47                 // Method onChanged:()V
      19: goto          34
      22: aload_0
      23: getfield      #23                 // Field tableBuilder_:Lcom/google/protobuf/SingleFieldBuilder;
      26: aload_1
      27: invokevirtual #81                 // Method org/apache/hadoop/hbase/protobuf/generated/HBaseProtos$TableSchema$Builder.build:()Lorg/apache/hadoop/hbase/protobuf/generated/HBaseProtos$TableSchema;
      30: invokevirtual #80                 // Method com/google/protobuf/SingleFieldBuilder.setMessage:(Lcom/google/protobuf/GeneratedMessage;)Lcom/google/protobuf/SingleFieldBuilder;
      33: pop
      34: aload_0
      35: dup
      36: getfield      #22                 // Field bitField0_:I
      39: iconst_2
      40: ior
      41: putfield      #22                 // Field bitField0_:I
      44: aload_0
      45: areturn

  public org.apache.hadoop.hbase.protobuf.generated.MapReduceProtos$TableSnapshotRegionSplit$Builder mergeTable(org.apache.hadoop.hbase.protobuf.generated.HBaseProtos$TableSchema);
    Code:
       0: aload_0
       1: getfield      #23                 // Field tableBuilder_:Lcom/google/protobuf/SingleFieldBuilder;
       4: ifnonnull     60
       7: aload_0
       8: getfield      #22                 // Field bitField0_:I
      11: iconst_2
      12: iand
      13: iconst_2
      14: if_icmpne     48
      17: aload_0
      18: getfield      #12                 // Field table_:Lorg/apache/hadoop/hbase/protobuf/generated/HBaseProtos$TableSchema;
      21: invokestatic  #11                 // Method org/apache/hadoop/hbase/protobuf/generated/HBaseProtos$TableSchema.getDefaultInstance:()Lorg/apache/hadoop/hbase/protobuf/generated/HBaseProtos$TableSchema;
      24: if_acmpeq     48
      27: aload_0
      28: aload_0
      29: getfield      #12                 // Field table_:Lorg/apache/hadoop/hbase/protobuf/generated/HBaseProtos$TableSchema;
      32: invokestatic  #82                 // Method org/apache/hadoop/hbase/protobuf/generated/HBaseProtos$TableSchema.newBuilder:(Lorg/apache/hadoop/hbase/protobuf/generated/HBaseProtos$TableSchema;)Lorg/apache/hadoop/hbase/protobuf/generated/HBaseProtos$TableSchema$Builder;
      35: aload_1
      36: invokevirtual #83                 // Method org/apache/hadoop/hbase/protobuf/generated/HBaseProtos$TableSchema$Builder.mergeFrom:(Lorg/apache/hadoop/hbase/protobuf/generated/HBaseProtos$TableSchema;)Lorg/apache/hadoop/hbase/protobuf/generated/HBaseProtos$TableSchema$Builder;
      39: invokevirtual #84                 // Method org/apache/hadoop/hbase/protobuf/generated/HBaseProtos$TableSchema$Builder.buildPartial:()Lorg/apache/hadoop/hbase/protobuf/generated/HBaseProtos$TableSchema;
      42: putfield      #12                 // Field table_:Lorg/apache/hadoop/hbase/protobuf/generated/HBaseProtos$TableSchema;
      45: goto          53
      48: aload_0
      49: aload_1
      50: putfield      #12                 // Field table_:Lorg/apache/hadoop/hbase/protobuf/generated/HBaseProtos$TableSchema;
      53: aload_0
      54: invokevirtual #47                 // Method onChanged:()V
      57: goto          69
      60: aload_0
      61: getfield      #23                 // Field tableBuilder_:Lcom/google/protobuf/SingleFieldBuilder;
      64: aload_1
      65: invokevirtual #85                 // Method com/google/protobuf/SingleFieldBuilder.mergeFrom:(Lcom/google/protobuf/GeneratedMessage;)Lcom/google/protobuf/SingleFieldBuilder;
      68: pop
      69: aload_0
      70: dup
      71: getfield      #22                 // Field bitField0_:I
      74: iconst_2
      75: ior
      76: putfield      #22                 // Field bitField0_:I
      79: aload_0
      80: areturn

  public org.apache.hadoop.hbase.protobuf.generated.MapReduceProtos$TableSnapshotRegionSplit$Builder clearTable();
    Code:
       0: aload_0
       1: getfield      #23                 // Field tableBuilder_:Lcom/google/protobuf/SingleFieldBuilder;
       4: ifnonnull     21
       7: aload_0
       8: invokestatic  #11                 // Method org/apache/hadoop/hbase/protobuf/generated/HBaseProtos$TableSchema.getDefaultInstance:()Lorg/apache/hadoop/hbase/protobuf/generated/HBaseProtos$TableSchema;
      11: putfield      #12                 // Field table_:Lorg/apache/hadoop/hbase/protobuf/generated/HBaseProtos$TableSchema;
      14: aload_0
      15: invokevirtual #47                 // Method onChanged:()V
      18: goto          29
      21: aload_0
      22: getfield      #23                 // Field tableBuilder_:Lcom/google/protobuf/SingleFieldBuilder;
      25: invokevirtual #24                 // Method com/google/protobuf/SingleFieldBuilder.clear:()Lcom/google/protobuf/SingleFieldBuilder;
      28: pop
      29: aload_0
      30: aload_0
      31: getfield      #22                 // Field bitField0_:I
      34: bipush        -3
      36: iand
      37: putfield      #22                 // Field bitField0_:I
      40: aload_0
      41: areturn

  public org.apache.hadoop.hbase.protobuf.generated.HBaseProtos$TableSchema$Builder getTableBuilder();
    Code:
       0: aload_0
       1: dup
       2: getfield      #22                 // Field bitField0_:I
       5: iconst_2
       6: ior
       7: putfield      #22                 // Field bitField0_:I
      10: aload_0
      11: invokevirtual #47                 // Method onChanged:()V
      14: aload_0
      15: invokespecial #18                 // Method getTableFieldBuilder:()Lcom/google/protobuf/SingleFieldBuilder;
      18: invokevirtual #86                 // Method com/google/protobuf/SingleFieldBuilder.getBuilder:()Lcom/google/protobuf/GeneratedMessage$Builder;
      21: checkcast     #87                 // class org/apache/hadoop/hbase/protobuf/generated/HBaseProtos$TableSchema$Builder
      24: areturn

  public org.apache.hadoop.hbase.protobuf.generated.HBaseProtos$TableSchemaOrBuilder getTableOrBuilder();
    Code:
       0: aload_0
       1: getfield      #23                 // Field tableBuilder_:Lcom/google/protobuf/SingleFieldBuilder;
       4: ifnull        18
       7: aload_0
       8: getfield      #23                 // Field tableBuilder_:Lcom/google/protobuf/SingleFieldBuilder;
      11: invokevirtual #88                 // Method com/google/protobuf/SingleFieldBuilder.getMessageOrBuilder:()Lcom/google/protobuf/MessageOrBuilder;
      14: checkcast     #89                 // class org/apache/hadoop/hbase/protobuf/generated/HBaseProtos$TableSchemaOrBuilder
      17: areturn
      18: aload_0
      19: getfield      #12                 // Field table_:Lorg/apache/hadoop/hbase/protobuf/generated/HBaseProtos$TableSchema;
      22: areturn

  public boolean hasRegion();
    Code:
       0: aload_0
       1: getfield      #22                 // Field bitField0_:I
       4: iconst_4
       5: iand
       6: iconst_4
       7: if_icmpne     14
      10: iconst_1
      11: goto          15
      14: iconst_0
      15: ireturn

  public org.apache.hadoop.hbase.protobuf.generated.HBaseProtos$RegionInfo getRegion();
    Code:
       0: aload_0
       1: getfield      #25                 // Field regionBuilder_:Lcom/google/protobuf/SingleFieldBuilder;
       4: ifnonnull     12
       7: aload_0
       8: getfield      #14                 // Field region_:Lorg/apache/hadoop/hbase/protobuf/generated/HBaseProtos$RegionInfo;
      11: areturn
      12: aload_0
      13: getfield      #25                 // Field regionBuilder_:Lcom/google/protobuf/SingleFieldBuilder;
      16: invokevirtual #79                 // Method com/google/protobuf/SingleFieldBuilder.getMessage:()Lcom/google/protobuf/GeneratedMessage;
      19: checkcast     #39                 // class org/apache/hadoop/hbase/protobuf/generated/HBaseProtos$RegionInfo
      22: areturn

  public org.apache.hadoop.hbase.protobuf.generated.MapReduceProtos$TableSnapshotRegionSplit$Builder setRegion(org.apache.hadoop.hbase.protobuf.generated.HBaseProtos$RegionInfo);
    Code:
       0: aload_0
       1: getfield      #25                 // Field regionBuilder_:Lcom/google/protobuf/SingleFieldBuilder;
       4: ifnonnull     31
       7: aload_1
       8: ifnonnull     19
      11: new           #73                 // class java/lang/NullPointerException
      14: dup
      15: invokespecial #74                 // Method java/lang/NullPointerException."<init>":()V
      18: athrow
      19: aload_0
      20: aload_1
      21: putfield      #14                 // Field region_:Lorg/apache/hadoop/hbase/protobuf/generated/HBaseProtos$RegionInfo;
      24: aload_0
      25: invokevirtual #47                 // Method onChanged:()V
      28: goto          40
      31: aload_0
      32: getfield      #25                 // Field regionBuilder_:Lcom/google/protobuf/SingleFieldBuilder;
      35: aload_1
      36: invokevirtual #80                 // Method com/google/protobuf/SingleFieldBuilder.setMessage:(Lcom/google/protobuf/GeneratedMessage;)Lcom/google/protobuf/SingleFieldBuilder;
      39: pop
      40: aload_0
      41: dup
      42: getfield      #22                 // Field bitField0_:I
      45: iconst_4
      46: ior
      47: putfield      #22                 // Field bitField0_:I
      50: aload_0
      51: areturn

  public org.apache.hadoop.hbase.protobuf.generated.MapReduceProtos$TableSnapshotRegionSplit$Builder setRegion(org.apache.hadoop.hbase.protobuf.generated.HBaseProtos$RegionInfo$Builder);
    Code:
       0: aload_0
       1: getfield      #25                 // Field regionBuilder_:Lcom/google/protobuf/SingleFieldBuilder;
       4: ifnonnull     22
       7: aload_0
       8: aload_1
       9: invokevirtual #94                 // Method org/apache/hadoop/hbase/protobuf/generated/HBaseProtos$RegionInfo$Builder.build:()Lorg/apache/hadoop/hbase/protobuf/generated/HBaseProtos$RegionInfo;
      12: putfield      #14                 // Field region_:Lorg/apache/hadoop/hbase/protobuf/generated/HBaseProtos$RegionInfo;
      15: aload_0
      16: invokevirtual #47                 // Method onChanged:()V
      19: goto          34
      22: aload_0
      23: getfield      #25                 // Field regionBuilder_:Lcom/google/protobuf/SingleFieldBuilder;
      26: aload_1
      27: invokevirtual #94                 // Method org/apache/hadoop/hbase/protobuf/generated/HBaseProtos$RegionInfo$Builder.build:()Lorg/apache/hadoop/hbase/protobuf/generated/HBaseProtos$RegionInfo;
      30: invokevirtual #80                 // Method com/google/protobuf/SingleFieldBuilder.setMessage:(Lcom/google/protobuf/GeneratedMessage;)Lcom/google/protobuf/SingleFieldBuilder;
      33: pop
      34: aload_0
      35: dup
      36: getfield      #22                 // Field bitField0_:I
      39: iconst_4
      40: ior
      41: putfield      #22                 // Field bitField0_:I
      44: aload_0
      45: areturn

  public org.apache.hadoop.hbase.protobuf.generated.MapReduceProtos$TableSnapshotRegionSplit$Builder mergeRegion(org.apache.hadoop.hbase.protobuf.generated.HBaseProtos$RegionInfo);
    Code:
       0: aload_0
       1: getfield      #25                 // Field regionBuilder_:Lcom/google/protobuf/SingleFieldBuilder;
       4: ifnonnull     60
       7: aload_0
       8: getfield      #22                 // Field bitField0_:I
      11: iconst_4
      12: iand
      13: iconst_4
      14: if_icmpne     48
      17: aload_0
      18: getfield      #14                 // Field region_:Lorg/apache/hadoop/hbase/protobuf/generated/HBaseProtos$RegionInfo;
      21: invokestatic  #13                 // Method org/apache/hadoop/hbase/protobuf/generated/HBaseProtos$RegionInfo.getDefaultInstance:()Lorg/apache/hadoop/hbase/protobuf/generated/HBaseProtos$RegionInfo;
      24: if_acmpeq     48
      27: aload_0
      28: aload_0
      29: getfield      #14                 // Field region_:Lorg/apache/hadoop/hbase/protobuf/generated/HBaseProtos$RegionInfo;
      32: invokestatic  #95                 // Method org/apache/hadoop/hbase/protobuf/generated/HBaseProtos$RegionInfo.newBuilder:(Lorg/apache/hadoop/hbase/protobuf/generated/HBaseProtos$RegionInfo;)Lorg/apache/hadoop/hbase/protobuf/generated/HBaseProtos$RegionInfo$Builder;
      35: aload_1
      36: invokevirtual #96                 // Method org/apache/hadoop/hbase/protobuf/generated/HBaseProtos$RegionInfo$Builder.mergeFrom:(Lorg/apache/hadoop/hbase/protobuf/generated/HBaseProtos$RegionInfo;)Lorg/apache/hadoop/hbase/protobuf/generated/HBaseProtos$RegionInfo$Builder;
      39: invokevirtual #97                 // Method org/apache/hadoop/hbase/protobuf/generated/HBaseProtos$RegionInfo$Builder.buildPartial:()Lorg/apache/hadoop/hbase/protobuf/generated/HBaseProtos$RegionInfo;
      42: putfield      #14                 // Field region_:Lorg/apache/hadoop/hbase/protobuf/generated/HBaseProtos$RegionInfo;
      45: goto          53
      48: aload_0
      49: aload_1
      50: putfield      #14                 // Field region_:Lorg/apache/hadoop/hbase/protobuf/generated/HBaseProtos$RegionInfo;
      53: aload_0
      54: invokevirtual #47                 // Method onChanged:()V
      57: goto          69
      60: aload_0
      61: getfield      #25                 // Field regionBuilder_:Lcom/google/protobuf/SingleFieldBuilder;
      64: aload_1
      65: invokevirtual #85                 // Method com/google/protobuf/SingleFieldBuilder.mergeFrom:(Lcom/google/protobuf/GeneratedMessage;)Lcom/google/protobuf/SingleFieldBuilder;
      68: pop
      69: aload_0
      70: dup
      71: getfield      #22                 // Field bitField0_:I
      74: iconst_4
      75: ior
      76: putfield      #22                 // Field bitField0_:I
      79: aload_0
      80: areturn

  public org.apache.hadoop.hbase.protobuf.generated.MapReduceProtos$TableSnapshotRegionSplit$Builder clearRegion();
    Code:
       0: aload_0
       1: getfield      #25                 // Field regionBuilder_:Lcom/google/protobuf/SingleFieldBuilder;
       4: ifnonnull     21
       7: aload_0
       8: invokestatic  #13                 // Method org/apache/hadoop/hbase/protobuf/generated/HBaseProtos$RegionInfo.getDefaultInstance:()Lorg/apache/hadoop/hbase/protobuf/generated/HBaseProtos$RegionInfo;
      11: putfield      #14                 // Field region_:Lorg/apache/hadoop/hbase/protobuf/generated/HBaseProtos$RegionInfo;
      14: aload_0
      15: invokevirtual #47                 // Method onChanged:()V
      18: goto          29
      21: aload_0
      22: getfield      #25                 // Field regionBuilder_:Lcom/google/protobuf/SingleFieldBuilder;
      25: invokevirtual #24                 // Method com/google/protobuf/SingleFieldBuilder.clear:()Lcom/google/protobuf/SingleFieldBuilder;
      28: pop
      29: aload_0
      30: aload_0
      31: getfield      #22                 // Field bitField0_:I
      34: bipush        -5
      36: iand
      37: putfield      #22                 // Field bitField0_:I
      40: aload_0
      41: areturn

  public org.apache.hadoop.hbase.protobuf.generated.HBaseProtos$RegionInfo$Builder getRegionBuilder();
    Code:
       0: aload_0
       1: dup
       2: getfield      #22                 // Field bitField0_:I
       5: iconst_4
       6: ior
       7: putfield      #22                 // Field bitField0_:I
      10: aload_0
      11: invokevirtual #47                 // Method onChanged:()V
      14: aload_0
      15: invokespecial #19                 // Method getRegionFieldBuilder:()Lcom/google/protobuf/SingleFieldBuilder;
      18: invokevirtual #86                 // Method com/google/protobuf/SingleFieldBuilder.getBuilder:()Lcom/google/protobuf/GeneratedMessage$Builder;
      21: checkcast     #98                 // class org/apache/hadoop/hbase/protobuf/generated/HBaseProtos$RegionInfo$Builder
      24: areturn

  public org.apache.hadoop.hbase.protobuf.generated.HBaseProtos$RegionInfoOrBuilder getRegionOrBuilder();
    Code:
       0: aload_0
       1: getfield      #25                 // Field regionBuilder_:Lcom/google/protobuf/SingleFieldBuilder;
       4: ifnull        18
       7: aload_0
       8: getfield      #25                 // Field regionBuilder_:Lcom/google/protobuf/SingleFieldBuilder;
      11: invokevirtual #88                 // Method com/google/protobuf/SingleFieldBuilder.getMessageOrBuilder:()Lcom/google/protobuf/MessageOrBuilder;
      14: checkcast     #99                 // class org/apache/hadoop/hbase/protobuf/generated/HBaseProtos$RegionInfoOrBuilder
      17: areturn
      18: aload_0
      19: getfield      #14                 // Field region_:Lorg/apache/hadoop/hbase/protobuf/generated/HBaseProtos$RegionInfo;
      22: areturn

  public com.google.protobuf.GeneratedMessage$Builder clear();
    Code:
       0: aload_0
       1: invokevirtual #100                // Method clear:()Lorg/apache/hadoop/hbase/protobuf/generated/MapReduceProtos$TableSnapshotRegionSplit$Builder;
       4: areturn

  public com.google.protobuf.GeneratedMessage$Builder clone();
    Code:
       0: aload_0
       1: invokevirtual #101                // Method clone:()Lorg/apache/hadoop/hbase/protobuf/generated/MapReduceProtos$TableSnapshotRegionSplit$Builder;
       4: areturn

  public com.google.protobuf.AbstractMessage$Builder mergeFrom(com.google.protobuf.CodedInputStream, com.google.protobuf.ExtensionRegistryLite) throws java.io.IOException;
    Code:
       0: aload_0
       1: aload_1
       2: aload_2
       3: invokevirtual #102                // Method mergeFrom:(Lcom/google/protobuf/CodedInputStream;Lcom/google/protobuf/ExtensionRegistryLite;)Lorg/apache/hadoop/hbase/protobuf/generated/MapReduceProtos$TableSnapshotRegionSplit$Builder;
       6: areturn

  public com.google.protobuf.AbstractMessage$Builder mergeFrom(com.google.protobuf.Message);
    Code:
       0: aload_0
       1: aload_1
       2: invokevirtual #103                // Method mergeFrom:(Lcom/google/protobuf/Message;)Lorg/apache/hadoop/hbase/protobuf/generated/MapReduceProtos$TableSnapshotRegionSplit$Builder;
       5: areturn

  public com.google.protobuf.AbstractMessage$Builder clear();
    Code:
       0: aload_0
       1: invokevirtual #100                // Method clear:()Lorg/apache/hadoop/hbase/protobuf/generated/MapReduceProtos$TableSnapshotRegionSplit$Builder;
       4: areturn

  public com.google.protobuf.AbstractMessage$Builder clone();
    Code:
       0: aload_0
       1: invokevirtual #101                // Method clone:()Lorg/apache/hadoop/hbase/protobuf/generated/MapReduceProtos$TableSnapshotRegionSplit$Builder;
       4: areturn

  public com.google.protobuf.Message$Builder mergeFrom(com.google.protobuf.CodedInputStream, com.google.protobuf.ExtensionRegistryLite) throws java.io.IOException;
    Code:
       0: aload_0
       1: aload_1
       2: aload_2
       3: invokevirtual #102                // Method mergeFrom:(Lcom/google/protobuf/CodedInputStream;Lcom/google/protobuf/ExtensionRegistryLite;)Lorg/apache/hadoop/hbase/protobuf/generated/MapReduceProtos$TableSnapshotRegionSplit$Builder;
       6: areturn

  public com.google.protobuf.Message$Builder clone();
    Code:
       0: aload_0
       1: invokevirtual #101                // Method clone:()Lorg/apache/hadoop/hbase/protobuf/generated/MapReduceProtos$TableSnapshotRegionSplit$Builder;
       4: areturn

  public com.google.protobuf.Message buildPartial();
    Code:
       0: aload_0
       1: invokevirtual #26                 // Method buildPartial:()Lorg/apache/hadoop/hbase/protobuf/generated/MapReduceProtos$TableSnapshotRegionSplit;
       4: areturn

  public com.google.protobuf.Message build();
    Code:
       0: aload_0
       1: invokevirtual #104                // Method build:()Lorg/apache/hadoop/hbase/protobuf/generated/MapReduceProtos$TableSnapshotRegionSplit;
       4: areturn

  public com.google.protobuf.Message$Builder mergeFrom(com.google.protobuf.Message);
    Code:
       0: aload_0
       1: aload_1
       2: invokevirtual #103                // Method mergeFrom:(Lcom/google/protobuf/Message;)Lorg/apache/hadoop/hbase/protobuf/generated/MapReduceProtos$TableSnapshotRegionSplit$Builder;
       5: areturn

  public com.google.protobuf.Message$Builder clear();
    Code:
       0: aload_0
       1: invokevirtual #100                // Method clear:()Lorg/apache/hadoop/hbase/protobuf/generated/MapReduceProtos$TableSnapshotRegionSplit$Builder;
       4: areturn

  public com.google.protobuf.MessageLite$Builder mergeFrom(com.google.protobuf.CodedInputStream, com.google.protobuf.ExtensionRegistryLite) throws java.io.IOException;
    Code:
       0: aload_0
       1: aload_1
       2: aload_2
       3: invokevirtual #102                // Method mergeFrom:(Lcom/google/protobuf/CodedInputStream;Lcom/google/protobuf/ExtensionRegistryLite;)Lorg/apache/hadoop/hbase/protobuf/generated/MapReduceProtos$TableSnapshotRegionSplit$Builder;
       6: areturn

  public com.google.protobuf.MessageLite$Builder clone();
    Code:
       0: aload_0
       1: invokevirtual #101                // Method clone:()Lorg/apache/hadoop/hbase/protobuf/generated/MapReduceProtos$TableSnapshotRegionSplit$Builder;
       4: areturn

  public com.google.protobuf.MessageLite buildPartial();
    Code:
       0: aload_0
       1: invokevirtual #26                 // Method buildPartial:()Lorg/apache/hadoop/hbase/protobuf/generated/MapReduceProtos$TableSnapshotRegionSplit;
       4: areturn

  public com.google.protobuf.MessageLite build();
    Code:
       0: aload_0
       1: invokevirtual #104                // Method build:()Lorg/apache/hadoop/hbase/protobuf/generated/MapReduceProtos$TableSnapshotRegionSplit;
       4: areturn

  public com.google.protobuf.MessageLite$Builder clear();
    Code:
       0: aload_0
       1: invokevirtual #100                // Method clear:()Lorg/apache/hadoop/hbase/protobuf/generated/MapReduceProtos$TableSnapshotRegionSplit$Builder;
       4: areturn

  public com.google.protobuf.MessageLite getDefaultInstanceForType();
    Code:
       0: aload_0
       1: invokevirtual #105                // Method getDefaultInstanceForType:()Lorg/apache/hadoop/hbase/protobuf/generated/MapReduceProtos$TableSnapshotRegionSplit;
       4: areturn

  public com.google.protobuf.Message getDefaultInstanceForType();
    Code:
       0: aload_0
       1: invokevirtual #105                // Method getDefaultInstanceForType:()Lorg/apache/hadoop/hbase/protobuf/generated/MapReduceProtos$TableSnapshotRegionSplit;
       4: areturn

  public com.google.protobuf.AbstractMessageLite$Builder mergeFrom(com.google.protobuf.CodedInputStream, com.google.protobuf.ExtensionRegistryLite) throws java.io.IOException;
    Code:
       0: aload_0
       1: aload_1
       2: aload_2
       3: invokevirtual #102                // Method mergeFrom:(Lcom/google/protobuf/CodedInputStream;Lcom/google/protobuf/ExtensionRegistryLite;)Lorg/apache/hadoop/hbase/protobuf/generated/MapReduceProtos$TableSnapshotRegionSplit$Builder;
       6: areturn

  public com.google.protobuf.AbstractMessageLite$Builder clone();
    Code:
       0: aload_0
       1: invokevirtual #101                // Method clone:()Lorg/apache/hadoop/hbase/protobuf/generated/MapReduceProtos$TableSnapshotRegionSplit$Builder;
       4: areturn

  public java.lang.Object clone() throws java.lang.CloneNotSupportedException;
    Code:
       0: aload_0
       1: invokevirtual #101                // Method clone:()Lorg/apache/hadoop/hbase/protobuf/generated/MapReduceProtos$TableSnapshotRegionSplit$Builder;
       4: areturn

  static org.apache.hadoop.hbase.protobuf.generated.MapReduceProtos$TableSnapshotRegionSplit$Builder access$1200();
    Code:
       0: invokestatic  #2                  // Method create:()Lorg/apache/hadoop/hbase/protobuf/generated/MapReduceProtos$TableSnapshotRegionSplit$Builder;
       3: areturn

  org.apache.hadoop.hbase.protobuf.generated.MapReduceProtos$TableSnapshotRegionSplit$Builder(com.google.protobuf.GeneratedMessage$BuilderParent, org.apache.hadoop.hbase.protobuf.generated.MapReduceProtos$1);
    Code:
       0: aload_0
       1: aload_1
       2: invokespecial #1                  // Method "<init>":(Lcom/google/protobuf/GeneratedMessage$BuilderParent;)V
       5: return
}
