Compiled from "MasterStatusTmpl.java"
public class org.apache.hadoop.hbase.tmpl.master.MasterStatusTmpl extends org.jamon.AbstractTemplateProxy {
  protected org.apache.hadoop.hbase.master.assignment.AssignmentManager assignmentManager;

  protected boolean catalogJanitorEnabled;

  protected java.util.Set<org.apache.hadoop.hbase.ServerName> deadServers;

  protected java.lang.String filter;

  protected java.lang.String format;

  protected java.util.Map<java.lang.String, java.lang.Integer> frags;

  protected org.apache.hadoop.hbase.ServerName metaLocation;

  protected org.apache.hadoop.hbase.master.ServerManager serverManager;

  protected java.util.List<org.apache.hadoop.hbase.ServerName> servers;

  public org.apache.hadoop.hbase.tmpl.master.MasterStatusTmpl(org.jamon.TemplateManager);
    Code:
       0: aload_0
       1: aload_1
       2: invokespecial #1                  // Method org/jamon/AbstractTemplateProxy."<init>":(Lorg/jamon/TemplateManager;)V
       5: return

  protected org.apache.hadoop.hbase.tmpl.master.MasterStatusTmpl(java.lang.String);
    Code:
       0: aload_0
       1: aload_1
       2: invokespecial #2                  // Method org/jamon/AbstractTemplateProxy."<init>":(Ljava/lang/String;)V
       5: return

  public org.apache.hadoop.hbase.tmpl.master.MasterStatusTmpl();
    Code:
       0: aload_0
       1: ldc           #3                  // String /org/apache/hadoop/hbase/tmpl/master/MasterStatusTmpl
       3: invokespecial #2                  // Method org/jamon/AbstractTemplateProxy."<init>":(Ljava/lang/String;)V
       6: return

  protected org.jamon.AbstractTemplateProxy$ImplData makeImplData();
    Code:
       0: new           #4                  // class org/apache/hadoop/hbase/tmpl/master/MasterStatusTmpl$ImplData
       3: dup
       4: invokespecial #5                  // Method org/apache/hadoop/hbase/tmpl/master/MasterStatusTmpl$ImplData."<init>":()V
       7: areturn

  public org.apache.hadoop.hbase.tmpl.master.MasterStatusTmpl$ImplData getImplData();
    Code:
       0: aload_0
       1: invokespecial #6                  // Method org/jamon/AbstractTemplateProxy.getImplData:()Lorg/jamon/AbstractTemplateProxy$ImplData;
       4: checkcast     #4                  // class org/apache/hadoop/hbase/tmpl/master/MasterStatusTmpl$ImplData
       7: areturn

  public final org.apache.hadoop.hbase.tmpl.master.MasterStatusTmpl setAssignmentManager(org.apache.hadoop.hbase.master.assignment.AssignmentManager);
    Code:
       0: aload_0
       1: invokevirtual #7                  // Method getImplData:()Lorg/apache/hadoop/hbase/tmpl/master/MasterStatusTmpl$ImplData;
       4: aload_1
       5: invokevirtual #8                  // Method org/apache/hadoop/hbase/tmpl/master/MasterStatusTmpl$ImplData.setAssignmentManager:(Lorg/apache/hadoop/hbase/master/assignment/AssignmentManager;)V
       8: aload_0
       9: areturn

  public final org.apache.hadoop.hbase.tmpl.master.MasterStatusTmpl setCatalogJanitorEnabled(boolean);
    Code:
       0: aload_0
       1: invokevirtual #7                  // Method getImplData:()Lorg/apache/hadoop/hbase/tmpl/master/MasterStatusTmpl$ImplData;
       4: iload_1
       5: invokevirtual #9                  // Method org/apache/hadoop/hbase/tmpl/master/MasterStatusTmpl$ImplData.setCatalogJanitorEnabled:(Z)V
       8: aload_0
       9: areturn

  public final org.apache.hadoop.hbase.tmpl.master.MasterStatusTmpl setDeadServers(java.util.Set<org.apache.hadoop.hbase.ServerName>);
    Code:
       0: aload_0
       1: invokevirtual #7                  // Method getImplData:()Lorg/apache/hadoop/hbase/tmpl/master/MasterStatusTmpl$ImplData;
       4: aload_1
       5: invokevirtual #10                 // Method org/apache/hadoop/hbase/tmpl/master/MasterStatusTmpl$ImplData.setDeadServers:(Ljava/util/Set;)V
       8: aload_0
       9: areturn

  public final org.apache.hadoop.hbase.tmpl.master.MasterStatusTmpl setFilter(java.lang.String);
    Code:
       0: aload_0
       1: invokevirtual #7                  // Method getImplData:()Lorg/apache/hadoop/hbase/tmpl/master/MasterStatusTmpl$ImplData;
       4: aload_1
       5: invokevirtual #11                 // Method org/apache/hadoop/hbase/tmpl/master/MasterStatusTmpl$ImplData.setFilter:(Ljava/lang/String;)V
       8: aload_0
       9: areturn

  public final org.apache.hadoop.hbase.tmpl.master.MasterStatusTmpl setFormat(java.lang.String);
    Code:
       0: aload_0
       1: invokevirtual #7                  // Method getImplData:()Lorg/apache/hadoop/hbase/tmpl/master/MasterStatusTmpl$ImplData;
       4: aload_1
       5: invokevirtual #12                 // Method org/apache/hadoop/hbase/tmpl/master/MasterStatusTmpl$ImplData.setFormat:(Ljava/lang/String;)V
       8: aload_0
       9: areturn

  public final org.apache.hadoop.hbase.tmpl.master.MasterStatusTmpl setFrags(java.util.Map<java.lang.String, java.lang.Integer>);
    Code:
       0: aload_0
       1: invokevirtual #7                  // Method getImplData:()Lorg/apache/hadoop/hbase/tmpl/master/MasterStatusTmpl$ImplData;
       4: aload_1
       5: invokevirtual #13                 // Method org/apache/hadoop/hbase/tmpl/master/MasterStatusTmpl$ImplData.setFrags:(Ljava/util/Map;)V
       8: aload_0
       9: areturn

  public final org.apache.hadoop.hbase.tmpl.master.MasterStatusTmpl setMetaLocation(org.apache.hadoop.hbase.ServerName);
    Code:
       0: aload_0
       1: invokevirtual #7                  // Method getImplData:()Lorg/apache/hadoop/hbase/tmpl/master/MasterStatusTmpl$ImplData;
       4: aload_1
       5: invokevirtual #14                 // Method org/apache/hadoop/hbase/tmpl/master/MasterStatusTmpl$ImplData.setMetaLocation:(Lorg/apache/hadoop/hbase/ServerName;)V
       8: aload_0
       9: areturn

  public final org.apache.hadoop.hbase.tmpl.master.MasterStatusTmpl setServerManager(org.apache.hadoop.hbase.master.ServerManager);
    Code:
       0: aload_0
       1: invokevirtual #7                  // Method getImplData:()Lorg/apache/hadoop/hbase/tmpl/master/MasterStatusTmpl$ImplData;
       4: aload_1
       5: invokevirtual #15                 // Method org/apache/hadoop/hbase/tmpl/master/MasterStatusTmpl$ImplData.setServerManager:(Lorg/apache/hadoop/hbase/master/ServerManager;)V
       8: aload_0
       9: areturn

  public final org.apache.hadoop.hbase.tmpl.master.MasterStatusTmpl setServers(java.util.List<org.apache.hadoop.hbase.ServerName>);
    Code:
       0: aload_0
       1: invokevirtual #7                  // Method getImplData:()Lorg/apache/hadoop/hbase/tmpl/master/MasterStatusTmpl$ImplData;
       4: aload_1
       5: invokevirtual #16                 // Method org/apache/hadoop/hbase/tmpl/master/MasterStatusTmpl$ImplData.setServers:(Ljava/util/List;)V
       8: aload_0
       9: areturn

  public org.jamon.AbstractTemplateImpl constructImpl(java.lang.Class<? extends org.jamon.AbstractTemplateImpl>);
    Code:
       0: aload_1
       1: iconst_2
       2: anewarray     #17                 // class java/lang/Class
       5: dup
       6: iconst_0
       7: ldc           #18                 // class org/jamon/TemplateManager
       9: aastore
      10: dup
      11: iconst_1
      12: ldc           #4                  // class org/apache/hadoop/hbase/tmpl/master/MasterStatusTmpl$ImplData
      14: aastore
      15: invokevirtual #19                 // Method java/lang/Class.getConstructor:([Ljava/lang/Class;)Ljava/lang/reflect/Constructor;
      18: iconst_2
      19: anewarray     #20                 // class java/lang/Object
      22: dup
      23: iconst_0
      24: aload_0
      25: invokevirtual #21                 // Method getTemplateManager:()Lorg/jamon/TemplateManager;
      28: aastore
      29: dup
      30: iconst_1
      31: aload_0
      32: invokevirtual #7                  // Method getImplData:()Lorg/apache/hadoop/hbase/tmpl/master/MasterStatusTmpl$ImplData;
      35: aastore
      36: invokevirtual #22                 // Method java/lang/reflect/Constructor.newInstance:([Ljava/lang/Object;)Ljava/lang/Object;
      39: checkcast     #23                 // class org/jamon/AbstractTemplateImpl
      42: areturn
      43: astore_2
      44: aload_2
      45: athrow
      46: astore_2
      47: new           #24                 // class java/lang/RuntimeException
      50: dup
      51: aload_2
      52: invokespecial #26                 // Method java/lang/RuntimeException."<init>":(Ljava/lang/Throwable;)V
      55: athrow
    Exception table:
       from    to  target type
           0    42    43   Class java/lang/RuntimeException
           0    42    46   Class java/lang/Exception

  protected org.jamon.AbstractTemplateImpl constructImpl();
    Code:
       0: new           #27                 // class org/apache/hadoop/hbase/tmpl/master/MasterStatusTmplImpl
       3: dup
       4: aload_0
       5: invokevirtual #21                 // Method getTemplateManager:()Lorg/jamon/TemplateManager;
       8: aload_0
       9: invokevirtual #7                  // Method getImplData:()Lorg/apache/hadoop/hbase/tmpl/master/MasterStatusTmpl$ImplData;
      12: invokespecial #28                 // Method org/apache/hadoop/hbase/tmpl/master/MasterStatusTmplImpl."<init>":(Lorg/jamon/TemplateManager;Lorg/apache/hadoop/hbase/tmpl/master/MasterStatusTmpl$ImplData;)V
      15: areturn

  public org.jamon.Renderer makeRenderer(org.apache.hadoop.hbase.master.HMaster);
    Code:
       0: new           #29                 // class org/apache/hadoop/hbase/tmpl/master/MasterStatusTmpl$1
       3: dup
       4: aload_0
       5: aload_1
       6: invokespecial #30                 // Method org/apache/hadoop/hbase/tmpl/master/MasterStatusTmpl$1."<init>":(Lorg/apache/hadoop/hbase/tmpl/master/MasterStatusTmpl;Lorg/apache/hadoop/hbase/master/HMaster;)V
       9: areturn

  public void render(java.io.Writer, org.apache.hadoop.hbase.master.HMaster) throws java.io.IOException;
    Code:
       0: aload_0
       1: aload_1
       2: aload_2
       3: invokevirtual #31                 // Method renderNoFlush:(Ljava/io/Writer;Lorg/apache/hadoop/hbase/master/HMaster;)V
       6: aload_1
       7: invokevirtual #32                 // Method java/io/Writer.flush:()V
      10: return

  public void renderNoFlush(java.io.Writer, org.apache.hadoop.hbase.master.HMaster) throws java.io.IOException;
    Code:
       0: aload_0
       1: invokevirtual #7                  // Method getImplData:()Lorg/apache/hadoop/hbase/tmpl/master/MasterStatusTmpl$ImplData;
       4: astore_3
       5: aload_3
       6: aload_2
       7: invokevirtual #33                 // Method org/apache/hadoop/hbase/tmpl/master/MasterStatusTmpl$ImplData.setMaster:(Lorg/apache/hadoop/hbase/master/HMaster;)V
      10: aload_0
      11: invokevirtual #21                 // Method getTemplateManager:()Lorg/jamon/TemplateManager;
      14: aload_0
      15: invokeinterface #34,  2           // InterfaceMethod org/jamon/TemplateManager.constructImpl:(Lorg/jamon/AbstractTemplateProxy;)Lorg/jamon/AbstractTemplateProxy$Intf;
      20: checkcast     #35                 // class org/apache/hadoop/hbase/tmpl/master/MasterStatusTmpl$Intf
      23: astore        4
      25: aload         4
      27: aload_1
      28: invokeinterface #36,  2           // InterfaceMethod org/apache/hadoop/hbase/tmpl/master/MasterStatusTmpl$Intf.renderNoFlush:(Ljava/io/Writer;)V
      33: aload_0
      34: invokevirtual #37                 // Method reset:()V
      37: return

  public org.jamon.AbstractTemplateProxy$ImplData getImplData();
    Code:
       0: aload_0
       1: invokevirtual #7                  // Method getImplData:()Lorg/apache/hadoop/hbase/tmpl/master/MasterStatusTmpl$ImplData;
       4: areturn
}
