Compiled from "MasterCoprocessorHost.java"
public class org.apache.hadoop.hbase.master.MasterCoprocessorHost extends org.apache.hadoop.hbase.coprocessor.CoprocessorHost<org.apache.hadoop.hbase.coprocessor.MasterCoprocessor, org.apache.hadoop.hbase.coprocessor.MasterCoprocessorEnvironment> {
  public org.apache.hadoop.hbase.master.MasterCoprocessorHost(org.apache.hadoop.hbase.master.MasterServices, org.apache.hadoop.conf.Configuration);
    Code:
       0: aload_0
       1: aload_1
       2: invokespecial #2                  // Method org/apache/hadoop/hbase/coprocessor/CoprocessorHost."<init>":(Lorg/apache/hadoop/hbase/Abortable;)V
       5: aload_0
       6: invokedynamic #3,  0              // InvokeDynamic #0:apply:()Lorg/apache/hadoop/hbase/coprocessor/CoprocessorHost$ObserverGetter;
      11: putfield      #1                  // Field masterObserverGetter:Lorg/apache/hadoop/hbase/coprocessor/CoprocessorHost$ObserverGetter;
      14: aload_0
      15: aload_2
      16: putfield      #4                  // Field conf:Lorg/apache/hadoop/conf/Configuration;
      19: aload_0
      20: aload_1
      21: putfield      #5                  // Field masterServices:Lorg/apache/hadoop/hbase/master/MasterServices;
      24: aload_2
      25: ldc           #7                  // String hbase.coprocessor.enabled
      27: iconst_1
      28: invokevirtual #8                  // Method org/apache/hadoop/conf/Configuration.getBoolean:(Ljava/lang/String;Z)Z
      31: istore_3
      32: getstatic     #9                  // Field LOG:Lorg/slf4j/Logger;
      35: ldc           #10                 // String System coprocessor loading is {}
      37: iload_3
      38: ifeq          46
      41: ldc           #11                 // String enabled
      43: goto          48
      46: ldc           #12                 // String disabled
      48: invokeinterface #13,  3           // InterfaceMethod org/slf4j/Logger.trace:(Ljava/lang/String;Ljava/lang/Object;)V
      53: aload_0
      54: aload_2
      55: ldc           #14                 // String hbase.coprocessor.master.classes
      57: invokevirtual #15                 // Method loadSystemCoprocessors:(Lorg/apache/hadoop/conf/Configuration;Ljava/lang/String;)V
      60: return

  public org.apache.hadoop.hbase.master.MasterCoprocessorHost$MasterEnvironment createEnvironment(org.apache.hadoop.hbase.coprocessor.MasterCoprocessor, int, int, org.apache.hadoop.conf.Configuration);
    Code:
       0: aload_1
       1: invokeinterface #16,  1           // InterfaceMethod org/apache/hadoop/hbase/coprocessor/MasterCoprocessor.getServices:()Ljava/lang/Iterable;
       6: invokeinterface #17,  1           // InterfaceMethod java/lang/Iterable.iterator:()Ljava/util/Iterator;
      11: astore        5
      13: aload         5
      15: invokeinterface #18,  1           // InterfaceMethod java/util/Iterator.hasNext:()Z
      20: ifeq          50
      23: aload         5
      25: invokeinterface #19,  1           // InterfaceMethod java/util/Iterator.next:()Ljava/lang/Object;
      30: checkcast     #20                 // class com/google/protobuf/Service
      33: astore        6
      35: aload_0
      36: getfield      #5                  // Field masterServices:Lorg/apache/hadoop/hbase/master/MasterServices;
      39: aload         6
      41: invokeinterface #21,  2           // InterfaceMethod org/apache/hadoop/hbase/master/MasterServices.registerService:(Lcom/google/protobuf/Service;)Z
      46: pop
      47: goto          13
      50: aload_1
      51: invokevirtual #22                 // Method java/lang/Object.getClass:()Ljava/lang/Class;
      54: ldc           #23                 // class org/apache/hadoop/hbase/coprocessor/CoreCoprocessor
      56: invokevirtual #24                 // Method java/lang/Class.isAnnotationPresent:(Ljava/lang/Class;)Z
      59: ifeq          81
      62: new           #25                 // class org/apache/hadoop/hbase/master/MasterCoprocessorHost$MasterEnvironmentForCoreCoprocessors
      65: dup
      66: aload_1
      67: iload_2
      68: iload_3
      69: aload         4
      71: aload_0
      72: getfield      #5                  // Field masterServices:Lorg/apache/hadoop/hbase/master/MasterServices;
      75: invokespecial #26                 // Method org/apache/hadoop/hbase/master/MasterCoprocessorHost$MasterEnvironmentForCoreCoprocessors."<init>":(Lorg/apache/hadoop/hbase/coprocessor/MasterCoprocessor;IILorg/apache/hadoop/conf/Configuration;Lorg/apache/hadoop/hbase/master/MasterServices;)V
      78: goto          97
      81: new           #27                 // class org/apache/hadoop/hbase/master/MasterCoprocessorHost$MasterEnvironment
      84: dup
      85: aload_1
      86: iload_2
      87: iload_3
      88: aload         4
      90: aload_0
      91: getfield      #5                  // Field masterServices:Lorg/apache/hadoop/hbase/master/MasterServices;
      94: invokespecial #28                 // Method org/apache/hadoop/hbase/master/MasterCoprocessorHost$MasterEnvironment."<init>":(Lorg/apache/hadoop/hbase/coprocessor/MasterCoprocessor;IILorg/apache/hadoop/conf/Configuration;Lorg/apache/hadoop/hbase/master/MasterServices;)V
      97: areturn

  public org.apache.hadoop.hbase.coprocessor.MasterCoprocessor checkAndGetInstance(java.lang.Class<?>) throws java.lang.InstantiationException, java.lang.IllegalAccessException;
    Code:
       0: ldc           #29                 // class org/apache/hadoop/hbase/coprocessor/MasterCoprocessor
       2: aload_1
       3: invokevirtual #30                 // Method java/lang/Class.isAssignableFrom:(Ljava/lang/Class;)Z
       6: ifeq          33
       9: aload_1
      10: ldc           #29                 // class org/apache/hadoop/hbase/coprocessor/MasterCoprocessor
      12: invokevirtual #31                 // Method java/lang/Class.asSubclass:(Ljava/lang/Class;)Ljava/lang/Class;
      15: iconst_0
      16: anewarray     #32                 // class java/lang/Class
      19: invokevirtual #33                 // Method java/lang/Class.getDeclaredConstructor:([Ljava/lang/Class;)Ljava/lang/reflect/Constructor;
      22: iconst_0
      23: anewarray     #34                 // class java/lang/Object
      26: invokevirtual #35                 // Method java/lang/reflect/Constructor.newInstance:([Ljava/lang/Object;)Ljava/lang/Object;
      29: checkcast     #29                 // class org/apache/hadoop/hbase/coprocessor/MasterCoprocessor
      32: areturn
      33: ldc           #36                 // class org/apache/hadoop/hbase/coprocessor/CoprocessorService
      35: aload_1
      36: invokevirtual #30                 // Method java/lang/Class.isAssignableFrom:(Ljava/lang/Class;)Z
      39: ifeq          75
      42: aload_1
      43: ldc           #36                 // class org/apache/hadoop/hbase/coprocessor/CoprocessorService
      45: invokevirtual #31                 // Method java/lang/Class.asSubclass:(Ljava/lang/Class;)Ljava/lang/Class;
      48: iconst_0
      49: anewarray     #32                 // class java/lang/Class
      52: invokevirtual #33                 // Method java/lang/Class.getDeclaredConstructor:([Ljava/lang/Class;)Ljava/lang/reflect/Constructor;
      55: iconst_0
      56: anewarray     #34                 // class java/lang/Object
      59: invokevirtual #35                 // Method java/lang/reflect/Constructor.newInstance:([Ljava/lang/Object;)Ljava/lang/Object;
      62: checkcast     #36                 // class org/apache/hadoop/hbase/coprocessor/CoprocessorService
      65: astore_2
      66: new           #37                 // class org/apache/hadoop/hbase/coprocessor/CoprocessorServiceBackwardCompatiblity$MasterCoprocessorService
      69: dup
      70: aload_2
      71: invokespecial #38                 // Method org/apache/hadoop/hbase/coprocessor/CoprocessorServiceBackwardCompatiblity$MasterCoprocessorService."<init>":(Lorg/apache/hadoop/hbase/coprocessor/CoprocessorService;)V
      74: areturn
      75: getstatic     #9                  // Field LOG:Lorg/slf4j/Logger;
      78: ldc           #39                 // String {} is not of type MasterCoprocessor. Check the configuration of {}
      80: aload_1
      81: invokevirtual #40                 // Method java/lang/Class.getName:()Ljava/lang/String;
      84: ldc           #14                 // String hbase.coprocessor.master.classes
      86: invokeinterface #41,  4           // InterfaceMethod org/slf4j/Logger.error:(Ljava/lang/String;Ljava/lang/Object;Ljava/lang/Object;)V
      91: aconst_null
      92: areturn
      93: astore_2
      94: new           #44                 // class java/lang/InstantiationException
      97: dup
      98: aload_1
      99: invokevirtual #40                 // Method java/lang/Class.getName:()Ljava/lang/String;
     102: invokespecial #45                 // Method java/lang/InstantiationException."<init>":(Ljava/lang/String;)V
     105: aload_2
     106: invokevirtual #46                 // Method java/lang/InstantiationException.initCause:(Ljava/lang/Throwable;)Ljava/lang/Throwable;
     109: checkcast     #44                 // class java/lang/InstantiationException
     112: athrow
    Exception table:
       from    to  target type
           0    32    93   Class java/lang/NoSuchMethodException
           0    32    93   Class java/lang/reflect/InvocationTargetException
          33    74    93   Class java/lang/NoSuchMethodException
          33    74    93   Class java/lang/reflect/InvocationTargetException
          75    92    93   Class java/lang/NoSuchMethodException
          75    92    93   Class java/lang/reflect/InvocationTargetException

  public void preCreateNamespace(org.apache.hadoop.hbase.NamespaceDescriptor) throws java.io.IOException;
    Code:
       0: aload_0
       1: aload_0
       2: getfield      #47                 // Field coprocEnvironments:Lorg/apache/hadoop/hbase/util/SortedList;
       5: invokevirtual #48                 // Method org/apache/hadoop/hbase/util/SortedList.isEmpty:()Z
       8: ifeq          15
      11: aconst_null
      12: goto          24
      15: new           #49                 // class org/apache/hadoop/hbase/master/MasterCoprocessorHost$1
      18: dup
      19: aload_0
      20: aload_1
      21: invokespecial #50                 // Method org/apache/hadoop/hbase/master/MasterCoprocessorHost$1."<init>":(Lorg/apache/hadoop/hbase/master/MasterCoprocessorHost;Lorg/apache/hadoop/hbase/NamespaceDescriptor;)V
      24: invokevirtual #51                 // Method execOperation:(Lorg/apache/hadoop/hbase/coprocessor/CoprocessorHost$ObserverOperation;)Z
      27: pop
      28: return

  public void postCreateNamespace(org.apache.hadoop.hbase.NamespaceDescriptor) throws java.io.IOException;
    Code:
       0: aload_0
       1: aload_0
       2: getfield      #47                 // Field coprocEnvironments:Lorg/apache/hadoop/hbase/util/SortedList;
       5: invokevirtual #48                 // Method org/apache/hadoop/hbase/util/SortedList.isEmpty:()Z
       8: ifeq          15
      11: aconst_null
      12: goto          24
      15: new           #52                 // class org/apache/hadoop/hbase/master/MasterCoprocessorHost$2
      18: dup
      19: aload_0
      20: aload_1
      21: invokespecial #53                 // Method org/apache/hadoop/hbase/master/MasterCoprocessorHost$2."<init>":(Lorg/apache/hadoop/hbase/master/MasterCoprocessorHost;Lorg/apache/hadoop/hbase/NamespaceDescriptor;)V
      24: invokevirtual #51                 // Method execOperation:(Lorg/apache/hadoop/hbase/coprocessor/CoprocessorHost$ObserverOperation;)Z
      27: pop
      28: return

  public void preDeleteNamespace(java.lang.String) throws java.io.IOException;
    Code:
       0: aload_0
       1: aload_0
       2: getfield      #47                 // Field coprocEnvironments:Lorg/apache/hadoop/hbase/util/SortedList;
       5: invokevirtual #48                 // Method org/apache/hadoop/hbase/util/SortedList.isEmpty:()Z
       8: ifeq          15
      11: aconst_null
      12: goto          24
      15: new           #54                 // class org/apache/hadoop/hbase/master/MasterCoprocessorHost$3
      18: dup
      19: aload_0
      20: aload_1
      21: invokespecial #55                 // Method org/apache/hadoop/hbase/master/MasterCoprocessorHost$3."<init>":(Lorg/apache/hadoop/hbase/master/MasterCoprocessorHost;Ljava/lang/String;)V
      24: invokevirtual #51                 // Method execOperation:(Lorg/apache/hadoop/hbase/coprocessor/CoprocessorHost$ObserverOperation;)Z
      27: pop
      28: return

  public void postDeleteNamespace(java.lang.String) throws java.io.IOException;
    Code:
       0: aload_0
       1: aload_0
       2: getfield      #47                 // Field coprocEnvironments:Lorg/apache/hadoop/hbase/util/SortedList;
       5: invokevirtual #48                 // Method org/apache/hadoop/hbase/util/SortedList.isEmpty:()Z
       8: ifeq          15
      11: aconst_null
      12: goto          24
      15: new           #56                 // class org/apache/hadoop/hbase/master/MasterCoprocessorHost$4
      18: dup
      19: aload_0
      20: aload_1
      21: invokespecial #57                 // Method org/apache/hadoop/hbase/master/MasterCoprocessorHost$4."<init>":(Lorg/apache/hadoop/hbase/master/MasterCoprocessorHost;Ljava/lang/String;)V
      24: invokevirtual #51                 // Method execOperation:(Lorg/apache/hadoop/hbase/coprocessor/CoprocessorHost$ObserverOperation;)Z
      27: pop
      28: return

  public void preModifyNamespace(org.apache.hadoop.hbase.NamespaceDescriptor, org.apache.hadoop.hbase.NamespaceDescriptor) throws java.io.IOException;
    Code:
       0: aload_0
       1: aload_0
       2: getfield      #47                 // Field coprocEnvironments:Lorg/apache/hadoop/hbase/util/SortedList;
       5: invokevirtual #48                 // Method org/apache/hadoop/hbase/util/SortedList.isEmpty:()Z
       8: ifeq          15
      11: aconst_null
      12: goto          25
      15: new           #58                 // class org/apache/hadoop/hbase/master/MasterCoprocessorHost$5
      18: dup
      19: aload_0
      20: aload_1
      21: aload_2
      22: invokespecial #59                 // Method org/apache/hadoop/hbase/master/MasterCoprocessorHost$5."<init>":(Lorg/apache/hadoop/hbase/master/MasterCoprocessorHost;Lorg/apache/hadoop/hbase/NamespaceDescriptor;Lorg/apache/hadoop/hbase/NamespaceDescriptor;)V
      25: invokevirtual #51                 // Method execOperation:(Lorg/apache/hadoop/hbase/coprocessor/CoprocessorHost$ObserverOperation;)Z
      28: pop
      29: return

  public void postModifyNamespace(org.apache.hadoop.hbase.NamespaceDescriptor, org.apache.hadoop.hbase.NamespaceDescriptor) throws java.io.IOException;
    Code:
       0: aload_0
       1: aload_0
       2: getfield      #47                 // Field coprocEnvironments:Lorg/apache/hadoop/hbase/util/SortedList;
       5: invokevirtual #48                 // Method org/apache/hadoop/hbase/util/SortedList.isEmpty:()Z
       8: ifeq          15
      11: aconst_null
      12: goto          25
      15: new           #60                 // class org/apache/hadoop/hbase/master/MasterCoprocessorHost$6
      18: dup
      19: aload_0
      20: aload_1
      21: aload_2
      22: invokespecial #61                 // Method org/apache/hadoop/hbase/master/MasterCoprocessorHost$6."<init>":(Lorg/apache/hadoop/hbase/master/MasterCoprocessorHost;Lorg/apache/hadoop/hbase/NamespaceDescriptor;Lorg/apache/hadoop/hbase/NamespaceDescriptor;)V
      25: invokevirtual #51                 // Method execOperation:(Lorg/apache/hadoop/hbase/coprocessor/CoprocessorHost$ObserverOperation;)Z
      28: pop
      29: return

  public void preGetNamespaceDescriptor(java.lang.String) throws java.io.IOException;
    Code:
       0: aload_0
       1: aload_0
       2: getfield      #47                 // Field coprocEnvironments:Lorg/apache/hadoop/hbase/util/SortedList;
       5: invokevirtual #48                 // Method org/apache/hadoop/hbase/util/SortedList.isEmpty:()Z
       8: ifeq          15
      11: aconst_null
      12: goto          24
      15: new           #62                 // class org/apache/hadoop/hbase/master/MasterCoprocessorHost$7
      18: dup
      19: aload_0
      20: aload_1
      21: invokespecial #63                 // Method org/apache/hadoop/hbase/master/MasterCoprocessorHost$7."<init>":(Lorg/apache/hadoop/hbase/master/MasterCoprocessorHost;Ljava/lang/String;)V
      24: invokevirtual #51                 // Method execOperation:(Lorg/apache/hadoop/hbase/coprocessor/CoprocessorHost$ObserverOperation;)Z
      27: pop
      28: return

  public void postGetNamespaceDescriptor(org.apache.hadoop.hbase.NamespaceDescriptor) throws java.io.IOException;
    Code:
       0: aload_0
       1: aload_0
       2: getfield      #47                 // Field coprocEnvironments:Lorg/apache/hadoop/hbase/util/SortedList;
       5: invokevirtual #48                 // Method org/apache/hadoop/hbase/util/SortedList.isEmpty:()Z
       8: ifeq          15
      11: aconst_null
      12: goto          24
      15: new           #64                 // class org/apache/hadoop/hbase/master/MasterCoprocessorHost$8
      18: dup
      19: aload_0
      20: aload_1
      21: invokespecial #65                 // Method org/apache/hadoop/hbase/master/MasterCoprocessorHost$8."<init>":(Lorg/apache/hadoop/hbase/master/MasterCoprocessorHost;Lorg/apache/hadoop/hbase/NamespaceDescriptor;)V
      24: invokevirtual #51                 // Method execOperation:(Lorg/apache/hadoop/hbase/coprocessor/CoprocessorHost$ObserverOperation;)Z
      27: pop
      28: return

  public void preListNamespaces(java.util.List<java.lang.String>) throws java.io.IOException;
    Code:
       0: aload_0
       1: aload_0
       2: getfield      #47                 // Field coprocEnvironments:Lorg/apache/hadoop/hbase/util/SortedList;
       5: invokevirtual #48                 // Method org/apache/hadoop/hbase/util/SortedList.isEmpty:()Z
       8: ifeq          15
      11: aconst_null
      12: goto          24
      15: new           #66                 // class org/apache/hadoop/hbase/master/MasterCoprocessorHost$9
      18: dup
      19: aload_0
      20: aload_1
      21: invokespecial #67                 // Method org/apache/hadoop/hbase/master/MasterCoprocessorHost$9."<init>":(Lorg/apache/hadoop/hbase/master/MasterCoprocessorHost;Ljava/util/List;)V
      24: invokevirtual #51                 // Method execOperation:(Lorg/apache/hadoop/hbase/coprocessor/CoprocessorHost$ObserverOperation;)Z
      27: pop
      28: return

  public void postListNamespaces(java.util.List<java.lang.String>) throws java.io.IOException;
    Code:
       0: aload_0
       1: aload_0
       2: getfield      #47                 // Field coprocEnvironments:Lorg/apache/hadoop/hbase/util/SortedList;
       5: invokevirtual #48                 // Method org/apache/hadoop/hbase/util/SortedList.isEmpty:()Z
       8: ifeq          15
      11: aconst_null
      12: goto          24
      15: new           #68                 // class org/apache/hadoop/hbase/master/MasterCoprocessorHost$10
      18: dup
      19: aload_0
      20: aload_1
      21: invokespecial #69                 // Method org/apache/hadoop/hbase/master/MasterCoprocessorHost$10."<init>":(Lorg/apache/hadoop/hbase/master/MasterCoprocessorHost;Ljava/util/List;)V
      24: invokevirtual #51                 // Method execOperation:(Lorg/apache/hadoop/hbase/coprocessor/CoprocessorHost$ObserverOperation;)Z
      27: pop
      28: return

  public void preListNamespaceDescriptors(java.util.List<org.apache.hadoop.hbase.NamespaceDescriptor>) throws java.io.IOException;
    Code:
       0: aload_0
       1: aload_0
       2: getfield      #47                 // Field coprocEnvironments:Lorg/apache/hadoop/hbase/util/SortedList;
       5: invokevirtual #48                 // Method org/apache/hadoop/hbase/util/SortedList.isEmpty:()Z
       8: ifeq          15
      11: aconst_null
      12: goto          24
      15: new           #70                 // class org/apache/hadoop/hbase/master/MasterCoprocessorHost$11
      18: dup
      19: aload_0
      20: aload_1
      21: invokespecial #71                 // Method org/apache/hadoop/hbase/master/MasterCoprocessorHost$11."<init>":(Lorg/apache/hadoop/hbase/master/MasterCoprocessorHost;Ljava/util/List;)V
      24: invokevirtual #51                 // Method execOperation:(Lorg/apache/hadoop/hbase/coprocessor/CoprocessorHost$ObserverOperation;)Z
      27: pop
      28: return

  public void postListNamespaceDescriptors(java.util.List<org.apache.hadoop.hbase.NamespaceDescriptor>) throws java.io.IOException;
    Code:
       0: aload_0
       1: aload_0
       2: getfield      #47                 // Field coprocEnvironments:Lorg/apache/hadoop/hbase/util/SortedList;
       5: invokevirtual #48                 // Method org/apache/hadoop/hbase/util/SortedList.isEmpty:()Z
       8: ifeq          15
      11: aconst_null
      12: goto          24
      15: new           #72                 // class org/apache/hadoop/hbase/master/MasterCoprocessorHost$12
      18: dup
      19: aload_0
      20: aload_1
      21: invokespecial #73                 // Method org/apache/hadoop/hbase/master/MasterCoprocessorHost$12."<init>":(Lorg/apache/hadoop/hbase/master/MasterCoprocessorHost;Ljava/util/List;)V
      24: invokevirtual #51                 // Method execOperation:(Lorg/apache/hadoop/hbase/coprocessor/CoprocessorHost$ObserverOperation;)Z
      27: pop
      28: return

  public org.apache.hadoop.hbase.client.TableDescriptor preCreateTableRegionsInfos(org.apache.hadoop.hbase.client.TableDescriptor) throws java.io.IOException;
    Code:
       0: aload_0
       1: getfield      #47                 // Field coprocEnvironments:Lorg/apache/hadoop/hbase/util/SortedList;
       4: invokevirtual #48                 // Method org/apache/hadoop/hbase/util/SortedList.isEmpty:()Z
       7: ifeq          12
      10: aload_1
      11: areturn
      12: aload_0
      13: new           #74                 // class org/apache/hadoop/hbase/master/MasterCoprocessorHost$13
      16: dup
      17: aload_0
      18: aload_0
      19: getfield      #1                  // Field masterObserverGetter:Lorg/apache/hadoop/hbase/coprocessor/CoprocessorHost$ObserverGetter;
      22: aload_1
      23: invokespecial #75                 // Method org/apache/hadoop/hbase/master/MasterCoprocessorHost$13."<init>":(Lorg/apache/hadoop/hbase/master/MasterCoprocessorHost;Lorg/apache/hadoop/hbase/coprocessor/CoprocessorHost$ObserverGetter;Lorg/apache/hadoop/hbase/client/TableDescriptor;)V
      26: invokevirtual #76                 // Method execOperationWithResult:(Lorg/apache/hadoop/hbase/coprocessor/CoprocessorHost$ObserverOperationWithResult;)Ljava/lang/Object;
      29: checkcast     #77                 // class org/apache/hadoop/hbase/client/TableDescriptor
      32: areturn

  public void preCreateTable(org.apache.hadoop.hbase.client.TableDescriptor, org.apache.hadoop.hbase.client.RegionInfo[]) throws java.io.IOException;
    Code:
       0: aload_0
       1: aload_0
       2: getfield      #47                 // Field coprocEnvironments:Lorg/apache/hadoop/hbase/util/SortedList;
       5: invokevirtual #48                 // Method org/apache/hadoop/hbase/util/SortedList.isEmpty:()Z
       8: ifeq          15
      11: aconst_null
      12: goto          25
      15: new           #78                 // class org/apache/hadoop/hbase/master/MasterCoprocessorHost$14
      18: dup
      19: aload_0
      20: aload_1
      21: aload_2
      22: invokespecial #79                 // Method org/apache/hadoop/hbase/master/MasterCoprocessorHost$14."<init>":(Lorg/apache/hadoop/hbase/master/MasterCoprocessorHost;Lorg/apache/hadoop/hbase/client/TableDescriptor;[Lorg/apache/hadoop/hbase/client/RegionInfo;)V
      25: invokevirtual #51                 // Method execOperation:(Lorg/apache/hadoop/hbase/coprocessor/CoprocessorHost$ObserverOperation;)Z
      28: pop
      29: return

  public void postCreateTable(org.apache.hadoop.hbase.client.TableDescriptor, org.apache.hadoop.hbase.client.RegionInfo[]) throws java.io.IOException;
    Code:
       0: aload_0
       1: aload_0
       2: getfield      #47                 // Field coprocEnvironments:Lorg/apache/hadoop/hbase/util/SortedList;
       5: invokevirtual #48                 // Method org/apache/hadoop/hbase/util/SortedList.isEmpty:()Z
       8: ifeq          15
      11: aconst_null
      12: goto          25
      15: new           #80                 // class org/apache/hadoop/hbase/master/MasterCoprocessorHost$15
      18: dup
      19: aload_0
      20: aload_1
      21: aload_2
      22: invokespecial #81                 // Method org/apache/hadoop/hbase/master/MasterCoprocessorHost$15."<init>":(Lorg/apache/hadoop/hbase/master/MasterCoprocessorHost;Lorg/apache/hadoop/hbase/client/TableDescriptor;[Lorg/apache/hadoop/hbase/client/RegionInfo;)V
      25: invokevirtual #51                 // Method execOperation:(Lorg/apache/hadoop/hbase/coprocessor/CoprocessorHost$ObserverOperation;)Z
      28: pop
      29: return

  public void preCreateTableAction(org.apache.hadoop.hbase.client.TableDescriptor, org.apache.hadoop.hbase.client.RegionInfo[], org.apache.hadoop.hbase.security.User) throws java.io.IOException;
    Code:
       0: aload_0
       1: aload_0
       2: getfield      #47                 // Field coprocEnvironments:Lorg/apache/hadoop/hbase/util/SortedList;
       5: invokevirtual #48                 // Method org/apache/hadoop/hbase/util/SortedList.isEmpty:()Z
       8: ifeq          15
      11: aconst_null
      12: goto          26
      15: new           #82                 // class org/apache/hadoop/hbase/master/MasterCoprocessorHost$16
      18: dup
      19: aload_0
      20: aload_3
      21: aload_1
      22: aload_2
      23: invokespecial #83                 // Method org/apache/hadoop/hbase/master/MasterCoprocessorHost$16."<init>":(Lorg/apache/hadoop/hbase/master/MasterCoprocessorHost;Lorg/apache/hadoop/hbase/security/User;Lorg/apache/hadoop/hbase/client/TableDescriptor;[Lorg/apache/hadoop/hbase/client/RegionInfo;)V
      26: invokevirtual #51                 // Method execOperation:(Lorg/apache/hadoop/hbase/coprocessor/CoprocessorHost$ObserverOperation;)Z
      29: pop
      30: return

  public void postCompletedCreateTableAction(org.apache.hadoop.hbase.client.TableDescriptor, org.apache.hadoop.hbase.client.RegionInfo[], org.apache.hadoop.hbase.security.User) throws java.io.IOException;
    Code:
       0: aload_0
       1: aload_0
       2: getfield      #47                 // Field coprocEnvironments:Lorg/apache/hadoop/hbase/util/SortedList;
       5: invokevirtual #48                 // Method org/apache/hadoop/hbase/util/SortedList.isEmpty:()Z
       8: ifeq          15
      11: aconst_null
      12: goto          26
      15: new           #84                 // class org/apache/hadoop/hbase/master/MasterCoprocessorHost$17
      18: dup
      19: aload_0
      20: aload_3
      21: aload_1
      22: aload_2
      23: invokespecial #85                 // Method org/apache/hadoop/hbase/master/MasterCoprocessorHost$17."<init>":(Lorg/apache/hadoop/hbase/master/MasterCoprocessorHost;Lorg/apache/hadoop/hbase/security/User;Lorg/apache/hadoop/hbase/client/TableDescriptor;[Lorg/apache/hadoop/hbase/client/RegionInfo;)V
      26: invokevirtual #51                 // Method execOperation:(Lorg/apache/hadoop/hbase/coprocessor/CoprocessorHost$ObserverOperation;)Z
      29: pop
      30: return

  public void preDeleteTable(org.apache.hadoop.hbase.TableName) throws java.io.IOException;
    Code:
       0: aload_0
       1: aload_0
       2: getfield      #47                 // Field coprocEnvironments:Lorg/apache/hadoop/hbase/util/SortedList;
       5: invokevirtual #48                 // Method org/apache/hadoop/hbase/util/SortedList.isEmpty:()Z
       8: ifeq          15
      11: aconst_null
      12: goto          24
      15: new           #86                 // class org/apache/hadoop/hbase/master/MasterCoprocessorHost$18
      18: dup
      19: aload_0
      20: aload_1
      21: invokespecial #87                 // Method org/apache/hadoop/hbase/master/MasterCoprocessorHost$18."<init>":(Lorg/apache/hadoop/hbase/master/MasterCoprocessorHost;Lorg/apache/hadoop/hbase/TableName;)V
      24: invokevirtual #51                 // Method execOperation:(Lorg/apache/hadoop/hbase/coprocessor/CoprocessorHost$ObserverOperation;)Z
      27: pop
      28: return

  public void postDeleteTable(org.apache.hadoop.hbase.TableName) throws java.io.IOException;
    Code:
       0: aload_0
       1: aload_0
       2: getfield      #47                 // Field coprocEnvironments:Lorg/apache/hadoop/hbase/util/SortedList;
       5: invokevirtual #48                 // Method org/apache/hadoop/hbase/util/SortedList.isEmpty:()Z
       8: ifeq          15
      11: aconst_null
      12: goto          24
      15: new           #88                 // class org/apache/hadoop/hbase/master/MasterCoprocessorHost$19
      18: dup
      19: aload_0
      20: aload_1
      21: invokespecial #89                 // Method org/apache/hadoop/hbase/master/MasterCoprocessorHost$19."<init>":(Lorg/apache/hadoop/hbase/master/MasterCoprocessorHost;Lorg/apache/hadoop/hbase/TableName;)V
      24: invokevirtual #51                 // Method execOperation:(Lorg/apache/hadoop/hbase/coprocessor/CoprocessorHost$ObserverOperation;)Z
      27: pop
      28: return

  public void preDeleteTableAction(org.apache.hadoop.hbase.TableName, org.apache.hadoop.hbase.security.User) throws java.io.IOException;
    Code:
       0: aload_0
       1: aload_0
       2: getfield      #47                 // Field coprocEnvironments:Lorg/apache/hadoop/hbase/util/SortedList;
       5: invokevirtual #48                 // Method org/apache/hadoop/hbase/util/SortedList.isEmpty:()Z
       8: ifeq          15
      11: aconst_null
      12: goto          25
      15: new           #90                 // class org/apache/hadoop/hbase/master/MasterCoprocessorHost$20
      18: dup
      19: aload_0
      20: aload_2
      21: aload_1
      22: invokespecial #91                 // Method org/apache/hadoop/hbase/master/MasterCoprocessorHost$20."<init>":(Lorg/apache/hadoop/hbase/master/MasterCoprocessorHost;Lorg/apache/hadoop/hbase/security/User;Lorg/apache/hadoop/hbase/TableName;)V
      25: invokevirtual #51                 // Method execOperation:(Lorg/apache/hadoop/hbase/coprocessor/CoprocessorHost$ObserverOperation;)Z
      28: pop
      29: return

  public void postCompletedDeleteTableAction(org.apache.hadoop.hbase.TableName, org.apache.hadoop.hbase.security.User) throws java.io.IOException;
    Code:
       0: aload_0
       1: aload_0
       2: getfield      #47                 // Field coprocEnvironments:Lorg/apache/hadoop/hbase/util/SortedList;
       5: invokevirtual #48                 // Method org/apache/hadoop/hbase/util/SortedList.isEmpty:()Z
       8: ifeq          15
      11: aconst_null
      12: goto          25
      15: new           #92                 // class org/apache/hadoop/hbase/master/MasterCoprocessorHost$21
      18: dup
      19: aload_0
      20: aload_2
      21: aload_1
      22: invokespecial #93                 // Method org/apache/hadoop/hbase/master/MasterCoprocessorHost$21."<init>":(Lorg/apache/hadoop/hbase/master/MasterCoprocessorHost;Lorg/apache/hadoop/hbase/security/User;Lorg/apache/hadoop/hbase/TableName;)V
      25: invokevirtual #51                 // Method execOperation:(Lorg/apache/hadoop/hbase/coprocessor/CoprocessorHost$ObserverOperation;)Z
      28: pop
      29: return

  public void preTruncateTable(org.apache.hadoop.hbase.TableName) throws java.io.IOException;
    Code:
       0: aload_0
       1: aload_0
       2: getfield      #47                 // Field coprocEnvironments:Lorg/apache/hadoop/hbase/util/SortedList;
       5: invokevirtual #48                 // Method org/apache/hadoop/hbase/util/SortedList.isEmpty:()Z
       8: ifeq          15
      11: aconst_null
      12: goto          24
      15: new           #94                 // class org/apache/hadoop/hbase/master/MasterCoprocessorHost$22
      18: dup
      19: aload_0
      20: aload_1
      21: invokespecial #95                 // Method org/apache/hadoop/hbase/master/MasterCoprocessorHost$22."<init>":(Lorg/apache/hadoop/hbase/master/MasterCoprocessorHost;Lorg/apache/hadoop/hbase/TableName;)V
      24: invokevirtual #51                 // Method execOperation:(Lorg/apache/hadoop/hbase/coprocessor/CoprocessorHost$ObserverOperation;)Z
      27: pop
      28: return

  public void postTruncateTable(org.apache.hadoop.hbase.TableName) throws java.io.IOException;
    Code:
       0: aload_0
       1: aload_0
       2: getfield      #47                 // Field coprocEnvironments:Lorg/apache/hadoop/hbase/util/SortedList;
       5: invokevirtual #48                 // Method org/apache/hadoop/hbase/util/SortedList.isEmpty:()Z
       8: ifeq          15
      11: aconst_null
      12: goto          24
      15: new           #96                 // class org/apache/hadoop/hbase/master/MasterCoprocessorHost$23
      18: dup
      19: aload_0
      20: aload_1
      21: invokespecial #97                 // Method org/apache/hadoop/hbase/master/MasterCoprocessorHost$23."<init>":(Lorg/apache/hadoop/hbase/master/MasterCoprocessorHost;Lorg/apache/hadoop/hbase/TableName;)V
      24: invokevirtual #51                 // Method execOperation:(Lorg/apache/hadoop/hbase/coprocessor/CoprocessorHost$ObserverOperation;)Z
      27: pop
      28: return

  public void preTruncateTableAction(org.apache.hadoop.hbase.TableName, org.apache.hadoop.hbase.security.User) throws java.io.IOException;
    Code:
       0: aload_0
       1: aload_0
       2: getfield      #47                 // Field coprocEnvironments:Lorg/apache/hadoop/hbase/util/SortedList;
       5: invokevirtual #48                 // Method org/apache/hadoop/hbase/util/SortedList.isEmpty:()Z
       8: ifeq          15
      11: aconst_null
      12: goto          25
      15: new           #98                 // class org/apache/hadoop/hbase/master/MasterCoprocessorHost$24
      18: dup
      19: aload_0
      20: aload_2
      21: aload_1
      22: invokespecial #99                 // Method org/apache/hadoop/hbase/master/MasterCoprocessorHost$24."<init>":(Lorg/apache/hadoop/hbase/master/MasterCoprocessorHost;Lorg/apache/hadoop/hbase/security/User;Lorg/apache/hadoop/hbase/TableName;)V
      25: invokevirtual #51                 // Method execOperation:(Lorg/apache/hadoop/hbase/coprocessor/CoprocessorHost$ObserverOperation;)Z
      28: pop
      29: return

  public void postCompletedTruncateTableAction(org.apache.hadoop.hbase.TableName, org.apache.hadoop.hbase.security.User) throws java.io.IOException;
    Code:
       0: aload_0
       1: aload_0
       2: getfield      #47                 // Field coprocEnvironments:Lorg/apache/hadoop/hbase/util/SortedList;
       5: invokevirtual #48                 // Method org/apache/hadoop/hbase/util/SortedList.isEmpty:()Z
       8: ifeq          15
      11: aconst_null
      12: goto          25
      15: new           #100                // class org/apache/hadoop/hbase/master/MasterCoprocessorHost$25
      18: dup
      19: aload_0
      20: aload_2
      21: aload_1
      22: invokespecial #101                // Method org/apache/hadoop/hbase/master/MasterCoprocessorHost$25."<init>":(Lorg/apache/hadoop/hbase/master/MasterCoprocessorHost;Lorg/apache/hadoop/hbase/security/User;Lorg/apache/hadoop/hbase/TableName;)V
      25: invokevirtual #51                 // Method execOperation:(Lorg/apache/hadoop/hbase/coprocessor/CoprocessorHost$ObserverOperation;)Z
      28: pop
      29: return

  public org.apache.hadoop.hbase.client.TableDescriptor preModifyTable(org.apache.hadoop.hbase.TableName, org.apache.hadoop.hbase.client.TableDescriptor, org.apache.hadoop.hbase.client.TableDescriptor) throws java.io.IOException;
    Code:
       0: aload_0
       1: getfield      #47                 // Field coprocEnvironments:Lorg/apache/hadoop/hbase/util/SortedList;
       4: invokevirtual #48                 // Method org/apache/hadoop/hbase/util/SortedList.isEmpty:()Z
       7: ifeq          12
      10: aload_3
      11: areturn
      12: aload_0
      13: new           #102                // class org/apache/hadoop/hbase/master/MasterCoprocessorHost$26
      16: dup
      17: aload_0
      18: aload_0
      19: getfield      #1                  // Field masterObserverGetter:Lorg/apache/hadoop/hbase/coprocessor/CoprocessorHost$ObserverGetter;
      22: aload_3
      23: aload_1
      24: aload_2
      25: invokespecial #103                // Method org/apache/hadoop/hbase/master/MasterCoprocessorHost$26."<init>":(Lorg/apache/hadoop/hbase/master/MasterCoprocessorHost;Lorg/apache/hadoop/hbase/coprocessor/CoprocessorHost$ObserverGetter;Lorg/apache/hadoop/hbase/client/TableDescriptor;Lorg/apache/hadoop/hbase/TableName;Lorg/apache/hadoop/hbase/client/TableDescriptor;)V
      28: invokevirtual #76                 // Method execOperationWithResult:(Lorg/apache/hadoop/hbase/coprocessor/CoprocessorHost$ObserverOperationWithResult;)Ljava/lang/Object;
      31: checkcast     #77                 // class org/apache/hadoop/hbase/client/TableDescriptor
      34: areturn

  public void postModifyTable(org.apache.hadoop.hbase.TableName, org.apache.hadoop.hbase.client.TableDescriptor, org.apache.hadoop.hbase.client.TableDescriptor) throws java.io.IOException;
    Code:
       0: aload_0
       1: aload_0
       2: getfield      #47                 // Field coprocEnvironments:Lorg/apache/hadoop/hbase/util/SortedList;
       5: invokevirtual #48                 // Method org/apache/hadoop/hbase/util/SortedList.isEmpty:()Z
       8: ifeq          15
      11: aconst_null
      12: goto          26
      15: new           #104                // class org/apache/hadoop/hbase/master/MasterCoprocessorHost$27
      18: dup
      19: aload_0
      20: aload_1
      21: aload_2
      22: aload_3
      23: invokespecial #105                // Method org/apache/hadoop/hbase/master/MasterCoprocessorHost$27."<init>":(Lorg/apache/hadoop/hbase/master/MasterCoprocessorHost;Lorg/apache/hadoop/hbase/TableName;Lorg/apache/hadoop/hbase/client/TableDescriptor;Lorg/apache/hadoop/hbase/client/TableDescriptor;)V
      26: invokevirtual #51                 // Method execOperation:(Lorg/apache/hadoop/hbase/coprocessor/CoprocessorHost$ObserverOperation;)Z
      29: pop
      30: return

  public void preModifyTableAction(org.apache.hadoop.hbase.TableName, org.apache.hadoop.hbase.client.TableDescriptor, org.apache.hadoop.hbase.client.TableDescriptor, org.apache.hadoop.hbase.security.User) throws java.io.IOException;
    Code:
       0: aload_0
       1: aload_0
       2: getfield      #47                 // Field coprocEnvironments:Lorg/apache/hadoop/hbase/util/SortedList;
       5: invokevirtual #48                 // Method org/apache/hadoop/hbase/util/SortedList.isEmpty:()Z
       8: ifeq          15
      11: aconst_null
      12: goto          28
      15: new           #106                // class org/apache/hadoop/hbase/master/MasterCoprocessorHost$28
      18: dup
      19: aload_0
      20: aload         4
      22: aload_1
      23: aload_2
      24: aload_3
      25: invokespecial #107                // Method org/apache/hadoop/hbase/master/MasterCoprocessorHost$28."<init>":(Lorg/apache/hadoop/hbase/master/MasterCoprocessorHost;Lorg/apache/hadoop/hbase/security/User;Lorg/apache/hadoop/hbase/TableName;Lorg/apache/hadoop/hbase/client/TableDescriptor;Lorg/apache/hadoop/hbase/client/TableDescriptor;)V
      28: invokevirtual #51                 // Method execOperation:(Lorg/apache/hadoop/hbase/coprocessor/CoprocessorHost$ObserverOperation;)Z
      31: pop
      32: return

  public void postCompletedModifyTableAction(org.apache.hadoop.hbase.TableName, org.apache.hadoop.hbase.client.TableDescriptor, org.apache.hadoop.hbase.client.TableDescriptor, org.apache.hadoop.hbase.security.User) throws java.io.IOException;
    Code:
       0: aload_0
       1: aload_0
       2: getfield      #47                 // Field coprocEnvironments:Lorg/apache/hadoop/hbase/util/SortedList;
       5: invokevirtual #48                 // Method org/apache/hadoop/hbase/util/SortedList.isEmpty:()Z
       8: ifeq          15
      11: aconst_null
      12: goto          28
      15: new           #108                // class org/apache/hadoop/hbase/master/MasterCoprocessorHost$29
      18: dup
      19: aload_0
      20: aload         4
      22: aload_1
      23: aload_2
      24: aload_3
      25: invokespecial #109                // Method org/apache/hadoop/hbase/master/MasterCoprocessorHost$29."<init>":(Lorg/apache/hadoop/hbase/master/MasterCoprocessorHost;Lorg/apache/hadoop/hbase/security/User;Lorg/apache/hadoop/hbase/TableName;Lorg/apache/hadoop/hbase/client/TableDescriptor;Lorg/apache/hadoop/hbase/client/TableDescriptor;)V
      28: invokevirtual #51                 // Method execOperation:(Lorg/apache/hadoop/hbase/coprocessor/CoprocessorHost$ObserverOperation;)Z
      31: pop
      32: return

  public void preEnableTable(org.apache.hadoop.hbase.TableName) throws java.io.IOException;
    Code:
       0: aload_0
       1: aload_0
       2: getfield      #47                 // Field coprocEnvironments:Lorg/apache/hadoop/hbase/util/SortedList;
       5: invokevirtual #48                 // Method org/apache/hadoop/hbase/util/SortedList.isEmpty:()Z
       8: ifeq          15
      11: aconst_null
      12: goto          24
      15: new           #110                // class org/apache/hadoop/hbase/master/MasterCoprocessorHost$30
      18: dup
      19: aload_0
      20: aload_1
      21: invokespecial #111                // Method org/apache/hadoop/hbase/master/MasterCoprocessorHost$30."<init>":(Lorg/apache/hadoop/hbase/master/MasterCoprocessorHost;Lorg/apache/hadoop/hbase/TableName;)V
      24: invokevirtual #51                 // Method execOperation:(Lorg/apache/hadoop/hbase/coprocessor/CoprocessorHost$ObserverOperation;)Z
      27: pop
      28: return

  public void postEnableTable(org.apache.hadoop.hbase.TableName) throws java.io.IOException;
    Code:
       0: aload_0
       1: aload_0
       2: getfield      #47                 // Field coprocEnvironments:Lorg/apache/hadoop/hbase/util/SortedList;
       5: invokevirtual #48                 // Method org/apache/hadoop/hbase/util/SortedList.isEmpty:()Z
       8: ifeq          15
      11: aconst_null
      12: goto          24
      15: new           #112                // class org/apache/hadoop/hbase/master/MasterCoprocessorHost$31
      18: dup
      19: aload_0
      20: aload_1
      21: invokespecial #113                // Method org/apache/hadoop/hbase/master/MasterCoprocessorHost$31."<init>":(Lorg/apache/hadoop/hbase/master/MasterCoprocessorHost;Lorg/apache/hadoop/hbase/TableName;)V
      24: invokevirtual #51                 // Method execOperation:(Lorg/apache/hadoop/hbase/coprocessor/CoprocessorHost$ObserverOperation;)Z
      27: pop
      28: return

  public void preEnableTableAction(org.apache.hadoop.hbase.TableName, org.apache.hadoop.hbase.security.User) throws java.io.IOException;
    Code:
       0: aload_0
       1: aload_0
       2: getfield      #47                 // Field coprocEnvironments:Lorg/apache/hadoop/hbase/util/SortedList;
       5: invokevirtual #48                 // Method org/apache/hadoop/hbase/util/SortedList.isEmpty:()Z
       8: ifeq          15
      11: aconst_null
      12: goto          25
      15: new           #114                // class org/apache/hadoop/hbase/master/MasterCoprocessorHost$32
      18: dup
      19: aload_0
      20: aload_2
      21: aload_1
      22: invokespecial #115                // Method org/apache/hadoop/hbase/master/MasterCoprocessorHost$32."<init>":(Lorg/apache/hadoop/hbase/master/MasterCoprocessorHost;Lorg/apache/hadoop/hbase/security/User;Lorg/apache/hadoop/hbase/TableName;)V
      25: invokevirtual #51                 // Method execOperation:(Lorg/apache/hadoop/hbase/coprocessor/CoprocessorHost$ObserverOperation;)Z
      28: pop
      29: return

  public void postCompletedEnableTableAction(org.apache.hadoop.hbase.TableName, org.apache.hadoop.hbase.security.User) throws java.io.IOException;
    Code:
       0: aload_0
       1: aload_0
       2: getfield      #47                 // Field coprocEnvironments:Lorg/apache/hadoop/hbase/util/SortedList;
       5: invokevirtual #48                 // Method org/apache/hadoop/hbase/util/SortedList.isEmpty:()Z
       8: ifeq          15
      11: aconst_null
      12: goto          25
      15: new           #116                // class org/apache/hadoop/hbase/master/MasterCoprocessorHost$33
      18: dup
      19: aload_0
      20: aload_2
      21: aload_1
      22: invokespecial #117                // Method org/apache/hadoop/hbase/master/MasterCoprocessorHost$33."<init>":(Lorg/apache/hadoop/hbase/master/MasterCoprocessorHost;Lorg/apache/hadoop/hbase/security/User;Lorg/apache/hadoop/hbase/TableName;)V
      25: invokevirtual #51                 // Method execOperation:(Lorg/apache/hadoop/hbase/coprocessor/CoprocessorHost$ObserverOperation;)Z
      28: pop
      29: return

  public void preDisableTable(org.apache.hadoop.hbase.TableName) throws java.io.IOException;
    Code:
       0: aload_0
       1: aload_0
       2: getfield      #47                 // Field coprocEnvironments:Lorg/apache/hadoop/hbase/util/SortedList;
       5: invokevirtual #48                 // Method org/apache/hadoop/hbase/util/SortedList.isEmpty:()Z
       8: ifeq          15
      11: aconst_null
      12: goto          24
      15: new           #118                // class org/apache/hadoop/hbase/master/MasterCoprocessorHost$34
      18: dup
      19: aload_0
      20: aload_1
      21: invokespecial #119                // Method org/apache/hadoop/hbase/master/MasterCoprocessorHost$34."<init>":(Lorg/apache/hadoop/hbase/master/MasterCoprocessorHost;Lorg/apache/hadoop/hbase/TableName;)V
      24: invokevirtual #51                 // Method execOperation:(Lorg/apache/hadoop/hbase/coprocessor/CoprocessorHost$ObserverOperation;)Z
      27: pop
      28: return

  public void postDisableTable(org.apache.hadoop.hbase.TableName) throws java.io.IOException;
    Code:
       0: aload_0
       1: aload_0
       2: getfield      #47                 // Field coprocEnvironments:Lorg/apache/hadoop/hbase/util/SortedList;
       5: invokevirtual #48                 // Method org/apache/hadoop/hbase/util/SortedList.isEmpty:()Z
       8: ifeq          15
      11: aconst_null
      12: goto          24
      15: new           #120                // class org/apache/hadoop/hbase/master/MasterCoprocessorHost$35
      18: dup
      19: aload_0
      20: aload_1
      21: invokespecial #121                // Method org/apache/hadoop/hbase/master/MasterCoprocessorHost$35."<init>":(Lorg/apache/hadoop/hbase/master/MasterCoprocessorHost;Lorg/apache/hadoop/hbase/TableName;)V
      24: invokevirtual #51                 // Method execOperation:(Lorg/apache/hadoop/hbase/coprocessor/CoprocessorHost$ObserverOperation;)Z
      27: pop
      28: return

  public void preDisableTableAction(org.apache.hadoop.hbase.TableName, org.apache.hadoop.hbase.security.User) throws java.io.IOException;
    Code:
       0: aload_0
       1: aload_0
       2: getfield      #47                 // Field coprocEnvironments:Lorg/apache/hadoop/hbase/util/SortedList;
       5: invokevirtual #48                 // Method org/apache/hadoop/hbase/util/SortedList.isEmpty:()Z
       8: ifeq          15
      11: aconst_null
      12: goto          25
      15: new           #122                // class org/apache/hadoop/hbase/master/MasterCoprocessorHost$36
      18: dup
      19: aload_0
      20: aload_2
      21: aload_1
      22: invokespecial #123                // Method org/apache/hadoop/hbase/master/MasterCoprocessorHost$36."<init>":(Lorg/apache/hadoop/hbase/master/MasterCoprocessorHost;Lorg/apache/hadoop/hbase/security/User;Lorg/apache/hadoop/hbase/TableName;)V
      25: invokevirtual #51                 // Method execOperation:(Lorg/apache/hadoop/hbase/coprocessor/CoprocessorHost$ObserverOperation;)Z
      28: pop
      29: return

  public void postCompletedDisableTableAction(org.apache.hadoop.hbase.TableName, org.apache.hadoop.hbase.security.User) throws java.io.IOException;
    Code:
       0: aload_0
       1: aload_0
       2: getfield      #47                 // Field coprocEnvironments:Lorg/apache/hadoop/hbase/util/SortedList;
       5: invokevirtual #48                 // Method org/apache/hadoop/hbase/util/SortedList.isEmpty:()Z
       8: ifeq          15
      11: aconst_null
      12: goto          25
      15: new           #124                // class org/apache/hadoop/hbase/master/MasterCoprocessorHost$37
      18: dup
      19: aload_0
      20: aload_2
      21: aload_1
      22: invokespecial #125                // Method org/apache/hadoop/hbase/master/MasterCoprocessorHost$37."<init>":(Lorg/apache/hadoop/hbase/master/MasterCoprocessorHost;Lorg/apache/hadoop/hbase/security/User;Lorg/apache/hadoop/hbase/TableName;)V
      25: invokevirtual #51                 // Method execOperation:(Lorg/apache/hadoop/hbase/coprocessor/CoprocessorHost$ObserverOperation;)Z
      28: pop
      29: return

  public void preAbortProcedure(org.apache.hadoop.hbase.procedure2.ProcedureExecutor<org.apache.hadoop.hbase.master.procedure.MasterProcedureEnv>, long) throws java.io.IOException;
    Code:
       0: aload_0
       1: aload_0
       2: getfield      #47                 // Field coprocEnvironments:Lorg/apache/hadoop/hbase/util/SortedList;
       5: invokevirtual #48                 // Method org/apache/hadoop/hbase/util/SortedList.isEmpty:()Z
       8: ifeq          15
      11: aconst_null
      12: goto          24
      15: new           #126                // class org/apache/hadoop/hbase/master/MasterCoprocessorHost$38
      18: dup
      19: aload_0
      20: lload_2
      21: invokespecial #127                // Method org/apache/hadoop/hbase/master/MasterCoprocessorHost$38."<init>":(Lorg/apache/hadoop/hbase/master/MasterCoprocessorHost;J)V
      24: invokevirtual #51                 // Method execOperation:(Lorg/apache/hadoop/hbase/coprocessor/CoprocessorHost$ObserverOperation;)Z
      27: pop
      28: return

  public void postAbortProcedure() throws java.io.IOException;
    Code:
       0: aload_0
       1: aload_0
       2: getfield      #47                 // Field coprocEnvironments:Lorg/apache/hadoop/hbase/util/SortedList;
       5: invokevirtual #48                 // Method org/apache/hadoop/hbase/util/SortedList.isEmpty:()Z
       8: ifeq          15
      11: aconst_null
      12: goto          23
      15: new           #128                // class org/apache/hadoop/hbase/master/MasterCoprocessorHost$39
      18: dup
      19: aload_0
      20: invokespecial #129                // Method org/apache/hadoop/hbase/master/MasterCoprocessorHost$39."<init>":(Lorg/apache/hadoop/hbase/master/MasterCoprocessorHost;)V
      23: invokevirtual #51                 // Method execOperation:(Lorg/apache/hadoop/hbase/coprocessor/CoprocessorHost$ObserverOperation;)Z
      26: pop
      27: return

  public void preGetProcedures() throws java.io.IOException;
    Code:
       0: aload_0
       1: aload_0
       2: getfield      #47                 // Field coprocEnvironments:Lorg/apache/hadoop/hbase/util/SortedList;
       5: invokevirtual #48                 // Method org/apache/hadoop/hbase/util/SortedList.isEmpty:()Z
       8: ifeq          15
      11: aconst_null
      12: goto          23
      15: new           #130                // class org/apache/hadoop/hbase/master/MasterCoprocessorHost$40
      18: dup
      19: aload_0
      20: invokespecial #131                // Method org/apache/hadoop/hbase/master/MasterCoprocessorHost$40."<init>":(Lorg/apache/hadoop/hbase/master/MasterCoprocessorHost;)V
      23: invokevirtual #51                 // Method execOperation:(Lorg/apache/hadoop/hbase/coprocessor/CoprocessorHost$ObserverOperation;)Z
      26: pop
      27: return

  public void postGetProcedures(java.util.List<org.apache.hadoop.hbase.procedure2.Procedure<?>>) throws java.io.IOException;
    Code:
       0: aload_0
       1: aload_0
       2: getfield      #47                 // Field coprocEnvironments:Lorg/apache/hadoop/hbase/util/SortedList;
       5: invokevirtual #48                 // Method org/apache/hadoop/hbase/util/SortedList.isEmpty:()Z
       8: ifeq          15
      11: aconst_null
      12: goto          23
      15: new           #132                // class org/apache/hadoop/hbase/master/MasterCoprocessorHost$41
      18: dup
      19: aload_0
      20: invokespecial #133                // Method org/apache/hadoop/hbase/master/MasterCoprocessorHost$41."<init>":(Lorg/apache/hadoop/hbase/master/MasterCoprocessorHost;)V
      23: invokevirtual #51                 // Method execOperation:(Lorg/apache/hadoop/hbase/coprocessor/CoprocessorHost$ObserverOperation;)Z
      26: pop
      27: return

  public void preGetLocks() throws java.io.IOException;
    Code:
       0: aload_0
       1: aload_0
       2: getfield      #47                 // Field coprocEnvironments:Lorg/apache/hadoop/hbase/util/SortedList;
       5: invokevirtual #48                 // Method org/apache/hadoop/hbase/util/SortedList.isEmpty:()Z
       8: ifeq          15
      11: aconst_null
      12: goto          23
      15: new           #134                // class org/apache/hadoop/hbase/master/MasterCoprocessorHost$42
      18: dup
      19: aload_0
      20: invokespecial #135                // Method org/apache/hadoop/hbase/master/MasterCoprocessorHost$42."<init>":(Lorg/apache/hadoop/hbase/master/MasterCoprocessorHost;)V
      23: invokevirtual #51                 // Method execOperation:(Lorg/apache/hadoop/hbase/coprocessor/CoprocessorHost$ObserverOperation;)Z
      26: pop
      27: return

  public void postGetLocks(java.util.List<org.apache.hadoop.hbase.procedure2.LockedResource>) throws java.io.IOException;
    Code:
       0: aload_0
       1: aload_0
       2: getfield      #47                 // Field coprocEnvironments:Lorg/apache/hadoop/hbase/util/SortedList;
       5: invokevirtual #48                 // Method org/apache/hadoop/hbase/util/SortedList.isEmpty:()Z
       8: ifeq          15
      11: aconst_null
      12: goto          23
      15: new           #136                // class org/apache/hadoop/hbase/master/MasterCoprocessorHost$43
      18: dup
      19: aload_0
      20: invokespecial #137                // Method org/apache/hadoop/hbase/master/MasterCoprocessorHost$43."<init>":(Lorg/apache/hadoop/hbase/master/MasterCoprocessorHost;)V
      23: invokevirtual #51                 // Method execOperation:(Lorg/apache/hadoop/hbase/coprocessor/CoprocessorHost$ObserverOperation;)Z
      26: pop
      27: return

  public void preMove(org.apache.hadoop.hbase.client.RegionInfo, org.apache.hadoop.hbase.ServerName, org.apache.hadoop.hbase.ServerName) throws java.io.IOException;
    Code:
       0: aload_0
       1: aload_0
       2: getfield      #47                 // Field coprocEnvironments:Lorg/apache/hadoop/hbase/util/SortedList;
       5: invokevirtual #48                 // Method org/apache/hadoop/hbase/util/SortedList.isEmpty:()Z
       8: ifeq          15
      11: aconst_null
      12: goto          26
      15: new           #138                // class org/apache/hadoop/hbase/master/MasterCoprocessorHost$44
      18: dup
      19: aload_0
      20: aload_1
      21: aload_2
      22: aload_3
      23: invokespecial #139                // Method org/apache/hadoop/hbase/master/MasterCoprocessorHost$44."<init>":(Lorg/apache/hadoop/hbase/master/MasterCoprocessorHost;Lorg/apache/hadoop/hbase/client/RegionInfo;Lorg/apache/hadoop/hbase/ServerName;Lorg/apache/hadoop/hbase/ServerName;)V
      26: invokevirtual #51                 // Method execOperation:(Lorg/apache/hadoop/hbase/coprocessor/CoprocessorHost$ObserverOperation;)Z
      29: pop
      30: return

  public void postMove(org.apache.hadoop.hbase.client.RegionInfo, org.apache.hadoop.hbase.ServerName, org.apache.hadoop.hbase.ServerName) throws java.io.IOException;
    Code:
       0: aload_0
       1: aload_0
       2: getfield      #47                 // Field coprocEnvironments:Lorg/apache/hadoop/hbase/util/SortedList;
       5: invokevirtual #48                 // Method org/apache/hadoop/hbase/util/SortedList.isEmpty:()Z
       8: ifeq          15
      11: aconst_null
      12: goto          26
      15: new           #140                // class org/apache/hadoop/hbase/master/MasterCoprocessorHost$45
      18: dup
      19: aload_0
      20: aload_1
      21: aload_2
      22: aload_3
      23: invokespecial #141                // Method org/apache/hadoop/hbase/master/MasterCoprocessorHost$45."<init>":(Lorg/apache/hadoop/hbase/master/MasterCoprocessorHost;Lorg/apache/hadoop/hbase/client/RegionInfo;Lorg/apache/hadoop/hbase/ServerName;Lorg/apache/hadoop/hbase/ServerName;)V
      26: invokevirtual #51                 // Method execOperation:(Lorg/apache/hadoop/hbase/coprocessor/CoprocessorHost$ObserverOperation;)Z
      29: pop
      30: return

  public void preAssign(org.apache.hadoop.hbase.client.RegionInfo) throws java.io.IOException;
    Code:
       0: aload_0
       1: aload_0
       2: getfield      #47                 // Field coprocEnvironments:Lorg/apache/hadoop/hbase/util/SortedList;
       5: invokevirtual #48                 // Method org/apache/hadoop/hbase/util/SortedList.isEmpty:()Z
       8: ifeq          15
      11: aconst_null
      12: goto          24
      15: new           #142                // class org/apache/hadoop/hbase/master/MasterCoprocessorHost$46
      18: dup
      19: aload_0
      20: aload_1
      21: invokespecial #143                // Method org/apache/hadoop/hbase/master/MasterCoprocessorHost$46."<init>":(Lorg/apache/hadoop/hbase/master/MasterCoprocessorHost;Lorg/apache/hadoop/hbase/client/RegionInfo;)V
      24: invokevirtual #51                 // Method execOperation:(Lorg/apache/hadoop/hbase/coprocessor/CoprocessorHost$ObserverOperation;)Z
      27: pop
      28: return

  public void postAssign(org.apache.hadoop.hbase.client.RegionInfo) throws java.io.IOException;
    Code:
       0: aload_0
       1: aload_0
       2: getfield      #47                 // Field coprocEnvironments:Lorg/apache/hadoop/hbase/util/SortedList;
       5: invokevirtual #48                 // Method org/apache/hadoop/hbase/util/SortedList.isEmpty:()Z
       8: ifeq          15
      11: aconst_null
      12: goto          24
      15: new           #144                // class org/apache/hadoop/hbase/master/MasterCoprocessorHost$47
      18: dup
      19: aload_0
      20: aload_1
      21: invokespecial #145                // Method org/apache/hadoop/hbase/master/MasterCoprocessorHost$47."<init>":(Lorg/apache/hadoop/hbase/master/MasterCoprocessorHost;Lorg/apache/hadoop/hbase/client/RegionInfo;)V
      24: invokevirtual #51                 // Method execOperation:(Lorg/apache/hadoop/hbase/coprocessor/CoprocessorHost$ObserverOperation;)Z
      27: pop
      28: return

  public void preUnassign(org.apache.hadoop.hbase.client.RegionInfo, boolean) throws java.io.IOException;
    Code:
       0: aload_0
       1: aload_0
       2: getfield      #47                 // Field coprocEnvironments:Lorg/apache/hadoop/hbase/util/SortedList;
       5: invokevirtual #48                 // Method org/apache/hadoop/hbase/util/SortedList.isEmpty:()Z
       8: ifeq          15
      11: aconst_null
      12: goto          25
      15: new           #146                // class org/apache/hadoop/hbase/master/MasterCoprocessorHost$48
      18: dup
      19: aload_0
      20: aload_1
      21: iload_2
      22: invokespecial #147                // Method org/apache/hadoop/hbase/master/MasterCoprocessorHost$48."<init>":(Lorg/apache/hadoop/hbase/master/MasterCoprocessorHost;Lorg/apache/hadoop/hbase/client/RegionInfo;Z)V
      25: invokevirtual #51                 // Method execOperation:(Lorg/apache/hadoop/hbase/coprocessor/CoprocessorHost$ObserverOperation;)Z
      28: pop
      29: return

  public void postUnassign(org.apache.hadoop.hbase.client.RegionInfo, boolean) throws java.io.IOException;
    Code:
       0: aload_0
       1: aload_0
       2: getfield      #47                 // Field coprocEnvironments:Lorg/apache/hadoop/hbase/util/SortedList;
       5: invokevirtual #48                 // Method org/apache/hadoop/hbase/util/SortedList.isEmpty:()Z
       8: ifeq          15
      11: aconst_null
      12: goto          25
      15: new           #148                // class org/apache/hadoop/hbase/master/MasterCoprocessorHost$49
      18: dup
      19: aload_0
      20: aload_1
      21: iload_2
      22: invokespecial #149                // Method org/apache/hadoop/hbase/master/MasterCoprocessorHost$49."<init>":(Lorg/apache/hadoop/hbase/master/MasterCoprocessorHost;Lorg/apache/hadoop/hbase/client/RegionInfo;Z)V
      25: invokevirtual #51                 // Method execOperation:(Lorg/apache/hadoop/hbase/coprocessor/CoprocessorHost$ObserverOperation;)Z
      28: pop
      29: return

  public void preRegionOffline(org.apache.hadoop.hbase.client.RegionInfo) throws java.io.IOException;
    Code:
       0: aload_0
       1: aload_0
       2: getfield      #47                 // Field coprocEnvironments:Lorg/apache/hadoop/hbase/util/SortedList;
       5: invokevirtual #48                 // Method org/apache/hadoop/hbase/util/SortedList.isEmpty:()Z
       8: ifeq          15
      11: aconst_null
      12: goto          24
      15: new           #150                // class org/apache/hadoop/hbase/master/MasterCoprocessorHost$50
      18: dup
      19: aload_0
      20: aload_1
      21: invokespecial #151                // Method org/apache/hadoop/hbase/master/MasterCoprocessorHost$50."<init>":(Lorg/apache/hadoop/hbase/master/MasterCoprocessorHost;Lorg/apache/hadoop/hbase/client/RegionInfo;)V
      24: invokevirtual #51                 // Method execOperation:(Lorg/apache/hadoop/hbase/coprocessor/CoprocessorHost$ObserverOperation;)Z
      27: pop
      28: return

  public void postRegionOffline(org.apache.hadoop.hbase.client.RegionInfo) throws java.io.IOException;
    Code:
       0: aload_0
       1: aload_0
       2: getfield      #47                 // Field coprocEnvironments:Lorg/apache/hadoop/hbase/util/SortedList;
       5: invokevirtual #48                 // Method org/apache/hadoop/hbase/util/SortedList.isEmpty:()Z
       8: ifeq          15
      11: aconst_null
      12: goto          24
      15: new           #152                // class org/apache/hadoop/hbase/master/MasterCoprocessorHost$51
      18: dup
      19: aload_0
      20: aload_1
      21: invokespecial #153                // Method org/apache/hadoop/hbase/master/MasterCoprocessorHost$51."<init>":(Lorg/apache/hadoop/hbase/master/MasterCoprocessorHost;Lorg/apache/hadoop/hbase/client/RegionInfo;)V
      24: invokevirtual #51                 // Method execOperation:(Lorg/apache/hadoop/hbase/coprocessor/CoprocessorHost$ObserverOperation;)Z
      27: pop
      28: return

  public void preMergeRegions(org.apache.hadoop.hbase.client.RegionInfo[]) throws java.io.IOException;
    Code:
       0: aload_0
       1: aload_0
       2: getfield      #47                 // Field coprocEnvironments:Lorg/apache/hadoop/hbase/util/SortedList;
       5: invokevirtual #48                 // Method org/apache/hadoop/hbase/util/SortedList.isEmpty:()Z
       8: ifeq          15
      11: aconst_null
      12: goto          24
      15: new           #154                // class org/apache/hadoop/hbase/master/MasterCoprocessorHost$52
      18: dup
      19: aload_0
      20: aload_1
      21: invokespecial #155                // Method org/apache/hadoop/hbase/master/MasterCoprocessorHost$52."<init>":(Lorg/apache/hadoop/hbase/master/MasterCoprocessorHost;[Lorg/apache/hadoop/hbase/client/RegionInfo;)V
      24: invokevirtual #51                 // Method execOperation:(Lorg/apache/hadoop/hbase/coprocessor/CoprocessorHost$ObserverOperation;)Z
      27: pop
      28: return

  public void postMergeRegions(org.apache.hadoop.hbase.client.RegionInfo[]) throws java.io.IOException;
    Code:
       0: aload_0
       1: aload_0
       2: getfield      #47                 // Field coprocEnvironments:Lorg/apache/hadoop/hbase/util/SortedList;
       5: invokevirtual #48                 // Method org/apache/hadoop/hbase/util/SortedList.isEmpty:()Z
       8: ifeq          15
      11: aconst_null
      12: goto          24
      15: new           #156                // class org/apache/hadoop/hbase/master/MasterCoprocessorHost$53
      18: dup
      19: aload_0
      20: aload_1
      21: invokespecial #157                // Method org/apache/hadoop/hbase/master/MasterCoprocessorHost$53."<init>":(Lorg/apache/hadoop/hbase/master/MasterCoprocessorHost;[Lorg/apache/hadoop/hbase/client/RegionInfo;)V
      24: invokevirtual #51                 // Method execOperation:(Lorg/apache/hadoop/hbase/coprocessor/CoprocessorHost$ObserverOperation;)Z
      27: pop
      28: return

  public boolean preBalance() throws java.io.IOException;
    Code:
       0: aload_0
       1: aload_0
       2: getfield      #47                 // Field coprocEnvironments:Lorg/apache/hadoop/hbase/util/SortedList;
       5: invokevirtual #48                 // Method org/apache/hadoop/hbase/util/SortedList.isEmpty:()Z
       8: ifeq          15
      11: aconst_null
      12: goto          23
      15: new           #158                // class org/apache/hadoop/hbase/master/MasterCoprocessorHost$54
      18: dup
      19: aload_0
      20: invokespecial #159                // Method org/apache/hadoop/hbase/master/MasterCoprocessorHost$54."<init>":(Lorg/apache/hadoop/hbase/master/MasterCoprocessorHost;)V
      23: invokevirtual #51                 // Method execOperation:(Lorg/apache/hadoop/hbase/coprocessor/CoprocessorHost$ObserverOperation;)Z
      26: ireturn

  public void postBalance(java.util.List<org.apache.hadoop.hbase.master.RegionPlan>) throws java.io.IOException;
    Code:
       0: aload_0
       1: aload_0
       2: getfield      #47                 // Field coprocEnvironments:Lorg/apache/hadoop/hbase/util/SortedList;
       5: invokevirtual #48                 // Method org/apache/hadoop/hbase/util/SortedList.isEmpty:()Z
       8: ifeq          15
      11: aconst_null
      12: goto          24
      15: new           #160                // class org/apache/hadoop/hbase/master/MasterCoprocessorHost$55
      18: dup
      19: aload_0
      20: aload_1
      21: invokespecial #161                // Method org/apache/hadoop/hbase/master/MasterCoprocessorHost$55."<init>":(Lorg/apache/hadoop/hbase/master/MasterCoprocessorHost;Ljava/util/List;)V
      24: invokevirtual #51                 // Method execOperation:(Lorg/apache/hadoop/hbase/coprocessor/CoprocessorHost$ObserverOperation;)Z
      27: pop
      28: return

  public void preSetSplitOrMergeEnabled(boolean, org.apache.hadoop.hbase.client.MasterSwitchType) throws java.io.IOException;
    Code:
       0: aload_0
       1: aload_0
       2: getfield      #47                 // Field coprocEnvironments:Lorg/apache/hadoop/hbase/util/SortedList;
       5: invokevirtual #48                 // Method org/apache/hadoop/hbase/util/SortedList.isEmpty:()Z
       8: ifeq          15
      11: aconst_null
      12: goto          25
      15: new           #162                // class org/apache/hadoop/hbase/master/MasterCoprocessorHost$56
      18: dup
      19: aload_0
      20: iload_1
      21: aload_2
      22: invokespecial #163                // Method org/apache/hadoop/hbase/master/MasterCoprocessorHost$56."<init>":(Lorg/apache/hadoop/hbase/master/MasterCoprocessorHost;ZLorg/apache/hadoop/hbase/client/MasterSwitchType;)V
      25: invokevirtual #51                 // Method execOperation:(Lorg/apache/hadoop/hbase/coprocessor/CoprocessorHost$ObserverOperation;)Z
      28: pop
      29: return

  public void postSetSplitOrMergeEnabled(boolean, org.apache.hadoop.hbase.client.MasterSwitchType) throws java.io.IOException;
    Code:
       0: aload_0
       1: aload_0
       2: getfield      #47                 // Field coprocEnvironments:Lorg/apache/hadoop/hbase/util/SortedList;
       5: invokevirtual #48                 // Method org/apache/hadoop/hbase/util/SortedList.isEmpty:()Z
       8: ifeq          15
      11: aconst_null
      12: goto          25
      15: new           #164                // class org/apache/hadoop/hbase/master/MasterCoprocessorHost$57
      18: dup
      19: aload_0
      20: iload_1
      21: aload_2
      22: invokespecial #165                // Method org/apache/hadoop/hbase/master/MasterCoprocessorHost$57."<init>":(Lorg/apache/hadoop/hbase/master/MasterCoprocessorHost;ZLorg/apache/hadoop/hbase/client/MasterSwitchType;)V
      25: invokevirtual #51                 // Method execOperation:(Lorg/apache/hadoop/hbase/coprocessor/CoprocessorHost$ObserverOperation;)Z
      28: pop
      29: return

  public void preSplitRegion(org.apache.hadoop.hbase.TableName, byte[]) throws java.io.IOException;
    Code:
       0: aload_0
       1: aload_0
       2: getfield      #47                 // Field coprocEnvironments:Lorg/apache/hadoop/hbase/util/SortedList;
       5: invokevirtual #48                 // Method org/apache/hadoop/hbase/util/SortedList.isEmpty:()Z
       8: ifeq          15
      11: aconst_null
      12: goto          25
      15: new           #166                // class org/apache/hadoop/hbase/master/MasterCoprocessorHost$58
      18: dup
      19: aload_0
      20: aload_1
      21: aload_2
      22: invokespecial #167                // Method org/apache/hadoop/hbase/master/MasterCoprocessorHost$58."<init>":(Lorg/apache/hadoop/hbase/master/MasterCoprocessorHost;Lorg/apache/hadoop/hbase/TableName;[B)V
      25: invokevirtual #51                 // Method execOperation:(Lorg/apache/hadoop/hbase/coprocessor/CoprocessorHost$ObserverOperation;)Z
      28: pop
      29: return

  public void preSplitRegionAction(org.apache.hadoop.hbase.TableName, byte[], org.apache.hadoop.hbase.security.User) throws java.io.IOException;
    Code:
       0: aload_0
       1: aload_0
       2: getfield      #47                 // Field coprocEnvironments:Lorg/apache/hadoop/hbase/util/SortedList;
       5: invokevirtual #48                 // Method org/apache/hadoop/hbase/util/SortedList.isEmpty:()Z
       8: ifeq          15
      11: aconst_null
      12: goto          26
      15: new           #168                // class org/apache/hadoop/hbase/master/MasterCoprocessorHost$59
      18: dup
      19: aload_0
      20: aload_3
      21: aload_1
      22: aload_2
      23: invokespecial #169                // Method org/apache/hadoop/hbase/master/MasterCoprocessorHost$59."<init>":(Lorg/apache/hadoop/hbase/master/MasterCoprocessorHost;Lorg/apache/hadoop/hbase/security/User;Lorg/apache/hadoop/hbase/TableName;[B)V
      26: invokevirtual #51                 // Method execOperation:(Lorg/apache/hadoop/hbase/coprocessor/CoprocessorHost$ObserverOperation;)Z
      29: pop
      30: return

  public void postCompletedSplitRegionAction(org.apache.hadoop.hbase.client.RegionInfo, org.apache.hadoop.hbase.client.RegionInfo, org.apache.hadoop.hbase.security.User) throws java.io.IOException;
    Code:
       0: aload_0
       1: aload_0
       2: getfield      #47                 // Field coprocEnvironments:Lorg/apache/hadoop/hbase/util/SortedList;
       5: invokevirtual #48                 // Method org/apache/hadoop/hbase/util/SortedList.isEmpty:()Z
       8: ifeq          15
      11: aconst_null
      12: goto          26
      15: new           #170                // class org/apache/hadoop/hbase/master/MasterCoprocessorHost$60
      18: dup
      19: aload_0
      20: aload_3
      21: aload_1
      22: aload_2
      23: invokespecial #171                // Method org/apache/hadoop/hbase/master/MasterCoprocessorHost$60."<init>":(Lorg/apache/hadoop/hbase/master/MasterCoprocessorHost;Lorg/apache/hadoop/hbase/security/User;Lorg/apache/hadoop/hbase/client/RegionInfo;Lorg/apache/hadoop/hbase/client/RegionInfo;)V
      26: invokevirtual #51                 // Method execOperation:(Lorg/apache/hadoop/hbase/coprocessor/CoprocessorHost$ObserverOperation;)Z
      29: pop
      30: return

  public void preSplitBeforeMETAAction(byte[], java.util.List<org.apache.hadoop.hbase.client.Mutation>, org.apache.hadoop.hbase.security.User) throws java.io.IOException;
    Code:
       0: aload_0
       1: aload_0
       2: getfield      #47                 // Field coprocEnvironments:Lorg/apache/hadoop/hbase/util/SortedList;
       5: invokevirtual #48                 // Method org/apache/hadoop/hbase/util/SortedList.isEmpty:()Z
       8: ifeq          15
      11: aconst_null
      12: goto          26
      15: new           #172                // class org/apache/hadoop/hbase/master/MasterCoprocessorHost$61
      18: dup
      19: aload_0
      20: aload_3
      21: aload_1
      22: aload_2
      23: invokespecial #173                // Method org/apache/hadoop/hbase/master/MasterCoprocessorHost$61."<init>":(Lorg/apache/hadoop/hbase/master/MasterCoprocessorHost;Lorg/apache/hadoop/hbase/security/User;[BLjava/util/List;)V
      26: invokevirtual #51                 // Method execOperation:(Lorg/apache/hadoop/hbase/coprocessor/CoprocessorHost$ObserverOperation;)Z
      29: pop
      30: return

  public void preSplitAfterMETAAction(org.apache.hadoop.hbase.security.User) throws java.io.IOException;
    Code:
       0: aload_0
       1: aload_0
       2: getfield      #47                 // Field coprocEnvironments:Lorg/apache/hadoop/hbase/util/SortedList;
       5: invokevirtual #48                 // Method org/apache/hadoop/hbase/util/SortedList.isEmpty:()Z
       8: ifeq          15
      11: aconst_null
      12: goto          24
      15: new           #174                // class org/apache/hadoop/hbase/master/MasterCoprocessorHost$62
      18: dup
      19: aload_0
      20: aload_1
      21: invokespecial #175                // Method org/apache/hadoop/hbase/master/MasterCoprocessorHost$62."<init>":(Lorg/apache/hadoop/hbase/master/MasterCoprocessorHost;Lorg/apache/hadoop/hbase/security/User;)V
      24: invokevirtual #51                 // Method execOperation:(Lorg/apache/hadoop/hbase/coprocessor/CoprocessorHost$ObserverOperation;)Z
      27: pop
      28: return

  public void postRollBackSplitRegionAction(org.apache.hadoop.hbase.security.User) throws java.io.IOException;
    Code:
       0: aload_0
       1: aload_0
       2: getfield      #47                 // Field coprocEnvironments:Lorg/apache/hadoop/hbase/util/SortedList;
       5: invokevirtual #48                 // Method org/apache/hadoop/hbase/util/SortedList.isEmpty:()Z
       8: ifeq          15
      11: aconst_null
      12: goto          24
      15: new           #176                // class org/apache/hadoop/hbase/master/MasterCoprocessorHost$63
      18: dup
      19: aload_0
      20: aload_1
      21: invokespecial #177                // Method org/apache/hadoop/hbase/master/MasterCoprocessorHost$63."<init>":(Lorg/apache/hadoop/hbase/master/MasterCoprocessorHost;Lorg/apache/hadoop/hbase/security/User;)V
      24: invokevirtual #51                 // Method execOperation:(Lorg/apache/hadoop/hbase/coprocessor/CoprocessorHost$ObserverOperation;)Z
      27: pop
      28: return

  public void preMergeRegionsAction(org.apache.hadoop.hbase.client.RegionInfo[], org.apache.hadoop.hbase.security.User) throws java.io.IOException;
    Code:
       0: aload_0
       1: aload_0
       2: getfield      #47                 // Field coprocEnvironments:Lorg/apache/hadoop/hbase/util/SortedList;
       5: invokevirtual #48                 // Method org/apache/hadoop/hbase/util/SortedList.isEmpty:()Z
       8: ifeq          15
      11: aconst_null
      12: goto          25
      15: new           #178                // class org/apache/hadoop/hbase/master/MasterCoprocessorHost$64
      18: dup
      19: aload_0
      20: aload_2
      21: aload_1
      22: invokespecial #179                // Method org/apache/hadoop/hbase/master/MasterCoprocessorHost$64."<init>":(Lorg/apache/hadoop/hbase/master/MasterCoprocessorHost;Lorg/apache/hadoop/hbase/security/User;[Lorg/apache/hadoop/hbase/client/RegionInfo;)V
      25: invokevirtual #51                 // Method execOperation:(Lorg/apache/hadoop/hbase/coprocessor/CoprocessorHost$ObserverOperation;)Z
      28: pop
      29: return

  public void postCompletedMergeRegionsAction(org.apache.hadoop.hbase.client.RegionInfo[], org.apache.hadoop.hbase.client.RegionInfo, org.apache.hadoop.hbase.security.User) throws java.io.IOException;
    Code:
       0: aload_0
       1: aload_0
       2: getfield      #47                 // Field coprocEnvironments:Lorg/apache/hadoop/hbase/util/SortedList;
       5: invokevirtual #48                 // Method org/apache/hadoop/hbase/util/SortedList.isEmpty:()Z
       8: ifeq          15
      11: aconst_null
      12: goto          26
      15: new           #180                // class org/apache/hadoop/hbase/master/MasterCoprocessorHost$65
      18: dup
      19: aload_0
      20: aload_3
      21: aload_1
      22: aload_2
      23: invokespecial #181                // Method org/apache/hadoop/hbase/master/MasterCoprocessorHost$65."<init>":(Lorg/apache/hadoop/hbase/master/MasterCoprocessorHost;Lorg/apache/hadoop/hbase/security/User;[Lorg/apache/hadoop/hbase/client/RegionInfo;Lorg/apache/hadoop/hbase/client/RegionInfo;)V
      26: invokevirtual #51                 // Method execOperation:(Lorg/apache/hadoop/hbase/coprocessor/CoprocessorHost$ObserverOperation;)Z
      29: pop
      30: return

  public void preMergeRegionsCommit(org.apache.hadoop.hbase.client.RegionInfo[], java.util.List<org.apache.hadoop.hbase.client.Mutation>, org.apache.hadoop.hbase.security.User) throws java.io.IOException;
    Code:
       0: aload_0
       1: aload_0
       2: getfield      #47                 // Field coprocEnvironments:Lorg/apache/hadoop/hbase/util/SortedList;
       5: invokevirtual #48                 // Method org/apache/hadoop/hbase/util/SortedList.isEmpty:()Z
       8: ifeq          15
      11: aconst_null
      12: goto          26
      15: new           #182                // class org/apache/hadoop/hbase/master/MasterCoprocessorHost$66
      18: dup
      19: aload_0
      20: aload_3
      21: aload_1
      22: aload_2
      23: invokespecial #183                // Method org/apache/hadoop/hbase/master/MasterCoprocessorHost$66."<init>":(Lorg/apache/hadoop/hbase/master/MasterCoprocessorHost;Lorg/apache/hadoop/hbase/security/User;[Lorg/apache/hadoop/hbase/client/RegionInfo;Ljava/util/List;)V
      26: invokevirtual #51                 // Method execOperation:(Lorg/apache/hadoop/hbase/coprocessor/CoprocessorHost$ObserverOperation;)Z
      29: pop
      30: return

  public void postMergeRegionsCommit(org.apache.hadoop.hbase.client.RegionInfo[], org.apache.hadoop.hbase.client.RegionInfo, org.apache.hadoop.hbase.security.User) throws java.io.IOException;
    Code:
       0: aload_0
       1: aload_0
       2: getfield      #47                 // Field coprocEnvironments:Lorg/apache/hadoop/hbase/util/SortedList;
       5: invokevirtual #48                 // Method org/apache/hadoop/hbase/util/SortedList.isEmpty:()Z
       8: ifeq          15
      11: aconst_null
      12: goto          26
      15: new           #184                // class org/apache/hadoop/hbase/master/MasterCoprocessorHost$67
      18: dup
      19: aload_0
      20: aload_3
      21: aload_1
      22: aload_2
      23: invokespecial #185                // Method org/apache/hadoop/hbase/master/MasterCoprocessorHost$67."<init>":(Lorg/apache/hadoop/hbase/master/MasterCoprocessorHost;Lorg/apache/hadoop/hbase/security/User;[Lorg/apache/hadoop/hbase/client/RegionInfo;Lorg/apache/hadoop/hbase/client/RegionInfo;)V
      26: invokevirtual #51                 // Method execOperation:(Lorg/apache/hadoop/hbase/coprocessor/CoprocessorHost$ObserverOperation;)Z
      29: pop
      30: return

  public void postRollBackMergeRegionsAction(org.apache.hadoop.hbase.client.RegionInfo[], org.apache.hadoop.hbase.security.User) throws java.io.IOException;
    Code:
       0: aload_0
       1: aload_0
       2: getfield      #47                 // Field coprocEnvironments:Lorg/apache/hadoop/hbase/util/SortedList;
       5: invokevirtual #48                 // Method org/apache/hadoop/hbase/util/SortedList.isEmpty:()Z
       8: ifeq          15
      11: aconst_null
      12: goto          25
      15: new           #186                // class org/apache/hadoop/hbase/master/MasterCoprocessorHost$68
      18: dup
      19: aload_0
      20: aload_2
      21: aload_1
      22: invokespecial #187                // Method org/apache/hadoop/hbase/master/MasterCoprocessorHost$68."<init>":(Lorg/apache/hadoop/hbase/master/MasterCoprocessorHost;Lorg/apache/hadoop/hbase/security/User;[Lorg/apache/hadoop/hbase/client/RegionInfo;)V
      25: invokevirtual #51                 // Method execOperation:(Lorg/apache/hadoop/hbase/coprocessor/CoprocessorHost$ObserverOperation;)Z
      28: pop
      29: return

  public void preBalanceSwitch(boolean) throws java.io.IOException;
    Code:
       0: aload_0
       1: getfield      #47                 // Field coprocEnvironments:Lorg/apache/hadoop/hbase/util/SortedList;
       4: invokevirtual #48                 // Method org/apache/hadoop/hbase/util/SortedList.isEmpty:()Z
       7: ifeq          11
      10: return
      11: aload_0
      12: new           #188                // class org/apache/hadoop/hbase/master/MasterCoprocessorHost$69
      15: dup
      16: aload_0
      17: iload_1
      18: invokespecial #189                // Method org/apache/hadoop/hbase/master/MasterCoprocessorHost$69."<init>":(Lorg/apache/hadoop/hbase/master/MasterCoprocessorHost;Z)V
      21: invokevirtual #51                 // Method execOperation:(Lorg/apache/hadoop/hbase/coprocessor/CoprocessorHost$ObserverOperation;)Z
      24: pop
      25: return

  public void postBalanceSwitch(boolean, boolean) throws java.io.IOException;
    Code:
       0: aload_0
       1: aload_0
       2: getfield      #47                 // Field coprocEnvironments:Lorg/apache/hadoop/hbase/util/SortedList;
       5: invokevirtual #48                 // Method org/apache/hadoop/hbase/util/SortedList.isEmpty:()Z
       8: ifeq          15
      11: aconst_null
      12: goto          25
      15: new           #190                // class org/apache/hadoop/hbase/master/MasterCoprocessorHost$70
      18: dup
      19: aload_0
      20: iload_1
      21: iload_2
      22: invokespecial #191                // Method org/apache/hadoop/hbase/master/MasterCoprocessorHost$70."<init>":(Lorg/apache/hadoop/hbase/master/MasterCoprocessorHost;ZZ)V
      25: invokevirtual #51                 // Method execOperation:(Lorg/apache/hadoop/hbase/coprocessor/CoprocessorHost$ObserverOperation;)Z
      28: pop
      29: return

  public void preShutdown() throws java.io.IOException;
    Code:
       0: aload_0
       1: getfield      #47                 // Field coprocEnvironments:Lorg/apache/hadoop/hbase/util/SortedList;
       4: invokevirtual #48                 // Method org/apache/hadoop/hbase/util/SortedList.isEmpty:()Z
       7: ifeq          11
      10: return
      11: aload_0
      12: new           #192                // class org/apache/hadoop/hbase/master/MasterCoprocessorHost$71
      15: dup
      16: aload_0
      17: invokespecial #193                // Method org/apache/hadoop/hbase/master/MasterCoprocessorHost$71."<init>":(Lorg/apache/hadoop/hbase/master/MasterCoprocessorHost;)V
      20: invokevirtual #194                // Method execShutdown:(Lorg/apache/hadoop/hbase/coprocessor/CoprocessorHost$ObserverOperation;)Z
      23: pop
      24: return

  public void preStopMaster() throws java.io.IOException;
    Code:
       0: aload_0
       1: getfield      #47                 // Field coprocEnvironments:Lorg/apache/hadoop/hbase/util/SortedList;
       4: invokevirtual #48                 // Method org/apache/hadoop/hbase/util/SortedList.isEmpty:()Z
       7: ifeq          11
      10: return
      11: aload_0
      12: new           #195                // class org/apache/hadoop/hbase/master/MasterCoprocessorHost$72
      15: dup
      16: aload_0
      17: invokespecial #196                // Method org/apache/hadoop/hbase/master/MasterCoprocessorHost$72."<init>":(Lorg/apache/hadoop/hbase/master/MasterCoprocessorHost;)V
      20: invokevirtual #194                // Method execShutdown:(Lorg/apache/hadoop/hbase/coprocessor/CoprocessorHost$ObserverOperation;)Z
      23: pop
      24: return

  public void preMasterInitialization() throws java.io.IOException;
    Code:
       0: aload_0
       1: aload_0
       2: getfield      #47                 // Field coprocEnvironments:Lorg/apache/hadoop/hbase/util/SortedList;
       5: invokevirtual #48                 // Method org/apache/hadoop/hbase/util/SortedList.isEmpty:()Z
       8: ifeq          15
      11: aconst_null
      12: goto          23
      15: new           #197                // class org/apache/hadoop/hbase/master/MasterCoprocessorHost$73
      18: dup
      19: aload_0
      20: invokespecial #198                // Method org/apache/hadoop/hbase/master/MasterCoprocessorHost$73."<init>":(Lorg/apache/hadoop/hbase/master/MasterCoprocessorHost;)V
      23: invokevirtual #51                 // Method execOperation:(Lorg/apache/hadoop/hbase/coprocessor/CoprocessorHost$ObserverOperation;)Z
      26: pop
      27: return

  public void postStartMaster() throws java.io.IOException;
    Code:
       0: aload_0
       1: aload_0
       2: getfield      #47                 // Field coprocEnvironments:Lorg/apache/hadoop/hbase/util/SortedList;
       5: invokevirtual #48                 // Method org/apache/hadoop/hbase/util/SortedList.isEmpty:()Z
       8: ifeq          15
      11: aconst_null
      12: goto          23
      15: new           #199                // class org/apache/hadoop/hbase/master/MasterCoprocessorHost$74
      18: dup
      19: aload_0
      20: invokespecial #200                // Method org/apache/hadoop/hbase/master/MasterCoprocessorHost$74."<init>":(Lorg/apache/hadoop/hbase/master/MasterCoprocessorHost;)V
      23: invokevirtual #51                 // Method execOperation:(Lorg/apache/hadoop/hbase/coprocessor/CoprocessorHost$ObserverOperation;)Z
      26: pop
      27: return

  public void preSnapshot(org.apache.hadoop.hbase.client.SnapshotDescription, org.apache.hadoop.hbase.client.TableDescriptor) throws java.io.IOException;
    Code:
       0: aload_0
       1: aload_0
       2: getfield      #47                 // Field coprocEnvironments:Lorg/apache/hadoop/hbase/util/SortedList;
       5: invokevirtual #48                 // Method org/apache/hadoop/hbase/util/SortedList.isEmpty:()Z
       8: ifeq          15
      11: aconst_null
      12: goto          25
      15: new           #201                // class org/apache/hadoop/hbase/master/MasterCoprocessorHost$75
      18: dup
      19: aload_0
      20: aload_1
      21: aload_2
      22: invokespecial #202                // Method org/apache/hadoop/hbase/master/MasterCoprocessorHost$75."<init>":(Lorg/apache/hadoop/hbase/master/MasterCoprocessorHost;Lorg/apache/hadoop/hbase/client/SnapshotDescription;Lorg/apache/hadoop/hbase/client/TableDescriptor;)V
      25: invokevirtual #51                 // Method execOperation:(Lorg/apache/hadoop/hbase/coprocessor/CoprocessorHost$ObserverOperation;)Z
      28: pop
      29: return

  public void postSnapshot(org.apache.hadoop.hbase.client.SnapshotDescription, org.apache.hadoop.hbase.client.TableDescriptor) throws java.io.IOException;
    Code:
       0: aload_0
       1: aload_0
       2: getfield      #47                 // Field coprocEnvironments:Lorg/apache/hadoop/hbase/util/SortedList;
       5: invokevirtual #48                 // Method org/apache/hadoop/hbase/util/SortedList.isEmpty:()Z
       8: ifeq          15
      11: aconst_null
      12: goto          25
      15: new           #203                // class org/apache/hadoop/hbase/master/MasterCoprocessorHost$76
      18: dup
      19: aload_0
      20: aload_1
      21: aload_2
      22: invokespecial #204                // Method org/apache/hadoop/hbase/master/MasterCoprocessorHost$76."<init>":(Lorg/apache/hadoop/hbase/master/MasterCoprocessorHost;Lorg/apache/hadoop/hbase/client/SnapshotDescription;Lorg/apache/hadoop/hbase/client/TableDescriptor;)V
      25: invokevirtual #51                 // Method execOperation:(Lorg/apache/hadoop/hbase/coprocessor/CoprocessorHost$ObserverOperation;)Z
      28: pop
      29: return

  public void preListSnapshot(org.apache.hadoop.hbase.client.SnapshotDescription) throws java.io.IOException;
    Code:
       0: aload_0
       1: aload_0
       2: getfield      #47                 // Field coprocEnvironments:Lorg/apache/hadoop/hbase/util/SortedList;
       5: invokevirtual #48                 // Method org/apache/hadoop/hbase/util/SortedList.isEmpty:()Z
       8: ifeq          15
      11: aconst_null
      12: goto          24
      15: new           #205                // class org/apache/hadoop/hbase/master/MasterCoprocessorHost$77
      18: dup
      19: aload_0
      20: aload_1
      21: invokespecial #206                // Method org/apache/hadoop/hbase/master/MasterCoprocessorHost$77."<init>":(Lorg/apache/hadoop/hbase/master/MasterCoprocessorHost;Lorg/apache/hadoop/hbase/client/SnapshotDescription;)V
      24: invokevirtual #51                 // Method execOperation:(Lorg/apache/hadoop/hbase/coprocessor/CoprocessorHost$ObserverOperation;)Z
      27: pop
      28: return

  public void postListSnapshot(org.apache.hadoop.hbase.client.SnapshotDescription) throws java.io.IOException;
    Code:
       0: aload_0
       1: aload_0
       2: getfield      #47                 // Field coprocEnvironments:Lorg/apache/hadoop/hbase/util/SortedList;
       5: invokevirtual #48                 // Method org/apache/hadoop/hbase/util/SortedList.isEmpty:()Z
       8: ifeq          15
      11: aconst_null
      12: goto          24
      15: new           #207                // class org/apache/hadoop/hbase/master/MasterCoprocessorHost$78
      18: dup
      19: aload_0
      20: aload_1
      21: invokespecial #208                // Method org/apache/hadoop/hbase/master/MasterCoprocessorHost$78."<init>":(Lorg/apache/hadoop/hbase/master/MasterCoprocessorHost;Lorg/apache/hadoop/hbase/client/SnapshotDescription;)V
      24: invokevirtual #51                 // Method execOperation:(Lorg/apache/hadoop/hbase/coprocessor/CoprocessorHost$ObserverOperation;)Z
      27: pop
      28: return

  public void preCloneSnapshot(org.apache.hadoop.hbase.client.SnapshotDescription, org.apache.hadoop.hbase.client.TableDescriptor) throws java.io.IOException;
    Code:
       0: aload_0
       1: aload_0
       2: getfield      #47                 // Field coprocEnvironments:Lorg/apache/hadoop/hbase/util/SortedList;
       5: invokevirtual #48                 // Method org/apache/hadoop/hbase/util/SortedList.isEmpty:()Z
       8: ifeq          15
      11: aconst_null
      12: goto          25
      15: new           #209                // class org/apache/hadoop/hbase/master/MasterCoprocessorHost$79
      18: dup
      19: aload_0
      20: aload_1
      21: aload_2
      22: invokespecial #210                // Method org/apache/hadoop/hbase/master/MasterCoprocessorHost$79."<init>":(Lorg/apache/hadoop/hbase/master/MasterCoprocessorHost;Lorg/apache/hadoop/hbase/client/SnapshotDescription;Lorg/apache/hadoop/hbase/client/TableDescriptor;)V
      25: invokevirtual #51                 // Method execOperation:(Lorg/apache/hadoop/hbase/coprocessor/CoprocessorHost$ObserverOperation;)Z
      28: pop
      29: return

  public void postCloneSnapshot(org.apache.hadoop.hbase.client.SnapshotDescription, org.apache.hadoop.hbase.client.TableDescriptor) throws java.io.IOException;
    Code:
       0: aload_0
       1: aload_0
       2: getfield      #47                 // Field coprocEnvironments:Lorg/apache/hadoop/hbase/util/SortedList;
       5: invokevirtual #48                 // Method org/apache/hadoop/hbase/util/SortedList.isEmpty:()Z
       8: ifeq          15
      11: aconst_null
      12: goto          25
      15: new           #211                // class org/apache/hadoop/hbase/master/MasterCoprocessorHost$80
      18: dup
      19: aload_0
      20: aload_1
      21: aload_2
      22: invokespecial #212                // Method org/apache/hadoop/hbase/master/MasterCoprocessorHost$80."<init>":(Lorg/apache/hadoop/hbase/master/MasterCoprocessorHost;Lorg/apache/hadoop/hbase/client/SnapshotDescription;Lorg/apache/hadoop/hbase/client/TableDescriptor;)V
      25: invokevirtual #51                 // Method execOperation:(Lorg/apache/hadoop/hbase/coprocessor/CoprocessorHost$ObserverOperation;)Z
      28: pop
      29: return

  public void preRestoreSnapshot(org.apache.hadoop.hbase.client.SnapshotDescription, org.apache.hadoop.hbase.client.TableDescriptor) throws java.io.IOException;
    Code:
       0: aload_0
       1: aload_0
       2: getfield      #47                 // Field coprocEnvironments:Lorg/apache/hadoop/hbase/util/SortedList;
       5: invokevirtual #48                 // Method org/apache/hadoop/hbase/util/SortedList.isEmpty:()Z
       8: ifeq          15
      11: aconst_null
      12: goto          25
      15: new           #213                // class org/apache/hadoop/hbase/master/MasterCoprocessorHost$81
      18: dup
      19: aload_0
      20: aload_1
      21: aload_2
      22: invokespecial #214                // Method org/apache/hadoop/hbase/master/MasterCoprocessorHost$81."<init>":(Lorg/apache/hadoop/hbase/master/MasterCoprocessorHost;Lorg/apache/hadoop/hbase/client/SnapshotDescription;Lorg/apache/hadoop/hbase/client/TableDescriptor;)V
      25: invokevirtual #51                 // Method execOperation:(Lorg/apache/hadoop/hbase/coprocessor/CoprocessorHost$ObserverOperation;)Z
      28: pop
      29: return

  public void postRestoreSnapshot(org.apache.hadoop.hbase.client.SnapshotDescription, org.apache.hadoop.hbase.client.TableDescriptor) throws java.io.IOException;
    Code:
       0: aload_0
       1: aload_0
       2: getfield      #47                 // Field coprocEnvironments:Lorg/apache/hadoop/hbase/util/SortedList;
       5: invokevirtual #48                 // Method org/apache/hadoop/hbase/util/SortedList.isEmpty:()Z
       8: ifeq          15
      11: aconst_null
      12: goto          25
      15: new           #215                // class org/apache/hadoop/hbase/master/MasterCoprocessorHost$82
      18: dup
      19: aload_0
      20: aload_1
      21: aload_2
      22: invokespecial #216                // Method org/apache/hadoop/hbase/master/MasterCoprocessorHost$82."<init>":(Lorg/apache/hadoop/hbase/master/MasterCoprocessorHost;Lorg/apache/hadoop/hbase/client/SnapshotDescription;Lorg/apache/hadoop/hbase/client/TableDescriptor;)V
      25: invokevirtual #51                 // Method execOperation:(Lorg/apache/hadoop/hbase/coprocessor/CoprocessorHost$ObserverOperation;)Z
      28: pop
      29: return

  public void preDeleteSnapshot(org.apache.hadoop.hbase.client.SnapshotDescription) throws java.io.IOException;
    Code:
       0: aload_0
       1: aload_0
       2: getfield      #47                 // Field coprocEnvironments:Lorg/apache/hadoop/hbase/util/SortedList;
       5: invokevirtual #48                 // Method org/apache/hadoop/hbase/util/SortedList.isEmpty:()Z
       8: ifeq          15
      11: aconst_null
      12: goto          24
      15: new           #217                // class org/apache/hadoop/hbase/master/MasterCoprocessorHost$83
      18: dup
      19: aload_0
      20: aload_1
      21: invokespecial #218                // Method org/apache/hadoop/hbase/master/MasterCoprocessorHost$83."<init>":(Lorg/apache/hadoop/hbase/master/MasterCoprocessorHost;Lorg/apache/hadoop/hbase/client/SnapshotDescription;)V
      24: invokevirtual #51                 // Method execOperation:(Lorg/apache/hadoop/hbase/coprocessor/CoprocessorHost$ObserverOperation;)Z
      27: pop
      28: return

  public void postDeleteSnapshot(org.apache.hadoop.hbase.client.SnapshotDescription) throws java.io.IOException;
    Code:
       0: aload_0
       1: aload_0
       2: getfield      #47                 // Field coprocEnvironments:Lorg/apache/hadoop/hbase/util/SortedList;
       5: invokevirtual #48                 // Method org/apache/hadoop/hbase/util/SortedList.isEmpty:()Z
       8: ifeq          15
      11: aconst_null
      12: goto          24
      15: new           #219                // class org/apache/hadoop/hbase/master/MasterCoprocessorHost$84
      18: dup
      19: aload_0
      20: aload_1
      21: invokespecial #220                // Method org/apache/hadoop/hbase/master/MasterCoprocessorHost$84."<init>":(Lorg/apache/hadoop/hbase/master/MasterCoprocessorHost;Lorg/apache/hadoop/hbase/client/SnapshotDescription;)V
      24: invokevirtual #51                 // Method execOperation:(Lorg/apache/hadoop/hbase/coprocessor/CoprocessorHost$ObserverOperation;)Z
      27: pop
      28: return

  public void preGetTableDescriptors(java.util.List<org.apache.hadoop.hbase.TableName>, java.util.List<org.apache.hadoop.hbase.client.TableDescriptor>, java.lang.String) throws java.io.IOException;
    Code:
       0: aload_0
       1: aload_0
       2: getfield      #47                 // Field coprocEnvironments:Lorg/apache/hadoop/hbase/util/SortedList;
       5: invokevirtual #48                 // Method org/apache/hadoop/hbase/util/SortedList.isEmpty:()Z
       8: ifeq          15
      11: aconst_null
      12: goto          26
      15: new           #221                // class org/apache/hadoop/hbase/master/MasterCoprocessorHost$85
      18: dup
      19: aload_0
      20: aload_1
      21: aload_2
      22: aload_3
      23: invokespecial #222                // Method org/apache/hadoop/hbase/master/MasterCoprocessorHost$85."<init>":(Lorg/apache/hadoop/hbase/master/MasterCoprocessorHost;Ljava/util/List;Ljava/util/List;Ljava/lang/String;)V
      26: invokevirtual #51                 // Method execOperation:(Lorg/apache/hadoop/hbase/coprocessor/CoprocessorHost$ObserverOperation;)Z
      29: pop
      30: return

  public void postGetTableDescriptors(java.util.List<org.apache.hadoop.hbase.TableName>, java.util.List<org.apache.hadoop.hbase.client.TableDescriptor>, java.lang.String) throws java.io.IOException;
    Code:
       0: aload_0
       1: aload_0
       2: getfield      #47                 // Field coprocEnvironments:Lorg/apache/hadoop/hbase/util/SortedList;
       5: invokevirtual #48                 // Method org/apache/hadoop/hbase/util/SortedList.isEmpty:()Z
       8: ifeq          15
      11: aconst_null
      12: goto          26
      15: new           #223                // class org/apache/hadoop/hbase/master/MasterCoprocessorHost$86
      18: dup
      19: aload_0
      20: aload_1
      21: aload_2
      22: aload_3
      23: invokespecial #224                // Method org/apache/hadoop/hbase/master/MasterCoprocessorHost$86."<init>":(Lorg/apache/hadoop/hbase/master/MasterCoprocessorHost;Ljava/util/List;Ljava/util/List;Ljava/lang/String;)V
      26: invokevirtual #51                 // Method execOperation:(Lorg/apache/hadoop/hbase/coprocessor/CoprocessorHost$ObserverOperation;)Z
      29: pop
      30: return

  public void preGetTableNames(java.util.List<org.apache.hadoop.hbase.client.TableDescriptor>, java.lang.String) throws java.io.IOException;
    Code:
       0: aload_0
       1: aload_0
       2: getfield      #47                 // Field coprocEnvironments:Lorg/apache/hadoop/hbase/util/SortedList;
       5: invokevirtual #48                 // Method org/apache/hadoop/hbase/util/SortedList.isEmpty:()Z
       8: ifeq          15
      11: aconst_null
      12: goto          25
      15: new           #225                // class org/apache/hadoop/hbase/master/MasterCoprocessorHost$87
      18: dup
      19: aload_0
      20: aload_1
      21: aload_2
      22: invokespecial #226                // Method org/apache/hadoop/hbase/master/MasterCoprocessorHost$87."<init>":(Lorg/apache/hadoop/hbase/master/MasterCoprocessorHost;Ljava/util/List;Ljava/lang/String;)V
      25: invokevirtual #51                 // Method execOperation:(Lorg/apache/hadoop/hbase/coprocessor/CoprocessorHost$ObserverOperation;)Z
      28: pop
      29: return

  public void postGetTableNames(java.util.List<org.apache.hadoop.hbase.client.TableDescriptor>, java.lang.String) throws java.io.IOException;
    Code:
       0: aload_0
       1: aload_0
       2: getfield      #47                 // Field coprocEnvironments:Lorg/apache/hadoop/hbase/util/SortedList;
       5: invokevirtual #48                 // Method org/apache/hadoop/hbase/util/SortedList.isEmpty:()Z
       8: ifeq          15
      11: aconst_null
      12: goto          25
      15: new           #227                // class org/apache/hadoop/hbase/master/MasterCoprocessorHost$88
      18: dup
      19: aload_0
      20: aload_1
      21: aload_2
      22: invokespecial #228                // Method org/apache/hadoop/hbase/master/MasterCoprocessorHost$88."<init>":(Lorg/apache/hadoop/hbase/master/MasterCoprocessorHost;Ljava/util/List;Ljava/lang/String;)V
      25: invokevirtual #51                 // Method execOperation:(Lorg/apache/hadoop/hbase/coprocessor/CoprocessorHost$ObserverOperation;)Z
      28: pop
      29: return

  public void preTableFlush(org.apache.hadoop.hbase.TableName) throws java.io.IOException;
    Code:
       0: aload_0
       1: aload_0
       2: getfield      #47                 // Field coprocEnvironments:Lorg/apache/hadoop/hbase/util/SortedList;
       5: invokevirtual #48                 // Method org/apache/hadoop/hbase/util/SortedList.isEmpty:()Z
       8: ifeq          15
      11: aconst_null
      12: goto          24
      15: new           #229                // class org/apache/hadoop/hbase/master/MasterCoprocessorHost$89
      18: dup
      19: aload_0
      20: aload_1
      21: invokespecial #230                // Method org/apache/hadoop/hbase/master/MasterCoprocessorHost$89."<init>":(Lorg/apache/hadoop/hbase/master/MasterCoprocessorHost;Lorg/apache/hadoop/hbase/TableName;)V
      24: invokevirtual #51                 // Method execOperation:(Lorg/apache/hadoop/hbase/coprocessor/CoprocessorHost$ObserverOperation;)Z
      27: pop
      28: return

  public void postTableFlush(org.apache.hadoop.hbase.TableName) throws java.io.IOException;
    Code:
       0: aload_0
       1: aload_0
       2: getfield      #47                 // Field coprocEnvironments:Lorg/apache/hadoop/hbase/util/SortedList;
       5: invokevirtual #48                 // Method org/apache/hadoop/hbase/util/SortedList.isEmpty:()Z
       8: ifeq          15
      11: aconst_null
      12: goto          24
      15: new           #231                // class org/apache/hadoop/hbase/master/MasterCoprocessorHost$90
      18: dup
      19: aload_0
      20: aload_1
      21: invokespecial #232                // Method org/apache/hadoop/hbase/master/MasterCoprocessorHost$90."<init>":(Lorg/apache/hadoop/hbase/master/MasterCoprocessorHost;Lorg/apache/hadoop/hbase/TableName;)V
      24: invokevirtual #51                 // Method execOperation:(Lorg/apache/hadoop/hbase/coprocessor/CoprocessorHost$ObserverOperation;)Z
      27: pop
      28: return

  public void preSetUserQuota(java.lang.String, org.apache.hadoop.hbase.quotas.GlobalQuotaSettings) throws java.io.IOException;
    Code:
       0: aload_0
       1: aload_0
       2: getfield      #47                 // Field coprocEnvironments:Lorg/apache/hadoop/hbase/util/SortedList;
       5: invokevirtual #48                 // Method org/apache/hadoop/hbase/util/SortedList.isEmpty:()Z
       8: ifeq          15
      11: aconst_null
      12: goto          25
      15: new           #233                // class org/apache/hadoop/hbase/master/MasterCoprocessorHost$91
      18: dup
      19: aload_0
      20: aload_1
      21: aload_2
      22: invokespecial #234                // Method org/apache/hadoop/hbase/master/MasterCoprocessorHost$91."<init>":(Lorg/apache/hadoop/hbase/master/MasterCoprocessorHost;Ljava/lang/String;Lorg/apache/hadoop/hbase/quotas/GlobalQuotaSettings;)V
      25: invokevirtual #51                 // Method execOperation:(Lorg/apache/hadoop/hbase/coprocessor/CoprocessorHost$ObserverOperation;)Z
      28: pop
      29: return

  public void postSetUserQuota(java.lang.String, org.apache.hadoop.hbase.quotas.GlobalQuotaSettings) throws java.io.IOException;
    Code:
       0: aload_0
       1: aload_0
       2: getfield      #47                 // Field coprocEnvironments:Lorg/apache/hadoop/hbase/util/SortedList;
       5: invokevirtual #48                 // Method org/apache/hadoop/hbase/util/SortedList.isEmpty:()Z
       8: ifeq          15
      11: aconst_null
      12: goto          25
      15: new           #235                // class org/apache/hadoop/hbase/master/MasterCoprocessorHost$92
      18: dup
      19: aload_0
      20: aload_1
      21: aload_2
      22: invokespecial #236                // Method org/apache/hadoop/hbase/master/MasterCoprocessorHost$92."<init>":(Lorg/apache/hadoop/hbase/master/MasterCoprocessorHost;Ljava/lang/String;Lorg/apache/hadoop/hbase/quotas/GlobalQuotaSettings;)V
      25: invokevirtual #51                 // Method execOperation:(Lorg/apache/hadoop/hbase/coprocessor/CoprocessorHost$ObserverOperation;)Z
      28: pop
      29: return

  public void preSetUserQuota(java.lang.String, org.apache.hadoop.hbase.TableName, org.apache.hadoop.hbase.quotas.GlobalQuotaSettings) throws java.io.IOException;
    Code:
       0: aload_0
       1: aload_0
       2: getfield      #47                 // Field coprocEnvironments:Lorg/apache/hadoop/hbase/util/SortedList;
       5: invokevirtual #48                 // Method org/apache/hadoop/hbase/util/SortedList.isEmpty:()Z
       8: ifeq          15
      11: aconst_null
      12: goto          26
      15: new           #237                // class org/apache/hadoop/hbase/master/MasterCoprocessorHost$93
      18: dup
      19: aload_0
      20: aload_1
      21: aload_2
      22: aload_3
      23: invokespecial #238                // Method org/apache/hadoop/hbase/master/MasterCoprocessorHost$93."<init>":(Lorg/apache/hadoop/hbase/master/MasterCoprocessorHost;Ljava/lang/String;Lorg/apache/hadoop/hbase/TableName;Lorg/apache/hadoop/hbase/quotas/GlobalQuotaSettings;)V
      26: invokevirtual #51                 // Method execOperation:(Lorg/apache/hadoop/hbase/coprocessor/CoprocessorHost$ObserverOperation;)Z
      29: pop
      30: return

  public void postSetUserQuota(java.lang.String, org.apache.hadoop.hbase.TableName, org.apache.hadoop.hbase.quotas.GlobalQuotaSettings) throws java.io.IOException;
    Code:
       0: aload_0
       1: aload_0
       2: getfield      #47                 // Field coprocEnvironments:Lorg/apache/hadoop/hbase/util/SortedList;
       5: invokevirtual #48                 // Method org/apache/hadoop/hbase/util/SortedList.isEmpty:()Z
       8: ifeq          15
      11: aconst_null
      12: goto          26
      15: new           #239                // class org/apache/hadoop/hbase/master/MasterCoprocessorHost$94
      18: dup
      19: aload_0
      20: aload_1
      21: aload_2
      22: aload_3
      23: invokespecial #240                // Method org/apache/hadoop/hbase/master/MasterCoprocessorHost$94."<init>":(Lorg/apache/hadoop/hbase/master/MasterCoprocessorHost;Ljava/lang/String;Lorg/apache/hadoop/hbase/TableName;Lorg/apache/hadoop/hbase/quotas/GlobalQuotaSettings;)V
      26: invokevirtual #51                 // Method execOperation:(Lorg/apache/hadoop/hbase/coprocessor/CoprocessorHost$ObserverOperation;)Z
      29: pop
      30: return

  public void preSetUserQuota(java.lang.String, java.lang.String, org.apache.hadoop.hbase.quotas.GlobalQuotaSettings) throws java.io.IOException;
    Code:
       0: aload_0
       1: aload_0
       2: getfield      #47                 // Field coprocEnvironments:Lorg/apache/hadoop/hbase/util/SortedList;
       5: invokevirtual #48                 // Method org/apache/hadoop/hbase/util/SortedList.isEmpty:()Z
       8: ifeq          15
      11: aconst_null
      12: goto          26
      15: new           #241                // class org/apache/hadoop/hbase/master/MasterCoprocessorHost$95
      18: dup
      19: aload_0
      20: aload_1
      21: aload_2
      22: aload_3
      23: invokespecial #242                // Method org/apache/hadoop/hbase/master/MasterCoprocessorHost$95."<init>":(Lorg/apache/hadoop/hbase/master/MasterCoprocessorHost;Ljava/lang/String;Ljava/lang/String;Lorg/apache/hadoop/hbase/quotas/GlobalQuotaSettings;)V
      26: invokevirtual #51                 // Method execOperation:(Lorg/apache/hadoop/hbase/coprocessor/CoprocessorHost$ObserverOperation;)Z
      29: pop
      30: return

  public void postSetUserQuota(java.lang.String, java.lang.String, org.apache.hadoop.hbase.quotas.GlobalQuotaSettings) throws java.io.IOException;
    Code:
       0: aload_0
       1: aload_0
       2: getfield      #47                 // Field coprocEnvironments:Lorg/apache/hadoop/hbase/util/SortedList;
       5: invokevirtual #48                 // Method org/apache/hadoop/hbase/util/SortedList.isEmpty:()Z
       8: ifeq          15
      11: aconst_null
      12: goto          26
      15: new           #243                // class org/apache/hadoop/hbase/master/MasterCoprocessorHost$96
      18: dup
      19: aload_0
      20: aload_1
      21: aload_2
      22: aload_3
      23: invokespecial #244                // Method org/apache/hadoop/hbase/master/MasterCoprocessorHost$96."<init>":(Lorg/apache/hadoop/hbase/master/MasterCoprocessorHost;Ljava/lang/String;Ljava/lang/String;Lorg/apache/hadoop/hbase/quotas/GlobalQuotaSettings;)V
      26: invokevirtual #51                 // Method execOperation:(Lorg/apache/hadoop/hbase/coprocessor/CoprocessorHost$ObserverOperation;)Z
      29: pop
      30: return

  public void preSetTableQuota(org.apache.hadoop.hbase.TableName, org.apache.hadoop.hbase.quotas.GlobalQuotaSettings) throws java.io.IOException;
    Code:
       0: aload_0
       1: aload_0
       2: getfield      #47                 // Field coprocEnvironments:Lorg/apache/hadoop/hbase/util/SortedList;
       5: invokevirtual #48                 // Method org/apache/hadoop/hbase/util/SortedList.isEmpty:()Z
       8: ifeq          15
      11: aconst_null
      12: goto          25
      15: new           #245                // class org/apache/hadoop/hbase/master/MasterCoprocessorHost$97
      18: dup
      19: aload_0
      20: aload_1
      21: aload_2
      22: invokespecial #246                // Method org/apache/hadoop/hbase/master/MasterCoprocessorHost$97."<init>":(Lorg/apache/hadoop/hbase/master/MasterCoprocessorHost;Lorg/apache/hadoop/hbase/TableName;Lorg/apache/hadoop/hbase/quotas/GlobalQuotaSettings;)V
      25: invokevirtual #51                 // Method execOperation:(Lorg/apache/hadoop/hbase/coprocessor/CoprocessorHost$ObserverOperation;)Z
      28: pop
      29: return

  public void postSetTableQuota(org.apache.hadoop.hbase.TableName, org.apache.hadoop.hbase.quotas.GlobalQuotaSettings) throws java.io.IOException;
    Code:
       0: aload_0
       1: aload_0
       2: getfield      #47                 // Field coprocEnvironments:Lorg/apache/hadoop/hbase/util/SortedList;
       5: invokevirtual #48                 // Method org/apache/hadoop/hbase/util/SortedList.isEmpty:()Z
       8: ifeq          15
      11: aconst_null
      12: goto          25
      15: new           #247                // class org/apache/hadoop/hbase/master/MasterCoprocessorHost$98
      18: dup
      19: aload_0
      20: aload_1
      21: aload_2
      22: invokespecial #248                // Method org/apache/hadoop/hbase/master/MasterCoprocessorHost$98."<init>":(Lorg/apache/hadoop/hbase/master/MasterCoprocessorHost;Lorg/apache/hadoop/hbase/TableName;Lorg/apache/hadoop/hbase/quotas/GlobalQuotaSettings;)V
      25: invokevirtual #51                 // Method execOperation:(Lorg/apache/hadoop/hbase/coprocessor/CoprocessorHost$ObserverOperation;)Z
      28: pop
      29: return

  public void preSetNamespaceQuota(java.lang.String, org.apache.hadoop.hbase.quotas.GlobalQuotaSettings) throws java.io.IOException;
    Code:
       0: aload_0
       1: aload_0
       2: getfield      #47                 // Field coprocEnvironments:Lorg/apache/hadoop/hbase/util/SortedList;
       5: invokevirtual #48                 // Method org/apache/hadoop/hbase/util/SortedList.isEmpty:()Z
       8: ifeq          15
      11: aconst_null
      12: goto          25
      15: new           #249                // class org/apache/hadoop/hbase/master/MasterCoprocessorHost$99
      18: dup
      19: aload_0
      20: aload_1
      21: aload_2
      22: invokespecial #250                // Method org/apache/hadoop/hbase/master/MasterCoprocessorHost$99."<init>":(Lorg/apache/hadoop/hbase/master/MasterCoprocessorHost;Ljava/lang/String;Lorg/apache/hadoop/hbase/quotas/GlobalQuotaSettings;)V
      25: invokevirtual #51                 // Method execOperation:(Lorg/apache/hadoop/hbase/coprocessor/CoprocessorHost$ObserverOperation;)Z
      28: pop
      29: return

  public void postSetNamespaceQuota(java.lang.String, org.apache.hadoop.hbase.quotas.GlobalQuotaSettings) throws java.io.IOException;
    Code:
       0: aload_0
       1: aload_0
       2: getfield      #47                 // Field coprocEnvironments:Lorg/apache/hadoop/hbase/util/SortedList;
       5: invokevirtual #48                 // Method org/apache/hadoop/hbase/util/SortedList.isEmpty:()Z
       8: ifeq          15
      11: aconst_null
      12: goto          25
      15: new           #251                // class org/apache/hadoop/hbase/master/MasterCoprocessorHost$100
      18: dup
      19: aload_0
      20: aload_1
      21: aload_2
      22: invokespecial #252                // Method org/apache/hadoop/hbase/master/MasterCoprocessorHost$100."<init>":(Lorg/apache/hadoop/hbase/master/MasterCoprocessorHost;Ljava/lang/String;Lorg/apache/hadoop/hbase/quotas/GlobalQuotaSettings;)V
      25: invokevirtual #51                 // Method execOperation:(Lorg/apache/hadoop/hbase/coprocessor/CoprocessorHost$ObserverOperation;)Z
      28: pop
      29: return

  public void preSetRegionServerQuota(java.lang.String, org.apache.hadoop.hbase.quotas.GlobalQuotaSettings) throws java.io.IOException;
    Code:
       0: aload_0
       1: aload_0
       2: getfield      #47                 // Field coprocEnvironments:Lorg/apache/hadoop/hbase/util/SortedList;
       5: invokevirtual #48                 // Method org/apache/hadoop/hbase/util/SortedList.isEmpty:()Z
       8: ifeq          15
      11: aconst_null
      12: goto          25
      15: new           #253                // class org/apache/hadoop/hbase/master/MasterCoprocessorHost$101
      18: dup
      19: aload_0
      20: aload_1
      21: aload_2
      22: invokespecial #254                // Method org/apache/hadoop/hbase/master/MasterCoprocessorHost$101."<init>":(Lorg/apache/hadoop/hbase/master/MasterCoprocessorHost;Ljava/lang/String;Lorg/apache/hadoop/hbase/quotas/GlobalQuotaSettings;)V
      25: invokevirtual #51                 // Method execOperation:(Lorg/apache/hadoop/hbase/coprocessor/CoprocessorHost$ObserverOperation;)Z
      28: pop
      29: return

  public void postSetRegionServerQuota(java.lang.String, org.apache.hadoop.hbase.quotas.GlobalQuotaSettings) throws java.io.IOException;
    Code:
       0: aload_0
       1: aload_0
       2: getfield      #47                 // Field coprocEnvironments:Lorg/apache/hadoop/hbase/util/SortedList;
       5: invokevirtual #48                 // Method org/apache/hadoop/hbase/util/SortedList.isEmpty:()Z
       8: ifeq          15
      11: aconst_null
      12: goto          25
      15: new           #255                // class org/apache/hadoop/hbase/master/MasterCoprocessorHost$102
      18: dup
      19: aload_0
      20: aload_1
      21: aload_2
      22: invokespecial #256                // Method org/apache/hadoop/hbase/master/MasterCoprocessorHost$102."<init>":(Lorg/apache/hadoop/hbase/master/MasterCoprocessorHost;Ljava/lang/String;Lorg/apache/hadoop/hbase/quotas/GlobalQuotaSettings;)V
      25: invokevirtual #51                 // Method execOperation:(Lorg/apache/hadoop/hbase/coprocessor/CoprocessorHost$ObserverOperation;)Z
      28: pop
      29: return

  public void preMoveServersAndTables(java.util.Set<org.apache.hadoop.hbase.net.Address>, java.util.Set<org.apache.hadoop.hbase.TableName>, java.lang.String) throws java.io.IOException;
    Code:
       0: aload_0
       1: aload_0
       2: getfield      #47                 // Field coprocEnvironments:Lorg/apache/hadoop/hbase/util/SortedList;
       5: invokevirtual #48                 // Method org/apache/hadoop/hbase/util/SortedList.isEmpty:()Z
       8: ifeq          15
      11: aconst_null
      12: goto          26
      15: new           #257                // class org/apache/hadoop/hbase/master/MasterCoprocessorHost$103
      18: dup
      19: aload_0
      20: aload_1
      21: aload_2
      22: aload_3
      23: invokespecial #258                // Method org/apache/hadoop/hbase/master/MasterCoprocessorHost$103."<init>":(Lorg/apache/hadoop/hbase/master/MasterCoprocessorHost;Ljava/util/Set;Ljava/util/Set;Ljava/lang/String;)V
      26: invokevirtual #51                 // Method execOperation:(Lorg/apache/hadoop/hbase/coprocessor/CoprocessorHost$ObserverOperation;)Z
      29: pop
      30: return

  public void postMoveServersAndTables(java.util.Set<org.apache.hadoop.hbase.net.Address>, java.util.Set<org.apache.hadoop.hbase.TableName>, java.lang.String) throws java.io.IOException;
    Code:
       0: aload_0
       1: aload_0
       2: getfield      #47                 // Field coprocEnvironments:Lorg/apache/hadoop/hbase/util/SortedList;
       5: invokevirtual #48                 // Method org/apache/hadoop/hbase/util/SortedList.isEmpty:()Z
       8: ifeq          15
      11: aconst_null
      12: goto          26
      15: new           #259                // class org/apache/hadoop/hbase/master/MasterCoprocessorHost$104
      18: dup
      19: aload_0
      20: aload_1
      21: aload_2
      22: aload_3
      23: invokespecial #260                // Method org/apache/hadoop/hbase/master/MasterCoprocessorHost$104."<init>":(Lorg/apache/hadoop/hbase/master/MasterCoprocessorHost;Ljava/util/Set;Ljava/util/Set;Ljava/lang/String;)V
      26: invokevirtual #51                 // Method execOperation:(Lorg/apache/hadoop/hbase/coprocessor/CoprocessorHost$ObserverOperation;)Z
      29: pop
      30: return

  public void preMoveServers(java.util.Set<org.apache.hadoop.hbase.net.Address>, java.lang.String) throws java.io.IOException;
    Code:
       0: aload_0
       1: aload_0
       2: getfield      #47                 // Field coprocEnvironments:Lorg/apache/hadoop/hbase/util/SortedList;
       5: invokevirtual #48                 // Method org/apache/hadoop/hbase/util/SortedList.isEmpty:()Z
       8: ifeq          15
      11: aconst_null
      12: goto          25
      15: new           #261                // class org/apache/hadoop/hbase/master/MasterCoprocessorHost$105
      18: dup
      19: aload_0
      20: aload_1
      21: aload_2
      22: invokespecial #262                // Method org/apache/hadoop/hbase/master/MasterCoprocessorHost$105."<init>":(Lorg/apache/hadoop/hbase/master/MasterCoprocessorHost;Ljava/util/Set;Ljava/lang/String;)V
      25: invokevirtual #51                 // Method execOperation:(Lorg/apache/hadoop/hbase/coprocessor/CoprocessorHost$ObserverOperation;)Z
      28: pop
      29: return

  public void postMoveServers(java.util.Set<org.apache.hadoop.hbase.net.Address>, java.lang.String) throws java.io.IOException;
    Code:
       0: aload_0
       1: aload_0
       2: getfield      #47                 // Field coprocEnvironments:Lorg/apache/hadoop/hbase/util/SortedList;
       5: invokevirtual #48                 // Method org/apache/hadoop/hbase/util/SortedList.isEmpty:()Z
       8: ifeq          15
      11: aconst_null
      12: goto          25
      15: new           #263                // class org/apache/hadoop/hbase/master/MasterCoprocessorHost$106
      18: dup
      19: aload_0
      20: aload_1
      21: aload_2
      22: invokespecial #264                // Method org/apache/hadoop/hbase/master/MasterCoprocessorHost$106."<init>":(Lorg/apache/hadoop/hbase/master/MasterCoprocessorHost;Ljava/util/Set;Ljava/lang/String;)V
      25: invokevirtual #51                 // Method execOperation:(Lorg/apache/hadoop/hbase/coprocessor/CoprocessorHost$ObserverOperation;)Z
      28: pop
      29: return

  public void preMoveTables(java.util.Set<org.apache.hadoop.hbase.TableName>, java.lang.String) throws java.io.IOException;
    Code:
       0: aload_0
       1: aload_0
       2: getfield      #47                 // Field coprocEnvironments:Lorg/apache/hadoop/hbase/util/SortedList;
       5: invokevirtual #48                 // Method org/apache/hadoop/hbase/util/SortedList.isEmpty:()Z
       8: ifeq          15
      11: aconst_null
      12: goto          25
      15: new           #265                // class org/apache/hadoop/hbase/master/MasterCoprocessorHost$107
      18: dup
      19: aload_0
      20: aload_1
      21: aload_2
      22: invokespecial #266                // Method org/apache/hadoop/hbase/master/MasterCoprocessorHost$107."<init>":(Lorg/apache/hadoop/hbase/master/MasterCoprocessorHost;Ljava/util/Set;Ljava/lang/String;)V
      25: invokevirtual #51                 // Method execOperation:(Lorg/apache/hadoop/hbase/coprocessor/CoprocessorHost$ObserverOperation;)Z
      28: pop
      29: return

  public void postMoveTables(java.util.Set<org.apache.hadoop.hbase.TableName>, java.lang.String) throws java.io.IOException;
    Code:
       0: aload_0
       1: aload_0
       2: getfield      #47                 // Field coprocEnvironments:Lorg/apache/hadoop/hbase/util/SortedList;
       5: invokevirtual #48                 // Method org/apache/hadoop/hbase/util/SortedList.isEmpty:()Z
       8: ifeq          15
      11: aconst_null
      12: goto          25
      15: new           #267                // class org/apache/hadoop/hbase/master/MasterCoprocessorHost$108
      18: dup
      19: aload_0
      20: aload_1
      21: aload_2
      22: invokespecial #268                // Method org/apache/hadoop/hbase/master/MasterCoprocessorHost$108."<init>":(Lorg/apache/hadoop/hbase/master/MasterCoprocessorHost;Ljava/util/Set;Ljava/lang/String;)V
      25: invokevirtual #51                 // Method execOperation:(Lorg/apache/hadoop/hbase/coprocessor/CoprocessorHost$ObserverOperation;)Z
      28: pop
      29: return

  public void preAddRSGroup(java.lang.String) throws java.io.IOException;
    Code:
       0: aload_0
       1: aload_0
       2: getfield      #47                 // Field coprocEnvironments:Lorg/apache/hadoop/hbase/util/SortedList;
       5: invokevirtual #48                 // Method org/apache/hadoop/hbase/util/SortedList.isEmpty:()Z
       8: ifeq          15
      11: aconst_null
      12: goto          24
      15: new           #269                // class org/apache/hadoop/hbase/master/MasterCoprocessorHost$109
      18: dup
      19: aload_0
      20: aload_1
      21: invokespecial #270                // Method org/apache/hadoop/hbase/master/MasterCoprocessorHost$109."<init>":(Lorg/apache/hadoop/hbase/master/MasterCoprocessorHost;Ljava/lang/String;)V
      24: invokevirtual #51                 // Method execOperation:(Lorg/apache/hadoop/hbase/coprocessor/CoprocessorHost$ObserverOperation;)Z
      27: pop
      28: return

  public void postAddRSGroup(java.lang.String) throws java.io.IOException;
    Code:
       0: aload_0
       1: aload_0
       2: getfield      #47                 // Field coprocEnvironments:Lorg/apache/hadoop/hbase/util/SortedList;
       5: invokevirtual #48                 // Method org/apache/hadoop/hbase/util/SortedList.isEmpty:()Z
       8: ifeq          15
      11: aconst_null
      12: goto          24
      15: new           #271                // class org/apache/hadoop/hbase/master/MasterCoprocessorHost$110
      18: dup
      19: aload_0
      20: aload_1
      21: invokespecial #272                // Method org/apache/hadoop/hbase/master/MasterCoprocessorHost$110."<init>":(Lorg/apache/hadoop/hbase/master/MasterCoprocessorHost;Ljava/lang/String;)V
      24: invokevirtual #51                 // Method execOperation:(Lorg/apache/hadoop/hbase/coprocessor/CoprocessorHost$ObserverOperation;)Z
      27: pop
      28: return

  public void preRemoveRSGroup(java.lang.String) throws java.io.IOException;
    Code:
       0: aload_0
       1: aload_0
       2: getfield      #47                 // Field coprocEnvironments:Lorg/apache/hadoop/hbase/util/SortedList;
       5: invokevirtual #48                 // Method org/apache/hadoop/hbase/util/SortedList.isEmpty:()Z
       8: ifeq          15
      11: aconst_null
      12: goto          24
      15: new           #273                // class org/apache/hadoop/hbase/master/MasterCoprocessorHost$111
      18: dup
      19: aload_0
      20: aload_1
      21: invokespecial #274                // Method org/apache/hadoop/hbase/master/MasterCoprocessorHost$111."<init>":(Lorg/apache/hadoop/hbase/master/MasterCoprocessorHost;Ljava/lang/String;)V
      24: invokevirtual #51                 // Method execOperation:(Lorg/apache/hadoop/hbase/coprocessor/CoprocessorHost$ObserverOperation;)Z
      27: pop
      28: return

  public void postRemoveRSGroup(java.lang.String) throws java.io.IOException;
    Code:
       0: aload_0
       1: aload_0
       2: getfield      #47                 // Field coprocEnvironments:Lorg/apache/hadoop/hbase/util/SortedList;
       5: invokevirtual #48                 // Method org/apache/hadoop/hbase/util/SortedList.isEmpty:()Z
       8: ifeq          15
      11: aconst_null
      12: goto          24
      15: new           #275                // class org/apache/hadoop/hbase/master/MasterCoprocessorHost$112
      18: dup
      19: aload_0
      20: aload_1
      21: invokespecial #276                // Method org/apache/hadoop/hbase/master/MasterCoprocessorHost$112."<init>":(Lorg/apache/hadoop/hbase/master/MasterCoprocessorHost;Ljava/lang/String;)V
      24: invokevirtual #51                 // Method execOperation:(Lorg/apache/hadoop/hbase/coprocessor/CoprocessorHost$ObserverOperation;)Z
      27: pop
      28: return

  public void preBalanceRSGroup(java.lang.String) throws java.io.IOException;
    Code:
       0: aload_0
       1: aload_0
       2: getfield      #47                 // Field coprocEnvironments:Lorg/apache/hadoop/hbase/util/SortedList;
       5: invokevirtual #48                 // Method org/apache/hadoop/hbase/util/SortedList.isEmpty:()Z
       8: ifeq          15
      11: aconst_null
      12: goto          24
      15: new           #277                // class org/apache/hadoop/hbase/master/MasterCoprocessorHost$113
      18: dup
      19: aload_0
      20: aload_1
      21: invokespecial #278                // Method org/apache/hadoop/hbase/master/MasterCoprocessorHost$113."<init>":(Lorg/apache/hadoop/hbase/master/MasterCoprocessorHost;Ljava/lang/String;)V
      24: invokevirtual #51                 // Method execOperation:(Lorg/apache/hadoop/hbase/coprocessor/CoprocessorHost$ObserverOperation;)Z
      27: pop
      28: return

  public void postBalanceRSGroup(java.lang.String, boolean) throws java.io.IOException;
    Code:
       0: aload_0
       1: aload_0
       2: getfield      #47                 // Field coprocEnvironments:Lorg/apache/hadoop/hbase/util/SortedList;
       5: invokevirtual #48                 // Method org/apache/hadoop/hbase/util/SortedList.isEmpty:()Z
       8: ifeq          15
      11: aconst_null
      12: goto          25
      15: new           #279                // class org/apache/hadoop/hbase/master/MasterCoprocessorHost$114
      18: dup
      19: aload_0
      20: aload_1
      21: iload_2
      22: invokespecial #280                // Method org/apache/hadoop/hbase/master/MasterCoprocessorHost$114."<init>":(Lorg/apache/hadoop/hbase/master/MasterCoprocessorHost;Ljava/lang/String;Z)V
      25: invokevirtual #51                 // Method execOperation:(Lorg/apache/hadoop/hbase/coprocessor/CoprocessorHost$ObserverOperation;)Z
      28: pop
      29: return

  public void preRemoveServers(java.util.Set<org.apache.hadoop.hbase.net.Address>) throws java.io.IOException;
    Code:
       0: aload_0
       1: aload_0
       2: getfield      #47                 // Field coprocEnvironments:Lorg/apache/hadoop/hbase/util/SortedList;
       5: invokevirtual #48                 // Method org/apache/hadoop/hbase/util/SortedList.isEmpty:()Z
       8: ifeq          15
      11: aconst_null
      12: goto          24
      15: new           #281                // class org/apache/hadoop/hbase/master/MasterCoprocessorHost$115
      18: dup
      19: aload_0
      20: aload_1
      21: invokespecial #282                // Method org/apache/hadoop/hbase/master/MasterCoprocessorHost$115."<init>":(Lorg/apache/hadoop/hbase/master/MasterCoprocessorHost;Ljava/util/Set;)V
      24: invokevirtual #51                 // Method execOperation:(Lorg/apache/hadoop/hbase/coprocessor/CoprocessorHost$ObserverOperation;)Z
      27: pop
      28: return

  public void postRemoveServers(java.util.Set<org.apache.hadoop.hbase.net.Address>) throws java.io.IOException;
    Code:
       0: aload_0
       1: aload_0
       2: getfield      #47                 // Field coprocEnvironments:Lorg/apache/hadoop/hbase/util/SortedList;
       5: invokevirtual #48                 // Method org/apache/hadoop/hbase/util/SortedList.isEmpty:()Z
       8: ifeq          15
      11: aconst_null
      12: goto          24
      15: new           #283                // class org/apache/hadoop/hbase/master/MasterCoprocessorHost$116
      18: dup
      19: aload_0
      20: aload_1
      21: invokespecial #284                // Method org/apache/hadoop/hbase/master/MasterCoprocessorHost$116."<init>":(Lorg/apache/hadoop/hbase/master/MasterCoprocessorHost;Ljava/util/Set;)V
      24: invokevirtual #51                 // Method execOperation:(Lorg/apache/hadoop/hbase/coprocessor/CoprocessorHost$ObserverOperation;)Z
      27: pop
      28: return

  public void preGetRSGroupInfo(java.lang.String) throws java.io.IOException;
    Code:
       0: aload_0
       1: aload_0
       2: getfield      #47                 // Field coprocEnvironments:Lorg/apache/hadoop/hbase/util/SortedList;
       5: invokevirtual #48                 // Method org/apache/hadoop/hbase/util/SortedList.isEmpty:()Z
       8: ifeq          15
      11: aconst_null
      12: goto          24
      15: new           #285                // class org/apache/hadoop/hbase/master/MasterCoprocessorHost$117
      18: dup
      19: aload_0
      20: aload_1
      21: invokespecial #286                // Method org/apache/hadoop/hbase/master/MasterCoprocessorHost$117."<init>":(Lorg/apache/hadoop/hbase/master/MasterCoprocessorHost;Ljava/lang/String;)V
      24: invokevirtual #51                 // Method execOperation:(Lorg/apache/hadoop/hbase/coprocessor/CoprocessorHost$ObserverOperation;)Z
      27: pop
      28: return

  public void postGetRSGroupInfo(java.lang.String) throws java.io.IOException;
    Code:
       0: aload_0
       1: aload_0
       2: getfield      #47                 // Field coprocEnvironments:Lorg/apache/hadoop/hbase/util/SortedList;
       5: invokevirtual #48                 // Method org/apache/hadoop/hbase/util/SortedList.isEmpty:()Z
       8: ifeq          15
      11: aconst_null
      12: goto          24
      15: new           #287                // class org/apache/hadoop/hbase/master/MasterCoprocessorHost$118
      18: dup
      19: aload_0
      20: aload_1
      21: invokespecial #288                // Method org/apache/hadoop/hbase/master/MasterCoprocessorHost$118."<init>":(Lorg/apache/hadoop/hbase/master/MasterCoprocessorHost;Ljava/lang/String;)V
      24: invokevirtual #51                 // Method execOperation:(Lorg/apache/hadoop/hbase/coprocessor/CoprocessorHost$ObserverOperation;)Z
      27: pop
      28: return

  public void preGetRSGroupInfoOfTable(org.apache.hadoop.hbase.TableName) throws java.io.IOException;
    Code:
       0: aload_0
       1: aload_0
       2: getfield      #47                 // Field coprocEnvironments:Lorg/apache/hadoop/hbase/util/SortedList;
       5: invokevirtual #48                 // Method org/apache/hadoop/hbase/util/SortedList.isEmpty:()Z
       8: ifeq          15
      11: aconst_null
      12: goto          24
      15: new           #289                // class org/apache/hadoop/hbase/master/MasterCoprocessorHost$119
      18: dup
      19: aload_0
      20: aload_1
      21: invokespecial #290                // Method org/apache/hadoop/hbase/master/MasterCoprocessorHost$119."<init>":(Lorg/apache/hadoop/hbase/master/MasterCoprocessorHost;Lorg/apache/hadoop/hbase/TableName;)V
      24: invokevirtual #51                 // Method execOperation:(Lorg/apache/hadoop/hbase/coprocessor/CoprocessorHost$ObserverOperation;)Z
      27: pop
      28: return

  public void postGetRSGroupInfoOfTable(org.apache.hadoop.hbase.TableName) throws java.io.IOException;
    Code:
       0: aload_0
       1: aload_0
       2: getfield      #47                 // Field coprocEnvironments:Lorg/apache/hadoop/hbase/util/SortedList;
       5: invokevirtual #48                 // Method org/apache/hadoop/hbase/util/SortedList.isEmpty:()Z
       8: ifeq          15
      11: aconst_null
      12: goto          24
      15: new           #291                // class org/apache/hadoop/hbase/master/MasterCoprocessorHost$120
      18: dup
      19: aload_0
      20: aload_1
      21: invokespecial #292                // Method org/apache/hadoop/hbase/master/MasterCoprocessorHost$120."<init>":(Lorg/apache/hadoop/hbase/master/MasterCoprocessorHost;Lorg/apache/hadoop/hbase/TableName;)V
      24: invokevirtual #51                 // Method execOperation:(Lorg/apache/hadoop/hbase/coprocessor/CoprocessorHost$ObserverOperation;)Z
      27: pop
      28: return

  public void preListRSGroups() throws java.io.IOException;
    Code:
       0: aload_0
       1: aload_0
       2: getfield      #47                 // Field coprocEnvironments:Lorg/apache/hadoop/hbase/util/SortedList;
       5: invokevirtual #48                 // Method org/apache/hadoop/hbase/util/SortedList.isEmpty:()Z
       8: ifeq          15
      11: aconst_null
      12: goto          23
      15: new           #293                // class org/apache/hadoop/hbase/master/MasterCoprocessorHost$121
      18: dup
      19: aload_0
      20: invokespecial #294                // Method org/apache/hadoop/hbase/master/MasterCoprocessorHost$121."<init>":(Lorg/apache/hadoop/hbase/master/MasterCoprocessorHost;)V
      23: invokevirtual #51                 // Method execOperation:(Lorg/apache/hadoop/hbase/coprocessor/CoprocessorHost$ObserverOperation;)Z
      26: pop
      27: return

  public void postListRSGroups() throws java.io.IOException;
    Code:
       0: aload_0
       1: aload_0
       2: getfield      #47                 // Field coprocEnvironments:Lorg/apache/hadoop/hbase/util/SortedList;
       5: invokevirtual #48                 // Method org/apache/hadoop/hbase/util/SortedList.isEmpty:()Z
       8: ifeq          15
      11: aconst_null
      12: goto          23
      15: new           #295                // class org/apache/hadoop/hbase/master/MasterCoprocessorHost$122
      18: dup
      19: aload_0
      20: invokespecial #296                // Method org/apache/hadoop/hbase/master/MasterCoprocessorHost$122."<init>":(Lorg/apache/hadoop/hbase/master/MasterCoprocessorHost;)V
      23: invokevirtual #51                 // Method execOperation:(Lorg/apache/hadoop/hbase/coprocessor/CoprocessorHost$ObserverOperation;)Z
      26: pop
      27: return

  public void preGetRSGroupInfoOfServer(org.apache.hadoop.hbase.net.Address) throws java.io.IOException;
    Code:
       0: aload_0
       1: aload_0
       2: getfield      #47                 // Field coprocEnvironments:Lorg/apache/hadoop/hbase/util/SortedList;
       5: invokevirtual #48                 // Method org/apache/hadoop/hbase/util/SortedList.isEmpty:()Z
       8: ifeq          15
      11: aconst_null
      12: goto          24
      15: new           #297                // class org/apache/hadoop/hbase/master/MasterCoprocessorHost$123
      18: dup
      19: aload_0
      20: aload_1
      21: invokespecial #298                // Method org/apache/hadoop/hbase/master/MasterCoprocessorHost$123."<init>":(Lorg/apache/hadoop/hbase/master/MasterCoprocessorHost;Lorg/apache/hadoop/hbase/net/Address;)V
      24: invokevirtual #51                 // Method execOperation:(Lorg/apache/hadoop/hbase/coprocessor/CoprocessorHost$ObserverOperation;)Z
      27: pop
      28: return

  public void postGetRSGroupInfoOfServer(org.apache.hadoop.hbase.net.Address) throws java.io.IOException;
    Code:
       0: aload_0
       1: aload_0
       2: getfield      #47                 // Field coprocEnvironments:Lorg/apache/hadoop/hbase/util/SortedList;
       5: invokevirtual #48                 // Method org/apache/hadoop/hbase/util/SortedList.isEmpty:()Z
       8: ifeq          15
      11: aconst_null
      12: goto          24
      15: new           #299                // class org/apache/hadoop/hbase/master/MasterCoprocessorHost$124
      18: dup
      19: aload_0
      20: aload_1
      21: invokespecial #300                // Method org/apache/hadoop/hbase/master/MasterCoprocessorHost$124."<init>":(Lorg/apache/hadoop/hbase/master/MasterCoprocessorHost;Lorg/apache/hadoop/hbase/net/Address;)V
      24: invokevirtual #51                 // Method execOperation:(Lorg/apache/hadoop/hbase/coprocessor/CoprocessorHost$ObserverOperation;)Z
      27: pop
      28: return

  public void preAddReplicationPeer(java.lang.String, org.apache.hadoop.hbase.replication.ReplicationPeerConfig) throws java.io.IOException;
    Code:
       0: aload_0
       1: aload_0
       2: getfield      #47                 // Field coprocEnvironments:Lorg/apache/hadoop/hbase/util/SortedList;
       5: invokevirtual #48                 // Method org/apache/hadoop/hbase/util/SortedList.isEmpty:()Z
       8: ifeq          15
      11: aconst_null
      12: goto          25
      15: new           #301                // class org/apache/hadoop/hbase/master/MasterCoprocessorHost$125
      18: dup
      19: aload_0
      20: aload_1
      21: aload_2
      22: invokespecial #302                // Method org/apache/hadoop/hbase/master/MasterCoprocessorHost$125."<init>":(Lorg/apache/hadoop/hbase/master/MasterCoprocessorHost;Ljava/lang/String;Lorg/apache/hadoop/hbase/replication/ReplicationPeerConfig;)V
      25: invokevirtual #51                 // Method execOperation:(Lorg/apache/hadoop/hbase/coprocessor/CoprocessorHost$ObserverOperation;)Z
      28: pop
      29: return

  public void postAddReplicationPeer(java.lang.String, org.apache.hadoop.hbase.replication.ReplicationPeerConfig) throws java.io.IOException;
    Code:
       0: aload_0
       1: aload_0
       2: getfield      #47                 // Field coprocEnvironments:Lorg/apache/hadoop/hbase/util/SortedList;
       5: invokevirtual #48                 // Method org/apache/hadoop/hbase/util/SortedList.isEmpty:()Z
       8: ifeq          15
      11: aconst_null
      12: goto          25
      15: new           #303                // class org/apache/hadoop/hbase/master/MasterCoprocessorHost$126
      18: dup
      19: aload_0
      20: aload_1
      21: aload_2
      22: invokespecial #304                // Method org/apache/hadoop/hbase/master/MasterCoprocessorHost$126."<init>":(Lorg/apache/hadoop/hbase/master/MasterCoprocessorHost;Ljava/lang/String;Lorg/apache/hadoop/hbase/replication/ReplicationPeerConfig;)V
      25: invokevirtual #51                 // Method execOperation:(Lorg/apache/hadoop/hbase/coprocessor/CoprocessorHost$ObserverOperation;)Z
      28: pop
      29: return

  public void preRemoveReplicationPeer(java.lang.String) throws java.io.IOException;
    Code:
       0: aload_0
       1: aload_0
       2: getfield      #47                 // Field coprocEnvironments:Lorg/apache/hadoop/hbase/util/SortedList;
       5: invokevirtual #48                 // Method org/apache/hadoop/hbase/util/SortedList.isEmpty:()Z
       8: ifeq          15
      11: aconst_null
      12: goto          24
      15: new           #305                // class org/apache/hadoop/hbase/master/MasterCoprocessorHost$127
      18: dup
      19: aload_0
      20: aload_1
      21: invokespecial #306                // Method org/apache/hadoop/hbase/master/MasterCoprocessorHost$127."<init>":(Lorg/apache/hadoop/hbase/master/MasterCoprocessorHost;Ljava/lang/String;)V
      24: invokevirtual #51                 // Method execOperation:(Lorg/apache/hadoop/hbase/coprocessor/CoprocessorHost$ObserverOperation;)Z
      27: pop
      28: return

  public void postRemoveReplicationPeer(java.lang.String) throws java.io.IOException;
    Code:
       0: aload_0
       1: aload_0
       2: getfield      #47                 // Field coprocEnvironments:Lorg/apache/hadoop/hbase/util/SortedList;
       5: invokevirtual #48                 // Method org/apache/hadoop/hbase/util/SortedList.isEmpty:()Z
       8: ifeq          15
      11: aconst_null
      12: goto          24
      15: new           #307                // class org/apache/hadoop/hbase/master/MasterCoprocessorHost$128
      18: dup
      19: aload_0
      20: aload_1
      21: invokespecial #308                // Method org/apache/hadoop/hbase/master/MasterCoprocessorHost$128."<init>":(Lorg/apache/hadoop/hbase/master/MasterCoprocessorHost;Ljava/lang/String;)V
      24: invokevirtual #51                 // Method execOperation:(Lorg/apache/hadoop/hbase/coprocessor/CoprocessorHost$ObserverOperation;)Z
      27: pop
      28: return

  public void preEnableReplicationPeer(java.lang.String) throws java.io.IOException;
    Code:
       0: aload_0
       1: aload_0
       2: getfield      #47                 // Field coprocEnvironments:Lorg/apache/hadoop/hbase/util/SortedList;
       5: invokevirtual #48                 // Method org/apache/hadoop/hbase/util/SortedList.isEmpty:()Z
       8: ifeq          15
      11: aconst_null
      12: goto          24
      15: new           #309                // class org/apache/hadoop/hbase/master/MasterCoprocessorHost$129
      18: dup
      19: aload_0
      20: aload_1
      21: invokespecial #310                // Method org/apache/hadoop/hbase/master/MasterCoprocessorHost$129."<init>":(Lorg/apache/hadoop/hbase/master/MasterCoprocessorHost;Ljava/lang/String;)V
      24: invokevirtual #51                 // Method execOperation:(Lorg/apache/hadoop/hbase/coprocessor/CoprocessorHost$ObserverOperation;)Z
      27: pop
      28: return

  public void postEnableReplicationPeer(java.lang.String) throws java.io.IOException;
    Code:
       0: aload_0
       1: aload_0
       2: getfield      #47                 // Field coprocEnvironments:Lorg/apache/hadoop/hbase/util/SortedList;
       5: invokevirtual #48                 // Method org/apache/hadoop/hbase/util/SortedList.isEmpty:()Z
       8: ifeq          15
      11: aconst_null
      12: goto          24
      15: new           #311                // class org/apache/hadoop/hbase/master/MasterCoprocessorHost$130
      18: dup
      19: aload_0
      20: aload_1
      21: invokespecial #312                // Method org/apache/hadoop/hbase/master/MasterCoprocessorHost$130."<init>":(Lorg/apache/hadoop/hbase/master/MasterCoprocessorHost;Ljava/lang/String;)V
      24: invokevirtual #51                 // Method execOperation:(Lorg/apache/hadoop/hbase/coprocessor/CoprocessorHost$ObserverOperation;)Z
      27: pop
      28: return

  public void preDisableReplicationPeer(java.lang.String) throws java.io.IOException;
    Code:
       0: aload_0
       1: aload_0
       2: getfield      #47                 // Field coprocEnvironments:Lorg/apache/hadoop/hbase/util/SortedList;
       5: invokevirtual #48                 // Method org/apache/hadoop/hbase/util/SortedList.isEmpty:()Z
       8: ifeq          15
      11: aconst_null
      12: goto          24
      15: new           #313                // class org/apache/hadoop/hbase/master/MasterCoprocessorHost$131
      18: dup
      19: aload_0
      20: aload_1
      21: invokespecial #314                // Method org/apache/hadoop/hbase/master/MasterCoprocessorHost$131."<init>":(Lorg/apache/hadoop/hbase/master/MasterCoprocessorHost;Ljava/lang/String;)V
      24: invokevirtual #51                 // Method execOperation:(Lorg/apache/hadoop/hbase/coprocessor/CoprocessorHost$ObserverOperation;)Z
      27: pop
      28: return

  public void postDisableReplicationPeer(java.lang.String) throws java.io.IOException;
    Code:
       0: aload_0
       1: aload_0
       2: getfield      #47                 // Field coprocEnvironments:Lorg/apache/hadoop/hbase/util/SortedList;
       5: invokevirtual #48                 // Method org/apache/hadoop/hbase/util/SortedList.isEmpty:()Z
       8: ifeq          15
      11: aconst_null
      12: goto          24
      15: new           #315                // class org/apache/hadoop/hbase/master/MasterCoprocessorHost$132
      18: dup
      19: aload_0
      20: aload_1
      21: invokespecial #316                // Method org/apache/hadoop/hbase/master/MasterCoprocessorHost$132."<init>":(Lorg/apache/hadoop/hbase/master/MasterCoprocessorHost;Ljava/lang/String;)V
      24: invokevirtual #51                 // Method execOperation:(Lorg/apache/hadoop/hbase/coprocessor/CoprocessorHost$ObserverOperation;)Z
      27: pop
      28: return

  public void preGetReplicationPeerConfig(java.lang.String) throws java.io.IOException;
    Code:
       0: aload_0
       1: aload_0
       2: getfield      #47                 // Field coprocEnvironments:Lorg/apache/hadoop/hbase/util/SortedList;
       5: invokevirtual #48                 // Method org/apache/hadoop/hbase/util/SortedList.isEmpty:()Z
       8: ifeq          15
      11: aconst_null
      12: goto          24
      15: new           #317                // class org/apache/hadoop/hbase/master/MasterCoprocessorHost$133
      18: dup
      19: aload_0
      20: aload_1
      21: invokespecial #318                // Method org/apache/hadoop/hbase/master/MasterCoprocessorHost$133."<init>":(Lorg/apache/hadoop/hbase/master/MasterCoprocessorHost;Ljava/lang/String;)V
      24: invokevirtual #51                 // Method execOperation:(Lorg/apache/hadoop/hbase/coprocessor/CoprocessorHost$ObserverOperation;)Z
      27: pop
      28: return

  public void postGetReplicationPeerConfig(java.lang.String) throws java.io.IOException;
    Code:
       0: aload_0
       1: aload_0
       2: getfield      #47                 // Field coprocEnvironments:Lorg/apache/hadoop/hbase/util/SortedList;
       5: invokevirtual #48                 // Method org/apache/hadoop/hbase/util/SortedList.isEmpty:()Z
       8: ifeq          15
      11: aconst_null
      12: goto          24
      15: new           #319                // class org/apache/hadoop/hbase/master/MasterCoprocessorHost$134
      18: dup
      19: aload_0
      20: aload_1
      21: invokespecial #320                // Method org/apache/hadoop/hbase/master/MasterCoprocessorHost$134."<init>":(Lorg/apache/hadoop/hbase/master/MasterCoprocessorHost;Ljava/lang/String;)V
      24: invokevirtual #51                 // Method execOperation:(Lorg/apache/hadoop/hbase/coprocessor/CoprocessorHost$ObserverOperation;)Z
      27: pop
      28: return

  public void preUpdateReplicationPeerConfig(java.lang.String, org.apache.hadoop.hbase.replication.ReplicationPeerConfig) throws java.io.IOException;
    Code:
       0: aload_0
       1: aload_0
       2: getfield      #47                 // Field coprocEnvironments:Lorg/apache/hadoop/hbase/util/SortedList;
       5: invokevirtual #48                 // Method org/apache/hadoop/hbase/util/SortedList.isEmpty:()Z
       8: ifeq          15
      11: aconst_null
      12: goto          25
      15: new           #321                // class org/apache/hadoop/hbase/master/MasterCoprocessorHost$135
      18: dup
      19: aload_0
      20: aload_1
      21: aload_2
      22: invokespecial #322                // Method org/apache/hadoop/hbase/master/MasterCoprocessorHost$135."<init>":(Lorg/apache/hadoop/hbase/master/MasterCoprocessorHost;Ljava/lang/String;Lorg/apache/hadoop/hbase/replication/ReplicationPeerConfig;)V
      25: invokevirtual #51                 // Method execOperation:(Lorg/apache/hadoop/hbase/coprocessor/CoprocessorHost$ObserverOperation;)Z
      28: pop
      29: return

  public void postUpdateReplicationPeerConfig(java.lang.String, org.apache.hadoop.hbase.replication.ReplicationPeerConfig) throws java.io.IOException;
    Code:
       0: aload_0
       1: aload_0
       2: getfield      #47                 // Field coprocEnvironments:Lorg/apache/hadoop/hbase/util/SortedList;
       5: invokevirtual #48                 // Method org/apache/hadoop/hbase/util/SortedList.isEmpty:()Z
       8: ifeq          15
      11: aconst_null
      12: goto          25
      15: new           #323                // class org/apache/hadoop/hbase/master/MasterCoprocessorHost$136
      18: dup
      19: aload_0
      20: aload_1
      21: aload_2
      22: invokespecial #324                // Method org/apache/hadoop/hbase/master/MasterCoprocessorHost$136."<init>":(Lorg/apache/hadoop/hbase/master/MasterCoprocessorHost;Ljava/lang/String;Lorg/apache/hadoop/hbase/replication/ReplicationPeerConfig;)V
      25: invokevirtual #51                 // Method execOperation:(Lorg/apache/hadoop/hbase/coprocessor/CoprocessorHost$ObserverOperation;)Z
      28: pop
      29: return

  public void preListReplicationPeers(java.lang.String) throws java.io.IOException;
    Code:
       0: aload_0
       1: aload_0
       2: getfield      #47                 // Field coprocEnvironments:Lorg/apache/hadoop/hbase/util/SortedList;
       5: invokevirtual #48                 // Method org/apache/hadoop/hbase/util/SortedList.isEmpty:()Z
       8: ifeq          15
      11: aconst_null
      12: goto          24
      15: new           #325                // class org/apache/hadoop/hbase/master/MasterCoprocessorHost$137
      18: dup
      19: aload_0
      20: aload_1
      21: invokespecial #326                // Method org/apache/hadoop/hbase/master/MasterCoprocessorHost$137."<init>":(Lorg/apache/hadoop/hbase/master/MasterCoprocessorHost;Ljava/lang/String;)V
      24: invokevirtual #51                 // Method execOperation:(Lorg/apache/hadoop/hbase/coprocessor/CoprocessorHost$ObserverOperation;)Z
      27: pop
      28: return

  public void postListReplicationPeers(java.lang.String) throws java.io.IOException;
    Code:
       0: aload_0
       1: aload_0
       2: getfield      #47                 // Field coprocEnvironments:Lorg/apache/hadoop/hbase/util/SortedList;
       5: invokevirtual #48                 // Method org/apache/hadoop/hbase/util/SortedList.isEmpty:()Z
       8: ifeq          15
      11: aconst_null
      12: goto          24
      15: new           #327                // class org/apache/hadoop/hbase/master/MasterCoprocessorHost$138
      18: dup
      19: aload_0
      20: aload_1
      21: invokespecial #328                // Method org/apache/hadoop/hbase/master/MasterCoprocessorHost$138."<init>":(Lorg/apache/hadoop/hbase/master/MasterCoprocessorHost;Ljava/lang/String;)V
      24: invokevirtual #51                 // Method execOperation:(Lorg/apache/hadoop/hbase/coprocessor/CoprocessorHost$ObserverOperation;)Z
      27: pop
      28: return

  public void preTransitReplicationPeerSyncReplicationState(java.lang.String, org.apache.hadoop.hbase.replication.SyncReplicationState) throws java.io.IOException;
    Code:
       0: aload_0
       1: aload_0
       2: getfield      #47                 // Field coprocEnvironments:Lorg/apache/hadoop/hbase/util/SortedList;
       5: invokevirtual #48                 // Method org/apache/hadoop/hbase/util/SortedList.isEmpty:()Z
       8: ifeq          15
      11: aconst_null
      12: goto          25
      15: new           #329                // class org/apache/hadoop/hbase/master/MasterCoprocessorHost$139
      18: dup
      19: aload_0
      20: aload_1
      21: aload_2
      22: invokespecial #330                // Method org/apache/hadoop/hbase/master/MasterCoprocessorHost$139."<init>":(Lorg/apache/hadoop/hbase/master/MasterCoprocessorHost;Ljava/lang/String;Lorg/apache/hadoop/hbase/replication/SyncReplicationState;)V
      25: invokevirtual #51                 // Method execOperation:(Lorg/apache/hadoop/hbase/coprocessor/CoprocessorHost$ObserverOperation;)Z
      28: pop
      29: return

  public void postTransitReplicationPeerSyncReplicationState(java.lang.String, org.apache.hadoop.hbase.replication.SyncReplicationState, org.apache.hadoop.hbase.replication.SyncReplicationState) throws java.io.IOException;
    Code:
       0: aload_0
       1: aload_0
       2: getfield      #47                 // Field coprocEnvironments:Lorg/apache/hadoop/hbase/util/SortedList;
       5: invokevirtual #48                 // Method org/apache/hadoop/hbase/util/SortedList.isEmpty:()Z
       8: ifeq          15
      11: aconst_null
      12: goto          26
      15: new           #331                // class org/apache/hadoop/hbase/master/MasterCoprocessorHost$140
      18: dup
      19: aload_0
      20: aload_1
      21: aload_2
      22: aload_3
      23: invokespecial #332                // Method org/apache/hadoop/hbase/master/MasterCoprocessorHost$140."<init>":(Lorg/apache/hadoop/hbase/master/MasterCoprocessorHost;Ljava/lang/String;Lorg/apache/hadoop/hbase/replication/SyncReplicationState;Lorg/apache/hadoop/hbase/replication/SyncReplicationState;)V
      26: invokevirtual #51                 // Method execOperation:(Lorg/apache/hadoop/hbase/coprocessor/CoprocessorHost$ObserverOperation;)Z
      29: pop
      30: return

  public void preRequestLock(java.lang.String, org.apache.hadoop.hbase.TableName, org.apache.hadoop.hbase.client.RegionInfo[], org.apache.hadoop.hbase.procedure2.LockType, java.lang.String) throws java.io.IOException;
    Code:
       0: aload_0
       1: aload_0
       2: getfield      #47                 // Field coprocEnvironments:Lorg/apache/hadoop/hbase/util/SortedList;
       5: invokevirtual #48                 // Method org/apache/hadoop/hbase/util/SortedList.isEmpty:()Z
       8: ifeq          15
      11: aconst_null
      12: goto          28
      15: new           #333                // class org/apache/hadoop/hbase/master/MasterCoprocessorHost$141
      18: dup
      19: aload_0
      20: aload_1
      21: aload_2
      22: aload_3
      23: aload         5
      25: invokespecial #334                // Method org/apache/hadoop/hbase/master/MasterCoprocessorHost$141."<init>":(Lorg/apache/hadoop/hbase/master/MasterCoprocessorHost;Ljava/lang/String;Lorg/apache/hadoop/hbase/TableName;[Lorg/apache/hadoop/hbase/client/RegionInfo;Ljava/lang/String;)V
      28: invokevirtual #51                 // Method execOperation:(Lorg/apache/hadoop/hbase/coprocessor/CoprocessorHost$ObserverOperation;)Z
      31: pop
      32: return

  public void postRequestLock(java.lang.String, org.apache.hadoop.hbase.TableName, org.apache.hadoop.hbase.client.RegionInfo[], org.apache.hadoop.hbase.procedure2.LockType, java.lang.String) throws java.io.IOException;
    Code:
       0: aload_0
       1: aload_0
       2: getfield      #47                 // Field coprocEnvironments:Lorg/apache/hadoop/hbase/util/SortedList;
       5: invokevirtual #48                 // Method org/apache/hadoop/hbase/util/SortedList.isEmpty:()Z
       8: ifeq          15
      11: aconst_null
      12: goto          28
      15: new           #335                // class org/apache/hadoop/hbase/master/MasterCoprocessorHost$142
      18: dup
      19: aload_0
      20: aload_1
      21: aload_2
      22: aload_3
      23: aload         5
      25: invokespecial #336                // Method org/apache/hadoop/hbase/master/MasterCoprocessorHost$142."<init>":(Lorg/apache/hadoop/hbase/master/MasterCoprocessorHost;Ljava/lang/String;Lorg/apache/hadoop/hbase/TableName;[Lorg/apache/hadoop/hbase/client/RegionInfo;Ljava/lang/String;)V
      28: invokevirtual #51                 // Method execOperation:(Lorg/apache/hadoop/hbase/coprocessor/CoprocessorHost$ObserverOperation;)Z
      31: pop
      32: return

  public void preLockHeartbeat(org.apache.hadoop.hbase.master.locking.LockProcedure, boolean) throws java.io.IOException;
    Code:
       0: aload_0
       1: aload_0
       2: getfield      #47                 // Field coprocEnvironments:Lorg/apache/hadoop/hbase/util/SortedList;
       5: invokevirtual #48                 // Method org/apache/hadoop/hbase/util/SortedList.isEmpty:()Z
       8: ifeq          15
      11: aconst_null
      12: goto          24
      15: new           #337                // class org/apache/hadoop/hbase/master/MasterCoprocessorHost$143
      18: dup
      19: aload_0
      20: aload_1
      21: invokespecial #338                // Method org/apache/hadoop/hbase/master/MasterCoprocessorHost$143."<init>":(Lorg/apache/hadoop/hbase/master/MasterCoprocessorHost;Lorg/apache/hadoop/hbase/master/locking/LockProcedure;)V
      24: invokevirtual #51                 // Method execOperation:(Lorg/apache/hadoop/hbase/coprocessor/CoprocessorHost$ObserverOperation;)Z
      27: pop
      28: return

  public void postLockHeartbeat(org.apache.hadoop.hbase.master.locking.LockProcedure, boolean) throws java.io.IOException;
    Code:
       0: aload_0
       1: aload_0
       2: getfield      #47                 // Field coprocEnvironments:Lorg/apache/hadoop/hbase/util/SortedList;
       5: invokevirtual #48                 // Method org/apache/hadoop/hbase/util/SortedList.isEmpty:()Z
       8: ifeq          15
      11: aconst_null
      12: goto          23
      15: new           #339                // class org/apache/hadoop/hbase/master/MasterCoprocessorHost$144
      18: dup
      19: aload_0
      20: invokespecial #340                // Method org/apache/hadoop/hbase/master/MasterCoprocessorHost$144."<init>":(Lorg/apache/hadoop/hbase/master/MasterCoprocessorHost;)V
      23: invokevirtual #51                 // Method execOperation:(Lorg/apache/hadoop/hbase/coprocessor/CoprocessorHost$ObserverOperation;)Z
      26: pop
      27: return

  public void preGetClusterMetrics() throws java.io.IOException;
    Code:
       0: aload_0
       1: aload_0
       2: getfield      #47                 // Field coprocEnvironments:Lorg/apache/hadoop/hbase/util/SortedList;
       5: invokevirtual #48                 // Method org/apache/hadoop/hbase/util/SortedList.isEmpty:()Z
       8: ifeq          15
      11: aconst_null
      12: goto          23
      15: new           #341                // class org/apache/hadoop/hbase/master/MasterCoprocessorHost$145
      18: dup
      19: aload_0
      20: invokespecial #342                // Method org/apache/hadoop/hbase/master/MasterCoprocessorHost$145."<init>":(Lorg/apache/hadoop/hbase/master/MasterCoprocessorHost;)V
      23: invokevirtual #51                 // Method execOperation:(Lorg/apache/hadoop/hbase/coprocessor/CoprocessorHost$ObserverOperation;)Z
      26: pop
      27: return

  public void postGetClusterMetrics(org.apache.hadoop.hbase.ClusterMetrics) throws java.io.IOException;
    Code:
       0: aload_0
       1: aload_0
       2: getfield      #47                 // Field coprocEnvironments:Lorg/apache/hadoop/hbase/util/SortedList;
       5: invokevirtual #48                 // Method org/apache/hadoop/hbase/util/SortedList.isEmpty:()Z
       8: ifeq          15
      11: aconst_null
      12: goto          24
      15: new           #343                // class org/apache/hadoop/hbase/master/MasterCoprocessorHost$146
      18: dup
      19: aload_0
      20: aload_1
      21: invokespecial #344                // Method org/apache/hadoop/hbase/master/MasterCoprocessorHost$146."<init>":(Lorg/apache/hadoop/hbase/master/MasterCoprocessorHost;Lorg/apache/hadoop/hbase/ClusterMetrics;)V
      24: invokevirtual #51                 // Method execOperation:(Lorg/apache/hadoop/hbase/coprocessor/CoprocessorHost$ObserverOperation;)Z
      27: pop
      28: return

  public void preClearDeadServers() throws java.io.IOException;
    Code:
       0: aload_0
       1: aload_0
       2: getfield      #47                 // Field coprocEnvironments:Lorg/apache/hadoop/hbase/util/SortedList;
       5: invokevirtual #48                 // Method org/apache/hadoop/hbase/util/SortedList.isEmpty:()Z
       8: ifeq          15
      11: aconst_null
      12: goto          23
      15: new           #345                // class org/apache/hadoop/hbase/master/MasterCoprocessorHost$147
      18: dup
      19: aload_0
      20: invokespecial #346                // Method org/apache/hadoop/hbase/master/MasterCoprocessorHost$147."<init>":(Lorg/apache/hadoop/hbase/master/MasterCoprocessorHost;)V
      23: invokevirtual #51                 // Method execOperation:(Lorg/apache/hadoop/hbase/coprocessor/CoprocessorHost$ObserverOperation;)Z
      26: pop
      27: return

  public void postClearDeadServers(java.util.List<org.apache.hadoop.hbase.ServerName>, java.util.List<org.apache.hadoop.hbase.ServerName>) throws java.io.IOException;
    Code:
       0: aload_0
       1: aload_0
       2: getfield      #47                 // Field coprocEnvironments:Lorg/apache/hadoop/hbase/util/SortedList;
       5: invokevirtual #48                 // Method org/apache/hadoop/hbase/util/SortedList.isEmpty:()Z
       8: ifeq          15
      11: aconst_null
      12: goto          25
      15: new           #347                // class org/apache/hadoop/hbase/master/MasterCoprocessorHost$148
      18: dup
      19: aload_0
      20: aload_1
      21: aload_2
      22: invokespecial #348                // Method org/apache/hadoop/hbase/master/MasterCoprocessorHost$148."<init>":(Lorg/apache/hadoop/hbase/master/MasterCoprocessorHost;Ljava/util/List;Ljava/util/List;)V
      25: invokevirtual #51                 // Method execOperation:(Lorg/apache/hadoop/hbase/coprocessor/CoprocessorHost$ObserverOperation;)Z
      28: pop
      29: return

  public void preDecommissionRegionServers(java.util.List<org.apache.hadoop.hbase.ServerName>, boolean) throws java.io.IOException;
    Code:
       0: aload_0
       1: aload_0
       2: getfield      #47                 // Field coprocEnvironments:Lorg/apache/hadoop/hbase/util/SortedList;
       5: invokevirtual #48                 // Method org/apache/hadoop/hbase/util/SortedList.isEmpty:()Z
       8: ifeq          15
      11: aconst_null
      12: goto          25
      15: new           #349                // class org/apache/hadoop/hbase/master/MasterCoprocessorHost$149
      18: dup
      19: aload_0
      20: aload_1
      21: iload_2
      22: invokespecial #350                // Method org/apache/hadoop/hbase/master/MasterCoprocessorHost$149."<init>":(Lorg/apache/hadoop/hbase/master/MasterCoprocessorHost;Ljava/util/List;Z)V
      25: invokevirtual #51                 // Method execOperation:(Lorg/apache/hadoop/hbase/coprocessor/CoprocessorHost$ObserverOperation;)Z
      28: pop
      29: return

  public void postDecommissionRegionServers(java.util.List<org.apache.hadoop.hbase.ServerName>, boolean) throws java.io.IOException;
    Code:
       0: aload_0
       1: aload_0
       2: getfield      #47                 // Field coprocEnvironments:Lorg/apache/hadoop/hbase/util/SortedList;
       5: invokevirtual #48                 // Method org/apache/hadoop/hbase/util/SortedList.isEmpty:()Z
       8: ifeq          15
      11: aconst_null
      12: goto          25
      15: new           #351                // class org/apache/hadoop/hbase/master/MasterCoprocessorHost$150
      18: dup
      19: aload_0
      20: aload_1
      21: iload_2
      22: invokespecial #352                // Method org/apache/hadoop/hbase/master/MasterCoprocessorHost$150."<init>":(Lorg/apache/hadoop/hbase/master/MasterCoprocessorHost;Ljava/util/List;Z)V
      25: invokevirtual #51                 // Method execOperation:(Lorg/apache/hadoop/hbase/coprocessor/CoprocessorHost$ObserverOperation;)Z
      28: pop
      29: return

  public void preListDecommissionedRegionServers() throws java.io.IOException;
    Code:
       0: aload_0
       1: aload_0
       2: getfield      #47                 // Field coprocEnvironments:Lorg/apache/hadoop/hbase/util/SortedList;
       5: invokevirtual #48                 // Method org/apache/hadoop/hbase/util/SortedList.isEmpty:()Z
       8: ifeq          15
      11: aconst_null
      12: goto          23
      15: new           #353                // class org/apache/hadoop/hbase/master/MasterCoprocessorHost$151
      18: dup
      19: aload_0
      20: invokespecial #354                // Method org/apache/hadoop/hbase/master/MasterCoprocessorHost$151."<init>":(Lorg/apache/hadoop/hbase/master/MasterCoprocessorHost;)V
      23: invokevirtual #51                 // Method execOperation:(Lorg/apache/hadoop/hbase/coprocessor/CoprocessorHost$ObserverOperation;)Z
      26: pop
      27: return

  public void postListDecommissionedRegionServers() throws java.io.IOException;
    Code:
       0: aload_0
       1: aload_0
       2: getfield      #47                 // Field coprocEnvironments:Lorg/apache/hadoop/hbase/util/SortedList;
       5: invokevirtual #48                 // Method org/apache/hadoop/hbase/util/SortedList.isEmpty:()Z
       8: ifeq          15
      11: aconst_null
      12: goto          23
      15: new           #355                // class org/apache/hadoop/hbase/master/MasterCoprocessorHost$152
      18: dup
      19: aload_0
      20: invokespecial #356                // Method org/apache/hadoop/hbase/master/MasterCoprocessorHost$152."<init>":(Lorg/apache/hadoop/hbase/master/MasterCoprocessorHost;)V
      23: invokevirtual #51                 // Method execOperation:(Lorg/apache/hadoop/hbase/coprocessor/CoprocessorHost$ObserverOperation;)Z
      26: pop
      27: return

  public void preRecommissionRegionServer(org.apache.hadoop.hbase.ServerName, java.util.List<byte[]>) throws java.io.IOException;
    Code:
       0: aload_0
       1: aload_0
       2: getfield      #47                 // Field coprocEnvironments:Lorg/apache/hadoop/hbase/util/SortedList;
       5: invokevirtual #48                 // Method org/apache/hadoop/hbase/util/SortedList.isEmpty:()Z
       8: ifeq          15
      11: aconst_null
      12: goto          25
      15: new           #357                // class org/apache/hadoop/hbase/master/MasterCoprocessorHost$153
      18: dup
      19: aload_0
      20: aload_1
      21: aload_2
      22: invokespecial #358                // Method org/apache/hadoop/hbase/master/MasterCoprocessorHost$153."<init>":(Lorg/apache/hadoop/hbase/master/MasterCoprocessorHost;Lorg/apache/hadoop/hbase/ServerName;Ljava/util/List;)V
      25: invokevirtual #51                 // Method execOperation:(Lorg/apache/hadoop/hbase/coprocessor/CoprocessorHost$ObserverOperation;)Z
      28: pop
      29: return

  public void postRecommissionRegionServer(org.apache.hadoop.hbase.ServerName, java.util.List<byte[]>) throws java.io.IOException;
    Code:
       0: aload_0
       1: aload_0
       2: getfield      #47                 // Field coprocEnvironments:Lorg/apache/hadoop/hbase/util/SortedList;
       5: invokevirtual #48                 // Method org/apache/hadoop/hbase/util/SortedList.isEmpty:()Z
       8: ifeq          15
      11: aconst_null
      12: goto          25
      15: new           #359                // class org/apache/hadoop/hbase/master/MasterCoprocessorHost$154
      18: dup
      19: aload_0
      20: aload_1
      21: aload_2
      22: invokespecial #360                // Method org/apache/hadoop/hbase/master/MasterCoprocessorHost$154."<init>":(Lorg/apache/hadoop/hbase/master/MasterCoprocessorHost;Lorg/apache/hadoop/hbase/ServerName;Ljava/util/List;)V
      25: invokevirtual #51                 // Method execOperation:(Lorg/apache/hadoop/hbase/coprocessor/CoprocessorHost$ObserverOperation;)Z
      28: pop
      29: return

  public void preSwitchRpcThrottle(boolean) throws java.io.IOException;
    Code:
       0: aload_0
       1: aload_0
       2: getfield      #47                 // Field coprocEnvironments:Lorg/apache/hadoop/hbase/util/SortedList;
       5: invokevirtual #48                 // Method org/apache/hadoop/hbase/util/SortedList.isEmpty:()Z
       8: ifeq          15
      11: aconst_null
      12: goto          24
      15: new           #361                // class org/apache/hadoop/hbase/master/MasterCoprocessorHost$155
      18: dup
      19: aload_0
      20: iload_1
      21: invokespecial #362                // Method org/apache/hadoop/hbase/master/MasterCoprocessorHost$155."<init>":(Lorg/apache/hadoop/hbase/master/MasterCoprocessorHost;Z)V
      24: invokevirtual #51                 // Method execOperation:(Lorg/apache/hadoop/hbase/coprocessor/CoprocessorHost$ObserverOperation;)Z
      27: pop
      28: return

  public void postSwitchRpcThrottle(boolean, boolean) throws java.io.IOException;
    Code:
       0: aload_0
       1: aload_0
       2: getfield      #47                 // Field coprocEnvironments:Lorg/apache/hadoop/hbase/util/SortedList;
       5: invokevirtual #48                 // Method org/apache/hadoop/hbase/util/SortedList.isEmpty:()Z
       8: ifeq          15
      11: aconst_null
      12: goto          25
      15: new           #363                // class org/apache/hadoop/hbase/master/MasterCoprocessorHost$156
      18: dup
      19: aload_0
      20: iload_1
      21: iload_2
      22: invokespecial #364                // Method org/apache/hadoop/hbase/master/MasterCoprocessorHost$156."<init>":(Lorg/apache/hadoop/hbase/master/MasterCoprocessorHost;ZZ)V
      25: invokevirtual #51                 // Method execOperation:(Lorg/apache/hadoop/hbase/coprocessor/CoprocessorHost$ObserverOperation;)Z
      28: pop
      29: return

  public void preIsRpcThrottleEnabled() throws java.io.IOException;
    Code:
       0: aload_0
       1: aload_0
       2: getfield      #47                 // Field coprocEnvironments:Lorg/apache/hadoop/hbase/util/SortedList;
       5: invokevirtual #48                 // Method org/apache/hadoop/hbase/util/SortedList.isEmpty:()Z
       8: ifeq          15
      11: aconst_null
      12: goto          23
      15: new           #365                // class org/apache/hadoop/hbase/master/MasterCoprocessorHost$157
      18: dup
      19: aload_0
      20: invokespecial #366                // Method org/apache/hadoop/hbase/master/MasterCoprocessorHost$157."<init>":(Lorg/apache/hadoop/hbase/master/MasterCoprocessorHost;)V
      23: invokevirtual #51                 // Method execOperation:(Lorg/apache/hadoop/hbase/coprocessor/CoprocessorHost$ObserverOperation;)Z
      26: pop
      27: return

  public void postIsRpcThrottleEnabled(boolean) throws java.io.IOException;
    Code:
       0: aload_0
       1: aload_0
       2: getfield      #47                 // Field coprocEnvironments:Lorg/apache/hadoop/hbase/util/SortedList;
       5: invokevirtual #48                 // Method org/apache/hadoop/hbase/util/SortedList.isEmpty:()Z
       8: ifeq          15
      11: aconst_null
      12: goto          24
      15: new           #367                // class org/apache/hadoop/hbase/master/MasterCoprocessorHost$158
      18: dup
      19: aload_0
      20: iload_1
      21: invokespecial #368                // Method org/apache/hadoop/hbase/master/MasterCoprocessorHost$158."<init>":(Lorg/apache/hadoop/hbase/master/MasterCoprocessorHost;Z)V
      24: invokevirtual #51                 // Method execOperation:(Lorg/apache/hadoop/hbase/coprocessor/CoprocessorHost$ObserverOperation;)Z
      27: pop
      28: return

  public void preSwitchExceedThrottleQuota(boolean) throws java.io.IOException;
    Code:
       0: aload_0
       1: aload_0
       2: getfield      #47                 // Field coprocEnvironments:Lorg/apache/hadoop/hbase/util/SortedList;
       5: invokevirtual #48                 // Method org/apache/hadoop/hbase/util/SortedList.isEmpty:()Z
       8: ifeq          15
      11: aconst_null
      12: goto          24
      15: new           #369                // class org/apache/hadoop/hbase/master/MasterCoprocessorHost$159
      18: dup
      19: aload_0
      20: iload_1
      21: invokespecial #370                // Method org/apache/hadoop/hbase/master/MasterCoprocessorHost$159."<init>":(Lorg/apache/hadoop/hbase/master/MasterCoprocessorHost;Z)V
      24: invokevirtual #51                 // Method execOperation:(Lorg/apache/hadoop/hbase/coprocessor/CoprocessorHost$ObserverOperation;)Z
      27: pop
      28: return

  public void postSwitchExceedThrottleQuota(boolean, boolean) throws java.io.IOException;
    Code:
       0: aload_0
       1: aload_0
       2: getfield      #47                 // Field coprocEnvironments:Lorg/apache/hadoop/hbase/util/SortedList;
       5: invokevirtual #48                 // Method org/apache/hadoop/hbase/util/SortedList.isEmpty:()Z
       8: ifeq          15
      11: aconst_null
      12: goto          25
      15: new           #371                // class org/apache/hadoop/hbase/master/MasterCoprocessorHost$160
      18: dup
      19: aload_0
      20: iload_1
      21: iload_2
      22: invokespecial #372                // Method org/apache/hadoop/hbase/master/MasterCoprocessorHost$160."<init>":(Lorg/apache/hadoop/hbase/master/MasterCoprocessorHost;ZZ)V
      25: invokevirtual #51                 // Method execOperation:(Lorg/apache/hadoop/hbase/coprocessor/CoprocessorHost$ObserverOperation;)Z
      28: pop
      29: return

  public void preGrant(org.apache.hadoop.hbase.security.access.UserPermission, boolean) throws java.io.IOException;
    Code:
       0: aload_0
       1: aload_0
       2: getfield      #47                 // Field coprocEnvironments:Lorg/apache/hadoop/hbase/util/SortedList;
       5: invokevirtual #48                 // Method org/apache/hadoop/hbase/util/SortedList.isEmpty:()Z
       8: ifeq          15
      11: aconst_null
      12: goto          25
      15: new           #373                // class org/apache/hadoop/hbase/master/MasterCoprocessorHost$161
      18: dup
      19: aload_0
      20: aload_1
      21: iload_2
      22: invokespecial #374                // Method org/apache/hadoop/hbase/master/MasterCoprocessorHost$161."<init>":(Lorg/apache/hadoop/hbase/master/MasterCoprocessorHost;Lorg/apache/hadoop/hbase/security/access/UserPermission;Z)V
      25: invokevirtual #51                 // Method execOperation:(Lorg/apache/hadoop/hbase/coprocessor/CoprocessorHost$ObserverOperation;)Z
      28: pop
      29: return

  public void postGrant(org.apache.hadoop.hbase.security.access.UserPermission, boolean) throws java.io.IOException;
    Code:
       0: aload_0
       1: aload_0
       2: getfield      #47                 // Field coprocEnvironments:Lorg/apache/hadoop/hbase/util/SortedList;
       5: invokevirtual #48                 // Method org/apache/hadoop/hbase/util/SortedList.isEmpty:()Z
       8: ifeq          15
      11: aconst_null
      12: goto          25
      15: new           #375                // class org/apache/hadoop/hbase/master/MasterCoprocessorHost$162
      18: dup
      19: aload_0
      20: aload_1
      21: iload_2
      22: invokespecial #376                // Method org/apache/hadoop/hbase/master/MasterCoprocessorHost$162."<init>":(Lorg/apache/hadoop/hbase/master/MasterCoprocessorHost;Lorg/apache/hadoop/hbase/security/access/UserPermission;Z)V
      25: invokevirtual #51                 // Method execOperation:(Lorg/apache/hadoop/hbase/coprocessor/CoprocessorHost$ObserverOperation;)Z
      28: pop
      29: return

  public void preRevoke(org.apache.hadoop.hbase.security.access.UserPermission) throws java.io.IOException;
    Code:
       0: aload_0
       1: aload_0
       2: getfield      #47                 // Field coprocEnvironments:Lorg/apache/hadoop/hbase/util/SortedList;
       5: invokevirtual #48                 // Method org/apache/hadoop/hbase/util/SortedList.isEmpty:()Z
       8: ifeq          15
      11: aconst_null
      12: goto          24
      15: new           #377                // class org/apache/hadoop/hbase/master/MasterCoprocessorHost$163
      18: dup
      19: aload_0
      20: aload_1
      21: invokespecial #378                // Method org/apache/hadoop/hbase/master/MasterCoprocessorHost$163."<init>":(Lorg/apache/hadoop/hbase/master/MasterCoprocessorHost;Lorg/apache/hadoop/hbase/security/access/UserPermission;)V
      24: invokevirtual #51                 // Method execOperation:(Lorg/apache/hadoop/hbase/coprocessor/CoprocessorHost$ObserverOperation;)Z
      27: pop
      28: return

  public void postRevoke(org.apache.hadoop.hbase.security.access.UserPermission) throws java.io.IOException;
    Code:
       0: aload_0
       1: aload_0
       2: getfield      #47                 // Field coprocEnvironments:Lorg/apache/hadoop/hbase/util/SortedList;
       5: invokevirtual #48                 // Method org/apache/hadoop/hbase/util/SortedList.isEmpty:()Z
       8: ifeq          15
      11: aconst_null
      12: goto          24
      15: new           #379                // class org/apache/hadoop/hbase/master/MasterCoprocessorHost$164
      18: dup
      19: aload_0
      20: aload_1
      21: invokespecial #380                // Method org/apache/hadoop/hbase/master/MasterCoprocessorHost$164."<init>":(Lorg/apache/hadoop/hbase/master/MasterCoprocessorHost;Lorg/apache/hadoop/hbase/security/access/UserPermission;)V
      24: invokevirtual #51                 // Method execOperation:(Lorg/apache/hadoop/hbase/coprocessor/CoprocessorHost$ObserverOperation;)Z
      27: pop
      28: return

  public void preGetUserPermissions(java.lang.String, java.lang.String, org.apache.hadoop.hbase.TableName, byte[], byte[]) throws java.io.IOException;
    Code:
       0: aload_0
       1: aload_0
       2: getfield      #47                 // Field coprocEnvironments:Lorg/apache/hadoop/hbase/util/SortedList;
       5: invokevirtual #48                 // Method org/apache/hadoop/hbase/util/SortedList.isEmpty:()Z
       8: ifeq          15
      11: aconst_null
      12: goto          30
      15: new           #381                // class org/apache/hadoop/hbase/master/MasterCoprocessorHost$165
      18: dup
      19: aload_0
      20: aload_1
      21: aload_2
      22: aload_3
      23: aload         4
      25: aload         5
      27: invokespecial #382                // Method org/apache/hadoop/hbase/master/MasterCoprocessorHost$165."<init>":(Lorg/apache/hadoop/hbase/master/MasterCoprocessorHost;Ljava/lang/String;Ljava/lang/String;Lorg/apache/hadoop/hbase/TableName;[B[B)V
      30: invokevirtual #51                 // Method execOperation:(Lorg/apache/hadoop/hbase/coprocessor/CoprocessorHost$ObserverOperation;)Z
      33: pop
      34: return

  public void postGetUserPermissions(java.lang.String, java.lang.String, org.apache.hadoop.hbase.TableName, byte[], byte[]) throws java.io.IOException;
    Code:
       0: aload_0
       1: aload_0
       2: getfield      #47                 // Field coprocEnvironments:Lorg/apache/hadoop/hbase/util/SortedList;
       5: invokevirtual #48                 // Method org/apache/hadoop/hbase/util/SortedList.isEmpty:()Z
       8: ifeq          15
      11: aconst_null
      12: goto          30
      15: new           #383                // class org/apache/hadoop/hbase/master/MasterCoprocessorHost$166
      18: dup
      19: aload_0
      20: aload_1
      21: aload_2
      22: aload_3
      23: aload         4
      25: aload         5
      27: invokespecial #384                // Method org/apache/hadoop/hbase/master/MasterCoprocessorHost$166."<init>":(Lorg/apache/hadoop/hbase/master/MasterCoprocessorHost;Ljava/lang/String;Ljava/lang/String;Lorg/apache/hadoop/hbase/TableName;[B[B)V
      30: invokevirtual #51                 // Method execOperation:(Lorg/apache/hadoop/hbase/coprocessor/CoprocessorHost$ObserverOperation;)Z
      33: pop
      34: return

  public void preHasUserPermissions(java.lang.String, java.util.List<org.apache.hadoop.hbase.security.access.Permission>) throws java.io.IOException;
    Code:
       0: aload_0
       1: aload_0
       2: getfield      #47                 // Field coprocEnvironments:Lorg/apache/hadoop/hbase/util/SortedList;
       5: invokevirtual #48                 // Method org/apache/hadoop/hbase/util/SortedList.isEmpty:()Z
       8: ifeq          15
      11: aconst_null
      12: goto          25
      15: new           #385                // class org/apache/hadoop/hbase/master/MasterCoprocessorHost$167
      18: dup
      19: aload_0
      20: aload_1
      21: aload_2
      22: invokespecial #386                // Method org/apache/hadoop/hbase/master/MasterCoprocessorHost$167."<init>":(Lorg/apache/hadoop/hbase/master/MasterCoprocessorHost;Ljava/lang/String;Ljava/util/List;)V
      25: invokevirtual #51                 // Method execOperation:(Lorg/apache/hadoop/hbase/coprocessor/CoprocessorHost$ObserverOperation;)Z
      28: pop
      29: return

  public void postHasUserPermissions(java.lang.String, java.util.List<org.apache.hadoop.hbase.security.access.Permission>) throws java.io.IOException;
    Code:
       0: aload_0
       1: aload_0
       2: getfield      #47                 // Field coprocEnvironments:Lorg/apache/hadoop/hbase/util/SortedList;
       5: invokevirtual #48                 // Method org/apache/hadoop/hbase/util/SortedList.isEmpty:()Z
       8: ifeq          15
      11: aconst_null
      12: goto          25
      15: new           #387                // class org/apache/hadoop/hbase/master/MasterCoprocessorHost$168
      18: dup
      19: aload_0
      20: aload_1
      21: aload_2
      22: invokespecial #388                // Method org/apache/hadoop/hbase/master/MasterCoprocessorHost$168."<init>":(Lorg/apache/hadoop/hbase/master/MasterCoprocessorHost;Ljava/lang/String;Ljava/util/List;)V
      25: invokevirtual #51                 // Method execOperation:(Lorg/apache/hadoop/hbase/coprocessor/CoprocessorHost$ObserverOperation;)Z
      28: pop
      29: return

  public org.apache.hadoop.hbase.Coprocessor checkAndGetInstance(java.lang.Class) throws java.lang.InstantiationException, java.lang.IllegalAccessException;
    Code:
       0: aload_0
       1: aload_1
       2: invokevirtual #389                // Method checkAndGetInstance:(Ljava/lang/Class;)Lorg/apache/hadoop/hbase/coprocessor/MasterCoprocessor;
       5: areturn

  public org.apache.hadoop.hbase.CoprocessorEnvironment createEnvironment(org.apache.hadoop.hbase.Coprocessor, int, int, org.apache.hadoop.conf.Configuration);
    Code:
       0: aload_0
       1: aload_1
       2: checkcast     #29                 // class org/apache/hadoop/hbase/coprocessor/MasterCoprocessor
       5: iload_2
       6: iload_3
       7: aload         4
       9: invokevirtual #390                // Method createEnvironment:(Lorg/apache/hadoop/hbase/coprocessor/MasterCoprocessor;IILorg/apache/hadoop/conf/Configuration;)Lorg/apache/hadoop/hbase/master/MasterCoprocessorHost$MasterEnvironment;
      12: areturn

  static org.apache.hadoop.hbase.coprocessor.CoprocessorHost$ObserverGetter access$000(org.apache.hadoop.hbase.master.MasterCoprocessorHost);
    Code:
       0: aload_0
       1: getfield      #1                  // Field masterObserverGetter:Lorg/apache/hadoop/hbase/coprocessor/CoprocessorHost$ObserverGetter;
       4: areturn

  static {};
    Code:
       0: ldc_w         #391                // class org/apache/hadoop/hbase/master/MasterCoprocessorHost
       3: invokestatic  #392                // Method org/slf4j/LoggerFactory.getLogger:(Ljava/lang/Class;)Lorg/slf4j/Logger;
       6: putstatic     #9                  // Field LOG:Lorg/slf4j/Logger;
       9: return
}
