Compiled from "MasterProcedureManagerHost.java"
public class org.apache.hadoop.hbase.procedure.MasterProcedureManagerHost extends org.apache.hadoop.hbase.procedure.ProcedureManagerHost<org.apache.hadoop.hbase.procedure.MasterProcedureManager> {
  public org.apache.hadoop.hbase.procedure.MasterProcedureManagerHost();
    Code:
       0: aload_0
       1: invokespecial #1                  // Method org/apache/hadoop/hbase/procedure/ProcedureManagerHost."<init>":()V
       4: aload_0
       5: new           #2                  // class java/util/Hashtable
       8: dup
       9: invokespecial #3                  // Method java/util/Hashtable."<init>":()V
      12: putfield      #4                  // Field procedureMgrMap:Ljava/util/Hashtable;
      15: return

  public void loadProcedures(org.apache.hadoop.conf.Configuration);
    Code:
       0: aload_0
       1: aload_1
       2: ldc           #6                  // String hbase.procedure.master.classes
       4: invokevirtual #7                  // Method loadUserProcedures:(Lorg/apache/hadoop/conf/Configuration;Ljava/lang/String;)V
       7: aload_0
       8: invokevirtual #8                  // Method getProcedureManagers:()Ljava/util/Set;
      11: invokeinterface #9,  1            // InterfaceMethod java/util/Set.iterator:()Ljava/util/Iterator;
      16: astore_2
      17: aload_2
      18: invokeinterface #10,  1           // InterfaceMethod java/util/Iterator.hasNext:()Z
      23: ifeq          52
      26: aload_2
      27: invokeinterface #11,  1           // InterfaceMethod java/util/Iterator.next:()Ljava/lang/Object;
      32: checkcast     #12                 // class org/apache/hadoop/hbase/procedure/MasterProcedureManager
      35: astore_3
      36: aload_0
      37: getfield      #4                  // Field procedureMgrMap:Ljava/util/Hashtable;
      40: aload_3
      41: invokevirtual #13                 // Method org/apache/hadoop/hbase/procedure/MasterProcedureManager.getProcedureSignature:()Ljava/lang/String;
      44: aload_3
      45: invokevirtual #14                 // Method java/util/Hashtable.put:(Ljava/lang/Object;Ljava/lang/Object;)Ljava/lang/Object;
      48: pop
      49: goto          17
      52: return

  public void initialize(org.apache.hadoop.hbase.master.MasterServices, org.apache.hadoop.hbase.master.MetricsMaster) throws org.apache.zookeeper.KeeperException, java.io.IOException, java.lang.UnsupportedOperationException;
    Code:
       0: aload_0
       1: invokevirtual #8                  // Method getProcedureManagers:()Ljava/util/Set;
       4: invokeinterface #9,  1            // InterfaceMethod java/util/Set.iterator:()Ljava/util/Iterator;
       9: astore_3
      10: aload_3
      11: invokeinterface #10,  1           // InterfaceMethod java/util/Iterator.hasNext:()Z
      16: ifeq          40
      19: aload_3
      20: invokeinterface #11,  1           // InterfaceMethod java/util/Iterator.next:()Ljava/lang/Object;
      25: checkcast     #12                 // class org/apache/hadoop/hbase/procedure/MasterProcedureManager
      28: astore        4
      30: aload         4
      32: aload_1
      33: aload_2
      34: invokevirtual #15                 // Method org/apache/hadoop/hbase/procedure/MasterProcedureManager.initialize:(Lorg/apache/hadoop/hbase/master/MasterServices;Lorg/apache/hadoop/hbase/master/MetricsMaster;)V
      37: goto          10
      40: return

  public void stop(java.lang.String);
    Code:
       0: aload_0
       1: invokevirtual #8                  // Method getProcedureManagers:()Ljava/util/Set;
       4: invokeinterface #9,  1            // InterfaceMethod java/util/Set.iterator:()Ljava/util/Iterator;
       9: astore_2
      10: aload_2
      11: invokeinterface #10,  1           // InterfaceMethod java/util/Iterator.hasNext:()Z
      16: ifeq          37
      19: aload_2
      20: invokeinterface #11,  1           // InterfaceMethod java/util/Iterator.next:()Ljava/lang/Object;
      25: checkcast     #12                 // class org/apache/hadoop/hbase/procedure/MasterProcedureManager
      28: astore_3
      29: aload_3
      30: aload_1
      31: invokevirtual #16                 // Method org/apache/hadoop/hbase/procedure/MasterProcedureManager.stop:(Ljava/lang/String;)V
      34: goto          10
      37: return

  public org.apache.hadoop.hbase.procedure.MasterProcedureManager getProcedureManager(java.lang.String);
    Code:
       0: aload_0
       1: getfield      #4                  // Field procedureMgrMap:Ljava/util/Hashtable;
       4: aload_1
       5: invokevirtual #17                 // Method java/util/Hashtable.get:(Ljava/lang/Object;)Ljava/lang/Object;
       8: checkcast     #12                 // class org/apache/hadoop/hbase/procedure/MasterProcedureManager
      11: areturn
}
