Compiled from "MasterMobCompactionThread.java"
class org.apache.hadoop.hbase.master.MasterMobCompactionThread$1 implements java.util.concurrent.ThreadFactory {
  final java.lang.String val$n;

  final org.apache.hadoop.hbase.master.MasterMobCompactionThread this$0;

  org.apache.hadoop.hbase.master.MasterMobCompactionThread$1(org.apache.hadoop.hbase.master.MasterMobCompactionThread, java.lang.String);
    Code:
       0: aload_0
       1: aload_1
       2: putfield      #1                  // Field this$0:Lorg/apache/hadoop/hbase/master/MasterMobCompactionThread;
       5: aload_0
       6: aload_2
       7: putfield      #2                  // Field val$n:Ljava/lang/String;
      10: aload_0
      11: invokespecial #3                  // Method java/lang/Object."<init>":()V
      14: return

  public java.lang.Thread newThread(java.lang.Runnable);
    Code:
       0: new           #4                  // class java/lang/StringBuilder
       3: dup
       4: invokespecial #5                  // Method java/lang/StringBuilder."<init>":()V
       7: aload_0
       8: getfield      #2                  // Field val$n:Ljava/lang/String;
      11: invokevirtual #6                  // Method java/lang/StringBuilder.append:(Ljava/lang/String;)Ljava/lang/StringBuilder;
      14: ldc           #7                  // String -MasterMobCompaction-
      16: invokevirtual #6                  // Method java/lang/StringBuilder.append:(Ljava/lang/String;)Ljava/lang/StringBuilder;
      19: invokestatic  #8                  // Method org/apache/hadoop/hbase/util/EnvironmentEdgeManager.currentTime:()J
      22: invokevirtual #9                  // Method java/lang/StringBuilder.append:(J)Ljava/lang/StringBuilder;
      25: invokevirtual #10                 // Method java/lang/StringBuilder.toString:()Ljava/lang/String;
      28: astore_2
      29: new           #11                 // class java/lang/Thread
      32: dup
      33: aload_1
      34: aload_2
      35: invokespecial #12                 // Method java/lang/Thread."<init>":(Ljava/lang/Runnable;Ljava/lang/String;)V
      38: areturn
}
