Compiled from "MasterProcedureProtos.java"
public final class org.apache.hadoop.hbase.shaded.protobuf.generated.MasterProcedureProtos$ServerCrashStateData$Builder extends org.apache.hbase.thirdparty.com.google.protobuf.GeneratedMessageV3$Builder<org.apache.hadoop.hbase.shaded.protobuf.generated.MasterProcedureProtos$ServerCrashStateData$Builder> implements org.apache.hadoop.hbase.shaded.protobuf.generated.MasterProcedureProtos$ServerCrashStateDataOrBuilder {
  public static final org.apache.hbase.thirdparty.com.google.protobuf.Descriptors$Descriptor getDescriptor();
    Code:
       0: invokestatic  #3                  // Method org/apache/hadoop/hbase/shaded/protobuf/generated/MasterProcedureProtos.access$20000:()Lorg/apache/hbase/thirdparty/com/google/protobuf/Descriptors$Descriptor;
       3: areturn

  protected org.apache.hbase.thirdparty.com.google.protobuf.GeneratedMessageV3$FieldAccessorTable internalGetFieldAccessorTable();
    Code:
       0: invokestatic  #4                  // Method org/apache/hadoop/hbase/shaded/protobuf/generated/MasterProcedureProtos.access$20100:()Lorg/apache/hbase/thirdparty/com/google/protobuf/GeneratedMessageV3$FieldAccessorTable;
       3: ldc           #5                  // class org/apache/hadoop/hbase/shaded/protobuf/generated/MasterProcedureProtos$ServerCrashStateData
       5: ldc           #6                  // class org/apache/hadoop/hbase/shaded/protobuf/generated/MasterProcedureProtos$ServerCrashStateData$Builder
       7: invokevirtual #7                  // Method org/apache/hbase/thirdparty/com/google/protobuf/GeneratedMessageV3$FieldAccessorTable.ensureFieldAccessorsInitialized:(Ljava/lang/Class;Ljava/lang/Class;)Lorg/apache/hbase/thirdparty/com/google/protobuf/GeneratedMessageV3$FieldAccessorTable;
      10: areturn

  public org.apache.hadoop.hbase.shaded.protobuf.generated.MasterProcedureProtos$ServerCrashStateData$Builder clear();
    Code:
       0: aload_0
       1: invokespecial #20                 // Method org/apache/hbase/thirdparty/com/google/protobuf/GeneratedMessageV3$Builder.clear:()Lorg/apache/hbase/thirdparty/com/google/protobuf/GeneratedMessageV3$Builder;
       4: pop
       5: aload_0
       6: getfield      #21                 // Field serverNameBuilder_:Lorg/apache/hbase/thirdparty/com/google/protobuf/SingleFieldBuilderV3;
       9: ifnonnull     20
      12: aload_0
      13: aconst_null
      14: putfield      #9                  // Field serverName_:Lorg/apache/hadoop/hbase/shaded/protobuf/generated/HBaseProtos$ServerName;
      17: goto          28
      20: aload_0
      21: getfield      #21                 // Field serverNameBuilder_:Lorg/apache/hbase/thirdparty/com/google/protobuf/SingleFieldBuilderV3;
      24: invokevirtual #22                 // Method org/apache/hbase/thirdparty/com/google/protobuf/SingleFieldBuilderV3.clear:()Lorg/apache/hbase/thirdparty/com/google/protobuf/SingleFieldBuilderV3;
      27: pop
      28: aload_0
      29: aload_0
      30: getfield      #23                 // Field bitField0_:I
      33: bipush        -2
      35: iand
      36: putfield      #23                 // Field bitField0_:I
      39: aload_0
      40: getfield      #24                 // Field regionsOnCrashedServerBuilder_:Lorg/apache/hbase/thirdparty/com/google/protobuf/RepeatedFieldBuilderV3;
      43: ifnonnull     67
      46: aload_0
      47: invokestatic  #10                 // Method java/util/Collections.emptyList:()Ljava/util/List;
      50: putfield      #11                 // Field regionsOnCrashedServer_:Ljava/util/List;
      53: aload_0
      54: aload_0
      55: getfield      #23                 // Field bitField0_:I
      58: bipush        -3
      60: iand
      61: putfield      #23                 // Field bitField0_:I
      64: goto          74
      67: aload_0
      68: getfield      #24                 // Field regionsOnCrashedServerBuilder_:Lorg/apache/hbase/thirdparty/com/google/protobuf/RepeatedFieldBuilderV3;
      71: invokevirtual #25                 // Method org/apache/hbase/thirdparty/com/google/protobuf/RepeatedFieldBuilderV3.clear:()V
      74: aload_0
      75: getfield      #26                 // Field regionsAssignedBuilder_:Lorg/apache/hbase/thirdparty/com/google/protobuf/RepeatedFieldBuilderV3;
      78: ifnonnull     102
      81: aload_0
      82: invokestatic  #10                 // Method java/util/Collections.emptyList:()Ljava/util/List;
      85: putfield      #12                 // Field regionsAssigned_:Ljava/util/List;
      88: aload_0
      89: aload_0
      90: getfield      #23                 // Field bitField0_:I
      93: bipush        -5
      95: iand
      96: putfield      #23                 // Field bitField0_:I
      99: goto          109
     102: aload_0
     103: getfield      #26                 // Field regionsAssignedBuilder_:Lorg/apache/hbase/thirdparty/com/google/protobuf/RepeatedFieldBuilderV3;
     106: invokevirtual #25                 // Method org/apache/hbase/thirdparty/com/google/protobuf/RepeatedFieldBuilderV3.clear:()V
     109: aload_0
     110: iconst_0
     111: putfield      #27                 // Field carryingMeta_:Z
     114: aload_0
     115: aload_0
     116: getfield      #23                 // Field bitField0_:I
     119: bipush        -9
     121: iand
     122: putfield      #23                 // Field bitField0_:I
     125: aload_0
     126: iconst_1
     127: putfield      #13                 // Field shouldSplitWal_:Z
     130: aload_0
     131: aload_0
     132: getfield      #23                 // Field bitField0_:I
     135: bipush        -17
     137: iand
     138: putfield      #23                 // Field bitField0_:I
     141: aload_0
     142: areturn

  public org.apache.hbase.thirdparty.com.google.protobuf.Descriptors$Descriptor getDescriptorForType();
    Code:
       0: invokestatic  #3                  // Method org/apache/hadoop/hbase/shaded/protobuf/generated/MasterProcedureProtos.access$20000:()Lorg/apache/hbase/thirdparty/com/google/protobuf/Descriptors$Descriptor;
       3: areturn

  public org.apache.hadoop.hbase.shaded.protobuf.generated.MasterProcedureProtos$ServerCrashStateData getDefaultInstanceForType();
    Code:
       0: invokestatic  #28                 // Method org/apache/hadoop/hbase/shaded/protobuf/generated/MasterProcedureProtos$ServerCrashStateData.getDefaultInstance:()Lorg/apache/hadoop/hbase/shaded/protobuf/generated/MasterProcedureProtos$ServerCrashStateData;
       3: areturn

  public org.apache.hadoop.hbase.shaded.protobuf.generated.MasterProcedureProtos$ServerCrashStateData build();
    Code:
       0: aload_0
       1: invokevirtual #29                 // Method buildPartial:()Lorg/apache/hadoop/hbase/shaded/protobuf/generated/MasterProcedureProtos$ServerCrashStateData;
       4: astore_1
       5: aload_1
       6: invokevirtual #30                 // Method org/apache/hadoop/hbase/shaded/protobuf/generated/MasterProcedureProtos$ServerCrashStateData.isInitialized:()Z
       9: ifne          17
      12: aload_1
      13: invokestatic  #31                 // Method newUninitializedMessageException:(Lorg/apache/hbase/thirdparty/com/google/protobuf/Message;)Lorg/apache/hbase/thirdparty/com/google/protobuf/UninitializedMessageException;
      16: athrow
      17: aload_1
      18: areturn

  public org.apache.hadoop.hbase.shaded.protobuf.generated.MasterProcedureProtos$ServerCrashStateData buildPartial();
    Code:
       0: new           #5                  // class org/apache/hadoop/hbase/shaded/protobuf/generated/MasterProcedureProtos$ServerCrashStateData
       3: dup
       4: aload_0
       5: aconst_null
       6: invokespecial #32                 // Method org/apache/hadoop/hbase/shaded/protobuf/generated/MasterProcedureProtos$ServerCrashStateData."<init>":(Lorg/apache/hbase/thirdparty/com/google/protobuf/GeneratedMessageV3$Builder;Lorg/apache/hadoop/hbase/shaded/protobuf/generated/MasterProcedureProtos$1;)V
       9: astore_1
      10: aload_0
      11: getfield      #23                 // Field bitField0_:I
      14: istore_2
      15: iconst_0
      16: istore_3
      17: iload_2
      18: iconst_1
      19: iand
      20: iconst_1
      21: if_icmpne     28
      24: iload_3
      25: iconst_1
      26: ior
      27: istore_3
      28: aload_0
      29: getfield      #21                 // Field serverNameBuilder_:Lorg/apache/hbase/thirdparty/com/google/protobuf/SingleFieldBuilderV3;
      32: ifnonnull     47
      35: aload_1
      36: aload_0
      37: getfield      #9                  // Field serverName_:Lorg/apache/hadoop/hbase/shaded/protobuf/generated/HBaseProtos$ServerName;
      40: invokestatic  #33                 // Method org/apache/hadoop/hbase/shaded/protobuf/generated/MasterProcedureProtos$ServerCrashStateData.access$20602:(Lorg/apache/hadoop/hbase/shaded/protobuf/generated/MasterProcedureProtos$ServerCrashStateData;Lorg/apache/hadoop/hbase/shaded/protobuf/generated/HBaseProtos$ServerName;)Lorg/apache/hadoop/hbase/shaded/protobuf/generated/HBaseProtos$ServerName;
      43: pop
      44: goto          62
      47: aload_1
      48: aload_0
      49: getfield      #21                 // Field serverNameBuilder_:Lorg/apache/hbase/thirdparty/com/google/protobuf/SingleFieldBuilderV3;
      52: invokevirtual #34                 // Method org/apache/hbase/thirdparty/com/google/protobuf/SingleFieldBuilderV3.build:()Lorg/apache/hbase/thirdparty/com/google/protobuf/AbstractMessage;
      55: checkcast     #35                 // class org/apache/hadoop/hbase/shaded/protobuf/generated/HBaseProtos$ServerName
      58: invokestatic  #33                 // Method org/apache/hadoop/hbase/shaded/protobuf/generated/MasterProcedureProtos$ServerCrashStateData.access$20602:(Lorg/apache/hadoop/hbase/shaded/protobuf/generated/MasterProcedureProtos$ServerCrashStateData;Lorg/apache/hadoop/hbase/shaded/protobuf/generated/HBaseProtos$ServerName;)Lorg/apache/hadoop/hbase/shaded/protobuf/generated/HBaseProtos$ServerName;
      61: pop
      62: aload_0
      63: getfield      #24                 // Field regionsOnCrashedServerBuilder_:Lorg/apache/hbase/thirdparty/com/google/protobuf/RepeatedFieldBuilderV3;
      66: ifnonnull     113
      69: aload_0
      70: getfield      #23                 // Field bitField0_:I
      73: iconst_2
      74: iand
      75: iconst_2
      76: if_icmpne     101
      79: aload_0
      80: aload_0
      81: getfield      #11                 // Field regionsOnCrashedServer_:Ljava/util/List;
      84: invokestatic  #36                 // Method java/util/Collections.unmodifiableList:(Ljava/util/List;)Ljava/util/List;
      87: putfield      #11                 // Field regionsOnCrashedServer_:Ljava/util/List;
      90: aload_0
      91: aload_0
      92: getfield      #23                 // Field bitField0_:I
      95: bipush        -3
      97: iand
      98: putfield      #23                 // Field bitField0_:I
     101: aload_1
     102: aload_0
     103: getfield      #11                 // Field regionsOnCrashedServer_:Ljava/util/List;
     106: invokestatic  #37                 // Method org/apache/hadoop/hbase/shaded/protobuf/generated/MasterProcedureProtos$ServerCrashStateData.access$20702:(Lorg/apache/hadoop/hbase/shaded/protobuf/generated/MasterProcedureProtos$ServerCrashStateData;Ljava/util/List;)Ljava/util/List;
     109: pop
     110: goto          125
     113: aload_1
     114: aload_0
     115: getfield      #24                 // Field regionsOnCrashedServerBuilder_:Lorg/apache/hbase/thirdparty/com/google/protobuf/RepeatedFieldBuilderV3;
     118: invokevirtual #38                 // Method org/apache/hbase/thirdparty/com/google/protobuf/RepeatedFieldBuilderV3.build:()Ljava/util/List;
     121: invokestatic  #37                 // Method org/apache/hadoop/hbase/shaded/protobuf/generated/MasterProcedureProtos$ServerCrashStateData.access$20702:(Lorg/apache/hadoop/hbase/shaded/protobuf/generated/MasterProcedureProtos$ServerCrashStateData;Ljava/util/List;)Ljava/util/List;
     124: pop
     125: aload_0
     126: getfield      #26                 // Field regionsAssignedBuilder_:Lorg/apache/hbase/thirdparty/com/google/protobuf/RepeatedFieldBuilderV3;
     129: ifnonnull     176
     132: aload_0
     133: getfield      #23                 // Field bitField0_:I
     136: iconst_4
     137: iand
     138: iconst_4
     139: if_icmpne     164
     142: aload_0
     143: aload_0
     144: getfield      #12                 // Field regionsAssigned_:Ljava/util/List;
     147: invokestatic  #36                 // Method java/util/Collections.unmodifiableList:(Ljava/util/List;)Ljava/util/List;
     150: putfield      #12                 // Field regionsAssigned_:Ljava/util/List;
     153: aload_0
     154: aload_0
     155: getfield      #23                 // Field bitField0_:I
     158: bipush        -5
     160: iand
     161: putfield      #23                 // Field bitField0_:I
     164: aload_1
     165: aload_0
     166: getfield      #12                 // Field regionsAssigned_:Ljava/util/List;
     169: invokestatic  #39                 // Method org/apache/hadoop/hbase/shaded/protobuf/generated/MasterProcedureProtos$ServerCrashStateData.access$20802:(Lorg/apache/hadoop/hbase/shaded/protobuf/generated/MasterProcedureProtos$ServerCrashStateData;Ljava/util/List;)Ljava/util/List;
     172: pop
     173: goto          188
     176: aload_1
     177: aload_0
     178: getfield      #26                 // Field regionsAssignedBuilder_:Lorg/apache/hbase/thirdparty/com/google/protobuf/RepeatedFieldBuilderV3;
     181: invokevirtual #38                 // Method org/apache/hbase/thirdparty/com/google/protobuf/RepeatedFieldBuilderV3.build:()Ljava/util/List;
     184: invokestatic  #39                 // Method org/apache/hadoop/hbase/shaded/protobuf/generated/MasterProcedureProtos$ServerCrashStateData.access$20802:(Lorg/apache/hadoop/hbase/shaded/protobuf/generated/MasterProcedureProtos$ServerCrashStateData;Ljava/util/List;)Ljava/util/List;
     187: pop
     188: iload_2
     189: bipush        8
     191: iand
     192: bipush        8
     194: if_icmpne     201
     197: iload_3
     198: iconst_2
     199: ior
     200: istore_3
     201: aload_1
     202: aload_0
     203: getfield      #27                 // Field carryingMeta_:Z
     206: invokestatic  #40                 // Method org/apache/hadoop/hbase/shaded/protobuf/generated/MasterProcedureProtos$ServerCrashStateData.access$20902:(Lorg/apache/hadoop/hbase/shaded/protobuf/generated/MasterProcedureProtos$ServerCrashStateData;Z)Z
     209: pop
     210: iload_2
     211: bipush        16
     213: iand
     214: bipush        16
     216: if_icmpne     223
     219: iload_3
     220: iconst_4
     221: ior
     222: istore_3
     223: aload_1
     224: aload_0
     225: getfield      #13                 // Field shouldSplitWal_:Z
     228: invokestatic  #41                 // Method org/apache/hadoop/hbase/shaded/protobuf/generated/MasterProcedureProtos$ServerCrashStateData.access$21002:(Lorg/apache/hadoop/hbase/shaded/protobuf/generated/MasterProcedureProtos$ServerCrashStateData;Z)Z
     231: pop
     232: aload_1
     233: iload_3
     234: invokestatic  #42                 // Method org/apache/hadoop/hbase/shaded/protobuf/generated/MasterProcedureProtos$ServerCrashStateData.access$21102:(Lorg/apache/hadoop/hbase/shaded/protobuf/generated/MasterProcedureProtos$ServerCrashStateData;I)I
     237: pop
     238: aload_0
     239: invokevirtual #43                 // Method onBuilt:()V
     242: aload_1
     243: areturn

  public org.apache.hadoop.hbase.shaded.protobuf.generated.MasterProcedureProtos$ServerCrashStateData$Builder clone();
    Code:
       0: aload_0
       1: invokespecial #44                 // Method org/apache/hbase/thirdparty/com/google/protobuf/GeneratedMessageV3$Builder.clone:()Lorg/apache/hbase/thirdparty/com/google/protobuf/GeneratedMessageV3$Builder;
       4: checkcast     #6                  // class org/apache/hadoop/hbase/shaded/protobuf/generated/MasterProcedureProtos$ServerCrashStateData$Builder
       7: areturn

  public org.apache.hadoop.hbase.shaded.protobuf.generated.MasterProcedureProtos$ServerCrashStateData$Builder setField(org.apache.hbase.thirdparty.com.google.protobuf.Descriptors$FieldDescriptor, java.lang.Object);
    Code:
       0: aload_0
       1: aload_1
       2: aload_2
       3: invokespecial #45                 // Method org/apache/hbase/thirdparty/com/google/protobuf/GeneratedMessageV3$Builder.setField:(Lorg/apache/hbase/thirdparty/com/google/protobuf/Descriptors$FieldDescriptor;Ljava/lang/Object;)Lorg/apache/hbase/thirdparty/com/google/protobuf/GeneratedMessageV3$Builder;
       6: checkcast     #6                  // class org/apache/hadoop/hbase/shaded/protobuf/generated/MasterProcedureProtos$ServerCrashStateData$Builder
       9: areturn

  public org.apache.hadoop.hbase.shaded.protobuf.generated.MasterProcedureProtos$ServerCrashStateData$Builder clearField(org.apache.hbase.thirdparty.com.google.protobuf.Descriptors$FieldDescriptor);
    Code:
       0: aload_0
       1: aload_1
       2: invokespecial #46                 // Method org/apache/hbase/thirdparty/com/google/protobuf/GeneratedMessageV3$Builder.clearField:(Lorg/apache/hbase/thirdparty/com/google/protobuf/Descriptors$FieldDescriptor;)Lorg/apache/hbase/thirdparty/com/google/protobuf/GeneratedMessageV3$Builder;
       5: checkcast     #6                  // class org/apache/hadoop/hbase/shaded/protobuf/generated/MasterProcedureProtos$ServerCrashStateData$Builder
       8: areturn

  public org.apache.hadoop.hbase.shaded.protobuf.generated.MasterProcedureProtos$ServerCrashStateData$Builder clearOneof(org.apache.hbase.thirdparty.com.google.protobuf.Descriptors$OneofDescriptor);
    Code:
       0: aload_0
       1: aload_1
       2: invokespecial #47                 // Method org/apache/hbase/thirdparty/com/google/protobuf/GeneratedMessageV3$Builder.clearOneof:(Lorg/apache/hbase/thirdparty/com/google/protobuf/Descriptors$OneofDescriptor;)Lorg/apache/hbase/thirdparty/com/google/protobuf/GeneratedMessageV3$Builder;
       5: checkcast     #6                  // class org/apache/hadoop/hbase/shaded/protobuf/generated/MasterProcedureProtos$ServerCrashStateData$Builder
       8: areturn

  public org.apache.hadoop.hbase.shaded.protobuf.generated.MasterProcedureProtos$ServerCrashStateData$Builder setRepeatedField(org.apache.hbase.thirdparty.com.google.protobuf.Descriptors$FieldDescriptor, int, java.lang.Object);
    Code:
       0: aload_0
       1: aload_1
       2: iload_2
       3: aload_3
       4: invokespecial #48                 // Method org/apache/hbase/thirdparty/com/google/protobuf/GeneratedMessageV3$Builder.setRepeatedField:(Lorg/apache/hbase/thirdparty/com/google/protobuf/Descriptors$FieldDescriptor;ILjava/lang/Object;)Lorg/apache/hbase/thirdparty/com/google/protobuf/GeneratedMessageV3$Builder;
       7: checkcast     #6                  // class org/apache/hadoop/hbase/shaded/protobuf/generated/MasterProcedureProtos$ServerCrashStateData$Builder
      10: areturn

  public org.apache.hadoop.hbase.shaded.protobuf.generated.MasterProcedureProtos$ServerCrashStateData$Builder addRepeatedField(org.apache.hbase.thirdparty.com.google.protobuf.Descriptors$FieldDescriptor, java.lang.Object);
    Code:
       0: aload_0
       1: aload_1
       2: aload_2
       3: invokespecial #49                 // Method org/apache/hbase/thirdparty/com/google/protobuf/GeneratedMessageV3$Builder.addRepeatedField:(Lorg/apache/hbase/thirdparty/com/google/protobuf/Descriptors$FieldDescriptor;Ljava/lang/Object;)Lorg/apache/hbase/thirdparty/com/google/protobuf/GeneratedMessageV3$Builder;
       6: checkcast     #6                  // class org/apache/hadoop/hbase/shaded/protobuf/generated/MasterProcedureProtos$ServerCrashStateData$Builder
       9: areturn

  public org.apache.hadoop.hbase.shaded.protobuf.generated.MasterProcedureProtos$ServerCrashStateData$Builder mergeFrom(org.apache.hbase.thirdparty.com.google.protobuf.Message);
    Code:
       0: aload_1
       1: instanceof    #5                  // class org/apache/hadoop/hbase/shaded/protobuf/generated/MasterProcedureProtos$ServerCrashStateData
       4: ifeq          16
       7: aload_0
       8: aload_1
       9: checkcast     #5                  // class org/apache/hadoop/hbase/shaded/protobuf/generated/MasterProcedureProtos$ServerCrashStateData
      12: invokevirtual #50                 // Method mergeFrom:(Lorg/apache/hadoop/hbase/shaded/protobuf/generated/MasterProcedureProtos$ServerCrashStateData;)Lorg/apache/hadoop/hbase/shaded/protobuf/generated/MasterProcedureProtos$ServerCrashStateData$Builder;
      15: areturn
      16: aload_0
      17: aload_1
      18: invokespecial #51                 // Method org/apache/hbase/thirdparty/com/google/protobuf/GeneratedMessageV3$Builder.mergeFrom:(Lorg/apache/hbase/thirdparty/com/google/protobuf/Message;)Lorg/apache/hbase/thirdparty/com/google/protobuf/AbstractMessage$Builder;
      21: pop
      22: aload_0
      23: areturn

  public org.apache.hadoop.hbase.shaded.protobuf.generated.MasterProcedureProtos$ServerCrashStateData$Builder mergeFrom(org.apache.hadoop.hbase.shaded.protobuf.generated.MasterProcedureProtos$ServerCrashStateData);
    Code:
       0: aload_1
       1: invokestatic  #28                 // Method org/apache/hadoop/hbase/shaded/protobuf/generated/MasterProcedureProtos$ServerCrashStateData.getDefaultInstance:()Lorg/apache/hadoop/hbase/shaded/protobuf/generated/MasterProcedureProtos$ServerCrashStateData;
       4: if_acmpne     9
       7: aload_0
       8: areturn
       9: aload_1
      10: invokevirtual #52                 // Method org/apache/hadoop/hbase/shaded/protobuf/generated/MasterProcedureProtos$ServerCrashStateData.hasServerName:()Z
      13: ifeq          25
      16: aload_0
      17: aload_1
      18: invokevirtual #53                 // Method org/apache/hadoop/hbase/shaded/protobuf/generated/MasterProcedureProtos$ServerCrashStateData.getServerName:()Lorg/apache/hadoop/hbase/shaded/protobuf/generated/HBaseProtos$ServerName;
      21: invokevirtual #54                 // Method mergeServerName:(Lorg/apache/hadoop/hbase/shaded/protobuf/generated/HBaseProtos$ServerName;)Lorg/apache/hadoop/hbase/shaded/protobuf/generated/MasterProcedureProtos$ServerCrashStateData$Builder;
      24: pop
      25: aload_0
      26: getfield      #24                 // Field regionsOnCrashedServerBuilder_:Lorg/apache/hbase/thirdparty/com/google/protobuf/RepeatedFieldBuilderV3;
      29: ifnonnull     103
      32: aload_1
      33: invokestatic  #55                 // Method org/apache/hadoop/hbase/shaded/protobuf/generated/MasterProcedureProtos$ServerCrashStateData.access$20700:(Lorg/apache/hadoop/hbase/shaded/protobuf/generated/MasterProcedureProtos$ServerCrashStateData;)Ljava/util/List;
      36: invokeinterface #56,  1           // InterfaceMethod java/util/List.isEmpty:()Z
      41: ifne          189
      44: aload_0
      45: getfield      #11                 // Field regionsOnCrashedServer_:Ljava/util/List;
      48: invokeinterface #56,  1           // InterfaceMethod java/util/List.isEmpty:()Z
      53: ifeq          78
      56: aload_0
      57: aload_1
      58: invokestatic  #55                 // Method org/apache/hadoop/hbase/shaded/protobuf/generated/MasterProcedureProtos$ServerCrashStateData.access$20700:(Lorg/apache/hadoop/hbase/shaded/protobuf/generated/MasterProcedureProtos$ServerCrashStateData;)Ljava/util/List;
      61: putfield      #11                 // Field regionsOnCrashedServer_:Ljava/util/List;
      64: aload_0
      65: aload_0
      66: getfield      #23                 // Field bitField0_:I
      69: bipush        -3
      71: iand
      72: putfield      #23                 // Field bitField0_:I
      75: goto          96
      78: aload_0
      79: invokespecial #57                 // Method ensureRegionsOnCrashedServerIsMutable:()V
      82: aload_0
      83: getfield      #11                 // Field regionsOnCrashedServer_:Ljava/util/List;
      86: aload_1
      87: invokestatic  #55                 // Method org/apache/hadoop/hbase/shaded/protobuf/generated/MasterProcedureProtos$ServerCrashStateData.access$20700:(Lorg/apache/hadoop/hbase/shaded/protobuf/generated/MasterProcedureProtos$ServerCrashStateData;)Ljava/util/List;
      90: invokeinterface #58,  2           // InterfaceMethod java/util/List.addAll:(Ljava/util/Collection;)Z
      95: pop
      96: aload_0
      97: invokevirtual #59                 // Method onChanged:()V
     100: goto          189
     103: aload_1
     104: invokestatic  #55                 // Method org/apache/hadoop/hbase/shaded/protobuf/generated/MasterProcedureProtos$ServerCrashStateData.access$20700:(Lorg/apache/hadoop/hbase/shaded/protobuf/generated/MasterProcedureProtos$ServerCrashStateData;)Ljava/util/List;
     107: invokeinterface #56,  1           // InterfaceMethod java/util/List.isEmpty:()Z
     112: ifne          189
     115: aload_0
     116: getfield      #24                 // Field regionsOnCrashedServerBuilder_:Lorg/apache/hbase/thirdparty/com/google/protobuf/RepeatedFieldBuilderV3;
     119: invokevirtual #60                 // Method org/apache/hbase/thirdparty/com/google/protobuf/RepeatedFieldBuilderV3.isEmpty:()Z
     122: ifeq          177
     125: aload_0
     126: getfield      #24                 // Field regionsOnCrashedServerBuilder_:Lorg/apache/hbase/thirdparty/com/google/protobuf/RepeatedFieldBuilderV3;
     129: invokevirtual #61                 // Method org/apache/hbase/thirdparty/com/google/protobuf/RepeatedFieldBuilderV3.dispose:()V
     132: aload_0
     133: aconst_null
     134: putfield      #24                 // Field regionsOnCrashedServerBuilder_:Lorg/apache/hbase/thirdparty/com/google/protobuf/RepeatedFieldBuilderV3;
     137: aload_0
     138: aload_1
     139: invokestatic  #55                 // Method org/apache/hadoop/hbase/shaded/protobuf/generated/MasterProcedureProtos$ServerCrashStateData.access$20700:(Lorg/apache/hadoop/hbase/shaded/protobuf/generated/MasterProcedureProtos$ServerCrashStateData;)Ljava/util/List;
     142: putfield      #11                 // Field regionsOnCrashedServer_:Ljava/util/List;
     145: aload_0
     146: aload_0
     147: getfield      #23                 // Field bitField0_:I
     150: bipush        -3
     152: iand
     153: putfield      #23                 // Field bitField0_:I
     156: aload_0
     157: invokestatic  #62                 // Method org/apache/hadoop/hbase/shaded/protobuf/generated/MasterProcedureProtos$ServerCrashStateData.access$21200:()Z
     160: ifeq          170
     163: aload_0
     164: invokespecial #18                 // Method getRegionsOnCrashedServerFieldBuilder:()Lorg/apache/hbase/thirdparty/com/google/protobuf/RepeatedFieldBuilderV3;
     167: goto          171
     170: aconst_null
     171: putfield      #24                 // Field regionsOnCrashedServerBuilder_:Lorg/apache/hbase/thirdparty/com/google/protobuf/RepeatedFieldBuilderV3;
     174: goto          189
     177: aload_0
     178: getfield      #24                 // Field regionsOnCrashedServerBuilder_:Lorg/apache/hbase/thirdparty/com/google/protobuf/RepeatedFieldBuilderV3;
     181: aload_1
     182: invokestatic  #55                 // Method org/apache/hadoop/hbase/shaded/protobuf/generated/MasterProcedureProtos$ServerCrashStateData.access$20700:(Lorg/apache/hadoop/hbase/shaded/protobuf/generated/MasterProcedureProtos$ServerCrashStateData;)Ljava/util/List;
     185: invokevirtual #63                 // Method org/apache/hbase/thirdparty/com/google/protobuf/RepeatedFieldBuilderV3.addAllMessages:(Ljava/lang/Iterable;)Lorg/apache/hbase/thirdparty/com/google/protobuf/RepeatedFieldBuilderV3;
     188: pop
     189: aload_0
     190: getfield      #26                 // Field regionsAssignedBuilder_:Lorg/apache/hbase/thirdparty/com/google/protobuf/RepeatedFieldBuilderV3;
     193: ifnonnull     267
     196: aload_1
     197: invokestatic  #64                 // Method org/apache/hadoop/hbase/shaded/protobuf/generated/MasterProcedureProtos$ServerCrashStateData.access$20800:(Lorg/apache/hadoop/hbase/shaded/protobuf/generated/MasterProcedureProtos$ServerCrashStateData;)Ljava/util/List;
     200: invokeinterface #56,  1           // InterfaceMethod java/util/List.isEmpty:()Z
     205: ifne          353
     208: aload_0
     209: getfield      #12                 // Field regionsAssigned_:Ljava/util/List;
     212: invokeinterface #56,  1           // InterfaceMethod java/util/List.isEmpty:()Z
     217: ifeq          242
     220: aload_0
     221: aload_1
     222: invokestatic  #64                 // Method org/apache/hadoop/hbase/shaded/protobuf/generated/MasterProcedureProtos$ServerCrashStateData.access$20800:(Lorg/apache/hadoop/hbase/shaded/protobuf/generated/MasterProcedureProtos$ServerCrashStateData;)Ljava/util/List;
     225: putfield      #12                 // Field regionsAssigned_:Ljava/util/List;
     228: aload_0
     229: aload_0
     230: getfield      #23                 // Field bitField0_:I
     233: bipush        -5
     235: iand
     236: putfield      #23                 // Field bitField0_:I
     239: goto          260
     242: aload_0
     243: invokespecial #65                 // Method ensureRegionsAssignedIsMutable:()V
     246: aload_0
     247: getfield      #12                 // Field regionsAssigned_:Ljava/util/List;
     250: aload_1
     251: invokestatic  #64                 // Method org/apache/hadoop/hbase/shaded/protobuf/generated/MasterProcedureProtos$ServerCrashStateData.access$20800:(Lorg/apache/hadoop/hbase/shaded/protobuf/generated/MasterProcedureProtos$ServerCrashStateData;)Ljava/util/List;
     254: invokeinterface #58,  2           // InterfaceMethod java/util/List.addAll:(Ljava/util/Collection;)Z
     259: pop
     260: aload_0
     261: invokevirtual #59                 // Method onChanged:()V
     264: goto          353
     267: aload_1
     268: invokestatic  #64                 // Method org/apache/hadoop/hbase/shaded/protobuf/generated/MasterProcedureProtos$ServerCrashStateData.access$20800:(Lorg/apache/hadoop/hbase/shaded/protobuf/generated/MasterProcedureProtos$ServerCrashStateData;)Ljava/util/List;
     271: invokeinterface #56,  1           // InterfaceMethod java/util/List.isEmpty:()Z
     276: ifne          353
     279: aload_0
     280: getfield      #26                 // Field regionsAssignedBuilder_:Lorg/apache/hbase/thirdparty/com/google/protobuf/RepeatedFieldBuilderV3;
     283: invokevirtual #60                 // Method org/apache/hbase/thirdparty/com/google/protobuf/RepeatedFieldBuilderV3.isEmpty:()Z
     286: ifeq          341
     289: aload_0
     290: getfield      #26                 // Field regionsAssignedBuilder_:Lorg/apache/hbase/thirdparty/com/google/protobuf/RepeatedFieldBuilderV3;
     293: invokevirtual #61                 // Method org/apache/hbase/thirdparty/com/google/protobuf/RepeatedFieldBuilderV3.dispose:()V
     296: aload_0
     297: aconst_null
     298: putfield      #26                 // Field regionsAssignedBuilder_:Lorg/apache/hbase/thirdparty/com/google/protobuf/RepeatedFieldBuilderV3;
     301: aload_0
     302: aload_1
     303: invokestatic  #64                 // Method org/apache/hadoop/hbase/shaded/protobuf/generated/MasterProcedureProtos$ServerCrashStateData.access$20800:(Lorg/apache/hadoop/hbase/shaded/protobuf/generated/MasterProcedureProtos$ServerCrashStateData;)Ljava/util/List;
     306: putfield      #12                 // Field regionsAssigned_:Ljava/util/List;
     309: aload_0
     310: aload_0
     311: getfield      #23                 // Field bitField0_:I
     314: bipush        -5
     316: iand
     317: putfield      #23                 // Field bitField0_:I
     320: aload_0
     321: invokestatic  #66                 // Method org/apache/hadoop/hbase/shaded/protobuf/generated/MasterProcedureProtos$ServerCrashStateData.access$21300:()Z
     324: ifeq          334
     327: aload_0
     328: invokespecial #19                 // Method getRegionsAssignedFieldBuilder:()Lorg/apache/hbase/thirdparty/com/google/protobuf/RepeatedFieldBuilderV3;
     331: goto          335
     334: aconst_null
     335: putfield      #26                 // Field regionsAssignedBuilder_:Lorg/apache/hbase/thirdparty/com/google/protobuf/RepeatedFieldBuilderV3;
     338: goto          353
     341: aload_0
     342: getfield      #26                 // Field regionsAssignedBuilder_:Lorg/apache/hbase/thirdparty/com/google/protobuf/RepeatedFieldBuilderV3;
     345: aload_1
     346: invokestatic  #64                 // Method org/apache/hadoop/hbase/shaded/protobuf/generated/MasterProcedureProtos$ServerCrashStateData.access$20800:(Lorg/apache/hadoop/hbase/shaded/protobuf/generated/MasterProcedureProtos$ServerCrashStateData;)Ljava/util/List;
     349: invokevirtual #63                 // Method org/apache/hbase/thirdparty/com/google/protobuf/RepeatedFieldBuilderV3.addAllMessages:(Ljava/lang/Iterable;)Lorg/apache/hbase/thirdparty/com/google/protobuf/RepeatedFieldBuilderV3;
     352: pop
     353: aload_1
     354: invokevirtual #67                 // Method org/apache/hadoop/hbase/shaded/protobuf/generated/MasterProcedureProtos$ServerCrashStateData.hasCarryingMeta:()Z
     357: ifeq          369
     360: aload_0
     361: aload_1
     362: invokevirtual #68                 // Method org/apache/hadoop/hbase/shaded/protobuf/generated/MasterProcedureProtos$ServerCrashStateData.getCarryingMeta:()Z
     365: invokevirtual #69                 // Method setCarryingMeta:(Z)Lorg/apache/hadoop/hbase/shaded/protobuf/generated/MasterProcedureProtos$ServerCrashStateData$Builder;
     368: pop
     369: aload_1
     370: invokevirtual #70                 // Method org/apache/hadoop/hbase/shaded/protobuf/generated/MasterProcedureProtos$ServerCrashStateData.hasShouldSplitWal:()Z
     373: ifeq          385
     376: aload_0
     377: aload_1
     378: invokevirtual #71                 // Method org/apache/hadoop/hbase/shaded/protobuf/generated/MasterProcedureProtos$ServerCrashStateData.getShouldSplitWal:()Z
     381: invokevirtual #72                 // Method setShouldSplitWal:(Z)Lorg/apache/hadoop/hbase/shaded/protobuf/generated/MasterProcedureProtos$ServerCrashStateData$Builder;
     384: pop
     385: aload_0
     386: aload_1
     387: invokestatic  #73                 // Method org/apache/hadoop/hbase/shaded/protobuf/generated/MasterProcedureProtos$ServerCrashStateData.access$21400:(Lorg/apache/hadoop/hbase/shaded/protobuf/generated/MasterProcedureProtos$ServerCrashStateData;)Lorg/apache/hbase/thirdparty/com/google/protobuf/UnknownFieldSet;
     390: invokevirtual #74                 // Method mergeUnknownFields:(Lorg/apache/hbase/thirdparty/com/google/protobuf/UnknownFieldSet;)Lorg/apache/hadoop/hbase/shaded/protobuf/generated/MasterProcedureProtos$ServerCrashStateData$Builder;
     393: pop
     394: aload_0
     395: invokevirtual #59                 // Method onChanged:()V
     398: aload_0
     399: areturn

  public final boolean isInitialized();
    Code:
       0: aload_0
       1: invokevirtual #75                 // Method hasServerName:()Z
       4: ifne          9
       7: iconst_0
       8: ireturn
       9: aload_0
      10: invokevirtual #76                 // Method getServerName:()Lorg/apache/hadoop/hbase/shaded/protobuf/generated/HBaseProtos$ServerName;
      13: invokevirtual #77                 // Method org/apache/hadoop/hbase/shaded/protobuf/generated/HBaseProtos$ServerName.isInitialized:()Z
      16: ifne          21
      19: iconst_0
      20: ireturn
      21: iconst_0
      22: istore_1
      23: iload_1
      24: aload_0
      25: invokevirtual #78                 // Method getRegionsOnCrashedServerCount:()I
      28: if_icmpge     50
      31: aload_0
      32: iload_1
      33: invokevirtual #79                 // Method getRegionsOnCrashedServer:(I)Lorg/apache/hadoop/hbase/shaded/protobuf/generated/HBaseProtos$RegionInfo;
      36: invokevirtual #80                 // Method org/apache/hadoop/hbase/shaded/protobuf/generated/HBaseProtos$RegionInfo.isInitialized:()Z
      39: ifne          44
      42: iconst_0
      43: ireturn
      44: iinc          1, 1
      47: goto          23
      50: iconst_0
      51: istore_1
      52: iload_1
      53: aload_0
      54: invokevirtual #81                 // Method getRegionsAssignedCount:()I
      57: if_icmpge     79
      60: aload_0
      61: iload_1
      62: invokevirtual #82                 // Method getRegionsAssigned:(I)Lorg/apache/hadoop/hbase/shaded/protobuf/generated/HBaseProtos$RegionInfo;
      65: invokevirtual #80                 // Method org/apache/hadoop/hbase/shaded/protobuf/generated/HBaseProtos$RegionInfo.isInitialized:()Z
      68: ifne          73
      71: iconst_0
      72: ireturn
      73: iinc          1, 1
      76: goto          52
      79: iconst_1
      80: ireturn

  public org.apache.hadoop.hbase.shaded.protobuf.generated.MasterProcedureProtos$ServerCrashStateData$Builder mergeFrom(org.apache.hbase.thirdparty.com.google.protobuf.CodedInputStream, org.apache.hbase.thirdparty.com.google.protobuf.ExtensionRegistryLite) throws java.io.IOException;
    Code:
       0: aconst_null
       1: astore_3
       2: getstatic     #83                 // Field org/apache/hadoop/hbase/shaded/protobuf/generated/MasterProcedureProtos$ServerCrashStateData.PARSER:Lorg/apache/hbase/thirdparty/com/google/protobuf/Parser;
       5: aload_1
       6: aload_2
       7: invokeinterface #84,  3           // InterfaceMethod org/apache/hbase/thirdparty/com/google/protobuf/Parser.parsePartialFrom:(Lorg/apache/hbase/thirdparty/com/google/protobuf/CodedInputStream;Lorg/apache/hbase/thirdparty/com/google/protobuf/ExtensionRegistryLite;)Ljava/lang/Object;
      12: checkcast     #5                  // class org/apache/hadoop/hbase/shaded/protobuf/generated/MasterProcedureProtos$ServerCrashStateData
      15: astore_3
      16: aload_3
      17: ifnull        61
      20: aload_0
      21: aload_3
      22: invokevirtual #50                 // Method mergeFrom:(Lorg/apache/hadoop/hbase/shaded/protobuf/generated/MasterProcedureProtos$ServerCrashStateData;)Lorg/apache/hadoop/hbase/shaded/protobuf/generated/MasterProcedureProtos$ServerCrashStateData$Builder;
      25: pop
      26: goto          61
      29: astore        4
      31: aload         4
      33: invokevirtual #86                 // Method org/apache/hbase/thirdparty/com/google/protobuf/InvalidProtocolBufferException.getUnfinishedMessage:()Lorg/apache/hbase/thirdparty/com/google/protobuf/MessageLite;
      36: checkcast     #5                  // class org/apache/hadoop/hbase/shaded/protobuf/generated/MasterProcedureProtos$ServerCrashStateData
      39: astore_3
      40: aload         4
      42: invokevirtual #87                 // Method org/apache/hbase/thirdparty/com/google/protobuf/InvalidProtocolBufferException.unwrapIOException:()Ljava/io/IOException;
      45: athrow
      46: astore        5
      48: aload_3
      49: ifnull        58
      52: aload_0
      53: aload_3
      54: invokevirtual #50                 // Method mergeFrom:(Lorg/apache/hadoop/hbase/shaded/protobuf/generated/MasterProcedureProtos$ServerCrashStateData;)Lorg/apache/hadoop/hbase/shaded/protobuf/generated/MasterProcedureProtos$ServerCrashStateData$Builder;
      57: pop
      58: aload         5
      60: athrow
      61: aload_0
      62: areturn
    Exception table:
       from    to  target type
           2    16    29   Class org/apache/hbase/thirdparty/com/google/protobuf/InvalidProtocolBufferException
           2    16    46   any
          29    48    46   any

  public boolean hasServerName();
    Code:
       0: aload_0
       1: getfield      #23                 // Field bitField0_:I
       4: iconst_1
       5: iand
       6: iconst_1
       7: if_icmpne     14
      10: iconst_1
      11: goto          15
      14: iconst_0
      15: ireturn

  public org.apache.hadoop.hbase.shaded.protobuf.generated.HBaseProtos$ServerName getServerName();
    Code:
       0: aload_0
       1: getfield      #21                 // Field serverNameBuilder_:Lorg/apache/hbase/thirdparty/com/google/protobuf/SingleFieldBuilderV3;
       4: ifnonnull     25
       7: aload_0
       8: getfield      #9                  // Field serverName_:Lorg/apache/hadoop/hbase/shaded/protobuf/generated/HBaseProtos$ServerName;
      11: ifnonnull     20
      14: invokestatic  #88                 // Method org/apache/hadoop/hbase/shaded/protobuf/generated/HBaseProtos$ServerName.getDefaultInstance:()Lorg/apache/hadoop/hbase/shaded/protobuf/generated/HBaseProtos$ServerName;
      17: goto          24
      20: aload_0
      21: getfield      #9                  // Field serverName_:Lorg/apache/hadoop/hbase/shaded/protobuf/generated/HBaseProtos$ServerName;
      24: areturn
      25: aload_0
      26: getfield      #21                 // Field serverNameBuilder_:Lorg/apache/hbase/thirdparty/com/google/protobuf/SingleFieldBuilderV3;
      29: invokevirtual #89                 // Method org/apache/hbase/thirdparty/com/google/protobuf/SingleFieldBuilderV3.getMessage:()Lorg/apache/hbase/thirdparty/com/google/protobuf/AbstractMessage;
      32: checkcast     #35                 // class org/apache/hadoop/hbase/shaded/protobuf/generated/HBaseProtos$ServerName
      35: areturn

  public org.apache.hadoop.hbase.shaded.protobuf.generated.MasterProcedureProtos$ServerCrashStateData$Builder setServerName(org.apache.hadoop.hbase.shaded.protobuf.generated.HBaseProtos$ServerName);
    Code:
       0: aload_0
       1: getfield      #21                 // Field serverNameBuilder_:Lorg/apache/hbase/thirdparty/com/google/protobuf/SingleFieldBuilderV3;
       4: ifnonnull     31
       7: aload_1
       8: ifnonnull     19
      11: new           #90                 // class java/lang/NullPointerException
      14: dup
      15: invokespecial #91                 // Method java/lang/NullPointerException."<init>":()V
      18: athrow
      19: aload_0
      20: aload_1
      21: putfield      #9                  // Field serverName_:Lorg/apache/hadoop/hbase/shaded/protobuf/generated/HBaseProtos$ServerName;
      24: aload_0
      25: invokevirtual #59                 // Method onChanged:()V
      28: goto          40
      31: aload_0
      32: getfield      #21                 // Field serverNameBuilder_:Lorg/apache/hbase/thirdparty/com/google/protobuf/SingleFieldBuilderV3;
      35: aload_1
      36: invokevirtual #92                 // Method org/apache/hbase/thirdparty/com/google/protobuf/SingleFieldBuilderV3.setMessage:(Lorg/apache/hbase/thirdparty/com/google/protobuf/AbstractMessage;)Lorg/apache/hbase/thirdparty/com/google/protobuf/SingleFieldBuilderV3;
      39: pop
      40: aload_0
      41: dup
      42: getfield      #23                 // Field bitField0_:I
      45: iconst_1
      46: ior
      47: putfield      #23                 // Field bitField0_:I
      50: aload_0
      51: areturn

  public org.apache.hadoop.hbase.shaded.protobuf.generated.MasterProcedureProtos$ServerCrashStateData$Builder setServerName(org.apache.hadoop.hbase.shaded.protobuf.generated.HBaseProtos$ServerName$Builder);
    Code:
       0: aload_0
       1: getfield      #21                 // Field serverNameBuilder_:Lorg/apache/hbase/thirdparty/com/google/protobuf/SingleFieldBuilderV3;
       4: ifnonnull     22
       7: aload_0
       8: aload_1
       9: invokevirtual #93                 // Method org/apache/hadoop/hbase/shaded/protobuf/generated/HBaseProtos$ServerName$Builder.build:()Lorg/apache/hadoop/hbase/shaded/protobuf/generated/HBaseProtos$ServerName;
      12: putfield      #9                  // Field serverName_:Lorg/apache/hadoop/hbase/shaded/protobuf/generated/HBaseProtos$ServerName;
      15: aload_0
      16: invokevirtual #59                 // Method onChanged:()V
      19: goto          34
      22: aload_0
      23: getfield      #21                 // Field serverNameBuilder_:Lorg/apache/hbase/thirdparty/com/google/protobuf/SingleFieldBuilderV3;
      26: aload_1
      27: invokevirtual #93                 // Method org/apache/hadoop/hbase/shaded/protobuf/generated/HBaseProtos$ServerName$Builder.build:()Lorg/apache/hadoop/hbase/shaded/protobuf/generated/HBaseProtos$ServerName;
      30: invokevirtual #92                 // Method org/apache/hbase/thirdparty/com/google/protobuf/SingleFieldBuilderV3.setMessage:(Lorg/apache/hbase/thirdparty/com/google/protobuf/AbstractMessage;)Lorg/apache/hbase/thirdparty/com/google/protobuf/SingleFieldBuilderV3;
      33: pop
      34: aload_0
      35: dup
      36: getfield      #23                 // Field bitField0_:I
      39: iconst_1
      40: ior
      41: putfield      #23                 // Field bitField0_:I
      44: aload_0
      45: areturn

  public org.apache.hadoop.hbase.shaded.protobuf.generated.MasterProcedureProtos$ServerCrashStateData$Builder mergeServerName(org.apache.hadoop.hbase.shaded.protobuf.generated.HBaseProtos$ServerName);
    Code:
       0: aload_0
       1: getfield      #21                 // Field serverNameBuilder_:Lorg/apache/hbase/thirdparty/com/google/protobuf/SingleFieldBuilderV3;
       4: ifnonnull     67
       7: aload_0
       8: getfield      #23                 // Field bitField0_:I
      11: iconst_1
      12: iand
      13: iconst_1
      14: if_icmpne     55
      17: aload_0
      18: getfield      #9                  // Field serverName_:Lorg/apache/hadoop/hbase/shaded/protobuf/generated/HBaseProtos$ServerName;
      21: ifnull        55
      24: aload_0
      25: getfield      #9                  // Field serverName_:Lorg/apache/hadoop/hbase/shaded/protobuf/generated/HBaseProtos$ServerName;
      28: invokestatic  #88                 // Method org/apache/hadoop/hbase/shaded/protobuf/generated/HBaseProtos$ServerName.getDefaultInstance:()Lorg/apache/hadoop/hbase/shaded/protobuf/generated/HBaseProtos$ServerName;
      31: if_acmpeq     55
      34: aload_0
      35: aload_0
      36: getfield      #9                  // Field serverName_:Lorg/apache/hadoop/hbase/shaded/protobuf/generated/HBaseProtos$ServerName;
      39: invokestatic  #94                 // Method org/apache/hadoop/hbase/shaded/protobuf/generated/HBaseProtos$ServerName.newBuilder:(Lorg/apache/hadoop/hbase/shaded/protobuf/generated/HBaseProtos$ServerName;)Lorg/apache/hadoop/hbase/shaded/protobuf/generated/HBaseProtos$ServerName$Builder;
      42: aload_1
      43: invokevirtual #95                 // Method org/apache/hadoop/hbase/shaded/protobuf/generated/HBaseProtos$ServerName$Builder.mergeFrom:(Lorg/apache/hadoop/hbase/shaded/protobuf/generated/HBaseProtos$ServerName;)Lorg/apache/hadoop/hbase/shaded/protobuf/generated/HBaseProtos$ServerName$Builder;
      46: invokevirtual #96                 // Method org/apache/hadoop/hbase/shaded/protobuf/generated/HBaseProtos$ServerName$Builder.buildPartial:()Lorg/apache/hadoop/hbase/shaded/protobuf/generated/HBaseProtos$ServerName;
      49: putfield      #9                  // Field serverName_:Lorg/apache/hadoop/hbase/shaded/protobuf/generated/HBaseProtos$ServerName;
      52: goto          60
      55: aload_0
      56: aload_1
      57: putfield      #9                  // Field serverName_:Lorg/apache/hadoop/hbase/shaded/protobuf/generated/HBaseProtos$ServerName;
      60: aload_0
      61: invokevirtual #59                 // Method onChanged:()V
      64: goto          76
      67: aload_0
      68: getfield      #21                 // Field serverNameBuilder_:Lorg/apache/hbase/thirdparty/com/google/protobuf/SingleFieldBuilderV3;
      71: aload_1
      72: invokevirtual #97                 // Method org/apache/hbase/thirdparty/com/google/protobuf/SingleFieldBuilderV3.mergeFrom:(Lorg/apache/hbase/thirdparty/com/google/protobuf/AbstractMessage;)Lorg/apache/hbase/thirdparty/com/google/protobuf/SingleFieldBuilderV3;
      75: pop
      76: aload_0
      77: dup
      78: getfield      #23                 // Field bitField0_:I
      81: iconst_1
      82: ior
      83: putfield      #23                 // Field bitField0_:I
      86: aload_0
      87: areturn

  public org.apache.hadoop.hbase.shaded.protobuf.generated.MasterProcedureProtos$ServerCrashStateData$Builder clearServerName();
    Code:
       0: aload_0
       1: getfield      #21                 // Field serverNameBuilder_:Lorg/apache/hbase/thirdparty/com/google/protobuf/SingleFieldBuilderV3;
       4: ifnonnull     19
       7: aload_0
       8: aconst_null
       9: putfield      #9                  // Field serverName_:Lorg/apache/hadoop/hbase/shaded/protobuf/generated/HBaseProtos$ServerName;
      12: aload_0
      13: invokevirtual #59                 // Method onChanged:()V
      16: goto          27
      19: aload_0
      20: getfield      #21                 // Field serverNameBuilder_:Lorg/apache/hbase/thirdparty/com/google/protobuf/SingleFieldBuilderV3;
      23: invokevirtual #22                 // Method org/apache/hbase/thirdparty/com/google/protobuf/SingleFieldBuilderV3.clear:()Lorg/apache/hbase/thirdparty/com/google/protobuf/SingleFieldBuilderV3;
      26: pop
      27: aload_0
      28: aload_0
      29: getfield      #23                 // Field bitField0_:I
      32: bipush        -2
      34: iand
      35: putfield      #23                 // Field bitField0_:I
      38: aload_0
      39: areturn

  public org.apache.hadoop.hbase.shaded.protobuf.generated.HBaseProtos$ServerName$Builder getServerNameBuilder();
    Code:
       0: aload_0
       1: dup
       2: getfield      #23                 // Field bitField0_:I
       5: iconst_1
       6: ior
       7: putfield      #23                 // Field bitField0_:I
      10: aload_0
      11: invokevirtual #59                 // Method onChanged:()V
      14: aload_0
      15: invokespecial #17                 // Method getServerNameFieldBuilder:()Lorg/apache/hbase/thirdparty/com/google/protobuf/SingleFieldBuilderV3;
      18: invokevirtual #98                 // Method org/apache/hbase/thirdparty/com/google/protobuf/SingleFieldBuilderV3.getBuilder:()Lorg/apache/hbase/thirdparty/com/google/protobuf/AbstractMessage$Builder;
      21: checkcast     #99                 // class org/apache/hadoop/hbase/shaded/protobuf/generated/HBaseProtos$ServerName$Builder
      24: areturn

  public org.apache.hadoop.hbase.shaded.protobuf.generated.HBaseProtos$ServerNameOrBuilder getServerNameOrBuilder();
    Code:
       0: aload_0
       1: getfield      #21                 // Field serverNameBuilder_:Lorg/apache/hbase/thirdparty/com/google/protobuf/SingleFieldBuilderV3;
       4: ifnull        18
       7: aload_0
       8: getfield      #21                 // Field serverNameBuilder_:Lorg/apache/hbase/thirdparty/com/google/protobuf/SingleFieldBuilderV3;
      11: invokevirtual #100                // Method org/apache/hbase/thirdparty/com/google/protobuf/SingleFieldBuilderV3.getMessageOrBuilder:()Lorg/apache/hbase/thirdparty/com/google/protobuf/MessageOrBuilder;
      14: checkcast     #101                // class org/apache/hadoop/hbase/shaded/protobuf/generated/HBaseProtos$ServerNameOrBuilder
      17: areturn
      18: aload_0
      19: getfield      #9                  // Field serverName_:Lorg/apache/hadoop/hbase/shaded/protobuf/generated/HBaseProtos$ServerName;
      22: ifnonnull     31
      25: invokestatic  #88                 // Method org/apache/hadoop/hbase/shaded/protobuf/generated/HBaseProtos$ServerName.getDefaultInstance:()Lorg/apache/hadoop/hbase/shaded/protobuf/generated/HBaseProtos$ServerName;
      28: goto          35
      31: aload_0
      32: getfield      #9                  // Field serverName_:Lorg/apache/hadoop/hbase/shaded/protobuf/generated/HBaseProtos$ServerName;
      35: areturn

  public java.util.List<org.apache.hadoop.hbase.shaded.protobuf.generated.HBaseProtos$RegionInfo> getRegionsOnCrashedServerList();
    Code:
       0: aload_0
       1: getfield      #24                 // Field regionsOnCrashedServerBuilder_:Lorg/apache/hbase/thirdparty/com/google/protobuf/RepeatedFieldBuilderV3;
       4: ifnonnull     15
       7: aload_0
       8: getfield      #11                 // Field regionsOnCrashedServer_:Ljava/util/List;
      11: invokestatic  #36                 // Method java/util/Collections.unmodifiableList:(Ljava/util/List;)Ljava/util/List;
      14: areturn
      15: aload_0
      16: getfield      #24                 // Field regionsOnCrashedServerBuilder_:Lorg/apache/hbase/thirdparty/com/google/protobuf/RepeatedFieldBuilderV3;
      19: invokevirtual #108                // Method org/apache/hbase/thirdparty/com/google/protobuf/RepeatedFieldBuilderV3.getMessageList:()Ljava/util/List;
      22: areturn

  public int getRegionsOnCrashedServerCount();
    Code:
       0: aload_0
       1: getfield      #24                 // Field regionsOnCrashedServerBuilder_:Lorg/apache/hbase/thirdparty/com/google/protobuf/RepeatedFieldBuilderV3;
       4: ifnonnull     17
       7: aload_0
       8: getfield      #11                 // Field regionsOnCrashedServer_:Ljava/util/List;
      11: invokeinterface #109,  1          // InterfaceMethod java/util/List.size:()I
      16: ireturn
      17: aload_0
      18: getfield      #24                 // Field regionsOnCrashedServerBuilder_:Lorg/apache/hbase/thirdparty/com/google/protobuf/RepeatedFieldBuilderV3;
      21: invokevirtual #110                // Method org/apache/hbase/thirdparty/com/google/protobuf/RepeatedFieldBuilderV3.getCount:()I
      24: ireturn

  public org.apache.hadoop.hbase.shaded.protobuf.generated.HBaseProtos$RegionInfo getRegionsOnCrashedServer(int);
    Code:
       0: aload_0
       1: getfield      #24                 // Field regionsOnCrashedServerBuilder_:Lorg/apache/hbase/thirdparty/com/google/protobuf/RepeatedFieldBuilderV3;
       4: ifnonnull     21
       7: aload_0
       8: getfield      #11                 // Field regionsOnCrashedServer_:Ljava/util/List;
      11: iload_1
      12: invokeinterface #111,  2          // InterfaceMethod java/util/List.get:(I)Ljava/lang/Object;
      17: checkcast     #112                // class org/apache/hadoop/hbase/shaded/protobuf/generated/HBaseProtos$RegionInfo
      20: areturn
      21: aload_0
      22: getfield      #24                 // Field regionsOnCrashedServerBuilder_:Lorg/apache/hbase/thirdparty/com/google/protobuf/RepeatedFieldBuilderV3;
      25: iload_1
      26: invokevirtual #113                // Method org/apache/hbase/thirdparty/com/google/protobuf/RepeatedFieldBuilderV3.getMessage:(I)Lorg/apache/hbase/thirdparty/com/google/protobuf/AbstractMessage;
      29: checkcast     #112                // class org/apache/hadoop/hbase/shaded/protobuf/generated/HBaseProtos$RegionInfo
      32: areturn

  public org.apache.hadoop.hbase.shaded.protobuf.generated.MasterProcedureProtos$ServerCrashStateData$Builder setRegionsOnCrashedServer(int, org.apache.hadoop.hbase.shaded.protobuf.generated.HBaseProtos$RegionInfo);
    Code:
       0: aload_0
       1: getfield      #24                 // Field regionsOnCrashedServerBuilder_:Lorg/apache/hbase/thirdparty/com/google/protobuf/RepeatedFieldBuilderV3;
       4: ifnonnull     42
       7: aload_2
       8: ifnonnull     19
      11: new           #90                 // class java/lang/NullPointerException
      14: dup
      15: invokespecial #91                 // Method java/lang/NullPointerException."<init>":()V
      18: athrow
      19: aload_0
      20: invokespecial #57                 // Method ensureRegionsOnCrashedServerIsMutable:()V
      23: aload_0
      24: getfield      #11                 // Field regionsOnCrashedServer_:Ljava/util/List;
      27: iload_1
      28: aload_2
      29: invokeinterface #114,  3          // InterfaceMethod java/util/List.set:(ILjava/lang/Object;)Ljava/lang/Object;
      34: pop
      35: aload_0
      36: invokevirtual #59                 // Method onChanged:()V
      39: goto          52
      42: aload_0
      43: getfield      #24                 // Field regionsOnCrashedServerBuilder_:Lorg/apache/hbase/thirdparty/com/google/protobuf/RepeatedFieldBuilderV3;
      46: iload_1
      47: aload_2
      48: invokevirtual #115                // Method org/apache/hbase/thirdparty/com/google/protobuf/RepeatedFieldBuilderV3.setMessage:(ILorg/apache/hbase/thirdparty/com/google/protobuf/AbstractMessage;)Lorg/apache/hbase/thirdparty/com/google/protobuf/RepeatedFieldBuilderV3;
      51: pop
      52: aload_0
      53: areturn

  public org.apache.hadoop.hbase.shaded.protobuf.generated.MasterProcedureProtos$ServerCrashStateData$Builder setRegionsOnCrashedServer(int, org.apache.hadoop.hbase.shaded.protobuf.generated.HBaseProtos$RegionInfo$Builder);
    Code:
       0: aload_0
       1: getfield      #24                 // Field regionsOnCrashedServerBuilder_:Lorg/apache/hbase/thirdparty/com/google/protobuf/RepeatedFieldBuilderV3;
       4: ifnonnull     33
       7: aload_0
       8: invokespecial #57                 // Method ensureRegionsOnCrashedServerIsMutable:()V
      11: aload_0
      12: getfield      #11                 // Field regionsOnCrashedServer_:Ljava/util/List;
      15: iload_1
      16: aload_2
      17: invokevirtual #116                // Method org/apache/hadoop/hbase/shaded/protobuf/generated/HBaseProtos$RegionInfo$Builder.build:()Lorg/apache/hadoop/hbase/shaded/protobuf/generated/HBaseProtos$RegionInfo;
      20: invokeinterface #114,  3          // InterfaceMethod java/util/List.set:(ILjava/lang/Object;)Ljava/lang/Object;
      25: pop
      26: aload_0
      27: invokevirtual #59                 // Method onChanged:()V
      30: goto          46
      33: aload_0
      34: getfield      #24                 // Field regionsOnCrashedServerBuilder_:Lorg/apache/hbase/thirdparty/com/google/protobuf/RepeatedFieldBuilderV3;
      37: iload_1
      38: aload_2
      39: invokevirtual #116                // Method org/apache/hadoop/hbase/shaded/protobuf/generated/HBaseProtos$RegionInfo$Builder.build:()Lorg/apache/hadoop/hbase/shaded/protobuf/generated/HBaseProtos$RegionInfo;
      42: invokevirtual #115                // Method org/apache/hbase/thirdparty/com/google/protobuf/RepeatedFieldBuilderV3.setMessage:(ILorg/apache/hbase/thirdparty/com/google/protobuf/AbstractMessage;)Lorg/apache/hbase/thirdparty/com/google/protobuf/RepeatedFieldBuilderV3;
      45: pop
      46: aload_0
      47: areturn

  public org.apache.hadoop.hbase.shaded.protobuf.generated.MasterProcedureProtos$ServerCrashStateData$Builder addRegionsOnCrashedServer(org.apache.hadoop.hbase.shaded.protobuf.generated.HBaseProtos$RegionInfo);
    Code:
       0: aload_0
       1: getfield      #24                 // Field regionsOnCrashedServerBuilder_:Lorg/apache/hbase/thirdparty/com/google/protobuf/RepeatedFieldBuilderV3;
       4: ifnonnull     41
       7: aload_1
       8: ifnonnull     19
      11: new           #90                 // class java/lang/NullPointerException
      14: dup
      15: invokespecial #91                 // Method java/lang/NullPointerException."<init>":()V
      18: athrow
      19: aload_0
      20: invokespecial #57                 // Method ensureRegionsOnCrashedServerIsMutable:()V
      23: aload_0
      24: getfield      #11                 // Field regionsOnCrashedServer_:Ljava/util/List;
      27: aload_1
      28: invokeinterface #117,  2          // InterfaceMethod java/util/List.add:(Ljava/lang/Object;)Z
      33: pop
      34: aload_0
      35: invokevirtual #59                 // Method onChanged:()V
      38: goto          50
      41: aload_0
      42: getfield      #24                 // Field regionsOnCrashedServerBuilder_:Lorg/apache/hbase/thirdparty/com/google/protobuf/RepeatedFieldBuilderV3;
      45: aload_1
      46: invokevirtual #118                // Method org/apache/hbase/thirdparty/com/google/protobuf/RepeatedFieldBuilderV3.addMessage:(Lorg/apache/hbase/thirdparty/com/google/protobuf/AbstractMessage;)Lorg/apache/hbase/thirdparty/com/google/protobuf/RepeatedFieldBuilderV3;
      49: pop
      50: aload_0
      51: areturn

  public org.apache.hadoop.hbase.shaded.protobuf.generated.MasterProcedureProtos$ServerCrashStateData$Builder addRegionsOnCrashedServer(int, org.apache.hadoop.hbase.shaded.protobuf.generated.HBaseProtos$RegionInfo);
    Code:
       0: aload_0
       1: getfield      #24                 // Field regionsOnCrashedServerBuilder_:Lorg/apache/hbase/thirdparty/com/google/protobuf/RepeatedFieldBuilderV3;
       4: ifnonnull     41
       7: aload_2
       8: ifnonnull     19
      11: new           #90                 // class java/lang/NullPointerException
      14: dup
      15: invokespecial #91                 // Method java/lang/NullPointerException."<init>":()V
      18: athrow
      19: aload_0
      20: invokespecial #57                 // Method ensureRegionsOnCrashedServerIsMutable:()V
      23: aload_0
      24: getfield      #11                 // Field regionsOnCrashedServer_:Ljava/util/List;
      27: iload_1
      28: aload_2
      29: invokeinterface #119,  3          // InterfaceMethod java/util/List.add:(ILjava/lang/Object;)V
      34: aload_0
      35: invokevirtual #59                 // Method onChanged:()V
      38: goto          51
      41: aload_0
      42: getfield      #24                 // Field regionsOnCrashedServerBuilder_:Lorg/apache/hbase/thirdparty/com/google/protobuf/RepeatedFieldBuilderV3;
      45: iload_1
      46: aload_2
      47: invokevirtual #120                // Method org/apache/hbase/thirdparty/com/google/protobuf/RepeatedFieldBuilderV3.addMessage:(ILorg/apache/hbase/thirdparty/com/google/protobuf/AbstractMessage;)Lorg/apache/hbase/thirdparty/com/google/protobuf/RepeatedFieldBuilderV3;
      50: pop
      51: aload_0
      52: areturn

  public org.apache.hadoop.hbase.shaded.protobuf.generated.MasterProcedureProtos$ServerCrashStateData$Builder addRegionsOnCrashedServer(org.apache.hadoop.hbase.shaded.protobuf.generated.HBaseProtos$RegionInfo$Builder);
    Code:
       0: aload_0
       1: getfield      #24                 // Field regionsOnCrashedServerBuilder_:Lorg/apache/hbase/thirdparty/com/google/protobuf/RepeatedFieldBuilderV3;
       4: ifnonnull     32
       7: aload_0
       8: invokespecial #57                 // Method ensureRegionsOnCrashedServerIsMutable:()V
      11: aload_0
      12: getfield      #11                 // Field regionsOnCrashedServer_:Ljava/util/List;
      15: aload_1
      16: invokevirtual #116                // Method org/apache/hadoop/hbase/shaded/protobuf/generated/HBaseProtos$RegionInfo$Builder.build:()Lorg/apache/hadoop/hbase/shaded/protobuf/generated/HBaseProtos$RegionInfo;
      19: invokeinterface #117,  2          // InterfaceMethod java/util/List.add:(Ljava/lang/Object;)Z
      24: pop
      25: aload_0
      26: invokevirtual #59                 // Method onChanged:()V
      29: goto          44
      32: aload_0
      33: getfield      #24                 // Field regionsOnCrashedServerBuilder_:Lorg/apache/hbase/thirdparty/com/google/protobuf/RepeatedFieldBuilderV3;
      36: aload_1
      37: invokevirtual #116                // Method org/apache/hadoop/hbase/shaded/protobuf/generated/HBaseProtos$RegionInfo$Builder.build:()Lorg/apache/hadoop/hbase/shaded/protobuf/generated/HBaseProtos$RegionInfo;
      40: invokevirtual #118                // Method org/apache/hbase/thirdparty/com/google/protobuf/RepeatedFieldBuilderV3.addMessage:(Lorg/apache/hbase/thirdparty/com/google/protobuf/AbstractMessage;)Lorg/apache/hbase/thirdparty/com/google/protobuf/RepeatedFieldBuilderV3;
      43: pop
      44: aload_0
      45: areturn

  public org.apache.hadoop.hbase.shaded.protobuf.generated.MasterProcedureProtos$ServerCrashStateData$Builder addRegionsOnCrashedServer(int, org.apache.hadoop.hbase.shaded.protobuf.generated.HBaseProtos$RegionInfo$Builder);
    Code:
       0: aload_0
       1: getfield      #24                 // Field regionsOnCrashedServerBuilder_:Lorg/apache/hbase/thirdparty/com/google/protobuf/RepeatedFieldBuilderV3;
       4: ifnonnull     32
       7: aload_0
       8: invokespecial #57                 // Method ensureRegionsOnCrashedServerIsMutable:()V
      11: aload_0
      12: getfield      #11                 // Field regionsOnCrashedServer_:Ljava/util/List;
      15: iload_1
      16: aload_2
      17: invokevirtual #116                // Method org/apache/hadoop/hbase/shaded/protobuf/generated/HBaseProtos$RegionInfo$Builder.build:()Lorg/apache/hadoop/hbase/shaded/protobuf/generated/HBaseProtos$RegionInfo;
      20: invokeinterface #119,  3          // InterfaceMethod java/util/List.add:(ILjava/lang/Object;)V
      25: aload_0
      26: invokevirtual #59                 // Method onChanged:()V
      29: goto          45
      32: aload_0
      33: getfield      #24                 // Field regionsOnCrashedServerBuilder_:Lorg/apache/hbase/thirdparty/com/google/protobuf/RepeatedFieldBuilderV3;
      36: iload_1
      37: aload_2
      38: invokevirtual #116                // Method org/apache/hadoop/hbase/shaded/protobuf/generated/HBaseProtos$RegionInfo$Builder.build:()Lorg/apache/hadoop/hbase/shaded/protobuf/generated/HBaseProtos$RegionInfo;
      41: invokevirtual #120                // Method org/apache/hbase/thirdparty/com/google/protobuf/RepeatedFieldBuilderV3.addMessage:(ILorg/apache/hbase/thirdparty/com/google/protobuf/AbstractMessage;)Lorg/apache/hbase/thirdparty/com/google/protobuf/RepeatedFieldBuilderV3;
      44: pop
      45: aload_0
      46: areturn

  public org.apache.hadoop.hbase.shaded.protobuf.generated.MasterProcedureProtos$ServerCrashStateData$Builder addAllRegionsOnCrashedServer(java.lang.Iterable<? extends org.apache.hadoop.hbase.shaded.protobuf.generated.HBaseProtos$RegionInfo>);
    Code:
       0: aload_0
       1: getfield      #24                 // Field regionsOnCrashedServerBuilder_:Lorg/apache/hbase/thirdparty/com/google/protobuf/RepeatedFieldBuilderV3;
       4: ifnonnull     26
       7: aload_0
       8: invokespecial #57                 // Method ensureRegionsOnCrashedServerIsMutable:()V
      11: aload_1
      12: aload_0
      13: getfield      #11                 // Field regionsOnCrashedServer_:Ljava/util/List;
      16: invokestatic  #121                // Method org/apache/hbase/thirdparty/com/google/protobuf/AbstractMessageLite$Builder.addAll:(Ljava/lang/Iterable;Ljava/util/List;)V
      19: aload_0
      20: invokevirtual #59                 // Method onChanged:()V
      23: goto          35
      26: aload_0
      27: getfield      #24                 // Field regionsOnCrashedServerBuilder_:Lorg/apache/hbase/thirdparty/com/google/protobuf/RepeatedFieldBuilderV3;
      30: aload_1
      31: invokevirtual #63                 // Method org/apache/hbase/thirdparty/com/google/protobuf/RepeatedFieldBuilderV3.addAllMessages:(Ljava/lang/Iterable;)Lorg/apache/hbase/thirdparty/com/google/protobuf/RepeatedFieldBuilderV3;
      34: pop
      35: aload_0
      36: areturn

  public org.apache.hadoop.hbase.shaded.protobuf.generated.MasterProcedureProtos$ServerCrashStateData$Builder clearRegionsOnCrashedServer();
    Code:
       0: aload_0
       1: getfield      #24                 // Field regionsOnCrashedServerBuilder_:Lorg/apache/hbase/thirdparty/com/google/protobuf/RepeatedFieldBuilderV3;
       4: ifnonnull     32
       7: aload_0
       8: invokestatic  #10                 // Method java/util/Collections.emptyList:()Ljava/util/List;
      11: putfield      #11                 // Field regionsOnCrashedServer_:Ljava/util/List;
      14: aload_0
      15: aload_0
      16: getfield      #23                 // Field bitField0_:I
      19: bipush        -3
      21: iand
      22: putfield      #23                 // Field bitField0_:I
      25: aload_0
      26: invokevirtual #59                 // Method onChanged:()V
      29: goto          39
      32: aload_0
      33: getfield      #24                 // Field regionsOnCrashedServerBuilder_:Lorg/apache/hbase/thirdparty/com/google/protobuf/RepeatedFieldBuilderV3;
      36: invokevirtual #25                 // Method org/apache/hbase/thirdparty/com/google/protobuf/RepeatedFieldBuilderV3.clear:()V
      39: aload_0
      40: areturn

  public org.apache.hadoop.hbase.shaded.protobuf.generated.MasterProcedureProtos$ServerCrashStateData$Builder removeRegionsOnCrashedServer(int);
    Code:
       0: aload_0
       1: getfield      #24                 // Field regionsOnCrashedServerBuilder_:Lorg/apache/hbase/thirdparty/com/google/protobuf/RepeatedFieldBuilderV3;
       4: ifnonnull     29
       7: aload_0
       8: invokespecial #57                 // Method ensureRegionsOnCrashedServerIsMutable:()V
      11: aload_0
      12: getfield      #11                 // Field regionsOnCrashedServer_:Ljava/util/List;
      15: iload_1
      16: invokeinterface #122,  2          // InterfaceMethod java/util/List.remove:(I)Ljava/lang/Object;
      21: pop
      22: aload_0
      23: invokevirtual #59                 // Method onChanged:()V
      26: goto          37
      29: aload_0
      30: getfield      #24                 // Field regionsOnCrashedServerBuilder_:Lorg/apache/hbase/thirdparty/com/google/protobuf/RepeatedFieldBuilderV3;
      33: iload_1
      34: invokevirtual #123                // Method org/apache/hbase/thirdparty/com/google/protobuf/RepeatedFieldBuilderV3.remove:(I)V
      37: aload_0
      38: areturn

  public org.apache.hadoop.hbase.shaded.protobuf.generated.HBaseProtos$RegionInfo$Builder getRegionsOnCrashedServerBuilder(int);
    Code:
       0: aload_0
       1: invokespecial #18                 // Method getRegionsOnCrashedServerFieldBuilder:()Lorg/apache/hbase/thirdparty/com/google/protobuf/RepeatedFieldBuilderV3;
       4: iload_1
       5: invokevirtual #124                // Method org/apache/hbase/thirdparty/com/google/protobuf/RepeatedFieldBuilderV3.getBuilder:(I)Lorg/apache/hbase/thirdparty/com/google/protobuf/AbstractMessage$Builder;
       8: checkcast     #125                // class org/apache/hadoop/hbase/shaded/protobuf/generated/HBaseProtos$RegionInfo$Builder
      11: areturn

  public org.apache.hadoop.hbase.shaded.protobuf.generated.HBaseProtos$RegionInfoOrBuilder getRegionsOnCrashedServerOrBuilder(int);
    Code:
       0: aload_0
       1: getfield      #24                 // Field regionsOnCrashedServerBuilder_:Lorg/apache/hbase/thirdparty/com/google/protobuf/RepeatedFieldBuilderV3;
       4: ifnonnull     21
       7: aload_0
       8: getfield      #11                 // Field regionsOnCrashedServer_:Ljava/util/List;
      11: iload_1
      12: invokeinterface #111,  2          // InterfaceMethod java/util/List.get:(I)Ljava/lang/Object;
      17: checkcast     #126                // class org/apache/hadoop/hbase/shaded/protobuf/generated/HBaseProtos$RegionInfoOrBuilder
      20: areturn
      21: aload_0
      22: getfield      #24                 // Field regionsOnCrashedServerBuilder_:Lorg/apache/hbase/thirdparty/com/google/protobuf/RepeatedFieldBuilderV3;
      25: iload_1
      26: invokevirtual #127                // Method org/apache/hbase/thirdparty/com/google/protobuf/RepeatedFieldBuilderV3.getMessageOrBuilder:(I)Lorg/apache/hbase/thirdparty/com/google/protobuf/MessageOrBuilder;
      29: checkcast     #126                // class org/apache/hadoop/hbase/shaded/protobuf/generated/HBaseProtos$RegionInfoOrBuilder
      32: areturn

  public java.util.List<? extends org.apache.hadoop.hbase.shaded.protobuf.generated.HBaseProtos$RegionInfoOrBuilder> getRegionsOnCrashedServerOrBuilderList();
    Code:
       0: aload_0
       1: getfield      #24                 // Field regionsOnCrashedServerBuilder_:Lorg/apache/hbase/thirdparty/com/google/protobuf/RepeatedFieldBuilderV3;
       4: ifnull        15
       7: aload_0
       8: getfield      #24                 // Field regionsOnCrashedServerBuilder_:Lorg/apache/hbase/thirdparty/com/google/protobuf/RepeatedFieldBuilderV3;
      11: invokevirtual #128                // Method org/apache/hbase/thirdparty/com/google/protobuf/RepeatedFieldBuilderV3.getMessageOrBuilderList:()Ljava/util/List;
      14: areturn
      15: aload_0
      16: getfield      #11                 // Field regionsOnCrashedServer_:Ljava/util/List;
      19: invokestatic  #36                 // Method java/util/Collections.unmodifiableList:(Ljava/util/List;)Ljava/util/List;
      22: areturn

  public org.apache.hadoop.hbase.shaded.protobuf.generated.HBaseProtos$RegionInfo$Builder addRegionsOnCrashedServerBuilder();
    Code:
       0: aload_0
       1: invokespecial #18                 // Method getRegionsOnCrashedServerFieldBuilder:()Lorg/apache/hbase/thirdparty/com/google/protobuf/RepeatedFieldBuilderV3;
       4: invokestatic  #129                // Method org/apache/hadoop/hbase/shaded/protobuf/generated/HBaseProtos$RegionInfo.getDefaultInstance:()Lorg/apache/hadoop/hbase/shaded/protobuf/generated/HBaseProtos$RegionInfo;
       7: invokevirtual #130                // Method org/apache/hbase/thirdparty/com/google/protobuf/RepeatedFieldBuilderV3.addBuilder:(Lorg/apache/hbase/thirdparty/com/google/protobuf/AbstractMessage;)Lorg/apache/hbase/thirdparty/com/google/protobuf/AbstractMessage$Builder;
      10: checkcast     #125                // class org/apache/hadoop/hbase/shaded/protobuf/generated/HBaseProtos$RegionInfo$Builder
      13: areturn

  public org.apache.hadoop.hbase.shaded.protobuf.generated.HBaseProtos$RegionInfo$Builder addRegionsOnCrashedServerBuilder(int);
    Code:
       0: aload_0
       1: invokespecial #18                 // Method getRegionsOnCrashedServerFieldBuilder:()Lorg/apache/hbase/thirdparty/com/google/protobuf/RepeatedFieldBuilderV3;
       4: iload_1
       5: invokestatic  #129                // Method org/apache/hadoop/hbase/shaded/protobuf/generated/HBaseProtos$RegionInfo.getDefaultInstance:()Lorg/apache/hadoop/hbase/shaded/protobuf/generated/HBaseProtos$RegionInfo;
       8: invokevirtual #131                // Method org/apache/hbase/thirdparty/com/google/protobuf/RepeatedFieldBuilderV3.addBuilder:(ILorg/apache/hbase/thirdparty/com/google/protobuf/AbstractMessage;)Lorg/apache/hbase/thirdparty/com/google/protobuf/AbstractMessage$Builder;
      11: checkcast     #125                // class org/apache/hadoop/hbase/shaded/protobuf/generated/HBaseProtos$RegionInfo$Builder
      14: areturn

  public java.util.List<org.apache.hadoop.hbase.shaded.protobuf.generated.HBaseProtos$RegionInfo$Builder> getRegionsOnCrashedServerBuilderList();
    Code:
       0: aload_0
       1: invokespecial #18                 // Method getRegionsOnCrashedServerFieldBuilder:()Lorg/apache/hbase/thirdparty/com/google/protobuf/RepeatedFieldBuilderV3;
       4: invokevirtual #132                // Method org/apache/hbase/thirdparty/com/google/protobuf/RepeatedFieldBuilderV3.getBuilderList:()Ljava/util/List;
       7: areturn

  public java.util.List<org.apache.hadoop.hbase.shaded.protobuf.generated.HBaseProtos$RegionInfo> getRegionsAssignedList();
    Code:
       0: aload_0
       1: getfield      #26                 // Field regionsAssignedBuilder_:Lorg/apache/hbase/thirdparty/com/google/protobuf/RepeatedFieldBuilderV3;
       4: ifnonnull     15
       7: aload_0
       8: getfield      #12                 // Field regionsAssigned_:Ljava/util/List;
      11: invokestatic  #36                 // Method java/util/Collections.unmodifiableList:(Ljava/util/List;)Ljava/util/List;
      14: areturn
      15: aload_0
      16: getfield      #26                 // Field regionsAssignedBuilder_:Lorg/apache/hbase/thirdparty/com/google/protobuf/RepeatedFieldBuilderV3;
      19: invokevirtual #108                // Method org/apache/hbase/thirdparty/com/google/protobuf/RepeatedFieldBuilderV3.getMessageList:()Ljava/util/List;
      22: areturn

  public int getRegionsAssignedCount();
    Code:
       0: aload_0
       1: getfield      #26                 // Field regionsAssignedBuilder_:Lorg/apache/hbase/thirdparty/com/google/protobuf/RepeatedFieldBuilderV3;
       4: ifnonnull     17
       7: aload_0
       8: getfield      #12                 // Field regionsAssigned_:Ljava/util/List;
      11: invokeinterface #109,  1          // InterfaceMethod java/util/List.size:()I
      16: ireturn
      17: aload_0
      18: getfield      #26                 // Field regionsAssignedBuilder_:Lorg/apache/hbase/thirdparty/com/google/protobuf/RepeatedFieldBuilderV3;
      21: invokevirtual #110                // Method org/apache/hbase/thirdparty/com/google/protobuf/RepeatedFieldBuilderV3.getCount:()I
      24: ireturn

  public org.apache.hadoop.hbase.shaded.protobuf.generated.HBaseProtos$RegionInfo getRegionsAssigned(int);
    Code:
       0: aload_0
       1: getfield      #26                 // Field regionsAssignedBuilder_:Lorg/apache/hbase/thirdparty/com/google/protobuf/RepeatedFieldBuilderV3;
       4: ifnonnull     21
       7: aload_0
       8: getfield      #12                 // Field regionsAssigned_:Ljava/util/List;
      11: iload_1
      12: invokeinterface #111,  2          // InterfaceMethod java/util/List.get:(I)Ljava/lang/Object;
      17: checkcast     #112                // class org/apache/hadoop/hbase/shaded/protobuf/generated/HBaseProtos$RegionInfo
      20: areturn
      21: aload_0
      22: getfield      #26                 // Field regionsAssignedBuilder_:Lorg/apache/hbase/thirdparty/com/google/protobuf/RepeatedFieldBuilderV3;
      25: iload_1
      26: invokevirtual #113                // Method org/apache/hbase/thirdparty/com/google/protobuf/RepeatedFieldBuilderV3.getMessage:(I)Lorg/apache/hbase/thirdparty/com/google/protobuf/AbstractMessage;
      29: checkcast     #112                // class org/apache/hadoop/hbase/shaded/protobuf/generated/HBaseProtos$RegionInfo
      32: areturn

  public org.apache.hadoop.hbase.shaded.protobuf.generated.MasterProcedureProtos$ServerCrashStateData$Builder setRegionsAssigned(int, org.apache.hadoop.hbase.shaded.protobuf.generated.HBaseProtos$RegionInfo);
    Code:
       0: aload_0
       1: getfield      #26                 // Field regionsAssignedBuilder_:Lorg/apache/hbase/thirdparty/com/google/protobuf/RepeatedFieldBuilderV3;
       4: ifnonnull     42
       7: aload_2
       8: ifnonnull     19
      11: new           #90                 // class java/lang/NullPointerException
      14: dup
      15: invokespecial #91                 // Method java/lang/NullPointerException."<init>":()V
      18: athrow
      19: aload_0
      20: invokespecial #65                 // Method ensureRegionsAssignedIsMutable:()V
      23: aload_0
      24: getfield      #12                 // Field regionsAssigned_:Ljava/util/List;
      27: iload_1
      28: aload_2
      29: invokeinterface #114,  3          // InterfaceMethod java/util/List.set:(ILjava/lang/Object;)Ljava/lang/Object;
      34: pop
      35: aload_0
      36: invokevirtual #59                 // Method onChanged:()V
      39: goto          52
      42: aload_0
      43: getfield      #26                 // Field regionsAssignedBuilder_:Lorg/apache/hbase/thirdparty/com/google/protobuf/RepeatedFieldBuilderV3;
      46: iload_1
      47: aload_2
      48: invokevirtual #115                // Method org/apache/hbase/thirdparty/com/google/protobuf/RepeatedFieldBuilderV3.setMessage:(ILorg/apache/hbase/thirdparty/com/google/protobuf/AbstractMessage;)Lorg/apache/hbase/thirdparty/com/google/protobuf/RepeatedFieldBuilderV3;
      51: pop
      52: aload_0
      53: areturn

  public org.apache.hadoop.hbase.shaded.protobuf.generated.MasterProcedureProtos$ServerCrashStateData$Builder setRegionsAssigned(int, org.apache.hadoop.hbase.shaded.protobuf.generated.HBaseProtos$RegionInfo$Builder);
    Code:
       0: aload_0
       1: getfield      #26                 // Field regionsAssignedBuilder_:Lorg/apache/hbase/thirdparty/com/google/protobuf/RepeatedFieldBuilderV3;
       4: ifnonnull     33
       7: aload_0
       8: invokespecial #65                 // Method ensureRegionsAssignedIsMutable:()V
      11: aload_0
      12: getfield      #12                 // Field regionsAssigned_:Ljava/util/List;
      15: iload_1
      16: aload_2
      17: invokevirtual #116                // Method org/apache/hadoop/hbase/shaded/protobuf/generated/HBaseProtos$RegionInfo$Builder.build:()Lorg/apache/hadoop/hbase/shaded/protobuf/generated/HBaseProtos$RegionInfo;
      20: invokeinterface #114,  3          // InterfaceMethod java/util/List.set:(ILjava/lang/Object;)Ljava/lang/Object;
      25: pop
      26: aload_0
      27: invokevirtual #59                 // Method onChanged:()V
      30: goto          46
      33: aload_0
      34: getfield      #26                 // Field regionsAssignedBuilder_:Lorg/apache/hbase/thirdparty/com/google/protobuf/RepeatedFieldBuilderV3;
      37: iload_1
      38: aload_2
      39: invokevirtual #116                // Method org/apache/hadoop/hbase/shaded/protobuf/generated/HBaseProtos$RegionInfo$Builder.build:()Lorg/apache/hadoop/hbase/shaded/protobuf/generated/HBaseProtos$RegionInfo;
      42: invokevirtual #115                // Method org/apache/hbase/thirdparty/com/google/protobuf/RepeatedFieldBuilderV3.setMessage:(ILorg/apache/hbase/thirdparty/com/google/protobuf/AbstractMessage;)Lorg/apache/hbase/thirdparty/com/google/protobuf/RepeatedFieldBuilderV3;
      45: pop
      46: aload_0
      47: areturn

  public org.apache.hadoop.hbase.shaded.protobuf.generated.MasterProcedureProtos$ServerCrashStateData$Builder addRegionsAssigned(org.apache.hadoop.hbase.shaded.protobuf.generated.HBaseProtos$RegionInfo);
    Code:
       0: aload_0
       1: getfield      #26                 // Field regionsAssignedBuilder_:Lorg/apache/hbase/thirdparty/com/google/protobuf/RepeatedFieldBuilderV3;
       4: ifnonnull     41
       7: aload_1
       8: ifnonnull     19
      11: new           #90                 // class java/lang/NullPointerException
      14: dup
      15: invokespecial #91                 // Method java/lang/NullPointerException."<init>":()V
      18: athrow
      19: aload_0
      20: invokespecial #65                 // Method ensureRegionsAssignedIsMutable:()V
      23: aload_0
      24: getfield      #12                 // Field regionsAssigned_:Ljava/util/List;
      27: aload_1
      28: invokeinterface #117,  2          // InterfaceMethod java/util/List.add:(Ljava/lang/Object;)Z
      33: pop
      34: aload_0
      35: invokevirtual #59                 // Method onChanged:()V
      38: goto          50
      41: aload_0
      42: getfield      #26                 // Field regionsAssignedBuilder_:Lorg/apache/hbase/thirdparty/com/google/protobuf/RepeatedFieldBuilderV3;
      45: aload_1
      46: invokevirtual #118                // Method org/apache/hbase/thirdparty/com/google/protobuf/RepeatedFieldBuilderV3.addMessage:(Lorg/apache/hbase/thirdparty/com/google/protobuf/AbstractMessage;)Lorg/apache/hbase/thirdparty/com/google/protobuf/RepeatedFieldBuilderV3;
      49: pop
      50: aload_0
      51: areturn

  public org.apache.hadoop.hbase.shaded.protobuf.generated.MasterProcedureProtos$ServerCrashStateData$Builder addRegionsAssigned(int, org.apache.hadoop.hbase.shaded.protobuf.generated.HBaseProtos$RegionInfo);
    Code:
       0: aload_0
       1: getfield      #26                 // Field regionsAssignedBuilder_:Lorg/apache/hbase/thirdparty/com/google/protobuf/RepeatedFieldBuilderV3;
       4: ifnonnull     41
       7: aload_2
       8: ifnonnull     19
      11: new           #90                 // class java/lang/NullPointerException
      14: dup
      15: invokespecial #91                 // Method java/lang/NullPointerException."<init>":()V
      18: athrow
      19: aload_0
      20: invokespecial #65                 // Method ensureRegionsAssignedIsMutable:()V
      23: aload_0
      24: getfield      #12                 // Field regionsAssigned_:Ljava/util/List;
      27: iload_1
      28: aload_2
      29: invokeinterface #119,  3          // InterfaceMethod java/util/List.add:(ILjava/lang/Object;)V
      34: aload_0
      35: invokevirtual #59                 // Method onChanged:()V
      38: goto          51
      41: aload_0
      42: getfield      #26                 // Field regionsAssignedBuilder_:Lorg/apache/hbase/thirdparty/com/google/protobuf/RepeatedFieldBuilderV3;
      45: iload_1
      46: aload_2
      47: invokevirtual #120                // Method org/apache/hbase/thirdparty/com/google/protobuf/RepeatedFieldBuilderV3.addMessage:(ILorg/apache/hbase/thirdparty/com/google/protobuf/AbstractMessage;)Lorg/apache/hbase/thirdparty/com/google/protobuf/RepeatedFieldBuilderV3;
      50: pop
      51: aload_0
      52: areturn

  public org.apache.hadoop.hbase.shaded.protobuf.generated.MasterProcedureProtos$ServerCrashStateData$Builder addRegionsAssigned(org.apache.hadoop.hbase.shaded.protobuf.generated.HBaseProtos$RegionInfo$Builder);
    Code:
       0: aload_0
       1: getfield      #26                 // Field regionsAssignedBuilder_:Lorg/apache/hbase/thirdparty/com/google/protobuf/RepeatedFieldBuilderV3;
       4: ifnonnull     32
       7: aload_0
       8: invokespecial #65                 // Method ensureRegionsAssignedIsMutable:()V
      11: aload_0
      12: getfield      #12                 // Field regionsAssigned_:Ljava/util/List;
      15: aload_1
      16: invokevirtual #116                // Method org/apache/hadoop/hbase/shaded/protobuf/generated/HBaseProtos$RegionInfo$Builder.build:()Lorg/apache/hadoop/hbase/shaded/protobuf/generated/HBaseProtos$RegionInfo;
      19: invokeinterface #117,  2          // InterfaceMethod java/util/List.add:(Ljava/lang/Object;)Z
      24: pop
      25: aload_0
      26: invokevirtual #59                 // Method onChanged:()V
      29: goto          44
      32: aload_0
      33: getfield      #26                 // Field regionsAssignedBuilder_:Lorg/apache/hbase/thirdparty/com/google/protobuf/RepeatedFieldBuilderV3;
      36: aload_1
      37: invokevirtual #116                // Method org/apache/hadoop/hbase/shaded/protobuf/generated/HBaseProtos$RegionInfo$Builder.build:()Lorg/apache/hadoop/hbase/shaded/protobuf/generated/HBaseProtos$RegionInfo;
      40: invokevirtual #118                // Method org/apache/hbase/thirdparty/com/google/protobuf/RepeatedFieldBuilderV3.addMessage:(Lorg/apache/hbase/thirdparty/com/google/protobuf/AbstractMessage;)Lorg/apache/hbase/thirdparty/com/google/protobuf/RepeatedFieldBuilderV3;
      43: pop
      44: aload_0
      45: areturn

  public org.apache.hadoop.hbase.shaded.protobuf.generated.MasterProcedureProtos$ServerCrashStateData$Builder addRegionsAssigned(int, org.apache.hadoop.hbase.shaded.protobuf.generated.HBaseProtos$RegionInfo$Builder);
    Code:
       0: aload_0
       1: getfield      #26                 // Field regionsAssignedBuilder_:Lorg/apache/hbase/thirdparty/com/google/protobuf/RepeatedFieldBuilderV3;
       4: ifnonnull     32
       7: aload_0
       8: invokespecial #65                 // Method ensureRegionsAssignedIsMutable:()V
      11: aload_0
      12: getfield      #12                 // Field regionsAssigned_:Ljava/util/List;
      15: iload_1
      16: aload_2
      17: invokevirtual #116                // Method org/apache/hadoop/hbase/shaded/protobuf/generated/HBaseProtos$RegionInfo$Builder.build:()Lorg/apache/hadoop/hbase/shaded/protobuf/generated/HBaseProtos$RegionInfo;
      20: invokeinterface #119,  3          // InterfaceMethod java/util/List.add:(ILjava/lang/Object;)V
      25: aload_0
      26: invokevirtual #59                 // Method onChanged:()V
      29: goto          45
      32: aload_0
      33: getfield      #26                 // Field regionsAssignedBuilder_:Lorg/apache/hbase/thirdparty/com/google/protobuf/RepeatedFieldBuilderV3;
      36: iload_1
      37: aload_2
      38: invokevirtual #116                // Method org/apache/hadoop/hbase/shaded/protobuf/generated/HBaseProtos$RegionInfo$Builder.build:()Lorg/apache/hadoop/hbase/shaded/protobuf/generated/HBaseProtos$RegionInfo;
      41: invokevirtual #120                // Method org/apache/hbase/thirdparty/com/google/protobuf/RepeatedFieldBuilderV3.addMessage:(ILorg/apache/hbase/thirdparty/com/google/protobuf/AbstractMessage;)Lorg/apache/hbase/thirdparty/com/google/protobuf/RepeatedFieldBuilderV3;
      44: pop
      45: aload_0
      46: areturn

  public org.apache.hadoop.hbase.shaded.protobuf.generated.MasterProcedureProtos$ServerCrashStateData$Builder addAllRegionsAssigned(java.lang.Iterable<? extends org.apache.hadoop.hbase.shaded.protobuf.generated.HBaseProtos$RegionInfo>);
    Code:
       0: aload_0
       1: getfield      #26                 // Field regionsAssignedBuilder_:Lorg/apache/hbase/thirdparty/com/google/protobuf/RepeatedFieldBuilderV3;
       4: ifnonnull     26
       7: aload_0
       8: invokespecial #65                 // Method ensureRegionsAssignedIsMutable:()V
      11: aload_1
      12: aload_0
      13: getfield      #12                 // Field regionsAssigned_:Ljava/util/List;
      16: invokestatic  #121                // Method org/apache/hbase/thirdparty/com/google/protobuf/AbstractMessageLite$Builder.addAll:(Ljava/lang/Iterable;Ljava/util/List;)V
      19: aload_0
      20: invokevirtual #59                 // Method onChanged:()V
      23: goto          35
      26: aload_0
      27: getfield      #26                 // Field regionsAssignedBuilder_:Lorg/apache/hbase/thirdparty/com/google/protobuf/RepeatedFieldBuilderV3;
      30: aload_1
      31: invokevirtual #63                 // Method org/apache/hbase/thirdparty/com/google/protobuf/RepeatedFieldBuilderV3.addAllMessages:(Ljava/lang/Iterable;)Lorg/apache/hbase/thirdparty/com/google/protobuf/RepeatedFieldBuilderV3;
      34: pop
      35: aload_0
      36: areturn

  public org.apache.hadoop.hbase.shaded.protobuf.generated.MasterProcedureProtos$ServerCrashStateData$Builder clearRegionsAssigned();
    Code:
       0: aload_0
       1: getfield      #26                 // Field regionsAssignedBuilder_:Lorg/apache/hbase/thirdparty/com/google/protobuf/RepeatedFieldBuilderV3;
       4: ifnonnull     32
       7: aload_0
       8: invokestatic  #10                 // Method java/util/Collections.emptyList:()Ljava/util/List;
      11: putfield      #12                 // Field regionsAssigned_:Ljava/util/List;
      14: aload_0
      15: aload_0
      16: getfield      #23                 // Field bitField0_:I
      19: bipush        -5
      21: iand
      22: putfield      #23                 // Field bitField0_:I
      25: aload_0
      26: invokevirtual #59                 // Method onChanged:()V
      29: goto          39
      32: aload_0
      33: getfield      #26                 // Field regionsAssignedBuilder_:Lorg/apache/hbase/thirdparty/com/google/protobuf/RepeatedFieldBuilderV3;
      36: invokevirtual #25                 // Method org/apache/hbase/thirdparty/com/google/protobuf/RepeatedFieldBuilderV3.clear:()V
      39: aload_0
      40: areturn

  public org.apache.hadoop.hbase.shaded.protobuf.generated.MasterProcedureProtos$ServerCrashStateData$Builder removeRegionsAssigned(int);
    Code:
       0: aload_0
       1: getfield      #26                 // Field regionsAssignedBuilder_:Lorg/apache/hbase/thirdparty/com/google/protobuf/RepeatedFieldBuilderV3;
       4: ifnonnull     29
       7: aload_0
       8: invokespecial #65                 // Method ensureRegionsAssignedIsMutable:()V
      11: aload_0
      12: getfield      #12                 // Field regionsAssigned_:Ljava/util/List;
      15: iload_1
      16: invokeinterface #122,  2          // InterfaceMethod java/util/List.remove:(I)Ljava/lang/Object;
      21: pop
      22: aload_0
      23: invokevirtual #59                 // Method onChanged:()V
      26: goto          37
      29: aload_0
      30: getfield      #26                 // Field regionsAssignedBuilder_:Lorg/apache/hbase/thirdparty/com/google/protobuf/RepeatedFieldBuilderV3;
      33: iload_1
      34: invokevirtual #123                // Method org/apache/hbase/thirdparty/com/google/protobuf/RepeatedFieldBuilderV3.remove:(I)V
      37: aload_0
      38: areturn

  public org.apache.hadoop.hbase.shaded.protobuf.generated.HBaseProtos$RegionInfo$Builder getRegionsAssignedBuilder(int);
    Code:
       0: aload_0
       1: invokespecial #19                 // Method getRegionsAssignedFieldBuilder:()Lorg/apache/hbase/thirdparty/com/google/protobuf/RepeatedFieldBuilderV3;
       4: iload_1
       5: invokevirtual #124                // Method org/apache/hbase/thirdparty/com/google/protobuf/RepeatedFieldBuilderV3.getBuilder:(I)Lorg/apache/hbase/thirdparty/com/google/protobuf/AbstractMessage$Builder;
       8: checkcast     #125                // class org/apache/hadoop/hbase/shaded/protobuf/generated/HBaseProtos$RegionInfo$Builder
      11: areturn

  public org.apache.hadoop.hbase.shaded.protobuf.generated.HBaseProtos$RegionInfoOrBuilder getRegionsAssignedOrBuilder(int);
    Code:
       0: aload_0
       1: getfield      #26                 // Field regionsAssignedBuilder_:Lorg/apache/hbase/thirdparty/com/google/protobuf/RepeatedFieldBuilderV3;
       4: ifnonnull     21
       7: aload_0
       8: getfield      #12                 // Field regionsAssigned_:Ljava/util/List;
      11: iload_1
      12: invokeinterface #111,  2          // InterfaceMethod java/util/List.get:(I)Ljava/lang/Object;
      17: checkcast     #126                // class org/apache/hadoop/hbase/shaded/protobuf/generated/HBaseProtos$RegionInfoOrBuilder
      20: areturn
      21: aload_0
      22: getfield      #26                 // Field regionsAssignedBuilder_:Lorg/apache/hbase/thirdparty/com/google/protobuf/RepeatedFieldBuilderV3;
      25: iload_1
      26: invokevirtual #127                // Method org/apache/hbase/thirdparty/com/google/protobuf/RepeatedFieldBuilderV3.getMessageOrBuilder:(I)Lorg/apache/hbase/thirdparty/com/google/protobuf/MessageOrBuilder;
      29: checkcast     #126                // class org/apache/hadoop/hbase/shaded/protobuf/generated/HBaseProtos$RegionInfoOrBuilder
      32: areturn

  public java.util.List<? extends org.apache.hadoop.hbase.shaded.protobuf.generated.HBaseProtos$RegionInfoOrBuilder> getRegionsAssignedOrBuilderList();
    Code:
       0: aload_0
       1: getfield      #26                 // Field regionsAssignedBuilder_:Lorg/apache/hbase/thirdparty/com/google/protobuf/RepeatedFieldBuilderV3;
       4: ifnull        15
       7: aload_0
       8: getfield      #26                 // Field regionsAssignedBuilder_:Lorg/apache/hbase/thirdparty/com/google/protobuf/RepeatedFieldBuilderV3;
      11: invokevirtual #128                // Method org/apache/hbase/thirdparty/com/google/protobuf/RepeatedFieldBuilderV3.getMessageOrBuilderList:()Ljava/util/List;
      14: areturn
      15: aload_0
      16: getfield      #12                 // Field regionsAssigned_:Ljava/util/List;
      19: invokestatic  #36                 // Method java/util/Collections.unmodifiableList:(Ljava/util/List;)Ljava/util/List;
      22: areturn

  public org.apache.hadoop.hbase.shaded.protobuf.generated.HBaseProtos$RegionInfo$Builder addRegionsAssignedBuilder();
    Code:
       0: aload_0
       1: invokespecial #19                 // Method getRegionsAssignedFieldBuilder:()Lorg/apache/hbase/thirdparty/com/google/protobuf/RepeatedFieldBuilderV3;
       4: invokestatic  #129                // Method org/apache/hadoop/hbase/shaded/protobuf/generated/HBaseProtos$RegionInfo.getDefaultInstance:()Lorg/apache/hadoop/hbase/shaded/protobuf/generated/HBaseProtos$RegionInfo;
       7: invokevirtual #130                // Method org/apache/hbase/thirdparty/com/google/protobuf/RepeatedFieldBuilderV3.addBuilder:(Lorg/apache/hbase/thirdparty/com/google/protobuf/AbstractMessage;)Lorg/apache/hbase/thirdparty/com/google/protobuf/AbstractMessage$Builder;
      10: checkcast     #125                // class org/apache/hadoop/hbase/shaded/protobuf/generated/HBaseProtos$RegionInfo$Builder
      13: areturn

  public org.apache.hadoop.hbase.shaded.protobuf.generated.HBaseProtos$RegionInfo$Builder addRegionsAssignedBuilder(int);
    Code:
       0: aload_0
       1: invokespecial #19                 // Method getRegionsAssignedFieldBuilder:()Lorg/apache/hbase/thirdparty/com/google/protobuf/RepeatedFieldBuilderV3;
       4: iload_1
       5: invokestatic  #129                // Method org/apache/hadoop/hbase/shaded/protobuf/generated/HBaseProtos$RegionInfo.getDefaultInstance:()Lorg/apache/hadoop/hbase/shaded/protobuf/generated/HBaseProtos$RegionInfo;
       8: invokevirtual #131                // Method org/apache/hbase/thirdparty/com/google/protobuf/RepeatedFieldBuilderV3.addBuilder:(ILorg/apache/hbase/thirdparty/com/google/protobuf/AbstractMessage;)Lorg/apache/hbase/thirdparty/com/google/protobuf/AbstractMessage$Builder;
      11: checkcast     #125                // class org/apache/hadoop/hbase/shaded/protobuf/generated/HBaseProtos$RegionInfo$Builder
      14: areturn

  public java.util.List<org.apache.hadoop.hbase.shaded.protobuf.generated.HBaseProtos$RegionInfo$Builder> getRegionsAssignedBuilderList();
    Code:
       0: aload_0
       1: invokespecial #19                 // Method getRegionsAssignedFieldBuilder:()Lorg/apache/hbase/thirdparty/com/google/protobuf/RepeatedFieldBuilderV3;
       4: invokevirtual #132                // Method org/apache/hbase/thirdparty/com/google/protobuf/RepeatedFieldBuilderV3.getBuilderList:()Ljava/util/List;
       7: areturn

  public boolean hasCarryingMeta();
    Code:
       0: aload_0
       1: getfield      #23                 // Field bitField0_:I
       4: bipush        8
       6: iand
       7: bipush        8
       9: if_icmpne     16
      12: iconst_1
      13: goto          17
      16: iconst_0
      17: ireturn

  public boolean getCarryingMeta();
    Code:
       0: aload_0
       1: getfield      #27                 // Field carryingMeta_:Z
       4: ireturn

  public org.apache.hadoop.hbase.shaded.protobuf.generated.MasterProcedureProtos$ServerCrashStateData$Builder setCarryingMeta(boolean);
    Code:
       0: aload_0
       1: dup
       2: getfield      #23                 // Field bitField0_:I
       5: bipush        8
       7: ior
       8: putfield      #23                 // Field bitField0_:I
      11: aload_0
      12: iload_1
      13: putfield      #27                 // Field carryingMeta_:Z
      16: aload_0
      17: invokevirtual #59                 // Method onChanged:()V
      20: aload_0
      21: areturn

  public org.apache.hadoop.hbase.shaded.protobuf.generated.MasterProcedureProtos$ServerCrashStateData$Builder clearCarryingMeta();
    Code:
       0: aload_0
       1: aload_0
       2: getfield      #23                 // Field bitField0_:I
       5: bipush        -9
       7: iand
       8: putfield      #23                 // Field bitField0_:I
      11: aload_0
      12: iconst_0
      13: putfield      #27                 // Field carryingMeta_:Z
      16: aload_0
      17: invokevirtual #59                 // Method onChanged:()V
      20: aload_0
      21: areturn

  public boolean hasShouldSplitWal();
    Code:
       0: aload_0
       1: getfield      #23                 // Field bitField0_:I
       4: bipush        16
       6: iand
       7: bipush        16
       9: if_icmpne     16
      12: iconst_1
      13: goto          17
      16: iconst_0
      17: ireturn

  public boolean getShouldSplitWal();
    Code:
       0: aload_0
       1: getfield      #13                 // Field shouldSplitWal_:Z
       4: ireturn

  public org.apache.hadoop.hbase.shaded.protobuf.generated.MasterProcedureProtos$ServerCrashStateData$Builder setShouldSplitWal(boolean);
    Code:
       0: aload_0
       1: dup
       2: getfield      #23                 // Field bitField0_:I
       5: bipush        16
       7: ior
       8: putfield      #23                 // Field bitField0_:I
      11: aload_0
      12: iload_1
      13: putfield      #13                 // Field shouldSplitWal_:Z
      16: aload_0
      17: invokevirtual #59                 // Method onChanged:()V
      20: aload_0
      21: areturn

  public org.apache.hadoop.hbase.shaded.protobuf.generated.MasterProcedureProtos$ServerCrashStateData$Builder clearShouldSplitWal();
    Code:
       0: aload_0
       1: aload_0
       2: getfield      #23                 // Field bitField0_:I
       5: bipush        -17
       7: iand
       8: putfield      #23                 // Field bitField0_:I
      11: aload_0
      12: iconst_1
      13: putfield      #13                 // Field shouldSplitWal_:Z
      16: aload_0
      17: invokevirtual #59                 // Method onChanged:()V
      20: aload_0
      21: areturn

  public final org.apache.hadoop.hbase.shaded.protobuf.generated.MasterProcedureProtos$ServerCrashStateData$Builder setUnknownFields(org.apache.hbase.thirdparty.com.google.protobuf.UnknownFieldSet);
    Code:
       0: aload_0
       1: aload_1
       2: invokespecial #135                // Method org/apache/hbase/thirdparty/com/google/protobuf/GeneratedMessageV3$Builder.setUnknownFields:(Lorg/apache/hbase/thirdparty/com/google/protobuf/UnknownFieldSet;)Lorg/apache/hbase/thirdparty/com/google/protobuf/GeneratedMessageV3$Builder;
       5: checkcast     #6                  // class org/apache/hadoop/hbase/shaded/protobuf/generated/MasterProcedureProtos$ServerCrashStateData$Builder
       8: areturn

  public final org.apache.hadoop.hbase.shaded.protobuf.generated.MasterProcedureProtos$ServerCrashStateData$Builder mergeUnknownFields(org.apache.hbase.thirdparty.com.google.protobuf.UnknownFieldSet);
    Code:
       0: aload_0
       1: aload_1
       2: invokespecial #136                // Method org/apache/hbase/thirdparty/com/google/protobuf/GeneratedMessageV3$Builder.mergeUnknownFields:(Lorg/apache/hbase/thirdparty/com/google/protobuf/UnknownFieldSet;)Lorg/apache/hbase/thirdparty/com/google/protobuf/GeneratedMessageV3$Builder;
       5: checkcast     #6                  // class org/apache/hadoop/hbase/shaded/protobuf/generated/MasterProcedureProtos$ServerCrashStateData$Builder
       8: areturn

  public org.apache.hbase.thirdparty.com.google.protobuf.GeneratedMessageV3$Builder mergeUnknownFields(org.apache.hbase.thirdparty.com.google.protobuf.UnknownFieldSet);
    Code:
       0: aload_0
       1: aload_1
       2: invokevirtual #74                 // Method mergeUnknownFields:(Lorg/apache/hbase/thirdparty/com/google/protobuf/UnknownFieldSet;)Lorg/apache/hadoop/hbase/shaded/protobuf/generated/MasterProcedureProtos$ServerCrashStateData$Builder;
       5: areturn

  public org.apache.hbase.thirdparty.com.google.protobuf.GeneratedMessageV3$Builder setUnknownFields(org.apache.hbase.thirdparty.com.google.protobuf.UnknownFieldSet);
    Code:
       0: aload_0
       1: aload_1
       2: invokevirtual #137                // Method setUnknownFields:(Lorg/apache/hbase/thirdparty/com/google/protobuf/UnknownFieldSet;)Lorg/apache/hadoop/hbase/shaded/protobuf/generated/MasterProcedureProtos$ServerCrashStateData$Builder;
       5: areturn

  public org.apache.hbase.thirdparty.com.google.protobuf.GeneratedMessageV3$Builder addRepeatedField(org.apache.hbase.thirdparty.com.google.protobuf.Descriptors$FieldDescriptor, java.lang.Object);
    Code:
       0: aload_0
       1: aload_1
       2: aload_2
       3: invokevirtual #138                // Method addRepeatedField:(Lorg/apache/hbase/thirdparty/com/google/protobuf/Descriptors$FieldDescriptor;Ljava/lang/Object;)Lorg/apache/hadoop/hbase/shaded/protobuf/generated/MasterProcedureProtos$ServerCrashStateData$Builder;
       6: areturn

  public org.apache.hbase.thirdparty.com.google.protobuf.GeneratedMessageV3$Builder setRepeatedField(org.apache.hbase.thirdparty.com.google.protobuf.Descriptors$FieldDescriptor, int, java.lang.Object);
    Code:
       0: aload_0
       1: aload_1
       2: iload_2
       3: aload_3
       4: invokevirtual #139                // Method setRepeatedField:(Lorg/apache/hbase/thirdparty/com/google/protobuf/Descriptors$FieldDescriptor;ILjava/lang/Object;)Lorg/apache/hadoop/hbase/shaded/protobuf/generated/MasterProcedureProtos$ServerCrashStateData$Builder;
       7: areturn

  public org.apache.hbase.thirdparty.com.google.protobuf.GeneratedMessageV3$Builder clearOneof(org.apache.hbase.thirdparty.com.google.protobuf.Descriptors$OneofDescriptor);
    Code:
       0: aload_0
       1: aload_1
       2: invokevirtual #140                // Method clearOneof:(Lorg/apache/hbase/thirdparty/com/google/protobuf/Descriptors$OneofDescriptor;)Lorg/apache/hadoop/hbase/shaded/protobuf/generated/MasterProcedureProtos$ServerCrashStateData$Builder;
       5: areturn

  public org.apache.hbase.thirdparty.com.google.protobuf.GeneratedMessageV3$Builder clearField(org.apache.hbase.thirdparty.com.google.protobuf.Descriptors$FieldDescriptor);
    Code:
       0: aload_0
       1: aload_1
       2: invokevirtual #141                // Method clearField:(Lorg/apache/hbase/thirdparty/com/google/protobuf/Descriptors$FieldDescriptor;)Lorg/apache/hadoop/hbase/shaded/protobuf/generated/MasterProcedureProtos$ServerCrashStateData$Builder;
       5: areturn

  public org.apache.hbase.thirdparty.com.google.protobuf.GeneratedMessageV3$Builder setField(org.apache.hbase.thirdparty.com.google.protobuf.Descriptors$FieldDescriptor, java.lang.Object);
    Code:
       0: aload_0
       1: aload_1
       2: aload_2
       3: invokevirtual #142                // Method setField:(Lorg/apache/hbase/thirdparty/com/google/protobuf/Descriptors$FieldDescriptor;Ljava/lang/Object;)Lorg/apache/hadoop/hbase/shaded/protobuf/generated/MasterProcedureProtos$ServerCrashStateData$Builder;
       6: areturn

  public org.apache.hbase.thirdparty.com.google.protobuf.GeneratedMessageV3$Builder clear();
    Code:
       0: aload_0
       1: invokevirtual #143                // Method clear:()Lorg/apache/hadoop/hbase/shaded/protobuf/generated/MasterProcedureProtos$ServerCrashStateData$Builder;
       4: areturn

  public org.apache.hbase.thirdparty.com.google.protobuf.GeneratedMessageV3$Builder clone();
    Code:
       0: aload_0
       1: invokevirtual #144                // Method clone:()Lorg/apache/hadoop/hbase/shaded/protobuf/generated/MasterProcedureProtos$ServerCrashStateData$Builder;
       4: areturn

  public org.apache.hbase.thirdparty.com.google.protobuf.AbstractMessage$Builder mergeUnknownFields(org.apache.hbase.thirdparty.com.google.protobuf.UnknownFieldSet);
    Code:
       0: aload_0
       1: aload_1
       2: invokevirtual #74                 // Method mergeUnknownFields:(Lorg/apache/hbase/thirdparty/com/google/protobuf/UnknownFieldSet;)Lorg/apache/hadoop/hbase/shaded/protobuf/generated/MasterProcedureProtos$ServerCrashStateData$Builder;
       5: areturn

  public org.apache.hbase.thirdparty.com.google.protobuf.AbstractMessage$Builder mergeFrom(org.apache.hbase.thirdparty.com.google.protobuf.CodedInputStream, org.apache.hbase.thirdparty.com.google.protobuf.ExtensionRegistryLite) throws java.io.IOException;
    Code:
       0: aload_0
       1: aload_1
       2: aload_2
       3: invokevirtual #145                // Method mergeFrom:(Lorg/apache/hbase/thirdparty/com/google/protobuf/CodedInputStream;Lorg/apache/hbase/thirdparty/com/google/protobuf/ExtensionRegistryLite;)Lorg/apache/hadoop/hbase/shaded/protobuf/generated/MasterProcedureProtos$ServerCrashStateData$Builder;
       6: areturn

  public org.apache.hbase.thirdparty.com.google.protobuf.AbstractMessage$Builder mergeFrom(org.apache.hbase.thirdparty.com.google.protobuf.Message);
    Code:
       0: aload_0
       1: aload_1
       2: invokevirtual #146                // Method mergeFrom:(Lorg/apache/hbase/thirdparty/com/google/protobuf/Message;)Lorg/apache/hadoop/hbase/shaded/protobuf/generated/MasterProcedureProtos$ServerCrashStateData$Builder;
       5: areturn

  public org.apache.hbase.thirdparty.com.google.protobuf.AbstractMessage$Builder clear();
    Code:
       0: aload_0
       1: invokevirtual #143                // Method clear:()Lorg/apache/hadoop/hbase/shaded/protobuf/generated/MasterProcedureProtos$ServerCrashStateData$Builder;
       4: areturn

  public org.apache.hbase.thirdparty.com.google.protobuf.AbstractMessage$Builder clearOneof(org.apache.hbase.thirdparty.com.google.protobuf.Descriptors$OneofDescriptor);
    Code:
       0: aload_0
       1: aload_1
       2: invokevirtual #140                // Method clearOneof:(Lorg/apache/hbase/thirdparty/com/google/protobuf/Descriptors$OneofDescriptor;)Lorg/apache/hadoop/hbase/shaded/protobuf/generated/MasterProcedureProtos$ServerCrashStateData$Builder;
       5: areturn

  public org.apache.hbase.thirdparty.com.google.protobuf.AbstractMessage$Builder clone();
    Code:
       0: aload_0
       1: invokevirtual #144                // Method clone:()Lorg/apache/hadoop/hbase/shaded/protobuf/generated/MasterProcedureProtos$ServerCrashStateData$Builder;
       4: areturn

  public org.apache.hbase.thirdparty.com.google.protobuf.Message$Builder mergeUnknownFields(org.apache.hbase.thirdparty.com.google.protobuf.UnknownFieldSet);
    Code:
       0: aload_0
       1: aload_1
       2: invokevirtual #74                 // Method mergeUnknownFields:(Lorg/apache/hbase/thirdparty/com/google/protobuf/UnknownFieldSet;)Lorg/apache/hadoop/hbase/shaded/protobuf/generated/MasterProcedureProtos$ServerCrashStateData$Builder;
       5: areturn

  public org.apache.hbase.thirdparty.com.google.protobuf.Message$Builder setUnknownFields(org.apache.hbase.thirdparty.com.google.protobuf.UnknownFieldSet);
    Code:
       0: aload_0
       1: aload_1
       2: invokevirtual #137                // Method setUnknownFields:(Lorg/apache/hbase/thirdparty/com/google/protobuf/UnknownFieldSet;)Lorg/apache/hadoop/hbase/shaded/protobuf/generated/MasterProcedureProtos$ServerCrashStateData$Builder;
       5: areturn

  public org.apache.hbase.thirdparty.com.google.protobuf.Message$Builder addRepeatedField(org.apache.hbase.thirdparty.com.google.protobuf.Descriptors$FieldDescriptor, java.lang.Object);
    Code:
       0: aload_0
       1: aload_1
       2: aload_2
       3: invokevirtual #138                // Method addRepeatedField:(Lorg/apache/hbase/thirdparty/com/google/protobuf/Descriptors$FieldDescriptor;Ljava/lang/Object;)Lorg/apache/hadoop/hbase/shaded/protobuf/generated/MasterProcedureProtos$ServerCrashStateData$Builder;
       6: areturn

  public org.apache.hbase.thirdparty.com.google.protobuf.Message$Builder setRepeatedField(org.apache.hbase.thirdparty.com.google.protobuf.Descriptors$FieldDescriptor, int, java.lang.Object);
    Code:
       0: aload_0
       1: aload_1
       2: iload_2
       3: aload_3
       4: invokevirtual #139                // Method setRepeatedField:(Lorg/apache/hbase/thirdparty/com/google/protobuf/Descriptors$FieldDescriptor;ILjava/lang/Object;)Lorg/apache/hadoop/hbase/shaded/protobuf/generated/MasterProcedureProtos$ServerCrashStateData$Builder;
       7: areturn

  public org.apache.hbase.thirdparty.com.google.protobuf.Message$Builder clearOneof(org.apache.hbase.thirdparty.com.google.protobuf.Descriptors$OneofDescriptor);
    Code:
       0: aload_0
       1: aload_1
       2: invokevirtual #140                // Method clearOneof:(Lorg/apache/hbase/thirdparty/com/google/protobuf/Descriptors$OneofDescriptor;)Lorg/apache/hadoop/hbase/shaded/protobuf/generated/MasterProcedureProtos$ServerCrashStateData$Builder;
       5: areturn

  public org.apache.hbase.thirdparty.com.google.protobuf.Message$Builder clearField(org.apache.hbase.thirdparty.com.google.protobuf.Descriptors$FieldDescriptor);
    Code:
       0: aload_0
       1: aload_1
       2: invokevirtual #141                // Method clearField:(Lorg/apache/hbase/thirdparty/com/google/protobuf/Descriptors$FieldDescriptor;)Lorg/apache/hadoop/hbase/shaded/protobuf/generated/MasterProcedureProtos$ServerCrashStateData$Builder;
       5: areturn

  public org.apache.hbase.thirdparty.com.google.protobuf.Message$Builder setField(org.apache.hbase.thirdparty.com.google.protobuf.Descriptors$FieldDescriptor, java.lang.Object);
    Code:
       0: aload_0
       1: aload_1
       2: aload_2
       3: invokevirtual #142                // Method setField:(Lorg/apache/hbase/thirdparty/com/google/protobuf/Descriptors$FieldDescriptor;Ljava/lang/Object;)Lorg/apache/hadoop/hbase/shaded/protobuf/generated/MasterProcedureProtos$ServerCrashStateData$Builder;
       6: areturn

  public org.apache.hbase.thirdparty.com.google.protobuf.Message$Builder mergeFrom(org.apache.hbase.thirdparty.com.google.protobuf.CodedInputStream, org.apache.hbase.thirdparty.com.google.protobuf.ExtensionRegistryLite) throws java.io.IOException;
    Code:
       0: aload_0
       1: aload_1
       2: aload_2
       3: invokevirtual #145                // Method mergeFrom:(Lorg/apache/hbase/thirdparty/com/google/protobuf/CodedInputStream;Lorg/apache/hbase/thirdparty/com/google/protobuf/ExtensionRegistryLite;)Lorg/apache/hadoop/hbase/shaded/protobuf/generated/MasterProcedureProtos$ServerCrashStateData$Builder;
       6: areturn

  public org.apache.hbase.thirdparty.com.google.protobuf.Message$Builder clone();
    Code:
       0: aload_0
       1: invokevirtual #144                // Method clone:()Lorg/apache/hadoop/hbase/shaded/protobuf/generated/MasterProcedureProtos$ServerCrashStateData$Builder;
       4: areturn

  public org.apache.hbase.thirdparty.com.google.protobuf.Message buildPartial();
    Code:
       0: aload_0
       1: invokevirtual #29                 // Method buildPartial:()Lorg/apache/hadoop/hbase/shaded/protobuf/generated/MasterProcedureProtos$ServerCrashStateData;
       4: areturn

  public org.apache.hbase.thirdparty.com.google.protobuf.Message build();
    Code:
       0: aload_0
       1: invokevirtual #147                // Method build:()Lorg/apache/hadoop/hbase/shaded/protobuf/generated/MasterProcedureProtos$ServerCrashStateData;
       4: areturn

  public org.apache.hbase.thirdparty.com.google.protobuf.Message$Builder mergeFrom(org.apache.hbase.thirdparty.com.google.protobuf.Message);
    Code:
       0: aload_0
       1: aload_1
       2: invokevirtual #146                // Method mergeFrom:(Lorg/apache/hbase/thirdparty/com/google/protobuf/Message;)Lorg/apache/hadoop/hbase/shaded/protobuf/generated/MasterProcedureProtos$ServerCrashStateData$Builder;
       5: areturn

  public org.apache.hbase.thirdparty.com.google.protobuf.Message$Builder clear();
    Code:
       0: aload_0
       1: invokevirtual #143                // Method clear:()Lorg/apache/hadoop/hbase/shaded/protobuf/generated/MasterProcedureProtos$ServerCrashStateData$Builder;
       4: areturn

  public org.apache.hbase.thirdparty.com.google.protobuf.MessageLite$Builder mergeFrom(org.apache.hbase.thirdparty.com.google.protobuf.CodedInputStream, org.apache.hbase.thirdparty.com.google.protobuf.ExtensionRegistryLite) throws java.io.IOException;
    Code:
       0: aload_0
       1: aload_1
       2: aload_2
       3: invokevirtual #145                // Method mergeFrom:(Lorg/apache/hbase/thirdparty/com/google/protobuf/CodedInputStream;Lorg/apache/hbase/thirdparty/com/google/protobuf/ExtensionRegistryLite;)Lorg/apache/hadoop/hbase/shaded/protobuf/generated/MasterProcedureProtos$ServerCrashStateData$Builder;
       6: areturn

  public org.apache.hbase.thirdparty.com.google.protobuf.MessageLite$Builder clone();
    Code:
       0: aload_0
       1: invokevirtual #144                // Method clone:()Lorg/apache/hadoop/hbase/shaded/protobuf/generated/MasterProcedureProtos$ServerCrashStateData$Builder;
       4: areturn

  public org.apache.hbase.thirdparty.com.google.protobuf.MessageLite buildPartial();
    Code:
       0: aload_0
       1: invokevirtual #29                 // Method buildPartial:()Lorg/apache/hadoop/hbase/shaded/protobuf/generated/MasterProcedureProtos$ServerCrashStateData;
       4: areturn

  public org.apache.hbase.thirdparty.com.google.protobuf.MessageLite build();
    Code:
       0: aload_0
       1: invokevirtual #147                // Method build:()Lorg/apache/hadoop/hbase/shaded/protobuf/generated/MasterProcedureProtos$ServerCrashStateData;
       4: areturn

  public org.apache.hbase.thirdparty.com.google.protobuf.MessageLite$Builder clear();
    Code:
       0: aload_0
       1: invokevirtual #143                // Method clear:()Lorg/apache/hadoop/hbase/shaded/protobuf/generated/MasterProcedureProtos$ServerCrashStateData$Builder;
       4: areturn

  public org.apache.hbase.thirdparty.com.google.protobuf.MessageLite getDefaultInstanceForType();
    Code:
       0: aload_0
       1: invokevirtual #148                // Method getDefaultInstanceForType:()Lorg/apache/hadoop/hbase/shaded/protobuf/generated/MasterProcedureProtos$ServerCrashStateData;
       4: areturn

  public org.apache.hbase.thirdparty.com.google.protobuf.Message getDefaultInstanceForType();
    Code:
       0: aload_0
       1: invokevirtual #148                // Method getDefaultInstanceForType:()Lorg/apache/hadoop/hbase/shaded/protobuf/generated/MasterProcedureProtos$ServerCrashStateData;
       4: areturn

  public org.apache.hbase.thirdparty.com.google.protobuf.AbstractMessageLite$Builder mergeFrom(org.apache.hbase.thirdparty.com.google.protobuf.CodedInputStream, org.apache.hbase.thirdparty.com.google.protobuf.ExtensionRegistryLite) throws java.io.IOException;
    Code:
       0: aload_0
       1: aload_1
       2: aload_2
       3: invokevirtual #145                // Method mergeFrom:(Lorg/apache/hbase/thirdparty/com/google/protobuf/CodedInputStream;Lorg/apache/hbase/thirdparty/com/google/protobuf/ExtensionRegistryLite;)Lorg/apache/hadoop/hbase/shaded/protobuf/generated/MasterProcedureProtos$ServerCrashStateData$Builder;
       6: areturn

  public org.apache.hbase.thirdparty.com.google.protobuf.AbstractMessageLite$Builder clone();
    Code:
       0: aload_0
       1: invokevirtual #144                // Method clone:()Lorg/apache/hadoop/hbase/shaded/protobuf/generated/MasterProcedureProtos$ServerCrashStateData$Builder;
       4: areturn

  public java.lang.Object clone() throws java.lang.CloneNotSupportedException;
    Code:
       0: aload_0
       1: invokevirtual #144                // Method clone:()Lorg/apache/hadoop/hbase/shaded/protobuf/generated/MasterProcedureProtos$ServerCrashStateData$Builder;
       4: areturn

  org.apache.hadoop.hbase.shaded.protobuf.generated.MasterProcedureProtos$ServerCrashStateData$Builder(org.apache.hadoop.hbase.shaded.protobuf.generated.MasterProcedureProtos$1);
    Code:
       0: aload_0
       1: invokespecial #2                  // Method "<init>":()V
       4: return

  org.apache.hadoop.hbase.shaded.protobuf.generated.MasterProcedureProtos$ServerCrashStateData$Builder(org.apache.hbase.thirdparty.com.google.protobuf.GeneratedMessageV3$BuilderParent, org.apache.hadoop.hbase.shaded.protobuf.generated.MasterProcedureProtos$1);
    Code:
       0: aload_0
       1: aload_1
       2: invokespecial #1                  // Method "<init>":(Lorg/apache/hbase/thirdparty/com/google/protobuf/GeneratedMessageV3$BuilderParent;)V
       5: return
}
