Compiled from "MasterProtos.java"
public final class org.apache.hadoop.hbase.shaded.protobuf.generated.MasterProtos$SecurityCapabilitiesResponse$Capability extends java.lang.Enum<org.apache.hadoop.hbase.shaded.protobuf.generated.MasterProtos$SecurityCapabilitiesResponse$Capability> implements org.apache.hbase.thirdparty.com.google.protobuf.ProtocolMessageEnum {
  public static final org.apache.hadoop.hbase.shaded.protobuf.generated.MasterProtos$SecurityCapabilitiesResponse$Capability SIMPLE_AUTHENTICATION;

  public static final org.apache.hadoop.hbase.shaded.protobuf.generated.MasterProtos$SecurityCapabilitiesResponse$Capability SECURE_AUTHENTICATION;

  public static final org.apache.hadoop.hbase.shaded.protobuf.generated.MasterProtos$SecurityCapabilitiesResponse$Capability AUTHORIZATION;

  public static final org.apache.hadoop.hbase.shaded.protobuf.generated.MasterProtos$SecurityCapabilitiesResponse$Capability CELL_AUTHORIZATION;

  public static final org.apache.hadoop.hbase.shaded.protobuf.generated.MasterProtos$SecurityCapabilitiesResponse$Capability CELL_VISIBILITY;

  public static final int SIMPLE_AUTHENTICATION_VALUE;

  public static final int SECURE_AUTHENTICATION_VALUE;

  public static final int AUTHORIZATION_VALUE;

  public static final int CELL_AUTHORIZATION_VALUE;

  public static final int CELL_VISIBILITY_VALUE;

  public static org.apache.hadoop.hbase.shaded.protobuf.generated.MasterProtos$SecurityCapabilitiesResponse$Capability[] values();
    Code:
       0: getstatic     #1                  // Field $VALUES:[Lorg/apache/hadoop/hbase/shaded/protobuf/generated/MasterProtos$SecurityCapabilitiesResponse$Capability;
       3: invokevirtual #2                  // Method "[Lorg/apache/hadoop/hbase/shaded/protobuf/generated/MasterProtos$SecurityCapabilitiesResponse$Capability;".clone:()Ljava/lang/Object;
       6: checkcast     #3                  // class "[Lorg/apache/hadoop/hbase/shaded/protobuf/generated/MasterProtos$SecurityCapabilitiesResponse$Capability;"
       9: areturn

  public static org.apache.hadoop.hbase.shaded.protobuf.generated.MasterProtos$SecurityCapabilitiesResponse$Capability valueOf(java.lang.String);
    Code:
       0: ldc           #4                  // class org/apache/hadoop/hbase/shaded/protobuf/generated/MasterProtos$SecurityCapabilitiesResponse$Capability
       2: aload_0
       3: invokestatic  #5                  // Method java/lang/Enum.valueOf:(Ljava/lang/Class;Ljava/lang/String;)Ljava/lang/Enum;
       6: checkcast     #4                  // class org/apache/hadoop/hbase/shaded/protobuf/generated/MasterProtos$SecurityCapabilitiesResponse$Capability
       9: areturn

  public final int getNumber();
    Code:
       0: aload_0
       1: getfield      #6                  // Field value:I
       4: ireturn

  public static org.apache.hadoop.hbase.shaded.protobuf.generated.MasterProtos$SecurityCapabilitiesResponse$Capability valueOf(int);
    Code:
       0: iload_0
       1: invokestatic  #7                  // Method forNumber:(I)Lorg/apache/hadoop/hbase/shaded/protobuf/generated/MasterProtos$SecurityCapabilitiesResponse$Capability;
       4: areturn

  public static org.apache.hadoop.hbase.shaded.protobuf.generated.MasterProtos$SecurityCapabilitiesResponse$Capability forNumber(int);
    Code:
       0: iload_0
       1: tableswitch   { // 0 to 4
                     0: 36
                     1: 40
                     2: 44
                     3: 48
                     4: 52
               default: 56
          }
      36: getstatic     #8                  // Field SIMPLE_AUTHENTICATION:Lorg/apache/hadoop/hbase/shaded/protobuf/generated/MasterProtos$SecurityCapabilitiesResponse$Capability;
      39: areturn
      40: getstatic     #9                  // Field SECURE_AUTHENTICATION:Lorg/apache/hadoop/hbase/shaded/protobuf/generated/MasterProtos$SecurityCapabilitiesResponse$Capability;
      43: areturn
      44: getstatic     #10                 // Field AUTHORIZATION:Lorg/apache/hadoop/hbase/shaded/protobuf/generated/MasterProtos$SecurityCapabilitiesResponse$Capability;
      47: areturn
      48: getstatic     #11                 // Field CELL_AUTHORIZATION:Lorg/apache/hadoop/hbase/shaded/protobuf/generated/MasterProtos$SecurityCapabilitiesResponse$Capability;
      51: areturn
      52: getstatic     #12                 // Field CELL_VISIBILITY:Lorg/apache/hadoop/hbase/shaded/protobuf/generated/MasterProtos$SecurityCapabilitiesResponse$Capability;
      55: areturn
      56: aconst_null
      57: areturn

  public static org.apache.hbase.thirdparty.com.google.protobuf.Internal$EnumLiteMap<org.apache.hadoop.hbase.shaded.protobuf.generated.MasterProtos$SecurityCapabilitiesResponse$Capability> internalGetValueMap();
    Code:
       0: getstatic     #13                 // Field internalValueMap:Lorg/apache/hbase/thirdparty/com/google/protobuf/Internal$EnumLiteMap;
       3: areturn

  public final org.apache.hbase.thirdparty.com.google.protobuf.Descriptors$EnumValueDescriptor getValueDescriptor();
    Code:
       0: invokestatic  #14                 // Method getDescriptor:()Lorg/apache/hbase/thirdparty/com/google/protobuf/Descriptors$EnumDescriptor;
       3: invokevirtual #15                 // Method org/apache/hbase/thirdparty/com/google/protobuf/Descriptors$EnumDescriptor.getValues:()Ljava/util/List;
       6: aload_0
       7: invokevirtual #16                 // Method ordinal:()I
      10: invokeinterface #17,  2           // InterfaceMethod java/util/List.get:(I)Ljava/lang/Object;
      15: checkcast     #18                 // class org/apache/hbase/thirdparty/com/google/protobuf/Descriptors$EnumValueDescriptor
      18: areturn

  public final org.apache.hbase.thirdparty.com.google.protobuf.Descriptors$EnumDescriptor getDescriptorForType();
    Code:
       0: invokestatic  #14                 // Method getDescriptor:()Lorg/apache/hbase/thirdparty/com/google/protobuf/Descriptors$EnumDescriptor;
       3: areturn

  public static final org.apache.hbase.thirdparty.com.google.protobuf.Descriptors$EnumDescriptor getDescriptor();
    Code:
       0: invokestatic  #19                 // Method org/apache/hadoop/hbase/shaded/protobuf/generated/MasterProtos$SecurityCapabilitiesResponse.getDescriptor:()Lorg/apache/hbase/thirdparty/com/google/protobuf/Descriptors$Descriptor;
       3: invokevirtual #20                 // Method org/apache/hbase/thirdparty/com/google/protobuf/Descriptors$Descriptor.getEnumTypes:()Ljava/util/List;
       6: iconst_0
       7: invokeinterface #17,  2           // InterfaceMethod java/util/List.get:(I)Ljava/lang/Object;
      12: checkcast     #21                 // class org/apache/hbase/thirdparty/com/google/protobuf/Descriptors$EnumDescriptor
      15: areturn

  public static org.apache.hadoop.hbase.shaded.protobuf.generated.MasterProtos$SecurityCapabilitiesResponse$Capability valueOf(org.apache.hbase.thirdparty.com.google.protobuf.Descriptors$EnumValueDescriptor);
    Code:
       0: aload_0
       1: invokevirtual #22                 // Method org/apache/hbase/thirdparty/com/google/protobuf/Descriptors$EnumValueDescriptor.getType:()Lorg/apache/hbase/thirdparty/com/google/protobuf/Descriptors$EnumDescriptor;
       4: invokestatic  #14                 // Method getDescriptor:()Lorg/apache/hbase/thirdparty/com/google/protobuf/Descriptors$EnumDescriptor;
       7: if_acmpeq     20
      10: new           #23                 // class java/lang/IllegalArgumentException
      13: dup
      14: ldc           #24                 // String EnumValueDescriptor is not for this type.
      16: invokespecial #25                 // Method java/lang/IllegalArgumentException."<init>":(Ljava/lang/String;)V
      19: athrow
      20: getstatic     #26                 // Field VALUES:[Lorg/apache/hadoop/hbase/shaded/protobuf/generated/MasterProtos$SecurityCapabilitiesResponse$Capability;
      23: aload_0
      24: invokevirtual #27                 // Method org/apache/hbase/thirdparty/com/google/protobuf/Descriptors$EnumValueDescriptor.getIndex:()I
      27: aaload
      28: areturn

  static {};
    Code:
       0: new           #4                  // class org/apache/hadoop/hbase/shaded/protobuf/generated/MasterProtos$SecurityCapabilitiesResponse$Capability
       3: dup
       4: ldc           #29                 // String SIMPLE_AUTHENTICATION
       6: iconst_0
       7: iconst_0
       8: invokespecial #30                 // Method "<init>":(Ljava/lang/String;II)V
      11: putstatic     #8                  // Field SIMPLE_AUTHENTICATION:Lorg/apache/hadoop/hbase/shaded/protobuf/generated/MasterProtos$SecurityCapabilitiesResponse$Capability;
      14: new           #4                  // class org/apache/hadoop/hbase/shaded/protobuf/generated/MasterProtos$SecurityCapabilitiesResponse$Capability
      17: dup
      18: ldc           #31                 // String SECURE_AUTHENTICATION
      20: iconst_1
      21: iconst_1
      22: invokespecial #30                 // Method "<init>":(Ljava/lang/String;II)V
      25: putstatic     #9                  // Field SECURE_AUTHENTICATION:Lorg/apache/hadoop/hbase/shaded/protobuf/generated/MasterProtos$SecurityCapabilitiesResponse$Capability;
      28: new           #4                  // class org/apache/hadoop/hbase/shaded/protobuf/generated/MasterProtos$SecurityCapabilitiesResponse$Capability
      31: dup
      32: ldc           #32                 // String AUTHORIZATION
      34: iconst_2
      35: iconst_2
      36: invokespecial #30                 // Method "<init>":(Ljava/lang/String;II)V
      39: putstatic     #10                 // Field AUTHORIZATION:Lorg/apache/hadoop/hbase/shaded/protobuf/generated/MasterProtos$SecurityCapabilitiesResponse$Capability;
      42: new           #4                  // class org/apache/hadoop/hbase/shaded/protobuf/generated/MasterProtos$SecurityCapabilitiesResponse$Capability
      45: dup
      46: ldc           #33                 // String CELL_AUTHORIZATION
      48: iconst_3
      49: iconst_3
      50: invokespecial #30                 // Method "<init>":(Ljava/lang/String;II)V
      53: putstatic     #11                 // Field CELL_AUTHORIZATION:Lorg/apache/hadoop/hbase/shaded/protobuf/generated/MasterProtos$SecurityCapabilitiesResponse$Capability;
      56: new           #4                  // class org/apache/hadoop/hbase/shaded/protobuf/generated/MasterProtos$SecurityCapabilitiesResponse$Capability
      59: dup
      60: ldc           #34                 // String CELL_VISIBILITY
      62: iconst_4
      63: iconst_4
      64: invokespecial #30                 // Method "<init>":(Ljava/lang/String;II)V
      67: putstatic     #12                 // Field CELL_VISIBILITY:Lorg/apache/hadoop/hbase/shaded/protobuf/generated/MasterProtos$SecurityCapabilitiesResponse$Capability;
      70: iconst_5
      71: anewarray     #4                  // class org/apache/hadoop/hbase/shaded/protobuf/generated/MasterProtos$SecurityCapabilitiesResponse$Capability
      74: dup
      75: iconst_0
      76: getstatic     #8                  // Field SIMPLE_AUTHENTICATION:Lorg/apache/hadoop/hbase/shaded/protobuf/generated/MasterProtos$SecurityCapabilitiesResponse$Capability;
      79: aastore
      80: dup
      81: iconst_1
      82: getstatic     #9                  // Field SECURE_AUTHENTICATION:Lorg/apache/hadoop/hbase/shaded/protobuf/generated/MasterProtos$SecurityCapabilitiesResponse$Capability;
      85: aastore
      86: dup
      87: iconst_2
      88: getstatic     #10                 // Field AUTHORIZATION:Lorg/apache/hadoop/hbase/shaded/protobuf/generated/MasterProtos$SecurityCapabilitiesResponse$Capability;
      91: aastore
      92: dup
      93: iconst_3
      94: getstatic     #11                 // Field CELL_AUTHORIZATION:Lorg/apache/hadoop/hbase/shaded/protobuf/generated/MasterProtos$SecurityCapabilitiesResponse$Capability;
      97: aastore
      98: dup
      99: iconst_4
     100: getstatic     #12                 // Field CELL_VISIBILITY:Lorg/apache/hadoop/hbase/shaded/protobuf/generated/MasterProtos$SecurityCapabilitiesResponse$Capability;
     103: aastore
     104: putstatic     #1                  // Field $VALUES:[Lorg/apache/hadoop/hbase/shaded/protobuf/generated/MasterProtos$SecurityCapabilitiesResponse$Capability;
     107: new           #35                 // class org/apache/hadoop/hbase/shaded/protobuf/generated/MasterProtos$SecurityCapabilitiesResponse$Capability$1
     110: dup
     111: invokespecial #36                 // Method org/apache/hadoop/hbase/shaded/protobuf/generated/MasterProtos$SecurityCapabilitiesResponse$Capability$1."<init>":()V
     114: putstatic     #13                 // Field internalValueMap:Lorg/apache/hbase/thirdparty/com/google/protobuf/Internal$EnumLiteMap;
     117: invokestatic  #37                 // Method values:()[Lorg/apache/hadoop/hbase/shaded/protobuf/generated/MasterProtos$SecurityCapabilitiesResponse$Capability;
     120: putstatic     #26                 // Field VALUES:[Lorg/apache/hadoop/hbase/shaded/protobuf/generated/MasterProtos$SecurityCapabilitiesResponse$Capability;
     123: return
}
