Compiled from "MasterMobCompactionThread.java"
public class org.apache.hadoop.hbase.master.MasterMobCompactionThread {
  static final org.slf4j.Logger LOG;

  public org.apache.hadoop.hbase.master.MasterMobCompactionThread(org.apache.hadoop.hbase.master.HMaster);
    Code:
       0: aload_0
       1: invokespecial #3                  // Method java/lang/Object."<init>":()V
       4: aload_0
       5: aload_1
       6: putfield      #2                  // Field master:Lorg/apache/hadoop/hbase/master/HMaster;
       9: aload_0
      10: aload_1
      11: invokevirtual #4                  // Method org/apache/hadoop/hbase/master/HMaster.getConfiguration:()Lorg/apache/hadoop/conf/Configuration;
      14: putfield      #1                  // Field conf:Lorg/apache/hadoop/conf/Configuration;
      17: invokestatic  #5                  // Method java/lang/Thread.currentThread:()Ljava/lang/Thread;
      20: invokevirtual #6                  // Method java/lang/Thread.getName:()Ljava/lang/String;
      23: astore_2
      24: aload_0
      25: new           #7                  // class java/util/concurrent/ThreadPoolExecutor
      28: dup
      29: iconst_1
      30: iconst_2
      31: ldc2_w        #8                  // long 60l
      34: getstatic     #10                 // Field java/util/concurrent/TimeUnit.SECONDS:Ljava/util/concurrent/TimeUnit;
      37: new           #11                 // class java/util/concurrent/SynchronousQueue
      40: dup
      41: invokespecial #12                 // Method java/util/concurrent/SynchronousQueue."<init>":()V
      44: new           #13                 // class org/apache/hadoop/hbase/master/MasterMobCompactionThread$1
      47: dup
      48: aload_0
      49: aload_2
      50: invokespecial #14                 // Method org/apache/hadoop/hbase/master/MasterMobCompactionThread$1."<init>":(Lorg/apache/hadoop/hbase/master/MasterMobCompactionThread;Ljava/lang/String;)V
      53: invokespecial #15                 // Method java/util/concurrent/ThreadPoolExecutor."<init>":(IIJLjava/util/concurrent/TimeUnit;Ljava/util/concurrent/BlockingQueue;Ljava/util/concurrent/ThreadFactory;)V
      56: putfield      #16                 // Field masterMobPool:Ljava/util/concurrent/ExecutorService;
      59: aload_0
      60: getfield      #16                 // Field masterMobPool:Ljava/util/concurrent/ExecutorService;
      63: checkcast     #7                  // class java/util/concurrent/ThreadPoolExecutor
      66: iconst_1
      67: invokevirtual #17                 // Method java/util/concurrent/ThreadPoolExecutor.allowCoreThreadTimeOut:(Z)V
      70: aload_0
      71: aload_1
      72: invokevirtual #4                  // Method org/apache/hadoop/hbase/master/HMaster.getConfiguration:()Lorg/apache/hadoop/conf/Configuration;
      75: invokestatic  #18                 // Method org/apache/hadoop/hbase/mob/MobUtils.createMobCompactorThreadPool:(Lorg/apache/hadoop/conf/Configuration;)Ljava/util/concurrent/ExecutorService;
      78: putfield      #19                 // Field mobCompactorPool:Ljava/util/concurrent/ExecutorService;
      81: return

  public void requestMobCompaction(org.apache.hadoop.conf.Configuration, org.apache.hadoop.fs.FileSystem, org.apache.hadoop.hbase.TableName, java.util.List<org.apache.hadoop.hbase.client.ColumnFamilyDescriptor>, boolean) throws java.io.IOException;
    Code:
       0: aload_0
       1: getfield      #2                  // Field master:Lorg/apache/hadoop/hbase/master/HMaster;
       4: aload_3
       5: invokevirtual #20                 // Method org/apache/hadoop/hbase/master/HMaster.reportMobCompactionStart:(Lorg/apache/hadoop/hbase/TableName;)V
       8: aload_0
       9: getfield      #16                 // Field masterMobPool:Ljava/util/concurrent/ExecutorService;
      12: new           #21                 // class org/apache/hadoop/hbase/master/MasterMobCompactionThread$CompactionRunner
      15: dup
      16: aload_0
      17: aload_2
      18: aload_3
      19: aload         4
      21: iload         5
      23: aload_0
      24: getfield      #19                 // Field mobCompactorPool:Ljava/util/concurrent/ExecutorService;
      27: invokespecial #22                 // Method org/apache/hadoop/hbase/master/MasterMobCompactionThread$CompactionRunner."<init>":(Lorg/apache/hadoop/hbase/master/MasterMobCompactionThread;Lorg/apache/hadoop/fs/FileSystem;Lorg/apache/hadoop/hbase/TableName;Ljava/util/List;ZLjava/util/concurrent/ExecutorService;)V
      30: invokeinterface #23,  2           // InterfaceMethod java/util/concurrent/ExecutorService.execute:(Ljava/lang/Runnable;)V
      35: goto          68
      38: astore        6
      40: aload_0
      41: getfield      #2                  // Field master:Lorg/apache/hadoop/hbase/master/HMaster;
      44: aload_3
      45: invokevirtual #25                 // Method org/apache/hadoop/hbase/master/HMaster.reportMobCompactionEnd:(Lorg/apache/hadoop/hbase/TableName;)V
      48: goto          65
      51: astore        7
      53: getstatic     #27                 // Field LOG:Lorg/slf4j/Logger;
      56: ldc           #28                 // String Failed to mark end of mob compaction
      58: aload         7
      60: invokeinterface #29,  3           // InterfaceMethod org/slf4j/Logger.error:(Ljava/lang/String;Ljava/lang/Throwable;)V
      65: aload         6
      67: athrow
      68: getstatic     #27                 // Field LOG:Lorg/slf4j/Logger;
      71: invokeinterface #30,  1           // InterfaceMethod org/slf4j/Logger.isDebugEnabled:()Z
      76: ifeq          119
      79: getstatic     #27                 // Field LOG:Lorg/slf4j/Logger;
      82: new           #31                 // class java/lang/StringBuilder
      85: dup
      86: invokespecial #32                 // Method java/lang/StringBuilder."<init>":()V
      89: ldc           #33                 // String The mob compaction is requested for the columns
      91: invokevirtual #34                 // Method java/lang/StringBuilder.append:(Ljava/lang/String;)Ljava/lang/StringBuilder;
      94: aload         4
      96: invokevirtual #35                 // Method java/lang/StringBuilder.append:(Ljava/lang/Object;)Ljava/lang/StringBuilder;
      99: ldc           #36                 // String  of the table
     101: invokevirtual #34                 // Method java/lang/StringBuilder.append:(Ljava/lang/String;)Ljava/lang/StringBuilder;
     104: aload_3
     105: invokevirtual #37                 // Method org/apache/hadoop/hbase/TableName.getNameAsString:()Ljava/lang/String;
     108: invokevirtual #34                 // Method java/lang/StringBuilder.append:(Ljava/lang/String;)Ljava/lang/StringBuilder;
     111: invokevirtual #38                 // Method java/lang/StringBuilder.toString:()Ljava/lang/String;
     114: invokeinterface #39,  2           // InterfaceMethod org/slf4j/Logger.debug:(Ljava/lang/String;)V
     119: return
    Exception table:
       from    to  target type
           8    35    38   Class java/util/concurrent/RejectedExecutionException
          40    48    51   Class java/io/IOException

  public void close();
    Code:
       0: aload_0
       1: invokespecial #44                 // Method interruptIfNecessary:()V
       4: aload_0
       5: invokespecial #45                 // Method join:()V
       8: return

  static org.apache.hadoop.hbase.master.HMaster access$000(org.apache.hadoop.hbase.master.MasterMobCompactionThread);
    Code:
       0: aload_0
       1: getfield      #2                  // Field master:Lorg/apache/hadoop/hbase/master/HMaster;
       4: areturn

  static org.apache.hadoop.conf.Configuration access$100(org.apache.hadoop.hbase.master.MasterMobCompactionThread);
    Code:
       0: aload_0
       1: getfield      #1                  // Field conf:Lorg/apache/hadoop/conf/Configuration;
       4: areturn

  static {};
    Code:
       0: ldc           #54                 // class org/apache/hadoop/hbase/master/MasterMobCompactionThread
       2: invokestatic  #55                 // Method org/slf4j/LoggerFactory.getLogger:(Ljava/lang/Class;)Lorg/slf4j/Logger;
       5: putstatic     #27                 // Field LOG:Lorg/slf4j/Logger;
       8: return
}
