Compiled from "MasterCoprocessorHost.java"
class org.apache.hadoop.hbase.master.MasterCoprocessorHost$29 extends org.apache.hadoop.hbase.master.MasterCoprocessorHost$MasterObserverOperation {
  final org.apache.hadoop.hbase.TableName val$tableName;

  final org.apache.hadoop.hbase.client.TableDescriptor val$oldDescriptor;

  final org.apache.hadoop.hbase.client.TableDescriptor val$currentDescriptor;

  final org.apache.hadoop.hbase.master.MasterCoprocessorHost this$0;

  org.apache.hadoop.hbase.master.MasterCoprocessorHost$29(org.apache.hadoop.hbase.master.MasterCoprocessorHost, org.apache.hadoop.hbase.security.User, org.apache.hadoop.hbase.TableName, org.apache.hadoop.hbase.client.TableDescriptor, org.apache.hadoop.hbase.client.TableDescriptor);
    Code:
       0: aload_0
       1: aload_1
       2: putfield      #1                  // Field this$0:Lorg/apache/hadoop/hbase/master/MasterCoprocessorHost;
       5: aload_0
       6: aload_3
       7: putfield      #2                  // Field val$tableName:Lorg/apache/hadoop/hbase/TableName;
      10: aload_0
      11: aload         4
      13: putfield      #3                  // Field val$oldDescriptor:Lorg/apache/hadoop/hbase/client/TableDescriptor;
      16: aload_0
      17: aload         5
      19: putfield      #4                  // Field val$currentDescriptor:Lorg/apache/hadoop/hbase/client/TableDescriptor;
      22: aload_0
      23: aload_1
      24: aload_2
      25: invokespecial #5                  // Method org/apache/hadoop/hbase/master/MasterCoprocessorHost$MasterObserverOperation."<init>":(Lorg/apache/hadoop/hbase/master/MasterCoprocessorHost;Lorg/apache/hadoop/hbase/security/User;)V
      28: return

  public void call(org.apache.hadoop.hbase.coprocessor.MasterObserver) throws java.io.IOException;
    Code:
       0: aload_1
       1: aload_0
       2: aload_0
       3: getfield      #2                  // Field val$tableName:Lorg/apache/hadoop/hbase/TableName;
       6: aload_0
       7: getfield      #3                  // Field val$oldDescriptor:Lorg/apache/hadoop/hbase/client/TableDescriptor;
      10: aload_0
      11: getfield      #4                  // Field val$currentDescriptor:Lorg/apache/hadoop/hbase/client/TableDescriptor;
      14: invokeinterface #6,  5            // InterfaceMethod org/apache/hadoop/hbase/coprocessor/MasterObserver.postCompletedModifyTableAction:(Lorg/apache/hadoop/hbase/coprocessor/ObserverContext;Lorg/apache/hadoop/hbase/TableName;Lorg/apache/hadoop/hbase/client/TableDescriptor;Lorg/apache/hadoop/hbase/client/TableDescriptor;)V
      19: return

  public void call(java.lang.Object) throws java.io.IOException;
    Code:
       0: aload_0
       1: aload_1
       2: checkcast     #7                  // class org/apache/hadoop/hbase/coprocessor/MasterObserver
       5: invokevirtual #8                  // Method call:(Lorg/apache/hadoop/hbase/coprocessor/MasterObserver;)V
       8: return
}
