Compiled from "MasterDumpServlet.java"
public class org.apache.hadoop.hbase.master.MasterDumpServlet extends org.apache.hadoop.hbase.monitoring.StateDumpServlet {
  static final boolean $assertionsDisabled;

  public org.apache.hadoop.hbase.master.MasterDumpServlet();
    Code:
       0: aload_0
       1: invokespecial #1                  // Method org/apache/hadoop/hbase/monitoring/StateDumpServlet."<init>":()V
       4: return

  public void doGet(javax.servlet.http.HttpServletRequest, javax.servlet.http.HttpServletResponse) throws java.io.IOException;
    Code:
       0: aload_0
       1: invokevirtual #2                  // Method getServletContext:()Ljavax/servlet/ServletContext;
       4: ldc           #4                  // String master
       6: invokeinterface #5,  2            // InterfaceMethod javax/servlet/ServletContext.getAttribute:(Ljava/lang/String;)Ljava/lang/Object;
      11: checkcast     #3                  // class org/apache/hadoop/hbase/master/HMaster
      14: astore_3
      15: getstatic     #6                  // Field $assertionsDisabled:Z
      18: ifne          35
      21: aload_3
      22: ifnonnull     35
      25: new           #7                  // class java/lang/AssertionError
      28: dup
      29: ldc           #8                  // String No Master in context!
      31: invokespecial #9                  // Method java/lang/AssertionError."<init>":(Ljava/lang/Object;)V
      34: athrow
      35: aload_2
      36: ldc           #10                 // String text/plain
      38: invokeinterface #11,  2           // InterfaceMethod javax/servlet/http/HttpServletResponse.setContentType:(Ljava/lang/String;)V
      43: aload_2
      44: invokeinterface #12,  1           // InterfaceMethod javax/servlet/http/HttpServletResponse.getOutputStream:()Ljavax/servlet/ServletOutputStream;
      49: astore        4
      51: new           #13                 // class java/io/PrintWriter
      54: dup
      55: aload         4
      57: invokespecial #14                 // Method java/io/PrintWriter."<init>":(Ljava/io/OutputStream;)V
      60: astore        5
      62: aconst_null
      63: astore        6
      65: aload         5
      67: new           #15                 // class java/lang/StringBuilder
      70: dup
      71: invokespecial #16                 // Method java/lang/StringBuilder."<init>":()V
      74: ldc           #17                 // String Master status for
      76: invokevirtual #18                 // Method java/lang/StringBuilder.append:(Ljava/lang/String;)Ljava/lang/StringBuilder;
      79: aload_3
      80: invokevirtual #19                 // Method org/apache/hadoop/hbase/master/HMaster.getServerName:()Lorg/apache/hadoop/hbase/ServerName;
      83: invokevirtual #20                 // Method java/lang/StringBuilder.append:(Ljava/lang/Object;)Ljava/lang/StringBuilder;
      86: ldc           #21                 // String  as of
      88: invokevirtual #18                 // Method java/lang/StringBuilder.append:(Ljava/lang/String;)Ljava/lang/StringBuilder;
      91: new           #22                 // class java/util/Date
      94: dup
      95: invokespecial #23                 // Method java/util/Date."<init>":()V
      98: invokevirtual #20                 // Method java/lang/StringBuilder.append:(Ljava/lang/Object;)Ljava/lang/StringBuilder;
     101: invokevirtual #24                 // Method java/lang/StringBuilder.toString:()Ljava/lang/String;
     104: invokevirtual #25                 // Method java/io/PrintWriter.println:(Ljava/lang/String;)V
     107: aload         5
     109: ldc           #26                 // String \n\nVersion Info:
     111: invokevirtual #25                 // Method java/io/PrintWriter.println:(Ljava/lang/String;)V
     114: aload         5
     116: ldc           #28                 // String ===========================================================
     118: invokevirtual #25                 // Method java/io/PrintWriter.println:(Ljava/lang/String;)V
     121: aload_0
     122: aload         5
     124: invokevirtual #29                 // Method dumpVersionInfo:(Ljava/io/PrintWriter;)V
     127: aload         5
     129: ldc           #30                 // String \n\nTasks:
     131: invokevirtual #25                 // Method java/io/PrintWriter.println:(Ljava/lang/String;)V
     134: aload         5
     136: ldc           #28                 // String ===========================================================
     138: invokevirtual #25                 // Method java/io/PrintWriter.println:(Ljava/lang/String;)V
     141: invokestatic  #31                 // Method org/apache/hadoop/hbase/monitoring/TaskMonitor.get:()Lorg/apache/hadoop/hbase/monitoring/TaskMonitor;
     144: aload         5
     146: invokevirtual #32                 // Method org/apache/hadoop/hbase/monitoring/TaskMonitor.dumpAsText:(Ljava/io/PrintWriter;)V
     149: aload         5
     151: ldc           #33                 // String \n\nServers:
     153: invokevirtual #25                 // Method java/io/PrintWriter.println:(Ljava/lang/String;)V
     156: aload         5
     158: ldc           #28                 // String ===========================================================
     160: invokevirtual #25                 // Method java/io/PrintWriter.println:(Ljava/lang/String;)V
     163: aload_0
     164: aload_3
     165: aload         5
     167: invokespecial #34                 // Method dumpServers:(Lorg/apache/hadoop/hbase/master/HMaster;Ljava/io/PrintWriter;)V
     170: aload         5
     172: ldc           #35                 // String \n\nRegions-in-transition:
     174: invokevirtual #25                 // Method java/io/PrintWriter.println:(Ljava/lang/String;)V
     177: aload         5
     179: ldc           #28                 // String ===========================================================
     181: invokevirtual #25                 // Method java/io/PrintWriter.println:(Ljava/lang/String;)V
     184: aload_0
     185: aload_3
     186: aload         5
     188: invokespecial #36                 // Method dumpRIT:(Lorg/apache/hadoop/hbase/master/HMaster;Ljava/io/PrintWriter;)V
     191: aload         5
     193: ldc           #37                 // String \n\nExecutors:
     195: invokevirtual #25                 // Method java/io/PrintWriter.println:(Ljava/lang/String;)V
     198: aload         5
     200: ldc           #28                 // String ===========================================================
     202: invokevirtual #25                 // Method java/io/PrintWriter.println:(Ljava/lang/String;)V
     205: aload_0
     206: aload_3
     207: invokevirtual #38                 // Method org/apache/hadoop/hbase/master/HMaster.getExecutorService:()Lorg/apache/hadoop/hbase/executor/ExecutorService;
     210: aload         5
     212: invokevirtual #39                 // Method dumpExecutors:(Lorg/apache/hadoop/hbase/executor/ExecutorService;Ljava/io/PrintWriter;)V
     215: aload         5
     217: ldc           #40                 // String \n\nStacks:
     219: invokevirtual #25                 // Method java/io/PrintWriter.println:(Ljava/lang/String;)V
     222: aload         5
     224: ldc           #28                 // String ===========================================================
     226: invokevirtual #25                 // Method java/io/PrintWriter.println:(Ljava/lang/String;)V
     229: aload         5
     231: invokevirtual #41                 // Method java/io/PrintWriter.flush:()V
     234: new           #42                 // class java/io/PrintStream
     237: dup
     238: aload_2
     239: invokeinterface #12,  1           // InterfaceMethod javax/servlet/http/HttpServletResponse.getOutputStream:()Ljavax/servlet/ServletOutputStream;
     244: iconst_0
     245: ldc           #43                 // String UTF-8
     247: invokespecial #44                 // Method java/io/PrintStream."<init>":(Ljava/io/OutputStream;ZLjava/lang/String;)V
     250: astore        7
     252: aload         7
     254: ldc           #45                 // String
     256: invokestatic  #46                 // Method org/apache/hadoop/hbase/util/Threads.printThreadInfo:(Ljava/io/PrintStream;Ljava/lang/String;)V
     259: aload         7
     261: invokevirtual #47                 // Method java/io/PrintStream.flush:()V
     264: aload         5
     266: ldc           #48                 // String \n\nMaster configuration:
     268: invokevirtual #25                 // Method java/io/PrintWriter.println:(Ljava/lang/String;)V
     271: aload         5
     273: ldc           #28                 // String ===========================================================
     275: invokevirtual #25                 // Method java/io/PrintWriter.println:(Ljava/lang/String;)V
     278: aload_3
     279: invokevirtual #49                 // Method org/apache/hadoop/hbase/master/HMaster.getConfiguration:()Lorg/apache/hadoop/conf/Configuration;
     282: astore        8
     284: aload         5
     286: invokevirtual #41                 // Method java/io/PrintWriter.flush:()V
     289: aload         8
     291: aload         4
     293: invokevirtual #50                 // Method org/apache/hadoop/conf/Configuration.writeXml:(Ljava/io/OutputStream;)V
     296: aload         4
     298: invokevirtual #51                 // Method java/io/OutputStream.flush:()V
     301: aload         5
     303: ldc           #52                 // String \n\nRecent regionserver aborts:
     305: invokevirtual #25                 // Method java/io/PrintWriter.println:(Ljava/lang/String;)V
     308: aload         5
     310: ldc           #28                 // String ===========================================================
     312: invokevirtual #25                 // Method java/io/PrintWriter.println:(Ljava/lang/String;)V
     315: aload_3
     316: invokevirtual #53                 // Method org/apache/hadoop/hbase/master/HMaster.getRegionServerFatalLogBuffer:()Lorg/apache/hadoop/hbase/monitoring/MemoryBoundedLogMessageBuffer;
     319: aload         5
     321: invokevirtual #54                 // Method org/apache/hadoop/hbase/monitoring/MemoryBoundedLogMessageBuffer.dumpTo:(Ljava/io/PrintWriter;)V
     324: aload         5
     326: ldc           #55                 // String \n\nLogs
     328: invokevirtual #25                 // Method java/io/PrintWriter.println:(Ljava/lang/String;)V
     331: aload         5
     333: ldc           #28                 // String ===========================================================
     335: invokevirtual #25                 // Method java/io/PrintWriter.println:(Ljava/lang/String;)V
     338: aload_0
     339: aload_1
     340: invokevirtual #56                 // Method getTailKbParam:(Ljavax/servlet/http/HttpServletRequest;)J
     343: lstore        9
     345: aload         5
     347: lload         9
     349: invokestatic  #57                 // Method org/apache/hadoop/hbase/monitoring/LogMonitoring.dumpTailOfLogs:(Ljava/io/PrintWriter;J)V
     352: aload         5
     354: ldc           #58                 // String \n\nRS Queue:
     356: invokevirtual #25                 // Method java/io/PrintWriter.println:(Ljava/lang/String;)V
     359: aload         5
     361: ldc           #28                 // String ===========================================================
     363: invokevirtual #25                 // Method java/io/PrintWriter.println:(Ljava/lang/String;)V
     366: aload_0
     367: aload         8
     369: invokevirtual #59                 // Method isShowQueueDump:(Lorg/apache/hadoop/conf/Configuration;)Z
     372: ifeq          381
     375: aload_3
     376: aload         5
     378: invokestatic  #60                 // Method org/apache/hadoop/hbase/regionserver/RSDumpServlet.dumpQueue:(Lorg/apache/hadoop/hbase/regionserver/HRegionServer;Ljava/io/PrintWriter;)V
     381: aload         5
     383: invokevirtual #41                 // Method java/io/PrintWriter.flush:()V
     386: aload         5
     388: ifnull        473
     391: aload         6
     393: ifnull        416
     396: aload         5
     398: invokevirtual #61                 // Method java/io/PrintWriter.close:()V
     401: goto          473
     404: astore        7
     406: aload         6
     408: aload         7
     410: invokevirtual #63                 // Method java/lang/Throwable.addSuppressed:(Ljava/lang/Throwable;)V
     413: goto          473
     416: aload         5
     418: invokevirtual #61                 // Method java/io/PrintWriter.close:()V
     421: goto          473
     424: astore        7
     426: aload         7
     428: astore        6
     430: aload         7
     432: athrow
     433: astore        11
     435: aload         5
     437: ifnull        470
     440: aload         6
     442: ifnull        465
     445: aload         5
     447: invokevirtual #61                 // Method java/io/PrintWriter.close:()V
     450: goto          470
     453: astore        12
     455: aload         6
     457: aload         12
     459: invokevirtual #63                 // Method java/lang/Throwable.addSuppressed:(Ljava/lang/Throwable;)V
     462: goto          470
     465: aload         5
     467: invokevirtual #61                 // Method java/io/PrintWriter.close:()V
     470: aload         11
     472: athrow
     473: return
    Exception table:
       from    to  target type
         396   401   404   Class java/lang/Throwable
          65   386   424   Class java/lang/Throwable
          65   386   433   any
         445   450   453   Class java/lang/Throwable
         424   435   433   any

  static {};
    Code:
       0: ldc           #27                 // class org/apache/hadoop/hbase/master/MasterDumpServlet
       2: invokevirtual #84                 // Method java/lang/Class.desiredAssertionStatus:()Z
       5: ifne          12
       8: iconst_1
       9: goto          13
      12: iconst_0
      13: putstatic     #6                  // Field $assertionsDisabled:Z
      16: return
}
