Compiled from "MasterProtos.java"
public final class org.apache.hadoop.hbase.shaded.protobuf.generated.MasterProtos$SetQuotaRequest$Builder extends org.apache.hbase.thirdparty.com.google.protobuf.GeneratedMessageV3$Builder<org.apache.hadoop.hbase.shaded.protobuf.generated.MasterProtos$SetQuotaRequest$Builder> implements org.apache.hadoop.hbase.shaded.protobuf.generated.MasterProtos$SetQuotaRequestOrBuilder {
  public static final org.apache.hbase.thirdparty.com.google.protobuf.Descriptors$Descriptor getDescriptor();
    Code:
       0: invokestatic  #3                  // Method org/apache/hadoop/hbase/shaded/protobuf/generated/MasterProtos.access$117400:()Lorg/apache/hbase/thirdparty/com/google/protobuf/Descriptors$Descriptor;
       3: areturn

  protected org.apache.hbase.thirdparty.com.google.protobuf.GeneratedMessageV3$FieldAccessorTable internalGetFieldAccessorTable();
    Code:
       0: invokestatic  #4                  // Method org/apache/hadoop/hbase/shaded/protobuf/generated/MasterProtos.access$117500:()Lorg/apache/hbase/thirdparty/com/google/protobuf/GeneratedMessageV3$FieldAccessorTable;
       3: ldc           #5                  // class org/apache/hadoop/hbase/shaded/protobuf/generated/MasterProtos$SetQuotaRequest
       5: ldc           #6                  // class org/apache/hadoop/hbase/shaded/protobuf/generated/MasterProtos$SetQuotaRequest$Builder
       7: invokevirtual #7                  // Method org/apache/hbase/thirdparty/com/google/protobuf/GeneratedMessageV3$FieldAccessorTable.ensureFieldAccessorsInitialized:(Ljava/lang/Class;Ljava/lang/Class;)Lorg/apache/hbase/thirdparty/com/google/protobuf/GeneratedMessageV3$FieldAccessorTable;
      10: areturn

  public org.apache.hadoop.hbase.shaded.protobuf.generated.MasterProtos$SetQuotaRequest$Builder clear();
    Code:
       0: aload_0
       1: invokespecial #23                 // Method org/apache/hbase/thirdparty/com/google/protobuf/GeneratedMessageV3$Builder.clear:()Lorg/apache/hbase/thirdparty/com/google/protobuf/GeneratedMessageV3$Builder;
       4: pop
       5: aload_0
       6: ldc           #9                  // String
       8: putfield      #10                 // Field userName_:Ljava/lang/Object;
      11: aload_0
      12: aload_0
      13: getfield      #24                 // Field bitField0_:I
      16: bipush        -2
      18: iand
      19: putfield      #24                 // Field bitField0_:I
      22: aload_0
      23: ldc           #9                  // String
      25: putfield      #11                 // Field userGroup_:Ljava/lang/Object;
      28: aload_0
      29: aload_0
      30: getfield      #24                 // Field bitField0_:I
      33: bipush        -3
      35: iand
      36: putfield      #24                 // Field bitField0_:I
      39: aload_0
      40: ldc           #9                  // String
      42: putfield      #12                 // Field namespace_:Ljava/lang/Object;
      45: aload_0
      46: aload_0
      47: getfield      #24                 // Field bitField0_:I
      50: bipush        -5
      52: iand
      53: putfield      #24                 // Field bitField0_:I
      56: aload_0
      57: getfield      #25                 // Field tableNameBuilder_:Lorg/apache/hbase/thirdparty/com/google/protobuf/SingleFieldBuilderV3;
      60: ifnonnull     71
      63: aload_0
      64: aconst_null
      65: putfield      #13                 // Field tableName_:Lorg/apache/hadoop/hbase/shaded/protobuf/generated/HBaseProtos$TableName;
      68: goto          79
      71: aload_0
      72: getfield      #25                 // Field tableNameBuilder_:Lorg/apache/hbase/thirdparty/com/google/protobuf/SingleFieldBuilderV3;
      75: invokevirtual #26                 // Method org/apache/hbase/thirdparty/com/google/protobuf/SingleFieldBuilderV3.clear:()Lorg/apache/hbase/thirdparty/com/google/protobuf/SingleFieldBuilderV3;
      78: pop
      79: aload_0
      80: aload_0
      81: getfield      #24                 // Field bitField0_:I
      84: bipush        -9
      86: iand
      87: putfield      #24                 // Field bitField0_:I
      90: aload_0
      91: iconst_0
      92: putfield      #27                 // Field removeAll_:Z
      95: aload_0
      96: aload_0
      97: getfield      #24                 // Field bitField0_:I
     100: bipush        -17
     102: iand
     103: putfield      #24                 // Field bitField0_:I
     106: aload_0
     107: iconst_0
     108: putfield      #28                 // Field bypassGlobals_:Z
     111: aload_0
     112: aload_0
     113: getfield      #24                 // Field bitField0_:I
     116: bipush        -33
     118: iand
     119: putfield      #24                 // Field bitField0_:I
     122: aload_0
     123: getfield      #29                 // Field throttleBuilder_:Lorg/apache/hbase/thirdparty/com/google/protobuf/SingleFieldBuilderV3;
     126: ifnonnull     137
     129: aload_0
     130: aconst_null
     131: putfield      #14                 // Field throttle_:Lorg/apache/hadoop/hbase/shaded/protobuf/generated/QuotaProtos$ThrottleRequest;
     134: goto          145
     137: aload_0
     138: getfield      #29                 // Field throttleBuilder_:Lorg/apache/hbase/thirdparty/com/google/protobuf/SingleFieldBuilderV3;
     141: invokevirtual #26                 // Method org/apache/hbase/thirdparty/com/google/protobuf/SingleFieldBuilderV3.clear:()Lorg/apache/hbase/thirdparty/com/google/protobuf/SingleFieldBuilderV3;
     144: pop
     145: aload_0
     146: aload_0
     147: getfield      #24                 // Field bitField0_:I
     150: bipush        -65
     152: iand
     153: putfield      #24                 // Field bitField0_:I
     156: aload_0
     157: getfield      #30                 // Field spaceLimitBuilder_:Lorg/apache/hbase/thirdparty/com/google/protobuf/SingleFieldBuilderV3;
     160: ifnonnull     171
     163: aload_0
     164: aconst_null
     165: putfield      #15                 // Field spaceLimit_:Lorg/apache/hadoop/hbase/shaded/protobuf/generated/QuotaProtos$SpaceLimitRequest;
     168: goto          179
     171: aload_0
     172: getfield      #30                 // Field spaceLimitBuilder_:Lorg/apache/hbase/thirdparty/com/google/protobuf/SingleFieldBuilderV3;
     175: invokevirtual #26                 // Method org/apache/hbase/thirdparty/com/google/protobuf/SingleFieldBuilderV3.clear:()Lorg/apache/hbase/thirdparty/com/google/protobuf/SingleFieldBuilderV3;
     178: pop
     179: aload_0
     180: aload_0
     181: getfield      #24                 // Field bitField0_:I
     184: sipush        -129
     187: iand
     188: putfield      #24                 // Field bitField0_:I
     191: aload_0
     192: ldc           #9                  // String
     194: putfield      #16                 // Field regionServer_:Ljava/lang/Object;
     197: aload_0
     198: aload_0
     199: getfield      #24                 // Field bitField0_:I
     202: sipush        -257
     205: iand
     206: putfield      #24                 // Field bitField0_:I
     209: aload_0
     210: areturn

  public org.apache.hbase.thirdparty.com.google.protobuf.Descriptors$Descriptor getDescriptorForType();
    Code:
       0: invokestatic  #3                  // Method org/apache/hadoop/hbase/shaded/protobuf/generated/MasterProtos.access$117400:()Lorg/apache/hbase/thirdparty/com/google/protobuf/Descriptors$Descriptor;
       3: areturn

  public org.apache.hadoop.hbase.shaded.protobuf.generated.MasterProtos$SetQuotaRequest getDefaultInstanceForType();
    Code:
       0: invokestatic  #31                 // Method org/apache/hadoop/hbase/shaded/protobuf/generated/MasterProtos$SetQuotaRequest.getDefaultInstance:()Lorg/apache/hadoop/hbase/shaded/protobuf/generated/MasterProtos$SetQuotaRequest;
       3: areturn

  public org.apache.hadoop.hbase.shaded.protobuf.generated.MasterProtos$SetQuotaRequest build();
    Code:
       0: aload_0
       1: invokevirtual #32                 // Method buildPartial:()Lorg/apache/hadoop/hbase/shaded/protobuf/generated/MasterProtos$SetQuotaRequest;
       4: astore_1
       5: aload_1
       6: invokevirtual #33                 // Method org/apache/hadoop/hbase/shaded/protobuf/generated/MasterProtos$SetQuotaRequest.isInitialized:()Z
       9: ifne          17
      12: aload_1
      13: invokestatic  #34                 // Method newUninitializedMessageException:(Lorg/apache/hbase/thirdparty/com/google/protobuf/Message;)Lorg/apache/hbase/thirdparty/com/google/protobuf/UninitializedMessageException;
      16: athrow
      17: aload_1
      18: areturn

  public org.apache.hadoop.hbase.shaded.protobuf.generated.MasterProtos$SetQuotaRequest buildPartial();
    Code:
       0: new           #5                  // class org/apache/hadoop/hbase/shaded/protobuf/generated/MasterProtos$SetQuotaRequest
       3: dup
       4: aload_0
       5: aconst_null
       6: invokespecial #35                 // Method org/apache/hadoop/hbase/shaded/protobuf/generated/MasterProtos$SetQuotaRequest."<init>":(Lorg/apache/hbase/thirdparty/com/google/protobuf/GeneratedMessageV3$Builder;Lorg/apache/hadoop/hbase/shaded/protobuf/generated/MasterProtos$1;)V
       9: astore_1
      10: aload_0
      11: getfield      #24                 // Field bitField0_:I
      14: istore_2
      15: iconst_0
      16: istore_3
      17: iload_2
      18: iconst_1
      19: iand
      20: iconst_1
      21: if_icmpne     28
      24: iload_3
      25: iconst_1
      26: ior
      27: istore_3
      28: aload_1
      29: aload_0
      30: getfield      #10                 // Field userName_:Ljava/lang/Object;
      33: invokestatic  #36                 // Method org/apache/hadoop/hbase/shaded/protobuf/generated/MasterProtos$SetQuotaRequest.access$118002:(Lorg/apache/hadoop/hbase/shaded/protobuf/generated/MasterProtos$SetQuotaRequest;Ljava/lang/Object;)Ljava/lang/Object;
      36: pop
      37: iload_2
      38: iconst_2
      39: iand
      40: iconst_2
      41: if_icmpne     48
      44: iload_3
      45: iconst_2
      46: ior
      47: istore_3
      48: aload_1
      49: aload_0
      50: getfield      #11                 // Field userGroup_:Ljava/lang/Object;
      53: invokestatic  #37                 // Method org/apache/hadoop/hbase/shaded/protobuf/generated/MasterProtos$SetQuotaRequest.access$118102:(Lorg/apache/hadoop/hbase/shaded/protobuf/generated/MasterProtos$SetQuotaRequest;Ljava/lang/Object;)Ljava/lang/Object;
      56: pop
      57: iload_2
      58: iconst_4
      59: iand
      60: iconst_4
      61: if_icmpne     68
      64: iload_3
      65: iconst_4
      66: ior
      67: istore_3
      68: aload_1
      69: aload_0
      70: getfield      #12                 // Field namespace_:Ljava/lang/Object;
      73: invokestatic  #38                 // Method org/apache/hadoop/hbase/shaded/protobuf/generated/MasterProtos$SetQuotaRequest.access$118202:(Lorg/apache/hadoop/hbase/shaded/protobuf/generated/MasterProtos$SetQuotaRequest;Ljava/lang/Object;)Ljava/lang/Object;
      76: pop
      77: iload_2
      78: bipush        8
      80: iand
      81: bipush        8
      83: if_icmpne     91
      86: iload_3
      87: bipush        8
      89: ior
      90: istore_3
      91: aload_0
      92: getfield      #25                 // Field tableNameBuilder_:Lorg/apache/hbase/thirdparty/com/google/protobuf/SingleFieldBuilderV3;
      95: ifnonnull     110
      98: aload_1
      99: aload_0
     100: getfield      #13                 // Field tableName_:Lorg/apache/hadoop/hbase/shaded/protobuf/generated/HBaseProtos$TableName;
     103: invokestatic  #39                 // Method org/apache/hadoop/hbase/shaded/protobuf/generated/MasterProtos$SetQuotaRequest.access$118302:(Lorg/apache/hadoop/hbase/shaded/protobuf/generated/MasterProtos$SetQuotaRequest;Lorg/apache/hadoop/hbase/shaded/protobuf/generated/HBaseProtos$TableName;)Lorg/apache/hadoop/hbase/shaded/protobuf/generated/HBaseProtos$TableName;
     106: pop
     107: goto          125
     110: aload_1
     111: aload_0
     112: getfield      #25                 // Field tableNameBuilder_:Lorg/apache/hbase/thirdparty/com/google/protobuf/SingleFieldBuilderV3;
     115: invokevirtual #40                 // Method org/apache/hbase/thirdparty/com/google/protobuf/SingleFieldBuilderV3.build:()Lorg/apache/hbase/thirdparty/com/google/protobuf/AbstractMessage;
     118: checkcast     #41                 // class org/apache/hadoop/hbase/shaded/protobuf/generated/HBaseProtos$TableName
     121: invokestatic  #39                 // Method org/apache/hadoop/hbase/shaded/protobuf/generated/MasterProtos$SetQuotaRequest.access$118302:(Lorg/apache/hadoop/hbase/shaded/protobuf/generated/MasterProtos$SetQuotaRequest;Lorg/apache/hadoop/hbase/shaded/protobuf/generated/HBaseProtos$TableName;)Lorg/apache/hadoop/hbase/shaded/protobuf/generated/HBaseProtos$TableName;
     124: pop
     125: iload_2
     126: bipush        16
     128: iand
     129: bipush        16
     131: if_icmpne     139
     134: iload_3
     135: bipush        16
     137: ior
     138: istore_3
     139: aload_1
     140: aload_0
     141: getfield      #27                 // Field removeAll_:Z
     144: invokestatic  #42                 // Method org/apache/hadoop/hbase/shaded/protobuf/generated/MasterProtos$SetQuotaRequest.access$118402:(Lorg/apache/hadoop/hbase/shaded/protobuf/generated/MasterProtos$SetQuotaRequest;Z)Z
     147: pop
     148: iload_2
     149: bipush        32
     151: iand
     152: bipush        32
     154: if_icmpne     162
     157: iload_3
     158: bipush        32
     160: ior
     161: istore_3
     162: aload_1
     163: aload_0
     164: getfield      #28                 // Field bypassGlobals_:Z
     167: invokestatic  #43                 // Method org/apache/hadoop/hbase/shaded/protobuf/generated/MasterProtos$SetQuotaRequest.access$118502:(Lorg/apache/hadoop/hbase/shaded/protobuf/generated/MasterProtos$SetQuotaRequest;Z)Z
     170: pop
     171: iload_2
     172: bipush        64
     174: iand
     175: bipush        64
     177: if_icmpne     185
     180: iload_3
     181: bipush        64
     183: ior
     184: istore_3
     185: aload_0
     186: getfield      #29                 // Field throttleBuilder_:Lorg/apache/hbase/thirdparty/com/google/protobuf/SingleFieldBuilderV3;
     189: ifnonnull     204
     192: aload_1
     193: aload_0
     194: getfield      #14                 // Field throttle_:Lorg/apache/hadoop/hbase/shaded/protobuf/generated/QuotaProtos$ThrottleRequest;
     197: invokestatic  #44                 // Method org/apache/hadoop/hbase/shaded/protobuf/generated/MasterProtos$SetQuotaRequest.access$118602:(Lorg/apache/hadoop/hbase/shaded/protobuf/generated/MasterProtos$SetQuotaRequest;Lorg/apache/hadoop/hbase/shaded/protobuf/generated/QuotaProtos$ThrottleRequest;)Lorg/apache/hadoop/hbase/shaded/protobuf/generated/QuotaProtos$ThrottleRequest;
     200: pop
     201: goto          219
     204: aload_1
     205: aload_0
     206: getfield      #29                 // Field throttleBuilder_:Lorg/apache/hbase/thirdparty/com/google/protobuf/SingleFieldBuilderV3;
     209: invokevirtual #40                 // Method org/apache/hbase/thirdparty/com/google/protobuf/SingleFieldBuilderV3.build:()Lorg/apache/hbase/thirdparty/com/google/protobuf/AbstractMessage;
     212: checkcast     #45                 // class org/apache/hadoop/hbase/shaded/protobuf/generated/QuotaProtos$ThrottleRequest
     215: invokestatic  #44                 // Method org/apache/hadoop/hbase/shaded/protobuf/generated/MasterProtos$SetQuotaRequest.access$118602:(Lorg/apache/hadoop/hbase/shaded/protobuf/generated/MasterProtos$SetQuotaRequest;Lorg/apache/hadoop/hbase/shaded/protobuf/generated/QuotaProtos$ThrottleRequest;)Lorg/apache/hadoop/hbase/shaded/protobuf/generated/QuotaProtos$ThrottleRequest;
     218: pop
     219: iload_2
     220: sipush        128
     223: iand
     224: sipush        128
     227: if_icmpne     236
     230: iload_3
     231: sipush        128
     234: ior
     235: istore_3
     236: aload_0
     237: getfield      #30                 // Field spaceLimitBuilder_:Lorg/apache/hbase/thirdparty/com/google/protobuf/SingleFieldBuilderV3;
     240: ifnonnull     255
     243: aload_1
     244: aload_0
     245: getfield      #15                 // Field spaceLimit_:Lorg/apache/hadoop/hbase/shaded/protobuf/generated/QuotaProtos$SpaceLimitRequest;
     248: invokestatic  #46                 // Method org/apache/hadoop/hbase/shaded/protobuf/generated/MasterProtos$SetQuotaRequest.access$118702:(Lorg/apache/hadoop/hbase/shaded/protobuf/generated/MasterProtos$SetQuotaRequest;Lorg/apache/hadoop/hbase/shaded/protobuf/generated/QuotaProtos$SpaceLimitRequest;)Lorg/apache/hadoop/hbase/shaded/protobuf/generated/QuotaProtos$SpaceLimitRequest;
     251: pop
     252: goto          270
     255: aload_1
     256: aload_0
     257: getfield      #30                 // Field spaceLimitBuilder_:Lorg/apache/hbase/thirdparty/com/google/protobuf/SingleFieldBuilderV3;
     260: invokevirtual #40                 // Method org/apache/hbase/thirdparty/com/google/protobuf/SingleFieldBuilderV3.build:()Lorg/apache/hbase/thirdparty/com/google/protobuf/AbstractMessage;
     263: checkcast     #47                 // class org/apache/hadoop/hbase/shaded/protobuf/generated/QuotaProtos$SpaceLimitRequest
     266: invokestatic  #46                 // Method org/apache/hadoop/hbase/shaded/protobuf/generated/MasterProtos$SetQuotaRequest.access$118702:(Lorg/apache/hadoop/hbase/shaded/protobuf/generated/MasterProtos$SetQuotaRequest;Lorg/apache/hadoop/hbase/shaded/protobuf/generated/QuotaProtos$SpaceLimitRequest;)Lorg/apache/hadoop/hbase/shaded/protobuf/generated/QuotaProtos$SpaceLimitRequest;
     269: pop
     270: iload_2
     271: sipush        256
     274: iand
     275: sipush        256
     278: if_icmpne     287
     281: iload_3
     282: sipush        256
     285: ior
     286: istore_3
     287: aload_1
     288: aload_0
     289: getfield      #16                 // Field regionServer_:Ljava/lang/Object;
     292: invokestatic  #48                 // Method org/apache/hadoop/hbase/shaded/protobuf/generated/MasterProtos$SetQuotaRequest.access$118802:(Lorg/apache/hadoop/hbase/shaded/protobuf/generated/MasterProtos$SetQuotaRequest;Ljava/lang/Object;)Ljava/lang/Object;
     295: pop
     296: aload_1
     297: iload_3
     298: invokestatic  #49                 // Method org/apache/hadoop/hbase/shaded/protobuf/generated/MasterProtos$SetQuotaRequest.access$118902:(Lorg/apache/hadoop/hbase/shaded/protobuf/generated/MasterProtos$SetQuotaRequest;I)I
     301: pop
     302: aload_0
     303: invokevirtual #50                 // Method onBuilt:()V
     306: aload_1
     307: areturn

  public org.apache.hadoop.hbase.shaded.protobuf.generated.MasterProtos$SetQuotaRequest$Builder clone();
    Code:
       0: aload_0
       1: invokespecial #51                 // Method org/apache/hbase/thirdparty/com/google/protobuf/GeneratedMessageV3$Builder.clone:()Lorg/apache/hbase/thirdparty/com/google/protobuf/GeneratedMessageV3$Builder;
       4: checkcast     #6                  // class org/apache/hadoop/hbase/shaded/protobuf/generated/MasterProtos$SetQuotaRequest$Builder
       7: areturn

  public org.apache.hadoop.hbase.shaded.protobuf.generated.MasterProtos$SetQuotaRequest$Builder setField(org.apache.hbase.thirdparty.com.google.protobuf.Descriptors$FieldDescriptor, java.lang.Object);
    Code:
       0: aload_0
       1: aload_1
       2: aload_2
       3: invokespecial #52                 // Method org/apache/hbase/thirdparty/com/google/protobuf/GeneratedMessageV3$Builder.setField:(Lorg/apache/hbase/thirdparty/com/google/protobuf/Descriptors$FieldDescriptor;Ljava/lang/Object;)Lorg/apache/hbase/thirdparty/com/google/protobuf/GeneratedMessageV3$Builder;
       6: checkcast     #6                  // class org/apache/hadoop/hbase/shaded/protobuf/generated/MasterProtos$SetQuotaRequest$Builder
       9: areturn

  public org.apache.hadoop.hbase.shaded.protobuf.generated.MasterProtos$SetQuotaRequest$Builder clearField(org.apache.hbase.thirdparty.com.google.protobuf.Descriptors$FieldDescriptor);
    Code:
       0: aload_0
       1: aload_1
       2: invokespecial #53                 // Method org/apache/hbase/thirdparty/com/google/protobuf/GeneratedMessageV3$Builder.clearField:(Lorg/apache/hbase/thirdparty/com/google/protobuf/Descriptors$FieldDescriptor;)Lorg/apache/hbase/thirdparty/com/google/protobuf/GeneratedMessageV3$Builder;
       5: checkcast     #6                  // class org/apache/hadoop/hbase/shaded/protobuf/generated/MasterProtos$SetQuotaRequest$Builder
       8: areturn

  public org.apache.hadoop.hbase.shaded.protobuf.generated.MasterProtos$SetQuotaRequest$Builder clearOneof(org.apache.hbase.thirdparty.com.google.protobuf.Descriptors$OneofDescriptor);
    Code:
       0: aload_0
       1: aload_1
       2: invokespecial #54                 // Method org/apache/hbase/thirdparty/com/google/protobuf/GeneratedMessageV3$Builder.clearOneof:(Lorg/apache/hbase/thirdparty/com/google/protobuf/Descriptors$OneofDescriptor;)Lorg/apache/hbase/thirdparty/com/google/protobuf/GeneratedMessageV3$Builder;
       5: checkcast     #6                  // class org/apache/hadoop/hbase/shaded/protobuf/generated/MasterProtos$SetQuotaRequest$Builder
       8: areturn

  public org.apache.hadoop.hbase.shaded.protobuf.generated.MasterProtos$SetQuotaRequest$Builder setRepeatedField(org.apache.hbase.thirdparty.com.google.protobuf.Descriptors$FieldDescriptor, int, java.lang.Object);
    Code:
       0: aload_0
       1: aload_1
       2: iload_2
       3: aload_3
       4: invokespecial #55                 // Method org/apache/hbase/thirdparty/com/google/protobuf/GeneratedMessageV3$Builder.setRepeatedField:(Lorg/apache/hbase/thirdparty/com/google/protobuf/Descriptors$FieldDescriptor;ILjava/lang/Object;)Lorg/apache/hbase/thirdparty/com/google/protobuf/GeneratedMessageV3$Builder;
       7: checkcast     #6                  // class org/apache/hadoop/hbase/shaded/protobuf/generated/MasterProtos$SetQuotaRequest$Builder
      10: areturn

  public org.apache.hadoop.hbase.shaded.protobuf.generated.MasterProtos$SetQuotaRequest$Builder addRepeatedField(org.apache.hbase.thirdparty.com.google.protobuf.Descriptors$FieldDescriptor, java.lang.Object);
    Code:
       0: aload_0
       1: aload_1
       2: aload_2
       3: invokespecial #56                 // Method org/apache/hbase/thirdparty/com/google/protobuf/GeneratedMessageV3$Builder.addRepeatedField:(Lorg/apache/hbase/thirdparty/com/google/protobuf/Descriptors$FieldDescriptor;Ljava/lang/Object;)Lorg/apache/hbase/thirdparty/com/google/protobuf/GeneratedMessageV3$Builder;
       6: checkcast     #6                  // class org/apache/hadoop/hbase/shaded/protobuf/generated/MasterProtos$SetQuotaRequest$Builder
       9: areturn

  public org.apache.hadoop.hbase.shaded.protobuf.generated.MasterProtos$SetQuotaRequest$Builder mergeFrom(org.apache.hbase.thirdparty.com.google.protobuf.Message);
    Code:
       0: aload_1
       1: instanceof    #5                  // class org/apache/hadoop/hbase/shaded/protobuf/generated/MasterProtos$SetQuotaRequest
       4: ifeq          16
       7: aload_0
       8: aload_1
       9: checkcast     #5                  // class org/apache/hadoop/hbase/shaded/protobuf/generated/MasterProtos$SetQuotaRequest
      12: invokevirtual #57                 // Method mergeFrom:(Lorg/apache/hadoop/hbase/shaded/protobuf/generated/MasterProtos$SetQuotaRequest;)Lorg/apache/hadoop/hbase/shaded/protobuf/generated/MasterProtos$SetQuotaRequest$Builder;
      15: areturn
      16: aload_0
      17: aload_1
      18: invokespecial #58                 // Method org/apache/hbase/thirdparty/com/google/protobuf/GeneratedMessageV3$Builder.mergeFrom:(Lorg/apache/hbase/thirdparty/com/google/protobuf/Message;)Lorg/apache/hbase/thirdparty/com/google/protobuf/AbstractMessage$Builder;
      21: pop
      22: aload_0
      23: areturn

  public org.apache.hadoop.hbase.shaded.protobuf.generated.MasterProtos$SetQuotaRequest$Builder mergeFrom(org.apache.hadoop.hbase.shaded.protobuf.generated.MasterProtos$SetQuotaRequest);
    Code:
       0: aload_1
       1: invokestatic  #31                 // Method org/apache/hadoop/hbase/shaded/protobuf/generated/MasterProtos$SetQuotaRequest.getDefaultInstance:()Lorg/apache/hadoop/hbase/shaded/protobuf/generated/MasterProtos$SetQuotaRequest;
       4: if_acmpne     9
       7: aload_0
       8: areturn
       9: aload_1
      10: invokevirtual #59                 // Method org/apache/hadoop/hbase/shaded/protobuf/generated/MasterProtos$SetQuotaRequest.hasUserName:()Z
      13: ifeq          38
      16: aload_0
      17: dup
      18: getfield      #24                 // Field bitField0_:I
      21: iconst_1
      22: ior
      23: putfield      #24                 // Field bitField0_:I
      26: aload_0
      27: aload_1
      28: invokestatic  #60                 // Method org/apache/hadoop/hbase/shaded/protobuf/generated/MasterProtos$SetQuotaRequest.access$118000:(Lorg/apache/hadoop/hbase/shaded/protobuf/generated/MasterProtos$SetQuotaRequest;)Ljava/lang/Object;
      31: putfield      #10                 // Field userName_:Ljava/lang/Object;
      34: aload_0
      35: invokevirtual #61                 // Method onChanged:()V
      38: aload_1
      39: invokevirtual #62                 // Method org/apache/hadoop/hbase/shaded/protobuf/generated/MasterProtos$SetQuotaRequest.hasUserGroup:()Z
      42: ifeq          67
      45: aload_0
      46: dup
      47: getfield      #24                 // Field bitField0_:I
      50: iconst_2
      51: ior
      52: putfield      #24                 // Field bitField0_:I
      55: aload_0
      56: aload_1
      57: invokestatic  #63                 // Method org/apache/hadoop/hbase/shaded/protobuf/generated/MasterProtos$SetQuotaRequest.access$118100:(Lorg/apache/hadoop/hbase/shaded/protobuf/generated/MasterProtos$SetQuotaRequest;)Ljava/lang/Object;
      60: putfield      #11                 // Field userGroup_:Ljava/lang/Object;
      63: aload_0
      64: invokevirtual #61                 // Method onChanged:()V
      67: aload_1
      68: invokevirtual #64                 // Method org/apache/hadoop/hbase/shaded/protobuf/generated/MasterProtos$SetQuotaRequest.hasNamespace:()Z
      71: ifeq          96
      74: aload_0
      75: dup
      76: getfield      #24                 // Field bitField0_:I
      79: iconst_4
      80: ior
      81: putfield      #24                 // Field bitField0_:I
      84: aload_0
      85: aload_1
      86: invokestatic  #65                 // Method org/apache/hadoop/hbase/shaded/protobuf/generated/MasterProtos$SetQuotaRequest.access$118200:(Lorg/apache/hadoop/hbase/shaded/protobuf/generated/MasterProtos$SetQuotaRequest;)Ljava/lang/Object;
      89: putfield      #12                 // Field namespace_:Ljava/lang/Object;
      92: aload_0
      93: invokevirtual #61                 // Method onChanged:()V
      96: aload_1
      97: invokevirtual #66                 // Method org/apache/hadoop/hbase/shaded/protobuf/generated/MasterProtos$SetQuotaRequest.hasTableName:()Z
     100: ifeq          112
     103: aload_0
     104: aload_1
     105: invokevirtual #67                 // Method org/apache/hadoop/hbase/shaded/protobuf/generated/MasterProtos$SetQuotaRequest.getTableName:()Lorg/apache/hadoop/hbase/shaded/protobuf/generated/HBaseProtos$TableName;
     108: invokevirtual #68                 // Method mergeTableName:(Lorg/apache/hadoop/hbase/shaded/protobuf/generated/HBaseProtos$TableName;)Lorg/apache/hadoop/hbase/shaded/protobuf/generated/MasterProtos$SetQuotaRequest$Builder;
     111: pop
     112: aload_1
     113: invokevirtual #69                 // Method org/apache/hadoop/hbase/shaded/protobuf/generated/MasterProtos$SetQuotaRequest.hasRemoveAll:()Z
     116: ifeq          128
     119: aload_0
     120: aload_1
     121: invokevirtual #70                 // Method org/apache/hadoop/hbase/shaded/protobuf/generated/MasterProtos$SetQuotaRequest.getRemoveAll:()Z
     124: invokevirtual #71                 // Method setRemoveAll:(Z)Lorg/apache/hadoop/hbase/shaded/protobuf/generated/MasterProtos$SetQuotaRequest$Builder;
     127: pop
     128: aload_1
     129: invokevirtual #72                 // Method org/apache/hadoop/hbase/shaded/protobuf/generated/MasterProtos$SetQuotaRequest.hasBypassGlobals:()Z
     132: ifeq          144
     135: aload_0
     136: aload_1
     137: invokevirtual #73                 // Method org/apache/hadoop/hbase/shaded/protobuf/generated/MasterProtos$SetQuotaRequest.getBypassGlobals:()Z
     140: invokevirtual #74                 // Method setBypassGlobals:(Z)Lorg/apache/hadoop/hbase/shaded/protobuf/generated/MasterProtos$SetQuotaRequest$Builder;
     143: pop
     144: aload_1
     145: invokevirtual #75                 // Method org/apache/hadoop/hbase/shaded/protobuf/generated/MasterProtos$SetQuotaRequest.hasThrottle:()Z
     148: ifeq          160
     151: aload_0
     152: aload_1
     153: invokevirtual #76                 // Method org/apache/hadoop/hbase/shaded/protobuf/generated/MasterProtos$SetQuotaRequest.getThrottle:()Lorg/apache/hadoop/hbase/shaded/protobuf/generated/QuotaProtos$ThrottleRequest;
     156: invokevirtual #77                 // Method mergeThrottle:(Lorg/apache/hadoop/hbase/shaded/protobuf/generated/QuotaProtos$ThrottleRequest;)Lorg/apache/hadoop/hbase/shaded/protobuf/generated/MasterProtos$SetQuotaRequest$Builder;
     159: pop
     160: aload_1
     161: invokevirtual #78                 // Method org/apache/hadoop/hbase/shaded/protobuf/generated/MasterProtos$SetQuotaRequest.hasSpaceLimit:()Z
     164: ifeq          176
     167: aload_0
     168: aload_1
     169: invokevirtual #79                 // Method org/apache/hadoop/hbase/shaded/protobuf/generated/MasterProtos$SetQuotaRequest.getSpaceLimit:()Lorg/apache/hadoop/hbase/shaded/protobuf/generated/QuotaProtos$SpaceLimitRequest;
     172: invokevirtual #80                 // Method mergeSpaceLimit:(Lorg/apache/hadoop/hbase/shaded/protobuf/generated/QuotaProtos$SpaceLimitRequest;)Lorg/apache/hadoop/hbase/shaded/protobuf/generated/MasterProtos$SetQuotaRequest$Builder;
     175: pop
     176: aload_1
     177: invokevirtual #81                 // Method org/apache/hadoop/hbase/shaded/protobuf/generated/MasterProtos$SetQuotaRequest.hasRegionServer:()Z
     180: ifeq          207
     183: aload_0
     184: dup
     185: getfield      #24                 // Field bitField0_:I
     188: sipush        256
     191: ior
     192: putfield      #24                 // Field bitField0_:I
     195: aload_0
     196: aload_1
     197: invokestatic  #82                 // Method org/apache/hadoop/hbase/shaded/protobuf/generated/MasterProtos$SetQuotaRequest.access$118800:(Lorg/apache/hadoop/hbase/shaded/protobuf/generated/MasterProtos$SetQuotaRequest;)Ljava/lang/Object;
     200: putfield      #16                 // Field regionServer_:Ljava/lang/Object;
     203: aload_0
     204: invokevirtual #61                 // Method onChanged:()V
     207: aload_0
     208: aload_1
     209: invokestatic  #83                 // Method org/apache/hadoop/hbase/shaded/protobuf/generated/MasterProtos$SetQuotaRequest.access$119000:(Lorg/apache/hadoop/hbase/shaded/protobuf/generated/MasterProtos$SetQuotaRequest;)Lorg/apache/hbase/thirdparty/com/google/protobuf/UnknownFieldSet;
     212: invokevirtual #84                 // Method mergeUnknownFields:(Lorg/apache/hbase/thirdparty/com/google/protobuf/UnknownFieldSet;)Lorg/apache/hadoop/hbase/shaded/protobuf/generated/MasterProtos$SetQuotaRequest$Builder;
     215: pop
     216: aload_0
     217: invokevirtual #61                 // Method onChanged:()V
     220: aload_0
     221: areturn

  public final boolean isInitialized();
    Code:
       0: aload_0
       1: invokevirtual #85                 // Method hasTableName:()Z
       4: ifeq          19
       7: aload_0
       8: invokevirtual #86                 // Method getTableName:()Lorg/apache/hadoop/hbase/shaded/protobuf/generated/HBaseProtos$TableName;
      11: invokevirtual #87                 // Method org/apache/hadoop/hbase/shaded/protobuf/generated/HBaseProtos$TableName.isInitialized:()Z
      14: ifne          19
      17: iconst_0
      18: ireturn
      19: aload_0
      20: invokevirtual #88                 // Method hasThrottle:()Z
      23: ifeq          38
      26: aload_0
      27: invokevirtual #89                 // Method getThrottle:()Lorg/apache/hadoop/hbase/shaded/protobuf/generated/QuotaProtos$ThrottleRequest;
      30: invokevirtual #90                 // Method org/apache/hadoop/hbase/shaded/protobuf/generated/QuotaProtos$ThrottleRequest.isInitialized:()Z
      33: ifne          38
      36: iconst_0
      37: ireturn
      38: iconst_1
      39: ireturn

  public org.apache.hadoop.hbase.shaded.protobuf.generated.MasterProtos$SetQuotaRequest$Builder mergeFrom(org.apache.hbase.thirdparty.com.google.protobuf.CodedInputStream, org.apache.hbase.thirdparty.com.google.protobuf.ExtensionRegistryLite) throws java.io.IOException;
    Code:
       0: aconst_null
       1: astore_3
       2: getstatic     #91                 // Field org/apache/hadoop/hbase/shaded/protobuf/generated/MasterProtos$SetQuotaRequest.PARSER:Lorg/apache/hbase/thirdparty/com/google/protobuf/Parser;
       5: aload_1
       6: aload_2
       7: invokeinterface #92,  3           // InterfaceMethod org/apache/hbase/thirdparty/com/google/protobuf/Parser.parsePartialFrom:(Lorg/apache/hbase/thirdparty/com/google/protobuf/CodedInputStream;Lorg/apache/hbase/thirdparty/com/google/protobuf/ExtensionRegistryLite;)Ljava/lang/Object;
      12: checkcast     #5                  // class org/apache/hadoop/hbase/shaded/protobuf/generated/MasterProtos$SetQuotaRequest
      15: astore_3
      16: aload_3
      17: ifnull        61
      20: aload_0
      21: aload_3
      22: invokevirtual #57                 // Method mergeFrom:(Lorg/apache/hadoop/hbase/shaded/protobuf/generated/MasterProtos$SetQuotaRequest;)Lorg/apache/hadoop/hbase/shaded/protobuf/generated/MasterProtos$SetQuotaRequest$Builder;
      25: pop
      26: goto          61
      29: astore        4
      31: aload         4
      33: invokevirtual #94                 // Method org/apache/hbase/thirdparty/com/google/protobuf/InvalidProtocolBufferException.getUnfinishedMessage:()Lorg/apache/hbase/thirdparty/com/google/protobuf/MessageLite;
      36: checkcast     #5                  // class org/apache/hadoop/hbase/shaded/protobuf/generated/MasterProtos$SetQuotaRequest
      39: astore_3
      40: aload         4
      42: invokevirtual #95                 // Method org/apache/hbase/thirdparty/com/google/protobuf/InvalidProtocolBufferException.unwrapIOException:()Ljava/io/IOException;
      45: athrow
      46: astore        5
      48: aload_3
      49: ifnull        58
      52: aload_0
      53: aload_3
      54: invokevirtual #57                 // Method mergeFrom:(Lorg/apache/hadoop/hbase/shaded/protobuf/generated/MasterProtos$SetQuotaRequest;)Lorg/apache/hadoop/hbase/shaded/protobuf/generated/MasterProtos$SetQuotaRequest$Builder;
      57: pop
      58: aload         5
      60: athrow
      61: aload_0
      62: areturn
    Exception table:
       from    to  target type
           2    16    29   Class org/apache/hbase/thirdparty/com/google/protobuf/InvalidProtocolBufferException
           2    16    46   any
          29    48    46   any

  public boolean hasUserName();
    Code:
       0: aload_0
       1: getfield      #24                 // Field bitField0_:I
       4: iconst_1
       5: iand
       6: iconst_1
       7: if_icmpne     14
      10: iconst_1
      11: goto          15
      14: iconst_0
      15: ireturn

  public java.lang.String getUserName();
    Code:
       0: aload_0
       1: getfield      #10                 // Field userName_:Ljava/lang/Object;
       4: astore_1
       5: aload_1
       6: instanceof    #96                 // class java/lang/String
       9: ifne          36
      12: aload_1
      13: checkcast     #97                 // class org/apache/hbase/thirdparty/com/google/protobuf/ByteString
      16: astore_2
      17: aload_2
      18: invokevirtual #98                 // Method org/apache/hbase/thirdparty/com/google/protobuf/ByteString.toStringUtf8:()Ljava/lang/String;
      21: astore_3
      22: aload_2
      23: invokevirtual #99                 // Method org/apache/hbase/thirdparty/com/google/protobuf/ByteString.isValidUtf8:()Z
      26: ifeq          34
      29: aload_0
      30: aload_3
      31: putfield      #10                 // Field userName_:Ljava/lang/Object;
      34: aload_3
      35: areturn
      36: aload_1
      37: checkcast     #96                 // class java/lang/String
      40: areturn

  public org.apache.hbase.thirdparty.com.google.protobuf.ByteString getUserNameBytes();
    Code:
       0: aload_0
       1: getfield      #10                 // Field userName_:Ljava/lang/Object;
       4: astore_1
       5: aload_1
       6: instanceof    #96                 // class java/lang/String
       9: ifeq          27
      12: aload_1
      13: checkcast     #96                 // class java/lang/String
      16: invokestatic  #100                // Method org/apache/hbase/thirdparty/com/google/protobuf/ByteString.copyFromUtf8:(Ljava/lang/String;)Lorg/apache/hbase/thirdparty/com/google/protobuf/ByteString;
      19: astore_2
      20: aload_0
      21: aload_2
      22: putfield      #10                 // Field userName_:Ljava/lang/Object;
      25: aload_2
      26: areturn
      27: aload_1
      28: checkcast     #97                 // class org/apache/hbase/thirdparty/com/google/protobuf/ByteString
      31: areturn

  public org.apache.hadoop.hbase.shaded.protobuf.generated.MasterProtos$SetQuotaRequest$Builder setUserName(java.lang.String);
    Code:
       0: aload_1
       1: ifnonnull     12
       4: new           #101                // class java/lang/NullPointerException
       7: dup
       8: invokespecial #102                // Method java/lang/NullPointerException."<init>":()V
      11: athrow
      12: aload_0
      13: dup
      14: getfield      #24                 // Field bitField0_:I
      17: iconst_1
      18: ior
      19: putfield      #24                 // Field bitField0_:I
      22: aload_0
      23: aload_1
      24: putfield      #10                 // Field userName_:Ljava/lang/Object;
      27: aload_0
      28: invokevirtual #61                 // Method onChanged:()V
      31: aload_0
      32: areturn

  public org.apache.hadoop.hbase.shaded.protobuf.generated.MasterProtos$SetQuotaRequest$Builder clearUserName();
    Code:
       0: aload_0
       1: aload_0
       2: getfield      #24                 // Field bitField0_:I
       5: bipush        -2
       7: iand
       8: putfield      #24                 // Field bitField0_:I
      11: aload_0
      12: invokestatic  #31                 // Method org/apache/hadoop/hbase/shaded/protobuf/generated/MasterProtos$SetQuotaRequest.getDefaultInstance:()Lorg/apache/hadoop/hbase/shaded/protobuf/generated/MasterProtos$SetQuotaRequest;
      15: invokevirtual #103                // Method org/apache/hadoop/hbase/shaded/protobuf/generated/MasterProtos$SetQuotaRequest.getUserName:()Ljava/lang/String;
      18: putfield      #10                 // Field userName_:Ljava/lang/Object;
      21: aload_0
      22: invokevirtual #61                 // Method onChanged:()V
      25: aload_0
      26: areturn

  public org.apache.hadoop.hbase.shaded.protobuf.generated.MasterProtos$SetQuotaRequest$Builder setUserNameBytes(org.apache.hbase.thirdparty.com.google.protobuf.ByteString);
    Code:
       0: aload_1
       1: ifnonnull     12
       4: new           #101                // class java/lang/NullPointerException
       7: dup
       8: invokespecial #102                // Method java/lang/NullPointerException."<init>":()V
      11: athrow
      12: aload_0
      13: dup
      14: getfield      #24                 // Field bitField0_:I
      17: iconst_1
      18: ior
      19: putfield      #24                 // Field bitField0_:I
      22: aload_0
      23: aload_1
      24: putfield      #10                 // Field userName_:Ljava/lang/Object;
      27: aload_0
      28: invokevirtual #61                 // Method onChanged:()V
      31: aload_0
      32: areturn

  public boolean hasUserGroup();
    Code:
       0: aload_0
       1: getfield      #24                 // Field bitField0_:I
       4: iconst_2
       5: iand
       6: iconst_2
       7: if_icmpne     14
      10: iconst_1
      11: goto          15
      14: iconst_0
      15: ireturn

  public java.lang.String getUserGroup();
    Code:
       0: aload_0
       1: getfield      #11                 // Field userGroup_:Ljava/lang/Object;
       4: astore_1
       5: aload_1
       6: instanceof    #96                 // class java/lang/String
       9: ifne          36
      12: aload_1
      13: checkcast     #97                 // class org/apache/hbase/thirdparty/com/google/protobuf/ByteString
      16: astore_2
      17: aload_2
      18: invokevirtual #98                 // Method org/apache/hbase/thirdparty/com/google/protobuf/ByteString.toStringUtf8:()Ljava/lang/String;
      21: astore_3
      22: aload_2
      23: invokevirtual #99                 // Method org/apache/hbase/thirdparty/com/google/protobuf/ByteString.isValidUtf8:()Z
      26: ifeq          34
      29: aload_0
      30: aload_3
      31: putfield      #11                 // Field userGroup_:Ljava/lang/Object;
      34: aload_3
      35: areturn
      36: aload_1
      37: checkcast     #96                 // class java/lang/String
      40: areturn

  public org.apache.hbase.thirdparty.com.google.protobuf.ByteString getUserGroupBytes();
    Code:
       0: aload_0
       1: getfield      #11                 // Field userGroup_:Ljava/lang/Object;
       4: astore_1
       5: aload_1
       6: instanceof    #96                 // class java/lang/String
       9: ifeq          27
      12: aload_1
      13: checkcast     #96                 // class java/lang/String
      16: invokestatic  #100                // Method org/apache/hbase/thirdparty/com/google/protobuf/ByteString.copyFromUtf8:(Ljava/lang/String;)Lorg/apache/hbase/thirdparty/com/google/protobuf/ByteString;
      19: astore_2
      20: aload_0
      21: aload_2
      22: putfield      #11                 // Field userGroup_:Ljava/lang/Object;
      25: aload_2
      26: areturn
      27: aload_1
      28: checkcast     #97                 // class org/apache/hbase/thirdparty/com/google/protobuf/ByteString
      31: areturn

  public org.apache.hadoop.hbase.shaded.protobuf.generated.MasterProtos$SetQuotaRequest$Builder setUserGroup(java.lang.String);
    Code:
       0: aload_1
       1: ifnonnull     12
       4: new           #101                // class java/lang/NullPointerException
       7: dup
       8: invokespecial #102                // Method java/lang/NullPointerException."<init>":()V
      11: athrow
      12: aload_0
      13: dup
      14: getfield      #24                 // Field bitField0_:I
      17: iconst_2
      18: ior
      19: putfield      #24                 // Field bitField0_:I
      22: aload_0
      23: aload_1
      24: putfield      #11                 // Field userGroup_:Ljava/lang/Object;
      27: aload_0
      28: invokevirtual #61                 // Method onChanged:()V
      31: aload_0
      32: areturn

  public org.apache.hadoop.hbase.shaded.protobuf.generated.MasterProtos$SetQuotaRequest$Builder clearUserGroup();
    Code:
       0: aload_0
       1: aload_0
       2: getfield      #24                 // Field bitField0_:I
       5: bipush        -3
       7: iand
       8: putfield      #24                 // Field bitField0_:I
      11: aload_0
      12: invokestatic  #31                 // Method org/apache/hadoop/hbase/shaded/protobuf/generated/MasterProtos$SetQuotaRequest.getDefaultInstance:()Lorg/apache/hadoop/hbase/shaded/protobuf/generated/MasterProtos$SetQuotaRequest;
      15: invokevirtual #104                // Method org/apache/hadoop/hbase/shaded/protobuf/generated/MasterProtos$SetQuotaRequest.getUserGroup:()Ljava/lang/String;
      18: putfield      #11                 // Field userGroup_:Ljava/lang/Object;
      21: aload_0
      22: invokevirtual #61                 // Method onChanged:()V
      25: aload_0
      26: areturn

  public org.apache.hadoop.hbase.shaded.protobuf.generated.MasterProtos$SetQuotaRequest$Builder setUserGroupBytes(org.apache.hbase.thirdparty.com.google.protobuf.ByteString);
    Code:
       0: aload_1
       1: ifnonnull     12
       4: new           #101                // class java/lang/NullPointerException
       7: dup
       8: invokespecial #102                // Method java/lang/NullPointerException."<init>":()V
      11: athrow
      12: aload_0
      13: dup
      14: getfield      #24                 // Field bitField0_:I
      17: iconst_2
      18: ior
      19: putfield      #24                 // Field bitField0_:I
      22: aload_0
      23: aload_1
      24: putfield      #11                 // Field userGroup_:Ljava/lang/Object;
      27: aload_0
      28: invokevirtual #61                 // Method onChanged:()V
      31: aload_0
      32: areturn

  public boolean hasNamespace();
    Code:
       0: aload_0
       1: getfield      #24                 // Field bitField0_:I
       4: iconst_4
       5: iand
       6: iconst_4
       7: if_icmpne     14
      10: iconst_1
      11: goto          15
      14: iconst_0
      15: ireturn

  public java.lang.String getNamespace();
    Code:
       0: aload_0
       1: getfield      #12                 // Field namespace_:Ljava/lang/Object;
       4: astore_1
       5: aload_1
       6: instanceof    #96                 // class java/lang/String
       9: ifne          36
      12: aload_1
      13: checkcast     #97                 // class org/apache/hbase/thirdparty/com/google/protobuf/ByteString
      16: astore_2
      17: aload_2
      18: invokevirtual #98                 // Method org/apache/hbase/thirdparty/com/google/protobuf/ByteString.toStringUtf8:()Ljava/lang/String;
      21: astore_3
      22: aload_2
      23: invokevirtual #99                 // Method org/apache/hbase/thirdparty/com/google/protobuf/ByteString.isValidUtf8:()Z
      26: ifeq          34
      29: aload_0
      30: aload_3
      31: putfield      #12                 // Field namespace_:Ljava/lang/Object;
      34: aload_3
      35: areturn
      36: aload_1
      37: checkcast     #96                 // class java/lang/String
      40: areturn

  public org.apache.hbase.thirdparty.com.google.protobuf.ByteString getNamespaceBytes();
    Code:
       0: aload_0
       1: getfield      #12                 // Field namespace_:Ljava/lang/Object;
       4: astore_1
       5: aload_1
       6: instanceof    #96                 // class java/lang/String
       9: ifeq          27
      12: aload_1
      13: checkcast     #96                 // class java/lang/String
      16: invokestatic  #100                // Method org/apache/hbase/thirdparty/com/google/protobuf/ByteString.copyFromUtf8:(Ljava/lang/String;)Lorg/apache/hbase/thirdparty/com/google/protobuf/ByteString;
      19: astore_2
      20: aload_0
      21: aload_2
      22: putfield      #12                 // Field namespace_:Ljava/lang/Object;
      25: aload_2
      26: areturn
      27: aload_1
      28: checkcast     #97                 // class org/apache/hbase/thirdparty/com/google/protobuf/ByteString
      31: areturn

  public org.apache.hadoop.hbase.shaded.protobuf.generated.MasterProtos$SetQuotaRequest$Builder setNamespace(java.lang.String);
    Code:
       0: aload_1
       1: ifnonnull     12
       4: new           #101                // class java/lang/NullPointerException
       7: dup
       8: invokespecial #102                // Method java/lang/NullPointerException."<init>":()V
      11: athrow
      12: aload_0
      13: dup
      14: getfield      #24                 // Field bitField0_:I
      17: iconst_4
      18: ior
      19: putfield      #24                 // Field bitField0_:I
      22: aload_0
      23: aload_1
      24: putfield      #12                 // Field namespace_:Ljava/lang/Object;
      27: aload_0
      28: invokevirtual #61                 // Method onChanged:()V
      31: aload_0
      32: areturn

  public org.apache.hadoop.hbase.shaded.protobuf.generated.MasterProtos$SetQuotaRequest$Builder clearNamespace();
    Code:
       0: aload_0
       1: aload_0
       2: getfield      #24                 // Field bitField0_:I
       5: bipush        -5
       7: iand
       8: putfield      #24                 // Field bitField0_:I
      11: aload_0
      12: invokestatic  #31                 // Method org/apache/hadoop/hbase/shaded/protobuf/generated/MasterProtos$SetQuotaRequest.getDefaultInstance:()Lorg/apache/hadoop/hbase/shaded/protobuf/generated/MasterProtos$SetQuotaRequest;
      15: invokevirtual #105                // Method org/apache/hadoop/hbase/shaded/protobuf/generated/MasterProtos$SetQuotaRequest.getNamespace:()Ljava/lang/String;
      18: putfield      #12                 // Field namespace_:Ljava/lang/Object;
      21: aload_0
      22: invokevirtual #61                 // Method onChanged:()V
      25: aload_0
      26: areturn

  public org.apache.hadoop.hbase.shaded.protobuf.generated.MasterProtos$SetQuotaRequest$Builder setNamespaceBytes(org.apache.hbase.thirdparty.com.google.protobuf.ByteString);
    Code:
       0: aload_1
       1: ifnonnull     12
       4: new           #101                // class java/lang/NullPointerException
       7: dup
       8: invokespecial #102                // Method java/lang/NullPointerException."<init>":()V
      11: athrow
      12: aload_0
      13: dup
      14: getfield      #24                 // Field bitField0_:I
      17: iconst_4
      18: ior
      19: putfield      #24                 // Field bitField0_:I
      22: aload_0
      23: aload_1
      24: putfield      #12                 // Field namespace_:Ljava/lang/Object;
      27: aload_0
      28: invokevirtual #61                 // Method onChanged:()V
      31: aload_0
      32: areturn

  public boolean hasTableName();
    Code:
       0: aload_0
       1: getfield      #24                 // Field bitField0_:I
       4: bipush        8
       6: iand
       7: bipush        8
       9: if_icmpne     16
      12: iconst_1
      13: goto          17
      16: iconst_0
      17: ireturn

  public org.apache.hadoop.hbase.shaded.protobuf.generated.HBaseProtos$TableName getTableName();
    Code:
       0: aload_0
       1: getfield      #25                 // Field tableNameBuilder_:Lorg/apache/hbase/thirdparty/com/google/protobuf/SingleFieldBuilderV3;
       4: ifnonnull     25
       7: aload_0
       8: getfield      #13                 // Field tableName_:Lorg/apache/hadoop/hbase/shaded/protobuf/generated/HBaseProtos$TableName;
      11: ifnonnull     20
      14: invokestatic  #106                // Method org/apache/hadoop/hbase/shaded/protobuf/generated/HBaseProtos$TableName.getDefaultInstance:()Lorg/apache/hadoop/hbase/shaded/protobuf/generated/HBaseProtos$TableName;
      17: goto          24
      20: aload_0
      21: getfield      #13                 // Field tableName_:Lorg/apache/hadoop/hbase/shaded/protobuf/generated/HBaseProtos$TableName;
      24: areturn
      25: aload_0
      26: getfield      #25                 // Field tableNameBuilder_:Lorg/apache/hbase/thirdparty/com/google/protobuf/SingleFieldBuilderV3;
      29: invokevirtual #107                // Method org/apache/hbase/thirdparty/com/google/protobuf/SingleFieldBuilderV3.getMessage:()Lorg/apache/hbase/thirdparty/com/google/protobuf/AbstractMessage;
      32: checkcast     #41                 // class org/apache/hadoop/hbase/shaded/protobuf/generated/HBaseProtos$TableName
      35: areturn

  public org.apache.hadoop.hbase.shaded.protobuf.generated.MasterProtos$SetQuotaRequest$Builder setTableName(org.apache.hadoop.hbase.shaded.protobuf.generated.HBaseProtos$TableName);
    Code:
       0: aload_0
       1: getfield      #25                 // Field tableNameBuilder_:Lorg/apache/hbase/thirdparty/com/google/protobuf/SingleFieldBuilderV3;
       4: ifnonnull     31
       7: aload_1
       8: ifnonnull     19
      11: new           #101                // class java/lang/NullPointerException
      14: dup
      15: invokespecial #102                // Method java/lang/NullPointerException."<init>":()V
      18: athrow
      19: aload_0
      20: aload_1
      21: putfield      #13                 // Field tableName_:Lorg/apache/hadoop/hbase/shaded/protobuf/generated/HBaseProtos$TableName;
      24: aload_0
      25: invokevirtual #61                 // Method onChanged:()V
      28: goto          40
      31: aload_0
      32: getfield      #25                 // Field tableNameBuilder_:Lorg/apache/hbase/thirdparty/com/google/protobuf/SingleFieldBuilderV3;
      35: aload_1
      36: invokevirtual #108                // Method org/apache/hbase/thirdparty/com/google/protobuf/SingleFieldBuilderV3.setMessage:(Lorg/apache/hbase/thirdparty/com/google/protobuf/AbstractMessage;)Lorg/apache/hbase/thirdparty/com/google/protobuf/SingleFieldBuilderV3;
      39: pop
      40: aload_0
      41: dup
      42: getfield      #24                 // Field bitField0_:I
      45: bipush        8
      47: ior
      48: putfield      #24                 // Field bitField0_:I
      51: aload_0
      52: areturn

  public org.apache.hadoop.hbase.shaded.protobuf.generated.MasterProtos$SetQuotaRequest$Builder setTableName(org.apache.hadoop.hbase.shaded.protobuf.generated.HBaseProtos$TableName$Builder);
    Code:
       0: aload_0
       1: getfield      #25                 // Field tableNameBuilder_:Lorg/apache/hbase/thirdparty/com/google/protobuf/SingleFieldBuilderV3;
       4: ifnonnull     22
       7: aload_0
       8: aload_1
       9: invokevirtual #109                // Method org/apache/hadoop/hbase/shaded/protobuf/generated/HBaseProtos$TableName$Builder.build:()Lorg/apache/hadoop/hbase/shaded/protobuf/generated/HBaseProtos$TableName;
      12: putfield      #13                 // Field tableName_:Lorg/apache/hadoop/hbase/shaded/protobuf/generated/HBaseProtos$TableName;
      15: aload_0
      16: invokevirtual #61                 // Method onChanged:()V
      19: goto          34
      22: aload_0
      23: getfield      #25                 // Field tableNameBuilder_:Lorg/apache/hbase/thirdparty/com/google/protobuf/SingleFieldBuilderV3;
      26: aload_1
      27: invokevirtual #109                // Method org/apache/hadoop/hbase/shaded/protobuf/generated/HBaseProtos$TableName$Builder.build:()Lorg/apache/hadoop/hbase/shaded/protobuf/generated/HBaseProtos$TableName;
      30: invokevirtual #108                // Method org/apache/hbase/thirdparty/com/google/protobuf/SingleFieldBuilderV3.setMessage:(Lorg/apache/hbase/thirdparty/com/google/protobuf/AbstractMessage;)Lorg/apache/hbase/thirdparty/com/google/protobuf/SingleFieldBuilderV3;
      33: pop
      34: aload_0
      35: dup
      36: getfield      #24                 // Field bitField0_:I
      39: bipush        8
      41: ior
      42: putfield      #24                 // Field bitField0_:I
      45: aload_0
      46: areturn

  public org.apache.hadoop.hbase.shaded.protobuf.generated.MasterProtos$SetQuotaRequest$Builder mergeTableName(org.apache.hadoop.hbase.shaded.protobuf.generated.HBaseProtos$TableName);
    Code:
       0: aload_0
       1: getfield      #25                 // Field tableNameBuilder_:Lorg/apache/hbase/thirdparty/com/google/protobuf/SingleFieldBuilderV3;
       4: ifnonnull     69
       7: aload_0
       8: getfield      #24                 // Field bitField0_:I
      11: bipush        8
      13: iand
      14: bipush        8
      16: if_icmpne     57
      19: aload_0
      20: getfield      #13                 // Field tableName_:Lorg/apache/hadoop/hbase/shaded/protobuf/generated/HBaseProtos$TableName;
      23: ifnull        57
      26: aload_0
      27: getfield      #13                 // Field tableName_:Lorg/apache/hadoop/hbase/shaded/protobuf/generated/HBaseProtos$TableName;
      30: invokestatic  #106                // Method org/apache/hadoop/hbase/shaded/protobuf/generated/HBaseProtos$TableName.getDefaultInstance:()Lorg/apache/hadoop/hbase/shaded/protobuf/generated/HBaseProtos$TableName;
      33: if_acmpeq     57
      36: aload_0
      37: aload_0
      38: getfield      #13                 // Field tableName_:Lorg/apache/hadoop/hbase/shaded/protobuf/generated/HBaseProtos$TableName;
      41: invokestatic  #110                // Method org/apache/hadoop/hbase/shaded/protobuf/generated/HBaseProtos$TableName.newBuilder:(Lorg/apache/hadoop/hbase/shaded/protobuf/generated/HBaseProtos$TableName;)Lorg/apache/hadoop/hbase/shaded/protobuf/generated/HBaseProtos$TableName$Builder;
      44: aload_1
      45: invokevirtual #111                // Method org/apache/hadoop/hbase/shaded/protobuf/generated/HBaseProtos$TableName$Builder.mergeFrom:(Lorg/apache/hadoop/hbase/shaded/protobuf/generated/HBaseProtos$TableName;)Lorg/apache/hadoop/hbase/shaded/protobuf/generated/HBaseProtos$TableName$Builder;
      48: invokevirtual #112                // Method org/apache/hadoop/hbase/shaded/protobuf/generated/HBaseProtos$TableName$Builder.buildPartial:()Lorg/apache/hadoop/hbase/shaded/protobuf/generated/HBaseProtos$TableName;
      51: putfield      #13                 // Field tableName_:Lorg/apache/hadoop/hbase/shaded/protobuf/generated/HBaseProtos$TableName;
      54: goto          62
      57: aload_0
      58: aload_1
      59: putfield      #13                 // Field tableName_:Lorg/apache/hadoop/hbase/shaded/protobuf/generated/HBaseProtos$TableName;
      62: aload_0
      63: invokevirtual #61                 // Method onChanged:()V
      66: goto          78
      69: aload_0
      70: getfield      #25                 // Field tableNameBuilder_:Lorg/apache/hbase/thirdparty/com/google/protobuf/SingleFieldBuilderV3;
      73: aload_1
      74: invokevirtual #113                // Method org/apache/hbase/thirdparty/com/google/protobuf/SingleFieldBuilderV3.mergeFrom:(Lorg/apache/hbase/thirdparty/com/google/protobuf/AbstractMessage;)Lorg/apache/hbase/thirdparty/com/google/protobuf/SingleFieldBuilderV3;
      77: pop
      78: aload_0
      79: dup
      80: getfield      #24                 // Field bitField0_:I
      83: bipush        8
      85: ior
      86: putfield      #24                 // Field bitField0_:I
      89: aload_0
      90: areturn

  public org.apache.hadoop.hbase.shaded.protobuf.generated.MasterProtos$SetQuotaRequest$Builder clearTableName();
    Code:
       0: aload_0
       1: getfield      #25                 // Field tableNameBuilder_:Lorg/apache/hbase/thirdparty/com/google/protobuf/SingleFieldBuilderV3;
       4: ifnonnull     19
       7: aload_0
       8: aconst_null
       9: putfield      #13                 // Field tableName_:Lorg/apache/hadoop/hbase/shaded/protobuf/generated/HBaseProtos$TableName;
      12: aload_0
      13: invokevirtual #61                 // Method onChanged:()V
      16: goto          27
      19: aload_0
      20: getfield      #25                 // Field tableNameBuilder_:Lorg/apache/hbase/thirdparty/com/google/protobuf/SingleFieldBuilderV3;
      23: invokevirtual #26                 // Method org/apache/hbase/thirdparty/com/google/protobuf/SingleFieldBuilderV3.clear:()Lorg/apache/hbase/thirdparty/com/google/protobuf/SingleFieldBuilderV3;
      26: pop
      27: aload_0
      28: aload_0
      29: getfield      #24                 // Field bitField0_:I
      32: bipush        -9
      34: iand
      35: putfield      #24                 // Field bitField0_:I
      38: aload_0
      39: areturn

  public org.apache.hadoop.hbase.shaded.protobuf.generated.HBaseProtos$TableName$Builder getTableNameBuilder();
    Code:
       0: aload_0
       1: dup
       2: getfield      #24                 // Field bitField0_:I
       5: bipush        8
       7: ior
       8: putfield      #24                 // Field bitField0_:I
      11: aload_0
      12: invokevirtual #61                 // Method onChanged:()V
      15: aload_0
      16: invokespecial #20                 // Method getTableNameFieldBuilder:()Lorg/apache/hbase/thirdparty/com/google/protobuf/SingleFieldBuilderV3;
      19: invokevirtual #114                // Method org/apache/hbase/thirdparty/com/google/protobuf/SingleFieldBuilderV3.getBuilder:()Lorg/apache/hbase/thirdparty/com/google/protobuf/AbstractMessage$Builder;
      22: checkcast     #115                // class org/apache/hadoop/hbase/shaded/protobuf/generated/HBaseProtos$TableName$Builder
      25: areturn

  public org.apache.hadoop.hbase.shaded.protobuf.generated.HBaseProtos$TableNameOrBuilder getTableNameOrBuilder();
    Code:
       0: aload_0
       1: getfield      #25                 // Field tableNameBuilder_:Lorg/apache/hbase/thirdparty/com/google/protobuf/SingleFieldBuilderV3;
       4: ifnull        18
       7: aload_0
       8: getfield      #25                 // Field tableNameBuilder_:Lorg/apache/hbase/thirdparty/com/google/protobuf/SingleFieldBuilderV3;
      11: invokevirtual #116                // Method org/apache/hbase/thirdparty/com/google/protobuf/SingleFieldBuilderV3.getMessageOrBuilder:()Lorg/apache/hbase/thirdparty/com/google/protobuf/MessageOrBuilder;
      14: checkcast     #117                // class org/apache/hadoop/hbase/shaded/protobuf/generated/HBaseProtos$TableNameOrBuilder
      17: areturn
      18: aload_0
      19: getfield      #13                 // Field tableName_:Lorg/apache/hadoop/hbase/shaded/protobuf/generated/HBaseProtos$TableName;
      22: ifnonnull     31
      25: invokestatic  #106                // Method org/apache/hadoop/hbase/shaded/protobuf/generated/HBaseProtos$TableName.getDefaultInstance:()Lorg/apache/hadoop/hbase/shaded/protobuf/generated/HBaseProtos$TableName;
      28: goto          35
      31: aload_0
      32: getfield      #13                 // Field tableName_:Lorg/apache/hadoop/hbase/shaded/protobuf/generated/HBaseProtos$TableName;
      35: areturn

  public boolean hasRemoveAll();
    Code:
       0: aload_0
       1: getfield      #24                 // Field bitField0_:I
       4: bipush        16
       6: iand
       7: bipush        16
       9: if_icmpne     16
      12: iconst_1
      13: goto          17
      16: iconst_0
      17: ireturn

  public boolean getRemoveAll();
    Code:
       0: aload_0
       1: getfield      #27                 // Field removeAll_:Z
       4: ireturn

  public org.apache.hadoop.hbase.shaded.protobuf.generated.MasterProtos$SetQuotaRequest$Builder setRemoveAll(boolean);
    Code:
       0: aload_0
       1: dup
       2: getfield      #24                 // Field bitField0_:I
       5: bipush        16
       7: ior
       8: putfield      #24                 // Field bitField0_:I
      11: aload_0
      12: iload_1
      13: putfield      #27                 // Field removeAll_:Z
      16: aload_0
      17: invokevirtual #61                 // Method onChanged:()V
      20: aload_0
      21: areturn

  public org.apache.hadoop.hbase.shaded.protobuf.generated.MasterProtos$SetQuotaRequest$Builder clearRemoveAll();
    Code:
       0: aload_0
       1: aload_0
       2: getfield      #24                 // Field bitField0_:I
       5: bipush        -17
       7: iand
       8: putfield      #24                 // Field bitField0_:I
      11: aload_0
      12: iconst_0
      13: putfield      #27                 // Field removeAll_:Z
      16: aload_0
      17: invokevirtual #61                 // Method onChanged:()V
      20: aload_0
      21: areturn

  public boolean hasBypassGlobals();
    Code:
       0: aload_0
       1: getfield      #24                 // Field bitField0_:I
       4: bipush        32
       6: iand
       7: bipush        32
       9: if_icmpne     16
      12: iconst_1
      13: goto          17
      16: iconst_0
      17: ireturn

  public boolean getBypassGlobals();
    Code:
       0: aload_0
       1: getfield      #28                 // Field bypassGlobals_:Z
       4: ireturn

  public org.apache.hadoop.hbase.shaded.protobuf.generated.MasterProtos$SetQuotaRequest$Builder setBypassGlobals(boolean);
    Code:
       0: aload_0
       1: dup
       2: getfield      #24                 // Field bitField0_:I
       5: bipush        32
       7: ior
       8: putfield      #24                 // Field bitField0_:I
      11: aload_0
      12: iload_1
      13: putfield      #28                 // Field bypassGlobals_:Z
      16: aload_0
      17: invokevirtual #61                 // Method onChanged:()V
      20: aload_0
      21: areturn

  public org.apache.hadoop.hbase.shaded.protobuf.generated.MasterProtos$SetQuotaRequest$Builder clearBypassGlobals();
    Code:
       0: aload_0
       1: aload_0
       2: getfield      #24                 // Field bitField0_:I
       5: bipush        -33
       7: iand
       8: putfield      #24                 // Field bitField0_:I
      11: aload_0
      12: iconst_0
      13: putfield      #28                 // Field bypassGlobals_:Z
      16: aload_0
      17: invokevirtual #61                 // Method onChanged:()V
      20: aload_0
      21: areturn

  public boolean hasThrottle();
    Code:
       0: aload_0
       1: getfield      #24                 // Field bitField0_:I
       4: bipush        64
       6: iand
       7: bipush        64
       9: if_icmpne     16
      12: iconst_1
      13: goto          17
      16: iconst_0
      17: ireturn

  public org.apache.hadoop.hbase.shaded.protobuf.generated.QuotaProtos$ThrottleRequest getThrottle();
    Code:
       0: aload_0
       1: getfield      #29                 // Field throttleBuilder_:Lorg/apache/hbase/thirdparty/com/google/protobuf/SingleFieldBuilderV3;
       4: ifnonnull     25
       7: aload_0
       8: getfield      #14                 // Field throttle_:Lorg/apache/hadoop/hbase/shaded/protobuf/generated/QuotaProtos$ThrottleRequest;
      11: ifnonnull     20
      14: invokestatic  #122                // Method org/apache/hadoop/hbase/shaded/protobuf/generated/QuotaProtos$ThrottleRequest.getDefaultInstance:()Lorg/apache/hadoop/hbase/shaded/protobuf/generated/QuotaProtos$ThrottleRequest;
      17: goto          24
      20: aload_0
      21: getfield      #14                 // Field throttle_:Lorg/apache/hadoop/hbase/shaded/protobuf/generated/QuotaProtos$ThrottleRequest;
      24: areturn
      25: aload_0
      26: getfield      #29                 // Field throttleBuilder_:Lorg/apache/hbase/thirdparty/com/google/protobuf/SingleFieldBuilderV3;
      29: invokevirtual #107                // Method org/apache/hbase/thirdparty/com/google/protobuf/SingleFieldBuilderV3.getMessage:()Lorg/apache/hbase/thirdparty/com/google/protobuf/AbstractMessage;
      32: checkcast     #45                 // class org/apache/hadoop/hbase/shaded/protobuf/generated/QuotaProtos$ThrottleRequest
      35: areturn

  public org.apache.hadoop.hbase.shaded.protobuf.generated.MasterProtos$SetQuotaRequest$Builder setThrottle(org.apache.hadoop.hbase.shaded.protobuf.generated.QuotaProtos$ThrottleRequest);
    Code:
       0: aload_0
       1: getfield      #29                 // Field throttleBuilder_:Lorg/apache/hbase/thirdparty/com/google/protobuf/SingleFieldBuilderV3;
       4: ifnonnull     31
       7: aload_1
       8: ifnonnull     19
      11: new           #101                // class java/lang/NullPointerException
      14: dup
      15: invokespecial #102                // Method java/lang/NullPointerException."<init>":()V
      18: athrow
      19: aload_0
      20: aload_1
      21: putfield      #14                 // Field throttle_:Lorg/apache/hadoop/hbase/shaded/protobuf/generated/QuotaProtos$ThrottleRequest;
      24: aload_0
      25: invokevirtual #61                 // Method onChanged:()V
      28: goto          40
      31: aload_0
      32: getfield      #29                 // Field throttleBuilder_:Lorg/apache/hbase/thirdparty/com/google/protobuf/SingleFieldBuilderV3;
      35: aload_1
      36: invokevirtual #108                // Method org/apache/hbase/thirdparty/com/google/protobuf/SingleFieldBuilderV3.setMessage:(Lorg/apache/hbase/thirdparty/com/google/protobuf/AbstractMessage;)Lorg/apache/hbase/thirdparty/com/google/protobuf/SingleFieldBuilderV3;
      39: pop
      40: aload_0
      41: dup
      42: getfield      #24                 // Field bitField0_:I
      45: bipush        64
      47: ior
      48: putfield      #24                 // Field bitField0_:I
      51: aload_0
      52: areturn

  public org.apache.hadoop.hbase.shaded.protobuf.generated.MasterProtos$SetQuotaRequest$Builder setThrottle(org.apache.hadoop.hbase.shaded.protobuf.generated.QuotaProtos$ThrottleRequest$Builder);
    Code:
       0: aload_0
       1: getfield      #29                 // Field throttleBuilder_:Lorg/apache/hbase/thirdparty/com/google/protobuf/SingleFieldBuilderV3;
       4: ifnonnull     22
       7: aload_0
       8: aload_1
       9: invokevirtual #123                // Method org/apache/hadoop/hbase/shaded/protobuf/generated/QuotaProtos$ThrottleRequest$Builder.build:()Lorg/apache/hadoop/hbase/shaded/protobuf/generated/QuotaProtos$ThrottleRequest;
      12: putfield      #14                 // Field throttle_:Lorg/apache/hadoop/hbase/shaded/protobuf/generated/QuotaProtos$ThrottleRequest;
      15: aload_0
      16: invokevirtual #61                 // Method onChanged:()V
      19: goto          34
      22: aload_0
      23: getfield      #29                 // Field throttleBuilder_:Lorg/apache/hbase/thirdparty/com/google/protobuf/SingleFieldBuilderV3;
      26: aload_1
      27: invokevirtual #123                // Method org/apache/hadoop/hbase/shaded/protobuf/generated/QuotaProtos$ThrottleRequest$Builder.build:()Lorg/apache/hadoop/hbase/shaded/protobuf/generated/QuotaProtos$ThrottleRequest;
      30: invokevirtual #108                // Method org/apache/hbase/thirdparty/com/google/protobuf/SingleFieldBuilderV3.setMessage:(Lorg/apache/hbase/thirdparty/com/google/protobuf/AbstractMessage;)Lorg/apache/hbase/thirdparty/com/google/protobuf/SingleFieldBuilderV3;
      33: pop
      34: aload_0
      35: dup
      36: getfield      #24                 // Field bitField0_:I
      39: bipush        64
      41: ior
      42: putfield      #24                 // Field bitField0_:I
      45: aload_0
      46: areturn

  public org.apache.hadoop.hbase.shaded.protobuf.generated.MasterProtos$SetQuotaRequest$Builder mergeThrottle(org.apache.hadoop.hbase.shaded.protobuf.generated.QuotaProtos$ThrottleRequest);
    Code:
       0: aload_0
       1: getfield      #29                 // Field throttleBuilder_:Lorg/apache/hbase/thirdparty/com/google/protobuf/SingleFieldBuilderV3;
       4: ifnonnull     69
       7: aload_0
       8: getfield      #24                 // Field bitField0_:I
      11: bipush        64
      13: iand
      14: bipush        64
      16: if_icmpne     57
      19: aload_0
      20: getfield      #14                 // Field throttle_:Lorg/apache/hadoop/hbase/shaded/protobuf/generated/QuotaProtos$ThrottleRequest;
      23: ifnull        57
      26: aload_0
      27: getfield      #14                 // Field throttle_:Lorg/apache/hadoop/hbase/shaded/protobuf/generated/QuotaProtos$ThrottleRequest;
      30: invokestatic  #122                // Method org/apache/hadoop/hbase/shaded/protobuf/generated/QuotaProtos$ThrottleRequest.getDefaultInstance:()Lorg/apache/hadoop/hbase/shaded/protobuf/generated/QuotaProtos$ThrottleRequest;
      33: if_acmpeq     57
      36: aload_0
      37: aload_0
      38: getfield      #14                 // Field throttle_:Lorg/apache/hadoop/hbase/shaded/protobuf/generated/QuotaProtos$ThrottleRequest;
      41: invokestatic  #124                // Method org/apache/hadoop/hbase/shaded/protobuf/generated/QuotaProtos$ThrottleRequest.newBuilder:(Lorg/apache/hadoop/hbase/shaded/protobuf/generated/QuotaProtos$ThrottleRequest;)Lorg/apache/hadoop/hbase/shaded/protobuf/generated/QuotaProtos$ThrottleRequest$Builder;
      44: aload_1
      45: invokevirtual #125                // Method org/apache/hadoop/hbase/shaded/protobuf/generated/QuotaProtos$ThrottleRequest$Builder.mergeFrom:(Lorg/apache/hadoop/hbase/shaded/protobuf/generated/QuotaProtos$ThrottleRequest;)Lorg/apache/hadoop/hbase/shaded/protobuf/generated/QuotaProtos$ThrottleRequest$Builder;
      48: invokevirtual #126                // Method org/apache/hadoop/hbase/shaded/protobuf/generated/QuotaProtos$ThrottleRequest$Builder.buildPartial:()Lorg/apache/hadoop/hbase/shaded/protobuf/generated/QuotaProtos$ThrottleRequest;
      51: putfield      #14                 // Field throttle_:Lorg/apache/hadoop/hbase/shaded/protobuf/generated/QuotaProtos$ThrottleRequest;
      54: goto          62
      57: aload_0
      58: aload_1
      59: putfield      #14                 // Field throttle_:Lorg/apache/hadoop/hbase/shaded/protobuf/generated/QuotaProtos$ThrottleRequest;
      62: aload_0
      63: invokevirtual #61                 // Method onChanged:()V
      66: goto          78
      69: aload_0
      70: getfield      #29                 // Field throttleBuilder_:Lorg/apache/hbase/thirdparty/com/google/protobuf/SingleFieldBuilderV3;
      73: aload_1
      74: invokevirtual #113                // Method org/apache/hbase/thirdparty/com/google/protobuf/SingleFieldBuilderV3.mergeFrom:(Lorg/apache/hbase/thirdparty/com/google/protobuf/AbstractMessage;)Lorg/apache/hbase/thirdparty/com/google/protobuf/SingleFieldBuilderV3;
      77: pop
      78: aload_0
      79: dup
      80: getfield      #24                 // Field bitField0_:I
      83: bipush        64
      85: ior
      86: putfield      #24                 // Field bitField0_:I
      89: aload_0
      90: areturn

  public org.apache.hadoop.hbase.shaded.protobuf.generated.MasterProtos$SetQuotaRequest$Builder clearThrottle();
    Code:
       0: aload_0
       1: getfield      #29                 // Field throttleBuilder_:Lorg/apache/hbase/thirdparty/com/google/protobuf/SingleFieldBuilderV3;
       4: ifnonnull     19
       7: aload_0
       8: aconst_null
       9: putfield      #14                 // Field throttle_:Lorg/apache/hadoop/hbase/shaded/protobuf/generated/QuotaProtos$ThrottleRequest;
      12: aload_0
      13: invokevirtual #61                 // Method onChanged:()V
      16: goto          27
      19: aload_0
      20: getfield      #29                 // Field throttleBuilder_:Lorg/apache/hbase/thirdparty/com/google/protobuf/SingleFieldBuilderV3;
      23: invokevirtual #26                 // Method org/apache/hbase/thirdparty/com/google/protobuf/SingleFieldBuilderV3.clear:()Lorg/apache/hbase/thirdparty/com/google/protobuf/SingleFieldBuilderV3;
      26: pop
      27: aload_0
      28: aload_0
      29: getfield      #24                 // Field bitField0_:I
      32: bipush        -65
      34: iand
      35: putfield      #24                 // Field bitField0_:I
      38: aload_0
      39: areturn

  public org.apache.hadoop.hbase.shaded.protobuf.generated.QuotaProtos$ThrottleRequest$Builder getThrottleBuilder();
    Code:
       0: aload_0
       1: dup
       2: getfield      #24                 // Field bitField0_:I
       5: bipush        64
       7: ior
       8: putfield      #24                 // Field bitField0_:I
      11: aload_0
      12: invokevirtual #61                 // Method onChanged:()V
      15: aload_0
      16: invokespecial #21                 // Method getThrottleFieldBuilder:()Lorg/apache/hbase/thirdparty/com/google/protobuf/SingleFieldBuilderV3;
      19: invokevirtual #114                // Method org/apache/hbase/thirdparty/com/google/protobuf/SingleFieldBuilderV3.getBuilder:()Lorg/apache/hbase/thirdparty/com/google/protobuf/AbstractMessage$Builder;
      22: checkcast     #127                // class org/apache/hadoop/hbase/shaded/protobuf/generated/QuotaProtos$ThrottleRequest$Builder
      25: areturn

  public org.apache.hadoop.hbase.shaded.protobuf.generated.QuotaProtos$ThrottleRequestOrBuilder getThrottleOrBuilder();
    Code:
       0: aload_0
       1: getfield      #29                 // Field throttleBuilder_:Lorg/apache/hbase/thirdparty/com/google/protobuf/SingleFieldBuilderV3;
       4: ifnull        18
       7: aload_0
       8: getfield      #29                 // Field throttleBuilder_:Lorg/apache/hbase/thirdparty/com/google/protobuf/SingleFieldBuilderV3;
      11: invokevirtual #116                // Method org/apache/hbase/thirdparty/com/google/protobuf/SingleFieldBuilderV3.getMessageOrBuilder:()Lorg/apache/hbase/thirdparty/com/google/protobuf/MessageOrBuilder;
      14: checkcast     #128                // class org/apache/hadoop/hbase/shaded/protobuf/generated/QuotaProtos$ThrottleRequestOrBuilder
      17: areturn
      18: aload_0
      19: getfield      #14                 // Field throttle_:Lorg/apache/hadoop/hbase/shaded/protobuf/generated/QuotaProtos$ThrottleRequest;
      22: ifnonnull     31
      25: invokestatic  #122                // Method org/apache/hadoop/hbase/shaded/protobuf/generated/QuotaProtos$ThrottleRequest.getDefaultInstance:()Lorg/apache/hadoop/hbase/shaded/protobuf/generated/QuotaProtos$ThrottleRequest;
      28: goto          35
      31: aload_0
      32: getfield      #14                 // Field throttle_:Lorg/apache/hadoop/hbase/shaded/protobuf/generated/QuotaProtos$ThrottleRequest;
      35: areturn

  public boolean hasSpaceLimit();
    Code:
       0: aload_0
       1: getfield      #24                 // Field bitField0_:I
       4: sipush        128
       7: iand
       8: sipush        128
      11: if_icmpne     18
      14: iconst_1
      15: goto          19
      18: iconst_0
      19: ireturn

  public org.apache.hadoop.hbase.shaded.protobuf.generated.QuotaProtos$SpaceLimitRequest getSpaceLimit();
    Code:
       0: aload_0
       1: getfield      #30                 // Field spaceLimitBuilder_:Lorg/apache/hbase/thirdparty/com/google/protobuf/SingleFieldBuilderV3;
       4: ifnonnull     25
       7: aload_0
       8: getfield      #15                 // Field spaceLimit_:Lorg/apache/hadoop/hbase/shaded/protobuf/generated/QuotaProtos$SpaceLimitRequest;
      11: ifnonnull     20
      14: invokestatic  #129                // Method org/apache/hadoop/hbase/shaded/protobuf/generated/QuotaProtos$SpaceLimitRequest.getDefaultInstance:()Lorg/apache/hadoop/hbase/shaded/protobuf/generated/QuotaProtos$SpaceLimitRequest;
      17: goto          24
      20: aload_0
      21: getfield      #15                 // Field spaceLimit_:Lorg/apache/hadoop/hbase/shaded/protobuf/generated/QuotaProtos$SpaceLimitRequest;
      24: areturn
      25: aload_0
      26: getfield      #30                 // Field spaceLimitBuilder_:Lorg/apache/hbase/thirdparty/com/google/protobuf/SingleFieldBuilderV3;
      29: invokevirtual #107                // Method org/apache/hbase/thirdparty/com/google/protobuf/SingleFieldBuilderV3.getMessage:()Lorg/apache/hbase/thirdparty/com/google/protobuf/AbstractMessage;
      32: checkcast     #47                 // class org/apache/hadoop/hbase/shaded/protobuf/generated/QuotaProtos$SpaceLimitRequest
      35: areturn

  public org.apache.hadoop.hbase.shaded.protobuf.generated.MasterProtos$SetQuotaRequest$Builder setSpaceLimit(org.apache.hadoop.hbase.shaded.protobuf.generated.QuotaProtos$SpaceLimitRequest);
    Code:
       0: aload_0
       1: getfield      #30                 // Field spaceLimitBuilder_:Lorg/apache/hbase/thirdparty/com/google/protobuf/SingleFieldBuilderV3;
       4: ifnonnull     31
       7: aload_1
       8: ifnonnull     19
      11: new           #101                // class java/lang/NullPointerException
      14: dup
      15: invokespecial #102                // Method java/lang/NullPointerException."<init>":()V
      18: athrow
      19: aload_0
      20: aload_1
      21: putfield      #15                 // Field spaceLimit_:Lorg/apache/hadoop/hbase/shaded/protobuf/generated/QuotaProtos$SpaceLimitRequest;
      24: aload_0
      25: invokevirtual #61                 // Method onChanged:()V
      28: goto          40
      31: aload_0
      32: getfield      #30                 // Field spaceLimitBuilder_:Lorg/apache/hbase/thirdparty/com/google/protobuf/SingleFieldBuilderV3;
      35: aload_1
      36: invokevirtual #108                // Method org/apache/hbase/thirdparty/com/google/protobuf/SingleFieldBuilderV3.setMessage:(Lorg/apache/hbase/thirdparty/com/google/protobuf/AbstractMessage;)Lorg/apache/hbase/thirdparty/com/google/protobuf/SingleFieldBuilderV3;
      39: pop
      40: aload_0
      41: dup
      42: getfield      #24                 // Field bitField0_:I
      45: sipush        128
      48: ior
      49: putfield      #24                 // Field bitField0_:I
      52: aload_0
      53: areturn

  public org.apache.hadoop.hbase.shaded.protobuf.generated.MasterProtos$SetQuotaRequest$Builder setSpaceLimit(org.apache.hadoop.hbase.shaded.protobuf.generated.QuotaProtos$SpaceLimitRequest$Builder);
    Code:
       0: aload_0
       1: getfield      #30                 // Field spaceLimitBuilder_:Lorg/apache/hbase/thirdparty/com/google/protobuf/SingleFieldBuilderV3;
       4: ifnonnull     22
       7: aload_0
       8: aload_1
       9: invokevirtual #130                // Method org/apache/hadoop/hbase/shaded/protobuf/generated/QuotaProtos$SpaceLimitRequest$Builder.build:()Lorg/apache/hadoop/hbase/shaded/protobuf/generated/QuotaProtos$SpaceLimitRequest;
      12: putfield      #15                 // Field spaceLimit_:Lorg/apache/hadoop/hbase/shaded/protobuf/generated/QuotaProtos$SpaceLimitRequest;
      15: aload_0
      16: invokevirtual #61                 // Method onChanged:()V
      19: goto          34
      22: aload_0
      23: getfield      #30                 // Field spaceLimitBuilder_:Lorg/apache/hbase/thirdparty/com/google/protobuf/SingleFieldBuilderV3;
      26: aload_1
      27: invokevirtual #130                // Method org/apache/hadoop/hbase/shaded/protobuf/generated/QuotaProtos$SpaceLimitRequest$Builder.build:()Lorg/apache/hadoop/hbase/shaded/protobuf/generated/QuotaProtos$SpaceLimitRequest;
      30: invokevirtual #108                // Method org/apache/hbase/thirdparty/com/google/protobuf/SingleFieldBuilderV3.setMessage:(Lorg/apache/hbase/thirdparty/com/google/protobuf/AbstractMessage;)Lorg/apache/hbase/thirdparty/com/google/protobuf/SingleFieldBuilderV3;
      33: pop
      34: aload_0
      35: dup
      36: getfield      #24                 // Field bitField0_:I
      39: sipush        128
      42: ior
      43: putfield      #24                 // Field bitField0_:I
      46: aload_0
      47: areturn

  public org.apache.hadoop.hbase.shaded.protobuf.generated.MasterProtos$SetQuotaRequest$Builder mergeSpaceLimit(org.apache.hadoop.hbase.shaded.protobuf.generated.QuotaProtos$SpaceLimitRequest);
    Code:
       0: aload_0
       1: getfield      #30                 // Field spaceLimitBuilder_:Lorg/apache/hbase/thirdparty/com/google/protobuf/SingleFieldBuilderV3;
       4: ifnonnull     71
       7: aload_0
       8: getfield      #24                 // Field bitField0_:I
      11: sipush        128
      14: iand
      15: sipush        128
      18: if_icmpne     59
      21: aload_0
      22: getfield      #15                 // Field spaceLimit_:Lorg/apache/hadoop/hbase/shaded/protobuf/generated/QuotaProtos$SpaceLimitRequest;
      25: ifnull        59
      28: aload_0
      29: getfield      #15                 // Field spaceLimit_:Lorg/apache/hadoop/hbase/shaded/protobuf/generated/QuotaProtos$SpaceLimitRequest;
      32: invokestatic  #129                // Method org/apache/hadoop/hbase/shaded/protobuf/generated/QuotaProtos$SpaceLimitRequest.getDefaultInstance:()Lorg/apache/hadoop/hbase/shaded/protobuf/generated/QuotaProtos$SpaceLimitRequest;
      35: if_acmpeq     59
      38: aload_0
      39: aload_0
      40: getfield      #15                 // Field spaceLimit_:Lorg/apache/hadoop/hbase/shaded/protobuf/generated/QuotaProtos$SpaceLimitRequest;
      43: invokestatic  #131                // Method org/apache/hadoop/hbase/shaded/protobuf/generated/QuotaProtos$SpaceLimitRequest.newBuilder:(Lorg/apache/hadoop/hbase/shaded/protobuf/generated/QuotaProtos$SpaceLimitRequest;)Lorg/apache/hadoop/hbase/shaded/protobuf/generated/QuotaProtos$SpaceLimitRequest$Builder;
      46: aload_1
      47: invokevirtual #132                // Method org/apache/hadoop/hbase/shaded/protobuf/generated/QuotaProtos$SpaceLimitRequest$Builder.mergeFrom:(Lorg/apache/hadoop/hbase/shaded/protobuf/generated/QuotaProtos$SpaceLimitRequest;)Lorg/apache/hadoop/hbase/shaded/protobuf/generated/QuotaProtos$SpaceLimitRequest$Builder;
      50: invokevirtual #133                // Method org/apache/hadoop/hbase/shaded/protobuf/generated/QuotaProtos$SpaceLimitRequest$Builder.buildPartial:()Lorg/apache/hadoop/hbase/shaded/protobuf/generated/QuotaProtos$SpaceLimitRequest;
      53: putfield      #15                 // Field spaceLimit_:Lorg/apache/hadoop/hbase/shaded/protobuf/generated/QuotaProtos$SpaceLimitRequest;
      56: goto          64
      59: aload_0
      60: aload_1
      61: putfield      #15                 // Field spaceLimit_:Lorg/apache/hadoop/hbase/shaded/protobuf/generated/QuotaProtos$SpaceLimitRequest;
      64: aload_0
      65: invokevirtual #61                 // Method onChanged:()V
      68: goto          80
      71: aload_0
      72: getfield      #30                 // Field spaceLimitBuilder_:Lorg/apache/hbase/thirdparty/com/google/protobuf/SingleFieldBuilderV3;
      75: aload_1
      76: invokevirtual #113                // Method org/apache/hbase/thirdparty/com/google/protobuf/SingleFieldBuilderV3.mergeFrom:(Lorg/apache/hbase/thirdparty/com/google/protobuf/AbstractMessage;)Lorg/apache/hbase/thirdparty/com/google/protobuf/SingleFieldBuilderV3;
      79: pop
      80: aload_0
      81: dup
      82: getfield      #24                 // Field bitField0_:I
      85: sipush        128
      88: ior
      89: putfield      #24                 // Field bitField0_:I
      92: aload_0
      93: areturn

  public org.apache.hadoop.hbase.shaded.protobuf.generated.MasterProtos$SetQuotaRequest$Builder clearSpaceLimit();
    Code:
       0: aload_0
       1: getfield      #30                 // Field spaceLimitBuilder_:Lorg/apache/hbase/thirdparty/com/google/protobuf/SingleFieldBuilderV3;
       4: ifnonnull     19
       7: aload_0
       8: aconst_null
       9: putfield      #15                 // Field spaceLimit_:Lorg/apache/hadoop/hbase/shaded/protobuf/generated/QuotaProtos$SpaceLimitRequest;
      12: aload_0
      13: invokevirtual #61                 // Method onChanged:()V
      16: goto          27
      19: aload_0
      20: getfield      #30                 // Field spaceLimitBuilder_:Lorg/apache/hbase/thirdparty/com/google/protobuf/SingleFieldBuilderV3;
      23: invokevirtual #26                 // Method org/apache/hbase/thirdparty/com/google/protobuf/SingleFieldBuilderV3.clear:()Lorg/apache/hbase/thirdparty/com/google/protobuf/SingleFieldBuilderV3;
      26: pop
      27: aload_0
      28: aload_0
      29: getfield      #24                 // Field bitField0_:I
      32: sipush        -129
      35: iand
      36: putfield      #24                 // Field bitField0_:I
      39: aload_0
      40: areturn

  public org.apache.hadoop.hbase.shaded.protobuf.generated.QuotaProtos$SpaceLimitRequest$Builder getSpaceLimitBuilder();
    Code:
       0: aload_0
       1: dup
       2: getfield      #24                 // Field bitField0_:I
       5: sipush        128
       8: ior
       9: putfield      #24                 // Field bitField0_:I
      12: aload_0
      13: invokevirtual #61                 // Method onChanged:()V
      16: aload_0
      17: invokespecial #22                 // Method getSpaceLimitFieldBuilder:()Lorg/apache/hbase/thirdparty/com/google/protobuf/SingleFieldBuilderV3;
      20: invokevirtual #114                // Method org/apache/hbase/thirdparty/com/google/protobuf/SingleFieldBuilderV3.getBuilder:()Lorg/apache/hbase/thirdparty/com/google/protobuf/AbstractMessage$Builder;
      23: checkcast     #134                // class org/apache/hadoop/hbase/shaded/protobuf/generated/QuotaProtos$SpaceLimitRequest$Builder
      26: areturn

  public org.apache.hadoop.hbase.shaded.protobuf.generated.QuotaProtos$SpaceLimitRequestOrBuilder getSpaceLimitOrBuilder();
    Code:
       0: aload_0
       1: getfield      #30                 // Field spaceLimitBuilder_:Lorg/apache/hbase/thirdparty/com/google/protobuf/SingleFieldBuilderV3;
       4: ifnull        18
       7: aload_0
       8: getfield      #30                 // Field spaceLimitBuilder_:Lorg/apache/hbase/thirdparty/com/google/protobuf/SingleFieldBuilderV3;
      11: invokevirtual #116                // Method org/apache/hbase/thirdparty/com/google/protobuf/SingleFieldBuilderV3.getMessageOrBuilder:()Lorg/apache/hbase/thirdparty/com/google/protobuf/MessageOrBuilder;
      14: checkcast     #135                // class org/apache/hadoop/hbase/shaded/protobuf/generated/QuotaProtos$SpaceLimitRequestOrBuilder
      17: areturn
      18: aload_0
      19: getfield      #15                 // Field spaceLimit_:Lorg/apache/hadoop/hbase/shaded/protobuf/generated/QuotaProtos$SpaceLimitRequest;
      22: ifnonnull     31
      25: invokestatic  #129                // Method org/apache/hadoop/hbase/shaded/protobuf/generated/QuotaProtos$SpaceLimitRequest.getDefaultInstance:()Lorg/apache/hadoop/hbase/shaded/protobuf/generated/QuotaProtos$SpaceLimitRequest;
      28: goto          35
      31: aload_0
      32: getfield      #15                 // Field spaceLimit_:Lorg/apache/hadoop/hbase/shaded/protobuf/generated/QuotaProtos$SpaceLimitRequest;
      35: areturn

  public boolean hasRegionServer();
    Code:
       0: aload_0
       1: getfield      #24                 // Field bitField0_:I
       4: sipush        256
       7: iand
       8: sipush        256
      11: if_icmpne     18
      14: iconst_1
      15: goto          19
      18: iconst_0
      19: ireturn

  public java.lang.String getRegionServer();
    Code:
       0: aload_0
       1: getfield      #16                 // Field regionServer_:Ljava/lang/Object;
       4: astore_1
       5: aload_1
       6: instanceof    #96                 // class java/lang/String
       9: ifne          36
      12: aload_1
      13: checkcast     #97                 // class org/apache/hbase/thirdparty/com/google/protobuf/ByteString
      16: astore_2
      17: aload_2
      18: invokevirtual #98                 // Method org/apache/hbase/thirdparty/com/google/protobuf/ByteString.toStringUtf8:()Ljava/lang/String;
      21: astore_3
      22: aload_2
      23: invokevirtual #99                 // Method org/apache/hbase/thirdparty/com/google/protobuf/ByteString.isValidUtf8:()Z
      26: ifeq          34
      29: aload_0
      30: aload_3
      31: putfield      #16                 // Field regionServer_:Ljava/lang/Object;
      34: aload_3
      35: areturn
      36: aload_1
      37: checkcast     #96                 // class java/lang/String
      40: areturn

  public org.apache.hbase.thirdparty.com.google.protobuf.ByteString getRegionServerBytes();
    Code:
       0: aload_0
       1: getfield      #16                 // Field regionServer_:Ljava/lang/Object;
       4: astore_1
       5: aload_1
       6: instanceof    #96                 // class java/lang/String
       9: ifeq          27
      12: aload_1
      13: checkcast     #96                 // class java/lang/String
      16: invokestatic  #100                // Method org/apache/hbase/thirdparty/com/google/protobuf/ByteString.copyFromUtf8:(Ljava/lang/String;)Lorg/apache/hbase/thirdparty/com/google/protobuf/ByteString;
      19: astore_2
      20: aload_0
      21: aload_2
      22: putfield      #16                 // Field regionServer_:Ljava/lang/Object;
      25: aload_2
      26: areturn
      27: aload_1
      28: checkcast     #97                 // class org/apache/hbase/thirdparty/com/google/protobuf/ByteString
      31: areturn

  public org.apache.hadoop.hbase.shaded.protobuf.generated.MasterProtos$SetQuotaRequest$Builder setRegionServer(java.lang.String);
    Code:
       0: aload_1
       1: ifnonnull     12
       4: new           #101                // class java/lang/NullPointerException
       7: dup
       8: invokespecial #102                // Method java/lang/NullPointerException."<init>":()V
      11: athrow
      12: aload_0
      13: dup
      14: getfield      #24                 // Field bitField0_:I
      17: sipush        256
      20: ior
      21: putfield      #24                 // Field bitField0_:I
      24: aload_0
      25: aload_1
      26: putfield      #16                 // Field regionServer_:Ljava/lang/Object;
      29: aload_0
      30: invokevirtual #61                 // Method onChanged:()V
      33: aload_0
      34: areturn

  public org.apache.hadoop.hbase.shaded.protobuf.generated.MasterProtos$SetQuotaRequest$Builder clearRegionServer();
    Code:
       0: aload_0
       1: aload_0
       2: getfield      #24                 // Field bitField0_:I
       5: sipush        -257
       8: iand
       9: putfield      #24                 // Field bitField0_:I
      12: aload_0
      13: invokestatic  #31                 // Method org/apache/hadoop/hbase/shaded/protobuf/generated/MasterProtos$SetQuotaRequest.getDefaultInstance:()Lorg/apache/hadoop/hbase/shaded/protobuf/generated/MasterProtos$SetQuotaRequest;
      16: invokevirtual #137                // Method org/apache/hadoop/hbase/shaded/protobuf/generated/MasterProtos$SetQuotaRequest.getRegionServer:()Ljava/lang/String;
      19: putfield      #16                 // Field regionServer_:Ljava/lang/Object;
      22: aload_0
      23: invokevirtual #61                 // Method onChanged:()V
      26: aload_0
      27: areturn

  public org.apache.hadoop.hbase.shaded.protobuf.generated.MasterProtos$SetQuotaRequest$Builder setRegionServerBytes(org.apache.hbase.thirdparty.com.google.protobuf.ByteString);
    Code:
       0: aload_1
       1: ifnonnull     12
       4: new           #101                // class java/lang/NullPointerException
       7: dup
       8: invokespecial #102                // Method java/lang/NullPointerException."<init>":()V
      11: athrow
      12: aload_0
      13: dup
      14: getfield      #24                 // Field bitField0_:I
      17: sipush        256
      20: ior
      21: putfield      #24                 // Field bitField0_:I
      24: aload_0
      25: aload_1
      26: putfield      #16                 // Field regionServer_:Ljava/lang/Object;
      29: aload_0
      30: invokevirtual #61                 // Method onChanged:()V
      33: aload_0
      34: areturn

  public final org.apache.hadoop.hbase.shaded.protobuf.generated.MasterProtos$SetQuotaRequest$Builder setUnknownFields(org.apache.hbase.thirdparty.com.google.protobuf.UnknownFieldSet);
    Code:
       0: aload_0
       1: aload_1
       2: invokespecial #138                // Method org/apache/hbase/thirdparty/com/google/protobuf/GeneratedMessageV3$Builder.setUnknownFields:(Lorg/apache/hbase/thirdparty/com/google/protobuf/UnknownFieldSet;)Lorg/apache/hbase/thirdparty/com/google/protobuf/GeneratedMessageV3$Builder;
       5: checkcast     #6                  // class org/apache/hadoop/hbase/shaded/protobuf/generated/MasterProtos$SetQuotaRequest$Builder
       8: areturn

  public final org.apache.hadoop.hbase.shaded.protobuf.generated.MasterProtos$SetQuotaRequest$Builder mergeUnknownFields(org.apache.hbase.thirdparty.com.google.protobuf.UnknownFieldSet);
    Code:
       0: aload_0
       1: aload_1
       2: invokespecial #139                // Method org/apache/hbase/thirdparty/com/google/protobuf/GeneratedMessageV3$Builder.mergeUnknownFields:(Lorg/apache/hbase/thirdparty/com/google/protobuf/UnknownFieldSet;)Lorg/apache/hbase/thirdparty/com/google/protobuf/GeneratedMessageV3$Builder;
       5: checkcast     #6                  // class org/apache/hadoop/hbase/shaded/protobuf/generated/MasterProtos$SetQuotaRequest$Builder
       8: areturn

  public org.apache.hbase.thirdparty.com.google.protobuf.GeneratedMessageV3$Builder mergeUnknownFields(org.apache.hbase.thirdparty.com.google.protobuf.UnknownFieldSet);
    Code:
       0: aload_0
       1: aload_1
       2: invokevirtual #84                 // Method mergeUnknownFields:(Lorg/apache/hbase/thirdparty/com/google/protobuf/UnknownFieldSet;)Lorg/apache/hadoop/hbase/shaded/protobuf/generated/MasterProtos$SetQuotaRequest$Builder;
       5: areturn

  public org.apache.hbase.thirdparty.com.google.protobuf.GeneratedMessageV3$Builder setUnknownFields(org.apache.hbase.thirdparty.com.google.protobuf.UnknownFieldSet);
    Code:
       0: aload_0
       1: aload_1
       2: invokevirtual #140                // Method setUnknownFields:(Lorg/apache/hbase/thirdparty/com/google/protobuf/UnknownFieldSet;)Lorg/apache/hadoop/hbase/shaded/protobuf/generated/MasterProtos$SetQuotaRequest$Builder;
       5: areturn

  public org.apache.hbase.thirdparty.com.google.protobuf.GeneratedMessageV3$Builder addRepeatedField(org.apache.hbase.thirdparty.com.google.protobuf.Descriptors$FieldDescriptor, java.lang.Object);
    Code:
       0: aload_0
       1: aload_1
       2: aload_2
       3: invokevirtual #141                // Method addRepeatedField:(Lorg/apache/hbase/thirdparty/com/google/protobuf/Descriptors$FieldDescriptor;Ljava/lang/Object;)Lorg/apache/hadoop/hbase/shaded/protobuf/generated/MasterProtos$SetQuotaRequest$Builder;
       6: areturn

  public org.apache.hbase.thirdparty.com.google.protobuf.GeneratedMessageV3$Builder setRepeatedField(org.apache.hbase.thirdparty.com.google.protobuf.Descriptors$FieldDescriptor, int, java.lang.Object);
    Code:
       0: aload_0
       1: aload_1
       2: iload_2
       3: aload_3
       4: invokevirtual #142                // Method setRepeatedField:(Lorg/apache/hbase/thirdparty/com/google/protobuf/Descriptors$FieldDescriptor;ILjava/lang/Object;)Lorg/apache/hadoop/hbase/shaded/protobuf/generated/MasterProtos$SetQuotaRequest$Builder;
       7: areturn

  public org.apache.hbase.thirdparty.com.google.protobuf.GeneratedMessageV3$Builder clearOneof(org.apache.hbase.thirdparty.com.google.protobuf.Descriptors$OneofDescriptor);
    Code:
       0: aload_0
       1: aload_1
       2: invokevirtual #143                // Method clearOneof:(Lorg/apache/hbase/thirdparty/com/google/protobuf/Descriptors$OneofDescriptor;)Lorg/apache/hadoop/hbase/shaded/protobuf/generated/MasterProtos$SetQuotaRequest$Builder;
       5: areturn

  public org.apache.hbase.thirdparty.com.google.protobuf.GeneratedMessageV3$Builder clearField(org.apache.hbase.thirdparty.com.google.protobuf.Descriptors$FieldDescriptor);
    Code:
       0: aload_0
       1: aload_1
       2: invokevirtual #144                // Method clearField:(Lorg/apache/hbase/thirdparty/com/google/protobuf/Descriptors$FieldDescriptor;)Lorg/apache/hadoop/hbase/shaded/protobuf/generated/MasterProtos$SetQuotaRequest$Builder;
       5: areturn

  public org.apache.hbase.thirdparty.com.google.protobuf.GeneratedMessageV3$Builder setField(org.apache.hbase.thirdparty.com.google.protobuf.Descriptors$FieldDescriptor, java.lang.Object);
    Code:
       0: aload_0
       1: aload_1
       2: aload_2
       3: invokevirtual #145                // Method setField:(Lorg/apache/hbase/thirdparty/com/google/protobuf/Descriptors$FieldDescriptor;Ljava/lang/Object;)Lorg/apache/hadoop/hbase/shaded/protobuf/generated/MasterProtos$SetQuotaRequest$Builder;
       6: areturn

  public org.apache.hbase.thirdparty.com.google.protobuf.GeneratedMessageV3$Builder clear();
    Code:
       0: aload_0
       1: invokevirtual #146                // Method clear:()Lorg/apache/hadoop/hbase/shaded/protobuf/generated/MasterProtos$SetQuotaRequest$Builder;
       4: areturn

  public org.apache.hbase.thirdparty.com.google.protobuf.GeneratedMessageV3$Builder clone();
    Code:
       0: aload_0
       1: invokevirtual #147                // Method clone:()Lorg/apache/hadoop/hbase/shaded/protobuf/generated/MasterProtos$SetQuotaRequest$Builder;
       4: areturn

  public org.apache.hbase.thirdparty.com.google.protobuf.AbstractMessage$Builder mergeUnknownFields(org.apache.hbase.thirdparty.com.google.protobuf.UnknownFieldSet);
    Code:
       0: aload_0
       1: aload_1
       2: invokevirtual #84                 // Method mergeUnknownFields:(Lorg/apache/hbase/thirdparty/com/google/protobuf/UnknownFieldSet;)Lorg/apache/hadoop/hbase/shaded/protobuf/generated/MasterProtos$SetQuotaRequest$Builder;
       5: areturn

  public org.apache.hbase.thirdparty.com.google.protobuf.AbstractMessage$Builder mergeFrom(org.apache.hbase.thirdparty.com.google.protobuf.CodedInputStream, org.apache.hbase.thirdparty.com.google.protobuf.ExtensionRegistryLite) throws java.io.IOException;
    Code:
       0: aload_0
       1: aload_1
       2: aload_2
       3: invokevirtual #148                // Method mergeFrom:(Lorg/apache/hbase/thirdparty/com/google/protobuf/CodedInputStream;Lorg/apache/hbase/thirdparty/com/google/protobuf/ExtensionRegistryLite;)Lorg/apache/hadoop/hbase/shaded/protobuf/generated/MasterProtos$SetQuotaRequest$Builder;
       6: areturn

  public org.apache.hbase.thirdparty.com.google.protobuf.AbstractMessage$Builder mergeFrom(org.apache.hbase.thirdparty.com.google.protobuf.Message);
    Code:
       0: aload_0
       1: aload_1
       2: invokevirtual #149                // Method mergeFrom:(Lorg/apache/hbase/thirdparty/com/google/protobuf/Message;)Lorg/apache/hadoop/hbase/shaded/protobuf/generated/MasterProtos$SetQuotaRequest$Builder;
       5: areturn

  public org.apache.hbase.thirdparty.com.google.protobuf.AbstractMessage$Builder clear();
    Code:
       0: aload_0
       1: invokevirtual #146                // Method clear:()Lorg/apache/hadoop/hbase/shaded/protobuf/generated/MasterProtos$SetQuotaRequest$Builder;
       4: areturn

  public org.apache.hbase.thirdparty.com.google.protobuf.AbstractMessage$Builder clearOneof(org.apache.hbase.thirdparty.com.google.protobuf.Descriptors$OneofDescriptor);
    Code:
       0: aload_0
       1: aload_1
       2: invokevirtual #143                // Method clearOneof:(Lorg/apache/hbase/thirdparty/com/google/protobuf/Descriptors$OneofDescriptor;)Lorg/apache/hadoop/hbase/shaded/protobuf/generated/MasterProtos$SetQuotaRequest$Builder;
       5: areturn

  public org.apache.hbase.thirdparty.com.google.protobuf.AbstractMessage$Builder clone();
    Code:
       0: aload_0
       1: invokevirtual #147                // Method clone:()Lorg/apache/hadoop/hbase/shaded/protobuf/generated/MasterProtos$SetQuotaRequest$Builder;
       4: areturn

  public org.apache.hbase.thirdparty.com.google.protobuf.Message$Builder mergeUnknownFields(org.apache.hbase.thirdparty.com.google.protobuf.UnknownFieldSet);
    Code:
       0: aload_0
       1: aload_1
       2: invokevirtual #84                 // Method mergeUnknownFields:(Lorg/apache/hbase/thirdparty/com/google/protobuf/UnknownFieldSet;)Lorg/apache/hadoop/hbase/shaded/protobuf/generated/MasterProtos$SetQuotaRequest$Builder;
       5: areturn

  public org.apache.hbase.thirdparty.com.google.protobuf.Message$Builder setUnknownFields(org.apache.hbase.thirdparty.com.google.protobuf.UnknownFieldSet);
    Code:
       0: aload_0
       1: aload_1
       2: invokevirtual #140                // Method setUnknownFields:(Lorg/apache/hbase/thirdparty/com/google/protobuf/UnknownFieldSet;)Lorg/apache/hadoop/hbase/shaded/protobuf/generated/MasterProtos$SetQuotaRequest$Builder;
       5: areturn

  public org.apache.hbase.thirdparty.com.google.protobuf.Message$Builder addRepeatedField(org.apache.hbase.thirdparty.com.google.protobuf.Descriptors$FieldDescriptor, java.lang.Object);
    Code:
       0: aload_0
       1: aload_1
       2: aload_2
       3: invokevirtual #141                // Method addRepeatedField:(Lorg/apache/hbase/thirdparty/com/google/protobuf/Descriptors$FieldDescriptor;Ljava/lang/Object;)Lorg/apache/hadoop/hbase/shaded/protobuf/generated/MasterProtos$SetQuotaRequest$Builder;
       6: areturn

  public org.apache.hbase.thirdparty.com.google.protobuf.Message$Builder setRepeatedField(org.apache.hbase.thirdparty.com.google.protobuf.Descriptors$FieldDescriptor, int, java.lang.Object);
    Code:
       0: aload_0
       1: aload_1
       2: iload_2
       3: aload_3
       4: invokevirtual #142                // Method setRepeatedField:(Lorg/apache/hbase/thirdparty/com/google/protobuf/Descriptors$FieldDescriptor;ILjava/lang/Object;)Lorg/apache/hadoop/hbase/shaded/protobuf/generated/MasterProtos$SetQuotaRequest$Builder;
       7: areturn

  public org.apache.hbase.thirdparty.com.google.protobuf.Message$Builder clearOneof(org.apache.hbase.thirdparty.com.google.protobuf.Descriptors$OneofDescriptor);
    Code:
       0: aload_0
       1: aload_1
       2: invokevirtual #143                // Method clearOneof:(Lorg/apache/hbase/thirdparty/com/google/protobuf/Descriptors$OneofDescriptor;)Lorg/apache/hadoop/hbase/shaded/protobuf/generated/MasterProtos$SetQuotaRequest$Builder;
       5: areturn

  public org.apache.hbase.thirdparty.com.google.protobuf.Message$Builder clearField(org.apache.hbase.thirdparty.com.google.protobuf.Descriptors$FieldDescriptor);
    Code:
       0: aload_0
       1: aload_1
       2: invokevirtual #144                // Method clearField:(Lorg/apache/hbase/thirdparty/com/google/protobuf/Descriptors$FieldDescriptor;)Lorg/apache/hadoop/hbase/shaded/protobuf/generated/MasterProtos$SetQuotaRequest$Builder;
       5: areturn

  public org.apache.hbase.thirdparty.com.google.protobuf.Message$Builder setField(org.apache.hbase.thirdparty.com.google.protobuf.Descriptors$FieldDescriptor, java.lang.Object);
    Code:
       0: aload_0
       1: aload_1
       2: aload_2
       3: invokevirtual #145                // Method setField:(Lorg/apache/hbase/thirdparty/com/google/protobuf/Descriptors$FieldDescriptor;Ljava/lang/Object;)Lorg/apache/hadoop/hbase/shaded/protobuf/generated/MasterProtos$SetQuotaRequest$Builder;
       6: areturn

  public org.apache.hbase.thirdparty.com.google.protobuf.Message$Builder mergeFrom(org.apache.hbase.thirdparty.com.google.protobuf.CodedInputStream, org.apache.hbase.thirdparty.com.google.protobuf.ExtensionRegistryLite) throws java.io.IOException;
    Code:
       0: aload_0
       1: aload_1
       2: aload_2
       3: invokevirtual #148                // Method mergeFrom:(Lorg/apache/hbase/thirdparty/com/google/protobuf/CodedInputStream;Lorg/apache/hbase/thirdparty/com/google/protobuf/ExtensionRegistryLite;)Lorg/apache/hadoop/hbase/shaded/protobuf/generated/MasterProtos$SetQuotaRequest$Builder;
       6: areturn

  public org.apache.hbase.thirdparty.com.google.protobuf.Message$Builder clone();
    Code:
       0: aload_0
       1: invokevirtual #147                // Method clone:()Lorg/apache/hadoop/hbase/shaded/protobuf/generated/MasterProtos$SetQuotaRequest$Builder;
       4: areturn

  public org.apache.hbase.thirdparty.com.google.protobuf.Message buildPartial();
    Code:
       0: aload_0
       1: invokevirtual #32                 // Method buildPartial:()Lorg/apache/hadoop/hbase/shaded/protobuf/generated/MasterProtos$SetQuotaRequest;
       4: areturn

  public org.apache.hbase.thirdparty.com.google.protobuf.Message build();
    Code:
       0: aload_0
       1: invokevirtual #150                // Method build:()Lorg/apache/hadoop/hbase/shaded/protobuf/generated/MasterProtos$SetQuotaRequest;
       4: areturn

  public org.apache.hbase.thirdparty.com.google.protobuf.Message$Builder mergeFrom(org.apache.hbase.thirdparty.com.google.protobuf.Message);
    Code:
       0: aload_0
       1: aload_1
       2: invokevirtual #149                // Method mergeFrom:(Lorg/apache/hbase/thirdparty/com/google/protobuf/Message;)Lorg/apache/hadoop/hbase/shaded/protobuf/generated/MasterProtos$SetQuotaRequest$Builder;
       5: areturn

  public org.apache.hbase.thirdparty.com.google.protobuf.Message$Builder clear();
    Code:
       0: aload_0
       1: invokevirtual #146                // Method clear:()Lorg/apache/hadoop/hbase/shaded/protobuf/generated/MasterProtos$SetQuotaRequest$Builder;
       4: areturn

  public org.apache.hbase.thirdparty.com.google.protobuf.MessageLite$Builder mergeFrom(org.apache.hbase.thirdparty.com.google.protobuf.CodedInputStream, org.apache.hbase.thirdparty.com.google.protobuf.ExtensionRegistryLite) throws java.io.IOException;
    Code:
       0: aload_0
       1: aload_1
       2: aload_2
       3: invokevirtual #148                // Method mergeFrom:(Lorg/apache/hbase/thirdparty/com/google/protobuf/CodedInputStream;Lorg/apache/hbase/thirdparty/com/google/protobuf/ExtensionRegistryLite;)Lorg/apache/hadoop/hbase/shaded/protobuf/generated/MasterProtos$SetQuotaRequest$Builder;
       6: areturn

  public org.apache.hbase.thirdparty.com.google.protobuf.MessageLite$Builder clone();
    Code:
       0: aload_0
       1: invokevirtual #147                // Method clone:()Lorg/apache/hadoop/hbase/shaded/protobuf/generated/MasterProtos$SetQuotaRequest$Builder;
       4: areturn

  public org.apache.hbase.thirdparty.com.google.protobuf.MessageLite buildPartial();
    Code:
       0: aload_0
       1: invokevirtual #32                 // Method buildPartial:()Lorg/apache/hadoop/hbase/shaded/protobuf/generated/MasterProtos$SetQuotaRequest;
       4: areturn

  public org.apache.hbase.thirdparty.com.google.protobuf.MessageLite build();
    Code:
       0: aload_0
       1: invokevirtual #150                // Method build:()Lorg/apache/hadoop/hbase/shaded/protobuf/generated/MasterProtos$SetQuotaRequest;
       4: areturn

  public org.apache.hbase.thirdparty.com.google.protobuf.MessageLite$Builder clear();
    Code:
       0: aload_0
       1: invokevirtual #146                // Method clear:()Lorg/apache/hadoop/hbase/shaded/protobuf/generated/MasterProtos$SetQuotaRequest$Builder;
       4: areturn

  public org.apache.hbase.thirdparty.com.google.protobuf.MessageLite getDefaultInstanceForType();
    Code:
       0: aload_0
       1: invokevirtual #151                // Method getDefaultInstanceForType:()Lorg/apache/hadoop/hbase/shaded/protobuf/generated/MasterProtos$SetQuotaRequest;
       4: areturn

  public org.apache.hbase.thirdparty.com.google.protobuf.Message getDefaultInstanceForType();
    Code:
       0: aload_0
       1: invokevirtual #151                // Method getDefaultInstanceForType:()Lorg/apache/hadoop/hbase/shaded/protobuf/generated/MasterProtos$SetQuotaRequest;
       4: areturn

  public org.apache.hbase.thirdparty.com.google.protobuf.AbstractMessageLite$Builder mergeFrom(org.apache.hbase.thirdparty.com.google.protobuf.CodedInputStream, org.apache.hbase.thirdparty.com.google.protobuf.ExtensionRegistryLite) throws java.io.IOException;
    Code:
       0: aload_0
       1: aload_1
       2: aload_2
       3: invokevirtual #148                // Method mergeFrom:(Lorg/apache/hbase/thirdparty/com/google/protobuf/CodedInputStream;Lorg/apache/hbase/thirdparty/com/google/protobuf/ExtensionRegistryLite;)Lorg/apache/hadoop/hbase/shaded/protobuf/generated/MasterProtos$SetQuotaRequest$Builder;
       6: areturn

  public org.apache.hbase.thirdparty.com.google.protobuf.AbstractMessageLite$Builder clone();
    Code:
       0: aload_0
       1: invokevirtual #147                // Method clone:()Lorg/apache/hadoop/hbase/shaded/protobuf/generated/MasterProtos$SetQuotaRequest$Builder;
       4: areturn

  public java.lang.Object clone() throws java.lang.CloneNotSupportedException;
    Code:
       0: aload_0
       1: invokevirtual #147                // Method clone:()Lorg/apache/hadoop/hbase/shaded/protobuf/generated/MasterProtos$SetQuotaRequest$Builder;
       4: areturn

  org.apache.hadoop.hbase.shaded.protobuf.generated.MasterProtos$SetQuotaRequest$Builder(org.apache.hadoop.hbase.shaded.protobuf.generated.MasterProtos$1);
    Code:
       0: aload_0
       1: invokespecial #2                  // Method "<init>":()V
       4: return

  org.apache.hadoop.hbase.shaded.protobuf.generated.MasterProtos$SetQuotaRequest$Builder(org.apache.hbase.thirdparty.com.google.protobuf.GeneratedMessageV3$BuilderParent, org.apache.hadoop.hbase.shaded.protobuf.generated.MasterProtos$1);
    Code:
       0: aload_0
       1: aload_1
       2: invokespecial #1                  // Method "<init>":(Lorg/apache/hbase/thirdparty/com/google/protobuf/GeneratedMessageV3$BuilderParent;)V
       5: return
}
