Compiled from "MasterProcedureProtos.java"
public final class org.apache.hadoop.hbase.shaded.protobuf.generated.MasterProcedureProtos$ReplaySyncReplicationWALParameter extends org.apache.hbase.thirdparty.com.google.protobuf.GeneratedMessageV3 implements org.apache.hadoop.hbase.shaded.protobuf.generated.MasterProcedureProtos$ReplaySyncReplicationWALParameterOrBuilder {
  public static final int PEER_ID_FIELD_NUMBER;

  public static final int WAL_FIELD_NUMBER;

  public static final org.apache.hbase.thirdparty.com.google.protobuf.Parser<org.apache.hadoop.hbase.shaded.protobuf.generated.MasterProcedureProtos$ReplaySyncReplicationWALParameter> PARSER;

  public final org.apache.hbase.thirdparty.com.google.protobuf.UnknownFieldSet getUnknownFields();
    Code:
       0: aload_0
       1: getfield      #2                  // Field unknownFields:Lorg/apache/hbase/thirdparty/com/google/protobuf/UnknownFieldSet;
       4: areturn

  public static final org.apache.hbase.thirdparty.com.google.protobuf.Descriptors$Descriptor getDescriptor();
    Code:
       0: invokestatic  #30                 // Method org/apache/hadoop/hbase/shaded/protobuf/generated/MasterProcedureProtos.access$45200:()Lorg/apache/hbase/thirdparty/com/google/protobuf/Descriptors$Descriptor;
       3: areturn

  protected org.apache.hbase.thirdparty.com.google.protobuf.GeneratedMessageV3$FieldAccessorTable internalGetFieldAccessorTable();
    Code:
       0: invokestatic  #31                 // Method org/apache/hadoop/hbase/shaded/protobuf/generated/MasterProcedureProtos.access$45300:()Lorg/apache/hbase/thirdparty/com/google/protobuf/GeneratedMessageV3$FieldAccessorTable;
       3: ldc           #32                 // class org/apache/hadoop/hbase/shaded/protobuf/generated/MasterProcedureProtos$ReplaySyncReplicationWALParameter
       5: ldc           #33                 // class org/apache/hadoop/hbase/shaded/protobuf/generated/MasterProcedureProtos$ReplaySyncReplicationWALParameter$Builder
       7: invokevirtual #34                 // Method org/apache/hbase/thirdparty/com/google/protobuf/GeneratedMessageV3$FieldAccessorTable.ensureFieldAccessorsInitialized:(Ljava/lang/Class;Ljava/lang/Class;)Lorg/apache/hbase/thirdparty/com/google/protobuf/GeneratedMessageV3$FieldAccessorTable;
      10: areturn

  public boolean hasPeerId();
    Code:
       0: aload_0
       1: getfield      #3                  // Field bitField0_:I
       4: iconst_1
       5: iand
       6: iconst_1
       7: if_icmpne     14
      10: iconst_1
      11: goto          15
      14: iconst_0
      15: ireturn

  public java.lang.String getPeerId();
    Code:
       0: aload_0
       1: getfield      #5                  // Field peerId_:Ljava/lang/Object;
       4: astore_1
       5: aload_1
       6: instanceof    #35                 // class java/lang/String
       9: ifeq          17
      12: aload_1
      13: checkcast     #35                 // class java/lang/String
      16: areturn
      17: aload_1
      18: checkcast     #36                 // class org/apache/hbase/thirdparty/com/google/protobuf/ByteString
      21: astore_2
      22: aload_2
      23: invokevirtual #37                 // Method org/apache/hbase/thirdparty/com/google/protobuf/ByteString.toStringUtf8:()Ljava/lang/String;
      26: astore_3
      27: aload_2
      28: invokevirtual #38                 // Method org/apache/hbase/thirdparty/com/google/protobuf/ByteString.isValidUtf8:()Z
      31: ifeq          39
      34: aload_0
      35: aload_3
      36: putfield      #5                  // Field peerId_:Ljava/lang/Object;
      39: aload_3
      40: areturn

  public org.apache.hbase.thirdparty.com.google.protobuf.ByteString getPeerIdBytes();
    Code:
       0: aload_0
       1: getfield      #5                  // Field peerId_:Ljava/lang/Object;
       4: astore_1
       5: aload_1
       6: instanceof    #35                 // class java/lang/String
       9: ifeq          27
      12: aload_1
      13: checkcast     #35                 // class java/lang/String
      16: invokestatic  #39                 // Method org/apache/hbase/thirdparty/com/google/protobuf/ByteString.copyFromUtf8:(Ljava/lang/String;)Lorg/apache/hbase/thirdparty/com/google/protobuf/ByteString;
      19: astore_2
      20: aload_0
      21: aload_2
      22: putfield      #5                  // Field peerId_:Ljava/lang/Object;
      25: aload_2
      26: areturn
      27: aload_1
      28: checkcast     #36                 // class org/apache/hbase/thirdparty/com/google/protobuf/ByteString
      31: areturn

  public org.apache.hbase.thirdparty.com.google.protobuf.ProtocolStringList getWalList();
    Code:
       0: aload_0
       1: getfield      #4                  // Field wal_:Lorg/apache/hbase/thirdparty/com/google/protobuf/LazyStringList;
       4: areturn

  public int getWalCount();
    Code:
       0: aload_0
       1: getfield      #4                  // Field wal_:Lorg/apache/hbase/thirdparty/com/google/protobuf/LazyStringList;
       4: invokeinterface #40,  1           // InterfaceMethod org/apache/hbase/thirdparty/com/google/protobuf/LazyStringList.size:()I
       9: ireturn

  public java.lang.String getWal(int);
    Code:
       0: aload_0
       1: getfield      #4                  // Field wal_:Lorg/apache/hbase/thirdparty/com/google/protobuf/LazyStringList;
       4: iload_1
       5: invokeinterface #41,  2           // InterfaceMethod org/apache/hbase/thirdparty/com/google/protobuf/LazyStringList.get:(I)Ljava/lang/Object;
      10: checkcast     #35                 // class java/lang/String
      13: areturn

  public org.apache.hbase.thirdparty.com.google.protobuf.ByteString getWalBytes(int);
    Code:
       0: aload_0
       1: getfield      #4                  // Field wal_:Lorg/apache/hbase/thirdparty/com/google/protobuf/LazyStringList;
       4: iload_1
       5: invokeinterface #42,  2           // InterfaceMethod org/apache/hbase/thirdparty/com/google/protobuf/LazyStringList.getByteString:(I)Lorg/apache/hbase/thirdparty/com/google/protobuf/ByteString;
      10: areturn

  public final boolean isInitialized();
    Code:
       0: aload_0
       1: getfield      #9                  // Field memoizedIsInitialized:B
       4: istore_1
       5: iload_1
       6: iconst_1
       7: if_icmpne     12
      10: iconst_1
      11: ireturn
      12: iload_1
      13: ifne          18
      16: iconst_0
      17: ireturn
      18: aload_0
      19: invokevirtual #43                 // Method hasPeerId:()Z
      22: ifne          32
      25: aload_0
      26: iconst_0
      27: putfield      #9                  // Field memoizedIsInitialized:B
      30: iconst_0
      31: ireturn
      32: aload_0
      33: iconst_1
      34: putfield      #9                  // Field memoizedIsInitialized:B
      37: iconst_1
      38: ireturn

  public void writeTo(org.apache.hbase.thirdparty.com.google.protobuf.CodedOutputStream) throws java.io.IOException;
    Code:
       0: aload_0
       1: getfield      #3                  // Field bitField0_:I
       4: iconst_1
       5: iand
       6: iconst_1
       7: if_icmpne     19
      10: aload_1
      11: iconst_1
      12: aload_0
      13: getfield      #5                  // Field peerId_:Ljava/lang/Object;
      16: invokestatic  #44                 // Method org/apache/hbase/thirdparty/com/google/protobuf/GeneratedMessageV3.writeString:(Lorg/apache/hbase/thirdparty/com/google/protobuf/CodedOutputStream;ILjava/lang/Object;)V
      19: iconst_0
      20: istore_2
      21: iload_2
      22: aload_0
      23: getfield      #4                  // Field wal_:Lorg/apache/hbase/thirdparty/com/google/protobuf/LazyStringList;
      26: invokeinterface #40,  1           // InterfaceMethod org/apache/hbase/thirdparty/com/google/protobuf/LazyStringList.size:()I
      31: if_icmpge     55
      34: aload_1
      35: iconst_2
      36: aload_0
      37: getfield      #4                  // Field wal_:Lorg/apache/hbase/thirdparty/com/google/protobuf/LazyStringList;
      40: iload_2
      41: invokeinterface #45,  2           // InterfaceMethod org/apache/hbase/thirdparty/com/google/protobuf/LazyStringList.getRaw:(I)Ljava/lang/Object;
      46: invokestatic  #44                 // Method org/apache/hbase/thirdparty/com/google/protobuf/GeneratedMessageV3.writeString:(Lorg/apache/hbase/thirdparty/com/google/protobuf/CodedOutputStream;ILjava/lang/Object;)V
      49: iinc          2, 1
      52: goto          21
      55: aload_0
      56: getfield      #2                  // Field unknownFields:Lorg/apache/hbase/thirdparty/com/google/protobuf/UnknownFieldSet;
      59: aload_1
      60: invokevirtual #46                 // Method org/apache/hbase/thirdparty/com/google/protobuf/UnknownFieldSet.writeTo:(Lorg/apache/hbase/thirdparty/com/google/protobuf/CodedOutputStream;)V
      63: return

  public int getSerializedSize();
    Code:
       0: aload_0
       1: getfield      #47                 // Field memoizedSize:I
       4: istore_1
       5: iload_1
       6: iconst_m1
       7: if_icmpeq     12
      10: iload_1
      11: ireturn
      12: iconst_0
      13: istore_1
      14: aload_0
      15: getfield      #3                  // Field bitField0_:I
      18: iconst_1
      19: iand
      20: iconst_1
      21: if_icmpne     35
      24: iload_1
      25: iconst_1
      26: aload_0
      27: getfield      #5                  // Field peerId_:Ljava/lang/Object;
      30: invokestatic  #48                 // Method org/apache/hbase/thirdparty/com/google/protobuf/GeneratedMessageV3.computeStringSize:(ILjava/lang/Object;)I
      33: iadd
      34: istore_1
      35: iconst_0
      36: istore_2
      37: iconst_0
      38: istore_3
      39: iload_3
      40: aload_0
      41: getfield      #4                  // Field wal_:Lorg/apache/hbase/thirdparty/com/google/protobuf/LazyStringList;
      44: invokeinterface #40,  1           // InterfaceMethod org/apache/hbase/thirdparty/com/google/protobuf/LazyStringList.size:()I
      49: if_icmpge     74
      52: iload_2
      53: aload_0
      54: getfield      #4                  // Field wal_:Lorg/apache/hbase/thirdparty/com/google/protobuf/LazyStringList;
      57: iload_3
      58: invokeinterface #45,  2           // InterfaceMethod org/apache/hbase/thirdparty/com/google/protobuf/LazyStringList.getRaw:(I)Ljava/lang/Object;
      63: invokestatic  #49                 // Method computeStringSizeNoTag:(Ljava/lang/Object;)I
      66: iadd
      67: istore_2
      68: iinc          3, 1
      71: goto          39
      74: iload_1
      75: iload_2
      76: iadd
      77: istore_1
      78: iload_1
      79: iconst_1
      80: aload_0
      81: invokevirtual #50                 // Method getWalList:()Lorg/apache/hbase/thirdparty/com/google/protobuf/ProtocolStringList;
      84: invokeinterface #51,  1           // InterfaceMethod org/apache/hbase/thirdparty/com/google/protobuf/ProtocolStringList.size:()I
      89: imul
      90: iadd
      91: istore_1
      92: iload_1
      93: aload_0
      94: getfield      #2                  // Field unknownFields:Lorg/apache/hbase/thirdparty/com/google/protobuf/UnknownFieldSet;
      97: invokevirtual #52                 // Method org/apache/hbase/thirdparty/com/google/protobuf/UnknownFieldSet.getSerializedSize:()I
     100: iadd
     101: istore_1
     102: aload_0
     103: iload_1
     104: putfield      #47                 // Field memoizedSize:I
     107: iload_1
     108: ireturn

  public boolean equals(java.lang.Object);
    Code:
       0: aload_1
       1: aload_0
       2: if_acmpne     7
       5: iconst_1
       6: ireturn
       7: aload_1
       8: instanceof    #32                 // class org/apache/hadoop/hbase/shaded/protobuf/generated/MasterProcedureProtos$ReplaySyncReplicationWALParameter
      11: ifne          20
      14: aload_0
      15: aload_1
      16: invokespecial #53                 // Method org/apache/hbase/thirdparty/com/google/protobuf/GeneratedMessageV3.equals:(Ljava/lang/Object;)Z
      19: ireturn
      20: aload_1
      21: checkcast     #32                 // class org/apache/hadoop/hbase/shaded/protobuf/generated/MasterProcedureProtos$ReplaySyncReplicationWALParameter
      24: astore_2
      25: iconst_1
      26: istore_3
      27: iload_3
      28: ifeq          46
      31: aload_0
      32: invokevirtual #43                 // Method hasPeerId:()Z
      35: aload_2
      36: invokevirtual #43                 // Method hasPeerId:()Z
      39: if_icmpne     46
      42: iconst_1
      43: goto          47
      46: iconst_0
      47: istore_3
      48: aload_0
      49: invokevirtual #43                 // Method hasPeerId:()Z
      52: ifeq          79
      55: iload_3
      56: ifeq          77
      59: aload_0
      60: invokevirtual #54                 // Method getPeerId:()Ljava/lang/String;
      63: aload_2
      64: invokevirtual #54                 // Method getPeerId:()Ljava/lang/String;
      67: invokevirtual #55                 // Method java/lang/String.equals:(Ljava/lang/Object;)Z
      70: ifeq          77
      73: iconst_1
      74: goto          78
      77: iconst_0
      78: istore_3
      79: iload_3
      80: ifeq          101
      83: aload_0
      84: invokevirtual #50                 // Method getWalList:()Lorg/apache/hbase/thirdparty/com/google/protobuf/ProtocolStringList;
      87: aload_2
      88: invokevirtual #50                 // Method getWalList:()Lorg/apache/hbase/thirdparty/com/google/protobuf/ProtocolStringList;
      91: invokevirtual #56                 // Method java/lang/Object.equals:(Ljava/lang/Object;)Z
      94: ifeq          101
      97: iconst_1
      98: goto          102
     101: iconst_0
     102: istore_3
     103: iload_3
     104: ifeq          125
     107: aload_0
     108: getfield      #2                  // Field unknownFields:Lorg/apache/hbase/thirdparty/com/google/protobuf/UnknownFieldSet;
     111: aload_2
     112: getfield      #2                  // Field unknownFields:Lorg/apache/hbase/thirdparty/com/google/protobuf/UnknownFieldSet;
     115: invokevirtual #57                 // Method org/apache/hbase/thirdparty/com/google/protobuf/UnknownFieldSet.equals:(Ljava/lang/Object;)Z
     118: ifeq          125
     121: iconst_1
     122: goto          126
     125: iconst_0
     126: istore_3
     127: iload_3
     128: ireturn

  public int hashCode();
    Code:
       0: aload_0
       1: getfield      #58                 // Field memoizedHashCode:I
       4: ifeq          12
       7: aload_0
       8: getfield      #58                 // Field memoizedHashCode:I
      11: ireturn
      12: bipush        41
      14: istore_1
      15: bipush        19
      17: iload_1
      18: imul
      19: invokestatic  #59                 // Method getDescriptor:()Lorg/apache/hbase/thirdparty/com/google/protobuf/Descriptors$Descriptor;
      22: invokevirtual #60                 // Method java/lang/Object.hashCode:()I
      25: iadd
      26: istore_1
      27: aload_0
      28: invokevirtual #43                 // Method hasPeerId:()Z
      31: ifeq          54
      34: bipush        37
      36: iload_1
      37: imul
      38: iconst_1
      39: iadd
      40: istore_1
      41: bipush        53
      43: iload_1
      44: imul
      45: aload_0
      46: invokevirtual #54                 // Method getPeerId:()Ljava/lang/String;
      49: invokevirtual #61                 // Method java/lang/String.hashCode:()I
      52: iadd
      53: istore_1
      54: aload_0
      55: invokevirtual #62                 // Method getWalCount:()I
      58: ifle          81
      61: bipush        37
      63: iload_1
      64: imul
      65: iconst_2
      66: iadd
      67: istore_1
      68: bipush        53
      70: iload_1
      71: imul
      72: aload_0
      73: invokevirtual #50                 // Method getWalList:()Lorg/apache/hbase/thirdparty/com/google/protobuf/ProtocolStringList;
      76: invokevirtual #60                 // Method java/lang/Object.hashCode:()I
      79: iadd
      80: istore_1
      81: bipush        29
      83: iload_1
      84: imul
      85: aload_0
      86: getfield      #2                  // Field unknownFields:Lorg/apache/hbase/thirdparty/com/google/protobuf/UnknownFieldSet;
      89: invokevirtual #63                 // Method org/apache/hbase/thirdparty/com/google/protobuf/UnknownFieldSet.hashCode:()I
      92: iadd
      93: istore_1
      94: aload_0
      95: iload_1
      96: putfield      #58                 // Field memoizedHashCode:I
      99: iload_1
     100: ireturn

  public static org.apache.hadoop.hbase.shaded.protobuf.generated.MasterProcedureProtos$ReplaySyncReplicationWALParameter parseFrom(java.nio.ByteBuffer) throws org.apache.hbase.thirdparty.com.google.protobuf.InvalidProtocolBufferException;
    Code:
       0: getstatic     #64                 // Field PARSER:Lorg/apache/hbase/thirdparty/com/google/protobuf/Parser;
       3: aload_0
       4: invokeinterface #65,  2           // InterfaceMethod org/apache/hbase/thirdparty/com/google/protobuf/Parser.parseFrom:(Ljava/nio/ByteBuffer;)Ljava/lang/Object;
       9: checkcast     #32                 // class org/apache/hadoop/hbase/shaded/protobuf/generated/MasterProcedureProtos$ReplaySyncReplicationWALParameter
      12: areturn

  public static org.apache.hadoop.hbase.shaded.protobuf.generated.MasterProcedureProtos$ReplaySyncReplicationWALParameter parseFrom(java.nio.ByteBuffer, org.apache.hbase.thirdparty.com.google.protobuf.ExtensionRegistryLite) throws org.apache.hbase.thirdparty.com.google.protobuf.InvalidProtocolBufferException;
    Code:
       0: getstatic     #64                 // Field PARSER:Lorg/apache/hbase/thirdparty/com/google/protobuf/Parser;
       3: aload_0
       4: aload_1
       5: invokeinterface #66,  3           // InterfaceMethod org/apache/hbase/thirdparty/com/google/protobuf/Parser.parseFrom:(Ljava/nio/ByteBuffer;Lorg/apache/hbase/thirdparty/com/google/protobuf/ExtensionRegistryLite;)Ljava/lang/Object;
      10: checkcast     #32                 // class org/apache/hadoop/hbase/shaded/protobuf/generated/MasterProcedureProtos$ReplaySyncReplicationWALParameter
      13: areturn

  public static org.apache.hadoop.hbase.shaded.protobuf.generated.MasterProcedureProtos$ReplaySyncReplicationWALParameter parseFrom(org.apache.hbase.thirdparty.com.google.protobuf.ByteString) throws org.apache.hbase.thirdparty.com.google.protobuf.InvalidProtocolBufferException;
    Code:
       0: getstatic     #64                 // Field PARSER:Lorg/apache/hbase/thirdparty/com/google/protobuf/Parser;
       3: aload_0
       4: invokeinterface #67,  2           // InterfaceMethod org/apache/hbase/thirdparty/com/google/protobuf/Parser.parseFrom:(Lorg/apache/hbase/thirdparty/com/google/protobuf/ByteString;)Ljava/lang/Object;
       9: checkcast     #32                 // class org/apache/hadoop/hbase/shaded/protobuf/generated/MasterProcedureProtos$ReplaySyncReplicationWALParameter
      12: areturn

  public static org.apache.hadoop.hbase.shaded.protobuf.generated.MasterProcedureProtos$ReplaySyncReplicationWALParameter parseFrom(org.apache.hbase.thirdparty.com.google.protobuf.ByteString, org.apache.hbase.thirdparty.com.google.protobuf.ExtensionRegistryLite) throws org.apache.hbase.thirdparty.com.google.protobuf.InvalidProtocolBufferException;
    Code:
       0: getstatic     #64                 // Field PARSER:Lorg/apache/hbase/thirdparty/com/google/protobuf/Parser;
       3: aload_0
       4: aload_1
       5: invokeinterface #68,  3           // InterfaceMethod org/apache/hbase/thirdparty/com/google/protobuf/Parser.parseFrom:(Lorg/apache/hbase/thirdparty/com/google/protobuf/ByteString;Lorg/apache/hbase/thirdparty/com/google/protobuf/ExtensionRegistryLite;)Ljava/lang/Object;
      10: checkcast     #32                 // class org/apache/hadoop/hbase/shaded/protobuf/generated/MasterProcedureProtos$ReplaySyncReplicationWALParameter
      13: areturn

  public static org.apache.hadoop.hbase.shaded.protobuf.generated.MasterProcedureProtos$ReplaySyncReplicationWALParameter parseFrom(byte[]) throws org.apache.hbase.thirdparty.com.google.protobuf.InvalidProtocolBufferException;
    Code:
       0: getstatic     #64                 // Field PARSER:Lorg/apache/hbase/thirdparty/com/google/protobuf/Parser;
       3: aload_0
       4: invokeinterface #69,  2           // InterfaceMethod org/apache/hbase/thirdparty/com/google/protobuf/Parser.parseFrom:([B)Ljava/lang/Object;
       9: checkcast     #32                 // class org/apache/hadoop/hbase/shaded/protobuf/generated/MasterProcedureProtos$ReplaySyncReplicationWALParameter
      12: areturn

  public static org.apache.hadoop.hbase.shaded.protobuf.generated.MasterProcedureProtos$ReplaySyncReplicationWALParameter parseFrom(byte[], org.apache.hbase.thirdparty.com.google.protobuf.ExtensionRegistryLite) throws org.apache.hbase.thirdparty.com.google.protobuf.InvalidProtocolBufferException;
    Code:
       0: getstatic     #64                 // Field PARSER:Lorg/apache/hbase/thirdparty/com/google/protobuf/Parser;
       3: aload_0
       4: aload_1
       5: invokeinterface #70,  3           // InterfaceMethod org/apache/hbase/thirdparty/com/google/protobuf/Parser.parseFrom:([BLorg/apache/hbase/thirdparty/com/google/protobuf/ExtensionRegistryLite;)Ljava/lang/Object;
      10: checkcast     #32                 // class org/apache/hadoop/hbase/shaded/protobuf/generated/MasterProcedureProtos$ReplaySyncReplicationWALParameter
      13: areturn

  public static org.apache.hadoop.hbase.shaded.protobuf.generated.MasterProcedureProtos$ReplaySyncReplicationWALParameter parseFrom(java.io.InputStream) throws java.io.IOException;
    Code:
       0: getstatic     #64                 // Field PARSER:Lorg/apache/hbase/thirdparty/com/google/protobuf/Parser;
       3: aload_0
       4: invokestatic  #71                 // Method org/apache/hbase/thirdparty/com/google/protobuf/GeneratedMessageV3.parseWithIOException:(Lorg/apache/hbase/thirdparty/com/google/protobuf/Parser;Ljava/io/InputStream;)Lorg/apache/hbase/thirdparty/com/google/protobuf/Message;
       7: checkcast     #32                 // class org/apache/hadoop/hbase/shaded/protobuf/generated/MasterProcedureProtos$ReplaySyncReplicationWALParameter
      10: areturn

  public static org.apache.hadoop.hbase.shaded.protobuf.generated.MasterProcedureProtos$ReplaySyncReplicationWALParameter parseFrom(java.io.InputStream, org.apache.hbase.thirdparty.com.google.protobuf.ExtensionRegistryLite) throws java.io.IOException;
    Code:
       0: getstatic     #64                 // Field PARSER:Lorg/apache/hbase/thirdparty/com/google/protobuf/Parser;
       3: aload_0
       4: aload_1
       5: invokestatic  #72                 // Method org/apache/hbase/thirdparty/com/google/protobuf/GeneratedMessageV3.parseWithIOException:(Lorg/apache/hbase/thirdparty/com/google/protobuf/Parser;Ljava/io/InputStream;Lorg/apache/hbase/thirdparty/com/google/protobuf/ExtensionRegistryLite;)Lorg/apache/hbase/thirdparty/com/google/protobuf/Message;
       8: checkcast     #32                 // class org/apache/hadoop/hbase/shaded/protobuf/generated/MasterProcedureProtos$ReplaySyncReplicationWALParameter
      11: areturn

  public static org.apache.hadoop.hbase.shaded.protobuf.generated.MasterProcedureProtos$ReplaySyncReplicationWALParameter parseDelimitedFrom(java.io.InputStream) throws java.io.IOException;
    Code:
       0: getstatic     #64                 // Field PARSER:Lorg/apache/hbase/thirdparty/com/google/protobuf/Parser;
       3: aload_0
       4: invokestatic  #73                 // Method org/apache/hbase/thirdparty/com/google/protobuf/GeneratedMessageV3.parseDelimitedWithIOException:(Lorg/apache/hbase/thirdparty/com/google/protobuf/Parser;Ljava/io/InputStream;)Lorg/apache/hbase/thirdparty/com/google/protobuf/Message;
       7: checkcast     #32                 // class org/apache/hadoop/hbase/shaded/protobuf/generated/MasterProcedureProtos$ReplaySyncReplicationWALParameter
      10: areturn

  public static org.apache.hadoop.hbase.shaded.protobuf.generated.MasterProcedureProtos$ReplaySyncReplicationWALParameter parseDelimitedFrom(java.io.InputStream, org.apache.hbase.thirdparty.com.google.protobuf.ExtensionRegistryLite) throws java.io.IOException;
    Code:
       0: getstatic     #64                 // Field PARSER:Lorg/apache/hbase/thirdparty/com/google/protobuf/Parser;
       3: aload_0
       4: aload_1
       5: invokestatic  #74                 // Method org/apache/hbase/thirdparty/com/google/protobuf/GeneratedMessageV3.parseDelimitedWithIOException:(Lorg/apache/hbase/thirdparty/com/google/protobuf/Parser;Ljava/io/InputStream;Lorg/apache/hbase/thirdparty/com/google/protobuf/ExtensionRegistryLite;)Lorg/apache/hbase/thirdparty/com/google/protobuf/Message;
       8: checkcast     #32                 // class org/apache/hadoop/hbase/shaded/protobuf/generated/MasterProcedureProtos$ReplaySyncReplicationWALParameter
      11: areturn

  public static org.apache.hadoop.hbase.shaded.protobuf.generated.MasterProcedureProtos$ReplaySyncReplicationWALParameter parseFrom(org.apache.hbase.thirdparty.com.google.protobuf.CodedInputStream) throws java.io.IOException;
    Code:
       0: getstatic     #64                 // Field PARSER:Lorg/apache/hbase/thirdparty/com/google/protobuf/Parser;
       3: aload_0
       4: invokestatic  #75                 // Method org/apache/hbase/thirdparty/com/google/protobuf/GeneratedMessageV3.parseWithIOException:(Lorg/apache/hbase/thirdparty/com/google/protobuf/Parser;Lorg/apache/hbase/thirdparty/com/google/protobuf/CodedInputStream;)Lorg/apache/hbase/thirdparty/com/google/protobuf/Message;
       7: checkcast     #32                 // class org/apache/hadoop/hbase/shaded/protobuf/generated/MasterProcedureProtos$ReplaySyncReplicationWALParameter
      10: areturn

  public static org.apache.hadoop.hbase.shaded.protobuf.generated.MasterProcedureProtos$ReplaySyncReplicationWALParameter parseFrom(org.apache.hbase.thirdparty.com.google.protobuf.CodedInputStream, org.apache.hbase.thirdparty.com.google.protobuf.ExtensionRegistryLite) throws java.io.IOException;
    Code:
       0: getstatic     #64                 // Field PARSER:Lorg/apache/hbase/thirdparty/com/google/protobuf/Parser;
       3: aload_0
       4: aload_1
       5: invokestatic  #76                 // Method org/apache/hbase/thirdparty/com/google/protobuf/GeneratedMessageV3.parseWithIOException:(Lorg/apache/hbase/thirdparty/com/google/protobuf/Parser;Lorg/apache/hbase/thirdparty/com/google/protobuf/CodedInputStream;Lorg/apache/hbase/thirdparty/com/google/protobuf/ExtensionRegistryLite;)Lorg/apache/hbase/thirdparty/com/google/protobuf/Message;
       8: checkcast     #32                 // class org/apache/hadoop/hbase/shaded/protobuf/generated/MasterProcedureProtos$ReplaySyncReplicationWALParameter
      11: areturn

  public org.apache.hadoop.hbase.shaded.protobuf.generated.MasterProcedureProtos$ReplaySyncReplicationWALParameter$Builder newBuilderForType();
    Code:
       0: invokestatic  #77                 // Method newBuilder:()Lorg/apache/hadoop/hbase/shaded/protobuf/generated/MasterProcedureProtos$ReplaySyncReplicationWALParameter$Builder;
       3: areturn

  public static org.apache.hadoop.hbase.shaded.protobuf.generated.MasterProcedureProtos$ReplaySyncReplicationWALParameter$Builder newBuilder();
    Code:
       0: getstatic     #78                 // Field DEFAULT_INSTANCE:Lorg/apache/hadoop/hbase/shaded/protobuf/generated/MasterProcedureProtos$ReplaySyncReplicationWALParameter;
       3: invokevirtual #79                 // Method toBuilder:()Lorg/apache/hadoop/hbase/shaded/protobuf/generated/MasterProcedureProtos$ReplaySyncReplicationWALParameter$Builder;
       6: areturn

  public static org.apache.hadoop.hbase.shaded.protobuf.generated.MasterProcedureProtos$ReplaySyncReplicationWALParameter$Builder newBuilder(org.apache.hadoop.hbase.shaded.protobuf.generated.MasterProcedureProtos$ReplaySyncReplicationWALParameter);
    Code:
       0: getstatic     #78                 // Field DEFAULT_INSTANCE:Lorg/apache/hadoop/hbase/shaded/protobuf/generated/MasterProcedureProtos$ReplaySyncReplicationWALParameter;
       3: invokevirtual #79                 // Method toBuilder:()Lorg/apache/hadoop/hbase/shaded/protobuf/generated/MasterProcedureProtos$ReplaySyncReplicationWALParameter$Builder;
       6: aload_0
       7: invokevirtual #80                 // Method org/apache/hadoop/hbase/shaded/protobuf/generated/MasterProcedureProtos$ReplaySyncReplicationWALParameter$Builder.mergeFrom:(Lorg/apache/hadoop/hbase/shaded/protobuf/generated/MasterProcedureProtos$ReplaySyncReplicationWALParameter;)Lorg/apache/hadoop/hbase/shaded/protobuf/generated/MasterProcedureProtos$ReplaySyncReplicationWALParameter$Builder;
      10: areturn

  public org.apache.hadoop.hbase.shaded.protobuf.generated.MasterProcedureProtos$ReplaySyncReplicationWALParameter$Builder toBuilder();
    Code:
       0: aload_0
       1: getstatic     #78                 // Field DEFAULT_INSTANCE:Lorg/apache/hadoop/hbase/shaded/protobuf/generated/MasterProcedureProtos$ReplaySyncReplicationWALParameter;
       4: if_acmpne     18
       7: new           #33                 // class org/apache/hadoop/hbase/shaded/protobuf/generated/MasterProcedureProtos$ReplaySyncReplicationWALParameter$Builder
      10: dup
      11: aconst_null
      12: invokespecial #81                 // Method org/apache/hadoop/hbase/shaded/protobuf/generated/MasterProcedureProtos$ReplaySyncReplicationWALParameter$Builder."<init>":(Lorg/apache/hadoop/hbase/shaded/protobuf/generated/MasterProcedureProtos$1;)V
      15: goto          30
      18: new           #33                 // class org/apache/hadoop/hbase/shaded/protobuf/generated/MasterProcedureProtos$ReplaySyncReplicationWALParameter$Builder
      21: dup
      22: aconst_null
      23: invokespecial #81                 // Method org/apache/hadoop/hbase/shaded/protobuf/generated/MasterProcedureProtos$ReplaySyncReplicationWALParameter$Builder."<init>":(Lorg/apache/hadoop/hbase/shaded/protobuf/generated/MasterProcedureProtos$1;)V
      26: aload_0
      27: invokevirtual #80                 // Method org/apache/hadoop/hbase/shaded/protobuf/generated/MasterProcedureProtos$ReplaySyncReplicationWALParameter$Builder.mergeFrom:(Lorg/apache/hadoop/hbase/shaded/protobuf/generated/MasterProcedureProtos$ReplaySyncReplicationWALParameter;)Lorg/apache/hadoop/hbase/shaded/protobuf/generated/MasterProcedureProtos$ReplaySyncReplicationWALParameter$Builder;
      30: areturn

  protected org.apache.hadoop.hbase.shaded.protobuf.generated.MasterProcedureProtos$ReplaySyncReplicationWALParameter$Builder newBuilderForType(org.apache.hbase.thirdparty.com.google.protobuf.GeneratedMessageV3$BuilderParent);
    Code:
       0: new           #33                 // class org/apache/hadoop/hbase/shaded/protobuf/generated/MasterProcedureProtos$ReplaySyncReplicationWALParameter$Builder
       3: dup
       4: aload_1
       5: aconst_null
       6: invokespecial #82                 // Method org/apache/hadoop/hbase/shaded/protobuf/generated/MasterProcedureProtos$ReplaySyncReplicationWALParameter$Builder."<init>":(Lorg/apache/hbase/thirdparty/com/google/protobuf/GeneratedMessageV3$BuilderParent;Lorg/apache/hadoop/hbase/shaded/protobuf/generated/MasterProcedureProtos$1;)V
       9: astore_2
      10: aload_2
      11: areturn

  public static org.apache.hadoop.hbase.shaded.protobuf.generated.MasterProcedureProtos$ReplaySyncReplicationWALParameter getDefaultInstance();
    Code:
       0: getstatic     #78                 // Field DEFAULT_INSTANCE:Lorg/apache/hadoop/hbase/shaded/protobuf/generated/MasterProcedureProtos$ReplaySyncReplicationWALParameter;
       3: areturn

  public static org.apache.hbase.thirdparty.com.google.protobuf.Parser<org.apache.hadoop.hbase.shaded.protobuf.generated.MasterProcedureProtos$ReplaySyncReplicationWALParameter> parser();
    Code:
       0: getstatic     #64                 // Field PARSER:Lorg/apache/hbase/thirdparty/com/google/protobuf/Parser;
       3: areturn

  public org.apache.hbase.thirdparty.com.google.protobuf.Parser<org.apache.hadoop.hbase.shaded.protobuf.generated.MasterProcedureProtos$ReplaySyncReplicationWALParameter> getParserForType();
    Code:
       0: getstatic     #64                 // Field PARSER:Lorg/apache/hbase/thirdparty/com/google/protobuf/Parser;
       3: areturn

  public org.apache.hadoop.hbase.shaded.protobuf.generated.MasterProcedureProtos$ReplaySyncReplicationWALParameter getDefaultInstanceForType();
    Code:
       0: getstatic     #78                 // Field DEFAULT_INSTANCE:Lorg/apache/hadoop/hbase/shaded/protobuf/generated/MasterProcedureProtos$ReplaySyncReplicationWALParameter;
       3: areturn

  protected org.apache.hbase.thirdparty.com.google.protobuf.Message$Builder newBuilderForType(org.apache.hbase.thirdparty.com.google.protobuf.GeneratedMessageV3$BuilderParent);
    Code:
       0: aload_0
       1: aload_1
       2: invokevirtual #83                 // Method newBuilderForType:(Lorg/apache/hbase/thirdparty/com/google/protobuf/GeneratedMessageV3$BuilderParent;)Lorg/apache/hadoop/hbase/shaded/protobuf/generated/MasterProcedureProtos$ReplaySyncReplicationWALParameter$Builder;
       5: areturn

  public org.apache.hbase.thirdparty.com.google.protobuf.Message$Builder toBuilder();
    Code:
       0: aload_0
       1: invokevirtual #79                 // Method toBuilder:()Lorg/apache/hadoop/hbase/shaded/protobuf/generated/MasterProcedureProtos$ReplaySyncReplicationWALParameter$Builder;
       4: areturn

  public org.apache.hbase.thirdparty.com.google.protobuf.Message$Builder newBuilderForType();
    Code:
       0: aload_0
       1: invokevirtual #84                 // Method newBuilderForType:()Lorg/apache/hadoop/hbase/shaded/protobuf/generated/MasterProcedureProtos$ReplaySyncReplicationWALParameter$Builder;
       4: areturn

  public org.apache.hbase.thirdparty.com.google.protobuf.MessageLite$Builder toBuilder();
    Code:
       0: aload_0
       1: invokevirtual #79                 // Method toBuilder:()Lorg/apache/hadoop/hbase/shaded/protobuf/generated/MasterProcedureProtos$ReplaySyncReplicationWALParameter$Builder;
       4: areturn

  public org.apache.hbase.thirdparty.com.google.protobuf.MessageLite$Builder newBuilderForType();
    Code:
       0: aload_0
       1: invokevirtual #84                 // Method newBuilderForType:()Lorg/apache/hadoop/hbase/shaded/protobuf/generated/MasterProcedureProtos$ReplaySyncReplicationWALParameter$Builder;
       4: areturn

  public org.apache.hbase.thirdparty.com.google.protobuf.MessageLite getDefaultInstanceForType();
    Code:
       0: aload_0
       1: invokevirtual #85                 // Method getDefaultInstanceForType:()Lorg/apache/hadoop/hbase/shaded/protobuf/generated/MasterProcedureProtos$ReplaySyncReplicationWALParameter;
       4: areturn

  public org.apache.hbase.thirdparty.com.google.protobuf.Message getDefaultInstanceForType();
    Code:
       0: aload_0
       1: invokevirtual #85                 // Method getDefaultInstanceForType:()Lorg/apache/hadoop/hbase/shaded/protobuf/generated/MasterProcedureProtos$ReplaySyncReplicationWALParameter;
       4: areturn

  public java.util.List getWalList();
    Code:
       0: aload_0
       1: invokevirtual #50                 // Method getWalList:()Lorg/apache/hbase/thirdparty/com/google/protobuf/ProtocolStringList;
       4: areturn

  static boolean access$45600();
    Code:
       0: getstatic     #7                  // Field alwaysUseFieldBuilders:Z
       3: ireturn

  org.apache.hadoop.hbase.shaded.protobuf.generated.MasterProcedureProtos$ReplaySyncReplicationWALParameter(org.apache.hbase.thirdparty.com.google.protobuf.GeneratedMessageV3$Builder, org.apache.hadoop.hbase.shaded.protobuf.generated.MasterProcedureProtos$1);
    Code:
       0: aload_0
       1: aload_1
       2: invokespecial #6                  // Method "<init>":(Lorg/apache/hbase/thirdparty/com/google/protobuf/GeneratedMessageV3$Builder;)V
       5: return

  static java.lang.Object access$45802(org.apache.hadoop.hbase.shaded.protobuf.generated.MasterProcedureProtos$ReplaySyncReplicationWALParameter, java.lang.Object);
    Code:
       0: aload_0
       1: aload_1
       2: dup_x1
       3: putfield      #5                  // Field peerId_:Ljava/lang/Object;
       6: areturn

  static org.apache.hbase.thirdparty.com.google.protobuf.LazyStringList access$45902(org.apache.hadoop.hbase.shaded.protobuf.generated.MasterProcedureProtos$ReplaySyncReplicationWALParameter, org.apache.hbase.thirdparty.com.google.protobuf.LazyStringList);
    Code:
       0: aload_0
       1: aload_1
       2: dup_x1
       3: putfield      #4                  // Field wal_:Lorg/apache/hbase/thirdparty/com/google/protobuf/LazyStringList;
       6: areturn

  static int access$46002(org.apache.hadoop.hbase.shaded.protobuf.generated.MasterProcedureProtos$ReplaySyncReplicationWALParameter, int);
    Code:
       0: aload_0
       1: iload_1
       2: dup_x1
       3: putfield      #3                  // Field bitField0_:I
       6: ireturn

  static java.lang.Object access$45800(org.apache.hadoop.hbase.shaded.protobuf.generated.MasterProcedureProtos$ReplaySyncReplicationWALParameter);
    Code:
       0: aload_0
       1: getfield      #5                  // Field peerId_:Ljava/lang/Object;
       4: areturn

  static org.apache.hbase.thirdparty.com.google.protobuf.LazyStringList access$45900(org.apache.hadoop.hbase.shaded.protobuf.generated.MasterProcedureProtos$ReplaySyncReplicationWALParameter);
    Code:
       0: aload_0
       1: getfield      #4                  // Field wal_:Lorg/apache/hbase/thirdparty/com/google/protobuf/LazyStringList;
       4: areturn

  static org.apache.hbase.thirdparty.com.google.protobuf.UnknownFieldSet access$46100(org.apache.hadoop.hbase.shaded.protobuf.generated.MasterProcedureProtos$ReplaySyncReplicationWALParameter);
    Code:
       0: aload_0
       1: getfield      #2                  // Field unknownFields:Lorg/apache/hbase/thirdparty/com/google/protobuf/UnknownFieldSet;
       4: areturn

  org.apache.hadoop.hbase.shaded.protobuf.generated.MasterProcedureProtos$ReplaySyncReplicationWALParameter(org.apache.hbase.thirdparty.com.google.protobuf.CodedInputStream, org.apache.hbase.thirdparty.com.google.protobuf.ExtensionRegistryLite, org.apache.hadoop.hbase.shaded.protobuf.generated.MasterProcedureProtos$1) throws org.apache.hbase.thirdparty.com.google.protobuf.InvalidProtocolBufferException;
    Code:
       0: aload_0
       1: aload_1
       2: aload_2
       3: invokespecial #1                  // Method "<init>":(Lorg/apache/hbase/thirdparty/com/google/protobuf/CodedInputStream;Lorg/apache/hbase/thirdparty/com/google/protobuf/ExtensionRegistryLite;)V
       6: return

  static {};
    Code:
       0: new           #32                 // class org/apache/hadoop/hbase/shaded/protobuf/generated/MasterProcedureProtos$ReplaySyncReplicationWALParameter
       3: dup
       4: invokespecial #13                 // Method "<init>":()V
       7: putstatic     #78                 // Field DEFAULT_INSTANCE:Lorg/apache/hadoop/hbase/shaded/protobuf/generated/MasterProcedureProtos$ReplaySyncReplicationWALParameter;
      10: new           #86                 // class org/apache/hadoop/hbase/shaded/protobuf/generated/MasterProcedureProtos$ReplaySyncReplicationWALParameter$1
      13: dup
      14: invokespecial #87                 // Method org/apache/hadoop/hbase/shaded/protobuf/generated/MasterProcedureProtos$ReplaySyncReplicationWALParameter$1."<init>":()V
      17: putstatic     #64                 // Field PARSER:Lorg/apache/hbase/thirdparty/com/google/protobuf/Parser;
      20: return
}
