Compiled from "MasterProcedureProtos.java"
public final class org.apache.hadoop.hbase.shaded.protobuf.generated.MasterProcedureProtos$MergeTableRegionsState extends java.lang.Enum<org.apache.hadoop.hbase.shaded.protobuf.generated.MasterProcedureProtos$MergeTableRegionsState> implements org.apache.hbase.thirdparty.com.google.protobuf.ProtocolMessageEnum {
  public static final org.apache.hadoop.hbase.shaded.protobuf.generated.MasterProcedureProtos$MergeTableRegionsState MERGE_TABLE_REGIONS_PREPARE;

  public static final org.apache.hadoop.hbase.shaded.protobuf.generated.MasterProcedureProtos$MergeTableRegionsState MERGE_TABLE_REGIONS_PRE_OPERATION;

  public static final org.apache.hadoop.hbase.shaded.protobuf.generated.MasterProcedureProtos$MergeTableRegionsState MERGE_TABLE_REGIONS_PRE_MERGE_OPERATION;

  public static final org.apache.hadoop.hbase.shaded.protobuf.generated.MasterProcedureProtos$MergeTableRegionsState MERGE_TABLE_REGIONS_CLOSE_REGIONS;

  public static final org.apache.hadoop.hbase.shaded.protobuf.generated.MasterProcedureProtos$MergeTableRegionsState MERGE_TABLE_REGIONS_CREATE_MERGED_REGION;

  public static final org.apache.hadoop.hbase.shaded.protobuf.generated.MasterProcedureProtos$MergeTableRegionsState MERGE_TABLE_REGIONS_WRITE_MAX_SEQUENCE_ID_FILE;

  public static final org.apache.hadoop.hbase.shaded.protobuf.generated.MasterProcedureProtos$MergeTableRegionsState MERGE_TABLE_REGIONS_PRE_MERGE_COMMIT_OPERATION;

  public static final org.apache.hadoop.hbase.shaded.protobuf.generated.MasterProcedureProtos$MergeTableRegionsState MERGE_TABLE_REGIONS_UPDATE_META;

  public static final org.apache.hadoop.hbase.shaded.protobuf.generated.MasterProcedureProtos$MergeTableRegionsState MERGE_TABLE_REGIONS_POST_MERGE_COMMIT_OPERATION;

  public static final org.apache.hadoop.hbase.shaded.protobuf.generated.MasterProcedureProtos$MergeTableRegionsState MERGE_TABLE_REGIONS_OPEN_MERGED_REGION;

  public static final org.apache.hadoop.hbase.shaded.protobuf.generated.MasterProcedureProtos$MergeTableRegionsState MERGE_TABLE_REGIONS_POST_OPERATION;

  public static final org.apache.hadoop.hbase.shaded.protobuf.generated.MasterProcedureProtos$MergeTableRegionsState MERGE_TABLE_REGIONS_CHECK_CLOSED_REGIONS;

  public static final int MERGE_TABLE_REGIONS_PREPARE_VALUE;

  public static final int MERGE_TABLE_REGIONS_PRE_OPERATION_VALUE;

  public static final int MERGE_TABLE_REGIONS_PRE_MERGE_OPERATION_VALUE;

  public static final int MERGE_TABLE_REGIONS_CLOSE_REGIONS_VALUE;

  public static final int MERGE_TABLE_REGIONS_CREATE_MERGED_REGION_VALUE;

  public static final int MERGE_TABLE_REGIONS_WRITE_MAX_SEQUENCE_ID_FILE_VALUE;

  public static final int MERGE_TABLE_REGIONS_PRE_MERGE_COMMIT_OPERATION_VALUE;

  public static final int MERGE_TABLE_REGIONS_UPDATE_META_VALUE;

  public static final int MERGE_TABLE_REGIONS_POST_MERGE_COMMIT_OPERATION_VALUE;

  public static final int MERGE_TABLE_REGIONS_OPEN_MERGED_REGION_VALUE;

  public static final int MERGE_TABLE_REGIONS_POST_OPERATION_VALUE;

  public static final int MERGE_TABLE_REGIONS_CHECK_CLOSED_REGIONS_VALUE;

  public static org.apache.hadoop.hbase.shaded.protobuf.generated.MasterProcedureProtos$MergeTableRegionsState[] values();
    Code:
       0: getstatic     #1                  // Field $VALUES:[Lorg/apache/hadoop/hbase/shaded/protobuf/generated/MasterProcedureProtos$MergeTableRegionsState;
       3: invokevirtual #2                  // Method "[Lorg/apache/hadoop/hbase/shaded/protobuf/generated/MasterProcedureProtos$MergeTableRegionsState;".clone:()Ljava/lang/Object;
       6: checkcast     #3                  // class "[Lorg/apache/hadoop/hbase/shaded/protobuf/generated/MasterProcedureProtos$MergeTableRegionsState;"
       9: areturn

  public static org.apache.hadoop.hbase.shaded.protobuf.generated.MasterProcedureProtos$MergeTableRegionsState valueOf(java.lang.String);
    Code:
       0: ldc           #4                  // class org/apache/hadoop/hbase/shaded/protobuf/generated/MasterProcedureProtos$MergeTableRegionsState
       2: aload_0
       3: invokestatic  #5                  // Method java/lang/Enum.valueOf:(Ljava/lang/Class;Ljava/lang/String;)Ljava/lang/Enum;
       6: checkcast     #4                  // class org/apache/hadoop/hbase/shaded/protobuf/generated/MasterProcedureProtos$MergeTableRegionsState
       9: areturn

  public final int getNumber();
    Code:
       0: aload_0
       1: getfield      #6                  // Field value:I
       4: ireturn

  public static org.apache.hadoop.hbase.shaded.protobuf.generated.MasterProcedureProtos$MergeTableRegionsState valueOf(int);
    Code:
       0: iload_0
       1: invokestatic  #7                  // Method forNumber:(I)Lorg/apache/hadoop/hbase/shaded/protobuf/generated/MasterProcedureProtos$MergeTableRegionsState;
       4: areturn

  public static org.apache.hadoop.hbase.shaded.protobuf.generated.MasterProcedureProtos$MergeTableRegionsState forNumber(int);
    Code:
       0: iload_0
       1: tableswitch   { // 1 to 12
                     1: 64
                     2: 68
                     3: 72
                     4: 76
                     5: 80
                     6: 84
                     7: 88
                     8: 92
                     9: 96
                    10: 100
                    11: 104
                    12: 108
               default: 112
          }
      64: getstatic     #8                  // Field MERGE_TABLE_REGIONS_PREPARE:Lorg/apache/hadoop/hbase/shaded/protobuf/generated/MasterProcedureProtos$MergeTableRegionsState;
      67: areturn
      68: getstatic     #9                  // Field MERGE_TABLE_REGIONS_PRE_OPERATION:Lorg/apache/hadoop/hbase/shaded/protobuf/generated/MasterProcedureProtos$MergeTableRegionsState;
      71: areturn
      72: getstatic     #10                 // Field MERGE_TABLE_REGIONS_PRE_MERGE_OPERATION:Lorg/apache/hadoop/hbase/shaded/protobuf/generated/MasterProcedureProtos$MergeTableRegionsState;
      75: areturn
      76: getstatic     #11                 // Field MERGE_TABLE_REGIONS_CLOSE_REGIONS:Lorg/apache/hadoop/hbase/shaded/protobuf/generated/MasterProcedureProtos$MergeTableRegionsState;
      79: areturn
      80: getstatic     #12                 // Field MERGE_TABLE_REGIONS_CREATE_MERGED_REGION:Lorg/apache/hadoop/hbase/shaded/protobuf/generated/MasterProcedureProtos$MergeTableRegionsState;
      83: areturn
      84: getstatic     #13                 // Field MERGE_TABLE_REGIONS_WRITE_MAX_SEQUENCE_ID_FILE:Lorg/apache/hadoop/hbase/shaded/protobuf/generated/MasterProcedureProtos$MergeTableRegionsState;
      87: areturn
      88: getstatic     #14                 // Field MERGE_TABLE_REGIONS_PRE_MERGE_COMMIT_OPERATION:Lorg/apache/hadoop/hbase/shaded/protobuf/generated/MasterProcedureProtos$MergeTableRegionsState;
      91: areturn
      92: getstatic     #15                 // Field MERGE_TABLE_REGIONS_UPDATE_META:Lorg/apache/hadoop/hbase/shaded/protobuf/generated/MasterProcedureProtos$MergeTableRegionsState;
      95: areturn
      96: getstatic     #16                 // Field MERGE_TABLE_REGIONS_POST_MERGE_COMMIT_OPERATION:Lorg/apache/hadoop/hbase/shaded/protobuf/generated/MasterProcedureProtos$MergeTableRegionsState;
      99: areturn
     100: getstatic     #17                 // Field MERGE_TABLE_REGIONS_OPEN_MERGED_REGION:Lorg/apache/hadoop/hbase/shaded/protobuf/generated/MasterProcedureProtos$MergeTableRegionsState;
     103: areturn
     104: getstatic     #18                 // Field MERGE_TABLE_REGIONS_POST_OPERATION:Lorg/apache/hadoop/hbase/shaded/protobuf/generated/MasterProcedureProtos$MergeTableRegionsState;
     107: areturn
     108: getstatic     #19                 // Field MERGE_TABLE_REGIONS_CHECK_CLOSED_REGIONS:Lorg/apache/hadoop/hbase/shaded/protobuf/generated/MasterProcedureProtos$MergeTableRegionsState;
     111: areturn
     112: aconst_null
     113: areturn

  public static org.apache.hbase.thirdparty.com.google.protobuf.Internal$EnumLiteMap<org.apache.hadoop.hbase.shaded.protobuf.generated.MasterProcedureProtos$MergeTableRegionsState> internalGetValueMap();
    Code:
       0: getstatic     #20                 // Field internalValueMap:Lorg/apache/hbase/thirdparty/com/google/protobuf/Internal$EnumLiteMap;
       3: areturn

  public final org.apache.hbase.thirdparty.com.google.protobuf.Descriptors$EnumValueDescriptor getValueDescriptor();
    Code:
       0: invokestatic  #21                 // Method getDescriptor:()Lorg/apache/hbase/thirdparty/com/google/protobuf/Descriptors$EnumDescriptor;
       3: invokevirtual #22                 // Method org/apache/hbase/thirdparty/com/google/protobuf/Descriptors$EnumDescriptor.getValues:()Ljava/util/List;
       6: aload_0
       7: invokevirtual #23                 // Method ordinal:()I
      10: invokeinterface #24,  2           // InterfaceMethod java/util/List.get:(I)Ljava/lang/Object;
      15: checkcast     #25                 // class org/apache/hbase/thirdparty/com/google/protobuf/Descriptors$EnumValueDescriptor
      18: areturn

  public final org.apache.hbase.thirdparty.com.google.protobuf.Descriptors$EnumDescriptor getDescriptorForType();
    Code:
       0: invokestatic  #21                 // Method getDescriptor:()Lorg/apache/hbase/thirdparty/com/google/protobuf/Descriptors$EnumDescriptor;
       3: areturn

  public static final org.apache.hbase.thirdparty.com.google.protobuf.Descriptors$EnumDescriptor getDescriptor();
    Code:
       0: invokestatic  #26                 // Method org/apache/hadoop/hbase/shaded/protobuf/generated/MasterProcedureProtos.getDescriptor:()Lorg/apache/hbase/thirdparty/com/google/protobuf/Descriptors$FileDescriptor;
       3: invokevirtual #27                 // Method org/apache/hbase/thirdparty/com/google/protobuf/Descriptors$FileDescriptor.getEnumTypes:()Ljava/util/List;
       6: bipush        13
       8: invokeinterface #24,  2           // InterfaceMethod java/util/List.get:(I)Ljava/lang/Object;
      13: checkcast     #28                 // class org/apache/hbase/thirdparty/com/google/protobuf/Descriptors$EnumDescriptor
      16: areturn

  public static org.apache.hadoop.hbase.shaded.protobuf.generated.MasterProcedureProtos$MergeTableRegionsState valueOf(org.apache.hbase.thirdparty.com.google.protobuf.Descriptors$EnumValueDescriptor);
    Code:
       0: aload_0
       1: invokevirtual #29                 // Method org/apache/hbase/thirdparty/com/google/protobuf/Descriptors$EnumValueDescriptor.getType:()Lorg/apache/hbase/thirdparty/com/google/protobuf/Descriptors$EnumDescriptor;
       4: invokestatic  #21                 // Method getDescriptor:()Lorg/apache/hbase/thirdparty/com/google/protobuf/Descriptors$EnumDescriptor;
       7: if_acmpeq     20
      10: new           #30                 // class java/lang/IllegalArgumentException
      13: dup
      14: ldc           #31                 // String EnumValueDescriptor is not for this type.
      16: invokespecial #32                 // Method java/lang/IllegalArgumentException."<init>":(Ljava/lang/String;)V
      19: athrow
      20: getstatic     #33                 // Field VALUES:[Lorg/apache/hadoop/hbase/shaded/protobuf/generated/MasterProcedureProtos$MergeTableRegionsState;
      23: aload_0
      24: invokevirtual #34                 // Method org/apache/hbase/thirdparty/com/google/protobuf/Descriptors$EnumValueDescriptor.getIndex:()I
      27: aaload
      28: areturn

  static {};
    Code:
       0: new           #4                  // class org/apache/hadoop/hbase/shaded/protobuf/generated/MasterProcedureProtos$MergeTableRegionsState
       3: dup
       4: ldc           #36                 // String MERGE_TABLE_REGIONS_PREPARE
       6: iconst_0
       7: iconst_1
       8: invokespecial #37                 // Method "<init>":(Ljava/lang/String;II)V
      11: putstatic     #8                  // Field MERGE_TABLE_REGIONS_PREPARE:Lorg/apache/hadoop/hbase/shaded/protobuf/generated/MasterProcedureProtos$MergeTableRegionsState;
      14: new           #4                  // class org/apache/hadoop/hbase/shaded/protobuf/generated/MasterProcedureProtos$MergeTableRegionsState
      17: dup
      18: ldc           #38                 // String MERGE_TABLE_REGIONS_PRE_OPERATION
      20: iconst_1
      21: iconst_2
      22: invokespecial #37                 // Method "<init>":(Ljava/lang/String;II)V
      25: putstatic     #9                  // Field MERGE_TABLE_REGIONS_PRE_OPERATION:Lorg/apache/hadoop/hbase/shaded/protobuf/generated/MasterProcedureProtos$MergeTableRegionsState;
      28: new           #4                  // class org/apache/hadoop/hbase/shaded/protobuf/generated/MasterProcedureProtos$MergeTableRegionsState
      31: dup
      32: ldc           #39                 // String MERGE_TABLE_REGIONS_PRE_MERGE_OPERATION
      34: iconst_2
      35: iconst_3
      36: invokespecial #37                 // Method "<init>":(Ljava/lang/String;II)V
      39: putstatic     #10                 // Field MERGE_TABLE_REGIONS_PRE_MERGE_OPERATION:Lorg/apache/hadoop/hbase/shaded/protobuf/generated/MasterProcedureProtos$MergeTableRegionsState;
      42: new           #4                  // class org/apache/hadoop/hbase/shaded/protobuf/generated/MasterProcedureProtos$MergeTableRegionsState
      45: dup
      46: ldc           #40                 // String MERGE_TABLE_REGIONS_CLOSE_REGIONS
      48: iconst_3
      49: iconst_4
      50: invokespecial #37                 // Method "<init>":(Ljava/lang/String;II)V
      53: putstatic     #11                 // Field MERGE_TABLE_REGIONS_CLOSE_REGIONS:Lorg/apache/hadoop/hbase/shaded/protobuf/generated/MasterProcedureProtos$MergeTableRegionsState;
      56: new           #4                  // class org/apache/hadoop/hbase/shaded/protobuf/generated/MasterProcedureProtos$MergeTableRegionsState
      59: dup
      60: ldc           #41                 // String MERGE_TABLE_REGIONS_CREATE_MERGED_REGION
      62: iconst_4
      63: iconst_5
      64: invokespecial #37                 // Method "<init>":(Ljava/lang/String;II)V
      67: putstatic     #12                 // Field MERGE_TABLE_REGIONS_CREATE_MERGED_REGION:Lorg/apache/hadoop/hbase/shaded/protobuf/generated/MasterProcedureProtos$MergeTableRegionsState;
      70: new           #4                  // class org/apache/hadoop/hbase/shaded/protobuf/generated/MasterProcedureProtos$MergeTableRegionsState
      73: dup
      74: ldc           #42                 // String MERGE_TABLE_REGIONS_WRITE_MAX_SEQUENCE_ID_FILE
      76: iconst_5
      77: bipush        6
      79: invokespecial #37                 // Method "<init>":(Ljava/lang/String;II)V
      82: putstatic     #13                 // Field MERGE_TABLE_REGIONS_WRITE_MAX_SEQUENCE_ID_FILE:Lorg/apache/hadoop/hbase/shaded/protobuf/generated/MasterProcedureProtos$MergeTableRegionsState;
      85: new           #4                  // class org/apache/hadoop/hbase/shaded/protobuf/generated/MasterProcedureProtos$MergeTableRegionsState
      88: dup
      89: ldc           #43                 // String MERGE_TABLE_REGIONS_PRE_MERGE_COMMIT_OPERATION
      91: bipush        6
      93: bipush        7
      95: invokespecial #37                 // Method "<init>":(Ljava/lang/String;II)V
      98: putstatic     #14                 // Field MERGE_TABLE_REGIONS_PRE_MERGE_COMMIT_OPERATION:Lorg/apache/hadoop/hbase/shaded/protobuf/generated/MasterProcedureProtos$MergeTableRegionsState;
     101: new           #4                  // class org/apache/hadoop/hbase/shaded/protobuf/generated/MasterProcedureProtos$MergeTableRegionsState
     104: dup
     105: ldc           #44                 // String MERGE_TABLE_REGIONS_UPDATE_META
     107: bipush        7
     109: bipush        8
     111: invokespecial #37                 // Method "<init>":(Ljava/lang/String;II)V
     114: putstatic     #15                 // Field MERGE_TABLE_REGIONS_UPDATE_META:Lorg/apache/hadoop/hbase/shaded/protobuf/generated/MasterProcedureProtos$MergeTableRegionsState;
     117: new           #4                  // class org/apache/hadoop/hbase/shaded/protobuf/generated/MasterProcedureProtos$MergeTableRegionsState
     120: dup
     121: ldc           #45                 // String MERGE_TABLE_REGIONS_POST_MERGE_COMMIT_OPERATION
     123: bipush        8
     125: bipush        9
     127: invokespecial #37                 // Method "<init>":(Ljava/lang/String;II)V
     130: putstatic     #16                 // Field MERGE_TABLE_REGIONS_POST_MERGE_COMMIT_OPERATION:Lorg/apache/hadoop/hbase/shaded/protobuf/generated/MasterProcedureProtos$MergeTableRegionsState;
     133: new           #4                  // class org/apache/hadoop/hbase/shaded/protobuf/generated/MasterProcedureProtos$MergeTableRegionsState
     136: dup
     137: ldc           #46                 // String MERGE_TABLE_REGIONS_OPEN_MERGED_REGION
     139: bipush        9
     141: bipush        10
     143: invokespecial #37                 // Method "<init>":(Ljava/lang/String;II)V
     146: putstatic     #17                 // Field MERGE_TABLE_REGIONS_OPEN_MERGED_REGION:Lorg/apache/hadoop/hbase/shaded/protobuf/generated/MasterProcedureProtos$MergeTableRegionsState;
     149: new           #4                  // class org/apache/hadoop/hbase/shaded/protobuf/generated/MasterProcedureProtos$MergeTableRegionsState
     152: dup
     153: ldc           #47                 // String MERGE_TABLE_REGIONS_POST_OPERATION
     155: bipush        10
     157: bipush        11
     159: invokespecial #37                 // Method "<init>":(Ljava/lang/String;II)V
     162: putstatic     #18                 // Field MERGE_TABLE_REGIONS_POST_OPERATION:Lorg/apache/hadoop/hbase/shaded/protobuf/generated/MasterProcedureProtos$MergeTableRegionsState;
     165: new           #4                  // class org/apache/hadoop/hbase/shaded/protobuf/generated/MasterProcedureProtos$MergeTableRegionsState
     168: dup
     169: ldc           #48                 // String MERGE_TABLE_REGIONS_CHECK_CLOSED_REGIONS
     171: bipush        11
     173: bipush        12
     175: invokespecial #37                 // Method "<init>":(Ljava/lang/String;II)V
     178: putstatic     #19                 // Field MERGE_TABLE_REGIONS_CHECK_CLOSED_REGIONS:Lorg/apache/hadoop/hbase/shaded/protobuf/generated/MasterProcedureProtos$MergeTableRegionsState;
     181: bipush        12
     183: anewarray     #4                  // class org/apache/hadoop/hbase/shaded/protobuf/generated/MasterProcedureProtos$MergeTableRegionsState
     186: dup
     187: iconst_0
     188: getstatic     #8                  // Field MERGE_TABLE_REGIONS_PREPARE:Lorg/apache/hadoop/hbase/shaded/protobuf/generated/MasterProcedureProtos$MergeTableRegionsState;
     191: aastore
     192: dup
     193: iconst_1
     194: getstatic     #9                  // Field MERGE_TABLE_REGIONS_PRE_OPERATION:Lorg/apache/hadoop/hbase/shaded/protobuf/generated/MasterProcedureProtos$MergeTableRegionsState;
     197: aastore
     198: dup
     199: iconst_2
     200: getstatic     #10                 // Field MERGE_TABLE_REGIONS_PRE_MERGE_OPERATION:Lorg/apache/hadoop/hbase/shaded/protobuf/generated/MasterProcedureProtos$MergeTableRegionsState;
     203: aastore
     204: dup
     205: iconst_3
     206: getstatic     #11                 // Field MERGE_TABLE_REGIONS_CLOSE_REGIONS:Lorg/apache/hadoop/hbase/shaded/protobuf/generated/MasterProcedureProtos$MergeTableRegionsState;
     209: aastore
     210: dup
     211: iconst_4
     212: getstatic     #12                 // Field MERGE_TABLE_REGIONS_CREATE_MERGED_REGION:Lorg/apache/hadoop/hbase/shaded/protobuf/generated/MasterProcedureProtos$MergeTableRegionsState;
     215: aastore
     216: dup
     217: iconst_5
     218: getstatic     #13                 // Field MERGE_TABLE_REGIONS_WRITE_MAX_SEQUENCE_ID_FILE:Lorg/apache/hadoop/hbase/shaded/protobuf/generated/MasterProcedureProtos$MergeTableRegionsState;
     221: aastore
     222: dup
     223: bipush        6
     225: getstatic     #14                 // Field MERGE_TABLE_REGIONS_PRE_MERGE_COMMIT_OPERATION:Lorg/apache/hadoop/hbase/shaded/protobuf/generated/MasterProcedureProtos$MergeTableRegionsState;
     228: aastore
     229: dup
     230: bipush        7
     232: getstatic     #15                 // Field MERGE_TABLE_REGIONS_UPDATE_META:Lorg/apache/hadoop/hbase/shaded/protobuf/generated/MasterProcedureProtos$MergeTableRegionsState;
     235: aastore
     236: dup
     237: bipush        8
     239: getstatic     #16                 // Field MERGE_TABLE_REGIONS_POST_MERGE_COMMIT_OPERATION:Lorg/apache/hadoop/hbase/shaded/protobuf/generated/MasterProcedureProtos$MergeTableRegionsState;
     242: aastore
     243: dup
     244: bipush        9
     246: getstatic     #17                 // Field MERGE_TABLE_REGIONS_OPEN_MERGED_REGION:Lorg/apache/hadoop/hbase/shaded/protobuf/generated/MasterProcedureProtos$MergeTableRegionsState;
     249: aastore
     250: dup
     251: bipush        10
     253: getstatic     #18                 // Field MERGE_TABLE_REGIONS_POST_OPERATION:Lorg/apache/hadoop/hbase/shaded/protobuf/generated/MasterProcedureProtos$MergeTableRegionsState;
     256: aastore
     257: dup
     258: bipush        11
     260: getstatic     #19                 // Field MERGE_TABLE_REGIONS_CHECK_CLOSED_REGIONS:Lorg/apache/hadoop/hbase/shaded/protobuf/generated/MasterProcedureProtos$MergeTableRegionsState;
     263: aastore
     264: putstatic     #1                  // Field $VALUES:[Lorg/apache/hadoop/hbase/shaded/protobuf/generated/MasterProcedureProtos$MergeTableRegionsState;
     267: new           #49                 // class org/apache/hadoop/hbase/shaded/protobuf/generated/MasterProcedureProtos$MergeTableRegionsState$1
     270: dup
     271: invokespecial #50                 // Method org/apache/hadoop/hbase/shaded/protobuf/generated/MasterProcedureProtos$MergeTableRegionsState$1."<init>":()V
     274: putstatic     #20                 // Field internalValueMap:Lorg/apache/hbase/thirdparty/com/google/protobuf/Internal$EnumLiteMap;
     277: invokestatic  #51                 // Method values:()[Lorg/apache/hadoop/hbase/shaded/protobuf/generated/MasterProcedureProtos$MergeTableRegionsState;
     280: putstatic     #33                 // Field VALUES:[Lorg/apache/hadoop/hbase/shaded/protobuf/generated/MasterProcedureProtos$MergeTableRegionsState;
     283: return
}
