Compiled from "MasterProcedureProtos.java"
public final class org.apache.hadoop.hbase.shaded.protobuf.generated.MasterProcedureProtos$RestoreSnapshotStateData$Builder extends org.apache.hbase.thirdparty.com.google.protobuf.GeneratedMessageV3$Builder<org.apache.hadoop.hbase.shaded.protobuf.generated.MasterProcedureProtos$RestoreSnapshotStateData$Builder> implements org.apache.hadoop.hbase.shaded.protobuf.generated.MasterProcedureProtos$RestoreSnapshotStateDataOrBuilder {
  public static final org.apache.hbase.thirdparty.com.google.protobuf.Descriptors$Descriptor getDescriptor();
    Code:
       0: invokestatic  #3                  // Method org/apache/hadoop/hbase/shaded/protobuf/generated/MasterProcedureProtos.access$13900:()Lorg/apache/hbase/thirdparty/com/google/protobuf/Descriptors$Descriptor;
       3: areturn

  protected org.apache.hbase.thirdparty.com.google.protobuf.GeneratedMessageV3$FieldAccessorTable internalGetFieldAccessorTable();
    Code:
       0: invokestatic  #4                  // Method org/apache/hadoop/hbase/shaded/protobuf/generated/MasterProcedureProtos.access$14000:()Lorg/apache/hbase/thirdparty/com/google/protobuf/GeneratedMessageV3$FieldAccessorTable;
       3: ldc           #5                  // class org/apache/hadoop/hbase/shaded/protobuf/generated/MasterProcedureProtos$RestoreSnapshotStateData
       5: ldc           #6                  // class org/apache/hadoop/hbase/shaded/protobuf/generated/MasterProcedureProtos$RestoreSnapshotStateData$Builder
       7: invokevirtual #7                  // Method org/apache/hbase/thirdparty/com/google/protobuf/GeneratedMessageV3$FieldAccessorTable.ensureFieldAccessorsInitialized:(Ljava/lang/Class;Ljava/lang/Class;)Lorg/apache/hbase/thirdparty/com/google/protobuf/GeneratedMessageV3$FieldAccessorTable;
      10: areturn

  public org.apache.hadoop.hbase.shaded.protobuf.generated.MasterProcedureProtos$RestoreSnapshotStateData$Builder clear();
    Code:
       0: aload_0
       1: invokespecial #27                 // Method org/apache/hbase/thirdparty/com/google/protobuf/GeneratedMessageV3$Builder.clear:()Lorg/apache/hbase/thirdparty/com/google/protobuf/GeneratedMessageV3$Builder;
       4: pop
       5: aload_0
       6: getfield      #28                 // Field userInfoBuilder_:Lorg/apache/hbase/thirdparty/com/google/protobuf/SingleFieldBuilderV3;
       9: ifnonnull     20
      12: aload_0
      13: aconst_null
      14: putfield      #9                  // Field userInfo_:Lorg/apache/hadoop/hbase/shaded/protobuf/generated/RPCProtos$UserInformation;
      17: goto          28
      20: aload_0
      21: getfield      #28                 // Field userInfoBuilder_:Lorg/apache/hbase/thirdparty/com/google/protobuf/SingleFieldBuilderV3;
      24: invokevirtual #29                 // Method org/apache/hbase/thirdparty/com/google/protobuf/SingleFieldBuilderV3.clear:()Lorg/apache/hbase/thirdparty/com/google/protobuf/SingleFieldBuilderV3;
      27: pop
      28: aload_0
      29: aload_0
      30: getfield      #30                 // Field bitField0_:I
      33: bipush        -2
      35: iand
      36: putfield      #30                 // Field bitField0_:I
      39: aload_0
      40: getfield      #31                 // Field snapshotBuilder_:Lorg/apache/hbase/thirdparty/com/google/protobuf/SingleFieldBuilderV3;
      43: ifnonnull     54
      46: aload_0
      47: aconst_null
      48: putfield      #10                 // Field snapshot_:Lorg/apache/hadoop/hbase/shaded/protobuf/generated/SnapshotProtos$SnapshotDescription;
      51: goto          62
      54: aload_0
      55: getfield      #31                 // Field snapshotBuilder_:Lorg/apache/hbase/thirdparty/com/google/protobuf/SingleFieldBuilderV3;
      58: invokevirtual #29                 // Method org/apache/hbase/thirdparty/com/google/protobuf/SingleFieldBuilderV3.clear:()Lorg/apache/hbase/thirdparty/com/google/protobuf/SingleFieldBuilderV3;
      61: pop
      62: aload_0
      63: aload_0
      64: getfield      #30                 // Field bitField0_:I
      67: bipush        -3
      69: iand
      70: putfield      #30                 // Field bitField0_:I
      73: aload_0
      74: getfield      #32                 // Field modifiedTableSchemaBuilder_:Lorg/apache/hbase/thirdparty/com/google/protobuf/SingleFieldBuilderV3;
      77: ifnonnull     88
      80: aload_0
      81: aconst_null
      82: putfield      #11                 // Field modifiedTableSchema_:Lorg/apache/hadoop/hbase/shaded/protobuf/generated/HBaseProtos$TableSchema;
      85: goto          96
      88: aload_0
      89: getfield      #32                 // Field modifiedTableSchemaBuilder_:Lorg/apache/hbase/thirdparty/com/google/protobuf/SingleFieldBuilderV3;
      92: invokevirtual #29                 // Method org/apache/hbase/thirdparty/com/google/protobuf/SingleFieldBuilderV3.clear:()Lorg/apache/hbase/thirdparty/com/google/protobuf/SingleFieldBuilderV3;
      95: pop
      96: aload_0
      97: aload_0
      98: getfield      #30                 // Field bitField0_:I
     101: bipush        -5
     103: iand
     104: putfield      #30                 // Field bitField0_:I
     107: aload_0
     108: getfield      #33                 // Field regionInfoForRestoreBuilder_:Lorg/apache/hbase/thirdparty/com/google/protobuf/RepeatedFieldBuilderV3;
     111: ifnonnull     135
     114: aload_0
     115: invokestatic  #12                 // Method java/util/Collections.emptyList:()Ljava/util/List;
     118: putfield      #13                 // Field regionInfoForRestore_:Ljava/util/List;
     121: aload_0
     122: aload_0
     123: getfield      #30                 // Field bitField0_:I
     126: bipush        -9
     128: iand
     129: putfield      #30                 // Field bitField0_:I
     132: goto          142
     135: aload_0
     136: getfield      #33                 // Field regionInfoForRestoreBuilder_:Lorg/apache/hbase/thirdparty/com/google/protobuf/RepeatedFieldBuilderV3;
     139: invokevirtual #34                 // Method org/apache/hbase/thirdparty/com/google/protobuf/RepeatedFieldBuilderV3.clear:()V
     142: aload_0
     143: getfield      #35                 // Field regionInfoForRemoveBuilder_:Lorg/apache/hbase/thirdparty/com/google/protobuf/RepeatedFieldBuilderV3;
     146: ifnonnull     170
     149: aload_0
     150: invokestatic  #12                 // Method java/util/Collections.emptyList:()Ljava/util/List;
     153: putfield      #14                 // Field regionInfoForRemove_:Ljava/util/List;
     156: aload_0
     157: aload_0
     158: getfield      #30                 // Field bitField0_:I
     161: bipush        -17
     163: iand
     164: putfield      #30                 // Field bitField0_:I
     167: goto          177
     170: aload_0
     171: getfield      #35                 // Field regionInfoForRemoveBuilder_:Lorg/apache/hbase/thirdparty/com/google/protobuf/RepeatedFieldBuilderV3;
     174: invokevirtual #34                 // Method org/apache/hbase/thirdparty/com/google/protobuf/RepeatedFieldBuilderV3.clear:()V
     177: aload_0
     178: getfield      #36                 // Field regionInfoForAddBuilder_:Lorg/apache/hbase/thirdparty/com/google/protobuf/RepeatedFieldBuilderV3;
     181: ifnonnull     205
     184: aload_0
     185: invokestatic  #12                 // Method java/util/Collections.emptyList:()Ljava/util/List;
     188: putfield      #15                 // Field regionInfoForAdd_:Ljava/util/List;
     191: aload_0
     192: aload_0
     193: getfield      #30                 // Field bitField0_:I
     196: bipush        -33
     198: iand
     199: putfield      #30                 // Field bitField0_:I
     202: goto          212
     205: aload_0
     206: getfield      #36                 // Field regionInfoForAddBuilder_:Lorg/apache/hbase/thirdparty/com/google/protobuf/RepeatedFieldBuilderV3;
     209: invokevirtual #34                 // Method org/apache/hbase/thirdparty/com/google/protobuf/RepeatedFieldBuilderV3.clear:()V
     212: aload_0
     213: getfield      #37                 // Field parentToChildRegionsPairListBuilder_:Lorg/apache/hbase/thirdparty/com/google/protobuf/RepeatedFieldBuilderV3;
     216: ifnonnull     240
     219: aload_0
     220: invokestatic  #12                 // Method java/util/Collections.emptyList:()Ljava/util/List;
     223: putfield      #16                 // Field parentToChildRegionsPairList_:Ljava/util/List;
     226: aload_0
     227: aload_0
     228: getfield      #30                 // Field bitField0_:I
     231: bipush        -65
     233: iand
     234: putfield      #30                 // Field bitField0_:I
     237: goto          247
     240: aload_0
     241: getfield      #37                 // Field parentToChildRegionsPairListBuilder_:Lorg/apache/hbase/thirdparty/com/google/protobuf/RepeatedFieldBuilderV3;
     244: invokevirtual #34                 // Method org/apache/hbase/thirdparty/com/google/protobuf/RepeatedFieldBuilderV3.clear:()V
     247: aload_0
     248: areturn

  public org.apache.hbase.thirdparty.com.google.protobuf.Descriptors$Descriptor getDescriptorForType();
    Code:
       0: invokestatic  #3                  // Method org/apache/hadoop/hbase/shaded/protobuf/generated/MasterProcedureProtos.access$13900:()Lorg/apache/hbase/thirdparty/com/google/protobuf/Descriptors$Descriptor;
       3: areturn

  public org.apache.hadoop.hbase.shaded.protobuf.generated.MasterProcedureProtos$RestoreSnapshotStateData getDefaultInstanceForType();
    Code:
       0: invokestatic  #38                 // Method org/apache/hadoop/hbase/shaded/protobuf/generated/MasterProcedureProtos$RestoreSnapshotStateData.getDefaultInstance:()Lorg/apache/hadoop/hbase/shaded/protobuf/generated/MasterProcedureProtos$RestoreSnapshotStateData;
       3: areturn

  public org.apache.hadoop.hbase.shaded.protobuf.generated.MasterProcedureProtos$RestoreSnapshotStateData build();
    Code:
       0: aload_0
       1: invokevirtual #39                 // Method buildPartial:()Lorg/apache/hadoop/hbase/shaded/protobuf/generated/MasterProcedureProtos$RestoreSnapshotStateData;
       4: astore_1
       5: aload_1
       6: invokevirtual #40                 // Method org/apache/hadoop/hbase/shaded/protobuf/generated/MasterProcedureProtos$RestoreSnapshotStateData.isInitialized:()Z
       9: ifne          17
      12: aload_1
      13: invokestatic  #41                 // Method newUninitializedMessageException:(Lorg/apache/hbase/thirdparty/com/google/protobuf/Message;)Lorg/apache/hbase/thirdparty/com/google/protobuf/UninitializedMessageException;
      16: athrow
      17: aload_1
      18: areturn

  public org.apache.hadoop.hbase.shaded.protobuf.generated.MasterProcedureProtos$RestoreSnapshotStateData buildPartial();
    Code:
       0: new           #5                  // class org/apache/hadoop/hbase/shaded/protobuf/generated/MasterProcedureProtos$RestoreSnapshotStateData
       3: dup
       4: aload_0
       5: aconst_null
       6: invokespecial #42                 // Method org/apache/hadoop/hbase/shaded/protobuf/generated/MasterProcedureProtos$RestoreSnapshotStateData."<init>":(Lorg/apache/hbase/thirdparty/com/google/protobuf/GeneratedMessageV3$Builder;Lorg/apache/hadoop/hbase/shaded/protobuf/generated/MasterProcedureProtos$1;)V
       9: astore_1
      10: aload_0
      11: getfield      #30                 // Field bitField0_:I
      14: istore_2
      15: iconst_0
      16: istore_3
      17: iload_2
      18: iconst_1
      19: iand
      20: iconst_1
      21: if_icmpne     28
      24: iload_3
      25: iconst_1
      26: ior
      27: istore_3
      28: aload_0
      29: getfield      #28                 // Field userInfoBuilder_:Lorg/apache/hbase/thirdparty/com/google/protobuf/SingleFieldBuilderV3;
      32: ifnonnull     47
      35: aload_1
      36: aload_0
      37: getfield      #9                  // Field userInfo_:Lorg/apache/hadoop/hbase/shaded/protobuf/generated/RPCProtos$UserInformation;
      40: invokestatic  #43                 // Method org/apache/hadoop/hbase/shaded/protobuf/generated/MasterProcedureProtos$RestoreSnapshotStateData.access$14502:(Lorg/apache/hadoop/hbase/shaded/protobuf/generated/MasterProcedureProtos$RestoreSnapshotStateData;Lorg/apache/hadoop/hbase/shaded/protobuf/generated/RPCProtos$UserInformation;)Lorg/apache/hadoop/hbase/shaded/protobuf/generated/RPCProtos$UserInformation;
      43: pop
      44: goto          62
      47: aload_1
      48: aload_0
      49: getfield      #28                 // Field userInfoBuilder_:Lorg/apache/hbase/thirdparty/com/google/protobuf/SingleFieldBuilderV3;
      52: invokevirtual #44                 // Method org/apache/hbase/thirdparty/com/google/protobuf/SingleFieldBuilderV3.build:()Lorg/apache/hbase/thirdparty/com/google/protobuf/AbstractMessage;
      55: checkcast     #45                 // class org/apache/hadoop/hbase/shaded/protobuf/generated/RPCProtos$UserInformation
      58: invokestatic  #43                 // Method org/apache/hadoop/hbase/shaded/protobuf/generated/MasterProcedureProtos$RestoreSnapshotStateData.access$14502:(Lorg/apache/hadoop/hbase/shaded/protobuf/generated/MasterProcedureProtos$RestoreSnapshotStateData;Lorg/apache/hadoop/hbase/shaded/protobuf/generated/RPCProtos$UserInformation;)Lorg/apache/hadoop/hbase/shaded/protobuf/generated/RPCProtos$UserInformation;
      61: pop
      62: iload_2
      63: iconst_2
      64: iand
      65: iconst_2
      66: if_icmpne     73
      69: iload_3
      70: iconst_2
      71: ior
      72: istore_3
      73: aload_0
      74: getfield      #31                 // Field snapshotBuilder_:Lorg/apache/hbase/thirdparty/com/google/protobuf/SingleFieldBuilderV3;
      77: ifnonnull     92
      80: aload_1
      81: aload_0
      82: getfield      #10                 // Field snapshot_:Lorg/apache/hadoop/hbase/shaded/protobuf/generated/SnapshotProtos$SnapshotDescription;
      85: invokestatic  #46                 // Method org/apache/hadoop/hbase/shaded/protobuf/generated/MasterProcedureProtos$RestoreSnapshotStateData.access$14602:(Lorg/apache/hadoop/hbase/shaded/protobuf/generated/MasterProcedureProtos$RestoreSnapshotStateData;Lorg/apache/hadoop/hbase/shaded/protobuf/generated/SnapshotProtos$SnapshotDescription;)Lorg/apache/hadoop/hbase/shaded/protobuf/generated/SnapshotProtos$SnapshotDescription;
      88: pop
      89: goto          107
      92: aload_1
      93: aload_0
      94: getfield      #31                 // Field snapshotBuilder_:Lorg/apache/hbase/thirdparty/com/google/protobuf/SingleFieldBuilderV3;
      97: invokevirtual #44                 // Method org/apache/hbase/thirdparty/com/google/protobuf/SingleFieldBuilderV3.build:()Lorg/apache/hbase/thirdparty/com/google/protobuf/AbstractMessage;
     100: checkcast     #47                 // class org/apache/hadoop/hbase/shaded/protobuf/generated/SnapshotProtos$SnapshotDescription
     103: invokestatic  #46                 // Method org/apache/hadoop/hbase/shaded/protobuf/generated/MasterProcedureProtos$RestoreSnapshotStateData.access$14602:(Lorg/apache/hadoop/hbase/shaded/protobuf/generated/MasterProcedureProtos$RestoreSnapshotStateData;Lorg/apache/hadoop/hbase/shaded/protobuf/generated/SnapshotProtos$SnapshotDescription;)Lorg/apache/hadoop/hbase/shaded/protobuf/generated/SnapshotProtos$SnapshotDescription;
     106: pop
     107: iload_2
     108: iconst_4
     109: iand
     110: iconst_4
     111: if_icmpne     118
     114: iload_3
     115: iconst_4
     116: ior
     117: istore_3
     118: aload_0
     119: getfield      #32                 // Field modifiedTableSchemaBuilder_:Lorg/apache/hbase/thirdparty/com/google/protobuf/SingleFieldBuilderV3;
     122: ifnonnull     137
     125: aload_1
     126: aload_0
     127: getfield      #11                 // Field modifiedTableSchema_:Lorg/apache/hadoop/hbase/shaded/protobuf/generated/HBaseProtos$TableSchema;
     130: invokestatic  #48                 // Method org/apache/hadoop/hbase/shaded/protobuf/generated/MasterProcedureProtos$RestoreSnapshotStateData.access$14702:(Lorg/apache/hadoop/hbase/shaded/protobuf/generated/MasterProcedureProtos$RestoreSnapshotStateData;Lorg/apache/hadoop/hbase/shaded/protobuf/generated/HBaseProtos$TableSchema;)Lorg/apache/hadoop/hbase/shaded/protobuf/generated/HBaseProtos$TableSchema;
     133: pop
     134: goto          152
     137: aload_1
     138: aload_0
     139: getfield      #32                 // Field modifiedTableSchemaBuilder_:Lorg/apache/hbase/thirdparty/com/google/protobuf/SingleFieldBuilderV3;
     142: invokevirtual #44                 // Method org/apache/hbase/thirdparty/com/google/protobuf/SingleFieldBuilderV3.build:()Lorg/apache/hbase/thirdparty/com/google/protobuf/AbstractMessage;
     145: checkcast     #49                 // class org/apache/hadoop/hbase/shaded/protobuf/generated/HBaseProtos$TableSchema
     148: invokestatic  #48                 // Method org/apache/hadoop/hbase/shaded/protobuf/generated/MasterProcedureProtos$RestoreSnapshotStateData.access$14702:(Lorg/apache/hadoop/hbase/shaded/protobuf/generated/MasterProcedureProtos$RestoreSnapshotStateData;Lorg/apache/hadoop/hbase/shaded/protobuf/generated/HBaseProtos$TableSchema;)Lorg/apache/hadoop/hbase/shaded/protobuf/generated/HBaseProtos$TableSchema;
     151: pop
     152: aload_0
     153: getfield      #33                 // Field regionInfoForRestoreBuilder_:Lorg/apache/hbase/thirdparty/com/google/protobuf/RepeatedFieldBuilderV3;
     156: ifnonnull     205
     159: aload_0
     160: getfield      #30                 // Field bitField0_:I
     163: bipush        8
     165: iand
     166: bipush        8
     168: if_icmpne     193
     171: aload_0
     172: aload_0
     173: getfield      #13                 // Field regionInfoForRestore_:Ljava/util/List;
     176: invokestatic  #50                 // Method java/util/Collections.unmodifiableList:(Ljava/util/List;)Ljava/util/List;
     179: putfield      #13                 // Field regionInfoForRestore_:Ljava/util/List;
     182: aload_0
     183: aload_0
     184: getfield      #30                 // Field bitField0_:I
     187: bipush        -9
     189: iand
     190: putfield      #30                 // Field bitField0_:I
     193: aload_1
     194: aload_0
     195: getfield      #13                 // Field regionInfoForRestore_:Ljava/util/List;
     198: invokestatic  #51                 // Method org/apache/hadoop/hbase/shaded/protobuf/generated/MasterProcedureProtos$RestoreSnapshotStateData.access$14802:(Lorg/apache/hadoop/hbase/shaded/protobuf/generated/MasterProcedureProtos$RestoreSnapshotStateData;Ljava/util/List;)Ljava/util/List;
     201: pop
     202: goto          217
     205: aload_1
     206: aload_0
     207: getfield      #33                 // Field regionInfoForRestoreBuilder_:Lorg/apache/hbase/thirdparty/com/google/protobuf/RepeatedFieldBuilderV3;
     210: invokevirtual #52                 // Method org/apache/hbase/thirdparty/com/google/protobuf/RepeatedFieldBuilderV3.build:()Ljava/util/List;
     213: invokestatic  #51                 // Method org/apache/hadoop/hbase/shaded/protobuf/generated/MasterProcedureProtos$RestoreSnapshotStateData.access$14802:(Lorg/apache/hadoop/hbase/shaded/protobuf/generated/MasterProcedureProtos$RestoreSnapshotStateData;Ljava/util/List;)Ljava/util/List;
     216: pop
     217: aload_0
     218: getfield      #35                 // Field regionInfoForRemoveBuilder_:Lorg/apache/hbase/thirdparty/com/google/protobuf/RepeatedFieldBuilderV3;
     221: ifnonnull     270
     224: aload_0
     225: getfield      #30                 // Field bitField0_:I
     228: bipush        16
     230: iand
     231: bipush        16
     233: if_icmpne     258
     236: aload_0
     237: aload_0
     238: getfield      #14                 // Field regionInfoForRemove_:Ljava/util/List;
     241: invokestatic  #50                 // Method java/util/Collections.unmodifiableList:(Ljava/util/List;)Ljava/util/List;
     244: putfield      #14                 // Field regionInfoForRemove_:Ljava/util/List;
     247: aload_0
     248: aload_0
     249: getfield      #30                 // Field bitField0_:I
     252: bipush        -17
     254: iand
     255: putfield      #30                 // Field bitField0_:I
     258: aload_1
     259: aload_0
     260: getfield      #14                 // Field regionInfoForRemove_:Ljava/util/List;
     263: invokestatic  #53                 // Method org/apache/hadoop/hbase/shaded/protobuf/generated/MasterProcedureProtos$RestoreSnapshotStateData.access$14902:(Lorg/apache/hadoop/hbase/shaded/protobuf/generated/MasterProcedureProtos$RestoreSnapshotStateData;Ljava/util/List;)Ljava/util/List;
     266: pop
     267: goto          282
     270: aload_1
     271: aload_0
     272: getfield      #35                 // Field regionInfoForRemoveBuilder_:Lorg/apache/hbase/thirdparty/com/google/protobuf/RepeatedFieldBuilderV3;
     275: invokevirtual #52                 // Method org/apache/hbase/thirdparty/com/google/protobuf/RepeatedFieldBuilderV3.build:()Ljava/util/List;
     278: invokestatic  #53                 // Method org/apache/hadoop/hbase/shaded/protobuf/generated/MasterProcedureProtos$RestoreSnapshotStateData.access$14902:(Lorg/apache/hadoop/hbase/shaded/protobuf/generated/MasterProcedureProtos$RestoreSnapshotStateData;Ljava/util/List;)Ljava/util/List;
     281: pop
     282: aload_0
     283: getfield      #36                 // Field regionInfoForAddBuilder_:Lorg/apache/hbase/thirdparty/com/google/protobuf/RepeatedFieldBuilderV3;
     286: ifnonnull     335
     289: aload_0
     290: getfield      #30                 // Field bitField0_:I
     293: bipush        32
     295: iand
     296: bipush        32
     298: if_icmpne     323
     301: aload_0
     302: aload_0
     303: getfield      #15                 // Field regionInfoForAdd_:Ljava/util/List;
     306: invokestatic  #50                 // Method java/util/Collections.unmodifiableList:(Ljava/util/List;)Ljava/util/List;
     309: putfield      #15                 // Field regionInfoForAdd_:Ljava/util/List;
     312: aload_0
     313: aload_0
     314: getfield      #30                 // Field bitField0_:I
     317: bipush        -33
     319: iand
     320: putfield      #30                 // Field bitField0_:I
     323: aload_1
     324: aload_0
     325: getfield      #15                 // Field regionInfoForAdd_:Ljava/util/List;
     328: invokestatic  #54                 // Method org/apache/hadoop/hbase/shaded/protobuf/generated/MasterProcedureProtos$RestoreSnapshotStateData.access$15002:(Lorg/apache/hadoop/hbase/shaded/protobuf/generated/MasterProcedureProtos$RestoreSnapshotStateData;Ljava/util/List;)Ljava/util/List;
     331: pop
     332: goto          347
     335: aload_1
     336: aload_0
     337: getfield      #36                 // Field regionInfoForAddBuilder_:Lorg/apache/hbase/thirdparty/com/google/protobuf/RepeatedFieldBuilderV3;
     340: invokevirtual #52                 // Method org/apache/hbase/thirdparty/com/google/protobuf/RepeatedFieldBuilderV3.build:()Ljava/util/List;
     343: invokestatic  #54                 // Method org/apache/hadoop/hbase/shaded/protobuf/generated/MasterProcedureProtos$RestoreSnapshotStateData.access$15002:(Lorg/apache/hadoop/hbase/shaded/protobuf/generated/MasterProcedureProtos$RestoreSnapshotStateData;Ljava/util/List;)Ljava/util/List;
     346: pop
     347: aload_0
     348: getfield      #37                 // Field parentToChildRegionsPairListBuilder_:Lorg/apache/hbase/thirdparty/com/google/protobuf/RepeatedFieldBuilderV3;
     351: ifnonnull     400
     354: aload_0
     355: getfield      #30                 // Field bitField0_:I
     358: bipush        64
     360: iand
     361: bipush        64
     363: if_icmpne     388
     366: aload_0
     367: aload_0
     368: getfield      #16                 // Field parentToChildRegionsPairList_:Ljava/util/List;
     371: invokestatic  #50                 // Method java/util/Collections.unmodifiableList:(Ljava/util/List;)Ljava/util/List;
     374: putfield      #16                 // Field parentToChildRegionsPairList_:Ljava/util/List;
     377: aload_0
     378: aload_0
     379: getfield      #30                 // Field bitField0_:I
     382: bipush        -65
     384: iand
     385: putfield      #30                 // Field bitField0_:I
     388: aload_1
     389: aload_0
     390: getfield      #16                 // Field parentToChildRegionsPairList_:Ljava/util/List;
     393: invokestatic  #55                 // Method org/apache/hadoop/hbase/shaded/protobuf/generated/MasterProcedureProtos$RestoreSnapshotStateData.access$15102:(Lorg/apache/hadoop/hbase/shaded/protobuf/generated/MasterProcedureProtos$RestoreSnapshotStateData;Ljava/util/List;)Ljava/util/List;
     396: pop
     397: goto          412
     400: aload_1
     401: aload_0
     402: getfield      #37                 // Field parentToChildRegionsPairListBuilder_:Lorg/apache/hbase/thirdparty/com/google/protobuf/RepeatedFieldBuilderV3;
     405: invokevirtual #52                 // Method org/apache/hbase/thirdparty/com/google/protobuf/RepeatedFieldBuilderV3.build:()Ljava/util/List;
     408: invokestatic  #55                 // Method org/apache/hadoop/hbase/shaded/protobuf/generated/MasterProcedureProtos$RestoreSnapshotStateData.access$15102:(Lorg/apache/hadoop/hbase/shaded/protobuf/generated/MasterProcedureProtos$RestoreSnapshotStateData;Ljava/util/List;)Ljava/util/List;
     411: pop
     412: aload_1
     413: iload_3
     414: invokestatic  #56                 // Method org/apache/hadoop/hbase/shaded/protobuf/generated/MasterProcedureProtos$RestoreSnapshotStateData.access$15202:(Lorg/apache/hadoop/hbase/shaded/protobuf/generated/MasterProcedureProtos$RestoreSnapshotStateData;I)I
     417: pop
     418: aload_0
     419: invokevirtual #57                 // Method onBuilt:()V
     422: aload_1
     423: areturn

  public org.apache.hadoop.hbase.shaded.protobuf.generated.MasterProcedureProtos$RestoreSnapshotStateData$Builder clone();
    Code:
       0: aload_0
       1: invokespecial #58                 // Method org/apache/hbase/thirdparty/com/google/protobuf/GeneratedMessageV3$Builder.clone:()Lorg/apache/hbase/thirdparty/com/google/protobuf/GeneratedMessageV3$Builder;
       4: checkcast     #6                  // class org/apache/hadoop/hbase/shaded/protobuf/generated/MasterProcedureProtos$RestoreSnapshotStateData$Builder
       7: areturn

  public org.apache.hadoop.hbase.shaded.protobuf.generated.MasterProcedureProtos$RestoreSnapshotStateData$Builder setField(org.apache.hbase.thirdparty.com.google.protobuf.Descriptors$FieldDescriptor, java.lang.Object);
    Code:
       0: aload_0
       1: aload_1
       2: aload_2
       3: invokespecial #59                 // Method org/apache/hbase/thirdparty/com/google/protobuf/GeneratedMessageV3$Builder.setField:(Lorg/apache/hbase/thirdparty/com/google/protobuf/Descriptors$FieldDescriptor;Ljava/lang/Object;)Lorg/apache/hbase/thirdparty/com/google/protobuf/GeneratedMessageV3$Builder;
       6: checkcast     #6                  // class org/apache/hadoop/hbase/shaded/protobuf/generated/MasterProcedureProtos$RestoreSnapshotStateData$Builder
       9: areturn

  public org.apache.hadoop.hbase.shaded.protobuf.generated.MasterProcedureProtos$RestoreSnapshotStateData$Builder clearField(org.apache.hbase.thirdparty.com.google.protobuf.Descriptors$FieldDescriptor);
    Code:
       0: aload_0
       1: aload_1
       2: invokespecial #60                 // Method org/apache/hbase/thirdparty/com/google/protobuf/GeneratedMessageV3$Builder.clearField:(Lorg/apache/hbase/thirdparty/com/google/protobuf/Descriptors$FieldDescriptor;)Lorg/apache/hbase/thirdparty/com/google/protobuf/GeneratedMessageV3$Builder;
       5: checkcast     #6                  // class org/apache/hadoop/hbase/shaded/protobuf/generated/MasterProcedureProtos$RestoreSnapshotStateData$Builder
       8: areturn

  public org.apache.hadoop.hbase.shaded.protobuf.generated.MasterProcedureProtos$RestoreSnapshotStateData$Builder clearOneof(org.apache.hbase.thirdparty.com.google.protobuf.Descriptors$OneofDescriptor);
    Code:
       0: aload_0
       1: aload_1
       2: invokespecial #61                 // Method org/apache/hbase/thirdparty/com/google/protobuf/GeneratedMessageV3$Builder.clearOneof:(Lorg/apache/hbase/thirdparty/com/google/protobuf/Descriptors$OneofDescriptor;)Lorg/apache/hbase/thirdparty/com/google/protobuf/GeneratedMessageV3$Builder;
       5: checkcast     #6                  // class org/apache/hadoop/hbase/shaded/protobuf/generated/MasterProcedureProtos$RestoreSnapshotStateData$Builder
       8: areturn

  public org.apache.hadoop.hbase.shaded.protobuf.generated.MasterProcedureProtos$RestoreSnapshotStateData$Builder setRepeatedField(org.apache.hbase.thirdparty.com.google.protobuf.Descriptors$FieldDescriptor, int, java.lang.Object);
    Code:
       0: aload_0
       1: aload_1
       2: iload_2
       3: aload_3
       4: invokespecial #62                 // Method org/apache/hbase/thirdparty/com/google/protobuf/GeneratedMessageV3$Builder.setRepeatedField:(Lorg/apache/hbase/thirdparty/com/google/protobuf/Descriptors$FieldDescriptor;ILjava/lang/Object;)Lorg/apache/hbase/thirdparty/com/google/protobuf/GeneratedMessageV3$Builder;
       7: checkcast     #6                  // class org/apache/hadoop/hbase/shaded/protobuf/generated/MasterProcedureProtos$RestoreSnapshotStateData$Builder
      10: areturn

  public org.apache.hadoop.hbase.shaded.protobuf.generated.MasterProcedureProtos$RestoreSnapshotStateData$Builder addRepeatedField(org.apache.hbase.thirdparty.com.google.protobuf.Descriptors$FieldDescriptor, java.lang.Object);
    Code:
       0: aload_0
       1: aload_1
       2: aload_2
       3: invokespecial #63                 // Method org/apache/hbase/thirdparty/com/google/protobuf/GeneratedMessageV3$Builder.addRepeatedField:(Lorg/apache/hbase/thirdparty/com/google/protobuf/Descriptors$FieldDescriptor;Ljava/lang/Object;)Lorg/apache/hbase/thirdparty/com/google/protobuf/GeneratedMessageV3$Builder;
       6: checkcast     #6                  // class org/apache/hadoop/hbase/shaded/protobuf/generated/MasterProcedureProtos$RestoreSnapshotStateData$Builder
       9: areturn

  public org.apache.hadoop.hbase.shaded.protobuf.generated.MasterProcedureProtos$RestoreSnapshotStateData$Builder mergeFrom(org.apache.hbase.thirdparty.com.google.protobuf.Message);
    Code:
       0: aload_1
       1: instanceof    #5                  // class org/apache/hadoop/hbase/shaded/protobuf/generated/MasterProcedureProtos$RestoreSnapshotStateData
       4: ifeq          16
       7: aload_0
       8: aload_1
       9: checkcast     #5                  // class org/apache/hadoop/hbase/shaded/protobuf/generated/MasterProcedureProtos$RestoreSnapshotStateData
      12: invokevirtual #64                 // Method mergeFrom:(Lorg/apache/hadoop/hbase/shaded/protobuf/generated/MasterProcedureProtos$RestoreSnapshotStateData;)Lorg/apache/hadoop/hbase/shaded/protobuf/generated/MasterProcedureProtos$RestoreSnapshotStateData$Builder;
      15: areturn
      16: aload_0
      17: aload_1
      18: invokespecial #65                 // Method org/apache/hbase/thirdparty/com/google/protobuf/GeneratedMessageV3$Builder.mergeFrom:(Lorg/apache/hbase/thirdparty/com/google/protobuf/Message;)Lorg/apache/hbase/thirdparty/com/google/protobuf/AbstractMessage$Builder;
      21: pop
      22: aload_0
      23: areturn

  public org.apache.hadoop.hbase.shaded.protobuf.generated.MasterProcedureProtos$RestoreSnapshotStateData$Builder mergeFrom(org.apache.hadoop.hbase.shaded.protobuf.generated.MasterProcedureProtos$RestoreSnapshotStateData);
    Code:
       0: aload_1
       1: invokestatic  #38                 // Method org/apache/hadoop/hbase/shaded/protobuf/generated/MasterProcedureProtos$RestoreSnapshotStateData.getDefaultInstance:()Lorg/apache/hadoop/hbase/shaded/protobuf/generated/MasterProcedureProtos$RestoreSnapshotStateData;
       4: if_acmpne     9
       7: aload_0
       8: areturn
       9: aload_1
      10: invokevirtual #66                 // Method org/apache/hadoop/hbase/shaded/protobuf/generated/MasterProcedureProtos$RestoreSnapshotStateData.hasUserInfo:()Z
      13: ifeq          25
      16: aload_0
      17: aload_1
      18: invokevirtual #67                 // Method org/apache/hadoop/hbase/shaded/protobuf/generated/MasterProcedureProtos$RestoreSnapshotStateData.getUserInfo:()Lorg/apache/hadoop/hbase/shaded/protobuf/generated/RPCProtos$UserInformation;
      21: invokevirtual #68                 // Method mergeUserInfo:(Lorg/apache/hadoop/hbase/shaded/protobuf/generated/RPCProtos$UserInformation;)Lorg/apache/hadoop/hbase/shaded/protobuf/generated/MasterProcedureProtos$RestoreSnapshotStateData$Builder;
      24: pop
      25: aload_1
      26: invokevirtual #69                 // Method org/apache/hadoop/hbase/shaded/protobuf/generated/MasterProcedureProtos$RestoreSnapshotStateData.hasSnapshot:()Z
      29: ifeq          41
      32: aload_0
      33: aload_1
      34: invokevirtual #70                 // Method org/apache/hadoop/hbase/shaded/protobuf/generated/MasterProcedureProtos$RestoreSnapshotStateData.getSnapshot:()Lorg/apache/hadoop/hbase/shaded/protobuf/generated/SnapshotProtos$SnapshotDescription;
      37: invokevirtual #71                 // Method mergeSnapshot:(Lorg/apache/hadoop/hbase/shaded/protobuf/generated/SnapshotProtos$SnapshotDescription;)Lorg/apache/hadoop/hbase/shaded/protobuf/generated/MasterProcedureProtos$RestoreSnapshotStateData$Builder;
      40: pop
      41: aload_1
      42: invokevirtual #72                 // Method org/apache/hadoop/hbase/shaded/protobuf/generated/MasterProcedureProtos$RestoreSnapshotStateData.hasModifiedTableSchema:()Z
      45: ifeq          57
      48: aload_0
      49: aload_1
      50: invokevirtual #73                 // Method org/apache/hadoop/hbase/shaded/protobuf/generated/MasterProcedureProtos$RestoreSnapshotStateData.getModifiedTableSchema:()Lorg/apache/hadoop/hbase/shaded/protobuf/generated/HBaseProtos$TableSchema;
      53: invokevirtual #74                 // Method mergeModifiedTableSchema:(Lorg/apache/hadoop/hbase/shaded/protobuf/generated/HBaseProtos$TableSchema;)Lorg/apache/hadoop/hbase/shaded/protobuf/generated/MasterProcedureProtos$RestoreSnapshotStateData$Builder;
      56: pop
      57: aload_0
      58: getfield      #33                 // Field regionInfoForRestoreBuilder_:Lorg/apache/hbase/thirdparty/com/google/protobuf/RepeatedFieldBuilderV3;
      61: ifnonnull     135
      64: aload_1
      65: invokestatic  #75                 // Method org/apache/hadoop/hbase/shaded/protobuf/generated/MasterProcedureProtos$RestoreSnapshotStateData.access$14800:(Lorg/apache/hadoop/hbase/shaded/protobuf/generated/MasterProcedureProtos$RestoreSnapshotStateData;)Ljava/util/List;
      68: invokeinterface #76,  1           // InterfaceMethod java/util/List.isEmpty:()Z
      73: ifne          221
      76: aload_0
      77: getfield      #13                 // Field regionInfoForRestore_:Ljava/util/List;
      80: invokeinterface #76,  1           // InterfaceMethod java/util/List.isEmpty:()Z
      85: ifeq          110
      88: aload_0
      89: aload_1
      90: invokestatic  #75                 // Method org/apache/hadoop/hbase/shaded/protobuf/generated/MasterProcedureProtos$RestoreSnapshotStateData.access$14800:(Lorg/apache/hadoop/hbase/shaded/protobuf/generated/MasterProcedureProtos$RestoreSnapshotStateData;)Ljava/util/List;
      93: putfield      #13                 // Field regionInfoForRestore_:Ljava/util/List;
      96: aload_0
      97: aload_0
      98: getfield      #30                 // Field bitField0_:I
     101: bipush        -9
     103: iand
     104: putfield      #30                 // Field bitField0_:I
     107: goto          128
     110: aload_0
     111: invokespecial #77                 // Method ensureRegionInfoForRestoreIsMutable:()V
     114: aload_0
     115: getfield      #13                 // Field regionInfoForRestore_:Ljava/util/List;
     118: aload_1
     119: invokestatic  #75                 // Method org/apache/hadoop/hbase/shaded/protobuf/generated/MasterProcedureProtos$RestoreSnapshotStateData.access$14800:(Lorg/apache/hadoop/hbase/shaded/protobuf/generated/MasterProcedureProtos$RestoreSnapshotStateData;)Ljava/util/List;
     122: invokeinterface #78,  2           // InterfaceMethod java/util/List.addAll:(Ljava/util/Collection;)Z
     127: pop
     128: aload_0
     129: invokevirtual #79                 // Method onChanged:()V
     132: goto          221
     135: aload_1
     136: invokestatic  #75                 // Method org/apache/hadoop/hbase/shaded/protobuf/generated/MasterProcedureProtos$RestoreSnapshotStateData.access$14800:(Lorg/apache/hadoop/hbase/shaded/protobuf/generated/MasterProcedureProtos$RestoreSnapshotStateData;)Ljava/util/List;
     139: invokeinterface #76,  1           // InterfaceMethod java/util/List.isEmpty:()Z
     144: ifne          221
     147: aload_0
     148: getfield      #33                 // Field regionInfoForRestoreBuilder_:Lorg/apache/hbase/thirdparty/com/google/protobuf/RepeatedFieldBuilderV3;
     151: invokevirtual #80                 // Method org/apache/hbase/thirdparty/com/google/protobuf/RepeatedFieldBuilderV3.isEmpty:()Z
     154: ifeq          209
     157: aload_0
     158: getfield      #33                 // Field regionInfoForRestoreBuilder_:Lorg/apache/hbase/thirdparty/com/google/protobuf/RepeatedFieldBuilderV3;
     161: invokevirtual #81                 // Method org/apache/hbase/thirdparty/com/google/protobuf/RepeatedFieldBuilderV3.dispose:()V
     164: aload_0
     165: aconst_null
     166: putfield      #33                 // Field regionInfoForRestoreBuilder_:Lorg/apache/hbase/thirdparty/com/google/protobuf/RepeatedFieldBuilderV3;
     169: aload_0
     170: aload_1
     171: invokestatic  #75                 // Method org/apache/hadoop/hbase/shaded/protobuf/generated/MasterProcedureProtos$RestoreSnapshotStateData.access$14800:(Lorg/apache/hadoop/hbase/shaded/protobuf/generated/MasterProcedureProtos$RestoreSnapshotStateData;)Ljava/util/List;
     174: putfield      #13                 // Field regionInfoForRestore_:Ljava/util/List;
     177: aload_0
     178: aload_0
     179: getfield      #30                 // Field bitField0_:I
     182: bipush        -9
     184: iand
     185: putfield      #30                 // Field bitField0_:I
     188: aload_0
     189: invokestatic  #82                 // Method org/apache/hadoop/hbase/shaded/protobuf/generated/MasterProcedureProtos$RestoreSnapshotStateData.access$15300:()Z
     192: ifeq          202
     195: aload_0
     196: invokespecial #23                 // Method getRegionInfoForRestoreFieldBuilder:()Lorg/apache/hbase/thirdparty/com/google/protobuf/RepeatedFieldBuilderV3;
     199: goto          203
     202: aconst_null
     203: putfield      #33                 // Field regionInfoForRestoreBuilder_:Lorg/apache/hbase/thirdparty/com/google/protobuf/RepeatedFieldBuilderV3;
     206: goto          221
     209: aload_0
     210: getfield      #33                 // Field regionInfoForRestoreBuilder_:Lorg/apache/hbase/thirdparty/com/google/protobuf/RepeatedFieldBuilderV3;
     213: aload_1
     214: invokestatic  #75                 // Method org/apache/hadoop/hbase/shaded/protobuf/generated/MasterProcedureProtos$RestoreSnapshotStateData.access$14800:(Lorg/apache/hadoop/hbase/shaded/protobuf/generated/MasterProcedureProtos$RestoreSnapshotStateData;)Ljava/util/List;
     217: invokevirtual #83                 // Method org/apache/hbase/thirdparty/com/google/protobuf/RepeatedFieldBuilderV3.addAllMessages:(Ljava/lang/Iterable;)Lorg/apache/hbase/thirdparty/com/google/protobuf/RepeatedFieldBuilderV3;
     220: pop
     221: aload_0
     222: getfield      #35                 // Field regionInfoForRemoveBuilder_:Lorg/apache/hbase/thirdparty/com/google/protobuf/RepeatedFieldBuilderV3;
     225: ifnonnull     299
     228: aload_1
     229: invokestatic  #84                 // Method org/apache/hadoop/hbase/shaded/protobuf/generated/MasterProcedureProtos$RestoreSnapshotStateData.access$14900:(Lorg/apache/hadoop/hbase/shaded/protobuf/generated/MasterProcedureProtos$RestoreSnapshotStateData;)Ljava/util/List;
     232: invokeinterface #76,  1           // InterfaceMethod java/util/List.isEmpty:()Z
     237: ifne          385
     240: aload_0
     241: getfield      #14                 // Field regionInfoForRemove_:Ljava/util/List;
     244: invokeinterface #76,  1           // InterfaceMethod java/util/List.isEmpty:()Z
     249: ifeq          274
     252: aload_0
     253: aload_1
     254: invokestatic  #84                 // Method org/apache/hadoop/hbase/shaded/protobuf/generated/MasterProcedureProtos$RestoreSnapshotStateData.access$14900:(Lorg/apache/hadoop/hbase/shaded/protobuf/generated/MasterProcedureProtos$RestoreSnapshotStateData;)Ljava/util/List;
     257: putfield      #14                 // Field regionInfoForRemove_:Ljava/util/List;
     260: aload_0
     261: aload_0
     262: getfield      #30                 // Field bitField0_:I
     265: bipush        -17
     267: iand
     268: putfield      #30                 // Field bitField0_:I
     271: goto          292
     274: aload_0
     275: invokespecial #85                 // Method ensureRegionInfoForRemoveIsMutable:()V
     278: aload_0
     279: getfield      #14                 // Field regionInfoForRemove_:Ljava/util/List;
     282: aload_1
     283: invokestatic  #84                 // Method org/apache/hadoop/hbase/shaded/protobuf/generated/MasterProcedureProtos$RestoreSnapshotStateData.access$14900:(Lorg/apache/hadoop/hbase/shaded/protobuf/generated/MasterProcedureProtos$RestoreSnapshotStateData;)Ljava/util/List;
     286: invokeinterface #78,  2           // InterfaceMethod java/util/List.addAll:(Ljava/util/Collection;)Z
     291: pop
     292: aload_0
     293: invokevirtual #79                 // Method onChanged:()V
     296: goto          385
     299: aload_1
     300: invokestatic  #84                 // Method org/apache/hadoop/hbase/shaded/protobuf/generated/MasterProcedureProtos$RestoreSnapshotStateData.access$14900:(Lorg/apache/hadoop/hbase/shaded/protobuf/generated/MasterProcedureProtos$RestoreSnapshotStateData;)Ljava/util/List;
     303: invokeinterface #76,  1           // InterfaceMethod java/util/List.isEmpty:()Z
     308: ifne          385
     311: aload_0
     312: getfield      #35                 // Field regionInfoForRemoveBuilder_:Lorg/apache/hbase/thirdparty/com/google/protobuf/RepeatedFieldBuilderV3;
     315: invokevirtual #80                 // Method org/apache/hbase/thirdparty/com/google/protobuf/RepeatedFieldBuilderV3.isEmpty:()Z
     318: ifeq          373
     321: aload_0
     322: getfield      #35                 // Field regionInfoForRemoveBuilder_:Lorg/apache/hbase/thirdparty/com/google/protobuf/RepeatedFieldBuilderV3;
     325: invokevirtual #81                 // Method org/apache/hbase/thirdparty/com/google/protobuf/RepeatedFieldBuilderV3.dispose:()V
     328: aload_0
     329: aconst_null
     330: putfield      #35                 // Field regionInfoForRemoveBuilder_:Lorg/apache/hbase/thirdparty/com/google/protobuf/RepeatedFieldBuilderV3;
     333: aload_0
     334: aload_1
     335: invokestatic  #84                 // Method org/apache/hadoop/hbase/shaded/protobuf/generated/MasterProcedureProtos$RestoreSnapshotStateData.access$14900:(Lorg/apache/hadoop/hbase/shaded/protobuf/generated/MasterProcedureProtos$RestoreSnapshotStateData;)Ljava/util/List;
     338: putfield      #14                 // Field regionInfoForRemove_:Ljava/util/List;
     341: aload_0
     342: aload_0
     343: getfield      #30                 // Field bitField0_:I
     346: bipush        -17
     348: iand
     349: putfield      #30                 // Field bitField0_:I
     352: aload_0
     353: invokestatic  #86                 // Method org/apache/hadoop/hbase/shaded/protobuf/generated/MasterProcedureProtos$RestoreSnapshotStateData.access$15400:()Z
     356: ifeq          366
     359: aload_0
     360: invokespecial #24                 // Method getRegionInfoForRemoveFieldBuilder:()Lorg/apache/hbase/thirdparty/com/google/protobuf/RepeatedFieldBuilderV3;
     363: goto          367
     366: aconst_null
     367: putfield      #35                 // Field regionInfoForRemoveBuilder_:Lorg/apache/hbase/thirdparty/com/google/protobuf/RepeatedFieldBuilderV3;
     370: goto          385
     373: aload_0
     374: getfield      #35                 // Field regionInfoForRemoveBuilder_:Lorg/apache/hbase/thirdparty/com/google/protobuf/RepeatedFieldBuilderV3;
     377: aload_1
     378: invokestatic  #84                 // Method org/apache/hadoop/hbase/shaded/protobuf/generated/MasterProcedureProtos$RestoreSnapshotStateData.access$14900:(Lorg/apache/hadoop/hbase/shaded/protobuf/generated/MasterProcedureProtos$RestoreSnapshotStateData;)Ljava/util/List;
     381: invokevirtual #83                 // Method org/apache/hbase/thirdparty/com/google/protobuf/RepeatedFieldBuilderV3.addAllMessages:(Ljava/lang/Iterable;)Lorg/apache/hbase/thirdparty/com/google/protobuf/RepeatedFieldBuilderV3;
     384: pop
     385: aload_0
     386: getfield      #36                 // Field regionInfoForAddBuilder_:Lorg/apache/hbase/thirdparty/com/google/protobuf/RepeatedFieldBuilderV3;
     389: ifnonnull     463
     392: aload_1
     393: invokestatic  #87                 // Method org/apache/hadoop/hbase/shaded/protobuf/generated/MasterProcedureProtos$RestoreSnapshotStateData.access$15000:(Lorg/apache/hadoop/hbase/shaded/protobuf/generated/MasterProcedureProtos$RestoreSnapshotStateData;)Ljava/util/List;
     396: invokeinterface #76,  1           // InterfaceMethod java/util/List.isEmpty:()Z
     401: ifne          549
     404: aload_0
     405: getfield      #15                 // Field regionInfoForAdd_:Ljava/util/List;
     408: invokeinterface #76,  1           // InterfaceMethod java/util/List.isEmpty:()Z
     413: ifeq          438
     416: aload_0
     417: aload_1
     418: invokestatic  #87                 // Method org/apache/hadoop/hbase/shaded/protobuf/generated/MasterProcedureProtos$RestoreSnapshotStateData.access$15000:(Lorg/apache/hadoop/hbase/shaded/protobuf/generated/MasterProcedureProtos$RestoreSnapshotStateData;)Ljava/util/List;
     421: putfield      #15                 // Field regionInfoForAdd_:Ljava/util/List;
     424: aload_0
     425: aload_0
     426: getfield      #30                 // Field bitField0_:I
     429: bipush        -33
     431: iand
     432: putfield      #30                 // Field bitField0_:I
     435: goto          456
     438: aload_0
     439: invokespecial #88                 // Method ensureRegionInfoForAddIsMutable:()V
     442: aload_0
     443: getfield      #15                 // Field regionInfoForAdd_:Ljava/util/List;
     446: aload_1
     447: invokestatic  #87                 // Method org/apache/hadoop/hbase/shaded/protobuf/generated/MasterProcedureProtos$RestoreSnapshotStateData.access$15000:(Lorg/apache/hadoop/hbase/shaded/protobuf/generated/MasterProcedureProtos$RestoreSnapshotStateData;)Ljava/util/List;
     450: invokeinterface #78,  2           // InterfaceMethod java/util/List.addAll:(Ljava/util/Collection;)Z
     455: pop
     456: aload_0
     457: invokevirtual #79                 // Method onChanged:()V
     460: goto          549
     463: aload_1
     464: invokestatic  #87                 // Method org/apache/hadoop/hbase/shaded/protobuf/generated/MasterProcedureProtos$RestoreSnapshotStateData.access$15000:(Lorg/apache/hadoop/hbase/shaded/protobuf/generated/MasterProcedureProtos$RestoreSnapshotStateData;)Ljava/util/List;
     467: invokeinterface #76,  1           // InterfaceMethod java/util/List.isEmpty:()Z
     472: ifne          549
     475: aload_0
     476: getfield      #36                 // Field regionInfoForAddBuilder_:Lorg/apache/hbase/thirdparty/com/google/protobuf/RepeatedFieldBuilderV3;
     479: invokevirtual #80                 // Method org/apache/hbase/thirdparty/com/google/protobuf/RepeatedFieldBuilderV3.isEmpty:()Z
     482: ifeq          537
     485: aload_0
     486: getfield      #36                 // Field regionInfoForAddBuilder_:Lorg/apache/hbase/thirdparty/com/google/protobuf/RepeatedFieldBuilderV3;
     489: invokevirtual #81                 // Method org/apache/hbase/thirdparty/com/google/protobuf/RepeatedFieldBuilderV3.dispose:()V
     492: aload_0
     493: aconst_null
     494: putfield      #36                 // Field regionInfoForAddBuilder_:Lorg/apache/hbase/thirdparty/com/google/protobuf/RepeatedFieldBuilderV3;
     497: aload_0
     498: aload_1
     499: invokestatic  #87                 // Method org/apache/hadoop/hbase/shaded/protobuf/generated/MasterProcedureProtos$RestoreSnapshotStateData.access$15000:(Lorg/apache/hadoop/hbase/shaded/protobuf/generated/MasterProcedureProtos$RestoreSnapshotStateData;)Ljava/util/List;
     502: putfield      #15                 // Field regionInfoForAdd_:Ljava/util/List;
     505: aload_0
     506: aload_0
     507: getfield      #30                 // Field bitField0_:I
     510: bipush        -33
     512: iand
     513: putfield      #30                 // Field bitField0_:I
     516: aload_0
     517: invokestatic  #89                 // Method org/apache/hadoop/hbase/shaded/protobuf/generated/MasterProcedureProtos$RestoreSnapshotStateData.access$15500:()Z
     520: ifeq          530
     523: aload_0
     524: invokespecial #25                 // Method getRegionInfoForAddFieldBuilder:()Lorg/apache/hbase/thirdparty/com/google/protobuf/RepeatedFieldBuilderV3;
     527: goto          531
     530: aconst_null
     531: putfield      #36                 // Field regionInfoForAddBuilder_:Lorg/apache/hbase/thirdparty/com/google/protobuf/RepeatedFieldBuilderV3;
     534: goto          549
     537: aload_0
     538: getfield      #36                 // Field regionInfoForAddBuilder_:Lorg/apache/hbase/thirdparty/com/google/protobuf/RepeatedFieldBuilderV3;
     541: aload_1
     542: invokestatic  #87                 // Method org/apache/hadoop/hbase/shaded/protobuf/generated/MasterProcedureProtos$RestoreSnapshotStateData.access$15000:(Lorg/apache/hadoop/hbase/shaded/protobuf/generated/MasterProcedureProtos$RestoreSnapshotStateData;)Ljava/util/List;
     545: invokevirtual #83                 // Method org/apache/hbase/thirdparty/com/google/protobuf/RepeatedFieldBuilderV3.addAllMessages:(Ljava/lang/Iterable;)Lorg/apache/hbase/thirdparty/com/google/protobuf/RepeatedFieldBuilderV3;
     548: pop
     549: aload_0
     550: getfield      #37                 // Field parentToChildRegionsPairListBuilder_:Lorg/apache/hbase/thirdparty/com/google/protobuf/RepeatedFieldBuilderV3;
     553: ifnonnull     627
     556: aload_1
     557: invokestatic  #90                 // Method org/apache/hadoop/hbase/shaded/protobuf/generated/MasterProcedureProtos$RestoreSnapshotStateData.access$15100:(Lorg/apache/hadoop/hbase/shaded/protobuf/generated/MasterProcedureProtos$RestoreSnapshotStateData;)Ljava/util/List;
     560: invokeinterface #76,  1           // InterfaceMethod java/util/List.isEmpty:()Z
     565: ifne          713
     568: aload_0
     569: getfield      #16                 // Field parentToChildRegionsPairList_:Ljava/util/List;
     572: invokeinterface #76,  1           // InterfaceMethod java/util/List.isEmpty:()Z
     577: ifeq          602
     580: aload_0
     581: aload_1
     582: invokestatic  #90                 // Method org/apache/hadoop/hbase/shaded/protobuf/generated/MasterProcedureProtos$RestoreSnapshotStateData.access$15100:(Lorg/apache/hadoop/hbase/shaded/protobuf/generated/MasterProcedureProtos$RestoreSnapshotStateData;)Ljava/util/List;
     585: putfield      #16                 // Field parentToChildRegionsPairList_:Ljava/util/List;
     588: aload_0
     589: aload_0
     590: getfield      #30                 // Field bitField0_:I
     593: bipush        -65
     595: iand
     596: putfield      #30                 // Field bitField0_:I
     599: goto          620
     602: aload_0
     603: invokespecial #91                 // Method ensureParentToChildRegionsPairListIsMutable:()V
     606: aload_0
     607: getfield      #16                 // Field parentToChildRegionsPairList_:Ljava/util/List;
     610: aload_1
     611: invokestatic  #90                 // Method org/apache/hadoop/hbase/shaded/protobuf/generated/MasterProcedureProtos$RestoreSnapshotStateData.access$15100:(Lorg/apache/hadoop/hbase/shaded/protobuf/generated/MasterProcedureProtos$RestoreSnapshotStateData;)Ljava/util/List;
     614: invokeinterface #78,  2           // InterfaceMethod java/util/List.addAll:(Ljava/util/Collection;)Z
     619: pop
     620: aload_0
     621: invokevirtual #79                 // Method onChanged:()V
     624: goto          713
     627: aload_1
     628: invokestatic  #90                 // Method org/apache/hadoop/hbase/shaded/protobuf/generated/MasterProcedureProtos$RestoreSnapshotStateData.access$15100:(Lorg/apache/hadoop/hbase/shaded/protobuf/generated/MasterProcedureProtos$RestoreSnapshotStateData;)Ljava/util/List;
     631: invokeinterface #76,  1           // InterfaceMethod java/util/List.isEmpty:()Z
     636: ifne          713
     639: aload_0
     640: getfield      #37                 // Field parentToChildRegionsPairListBuilder_:Lorg/apache/hbase/thirdparty/com/google/protobuf/RepeatedFieldBuilderV3;
     643: invokevirtual #80                 // Method org/apache/hbase/thirdparty/com/google/protobuf/RepeatedFieldBuilderV3.isEmpty:()Z
     646: ifeq          701
     649: aload_0
     650: getfield      #37                 // Field parentToChildRegionsPairListBuilder_:Lorg/apache/hbase/thirdparty/com/google/protobuf/RepeatedFieldBuilderV3;
     653: invokevirtual #81                 // Method org/apache/hbase/thirdparty/com/google/protobuf/RepeatedFieldBuilderV3.dispose:()V
     656: aload_0
     657: aconst_null
     658: putfield      #37                 // Field parentToChildRegionsPairListBuilder_:Lorg/apache/hbase/thirdparty/com/google/protobuf/RepeatedFieldBuilderV3;
     661: aload_0
     662: aload_1
     663: invokestatic  #90                 // Method org/apache/hadoop/hbase/shaded/protobuf/generated/MasterProcedureProtos$RestoreSnapshotStateData.access$15100:(Lorg/apache/hadoop/hbase/shaded/protobuf/generated/MasterProcedureProtos$RestoreSnapshotStateData;)Ljava/util/List;
     666: putfield      #16                 // Field parentToChildRegionsPairList_:Ljava/util/List;
     669: aload_0
     670: aload_0
     671: getfield      #30                 // Field bitField0_:I
     674: bipush        -65
     676: iand
     677: putfield      #30                 // Field bitField0_:I
     680: aload_0
     681: invokestatic  #92                 // Method org/apache/hadoop/hbase/shaded/protobuf/generated/MasterProcedureProtos$RestoreSnapshotStateData.access$15600:()Z
     684: ifeq          694
     687: aload_0
     688: invokespecial #26                 // Method getParentToChildRegionsPairListFieldBuilder:()Lorg/apache/hbase/thirdparty/com/google/protobuf/RepeatedFieldBuilderV3;
     691: goto          695
     694: aconst_null
     695: putfield      #37                 // Field parentToChildRegionsPairListBuilder_:Lorg/apache/hbase/thirdparty/com/google/protobuf/RepeatedFieldBuilderV3;
     698: goto          713
     701: aload_0
     702: getfield      #37                 // Field parentToChildRegionsPairListBuilder_:Lorg/apache/hbase/thirdparty/com/google/protobuf/RepeatedFieldBuilderV3;
     705: aload_1
     706: invokestatic  #90                 // Method org/apache/hadoop/hbase/shaded/protobuf/generated/MasterProcedureProtos$RestoreSnapshotStateData.access$15100:(Lorg/apache/hadoop/hbase/shaded/protobuf/generated/MasterProcedureProtos$RestoreSnapshotStateData;)Ljava/util/List;
     709: invokevirtual #83                 // Method org/apache/hbase/thirdparty/com/google/protobuf/RepeatedFieldBuilderV3.addAllMessages:(Ljava/lang/Iterable;)Lorg/apache/hbase/thirdparty/com/google/protobuf/RepeatedFieldBuilderV3;
     712: pop
     713: aload_0
     714: aload_1
     715: invokestatic  #93                 // Method org/apache/hadoop/hbase/shaded/protobuf/generated/MasterProcedureProtos$RestoreSnapshotStateData.access$15700:(Lorg/apache/hadoop/hbase/shaded/protobuf/generated/MasterProcedureProtos$RestoreSnapshotStateData;)Lorg/apache/hbase/thirdparty/com/google/protobuf/UnknownFieldSet;
     718: invokevirtual #94                 // Method mergeUnknownFields:(Lorg/apache/hbase/thirdparty/com/google/protobuf/UnknownFieldSet;)Lorg/apache/hadoop/hbase/shaded/protobuf/generated/MasterProcedureProtos$RestoreSnapshotStateData$Builder;
     721: pop
     722: aload_0
     723: invokevirtual #79                 // Method onChanged:()V
     726: aload_0
     727: areturn

  public final boolean isInitialized();
    Code:
       0: aload_0
       1: invokevirtual #95                 // Method hasUserInfo:()Z
       4: ifne          9
       7: iconst_0
       8: ireturn
       9: aload_0
      10: invokevirtual #96                 // Method hasSnapshot:()Z
      13: ifne          18
      16: iconst_0
      17: ireturn
      18: aload_0
      19: invokevirtual #97                 // Method hasModifiedTableSchema:()Z
      22: ifne          27
      25: iconst_0
      26: ireturn
      27: aload_0
      28: invokevirtual #98                 // Method getUserInfo:()Lorg/apache/hadoop/hbase/shaded/protobuf/generated/RPCProtos$UserInformation;
      31: invokevirtual #99                 // Method org/apache/hadoop/hbase/shaded/protobuf/generated/RPCProtos$UserInformation.isInitialized:()Z
      34: ifne          39
      37: iconst_0
      38: ireturn
      39: aload_0
      40: invokevirtual #100                // Method getSnapshot:()Lorg/apache/hadoop/hbase/shaded/protobuf/generated/SnapshotProtos$SnapshotDescription;
      43: invokevirtual #101                // Method org/apache/hadoop/hbase/shaded/protobuf/generated/SnapshotProtos$SnapshotDescription.isInitialized:()Z
      46: ifne          51
      49: iconst_0
      50: ireturn
      51: aload_0
      52: invokevirtual #102                // Method getModifiedTableSchema:()Lorg/apache/hadoop/hbase/shaded/protobuf/generated/HBaseProtos$TableSchema;
      55: invokevirtual #103                // Method org/apache/hadoop/hbase/shaded/protobuf/generated/HBaseProtos$TableSchema.isInitialized:()Z
      58: ifne          63
      61: iconst_0
      62: ireturn
      63: iconst_0
      64: istore_1
      65: iload_1
      66: aload_0
      67: invokevirtual #104                // Method getRegionInfoForRestoreCount:()I
      70: if_icmpge     92
      73: aload_0
      74: iload_1
      75: invokevirtual #105                // Method getRegionInfoForRestore:(I)Lorg/apache/hadoop/hbase/shaded/protobuf/generated/HBaseProtos$RegionInfo;
      78: invokevirtual #106                // Method org/apache/hadoop/hbase/shaded/protobuf/generated/HBaseProtos$RegionInfo.isInitialized:()Z
      81: ifne          86
      84: iconst_0
      85: ireturn
      86: iinc          1, 1
      89: goto          65
      92: iconst_0
      93: istore_1
      94: iload_1
      95: aload_0
      96: invokevirtual #107                // Method getRegionInfoForRemoveCount:()I
      99: if_icmpge     121
     102: aload_0
     103: iload_1
     104: invokevirtual #108                // Method getRegionInfoForRemove:(I)Lorg/apache/hadoop/hbase/shaded/protobuf/generated/HBaseProtos$RegionInfo;
     107: invokevirtual #106                // Method org/apache/hadoop/hbase/shaded/protobuf/generated/HBaseProtos$RegionInfo.isInitialized:()Z
     110: ifne          115
     113: iconst_0
     114: ireturn
     115: iinc          1, 1
     118: goto          94
     121: iconst_0
     122: istore_1
     123: iload_1
     124: aload_0
     125: invokevirtual #109                // Method getRegionInfoForAddCount:()I
     128: if_icmpge     150
     131: aload_0
     132: iload_1
     133: invokevirtual #110                // Method getRegionInfoForAdd:(I)Lorg/apache/hadoop/hbase/shaded/protobuf/generated/HBaseProtos$RegionInfo;
     136: invokevirtual #106                // Method org/apache/hadoop/hbase/shaded/protobuf/generated/HBaseProtos$RegionInfo.isInitialized:()Z
     139: ifne          144
     142: iconst_0
     143: ireturn
     144: iinc          1, 1
     147: goto          123
     150: iconst_0
     151: istore_1
     152: iload_1
     153: aload_0
     154: invokevirtual #111                // Method getParentToChildRegionsPairListCount:()I
     157: if_icmpge     179
     160: aload_0
     161: iload_1
     162: invokevirtual #112                // Method getParentToChildRegionsPairList:(I)Lorg/apache/hadoop/hbase/shaded/protobuf/generated/MasterProcedureProtos$RestoreParentToChildRegionsPair;
     165: invokevirtual #113                // Method org/apache/hadoop/hbase/shaded/protobuf/generated/MasterProcedureProtos$RestoreParentToChildRegionsPair.isInitialized:()Z
     168: ifne          173
     171: iconst_0
     172: ireturn
     173: iinc          1, 1
     176: goto          152
     179: iconst_1
     180: ireturn

  public org.apache.hadoop.hbase.shaded.protobuf.generated.MasterProcedureProtos$RestoreSnapshotStateData$Builder mergeFrom(org.apache.hbase.thirdparty.com.google.protobuf.CodedInputStream, org.apache.hbase.thirdparty.com.google.protobuf.ExtensionRegistryLite) throws java.io.IOException;
    Code:
       0: aconst_null
       1: astore_3
       2: getstatic     #114                // Field org/apache/hadoop/hbase/shaded/protobuf/generated/MasterProcedureProtos$RestoreSnapshotStateData.PARSER:Lorg/apache/hbase/thirdparty/com/google/protobuf/Parser;
       5: aload_1
       6: aload_2
       7: invokeinterface #115,  3          // InterfaceMethod org/apache/hbase/thirdparty/com/google/protobuf/Parser.parsePartialFrom:(Lorg/apache/hbase/thirdparty/com/google/protobuf/CodedInputStream;Lorg/apache/hbase/thirdparty/com/google/protobuf/ExtensionRegistryLite;)Ljava/lang/Object;
      12: checkcast     #5                  // class org/apache/hadoop/hbase/shaded/protobuf/generated/MasterProcedureProtos$RestoreSnapshotStateData
      15: astore_3
      16: aload_3
      17: ifnull        61
      20: aload_0
      21: aload_3
      22: invokevirtual #64                 // Method mergeFrom:(Lorg/apache/hadoop/hbase/shaded/protobuf/generated/MasterProcedureProtos$RestoreSnapshotStateData;)Lorg/apache/hadoop/hbase/shaded/protobuf/generated/MasterProcedureProtos$RestoreSnapshotStateData$Builder;
      25: pop
      26: goto          61
      29: astore        4
      31: aload         4
      33: invokevirtual #117                // Method org/apache/hbase/thirdparty/com/google/protobuf/InvalidProtocolBufferException.getUnfinishedMessage:()Lorg/apache/hbase/thirdparty/com/google/protobuf/MessageLite;
      36: checkcast     #5                  // class org/apache/hadoop/hbase/shaded/protobuf/generated/MasterProcedureProtos$RestoreSnapshotStateData
      39: astore_3
      40: aload         4
      42: invokevirtual #118                // Method org/apache/hbase/thirdparty/com/google/protobuf/InvalidProtocolBufferException.unwrapIOException:()Ljava/io/IOException;
      45: athrow
      46: astore        5
      48: aload_3
      49: ifnull        58
      52: aload_0
      53: aload_3
      54: invokevirtual #64                 // Method mergeFrom:(Lorg/apache/hadoop/hbase/shaded/protobuf/generated/MasterProcedureProtos$RestoreSnapshotStateData;)Lorg/apache/hadoop/hbase/shaded/protobuf/generated/MasterProcedureProtos$RestoreSnapshotStateData$Builder;
      57: pop
      58: aload         5
      60: athrow
      61: aload_0
      62: areturn
    Exception table:
       from    to  target type
           2    16    29   Class org/apache/hbase/thirdparty/com/google/protobuf/InvalidProtocolBufferException
           2    16    46   any
          29    48    46   any

  public boolean hasUserInfo();
    Code:
       0: aload_0
       1: getfield      #30                 // Field bitField0_:I
       4: iconst_1
       5: iand
       6: iconst_1
       7: if_icmpne     14
      10: iconst_1
      11: goto          15
      14: iconst_0
      15: ireturn

  public org.apache.hadoop.hbase.shaded.protobuf.generated.RPCProtos$UserInformation getUserInfo();
    Code:
       0: aload_0
       1: getfield      #28                 // Field userInfoBuilder_:Lorg/apache/hbase/thirdparty/com/google/protobuf/SingleFieldBuilderV3;
       4: ifnonnull     25
       7: aload_0
       8: getfield      #9                  // Field userInfo_:Lorg/apache/hadoop/hbase/shaded/protobuf/generated/RPCProtos$UserInformation;
      11: ifnonnull     20
      14: invokestatic  #119                // Method org/apache/hadoop/hbase/shaded/protobuf/generated/RPCProtos$UserInformation.getDefaultInstance:()Lorg/apache/hadoop/hbase/shaded/protobuf/generated/RPCProtos$UserInformation;
      17: goto          24
      20: aload_0
      21: getfield      #9                  // Field userInfo_:Lorg/apache/hadoop/hbase/shaded/protobuf/generated/RPCProtos$UserInformation;
      24: areturn
      25: aload_0
      26: getfield      #28                 // Field userInfoBuilder_:Lorg/apache/hbase/thirdparty/com/google/protobuf/SingleFieldBuilderV3;
      29: invokevirtual #120                // Method org/apache/hbase/thirdparty/com/google/protobuf/SingleFieldBuilderV3.getMessage:()Lorg/apache/hbase/thirdparty/com/google/protobuf/AbstractMessage;
      32: checkcast     #45                 // class org/apache/hadoop/hbase/shaded/protobuf/generated/RPCProtos$UserInformation
      35: areturn

  public org.apache.hadoop.hbase.shaded.protobuf.generated.MasterProcedureProtos$RestoreSnapshotStateData$Builder setUserInfo(org.apache.hadoop.hbase.shaded.protobuf.generated.RPCProtos$UserInformation);
    Code:
       0: aload_0
       1: getfield      #28                 // Field userInfoBuilder_:Lorg/apache/hbase/thirdparty/com/google/protobuf/SingleFieldBuilderV3;
       4: ifnonnull     31
       7: aload_1
       8: ifnonnull     19
      11: new           #121                // class java/lang/NullPointerException
      14: dup
      15: invokespecial #122                // Method java/lang/NullPointerException."<init>":()V
      18: athrow
      19: aload_0
      20: aload_1
      21: putfield      #9                  // Field userInfo_:Lorg/apache/hadoop/hbase/shaded/protobuf/generated/RPCProtos$UserInformation;
      24: aload_0
      25: invokevirtual #79                 // Method onChanged:()V
      28: goto          40
      31: aload_0
      32: getfield      #28                 // Field userInfoBuilder_:Lorg/apache/hbase/thirdparty/com/google/protobuf/SingleFieldBuilderV3;
      35: aload_1
      36: invokevirtual #123                // Method org/apache/hbase/thirdparty/com/google/protobuf/SingleFieldBuilderV3.setMessage:(Lorg/apache/hbase/thirdparty/com/google/protobuf/AbstractMessage;)Lorg/apache/hbase/thirdparty/com/google/protobuf/SingleFieldBuilderV3;
      39: pop
      40: aload_0
      41: dup
      42: getfield      #30                 // Field bitField0_:I
      45: iconst_1
      46: ior
      47: putfield      #30                 // Field bitField0_:I
      50: aload_0
      51: areturn

  public org.apache.hadoop.hbase.shaded.protobuf.generated.MasterProcedureProtos$RestoreSnapshotStateData$Builder setUserInfo(org.apache.hadoop.hbase.shaded.protobuf.generated.RPCProtos$UserInformation$Builder);
    Code:
       0: aload_0
       1: getfield      #28                 // Field userInfoBuilder_:Lorg/apache/hbase/thirdparty/com/google/protobuf/SingleFieldBuilderV3;
       4: ifnonnull     22
       7: aload_0
       8: aload_1
       9: invokevirtual #124                // Method org/apache/hadoop/hbase/shaded/protobuf/generated/RPCProtos$UserInformation$Builder.build:()Lorg/apache/hadoop/hbase/shaded/protobuf/generated/RPCProtos$UserInformation;
      12: putfield      #9                  // Field userInfo_:Lorg/apache/hadoop/hbase/shaded/protobuf/generated/RPCProtos$UserInformation;
      15: aload_0
      16: invokevirtual #79                 // Method onChanged:()V
      19: goto          34
      22: aload_0
      23: getfield      #28                 // Field userInfoBuilder_:Lorg/apache/hbase/thirdparty/com/google/protobuf/SingleFieldBuilderV3;
      26: aload_1
      27: invokevirtual #124                // Method org/apache/hadoop/hbase/shaded/protobuf/generated/RPCProtos$UserInformation$Builder.build:()Lorg/apache/hadoop/hbase/shaded/protobuf/generated/RPCProtos$UserInformation;
      30: invokevirtual #123                // Method org/apache/hbase/thirdparty/com/google/protobuf/SingleFieldBuilderV3.setMessage:(Lorg/apache/hbase/thirdparty/com/google/protobuf/AbstractMessage;)Lorg/apache/hbase/thirdparty/com/google/protobuf/SingleFieldBuilderV3;
      33: pop
      34: aload_0
      35: dup
      36: getfield      #30                 // Field bitField0_:I
      39: iconst_1
      40: ior
      41: putfield      #30                 // Field bitField0_:I
      44: aload_0
      45: areturn

  public org.apache.hadoop.hbase.shaded.protobuf.generated.MasterProcedureProtos$RestoreSnapshotStateData$Builder mergeUserInfo(org.apache.hadoop.hbase.shaded.protobuf.generated.RPCProtos$UserInformation);
    Code:
       0: aload_0
       1: getfield      #28                 // Field userInfoBuilder_:Lorg/apache/hbase/thirdparty/com/google/protobuf/SingleFieldBuilderV3;
       4: ifnonnull     67
       7: aload_0
       8: getfield      #30                 // Field bitField0_:I
      11: iconst_1
      12: iand
      13: iconst_1
      14: if_icmpne     55
      17: aload_0
      18: getfield      #9                  // Field userInfo_:Lorg/apache/hadoop/hbase/shaded/protobuf/generated/RPCProtos$UserInformation;
      21: ifnull        55
      24: aload_0
      25: getfield      #9                  // Field userInfo_:Lorg/apache/hadoop/hbase/shaded/protobuf/generated/RPCProtos$UserInformation;
      28: invokestatic  #119                // Method org/apache/hadoop/hbase/shaded/protobuf/generated/RPCProtos$UserInformation.getDefaultInstance:()Lorg/apache/hadoop/hbase/shaded/protobuf/generated/RPCProtos$UserInformation;
      31: if_acmpeq     55
      34: aload_0
      35: aload_0
      36: getfield      #9                  // Field userInfo_:Lorg/apache/hadoop/hbase/shaded/protobuf/generated/RPCProtos$UserInformation;
      39: invokestatic  #125                // Method org/apache/hadoop/hbase/shaded/protobuf/generated/RPCProtos$UserInformation.newBuilder:(Lorg/apache/hadoop/hbase/shaded/protobuf/generated/RPCProtos$UserInformation;)Lorg/apache/hadoop/hbase/shaded/protobuf/generated/RPCProtos$UserInformation$Builder;
      42: aload_1
      43: invokevirtual #126                // Method org/apache/hadoop/hbase/shaded/protobuf/generated/RPCProtos$UserInformation$Builder.mergeFrom:(Lorg/apache/hadoop/hbase/shaded/protobuf/generated/RPCProtos$UserInformation;)Lorg/apache/hadoop/hbase/shaded/protobuf/generated/RPCProtos$UserInformation$Builder;
      46: invokevirtual #127                // Method org/apache/hadoop/hbase/shaded/protobuf/generated/RPCProtos$UserInformation$Builder.buildPartial:()Lorg/apache/hadoop/hbase/shaded/protobuf/generated/RPCProtos$UserInformation;
      49: putfield      #9                  // Field userInfo_:Lorg/apache/hadoop/hbase/shaded/protobuf/generated/RPCProtos$UserInformation;
      52: goto          60
      55: aload_0
      56: aload_1
      57: putfield      #9                  // Field userInfo_:Lorg/apache/hadoop/hbase/shaded/protobuf/generated/RPCProtos$UserInformation;
      60: aload_0
      61: invokevirtual #79                 // Method onChanged:()V
      64: goto          76
      67: aload_0
      68: getfield      #28                 // Field userInfoBuilder_:Lorg/apache/hbase/thirdparty/com/google/protobuf/SingleFieldBuilderV3;
      71: aload_1
      72: invokevirtual #128                // Method org/apache/hbase/thirdparty/com/google/protobuf/SingleFieldBuilderV3.mergeFrom:(Lorg/apache/hbase/thirdparty/com/google/protobuf/AbstractMessage;)Lorg/apache/hbase/thirdparty/com/google/protobuf/SingleFieldBuilderV3;
      75: pop
      76: aload_0
      77: dup
      78: getfield      #30                 // Field bitField0_:I
      81: iconst_1
      82: ior
      83: putfield      #30                 // Field bitField0_:I
      86: aload_0
      87: areturn

  public org.apache.hadoop.hbase.shaded.protobuf.generated.MasterProcedureProtos$RestoreSnapshotStateData$Builder clearUserInfo();
    Code:
       0: aload_0
       1: getfield      #28                 // Field userInfoBuilder_:Lorg/apache/hbase/thirdparty/com/google/protobuf/SingleFieldBuilderV3;
       4: ifnonnull     19
       7: aload_0
       8: aconst_null
       9: putfield      #9                  // Field userInfo_:Lorg/apache/hadoop/hbase/shaded/protobuf/generated/RPCProtos$UserInformation;
      12: aload_0
      13: invokevirtual #79                 // Method onChanged:()V
      16: goto          27
      19: aload_0
      20: getfield      #28                 // Field userInfoBuilder_:Lorg/apache/hbase/thirdparty/com/google/protobuf/SingleFieldBuilderV3;
      23: invokevirtual #29                 // Method org/apache/hbase/thirdparty/com/google/protobuf/SingleFieldBuilderV3.clear:()Lorg/apache/hbase/thirdparty/com/google/protobuf/SingleFieldBuilderV3;
      26: pop
      27: aload_0
      28: aload_0
      29: getfield      #30                 // Field bitField0_:I
      32: bipush        -2
      34: iand
      35: putfield      #30                 // Field bitField0_:I
      38: aload_0
      39: areturn

  public org.apache.hadoop.hbase.shaded.protobuf.generated.RPCProtos$UserInformation$Builder getUserInfoBuilder();
    Code:
       0: aload_0
       1: dup
       2: getfield      #30                 // Field bitField0_:I
       5: iconst_1
       6: ior
       7: putfield      #30                 // Field bitField0_:I
      10: aload_0
      11: invokevirtual #79                 // Method onChanged:()V
      14: aload_0
      15: invokespecial #20                 // Method getUserInfoFieldBuilder:()Lorg/apache/hbase/thirdparty/com/google/protobuf/SingleFieldBuilderV3;
      18: invokevirtual #129                // Method org/apache/hbase/thirdparty/com/google/protobuf/SingleFieldBuilderV3.getBuilder:()Lorg/apache/hbase/thirdparty/com/google/protobuf/AbstractMessage$Builder;
      21: checkcast     #130                // class org/apache/hadoop/hbase/shaded/protobuf/generated/RPCProtos$UserInformation$Builder
      24: areturn

  public org.apache.hadoop.hbase.shaded.protobuf.generated.RPCProtos$UserInformationOrBuilder getUserInfoOrBuilder();
    Code:
       0: aload_0
       1: getfield      #28                 // Field userInfoBuilder_:Lorg/apache/hbase/thirdparty/com/google/protobuf/SingleFieldBuilderV3;
       4: ifnull        18
       7: aload_0
       8: getfield      #28                 // Field userInfoBuilder_:Lorg/apache/hbase/thirdparty/com/google/protobuf/SingleFieldBuilderV3;
      11: invokevirtual #131                // Method org/apache/hbase/thirdparty/com/google/protobuf/SingleFieldBuilderV3.getMessageOrBuilder:()Lorg/apache/hbase/thirdparty/com/google/protobuf/MessageOrBuilder;
      14: checkcast     #132                // class org/apache/hadoop/hbase/shaded/protobuf/generated/RPCProtos$UserInformationOrBuilder
      17: areturn
      18: aload_0
      19: getfield      #9                  // Field userInfo_:Lorg/apache/hadoop/hbase/shaded/protobuf/generated/RPCProtos$UserInformation;
      22: ifnonnull     31
      25: invokestatic  #119                // Method org/apache/hadoop/hbase/shaded/protobuf/generated/RPCProtos$UserInformation.getDefaultInstance:()Lorg/apache/hadoop/hbase/shaded/protobuf/generated/RPCProtos$UserInformation;
      28: goto          35
      31: aload_0
      32: getfield      #9                  // Field userInfo_:Lorg/apache/hadoop/hbase/shaded/protobuf/generated/RPCProtos$UserInformation;
      35: areturn

  public boolean hasSnapshot();
    Code:
       0: aload_0
       1: getfield      #30                 // Field bitField0_:I
       4: iconst_2
       5: iand
       6: iconst_2
       7: if_icmpne     14
      10: iconst_1
      11: goto          15
      14: iconst_0
      15: ireturn

  public org.apache.hadoop.hbase.shaded.protobuf.generated.SnapshotProtos$SnapshotDescription getSnapshot();
    Code:
       0: aload_0
       1: getfield      #31                 // Field snapshotBuilder_:Lorg/apache/hbase/thirdparty/com/google/protobuf/SingleFieldBuilderV3;
       4: ifnonnull     25
       7: aload_0
       8: getfield      #10                 // Field snapshot_:Lorg/apache/hadoop/hbase/shaded/protobuf/generated/SnapshotProtos$SnapshotDescription;
      11: ifnonnull     20
      14: invokestatic  #137                // Method org/apache/hadoop/hbase/shaded/protobuf/generated/SnapshotProtos$SnapshotDescription.getDefaultInstance:()Lorg/apache/hadoop/hbase/shaded/protobuf/generated/SnapshotProtos$SnapshotDescription;
      17: goto          24
      20: aload_0
      21: getfield      #10                 // Field snapshot_:Lorg/apache/hadoop/hbase/shaded/protobuf/generated/SnapshotProtos$SnapshotDescription;
      24: areturn
      25: aload_0
      26: getfield      #31                 // Field snapshotBuilder_:Lorg/apache/hbase/thirdparty/com/google/protobuf/SingleFieldBuilderV3;
      29: invokevirtual #120                // Method org/apache/hbase/thirdparty/com/google/protobuf/SingleFieldBuilderV3.getMessage:()Lorg/apache/hbase/thirdparty/com/google/protobuf/AbstractMessage;
      32: checkcast     #47                 // class org/apache/hadoop/hbase/shaded/protobuf/generated/SnapshotProtos$SnapshotDescription
      35: areturn

  public org.apache.hadoop.hbase.shaded.protobuf.generated.MasterProcedureProtos$RestoreSnapshotStateData$Builder setSnapshot(org.apache.hadoop.hbase.shaded.protobuf.generated.SnapshotProtos$SnapshotDescription);
    Code:
       0: aload_0
       1: getfield      #31                 // Field snapshotBuilder_:Lorg/apache/hbase/thirdparty/com/google/protobuf/SingleFieldBuilderV3;
       4: ifnonnull     31
       7: aload_1
       8: ifnonnull     19
      11: new           #121                // class java/lang/NullPointerException
      14: dup
      15: invokespecial #122                // Method java/lang/NullPointerException."<init>":()V
      18: athrow
      19: aload_0
      20: aload_1
      21: putfield      #10                 // Field snapshot_:Lorg/apache/hadoop/hbase/shaded/protobuf/generated/SnapshotProtos$SnapshotDescription;
      24: aload_0
      25: invokevirtual #79                 // Method onChanged:()V
      28: goto          40
      31: aload_0
      32: getfield      #31                 // Field snapshotBuilder_:Lorg/apache/hbase/thirdparty/com/google/protobuf/SingleFieldBuilderV3;
      35: aload_1
      36: invokevirtual #123                // Method org/apache/hbase/thirdparty/com/google/protobuf/SingleFieldBuilderV3.setMessage:(Lorg/apache/hbase/thirdparty/com/google/protobuf/AbstractMessage;)Lorg/apache/hbase/thirdparty/com/google/protobuf/SingleFieldBuilderV3;
      39: pop
      40: aload_0
      41: dup
      42: getfield      #30                 // Field bitField0_:I
      45: iconst_2
      46: ior
      47: putfield      #30                 // Field bitField0_:I
      50: aload_0
      51: areturn

  public org.apache.hadoop.hbase.shaded.protobuf.generated.MasterProcedureProtos$RestoreSnapshotStateData$Builder setSnapshot(org.apache.hadoop.hbase.shaded.protobuf.generated.SnapshotProtos$SnapshotDescription$Builder);
    Code:
       0: aload_0
       1: getfield      #31                 // Field snapshotBuilder_:Lorg/apache/hbase/thirdparty/com/google/protobuf/SingleFieldBuilderV3;
       4: ifnonnull     22
       7: aload_0
       8: aload_1
       9: invokevirtual #138                // Method org/apache/hadoop/hbase/shaded/protobuf/generated/SnapshotProtos$SnapshotDescription$Builder.build:()Lorg/apache/hadoop/hbase/shaded/protobuf/generated/SnapshotProtos$SnapshotDescription;
      12: putfield      #10                 // Field snapshot_:Lorg/apache/hadoop/hbase/shaded/protobuf/generated/SnapshotProtos$SnapshotDescription;
      15: aload_0
      16: invokevirtual #79                 // Method onChanged:()V
      19: goto          34
      22: aload_0
      23: getfield      #31                 // Field snapshotBuilder_:Lorg/apache/hbase/thirdparty/com/google/protobuf/SingleFieldBuilderV3;
      26: aload_1
      27: invokevirtual #138                // Method org/apache/hadoop/hbase/shaded/protobuf/generated/SnapshotProtos$SnapshotDescription$Builder.build:()Lorg/apache/hadoop/hbase/shaded/protobuf/generated/SnapshotProtos$SnapshotDescription;
      30: invokevirtual #123                // Method org/apache/hbase/thirdparty/com/google/protobuf/SingleFieldBuilderV3.setMessage:(Lorg/apache/hbase/thirdparty/com/google/protobuf/AbstractMessage;)Lorg/apache/hbase/thirdparty/com/google/protobuf/SingleFieldBuilderV3;
      33: pop
      34: aload_0
      35: dup
      36: getfield      #30                 // Field bitField0_:I
      39: iconst_2
      40: ior
      41: putfield      #30                 // Field bitField0_:I
      44: aload_0
      45: areturn

  public org.apache.hadoop.hbase.shaded.protobuf.generated.MasterProcedureProtos$RestoreSnapshotStateData$Builder mergeSnapshot(org.apache.hadoop.hbase.shaded.protobuf.generated.SnapshotProtos$SnapshotDescription);
    Code:
       0: aload_0
       1: getfield      #31                 // Field snapshotBuilder_:Lorg/apache/hbase/thirdparty/com/google/protobuf/SingleFieldBuilderV3;
       4: ifnonnull     67
       7: aload_0
       8: getfield      #30                 // Field bitField0_:I
      11: iconst_2
      12: iand
      13: iconst_2
      14: if_icmpne     55
      17: aload_0
      18: getfield      #10                 // Field snapshot_:Lorg/apache/hadoop/hbase/shaded/protobuf/generated/SnapshotProtos$SnapshotDescription;
      21: ifnull        55
      24: aload_0
      25: getfield      #10                 // Field snapshot_:Lorg/apache/hadoop/hbase/shaded/protobuf/generated/SnapshotProtos$SnapshotDescription;
      28: invokestatic  #137                // Method org/apache/hadoop/hbase/shaded/protobuf/generated/SnapshotProtos$SnapshotDescription.getDefaultInstance:()Lorg/apache/hadoop/hbase/shaded/protobuf/generated/SnapshotProtos$SnapshotDescription;
      31: if_acmpeq     55
      34: aload_0
      35: aload_0
      36: getfield      #10                 // Field snapshot_:Lorg/apache/hadoop/hbase/shaded/protobuf/generated/SnapshotProtos$SnapshotDescription;
      39: invokestatic  #139                // Method org/apache/hadoop/hbase/shaded/protobuf/generated/SnapshotProtos$SnapshotDescription.newBuilder:(Lorg/apache/hadoop/hbase/shaded/protobuf/generated/SnapshotProtos$SnapshotDescription;)Lorg/apache/hadoop/hbase/shaded/protobuf/generated/SnapshotProtos$SnapshotDescription$Builder;
      42: aload_1
      43: invokevirtual #140                // Method org/apache/hadoop/hbase/shaded/protobuf/generated/SnapshotProtos$SnapshotDescription$Builder.mergeFrom:(Lorg/apache/hadoop/hbase/shaded/protobuf/generated/SnapshotProtos$SnapshotDescription;)Lorg/apache/hadoop/hbase/shaded/protobuf/generated/SnapshotProtos$SnapshotDescription$Builder;
      46: invokevirtual #141                // Method org/apache/hadoop/hbase/shaded/protobuf/generated/SnapshotProtos$SnapshotDescription$Builder.buildPartial:()Lorg/apache/hadoop/hbase/shaded/protobuf/generated/SnapshotProtos$SnapshotDescription;
      49: putfield      #10                 // Field snapshot_:Lorg/apache/hadoop/hbase/shaded/protobuf/generated/SnapshotProtos$SnapshotDescription;
      52: goto          60
      55: aload_0
      56: aload_1
      57: putfield      #10                 // Field snapshot_:Lorg/apache/hadoop/hbase/shaded/protobuf/generated/SnapshotProtos$SnapshotDescription;
      60: aload_0
      61: invokevirtual #79                 // Method onChanged:()V
      64: goto          76
      67: aload_0
      68: getfield      #31                 // Field snapshotBuilder_:Lorg/apache/hbase/thirdparty/com/google/protobuf/SingleFieldBuilderV3;
      71: aload_1
      72: invokevirtual #128                // Method org/apache/hbase/thirdparty/com/google/protobuf/SingleFieldBuilderV3.mergeFrom:(Lorg/apache/hbase/thirdparty/com/google/protobuf/AbstractMessage;)Lorg/apache/hbase/thirdparty/com/google/protobuf/SingleFieldBuilderV3;
      75: pop
      76: aload_0
      77: dup
      78: getfield      #30                 // Field bitField0_:I
      81: iconst_2
      82: ior
      83: putfield      #30                 // Field bitField0_:I
      86: aload_0
      87: areturn

  public org.apache.hadoop.hbase.shaded.protobuf.generated.MasterProcedureProtos$RestoreSnapshotStateData$Builder clearSnapshot();
    Code:
       0: aload_0
       1: getfield      #31                 // Field snapshotBuilder_:Lorg/apache/hbase/thirdparty/com/google/protobuf/SingleFieldBuilderV3;
       4: ifnonnull     19
       7: aload_0
       8: aconst_null
       9: putfield      #10                 // Field snapshot_:Lorg/apache/hadoop/hbase/shaded/protobuf/generated/SnapshotProtos$SnapshotDescription;
      12: aload_0
      13: invokevirtual #79                 // Method onChanged:()V
      16: goto          27
      19: aload_0
      20: getfield      #31                 // Field snapshotBuilder_:Lorg/apache/hbase/thirdparty/com/google/protobuf/SingleFieldBuilderV3;
      23: invokevirtual #29                 // Method org/apache/hbase/thirdparty/com/google/protobuf/SingleFieldBuilderV3.clear:()Lorg/apache/hbase/thirdparty/com/google/protobuf/SingleFieldBuilderV3;
      26: pop
      27: aload_0
      28: aload_0
      29: getfield      #30                 // Field bitField0_:I
      32: bipush        -3
      34: iand
      35: putfield      #30                 // Field bitField0_:I
      38: aload_0
      39: areturn

  public org.apache.hadoop.hbase.shaded.protobuf.generated.SnapshotProtos$SnapshotDescription$Builder getSnapshotBuilder();
    Code:
       0: aload_0
       1: dup
       2: getfield      #30                 // Field bitField0_:I
       5: iconst_2
       6: ior
       7: putfield      #30                 // Field bitField0_:I
      10: aload_0
      11: invokevirtual #79                 // Method onChanged:()V
      14: aload_0
      15: invokespecial #21                 // Method getSnapshotFieldBuilder:()Lorg/apache/hbase/thirdparty/com/google/protobuf/SingleFieldBuilderV3;
      18: invokevirtual #129                // Method org/apache/hbase/thirdparty/com/google/protobuf/SingleFieldBuilderV3.getBuilder:()Lorg/apache/hbase/thirdparty/com/google/protobuf/AbstractMessage$Builder;
      21: checkcast     #142                // class org/apache/hadoop/hbase/shaded/protobuf/generated/SnapshotProtos$SnapshotDescription$Builder
      24: areturn

  public org.apache.hadoop.hbase.shaded.protobuf.generated.SnapshotProtos$SnapshotDescriptionOrBuilder getSnapshotOrBuilder();
    Code:
       0: aload_0
       1: getfield      #31                 // Field snapshotBuilder_:Lorg/apache/hbase/thirdparty/com/google/protobuf/SingleFieldBuilderV3;
       4: ifnull        18
       7: aload_0
       8: getfield      #31                 // Field snapshotBuilder_:Lorg/apache/hbase/thirdparty/com/google/protobuf/SingleFieldBuilderV3;
      11: invokevirtual #131                // Method org/apache/hbase/thirdparty/com/google/protobuf/SingleFieldBuilderV3.getMessageOrBuilder:()Lorg/apache/hbase/thirdparty/com/google/protobuf/MessageOrBuilder;
      14: checkcast     #143                // class org/apache/hadoop/hbase/shaded/protobuf/generated/SnapshotProtos$SnapshotDescriptionOrBuilder
      17: areturn
      18: aload_0
      19: getfield      #10                 // Field snapshot_:Lorg/apache/hadoop/hbase/shaded/protobuf/generated/SnapshotProtos$SnapshotDescription;
      22: ifnonnull     31
      25: invokestatic  #137                // Method org/apache/hadoop/hbase/shaded/protobuf/generated/SnapshotProtos$SnapshotDescription.getDefaultInstance:()Lorg/apache/hadoop/hbase/shaded/protobuf/generated/SnapshotProtos$SnapshotDescription;
      28: goto          35
      31: aload_0
      32: getfield      #10                 // Field snapshot_:Lorg/apache/hadoop/hbase/shaded/protobuf/generated/SnapshotProtos$SnapshotDescription;
      35: areturn

  public boolean hasModifiedTableSchema();
    Code:
       0: aload_0
       1: getfield      #30                 // Field bitField0_:I
       4: iconst_4
       5: iand
       6: iconst_4
       7: if_icmpne     14
      10: iconst_1
      11: goto          15
      14: iconst_0
      15: ireturn

  public org.apache.hadoop.hbase.shaded.protobuf.generated.HBaseProtos$TableSchema getModifiedTableSchema();
    Code:
       0: aload_0
       1: getfield      #32                 // Field modifiedTableSchemaBuilder_:Lorg/apache/hbase/thirdparty/com/google/protobuf/SingleFieldBuilderV3;
       4: ifnonnull     25
       7: aload_0
       8: getfield      #11                 // Field modifiedTableSchema_:Lorg/apache/hadoop/hbase/shaded/protobuf/generated/HBaseProtos$TableSchema;
      11: ifnonnull     20
      14: invokestatic  #144                // Method org/apache/hadoop/hbase/shaded/protobuf/generated/HBaseProtos$TableSchema.getDefaultInstance:()Lorg/apache/hadoop/hbase/shaded/protobuf/generated/HBaseProtos$TableSchema;
      17: goto          24
      20: aload_0
      21: getfield      #11                 // Field modifiedTableSchema_:Lorg/apache/hadoop/hbase/shaded/protobuf/generated/HBaseProtos$TableSchema;
      24: areturn
      25: aload_0
      26: getfield      #32                 // Field modifiedTableSchemaBuilder_:Lorg/apache/hbase/thirdparty/com/google/protobuf/SingleFieldBuilderV3;
      29: invokevirtual #120                // Method org/apache/hbase/thirdparty/com/google/protobuf/SingleFieldBuilderV3.getMessage:()Lorg/apache/hbase/thirdparty/com/google/protobuf/AbstractMessage;
      32: checkcast     #49                 // class org/apache/hadoop/hbase/shaded/protobuf/generated/HBaseProtos$TableSchema
      35: areturn

  public org.apache.hadoop.hbase.shaded.protobuf.generated.MasterProcedureProtos$RestoreSnapshotStateData$Builder setModifiedTableSchema(org.apache.hadoop.hbase.shaded.protobuf.generated.HBaseProtos$TableSchema);
    Code:
       0: aload_0
       1: getfield      #32                 // Field modifiedTableSchemaBuilder_:Lorg/apache/hbase/thirdparty/com/google/protobuf/SingleFieldBuilderV3;
       4: ifnonnull     31
       7: aload_1
       8: ifnonnull     19
      11: new           #121                // class java/lang/NullPointerException
      14: dup
      15: invokespecial #122                // Method java/lang/NullPointerException."<init>":()V
      18: athrow
      19: aload_0
      20: aload_1
      21: putfield      #11                 // Field modifiedTableSchema_:Lorg/apache/hadoop/hbase/shaded/protobuf/generated/HBaseProtos$TableSchema;
      24: aload_0
      25: invokevirtual #79                 // Method onChanged:()V
      28: goto          40
      31: aload_0
      32: getfield      #32                 // Field modifiedTableSchemaBuilder_:Lorg/apache/hbase/thirdparty/com/google/protobuf/SingleFieldBuilderV3;
      35: aload_1
      36: invokevirtual #123                // Method org/apache/hbase/thirdparty/com/google/protobuf/SingleFieldBuilderV3.setMessage:(Lorg/apache/hbase/thirdparty/com/google/protobuf/AbstractMessage;)Lorg/apache/hbase/thirdparty/com/google/protobuf/SingleFieldBuilderV3;
      39: pop
      40: aload_0
      41: dup
      42: getfield      #30                 // Field bitField0_:I
      45: iconst_4
      46: ior
      47: putfield      #30                 // Field bitField0_:I
      50: aload_0
      51: areturn

  public org.apache.hadoop.hbase.shaded.protobuf.generated.MasterProcedureProtos$RestoreSnapshotStateData$Builder setModifiedTableSchema(org.apache.hadoop.hbase.shaded.protobuf.generated.HBaseProtos$TableSchema$Builder);
    Code:
       0: aload_0
       1: getfield      #32                 // Field modifiedTableSchemaBuilder_:Lorg/apache/hbase/thirdparty/com/google/protobuf/SingleFieldBuilderV3;
       4: ifnonnull     22
       7: aload_0
       8: aload_1
       9: invokevirtual #145                // Method org/apache/hadoop/hbase/shaded/protobuf/generated/HBaseProtos$TableSchema$Builder.build:()Lorg/apache/hadoop/hbase/shaded/protobuf/generated/HBaseProtos$TableSchema;
      12: putfield      #11                 // Field modifiedTableSchema_:Lorg/apache/hadoop/hbase/shaded/protobuf/generated/HBaseProtos$TableSchema;
      15: aload_0
      16: invokevirtual #79                 // Method onChanged:()V
      19: goto          34
      22: aload_0
      23: getfield      #32                 // Field modifiedTableSchemaBuilder_:Lorg/apache/hbase/thirdparty/com/google/protobuf/SingleFieldBuilderV3;
      26: aload_1
      27: invokevirtual #145                // Method org/apache/hadoop/hbase/shaded/protobuf/generated/HBaseProtos$TableSchema$Builder.build:()Lorg/apache/hadoop/hbase/shaded/protobuf/generated/HBaseProtos$TableSchema;
      30: invokevirtual #123                // Method org/apache/hbase/thirdparty/com/google/protobuf/SingleFieldBuilderV3.setMessage:(Lorg/apache/hbase/thirdparty/com/google/protobuf/AbstractMessage;)Lorg/apache/hbase/thirdparty/com/google/protobuf/SingleFieldBuilderV3;
      33: pop
      34: aload_0
      35: dup
      36: getfield      #30                 // Field bitField0_:I
      39: iconst_4
      40: ior
      41: putfield      #30                 // Field bitField0_:I
      44: aload_0
      45: areturn

  public org.apache.hadoop.hbase.shaded.protobuf.generated.MasterProcedureProtos$RestoreSnapshotStateData$Builder mergeModifiedTableSchema(org.apache.hadoop.hbase.shaded.protobuf.generated.HBaseProtos$TableSchema);
    Code:
       0: aload_0
       1: getfield      #32                 // Field modifiedTableSchemaBuilder_:Lorg/apache/hbase/thirdparty/com/google/protobuf/SingleFieldBuilderV3;
       4: ifnonnull     67
       7: aload_0
       8: getfield      #30                 // Field bitField0_:I
      11: iconst_4
      12: iand
      13: iconst_4
      14: if_icmpne     55
      17: aload_0
      18: getfield      #11                 // Field modifiedTableSchema_:Lorg/apache/hadoop/hbase/shaded/protobuf/generated/HBaseProtos$TableSchema;
      21: ifnull        55
      24: aload_0
      25: getfield      #11                 // Field modifiedTableSchema_:Lorg/apache/hadoop/hbase/shaded/protobuf/generated/HBaseProtos$TableSchema;
      28: invokestatic  #144                // Method org/apache/hadoop/hbase/shaded/protobuf/generated/HBaseProtos$TableSchema.getDefaultInstance:()Lorg/apache/hadoop/hbase/shaded/protobuf/generated/HBaseProtos$TableSchema;
      31: if_acmpeq     55
      34: aload_0
      35: aload_0
      36: getfield      #11                 // Field modifiedTableSchema_:Lorg/apache/hadoop/hbase/shaded/protobuf/generated/HBaseProtos$TableSchema;
      39: invokestatic  #146                // Method org/apache/hadoop/hbase/shaded/protobuf/generated/HBaseProtos$TableSchema.newBuilder:(Lorg/apache/hadoop/hbase/shaded/protobuf/generated/HBaseProtos$TableSchema;)Lorg/apache/hadoop/hbase/shaded/protobuf/generated/HBaseProtos$TableSchema$Builder;
      42: aload_1
      43: invokevirtual #147                // Method org/apache/hadoop/hbase/shaded/protobuf/generated/HBaseProtos$TableSchema$Builder.mergeFrom:(Lorg/apache/hadoop/hbase/shaded/protobuf/generated/HBaseProtos$TableSchema;)Lorg/apache/hadoop/hbase/shaded/protobuf/generated/HBaseProtos$TableSchema$Builder;
      46: invokevirtual #148                // Method org/apache/hadoop/hbase/shaded/protobuf/generated/HBaseProtos$TableSchema$Builder.buildPartial:()Lorg/apache/hadoop/hbase/shaded/protobuf/generated/HBaseProtos$TableSchema;
      49: putfield      #11                 // Field modifiedTableSchema_:Lorg/apache/hadoop/hbase/shaded/protobuf/generated/HBaseProtos$TableSchema;
      52: goto          60
      55: aload_0
      56: aload_1
      57: putfield      #11                 // Field modifiedTableSchema_:Lorg/apache/hadoop/hbase/shaded/protobuf/generated/HBaseProtos$TableSchema;
      60: aload_0
      61: invokevirtual #79                 // Method onChanged:()V
      64: goto          76
      67: aload_0
      68: getfield      #32                 // Field modifiedTableSchemaBuilder_:Lorg/apache/hbase/thirdparty/com/google/protobuf/SingleFieldBuilderV3;
      71: aload_1
      72: invokevirtual #128                // Method org/apache/hbase/thirdparty/com/google/protobuf/SingleFieldBuilderV3.mergeFrom:(Lorg/apache/hbase/thirdparty/com/google/protobuf/AbstractMessage;)Lorg/apache/hbase/thirdparty/com/google/protobuf/SingleFieldBuilderV3;
      75: pop
      76: aload_0
      77: dup
      78: getfield      #30                 // Field bitField0_:I
      81: iconst_4
      82: ior
      83: putfield      #30                 // Field bitField0_:I
      86: aload_0
      87: areturn

  public org.apache.hadoop.hbase.shaded.protobuf.generated.MasterProcedureProtos$RestoreSnapshotStateData$Builder clearModifiedTableSchema();
    Code:
       0: aload_0
       1: getfield      #32                 // Field modifiedTableSchemaBuilder_:Lorg/apache/hbase/thirdparty/com/google/protobuf/SingleFieldBuilderV3;
       4: ifnonnull     19
       7: aload_0
       8: aconst_null
       9: putfield      #11                 // Field modifiedTableSchema_:Lorg/apache/hadoop/hbase/shaded/protobuf/generated/HBaseProtos$TableSchema;
      12: aload_0
      13: invokevirtual #79                 // Method onChanged:()V
      16: goto          27
      19: aload_0
      20: getfield      #32                 // Field modifiedTableSchemaBuilder_:Lorg/apache/hbase/thirdparty/com/google/protobuf/SingleFieldBuilderV3;
      23: invokevirtual #29                 // Method org/apache/hbase/thirdparty/com/google/protobuf/SingleFieldBuilderV3.clear:()Lorg/apache/hbase/thirdparty/com/google/protobuf/SingleFieldBuilderV3;
      26: pop
      27: aload_0
      28: aload_0
      29: getfield      #30                 // Field bitField0_:I
      32: bipush        -5
      34: iand
      35: putfield      #30                 // Field bitField0_:I
      38: aload_0
      39: areturn

  public org.apache.hadoop.hbase.shaded.protobuf.generated.HBaseProtos$TableSchema$Builder getModifiedTableSchemaBuilder();
    Code:
       0: aload_0
       1: dup
       2: getfield      #30                 // Field bitField0_:I
       5: iconst_4
       6: ior
       7: putfield      #30                 // Field bitField0_:I
      10: aload_0
      11: invokevirtual #79                 // Method onChanged:()V
      14: aload_0
      15: invokespecial #22                 // Method getModifiedTableSchemaFieldBuilder:()Lorg/apache/hbase/thirdparty/com/google/protobuf/SingleFieldBuilderV3;
      18: invokevirtual #129                // Method org/apache/hbase/thirdparty/com/google/protobuf/SingleFieldBuilderV3.getBuilder:()Lorg/apache/hbase/thirdparty/com/google/protobuf/AbstractMessage$Builder;
      21: checkcast     #149                // class org/apache/hadoop/hbase/shaded/protobuf/generated/HBaseProtos$TableSchema$Builder
      24: areturn

  public org.apache.hadoop.hbase.shaded.protobuf.generated.HBaseProtos$TableSchemaOrBuilder getModifiedTableSchemaOrBuilder();
    Code:
       0: aload_0
       1: getfield      #32                 // Field modifiedTableSchemaBuilder_:Lorg/apache/hbase/thirdparty/com/google/protobuf/SingleFieldBuilderV3;
       4: ifnull        18
       7: aload_0
       8: getfield      #32                 // Field modifiedTableSchemaBuilder_:Lorg/apache/hbase/thirdparty/com/google/protobuf/SingleFieldBuilderV3;
      11: invokevirtual #131                // Method org/apache/hbase/thirdparty/com/google/protobuf/SingleFieldBuilderV3.getMessageOrBuilder:()Lorg/apache/hbase/thirdparty/com/google/protobuf/MessageOrBuilder;
      14: checkcast     #150                // class org/apache/hadoop/hbase/shaded/protobuf/generated/HBaseProtos$TableSchemaOrBuilder
      17: areturn
      18: aload_0
      19: getfield      #11                 // Field modifiedTableSchema_:Lorg/apache/hadoop/hbase/shaded/protobuf/generated/HBaseProtos$TableSchema;
      22: ifnonnull     31
      25: invokestatic  #144                // Method org/apache/hadoop/hbase/shaded/protobuf/generated/HBaseProtos$TableSchema.getDefaultInstance:()Lorg/apache/hadoop/hbase/shaded/protobuf/generated/HBaseProtos$TableSchema;
      28: goto          35
      31: aload_0
      32: getfield      #11                 // Field modifiedTableSchema_:Lorg/apache/hadoop/hbase/shaded/protobuf/generated/HBaseProtos$TableSchema;
      35: areturn

  public java.util.List<org.apache.hadoop.hbase.shaded.protobuf.generated.HBaseProtos$RegionInfo> getRegionInfoForRestoreList();
    Code:
       0: aload_0
       1: getfield      #33                 // Field regionInfoForRestoreBuilder_:Lorg/apache/hbase/thirdparty/com/google/protobuf/RepeatedFieldBuilderV3;
       4: ifnonnull     15
       7: aload_0
       8: getfield      #13                 // Field regionInfoForRestore_:Ljava/util/List;
      11: invokestatic  #50                 // Method java/util/Collections.unmodifiableList:(Ljava/util/List;)Ljava/util/List;
      14: areturn
      15: aload_0
      16: getfield      #33                 // Field regionInfoForRestoreBuilder_:Lorg/apache/hbase/thirdparty/com/google/protobuf/RepeatedFieldBuilderV3;
      19: invokevirtual #153                // Method org/apache/hbase/thirdparty/com/google/protobuf/RepeatedFieldBuilderV3.getMessageList:()Ljava/util/List;
      22: areturn

  public int getRegionInfoForRestoreCount();
    Code:
       0: aload_0
       1: getfield      #33                 // Field regionInfoForRestoreBuilder_:Lorg/apache/hbase/thirdparty/com/google/protobuf/RepeatedFieldBuilderV3;
       4: ifnonnull     17
       7: aload_0
       8: getfield      #13                 // Field regionInfoForRestore_:Ljava/util/List;
      11: invokeinterface #154,  1          // InterfaceMethod java/util/List.size:()I
      16: ireturn
      17: aload_0
      18: getfield      #33                 // Field regionInfoForRestoreBuilder_:Lorg/apache/hbase/thirdparty/com/google/protobuf/RepeatedFieldBuilderV3;
      21: invokevirtual #155                // Method org/apache/hbase/thirdparty/com/google/protobuf/RepeatedFieldBuilderV3.getCount:()I
      24: ireturn

  public org.apache.hadoop.hbase.shaded.protobuf.generated.HBaseProtos$RegionInfo getRegionInfoForRestore(int);
    Code:
       0: aload_0
       1: getfield      #33                 // Field regionInfoForRestoreBuilder_:Lorg/apache/hbase/thirdparty/com/google/protobuf/RepeatedFieldBuilderV3;
       4: ifnonnull     21
       7: aload_0
       8: getfield      #13                 // Field regionInfoForRestore_:Ljava/util/List;
      11: iload_1
      12: invokeinterface #156,  2          // InterfaceMethod java/util/List.get:(I)Ljava/lang/Object;
      17: checkcast     #157                // class org/apache/hadoop/hbase/shaded/protobuf/generated/HBaseProtos$RegionInfo
      20: areturn
      21: aload_0
      22: getfield      #33                 // Field regionInfoForRestoreBuilder_:Lorg/apache/hbase/thirdparty/com/google/protobuf/RepeatedFieldBuilderV3;
      25: iload_1
      26: invokevirtual #158                // Method org/apache/hbase/thirdparty/com/google/protobuf/RepeatedFieldBuilderV3.getMessage:(I)Lorg/apache/hbase/thirdparty/com/google/protobuf/AbstractMessage;
      29: checkcast     #157                // class org/apache/hadoop/hbase/shaded/protobuf/generated/HBaseProtos$RegionInfo
      32: areturn

  public org.apache.hadoop.hbase.shaded.protobuf.generated.MasterProcedureProtos$RestoreSnapshotStateData$Builder setRegionInfoForRestore(int, org.apache.hadoop.hbase.shaded.protobuf.generated.HBaseProtos$RegionInfo);
    Code:
       0: aload_0
       1: getfield      #33                 // Field regionInfoForRestoreBuilder_:Lorg/apache/hbase/thirdparty/com/google/protobuf/RepeatedFieldBuilderV3;
       4: ifnonnull     42
       7: aload_2
       8: ifnonnull     19
      11: new           #121                // class java/lang/NullPointerException
      14: dup
      15: invokespecial #122                // Method java/lang/NullPointerException."<init>":()V
      18: athrow
      19: aload_0
      20: invokespecial #77                 // Method ensureRegionInfoForRestoreIsMutable:()V
      23: aload_0
      24: getfield      #13                 // Field regionInfoForRestore_:Ljava/util/List;
      27: iload_1
      28: aload_2
      29: invokeinterface #159,  3          // InterfaceMethod java/util/List.set:(ILjava/lang/Object;)Ljava/lang/Object;
      34: pop
      35: aload_0
      36: invokevirtual #79                 // Method onChanged:()V
      39: goto          52
      42: aload_0
      43: getfield      #33                 // Field regionInfoForRestoreBuilder_:Lorg/apache/hbase/thirdparty/com/google/protobuf/RepeatedFieldBuilderV3;
      46: iload_1
      47: aload_2
      48: invokevirtual #160                // Method org/apache/hbase/thirdparty/com/google/protobuf/RepeatedFieldBuilderV3.setMessage:(ILorg/apache/hbase/thirdparty/com/google/protobuf/AbstractMessage;)Lorg/apache/hbase/thirdparty/com/google/protobuf/RepeatedFieldBuilderV3;
      51: pop
      52: aload_0
      53: areturn

  public org.apache.hadoop.hbase.shaded.protobuf.generated.MasterProcedureProtos$RestoreSnapshotStateData$Builder setRegionInfoForRestore(int, org.apache.hadoop.hbase.shaded.protobuf.generated.HBaseProtos$RegionInfo$Builder);
    Code:
       0: aload_0
       1: getfield      #33                 // Field regionInfoForRestoreBuilder_:Lorg/apache/hbase/thirdparty/com/google/protobuf/RepeatedFieldBuilderV3;
       4: ifnonnull     33
       7: aload_0
       8: invokespecial #77                 // Method ensureRegionInfoForRestoreIsMutable:()V
      11: aload_0
      12: getfield      #13                 // Field regionInfoForRestore_:Ljava/util/List;
      15: iload_1
      16: aload_2
      17: invokevirtual #161                // Method org/apache/hadoop/hbase/shaded/protobuf/generated/HBaseProtos$RegionInfo$Builder.build:()Lorg/apache/hadoop/hbase/shaded/protobuf/generated/HBaseProtos$RegionInfo;
      20: invokeinterface #159,  3          // InterfaceMethod java/util/List.set:(ILjava/lang/Object;)Ljava/lang/Object;
      25: pop
      26: aload_0
      27: invokevirtual #79                 // Method onChanged:()V
      30: goto          46
      33: aload_0
      34: getfield      #33                 // Field regionInfoForRestoreBuilder_:Lorg/apache/hbase/thirdparty/com/google/protobuf/RepeatedFieldBuilderV3;
      37: iload_1
      38: aload_2
      39: invokevirtual #161                // Method org/apache/hadoop/hbase/shaded/protobuf/generated/HBaseProtos$RegionInfo$Builder.build:()Lorg/apache/hadoop/hbase/shaded/protobuf/generated/HBaseProtos$RegionInfo;
      42: invokevirtual #160                // Method org/apache/hbase/thirdparty/com/google/protobuf/RepeatedFieldBuilderV3.setMessage:(ILorg/apache/hbase/thirdparty/com/google/protobuf/AbstractMessage;)Lorg/apache/hbase/thirdparty/com/google/protobuf/RepeatedFieldBuilderV3;
      45: pop
      46: aload_0
      47: areturn

  public org.apache.hadoop.hbase.shaded.protobuf.generated.MasterProcedureProtos$RestoreSnapshotStateData$Builder addRegionInfoForRestore(org.apache.hadoop.hbase.shaded.protobuf.generated.HBaseProtos$RegionInfo);
    Code:
       0: aload_0
       1: getfield      #33                 // Field regionInfoForRestoreBuilder_:Lorg/apache/hbase/thirdparty/com/google/protobuf/RepeatedFieldBuilderV3;
       4: ifnonnull     41
       7: aload_1
       8: ifnonnull     19
      11: new           #121                // class java/lang/NullPointerException
      14: dup
      15: invokespecial #122                // Method java/lang/NullPointerException."<init>":()V
      18: athrow
      19: aload_0
      20: invokespecial #77                 // Method ensureRegionInfoForRestoreIsMutable:()V
      23: aload_0
      24: getfield      #13                 // Field regionInfoForRestore_:Ljava/util/List;
      27: aload_1
      28: invokeinterface #162,  2          // InterfaceMethod java/util/List.add:(Ljava/lang/Object;)Z
      33: pop
      34: aload_0
      35: invokevirtual #79                 // Method onChanged:()V
      38: goto          50
      41: aload_0
      42: getfield      #33                 // Field regionInfoForRestoreBuilder_:Lorg/apache/hbase/thirdparty/com/google/protobuf/RepeatedFieldBuilderV3;
      45: aload_1
      46: invokevirtual #163                // Method org/apache/hbase/thirdparty/com/google/protobuf/RepeatedFieldBuilderV3.addMessage:(Lorg/apache/hbase/thirdparty/com/google/protobuf/AbstractMessage;)Lorg/apache/hbase/thirdparty/com/google/protobuf/RepeatedFieldBuilderV3;
      49: pop
      50: aload_0
      51: areturn

  public org.apache.hadoop.hbase.shaded.protobuf.generated.MasterProcedureProtos$RestoreSnapshotStateData$Builder addRegionInfoForRestore(int, org.apache.hadoop.hbase.shaded.protobuf.generated.HBaseProtos$RegionInfo);
    Code:
       0: aload_0
       1: getfield      #33                 // Field regionInfoForRestoreBuilder_:Lorg/apache/hbase/thirdparty/com/google/protobuf/RepeatedFieldBuilderV3;
       4: ifnonnull     41
       7: aload_2
       8: ifnonnull     19
      11: new           #121                // class java/lang/NullPointerException
      14: dup
      15: invokespecial #122                // Method java/lang/NullPointerException."<init>":()V
      18: athrow
      19: aload_0
      20: invokespecial #77                 // Method ensureRegionInfoForRestoreIsMutable:()V
      23: aload_0
      24: getfield      #13                 // Field regionInfoForRestore_:Ljava/util/List;
      27: iload_1
      28: aload_2
      29: invokeinterface #164,  3          // InterfaceMethod java/util/List.add:(ILjava/lang/Object;)V
      34: aload_0
      35: invokevirtual #79                 // Method onChanged:()V
      38: goto          51
      41: aload_0
      42: getfield      #33                 // Field regionInfoForRestoreBuilder_:Lorg/apache/hbase/thirdparty/com/google/protobuf/RepeatedFieldBuilderV3;
      45: iload_1
      46: aload_2
      47: invokevirtual #165                // Method org/apache/hbase/thirdparty/com/google/protobuf/RepeatedFieldBuilderV3.addMessage:(ILorg/apache/hbase/thirdparty/com/google/protobuf/AbstractMessage;)Lorg/apache/hbase/thirdparty/com/google/protobuf/RepeatedFieldBuilderV3;
      50: pop
      51: aload_0
      52: areturn

  public org.apache.hadoop.hbase.shaded.protobuf.generated.MasterProcedureProtos$RestoreSnapshotStateData$Builder addRegionInfoForRestore(org.apache.hadoop.hbase.shaded.protobuf.generated.HBaseProtos$RegionInfo$Builder);
    Code:
       0: aload_0
       1: getfield      #33                 // Field regionInfoForRestoreBuilder_:Lorg/apache/hbase/thirdparty/com/google/protobuf/RepeatedFieldBuilderV3;
       4: ifnonnull     32
       7: aload_0
       8: invokespecial #77                 // Method ensureRegionInfoForRestoreIsMutable:()V
      11: aload_0
      12: getfield      #13                 // Field regionInfoForRestore_:Ljava/util/List;
      15: aload_1
      16: invokevirtual #161                // Method org/apache/hadoop/hbase/shaded/protobuf/generated/HBaseProtos$RegionInfo$Builder.build:()Lorg/apache/hadoop/hbase/shaded/protobuf/generated/HBaseProtos$RegionInfo;
      19: invokeinterface #162,  2          // InterfaceMethod java/util/List.add:(Ljava/lang/Object;)Z
      24: pop
      25: aload_0
      26: invokevirtual #79                 // Method onChanged:()V
      29: goto          44
      32: aload_0
      33: getfield      #33                 // Field regionInfoForRestoreBuilder_:Lorg/apache/hbase/thirdparty/com/google/protobuf/RepeatedFieldBuilderV3;
      36: aload_1
      37: invokevirtual #161                // Method org/apache/hadoop/hbase/shaded/protobuf/generated/HBaseProtos$RegionInfo$Builder.build:()Lorg/apache/hadoop/hbase/shaded/protobuf/generated/HBaseProtos$RegionInfo;
      40: invokevirtual #163                // Method org/apache/hbase/thirdparty/com/google/protobuf/RepeatedFieldBuilderV3.addMessage:(Lorg/apache/hbase/thirdparty/com/google/protobuf/AbstractMessage;)Lorg/apache/hbase/thirdparty/com/google/protobuf/RepeatedFieldBuilderV3;
      43: pop
      44: aload_0
      45: areturn

  public org.apache.hadoop.hbase.shaded.protobuf.generated.MasterProcedureProtos$RestoreSnapshotStateData$Builder addRegionInfoForRestore(int, org.apache.hadoop.hbase.shaded.protobuf.generated.HBaseProtos$RegionInfo$Builder);
    Code:
       0: aload_0
       1: getfield      #33                 // Field regionInfoForRestoreBuilder_:Lorg/apache/hbase/thirdparty/com/google/protobuf/RepeatedFieldBuilderV3;
       4: ifnonnull     32
       7: aload_0
       8: invokespecial #77                 // Method ensureRegionInfoForRestoreIsMutable:()V
      11: aload_0
      12: getfield      #13                 // Field regionInfoForRestore_:Ljava/util/List;
      15: iload_1
      16: aload_2
      17: invokevirtual #161                // Method org/apache/hadoop/hbase/shaded/protobuf/generated/HBaseProtos$RegionInfo$Builder.build:()Lorg/apache/hadoop/hbase/shaded/protobuf/generated/HBaseProtos$RegionInfo;
      20: invokeinterface #164,  3          // InterfaceMethod java/util/List.add:(ILjava/lang/Object;)V
      25: aload_0
      26: invokevirtual #79                 // Method onChanged:()V
      29: goto          45
      32: aload_0
      33: getfield      #33                 // Field regionInfoForRestoreBuilder_:Lorg/apache/hbase/thirdparty/com/google/protobuf/RepeatedFieldBuilderV3;
      36: iload_1
      37: aload_2
      38: invokevirtual #161                // Method org/apache/hadoop/hbase/shaded/protobuf/generated/HBaseProtos$RegionInfo$Builder.build:()Lorg/apache/hadoop/hbase/shaded/protobuf/generated/HBaseProtos$RegionInfo;
      41: invokevirtual #165                // Method org/apache/hbase/thirdparty/com/google/protobuf/RepeatedFieldBuilderV3.addMessage:(ILorg/apache/hbase/thirdparty/com/google/protobuf/AbstractMessage;)Lorg/apache/hbase/thirdparty/com/google/protobuf/RepeatedFieldBuilderV3;
      44: pop
      45: aload_0
      46: areturn

  public org.apache.hadoop.hbase.shaded.protobuf.generated.MasterProcedureProtos$RestoreSnapshotStateData$Builder addAllRegionInfoForRestore(java.lang.Iterable<? extends org.apache.hadoop.hbase.shaded.protobuf.generated.HBaseProtos$RegionInfo>);
    Code:
       0: aload_0
       1: getfield      #33                 // Field regionInfoForRestoreBuilder_:Lorg/apache/hbase/thirdparty/com/google/protobuf/RepeatedFieldBuilderV3;
       4: ifnonnull     26
       7: aload_0
       8: invokespecial #77                 // Method ensureRegionInfoForRestoreIsMutable:()V
      11: aload_1
      12: aload_0
      13: getfield      #13                 // Field regionInfoForRestore_:Ljava/util/List;
      16: invokestatic  #166                // Method org/apache/hbase/thirdparty/com/google/protobuf/AbstractMessageLite$Builder.addAll:(Ljava/lang/Iterable;Ljava/util/List;)V
      19: aload_0
      20: invokevirtual #79                 // Method onChanged:()V
      23: goto          35
      26: aload_0
      27: getfield      #33                 // Field regionInfoForRestoreBuilder_:Lorg/apache/hbase/thirdparty/com/google/protobuf/RepeatedFieldBuilderV3;
      30: aload_1
      31: invokevirtual #83                 // Method org/apache/hbase/thirdparty/com/google/protobuf/RepeatedFieldBuilderV3.addAllMessages:(Ljava/lang/Iterable;)Lorg/apache/hbase/thirdparty/com/google/protobuf/RepeatedFieldBuilderV3;
      34: pop
      35: aload_0
      36: areturn

  public org.apache.hadoop.hbase.shaded.protobuf.generated.MasterProcedureProtos$RestoreSnapshotStateData$Builder clearRegionInfoForRestore();
    Code:
       0: aload_0
       1: getfield      #33                 // Field regionInfoForRestoreBuilder_:Lorg/apache/hbase/thirdparty/com/google/protobuf/RepeatedFieldBuilderV3;
       4: ifnonnull     32
       7: aload_0
       8: invokestatic  #12                 // Method java/util/Collections.emptyList:()Ljava/util/List;
      11: putfield      #13                 // Field regionInfoForRestore_:Ljava/util/List;
      14: aload_0
      15: aload_0
      16: getfield      #30                 // Field bitField0_:I
      19: bipush        -9
      21: iand
      22: putfield      #30                 // Field bitField0_:I
      25: aload_0
      26: invokevirtual #79                 // Method onChanged:()V
      29: goto          39
      32: aload_0
      33: getfield      #33                 // Field regionInfoForRestoreBuilder_:Lorg/apache/hbase/thirdparty/com/google/protobuf/RepeatedFieldBuilderV3;
      36: invokevirtual #34                 // Method org/apache/hbase/thirdparty/com/google/protobuf/RepeatedFieldBuilderV3.clear:()V
      39: aload_0
      40: areturn

  public org.apache.hadoop.hbase.shaded.protobuf.generated.MasterProcedureProtos$RestoreSnapshotStateData$Builder removeRegionInfoForRestore(int);
    Code:
       0: aload_0
       1: getfield      #33                 // Field regionInfoForRestoreBuilder_:Lorg/apache/hbase/thirdparty/com/google/protobuf/RepeatedFieldBuilderV3;
       4: ifnonnull     29
       7: aload_0
       8: invokespecial #77                 // Method ensureRegionInfoForRestoreIsMutable:()V
      11: aload_0
      12: getfield      #13                 // Field regionInfoForRestore_:Ljava/util/List;
      15: iload_1
      16: invokeinterface #167,  2          // InterfaceMethod java/util/List.remove:(I)Ljava/lang/Object;
      21: pop
      22: aload_0
      23: invokevirtual #79                 // Method onChanged:()V
      26: goto          37
      29: aload_0
      30: getfield      #33                 // Field regionInfoForRestoreBuilder_:Lorg/apache/hbase/thirdparty/com/google/protobuf/RepeatedFieldBuilderV3;
      33: iload_1
      34: invokevirtual #168                // Method org/apache/hbase/thirdparty/com/google/protobuf/RepeatedFieldBuilderV3.remove:(I)V
      37: aload_0
      38: areturn

  public org.apache.hadoop.hbase.shaded.protobuf.generated.HBaseProtos$RegionInfo$Builder getRegionInfoForRestoreBuilder(int);
    Code:
       0: aload_0
       1: invokespecial #23                 // Method getRegionInfoForRestoreFieldBuilder:()Lorg/apache/hbase/thirdparty/com/google/protobuf/RepeatedFieldBuilderV3;
       4: iload_1
       5: invokevirtual #169                // Method org/apache/hbase/thirdparty/com/google/protobuf/RepeatedFieldBuilderV3.getBuilder:(I)Lorg/apache/hbase/thirdparty/com/google/protobuf/AbstractMessage$Builder;
       8: checkcast     #170                // class org/apache/hadoop/hbase/shaded/protobuf/generated/HBaseProtos$RegionInfo$Builder
      11: areturn

  public org.apache.hadoop.hbase.shaded.protobuf.generated.HBaseProtos$RegionInfoOrBuilder getRegionInfoForRestoreOrBuilder(int);
    Code:
       0: aload_0
       1: getfield      #33                 // Field regionInfoForRestoreBuilder_:Lorg/apache/hbase/thirdparty/com/google/protobuf/RepeatedFieldBuilderV3;
       4: ifnonnull     21
       7: aload_0
       8: getfield      #13                 // Field regionInfoForRestore_:Ljava/util/List;
      11: iload_1
      12: invokeinterface #156,  2          // InterfaceMethod java/util/List.get:(I)Ljava/lang/Object;
      17: checkcast     #171                // class org/apache/hadoop/hbase/shaded/protobuf/generated/HBaseProtos$RegionInfoOrBuilder
      20: areturn
      21: aload_0
      22: getfield      #33                 // Field regionInfoForRestoreBuilder_:Lorg/apache/hbase/thirdparty/com/google/protobuf/RepeatedFieldBuilderV3;
      25: iload_1
      26: invokevirtual #172                // Method org/apache/hbase/thirdparty/com/google/protobuf/RepeatedFieldBuilderV3.getMessageOrBuilder:(I)Lorg/apache/hbase/thirdparty/com/google/protobuf/MessageOrBuilder;
      29: checkcast     #171                // class org/apache/hadoop/hbase/shaded/protobuf/generated/HBaseProtos$RegionInfoOrBuilder
      32: areturn

  public java.util.List<? extends org.apache.hadoop.hbase.shaded.protobuf.generated.HBaseProtos$RegionInfoOrBuilder> getRegionInfoForRestoreOrBuilderList();
    Code:
       0: aload_0
       1: getfield      #33                 // Field regionInfoForRestoreBuilder_:Lorg/apache/hbase/thirdparty/com/google/protobuf/RepeatedFieldBuilderV3;
       4: ifnull        15
       7: aload_0
       8: getfield      #33                 // Field regionInfoForRestoreBuilder_:Lorg/apache/hbase/thirdparty/com/google/protobuf/RepeatedFieldBuilderV3;
      11: invokevirtual #173                // Method org/apache/hbase/thirdparty/com/google/protobuf/RepeatedFieldBuilderV3.getMessageOrBuilderList:()Ljava/util/List;
      14: areturn
      15: aload_0
      16: getfield      #13                 // Field regionInfoForRestore_:Ljava/util/List;
      19: invokestatic  #50                 // Method java/util/Collections.unmodifiableList:(Ljava/util/List;)Ljava/util/List;
      22: areturn

  public org.apache.hadoop.hbase.shaded.protobuf.generated.HBaseProtos$RegionInfo$Builder addRegionInfoForRestoreBuilder();
    Code:
       0: aload_0
       1: invokespecial #23                 // Method getRegionInfoForRestoreFieldBuilder:()Lorg/apache/hbase/thirdparty/com/google/protobuf/RepeatedFieldBuilderV3;
       4: invokestatic  #174                // Method org/apache/hadoop/hbase/shaded/protobuf/generated/HBaseProtos$RegionInfo.getDefaultInstance:()Lorg/apache/hadoop/hbase/shaded/protobuf/generated/HBaseProtos$RegionInfo;
       7: invokevirtual #175                // Method org/apache/hbase/thirdparty/com/google/protobuf/RepeatedFieldBuilderV3.addBuilder:(Lorg/apache/hbase/thirdparty/com/google/protobuf/AbstractMessage;)Lorg/apache/hbase/thirdparty/com/google/protobuf/AbstractMessage$Builder;
      10: checkcast     #170                // class org/apache/hadoop/hbase/shaded/protobuf/generated/HBaseProtos$RegionInfo$Builder
      13: areturn

  public org.apache.hadoop.hbase.shaded.protobuf.generated.HBaseProtos$RegionInfo$Builder addRegionInfoForRestoreBuilder(int);
    Code:
       0: aload_0
       1: invokespecial #23                 // Method getRegionInfoForRestoreFieldBuilder:()Lorg/apache/hbase/thirdparty/com/google/protobuf/RepeatedFieldBuilderV3;
       4: iload_1
       5: invokestatic  #174                // Method org/apache/hadoop/hbase/shaded/protobuf/generated/HBaseProtos$RegionInfo.getDefaultInstance:()Lorg/apache/hadoop/hbase/shaded/protobuf/generated/HBaseProtos$RegionInfo;
       8: invokevirtual #176                // Method org/apache/hbase/thirdparty/com/google/protobuf/RepeatedFieldBuilderV3.addBuilder:(ILorg/apache/hbase/thirdparty/com/google/protobuf/AbstractMessage;)Lorg/apache/hbase/thirdparty/com/google/protobuf/AbstractMessage$Builder;
      11: checkcast     #170                // class org/apache/hadoop/hbase/shaded/protobuf/generated/HBaseProtos$RegionInfo$Builder
      14: areturn

  public java.util.List<org.apache.hadoop.hbase.shaded.protobuf.generated.HBaseProtos$RegionInfo$Builder> getRegionInfoForRestoreBuilderList();
    Code:
       0: aload_0
       1: invokespecial #23                 // Method getRegionInfoForRestoreFieldBuilder:()Lorg/apache/hbase/thirdparty/com/google/protobuf/RepeatedFieldBuilderV3;
       4: invokevirtual #177                // Method org/apache/hbase/thirdparty/com/google/protobuf/RepeatedFieldBuilderV3.getBuilderList:()Ljava/util/List;
       7: areturn

  public java.util.List<org.apache.hadoop.hbase.shaded.protobuf.generated.HBaseProtos$RegionInfo> getRegionInfoForRemoveList();
    Code:
       0: aload_0
       1: getfield      #35                 // Field regionInfoForRemoveBuilder_:Lorg/apache/hbase/thirdparty/com/google/protobuf/RepeatedFieldBuilderV3;
       4: ifnonnull     15
       7: aload_0
       8: getfield      #14                 // Field regionInfoForRemove_:Ljava/util/List;
      11: invokestatic  #50                 // Method java/util/Collections.unmodifiableList:(Ljava/util/List;)Ljava/util/List;
      14: areturn
      15: aload_0
      16: getfield      #35                 // Field regionInfoForRemoveBuilder_:Lorg/apache/hbase/thirdparty/com/google/protobuf/RepeatedFieldBuilderV3;
      19: invokevirtual #153                // Method org/apache/hbase/thirdparty/com/google/protobuf/RepeatedFieldBuilderV3.getMessageList:()Ljava/util/List;
      22: areturn

  public int getRegionInfoForRemoveCount();
    Code:
       0: aload_0
       1: getfield      #35                 // Field regionInfoForRemoveBuilder_:Lorg/apache/hbase/thirdparty/com/google/protobuf/RepeatedFieldBuilderV3;
       4: ifnonnull     17
       7: aload_0
       8: getfield      #14                 // Field regionInfoForRemove_:Ljava/util/List;
      11: invokeinterface #154,  1          // InterfaceMethod java/util/List.size:()I
      16: ireturn
      17: aload_0
      18: getfield      #35                 // Field regionInfoForRemoveBuilder_:Lorg/apache/hbase/thirdparty/com/google/protobuf/RepeatedFieldBuilderV3;
      21: invokevirtual #155                // Method org/apache/hbase/thirdparty/com/google/protobuf/RepeatedFieldBuilderV3.getCount:()I
      24: ireturn

  public org.apache.hadoop.hbase.shaded.protobuf.generated.HBaseProtos$RegionInfo getRegionInfoForRemove(int);
    Code:
       0: aload_0
       1: getfield      #35                 // Field regionInfoForRemoveBuilder_:Lorg/apache/hbase/thirdparty/com/google/protobuf/RepeatedFieldBuilderV3;
       4: ifnonnull     21
       7: aload_0
       8: getfield      #14                 // Field regionInfoForRemove_:Ljava/util/List;
      11: iload_1
      12: invokeinterface #156,  2          // InterfaceMethod java/util/List.get:(I)Ljava/lang/Object;
      17: checkcast     #157                // class org/apache/hadoop/hbase/shaded/protobuf/generated/HBaseProtos$RegionInfo
      20: areturn
      21: aload_0
      22: getfield      #35                 // Field regionInfoForRemoveBuilder_:Lorg/apache/hbase/thirdparty/com/google/protobuf/RepeatedFieldBuilderV3;
      25: iload_1
      26: invokevirtual #158                // Method org/apache/hbase/thirdparty/com/google/protobuf/RepeatedFieldBuilderV3.getMessage:(I)Lorg/apache/hbase/thirdparty/com/google/protobuf/AbstractMessage;
      29: checkcast     #157                // class org/apache/hadoop/hbase/shaded/protobuf/generated/HBaseProtos$RegionInfo
      32: areturn

  public org.apache.hadoop.hbase.shaded.protobuf.generated.MasterProcedureProtos$RestoreSnapshotStateData$Builder setRegionInfoForRemove(int, org.apache.hadoop.hbase.shaded.protobuf.generated.HBaseProtos$RegionInfo);
    Code:
       0: aload_0
       1: getfield      #35                 // Field regionInfoForRemoveBuilder_:Lorg/apache/hbase/thirdparty/com/google/protobuf/RepeatedFieldBuilderV3;
       4: ifnonnull     42
       7: aload_2
       8: ifnonnull     19
      11: new           #121                // class java/lang/NullPointerException
      14: dup
      15: invokespecial #122                // Method java/lang/NullPointerException."<init>":()V
      18: athrow
      19: aload_0
      20: invokespecial #85                 // Method ensureRegionInfoForRemoveIsMutable:()V
      23: aload_0
      24: getfield      #14                 // Field regionInfoForRemove_:Ljava/util/List;
      27: iload_1
      28: aload_2
      29: invokeinterface #159,  3          // InterfaceMethod java/util/List.set:(ILjava/lang/Object;)Ljava/lang/Object;
      34: pop
      35: aload_0
      36: invokevirtual #79                 // Method onChanged:()V
      39: goto          52
      42: aload_0
      43: getfield      #35                 // Field regionInfoForRemoveBuilder_:Lorg/apache/hbase/thirdparty/com/google/protobuf/RepeatedFieldBuilderV3;
      46: iload_1
      47: aload_2
      48: invokevirtual #160                // Method org/apache/hbase/thirdparty/com/google/protobuf/RepeatedFieldBuilderV3.setMessage:(ILorg/apache/hbase/thirdparty/com/google/protobuf/AbstractMessage;)Lorg/apache/hbase/thirdparty/com/google/protobuf/RepeatedFieldBuilderV3;
      51: pop
      52: aload_0
      53: areturn

  public org.apache.hadoop.hbase.shaded.protobuf.generated.MasterProcedureProtos$RestoreSnapshotStateData$Builder setRegionInfoForRemove(int, org.apache.hadoop.hbase.shaded.protobuf.generated.HBaseProtos$RegionInfo$Builder);
    Code:
       0: aload_0
       1: getfield      #35                 // Field regionInfoForRemoveBuilder_:Lorg/apache/hbase/thirdparty/com/google/protobuf/RepeatedFieldBuilderV3;
       4: ifnonnull     33
       7: aload_0
       8: invokespecial #85                 // Method ensureRegionInfoForRemoveIsMutable:()V
      11: aload_0
      12: getfield      #14                 // Field regionInfoForRemove_:Ljava/util/List;
      15: iload_1
      16: aload_2
      17: invokevirtual #161                // Method org/apache/hadoop/hbase/shaded/protobuf/generated/HBaseProtos$RegionInfo$Builder.build:()Lorg/apache/hadoop/hbase/shaded/protobuf/generated/HBaseProtos$RegionInfo;
      20: invokeinterface #159,  3          // InterfaceMethod java/util/List.set:(ILjava/lang/Object;)Ljava/lang/Object;
      25: pop
      26: aload_0
      27: invokevirtual #79                 // Method onChanged:()V
      30: goto          46
      33: aload_0
      34: getfield      #35                 // Field regionInfoForRemoveBuilder_:Lorg/apache/hbase/thirdparty/com/google/protobuf/RepeatedFieldBuilderV3;
      37: iload_1
      38: aload_2
      39: invokevirtual #161                // Method org/apache/hadoop/hbase/shaded/protobuf/generated/HBaseProtos$RegionInfo$Builder.build:()Lorg/apache/hadoop/hbase/shaded/protobuf/generated/HBaseProtos$RegionInfo;
      42: invokevirtual #160                // Method org/apache/hbase/thirdparty/com/google/protobuf/RepeatedFieldBuilderV3.setMessage:(ILorg/apache/hbase/thirdparty/com/google/protobuf/AbstractMessage;)Lorg/apache/hbase/thirdparty/com/google/protobuf/RepeatedFieldBuilderV3;
      45: pop
      46: aload_0
      47: areturn

  public org.apache.hadoop.hbase.shaded.protobuf.generated.MasterProcedureProtos$RestoreSnapshotStateData$Builder addRegionInfoForRemove(org.apache.hadoop.hbase.shaded.protobuf.generated.HBaseProtos$RegionInfo);
    Code:
       0: aload_0
       1: getfield      #35                 // Field regionInfoForRemoveBuilder_:Lorg/apache/hbase/thirdparty/com/google/protobuf/RepeatedFieldBuilderV3;
       4: ifnonnull     41
       7: aload_1
       8: ifnonnull     19
      11: new           #121                // class java/lang/NullPointerException
      14: dup
      15: invokespecial #122                // Method java/lang/NullPointerException."<init>":()V
      18: athrow
      19: aload_0
      20: invokespecial #85                 // Method ensureRegionInfoForRemoveIsMutable:()V
      23: aload_0
      24: getfield      #14                 // Field regionInfoForRemove_:Ljava/util/List;
      27: aload_1
      28: invokeinterface #162,  2          // InterfaceMethod java/util/List.add:(Ljava/lang/Object;)Z
      33: pop
      34: aload_0
      35: invokevirtual #79                 // Method onChanged:()V
      38: goto          50
      41: aload_0
      42: getfield      #35                 // Field regionInfoForRemoveBuilder_:Lorg/apache/hbase/thirdparty/com/google/protobuf/RepeatedFieldBuilderV3;
      45: aload_1
      46: invokevirtual #163                // Method org/apache/hbase/thirdparty/com/google/protobuf/RepeatedFieldBuilderV3.addMessage:(Lorg/apache/hbase/thirdparty/com/google/protobuf/AbstractMessage;)Lorg/apache/hbase/thirdparty/com/google/protobuf/RepeatedFieldBuilderV3;
      49: pop
      50: aload_0
      51: areturn

  public org.apache.hadoop.hbase.shaded.protobuf.generated.MasterProcedureProtos$RestoreSnapshotStateData$Builder addRegionInfoForRemove(int, org.apache.hadoop.hbase.shaded.protobuf.generated.HBaseProtos$RegionInfo);
    Code:
       0: aload_0
       1: getfield      #35                 // Field regionInfoForRemoveBuilder_:Lorg/apache/hbase/thirdparty/com/google/protobuf/RepeatedFieldBuilderV3;
       4: ifnonnull     41
       7: aload_2
       8: ifnonnull     19
      11: new           #121                // class java/lang/NullPointerException
      14: dup
      15: invokespecial #122                // Method java/lang/NullPointerException."<init>":()V
      18: athrow
      19: aload_0
      20: invokespecial #85                 // Method ensureRegionInfoForRemoveIsMutable:()V
      23: aload_0
      24: getfield      #14                 // Field regionInfoForRemove_:Ljava/util/List;
      27: iload_1
      28: aload_2
      29: invokeinterface #164,  3          // InterfaceMethod java/util/List.add:(ILjava/lang/Object;)V
      34: aload_0
      35: invokevirtual #79                 // Method onChanged:()V
      38: goto          51
      41: aload_0
      42: getfield      #35                 // Field regionInfoForRemoveBuilder_:Lorg/apache/hbase/thirdparty/com/google/protobuf/RepeatedFieldBuilderV3;
      45: iload_1
      46: aload_2
      47: invokevirtual #165                // Method org/apache/hbase/thirdparty/com/google/protobuf/RepeatedFieldBuilderV3.addMessage:(ILorg/apache/hbase/thirdparty/com/google/protobuf/AbstractMessage;)Lorg/apache/hbase/thirdparty/com/google/protobuf/RepeatedFieldBuilderV3;
      50: pop
      51: aload_0
      52: areturn

  public org.apache.hadoop.hbase.shaded.protobuf.generated.MasterProcedureProtos$RestoreSnapshotStateData$Builder addRegionInfoForRemove(org.apache.hadoop.hbase.shaded.protobuf.generated.HBaseProtos$RegionInfo$Builder);
    Code:
       0: aload_0
       1: getfield      #35                 // Field regionInfoForRemoveBuilder_:Lorg/apache/hbase/thirdparty/com/google/protobuf/RepeatedFieldBuilderV3;
       4: ifnonnull     32
       7: aload_0
       8: invokespecial #85                 // Method ensureRegionInfoForRemoveIsMutable:()V
      11: aload_0
      12: getfield      #14                 // Field regionInfoForRemove_:Ljava/util/List;
      15: aload_1
      16: invokevirtual #161                // Method org/apache/hadoop/hbase/shaded/protobuf/generated/HBaseProtos$RegionInfo$Builder.build:()Lorg/apache/hadoop/hbase/shaded/protobuf/generated/HBaseProtos$RegionInfo;
      19: invokeinterface #162,  2          // InterfaceMethod java/util/List.add:(Ljava/lang/Object;)Z
      24: pop
      25: aload_0
      26: invokevirtual #79                 // Method onChanged:()V
      29: goto          44
      32: aload_0
      33: getfield      #35                 // Field regionInfoForRemoveBuilder_:Lorg/apache/hbase/thirdparty/com/google/protobuf/RepeatedFieldBuilderV3;
      36: aload_1
      37: invokevirtual #161                // Method org/apache/hadoop/hbase/shaded/protobuf/generated/HBaseProtos$RegionInfo$Builder.build:()Lorg/apache/hadoop/hbase/shaded/protobuf/generated/HBaseProtos$RegionInfo;
      40: invokevirtual #163                // Method org/apache/hbase/thirdparty/com/google/protobuf/RepeatedFieldBuilderV3.addMessage:(Lorg/apache/hbase/thirdparty/com/google/protobuf/AbstractMessage;)Lorg/apache/hbase/thirdparty/com/google/protobuf/RepeatedFieldBuilderV3;
      43: pop
      44: aload_0
      45: areturn

  public org.apache.hadoop.hbase.shaded.protobuf.generated.MasterProcedureProtos$RestoreSnapshotStateData$Builder addRegionInfoForRemove(int, org.apache.hadoop.hbase.shaded.protobuf.generated.HBaseProtos$RegionInfo$Builder);
    Code:
       0: aload_0
       1: getfield      #35                 // Field regionInfoForRemoveBuilder_:Lorg/apache/hbase/thirdparty/com/google/protobuf/RepeatedFieldBuilderV3;
       4: ifnonnull     32
       7: aload_0
       8: invokespecial #85                 // Method ensureRegionInfoForRemoveIsMutable:()V
      11: aload_0
      12: getfield      #14                 // Field regionInfoForRemove_:Ljava/util/List;
      15: iload_1
      16: aload_2
      17: invokevirtual #161                // Method org/apache/hadoop/hbase/shaded/protobuf/generated/HBaseProtos$RegionInfo$Builder.build:()Lorg/apache/hadoop/hbase/shaded/protobuf/generated/HBaseProtos$RegionInfo;
      20: invokeinterface #164,  3          // InterfaceMethod java/util/List.add:(ILjava/lang/Object;)V
      25: aload_0
      26: invokevirtual #79                 // Method onChanged:()V
      29: goto          45
      32: aload_0
      33: getfield      #35                 // Field regionInfoForRemoveBuilder_:Lorg/apache/hbase/thirdparty/com/google/protobuf/RepeatedFieldBuilderV3;
      36: iload_1
      37: aload_2
      38: invokevirtual #161                // Method org/apache/hadoop/hbase/shaded/protobuf/generated/HBaseProtos$RegionInfo$Builder.build:()Lorg/apache/hadoop/hbase/shaded/protobuf/generated/HBaseProtos$RegionInfo;
      41: invokevirtual #165                // Method org/apache/hbase/thirdparty/com/google/protobuf/RepeatedFieldBuilderV3.addMessage:(ILorg/apache/hbase/thirdparty/com/google/protobuf/AbstractMessage;)Lorg/apache/hbase/thirdparty/com/google/protobuf/RepeatedFieldBuilderV3;
      44: pop
      45: aload_0
      46: areturn

  public org.apache.hadoop.hbase.shaded.protobuf.generated.MasterProcedureProtos$RestoreSnapshotStateData$Builder addAllRegionInfoForRemove(java.lang.Iterable<? extends org.apache.hadoop.hbase.shaded.protobuf.generated.HBaseProtos$RegionInfo>);
    Code:
       0: aload_0
       1: getfield      #35                 // Field regionInfoForRemoveBuilder_:Lorg/apache/hbase/thirdparty/com/google/protobuf/RepeatedFieldBuilderV3;
       4: ifnonnull     26
       7: aload_0
       8: invokespecial #85                 // Method ensureRegionInfoForRemoveIsMutable:()V
      11: aload_1
      12: aload_0
      13: getfield      #14                 // Field regionInfoForRemove_:Ljava/util/List;
      16: invokestatic  #166                // Method org/apache/hbase/thirdparty/com/google/protobuf/AbstractMessageLite$Builder.addAll:(Ljava/lang/Iterable;Ljava/util/List;)V
      19: aload_0
      20: invokevirtual #79                 // Method onChanged:()V
      23: goto          35
      26: aload_0
      27: getfield      #35                 // Field regionInfoForRemoveBuilder_:Lorg/apache/hbase/thirdparty/com/google/protobuf/RepeatedFieldBuilderV3;
      30: aload_1
      31: invokevirtual #83                 // Method org/apache/hbase/thirdparty/com/google/protobuf/RepeatedFieldBuilderV3.addAllMessages:(Ljava/lang/Iterable;)Lorg/apache/hbase/thirdparty/com/google/protobuf/RepeatedFieldBuilderV3;
      34: pop
      35: aload_0
      36: areturn

  public org.apache.hadoop.hbase.shaded.protobuf.generated.MasterProcedureProtos$RestoreSnapshotStateData$Builder clearRegionInfoForRemove();
    Code:
       0: aload_0
       1: getfield      #35                 // Field regionInfoForRemoveBuilder_:Lorg/apache/hbase/thirdparty/com/google/protobuf/RepeatedFieldBuilderV3;
       4: ifnonnull     32
       7: aload_0
       8: invokestatic  #12                 // Method java/util/Collections.emptyList:()Ljava/util/List;
      11: putfield      #14                 // Field regionInfoForRemove_:Ljava/util/List;
      14: aload_0
      15: aload_0
      16: getfield      #30                 // Field bitField0_:I
      19: bipush        -17
      21: iand
      22: putfield      #30                 // Field bitField0_:I
      25: aload_0
      26: invokevirtual #79                 // Method onChanged:()V
      29: goto          39
      32: aload_0
      33: getfield      #35                 // Field regionInfoForRemoveBuilder_:Lorg/apache/hbase/thirdparty/com/google/protobuf/RepeatedFieldBuilderV3;
      36: invokevirtual #34                 // Method org/apache/hbase/thirdparty/com/google/protobuf/RepeatedFieldBuilderV3.clear:()V
      39: aload_0
      40: areturn

  public org.apache.hadoop.hbase.shaded.protobuf.generated.MasterProcedureProtos$RestoreSnapshotStateData$Builder removeRegionInfoForRemove(int);
    Code:
       0: aload_0
       1: getfield      #35                 // Field regionInfoForRemoveBuilder_:Lorg/apache/hbase/thirdparty/com/google/protobuf/RepeatedFieldBuilderV3;
       4: ifnonnull     29
       7: aload_0
       8: invokespecial #85                 // Method ensureRegionInfoForRemoveIsMutable:()V
      11: aload_0
      12: getfield      #14                 // Field regionInfoForRemove_:Ljava/util/List;
      15: iload_1
      16: invokeinterface #167,  2          // InterfaceMethod java/util/List.remove:(I)Ljava/lang/Object;
      21: pop
      22: aload_0
      23: invokevirtual #79                 // Method onChanged:()V
      26: goto          37
      29: aload_0
      30: getfield      #35                 // Field regionInfoForRemoveBuilder_:Lorg/apache/hbase/thirdparty/com/google/protobuf/RepeatedFieldBuilderV3;
      33: iload_1
      34: invokevirtual #168                // Method org/apache/hbase/thirdparty/com/google/protobuf/RepeatedFieldBuilderV3.remove:(I)V
      37: aload_0
      38: areturn

  public org.apache.hadoop.hbase.shaded.protobuf.generated.HBaseProtos$RegionInfo$Builder getRegionInfoForRemoveBuilder(int);
    Code:
       0: aload_0
       1: invokespecial #24                 // Method getRegionInfoForRemoveFieldBuilder:()Lorg/apache/hbase/thirdparty/com/google/protobuf/RepeatedFieldBuilderV3;
       4: iload_1
       5: invokevirtual #169                // Method org/apache/hbase/thirdparty/com/google/protobuf/RepeatedFieldBuilderV3.getBuilder:(I)Lorg/apache/hbase/thirdparty/com/google/protobuf/AbstractMessage$Builder;
       8: checkcast     #170                // class org/apache/hadoop/hbase/shaded/protobuf/generated/HBaseProtos$RegionInfo$Builder
      11: areturn

  public org.apache.hadoop.hbase.shaded.protobuf.generated.HBaseProtos$RegionInfoOrBuilder getRegionInfoForRemoveOrBuilder(int);
    Code:
       0: aload_0
       1: getfield      #35                 // Field regionInfoForRemoveBuilder_:Lorg/apache/hbase/thirdparty/com/google/protobuf/RepeatedFieldBuilderV3;
       4: ifnonnull     21
       7: aload_0
       8: getfield      #14                 // Field regionInfoForRemove_:Ljava/util/List;
      11: iload_1
      12: invokeinterface #156,  2          // InterfaceMethod java/util/List.get:(I)Ljava/lang/Object;
      17: checkcast     #171                // class org/apache/hadoop/hbase/shaded/protobuf/generated/HBaseProtos$RegionInfoOrBuilder
      20: areturn
      21: aload_0
      22: getfield      #35                 // Field regionInfoForRemoveBuilder_:Lorg/apache/hbase/thirdparty/com/google/protobuf/RepeatedFieldBuilderV3;
      25: iload_1
      26: invokevirtual #172                // Method org/apache/hbase/thirdparty/com/google/protobuf/RepeatedFieldBuilderV3.getMessageOrBuilder:(I)Lorg/apache/hbase/thirdparty/com/google/protobuf/MessageOrBuilder;
      29: checkcast     #171                // class org/apache/hadoop/hbase/shaded/protobuf/generated/HBaseProtos$RegionInfoOrBuilder
      32: areturn

  public java.util.List<? extends org.apache.hadoop.hbase.shaded.protobuf.generated.HBaseProtos$RegionInfoOrBuilder> getRegionInfoForRemoveOrBuilderList();
    Code:
       0: aload_0
       1: getfield      #35                 // Field regionInfoForRemoveBuilder_:Lorg/apache/hbase/thirdparty/com/google/protobuf/RepeatedFieldBuilderV3;
       4: ifnull        15
       7: aload_0
       8: getfield      #35                 // Field regionInfoForRemoveBuilder_:Lorg/apache/hbase/thirdparty/com/google/protobuf/RepeatedFieldBuilderV3;
      11: invokevirtual #173                // Method org/apache/hbase/thirdparty/com/google/protobuf/RepeatedFieldBuilderV3.getMessageOrBuilderList:()Ljava/util/List;
      14: areturn
      15: aload_0
      16: getfield      #14                 // Field regionInfoForRemove_:Ljava/util/List;
      19: invokestatic  #50                 // Method java/util/Collections.unmodifiableList:(Ljava/util/List;)Ljava/util/List;
      22: areturn

  public org.apache.hadoop.hbase.shaded.protobuf.generated.HBaseProtos$RegionInfo$Builder addRegionInfoForRemoveBuilder();
    Code:
       0: aload_0
       1: invokespecial #24                 // Method getRegionInfoForRemoveFieldBuilder:()Lorg/apache/hbase/thirdparty/com/google/protobuf/RepeatedFieldBuilderV3;
       4: invokestatic  #174                // Method org/apache/hadoop/hbase/shaded/protobuf/generated/HBaseProtos$RegionInfo.getDefaultInstance:()Lorg/apache/hadoop/hbase/shaded/protobuf/generated/HBaseProtos$RegionInfo;
       7: invokevirtual #175                // Method org/apache/hbase/thirdparty/com/google/protobuf/RepeatedFieldBuilderV3.addBuilder:(Lorg/apache/hbase/thirdparty/com/google/protobuf/AbstractMessage;)Lorg/apache/hbase/thirdparty/com/google/protobuf/AbstractMessage$Builder;
      10: checkcast     #170                // class org/apache/hadoop/hbase/shaded/protobuf/generated/HBaseProtos$RegionInfo$Builder
      13: areturn

  public org.apache.hadoop.hbase.shaded.protobuf.generated.HBaseProtos$RegionInfo$Builder addRegionInfoForRemoveBuilder(int);
    Code:
       0: aload_0
       1: invokespecial #24                 // Method getRegionInfoForRemoveFieldBuilder:()Lorg/apache/hbase/thirdparty/com/google/protobuf/RepeatedFieldBuilderV3;
       4: iload_1
       5: invokestatic  #174                // Method org/apache/hadoop/hbase/shaded/protobuf/generated/HBaseProtos$RegionInfo.getDefaultInstance:()Lorg/apache/hadoop/hbase/shaded/protobuf/generated/HBaseProtos$RegionInfo;
       8: invokevirtual #176                // Method org/apache/hbase/thirdparty/com/google/protobuf/RepeatedFieldBuilderV3.addBuilder:(ILorg/apache/hbase/thirdparty/com/google/protobuf/AbstractMessage;)Lorg/apache/hbase/thirdparty/com/google/protobuf/AbstractMessage$Builder;
      11: checkcast     #170                // class org/apache/hadoop/hbase/shaded/protobuf/generated/HBaseProtos$RegionInfo$Builder
      14: areturn

  public java.util.List<org.apache.hadoop.hbase.shaded.protobuf.generated.HBaseProtos$RegionInfo$Builder> getRegionInfoForRemoveBuilderList();
    Code:
       0: aload_0
       1: invokespecial #24                 // Method getRegionInfoForRemoveFieldBuilder:()Lorg/apache/hbase/thirdparty/com/google/protobuf/RepeatedFieldBuilderV3;
       4: invokevirtual #177                // Method org/apache/hbase/thirdparty/com/google/protobuf/RepeatedFieldBuilderV3.getBuilderList:()Ljava/util/List;
       7: areturn

  public java.util.List<org.apache.hadoop.hbase.shaded.protobuf.generated.HBaseProtos$RegionInfo> getRegionInfoForAddList();
    Code:
       0: aload_0
       1: getfield      #36                 // Field regionInfoForAddBuilder_:Lorg/apache/hbase/thirdparty/com/google/protobuf/RepeatedFieldBuilderV3;
       4: ifnonnull     15
       7: aload_0
       8: getfield      #15                 // Field regionInfoForAdd_:Ljava/util/List;
      11: invokestatic  #50                 // Method java/util/Collections.unmodifiableList:(Ljava/util/List;)Ljava/util/List;
      14: areturn
      15: aload_0
      16: getfield      #36                 // Field regionInfoForAddBuilder_:Lorg/apache/hbase/thirdparty/com/google/protobuf/RepeatedFieldBuilderV3;
      19: invokevirtual #153                // Method org/apache/hbase/thirdparty/com/google/protobuf/RepeatedFieldBuilderV3.getMessageList:()Ljava/util/List;
      22: areturn

  public int getRegionInfoForAddCount();
    Code:
       0: aload_0
       1: getfield      #36                 // Field regionInfoForAddBuilder_:Lorg/apache/hbase/thirdparty/com/google/protobuf/RepeatedFieldBuilderV3;
       4: ifnonnull     17
       7: aload_0
       8: getfield      #15                 // Field regionInfoForAdd_:Ljava/util/List;
      11: invokeinterface #154,  1          // InterfaceMethod java/util/List.size:()I
      16: ireturn
      17: aload_0
      18: getfield      #36                 // Field regionInfoForAddBuilder_:Lorg/apache/hbase/thirdparty/com/google/protobuf/RepeatedFieldBuilderV3;
      21: invokevirtual #155                // Method org/apache/hbase/thirdparty/com/google/protobuf/RepeatedFieldBuilderV3.getCount:()I
      24: ireturn

  public org.apache.hadoop.hbase.shaded.protobuf.generated.HBaseProtos$RegionInfo getRegionInfoForAdd(int);
    Code:
       0: aload_0
       1: getfield      #36                 // Field regionInfoForAddBuilder_:Lorg/apache/hbase/thirdparty/com/google/protobuf/RepeatedFieldBuilderV3;
       4: ifnonnull     21
       7: aload_0
       8: getfield      #15                 // Field regionInfoForAdd_:Ljava/util/List;
      11: iload_1
      12: invokeinterface #156,  2          // InterfaceMethod java/util/List.get:(I)Ljava/lang/Object;
      17: checkcast     #157                // class org/apache/hadoop/hbase/shaded/protobuf/generated/HBaseProtos$RegionInfo
      20: areturn
      21: aload_0
      22: getfield      #36                 // Field regionInfoForAddBuilder_:Lorg/apache/hbase/thirdparty/com/google/protobuf/RepeatedFieldBuilderV3;
      25: iload_1
      26: invokevirtual #158                // Method org/apache/hbase/thirdparty/com/google/protobuf/RepeatedFieldBuilderV3.getMessage:(I)Lorg/apache/hbase/thirdparty/com/google/protobuf/AbstractMessage;
      29: checkcast     #157                // class org/apache/hadoop/hbase/shaded/protobuf/generated/HBaseProtos$RegionInfo
      32: areturn

  public org.apache.hadoop.hbase.shaded.protobuf.generated.MasterProcedureProtos$RestoreSnapshotStateData$Builder setRegionInfoForAdd(int, org.apache.hadoop.hbase.shaded.protobuf.generated.HBaseProtos$RegionInfo);
    Code:
       0: aload_0
       1: getfield      #36                 // Field regionInfoForAddBuilder_:Lorg/apache/hbase/thirdparty/com/google/protobuf/RepeatedFieldBuilderV3;
       4: ifnonnull     42
       7: aload_2
       8: ifnonnull     19
      11: new           #121                // class java/lang/NullPointerException
      14: dup
      15: invokespecial #122                // Method java/lang/NullPointerException."<init>":()V
      18: athrow
      19: aload_0
      20: invokespecial #88                 // Method ensureRegionInfoForAddIsMutable:()V
      23: aload_0
      24: getfield      #15                 // Field regionInfoForAdd_:Ljava/util/List;
      27: iload_1
      28: aload_2
      29: invokeinterface #159,  3          // InterfaceMethod java/util/List.set:(ILjava/lang/Object;)Ljava/lang/Object;
      34: pop
      35: aload_0
      36: invokevirtual #79                 // Method onChanged:()V
      39: goto          52
      42: aload_0
      43: getfield      #36                 // Field regionInfoForAddBuilder_:Lorg/apache/hbase/thirdparty/com/google/protobuf/RepeatedFieldBuilderV3;
      46: iload_1
      47: aload_2
      48: invokevirtual #160                // Method org/apache/hbase/thirdparty/com/google/protobuf/RepeatedFieldBuilderV3.setMessage:(ILorg/apache/hbase/thirdparty/com/google/protobuf/AbstractMessage;)Lorg/apache/hbase/thirdparty/com/google/protobuf/RepeatedFieldBuilderV3;
      51: pop
      52: aload_0
      53: areturn

  public org.apache.hadoop.hbase.shaded.protobuf.generated.MasterProcedureProtos$RestoreSnapshotStateData$Builder setRegionInfoForAdd(int, org.apache.hadoop.hbase.shaded.protobuf.generated.HBaseProtos$RegionInfo$Builder);
    Code:
       0: aload_0
       1: getfield      #36                 // Field regionInfoForAddBuilder_:Lorg/apache/hbase/thirdparty/com/google/protobuf/RepeatedFieldBuilderV3;
       4: ifnonnull     33
       7: aload_0
       8: invokespecial #88                 // Method ensureRegionInfoForAddIsMutable:()V
      11: aload_0
      12: getfield      #15                 // Field regionInfoForAdd_:Ljava/util/List;
      15: iload_1
      16: aload_2
      17: invokevirtual #161                // Method org/apache/hadoop/hbase/shaded/protobuf/generated/HBaseProtos$RegionInfo$Builder.build:()Lorg/apache/hadoop/hbase/shaded/protobuf/generated/HBaseProtos$RegionInfo;
      20: invokeinterface #159,  3          // InterfaceMethod java/util/List.set:(ILjava/lang/Object;)Ljava/lang/Object;
      25: pop
      26: aload_0
      27: invokevirtual #79                 // Method onChanged:()V
      30: goto          46
      33: aload_0
      34: getfield      #36                 // Field regionInfoForAddBuilder_:Lorg/apache/hbase/thirdparty/com/google/protobuf/RepeatedFieldBuilderV3;
      37: iload_1
      38: aload_2
      39: invokevirtual #161                // Method org/apache/hadoop/hbase/shaded/protobuf/generated/HBaseProtos$RegionInfo$Builder.build:()Lorg/apache/hadoop/hbase/shaded/protobuf/generated/HBaseProtos$RegionInfo;
      42: invokevirtual #160                // Method org/apache/hbase/thirdparty/com/google/protobuf/RepeatedFieldBuilderV3.setMessage:(ILorg/apache/hbase/thirdparty/com/google/protobuf/AbstractMessage;)Lorg/apache/hbase/thirdparty/com/google/protobuf/RepeatedFieldBuilderV3;
      45: pop
      46: aload_0
      47: areturn

  public org.apache.hadoop.hbase.shaded.protobuf.generated.MasterProcedureProtos$RestoreSnapshotStateData$Builder addRegionInfoForAdd(org.apache.hadoop.hbase.shaded.protobuf.generated.HBaseProtos$RegionInfo);
    Code:
       0: aload_0
       1: getfield      #36                 // Field regionInfoForAddBuilder_:Lorg/apache/hbase/thirdparty/com/google/protobuf/RepeatedFieldBuilderV3;
       4: ifnonnull     41
       7: aload_1
       8: ifnonnull     19
      11: new           #121                // class java/lang/NullPointerException
      14: dup
      15: invokespecial #122                // Method java/lang/NullPointerException."<init>":()V
      18: athrow
      19: aload_0
      20: invokespecial #88                 // Method ensureRegionInfoForAddIsMutable:()V
      23: aload_0
      24: getfield      #15                 // Field regionInfoForAdd_:Ljava/util/List;
      27: aload_1
      28: invokeinterface #162,  2          // InterfaceMethod java/util/List.add:(Ljava/lang/Object;)Z
      33: pop
      34: aload_0
      35: invokevirtual #79                 // Method onChanged:()V
      38: goto          50
      41: aload_0
      42: getfield      #36                 // Field regionInfoForAddBuilder_:Lorg/apache/hbase/thirdparty/com/google/protobuf/RepeatedFieldBuilderV3;
      45: aload_1
      46: invokevirtual #163                // Method org/apache/hbase/thirdparty/com/google/protobuf/RepeatedFieldBuilderV3.addMessage:(Lorg/apache/hbase/thirdparty/com/google/protobuf/AbstractMessage;)Lorg/apache/hbase/thirdparty/com/google/protobuf/RepeatedFieldBuilderV3;
      49: pop
      50: aload_0
      51: areturn

  public org.apache.hadoop.hbase.shaded.protobuf.generated.MasterProcedureProtos$RestoreSnapshotStateData$Builder addRegionInfoForAdd(int, org.apache.hadoop.hbase.shaded.protobuf.generated.HBaseProtos$RegionInfo);
    Code:
       0: aload_0
       1: getfield      #36                 // Field regionInfoForAddBuilder_:Lorg/apache/hbase/thirdparty/com/google/protobuf/RepeatedFieldBuilderV3;
       4: ifnonnull     41
       7: aload_2
       8: ifnonnull     19
      11: new           #121                // class java/lang/NullPointerException
      14: dup
      15: invokespecial #122                // Method java/lang/NullPointerException."<init>":()V
      18: athrow
      19: aload_0
      20: invokespecial #88                 // Method ensureRegionInfoForAddIsMutable:()V
      23: aload_0
      24: getfield      #15                 // Field regionInfoForAdd_:Ljava/util/List;
      27: iload_1
      28: aload_2
      29: invokeinterface #164,  3          // InterfaceMethod java/util/List.add:(ILjava/lang/Object;)V
      34: aload_0
      35: invokevirtual #79                 // Method onChanged:()V
      38: goto          51
      41: aload_0
      42: getfield      #36                 // Field regionInfoForAddBuilder_:Lorg/apache/hbase/thirdparty/com/google/protobuf/RepeatedFieldBuilderV3;
      45: iload_1
      46: aload_2
      47: invokevirtual #165                // Method org/apache/hbase/thirdparty/com/google/protobuf/RepeatedFieldBuilderV3.addMessage:(ILorg/apache/hbase/thirdparty/com/google/protobuf/AbstractMessage;)Lorg/apache/hbase/thirdparty/com/google/protobuf/RepeatedFieldBuilderV3;
      50: pop
      51: aload_0
      52: areturn

  public org.apache.hadoop.hbase.shaded.protobuf.generated.MasterProcedureProtos$RestoreSnapshotStateData$Builder addRegionInfoForAdd(org.apache.hadoop.hbase.shaded.protobuf.generated.HBaseProtos$RegionInfo$Builder);
    Code:
       0: aload_0
       1: getfield      #36                 // Field regionInfoForAddBuilder_:Lorg/apache/hbase/thirdparty/com/google/protobuf/RepeatedFieldBuilderV3;
       4: ifnonnull     32
       7: aload_0
       8: invokespecial #88                 // Method ensureRegionInfoForAddIsMutable:()V
      11: aload_0
      12: getfield      #15                 // Field regionInfoForAdd_:Ljava/util/List;
      15: aload_1
      16: invokevirtual #161                // Method org/apache/hadoop/hbase/shaded/protobuf/generated/HBaseProtos$RegionInfo$Builder.build:()Lorg/apache/hadoop/hbase/shaded/protobuf/generated/HBaseProtos$RegionInfo;
      19: invokeinterface #162,  2          // InterfaceMethod java/util/List.add:(Ljava/lang/Object;)Z
      24: pop
      25: aload_0
      26: invokevirtual #79                 // Method onChanged:()V
      29: goto          44
      32: aload_0
      33: getfield      #36                 // Field regionInfoForAddBuilder_:Lorg/apache/hbase/thirdparty/com/google/protobuf/RepeatedFieldBuilderV3;
      36: aload_1
      37: invokevirtual #161                // Method org/apache/hadoop/hbase/shaded/protobuf/generated/HBaseProtos$RegionInfo$Builder.build:()Lorg/apache/hadoop/hbase/shaded/protobuf/generated/HBaseProtos$RegionInfo;
      40: invokevirtual #163                // Method org/apache/hbase/thirdparty/com/google/protobuf/RepeatedFieldBuilderV3.addMessage:(Lorg/apache/hbase/thirdparty/com/google/protobuf/AbstractMessage;)Lorg/apache/hbase/thirdparty/com/google/protobuf/RepeatedFieldBuilderV3;
      43: pop
      44: aload_0
      45: areturn

  public org.apache.hadoop.hbase.shaded.protobuf.generated.MasterProcedureProtos$RestoreSnapshotStateData$Builder addRegionInfoForAdd(int, org.apache.hadoop.hbase.shaded.protobuf.generated.HBaseProtos$RegionInfo$Builder);
    Code:
       0: aload_0
       1: getfield      #36                 // Field regionInfoForAddBuilder_:Lorg/apache/hbase/thirdparty/com/google/protobuf/RepeatedFieldBuilderV3;
       4: ifnonnull     32
       7: aload_0
       8: invokespecial #88                 // Method ensureRegionInfoForAddIsMutable:()V
      11: aload_0
      12: getfield      #15                 // Field regionInfoForAdd_:Ljava/util/List;
      15: iload_1
      16: aload_2
      17: invokevirtual #161                // Method org/apache/hadoop/hbase/shaded/protobuf/generated/HBaseProtos$RegionInfo$Builder.build:()Lorg/apache/hadoop/hbase/shaded/protobuf/generated/HBaseProtos$RegionInfo;
      20: invokeinterface #164,  3          // InterfaceMethod java/util/List.add:(ILjava/lang/Object;)V
      25: aload_0
      26: invokevirtual #79                 // Method onChanged:()V
      29: goto          45
      32: aload_0
      33: getfield      #36                 // Field regionInfoForAddBuilder_:Lorg/apache/hbase/thirdparty/com/google/protobuf/RepeatedFieldBuilderV3;
      36: iload_1
      37: aload_2
      38: invokevirtual #161                // Method org/apache/hadoop/hbase/shaded/protobuf/generated/HBaseProtos$RegionInfo$Builder.build:()Lorg/apache/hadoop/hbase/shaded/protobuf/generated/HBaseProtos$RegionInfo;
      41: invokevirtual #165                // Method org/apache/hbase/thirdparty/com/google/protobuf/RepeatedFieldBuilderV3.addMessage:(ILorg/apache/hbase/thirdparty/com/google/protobuf/AbstractMessage;)Lorg/apache/hbase/thirdparty/com/google/protobuf/RepeatedFieldBuilderV3;
      44: pop
      45: aload_0
      46: areturn

  public org.apache.hadoop.hbase.shaded.protobuf.generated.MasterProcedureProtos$RestoreSnapshotStateData$Builder addAllRegionInfoForAdd(java.lang.Iterable<? extends org.apache.hadoop.hbase.shaded.protobuf.generated.HBaseProtos$RegionInfo>);
    Code:
       0: aload_0
       1: getfield      #36                 // Field regionInfoForAddBuilder_:Lorg/apache/hbase/thirdparty/com/google/protobuf/RepeatedFieldBuilderV3;
       4: ifnonnull     26
       7: aload_0
       8: invokespecial #88                 // Method ensureRegionInfoForAddIsMutable:()V
      11: aload_1
      12: aload_0
      13: getfield      #15                 // Field regionInfoForAdd_:Ljava/util/List;
      16: invokestatic  #166                // Method org/apache/hbase/thirdparty/com/google/protobuf/AbstractMessageLite$Builder.addAll:(Ljava/lang/Iterable;Ljava/util/List;)V
      19: aload_0
      20: invokevirtual #79                 // Method onChanged:()V
      23: goto          35
      26: aload_0
      27: getfield      #36                 // Field regionInfoForAddBuilder_:Lorg/apache/hbase/thirdparty/com/google/protobuf/RepeatedFieldBuilderV3;
      30: aload_1
      31: invokevirtual #83                 // Method org/apache/hbase/thirdparty/com/google/protobuf/RepeatedFieldBuilderV3.addAllMessages:(Ljava/lang/Iterable;)Lorg/apache/hbase/thirdparty/com/google/protobuf/RepeatedFieldBuilderV3;
      34: pop
      35: aload_0
      36: areturn

  public org.apache.hadoop.hbase.shaded.protobuf.generated.MasterProcedureProtos$RestoreSnapshotStateData$Builder clearRegionInfoForAdd();
    Code:
       0: aload_0
       1: getfield      #36                 // Field regionInfoForAddBuilder_:Lorg/apache/hbase/thirdparty/com/google/protobuf/RepeatedFieldBuilderV3;
       4: ifnonnull     32
       7: aload_0
       8: invokestatic  #12                 // Method java/util/Collections.emptyList:()Ljava/util/List;
      11: putfield      #15                 // Field regionInfoForAdd_:Ljava/util/List;
      14: aload_0
      15: aload_0
      16: getfield      #30                 // Field bitField0_:I
      19: bipush        -33
      21: iand
      22: putfield      #30                 // Field bitField0_:I
      25: aload_0
      26: invokevirtual #79                 // Method onChanged:()V
      29: goto          39
      32: aload_0
      33: getfield      #36                 // Field regionInfoForAddBuilder_:Lorg/apache/hbase/thirdparty/com/google/protobuf/RepeatedFieldBuilderV3;
      36: invokevirtual #34                 // Method org/apache/hbase/thirdparty/com/google/protobuf/RepeatedFieldBuilderV3.clear:()V
      39: aload_0
      40: areturn

  public org.apache.hadoop.hbase.shaded.protobuf.generated.MasterProcedureProtos$RestoreSnapshotStateData$Builder removeRegionInfoForAdd(int);
    Code:
       0: aload_0
       1: getfield      #36                 // Field regionInfoForAddBuilder_:Lorg/apache/hbase/thirdparty/com/google/protobuf/RepeatedFieldBuilderV3;
       4: ifnonnull     29
       7: aload_0
       8: invokespecial #88                 // Method ensureRegionInfoForAddIsMutable:()V
      11: aload_0
      12: getfield      #15                 // Field regionInfoForAdd_:Ljava/util/List;
      15: iload_1
      16: invokeinterface #167,  2          // InterfaceMethod java/util/List.remove:(I)Ljava/lang/Object;
      21: pop
      22: aload_0
      23: invokevirtual #79                 // Method onChanged:()V
      26: goto          37
      29: aload_0
      30: getfield      #36                 // Field regionInfoForAddBuilder_:Lorg/apache/hbase/thirdparty/com/google/protobuf/RepeatedFieldBuilderV3;
      33: iload_1
      34: invokevirtual #168                // Method org/apache/hbase/thirdparty/com/google/protobuf/RepeatedFieldBuilderV3.remove:(I)V
      37: aload_0
      38: areturn

  public org.apache.hadoop.hbase.shaded.protobuf.generated.HBaseProtos$RegionInfo$Builder getRegionInfoForAddBuilder(int);
    Code:
       0: aload_0
       1: invokespecial #25                 // Method getRegionInfoForAddFieldBuilder:()Lorg/apache/hbase/thirdparty/com/google/protobuf/RepeatedFieldBuilderV3;
       4: iload_1
       5: invokevirtual #169                // Method org/apache/hbase/thirdparty/com/google/protobuf/RepeatedFieldBuilderV3.getBuilder:(I)Lorg/apache/hbase/thirdparty/com/google/protobuf/AbstractMessage$Builder;
       8: checkcast     #170                // class org/apache/hadoop/hbase/shaded/protobuf/generated/HBaseProtos$RegionInfo$Builder
      11: areturn

  public org.apache.hadoop.hbase.shaded.protobuf.generated.HBaseProtos$RegionInfoOrBuilder getRegionInfoForAddOrBuilder(int);
    Code:
       0: aload_0
       1: getfield      #36                 // Field regionInfoForAddBuilder_:Lorg/apache/hbase/thirdparty/com/google/protobuf/RepeatedFieldBuilderV3;
       4: ifnonnull     21
       7: aload_0
       8: getfield      #15                 // Field regionInfoForAdd_:Ljava/util/List;
      11: iload_1
      12: invokeinterface #156,  2          // InterfaceMethod java/util/List.get:(I)Ljava/lang/Object;
      17: checkcast     #171                // class org/apache/hadoop/hbase/shaded/protobuf/generated/HBaseProtos$RegionInfoOrBuilder
      20: areturn
      21: aload_0
      22: getfield      #36                 // Field regionInfoForAddBuilder_:Lorg/apache/hbase/thirdparty/com/google/protobuf/RepeatedFieldBuilderV3;
      25: iload_1
      26: invokevirtual #172                // Method org/apache/hbase/thirdparty/com/google/protobuf/RepeatedFieldBuilderV3.getMessageOrBuilder:(I)Lorg/apache/hbase/thirdparty/com/google/protobuf/MessageOrBuilder;
      29: checkcast     #171                // class org/apache/hadoop/hbase/shaded/protobuf/generated/HBaseProtos$RegionInfoOrBuilder
      32: areturn

  public java.util.List<? extends org.apache.hadoop.hbase.shaded.protobuf.generated.HBaseProtos$RegionInfoOrBuilder> getRegionInfoForAddOrBuilderList();
    Code:
       0: aload_0
       1: getfield      #36                 // Field regionInfoForAddBuilder_:Lorg/apache/hbase/thirdparty/com/google/protobuf/RepeatedFieldBuilderV3;
       4: ifnull        15
       7: aload_0
       8: getfield      #36                 // Field regionInfoForAddBuilder_:Lorg/apache/hbase/thirdparty/com/google/protobuf/RepeatedFieldBuilderV3;
      11: invokevirtual #173                // Method org/apache/hbase/thirdparty/com/google/protobuf/RepeatedFieldBuilderV3.getMessageOrBuilderList:()Ljava/util/List;
      14: areturn
      15: aload_0
      16: getfield      #15                 // Field regionInfoForAdd_:Ljava/util/List;
      19: invokestatic  #50                 // Method java/util/Collections.unmodifiableList:(Ljava/util/List;)Ljava/util/List;
      22: areturn

  public org.apache.hadoop.hbase.shaded.protobuf.generated.HBaseProtos$RegionInfo$Builder addRegionInfoForAddBuilder();
    Code:
       0: aload_0
       1: invokespecial #25                 // Method getRegionInfoForAddFieldBuilder:()Lorg/apache/hbase/thirdparty/com/google/protobuf/RepeatedFieldBuilderV3;
       4: invokestatic  #174                // Method org/apache/hadoop/hbase/shaded/protobuf/generated/HBaseProtos$RegionInfo.getDefaultInstance:()Lorg/apache/hadoop/hbase/shaded/protobuf/generated/HBaseProtos$RegionInfo;
       7: invokevirtual #175                // Method org/apache/hbase/thirdparty/com/google/protobuf/RepeatedFieldBuilderV3.addBuilder:(Lorg/apache/hbase/thirdparty/com/google/protobuf/AbstractMessage;)Lorg/apache/hbase/thirdparty/com/google/protobuf/AbstractMessage$Builder;
      10: checkcast     #170                // class org/apache/hadoop/hbase/shaded/protobuf/generated/HBaseProtos$RegionInfo$Builder
      13: areturn

  public org.apache.hadoop.hbase.shaded.protobuf.generated.HBaseProtos$RegionInfo$Builder addRegionInfoForAddBuilder(int);
    Code:
       0: aload_0
       1: invokespecial #25                 // Method getRegionInfoForAddFieldBuilder:()Lorg/apache/hbase/thirdparty/com/google/protobuf/RepeatedFieldBuilderV3;
       4: iload_1
       5: invokestatic  #174                // Method org/apache/hadoop/hbase/shaded/protobuf/generated/HBaseProtos$RegionInfo.getDefaultInstance:()Lorg/apache/hadoop/hbase/shaded/protobuf/generated/HBaseProtos$RegionInfo;
       8: invokevirtual #176                // Method org/apache/hbase/thirdparty/com/google/protobuf/RepeatedFieldBuilderV3.addBuilder:(ILorg/apache/hbase/thirdparty/com/google/protobuf/AbstractMessage;)Lorg/apache/hbase/thirdparty/com/google/protobuf/AbstractMessage$Builder;
      11: checkcast     #170                // class org/apache/hadoop/hbase/shaded/protobuf/generated/HBaseProtos$RegionInfo$Builder
      14: areturn

  public java.util.List<org.apache.hadoop.hbase.shaded.protobuf.generated.HBaseProtos$RegionInfo$Builder> getRegionInfoForAddBuilderList();
    Code:
       0: aload_0
       1: invokespecial #25                 // Method getRegionInfoForAddFieldBuilder:()Lorg/apache/hbase/thirdparty/com/google/protobuf/RepeatedFieldBuilderV3;
       4: invokevirtual #177                // Method org/apache/hbase/thirdparty/com/google/protobuf/RepeatedFieldBuilderV3.getBuilderList:()Ljava/util/List;
       7: areturn

  public java.util.List<org.apache.hadoop.hbase.shaded.protobuf.generated.MasterProcedureProtos$RestoreParentToChildRegionsPair> getParentToChildRegionsPairListList();
    Code:
       0: aload_0
       1: getfield      #37                 // Field parentToChildRegionsPairListBuilder_:Lorg/apache/hbase/thirdparty/com/google/protobuf/RepeatedFieldBuilderV3;
       4: ifnonnull     15
       7: aload_0
       8: getfield      #16                 // Field parentToChildRegionsPairList_:Ljava/util/List;
      11: invokestatic  #50                 // Method java/util/Collections.unmodifiableList:(Ljava/util/List;)Ljava/util/List;
      14: areturn
      15: aload_0
      16: getfield      #37                 // Field parentToChildRegionsPairListBuilder_:Lorg/apache/hbase/thirdparty/com/google/protobuf/RepeatedFieldBuilderV3;
      19: invokevirtual #153                // Method org/apache/hbase/thirdparty/com/google/protobuf/RepeatedFieldBuilderV3.getMessageList:()Ljava/util/List;
      22: areturn

  public int getParentToChildRegionsPairListCount();
    Code:
       0: aload_0
       1: getfield      #37                 // Field parentToChildRegionsPairListBuilder_:Lorg/apache/hbase/thirdparty/com/google/protobuf/RepeatedFieldBuilderV3;
       4: ifnonnull     17
       7: aload_0
       8: getfield      #16                 // Field parentToChildRegionsPairList_:Ljava/util/List;
      11: invokeinterface #154,  1          // InterfaceMethod java/util/List.size:()I
      16: ireturn
      17: aload_0
      18: getfield      #37                 // Field parentToChildRegionsPairListBuilder_:Lorg/apache/hbase/thirdparty/com/google/protobuf/RepeatedFieldBuilderV3;
      21: invokevirtual #155                // Method org/apache/hbase/thirdparty/com/google/protobuf/RepeatedFieldBuilderV3.getCount:()I
      24: ireturn

  public org.apache.hadoop.hbase.shaded.protobuf.generated.MasterProcedureProtos$RestoreParentToChildRegionsPair getParentToChildRegionsPairList(int);
    Code:
       0: aload_0
       1: getfield      #37                 // Field parentToChildRegionsPairListBuilder_:Lorg/apache/hbase/thirdparty/com/google/protobuf/RepeatedFieldBuilderV3;
       4: ifnonnull     21
       7: aload_0
       8: getfield      #16                 // Field parentToChildRegionsPairList_:Ljava/util/List;
      11: iload_1
      12: invokeinterface #156,  2          // InterfaceMethod java/util/List.get:(I)Ljava/lang/Object;
      17: checkcast     #180                // class org/apache/hadoop/hbase/shaded/protobuf/generated/MasterProcedureProtos$RestoreParentToChildRegionsPair
      20: areturn
      21: aload_0
      22: getfield      #37                 // Field parentToChildRegionsPairListBuilder_:Lorg/apache/hbase/thirdparty/com/google/protobuf/RepeatedFieldBuilderV3;
      25: iload_1
      26: invokevirtual #158                // Method org/apache/hbase/thirdparty/com/google/protobuf/RepeatedFieldBuilderV3.getMessage:(I)Lorg/apache/hbase/thirdparty/com/google/protobuf/AbstractMessage;
      29: checkcast     #180                // class org/apache/hadoop/hbase/shaded/protobuf/generated/MasterProcedureProtos$RestoreParentToChildRegionsPair
      32: areturn

  public org.apache.hadoop.hbase.shaded.protobuf.generated.MasterProcedureProtos$RestoreSnapshotStateData$Builder setParentToChildRegionsPairList(int, org.apache.hadoop.hbase.shaded.protobuf.generated.MasterProcedureProtos$RestoreParentToChildRegionsPair);
    Code:
       0: aload_0
       1: getfield      #37                 // Field parentToChildRegionsPairListBuilder_:Lorg/apache/hbase/thirdparty/com/google/protobuf/RepeatedFieldBuilderV3;
       4: ifnonnull     42
       7: aload_2
       8: ifnonnull     19
      11: new           #121                // class java/lang/NullPointerException
      14: dup
      15: invokespecial #122                // Method java/lang/NullPointerException."<init>":()V
      18: athrow
      19: aload_0
      20: invokespecial #91                 // Method ensureParentToChildRegionsPairListIsMutable:()V
      23: aload_0
      24: getfield      #16                 // Field parentToChildRegionsPairList_:Ljava/util/List;
      27: iload_1
      28: aload_2
      29: invokeinterface #159,  3          // InterfaceMethod java/util/List.set:(ILjava/lang/Object;)Ljava/lang/Object;
      34: pop
      35: aload_0
      36: invokevirtual #79                 // Method onChanged:()V
      39: goto          52
      42: aload_0
      43: getfield      #37                 // Field parentToChildRegionsPairListBuilder_:Lorg/apache/hbase/thirdparty/com/google/protobuf/RepeatedFieldBuilderV3;
      46: iload_1
      47: aload_2
      48: invokevirtual #160                // Method org/apache/hbase/thirdparty/com/google/protobuf/RepeatedFieldBuilderV3.setMessage:(ILorg/apache/hbase/thirdparty/com/google/protobuf/AbstractMessage;)Lorg/apache/hbase/thirdparty/com/google/protobuf/RepeatedFieldBuilderV3;
      51: pop
      52: aload_0
      53: areturn

  public org.apache.hadoop.hbase.shaded.protobuf.generated.MasterProcedureProtos$RestoreSnapshotStateData$Builder setParentToChildRegionsPairList(int, org.apache.hadoop.hbase.shaded.protobuf.generated.MasterProcedureProtos$RestoreParentToChildRegionsPair$Builder);
    Code:
       0: aload_0
       1: getfield      #37                 // Field parentToChildRegionsPairListBuilder_:Lorg/apache/hbase/thirdparty/com/google/protobuf/RepeatedFieldBuilderV3;
       4: ifnonnull     33
       7: aload_0
       8: invokespecial #91                 // Method ensureParentToChildRegionsPairListIsMutable:()V
      11: aload_0
      12: getfield      #16                 // Field parentToChildRegionsPairList_:Ljava/util/List;
      15: iload_1
      16: aload_2
      17: invokevirtual #181                // Method org/apache/hadoop/hbase/shaded/protobuf/generated/MasterProcedureProtos$RestoreParentToChildRegionsPair$Builder.build:()Lorg/apache/hadoop/hbase/shaded/protobuf/generated/MasterProcedureProtos$RestoreParentToChildRegionsPair;
      20: invokeinterface #159,  3          // InterfaceMethod java/util/List.set:(ILjava/lang/Object;)Ljava/lang/Object;
      25: pop
      26: aload_0
      27: invokevirtual #79                 // Method onChanged:()V
      30: goto          46
      33: aload_0
      34: getfield      #37                 // Field parentToChildRegionsPairListBuilder_:Lorg/apache/hbase/thirdparty/com/google/protobuf/RepeatedFieldBuilderV3;
      37: iload_1
      38: aload_2
      39: invokevirtual #181                // Method org/apache/hadoop/hbase/shaded/protobuf/generated/MasterProcedureProtos$RestoreParentToChildRegionsPair$Builder.build:()Lorg/apache/hadoop/hbase/shaded/protobuf/generated/MasterProcedureProtos$RestoreParentToChildRegionsPair;
      42: invokevirtual #160                // Method org/apache/hbase/thirdparty/com/google/protobuf/RepeatedFieldBuilderV3.setMessage:(ILorg/apache/hbase/thirdparty/com/google/protobuf/AbstractMessage;)Lorg/apache/hbase/thirdparty/com/google/protobuf/RepeatedFieldBuilderV3;
      45: pop
      46: aload_0
      47: areturn

  public org.apache.hadoop.hbase.shaded.protobuf.generated.MasterProcedureProtos$RestoreSnapshotStateData$Builder addParentToChildRegionsPairList(org.apache.hadoop.hbase.shaded.protobuf.generated.MasterProcedureProtos$RestoreParentToChildRegionsPair);
    Code:
       0: aload_0
       1: getfield      #37                 // Field parentToChildRegionsPairListBuilder_:Lorg/apache/hbase/thirdparty/com/google/protobuf/RepeatedFieldBuilderV3;
       4: ifnonnull     41
       7: aload_1
       8: ifnonnull     19
      11: new           #121                // class java/lang/NullPointerException
      14: dup
      15: invokespecial #122                // Method java/lang/NullPointerException."<init>":()V
      18: athrow
      19: aload_0
      20: invokespecial #91                 // Method ensureParentToChildRegionsPairListIsMutable:()V
      23: aload_0
      24: getfield      #16                 // Field parentToChildRegionsPairList_:Ljava/util/List;
      27: aload_1
      28: invokeinterface #162,  2          // InterfaceMethod java/util/List.add:(Ljava/lang/Object;)Z
      33: pop
      34: aload_0
      35: invokevirtual #79                 // Method onChanged:()V
      38: goto          50
      41: aload_0
      42: getfield      #37                 // Field parentToChildRegionsPairListBuilder_:Lorg/apache/hbase/thirdparty/com/google/protobuf/RepeatedFieldBuilderV3;
      45: aload_1
      46: invokevirtual #163                // Method org/apache/hbase/thirdparty/com/google/protobuf/RepeatedFieldBuilderV3.addMessage:(Lorg/apache/hbase/thirdparty/com/google/protobuf/AbstractMessage;)Lorg/apache/hbase/thirdparty/com/google/protobuf/RepeatedFieldBuilderV3;
      49: pop
      50: aload_0
      51: areturn

  public org.apache.hadoop.hbase.shaded.protobuf.generated.MasterProcedureProtos$RestoreSnapshotStateData$Builder addParentToChildRegionsPairList(int, org.apache.hadoop.hbase.shaded.protobuf.generated.MasterProcedureProtos$RestoreParentToChildRegionsPair);
    Code:
       0: aload_0
       1: getfield      #37                 // Field parentToChildRegionsPairListBuilder_:Lorg/apache/hbase/thirdparty/com/google/protobuf/RepeatedFieldBuilderV3;
       4: ifnonnull     41
       7: aload_2
       8: ifnonnull     19
      11: new           #121                // class java/lang/NullPointerException
      14: dup
      15: invokespecial #122                // Method java/lang/NullPointerException."<init>":()V
      18: athrow
      19: aload_0
      20: invokespecial #91                 // Method ensureParentToChildRegionsPairListIsMutable:()V
      23: aload_0
      24: getfield      #16                 // Field parentToChildRegionsPairList_:Ljava/util/List;
      27: iload_1
      28: aload_2
      29: invokeinterface #164,  3          // InterfaceMethod java/util/List.add:(ILjava/lang/Object;)V
      34: aload_0
      35: invokevirtual #79                 // Method onChanged:()V
      38: goto          51
      41: aload_0
      42: getfield      #37                 // Field parentToChildRegionsPairListBuilder_:Lorg/apache/hbase/thirdparty/com/google/protobuf/RepeatedFieldBuilderV3;
      45: iload_1
      46: aload_2
      47: invokevirtual #165                // Method org/apache/hbase/thirdparty/com/google/protobuf/RepeatedFieldBuilderV3.addMessage:(ILorg/apache/hbase/thirdparty/com/google/protobuf/AbstractMessage;)Lorg/apache/hbase/thirdparty/com/google/protobuf/RepeatedFieldBuilderV3;
      50: pop
      51: aload_0
      52: areturn

  public org.apache.hadoop.hbase.shaded.protobuf.generated.MasterProcedureProtos$RestoreSnapshotStateData$Builder addParentToChildRegionsPairList(org.apache.hadoop.hbase.shaded.protobuf.generated.MasterProcedureProtos$RestoreParentToChildRegionsPair$Builder);
    Code:
       0: aload_0
       1: getfield      #37                 // Field parentToChildRegionsPairListBuilder_:Lorg/apache/hbase/thirdparty/com/google/protobuf/RepeatedFieldBuilderV3;
       4: ifnonnull     32
       7: aload_0
       8: invokespecial #91                 // Method ensureParentToChildRegionsPairListIsMutable:()V
      11: aload_0
      12: getfield      #16                 // Field parentToChildRegionsPairList_:Ljava/util/List;
      15: aload_1
      16: invokevirtual #181                // Method org/apache/hadoop/hbase/shaded/protobuf/generated/MasterProcedureProtos$RestoreParentToChildRegionsPair$Builder.build:()Lorg/apache/hadoop/hbase/shaded/protobuf/generated/MasterProcedureProtos$RestoreParentToChildRegionsPair;
      19: invokeinterface #162,  2          // InterfaceMethod java/util/List.add:(Ljava/lang/Object;)Z
      24: pop
      25: aload_0
      26: invokevirtual #79                 // Method onChanged:()V
      29: goto          44
      32: aload_0
      33: getfield      #37                 // Field parentToChildRegionsPairListBuilder_:Lorg/apache/hbase/thirdparty/com/google/protobuf/RepeatedFieldBuilderV3;
      36: aload_1
      37: invokevirtual #181                // Method org/apache/hadoop/hbase/shaded/protobuf/generated/MasterProcedureProtos$RestoreParentToChildRegionsPair$Builder.build:()Lorg/apache/hadoop/hbase/shaded/protobuf/generated/MasterProcedureProtos$RestoreParentToChildRegionsPair;
      40: invokevirtual #163                // Method org/apache/hbase/thirdparty/com/google/protobuf/RepeatedFieldBuilderV3.addMessage:(Lorg/apache/hbase/thirdparty/com/google/protobuf/AbstractMessage;)Lorg/apache/hbase/thirdparty/com/google/protobuf/RepeatedFieldBuilderV3;
      43: pop
      44: aload_0
      45: areturn

  public org.apache.hadoop.hbase.shaded.protobuf.generated.MasterProcedureProtos$RestoreSnapshotStateData$Builder addParentToChildRegionsPairList(int, org.apache.hadoop.hbase.shaded.protobuf.generated.MasterProcedureProtos$RestoreParentToChildRegionsPair$Builder);
    Code:
       0: aload_0
       1: getfield      #37                 // Field parentToChildRegionsPairListBuilder_:Lorg/apache/hbase/thirdparty/com/google/protobuf/RepeatedFieldBuilderV3;
       4: ifnonnull     32
       7: aload_0
       8: invokespecial #91                 // Method ensureParentToChildRegionsPairListIsMutable:()V
      11: aload_0
      12: getfield      #16                 // Field parentToChildRegionsPairList_:Ljava/util/List;
      15: iload_1
      16: aload_2
      17: invokevirtual #181                // Method org/apache/hadoop/hbase/shaded/protobuf/generated/MasterProcedureProtos$RestoreParentToChildRegionsPair$Builder.build:()Lorg/apache/hadoop/hbase/shaded/protobuf/generated/MasterProcedureProtos$RestoreParentToChildRegionsPair;
      20: invokeinterface #164,  3          // InterfaceMethod java/util/List.add:(ILjava/lang/Object;)V
      25: aload_0
      26: invokevirtual #79                 // Method onChanged:()V
      29: goto          45
      32: aload_0
      33: getfield      #37                 // Field parentToChildRegionsPairListBuilder_:Lorg/apache/hbase/thirdparty/com/google/protobuf/RepeatedFieldBuilderV3;
      36: iload_1
      37: aload_2
      38: invokevirtual #181                // Method org/apache/hadoop/hbase/shaded/protobuf/generated/MasterProcedureProtos$RestoreParentToChildRegionsPair$Builder.build:()Lorg/apache/hadoop/hbase/shaded/protobuf/generated/MasterProcedureProtos$RestoreParentToChildRegionsPair;
      41: invokevirtual #165                // Method org/apache/hbase/thirdparty/com/google/protobuf/RepeatedFieldBuilderV3.addMessage:(ILorg/apache/hbase/thirdparty/com/google/protobuf/AbstractMessage;)Lorg/apache/hbase/thirdparty/com/google/protobuf/RepeatedFieldBuilderV3;
      44: pop
      45: aload_0
      46: areturn

  public org.apache.hadoop.hbase.shaded.protobuf.generated.MasterProcedureProtos$RestoreSnapshotStateData$Builder addAllParentToChildRegionsPairList(java.lang.Iterable<? extends org.apache.hadoop.hbase.shaded.protobuf.generated.MasterProcedureProtos$RestoreParentToChildRegionsPair>);
    Code:
       0: aload_0
       1: getfield      #37                 // Field parentToChildRegionsPairListBuilder_:Lorg/apache/hbase/thirdparty/com/google/protobuf/RepeatedFieldBuilderV3;
       4: ifnonnull     26
       7: aload_0
       8: invokespecial #91                 // Method ensureParentToChildRegionsPairListIsMutable:()V
      11: aload_1
      12: aload_0
      13: getfield      #16                 // Field parentToChildRegionsPairList_:Ljava/util/List;
      16: invokestatic  #166                // Method org/apache/hbase/thirdparty/com/google/protobuf/AbstractMessageLite$Builder.addAll:(Ljava/lang/Iterable;Ljava/util/List;)V
      19: aload_0
      20: invokevirtual #79                 // Method onChanged:()V
      23: goto          35
      26: aload_0
      27: getfield      #37                 // Field parentToChildRegionsPairListBuilder_:Lorg/apache/hbase/thirdparty/com/google/protobuf/RepeatedFieldBuilderV3;
      30: aload_1
      31: invokevirtual #83                 // Method org/apache/hbase/thirdparty/com/google/protobuf/RepeatedFieldBuilderV3.addAllMessages:(Ljava/lang/Iterable;)Lorg/apache/hbase/thirdparty/com/google/protobuf/RepeatedFieldBuilderV3;
      34: pop
      35: aload_0
      36: areturn

  public org.apache.hadoop.hbase.shaded.protobuf.generated.MasterProcedureProtos$RestoreSnapshotStateData$Builder clearParentToChildRegionsPairList();
    Code:
       0: aload_0
       1: getfield      #37                 // Field parentToChildRegionsPairListBuilder_:Lorg/apache/hbase/thirdparty/com/google/protobuf/RepeatedFieldBuilderV3;
       4: ifnonnull     32
       7: aload_0
       8: invokestatic  #12                 // Method java/util/Collections.emptyList:()Ljava/util/List;
      11: putfield      #16                 // Field parentToChildRegionsPairList_:Ljava/util/List;
      14: aload_0
      15: aload_0
      16: getfield      #30                 // Field bitField0_:I
      19: bipush        -65
      21: iand
      22: putfield      #30                 // Field bitField0_:I
      25: aload_0
      26: invokevirtual #79                 // Method onChanged:()V
      29: goto          39
      32: aload_0
      33: getfield      #37                 // Field parentToChildRegionsPairListBuilder_:Lorg/apache/hbase/thirdparty/com/google/protobuf/RepeatedFieldBuilderV3;
      36: invokevirtual #34                 // Method org/apache/hbase/thirdparty/com/google/protobuf/RepeatedFieldBuilderV3.clear:()V
      39: aload_0
      40: areturn

  public org.apache.hadoop.hbase.shaded.protobuf.generated.MasterProcedureProtos$RestoreSnapshotStateData$Builder removeParentToChildRegionsPairList(int);
    Code:
       0: aload_0
       1: getfield      #37                 // Field parentToChildRegionsPairListBuilder_:Lorg/apache/hbase/thirdparty/com/google/protobuf/RepeatedFieldBuilderV3;
       4: ifnonnull     29
       7: aload_0
       8: invokespecial #91                 // Method ensureParentToChildRegionsPairListIsMutable:()V
      11: aload_0
      12: getfield      #16                 // Field parentToChildRegionsPairList_:Ljava/util/List;
      15: iload_1
      16: invokeinterface #167,  2          // InterfaceMethod java/util/List.remove:(I)Ljava/lang/Object;
      21: pop
      22: aload_0
      23: invokevirtual #79                 // Method onChanged:()V
      26: goto          37
      29: aload_0
      30: getfield      #37                 // Field parentToChildRegionsPairListBuilder_:Lorg/apache/hbase/thirdparty/com/google/protobuf/RepeatedFieldBuilderV3;
      33: iload_1
      34: invokevirtual #168                // Method org/apache/hbase/thirdparty/com/google/protobuf/RepeatedFieldBuilderV3.remove:(I)V
      37: aload_0
      38: areturn

  public org.apache.hadoop.hbase.shaded.protobuf.generated.MasterProcedureProtos$RestoreParentToChildRegionsPair$Builder getParentToChildRegionsPairListBuilder(int);
    Code:
       0: aload_0
       1: invokespecial #26                 // Method getParentToChildRegionsPairListFieldBuilder:()Lorg/apache/hbase/thirdparty/com/google/protobuf/RepeatedFieldBuilderV3;
       4: iload_1
       5: invokevirtual #169                // Method org/apache/hbase/thirdparty/com/google/protobuf/RepeatedFieldBuilderV3.getBuilder:(I)Lorg/apache/hbase/thirdparty/com/google/protobuf/AbstractMessage$Builder;
       8: checkcast     #182                // class org/apache/hadoop/hbase/shaded/protobuf/generated/MasterProcedureProtos$RestoreParentToChildRegionsPair$Builder
      11: areturn

  public org.apache.hadoop.hbase.shaded.protobuf.generated.MasterProcedureProtos$RestoreParentToChildRegionsPairOrBuilder getParentToChildRegionsPairListOrBuilder(int);
    Code:
       0: aload_0
       1: getfield      #37                 // Field parentToChildRegionsPairListBuilder_:Lorg/apache/hbase/thirdparty/com/google/protobuf/RepeatedFieldBuilderV3;
       4: ifnonnull     21
       7: aload_0
       8: getfield      #16                 // Field parentToChildRegionsPairList_:Ljava/util/List;
      11: iload_1
      12: invokeinterface #156,  2          // InterfaceMethod java/util/List.get:(I)Ljava/lang/Object;
      17: checkcast     #183                // class org/apache/hadoop/hbase/shaded/protobuf/generated/MasterProcedureProtos$RestoreParentToChildRegionsPairOrBuilder
      20: areturn
      21: aload_0
      22: getfield      #37                 // Field parentToChildRegionsPairListBuilder_:Lorg/apache/hbase/thirdparty/com/google/protobuf/RepeatedFieldBuilderV3;
      25: iload_1
      26: invokevirtual #172                // Method org/apache/hbase/thirdparty/com/google/protobuf/RepeatedFieldBuilderV3.getMessageOrBuilder:(I)Lorg/apache/hbase/thirdparty/com/google/protobuf/MessageOrBuilder;
      29: checkcast     #183                // class org/apache/hadoop/hbase/shaded/protobuf/generated/MasterProcedureProtos$RestoreParentToChildRegionsPairOrBuilder
      32: areturn

  public java.util.List<? extends org.apache.hadoop.hbase.shaded.protobuf.generated.MasterProcedureProtos$RestoreParentToChildRegionsPairOrBuilder> getParentToChildRegionsPairListOrBuilderList();
    Code:
       0: aload_0
       1: getfield      #37                 // Field parentToChildRegionsPairListBuilder_:Lorg/apache/hbase/thirdparty/com/google/protobuf/RepeatedFieldBuilderV3;
       4: ifnull        15
       7: aload_0
       8: getfield      #37                 // Field parentToChildRegionsPairListBuilder_:Lorg/apache/hbase/thirdparty/com/google/protobuf/RepeatedFieldBuilderV3;
      11: invokevirtual #173                // Method org/apache/hbase/thirdparty/com/google/protobuf/RepeatedFieldBuilderV3.getMessageOrBuilderList:()Ljava/util/List;
      14: areturn
      15: aload_0
      16: getfield      #16                 // Field parentToChildRegionsPairList_:Ljava/util/List;
      19: invokestatic  #50                 // Method java/util/Collections.unmodifiableList:(Ljava/util/List;)Ljava/util/List;
      22: areturn

  public org.apache.hadoop.hbase.shaded.protobuf.generated.MasterProcedureProtos$RestoreParentToChildRegionsPair$Builder addParentToChildRegionsPairListBuilder();
    Code:
       0: aload_0
       1: invokespecial #26                 // Method getParentToChildRegionsPairListFieldBuilder:()Lorg/apache/hbase/thirdparty/com/google/protobuf/RepeatedFieldBuilderV3;
       4: invokestatic  #184                // Method org/apache/hadoop/hbase/shaded/protobuf/generated/MasterProcedureProtos$RestoreParentToChildRegionsPair.getDefaultInstance:()Lorg/apache/hadoop/hbase/shaded/protobuf/generated/MasterProcedureProtos$RestoreParentToChildRegionsPair;
       7: invokevirtual #175                // Method org/apache/hbase/thirdparty/com/google/protobuf/RepeatedFieldBuilderV3.addBuilder:(Lorg/apache/hbase/thirdparty/com/google/protobuf/AbstractMessage;)Lorg/apache/hbase/thirdparty/com/google/protobuf/AbstractMessage$Builder;
      10: checkcast     #182                // class org/apache/hadoop/hbase/shaded/protobuf/generated/MasterProcedureProtos$RestoreParentToChildRegionsPair$Builder
      13: areturn

  public org.apache.hadoop.hbase.shaded.protobuf.generated.MasterProcedureProtos$RestoreParentToChildRegionsPair$Builder addParentToChildRegionsPairListBuilder(int);
    Code:
       0: aload_0
       1: invokespecial #26                 // Method getParentToChildRegionsPairListFieldBuilder:()Lorg/apache/hbase/thirdparty/com/google/protobuf/RepeatedFieldBuilderV3;
       4: iload_1
       5: invokestatic  #184                // Method org/apache/hadoop/hbase/shaded/protobuf/generated/MasterProcedureProtos$RestoreParentToChildRegionsPair.getDefaultInstance:()Lorg/apache/hadoop/hbase/shaded/protobuf/generated/MasterProcedureProtos$RestoreParentToChildRegionsPair;
       8: invokevirtual #176                // Method org/apache/hbase/thirdparty/com/google/protobuf/RepeatedFieldBuilderV3.addBuilder:(ILorg/apache/hbase/thirdparty/com/google/protobuf/AbstractMessage;)Lorg/apache/hbase/thirdparty/com/google/protobuf/AbstractMessage$Builder;
      11: checkcast     #182                // class org/apache/hadoop/hbase/shaded/protobuf/generated/MasterProcedureProtos$RestoreParentToChildRegionsPair$Builder
      14: areturn

  public java.util.List<org.apache.hadoop.hbase.shaded.protobuf.generated.MasterProcedureProtos$RestoreParentToChildRegionsPair$Builder> getParentToChildRegionsPairListBuilderList();
    Code:
       0: aload_0
       1: invokespecial #26                 // Method getParentToChildRegionsPairListFieldBuilder:()Lorg/apache/hbase/thirdparty/com/google/protobuf/RepeatedFieldBuilderV3;
       4: invokevirtual #177                // Method org/apache/hbase/thirdparty/com/google/protobuf/RepeatedFieldBuilderV3.getBuilderList:()Ljava/util/List;
       7: areturn

  public final org.apache.hadoop.hbase.shaded.protobuf.generated.MasterProcedureProtos$RestoreSnapshotStateData$Builder setUnknownFields(org.apache.hbase.thirdparty.com.google.protobuf.UnknownFieldSet);
    Code:
       0: aload_0
       1: aload_1
       2: invokespecial #185                // Method org/apache/hbase/thirdparty/com/google/protobuf/GeneratedMessageV3$Builder.setUnknownFields:(Lorg/apache/hbase/thirdparty/com/google/protobuf/UnknownFieldSet;)Lorg/apache/hbase/thirdparty/com/google/protobuf/GeneratedMessageV3$Builder;
       5: checkcast     #6                  // class org/apache/hadoop/hbase/shaded/protobuf/generated/MasterProcedureProtos$RestoreSnapshotStateData$Builder
       8: areturn

  public final org.apache.hadoop.hbase.shaded.protobuf.generated.MasterProcedureProtos$RestoreSnapshotStateData$Builder mergeUnknownFields(org.apache.hbase.thirdparty.com.google.protobuf.UnknownFieldSet);
    Code:
       0: aload_0
       1: aload_1
       2: invokespecial #186                // Method org/apache/hbase/thirdparty/com/google/protobuf/GeneratedMessageV3$Builder.mergeUnknownFields:(Lorg/apache/hbase/thirdparty/com/google/protobuf/UnknownFieldSet;)Lorg/apache/hbase/thirdparty/com/google/protobuf/GeneratedMessageV3$Builder;
       5: checkcast     #6                  // class org/apache/hadoop/hbase/shaded/protobuf/generated/MasterProcedureProtos$RestoreSnapshotStateData$Builder
       8: areturn

  public org.apache.hbase.thirdparty.com.google.protobuf.GeneratedMessageV3$Builder mergeUnknownFields(org.apache.hbase.thirdparty.com.google.protobuf.UnknownFieldSet);
    Code:
       0: aload_0
       1: aload_1
       2: invokevirtual #94                 // Method mergeUnknownFields:(Lorg/apache/hbase/thirdparty/com/google/protobuf/UnknownFieldSet;)Lorg/apache/hadoop/hbase/shaded/protobuf/generated/MasterProcedureProtos$RestoreSnapshotStateData$Builder;
       5: areturn

  public org.apache.hbase.thirdparty.com.google.protobuf.GeneratedMessageV3$Builder setUnknownFields(org.apache.hbase.thirdparty.com.google.protobuf.UnknownFieldSet);
    Code:
       0: aload_0
       1: aload_1
       2: invokevirtual #187                // Method setUnknownFields:(Lorg/apache/hbase/thirdparty/com/google/protobuf/UnknownFieldSet;)Lorg/apache/hadoop/hbase/shaded/protobuf/generated/MasterProcedureProtos$RestoreSnapshotStateData$Builder;
       5: areturn

  public org.apache.hbase.thirdparty.com.google.protobuf.GeneratedMessageV3$Builder addRepeatedField(org.apache.hbase.thirdparty.com.google.protobuf.Descriptors$FieldDescriptor, java.lang.Object);
    Code:
       0: aload_0
       1: aload_1
       2: aload_2
       3: invokevirtual #188                // Method addRepeatedField:(Lorg/apache/hbase/thirdparty/com/google/protobuf/Descriptors$FieldDescriptor;Ljava/lang/Object;)Lorg/apache/hadoop/hbase/shaded/protobuf/generated/MasterProcedureProtos$RestoreSnapshotStateData$Builder;
       6: areturn

  public org.apache.hbase.thirdparty.com.google.protobuf.GeneratedMessageV3$Builder setRepeatedField(org.apache.hbase.thirdparty.com.google.protobuf.Descriptors$FieldDescriptor, int, java.lang.Object);
    Code:
       0: aload_0
       1: aload_1
       2: iload_2
       3: aload_3
       4: invokevirtual #189                // Method setRepeatedField:(Lorg/apache/hbase/thirdparty/com/google/protobuf/Descriptors$FieldDescriptor;ILjava/lang/Object;)Lorg/apache/hadoop/hbase/shaded/protobuf/generated/MasterProcedureProtos$RestoreSnapshotStateData$Builder;
       7: areturn

  public org.apache.hbase.thirdparty.com.google.protobuf.GeneratedMessageV3$Builder clearOneof(org.apache.hbase.thirdparty.com.google.protobuf.Descriptors$OneofDescriptor);
    Code:
       0: aload_0
       1: aload_1
       2: invokevirtual #190                // Method clearOneof:(Lorg/apache/hbase/thirdparty/com/google/protobuf/Descriptors$OneofDescriptor;)Lorg/apache/hadoop/hbase/shaded/protobuf/generated/MasterProcedureProtos$RestoreSnapshotStateData$Builder;
       5: areturn

  public org.apache.hbase.thirdparty.com.google.protobuf.GeneratedMessageV3$Builder clearField(org.apache.hbase.thirdparty.com.google.protobuf.Descriptors$FieldDescriptor);
    Code:
       0: aload_0
       1: aload_1
       2: invokevirtual #191                // Method clearField:(Lorg/apache/hbase/thirdparty/com/google/protobuf/Descriptors$FieldDescriptor;)Lorg/apache/hadoop/hbase/shaded/protobuf/generated/MasterProcedureProtos$RestoreSnapshotStateData$Builder;
       5: areturn

  public org.apache.hbase.thirdparty.com.google.protobuf.GeneratedMessageV3$Builder setField(org.apache.hbase.thirdparty.com.google.protobuf.Descriptors$FieldDescriptor, java.lang.Object);
    Code:
       0: aload_0
       1: aload_1
       2: aload_2
       3: invokevirtual #192                // Method setField:(Lorg/apache/hbase/thirdparty/com/google/protobuf/Descriptors$FieldDescriptor;Ljava/lang/Object;)Lorg/apache/hadoop/hbase/shaded/protobuf/generated/MasterProcedureProtos$RestoreSnapshotStateData$Builder;
       6: areturn

  public org.apache.hbase.thirdparty.com.google.protobuf.GeneratedMessageV3$Builder clear();
    Code:
       0: aload_0
       1: invokevirtual #193                // Method clear:()Lorg/apache/hadoop/hbase/shaded/protobuf/generated/MasterProcedureProtos$RestoreSnapshotStateData$Builder;
       4: areturn

  public org.apache.hbase.thirdparty.com.google.protobuf.GeneratedMessageV3$Builder clone();
    Code:
       0: aload_0
       1: invokevirtual #194                // Method clone:()Lorg/apache/hadoop/hbase/shaded/protobuf/generated/MasterProcedureProtos$RestoreSnapshotStateData$Builder;
       4: areturn

  public org.apache.hbase.thirdparty.com.google.protobuf.AbstractMessage$Builder mergeUnknownFields(org.apache.hbase.thirdparty.com.google.protobuf.UnknownFieldSet);
    Code:
       0: aload_0
       1: aload_1
       2: invokevirtual #94                 // Method mergeUnknownFields:(Lorg/apache/hbase/thirdparty/com/google/protobuf/UnknownFieldSet;)Lorg/apache/hadoop/hbase/shaded/protobuf/generated/MasterProcedureProtos$RestoreSnapshotStateData$Builder;
       5: areturn

  public org.apache.hbase.thirdparty.com.google.protobuf.AbstractMessage$Builder mergeFrom(org.apache.hbase.thirdparty.com.google.protobuf.CodedInputStream, org.apache.hbase.thirdparty.com.google.protobuf.ExtensionRegistryLite) throws java.io.IOException;
    Code:
       0: aload_0
       1: aload_1
       2: aload_2
       3: invokevirtual #195                // Method mergeFrom:(Lorg/apache/hbase/thirdparty/com/google/protobuf/CodedInputStream;Lorg/apache/hbase/thirdparty/com/google/protobuf/ExtensionRegistryLite;)Lorg/apache/hadoop/hbase/shaded/protobuf/generated/MasterProcedureProtos$RestoreSnapshotStateData$Builder;
       6: areturn

  public org.apache.hbase.thirdparty.com.google.protobuf.AbstractMessage$Builder mergeFrom(org.apache.hbase.thirdparty.com.google.protobuf.Message);
    Code:
       0: aload_0
       1: aload_1
       2: invokevirtual #196                // Method mergeFrom:(Lorg/apache/hbase/thirdparty/com/google/protobuf/Message;)Lorg/apache/hadoop/hbase/shaded/protobuf/generated/MasterProcedureProtos$RestoreSnapshotStateData$Builder;
       5: areturn

  public org.apache.hbase.thirdparty.com.google.protobuf.AbstractMessage$Builder clear();
    Code:
       0: aload_0
       1: invokevirtual #193                // Method clear:()Lorg/apache/hadoop/hbase/shaded/protobuf/generated/MasterProcedureProtos$RestoreSnapshotStateData$Builder;
       4: areturn

  public org.apache.hbase.thirdparty.com.google.protobuf.AbstractMessage$Builder clearOneof(org.apache.hbase.thirdparty.com.google.protobuf.Descriptors$OneofDescriptor);
    Code:
       0: aload_0
       1: aload_1
       2: invokevirtual #190                // Method clearOneof:(Lorg/apache/hbase/thirdparty/com/google/protobuf/Descriptors$OneofDescriptor;)Lorg/apache/hadoop/hbase/shaded/protobuf/generated/MasterProcedureProtos$RestoreSnapshotStateData$Builder;
       5: areturn

  public org.apache.hbase.thirdparty.com.google.protobuf.AbstractMessage$Builder clone();
    Code:
       0: aload_0
       1: invokevirtual #194                // Method clone:()Lorg/apache/hadoop/hbase/shaded/protobuf/generated/MasterProcedureProtos$RestoreSnapshotStateData$Builder;
       4: areturn

  public org.apache.hbase.thirdparty.com.google.protobuf.Message$Builder mergeUnknownFields(org.apache.hbase.thirdparty.com.google.protobuf.UnknownFieldSet);
    Code:
       0: aload_0
       1: aload_1
       2: invokevirtual #94                 // Method mergeUnknownFields:(Lorg/apache/hbase/thirdparty/com/google/protobuf/UnknownFieldSet;)Lorg/apache/hadoop/hbase/shaded/protobuf/generated/MasterProcedureProtos$RestoreSnapshotStateData$Builder;
       5: areturn

  public org.apache.hbase.thirdparty.com.google.protobuf.Message$Builder setUnknownFields(org.apache.hbase.thirdparty.com.google.protobuf.UnknownFieldSet);
    Code:
       0: aload_0
       1: aload_1
       2: invokevirtual #187                // Method setUnknownFields:(Lorg/apache/hbase/thirdparty/com/google/protobuf/UnknownFieldSet;)Lorg/apache/hadoop/hbase/shaded/protobuf/generated/MasterProcedureProtos$RestoreSnapshotStateData$Builder;
       5: areturn

  public org.apache.hbase.thirdparty.com.google.protobuf.Message$Builder addRepeatedField(org.apache.hbase.thirdparty.com.google.protobuf.Descriptors$FieldDescriptor, java.lang.Object);
    Code:
       0: aload_0
       1: aload_1
       2: aload_2
       3: invokevirtual #188                // Method addRepeatedField:(Lorg/apache/hbase/thirdparty/com/google/protobuf/Descriptors$FieldDescriptor;Ljava/lang/Object;)Lorg/apache/hadoop/hbase/shaded/protobuf/generated/MasterProcedureProtos$RestoreSnapshotStateData$Builder;
       6: areturn

  public org.apache.hbase.thirdparty.com.google.protobuf.Message$Builder setRepeatedField(org.apache.hbase.thirdparty.com.google.protobuf.Descriptors$FieldDescriptor, int, java.lang.Object);
    Code:
       0: aload_0
       1: aload_1
       2: iload_2
       3: aload_3
       4: invokevirtual #189                // Method setRepeatedField:(Lorg/apache/hbase/thirdparty/com/google/protobuf/Descriptors$FieldDescriptor;ILjava/lang/Object;)Lorg/apache/hadoop/hbase/shaded/protobuf/generated/MasterProcedureProtos$RestoreSnapshotStateData$Builder;
       7: areturn

  public org.apache.hbase.thirdparty.com.google.protobuf.Message$Builder clearOneof(org.apache.hbase.thirdparty.com.google.protobuf.Descriptors$OneofDescriptor);
    Code:
       0: aload_0
       1: aload_1
       2: invokevirtual #190                // Method clearOneof:(Lorg/apache/hbase/thirdparty/com/google/protobuf/Descriptors$OneofDescriptor;)Lorg/apache/hadoop/hbase/shaded/protobuf/generated/MasterProcedureProtos$RestoreSnapshotStateData$Builder;
       5: areturn

  public org.apache.hbase.thirdparty.com.google.protobuf.Message$Builder clearField(org.apache.hbase.thirdparty.com.google.protobuf.Descriptors$FieldDescriptor);
    Code:
       0: aload_0
       1: aload_1
       2: invokevirtual #191                // Method clearField:(Lorg/apache/hbase/thirdparty/com/google/protobuf/Descriptors$FieldDescriptor;)Lorg/apache/hadoop/hbase/shaded/protobuf/generated/MasterProcedureProtos$RestoreSnapshotStateData$Builder;
       5: areturn

  public org.apache.hbase.thirdparty.com.google.protobuf.Message$Builder setField(org.apache.hbase.thirdparty.com.google.protobuf.Descriptors$FieldDescriptor, java.lang.Object);
    Code:
       0: aload_0
       1: aload_1
       2: aload_2
       3: invokevirtual #192                // Method setField:(Lorg/apache/hbase/thirdparty/com/google/protobuf/Descriptors$FieldDescriptor;Ljava/lang/Object;)Lorg/apache/hadoop/hbase/shaded/protobuf/generated/MasterProcedureProtos$RestoreSnapshotStateData$Builder;
       6: areturn

  public org.apache.hbase.thirdparty.com.google.protobuf.Message$Builder mergeFrom(org.apache.hbase.thirdparty.com.google.protobuf.CodedInputStream, org.apache.hbase.thirdparty.com.google.protobuf.ExtensionRegistryLite) throws java.io.IOException;
    Code:
       0: aload_0
       1: aload_1
       2: aload_2
       3: invokevirtual #195                // Method mergeFrom:(Lorg/apache/hbase/thirdparty/com/google/protobuf/CodedInputStream;Lorg/apache/hbase/thirdparty/com/google/protobuf/ExtensionRegistryLite;)Lorg/apache/hadoop/hbase/shaded/protobuf/generated/MasterProcedureProtos$RestoreSnapshotStateData$Builder;
       6: areturn

  public org.apache.hbase.thirdparty.com.google.protobuf.Message$Builder clone();
    Code:
       0: aload_0
       1: invokevirtual #194                // Method clone:()Lorg/apache/hadoop/hbase/shaded/protobuf/generated/MasterProcedureProtos$RestoreSnapshotStateData$Builder;
       4: areturn

  public org.apache.hbase.thirdparty.com.google.protobuf.Message buildPartial();
    Code:
       0: aload_0
       1: invokevirtual #39                 // Method buildPartial:()Lorg/apache/hadoop/hbase/shaded/protobuf/generated/MasterProcedureProtos$RestoreSnapshotStateData;
       4: areturn

  public org.apache.hbase.thirdparty.com.google.protobuf.Message build();
    Code:
       0: aload_0
       1: invokevirtual #197                // Method build:()Lorg/apache/hadoop/hbase/shaded/protobuf/generated/MasterProcedureProtos$RestoreSnapshotStateData;
       4: areturn

  public org.apache.hbase.thirdparty.com.google.protobuf.Message$Builder mergeFrom(org.apache.hbase.thirdparty.com.google.protobuf.Message);
    Code:
       0: aload_0
       1: aload_1
       2: invokevirtual #196                // Method mergeFrom:(Lorg/apache/hbase/thirdparty/com/google/protobuf/Message;)Lorg/apache/hadoop/hbase/shaded/protobuf/generated/MasterProcedureProtos$RestoreSnapshotStateData$Builder;
       5: areturn

  public org.apache.hbase.thirdparty.com.google.protobuf.Message$Builder clear();
    Code:
       0: aload_0
       1: invokevirtual #193                // Method clear:()Lorg/apache/hadoop/hbase/shaded/protobuf/generated/MasterProcedureProtos$RestoreSnapshotStateData$Builder;
       4: areturn

  public org.apache.hbase.thirdparty.com.google.protobuf.MessageLite$Builder mergeFrom(org.apache.hbase.thirdparty.com.google.protobuf.CodedInputStream, org.apache.hbase.thirdparty.com.google.protobuf.ExtensionRegistryLite) throws java.io.IOException;
    Code:
       0: aload_0
       1: aload_1
       2: aload_2
       3: invokevirtual #195                // Method mergeFrom:(Lorg/apache/hbase/thirdparty/com/google/protobuf/CodedInputStream;Lorg/apache/hbase/thirdparty/com/google/protobuf/ExtensionRegistryLite;)Lorg/apache/hadoop/hbase/shaded/protobuf/generated/MasterProcedureProtos$RestoreSnapshotStateData$Builder;
       6: areturn

  public org.apache.hbase.thirdparty.com.google.protobuf.MessageLite$Builder clone();
    Code:
       0: aload_0
       1: invokevirtual #194                // Method clone:()Lorg/apache/hadoop/hbase/shaded/protobuf/generated/MasterProcedureProtos$RestoreSnapshotStateData$Builder;
       4: areturn

  public org.apache.hbase.thirdparty.com.google.protobuf.MessageLite buildPartial();
    Code:
       0: aload_0
       1: invokevirtual #39                 // Method buildPartial:()Lorg/apache/hadoop/hbase/shaded/protobuf/generated/MasterProcedureProtos$RestoreSnapshotStateData;
       4: areturn

  public org.apache.hbase.thirdparty.com.google.protobuf.MessageLite build();
    Code:
       0: aload_0
       1: invokevirtual #197                // Method build:()Lorg/apache/hadoop/hbase/shaded/protobuf/generated/MasterProcedureProtos$RestoreSnapshotStateData;
       4: areturn

  public org.apache.hbase.thirdparty.com.google.protobuf.MessageLite$Builder clear();
    Code:
       0: aload_0
       1: invokevirtual #193                // Method clear:()Lorg/apache/hadoop/hbase/shaded/protobuf/generated/MasterProcedureProtos$RestoreSnapshotStateData$Builder;
       4: areturn

  public org.apache.hbase.thirdparty.com.google.protobuf.MessageLite getDefaultInstanceForType();
    Code:
       0: aload_0
       1: invokevirtual #198                // Method getDefaultInstanceForType:()Lorg/apache/hadoop/hbase/shaded/protobuf/generated/MasterProcedureProtos$RestoreSnapshotStateData;
       4: areturn

  public org.apache.hbase.thirdparty.com.google.protobuf.Message getDefaultInstanceForType();
    Code:
       0: aload_0
       1: invokevirtual #198                // Method getDefaultInstanceForType:()Lorg/apache/hadoop/hbase/shaded/protobuf/generated/MasterProcedureProtos$RestoreSnapshotStateData;
       4: areturn

  public org.apache.hbase.thirdparty.com.google.protobuf.AbstractMessageLite$Builder mergeFrom(org.apache.hbase.thirdparty.com.google.protobuf.CodedInputStream, org.apache.hbase.thirdparty.com.google.protobuf.ExtensionRegistryLite) throws java.io.IOException;
    Code:
       0: aload_0
       1: aload_1
       2: aload_2
       3: invokevirtual #195                // Method mergeFrom:(Lorg/apache/hbase/thirdparty/com/google/protobuf/CodedInputStream;Lorg/apache/hbase/thirdparty/com/google/protobuf/ExtensionRegistryLite;)Lorg/apache/hadoop/hbase/shaded/protobuf/generated/MasterProcedureProtos$RestoreSnapshotStateData$Builder;
       6: areturn

  public org.apache.hbase.thirdparty.com.google.protobuf.AbstractMessageLite$Builder clone();
    Code:
       0: aload_0
       1: invokevirtual #194                // Method clone:()Lorg/apache/hadoop/hbase/shaded/protobuf/generated/MasterProcedureProtos$RestoreSnapshotStateData$Builder;
       4: areturn

  public java.lang.Object clone() throws java.lang.CloneNotSupportedException;
    Code:
       0: aload_0
       1: invokevirtual #194                // Method clone:()Lorg/apache/hadoop/hbase/shaded/protobuf/generated/MasterProcedureProtos$RestoreSnapshotStateData$Builder;
       4: areturn

  org.apache.hadoop.hbase.shaded.protobuf.generated.MasterProcedureProtos$RestoreSnapshotStateData$Builder(org.apache.hadoop.hbase.shaded.protobuf.generated.MasterProcedureProtos$1);
    Code:
       0: aload_0
       1: invokespecial #2                  // Method "<init>":()V
       4: return

  org.apache.hadoop.hbase.shaded.protobuf.generated.MasterProcedureProtos$RestoreSnapshotStateData$Builder(org.apache.hbase.thirdparty.com.google.protobuf.GeneratedMessageV3$BuilderParent, org.apache.hadoop.hbase.shaded.protobuf.generated.MasterProcedureProtos$1);
    Code:
       0: aload_0
       1: aload_1
       2: invokespecial #1                  // Method "<init>":(Lorg/apache/hbase/thirdparty/com/google/protobuf/GeneratedMessageV3$BuilderParent;)V
       5: return
}
