Compiled from "MasterWalManager.java"
public class org.apache.hadoop.hbase.master.MasterWalManager {
  static final org.apache.hadoop.fs.PathFilter META_FILTER;

  public static final org.apache.hadoop.fs.PathFilter NON_META_FILTER;

  public org.apache.hadoop.hbase.master.MasterWalManager(org.apache.hadoop.hbase.master.MasterServices) throws java.io.IOException;
    Code:
       0: aload_0
       1: aload_1
       2: invokeinterface #1,  1            // InterfaceMethod org/apache/hadoop/hbase/master/MasterServices.getConfiguration:()Lorg/apache/hadoop/conf/Configuration;
       7: aload_1
       8: invokeinterface #2,  1            // InterfaceMethod org/apache/hadoop/hbase/master/MasterServices.getMasterFileSystem:()Lorg/apache/hadoop/hbase/master/MasterFileSystem;
      13: invokevirtual #3                  // Method org/apache/hadoop/hbase/master/MasterFileSystem.getWALFileSystem:()Lorg/apache/hadoop/fs/FileSystem;
      16: aload_1
      17: invokeinterface #2,  1            // InterfaceMethod org/apache/hadoop/hbase/master/MasterServices.getMasterFileSystem:()Lorg/apache/hadoop/hbase/master/MasterFileSystem;
      22: invokevirtual #4                  // Method org/apache/hadoop/hbase/master/MasterFileSystem.getWALRootDir:()Lorg/apache/hadoop/fs/Path;
      25: aload_1
      26: invokespecial #5                  // Method "<init>":(Lorg/apache/hadoop/conf/Configuration;Lorg/apache/hadoop/fs/FileSystem;Lorg/apache/hadoop/fs/Path;Lorg/apache/hadoop/hbase/master/MasterServices;)V
      29: return

  public org.apache.hadoop.hbase.master.MasterWalManager(org.apache.hadoop.conf.Configuration, org.apache.hadoop.fs.FileSystem, org.apache.hadoop.fs.Path, org.apache.hadoop.hbase.master.MasterServices) throws java.io.IOException;
    Code:
       0: aload_0
       1: invokespecial #6                  // Method java/lang/Object."<init>":()V
       4: aload_0
       5: new           #7                  // class org/apache/hadoop/hbase/master/MetricsMasterFileSystem
       8: dup
       9: invokespecial #8                  // Method org/apache/hadoop/hbase/master/MetricsMasterFileSystem."<init>":()V
      12: putfield      #9                  // Field metricsMasterFilesystem:Lorg/apache/hadoop/hbase/master/MetricsMasterFileSystem;
      15: aload_0
      16: new           #10                 // class java/util/concurrent/locks/ReentrantLock
      19: dup
      20: invokespecial #11                 // Method java/util/concurrent/locks/ReentrantLock."<init>":()V
      23: putfield      #12                 // Field splitLogLock:Ljava/util/concurrent/locks/Lock;
      26: aload_0
      27: iconst_1
      28: putfield      #13                 // Field fsOk:Z
      31: aload_0
      32: aload_2
      33: putfield      #14                 // Field fs:Lorg/apache/hadoop/fs/FileSystem;
      36: aload_0
      37: aload_1
      38: putfield      #15                 // Field conf:Lorg/apache/hadoop/conf/Configuration;
      41: aload_0
      42: aload_3
      43: putfield      #16                 // Field rootDir:Lorg/apache/hadoop/fs/Path;
      46: aload_0
      47: aload         4
      49: putfield      #17                 // Field services:Lorg/apache/hadoop/hbase/master/MasterServices;
      52: aload_0
      53: new           #18                 // class org/apache/hadoop/hbase/master/SplitLogManager
      56: dup
      57: aload         4
      59: aload_1
      60: invokespecial #19                 // Method org/apache/hadoop/hbase/master/SplitLogManager."<init>":(Lorg/apache/hadoop/hbase/master/MasterServices;Lorg/apache/hadoop/conf/Configuration;)V
      63: putfield      #20                 // Field splitLogManager:Lorg/apache/hadoop/hbase/master/SplitLogManager;
      66: aload_0
      67: new           #21                 // class org/apache/hadoop/fs/Path
      70: dup
      71: aload_3
      72: ldc           #23                 // String oldWALs
      74: invokespecial #24                 // Method org/apache/hadoop/fs/Path."<init>":(Lorg/apache/hadoop/fs/Path;Ljava/lang/String;)V
      77: putfield      #25                 // Field oldLogDir:Lorg/apache/hadoop/fs/Path;
      80: return

  public void stop();
    Code:
       0: aload_0
       1: getfield      #20                 // Field splitLogManager:Lorg/apache/hadoop/hbase/master/SplitLogManager;
       4: ifnull        14
       7: aload_0
       8: getfield      #20                 // Field splitLogManager:Lorg/apache/hadoop/hbase/master/SplitLogManager;
      11: invokevirtual #26                 // Method org/apache/hadoop/hbase/master/SplitLogManager.stop:()V
      14: return

  org.apache.hadoop.hbase.master.SplitLogManager getSplitLogManager();
    Code:
       0: aload_0
       1: getfield      #20                 // Field splitLogManager:Lorg/apache/hadoop/hbase/master/SplitLogManager;
       4: areturn

  org.apache.hadoop.fs.Path getOldLogDir();
    Code:
       0: aload_0
       1: getfield      #25                 // Field oldLogDir:Lorg/apache/hadoop/fs/Path;
       4: areturn

  public org.apache.hadoop.fs.FileSystem getFileSystem();
    Code:
       0: aload_0
       1: getfield      #14                 // Field fs:Lorg/apache/hadoop/fs/FileSystem;
       4: areturn

  public java.util.Set<org.apache.hadoop.hbase.ServerName> getSplittingServersFromWALDir() throws java.io.IOException;
    Code:
       0: aload_0
       1: invokedynamic #32,  0             // InvokeDynamic #0:accept:()Lorg/apache/hadoop/fs/PathFilter;
       6: invokevirtual #33                 // Method getServerNamesFromWALDirPath:(Lorg/apache/hadoop/fs/PathFilter;)Ljava/util/Set;
       9: areturn

  public java.util.Set<org.apache.hadoop.hbase.ServerName> getLiveServersFromWALDir() throws java.io.IOException;
    Code:
       0: aload_0
       1: invokedynamic #34,  0             // InvokeDynamic #1:accept:()Lorg/apache/hadoop/fs/PathFilter;
       6: invokevirtual #33                 // Method getServerNamesFromWALDirPath:(Lorg/apache/hadoop/fs/PathFilter;)Ljava/util/Set;
       9: areturn

  public java.util.Set<org.apache.hadoop.hbase.ServerName> getServerNamesFromWALDirPath(org.apache.hadoop.fs.PathFilter) throws java.io.IOException;
    Code:
       0: aload_0
       1: aload_1
       2: invokevirtual #35                 // Method getWALDirPaths:(Lorg/apache/hadoop/fs/PathFilter;)[Lorg/apache/hadoop/fs/FileStatus;
       5: astore_2
       6: aload_2
       7: invokestatic  #36                 // InterfaceMethod java/util/stream/Stream.of:([Ljava/lang/Object;)Ljava/util/stream/Stream;
      10: invokedynamic #37,  0             // InvokeDynamic #2:apply:()Ljava/util/function/Function;
      15: invokeinterface #38,  2           // InterfaceMethod java/util/stream/Stream.map:(Ljava/util/function/Function;)Ljava/util/stream/Stream;
      20: invokedynamic #39,  0             // InvokeDynamic #3:test:()Ljava/util/function/Predicate;
      25: invokeinterface #40,  2           // InterfaceMethod java/util/stream/Stream.filter:(Ljava/util/function/Predicate;)Ljava/util/stream/Stream;
      30: invokestatic  #41                 // Method java/util/stream/Collectors.toSet:()Ljava/util/stream/Collector;
      33: invokeinterface #42,  2           // InterfaceMethod java/util/stream/Stream.collect:(Ljava/util/stream/Collector;)Ljava/lang/Object;
      38: checkcast     #43                 // class java/util/Set
      41: areturn

  public org.apache.hadoop.fs.FileStatus[] getWALDirPaths(org.apache.hadoop.fs.PathFilter) throws java.io.IOException;
    Code:
       0: new           #21                 // class org/apache/hadoop/fs/Path
       3: dup
       4: aload_0
       5: getfield      #15                 // Field conf:Lorg/apache/hadoop/conf/Configuration;
       8: invokestatic  #44                 // Method org/apache/hadoop/hbase/util/CommonFSUtils.getWALRootDir:(Lorg/apache/hadoop/conf/Configuration;)Lorg/apache/hadoop/fs/Path;
      11: ldc           #45                 // String WALs
      13: invokespecial #24                 // Method org/apache/hadoop/fs/Path."<init>":(Lorg/apache/hadoop/fs/Path;Ljava/lang/String;)V
      16: astore_2
      17: aload_0
      18: getfield      #14                 // Field fs:Lorg/apache/hadoop/fs/FileSystem;
      21: aload_2
      22: aload_1
      23: invokestatic  #46                 // Method org/apache/hadoop/hbase/util/FSUtils.listStatus:(Lorg/apache/hadoop/fs/FileSystem;Lorg/apache/hadoop/fs/Path;Lorg/apache/hadoop/fs/PathFilter;)[Lorg/apache/hadoop/fs/FileStatus;
      26: astore_3
      27: aload_3
      28: ifnonnull     38
      31: iconst_0
      32: anewarray     #47                 // class org/apache/hadoop/fs/FileStatus
      35: goto          39
      38: aload_3
      39: areturn

  public java.util.Set<org.apache.hadoop.hbase.ServerName> getFailedServersFromLogFolders() throws java.io.IOException;
    Code:
       0: aload_0
       1: getfield      #15                 // Field conf:Lorg/apache/hadoop/conf/Configuration;
       4: ldc           #48                 // String hbase.hlog.split.skip.errors
       6: iconst_0
       7: invokevirtual #50                 // Method org/apache/hadoop/conf/Configuration.getBoolean:(Ljava/lang/String;Z)Z
      10: ifne          17
      13: iconst_1
      14: goto          18
      17: iconst_0
      18: istore_1
      19: new           #51                 // class java/util/HashSet
      22: dup
      23: invokespecial #52                 // Method java/util/HashSet."<init>":()V
      26: astore_2
      27: new           #21                 // class org/apache/hadoop/fs/Path
      30: dup
      31: aload_0
      32: getfield      #15                 // Field conf:Lorg/apache/hadoop/conf/Configuration;
      35: invokestatic  #44                 // Method org/apache/hadoop/hbase/util/CommonFSUtils.getWALRootDir:(Lorg/apache/hadoop/conf/Configuration;)Lorg/apache/hadoop/fs/Path;
      38: ldc           #45                 // String WALs
      40: invokespecial #24                 // Method org/apache/hadoop/fs/Path."<init>":(Lorg/apache/hadoop/fs/Path;Ljava/lang/String;)V
      43: astore_3
      44: aload_0
      45: getfield      #17                 // Field services:Lorg/apache/hadoop/hbase/master/MasterServices;
      48: invokeinterface #53,  1           // InterfaceMethod org/apache/hadoop/hbase/master/MasterServices.isStopped:()Z
      53: ifeq          69
      56: getstatic     #54                 // Field LOG:Lorg/slf4j/Logger;
      59: ldc           #55                 // String Master stopped while trying to get failed servers.
      61: invokeinterface #56,  2           // InterfaceMethod org/slf4j/Logger.warn:(Ljava/lang/String;)V
      66: goto          444
      69: aload_0
      70: getfield      #14                 // Field fs:Lorg/apache/hadoop/fs/FileSystem;
      73: aload_3
      74: invokevirtual #57                 // Method org/apache/hadoop/fs/FileSystem.exists:(Lorg/apache/hadoop/fs/Path;)Z
      77: ifne          82
      80: aload_2
      81: areturn
      82: aload_0
      83: getfield      #14                 // Field fs:Lorg/apache/hadoop/fs/FileSystem;
      86: aload_3
      87: aconst_null
      88: invokestatic  #46                 // Method org/apache/hadoop/hbase/util/FSUtils.listStatus:(Lorg/apache/hadoop/fs/FileSystem;Lorg/apache/hadoop/fs/Path;Lorg/apache/hadoop/fs/PathFilter;)[Lorg/apache/hadoop/fs/FileStatus;
      91: astore        4
      93: aload_0
      94: getfield      #17                 // Field services:Lorg/apache/hadoop/hbase/master/MasterServices;
      97: invokeinterface #58,  1           // InterfaceMethod org/apache/hadoop/hbase/master/MasterServices.getServerManager:()Lorg/apache/hadoop/hbase/master/ServerManager;
     102: invokevirtual #59                 // Method org/apache/hadoop/hbase/master/ServerManager.getOnlineServers:()Ljava/util/Map;
     105: invokeinterface #60,  1           // InterfaceMethod java/util/Map.keySet:()Ljava/util/Set;
     110: astore        5
     112: aload         4
     114: ifnull        123
     117: aload         4
     119: arraylength
     120: ifne          135
     123: getstatic     #54                 // Field LOG:Lorg/slf4j/Logger;
     126: ldc           #61                 // String No log files to split, proceeding...
     128: invokeinterface #62,  2           // InterfaceMethod org/slf4j/Logger.debug:(Ljava/lang/String;)V
     133: aload_2
     134: areturn
     135: aload         4
     137: astore        6
     139: aload         6
     141: arraylength
     142: istore        7
     144: iconst_0
     145: istore        8
     147: iload         8
     149: iload         7
     151: if_icmpge     347
     154: aload         6
     156: iload         8
     158: aaload
     159: astore        9
     161: aload_0
     162: getfield      #14                 // Field fs:Lorg/apache/hadoop/fs/FileSystem;
     165: aload         9
     167: invokevirtual #63                 // Method org/apache/hadoop/fs/FileStatus.getPath:()Lorg/apache/hadoop/fs/Path;
     170: aconst_null
     171: invokestatic  #46                 // Method org/apache/hadoop/hbase/util/FSUtils.listStatus:(Lorg/apache/hadoop/fs/FileSystem;Lorg/apache/hadoop/fs/Path;Lorg/apache/hadoop/fs/PathFilter;)[Lorg/apache/hadoop/fs/FileStatus;
     174: astore        10
     176: aload         10
     178: ifnull        341
     181: aload         10
     183: arraylength
     184: ifne          190
     187: goto          341
     190: aload         9
     192: invokevirtual #63                 // Method org/apache/hadoop/fs/FileStatus.getPath:()Lorg/apache/hadoop/fs/Path;
     195: invokestatic  #64                 // Method org/apache/hadoop/hbase/wal/AbstractFSWALProvider.getServerNameFromWALDirectoryName:(Lorg/apache/hadoop/fs/Path;)Lorg/apache/hadoop/hbase/ServerName;
     198: astore        11
     200: aconst_null
     201: aload         11
     203: if_acmpne     245
     206: getstatic     #54                 // Field LOG:Lorg/slf4j/Logger;
     209: new           #65                 // class java/lang/StringBuilder
     212: dup
     213: invokespecial #66                 // Method java/lang/StringBuilder."<init>":()V
     216: ldc           #67                 // String Log folder
     218: invokevirtual #68                 // Method java/lang/StringBuilder.append:(Ljava/lang/String;)Ljava/lang/StringBuilder;
     221: aload         9
     223: invokevirtual #63                 // Method org/apache/hadoop/fs/FileStatus.getPath:()Lorg/apache/hadoop/fs/Path;
     226: invokevirtual #69                 // Method java/lang/StringBuilder.append:(Ljava/lang/Object;)Ljava/lang/StringBuilder;
     229: ldc           #70                 // String  doesn't look like its name includes a region server name; leaving in place. If you see later errors about missing write ahead logs they may be saved in this location.
     231: invokevirtual #68                 // Method java/lang/StringBuilder.append:(Ljava/lang/String;)Ljava/lang/StringBuilder;
     234: invokevirtual #71                 // Method java/lang/StringBuilder.toString:()Ljava/lang/String;
     237: invokeinterface #56,  2           // InterfaceMethod org/slf4j/Logger.warn:(Ljava/lang/String;)V
     242: goto          341
     245: aload         5
     247: aload         11
     249: invokeinterface #72,  2           // InterfaceMethod java/util/Set.contains:(Ljava/lang/Object;)Z
     254: ifne          305
     257: getstatic     #54                 // Field LOG:Lorg/slf4j/Logger;
     260: new           #65                 // class java/lang/StringBuilder
     263: dup
     264: invokespecial #66                 // Method java/lang/StringBuilder."<init>":()V
     267: ldc           #67                 // String Log folder
     269: invokevirtual #68                 // Method java/lang/StringBuilder.append:(Ljava/lang/String;)Ljava/lang/StringBuilder;
     272: aload         9
     274: invokevirtual #63                 // Method org/apache/hadoop/fs/FileStatus.getPath:()Lorg/apache/hadoop/fs/Path;
     277: invokevirtual #69                 // Method java/lang/StringBuilder.append:(Ljava/lang/Object;)Ljava/lang/StringBuilder;
     280: ldc           #73                 // String  doesn't belong to a known region server, splitting
     282: invokevirtual #68                 // Method java/lang/StringBuilder.append:(Ljava/lang/String;)Ljava/lang/StringBuilder;
     285: invokevirtual #71                 // Method java/lang/StringBuilder.toString:()Ljava/lang/String;
     288: invokeinterface #74,  2           // InterfaceMethod org/slf4j/Logger.info:(Ljava/lang/String;)V
     293: aload_2
     294: aload         11
     296: invokeinterface #75,  2           // InterfaceMethod java/util/Set.add:(Ljava/lang/Object;)Z
     301: pop
     302: goto          341
     305: getstatic     #54                 // Field LOG:Lorg/slf4j/Logger;
     308: new           #65                 // class java/lang/StringBuilder
     311: dup
     312: invokespecial #66                 // Method java/lang/StringBuilder."<init>":()V
     315: ldc           #67                 // String Log folder
     317: invokevirtual #68                 // Method java/lang/StringBuilder.append:(Ljava/lang/String;)Ljava/lang/StringBuilder;
     320: aload         9
     322: invokevirtual #63                 // Method org/apache/hadoop/fs/FileStatus.getPath:()Lorg/apache/hadoop/fs/Path;
     325: invokevirtual #69                 // Method java/lang/StringBuilder.append:(Ljava/lang/Object;)Ljava/lang/StringBuilder;
     328: ldc           #76                 // String  belongs to an existing region server
     330: invokevirtual #68                 // Method java/lang/StringBuilder.append:(Ljava/lang/String;)Ljava/lang/StringBuilder;
     333: invokevirtual #71                 // Method java/lang/StringBuilder.toString:()Ljava/lang/String;
     336: invokeinterface #74,  2           // InterfaceMethod org/slf4j/Logger.info:(Ljava/lang/String;)V
     341: iinc          8, 1
     344: goto          147
     347: iconst_0
     348: istore_1
     349: goto          440
     352: astore        4
     354: getstatic     #54                 // Field LOG:Lorg/slf4j/Logger;
     357: ldc           #77                 // String Failed getting failed servers to be recovered.
     359: aload         4
     361: invokeinterface #78,  3           // InterfaceMethod org/slf4j/Logger.warn:(Ljava/lang/String;Ljava/lang/Throwable;)V
     366: aload_0
     367: invokespecial #79                 // Method checkFileSystem:()Z
     370: ifne          390
     373: getstatic     #54                 // Field LOG:Lorg/slf4j/Logger;
     376: ldc           #80                 // String Bad Filesystem, exiting
     378: invokeinterface #56,  2           // InterfaceMethod org/slf4j/Logger.warn:(Ljava/lang/String;)V
     383: invokestatic  #81                 // Method java/lang/Runtime.getRuntime:()Ljava/lang/Runtime;
     386: iconst_1
     387: invokevirtual #82                 // Method java/lang/Runtime.halt:(I)V
     390: iload_1
     391: ifeq          410
     394: aload_0
     395: getfield      #15                 // Field conf:Lorg/apache/hadoop/conf/Configuration;
     398: ldc           #83                 // String hbase.hlog.split.failure.retry.interval
     400: sipush        30000
     403: invokevirtual #84                 // Method org/apache/hadoop/conf/Configuration.getInt:(Ljava/lang/String;I)I
     406: i2l
     407: invokestatic  #85                 // Method java/lang/Thread.sleep:(J)V
     410: goto          440
     413: astore        5
     415: getstatic     #54                 // Field LOG:Lorg/slf4j/Logger;
     418: ldc           #87                 // String Interrupted, aborting since cannot return w/o splitting
     420: invokeinterface #56,  2           // InterfaceMethod org/slf4j/Logger.warn:(Ljava/lang/String;)V
     425: invokestatic  #88                 // Method java/lang/Thread.currentThread:()Ljava/lang/Thread;
     428: invokevirtual #89                 // Method java/lang/Thread.interrupt:()V
     431: iconst_0
     432: istore_1
     433: invokestatic  #81                 // Method java/lang/Runtime.getRuntime:()Ljava/lang/Runtime;
     436: iconst_1
     437: invokevirtual #82                 // Method java/lang/Runtime.halt:(I)V
     440: iload_1
     441: ifne          44
     444: aload_2
     445: areturn
    Exception table:
       from    to  target type
          69    81   352   Class java/io/IOException
          82   134   352   Class java/io/IOException
         135   349   352   Class java/io/IOException
         390   410   413   Class java/lang/InterruptedException

  public void splitLog(org.apache.hadoop.hbase.ServerName) throws java.io.IOException;
    Code:
       0: aload_0
       1: aload_1
       2: invokestatic  #90                 // Method java/util/Collections.singleton:(Ljava/lang/Object;)Ljava/util/Set;
       5: invokevirtual #91                 // Method splitLog:(Ljava/util/Set;)V
       8: return

  public void splitMetaLog(org.apache.hadoop.hbase.ServerName) throws java.io.IOException;
    Code:
       0: aload_0
       1: aload_1
       2: invokestatic  #90                 // Method java/util/Collections.singleton:(Ljava/lang/Object;)Ljava/util/Set;
       5: invokevirtual #92                 // Method splitMetaLog:(Ljava/util/Set;)V
       8: return

  public void splitMetaLog(java.util.Set<org.apache.hadoop.hbase.ServerName>) throws java.io.IOException;
    Code:
       0: aload_0
       1: aload_1
       2: getstatic     #93                 // Field META_FILTER:Lorg/apache/hadoop/fs/PathFilter;
       5: invokevirtual #94                 // Method splitLog:(Ljava/util/Set;Lorg/apache/hadoop/fs/PathFilter;)V
       8: return

  java.util.List<org.apache.hadoop.fs.Path> getLogDirs(java.util.Set<org.apache.hadoop.hbase.ServerName>) throws java.io.IOException;
    Code:
       0: new           #95                 // class java/util/ArrayList
       3: dup
       4: invokespecial #96                 // Method java/util/ArrayList."<init>":()V
       7: astore_2
       8: iconst_0
       9: istore_3
      10: aload_0
      11: getfield      #17                 // Field services:Lorg/apache/hadoop/hbase/master/MasterServices;
      14: invokeinterface #97,  1           // InterfaceMethod org/apache/hadoop/hbase/master/MasterServices.isInitialized:()Z
      19: ifne          33
      22: aload_0
      23: getfield      #12                 // Field splitLogLock:Ljava/util/concurrent/locks/Lock;
      26: invokeinterface #98,  1           // InterfaceMethod java/util/concurrent/locks/Lock.lock:()V
      31: iconst_1
      32: istore_3
      33: aload_1
      34: invokeinterface #99,  1           // InterfaceMethod java/util/Set.iterator:()Ljava/util/Iterator;
      39: astore        4
      41: aload         4
      43: invokeinterface #100,  1          // InterfaceMethod java/util/Iterator.hasNext:()Z
      48: ifeq          242
      51: aload         4
      53: invokeinterface #101,  1          // InterfaceMethod java/util/Iterator.next:()Ljava/lang/Object;
      58: checkcast     #102                // class org/apache/hadoop/hbase/ServerName
      61: astore        5
      63: new           #21                 // class org/apache/hadoop/fs/Path
      66: dup
      67: aload_0
      68: getfield      #16                 // Field rootDir:Lorg/apache/hadoop/fs/Path;
      71: aload         5
      73: invokevirtual #103                // Method org/apache/hadoop/hbase/ServerName.toString:()Ljava/lang/String;
      76: invokestatic  #104                // Method org/apache/hadoop/hbase/wal/AbstractFSWALProvider.getWALDirectoryName:(Ljava/lang/String;)Ljava/lang/String;
      79: invokespecial #24                 // Method org/apache/hadoop/fs/Path."<init>":(Lorg/apache/hadoop/fs/Path;Ljava/lang/String;)V
      82: astore        6
      84: aload         6
      86: ldc           #106                // String -splitting
      88: invokevirtual #107                // Method org/apache/hadoop/fs/Path.suffix:(Ljava/lang/String;)Lorg/apache/hadoop/fs/Path;
      91: astore        7
      93: aload_0
      94: getfield      #14                 // Field fs:Lorg/apache/hadoop/fs/FileSystem;
      97: aload         6
      99: invokevirtual #57                 // Method org/apache/hadoop/fs/FileSystem.exists:(Lorg/apache/hadoop/fs/Path;)Z
     102: ifeq          182
     105: aload_0
     106: getfield      #14                 // Field fs:Lorg/apache/hadoop/fs/FileSystem;
     109: aload         6
     111: aload         7
     113: invokevirtual #108                // Method org/apache/hadoop/fs/FileSystem.rename:(Lorg/apache/hadoop/fs/Path;Lorg/apache/hadoop/fs/Path;)Z
     116: ifne          147
     119: new           #29                 // class java/io/IOException
     122: dup
     123: new           #65                 // class java/lang/StringBuilder
     126: dup
     127: invokespecial #66                 // Method java/lang/StringBuilder."<init>":()V
     130: ldc           #109                // String Failed fs.rename for log split:
     132: invokevirtual #68                 // Method java/lang/StringBuilder.append:(Ljava/lang/String;)Ljava/lang/StringBuilder;
     135: aload         6
     137: invokevirtual #69                 // Method java/lang/StringBuilder.append:(Ljava/lang/Object;)Ljava/lang/StringBuilder;
     140: invokevirtual #71                 // Method java/lang/StringBuilder.toString:()Ljava/lang/String;
     143: invokespecial #110                // Method java/io/IOException."<init>":(Ljava/lang/String;)V
     146: athrow
     147: aload         7
     149: astore        6
     151: getstatic     #54                 // Field LOG:Lorg/slf4j/Logger;
     154: new           #65                 // class java/lang/StringBuilder
     157: dup
     158: invokespecial #66                 // Method java/lang/StringBuilder."<init>":()V
     161: ldc           #111                // String Renamed region directory:
     163: invokevirtual #68                 // Method java/lang/StringBuilder.append:(Ljava/lang/String;)Ljava/lang/StringBuilder;
     166: aload         7
     168: invokevirtual #69                 // Method java/lang/StringBuilder.append:(Ljava/lang/Object;)Ljava/lang/StringBuilder;
     171: invokevirtual #71                 // Method java/lang/StringBuilder.toString:()Ljava/lang/String;
     174: invokeinterface #62,  2           // InterfaceMethod org/slf4j/Logger.debug:(Ljava/lang/String;)V
     179: goto          230
     182: aload_0
     183: getfield      #14                 // Field fs:Lorg/apache/hadoop/fs/FileSystem;
     186: aload         7
     188: invokevirtual #57                 // Method org/apache/hadoop/fs/FileSystem.exists:(Lorg/apache/hadoop/fs/Path;)Z
     191: ifne          230
     194: getstatic     #54                 // Field LOG:Lorg/slf4j/Logger;
     197: new           #65                 // class java/lang/StringBuilder
     200: dup
     201: invokespecial #66                 // Method java/lang/StringBuilder."<init>":()V
     204: ldc           #112                // String Log dir for server
     206: invokevirtual #68                 // Method java/lang/StringBuilder.append:(Ljava/lang/String;)Ljava/lang/StringBuilder;
     209: aload         5
     211: invokevirtual #69                 // Method java/lang/StringBuilder.append:(Ljava/lang/Object;)Ljava/lang/StringBuilder;
     214: ldc           #113                // String  does not exist
     216: invokevirtual #68                 // Method java/lang/StringBuilder.append:(Ljava/lang/String;)Ljava/lang/StringBuilder;
     219: invokevirtual #71                 // Method java/lang/StringBuilder.toString:()Ljava/lang/String;
     222: invokeinterface #74,  2           // InterfaceMethod org/slf4j/Logger.info:(Ljava/lang/String;)V
     227: goto          41
     230: aload_2
     231: aload         7
     233: invokeinterface #114,  2          // InterfaceMethod java/util/List.add:(Ljava/lang/Object;)Z
     238: pop
     239: goto          41
     242: iload_3
     243: ifeq          317
     246: aload_0
     247: getfield      #12                 // Field splitLogLock:Ljava/util/concurrent/locks/Lock;
     250: invokeinterface #115,  1          // InterfaceMethod java/util/concurrent/locks/Lock.unlock:()V
     255: goto          317
     258: astore        4
     260: aload_0
     261: invokespecial #79                 // Method checkFileSystem:()Z
     264: ifne          283
     267: aload_0
     268: getfield      #17                 // Field services:Lorg/apache/hadoop/hbase/master/MasterServices;
     271: ldc           #116                // String Aborting due to filesystem unavailable
     273: aload         4
     275: invokeinterface #31,  3           // InterfaceMethod org/apache/hadoop/hbase/master/MasterServices.abort:(Ljava/lang/String;Ljava/lang/Throwable;)V
     280: aload         4
     282: athrow
     283: iload_3
     284: ifeq          317
     287: aload_0
     288: getfield      #12                 // Field splitLogLock:Ljava/util/concurrent/locks/Lock;
     291: invokeinterface #115,  1          // InterfaceMethod java/util/concurrent/locks/Lock.unlock:()V
     296: goto          317
     299: astore        8
     301: iload_3
     302: ifeq          314
     305: aload_0
     306: getfield      #12                 // Field splitLogLock:Ljava/util/concurrent/locks/Lock;
     309: invokeinterface #115,  1          // InterfaceMethod java/util/concurrent/locks/Lock.unlock:()V
     314: aload         8
     316: athrow
     317: aload_2
     318: areturn
    Exception table:
       from    to  target type
          33   242   258   Class java/io/IOException
          33   242   299   any
         258   283   299   any
         299   301   299   any

  public void splitLog(java.util.Set<org.apache.hadoop.hbase.ServerName>) throws java.io.IOException;
    Code:
       0: aload_0
       1: aload_1
       2: getstatic     #117                // Field NON_META_FILTER:Lorg/apache/hadoop/fs/PathFilter;
       5: invokevirtual #94                 // Method splitLog:(Ljava/util/Set;Lorg/apache/hadoop/fs/PathFilter;)V
       8: return

  public void splitLog(java.util.Set<org.apache.hadoop.hbase.ServerName>, org.apache.hadoop.fs.PathFilter) throws java.io.IOException;
    Code:
       0: lconst_0
       1: lstore_3
       2: lconst_0
       3: lstore        5
       5: aload_0
       6: aload_1
       7: invokevirtual #118                // Method getLogDirs:(Ljava/util/Set;)Ljava/util/List;
      10: astore        7
      12: aload_0
      13: getfield      #20                 // Field splitLogManager:Lorg/apache/hadoop/hbase/master/SplitLogManager;
      16: aload_1
      17: invokevirtual #119                // Method org/apache/hadoop/hbase/master/SplitLogManager.handleDeadWorkers:(Ljava/util/Set;)V
      20: invokestatic  #120                // Method org/apache/hadoop/hbase/util/EnvironmentEdgeManager.currentTime:()J
      23: lstore_3
      24: aload_0
      25: getfield      #20                 // Field splitLogManager:Lorg/apache/hadoop/hbase/master/SplitLogManager;
      28: aload_1
      29: aload         7
      31: aload_2
      32: invokevirtual #121                // Method org/apache/hadoop/hbase/master/SplitLogManager.splitLogDistributed:(Ljava/util/Set;Ljava/util/List;Lorg/apache/hadoop/fs/PathFilter;)J
      35: lstore        5
      37: invokestatic  #120                // Method org/apache/hadoop/hbase/util/EnvironmentEdgeManager.currentTime:()J
      40: lload_3
      41: lsub
      42: lstore_3
      43: aload_0
      44: getfield      #9                  // Field metricsMasterFilesystem:Lorg/apache/hadoop/hbase/master/MetricsMasterFileSystem;
      47: ifnull        80
      50: aload_2
      51: getstatic     #93                 // Field META_FILTER:Lorg/apache/hadoop/fs/PathFilter;
      54: if_acmpne     70
      57: aload_0
      58: getfield      #9                  // Field metricsMasterFilesystem:Lorg/apache/hadoop/hbase/master/MetricsMasterFileSystem;
      61: lload_3
      62: lload         5
      64: invokevirtual #122                // Method org/apache/hadoop/hbase/master/MetricsMasterFileSystem.addMetaWALSplit:(JJ)V
      67: goto          80
      70: aload_0
      71: getfield      #9                  // Field metricsMasterFilesystem:Lorg/apache/hadoop/hbase/master/MetricsMasterFileSystem;
      74: lload_3
      75: lload         5
      77: invokevirtual #123                // Method org/apache/hadoop/hbase/master/MetricsMasterFileSystem.addSplit:(JJ)V
      80: return

  public void archiveMetaLog(org.apache.hadoop.hbase.ServerName);
    Code:
       0: new           #21                 // class org/apache/hadoop/fs/Path
       3: dup
       4: aload_0
       5: getfield      #16                 // Field rootDir:Lorg/apache/hadoop/fs/Path;
       8: aload_1
       9: invokevirtual #103                // Method org/apache/hadoop/hbase/ServerName.toString:()Ljava/lang/String;
      12: invokestatic  #104                // Method org/apache/hadoop/hbase/wal/AbstractFSWALProvider.getWALDirectoryName:(Ljava/lang/String;)Ljava/lang/String;
      15: invokespecial #24                 // Method org/apache/hadoop/fs/Path."<init>":(Lorg/apache/hadoop/fs/Path;Ljava/lang/String;)V
      18: astore_2
      19: aload_2
      20: ldc           #106                // String -splitting
      22: invokevirtual #107                // Method org/apache/hadoop/fs/Path.suffix:(Ljava/lang/String;)Lorg/apache/hadoop/fs/Path;
      25: astore_3
      26: aload_0
      27: getfield      #14                 // Field fs:Lorg/apache/hadoop/fs/FileSystem;
      30: aload_3
      31: invokevirtual #57                 // Method org/apache/hadoop/fs/FileSystem.exists:(Lorg/apache/hadoop/fs/Path;)Z
      34: ifeq          250
      37: aload_0
      38: getfield      #14                 // Field fs:Lorg/apache/hadoop/fs/FileSystem;
      41: aload_3
      42: getstatic     #93                 // Field META_FILTER:Lorg/apache/hadoop/fs/PathFilter;
      45: invokestatic  #46                 // Method org/apache/hadoop/hbase/util/FSUtils.listStatus:(Lorg/apache/hadoop/fs/FileSystem;Lorg/apache/hadoop/fs/Path;Lorg/apache/hadoop/fs/PathFilter;)[Lorg/apache/hadoop/fs/FileStatus;
      48: astore        4
      50: aload         4
      52: ifnull        211
      55: aload         4
      57: astore        5
      59: aload         5
      61: arraylength
      62: istore        6
      64: iconst_0
      65: istore        7
      67: iload         7
      69: iload         6
      71: if_icmpge     211
      74: aload         5
      76: iload         7
      78: aaload
      79: astore        8
      81: aload         8
      83: invokevirtual #124                // Method org/apache/hadoop/fs/FileStatus.isDir:()Z
      86: ifne          205
      89: aload_0
      90: getfield      #25                 // Field oldLogDir:Lorg/apache/hadoop/fs/Path;
      93: aload         8
      95: invokevirtual #63                 // Method org/apache/hadoop/fs/FileStatus.getPath:()Lorg/apache/hadoop/fs/Path;
      98: invokestatic  #125                // Method org/apache/hadoop/hbase/regionserver/wal/AbstractFSWAL.getWALArchivePath:(Lorg/apache/hadoop/fs/Path;Lorg/apache/hadoop/fs/Path;)Lorg/apache/hadoop/fs/Path;
     101: astore        9
     103: aload_0
     104: getfield      #14                 // Field fs:Lorg/apache/hadoop/fs/FileSystem;
     107: aload         8
     109: invokevirtual #63                 // Method org/apache/hadoop/fs/FileStatus.getPath:()Lorg/apache/hadoop/fs/Path;
     112: aload         9
     114: invokestatic  #126                // Method org/apache/hadoop/hbase/util/FSUtils.renameAndSetModifyTime:(Lorg/apache/hadoop/fs/FileSystem;Lorg/apache/hadoop/fs/Path;Lorg/apache/hadoop/fs/Path;)Z
     117: ifne          164
     120: getstatic     #54                 // Field LOG:Lorg/slf4j/Logger;
     123: new           #65                 // class java/lang/StringBuilder
     126: dup
     127: invokespecial #66                 // Method java/lang/StringBuilder."<init>":()V
     130: ldc           #127                // String Unable to move
     132: invokevirtual #68                 // Method java/lang/StringBuilder.append:(Ljava/lang/String;)Ljava/lang/StringBuilder;
     135: aload         8
     137: invokevirtual #63                 // Method org/apache/hadoop/fs/FileStatus.getPath:()Lorg/apache/hadoop/fs/Path;
     140: invokevirtual #69                 // Method java/lang/StringBuilder.append:(Ljava/lang/Object;)Ljava/lang/StringBuilder;
     143: ldc           #128                // String  to
     145: invokevirtual #68                 // Method java/lang/StringBuilder.append:(Ljava/lang/String;)Ljava/lang/StringBuilder;
     148: aload         9
     150: invokevirtual #69                 // Method java/lang/StringBuilder.append:(Ljava/lang/Object;)Ljava/lang/StringBuilder;
     153: invokevirtual #71                 // Method java/lang/StringBuilder.toString:()Ljava/lang/String;
     156: invokeinterface #56,  2           // InterfaceMethod org/slf4j/Logger.warn:(Ljava/lang/String;)V
     161: goto          205
     164: getstatic     #54                 // Field LOG:Lorg/slf4j/Logger;
     167: new           #65                 // class java/lang/StringBuilder
     170: dup
     171: invokespecial #66                 // Method java/lang/StringBuilder."<init>":()V
     174: ldc           #129                // String Archived meta log
     176: invokevirtual #68                 // Method java/lang/StringBuilder.append:(Ljava/lang/String;)Ljava/lang/StringBuilder;
     179: aload         8
     181: invokevirtual #63                 // Method org/apache/hadoop/fs/FileStatus.getPath:()Lorg/apache/hadoop/fs/Path;
     184: invokevirtual #69                 // Method java/lang/StringBuilder.append:(Ljava/lang/Object;)Ljava/lang/StringBuilder;
     187: ldc           #128                // String  to
     189: invokevirtual #68                 // Method java/lang/StringBuilder.append:(Ljava/lang/String;)Ljava/lang/StringBuilder;
     192: aload         9
     194: invokevirtual #69                 // Method java/lang/StringBuilder.append:(Ljava/lang/Object;)Ljava/lang/StringBuilder;
     197: invokevirtual #71                 // Method java/lang/StringBuilder.toString:()Ljava/lang/String;
     200: invokeinterface #62,  2           // InterfaceMethod org/slf4j/Logger.debug:(Ljava/lang/String;)V
     205: iinc          7, 1
     208: goto          67
     211: aload_0
     212: getfield      #14                 // Field fs:Lorg/apache/hadoop/fs/FileSystem;
     215: aload_3
     216: iconst_0
     217: invokevirtual #130                // Method org/apache/hadoop/fs/FileSystem.delete:(Lorg/apache/hadoop/fs/Path;Z)Z
     220: ifne          250
     223: getstatic     #54                 // Field LOG:Lorg/slf4j/Logger;
     226: new           #65                 // class java/lang/StringBuilder
     229: dup
     230: invokespecial #66                 // Method java/lang/StringBuilder."<init>":()V
     233: ldc           #131                // String Unable to delete log dir. Ignoring.
     235: invokevirtual #68                 // Method java/lang/StringBuilder.append:(Ljava/lang/String;)Ljava/lang/StringBuilder;
     238: aload_3
     239: invokevirtual #69                 // Method java/lang/StringBuilder.append:(Ljava/lang/Object;)Ljava/lang/StringBuilder;
     242: invokevirtual #71                 // Method java/lang/StringBuilder.toString:()Ljava/lang/String;
     245: invokeinterface #56,  2           // InterfaceMethod org/slf4j/Logger.warn:(Ljava/lang/String;)V
     250: goto          282
     253: astore_2
     254: getstatic     #54                 // Field LOG:Lorg/slf4j/Logger;
     257: new           #65                 // class java/lang/StringBuilder
     260: dup
     261: invokespecial #66                 // Method java/lang/StringBuilder."<init>":()V
     264: ldc           #132                // String Failed archiving meta log for server
     266: invokevirtual #68                 // Method java/lang/StringBuilder.append:(Ljava/lang/String;)Ljava/lang/StringBuilder;
     269: aload_1
     270: invokevirtual #69                 // Method java/lang/StringBuilder.append:(Ljava/lang/Object;)Ljava/lang/StringBuilder;
     273: invokevirtual #71                 // Method java/lang/StringBuilder.toString:()Ljava/lang/String;
     276: aload_2
     277: invokeinterface #78,  3           // InterfaceMethod org/slf4j/Logger.warn:(Ljava/lang/String;Ljava/lang/Throwable;)V
     282: return
    Exception table:
       from    to  target type
           0   250   253   Class java/io/IOException

  static {};
    Code:
       0: ldc           #137                // class org/apache/hadoop/hbase/master/MasterWalManager
       2: invokestatic  #138                // Method org/slf4j/LoggerFactory.getLogger:(Ljava/lang/Class;)Lorg/slf4j/Logger;
       5: putstatic     #54                 // Field LOG:Lorg/slf4j/Logger;
       8: new           #139                // class org/apache/hadoop/hbase/master/MasterWalManager$1
      11: dup
      12: invokespecial #140                // Method org/apache/hadoop/hbase/master/MasterWalManager$1."<init>":()V
      15: putstatic     #93                 // Field META_FILTER:Lorg/apache/hadoop/fs/PathFilter;
      18: new           #141                // class org/apache/hadoop/hbase/master/MasterWalManager$2
      21: dup
      22: invokespecial #142                // Method org/apache/hadoop/hbase/master/MasterWalManager$2."<init>":()V
      25: putstatic     #117                // Field NON_META_FILTER:Lorg/apache/hadoop/fs/PathFilter;
      28: return
}
