Compiled from "MasterProcedureEnv.java"
public class org.apache.hadoop.hbase.master.procedure.MasterProcedureEnv implements org.apache.hadoop.hbase.conf.ConfigurationObserver {
  public org.apache.hadoop.hbase.master.procedure.MasterProcedureEnv(org.apache.hadoop.hbase.master.MasterServices);
    Code:
       0: aload_0
       1: aload_1
       2: new           #2                  // class org/apache/hadoop/hbase/master/procedure/RSProcedureDispatcher
       5: dup
       6: aload_1
       7: invokespecial #3                  // Method org/apache/hadoop/hbase/master/procedure/RSProcedureDispatcher."<init>":(Lorg/apache/hadoop/hbase/master/MasterServices;)V
      10: invokespecial #4                  // Method "<init>":(Lorg/apache/hadoop/hbase/master/MasterServices;Lorg/apache/hadoop/hbase/master/procedure/RSProcedureDispatcher;)V
      13: return

  public org.apache.hadoop.hbase.master.procedure.MasterProcedureEnv(org.apache.hadoop.hbase.master.MasterServices, org.apache.hadoop.hbase.master.procedure.RSProcedureDispatcher);
    Code:
       0: aload_0
       1: invokespecial #5                  // Method java/lang/Object."<init>":()V
       4: aload_0
       5: aload_1
       6: putfield      #6                  // Field master:Lorg/apache/hadoop/hbase/master/MasterServices;
       9: aload_0
      10: new           #7                  // class org/apache/hadoop/hbase/master/procedure/MasterProcedureScheduler
      13: dup
      14: aload_1
      15: invokedynamic #8,  0              // InvokeDynamic #0:apply:(Lorg/apache/hadoop/hbase/master/MasterServices;)Ljava/util/function/Function;
      20: invokespecial #9                  // Method org/apache/hadoop/hbase/master/procedure/MasterProcedureScheduler."<init>":(Ljava/util/function/Function;)V
      23: putfield      #10                 // Field procSched:Lorg/apache/hadoop/hbase/master/procedure/MasterProcedureScheduler;
      26: aload_0
      27: aload_2
      28: putfield      #11                 // Field remoteDispatcher:Lorg/apache/hadoop/hbase/master/procedure/RSProcedureDispatcher;
      31: return

  public org.apache.hadoop.hbase.security.User getRequestUser();
    Code:
       0: invokestatic  #12                 // Method org/apache/hadoop/hbase/ipc/RpcServer.getRequestUser:()Ljava/util/Optional;
       3: invokestatic  #13                 // Method org/apache/hadoop/hbase/security/Superusers.getSystemUser:()Lorg/apache/hadoop/hbase/security/User;
       6: invokevirtual #14                 // Method java/util/Optional.orElse:(Ljava/lang/Object;)Ljava/lang/Object;
       9: checkcast     #15                 // class org/apache/hadoop/hbase/security/User
      12: areturn

  public org.apache.hadoop.hbase.master.MasterServices getMasterServices();
    Code:
       0: aload_0
       1: getfield      #6                  // Field master:Lorg/apache/hadoop/hbase/master/MasterServices;
       4: areturn

  public org.apache.hadoop.conf.Configuration getMasterConfiguration();
    Code:
       0: aload_0
       1: getfield      #6                  // Field master:Lorg/apache/hadoop/hbase/master/MasterServices;
       4: invokeinterface #16,  1           // InterfaceMethod org/apache/hadoop/hbase/master/MasterServices.getConfiguration:()Lorg/apache/hadoop/conf/Configuration;
       9: areturn

  public org.apache.hadoop.hbase.master.assignment.AssignmentManager getAssignmentManager();
    Code:
       0: aload_0
       1: getfield      #6                  // Field master:Lorg/apache/hadoop/hbase/master/MasterServices;
       4: invokeinterface #17,  1           // InterfaceMethod org/apache/hadoop/hbase/master/MasterServices.getAssignmentManager:()Lorg/apache/hadoop/hbase/master/assignment/AssignmentManager;
       9: areturn

  public org.apache.hadoop.hbase.master.MasterCoprocessorHost getMasterCoprocessorHost();
    Code:
       0: aload_0
       1: getfield      #6                  // Field master:Lorg/apache/hadoop/hbase/master/MasterServices;
       4: invokeinterface #18,  1           // InterfaceMethod org/apache/hadoop/hbase/master/MasterServices.getMasterCoprocessorHost:()Lorg/apache/hadoop/hbase/master/MasterCoprocessorHost;
       9: areturn

  public org.apache.hadoop.hbase.master.procedure.MasterProcedureScheduler getProcedureScheduler();
    Code:
       0: aload_0
       1: getfield      #10                 // Field procSched:Lorg/apache/hadoop/hbase/master/procedure/MasterProcedureScheduler;
       4: areturn

  public org.apache.hadoop.hbase.master.procedure.RSProcedureDispatcher getRemoteDispatcher();
    Code:
       0: aload_0
       1: getfield      #11                 // Field remoteDispatcher:Lorg/apache/hadoop/hbase/master/procedure/RSProcedureDispatcher;
       4: areturn

  public org.apache.hadoop.hbase.master.replication.ReplicationPeerManager getReplicationPeerManager();
    Code:
       0: aload_0
       1: getfield      #6                  // Field master:Lorg/apache/hadoop/hbase/master/MasterServices;
       4: invokeinterface #19,  1           // InterfaceMethod org/apache/hadoop/hbase/master/MasterServices.getReplicationPeerManager:()Lorg/apache/hadoop/hbase/master/replication/ReplicationPeerManager;
       9: areturn

  public org.apache.hadoop.hbase.master.MasterFileSystem getMasterFileSystem();
    Code:
       0: aload_0
       1: getfield      #6                  // Field master:Lorg/apache/hadoop/hbase/master/MasterServices;
       4: invokeinterface #20,  1           // InterfaceMethod org/apache/hadoop/hbase/master/MasterServices.getMasterFileSystem:()Lorg/apache/hadoop/hbase/master/MasterFileSystem;
       9: areturn

  public boolean isRunning();
    Code:
       0: aload_0
       1: getfield      #6                  // Field master:Lorg/apache/hadoop/hbase/master/MasterServices;
       4: ifnull        19
       7: aload_0
       8: getfield      #6                  // Field master:Lorg/apache/hadoop/hbase/master/MasterServices;
      11: invokeinterface #21,  1           // InterfaceMethod org/apache/hadoop/hbase/master/MasterServices.getMasterProcedureExecutor:()Lorg/apache/hadoop/hbase/procedure2/ProcedureExecutor;
      16: ifnonnull     21
      19: iconst_0
      20: ireturn
      21: aload_0
      22: getfield      #6                  // Field master:Lorg/apache/hadoop/hbase/master/MasterServices;
      25: invokeinterface #21,  1           // InterfaceMethod org/apache/hadoop/hbase/master/MasterServices.getMasterProcedureExecutor:()Lorg/apache/hadoop/hbase/procedure2/ProcedureExecutor;
      30: invokevirtual #22                 // Method org/apache/hadoop/hbase/procedure2/ProcedureExecutor.isRunning:()Z
      33: ireturn

  public boolean isInitialized();
    Code:
       0: aload_0
       1: getfield      #6                  // Field master:Lorg/apache/hadoop/hbase/master/MasterServices;
       4: invokeinterface #23,  1           // InterfaceMethod org/apache/hadoop/hbase/master/MasterServices.isInitialized:()Z
       9: ireturn

  public boolean waitInitialized(org.apache.hadoop.hbase.procedure2.Procedure<?>);
    Code:
       0: aload_0
       1: getfield      #6                  // Field master:Lorg/apache/hadoop/hbase/master/MasterServices;
       4: invokeinterface #24,  1           // InterfaceMethod org/apache/hadoop/hbase/master/MasterServices.getInitializedEvent:()Lorg/apache/hadoop/hbase/procedure2/ProcedureEvent;
       9: aload_1
      10: invokevirtual #25                 // Method org/apache/hadoop/hbase/procedure2/ProcedureEvent.suspendIfNotReady:(Lorg/apache/hadoop/hbase/procedure2/Procedure;)Z
      13: ireturn

  public void setEventReady(org.apache.hadoop.hbase.procedure2.ProcedureEvent<?>, boolean);
    Code:
       0: iload_2
       1: ifeq          15
       4: aload_1
       5: aload_0
       6: getfield      #10                 // Field procSched:Lorg/apache/hadoop/hbase/master/procedure/MasterProcedureScheduler;
       9: invokevirtual #26                 // Method org/apache/hadoop/hbase/procedure2/ProcedureEvent.wake:(Lorg/apache/hadoop/hbase/procedure2/AbstractProcedureScheduler;)V
      12: goto          19
      15: aload_1
      16: invokevirtual #27                 // Method org/apache/hadoop/hbase/procedure2/ProcedureEvent.suspend:()V
      19: return

  public void onConfigurationChange(org.apache.hadoop.conf.Configuration);
    Code:
       0: aload_0
       1: getfield      #6                  // Field master:Lorg/apache/hadoop/hbase/master/MasterServices;
       4: invokeinterface #21,  1           // InterfaceMethod org/apache/hadoop/hbase/master/MasterServices.getMasterProcedureExecutor:()Lorg/apache/hadoop/hbase/procedure2/ProcedureExecutor;
       9: aload_1
      10: invokevirtual #28                 // Method org/apache/hadoop/hbase/procedure2/ProcedureExecutor.refreshConfiguration:(Lorg/apache/hadoop/conf/Configuration;)V
      13: return

  static org.slf4j.Logger access$000();
    Code:
       0: getstatic     #1                  // Field LOG:Lorg/slf4j/Logger;
       3: areturn

  static {};
    Code:
       0: ldc           #31                 // class org/apache/hadoop/hbase/master/procedure/MasterProcedureEnv
       2: invokestatic  #32                 // Method org/slf4j/LoggerFactory.getLogger:(Ljava/lang/Class;)Lorg/slf4j/Logger;
       5: putstatic     #1                  // Field LOG:Lorg/slf4j/Logger;
       8: return
}
