Compiled from "MasterQuotaManager.java"
class org.apache.hadoop.hbase.quotas.MasterQuotaManager$SizeSnapshotWithTimestamp {
  public org.apache.hadoop.hbase.quotas.MasterQuotaManager$SizeSnapshotWithTimestamp(long, long);
    Code:
       0: aload_0
       1: invokespecial #1                  // Method java/lang/Object."<init>":()V
       4: aload_0
       5: lload_1
       6: putfield      #2                  // Field size:J
       9: aload_0
      10: lload_3
      11: putfield      #3                  // Field time:J
      14: return

  public long getSize();
    Code:
       0: aload_0
       1: getfield      #2                  // Field size:J
       4: lreturn

  public long getTime();
    Code:
       0: aload_0
       1: getfield      #3                  // Field time:J
       4: lreturn

  public boolean equals(java.lang.Object);
    Code:
       0: aload_1
       1: instanceof    #4                  // class org/apache/hadoop/hbase/quotas/MasterQuotaManager$SizeSnapshotWithTimestamp
       4: ifeq          42
       7: aload_1
       8: checkcast     #4                  // class org/apache/hadoop/hbase/quotas/MasterQuotaManager$SizeSnapshotWithTimestamp
      11: astore_2
      12: aload_0
      13: getfield      #2                  // Field size:J
      16: aload_2
      17: getfield      #2                  // Field size:J
      20: lcmp
      21: ifne          40
      24: aload_0
      25: getfield      #3                  // Field time:J
      28: aload_2
      29: getfield      #3                  // Field time:J
      32: lcmp
      33: ifne          40
      36: iconst_1
      37: goto          41
      40: iconst_0
      41: ireturn
      42: iconst_0
      43: ireturn

  public int hashCode();
    Code:
       0: new           #5                  // class org/apache/commons/lang3/builder/HashCodeBuilder
       3: dup
       4: invokespecial #6                  // Method org/apache/commons/lang3/builder/HashCodeBuilder."<init>":()V
       7: astore_1
       8: aload_1
       9: aload_0
      10: getfield      #2                  // Field size:J
      13: invokevirtual #7                  // Method org/apache/commons/lang3/builder/HashCodeBuilder.append:(J)Lorg/apache/commons/lang3/builder/HashCodeBuilder;
      16: aload_0
      17: getfield      #3                  // Field time:J
      20: invokevirtual #7                  // Method org/apache/commons/lang3/builder/HashCodeBuilder.append:(J)Lorg/apache/commons/lang3/builder/HashCodeBuilder;
      23: invokevirtual #8                  // Method org/apache/commons/lang3/builder/HashCodeBuilder.toHashCode:()I
      26: ireturn

  public java.lang.String toString();
    Code:
       0: new           #9                  // class java/lang/StringBuilder
       3: dup
       4: bipush        32
       6: invokespecial #10                 // Method java/lang/StringBuilder."<init>":(I)V
       9: astore_1
      10: aload_1
      11: ldc           #11                 // String SizeSnapshotWithTimestamp={size=
      13: invokevirtual #12                 // Method java/lang/StringBuilder.append:(Ljava/lang/String;)Ljava/lang/StringBuilder;
      16: aload_0
      17: getfield      #2                  // Field size:J
      20: invokevirtual #13                 // Method java/lang/StringBuilder.append:(J)Ljava/lang/StringBuilder;
      23: ldc           #14                 // String B,
      25: invokevirtual #12                 // Method java/lang/StringBuilder.append:(Ljava/lang/String;)Ljava/lang/StringBuilder;
      28: pop
      29: aload_1
      30: ldc           #15                 // String time=
      32: invokevirtual #12                 // Method java/lang/StringBuilder.append:(Ljava/lang/String;)Ljava/lang/StringBuilder;
      35: aload_0
      36: getfield      #3                  // Field time:J
      39: invokevirtual #13                 // Method java/lang/StringBuilder.append:(J)Ljava/lang/StringBuilder;
      42: ldc           #16                 // String }
      44: invokevirtual #12                 // Method java/lang/StringBuilder.append:(Ljava/lang/String;)Ljava/lang/StringBuilder;
      47: pop
      48: aload_1
      49: invokevirtual #17                 // Method java/lang/StringBuilder.toString:()Ljava/lang/String;
      52: areturn
}
