Compiled from "MasterProtos.java"
public final class org.apache.hadoop.hbase.shaded.protobuf.generated.MasterProtos$HbckService$Stub extends org.apache.hadoop.hbase.shaded.protobuf.generated.MasterProtos$HbckService implements org.apache.hadoop.hbase.shaded.protobuf.generated.MasterProtos$HbckService$Interface {
  public org.apache.hbase.thirdparty.com.google.protobuf.RpcChannel getChannel();
    Code:
       0: aload_0
       1: getfield      #3                  // Field channel:Lorg/apache/hbase/thirdparty/com/google/protobuf/RpcChannel;
       4: areturn

  public void setTableStateInMeta(org.apache.hbase.thirdparty.com.google.protobuf.RpcController, org.apache.hadoop.hbase.shaded.protobuf.generated.MasterProtos$SetTableStateInMetaRequest, org.apache.hbase.thirdparty.com.google.protobuf.RpcCallback<org.apache.hadoop.hbase.shaded.protobuf.generated.MasterProtos$GetTableStateResponse>);
    Code:
       0: aload_0
       1: getfield      #3                  // Field channel:Lorg/apache/hbase/thirdparty/com/google/protobuf/RpcChannel;
       4: invokestatic  #4                  // Method getDescriptor:()Lorg/apache/hbase/thirdparty/com/google/protobuf/Descriptors$ServiceDescriptor;
       7: invokevirtual #5                  // Method org/apache/hbase/thirdparty/com/google/protobuf/Descriptors$ServiceDescriptor.getMethods:()Ljava/util/List;
      10: iconst_0
      11: invokeinterface #6,  2            // InterfaceMethod java/util/List.get:(I)Ljava/lang/Object;
      16: checkcast     #7                  // class org/apache/hbase/thirdparty/com/google/protobuf/Descriptors$MethodDescriptor
      19: aload_1
      20: aload_2
      21: invokestatic  #8                  // Method org/apache/hadoop/hbase/shaded/protobuf/generated/MasterProtos$GetTableStateResponse.getDefaultInstance:()Lorg/apache/hadoop/hbase/shaded/protobuf/generated/MasterProtos$GetTableStateResponse;
      24: aload_3
      25: ldc           #9                  // class org/apache/hadoop/hbase/shaded/protobuf/generated/MasterProtos$GetTableStateResponse
      27: invokestatic  #8                  // Method org/apache/hadoop/hbase/shaded/protobuf/generated/MasterProtos$GetTableStateResponse.getDefaultInstance:()Lorg/apache/hadoop/hbase/shaded/protobuf/generated/MasterProtos$GetTableStateResponse;
      30: invokestatic  #10                 // Method org/apache/hbase/thirdparty/com/google/protobuf/RpcUtil.generalizeCallback:(Lorg/apache/hbase/thirdparty/com/google/protobuf/RpcCallback;Ljava/lang/Class;Lorg/apache/hbase/thirdparty/com/google/protobuf/Message;)Lorg/apache/hbase/thirdparty/com/google/protobuf/RpcCallback;
      33: invokeinterface #11,  6           // InterfaceMethod org/apache/hbase/thirdparty/com/google/protobuf/RpcChannel.callMethod:(Lorg/apache/hbase/thirdparty/com/google/protobuf/Descriptors$MethodDescriptor;Lorg/apache/hbase/thirdparty/com/google/protobuf/RpcController;Lorg/apache/hbase/thirdparty/com/google/protobuf/Message;Lorg/apache/hbase/thirdparty/com/google/protobuf/Message;Lorg/apache/hbase/thirdparty/com/google/protobuf/RpcCallback;)V
      38: return

  public void assigns(org.apache.hbase.thirdparty.com.google.protobuf.RpcController, org.apache.hadoop.hbase.shaded.protobuf.generated.MasterProtos$AssignsRequest, org.apache.hbase.thirdparty.com.google.protobuf.RpcCallback<org.apache.hadoop.hbase.shaded.protobuf.generated.MasterProtos$AssignsResponse>);
    Code:
       0: aload_0
       1: getfield      #3                  // Field channel:Lorg/apache/hbase/thirdparty/com/google/protobuf/RpcChannel;
       4: invokestatic  #4                  // Method getDescriptor:()Lorg/apache/hbase/thirdparty/com/google/protobuf/Descriptors$ServiceDescriptor;
       7: invokevirtual #5                  // Method org/apache/hbase/thirdparty/com/google/protobuf/Descriptors$ServiceDescriptor.getMethods:()Ljava/util/List;
      10: iconst_1
      11: invokeinterface #6,  2            // InterfaceMethod java/util/List.get:(I)Ljava/lang/Object;
      16: checkcast     #7                  // class org/apache/hbase/thirdparty/com/google/protobuf/Descriptors$MethodDescriptor
      19: aload_1
      20: aload_2
      21: invokestatic  #12                 // Method org/apache/hadoop/hbase/shaded/protobuf/generated/MasterProtos$AssignsResponse.getDefaultInstance:()Lorg/apache/hadoop/hbase/shaded/protobuf/generated/MasterProtos$AssignsResponse;
      24: aload_3
      25: ldc           #13                 // class org/apache/hadoop/hbase/shaded/protobuf/generated/MasterProtos$AssignsResponse
      27: invokestatic  #12                 // Method org/apache/hadoop/hbase/shaded/protobuf/generated/MasterProtos$AssignsResponse.getDefaultInstance:()Lorg/apache/hadoop/hbase/shaded/protobuf/generated/MasterProtos$AssignsResponse;
      30: invokestatic  #10                 // Method org/apache/hbase/thirdparty/com/google/protobuf/RpcUtil.generalizeCallback:(Lorg/apache/hbase/thirdparty/com/google/protobuf/RpcCallback;Ljava/lang/Class;Lorg/apache/hbase/thirdparty/com/google/protobuf/Message;)Lorg/apache/hbase/thirdparty/com/google/protobuf/RpcCallback;
      33: invokeinterface #11,  6           // InterfaceMethod org/apache/hbase/thirdparty/com/google/protobuf/RpcChannel.callMethod:(Lorg/apache/hbase/thirdparty/com/google/protobuf/Descriptors$MethodDescriptor;Lorg/apache/hbase/thirdparty/com/google/protobuf/RpcController;Lorg/apache/hbase/thirdparty/com/google/protobuf/Message;Lorg/apache/hbase/thirdparty/com/google/protobuf/Message;Lorg/apache/hbase/thirdparty/com/google/protobuf/RpcCallback;)V
      38: return

  public void unassigns(org.apache.hbase.thirdparty.com.google.protobuf.RpcController, org.apache.hadoop.hbase.shaded.protobuf.generated.MasterProtos$UnassignsRequest, org.apache.hbase.thirdparty.com.google.protobuf.RpcCallback<org.apache.hadoop.hbase.shaded.protobuf.generated.MasterProtos$UnassignsResponse>);
    Code:
       0: aload_0
       1: getfield      #3                  // Field channel:Lorg/apache/hbase/thirdparty/com/google/protobuf/RpcChannel;
       4: invokestatic  #4                  // Method getDescriptor:()Lorg/apache/hbase/thirdparty/com/google/protobuf/Descriptors$ServiceDescriptor;
       7: invokevirtual #5                  // Method org/apache/hbase/thirdparty/com/google/protobuf/Descriptors$ServiceDescriptor.getMethods:()Ljava/util/List;
      10: iconst_2
      11: invokeinterface #6,  2            // InterfaceMethod java/util/List.get:(I)Ljava/lang/Object;
      16: checkcast     #7                  // class org/apache/hbase/thirdparty/com/google/protobuf/Descriptors$MethodDescriptor
      19: aload_1
      20: aload_2
      21: invokestatic  #14                 // Method org/apache/hadoop/hbase/shaded/protobuf/generated/MasterProtos$UnassignsResponse.getDefaultInstance:()Lorg/apache/hadoop/hbase/shaded/protobuf/generated/MasterProtos$UnassignsResponse;
      24: aload_3
      25: ldc           #15                 // class org/apache/hadoop/hbase/shaded/protobuf/generated/MasterProtos$UnassignsResponse
      27: invokestatic  #14                 // Method org/apache/hadoop/hbase/shaded/protobuf/generated/MasterProtos$UnassignsResponse.getDefaultInstance:()Lorg/apache/hadoop/hbase/shaded/protobuf/generated/MasterProtos$UnassignsResponse;
      30: invokestatic  #10                 // Method org/apache/hbase/thirdparty/com/google/protobuf/RpcUtil.generalizeCallback:(Lorg/apache/hbase/thirdparty/com/google/protobuf/RpcCallback;Ljava/lang/Class;Lorg/apache/hbase/thirdparty/com/google/protobuf/Message;)Lorg/apache/hbase/thirdparty/com/google/protobuf/RpcCallback;
      33: invokeinterface #11,  6           // InterfaceMethod org/apache/hbase/thirdparty/com/google/protobuf/RpcChannel.callMethod:(Lorg/apache/hbase/thirdparty/com/google/protobuf/Descriptors$MethodDescriptor;Lorg/apache/hbase/thirdparty/com/google/protobuf/RpcController;Lorg/apache/hbase/thirdparty/com/google/protobuf/Message;Lorg/apache/hbase/thirdparty/com/google/protobuf/Message;Lorg/apache/hbase/thirdparty/com/google/protobuf/RpcCallback;)V
      38: return

  public void bypassProcedure(org.apache.hbase.thirdparty.com.google.protobuf.RpcController, org.apache.hadoop.hbase.shaded.protobuf.generated.MasterProtos$BypassProcedureRequest, org.apache.hbase.thirdparty.com.google.protobuf.RpcCallback<org.apache.hadoop.hbase.shaded.protobuf.generated.MasterProtos$BypassProcedureResponse>);
    Code:
       0: aload_0
       1: getfield      #3                  // Field channel:Lorg/apache/hbase/thirdparty/com/google/protobuf/RpcChannel;
       4: invokestatic  #4                  // Method getDescriptor:()Lorg/apache/hbase/thirdparty/com/google/protobuf/Descriptors$ServiceDescriptor;
       7: invokevirtual #5                  // Method org/apache/hbase/thirdparty/com/google/protobuf/Descriptors$ServiceDescriptor.getMethods:()Ljava/util/List;
      10: iconst_3
      11: invokeinterface #6,  2            // InterfaceMethod java/util/List.get:(I)Ljava/lang/Object;
      16: checkcast     #7                  // class org/apache/hbase/thirdparty/com/google/protobuf/Descriptors$MethodDescriptor
      19: aload_1
      20: aload_2
      21: invokestatic  #16                 // Method org/apache/hadoop/hbase/shaded/protobuf/generated/MasterProtos$BypassProcedureResponse.getDefaultInstance:()Lorg/apache/hadoop/hbase/shaded/protobuf/generated/MasterProtos$BypassProcedureResponse;
      24: aload_3
      25: ldc           #17                 // class org/apache/hadoop/hbase/shaded/protobuf/generated/MasterProtos$BypassProcedureResponse
      27: invokestatic  #16                 // Method org/apache/hadoop/hbase/shaded/protobuf/generated/MasterProtos$BypassProcedureResponse.getDefaultInstance:()Lorg/apache/hadoop/hbase/shaded/protobuf/generated/MasterProtos$BypassProcedureResponse;
      30: invokestatic  #10                 // Method org/apache/hbase/thirdparty/com/google/protobuf/RpcUtil.generalizeCallback:(Lorg/apache/hbase/thirdparty/com/google/protobuf/RpcCallback;Ljava/lang/Class;Lorg/apache/hbase/thirdparty/com/google/protobuf/Message;)Lorg/apache/hbase/thirdparty/com/google/protobuf/RpcCallback;
      33: invokeinterface #11,  6           // InterfaceMethod org/apache/hbase/thirdparty/com/google/protobuf/RpcChannel.callMethod:(Lorg/apache/hbase/thirdparty/com/google/protobuf/Descriptors$MethodDescriptor;Lorg/apache/hbase/thirdparty/com/google/protobuf/RpcController;Lorg/apache/hbase/thirdparty/com/google/protobuf/Message;Lorg/apache/hbase/thirdparty/com/google/protobuf/Message;Lorg/apache/hbase/thirdparty/com/google/protobuf/RpcCallback;)V
      38: return

  public void scheduleServerCrashProcedure(org.apache.hbase.thirdparty.com.google.protobuf.RpcController, org.apache.hadoop.hbase.shaded.protobuf.generated.MasterProtos$ScheduleServerCrashProcedureRequest, org.apache.hbase.thirdparty.com.google.protobuf.RpcCallback<org.apache.hadoop.hbase.shaded.protobuf.generated.MasterProtos$ScheduleServerCrashProcedureResponse>);
    Code:
       0: aload_0
       1: getfield      #3                  // Field channel:Lorg/apache/hbase/thirdparty/com/google/protobuf/RpcChannel;
       4: invokestatic  #4                  // Method getDescriptor:()Lorg/apache/hbase/thirdparty/com/google/protobuf/Descriptors$ServiceDescriptor;
       7: invokevirtual #5                  // Method org/apache/hbase/thirdparty/com/google/protobuf/Descriptors$ServiceDescriptor.getMethods:()Ljava/util/List;
      10: iconst_4
      11: invokeinterface #6,  2            // InterfaceMethod java/util/List.get:(I)Ljava/lang/Object;
      16: checkcast     #7                  // class org/apache/hbase/thirdparty/com/google/protobuf/Descriptors$MethodDescriptor
      19: aload_1
      20: aload_2
      21: invokestatic  #18                 // Method org/apache/hadoop/hbase/shaded/protobuf/generated/MasterProtos$ScheduleServerCrashProcedureResponse.getDefaultInstance:()Lorg/apache/hadoop/hbase/shaded/protobuf/generated/MasterProtos$ScheduleServerCrashProcedureResponse;
      24: aload_3
      25: ldc           #19                 // class org/apache/hadoop/hbase/shaded/protobuf/generated/MasterProtos$ScheduleServerCrashProcedureResponse
      27: invokestatic  #18                 // Method org/apache/hadoop/hbase/shaded/protobuf/generated/MasterProtos$ScheduleServerCrashProcedureResponse.getDefaultInstance:()Lorg/apache/hadoop/hbase/shaded/protobuf/generated/MasterProtos$ScheduleServerCrashProcedureResponse;
      30: invokestatic  #10                 // Method org/apache/hbase/thirdparty/com/google/protobuf/RpcUtil.generalizeCallback:(Lorg/apache/hbase/thirdparty/com/google/protobuf/RpcCallback;Ljava/lang/Class;Lorg/apache/hbase/thirdparty/com/google/protobuf/Message;)Lorg/apache/hbase/thirdparty/com/google/protobuf/RpcCallback;
      33: invokeinterface #11,  6           // InterfaceMethod org/apache/hbase/thirdparty/com/google/protobuf/RpcChannel.callMethod:(Lorg/apache/hbase/thirdparty/com/google/protobuf/Descriptors$MethodDescriptor;Lorg/apache/hbase/thirdparty/com/google/protobuf/RpcController;Lorg/apache/hbase/thirdparty/com/google/protobuf/Message;Lorg/apache/hbase/thirdparty/com/google/protobuf/Message;Lorg/apache/hbase/thirdparty/com/google/protobuf/RpcCallback;)V
      38: return

  public void getFailedSplitMergeLegacyRegions(org.apache.hbase.thirdparty.com.google.protobuf.RpcController, org.apache.hadoop.hbase.shaded.protobuf.generated.MasterProtos$GetFailedSplitMergeLegacyRegionsRequest, org.apache.hbase.thirdparty.com.google.protobuf.RpcCallback<org.apache.hadoop.hbase.shaded.protobuf.generated.MasterProtos$GetFailedSplitMergeLegacyRegionsResponse>);
    Code:
       0: aload_0
       1: getfield      #3                  // Field channel:Lorg/apache/hbase/thirdparty/com/google/protobuf/RpcChannel;
       4: invokestatic  #4                  // Method getDescriptor:()Lorg/apache/hbase/thirdparty/com/google/protobuf/Descriptors$ServiceDescriptor;
       7: invokevirtual #5                  // Method org/apache/hbase/thirdparty/com/google/protobuf/Descriptors$ServiceDescriptor.getMethods:()Ljava/util/List;
      10: iconst_5
      11: invokeinterface #6,  2            // InterfaceMethod java/util/List.get:(I)Ljava/lang/Object;
      16: checkcast     #7                  // class org/apache/hbase/thirdparty/com/google/protobuf/Descriptors$MethodDescriptor
      19: aload_1
      20: aload_2
      21: invokestatic  #20                 // Method org/apache/hadoop/hbase/shaded/protobuf/generated/MasterProtos$GetFailedSplitMergeLegacyRegionsResponse.getDefaultInstance:()Lorg/apache/hadoop/hbase/shaded/protobuf/generated/MasterProtos$GetFailedSplitMergeLegacyRegionsResponse;
      24: aload_3
      25: ldc           #21                 // class org/apache/hadoop/hbase/shaded/protobuf/generated/MasterProtos$GetFailedSplitMergeLegacyRegionsResponse
      27: invokestatic  #20                 // Method org/apache/hadoop/hbase/shaded/protobuf/generated/MasterProtos$GetFailedSplitMergeLegacyRegionsResponse.getDefaultInstance:()Lorg/apache/hadoop/hbase/shaded/protobuf/generated/MasterProtos$GetFailedSplitMergeLegacyRegionsResponse;
      30: invokestatic  #10                 // Method org/apache/hbase/thirdparty/com/google/protobuf/RpcUtil.generalizeCallback:(Lorg/apache/hbase/thirdparty/com/google/protobuf/RpcCallback;Ljava/lang/Class;Lorg/apache/hbase/thirdparty/com/google/protobuf/Message;)Lorg/apache/hbase/thirdparty/com/google/protobuf/RpcCallback;
      33: invokeinterface #11,  6           // InterfaceMethod org/apache/hbase/thirdparty/com/google/protobuf/RpcChannel.callMethod:(Lorg/apache/hbase/thirdparty/com/google/protobuf/Descriptors$MethodDescriptor;Lorg/apache/hbase/thirdparty/com/google/protobuf/RpcController;Lorg/apache/hbase/thirdparty/com/google/protobuf/Message;Lorg/apache/hbase/thirdparty/com/google/protobuf/Message;Lorg/apache/hbase/thirdparty/com/google/protobuf/RpcCallback;)V
      38: return

  org.apache.hadoop.hbase.shaded.protobuf.generated.MasterProtos$HbckService$Stub(org.apache.hbase.thirdparty.com.google.protobuf.RpcChannel, org.apache.hadoop.hbase.shaded.protobuf.generated.MasterProtos$1);
    Code:
       0: aload_0
       1: aload_1
       2: invokespecial #1                  // Method "<init>":(Lorg/apache/hbase/thirdparty/com/google/protobuf/RpcChannel;)V
       5: return
}
