Compiled from "MasterObserver.java"
public interface org.apache.hadoop.hbase.coprocessor.MasterObserver {
  public org.apache.hadoop.hbase.client.TableDescriptor preCreateTableRegionsInfos(org.apache.hadoop.hbase.coprocessor.ObserverContext<org.apache.hadoop.hbase.coprocessor.MasterCoprocessorEnvironment>, org.apache.hadoop.hbase.client.TableDescriptor) throws java.io.IOException;
    Code:
       0: aload_2
       1: areturn

  public void preCreateTable(org.apache.hadoop.hbase.coprocessor.ObserverContext<org.apache.hadoop.hbase.coprocessor.MasterCoprocessorEnvironment>, org.apache.hadoop.hbase.client.TableDescriptor, org.apache.hadoop.hbase.client.RegionInfo[]) throws java.io.IOException;
    Code:
       0: return

  public void postCreateTable(org.apache.hadoop.hbase.coprocessor.ObserverContext<org.apache.hadoop.hbase.coprocessor.MasterCoprocessorEnvironment>, org.apache.hadoop.hbase.client.TableDescriptor, org.apache.hadoop.hbase.client.RegionInfo[]) throws java.io.IOException;
    Code:
       0: return

  public void preCreateTableAction(org.apache.hadoop.hbase.coprocessor.ObserverContext<org.apache.hadoop.hbase.coprocessor.MasterCoprocessorEnvironment>, org.apache.hadoop.hbase.client.TableDescriptor, org.apache.hadoop.hbase.client.RegionInfo[]) throws java.io.IOException;
    Code:
       0: return

  public void postCompletedCreateTableAction(org.apache.hadoop.hbase.coprocessor.ObserverContext<org.apache.hadoop.hbase.coprocessor.MasterCoprocessorEnvironment>, org.apache.hadoop.hbase.client.TableDescriptor, org.apache.hadoop.hbase.client.RegionInfo[]) throws java.io.IOException;
    Code:
       0: return

  public void preDeleteTable(org.apache.hadoop.hbase.coprocessor.ObserverContext<org.apache.hadoop.hbase.coprocessor.MasterCoprocessorEnvironment>, org.apache.hadoop.hbase.TableName) throws java.io.IOException;
    Code:
       0: return

  public void postDeleteTable(org.apache.hadoop.hbase.coprocessor.ObserverContext<org.apache.hadoop.hbase.coprocessor.MasterCoprocessorEnvironment>, org.apache.hadoop.hbase.TableName) throws java.io.IOException;
    Code:
       0: return

  public void preDeleteTableAction(org.apache.hadoop.hbase.coprocessor.ObserverContext<org.apache.hadoop.hbase.coprocessor.MasterCoprocessorEnvironment>, org.apache.hadoop.hbase.TableName) throws java.io.IOException;
    Code:
       0: return

  public void postCompletedDeleteTableAction(org.apache.hadoop.hbase.coprocessor.ObserverContext<org.apache.hadoop.hbase.coprocessor.MasterCoprocessorEnvironment>, org.apache.hadoop.hbase.TableName) throws java.io.IOException;
    Code:
       0: return

  public void preTruncateTable(org.apache.hadoop.hbase.coprocessor.ObserverContext<org.apache.hadoop.hbase.coprocessor.MasterCoprocessorEnvironment>, org.apache.hadoop.hbase.TableName) throws java.io.IOException;
    Code:
       0: return

  public void postTruncateTable(org.apache.hadoop.hbase.coprocessor.ObserverContext<org.apache.hadoop.hbase.coprocessor.MasterCoprocessorEnvironment>, org.apache.hadoop.hbase.TableName) throws java.io.IOException;
    Code:
       0: return

  public void preTruncateTableAction(org.apache.hadoop.hbase.coprocessor.ObserverContext<org.apache.hadoop.hbase.coprocessor.MasterCoprocessorEnvironment>, org.apache.hadoop.hbase.TableName) throws java.io.IOException;
    Code:
       0: return

  public void postCompletedTruncateTableAction(org.apache.hadoop.hbase.coprocessor.ObserverContext<org.apache.hadoop.hbase.coprocessor.MasterCoprocessorEnvironment>, org.apache.hadoop.hbase.TableName) throws java.io.IOException;
    Code:
       0: return

  public void preModifyTable(org.apache.hadoop.hbase.coprocessor.ObserverContext<org.apache.hadoop.hbase.coprocessor.MasterCoprocessorEnvironment>, org.apache.hadoop.hbase.TableName, org.apache.hadoop.hbase.client.TableDescriptor) throws java.io.IOException;
    Code:
       0: return

  public org.apache.hadoop.hbase.client.TableDescriptor preModifyTable(org.apache.hadoop.hbase.coprocessor.ObserverContext<org.apache.hadoop.hbase.coprocessor.MasterCoprocessorEnvironment>, org.apache.hadoop.hbase.TableName, org.apache.hadoop.hbase.client.TableDescriptor, org.apache.hadoop.hbase.client.TableDescriptor) throws java.io.IOException;
    Code:
       0: aload_0
       1: aload_1
       2: aload_2
       3: aload         4
       5: invokeinterface #1,  4            // InterfaceMethod preModifyTable:(Lorg/apache/hadoop/hbase/coprocessor/ObserverContext;Lorg/apache/hadoop/hbase/TableName;Lorg/apache/hadoop/hbase/client/TableDescriptor;)V
      10: aload         4
      12: areturn

  public void postModifyTable(org.apache.hadoop.hbase.coprocessor.ObserverContext<org.apache.hadoop.hbase.coprocessor.MasterCoprocessorEnvironment>, org.apache.hadoop.hbase.TableName, org.apache.hadoop.hbase.client.TableDescriptor) throws java.io.IOException;
    Code:
       0: return

  public void postModifyTable(org.apache.hadoop.hbase.coprocessor.ObserverContext<org.apache.hadoop.hbase.coprocessor.MasterCoprocessorEnvironment>, org.apache.hadoop.hbase.TableName, org.apache.hadoop.hbase.client.TableDescriptor, org.apache.hadoop.hbase.client.TableDescriptor) throws java.io.IOException;
    Code:
       0: aload_0
       1: aload_1
       2: aload_2
       3: aload         4
       5: invokeinterface #2,  4            // InterfaceMethod postModifyTable:(Lorg/apache/hadoop/hbase/coprocessor/ObserverContext;Lorg/apache/hadoop/hbase/TableName;Lorg/apache/hadoop/hbase/client/TableDescriptor;)V
      10: return

  public void preModifyTableAction(org.apache.hadoop.hbase.coprocessor.ObserverContext<org.apache.hadoop.hbase.coprocessor.MasterCoprocessorEnvironment>, org.apache.hadoop.hbase.TableName, org.apache.hadoop.hbase.client.TableDescriptor) throws java.io.IOException;
    Code:
       0: return

  public void preModifyTableAction(org.apache.hadoop.hbase.coprocessor.ObserverContext<org.apache.hadoop.hbase.coprocessor.MasterCoprocessorEnvironment>, org.apache.hadoop.hbase.TableName, org.apache.hadoop.hbase.client.TableDescriptor, org.apache.hadoop.hbase.client.TableDescriptor) throws java.io.IOException;
    Code:
       0: aload_0
       1: aload_1
       2: aload_2
       3: aload         4
       5: invokeinterface #3,  4            // InterfaceMethod preModifyTableAction:(Lorg/apache/hadoop/hbase/coprocessor/ObserverContext;Lorg/apache/hadoop/hbase/TableName;Lorg/apache/hadoop/hbase/client/TableDescriptor;)V
      10: return

  public void postCompletedModifyTableAction(org.apache.hadoop.hbase.coprocessor.ObserverContext<org.apache.hadoop.hbase.coprocessor.MasterCoprocessorEnvironment>, org.apache.hadoop.hbase.TableName, org.apache.hadoop.hbase.client.TableDescriptor) throws java.io.IOException;
    Code:
       0: return

  public void postCompletedModifyTableAction(org.apache.hadoop.hbase.coprocessor.ObserverContext<org.apache.hadoop.hbase.coprocessor.MasterCoprocessorEnvironment>, org.apache.hadoop.hbase.TableName, org.apache.hadoop.hbase.client.TableDescriptor, org.apache.hadoop.hbase.client.TableDescriptor) throws java.io.IOException;
    Code:
       0: aload_0
       1: aload_1
       2: aload_2
       3: aload         4
       5: invokeinterface #4,  4            // InterfaceMethod postCompletedModifyTableAction:(Lorg/apache/hadoop/hbase/coprocessor/ObserverContext;Lorg/apache/hadoop/hbase/TableName;Lorg/apache/hadoop/hbase/client/TableDescriptor;)V
      10: return

  public void preEnableTable(org.apache.hadoop.hbase.coprocessor.ObserverContext<org.apache.hadoop.hbase.coprocessor.MasterCoprocessorEnvironment>, org.apache.hadoop.hbase.TableName) throws java.io.IOException;
    Code:
       0: return

  public void postEnableTable(org.apache.hadoop.hbase.coprocessor.ObserverContext<org.apache.hadoop.hbase.coprocessor.MasterCoprocessorEnvironment>, org.apache.hadoop.hbase.TableName) throws java.io.IOException;
    Code:
       0: return

  public void preEnableTableAction(org.apache.hadoop.hbase.coprocessor.ObserverContext<org.apache.hadoop.hbase.coprocessor.MasterCoprocessorEnvironment>, org.apache.hadoop.hbase.TableName) throws java.io.IOException;
    Code:
       0: return

  public void postCompletedEnableTableAction(org.apache.hadoop.hbase.coprocessor.ObserverContext<org.apache.hadoop.hbase.coprocessor.MasterCoprocessorEnvironment>, org.apache.hadoop.hbase.TableName) throws java.io.IOException;
    Code:
       0: return

  public void preDisableTable(org.apache.hadoop.hbase.coprocessor.ObserverContext<org.apache.hadoop.hbase.coprocessor.MasterCoprocessorEnvironment>, org.apache.hadoop.hbase.TableName) throws java.io.IOException;
    Code:
       0: return

  public void postDisableTable(org.apache.hadoop.hbase.coprocessor.ObserverContext<org.apache.hadoop.hbase.coprocessor.MasterCoprocessorEnvironment>, org.apache.hadoop.hbase.TableName) throws java.io.IOException;
    Code:
       0: return

  public void preDisableTableAction(org.apache.hadoop.hbase.coprocessor.ObserverContext<org.apache.hadoop.hbase.coprocessor.MasterCoprocessorEnvironment>, org.apache.hadoop.hbase.TableName) throws java.io.IOException;
    Code:
       0: return

  public void postCompletedDisableTableAction(org.apache.hadoop.hbase.coprocessor.ObserverContext<org.apache.hadoop.hbase.coprocessor.MasterCoprocessorEnvironment>, org.apache.hadoop.hbase.TableName) throws java.io.IOException;
    Code:
       0: return

  public void preAbortProcedure(org.apache.hadoop.hbase.coprocessor.ObserverContext<org.apache.hadoop.hbase.coprocessor.MasterCoprocessorEnvironment>, long) throws java.io.IOException;
    Code:
       0: return

  public void postAbortProcedure(org.apache.hadoop.hbase.coprocessor.ObserverContext<org.apache.hadoop.hbase.coprocessor.MasterCoprocessorEnvironment>) throws java.io.IOException;
    Code:
       0: return

  public void preGetProcedures(org.apache.hadoop.hbase.coprocessor.ObserverContext<org.apache.hadoop.hbase.coprocessor.MasterCoprocessorEnvironment>) throws java.io.IOException;
    Code:
       0: return

  public void postGetProcedures(org.apache.hadoop.hbase.coprocessor.ObserverContext<org.apache.hadoop.hbase.coprocessor.MasterCoprocessorEnvironment>) throws java.io.IOException;
    Code:
       0: return

  public void preGetLocks(org.apache.hadoop.hbase.coprocessor.ObserverContext<org.apache.hadoop.hbase.coprocessor.MasterCoprocessorEnvironment>) throws java.io.IOException;
    Code:
       0: return

  public void postGetLocks(org.apache.hadoop.hbase.coprocessor.ObserverContext<org.apache.hadoop.hbase.coprocessor.MasterCoprocessorEnvironment>) throws java.io.IOException;
    Code:
       0: return

  public void preMove(org.apache.hadoop.hbase.coprocessor.ObserverContext<org.apache.hadoop.hbase.coprocessor.MasterCoprocessorEnvironment>, org.apache.hadoop.hbase.client.RegionInfo, org.apache.hadoop.hbase.ServerName, org.apache.hadoop.hbase.ServerName) throws java.io.IOException;
    Code:
       0: return

  public void postMove(org.apache.hadoop.hbase.coprocessor.ObserverContext<org.apache.hadoop.hbase.coprocessor.MasterCoprocessorEnvironment>, org.apache.hadoop.hbase.client.RegionInfo, org.apache.hadoop.hbase.ServerName, org.apache.hadoop.hbase.ServerName) throws java.io.IOException;
    Code:
       0: return

  public void preAssign(org.apache.hadoop.hbase.coprocessor.ObserverContext<org.apache.hadoop.hbase.coprocessor.MasterCoprocessorEnvironment>, org.apache.hadoop.hbase.client.RegionInfo) throws java.io.IOException;
    Code:
       0: return

  public void postAssign(org.apache.hadoop.hbase.coprocessor.ObserverContext<org.apache.hadoop.hbase.coprocessor.MasterCoprocessorEnvironment>, org.apache.hadoop.hbase.client.RegionInfo) throws java.io.IOException;
    Code:
       0: return

  public void preUnassign(org.apache.hadoop.hbase.coprocessor.ObserverContext<org.apache.hadoop.hbase.coprocessor.MasterCoprocessorEnvironment>, org.apache.hadoop.hbase.client.RegionInfo, boolean) throws java.io.IOException;
    Code:
       0: return

  public void postUnassign(org.apache.hadoop.hbase.coprocessor.ObserverContext<org.apache.hadoop.hbase.coprocessor.MasterCoprocessorEnvironment>, org.apache.hadoop.hbase.client.RegionInfo, boolean) throws java.io.IOException;
    Code:
       0: return

  public void preRegionOffline(org.apache.hadoop.hbase.coprocessor.ObserverContext<org.apache.hadoop.hbase.coprocessor.MasterCoprocessorEnvironment>, org.apache.hadoop.hbase.client.RegionInfo) throws java.io.IOException;
    Code:
       0: return

  public void postRegionOffline(org.apache.hadoop.hbase.coprocessor.ObserverContext<org.apache.hadoop.hbase.coprocessor.MasterCoprocessorEnvironment>, org.apache.hadoop.hbase.client.RegionInfo) throws java.io.IOException;
    Code:
       0: return

  public void preBalance(org.apache.hadoop.hbase.coprocessor.ObserverContext<org.apache.hadoop.hbase.coprocessor.MasterCoprocessorEnvironment>) throws java.io.IOException;
    Code:
       0: return

  public void postBalance(org.apache.hadoop.hbase.coprocessor.ObserverContext<org.apache.hadoop.hbase.coprocessor.MasterCoprocessorEnvironment>, java.util.List<org.apache.hadoop.hbase.master.RegionPlan>) throws java.io.IOException;
    Code:
       0: return

  public void preSetSplitOrMergeEnabled(org.apache.hadoop.hbase.coprocessor.ObserverContext<org.apache.hadoop.hbase.coprocessor.MasterCoprocessorEnvironment>, boolean, org.apache.hadoop.hbase.client.MasterSwitchType) throws java.io.IOException;
    Code:
       0: return

  public void postSetSplitOrMergeEnabled(org.apache.hadoop.hbase.coprocessor.ObserverContext<org.apache.hadoop.hbase.coprocessor.MasterCoprocessorEnvironment>, boolean, org.apache.hadoop.hbase.client.MasterSwitchType) throws java.io.IOException;
    Code:
       0: return

  public void preSplitRegion(org.apache.hadoop.hbase.coprocessor.ObserverContext<org.apache.hadoop.hbase.coprocessor.MasterCoprocessorEnvironment>, org.apache.hadoop.hbase.TableName, byte[]) throws java.io.IOException;
    Code:
       0: return

  public void preSplitRegionAction(org.apache.hadoop.hbase.coprocessor.ObserverContext<org.apache.hadoop.hbase.coprocessor.MasterCoprocessorEnvironment>, org.apache.hadoop.hbase.TableName, byte[]) throws java.io.IOException;
    Code:
       0: return

  public void postCompletedSplitRegionAction(org.apache.hadoop.hbase.coprocessor.ObserverContext<org.apache.hadoop.hbase.coprocessor.MasterCoprocessorEnvironment>, org.apache.hadoop.hbase.client.RegionInfo, org.apache.hadoop.hbase.client.RegionInfo) throws java.io.IOException;
    Code:
       0: return

  public void preSplitRegionBeforeMETAAction(org.apache.hadoop.hbase.coprocessor.ObserverContext<org.apache.hadoop.hbase.coprocessor.MasterCoprocessorEnvironment>, byte[], java.util.List<org.apache.hadoop.hbase.client.Mutation>) throws java.io.IOException;
    Code:
       0: return

  public void preSplitRegionAfterMETAAction(org.apache.hadoop.hbase.coprocessor.ObserverContext<org.apache.hadoop.hbase.coprocessor.MasterCoprocessorEnvironment>) throws java.io.IOException;
    Code:
       0: return

  public void postRollBackSplitRegionAction(org.apache.hadoop.hbase.coprocessor.ObserverContext<org.apache.hadoop.hbase.coprocessor.MasterCoprocessorEnvironment>) throws java.io.IOException;
    Code:
       0: return

  public void preMergeRegionsAction(org.apache.hadoop.hbase.coprocessor.ObserverContext<org.apache.hadoop.hbase.coprocessor.MasterCoprocessorEnvironment>, org.apache.hadoop.hbase.client.RegionInfo[]) throws java.io.IOException;
    Code:
       0: return

  public void postCompletedMergeRegionsAction(org.apache.hadoop.hbase.coprocessor.ObserverContext<org.apache.hadoop.hbase.coprocessor.MasterCoprocessorEnvironment>, org.apache.hadoop.hbase.client.RegionInfo[], org.apache.hadoop.hbase.client.RegionInfo) throws java.io.IOException;
    Code:
       0: return

  public void preMergeRegionsCommitAction(org.apache.hadoop.hbase.coprocessor.ObserverContext<org.apache.hadoop.hbase.coprocessor.MasterCoprocessorEnvironment>, org.apache.hadoop.hbase.client.RegionInfo[], java.util.List<org.apache.hadoop.hbase.client.Mutation>) throws java.io.IOException;
    Code:
       0: return

  public void postMergeRegionsCommitAction(org.apache.hadoop.hbase.coprocessor.ObserverContext<org.apache.hadoop.hbase.coprocessor.MasterCoprocessorEnvironment>, org.apache.hadoop.hbase.client.RegionInfo[], org.apache.hadoop.hbase.client.RegionInfo) throws java.io.IOException;
    Code:
       0: return

  public void postRollBackMergeRegionsAction(org.apache.hadoop.hbase.coprocessor.ObserverContext<org.apache.hadoop.hbase.coprocessor.MasterCoprocessorEnvironment>, org.apache.hadoop.hbase.client.RegionInfo[]) throws java.io.IOException;
    Code:
       0: return

  public void preBalanceSwitch(org.apache.hadoop.hbase.coprocessor.ObserverContext<org.apache.hadoop.hbase.coprocessor.MasterCoprocessorEnvironment>, boolean) throws java.io.IOException;
    Code:
       0: return

  public void postBalanceSwitch(org.apache.hadoop.hbase.coprocessor.ObserverContext<org.apache.hadoop.hbase.coprocessor.MasterCoprocessorEnvironment>, boolean, boolean) throws java.io.IOException;
    Code:
       0: return

  public void preShutdown(org.apache.hadoop.hbase.coprocessor.ObserverContext<org.apache.hadoop.hbase.coprocessor.MasterCoprocessorEnvironment>) throws java.io.IOException;
    Code:
       0: return

  public void preStopMaster(org.apache.hadoop.hbase.coprocessor.ObserverContext<org.apache.hadoop.hbase.coprocessor.MasterCoprocessorEnvironment>) throws java.io.IOException;
    Code:
       0: return

  public void postStartMaster(org.apache.hadoop.hbase.coprocessor.ObserverContext<org.apache.hadoop.hbase.coprocessor.MasterCoprocessorEnvironment>) throws java.io.IOException;
    Code:
       0: return

  public void preMasterInitialization(org.apache.hadoop.hbase.coprocessor.ObserverContext<org.apache.hadoop.hbase.coprocessor.MasterCoprocessorEnvironment>) throws java.io.IOException;
    Code:
       0: return

  public void preSnapshot(org.apache.hadoop.hbase.coprocessor.ObserverContext<org.apache.hadoop.hbase.coprocessor.MasterCoprocessorEnvironment>, org.apache.hadoop.hbase.client.SnapshotDescription, org.apache.hadoop.hbase.client.TableDescriptor) throws java.io.IOException;
    Code:
       0: return

  public void postSnapshot(org.apache.hadoop.hbase.coprocessor.ObserverContext<org.apache.hadoop.hbase.coprocessor.MasterCoprocessorEnvironment>, org.apache.hadoop.hbase.client.SnapshotDescription, org.apache.hadoop.hbase.client.TableDescriptor) throws java.io.IOException;
    Code:
       0: return

  public void preListSnapshot(org.apache.hadoop.hbase.coprocessor.ObserverContext<org.apache.hadoop.hbase.coprocessor.MasterCoprocessorEnvironment>, org.apache.hadoop.hbase.client.SnapshotDescription) throws java.io.IOException;
    Code:
       0: return

  public void postListSnapshot(org.apache.hadoop.hbase.coprocessor.ObserverContext<org.apache.hadoop.hbase.coprocessor.MasterCoprocessorEnvironment>, org.apache.hadoop.hbase.client.SnapshotDescription) throws java.io.IOException;
    Code:
       0: return

  public void preCloneSnapshot(org.apache.hadoop.hbase.coprocessor.ObserverContext<org.apache.hadoop.hbase.coprocessor.MasterCoprocessorEnvironment>, org.apache.hadoop.hbase.client.SnapshotDescription, org.apache.hadoop.hbase.client.TableDescriptor) throws java.io.IOException;
    Code:
       0: return

  public void postCloneSnapshot(org.apache.hadoop.hbase.coprocessor.ObserverContext<org.apache.hadoop.hbase.coprocessor.MasterCoprocessorEnvironment>, org.apache.hadoop.hbase.client.SnapshotDescription, org.apache.hadoop.hbase.client.TableDescriptor) throws java.io.IOException;
    Code:
       0: return

  public void preRestoreSnapshot(org.apache.hadoop.hbase.coprocessor.ObserverContext<org.apache.hadoop.hbase.coprocessor.MasterCoprocessorEnvironment>, org.apache.hadoop.hbase.client.SnapshotDescription, org.apache.hadoop.hbase.client.TableDescriptor) throws java.io.IOException;
    Code:
       0: return

  public void postRestoreSnapshot(org.apache.hadoop.hbase.coprocessor.ObserverContext<org.apache.hadoop.hbase.coprocessor.MasterCoprocessorEnvironment>, org.apache.hadoop.hbase.client.SnapshotDescription, org.apache.hadoop.hbase.client.TableDescriptor) throws java.io.IOException;
    Code:
       0: return

  public void preDeleteSnapshot(org.apache.hadoop.hbase.coprocessor.ObserverContext<org.apache.hadoop.hbase.coprocessor.MasterCoprocessorEnvironment>, org.apache.hadoop.hbase.client.SnapshotDescription) throws java.io.IOException;
    Code:
       0: return

  public void postDeleteSnapshot(org.apache.hadoop.hbase.coprocessor.ObserverContext<org.apache.hadoop.hbase.coprocessor.MasterCoprocessorEnvironment>, org.apache.hadoop.hbase.client.SnapshotDescription) throws java.io.IOException;
    Code:
       0: return

  public void preGetTableDescriptors(org.apache.hadoop.hbase.coprocessor.ObserverContext<org.apache.hadoop.hbase.coprocessor.MasterCoprocessorEnvironment>, java.util.List<org.apache.hadoop.hbase.TableName>, java.util.List<org.apache.hadoop.hbase.client.TableDescriptor>, java.lang.String) throws java.io.IOException;
    Code:
       0: return

  public void postGetTableDescriptors(org.apache.hadoop.hbase.coprocessor.ObserverContext<org.apache.hadoop.hbase.coprocessor.MasterCoprocessorEnvironment>, java.util.List<org.apache.hadoop.hbase.TableName>, java.util.List<org.apache.hadoop.hbase.client.TableDescriptor>, java.lang.String) throws java.io.IOException;
    Code:
       0: return

  public void preGetTableNames(org.apache.hadoop.hbase.coprocessor.ObserverContext<org.apache.hadoop.hbase.coprocessor.MasterCoprocessorEnvironment>, java.util.List<org.apache.hadoop.hbase.client.TableDescriptor>, java.lang.String) throws java.io.IOException;
    Code:
       0: return

  public void postGetTableNames(org.apache.hadoop.hbase.coprocessor.ObserverContext<org.apache.hadoop.hbase.coprocessor.MasterCoprocessorEnvironment>, java.util.List<org.apache.hadoop.hbase.client.TableDescriptor>, java.lang.String) throws java.io.IOException;
    Code:
       0: return

  public void preCreateNamespace(org.apache.hadoop.hbase.coprocessor.ObserverContext<org.apache.hadoop.hbase.coprocessor.MasterCoprocessorEnvironment>, org.apache.hadoop.hbase.NamespaceDescriptor) throws java.io.IOException;
    Code:
       0: return

  public void postCreateNamespace(org.apache.hadoop.hbase.coprocessor.ObserverContext<org.apache.hadoop.hbase.coprocessor.MasterCoprocessorEnvironment>, org.apache.hadoop.hbase.NamespaceDescriptor) throws java.io.IOException;
    Code:
       0: return

  public void preDeleteNamespace(org.apache.hadoop.hbase.coprocessor.ObserverContext<org.apache.hadoop.hbase.coprocessor.MasterCoprocessorEnvironment>, java.lang.String) throws java.io.IOException;
    Code:
       0: return

  public void postDeleteNamespace(org.apache.hadoop.hbase.coprocessor.ObserverContext<org.apache.hadoop.hbase.coprocessor.MasterCoprocessorEnvironment>, java.lang.String) throws java.io.IOException;
    Code:
       0: return

  public void preModifyNamespace(org.apache.hadoop.hbase.coprocessor.ObserverContext<org.apache.hadoop.hbase.coprocessor.MasterCoprocessorEnvironment>, org.apache.hadoop.hbase.NamespaceDescriptor) throws java.io.IOException;
    Code:
       0: return

  public void preModifyNamespace(org.apache.hadoop.hbase.coprocessor.ObserverContext<org.apache.hadoop.hbase.coprocessor.MasterCoprocessorEnvironment>, org.apache.hadoop.hbase.NamespaceDescriptor, org.apache.hadoop.hbase.NamespaceDescriptor) throws java.io.IOException;
    Code:
       0: aload_0
       1: aload_1
       2: aload_3
       3: invokeinterface #5,  3            // InterfaceMethod preModifyNamespace:(Lorg/apache/hadoop/hbase/coprocessor/ObserverContext;Lorg/apache/hadoop/hbase/NamespaceDescriptor;)V
       8: return

  public void postModifyNamespace(org.apache.hadoop.hbase.coprocessor.ObserverContext<org.apache.hadoop.hbase.coprocessor.MasterCoprocessorEnvironment>, org.apache.hadoop.hbase.NamespaceDescriptor) throws java.io.IOException;
    Code:
       0: return

  public void postModifyNamespace(org.apache.hadoop.hbase.coprocessor.ObserverContext<org.apache.hadoop.hbase.coprocessor.MasterCoprocessorEnvironment>, org.apache.hadoop.hbase.NamespaceDescriptor, org.apache.hadoop.hbase.NamespaceDescriptor) throws java.io.IOException;
    Code:
       0: aload_0
       1: aload_1
       2: aload_3
       3: invokeinterface #6,  3            // InterfaceMethod postModifyNamespace:(Lorg/apache/hadoop/hbase/coprocessor/ObserverContext;Lorg/apache/hadoop/hbase/NamespaceDescriptor;)V
       8: return

  public void preGetNamespaceDescriptor(org.apache.hadoop.hbase.coprocessor.ObserverContext<org.apache.hadoop.hbase.coprocessor.MasterCoprocessorEnvironment>, java.lang.String) throws java.io.IOException;
    Code:
       0: return

  public void postGetNamespaceDescriptor(org.apache.hadoop.hbase.coprocessor.ObserverContext<org.apache.hadoop.hbase.coprocessor.MasterCoprocessorEnvironment>, org.apache.hadoop.hbase.NamespaceDescriptor) throws java.io.IOException;
    Code:
       0: return

  public void preListNamespaces(org.apache.hadoop.hbase.coprocessor.ObserverContext<org.apache.hadoop.hbase.coprocessor.MasterCoprocessorEnvironment>, java.util.List<java.lang.String>) throws java.io.IOException;
    Code:
       0: return

  public void postListNamespaces(org.apache.hadoop.hbase.coprocessor.ObserverContext<org.apache.hadoop.hbase.coprocessor.MasterCoprocessorEnvironment>, java.util.List<java.lang.String>) throws java.io.IOException;
    Code:
       0: return

  public void preListNamespaceDescriptors(org.apache.hadoop.hbase.coprocessor.ObserverContext<org.apache.hadoop.hbase.coprocessor.MasterCoprocessorEnvironment>, java.util.List<org.apache.hadoop.hbase.NamespaceDescriptor>) throws java.io.IOException;
    Code:
       0: return

  public void postListNamespaceDescriptors(org.apache.hadoop.hbase.coprocessor.ObserverContext<org.apache.hadoop.hbase.coprocessor.MasterCoprocessorEnvironment>, java.util.List<org.apache.hadoop.hbase.NamespaceDescriptor>) throws java.io.IOException;
    Code:
       0: return

  public void preTableFlush(org.apache.hadoop.hbase.coprocessor.ObserverContext<org.apache.hadoop.hbase.coprocessor.MasterCoprocessorEnvironment>, org.apache.hadoop.hbase.TableName) throws java.io.IOException;
    Code:
       0: return

  public void postTableFlush(org.apache.hadoop.hbase.coprocessor.ObserverContext<org.apache.hadoop.hbase.coprocessor.MasterCoprocessorEnvironment>, org.apache.hadoop.hbase.TableName) throws java.io.IOException;
    Code:
       0: return

  public void preSetUserQuota(org.apache.hadoop.hbase.coprocessor.ObserverContext<org.apache.hadoop.hbase.coprocessor.MasterCoprocessorEnvironment>, java.lang.String, org.apache.hadoop.hbase.quotas.GlobalQuotaSettings) throws java.io.IOException;
    Code:
       0: return

  public void postSetUserQuota(org.apache.hadoop.hbase.coprocessor.ObserverContext<org.apache.hadoop.hbase.coprocessor.MasterCoprocessorEnvironment>, java.lang.String, org.apache.hadoop.hbase.quotas.GlobalQuotaSettings) throws java.io.IOException;
    Code:
       0: return

  public void preSetUserQuota(org.apache.hadoop.hbase.coprocessor.ObserverContext<org.apache.hadoop.hbase.coprocessor.MasterCoprocessorEnvironment>, java.lang.String, org.apache.hadoop.hbase.TableName, org.apache.hadoop.hbase.quotas.GlobalQuotaSettings) throws java.io.IOException;
    Code:
       0: return

  public void postSetUserQuota(org.apache.hadoop.hbase.coprocessor.ObserverContext<org.apache.hadoop.hbase.coprocessor.MasterCoprocessorEnvironment>, java.lang.String, org.apache.hadoop.hbase.TableName, org.apache.hadoop.hbase.quotas.GlobalQuotaSettings) throws java.io.IOException;
    Code:
       0: return

  public void preSetUserQuota(org.apache.hadoop.hbase.coprocessor.ObserverContext<org.apache.hadoop.hbase.coprocessor.MasterCoprocessorEnvironment>, java.lang.String, java.lang.String, org.apache.hadoop.hbase.quotas.GlobalQuotaSettings) throws java.io.IOException;
    Code:
       0: return

  public void postSetUserQuota(org.apache.hadoop.hbase.coprocessor.ObserverContext<org.apache.hadoop.hbase.coprocessor.MasterCoprocessorEnvironment>, java.lang.String, java.lang.String, org.apache.hadoop.hbase.quotas.GlobalQuotaSettings) throws java.io.IOException;
    Code:
       0: return

  public void preSetTableQuota(org.apache.hadoop.hbase.coprocessor.ObserverContext<org.apache.hadoop.hbase.coprocessor.MasterCoprocessorEnvironment>, org.apache.hadoop.hbase.TableName, org.apache.hadoop.hbase.quotas.GlobalQuotaSettings) throws java.io.IOException;
    Code:
       0: return

  public void postSetTableQuota(org.apache.hadoop.hbase.coprocessor.ObserverContext<org.apache.hadoop.hbase.coprocessor.MasterCoprocessorEnvironment>, org.apache.hadoop.hbase.TableName, org.apache.hadoop.hbase.quotas.GlobalQuotaSettings) throws java.io.IOException;
    Code:
       0: return

  public void preSetNamespaceQuota(org.apache.hadoop.hbase.coprocessor.ObserverContext<org.apache.hadoop.hbase.coprocessor.MasterCoprocessorEnvironment>, java.lang.String, org.apache.hadoop.hbase.quotas.GlobalQuotaSettings) throws java.io.IOException;
    Code:
       0: return

  public void postSetNamespaceQuota(org.apache.hadoop.hbase.coprocessor.ObserverContext<org.apache.hadoop.hbase.coprocessor.MasterCoprocessorEnvironment>, java.lang.String, org.apache.hadoop.hbase.quotas.GlobalQuotaSettings) throws java.io.IOException;
    Code:
       0: return

  public void preSetRegionServerQuota(org.apache.hadoop.hbase.coprocessor.ObserverContext<org.apache.hadoop.hbase.coprocessor.MasterCoprocessorEnvironment>, java.lang.String, org.apache.hadoop.hbase.quotas.GlobalQuotaSettings) throws java.io.IOException;
    Code:
       0: return

  public void postSetRegionServerQuota(org.apache.hadoop.hbase.coprocessor.ObserverContext<org.apache.hadoop.hbase.coprocessor.MasterCoprocessorEnvironment>, java.lang.String, org.apache.hadoop.hbase.quotas.GlobalQuotaSettings) throws java.io.IOException;
    Code:
       0: return

  public void preMergeRegions(org.apache.hadoop.hbase.coprocessor.ObserverContext<org.apache.hadoop.hbase.coprocessor.MasterCoprocessorEnvironment>, org.apache.hadoop.hbase.client.RegionInfo[]) throws java.io.IOException;
    Code:
       0: return

  public void postMergeRegions(org.apache.hadoop.hbase.coprocessor.ObserverContext<org.apache.hadoop.hbase.coprocessor.MasterCoprocessorEnvironment>, org.apache.hadoop.hbase.client.RegionInfo[]) throws java.io.IOException;
    Code:
       0: return

  public void preMoveServersAndTables(org.apache.hadoop.hbase.coprocessor.ObserverContext<org.apache.hadoop.hbase.coprocessor.MasterCoprocessorEnvironment>, java.util.Set<org.apache.hadoop.hbase.net.Address>, java.util.Set<org.apache.hadoop.hbase.TableName>, java.lang.String) throws java.io.IOException;
    Code:
       0: return

  public void postMoveServersAndTables(org.apache.hadoop.hbase.coprocessor.ObserverContext<org.apache.hadoop.hbase.coprocessor.MasterCoprocessorEnvironment>, java.util.Set<org.apache.hadoop.hbase.net.Address>, java.util.Set<org.apache.hadoop.hbase.TableName>, java.lang.String) throws java.io.IOException;
    Code:
       0: return

  public void preMoveServers(org.apache.hadoop.hbase.coprocessor.ObserverContext<org.apache.hadoop.hbase.coprocessor.MasterCoprocessorEnvironment>, java.util.Set<org.apache.hadoop.hbase.net.Address>, java.lang.String) throws java.io.IOException;
    Code:
       0: return

  public void postMoveServers(org.apache.hadoop.hbase.coprocessor.ObserverContext<org.apache.hadoop.hbase.coprocessor.MasterCoprocessorEnvironment>, java.util.Set<org.apache.hadoop.hbase.net.Address>, java.lang.String) throws java.io.IOException;
    Code:
       0: return

  public void preMoveTables(org.apache.hadoop.hbase.coprocessor.ObserverContext<org.apache.hadoop.hbase.coprocessor.MasterCoprocessorEnvironment>, java.util.Set<org.apache.hadoop.hbase.TableName>, java.lang.String) throws java.io.IOException;
    Code:
       0: return

  public void postMoveTables(org.apache.hadoop.hbase.coprocessor.ObserverContext<org.apache.hadoop.hbase.coprocessor.MasterCoprocessorEnvironment>, java.util.Set<org.apache.hadoop.hbase.TableName>, java.lang.String) throws java.io.IOException;
    Code:
       0: return

  public void preAddRSGroup(org.apache.hadoop.hbase.coprocessor.ObserverContext<org.apache.hadoop.hbase.coprocessor.MasterCoprocessorEnvironment>, java.lang.String) throws java.io.IOException;
    Code:
       0: return

  public void postAddRSGroup(org.apache.hadoop.hbase.coprocessor.ObserverContext<org.apache.hadoop.hbase.coprocessor.MasterCoprocessorEnvironment>, java.lang.String) throws java.io.IOException;
    Code:
       0: return

  public void preRemoveRSGroup(org.apache.hadoop.hbase.coprocessor.ObserverContext<org.apache.hadoop.hbase.coprocessor.MasterCoprocessorEnvironment>, java.lang.String) throws java.io.IOException;
    Code:
       0: return

  public void postRemoveRSGroup(org.apache.hadoop.hbase.coprocessor.ObserverContext<org.apache.hadoop.hbase.coprocessor.MasterCoprocessorEnvironment>, java.lang.String) throws java.io.IOException;
    Code:
       0: return

  public void preBalanceRSGroup(org.apache.hadoop.hbase.coprocessor.ObserverContext<org.apache.hadoop.hbase.coprocessor.MasterCoprocessorEnvironment>, java.lang.String) throws java.io.IOException;
    Code:
       0: return

  public void postBalanceRSGroup(org.apache.hadoop.hbase.coprocessor.ObserverContext<org.apache.hadoop.hbase.coprocessor.MasterCoprocessorEnvironment>, java.lang.String, boolean) throws java.io.IOException;
    Code:
       0: return

  public void preRemoveServers(org.apache.hadoop.hbase.coprocessor.ObserverContext<org.apache.hadoop.hbase.coprocessor.MasterCoprocessorEnvironment>, java.util.Set<org.apache.hadoop.hbase.net.Address>) throws java.io.IOException;
    Code:
       0: return

  public void postRemoveServers(org.apache.hadoop.hbase.coprocessor.ObserverContext<org.apache.hadoop.hbase.coprocessor.MasterCoprocessorEnvironment>, java.util.Set<org.apache.hadoop.hbase.net.Address>) throws java.io.IOException;
    Code:
       0: return

  public void preGetRSGroupInfo(org.apache.hadoop.hbase.coprocessor.ObserverContext<org.apache.hadoop.hbase.coprocessor.MasterCoprocessorEnvironment>, java.lang.String) throws java.io.IOException;
    Code:
       0: return

  public void postGetRSGroupInfo(org.apache.hadoop.hbase.coprocessor.ObserverContext<org.apache.hadoop.hbase.coprocessor.MasterCoprocessorEnvironment>, java.lang.String) throws java.io.IOException;
    Code:
       0: return

  public void preGetRSGroupInfoOfTable(org.apache.hadoop.hbase.coprocessor.ObserverContext<org.apache.hadoop.hbase.coprocessor.MasterCoprocessorEnvironment>, org.apache.hadoop.hbase.TableName) throws java.io.IOException;
    Code:
       0: return

  public void postGetRSGroupInfoOfTable(org.apache.hadoop.hbase.coprocessor.ObserverContext<org.apache.hadoop.hbase.coprocessor.MasterCoprocessorEnvironment>, org.apache.hadoop.hbase.TableName) throws java.io.IOException;
    Code:
       0: return

  public void preListRSGroups(org.apache.hadoop.hbase.coprocessor.ObserverContext<org.apache.hadoop.hbase.coprocessor.MasterCoprocessorEnvironment>) throws java.io.IOException;
    Code:
       0: return

  public void postListRSGroups(org.apache.hadoop.hbase.coprocessor.ObserverContext<org.apache.hadoop.hbase.coprocessor.MasterCoprocessorEnvironment>) throws java.io.IOException;
    Code:
       0: return

  public void preGetRSGroupInfoOfServer(org.apache.hadoop.hbase.coprocessor.ObserverContext<org.apache.hadoop.hbase.coprocessor.MasterCoprocessorEnvironment>, org.apache.hadoop.hbase.net.Address) throws java.io.IOException;
    Code:
       0: return

  public void postGetRSGroupInfoOfServer(org.apache.hadoop.hbase.coprocessor.ObserverContext<org.apache.hadoop.hbase.coprocessor.MasterCoprocessorEnvironment>, org.apache.hadoop.hbase.net.Address) throws java.io.IOException;
    Code:
       0: return

  public void preAddReplicationPeer(org.apache.hadoop.hbase.coprocessor.ObserverContext<org.apache.hadoop.hbase.coprocessor.MasterCoprocessorEnvironment>, java.lang.String, org.apache.hadoop.hbase.replication.ReplicationPeerConfig) throws java.io.IOException;
    Code:
       0: return

  public void postAddReplicationPeer(org.apache.hadoop.hbase.coprocessor.ObserverContext<org.apache.hadoop.hbase.coprocessor.MasterCoprocessorEnvironment>, java.lang.String, org.apache.hadoop.hbase.replication.ReplicationPeerConfig) throws java.io.IOException;
    Code:
       0: return

  public void preRemoveReplicationPeer(org.apache.hadoop.hbase.coprocessor.ObserverContext<org.apache.hadoop.hbase.coprocessor.MasterCoprocessorEnvironment>, java.lang.String) throws java.io.IOException;
    Code:
       0: return

  public void postRemoveReplicationPeer(org.apache.hadoop.hbase.coprocessor.ObserverContext<org.apache.hadoop.hbase.coprocessor.MasterCoprocessorEnvironment>, java.lang.String) throws java.io.IOException;
    Code:
       0: return

  public void preEnableReplicationPeer(org.apache.hadoop.hbase.coprocessor.ObserverContext<org.apache.hadoop.hbase.coprocessor.MasterCoprocessorEnvironment>, java.lang.String) throws java.io.IOException;
    Code:
       0: return

  public void postEnableReplicationPeer(org.apache.hadoop.hbase.coprocessor.ObserverContext<org.apache.hadoop.hbase.coprocessor.MasterCoprocessorEnvironment>, java.lang.String) throws java.io.IOException;
    Code:
       0: return

  public void preDisableReplicationPeer(org.apache.hadoop.hbase.coprocessor.ObserverContext<org.apache.hadoop.hbase.coprocessor.MasterCoprocessorEnvironment>, java.lang.String) throws java.io.IOException;
    Code:
       0: return

  public void postDisableReplicationPeer(org.apache.hadoop.hbase.coprocessor.ObserverContext<org.apache.hadoop.hbase.coprocessor.MasterCoprocessorEnvironment>, java.lang.String) throws java.io.IOException;
    Code:
       0: return

  public void preGetReplicationPeerConfig(org.apache.hadoop.hbase.coprocessor.ObserverContext<org.apache.hadoop.hbase.coprocessor.MasterCoprocessorEnvironment>, java.lang.String) throws java.io.IOException;
    Code:
       0: return

  public void postGetReplicationPeerConfig(org.apache.hadoop.hbase.coprocessor.ObserverContext<org.apache.hadoop.hbase.coprocessor.MasterCoprocessorEnvironment>, java.lang.String) throws java.io.IOException;
    Code:
       0: return

  public void preUpdateReplicationPeerConfig(org.apache.hadoop.hbase.coprocessor.ObserverContext<org.apache.hadoop.hbase.coprocessor.MasterCoprocessorEnvironment>, java.lang.String, org.apache.hadoop.hbase.replication.ReplicationPeerConfig) throws java.io.IOException;
    Code:
       0: return

  public void postUpdateReplicationPeerConfig(org.apache.hadoop.hbase.coprocessor.ObserverContext<org.apache.hadoop.hbase.coprocessor.MasterCoprocessorEnvironment>, java.lang.String, org.apache.hadoop.hbase.replication.ReplicationPeerConfig) throws java.io.IOException;
    Code:
       0: return

  public void preListReplicationPeers(org.apache.hadoop.hbase.coprocessor.ObserverContext<org.apache.hadoop.hbase.coprocessor.MasterCoprocessorEnvironment>, java.lang.String) throws java.io.IOException;
    Code:
       0: return

  public void postListReplicationPeers(org.apache.hadoop.hbase.coprocessor.ObserverContext<org.apache.hadoop.hbase.coprocessor.MasterCoprocessorEnvironment>, java.lang.String) throws java.io.IOException;
    Code:
       0: return

  public void preTransitReplicationPeerSyncReplicationState(org.apache.hadoop.hbase.coprocessor.ObserverContext<org.apache.hadoop.hbase.coprocessor.MasterCoprocessorEnvironment>, java.lang.String, org.apache.hadoop.hbase.replication.SyncReplicationState) throws java.io.IOException;
    Code:
       0: return

  public void postTransitReplicationPeerSyncReplicationState(org.apache.hadoop.hbase.coprocessor.ObserverContext<org.apache.hadoop.hbase.coprocessor.MasterCoprocessorEnvironment>, java.lang.String, org.apache.hadoop.hbase.replication.SyncReplicationState, org.apache.hadoop.hbase.replication.SyncReplicationState) throws java.io.IOException;
    Code:
       0: return

  public void preRequestLock(org.apache.hadoop.hbase.coprocessor.ObserverContext<org.apache.hadoop.hbase.coprocessor.MasterCoprocessorEnvironment>, java.lang.String, org.apache.hadoop.hbase.TableName, org.apache.hadoop.hbase.client.RegionInfo[], java.lang.String) throws java.io.IOException;
    Code:
       0: return

  public void postRequestLock(org.apache.hadoop.hbase.coprocessor.ObserverContext<org.apache.hadoop.hbase.coprocessor.MasterCoprocessorEnvironment>, java.lang.String, org.apache.hadoop.hbase.TableName, org.apache.hadoop.hbase.client.RegionInfo[], java.lang.String) throws java.io.IOException;
    Code:
       0: return

  public void preLockHeartbeat(org.apache.hadoop.hbase.coprocessor.ObserverContext<org.apache.hadoop.hbase.coprocessor.MasterCoprocessorEnvironment>, org.apache.hadoop.hbase.TableName, java.lang.String) throws java.io.IOException;
    Code:
       0: return

  public void postLockHeartbeat(org.apache.hadoop.hbase.coprocessor.ObserverContext<org.apache.hadoop.hbase.coprocessor.MasterCoprocessorEnvironment>) throws java.io.IOException;
    Code:
       0: return

  public void preGetClusterMetrics(org.apache.hadoop.hbase.coprocessor.ObserverContext<org.apache.hadoop.hbase.coprocessor.MasterCoprocessorEnvironment>) throws java.io.IOException;
    Code:
       0: return

  public void postGetClusterMetrics(org.apache.hadoop.hbase.coprocessor.ObserverContext<org.apache.hadoop.hbase.coprocessor.MasterCoprocessorEnvironment>, org.apache.hadoop.hbase.ClusterMetrics) throws java.io.IOException;
    Code:
       0: return

  public void preClearDeadServers(org.apache.hadoop.hbase.coprocessor.ObserverContext<org.apache.hadoop.hbase.coprocessor.MasterCoprocessorEnvironment>) throws java.io.IOException;
    Code:
       0: return

  public void postClearDeadServers(org.apache.hadoop.hbase.coprocessor.ObserverContext<org.apache.hadoop.hbase.coprocessor.MasterCoprocessorEnvironment>, java.util.List<org.apache.hadoop.hbase.ServerName>, java.util.List<org.apache.hadoop.hbase.ServerName>) throws java.io.IOException;
    Code:
       0: return

  public void preDecommissionRegionServers(org.apache.hadoop.hbase.coprocessor.ObserverContext<org.apache.hadoop.hbase.coprocessor.MasterCoprocessorEnvironment>, java.util.List<org.apache.hadoop.hbase.ServerName>, boolean) throws java.io.IOException;
    Code:
       0: return

  public void postDecommissionRegionServers(org.apache.hadoop.hbase.coprocessor.ObserverContext<org.apache.hadoop.hbase.coprocessor.MasterCoprocessorEnvironment>, java.util.List<org.apache.hadoop.hbase.ServerName>, boolean) throws java.io.IOException;
    Code:
       0: return

  public void preListDecommissionedRegionServers(org.apache.hadoop.hbase.coprocessor.ObserverContext<org.apache.hadoop.hbase.coprocessor.MasterCoprocessorEnvironment>) throws java.io.IOException;
    Code:
       0: return

  public void postListDecommissionedRegionServers(org.apache.hadoop.hbase.coprocessor.ObserverContext<org.apache.hadoop.hbase.coprocessor.MasterCoprocessorEnvironment>) throws java.io.IOException;
    Code:
       0: return

  public void preRecommissionRegionServer(org.apache.hadoop.hbase.coprocessor.ObserverContext<org.apache.hadoop.hbase.coprocessor.MasterCoprocessorEnvironment>, org.apache.hadoop.hbase.ServerName, java.util.List<byte[]>) throws java.io.IOException;
    Code:
       0: return

  public void postRecommissionRegionServer(org.apache.hadoop.hbase.coprocessor.ObserverContext<org.apache.hadoop.hbase.coprocessor.MasterCoprocessorEnvironment>, org.apache.hadoop.hbase.ServerName, java.util.List<byte[]>) throws java.io.IOException;
    Code:
       0: return

  public void preSwitchRpcThrottle(org.apache.hadoop.hbase.coprocessor.ObserverContext<org.apache.hadoop.hbase.coprocessor.MasterCoprocessorEnvironment>, boolean) throws java.io.IOException;
    Code:
       0: return

  public void postSwitchRpcThrottle(org.apache.hadoop.hbase.coprocessor.ObserverContext<org.apache.hadoop.hbase.coprocessor.MasterCoprocessorEnvironment>, boolean, boolean) throws java.io.IOException;
    Code:
       0: return

  public void preIsRpcThrottleEnabled(org.apache.hadoop.hbase.coprocessor.ObserverContext<org.apache.hadoop.hbase.coprocessor.MasterCoprocessorEnvironment>) throws java.io.IOException;
    Code:
       0: return

  public void postIsRpcThrottleEnabled(org.apache.hadoop.hbase.coprocessor.ObserverContext<org.apache.hadoop.hbase.coprocessor.MasterCoprocessorEnvironment>, boolean) throws java.io.IOException;
    Code:
       0: return

  public void preSwitchExceedThrottleQuota(org.apache.hadoop.hbase.coprocessor.ObserverContext<org.apache.hadoop.hbase.coprocessor.MasterCoprocessorEnvironment>, boolean) throws java.io.IOException;
    Code:
       0: return

  public void postSwitchExceedThrottleQuota(org.apache.hadoop.hbase.coprocessor.ObserverContext<org.apache.hadoop.hbase.coprocessor.MasterCoprocessorEnvironment>, boolean, boolean) throws java.io.IOException;
    Code:
       0: return

  public void preGrant(org.apache.hadoop.hbase.coprocessor.ObserverContext<org.apache.hadoop.hbase.coprocessor.MasterCoprocessorEnvironment>, org.apache.hadoop.hbase.security.access.UserPermission, boolean) throws java.io.IOException;
    Code:
       0: return

  public void postGrant(org.apache.hadoop.hbase.coprocessor.ObserverContext<org.apache.hadoop.hbase.coprocessor.MasterCoprocessorEnvironment>, org.apache.hadoop.hbase.security.access.UserPermission, boolean) throws java.io.IOException;
    Code:
       0: return

  public void preRevoke(org.apache.hadoop.hbase.coprocessor.ObserverContext<org.apache.hadoop.hbase.coprocessor.MasterCoprocessorEnvironment>, org.apache.hadoop.hbase.security.access.UserPermission) throws java.io.IOException;
    Code:
       0: return

  public void postRevoke(org.apache.hadoop.hbase.coprocessor.ObserverContext<org.apache.hadoop.hbase.coprocessor.MasterCoprocessorEnvironment>, org.apache.hadoop.hbase.security.access.UserPermission) throws java.io.IOException;
    Code:
       0: return

  public void preGetUserPermissions(org.apache.hadoop.hbase.coprocessor.ObserverContext<org.apache.hadoop.hbase.coprocessor.MasterCoprocessorEnvironment>, java.lang.String, java.lang.String, org.apache.hadoop.hbase.TableName, byte[], byte[]) throws java.io.IOException;
    Code:
       0: return

  public void postGetUserPermissions(org.apache.hadoop.hbase.coprocessor.ObserverContext<org.apache.hadoop.hbase.coprocessor.MasterCoprocessorEnvironment>, java.lang.String, java.lang.String, org.apache.hadoop.hbase.TableName, byte[], byte[]) throws java.io.IOException;
    Code:
       0: return

  public void preHasUserPermissions(org.apache.hadoop.hbase.coprocessor.ObserverContext<org.apache.hadoop.hbase.coprocessor.MasterCoprocessorEnvironment>, java.lang.String, java.util.List<org.apache.hadoop.hbase.security.access.Permission>) throws java.io.IOException;
    Code:
       0: return

  public void postHasUserPermissions(org.apache.hadoop.hbase.coprocessor.ObserverContext<org.apache.hadoop.hbase.coprocessor.MasterCoprocessorEnvironment>, java.lang.String, java.util.List<org.apache.hadoop.hbase.security.access.Permission>) throws java.io.IOException;
    Code:
       0: return
}
