Compiled from "MasterWalManager.java"
final class org.apache.hadoop.hbase.master.MasterWalManager$2 implements org.apache.hadoop.fs.PathFilter {
  org.apache.hadoop.hbase.master.MasterWalManager$2();
    Code:
       0: aload_0
       1: invokespecial #1                  // Method java/lang/Object."<init>":()V
       4: return

  public boolean accept(org.apache.hadoop.fs.Path);
    Code:
       0: aload_1
       1: invokestatic  #2                  // Method org/apache/hadoop/hbase/wal/AbstractFSWALProvider.isMetaFile:(Lorg/apache/hadoop/fs/Path;)Z
       4: ifne          11
       7: iconst_1
       8: goto          12
      11: iconst_0
      12: ireturn
}
