Compiled from "master_jsp.java"
public final class org.apache.hadoop.hbase.generated.master.master_jsp extends org.apache.jasper.runtime.HttpJspBase implements org.apache.jasper.runtime.JspSourceDependent {
  public org.apache.hadoop.hbase.generated.master.master_jsp();
    Code:
       0: aload_0
       1: invokespecial #1                  // Method org/apache/jasper/runtime/HttpJspBase."<init>":()V
       4: return

  public java.util.List<java.lang.String> getDependants();
    Code:
       0: getstatic     #2                  // Field _jspx_dependants:Ljava/util/List;
       3: areturn

  public void _jspService(javax.servlet.http.HttpServletRequest, javax.servlet.http.HttpServletResponse) throws java.io.IOException, javax.servlet.ServletException;
    Code:
       0: aconst_null
       1: astore_3
       2: aconst_null
       3: astore        4
       5: aconst_null
       6: astore        5
       8: aconst_null
       9: astore        6
      11: aconst_null
      12: astore        7
      14: aload_0
      15: astore        8
      17: aconst_null
      18: astore        9
      20: aconst_null
      21: astore        10
      23: aload_2
      24: ldc           #3                  // String text/html
      26: invokeinterface #4,  2            // InterfaceMethod javax/servlet/http/HttpServletResponse.setContentType:(Ljava/lang/String;)V
      31: getstatic     #5                  // Field _jspxFactory:Ljavax/servlet/jsp/JspFactory;
      34: aload_0
      35: aload_1
      36: aload_2
      37: aconst_null
      38: iconst_1
      39: sipush        8192
      42: iconst_1
      43: invokevirtual #6                  // Method javax/servlet/jsp/JspFactory.getPageContext:(Ljavax/servlet/Servlet;Ljavax/servlet/ServletRequest;Ljavax/servlet/ServletResponse;Ljava/lang/String;ZIZ)Ljavax/servlet/jsp/PageContext;
      46: astore_3
      47: aload_3
      48: astore        10
      50: aload_3
      51: invokevirtual #7                  // Method javax/servlet/jsp/PageContext.getServletContext:()Ljavax/servlet/ServletContext;
      54: astore        5
      56: aload_3
      57: invokevirtual #8                  // Method javax/servlet/jsp/PageContext.getServletConfig:()Ljavax/servlet/ServletConfig;
      60: astore        6
      62: aload_3
      63: invokevirtual #9                  // Method javax/servlet/jsp/PageContext.getSession:()Ljavax/servlet/http/HttpSession;
      66: astore        4
      68: aload_3
      69: invokevirtual #10                 // Method javax/servlet/jsp/PageContext.getOut:()Ljavax/servlet/jsp/JspWriter;
      72: astore        7
      74: aload         7
      76: astore        9
      78: aload_0
      79: aload         5
      81: ldc           #11                 // String com.sun.appserv.jsp.resource.injector
      83: invokeinterface #12,  2           // InterfaceMethod javax/servlet/ServletContext.getAttribute:(Ljava/lang/String;)Ljava/lang/Object;
      88: checkcast     #13                 // class org/glassfish/jsp/api/ResourceInjector
      91: putfield      #14                 // Field _jspx_resourceInjector:Lorg/glassfish/jsp/api/ResourceInjector;
      94: aload         7
      96: ldc           #15                 // String \n<meta HTTP-EQUIV=\"REFRESH\" content=\"0;url=/master-status\"/>\n
      98: invokevirtual #16                 // Method javax/servlet/jsp/JspWriter.write:(Ljava/lang/String;)V
     101: getstatic     #5                  // Field _jspxFactory:Ljavax/servlet/jsp/JspFactory;
     104: aload         10
     106: invokevirtual #17                 // Method javax/servlet/jsp/JspFactory.releasePageContext:(Ljavax/servlet/jsp/PageContext;)V
     109: goto          193
     112: astore        11
     114: aload         11
     116: instanceof    #19                 // class javax/servlet/jsp/SkipPageException
     119: ifne          169
     122: aload         9
     124: astore        7
     126: aload         7
     128: ifnull        144
     131: aload         7
     133: invokevirtual #20                 // Method javax/servlet/jsp/JspWriter.getBufferSize:()I
     136: ifeq          144
     139: aload         7
     141: invokevirtual #21                 // Method javax/servlet/jsp/JspWriter.clearBuffer:()V
     144: aload         10
     146: ifnull        159
     149: aload         10
     151: aload         11
     153: invokevirtual #22                 // Method javax/servlet/jsp/PageContext.handlePageException:(Ljava/lang/Throwable;)V
     156: goto          169
     159: new           #23                 // class javax/servlet/ServletException
     162: dup
     163: aload         11
     165: invokespecial #24                 // Method javax/servlet/ServletException."<init>":(Ljava/lang/Throwable;)V
     168: athrow
     169: getstatic     #5                  // Field _jspxFactory:Ljavax/servlet/jsp/JspFactory;
     172: aload         10
     174: invokevirtual #17                 // Method javax/servlet/jsp/JspFactory.releasePageContext:(Ljavax/servlet/jsp/PageContext;)V
     177: goto          193
     180: astore        12
     182: getstatic     #5                  // Field _jspxFactory:Ljavax/servlet/jsp/JspFactory;
     185: aload         10
     187: invokevirtual #17                 // Method javax/servlet/jsp/JspFactory.releasePageContext:(Ljavax/servlet/jsp/PageContext;)V
     190: aload         12
     192: athrow
     193: return
    Exception table:
       from    to  target type
          23   101   112   Class java/lang/Throwable
          23   101   180   any
         112   169   180   any
         180   182   180   any

  static {};
    Code:
       0: invokestatic  #25                 // Method javax/servlet/jsp/JspFactory.getDefaultFactory:()Ljavax/servlet/jsp/JspFactory;
       3: putstatic     #5                  // Field _jspxFactory:Ljavax/servlet/jsp/JspFactory;
       6: return
}
