Compiled from "MasterProcedureScheduler.java"
public class org.apache.hadoop.hbase.master.procedure.MasterProcedureScheduler extends org.apache.hadoop.hbase.procedure2.AbstractProcedureScheduler {
  static final boolean $assertionsDisabled;

  public org.apache.hadoop.hbase.master.procedure.MasterProcedureScheduler(java.util.function.Function<java.lang.Long, org.apache.hadoop.hbase.procedure2.Procedure<?>>);
    Code:
       0: aload_0
       1: invokespecial #1                  // Method org/apache/hadoop/hbase/procedure2/AbstractProcedureScheduler."<init>":()V
       4: aload_0
       5: new           #2                  // class org/apache/hadoop/hbase/master/procedure/FairQueue
       8: dup
       9: invokespecial #3                  // Method org/apache/hadoop/hbase/master/procedure/FairQueue."<init>":()V
      12: putfield      #4                  // Field serverRunQueue:Lorg/apache/hadoop/hbase/master/procedure/FairQueue;
      15: aload_0
      16: new           #2                  // class org/apache/hadoop/hbase/master/procedure/FairQueue
      19: dup
      20: invokespecial #3                  // Method org/apache/hadoop/hbase/master/procedure/FairQueue."<init>":()V
      23: putfield      #5                  // Field tableRunQueue:Lorg/apache/hadoop/hbase/master/procedure/FairQueue;
      26: aload_0
      27: new           #2                  // class org/apache/hadoop/hbase/master/procedure/FairQueue
      30: dup
      31: invokespecial #3                  // Method org/apache/hadoop/hbase/master/procedure/FairQueue."<init>":()V
      34: putfield      #6                  // Field peerRunQueue:Lorg/apache/hadoop/hbase/master/procedure/FairQueue;
      37: aload_0
      38: new           #2                  // class org/apache/hadoop/hbase/master/procedure/FairQueue
      41: dup
      42: invokespecial #3                  // Method org/apache/hadoop/hbase/master/procedure/FairQueue."<init>":()V
      45: putfield      #7                  // Field metaRunQueue:Lorg/apache/hadoop/hbase/master/procedure/FairQueue;
      48: aload_0
      49: sipush        128
      52: anewarray     #8                  // class org/apache/hadoop/hbase/master/procedure/ServerQueue
      55: putfield      #9                  // Field serverBuckets:[Lorg/apache/hadoop/hbase/master/procedure/ServerQueue;
      58: aload_0
      59: aconst_null
      60: putfield      #10                 // Field tableMap:Lorg/apache/hadoop/hbase/master/procedure/TableQueue;
      63: aload_0
      64: aconst_null
      65: putfield      #11                 // Field peerMap:Lorg/apache/hadoop/hbase/master/procedure/PeerQueue;
      68: aload_0
      69: aconst_null
      70: putfield      #12                 // Field metaMap:Lorg/apache/hadoop/hbase/master/procedure/MetaQueue;
      73: aload_0
      74: new           #13                 // class org/apache/hadoop/hbase/master/procedure/SchemaLocking
      77: dup
      78: aload_1
      79: invokespecial #14                 // Method org/apache/hadoop/hbase/master/procedure/SchemaLocking."<init>":(Ljava/util/function/Function;)V
      82: putfield      #15                 // Field locking:Lorg/apache/hadoop/hbase/master/procedure/SchemaLocking;
      85: return

  public void yield(org.apache.hadoop.hbase.procedure2.Procedure);
    Code:
       0: aload_0
       1: aload_1
       2: iconst_0
       3: iconst_1
       4: invokevirtual #16                 // Method push:(Lorg/apache/hadoop/hbase/procedure2/Procedure;ZZ)V
       7: return

  protected void enqueue(org.apache.hadoop.hbase.procedure2.Procedure, boolean);
    Code:
       0: aload_1
       1: invokestatic  #17                 // Method isMetaProcedure:(Lorg/apache/hadoop/hbase/procedure2/Procedure;)Z
       4: ifeq          24
       7: aload_0
       8: aload_0
       9: getfield      #7                  // Field metaRunQueue:Lorg/apache/hadoop/hbase/master/procedure/FairQueue;
      12: aload_0
      13: invokespecial #18                 // Method getMetaQueue:()Lorg/apache/hadoop/hbase/master/procedure/MetaQueue;
      16: aload_1
      17: iload_2
      18: invokespecial #19                 // Method doAdd:(Lorg/apache/hadoop/hbase/master/procedure/FairQueue;Lorg/apache/hadoop/hbase/master/procedure/Queue;Lorg/apache/hadoop/hbase/procedure2/Procedure;Z)V
      21: goto          143
      24: aload_1
      25: invokestatic  #20                 // Method isTableProcedure:(Lorg/apache/hadoop/hbase/procedure2/Procedure;)Z
      28: ifeq          52
      31: aload_0
      32: aload_0
      33: getfield      #5                  // Field tableRunQueue:Lorg/apache/hadoop/hbase/master/procedure/FairQueue;
      36: aload_0
      37: aload_1
      38: invokestatic  #21                 // Method getTableName:(Lorg/apache/hadoop/hbase/procedure2/Procedure;)Lorg/apache/hadoop/hbase/TableName;
      41: invokespecial #22                 // Method getTableQueue:(Lorg/apache/hadoop/hbase/TableName;)Lorg/apache/hadoop/hbase/master/procedure/TableQueue;
      44: aload_1
      45: iload_2
      46: invokespecial #19                 // Method doAdd:(Lorg/apache/hadoop/hbase/master/procedure/FairQueue;Lorg/apache/hadoop/hbase/master/procedure/Queue;Lorg/apache/hadoop/hbase/procedure2/Procedure;Z)V
      49: goto          143
      52: aload_1
      53: invokestatic  #23                 // Method isServerProcedure:(Lorg/apache/hadoop/hbase/procedure2/Procedure;)Z
      56: ifeq          88
      59: aload_1
      60: checkcast     #24                 // class org/apache/hadoop/hbase/master/procedure/ServerProcedureInterface
      63: astore_3
      64: aload_0
      65: aload_0
      66: getfield      #4                  // Field serverRunQueue:Lorg/apache/hadoop/hbase/master/procedure/FairQueue;
      69: aload_0
      70: aload_3
      71: invokeinterface #25,  1           // InterfaceMethod org/apache/hadoop/hbase/master/procedure/ServerProcedureInterface.getServerName:()Lorg/apache/hadoop/hbase/ServerName;
      76: aload_3
      77: invokespecial #26                 // Method getServerQueue:(Lorg/apache/hadoop/hbase/ServerName;Lorg/apache/hadoop/hbase/master/procedure/ServerProcedureInterface;)Lorg/apache/hadoop/hbase/master/procedure/ServerQueue;
      80: aload_1
      81: iload_2
      82: invokespecial #19                 // Method doAdd:(Lorg/apache/hadoop/hbase/master/procedure/FairQueue;Lorg/apache/hadoop/hbase/master/procedure/Queue;Lorg/apache/hadoop/hbase/procedure2/Procedure;Z)V
      85: goto          143
      88: aload_1
      89: invokestatic  #27                 // Method isPeerProcedure:(Lorg/apache/hadoop/hbase/procedure2/Procedure;)Z
      92: ifeq          116
      95: aload_0
      96: aload_0
      97: getfield      #6                  // Field peerRunQueue:Lorg/apache/hadoop/hbase/master/procedure/FairQueue;
     100: aload_0
     101: aload_1
     102: invokestatic  #28                 // Method getPeerId:(Lorg/apache/hadoop/hbase/procedure2/Procedure;)Ljava/lang/String;
     105: invokespecial #29                 // Method getPeerQueue:(Ljava/lang/String;)Lorg/apache/hadoop/hbase/master/procedure/PeerQueue;
     108: aload_1
     109: iload_2
     110: invokespecial #19                 // Method doAdd:(Lorg/apache/hadoop/hbase/master/procedure/FairQueue;Lorg/apache/hadoop/hbase/master/procedure/Queue;Lorg/apache/hadoop/hbase/procedure2/Procedure;Z)V
     113: goto          143
     116: new           #30                 // class java/lang/UnsupportedOperationException
     119: dup
     120: new           #31                 // class java/lang/StringBuilder
     123: dup
     124: invokespecial #32                 // Method java/lang/StringBuilder."<init>":()V
     127: ldc           #33                 // String RQs for non-table/non-server procedures are not implemented yet:
     129: invokevirtual #34                 // Method java/lang/StringBuilder.append:(Ljava/lang/String;)Ljava/lang/StringBuilder;
     132: aload_1
     133: invokevirtual #35                 // Method java/lang/StringBuilder.append:(Ljava/lang/Object;)Ljava/lang/StringBuilder;
     136: invokevirtual #36                 // Method java/lang/StringBuilder.toString:()Ljava/lang/String;
     139: invokespecial #37                 // Method java/lang/UnsupportedOperationException."<init>":(Ljava/lang/String;)V
     142: athrow
     143: return

  protected boolean queueHasRunnables();
    Code:
       0: aload_0
       1: getfield      #7                  // Field metaRunQueue:Lorg/apache/hadoop/hbase/master/procedure/FairQueue;
       4: invokevirtual #49                 // Method org/apache/hadoop/hbase/master/procedure/FairQueue.hasRunnables:()Z
       7: ifne          40
      10: aload_0
      11: getfield      #5                  // Field tableRunQueue:Lorg/apache/hadoop/hbase/master/procedure/FairQueue;
      14: invokevirtual #49                 // Method org/apache/hadoop/hbase/master/procedure/FairQueue.hasRunnables:()Z
      17: ifne          40
      20: aload_0
      21: getfield      #4                  // Field serverRunQueue:Lorg/apache/hadoop/hbase/master/procedure/FairQueue;
      24: invokevirtual #49                 // Method org/apache/hadoop/hbase/master/procedure/FairQueue.hasRunnables:()Z
      27: ifne          40
      30: aload_0
      31: getfield      #6                  // Field peerRunQueue:Lorg/apache/hadoop/hbase/master/procedure/FairQueue;
      34: invokevirtual #49                 // Method org/apache/hadoop/hbase/master/procedure/FairQueue.hasRunnables:()Z
      37: ifeq          44
      40: iconst_1
      41: goto          45
      44: iconst_0
      45: ireturn

  protected org.apache.hadoop.hbase.procedure2.Procedure dequeue();
    Code:
       0: aload_0
       1: aload_0
       2: getfield      #7                  // Field metaRunQueue:Lorg/apache/hadoop/hbase/master/procedure/FairQueue;
       5: invokespecial #50                 // Method doPoll:(Lorg/apache/hadoop/hbase/master/procedure/FairQueue;)Lorg/apache/hadoop/hbase/procedure2/Procedure;
       8: astore_1
       9: aload_1
      10: ifnonnull     22
      13: aload_0
      14: aload_0
      15: getfield      #4                  // Field serverRunQueue:Lorg/apache/hadoop/hbase/master/procedure/FairQueue;
      18: invokespecial #50                 // Method doPoll:(Lorg/apache/hadoop/hbase/master/procedure/FairQueue;)Lorg/apache/hadoop/hbase/procedure2/Procedure;
      21: astore_1
      22: aload_1
      23: ifnonnull     35
      26: aload_0
      27: aload_0
      28: getfield      #6                  // Field peerRunQueue:Lorg/apache/hadoop/hbase/master/procedure/FairQueue;
      31: invokespecial #50                 // Method doPoll:(Lorg/apache/hadoop/hbase/master/procedure/FairQueue;)Lorg/apache/hadoop/hbase/procedure2/Procedure;
      34: astore_1
      35: aload_1
      36: ifnonnull     48
      39: aload_0
      40: aload_0
      41: getfield      #5                  // Field tableRunQueue:Lorg/apache/hadoop/hbase/master/procedure/FairQueue;
      44: invokespecial #50                 // Method doPoll:(Lorg/apache/hadoop/hbase/master/procedure/FairQueue;)Lorg/apache/hadoop/hbase/procedure2/Procedure;
      47: astore_1
      48: aload_1
      49: areturn

  public java.util.List<org.apache.hadoop.hbase.procedure2.LockedResource> getLocks();
    Code:
       0: aload_0
       1: invokevirtual #62                 // Method schedLock:()V
       4: aload_0
       5: getfield      #15                 // Field locking:Lorg/apache/hadoop/hbase/master/procedure/SchemaLocking;
       8: invokevirtual #63                 // Method org/apache/hadoop/hbase/master/procedure/SchemaLocking.getLocks:()Ljava/util/List;
      11: astore_1
      12: aload_0
      13: invokevirtual #64                 // Method schedUnlock:()V
      16: aload_1
      17: areturn
      18: astore_2
      19: aload_0
      20: invokevirtual #64                 // Method schedUnlock:()V
      23: aload_2
      24: athrow
    Exception table:
       from    to  target type
           4    12    18   any

  public org.apache.hadoop.hbase.procedure2.LockedResource getLockResource(org.apache.hadoop.hbase.procedure2.LockedResourceType, java.lang.String);
    Code:
       0: aload_0
       1: invokevirtual #62                 // Method schedLock:()V
       4: aload_0
       5: getfield      #15                 // Field locking:Lorg/apache/hadoop/hbase/master/procedure/SchemaLocking;
       8: aload_1
       9: aload_2
      10: invokevirtual #65                 // Method org/apache/hadoop/hbase/master/procedure/SchemaLocking.getLockResource:(Lorg/apache/hadoop/hbase/procedure2/LockedResourceType;Ljava/lang/String;)Lorg/apache/hadoop/hbase/procedure2/LockedResource;
      13: astore_3
      14: aload_0
      15: invokevirtual #64                 // Method schedUnlock:()V
      18: aload_3
      19: areturn
      20: astore        4
      22: aload_0
      23: invokevirtual #64                 // Method schedUnlock:()V
      26: aload         4
      28: athrow
    Exception table:
       from    to  target type
           4    14    20   any
          20    22    20   any

  public void clear();
    Code:
       0: aload_0
       1: invokevirtual #62                 // Method schedLock:()V
       4: aload_0
       5: invokespecial #66                 // Method clearQueue:()V
       8: aload_0
       9: getfield      #15                 // Field locking:Lorg/apache/hadoop/hbase/master/procedure/SchemaLocking;
      12: invokevirtual #67                 // Method org/apache/hadoop/hbase/master/procedure/SchemaLocking.clear:()V
      15: aload_0
      16: invokevirtual #64                 // Method schedUnlock:()V
      19: goto          29
      22: astore_1
      23: aload_0
      24: invokevirtual #64                 // Method schedUnlock:()V
      27: aload_1
      28: athrow
      29: return
    Exception table:
       from    to  target type
           4    15    22   any

  protected int queueSize();
    Code:
       0: iconst_0
       1: istore_1
       2: aload_0
       3: getfield      #9                  // Field serverBuckets:[Lorg/apache/hadoop/hbase/master/procedure/ServerQueue;
       6: astore_2
       7: aload_2
       8: arraylength
       9: istore_3
      10: iconst_0
      11: istore        4
      13: iload         4
      15: iload_3
      16: if_icmpge     40
      19: aload_2
      20: iload         4
      22: aaload
      23: astore        5
      25: iload_1
      26: aload_0
      27: aload         5
      29: invokespecial #87                 // Method queueSize:(Lorg/apache/hadoop/hbase/master/procedure/Queue;)I
      32: iadd
      33: istore_1
      34: iinc          4, 1
      37: goto          13
      40: iload_1
      41: aload_0
      42: aload_0
      43: getfield      #10                 // Field tableMap:Lorg/apache/hadoop/hbase/master/procedure/TableQueue;
      46: invokespecial #87                 // Method queueSize:(Lorg/apache/hadoop/hbase/master/procedure/Queue;)I
      49: iadd
      50: istore_1
      51: iload_1
      52: aload_0
      53: aload_0
      54: getfield      #11                 // Field peerMap:Lorg/apache/hadoop/hbase/master/procedure/PeerQueue;
      57: invokespecial #87                 // Method queueSize:(Lorg/apache/hadoop/hbase/master/procedure/Queue;)I
      60: iadd
      61: istore_1
      62: iload_1
      63: aload_0
      64: aload_0
      65: getfield      #12                 // Field metaMap:Lorg/apache/hadoop/hbase/master/procedure/MetaQueue;
      68: invokespecial #87                 // Method queueSize:(Lorg/apache/hadoop/hbase/master/procedure/Queue;)I
      71: iadd
      72: istore_1
      73: iload_1
      74: ireturn

  public void completionCleanup(org.apache.hadoop.hbase.procedure2.Procedure);
    Code:
       0: aload_1
       1: instanceof    #88                 // class org/apache/hadoop/hbase/master/procedure/TableProcedureInterface
       4: ifeq          104
       7: aload_1
       8: checkcast     #88                 // class org/apache/hadoop/hbase/master/procedure/TableProcedureInterface
      11: astore_2
      12: aload_1
      13: invokevirtual #89                 // Method org/apache/hadoop/hbase/procedure2/Procedure.hasException:()Z
      16: ifeq          66
      19: aload_1
      20: invokevirtual #90                 // Method org/apache/hadoop/hbase/procedure2/Procedure.getException:()Lorg/apache/hadoop/hbase/procedure2/RemoteProcedureException;
      23: invokevirtual #91                 // Method org/apache/hadoop/hbase/procedure2/RemoteProcedureException.unwrapRemoteException:()Ljava/lang/Exception;
      26: astore        4
      28: aload_2
      29: invokeinterface #92,  1           // InterfaceMethod org/apache/hadoop/hbase/master/procedure/TableProcedureInterface.getTableOperationType:()Lorg/apache/hadoop/hbase/master/procedure/TableProcedureInterface$TableOperationType;
      34: getstatic     #93                 // Field org/apache/hadoop/hbase/master/procedure/TableProcedureInterface$TableOperationType.CREATE:Lorg/apache/hadoop/hbase/master/procedure/TableProcedureInterface$TableOperationType;
      37: if_acmpne     57
      40: aload         4
      42: instanceof    #94                 // class org/apache/hadoop/hbase/TableExistsException
      45: ifne          52
      48: iconst_1
      49: goto          53
      52: iconst_0
      53: istore_3
      54: goto          63
      57: aload         4
      59: instanceof    #95                 // class org/apache/hadoop/hbase/TableNotFoundException
      62: istore_3
      63: goto          84
      66: aload_2
      67: invokeinterface #92,  1           // InterfaceMethod org/apache/hadoop/hbase/master/procedure/TableProcedureInterface.getTableOperationType:()Lorg/apache/hadoop/hbase/master/procedure/TableProcedureInterface$TableOperationType;
      72: getstatic     #96                 // Field org/apache/hadoop/hbase/master/procedure/TableProcedureInterface$TableOperationType.DELETE:Lorg/apache/hadoop/hbase/master/procedure/TableProcedureInterface$TableOperationType;
      75: if_acmpne     82
      78: iconst_1
      79: goto          83
      82: iconst_0
      83: istore_3
      84: iload_3
      85: ifeq          101
      88: aload_0
      89: aload_2
      90: invokeinterface #97,  1           // InterfaceMethod org/apache/hadoop/hbase/master/procedure/TableProcedureInterface.getTableName:()Lorg/apache/hadoop/hbase/TableName;
      95: aload_1
      96: invokevirtual #98                 // Method markTableAsDeleted:(Lorg/apache/hadoop/hbase/TableName;Lorg/apache/hadoop/hbase/procedure2/Procedure;)Z
      99: pop
     100: return
     101: goto          143
     104: aload_1
     105: instanceof    #99                 // class org/apache/hadoop/hbase/master/procedure/PeerProcedureInterface
     108: ifeq          123
     111: aload_0
     112: aload_1
     113: invokestatic  #28                 // Method getPeerId:(Lorg/apache/hadoop/hbase/procedure2/Procedure;)Ljava/lang/String;
     116: aload_1
     117: invokespecial #100                // Method tryCleanupPeerQueue:(Ljava/lang/String;Lorg/apache/hadoop/hbase/procedure2/Procedure;)V
     120: goto          143
     123: aload_1
     124: instanceof    #24                 // class org/apache/hadoop/hbase/master/procedure/ServerProcedureInterface
     127: ifeq          142
     130: aload_0
     131: aload_1
     132: invokestatic  #101                // Method getServerName:(Lorg/apache/hadoop/hbase/procedure2/Procedure;)Lorg/apache/hadoop/hbase/ServerName;
     135: aload_1
     136: invokespecial #102                // Method tryCleanupServerQueue:(Lorg/apache/hadoop/hbase/ServerName;Lorg/apache/hadoop/hbase/procedure2/Procedure;)V
     139: goto          143
     142: return
     143: return

  public boolean waitTableExclusiveLock(org.apache.hadoop.hbase.procedure2.Procedure<?>, org.apache.hadoop.hbase.TableName);
    Code:
       0: aload_0
       1: invokevirtual #62                 // Method schedLock:()V
       4: aload_2
       5: invokevirtual #116                // Method org/apache/hadoop/hbase/TableName.getNamespaceAsString:()Ljava/lang/String;
       8: astore_3
       9: aload_0
      10: getfield      #15                 // Field locking:Lorg/apache/hadoop/hbase/master/procedure/SchemaLocking;
      13: aload_3
      14: invokevirtual #117                // Method org/apache/hadoop/hbase/master/procedure/SchemaLocking.getNamespaceLock:(Ljava/lang/String;)Lorg/apache/hadoop/hbase/procedure2/LockAndQueue;
      17: astore        4
      19: aload_0
      20: getfield      #15                 // Field locking:Lorg/apache/hadoop/hbase/master/procedure/SchemaLocking;
      23: aload_2
      24: invokevirtual #115                // Method org/apache/hadoop/hbase/master/procedure/SchemaLocking.getTableLock:(Lorg/apache/hadoop/hbase/TableName;)Lorg/apache/hadoop/hbase/procedure2/LockAndQueue;
      27: astore        5
      29: aload         4
      31: aload_1
      32: invokevirtual #156                // Method org/apache/hadoop/hbase/procedure2/LockAndQueue.trySharedLock:(Lorg/apache/hadoop/hbase/procedure2/Procedure;)Z
      35: ifne          63
      38: aload_0
      39: aload         4
      41: aload_1
      42: invokevirtual #157                // Method waitProcedure:(Lorg/apache/hadoop/hbase/procedure2/LockAndQueue;Lorg/apache/hadoop/hbase/procedure2/Procedure;)V
      45: aload_0
      46: getstatic     #158                // Field org/apache/hadoop/hbase/procedure2/LockedResourceType.NAMESPACE:Lorg/apache/hadoop/hbase/procedure2/LockedResourceType;
      49: aload_3
      50: invokespecial #159                // Method logLockedResource:(Lorg/apache/hadoop/hbase/procedure2/LockedResourceType;Ljava/lang/String;)V
      53: iconst_1
      54: istore        6
      56: aload_0
      57: invokevirtual #64                 // Method schedUnlock:()V
      60: iload         6
      62: ireturn
      63: aload         5
      65: aload_1
      66: invokevirtual #128                // Method org/apache/hadoop/hbase/procedure2/LockAndQueue.tryExclusiveLock:(Lorg/apache/hadoop/hbase/procedure2/Procedure;)Z
      69: ifne          106
      72: aload         4
      74: invokevirtual #160                // Method org/apache/hadoop/hbase/procedure2/LockAndQueue.releaseSharedLock:()Z
      77: pop
      78: aload_0
      79: aload         5
      81: aload_1
      82: invokevirtual #157                // Method waitProcedure:(Lorg/apache/hadoop/hbase/procedure2/LockAndQueue;Lorg/apache/hadoop/hbase/procedure2/Procedure;)V
      85: aload_0
      86: getstatic     #161                // Field org/apache/hadoop/hbase/procedure2/LockedResourceType.TABLE:Lorg/apache/hadoop/hbase/procedure2/LockedResourceType;
      89: aload_2
      90: invokevirtual #162                // Method org/apache/hadoop/hbase/TableName.getNameAsString:()Ljava/lang/String;
      93: invokespecial #159                // Method logLockedResource:(Lorg/apache/hadoop/hbase/procedure2/LockedResourceType;Ljava/lang/String;)V
      96: iconst_1
      97: istore        6
      99: aload_0
     100: invokevirtual #64                 // Method schedUnlock:()V
     103: iload         6
     105: ireturn
     106: aload_0
     107: getfield      #5                  // Field tableRunQueue:Lorg/apache/hadoop/hbase/master/procedure/FairQueue;
     110: aload_0
     111: aload_2
     112: invokespecial #22                 // Method getTableQueue:(Lorg/apache/hadoop/hbase/TableName;)Lorg/apache/hadoop/hbase/master/procedure/TableQueue;
     115: aload_1
     116: invokedynamic #163,  0            // InvokeDynamic #9:get:(Lorg/apache/hadoop/hbase/procedure2/Procedure;)Ljava/util/function/Supplier;
     121: invokestatic  #60                 // Method removeFromRunQueue:(Lorg/apache/hadoop/hbase/master/procedure/FairQueue;Lorg/apache/hadoop/hbase/master/procedure/Queue;Ljava/util/function/Supplier;)V
     124: iconst_0
     125: istore        6
     127: aload_0
     128: invokevirtual #64                 // Method schedUnlock:()V
     131: iload         6
     133: ireturn
     134: astore        7
     136: aload_0
     137: invokevirtual #64                 // Method schedUnlock:()V
     140: aload         7
     142: athrow
    Exception table:
       from    to  target type
           4    56   134   any
          63    99   134   any
         106   127   134   any
         134   136   134   any

  public void wakeTableExclusiveLock(org.apache.hadoop.hbase.procedure2.Procedure<?>, org.apache.hadoop.hbase.TableName);
    Code:
       0: aload_0
       1: invokevirtual #62                 // Method schedLock:()V
       4: aload_0
       5: getfield      #15                 // Field locking:Lorg/apache/hadoop/hbase/master/procedure/SchemaLocking;
       8: aload_2
       9: invokevirtual #116                // Method org/apache/hadoop/hbase/TableName.getNamespaceAsString:()Ljava/lang/String;
      12: invokevirtual #117                // Method org/apache/hadoop/hbase/master/procedure/SchemaLocking.getNamespaceLock:(Ljava/lang/String;)Lorg/apache/hadoop/hbase/procedure2/LockAndQueue;
      15: astore_3
      16: aload_0
      17: getfield      #15                 // Field locking:Lorg/apache/hadoop/hbase/master/procedure/SchemaLocking;
      20: aload_2
      21: invokevirtual #115                // Method org/apache/hadoop/hbase/master/procedure/SchemaLocking.getTableLock:(Lorg/apache/hadoop/hbase/TableName;)Lorg/apache/hadoop/hbase/procedure2/LockAndQueue;
      24: astore        4
      26: iconst_0
      27: istore        5
      29: aload         4
      31: aload_1
      32: invokevirtual #164                // Method org/apache/hadoop/hbase/procedure2/LockAndQueue.releaseExclusiveLock:(Lorg/apache/hadoop/hbase/procedure2/Procedure;)Z
      35: ifeq          49
      38: iload         5
      40: aload_0
      41: aload         4
      43: invokevirtual #165                // Method wakeWaitingProcedures:(Lorg/apache/hadoop/hbase/procedure2/LockAndQueue;)I
      46: iadd
      47: istore        5
      49: aload_3
      50: invokevirtual #160                // Method org/apache/hadoop/hbase/procedure2/LockAndQueue.releaseSharedLock:()Z
      53: ifeq          66
      56: iload         5
      58: aload_0
      59: aload_3
      60: invokevirtual #165                // Method wakeWaitingProcedures:(Lorg/apache/hadoop/hbase/procedure2/LockAndQueue;)I
      63: iadd
      64: istore        5
      66: aload_0
      67: getfield      #5                  // Field tableRunQueue:Lorg/apache/hadoop/hbase/master/procedure/FairQueue;
      70: aload_0
      71: aload_2
      72: invokespecial #22                 // Method getTableQueue:(Lorg/apache/hadoop/hbase/TableName;)Lorg/apache/hadoop/hbase/master/procedure/TableQueue;
      75: aload_1
      76: invokedynamic #166,  0            // InvokeDynamic #10:get:(Lorg/apache/hadoop/hbase/procedure2/Procedure;)Ljava/util/function/Supplier;
      81: invokestatic  #48                 // Method addToRunQueue:(Lorg/apache/hadoop/hbase/master/procedure/FairQueue;Lorg/apache/hadoop/hbase/master/procedure/Queue;Ljava/util/function/Supplier;)V
      84: aload_0
      85: iload         5
      87: invokevirtual #167                // Method wakePollIfNeeded:(I)V
      90: aload_0
      91: invokevirtual #64                 // Method schedUnlock:()V
      94: goto          106
      97: astore        6
      99: aload_0
     100: invokevirtual #64                 // Method schedUnlock:()V
     103: aload         6
     105: athrow
     106: return
    Exception table:
       from    to  target type
           4    90    97   any
          97    99    97   any

  public boolean waitTableSharedLock(org.apache.hadoop.hbase.procedure2.Procedure<?>, org.apache.hadoop.hbase.TableName);
    Code:
       0: aload_0
       1: aload_1
       2: aload_2
       3: invokespecial #168                // Method waitTableQueueSharedLock:(Lorg/apache/hadoop/hbase/procedure2/Procedure;Lorg/apache/hadoop/hbase/TableName;)Lorg/apache/hadoop/hbase/master/procedure/TableQueue;
       6: ifnonnull     13
       9: iconst_1
      10: goto          14
      13: iconst_0
      14: ireturn

  public void wakeTableSharedLock(org.apache.hadoop.hbase.procedure2.Procedure<?>, org.apache.hadoop.hbase.TableName);
    Code:
       0: aload_0
       1: invokevirtual #62                 // Method schedLock:()V
       4: aload_0
       5: getfield      #15                 // Field locking:Lorg/apache/hadoop/hbase/master/procedure/SchemaLocking;
       8: aload_2
       9: invokevirtual #116                // Method org/apache/hadoop/hbase/TableName.getNamespaceAsString:()Ljava/lang/String;
      12: invokevirtual #117                // Method org/apache/hadoop/hbase/master/procedure/SchemaLocking.getNamespaceLock:(Ljava/lang/String;)Lorg/apache/hadoop/hbase/procedure2/LockAndQueue;
      15: astore_3
      16: aload_0
      17: getfield      #15                 // Field locking:Lorg/apache/hadoop/hbase/master/procedure/SchemaLocking;
      20: aload_2
      21: invokevirtual #115                // Method org/apache/hadoop/hbase/master/procedure/SchemaLocking.getTableLock:(Lorg/apache/hadoop/hbase/TableName;)Lorg/apache/hadoop/hbase/procedure2/LockAndQueue;
      24: astore        4
      26: iconst_0
      27: istore        5
      29: aload         4
      31: invokevirtual #160                // Method org/apache/hadoop/hbase/procedure2/LockAndQueue.releaseSharedLock:()Z
      34: ifeq          66
      37: aload_0
      38: getfield      #5                  // Field tableRunQueue:Lorg/apache/hadoop/hbase/master/procedure/FairQueue;
      41: aload_0
      42: aload_2
      43: invokespecial #22                 // Method getTableQueue:(Lorg/apache/hadoop/hbase/TableName;)Lorg/apache/hadoop/hbase/master/procedure/TableQueue;
      46: aload_1
      47: invokedynamic #169,  0            // InvokeDynamic #11:get:(Lorg/apache/hadoop/hbase/procedure2/Procedure;)Ljava/util/function/Supplier;
      52: invokestatic  #48                 // Method addToRunQueue:(Lorg/apache/hadoop/hbase/master/procedure/FairQueue;Lorg/apache/hadoop/hbase/master/procedure/Queue;Ljava/util/function/Supplier;)V
      55: iload         5
      57: aload_0
      58: aload         4
      60: invokevirtual #165                // Method wakeWaitingProcedures:(Lorg/apache/hadoop/hbase/procedure2/LockAndQueue;)I
      63: iadd
      64: istore        5
      66: aload_3
      67: invokevirtual #160                // Method org/apache/hadoop/hbase/procedure2/LockAndQueue.releaseSharedLock:()Z
      70: ifeq          83
      73: iload         5
      75: aload_0
      76: aload_3
      77: invokevirtual #165                // Method wakeWaitingProcedures:(Lorg/apache/hadoop/hbase/procedure2/LockAndQueue;)I
      80: iadd
      81: istore        5
      83: aload_0
      84: iload         5
      86: invokevirtual #167                // Method wakePollIfNeeded:(I)V
      89: aload_0
      90: invokevirtual #64                 // Method schedUnlock:()V
      93: goto          105
      96: astore        6
      98: aload_0
      99: invokevirtual #64                 // Method schedUnlock:()V
     102: aload         6
     104: athrow
     105: return
    Exception table:
       from    to  target type
           4    89    96   any
          96    98    96   any

  boolean markTableAsDeleted(org.apache.hadoop.hbase.TableName, org.apache.hadoop.hbase.procedure2.Procedure<?>);
    Code:
       0: aload_0
       1: invokevirtual #62                 // Method schedLock:()V
       4: aload_0
       5: aload_1
       6: invokespecial #22                 // Method getTableQueue:(Lorg/apache/hadoop/hbase/TableName;)Lorg/apache/hadoop/hbase/master/procedure/TableQueue;
       9: astore_3
      10: aload_0
      11: getfield      #15                 // Field locking:Lorg/apache/hadoop/hbase/master/procedure/SchemaLocking;
      14: aload_1
      15: invokevirtual #115                // Method org/apache/hadoop/hbase/master/procedure/SchemaLocking.getTableLock:(Lorg/apache/hadoop/hbase/TableName;)Lorg/apache/hadoop/hbase/procedure2/LockAndQueue;
      18: astore        4
      20: aload_3
      21: ifnonnull     34
      24: iconst_1
      25: istore        5
      27: aload_0
      28: invokevirtual #64                 // Method schedUnlock:()V
      31: iload         5
      33: ireturn
      34: aload_3
      35: invokevirtual #170                // Method org/apache/hadoop/hbase/master/procedure/TableQueue.isEmpty:()Z
      38: ifeq          73
      41: aload         4
      43: aload_2
      44: invokevirtual #128                // Method org/apache/hadoop/hbase/procedure2/LockAndQueue.tryExclusiveLock:(Lorg/apache/hadoop/hbase/procedure2/Procedure;)Z
      47: ifeq          73
      50: aload_3
      51: invokestatic  #108                // Method org/apache/hadoop/hbase/util/AvlUtil$AvlIterableList.isLinked:(Lorg/apache/hadoop/hbase/util/AvlUtil$AvlLinkedNode;)Z
      54: ifeq          65
      57: aload_0
      58: getfield      #5                  // Field tableRunQueue:Lorg/apache/hadoop/hbase/master/procedure/FairQueue;
      61: aload_3
      62: invokevirtual #111                // Method org/apache/hadoop/hbase/master/procedure/FairQueue.remove:(Lorg/apache/hadoop/hbase/master/procedure/Queue;)V
      65: aload_0
      66: aload_1
      67: invokespecial #171                // Method removeTableQueue:(Lorg/apache/hadoop/hbase/TableName;)V
      70: goto          83
      73: iconst_0
      74: istore        5
      76: aload_0
      77: invokevirtual #64                 // Method schedUnlock:()V
      80: iload         5
      82: ireturn
      83: aload_0
      84: invokevirtual #64                 // Method schedUnlock:()V
      87: goto          99
      90: astore        6
      92: aload_0
      93: invokevirtual #64                 // Method schedUnlock:()V
      96: aload         6
      98: athrow
      99: iconst_1
     100: ireturn
    Exception table:
       from    to  target type
           4    27    90   any
          34    76    90   any
          90    92    90   any

  public boolean waitRegion(org.apache.hadoop.hbase.procedure2.Procedure<?>, org.apache.hadoop.hbase.client.RegionInfo);
    Code:
       0: aload_0
       1: aload_1
       2: aload_2
       3: invokeinterface #172,  1          // InterfaceMethod org/apache/hadoop/hbase/client/RegionInfo.getTable:()Lorg/apache/hadoop/hbase/TableName;
       8: iconst_1
       9: anewarray     #173                // class org/apache/hadoop/hbase/client/RegionInfo
      12: dup
      13: iconst_0
      14: aload_2
      15: aastore
      16: invokevirtual #174                // Method waitRegions:(Lorg/apache/hadoop/hbase/procedure2/Procedure;Lorg/apache/hadoop/hbase/TableName;[Lorg/apache/hadoop/hbase/client/RegionInfo;)Z
      19: ireturn

  public boolean waitRegions(org.apache.hadoop.hbase.procedure2.Procedure<?>, org.apache.hadoop.hbase.TableName, org.apache.hadoop.hbase.client.RegionInfo...);
    Code:
       0: aload_3
       1: getstatic     #175                // Field org/apache/hadoop/hbase/client/RegionInfo.COMPARATOR:Ljava/util/Comparator;
       4: invokestatic  #176                // Method java/util/Arrays.sort:([Ljava/lang/Object;Ljava/util/Comparator;)V
       7: aload_0
       8: invokevirtual #62                 // Method schedLock:()V
      11: getstatic     #72                 // Field $assertionsDisabled:Z
      14: ifne          29
      17: aload_2
      18: ifnonnull     29
      21: new           #74                 // class java/lang/AssertionError
      24: dup
      25: invokespecial #177                // Method java/lang/AssertionError."<init>":()V
      28: athrow
      29: aload_0
      30: aload_1
      31: aload_2
      32: invokevirtual #178                // Method waitTableSharedLock:(Lorg/apache/hadoop/hbase/procedure2/Procedure;Lorg/apache/hadoop/hbase/TableName;)Z
      35: ifeq          48
      38: iconst_1
      39: istore        4
      41: aload_0
      42: invokevirtual #64                 // Method schedUnlock:()V
      45: iload         4
      47: ireturn
      48: iconst_1
      49: istore        4
      51: aload_3
      52: arraylength
      53: anewarray     #179                // class org/apache/hadoop/hbase/procedure2/LockAndQueue
      56: astore        5
      58: iconst_0
      59: istore        6
      61: iload         6
      63: aload_3
      64: arraylength
      65: if_icmpge     331
      68: getstatic     #72                 // Field $assertionsDisabled:Z
      71: ifne          89
      74: aload_3
      75: iload         6
      77: aaload
      78: ifnonnull     89
      81: new           #74                 // class java/lang/AssertionError
      84: dup
      85: invokespecial #177                // Method java/lang/AssertionError."<init>":()V
      88: athrow
      89: getstatic     #72                 // Field $assertionsDisabled:Z
      92: ifne          115
      95: aload_3
      96: iload         6
      98: aaload
      99: invokeinterface #172,  1          // InterfaceMethod org/apache/hadoop/hbase/client/RegionInfo.getTable:()Lorg/apache/hadoop/hbase/TableName;
     104: ifnonnull     115
     107: new           #74                 // class java/lang/AssertionError
     110: dup
     111: invokespecial #177                // Method java/lang/AssertionError."<init>":()V
     114: athrow
     115: getstatic     #72                 // Field $assertionsDisabled:Z
     118: ifne          171
     121: aload_3
     122: iload         6
     124: aaload
     125: invokeinterface #172,  1          // InterfaceMethod org/apache/hadoop/hbase/client/RegionInfo.getTable:()Lorg/apache/hadoop/hbase/TableName;
     130: aload_2
     131: invokevirtual #180                // Method org/apache/hadoop/hbase/TableName.equals:(Ljava/lang/Object;)Z
     134: ifne          171
     137: new           #74                 // class java/lang/AssertionError
     140: dup
     141: new           #31                 // class java/lang/StringBuilder
     144: dup
     145: invokespecial #32                 // Method java/lang/StringBuilder."<init>":()V
     148: aload_3
     149: iload         6
     151: aaload
     152: invokevirtual #35                 // Method java/lang/StringBuilder.append:(Ljava/lang/Object;)Ljava/lang/StringBuilder;
     155: ldc           #181                // String
     157: invokevirtual #34                 // Method java/lang/StringBuilder.append:(Ljava/lang/String;)Ljava/lang/StringBuilder;
     160: aload_1
     161: invokevirtual #35                 // Method java/lang/StringBuilder.append:(Ljava/lang/Object;)Ljava/lang/StringBuilder;
     164: invokevirtual #36                 // Method java/lang/StringBuilder.toString:()Ljava/lang/String;
     167: invokespecial #77                 // Method java/lang/AssertionError."<init>":(Ljava/lang/Object;)V
     170: athrow
     171: getstatic     #72                 // Field $assertionsDisabled:Z
     174: ifne          225
     177: iload         6
     179: ifeq          225
     182: aload_3
     183: iload         6
     185: aaload
     186: aload_3
     187: iload         6
     189: iconst_1
     190: isub
     191: aaload
     192: if_acmpne     225
     195: new           #74                 // class java/lang/AssertionError
     198: dup
     199: new           #31                 // class java/lang/StringBuilder
     202: dup
     203: invokespecial #32                 // Method java/lang/StringBuilder."<init>":()V
     206: ldc           #182                // String duplicate region:
     208: invokevirtual #34                 // Method java/lang/StringBuilder.append:(Ljava/lang/String;)Ljava/lang/StringBuilder;
     211: aload_3
     212: iload         6
     214: aaload
     215: invokevirtual #35                 // Method java/lang/StringBuilder.append:(Ljava/lang/Object;)Ljava/lang/StringBuilder;
     218: invokevirtual #36                 // Method java/lang/StringBuilder.toString:()Ljava/lang/String;
     221: invokespecial #77                 // Method java/lang/AssertionError."<init>":(Ljava/lang/Object;)V
     224: athrow
     225: aload         5
     227: iload         6
     229: aload_0
     230: getfield      #15                 // Field locking:Lorg/apache/hadoop/hbase/master/procedure/SchemaLocking;
     233: aload_3
     234: iload         6
     236: aaload
     237: invokeinterface #183,  1          // InterfaceMethod org/apache/hadoop/hbase/client/RegionInfo.getEncodedName:()Ljava/lang/String;
     242: invokevirtual #184                // Method org/apache/hadoop/hbase/master/procedure/SchemaLocking.getRegionLock:(Ljava/lang/String;)Lorg/apache/hadoop/hbase/procedure2/LockAndQueue;
     245: aastore
     246: aload         5
     248: iload         6
     250: aaload
     251: aload_1
     252: invokevirtual #128                // Method org/apache/hadoop/hbase/procedure2/LockAndQueue.tryExclusiveLock:(Lorg/apache/hadoop/hbase/procedure2/Procedure;)Z
     255: ifne          314
     258: getstatic     #103                // Field LOG:Lorg/slf4j/Logger;
     261: ldc           #185                // String Waiting on xlock for {} held by pid={}
     263: aload_1
     264: aload         5
     266: iload         6
     268: aaload
     269: invokevirtual #186                // Method org/apache/hadoop/hbase/procedure2/LockAndQueue.getExclusiveLockProcIdOwner:()J
     272: invokestatic  #187                // Method java/lang/Long.valueOf:(J)Ljava/lang/Long;
     275: invokeinterface #188,  4          // InterfaceMethod org/slf4j/Logger.info:(Ljava/lang/String;Ljava/lang/Object;Ljava/lang/Object;)V
     280: aload_0
     281: aload         5
     283: iload         6
     285: aaload
     286: aload_1
     287: invokevirtual #157                // Method waitProcedure:(Lorg/apache/hadoop/hbase/procedure2/LockAndQueue;Lorg/apache/hadoop/hbase/procedure2/Procedure;)V
     290: iconst_0
     291: istore        4
     293: iload         6
     295: iinc          6, -1
     298: ifle          331
     301: aload         5
     303: iload         6
     305: aaload
     306: aload_1
     307: invokevirtual #164                // Method org/apache/hadoop/hbase/procedure2/LockAndQueue.releaseExclusiveLock:(Lorg/apache/hadoop/hbase/procedure2/Procedure;)Z
     310: pop
     311: goto          293
     314: getstatic     #103                // Field LOG:Lorg/slf4j/Logger;
     317: ldc           #189                // String Took xlock for {}
     319: aload_1
     320: invokeinterface #190,  3          // InterfaceMethod org/slf4j/Logger.info:(Ljava/lang/String;Ljava/lang/Object;)V
     325: iinc          6, 1
     328: goto          61
     331: iload         4
     333: ifne          342
     336: aload_0
     337: aload_1
     338: aload_2
     339: invokevirtual #191                // Method wakeTableSharedLock:(Lorg/apache/hadoop/hbase/procedure2/Procedure;Lorg/apache/hadoop/hbase/TableName;)V
     342: iload         4
     344: ifne          351
     347: iconst_1
     348: goto          352
     351: iconst_0
     352: istore        6
     354: aload_0
     355: invokevirtual #64                 // Method schedUnlock:()V
     358: iload         6
     360: ireturn
     361: astore        7
     363: aload_0
     364: invokevirtual #64                 // Method schedUnlock:()V
     367: aload         7
     369: athrow
    Exception table:
       from    to  target type
          11    41   361   any
          48   354   361   any
         361   363   361   any

  public void wakeRegion(org.apache.hadoop.hbase.procedure2.Procedure<?>, org.apache.hadoop.hbase.client.RegionInfo);
    Code:
       0: aload_0
       1: aload_1
       2: aload_2
       3: invokeinterface #172,  1          // InterfaceMethod org/apache/hadoop/hbase/client/RegionInfo.getTable:()Lorg/apache/hadoop/hbase/TableName;
       8: iconst_1
       9: anewarray     #173                // class org/apache/hadoop/hbase/client/RegionInfo
      12: dup
      13: iconst_0
      14: aload_2
      15: aastore
      16: invokevirtual #192                // Method wakeRegions:(Lorg/apache/hadoop/hbase/procedure2/Procedure;Lorg/apache/hadoop/hbase/TableName;[Lorg/apache/hadoop/hbase/client/RegionInfo;)V
      19: return

  public void wakeRegions(org.apache.hadoop.hbase.procedure2.Procedure<?>, org.apache.hadoop.hbase.TableName, org.apache.hadoop.hbase.client.RegionInfo...);
    Code:
       0: aload_3
       1: getstatic     #175                // Field org/apache/hadoop/hbase/client/RegionInfo.COMPARATOR:Ljava/util/Comparator;
       4: invokestatic  #176                // Method java/util/Arrays.sort:([Ljava/lang/Object;Ljava/util/Comparator;)V
       7: aload_0
       8: invokevirtual #62                 // Method schedLock:()V
      11: iconst_0
      12: istore        4
      14: aload_3
      15: arraylength
      16: anewarray     #193                // class org/apache/hadoop/hbase/procedure2/Procedure
      19: astore        5
      21: iconst_0
      22: istore        6
      24: iload         6
      26: aload_3
      27: arraylength
      28: if_icmpge     189
      31: getstatic     #72                 // Field $assertionsDisabled:Z
      34: ifne          61
      37: aload_3
      38: iload         6
      40: aaload
      41: invokeinterface #172,  1          // InterfaceMethod org/apache/hadoop/hbase/client/RegionInfo.getTable:()Lorg/apache/hadoop/hbase/TableName;
      46: aload_2
      47: invokevirtual #180                // Method org/apache/hadoop/hbase/TableName.equals:(Ljava/lang/Object;)Z
      50: ifne          61
      53: new           #74                 // class java/lang/AssertionError
      56: dup
      57: invokespecial #177                // Method java/lang/AssertionError."<init>":()V
      60: athrow
      61: getstatic     #72                 // Field $assertionsDisabled:Z
      64: ifne          115
      67: iload         6
      69: ifeq          115
      72: aload_3
      73: iload         6
      75: aaload
      76: aload_3
      77: iload         6
      79: iconst_1
      80: isub
      81: aaload
      82: if_acmpne     115
      85: new           #74                 // class java/lang/AssertionError
      88: dup
      89: new           #31                 // class java/lang/StringBuilder
      92: dup
      93: invokespecial #32                 // Method java/lang/StringBuilder."<init>":()V
      96: ldc           #182                // String duplicate region:
      98: invokevirtual #34                 // Method java/lang/StringBuilder.append:(Ljava/lang/String;)Ljava/lang/StringBuilder;
     101: aload_3
     102: iload         6
     104: aaload
     105: invokevirtual #35                 // Method java/lang/StringBuilder.append:(Ljava/lang/Object;)Ljava/lang/StringBuilder;
     108: invokevirtual #36                 // Method java/lang/StringBuilder.toString:()Ljava/lang/String;
     111: invokespecial #77                 // Method java/lang/AssertionError."<init>":(Ljava/lang/Object;)V
     114: athrow
     115: aload_0
     116: getfield      #15                 // Field locking:Lorg/apache/hadoop/hbase/master/procedure/SchemaLocking;
     119: aload_3
     120: iload         6
     122: aaload
     123: invokeinterface #183,  1          // InterfaceMethod org/apache/hadoop/hbase/client/RegionInfo.getEncodedName:()Ljava/lang/String;
     128: invokevirtual #184                // Method org/apache/hadoop/hbase/master/procedure/SchemaLocking.getRegionLock:(Ljava/lang/String;)Lorg/apache/hadoop/hbase/procedure2/LockAndQueue;
     131: astore        7
     133: aload         7
     135: aload_1
     136: invokevirtual #164                // Method org/apache/hadoop/hbase/procedure2/LockAndQueue.releaseExclusiveLock:(Lorg/apache/hadoop/hbase/procedure2/Procedure;)Z
     139: ifeq          183
     142: aload         7
     144: invokevirtual #194                // Method org/apache/hadoop/hbase/procedure2/LockAndQueue.isWaitingQueueEmpty:()Z
     147: ifne          166
     150: aload         5
     152: iload         4
     154: iinc          4, 1
     157: aload         7
     159: invokevirtual #195                // Method org/apache/hadoop/hbase/procedure2/LockAndQueue.removeFirst:()Lorg/apache/hadoop/hbase/procedure2/Procedure;
     162: aastore
     163: goto          183
     166: aload_0
     167: getfield      #15                 // Field locking:Lorg/apache/hadoop/hbase/master/procedure/SchemaLocking;
     170: aload_3
     171: iload         6
     173: aaload
     174: invokeinterface #183,  1          // InterfaceMethod org/apache/hadoop/hbase/client/RegionInfo.getEncodedName:()Ljava/lang/String;
     179: invokevirtual #196                // Method org/apache/hadoop/hbase/master/procedure/SchemaLocking.removeRegionLock:(Ljava/lang/String;)Lorg/apache/hadoop/hbase/procedure2/LockAndQueue;
     182: pop
     183: iinc          6, 1
     186: goto          24
     189: iload         4
     191: iconst_1
     192: isub
     193: istore        6
     195: iload         6
     197: iflt          215
     200: aload_0
     201: aload         5
     203: iload         6
     205: aaload
     206: invokevirtual #197                // Method wakeProcedure:(Lorg/apache/hadoop/hbase/procedure2/Procedure;)V
     209: iinc          6, -1
     212: goto          195
     215: aload_0
     216: iload         4
     218: invokevirtual #167                // Method wakePollIfNeeded:(I)V
     221: aload_0
     222: aload_1
     223: aload_2
     224: invokevirtual #191                // Method wakeTableSharedLock:(Lorg/apache/hadoop/hbase/procedure2/Procedure;Lorg/apache/hadoop/hbase/TableName;)V
     227: aload_0
     228: invokevirtual #64                 // Method schedUnlock:()V
     231: goto          243
     234: astore        8
     236: aload_0
     237: invokevirtual #64                 // Method schedUnlock:()V
     240: aload         8
     242: athrow
     243: return
    Exception table:
       from    to  target type
          11   227   234   any
         234   236   234   any

  public boolean waitNamespaceExclusiveLock(org.apache.hadoop.hbase.procedure2.Procedure<?>, java.lang.String);
    Code:
       0: aload_0
       1: invokevirtual #62                 // Method schedLock:()V
       4: aload_0
       5: getfield      #15                 // Field locking:Lorg/apache/hadoop/hbase/master/procedure/SchemaLocking;
       8: getstatic     #198                // Field org/apache/hadoop/hbase/master/procedure/TableProcedureInterface.DUMMY_NAMESPACE_TABLE_NAME:Lorg/apache/hadoop/hbase/TableName;
      11: invokevirtual #115                // Method org/apache/hadoop/hbase/master/procedure/SchemaLocking.getTableLock:(Lorg/apache/hadoop/hbase/TableName;)Lorg/apache/hadoop/hbase/procedure2/LockAndQueue;
      14: astore_3
      15: aload_3
      16: aload_1
      17: invokevirtual #156                // Method org/apache/hadoop/hbase/procedure2/LockAndQueue.trySharedLock:(Lorg/apache/hadoop/hbase/procedure2/Procedure;)Z
      20: ifne          52
      23: aload_0
      24: aload_3
      25: aload_1
      26: invokevirtual #157                // Method waitProcedure:(Lorg/apache/hadoop/hbase/procedure2/LockAndQueue;Lorg/apache/hadoop/hbase/procedure2/Procedure;)V
      29: aload_0
      30: getstatic     #161                // Field org/apache/hadoop/hbase/procedure2/LockedResourceType.TABLE:Lorg/apache/hadoop/hbase/procedure2/LockedResourceType;
      33: getstatic     #198                // Field org/apache/hadoop/hbase/master/procedure/TableProcedureInterface.DUMMY_NAMESPACE_TABLE_NAME:Lorg/apache/hadoop/hbase/TableName;
      36: invokevirtual #162                // Method org/apache/hadoop/hbase/TableName.getNameAsString:()Ljava/lang/String;
      39: invokespecial #159                // Method logLockedResource:(Lorg/apache/hadoop/hbase/procedure2/LockedResourceType;Ljava/lang/String;)V
      42: iconst_1
      43: istore        4
      45: aload_0
      46: invokevirtual #64                 // Method schedUnlock:()V
      49: iload         4
      51: ireturn
      52: aload_0
      53: getfield      #15                 // Field locking:Lorg/apache/hadoop/hbase/master/procedure/SchemaLocking;
      56: aload_2
      57: invokevirtual #117                // Method org/apache/hadoop/hbase/master/procedure/SchemaLocking.getNamespaceLock:(Ljava/lang/String;)Lorg/apache/hadoop/hbase/procedure2/LockAndQueue;
      60: astore        4
      62: aload         4
      64: aload_1
      65: invokevirtual #128                // Method org/apache/hadoop/hbase/procedure2/LockAndQueue.tryExclusiveLock:(Lorg/apache/hadoop/hbase/procedure2/Procedure;)Z
      68: ifne          101
      71: aload_3
      72: invokevirtual #160                // Method org/apache/hadoop/hbase/procedure2/LockAndQueue.releaseSharedLock:()Z
      75: pop
      76: aload_0
      77: aload         4
      79: aload_1
      80: invokevirtual #157                // Method waitProcedure:(Lorg/apache/hadoop/hbase/procedure2/LockAndQueue;Lorg/apache/hadoop/hbase/procedure2/Procedure;)V
      83: aload_0
      84: getstatic     #158                // Field org/apache/hadoop/hbase/procedure2/LockedResourceType.NAMESPACE:Lorg/apache/hadoop/hbase/procedure2/LockedResourceType;
      87: aload_2
      88: invokespecial #159                // Method logLockedResource:(Lorg/apache/hadoop/hbase/procedure2/LockedResourceType;Ljava/lang/String;)V
      91: iconst_1
      92: istore        5
      94: aload_0
      95: invokevirtual #64                 // Method schedUnlock:()V
      98: iload         5
     100: ireturn
     101: iconst_0
     102: istore        5
     104: aload_0
     105: invokevirtual #64                 // Method schedUnlock:()V
     108: iload         5
     110: ireturn
     111: astore        6
     113: aload_0
     114: invokevirtual #64                 // Method schedUnlock:()V
     117: aload         6
     119: athrow
    Exception table:
       from    to  target type
           4    45   111   any
          52    94   111   any
         101   104   111   any
         111   113   111   any

  public void wakeNamespaceExclusiveLock(org.apache.hadoop.hbase.procedure2.Procedure<?>, java.lang.String);
    Code:
       0: aload_0
       1: invokevirtual #62                 // Method schedLock:()V
       4: aload_0
       5: getfield      #15                 // Field locking:Lorg/apache/hadoop/hbase/master/procedure/SchemaLocking;
       8: aload_2
       9: invokevirtual #117                // Method org/apache/hadoop/hbase/master/procedure/SchemaLocking.getNamespaceLock:(Ljava/lang/String;)Lorg/apache/hadoop/hbase/procedure2/LockAndQueue;
      12: astore_3
      13: aload_0
      14: getfield      #15                 // Field locking:Lorg/apache/hadoop/hbase/master/procedure/SchemaLocking;
      17: getstatic     #198                // Field org/apache/hadoop/hbase/master/procedure/TableProcedureInterface.DUMMY_NAMESPACE_TABLE_NAME:Lorg/apache/hadoop/hbase/TableName;
      20: invokevirtual #115                // Method org/apache/hadoop/hbase/master/procedure/SchemaLocking.getTableLock:(Lorg/apache/hadoop/hbase/TableName;)Lorg/apache/hadoop/hbase/procedure2/LockAndQueue;
      23: astore        4
      25: iconst_0
      26: istore        5
      28: aload_3
      29: aload_1
      30: invokevirtual #164                // Method org/apache/hadoop/hbase/procedure2/LockAndQueue.releaseExclusiveLock:(Lorg/apache/hadoop/hbase/procedure2/Procedure;)Z
      33: ifeq          46
      36: iload         5
      38: aload_0
      39: aload_3
      40: invokevirtual #165                // Method wakeWaitingProcedures:(Lorg/apache/hadoop/hbase/procedure2/LockAndQueue;)I
      43: iadd
      44: istore        5
      46: aload         4
      48: invokevirtual #160                // Method org/apache/hadoop/hbase/procedure2/LockAndQueue.releaseSharedLock:()Z
      51: ifeq          85
      54: aload_0
      55: getfield      #5                  // Field tableRunQueue:Lorg/apache/hadoop/hbase/master/procedure/FairQueue;
      58: aload_0
      59: getstatic     #198                // Field org/apache/hadoop/hbase/master/procedure/TableProcedureInterface.DUMMY_NAMESPACE_TABLE_NAME:Lorg/apache/hadoop/hbase/TableName;
      62: invokespecial #22                 // Method getTableQueue:(Lorg/apache/hadoop/hbase/TableName;)Lorg/apache/hadoop/hbase/master/procedure/TableQueue;
      65: aload_1
      66: invokedynamic #199,  0            // InvokeDynamic #12:get:(Lorg/apache/hadoop/hbase/procedure2/Procedure;)Ljava/util/function/Supplier;
      71: invokestatic  #48                 // Method addToRunQueue:(Lorg/apache/hadoop/hbase/master/procedure/FairQueue;Lorg/apache/hadoop/hbase/master/procedure/Queue;Ljava/util/function/Supplier;)V
      74: iload         5
      76: aload_0
      77: aload         4
      79: invokevirtual #165                // Method wakeWaitingProcedures:(Lorg/apache/hadoop/hbase/procedure2/LockAndQueue;)I
      82: iadd
      83: istore        5
      85: aload_0
      86: iload         5
      88: invokevirtual #167                // Method wakePollIfNeeded:(I)V
      91: aload_0
      92: invokevirtual #64                 // Method schedUnlock:()V
      95: goto          107
      98: astore        6
     100: aload_0
     101: invokevirtual #64                 // Method schedUnlock:()V
     104: aload         6
     106: athrow
     107: return
    Exception table:
       from    to  target type
           4    91    98   any
          98   100    98   any

  public boolean waitServerExclusiveLock(org.apache.hadoop.hbase.procedure2.Procedure<?>, org.apache.hadoop.hbase.ServerName);
    Code:
       0: aload_0
       1: invokevirtual #62                 // Method schedLock:()V
       4: aload_0
       5: getfield      #15                 // Field locking:Lorg/apache/hadoop/hbase/master/procedure/SchemaLocking;
       8: aload_2
       9: invokevirtual #124                // Method org/apache/hadoop/hbase/master/procedure/SchemaLocking.getServerLock:(Lorg/apache/hadoop/hbase/ServerName;)Lorg/apache/hadoop/hbase/procedure2/LockAndQueue;
      12: astore_3
      13: aload_3
      14: aload_1
      15: invokevirtual #128                // Method org/apache/hadoop/hbase/procedure2/LockAndQueue.tryExclusiveLock:(Lorg/apache/hadoop/hbase/procedure2/Procedure;)Z
      18: ifeq          64
      21: aload_0
      22: getfield      #4                  // Field serverRunQueue:Lorg/apache/hadoop/hbase/master/procedure/FairQueue;
      25: aload_0
      26: aload_2
      27: aload_1
      28: instanceof    #24                 // class org/apache/hadoop/hbase/master/procedure/ServerProcedureInterface
      31: ifeq          41
      34: aload_1
      35: checkcast     #24                 // class org/apache/hadoop/hbase/master/procedure/ServerProcedureInterface
      38: goto          42
      41: aconst_null
      42: invokespecial #26                 // Method getServerQueue:(Lorg/apache/hadoop/hbase/ServerName;Lorg/apache/hadoop/hbase/master/procedure/ServerProcedureInterface;)Lorg/apache/hadoop/hbase/master/procedure/ServerQueue;
      45: aload_1
      46: invokedynamic #200,  0            // InvokeDynamic #13:get:(Lorg/apache/hadoop/hbase/procedure2/Procedure;)Ljava/util/function/Supplier;
      51: invokestatic  #60                 // Method removeFromRunQueue:(Lorg/apache/hadoop/hbase/master/procedure/FairQueue;Lorg/apache/hadoop/hbase/master/procedure/Queue;Ljava/util/function/Supplier;)V
      54: iconst_0
      55: istore        4
      57: aload_0
      58: invokevirtual #64                 // Method schedUnlock:()V
      61: iload         4
      63: ireturn
      64: aload_0
      65: aload_3
      66: aload_1
      67: invokevirtual #157                // Method waitProcedure:(Lorg/apache/hadoop/hbase/procedure2/LockAndQueue;Lorg/apache/hadoop/hbase/procedure2/Procedure;)V
      70: aload_0
      71: getstatic     #201                // Field org/apache/hadoop/hbase/procedure2/LockedResourceType.SERVER:Lorg/apache/hadoop/hbase/procedure2/LockedResourceType;
      74: aload_2
      75: invokevirtual #202                // Method org/apache/hadoop/hbase/ServerName.getServerName:()Ljava/lang/String;
      78: invokespecial #159                // Method logLockedResource:(Lorg/apache/hadoop/hbase/procedure2/LockedResourceType;Ljava/lang/String;)V
      81: iconst_1
      82: istore        4
      84: aload_0
      85: invokevirtual #64                 // Method schedUnlock:()V
      88: iload         4
      90: ireturn
      91: astore        5
      93: aload_0
      94: invokevirtual #64                 // Method schedUnlock:()V
      97: aload         5
      99: athrow
    Exception table:
       from    to  target type
           4    57    91   any
          64    84    91   any
          91    93    91   any

  public void wakeServerExclusiveLock(org.apache.hadoop.hbase.procedure2.Procedure<?>, org.apache.hadoop.hbase.ServerName);
    Code:
       0: aload_0
       1: invokevirtual #62                 // Method schedLock:()V
       4: aload_0
       5: getfield      #15                 // Field locking:Lorg/apache/hadoop/hbase/master/procedure/SchemaLocking;
       8: aload_2
       9: invokevirtual #124                // Method org/apache/hadoop/hbase/master/procedure/SchemaLocking.getServerLock:(Lorg/apache/hadoop/hbase/ServerName;)Lorg/apache/hadoop/hbase/procedure2/LockAndQueue;
      12: astore_3
      13: aload_3
      14: aload_1
      15: invokevirtual #164                // Method org/apache/hadoop/hbase/procedure2/LockAndQueue.releaseExclusiveLock:(Lorg/apache/hadoop/hbase/procedure2/Procedure;)Z
      18: pop
      19: aload_0
      20: getfield      #4                  // Field serverRunQueue:Lorg/apache/hadoop/hbase/master/procedure/FairQueue;
      23: aload_0
      24: aload_2
      25: aload_1
      26: instanceof    #24                 // class org/apache/hadoop/hbase/master/procedure/ServerProcedureInterface
      29: ifeq          39
      32: aload_1
      33: checkcast     #24                 // class org/apache/hadoop/hbase/master/procedure/ServerProcedureInterface
      36: goto          40
      39: aconst_null
      40: invokespecial #26                 // Method getServerQueue:(Lorg/apache/hadoop/hbase/ServerName;Lorg/apache/hadoop/hbase/master/procedure/ServerProcedureInterface;)Lorg/apache/hadoop/hbase/master/procedure/ServerQueue;
      43: aload_1
      44: invokedynamic #203,  0            // InvokeDynamic #14:get:(Lorg/apache/hadoop/hbase/procedure2/Procedure;)Ljava/util/function/Supplier;
      49: invokestatic  #48                 // Method addToRunQueue:(Lorg/apache/hadoop/hbase/master/procedure/FairQueue;Lorg/apache/hadoop/hbase/master/procedure/Queue;Ljava/util/function/Supplier;)V
      52: aload_0
      53: aload_3
      54: invokevirtual #165                // Method wakeWaitingProcedures:(Lorg/apache/hadoop/hbase/procedure2/LockAndQueue;)I
      57: istore        4
      59: aload_0
      60: iload         4
      62: invokevirtual #167                // Method wakePollIfNeeded:(I)V
      65: aload_0
      66: invokevirtual #64                 // Method schedUnlock:()V
      69: goto          81
      72: astore        5
      74: aload_0
      75: invokevirtual #64                 // Method schedUnlock:()V
      78: aload         5
      80: athrow
      81: return
    Exception table:
       from    to  target type
           4    65    72   any
          72    74    72   any

  public boolean waitPeerExclusiveLock(org.apache.hadoop.hbase.procedure2.Procedure<?>, java.lang.String);
    Code:
       0: aload_0
       1: invokevirtual #62                 // Method schedLock:()V
       4: aload_0
       5: getfield      #15                 // Field locking:Lorg/apache/hadoop/hbase/master/procedure/SchemaLocking;
       8: aload_2
       9: invokevirtual #133                // Method org/apache/hadoop/hbase/master/procedure/SchemaLocking.getPeerLock:(Ljava/lang/String;)Lorg/apache/hadoop/hbase/procedure2/LockAndQueue;
      12: astore_3
      13: aload_3
      14: aload_1
      15: invokevirtual #128                // Method org/apache/hadoop/hbase/procedure2/LockAndQueue.tryExclusiveLock:(Lorg/apache/hadoop/hbase/procedure2/Procedure;)Z
      18: ifeq          49
      21: aload_0
      22: getfield      #6                  // Field peerRunQueue:Lorg/apache/hadoop/hbase/master/procedure/FairQueue;
      25: aload_0
      26: aload_2
      27: invokespecial #29                 // Method getPeerQueue:(Ljava/lang/String;)Lorg/apache/hadoop/hbase/master/procedure/PeerQueue;
      30: aload_1
      31: invokedynamic #204,  0            // InvokeDynamic #15:get:(Lorg/apache/hadoop/hbase/procedure2/Procedure;)Ljava/util/function/Supplier;
      36: invokestatic  #60                 // Method removeFromRunQueue:(Lorg/apache/hadoop/hbase/master/procedure/FairQueue;Lorg/apache/hadoop/hbase/master/procedure/Queue;Ljava/util/function/Supplier;)V
      39: iconst_0
      40: istore        4
      42: aload_0
      43: invokevirtual #64                 // Method schedUnlock:()V
      46: iload         4
      48: ireturn
      49: aload_0
      50: aload_3
      51: aload_1
      52: invokevirtual #157                // Method waitProcedure:(Lorg/apache/hadoop/hbase/procedure2/LockAndQueue;Lorg/apache/hadoop/hbase/procedure2/Procedure;)V
      55: aload_0
      56: getstatic     #205                // Field org/apache/hadoop/hbase/procedure2/LockedResourceType.PEER:Lorg/apache/hadoop/hbase/procedure2/LockedResourceType;
      59: aload_2
      60: invokespecial #159                // Method logLockedResource:(Lorg/apache/hadoop/hbase/procedure2/LockedResourceType;Ljava/lang/String;)V
      63: iconst_1
      64: istore        4
      66: aload_0
      67: invokevirtual #64                 // Method schedUnlock:()V
      70: iload         4
      72: ireturn
      73: astore        5
      75: aload_0
      76: invokevirtual #64                 // Method schedUnlock:()V
      79: aload         5
      81: athrow
    Exception table:
       from    to  target type
           4    42    73   any
          49    66    73   any
          73    75    73   any

  public void wakePeerExclusiveLock(org.apache.hadoop.hbase.procedure2.Procedure<?>, java.lang.String);
    Code:
       0: aload_0
       1: invokevirtual #62                 // Method schedLock:()V
       4: aload_0
       5: getfield      #15                 // Field locking:Lorg/apache/hadoop/hbase/master/procedure/SchemaLocking;
       8: aload_2
       9: invokevirtual #133                // Method org/apache/hadoop/hbase/master/procedure/SchemaLocking.getPeerLock:(Ljava/lang/String;)Lorg/apache/hadoop/hbase/procedure2/LockAndQueue;
      12: astore_3
      13: aload_3
      14: aload_1
      15: invokevirtual #164                // Method org/apache/hadoop/hbase/procedure2/LockAndQueue.releaseExclusiveLock:(Lorg/apache/hadoop/hbase/procedure2/Procedure;)Z
      18: ifeq          52
      21: aload_0
      22: getfield      #6                  // Field peerRunQueue:Lorg/apache/hadoop/hbase/master/procedure/FairQueue;
      25: aload_0
      26: aload_2
      27: invokespecial #29                 // Method getPeerQueue:(Ljava/lang/String;)Lorg/apache/hadoop/hbase/master/procedure/PeerQueue;
      30: aload_1
      31: invokedynamic #206,  0            // InvokeDynamic #16:get:(Lorg/apache/hadoop/hbase/procedure2/Procedure;)Ljava/util/function/Supplier;
      36: invokestatic  #48                 // Method addToRunQueue:(Lorg/apache/hadoop/hbase/master/procedure/FairQueue;Lorg/apache/hadoop/hbase/master/procedure/Queue;Ljava/util/function/Supplier;)V
      39: aload_0
      40: aload_3
      41: invokevirtual #165                // Method wakeWaitingProcedures:(Lorg/apache/hadoop/hbase/procedure2/LockAndQueue;)I
      44: istore        4
      46: aload_0
      47: iload         4
      49: invokevirtual #167                // Method wakePollIfNeeded:(I)V
      52: aload_0
      53: invokevirtual #64                 // Method schedUnlock:()V
      56: goto          68
      59: astore        5
      61: aload_0
      62: invokevirtual #64                 // Method schedUnlock:()V
      65: aload         5
      67: athrow
      68: return
    Exception table:
       from    to  target type
           4    52    59   any
          59    61    59   any

  public boolean waitMetaExclusiveLock(org.apache.hadoop.hbase.procedure2.Procedure<?>);
    Code:
       0: aload_0
       1: invokevirtual #62                 // Method schedLock:()V
       4: aload_0
       5: getfield      #15                 // Field locking:Lorg/apache/hadoop/hbase/master/procedure/SchemaLocking;
       8: invokevirtual #143                // Method org/apache/hadoop/hbase/master/procedure/SchemaLocking.getMetaLock:()Lorg/apache/hadoop/hbase/procedure2/LockAndQueue;
      11: astore_2
      12: aload_2
      13: aload_1
      14: invokevirtual #128                // Method org/apache/hadoop/hbase/procedure2/LockAndQueue.tryExclusiveLock:(Lorg/apache/hadoop/hbase/procedure2/Procedure;)Z
      17: ifeq          45
      20: aload_0
      21: getfield      #7                  // Field metaRunQueue:Lorg/apache/hadoop/hbase/master/procedure/FairQueue;
      24: aload_0
      25: invokespecial #18                 // Method getMetaQueue:()Lorg/apache/hadoop/hbase/master/procedure/MetaQueue;
      28: aload_1
      29: invokedynamic #207,  0            // InvokeDynamic #17:get:(Lorg/apache/hadoop/hbase/procedure2/Procedure;)Ljava/util/function/Supplier;
      34: invokestatic  #60                 // Method removeFromRunQueue:(Lorg/apache/hadoop/hbase/master/procedure/FairQueue;Lorg/apache/hadoop/hbase/master/procedure/Queue;Ljava/util/function/Supplier;)V
      37: iconst_0
      38: istore_3
      39: aload_0
      40: invokevirtual #64                 // Method schedUnlock:()V
      43: iload_3
      44: ireturn
      45: aload_0
      46: aload_2
      47: aload_1
      48: invokevirtual #157                // Method waitProcedure:(Lorg/apache/hadoop/hbase/procedure2/LockAndQueue;Lorg/apache/hadoop/hbase/procedure2/Procedure;)V
      51: aload_0
      52: getstatic     #208                // Field org/apache/hadoop/hbase/procedure2/LockedResourceType.META:Lorg/apache/hadoop/hbase/procedure2/LockedResourceType;
      55: getstatic     #140                // Field org/apache/hadoop/hbase/TableName.META_TABLE_NAME:Lorg/apache/hadoop/hbase/TableName;
      58: invokevirtual #162                // Method org/apache/hadoop/hbase/TableName.getNameAsString:()Ljava/lang/String;
      61: invokespecial #159                // Method logLockedResource:(Lorg/apache/hadoop/hbase/procedure2/LockedResourceType;Ljava/lang/String;)V
      64: iconst_1
      65: istore_3
      66: aload_0
      67: invokevirtual #64                 // Method schedUnlock:()V
      70: iload_3
      71: ireturn
      72: astore        4
      74: aload_0
      75: invokevirtual #64                 // Method schedUnlock:()V
      78: aload         4
      80: athrow
    Exception table:
       from    to  target type
           4    39    72   any
          45    66    72   any
          72    74    72   any

  public void wakeMetaExclusiveLock(org.apache.hadoop.hbase.procedure2.Procedure<?>);
    Code:
       0: aload_0
       1: invokevirtual #62                 // Method schedLock:()V
       4: aload_0
       5: getfield      #15                 // Field locking:Lorg/apache/hadoop/hbase/master/procedure/SchemaLocking;
       8: invokevirtual #143                // Method org/apache/hadoop/hbase/master/procedure/SchemaLocking.getMetaLock:()Lorg/apache/hadoop/hbase/procedure2/LockAndQueue;
      11: astore_2
      12: aload_2
      13: aload_1
      14: invokevirtual #164                // Method org/apache/hadoop/hbase/procedure2/LockAndQueue.releaseExclusiveLock:(Lorg/apache/hadoop/hbase/procedure2/Procedure;)Z
      17: pop
      18: aload_0
      19: getfield      #7                  // Field metaRunQueue:Lorg/apache/hadoop/hbase/master/procedure/FairQueue;
      22: aload_0
      23: invokespecial #18                 // Method getMetaQueue:()Lorg/apache/hadoop/hbase/master/procedure/MetaQueue;
      26: aload_1
      27: invokedynamic #209,  0            // InvokeDynamic #18:get:(Lorg/apache/hadoop/hbase/procedure2/Procedure;)Ljava/util/function/Supplier;
      32: invokestatic  #48                 // Method addToRunQueue:(Lorg/apache/hadoop/hbase/master/procedure/FairQueue;Lorg/apache/hadoop/hbase/master/procedure/Queue;Ljava/util/function/Supplier;)V
      35: aload_0
      36: aload_2
      37: invokevirtual #165                // Method wakeWaitingProcedures:(Lorg/apache/hadoop/hbase/procedure2/LockAndQueue;)I
      40: istore_3
      41: aload_0
      42: iload_3
      43: invokevirtual #167                // Method wakePollIfNeeded:(I)V
      46: aload_0
      47: invokevirtual #64                 // Method schedUnlock:()V
      50: goto          62
      53: astore        4
      55: aload_0
      56: invokevirtual #64                 // Method schedUnlock:()V
      59: aload         4
      61: athrow
      62: return
    Exception table:
       from    to  target type
           4    46    53   any
          53    55    53   any

  public java.lang.String dumpLocks() throws java.io.IOException;
    Code:
       0: aload_0
       1: invokevirtual #62                 // Method schedLock:()V
       4: aload_0
       5: getfield      #15                 // Field locking:Lorg/apache/hadoop/hbase/master/procedure/SchemaLocking;
       8: invokevirtual #210                // Method org/apache/hadoop/hbase/master/procedure/SchemaLocking.toString:()Ljava/lang/String;
      11: astore_1
      12: aload_0
      13: invokevirtual #64                 // Method schedUnlock:()V
      16: aload_1
      17: areturn
      18: astore_2
      19: aload_0
      20: invokevirtual #64                 // Method schedUnlock:()V
      23: aload_2
      24: athrow
    Exception table:
       from    to  target type
           4    12    18   any

  static {};
    Code:
       0: ldc           #234                // class org/apache/hadoop/hbase/master/procedure/MasterProcedureScheduler
       2: invokevirtual #235                // Method java/lang/Class.desiredAssertionStatus:()Z
       5: ifne          12
       8: iconst_1
       9: goto          13
      12: iconst_0
      13: putstatic     #72                 // Field $assertionsDisabled:Z
      16: ldc           #234                // class org/apache/hadoop/hbase/master/procedure/MasterProcedureScheduler
      18: invokestatic  #236                // Method org/slf4j/LoggerFactory.getLogger:(Ljava/lang/Class;)Lorg/slf4j/Logger;
      21: putstatic     #103                // Field LOG:Lorg/slf4j/Logger;
      24: invokedynamic #237,  0            // InvokeDynamic #19:compareKey:()Lorg/apache/hadoop/hbase/util/AvlUtil$AvlKeyComparator;
      29: putstatic     #68                 // Field SERVER_QUEUE_KEY_COMPARATOR:Lorg/apache/hadoop/hbase/util/AvlUtil$AvlKeyComparator;
      32: invokedynamic #238,  0            // InvokeDynamic #20:compareKey:()Lorg/apache/hadoop/hbase/util/AvlUtil$AvlKeyComparator;
      37: putstatic     #70                 // Field TABLE_QUEUE_KEY_COMPARATOR:Lorg/apache/hadoop/hbase/util/AvlUtil$AvlKeyComparator;
      40: invokedynamic #239,  0            // InvokeDynamic #21:compareKey:()Lorg/apache/hadoop/hbase/util/AvlUtil$AvlKeyComparator;
      45: putstatic     #71                 // Field PEER_QUEUE_KEY_COMPARATOR:Lorg/apache/hadoop/hbase/util/AvlUtil$AvlKeyComparator;
      48: invokedynamic #240,  0            // InvokeDynamic #22:compareKey:()Lorg/apache/hadoop/hbase/util/AvlUtil$AvlKeyComparator;
      53: putstatic     #141                // Field META_QUEUE_KEY_COMPARATOR:Lorg/apache/hadoop/hbase/util/AvlUtil$AvlKeyComparator;
      56: return
}
