Compiled from "MemoryCompactionPolicy.java"
public final class org.apache.hadoop.hbase.MemoryCompactionPolicy extends java.lang.Enum<org.apache.hadoop.hbase.MemoryCompactionPolicy> {
  public static final org.apache.hadoop.hbase.MemoryCompactionPolicy NONE;

  public static final org.apache.hadoop.hbase.MemoryCompactionPolicy BASIC;

  public static final org.apache.hadoop.hbase.MemoryCompactionPolicy EAGER;

  public static final org.apache.hadoop.hbase.MemoryCompactionPolicy ADAPTIVE;

  public static org.apache.hadoop.hbase.MemoryCompactionPolicy[] values();
    Code:
       0: getstatic     #1                  // Field $VALUES:[Lorg/apache/hadoop/hbase/MemoryCompactionPolicy;
       3: invokevirtual #2                  // Method "[Lorg/apache/hadoop/hbase/MemoryCompactionPolicy;".clone:()Ljava/lang/Object;
       6: checkcast     #3                  // class "[Lorg/apache/hadoop/hbase/MemoryCompactionPolicy;"
       9: areturn

  public static org.apache.hadoop.hbase.MemoryCompactionPolicy valueOf(java.lang.String);
    Code:
       0: ldc           #4                  // class org/apache/hadoop/hbase/MemoryCompactionPolicy
       2: aload_0
       3: invokestatic  #5                  // Method java/lang/Enum.valueOf:(Ljava/lang/Class;Ljava/lang/String;)Ljava/lang/Enum;
       6: checkcast     #4                  // class org/apache/hadoop/hbase/MemoryCompactionPolicy
       9: areturn

  static {};
    Code:
       0: new           #4                  // class org/apache/hadoop/hbase/MemoryCompactionPolicy
       3: dup
       4: ldc           #7                  // String NONE
       6: iconst_0
       7: invokespecial #8                  // Method "<init>":(Ljava/lang/String;I)V
      10: putstatic     #9                  // Field NONE:Lorg/apache/hadoop/hbase/MemoryCompactionPolicy;
      13: new           #4                  // class org/apache/hadoop/hbase/MemoryCompactionPolicy
      16: dup
      17: ldc           #10                 // String BASIC
      19: iconst_1
      20: invokespecial #8                  // Method "<init>":(Ljava/lang/String;I)V
      23: putstatic     #11                 // Field BASIC:Lorg/apache/hadoop/hbase/MemoryCompactionPolicy;
      26: new           #4                  // class org/apache/hadoop/hbase/MemoryCompactionPolicy
      29: dup
      30: ldc           #12                 // String EAGER
      32: iconst_2
      33: invokespecial #8                  // Method "<init>":(Ljava/lang/String;I)V
      36: putstatic     #13                 // Field EAGER:Lorg/apache/hadoop/hbase/MemoryCompactionPolicy;
      39: new           #4                  // class org/apache/hadoop/hbase/MemoryCompactionPolicy
      42: dup
      43: ldc           #14                 // String ADAPTIVE
      45: iconst_3
      46: invokespecial #8                  // Method "<init>":(Ljava/lang/String;I)V
      49: putstatic     #15                 // Field ADAPTIVE:Lorg/apache/hadoop/hbase/MemoryCompactionPolicy;
      52: iconst_4
      53: anewarray     #4                  // class org/apache/hadoop/hbase/MemoryCompactionPolicy
      56: dup
      57: iconst_0
      58: getstatic     #9                  // Field NONE:Lorg/apache/hadoop/hbase/MemoryCompactionPolicy;
      61: aastore
      62: dup
      63: iconst_1
      64: getstatic     #11                 // Field BASIC:Lorg/apache/hadoop/hbase/MemoryCompactionPolicy;
      67: aastore
      68: dup
      69: iconst_2
      70: getstatic     #13                 // Field EAGER:Lorg/apache/hadoop/hbase/MemoryCompactionPolicy;
      73: aastore
      74: dup
      75: iconst_3
      76: getstatic     #15                 // Field ADAPTIVE:Lorg/apache/hadoop/hbase/MemoryCompactionPolicy;
      79: aastore
      80: putstatic     #1                  // Field $VALUES:[Lorg/apache/hadoop/hbase/MemoryCompactionPolicy;
      83: return
}
