Compiled from "MemStoreSizing.java"
final class org.apache.hadoop.hbase.regionserver.MemStoreSizing$1 implements org.apache.hadoop.hbase.regionserver.MemStoreSizing {
  org.apache.hadoop.hbase.regionserver.MemStoreSizing$1();
    Code:
       0: aload_0
       1: invokespecial #1                  // Method java/lang/Object."<init>":()V
       4: aload_0
       5: new           #2                  // class org/apache/hadoop/hbase/regionserver/MemStoreSize
       8: dup
       9: invokespecial #3                  // Method org/apache/hadoop/hbase/regionserver/MemStoreSize."<init>":()V
      12: putfield      #4                  // Field mss:Lorg/apache/hadoop/hbase/regionserver/MemStoreSize;
      15: return

  public org.apache.hadoop.hbase.regionserver.MemStoreSize getMemStoreSize();
    Code:
       0: aload_0
       1: getfield      #4                  // Field mss:Lorg/apache/hadoop/hbase/regionserver/MemStoreSize;
       4: areturn

  public long getDataSize();
    Code:
       0: aload_0
       1: getfield      #4                  // Field mss:Lorg/apache/hadoop/hbase/regionserver/MemStoreSize;
       4: invokevirtual #5                  // Method org/apache/hadoop/hbase/regionserver/MemStoreSize.getDataSize:()J
       7: lreturn

  public long getHeapSize();
    Code:
       0: aload_0
       1: getfield      #4                  // Field mss:Lorg/apache/hadoop/hbase/regionserver/MemStoreSize;
       4: invokevirtual #6                  // Method org/apache/hadoop/hbase/regionserver/MemStoreSize.getHeapSize:()J
       7: lreturn

  public long getOffHeapSize();
    Code:
       0: aload_0
       1: getfield      #4                  // Field mss:Lorg/apache/hadoop/hbase/regionserver/MemStoreSize;
       4: invokevirtual #7                  // Method org/apache/hadoop/hbase/regionserver/MemStoreSize.getOffHeapSize:()J
       7: lreturn

  public int getCellsCount();
    Code:
       0: aload_0
       1: getfield      #4                  // Field mss:Lorg/apache/hadoop/hbase/regionserver/MemStoreSize;
       4: invokevirtual #8                  // Method org/apache/hadoop/hbase/regionserver/MemStoreSize.getCellsCount:()I
       7: ireturn

  public long incMemStoreSize(long, long, long, int);
    Code:
       0: new           #9                  // class java/lang/RuntimeException
       3: dup
       4: ldc           #10                 // String I'm a DUD, you can't use me!
       6: invokespecial #11                 // Method java/lang/RuntimeException."<init>":(Ljava/lang/String;)V
       9: athrow

  public boolean compareAndSetDataSize(long, long);
    Code:
       0: new           #9                  // class java/lang/RuntimeException
       3: dup
       4: ldc           #10                 // String I'm a DUD, you can't use me!
       6: invokespecial #11                 // Method java/lang/RuntimeException."<init>":(Ljava/lang/String;)V
       9: athrow
}
