Compiled from "MemStoreFlusher.java"
class org.apache.hadoop.hbase.regionserver.MemStoreFlusher$FlushRegionEntry implements org.apache.hadoop.hbase.regionserver.MemStoreFlusher$FlushQueueEntry {
  org.apache.hadoop.hbase.regionserver.MemStoreFlusher$FlushRegionEntry(org.apache.hadoop.hbase.regionserver.HRegion, boolean, org.apache.hadoop.hbase.regionserver.FlushLifeCycleTracker);
    Code:
       0: aload_0
       1: invokespecial #3                  // Method java/lang/Object."<init>":()V
       4: aload_0
       5: iconst_0
       6: putfield      #4                  // Field requeueCount:I
       9: aload_0
      10: aload_1
      11: putfield      #2                  // Field region:Lorg/apache/hadoop/hbase/regionserver/HRegion;
      14: aload_0
      15: invokestatic  #5                  // Method org/apache/hadoop/hbase/util/EnvironmentEdgeManager.currentTime:()J
      18: putfield      #1                  // Field createTime:J
      21: aload_0
      22: aload_0
      23: getfield      #1                  // Field createTime:J
      26: putfield      #6                  // Field whenToExpire:J
      29: aload_0
      30: iload_2
      31: putfield      #7                  // Field forceFlushAllStores:Z
      34: aload_0
      35: aload_3
      36: putfield      #8                  // Field tracker:Lorg/apache/hadoop/hbase/regionserver/FlushLifeCycleTracker;
      39: return

  public boolean isMaximumWait(long);
    Code:
       0: invokestatic  #5                  // Method org/apache/hadoop/hbase/util/EnvironmentEdgeManager.currentTime:()J
       3: aload_0
       4: getfield      #1                  // Field createTime:J
       7: lsub
       8: lload_1
       9: lcmp
      10: ifle          17
      13: iconst_1
      14: goto          18
      17: iconst_0
      18: ireturn

  public int getRequeueCount();
    Code:
       0: aload_0
       1: getfield      #4                  // Field requeueCount:I
       4: ireturn

  public boolean isForceFlushAllStores();
    Code:
       0: aload_0
       1: getfield      #7                  // Field forceFlushAllStores:Z
       4: ireturn

  public org.apache.hadoop.hbase.regionserver.FlushLifeCycleTracker getTracker();
    Code:
       0: aload_0
       1: getfield      #8                  // Field tracker:Lorg/apache/hadoop/hbase/regionserver/FlushLifeCycleTracker;
       4: areturn

  public org.apache.hadoop.hbase.regionserver.MemStoreFlusher$FlushRegionEntry requeue(long);
    Code:
       0: aload_0
       1: invokestatic  #5                  // Method org/apache/hadoop/hbase/util/EnvironmentEdgeManager.currentTime:()J
       4: lload_1
       5: ladd
       6: putfield      #6                  // Field whenToExpire:J
       9: aload_0
      10: dup
      11: getfield      #4                  // Field requeueCount:I
      14: iconst_1
      15: iadd
      16: putfield      #4                  // Field requeueCount:I
      19: aload_0
      20: areturn

  public long getDelay(java.util.concurrent.TimeUnit);
    Code:
       0: aload_1
       1: aload_0
       2: getfield      #6                  // Field whenToExpire:J
       5: invokestatic  #5                  // Method org/apache/hadoop/hbase/util/EnvironmentEdgeManager.currentTime:()J
       8: lsub
       9: getstatic     #9                  // Field java/util/concurrent/TimeUnit.MILLISECONDS:Ljava/util/concurrent/TimeUnit;
      12: invokevirtual #10                 // Method java/util/concurrent/TimeUnit.convert:(JLjava/util/concurrent/TimeUnit;)J
      15: lreturn

  public int compareTo(java.util.concurrent.Delayed);
    Code:
       0: aload_0
       1: getstatic     #9                  // Field java/util/concurrent/TimeUnit.MILLISECONDS:Ljava/util/concurrent/TimeUnit;
       4: invokevirtual #11                 // Method getDelay:(Ljava/util/concurrent/TimeUnit;)J
       7: aload_1
       8: getstatic     #9                  // Field java/util/concurrent/TimeUnit.MILLISECONDS:Ljava/util/concurrent/TimeUnit;
      11: invokeinterface #12,  2           // InterfaceMethod java/util/concurrent/Delayed.getDelay:(Ljava/util/concurrent/TimeUnit;)J
      16: lsub
      17: invokestatic  #13                 // Method java/lang/Long.valueOf:(J)Ljava/lang/Long;
      20: invokevirtual #14                 // Method java/lang/Long.intValue:()I
      23: istore_2
      24: iload_2
      25: ifeq          30
      28: iload_2
      29: ireturn
      30: aload_1
      31: checkcast     #15                 // class org/apache/hadoop/hbase/regionserver/MemStoreFlusher$FlushQueueEntry
      34: astore_3
      35: aload_0
      36: invokevirtual #16                 // Method hashCode:()I
      39: aload_3
      40: invokevirtual #17                 // Method java/lang/Object.hashCode:()I
      43: isub
      44: ireturn

  public java.lang.String toString();
    Code:
       0: new           #18                 // class java/lang/StringBuilder
       3: dup
       4: invokespecial #19                 // Method java/lang/StringBuilder."<init>":()V
       7: ldc           #20                 // String [flush region
       9: invokevirtual #21                 // Method java/lang/StringBuilder.append:(Ljava/lang/String;)Ljava/lang/StringBuilder;
      12: aload_0
      13: getfield      #2                  // Field region:Lorg/apache/hadoop/hbase/regionserver/HRegion;
      16: invokevirtual #22                 // Method org/apache/hadoop/hbase/regionserver/HRegion.getRegionInfo:()Lorg/apache/hadoop/hbase/client/RegionInfo;
      19: invokeinterface #23,  1           // InterfaceMethod org/apache/hadoop/hbase/client/RegionInfo.getRegionName:()[B
      24: invokestatic  #24                 // Method org/apache/hadoop/hbase/util/Bytes.toStringBinary:([B)Ljava/lang/String;
      27: invokevirtual #21                 // Method java/lang/StringBuilder.append:(Ljava/lang/String;)Ljava/lang/StringBuilder;
      30: ldc           #25                 // String ]
      32: invokevirtual #21                 // Method java/lang/StringBuilder.append:(Ljava/lang/String;)Ljava/lang/StringBuilder;
      35: invokevirtual #26                 // Method java/lang/StringBuilder.toString:()Ljava/lang/String;
      38: areturn

  public int hashCode();
    Code:
       0: aload_0
       1: getstatic     #9                  // Field java/util/concurrent/TimeUnit.MILLISECONDS:Ljava/util/concurrent/TimeUnit;
       4: invokevirtual #11                 // Method getDelay:(Ljava/util/concurrent/TimeUnit;)J
       7: l2i
       8: istore_1
       9: iload_1
      10: aload_0
      11: getfield      #2                  // Field region:Lorg/apache/hadoop/hbase/regionserver/HRegion;
      14: invokevirtual #27                 // Method org/apache/hadoop/hbase/regionserver/HRegion.hashCode:()I
      17: ixor
      18: ireturn

  public boolean equals(java.lang.Object);
    Code:
       0: aload_0
       1: aload_1
       2: if_acmpne     7
       5: iconst_1
       6: ireturn
       7: aload_1
       8: ifnull        22
      11: aload_0
      12: invokevirtual #28                 // Method java/lang/Object.getClass:()Ljava/lang/Class;
      15: aload_1
      16: invokevirtual #28                 // Method java/lang/Object.getClass:()Ljava/lang/Class;
      19: if_acmpeq     24
      22: iconst_0
      23: ireturn
      24: aload_1
      25: checkcast     #29                 // class org/apache/hadoop/hbase/regionserver/MemStoreFlusher$FlushRegionEntry
      28: astore_2
      29: aload_0
      30: getfield      #2                  // Field region:Lorg/apache/hadoop/hbase/regionserver/HRegion;
      33: invokevirtual #22                 // Method org/apache/hadoop/hbase/regionserver/HRegion.getRegionInfo:()Lorg/apache/hadoop/hbase/client/RegionInfo;
      36: invokeinterface #23,  1           // InterfaceMethod org/apache/hadoop/hbase/client/RegionInfo.getRegionName:()[B
      41: aload_2
      42: getfield      #2                  // Field region:Lorg/apache/hadoop/hbase/regionserver/HRegion;
      45: invokevirtual #22                 // Method org/apache/hadoop/hbase/regionserver/HRegion.getRegionInfo:()Lorg/apache/hadoop/hbase/client/RegionInfo;
      48: invokeinterface #23,  1           // InterfaceMethod org/apache/hadoop/hbase/client/RegionInfo.getRegionName:()[B
      53: invokestatic  #30                 // Method org/apache/hadoop/hbase/util/Bytes.equals:([B[B)Z
      56: ifne          61
      59: iconst_0
      60: ireturn
      61: aload_0
      62: aload_2
      63: invokevirtual #31                 // Method compareTo:(Ljava/util/concurrent/Delayed;)I
      66: ifne          73
      69: iconst_1
      70: goto          74
      73: iconst_0
      74: ireturn

  public int compareTo(java.lang.Object);
    Code:
       0: aload_0
       1: aload_1
       2: checkcast     #32                 // class java/util/concurrent/Delayed
       5: invokevirtual #31                 // Method compareTo:(Ljava/util/concurrent/Delayed;)I
       8: ireturn

  static org.apache.hadoop.hbase.regionserver.HRegion access$1300(org.apache.hadoop.hbase.regionserver.MemStoreFlusher$FlushRegionEntry);
    Code:
       0: aload_0
       1: getfield      #2                  // Field region:Lorg/apache/hadoop/hbase/regionserver/HRegion;
       4: areturn

  static long access$1400(org.apache.hadoop.hbase.regionserver.MemStoreFlusher$FlushRegionEntry);
    Code:
       0: aload_0
       1: getfield      #1                  // Field createTime:J
       4: lreturn
}
