Compiled from "MergeTableRegionsProcedure.java"
public class org.apache.hadoop.hbase.master.assignment.MergeTableRegionsProcedure extends org.apache.hadoop.hbase.master.procedure.AbstractStateMachineTableProcedure<org.apache.hadoop.hbase.shaded.protobuf.generated.MasterProcedureProtos$MergeTableRegionsState> {
  static final boolean $assertionsDisabled;

  public org.apache.hadoop.hbase.master.assignment.MergeTableRegionsProcedure();
    Code:
       0: aload_0
       1: invokespecial #1                  // Method org/apache/hadoop/hbase/master/procedure/AbstractStateMachineTableProcedure."<init>":()V
       4: return

  public org.apache.hadoop.hbase.master.assignment.MergeTableRegionsProcedure(org.apache.hadoop.hbase.master.procedure.MasterProcedureEnv, org.apache.hadoop.hbase.client.RegionInfo, org.apache.hadoop.hbase.client.RegionInfo) throws java.io.IOException;
    Code:
       0: aload_0
       1: aload_1
       2: aload_2
       3: aload_3
       4: iconst_0
       5: invokespecial #2                  // Method "<init>":(Lorg/apache/hadoop/hbase/master/procedure/MasterProcedureEnv;Lorg/apache/hadoop/hbase/client/RegionInfo;Lorg/apache/hadoop/hbase/client/RegionInfo;Z)V
       8: return

  public org.apache.hadoop.hbase.master.assignment.MergeTableRegionsProcedure(org.apache.hadoop.hbase.master.procedure.MasterProcedureEnv, org.apache.hadoop.hbase.client.RegionInfo, org.apache.hadoop.hbase.client.RegionInfo, boolean) throws java.io.IOException;
    Code:
       0: aload_0
       1: aload_1
       2: iconst_2
       3: anewarray     #3                  // class org/apache/hadoop/hbase/client/RegionInfo
       6: dup
       7: iconst_0
       8: aload_2
       9: aastore
      10: dup
      11: iconst_1
      12: aload_3
      13: aastore
      14: iload         4
      16: invokespecial #4                  // Method "<init>":(Lorg/apache/hadoop/hbase/master/procedure/MasterProcedureEnv;[Lorg/apache/hadoop/hbase/client/RegionInfo;Z)V
      19: return

  public org.apache.hadoop.hbase.master.assignment.MergeTableRegionsProcedure(org.apache.hadoop.hbase.master.procedure.MasterProcedureEnv, org.apache.hadoop.hbase.client.RegionInfo[], boolean) throws java.io.IOException;
    Code:
       0: aload_0
       1: aload_1
       2: invokespecial #5                  // Method org/apache/hadoop/hbase/master/procedure/AbstractStateMachineTableProcedure."<init>":(Lorg/apache/hadoop/hbase/master/procedure/MasterProcedureEnv;)V
       5: aload_1
       6: aload_2
       7: iload_3
       8: invokestatic  #6                  // Method checkRegionsToMerge:(Lorg/apache/hadoop/hbase/master/procedure/MasterProcedureEnv;[Lorg/apache/hadoop/hbase/client/RegionInfo;Z)V
      11: aload_0
      12: aload_2
      13: putfield      #7                  // Field regionsToMerge:[Lorg/apache/hadoop/hbase/client/RegionInfo;
      16: aload_0
      17: aload_2
      18: invokestatic  #8                  // Method createMergedRegionInfo:([Lorg/apache/hadoop/hbase/client/RegionInfo;)Lorg/apache/hadoop/hbase/client/RegionInfo;
      21: putfield      #9                  // Field mergedRegion:Lorg/apache/hadoop/hbase/client/RegionInfo;
      24: aload_0
      25: aload_1
      26: iconst_1
      27: invokestatic  #10                 // Method java/lang/Boolean.valueOf:(Z)Ljava/lang/Boolean;
      30: invokevirtual #11                 // Method preflightChecks:(Lorg/apache/hadoop/hbase/master/procedure/MasterProcedureEnv;Ljava/lang/Boolean;)V
      33: aload_0
      34: iload_3
      35: putfield      #12                 // Field forcible:Z
      38: return

  protected org.apache.hadoop.hbase.procedure2.StateMachineProcedure$Flow executeFromState(org.apache.hadoop.hbase.master.procedure.MasterProcedureEnv, org.apache.hadoop.hbase.shaded.protobuf.generated.MasterProcedureProtos$MergeTableRegionsState);
    Code:
       0: getstatic     #37                 // Field LOG:Lorg/slf4j/Logger;
       3: ldc           #65                 // String {} execute state={}
       5: aload_0
       6: aload_2
       7: invokeinterface #66,  4           // InterfaceMethod org/slf4j/Logger.trace:(Ljava/lang/String;Ljava/lang/Object;Ljava/lang/Object;)V
      12: getstatic     #67                 // Field org/apache/hadoop/hbase/master/assignment/MergeTableRegionsProcedure$1.$SwitchMap$org$apache$hadoop$hbase$shaded$protobuf$generated$MasterProcedureProtos$MergeTableRegionsState:[I
      15: aload_2
      16: invokevirtual #68                 // Method org/apache/hadoop/hbase/shaded/protobuf/generated/MasterProcedureProtos$MergeTableRegionsState.ordinal:()I
      19: iaload
      20: tableswitch   { // 1 to 11
                     1: 80
                     2: 125
                     3: 140
                     4: 159
                     5: 174
                     6: 194
                     7: 209
                     8: 224
                     9: 239
                    10: 254
                    11: 273
               default: 282
          }
      80: aload_0
      81: aload_1
      82: invokespecial #69                 // Method prepareMergeRegion:(Lorg/apache/hadoop/hbase/master/procedure/MasterProcedureEnv;)Z
      85: ifne          115
      88: getstatic     #70                 // Field $assertionsDisabled:Z
      91: ifne          111
      94: aload_0
      95: invokevirtual #71                 // Method isFailed:()Z
      98: ifne          111
     101: new           #72                 // class java/lang/AssertionError
     104: dup
     105: ldc           #73                 // String Merge region should have an exception here
     107: invokespecial #74                 // Method java/lang/AssertionError."<init>":(Ljava/lang/Object;)V
     110: athrow
     111: getstatic     #75                 // Field org/apache/hadoop/hbase/procedure2/StateMachineProcedure$Flow.NO_MORE_STATE:Lorg/apache/hadoop/hbase/procedure2/StateMachineProcedure$Flow;
     114: areturn
     115: aload_0
     116: getstatic     #76                 // Field org/apache/hadoop/hbase/shaded/protobuf/generated/MasterProcedureProtos$MergeTableRegionsState.MERGE_TABLE_REGIONS_PRE_MERGE_OPERATION:Lorg/apache/hadoop/hbase/shaded/protobuf/generated/MasterProcedureProtos$MergeTableRegionsState;
     119: invokevirtual #77                 // Method setNextState:(Ljava/lang/Object;)V
     122: goto          313
     125: aload_0
     126: aload_1
     127: invokespecial #78                 // Method preMergeRegions:(Lorg/apache/hadoop/hbase/master/procedure/MasterProcedureEnv;)V
     130: aload_0
     131: getstatic     #79                 // Field org/apache/hadoop/hbase/shaded/protobuf/generated/MasterProcedureProtos$MergeTableRegionsState.MERGE_TABLE_REGIONS_CLOSE_REGIONS:Lorg/apache/hadoop/hbase/shaded/protobuf/generated/MasterProcedureProtos$MergeTableRegionsState;
     134: invokevirtual #77                 // Method setNextState:(Ljava/lang/Object;)V
     137: goto          313
     140: aload_0
     141: aload_0
     142: aload_1
     143: invokespecial #80                 // Method createUnassignProcedures:(Lorg/apache/hadoop/hbase/master/procedure/MasterProcedureEnv;)[Lorg/apache/hadoop/hbase/master/assignment/TransitRegionStateProcedure;
     146: invokevirtual #81                 // Method addChildProcedure:([Lorg/apache/hadoop/hbase/procedure2/Procedure;)V
     149: aload_0
     150: getstatic     #82                 // Field org/apache/hadoop/hbase/shaded/protobuf/generated/MasterProcedureProtos$MergeTableRegionsState.MERGE_TABLE_REGIONS_CHECK_CLOSED_REGIONS:Lorg/apache/hadoop/hbase/shaded/protobuf/generated/MasterProcedureProtos$MergeTableRegionsState;
     153: invokevirtual #77                 // Method setNextState:(Ljava/lang/Object;)V
     156: goto          313
     159: aload_0
     160: aload_1
     161: invokespecial #83                 // Method checkClosedRegions:(Lorg/apache/hadoop/hbase/master/procedure/MasterProcedureEnv;)V
     164: aload_0
     165: getstatic     #84                 // Field org/apache/hadoop/hbase/shaded/protobuf/generated/MasterProcedureProtos$MergeTableRegionsState.MERGE_TABLE_REGIONS_CREATE_MERGED_REGION:Lorg/apache/hadoop/hbase/shaded/protobuf/generated/MasterProcedureProtos$MergeTableRegionsState;
     168: invokevirtual #77                 // Method setNextState:(Ljava/lang/Object;)V
     171: goto          313
     174: aload_0
     175: aload_1
     176: invokespecial #85                 // Method removeNonDefaultReplicas:(Lorg/apache/hadoop/hbase/master/procedure/MasterProcedureEnv;)V
     179: aload_0
     180: aload_1
     181: invokespecial #86                 // Method createMergedRegion:(Lorg/apache/hadoop/hbase/master/procedure/MasterProcedureEnv;)V
     184: aload_0
     185: getstatic     #87                 // Field org/apache/hadoop/hbase/shaded/protobuf/generated/MasterProcedureProtos$MergeTableRegionsState.MERGE_TABLE_REGIONS_WRITE_MAX_SEQUENCE_ID_FILE:Lorg/apache/hadoop/hbase/shaded/protobuf/generated/MasterProcedureProtos$MergeTableRegionsState;
     188: invokevirtual #77                 // Method setNextState:(Ljava/lang/Object;)V
     191: goto          313
     194: aload_0
     195: aload_1
     196: invokespecial #88                 // Method writeMaxSequenceIdFile:(Lorg/apache/hadoop/hbase/master/procedure/MasterProcedureEnv;)V
     199: aload_0
     200: getstatic     #89                 // Field org/apache/hadoop/hbase/shaded/protobuf/generated/MasterProcedureProtos$MergeTableRegionsState.MERGE_TABLE_REGIONS_PRE_MERGE_COMMIT_OPERATION:Lorg/apache/hadoop/hbase/shaded/protobuf/generated/MasterProcedureProtos$MergeTableRegionsState;
     203: invokevirtual #77                 // Method setNextState:(Ljava/lang/Object;)V
     206: goto          313
     209: aload_0
     210: aload_1
     211: invokespecial #90                 // Method preMergeRegionsCommit:(Lorg/apache/hadoop/hbase/master/procedure/MasterProcedureEnv;)V
     214: aload_0
     215: getstatic     #91                 // Field org/apache/hadoop/hbase/shaded/protobuf/generated/MasterProcedureProtos$MergeTableRegionsState.MERGE_TABLE_REGIONS_UPDATE_META:Lorg/apache/hadoop/hbase/shaded/protobuf/generated/MasterProcedureProtos$MergeTableRegionsState;
     218: invokevirtual #77                 // Method setNextState:(Ljava/lang/Object;)V
     221: goto          313
     224: aload_0
     225: aload_1
     226: invokespecial #92                 // Method updateMetaForMergedRegions:(Lorg/apache/hadoop/hbase/master/procedure/MasterProcedureEnv;)V
     229: aload_0
     230: getstatic     #93                 // Field org/apache/hadoop/hbase/shaded/protobuf/generated/MasterProcedureProtos$MergeTableRegionsState.MERGE_TABLE_REGIONS_POST_MERGE_COMMIT_OPERATION:Lorg/apache/hadoop/hbase/shaded/protobuf/generated/MasterProcedureProtos$MergeTableRegionsState;
     233: invokevirtual #77                 // Method setNextState:(Ljava/lang/Object;)V
     236: goto          313
     239: aload_0
     240: aload_1
     241: invokespecial #94                 // Method postMergeRegionsCommit:(Lorg/apache/hadoop/hbase/master/procedure/MasterProcedureEnv;)V
     244: aload_0
     245: getstatic     #95                 // Field org/apache/hadoop/hbase/shaded/protobuf/generated/MasterProcedureProtos$MergeTableRegionsState.MERGE_TABLE_REGIONS_OPEN_MERGED_REGION:Lorg/apache/hadoop/hbase/shaded/protobuf/generated/MasterProcedureProtos$MergeTableRegionsState;
     248: invokevirtual #77                 // Method setNextState:(Ljava/lang/Object;)V
     251: goto          313
     254: aload_0
     255: aload_0
     256: aload_1
     257: invokespecial #96                 // Method createAssignProcedures:(Lorg/apache/hadoop/hbase/master/procedure/MasterProcedureEnv;)[Lorg/apache/hadoop/hbase/master/assignment/TransitRegionStateProcedure;
     260: invokevirtual #81                 // Method addChildProcedure:([Lorg/apache/hadoop/hbase/procedure2/Procedure;)V
     263: aload_0
     264: getstatic     #97                 // Field org/apache/hadoop/hbase/shaded/protobuf/generated/MasterProcedureProtos$MergeTableRegionsState.MERGE_TABLE_REGIONS_POST_OPERATION:Lorg/apache/hadoop/hbase/shaded/protobuf/generated/MasterProcedureProtos$MergeTableRegionsState;
     267: invokevirtual #77                 // Method setNextState:(Ljava/lang/Object;)V
     270: goto          313
     273: aload_0
     274: aload_1
     275: invokespecial #98                 // Method postCompletedMergeRegions:(Lorg/apache/hadoop/hbase/master/procedure/MasterProcedureEnv;)V
     278: getstatic     #75                 // Field org/apache/hadoop/hbase/procedure2/StateMachineProcedure$Flow.NO_MORE_STATE:Lorg/apache/hadoop/hbase/procedure2/StateMachineProcedure$Flow;
     281: areturn
     282: new           #99                 // class java/lang/UnsupportedOperationException
     285: dup
     286: new           #14                 // class java/lang/StringBuilder
     289: dup
     290: invokespecial #15                 // Method java/lang/StringBuilder."<init>":()V
     293: aload_0
     294: invokevirtual #25                 // Method java/lang/StringBuilder.append:(Ljava/lang/Object;)Ljava/lang/StringBuilder;
     297: ldc           #100                // String  unhandled state=
     299: invokevirtual #17                 // Method java/lang/StringBuilder.append:(Ljava/lang/String;)Ljava/lang/StringBuilder;
     302: aload_2
     303: invokevirtual #25                 // Method java/lang/StringBuilder.append:(Ljava/lang/Object;)Ljava/lang/StringBuilder;
     306: invokevirtual #19                 // Method java/lang/StringBuilder.toString:()Ljava/lang/String;
     309: invokespecial #101                // Method java/lang/UnsupportedOperationException."<init>":(Ljava/lang/String;)V
     312: athrow
     313: goto          410
     316: astore_3
     317: new           #14                 // class java/lang/StringBuilder
     320: dup
     321: invokespecial #15                 // Method java/lang/StringBuilder."<init>":()V
     324: ldc           #103                // String Error trying to merge regions
     326: invokevirtual #17                 // Method java/lang/StringBuilder.append:(Ljava/lang/String;)Ljava/lang/StringBuilder;
     329: aload_0
     330: getfield      #7                  // Field regionsToMerge:[Lorg/apache/hadoop/hbase/client/RegionInfo;
     333: invokestatic  #104                // InterfaceMethod org/apache/hadoop/hbase/client/RegionInfo.getShortNameToLog:([Lorg/apache/hadoop/hbase/client/RegionInfo;)Ljava/lang/String;
     336: invokevirtual #17                 // Method java/lang/StringBuilder.append:(Ljava/lang/String;)Ljava/lang/StringBuilder;
     339: ldc           #105                // String  in the table
     341: invokevirtual #17                 // Method java/lang/StringBuilder.append:(Ljava/lang/String;)Ljava/lang/StringBuilder;
     344: aload_0
     345: invokevirtual #106                // Method getTableName:()Lorg/apache/hadoop/hbase/TableName;
     348: invokevirtual #25                 // Method java/lang/StringBuilder.append:(Ljava/lang/Object;)Ljava/lang/StringBuilder;
     351: ldc           #107                // String  (in state=
     353: invokevirtual #17                 // Method java/lang/StringBuilder.append:(Ljava/lang/String;)Ljava/lang/StringBuilder;
     356: aload_2
     357: invokevirtual #25                 // Method java/lang/StringBuilder.append:(Ljava/lang/Object;)Ljava/lang/StringBuilder;
     360: ldc           #108                // String )
     362: invokevirtual #17                 // Method java/lang/StringBuilder.append:(Ljava/lang/String;)Ljava/lang/StringBuilder;
     365: invokevirtual #19                 // Method java/lang/StringBuilder.toString:()Ljava/lang/String;
     368: astore        4
     370: aload_0
     371: aload_2
     372: invokevirtual #109                // Method isRollbackSupported:(Lorg/apache/hadoop/hbase/shaded/protobuf/generated/MasterProcedureProtos$MergeTableRegionsState;)Z
     375: ifne          392
     378: getstatic     #37                 // Field LOG:Lorg/slf4j/Logger;
     381: aload         4
     383: aload_3
     384: invokeinterface #110,  3          // InterfaceMethod org/slf4j/Logger.warn:(Ljava/lang/String;Ljava/lang/Throwable;)V
     389: goto          410
     392: getstatic     #37                 // Field LOG:Lorg/slf4j/Logger;
     395: aload         4
     397: aload_3
     398: invokeinterface #111,  3          // InterfaceMethod org/slf4j/Logger.error:(Ljava/lang/String;Ljava/lang/Throwable;)V
     403: aload_0
     404: ldc           #112                // String master-merge-regions
     406: aload_3
     407: invokevirtual #113                // Method setFailure:(Ljava/lang/String;Ljava/lang/Throwable;)V
     410: getstatic     #114                // Field org/apache/hadoop/hbase/procedure2/StateMachineProcedure$Flow.HAS_MORE_STATE:Lorg/apache/hadoop/hbase/procedure2/StateMachineProcedure$Flow;
     413: areturn
    Exception table:
       from    to  target type
          12   114   316   Class java/io/IOException
         115   281   316   Class java/io/IOException
         282   313   316   Class java/io/IOException

  protected void rollbackState(org.apache.hadoop.hbase.master.procedure.MasterProcedureEnv, org.apache.hadoop.hbase.shaded.protobuf.generated.MasterProcedureProtos$MergeTableRegionsState) throws java.io.IOException;
    Code:
       0: aload_0
       1: invokespecial #115                // Method isTraceEnabled:()Ljava/lang/Boolean;
       4: invokevirtual #116                // Method java/lang/Boolean.booleanValue:()Z
       7: ifeq          41
      10: getstatic     #37                 // Field LOG:Lorg/slf4j/Logger;
      13: new           #14                 // class java/lang/StringBuilder
      16: dup
      17: invokespecial #15                 // Method java/lang/StringBuilder."<init>":()V
      20: aload_0
      21: invokevirtual #25                 // Method java/lang/StringBuilder.append:(Ljava/lang/Object;)Ljava/lang/StringBuilder;
      24: ldc           #117                // String  rollback state=
      26: invokevirtual #17                 // Method java/lang/StringBuilder.append:(Ljava/lang/String;)Ljava/lang/StringBuilder;
      29: aload_2
      30: invokevirtual #25                 // Method java/lang/StringBuilder.append:(Ljava/lang/Object;)Ljava/lang/StringBuilder;
      33: invokevirtual #19                 // Method java/lang/StringBuilder.toString:()Ljava/lang/String;
      36: invokeinterface #118,  2          // InterfaceMethod org/slf4j/Logger.trace:(Ljava/lang/String;)V
      41: getstatic     #67                 // Field org/apache/hadoop/hbase/master/assignment/MergeTableRegionsProcedure$1.$SwitchMap$org$apache$hadoop$hbase$shaded$protobuf$generated$MasterProcedureProtos$MergeTableRegionsState:[I
      44: aload_2
      45: invokevirtual #68                 // Method org/apache/hadoop/hbase/shaded/protobuf/generated/MasterProcedureProtos$MergeTableRegionsState.ordinal:()I
      48: iaload
      49: tableswitch   { // 1 to 11
                     1: 207
                     2: 199
                     3: 191
                     4: 188
                     5: 180
                     6: 180
                     7: 177
                     8: 108
                     9: 108
                    10: 108
                    11: 108
               default: 210
          }
     108: new           #14                 // class java/lang/StringBuilder
     111: dup
     112: invokespecial #15                 // Method java/lang/StringBuilder."<init>":()V
     115: aload_0
     116: invokevirtual #25                 // Method java/lang/StringBuilder.append:(Ljava/lang/Object;)Ljava/lang/StringBuilder;
     119: ldc           #119                // String  We are in the
     121: invokevirtual #17                 // Method java/lang/StringBuilder.append:(Ljava/lang/String;)Ljava/lang/StringBuilder;
     124: aload_2
     125: invokevirtual #25                 // Method java/lang/StringBuilder.append:(Ljava/lang/Object;)Ljava/lang/StringBuilder;
     128: ldc           #120                // String  state. It is complicated to rollback the merge operation that region server is working on. Rollback is not supported and we should let the merge operation to complete
     130: invokevirtual #17                 // Method java/lang/StringBuilder.append:(Ljava/lang/String;)Ljava/lang/StringBuilder;
     133: invokevirtual #19                 // Method java/lang/StringBuilder.toString:()Ljava/lang/String;
     136: astore_3
     137: getstatic     #37                 // Field LOG:Lorg/slf4j/Logger;
     140: aload_3
     141: invokeinterface #38,  2           // InterfaceMethod org/slf4j/Logger.warn:(Ljava/lang/String;)V
     146: new           #99                 // class java/lang/UnsupportedOperationException
     149: dup
     150: new           #14                 // class java/lang/StringBuilder
     153: dup
     154: invokespecial #15                 // Method java/lang/StringBuilder."<init>":()V
     157: aload_0
     158: invokevirtual #25                 // Method java/lang/StringBuilder.append:(Ljava/lang/Object;)Ljava/lang/StringBuilder;
     161: ldc           #100                // String  unhandled state=
     163: invokevirtual #17                 // Method java/lang/StringBuilder.append:(Ljava/lang/String;)Ljava/lang/StringBuilder;
     166: aload_2
     167: invokevirtual #25                 // Method java/lang/StringBuilder.append:(Ljava/lang/Object;)Ljava/lang/StringBuilder;
     170: invokevirtual #19                 // Method java/lang/StringBuilder.toString:()Ljava/lang/String;
     173: invokespecial #101                // Method java/lang/UnsupportedOperationException."<init>":(Ljava/lang/String;)V
     176: athrow
     177: goto          241
     180: aload_0
     181: aload_1
     182: invokespecial #121                // Method cleanupMergedRegion:(Lorg/apache/hadoop/hbase/master/procedure/MasterProcedureEnv;)V
     185: goto          241
     188: goto          241
     191: aload_0
     192: aload_1
     193: invokespecial #122                // Method rollbackCloseRegionsForMerge:(Lorg/apache/hadoop/hbase/master/procedure/MasterProcedureEnv;)V
     196: goto          241
     199: aload_0
     200: aload_1
     201: invokespecial #123                // Method postRollBackMergeRegions:(Lorg/apache/hadoop/hbase/master/procedure/MasterProcedureEnv;)V
     204: goto          241
     207: goto          241
     210: new           #99                 // class java/lang/UnsupportedOperationException
     213: dup
     214: new           #14                 // class java/lang/StringBuilder
     217: dup
     218: invokespecial #15                 // Method java/lang/StringBuilder."<init>":()V
     221: aload_0
     222: invokevirtual #25                 // Method java/lang/StringBuilder.append:(Ljava/lang/Object;)Ljava/lang/StringBuilder;
     225: ldc           #100                // String  unhandled state=
     227: invokevirtual #17                 // Method java/lang/StringBuilder.append:(Ljava/lang/String;)Ljava/lang/StringBuilder;
     230: aload_2
     231: invokevirtual #25                 // Method java/lang/StringBuilder.append:(Ljava/lang/Object;)Ljava/lang/StringBuilder;
     234: invokevirtual #19                 // Method java/lang/StringBuilder.toString:()Ljava/lang/String;
     237: invokespecial #101                // Method java/lang/UnsupportedOperationException."<init>":(Ljava/lang/String;)V
     240: athrow
     241: goto          302
     244: astore_3
     245: getstatic     #37                 // Field LOG:Lorg/slf4j/Logger;
     248: new           #14                 // class java/lang/StringBuilder
     251: dup
     252: invokespecial #15                 // Method java/lang/StringBuilder."<init>":()V
     255: ldc           #125                // String Failed rollback attempt step
     257: invokevirtual #17                 // Method java/lang/StringBuilder.append:(Ljava/lang/String;)Ljava/lang/StringBuilder;
     260: aload_2
     261: invokevirtual #25                 // Method java/lang/StringBuilder.append:(Ljava/lang/Object;)Ljava/lang/StringBuilder;
     264: ldc           #126                // String  for merging the regions
     266: invokevirtual #17                 // Method java/lang/StringBuilder.append:(Ljava/lang/String;)Ljava/lang/StringBuilder;
     269: aload_0
     270: getfield      #7                  // Field regionsToMerge:[Lorg/apache/hadoop/hbase/client/RegionInfo;
     273: invokestatic  #104                // InterfaceMethod org/apache/hadoop/hbase/client/RegionInfo.getShortNameToLog:([Lorg/apache/hadoop/hbase/client/RegionInfo;)Ljava/lang/String;
     276: invokevirtual #17                 // Method java/lang/StringBuilder.append:(Ljava/lang/String;)Ljava/lang/StringBuilder;
     279: ldc           #127                // String  in table
     281: invokevirtual #17                 // Method java/lang/StringBuilder.append:(Ljava/lang/String;)Ljava/lang/StringBuilder;
     284: aload_0
     285: invokevirtual #106                // Method getTableName:()Lorg/apache/hadoop/hbase/TableName;
     288: invokevirtual #25                 // Method java/lang/StringBuilder.append:(Ljava/lang/Object;)Ljava/lang/StringBuilder;
     291: invokevirtual #19                 // Method java/lang/StringBuilder.toString:()Ljava/lang/String;
     294: aload_3
     295: invokeinterface #110,  3          // InterfaceMethod org/slf4j/Logger.warn:(Ljava/lang/String;Ljava/lang/Throwable;)V
     300: aload_3
     301: athrow
     302: return
    Exception table:
       from    to  target type
          41   241   244   Class java/lang/Exception

  protected boolean isRollbackSupported(org.apache.hadoop.hbase.shaded.protobuf.generated.MasterProcedureProtos$MergeTableRegionsState);
    Code:
       0: getstatic     #67                 // Field org/apache/hadoop/hbase/master/assignment/MergeTableRegionsProcedure$1.$SwitchMap$org$apache$hadoop$hbase$shaded$protobuf$generated$MasterProcedureProtos$MergeTableRegionsState:[I
       3: aload_1
       4: invokevirtual #68                 // Method org/apache/hadoop/hbase/shaded/protobuf/generated/MasterProcedureProtos$MergeTableRegionsState.ordinal:()I
       7: iaload
       8: tableswitch   { // 8 to 11
                     8: 40
                     9: 40
                    10: 40
                    11: 40
               default: 42
          }
      40: iconst_0
      41: ireturn
      42: iconst_1
      43: ireturn

  protected org.apache.hadoop.hbase.shaded.protobuf.generated.MasterProcedureProtos$MergeTableRegionsState getState(int);
    Code:
       0: iload_1
       1: invokestatic  #128                // Method org/apache/hadoop/hbase/shaded/protobuf/generated/MasterProcedureProtos$MergeTableRegionsState.forNumber:(I)Lorg/apache/hadoop/hbase/shaded/protobuf/generated/MasterProcedureProtos$MergeTableRegionsState;
       4: areturn

  protected int getStateId(org.apache.hadoop.hbase.shaded.protobuf.generated.MasterProcedureProtos$MergeTableRegionsState);
    Code:
       0: aload_1
       1: invokevirtual #129                // Method org/apache/hadoop/hbase/shaded/protobuf/generated/MasterProcedureProtos$MergeTableRegionsState.getNumber:()I
       4: ireturn

  protected org.apache.hadoop.hbase.shaded.protobuf.generated.MasterProcedureProtos$MergeTableRegionsState getInitialState();
    Code:
       0: getstatic     #130                // Field org/apache/hadoop/hbase/shaded/protobuf/generated/MasterProcedureProtos$MergeTableRegionsState.MERGE_TABLE_REGIONS_PREPARE:Lorg/apache/hadoop/hbase/shaded/protobuf/generated/MasterProcedureProtos$MergeTableRegionsState;
       3: areturn

  protected void serializeStateData(org.apache.hadoop.hbase.procedure2.ProcedureStateSerializer) throws java.io.IOException;
    Code:
       0: aload_0
       1: aload_1
       2: invokespecial #131                // Method org/apache/hadoop/hbase/master/procedure/AbstractStateMachineTableProcedure.serializeStateData:(Lorg/apache/hadoop/hbase/procedure2/ProcedureStateSerializer;)V
       5: invokestatic  #132                // Method org/apache/hadoop/hbase/shaded/protobuf/generated/MasterProcedureProtos$MergeTableRegionsStateData.newBuilder:()Lorg/apache/hadoop/hbase/shaded/protobuf/generated/MasterProcedureProtos$MergeTableRegionsStateData$Builder;
       8: aload_0
       9: invokevirtual #133                // Method getUser:()Lorg/apache/hadoop/hbase/security/User;
      12: invokestatic  #134                // Method org/apache/hadoop/hbase/master/procedure/MasterProcedureUtil.toProtoUserInfo:(Lorg/apache/hadoop/hbase/security/User;)Lorg/apache/hadoop/hbase/shaded/protobuf/generated/RPCProtos$UserInformation;
      15: invokevirtual #135                // Method org/apache/hadoop/hbase/shaded/protobuf/generated/MasterProcedureProtos$MergeTableRegionsStateData$Builder.setUserInfo:(Lorg/apache/hadoop/hbase/shaded/protobuf/generated/RPCProtos$UserInformation;)Lorg/apache/hadoop/hbase/shaded/protobuf/generated/MasterProcedureProtos$MergeTableRegionsStateData$Builder;
      18: aload_0
      19: getfield      #9                  // Field mergedRegion:Lorg/apache/hadoop/hbase/client/RegionInfo;
      22: invokestatic  #136                // Method org/apache/hadoop/hbase/shaded/protobuf/ProtobufUtil.toRegionInfo:(Lorg/apache/hadoop/hbase/client/RegionInfo;)Lorg/apache/hadoop/hbase/shaded/protobuf/generated/HBaseProtos$RegionInfo;
      25: invokevirtual #137                // Method org/apache/hadoop/hbase/shaded/protobuf/generated/MasterProcedureProtos$MergeTableRegionsStateData$Builder.setMergedRegionInfo:(Lorg/apache/hadoop/hbase/shaded/protobuf/generated/HBaseProtos$RegionInfo;)Lorg/apache/hadoop/hbase/shaded/protobuf/generated/MasterProcedureProtos$MergeTableRegionsStateData$Builder;
      28: aload_0
      29: getfield      #12                 // Field forcible:Z
      32: invokevirtual #138                // Method org/apache/hadoop/hbase/shaded/protobuf/generated/MasterProcedureProtos$MergeTableRegionsStateData$Builder.setForcible:(Z)Lorg/apache/hadoop/hbase/shaded/protobuf/generated/MasterProcedureProtos$MergeTableRegionsStateData$Builder;
      35: astore_2
      36: iconst_0
      37: istore_3
      38: iload_3
      39: aload_0
      40: getfield      #7                  // Field regionsToMerge:[Lorg/apache/hadoop/hbase/client/RegionInfo;
      43: arraylength
      44: if_icmpge     67
      47: aload_2
      48: aload_0
      49: getfield      #7                  // Field regionsToMerge:[Lorg/apache/hadoop/hbase/client/RegionInfo;
      52: iload_3
      53: aaload
      54: invokestatic  #136                // Method org/apache/hadoop/hbase/shaded/protobuf/ProtobufUtil.toRegionInfo:(Lorg/apache/hadoop/hbase/client/RegionInfo;)Lorg/apache/hadoop/hbase/shaded/protobuf/generated/HBaseProtos$RegionInfo;
      57: invokevirtual #139                // Method org/apache/hadoop/hbase/shaded/protobuf/generated/MasterProcedureProtos$MergeTableRegionsStateData$Builder.addRegionInfo:(Lorg/apache/hadoop/hbase/shaded/protobuf/generated/HBaseProtos$RegionInfo;)Lorg/apache/hadoop/hbase/shaded/protobuf/generated/MasterProcedureProtos$MergeTableRegionsStateData$Builder;
      60: pop
      61: iinc          3, 1
      64: goto          38
      67: aload_1
      68: aload_2
      69: invokevirtual #140                // Method org/apache/hadoop/hbase/shaded/protobuf/generated/MasterProcedureProtos$MergeTableRegionsStateData$Builder.build:()Lorg/apache/hadoop/hbase/shaded/protobuf/generated/MasterProcedureProtos$MergeTableRegionsStateData;
      72: invokeinterface #141,  2          // InterfaceMethod org/apache/hadoop/hbase/procedure2/ProcedureStateSerializer.serialize:(Lorg/apache/hbase/thirdparty/com/google/protobuf/Message;)V
      77: return

  protected void deserializeStateData(org.apache.hadoop.hbase.procedure2.ProcedureStateSerializer) throws java.io.IOException;
    Code:
       0: aload_0
       1: aload_1
       2: invokespecial #142                // Method org/apache/hadoop/hbase/master/procedure/AbstractStateMachineTableProcedure.deserializeStateData:(Lorg/apache/hadoop/hbase/procedure2/ProcedureStateSerializer;)V
       5: aload_1
       6: ldc           #143                // class org/apache/hadoop/hbase/shaded/protobuf/generated/MasterProcedureProtos$MergeTableRegionsStateData
       8: invokeinterface #144,  2          // InterfaceMethod org/apache/hadoop/hbase/procedure2/ProcedureStateSerializer.deserialize:(Ljava/lang/Class;)Lorg/apache/hbase/thirdparty/com/google/protobuf/Message;
      13: checkcast     #143                // class org/apache/hadoop/hbase/shaded/protobuf/generated/MasterProcedureProtos$MergeTableRegionsStateData
      16: astore_2
      17: aload_0
      18: aload_2
      19: invokevirtual #145                // Method org/apache/hadoop/hbase/shaded/protobuf/generated/MasterProcedureProtos$MergeTableRegionsStateData.getUserInfo:()Lorg/apache/hadoop/hbase/shaded/protobuf/generated/RPCProtos$UserInformation;
      22: invokestatic  #146                // Method org/apache/hadoop/hbase/master/procedure/MasterProcedureUtil.toUserInfo:(Lorg/apache/hadoop/hbase/shaded/protobuf/generated/RPCProtos$UserInformation;)Lorg/apache/hadoop/hbase/security/User;
      25: invokevirtual #147                // Method setUser:(Lorg/apache/hadoop/hbase/security/User;)V
      28: getstatic     #70                 // Field $assertionsDisabled:Z
      31: ifne          50
      34: aload_2
      35: invokevirtual #148                // Method org/apache/hadoop/hbase/shaded/protobuf/generated/MasterProcedureProtos$MergeTableRegionsStateData.getRegionInfoCount:()I
      38: iconst_2
      39: if_icmpeq     50
      42: new           #72                 // class java/lang/AssertionError
      45: dup
      46: invokespecial #149                // Method java/lang/AssertionError."<init>":()V
      49: athrow
      50: aload_0
      51: aload_2
      52: invokevirtual #148                // Method org/apache/hadoop/hbase/shaded/protobuf/generated/MasterProcedureProtos$MergeTableRegionsStateData.getRegionInfoCount:()I
      55: anewarray     #3                  // class org/apache/hadoop/hbase/client/RegionInfo
      58: putfield      #7                  // Field regionsToMerge:[Lorg/apache/hadoop/hbase/client/RegionInfo;
      61: iconst_0
      62: istore_3
      63: iload_3
      64: aload_0
      65: getfield      #7                  // Field regionsToMerge:[Lorg/apache/hadoop/hbase/client/RegionInfo;
      68: arraylength
      69: if_icmpge     92
      72: aload_0
      73: getfield      #7                  // Field regionsToMerge:[Lorg/apache/hadoop/hbase/client/RegionInfo;
      76: iload_3
      77: aload_2
      78: iload_3
      79: invokevirtual #150                // Method org/apache/hadoop/hbase/shaded/protobuf/generated/MasterProcedureProtos$MergeTableRegionsStateData.getRegionInfo:(I)Lorg/apache/hadoop/hbase/shaded/protobuf/generated/HBaseProtos$RegionInfo;
      82: invokestatic  #151                // Method org/apache/hadoop/hbase/shaded/protobuf/ProtobufUtil.toRegionInfo:(Lorg/apache/hadoop/hbase/shaded/protobuf/generated/HBaseProtos$RegionInfo;)Lorg/apache/hadoop/hbase/client/RegionInfo;
      85: aastore
      86: iinc          3, 1
      89: goto          63
      92: aload_0
      93: aload_2
      94: invokevirtual #152                // Method org/apache/hadoop/hbase/shaded/protobuf/generated/MasterProcedureProtos$MergeTableRegionsStateData.getMergedRegionInfo:()Lorg/apache/hadoop/hbase/shaded/protobuf/generated/HBaseProtos$RegionInfo;
      97: invokestatic  #151                // Method org/apache/hadoop/hbase/shaded/protobuf/ProtobufUtil.toRegionInfo:(Lorg/apache/hadoop/hbase/shaded/protobuf/generated/HBaseProtos$RegionInfo;)Lorg/apache/hadoop/hbase/client/RegionInfo;
     100: putfield      #9                  // Field mergedRegion:Lorg/apache/hadoop/hbase/client/RegionInfo;
     103: return

  public void toStringClassDetails(java.lang.StringBuilder);
    Code:
       0: aload_1
       1: aload_0
       2: invokevirtual #153                // Method java/lang/Object.getClass:()Ljava/lang/Class;
       5: invokevirtual #154                // Method java/lang/Class.getSimpleName:()Ljava/lang/String;
       8: invokevirtual #17                 // Method java/lang/StringBuilder.append:(Ljava/lang/String;)Ljava/lang/StringBuilder;
      11: pop
      12: aload_1
      13: ldc           #155                // String  table=
      15: invokevirtual #17                 // Method java/lang/StringBuilder.append:(Ljava/lang/String;)Ljava/lang/StringBuilder;
      18: pop
      19: aload_1
      20: aload_0
      21: invokevirtual #106                // Method getTableName:()Lorg/apache/hadoop/hbase/TableName;
      24: invokevirtual #25                 // Method java/lang/StringBuilder.append:(Ljava/lang/Object;)Ljava/lang/StringBuilder;
      27: pop
      28: aload_1
      29: ldc           #156                // String , regions=
      31: invokevirtual #17                 // Method java/lang/StringBuilder.append:(Ljava/lang/String;)Ljava/lang/StringBuilder;
      34: pop
      35: aload_1
      36: aload_0
      37: getfield      #7                  // Field regionsToMerge:[Lorg/apache/hadoop/hbase/client/RegionInfo;
      40: invokestatic  #104                // InterfaceMethod org/apache/hadoop/hbase/client/RegionInfo.getShortNameToLog:([Lorg/apache/hadoop/hbase/client/RegionInfo;)Ljava/lang/String;
      43: invokevirtual #17                 // Method java/lang/StringBuilder.append:(Ljava/lang/String;)Ljava/lang/StringBuilder;
      46: pop
      47: aload_1
      48: ldc           #157                // String , forcibly=
      50: invokevirtual #17                 // Method java/lang/StringBuilder.append:(Ljava/lang/String;)Ljava/lang/StringBuilder;
      53: pop
      54: aload_1
      55: aload_0
      56: getfield      #12                 // Field forcible:Z
      59: invokevirtual #36                 // Method java/lang/StringBuilder.append:(Z)Ljava/lang/StringBuilder;
      62: pop
      63: return

  protected org.apache.hadoop.hbase.procedure2.Procedure$LockState acquireLock(org.apache.hadoop.hbase.master.procedure.MasterProcedureEnv);
    Code:
       0: aload_1
       1: invokevirtual #158                // Method org/apache/hadoop/hbase/master/procedure/MasterProcedureEnv.getProcedureScheduler:()Lorg/apache/hadoop/hbase/master/procedure/MasterProcedureScheduler;
       4: aload_0
       5: aload_0
       6: invokevirtual #106                // Method getTableName:()Lorg/apache/hadoop/hbase/TableName;
       9: iconst_3
      10: anewarray     #3                  // class org/apache/hadoop/hbase/client/RegionInfo
      13: dup
      14: iconst_0
      15: aload_0
      16: getfield      #9                  // Field mergedRegion:Lorg/apache/hadoop/hbase/client/RegionInfo;
      19: aastore
      20: dup
      21: iconst_1
      22: aload_0
      23: getfield      #7                  // Field regionsToMerge:[Lorg/apache/hadoop/hbase/client/RegionInfo;
      26: iconst_0
      27: aaload
      28: aastore
      29: dup
      30: iconst_2
      31: aload_0
      32: getfield      #7                  // Field regionsToMerge:[Lorg/apache/hadoop/hbase/client/RegionInfo;
      35: iconst_1
      36: aaload
      37: aastore
      38: invokevirtual #159                // Method org/apache/hadoop/hbase/master/procedure/MasterProcedureScheduler.waitRegions:(Lorg/apache/hadoop/hbase/procedure2/Procedure;Lorg/apache/hadoop/hbase/TableName;[Lorg/apache/hadoop/hbase/client/RegionInfo;)Z
      41: ifeq          91
      44: getstatic     #37                 // Field LOG:Lorg/slf4j/Logger;
      47: new           #14                 // class java/lang/StringBuilder
      50: dup
      51: invokespecial #15                 // Method java/lang/StringBuilder."<init>":()V
      54: getstatic     #160                // Field org/apache/hadoop/hbase/procedure2/Procedure$LockState.LOCK_EVENT_WAIT:Lorg/apache/hadoop/hbase/procedure2/Procedure$LockState;
      57: invokevirtual #25                 // Method java/lang/StringBuilder.append:(Ljava/lang/Object;)Ljava/lang/StringBuilder;
      60: ldc           #161                // String
      62: invokevirtual #17                 // Method java/lang/StringBuilder.append:(Ljava/lang/String;)Ljava/lang/StringBuilder;
      65: aload_1
      66: invokevirtual #158                // Method org/apache/hadoop/hbase/master/procedure/MasterProcedureEnv.getProcedureScheduler:()Lorg/apache/hadoop/hbase/master/procedure/MasterProcedureScheduler;
      69: invokevirtual #162                // Method org/apache/hadoop/hbase/master/procedure/MasterProcedureScheduler.dumpLocks:()Ljava/lang/String;
      72: invokevirtual #17                 // Method java/lang/StringBuilder.append:(Ljava/lang/String;)Ljava/lang/StringBuilder;
      75: invokevirtual #19                 // Method java/lang/StringBuilder.toString:()Ljava/lang/String;
      78: invokeinterface #163,  2          // InterfaceMethod org/slf4j/Logger.debug:(Ljava/lang/String;)V
      83: goto          87
      86: astore_2
      87: getstatic     #160                // Field org/apache/hadoop/hbase/procedure2/Procedure$LockState.LOCK_EVENT_WAIT:Lorg/apache/hadoop/hbase/procedure2/Procedure$LockState;
      90: areturn
      91: getstatic     #164                // Field org/apache/hadoop/hbase/procedure2/Procedure$LockState.LOCK_ACQUIRED:Lorg/apache/hadoop/hbase/procedure2/Procedure$LockState;
      94: areturn
    Exception table:
       from    to  target type
          44    83    86   Class java/io/IOException

  protected void releaseLock(org.apache.hadoop.hbase.master.procedure.MasterProcedureEnv);
    Code:
       0: aload_1
       1: invokevirtual #158                // Method org/apache/hadoop/hbase/master/procedure/MasterProcedureEnv.getProcedureScheduler:()Lorg/apache/hadoop/hbase/master/procedure/MasterProcedureScheduler;
       4: aload_0
       5: aload_0
       6: invokevirtual #106                // Method getTableName:()Lorg/apache/hadoop/hbase/TableName;
       9: iconst_3
      10: anewarray     #3                  // class org/apache/hadoop/hbase/client/RegionInfo
      13: dup
      14: iconst_0
      15: aload_0
      16: getfield      #9                  // Field mergedRegion:Lorg/apache/hadoop/hbase/client/RegionInfo;
      19: aastore
      20: dup
      21: iconst_1
      22: aload_0
      23: getfield      #7                  // Field regionsToMerge:[Lorg/apache/hadoop/hbase/client/RegionInfo;
      26: iconst_0
      27: aaload
      28: aastore
      29: dup
      30: iconst_2
      31: aload_0
      32: getfield      #7                  // Field regionsToMerge:[Lorg/apache/hadoop/hbase/client/RegionInfo;
      35: iconst_1
      36: aaload
      37: aastore
      38: invokevirtual #165                // Method org/apache/hadoop/hbase/master/procedure/MasterProcedureScheduler.wakeRegions:(Lorg/apache/hadoop/hbase/procedure2/Procedure;Lorg/apache/hadoop/hbase/TableName;[Lorg/apache/hadoop/hbase/client/RegionInfo;)V
      41: return

  protected boolean holdLock(org.apache.hadoop.hbase.master.procedure.MasterProcedureEnv);
    Code:
       0: iconst_1
       1: ireturn

  public org.apache.hadoop.hbase.TableName getTableName();
    Code:
       0: aload_0
       1: getfield      #9                  // Field mergedRegion:Lorg/apache/hadoop/hbase/client/RegionInfo;
       4: invokeinterface #22,  1           // InterfaceMethod org/apache/hadoop/hbase/client/RegionInfo.getTable:()Lorg/apache/hadoop/hbase/TableName;
       9: areturn

  public org.apache.hadoop.hbase.master.procedure.TableProcedureInterface$TableOperationType getTableOperationType();
    Code:
       0: getstatic     #166                // Field org/apache/hadoop/hbase/master/procedure/TableProcedureInterface$TableOperationType.REGION_MERGE:Lorg/apache/hadoop/hbase/master/procedure/TableProcedureInterface$TableOperationType;
       3: areturn

  protected org.apache.hadoop.hbase.procedure2.ProcedureMetrics getProcedureMetrics(org.apache.hadoop.hbase.master.procedure.MasterProcedureEnv);
    Code:
       0: aload_1
       1: invokevirtual #167                // Method org/apache/hadoop/hbase/master/procedure/MasterProcedureEnv.getAssignmentManager:()Lorg/apache/hadoop/hbase/master/assignment/AssignmentManager;
       4: invokevirtual #168                // Method org/apache/hadoop/hbase/master/assignment/AssignmentManager.getAssignmentManagerMetrics:()Lorg/apache/hadoop/hbase/master/MetricsAssignmentManager;
       7: invokevirtual #169                // Method org/apache/hadoop/hbase/master/MetricsAssignmentManager.getMergeProcMetrics:()Lorg/apache/hadoop/hbase/procedure2/ProcedureMetrics;
      10: areturn

  public org.apache.hadoop.hbase.client.RegionInfo getMergedRegion();
    Code:
       0: aload_0
       1: getfield      #9                  // Field mergedRegion:Lorg/apache/hadoop/hbase/client/RegionInfo;
       4: areturn

  protected boolean abort(org.apache.hadoop.hbase.master.procedure.MasterProcedureEnv);
    Code:
       0: aload_0
       1: aload_0
       2: invokevirtual #279                // Method getCurrentState:()Ljava/lang/Object;
       5: checkcast     #280                // class org/apache/hadoop/hbase/shaded/protobuf/generated/MasterProcedureProtos$MergeTableRegionsState
       8: invokevirtual #109                // Method isRollbackSupported:(Lorg/apache/hadoop/hbase/shaded/protobuf/generated/MasterProcedureProtos$MergeTableRegionsState;)Z
      11: ifeq          22
      14: aload_0
      15: aload_1
      16: invokespecial #281                // Method org/apache/hadoop/hbase/master/procedure/AbstractStateMachineTableProcedure.abort:(Ljava/lang/Object;)Z
      19: goto          23
      22: iconst_0
      23: ireturn

  protected boolean isRollbackSupported(java.lang.Object);
    Code:
       0: aload_0
       1: aload_1
       2: checkcast     #280                // class org/apache/hadoop/hbase/shaded/protobuf/generated/MasterProcedureProtos$MergeTableRegionsState
       5: invokevirtual #109                // Method isRollbackSupported:(Lorg/apache/hadoop/hbase/shaded/protobuf/generated/MasterProcedureProtos$MergeTableRegionsState;)Z
       8: ireturn

  protected boolean abort(java.lang.Object);
    Code:
       0: aload_0
       1: aload_1
       2: checkcast     #282                // class org/apache/hadoop/hbase/master/procedure/MasterProcedureEnv
       5: invokevirtual #283                // Method abort:(Lorg/apache/hadoop/hbase/master/procedure/MasterProcedureEnv;)Z
       8: ireturn

  protected java.lang.Object getInitialState();
    Code:
       0: aload_0
       1: invokevirtual #284                // Method getInitialState:()Lorg/apache/hadoop/hbase/shaded/protobuf/generated/MasterProcedureProtos$MergeTableRegionsState;
       4: areturn

  protected int getStateId(java.lang.Object);
    Code:
       0: aload_0
       1: aload_1
       2: checkcast     #280                // class org/apache/hadoop/hbase/shaded/protobuf/generated/MasterProcedureProtos$MergeTableRegionsState
       5: invokevirtual #285                // Method getStateId:(Lorg/apache/hadoop/hbase/shaded/protobuf/generated/MasterProcedureProtos$MergeTableRegionsState;)I
       8: ireturn

  protected java.lang.Object getState(int);
    Code:
       0: aload_0
       1: iload_1
       2: invokevirtual #286                // Method getState:(I)Lorg/apache/hadoop/hbase/shaded/protobuf/generated/MasterProcedureProtos$MergeTableRegionsState;
       5: areturn

  protected void rollbackState(java.lang.Object, java.lang.Object) throws java.io.IOException, java.lang.InterruptedException;
    Code:
       0: aload_0
       1: aload_1
       2: checkcast     #282                // class org/apache/hadoop/hbase/master/procedure/MasterProcedureEnv
       5: aload_2
       6: checkcast     #280                // class org/apache/hadoop/hbase/shaded/protobuf/generated/MasterProcedureProtos$MergeTableRegionsState
       9: invokevirtual #287                // Method rollbackState:(Lorg/apache/hadoop/hbase/master/procedure/MasterProcedureEnv;Lorg/apache/hadoop/hbase/shaded/protobuf/generated/MasterProcedureProtos$MergeTableRegionsState;)V
      12: return

  protected org.apache.hadoop.hbase.procedure2.StateMachineProcedure$Flow executeFromState(java.lang.Object, java.lang.Object) throws org.apache.hadoop.hbase.procedure2.ProcedureSuspendedException, org.apache.hadoop.hbase.procedure2.ProcedureYieldException, java.lang.InterruptedException;
    Code:
       0: aload_0
       1: aload_1
       2: checkcast     #282                // class org/apache/hadoop/hbase/master/procedure/MasterProcedureEnv
       5: aload_2
       6: checkcast     #280                // class org/apache/hadoop/hbase/shaded/protobuf/generated/MasterProcedureProtos$MergeTableRegionsState
       9: invokevirtual #288                // Method executeFromState:(Lorg/apache/hadoop/hbase/master/procedure/MasterProcedureEnv;Lorg/apache/hadoop/hbase/shaded/protobuf/generated/MasterProcedureProtos$MergeTableRegionsState;)Lorg/apache/hadoop/hbase/procedure2/StateMachineProcedure$Flow;
      12: areturn

  protected org.apache.hadoop.hbase.procedure2.ProcedureMetrics getProcedureMetrics(java.lang.Object);
    Code:
       0: aload_0
       1: aload_1
       2: checkcast     #282                // class org/apache/hadoop/hbase/master/procedure/MasterProcedureEnv
       5: invokevirtual #289                // Method getProcedureMetrics:(Lorg/apache/hadoop/hbase/master/procedure/MasterProcedureEnv;)Lorg/apache/hadoop/hbase/procedure2/ProcedureMetrics;
       8: areturn

  protected boolean holdLock(java.lang.Object);
    Code:
       0: aload_0
       1: aload_1
       2: checkcast     #282                // class org/apache/hadoop/hbase/master/procedure/MasterProcedureEnv
       5: invokevirtual #290                // Method holdLock:(Lorg/apache/hadoop/hbase/master/procedure/MasterProcedureEnv;)Z
       8: ireturn

  protected void releaseLock(java.lang.Object);
    Code:
       0: aload_0
       1: aload_1
       2: checkcast     #282                // class org/apache/hadoop/hbase/master/procedure/MasterProcedureEnv
       5: invokevirtual #291                // Method releaseLock:(Lorg/apache/hadoop/hbase/master/procedure/MasterProcedureEnv;)V
       8: return

  protected org.apache.hadoop.hbase.procedure2.Procedure$LockState acquireLock(java.lang.Object);
    Code:
       0: aload_0
       1: aload_1
       2: checkcast     #282                // class org/apache/hadoop/hbase/master/procedure/MasterProcedureEnv
       5: invokevirtual #292                // Method acquireLock:(Lorg/apache/hadoop/hbase/master/procedure/MasterProcedureEnv;)Lorg/apache/hadoop/hbase/procedure2/Procedure$LockState;
       8: areturn

  static {};
    Code:
       0: ldc_w         #293                // class org/apache/hadoop/hbase/master/assignment/MergeTableRegionsProcedure
       3: invokevirtual #294                // Method java/lang/Class.desiredAssertionStatus:()Z
       6: ifne          13
       9: iconst_1
      10: goto          14
      13: iconst_0
      14: putstatic     #70                 // Field $assertionsDisabled:Z
      17: ldc_w         #293                // class org/apache/hadoop/hbase/master/assignment/MergeTableRegionsProcedure
      20: invokestatic  #295                // Method org/slf4j/LoggerFactory.getLogger:(Ljava/lang/Class;)Lorg/slf4j/Logger;
      23: putstatic     #37                 // Field LOG:Lorg/slf4j/Logger;
      26: return
}
