Compiled from "MessageCodec.java"
class org.apache.hadoop.hbase.codec.MessageCodec$MessageDecoder extends org.apache.hadoop.hbase.codec.BaseDecoder {
  org.apache.hadoop.hbase.codec.MessageCodec$MessageDecoder(java.io.InputStream);
    Code:
       0: aload_0
       1: aload_1
       2: invokespecial #1                  // Method org/apache/hadoop/hbase/codec/BaseDecoder."<init>":(Ljava/io/InputStream;)V
       5: aload_0
       6: getstatic     #2                  // Field org/apache/hadoop/hbase/CellBuilderType.SHALLOW_COPY:Lorg/apache/hadoop/hbase/CellBuilderType;
       9: invokestatic  #3                  // Method org/apache/hadoop/hbase/ExtendedCellBuilderFactory.create:(Lorg/apache/hadoop/hbase/CellBuilderType;)Lorg/apache/hadoop/hbase/ExtendedCellBuilder;
      12: putfield      #4                  // Field cellBuilder:Lorg/apache/hadoop/hbase/ExtendedCellBuilder;
      15: return

  protected org.apache.hadoop.hbase.Cell parseCell() throws java.io.IOException;
    Code:
       0: aload_0
       1: getfield      #4                  // Field cellBuilder:Lorg/apache/hadoop/hbase/ExtendedCellBuilder;
       4: aload_0
       5: getfield      #5                  // Field in:Ljava/io/InputStream;
       8: invokestatic  #6                  // Method org/apache/hadoop/hbase/shaded/protobuf/generated/CellProtos$Cell.parseDelimitedFrom:(Ljava/io/InputStream;)Lorg/apache/hadoop/hbase/shaded/protobuf/generated/CellProtos$Cell;
      11: invokestatic  #7                  // Method org/apache/hadoop/hbase/shaded/protobuf/ProtobufUtil.toCell:(Lorg/apache/hadoop/hbase/ExtendedCellBuilder;Lorg/apache/hadoop/hbase/shaded/protobuf/generated/CellProtos$Cell;)Lorg/apache/hadoop/hbase/Cell;
      14: areturn
}
