Compiled from "MetaTableAccessor.java"
final class org.apache.hadoop.hbase.MetaTableAccessor$4 implements org.apache.hadoop.hbase.MetaTableAccessor$Visitor {
  org.apache.hadoop.hbase.MetaTableAccessor$4();
    Code:
       0: aload_0
       1: invokespecial #1                  // Method java/lang/Object."<init>":()V
       4: return

  public boolean visit(org.apache.hadoop.hbase.client.Result) throws java.io.IOException;
    Code:
       0: aload_1
       1: ifnull        11
       4: aload_1
       5: invokevirtual #2                  // Method org/apache/hadoop/hbase/client/Result.isEmpty:()Z
       8: ifeq          13
      11: iconst_1
      12: ireturn
      13: invokestatic  #3                  // Method org/apache/hadoop/hbase/MetaTableAccessor.access$000:()Lorg/slf4j/Logger;
      16: new           #4                  // class java/lang/StringBuilder
      19: dup
      20: invokespecial #5                  // Method java/lang/StringBuilder."<init>":()V
      23: ldc           #6                  // String fullScanMetaAndPrint.Current Meta Row:
      25: invokevirtual #7                  // Method java/lang/StringBuilder.append:(Ljava/lang/String;)Ljava/lang/StringBuilder;
      28: aload_1
      29: invokevirtual #8                  // Method java/lang/StringBuilder.append:(Ljava/lang/Object;)Ljava/lang/StringBuilder;
      32: invokevirtual #9                  // Method java/lang/StringBuilder.toString:()Ljava/lang/String;
      35: invokeinterface #10,  2           // InterfaceMethod org/slf4j/Logger.info:(Ljava/lang/String;)V
      40: aload_1
      41: invokestatic  #11                 // Method org/apache/hadoop/hbase/MetaTableAccessor.getTableState:(Lorg/apache/hadoop/hbase/client/Result;)Lorg/apache/hadoop/hbase/client/TableState;
      44: astore_2
      45: aload_2
      46: ifnull        79
      49: invokestatic  #3                  // Method org/apache/hadoop/hbase/MetaTableAccessor.access$000:()Lorg/slf4j/Logger;
      52: new           #4                  // class java/lang/StringBuilder
      55: dup
      56: invokespecial #5                  // Method java/lang/StringBuilder."<init>":()V
      59: ldc           #12                 // String Table State:
      61: invokevirtual #7                  // Method java/lang/StringBuilder.append:(Ljava/lang/String;)Ljava/lang/StringBuilder;
      64: aload_2
      65: invokevirtual #8                  // Method java/lang/StringBuilder.append:(Ljava/lang/Object;)Ljava/lang/StringBuilder;
      68: invokevirtual #9                  // Method java/lang/StringBuilder.toString:()Ljava/lang/String;
      71: invokeinterface #10,  2           // InterfaceMethod org/slf4j/Logger.info:(Ljava/lang/String;)V
      76: goto          160
      79: aload_1
      80: invokestatic  #13                 // Method org/apache/hadoop/hbase/MetaTableAccessor.getRegionLocations:(Lorg/apache/hadoop/hbase/client/Result;)Lorg/apache/hadoop/hbase/RegionLocations;
      83: astore_3
      84: aload_3
      85: ifnonnull     90
      88: iconst_1
      89: ireturn
      90: aload_3
      91: invokevirtual #14                 // Method org/apache/hadoop/hbase/RegionLocations.getRegionLocations:()[Lorg/apache/hadoop/hbase/HRegionLocation;
      94: astore        4
      96: aload         4
      98: arraylength
      99: istore        5
     101: iconst_0
     102: istore        6
     104: iload         6
     106: iload         5
     108: if_icmpge     160
     111: aload         4
     113: iload         6
     115: aaload
     116: astore        7
     118: aload         7
     120: ifnull        154
     123: invokestatic  #3                  // Method org/apache/hadoop/hbase/MetaTableAccessor.access$000:()Lorg/slf4j/Logger;
     126: new           #4                  // class java/lang/StringBuilder
     129: dup
     130: invokespecial #5                  // Method java/lang/StringBuilder."<init>":()V
     133: ldc           #15                 // String fullScanMetaAndPrint.HRI Print=
     135: invokevirtual #7                  // Method java/lang/StringBuilder.append:(Ljava/lang/String;)Ljava/lang/StringBuilder;
     138: aload         7
     140: invokevirtual #16                 // Method org/apache/hadoop/hbase/HRegionLocation.getRegion:()Lorg/apache/hadoop/hbase/client/RegionInfo;
     143: invokevirtual #8                  // Method java/lang/StringBuilder.append:(Ljava/lang/Object;)Ljava/lang/StringBuilder;
     146: invokevirtual #9                  // Method java/lang/StringBuilder.toString:()Ljava/lang/String;
     149: invokeinterface #10,  2           // InterfaceMethod org/slf4j/Logger.info:(Ljava/lang/String;)V
     154: iinc          6, 1
     157: goto          104
     160: iconst_1
     161: ireturn
}
