Compiled from "MetaMockingUtil.java"
public class org.apache.hadoop.hbase.MetaMockingUtil {
  public org.apache.hadoop.hbase.MetaMockingUtil();
    Code:
       0: aload_0
       1: invokespecial #1                  // Method java/lang/Object."<init>":()V
       4: return

  public static org.apache.hadoop.hbase.client.Result getMetaTableRowResult(org.apache.hadoop.hbase.HRegionInfo) throws java.io.IOException;
    Code:
       0: aload_0
       1: aconst_null
       2: aconst_null
       3: aconst_null
       4: invokestatic  #2                  // Method getMetaTableRowResult:(Lorg/apache/hadoop/hbase/HRegionInfo;Lorg/apache/hadoop/hbase/ServerName;Lorg/apache/hadoop/hbase/HRegionInfo;Lorg/apache/hadoop/hbase/HRegionInfo;)Lorg/apache/hadoop/hbase/client/Result;
       7: areturn

  public static org.apache.hadoop.hbase.client.Result getMetaTableRowResult(org.apache.hadoop.hbase.HRegionInfo, org.apache.hadoop.hbase.ServerName) throws java.io.IOException;
    Code:
       0: aload_0
       1: aload_1
       2: aconst_null
       3: aconst_null
       4: invokestatic  #2                  // Method getMetaTableRowResult:(Lorg/apache/hadoop/hbase/HRegionInfo;Lorg/apache/hadoop/hbase/ServerName;Lorg/apache/hadoop/hbase/HRegionInfo;Lorg/apache/hadoop/hbase/HRegionInfo;)Lorg/apache/hadoop/hbase/client/Result;
       7: areturn

  public static org.apache.hadoop.hbase.client.Result getMetaTableRowResult(org.apache.hadoop.hbase.HRegionInfo, org.apache.hadoop.hbase.ServerName, org.apache.hadoop.hbase.HRegionInfo, org.apache.hadoop.hbase.HRegionInfo) throws java.io.IOException;
    Code:
       0: new           #3                  // class java/util/ArrayList
       3: dup
       4: invokespecial #4                  // Method java/util/ArrayList."<init>":()V
       7: astore        4
       9: aload_0
      10: ifnull        42
      13: aload         4
      15: new           #5                  // class org/apache/hadoop/hbase/KeyValue
      18: dup
      19: aload_0
      20: invokevirtual #6                  // Method org/apache/hadoop/hbase/HRegionInfo.getRegionName:()[B
      23: getstatic     #7                  // Field org/apache/hadoop/hbase/HConstants.CATALOG_FAMILY:[B
      26: getstatic     #8                  // Field org/apache/hadoop/hbase/HConstants.REGIONINFO_QUALIFIER:[B
      29: aload_0
      30: invokevirtual #9                  // Method org/apache/hadoop/hbase/HRegionInfo.toByteArray:()[B
      33: invokespecial #10                 // Method org/apache/hadoop/hbase/KeyValue."<init>":([B[B[B[B)V
      36: invokeinterface #11,  2           // InterfaceMethod java/util/List.add:(Ljava/lang/Object;)Z
      41: pop
      42: aload_1
      43: ifnull        110
      46: aload         4
      48: new           #5                  // class org/apache/hadoop/hbase/KeyValue
      51: dup
      52: aload_0
      53: invokevirtual #6                  // Method org/apache/hadoop/hbase/HRegionInfo.getRegionName:()[B
      56: getstatic     #7                  // Field org/apache/hadoop/hbase/HConstants.CATALOG_FAMILY:[B
      59: getstatic     #12                 // Field org/apache/hadoop/hbase/HConstants.SERVER_QUALIFIER:[B
      62: aload_1
      63: invokevirtual #13                 // Method org/apache/hadoop/hbase/ServerName.getHostAndPort:()Ljava/lang/String;
      66: invokestatic  #14                 // Method org/apache/hadoop/hbase/util/Bytes.toBytes:(Ljava/lang/String;)[B
      69: invokespecial #10                 // Method org/apache/hadoop/hbase/KeyValue."<init>":([B[B[B[B)V
      72: invokeinterface #11,  2           // InterfaceMethod java/util/List.add:(Ljava/lang/Object;)Z
      77: pop
      78: aload         4
      80: new           #5                  // class org/apache/hadoop/hbase/KeyValue
      83: dup
      84: aload_0
      85: invokevirtual #6                  // Method org/apache/hadoop/hbase/HRegionInfo.getRegionName:()[B
      88: getstatic     #7                  // Field org/apache/hadoop/hbase/HConstants.CATALOG_FAMILY:[B
      91: getstatic     #15                 // Field org/apache/hadoop/hbase/HConstants.STARTCODE_QUALIFIER:[B
      94: aload_1
      95: invokevirtual #16                 // Method org/apache/hadoop/hbase/ServerName.getStartcode:()J
      98: invokestatic  #17                 // Method org/apache/hadoop/hbase/util/Bytes.toBytes:(J)[B
     101: invokespecial #10                 // Method org/apache/hadoop/hbase/KeyValue."<init>":([B[B[B[B)V
     104: invokeinterface #11,  2           // InterfaceMethod java/util/List.add:(Ljava/lang/Object;)Z
     109: pop
     110: aload_2
     111: ifnull        143
     114: aload         4
     116: new           #5                  // class org/apache/hadoop/hbase/KeyValue
     119: dup
     120: aload_0
     121: invokevirtual #6                  // Method org/apache/hadoop/hbase/HRegionInfo.getRegionName:()[B
     124: getstatic     #7                  // Field org/apache/hadoop/hbase/HConstants.CATALOG_FAMILY:[B
     127: getstatic     #18                 // Field org/apache/hadoop/hbase/HConstants.SPLITA_QUALIFIER:[B
     130: aload_2
     131: invokevirtual #9                  // Method org/apache/hadoop/hbase/HRegionInfo.toByteArray:()[B
     134: invokespecial #10                 // Method org/apache/hadoop/hbase/KeyValue."<init>":([B[B[B[B)V
     137: invokeinterface #11,  2           // InterfaceMethod java/util/List.add:(Ljava/lang/Object;)Z
     142: pop
     143: aload_3
     144: ifnull        176
     147: aload         4
     149: new           #5                  // class org/apache/hadoop/hbase/KeyValue
     152: dup
     153: aload_0
     154: invokevirtual #6                  // Method org/apache/hadoop/hbase/HRegionInfo.getRegionName:()[B
     157: getstatic     #7                  // Field org/apache/hadoop/hbase/HConstants.CATALOG_FAMILY:[B
     160: getstatic     #19                 // Field org/apache/hadoop/hbase/HConstants.SPLITB_QUALIFIER:[B
     163: aload_3
     164: invokevirtual #9                  // Method org/apache/hadoop/hbase/HRegionInfo.toByteArray:()[B
     167: invokespecial #10                 // Method org/apache/hadoop/hbase/KeyValue."<init>":([B[B[B[B)V
     170: invokeinterface #11,  2           // InterfaceMethod java/util/List.add:(Ljava/lang/Object;)Z
     175: pop
     176: aload         4
     178: getstatic     #20                 // Field org/apache/hadoop/hbase/CellComparatorImpl.META_COMPARATOR:Lorg/apache/hadoop/hbase/CellComparatorImpl;
     181: invokestatic  #21                 // Method java/util/Collections.sort:(Ljava/util/List;Ljava/util/Comparator;)V
     184: aload         4
     186: invokestatic  #22                 // Method org/apache/hadoop/hbase/client/Result.create:(Ljava/util/List;)Lorg/apache/hadoop/hbase/client/Result;
     189: areturn
}
