Compiled from "MetaTableAccessor.java"
final class org.apache.hadoop.hbase.MetaTableAccessor$6 implements org.apache.hadoop.hbase.client.coprocessor.Batch$Call<org.apache.hadoop.hbase.protobuf.generated.MultiRowMutationProtos$MultiRowMutationService, org.apache.hadoop.hbase.protobuf.generated.MultiRowMutationProtos$MutateRowsResponse> {
  final java.util.List val$mutations;

  org.apache.hadoop.hbase.MetaTableAccessor$6(java.util.List);
    Code:
       0: aload_0
       1: aload_1
       2: putfield      #1                  // Field val$mutations:Ljava/util/List;
       5: aload_0
       6: invokespecial #2                  // Method java/lang/Object."<init>":()V
       9: return

  public org.apache.hadoop.hbase.protobuf.generated.MultiRowMutationProtos$MutateRowsResponse call(org.apache.hadoop.hbase.protobuf.generated.MultiRowMutationProtos$MultiRowMutationService) throws java.io.IOException;
    Code:
       0: invokestatic  #3                  // Method org/apache/hadoop/hbase/protobuf/generated/MultiRowMutationProtos$MutateRowsRequest.newBuilder:()Lorg/apache/hadoop/hbase/protobuf/generated/MultiRowMutationProtos$MutateRowsRequest$Builder;
       3: astore_2
       4: aload_0
       5: getfield      #1                  // Field val$mutations:Ljava/util/List;
       8: invokeinterface #4,  1            // InterfaceMethod java/util/List.iterator:()Ljava/util/Iterator;
      13: astore_3
      14: aload_3
      15: invokeinterface #5,  1            // InterfaceMethod java/util/Iterator.hasNext:()Z
      20: ifeq          119
      23: aload_3
      24: invokeinterface #6,  1            // InterfaceMethod java/util/Iterator.next:()Ljava/lang/Object;
      29: checkcast     #7                  // class org/apache/hadoop/hbase/client/Mutation
      32: astore        4
      34: aload         4
      36: instanceof    #8                  // class org/apache/hadoop/hbase/client/Put
      39: ifeq          58
      42: aload_2
      43: getstatic     #9                  // Field org/apache/hadoop/hbase/protobuf/generated/ClientProtos$MutationProto$MutationType.PUT:Lorg/apache/hadoop/hbase/protobuf/generated/ClientProtos$MutationProto$MutationType;
      46: aload         4
      48: invokestatic  #10                 // Method org/apache/hadoop/hbase/protobuf/ProtobufUtil.toMutation:(Lorg/apache/hadoop/hbase/protobuf/generated/ClientProtos$MutationProto$MutationType;Lorg/apache/hadoop/hbase/client/Mutation;)Lorg/apache/hadoop/hbase/protobuf/generated/ClientProtos$MutationProto;
      51: invokevirtual #11                 // Method org/apache/hadoop/hbase/protobuf/generated/MultiRowMutationProtos$MutateRowsRequest$Builder.addMutationRequest:(Lorg/apache/hadoop/hbase/protobuf/generated/ClientProtos$MutationProto;)Lorg/apache/hadoop/hbase/protobuf/generated/MultiRowMutationProtos$MutateRowsRequest$Builder;
      54: pop
      55: goto          116
      58: aload         4
      60: instanceof    #12                 // class org/apache/hadoop/hbase/client/Delete
      63: ifeq          82
      66: aload_2
      67: getstatic     #13                 // Field org/apache/hadoop/hbase/protobuf/generated/ClientProtos$MutationProto$MutationType.DELETE:Lorg/apache/hadoop/hbase/protobuf/generated/ClientProtos$MutationProto$MutationType;
      70: aload         4
      72: invokestatic  #10                 // Method org/apache/hadoop/hbase/protobuf/ProtobufUtil.toMutation:(Lorg/apache/hadoop/hbase/protobuf/generated/ClientProtos$MutationProto$MutationType;Lorg/apache/hadoop/hbase/client/Mutation;)Lorg/apache/hadoop/hbase/protobuf/generated/ClientProtos$MutationProto;
      75: invokevirtual #11                 // Method org/apache/hadoop/hbase/protobuf/generated/MultiRowMutationProtos$MutateRowsRequest$Builder.addMutationRequest:(Lorg/apache/hadoop/hbase/protobuf/generated/ClientProtos$MutationProto;)Lorg/apache/hadoop/hbase/protobuf/generated/MultiRowMutationProtos$MutateRowsRequest$Builder;
      78: pop
      79: goto          116
      82: new           #14                 // class org/apache/hadoop/hbase/DoNotRetryIOException
      85: dup
      86: new           #15                 // class java/lang/StringBuilder
      89: dup
      90: invokespecial #16                 // Method java/lang/StringBuilder."<init>":()V
      93: ldc           #17                 // String multi in MetaEditor doesn't support
      95: invokevirtual #18                 // Method java/lang/StringBuilder.append:(Ljava/lang/String;)Ljava/lang/StringBuilder;
      98: aload         4
     100: invokevirtual #19                 // Method java/lang/Object.getClass:()Ljava/lang/Class;
     103: invokevirtual #20                 // Method java/lang/Class.getName:()Ljava/lang/String;
     106: invokevirtual #18                 // Method java/lang/StringBuilder.append:(Ljava/lang/String;)Ljava/lang/StringBuilder;
     109: invokevirtual #21                 // Method java/lang/StringBuilder.toString:()Ljava/lang/String;
     112: invokespecial #22                 // Method org/apache/hadoop/hbase/DoNotRetryIOException."<init>":(Ljava/lang/String;)V
     115: athrow
     116: goto          14
     119: new           #23                 // class org/apache/hadoop/hbase/ipc/ServerRpcController
     122: dup
     123: invokespecial #24                 // Method org/apache/hadoop/hbase/ipc/ServerRpcController."<init>":()V
     126: astore_3
     127: new           #25                 // class org/apache/hadoop/hbase/ipc/CoprocessorRpcUtils$BlockingRpcCallback
     130: dup
     131: invokespecial #26                 // Method org/apache/hadoop/hbase/ipc/CoprocessorRpcUtils$BlockingRpcCallback."<init>":()V
     134: astore        4
     136: aload_1
     137: aload_3
     138: aload_2
     139: invokevirtual #27                 // Method org/apache/hadoop/hbase/protobuf/generated/MultiRowMutationProtos$MutateRowsRequest$Builder.build:()Lorg/apache/hadoop/hbase/protobuf/generated/MultiRowMutationProtos$MutateRowsRequest;
     142: aload         4
     144: invokevirtual #28                 // Method org/apache/hadoop/hbase/protobuf/generated/MultiRowMutationProtos$MultiRowMutationService.mutateRows:(Lcom/google/protobuf/RpcController;Lorg/apache/hadoop/hbase/protobuf/generated/MultiRowMutationProtos$MutateRowsRequest;Lcom/google/protobuf/RpcCallback;)V
     147: aload         4
     149: invokevirtual #29                 // Method org/apache/hadoop/hbase/ipc/CoprocessorRpcUtils$BlockingRpcCallback.get:()Ljava/lang/Object;
     152: checkcast     #30                 // class org/apache/hadoop/hbase/protobuf/generated/MultiRowMutationProtos$MutateRowsResponse
     155: astore        5
     157: aload_3
     158: invokevirtual #31                 // Method org/apache/hadoop/hbase/ipc/ServerRpcController.failedOnException:()Z
     161: ifeq          169
     164: aload_3
     165: invokevirtual #32                 // Method org/apache/hadoop/hbase/ipc/ServerRpcController.getFailedOn:()Ljava/io/IOException;
     168: athrow
     169: aload         5
     171: areturn

  public java.lang.Object call(java.lang.Object) throws java.io.IOException;
    Code:
       0: aload_0
       1: aload_1
       2: checkcast     #33                 // class org/apache/hadoop/hbase/protobuf/generated/MultiRowMutationProtos$MultiRowMutationService
       5: invokevirtual #34                 // Method call:(Lorg/apache/hadoop/hbase/protobuf/generated/MultiRowMutationProtos$MultiRowMutationService;)Lorg/apache/hadoop/hbase/protobuf/generated/MultiRowMutationProtos$MutateRowsResponse;
       8: areturn
}
