Compiled from "MetaTableAccessor.java"
class org.apache.hadoop.hbase.MetaTableAccessor$CollectAllVisitor extends org.apache.hadoop.hbase.MetaTableAccessor$CollectingVisitor<org.apache.hadoop.hbase.client.Result> {
  org.apache.hadoop.hbase.MetaTableAccessor$CollectAllVisitor();
    Code:
       0: aload_0
       1: invokespecial #1                  // Method org/apache/hadoop/hbase/MetaTableAccessor$CollectingVisitor."<init>":()V
       4: return

  void add(org.apache.hadoop.hbase.client.Result);
    Code:
       0: aload_0
       1: getfield      #2                  // Field results:Ljava/util/List;
       4: aload_1
       5: invokeinterface #3,  2            // InterfaceMethod java/util/List.add:(Ljava/lang/Object;)Z
      10: pop
      11: return
}
