Compiled from "MetricsConnection.java"
public final class org.apache.hadoop.hbase.client.MetricsConnection$CallTracker {
  final com.codahale.metrics.Timer callTimer;

  final com.codahale.metrics.Histogram reqHist;

  final com.codahale.metrics.Histogram respHist;

  public void updateRpc(org.apache.hadoop.hbase.client.MetricsConnection$CallStats);
    Code:
       0: aload_0
       1: getfield      #19                 // Field callTimer:Lcom/codahale/metrics/Timer;
       4: aload_1
       5: invokevirtual #25                 // Method org/apache/hadoop/hbase/client/MetricsConnection$CallStats.getCallTimeMs:()J
       8: getstatic     #26                 // Field java/util/concurrent/TimeUnit.MILLISECONDS:Ljava/util/concurrent/TimeUnit;
      11: invokevirtual #27                 // Method com/codahale/metrics/Timer.update:(JLjava/util/concurrent/TimeUnit;)V
      14: aload_0
      15: getfield      #22                 // Field reqHist:Lcom/codahale/metrics/Histogram;
      18: aload_1
      19: invokevirtual #28                 // Method org/apache/hadoop/hbase/client/MetricsConnection$CallStats.getRequestSizeBytes:()J
      22: invokevirtual #29                 // Method com/codahale/metrics/Histogram.update:(J)V
      25: aload_0
      26: getfield      #24                 // Field respHist:Lcom/codahale/metrics/Histogram;
      29: aload_1
      30: invokevirtual #30                 // Method org/apache/hadoop/hbase/client/MetricsConnection$CallStats.getResponseSizeBytes:()J
      33: invokevirtual #29                 // Method com/codahale/metrics/Histogram.update:(J)V
      36: return

  public java.lang.String toString();
    Code:
       0: new           #5                  // class java/lang/StringBuilder
       3: dup
       4: invokespecial #15                 // Method java/lang/StringBuilder."<init>":()V
       7: ldc           #31                 // String CallTracker:
       9: invokevirtual #9                  // Method java/lang/StringBuilder.append:(Ljava/lang/String;)Ljava/lang/StringBuilder;
      12: aload_0
      13: getfield      #13                 // Field name:Ljava/lang/String;
      16: invokevirtual #9                  // Method java/lang/StringBuilder.append:(Ljava/lang/String;)Ljava/lang/StringBuilder;
      19: invokevirtual #12                 // Method java/lang/StringBuilder.toString:()Ljava/lang/String;
      22: areturn

  org.apache.hadoop.hbase.client.MetricsConnection$CallTracker(com.codahale.metrics.MetricRegistry, java.lang.String, java.lang.String, org.apache.hadoop.hbase.client.MetricsConnection$1);
    Code:
       0: aload_0
       1: aload_1
       2: aload_2
       3: aload_3
       4: invokespecial #3                  // Method "<init>":(Lcom/codahale/metrics/MetricRegistry;Ljava/lang/String;Ljava/lang/String;)V
       7: return

  org.apache.hadoop.hbase.client.MetricsConnection$CallTracker(com.codahale.metrics.MetricRegistry, java.lang.String, java.lang.String, java.lang.String, org.apache.hadoop.hbase.client.MetricsConnection$1);
    Code:
       0: aload_0
       1: aload_1
       2: aload_2
       3: aload_3
       4: aload         4
       6: invokespecial #2                  // Method "<init>":(Lcom/codahale/metrics/MetricRegistry;Ljava/lang/String;Ljava/lang/String;Ljava/lang/String;)V
       9: return
}
