Compiled from "MetricsTableWrapperAggregateImpl.java"
public class org.apache.hadoop.hbase.regionserver.MetricsTableWrapperAggregateImpl implements org.apache.hadoop.hbase.regionserver.MetricsTableWrapperAggregate,java.io.Closeable {
  public org.apache.hadoop.hbase.regionserver.MetricsTableWrapperAggregateImpl(org.apache.hadoop.hbase.regionserver.HRegionServer);
    Code:
       0: aload_0
       1: invokespecial #3                  // Method java/lang/Object."<init>":()V
       4: aload_0
       5: new           #4                  // class java/util/concurrent/ConcurrentHashMap
       8: dup
       9: invokespecial #5                  // Method java/util/concurrent/ConcurrentHashMap."<init>":()V
      12: putfield      #1                  // Field metricsTableMap:Ljava/util/concurrent/ConcurrentHashMap;
      15: aload_0
      16: aload_1
      17: putfield      #2                  // Field regionServer:Lorg/apache/hadoop/hbase/regionserver/HRegionServer;
      20: aload_0
      21: aload_1
      22: getfield      #6                  // Field org/apache/hadoop/hbase/regionserver/HRegionServer.conf:Lorg/apache/hadoop/conf/Configuration;
      25: ldc           #8                  // String hbase.regionserver.metrics.period
      27: ldc2_w        #9                  // long 5000l
      30: invokevirtual #11                 // Method org/apache/hadoop/conf/Configuration.getLong:(Ljava/lang/String;J)J
      33: ldc2_w        #12                 // long 1000l
      36: ladd
      37: putfield      #14                 // Field period:J
      40: aload_0
      41: ldc           #15                 // class org/apache/hadoop/metrics2/MetricsExecutor
      43: invokestatic  #16                 // Method org/apache/hadoop/hbase/CompatibilitySingletonFactory.getInstance:(Ljava/lang/Class;)Ljava/lang/Object;
      46: checkcast     #15                 // class org/apache/hadoop/metrics2/MetricsExecutor
      49: invokeinterface #17,  1           // InterfaceMethod org/apache/hadoop/metrics2/MetricsExecutor.getExecutor:()Ljava/util/concurrent/ScheduledExecutorService;
      54: putfield      #18                 // Field executor:Ljava/util/concurrent/ScheduledExecutorService;
      57: aload_0
      58: new           #19                 // class org/apache/hadoop/hbase/regionserver/MetricsTableWrapperAggregateImpl$TableMetricsWrapperRunnable
      61: dup
      62: aload_0
      63: invokespecial #20                 // Method org/apache/hadoop/hbase/regionserver/MetricsTableWrapperAggregateImpl$TableMetricsWrapperRunnable."<init>":(Lorg/apache/hadoop/hbase/regionserver/MetricsTableWrapperAggregateImpl;)V
      66: putfield      #21                 // Field runnable:Ljava/lang/Runnable;
      69: aload_0
      70: aload_0
      71: getfield      #18                 // Field executor:Ljava/util/concurrent/ScheduledExecutorService;
      74: aload_0
      75: getfield      #21                 // Field runnable:Ljava/lang/Runnable;
      78: aload_0
      79: getfield      #14                 // Field period:J
      82: aload_0
      83: getfield      #14                 // Field period:J
      86: getstatic     #22                 // Field java/util/concurrent/TimeUnit.MILLISECONDS:Ljava/util/concurrent/TimeUnit;
      89: invokeinterface #23,  7           // InterfaceMethod java/util/concurrent/ScheduledExecutorService.scheduleWithFixedDelay:(Ljava/lang/Runnable;JJLjava/util/concurrent/TimeUnit;)Ljava/util/concurrent/ScheduledFuture;
      94: putfield      #24                 // Field tableMetricsUpdateTask:Ljava/util/concurrent/ScheduledFuture;
      97: return

  public long getReadRequestCount(java.lang.String);
    Code:
       0: aload_0
       1: getfield      #1                  // Field metricsTableMap:Ljava/util/concurrent/ConcurrentHashMap;
       4: aload_1
       5: invokestatic  #25                 // Method org/apache/hadoop/hbase/TableName.valueOf:(Ljava/lang/String;)Lorg/apache/hadoop/hbase/TableName;
       8: invokevirtual #26                 // Method java/util/concurrent/ConcurrentHashMap.get:(Ljava/lang/Object;)Ljava/lang/Object;
      11: checkcast     #27                 // class org/apache/hadoop/hbase/regionserver/MetricsTableWrapperAggregateImpl$MetricsTableValues
      14: astore_2
      15: aload_2
      16: ifnonnull     21
      19: lconst_0
      20: lreturn
      21: aload_2
      22: getfield      #28                 // Field org/apache/hadoop/hbase/regionserver/MetricsTableWrapperAggregateImpl$MetricsTableValues.readRequestCount:J
      25: lreturn

  public long getCpRequestsCount(java.lang.String);
    Code:
       0: aload_0
       1: getfield      #1                  // Field metricsTableMap:Ljava/util/concurrent/ConcurrentHashMap;
       4: aload_1
       5: invokestatic  #25                 // Method org/apache/hadoop/hbase/TableName.valueOf:(Ljava/lang/String;)Lorg/apache/hadoop/hbase/TableName;
       8: invokevirtual #26                 // Method java/util/concurrent/ConcurrentHashMap.get:(Ljava/lang/Object;)Ljava/lang/Object;
      11: checkcast     #27                 // class org/apache/hadoop/hbase/regionserver/MetricsTableWrapperAggregateImpl$MetricsTableValues
      14: astore_2
      15: aload_2
      16: ifnonnull     21
      19: lconst_0
      20: lreturn
      21: aload_2
      22: getfield      #29                 // Field org/apache/hadoop/hbase/regionserver/MetricsTableWrapperAggregateImpl$MetricsTableValues.cpRequestCount:J
      25: lreturn

  public long getFilteredReadRequestCount(java.lang.String);
    Code:
       0: aload_0
       1: getfield      #1                  // Field metricsTableMap:Ljava/util/concurrent/ConcurrentHashMap;
       4: aload_1
       5: invokestatic  #25                 // Method org/apache/hadoop/hbase/TableName.valueOf:(Ljava/lang/String;)Lorg/apache/hadoop/hbase/TableName;
       8: invokevirtual #26                 // Method java/util/concurrent/ConcurrentHashMap.get:(Ljava/lang/Object;)Ljava/lang/Object;
      11: checkcast     #27                 // class org/apache/hadoop/hbase/regionserver/MetricsTableWrapperAggregateImpl$MetricsTableValues
      14: astore_2
      15: aload_2
      16: ifnonnull     21
      19: lconst_0
      20: lreturn
      21: aload_2
      22: getfield      #30                 // Field org/apache/hadoop/hbase/regionserver/MetricsTableWrapperAggregateImpl$MetricsTableValues.filteredReadRequestCount:J
      25: lreturn

  public long getWriteRequestCount(java.lang.String);
    Code:
       0: aload_0
       1: getfield      #1                  // Field metricsTableMap:Ljava/util/concurrent/ConcurrentHashMap;
       4: aload_1
       5: invokestatic  #25                 // Method org/apache/hadoop/hbase/TableName.valueOf:(Ljava/lang/String;)Lorg/apache/hadoop/hbase/TableName;
       8: invokevirtual #26                 // Method java/util/concurrent/ConcurrentHashMap.get:(Ljava/lang/Object;)Ljava/lang/Object;
      11: checkcast     #27                 // class org/apache/hadoop/hbase/regionserver/MetricsTableWrapperAggregateImpl$MetricsTableValues
      14: astore_2
      15: aload_2
      16: ifnonnull     21
      19: lconst_0
      20: lreturn
      21: aload_2
      22: getfield      #31                 // Field org/apache/hadoop/hbase/regionserver/MetricsTableWrapperAggregateImpl$MetricsTableValues.writeRequestCount:J
      25: lreturn

  public long getTotalRequestsCount(java.lang.String);
    Code:
       0: aload_0
       1: getfield      #1                  // Field metricsTableMap:Ljava/util/concurrent/ConcurrentHashMap;
       4: aload_1
       5: invokestatic  #25                 // Method org/apache/hadoop/hbase/TableName.valueOf:(Ljava/lang/String;)Lorg/apache/hadoop/hbase/TableName;
       8: invokevirtual #26                 // Method java/util/concurrent/ConcurrentHashMap.get:(Ljava/lang/Object;)Ljava/lang/Object;
      11: checkcast     #27                 // class org/apache/hadoop/hbase/regionserver/MetricsTableWrapperAggregateImpl$MetricsTableValues
      14: astore_2
      15: aload_2
      16: ifnonnull     21
      19: lconst_0
      20: lreturn
      21: aload_2
      22: getfield      #28                 // Field org/apache/hadoop/hbase/regionserver/MetricsTableWrapperAggregateImpl$MetricsTableValues.readRequestCount:J
      25: aload_2
      26: getfield      #31                 // Field org/apache/hadoop/hbase/regionserver/MetricsTableWrapperAggregateImpl$MetricsTableValues.writeRequestCount:J
      29: ladd
      30: lreturn

  public long getMemStoreSize(java.lang.String);
    Code:
       0: aload_0
       1: getfield      #1                  // Field metricsTableMap:Ljava/util/concurrent/ConcurrentHashMap;
       4: aload_1
       5: invokestatic  #25                 // Method org/apache/hadoop/hbase/TableName.valueOf:(Ljava/lang/String;)Lorg/apache/hadoop/hbase/TableName;
       8: invokevirtual #26                 // Method java/util/concurrent/ConcurrentHashMap.get:(Ljava/lang/Object;)Ljava/lang/Object;
      11: checkcast     #27                 // class org/apache/hadoop/hbase/regionserver/MetricsTableWrapperAggregateImpl$MetricsTableValues
      14: astore_2
      15: aload_2
      16: ifnonnull     21
      19: lconst_0
      20: lreturn
      21: aload_2
      22: getfield      #32                 // Field org/apache/hadoop/hbase/regionserver/MetricsTableWrapperAggregateImpl$MetricsTableValues.memstoreSize:J
      25: lreturn

  public long getStoreFileSize(java.lang.String);
    Code:
       0: aload_0
       1: getfield      #1                  // Field metricsTableMap:Ljava/util/concurrent/ConcurrentHashMap;
       4: aload_1
       5: invokestatic  #25                 // Method org/apache/hadoop/hbase/TableName.valueOf:(Ljava/lang/String;)Lorg/apache/hadoop/hbase/TableName;
       8: invokevirtual #26                 // Method java/util/concurrent/ConcurrentHashMap.get:(Ljava/lang/Object;)Ljava/lang/Object;
      11: checkcast     #27                 // class org/apache/hadoop/hbase/regionserver/MetricsTableWrapperAggregateImpl$MetricsTableValues
      14: astore_2
      15: aload_2
      16: ifnonnull     21
      19: lconst_0
      20: lreturn
      21: aload_2
      22: getfield      #33                 // Field org/apache/hadoop/hbase/regionserver/MetricsTableWrapperAggregateImpl$MetricsTableValues.storeFileSize:J
      25: lreturn

  public long getTableSize(java.lang.String);
    Code:
       0: aload_0
       1: getfield      #1                  // Field metricsTableMap:Ljava/util/concurrent/ConcurrentHashMap;
       4: aload_1
       5: invokestatic  #25                 // Method org/apache/hadoop/hbase/TableName.valueOf:(Ljava/lang/String;)Lorg/apache/hadoop/hbase/TableName;
       8: invokevirtual #26                 // Method java/util/concurrent/ConcurrentHashMap.get:(Ljava/lang/Object;)Ljava/lang/Object;
      11: checkcast     #27                 // class org/apache/hadoop/hbase/regionserver/MetricsTableWrapperAggregateImpl$MetricsTableValues
      14: astore_2
      15: aload_2
      16: ifnonnull     21
      19: lconst_0
      20: lreturn
      21: aload_2
      22: getfield      #32                 // Field org/apache/hadoop/hbase/regionserver/MetricsTableWrapperAggregateImpl$MetricsTableValues.memstoreSize:J
      25: aload_2
      26: getfield      #33                 // Field org/apache/hadoop/hbase/regionserver/MetricsTableWrapperAggregateImpl$MetricsTableValues.storeFileSize:J
      29: ladd
      30: lreturn

  public long getNumRegions(java.lang.String);
    Code:
       0: aload_0
       1: getfield      #1                  // Field metricsTableMap:Ljava/util/concurrent/ConcurrentHashMap;
       4: aload_1
       5: invokestatic  #25                 // Method org/apache/hadoop/hbase/TableName.valueOf:(Ljava/lang/String;)Lorg/apache/hadoop/hbase/TableName;
       8: invokevirtual #26                 // Method java/util/concurrent/ConcurrentHashMap.get:(Ljava/lang/Object;)Ljava/lang/Object;
      11: checkcast     #27                 // class org/apache/hadoop/hbase/regionserver/MetricsTableWrapperAggregateImpl$MetricsTableValues
      14: astore_2
      15: aload_2
      16: ifnonnull     21
      19: lconst_0
      20: lreturn
      21: aload_2
      22: getfield      #34                 // Field org/apache/hadoop/hbase/regionserver/MetricsTableWrapperAggregateImpl$MetricsTableValues.regionCount:J
      25: lreturn

  public long getNumStores(java.lang.String);
    Code:
       0: aload_0
       1: getfield      #1                  // Field metricsTableMap:Ljava/util/concurrent/ConcurrentHashMap;
       4: aload_1
       5: invokestatic  #25                 // Method org/apache/hadoop/hbase/TableName.valueOf:(Ljava/lang/String;)Lorg/apache/hadoop/hbase/TableName;
       8: invokevirtual #26                 // Method java/util/concurrent/ConcurrentHashMap.get:(Ljava/lang/Object;)Ljava/lang/Object;
      11: checkcast     #27                 // class org/apache/hadoop/hbase/regionserver/MetricsTableWrapperAggregateImpl$MetricsTableValues
      14: astore_2
      15: aload_2
      16: ifnonnull     21
      19: lconst_0
      20: lreturn
      21: aload_2
      22: getfield      #35                 // Field org/apache/hadoop/hbase/regionserver/MetricsTableWrapperAggregateImpl$MetricsTableValues.storeCount:J
      25: lreturn

  public long getNumStoreFiles(java.lang.String);
    Code:
       0: aload_0
       1: getfield      #1                  // Field metricsTableMap:Ljava/util/concurrent/ConcurrentHashMap;
       4: aload_1
       5: invokestatic  #25                 // Method org/apache/hadoop/hbase/TableName.valueOf:(Ljava/lang/String;)Lorg/apache/hadoop/hbase/TableName;
       8: invokevirtual #26                 // Method java/util/concurrent/ConcurrentHashMap.get:(Ljava/lang/Object;)Ljava/lang/Object;
      11: checkcast     #27                 // class org/apache/hadoop/hbase/regionserver/MetricsTableWrapperAggregateImpl$MetricsTableValues
      14: astore_2
      15: aload_2
      16: ifnonnull     21
      19: lconst_0
      20: lreturn
      21: aload_2
      22: getfield      #36                 // Field org/apache/hadoop/hbase/regionserver/MetricsTableWrapperAggregateImpl$MetricsTableValues.storeFileCount:J
      25: lreturn

  public long getMaxStoreFileAge(java.lang.String);
    Code:
       0: aload_0
       1: getfield      #1                  // Field metricsTableMap:Ljava/util/concurrent/ConcurrentHashMap;
       4: aload_1
       5: invokestatic  #25                 // Method org/apache/hadoop/hbase/TableName.valueOf:(Ljava/lang/String;)Lorg/apache/hadoop/hbase/TableName;
       8: invokevirtual #26                 // Method java/util/concurrent/ConcurrentHashMap.get:(Ljava/lang/Object;)Ljava/lang/Object;
      11: checkcast     #27                 // class org/apache/hadoop/hbase/regionserver/MetricsTableWrapperAggregateImpl$MetricsTableValues
      14: astore_2
      15: aload_2
      16: ifnonnull     21
      19: lconst_0
      20: lreturn
      21: aload_2
      22: getfield      #37                 // Field org/apache/hadoop/hbase/regionserver/MetricsTableWrapperAggregateImpl$MetricsTableValues.maxStoreFileAge:J
      25: lreturn

  public long getMinStoreFileAge(java.lang.String);
    Code:
       0: aload_0
       1: getfield      #1                  // Field metricsTableMap:Ljava/util/concurrent/ConcurrentHashMap;
       4: aload_1
       5: invokestatic  #25                 // Method org/apache/hadoop/hbase/TableName.valueOf:(Ljava/lang/String;)Lorg/apache/hadoop/hbase/TableName;
       8: invokevirtual #26                 // Method java/util/concurrent/ConcurrentHashMap.get:(Ljava/lang/Object;)Ljava/lang/Object;
      11: checkcast     #27                 // class org/apache/hadoop/hbase/regionserver/MetricsTableWrapperAggregateImpl$MetricsTableValues
      14: astore_2
      15: aload_2
      16: ifnonnull     21
      19: lconst_0
      20: lreturn
      21: aload_2
      22: getfield      #38                 // Field org/apache/hadoop/hbase/regionserver/MetricsTableWrapperAggregateImpl$MetricsTableValues.minStoreFileAge:J
      25: ldc2_w        #40                 // long 9223372036854775807l
      28: lcmp
      29: ifne          36
      32: lconst_0
      33: goto          40
      36: aload_2
      37: getfield      #38                 // Field org/apache/hadoop/hbase/regionserver/MetricsTableWrapperAggregateImpl$MetricsTableValues.minStoreFileAge:J
      40: lreturn

  public long getAvgStoreFileAge(java.lang.String);
    Code:
       0: aload_0
       1: getfield      #1                  // Field metricsTableMap:Ljava/util/concurrent/ConcurrentHashMap;
       4: aload_1
       5: invokestatic  #25                 // Method org/apache/hadoop/hbase/TableName.valueOf:(Ljava/lang/String;)Lorg/apache/hadoop/hbase/TableName;
       8: invokevirtual #26                 // Method java/util/concurrent/ConcurrentHashMap.get:(Ljava/lang/Object;)Ljava/lang/Object;
      11: checkcast     #27                 // class org/apache/hadoop/hbase/regionserver/MetricsTableWrapperAggregateImpl$MetricsTableValues
      14: astore_2
      15: aload_2
      16: ifnonnull     21
      19: lconst_0
      20: lreturn
      21: aload_2
      22: getfield      #36                 // Field org/apache/hadoop/hbase/regionserver/MetricsTableWrapperAggregateImpl$MetricsTableValues.storeFileCount:J
      25: lconst_0
      26: lcmp
      27: ifne          34
      30: lconst_0
      31: goto          43
      34: aload_2
      35: getfield      #42                 // Field org/apache/hadoop/hbase/regionserver/MetricsTableWrapperAggregateImpl$MetricsTableValues.totalStoreFileAge:J
      38: aload_2
      39: getfield      #36                 // Field org/apache/hadoop/hbase/regionserver/MetricsTableWrapperAggregateImpl$MetricsTableValues.storeFileCount:J
      42: ldiv
      43: lreturn

  public long getNumReferenceFiles(java.lang.String);
    Code:
       0: aload_0
       1: getfield      #1                  // Field metricsTableMap:Ljava/util/concurrent/ConcurrentHashMap;
       4: aload_1
       5: invokestatic  #25                 // Method org/apache/hadoop/hbase/TableName.valueOf:(Ljava/lang/String;)Lorg/apache/hadoop/hbase/TableName;
       8: invokevirtual #26                 // Method java/util/concurrent/ConcurrentHashMap.get:(Ljava/lang/Object;)Ljava/lang/Object;
      11: checkcast     #27                 // class org/apache/hadoop/hbase/regionserver/MetricsTableWrapperAggregateImpl$MetricsTableValues
      14: astore_2
      15: aload_2
      16: ifnonnull     21
      19: lconst_0
      20: lreturn
      21: aload_2
      22: getfield      #43                 // Field org/apache/hadoop/hbase/regionserver/MetricsTableWrapperAggregateImpl$MetricsTableValues.referenceFileCount:J
      25: lreturn

  public long getAvgRegionSize(java.lang.String);
    Code:
       0: aload_0
       1: getfield      #1                  // Field metricsTableMap:Ljava/util/concurrent/ConcurrentHashMap;
       4: aload_1
       5: invokestatic  #25                 // Method org/apache/hadoop/hbase/TableName.valueOf:(Ljava/lang/String;)Lorg/apache/hadoop/hbase/TableName;
       8: invokevirtual #26                 // Method java/util/concurrent/ConcurrentHashMap.get:(Ljava/lang/Object;)Ljava/lang/Object;
      11: checkcast     #27                 // class org/apache/hadoop/hbase/regionserver/MetricsTableWrapperAggregateImpl$MetricsTableValues
      14: astore_2
      15: aload_2
      16: ifnonnull     21
      19: lconst_0
      20: lreturn
      21: aload_2
      22: getfield      #34                 // Field org/apache/hadoop/hbase/regionserver/MetricsTableWrapperAggregateImpl$MetricsTableValues.regionCount:J
      25: lconst_0
      26: lcmp
      27: ifne          34
      30: lconst_0
      31: goto          48
      34: aload_2
      35: getfield      #32                 // Field org/apache/hadoop/hbase/regionserver/MetricsTableWrapperAggregateImpl$MetricsTableValues.memstoreSize:J
      38: aload_2
      39: getfield      #33                 // Field org/apache/hadoop/hbase/regionserver/MetricsTableWrapperAggregateImpl$MetricsTableValues.storeFileSize:J
      42: ladd
      43: aload_2
      44: getfield      #34                 // Field org/apache/hadoop/hbase/regionserver/MetricsTableWrapperAggregateImpl$MetricsTableValues.regionCount:J
      47: ldiv
      48: lreturn

  public long getCpRequestCount(java.lang.String);
    Code:
       0: aload_0
       1: getfield      #1                  // Field metricsTableMap:Ljava/util/concurrent/ConcurrentHashMap;
       4: aload_1
       5: invokestatic  #25                 // Method org/apache/hadoop/hbase/TableName.valueOf:(Ljava/lang/String;)Lorg/apache/hadoop/hbase/TableName;
       8: invokevirtual #26                 // Method java/util/concurrent/ConcurrentHashMap.get:(Ljava/lang/Object;)Ljava/lang/Object;
      11: checkcast     #27                 // class org/apache/hadoop/hbase/regionserver/MetricsTableWrapperAggregateImpl$MetricsTableValues
      14: astore_2
      15: aload_2
      16: ifnonnull     21
      19: lconst_0
      20: lreturn
      21: aload_2
      22: getfield      #29                 // Field org/apache/hadoop/hbase/regionserver/MetricsTableWrapperAggregateImpl$MetricsTableValues.cpRequestCount:J
      25: lreturn

  public void close() throws java.io.IOException;
    Code:
       0: aload_0
       1: getfield      #24                 // Field tableMetricsUpdateTask:Ljava/util/concurrent/ScheduledFuture;
       4: iconst_1
       5: invokeinterface #44,  2           // InterfaceMethod java/util/concurrent/ScheduledFuture.cancel:(Z)Z
      10: pop
      11: return

  static org.apache.hadoop.hbase.regionserver.HRegionServer access$000(org.apache.hadoop.hbase.regionserver.MetricsTableWrapperAggregateImpl);
    Code:
       0: aload_0
       1: getfield      #2                  // Field regionServer:Lorg/apache/hadoop/hbase/regionserver/HRegionServer;
       4: areturn

  static java.util.concurrent.ConcurrentHashMap access$200(org.apache.hadoop.hbase.regionserver.MetricsTableWrapperAggregateImpl);
    Code:
       0: aload_0
       1: getfield      #1                  // Field metricsTableMap:Ljava/util/concurrent/ConcurrentHashMap;
       4: areturn
}
