Compiled from "MetricsRegionAggregateSourceImpl.java"
public class org.apache.hadoop.hbase.regionserver.MetricsRegionAggregateSourceImpl extends org.apache.hadoop.hbase.metrics.BaseSourceImpl implements org.apache.hadoop.hbase.regionserver.MetricsRegionAggregateSource {
  public org.apache.hadoop.hbase.regionserver.MetricsRegionAggregateSourceImpl();
    Code:
       0: aload_0
       1: ldc           #2                  // String Regions
       3: ldc           #3                  // String Metrics about HBase RegionServer regions and tables
       5: ldc           #4                  // String regionserver
       7: ldc           #5                  // String RegionServer,sub=Regions
       9: invokespecial #6                  // Method "<init>":(Ljava/lang/String;Ljava/lang/String;Ljava/lang/String;Ljava/lang/String;)V
      12: return

  public org.apache.hadoop.hbase.regionserver.MetricsRegionAggregateSourceImpl(java.lang.String, java.lang.String, java.lang.String, java.lang.String);
    Code:
       0: aload_0
       1: aload_1
       2: aload_2
       3: aload_3
       4: aload         4
       6: invokespecial #7                  // Method org/apache/hadoop/hbase/metrics/BaseSourceImpl."<init>":(Ljava/lang/String;Ljava/lang/String;Ljava/lang/String;Ljava/lang/String;)V
       9: aload_0
      10: new           #8                  // class org/apache/hadoop/metrics2/lib/MetricsExecutorImpl
      13: dup
      14: invokespecial #9                  // Method org/apache/hadoop/metrics2/lib/MetricsExecutorImpl."<init>":()V
      17: putfield      #10                 // Field executor:Lorg/apache/hadoop/metrics2/lib/MetricsExecutorImpl;
      20: aload_0
      21: new           #11                 // class java/util/concurrent/ConcurrentHashMap
      24: dup
      25: invokespecial #12                 // Method java/util/concurrent/ConcurrentHashMap."<init>":()V
      28: invokestatic  #13                 // Method java/util/Collections.newSetFromMap:(Ljava/util/Map;)Ljava/util/Set;
      31: putfield      #14                 // Field regionSources:Ljava/util/Set;
      34: aload_0
      35: getfield      #10                 // Field executor:Lorg/apache/hadoop/metrics2/lib/MetricsExecutorImpl;
      38: invokevirtual #15                 // Method org/apache/hadoop/metrics2/lib/MetricsExecutorImpl.getExecutor:()Ljava/util/concurrent/ScheduledExecutorService;
      41: new           #16                 // class org/apache/hadoop/hbase/regionserver/MetricsRegionAggregateSourceImpl$1
      44: dup
      45: aload_0
      46: invokespecial #17                 // Method org/apache/hadoop/hbase/regionserver/MetricsRegionAggregateSourceImpl$1."<init>":(Lorg/apache/hadoop/hbase/regionserver/MetricsRegionAggregateSourceImpl;)V
      49: ldc2_w        #18                 // long 5l
      52: ldc2_w        #18                 // long 5l
      55: getstatic     #20                 // Field java/util/concurrent/TimeUnit.MINUTES:Ljava/util/concurrent/TimeUnit;
      58: invokeinterface #21,  7           // InterfaceMethod java/util/concurrent/ScheduledExecutorService.scheduleWithFixedDelay:(Ljava/lang/Runnable;JJLjava/util/concurrent/TimeUnit;)Ljava/util/concurrent/ScheduledFuture;
      63: pop
      64: return

  public void register(org.apache.hadoop.hbase.regionserver.MetricsRegionSource);
    Code:
       0: aload_0
       1: getfield      #14                 // Field regionSources:Ljava/util/Set;
       4: aload_1
       5: invokeinterface #22,  2           // InterfaceMethod java/util/Set.add:(Ljava/lang/Object;)Z
      10: pop
      11: aload_0
      12: invokespecial #23                 // Method clearCache:()V
      15: return

  public void deregister(org.apache.hadoop.hbase.regionserver.MetricsRegionSource);
    Code:
       0: aload_0
       1: getfield      #14                 // Field regionSources:Ljava/util/Set;
       4: aload_1
       5: invokeinterface #24,  2           // InterfaceMethod java/util/Set.remove:(Ljava/lang/Object;)Z
      10: pop
      11: goto          58
      14: astore_2
      15: getstatic     #26                 // Field LOG:Lorg/slf4j/Logger;
      18: new           #27                 // class java/lang/StringBuilder
      21: dup
      22: invokespecial #28                 // Method java/lang/StringBuilder."<init>":()V
      25: ldc           #29                 // String Error trying to remove
      27: invokevirtual #30                 // Method java/lang/StringBuilder.append:(Ljava/lang/String;)Ljava/lang/StringBuilder;
      30: aload_1
      31: invokevirtual #31                 // Method java/lang/StringBuilder.append:(Ljava/lang/Object;)Ljava/lang/StringBuilder;
      34: ldc           #32                 // String  from
      36: invokevirtual #30                 // Method java/lang/StringBuilder.append:(Ljava/lang/String;)Ljava/lang/StringBuilder;
      39: aload_0
      40: invokevirtual #33                 // Method java/lang/Object.getClass:()Ljava/lang/Class;
      43: invokevirtual #34                 // Method java/lang/Class.getSimpleName:()Ljava/lang/String;
      46: invokevirtual #30                 // Method java/lang/StringBuilder.append:(Ljava/lang/String;)Ljava/lang/StringBuilder;
      49: invokevirtual #35                 // Method java/lang/StringBuilder.toString:()Ljava/lang/String;
      52: aload_2
      53: invokeinterface #36,  3           // InterfaceMethod org/slf4j/Logger.info:(Ljava/lang/String;Ljava/lang/Throwable;)V
      58: aload_0
      59: invokespecial #23                 // Method clearCache:()V
      62: return
    Exception table:
       from    to  target type
           0    11    14   Class java/lang/Exception

  public void getMetrics(org.apache.hadoop.metrics2.MetricsCollector, boolean);
    Code:
       0: aload_1
       1: aload_0
       2: getfield      #38                 // Field metricsName:Ljava/lang/String;
       5: invokeinterface #39,  2           // InterfaceMethod org/apache/hadoop/metrics2/MetricsCollector.addRecord:(Ljava/lang/String;)Lorg/apache/hadoop/metrics2/MetricsRecordBuilder;
      10: astore_3
      11: aload_0
      12: getfield      #14                 // Field regionSources:Ljava/util/Set;
      15: ifnull        102
      18: aload_0
      19: getfield      #14                 // Field regionSources:Ljava/util/Set;
      22: invokeinterface #40,  1           // InterfaceMethod java/util/Set.iterator:()Ljava/util/Iterator;
      27: astore        4
      29: aload         4
      31: invokeinterface #41,  1           // InterfaceMethod java/util/Iterator.hasNext:()Z
      36: ifeq          72
      39: aload         4
      41: invokeinterface #42,  1           // InterfaceMethod java/util/Iterator.next:()Ljava/lang/Object;
      46: checkcast     #43                 // class org/apache/hadoop/hbase/regionserver/MetricsRegionSource
      49: astore        5
      51: aload         5
      53: instanceof    #44                 // class org/apache/hadoop/hbase/regionserver/MetricsRegionSourceImpl
      56: ifeq          69
      59: aload         5
      61: checkcast     #44                 // class org/apache/hadoop/hbase/regionserver/MetricsRegionSourceImpl
      64: aload_3
      65: iload_2
      66: invokevirtual #45                 // Method org/apache/hadoop/hbase/regionserver/MetricsRegionSourceImpl.snapshot:(Lorg/apache/hadoop/metrics2/MetricsRecordBuilder;Z)V
      69: goto          29
      72: aload_3
      73: ldc           #46                 // String numRegions
      75: ldc           #47                 // String Number of regions in the metrics system
      77: invokestatic  #48                 // Method org/apache/hadoop/hbase/metrics/Interns.info:(Ljava/lang/String;Ljava/lang/String;)Lorg/apache/hadoop/metrics2/MetricsInfo;
      80: aload_0
      81: getfield      #14                 // Field regionSources:Ljava/util/Set;
      84: invokeinterface #49,  1           // InterfaceMethod java/util/Set.size:()I
      89: invokevirtual #50                 // Method org/apache/hadoop/metrics2/MetricsRecordBuilder.addGauge:(Lorg/apache/hadoop/metrics2/MetricsInfo;I)Lorg/apache/hadoop/metrics2/MetricsRecordBuilder;
      92: pop
      93: aload_0
      94: getfield      #51                 // Field metricsRegistry:Lorg/apache/hadoop/metrics2/lib/DynamicMetricsRegistry;
      97: aload_3
      98: iload_2
      99: invokevirtual #52                 // Method org/apache/hadoop/metrics2/lib/DynamicMetricsRegistry.snapshot:(Lorg/apache/hadoop/metrics2/MetricsRecordBuilder;Z)V
     102: return

  static {};
    Code:
       0: ldc           #53                 // class org/apache/hadoop/hbase/regionserver/MetricsRegionAggregateSourceImpl
       2: invokestatic  #54                 // Method org/slf4j/LoggerFactory.getLogger:(Ljava/lang/Class;)Lorg/slf4j/Logger;
       5: putstatic     #26                 // Field LOG:Lorg/slf4j/Logger;
       8: return
}
