Compiled from "MetricsAssertHelperImpl.java"
public class org.apache.hadoop.hbase.test.MetricsAssertHelperImpl$MockMetricsBuilder implements org.apache.hadoop.metrics2.MetricsCollector {
  final org.apache.hadoop.hbase.test.MetricsAssertHelperImpl this$0;

  public org.apache.hadoop.hbase.test.MetricsAssertHelperImpl$MockMetricsBuilder(org.apache.hadoop.hbase.test.MetricsAssertHelperImpl);
    Code:
       0: aload_0
       1: aload_1
       2: putfield      #1                  // Field this$0:Lorg/apache/hadoop/hbase/test/MetricsAssertHelperImpl;
       5: aload_0
       6: invokespecial #2                  // Method java/lang/Object."<init>":()V
       9: return

  public org.apache.hadoop.metrics2.MetricsRecordBuilder addRecord(java.lang.String);
    Code:
       0: new           #3                  // class org/apache/hadoop/hbase/test/MetricsAssertHelperImpl$MockRecordBuilder
       3: dup
       4: aload_0
       5: getfield      #1                  // Field this$0:Lorg/apache/hadoop/hbase/test/MetricsAssertHelperImpl;
       8: aload_0
       9: invokespecial #4                  // Method org/apache/hadoop/hbase/test/MetricsAssertHelperImpl$MockRecordBuilder."<init>":(Lorg/apache/hadoop/hbase/test/MetricsAssertHelperImpl;Lorg/apache/hadoop/metrics2/MetricsCollector;)V
      12: areturn

  public org.apache.hadoop.metrics2.MetricsRecordBuilder addRecord(org.apache.hadoop.metrics2.MetricsInfo);
    Code:
       0: new           #3                  // class org/apache/hadoop/hbase/test/MetricsAssertHelperImpl$MockRecordBuilder
       3: dup
       4: aload_0
       5: getfield      #1                  // Field this$0:Lorg/apache/hadoop/hbase/test/MetricsAssertHelperImpl;
       8: aload_0
       9: invokespecial #4                  // Method org/apache/hadoop/hbase/test/MetricsAssertHelperImpl$MockRecordBuilder."<init>":(Lorg/apache/hadoop/hbase/test/MetricsAssertHelperImpl;Lorg/apache/hadoop/metrics2/MetricsCollector;)V
      12: areturn
}
