Compiled from "MetricsHeapMemoryManager.java"
public class org.apache.hadoop.hbase.regionserver.MetricsHeapMemoryManager {
  public org.apache.hadoop.hbase.regionserver.MetricsHeapMemoryManager();
    Code:
       0: aload_0
       1: ldc           #1                  // class org/apache/hadoop/hbase/regionserver/MetricsRegionServerSourceFactory
       3: invokestatic  #2                  // Method org/apache/hadoop/hbase/CompatibilitySingletonFactory.getInstance:(Ljava/lang/Class;)Ljava/lang/Object;
       6: checkcast     #1                  // class org/apache/hadoop/hbase/regionserver/MetricsRegionServerSourceFactory
       9: invokeinterface #3,  1            // InterfaceMethod org/apache/hadoop/hbase/regionserver/MetricsRegionServerSourceFactory.getHeapMemoryManager:()Lorg/apache/hadoop/hbase/regionserver/MetricsHeapMemoryManagerSource;
      14: invokespecial #4                  // Method "<init>":(Lorg/apache/hadoop/hbase/regionserver/MetricsHeapMemoryManagerSource;)V
      17: return

  public org.apache.hadoop.hbase.regionserver.MetricsHeapMemoryManager(org.apache.hadoop.hbase.regionserver.MetricsHeapMemoryManagerSource);
    Code:
       0: aload_0
       1: invokespecial #5                  // Method java/lang/Object."<init>":()V
       4: aload_0
       5: aload_1
       6: putfield      #6                  // Field source:Lorg/apache/hadoop/hbase/regionserver/MetricsHeapMemoryManagerSource;
       9: return

  public org.apache.hadoop.hbase.regionserver.MetricsHeapMemoryManagerSource getMetricsSource();
    Code:
       0: aload_0
       1: getfield      #6                  // Field source:Lorg/apache/hadoop/hbase/regionserver/MetricsHeapMemoryManagerSource;
       4: areturn

  public void updateBlockedFlushCount(long);
    Code:
       0: aload_0
       1: getfield      #6                  // Field source:Lorg/apache/hadoop/hbase/regionserver/MetricsHeapMemoryManagerSource;
       4: lload_1
       5: invokeinterface #7,  3            // InterfaceMethod org/apache/hadoop/hbase/regionserver/MetricsHeapMemoryManagerSource.updateBlockedFlushCount:(J)V
      10: return

  public void updateUnblockedFlushCount(long);
    Code:
       0: aload_0
       1: getfield      #6                  // Field source:Lorg/apache/hadoop/hbase/regionserver/MetricsHeapMemoryManagerSource;
       4: lload_1
       5: invokeinterface #8,  3            // InterfaceMethod org/apache/hadoop/hbase/regionserver/MetricsHeapMemoryManagerSource.updateUnblockedFlushCount:(J)V
      10: return

  public void setCurBlockCacheSizeGauge(long);
    Code:
       0: aload_0
       1: getfield      #6                  // Field source:Lorg/apache/hadoop/hbase/regionserver/MetricsHeapMemoryManagerSource;
       4: lload_1
       5: invokeinterface #9,  3            // InterfaceMethod org/apache/hadoop/hbase/regionserver/MetricsHeapMemoryManagerSource.setCurBlockCacheSizeGauge:(J)V
      10: return

  public void setCurMemStoreSizeGauge(long);
    Code:
       0: aload_0
       1: getfield      #6                  // Field source:Lorg/apache/hadoop/hbase/regionserver/MetricsHeapMemoryManagerSource;
       4: lload_1
       5: invokeinterface #10,  3           // InterfaceMethod org/apache/hadoop/hbase/regionserver/MetricsHeapMemoryManagerSource.setCurMemStoreSizeGauge:(J)V
      10: return

  public void updateMemStoreDeltaSizeHistogram(int);
    Code:
       0: aload_0
       1: getfield      #6                  // Field source:Lorg/apache/hadoop/hbase/regionserver/MetricsHeapMemoryManagerSource;
       4: iload_1
       5: invokeinterface #11,  2           // InterfaceMethod org/apache/hadoop/hbase/regionserver/MetricsHeapMemoryManagerSource.updateMemStoreDeltaSizeHistogram:(I)V
      10: return

  public void updateBlockCacheDeltaSizeHistogram(int);
    Code:
       0: aload_0
       1: getfield      #6                  // Field source:Lorg/apache/hadoop/hbase/regionserver/MetricsHeapMemoryManagerSource;
       4: iload_1
       5: invokeinterface #12,  2           // InterfaceMethod org/apache/hadoop/hbase/regionserver/MetricsHeapMemoryManagerSource.updateBlockCacheDeltaSizeHistogram:(I)V
      10: return

  public void increaseTunerDoNothingCounter();
    Code:
       0: aload_0
       1: getfield      #6                  // Field source:Lorg/apache/hadoop/hbase/regionserver/MetricsHeapMemoryManagerSource;
       4: invokeinterface #13,  1           // InterfaceMethod org/apache/hadoop/hbase/regionserver/MetricsHeapMemoryManagerSource.increaseTunerDoNothingCounter:()V
       9: return

  public void increaseAboveHeapOccupancyLowWatermarkCounter();
    Code:
       0: aload_0
       1: getfield      #6                  // Field source:Lorg/apache/hadoop/hbase/regionserver/MetricsHeapMemoryManagerSource;
       4: invokeinterface #14,  1           // InterfaceMethod org/apache/hadoop/hbase/regionserver/MetricsHeapMemoryManagerSource.increaseAboveHeapOccupancyLowWatermarkCounter:()V
       9: return
}
