Compiled from "MetricsInfoImpl.java"
class org.apache.hadoop.hbase.metrics.MetricsInfoImpl implements org.apache.hadoop.metrics2.MetricsInfo {
  org.apache.hadoop.hbase.metrics.MetricsInfoImpl(java.lang.String, java.lang.String);
    Code:
       0: aload_0
       1: invokespecial #1                  // Method java/lang/Object."<init>":()V
       4: aload_0
       5: aload_1
       6: ldc           #2                  // String name
       8: invokestatic  #3                  // Method org/apache/hbase/thirdparty/com/google/common/base/Preconditions.checkNotNull:(Ljava/lang/Object;Ljava/lang/Object;)Ljava/lang/Object;
      11: checkcast     #4                  // class java/lang/String
      14: putfield      #5                  // Field name:Ljava/lang/String;
      17: aload_0
      18: aload_2
      19: ldc           #6                  // String description
      21: invokestatic  #3                  // Method org/apache/hbase/thirdparty/com/google/common/base/Preconditions.checkNotNull:(Ljava/lang/Object;Ljava/lang/Object;)Ljava/lang/Object;
      24: checkcast     #4                  // class java/lang/String
      27: putfield      #7                  // Field description:Ljava/lang/String;
      30: return

  public java.lang.String name();
    Code:
       0: aload_0
       1: getfield      #5                  // Field name:Ljava/lang/String;
       4: areturn

  public java.lang.String description();
    Code:
       0: aload_0
       1: getfield      #7                  // Field description:Ljava/lang/String;
       4: areturn

  public boolean equals(java.lang.Object);
    Code:
       0: aload_1
       1: instanceof    #8                  // class org/apache/hadoop/metrics2/MetricsInfo
       4: ifeq          50
       7: aload_1
       8: checkcast     #8                  // class org/apache/hadoop/metrics2/MetricsInfo
      11: astore_2
      12: aload_0
      13: getfield      #5                  // Field name:Ljava/lang/String;
      16: aload_2
      17: invokeinterface #9,  1            // InterfaceMethod org/apache/hadoop/metrics2/MetricsInfo.name:()Ljava/lang/String;
      22: invokestatic  #10                 // Method org/apache/hbase/thirdparty/com/google/common/base/Objects.equal:(Ljava/lang/Object;Ljava/lang/Object;)Z
      25: ifeq          48
      28: aload_0
      29: getfield      #7                  // Field description:Ljava/lang/String;
      32: aload_2
      33: invokeinterface #11,  1           // InterfaceMethod org/apache/hadoop/metrics2/MetricsInfo.description:()Ljava/lang/String;
      38: invokestatic  #10                 // Method org/apache/hbase/thirdparty/com/google/common/base/Objects.equal:(Ljava/lang/Object;Ljava/lang/Object;)Z
      41: ifeq          48
      44: iconst_1
      45: goto          49
      48: iconst_0
      49: ireturn
      50: iconst_0
      51: ireturn

  public int hashCode();
    Code:
       0: iconst_2
       1: anewarray     #12                 // class java/lang/Object
       4: dup
       5: iconst_0
       6: aload_0
       7: getfield      #5                  // Field name:Ljava/lang/String;
      10: aastore
      11: dup
      12: iconst_1
      13: aload_0
      14: getfield      #7                  // Field description:Ljava/lang/String;
      17: aastore
      18: invokestatic  #13                 // Method org/apache/hbase/thirdparty/com/google/common/base/Objects.hashCode:([Ljava/lang/Object;)I
      21: ireturn

  public java.lang.String toString();
    Code:
       0: aload_0
       1: invokestatic  #14                 // Method org/apache/hbase/thirdparty/com/google/common/base/MoreObjects.toStringHelper:(Ljava/lang/Object;)Lorg/apache/hbase/thirdparty/com/google/common/base/MoreObjects$ToStringHelper;
       4: ldc           #2                  // String name
       6: aload_0
       7: getfield      #5                  // Field name:Ljava/lang/String;
      10: invokevirtual #15                 // Method org/apache/hbase/thirdparty/com/google/common/base/MoreObjects$ToStringHelper.add:(Ljava/lang/String;Ljava/lang/Object;)Lorg/apache/hbase/thirdparty/com/google/common/base/MoreObjects$ToStringHelper;
      13: ldc           #6                  // String description
      15: aload_0
      16: getfield      #7                  // Field description:Ljava/lang/String;
      19: invokevirtual #15                 // Method org/apache/hbase/thirdparty/com/google/common/base/MoreObjects$ToStringHelper.add:(Ljava/lang/String;Ljava/lang/Object;)Lorg/apache/hbase/thirdparty/com/google/common/base/MoreObjects$ToStringHelper;
      22: invokevirtual #16                 // Method org/apache/hbase/thirdparty/com/google/common/base/MoreObjects$ToStringHelper.toString:()Ljava/lang/String;
      25: areturn
}
