Compiled from "MetricsStochasticBalancer.java"
public class org.apache.hadoop.hbase.master.balancer.MetricsStochasticBalancer extends org.apache.hadoop.hbase.master.balancer.MetricsBalancer {
  public org.apache.hadoop.hbase.master.balancer.MetricsStochasticBalancer();
    Code:
       0: aload_0
       1: invokespecial #1                  // Method org/apache/hadoop/hbase/master/balancer/MetricsBalancer."<init>":()V
       4: aload_0
       5: aconst_null
       6: putfield      #2                  // Field stochasticSource:Lorg/apache/hadoop/hbase/master/balancer/MetricsStochasticBalancerSource;
       9: aload_0
      10: invokevirtual #3                  // Method initSource:()V
      13: return

  protected void initSource();
    Code:
       0: aload_0
       1: ldc           #4                  // class org/apache/hadoop/hbase/master/balancer/MetricsStochasticBalancerSource
       3: invokestatic  #5                  // Method org/apache/hadoop/hbase/CompatibilitySingletonFactory.getInstance:(Ljava/lang/Class;)Ljava/lang/Object;
       6: checkcast     #4                  // class org/apache/hadoop/hbase/master/balancer/MetricsStochasticBalancerSource
       9: putfield      #2                  // Field stochasticSource:Lorg/apache/hadoop/hbase/master/balancer/MetricsStochasticBalancerSource;
      12: return

  public void balanceCluster(long);
    Code:
       0: aload_0
       1: getfield      #2                  // Field stochasticSource:Lorg/apache/hadoop/hbase/master/balancer/MetricsStochasticBalancerSource;
       4: lload_1
       5: invokeinterface #6,  3            // InterfaceMethod org/apache/hadoop/hbase/master/balancer/MetricsStochasticBalancerSource.updateBalanceCluster:(J)V
      10: return

  public void incrMiscInvocations();
    Code:
       0: aload_0
       1: getfield      #2                  // Field stochasticSource:Lorg/apache/hadoop/hbase/master/balancer/MetricsStochasticBalancerSource;
       4: invokeinterface #7,  1            // InterfaceMethod org/apache/hadoop/hbase/master/balancer/MetricsStochasticBalancerSource.incrMiscInvocations:()V
       9: return

  public void balancerStatus(boolean);
    Code:
       0: aload_0
       1: getfield      #2                  // Field stochasticSource:Lorg/apache/hadoop/hbase/master/balancer/MetricsStochasticBalancerSource;
       4: iload_1
       5: invokeinterface #8,  2            // InterfaceMethod org/apache/hadoop/hbase/master/balancer/MetricsStochasticBalancerSource.updateBalancerStatus:(Z)V
      10: return

  public void updateMetricsSize(int);
    Code:
       0: aload_0
       1: getfield      #2                  // Field stochasticSource:Lorg/apache/hadoop/hbase/master/balancer/MetricsStochasticBalancerSource;
       4: iload_1
       5: invokeinterface #9,  2            // InterfaceMethod org/apache/hadoop/hbase/master/balancer/MetricsStochasticBalancerSource.updateMetricsSize:(I)V
      10: return

  public void updateStochasticCost(java.lang.String, java.lang.String, java.lang.String, java.lang.Double);
    Code:
       0: aload_0
       1: getfield      #2                  // Field stochasticSource:Lorg/apache/hadoop/hbase/master/balancer/MetricsStochasticBalancerSource;
       4: aload_1
       5: aload_2
       6: aload_3
       7: aload         4
       9: invokeinterface #10,  5           // InterfaceMethod org/apache/hadoop/hbase/master/balancer/MetricsStochasticBalancerSource.updateStochasticCost:(Ljava/lang/String;Ljava/lang/String;Ljava/lang/String;Ljava/lang/Double;)V
      14: return
}
