Compiled from "MetricsReplicationGlobalSourceSource.java"
public class org.apache.hadoop.hbase.replication.regionserver.MetricsReplicationGlobalSourceSource implements org.apache.hadoop.hbase.replication.regionserver.MetricsReplicationSourceSource {
  public org.apache.hadoop.hbase.replication.regionserver.MetricsReplicationGlobalSourceSource(org.apache.hadoop.hbase.replication.regionserver.MetricsReplicationSourceImpl);
    Code:
       0: aload_0
       1: invokespecial #1                  // Method java/lang/Object."<init>":()V
       4: aload_0
       5: aload_1
       6: putfield      #2                  // Field rms:Lorg/apache/hadoop/hbase/replication/regionserver/MetricsReplicationSourceImpl;
       9: aload_0
      10: aload_1
      11: invokevirtual #3                  // Method org/apache/hadoop/hbase/replication/regionserver/MetricsReplicationSourceImpl.getMetricsRegistry:()Lorg/apache/hadoop/metrics2/lib/DynamicMetricsRegistry;
      14: ldc           #5                  // String source.ageOfLastShippedOp
      16: invokevirtual #6                  // Method org/apache/hadoop/metrics2/lib/DynamicMetricsRegistry.getHistogram:(Ljava/lang/String;)Lorg/apache/hadoop/metrics2/lib/MutableHistogram;
      19: putfield      #7                  // Field ageOfLastShippedOpHist:Lorg/apache/hadoop/metrics2/lib/MutableHistogram;
      22: aload_0
      23: aload_1
      24: invokevirtual #3                  // Method org/apache/hadoop/hbase/replication/regionserver/MetricsReplicationSourceImpl.getMetricsRegistry:()Lorg/apache/hadoop/metrics2/lib/DynamicMetricsRegistry;
      27: ldc           #8                  // String source.sizeOfLogQueue
      29: lconst_0
      30: invokevirtual #9                  // Method org/apache/hadoop/metrics2/lib/DynamicMetricsRegistry.getGauge:(Ljava/lang/String;J)Lorg/apache/hadoop/metrics2/lib/MutableGaugeLong;
      33: putfield      #10                 // Field sizeOfLogQueueGauge:Lorg/apache/hadoop/metrics2/lib/MutableGaugeLong;
      36: aload_0
      37: aload_1
      38: invokevirtual #3                  // Method org/apache/hadoop/hbase/replication/regionserver/MetricsReplicationSourceImpl.getMetricsRegistry:()Lorg/apache/hadoop/metrics2/lib/DynamicMetricsRegistry;
      41: ldc           #11                 // String source.shippedBatches
      43: lconst_0
      44: invokevirtual #12                 // Method org/apache/hadoop/metrics2/lib/DynamicMetricsRegistry.getCounter:(Ljava/lang/String;J)Lorg/apache/hadoop/metrics2/lib/MutableFastCounter;
      47: putfield      #13                 // Field shippedBatchesCounter:Lorg/apache/hadoop/metrics2/lib/MutableFastCounter;
      50: aload_0
      51: aload_1
      52: invokevirtual #3                  // Method org/apache/hadoop/hbase/replication/regionserver/MetricsReplicationSourceImpl.getMetricsRegistry:()Lorg/apache/hadoop/metrics2/lib/DynamicMetricsRegistry;
      55: ldc           #14                 // String source.shippedOps
      57: lconst_0
      58: invokevirtual #12                 // Method org/apache/hadoop/metrics2/lib/DynamicMetricsRegistry.getCounter:(Ljava/lang/String;J)Lorg/apache/hadoop/metrics2/lib/MutableFastCounter;
      61: putfield      #15                 // Field shippedOpsCounter:Lorg/apache/hadoop/metrics2/lib/MutableFastCounter;
      64: aload_0
      65: aload_1
      66: invokevirtual #3                  // Method org/apache/hadoop/hbase/replication/regionserver/MetricsReplicationSourceImpl.getMetricsRegistry:()Lorg/apache/hadoop/metrics2/lib/DynamicMetricsRegistry;
      69: ldc           #16                 // String source.shippedBytes
      71: lconst_0
      72: invokevirtual #12                 // Method org/apache/hadoop/metrics2/lib/DynamicMetricsRegistry.getCounter:(Ljava/lang/String;J)Lorg/apache/hadoop/metrics2/lib/MutableFastCounter;
      75: putfield      #17                 // Field shippedBytesCounter:Lorg/apache/hadoop/metrics2/lib/MutableFastCounter;
      78: aload_0
      79: aload_1
      80: invokevirtual #3                  // Method org/apache/hadoop/hbase/replication/regionserver/MetricsReplicationSourceImpl.getMetricsRegistry:()Lorg/apache/hadoop/metrics2/lib/DynamicMetricsRegistry;
      83: ldc           #18                 // String source.logReadInBytes
      85: lconst_0
      86: invokevirtual #12                 // Method org/apache/hadoop/metrics2/lib/DynamicMetricsRegistry.getCounter:(Ljava/lang/String;J)Lorg/apache/hadoop/metrics2/lib/MutableFastCounter;
      89: putfield      #19                 // Field logReadInBytesCounter:Lorg/apache/hadoop/metrics2/lib/MutableFastCounter;
      92: aload_0
      93: aload_1
      94: invokevirtual #3                  // Method org/apache/hadoop/hbase/replication/regionserver/MetricsReplicationSourceImpl.getMetricsRegistry:()Lorg/apache/hadoop/metrics2/lib/DynamicMetricsRegistry;
      97: ldc           #20                 // String source.logEditsRead
      99: lconst_0
     100: invokevirtual #12                 // Method org/apache/hadoop/metrics2/lib/DynamicMetricsRegistry.getCounter:(Ljava/lang/String;J)Lorg/apache/hadoop/metrics2/lib/MutableFastCounter;
     103: putfield      #21                 // Field logReadInEditsCounter:Lorg/apache/hadoop/metrics2/lib/MutableFastCounter;
     106: aload_0
     107: aload_1
     108: invokevirtual #3                  // Method org/apache/hadoop/hbase/replication/regionserver/MetricsReplicationSourceImpl.getMetricsRegistry:()Lorg/apache/hadoop/metrics2/lib/DynamicMetricsRegistry;
     111: ldc           #22                 // String source.logEditsFiltered
     113: lconst_0
     114: invokevirtual #12                 // Method org/apache/hadoop/metrics2/lib/DynamicMetricsRegistry.getCounter:(Ljava/lang/String;J)Lorg/apache/hadoop/metrics2/lib/MutableFastCounter;
     117: putfield      #23                 // Field walEditsFilteredCounter:Lorg/apache/hadoop/metrics2/lib/MutableFastCounter;
     120: aload_0
     121: aload_1
     122: invokevirtual #3                  // Method org/apache/hadoop/hbase/replication/regionserver/MetricsReplicationSourceImpl.getMetricsRegistry:()Lorg/apache/hadoop/metrics2/lib/DynamicMetricsRegistry;
     125: ldc           #24                 // String source.shippedHFiles
     127: lconst_0
     128: invokevirtual #12                 // Method org/apache/hadoop/metrics2/lib/DynamicMetricsRegistry.getCounter:(Ljava/lang/String;J)Lorg/apache/hadoop/metrics2/lib/MutableFastCounter;
     131: putfield      #25                 // Field shippedHFilesCounter:Lorg/apache/hadoop/metrics2/lib/MutableFastCounter;
     134: aload_0
     135: aload_1
     136: invokevirtual #3                  // Method org/apache/hadoop/hbase/replication/regionserver/MetricsReplicationSourceImpl.getMetricsRegistry:()Lorg/apache/hadoop/metrics2/lib/DynamicMetricsRegistry;
     139: ldc           #26                 // String source.sizeOfHFileRefsQueue
     141: lconst_0
     142: invokevirtual #9                  // Method org/apache/hadoop/metrics2/lib/DynamicMetricsRegistry.getGauge:(Ljava/lang/String;J)Lorg/apache/hadoop/metrics2/lib/MutableGaugeLong;
     145: putfield      #27                 // Field sizeOfHFileRefsQueueGauge:Lorg/apache/hadoop/metrics2/lib/MutableGaugeLong;
     148: aload_0
     149: aload_1
     150: invokevirtual #3                  // Method org/apache/hadoop/hbase/replication/regionserver/MetricsReplicationSourceImpl.getMetricsRegistry:()Lorg/apache/hadoop/metrics2/lib/DynamicMetricsRegistry;
     153: ldc           #28                 // String source.closedLogsWithUnknownFileLength
     155: lconst_0
     156: invokevirtual #12                 // Method org/apache/hadoop/metrics2/lib/DynamicMetricsRegistry.getCounter:(Ljava/lang/String;J)Lorg/apache/hadoop/metrics2/lib/MutableFastCounter;
     159: putfield      #29                 // Field unknownFileLengthForClosedWAL:Lorg/apache/hadoop/metrics2/lib/MutableFastCounter;
     162: aload_0
     163: aload_1
     164: invokevirtual #3                  // Method org/apache/hadoop/hbase/replication/regionserver/MetricsReplicationSourceImpl.getMetricsRegistry:()Lorg/apache/hadoop/metrics2/lib/DynamicMetricsRegistry;
     167: ldc           #30                 // String source.uncleanlyClosedLogs
     169: lconst_0
     170: invokevirtual #12                 // Method org/apache/hadoop/metrics2/lib/DynamicMetricsRegistry.getCounter:(Ljava/lang/String;J)Lorg/apache/hadoop/metrics2/lib/MutableFastCounter;
     173: putfield      #31                 // Field uncleanlyClosedWAL:Lorg/apache/hadoop/metrics2/lib/MutableFastCounter;
     176: aload_0
     177: aload_1
     178: invokevirtual #3                  // Method org/apache/hadoop/hbase/replication/regionserver/MetricsReplicationSourceImpl.getMetricsRegistry:()Lorg/apache/hadoop/metrics2/lib/DynamicMetricsRegistry;
     181: ldc           #32                 // String source.ignoredUncleanlyClosedLogContentsInBytes
     183: lconst_0
     184: invokevirtual #12                 // Method org/apache/hadoop/metrics2/lib/DynamicMetricsRegistry.getCounter:(Ljava/lang/String;J)Lorg/apache/hadoop/metrics2/lib/MutableFastCounter;
     187: putfield      #33                 // Field uncleanlyClosedSkippedBytes:Lorg/apache/hadoop/metrics2/lib/MutableFastCounter;
     190: aload_0
     191: aload_1
     192: invokevirtual #3                  // Method org/apache/hadoop/hbase/replication/regionserver/MetricsReplicationSourceImpl.getMetricsRegistry:()Lorg/apache/hadoop/metrics2/lib/DynamicMetricsRegistry;
     195: ldc           #34                 // String source.restartedLogReading
     197: lconst_0
     198: invokevirtual #12                 // Method org/apache/hadoop/metrics2/lib/DynamicMetricsRegistry.getCounter:(Ljava/lang/String;J)Lorg/apache/hadoop/metrics2/lib/MutableFastCounter;
     201: putfield      #35                 // Field restartWALReading:Lorg/apache/hadoop/metrics2/lib/MutableFastCounter;
     204: aload_0
     205: aload_1
     206: invokevirtual #3                  // Method org/apache/hadoop/hbase/replication/regionserver/MetricsReplicationSourceImpl.getMetricsRegistry:()Lorg/apache/hadoop/metrics2/lib/DynamicMetricsRegistry;
     209: ldc           #36                 // String source.repeatedLogFileBytes
     211: lconst_0
     212: invokevirtual #12                 // Method org/apache/hadoop/metrics2/lib/DynamicMetricsRegistry.getCounter:(Ljava/lang/String;J)Lorg/apache/hadoop/metrics2/lib/MutableFastCounter;
     215: putfield      #37                 // Field repeatedFileBytes:Lorg/apache/hadoop/metrics2/lib/MutableFastCounter;
     218: aload_0
     219: aload_1
     220: invokevirtual #3                  // Method org/apache/hadoop/hbase/replication/regionserver/MetricsReplicationSourceImpl.getMetricsRegistry:()Lorg/apache/hadoop/metrics2/lib/DynamicMetricsRegistry;
     223: ldc           #38                 // String source.completedLogs
     225: lconst_0
     226: invokevirtual #12                 // Method org/apache/hadoop/metrics2/lib/DynamicMetricsRegistry.getCounter:(Ljava/lang/String;J)Lorg/apache/hadoop/metrics2/lib/MutableFastCounter;
     229: putfield      #39                 // Field completedWAL:Lorg/apache/hadoop/metrics2/lib/MutableFastCounter;
     232: aload_0
     233: aload_1
     234: invokevirtual #3                  // Method org/apache/hadoop/hbase/replication/regionserver/MetricsReplicationSourceImpl.getMetricsRegistry:()Lorg/apache/hadoop/metrics2/lib/DynamicMetricsRegistry;
     237: ldc           #40                 // String source.completedRecoverQueues
     239: lconst_0
     240: invokevirtual #12                 // Method org/apache/hadoop/metrics2/lib/DynamicMetricsRegistry.getCounter:(Ljava/lang/String;J)Lorg/apache/hadoop/metrics2/lib/MutableFastCounter;
     243: putfield      #41                 // Field completedRecoveryQueue:Lorg/apache/hadoop/metrics2/lib/MutableFastCounter;
     246: aload_0
     247: aload_1
     248: invokevirtual #3                  // Method org/apache/hadoop/hbase/replication/regionserver/MetricsReplicationSourceImpl.getMetricsRegistry:()Lorg/apache/hadoop/metrics2/lib/DynamicMetricsRegistry;
     251: ldc           #42                 // String source.failedRecoverQueues
     253: lconst_0
     254: invokevirtual #12                 // Method org/apache/hadoop/metrics2/lib/DynamicMetricsRegistry.getCounter:(Ljava/lang/String;J)Lorg/apache/hadoop/metrics2/lib/MutableFastCounter;
     257: putfield      #43                 // Field failedRecoveryQueue:Lorg/apache/hadoop/metrics2/lib/MutableFastCounter;
     260: return

  public void setLastShippedAge(long);
    Code:
       0: aload_0
       1: getfield      #7                  // Field ageOfLastShippedOpHist:Lorg/apache/hadoop/metrics2/lib/MutableHistogram;
       4: lload_1
       5: invokevirtual #44                 // Method org/apache/hadoop/metrics2/lib/MutableHistogram.add:(J)V
       8: return

  public void incrSizeOfLogQueue(int);
    Code:
       0: aload_0
       1: getfield      #10                 // Field sizeOfLogQueueGauge:Lorg/apache/hadoop/metrics2/lib/MutableGaugeLong;
       4: iload_1
       5: i2l
       6: invokevirtual #45                 // Method org/apache/hadoop/metrics2/lib/MutableGaugeLong.incr:(J)V
       9: return

  public void decrSizeOfLogQueue(int);
    Code:
       0: aload_0
       1: getfield      #10                 // Field sizeOfLogQueueGauge:Lorg/apache/hadoop/metrics2/lib/MutableGaugeLong;
       4: iload_1
       5: i2l
       6: invokevirtual #46                 // Method org/apache/hadoop/metrics2/lib/MutableGaugeLong.decr:(J)V
       9: return

  public void incrLogReadInEdits(long);
    Code:
       0: aload_0
       1: getfield      #21                 // Field logReadInEditsCounter:Lorg/apache/hadoop/metrics2/lib/MutableFastCounter;
       4: lload_1
       5: invokevirtual #47                 // Method org/apache/hadoop/metrics2/lib/MutableFastCounter.incr:(J)V
       8: return

  public void incrLogEditsFiltered(long);
    Code:
       0: aload_0
       1: getfield      #23                 // Field walEditsFilteredCounter:Lorg/apache/hadoop/metrics2/lib/MutableFastCounter;
       4: lload_1
       5: invokevirtual #47                 // Method org/apache/hadoop/metrics2/lib/MutableFastCounter.incr:(J)V
       8: return

  public void incrBatchesShipped(int);
    Code:
       0: aload_0
       1: getfield      #13                 // Field shippedBatchesCounter:Lorg/apache/hadoop/metrics2/lib/MutableFastCounter;
       4: iload_1
       5: i2l
       6: invokevirtual #47                 // Method org/apache/hadoop/metrics2/lib/MutableFastCounter.incr:(J)V
       9: return

  public void incrOpsShipped(long);
    Code:
       0: aload_0
       1: getfield      #15                 // Field shippedOpsCounter:Lorg/apache/hadoop/metrics2/lib/MutableFastCounter;
       4: lload_1
       5: invokevirtual #47                 // Method org/apache/hadoop/metrics2/lib/MutableFastCounter.incr:(J)V
       8: return

  public void incrShippedBytes(long);
    Code:
       0: aload_0
       1: getfield      #17                 // Field shippedBytesCounter:Lorg/apache/hadoop/metrics2/lib/MutableFastCounter;
       4: lload_1
       5: invokevirtual #47                 // Method org/apache/hadoop/metrics2/lib/MutableFastCounter.incr:(J)V
       8: return

  public void incrLogReadInBytes(long);
    Code:
       0: aload_0
       1: getfield      #19                 // Field logReadInBytesCounter:Lorg/apache/hadoop/metrics2/lib/MutableFastCounter;
       4: lload_1
       5: invokevirtual #47                 // Method org/apache/hadoop/metrics2/lib/MutableFastCounter.incr:(J)V
       8: return

  public void clear();
    Code:
       0: return

  public long getLastShippedAge();
    Code:
       0: aload_0
       1: getfield      #7                  // Field ageOfLastShippedOpHist:Lorg/apache/hadoop/metrics2/lib/MutableHistogram;
       4: invokevirtual #48                 // Method org/apache/hadoop/metrics2/lib/MutableHistogram.getMax:()J
       7: lreturn

  public void incrHFilesShipped(long);
    Code:
       0: aload_0
       1: getfield      #25                 // Field shippedHFilesCounter:Lorg/apache/hadoop/metrics2/lib/MutableFastCounter;
       4: lload_1
       5: invokevirtual #47                 // Method org/apache/hadoop/metrics2/lib/MutableFastCounter.incr:(J)V
       8: return

  public void incrSizeOfHFileRefsQueue(long);
    Code:
       0: aload_0
       1: getfield      #27                 // Field sizeOfHFileRefsQueueGauge:Lorg/apache/hadoop/metrics2/lib/MutableGaugeLong;
       4: lload_1
       5: invokevirtual #45                 // Method org/apache/hadoop/metrics2/lib/MutableGaugeLong.incr:(J)V
       8: return

  public void decrSizeOfHFileRefsQueue(long);
    Code:
       0: aload_0
       1: getfield      #27                 // Field sizeOfHFileRefsQueueGauge:Lorg/apache/hadoop/metrics2/lib/MutableGaugeLong;
       4: lload_1
       5: invokevirtual #46                 // Method org/apache/hadoop/metrics2/lib/MutableGaugeLong.decr:(J)V
       8: return

  public int getSizeOfLogQueue();
    Code:
       0: aload_0
       1: getfield      #10                 // Field sizeOfLogQueueGauge:Lorg/apache/hadoop/metrics2/lib/MutableGaugeLong;
       4: invokevirtual #49                 // Method org/apache/hadoop/metrics2/lib/MutableGaugeLong.value:()J
       7: l2i
       8: ireturn

  public void incrUnknownFileLengthForClosedWAL();
    Code:
       0: aload_0
       1: getfield      #29                 // Field unknownFileLengthForClosedWAL:Lorg/apache/hadoop/metrics2/lib/MutableFastCounter;
       4: lconst_1
       5: invokevirtual #47                 // Method org/apache/hadoop/metrics2/lib/MutableFastCounter.incr:(J)V
       8: return

  public void incrUncleanlyClosedWALs();
    Code:
       0: aload_0
       1: getfield      #31                 // Field uncleanlyClosedWAL:Lorg/apache/hadoop/metrics2/lib/MutableFastCounter;
       4: lconst_1
       5: invokevirtual #47                 // Method org/apache/hadoop/metrics2/lib/MutableFastCounter.incr:(J)V
       8: return

  public void incrBytesSkippedInUncleanlyClosedWALs(long);
    Code:
       0: aload_0
       1: getfield      #33                 // Field uncleanlyClosedSkippedBytes:Lorg/apache/hadoop/metrics2/lib/MutableFastCounter;
       4: lload_1
       5: invokevirtual #47                 // Method org/apache/hadoop/metrics2/lib/MutableFastCounter.incr:(J)V
       8: return

  public void incrRestartedWALReading();
    Code:
       0: aload_0
       1: getfield      #35                 // Field restartWALReading:Lorg/apache/hadoop/metrics2/lib/MutableFastCounter;
       4: lconst_1
       5: invokevirtual #47                 // Method org/apache/hadoop/metrics2/lib/MutableFastCounter.incr:(J)V
       8: return

  public void incrRepeatedFileBytes(long);
    Code:
       0: aload_0
       1: getfield      #37                 // Field repeatedFileBytes:Lorg/apache/hadoop/metrics2/lib/MutableFastCounter;
       4: lload_1
       5: invokevirtual #47                 // Method org/apache/hadoop/metrics2/lib/MutableFastCounter.incr:(J)V
       8: return

  public void incrCompletedWAL();
    Code:
       0: aload_0
       1: getfield      #39                 // Field completedWAL:Lorg/apache/hadoop/metrics2/lib/MutableFastCounter;
       4: lconst_1
       5: invokevirtual #47                 // Method org/apache/hadoop/metrics2/lib/MutableFastCounter.incr:(J)V
       8: return

  public void incrCompletedRecoveryQueue();
    Code:
       0: aload_0
       1: getfield      #41                 // Field completedRecoveryQueue:Lorg/apache/hadoop/metrics2/lib/MutableFastCounter;
       4: lconst_1
       5: invokevirtual #47                 // Method org/apache/hadoop/metrics2/lib/MutableFastCounter.incr:(J)V
       8: return

  public void incrFailedRecoveryQueue();
    Code:
       0: aload_0
       1: getfield      #43                 // Field failedRecoveryQueue:Lorg/apache/hadoop/metrics2/lib/MutableFastCounter;
       4: lconst_1
       5: invokevirtual #47                 // Method org/apache/hadoop/metrics2/lib/MutableFastCounter.incr:(J)V
       8: return

  public void init();
    Code:
       0: aload_0
       1: getfield      #2                  // Field rms:Lorg/apache/hadoop/hbase/replication/regionserver/MetricsReplicationSourceImpl;
       4: invokevirtual #50                 // Method org/apache/hadoop/hbase/replication/regionserver/MetricsReplicationSourceImpl.init:()V
       7: return

  public void setGauge(java.lang.String, long);
    Code:
       0: aload_0
       1: getfield      #2                  // Field rms:Lorg/apache/hadoop/hbase/replication/regionserver/MetricsReplicationSourceImpl;
       4: new           #51                 // class java/lang/StringBuilder
       7: dup
       8: invokespecial #52                 // Method java/lang/StringBuilder."<init>":()V
      11: ldc           #54                 // String source.
      13: invokevirtual #55                 // Method java/lang/StringBuilder.append:(Ljava/lang/String;)Ljava/lang/StringBuilder;
      16: aload_1
      17: invokevirtual #55                 // Method java/lang/StringBuilder.append:(Ljava/lang/String;)Ljava/lang/StringBuilder;
      20: invokevirtual #56                 // Method java/lang/StringBuilder.toString:()Ljava/lang/String;
      23: lload_2
      24: invokevirtual #57                 // Method org/apache/hadoop/hbase/replication/regionserver/MetricsReplicationSourceImpl.setGauge:(Ljava/lang/String;J)V
      27: return

  public void incGauge(java.lang.String, long);
    Code:
       0: aload_0
       1: getfield      #2                  // Field rms:Lorg/apache/hadoop/hbase/replication/regionserver/MetricsReplicationSourceImpl;
       4: new           #51                 // class java/lang/StringBuilder
       7: dup
       8: invokespecial #52                 // Method java/lang/StringBuilder."<init>":()V
      11: ldc           #54                 // String source.
      13: invokevirtual #55                 // Method java/lang/StringBuilder.append:(Ljava/lang/String;)Ljava/lang/StringBuilder;
      16: aload_1
      17: invokevirtual #55                 // Method java/lang/StringBuilder.append:(Ljava/lang/String;)Ljava/lang/StringBuilder;
      20: invokevirtual #56                 // Method java/lang/StringBuilder.toString:()Ljava/lang/String;
      23: lload_2
      24: invokevirtual #58                 // Method org/apache/hadoop/hbase/replication/regionserver/MetricsReplicationSourceImpl.incGauge:(Ljava/lang/String;J)V
      27: return

  public void decGauge(java.lang.String, long);
    Code:
       0: aload_0
       1: getfield      #2                  // Field rms:Lorg/apache/hadoop/hbase/replication/regionserver/MetricsReplicationSourceImpl;
       4: new           #51                 // class java/lang/StringBuilder
       7: dup
       8: invokespecial #52                 // Method java/lang/StringBuilder."<init>":()V
      11: ldc           #54                 // String source.
      13: invokevirtual #55                 // Method java/lang/StringBuilder.append:(Ljava/lang/String;)Ljava/lang/StringBuilder;
      16: aload_1
      17: invokevirtual #55                 // Method java/lang/StringBuilder.append:(Ljava/lang/String;)Ljava/lang/StringBuilder;
      20: invokevirtual #56                 // Method java/lang/StringBuilder.toString:()Ljava/lang/String;
      23: lload_2
      24: invokevirtual #59                 // Method org/apache/hadoop/hbase/replication/regionserver/MetricsReplicationSourceImpl.decGauge:(Ljava/lang/String;J)V
      27: return

  public void removeMetric(java.lang.String);
    Code:
       0: aload_0
       1: getfield      #2                  // Field rms:Lorg/apache/hadoop/hbase/replication/regionserver/MetricsReplicationSourceImpl;
       4: new           #51                 // class java/lang/StringBuilder
       7: dup
       8: invokespecial #52                 // Method java/lang/StringBuilder."<init>":()V
      11: ldc           #54                 // String source.
      13: invokevirtual #55                 // Method java/lang/StringBuilder.append:(Ljava/lang/String;)Ljava/lang/StringBuilder;
      16: aload_1
      17: invokevirtual #55                 // Method java/lang/StringBuilder.append:(Ljava/lang/String;)Ljava/lang/StringBuilder;
      20: invokevirtual #56                 // Method java/lang/StringBuilder.toString:()Ljava/lang/String;
      23: invokevirtual #60                 // Method org/apache/hadoop/hbase/replication/regionserver/MetricsReplicationSourceImpl.removeMetric:(Ljava/lang/String;)V
      26: return

  public void incCounters(java.lang.String, long);
    Code:
       0: aload_0
       1: getfield      #2                  // Field rms:Lorg/apache/hadoop/hbase/replication/regionserver/MetricsReplicationSourceImpl;
       4: new           #51                 // class java/lang/StringBuilder
       7: dup
       8: invokespecial #52                 // Method java/lang/StringBuilder."<init>":()V
      11: ldc           #54                 // String source.
      13: invokevirtual #55                 // Method java/lang/StringBuilder.append:(Ljava/lang/String;)Ljava/lang/StringBuilder;
      16: aload_1
      17: invokevirtual #55                 // Method java/lang/StringBuilder.append:(Ljava/lang/String;)Ljava/lang/StringBuilder;
      20: invokevirtual #56                 // Method java/lang/StringBuilder.toString:()Ljava/lang/String;
      23: lload_2
      24: invokevirtual #61                 // Method org/apache/hadoop/hbase/replication/regionserver/MetricsReplicationSourceImpl.incCounters:(Ljava/lang/String;J)V
      27: return

  public void updateHistogram(java.lang.String, long);
    Code:
       0: aload_0
       1: getfield      #2                  // Field rms:Lorg/apache/hadoop/hbase/replication/regionserver/MetricsReplicationSourceImpl;
       4: new           #51                 // class java/lang/StringBuilder
       7: dup
       8: invokespecial #52                 // Method java/lang/StringBuilder."<init>":()V
      11: ldc           #54                 // String source.
      13: invokevirtual #55                 // Method java/lang/StringBuilder.append:(Ljava/lang/String;)Ljava/lang/StringBuilder;
      16: aload_1
      17: invokevirtual #55                 // Method java/lang/StringBuilder.append:(Ljava/lang/String;)Ljava/lang/StringBuilder;
      20: invokevirtual #56                 // Method java/lang/StringBuilder.toString:()Ljava/lang/String;
      23: lload_2
      24: invokevirtual #62                 // Method org/apache/hadoop/hbase/replication/regionserver/MetricsReplicationSourceImpl.updateHistogram:(Ljava/lang/String;J)V
      27: return

  public java.lang.String getMetricsContext();
    Code:
       0: aload_0
       1: getfield      #2                  // Field rms:Lorg/apache/hadoop/hbase/replication/regionserver/MetricsReplicationSourceImpl;
       4: invokevirtual #63                 // Method org/apache/hadoop/hbase/replication/regionserver/MetricsReplicationSourceImpl.getMetricsContext:()Ljava/lang/String;
       7: areturn

  public java.lang.String getMetricsDescription();
    Code:
       0: aload_0
       1: getfield      #2                  // Field rms:Lorg/apache/hadoop/hbase/replication/regionserver/MetricsReplicationSourceImpl;
       4: invokevirtual #64                 // Method org/apache/hadoop/hbase/replication/regionserver/MetricsReplicationSourceImpl.getMetricsDescription:()Ljava/lang/String;
       7: areturn

  public java.lang.String getMetricsJmxContext();
    Code:
       0: aload_0
       1: getfield      #2                  // Field rms:Lorg/apache/hadoop/hbase/replication/regionserver/MetricsReplicationSourceImpl;
       4: invokevirtual #65                 // Method org/apache/hadoop/hbase/replication/regionserver/MetricsReplicationSourceImpl.getMetricsJmxContext:()Ljava/lang/String;
       7: areturn

  public java.lang.String getMetricsName();
    Code:
       0: aload_0
       1: getfield      #2                  // Field rms:Lorg/apache/hadoop/hbase/replication/regionserver/MetricsReplicationSourceImpl;
       4: invokevirtual #66                 // Method org/apache/hadoop/hbase/replication/regionserver/MetricsReplicationSourceImpl.getMetricsName:()Ljava/lang/String;
       7: areturn

  public long getWALEditsRead();
    Code:
       0: aload_0
       1: getfield      #21                 // Field logReadInEditsCounter:Lorg/apache/hadoop/metrics2/lib/MutableFastCounter;
       4: invokevirtual #67                 // Method org/apache/hadoop/metrics2/lib/MutableFastCounter.value:()J
       7: lreturn

  public long getShippedOps();
    Code:
       0: aload_0
       1: getfield      #15                 // Field shippedOpsCounter:Lorg/apache/hadoop/metrics2/lib/MutableFastCounter;
       4: invokevirtual #67                 // Method org/apache/hadoop/metrics2/lib/MutableFastCounter.value:()J
       7: lreturn

  public long getEditsFiltered();
    Code:
       0: aload_0
       1: getfield      #23                 // Field walEditsFilteredCounter:Lorg/apache/hadoop/metrics2/lib/MutableFastCounter;
       4: invokevirtual #67                 // Method org/apache/hadoop/metrics2/lib/MutableFastCounter.value:()J
       7: lreturn
}
