Compiled from "MetricsRegionServerSourceFactoryImpl.java"
public class org.apache.hadoop.hbase.regionserver.MetricsRegionServerSourceFactoryImpl implements org.apache.hadoop.hbase.regionserver.MetricsRegionServerSourceFactory {
  public org.apache.hadoop.hbase.regionserver.MetricsRegionServerSourceFactoryImpl();
    Code:
       0: aload_0
       1: invokespecial #1                  // Method java/lang/Object."<init>":()V
       4: return

  public synchronized org.apache.hadoop.hbase.regionserver.MetricsTableAggregateSourceImpl getTableAggregate();
    Code:
       0: getstatic     #2                  // Field org/apache/hadoop/hbase/regionserver/MetricsRegionServerSourceFactoryImpl$FactoryStorage.INSTANCE:Lorg/apache/hadoop/hbase/regionserver/MetricsRegionServerSourceFactoryImpl$FactoryStorage;
       3: invokestatic  #3                  // Method org/apache/hadoop/hbase/regionserver/MetricsRegionServerSourceFactoryImpl$FactoryStorage.access$000:(Lorg/apache/hadoop/hbase/regionserver/MetricsRegionServerSourceFactoryImpl$FactoryStorage;)Ljava/lang/Object;
       6: dup
       7: astore_1
       8: monitorenter
       9: getstatic     #2                  // Field org/apache/hadoop/hbase/regionserver/MetricsRegionServerSourceFactoryImpl$FactoryStorage.INSTANCE:Lorg/apache/hadoop/hbase/regionserver/MetricsRegionServerSourceFactoryImpl$FactoryStorage;
      12: invokestatic  #8                  // Method org/apache/hadoop/hbase/regionserver/MetricsRegionServerSourceFactoryImpl$FactoryStorage.access$200:(Lorg/apache/hadoop/hbase/regionserver/MetricsRegionServerSourceFactoryImpl$FactoryStorage;)Lorg/apache/hadoop/hbase/regionserver/MetricsTableAggregateSourceImpl;
      15: ifnonnull     32
      18: getstatic     #2                  // Field org/apache/hadoop/hbase/regionserver/MetricsRegionServerSourceFactoryImpl$FactoryStorage.INSTANCE:Lorg/apache/hadoop/hbase/regionserver/MetricsRegionServerSourceFactoryImpl$FactoryStorage;
      21: new           #9                  // class org/apache/hadoop/hbase/regionserver/MetricsTableAggregateSourceImpl
      24: dup
      25: invokespecial #10                 // Method org/apache/hadoop/hbase/regionserver/MetricsTableAggregateSourceImpl."<init>":()V
      28: invokestatic  #11                 // Method org/apache/hadoop/hbase/regionserver/MetricsRegionServerSourceFactoryImpl$FactoryStorage.access$202:(Lorg/apache/hadoop/hbase/regionserver/MetricsRegionServerSourceFactoryImpl$FactoryStorage;Lorg/apache/hadoop/hbase/regionserver/MetricsTableAggregateSourceImpl;)Lorg/apache/hadoop/hbase/regionserver/MetricsTableAggregateSourceImpl;
      31: pop
      32: getstatic     #2                  // Field org/apache/hadoop/hbase/regionserver/MetricsRegionServerSourceFactoryImpl$FactoryStorage.INSTANCE:Lorg/apache/hadoop/hbase/regionserver/MetricsRegionServerSourceFactoryImpl$FactoryStorage;
      35: invokestatic  #8                  // Method org/apache/hadoop/hbase/regionserver/MetricsRegionServerSourceFactoryImpl$FactoryStorage.access$200:(Lorg/apache/hadoop/hbase/regionserver/MetricsRegionServerSourceFactoryImpl$FactoryStorage;)Lorg/apache/hadoop/hbase/regionserver/MetricsTableAggregateSourceImpl;
      38: aload_1
      39: monitorexit
      40: areturn
      41: astore_2
      42: aload_1
      43: monitorexit
      44: aload_2
      45: athrow
    Exception table:
       from    to  target type
           9    40    41   any
          41    44    41   any

  public synchronized org.apache.hadoop.hbase.regionserver.MetricsHeapMemoryManagerSource getHeapMemoryManager();
    Code:
       0: getstatic     #2                  // Field org/apache/hadoop/hbase/regionserver/MetricsRegionServerSourceFactoryImpl$FactoryStorage.INSTANCE:Lorg/apache/hadoop/hbase/regionserver/MetricsRegionServerSourceFactoryImpl$FactoryStorage;
       3: invokestatic  #3                  // Method org/apache/hadoop/hbase/regionserver/MetricsRegionServerSourceFactoryImpl$FactoryStorage.access$000:(Lorg/apache/hadoop/hbase/regionserver/MetricsRegionServerSourceFactoryImpl$FactoryStorage;)Ljava/lang/Object;
       6: dup
       7: astore_1
       8: monitorenter
       9: getstatic     #2                  // Field org/apache/hadoop/hbase/regionserver/MetricsRegionServerSourceFactoryImpl$FactoryStorage.INSTANCE:Lorg/apache/hadoop/hbase/regionserver/MetricsRegionServerSourceFactoryImpl$FactoryStorage;
      12: invokestatic  #12                 // Method org/apache/hadoop/hbase/regionserver/MetricsRegionServerSourceFactoryImpl$FactoryStorage.access$300:(Lorg/apache/hadoop/hbase/regionserver/MetricsRegionServerSourceFactoryImpl$FactoryStorage;)Lorg/apache/hadoop/hbase/regionserver/MetricsHeapMemoryManagerSourceImpl;
      15: ifnonnull     32
      18: getstatic     #2                  // Field org/apache/hadoop/hbase/regionserver/MetricsRegionServerSourceFactoryImpl$FactoryStorage.INSTANCE:Lorg/apache/hadoop/hbase/regionserver/MetricsRegionServerSourceFactoryImpl$FactoryStorage;
      21: new           #13                 // class org/apache/hadoop/hbase/regionserver/MetricsHeapMemoryManagerSourceImpl
      24: dup
      25: invokespecial #14                 // Method org/apache/hadoop/hbase/regionserver/MetricsHeapMemoryManagerSourceImpl."<init>":()V
      28: invokestatic  #15                 // Method org/apache/hadoop/hbase/regionserver/MetricsRegionServerSourceFactoryImpl$FactoryStorage.access$302:(Lorg/apache/hadoop/hbase/regionserver/MetricsRegionServerSourceFactoryImpl$FactoryStorage;Lorg/apache/hadoop/hbase/regionserver/MetricsHeapMemoryManagerSourceImpl;)Lorg/apache/hadoop/hbase/regionserver/MetricsHeapMemoryManagerSourceImpl;
      31: pop
      32: getstatic     #2                  // Field org/apache/hadoop/hbase/regionserver/MetricsRegionServerSourceFactoryImpl$FactoryStorage.INSTANCE:Lorg/apache/hadoop/hbase/regionserver/MetricsRegionServerSourceFactoryImpl$FactoryStorage;
      35: invokestatic  #12                 // Method org/apache/hadoop/hbase/regionserver/MetricsRegionServerSourceFactoryImpl$FactoryStorage.access$300:(Lorg/apache/hadoop/hbase/regionserver/MetricsRegionServerSourceFactoryImpl$FactoryStorage;)Lorg/apache/hadoop/hbase/regionserver/MetricsHeapMemoryManagerSourceImpl;
      38: aload_1
      39: monitorexit
      40: areturn
      41: astore_2
      42: aload_1
      43: monitorexit
      44: aload_2
      45: athrow
    Exception table:
       from    to  target type
           9    40    41   any
          41    44    41   any

  public synchronized org.apache.hadoop.hbase.regionserver.MetricsRegionServerSource createServer(org.apache.hadoop.hbase.regionserver.MetricsRegionServerWrapper);
    Code:
       0: new           #16                 // class org/apache/hadoop/hbase/regionserver/MetricsRegionServerSourceImpl
       3: dup
       4: aload_1
       5: invokespecial #17                 // Method org/apache/hadoop/hbase/regionserver/MetricsRegionServerSourceImpl."<init>":(Lorg/apache/hadoop/hbase/regionserver/MetricsRegionServerWrapper;)V
       8: areturn

  public org.apache.hadoop.hbase.regionserver.MetricsRegionSource createRegion(org.apache.hadoop.hbase.regionserver.MetricsRegionWrapper);
    Code:
       0: new           #18                 // class org/apache/hadoop/hbase/regionserver/MetricsRegionSourceImpl
       3: dup
       4: aload_1
       5: aload_0
       6: invokespecial #19                 // Method getAggregate:()Lorg/apache/hadoop/hbase/regionserver/MetricsRegionAggregateSourceImpl;
       9: invokespecial #20                 // Method org/apache/hadoop/hbase/regionserver/MetricsRegionSourceImpl."<init>":(Lorg/apache/hadoop/hbase/regionserver/MetricsRegionWrapper;Lorg/apache/hadoop/hbase/regionserver/MetricsRegionAggregateSourceImpl;)V
      12: areturn

  public org.apache.hadoop.hbase.regionserver.MetricsTableSource createTable(java.lang.String, org.apache.hadoop.hbase.regionserver.MetricsTableWrapperAggregate);
    Code:
       0: new           #21                 // class org/apache/hadoop/hbase/regionserver/MetricsTableSourceImpl
       3: dup
       4: aload_1
       5: aload_0
       6: invokevirtual #22                 // Method getTableAggregate:()Lorg/apache/hadoop/hbase/regionserver/MetricsTableAggregateSourceImpl;
       9: aload_2
      10: invokespecial #23                 // Method org/apache/hadoop/hbase/regionserver/MetricsTableSourceImpl."<init>":(Ljava/lang/String;Lorg/apache/hadoop/hbase/regionserver/MetricsTableAggregateSourceImpl;Lorg/apache/hadoop/hbase/regionserver/MetricsTableWrapperAggregate;)V
      13: areturn

  public org.apache.hadoop.hbase.io.MetricsIOSource createIO(org.apache.hadoop.hbase.io.MetricsIOWrapper);
    Code:
       0: new           #24                 // class org/apache/hadoop/hbase/io/MetricsIOSourceImpl
       3: dup
       4: aload_1
       5: invokespecial #25                 // Method org/apache/hadoop/hbase/io/MetricsIOSourceImpl."<init>":(Lorg/apache/hadoop/hbase/io/MetricsIOWrapper;)V
       8: areturn

  public org.apache.hadoop.hbase.regionserver.MetricsTableAggregateSource getTableAggregate();
    Code:
       0: aload_0
       1: invokevirtual #22                 // Method getTableAggregate:()Lorg/apache/hadoop/hbase/regionserver/MetricsTableAggregateSourceImpl;
       4: areturn
}
