Compiled from "MetricsExecutorImpl.java"
public class org.apache.hadoop.metrics2.lib.MetricsExecutorImpl implements org.apache.hadoop.metrics2.MetricsExecutor {
  public org.apache.hadoop.metrics2.lib.MetricsExecutorImpl();
    Code:
       0: aload_0
       1: invokespecial #1                  // Method java/lang/Object."<init>":()V
       4: return

  public java.util.concurrent.ScheduledExecutorService getExecutor();
    Code:
       0: getstatic     #2                  // Field org/apache/hadoop/metrics2/lib/MetricsExecutorImpl$ExecutorSingleton.INSTANCE:Lorg/apache/hadoop/metrics2/lib/MetricsExecutorImpl$ExecutorSingleton;
       3: invokestatic  #3                  // Method org/apache/hadoop/metrics2/lib/MetricsExecutorImpl$ExecutorSingleton.access$000:(Lorg/apache/hadoop/metrics2/lib/MetricsExecutorImpl$ExecutorSingleton;)Ljava/util/concurrent/ScheduledExecutorService;
       6: areturn

  public void stop();
    Code:
       0: aload_0
       1: invokevirtual #4                  // Method getExecutor:()Ljava/util/concurrent/ScheduledExecutorService;
       4: invokeinterface #5,  1            // InterfaceMethod java/util/concurrent/ScheduledExecutorService.isShutdown:()Z
       9: ifne          21
      12: aload_0
      13: invokevirtual #4                  // Method getExecutor:()Ljava/util/concurrent/ScheduledExecutorService;
      16: invokeinterface #6,  1            // InterfaceMethod java/util/concurrent/ScheduledExecutorService.shutdown:()V
      21: return
}
