Compiled from "MetricsIOSourceImpl.java"
public class org.apache.hadoop.hbase.io.MetricsIOSourceImpl extends org.apache.hadoop.hbase.metrics.BaseSourceImpl implements org.apache.hadoop.hbase.io.MetricsIOSource {
  public org.apache.hadoop.hbase.io.MetricsIOSourceImpl(org.apache.hadoop.hbase.io.MetricsIOWrapper);
    Code:
       0: aload_0
       1: ldc           #2                  // String IO
       3: ldc           #3                  // String Metrics about FileSystem IO
       5: ldc           #4                  // String regionserver
       7: ldc           #5                  // String RegionServer,sub=IO
       9: aload_1
      10: invokespecial #6                  // Method "<init>":(Ljava/lang/String;Ljava/lang/String;Ljava/lang/String;Ljava/lang/String;Lorg/apache/hadoop/hbase/io/MetricsIOWrapper;)V
      13: return

  public org.apache.hadoop.hbase.io.MetricsIOSourceImpl(java.lang.String, java.lang.String, java.lang.String, java.lang.String, org.apache.hadoop.hbase.io.MetricsIOWrapper);
    Code:
       0: aload_0
       1: aload_1
       2: aload_2
       3: aload_3
       4: aload         4
       6: invokespecial #7                  // Method org/apache/hadoop/hbase/metrics/BaseSourceImpl."<init>":(Ljava/lang/String;Ljava/lang/String;Ljava/lang/String;Ljava/lang/String;)V
       9: aload_0
      10: aload         5
      12: putfield      #8                  // Field wrapper:Lorg/apache/hadoop/hbase/io/MetricsIOWrapper;
      15: aload_0
      16: aload_0
      17: invokevirtual #9                  // Method getMetricsRegistry:()Lorg/apache/hadoop/metrics2/lib/DynamicMetricsRegistry;
      20: ldc           #10                 // String fsReadTime
      22: ldc           #11                 // String Latency of HFile's sequential reads on this region server in milliseconds
      24: invokevirtual #12                 // Method org/apache/hadoop/metrics2/lib/DynamicMetricsRegistry.newTimeHistogram:(Ljava/lang/String;Ljava/lang/String;)Lorg/apache/hadoop/metrics2/lib/MutableTimeHistogram;
      27: putfield      #13                 // Field fsReadTimeHisto:Lorg/apache/hadoop/metrics2/MetricHistogram;
      30: aload_0
      31: aload_0
      32: invokevirtual #9                  // Method getMetricsRegistry:()Lorg/apache/hadoop/metrics2/lib/DynamicMetricsRegistry;
      35: ldc           #14                 // String fsPReadTime
      37: ldc           #15                 // String Latency of HFile's positional reads on this region server in milliseconds
      39: invokevirtual #12                 // Method org/apache/hadoop/metrics2/lib/DynamicMetricsRegistry.newTimeHistogram:(Ljava/lang/String;Ljava/lang/String;)Lorg/apache/hadoop/metrics2/lib/MutableTimeHistogram;
      42: putfield      #16                 // Field fsPReadTimeHisto:Lorg/apache/hadoop/metrics2/MetricHistogram;
      45: aload_0
      46: aload_0
      47: invokevirtual #9                  // Method getMetricsRegistry:()Lorg/apache/hadoop/metrics2/lib/DynamicMetricsRegistry;
      50: ldc           #17                 // String fsWriteTime
      52: ldc           #18                 // String Latency of HFile's writes on this region server in milliseconds
      54: invokevirtual #12                 // Method org/apache/hadoop/metrics2/lib/DynamicMetricsRegistry.newTimeHistogram:(Ljava/lang/String;Ljava/lang/String;)Lorg/apache/hadoop/metrics2/lib/MutableTimeHistogram;
      57: putfield      #19                 // Field fsWriteTimeHisto:Lorg/apache/hadoop/metrics2/MetricHistogram;
      60: return

  public void updateFsReadTime(long);
    Code:
       0: aload_0
       1: getfield      #13                 // Field fsReadTimeHisto:Lorg/apache/hadoop/metrics2/MetricHistogram;
       4: lload_1
       5: invokeinterface #20,  3           // InterfaceMethod org/apache/hadoop/metrics2/MetricHistogram.add:(J)V
      10: return

  public void updateFsPReadTime(long);
    Code:
       0: aload_0
       1: getfield      #16                 // Field fsPReadTimeHisto:Lorg/apache/hadoop/metrics2/MetricHistogram;
       4: lload_1
       5: invokeinterface #20,  3           // InterfaceMethod org/apache/hadoop/metrics2/MetricHistogram.add:(J)V
      10: return

  public void updateFsWriteTime(long);
    Code:
       0: aload_0
       1: getfield      #19                 // Field fsWriteTimeHisto:Lorg/apache/hadoop/metrics2/MetricHistogram;
       4: lload_1
       5: invokeinterface #20,  3           // InterfaceMethod org/apache/hadoop/metrics2/MetricHistogram.add:(J)V
      10: return

  public void getMetrics(org.apache.hadoop.metrics2.MetricsCollector, boolean);
    Code:
       0: aload_1
       1: aload_0
       2: getfield      #21                 // Field metricsName:Ljava/lang/String;
       5: invokeinterface #22,  2           // InterfaceMethod org/apache/hadoop/metrics2/MetricsCollector.addRecord:(Ljava/lang/String;)Lorg/apache/hadoop/metrics2/MetricsRecordBuilder;
      10: astore_3
      11: aload_0
      12: getfield      #8                  // Field wrapper:Lorg/apache/hadoop/hbase/io/MetricsIOWrapper;
      15: ifnull        39
      18: aload_3
      19: ldc           #23                 // String fsChecksumFailureCount
      21: ldc           #24                 // String Number of checksum failures for the HBase HFile checksums at the HBase level (separate from HDFS checksums)
      23: invokestatic  #25                 // Method org/apache/hadoop/metrics2/lib/Interns.info:(Ljava/lang/String;Ljava/lang/String;)Lorg/apache/hadoop/metrics2/MetricsInfo;
      26: aload_0
      27: getfield      #8                  // Field wrapper:Lorg/apache/hadoop/hbase/io/MetricsIOWrapper;
      30: invokeinterface #26,  1           // InterfaceMethod org/apache/hadoop/hbase/io/MetricsIOWrapper.getChecksumFailures:()J
      35: invokevirtual #27                 // Method org/apache/hadoop/metrics2/MetricsRecordBuilder.addCounter:(Lorg/apache/hadoop/metrics2/MetricsInfo;J)Lorg/apache/hadoop/metrics2/MetricsRecordBuilder;
      38: pop
      39: aload_0
      40: getfield      #28                 // Field metricsRegistry:Lorg/apache/hadoop/metrics2/lib/DynamicMetricsRegistry;
      43: aload_3
      44: iload_2
      45: invokevirtual #29                 // Method org/apache/hadoop/metrics2/lib/DynamicMetricsRegistry.snapshot:(Lorg/apache/hadoop/metrics2/MetricsRecordBuilder;Z)V
      48: return
}
