Compiled from "MetricsRegionServerWrapperImpl.java"
public class org.apache.hadoop.hbase.regionserver.MetricsRegionServerWrapperImpl$RegionServerMetricsWrapperRunnable implements java.lang.Runnable {
  final org.apache.hadoop.hbase.regionserver.MetricsRegionServerWrapperImpl this$0;

  public org.apache.hadoop.hbase.regionserver.MetricsRegionServerWrapperImpl$RegionServerMetricsWrapperRunnable(org.apache.hadoop.hbase.regionserver.MetricsRegionServerWrapperImpl);
    Code:
       0: aload_0
       1: aload_1
       2: putfield      #1                  // Field this$0:Lorg/apache/hadoop/hbase/regionserver/MetricsRegionServerWrapperImpl;
       5: aload_0
       6: invokespecial #2                  // Method java/lang/Object."<init>":()V
       9: aload_0
      10: lconst_0
      11: putfield      #3                  // Field lastRan:J
      14: aload_0
      15: lconst_0
      16: putfield      #4                  // Field lastRequestCount:J
      19: aload_0
      20: lconst_0
      21: putfield      #5                  // Field lastReadRequestsCount:J
      24: aload_0
      25: lconst_0
      26: putfield      #6                  // Field lastWriteRequestsCount:J
      29: aload_0
      30: lconst_0
      31: putfield      #7                  // Field lastStoreFileSize:J
      34: return

  public synchronized void run();
    Code:
       0: new           #8                  // class org/apache/hadoop/hbase/HDFSBlocksDistribution
       3: dup
       4: invokespecial #9                  // Method org/apache/hadoop/hbase/HDFSBlocksDistribution."<init>":()V
       7: astore_1
       8: new           #8                  // class org/apache/hadoop/hbase/HDFSBlocksDistribution
      11: dup
      12: invokespecial #9                  // Method org/apache/hadoop/hbase/HDFSBlocksDistribution."<init>":()V
      15: astore_2
      16: lconst_0
      17: lstore_3
      18: lconst_0
      19: lstore        5
      21: lconst_0
      22: lstore        7
      24: lconst_0
      25: lstore        9
      27: lconst_0
      28: lstore        11
      30: lconst_0
      31: lstore        13
      33: lconst_0
      34: lstore        15
      36: lconst_0
      37: lstore        17
      39: ldc2_w        #11                 // long 9223372036854775807l
      42: lstore        19
      44: lconst_0
      45: lstore        21
      47: lconst_0
      48: lstore        23
      50: lconst_0
      51: lstore        25
      53: lconst_0
      54: lstore        27
      56: lconst_0
      57: lstore        29
      59: lconst_0
      60: lstore        31
      62: lconst_0
      63: lstore        33
      65: lconst_0
      66: lstore        35
      68: lconst_0
      69: lstore        37
      71: lconst_0
      72: lstore        39
      74: lconst_0
      75: lstore        41
      77: dconst_0
      78: dstore        43
      80: dconst_0
      81: dstore        45
      83: lconst_0
      84: lstore        47
      86: lconst_0
      87: lstore        49
      89: lconst_0
      90: lstore        51
      92: lconst_0
      93: lstore        53
      95: lconst_0
      96: lstore        55
      98: lconst_0
      99: lstore        57
     101: lconst_0
     102: lstore        59
     104: lconst_0
     105: lstore        61
     107: lconst_0
     108: lstore        63
     110: lconst_0
     111: lstore        65
     113: lconst_0
     114: lstore        67
     116: lconst_0
     117: lstore        69
     119: lconst_0
     120: lstore        71
     122: lconst_0
     123: lstore        73
     125: lconst_0
     126: lstore        75
     128: lconst_0
     129: lstore        77
     131: iconst_0
     132: istore        79
     134: aload_0
     135: getfield      #1                  // Field this$0:Lorg/apache/hadoop/hbase/regionserver/MetricsRegionServerWrapperImpl;
     138: invokestatic  #13                 // Method org/apache/hadoop/hbase/regionserver/MetricsRegionServerWrapperImpl.access$000:(Lorg/apache/hadoop/hbase/regionserver/MetricsRegionServerWrapperImpl;)Lorg/apache/hadoop/hbase/regionserver/HRegionServer;
     141: invokevirtual #14                 // Method org/apache/hadoop/hbase/regionserver/HRegionServer.getOnlineRegionsLocalContext:()Ljava/util/Collection;
     144: invokeinterface #15,  1           // InterfaceMethod java/util/Collection.iterator:()Ljava/util/Iterator;
     149: astore        80
     151: aload         80
     153: invokeinterface #16,  1           // InterfaceMethod java/util/Iterator.hasNext:()Z
     158: ifeq          737
     161: aload         80
     163: invokeinterface #17,  1           // InterfaceMethod java/util/Iterator.next:()Ljava/lang/Object;
     168: checkcast     #18                 // class org/apache/hadoop/hbase/regionserver/HRegion
     171: astore        81
     173: lload         39
     175: aload         81
     177: invokevirtual #19                 // Method org/apache/hadoop/hbase/regionserver/HRegion.getNumMutationsWithoutWAL:()J
     180: ladd
     181: lstore        39
     183: lload         41
     185: aload         81
     187: invokevirtual #20                 // Method org/apache/hadoop/hbase/regionserver/HRegion.getDataInMemoryWithoutWAL:()J
     190: ladd
     191: lstore        41
     193: lload         21
     195: aload         81
     197: invokevirtual #21                 // Method org/apache/hadoop/hbase/regionserver/HRegion.getReadRequestsCount:()J
     200: ladd
     201: lstore        21
     203: lload         27
     205: aload         81
     207: invokevirtual #22                 // Method org/apache/hadoop/hbase/regionserver/HRegion.getCpRequestsCount:()J
     210: ladd
     211: lstore        27
     213: lload         23
     215: aload         81
     217: invokevirtual #23                 // Method org/apache/hadoop/hbase/regionserver/HRegion.getFilteredReadRequestsCount:()J
     220: ladd
     221: lstore        23
     223: lload         25
     225: aload         81
     227: invokevirtual #24                 // Method org/apache/hadoop/hbase/regionserver/HRegion.getWriteRequestsCount:()J
     230: ladd
     231: lstore        25
     233: lload         29
     235: aload         81
     237: invokevirtual #25                 // Method org/apache/hadoop/hbase/regionserver/HRegion.getCheckAndMutateChecksFailed:()J
     240: ladd
     241: lstore        29
     243: lload         31
     245: aload         81
     247: invokevirtual #26                 // Method org/apache/hadoop/hbase/regionserver/HRegion.getCheckAndMutateChecksPassed:()J
     250: ladd
     251: lstore        31
     253: lload         77
     255: aload         81
     257: invokevirtual #27                 // Method org/apache/hadoop/hbase/regionserver/HRegion.getBlockedRequestsCount:()J
     260: ladd
     261: lstore        77
     263: aload         81
     265: invokevirtual #28                 // Method org/apache/hadoop/hbase/regionserver/HRegion.getStores:()Ljava/util/List;
     268: astore        82
     270: lload_3
     271: aload         82
     273: invokeinterface #29,  1           // InterfaceMethod java/util/List.size:()I
     278: i2l
     279: ladd
     280: lstore_3
     281: aload         82
     283: invokeinterface #30,  1           // InterfaceMethod java/util/List.iterator:()Ljava/util/Iterator;
     288: astore        83
     290: aload         83
     292: invokeinterface #16,  1           // InterfaceMethod java/util/Iterator.hasNext:()Z
     297: ifeq          699
     300: aload         83
     302: invokeinterface #17,  1           // InterfaceMethod java/util/Iterator.next:()Ljava/lang/Object;
     307: checkcast     #31                 // class org/apache/hadoop/hbase/regionserver/Store
     310: astore        84
     312: lload         5
     314: aload         84
     316: invokeinterface #32,  1           // InterfaceMethod org/apache/hadoop/hbase/regionserver/Store.getStorefilesCount:()I
     321: i2l
     322: ladd
     323: lstore        5
     325: lload         7
     327: aload         84
     329: invokeinterface #33,  1           // InterfaceMethod org/apache/hadoop/hbase/regionserver/Store.getMemStoreSize:()Lorg/apache/hadoop/hbase/regionserver/MemStoreSize;
     334: invokevirtual #34                 // Method org/apache/hadoop/hbase/regionserver/MemStoreSize.getDataSize:()J
     337: ladd
     338: lstore        7
     340: lload         9
     342: aload         84
     344: invokeinterface #35,  1           // InterfaceMethod org/apache/hadoop/hbase/regionserver/Store.getStorefilesSize:()J
     349: ladd
     350: lstore        9
     352: aload         84
     354: invokeinterface #36,  1           // InterfaceMethod org/apache/hadoop/hbase/regionserver/Store.getMaxStoreFileAge:()Ljava/util/OptionalLong;
     359: astore        85
     361: aload         85
     363: invokevirtual #37                 // Method java/util/OptionalLong.isPresent:()Z
     366: ifeq          387
     369: aload         85
     371: invokevirtual #38                 // Method java/util/OptionalLong.getAsLong:()J
     374: lload         11
     376: lcmp
     377: ifle          387
     380: aload         85
     382: invokevirtual #38                 // Method java/util/OptionalLong.getAsLong:()J
     385: lstore        11
     387: aload         84
     389: invokeinterface #39,  1           // InterfaceMethod org/apache/hadoop/hbase/regionserver/Store.getMinStoreFileAge:()Ljava/util/OptionalLong;
     394: astore        86
     396: aload         86
     398: invokevirtual #37                 // Method java/util/OptionalLong.isPresent:()Z
     401: ifeq          422
     404: aload         86
     406: invokevirtual #38                 // Method java/util/OptionalLong.getAsLong:()J
     409: lload         19
     411: lcmp
     412: ifge          422
     415: aload         86
     417: invokevirtual #38                 // Method java/util/OptionalLong.getAsLong:()J
     420: lstore        19
     422: aload         84
     424: invokeinterface #40,  1           // InterfaceMethod org/apache/hadoop/hbase/regionserver/Store.getNumHFiles:()J
     429: lstore        87
     431: lload         17
     433: lload         87
     435: ladd
     436: lstore        17
     438: lload         13
     440: aload         84
     442: invokeinterface #41,  1           // InterfaceMethod org/apache/hadoop/hbase/regionserver/Store.getNumReferenceFiles:()J
     447: ladd
     448: lstore        13
     450: aload         84
     452: invokeinterface #42,  1           // InterfaceMethod org/apache/hadoop/hbase/regionserver/Store.getAvgStoreFileAge:()Ljava/util/OptionalDouble;
     457: astore        89
     459: aload         89
     461: invokevirtual #43                 // Method java/util/OptionalDouble.isPresent:()Z
     464: ifeq          483
     467: lload         15
     469: l2d
     470: aload         89
     472: invokevirtual #44                 // Method java/util/OptionalDouble.getAsDouble:()D
     475: lload         87
     477: l2d
     478: dmul
     479: dadd
     480: d2l
     481: lstore        15
     483: lload         33
     485: aload         84
     487: invokeinterface #45,  1           // InterfaceMethod org/apache/hadoop/hbase/regionserver/Store.getStorefilesRootLevelIndexSize:()J
     492: ladd
     493: lstore        33
     495: lload         37
     497: aload         84
     499: invokeinterface #46,  1           // InterfaceMethod org/apache/hadoop/hbase/regionserver/Store.getTotalStaticBloomSize:()J
     504: ladd
     505: lstore        37
     507: lload         35
     509: aload         84
     511: invokeinterface #47,  1           // InterfaceMethod org/apache/hadoop/hbase/regionserver/Store.getTotalStaticIndexSize:()J
     516: ladd
     517: lstore        35
     519: lload         47
     521: aload         84
     523: invokeinterface #48,  1           // InterfaceMethod org/apache/hadoop/hbase/regionserver/Store.getFlushedCellsCount:()J
     528: ladd
     529: lstore        47
     531: lload         49
     533: aload         84
     535: invokeinterface #49,  1           // InterfaceMethod org/apache/hadoop/hbase/regionserver/Store.getCompactedCellsCount:()J
     540: ladd
     541: lstore        49
     543: lload         51
     545: aload         84
     547: invokeinterface #50,  1           // InterfaceMethod org/apache/hadoop/hbase/regionserver/Store.getMajorCompactedCellsCount:()J
     552: ladd
     553: lstore        51
     555: lload         53
     557: aload         84
     559: invokeinterface #51,  1           // InterfaceMethod org/apache/hadoop/hbase/regionserver/Store.getFlushedCellsSize:()J
     564: ladd
     565: lstore        53
     567: lload         55
     569: aload         84
     571: invokeinterface #52,  1           // InterfaceMethod org/apache/hadoop/hbase/regionserver/Store.getCompactedCellsSize:()J
     576: ladd
     577: lstore        55
     579: lload         57
     581: aload         84
     583: invokeinterface #53,  1           // InterfaceMethod org/apache/hadoop/hbase/regionserver/Store.getMajorCompactedCellsSize:()J
     588: ladd
     589: lstore        57
     591: aload         84
     593: instanceof    #54                 // class org/apache/hadoop/hbase/regionserver/HMobStore
     596: ifeq          696
     599: aload         84
     601: checkcast     #54                 // class org/apache/hadoop/hbase/regionserver/HMobStore
     604: astore        90
     606: lload         59
     608: aload         90
     610: invokevirtual #55                 // Method org/apache/hadoop/hbase/regionserver/HMobStore.getCellsCountCompactedToMob:()J
     613: ladd
     614: lstore        59
     616: lload         61
     618: aload         90
     620: invokevirtual #56                 // Method org/apache/hadoop/hbase/regionserver/HMobStore.getCellsCountCompactedFromMob:()J
     623: ladd
     624: lstore        61
     626: lload         63
     628: aload         90
     630: invokevirtual #57                 // Method org/apache/hadoop/hbase/regionserver/HMobStore.getCellsSizeCompactedToMob:()J
     633: ladd
     634: lstore        63
     636: lload         65
     638: aload         90
     640: invokevirtual #58                 // Method org/apache/hadoop/hbase/regionserver/HMobStore.getCellsSizeCompactedFromMob:()J
     643: ladd
     644: lstore        65
     646: lload         67
     648: aload         90
     650: invokevirtual #59                 // Method org/apache/hadoop/hbase/regionserver/HMobStore.getMobFlushCount:()J
     653: ladd
     654: lstore        67
     656: lload         69
     658: aload         90
     660: invokevirtual #60                 // Method org/apache/hadoop/hbase/regionserver/HMobStore.getMobFlushedCellsCount:()J
     663: ladd
     664: lstore        69
     666: lload         71
     668: aload         90
     670: invokevirtual #61                 // Method org/apache/hadoop/hbase/regionserver/HMobStore.getMobFlushedCellsSize:()J
     673: ladd
     674: lstore        71
     676: lload         73
     678: aload         90
     680: invokevirtual #62                 // Method org/apache/hadoop/hbase/regionserver/HMobStore.getMobScanCellsCount:()J
     683: ladd
     684: lstore        73
     686: lload         75
     688: aload         90
     690: invokevirtual #63                 // Method org/apache/hadoop/hbase/regionserver/HMobStore.getMobScanCellsSize:()J
     693: ladd
     694: lstore        75
     696: goto          290
     699: aload         81
     701: invokevirtual #64                 // Method org/apache/hadoop/hbase/regionserver/HRegion.getHDFSBlocksDistribution:()Lorg/apache/hadoop/hbase/HDFSBlocksDistribution;
     704: astore        83
     706: aload_1
     707: aload         83
     709: invokevirtual #65                 // Method org/apache/hadoop/hbase/HDFSBlocksDistribution.add:(Lorg/apache/hadoop/hbase/HDFSBlocksDistribution;)V
     712: aload         81
     714: invokevirtual #66                 // Method org/apache/hadoop/hbase/regionserver/HRegion.getRegionInfo:()Lorg/apache/hadoop/hbase/client/RegionInfo;
     717: invokeinterface #67,  1           // InterfaceMethod org/apache/hadoop/hbase/client/RegionInfo.getReplicaId:()I
     722: ifeq          731
     725: aload_2
     726: aload         83
     728: invokevirtual #65                 // Method org/apache/hadoop/hbase/HDFSBlocksDistribution.add:(Lorg/apache/hadoop/hbase/HDFSBlocksDistribution;)V
     731: iinc          79, 1
     734: goto          151
     737: aload_1
     738: aload_0
     739: getfield      #1                  // Field this$0:Lorg/apache/hadoop/hbase/regionserver/MetricsRegionServerWrapperImpl;
     742: invokestatic  #13                 // Method org/apache/hadoop/hbase/regionserver/MetricsRegionServerWrapperImpl.access$000:(Lorg/apache/hadoop/hbase/regionserver/MetricsRegionServerWrapperImpl;)Lorg/apache/hadoop/hbase/regionserver/HRegionServer;
     745: invokevirtual #68                 // Method org/apache/hadoop/hbase/regionserver/HRegionServer.getServerName:()Lorg/apache/hadoop/hbase/ServerName;
     748: invokevirtual #69                 // Method org/apache/hadoop/hbase/ServerName.getHostname:()Ljava/lang/String;
     751: invokevirtual #70                 // Method org/apache/hadoop/hbase/HDFSBlocksDistribution.getBlockLocalityIndex:(Ljava/lang/String;)F
     754: fstore        80
     756: lload         77
     758: l2d
     759: invokestatic  #71                 // Method java/lang/Double.isNaN:(D)Z
     762: ifeq          769
     765: dconst_0
     766: goto          775
     769: fload         80
     771: ldc           #72                 // float 100.0f
     773: fmul
     774: f2d
     775: dstore        43
     777: aload_2
     778: aload_0
     779: getfield      #1                  // Field this$0:Lorg/apache/hadoop/hbase/regionserver/MetricsRegionServerWrapperImpl;
     782: invokestatic  #13                 // Method org/apache/hadoop/hbase/regionserver/MetricsRegionServerWrapperImpl.access$000:(Lorg/apache/hadoop/hbase/regionserver/MetricsRegionServerWrapperImpl;)Lorg/apache/hadoop/hbase/regionserver/HRegionServer;
     785: invokevirtual #68                 // Method org/apache/hadoop/hbase/regionserver/HRegionServer.getServerName:()Lorg/apache/hadoop/hbase/ServerName;
     788: invokevirtual #69                 // Method org/apache/hadoop/hbase/ServerName.getHostname:()Ljava/lang/String;
     791: invokevirtual #70                 // Method org/apache/hadoop/hbase/HDFSBlocksDistribution.getBlockLocalityIndex:(Ljava/lang/String;)F
     794: fstore        81
     796: fload         81
     798: f2d
     799: invokestatic  #71                 // Method java/lang/Double.isNaN:(D)Z
     802: ifeq          809
     805: dconst_0
     806: goto          815
     809: fload         81
     811: ldc           #72                 // float 100.0f
     813: fmul
     814: f2d
     815: dstore        45
     817: invokestatic  #73                 // Method org/apache/hadoop/hbase/util/EnvironmentEdgeManager.currentTime:()J
     820: lstore        82
     822: aload_0
     823: getfield      #3                  // Field lastRan:J
     826: lconst_0
     827: lcmp
     828: ifne          845
     831: aload_0
     832: lload         82
     834: aload_0
     835: getfield      #1                  // Field this$0:Lorg/apache/hadoop/hbase/regionserver/MetricsRegionServerWrapperImpl;
     838: invokestatic  #74                 // Method org/apache/hadoop/hbase/regionserver/MetricsRegionServerWrapperImpl.access$100:(Lorg/apache/hadoop/hbase/regionserver/MetricsRegionServerWrapperImpl;)J
     841: lsub
     842: putfield      #3                  // Field lastRan:J
     845: lload         82
     847: aload_0
     848: getfield      #3                  // Field lastRan:J
     851: lsub
     852: lconst_0
     853: lcmp
     854: ifle          1026
     857: aload_0
     858: getfield      #1                  // Field this$0:Lorg/apache/hadoop/hbase/regionserver/MetricsRegionServerWrapperImpl;
     861: invokevirtual #75                 // Method org/apache/hadoop/hbase/regionserver/MetricsRegionServerWrapperImpl.getTotalRequestCount:()J
     864: lstore        84
     866: aload_0
     867: getfield      #1                  // Field this$0:Lorg/apache/hadoop/hbase/regionserver/MetricsRegionServerWrapperImpl;
     870: lload         84
     872: aload_0
     873: getfield      #4                  // Field lastRequestCount:J
     876: lsub
     877: l2d
     878: lload         82
     880: aload_0
     881: getfield      #3                  // Field lastRan:J
     884: lsub
     885: l2d
     886: ldc2_w        #76                 // double 1000.0d
     889: ddiv
     890: ddiv
     891: invokestatic  #78                 // Method org/apache/hadoop/hbase/regionserver/MetricsRegionServerWrapperImpl.access$202:(Lorg/apache/hadoop/hbase/regionserver/MetricsRegionServerWrapperImpl;D)D
     894: pop2
     895: aload_0
     896: lload         84
     898: putfield      #4                  // Field lastRequestCount:J
     901: lload         21
     903: aload_0
     904: getfield      #5                  // Field lastReadRequestsCount:J
     907: lsub
     908: lstore        86
     910: lload         25
     912: aload_0
     913: getfield      #6                  // Field lastWriteRequestsCount:J
     916: lsub
     917: lstore        88
     919: lload         86
     921: l2d
     922: aload_0
     923: getfield      #1                  // Field this$0:Lorg/apache/hadoop/hbase/regionserver/MetricsRegionServerWrapperImpl;
     926: invokestatic  #74                 // Method org/apache/hadoop/hbase/regionserver/MetricsRegionServerWrapperImpl.access$100:(Lorg/apache/hadoop/hbase/regionserver/MetricsRegionServerWrapperImpl;)J
     929: l2d
     930: ddiv
     931: dstore        90
     933: lload         88
     935: l2d
     936: aload_0
     937: getfield      #1                  // Field this$0:Lorg/apache/hadoop/hbase/regionserver/MetricsRegionServerWrapperImpl;
     940: invokestatic  #74                 // Method org/apache/hadoop/hbase/regionserver/MetricsRegionServerWrapperImpl.access$100:(Lorg/apache/hadoop/hbase/regionserver/MetricsRegionServerWrapperImpl;)J
     943: l2d
     944: ddiv
     945: dstore        92
     947: aload_0
     948: getfield      #1                  // Field this$0:Lorg/apache/hadoop/hbase/regionserver/MetricsRegionServerWrapperImpl;
     951: dload         90
     953: ldc2_w        #76                 // double 1000.0d
     956: dmul
     957: invokestatic  #79                 // Method org/apache/hadoop/hbase/regionserver/MetricsRegionServerWrapperImpl.access$302:(Lorg/apache/hadoop/hbase/regionserver/MetricsRegionServerWrapperImpl;D)D
     960: pop2
     961: aload_0
     962: getfield      #1                  // Field this$0:Lorg/apache/hadoop/hbase/regionserver/MetricsRegionServerWrapperImpl;
     965: dload         92
     967: ldc2_w        #76                 // double 1000.0d
     970: dmul
     971: invokestatic  #80                 // Method org/apache/hadoop/hbase/regionserver/MetricsRegionServerWrapperImpl.access$402:(Lorg/apache/hadoop/hbase/regionserver/MetricsRegionServerWrapperImpl;D)D
     974: pop2
     975: lload         9
     977: aload_0
     978: getfield      #7                  // Field lastStoreFileSize:J
     981: lsub
     982: lstore        94
     984: aload_0
     985: getfield      #1                  // Field this$0:Lorg/apache/hadoop/hbase/regionserver/MetricsRegionServerWrapperImpl;
     988: lload         94
     990: l2d
     991: ldc2_w        #76                 // double 1000.0d
     994: dmul
     995: aload_0
     996: getfield      #1                  // Field this$0:Lorg/apache/hadoop/hbase/regionserver/MetricsRegionServerWrapperImpl;
     999: invokestatic  #74                 // Method org/apache/hadoop/hbase/regionserver/MetricsRegionServerWrapperImpl.access$100:(Lorg/apache/hadoop/hbase/regionserver/MetricsRegionServerWrapperImpl;)J
    1002: l2d
    1003: ddiv
    1004: invokestatic  #81                 // Method org/apache/hadoop/hbase/regionserver/MetricsRegionServerWrapperImpl.access$502:(Lorg/apache/hadoop/hbase/regionserver/MetricsRegionServerWrapperImpl;D)D
    1007: pop2
    1008: aload_0
    1009: lload         21
    1011: putfield      #5                  // Field lastReadRequestsCount:J
    1014: aload_0
    1015: lload         25
    1017: putfield      #6                  // Field lastWriteRequestsCount:J
    1020: aload_0
    1021: lload         9
    1023: putfield      #7                  // Field lastStoreFileSize:J
    1026: aload_0
    1027: lload         82
    1029: putfield      #3                  // Field lastRan:J
    1032: aload_0
    1033: getfield      #1                  // Field this$0:Lorg/apache/hadoop/hbase/regionserver/MetricsRegionServerWrapperImpl;
    1036: invokestatic  #13                 // Method org/apache/hadoop/hbase/regionserver/MetricsRegionServerWrapperImpl.access$000:(Lorg/apache/hadoop/hbase/regionserver/MetricsRegionServerWrapperImpl;)Lorg/apache/hadoop/hbase/regionserver/HRegionServer;
    1039: getfield      #82                 // Field org/apache/hadoop/hbase/regionserver/HRegionServer.walFactory:Lorg/apache/hadoop/hbase/wal/WALFactory;
    1042: invokevirtual #83                 // Method org/apache/hadoop/hbase/wal/WALFactory.getWALProvider:()Lorg/apache/hadoop/hbase/wal/WALProvider;
    1045: astore        84
    1047: aload_0
    1048: getfield      #1                  // Field this$0:Lorg/apache/hadoop/hbase/regionserver/MetricsRegionServerWrapperImpl;
    1051: invokestatic  #13                 // Method org/apache/hadoop/hbase/regionserver/MetricsRegionServerWrapperImpl.access$000:(Lorg/apache/hadoop/hbase/regionserver/MetricsRegionServerWrapperImpl;)Lorg/apache/hadoop/hbase/regionserver/HRegionServer;
    1054: getfield      #82                 // Field org/apache/hadoop/hbase/regionserver/HRegionServer.walFactory:Lorg/apache/hadoop/hbase/wal/WALFactory;
    1057: invokevirtual #84                 // Method org/apache/hadoop/hbase/wal/WALFactory.getMetaWALProvider:()Lorg/apache/hadoop/hbase/wal/WALProvider;
    1060: astore        85
    1062: aload_0
    1063: getfield      #1                  // Field this$0:Lorg/apache/hadoop/hbase/regionserver/MetricsRegionServerWrapperImpl;
    1066: aload         84
    1068: ifnonnull     1075
    1071: lconst_0
    1072: goto          1082
    1075: aload         84
    1077: invokeinterface #85,  1           // InterfaceMethod org/apache/hadoop/hbase/wal/WALProvider.getNumLogFiles:()J
    1082: aload         85
    1084: ifnonnull     1091
    1087: lconst_0
    1088: goto          1098
    1091: aload         85
    1093: invokeinterface #85,  1           // InterfaceMethod org/apache/hadoop/hbase/wal/WALProvider.getNumLogFiles:()J
    1098: ladd
    1099: invokestatic  #86                 // Method org/apache/hadoop/hbase/regionserver/MetricsRegionServerWrapperImpl.access$602:(Lorg/apache/hadoop/hbase/regionserver/MetricsRegionServerWrapperImpl;J)J
    1102: pop2
    1103: aload_0
    1104: getfield      #1                  // Field this$0:Lorg/apache/hadoop/hbase/regionserver/MetricsRegionServerWrapperImpl;
    1107: aload         84
    1109: ifnonnull     1116
    1112: lconst_0
    1113: goto          1123
    1116: aload         84
    1118: invokeinterface #87,  1           // InterfaceMethod org/apache/hadoop/hbase/wal/WALProvider.getLogFileSize:()J
    1123: aload         84
    1125: ifnonnull     1132
    1128: lconst_0
    1129: goto          1139
    1132: aload         84
    1134: invokeinterface #87,  1           // InterfaceMethod org/apache/hadoop/hbase/wal/WALProvider.getLogFileSize:()J
    1139: ladd
    1140: invokestatic  #88                 // Method org/apache/hadoop/hbase/regionserver/MetricsRegionServerWrapperImpl.access$702:(Lorg/apache/hadoop/hbase/regionserver/MetricsRegionServerWrapperImpl;J)J
    1143: pop2
    1144: aload_0
    1145: getfield      #1                  // Field this$0:Lorg/apache/hadoop/hbase/regionserver/MetricsRegionServerWrapperImpl;
    1148: lload_3
    1149: invokestatic  #89                 // Method org/apache/hadoop/hbase/regionserver/MetricsRegionServerWrapperImpl.access$802:(Lorg/apache/hadoop/hbase/regionserver/MetricsRegionServerWrapperImpl;J)J
    1152: pop2
    1153: aload_0
    1154: getfield      #1                  // Field this$0:Lorg/apache/hadoop/hbase/regionserver/MetricsRegionServerWrapperImpl;
    1157: lload         5
    1159: invokestatic  #90                 // Method org/apache/hadoop/hbase/regionserver/MetricsRegionServerWrapperImpl.access$902:(Lorg/apache/hadoop/hbase/regionserver/MetricsRegionServerWrapperImpl;J)J
    1162: pop2
    1163: aload_0
    1164: getfield      #1                  // Field this$0:Lorg/apache/hadoop/hbase/regionserver/MetricsRegionServerWrapperImpl;
    1167: lload         7
    1169: invokestatic  #91                 // Method org/apache/hadoop/hbase/regionserver/MetricsRegionServerWrapperImpl.access$1002:(Lorg/apache/hadoop/hbase/regionserver/MetricsRegionServerWrapperImpl;J)J
    1172: pop2
    1173: aload_0
    1174: getfield      #1                  // Field this$0:Lorg/apache/hadoop/hbase/regionserver/MetricsRegionServerWrapperImpl;
    1177: lload         9
    1179: invokestatic  #92                 // Method org/apache/hadoop/hbase/regionserver/MetricsRegionServerWrapperImpl.access$1102:(Lorg/apache/hadoop/hbase/regionserver/MetricsRegionServerWrapperImpl;J)J
    1182: pop2
    1183: aload_0
    1184: getfield      #1                  // Field this$0:Lorg/apache/hadoop/hbase/regionserver/MetricsRegionServerWrapperImpl;
    1187: lload         11
    1189: invokestatic  #93                 // Method org/apache/hadoop/hbase/regionserver/MetricsRegionServerWrapperImpl.access$1202:(Lorg/apache/hadoop/hbase/regionserver/MetricsRegionServerWrapperImpl;J)J
    1192: pop2
    1193: iload         79
    1195: ifle          1225
    1198: aload_0
    1199: getfield      #1                  // Field this$0:Lorg/apache/hadoop/hbase/regionserver/MetricsRegionServerWrapperImpl;
    1202: aload_0
    1203: getfield      #1                  // Field this$0:Lorg/apache/hadoop/hbase/regionserver/MetricsRegionServerWrapperImpl;
    1206: invokestatic  #94                 // Method org/apache/hadoop/hbase/regionserver/MetricsRegionServerWrapperImpl.access$1000:(Lorg/apache/hadoop/hbase/regionserver/MetricsRegionServerWrapperImpl;)J
    1209: aload_0
    1210: getfield      #1                  // Field this$0:Lorg/apache/hadoop/hbase/regionserver/MetricsRegionServerWrapperImpl;
    1213: invokestatic  #95                 // Method org/apache/hadoop/hbase/regionserver/MetricsRegionServerWrapperImpl.access$1100:(Lorg/apache/hadoop/hbase/regionserver/MetricsRegionServerWrapperImpl;)J
    1216: ladd
    1217: iload         79
    1219: i2l
    1220: ldiv
    1221: invokestatic  #96                 // Method org/apache/hadoop/hbase/regionserver/MetricsRegionServerWrapperImpl.access$1302:(Lorg/apache/hadoop/hbase/regionserver/MetricsRegionServerWrapperImpl;J)J
    1224: pop2
    1225: lload         19
    1227: ldc2_w        #11                 // long 9223372036854775807l
    1230: lcmp
    1231: ifeq          1244
    1234: aload_0
    1235: getfield      #1                  // Field this$0:Lorg/apache/hadoop/hbase/regionserver/MetricsRegionServerWrapperImpl;
    1238: lload         19
    1240: invokestatic  #97                 // Method org/apache/hadoop/hbase/regionserver/MetricsRegionServerWrapperImpl.access$1402:(Lorg/apache/hadoop/hbase/regionserver/MetricsRegionServerWrapperImpl;J)J
    1243: pop2
    1244: lload         17
    1246: lconst_0
    1247: lcmp
    1248: ifeq          1264
    1251: aload_0
    1252: getfield      #1                  // Field this$0:Lorg/apache/hadoop/hbase/regionserver/MetricsRegionServerWrapperImpl;
    1255: lload         15
    1257: lload         17
    1259: ldiv
    1260: invokestatic  #98                 // Method org/apache/hadoop/hbase/regionserver/MetricsRegionServerWrapperImpl.access$1502:(Lorg/apache/hadoop/hbase/regionserver/MetricsRegionServerWrapperImpl;J)J
    1263: pop2
    1264: aload_0
    1265: getfield      #1                  // Field this$0:Lorg/apache/hadoop/hbase/regionserver/MetricsRegionServerWrapperImpl;
    1268: lload         13
    1270: invokestatic  #99                 // Method org/apache/hadoop/hbase/regionserver/MetricsRegionServerWrapperImpl.access$1602:(Lorg/apache/hadoop/hbase/regionserver/MetricsRegionServerWrapperImpl;J)J
    1273: pop2
    1274: aload_0
    1275: getfield      #1                  // Field this$0:Lorg/apache/hadoop/hbase/regionserver/MetricsRegionServerWrapperImpl;
    1278: lload         21
    1280: invokestatic  #100                // Method org/apache/hadoop/hbase/regionserver/MetricsRegionServerWrapperImpl.access$1702:(Lorg/apache/hadoop/hbase/regionserver/MetricsRegionServerWrapperImpl;J)J
    1283: pop2
    1284: aload_0
    1285: getfield      #1                  // Field this$0:Lorg/apache/hadoop/hbase/regionserver/MetricsRegionServerWrapperImpl;
    1288: lload         27
    1290: invokestatic  #101                // Method org/apache/hadoop/hbase/regionserver/MetricsRegionServerWrapperImpl.access$1802:(Lorg/apache/hadoop/hbase/regionserver/MetricsRegionServerWrapperImpl;J)J
    1293: pop2
    1294: aload_0
    1295: getfield      #1                  // Field this$0:Lorg/apache/hadoop/hbase/regionserver/MetricsRegionServerWrapperImpl;
    1298: lload         23
    1300: invokestatic  #102                // Method org/apache/hadoop/hbase/regionserver/MetricsRegionServerWrapperImpl.access$1902:(Lorg/apache/hadoop/hbase/regionserver/MetricsRegionServerWrapperImpl;J)J
    1303: pop2
    1304: aload_0
    1305: getfield      #1                  // Field this$0:Lorg/apache/hadoop/hbase/regionserver/MetricsRegionServerWrapperImpl;
    1308: lload         25
    1310: invokestatic  #103                // Method org/apache/hadoop/hbase/regionserver/MetricsRegionServerWrapperImpl.access$2002:(Lorg/apache/hadoop/hbase/regionserver/MetricsRegionServerWrapperImpl;J)J
    1313: pop2
    1314: aload_0
    1315: getfield      #1                  // Field this$0:Lorg/apache/hadoop/hbase/regionserver/MetricsRegionServerWrapperImpl;
    1318: lload         29
    1320: invokestatic  #104                // Method org/apache/hadoop/hbase/regionserver/MetricsRegionServerWrapperImpl.access$2102:(Lorg/apache/hadoop/hbase/regionserver/MetricsRegionServerWrapperImpl;J)J
    1323: pop2
    1324: aload_0
    1325: getfield      #1                  // Field this$0:Lorg/apache/hadoop/hbase/regionserver/MetricsRegionServerWrapperImpl;
    1328: lload         31
    1330: invokestatic  #105                // Method org/apache/hadoop/hbase/regionserver/MetricsRegionServerWrapperImpl.access$2202:(Lorg/apache/hadoop/hbase/regionserver/MetricsRegionServerWrapperImpl;J)J
    1333: pop2
    1334: aload_0
    1335: getfield      #1                  // Field this$0:Lorg/apache/hadoop/hbase/regionserver/MetricsRegionServerWrapperImpl;
    1338: lload         33
    1340: invokestatic  #106                // Method org/apache/hadoop/hbase/regionserver/MetricsRegionServerWrapperImpl.access$2302:(Lorg/apache/hadoop/hbase/regionserver/MetricsRegionServerWrapperImpl;J)J
    1343: pop2
    1344: aload_0
    1345: getfield      #1                  // Field this$0:Lorg/apache/hadoop/hbase/regionserver/MetricsRegionServerWrapperImpl;
    1348: lload         35
    1350: invokestatic  #107                // Method org/apache/hadoop/hbase/regionserver/MetricsRegionServerWrapperImpl.access$2402:(Lorg/apache/hadoop/hbase/regionserver/MetricsRegionServerWrapperImpl;J)J
    1353: pop2
    1354: aload_0
    1355: getfield      #1                  // Field this$0:Lorg/apache/hadoop/hbase/regionserver/MetricsRegionServerWrapperImpl;
    1358: lload         37
    1360: invokestatic  #108                // Method org/apache/hadoop/hbase/regionserver/MetricsRegionServerWrapperImpl.access$2502:(Lorg/apache/hadoop/hbase/regionserver/MetricsRegionServerWrapperImpl;J)J
    1363: pop2
    1364: aload_0
    1365: getfield      #1                  // Field this$0:Lorg/apache/hadoop/hbase/regionserver/MetricsRegionServerWrapperImpl;
    1368: lload         39
    1370: invokestatic  #109                // Method org/apache/hadoop/hbase/regionserver/MetricsRegionServerWrapperImpl.access$2602:(Lorg/apache/hadoop/hbase/regionserver/MetricsRegionServerWrapperImpl;J)J
    1373: pop2
    1374: aload_0
    1375: getfield      #1                  // Field this$0:Lorg/apache/hadoop/hbase/regionserver/MetricsRegionServerWrapperImpl;
    1378: lload         41
    1380: invokestatic  #110                // Method org/apache/hadoop/hbase/regionserver/MetricsRegionServerWrapperImpl.access$2702:(Lorg/apache/hadoop/hbase/regionserver/MetricsRegionServerWrapperImpl;J)J
    1383: pop2
    1384: aload_0
    1385: getfield      #1                  // Field this$0:Lorg/apache/hadoop/hbase/regionserver/MetricsRegionServerWrapperImpl;
    1388: dload         43
    1390: invokestatic  #111                // Method org/apache/hadoop/hbase/regionserver/MetricsRegionServerWrapperImpl.access$2802:(Lorg/apache/hadoop/hbase/regionserver/MetricsRegionServerWrapperImpl;D)D
    1393: pop2
    1394: aload_0
    1395: getfield      #1                  // Field this$0:Lorg/apache/hadoop/hbase/regionserver/MetricsRegionServerWrapperImpl;
    1398: dload         45
    1400: invokestatic  #112                // Method org/apache/hadoop/hbase/regionserver/MetricsRegionServerWrapperImpl.access$2902:(Lorg/apache/hadoop/hbase/regionserver/MetricsRegionServerWrapperImpl;D)D
    1403: pop2
    1404: aload_0
    1405: getfield      #1                  // Field this$0:Lorg/apache/hadoop/hbase/regionserver/MetricsRegionServerWrapperImpl;
    1408: lload         47
    1410: invokestatic  #113                // Method org/apache/hadoop/hbase/regionserver/MetricsRegionServerWrapperImpl.access$3002:(Lorg/apache/hadoop/hbase/regionserver/MetricsRegionServerWrapperImpl;J)J
    1413: pop2
    1414: aload_0
    1415: getfield      #1                  // Field this$0:Lorg/apache/hadoop/hbase/regionserver/MetricsRegionServerWrapperImpl;
    1418: lload         49
    1420: invokestatic  #114                // Method org/apache/hadoop/hbase/regionserver/MetricsRegionServerWrapperImpl.access$3102:(Lorg/apache/hadoop/hbase/regionserver/MetricsRegionServerWrapperImpl;J)J
    1423: pop2
    1424: aload_0
    1425: getfield      #1                  // Field this$0:Lorg/apache/hadoop/hbase/regionserver/MetricsRegionServerWrapperImpl;
    1428: lload         51
    1430: invokestatic  #115                // Method org/apache/hadoop/hbase/regionserver/MetricsRegionServerWrapperImpl.access$3202:(Lorg/apache/hadoop/hbase/regionserver/MetricsRegionServerWrapperImpl;J)J
    1433: pop2
    1434: aload_0
    1435: getfield      #1                  // Field this$0:Lorg/apache/hadoop/hbase/regionserver/MetricsRegionServerWrapperImpl;
    1438: lload         53
    1440: invokestatic  #116                // Method org/apache/hadoop/hbase/regionserver/MetricsRegionServerWrapperImpl.access$3302:(Lorg/apache/hadoop/hbase/regionserver/MetricsRegionServerWrapperImpl;J)J
    1443: pop2
    1444: aload_0
    1445: getfield      #1                  // Field this$0:Lorg/apache/hadoop/hbase/regionserver/MetricsRegionServerWrapperImpl;
    1448: lload         55
    1450: invokestatic  #117                // Method org/apache/hadoop/hbase/regionserver/MetricsRegionServerWrapperImpl.access$3402:(Lorg/apache/hadoop/hbase/regionserver/MetricsRegionServerWrapperImpl;J)J
    1453: pop2
    1454: aload_0
    1455: getfield      #1                  // Field this$0:Lorg/apache/hadoop/hbase/regionserver/MetricsRegionServerWrapperImpl;
    1458: lload         57
    1460: invokestatic  #118                // Method org/apache/hadoop/hbase/regionserver/MetricsRegionServerWrapperImpl.access$3502:(Lorg/apache/hadoop/hbase/regionserver/MetricsRegionServerWrapperImpl;J)J
    1463: pop2
    1464: aload_0
    1465: getfield      #1                  // Field this$0:Lorg/apache/hadoop/hbase/regionserver/MetricsRegionServerWrapperImpl;
    1468: lload         59
    1470: invokestatic  #119                // Method org/apache/hadoop/hbase/regionserver/MetricsRegionServerWrapperImpl.access$3602:(Lorg/apache/hadoop/hbase/regionserver/MetricsRegionServerWrapperImpl;J)J
    1473: pop2
    1474: aload_0
    1475: getfield      #1                  // Field this$0:Lorg/apache/hadoop/hbase/regionserver/MetricsRegionServerWrapperImpl;
    1478: lload         61
    1480: invokestatic  #120                // Method org/apache/hadoop/hbase/regionserver/MetricsRegionServerWrapperImpl.access$3702:(Lorg/apache/hadoop/hbase/regionserver/MetricsRegionServerWrapperImpl;J)J
    1483: pop2
    1484: aload_0
    1485: getfield      #1                  // Field this$0:Lorg/apache/hadoop/hbase/regionserver/MetricsRegionServerWrapperImpl;
    1488: lload         63
    1490: invokestatic  #121                // Method org/apache/hadoop/hbase/regionserver/MetricsRegionServerWrapperImpl.access$3802:(Lorg/apache/hadoop/hbase/regionserver/MetricsRegionServerWrapperImpl;J)J
    1493: pop2
    1494: aload_0
    1495: getfield      #1                  // Field this$0:Lorg/apache/hadoop/hbase/regionserver/MetricsRegionServerWrapperImpl;
    1498: lload         65
    1500: invokestatic  #122                // Method org/apache/hadoop/hbase/regionserver/MetricsRegionServerWrapperImpl.access$3902:(Lorg/apache/hadoop/hbase/regionserver/MetricsRegionServerWrapperImpl;J)J
    1503: pop2
    1504: aload_0
    1505: getfield      #1                  // Field this$0:Lorg/apache/hadoop/hbase/regionserver/MetricsRegionServerWrapperImpl;
    1508: lload         67
    1510: invokestatic  #123                // Method org/apache/hadoop/hbase/regionserver/MetricsRegionServerWrapperImpl.access$4002:(Lorg/apache/hadoop/hbase/regionserver/MetricsRegionServerWrapperImpl;J)J
    1513: pop2
    1514: aload_0
    1515: getfield      #1                  // Field this$0:Lorg/apache/hadoop/hbase/regionserver/MetricsRegionServerWrapperImpl;
    1518: lload         69
    1520: invokestatic  #124                // Method org/apache/hadoop/hbase/regionserver/MetricsRegionServerWrapperImpl.access$4102:(Lorg/apache/hadoop/hbase/regionserver/MetricsRegionServerWrapperImpl;J)J
    1523: pop2
    1524: aload_0
    1525: getfield      #1                  // Field this$0:Lorg/apache/hadoop/hbase/regionserver/MetricsRegionServerWrapperImpl;
    1528: lload         71
    1530: invokestatic  #125                // Method org/apache/hadoop/hbase/regionserver/MetricsRegionServerWrapperImpl.access$4202:(Lorg/apache/hadoop/hbase/regionserver/MetricsRegionServerWrapperImpl;J)J
    1533: pop2
    1534: aload_0
    1535: getfield      #1                  // Field this$0:Lorg/apache/hadoop/hbase/regionserver/MetricsRegionServerWrapperImpl;
    1538: lload         73
    1540: invokestatic  #126                // Method org/apache/hadoop/hbase/regionserver/MetricsRegionServerWrapperImpl.access$4302:(Lorg/apache/hadoop/hbase/regionserver/MetricsRegionServerWrapperImpl;J)J
    1543: pop2
    1544: aload_0
    1545: getfield      #1                  // Field this$0:Lorg/apache/hadoop/hbase/regionserver/MetricsRegionServerWrapperImpl;
    1548: lload         75
    1550: invokestatic  #127                // Method org/apache/hadoop/hbase/regionserver/MetricsRegionServerWrapperImpl.access$4402:(Lorg/apache/hadoop/hbase/regionserver/MetricsRegionServerWrapperImpl;J)J
    1553: pop2
    1554: aload_0
    1555: getfield      #1                  // Field this$0:Lorg/apache/hadoop/hbase/regionserver/MetricsRegionServerWrapperImpl;
    1558: aload_0
    1559: getfield      #1                  // Field this$0:Lorg/apache/hadoop/hbase/regionserver/MetricsRegionServerWrapperImpl;
    1562: invokestatic  #128                // Method org/apache/hadoop/hbase/regionserver/MetricsRegionServerWrapperImpl.access$4600:(Lorg/apache/hadoop/hbase/regionserver/MetricsRegionServerWrapperImpl;)Ljava/util/Optional;
    1565: invokedynamic #129,  0            // InvokeDynamic #0:apply:()Ljava/util/function/Function;
    1570: invokevirtual #130                // Method java/util/Optional.map:(Ljava/util/function/Function;)Ljava/util/Optional;
    1573: lconst_0
    1574: invokestatic  #131                // Method java/lang/Long.valueOf:(J)Ljava/lang/Long;
    1577: invokevirtual #132                // Method java/util/Optional.orElse:(Ljava/lang/Object;)Ljava/lang/Object;
    1580: checkcast     #10                 // class java/lang/Long
    1583: invokevirtual #133                // Method java/lang/Long.longValue:()J
    1586: invokestatic  #134                // Method org/apache/hadoop/hbase/regionserver/MetricsRegionServerWrapperImpl.access$4502:(Lorg/apache/hadoop/hbase/regionserver/MetricsRegionServerWrapperImpl;J)J
    1589: pop2
    1590: aload_0
    1591: getfield      #1                  // Field this$0:Lorg/apache/hadoop/hbase/regionserver/MetricsRegionServerWrapperImpl;
    1594: aload_0
    1595: getfield      #1                  // Field this$0:Lorg/apache/hadoop/hbase/regionserver/MetricsRegionServerWrapperImpl;
    1598: invokestatic  #128                // Method org/apache/hadoop/hbase/regionserver/MetricsRegionServerWrapperImpl.access$4600:(Lorg/apache/hadoop/hbase/regionserver/MetricsRegionServerWrapperImpl;)Ljava/util/Optional;
    1601: invokedynamic #135,  0            // InvokeDynamic #1:apply:()Ljava/util/function/Function;
    1606: invokevirtual #130                // Method java/util/Optional.map:(Ljava/util/function/Function;)Ljava/util/Optional;
    1609: lconst_0
    1610: invokestatic  #131                // Method java/lang/Long.valueOf:(J)Ljava/lang/Long;
    1613: invokevirtual #132                // Method java/util/Optional.orElse:(Ljava/lang/Object;)Ljava/lang/Object;
    1616: checkcast     #10                 // class java/lang/Long
    1619: invokevirtual #133                // Method java/lang/Long.longValue:()J
    1622: invokestatic  #136                // Method org/apache/hadoop/hbase/regionserver/MetricsRegionServerWrapperImpl.access$4702:(Lorg/apache/hadoop/hbase/regionserver/MetricsRegionServerWrapperImpl;J)J
    1625: pop2
    1626: aload_0
    1627: getfield      #1                  // Field this$0:Lorg/apache/hadoop/hbase/regionserver/MetricsRegionServerWrapperImpl;
    1630: aload_0
    1631: getfield      #1                  // Field this$0:Lorg/apache/hadoop/hbase/regionserver/MetricsRegionServerWrapperImpl;
    1634: invokestatic  #128                // Method org/apache/hadoop/hbase/regionserver/MetricsRegionServerWrapperImpl.access$4600:(Lorg/apache/hadoop/hbase/regionserver/MetricsRegionServerWrapperImpl;)Ljava/util/Optional;
    1637: invokedynamic #137,  0            // InvokeDynamic #2:apply:()Ljava/util/function/Function;
    1642: invokevirtual #130                // Method java/util/Optional.map:(Ljava/util/function/Function;)Ljava/util/Optional;
    1645: dconst_0
    1646: invokestatic  #138                // Method java/lang/Double.valueOf:(D)Ljava/lang/Double;
    1649: invokevirtual #132                // Method java/util/Optional.orElse:(Ljava/lang/Object;)Ljava/lang/Object;
    1652: checkcast     #139                // class java/lang/Double
    1655: invokevirtual #140                // Method java/lang/Double.doubleValue:()D
    1658: invokestatic  #141                // Method org/apache/hadoop/hbase/regionserver/MetricsRegionServerWrapperImpl.access$4802:(Lorg/apache/hadoop/hbase/regionserver/MetricsRegionServerWrapperImpl;D)D
    1661: pop2
    1662: aload_0
    1663: getfield      #1                  // Field this$0:Lorg/apache/hadoop/hbase/regionserver/MetricsRegionServerWrapperImpl;
    1666: invokestatic  #142                // Method org/apache/hadoop/hbase/regionserver/MetricsRegionServerWrapperImpl.access$4800:(Lorg/apache/hadoop/hbase/regionserver/MetricsRegionServerWrapperImpl;)D
    1669: invokestatic  #71                 // Method java/lang/Double.isNaN:(D)Z
    1672: ifeq          1684
    1675: aload_0
    1676: getfield      #1                  // Field this$0:Lorg/apache/hadoop/hbase/regionserver/MetricsRegionServerWrapperImpl;
    1679: dconst_0
    1680: invokestatic  #141                // Method org/apache/hadoop/hbase/regionserver/MetricsRegionServerWrapperImpl.access$4802:(Lorg/apache/hadoop/hbase/regionserver/MetricsRegionServerWrapperImpl;D)D
    1683: pop2
    1684: aload_0
    1685: getfield      #1                  // Field this$0:Lorg/apache/hadoop/hbase/regionserver/MetricsRegionServerWrapperImpl;
    1688: aload_0
    1689: getfield      #1                  // Field this$0:Lorg/apache/hadoop/hbase/regionserver/MetricsRegionServerWrapperImpl;
    1692: invokestatic  #128                // Method org/apache/hadoop/hbase/regionserver/MetricsRegionServerWrapperImpl.access$4600:(Lorg/apache/hadoop/hbase/regionserver/MetricsRegionServerWrapperImpl;)Ljava/util/Optional;
    1695: invokedynamic #143,  0            // InvokeDynamic #3:apply:()Ljava/util/function/Function;
    1700: invokevirtual #130                // Method java/util/Optional.map:(Ljava/util/function/Function;)Ljava/util/Optional;
    1703: lconst_0
    1704: invokestatic  #131                // Method java/lang/Long.valueOf:(J)Ljava/lang/Long;
    1707: invokevirtual #132                // Method java/util/Optional.orElse:(Ljava/lang/Object;)Ljava/lang/Object;
    1710: checkcast     #10                 // class java/lang/Long
    1713: invokevirtual #133                // Method java/lang/Long.longValue:()J
    1716: invokestatic  #144                // Method org/apache/hadoop/hbase/regionserver/MetricsRegionServerWrapperImpl.access$4902:(Lorg/apache/hadoop/hbase/regionserver/MetricsRegionServerWrapperImpl;J)J
    1719: pop2
    1720: aload_0
    1721: getfield      #1                  // Field this$0:Lorg/apache/hadoop/hbase/regionserver/MetricsRegionServerWrapperImpl;
    1724: aload_0
    1725: getfield      #1                  // Field this$0:Lorg/apache/hadoop/hbase/regionserver/MetricsRegionServerWrapperImpl;
    1728: invokestatic  #128                // Method org/apache/hadoop/hbase/regionserver/MetricsRegionServerWrapperImpl.access$4600:(Lorg/apache/hadoop/hbase/regionserver/MetricsRegionServerWrapperImpl;)Ljava/util/Optional;
    1731: invokedynamic #145,  0            // InvokeDynamic #4:apply:()Ljava/util/function/Function;
    1736: invokevirtual #130                // Method java/util/Optional.map:(Ljava/util/function/Function;)Ljava/util/Optional;
    1739: iconst_0
    1740: invokestatic  #146                // Method java/lang/Integer.valueOf:(I)Ljava/lang/Integer;
    1743: invokevirtual #132                // Method java/util/Optional.orElse:(Ljava/lang/Object;)Ljava/lang/Object;
    1746: checkcast     #147                // class java/lang/Integer
    1749: invokevirtual #148                // Method java/lang/Integer.intValue:()I
    1752: i2l
    1753: invokestatic  #149                // Method org/apache/hadoop/hbase/regionserver/MetricsRegionServerWrapperImpl.access$5002:(Lorg/apache/hadoop/hbase/regionserver/MetricsRegionServerWrapperImpl;J)J
    1756: pop2
    1757: aload_0
    1758: getfield      #1                  // Field this$0:Lorg/apache/hadoop/hbase/regionserver/MetricsRegionServerWrapperImpl;
    1761: lload         77
    1763: invokestatic  #150                // Method org/apache/hadoop/hbase/regionserver/MetricsRegionServerWrapperImpl.access$5102:(Lorg/apache/hadoop/hbase/regionserver/MetricsRegionServerWrapperImpl;J)J
    1766: pop2
    1767: goto          1782
    1770: astore_1
    1771: invokestatic  #152                // Method org/apache/hadoop/hbase/regionserver/MetricsRegionServerWrapperImpl.access$5200:()Lorg/slf4j/Logger;
    1774: ldc           #153                // String Caught exception! Will suppress and retry.
    1776: aload_1
    1777: invokeinterface #154,  3          // InterfaceMethod org/slf4j/Logger.warn:(Ljava/lang/String;Ljava/lang/Throwable;)V
    1782: return
    Exception table:
       from    to  target type
           0  1767  1770   Class java/lang/Throwable
}
