Compiled from "MetricsTableAggregateSourceImpl.java"
public class org.apache.hadoop.hbase.regionserver.MetricsTableAggregateSourceImpl extends org.apache.hadoop.hbase.metrics.BaseSourceImpl implements org.apache.hadoop.hbase.regionserver.MetricsTableAggregateSource {
  public org.apache.hadoop.hbase.regionserver.MetricsTableAggregateSourceImpl();
    Code:
       0: aload_0
       1: ldc           #2                  // String Tables
       3: ldc           #3                  // String Metrics about HBase RegionServer tables
       5: ldc           #4                  // String regionserver
       7: ldc           #5                  // String RegionServer,sub=Tables
       9: invokespecial #6                  // Method "<init>":(Ljava/lang/String;Ljava/lang/String;Ljava/lang/String;Ljava/lang/String;)V
      12: return

  public org.apache.hadoop.hbase.regionserver.MetricsTableAggregateSourceImpl(java.lang.String, java.lang.String, java.lang.String, java.lang.String);
    Code:
       0: aload_0
       1: aload_1
       2: aload_2
       3: aload_3
       4: aload         4
       6: invokespecial #7                  // Method org/apache/hadoop/hbase/metrics/BaseSourceImpl."<init>":(Ljava/lang/String;Ljava/lang/String;Ljava/lang/String;Ljava/lang/String;)V
       9: aload_0
      10: new           #8                  // class java/util/concurrent/ConcurrentHashMap
      13: dup
      14: invokespecial #9                  // Method java/util/concurrent/ConcurrentHashMap."<init>":()V
      17: putfield      #10                 // Field tableSources:Ljava/util/concurrent/ConcurrentHashMap;
      20: return

  public void deleteTableSource(java.lang.String);
    Code:
       0: aload_0
       1: getfield      #10                 // Field tableSources:Ljava/util/concurrent/ConcurrentHashMap;
       4: aload_1
       5: invokevirtual #12                 // Method java/util/concurrent/ConcurrentHashMap.remove:(Ljava/lang/Object;)Ljava/lang/Object;
       8: checkcast     #13                 // class org/apache/hadoop/hbase/regionserver/MetricsTableSource
      11: astore_2
      12: aload_2
      13: ifnull        22
      16: aload_2
      17: invokeinterface #14,  1           // InterfaceMethod org/apache/hadoop/hbase/regionserver/MetricsTableSource.close:()V
      22: goto          69
      25: astore_2
      26: getstatic     #16                 // Field LOG:Lorg/slf4j/Logger;
      29: new           #17                 // class java/lang/StringBuilder
      32: dup
      33: invokespecial #18                 // Method java/lang/StringBuilder."<init>":()V
      36: ldc           #19                 // String Error trying to remove
      38: invokevirtual #20                 // Method java/lang/StringBuilder.append:(Ljava/lang/String;)Ljava/lang/StringBuilder;
      41: aload_1
      42: invokevirtual #20                 // Method java/lang/StringBuilder.append:(Ljava/lang/String;)Ljava/lang/StringBuilder;
      45: ldc           #21                 // String  from
      47: invokevirtual #20                 // Method java/lang/StringBuilder.append:(Ljava/lang/String;)Ljava/lang/StringBuilder;
      50: aload_0
      51: invokevirtual #22                 // Method java/lang/Object.getClass:()Ljava/lang/Class;
      54: invokevirtual #23                 // Method java/lang/Class.getSimpleName:()Ljava/lang/String;
      57: invokevirtual #20                 // Method java/lang/StringBuilder.append:(Ljava/lang/String;)Ljava/lang/StringBuilder;
      60: invokevirtual #24                 // Method java/lang/StringBuilder.toString:()Ljava/lang/String;
      63: aload_2
      64: invokeinterface #25,  3           // InterfaceMethod org/slf4j/Logger.info:(Ljava/lang/String;Ljava/lang/Throwable;)V
      69: return
    Exception table:
       from    to  target type
           0    22    25   Class java/lang/Exception

  public org.apache.hadoop.hbase.regionserver.MetricsTableSource getOrCreateTableSource(java.lang.String, org.apache.hadoop.hbase.regionserver.MetricsTableWrapperAggregate);
    Code:
       0: aload_0
       1: getfield      #10                 // Field tableSources:Ljava/util/concurrent/ConcurrentHashMap;
       4: aload_1
       5: invokevirtual #26                 // Method java/util/concurrent/ConcurrentHashMap.get:(Ljava/lang/Object;)Ljava/lang/Object;
       8: checkcast     #13                 // class org/apache/hadoop/hbase/regionserver/MetricsTableSource
      11: astore_3
      12: aload_3
      13: ifnull        18
      16: aload_3
      17: areturn
      18: ldc           #27                 // class org/apache/hadoop/hbase/regionserver/MetricsRegionServerSourceFactory
      20: invokestatic  #28                 // Method org/apache/hadoop/hbase/CompatibilitySingletonFactory.getInstance:(Ljava/lang/Class;)Ljava/lang/Object;
      23: checkcast     #27                 // class org/apache/hadoop/hbase/regionserver/MetricsRegionServerSourceFactory
      26: aload_1
      27: aload_2
      28: invokeinterface #29,  3           // InterfaceMethod org/apache/hadoop/hbase/regionserver/MetricsRegionServerSourceFactory.createTable:(Ljava/lang/String;Lorg/apache/hadoop/hbase/regionserver/MetricsTableWrapperAggregate;)Lorg/apache/hadoop/hbase/regionserver/MetricsTableSource;
      33: astore        4
      35: aload_0
      36: getfield      #10                 // Field tableSources:Ljava/util/concurrent/ConcurrentHashMap;
      39: aload_1
      40: aload         4
      42: invokedynamic #30,  0             // InvokeDynamic #0:apply:(Lorg/apache/hadoop/hbase/regionserver/MetricsTableSource;)Ljava/util/function/Function;
      47: invokevirtual #31                 // Method java/util/concurrent/ConcurrentHashMap.computeIfAbsent:(Ljava/lang/Object;Ljava/util/function/Function;)Ljava/lang/Object;
      50: checkcast     #13                 // class org/apache/hadoop/hbase/regionserver/MetricsTableSource
      53: areturn

  public void getMetrics(org.apache.hadoop.metrics2.MetricsCollector, boolean);
    Code:
       0: aload_1
       1: aload_0
       2: getfield      #32                 // Field metricsName:Ljava/lang/String;
       5: invokeinterface #33,  2           // InterfaceMethod org/apache/hadoop/metrics2/MetricsCollector.addRecord:(Ljava/lang/String;)Lorg/apache/hadoop/metrics2/MetricsRecordBuilder;
      10: astore_3
      11: aload_0
      12: getfield      #10                 // Field tableSources:Ljava/util/concurrent/ConcurrentHashMap;
      15: ifnull        103
      18: aload_0
      19: getfield      #10                 // Field tableSources:Ljava/util/concurrent/ConcurrentHashMap;
      22: invokevirtual #34                 // Method java/util/concurrent/ConcurrentHashMap.values:()Ljava/util/Collection;
      25: invokeinterface #35,  1           // InterfaceMethod java/util/Collection.iterator:()Ljava/util/Iterator;
      30: astore        4
      32: aload         4
      34: invokeinterface #36,  1           // InterfaceMethod java/util/Iterator.hasNext:()Z
      39: ifeq          75
      42: aload         4
      44: invokeinterface #37,  1           // InterfaceMethod java/util/Iterator.next:()Ljava/lang/Object;
      49: checkcast     #13                 // class org/apache/hadoop/hbase/regionserver/MetricsTableSource
      52: astore        5
      54: aload         5
      56: instanceof    #38                 // class org/apache/hadoop/hbase/regionserver/MetricsTableSourceImpl
      59: ifeq          72
      62: aload         5
      64: checkcast     #38                 // class org/apache/hadoop/hbase/regionserver/MetricsTableSourceImpl
      67: aload_3
      68: iload_2
      69: invokevirtual #39                 // Method org/apache/hadoop/hbase/regionserver/MetricsTableSourceImpl.snapshot:(Lorg/apache/hadoop/metrics2/MetricsRecordBuilder;Z)V
      72: goto          32
      75: aload_3
      76: ldc           #40                 // String numTables
      78: ldc           #41                 // String Number of tables in the metrics system
      80: invokestatic  #42                 // Method org/apache/hadoop/hbase/metrics/Interns.info:(Ljava/lang/String;Ljava/lang/String;)Lorg/apache/hadoop/metrics2/MetricsInfo;
      83: aload_0
      84: getfield      #10                 // Field tableSources:Ljava/util/concurrent/ConcurrentHashMap;
      87: invokevirtual #43                 // Method java/util/concurrent/ConcurrentHashMap.size:()I
      90: invokevirtual #44                 // Method org/apache/hadoop/metrics2/MetricsRecordBuilder.addGauge:(Lorg/apache/hadoop/metrics2/MetricsInfo;I)Lorg/apache/hadoop/metrics2/MetricsRecordBuilder;
      93: pop
      94: aload_0
      95: getfield      #45                 // Field metricsRegistry:Lorg/apache/hadoop/metrics2/lib/DynamicMetricsRegistry;
      98: aload_3
      99: iload_2
     100: invokevirtual #46                 // Method org/apache/hadoop/metrics2/lib/DynamicMetricsRegistry.snapshot:(Lorg/apache/hadoop/metrics2/MetricsRecordBuilder;Z)V
     103: return

  static {};
    Code:
       0: ldc           #47                 // class org/apache/hadoop/hbase/regionserver/MetricsTableAggregateSourceImpl
       2: invokestatic  #48                 // Method org/slf4j/LoggerFactory.getLogger:(Ljava/lang/Class;)Lorg/slf4j/Logger;
       5: putstatic     #16                 // Field LOG:Lorg/slf4j/Logger;
       8: return
}
