Compiled from "MetricsRegion.java"
public class org.apache.hadoop.hbase.regionserver.MetricsRegion {
  public org.apache.hadoop.hbase.regionserver.MetricsRegion(org.apache.hadoop.hbase.regionserver.MetricsRegionWrapper);
    Code:
       0: aload_0
       1: invokespecial #1                  // Method java/lang/Object."<init>":()V
       4: aload_0
       5: ldc           #2                  // class org/apache/hadoop/hbase/regionserver/MetricsRegionServerSourceFactory
       7: invokestatic  #3                  // Method org/apache/hadoop/hbase/CompatibilitySingletonFactory.getInstance:(Ljava/lang/Class;)Ljava/lang/Object;
      10: checkcast     #2                  // class org/apache/hadoop/hbase/regionserver/MetricsRegionServerSourceFactory
      13: aload_1
      14: invokeinterface #4,  2            // InterfaceMethod org/apache/hadoop/hbase/regionserver/MetricsRegionServerSourceFactory.createRegion:(Lorg/apache/hadoop/hbase/regionserver/MetricsRegionWrapper;)Lorg/apache/hadoop/hbase/regionserver/MetricsRegionSource;
      19: putfield      #5                  // Field source:Lorg/apache/hadoop/hbase/regionserver/MetricsRegionSource;
      22: aload_0
      23: aload_1
      24: putfield      #6                  // Field regionWrapper:Lorg/apache/hadoop/hbase/regionserver/MetricsRegionWrapper;
      27: return

  public void close();
    Code:
       0: aload_0
       1: getfield      #5                  // Field source:Lorg/apache/hadoop/hbase/regionserver/MetricsRegionSource;
       4: invokeinterface #7,  1            // InterfaceMethod org/apache/hadoop/hbase/regionserver/MetricsRegionSource.close:()V
       9: return

  public void updatePut();
    Code:
       0: aload_0
       1: getfield      #5                  // Field source:Lorg/apache/hadoop/hbase/regionserver/MetricsRegionSource;
       4: invokeinterface #8,  1            // InterfaceMethod org/apache/hadoop/hbase/regionserver/MetricsRegionSource.updatePut:()V
       9: return

  public void updateDelete();
    Code:
       0: aload_0
       1: getfield      #5                  // Field source:Lorg/apache/hadoop/hbase/regionserver/MetricsRegionSource;
       4: invokeinterface #9,  1            // InterfaceMethod org/apache/hadoop/hbase/regionserver/MetricsRegionSource.updateDelete:()V
       9: return

  public void updateGet(long);
    Code:
       0: aload_0
       1: getfield      #5                  // Field source:Lorg/apache/hadoop/hbase/regionserver/MetricsRegionSource;
       4: lload_1
       5: invokeinterface #10,  3           // InterfaceMethod org/apache/hadoop/hbase/regionserver/MetricsRegionSource.updateGet:(J)V
      10: return

  public void updateScanTime(long);
    Code:
       0: aload_0
       1: getfield      #5                  // Field source:Lorg/apache/hadoop/hbase/regionserver/MetricsRegionSource;
       4: lload_1
       5: invokeinterface #11,  3           // InterfaceMethod org/apache/hadoop/hbase/regionserver/MetricsRegionSource.updateScanTime:(J)V
      10: return

  public void updateAppend();
    Code:
       0: aload_0
       1: getfield      #5                  // Field source:Lorg/apache/hadoop/hbase/regionserver/MetricsRegionSource;
       4: invokeinterface #12,  1           // InterfaceMethod org/apache/hadoop/hbase/regionserver/MetricsRegionSource.updateAppend:()V
       9: return

  public void updateIncrement();
    Code:
       0: aload_0
       1: getfield      #5                  // Field source:Lorg/apache/hadoop/hbase/regionserver/MetricsRegionSource;
       4: invokeinterface #13,  1           // InterfaceMethod org/apache/hadoop/hbase/regionserver/MetricsRegionSource.updateIncrement:()V
       9: return

  org.apache.hadoop.hbase.regionserver.MetricsRegionSource getSource();
    Code:
       0: aload_0
       1: getfield      #5                  // Field source:Lorg/apache/hadoop/hbase/regionserver/MetricsRegionSource;
       4: areturn

  public org.apache.hadoop.hbase.regionserver.MetricsRegionWrapper getRegionWrapper();
    Code:
       0: aload_0
       1: getfield      #6                  // Field regionWrapper:Lorg/apache/hadoop/hbase/regionserver/MetricsRegionWrapper;
       4: areturn
}
