Compiled from "MetricsMasterProcSourceFactoryImpl.java"
public class org.apache.hadoop.hbase.master.MetricsMasterProcSourceFactoryImpl implements org.apache.hadoop.hbase.master.MetricsMasterProcSourceFactory {
  public org.apache.hadoop.hbase.master.MetricsMasterProcSourceFactoryImpl();
    Code:
       0: aload_0
       1: invokespecial #1                  // Method java/lang/Object."<init>":()V
       4: return

  public synchronized org.apache.hadoop.hbase.master.MetricsMasterProcSource create(org.apache.hadoop.hbase.master.MetricsMasterWrapper);
    Code:
       0: aload_0
       1: getfield      #2                  // Field masterProcSource:Lorg/apache/hadoop/hbase/master/MetricsMasterProcSource;
       4: ifnonnull     19
       7: aload_0
       8: new           #3                  // class org/apache/hadoop/hbase/master/MetricsMasterProcSourceImpl
      11: dup
      12: aload_1
      13: invokespecial #4                  // Method org/apache/hadoop/hbase/master/MetricsMasterProcSourceImpl."<init>":(Lorg/apache/hadoop/hbase/master/MetricsMasterWrapper;)V
      16: putfield      #2                  // Field masterProcSource:Lorg/apache/hadoop/hbase/master/MetricsMasterProcSource;
      19: aload_0
      20: getfield      #2                  // Field masterProcSource:Lorg/apache/hadoop/hbase/master/MetricsMasterProcSource;
      23: areturn
}
