Compiled from "MetricsRegionAggregateSourceImpl.java"
class org.apache.hadoop.hbase.regionserver.MetricsRegionAggregateSourceImpl$1 implements java.lang.Runnable {
  final org.apache.hadoop.hbase.regionserver.MetricsRegionAggregateSourceImpl this$0;

  org.apache.hadoop.hbase.regionserver.MetricsRegionAggregateSourceImpl$1(org.apache.hadoop.hbase.regionserver.MetricsRegionAggregateSourceImpl);
    Code:
       0: aload_0
       1: aload_1
       2: putfield      #1                  // Field this$0:Lorg/apache/hadoop/hbase/regionserver/MetricsRegionAggregateSourceImpl;
       5: aload_0
       6: invokespecial #2                  // Method java/lang/Object."<init>":()V
       9: return

  public void run();
    Code:
       0: invokestatic  #3                  // Method org/apache/hadoop/metrics2/impl/JmxCacheBuster.clearJmxCache:()V
       3: return
}
