Compiled from "MobFile.java"
public class org.apache.hadoop.hbase.mob.MobFile {
  protected org.apache.hadoop.hbase.mob.MobFile();
    Code:
       0: aload_0
       1: invokespecial #1                  // Method java/lang/Object."<init>":()V
       4: return

  protected org.apache.hadoop.hbase.mob.MobFile(org.apache.hadoop.hbase.regionserver.HStoreFile);
    Code:
       0: aload_0
       1: invokespecial #1                  // Method java/lang/Object."<init>":()V
       4: aload_0
       5: aload_1
       6: putfield      #2                  // Field sf:Lorg/apache/hadoop/hbase/regionserver/HStoreFile;
       9: return

  public org.apache.hadoop.hbase.regionserver.StoreFileScanner getScanner() throws java.io.IOException;
    Code:
       0: new           #3                  // class java/util/ArrayList
       3: dup
       4: invokespecial #4                  // Method java/util/ArrayList."<init>":()V
       7: astore_1
       8: aload_1
       9: aload_0
      10: getfield      #2                  // Field sf:Lorg/apache/hadoop/hbase/regionserver/HStoreFile;
      13: invokeinterface #5,  2            // InterfaceMethod java/util/List.add:(Ljava/lang/Object;)Z
      18: pop
      19: aload_1
      20: iconst_0
      21: iconst_1
      22: iconst_0
      23: iconst_0
      24: aload_0
      25: getfield      #2                  // Field sf:Lorg/apache/hadoop/hbase/regionserver/HStoreFile;
      28: invokevirtual #6                  // Method org/apache/hadoop/hbase/regionserver/HStoreFile.getMaxMemStoreTS:()J
      31: invokestatic  #7                  // Method org/apache/hadoop/hbase/regionserver/StoreFileScanner.getScannersForStoreFiles:(Ljava/util/Collection;ZZZZJ)Ljava/util/List;
      34: astore_2
      35: aload_2
      36: iconst_0
      37: invokeinterface #8,  2            // InterfaceMethod java/util/List.get:(I)Ljava/lang/Object;
      42: checkcast     #9                  // class org/apache/hadoop/hbase/regionserver/StoreFileScanner
      45: areturn

  public org.apache.hadoop.hbase.Cell readCell(org.apache.hadoop.hbase.Cell, boolean) throws java.io.IOException;
    Code:
       0: aload_0
       1: aload_1
       2: iload_2
       3: aload_0
       4: getfield      #2                  // Field sf:Lorg/apache/hadoop/hbase/regionserver/HStoreFile;
       7: invokevirtual #6                  // Method org/apache/hadoop/hbase/regionserver/HStoreFile.getMaxMemStoreTS:()J
      10: invokevirtual #10                 // Method readCell:(Lorg/apache/hadoop/hbase/Cell;ZJ)Lorg/apache/hadoop/hbase/Cell;
      13: areturn

  public org.apache.hadoop.hbase.Cell readCell(org.apache.hadoop.hbase.Cell, boolean, long) throws java.io.IOException;
    Code:
       0: aconst_null
       1: astore        5
       3: aconst_null
       4: astore        6
       6: new           #3                  // class java/util/ArrayList
       9: dup
      10: invokespecial #4                  // Method java/util/ArrayList."<init>":()V
      13: astore        7
      15: aload         7
      17: aload_0
      18: getfield      #2                  // Field sf:Lorg/apache/hadoop/hbase/regionserver/HStoreFile;
      21: invokeinterface #5,  2            // InterfaceMethod java/util/List.add:(Ljava/lang/Object;)Z
      26: pop
      27: aload         7
      29: iload_2
      30: iconst_1
      31: iconst_0
      32: iconst_0
      33: lload_3
      34: invokestatic  #7                  // Method org/apache/hadoop/hbase/regionserver/StoreFileScanner.getScannersForStoreFiles:(Ljava/util/Collection;ZZZZJ)Ljava/util/List;
      37: astore        8
      39: aload         8
      41: invokeinterface #11,  1           // InterfaceMethod java/util/List.isEmpty:()Z
      46: ifne          78
      49: aload         8
      51: iconst_0
      52: invokeinterface #8,  2            // InterfaceMethod java/util/List.get:(I)Ljava/lang/Object;
      57: checkcast     #9                  // class org/apache/hadoop/hbase/regionserver/StoreFileScanner
      60: astore        6
      62: aload         6
      64: aload_1
      65: invokevirtual #12                 // Method org/apache/hadoop/hbase/regionserver/StoreFileScanner.seek:(Lorg/apache/hadoop/hbase/Cell;)Z
      68: ifeq          78
      71: aload         6
      73: invokevirtual #13                 // Method org/apache/hadoop/hbase/regionserver/StoreFileScanner.peek:()Lorg/apache/hadoop/hbase/Cell;
      76: astore        5
      78: aload         6
      80: ifnull        106
      83: aload         6
      85: invokevirtual #14                 // Method org/apache/hadoop/hbase/regionserver/StoreFileScanner.close:()V
      88: goto          106
      91: astore        9
      93: aload         6
      95: ifnull        103
      98: aload         6
     100: invokevirtual #14                 // Method org/apache/hadoop/hbase/regionserver/StoreFileScanner.close:()V
     103: aload         9
     105: athrow
     106: aload         5
     108: areturn
    Exception table:
       from    to  target type
          27    78    91   any
          91    93    91   any

  public java.lang.String getFileName();
    Code:
       0: aload_0
       1: getfield      #2                  // Field sf:Lorg/apache/hadoop/hbase/regionserver/HStoreFile;
       4: invokevirtual #15                 // Method org/apache/hadoop/hbase/regionserver/HStoreFile.getPath:()Lorg/apache/hadoop/fs/Path;
       7: invokevirtual #16                 // Method org/apache/hadoop/fs/Path.getName:()Ljava/lang/String;
      10: areturn

  public void open() throws java.io.IOException;
    Code:
       0: aload_0
       1: getfield      #2                  // Field sf:Lorg/apache/hadoop/hbase/regionserver/HStoreFile;
       4: invokevirtual #17                 // Method org/apache/hadoop/hbase/regionserver/HStoreFile.initReader:()V
       7: return

  public void close() throws java.io.IOException;
    Code:
       0: aload_0
       1: getfield      #2                  // Field sf:Lorg/apache/hadoop/hbase/regionserver/HStoreFile;
       4: ifnull        20
       7: aload_0
       8: getfield      #2                  // Field sf:Lorg/apache/hadoop/hbase/regionserver/HStoreFile;
      11: iconst_0
      12: invokevirtual #18                 // Method org/apache/hadoop/hbase/regionserver/HStoreFile.closeStoreFile:(Z)V
      15: aload_0
      16: aconst_null
      17: putfield      #2                  // Field sf:Lorg/apache/hadoop/hbase/regionserver/HStoreFile;
      20: return

  public static org.apache.hadoop.hbase.mob.MobFile create(org.apache.hadoop.fs.FileSystem, org.apache.hadoop.fs.Path, org.apache.hadoop.conf.Configuration, org.apache.hadoop.hbase.io.hfile.CacheConfig) throws java.io.IOException;
    Code:
       0: new           #19                 // class org/apache/hadoop/hbase/regionserver/HStoreFile
       3: dup
       4: aload_0
       5: aload_1
       6: aload_2
       7: aload_3
       8: getstatic     #20                 // Field org/apache/hadoop/hbase/regionserver/BloomType.NONE:Lorg/apache/hadoop/hbase/regionserver/BloomType;
      11: iconst_1
      12: invokespecial #21                 // Method org/apache/hadoop/hbase/regionserver/HStoreFile."<init>":(Lorg/apache/hadoop/fs/FileSystem;Lorg/apache/hadoop/fs/Path;Lorg/apache/hadoop/conf/Configuration;Lorg/apache/hadoop/hbase/io/hfile/CacheConfig;Lorg/apache/hadoop/hbase/regionserver/BloomType;Z)V
      15: astore        4
      17: new           #22                 // class org/apache/hadoop/hbase/mob/MobFile
      20: dup
      21: aload         4
      23: invokespecial #23                 // Method "<init>":(Lorg/apache/hadoop/hbase/regionserver/HStoreFile;)V
      26: areturn
}
