Compiled from "MockServer.java"
public class org.apache.hadoop.hbase.util.MockServer implements org.apache.hadoop.hbase.Server {
  static final org.apache.hadoop.hbase.ServerName NAME;

  boolean stopped;

  boolean aborted;

  final org.apache.hadoop.hbase.zookeeper.ZKWatcher zk;

  final org.apache.hadoop.hbase.HBaseTestingUtility htu;

  public org.apache.hadoop.hbase.util.MockServer() throws org.apache.hadoop.hbase.ZooKeeperConnectionException, java.io.IOException;
    Code:
       0: aload_0
       1: aconst_null
       2: invokespecial #1                  // Method "<init>":(Lorg/apache/hadoop/hbase/HBaseTestingUtility;)V
       5: return

  public org.apache.hadoop.hbase.util.MockServer(org.apache.hadoop.hbase.HBaseTestingUtility) throws org.apache.hadoop.hbase.ZooKeeperConnectionException, java.io.IOException;
    Code:
       0: aload_0
       1: aload_1
       2: iconst_1
       3: invokespecial #2                  // Method "<init>":(Lorg/apache/hadoop/hbase/HBaseTestingUtility;Z)V
       6: return

  public org.apache.hadoop.hbase.util.MockServer(org.apache.hadoop.hbase.HBaseTestingUtility, boolean) throws org.apache.hadoop.hbase.ZooKeeperConnectionException, java.io.IOException;
    Code:
       0: aload_0
       1: invokespecial #3                  // Method java/lang/Object."<init>":()V
       4: aload_0
       5: aload_1
       6: putfield      #4                  // Field htu:Lorg/apache/hadoop/hbase/HBaseTestingUtility;
       9: aload_0
      10: iload_2
      11: ifeq          36
      14: new           #5                  // class org/apache/hadoop/hbase/zookeeper/ZKWatcher
      17: dup
      18: aload_1
      19: invokevirtual #6                  // Method org/apache/hadoop/hbase/HBaseTestingUtility.getConfiguration:()Lorg/apache/hadoop/conf/Configuration;
      22: getstatic     #7                  // Field NAME:Lorg/apache/hadoop/hbase/ServerName;
      25: invokevirtual #8                  // Method org/apache/hadoop/hbase/ServerName.toString:()Ljava/lang/String;
      28: aload_0
      29: iconst_1
      30: invokespecial #9                  // Method org/apache/hadoop/hbase/zookeeper/ZKWatcher."<init>":(Lorg/apache/hadoop/conf/Configuration;Ljava/lang/String;Lorg/apache/hadoop/hbase/Abortable;Z)V
      33: goto          37
      36: aconst_null
      37: putfield      #10                 // Field zk:Lorg/apache/hadoop/hbase/zookeeper/ZKWatcher;
      40: return

  public void abort(java.lang.String, java.lang.Throwable);
    Code:
       0: getstatic     #11                 // Field LOG:Lorg/slf4j/Logger;
       3: getstatic     #12                 // Field org/apache/hadoop/hbase/log/HBaseMarkers.FATAL:Lorg/slf4j/Marker;
       6: new           #13                 // class java/lang/StringBuilder
       9: dup
      10: invokespecial #14                 // Method java/lang/StringBuilder."<init>":()V
      13: ldc           #15                 // String Abort why=
      15: invokevirtual #16                 // Method java/lang/StringBuilder.append:(Ljava/lang/String;)Ljava/lang/StringBuilder;
      18: aload_1
      19: invokevirtual #16                 // Method java/lang/StringBuilder.append:(Ljava/lang/String;)Ljava/lang/StringBuilder;
      22: invokevirtual #17                 // Method java/lang/StringBuilder.toString:()Ljava/lang/String;
      25: aload_2
      26: invokeinterface #18,  4           // InterfaceMethod org/slf4j/Logger.error:(Lorg/slf4j/Marker;Ljava/lang/String;Ljava/lang/Throwable;)V
      31: aload_0
      32: aload_1
      33: invokevirtual #19                 // Method stop:(Ljava/lang/String;)V
      36: aload_0
      37: iconst_1
      38: putfield      #20                 // Field aborted:Z
      41: return

  public void stop(java.lang.String);
    Code:
       0: getstatic     #11                 // Field LOG:Lorg/slf4j/Logger;
       3: new           #13                 // class java/lang/StringBuilder
       6: dup
       7: invokespecial #14                 // Method java/lang/StringBuilder."<init>":()V
      10: ldc           #21                 // String Stop why=
      12: invokevirtual #16                 // Method java/lang/StringBuilder.append:(Ljava/lang/String;)Ljava/lang/StringBuilder;
      15: aload_1
      16: invokevirtual #16                 // Method java/lang/StringBuilder.append:(Ljava/lang/String;)Ljava/lang/StringBuilder;
      19: invokevirtual #17                 // Method java/lang/StringBuilder.toString:()Ljava/lang/String;
      22: invokeinterface #22,  2           // InterfaceMethod org/slf4j/Logger.debug:(Ljava/lang/String;)V
      27: aload_0
      28: iconst_1
      29: putfield      #23                 // Field stopped:Z
      32: return

  public boolean isStopped();
    Code:
       0: aload_0
       1: getfield      #23                 // Field stopped:Z
       4: ireturn

  public org.apache.hadoop.conf.Configuration getConfiguration();
    Code:
       0: aload_0
       1: getfield      #4                  // Field htu:Lorg/apache/hadoop/hbase/HBaseTestingUtility;
       4: invokevirtual #6                  // Method org/apache/hadoop/hbase/HBaseTestingUtility.getConfiguration:()Lorg/apache/hadoop/conf/Configuration;
       7: areturn

  public org.apache.hadoop.hbase.zookeeper.ZKWatcher getZooKeeper();
    Code:
       0: aload_0
       1: getfield      #10                 // Field zk:Lorg/apache/hadoop/hbase/zookeeper/ZKWatcher;
       4: areturn

  public org.apache.hadoop.hbase.CoordinatedStateManager getCoordinatedStateManager();
    Code:
       0: aconst_null
       1: areturn

  public org.apache.hadoop.hbase.client.ClusterConnection getConnection();
    Code:
       0: aconst_null
       1: areturn

  public org.apache.hadoop.hbase.ServerName getServerName();
    Code:
       0: getstatic     #7                  // Field NAME:Lorg/apache/hadoop/hbase/ServerName;
       3: areturn

  public boolean isAborted();
    Code:
       0: aload_0
       1: getfield      #20                 // Field aborted:Z
       4: ireturn

  public org.apache.hadoop.hbase.ChoreService getChoreService();
    Code:
       0: aconst_null
       1: areturn

  public org.apache.hadoop.hbase.client.ClusterConnection getClusterConnection();
    Code:
       0: aconst_null
       1: areturn

  public org.apache.hadoop.fs.FileSystem getFileSystem();
    Code:
       0: aconst_null
       1: areturn

  public boolean isStopping();
    Code:
       0: iconst_0
       1: ireturn

  public org.apache.hadoop.hbase.client.Connection createConnection(org.apache.hadoop.conf.Configuration) throws java.io.IOException;
    Code:
       0: aconst_null
       1: areturn

  public org.apache.hadoop.hbase.client.Connection getConnection();
    Code:
       0: aload_0
       1: invokevirtual #24                 // Method getConnection:()Lorg/apache/hadoop/hbase/client/ClusterConnection;
       4: areturn

  static {};
    Code:
       0: ldc           #25                 // class org/apache/hadoop/hbase/util/MockServer
       2: invokestatic  #26                 // Method org/slf4j/LoggerFactory.getLogger:(Ljava/lang/Class;)Lorg/slf4j/Logger;
       5: putstatic     #11                 // Field LOG:Lorg/slf4j/Logger;
       8: ldc           #27                 // String MockServer
      10: bipush        123
      12: ldc2_w        #28                 // long -1l
      15: invokestatic  #30                 // Method org/apache/hadoop/hbase/ServerName.valueOf:(Ljava/lang/String;IJ)Lorg/apache/hadoop/hbase/ServerName;
      18: putstatic     #7                  // Field NAME:Lorg/apache/hadoop/hbase/ServerName;
      21: return
}
