Compiled from "ModifyRegionUtils.java"
final class org.apache.hadoop.hbase.util.ModifyRegionUtils$1 implements java.util.concurrent.Callable<org.apache.hadoop.hbase.client.RegionInfo> {
  final org.apache.hadoop.conf.Configuration val$conf;

  final org.apache.hadoop.fs.Path val$rootDir;

  final org.apache.hadoop.hbase.client.TableDescriptor val$tableDescriptor;

  final org.apache.hadoop.hbase.client.RegionInfo val$newRegion;

  final org.apache.hadoop.hbase.util.ModifyRegionUtils$RegionFillTask val$task;

  org.apache.hadoop.hbase.util.ModifyRegionUtils$1(org.apache.hadoop.conf.Configuration, org.apache.hadoop.fs.Path, org.apache.hadoop.hbase.client.TableDescriptor, org.apache.hadoop.hbase.client.RegionInfo, org.apache.hadoop.hbase.util.ModifyRegionUtils$RegionFillTask);
    Code:
       0: aload_0
       1: aload_1
       2: putfield      #1                  // Field val$conf:Lorg/apache/hadoop/conf/Configuration;
       5: aload_0
       6: aload_2
       7: putfield      #2                  // Field val$rootDir:Lorg/apache/hadoop/fs/Path;
      10: aload_0
      11: aload_3
      12: putfield      #3                  // Field val$tableDescriptor:Lorg/apache/hadoop/hbase/client/TableDescriptor;
      15: aload_0
      16: aload         4
      18: putfield      #4                  // Field val$newRegion:Lorg/apache/hadoop/hbase/client/RegionInfo;
      21: aload_0
      22: aload         5
      24: putfield      #5                  // Field val$task:Lorg/apache/hadoop/hbase/util/ModifyRegionUtils$RegionFillTask;
      27: aload_0
      28: invokespecial #6                  // Method java/lang/Object."<init>":()V
      31: return

  public org.apache.hadoop.hbase.client.RegionInfo call() throws java.io.IOException;
    Code:
       0: aload_0
       1: getfield      #1                  // Field val$conf:Lorg/apache/hadoop/conf/Configuration;
       4: aload_0
       5: getfield      #2                  // Field val$rootDir:Lorg/apache/hadoop/fs/Path;
       8: aload_0
       9: getfield      #3                  // Field val$tableDescriptor:Lorg/apache/hadoop/hbase/client/TableDescriptor;
      12: aload_0
      13: getfield      #4                  // Field val$newRegion:Lorg/apache/hadoop/hbase/client/RegionInfo;
      16: aload_0
      17: getfield      #5                  // Field val$task:Lorg/apache/hadoop/hbase/util/ModifyRegionUtils$RegionFillTask;
      20: invokestatic  #7                  // Method org/apache/hadoop/hbase/util/ModifyRegionUtils.createRegion:(Lorg/apache/hadoop/conf/Configuration;Lorg/apache/hadoop/fs/Path;Lorg/apache/hadoop/hbase/client/TableDescriptor;Lorg/apache/hadoop/hbase/client/RegionInfo;Lorg/apache/hadoop/hbase/util/ModifyRegionUtils$RegionFillTask;)Lorg/apache/hadoop/hbase/client/RegionInfo;
      23: areturn

  public java.lang.Object call() throws java.lang.Exception;
    Code:
       0: aload_0
       1: invokevirtual #8                  // Method call:()Lorg/apache/hadoop/hbase/client/RegionInfo;
       4: areturn
}
