Compiled from "MultiThreadedAction.java"
class org.apache.hadoop.hbase.util.MultiThreadedAction$ProgressReporter implements java.lang.Runnable {
  final org.apache.hadoop.hbase.util.MultiThreadedAction this$0;

  public org.apache.hadoop.hbase.util.MultiThreadedAction$ProgressReporter(org.apache.hadoop.hbase.util.MultiThreadedAction, java.lang.String);
    Code:
       0: aload_0
       1: aload_1
       2: putfield      #2                  // Field this$0:Lorg/apache/hadoop/hbase/util/MultiThreadedAction;
       5: aload_0
       6: invokespecial #3                  // Method java/lang/Object."<init>":()V
       9: aload_0
      10: ldc           #4                  // String
      12: putfield      #5                  // Field reporterId:Ljava/lang/String;
      15: aload_0
      16: aload_2
      17: putfield      #5                  // Field reporterId:Ljava/lang/String;
      20: return

  public void run();
    Code:
       0: invokestatic  #6                  // Method java/lang/System.currentTimeMillis:()J
       3: lstore_1
       4: lconst_0
       5: lstore_3
       6: lconst_0
       7: lstore        5
       9: iconst_0
      10: istore        7
      12: ldc2_w        #7                  // long 5000l
      15: invokestatic  #9                  // Method org/apache/hadoop/hbase/util/Threads.sleep:(J)V
      18: aload_0
      19: getfield      #2                  // Field this$0:Lorg/apache/hadoop/hbase/util/MultiThreadedAction;
      22: getfield      #10                 // Field org/apache/hadoop/hbase/util/MultiThreadedAction.numThreadsWorking:Ljava/util/concurrent/atomic/AtomicInteger;
      25: invokevirtual #11                 // Method java/util/concurrent/atomic/AtomicInteger.get:()I
      28: ifeq          473
      31: new           #12                 // class java/lang/StringBuilder
      34: dup
      35: invokespecial #13                 // Method java/lang/StringBuilder."<init>":()V
      38: ldc           #14                 // String [
      40: invokevirtual #15                 // Method java/lang/StringBuilder.append:(Ljava/lang/String;)Ljava/lang/StringBuilder;
      43: aload_0
      44: getfield      #5                  // Field reporterId:Ljava/lang/String;
      47: invokevirtual #15                 // Method java/lang/StringBuilder.append:(Ljava/lang/String;)Ljava/lang/StringBuilder;
      50: ldc           #16                 // String :
      52: invokevirtual #15                 // Method java/lang/StringBuilder.append:(Ljava/lang/String;)Ljava/lang/StringBuilder;
      55: aload_0
      56: getfield      #2                  // Field this$0:Lorg/apache/hadoop/hbase/util/MultiThreadedAction;
      59: getfield      #10                 // Field org/apache/hadoop/hbase/util/MultiThreadedAction.numThreadsWorking:Ljava/util/concurrent/atomic/AtomicInteger;
      62: invokevirtual #11                 // Method java/util/concurrent/atomic/AtomicInteger.get:()I
      65: invokevirtual #17                 // Method java/lang/StringBuilder.append:(I)Ljava/lang/StringBuilder;
      68: ldc           #18                 // String ]
      70: invokevirtual #15                 // Method java/lang/StringBuilder.append:(Ljava/lang/String;)Ljava/lang/StringBuilder;
      73: invokevirtual #19                 // Method java/lang/StringBuilder.toString:()Ljava/lang/String;
      76: astore        8
      78: aload_0
      79: getfield      #2                  // Field this$0:Lorg/apache/hadoop/hbase/util/MultiThreadedAction;
      82: getfield      #20                 // Field org/apache/hadoop/hbase/util/MultiThreadedAction.numKeys:Ljava/util/concurrent/atomic/AtomicLong;
      85: invokevirtual #21                 // Method java/util/concurrent/atomic/AtomicLong.get:()J
      88: lconst_0
      89: lcmp
      90: ifne          124
      93: invokestatic  #22                 // Method org/apache/hadoop/hbase/util/MultiThreadedAction.access$000:()Lorg/slf4j/Logger;
      96: new           #12                 // class java/lang/StringBuilder
      99: dup
     100: invokespecial #13                 // Method java/lang/StringBuilder."<init>":()V
     103: aload         8
     105: invokevirtual #15                 // Method java/lang/StringBuilder.append:(Ljava/lang/String;)Ljava/lang/StringBuilder;
     108: ldc           #23                 // String Number of keys = 0
     110: invokevirtual #15                 // Method java/lang/StringBuilder.append:(Ljava/lang/String;)Ljava/lang/StringBuilder;
     113: invokevirtual #19                 // Method java/lang/StringBuilder.toString:()Ljava/lang/String;
     116: invokeinterface #24,  2           // InterfaceMethod org/slf4j/Logger.info:(Ljava/lang/String;)V
     121: goto          464
     124: aload_0
     125: getfield      #2                  // Field this$0:Lorg/apache/hadoop/hbase/util/MultiThreadedAction;
     128: getfield      #20                 // Field org/apache/hadoop/hbase/util/MultiThreadedAction.numKeys:Ljava/util/concurrent/atomic/AtomicLong;
     131: invokevirtual #21                 // Method java/util/concurrent/atomic/AtomicLong.get:()J
     134: lstore        9
     136: invokestatic  #6                  // Method java/lang/System.currentTimeMillis:()J
     139: lload_1
     140: lsub
     141: lstore        11
     143: aload_0
     144: getfield      #2                  // Field this$0:Lorg/apache/hadoop/hbase/util/MultiThreadedAction;
     147: getfield      #25                 // Field org/apache/hadoop/hbase/util/MultiThreadedAction.totalOpTimeMs:Ljava/util/concurrent/atomic/AtomicLong;
     150: invokevirtual #21                 // Method java/util/concurrent/atomic/AtomicLong.get:()J
     153: lstore        13
     155: lload         9
     157: lload_3
     158: lsub
     159: lstore        15
     161: lload         13
     163: lload         5
     165: lsub
     166: lstore        17
     168: lload         11
     170: lconst_0
     171: lcmp
     172: ifle          188
     175: lload         9
     177: ldc2_w        #26                 // long 1000l
     180: lmul
     181: lload         11
     183: ldiv
     184: l2d
     185: goto          189
     188: dconst_0
     189: dstore        19
     191: invokestatic  #22                 // Method org/apache/hadoop/hbase/util/MultiThreadedAction.access$000:()Lorg/slf4j/Logger;
     194: new           #12                 // class java/lang/StringBuilder
     197: dup
     198: invokespecial #13                 // Method java/lang/StringBuilder."<init>":()V
     201: aload         8
     203: invokevirtual #15                 // Method java/lang/StringBuilder.append:(Ljava/lang/String;)Ljava/lang/StringBuilder;
     206: ldc           #28                 // String Keys=
     208: invokevirtual #15                 // Method java/lang/StringBuilder.append:(Ljava/lang/String;)Ljava/lang/StringBuilder;
     211: lload         9
     213: invokevirtual #29                 // Method java/lang/StringBuilder.append:(J)Ljava/lang/StringBuilder;
     216: ldc           #30                 // String , cols=
     218: invokevirtual #15                 // Method java/lang/StringBuilder.append:(Ljava/lang/String;)Ljava/lang/StringBuilder;
     221: aload_0
     222: getfield      #2                  // Field this$0:Lorg/apache/hadoop/hbase/util/MultiThreadedAction;
     225: getfield      #31                 // Field org/apache/hadoop/hbase/util/MultiThreadedAction.numCols:Ljava/util/concurrent/atomic/AtomicLong;
     228: invokevirtual #21                 // Method java/util/concurrent/atomic/AtomicLong.get:()J
     231: invokestatic  #32                 // Method org/apache/hadoop/util/StringUtils.humanReadableInt:(J)Ljava/lang/String;
     234: invokevirtual #15                 // Method java/lang/StringBuilder.append:(Ljava/lang/String;)Ljava/lang/StringBuilder;
     237: ldc           #33                 // String , time=
     239: invokevirtual #15                 // Method java/lang/StringBuilder.append:(Ljava/lang/String;)Ljava/lang/StringBuilder;
     242: lload         11
     244: invokestatic  #34                 // Method org/apache/hadoop/hbase/util/MultiThreadedAction.access$100:(J)Ljava/lang/String;
     247: invokevirtual #15                 // Method java/lang/StringBuilder.append:(Ljava/lang/String;)Ljava/lang/StringBuilder;
     250: lload         9
     252: lconst_0
     253: lcmp
     254: ifle          329
     257: lload         11
     259: lconst_0
     260: lcmp
     261: ifle          329
     264: new           #12                 // class java/lang/StringBuilder
     267: dup
     268: invokespecial #13                 // Method java/lang/StringBuilder."<init>":()V
     271: ldc           #35                 // String  Overall: [keys/s=
     273: invokevirtual #15                 // Method java/lang/StringBuilder.append:(Ljava/lang/String;)Ljava/lang/StringBuilder;
     276: lload         9
     278: ldc2_w        #26                 // long 1000l
     281: lmul
     282: lload         11
     284: ldiv
     285: invokevirtual #29                 // Method java/lang/StringBuilder.append:(J)Ljava/lang/StringBuilder;
     288: ldc           #36                 // String , latency=
     290: invokevirtual #15                 // Method java/lang/StringBuilder.append:(Ljava/lang/String;)Ljava/lang/StringBuilder;
     293: ldc           #37                 // String %.2f
     295: iconst_1
     296: anewarray     #38                 // class java/lang/Object
     299: dup
     300: iconst_0
     301: lload         13
     303: l2d
     304: lload         9
     306: l2d
     307: ddiv
     308: invokestatic  #39                 // Method java/lang/Double.valueOf:(D)Ljava/lang/Double;
     311: aastore
     312: invokestatic  #40                 // Method java/lang/String.format:(Ljava/lang/String;[Ljava/lang/Object;)Ljava/lang/String;
     315: invokevirtual #15                 // Method java/lang/StringBuilder.append:(Ljava/lang/String;)Ljava/lang/StringBuilder;
     318: ldc           #41                 // String  ms]
     320: invokevirtual #15                 // Method java/lang/StringBuilder.append:(Ljava/lang/String;)Ljava/lang/StringBuilder;
     323: invokevirtual #19                 // Method java/lang/StringBuilder.toString:()Ljava/lang/String;
     326: goto          331
     329: ldc           #4                  // String
     331: invokevirtual #15                 // Method java/lang/StringBuilder.append:(Ljava/lang/String;)Ljava/lang/StringBuilder;
     334: lload         15
     336: lconst_0
     337: lcmp
     338: ifle          407
     341: new           #12                 // class java/lang/StringBuilder
     344: dup
     345: invokespecial #13                 // Method java/lang/StringBuilder."<init>":()V
     348: ldc           #42                 // String  Current: [keys/s=
     350: invokevirtual #15                 // Method java/lang/StringBuilder.append:(Ljava/lang/String;)Ljava/lang/StringBuilder;
     353: lload         15
     355: ldc2_w        #26                 // long 1000l
     358: lmul
     359: ldc2_w        #7                  // long 5000l
     362: ldiv
     363: invokevirtual #29                 // Method java/lang/StringBuilder.append:(J)Ljava/lang/StringBuilder;
     366: ldc           #36                 // String , latency=
     368: invokevirtual #15                 // Method java/lang/StringBuilder.append:(Ljava/lang/String;)Ljava/lang/StringBuilder;
     371: ldc           #37                 // String %.2f
     373: iconst_1
     374: anewarray     #38                 // class java/lang/Object
     377: dup
     378: iconst_0
     379: lload         17
     381: l2d
     382: lload         15
     384: l2d
     385: ddiv
     386: invokestatic  #39                 // Method java/lang/Double.valueOf:(D)Ljava/lang/Double;
     389: aastore
     390: invokestatic  #40                 // Method java/lang/String.format:(Ljava/lang/String;[Ljava/lang/Object;)Ljava/lang/String;
     393: invokevirtual #15                 // Method java/lang/StringBuilder.append:(Ljava/lang/String;)Ljava/lang/StringBuilder;
     396: ldc           #41                 // String  ms]
     398: invokevirtual #15                 // Method java/lang/StringBuilder.append:(Ljava/lang/String;)Ljava/lang/StringBuilder;
     401: invokevirtual #19                 // Method java/lang/StringBuilder.toString:()Ljava/lang/String;
     404: goto          409
     407: ldc           #4                  // String
     409: invokevirtual #15                 // Method java/lang/StringBuilder.append:(Ljava/lang/String;)Ljava/lang/StringBuilder;
     412: aload_0
     413: getfield      #2                  // Field this$0:Lorg/apache/hadoop/hbase/util/MultiThreadedAction;
     416: invokevirtual #43                 // Method org/apache/hadoop/hbase/util/MultiThreadedAction.progressInfo:()Ljava/lang/String;
     419: invokevirtual #15                 // Method java/lang/StringBuilder.append:(Ljava/lang/String;)Ljava/lang/StringBuilder;
     422: invokevirtual #19                 // Method java/lang/StringBuilder.toString:()Ljava/lang/String;
     425: invokeinterface #24,  2           // InterfaceMethod org/slf4j/Logger.info:(Ljava/lang/String;)V
     430: aload_0
     431: getfield      #2                  // Field this$0:Lorg/apache/hadoop/hbase/util/MultiThreadedAction;
     434: invokestatic  #44                 // Method org/apache/hadoop/hbase/util/MultiThreadedAction.access$200:(Lorg/apache/hadoop/hbase/util/MultiThreadedAction;)Z
     437: ifeq          452
     440: aload_0
     441: lload         15
     443: dload         19
     445: iload         7
     447: i2d
     448: dsub
     449: invokespecial #45                 // Method printStreamingCounters:(JD)V
     452: lload         9
     454: lstore_3
     455: lload         13
     457: lstore        5
     459: dload         19
     461: d2i
     462: istore        7
     464: ldc2_w        #7                  // long 5000l
     467: invokestatic  #9                  // Method org/apache/hadoop/hbase/util/Threads.sleep:(J)V
     470: goto          18
     473: return
}
