Compiled from "MultiServerCallable.java"
class org.apache.hadoop.hbase.client.MultiServerCallable extends org.apache.hadoop.hbase.client.CancellableRegionServerCallable<org.apache.hadoop.hbase.client.MultiResponse> {
  org.apache.hadoop.hbase.client.MultiServerCallable(org.apache.hadoop.hbase.client.ClusterConnection, org.apache.hadoop.hbase.TableName, org.apache.hadoop.hbase.ServerName, org.apache.hadoop.hbase.client.MultiAction, org.apache.hbase.thirdparty.com.google.protobuf.RpcController, int, org.apache.hadoop.hbase.client.RetryingTimeTracker, int);
    Code:
       0: aload_0
       1: aload_1
       2: aload_2
       3: aconst_null
       4: aload         5
       6: iload         6
       8: aload         7
      10: iload         8
      12: invokespecial #1                  // Method org/apache/hadoop/hbase/client/CancellableRegionServerCallable."<init>":(Lorg/apache/hadoop/hbase/client/Connection;Lorg/apache/hadoop/hbase/TableName;[BLorg/apache/hbase/thirdparty/com/google/protobuf/RpcController;ILorg/apache/hadoop/hbase/client/RetryingTimeTracker;I)V
      15: aload_0
      16: aload         4
      18: putfield      #2                  // Field multiAction:Lorg/apache/hadoop/hbase/client/MultiAction;
      21: aload_0
      22: new           #3                  // class org/apache/hadoop/hbase/HRegionLocation
      25: dup
      26: aconst_null
      27: aload_3
      28: invokespecial #4                  // Method org/apache/hadoop/hbase/HRegionLocation."<init>":(Lorg/apache/hadoop/hbase/client/RegionInfo;Lorg/apache/hadoop/hbase/ServerName;)V
      31: putfield      #5                  // Field location:Lorg/apache/hadoop/hbase/HRegionLocation;
      34: aload_0
      35: aload_0
      36: invokespecial #6                  // Method isCellBlock:()Z
      39: putfield      #7                  // Field cellBlock:Z
      42: return

  public void reset(org.apache.hadoop.hbase.ServerName, org.apache.hadoop.hbase.client.MultiAction);
    Code:
       0: aload_0
       1: new           #3                  // class org/apache/hadoop/hbase/HRegionLocation
       4: dup
       5: aconst_null
       6: aload_1
       7: invokespecial #4                  // Method org/apache/hadoop/hbase/HRegionLocation."<init>":(Lorg/apache/hadoop/hbase/client/RegionInfo;Lorg/apache/hadoop/hbase/ServerName;)V
      10: putfield      #5                  // Field location:Lorg/apache/hadoop/hbase/HRegionLocation;
      13: aload_0
      14: aload_2
      15: putfield      #2                  // Field multiAction:Lorg/apache/hadoop/hbase/client/MultiAction;
      18: aload_0
      19: aload_0
      20: invokespecial #6                  // Method isCellBlock:()Z
      23: putfield      #7                  // Field cellBlock:Z
      26: return

  protected org.apache.hadoop.hbase.HRegionLocation getLocation();
    Code:
       0: new           #8                  // class java/lang/RuntimeException
       3: dup
       4: ldc           #9                  // String Cannot get region location for multi-region request
       6: invokespecial #10                 // Method java/lang/RuntimeException."<init>":(Ljava/lang/String;)V
       9: athrow

  public org.apache.hadoop.hbase.HRegionInfo getHRegionInfo();
    Code:
       0: new           #8                  // class java/lang/RuntimeException
       3: dup
       4: ldc           #11                 // String Cannot get region info for multi-region request
       6: invokespecial #10                 // Method java/lang/RuntimeException."<init>":(Ljava/lang/String;)V
       9: athrow

  org.apache.hadoop.hbase.client.MultiAction getMulti();
    Code:
       0: aload_0
       1: getfield      #2                  // Field multiAction:Lorg/apache/hadoop/hbase/client/MultiAction;
       4: areturn

  protected org.apache.hadoop.hbase.client.MultiResponse rpcCall() throws java.lang.Exception;
    Code:
       0: aload_0
       1: getfield      #2                  // Field multiAction:Lorg/apache/hadoop/hbase/client/MultiAction;
       4: invokevirtual #12                 // Method org/apache/hadoop/hbase/client/MultiAction.size:()I
       7: istore_1
       8: iload_1
       9: ifgt          22
      12: new           #13                 // class org/apache/hadoop/hbase/DoNotRetryIOException
      15: dup
      16: ldc           #14                 // String No Actions
      18: invokespecial #15                 // Method org/apache/hadoop/hbase/DoNotRetryIOException."<init>":(Ljava/lang/String;)V
      21: athrow
      22: invokestatic  #16                 // Method org/apache/hadoop/hbase/shaded/protobuf/generated/ClientProtos$MultiRequest.newBuilder:()Lorg/apache/hadoop/hbase/shaded/protobuf/generated/ClientProtos$MultiRequest$Builder;
      25: astore_2
      26: invokestatic  #17                 // Method org/apache/hadoop/hbase/shaded/protobuf/generated/ClientProtos$RegionAction.newBuilder:()Lorg/apache/hadoop/hbase/shaded/protobuf/generated/ClientProtos$RegionAction$Builder;
      29: astore_3
      30: invokestatic  #18                 // Method org/apache/hadoop/hbase/shaded/protobuf/generated/ClientProtos$Action.newBuilder:()Lorg/apache/hadoop/hbase/shaded/protobuf/generated/ClientProtos$Action$Builder;
      33: astore        4
      35: invokestatic  #19                 // Method org/apache/hadoop/hbase/shaded/protobuf/generated/ClientProtos$MutationProto.newBuilder:()Lorg/apache/hadoop/hbase/shaded/protobuf/generated/ClientProtos$MutationProto$Builder;
      38: astore        5
      40: aload_0
      41: getfield      #7                  // Field cellBlock:Z
      44: ifeq          58
      47: new           #20                 // class java/util/ArrayList
      50: dup
      51: iload_1
      52: invokespecial #21                 // Method java/util/ArrayList."<init>":(I)V
      55: goto          59
      58: aconst_null
      59: astore        6
      61: aload_0
      62: getfield      #2                  // Field multiAction:Lorg/apache/hadoop/hbase/client/MultiAction;
      65: invokevirtual #22                 // Method org/apache/hadoop/hbase/client/MultiAction.getNonceGroup:()J
      68: lstore        7
      70: new           #23                 // class java/util/HashMap
      73: dup
      74: invokespecial #24                 // Method java/util/HashMap."<init>":()V
      77: astore        9
      79: aload_0
      80: getfield      #2                  // Field multiAction:Lorg/apache/hadoop/hbase/client/MultiAction;
      83: getfield      #25                 // Field org/apache/hadoop/hbase/client/MultiAction.actions:Ljava/util/Map;
      86: invokeinterface #26,  1           // InterfaceMethod java/util/Map.entrySet:()Ljava/util/Set;
      91: invokeinterface #27,  1           // InterfaceMethod java/util/Set.iterator:()Ljava/util/Iterator;
      96: astore        10
      98: aload         10
     100: invokeinterface #28,  1           // InterfaceMethod java/util/Iterator.hasNext:()Z
     105: ifeq          193
     108: aload         10
     110: invokeinterface #29,  1           // InterfaceMethod java/util/Iterator.next:()Ljava/lang/Object;
     115: checkcast     #30                 // class java/util/Map$Entry
     118: astore        11
     120: aload         11
     122: invokeinterface #31,  1           // InterfaceMethod java/util/Map$Entry.getKey:()Ljava/lang/Object;
     127: checkcast     #32                 // class "[B"
     130: astore        12
     132: aload         11
     134: invokeinterface #33,  1           // InterfaceMethod java/util/Map$Entry.getValue:()Ljava/lang/Object;
     139: checkcast     #34                 // class java/util/List
     142: astore        13
     144: aload_0
     145: getfield      #7                  // Field cellBlock:Z
     148: ifeq          173
     151: aload         12
     153: aload         13
     155: aload         6
     157: aload_2
     158: aload_3
     159: aload         4
     161: aload         5
     163: lload         7
     165: aload         9
     167: invokestatic  #35                 // Method org/apache/hadoop/hbase/shaded/protobuf/RequestConverter.buildNoDataRegionActions:([BLjava/lang/Iterable;Ljava/util/List;Lorg/apache/hadoop/hbase/shaded/protobuf/generated/ClientProtos$MultiRequest$Builder;Lorg/apache/hadoop/hbase/shaded/protobuf/generated/ClientProtos$RegionAction$Builder;Lorg/apache/hadoop/hbase/shaded/protobuf/generated/ClientProtos$Action$Builder;Lorg/apache/hadoop/hbase/shaded/protobuf/generated/ClientProtos$MutationProto$Builder;JLjava/util/Map;)V
     170: goto          190
     173: aload         12
     175: aload         13
     177: aload_2
     178: aload_3
     179: aload         4
     181: aload         5
     183: lload         7
     185: aload         9
     187: invokestatic  #36                 // Method org/apache/hadoop/hbase/shaded/protobuf/RequestConverter.buildRegionActions:([BLjava/util/List;Lorg/apache/hadoop/hbase/shaded/protobuf/generated/ClientProtos$MultiRequest$Builder;Lorg/apache/hadoop/hbase/shaded/protobuf/generated/ClientProtos$RegionAction$Builder;Lorg/apache/hadoop/hbase/shaded/protobuf/generated/ClientProtos$Action$Builder;Lorg/apache/hadoop/hbase/shaded/protobuf/generated/ClientProtos$MutationProto$Builder;JLjava/util/Map;)V
     190: goto          98
     193: aload         6
     195: ifnull        207
     198: aload_0
     199: aload         6
     201: invokestatic  #37                 // Method org/apache/hadoop/hbase/CellUtil.createCellScanner:(Ljava/util/List;)Lorg/apache/hadoop/hbase/CellScanner;
     204: invokevirtual #38                 // Method setRpcControllerCellScanner:(Lorg/apache/hadoop/hbase/CellScanner;)V
     207: aload_2
     208: invokevirtual #39                 // Method org/apache/hadoop/hbase/shaded/protobuf/generated/ClientProtos$MultiRequest$Builder.build:()Lorg/apache/hadoop/hbase/shaded/protobuf/generated/ClientProtos$MultiRequest;
     211: astore        10
     213: aload_0
     214: invokevirtual #40                 // Method getStub:()Ljava/lang/Object;
     217: checkcast     #41                 // class org/apache/hadoop/hbase/shaded/protobuf/generated/ClientProtos$ClientService$BlockingInterface
     220: aload_0
     221: invokevirtual #42                 // Method getRpcController:()Lorg/apache/hbase/thirdparty/com/google/protobuf/RpcController;
     224: aload         10
     226: invokeinterface #43,  3           // InterfaceMethod org/apache/hadoop/hbase/shaded/protobuf/generated/ClientProtos$ClientService$BlockingInterface.multi:(Lorg/apache/hbase/thirdparty/com/google/protobuf/RpcController;Lorg/apache/hadoop/hbase/shaded/protobuf/generated/ClientProtos$MultiRequest;)Lorg/apache/hadoop/hbase/shaded/protobuf/generated/ClientProtos$MultiResponse;
     231: astore        11
     233: aload         11
     235: ifnonnull     240
     238: aconst_null
     239: areturn
     240: aload         10
     242: aload         9
     244: aload         11
     246: aload_0
     247: invokevirtual #44                 // Method getRpcControllerCellScanner:()Lorg/apache/hadoop/hbase/CellScanner;
     250: invokestatic  #45                 // Method org/apache/hadoop/hbase/shaded/protobuf/ResponseConverter.getResults:(Lorg/apache/hadoop/hbase/shaded/protobuf/generated/ClientProtos$MultiRequest;Ljava/util/Map;Lorg/apache/hadoop/hbase/shaded/protobuf/generated/ClientProtos$MultiResponse;Lorg/apache/hadoop/hbase/CellScanner;)Lorg/apache/hadoop/hbase/client/MultiResponse;
     253: areturn

  public void prepare(boolean) throws java.io.IOException;
    Code:
       0: aload_0
       1: aload_0
       2: invokevirtual #46                 // Method getConnection:()Lorg/apache/hadoop/hbase/client/ClusterConnection;
       5: aload_0
       6: getfield      #5                  // Field location:Lorg/apache/hadoop/hbase/HRegionLocation;
       9: invokevirtual #48                 // Method org/apache/hadoop/hbase/HRegionLocation.getServerName:()Lorg/apache/hadoop/hbase/ServerName;
      12: invokeinterface #49,  2           // InterfaceMethod org/apache/hadoop/hbase/client/ClusterConnection.getClient:(Lorg/apache/hadoop/hbase/ServerName;)Lorg/apache/hadoop/hbase/shaded/protobuf/generated/ClientProtos$ClientService$BlockingInterface;
      17: invokevirtual #50                 // Method setStub:(Ljava/lang/Object;)V
      20: return

  org.apache.hadoop.hbase.ServerName getServerName();
    Code:
       0: aload_0
       1: getfield      #5                  // Field location:Lorg/apache/hadoop/hbase/HRegionLocation;
       4: invokevirtual #48                 // Method org/apache/hadoop/hbase/HRegionLocation.getServerName:()Lorg/apache/hadoop/hbase/ServerName;
       7: areturn

  protected java.lang.Object rpcCall() throws java.lang.Exception;
    Code:
       0: aload_0
       1: invokevirtual #51                 // Method rpcCall:()Lorg/apache/hadoop/hbase/client/MultiResponse;
       4: areturn
}
