Compiled from "NamespaceTableAndRegionInfo.java"
class org.apache.hadoop.hbase.namespace.NamespaceTableAndRegionInfo {
  public org.apache.hadoop.hbase.namespace.NamespaceTableAndRegionInfo(java.lang.String);
    Code:
       0: aload_0
       1: invokespecial #1                  // Method java/lang/Object."<init>":()V
       4: aload_0
       5: aload_1
       6: putfield      #2                  // Field name:Ljava/lang/String;
       9: aload_0
      10: new           #3                  // class java/util/HashMap
      13: dup
      14: invokespecial #4                  // Method java/util/HashMap."<init>":()V
      17: putfield      #5                  // Field tableAndRegionInfo:Ljava/util/Map;
      20: return

  java.lang.String getName();
    Code:
       0: aload_0
       1: getfield      #2                  // Field name:Ljava/lang/String;
       4: areturn

  synchronized java.util.Set<org.apache.hadoop.hbase.TableName> getTables();
    Code:
       0: aload_0
       1: getfield      #5                  // Field tableAndRegionInfo:Ljava/util/Map;
       4: invokeinterface #6,  1            // InterfaceMethod java/util/Map.keySet:()Ljava/util/Set;
       9: areturn

  synchronized int getRegionCount();
    Code:
       0: iconst_0
       1: istore_1
       2: aload_0
       3: getfield      #5                  // Field tableAndRegionInfo:Ljava/util/Map;
       6: invokeinterface #7,  1            // InterfaceMethod java/util/Map.entrySet:()Ljava/util/Set;
      11: invokeinterface #8,  1            // InterfaceMethod java/util/Set.iterator:()Ljava/util/Iterator;
      16: astore_2
      17: aload_2
      18: invokeinterface #9,  1            // InterfaceMethod java/util/Iterator.hasNext:()Z
      23: ifeq          54
      26: aload_2
      27: invokeinterface #10,  1           // InterfaceMethod java/util/Iterator.next:()Ljava/lang/Object;
      32: checkcast     #11                 // class java/util/Map$Entry
      35: astore_3
      36: iload_1
      37: aload_3
      38: invokeinterface #12,  1           // InterfaceMethod java/util/Map$Entry.getValue:()Ljava/lang/Object;
      43: checkcast     #13                 // class java/util/concurrent/atomic/AtomicInteger
      46: invokevirtual #14                 // Method java/util/concurrent/atomic/AtomicInteger.get:()I
      49: iadd
      50: istore_1
      51: goto          17
      54: iload_1
      55: ireturn

  synchronized int getRegionCountOfTable(org.apache.hadoop.hbase.TableName);
    Code:
       0: aload_0
       1: getfield      #5                  // Field tableAndRegionInfo:Ljava/util/Map;
       4: aload_1
       5: invokeinterface #15,  2           // InterfaceMethod java/util/Map.containsKey:(Ljava/lang/Object;)Z
      10: ifeq          30
      13: aload_0
      14: getfield      #5                  // Field tableAndRegionInfo:Ljava/util/Map;
      17: aload_1
      18: invokeinterface #16,  2           // InterfaceMethod java/util/Map.get:(Ljava/lang/Object;)Ljava/lang/Object;
      23: checkcast     #13                 // class java/util/concurrent/atomic/AtomicInteger
      26: invokevirtual #14                 // Method java/util/concurrent/atomic/AtomicInteger.get:()I
      29: ireturn
      30: iconst_m1
      31: ireturn

  synchronized boolean containsTable(org.apache.hadoop.hbase.TableName);
    Code:
       0: aload_0
       1: getfield      #5                  // Field tableAndRegionInfo:Ljava/util/Map;
       4: aload_1
       5: invokeinterface #15,  2           // InterfaceMethod java/util/Map.containsKey:(Ljava/lang/Object;)Z
      10: ireturn

  synchronized void addTable(org.apache.hadoop.hbase.TableName, int);
    Code:
       0: aload_0
       1: getfield      #2                  // Field name:Ljava/lang/String;
       4: aload_1
       5: invokevirtual #17                 // Method org/apache/hadoop/hbase/TableName.getNamespaceAsString:()Ljava/lang/String;
       8: invokevirtual #18                 // Method java/lang/String.equalsIgnoreCase:(Ljava/lang/String;)Z
      11: ifne          53
      14: new           #19                 // class java/lang/IllegalStateException
      17: dup
      18: new           #20                 // class java/lang/StringBuilder
      21: dup
      22: invokespecial #21                 // Method java/lang/StringBuilder."<init>":()V
      25: ldc           #22                 // String Table :
      27: invokevirtual #23                 // Method java/lang/StringBuilder.append:(Ljava/lang/String;)Ljava/lang/StringBuilder;
      30: aload_1
      31: invokevirtual #24                 // Method java/lang/StringBuilder.append:(Ljava/lang/Object;)Ljava/lang/StringBuilder;
      34: ldc           #25                 // String  does not belong to namespace
      36: invokevirtual #23                 // Method java/lang/StringBuilder.append:(Ljava/lang/String;)Ljava/lang/StringBuilder;
      39: aload_0
      40: getfield      #2                  // Field name:Ljava/lang/String;
      43: invokevirtual #23                 // Method java/lang/StringBuilder.append:(Ljava/lang/String;)Ljava/lang/StringBuilder;
      46: invokevirtual #26                 // Method java/lang/StringBuilder.toString:()Ljava/lang/String;
      49: invokespecial #27                 // Method java/lang/IllegalStateException."<init>":(Ljava/lang/String;)V
      52: athrow
      53: aload_0
      54: getfield      #5                  // Field tableAndRegionInfo:Ljava/util/Map;
      57: aload_1
      58: invokeinterface #15,  2           // InterfaceMethod java/util/Map.containsKey:(Ljava/lang/Object;)Z
      63: ifne          88
      66: aload_0
      67: getfield      #5                  // Field tableAndRegionInfo:Ljava/util/Map;
      70: aload_1
      71: new           #13                 // class java/util/concurrent/atomic/AtomicInteger
      74: dup
      75: iload_2
      76: invokespecial #28                 // Method java/util/concurrent/atomic/AtomicInteger."<init>":(I)V
      79: invokeinterface #29,  3           // InterfaceMethod java/util/Map.put:(Ljava/lang/Object;Ljava/lang/Object;)Ljava/lang/Object;
      84: pop
      85: goto          115
      88: new           #19                 // class java/lang/IllegalStateException
      91: dup
      92: new           #20                 // class java/lang/StringBuilder
      95: dup
      96: invokespecial #21                 // Method java/lang/StringBuilder."<init>":()V
      99: ldc           #30                 // String Table already in the cache
     101: invokevirtual #23                 // Method java/lang/StringBuilder.append:(Ljava/lang/String;)Ljava/lang/StringBuilder;
     104: aload_1
     105: invokevirtual #24                 // Method java/lang/StringBuilder.append:(Ljava/lang/Object;)Ljava/lang/StringBuilder;
     108: invokevirtual #26                 // Method java/lang/StringBuilder.toString:()Ljava/lang/String;
     111: invokespecial #27                 // Method java/lang/IllegalStateException."<init>":(Ljava/lang/String;)V
     114: athrow
     115: return

  synchronized void removeTable(org.apache.hadoop.hbase.TableName);
    Code:
       0: aload_0
       1: getfield      #5                  // Field tableAndRegionInfo:Ljava/util/Map;
       4: aload_1
       5: invokeinterface #31,  2           // InterfaceMethod java/util/Map.remove:(Ljava/lang/Object;)Ljava/lang/Object;
      10: pop
      11: return

  synchronized int incRegionCountForTable(org.apache.hadoop.hbase.TableName, int);
    Code:
       0: aload_0
       1: getfield      #5                  // Field tableAndRegionInfo:Ljava/util/Map;
       4: aload_1
       5: invokeinterface #16,  2           // InterfaceMethod java/util/Map.get:(Ljava/lang/Object;)Ljava/lang/Object;
      10: checkcast     #13                 // class java/util/concurrent/atomic/AtomicInteger
      13: iload_2
      14: invokevirtual #32                 // Method java/util/concurrent/atomic/AtomicInteger.addAndGet:(I)I
      17: ireturn

  synchronized int decrementRegionCountForTable(org.apache.hadoop.hbase.TableName, int);
    Code:
       0: aload_0
       1: getfield      #5                  // Field tableAndRegionInfo:Ljava/util/Map;
       4: aload_1
       5: invokeinterface #16,  2           // InterfaceMethod java/util/Map.get:(Ljava/lang/Object;)Ljava/lang/Object;
      10: checkcast     #13                 // class java/util/concurrent/atomic/AtomicInteger
      13: invokevirtual #33                 // Method java/util/concurrent/atomic/AtomicInteger.decrementAndGet:()I
      16: ireturn

  public java.lang.String toString();
    Code:
       0: bipush        44
       2: invokestatic  #34                 // Method org/apache/hbase/thirdparty/com/google/common/base/Joiner.on:(C)Lorg/apache/hbase/thirdparty/com/google/common/base/Joiner;
       5: ldc           #35                 // String =
       7: invokevirtual #36                 // Method org/apache/hbase/thirdparty/com/google/common/base/Joiner.withKeyValueSeparator:(Ljava/lang/String;)Lorg/apache/hbase/thirdparty/com/google/common/base/Joiner$MapJoiner;
      10: astore_1
      11: new           #20                 // class java/lang/StringBuilder
      14: dup
      15: invokespecial #21                 // Method java/lang/StringBuilder."<init>":()V
      18: ldc           #37                 // String NamespaceTableAndRegionInfo [name=
      20: invokevirtual #23                 // Method java/lang/StringBuilder.append:(Ljava/lang/String;)Ljava/lang/StringBuilder;
      23: aload_0
      24: getfield      #2                  // Field name:Ljava/lang/String;
      27: invokevirtual #23                 // Method java/lang/StringBuilder.append:(Ljava/lang/String;)Ljava/lang/StringBuilder;
      30: ldc           #38                 // String , tableAndRegionInfo=
      32: invokevirtual #23                 // Method java/lang/StringBuilder.append:(Ljava/lang/String;)Ljava/lang/StringBuilder;
      35: aload_1
      36: aload_0
      37: getfield      #5                  // Field tableAndRegionInfo:Ljava/util/Map;
      40: invokevirtual #39                 // Method org/apache/hbase/thirdparty/com/google/common/base/Joiner$MapJoiner.join:(Ljava/util/Map;)Ljava/lang/String;
      43: invokevirtual #23                 // Method java/lang/StringBuilder.append:(Ljava/lang/String;)Ljava/lang/StringBuilder;
      46: ldc           #40                 // String ]
      48: invokevirtual #23                 // Method java/lang/StringBuilder.append:(Ljava/lang/String;)Ljava/lang/StringBuilder;
      51: invokevirtual #26                 // Method java/lang/StringBuilder.toString:()Ljava/lang/String;
      54: areturn
}
