Compiled from "NettyRpcConnection.java"
class org.apache.hadoop.hbase.ipc.NettyRpcConnection$1 implements java.lang.Runnable {
  final org.apache.hadoop.hbase.ipc.NettyRpcConnection this$0;

  org.apache.hadoop.hbase.ipc.NettyRpcConnection$1(org.apache.hadoop.hbase.ipc.NettyRpcConnection);
    Code:
       0: aload_0
       1: aload_1
       2: putfield      #1                  // Field this$0:Lorg/apache/hadoop/hbase/ipc/NettyRpcConnection;
       5: aload_0
       6: invokespecial #2                  // Method java/lang/Object."<init>":()V
       9: return

  public void run();
    Code:
       0: aload_0
       1: getfield      #1                  // Field this$0:Lorg/apache/hadoop/hbase/ipc/NettyRpcConnection;
       4: invokevirtual #3                  // Method org/apache/hadoop/hbase/ipc/NettyRpcConnection.shouldAuthenticateOverKrb:()Z
       7: ifeq          17
      10: aload_0
      11: getfield      #1                  // Field this$0:Lorg/apache/hadoop/hbase/ipc/NettyRpcConnection;
      14: invokevirtual #4                  // Method org/apache/hadoop/hbase/ipc/NettyRpcConnection.relogin:()V
      17: goto          32
      20: astore_1
      21: invokestatic  #6                  // Method org/apache/hadoop/hbase/ipc/NettyRpcConnection.access$000:()Lorg/slf4j/Logger;
      24: ldc           #7                  // String Relogin failed
      26: aload_1
      27: invokeinterface #8,  3            // InterfaceMethod org/slf4j/Logger.warn:(Ljava/lang/String;Ljava/lang/Throwable;)V
      32: aload_0
      33: dup
      34: astore_1
      35: monitorenter
      36: aload_0
      37: getfield      #1                  // Field this$0:Lorg/apache/hadoop/hbase/ipc/NettyRpcConnection;
      40: iconst_0
      41: invokestatic  #9                  // Method org/apache/hadoop/hbase/ipc/NettyRpcConnection.access$102:(Lorg/apache/hadoop/hbase/ipc/NettyRpcConnection;Z)Z
      44: pop
      45: aload_1
      46: monitorexit
      47: goto          55
      50: astore_2
      51: aload_1
      52: monitorexit
      53: aload_2
      54: athrow
      55: return
    Exception table:
       from    to  target type
           0    17    20   Class java/io/IOException
          36    47    50   any
          50    53    50   any
}
