Compiled from "NettyServerRpcConnection.java"
class org.apache.hadoop.hbase.ipc.NettyServerRpcConnection extends org.apache.hadoop.hbase.ipc.ServerRpcConnection {
  final org.apache.hbase.thirdparty.io.netty.channel.Channel channel;

  org.apache.hadoop.hbase.ipc.NettyServerRpcConnection(org.apache.hadoop.hbase.ipc.NettyRpcServer, org.apache.hbase.thirdparty.io.netty.channel.Channel);
    Code:
       0: aload_0
       1: aload_1
       2: invokespecial #1                  // Method org/apache/hadoop/hbase/ipc/ServerRpcConnection."<init>":(Lorg/apache/hadoop/hbase/ipc/RpcServer;)V
       5: aload_0
       6: aload_2
       7: putfield      #2                  // Field channel:Lorg/apache/hbase/thirdparty/io/netty/channel/Channel;
      10: aload_2
      11: invokeinterface #3,  1            // InterfaceMethod org/apache/hbase/thirdparty/io/netty/channel/Channel.remoteAddress:()Ljava/net/SocketAddress;
      16: checkcast     #4                  // class java/net/InetSocketAddress
      19: astore_3
      20: aload_0
      21: aload_3
      22: invokevirtual #5                  // Method java/net/InetSocketAddress.getAddress:()Ljava/net/InetAddress;
      25: putfield      #6                  // Field addr:Ljava/net/InetAddress;
      28: aload_0
      29: getfield      #6                  // Field addr:Ljava/net/InetAddress;
      32: ifnonnull     44
      35: aload_0
      36: ldc           #7                  // String *Unknown*
      38: putfield      #8                  // Field hostAddress:Ljava/lang/String;
      41: goto          55
      44: aload_0
      45: aload_3
      46: invokevirtual #5                  // Method java/net/InetSocketAddress.getAddress:()Ljava/net/InetAddress;
      49: invokevirtual #9                  // Method java/net/InetAddress.getHostAddress:()Ljava/lang/String;
      52: putfield      #8                  // Field hostAddress:Ljava/lang/String;
      55: aload_0
      56: aload_3
      57: invokevirtual #10                 // Method java/net/InetSocketAddress.getPort:()I
      60: putfield      #11                 // Field remotePort:I
      63: return

  void process(org.apache.hbase.thirdparty.io.netty.buffer.ByteBuf) throws java.io.IOException, java.lang.InterruptedException;
    Code:
       0: aload_0
       1: getfield      #12                 // Field connectionHeaderRead:Z
       4: ifeq          38
       7: aload_0
       8: new           #13                 // class org/apache/hadoop/hbase/ipc/NettyServerRpcConnection$1
      11: dup
      12: aload_0
      13: aload_1
      14: invokespecial #14                 // Method org/apache/hadoop/hbase/ipc/NettyServerRpcConnection$1."<init>":(Lorg/apache/hadoop/hbase/ipc/NettyServerRpcConnection;Lorg/apache/hbase/thirdparty/io/netty/buffer/ByteBuf;)V
      17: putfield      #15                 // Field callCleanup:Lorg/apache/hadoop/hbase/ipc/RpcServer$CallCleanup;
      20: aload_0
      21: new           #16                 // class org/apache/hadoop/hbase/nio/SingleByteBuff
      24: dup
      25: aload_1
      26: invokevirtual #17                 // Method org/apache/hbase/thirdparty/io/netty/buffer/ByteBuf.nioBuffer:()Ljava/nio/ByteBuffer;
      29: invokespecial #18                 // Method org/apache/hadoop/hbase/nio/SingleByteBuff."<init>":(Ljava/nio/ByteBuffer;)V
      32: invokevirtual #19                 // Method process:(Lorg/apache/hadoop/hbase/nio/ByteBuff;)V
      35: goto          62
      38: aload_1
      39: invokevirtual #20                 // Method org/apache/hbase/thirdparty/io/netty/buffer/ByteBuf.readableBytes:()I
      42: invokestatic  #21                 // Method java/nio/ByteBuffer.allocate:(I)Ljava/nio/ByteBuffer;
      45: astore_2
      46: aload_1
      47: aload_2
      48: invokevirtual #22                 // Method org/apache/hbase/thirdparty/io/netty/buffer/ByteBuf.readBytes:(Ljava/nio/ByteBuffer;)Lorg/apache/hbase/thirdparty/io/netty/buffer/ByteBuf;
      51: pop
      52: aload_1
      53: invokevirtual #23                 // Method org/apache/hbase/thirdparty/io/netty/buffer/ByteBuf.release:()Z
      56: pop
      57: aload_0
      58: aload_2
      59: invokevirtual #24                 // Method process:(Ljava/nio/ByteBuffer;)V
      62: return

  void process(java.nio.ByteBuffer) throws java.io.IOException, java.lang.InterruptedException;
    Code:
       0: aload_0
       1: new           #16                 // class org/apache/hadoop/hbase/nio/SingleByteBuff
       4: dup
       5: aload_1
       6: invokespecial #18                 // Method org/apache/hadoop/hbase/nio/SingleByteBuff."<init>":(Ljava/nio/ByteBuffer;)V
       9: invokevirtual #19                 // Method process:(Lorg/apache/hadoop/hbase/nio/ByteBuff;)V
      12: return

  void process(org.apache.hadoop.hbase.nio.ByteBuff) throws java.io.IOException, java.lang.InterruptedException;
    Code:
       0: aload_0
       1: getfield      #25                 // Field skipInitialSaslHandshake:Z
       4: ifeq          34
       7: aload_0
       8: iconst_0
       9: putfield      #25                 // Field skipInitialSaslHandshake:Z
      12: aload_0
      13: getfield      #15                 // Field callCleanup:Lorg/apache/hadoop/hbase/ipc/RpcServer$CallCleanup;
      16: ifnull        28
      19: aload_0
      20: getfield      #15                 // Field callCleanup:Lorg/apache/hadoop/hbase/ipc/RpcServer$CallCleanup;
      23: invokeinterface #26,  1           // InterfaceMethod org/apache/hadoop/hbase/ipc/RpcServer$CallCleanup.run:()V
      28: aload_0
      29: aconst_null
      30: putfield      #15                 // Field callCleanup:Lorg/apache/hadoop/hbase/ipc/RpcServer$CallCleanup;
      33: return
      34: aload_0
      35: getfield      #27                 // Field useSasl:Z
      38: ifeq          49
      41: aload_0
      42: aload_1
      43: invokevirtual #28                 // Method saslReadAndProcess:(Lorg/apache/hadoop/hbase/nio/ByteBuff;)V
      46: goto          54
      49: aload_0
      50: aload_1
      51: invokevirtual #29                 // Method processOneRpc:(Lorg/apache/hadoop/hbase/nio/ByteBuff;)V
      54: aload_0
      55: aconst_null
      56: putfield      #15                 // Field callCleanup:Lorg/apache/hadoop/hbase/ipc/RpcServer$CallCleanup;
      59: goto          89
      62: astore_2
      63: aload_0
      64: getfield      #15                 // Field callCleanup:Lorg/apache/hadoop/hbase/ipc/RpcServer$CallCleanup;
      67: ifnull        79
      70: aload_0
      71: getfield      #15                 // Field callCleanup:Lorg/apache/hadoop/hbase/ipc/RpcServer$CallCleanup;
      74: invokeinterface #26,  1           // InterfaceMethod org/apache/hadoop/hbase/ipc/RpcServer$CallCleanup.run:()V
      79: aload_2
      80: athrow
      81: astore_3
      82: aload_0
      83: aconst_null
      84: putfield      #15                 // Field callCleanup:Lorg/apache/hadoop/hbase/ipc/RpcServer$CallCleanup;
      87: aload_3
      88: athrow
      89: return
    Exception table:
       from    to  target type
           0    28    62   Class java/lang/Exception
          34    54    62   Class java/lang/Exception
           0    28    81   any
          34    54    81   any
          62    82    81   any

  public synchronized void close();
    Code:
       0: aload_0
       1: invokevirtual #31                 // Method disposeSasl:()V
       4: aload_0
       5: getfield      #2                  // Field channel:Lorg/apache/hbase/thirdparty/io/netty/channel/Channel;
       8: invokeinterface #32,  1           // InterfaceMethod org/apache/hbase/thirdparty/io/netty/channel/Channel.close:()Lorg/apache/hbase/thirdparty/io/netty/channel/ChannelFuture;
      13: pop
      14: aload_0
      15: aconst_null
      16: putfield      #15                 // Field callCleanup:Lorg/apache/hadoop/hbase/ipc/RpcServer$CallCleanup;
      19: return

  public boolean isConnectionOpen();
    Code:
       0: aload_0
       1: getfield      #2                  // Field channel:Lorg/apache/hbase/thirdparty/io/netty/channel/Channel;
       4: invokeinterface #33,  1           // InterfaceMethod org/apache/hbase/thirdparty/io/netty/channel/Channel.isOpen:()Z
       9: ireturn

  public org.apache.hadoop.hbase.ipc.NettyServerCall createCall(int, org.apache.hbase.thirdparty.com.google.protobuf.BlockingService, org.apache.hbase.thirdparty.com.google.protobuf.Descriptors$MethodDescriptor, org.apache.hadoop.hbase.shaded.protobuf.generated.RPCProtos$RequestHeader, org.apache.hbase.thirdparty.com.google.protobuf.Message, org.apache.hadoop.hbase.CellScanner, long, java.net.InetAddress, int, org.apache.hadoop.hbase.ipc.RpcServer$CallCleanup);
    Code:
       0: new           #34                 // class org/apache/hadoop/hbase/ipc/NettyServerCall
       3: dup
       4: iload_1
       5: aload_2
       6: aload_3
       7: aload         4
       9: aload         5
      11: aload         6
      13: aload_0
      14: lload         7
      16: aload         9
      18: invokestatic  #35                 // Method java/lang/System.currentTimeMillis:()J
      21: iload         10
      23: aload_0
      24: getfield      #36                 // Field rpcServer:Lorg/apache/hadoop/hbase/ipc/RpcServer;
      27: getfield      #37                 // Field org/apache/hadoop/hbase/ipc/RpcServer.reservoir:Lorg/apache/hadoop/hbase/io/ByteBufferPool;
      30: aload_0
      31: getfield      #36                 // Field rpcServer:Lorg/apache/hadoop/hbase/ipc/RpcServer;
      34: getfield      #38                 // Field org/apache/hadoop/hbase/ipc/RpcServer.cellBlockBuilder:Lorg/apache/hadoop/hbase/ipc/CellBlockBuilder;
      37: aload         11
      39: invokespecial #39                 // Method org/apache/hadoop/hbase/ipc/NettyServerCall."<init>":(ILorg/apache/hbase/thirdparty/com/google/protobuf/BlockingService;Lorg/apache/hbase/thirdparty/com/google/protobuf/Descriptors$MethodDescriptor;Lorg/apache/hadoop/hbase/shaded/protobuf/generated/RPCProtos$RequestHeader;Lorg/apache/hbase/thirdparty/com/google/protobuf/Message;Lorg/apache/hadoop/hbase/CellScanner;Lorg/apache/hadoop/hbase/ipc/NettyServerRpcConnection;JLjava/net/InetAddress;JILorg/apache/hadoop/hbase/io/ByteBufferPool;Lorg/apache/hadoop/hbase/ipc/CellBlockBuilder;Lorg/apache/hadoop/hbase/ipc/RpcServer$CallCleanup;)V
      42: areturn

  protected void doRespond(org.apache.hadoop.hbase.ipc.RpcResponse);
    Code:
       0: aload_0
       1: getfield      #2                  // Field channel:Lorg/apache/hbase/thirdparty/io/netty/channel/Channel;
       4: aload_1
       5: invokeinterface #40,  2           // InterfaceMethod org/apache/hbase/thirdparty/io/netty/channel/Channel.writeAndFlush:(Ljava/lang/Object;)Lorg/apache/hbase/thirdparty/io/netty/channel/ChannelFuture;
      10: pop
      11: return

  public org.apache.hadoop.hbase.ipc.ServerCall createCall(int, org.apache.hbase.thirdparty.com.google.protobuf.BlockingService, org.apache.hbase.thirdparty.com.google.protobuf.Descriptors$MethodDescriptor, org.apache.hadoop.hbase.shaded.protobuf.generated.RPCProtos$RequestHeader, org.apache.hbase.thirdparty.com.google.protobuf.Message, org.apache.hadoop.hbase.CellScanner, long, java.net.InetAddress, int, org.apache.hadoop.hbase.ipc.RpcServer$CallCleanup);
    Code:
       0: aload_0
       1: iload_1
       2: aload_2
       3: aload_3
       4: aload         4
       6: aload         5
       8: aload         6
      10: lload         7
      12: aload         9
      14: iload         10
      16: aload         11
      18: invokevirtual #41                 // Method createCall:(ILorg/apache/hbase/thirdparty/com/google/protobuf/BlockingService;Lorg/apache/hbase/thirdparty/com/google/protobuf/Descriptors$MethodDescriptor;Lorg/apache/hadoop/hbase/shaded/protobuf/generated/RPCProtos$RequestHeader;Lorg/apache/hbase/thirdparty/com/google/protobuf/Message;Lorg/apache/hadoop/hbase/CellScanner;JLjava/net/InetAddress;ILorg/apache/hadoop/hbase/ipc/RpcServer$CallCleanup;)Lorg/apache/hadoop/hbase/ipc/NettyServerCall;
      21: areturn
}
