Compiled from "NettyRpcConnection.java"
class org.apache.hadoop.hbase.ipc.NettyRpcConnection extends org.apache.hadoop.hbase.ipc.RpcConnection {
  org.apache.hadoop.hbase.ipc.NettyRpcConnection(org.apache.hadoop.hbase.ipc.NettyRpcClient, org.apache.hadoop.hbase.ipc.ConnectionId) throws java.io.IOException;
    Code:
       0: aload_0
       1: aload_1
       2: getfield      #13                 // Field org/apache/hadoop/hbase/ipc/NettyRpcClient.conf:Lorg/apache/hadoop/conf/Configuration;
       5: getstatic     #14                 // Field org/apache/hadoop/hbase/ipc/AbstractRpcClient.WHEEL_TIMER:Lorg/apache/hbase/thirdparty/io/netty/util/HashedWheelTimer;
       8: aload_2
       9: aload_1
      10: getfield      #15                 // Field org/apache/hadoop/hbase/ipc/NettyRpcClient.clusterId:Ljava/lang/String;
      13: aload_1
      14: getfield      #16                 // Field org/apache/hadoop/hbase/ipc/NettyRpcClient.userProvider:Lorg/apache/hadoop/hbase/security/UserProvider;
      17: invokevirtual #17                 // Method org/apache/hadoop/hbase/security/UserProvider.isHBaseSecurityEnabled:()Z
      20: aload_1
      21: getfield      #18                 // Field org/apache/hadoop/hbase/ipc/NettyRpcClient.codec:Lorg/apache/hadoop/hbase/codec/Codec;
      24: aload_1
      25: getfield      #19                 // Field org/apache/hadoop/hbase/ipc/NettyRpcClient.compressor:Lorg/apache/hadoop/io/compress/CompressionCodec;
      28: invokespecial #20                 // Method org/apache/hadoop/hbase/ipc/RpcConnection."<init>":(Lorg/apache/hadoop/conf/Configuration;Lorg/apache/hbase/thirdparty/io/netty/util/HashedWheelTimer;Lorg/apache/hadoop/hbase/ipc/ConnectionId;Ljava/lang/String;ZLorg/apache/hadoop/hbase/codec/Codec;Lorg/apache/hadoop/io/compress/CompressionCodec;)V
      31: aload_0
      32: aload_1
      33: putfield      #6                  // Field rpcClient:Lorg/apache/hadoop/hbase/ipc/NettyRpcClient;
      36: aload_0
      37: invokevirtual #21                 // Method getConnectionHeaderPreamble:()[B
      40: astore_3
      41: aload_0
      42: aload_3
      43: arraylength
      44: invokestatic  #22                 // Method org/apache/hbase/thirdparty/io/netty/buffer/Unpooled.directBuffer:(I)Lorg/apache/hbase/thirdparty/io/netty/buffer/ByteBuf;
      47: aload_3
      48: invokevirtual #23                 // Method org/apache/hbase/thirdparty/io/netty/buffer/ByteBuf.writeBytes:([B)Lorg/apache/hbase/thirdparty/io/netty/buffer/ByteBuf;
      51: putfield      #5                  // Field connectionHeaderPreamble:Lorg/apache/hbase/thirdparty/io/netty/buffer/ByteBuf;
      54: aload_0
      55: invokevirtual #24                 // Method getConnectionHeader:()Lorg/apache/hadoop/hbase/shaded/protobuf/generated/RPCProtos$ConnectionHeader;
      58: astore        4
      60: aload_0
      61: iconst_4
      62: aload         4
      64: invokevirtual #25                 // Method org/apache/hadoop/hbase/shaded/protobuf/generated/RPCProtos$ConnectionHeader.getSerializedSize:()I
      67: iadd
      68: invokestatic  #22                 // Method org/apache/hbase/thirdparty/io/netty/buffer/Unpooled.directBuffer:(I)Lorg/apache/hbase/thirdparty/io/netty/buffer/ByteBuf;
      71: putfield      #10                 // Field connectionHeaderWithLength:Lorg/apache/hbase/thirdparty/io/netty/buffer/ByteBuf;
      74: aload_0
      75: getfield      #10                 // Field connectionHeaderWithLength:Lorg/apache/hbase/thirdparty/io/netty/buffer/ByteBuf;
      78: aload         4
      80: invokevirtual #25                 // Method org/apache/hadoop/hbase/shaded/protobuf/generated/RPCProtos$ConnectionHeader.getSerializedSize:()I
      83: invokevirtual #26                 // Method org/apache/hbase/thirdparty/io/netty/buffer/ByteBuf.writeInt:(I)Lorg/apache/hbase/thirdparty/io/netty/buffer/ByteBuf;
      86: pop
      87: aload         4
      89: new           #27                 // class org/apache/hbase/thirdparty/io/netty/buffer/ByteBufOutputStream
      92: dup
      93: aload_0
      94: getfield      #10                 // Field connectionHeaderWithLength:Lorg/apache/hbase/thirdparty/io/netty/buffer/ByteBuf;
      97: invokespecial #28                 // Method org/apache/hbase/thirdparty/io/netty/buffer/ByteBufOutputStream."<init>":(Lorg/apache/hbase/thirdparty/io/netty/buffer/ByteBuf;)V
     100: invokevirtual #29                 // Method org/apache/hadoop/hbase/shaded/protobuf/generated/RPCProtos$ConnectionHeader.writeTo:(Ljava/io/OutputStream;)V
     103: return

  protected synchronized void callTimeout(org.apache.hadoop.hbase.ipc.Call);
    Code:
       0: aload_0
       1: getfield      #3                  // Field channel:Lorg/apache/hbase/thirdparty/io/netty/channel/Channel;
       4: ifnull        33
       7: aload_0
       8: getfield      #3                  // Field channel:Lorg/apache/hbase/thirdparty/io/netty/channel/Channel;
      11: invokeinterface #30,  1           // InterfaceMethod org/apache/hbase/thirdparty/io/netty/channel/Channel.pipeline:()Lorg/apache/hbase/thirdparty/io/netty/channel/ChannelPipeline;
      16: new           #31                 // class org/apache/hadoop/hbase/ipc/CallEvent
      19: dup
      20: getstatic     #32                 // Field org/apache/hadoop/hbase/ipc/CallEvent$Type.TIMEOUT:Lorg/apache/hadoop/hbase/ipc/CallEvent$Type;
      23: aload_1
      24: invokespecial #33                 // Method org/apache/hadoop/hbase/ipc/CallEvent."<init>":(Lorg/apache/hadoop/hbase/ipc/CallEvent$Type;Lorg/apache/hadoop/hbase/ipc/Call;)V
      27: invokeinterface #34,  2           // InterfaceMethod org/apache/hbase/thirdparty/io/netty/channel/ChannelPipeline.fireUserEventTriggered:(Ljava/lang/Object;)Lorg/apache/hbase/thirdparty/io/netty/channel/ChannelPipeline;
      32: pop
      33: return

  public synchronized boolean isActive();
    Code:
       0: aload_0
       1: getfield      #3                  // Field channel:Lorg/apache/hbase/thirdparty/io/netty/channel/Channel;
       4: ifnull        11
       7: iconst_1
       8: goto          12
      11: iconst_0
      12: ireturn

  public synchronized void shutdown();
    Code:
       0: aload_0
       1: invokespecial #36                 // Method shutdown0:()V
       4: return

  public synchronized void cleanupConnection();
    Code:
       0: aload_0
       1: getfield      #5                  // Field connectionHeaderPreamble:Lorg/apache/hbase/thirdparty/io/netty/buffer/ByteBuf;
       4: ifnull        14
       7: aload_0
       8: getfield      #5                  // Field connectionHeaderPreamble:Lorg/apache/hbase/thirdparty/io/netty/buffer/ByteBuf;
      11: invokestatic  #37                 // Method org/apache/hbase/thirdparty/io/netty/util/ReferenceCountUtil.safeRelease:(Ljava/lang/Object;)V
      14: aload_0
      15: getfield      #10                 // Field connectionHeaderWithLength:Lorg/apache/hbase/thirdparty/io/netty/buffer/ByteBuf;
      18: ifnull        28
      21: aload_0
      22: getfield      #10                 // Field connectionHeaderWithLength:Lorg/apache/hbase/thirdparty/io/netty/buffer/ByteBuf;
      25: invokestatic  #37                 // Method org/apache/hbase/thirdparty/io/netty/util/ReferenceCountUtil.safeRelease:(Ljava/lang/Object;)V
      28: return

  public synchronized void sendRequest(org.apache.hadoop.hbase.ipc.Call, org.apache.hadoop.hbase.ipc.HBaseRpcController) throws java.io.IOException;
    Code:
       0: aload_0
       1: getfield      #11                 // Field reloginInProgress:Z
       4: ifeq          17
       7: new           #77                 // class java/io/IOException
      10: dup
      11: ldc           #117                // String Can not send request because relogin is in progress.
      13: invokespecial #118                // Method java/io/IOException."<init>":(Ljava/lang/String;)V
      16: athrow
      17: aload_2
      18: new           #119                // class org/apache/hadoop/hbase/ipc/NettyRpcConnection$5
      21: dup
      22: aload_0
      23: aload_1
      24: invokespecial #120                // Method org/apache/hadoop/hbase/ipc/NettyRpcConnection$5."<init>":(Lorg/apache/hadoop/hbase/ipc/NettyRpcConnection;Lorg/apache/hadoop/hbase/ipc/Call;)V
      27: new           #121                // class org/apache/hadoop/hbase/ipc/NettyRpcConnection$6
      30: dup
      31: aload_0
      32: aload_1
      33: invokespecial #122                // Method org/apache/hadoop/hbase/ipc/NettyRpcConnection$6."<init>":(Lorg/apache/hadoop/hbase/ipc/NettyRpcConnection;Lorg/apache/hadoop/hbase/ipc/Call;)V
      36: invokeinterface #123,  3          // InterfaceMethod org/apache/hadoop/hbase/ipc/HBaseRpcController.notifyOnCancel:(Lorg/apache/hbase/thirdparty/com/google/protobuf/RpcCallback;Lorg/apache/hadoop/hbase/ipc/HBaseRpcController$CancellationCallback;)V
      41: return

  static org.slf4j.Logger access$000();
    Code:
       0: getstatic     #12                 // Field LOG:Lorg/slf4j/Logger;
       3: areturn

  static boolean access$102(org.apache.hadoop.hbase.ipc.NettyRpcConnection, boolean);
    Code:
       0: aload_0
       1: iload_1
       2: dup_x1
       3: putfield      #11                 // Field reloginInProgress:Z
       6: ireturn

  static org.apache.hbase.thirdparty.io.netty.buffer.ByteBuf access$200(org.apache.hadoop.hbase.ipc.NettyRpcConnection);
    Code:
       0: aload_0
       1: getfield      #10                 // Field connectionHeaderWithLength:Lorg/apache/hbase/thirdparty/io/netty/buffer/ByteBuf;
       4: areturn

  static void access$300(org.apache.hadoop.hbase.ipc.NettyRpcConnection, org.apache.hbase.thirdparty.io.netty.channel.Channel) throws java.io.IOException;
    Code:
       0: aload_0
       1: aload_1
       2: invokespecial #9                  // Method established:(Lorg/apache/hbase/thirdparty/io/netty/channel/Channel;)V
       5: return

  static void access$400(org.apache.hadoop.hbase.ipc.NettyRpcConnection, java.lang.Throwable);
    Code:
       0: aload_0
       1: aload_1
       2: invokespecial #8                  // Method scheduleRelogin:(Ljava/lang/Throwable;)V
       5: return

  static void access$500(org.apache.hadoop.hbase.ipc.NettyRpcConnection, org.apache.hbase.thirdparty.io.netty.channel.Channel, java.io.IOException);
    Code:
       0: aload_0
       1: aload_1
       2: aload_2
       3: invokespecial #7                  // Method failInit:(Lorg/apache/hbase/thirdparty/io/netty/channel/Channel;Ljava/io/IOException;)V
       6: return

  static org.apache.hadoop.hbase.ipc.NettyRpcClient access$600(org.apache.hadoop.hbase.ipc.NettyRpcConnection);
    Code:
       0: aload_0
       1: getfield      #6                  // Field rpcClient:Lorg/apache/hadoop/hbase/ipc/NettyRpcClient;
       4: areturn

  static org.apache.hbase.thirdparty.io.netty.buffer.ByteBuf access$700(org.apache.hadoop.hbase.ipc.NettyRpcConnection);
    Code:
       0: aload_0
       1: getfield      #5                  // Field connectionHeaderPreamble:Lorg/apache/hbase/thirdparty/io/netty/buffer/ByteBuf;
       4: areturn

  static void access$800(org.apache.hadoop.hbase.ipc.NettyRpcConnection, org.apache.hbase.thirdparty.io.netty.channel.Channel);
    Code:
       0: aload_0
       1: aload_1
       2: invokespecial #4                  // Method saslNegotiate:(Lorg/apache/hbase/thirdparty/io/netty/channel/Channel;)V
       5: return

  static org.apache.hbase.thirdparty.io.netty.channel.Channel access$900(org.apache.hadoop.hbase.ipc.NettyRpcConnection);
    Code:
       0: aload_0
       1: getfield      #3                  // Field channel:Lorg/apache/hbase/thirdparty/io/netty/channel/Channel;
       4: areturn

  static void access$1000(org.apache.hadoop.hbase.ipc.NettyRpcConnection);
    Code:
       0: aload_0
       1: invokespecial #2                  // Method connect:()V
       4: return

  static void access$1100(org.apache.hadoop.hbase.ipc.NettyRpcConnection, org.apache.hbase.thirdparty.io.netty.channel.Channel, org.apache.hadoop.hbase.ipc.Call);
    Code:
       0: aload_0
       1: aload_1
       2: aload_2
       3: invokespecial #1                  // Method write:(Lorg/apache/hbase/thirdparty/io/netty/channel/Channel;Lorg/apache/hadoop/hbase/ipc/Call;)V
       6: return

  static {};
    Code:
       0: ldc           #124                // class org/apache/hadoop/hbase/ipc/NettyRpcConnection
       2: invokestatic  #125                // Method org/slf4j/LoggerFactory.getLogger:(Ljava/lang/Class;)Lorg/slf4j/Logger;
       5: putstatic     #12                 // Field LOG:Lorg/slf4j/Logger;
       8: ldc           #126                // String Relogin
      10: invokestatic  #127                // Method org/apache/hadoop/hbase/util/Threads.newDaemonThreadFactory:(Ljava/lang/String;)Ljava/util/concurrent/ThreadFactory;
      13: invokestatic  #128                // Method java/util/concurrent/Executors.newSingleThreadScheduledExecutor:(Ljava/util/concurrent/ThreadFactory;)Ljava/util/concurrent/ScheduledExecutorService;
      16: putstatic     #57                 // Field RELOGIN_EXECUTOR:Ljava/util/concurrent/ScheduledExecutorService;
      19: return
}
