Compiled from "NettyRpcServerRequestDecoder.java"
class org.apache.hadoop.hbase.ipc.NettyRpcServerRequestDecoder extends org.apache.hbase.thirdparty.io.netty.channel.ChannelInboundHandlerAdapter {
  public org.apache.hadoop.hbase.ipc.NettyRpcServerRequestDecoder(org.apache.hbase.thirdparty.io.netty.channel.group.ChannelGroup, org.apache.hadoop.hbase.ipc.MetricsHBaseServer);
    Code:
       0: aload_0
       1: invokespecial #1                  // Method org/apache/hbase/thirdparty/io/netty/channel/ChannelInboundHandlerAdapter."<init>":()V
       4: aload_0
       5: aload_1
       6: putfield      #2                  // Field allChannels:Lorg/apache/hbase/thirdparty/io/netty/channel/group/ChannelGroup;
       9: aload_0
      10: aload_2
      11: putfield      #3                  // Field metrics:Lorg/apache/hadoop/hbase/ipc/MetricsHBaseServer;
      14: return

  void setConnection(org.apache.hadoop.hbase.ipc.NettyServerRpcConnection);
    Code:
       0: aload_0
       1: aload_1
       2: putfield      #4                  // Field connection:Lorg/apache/hadoop/hbase/ipc/NettyServerRpcConnection;
       5: return

  public void channelActive(org.apache.hbase.thirdparty.io.netty.channel.ChannelHandlerContext) throws java.lang.Exception;
    Code:
       0: aload_0
       1: getfield      #2                  // Field allChannels:Lorg/apache/hbase/thirdparty/io/netty/channel/group/ChannelGroup;
       4: aload_1
       5: invokeinterface #5,  1            // InterfaceMethod org/apache/hbase/thirdparty/io/netty/channel/ChannelHandlerContext.channel:()Lorg/apache/hbase/thirdparty/io/netty/channel/Channel;
      10: invokeinterface #6,  2            // InterfaceMethod org/apache/hbase/thirdparty/io/netty/channel/group/ChannelGroup.add:(Ljava/lang/Object;)Z
      15: pop
      16: getstatic     #7                  // Field org/apache/hadoop/hbase/ipc/NettyRpcServer.LOG:Lorg/slf4j/Logger;
      19: ldc           #8                  // String Connection {}; # active connections={}
      21: aload_1
      22: invokeinterface #5,  1            // InterfaceMethod org/apache/hbase/thirdparty/io/netty/channel/ChannelHandlerContext.channel:()Lorg/apache/hbase/thirdparty/io/netty/channel/Channel;
      27: invokeinterface #9,  1            // InterfaceMethod org/apache/hbase/thirdparty/io/netty/channel/Channel.remoteAddress:()Ljava/net/SocketAddress;
      32: aload_0
      33: getfield      #2                  // Field allChannels:Lorg/apache/hbase/thirdparty/io/netty/channel/group/ChannelGroup;
      36: invokeinterface #10,  1           // InterfaceMethod org/apache/hbase/thirdparty/io/netty/channel/group/ChannelGroup.size:()I
      41: iconst_1
      42: isub
      43: invokestatic  #11                 // Method java/lang/Integer.valueOf:(I)Ljava/lang/Integer;
      46: invokeinterface #12,  4           // InterfaceMethod org/slf4j/Logger.trace:(Ljava/lang/String;Ljava/lang/Object;Ljava/lang/Object;)V
      51: aload_0
      52: aload_1
      53: invokespecial #13                 // Method org/apache/hbase/thirdparty/io/netty/channel/ChannelInboundHandlerAdapter.channelActive:(Lorg/apache/hbase/thirdparty/io/netty/channel/ChannelHandlerContext;)V
      56: return

  public void channelRead(org.apache.hbase.thirdparty.io.netty.channel.ChannelHandlerContext, java.lang.Object) throws java.lang.Exception;
    Code:
       0: aload_2
       1: checkcast     #14                 // class org/apache/hbase/thirdparty/io/netty/buffer/ByteBuf
       4: astore_3
       5: aload_0
       6: getfield      #3                  // Field metrics:Lorg/apache/hadoop/hbase/ipc/MetricsHBaseServer;
       9: aload_3
      10: invokevirtual #15                 // Method org/apache/hbase/thirdparty/io/netty/buffer/ByteBuf.readableBytes:()I
      13: iconst_4
      14: iadd
      15: invokevirtual #16                 // Method org/apache/hadoop/hbase/ipc/MetricsHBaseServer.receivedBytes:(I)V
      18: aload_0
      19: getfield      #4                  // Field connection:Lorg/apache/hadoop/hbase/ipc/NettyServerRpcConnection;
      22: aload_3
      23: invokevirtual #17                 // Method org/apache/hadoop/hbase/ipc/NettyServerRpcConnection.process:(Lorg/apache/hbase/thirdparty/io/netty/buffer/ByteBuf;)V
      26: return

  public void channelInactive(org.apache.hbase.thirdparty.io.netty.channel.ChannelHandlerContext) throws java.lang.Exception;
    Code:
       0: aload_0
       1: getfield      #2                  // Field allChannels:Lorg/apache/hbase/thirdparty/io/netty/channel/group/ChannelGroup;
       4: aload_1
       5: invokeinterface #5,  1            // InterfaceMethod org/apache/hbase/thirdparty/io/netty/channel/ChannelHandlerContext.channel:()Lorg/apache/hbase/thirdparty/io/netty/channel/Channel;
      10: invokeinterface #18,  2           // InterfaceMethod org/apache/hbase/thirdparty/io/netty/channel/group/ChannelGroup.remove:(Ljava/lang/Object;)Z
      15: pop
      16: getstatic     #7                  // Field org/apache/hadoop/hbase/ipc/NettyRpcServer.LOG:Lorg/slf4j/Logger;
      19: ldc           #19                 // String Disconnection {}; # active connections={}
      21: aload_1
      22: invokeinterface #5,  1            // InterfaceMethod org/apache/hbase/thirdparty/io/netty/channel/ChannelHandlerContext.channel:()Lorg/apache/hbase/thirdparty/io/netty/channel/Channel;
      27: invokeinterface #9,  1            // InterfaceMethod org/apache/hbase/thirdparty/io/netty/channel/Channel.remoteAddress:()Ljava/net/SocketAddress;
      32: aload_0
      33: getfield      #2                  // Field allChannels:Lorg/apache/hbase/thirdparty/io/netty/channel/group/ChannelGroup;
      36: invokeinterface #10,  1           // InterfaceMethod org/apache/hbase/thirdparty/io/netty/channel/group/ChannelGroup.size:()I
      41: iconst_1
      42: isub
      43: invokestatic  #11                 // Method java/lang/Integer.valueOf:(I)Ljava/lang/Integer;
      46: invokeinterface #12,  4           // InterfaceMethod org/slf4j/Logger.trace:(Ljava/lang/String;Ljava/lang/Object;Ljava/lang/Object;)V
      51: aload_0
      52: aload_1
      53: invokespecial #20                 // Method org/apache/hbase/thirdparty/io/netty/channel/ChannelInboundHandlerAdapter.channelInactive:(Lorg/apache/hbase/thirdparty/io/netty/channel/ChannelHandlerContext;)V
      56: return

  public void exceptionCaught(org.apache.hbase.thirdparty.io.netty.channel.ChannelHandlerContext, java.lang.Throwable);
    Code:
       0: aload_0
       1: getfield      #2                  // Field allChannels:Lorg/apache/hbase/thirdparty/io/netty/channel/group/ChannelGroup;
       4: aload_1
       5: invokeinterface #5,  1            // InterfaceMethod org/apache/hbase/thirdparty/io/netty/channel/ChannelHandlerContext.channel:()Lorg/apache/hbase/thirdparty/io/netty/channel/Channel;
      10: invokeinterface #18,  2           // InterfaceMethod org/apache/hbase/thirdparty/io/netty/channel/group/ChannelGroup.remove:(Ljava/lang/Object;)Z
      15: pop
      16: getstatic     #7                  // Field org/apache/hadoop/hbase/ipc/NettyRpcServer.LOG:Lorg/slf4j/Logger;
      19: ldc           #21                 // String Connection {}; caught unexpected downstream exception.
      21: aload_1
      22: invokeinterface #5,  1            // InterfaceMethod org/apache/hbase/thirdparty/io/netty/channel/ChannelHandlerContext.channel:()Lorg/apache/hbase/thirdparty/io/netty/channel/Channel;
      27: invokeinterface #9,  1            // InterfaceMethod org/apache/hbase/thirdparty/io/netty/channel/Channel.remoteAddress:()Ljava/net/SocketAddress;
      32: aload_2
      33: invokevirtual #22                 // Method java/lang/Throwable.getCause:()Ljava/lang/Throwable;
      36: invokeinterface #12,  4           // InterfaceMethod org/slf4j/Logger.trace:(Ljava/lang/String;Ljava/lang/Object;Ljava/lang/Object;)V
      41: aload_1
      42: invokeinterface #5,  1            // InterfaceMethod org/apache/hbase/thirdparty/io/netty/channel/ChannelHandlerContext.channel:()Lorg/apache/hbase/thirdparty/io/netty/channel/Channel;
      47: invokeinterface #23,  1           // InterfaceMethod org/apache/hbase/thirdparty/io/netty/channel/Channel.close:()Lorg/apache/hbase/thirdparty/io/netty/channel/ChannelFuture;
      52: pop
      53: return
}
