Compiled from "NettyRpcServerResponseEncoder.java"
class org.apache.hadoop.hbase.ipc.NettyRpcServerResponseEncoder extends org.apache.hbase.thirdparty.io.netty.channel.ChannelOutboundHandlerAdapter {
  org.apache.hadoop.hbase.ipc.NettyRpcServerResponseEncoder(org.apache.hadoop.hbase.ipc.MetricsHBaseServer);
    Code:
       0: aload_0
       1: invokespecial #1                  // Method org/apache/hbase/thirdparty/io/netty/channel/ChannelOutboundHandlerAdapter."<init>":()V
       4: aload_0
       5: aload_1
       6: putfield      #2                  // Field metrics:Lorg/apache/hadoop/hbase/ipc/MetricsHBaseServer;
       9: return

  public void write(org.apache.hbase.thirdparty.io.netty.channel.ChannelHandlerContext, java.lang.Object, org.apache.hbase.thirdparty.io.netty.channel.ChannelPromise) throws java.lang.Exception;
    Code:
       0: aload_2
       1: instanceof    #3                  // class org/apache/hadoop/hbase/ipc/RpcResponse
       4: ifeq          56
       7: aload_2
       8: checkcast     #3                  // class org/apache/hadoop/hbase/ipc/RpcResponse
      11: astore        4
      13: aload         4
      15: invokeinterface #4,  1            // InterfaceMethod org/apache/hadoop/hbase/ipc/RpcResponse.getResponse:()Lorg/apache/hadoop/hbase/ipc/BufferChain;
      20: astore        5
      22: aload_1
      23: aload         5
      25: invokevirtual #5                  // Method org/apache/hadoop/hbase/ipc/BufferChain.getBuffers:()[Ljava/nio/ByteBuffer;
      28: invokestatic  #6                  // Method org/apache/hbase/thirdparty/io/netty/buffer/Unpooled.wrappedBuffer:([Ljava/nio/ByteBuffer;)Lorg/apache/hbase/thirdparty/io/netty/buffer/ByteBuf;
      31: aload_3
      32: invokeinterface #7,  3            // InterfaceMethod org/apache/hbase/thirdparty/io/netty/channel/ChannelHandlerContext.write:(Ljava/lang/Object;Lorg/apache/hbase/thirdparty/io/netty/channel/ChannelPromise;)Lorg/apache/hbase/thirdparty/io/netty/channel/ChannelFuture;
      37: aload_0
      38: aload         4
      40: aload         5
      42: invokedynamic #8,  0              // InvokeDynamic #0:operationComplete:(Lorg/apache/hadoop/hbase/ipc/NettyRpcServerResponseEncoder;Lorg/apache/hadoop/hbase/ipc/RpcResponse;Lorg/apache/hadoop/hbase/ipc/BufferChain;)Lorg/apache/hbase/thirdparty/io/netty/util/concurrent/GenericFutureListener;
      47: invokeinterface #9,  2            // InterfaceMethod org/apache/hbase/thirdparty/io/netty/channel/ChannelFuture.addListener:(Lorg/apache/hbase/thirdparty/io/netty/util/concurrent/GenericFutureListener;)Lorg/apache/hbase/thirdparty/io/netty/channel/ChannelFuture;
      52: pop
      53: goto          65
      56: aload_1
      57: aload_2
      58: aload_3
      59: invokeinterface #7,  3            // InterfaceMethod org/apache/hbase/thirdparty/io/netty/channel/ChannelHandlerContext.write:(Ljava/lang/Object;Lorg/apache/hbase/thirdparty/io/netty/channel/ChannelPromise;)Lorg/apache/hbase/thirdparty/io/netty/channel/ChannelFuture;
      64: pop
      65: return
}
