Compiled from "NonLeafExpressionNode.java"
public class org.apache.hadoop.hbase.security.visibility.expression.NonLeafExpressionNode implements org.apache.hadoop.hbase.security.visibility.expression.ExpressionNode {
  public org.apache.hadoop.hbase.security.visibility.expression.NonLeafExpressionNode();
    Code:
       0: aload_0
       1: invokespecial #1                  // Method java/lang/Object."<init>":()V
       4: aload_0
       5: new           #2                  // class java/util/ArrayList
       8: dup
       9: iconst_2
      10: invokespecial #3                  // Method java/util/ArrayList."<init>":(I)V
      13: putfield      #4                  // Field childExps:Ljava/util/List;
      16: return

  public org.apache.hadoop.hbase.security.visibility.expression.NonLeafExpressionNode(org.apache.hadoop.hbase.security.visibility.expression.Operator);
    Code:
       0: aload_0
       1: invokespecial #1                  // Method java/lang/Object."<init>":()V
       4: aload_0
       5: new           #2                  // class java/util/ArrayList
       8: dup
       9: iconst_2
      10: invokespecial #3                  // Method java/util/ArrayList."<init>":(I)V
      13: putfield      #4                  // Field childExps:Ljava/util/List;
      16: aload_0
      17: aload_1
      18: putfield      #5                  // Field op:Lorg/apache/hadoop/hbase/security/visibility/expression/Operator;
      21: return

  public org.apache.hadoop.hbase.security.visibility.expression.NonLeafExpressionNode(org.apache.hadoop.hbase.security.visibility.expression.Operator, java.util.List<org.apache.hadoop.hbase.security.visibility.expression.ExpressionNode>);
    Code:
       0: aload_0
       1: invokespecial #1                  // Method java/lang/Object."<init>":()V
       4: aload_0
       5: new           #2                  // class java/util/ArrayList
       8: dup
       9: iconst_2
      10: invokespecial #3                  // Method java/util/ArrayList."<init>":(I)V
      13: putfield      #4                  // Field childExps:Ljava/util/List;
      16: aload_0
      17: aload_1
      18: putfield      #5                  // Field op:Lorg/apache/hadoop/hbase/security/visibility/expression/Operator;
      21: aload_1
      22: getstatic     #6                  // Field org/apache/hadoop/hbase/security/visibility/expression/Operator.NOT:Lorg/apache/hadoop/hbase/security/visibility/expression/Operator;
      25: if_acmpne     67
      28: aload_2
      29: invokeinterface #7,  1            // InterfaceMethod java/util/List.size:()I
      34: iconst_1
      35: if_icmple     67
      38: new           #8                  // class java/lang/IllegalArgumentException
      41: dup
      42: new           #9                  // class java/lang/StringBuilder
      45: dup
      46: invokespecial #10                 // Method java/lang/StringBuilder."<init>":()V
      49: getstatic     #6                  // Field org/apache/hadoop/hbase/security/visibility/expression/Operator.NOT:Lorg/apache/hadoop/hbase/security/visibility/expression/Operator;
      52: invokevirtual #11                 // Method java/lang/StringBuilder.append:(Ljava/lang/Object;)Ljava/lang/StringBuilder;
      55: ldc           #12                 // String  should be on 1 child expression
      57: invokevirtual #13                 // Method java/lang/StringBuilder.append:(Ljava/lang/String;)Ljava/lang/StringBuilder;
      60: invokevirtual #14                 // Method java/lang/StringBuilder.toString:()Ljava/lang/String;
      63: invokespecial #15                 // Method java/lang/IllegalArgumentException."<init>":(Ljava/lang/String;)V
      66: athrow
      67: aload_0
      68: aload_2
      69: putfield      #4                  // Field childExps:Ljava/util/List;
      72: return

  public org.apache.hadoop.hbase.security.visibility.expression.NonLeafExpressionNode(org.apache.hadoop.hbase.security.visibility.expression.Operator, org.apache.hadoop.hbase.security.visibility.expression.ExpressionNode...);
    Code:
       0: aload_0
       1: invokespecial #1                  // Method java/lang/Object."<init>":()V
       4: aload_0
       5: new           #2                  // class java/util/ArrayList
       8: dup
       9: iconst_2
      10: invokespecial #3                  // Method java/util/ArrayList."<init>":(I)V
      13: putfield      #4                  // Field childExps:Ljava/util/List;
      16: aload_0
      17: aload_1
      18: putfield      #5                  // Field op:Lorg/apache/hadoop/hbase/security/visibility/expression/Operator;
      21: new           #2                  // class java/util/ArrayList
      24: dup
      25: invokespecial #16                 // Method java/util/ArrayList."<init>":()V
      28: astore_3
      29: aload_3
      30: aload_2
      31: invokestatic  #17                 // Method java/util/Collections.addAll:(Ljava/util/Collection;[Ljava/lang/Object;)Z
      34: pop
      35: aload_0
      36: aload_3
      37: putfield      #4                  // Field childExps:Ljava/util/List;
      40: return

  public org.apache.hadoop.hbase.security.visibility.expression.Operator getOperator();
    Code:
       0: aload_0
       1: getfield      #5                  // Field op:Lorg/apache/hadoop/hbase/security/visibility/expression/Operator;
       4: areturn

  public java.util.List<org.apache.hadoop.hbase.security.visibility.expression.ExpressionNode> getChildExps();
    Code:
       0: aload_0
       1: getfield      #4                  // Field childExps:Ljava/util/List;
       4: areturn

  public void addChildExp(org.apache.hadoop.hbase.security.visibility.expression.ExpressionNode);
    Code:
       0: aload_0
       1: getfield      #5                  // Field op:Lorg/apache/hadoop/hbase/security/visibility/expression/Operator;
       4: getstatic     #6                  // Field org/apache/hadoop/hbase/security/visibility/expression/Operator.NOT:Lorg/apache/hadoop/hbase/security/visibility/expression/Operator;
       7: if_acmpne     52
      10: aload_0
      11: getfield      #4                  // Field childExps:Ljava/util/List;
      14: invokeinterface #7,  1            // InterfaceMethod java/util/List.size:()I
      19: iconst_1
      20: if_icmpne     52
      23: new           #18                 // class java/lang/IllegalStateException
      26: dup
      27: new           #9                  // class java/lang/StringBuilder
      30: dup
      31: invokespecial #10                 // Method java/lang/StringBuilder."<init>":()V
      34: getstatic     #6                  // Field org/apache/hadoop/hbase/security/visibility/expression/Operator.NOT:Lorg/apache/hadoop/hbase/security/visibility/expression/Operator;
      37: invokevirtual #11                 // Method java/lang/StringBuilder.append:(Ljava/lang/Object;)Ljava/lang/StringBuilder;
      40: ldc           #12                 // String  should be on 1 child expression
      42: invokevirtual #13                 // Method java/lang/StringBuilder.append:(Ljava/lang/String;)Ljava/lang/StringBuilder;
      45: invokevirtual #14                 // Method java/lang/StringBuilder.toString:()Ljava/lang/String;
      48: invokespecial #19                 // Method java/lang/IllegalStateException."<init>":(Ljava/lang/String;)V
      51: athrow
      52: aload_0
      53: getfield      #4                  // Field childExps:Ljava/util/List;
      56: aload_1
      57: invokeinterface #20,  2           // InterfaceMethod java/util/List.add:(Ljava/lang/Object;)Z
      62: pop
      63: return

  public void addChildExps(java.util.List<org.apache.hadoop.hbase.security.visibility.expression.ExpressionNode>);
    Code:
       0: aload_0
       1: getfield      #4                  // Field childExps:Ljava/util/List;
       4: aload_1
       5: invokeinterface #21,  2           // InterfaceMethod java/util/List.addAll:(Ljava/util/Collection;)Z
      10: pop
      11: return

  public java.lang.String toString();
    Code:
       0: new           #9                  // class java/lang/StringBuilder
       3: dup
       4: ldc           #22                 // String (
       6: invokespecial #23                 // Method java/lang/StringBuilder."<init>":(Ljava/lang/String;)V
       9: astore_1
      10: aload_0
      11: getfield      #5                  // Field op:Lorg/apache/hadoop/hbase/security/visibility/expression/Operator;
      14: getstatic     #6                  // Field org/apache/hadoop/hbase/security/visibility/expression/Operator.NOT:Lorg/apache/hadoop/hbase/security/visibility/expression/Operator;
      17: if_acmpne     29
      20: aload_1
      21: aload_0
      22: getfield      #5                  // Field op:Lorg/apache/hadoop/hbase/security/visibility/expression/Operator;
      25: invokevirtual #11                 // Method java/lang/StringBuilder.append:(Ljava/lang/Object;)Ljava/lang/StringBuilder;
      28: pop
      29: iconst_0
      30: istore_2
      31: iload_2
      32: aload_0
      33: getfield      #4                  // Field childExps:Ljava/util/List;
      36: invokeinterface #7,  1            // InterfaceMethod java/util/List.size:()I
      41: if_icmpge     112
      44: aload_1
      45: aload_0
      46: getfield      #4                  // Field childExps:Ljava/util/List;
      49: iload_2
      50: invokeinterface #24,  2           // InterfaceMethod java/util/List.get:(I)Ljava/lang/Object;
      55: invokevirtual #11                 // Method java/lang/StringBuilder.append:(Ljava/lang/Object;)Ljava/lang/StringBuilder;
      58: pop
      59: iload_2
      60: aload_0
      61: getfield      #4                  // Field childExps:Ljava/util/List;
      64: invokeinterface #7,  1            // InterfaceMethod java/util/List.size:()I
      69: iconst_1
      70: isub
      71: if_icmpge     106
      74: aload_1
      75: new           #9                  // class java/lang/StringBuilder
      78: dup
      79: invokespecial #10                 // Method java/lang/StringBuilder."<init>":()V
      82: ldc           #25                 // String
      84: invokevirtual #13                 // Method java/lang/StringBuilder.append:(Ljava/lang/String;)Ljava/lang/StringBuilder;
      87: aload_0
      88: getfield      #5                  // Field op:Lorg/apache/hadoop/hbase/security/visibility/expression/Operator;
      91: invokevirtual #11                 // Method java/lang/StringBuilder.append:(Ljava/lang/Object;)Ljava/lang/StringBuilder;
      94: ldc           #25                 // String
      96: invokevirtual #13                 // Method java/lang/StringBuilder.append:(Ljava/lang/String;)Ljava/lang/StringBuilder;
      99: invokevirtual #14                 // Method java/lang/StringBuilder.toString:()Ljava/lang/String;
     102: invokevirtual #13                 // Method java/lang/StringBuilder.append:(Ljava/lang/String;)Ljava/lang/StringBuilder;
     105: pop
     106: iinc          2, 1
     109: goto          31
     112: aload_1
     113: ldc           #26                 // String )
     115: invokevirtual #13                 // Method java/lang/StringBuilder.append:(Ljava/lang/String;)Ljava/lang/StringBuilder;
     118: pop
     119: aload_1
     120: invokevirtual #14                 // Method java/lang/StringBuilder.toString:()Ljava/lang/String;
     123: areturn

  public boolean isSingleNode();
    Code:
       0: aload_0
       1: getfield      #5                  // Field op:Lorg/apache/hadoop/hbase/security/visibility/expression/Operator;
       4: getstatic     #6                  // Field org/apache/hadoop/hbase/security/visibility/expression/Operator.NOT:Lorg/apache/hadoop/hbase/security/visibility/expression/Operator;
       7: if_acmpne     14
      10: iconst_1
      11: goto          15
      14: iconst_0
      15: ireturn

  public org.apache.hadoop.hbase.security.visibility.expression.NonLeafExpressionNode deepClone();
    Code:
       0: new           #27                 // class org/apache/hadoop/hbase/security/visibility/expression/NonLeafExpressionNode
       3: dup
       4: aload_0
       5: getfield      #5                  // Field op:Lorg/apache/hadoop/hbase/security/visibility/expression/Operator;
       8: invokespecial #28                 // Method "<init>":(Lorg/apache/hadoop/hbase/security/visibility/expression/Operator;)V
      11: astore_1
      12: aload_0
      13: getfield      #4                  // Field childExps:Ljava/util/List;
      16: invokeinterface #29,  1           // InterfaceMethod java/util/List.iterator:()Ljava/util/Iterator;
      21: astore_2
      22: aload_2
      23: invokeinterface #30,  1           // InterfaceMethod java/util/Iterator.hasNext:()Z
      28: ifeq          54
      31: aload_2
      32: invokeinterface #31,  1           // InterfaceMethod java/util/Iterator.next:()Ljava/lang/Object;
      37: checkcast     #32                 // class org/apache/hadoop/hbase/security/visibility/expression/ExpressionNode
      40: astore_3
      41: aload_1
      42: aload_3
      43: invokeinterface #33,  1           // InterfaceMethod org/apache/hadoop/hbase/security/visibility/expression/ExpressionNode.deepClone:()Lorg/apache/hadoop/hbase/security/visibility/expression/ExpressionNode;
      48: invokevirtual #34                 // Method addChildExp:(Lorg/apache/hadoop/hbase/security/visibility/expression/ExpressionNode;)V
      51: goto          22
      54: aload_1
      55: areturn

  public org.apache.hadoop.hbase.security.visibility.expression.ExpressionNode deepClone();
    Code:
       0: aload_0
       1: invokevirtual #35                 // Method deepClone:()Lorg/apache/hadoop/hbase/security/visibility/expression/NonLeafExpressionNode;
       4: areturn
}
