Compiled from "NoWritesViolationPolicyEnforcement.java"
public class org.apache.hadoop.hbase.quotas.policies.NoWritesViolationPolicyEnforcement extends org.apache.hadoop.hbase.quotas.policies.DefaultViolationPolicyEnforcement {
  public org.apache.hadoop.hbase.quotas.policies.NoWritesViolationPolicyEnforcement();
    Code:
       0: aload_0
       1: invokespecial #1                  // Method org/apache/hadoop/hbase/quotas/policies/DefaultViolationPolicyEnforcement."<init>":()V
       4: return

  public void enable();
    Code:
       0: return

  public void disable();
    Code:
       0: return

  public void check(org.apache.hadoop.hbase.client.Mutation) throws org.apache.hadoop.hbase.quotas.SpaceLimitingException;
    Code:
       0: aload_1
       1: instanceof    #2                  // class org/apache/hadoop/hbase/client/Append
       4: ifne          28
       7: aload_1
       8: instanceof    #3                  // class org/apache/hadoop/hbase/client/Delete
      11: ifne          28
      14: aload_1
      15: instanceof    #4                  // class org/apache/hadoop/hbase/client/Increment
      18: ifne          28
      21: aload_1
      22: instanceof    #5                  // class org/apache/hadoop/hbase/client/Put
      25: ifeq          65
      28: new           #6                  // class org/apache/hadoop/hbase/quotas/SpaceLimitingException
      31: dup
      32: aload_0
      33: invokevirtual #7                  // Method getPolicyName:()Ljava/lang/String;
      36: new           #8                  // class java/lang/StringBuilder
      39: dup
      40: invokespecial #9                  // Method java/lang/StringBuilder."<init>":()V
      43: aload_1
      44: invokevirtual #10                 // Method java/lang/Object.getClass:()Ljava/lang/Class;
      47: invokevirtual #11                 // Method java/lang/Class.getSimpleName:()Ljava/lang/String;
      50: invokevirtual #12                 // Method java/lang/StringBuilder.append:(Ljava/lang/String;)Ljava/lang/StringBuilder;
      53: ldc           #13                 // String s are disallowed due to a space quota.
      55: invokevirtual #12                 // Method java/lang/StringBuilder.append:(Ljava/lang/String;)Ljava/lang/StringBuilder;
      58: invokevirtual #14                 // Method java/lang/StringBuilder.toString:()Ljava/lang/String;
      61: invokespecial #15                 // Method org/apache/hadoop/hbase/quotas/SpaceLimitingException."<init>":(Ljava/lang/String;Ljava/lang/String;)V
      64: athrow
      65: return

  public java.lang.String getPolicyName();
    Code:
       0: getstatic     #16                 // Field org/apache/hadoop/hbase/quotas/SpaceViolationPolicy.NO_WRITES:Lorg/apache/hadoop/hbase/quotas/SpaceViolationPolicy;
       3: invokevirtual #17                 // Method org/apache/hadoop/hbase/quotas/SpaceViolationPolicy.name:()Ljava/lang/String;
       6: areturn
}
