Compiled from "NullComparator.java"
public class org.apache.hadoop.hbase.filter.NullComparator extends org.apache.hadoop.hbase.filter.ByteArrayComparable {
  public org.apache.hadoop.hbase.filter.NullComparator();
    Code:
       0: aload_0
       1: iconst_0
       2: newarray       byte
       4: invokespecial #1                  // Method org/apache/hadoop/hbase/filter/ByteArrayComparable."<init>":([B)V
       7: return

  public int compareTo(byte[]);
    Code:
       0: aload_1
       1: ifnull        8
       4: iconst_1
       5: goto          9
       8: iconst_0
       9: ireturn

  public boolean equals(java.lang.Object);
    Code:
       0: aload_1
       1: ifnonnull     8
       4: iconst_1
       5: goto          9
       8: iconst_0
       9: ireturn

  public int hashCode();
    Code:
       0: iconst_0
       1: ireturn

  public int compareTo(byte[], int, int);
    Code:
       0: aload_0
       1: aload_1
       2: invokevirtual #2                  // Method compareTo:([B)I
       5: ireturn

  public int compareTo(java.nio.ByteBuffer, int, int);
    Code:
       0: aload_1
       1: ifnull        8
       4: iconst_1
       5: goto          9
       8: iconst_0
       9: ireturn

  public byte[] toByteArray();
    Code:
       0: invokestatic  #3                  // Method org/apache/hadoop/hbase/shaded/protobuf/generated/ComparatorProtos$NullComparator.newBuilder:()Lorg/apache/hadoop/hbase/shaded/protobuf/generated/ComparatorProtos$NullComparator$Builder;
       3: astore_1
       4: aload_1
       5: invokevirtual #4                  // Method org/apache/hadoop/hbase/shaded/protobuf/generated/ComparatorProtos$NullComparator$Builder.build:()Lorg/apache/hadoop/hbase/shaded/protobuf/generated/ComparatorProtos$NullComparator;
       8: invokevirtual #5                  // Method org/apache/hadoop/hbase/shaded/protobuf/generated/ComparatorProtos$NullComparator.toByteArray:()[B
      11: areturn

  public static org.apache.hadoop.hbase.filter.NullComparator parseFrom(byte[]) throws org.apache.hadoop.hbase.exceptions.DeserializationException;
    Code:
       0: aload_0
       1: invokestatic  #6                  // Method org/apache/hadoop/hbase/shaded/protobuf/generated/ComparatorProtos$NullComparator.parseFrom:([B)Lorg/apache/hadoop/hbase/shaded/protobuf/generated/ComparatorProtos$NullComparator;
       4: pop
       5: goto          18
       8: astore_1
       9: new           #8                  // class org/apache/hadoop/hbase/exceptions/DeserializationException
      12: dup
      13: aload_1
      14: invokespecial #9                  // Method org/apache/hadoop/hbase/exceptions/DeserializationException."<init>":(Ljava/lang/Throwable;)V
      17: athrow
      18: new           #10                 // class org/apache/hadoop/hbase/filter/NullComparator
      21: dup
      22: invokespecial #11                 // Method "<init>":()V
      25: areturn
    Exception table:
       from    to  target type
           0     5     8   Class org/apache/hbase/thirdparty/com/google/protobuf/InvalidProtocolBufferException

  boolean areSerializedFieldsEqual(org.apache.hadoop.hbase.filter.ByteArrayComparable);
    Code:
       0: aload_1
       1: aload_0
       2: if_acmpne     7
       5: iconst_1
       6: ireturn
       7: aload_1
       8: instanceof    #10                 // class org/apache/hadoop/hbase/filter/NullComparator
      11: ifne          16
      14: iconst_0
      15: ireturn
      16: aload_0
      17: aload_1
      18: invokespecial #12                 // Method org/apache/hadoop/hbase/filter/ByteArrayComparable.areSerializedFieldsEqual:(Lorg/apache/hadoop/hbase/filter/ByteArrayComparable;)Z
      21: ireturn

  public int compareTo(java.lang.Object);
    Code:
       0: aload_0
       1: aload_1
       2: checkcast     #13                 // class "[B"
       5: invokevirtual #2                  // Method compareTo:([B)I
       8: ireturn
}
