Compiled from "OffPeakHours.java"
public abstract class org.apache.hadoop.hbase.regionserver.compactions.OffPeakHours {
  public static final org.apache.hadoop.hbase.regionserver.compactions.OffPeakHours DISABLED;

  public org.apache.hadoop.hbase.regionserver.compactions.OffPeakHours();
    Code:
       0: aload_0
       1: invokespecial #1                  // Method java/lang/Object."<init>":()V
       4: return

  public static org.apache.hadoop.hbase.regionserver.compactions.OffPeakHours getInstance(org.apache.hadoop.conf.Configuration);
    Code:
       0: aload_0
       1: ldc           #3                  // String hbase.offpeak.start.hour
       3: iconst_m1
       4: invokevirtual #4                  // Method org/apache/hadoop/conf/Configuration.getInt:(Ljava/lang/String;I)I
       7: istore_1
       8: aload_0
       9: ldc           #5                  // String hbase.offpeak.end.hour
      11: iconst_m1
      12: invokevirtual #4                  // Method org/apache/hadoop/conf/Configuration.getInt:(Ljava/lang/String;I)I
      15: istore_2
      16: iload_1
      17: iload_2
      18: invokestatic  #6                  // Method getInstance:(II)Lorg/apache/hadoop/hbase/regionserver/compactions/OffPeakHours;
      21: areturn

  public static org.apache.hadoop.hbase.regionserver.compactions.OffPeakHours getInstance(int, int);
    Code:
       0: iload_0
       1: iconst_m1
       2: if_icmpne     14
       5: iload_1
       6: iconst_m1
       7: if_icmpne     14
      10: getstatic     #7                  // Field DISABLED:Lorg/apache/hadoop/hbase/regionserver/compactions/OffPeakHours;
      13: areturn
      14: iload_0
      15: invokestatic  #8                  // Method isValidHour:(I)Z
      18: ifeq          28
      21: iload_1
      22: invokestatic  #8                  // Method isValidHour:(I)Z
      25: ifne          84
      28: getstatic     #9                  // Field LOG:Lorg/slf4j/Logger;
      31: invokeinterface #10,  1           // InterfaceMethod org/slf4j/Logger.isWarnEnabled:()Z
      36: ifeq          80
      39: getstatic     #9                  // Field LOG:Lorg/slf4j/Logger;
      42: new           #11                 // class java/lang/StringBuilder
      45: dup
      46: invokespecial #12                 // Method java/lang/StringBuilder."<init>":()V
      49: ldc           #13                 // String Ignoring invalid start/end hour for peak hour : start =
      51: invokevirtual #14                 // Method java/lang/StringBuilder.append:(Ljava/lang/String;)Ljava/lang/StringBuilder;
      54: iload_0
      55: invokevirtual #15                 // Method java/lang/StringBuilder.append:(I)Ljava/lang/StringBuilder;
      58: ldc           #16                 // String  end =
      60: invokevirtual #14                 // Method java/lang/StringBuilder.append:(Ljava/lang/String;)Ljava/lang/StringBuilder;
      63: iload_1
      64: invokevirtual #15                 // Method java/lang/StringBuilder.append:(I)Ljava/lang/StringBuilder;
      67: ldc           #17                 // String . Valid numbers are [0-23]
      69: invokevirtual #14                 // Method java/lang/StringBuilder.append:(Ljava/lang/String;)Ljava/lang/StringBuilder;
      72: invokevirtual #18                 // Method java/lang/StringBuilder.toString:()Ljava/lang/String;
      75: invokeinterface #19,  2           // InterfaceMethod org/slf4j/Logger.warn:(Ljava/lang/String;)V
      80: getstatic     #7                  // Field DISABLED:Lorg/apache/hadoop/hbase/regionserver/compactions/OffPeakHours;
      83: areturn
      84: iload_0
      85: iload_1
      86: if_icmpne     93
      89: getstatic     #7                  // Field DISABLED:Lorg/apache/hadoop/hbase/regionserver/compactions/OffPeakHours;
      92: areturn
      93: new           #20                 // class org/apache/hadoop/hbase/regionserver/compactions/OffPeakHours$OffPeakHoursImpl
      96: dup
      97: iload_0
      98: iload_1
      99: invokespecial #21                 // Method org/apache/hadoop/hbase/regionserver/compactions/OffPeakHours$OffPeakHoursImpl."<init>":(II)V
     102: areturn

  public abstract boolean isOffPeakHour(int);

  public abstract boolean isOffPeakHour();

  static {};
    Code:
       0: ldc           #22                 // class org/apache/hadoop/hbase/regionserver/compactions/OffPeakHours
       2: invokestatic  #23                 // Method org/slf4j/LoggerFactory.getLogger:(Ljava/lang/Class;)Lorg/slf4j/Logger;
       5: putstatic     #9                  // Field LOG:Lorg/slf4j/Logger;
       8: new           #24                 // class org/apache/hadoop/hbase/regionserver/compactions/OffPeakHours$1
      11: dup
      12: invokespecial #25                 // Method org/apache/hadoop/hbase/regionserver/compactions/OffPeakHours$1."<init>":()V
      15: putstatic     #7                  // Field DISABLED:Lorg/apache/hadoop/hbase/regionserver/compactions/OffPeakHours;
      18: return
}
