Compiled from "OrderedBlob.java"
public class org.apache.hadoop.hbase.types.OrderedBlob extends org.apache.hadoop.hbase.types.OrderedBytesBase<byte[]> {
  public static final org.apache.hadoop.hbase.types.OrderedBlob ASCENDING;

  public static final org.apache.hadoop.hbase.types.OrderedBlob DESCENDING;

  protected org.apache.hadoop.hbase.types.OrderedBlob(org.apache.hadoop.hbase.util.Order);
    Code:
       0: aload_0
       1: aload_1
       2: invokespecial #1                  // Method org/apache/hadoop/hbase/types/OrderedBytesBase."<init>":(Lorg/apache/hadoop/hbase/util/Order;)V
       5: return

  public boolean isSkippable();
    Code:
       0: iconst_0
       1: ireturn

  public int encodedLength(byte[]);
    Code:
       0: aconst_null
       1: aload_1
       2: if_acmpne     23
       5: getstatic     #2                  // Field org/apache/hadoop/hbase/util/Order.ASCENDING:Lorg/apache/hadoop/hbase/util/Order;
       8: aload_0
       9: getfield      #3                  // Field order:Lorg/apache/hadoop/hbase/util/Order;
      12: if_acmpne     19
      15: iconst_1
      16: goto          44
      19: iconst_2
      20: goto          44
      23: getstatic     #2                  // Field org/apache/hadoop/hbase/util/Order.ASCENDING:Lorg/apache/hadoop/hbase/util/Order;
      26: aload_0
      27: getfield      #3                  // Field order:Lorg/apache/hadoop/hbase/util/Order;
      30: if_acmpne     40
      33: aload_1
      34: arraylength
      35: iconst_1
      36: iadd
      37: goto          44
      40: aload_1
      41: arraylength
      42: iconst_2
      43: iadd
      44: ireturn

  public java.lang.Class<byte[]> encodedClass();
    Code:
       0: ldc           #4                  // class "[B"
       2: areturn

  public byte[] decode(org.apache.hadoop.hbase.util.PositionedByteRange);
    Code:
       0: aload_1
       1: invokestatic  #5                  // Method org/apache/hadoop/hbase/util/OrderedBytes.decodeBlobCopy:(Lorg/apache/hadoop/hbase/util/PositionedByteRange;)[B
       4: areturn

  public int encode(org.apache.hadoop.hbase.util.PositionedByteRange, byte[]);
    Code:
       0: aload_1
       1: aload_2
       2: aload_0
       3: getfield      #3                  // Field order:Lorg/apache/hadoop/hbase/util/Order;
       6: invokestatic  #6                  // Method org/apache/hadoop/hbase/util/OrderedBytes.encodeBlobCopy:(Lorg/apache/hadoop/hbase/util/PositionedByteRange;[BLorg/apache/hadoop/hbase/util/Order;)I
       9: ireturn

  public int encode(org.apache.hadoop.hbase.util.PositionedByteRange, byte[], int, int);
    Code:
       0: aload_1
       1: aload_2
       2: iload_3
       3: iload         4
       5: aload_0
       6: getfield      #3                  // Field order:Lorg/apache/hadoop/hbase/util/Order;
       9: invokestatic  #7                  // Method org/apache/hadoop/hbase/util/OrderedBytes.encodeBlobCopy:(Lorg/apache/hadoop/hbase/util/PositionedByteRange;[BIILorg/apache/hadoop/hbase/util/Order;)I
      12: ireturn

  public int encode(org.apache.hadoop.hbase.util.PositionedByteRange, java.lang.Object);
    Code:
       0: aload_0
       1: aload_1
       2: aload_2
       3: checkcast     #4                  // class "[B"
       6: invokevirtual #8                  // Method encode:(Lorg/apache/hadoop/hbase/util/PositionedByteRange;[B)I
       9: ireturn

  public java.lang.Object decode(org.apache.hadoop.hbase.util.PositionedByteRange);
    Code:
       0: aload_0
       1: aload_1
       2: invokevirtual #9                  // Method decode:(Lorg/apache/hadoop/hbase/util/PositionedByteRange;)[B
       5: areturn

  public int encodedLength(java.lang.Object);
    Code:
       0: aload_0
       1: aload_1
       2: checkcast     #4                  // class "[B"
       5: invokevirtual #10                 // Method encodedLength:([B)I
       8: ireturn

  static {};
    Code:
       0: new           #11                 // class org/apache/hadoop/hbase/types/OrderedBlob
       3: dup
       4: getstatic     #2                  // Field org/apache/hadoop/hbase/util/Order.ASCENDING:Lorg/apache/hadoop/hbase/util/Order;
       7: invokespecial #12                 // Method "<init>":(Lorg/apache/hadoop/hbase/util/Order;)V
      10: putstatic     #13                 // Field ASCENDING:Lorg/apache/hadoop/hbase/types/OrderedBlob;
      13: new           #11                 // class org/apache/hadoop/hbase/types/OrderedBlob
      16: dup
      17: getstatic     #14                 // Field org/apache/hadoop/hbase/util/Order.DESCENDING:Lorg/apache/hadoop/hbase/util/Order;
      20: invokespecial #12                 // Method "<init>":(Lorg/apache/hadoop/hbase/util/Order;)V
      23: putstatic     #15                 // Field DESCENDING:Lorg/apache/hadoop/hbase/types/OrderedBlob;
      26: return
}
