Compiled from "OrderedBytesBase.java"
public abstract class org.apache.hadoop.hbase.types.OrderedBytesBase<T> implements org.apache.hadoop.hbase.types.DataType<T> {
  protected final org.apache.hadoop.hbase.util.Order order;

  protected org.apache.hadoop.hbase.types.OrderedBytesBase(org.apache.hadoop.hbase.util.Order);
    Code:
       0: aload_0
       1: invokespecial #1                  // Method java/lang/Object."<init>":()V
       4: aload_0
       5: aload_1
       6: putfield      #2                  // Field order:Lorg/apache/hadoop/hbase/util/Order;
       9: return

  public boolean isOrderPreserving();
    Code:
       0: iconst_1
       1: ireturn

  public org.apache.hadoop.hbase.util.Order getOrder();
    Code:
       0: aload_0
       1: getfield      #2                  // Field order:Lorg/apache/hadoop/hbase/util/Order;
       4: areturn

  public boolean isNullable();
    Code:
       0: iconst_1
       1: ireturn

  public boolean isSkippable();
    Code:
       0: iconst_1
       1: ireturn

  public int skip(org.apache.hadoop.hbase.util.PositionedByteRange);
    Code:
       0: aload_1
       1: invokestatic  #3                  // Method org/apache/hadoop/hbase/util/OrderedBytes.skip:(Lorg/apache/hadoop/hbase/util/PositionedByteRange;)I
       4: ireturn
}
