Compiled from "OrderedBytes.java"
public class org.apache.hadoop.hbase.util.OrderedBytes {
  public static final java.nio.charset.Charset UTF8;

  public static final int MAX_PRECISION;

  public static final java.math.MathContext DEFAULT_MATH_CONTEXT;

  static final boolean $assertionsDisabled;

  public org.apache.hadoop.hbase.util.OrderedBytes();
    Code:
       0: aload_0
       1: invokespecial #1                  // Method java/lang/Object."<init>":()V
       4: return

  static int putVaruint64(org.apache.hadoop.hbase.util.PositionedByteRange, long, boolean);
    Code:
       0: iconst_0
       1: istore        6
       3: aload_0
       4: invokeinterface #11,  1           // InterfaceMethod org/apache/hadoop/hbase/util/PositionedByteRange.getOffset:()I
       9: istore        7
      11: aload_0
      12: invokeinterface #12,  1           // InterfaceMethod org/apache/hadoop/hbase/util/PositionedByteRange.getPosition:()I
      17: istore        8
      19: aload_0
      20: invokeinterface #13,  1           // InterfaceMethod org/apache/hadoop/hbase/util/PositionedByteRange.getBytes:()[B
      25: astore        9
      27: iload_3
      28: ifeq          37
      31: getstatic     #14                 // Field org/apache/hadoop/hbase/util/Order.DESCENDING:Lorg/apache/hadoop/hbase/util/Order;
      34: goto          40
      37: getstatic     #15                 // Field org/apache/hadoop/hbase/util/Order.ASCENDING:Lorg/apache/hadoop/hbase/util/Order;
      40: astore        10
      42: iconst_m1
      43: lload_1
      44: ldc2_w        #16                 // long 241l
      47: invokestatic  #18                 // Method unsignedCmp:(JJ)I
      50: if_icmpne     91
      53: aload_0
      54: lload_1
      55: l2i
      56: i2b
      57: invokeinterface #10,  2           // InterfaceMethod org/apache/hadoop/hbase/util/PositionedByteRange.put:(B)Lorg/apache/hadoop/hbase/util/PositionedByteRange;
      62: pop
      63: aload_0
      64: invokeinterface #12,  1           // InterfaceMethod org/apache/hadoop/hbase/util/PositionedByteRange.getPosition:()I
      69: iload         8
      71: isub
      72: istore        6
      74: aload         10
      76: aload         9
      78: iload         7
      80: iload         8
      82: iadd
      83: iload         6
      85: invokevirtual #19                 // Method org/apache/hadoop/hbase/util/Order.apply:([BII)V
      88: iload         6
      90: ireturn
      91: iconst_m1
      92: lload_1
      93: ldc2_w        #20                 // long 2288l
      96: invokestatic  #18                 // Method unsignedCmp:(JJ)I
      99: if_icmpne     168
     102: lload_1
     103: ldc2_w        #22                 // long 240l
     106: lsub
     107: l2i
     108: istore        5
     110: aload_0
     111: iload         5
     113: sipush        256
     116: idiv
     117: sipush        241
     120: iadd
     121: i2b
     122: invokeinterface #10,  2           // InterfaceMethod org/apache/hadoop/hbase/util/PositionedByteRange.put:(B)Lorg/apache/hadoop/hbase/util/PositionedByteRange;
     127: iload         5
     129: sipush        256
     132: irem
     133: i2b
     134: invokeinterface #10,  2           // InterfaceMethod org/apache/hadoop/hbase/util/PositionedByteRange.put:(B)Lorg/apache/hadoop/hbase/util/PositionedByteRange;
     139: pop
     140: aload_0
     141: invokeinterface #12,  1           // InterfaceMethod org/apache/hadoop/hbase/util/PositionedByteRange.getPosition:()I
     146: iload         8
     148: isub
     149: istore        6
     151: aload         10
     153: aload         9
     155: iload         7
     157: iload         8
     159: iadd
     160: iload         6
     162: invokevirtual #19                 // Method org/apache/hadoop/hbase/util/Order.apply:([BII)V
     165: iload         6
     167: ireturn
     168: iconst_m1
     169: lload_1
     170: ldc2_w        #24                 // long 67824l
     173: invokestatic  #18                 // Method unsignedCmp:(JJ)I
     176: if_icmpne     248
     179: lload_1
     180: ldc2_w        #20                 // long 2288l
     183: lsub
     184: l2i
     185: istore        5
     187: aload_0
     188: bipush        -7
     190: invokeinterface #10,  2           // InterfaceMethod org/apache/hadoop/hbase/util/PositionedByteRange.put:(B)Lorg/apache/hadoop/hbase/util/PositionedByteRange;
     195: iload         5
     197: sipush        256
     200: idiv
     201: i2b
     202: invokeinterface #10,  2           // InterfaceMethod org/apache/hadoop/hbase/util/PositionedByteRange.put:(B)Lorg/apache/hadoop/hbase/util/PositionedByteRange;
     207: iload         5
     209: sipush        256
     212: irem
     213: i2b
     214: invokeinterface #10,  2           // InterfaceMethod org/apache/hadoop/hbase/util/PositionedByteRange.put:(B)Lorg/apache/hadoop/hbase/util/PositionedByteRange;
     219: pop
     220: aload_0
     221: invokeinterface #12,  1           // InterfaceMethod org/apache/hadoop/hbase/util/PositionedByteRange.getPosition:()I
     226: iload         8
     228: isub
     229: istore        6
     231: aload         10
     233: aload         9
     235: iload         7
     237: iload         8
     239: iadd
     240: iload         6
     242: invokevirtual #19                 // Method org/apache/hadoop/hbase/util/Order.apply:([BII)V
     245: iload         6
     247: ireturn
     248: lload_1
     249: l2i
     250: istore        5
     252: lload_1
     253: bipush        32
     255: lushr
     256: l2i
     257: istore        4
     259: iload         4
     261: ifne          388
     264: iconst_m1
     265: iload         5
     267: i2l
     268: ldc2_w        #26                 // long 16777216l
     271: invokestatic  #18                 // Method unsignedCmp:(JJ)I
     274: if_icmpne     344
     277: aload_0
     278: bipush        -6
     280: invokeinterface #10,  2           // InterfaceMethod org/apache/hadoop/hbase/util/PositionedByteRange.put:(B)Lorg/apache/hadoop/hbase/util/PositionedByteRange;
     285: iload         5
     287: bipush        16
     289: iushr
     290: i2b
     291: invokeinterface #10,  2           // InterfaceMethod org/apache/hadoop/hbase/util/PositionedByteRange.put:(B)Lorg/apache/hadoop/hbase/util/PositionedByteRange;
     296: iload         5
     298: bipush        8
     300: iushr
     301: i2b
     302: invokeinterface #10,  2           // InterfaceMethod org/apache/hadoop/hbase/util/PositionedByteRange.put:(B)Lorg/apache/hadoop/hbase/util/PositionedByteRange;
     307: iload         5
     309: i2b
     310: invokeinterface #10,  2           // InterfaceMethod org/apache/hadoop/hbase/util/PositionedByteRange.put:(B)Lorg/apache/hadoop/hbase/util/PositionedByteRange;
     315: pop
     316: aload_0
     317: invokeinterface #12,  1           // InterfaceMethod org/apache/hadoop/hbase/util/PositionedByteRange.getPosition:()I
     322: iload         8
     324: isub
     325: istore        6
     327: aload         10
     329: aload         9
     331: iload         7
     333: iload         8
     335: iadd
     336: iload         6
     338: invokevirtual #19                 // Method org/apache/hadoop/hbase/util/Order.apply:([BII)V
     341: iload         6
     343: ireturn
     344: aload_0
     345: bipush        -5
     347: invokeinterface #10,  2           // InterfaceMethod org/apache/hadoop/hbase/util/PositionedByteRange.put:(B)Lorg/apache/hadoop/hbase/util/PositionedByteRange;
     352: pop
     353: aload_0
     354: iload         5
     356: invokestatic  #28                 // Method putUint32:(Lorg/apache/hadoop/hbase/util/PositionedByteRange;I)I
     359: pop
     360: aload_0
     361: invokeinterface #12,  1           // InterfaceMethod org/apache/hadoop/hbase/util/PositionedByteRange.getPosition:()I
     366: iload         8
     368: isub
     369: istore        6
     371: aload         10
     373: aload         9
     375: iload         7
     377: iload         8
     379: iadd
     380: iload         6
     382: invokevirtual #19                 // Method org/apache/hadoop/hbase/util/Order.apply:([BII)V
     385: iload         6
     387: ireturn
     388: iconst_m1
     389: iload         4
     391: i2l
     392: ldc2_w        #29                 // long 256l
     395: invokestatic  #18                 // Method unsignedCmp:(JJ)I
     398: if_icmpne     453
     401: aload_0
     402: bipush        -4
     404: invokeinterface #10,  2           // InterfaceMethod org/apache/hadoop/hbase/util/PositionedByteRange.put:(B)Lorg/apache/hadoop/hbase/util/PositionedByteRange;
     409: iload         4
     411: i2b
     412: invokeinterface #10,  2           // InterfaceMethod org/apache/hadoop/hbase/util/PositionedByteRange.put:(B)Lorg/apache/hadoop/hbase/util/PositionedByteRange;
     417: pop
     418: aload_0
     419: iload         5
     421: invokestatic  #28                 // Method putUint32:(Lorg/apache/hadoop/hbase/util/PositionedByteRange;I)I
     424: pop
     425: aload_0
     426: invokeinterface #12,  1           // InterfaceMethod org/apache/hadoop/hbase/util/PositionedByteRange.getPosition:()I
     431: iload         8
     433: isub
     434: istore        6
     436: aload         10
     438: aload         9
     440: iload         7
     442: iload         8
     444: iadd
     445: iload         6
     447: invokevirtual #19                 // Method org/apache/hadoop/hbase/util/Order.apply:([BII)V
     450: iload         6
     452: ireturn
     453: iconst_m1
     454: iload         4
     456: i2l
     457: ldc2_w        #31                 // long 65536l
     460: invokestatic  #18                 // Method unsignedCmp:(JJ)I
     463: if_icmpne     529
     466: aload_0
     467: bipush        -3
     469: invokeinterface #10,  2           // InterfaceMethod org/apache/hadoop/hbase/util/PositionedByteRange.put:(B)Lorg/apache/hadoop/hbase/util/PositionedByteRange;
     474: iload         4
     476: bipush        8
     478: iushr
     479: i2b
     480: invokeinterface #10,  2           // InterfaceMethod org/apache/hadoop/hbase/util/PositionedByteRange.put:(B)Lorg/apache/hadoop/hbase/util/PositionedByteRange;
     485: iload         4
     487: i2b
     488: invokeinterface #10,  2           // InterfaceMethod org/apache/hadoop/hbase/util/PositionedByteRange.put:(B)Lorg/apache/hadoop/hbase/util/PositionedByteRange;
     493: pop
     494: aload_0
     495: iload         5
     497: invokestatic  #28                 // Method putUint32:(Lorg/apache/hadoop/hbase/util/PositionedByteRange;I)I
     500: pop
     501: aload_0
     502: invokeinterface #12,  1           // InterfaceMethod org/apache/hadoop/hbase/util/PositionedByteRange.getPosition:()I
     507: iload         8
     509: isub
     510: istore        6
     512: aload         10
     514: aload         9
     516: iload         7
     518: iload         8
     520: iadd
     521: iload         6
     523: invokevirtual #19                 // Method org/apache/hadoop/hbase/util/Order.apply:([BII)V
     526: iload         6
     528: ireturn
     529: iconst_m1
     530: iload         4
     532: i2l
     533: ldc2_w        #26                 // long 16777216l
     536: invokestatic  #18                 // Method unsignedCmp:(JJ)I
     539: if_icmpne     616
     542: aload_0
     543: bipush        -2
     545: invokeinterface #10,  2           // InterfaceMethod org/apache/hadoop/hbase/util/PositionedByteRange.put:(B)Lorg/apache/hadoop/hbase/util/PositionedByteRange;
     550: iload         4
     552: bipush        16
     554: iushr
     555: i2b
     556: invokeinterface #10,  2           // InterfaceMethod org/apache/hadoop/hbase/util/PositionedByteRange.put:(B)Lorg/apache/hadoop/hbase/util/PositionedByteRange;
     561: iload         4
     563: bipush        8
     565: iushr
     566: i2b
     567: invokeinterface #10,  2           // InterfaceMethod org/apache/hadoop/hbase/util/PositionedByteRange.put:(B)Lorg/apache/hadoop/hbase/util/PositionedByteRange;
     572: iload         4
     574: i2b
     575: invokeinterface #10,  2           // InterfaceMethod org/apache/hadoop/hbase/util/PositionedByteRange.put:(B)Lorg/apache/hadoop/hbase/util/PositionedByteRange;
     580: pop
     581: aload_0
     582: iload         5
     584: invokestatic  #28                 // Method putUint32:(Lorg/apache/hadoop/hbase/util/PositionedByteRange;I)I
     587: pop
     588: aload_0
     589: invokeinterface #12,  1           // InterfaceMethod org/apache/hadoop/hbase/util/PositionedByteRange.getPosition:()I
     594: iload         8
     596: isub
     597: istore        6
     599: aload         10
     601: aload         9
     603: iload         7
     605: iload         8
     607: iadd
     608: iload         6
     610: invokevirtual #19                 // Method org/apache/hadoop/hbase/util/Order.apply:([BII)V
     613: iload         6
     615: ireturn
     616: aload_0
     617: iconst_m1
     618: invokeinterface #10,  2           // InterfaceMethod org/apache/hadoop/hbase/util/PositionedByteRange.put:(B)Lorg/apache/hadoop/hbase/util/PositionedByteRange;
     623: pop
     624: aload_0
     625: iload         4
     627: invokestatic  #28                 // Method putUint32:(Lorg/apache/hadoop/hbase/util/PositionedByteRange;I)I
     630: pop
     631: aload_0
     632: iload         5
     634: invokestatic  #28                 // Method putUint32:(Lorg/apache/hadoop/hbase/util/PositionedByteRange;I)I
     637: pop
     638: aload_0
     639: invokeinterface #12,  1           // InterfaceMethod org/apache/hadoop/hbase/util/PositionedByteRange.getPosition:()I
     644: iload         8
     646: isub
     647: istore        6
     649: aload         10
     651: aload         9
     653: iload         7
     655: iload         8
     657: iadd
     658: iload         6
     660: invokevirtual #19                 // Method org/apache/hadoop/hbase/util/Order.apply:([BII)V
     663: iload         6
     665: ireturn

  static int lengthVaruint64(org.apache.hadoop.hbase.util.PositionedByteRange, boolean);
    Code:
       0: iload_1
       1: ifeq          10
       4: getstatic     #14                 // Field org/apache/hadoop/hbase/util/Order.DESCENDING:Lorg/apache/hadoop/hbase/util/Order;
       7: goto          13
      10: getstatic     #15                 // Field org/apache/hadoop/hbase/util/Order.ASCENDING:Lorg/apache/hadoop/hbase/util/Order;
      13: aload_0
      14: invokeinterface #33,  1           // InterfaceMethod org/apache/hadoop/hbase/util/PositionedByteRange.peek:()B
      19: invokevirtual #34                 // Method org/apache/hadoop/hbase/util/Order.apply:(B)B
      22: sipush        255
      25: iand
      26: istore_2
      27: iload_2
      28: sipush        240
      31: if_icmpgt     36
      34: iconst_1
      35: ireturn
      36: iload_2
      37: sipush        248
      40: if_icmpgt     45
      43: iconst_2
      44: ireturn
      45: iload_2
      46: sipush        249
      49: if_icmpne     54
      52: iconst_3
      53: ireturn
      54: iload_2
      55: sipush        250
      58: if_icmpne     63
      61: iconst_4
      62: ireturn
      63: iload_2
      64: sipush        251
      67: if_icmpne     72
      70: iconst_5
      71: ireturn
      72: iload_2
      73: sipush        252
      76: if_icmpne     82
      79: bipush        6
      81: ireturn
      82: iload_2
      83: sipush        253
      86: if_icmpne     92
      89: bipush        7
      91: ireturn
      92: iload_2
      93: sipush        254
      96: if_icmpne     102
      99: bipush        8
     101: ireturn
     102: iload_2
     103: sipush        255
     106: if_icmpne     112
     109: bipush        9
     111: ireturn
     112: aload_0
     113: invokeinterface #33,  1           // InterfaceMethod org/apache/hadoop/hbase/util/PositionedByteRange.peek:()B
     118: invokestatic  #35                 // Method unexpectedHeader:(B)Ljava/lang/IllegalArgumentException;
     121: athrow

  static int skipVaruint64(org.apache.hadoop.hbase.util.PositionedByteRange, boolean);
    Code:
       0: aload_0
       1: iload_1
       2: invokestatic  #36                 // Method lengthVaruint64:(Lorg/apache/hadoop/hbase/util/PositionedByteRange;Z)I
       5: istore_2
       6: aload_0
       7: aload_0
       8: invokeinterface #12,  1           // InterfaceMethod org/apache/hadoop/hbase/util/PositionedByteRange.getPosition:()I
      13: iload_2
      14: iadd
      15: invokeinterface #37,  2           // InterfaceMethod org/apache/hadoop/hbase/util/PositionedByteRange.setPosition:(I)Lorg/apache/hadoop/hbase/util/PositionedByteRange;
      20: pop
      21: iload_2
      22: ireturn

  static long getVaruint64(org.apache.hadoop.hbase.util.PositionedByteRange, boolean);
    Code:
       0: getstatic     #38                 // Field $assertionsDisabled:Z
       3: ifne          28
       6: aload_0
       7: invokeinterface #39,  1           // InterfaceMethod org/apache/hadoop/hbase/util/PositionedByteRange.getRemaining:()I
      12: aload_0
      13: iload_1
      14: invokestatic  #36                 // Method lengthVaruint64:(Lorg/apache/hadoop/hbase/util/PositionedByteRange;Z)I
      17: if_icmpge     28
      20: new           #40                 // class java/lang/AssertionError
      23: dup
      24: invokespecial #41                 // Method java/lang/AssertionError."<init>":()V
      27: athrow
      28: iload_1
      29: ifeq          38
      32: getstatic     #14                 // Field org/apache/hadoop/hbase/util/Order.DESCENDING:Lorg/apache/hadoop/hbase/util/Order;
      35: goto          41
      38: getstatic     #15                 // Field org/apache/hadoop/hbase/util/Order.ASCENDING:Lorg/apache/hadoop/hbase/util/Order;
      41: astore        4
      43: aload_0
      44: invokeinterface #42,  1           // InterfaceMethod org/apache/hadoop/hbase/util/PositionedByteRange.get:()B
      49: istore        5
      51: aload         4
      53: iload         5
      55: invokevirtual #34                 // Method org/apache/hadoop/hbase/util/Order.apply:(B)B
      58: sipush        255
      61: iand
      62: istore        6
      64: iconst_m1
      65: iload         6
      67: i2l
      68: ldc2_w        #16                 // long 241l
      71: invokestatic  #18                 // Method unsignedCmp:(JJ)I
      74: if_icmpne     81
      77: iload         6
      79: i2l
      80: lreturn
      81: aload_0
      82: invokeinterface #42,  1           // InterfaceMethod org/apache/hadoop/hbase/util/PositionedByteRange.get:()B
      87: istore        5
      89: aload         4
      91: iload         5
      93: invokevirtual #34                 // Method org/apache/hadoop/hbase/util/Order.apply:(B)B
      96: sipush        255
      99: iand
     100: istore        7
     102: iconst_m1
     103: iload         6
     105: i2l
     106: ldc2_w        #43                 // long 249l
     109: invokestatic  #18                 // Method unsignedCmp:(JJ)I
     112: if_icmpne     135
     115: iload         6
     117: i2l
     118: ldc2_w        #16                 // long 241l
     121: lsub
     122: ldc2_w        #29                 // long 256l
     125: lmul
     126: iload         7
     128: i2l
     129: ladd
     130: ldc2_w        #22                 // long 240l
     133: ladd
     134: lreturn
     135: aload_0
     136: invokeinterface #42,  1           // InterfaceMethod org/apache/hadoop/hbase/util/PositionedByteRange.get:()B
     141: istore        5
     143: aload         4
     145: iload         5
     147: invokevirtual #34                 // Method org/apache/hadoop/hbase/util/Order.apply:(B)B
     150: sipush        255
     153: iand
     154: istore        8
     156: iload         6
     158: sipush        249
     161: if_icmpne     180
     164: ldc2_w        #20                 // long 2288l
     167: sipush        256
     170: iload         7
     172: imul
     173: i2l
     174: ladd
     175: iload         8
     177: i2l
     178: ladd
     179: lreturn
     180: aload_0
     181: invokeinterface #42,  1           // InterfaceMethod org/apache/hadoop/hbase/util/PositionedByteRange.get:()B
     186: istore        5
     188: aload         4
     190: iload         5
     192: invokevirtual #34                 // Method org/apache/hadoop/hbase/util/Order.apply:(B)B
     195: sipush        255
     198: iand
     199: istore        9
     201: iload         6
     203: sipush        250
     206: if_icmpne     227
     209: iload         7
     211: i2l
     212: bipush        16
     214: lshl
     215: iload         8
     217: bipush        8
     219: ishl
     220: i2l
     221: lor
     222: iload         9
     224: i2l
     225: lor
     226: lreturn
     227: aload_0
     228: invokeinterface #42,  1           // InterfaceMethod org/apache/hadoop/hbase/util/PositionedByteRange.get:()B
     233: istore        5
     235: aload         4
     237: iload         5
     239: invokevirtual #34                 // Method org/apache/hadoop/hbase/util/Order.apply:(B)B
     242: sipush        255
     245: iand
     246: istore        10
     248: iload         7
     250: i2l
     251: bipush        24
     253: lshl
     254: iload         8
     256: bipush        16
     258: ishl
     259: i2l
     260: lor
     261: iload         9
     263: bipush        8
     265: ishl
     266: i2l
     267: lor
     268: iload         10
     270: i2l
     271: lor
     272: lstore_2
     273: iload         6
     275: sipush        251
     278: if_icmpne     283
     281: lload_2
     282: lreturn
     283: aload_0
     284: invokeinterface #42,  1           // InterfaceMethod org/apache/hadoop/hbase/util/PositionedByteRange.get:()B
     289: istore        5
     291: aload         4
     293: iload         5
     295: invokevirtual #34                 // Method org/apache/hadoop/hbase/util/Order.apply:(B)B
     298: sipush        255
     301: iand
     302: istore        11
     304: iload         6
     306: sipush        252
     309: if_icmpne     321
     312: lload_2
     313: bipush        8
     315: lshl
     316: iload         11
     318: i2l
     319: lor
     320: lreturn
     321: aload_0
     322: invokeinterface #42,  1           // InterfaceMethod org/apache/hadoop/hbase/util/PositionedByteRange.get:()B
     327: istore        5
     329: aload         4
     331: iload         5
     333: invokevirtual #34                 // Method org/apache/hadoop/hbase/util/Order.apply:(B)B
     336: sipush        255
     339: iand
     340: istore        12
     342: iload         6
     344: sipush        253
     347: if_icmpne     366
     350: lload_2
     351: bipush        16
     353: lshl
     354: iload         11
     356: bipush        8
     358: ishl
     359: i2l
     360: lor
     361: iload         12
     363: i2l
     364: lor
     365: lreturn
     366: aload_0
     367: invokeinterface #42,  1           // InterfaceMethod org/apache/hadoop/hbase/util/PositionedByteRange.get:()B
     372: istore        5
     374: aload         4
     376: iload         5
     378: invokevirtual #34                 // Method org/apache/hadoop/hbase/util/Order.apply:(B)B
     381: sipush        255
     384: iand
     385: istore        13
     387: iload         6
     389: sipush        254
     392: if_icmpne     418
     395: lload_2
     396: bipush        24
     398: lshl
     399: iload         11
     401: bipush        16
     403: ishl
     404: i2l
     405: lor
     406: iload         12
     408: bipush        8
     410: ishl
     411: i2l
     412: lor
     413: iload         13
     415: i2l
     416: lor
     417: lreturn
     418: aload_0
     419: invokeinterface #42,  1           // InterfaceMethod org/apache/hadoop/hbase/util/PositionedByteRange.get:()B
     424: istore        5
     426: aload         4
     428: iload         5
     430: invokevirtual #34                 // Method org/apache/hadoop/hbase/util/Order.apply:(B)B
     433: sipush        255
     436: iand
     437: istore        14
     439: lload_2
     440: bipush        32
     442: lshl
     443: iload         11
     445: i2l
     446: bipush        24
     448: lshl
     449: lor
     450: iload         12
     452: bipush        16
     454: ishl
     455: i2l
     456: lor
     457: iload         13
     459: bipush        8
     461: ishl
     462: i2l
     463: lor
     464: iload         14
     466: i2l
     467: lor
     468: lreturn

  static java.math.BigDecimal normalize(java.math.BigDecimal);
    Code:
       0: aconst_null
       1: aload_0
       2: if_acmpne     9
       5: aconst_null
       6: goto          19
       9: aload_0
      10: invokevirtual #45                 // Method java/math/BigDecimal.stripTrailingZeros:()Ljava/math/BigDecimal;
      13: getstatic     #46                 // Field DEFAULT_MATH_CONTEXT:Ljava/math/MathContext;
      16: invokevirtual #47                 // Method java/math/BigDecimal.round:(Ljava/math/MathContext;)Ljava/math/BigDecimal;
      19: areturn

  public static int encodeNumeric(org.apache.hadoop.hbase.util.PositionedByteRange, long, org.apache.hadoop.hbase.util.Order);
    Code:
       0: aload_0
       1: lload_1
       2: invokestatic  #55                 // Method java/math/BigDecimal.valueOf:(J)Ljava/math/BigDecimal;
       5: aload_3
       6: invokestatic  #74                 // Method encodeNumeric:(Lorg/apache/hadoop/hbase/util/PositionedByteRange;Ljava/math/BigDecimal;Lorg/apache/hadoop/hbase/util/Order;)I
       9: ireturn

  public static int encodeNumeric(org.apache.hadoop.hbase.util.PositionedByteRange, double, org.apache.hadoop.hbase.util.Order);
    Code:
       0: dload_1
       1: dconst_0
       2: dcmpl
       3: ifne          21
       6: aload_0
       7: aload_3
       8: bipush        21
      10: invokevirtual #34                 // Method org/apache/hadoop/hbase/util/Order.apply:(B)B
      13: invokeinterface #10,  2           // InterfaceMethod org/apache/hadoop/hbase/util/PositionedByteRange.put:(B)Lorg/apache/hadoop/hbase/util/PositionedByteRange;
      18: pop
      19: iconst_1
      20: ireturn
      21: dload_1
      22: invokestatic  #75                 // Method java/lang/Double.isNaN:(D)Z
      25: ifeq          43
      28: aload_0
      29: aload_3
      30: bipush        38
      32: invokevirtual #34                 // Method org/apache/hadoop/hbase/util/Order.apply:(B)B
      35: invokeinterface #10,  2           // InterfaceMethod org/apache/hadoop/hbase/util/PositionedByteRange.put:(B)Lorg/apache/hadoop/hbase/util/PositionedByteRange;
      40: pop
      41: iconst_1
      42: ireturn
      43: dload_1
      44: ldc2_w        #77                 // double -Infinityd
      47: dcmpl
      48: ifne          66
      51: aload_0
      52: aload_3
      53: bipush        7
      55: invokevirtual #34                 // Method org/apache/hadoop/hbase/util/Order.apply:(B)B
      58: invokeinterface #10,  2           // InterfaceMethod org/apache/hadoop/hbase/util/PositionedByteRange.put:(B)Lorg/apache/hadoop/hbase/util/PositionedByteRange;
      63: pop
      64: iconst_1
      65: ireturn
      66: dload_1
      67: ldc2_w        #79                 // double Infinityd
      70: dcmpl
      71: ifne          89
      74: aload_0
      75: aload_3
      76: bipush        35
      78: invokevirtual #34                 // Method org/apache/hadoop/hbase/util/Order.apply:(B)B
      81: invokeinterface #10,  2           // InterfaceMethod org/apache/hadoop/hbase/util/PositionedByteRange.put:(B)Lorg/apache/hadoop/hbase/util/PositionedByteRange;
      86: pop
      87: iconst_1
      88: ireturn
      89: aload_0
      90: dload_1
      91: invokestatic  #81                 // Method java/math/BigDecimal.valueOf:(D)Ljava/math/BigDecimal;
      94: aload_3
      95: invokestatic  #74                 // Method encodeNumeric:(Lorg/apache/hadoop/hbase/util/PositionedByteRange;Ljava/math/BigDecimal;Lorg/apache/hadoop/hbase/util/Order;)I
      98: ireturn

  public static int encodeNumeric(org.apache.hadoop.hbase.util.PositionedByteRange, java.math.BigDecimal, org.apache.hadoop.hbase.util.Order);
    Code:
       0: aload_0
       1: invokeinterface #11,  1           // InterfaceMethod org/apache/hadoop/hbase/util/PositionedByteRange.getOffset:()I
       6: istore        4
       8: aload_0
       9: invokeinterface #12,  1           // InterfaceMethod org/apache/hadoop/hbase/util/PositionedByteRange.getPosition:()I
      14: istore        5
      16: aconst_null
      17: aload_1
      18: if_acmpne     27
      21: aload_0
      22: aload_2
      23: invokestatic  #82                 // Method encodeNull:(Lorg/apache/hadoop/hbase/util/PositionedByteRange;Lorg/apache/hadoop/hbase/util/Order;)I
      26: ireturn
      27: getstatic     #48                 // Field java/math/BigDecimal.ZERO:Ljava/math/BigDecimal;
      30: aload_1
      31: invokevirtual #60                 // Method java/math/BigDecimal.compareTo:(Ljava/math/BigDecimal;)I
      34: ifne          52
      37: aload_0
      38: aload_2
      39: bipush        21
      41: invokevirtual #34                 // Method org/apache/hadoop/hbase/util/Order.apply:(B)B
      44: invokeinterface #10,  2           // InterfaceMethod org/apache/hadoop/hbase/util/PositionedByteRange.put:(B)Lorg/apache/hadoop/hbase/util/PositionedByteRange;
      49: pop
      50: iconst_1
      51: ireturn
      52: aload_1
      53: invokevirtual #59                 // Method java/math/BigDecimal.abs:()Ljava/math/BigDecimal;
      56: astore        6
      58: getstatic     #61                 // Field java/math/BigDecimal.ONE:Ljava/math/BigDecimal;
      61: aload         6
      63: invokevirtual #60                 // Method java/math/BigDecimal.compareTo:(Ljava/math/BigDecimal;)I
      66: ifgt          81
      69: aload_0
      70: aload_1
      71: invokestatic  #58                 // Method normalize:(Ljava/math/BigDecimal;)Ljava/math/BigDecimal;
      74: invokestatic  #83                 // Method encodeNumericLarge:(Lorg/apache/hadoop/hbase/util/PositionedByteRange;Ljava/math/BigDecimal;)I
      77: istore_3
      78: goto          90
      81: aload_0
      82: aload_1
      83: invokestatic  #58                 // Method normalize:(Ljava/math/BigDecimal;)Ljava/math/BigDecimal;
      86: invokestatic  #84                 // Method encodeNumericSmall:(Lorg/apache/hadoop/hbase/util/PositionedByteRange;Ljava/math/BigDecimal;)I
      89: istore_3
      90: aload_2
      91: aload_0
      92: invokeinterface #13,  1           // InterfaceMethod org/apache/hadoop/hbase/util/PositionedByteRange.getBytes:()[B
      97: iload         4
      99: iload         5
     101: iadd
     102: iload_3
     103: invokevirtual #19                 // Method org/apache/hadoop/hbase/util/Order.apply:([BII)V
     106: iload_3
     107: ireturn

  public static double decodeNumericAsDouble(org.apache.hadoop.hbase.util.PositionedByteRange);
    Code:
       0: aload_0
       1: invokestatic  #89                 // Method isNull:(Lorg/apache/hadoop/hbase/util/PositionedByteRange;)Z
       4: ifeq          17
       7: new           #90                 // class java/lang/NullPointerException
      10: dup
      11: ldc           #91                 // String A null value cannot be decoded to a double.
      13: invokespecial #92                 // Method java/lang/NullPointerException."<init>":(Ljava/lang/String;)V
      16: athrow
      17: aload_0
      18: invokestatic  #93                 // Method isNumericNaN:(Lorg/apache/hadoop/hbase/util/PositionedByteRange;)Z
      21: ifeq          35
      24: aload_0
      25: invokeinterface #42,  1           // InterfaceMethod org/apache/hadoop/hbase/util/PositionedByteRange.get:()B
      30: pop
      31: ldc2_w        #94                 // double NaNd
      34: dreturn
      35: aload_0
      36: invokestatic  #96                 // Method isNumericZero:(Lorg/apache/hadoop/hbase/util/PositionedByteRange;)Z
      39: ifeq          57
      42: aload_0
      43: invokeinterface #42,  1           // InterfaceMethod org/apache/hadoop/hbase/util/PositionedByteRange.get:()B
      48: pop
      49: dconst_0
      50: invokestatic  #97                 // Method java/lang/Double.valueOf:(D)Ljava/lang/Double;
      53: invokevirtual #98                 // Method java/lang/Double.doubleValue:()D
      56: dreturn
      57: iconst_m1
      58: aload_0
      59: invokeinterface #33,  1           // InterfaceMethod org/apache/hadoop/hbase/util/PositionedByteRange.peek:()B
      64: invokestatic  #85                 // Method java/lang/Integer.signum:(I)I
      67: if_icmpne     85
      70: getstatic     #14                 // Field org/apache/hadoop/hbase/util/Order.DESCENDING:Lorg/apache/hadoop/hbase/util/Order;
      73: aload_0
      74: invokeinterface #33,  1           // InterfaceMethod org/apache/hadoop/hbase/util/PositionedByteRange.peek:()B
      79: invokevirtual #34                 // Method org/apache/hadoop/hbase/util/Order.apply:(B)B
      82: goto          91
      85: aload_0
      86: invokeinterface #33,  1           // InterfaceMethod org/apache/hadoop/hbase/util/PositionedByteRange.peek:()B
      91: istore_1
      92: iload_1
      93: bipush        7
      95: if_icmpne     109
      98: aload_0
      99: invokeinterface #42,  1           // InterfaceMethod org/apache/hadoop/hbase/util/PositionedByteRange.get:()B
     104: pop
     105: ldc2_w        #77                 // double -Infinityd
     108: dreturn
     109: iload_1
     110: bipush        35
     112: if_icmpne     126
     115: aload_0
     116: invokeinterface #42,  1           // InterfaceMethod org/apache/hadoop/hbase/util/PositionedByteRange.get:()B
     121: pop
     122: ldc2_w        #79                 // double Infinityd
     125: dreturn
     126: aload_0
     127: invokestatic  #99                 // Method decodeNumericValue:(Lorg/apache/hadoop/hbase/util/PositionedByteRange;)Ljava/math/BigDecimal;
     130: invokevirtual #100                // Method java/math/BigDecimal.doubleValue:()D
     133: dreturn

  public static long decodeNumericAsLong(org.apache.hadoop.hbase.util.PositionedByteRange);
    Code:
       0: aload_0
       1: invokestatic  #89                 // Method isNull:(Lorg/apache/hadoop/hbase/util/PositionedByteRange;)Z
       4: ifeq          15
       7: new           #90                 // class java/lang/NullPointerException
      10: dup
      11: invokespecial #101                // Method java/lang/NullPointerException."<init>":()V
      14: athrow
      15: aload_0
      16: invokestatic  #102                // Method isNumeric:(Lorg/apache/hadoop/hbase/util/PositionedByteRange;)Z
      19: ifne          32
      22: aload_0
      23: invokeinterface #33,  1           // InterfaceMethod org/apache/hadoop/hbase/util/PositionedByteRange.peek:()B
      28: invokestatic  #35                 // Method unexpectedHeader:(B)Ljava/lang/IllegalArgumentException;
      31: athrow
      32: aload_0
      33: invokestatic  #93                 // Method isNumericNaN:(Lorg/apache/hadoop/hbase/util/PositionedByteRange;)Z
      36: ifeq          49
      39: aload_0
      40: invokeinterface #33,  1           // InterfaceMethod org/apache/hadoop/hbase/util/PositionedByteRange.peek:()B
      45: invokestatic  #35                 // Method unexpectedHeader:(B)Ljava/lang/IllegalArgumentException;
      48: athrow
      49: aload_0
      50: invokestatic  #103                // Method isNumericInfinite:(Lorg/apache/hadoop/hbase/util/PositionedByteRange;)Z
      53: ifeq          66
      56: aload_0
      57: invokeinterface #33,  1           // InterfaceMethod org/apache/hadoop/hbase/util/PositionedByteRange.peek:()B
      62: invokestatic  #35                 // Method unexpectedHeader:(B)Ljava/lang/IllegalArgumentException;
      65: athrow
      66: aload_0
      67: invokestatic  #96                 // Method isNumericZero:(Lorg/apache/hadoop/hbase/util/PositionedByteRange;)Z
      70: ifeq          88
      73: aload_0
      74: invokeinterface #42,  1           // InterfaceMethod org/apache/hadoop/hbase/util/PositionedByteRange.get:()B
      79: pop
      80: lconst_0
      81: invokestatic  #104                // Method java/lang/Long.valueOf:(J)Ljava/lang/Long;
      84: invokevirtual #105                // Method java/lang/Long.longValue:()J
      87: lreturn
      88: aload_0
      89: invokestatic  #99                 // Method decodeNumericValue:(Lorg/apache/hadoop/hbase/util/PositionedByteRange;)Ljava/math/BigDecimal;
      92: invokevirtual #106                // Method java/math/BigDecimal.longValue:()J
      95: lreturn

  public static java.math.BigDecimal decodeNumericAsBigDecimal(org.apache.hadoop.hbase.util.PositionedByteRange);
    Code:
       0: aload_0
       1: invokestatic  #89                 // Method isNull:(Lorg/apache/hadoop/hbase/util/PositionedByteRange;)Z
       4: ifeq          16
       7: aload_0
       8: invokeinterface #42,  1           // InterfaceMethod org/apache/hadoop/hbase/util/PositionedByteRange.get:()B
      13: pop
      14: aconst_null
      15: areturn
      16: aload_0
      17: invokestatic  #102                // Method isNumeric:(Lorg/apache/hadoop/hbase/util/PositionedByteRange;)Z
      20: ifne          33
      23: aload_0
      24: invokeinterface #33,  1           // InterfaceMethod org/apache/hadoop/hbase/util/PositionedByteRange.peek:()B
      29: invokestatic  #35                 // Method unexpectedHeader:(B)Ljava/lang/IllegalArgumentException;
      32: athrow
      33: aload_0
      34: invokestatic  #93                 // Method isNumericNaN:(Lorg/apache/hadoop/hbase/util/PositionedByteRange;)Z
      37: ifeq          50
      40: aload_0
      41: invokeinterface #33,  1           // InterfaceMethod org/apache/hadoop/hbase/util/PositionedByteRange.peek:()B
      46: invokestatic  #35                 // Method unexpectedHeader:(B)Ljava/lang/IllegalArgumentException;
      49: athrow
      50: aload_0
      51: invokestatic  #103                // Method isNumericInfinite:(Lorg/apache/hadoop/hbase/util/PositionedByteRange;)Z
      54: ifeq          67
      57: aload_0
      58: invokeinterface #33,  1           // InterfaceMethod org/apache/hadoop/hbase/util/PositionedByteRange.peek:()B
      63: invokestatic  #35                 // Method unexpectedHeader:(B)Ljava/lang/IllegalArgumentException;
      66: athrow
      67: aload_0
      68: invokestatic  #99                 // Method decodeNumericValue:(Lorg/apache/hadoop/hbase/util/PositionedByteRange;)Ljava/math/BigDecimal;
      71: areturn

  public static int encodeString(org.apache.hadoop.hbase.util.PositionedByteRange, java.lang.String, org.apache.hadoop.hbase.util.Order);
    Code:
       0: aconst_null
       1: aload_1
       2: if_acmpne     11
       5: aload_0
       6: aload_2
       7: invokestatic  #82                 // Method encodeNull:(Lorg/apache/hadoop/hbase/util/PositionedByteRange;Lorg/apache/hadoop/hbase/util/Order;)I
      10: ireturn
      11: aload_1
      12: ldc           #107                // String  
      14: invokevirtual #108                // Method java/lang/String.contains:(Ljava/lang/CharSequence;)Z
      17: ifeq          30
      20: new           #2                  // class java/lang/IllegalArgumentException
      23: dup
      24: ldc           #109                // String Cannot encode String values containing '\u0000'
      26: invokespecial #9                  // Method java/lang/IllegalArgumentException."<init>":(Ljava/lang/String;)V
      29: athrow
      30: aload_0
      31: invokeinterface #11,  1           // InterfaceMethod org/apache/hadoop/hbase/util/PositionedByteRange.getOffset:()I
      36: istore_3
      37: aload_0
      38: invokeinterface #12,  1           // InterfaceMethod org/apache/hadoop/hbase/util/PositionedByteRange.getPosition:()I
      43: istore        4
      45: aload_0
      46: bipush        52
      48: invokeinterface #10,  2           // InterfaceMethod org/apache/hadoop/hbase/util/PositionedByteRange.put:(B)Lorg/apache/hadoop/hbase/util/PositionedByteRange;
      53: pop
      54: aload_0
      55: aload_1
      56: getstatic     #110                // Field UTF8:Ljava/nio/charset/Charset;
      59: invokevirtual #111                // Method java/lang/String.getBytes:(Ljava/nio/charset/Charset;)[B
      62: invokeinterface #112,  2          // InterfaceMethod org/apache/hadoop/hbase/util/PositionedByteRange.put:([B)Lorg/apache/hadoop/hbase/util/PositionedByteRange;
      67: pop
      68: aload_0
      69: iconst_0
      70: invokeinterface #10,  2           // InterfaceMethod org/apache/hadoop/hbase/util/PositionedByteRange.put:(B)Lorg/apache/hadoop/hbase/util/PositionedByteRange;
      75: pop
      76: aload_2
      77: aload_0
      78: invokeinterface #13,  1           // InterfaceMethod org/apache/hadoop/hbase/util/PositionedByteRange.getBytes:()[B
      83: iload_3
      84: iload         4
      86: iadd
      87: aload_0
      88: invokeinterface #12,  1           // InterfaceMethod org/apache/hadoop/hbase/util/PositionedByteRange.getPosition:()I
      93: iload         4
      95: isub
      96: invokevirtual #19                 // Method org/apache/hadoop/hbase/util/Order.apply:([BII)V
      99: aload_0
     100: invokeinterface #12,  1           // InterfaceMethod org/apache/hadoop/hbase/util/PositionedByteRange.getPosition:()I
     105: iload         4
     107: isub
     108: ireturn

  public static java.lang.String decodeString(org.apache.hadoop.hbase.util.PositionedByteRange);
    Code:
       0: aload_0
       1: invokeinterface #42,  1           // InterfaceMethod org/apache/hadoop/hbase/util/PositionedByteRange.get:()B
       6: istore_1
       7: iload_1
       8: iconst_5
       9: if_icmpeq     23
      12: iload_1
      13: getstatic     #14                 // Field org/apache/hadoop/hbase/util/Order.DESCENDING:Lorg/apache/hadoop/hbase/util/Order;
      16: iconst_5
      17: invokevirtual #34                 // Method org/apache/hadoop/hbase/util/Order.apply:(B)B
      20: if_icmpne     25
      23: aconst_null
      24: areturn
      25: getstatic     #38                 // Field $assertionsDisabled:Z
      28: ifne          57
      31: iload_1
      32: bipush        52
      34: if_icmpeq     57
      37: iload_1
      38: getstatic     #14                 // Field org/apache/hadoop/hbase/util/Order.DESCENDING:Lorg/apache/hadoop/hbase/util/Order;
      41: bipush        52
      43: invokevirtual #34                 // Method org/apache/hadoop/hbase/util/Order.apply:(B)B
      46: if_icmpeq     57
      49: new           #40                 // class java/lang/AssertionError
      52: dup
      53: invokespecial #41                 // Method java/lang/AssertionError."<init>":()V
      56: athrow
      57: iload_1
      58: bipush        52
      60: if_icmpne     69
      63: getstatic     #15                 // Field org/apache/hadoop/hbase/util/Order.ASCENDING:Lorg/apache/hadoop/hbase/util/Order;
      66: goto          72
      69: getstatic     #14                 // Field org/apache/hadoop/hbase/util/Order.DESCENDING:Lorg/apache/hadoop/hbase/util/Order;
      72: astore_2
      73: aload_0
      74: invokeinterface #13,  1           // InterfaceMethod org/apache/hadoop/hbase/util/PositionedByteRange.getBytes:()[B
      79: astore_3
      80: aload_0
      81: invokeinterface #11,  1           // InterfaceMethod org/apache/hadoop/hbase/util/PositionedByteRange.getOffset:()I
      86: istore        4
      88: aload_0
      89: invokeinterface #12,  1           // InterfaceMethod org/apache/hadoop/hbase/util/PositionedByteRange.getPosition:()I
      94: istore        5
      96: aload_2
      97: iconst_0
      98: invokevirtual #34                 // Method org/apache/hadoop/hbase/util/Order.apply:(B)B
     101: istore        6
     103: iload         4
     105: iload         5
     107: iadd
     108: istore        7
     110: iload         7
     112: istore        8
     114: aload_3
     115: iload         8
     117: baload
     118: iload         6
     120: if_icmpeq     129
     123: iinc          8, 1
     126: goto          114
     129: aload_0
     130: iload         8
     132: iload         4
     134: isub
     135: iconst_1
     136: iadd
     137: invokeinterface #37,  2           // InterfaceMethod org/apache/hadoop/hbase/util/PositionedByteRange.setPosition:(I)Lorg/apache/hadoop/hbase/util/PositionedByteRange;
     142: pop
     143: getstatic     #14                 // Field org/apache/hadoop/hbase/util/Order.DESCENDING:Lorg/apache/hadoop/hbase/util/Order;
     146: aload_2
     147: if_acmpne     190
     150: iload         8
     152: iload         7
     154: isub
     155: newarray       byte
     157: astore        9
     159: aload_3
     160: iload         7
     162: aload         9
     164: iconst_0
     165: aload         9
     167: arraylength
     168: invokestatic  #113                // Method java/lang/System.arraycopy:(Ljava/lang/Object;ILjava/lang/Object;II)V
     171: aload_2
     172: aload         9
     174: invokevirtual #114                // Method org/apache/hadoop/hbase/util/Order.apply:([B)V
     177: new           #115                // class java/lang/String
     180: dup
     181: aload         9
     183: getstatic     #110                // Field UTF8:Ljava/nio/charset/Charset;
     186: invokespecial #116                // Method java/lang/String."<init>":([BLjava/nio/charset/Charset;)V
     189: areturn
     190: new           #115                // class java/lang/String
     193: dup
     194: aload_3
     195: iload         7
     197: iload         8
     199: iload         7
     201: isub
     202: getstatic     #110                // Field UTF8:Ljava/nio/charset/Charset;
     205: invokespecial #117                // Method java/lang/String."<init>":([BIILjava/nio/charset/Charset;)V
     208: areturn

  public static int blobVarEncodedLength(int);
    Code:
       0: iconst_0
       1: iload_0
       2: if_icmpne     7
       5: iconst_2
       6: ireturn
       7: iload_0
       8: bipush        8
      10: imul
      11: i2d
      12: ldc2_w        #118                // double 7.0d
      15: ddiv
      16: invokestatic  #120                // Method java/lang/Math.ceil:(D)D
      19: d2i
      20: iconst_1
      21: iadd
      22: ireturn

  static int blobVarDecodedLength(int);
    Code:
       0: iload_0
       1: iconst_1
       2: isub
       3: bipush        7
       5: imul
       6: bipush        8
       8: idiv
       9: ireturn

  public static int encodeBlobVar(org.apache.hadoop.hbase.util.PositionedByteRange, byte[], int, int, org.apache.hadoop.hbase.util.Order);
    Code:
       0: aconst_null
       1: aload_1
       2: if_acmpne     12
       5: aload_0
       6: aload         4
       8: invokestatic  #82                 // Method encodeNull:(Lorg/apache/hadoop/hbase/util/PositionedByteRange;Lorg/apache/hadoop/hbase/util/Order;)I
      11: ireturn
      12: getstatic     #38                 // Field $assertionsDisabled:Z
      15: ifne          41
      18: aload_0
      19: invokeinterface #39,  1           // InterfaceMethod org/apache/hadoop/hbase/util/PositionedByteRange.getRemaining:()I
      24: iload_3
      25: invokestatic  #121                // Method blobVarEncodedLength:(I)I
      28: if_icmpge     41
      31: new           #40                 // class java/lang/AssertionError
      34: dup
      35: ldc           #122                // String buffer overflow expected.
      37: invokespecial #123                // Method java/lang/AssertionError."<init>":(Ljava/lang/Object;)V
      40: athrow
      41: aload_0
      42: invokeinterface #11,  1           // InterfaceMethod org/apache/hadoop/hbase/util/PositionedByteRange.getOffset:()I
      47: istore        5
      49: aload_0
      50: invokeinterface #12,  1           // InterfaceMethod org/apache/hadoop/hbase/util/PositionedByteRange.getPosition:()I
      55: istore        6
      57: aload_0
      58: bipush        55
      60: invokeinterface #10,  2           // InterfaceMethod org/apache/hadoop/hbase/util/PositionedByteRange.put:(B)Lorg/apache/hadoop/hbase/util/PositionedByteRange;
      65: pop
      66: iconst_0
      67: iload_3
      68: if_icmpne     82
      71: aload_0
      72: iconst_0
      73: invokeinterface #10,  2           // InterfaceMethod org/apache/hadoop/hbase/util/PositionedByteRange.put:(B)Lorg/apache/hadoop/hbase/util/PositionedByteRange;
      78: pop
      79: goto          243
      82: iconst_1
      83: istore        7
      85: iconst_0
      86: istore        8
      88: iload_2
      89: istore        9
      91: iload         9
      93: iload_3
      94: if_icmpge     181
      97: aload_0
      98: sipush        128
     101: iload         8
     103: ior
     104: aload_1
     105: iload         9
     107: baload
     108: sipush        255
     111: iand
     112: iload         7
     114: iushr
     115: ior
     116: i2b
     117: invokeinterface #10,  2           // InterfaceMethod org/apache/hadoop/hbase/util/PositionedByteRange.put:(B)Lorg/apache/hadoop/hbase/util/PositionedByteRange;
     122: pop
     123: iload         7
     125: bipush        7
     127: if_icmpge     153
     130: aload_1
     131: iload         9
     133: baload
     134: bipush        7
     136: iload         7
     138: isub
     139: ishl
     140: i2b
     141: istore        8
     143: iload         7
     145: iconst_1
     146: iadd
     147: i2b
     148: istore        7
     150: goto          175
     153: aload_0
     154: sipush        128
     157: aload_1
     158: iload         9
     160: baload
     161: ior
     162: i2b
     163: invokeinterface #10,  2           // InterfaceMethod org/apache/hadoop/hbase/util/PositionedByteRange.put:(B)Lorg/apache/hadoop/hbase/util/PositionedByteRange;
     168: pop
     169: iconst_1
     170: istore        7
     172: iconst_0
     173: istore        8
     175: iinc          9, 1
     178: goto          91
     181: iload         7
     183: iconst_1
     184: if_icmple     203
     187: aload_0
     188: bipush        127
     190: iload         8
     192: iand
     193: i2b
     194: invokeinterface #10,  2           // InterfaceMethod org/apache/hadoop/hbase/util/PositionedByteRange.put:(B)Lorg/apache/hadoop/hbase/util/PositionedByteRange;
     199: pop
     200: goto          243
     203: aload_0
     204: invokeinterface #13,  1           // InterfaceMethod org/apache/hadoop/hbase/util/PositionedByteRange.getBytes:()[B
     209: iload         5
     211: aload_0
     212: invokeinterface #12,  1           // InterfaceMethod org/apache/hadoop/hbase/util/PositionedByteRange.getPosition:()I
     217: iadd
     218: iconst_1
     219: isub
     220: aload_0
     221: invokeinterface #13,  1           // InterfaceMethod org/apache/hadoop/hbase/util/PositionedByteRange.getBytes:()[B
     226: iload         5
     228: aload_0
     229: invokeinterface #12,  1           // InterfaceMethod org/apache/hadoop/hbase/util/PositionedByteRange.getPosition:()I
     234: iadd
     235: iconst_1
     236: isub
     237: baload
     238: bipush        127
     240: iand
     241: i2b
     242: bastore
     243: aload         4
     245: aload_0
     246: invokeinterface #13,  1           // InterfaceMethod org/apache/hadoop/hbase/util/PositionedByteRange.getBytes:()[B
     251: iload         5
     253: iload         6
     255: iadd
     256: aload_0
     257: invokeinterface #12,  1           // InterfaceMethod org/apache/hadoop/hbase/util/PositionedByteRange.getPosition:()I
     262: iload         6
     264: isub
     265: invokevirtual #19                 // Method org/apache/hadoop/hbase/util/Order.apply:([BII)V
     268: aload_0
     269: invokeinterface #12,  1           // InterfaceMethod org/apache/hadoop/hbase/util/PositionedByteRange.getPosition:()I
     274: iload         6
     276: isub
     277: ireturn

  public static int encodeBlobVar(org.apache.hadoop.hbase.util.PositionedByteRange, byte[], org.apache.hadoop.hbase.util.Order);
    Code:
       0: aload_0
       1: aload_1
       2: iconst_0
       3: aconst_null
       4: aload_1
       5: if_acmpeq     13
       8: aload_1
       9: arraylength
      10: goto          14
      13: iconst_0
      14: aload_2
      15: invokestatic  #124                // Method encodeBlobVar:(Lorg/apache/hadoop/hbase/util/PositionedByteRange;[BIILorg/apache/hadoop/hbase/util/Order;)I
      18: ireturn

  public static byte[] decodeBlobVar(org.apache.hadoop.hbase.util.PositionedByteRange);
    Code:
       0: aload_0
       1: invokeinterface #42,  1           // InterfaceMethod org/apache/hadoop/hbase/util/PositionedByteRange.get:()B
       6: istore_1
       7: iload_1
       8: iconst_5
       9: if_icmpeq     23
      12: iload_1
      13: getstatic     #14                 // Field org/apache/hadoop/hbase/util/Order.DESCENDING:Lorg/apache/hadoop/hbase/util/Order;
      16: iconst_5
      17: invokevirtual #34                 // Method org/apache/hadoop/hbase/util/Order.apply:(B)B
      20: if_icmpne     25
      23: aconst_null
      24: areturn
      25: getstatic     #38                 // Field $assertionsDisabled:Z
      28: ifne          57
      31: iload_1
      32: bipush        55
      34: if_icmpeq     57
      37: iload_1
      38: getstatic     #14                 // Field org/apache/hadoop/hbase/util/Order.DESCENDING:Lorg/apache/hadoop/hbase/util/Order;
      41: bipush        55
      43: invokevirtual #34                 // Method org/apache/hadoop/hbase/util/Order.apply:(B)B
      46: if_icmpeq     57
      49: new           #40                 // class java/lang/AssertionError
      52: dup
      53: invokespecial #41                 // Method java/lang/AssertionError."<init>":()V
      56: athrow
      57: bipush        55
      59: iload_1
      60: if_icmpne     69
      63: getstatic     #15                 // Field org/apache/hadoop/hbase/util/Order.ASCENDING:Lorg/apache/hadoop/hbase/util/Order;
      66: goto          72
      69: getstatic     #14                 // Field org/apache/hadoop/hbase/util/Order.DESCENDING:Lorg/apache/hadoop/hbase/util/Order;
      72: astore_2
      73: aload_0
      74: invokeinterface #33,  1           // InterfaceMethod org/apache/hadoop/hbase/util/PositionedByteRange.peek:()B
      79: aload_2
      80: iconst_0
      81: invokevirtual #34                 // Method org/apache/hadoop/hbase/util/Order.apply:(B)B
      84: if_icmpne     98
      87: aload_0
      88: invokeinterface #42,  1           // InterfaceMethod org/apache/hadoop/hbase/util/PositionedByteRange.get:()B
      93: pop
      94: iconst_0
      95: newarray       byte
      97: areturn
      98: aload_0
      99: invokeinterface #11,  1           // InterfaceMethod org/apache/hadoop/hbase/util/PositionedByteRange.getOffset:()I
     104: istore_3
     105: aload_0
     106: invokeinterface #12,  1           // InterfaceMethod org/apache/hadoop/hbase/util/PositionedByteRange.getPosition:()I
     111: istore        4
     113: aload_0
     114: invokeinterface #13,  1           // InterfaceMethod org/apache/hadoop/hbase/util/PositionedByteRange.getBytes:()[B
     119: astore        6
     121: iload         4
     123: istore        5
     125: aload_2
     126: aload         6
     128: iload_3
     129: iload         5
     131: iadd
     132: baload
     133: invokevirtual #34                 // Method org/apache/hadoop/hbase/util/Order.apply:(B)B
     136: sipush        128
     139: iand
     140: i2b
     141: ifeq          150
     144: iinc          5, 1
     147: goto          125
     150: iinc          5, 1
     153: new           #125                // class org/apache/hadoop/hbase/util/SimplePositionedMutableByteRange
     156: dup
     157: iload         5
     159: iload         4
     161: isub
     162: iconst_1
     163: iadd
     164: invokestatic  #126                // Method blobVarDecodedLength:(I)I
     167: invokespecial #127                // Method org/apache/hadoop/hbase/util/SimplePositionedMutableByteRange."<init>":(I)V
     170: astore        7
     172: bipush        6
     174: istore        8
     176: aload_2
     177: aload         6
     179: iload_3
     180: iload         4
     182: iadd
     183: baload
     184: invokevirtual #34                 // Method org/apache/hadoop/hbase/util/Order.apply:(B)B
     187: iconst_1
     188: ishl
     189: sipush        255
     192: iand
     193: i2b
     194: istore        9
     196: iload         4
     198: iconst_1
     199: iadd
     200: istore        10
     202: iload         10
     204: iload         5
     206: if_icmpge     337
     209: iload         8
     211: bipush        7
     213: if_icmpne     251
     216: aload         7
     218: iload         9
     220: aload_2
     221: aload         6
     223: iload_3
     224: iload         10
     226: iadd
     227: baload
     228: invokevirtual #34                 // Method org/apache/hadoop/hbase/util/Order.apply:(B)B
     231: bipush        127
     233: iand
     234: ior
     235: i2b
     236: invokeinterface #10,  2           // InterfaceMethod org/apache/hadoop/hbase/util/PositionedByteRange.put:(B)Lorg/apache/hadoop/hbase/util/PositionedByteRange;
     241: pop
     242: iinc          10, 1
     245: iconst_0
     246: istore        9
     248: goto          280
     251: aload         7
     253: iload         9
     255: aload_2
     256: aload         6
     258: iload_3
     259: iload         10
     261: iadd
     262: baload
     263: invokevirtual #34                 // Method org/apache/hadoop/hbase/util/Order.apply:(B)B
     266: bipush        127
     268: iand
     269: iload         8
     271: iushr
     272: ior
     273: i2b
     274: invokeinterface #10,  2           // InterfaceMethod org/apache/hadoop/hbase/util/PositionedByteRange.put:(B)Lorg/apache/hadoop/hbase/util/PositionedByteRange;
     279: pop
     280: iload         10
     282: iload         5
     284: if_icmpne     290
     287: goto          337
     290: aload_2
     291: aload         6
     293: iload_3
     294: iload         10
     296: iadd
     297: baload
     298: invokevirtual #34                 // Method org/apache/hadoop/hbase/util/Order.apply:(B)B
     301: bipush        8
     303: iload         8
     305: isub
     306: ishl
     307: sipush        255
     310: iand
     311: i2b
     312: istore        9
     314: iload         8
     316: iconst_1
     317: if_icmpne     325
     320: bipush        7
     322: goto          329
     325: iload         8
     327: iconst_1
     328: isub
     329: istore        8
     331: iinc          10, 1
     334: goto          202
     337: aload_0
     338: iload         5
     340: invokeinterface #37,  2           // InterfaceMethod org/apache/hadoop/hbase/util/PositionedByteRange.setPosition:(I)Lorg/apache/hadoop/hbase/util/PositionedByteRange;
     345: pop
     346: getstatic     #38                 // Field $assertionsDisabled:Z
     349: ifne          367
     352: iload         9
     354: ifeq          367
     357: new           #40                 // class java/lang/AssertionError
     360: dup
     361: ldc           #128                // String Unexpected bits remaining after decoding blob.
     363: invokespecial #123                // Method java/lang/AssertionError."<init>":(Ljava/lang/Object;)V
     366: athrow
     367: getstatic     #38                 // Field $assertionsDisabled:Z
     370: ifne          400
     373: aload         7
     375: invokeinterface #12,  1           // InterfaceMethod org/apache/hadoop/hbase/util/PositionedByteRange.getPosition:()I
     380: aload         7
     382: invokeinterface #129,  1          // InterfaceMethod org/apache/hadoop/hbase/util/PositionedByteRange.getLength:()I
     387: if_icmpeq     400
     390: new           #40                 // class java/lang/AssertionError
     393: dup
     394: ldc           #130                // String Allocated unnecessarily large return buffer.
     396: invokespecial #123                // Method java/lang/AssertionError."<init>":(Ljava/lang/Object;)V
     399: athrow
     400: aload         7
     402: invokeinterface #13,  1           // InterfaceMethod org/apache/hadoop/hbase/util/PositionedByteRange.getBytes:()[B
     407: areturn

  public static int encodeBlobCopy(org.apache.hadoop.hbase.util.PositionedByteRange, byte[], int, int, org.apache.hadoop.hbase.util.Order);
    Code:
       0: aconst_null
       1: aload_1
       2: if_acmpne     37
       5: aload_0
       6: aload         4
       8: invokestatic  #82                 // Method encodeNull:(Lorg/apache/hadoop/hbase/util/PositionedByteRange;Lorg/apache/hadoop/hbase/util/Order;)I
      11: pop
      12: getstatic     #15                 // Field org/apache/hadoop/hbase/util/Order.ASCENDING:Lorg/apache/hadoop/hbase/util/Order;
      15: aload         4
      17: if_acmpne     22
      20: iconst_1
      21: ireturn
      22: aload_0
      23: aload         4
      25: iconst_0
      26: invokevirtual #34                 // Method org/apache/hadoop/hbase/util/Order.apply:(B)B
      29: invokeinterface #10,  2           // InterfaceMethod org/apache/hadoop/hbase/util/PositionedByteRange.put:(B)Lorg/apache/hadoop/hbase/util/PositionedByteRange;
      34: pop
      35: iconst_2
      36: ireturn
      37: getstatic     #38                 // Field $assertionsDisabled:Z
      40: ifne          75
      43: aload_0
      44: invokeinterface #39,  1           // InterfaceMethod org/apache/hadoop/hbase/util/PositionedByteRange.getRemaining:()I
      49: iload_3
      50: getstatic     #15                 // Field org/apache/hadoop/hbase/util/Order.ASCENDING:Lorg/apache/hadoop/hbase/util/Order;
      53: aload         4
      55: if_acmpne     62
      58: iconst_1
      59: goto          63
      62: iconst_2
      63: iadd
      64: if_icmpge     75
      67: new           #40                 // class java/lang/AssertionError
      70: dup
      71: invokespecial #41                 // Method java/lang/AssertionError."<init>":()V
      74: athrow
      75: getstatic     #14                 // Field org/apache/hadoop/hbase/util/Order.DESCENDING:Lorg/apache/hadoop/hbase/util/Order;
      78: aload         4
      80: if_acmpne     118
      83: iconst_0
      84: istore        5
      86: iload         5
      88: iload_3
      89: if_icmpge     118
      92: iconst_0
      93: aload_1
      94: iload_2
      95: iload         5
      97: iadd
      98: baload
      99: if_icmpne     112
     102: new           #2                  // class java/lang/IllegalArgumentException
     105: dup
     106: ldc           #131                // String 0x00 bytes not permitted in value.
     108: invokespecial #9                  // Method java/lang/IllegalArgumentException."<init>":(Ljava/lang/String;)V
     111: athrow
     112: iinc          5, 1
     115: goto          86
     118: aload_0
     119: invokeinterface #11,  1           // InterfaceMethod org/apache/hadoop/hbase/util/PositionedByteRange.getOffset:()I
     124: istore        5
     126: aload_0
     127: invokeinterface #12,  1           // InterfaceMethod org/apache/hadoop/hbase/util/PositionedByteRange.getPosition:()I
     132: istore        6
     134: aload_0
     135: bipush        56
     137: invokeinterface #10,  2           // InterfaceMethod org/apache/hadoop/hbase/util/PositionedByteRange.put:(B)Lorg/apache/hadoop/hbase/util/PositionedByteRange;
     142: pop
     143: aload_0
     144: aload_1
     145: iload_2
     146: iload_3
     147: invokeinterface #132,  4          // InterfaceMethod org/apache/hadoop/hbase/util/PositionedByteRange.put:([BII)Lorg/apache/hadoop/hbase/util/PositionedByteRange;
     152: pop
     153: getstatic     #14                 // Field org/apache/hadoop/hbase/util/Order.DESCENDING:Lorg/apache/hadoop/hbase/util/Order;
     156: aload         4
     158: if_acmpne     169
     161: aload_0
     162: iconst_0
     163: invokeinterface #10,  2           // InterfaceMethod org/apache/hadoop/hbase/util/PositionedByteRange.put:(B)Lorg/apache/hadoop/hbase/util/PositionedByteRange;
     168: pop
     169: aload         4
     171: aload_0
     172: invokeinterface #13,  1           // InterfaceMethod org/apache/hadoop/hbase/util/PositionedByteRange.getBytes:()[B
     177: iload         5
     179: iload         6
     181: iadd
     182: aload_0
     183: invokeinterface #12,  1           // InterfaceMethod org/apache/hadoop/hbase/util/PositionedByteRange.getPosition:()I
     188: iload         6
     190: isub
     191: invokevirtual #19                 // Method org/apache/hadoop/hbase/util/Order.apply:([BII)V
     194: aload_0
     195: invokeinterface #12,  1           // InterfaceMethod org/apache/hadoop/hbase/util/PositionedByteRange.getPosition:()I
     200: iload         6
     202: isub
     203: ireturn

  public static int encodeBlobCopy(org.apache.hadoop.hbase.util.PositionedByteRange, byte[], org.apache.hadoop.hbase.util.Order);
    Code:
       0: aload_0
       1: aload_1
       2: iconst_0
       3: aconst_null
       4: aload_1
       5: if_acmpeq     13
       8: aload_1
       9: arraylength
      10: goto          14
      13: iconst_0
      14: aload_2
      15: invokestatic  #133                // Method encodeBlobCopy:(Lorg/apache/hadoop/hbase/util/PositionedByteRange;[BIILorg/apache/hadoop/hbase/util/Order;)I
      18: ireturn

  public static byte[] decodeBlobCopy(org.apache.hadoop.hbase.util.PositionedByteRange);
    Code:
       0: aload_0
       1: invokeinterface #42,  1           // InterfaceMethod org/apache/hadoop/hbase/util/PositionedByteRange.get:()B
       6: istore_1
       7: iload_1
       8: iconst_5
       9: if_icmpeq     23
      12: iload_1
      13: getstatic     #14                 // Field org/apache/hadoop/hbase/util/Order.DESCENDING:Lorg/apache/hadoop/hbase/util/Order;
      16: iconst_5
      17: invokevirtual #34                 // Method org/apache/hadoop/hbase/util/Order.apply:(B)B
      20: if_icmpne     25
      23: aconst_null
      24: areturn
      25: getstatic     #38                 // Field $assertionsDisabled:Z
      28: ifne          57
      31: iload_1
      32: bipush        56
      34: if_icmpeq     57
      37: iload_1
      38: getstatic     #14                 // Field org/apache/hadoop/hbase/util/Order.DESCENDING:Lorg/apache/hadoop/hbase/util/Order;
      41: bipush        56
      43: invokevirtual #34                 // Method org/apache/hadoop/hbase/util/Order.apply:(B)B
      46: if_icmpeq     57
      49: new           #40                 // class java/lang/AssertionError
      52: dup
      53: invokespecial #41                 // Method java/lang/AssertionError."<init>":()V
      56: athrow
      57: iload_1
      58: bipush        56
      60: if_icmpne     69
      63: getstatic     #15                 // Field org/apache/hadoop/hbase/util/Order.ASCENDING:Lorg/apache/hadoop/hbase/util/Order;
      66: goto          72
      69: getstatic     #14                 // Field org/apache/hadoop/hbase/util/Order.DESCENDING:Lorg/apache/hadoop/hbase/util/Order;
      72: astore_2
      73: aload_0
      74: invokeinterface #39,  1           // InterfaceMethod org/apache/hadoop/hbase/util/PositionedByteRange.getRemaining:()I
      79: getstatic     #15                 // Field org/apache/hadoop/hbase/util/Order.ASCENDING:Lorg/apache/hadoop/hbase/util/Order;
      82: aload_2
      83: if_acmpne     90
      86: iconst_0
      87: goto          91
      90: iconst_1
      91: isub
      92: istore_3
      93: iload_3
      94: newarray       byte
      96: astore        4
      98: aload_0
      99: aload         4
     101: invokeinterface #134,  2          // InterfaceMethod org/apache/hadoop/hbase/util/PositionedByteRange.get:([B)Lorg/apache/hadoop/hbase/util/PositionedByteRange;
     106: pop
     107: aload_2
     108: aload         4
     110: iconst_0
     111: aload         4
     113: arraylength
     114: invokevirtual #19                 // Method org/apache/hadoop/hbase/util/Order.apply:([BII)V
     117: getstatic     #14                 // Field org/apache/hadoop/hbase/util/Order.DESCENDING:Lorg/apache/hadoop/hbase/util/Order;
     120: aload_2
     121: if_acmpne     131
     124: aload_0
     125: invokeinterface #42,  1           // InterfaceMethod org/apache/hadoop/hbase/util/PositionedByteRange.get:()B
     130: pop
     131: aload         4
     133: areturn

  public static int encodeNull(org.apache.hadoop.hbase.util.PositionedByteRange, org.apache.hadoop.hbase.util.Order);
    Code:
       0: aload_0
       1: aload_1
       2: iconst_5
       3: invokevirtual #34                 // Method org/apache/hadoop/hbase/util/Order.apply:(B)B
       6: invokeinterface #10,  2           // InterfaceMethod org/apache/hadoop/hbase/util/PositionedByteRange.put:(B)Lorg/apache/hadoop/hbase/util/PositionedByteRange;
      11: pop
      12: iconst_1
      13: ireturn

  public static int encodeInt8(org.apache.hadoop.hbase.util.PositionedByteRange, byte, org.apache.hadoop.hbase.util.Order);
    Code:
       0: aload_0
       1: invokeinterface #11,  1           // InterfaceMethod org/apache/hadoop/hbase/util/PositionedByteRange.getOffset:()I
       6: istore_3
       7: aload_0
       8: invokeinterface #12,  1           // InterfaceMethod org/apache/hadoop/hbase/util/PositionedByteRange.getPosition:()I
      13: istore        4
      15: aload_0
      16: bipush        41
      18: invokeinterface #10,  2           // InterfaceMethod org/apache/hadoop/hbase/util/PositionedByteRange.put:(B)Lorg/apache/hadoop/hbase/util/PositionedByteRange;
      23: iload_1
      24: sipush        128
      27: ixor
      28: i2b
      29: invokeinterface #10,  2           // InterfaceMethod org/apache/hadoop/hbase/util/PositionedByteRange.put:(B)Lorg/apache/hadoop/hbase/util/PositionedByteRange;
      34: pop
      35: aload_2
      36: aload_0
      37: invokeinterface #13,  1           // InterfaceMethod org/apache/hadoop/hbase/util/PositionedByteRange.getBytes:()[B
      42: iload_3
      43: iload         4
      45: iadd
      46: iconst_2
      47: invokevirtual #19                 // Method org/apache/hadoop/hbase/util/Order.apply:([BII)V
      50: iconst_2
      51: ireturn

  public static byte decodeInt8(org.apache.hadoop.hbase.util.PositionedByteRange);
    Code:
       0: aload_0
       1: invokeinterface #42,  1           // InterfaceMethod org/apache/hadoop/hbase/util/PositionedByteRange.get:()B
       6: istore_1
       7: getstatic     #38                 // Field $assertionsDisabled:Z
      10: ifne          39
      13: iload_1
      14: bipush        41
      16: if_icmpeq     39
      19: iload_1
      20: getstatic     #14                 // Field org/apache/hadoop/hbase/util/Order.DESCENDING:Lorg/apache/hadoop/hbase/util/Order;
      23: bipush        41
      25: invokevirtual #34                 // Method org/apache/hadoop/hbase/util/Order.apply:(B)B
      28: if_icmpeq     39
      31: new           #40                 // class java/lang/AssertionError
      34: dup
      35: invokespecial #41                 // Method java/lang/AssertionError."<init>":()V
      38: athrow
      39: iload_1
      40: bipush        41
      42: if_icmpne     51
      45: getstatic     #15                 // Field org/apache/hadoop/hbase/util/Order.ASCENDING:Lorg/apache/hadoop/hbase/util/Order;
      48: goto          54
      51: getstatic     #14                 // Field org/apache/hadoop/hbase/util/Order.DESCENDING:Lorg/apache/hadoop/hbase/util/Order;
      54: astore_2
      55: aload_2
      56: aload_0
      57: invokeinterface #42,  1           // InterfaceMethod org/apache/hadoop/hbase/util/PositionedByteRange.get:()B
      62: invokevirtual #34                 // Method org/apache/hadoop/hbase/util/Order.apply:(B)B
      65: sipush        128
      68: ixor
      69: sipush        255
      72: iand
      73: i2b
      74: ireturn

  public static int encodeInt16(org.apache.hadoop.hbase.util.PositionedByteRange, short, org.apache.hadoop.hbase.util.Order);
    Code:
       0: aload_0
       1: invokeinterface #11,  1           // InterfaceMethod org/apache/hadoop/hbase/util/PositionedByteRange.getOffset:()I
       6: istore_3
       7: aload_0
       8: invokeinterface #12,  1           // InterfaceMethod org/apache/hadoop/hbase/util/PositionedByteRange.getPosition:()I
      13: istore        4
      15: aload_0
      16: bipush        42
      18: invokeinterface #10,  2           // InterfaceMethod org/apache/hadoop/hbase/util/PositionedByteRange.put:(B)Lorg/apache/hadoop/hbase/util/PositionedByteRange;
      23: iload_1
      24: bipush        8
      26: ishr
      27: sipush        128
      30: ixor
      31: i2b
      32: invokeinterface #10,  2           // InterfaceMethod org/apache/hadoop/hbase/util/PositionedByteRange.put:(B)Lorg/apache/hadoop/hbase/util/PositionedByteRange;
      37: iload_1
      38: i2b
      39: invokeinterface #10,  2           // InterfaceMethod org/apache/hadoop/hbase/util/PositionedByteRange.put:(B)Lorg/apache/hadoop/hbase/util/PositionedByteRange;
      44: pop
      45: aload_2
      46: aload_0
      47: invokeinterface #13,  1           // InterfaceMethod org/apache/hadoop/hbase/util/PositionedByteRange.getBytes:()[B
      52: iload_3
      53: iload         4
      55: iadd
      56: iconst_3
      57: invokevirtual #19                 // Method org/apache/hadoop/hbase/util/Order.apply:([BII)V
      60: iconst_3
      61: ireturn

  public static short decodeInt16(org.apache.hadoop.hbase.util.PositionedByteRange);
    Code:
       0: aload_0
       1: invokeinterface #42,  1           // InterfaceMethod org/apache/hadoop/hbase/util/PositionedByteRange.get:()B
       6: istore_1
       7: getstatic     #38                 // Field $assertionsDisabled:Z
      10: ifne          39
      13: iload_1
      14: bipush        42
      16: if_icmpeq     39
      19: iload_1
      20: getstatic     #14                 // Field org/apache/hadoop/hbase/util/Order.DESCENDING:Lorg/apache/hadoop/hbase/util/Order;
      23: bipush        42
      25: invokevirtual #34                 // Method org/apache/hadoop/hbase/util/Order.apply:(B)B
      28: if_icmpeq     39
      31: new           #40                 // class java/lang/AssertionError
      34: dup
      35: invokespecial #41                 // Method java/lang/AssertionError."<init>":()V
      38: athrow
      39: iload_1
      40: bipush        42
      42: if_icmpne     51
      45: getstatic     #15                 // Field org/apache/hadoop/hbase/util/Order.ASCENDING:Lorg/apache/hadoop/hbase/util/Order;
      48: goto          54
      51: getstatic     #14                 // Field org/apache/hadoop/hbase/util/Order.DESCENDING:Lorg/apache/hadoop/hbase/util/Order;
      54: astore_2
      55: aload_2
      56: aload_0
      57: invokeinterface #42,  1           // InterfaceMethod org/apache/hadoop/hbase/util/PositionedByteRange.get:()B
      62: invokevirtual #34                 // Method org/apache/hadoop/hbase/util/Order.apply:(B)B
      65: sipush        128
      68: ixor
      69: sipush        255
      72: iand
      73: i2s
      74: istore_3
      75: iload_3
      76: bipush        8
      78: ishl
      79: aload_2
      80: aload_0
      81: invokeinterface #42,  1           // InterfaceMethod org/apache/hadoop/hbase/util/PositionedByteRange.get:()B
      86: invokevirtual #34                 // Method org/apache/hadoop/hbase/util/Order.apply:(B)B
      89: sipush        255
      92: iand
      93: iadd
      94: i2s
      95: istore_3
      96: iload_3
      97: ireturn

  public static int encodeInt32(org.apache.hadoop.hbase.util.PositionedByteRange, int, org.apache.hadoop.hbase.util.Order);
    Code:
       0: aload_0
       1: invokeinterface #11,  1           // InterfaceMethod org/apache/hadoop/hbase/util/PositionedByteRange.getOffset:()I
       6: istore_3
       7: aload_0
       8: invokeinterface #12,  1           // InterfaceMethod org/apache/hadoop/hbase/util/PositionedByteRange.getPosition:()I
      13: istore        4
      15: aload_0
      16: bipush        43
      18: invokeinterface #10,  2           // InterfaceMethod org/apache/hadoop/hbase/util/PositionedByteRange.put:(B)Lorg/apache/hadoop/hbase/util/PositionedByteRange;
      23: iload_1
      24: bipush        24
      26: ishr
      27: sipush        128
      30: ixor
      31: i2b
      32: invokeinterface #10,  2           // InterfaceMethod org/apache/hadoop/hbase/util/PositionedByteRange.put:(B)Lorg/apache/hadoop/hbase/util/PositionedByteRange;
      37: iload_1
      38: bipush        16
      40: ishr
      41: i2b
      42: invokeinterface #10,  2           // InterfaceMethod org/apache/hadoop/hbase/util/PositionedByteRange.put:(B)Lorg/apache/hadoop/hbase/util/PositionedByteRange;
      47: iload_1
      48: bipush        8
      50: ishr
      51: i2b
      52: invokeinterface #10,  2           // InterfaceMethod org/apache/hadoop/hbase/util/PositionedByteRange.put:(B)Lorg/apache/hadoop/hbase/util/PositionedByteRange;
      57: iload_1
      58: i2b
      59: invokeinterface #10,  2           // InterfaceMethod org/apache/hadoop/hbase/util/PositionedByteRange.put:(B)Lorg/apache/hadoop/hbase/util/PositionedByteRange;
      64: pop
      65: aload_2
      66: aload_0
      67: invokeinterface #13,  1           // InterfaceMethod org/apache/hadoop/hbase/util/PositionedByteRange.getBytes:()[B
      72: iload_3
      73: iload         4
      75: iadd
      76: iconst_5
      77: invokevirtual #19                 // Method org/apache/hadoop/hbase/util/Order.apply:([BII)V
      80: iconst_5
      81: ireturn

  public static int decodeInt32(org.apache.hadoop.hbase.util.PositionedByteRange);
    Code:
       0: aload_0
       1: invokeinterface #42,  1           // InterfaceMethod org/apache/hadoop/hbase/util/PositionedByteRange.get:()B
       6: istore_1
       7: getstatic     #38                 // Field $assertionsDisabled:Z
      10: ifne          39
      13: iload_1
      14: bipush        43
      16: if_icmpeq     39
      19: iload_1
      20: getstatic     #14                 // Field org/apache/hadoop/hbase/util/Order.DESCENDING:Lorg/apache/hadoop/hbase/util/Order;
      23: bipush        43
      25: invokevirtual #34                 // Method org/apache/hadoop/hbase/util/Order.apply:(B)B
      28: if_icmpeq     39
      31: new           #40                 // class java/lang/AssertionError
      34: dup
      35: invokespecial #41                 // Method java/lang/AssertionError."<init>":()V
      38: athrow
      39: iload_1
      40: bipush        43
      42: if_icmpne     51
      45: getstatic     #15                 // Field org/apache/hadoop/hbase/util/Order.ASCENDING:Lorg/apache/hadoop/hbase/util/Order;
      48: goto          54
      51: getstatic     #14                 // Field org/apache/hadoop/hbase/util/Order.DESCENDING:Lorg/apache/hadoop/hbase/util/Order;
      54: astore_2
      55: aload_2
      56: aload_0
      57: invokeinterface #42,  1           // InterfaceMethod org/apache/hadoop/hbase/util/PositionedByteRange.get:()B
      62: invokevirtual #34                 // Method org/apache/hadoop/hbase/util/Order.apply:(B)B
      65: sipush        128
      68: ixor
      69: sipush        255
      72: iand
      73: istore_3
      74: iconst_1
      75: istore        4
      77: iload         4
      79: iconst_4
      80: if_icmpge     109
      83: iload_3
      84: bipush        8
      86: ishl
      87: aload_2
      88: aload_0
      89: invokeinterface #42,  1           // InterfaceMethod org/apache/hadoop/hbase/util/PositionedByteRange.get:()B
      94: invokevirtual #34                 // Method org/apache/hadoop/hbase/util/Order.apply:(B)B
      97: sipush        255
     100: iand
     101: iadd
     102: istore_3
     103: iinc          4, 1
     106: goto          77
     109: iload_3
     110: ireturn

  public static int encodeInt64(org.apache.hadoop.hbase.util.PositionedByteRange, long, org.apache.hadoop.hbase.util.Order);
    Code:
       0: aload_0
       1: invokeinterface #11,  1           // InterfaceMethod org/apache/hadoop/hbase/util/PositionedByteRange.getOffset:()I
       6: istore        4
       8: aload_0
       9: invokeinterface #12,  1           // InterfaceMethod org/apache/hadoop/hbase/util/PositionedByteRange.getPosition:()I
      14: istore        5
      16: aload_0
      17: bipush        44
      19: invokeinterface #10,  2           // InterfaceMethod org/apache/hadoop/hbase/util/PositionedByteRange.put:(B)Lorg/apache/hadoop/hbase/util/PositionedByteRange;
      24: lload_1
      25: bipush        56
      27: lshr
      28: ldc2_w        #135                // long 128l
      31: lxor
      32: l2i
      33: i2b
      34: invokeinterface #10,  2           // InterfaceMethod org/apache/hadoop/hbase/util/PositionedByteRange.put:(B)Lorg/apache/hadoop/hbase/util/PositionedByteRange;
      39: lload_1
      40: bipush        48
      42: lshr
      43: l2i
      44: i2b
      45: invokeinterface #10,  2           // InterfaceMethod org/apache/hadoop/hbase/util/PositionedByteRange.put:(B)Lorg/apache/hadoop/hbase/util/PositionedByteRange;
      50: lload_1
      51: bipush        40
      53: lshr
      54: l2i
      55: i2b
      56: invokeinterface #10,  2           // InterfaceMethod org/apache/hadoop/hbase/util/PositionedByteRange.put:(B)Lorg/apache/hadoop/hbase/util/PositionedByteRange;
      61: lload_1
      62: bipush        32
      64: lshr
      65: l2i
      66: i2b
      67: invokeinterface #10,  2           // InterfaceMethod org/apache/hadoop/hbase/util/PositionedByteRange.put:(B)Lorg/apache/hadoop/hbase/util/PositionedByteRange;
      72: lload_1
      73: bipush        24
      75: lshr
      76: l2i
      77: i2b
      78: invokeinterface #10,  2           // InterfaceMethod org/apache/hadoop/hbase/util/PositionedByteRange.put:(B)Lorg/apache/hadoop/hbase/util/PositionedByteRange;
      83: lload_1
      84: bipush        16
      86: lshr
      87: l2i
      88: i2b
      89: invokeinterface #10,  2           // InterfaceMethod org/apache/hadoop/hbase/util/PositionedByteRange.put:(B)Lorg/apache/hadoop/hbase/util/PositionedByteRange;
      94: lload_1
      95: bipush        8
      97: lshr
      98: l2i
      99: i2b
     100: invokeinterface #10,  2           // InterfaceMethod org/apache/hadoop/hbase/util/PositionedByteRange.put:(B)Lorg/apache/hadoop/hbase/util/PositionedByteRange;
     105: lload_1
     106: l2i
     107: i2b
     108: invokeinterface #10,  2           // InterfaceMethod org/apache/hadoop/hbase/util/PositionedByteRange.put:(B)Lorg/apache/hadoop/hbase/util/PositionedByteRange;
     113: pop
     114: aload_3
     115: aload_0
     116: invokeinterface #13,  1           // InterfaceMethod org/apache/hadoop/hbase/util/PositionedByteRange.getBytes:()[B
     121: iload         4
     123: iload         5
     125: iadd
     126: bipush        9
     128: invokevirtual #19                 // Method org/apache/hadoop/hbase/util/Order.apply:([BII)V
     131: bipush        9
     133: ireturn

  public static long decodeInt64(org.apache.hadoop.hbase.util.PositionedByteRange);
    Code:
       0: aload_0
       1: invokeinterface #42,  1           // InterfaceMethod org/apache/hadoop/hbase/util/PositionedByteRange.get:()B
       6: istore_1
       7: getstatic     #38                 // Field $assertionsDisabled:Z
      10: ifne          39
      13: iload_1
      14: bipush        44
      16: if_icmpeq     39
      19: iload_1
      20: getstatic     #14                 // Field org/apache/hadoop/hbase/util/Order.DESCENDING:Lorg/apache/hadoop/hbase/util/Order;
      23: bipush        44
      25: invokevirtual #34                 // Method org/apache/hadoop/hbase/util/Order.apply:(B)B
      28: if_icmpeq     39
      31: new           #40                 // class java/lang/AssertionError
      34: dup
      35: invokespecial #41                 // Method java/lang/AssertionError."<init>":()V
      38: athrow
      39: iload_1
      40: bipush        44
      42: if_icmpne     51
      45: getstatic     #15                 // Field org/apache/hadoop/hbase/util/Order.ASCENDING:Lorg/apache/hadoop/hbase/util/Order;
      48: goto          54
      51: getstatic     #14                 // Field org/apache/hadoop/hbase/util/Order.DESCENDING:Lorg/apache/hadoop/hbase/util/Order;
      54: astore_2
      55: aload_2
      56: aload_0
      57: invokeinterface #42,  1           // InterfaceMethod org/apache/hadoop/hbase/util/PositionedByteRange.get:()B
      62: invokevirtual #34                 // Method org/apache/hadoop/hbase/util/Order.apply:(B)B
      65: sipush        128
      68: ixor
      69: sipush        255
      72: iand
      73: i2l
      74: lstore_3
      75: iconst_1
      76: istore        5
      78: iload         5
      80: bipush        8
      82: if_icmpge     112
      85: lload_3
      86: bipush        8
      88: lshl
      89: aload_2
      90: aload_0
      91: invokeinterface #42,  1           // InterfaceMethod org/apache/hadoop/hbase/util/PositionedByteRange.get:()B
      96: invokevirtual #34                 // Method org/apache/hadoop/hbase/util/Order.apply:(B)B
      99: sipush        255
     102: iand
     103: i2l
     104: ladd
     105: lstore_3
     106: iinc          5, 1
     109: goto          78
     112: lload_3
     113: lreturn

  public static int encodeFloat32(org.apache.hadoop.hbase.util.PositionedByteRange, float, org.apache.hadoop.hbase.util.Order);
    Code:
       0: aload_0
       1: invokeinterface #11,  1           // InterfaceMethod org/apache/hadoop/hbase/util/PositionedByteRange.getOffset:()I
       6: istore_3
       7: aload_0
       8: invokeinterface #12,  1           // InterfaceMethod org/apache/hadoop/hbase/util/PositionedByteRange.getPosition:()I
      13: istore        4
      15: fload_1
      16: invokestatic  #137                // Method java/lang/Float.floatToIntBits:(F)I
      19: istore        5
      21: iload         5
      23: iload         5
      25: bipush        31
      27: ishr
      28: ldc           #139                // int -2147483648
      30: ior
      31: ixor
      32: istore        5
      34: aload_0
      35: bipush        48
      37: invokeinterface #10,  2           // InterfaceMethod org/apache/hadoop/hbase/util/PositionedByteRange.put:(B)Lorg/apache/hadoop/hbase/util/PositionedByteRange;
      42: iload         5
      44: bipush        24
      46: ishr
      47: i2b
      48: invokeinterface #10,  2           // InterfaceMethod org/apache/hadoop/hbase/util/PositionedByteRange.put:(B)Lorg/apache/hadoop/hbase/util/PositionedByteRange;
      53: iload         5
      55: bipush        16
      57: ishr
      58: i2b
      59: invokeinterface #10,  2           // InterfaceMethod org/apache/hadoop/hbase/util/PositionedByteRange.put:(B)Lorg/apache/hadoop/hbase/util/PositionedByteRange;
      64: iload         5
      66: bipush        8
      68: ishr
      69: i2b
      70: invokeinterface #10,  2           // InterfaceMethod org/apache/hadoop/hbase/util/PositionedByteRange.put:(B)Lorg/apache/hadoop/hbase/util/PositionedByteRange;
      75: iload         5
      77: i2b
      78: invokeinterface #10,  2           // InterfaceMethod org/apache/hadoop/hbase/util/PositionedByteRange.put:(B)Lorg/apache/hadoop/hbase/util/PositionedByteRange;
      83: pop
      84: aload_2
      85: aload_0
      86: invokeinterface #13,  1           // InterfaceMethod org/apache/hadoop/hbase/util/PositionedByteRange.getBytes:()[B
      91: iload_3
      92: iload         4
      94: iadd
      95: iconst_5
      96: invokevirtual #19                 // Method org/apache/hadoop/hbase/util/Order.apply:([BII)V
      99: iconst_5
     100: ireturn

  public static float decodeFloat32(org.apache.hadoop.hbase.util.PositionedByteRange);
    Code:
       0: aload_0
       1: invokeinterface #42,  1           // InterfaceMethod org/apache/hadoop/hbase/util/PositionedByteRange.get:()B
       6: istore_1
       7: getstatic     #38                 // Field $assertionsDisabled:Z
      10: ifne          39
      13: iload_1
      14: bipush        48
      16: if_icmpeq     39
      19: iload_1
      20: getstatic     #14                 // Field org/apache/hadoop/hbase/util/Order.DESCENDING:Lorg/apache/hadoop/hbase/util/Order;
      23: bipush        48
      25: invokevirtual #34                 // Method org/apache/hadoop/hbase/util/Order.apply:(B)B
      28: if_icmpeq     39
      31: new           #40                 // class java/lang/AssertionError
      34: dup
      35: invokespecial #41                 // Method java/lang/AssertionError."<init>":()V
      38: athrow
      39: iload_1
      40: bipush        48
      42: if_icmpne     51
      45: getstatic     #15                 // Field org/apache/hadoop/hbase/util/Order.ASCENDING:Lorg/apache/hadoop/hbase/util/Order;
      48: goto          54
      51: getstatic     #14                 // Field org/apache/hadoop/hbase/util/Order.DESCENDING:Lorg/apache/hadoop/hbase/util/Order;
      54: astore_2
      55: aload_2
      56: aload_0
      57: invokeinterface #42,  1           // InterfaceMethod org/apache/hadoop/hbase/util/PositionedByteRange.get:()B
      62: invokevirtual #34                 // Method org/apache/hadoop/hbase/util/Order.apply:(B)B
      65: sipush        255
      68: iand
      69: istore_3
      70: iconst_1
      71: istore        4
      73: iload         4
      75: iconst_4
      76: if_icmpge     105
      79: iload_3
      80: bipush        8
      82: ishl
      83: aload_2
      84: aload_0
      85: invokeinterface #42,  1           // InterfaceMethod org/apache/hadoop/hbase/util/PositionedByteRange.get:()B
      90: invokevirtual #34                 // Method org/apache/hadoop/hbase/util/Order.apply:(B)B
      93: sipush        255
      96: iand
      97: iadd
      98: istore_3
      99: iinc          4, 1
     102: goto          73
     105: iload_3
     106: iload_3
     107: iconst_m1
     108: ixor
     109: bipush        31
     111: ishr
     112: ldc           #139                // int -2147483648
     114: ior
     115: ixor
     116: istore_3
     117: iload_3
     118: invokestatic  #140                // Method java/lang/Float.intBitsToFloat:(I)F
     121: freturn

  public static int encodeFloat64(org.apache.hadoop.hbase.util.PositionedByteRange, double, org.apache.hadoop.hbase.util.Order);
    Code:
       0: aload_0
       1: invokeinterface #11,  1           // InterfaceMethod org/apache/hadoop/hbase/util/PositionedByteRange.getOffset:()I
       6: istore        4
       8: aload_0
       9: invokeinterface #12,  1           // InterfaceMethod org/apache/hadoop/hbase/util/PositionedByteRange.getPosition:()I
      14: istore        5
      16: dload_1
      17: invokestatic  #141                // Method java/lang/Double.doubleToLongBits:(D)J
      20: lstore        6
      22: lload         6
      24: lload         6
      26: bipush        63
      28: lshr
      29: ldc2_w        #143                // long -9223372036854775808l
      32: lor
      33: lxor
      34: lstore        6
      36: aload_0
      37: bipush        49
      39: invokeinterface #10,  2           // InterfaceMethod org/apache/hadoop/hbase/util/PositionedByteRange.put:(B)Lorg/apache/hadoop/hbase/util/PositionedByteRange;
      44: lload         6
      46: bipush        56
      48: lshr
      49: l2i
      50: i2b
      51: invokeinterface #10,  2           // InterfaceMethod org/apache/hadoop/hbase/util/PositionedByteRange.put:(B)Lorg/apache/hadoop/hbase/util/PositionedByteRange;
      56: lload         6
      58: bipush        48
      60: lshr
      61: l2i
      62: i2b
      63: invokeinterface #10,  2           // InterfaceMethod org/apache/hadoop/hbase/util/PositionedByteRange.put:(B)Lorg/apache/hadoop/hbase/util/PositionedByteRange;
      68: lload         6
      70: bipush        40
      72: lshr
      73: l2i
      74: i2b
      75: invokeinterface #10,  2           // InterfaceMethod org/apache/hadoop/hbase/util/PositionedByteRange.put:(B)Lorg/apache/hadoop/hbase/util/PositionedByteRange;
      80: lload         6
      82: bipush        32
      84: lshr
      85: l2i
      86: i2b
      87: invokeinterface #10,  2           // InterfaceMethod org/apache/hadoop/hbase/util/PositionedByteRange.put:(B)Lorg/apache/hadoop/hbase/util/PositionedByteRange;
      92: lload         6
      94: bipush        24
      96: lshr
      97: l2i
      98: i2b
      99: invokeinterface #10,  2           // InterfaceMethod org/apache/hadoop/hbase/util/PositionedByteRange.put:(B)Lorg/apache/hadoop/hbase/util/PositionedByteRange;
     104: lload         6
     106: bipush        16
     108: lshr
     109: l2i
     110: i2b
     111: invokeinterface #10,  2           // InterfaceMethod org/apache/hadoop/hbase/util/PositionedByteRange.put:(B)Lorg/apache/hadoop/hbase/util/PositionedByteRange;
     116: lload         6
     118: bipush        8
     120: lshr
     121: l2i
     122: i2b
     123: invokeinterface #10,  2           // InterfaceMethod org/apache/hadoop/hbase/util/PositionedByteRange.put:(B)Lorg/apache/hadoop/hbase/util/PositionedByteRange;
     128: lload         6
     130: l2i
     131: i2b
     132: invokeinterface #10,  2           // InterfaceMethod org/apache/hadoop/hbase/util/PositionedByteRange.put:(B)Lorg/apache/hadoop/hbase/util/PositionedByteRange;
     137: pop
     138: aload_3
     139: aload_0
     140: invokeinterface #13,  1           // InterfaceMethod org/apache/hadoop/hbase/util/PositionedByteRange.getBytes:()[B
     145: iload         4
     147: iload         5
     149: iadd
     150: bipush        9
     152: invokevirtual #19                 // Method org/apache/hadoop/hbase/util/Order.apply:([BII)V
     155: bipush        9
     157: ireturn

  public static double decodeFloat64(org.apache.hadoop.hbase.util.PositionedByteRange);
    Code:
       0: aload_0
       1: invokeinterface #42,  1           // InterfaceMethod org/apache/hadoop/hbase/util/PositionedByteRange.get:()B
       6: istore_1
       7: getstatic     #38                 // Field $assertionsDisabled:Z
      10: ifne          39
      13: iload_1
      14: bipush        49
      16: if_icmpeq     39
      19: iload_1
      20: getstatic     #14                 // Field org/apache/hadoop/hbase/util/Order.DESCENDING:Lorg/apache/hadoop/hbase/util/Order;
      23: bipush        49
      25: invokevirtual #34                 // Method org/apache/hadoop/hbase/util/Order.apply:(B)B
      28: if_icmpeq     39
      31: new           #40                 // class java/lang/AssertionError
      34: dup
      35: invokespecial #41                 // Method java/lang/AssertionError."<init>":()V
      38: athrow
      39: iload_1
      40: bipush        49
      42: if_icmpne     51
      45: getstatic     #15                 // Field org/apache/hadoop/hbase/util/Order.ASCENDING:Lorg/apache/hadoop/hbase/util/Order;
      48: goto          54
      51: getstatic     #14                 // Field org/apache/hadoop/hbase/util/Order.DESCENDING:Lorg/apache/hadoop/hbase/util/Order;
      54: astore_2
      55: aload_2
      56: aload_0
      57: invokeinterface #42,  1           // InterfaceMethod org/apache/hadoop/hbase/util/PositionedByteRange.get:()B
      62: invokevirtual #34                 // Method org/apache/hadoop/hbase/util/Order.apply:(B)B
      65: sipush        255
      68: iand
      69: i2l
      70: lstore_3
      71: iconst_1
      72: istore        5
      74: iload         5
      76: bipush        8
      78: if_icmpge     108
      81: lload_3
      82: bipush        8
      84: lshl
      85: aload_2
      86: aload_0
      87: invokeinterface #42,  1           // InterfaceMethod org/apache/hadoop/hbase/util/PositionedByteRange.get:()B
      92: invokevirtual #34                 // Method org/apache/hadoop/hbase/util/Order.apply:(B)B
      95: sipush        255
      98: iand
      99: i2l
     100: ladd
     101: lstore_3
     102: iinc          5, 1
     105: goto          74
     108: lload_3
     109: lload_3
     110: ldc2_w        #145                // long -1l
     113: lxor
     114: bipush        63
     116: lshr
     117: ldc2_w        #143                // long -9223372036854775808l
     120: lor
     121: lxor
     122: lstore_3
     123: lload_3
     124: invokestatic  #147                // Method java/lang/Double.longBitsToDouble:(J)D
     127: dreturn

  public static boolean isEncodedValue(org.apache.hadoop.hbase.util.PositionedByteRange);
    Code:
       0: aload_0
       1: invokestatic  #89                 // Method isNull:(Lorg/apache/hadoop/hbase/util/PositionedByteRange;)Z
       4: ifne          77
       7: aload_0
       8: invokestatic  #102                // Method isNumeric:(Lorg/apache/hadoop/hbase/util/PositionedByteRange;)Z
      11: ifne          77
      14: aload_0
      15: invokestatic  #148                // Method isFixedInt8:(Lorg/apache/hadoop/hbase/util/PositionedByteRange;)Z
      18: ifne          77
      21: aload_0
      22: invokestatic  #149                // Method isFixedInt16:(Lorg/apache/hadoop/hbase/util/PositionedByteRange;)Z
      25: ifne          77
      28: aload_0
      29: invokestatic  #150                // Method isFixedInt32:(Lorg/apache/hadoop/hbase/util/PositionedByteRange;)Z
      32: ifne          77
      35: aload_0
      36: invokestatic  #151                // Method isFixedInt64:(Lorg/apache/hadoop/hbase/util/PositionedByteRange;)Z
      39: ifne          77
      42: aload_0
      43: invokestatic  #152                // Method isFixedFloat32:(Lorg/apache/hadoop/hbase/util/PositionedByteRange;)Z
      46: ifne          77
      49: aload_0
      50: invokestatic  #153                // Method isFixedFloat64:(Lorg/apache/hadoop/hbase/util/PositionedByteRange;)Z
      53: ifne          77
      56: aload_0
      57: invokestatic  #154                // Method isText:(Lorg/apache/hadoop/hbase/util/PositionedByteRange;)Z
      60: ifne          77
      63: aload_0
      64: invokestatic  #155                // Method isBlobCopy:(Lorg/apache/hadoop/hbase/util/PositionedByteRange;)Z
      67: ifne          77
      70: aload_0
      71: invokestatic  #156                // Method isBlobVar:(Lorg/apache/hadoop/hbase/util/PositionedByteRange;)Z
      74: ifeq          81
      77: iconst_1
      78: goto          82
      81: iconst_0
      82: ireturn

  public static boolean isNull(org.apache.hadoop.hbase.util.PositionedByteRange);
    Code:
       0: iconst_5
       1: iconst_m1
       2: aload_0
       3: invokeinterface #33,  1           // InterfaceMethod org/apache/hadoop/hbase/util/PositionedByteRange.peek:()B
       8: invokestatic  #85                 // Method java/lang/Integer.signum:(I)I
      11: if_icmpne     20
      14: getstatic     #14                 // Field org/apache/hadoop/hbase/util/Order.DESCENDING:Lorg/apache/hadoop/hbase/util/Order;
      17: goto          23
      20: getstatic     #15                 // Field org/apache/hadoop/hbase/util/Order.ASCENDING:Lorg/apache/hadoop/hbase/util/Order;
      23: aload_0
      24: invokeinterface #33,  1           // InterfaceMethod org/apache/hadoop/hbase/util/PositionedByteRange.peek:()B
      29: invokevirtual #34                 // Method org/apache/hadoop/hbase/util/Order.apply:(B)B
      32: if_icmpne     39
      35: iconst_1
      36: goto          40
      39: iconst_0
      40: ireturn

  public static boolean isNumeric(org.apache.hadoop.hbase.util.PositionedByteRange);
    Code:
       0: iconst_m1
       1: aload_0
       2: invokeinterface #33,  1           // InterfaceMethod org/apache/hadoop/hbase/util/PositionedByteRange.peek:()B
       7: invokestatic  #85                 // Method java/lang/Integer.signum:(I)I
      10: if_icmpne     19
      13: getstatic     #14                 // Field org/apache/hadoop/hbase/util/Order.DESCENDING:Lorg/apache/hadoop/hbase/util/Order;
      16: goto          22
      19: getstatic     #15                 // Field org/apache/hadoop/hbase/util/Order.ASCENDING:Lorg/apache/hadoop/hbase/util/Order;
      22: aload_0
      23: invokeinterface #33,  1           // InterfaceMethod org/apache/hadoop/hbase/util/PositionedByteRange.peek:()B
      28: invokevirtual #34                 // Method org/apache/hadoop/hbase/util/Order.apply:(B)B
      31: istore_1
      32: iload_1
      33: bipush        7
      35: if_icmplt     48
      38: iload_1
      39: bipush        38
      41: if_icmpgt     48
      44: iconst_1
      45: goto          49
      48: iconst_0
      49: ireturn

  public static boolean isNumericInfinite(org.apache.hadoop.hbase.util.PositionedByteRange);
    Code:
       0: iconst_m1
       1: aload_0
       2: invokeinterface #33,  1           // InterfaceMethod org/apache/hadoop/hbase/util/PositionedByteRange.peek:()B
       7: invokestatic  #85                 // Method java/lang/Integer.signum:(I)I
      10: if_icmpne     19
      13: getstatic     #14                 // Field org/apache/hadoop/hbase/util/Order.DESCENDING:Lorg/apache/hadoop/hbase/util/Order;
      16: goto          22
      19: getstatic     #15                 // Field org/apache/hadoop/hbase/util/Order.ASCENDING:Lorg/apache/hadoop/hbase/util/Order;
      22: aload_0
      23: invokeinterface #33,  1           // InterfaceMethod org/apache/hadoop/hbase/util/PositionedByteRange.peek:()B
      28: invokevirtual #34                 // Method org/apache/hadoop/hbase/util/Order.apply:(B)B
      31: istore_1
      32: bipush        7
      34: iload_1
      35: if_icmpeq     44
      38: bipush        35
      40: iload_1
      41: if_icmpne     48
      44: iconst_1
      45: goto          49
      48: iconst_0
      49: ireturn

  public static boolean isNumericNaN(org.apache.hadoop.hbase.util.PositionedByteRange);
    Code:
       0: bipush        38
       2: iconst_m1
       3: aload_0
       4: invokeinterface #33,  1           // InterfaceMethod org/apache/hadoop/hbase/util/PositionedByteRange.peek:()B
       9: invokestatic  #85                 // Method java/lang/Integer.signum:(I)I
      12: if_icmpne     21
      15: getstatic     #14                 // Field org/apache/hadoop/hbase/util/Order.DESCENDING:Lorg/apache/hadoop/hbase/util/Order;
      18: goto          24
      21: getstatic     #15                 // Field org/apache/hadoop/hbase/util/Order.ASCENDING:Lorg/apache/hadoop/hbase/util/Order;
      24: aload_0
      25: invokeinterface #33,  1           // InterfaceMethod org/apache/hadoop/hbase/util/PositionedByteRange.peek:()B
      30: invokevirtual #34                 // Method org/apache/hadoop/hbase/util/Order.apply:(B)B
      33: if_icmpne     40
      36: iconst_1
      37: goto          41
      40: iconst_0
      41: ireturn

  public static boolean isNumericZero(org.apache.hadoop.hbase.util.PositionedByteRange);
    Code:
       0: bipush        21
       2: iconst_m1
       3: aload_0
       4: invokeinterface #33,  1           // InterfaceMethod org/apache/hadoop/hbase/util/PositionedByteRange.peek:()B
       9: invokestatic  #85                 // Method java/lang/Integer.signum:(I)I
      12: if_icmpne     21
      15: getstatic     #14                 // Field org/apache/hadoop/hbase/util/Order.DESCENDING:Lorg/apache/hadoop/hbase/util/Order;
      18: goto          24
      21: getstatic     #15                 // Field org/apache/hadoop/hbase/util/Order.ASCENDING:Lorg/apache/hadoop/hbase/util/Order;
      24: aload_0
      25: invokeinterface #33,  1           // InterfaceMethod org/apache/hadoop/hbase/util/PositionedByteRange.peek:()B
      30: invokevirtual #34                 // Method org/apache/hadoop/hbase/util/Order.apply:(B)B
      33: if_icmpne     40
      36: iconst_1
      37: goto          41
      40: iconst_0
      41: ireturn

  public static boolean isFixedInt8(org.apache.hadoop.hbase.util.PositionedByteRange);
    Code:
       0: bipush        41
       2: iconst_m1
       3: aload_0
       4: invokeinterface #33,  1           // InterfaceMethod org/apache/hadoop/hbase/util/PositionedByteRange.peek:()B
       9: invokestatic  #85                 // Method java/lang/Integer.signum:(I)I
      12: if_icmpne     21
      15: getstatic     #14                 // Field org/apache/hadoop/hbase/util/Order.DESCENDING:Lorg/apache/hadoop/hbase/util/Order;
      18: goto          24
      21: getstatic     #15                 // Field org/apache/hadoop/hbase/util/Order.ASCENDING:Lorg/apache/hadoop/hbase/util/Order;
      24: aload_0
      25: invokeinterface #33,  1           // InterfaceMethod org/apache/hadoop/hbase/util/PositionedByteRange.peek:()B
      30: invokevirtual #34                 // Method org/apache/hadoop/hbase/util/Order.apply:(B)B
      33: if_icmpne     40
      36: iconst_1
      37: goto          41
      40: iconst_0
      41: ireturn

  public static boolean isFixedInt16(org.apache.hadoop.hbase.util.PositionedByteRange);
    Code:
       0: bipush        42
       2: iconst_m1
       3: aload_0
       4: invokeinterface #33,  1           // InterfaceMethod org/apache/hadoop/hbase/util/PositionedByteRange.peek:()B
       9: invokestatic  #85                 // Method java/lang/Integer.signum:(I)I
      12: if_icmpne     21
      15: getstatic     #14                 // Field org/apache/hadoop/hbase/util/Order.DESCENDING:Lorg/apache/hadoop/hbase/util/Order;
      18: goto          24
      21: getstatic     #15                 // Field org/apache/hadoop/hbase/util/Order.ASCENDING:Lorg/apache/hadoop/hbase/util/Order;
      24: aload_0
      25: invokeinterface #33,  1           // InterfaceMethod org/apache/hadoop/hbase/util/PositionedByteRange.peek:()B
      30: invokevirtual #34                 // Method org/apache/hadoop/hbase/util/Order.apply:(B)B
      33: if_icmpne     40
      36: iconst_1
      37: goto          41
      40: iconst_0
      41: ireturn

  public static boolean isFixedInt32(org.apache.hadoop.hbase.util.PositionedByteRange);
    Code:
       0: bipush        43
       2: iconst_m1
       3: aload_0
       4: invokeinterface #33,  1           // InterfaceMethod org/apache/hadoop/hbase/util/PositionedByteRange.peek:()B
       9: invokestatic  #85                 // Method java/lang/Integer.signum:(I)I
      12: if_icmpne     21
      15: getstatic     #14                 // Field org/apache/hadoop/hbase/util/Order.DESCENDING:Lorg/apache/hadoop/hbase/util/Order;
      18: goto          24
      21: getstatic     #15                 // Field org/apache/hadoop/hbase/util/Order.ASCENDING:Lorg/apache/hadoop/hbase/util/Order;
      24: aload_0
      25: invokeinterface #33,  1           // InterfaceMethod org/apache/hadoop/hbase/util/PositionedByteRange.peek:()B
      30: invokevirtual #34                 // Method org/apache/hadoop/hbase/util/Order.apply:(B)B
      33: if_icmpne     40
      36: iconst_1
      37: goto          41
      40: iconst_0
      41: ireturn

  public static boolean isFixedInt64(org.apache.hadoop.hbase.util.PositionedByteRange);
    Code:
       0: bipush        44
       2: iconst_m1
       3: aload_0
       4: invokeinterface #33,  1           // InterfaceMethod org/apache/hadoop/hbase/util/PositionedByteRange.peek:()B
       9: invokestatic  #85                 // Method java/lang/Integer.signum:(I)I
      12: if_icmpne     21
      15: getstatic     #14                 // Field org/apache/hadoop/hbase/util/Order.DESCENDING:Lorg/apache/hadoop/hbase/util/Order;
      18: goto          24
      21: getstatic     #15                 // Field org/apache/hadoop/hbase/util/Order.ASCENDING:Lorg/apache/hadoop/hbase/util/Order;
      24: aload_0
      25: invokeinterface #33,  1           // InterfaceMethod org/apache/hadoop/hbase/util/PositionedByteRange.peek:()B
      30: invokevirtual #34                 // Method org/apache/hadoop/hbase/util/Order.apply:(B)B
      33: if_icmpne     40
      36: iconst_1
      37: goto          41
      40: iconst_0
      41: ireturn

  public static boolean isFixedFloat32(org.apache.hadoop.hbase.util.PositionedByteRange);
    Code:
       0: bipush        48
       2: iconst_m1
       3: aload_0
       4: invokeinterface #33,  1           // InterfaceMethod org/apache/hadoop/hbase/util/PositionedByteRange.peek:()B
       9: invokestatic  #85                 // Method java/lang/Integer.signum:(I)I
      12: if_icmpne     21
      15: getstatic     #14                 // Field org/apache/hadoop/hbase/util/Order.DESCENDING:Lorg/apache/hadoop/hbase/util/Order;
      18: goto          24
      21: getstatic     #15                 // Field org/apache/hadoop/hbase/util/Order.ASCENDING:Lorg/apache/hadoop/hbase/util/Order;
      24: aload_0
      25: invokeinterface #33,  1           // InterfaceMethod org/apache/hadoop/hbase/util/PositionedByteRange.peek:()B
      30: invokevirtual #34                 // Method org/apache/hadoop/hbase/util/Order.apply:(B)B
      33: if_icmpne     40
      36: iconst_1
      37: goto          41
      40: iconst_0
      41: ireturn

  public static boolean isFixedFloat64(org.apache.hadoop.hbase.util.PositionedByteRange);
    Code:
       0: bipush        49
       2: iconst_m1
       3: aload_0
       4: invokeinterface #33,  1           // InterfaceMethod org/apache/hadoop/hbase/util/PositionedByteRange.peek:()B
       9: invokestatic  #85                 // Method java/lang/Integer.signum:(I)I
      12: if_icmpne     21
      15: getstatic     #14                 // Field org/apache/hadoop/hbase/util/Order.DESCENDING:Lorg/apache/hadoop/hbase/util/Order;
      18: goto          24
      21: getstatic     #15                 // Field org/apache/hadoop/hbase/util/Order.ASCENDING:Lorg/apache/hadoop/hbase/util/Order;
      24: aload_0
      25: invokeinterface #33,  1           // InterfaceMethod org/apache/hadoop/hbase/util/PositionedByteRange.peek:()B
      30: invokevirtual #34                 // Method org/apache/hadoop/hbase/util/Order.apply:(B)B
      33: if_icmpne     40
      36: iconst_1
      37: goto          41
      40: iconst_0
      41: ireturn

  public static boolean isText(org.apache.hadoop.hbase.util.PositionedByteRange);
    Code:
       0: bipush        52
       2: iconst_m1
       3: aload_0
       4: invokeinterface #33,  1           // InterfaceMethod org/apache/hadoop/hbase/util/PositionedByteRange.peek:()B
       9: invokestatic  #85                 // Method java/lang/Integer.signum:(I)I
      12: if_icmpne     21
      15: getstatic     #14                 // Field org/apache/hadoop/hbase/util/Order.DESCENDING:Lorg/apache/hadoop/hbase/util/Order;
      18: goto          24
      21: getstatic     #15                 // Field org/apache/hadoop/hbase/util/Order.ASCENDING:Lorg/apache/hadoop/hbase/util/Order;
      24: aload_0
      25: invokeinterface #33,  1           // InterfaceMethod org/apache/hadoop/hbase/util/PositionedByteRange.peek:()B
      30: invokevirtual #34                 // Method org/apache/hadoop/hbase/util/Order.apply:(B)B
      33: if_icmpne     40
      36: iconst_1
      37: goto          41
      40: iconst_0
      41: ireturn

  public static boolean isBlobVar(org.apache.hadoop.hbase.util.PositionedByteRange);
    Code:
       0: bipush        55
       2: iconst_m1
       3: aload_0
       4: invokeinterface #33,  1           // InterfaceMethod org/apache/hadoop/hbase/util/PositionedByteRange.peek:()B
       9: invokestatic  #85                 // Method java/lang/Integer.signum:(I)I
      12: if_icmpne     21
      15: getstatic     #14                 // Field org/apache/hadoop/hbase/util/Order.DESCENDING:Lorg/apache/hadoop/hbase/util/Order;
      18: goto          24
      21: getstatic     #15                 // Field org/apache/hadoop/hbase/util/Order.ASCENDING:Lorg/apache/hadoop/hbase/util/Order;
      24: aload_0
      25: invokeinterface #33,  1           // InterfaceMethod org/apache/hadoop/hbase/util/PositionedByteRange.peek:()B
      30: invokevirtual #34                 // Method org/apache/hadoop/hbase/util/Order.apply:(B)B
      33: if_icmpne     40
      36: iconst_1
      37: goto          41
      40: iconst_0
      41: ireturn

  public static boolean isBlobCopy(org.apache.hadoop.hbase.util.PositionedByteRange);
    Code:
       0: bipush        56
       2: iconst_m1
       3: aload_0
       4: invokeinterface #33,  1           // InterfaceMethod org/apache/hadoop/hbase/util/PositionedByteRange.peek:()B
       9: invokestatic  #85                 // Method java/lang/Integer.signum:(I)I
      12: if_icmpne     21
      15: getstatic     #14                 // Field org/apache/hadoop/hbase/util/Order.DESCENDING:Lorg/apache/hadoop/hbase/util/Order;
      18: goto          24
      21: getstatic     #15                 // Field org/apache/hadoop/hbase/util/Order.ASCENDING:Lorg/apache/hadoop/hbase/util/Order;
      24: aload_0
      25: invokeinterface #33,  1           // InterfaceMethod org/apache/hadoop/hbase/util/PositionedByteRange.peek:()B
      30: invokevirtual #34                 // Method org/apache/hadoop/hbase/util/Order.apply:(B)B
      33: if_icmpne     40
      36: iconst_1
      37: goto          41
      40: iconst_0
      41: ireturn

  public static int skip(org.apache.hadoop.hbase.util.PositionedByteRange);
    Code:
       0: aload_0
       1: invokeinterface #12,  1           // InterfaceMethod org/apache/hadoop/hbase/util/PositionedByteRange.getPosition:()I
       6: istore_1
       7: aload_0
       8: invokeinterface #42,  1           // InterfaceMethod org/apache/hadoop/hbase/util/PositionedByteRange.get:()B
      13: istore_2
      14: iconst_m1
      15: iload_2
      16: invokestatic  #85                 // Method java/lang/Integer.signum:(I)I
      19: if_icmpne     28
      22: getstatic     #14                 // Field org/apache/hadoop/hbase/util/Order.DESCENDING:Lorg/apache/hadoop/hbase/util/Order;
      25: goto          31
      28: getstatic     #15                 // Field org/apache/hadoop/hbase/util/Order.ASCENDING:Lorg/apache/hadoop/hbase/util/Order;
      31: astore_3
      32: aload_3
      33: iload_2
      34: invokevirtual #34                 // Method org/apache/hadoop/hbase/util/Order.apply:(B)B
      37: istore_2
      38: iload_2
      39: tableswitch   { // 5 to 56
                     5: 260
                     6: 744
                     7: 260
                     8: 262
                     9: 305
                    10: 305
                    11: 305
                    12: 305
                    13: 305
                    14: 305
                    15: 305
                    16: 305
                    17: 305
                    18: 305
                    19: 305
                    20: 331
                    21: 374
                    22: 376
                    23: 419
                    24: 419
                    25: 419
                    26: 419
                    27: 419
                    28: 419
                    29: 419
                    30: 419
                    31: 419
                    32: 419
                    33: 419
                    34: 445
                    35: 488
                    36: 744
                    37: 744
                    38: 490
                    39: 744
                    40: 744
                    41: 492
                    42: 516
                    43: 540
                    44: 564
                    45: 744
                    46: 744
                    47: 744
                    48: 589
                    49: 613
                    50: 744
                    51: 744
                    52: 638
                    53: 744
                    54: 744
                    55: 662
                    56: 691
               default: 744
          }
     260: iconst_1
     261: ireturn
     262: aload_0
     263: getstatic     #14                 // Field org/apache/hadoop/hbase/util/Order.DESCENDING:Lorg/apache/hadoop/hbase/util/Order;
     266: aload_3
     267: if_acmpeq     274
     270: iconst_1
     271: goto          275
     274: iconst_0
     275: invokestatic  #157                // Method skipVaruint64:(Lorg/apache/hadoop/hbase/util/PositionedByteRange;Z)I
     278: pop
     279: aload_0
     280: getstatic     #14                 // Field org/apache/hadoop/hbase/util/Order.DESCENDING:Lorg/apache/hadoop/hbase/util/Order;
     283: aload_3
     284: if_acmpeq     291
     287: iconst_1
     288: goto          292
     291: iconst_0
     292: invokestatic  #158                // Method skipSignificand:(Lorg/apache/hadoop/hbase/util/PositionedByteRange;Z)I
     295: pop
     296: aload_0
     297: invokeinterface #12,  1           // InterfaceMethod org/apache/hadoop/hbase/util/PositionedByteRange.getPosition:()I
     302: iload_1
     303: isub
     304: ireturn
     305: aload_0
     306: getstatic     #14                 // Field org/apache/hadoop/hbase/util/Order.DESCENDING:Lorg/apache/hadoop/hbase/util/Order;
     309: aload_3
     310: if_acmpeq     317
     313: iconst_1
     314: goto          318
     317: iconst_0
     318: invokestatic  #158                // Method skipSignificand:(Lorg/apache/hadoop/hbase/util/PositionedByteRange;Z)I
     321: pop
     322: aload_0
     323: invokeinterface #12,  1           // InterfaceMethod org/apache/hadoop/hbase/util/PositionedByteRange.getPosition:()I
     328: iload_1
     329: isub
     330: ireturn
     331: aload_0
     332: getstatic     #14                 // Field org/apache/hadoop/hbase/util/Order.DESCENDING:Lorg/apache/hadoop/hbase/util/Order;
     335: aload_3
     336: if_acmpne     343
     339: iconst_1
     340: goto          344
     343: iconst_0
     344: invokestatic  #157                // Method skipVaruint64:(Lorg/apache/hadoop/hbase/util/PositionedByteRange;Z)I
     347: pop
     348: aload_0
     349: getstatic     #14                 // Field org/apache/hadoop/hbase/util/Order.DESCENDING:Lorg/apache/hadoop/hbase/util/Order;
     352: aload_3
     353: if_acmpeq     360
     356: iconst_1
     357: goto          361
     360: iconst_0
     361: invokestatic  #158                // Method skipSignificand:(Lorg/apache/hadoop/hbase/util/PositionedByteRange;Z)I
     364: pop
     365: aload_0
     366: invokeinterface #12,  1           // InterfaceMethod org/apache/hadoop/hbase/util/PositionedByteRange.getPosition:()I
     371: iload_1
     372: isub
     373: ireturn
     374: iconst_1
     375: ireturn
     376: aload_0
     377: getstatic     #14                 // Field org/apache/hadoop/hbase/util/Order.DESCENDING:Lorg/apache/hadoop/hbase/util/Order;
     380: aload_3
     381: if_acmpeq     388
     384: iconst_1
     385: goto          389
     388: iconst_0
     389: invokestatic  #157                // Method skipVaruint64:(Lorg/apache/hadoop/hbase/util/PositionedByteRange;Z)I
     392: pop
     393: aload_0
     394: getstatic     #14                 // Field org/apache/hadoop/hbase/util/Order.DESCENDING:Lorg/apache/hadoop/hbase/util/Order;
     397: aload_3
     398: if_acmpne     405
     401: iconst_1
     402: goto          406
     405: iconst_0
     406: invokestatic  #158                // Method skipSignificand:(Lorg/apache/hadoop/hbase/util/PositionedByteRange;Z)I
     409: pop
     410: aload_0
     411: invokeinterface #12,  1           // InterfaceMethod org/apache/hadoop/hbase/util/PositionedByteRange.getPosition:()I
     416: iload_1
     417: isub
     418: ireturn
     419: aload_0
     420: getstatic     #14                 // Field org/apache/hadoop/hbase/util/Order.DESCENDING:Lorg/apache/hadoop/hbase/util/Order;
     423: aload_3
     424: if_acmpne     431
     427: iconst_1
     428: goto          432
     431: iconst_0
     432: invokestatic  #158                // Method skipSignificand:(Lorg/apache/hadoop/hbase/util/PositionedByteRange;Z)I
     435: pop
     436: aload_0
     437: invokeinterface #12,  1           // InterfaceMethod org/apache/hadoop/hbase/util/PositionedByteRange.getPosition:()I
     442: iload_1
     443: isub
     444: ireturn
     445: aload_0
     446: getstatic     #14                 // Field org/apache/hadoop/hbase/util/Order.DESCENDING:Lorg/apache/hadoop/hbase/util/Order;
     449: aload_3
     450: if_acmpne     457
     453: iconst_1
     454: goto          458
     457: iconst_0
     458: invokestatic  #157                // Method skipVaruint64:(Lorg/apache/hadoop/hbase/util/PositionedByteRange;Z)I
     461: pop
     462: aload_0
     463: getstatic     #14                 // Field org/apache/hadoop/hbase/util/Order.DESCENDING:Lorg/apache/hadoop/hbase/util/Order;
     466: aload_3
     467: if_acmpne     474
     470: iconst_1
     471: goto          475
     474: iconst_0
     475: invokestatic  #158                // Method skipSignificand:(Lorg/apache/hadoop/hbase/util/PositionedByteRange;Z)I
     478: pop
     479: aload_0
     480: invokeinterface #12,  1           // InterfaceMethod org/apache/hadoop/hbase/util/PositionedByteRange.getPosition:()I
     485: iload_1
     486: isub
     487: ireturn
     488: iconst_1
     489: ireturn
     490: iconst_1
     491: ireturn
     492: aload_0
     493: aload_0
     494: invokeinterface #12,  1           // InterfaceMethod org/apache/hadoop/hbase/util/PositionedByteRange.getPosition:()I
     499: iconst_1
     500: iadd
     501: invokeinterface #37,  2           // InterfaceMethod org/apache/hadoop/hbase/util/PositionedByteRange.setPosition:(I)Lorg/apache/hadoop/hbase/util/PositionedByteRange;
     506: pop
     507: aload_0
     508: invokeinterface #12,  1           // InterfaceMethod org/apache/hadoop/hbase/util/PositionedByteRange.getPosition:()I
     513: iload_1
     514: isub
     515: ireturn
     516: aload_0
     517: aload_0
     518: invokeinterface #12,  1           // InterfaceMethod org/apache/hadoop/hbase/util/PositionedByteRange.getPosition:()I
     523: iconst_2
     524: iadd
     525: invokeinterface #37,  2           // InterfaceMethod org/apache/hadoop/hbase/util/PositionedByteRange.setPosition:(I)Lorg/apache/hadoop/hbase/util/PositionedByteRange;
     530: pop
     531: aload_0
     532: invokeinterface #12,  1           // InterfaceMethod org/apache/hadoop/hbase/util/PositionedByteRange.getPosition:()I
     537: iload_1
     538: isub
     539: ireturn
     540: aload_0
     541: aload_0
     542: invokeinterface #12,  1           // InterfaceMethod org/apache/hadoop/hbase/util/PositionedByteRange.getPosition:()I
     547: iconst_4
     548: iadd
     549: invokeinterface #37,  2           // InterfaceMethod org/apache/hadoop/hbase/util/PositionedByteRange.setPosition:(I)Lorg/apache/hadoop/hbase/util/PositionedByteRange;
     554: pop
     555: aload_0
     556: invokeinterface #12,  1           // InterfaceMethod org/apache/hadoop/hbase/util/PositionedByteRange.getPosition:()I
     561: iload_1
     562: isub
     563: ireturn
     564: aload_0
     565: aload_0
     566: invokeinterface #12,  1           // InterfaceMethod org/apache/hadoop/hbase/util/PositionedByteRange.getPosition:()I
     571: bipush        8
     573: iadd
     574: invokeinterface #37,  2           // InterfaceMethod org/apache/hadoop/hbase/util/PositionedByteRange.setPosition:(I)Lorg/apache/hadoop/hbase/util/PositionedByteRange;
     579: pop
     580: aload_0
     581: invokeinterface #12,  1           // InterfaceMethod org/apache/hadoop/hbase/util/PositionedByteRange.getPosition:()I
     586: iload_1
     587: isub
     588: ireturn
     589: aload_0
     590: aload_0
     591: invokeinterface #12,  1           // InterfaceMethod org/apache/hadoop/hbase/util/PositionedByteRange.getPosition:()I
     596: iconst_4
     597: iadd
     598: invokeinterface #37,  2           // InterfaceMethod org/apache/hadoop/hbase/util/PositionedByteRange.setPosition:(I)Lorg/apache/hadoop/hbase/util/PositionedByteRange;
     603: pop
     604: aload_0
     605: invokeinterface #12,  1           // InterfaceMethod org/apache/hadoop/hbase/util/PositionedByteRange.getPosition:()I
     610: iload_1
     611: isub
     612: ireturn
     613: aload_0
     614: aload_0
     615: invokeinterface #12,  1           // InterfaceMethod org/apache/hadoop/hbase/util/PositionedByteRange.getPosition:()I
     620: bipush        8
     622: iadd
     623: invokeinterface #37,  2           // InterfaceMethod org/apache/hadoop/hbase/util/PositionedByteRange.setPosition:(I)Lorg/apache/hadoop/hbase/util/PositionedByteRange;
     628: pop
     629: aload_0
     630: invokeinterface #12,  1           // InterfaceMethod org/apache/hadoop/hbase/util/PositionedByteRange.getPosition:()I
     635: iload_1
     636: isub
     637: ireturn
     638: aload_3
     639: aload_0
     640: invokeinterface #42,  1           // InterfaceMethod org/apache/hadoop/hbase/util/PositionedByteRange.get:()B
     645: invokevirtual #34                 // Method org/apache/hadoop/hbase/util/Order.apply:(B)B
     648: istore_2
     649: iload_2
     650: ifne          638
     653: aload_0
     654: invokeinterface #12,  1           // InterfaceMethod org/apache/hadoop/hbase/util/PositionedByteRange.getPosition:()I
     659: iload_1
     660: isub
     661: ireturn
     662: aload_3
     663: aload_0
     664: invokeinterface #42,  1           // InterfaceMethod org/apache/hadoop/hbase/util/PositionedByteRange.get:()B
     669: invokevirtual #34                 // Method org/apache/hadoop/hbase/util/Order.apply:(B)B
     672: istore_2
     673: iload_2
     674: sipush        128
     677: iand
     678: i2b
     679: ifne          662
     682: aload_0
     683: invokeinterface #12,  1           // InterfaceMethod org/apache/hadoop/hbase/util/PositionedByteRange.getPosition:()I
     688: iload_1
     689: isub
     690: ireturn
     691: getstatic     #14                 // Field org/apache/hadoop/hbase/util/Order.DESCENDING:Lorg/apache/hadoop/hbase/util/Order;
     694: aload_3
     695: if_acmpne     722
     698: aload_3
     699: aload_0
     700: invokeinterface #42,  1           // InterfaceMethod org/apache/hadoop/hbase/util/PositionedByteRange.get:()B
     705: invokevirtual #34                 // Method org/apache/hadoop/hbase/util/Order.apply:(B)B
     708: istore_2
     709: iload_2
     710: ifne          698
     713: aload_0
     714: invokeinterface #12,  1           // InterfaceMethod org/apache/hadoop/hbase/util/PositionedByteRange.getPosition:()I
     719: iload_1
     720: isub
     721: ireturn
     722: aload_0
     723: aload_0
     724: invokeinterface #129,  1          // InterfaceMethod org/apache/hadoop/hbase/util/PositionedByteRange.getLength:()I
     729: invokeinterface #37,  2           // InterfaceMethod org/apache/hadoop/hbase/util/PositionedByteRange.setPosition:(I)Lorg/apache/hadoop/hbase/util/PositionedByteRange;
     734: pop
     735: aload_0
     736: invokeinterface #12,  1           // InterfaceMethod org/apache/hadoop/hbase/util/PositionedByteRange.getPosition:()I
     741: iload_1
     742: isub
     743: ireturn
     744: iload_2
     745: invokestatic  #35                 // Method unexpectedHeader:(B)Ljava/lang/IllegalArgumentException;
     748: athrow

  public static int length(org.apache.hadoop.hbase.util.PositionedByteRange);
    Code:
       0: new           #125                // class org/apache/hadoop/hbase/util/SimplePositionedMutableByteRange
       3: dup
       4: aload_0
       5: invokeinterface #13,  1           // InterfaceMethod org/apache/hadoop/hbase/util/PositionedByteRange.getBytes:()[B
      10: aload_0
      11: invokeinterface #11,  1           // InterfaceMethod org/apache/hadoop/hbase/util/PositionedByteRange.getOffset:()I
      16: aload_0
      17: invokeinterface #129,  1          // InterfaceMethod org/apache/hadoop/hbase/util/PositionedByteRange.getLength:()I
      22: invokespecial #159                // Method org/apache/hadoop/hbase/util/SimplePositionedMutableByteRange."<init>":([BII)V
      25: astore_1
      26: aload_1
      27: aload_0
      28: invokeinterface #12,  1           // InterfaceMethod org/apache/hadoop/hbase/util/PositionedByteRange.getPosition:()I
      33: invokeinterface #37,  2           // InterfaceMethod org/apache/hadoop/hbase/util/PositionedByteRange.setPosition:(I)Lorg/apache/hadoop/hbase/util/PositionedByteRange;
      38: pop
      39: iconst_0
      40: istore_2
      41: aload_1
      42: invokestatic  #160                // Method isEncodedValue:(Lorg/apache/hadoop/hbase/util/PositionedByteRange;)Z
      45: ifeq          59
      48: aload_1
      49: invokestatic  #161                // Method skip:(Lorg/apache/hadoop/hbase/util/PositionedByteRange;)I
      52: pop
      53: iinc          2, 1
      56: goto          41
      59: iload_2
      60: ireturn

  static {};
    Code:
       0: ldc           #63                 // class org/apache/hadoop/hbase/util/OrderedBytes
       2: invokevirtual #162                // Method java/lang/Class.desiredAssertionStatus:()Z
       5: ifne          12
       8: iconst_1
       9: goto          13
      12: iconst_0
      13: putstatic     #38                 // Field $assertionsDisabled:Z
      16: ldc           #163                // String UTF-8
      18: invokestatic  #164                // Method java/nio/charset/Charset.forName:(Ljava/lang/String;)Ljava/nio/charset/Charset;
      21: putstatic     #110                // Field UTF8:Ljava/nio/charset/Charset;
      24: ldc2_w        #165                // double 1.0E8d
      27: invokestatic  #81                 // Method java/math/BigDecimal.valueOf:(D)Ljava/math/BigDecimal;
      30: putstatic     #72                 // Field E8:Ljava/math/BigDecimal;
      33: ldc2_w        #167                // double 1.0E32d
      36: invokestatic  #81                 // Method java/math/BigDecimal.valueOf:(D)Ljava/math/BigDecimal;
      39: putstatic     #70                 // Field E32:Ljava/math/BigDecimal;
      42: ldc2_w        #169                // double 0.01d
      45: invokestatic  #81                 // Method java/math/BigDecimal.valueOf:(D)Ljava/math/BigDecimal;
      48: putstatic     #66                 // Field EN2:Ljava/math/BigDecimal;
      51: ldc2_w        #171                // double 1.0E-10d
      54: invokestatic  #81                 // Method java/math/BigDecimal.valueOf:(D)Ljava/math/BigDecimal;
      57: putstatic     #64                 // Field EN10:Ljava/math/BigDecimal;
      60: new           #173                // class java/math/MathContext
      63: dup
      64: bipush        31
      66: getstatic     #174                // Field java/math/RoundingMode.HALF_UP:Ljava/math/RoundingMode;
      69: invokespecial #175                // Method java/math/MathContext."<init>":(ILjava/math/RoundingMode;)V
      72: putstatic     #46                 // Field DEFAULT_MATH_CONTEXT:Ljava/math/MathContext;
      75: return
}
