Compiled from "PackagePrivateFieldAccessor.java"
public class org.apache.hadoop.hbase.client.PackagePrivateFieldAccessor {
  public org.apache.hadoop.hbase.client.PackagePrivateFieldAccessor();
    Code:
       0: aload_0
       1: invokespecial #1                  // Method java/lang/Object."<init>":()V
       4: return

  public static void setMvccReadPoint(org.apache.hadoop.hbase.client.Scan, long);
    Code:
       0: aload_0
       1: lload_1
       2: invokevirtual #2                  // Method org/apache/hadoop/hbase/client/Scan.setMvccReadPoint:(J)Lorg/apache/hadoop/hbase/client/Scan;
       5: pop
       6: return

  public static long getMvccReadPoint(org.apache.hadoop.hbase.client.Scan);
    Code:
       0: aload_0
       1: invokevirtual #3                  // Method org/apache/hadoop/hbase/client/Scan.getMvccReadPoint:()J
       4: lreturn
}
