Compiled from "PairOfSameType.java"
public class org.apache.hadoop.hbase.util.PairOfSameType<T> implements java.lang.Iterable<T> {
  public org.apache.hadoop.hbase.util.PairOfSameType(T, T);
    Code:
       0: aload_0
       1: invokespecial #1                  // Method java/lang/Object."<init>":()V
       4: aload_0
       5: aload_1
       6: putfield      #2                  // Field first:Ljava/lang/Object;
       9: aload_0
      10: aload_2
      11: putfield      #3                  // Field second:Ljava/lang/Object;
      14: return

  public T getFirst();
    Code:
       0: aload_0
       1: getfield      #2                  // Field first:Ljava/lang/Object;
       4: areturn

  public T getSecond();
    Code:
       0: aload_0
       1: getfield      #3                  // Field second:Ljava/lang/Object;
       4: areturn

  public boolean equals(java.lang.Object);
    Code:
       0: aload_1
       1: instanceof    #5                  // class org/apache/hadoop/hbase/util/PairOfSameType
       4: ifeq          45
       7: aload_0
       8: getfield      #2                  // Field first:Ljava/lang/Object;
      11: aload_1
      12: checkcast     #5                  // class org/apache/hadoop/hbase/util/PairOfSameType
      15: getfield      #2                  // Field first:Ljava/lang/Object;
      18: invokestatic  #6                  // Method equals:(Ljava/lang/Object;Ljava/lang/Object;)Z
      21: ifeq          45
      24: aload_0
      25: getfield      #3                  // Field second:Ljava/lang/Object;
      28: aload_1
      29: checkcast     #5                  // class org/apache/hadoop/hbase/util/PairOfSameType
      32: getfield      #3                  // Field second:Ljava/lang/Object;
      35: invokestatic  #6                  // Method equals:(Ljava/lang/Object;Ljava/lang/Object;)Z
      38: ifeq          45
      41: iconst_1
      42: goto          46
      45: iconst_0
      46: ireturn

  public int hashCode();
    Code:
       0: aload_0
       1: getfield      #2                  // Field first:Ljava/lang/Object;
       4: ifnonnull     28
       7: aload_0
       8: getfield      #3                  // Field second:Ljava/lang/Object;
      11: ifnonnull     18
      14: iconst_0
      15: goto          27
      18: aload_0
      19: getfield      #3                  // Field second:Ljava/lang/Object;
      22: invokevirtual #7                  // Method java/lang/Object.hashCode:()I
      25: iconst_1
      26: iadd
      27: ireturn
      28: aload_0
      29: getfield      #3                  // Field second:Ljava/lang/Object;
      32: ifnonnull     45
      35: aload_0
      36: getfield      #2                  // Field first:Ljava/lang/Object;
      39: invokevirtual #7                  // Method java/lang/Object.hashCode:()I
      42: iconst_2
      43: iadd
      44: ireturn
      45: aload_0
      46: getfield      #2                  // Field first:Ljava/lang/Object;
      49: invokevirtual #7                  // Method java/lang/Object.hashCode:()I
      52: bipush        17
      54: imul
      55: aload_0
      56: getfield      #3                  // Field second:Ljava/lang/Object;
      59: invokevirtual #7                  // Method java/lang/Object.hashCode:()I
      62: iadd
      63: ireturn

  public java.lang.String toString();
    Code:
       0: new           #8                  // class java/lang/StringBuilder
       3: dup
       4: invokespecial #9                  // Method java/lang/StringBuilder."<init>":()V
       7: ldc           #10                 // String {
       9: invokevirtual #11                 // Method java/lang/StringBuilder.append:(Ljava/lang/String;)Ljava/lang/StringBuilder;
      12: aload_0
      13: invokevirtual #12                 // Method getFirst:()Ljava/lang/Object;
      16: invokevirtual #13                 // Method java/lang/StringBuilder.append:(Ljava/lang/Object;)Ljava/lang/StringBuilder;
      19: ldc           #14                 // String ,
      21: invokevirtual #11                 // Method java/lang/StringBuilder.append:(Ljava/lang/String;)Ljava/lang/StringBuilder;
      24: aload_0
      25: invokevirtual #15                 // Method getSecond:()Ljava/lang/Object;
      28: invokevirtual #13                 // Method java/lang/StringBuilder.append:(Ljava/lang/Object;)Ljava/lang/StringBuilder;
      31: ldc           #16                 // String }
      33: invokevirtual #11                 // Method java/lang/StringBuilder.append:(Ljava/lang/String;)Ljava/lang/StringBuilder;
      36: invokevirtual #17                 // Method java/lang/StringBuilder.toString:()Ljava/lang/String;
      39: areturn

  public java.util.Iterator<T> iterator();
    Code:
       0: new           #18                 // class org/apache/hadoop/hbase/util/PairOfSameType$1
       3: dup
       4: aload_0
       5: invokespecial #19                 // Method org/apache/hadoop/hbase/util/PairOfSameType$1."<init>":(Lorg/apache/hadoop/hbase/util/PairOfSameType;)V
       8: areturn
}
