Compiled from "ParallelSeekHandler.java"
public class org.apache.hadoop.hbase.regionserver.handler.ParallelSeekHandler extends org.apache.hadoop.hbase.executor.EventHandler {
  public org.apache.hadoop.hbase.regionserver.handler.ParallelSeekHandler(org.apache.hadoop.hbase.regionserver.KeyValueScanner, org.apache.hadoop.hbase.Cell, long, java.util.concurrent.CountDownLatch);
    Code:
       0: aload_0
       1: aconst_null
       2: getstatic     #1                  // Field org/apache/hadoop/hbase/executor/EventType.RS_PARALLEL_SEEK:Lorg/apache/hadoop/hbase/executor/EventType;
       5: invokespecial #2                  // Method org/apache/hadoop/hbase/executor/EventHandler."<init>":(Lorg/apache/hadoop/hbase/Server;Lorg/apache/hadoop/hbase/executor/EventType;)V
       8: aload_0
       9: aconst_null
      10: putfield      #3                  // Field err:Ljava/lang/Throwable;
      13: aload_0
      14: aload_1
      15: putfield      #4                  // Field scanner:Lorg/apache/hadoop/hbase/regionserver/KeyValueScanner;
      18: aload_0
      19: aload_2
      20: putfield      #5                  // Field keyValue:Lorg/apache/hadoop/hbase/Cell;
      23: aload_0
      24: lload_3
      25: putfield      #6                  // Field readPoint:J
      28: aload_0
      29: aload         5
      31: putfield      #7                  // Field latch:Ljava/util/concurrent/CountDownLatch;
      34: return

  public void process();
    Code:
       0: aload_0
       1: getfield      #4                  // Field scanner:Lorg/apache/hadoop/hbase/regionserver/KeyValueScanner;
       4: aload_0
       5: getfield      #5                  // Field keyValue:Lorg/apache/hadoop/hbase/Cell;
       8: invokeinterface #8,  2            // InterfaceMethod org/apache/hadoop/hbase/regionserver/KeyValueScanner.seek:(Lorg/apache/hadoop/hbase/Cell;)Z
      13: pop
      14: aload_0
      15: getfield      #7                  // Field latch:Ljava/util/concurrent/CountDownLatch;
      18: invokevirtual #9                  // Method java/util/concurrent/CountDownLatch.countDown:()V
      21: goto          61
      24: astore_1
      25: getstatic     #11                 // Field LOG:Lorg/slf4j/Logger;
      28: ldc           #12                 // String
      30: aload_1
      31: invokeinterface #13,  3           // InterfaceMethod org/slf4j/Logger.error:(Ljava/lang/String;Ljava/lang/Throwable;)V
      36: aload_0
      37: aload_1
      38: invokevirtual #14                 // Method setErr:(Ljava/lang/Throwable;)V
      41: aload_0
      42: getfield      #7                  // Field latch:Ljava/util/concurrent/CountDownLatch;
      45: invokevirtual #9                  // Method java/util/concurrent/CountDownLatch.countDown:()V
      48: goto          61
      51: astore_2
      52: aload_0
      53: getfield      #7                  // Field latch:Ljava/util/concurrent/CountDownLatch;
      56: invokevirtual #9                  // Method java/util/concurrent/CountDownLatch.countDown:()V
      59: aload_2
      60: athrow
      61: return
    Exception table:
       from    to  target type
           0    14    24   Class java/io/IOException
           0    14    51   any
          24    41    51   any

  public java.lang.Throwable getErr();
    Code:
       0: aload_0
       1: getfield      #3                  // Field err:Ljava/lang/Throwable;
       4: areturn

  public void setErr(java.lang.Throwable);
    Code:
       0: aload_0
       1: aload_1
       2: putfield      #3                  // Field err:Ljava/lang/Throwable;
       5: return

  static {};
    Code:
       0: ldc           #15                 // class org/apache/hadoop/hbase/regionserver/handler/ParallelSeekHandler
       2: invokestatic  #16                 // Method org/slf4j/LoggerFactory.getLogger:(Ljava/lang/Class;)Lorg/slf4j/Logger;
       5: putstatic     #11                 // Field LOG:Lorg/slf4j/Logger;
       8: return
}
