Compiled from "PBType.java"
public abstract class org.apache.hadoop.hbase.types.PBType<T extends com.google.protobuf.Message> implements org.apache.hadoop.hbase.types.DataType<T> {
  public org.apache.hadoop.hbase.types.PBType();
    Code:
       0: aload_0
       1: invokespecial #1                  // Method java/lang/Object."<init>":()V
       4: return

  public boolean isOrderPreserving();
    Code:
       0: iconst_0
       1: ireturn

  public org.apache.hadoop.hbase.util.Order getOrder();
    Code:
       0: aconst_null
       1: areturn

  public boolean isNullable();
    Code:
       0: iconst_0
       1: ireturn

  public boolean isSkippable();
    Code:
       0: iconst_1
       1: ireturn

  public int encodedLength(T);
    Code:
       0: aload_1
       1: invokeinterface #2,  1            // InterfaceMethod com/google/protobuf/Message.getSerializedSize:()I
       6: ireturn

  public static com.google.protobuf.CodedInputStream inputStreamFromByteRange(org.apache.hadoop.hbase.util.PositionedByteRange);
    Code:
       0: aload_0
       1: invokeinterface #3,  1            // InterfaceMethod org/apache/hadoop/hbase/util/PositionedByteRange.getBytes:()[B
       6: aload_0
       7: invokeinterface #4,  1            // InterfaceMethod org/apache/hadoop/hbase/util/PositionedByteRange.getOffset:()I
      12: aload_0
      13: invokeinterface #5,  1            // InterfaceMethod org/apache/hadoop/hbase/util/PositionedByteRange.getPosition:()I
      18: iadd
      19: aload_0
      20: invokeinterface #6,  1            // InterfaceMethod org/apache/hadoop/hbase/util/PositionedByteRange.getRemaining:()I
      25: invokestatic  #7                  // Method com/google/protobuf/CodedInputStream.newInstance:([BII)Lcom/google/protobuf/CodedInputStream;
      28: areturn

  public static com.google.protobuf.CodedOutputStream outputStreamFromByteRange(org.apache.hadoop.hbase.util.PositionedByteRange);
    Code:
       0: aload_0
       1: invokeinterface #3,  1            // InterfaceMethod org/apache/hadoop/hbase/util/PositionedByteRange.getBytes:()[B
       6: aload_0
       7: invokeinterface #4,  1            // InterfaceMethod org/apache/hadoop/hbase/util/PositionedByteRange.getOffset:()I
      12: aload_0
      13: invokeinterface #5,  1            // InterfaceMethod org/apache/hadoop/hbase/util/PositionedByteRange.getPosition:()I
      18: iadd
      19: aload_0
      20: invokeinterface #6,  1            // InterfaceMethod org/apache/hadoop/hbase/util/PositionedByteRange.getRemaining:()I
      25: invokestatic  #8                  // Method com/google/protobuf/CodedOutputStream.newInstance:([BII)Lcom/google/protobuf/CodedOutputStream;
      28: areturn

  public int encodedLength(java.lang.Object);
    Code:
       0: aload_0
       1: aload_1
       2: checkcast     #9                  // class com/google/protobuf/Message
       5: invokevirtual #10                 // Method encodedLength:(Lcom/google/protobuf/Message;)I
       8: ireturn
}
