Compiled from "PerClientRandomNonceGenerator.java"
public final class org.apache.hadoop.hbase.client.PerClientRandomNonceGenerator implements org.apache.hadoop.hbase.client.NonceGenerator {
  public long getNonceGroup();
    Code:
       0: aload_0
       1: getfield      #8                  // Field clientId:J
       4: lreturn

  public long newNonce();
    Code:
       0: lconst_0
       1: lstore_1
       2: aload_0
       3: getfield      #4                  // Field rdm:Ljava/util/Random;
       6: invokevirtual #10                 // Method java/util/Random.nextLong:()J
       9: lstore_1
      10: lload_1
      11: lconst_0
      12: lcmp
      13: ifeq          2
      16: lload_1
      17: lreturn

  public static org.apache.hadoop.hbase.client.PerClientRandomNonceGenerator get();
    Code:
       0: getstatic     #11                 // Field INST:Lorg/apache/hadoop/hbase/client/PerClientRandomNonceGenerator;
       3: areturn

  static {};
    Code:
       0: new           #12                 // class org/apache/hadoop/hbase/client/PerClientRandomNonceGenerator
       3: dup
       4: invokespecial #13                 // Method "<init>":()V
       7: putstatic     #11                 // Field INST:Lorg/apache/hadoop/hbase/client/PerClientRandomNonceGenerator;
      10: return
}
