Compiled from "Permission.java"
public final class org.apache.hadoop.hbase.security.access.Permission$Action extends java.lang.Enum<org.apache.hadoop.hbase.security.access.Permission$Action> {
  public static final org.apache.hadoop.hbase.security.access.Permission$Action READ;

  public static final org.apache.hadoop.hbase.security.access.Permission$Action WRITE;

  public static final org.apache.hadoop.hbase.security.access.Permission$Action EXEC;

  public static final org.apache.hadoop.hbase.security.access.Permission$Action CREATE;

  public static final org.apache.hadoop.hbase.security.access.Permission$Action ADMIN;

  public static org.apache.hadoop.hbase.security.access.Permission$Action[] values();
    Code:
       0: getstatic     #2                  // Field $VALUES:[Lorg/apache/hadoop/hbase/security/access/Permission$Action;
       3: invokevirtual #3                  // Method "[Lorg/apache/hadoop/hbase/security/access/Permission$Action;".clone:()Ljava/lang/Object;
       6: checkcast     #4                  // class "[Lorg/apache/hadoop/hbase/security/access/Permission$Action;"
       9: areturn

  public static org.apache.hadoop.hbase.security.access.Permission$Action valueOf(java.lang.String);
    Code:
       0: ldc           #5                  // class org/apache/hadoop/hbase/security/access/Permission$Action
       2: aload_0
       3: invokestatic  #6                  // Method java/lang/Enum.valueOf:(Ljava/lang/Class;Ljava/lang/String;)Ljava/lang/Enum;
       6: checkcast     #5                  // class org/apache/hadoop/hbase/security/access/Permission$Action
       9: areturn

  public byte code();
    Code:
       0: aload_0
       1: getfield      #1                  // Field code:B
       4: ireturn

  static byte access$000(org.apache.hadoop.hbase.security.access.Permission$Action);
    Code:
       0: aload_0
       1: getfield      #1                  // Field code:B
       4: ireturn

  static {};
    Code:
       0: new           #5                  // class org/apache/hadoop/hbase/security/access/Permission$Action
       3: dup
       4: ldc           #8                  // String READ
       6: iconst_0
       7: bipush        82
       9: invokespecial #9                  // Method "<init>":(Ljava/lang/String;IC)V
      12: putstatic     #10                 // Field READ:Lorg/apache/hadoop/hbase/security/access/Permission$Action;
      15: new           #5                  // class org/apache/hadoop/hbase/security/access/Permission$Action
      18: dup
      19: ldc           #11                 // String WRITE
      21: iconst_1
      22: bipush        87
      24: invokespecial #9                  // Method "<init>":(Ljava/lang/String;IC)V
      27: putstatic     #12                 // Field WRITE:Lorg/apache/hadoop/hbase/security/access/Permission$Action;
      30: new           #5                  // class org/apache/hadoop/hbase/security/access/Permission$Action
      33: dup
      34: ldc           #13                 // String EXEC
      36: iconst_2
      37: bipush        88
      39: invokespecial #9                  // Method "<init>":(Ljava/lang/String;IC)V
      42: putstatic     #14                 // Field EXEC:Lorg/apache/hadoop/hbase/security/access/Permission$Action;
      45: new           #5                  // class org/apache/hadoop/hbase/security/access/Permission$Action
      48: dup
      49: ldc           #15                 // String CREATE
      51: iconst_3
      52: bipush        67
      54: invokespecial #9                  // Method "<init>":(Ljava/lang/String;IC)V
      57: putstatic     #16                 // Field CREATE:Lorg/apache/hadoop/hbase/security/access/Permission$Action;
      60: new           #5                  // class org/apache/hadoop/hbase/security/access/Permission$Action
      63: dup
      64: ldc           #17                 // String ADMIN
      66: iconst_4
      67: bipush        65
      69: invokespecial #9                  // Method "<init>":(Ljava/lang/String;IC)V
      72: putstatic     #18                 // Field ADMIN:Lorg/apache/hadoop/hbase/security/access/Permission$Action;
      75: iconst_5
      76: anewarray     #5                  // class org/apache/hadoop/hbase/security/access/Permission$Action
      79: dup
      80: iconst_0
      81: getstatic     #10                 // Field READ:Lorg/apache/hadoop/hbase/security/access/Permission$Action;
      84: aastore
      85: dup
      86: iconst_1
      87: getstatic     #12                 // Field WRITE:Lorg/apache/hadoop/hbase/security/access/Permission$Action;
      90: aastore
      91: dup
      92: iconst_2
      93: getstatic     #14                 // Field EXEC:Lorg/apache/hadoop/hbase/security/access/Permission$Action;
      96: aastore
      97: dup
      98: iconst_3
      99: getstatic     #16                 // Field CREATE:Lorg/apache/hadoop/hbase/security/access/Permission$Action;
     102: aastore
     103: dup
     104: iconst_4
     105: getstatic     #18                 // Field ADMIN:Lorg/apache/hadoop/hbase/security/access/Permission$Action;
     108: aastore
     109: putstatic     #2                  // Field $VALUES:[Lorg/apache/hadoop/hbase/security/access/Permission$Action;
     112: return
}
