Compiled from "Permission.java"
public final class org.apache.hadoop.hbase.security.access.Permission$Builder {
  public org.apache.hadoop.hbase.security.access.Permission$Builder withFamily(byte[]);
    Code:
       0: aload_0
       1: getfield      #9                  // Field tableName:Lorg/apache/hadoop/hbase/TableName;
       4: ldc           #10                 // String The tableName can't be NULL
       6: invokestatic  #11                 // Method java/util/Objects.requireNonNull:(Ljava/lang/Object;Ljava/lang/String;)Ljava/lang/Object;
       9: pop
      10: aload_0
      11: aload_1
      12: putfield      #12                 // Field family:[B
      15: aload_0
      16: areturn

  public org.apache.hadoop.hbase.security.access.Permission$Builder withQualifier(byte[]);
    Code:
       0: aload_0
       1: getfield      #9                  // Field tableName:Lorg/apache/hadoop/hbase/TableName;
       4: ldc           #10                 // String The tableName can't be NULL
       6: invokestatic  #11                 // Method java/util/Objects.requireNonNull:(Ljava/lang/Object;Ljava/lang/String;)Ljava/lang/Object;
       9: pop
      10: aload_0
      11: aload_1
      12: putfield      #13                 // Field qualifier:[B
      15: aload_0
      16: areturn

  public org.apache.hadoop.hbase.security.access.Permission$Builder withActions(org.apache.hadoop.hbase.security.access.Permission$Action...);
    Code:
       0: aload_1
       1: astore_2
       2: aload_2
       3: arraylength
       4: istore_3
       5: iconst_0
       6: istore        4
       8: iload         4
      10: iload_3
      11: if_icmpge     43
      14: aload_2
      15: iload         4
      17: aaload
      18: astore        5
      20: aload         5
      22: ifnull        37
      25: aload_0
      26: getfield      #7                  // Field actions:Ljava/util/List;
      29: aload         5
      31: invokeinterface #14,  2           // InterfaceMethod java/util/List.add:(Ljava/lang/Object;)Z
      36: pop
      37: iinc          4, 1
      40: goto          8
      43: aload_0
      44: areturn

  public org.apache.hadoop.hbase.security.access.Permission$Builder withActionCodes(byte[]);
    Code:
       0: aload_1
       1: ifnull        89
       4: aload_1
       5: astore_2
       6: aload_2
       7: arraylength
       8: istore_3
       9: iconst_0
      10: istore        4
      12: iload         4
      14: iload_3
      15: if_icmpge     89
      18: aload_2
      19: iload         4
      21: baload
      22: istore        5
      24: getstatic     #15                 // Field org/apache/hadoop/hbase/security/access/Permission.ACTION_BY_CODE:Ljava/util/Map;
      27: iload         5
      29: invokestatic  #16                 // Method java/lang/Byte.valueOf:(B)Ljava/lang/Byte;
      32: invokeinterface #17,  2           // InterfaceMethod java/util/Map.get:(Ljava/lang/Object;)Ljava/lang/Object;
      37: checkcast     #18                 // class org/apache/hadoop/hbase/security/access/Permission$Action
      40: astore        6
      42: aload         6
      44: ifnonnull     71
      47: invokestatic  #19                 // Method org/apache/hadoop/hbase/security/access/Permission.access$500:()Lorg/slf4j/Logger;
      50: ldc           #20                 // String Ignoring unknown action code '{}'
      52: iconst_1
      53: newarray       byte
      55: dup
      56: iconst_0
      57: iload         5
      59: bastore
      60: invokestatic  #21                 // Method org/apache/hadoop/hbase/util/Bytes.toStringBinary:([B)Ljava/lang/String;
      63: invokeinterface #22,  3           // InterfaceMethod org/slf4j/Logger.error:(Ljava/lang/String;Ljava/lang/Object;)V
      68: goto          83
      71: aload_0
      72: getfield      #7                  // Field actions:Ljava/util/List;
      75: aload         6
      77: invokeinterface #14,  2           // InterfaceMethod java/util/List.add:(Ljava/lang/Object;)Z
      82: pop
      83: iinc          4, 1
      86: goto          12
      89: aload_0
      90: areturn

  public org.apache.hadoop.hbase.security.access.Permission build();
    Code:
       0: aload_0
       1: getfield      #7                  // Field actions:Ljava/util/List;
       4: aload_0
       5: getfield      #7                  // Field actions:Ljava/util/List;
       8: invokeinterface #23,  1           // InterfaceMethod java/util/List.size:()I
      13: anewarray     #18                 // class org/apache/hadoop/hbase/security/access/Permission$Action
      16: invokeinterface #24,  2           // InterfaceMethod java/util/List.toArray:([Ljava/lang/Object;)[Ljava/lang/Object;
      21: checkcast     #25                 // class "[Lorg/apache/hadoop/hbase/security/access/Permission$Action;"
      24: astore_1
      25: aload_0
      26: getfield      #8                  // Field namespace:Ljava/lang/String;
      29: ifnull        45
      32: new           #26                 // class org/apache/hadoop/hbase/security/access/NamespacePermission
      35: dup
      36: aload_0
      37: getfield      #8                  // Field namespace:Ljava/lang/String;
      40: aload_1
      41: invokespecial #27                 // Method org/apache/hadoop/hbase/security/access/NamespacePermission."<init>":(Ljava/lang/String;[Lorg/apache/hadoop/hbase/security/access/Permission$Action;)V
      44: areturn
      45: aload_0
      46: getfield      #9                  // Field tableName:Lorg/apache/hadoop/hbase/TableName;
      49: ifnull        73
      52: new           #28                 // class org/apache/hadoop/hbase/security/access/TablePermission
      55: dup
      56: aload_0
      57: getfield      #9                  // Field tableName:Lorg/apache/hadoop/hbase/TableName;
      60: aload_0
      61: getfield      #12                 // Field family:[B
      64: aload_0
      65: getfield      #13                 // Field qualifier:[B
      68: aload_1
      69: invokespecial #29                 // Method org/apache/hadoop/hbase/security/access/TablePermission."<init>":(Lorg/apache/hadoop/hbase/TableName;[B[B[Lorg/apache/hadoop/hbase/security/access/Permission$Action;)V
      72: areturn
      73: new           #30                 // class org/apache/hadoop/hbase/security/access/GlobalPermission
      76: dup
      77: aload_1
      78: invokespecial #31                 // Method org/apache/hadoop/hbase/security/access/GlobalPermission."<init>":([Lorg/apache/hadoop/hbase/security/access/Permission$Action;)V
      81: areturn

  org.apache.hadoop.hbase.security.access.Permission$Builder(org.apache.hadoop.hbase.security.access.Permission$1);
    Code:
       0: aload_0
       1: invokespecial #3                  // Method "<init>":()V
       4: return

  org.apache.hadoop.hbase.security.access.Permission$Builder(java.lang.String, org.apache.hadoop.hbase.security.access.Permission$1);
    Code:
       0: aload_0
       1: aload_1
       2: invokespecial #2                  // Method "<init>":(Ljava/lang/String;)V
       5: return

  org.apache.hadoop.hbase.security.access.Permission$Builder(org.apache.hadoop.hbase.TableName, org.apache.hadoop.hbase.security.access.Permission$1);
    Code:
       0: aload_0
       1: aload_1
       2: invokespecial #1                  // Method "<init>":(Lorg/apache/hadoop/hbase/TableName;)V
       5: return
}
