Compiled from "PingProtos.java"
final class org.apache.hadoop.hbase.coprocessor.protobuf.generated.PingProtos$PingService$1 extends org.apache.hadoop.hbase.coprocessor.protobuf.generated.PingProtos$PingService {
  final org.apache.hadoop.hbase.coprocessor.protobuf.generated.PingProtos$PingService$Interface val$impl;

  org.apache.hadoop.hbase.coprocessor.protobuf.generated.PingProtos$PingService$1(org.apache.hadoop.hbase.coprocessor.protobuf.generated.PingProtos$PingService$Interface);
    Code:
       0: aload_0
       1: aload_1
       2: putfield      #1                  // Field val$impl:Lorg/apache/hadoop/hbase/coprocessor/protobuf/generated/PingProtos$PingService$Interface;
       5: aload_0
       6: invokespecial #2                  // Method org/apache/hadoop/hbase/coprocessor/protobuf/generated/PingProtos$PingService."<init>":()V
       9: return

  public void ping(com.google.protobuf.RpcController, org.apache.hadoop.hbase.coprocessor.protobuf.generated.PingProtos$PingRequest, com.google.protobuf.RpcCallback<org.apache.hadoop.hbase.coprocessor.protobuf.generated.PingProtos$PingResponse>);
    Code:
       0: aload_0
       1: getfield      #1                  // Field val$impl:Lorg/apache/hadoop/hbase/coprocessor/protobuf/generated/PingProtos$PingService$Interface;
       4: aload_1
       5: aload_2
       6: aload_3
       7: invokeinterface #3,  4            // InterfaceMethod org/apache/hadoop/hbase/coprocessor/protobuf/generated/PingProtos$PingService$Interface.ping:(Lcom/google/protobuf/RpcController;Lorg/apache/hadoop/hbase/coprocessor/protobuf/generated/PingProtos$PingRequest;Lcom/google/protobuf/RpcCallback;)V
      12: return

  public void count(com.google.protobuf.RpcController, org.apache.hadoop.hbase.coprocessor.protobuf.generated.PingProtos$CountRequest, com.google.protobuf.RpcCallback<org.apache.hadoop.hbase.coprocessor.protobuf.generated.PingProtos$CountResponse>);
    Code:
       0: aload_0
       1: getfield      #1                  // Field val$impl:Lorg/apache/hadoop/hbase/coprocessor/protobuf/generated/PingProtos$PingService$Interface;
       4: aload_1
       5: aload_2
       6: aload_3
       7: invokeinterface #4,  4            // InterfaceMethod org/apache/hadoop/hbase/coprocessor/protobuf/generated/PingProtos$PingService$Interface.count:(Lcom/google/protobuf/RpcController;Lorg/apache/hadoop/hbase/coprocessor/protobuf/generated/PingProtos$CountRequest;Lcom/google/protobuf/RpcCallback;)V
      12: return

  public void increment(com.google.protobuf.RpcController, org.apache.hadoop.hbase.coprocessor.protobuf.generated.PingProtos$IncrementCountRequest, com.google.protobuf.RpcCallback<org.apache.hadoop.hbase.coprocessor.protobuf.generated.PingProtos$IncrementCountResponse>);
    Code:
       0: aload_0
       1: getfield      #1                  // Field val$impl:Lorg/apache/hadoop/hbase/coprocessor/protobuf/generated/PingProtos$PingService$Interface;
       4: aload_1
       5: aload_2
       6: aload_3
       7: invokeinterface #5,  4            // InterfaceMethod org/apache/hadoop/hbase/coprocessor/protobuf/generated/PingProtos$PingService$Interface.increment:(Lcom/google/protobuf/RpcController;Lorg/apache/hadoop/hbase/coprocessor/protobuf/generated/PingProtos$IncrementCountRequest;Lcom/google/protobuf/RpcCallback;)V
      12: return

  public void hello(com.google.protobuf.RpcController, org.apache.hadoop.hbase.coprocessor.protobuf.generated.PingProtos$HelloRequest, com.google.protobuf.RpcCallback<org.apache.hadoop.hbase.coprocessor.protobuf.generated.PingProtos$HelloResponse>);
    Code:
       0: aload_0
       1: getfield      #1                  // Field val$impl:Lorg/apache/hadoop/hbase/coprocessor/protobuf/generated/PingProtos$PingService$Interface;
       4: aload_1
       5: aload_2
       6: aload_3
       7: invokeinterface #6,  4            // InterfaceMethod org/apache/hadoop/hbase/coprocessor/protobuf/generated/PingProtos$PingService$Interface.hello:(Lcom/google/protobuf/RpcController;Lorg/apache/hadoop/hbase/coprocessor/protobuf/generated/PingProtos$HelloRequest;Lcom/google/protobuf/RpcCallback;)V
      12: return

  public void noop(com.google.protobuf.RpcController, org.apache.hadoop.hbase.coprocessor.protobuf.generated.PingProtos$NoopRequest, com.google.protobuf.RpcCallback<org.apache.hadoop.hbase.coprocessor.protobuf.generated.PingProtos$NoopResponse>);
    Code:
       0: aload_0
       1: getfield      #1                  // Field val$impl:Lorg/apache/hadoop/hbase/coprocessor/protobuf/generated/PingProtos$PingService$Interface;
       4: aload_1
       5: aload_2
       6: aload_3
       7: invokeinterface #7,  4            // InterfaceMethod org/apache/hadoop/hbase/coprocessor/protobuf/generated/PingProtos$PingService$Interface.noop:(Lcom/google/protobuf/RpcController;Lorg/apache/hadoop/hbase/coprocessor/protobuf/generated/PingProtos$NoopRequest;Lcom/google/protobuf/RpcCallback;)V
      12: return
}
