Compiled from "PoolMap.java"
public class org.apache.hadoop.hbase.util.PoolMap<K, V> implements java.util.Map<K, V> {
  public org.apache.hadoop.hbase.util.PoolMap(org.apache.hadoop.hbase.util.PoolMap$PoolType);
    Code:
       0: aload_0
       1: invokespecial #1                  // Method java/lang/Object."<init>":()V
       4: aload_0
       5: new           #2                  // class java/util/concurrent/ConcurrentHashMap
       8: dup
       9: invokespecial #3                  // Method java/util/concurrent/ConcurrentHashMap."<init>":()V
      12: putfield      #4                  // Field pools:Ljava/util/Map;
      15: aload_0
      16: aload_1
      17: putfield      #5                  // Field poolType:Lorg/apache/hadoop/hbase/util/PoolMap$PoolType;
      20: return

  public org.apache.hadoop.hbase.util.PoolMap(org.apache.hadoop.hbase.util.PoolMap$PoolType, int);
    Code:
       0: aload_0
       1: invokespecial #1                  // Method java/lang/Object."<init>":()V
       4: aload_0
       5: new           #2                  // class java/util/concurrent/ConcurrentHashMap
       8: dup
       9: invokespecial #3                  // Method java/util/concurrent/ConcurrentHashMap."<init>":()V
      12: putfield      #4                  // Field pools:Ljava/util/Map;
      15: aload_0
      16: aload_1
      17: putfield      #5                  // Field poolType:Lorg/apache/hadoop/hbase/util/PoolMap$PoolType;
      20: aload_0
      21: iload_2
      22: putfield      #6                  // Field poolMaxSize:I
      25: return

  public V get(java.lang.Object);
    Code:
       0: aload_0
       1: getfield      #4                  // Field pools:Ljava/util/Map;
       4: aload_1
       5: invokeinterface #7,  2            // InterfaceMethod java/util/Map.get:(Ljava/lang/Object;)Ljava/lang/Object;
      10: checkcast     #8                  // class org/apache/hadoop/hbase/util/PoolMap$Pool
      13: astore_2
      14: aload_2
      15: ifnull        27
      18: aload_2
      19: invokeinterface #9,  1            // InterfaceMethod org/apache/hadoop/hbase/util/PoolMap$Pool.get:()Ljava/lang/Object;
      24: goto          28
      27: aconst_null
      28: areturn

  public V put(K, V);
    Code:
       0: aload_0
       1: getfield      #4                  // Field pools:Ljava/util/Map;
       4: aload_1
       5: invokeinterface #7,  2            // InterfaceMethod java/util/Map.get:(Ljava/lang/Object;)Ljava/lang/Object;
      10: checkcast     #8                  // class org/apache/hadoop/hbase/util/PoolMap$Pool
      13: astore_3
      14: aload_3
      15: ifnonnull     35
      18: aload_0
      19: getfield      #4                  // Field pools:Ljava/util/Map;
      22: aload_1
      23: aload_0
      24: invokevirtual #10                 // Method createPool:()Lorg/apache/hadoop/hbase/util/PoolMap$Pool;
      27: dup
      28: astore_3
      29: invokeinterface #11,  3           // InterfaceMethod java/util/Map.put:(Ljava/lang/Object;Ljava/lang/Object;)Ljava/lang/Object;
      34: pop
      35: aload_3
      36: ifnull        49
      39: aload_3
      40: aload_2
      41: invokeinterface #12,  2           // InterfaceMethod org/apache/hadoop/hbase/util/PoolMap$Pool.put:(Ljava/lang/Object;)Ljava/lang/Object;
      46: goto          50
      49: aconst_null
      50: areturn

  public V remove(java.lang.Object);
    Code:
       0: aload_0
       1: getfield      #4                  // Field pools:Ljava/util/Map;
       4: aload_1
       5: invokeinterface #13,  2           // InterfaceMethod java/util/Map.remove:(Ljava/lang/Object;)Ljava/lang/Object;
      10: checkcast     #8                  // class org/apache/hadoop/hbase/util/PoolMap$Pool
      13: astore_2
      14: aload_2
      15: ifnull        30
      18: aload_0
      19: aload_1
      20: aload_2
      21: invokeinterface #9,  1            // InterfaceMethod org/apache/hadoop/hbase/util/PoolMap$Pool.get:()Ljava/lang/Object;
      26: invokevirtual #14                 // Method removeValue:(Ljava/lang/Object;Ljava/lang/Object;)Z
      29: pop
      30: aconst_null
      31: areturn

  public boolean removeValue(K, V);
    Code:
       0: aload_0
       1: getfield      #4                  // Field pools:Ljava/util/Map;
       4: aload_1
       5: invokeinterface #7,  2            // InterfaceMethod java/util/Map.get:(Ljava/lang/Object;)Ljava/lang/Object;
      10: checkcast     #8                  // class org/apache/hadoop/hbase/util/PoolMap$Pool
      13: astore_3
      14: iconst_0
      15: istore        4
      17: aload_3
      18: ifnull        55
      21: aload_3
      22: aload_2
      23: invokeinterface #15,  2           // InterfaceMethod org/apache/hadoop/hbase/util/PoolMap$Pool.remove:(Ljava/lang/Object;)Z
      28: istore        4
      30: iload         4
      32: ifeq          55
      35: aload_3
      36: invokeinterface #16,  1           // InterfaceMethod org/apache/hadoop/hbase/util/PoolMap$Pool.size:()I
      41: ifne          55
      44: aload_0
      45: getfield      #4                  // Field pools:Ljava/util/Map;
      48: aload_1
      49: invokeinterface #13,  2           // InterfaceMethod java/util/Map.remove:(Ljava/lang/Object;)Ljava/lang/Object;
      54: pop
      55: iload         4
      57: ireturn

  public java.util.Collection<V> values();
    Code:
       0: new           #17                 // class java/util/ArrayList
       3: dup
       4: invokespecial #18                 // Method java/util/ArrayList."<init>":()V
       7: astore_1
       8: aload_0
       9: getfield      #4                  // Field pools:Ljava/util/Map;
      12: invokeinterface #19,  1           // InterfaceMethod java/util/Map.values:()Ljava/util/Collection;
      17: invokeinterface #20,  1           // InterfaceMethod java/util/Collection.iterator:()Ljava/util/Iterator;
      22: astore_2
      23: aload_2
      24: invokeinterface #21,  1           // InterfaceMethod java/util/Iterator.hasNext:()Z
      29: ifeq          67
      32: aload_2
      33: invokeinterface #22,  1           // InterfaceMethod java/util/Iterator.next:()Ljava/lang/Object;
      38: checkcast     #8                  // class org/apache/hadoop/hbase/util/PoolMap$Pool
      41: astore_3
      42: aload_3
      43: invokeinterface #23,  1           // InterfaceMethod org/apache/hadoop/hbase/util/PoolMap$Pool.values:()Ljava/util/Collection;
      48: astore        4
      50: aload         4
      52: ifnull        64
      55: aload_1
      56: aload         4
      58: invokeinterface #24,  2           // InterfaceMethod java/util/Collection.addAll:(Ljava/util/Collection;)Z
      63: pop
      64: goto          23
      67: aload_1
      68: areturn

  public java.util.Collection<V> values(K);
    Code:
       0: new           #17                 // class java/util/ArrayList
       3: dup
       4: invokespecial #18                 // Method java/util/ArrayList."<init>":()V
       7: astore_2
       8: aload_0
       9: getfield      #4                  // Field pools:Ljava/util/Map;
      12: aload_1
      13: invokeinterface #7,  2            // InterfaceMethod java/util/Map.get:(Ljava/lang/Object;)Ljava/lang/Object;
      18: checkcast     #8                  // class org/apache/hadoop/hbase/util/PoolMap$Pool
      21: astore_3
      22: aload_3
      23: ifnull        48
      26: aload_3
      27: invokeinterface #23,  1           // InterfaceMethod org/apache/hadoop/hbase/util/PoolMap$Pool.values:()Ljava/util/Collection;
      32: astore        4
      34: aload         4
      36: ifnull        48
      39: aload_2
      40: aload         4
      42: invokeinterface #24,  2           // InterfaceMethod java/util/Collection.addAll:(Ljava/util/Collection;)Z
      47: pop
      48: aload_2
      49: areturn

  public boolean isEmpty();
    Code:
       0: aload_0
       1: getfield      #4                  // Field pools:Ljava/util/Map;
       4: invokeinterface #25,  1           // InterfaceMethod java/util/Map.isEmpty:()Z
       9: ireturn

  public int size();
    Code:
       0: aload_0
       1: getfield      #4                  // Field pools:Ljava/util/Map;
       4: invokeinterface #26,  1           // InterfaceMethod java/util/Map.size:()I
       9: ireturn

  public int size(K);
    Code:
       0: aload_0
       1: getfield      #4                  // Field pools:Ljava/util/Map;
       4: aload_1
       5: invokeinterface #7,  2            // InterfaceMethod java/util/Map.get:(Ljava/lang/Object;)Ljava/lang/Object;
      10: checkcast     #8                  // class org/apache/hadoop/hbase/util/PoolMap$Pool
      13: astore_2
      14: aload_2
      15: ifnull        27
      18: aload_2
      19: invokeinterface #16,  1           // InterfaceMethod org/apache/hadoop/hbase/util/PoolMap$Pool.size:()I
      24: goto          28
      27: iconst_0
      28: ireturn

  public boolean containsKey(java.lang.Object);
    Code:
       0: aload_0
       1: getfield      #4                  // Field pools:Ljava/util/Map;
       4: aload_1
       5: invokeinterface #27,  2           // InterfaceMethod java/util/Map.containsKey:(Ljava/lang/Object;)Z
      10: ireturn

  public boolean containsValue(java.lang.Object);
    Code:
       0: aload_1
       1: ifnonnull     6
       4: iconst_0
       5: ireturn
       6: aload_0
       7: getfield      #4                  // Field pools:Ljava/util/Map;
      10: invokeinterface #19,  1           // InterfaceMethod java/util/Map.values:()Ljava/util/Collection;
      15: invokeinterface #20,  1           // InterfaceMethod java/util/Collection.iterator:()Ljava/util/Iterator;
      20: astore_2
      21: aload_2
      22: invokeinterface #21,  1           // InterfaceMethod java/util/Iterator.hasNext:()Z
      27: ifeq          58
      30: aload_2
      31: invokeinterface #22,  1           // InterfaceMethod java/util/Iterator.next:()Ljava/lang/Object;
      36: checkcast     #8                  // class org/apache/hadoop/hbase/util/PoolMap$Pool
      39: astore_3
      40: aload_1
      41: aload_3
      42: invokeinterface #9,  1            // InterfaceMethod org/apache/hadoop/hbase/util/PoolMap$Pool.get:()Ljava/lang/Object;
      47: invokevirtual #28                 // Method java/lang/Object.equals:(Ljava/lang/Object;)Z
      50: ifeq          55
      53: iconst_1
      54: ireturn
      55: goto          21
      58: iconst_0
      59: ireturn

  public void putAll(java.util.Map<? extends K, ? extends V>);
    Code:
       0: aload_1
       1: invokeinterface #29,  1           // InterfaceMethod java/util/Map.entrySet:()Ljava/util/Set;
       6: invokeinterface #30,  1           // InterfaceMethod java/util/Set.iterator:()Ljava/util/Iterator;
      11: astore_2
      12: aload_2
      13: invokeinterface #21,  1           // InterfaceMethod java/util/Iterator.hasNext:()Z
      18: ifeq          51
      21: aload_2
      22: invokeinterface #22,  1           // InterfaceMethod java/util/Iterator.next:()Ljava/lang/Object;
      27: checkcast     #31                 // class java/util/Map$Entry
      30: astore_3
      31: aload_0
      32: aload_3
      33: invokeinterface #32,  1           // InterfaceMethod java/util/Map$Entry.getKey:()Ljava/lang/Object;
      38: aload_3
      39: invokeinterface #33,  1           // InterfaceMethod java/util/Map$Entry.getValue:()Ljava/lang/Object;
      44: invokevirtual #34                 // Method put:(Ljava/lang/Object;Ljava/lang/Object;)Ljava/lang/Object;
      47: pop
      48: goto          12
      51: return

  public void clear();
    Code:
       0: aload_0
       1: getfield      #4                  // Field pools:Ljava/util/Map;
       4: invokeinterface #19,  1           // InterfaceMethod java/util/Map.values:()Ljava/util/Collection;
       9: invokeinterface #20,  1           // InterfaceMethod java/util/Collection.iterator:()Ljava/util/Iterator;
      14: astore_1
      15: aload_1
      16: invokeinterface #21,  1           // InterfaceMethod java/util/Iterator.hasNext:()Z
      21: ifeq          43
      24: aload_1
      25: invokeinterface #22,  1           // InterfaceMethod java/util/Iterator.next:()Ljava/lang/Object;
      30: checkcast     #8                  // class org/apache/hadoop/hbase/util/PoolMap$Pool
      33: astore_2
      34: aload_2
      35: invokeinterface #35,  1           // InterfaceMethod org/apache/hadoop/hbase/util/PoolMap$Pool.clear:()V
      40: goto          15
      43: aload_0
      44: getfield      #4                  // Field pools:Ljava/util/Map;
      47: invokeinterface #36,  1           // InterfaceMethod java/util/Map.clear:()V
      52: return

  public java.util.Set<K> keySet();
    Code:
       0: aload_0
       1: getfield      #4                  // Field pools:Ljava/util/Map;
       4: invokeinterface #37,  1           // InterfaceMethod java/util/Map.keySet:()Ljava/util/Set;
       9: areturn

  public java.util.Set<java.util.Map$Entry<K, V>> entrySet();
    Code:
       0: new           #38                 // class java/util/HashSet
       3: dup
       4: invokespecial #39                 // Method java/util/HashSet."<init>":()V
       7: astore_1
       8: aload_0
       9: getfield      #4                  // Field pools:Ljava/util/Map;
      12: invokeinterface #29,  1           // InterfaceMethod java/util/Map.entrySet:()Ljava/util/Set;
      17: invokeinterface #30,  1           // InterfaceMethod java/util/Set.iterator:()Ljava/util/Iterator;
      22: astore_2
      23: aload_2
      24: invokeinterface #21,  1           // InterfaceMethod java/util/Iterator.hasNext:()Z
      29: ifeq          126
      32: aload_2
      33: invokeinterface #22,  1           // InterfaceMethod java/util/Iterator.next:()Ljava/lang/Object;
      38: checkcast     #31                 // class java/util/Map$Entry
      41: astore_3
      42: aload_3
      43: invokeinterface #32,  1           // InterfaceMethod java/util/Map$Entry.getKey:()Ljava/lang/Object;
      48: astore        4
      50: aload_3
      51: invokeinterface #33,  1           // InterfaceMethod java/util/Map$Entry.getValue:()Ljava/lang/Object;
      56: checkcast     #8                  // class org/apache/hadoop/hbase/util/PoolMap$Pool
      59: astore        5
      61: aload         5
      63: ifnull        123
      66: aload         5
      68: invokeinterface #23,  1           // InterfaceMethod org/apache/hadoop/hbase/util/PoolMap$Pool.values:()Ljava/util/Collection;
      73: invokeinterface #20,  1           // InterfaceMethod java/util/Collection.iterator:()Ljava/util/Iterator;
      78: astore        6
      80: aload         6
      82: invokeinterface #21,  1           // InterfaceMethod java/util/Iterator.hasNext:()Z
      87: ifeq          123
      90: aload         6
      92: invokeinterface #22,  1           // InterfaceMethod java/util/Iterator.next:()Ljava/lang/Object;
      97: astore        7
      99: aload_1
     100: new           #40                 // class org/apache/hadoop/hbase/util/PoolMap$1
     103: dup
     104: aload_0
     105: aload         4
     107: aload         7
     109: aload         5
     111: invokespecial #41                 // Method org/apache/hadoop/hbase/util/PoolMap$1."<init>":(Lorg/apache/hadoop/hbase/util/PoolMap;Ljava/lang/Object;Ljava/lang/Object;Lorg/apache/hadoop/hbase/util/PoolMap$Pool;)V
     114: invokeinterface #42,  2           // InterfaceMethod java/util/Set.add:(Ljava/lang/Object;)Z
     119: pop
     120: goto          80
     123: goto          23
     126: aload_1
     127: areturn

  protected org.apache.hadoop.hbase.util.PoolMap$Pool<V> createPool();
    Code:
       0: getstatic     #43                 // Field org/apache/hadoop/hbase/util/PoolMap$2.$SwitchMap$org$apache$hadoop$hbase$util$PoolMap$PoolType:[I
       3: aload_0
       4: getfield      #5                  // Field poolType:Lorg/apache/hadoop/hbase/util/PoolMap$PoolType;
       7: invokevirtual #44                 // Method org/apache/hadoop/hbase/util/PoolMap$PoolType.ordinal:()I
      10: iaload
      11: tableswitch   { // 1 to 3
                     1: 36
                     2: 48
                     3: 60
               default: 68
          }
      36: new           #45                 // class org/apache/hadoop/hbase/util/PoolMap$ReusablePool
      39: dup
      40: aload_0
      41: getfield      #6                  // Field poolMaxSize:I
      44: invokespecial #46                 // Method org/apache/hadoop/hbase/util/PoolMap$ReusablePool."<init>":(I)V
      47: areturn
      48: new           #47                 // class org/apache/hadoop/hbase/util/PoolMap$RoundRobinPool
      51: dup
      52: aload_0
      53: getfield      #6                  // Field poolMaxSize:I
      56: invokespecial #48                 // Method org/apache/hadoop/hbase/util/PoolMap$RoundRobinPool."<init>":(I)V
      59: areturn
      60: new           #49                 // class org/apache/hadoop/hbase/util/PoolMap$ThreadLocalPool
      63: dup
      64: invokespecial #50                 // Method org/apache/hadoop/hbase/util/PoolMap$ThreadLocalPool."<init>":()V
      67: areturn
      68: aconst_null
      69: areturn
}
