Compiled from "PrefetchExecutor.java"
final class org.apache.hadoop.hbase.io.hfile.PrefetchExecutor$1 implements java.util.concurrent.ThreadFactory {
  org.apache.hadoop.hbase.io.hfile.PrefetchExecutor$1();
    Code:
       0: aload_0
       1: invokespecial #1                  // Method java/lang/Object."<init>":()V
       4: return

  public java.lang.Thread newThread(java.lang.Runnable);
    Code:
       0: new           #2                  // class java/lang/StringBuilder
       3: dup
       4: invokespecial #3                  // Method java/lang/StringBuilder."<init>":()V
       7: ldc           #4                  // String hfile-prefetch-
       9: invokevirtual #5                  // Method java/lang/StringBuilder.append:(Ljava/lang/String;)Ljava/lang/StringBuilder;
      12: invokestatic  #6                  // Method java/lang/System.currentTimeMillis:()J
      15: invokevirtual #7                  // Method java/lang/StringBuilder.append:(J)Ljava/lang/StringBuilder;
      18: invokevirtual #8                  // Method java/lang/StringBuilder.toString:()Ljava/lang/String;
      21: astore_2
      22: new           #9                  // class java/lang/Thread
      25: dup
      26: aload_1
      27: aload_2
      28: invokespecial #10                 // Method java/lang/Thread."<init>":(Ljava/lang/Runnable;Ljava/lang/String;)V
      31: astore_3
      32: aload_3
      33: iconst_1
      34: invokevirtual #11                 // Method java/lang/Thread.setDaemon:(Z)V
      37: aload_3
      38: areturn
}
