Compiled from "PrivateCellUtil.java"
final class org.apache.hadoop.hbase.PrivateCellUtil$2 extends org.apache.hadoop.hbase.PrivateCellUtil$LastOnRowColByteBufferExtendedCell {
  final long val$ts;

  final byte val$type;

  org.apache.hadoop.hbase.PrivateCellUtil$2(java.nio.ByteBuffer, int, short, java.nio.ByteBuffer, int, byte, java.nio.ByteBuffer, int, int, long, byte);
    Code:
       0: aload_0
       1: lload         10
       3: putfield      #1                  // Field val$ts:J
       6: aload_0
       7: iload         12
       9: putfield      #2                  // Field val$type:B
      12: aload_0
      13: aload_1
      14: iload_2
      15: iload_3
      16: aload         4
      18: iload         5
      20: iload         6
      22: aload         7
      24: iload         8
      26: iload         9
      28: invokespecial #3                  // Method org/apache/hadoop/hbase/PrivateCellUtil$LastOnRowColByteBufferExtendedCell."<init>":(Ljava/nio/ByteBuffer;ISLjava/nio/ByteBuffer;IBLjava/nio/ByteBuffer;II)V
      31: return

  public long getTimestamp();
    Code:
       0: aload_0
       1: getfield      #1                  // Field val$ts:J
       4: lreturn

  public byte getTypeByte();
    Code:
       0: aload_0
       1: getfield      #2                  // Field val$type:B
       4: ireturn
}
