Compiled from "PrivateCellUtil.java"
class org.apache.hadoop.hbase.PrivateCellUtil$ValueAndTagRewriteCell extends org.apache.hadoop.hbase.PrivateCellUtil$TagRewriteCell {
  protected byte[] value;

  public org.apache.hadoop.hbase.PrivateCellUtil$ValueAndTagRewriteCell(org.apache.hadoop.hbase.Cell, byte[], byte[]);
    Code:
       0: aload_0
       1: aload_1
       2: aload_3
       3: invokespecial #1                  // Method org/apache/hadoop/hbase/PrivateCellUtil$TagRewriteCell."<init>":(Lorg/apache/hadoop/hbase/Cell;[B)V
       6: aload_0
       7: aload_2
       8: putfield      #2                  // Field value:[B
      11: return

  public byte[] getValueArray();
    Code:
       0: aload_0
       1: getfield      #2                  // Field value:[B
       4: areturn

  public int getValueOffset();
    Code:
       0: iconst_0
       1: ireturn

  public int getValueLength();
    Code:
       0: aload_0
       1: getfield      #2                  // Field value:[B
       4: ifnonnull     11
       7: iconst_0
       8: goto          16
      11: aload_0
      12: getfield      #2                  // Field value:[B
      15: arraylength
      16: ireturn

  public long heapSize();
    Code:
       0: getstatic     #3                  // Field org/apache/hadoop/hbase/util/ClassSize.REFERENCE:I
       3: i2l
       4: aload_0
       5: invokespecial #4                  // Method org/apache/hadoop/hbase/PrivateCellUtil$TagRewriteCell.heapSize:()J
       8: ladd
       9: lstore_1
      10: aload_0
      11: getfield      #2                  // Field value:[B
      14: ifnull        27
      17: lload_1
      18: aload_0
      19: getfield      #2                  // Field value:[B
      22: invokestatic  #5                  // Method org/apache/hadoop/hbase/util/ClassSize.sizeOf:([B)J
      25: ladd
      26: lstore_1
      27: lload_1
      28: lreturn

  public int write(java.io.OutputStream, boolean) throws java.io.IOException;
    Code:
       0: aload_1
       1: iload_2
       2: aload_0
       3: getfield      #6                  // Field cell:Lorg/apache/hadoop/hbase/Cell;
       6: aload_0
       7: getfield      #2                  // Field value:[B
      10: aload_0
      11: getfield      #7                  // Field tags:[B
      14: invokestatic  #8                  // Method write:(Ljava/io/OutputStream;ZLorg/apache/hadoop/hbase/Cell;[B[B)I
      17: ireturn

  static int write(java.io.OutputStream, boolean, org.apache.hadoop.hbase.Cell, byte[], byte[]) throws java.io.IOException;
    Code:
       0: aload_3
       1: ifnonnull     8
       4: iconst_0
       5: goto          10
       8: aload_3
       9: arraylength
      10: istore        5
      12: aload_0
      13: aload_2
      14: invokestatic  #9                  // Method org/apache/hadoop/hbase/KeyValueUtil.keyLength:(Lorg/apache/hadoop/hbase/Cell;)I
      17: invokestatic  #10                 // Method org/apache/hadoop/hbase/util/ByteBufferUtils.putInt:(Ljava/io/OutputStream;I)V
      20: aload_0
      21: iload         5
      23: invokestatic  #10                 // Method org/apache/hadoop/hbase/util/ByteBufferUtils.putInt:(Ljava/io/OutputStream;I)V
      26: bipush        8
      28: istore        6
      30: iload         6
      32: aload_2
      33: aload_0
      34: invokestatic  #12                 // Method org/apache/hadoop/hbase/PrivateCellUtil.writeFlatKey:(Lorg/apache/hadoop/hbase/Cell;Ljava/io/OutputStream;)I
      37: iadd
      38: istore        6
      40: iload         5
      42: ifle          50
      45: aload_0
      46: aload_3
      47: invokevirtual #13                 // Method java/io/OutputStream.write:([B)V
      50: iload         6
      52: iload         5
      54: iadd
      55: istore        6
      57: iload_1
      58: ifeq          109
      61: aload         4
      63: ifnull        109
      66: aload_0
      67: sipush        255
      70: aload         4
      72: arraylength
      73: bipush        8
      75: ishr
      76: iand
      77: i2b
      78: invokevirtual #14                 // Method java/io/OutputStream.write:(I)V
      81: aload_0
      82: sipush        255
      85: aload         4
      87: arraylength
      88: iand
      89: i2b
      90: invokevirtual #14                 // Method java/io/OutputStream.write:(I)V
      93: aload_0
      94: aload         4
      96: invokevirtual #13                 // Method java/io/OutputStream.write:([B)V
      99: iload         6
     101: iconst_2
     102: aload         4
     104: arraylength
     105: iadd
     106: iadd
     107: istore        6
     109: iload         6
     111: ireturn

  public int getSerializedSize(boolean);
    Code:
       0: aload_0
       1: iload_1
       2: invokespecial #16                 // Method org/apache/hadoop/hbase/PrivateCellUtil$TagRewriteCell.getSerializedSize:(Z)I
       5: aload_0
       6: getfield      #6                  // Field cell:Lorg/apache/hadoop/hbase/Cell;
       9: invokeinterface #17,  1           // InterfaceMethod org/apache/hadoop/hbase/Cell.getValueLength:()I
      14: isub
      15: aload_0
      16: getfield      #2                  // Field value:[B
      19: arraylength
      20: iadd
      21: ireturn

  public void write(java.nio.ByteBuffer, int);
    Code:
       0: aload_1
       1: iload_2
       2: aload_0
       3: getfield      #6                  // Field cell:Lorg/apache/hadoop/hbase/Cell;
       6: aload_0
       7: getfield      #2                  // Field value:[B
      10: aload_0
      11: getfield      #7                  // Field tags:[B
      14: invokestatic  #18                 // Method write:(Ljava/nio/ByteBuffer;ILorg/apache/hadoop/hbase/Cell;[B[B)V
      17: return

  static void write(java.nio.ByteBuffer, int, org.apache.hadoop.hbase.Cell, byte[], byte[]);
    Code:
       0: aload_0
       1: iload_1
       2: aload_2
       3: invokestatic  #9                  // Method org/apache/hadoop/hbase/KeyValueUtil.keyLength:(Lorg/apache/hadoop/hbase/Cell;)I
       6: invokestatic  #19                 // Method org/apache/hadoop/hbase/util/ByteBufferUtils.putInt:(Ljava/nio/ByteBuffer;II)I
       9: istore_1
      10: aload_0
      11: iload_1
      12: aload_3
      13: arraylength
      14: invokestatic  #19                 // Method org/apache/hadoop/hbase/util/ByteBufferUtils.putInt:(Ljava/nio/ByteBuffer;II)I
      17: istore_1
      18: aload_2
      19: aload_0
      20: iload_1
      21: invokestatic  #20                 // Method org/apache/hadoop/hbase/KeyValueUtil.appendKeyTo:(Lorg/apache/hadoop/hbase/Cell;Ljava/nio/ByteBuffer;I)I
      24: istore_1
      25: aload_0
      26: iload_1
      27: aload_3
      28: iconst_0
      29: aload_3
      30: arraylength
      31: invokestatic  #21                 // Method org/apache/hadoop/hbase/util/ByteBufferUtils.copyFromArrayToBuffer:(Ljava/nio/ByteBuffer;I[BII)V
      34: iload_1
      35: aload_3
      36: arraylength
      37: iadd
      38: istore_1
      39: aload         4
      41: ifnonnull     48
      44: iconst_0
      45: goto          51
      48: aload         4
      50: arraylength
      51: istore        5
      53: iload         5
      55: ifle          76
      58: aload_0
      59: iload_1
      60: iload         5
      62: invokestatic  #22                 // Method org/apache/hadoop/hbase/util/ByteBufferUtils.putAsShort:(Ljava/nio/ByteBuffer;II)I
      65: istore_1
      66: aload_0
      67: iload_1
      68: aload         4
      70: iconst_0
      71: iload         5
      73: invokestatic  #21                 // Method org/apache/hadoop/hbase/util/ByteBufferUtils.copyFromArrayToBuffer:(Ljava/nio/ByteBuffer;I[BII)V
      76: return

  public org.apache.hadoop.hbase.ExtendedCell deepClone();
    Code:
       0: aload_0
       1: getfield      #6                  // Field cell:Lorg/apache/hadoop/hbase/Cell;
       4: checkcast     #23                 // class org/apache/hadoop/hbase/ExtendedCell
       7: invokeinterface #24,  1           // InterfaceMethod org/apache/hadoop/hbase/ExtendedCell.deepClone:()Lorg/apache/hadoop/hbase/ExtendedCell;
      12: astore_1
      13: new           #25                 // class org/apache/hadoop/hbase/PrivateCellUtil$ValueAndTagRewriteCell
      16: dup
      17: aload_1
      18: aload_0
      19: getfield      #2                  // Field value:[B
      22: aload_0
      23: getfield      #7                  // Field tags:[B
      26: invokespecial #26                 // Method "<init>":(Lorg/apache/hadoop/hbase/Cell;[B[B)V
      29: areturn
}
