Compiled from "PrivateCellUtil.java"
final class org.apache.hadoop.hbase.PrivateCellUtil$1 implements java.util.Iterator<org.apache.hadoop.hbase.Tag> {
  final int val$offset;

  final int val$length;

  final java.nio.ByteBuffer val$tags;

  org.apache.hadoop.hbase.PrivateCellUtil$1(int, int, java.nio.ByteBuffer);
    Code:
       0: aload_0
       1: iload_1
       2: putfield      #1                  // Field val$offset:I
       5: aload_0
       6: iload_2
       7: putfield      #2                  // Field val$length:I
      10: aload_0
      11: aload_3
      12: putfield      #3                  // Field val$tags:Ljava/nio/ByteBuffer;
      15: aload_0
      16: invokespecial #4                  // Method java/lang/Object."<init>":()V
      19: aload_0
      20: aload_0
      21: getfield      #1                  // Field val$offset:I
      24: putfield      #5                  // Field pos:I
      27: aload_0
      28: aload_0
      29: getfield      #1                  // Field val$offset:I
      32: aload_0
      33: getfield      #2                  // Field val$length:I
      36: iadd
      37: iconst_1
      38: isub
      39: putfield      #6                  // Field endOffset:I
      42: return

  public boolean hasNext();
    Code:
       0: aload_0
       1: getfield      #5                  // Field pos:I
       4: aload_0
       5: getfield      #6                  // Field endOffset:I
       8: if_icmpge     15
      11: iconst_1
      12: goto          16
      15: iconst_0
      16: ireturn

  public org.apache.hadoop.hbase.Tag next();
    Code:
       0: aload_0
       1: invokevirtual #7                  // Method hasNext:()Z
       4: ifeq          53
       7: aload_0
       8: getfield      #3                  // Field val$tags:Ljava/nio/ByteBuffer;
      11: aload_0
      12: getfield      #5                  // Field pos:I
      15: iconst_2
      16: invokestatic  #9                  // Method org/apache/hadoop/hbase/util/ByteBufferUtils.readAsInt:(Ljava/nio/ByteBuffer;II)I
      19: istore_1
      20: new           #10                 // class org/apache/hadoop/hbase/ByteBufferTag
      23: dup
      24: aload_0
      25: getfield      #3                  // Field val$tags:Ljava/nio/ByteBuffer;
      28: aload_0
      29: getfield      #5                  // Field pos:I
      32: iload_1
      33: iconst_2
      34: iadd
      35: invokespecial #11                 // Method org/apache/hadoop/hbase/ByteBufferTag."<init>":(Ljava/nio/ByteBuffer;II)V
      38: astore_2
      39: aload_0
      40: dup
      41: getfield      #5                  // Field pos:I
      44: iconst_2
      45: iload_1
      46: iadd
      47: iadd
      48: putfield      #5                  // Field pos:I
      51: aload_2
      52: areturn
      53: aconst_null
      54: areturn

  public void remove();
    Code:
       0: new           #13                 // class java/lang/UnsupportedOperationException
       3: dup
       4: invokespecial #14                 // Method java/lang/UnsupportedOperationException."<init>":()V
       7: athrow

  public java.lang.Object next();
    Code:
       0: aload_0
       1: invokevirtual #15                 // Method next:()Lorg/apache/hadoop/hbase/Tag;
       4: areturn
}
