Compiled from "ProcedureTestingUtility.java"
public class org.apache.hadoop.hbase.procedure2.ProcedureTestingUtility$NoopProcedure<TEnv> extends org.apache.hadoop.hbase.procedure2.Procedure<TEnv> {
  public org.apache.hadoop.hbase.procedure2.ProcedureTestingUtility$NoopProcedure();
    Code:
       0: aload_0
       1: invokespecial #1                  // Method org/apache/hadoop/hbase/procedure2/Procedure."<init>":()V
       4: return

  protected org.apache.hadoop.hbase.procedure2.Procedure<TEnv>[] execute(TEnv) throws org.apache.hadoop.hbase.procedure2.ProcedureYieldException, org.apache.hadoop.hbase.procedure2.ProcedureSuspendedException, java.lang.InterruptedException;
    Code:
       0: aconst_null
       1: areturn

  protected void rollback(TEnv) throws java.io.IOException, java.lang.InterruptedException;
    Code:
       0: return

  protected boolean abort(TEnv);
    Code:
       0: iconst_0
       1: ireturn

  protected void serializeStateData(org.apache.hadoop.hbase.procedure2.ProcedureStateSerializer) throws java.io.IOException;
    Code:
       0: return

  protected void deserializeStateData(org.apache.hadoop.hbase.procedure2.ProcedureStateSerializer) throws java.io.IOException;
    Code:
       0: return
}
