Compiled from "ProcedureStoreTracker.java"
public final class org.apache.hadoop.hbase.procedure2.store.ProcedureStoreTracker$DeleteState extends java.lang.Enum<org.apache.hadoop.hbase.procedure2.store.ProcedureStoreTracker$DeleteState> {
  public static final org.apache.hadoop.hbase.procedure2.store.ProcedureStoreTracker$DeleteState YES;

  public static final org.apache.hadoop.hbase.procedure2.store.ProcedureStoreTracker$DeleteState NO;

  public static final org.apache.hadoop.hbase.procedure2.store.ProcedureStoreTracker$DeleteState MAYBE;

  public static org.apache.hadoop.hbase.procedure2.store.ProcedureStoreTracker$DeleteState[] values();
    Code:
       0: getstatic     #1                  // Field $VALUES:[Lorg/apache/hadoop/hbase/procedure2/store/ProcedureStoreTracker$DeleteState;
       3: invokevirtual #2                  // Method "[Lorg/apache/hadoop/hbase/procedure2/store/ProcedureStoreTracker$DeleteState;".clone:()Ljava/lang/Object;
       6: checkcast     #3                  // class "[Lorg/apache/hadoop/hbase/procedure2/store/ProcedureStoreTracker$DeleteState;"
       9: areturn

  public static org.apache.hadoop.hbase.procedure2.store.ProcedureStoreTracker$DeleteState valueOf(java.lang.String);
    Code:
       0: ldc           #4                  // class org/apache/hadoop/hbase/procedure2/store/ProcedureStoreTracker$DeleteState
       2: aload_0
       3: invokestatic  #5                  // Method java/lang/Enum.valueOf:(Ljava/lang/Class;Ljava/lang/String;)Ljava/lang/Enum;
       6: checkcast     #4                  // class org/apache/hadoop/hbase/procedure2/store/ProcedureStoreTracker$DeleteState
       9: areturn

  static {};
    Code:
       0: new           #4                  // class org/apache/hadoop/hbase/procedure2/store/ProcedureStoreTracker$DeleteState
       3: dup
       4: ldc           #7                  // String YES
       6: iconst_0
       7: invokespecial #8                  // Method "<init>":(Ljava/lang/String;I)V
      10: putstatic     #9                  // Field YES:Lorg/apache/hadoop/hbase/procedure2/store/ProcedureStoreTracker$DeleteState;
      13: new           #4                  // class org/apache/hadoop/hbase/procedure2/store/ProcedureStoreTracker$DeleteState
      16: dup
      17: ldc           #10                 // String NO
      19: iconst_1
      20: invokespecial #8                  // Method "<init>":(Ljava/lang/String;I)V
      23: putstatic     #11                 // Field NO:Lorg/apache/hadoop/hbase/procedure2/store/ProcedureStoreTracker$DeleteState;
      26: new           #4                  // class org/apache/hadoop/hbase/procedure2/store/ProcedureStoreTracker$DeleteState
      29: dup
      30: ldc           #12                 // String MAYBE
      32: iconst_2
      33: invokespecial #8                  // Method "<init>":(Ljava/lang/String;I)V
      36: putstatic     #13                 // Field MAYBE:Lorg/apache/hadoop/hbase/procedure2/store/ProcedureStoreTracker$DeleteState;
      39: iconst_3
      40: anewarray     #4                  // class org/apache/hadoop/hbase/procedure2/store/ProcedureStoreTracker$DeleteState
      43: dup
      44: iconst_0
      45: getstatic     #9                  // Field YES:Lorg/apache/hadoop/hbase/procedure2/store/ProcedureStoreTracker$DeleteState;
      48: aastore
      49: dup
      50: iconst_1
      51: getstatic     #11                 // Field NO:Lorg/apache/hadoop/hbase/procedure2/store/ProcedureStoreTracker$DeleteState;
      54: aastore
      55: dup
      56: iconst_2
      57: getstatic     #13                 // Field MAYBE:Lorg/apache/hadoop/hbase/procedure2/store/ProcedureStoreTracker$DeleteState;
      60: aastore
      61: putstatic     #1                  // Field $VALUES:[Lorg/apache/hadoop/hbase/procedure2/store/ProcedureStoreTracker$DeleteState;
      64: return
}
