Compiled from "ProcessBasedLocalHBaseCluster.java"
public class org.apache.hadoop.hbase.util.ProcessBasedLocalHBaseCluster {
  public org.apache.hadoop.hbase.util.ProcessBasedLocalHBaseCluster(org.apache.hadoop.conf.Configuration, int, int);
    Code:
       0: aload_0
       1: invokespecial #6                  // Method java/lang/Object."<init>":()V
       4: aload_0
       5: new           #7                  // class java/util/ArrayList
       8: dup
       9: invokespecial #8                  // Method java/util/ArrayList."<init>":()V
      12: invokestatic  #9                  // Method java/util/Collections.synchronizedList:(Ljava/util/List;)Ljava/util/List;
      15: putfield      #10                 // Field daemonPidFiles:Ljava/util/List;
      18: aload_0
      19: new           #7                  // class java/util/ArrayList
      22: dup
      23: invokespecial #8                  // Method java/util/ArrayList."<init>":()V
      26: invokestatic  #9                  // Method java/util/Collections.synchronizedList:(Ljava/util/List;)Ljava/util/List;
      29: putfield      #3                  // Field logTailDirs:Ljava/util/List;
      32: aload_0
      33: aload_1
      34: putfield      #11                 // Field conf:Lorg/apache/hadoop/conf/Configuration;
      37: aload_0
      38: invokestatic  #12                 // Method org/apache/hadoop/hbase/util/HBaseHomePath.getHomePath:()Ljava/lang/String;
      41: putfield      #13                 // Field hbaseHome:Ljava/lang/String;
      44: aload_0
      45: iconst_1
      46: putfield      #14                 // Field numMasters:I
      49: aload_0
      50: iload_3
      51: putfield      #15                 // Field numRegionServers:I
      54: aload_0
      55: new           #16                 // class java/lang/StringBuilder
      58: dup
      59: invokespecial #17                 // Method java/lang/StringBuilder."<init>":()V
      62: aload_0
      63: getfield      #13                 // Field hbaseHome:Ljava/lang/String;
      66: invokevirtual #18                 // Method java/lang/StringBuilder.append:(Ljava/lang/String;)Ljava/lang/StringBuilder;
      69: ldc           #19                 // String /target/local_cluster
      71: invokevirtual #18                 // Method java/lang/StringBuilder.append:(Ljava/lang/String;)Ljava/lang/StringBuilder;
      74: invokevirtual #20                 // Method java/lang/StringBuilder.toString:()Ljava/lang/String;
      77: putfield      #21                 // Field workDir:Ljava/lang/String;
      80: aload_0
      81: iload_2
      82: putfield      #22                 // Field numDataNodes:I
      85: aload_0
      86: new           #16                 // class java/lang/StringBuilder
      89: dup
      90: invokespecial #17                 // Method java/lang/StringBuilder."<init>":()V
      93: aload_0
      94: getfield      #13                 // Field hbaseHome:Ljava/lang/String;
      97: invokevirtual #18                 // Method java/lang/StringBuilder.append:(Ljava/lang/String;)Ljava/lang/StringBuilder;
     100: ldc           #23                 // String /bin/hbase-daemon.sh
     102: invokevirtual #18                 // Method java/lang/StringBuilder.append:(Ljava/lang/String;)Ljava/lang/StringBuilder;
     105: invokevirtual #20                 // Method java/lang/StringBuilder.toString:()Ljava/lang/String;
     108: putfield      #24                 // Field hbaseDaemonScript:Ljava/lang/String;
     111: aload_0
     112: invokestatic  #25                 // Method org/apache/hadoop/hbase/HBaseTestingUtility.randomFreePort:()I
     115: putfield      #26                 // Field zkClientPort:I
     118: aload_0
     119: iload_3
     120: invokestatic  #27                 // Method sortedPorts:(I)Ljava/util/List;
     123: putfield      #28                 // Field rsPorts:Ljava/util/List;
     126: aload_0
     127: aload_0
     128: getfield      #14                 // Field numMasters:I
     131: invokestatic  #27                 // Method sortedPorts:(I)Ljava/util/List;
     134: putfield      #29                 // Field masterPorts:Ljava/util/List;
     137: aload_1
     138: ldc           #31                 // String hbase.zookeeper.quorum
     140: ldc           #32                 // String localhost
     142: invokevirtual #33                 // Method org/apache/hadoop/conf/Configuration.set:(Ljava/lang/String;Ljava/lang/String;)V
     145: aload_1
     146: ldc           #34                 // String hbase.zookeeper.property.clientPort
     148: aload_0
     149: getfield      #26                 // Field zkClientPort:I
     152: invokevirtual #35                 // Method org/apache/hadoop/conf/Configuration.setInt:(Ljava/lang/String;I)V
     155: return

  public void startMiniDFS() throws java.lang.Exception;
    Code:
       0: aload_0
       1: getfield      #36                 // Field testUtil:Lorg/apache/hadoop/hbase/HBaseTestingUtility;
       4: ifnonnull     22
       7: aload_0
       8: new           #37                 // class org/apache/hadoop/hbase/HBaseTestingUtility
      11: dup
      12: aload_0
      13: getfield      #11                 // Field conf:Lorg/apache/hadoop/conf/Configuration;
      16: invokespecial #38                 // Method org/apache/hadoop/hbase/HBaseTestingUtility."<init>":(Lorg/apache/hadoop/conf/Configuration;)V
      19: putfield      #36                 // Field testUtil:Lorg/apache/hadoop/hbase/HBaseTestingUtility;
      22: aload_0
      23: aload_0
      24: getfield      #36                 // Field testUtil:Lorg/apache/hadoop/hbase/HBaseTestingUtility;
      27: aload_0
      28: getfield      #22                 // Field numDataNodes:I
      31: invokevirtual #39                 // Method org/apache/hadoop/hbase/HBaseTestingUtility.startMiniDFSCluster:(I)Lorg/apache/hadoop/hdfs/MiniDFSCluster;
      34: putfield      #40                 // Field dfsCluster:Lorg/apache/hadoop/hdfs/MiniDFSCluster;
      37: return

  public void startHBase() throws java.io.IOException;
    Code:
       0: aload_0
       1: invokespecial #45                 // Method startDaemonLogTailer:()V
       4: aload_0
       5: invokespecial #46                 // Method cleanupOldState:()V
       8: getstatic     #4                  // Field LOG:Lorg/slf4j/Logger;
      11: new           #16                 // class java/lang/StringBuilder
      14: dup
      15: invokespecial #17                 // Method java/lang/StringBuilder."<init>":()V
      18: ldc           #47                 // String Starting ZooKeeper on port
      20: invokevirtual #18                 // Method java/lang/StringBuilder.append:(Ljava/lang/String;)Ljava/lang/StringBuilder;
      23: aload_0
      24: getfield      #26                 // Field zkClientPort:I
      27: invokevirtual #48                 // Method java/lang/StringBuilder.append:(I)Ljava/lang/StringBuilder;
      30: invokevirtual #20                 // Method java/lang/StringBuilder.toString:()Ljava/lang/String;
      33: invokeinterface #49,  2           // InterfaceMethod org/slf4j/Logger.info:(Ljava/lang/String;)V
      38: aload_0
      39: invokevirtual #50                 // Method startZK:()V
      42: ldc           #32                 // String localhost
      44: aload_0
      45: getfield      #26                 // Field zkClientPort:I
      48: invokestatic  #51                 // Method org/apache/hadoop/hbase/HBaseTestingUtility.waitForHostPort:(Ljava/lang/String;I)V
      51: aload_0
      52: getfield      #29                 // Field masterPorts:Ljava/util/List;
      55: invokeinterface #52,  1           // InterfaceMethod java/util/List.iterator:()Ljava/util/Iterator;
      60: astore_1
      61: aload_1
      62: invokeinterface #53,  1           // InterfaceMethod java/util/Iterator.hasNext:()Z
      67: ifeq          91
      70: aload_1
      71: invokeinterface #54,  1           // InterfaceMethod java/util/Iterator.next:()Ljava/lang/Object;
      76: checkcast     #55                 // class java/lang/Integer
      79: invokevirtual #56                 // Method java/lang/Integer.intValue:()I
      82: istore_2
      83: aload_0
      84: iload_2
      85: invokevirtual #57                 // Method startMaster:(I)V
      88: goto          61
      91: aload_0
      92: getfield      #11                 // Field conf:Lorg/apache/hadoop/conf/Configuration;
      95: invokestatic  #58                 // Method org/apache/hadoop/hbase/zookeeper/ZKUtil.waitForBaseZNode:(Lorg/apache/hadoop/conf/Configuration;)V
      98: aload_0
      99: getfield      #28                 // Field rsPorts:Ljava/util/List;
     102: invokeinterface #52,  1           // InterfaceMethod java/util/List.iterator:()Ljava/util/Iterator;
     107: astore_1
     108: aload_1
     109: invokeinterface #53,  1           // InterfaceMethod java/util/Iterator.hasNext:()Z
     114: ifeq          138
     117: aload_1
     118: invokeinterface #54,  1           // InterfaceMethod java/util/Iterator.next:()Ljava/lang/Object;
     123: checkcast     #55                 // class java/lang/Integer
     126: invokevirtual #56                 // Method java/lang/Integer.intValue:()I
     129: istore_2
     130: aload_0
     131: iload_2
     132: invokevirtual #59                 // Method startRegionServer:(I)V
     135: goto          108
     138: getstatic     #4                  // Field LOG:Lorg/slf4j/Logger;
     141: ldc           #60                 // String Waiting for HBase startup by scanning META
     143: invokeinterface #49,  2           // InterfaceMethod org/slf4j/Logger.info:(Ljava/lang/String;)V
     148: bipush        10
     150: istore_1
     151: iload_1
     152: iinc          1, -1
     155: ifle          215
     158: aload_0
     159: getfield      #36                 // Field testUtil:Lorg/apache/hadoop/hbase/HBaseTestingUtility;
     162: invokevirtual #61                 // Method org/apache/hadoop/hbase/HBaseTestingUtility.getConnection:()Lorg/apache/hadoop/hbase/client/Connection;
     165: getstatic     #62                 // Field org/apache/hadoop/hbase/TableName.META_TABLE_NAME:Lorg/apache/hadoop/hbase/TableName;
     168: invokeinterface #63,  2           // InterfaceMethod org/apache/hadoop/hbase/client/Connection.getTable:(Lorg/apache/hadoop/hbase/TableName;)Lorg/apache/hadoop/hbase/client/Table;
     173: pop
     174: goto          151
     177: astore_2
     178: getstatic     #4                  // Field LOG:Lorg/slf4j/Logger;
     181: new           #16                 // class java/lang/StringBuilder
     184: dup
     185: invokespecial #17                 // Method java/lang/StringBuilder."<init>":()V
     188: ldc           #65                 // String Waiting for HBase to startup. Retries left:
     190: invokevirtual #18                 // Method java/lang/StringBuilder.append:(Ljava/lang/String;)Ljava/lang/StringBuilder;
     193: iload_1
     194: invokevirtual #48                 // Method java/lang/StringBuilder.append:(I)Ljava/lang/StringBuilder;
     197: invokevirtual #20                 // Method java/lang/StringBuilder.toString:()Ljava/lang/String;
     200: aload_2
     201: invokeinterface #66,  3           // InterfaceMethod org/slf4j/Logger.info:(Ljava/lang/String;Ljava/lang/Throwable;)V
     206: ldc2_w        #67                 // long 1000l
     209: invokestatic  #69                 // Method org/apache/hadoop/hbase/util/Threads.sleep:(J)V
     212: goto          151
     215: getstatic     #4                  // Field LOG:Lorg/slf4j/Logger;
     218: new           #16                 // class java/lang/StringBuilder
     221: dup
     222: invokespecial #17                 // Method java/lang/StringBuilder."<init>":()V
     225: ldc           #70                 // String Process-based HBase Cluster with
     227: invokevirtual #18                 // Method java/lang/StringBuilder.append:(Ljava/lang/String;)Ljava/lang/StringBuilder;
     230: aload_0
     231: getfield      #15                 // Field numRegionServers:I
     234: invokevirtual #48                 // Method java/lang/StringBuilder.append:(I)Ljava/lang/StringBuilder;
     237: ldc           #71                 // String  region servers up and running... \n\n
     239: invokevirtual #18                 // Method java/lang/StringBuilder.append:(Ljava/lang/String;)Ljava/lang/StringBuilder;
     242: invokevirtual #20                 // Method java/lang/StringBuilder.toString:()Ljava/lang/String;
     245: invokeinterface #49,  2           // InterfaceMethod org/slf4j/Logger.info:(Ljava/lang/String;)V
     250: return
    Exception table:
       from    to  target type
         158   174   177   Class java/lang/Exception

  public void startRegionServer(int);
    Code:
       0: aload_0
       1: getstatic     #72                 // Field org/apache/hadoop/hbase/util/ProcessBasedLocalHBaseCluster$ServerType.RS:Lorg/apache/hadoop/hbase/util/ProcessBasedLocalHBaseCluster$ServerType;
       4: iload_1
       5: invokespecial #73                 // Method startServer:(Lorg/apache/hadoop/hbase/util/ProcessBasedLocalHBaseCluster$ServerType;I)V
       8: return

  public void startMaster(int);
    Code:
       0: aload_0
       1: getstatic     #74                 // Field org/apache/hadoop/hbase/util/ProcessBasedLocalHBaseCluster$ServerType.MASTER:Lorg/apache/hadoop/hbase/util/ProcessBasedLocalHBaseCluster$ServerType;
       4: iload_1
       5: invokespecial #73                 // Method startServer:(Lorg/apache/hadoop/hbase/util/ProcessBasedLocalHBaseCluster$ServerType;I)V
       8: return

  public void killRegionServer(int) throws java.io.IOException;
    Code:
       0: aload_0
       1: getstatic     #72                 // Field org/apache/hadoop/hbase/util/ProcessBasedLocalHBaseCluster$ServerType.RS:Lorg/apache/hadoop/hbase/util/ProcessBasedLocalHBaseCluster$ServerType;
       4: iload_1
       5: invokespecial #75                 // Method killServer:(Lorg/apache/hadoop/hbase/util/ProcessBasedLocalHBaseCluster$ServerType;I)V
       8: return

  public void killMaster() throws java.io.IOException;
    Code:
       0: aload_0
       1: getstatic     #74                 // Field org/apache/hadoop/hbase/util/ProcessBasedLocalHBaseCluster$ServerType.MASTER:Lorg/apache/hadoop/hbase/util/ProcessBasedLocalHBaseCluster$ServerType;
       4: iconst_0
       5: invokespecial #75                 // Method killServer:(Lorg/apache/hadoop/hbase/util/ProcessBasedLocalHBaseCluster$ServerType;I)V
       8: return

  public void startZK();
    Code:
       0: aload_0
       1: getstatic     #76                 // Field org/apache/hadoop/hbase/util/ProcessBasedLocalHBaseCluster$ServerType.ZK:Lorg/apache/hadoop/hbase/util/ProcessBasedLocalHBaseCluster$ServerType;
       4: iconst_0
       5: invokespecial #73                 // Method startServer:(Lorg/apache/hadoop/hbase/util/ProcessBasedLocalHBaseCluster$ServerType;I)V
       8: return

  public org.apache.hadoop.conf.Configuration getConf();
    Code:
       0: aload_0
       1: getfield      #11                 // Field conf:Lorg/apache/hadoop/conf/Configuration;
       4: areturn

  public void shutdown();
    Code:
       0: aload_0
       1: getfield      #40                 // Field dfsCluster:Lorg/apache/hadoop/hdfs/MiniDFSCluster;
       4: ifnull        14
       7: aload_0
       8: getfield      #40                 // Field dfsCluster:Lorg/apache/hadoop/hdfs/MiniDFSCluster;
      11: invokevirtual #201                // Method org/apache/hadoop/hdfs/MiniDFSCluster.shutdown:()V
      14: aload_0
      15: invokespecial #5                  // Method shutdownAllProcesses:()V
      18: return

  static void access$000(org.apache.hadoop.hbase.util.ProcessBasedLocalHBaseCluster);
    Code:
       0: aload_0
       1: invokespecial #5                  // Method shutdownAllProcesses:()V
       4: return

  static org.slf4j.Logger access$200();
    Code:
       0: getstatic     #4                  // Field LOG:Lorg/slf4j/Logger;
       3: areturn

  static java.util.List access$300(org.apache.hadoop.hbase.util.ProcessBasedLocalHBaseCluster);
    Code:
       0: aload_0
       1: getfield      #3                  // Field logTailDirs:Ljava/util/List;
       4: areturn

  static java.util.regex.Pattern access$400();
    Code:
       0: getstatic     #2                  // Field LOG_PATH_FORMAT_RE:Ljava/util/regex/Pattern;
       3: areturn

  static java.lang.String access$500(java.lang.String);
    Code:
       0: aload_0
       1: invokestatic  #1                  // Method processLine:(Ljava/lang/String;)Ljava/lang/String;
       4: areturn

  static {};
    Code:
       0: ldc           #183                // class org/apache/hadoop/hbase/util/ProcessBasedLocalHBaseCluster
       2: invokestatic  #211                // Method org/slf4j/LoggerFactory.getLogger:(Ljava/lang/Class;)Lorg/slf4j/Logger;
       5: putstatic     #4                  // Field LOG:Lorg/slf4j/Logger;
       8: ldc           #212                // String org\.apache\.hadoop\.hbase\.
      10: invokestatic  #213                // Method java/util/regex/Pattern.compile:(Ljava/lang/String;)Ljava/util/regex/Pattern;
      13: putstatic     #202                // Field TO_REMOVE_FROM_LOG_LINES_RE:Ljava/util/regex/Pattern;
      16: ldc           #214                // String ^.*/([A-Z]+)-(\d+)/[^/]+$
      18: invokestatic  #213                // Method java/util/regex/Pattern.compile:(Ljava/lang/String;)Ljava/util/regex/Pattern;
      21: putstatic     #2                  // Field LOG_PATH_FORMAT_RE:Ljava/util/regex/Pattern;
      24: return
}
