Compiled from "ProcedureProtos.java"
public final class org.apache.hadoop.hbase.shaded.protobuf.generated.ProcedureProtos$Procedure extends org.apache.hbase.thirdparty.com.google.protobuf.GeneratedMessageV3 implements org.apache.hadoop.hbase.shaded.protobuf.generated.ProcedureProtos$ProcedureOrBuilder {
  public static final int CLASS_NAME_FIELD_NUMBER;

  public static final int PARENT_ID_FIELD_NUMBER;

  public static final int PROC_ID_FIELD_NUMBER;

  public static final int SUBMITTED_TIME_FIELD_NUMBER;

  public static final int OWNER_FIELD_NUMBER;

  public static final int STATE_FIELD_NUMBER;

  public static final int STACK_ID_FIELD_NUMBER;

  public static final int LAST_UPDATE_FIELD_NUMBER;

  public static final int TIMEOUT_FIELD_NUMBER;

  public static final int EXCEPTION_FIELD_NUMBER;

  public static final int RESULT_FIELD_NUMBER;

  public static final int STATE_DATA_FIELD_NUMBER;

  public static final int STATE_MESSAGE_FIELD_NUMBER;

  public static final int NONCE_GROUP_FIELD_NUMBER;

  public static final int NONCE_FIELD_NUMBER;

  public static final int LOCKED_FIELD_NUMBER;

  public static final int BYPASS_FIELD_NUMBER;

  public static final org.apache.hbase.thirdparty.com.google.protobuf.Parser<org.apache.hadoop.hbase.shaded.protobuf.generated.ProcedureProtos$Procedure> PARSER;

  public final org.apache.hbase.thirdparty.com.google.protobuf.UnknownFieldSet getUnknownFields();
    Code:
       0: aload_0
       1: getfield      #2                  // Field unknownFields:Lorg/apache/hbase/thirdparty/com/google/protobuf/UnknownFieldSet;
       4: areturn

  public static final org.apache.hbase.thirdparty.com.google.protobuf.Descriptors$Descriptor getDescriptor();
    Code:
       0: invokestatic  #64                 // Method org/apache/hadoop/hbase/shaded/protobuf/generated/ProcedureProtos.access$000:()Lorg/apache/hbase/thirdparty/com/google/protobuf/Descriptors$Descriptor;
       3: areturn

  protected org.apache.hbase.thirdparty.com.google.protobuf.GeneratedMessageV3$FieldAccessorTable internalGetFieldAccessorTable();
    Code:
       0: invokestatic  #65                 // Method org/apache/hadoop/hbase/shaded/protobuf/generated/ProcedureProtos.access$100:()Lorg/apache/hbase/thirdparty/com/google/protobuf/GeneratedMessageV3$FieldAccessorTable;
       3: ldc           #66                 // class org/apache/hadoop/hbase/shaded/protobuf/generated/ProcedureProtos$Procedure
       5: ldc           #67                 // class org/apache/hadoop/hbase/shaded/protobuf/generated/ProcedureProtos$Procedure$Builder
       7: invokevirtual #68                 // Method org/apache/hbase/thirdparty/com/google/protobuf/GeneratedMessageV3$FieldAccessorTable.ensureFieldAccessorsInitialized:(Ljava/lang/Class;Ljava/lang/Class;)Lorg/apache/hbase/thirdparty/com/google/protobuf/GeneratedMessageV3$FieldAccessorTable;
      10: areturn

  public boolean hasClassName();
    Code:
       0: aload_0
       1: getfield      #4                  // Field bitField0_:I
       4: iconst_1
       5: iand
       6: iconst_1
       7: if_icmpne     14
      10: iconst_1
      11: goto          15
      14: iconst_0
      15: ireturn

  public java.lang.String getClassName();
    Code:
       0: aload_0
       1: getfield      #21                 // Field className_:Ljava/lang/Object;
       4: astore_1
       5: aload_1
       6: instanceof    #69                 // class java/lang/String
       9: ifeq          17
      12: aload_1
      13: checkcast     #69                 // class java/lang/String
      16: areturn
      17: aload_1
      18: checkcast     #70                 // class org/apache/hbase/thirdparty/com/google/protobuf/ByteString
      21: astore_2
      22: aload_2
      23: invokevirtual #71                 // Method org/apache/hbase/thirdparty/com/google/protobuf/ByteString.toStringUtf8:()Ljava/lang/String;
      26: astore_3
      27: aload_2
      28: invokevirtual #72                 // Method org/apache/hbase/thirdparty/com/google/protobuf/ByteString.isValidUtf8:()Z
      31: ifeq          39
      34: aload_0
      35: aload_3
      36: putfield      #21                 // Field className_:Ljava/lang/Object;
      39: aload_3
      40: areturn

  public org.apache.hbase.thirdparty.com.google.protobuf.ByteString getClassNameBytes();
    Code:
       0: aload_0
       1: getfield      #21                 // Field className_:Ljava/lang/Object;
       4: astore_1
       5: aload_1
       6: instanceof    #69                 // class java/lang/String
       9: ifeq          27
      12: aload_1
      13: checkcast     #69                 // class java/lang/String
      16: invokestatic  #73                 // Method org/apache/hbase/thirdparty/com/google/protobuf/ByteString.copyFromUtf8:(Ljava/lang/String;)Lorg/apache/hbase/thirdparty/com/google/protobuf/ByteString;
      19: astore_2
      20: aload_0
      21: aload_2
      22: putfield      #21                 // Field className_:Ljava/lang/Object;
      25: aload_2
      26: areturn
      27: aload_1
      28: checkcast     #70                 // class org/apache/hbase/thirdparty/com/google/protobuf/ByteString
      31: areturn

  public boolean hasParentId();
    Code:
       0: aload_0
       1: getfield      #4                  // Field bitField0_:I
       4: iconst_2
       5: iand
       6: iconst_2
       7: if_icmpne     14
      10: iconst_1
      11: goto          15
      14: iconst_0
      15: ireturn

  public long getParentId();
    Code:
       0: aload_0
       1: getfield      #20                 // Field parentId_:J
       4: lreturn

  public boolean hasProcId();
    Code:
       0: aload_0
       1: getfield      #4                  // Field bitField0_:I
       4: iconst_4
       5: iand
       6: iconst_4
       7: if_icmpne     14
      10: iconst_1
      11: goto          15
      14: iconst_0
      15: ireturn

  public long getProcId();
    Code:
       0: aload_0
       1: getfield      #19                 // Field procId_:J
       4: lreturn

  public boolean hasSubmittedTime();
    Code:
       0: aload_0
       1: getfield      #4                  // Field bitField0_:I
       4: bipush        8
       6: iand
       7: bipush        8
       9: if_icmpne     16
      12: iconst_1
      13: goto          17
      16: iconst_0
      17: ireturn

  public long getSubmittedTime();
    Code:
       0: aload_0
       1: getfield      #18                 // Field submittedTime_:J
       4: lreturn

  public boolean hasOwner();
    Code:
       0: aload_0
       1: getfield      #4                  // Field bitField0_:I
       4: bipush        16
       6: iand
       7: bipush        16
       9: if_icmpne     16
      12: iconst_1
      13: goto          17
      16: iconst_0
      17: ireturn

  public java.lang.String getOwner();
    Code:
       0: aload_0
       1: getfield      #17                 // Field owner_:Ljava/lang/Object;
       4: astore_1
       5: aload_1
       6: instanceof    #69                 // class java/lang/String
       9: ifeq          17
      12: aload_1
      13: checkcast     #69                 // class java/lang/String
      16: areturn
      17: aload_1
      18: checkcast     #70                 // class org/apache/hbase/thirdparty/com/google/protobuf/ByteString
      21: astore_2
      22: aload_2
      23: invokevirtual #71                 // Method org/apache/hbase/thirdparty/com/google/protobuf/ByteString.toStringUtf8:()Ljava/lang/String;
      26: astore_3
      27: aload_2
      28: invokevirtual #72                 // Method org/apache/hbase/thirdparty/com/google/protobuf/ByteString.isValidUtf8:()Z
      31: ifeq          39
      34: aload_0
      35: aload_3
      36: putfield      #17                 // Field owner_:Ljava/lang/Object;
      39: aload_3
      40: areturn

  public org.apache.hbase.thirdparty.com.google.protobuf.ByteString getOwnerBytes();
    Code:
       0: aload_0
       1: getfield      #17                 // Field owner_:Ljava/lang/Object;
       4: astore_1
       5: aload_1
       6: instanceof    #69                 // class java/lang/String
       9: ifeq          27
      12: aload_1
      13: checkcast     #69                 // class java/lang/String
      16: invokestatic  #73                 // Method org/apache/hbase/thirdparty/com/google/protobuf/ByteString.copyFromUtf8:(Ljava/lang/String;)Lorg/apache/hbase/thirdparty/com/google/protobuf/ByteString;
      19: astore_2
      20: aload_0
      21: aload_2
      22: putfield      #17                 // Field owner_:Ljava/lang/Object;
      25: aload_2
      26: areturn
      27: aload_1
      28: checkcast     #70                 // class org/apache/hbase/thirdparty/com/google/protobuf/ByteString
      31: areturn

  public boolean hasState();
    Code:
       0: aload_0
       1: getfield      #4                  // Field bitField0_:I
       4: bipush        32
       6: iand
       7: bipush        32
       9: if_icmpne     16
      12: iconst_1
      13: goto          17
      16: iconst_0
      17: ireturn

  public org.apache.hadoop.hbase.shaded.protobuf.generated.ProcedureProtos$ProcedureState getState();
    Code:
       0: aload_0
       1: getfield      #16                 // Field state_:I
       4: invokestatic  #38                 // Method org/apache/hadoop/hbase/shaded/protobuf/generated/ProcedureProtos$ProcedureState.valueOf:(I)Lorg/apache/hadoop/hbase/shaded/protobuf/generated/ProcedureProtos$ProcedureState;
       7: astore_1
       8: aload_1
       9: ifnonnull     18
      12: getstatic     #74                 // Field org/apache/hadoop/hbase/shaded/protobuf/generated/ProcedureProtos$ProcedureState.INITIALIZING:Lorg/apache/hadoop/hbase/shaded/protobuf/generated/ProcedureProtos$ProcedureState;
      15: goto          19
      18: aload_1
      19: areturn

  public java.util.List<java.lang.Integer> getStackIdList();
    Code:
       0: aload_0
       1: getfield      #15                 // Field stackId_:Ljava/util/List;
       4: areturn

  public int getStackIdCount();
    Code:
       0: aload_0
       1: getfield      #15                 // Field stackId_:Ljava/util/List;
       4: invokeinterface #75,  1           // InterfaceMethod java/util/List.size:()I
       9: ireturn

  public int getStackId(int);
    Code:
       0: aload_0
       1: getfield      #15                 // Field stackId_:Ljava/util/List;
       4: iload_1
       5: invokeinterface #76,  2           // InterfaceMethod java/util/List.get:(I)Ljava/lang/Object;
      10: checkcast     #77                 // class java/lang/Integer
      13: invokevirtual #78                 // Method java/lang/Integer.intValue:()I
      16: ireturn

  public boolean hasLastUpdate();
    Code:
       0: aload_0
       1: getfield      #4                  // Field bitField0_:I
       4: bipush        64
       6: iand
       7: bipush        64
       9: if_icmpne     16
      12: iconst_1
      13: goto          17
      16: iconst_0
      17: ireturn

  public long getLastUpdate();
    Code:
       0: aload_0
       1: getfield      #14                 // Field lastUpdate_:J
       4: lreturn

  public boolean hasTimeout();
    Code:
       0: aload_0
       1: getfield      #4                  // Field bitField0_:I
       4: sipush        128
       7: iand
       8: sipush        128
      11: if_icmpne     18
      14: iconst_1
      15: goto          19
      18: iconst_0
      19: ireturn

  public int getTimeout();
    Code:
       0: aload_0
       1: getfield      #13                 // Field timeout_:I
       4: ireturn

  public boolean hasException();
    Code:
       0: aload_0
       1: getfield      #4                  // Field bitField0_:I
       4: sipush        256
       7: iand
       8: sipush        256
      11: if_icmpne     18
      14: iconst_1
      15: goto          19
      18: iconst_0
      19: ireturn

  public org.apache.hadoop.hbase.shaded.protobuf.generated.ErrorHandlingProtos$ForeignExceptionMessage getException();
    Code:
       0: aload_0
       1: getfield      #12                 // Field exception_:Lorg/apache/hadoop/hbase/shaded/protobuf/generated/ErrorHandlingProtos$ForeignExceptionMessage;
       4: ifnonnull     13
       7: invokestatic  #79                 // Method org/apache/hadoop/hbase/shaded/protobuf/generated/ErrorHandlingProtos$ForeignExceptionMessage.getDefaultInstance:()Lorg/apache/hadoop/hbase/shaded/protobuf/generated/ErrorHandlingProtos$ForeignExceptionMessage;
      10: goto          17
      13: aload_0
      14: getfield      #12                 // Field exception_:Lorg/apache/hadoop/hbase/shaded/protobuf/generated/ErrorHandlingProtos$ForeignExceptionMessage;
      17: areturn

  public org.apache.hadoop.hbase.shaded.protobuf.generated.ErrorHandlingProtos$ForeignExceptionMessageOrBuilder getExceptionOrBuilder();
    Code:
       0: aload_0
       1: getfield      #12                 // Field exception_:Lorg/apache/hadoop/hbase/shaded/protobuf/generated/ErrorHandlingProtos$ForeignExceptionMessage;
       4: ifnonnull     13
       7: invokestatic  #79                 // Method org/apache/hadoop/hbase/shaded/protobuf/generated/ErrorHandlingProtos$ForeignExceptionMessage.getDefaultInstance:()Lorg/apache/hadoop/hbase/shaded/protobuf/generated/ErrorHandlingProtos$ForeignExceptionMessage;
      10: goto          17
      13: aload_0
      14: getfield      #12                 // Field exception_:Lorg/apache/hadoop/hbase/shaded/protobuf/generated/ErrorHandlingProtos$ForeignExceptionMessage;
      17: areturn

  public boolean hasResult();
    Code:
       0: aload_0
       1: getfield      #4                  // Field bitField0_:I
       4: sipush        512
       7: iand
       8: sipush        512
      11: if_icmpne     18
      14: iconst_1
      15: goto          19
      18: iconst_0
      19: ireturn

  public org.apache.hbase.thirdparty.com.google.protobuf.ByteString getResult();
    Code:
       0: aload_0
       1: getfield      #11                 // Field result_:Lorg/apache/hbase/thirdparty/com/google/protobuf/ByteString;
       4: areturn

  public boolean hasStateData();
    Code:
       0: aload_0
       1: getfield      #4                  // Field bitField0_:I
       4: sipush        1024
       7: iand
       8: sipush        1024
      11: if_icmpne     18
      14: iconst_1
      15: goto          19
      18: iconst_0
      19: ireturn

  public org.apache.hbase.thirdparty.com.google.protobuf.ByteString getStateData();
    Code:
       0: aload_0
       1: getfield      #10                 // Field stateData_:Lorg/apache/hbase/thirdparty/com/google/protobuf/ByteString;
       4: areturn

  public java.util.List<org.apache.hbase.thirdparty.com.google.protobuf.Any> getStateMessageList();
    Code:
       0: aload_0
       1: getfield      #9                  // Field stateMessage_:Ljava/util/List;
       4: areturn

  public java.util.List<? extends org.apache.hbase.thirdparty.com.google.protobuf.AnyOrBuilder> getStateMessageOrBuilderList();
    Code:
       0: aload_0
       1: getfield      #9                  // Field stateMessage_:Ljava/util/List;
       4: areturn

  public int getStateMessageCount();
    Code:
       0: aload_0
       1: getfield      #9                  // Field stateMessage_:Ljava/util/List;
       4: invokeinterface #75,  1           // InterfaceMethod java/util/List.size:()I
       9: ireturn

  public org.apache.hbase.thirdparty.com.google.protobuf.Any getStateMessage(int);
    Code:
       0: aload_0
       1: getfield      #9                  // Field stateMessage_:Ljava/util/List;
       4: iload_1
       5: invokeinterface #76,  2           // InterfaceMethod java/util/List.get:(I)Ljava/lang/Object;
      10: checkcast     #80                 // class org/apache/hbase/thirdparty/com/google/protobuf/Any
      13: areturn

  public org.apache.hbase.thirdparty.com.google.protobuf.AnyOrBuilder getStateMessageOrBuilder(int);
    Code:
       0: aload_0
       1: getfield      #9                  // Field stateMessage_:Ljava/util/List;
       4: iload_1
       5: invokeinterface #76,  2           // InterfaceMethod java/util/List.get:(I)Ljava/lang/Object;
      10: checkcast     #81                 // class org/apache/hbase/thirdparty/com/google/protobuf/AnyOrBuilder
      13: areturn

  public boolean hasNonceGroup();
    Code:
       0: aload_0
       1: getfield      #4                  // Field bitField0_:I
       4: sipush        2048
       7: iand
       8: sipush        2048
      11: if_icmpne     18
      14: iconst_1
      15: goto          19
      18: iconst_0
      19: ireturn

  public long getNonceGroup();
    Code:
       0: aload_0
       1: getfield      #8                  // Field nonceGroup_:J
       4: lreturn

  public boolean hasNonce();
    Code:
       0: aload_0
       1: getfield      #4                  // Field bitField0_:I
       4: sipush        4096
       7: iand
       8: sipush        4096
      11: if_icmpne     18
      14: iconst_1
      15: goto          19
      18: iconst_0
      19: ireturn

  public long getNonce();
    Code:
       0: aload_0
       1: getfield      #7                  // Field nonce_:J
       4: lreturn

  public boolean hasLocked();
    Code:
       0: aload_0
       1: getfield      #4                  // Field bitField0_:I
       4: sipush        8192
       7: iand
       8: sipush        8192
      11: if_icmpne     18
      14: iconst_1
      15: goto          19
      18: iconst_0
      19: ireturn

  public boolean getLocked();
    Code:
       0: aload_0
       1: getfield      #6                  // Field locked_:Z
       4: ireturn

  public boolean hasBypass();
    Code:
       0: aload_0
       1: getfield      #4                  // Field bitField0_:I
       4: sipush        16384
       7: iand
       8: sipush        16384
      11: if_icmpne     18
      14: iconst_1
      15: goto          19
      18: iconst_0
      19: ireturn

  public boolean getBypass();
    Code:
       0: aload_0
       1: getfield      #5                  // Field bypass_:Z
       4: ireturn

  public final boolean isInitialized();
    Code:
       0: aload_0
       1: getfield      #24                 // Field memoizedIsInitialized:B
       4: istore_1
       5: iload_1
       6: iconst_1
       7: if_icmpne     12
      10: iconst_1
      11: ireturn
      12: iload_1
      13: ifne          18
      16: iconst_0
      17: ireturn
      18: aload_0
      19: invokevirtual #82                 // Method hasClassName:()Z
      22: ifne          32
      25: aload_0
      26: iconst_0
      27: putfield      #24                 // Field memoizedIsInitialized:B
      30: iconst_0
      31: ireturn
      32: aload_0
      33: invokevirtual #83                 // Method hasProcId:()Z
      36: ifne          46
      39: aload_0
      40: iconst_0
      41: putfield      #24                 // Field memoizedIsInitialized:B
      44: iconst_0
      45: ireturn
      46: aload_0
      47: invokevirtual #84                 // Method hasSubmittedTime:()Z
      50: ifne          60
      53: aload_0
      54: iconst_0
      55: putfield      #24                 // Field memoizedIsInitialized:B
      58: iconst_0
      59: ireturn
      60: aload_0
      61: invokevirtual #85                 // Method hasState:()Z
      64: ifne          74
      67: aload_0
      68: iconst_0
      69: putfield      #24                 // Field memoizedIsInitialized:B
      72: iconst_0
      73: ireturn
      74: aload_0
      75: invokevirtual #86                 // Method hasLastUpdate:()Z
      78: ifne          88
      81: aload_0
      82: iconst_0
      83: putfield      #24                 // Field memoizedIsInitialized:B
      86: iconst_0
      87: ireturn
      88: aload_0
      89: iconst_1
      90: putfield      #24                 // Field memoizedIsInitialized:B
      93: iconst_1
      94: ireturn

  public void writeTo(org.apache.hbase.thirdparty.com.google.protobuf.CodedOutputStream) throws java.io.IOException;
    Code:
       0: aload_0
       1: getfield      #4                  // Field bitField0_:I
       4: iconst_1
       5: iand
       6: iconst_1
       7: if_icmpne     19
      10: aload_1
      11: iconst_1
      12: aload_0
      13: getfield      #21                 // Field className_:Ljava/lang/Object;
      16: invokestatic  #87                 // Method org/apache/hbase/thirdparty/com/google/protobuf/GeneratedMessageV3.writeString:(Lorg/apache/hbase/thirdparty/com/google/protobuf/CodedOutputStream;ILjava/lang/Object;)V
      19: aload_0
      20: getfield      #4                  // Field bitField0_:I
      23: iconst_2
      24: iand
      25: iconst_2
      26: if_icmpne     38
      29: aload_1
      30: iconst_2
      31: aload_0
      32: getfield      #20                 // Field parentId_:J
      35: invokevirtual #88                 // Method org/apache/hbase/thirdparty/com/google/protobuf/CodedOutputStream.writeUInt64:(IJ)V
      38: aload_0
      39: getfield      #4                  // Field bitField0_:I
      42: iconst_4
      43: iand
      44: iconst_4
      45: if_icmpne     57
      48: aload_1
      49: iconst_3
      50: aload_0
      51: getfield      #19                 // Field procId_:J
      54: invokevirtual #88                 // Method org/apache/hbase/thirdparty/com/google/protobuf/CodedOutputStream.writeUInt64:(IJ)V
      57: aload_0
      58: getfield      #4                  // Field bitField0_:I
      61: bipush        8
      63: iand
      64: bipush        8
      66: if_icmpne     78
      69: aload_1
      70: iconst_4
      71: aload_0
      72: getfield      #18                 // Field submittedTime_:J
      75: invokevirtual #88                 // Method org/apache/hbase/thirdparty/com/google/protobuf/CodedOutputStream.writeUInt64:(IJ)V
      78: aload_0
      79: getfield      #4                  // Field bitField0_:I
      82: bipush        16
      84: iand
      85: bipush        16
      87: if_icmpne     99
      90: aload_1
      91: iconst_5
      92: aload_0
      93: getfield      #17                 // Field owner_:Ljava/lang/Object;
      96: invokestatic  #87                 // Method org/apache/hbase/thirdparty/com/google/protobuf/GeneratedMessageV3.writeString:(Lorg/apache/hbase/thirdparty/com/google/protobuf/CodedOutputStream;ILjava/lang/Object;)V
      99: aload_0
     100: getfield      #4                  // Field bitField0_:I
     103: bipush        32
     105: iand
     106: bipush        32
     108: if_icmpne     121
     111: aload_1
     112: bipush        6
     114: aload_0
     115: getfield      #16                 // Field state_:I
     118: invokevirtual #89                 // Method org/apache/hbase/thirdparty/com/google/protobuf/CodedOutputStream.writeEnum:(II)V
     121: iconst_0
     122: istore_2
     123: iload_2
     124: aload_0
     125: getfield      #15                 // Field stackId_:Ljava/util/List;
     128: invokeinterface #75,  1           // InterfaceMethod java/util/List.size:()I
     133: if_icmpge     164
     136: aload_1
     137: bipush        7
     139: aload_0
     140: getfield      #15                 // Field stackId_:Ljava/util/List;
     143: iload_2
     144: invokeinterface #76,  2           // InterfaceMethod java/util/List.get:(I)Ljava/lang/Object;
     149: checkcast     #77                 // class java/lang/Integer
     152: invokevirtual #78                 // Method java/lang/Integer.intValue:()I
     155: invokevirtual #90                 // Method org/apache/hbase/thirdparty/com/google/protobuf/CodedOutputStream.writeUInt32:(II)V
     158: iinc          2, 1
     161: goto          123
     164: aload_0
     165: getfield      #4                  // Field bitField0_:I
     168: bipush        64
     170: iand
     171: bipush        64
     173: if_icmpne     186
     176: aload_1
     177: bipush        8
     179: aload_0
     180: getfield      #14                 // Field lastUpdate_:J
     183: invokevirtual #88                 // Method org/apache/hbase/thirdparty/com/google/protobuf/CodedOutputStream.writeUInt64:(IJ)V
     186: aload_0
     187: getfield      #4                  // Field bitField0_:I
     190: sipush        128
     193: iand
     194: sipush        128
     197: if_icmpne     210
     200: aload_1
     201: bipush        9
     203: aload_0
     204: getfield      #13                 // Field timeout_:I
     207: invokevirtual #90                 // Method org/apache/hbase/thirdparty/com/google/protobuf/CodedOutputStream.writeUInt32:(II)V
     210: aload_0
     211: getfield      #4                  // Field bitField0_:I
     214: sipush        256
     217: iand
     218: sipush        256
     221: if_icmpne     234
     224: aload_1
     225: bipush        10
     227: aload_0
     228: invokevirtual #91                 // Method getException:()Lorg/apache/hadoop/hbase/shaded/protobuf/generated/ErrorHandlingProtos$ForeignExceptionMessage;
     231: invokevirtual #92                 // Method org/apache/hbase/thirdparty/com/google/protobuf/CodedOutputStream.writeMessage:(ILorg/apache/hbase/thirdparty/com/google/protobuf/MessageLite;)V
     234: aload_0
     235: getfield      #4                  // Field bitField0_:I
     238: sipush        512
     241: iand
     242: sipush        512
     245: if_icmpne     258
     248: aload_1
     249: bipush        11
     251: aload_0
     252: getfield      #11                 // Field result_:Lorg/apache/hbase/thirdparty/com/google/protobuf/ByteString;
     255: invokevirtual #93                 // Method org/apache/hbase/thirdparty/com/google/protobuf/CodedOutputStream.writeBytes:(ILorg/apache/hbase/thirdparty/com/google/protobuf/ByteString;)V
     258: aload_0
     259: getfield      #4                  // Field bitField0_:I
     262: sipush        1024
     265: iand
     266: sipush        1024
     269: if_icmpne     282
     272: aload_1
     273: bipush        12
     275: aload_0
     276: getfield      #10                 // Field stateData_:Lorg/apache/hbase/thirdparty/com/google/protobuf/ByteString;
     279: invokevirtual #93                 // Method org/apache/hbase/thirdparty/com/google/protobuf/CodedOutputStream.writeBytes:(ILorg/apache/hbase/thirdparty/com/google/protobuf/ByteString;)V
     282: aload_0
     283: getfield      #4                  // Field bitField0_:I
     286: sipush        2048
     289: iand
     290: sipush        2048
     293: if_icmpne     306
     296: aload_1
     297: bipush        13
     299: aload_0
     300: getfield      #8                  // Field nonceGroup_:J
     303: invokevirtual #88                 // Method org/apache/hbase/thirdparty/com/google/protobuf/CodedOutputStream.writeUInt64:(IJ)V
     306: aload_0
     307: getfield      #4                  // Field bitField0_:I
     310: sipush        4096
     313: iand
     314: sipush        4096
     317: if_icmpne     330
     320: aload_1
     321: bipush        14
     323: aload_0
     324: getfield      #7                  // Field nonce_:J
     327: invokevirtual #88                 // Method org/apache/hbase/thirdparty/com/google/protobuf/CodedOutputStream.writeUInt64:(IJ)V
     330: iconst_0
     331: istore_2
     332: iload_2
     333: aload_0
     334: getfield      #9                  // Field stateMessage_:Ljava/util/List;
     337: invokeinterface #75,  1           // InterfaceMethod java/util/List.size:()I
     342: if_icmpge     370
     345: aload_1
     346: bipush        15
     348: aload_0
     349: getfield      #9                  // Field stateMessage_:Ljava/util/List;
     352: iload_2
     353: invokeinterface #76,  2           // InterfaceMethod java/util/List.get:(I)Ljava/lang/Object;
     358: checkcast     #94                 // class org/apache/hbase/thirdparty/com/google/protobuf/MessageLite
     361: invokevirtual #92                 // Method org/apache/hbase/thirdparty/com/google/protobuf/CodedOutputStream.writeMessage:(ILorg/apache/hbase/thirdparty/com/google/protobuf/MessageLite;)V
     364: iinc          2, 1
     367: goto          332
     370: aload_0
     371: getfield      #4                  // Field bitField0_:I
     374: sipush        8192
     377: iand
     378: sipush        8192
     381: if_icmpne     394
     384: aload_1
     385: bipush        16
     387: aload_0
     388: getfield      #6                  // Field locked_:Z
     391: invokevirtual #95                 // Method org/apache/hbase/thirdparty/com/google/protobuf/CodedOutputStream.writeBool:(IZ)V
     394: aload_0
     395: getfield      #4                  // Field bitField0_:I
     398: sipush        16384
     401: iand
     402: sipush        16384
     405: if_icmpne     418
     408: aload_1
     409: bipush        17
     411: aload_0
     412: getfield      #5                  // Field bypass_:Z
     415: invokevirtual #95                 // Method org/apache/hbase/thirdparty/com/google/protobuf/CodedOutputStream.writeBool:(IZ)V
     418: aload_0
     419: getfield      #2                  // Field unknownFields:Lorg/apache/hbase/thirdparty/com/google/protobuf/UnknownFieldSet;
     422: aload_1
     423: invokevirtual #96                 // Method org/apache/hbase/thirdparty/com/google/protobuf/UnknownFieldSet.writeTo:(Lorg/apache/hbase/thirdparty/com/google/protobuf/CodedOutputStream;)V
     426: return

  public int getSerializedSize();
    Code:
       0: aload_0
       1: getfield      #97                 // Field memoizedSize:I
       4: istore_1
       5: iload_1
       6: iconst_m1
       7: if_icmpeq     12
      10: iload_1
      11: ireturn
      12: iconst_0
      13: istore_1
      14: aload_0
      15: getfield      #4                  // Field bitField0_:I
      18: iconst_1
      19: iand
      20: iconst_1
      21: if_icmpne     35
      24: iload_1
      25: iconst_1
      26: aload_0
      27: getfield      #21                 // Field className_:Ljava/lang/Object;
      30: invokestatic  #98                 // Method org/apache/hbase/thirdparty/com/google/protobuf/GeneratedMessageV3.computeStringSize:(ILjava/lang/Object;)I
      33: iadd
      34: istore_1
      35: aload_0
      36: getfield      #4                  // Field bitField0_:I
      39: iconst_2
      40: iand
      41: iconst_2
      42: if_icmpne     56
      45: iload_1
      46: iconst_2
      47: aload_0
      48: getfield      #20                 // Field parentId_:J
      51: invokestatic  #99                 // Method org/apache/hbase/thirdparty/com/google/protobuf/CodedOutputStream.computeUInt64Size:(IJ)I
      54: iadd
      55: istore_1
      56: aload_0
      57: getfield      #4                  // Field bitField0_:I
      60: iconst_4
      61: iand
      62: iconst_4
      63: if_icmpne     77
      66: iload_1
      67: iconst_3
      68: aload_0
      69: getfield      #19                 // Field procId_:J
      72: invokestatic  #99                 // Method org/apache/hbase/thirdparty/com/google/protobuf/CodedOutputStream.computeUInt64Size:(IJ)I
      75: iadd
      76: istore_1
      77: aload_0
      78: getfield      #4                  // Field bitField0_:I
      81: bipush        8
      83: iand
      84: bipush        8
      86: if_icmpne     100
      89: iload_1
      90: iconst_4
      91: aload_0
      92: getfield      #18                 // Field submittedTime_:J
      95: invokestatic  #99                 // Method org/apache/hbase/thirdparty/com/google/protobuf/CodedOutputStream.computeUInt64Size:(IJ)I
      98: iadd
      99: istore_1
     100: aload_0
     101: getfield      #4                  // Field bitField0_:I
     104: bipush        16
     106: iand
     107: bipush        16
     109: if_icmpne     123
     112: iload_1
     113: iconst_5
     114: aload_0
     115: getfield      #17                 // Field owner_:Ljava/lang/Object;
     118: invokestatic  #98                 // Method org/apache/hbase/thirdparty/com/google/protobuf/GeneratedMessageV3.computeStringSize:(ILjava/lang/Object;)I
     121: iadd
     122: istore_1
     123: aload_0
     124: getfield      #4                  // Field bitField0_:I
     127: bipush        32
     129: iand
     130: bipush        32
     132: if_icmpne     147
     135: iload_1
     136: bipush        6
     138: aload_0
     139: getfield      #16                 // Field state_:I
     142: invokestatic  #100                // Method org/apache/hbase/thirdparty/com/google/protobuf/CodedOutputStream.computeEnumSize:(II)I
     145: iadd
     146: istore_1
     147: iconst_0
     148: istore_2
     149: iconst_0
     150: istore_3
     151: iload_3
     152: aload_0
     153: getfield      #15                 // Field stackId_:Ljava/util/List;
     156: invokeinterface #75,  1           // InterfaceMethod java/util/List.size:()I
     161: if_icmpge     192
     164: iload_2
     165: aload_0
     166: getfield      #15                 // Field stackId_:Ljava/util/List;
     169: iload_3
     170: invokeinterface #76,  2           // InterfaceMethod java/util/List.get:(I)Ljava/lang/Object;
     175: checkcast     #77                 // class java/lang/Integer
     178: invokevirtual #78                 // Method java/lang/Integer.intValue:()I
     181: invokestatic  #101                // Method org/apache/hbase/thirdparty/com/google/protobuf/CodedOutputStream.computeUInt32SizeNoTag:(I)I
     184: iadd
     185: istore_2
     186: iinc          3, 1
     189: goto          151
     192: iload_1
     193: iload_2
     194: iadd
     195: istore_1
     196: iload_1
     197: iconst_1
     198: aload_0
     199: invokevirtual #102                // Method getStackIdList:()Ljava/util/List;
     202: invokeinterface #75,  1           // InterfaceMethod java/util/List.size:()I
     207: imul
     208: iadd
     209: istore_1
     210: aload_0
     211: getfield      #4                  // Field bitField0_:I
     214: bipush        64
     216: iand
     217: bipush        64
     219: if_icmpne     234
     222: iload_1
     223: bipush        8
     225: aload_0
     226: getfield      #14                 // Field lastUpdate_:J
     229: invokestatic  #99                 // Method org/apache/hbase/thirdparty/com/google/protobuf/CodedOutputStream.computeUInt64Size:(IJ)I
     232: iadd
     233: istore_1
     234: aload_0
     235: getfield      #4                  // Field bitField0_:I
     238: sipush        128
     241: iand
     242: sipush        128
     245: if_icmpne     260
     248: iload_1
     249: bipush        9
     251: aload_0
     252: getfield      #13                 // Field timeout_:I
     255: invokestatic  #103                // Method org/apache/hbase/thirdparty/com/google/protobuf/CodedOutputStream.computeUInt32Size:(II)I
     258: iadd
     259: istore_1
     260: aload_0
     261: getfield      #4                  // Field bitField0_:I
     264: sipush        256
     267: iand
     268: sipush        256
     271: if_icmpne     286
     274: iload_1
     275: bipush        10
     277: aload_0
     278: invokevirtual #91                 // Method getException:()Lorg/apache/hadoop/hbase/shaded/protobuf/generated/ErrorHandlingProtos$ForeignExceptionMessage;
     281: invokestatic  #104                // Method org/apache/hbase/thirdparty/com/google/protobuf/CodedOutputStream.computeMessageSize:(ILorg/apache/hbase/thirdparty/com/google/protobuf/MessageLite;)I
     284: iadd
     285: istore_1
     286: aload_0
     287: getfield      #4                  // Field bitField0_:I
     290: sipush        512
     293: iand
     294: sipush        512
     297: if_icmpne     312
     300: iload_1
     301: bipush        11
     303: aload_0
     304: getfield      #11                 // Field result_:Lorg/apache/hbase/thirdparty/com/google/protobuf/ByteString;
     307: invokestatic  #105                // Method org/apache/hbase/thirdparty/com/google/protobuf/CodedOutputStream.computeBytesSize:(ILorg/apache/hbase/thirdparty/com/google/protobuf/ByteString;)I
     310: iadd
     311: istore_1
     312: aload_0
     313: getfield      #4                  // Field bitField0_:I
     316: sipush        1024
     319: iand
     320: sipush        1024
     323: if_icmpne     338
     326: iload_1
     327: bipush        12
     329: aload_0
     330: getfield      #10                 // Field stateData_:Lorg/apache/hbase/thirdparty/com/google/protobuf/ByteString;
     333: invokestatic  #105                // Method org/apache/hbase/thirdparty/com/google/protobuf/CodedOutputStream.computeBytesSize:(ILorg/apache/hbase/thirdparty/com/google/protobuf/ByteString;)I
     336: iadd
     337: istore_1
     338: aload_0
     339: getfield      #4                  // Field bitField0_:I
     342: sipush        2048
     345: iand
     346: sipush        2048
     349: if_icmpne     364
     352: iload_1
     353: bipush        13
     355: aload_0
     356: getfield      #8                  // Field nonceGroup_:J
     359: invokestatic  #99                 // Method org/apache/hbase/thirdparty/com/google/protobuf/CodedOutputStream.computeUInt64Size:(IJ)I
     362: iadd
     363: istore_1
     364: aload_0
     365: getfield      #4                  // Field bitField0_:I
     368: sipush        4096
     371: iand
     372: sipush        4096
     375: if_icmpne     390
     378: iload_1
     379: bipush        14
     381: aload_0
     382: getfield      #7                  // Field nonce_:J
     385: invokestatic  #99                 // Method org/apache/hbase/thirdparty/com/google/protobuf/CodedOutputStream.computeUInt64Size:(IJ)I
     388: iadd
     389: istore_1
     390: iconst_0
     391: istore_2
     392: iload_2
     393: aload_0
     394: getfield      #9                  // Field stateMessage_:Ljava/util/List;
     397: invokeinterface #75,  1           // InterfaceMethod java/util/List.size:()I
     402: if_icmpge     432
     405: iload_1
     406: bipush        15
     408: aload_0
     409: getfield      #9                  // Field stateMessage_:Ljava/util/List;
     412: iload_2
     413: invokeinterface #76,  2           // InterfaceMethod java/util/List.get:(I)Ljava/lang/Object;
     418: checkcast     #94                 // class org/apache/hbase/thirdparty/com/google/protobuf/MessageLite
     421: invokestatic  #104                // Method org/apache/hbase/thirdparty/com/google/protobuf/CodedOutputStream.computeMessageSize:(ILorg/apache/hbase/thirdparty/com/google/protobuf/MessageLite;)I
     424: iadd
     425: istore_1
     426: iinc          2, 1
     429: goto          392
     432: aload_0
     433: getfield      #4                  // Field bitField0_:I
     436: sipush        8192
     439: iand
     440: sipush        8192
     443: if_icmpne     458
     446: iload_1
     447: bipush        16
     449: aload_0
     450: getfield      #6                  // Field locked_:Z
     453: invokestatic  #106                // Method org/apache/hbase/thirdparty/com/google/protobuf/CodedOutputStream.computeBoolSize:(IZ)I
     456: iadd
     457: istore_1
     458: aload_0
     459: getfield      #4                  // Field bitField0_:I
     462: sipush        16384
     465: iand
     466: sipush        16384
     469: if_icmpne     484
     472: iload_1
     473: bipush        17
     475: aload_0
     476: getfield      #5                  // Field bypass_:Z
     479: invokestatic  #106                // Method org/apache/hbase/thirdparty/com/google/protobuf/CodedOutputStream.computeBoolSize:(IZ)I
     482: iadd
     483: istore_1
     484: iload_1
     485: aload_0
     486: getfield      #2                  // Field unknownFields:Lorg/apache/hbase/thirdparty/com/google/protobuf/UnknownFieldSet;
     489: invokevirtual #107                // Method org/apache/hbase/thirdparty/com/google/protobuf/UnknownFieldSet.getSerializedSize:()I
     492: iadd
     493: istore_1
     494: aload_0
     495: iload_1
     496: putfield      #97                 // Field memoizedSize:I
     499: iload_1
     500: ireturn

  public boolean equals(java.lang.Object);
    Code:
       0: aload_1
       1: aload_0
       2: if_acmpne     7
       5: iconst_1
       6: ireturn
       7: aload_1
       8: instanceof    #66                 // class org/apache/hadoop/hbase/shaded/protobuf/generated/ProcedureProtos$Procedure
      11: ifne          20
      14: aload_0
      15: aload_1
      16: invokespecial #108                // Method org/apache/hbase/thirdparty/com/google/protobuf/GeneratedMessageV3.equals:(Ljava/lang/Object;)Z
      19: ireturn
      20: aload_1
      21: checkcast     #66                 // class org/apache/hadoop/hbase/shaded/protobuf/generated/ProcedureProtos$Procedure
      24: astore_2
      25: iconst_1
      26: istore_3
      27: iload_3
      28: ifeq          46
      31: aload_0
      32: invokevirtual #82                 // Method hasClassName:()Z
      35: aload_2
      36: invokevirtual #82                 // Method hasClassName:()Z
      39: if_icmpne     46
      42: iconst_1
      43: goto          47
      46: iconst_0
      47: istore_3
      48: aload_0
      49: invokevirtual #82                 // Method hasClassName:()Z
      52: ifeq          79
      55: iload_3
      56: ifeq          77
      59: aload_0
      60: invokevirtual #109                // Method getClassName:()Ljava/lang/String;
      63: aload_2
      64: invokevirtual #109                // Method getClassName:()Ljava/lang/String;
      67: invokevirtual #110                // Method java/lang/String.equals:(Ljava/lang/Object;)Z
      70: ifeq          77
      73: iconst_1
      74: goto          78
      77: iconst_0
      78: istore_3
      79: iload_3
      80: ifeq          98
      83: aload_0
      84: invokevirtual #111                // Method hasParentId:()Z
      87: aload_2
      88: invokevirtual #111                // Method hasParentId:()Z
      91: if_icmpne     98
      94: iconst_1
      95: goto          99
      98: iconst_0
      99: istore_3
     100: aload_0
     101: invokevirtual #111                // Method hasParentId:()Z
     104: ifeq          129
     107: iload_3
     108: ifeq          127
     111: aload_0
     112: invokevirtual #112                // Method getParentId:()J
     115: aload_2
     116: invokevirtual #112                // Method getParentId:()J
     119: lcmp
     120: ifne          127
     123: iconst_1
     124: goto          128
     127: iconst_0
     128: istore_3
     129: iload_3
     130: ifeq          148
     133: aload_0
     134: invokevirtual #83                 // Method hasProcId:()Z
     137: aload_2
     138: invokevirtual #83                 // Method hasProcId:()Z
     141: if_icmpne     148
     144: iconst_1
     145: goto          149
     148: iconst_0
     149: istore_3
     150: aload_0
     151: invokevirtual #83                 // Method hasProcId:()Z
     154: ifeq          179
     157: iload_3
     158: ifeq          177
     161: aload_0
     162: invokevirtual #113                // Method getProcId:()J
     165: aload_2
     166: invokevirtual #113                // Method getProcId:()J
     169: lcmp
     170: ifne          177
     173: iconst_1
     174: goto          178
     177: iconst_0
     178: istore_3
     179: iload_3
     180: ifeq          198
     183: aload_0
     184: invokevirtual #84                 // Method hasSubmittedTime:()Z
     187: aload_2
     188: invokevirtual #84                 // Method hasSubmittedTime:()Z
     191: if_icmpne     198
     194: iconst_1
     195: goto          199
     198: iconst_0
     199: istore_3
     200: aload_0
     201: invokevirtual #84                 // Method hasSubmittedTime:()Z
     204: ifeq          229
     207: iload_3
     208: ifeq          227
     211: aload_0
     212: invokevirtual #114                // Method getSubmittedTime:()J
     215: aload_2
     216: invokevirtual #114                // Method getSubmittedTime:()J
     219: lcmp
     220: ifne          227
     223: iconst_1
     224: goto          228
     227: iconst_0
     228: istore_3
     229: iload_3
     230: ifeq          248
     233: aload_0
     234: invokevirtual #115                // Method hasOwner:()Z
     237: aload_2
     238: invokevirtual #115                // Method hasOwner:()Z
     241: if_icmpne     248
     244: iconst_1
     245: goto          249
     248: iconst_0
     249: istore_3
     250: aload_0
     251: invokevirtual #115                // Method hasOwner:()Z
     254: ifeq          281
     257: iload_3
     258: ifeq          279
     261: aload_0
     262: invokevirtual #116                // Method getOwner:()Ljava/lang/String;
     265: aload_2
     266: invokevirtual #116                // Method getOwner:()Ljava/lang/String;
     269: invokevirtual #110                // Method java/lang/String.equals:(Ljava/lang/Object;)Z
     272: ifeq          279
     275: iconst_1
     276: goto          280
     279: iconst_0
     280: istore_3
     281: iload_3
     282: ifeq          300
     285: aload_0
     286: invokevirtual #85                 // Method hasState:()Z
     289: aload_2
     290: invokevirtual #85                 // Method hasState:()Z
     293: if_icmpne     300
     296: iconst_1
     297: goto          301
     300: iconst_0
     301: istore_3
     302: aload_0
     303: invokevirtual #85                 // Method hasState:()Z
     306: ifeq          330
     309: iload_3
     310: ifeq          328
     313: aload_0
     314: getfield      #16                 // Field state_:I
     317: aload_2
     318: getfield      #16                 // Field state_:I
     321: if_icmpne     328
     324: iconst_1
     325: goto          329
     328: iconst_0
     329: istore_3
     330: iload_3
     331: ifeq          354
     334: aload_0
     335: invokevirtual #102                // Method getStackIdList:()Ljava/util/List;
     338: aload_2
     339: invokevirtual #102                // Method getStackIdList:()Ljava/util/List;
     342: invokeinterface #117,  2          // InterfaceMethod java/util/List.equals:(Ljava/lang/Object;)Z
     347: ifeq          354
     350: iconst_1
     351: goto          355
     354: iconst_0
     355: istore_3
     356: iload_3
     357: ifeq          375
     360: aload_0
     361: invokevirtual #86                 // Method hasLastUpdate:()Z
     364: aload_2
     365: invokevirtual #86                 // Method hasLastUpdate:()Z
     368: if_icmpne     375
     371: iconst_1
     372: goto          376
     375: iconst_0
     376: istore_3
     377: aload_0
     378: invokevirtual #86                 // Method hasLastUpdate:()Z
     381: ifeq          406
     384: iload_3
     385: ifeq          404
     388: aload_0
     389: invokevirtual #118                // Method getLastUpdate:()J
     392: aload_2
     393: invokevirtual #118                // Method getLastUpdate:()J
     396: lcmp
     397: ifne          404
     400: iconst_1
     401: goto          405
     404: iconst_0
     405: istore_3
     406: iload_3
     407: ifeq          425
     410: aload_0
     411: invokevirtual #119                // Method hasTimeout:()Z
     414: aload_2
     415: invokevirtual #119                // Method hasTimeout:()Z
     418: if_icmpne     425
     421: iconst_1
     422: goto          426
     425: iconst_0
     426: istore_3
     427: aload_0
     428: invokevirtual #119                // Method hasTimeout:()Z
     431: ifeq          455
     434: iload_3
     435: ifeq          453
     438: aload_0
     439: invokevirtual #120                // Method getTimeout:()I
     442: aload_2
     443: invokevirtual #120                // Method getTimeout:()I
     446: if_icmpne     453
     449: iconst_1
     450: goto          454
     453: iconst_0
     454: istore_3
     455: iload_3
     456: ifeq          474
     459: aload_0
     460: invokevirtual #121                // Method hasException:()Z
     463: aload_2
     464: invokevirtual #121                // Method hasException:()Z
     467: if_icmpne     474
     470: iconst_1
     471: goto          475
     474: iconst_0
     475: istore_3
     476: aload_0
     477: invokevirtual #121                // Method hasException:()Z
     480: ifeq          507
     483: iload_3
     484: ifeq          505
     487: aload_0
     488: invokevirtual #91                 // Method getException:()Lorg/apache/hadoop/hbase/shaded/protobuf/generated/ErrorHandlingProtos$ForeignExceptionMessage;
     491: aload_2
     492: invokevirtual #91                 // Method getException:()Lorg/apache/hadoop/hbase/shaded/protobuf/generated/ErrorHandlingProtos$ForeignExceptionMessage;
     495: invokevirtual #122                // Method org/apache/hadoop/hbase/shaded/protobuf/generated/ErrorHandlingProtos$ForeignExceptionMessage.equals:(Ljava/lang/Object;)Z
     498: ifeq          505
     501: iconst_1
     502: goto          506
     505: iconst_0
     506: istore_3
     507: iload_3
     508: ifeq          526
     511: aload_0
     512: invokevirtual #123                // Method hasResult:()Z
     515: aload_2
     516: invokevirtual #123                // Method hasResult:()Z
     519: if_icmpne     526
     522: iconst_1
     523: goto          527
     526: iconst_0
     527: istore_3
     528: aload_0
     529: invokevirtual #123                // Method hasResult:()Z
     532: ifeq          559
     535: iload_3
     536: ifeq          557
     539: aload_0
     540: invokevirtual #124                // Method getResult:()Lorg/apache/hbase/thirdparty/com/google/protobuf/ByteString;
     543: aload_2
     544: invokevirtual #124                // Method getResult:()Lorg/apache/hbase/thirdparty/com/google/protobuf/ByteString;
     547: invokevirtual #125                // Method org/apache/hbase/thirdparty/com/google/protobuf/ByteString.equals:(Ljava/lang/Object;)Z
     550: ifeq          557
     553: iconst_1
     554: goto          558
     557: iconst_0
     558: istore_3
     559: iload_3
     560: ifeq          578
     563: aload_0
     564: invokevirtual #126                // Method hasStateData:()Z
     567: aload_2
     568: invokevirtual #126                // Method hasStateData:()Z
     571: if_icmpne     578
     574: iconst_1
     575: goto          579
     578: iconst_0
     579: istore_3
     580: aload_0
     581: invokevirtual #126                // Method hasStateData:()Z
     584: ifeq          611
     587: iload_3
     588: ifeq          609
     591: aload_0
     592: invokevirtual #127                // Method getStateData:()Lorg/apache/hbase/thirdparty/com/google/protobuf/ByteString;
     595: aload_2
     596: invokevirtual #127                // Method getStateData:()Lorg/apache/hbase/thirdparty/com/google/protobuf/ByteString;
     599: invokevirtual #125                // Method org/apache/hbase/thirdparty/com/google/protobuf/ByteString.equals:(Ljava/lang/Object;)Z
     602: ifeq          609
     605: iconst_1
     606: goto          610
     609: iconst_0
     610: istore_3
     611: iload_3
     612: ifeq          635
     615: aload_0
     616: invokevirtual #128                // Method getStateMessageList:()Ljava/util/List;
     619: aload_2
     620: invokevirtual #128                // Method getStateMessageList:()Ljava/util/List;
     623: invokeinterface #117,  2          // InterfaceMethod java/util/List.equals:(Ljava/lang/Object;)Z
     628: ifeq          635
     631: iconst_1
     632: goto          636
     635: iconst_0
     636: istore_3
     637: iload_3
     638: ifeq          656
     641: aload_0
     642: invokevirtual #129                // Method hasNonceGroup:()Z
     645: aload_2
     646: invokevirtual #129                // Method hasNonceGroup:()Z
     649: if_icmpne     656
     652: iconst_1
     653: goto          657
     656: iconst_0
     657: istore_3
     658: aload_0
     659: invokevirtual #129                // Method hasNonceGroup:()Z
     662: ifeq          687
     665: iload_3
     666: ifeq          685
     669: aload_0
     670: invokevirtual #130                // Method getNonceGroup:()J
     673: aload_2
     674: invokevirtual #130                // Method getNonceGroup:()J
     677: lcmp
     678: ifne          685
     681: iconst_1
     682: goto          686
     685: iconst_0
     686: istore_3
     687: iload_3
     688: ifeq          706
     691: aload_0
     692: invokevirtual #131                // Method hasNonce:()Z
     695: aload_2
     696: invokevirtual #131                // Method hasNonce:()Z
     699: if_icmpne     706
     702: iconst_1
     703: goto          707
     706: iconst_0
     707: istore_3
     708: aload_0
     709: invokevirtual #131                // Method hasNonce:()Z
     712: ifeq          737
     715: iload_3
     716: ifeq          735
     719: aload_0
     720: invokevirtual #132                // Method getNonce:()J
     723: aload_2
     724: invokevirtual #132                // Method getNonce:()J
     727: lcmp
     728: ifne          735
     731: iconst_1
     732: goto          736
     735: iconst_0
     736: istore_3
     737: iload_3
     738: ifeq          756
     741: aload_0
     742: invokevirtual #133                // Method hasLocked:()Z
     745: aload_2
     746: invokevirtual #133                // Method hasLocked:()Z
     749: if_icmpne     756
     752: iconst_1
     753: goto          757
     756: iconst_0
     757: istore_3
     758: aload_0
     759: invokevirtual #133                // Method hasLocked:()Z
     762: ifeq          786
     765: iload_3
     766: ifeq          784
     769: aload_0
     770: invokevirtual #134                // Method getLocked:()Z
     773: aload_2
     774: invokevirtual #134                // Method getLocked:()Z
     777: if_icmpne     784
     780: iconst_1
     781: goto          785
     784: iconst_0
     785: istore_3
     786: iload_3
     787: ifeq          805
     790: aload_0
     791: invokevirtual #135                // Method hasBypass:()Z
     794: aload_2
     795: invokevirtual #135                // Method hasBypass:()Z
     798: if_icmpne     805
     801: iconst_1
     802: goto          806
     805: iconst_0
     806: istore_3
     807: aload_0
     808: invokevirtual #135                // Method hasBypass:()Z
     811: ifeq          835
     814: iload_3
     815: ifeq          833
     818: aload_0
     819: invokevirtual #136                // Method getBypass:()Z
     822: aload_2
     823: invokevirtual #136                // Method getBypass:()Z
     826: if_icmpne     833
     829: iconst_1
     830: goto          834
     833: iconst_0
     834: istore_3
     835: iload_3
     836: ifeq          857
     839: aload_0
     840: getfield      #2                  // Field unknownFields:Lorg/apache/hbase/thirdparty/com/google/protobuf/UnknownFieldSet;
     843: aload_2
     844: getfield      #2                  // Field unknownFields:Lorg/apache/hbase/thirdparty/com/google/protobuf/UnknownFieldSet;
     847: invokevirtual #137                // Method org/apache/hbase/thirdparty/com/google/protobuf/UnknownFieldSet.equals:(Ljava/lang/Object;)Z
     850: ifeq          857
     853: iconst_1
     854: goto          858
     857: iconst_0
     858: istore_3
     859: iload_3
     860: ireturn

  public int hashCode();
    Code:
       0: aload_0
       1: getfield      #138                // Field memoizedHashCode:I
       4: ifeq          12
       7: aload_0
       8: getfield      #138                // Field memoizedHashCode:I
      11: ireturn
      12: bipush        41
      14: istore_1
      15: bipush        19
      17: iload_1
      18: imul
      19: invokestatic  #139                // Method getDescriptor:()Lorg/apache/hbase/thirdparty/com/google/protobuf/Descriptors$Descriptor;
      22: invokevirtual #140                // Method java/lang/Object.hashCode:()I
      25: iadd
      26: istore_1
      27: aload_0
      28: invokevirtual #82                 // Method hasClassName:()Z
      31: ifeq          54
      34: bipush        37
      36: iload_1
      37: imul
      38: iconst_1
      39: iadd
      40: istore_1
      41: bipush        53
      43: iload_1
      44: imul
      45: aload_0
      46: invokevirtual #109                // Method getClassName:()Ljava/lang/String;
      49: invokevirtual #141                // Method java/lang/String.hashCode:()I
      52: iadd
      53: istore_1
      54: aload_0
      55: invokevirtual #111                // Method hasParentId:()Z
      58: ifeq          81
      61: bipush        37
      63: iload_1
      64: imul
      65: iconst_2
      66: iadd
      67: istore_1
      68: bipush        53
      70: iload_1
      71: imul
      72: aload_0
      73: invokevirtual #112                // Method getParentId:()J
      76: invokestatic  #142                // Method org/apache/hbase/thirdparty/com/google/protobuf/Internal.hashLong:(J)I
      79: iadd
      80: istore_1
      81: aload_0
      82: invokevirtual #83                 // Method hasProcId:()Z
      85: ifeq          108
      88: bipush        37
      90: iload_1
      91: imul
      92: iconst_3
      93: iadd
      94: istore_1
      95: bipush        53
      97: iload_1
      98: imul
      99: aload_0
     100: invokevirtual #113                // Method getProcId:()J
     103: invokestatic  #142                // Method org/apache/hbase/thirdparty/com/google/protobuf/Internal.hashLong:(J)I
     106: iadd
     107: istore_1
     108: aload_0
     109: invokevirtual #84                 // Method hasSubmittedTime:()Z
     112: ifeq          135
     115: bipush        37
     117: iload_1
     118: imul
     119: iconst_4
     120: iadd
     121: istore_1
     122: bipush        53
     124: iload_1
     125: imul
     126: aload_0
     127: invokevirtual #114                // Method getSubmittedTime:()J
     130: invokestatic  #142                // Method org/apache/hbase/thirdparty/com/google/protobuf/Internal.hashLong:(J)I
     133: iadd
     134: istore_1
     135: aload_0
     136: invokevirtual #115                // Method hasOwner:()Z
     139: ifeq          162
     142: bipush        37
     144: iload_1
     145: imul
     146: iconst_5
     147: iadd
     148: istore_1
     149: bipush        53
     151: iload_1
     152: imul
     153: aload_0
     154: invokevirtual #116                // Method getOwner:()Ljava/lang/String;
     157: invokevirtual #141                // Method java/lang/String.hashCode:()I
     160: iadd
     161: istore_1
     162: aload_0
     163: invokevirtual #85                 // Method hasState:()Z
     166: ifeq          187
     169: bipush        37
     171: iload_1
     172: imul
     173: bipush        6
     175: iadd
     176: istore_1
     177: bipush        53
     179: iload_1
     180: imul
     181: aload_0
     182: getfield      #16                 // Field state_:I
     185: iadd
     186: istore_1
     187: aload_0
     188: invokevirtual #143                // Method getStackIdCount:()I
     191: ifle          217
     194: bipush        37
     196: iload_1
     197: imul
     198: bipush        7
     200: iadd
     201: istore_1
     202: bipush        53
     204: iload_1
     205: imul
     206: aload_0
     207: invokevirtual #102                // Method getStackIdList:()Ljava/util/List;
     210: invokeinterface #144,  1          // InterfaceMethod java/util/List.hashCode:()I
     215: iadd
     216: istore_1
     217: aload_0
     218: invokevirtual #86                 // Method hasLastUpdate:()Z
     221: ifeq          245
     224: bipush        37
     226: iload_1
     227: imul
     228: bipush        8
     230: iadd
     231: istore_1
     232: bipush        53
     234: iload_1
     235: imul
     236: aload_0
     237: invokevirtual #118                // Method getLastUpdate:()J
     240: invokestatic  #142                // Method org/apache/hbase/thirdparty/com/google/protobuf/Internal.hashLong:(J)I
     243: iadd
     244: istore_1
     245: aload_0
     246: invokevirtual #119                // Method hasTimeout:()Z
     249: ifeq          270
     252: bipush        37
     254: iload_1
     255: imul
     256: bipush        9
     258: iadd
     259: istore_1
     260: bipush        53
     262: iload_1
     263: imul
     264: aload_0
     265: invokevirtual #120                // Method getTimeout:()I
     268: iadd
     269: istore_1
     270: aload_0
     271: invokevirtual #121                // Method hasException:()Z
     274: ifeq          298
     277: bipush        37
     279: iload_1
     280: imul
     281: bipush        10
     283: iadd
     284: istore_1
     285: bipush        53
     287: iload_1
     288: imul
     289: aload_0
     290: invokevirtual #91                 // Method getException:()Lorg/apache/hadoop/hbase/shaded/protobuf/generated/ErrorHandlingProtos$ForeignExceptionMessage;
     293: invokevirtual #145                // Method org/apache/hadoop/hbase/shaded/protobuf/generated/ErrorHandlingProtos$ForeignExceptionMessage.hashCode:()I
     296: iadd
     297: istore_1
     298: aload_0
     299: invokevirtual #123                // Method hasResult:()Z
     302: ifeq          326
     305: bipush        37
     307: iload_1
     308: imul
     309: bipush        11
     311: iadd
     312: istore_1
     313: bipush        53
     315: iload_1
     316: imul
     317: aload_0
     318: invokevirtual #124                // Method getResult:()Lorg/apache/hbase/thirdparty/com/google/protobuf/ByteString;
     321: invokevirtual #146                // Method org/apache/hbase/thirdparty/com/google/protobuf/ByteString.hashCode:()I
     324: iadd
     325: istore_1
     326: aload_0
     327: invokevirtual #126                // Method hasStateData:()Z
     330: ifeq          354
     333: bipush        37
     335: iload_1
     336: imul
     337: bipush        12
     339: iadd
     340: istore_1
     341: bipush        53
     343: iload_1
     344: imul
     345: aload_0
     346: invokevirtual #127                // Method getStateData:()Lorg/apache/hbase/thirdparty/com/google/protobuf/ByteString;
     349: invokevirtual #146                // Method org/apache/hbase/thirdparty/com/google/protobuf/ByteString.hashCode:()I
     352: iadd
     353: istore_1
     354: aload_0
     355: invokevirtual #147                // Method getStateMessageCount:()I
     358: ifle          384
     361: bipush        37
     363: iload_1
     364: imul
     365: bipush        15
     367: iadd
     368: istore_1
     369: bipush        53
     371: iload_1
     372: imul
     373: aload_0
     374: invokevirtual #128                // Method getStateMessageList:()Ljava/util/List;
     377: invokeinterface #144,  1          // InterfaceMethod java/util/List.hashCode:()I
     382: iadd
     383: istore_1
     384: aload_0
     385: invokevirtual #129                // Method hasNonceGroup:()Z
     388: ifeq          412
     391: bipush        37
     393: iload_1
     394: imul
     395: bipush        13
     397: iadd
     398: istore_1
     399: bipush        53
     401: iload_1
     402: imul
     403: aload_0
     404: invokevirtual #130                // Method getNonceGroup:()J
     407: invokestatic  #142                // Method org/apache/hbase/thirdparty/com/google/protobuf/Internal.hashLong:(J)I
     410: iadd
     411: istore_1
     412: aload_0
     413: invokevirtual #131                // Method hasNonce:()Z
     416: ifeq          440
     419: bipush        37
     421: iload_1
     422: imul
     423: bipush        14
     425: iadd
     426: istore_1
     427: bipush        53
     429: iload_1
     430: imul
     431: aload_0
     432: invokevirtual #132                // Method getNonce:()J
     435: invokestatic  #142                // Method org/apache/hbase/thirdparty/com/google/protobuf/Internal.hashLong:(J)I
     438: iadd
     439: istore_1
     440: aload_0
     441: invokevirtual #133                // Method hasLocked:()Z
     444: ifeq          468
     447: bipush        37
     449: iload_1
     450: imul
     451: bipush        16
     453: iadd
     454: istore_1
     455: bipush        53
     457: iload_1
     458: imul
     459: aload_0
     460: invokevirtual #134                // Method getLocked:()Z
     463: invokestatic  #148                // Method org/apache/hbase/thirdparty/com/google/protobuf/Internal.hashBoolean:(Z)I
     466: iadd
     467: istore_1
     468: aload_0
     469: invokevirtual #135                // Method hasBypass:()Z
     472: ifeq          496
     475: bipush        37
     477: iload_1
     478: imul
     479: bipush        17
     481: iadd
     482: istore_1
     483: bipush        53
     485: iload_1
     486: imul
     487: aload_0
     488: invokevirtual #136                // Method getBypass:()Z
     491: invokestatic  #148                // Method org/apache/hbase/thirdparty/com/google/protobuf/Internal.hashBoolean:(Z)I
     494: iadd
     495: istore_1
     496: bipush        29
     498: iload_1
     499: imul
     500: aload_0
     501: getfield      #2                  // Field unknownFields:Lorg/apache/hbase/thirdparty/com/google/protobuf/UnknownFieldSet;
     504: invokevirtual #149                // Method org/apache/hbase/thirdparty/com/google/protobuf/UnknownFieldSet.hashCode:()I
     507: iadd
     508: istore_1
     509: aload_0
     510: iload_1
     511: putfield      #138                // Field memoizedHashCode:I
     514: iload_1
     515: ireturn

  public static org.apache.hadoop.hbase.shaded.protobuf.generated.ProcedureProtos$Procedure parseFrom(java.nio.ByteBuffer) throws org.apache.hbase.thirdparty.com.google.protobuf.InvalidProtocolBufferException;
    Code:
       0: getstatic     #150                // Field PARSER:Lorg/apache/hbase/thirdparty/com/google/protobuf/Parser;
       3: aload_0
       4: invokeinterface #151,  2          // InterfaceMethod org/apache/hbase/thirdparty/com/google/protobuf/Parser.parseFrom:(Ljava/nio/ByteBuffer;)Ljava/lang/Object;
       9: checkcast     #66                 // class org/apache/hadoop/hbase/shaded/protobuf/generated/ProcedureProtos$Procedure
      12: areturn

  public static org.apache.hadoop.hbase.shaded.protobuf.generated.ProcedureProtos$Procedure parseFrom(java.nio.ByteBuffer, org.apache.hbase.thirdparty.com.google.protobuf.ExtensionRegistryLite) throws org.apache.hbase.thirdparty.com.google.protobuf.InvalidProtocolBufferException;
    Code:
       0: getstatic     #150                // Field PARSER:Lorg/apache/hbase/thirdparty/com/google/protobuf/Parser;
       3: aload_0
       4: aload_1
       5: invokeinterface #152,  3          // InterfaceMethod org/apache/hbase/thirdparty/com/google/protobuf/Parser.parseFrom:(Ljava/nio/ByteBuffer;Lorg/apache/hbase/thirdparty/com/google/protobuf/ExtensionRegistryLite;)Ljava/lang/Object;
      10: checkcast     #66                 // class org/apache/hadoop/hbase/shaded/protobuf/generated/ProcedureProtos$Procedure
      13: areturn

  public static org.apache.hadoop.hbase.shaded.protobuf.generated.ProcedureProtos$Procedure parseFrom(org.apache.hbase.thirdparty.com.google.protobuf.ByteString) throws org.apache.hbase.thirdparty.com.google.protobuf.InvalidProtocolBufferException;
    Code:
       0: getstatic     #150                // Field PARSER:Lorg/apache/hbase/thirdparty/com/google/protobuf/Parser;
       3: aload_0
       4: invokeinterface #153,  2          // InterfaceMethod org/apache/hbase/thirdparty/com/google/protobuf/Parser.parseFrom:(Lorg/apache/hbase/thirdparty/com/google/protobuf/ByteString;)Ljava/lang/Object;
       9: checkcast     #66                 // class org/apache/hadoop/hbase/shaded/protobuf/generated/ProcedureProtos$Procedure
      12: areturn

  public static org.apache.hadoop.hbase.shaded.protobuf.generated.ProcedureProtos$Procedure parseFrom(org.apache.hbase.thirdparty.com.google.protobuf.ByteString, org.apache.hbase.thirdparty.com.google.protobuf.ExtensionRegistryLite) throws org.apache.hbase.thirdparty.com.google.protobuf.InvalidProtocolBufferException;
    Code:
       0: getstatic     #150                // Field PARSER:Lorg/apache/hbase/thirdparty/com/google/protobuf/Parser;
       3: aload_0
       4: aload_1
       5: invokeinterface #154,  3          // InterfaceMethod org/apache/hbase/thirdparty/com/google/protobuf/Parser.parseFrom:(Lorg/apache/hbase/thirdparty/com/google/protobuf/ByteString;Lorg/apache/hbase/thirdparty/com/google/protobuf/ExtensionRegistryLite;)Ljava/lang/Object;
      10: checkcast     #66                 // class org/apache/hadoop/hbase/shaded/protobuf/generated/ProcedureProtos$Procedure
      13: areturn

  public static org.apache.hadoop.hbase.shaded.protobuf.generated.ProcedureProtos$Procedure parseFrom(byte[]) throws org.apache.hbase.thirdparty.com.google.protobuf.InvalidProtocolBufferException;
    Code:
       0: getstatic     #150                // Field PARSER:Lorg/apache/hbase/thirdparty/com/google/protobuf/Parser;
       3: aload_0
       4: invokeinterface #155,  2          // InterfaceMethod org/apache/hbase/thirdparty/com/google/protobuf/Parser.parseFrom:([B)Ljava/lang/Object;
       9: checkcast     #66                 // class org/apache/hadoop/hbase/shaded/protobuf/generated/ProcedureProtos$Procedure
      12: areturn

  public static org.apache.hadoop.hbase.shaded.protobuf.generated.ProcedureProtos$Procedure parseFrom(byte[], org.apache.hbase.thirdparty.com.google.protobuf.ExtensionRegistryLite) throws org.apache.hbase.thirdparty.com.google.protobuf.InvalidProtocolBufferException;
    Code:
       0: getstatic     #150                // Field PARSER:Lorg/apache/hbase/thirdparty/com/google/protobuf/Parser;
       3: aload_0
       4: aload_1
       5: invokeinterface #156,  3          // InterfaceMethod org/apache/hbase/thirdparty/com/google/protobuf/Parser.parseFrom:([BLorg/apache/hbase/thirdparty/com/google/protobuf/ExtensionRegistryLite;)Ljava/lang/Object;
      10: checkcast     #66                 // class org/apache/hadoop/hbase/shaded/protobuf/generated/ProcedureProtos$Procedure
      13: areturn

  public static org.apache.hadoop.hbase.shaded.protobuf.generated.ProcedureProtos$Procedure parseFrom(java.io.InputStream) throws java.io.IOException;
    Code:
       0: getstatic     #150                // Field PARSER:Lorg/apache/hbase/thirdparty/com/google/protobuf/Parser;
       3: aload_0
       4: invokestatic  #157                // Method org/apache/hbase/thirdparty/com/google/protobuf/GeneratedMessageV3.parseWithIOException:(Lorg/apache/hbase/thirdparty/com/google/protobuf/Parser;Ljava/io/InputStream;)Lorg/apache/hbase/thirdparty/com/google/protobuf/Message;
       7: checkcast     #66                 // class org/apache/hadoop/hbase/shaded/protobuf/generated/ProcedureProtos$Procedure
      10: areturn

  public static org.apache.hadoop.hbase.shaded.protobuf.generated.ProcedureProtos$Procedure parseFrom(java.io.InputStream, org.apache.hbase.thirdparty.com.google.protobuf.ExtensionRegistryLite) throws java.io.IOException;
    Code:
       0: getstatic     #150                // Field PARSER:Lorg/apache/hbase/thirdparty/com/google/protobuf/Parser;
       3: aload_0
       4: aload_1
       5: invokestatic  #158                // Method org/apache/hbase/thirdparty/com/google/protobuf/GeneratedMessageV3.parseWithIOException:(Lorg/apache/hbase/thirdparty/com/google/protobuf/Parser;Ljava/io/InputStream;Lorg/apache/hbase/thirdparty/com/google/protobuf/ExtensionRegistryLite;)Lorg/apache/hbase/thirdparty/com/google/protobuf/Message;
       8: checkcast     #66                 // class org/apache/hadoop/hbase/shaded/protobuf/generated/ProcedureProtos$Procedure
      11: areturn

  public static org.apache.hadoop.hbase.shaded.protobuf.generated.ProcedureProtos$Procedure parseDelimitedFrom(java.io.InputStream) throws java.io.IOException;
    Code:
       0: getstatic     #150                // Field PARSER:Lorg/apache/hbase/thirdparty/com/google/protobuf/Parser;
       3: aload_0
       4: invokestatic  #159                // Method org/apache/hbase/thirdparty/com/google/protobuf/GeneratedMessageV3.parseDelimitedWithIOException:(Lorg/apache/hbase/thirdparty/com/google/protobuf/Parser;Ljava/io/InputStream;)Lorg/apache/hbase/thirdparty/com/google/protobuf/Message;
       7: checkcast     #66                 // class org/apache/hadoop/hbase/shaded/protobuf/generated/ProcedureProtos$Procedure
      10: areturn

  public static org.apache.hadoop.hbase.shaded.protobuf.generated.ProcedureProtos$Procedure parseDelimitedFrom(java.io.InputStream, org.apache.hbase.thirdparty.com.google.protobuf.ExtensionRegistryLite) throws java.io.IOException;
    Code:
       0: getstatic     #150                // Field PARSER:Lorg/apache/hbase/thirdparty/com/google/protobuf/Parser;
       3: aload_0
       4: aload_1
       5: invokestatic  #160                // Method org/apache/hbase/thirdparty/com/google/protobuf/GeneratedMessageV3.parseDelimitedWithIOException:(Lorg/apache/hbase/thirdparty/com/google/protobuf/Parser;Ljava/io/InputStream;Lorg/apache/hbase/thirdparty/com/google/protobuf/ExtensionRegistryLite;)Lorg/apache/hbase/thirdparty/com/google/protobuf/Message;
       8: checkcast     #66                 // class org/apache/hadoop/hbase/shaded/protobuf/generated/ProcedureProtos$Procedure
      11: areturn

  public static org.apache.hadoop.hbase.shaded.protobuf.generated.ProcedureProtos$Procedure parseFrom(org.apache.hbase.thirdparty.com.google.protobuf.CodedInputStream) throws java.io.IOException;
    Code:
       0: getstatic     #150                // Field PARSER:Lorg/apache/hbase/thirdparty/com/google/protobuf/Parser;
       3: aload_0
       4: invokestatic  #161                // Method org/apache/hbase/thirdparty/com/google/protobuf/GeneratedMessageV3.parseWithIOException:(Lorg/apache/hbase/thirdparty/com/google/protobuf/Parser;Lorg/apache/hbase/thirdparty/com/google/protobuf/CodedInputStream;)Lorg/apache/hbase/thirdparty/com/google/protobuf/Message;
       7: checkcast     #66                 // class org/apache/hadoop/hbase/shaded/protobuf/generated/ProcedureProtos$Procedure
      10: areturn

  public static org.apache.hadoop.hbase.shaded.protobuf.generated.ProcedureProtos$Procedure parseFrom(org.apache.hbase.thirdparty.com.google.protobuf.CodedInputStream, org.apache.hbase.thirdparty.com.google.protobuf.ExtensionRegistryLite) throws java.io.IOException;
    Code:
       0: getstatic     #150                // Field PARSER:Lorg/apache/hbase/thirdparty/com/google/protobuf/Parser;
       3: aload_0
       4: aload_1
       5: invokestatic  #162                // Method org/apache/hbase/thirdparty/com/google/protobuf/GeneratedMessageV3.parseWithIOException:(Lorg/apache/hbase/thirdparty/com/google/protobuf/Parser;Lorg/apache/hbase/thirdparty/com/google/protobuf/CodedInputStream;Lorg/apache/hbase/thirdparty/com/google/protobuf/ExtensionRegistryLite;)Lorg/apache/hbase/thirdparty/com/google/protobuf/Message;
       8: checkcast     #66                 // class org/apache/hadoop/hbase/shaded/protobuf/generated/ProcedureProtos$Procedure
      11: areturn

  public org.apache.hadoop.hbase.shaded.protobuf.generated.ProcedureProtos$Procedure$Builder newBuilderForType();
    Code:
       0: invokestatic  #163                // Method newBuilder:()Lorg/apache/hadoop/hbase/shaded/protobuf/generated/ProcedureProtos$Procedure$Builder;
       3: areturn

  public static org.apache.hadoop.hbase.shaded.protobuf.generated.ProcedureProtos$Procedure$Builder newBuilder();
    Code:
       0: getstatic     #164                // Field DEFAULT_INSTANCE:Lorg/apache/hadoop/hbase/shaded/protobuf/generated/ProcedureProtos$Procedure;
       3: invokevirtual #165                // Method toBuilder:()Lorg/apache/hadoop/hbase/shaded/protobuf/generated/ProcedureProtos$Procedure$Builder;
       6: areturn

  public static org.apache.hadoop.hbase.shaded.protobuf.generated.ProcedureProtos$Procedure$Builder newBuilder(org.apache.hadoop.hbase.shaded.protobuf.generated.ProcedureProtos$Procedure);
    Code:
       0: getstatic     #164                // Field DEFAULT_INSTANCE:Lorg/apache/hadoop/hbase/shaded/protobuf/generated/ProcedureProtos$Procedure;
       3: invokevirtual #165                // Method toBuilder:()Lorg/apache/hadoop/hbase/shaded/protobuf/generated/ProcedureProtos$Procedure$Builder;
       6: aload_0
       7: invokevirtual #166                // Method org/apache/hadoop/hbase/shaded/protobuf/generated/ProcedureProtos$Procedure$Builder.mergeFrom:(Lorg/apache/hadoop/hbase/shaded/protobuf/generated/ProcedureProtos$Procedure;)Lorg/apache/hadoop/hbase/shaded/protobuf/generated/ProcedureProtos$Procedure$Builder;
      10: areturn

  public org.apache.hadoop.hbase.shaded.protobuf.generated.ProcedureProtos$Procedure$Builder toBuilder();
    Code:
       0: aload_0
       1: getstatic     #164                // Field DEFAULT_INSTANCE:Lorg/apache/hadoop/hbase/shaded/protobuf/generated/ProcedureProtos$Procedure;
       4: if_acmpne     18
       7: new           #67                 // class org/apache/hadoop/hbase/shaded/protobuf/generated/ProcedureProtos$Procedure$Builder
      10: dup
      11: aconst_null
      12: invokespecial #167                // Method org/apache/hadoop/hbase/shaded/protobuf/generated/ProcedureProtos$Procedure$Builder."<init>":(Lorg/apache/hadoop/hbase/shaded/protobuf/generated/ProcedureProtos$1;)V
      15: goto          30
      18: new           #67                 // class org/apache/hadoop/hbase/shaded/protobuf/generated/ProcedureProtos$Procedure$Builder
      21: dup
      22: aconst_null
      23: invokespecial #167                // Method org/apache/hadoop/hbase/shaded/protobuf/generated/ProcedureProtos$Procedure$Builder."<init>":(Lorg/apache/hadoop/hbase/shaded/protobuf/generated/ProcedureProtos$1;)V
      26: aload_0
      27: invokevirtual #166                // Method org/apache/hadoop/hbase/shaded/protobuf/generated/ProcedureProtos$Procedure$Builder.mergeFrom:(Lorg/apache/hadoop/hbase/shaded/protobuf/generated/ProcedureProtos$Procedure;)Lorg/apache/hadoop/hbase/shaded/protobuf/generated/ProcedureProtos$Procedure$Builder;
      30: areturn

  protected org.apache.hadoop.hbase.shaded.protobuf.generated.ProcedureProtos$Procedure$Builder newBuilderForType(org.apache.hbase.thirdparty.com.google.protobuf.GeneratedMessageV3$BuilderParent);
    Code:
       0: new           #67                 // class org/apache/hadoop/hbase/shaded/protobuf/generated/ProcedureProtos$Procedure$Builder
       3: dup
       4: aload_1
       5: aconst_null
       6: invokespecial #168                // Method org/apache/hadoop/hbase/shaded/protobuf/generated/ProcedureProtos$Procedure$Builder."<init>":(Lorg/apache/hbase/thirdparty/com/google/protobuf/GeneratedMessageV3$BuilderParent;Lorg/apache/hadoop/hbase/shaded/protobuf/generated/ProcedureProtos$1;)V
       9: astore_2
      10: aload_2
      11: areturn

  public static org.apache.hadoop.hbase.shaded.protobuf.generated.ProcedureProtos$Procedure getDefaultInstance();
    Code:
       0: getstatic     #164                // Field DEFAULT_INSTANCE:Lorg/apache/hadoop/hbase/shaded/protobuf/generated/ProcedureProtos$Procedure;
       3: areturn

  public static org.apache.hbase.thirdparty.com.google.protobuf.Parser<org.apache.hadoop.hbase.shaded.protobuf.generated.ProcedureProtos$Procedure> parser();
    Code:
       0: getstatic     #150                // Field PARSER:Lorg/apache/hbase/thirdparty/com/google/protobuf/Parser;
       3: areturn

  public org.apache.hbase.thirdparty.com.google.protobuf.Parser<org.apache.hadoop.hbase.shaded.protobuf.generated.ProcedureProtos$Procedure> getParserForType();
    Code:
       0: getstatic     #150                // Field PARSER:Lorg/apache/hbase/thirdparty/com/google/protobuf/Parser;
       3: areturn

  public org.apache.hadoop.hbase.shaded.protobuf.generated.ProcedureProtos$Procedure getDefaultInstanceForType();
    Code:
       0: getstatic     #164                // Field DEFAULT_INSTANCE:Lorg/apache/hadoop/hbase/shaded/protobuf/generated/ProcedureProtos$Procedure;
       3: areturn

  protected org.apache.hbase.thirdparty.com.google.protobuf.Message$Builder newBuilderForType(org.apache.hbase.thirdparty.com.google.protobuf.GeneratedMessageV3$BuilderParent);
    Code:
       0: aload_0
       1: aload_1
       2: invokevirtual #169                // Method newBuilderForType:(Lorg/apache/hbase/thirdparty/com/google/protobuf/GeneratedMessageV3$BuilderParent;)Lorg/apache/hadoop/hbase/shaded/protobuf/generated/ProcedureProtos$Procedure$Builder;
       5: areturn

  public org.apache.hbase.thirdparty.com.google.protobuf.Message$Builder toBuilder();
    Code:
       0: aload_0
       1: invokevirtual #165                // Method toBuilder:()Lorg/apache/hadoop/hbase/shaded/protobuf/generated/ProcedureProtos$Procedure$Builder;
       4: areturn

  public org.apache.hbase.thirdparty.com.google.protobuf.Message$Builder newBuilderForType();
    Code:
       0: aload_0
       1: invokevirtual #170                // Method newBuilderForType:()Lorg/apache/hadoop/hbase/shaded/protobuf/generated/ProcedureProtos$Procedure$Builder;
       4: areturn

  public org.apache.hbase.thirdparty.com.google.protobuf.MessageLite$Builder toBuilder();
    Code:
       0: aload_0
       1: invokevirtual #165                // Method toBuilder:()Lorg/apache/hadoop/hbase/shaded/protobuf/generated/ProcedureProtos$Procedure$Builder;
       4: areturn

  public org.apache.hbase.thirdparty.com.google.protobuf.MessageLite$Builder newBuilderForType();
    Code:
       0: aload_0
       1: invokevirtual #170                // Method newBuilderForType:()Lorg/apache/hadoop/hbase/shaded/protobuf/generated/ProcedureProtos$Procedure$Builder;
       4: areturn

  public org.apache.hbase.thirdparty.com.google.protobuf.MessageLite getDefaultInstanceForType();
    Code:
       0: aload_0
       1: invokevirtual #171                // Method getDefaultInstanceForType:()Lorg/apache/hadoop/hbase/shaded/protobuf/generated/ProcedureProtos$Procedure;
       4: areturn

  public org.apache.hbase.thirdparty.com.google.protobuf.Message getDefaultInstanceForType();
    Code:
       0: aload_0
       1: invokevirtual #171                // Method getDefaultInstanceForType:()Lorg/apache/hadoop/hbase/shaded/protobuf/generated/ProcedureProtos$Procedure;
       4: areturn

  static boolean access$400();
    Code:
       0: getstatic     #3                  // Field alwaysUseFieldBuilders:Z
       3: ireturn

  org.apache.hadoop.hbase.shaded.protobuf.generated.ProcedureProtos$Procedure(org.apache.hbase.thirdparty.com.google.protobuf.GeneratedMessageV3$Builder, org.apache.hadoop.hbase.shaded.protobuf.generated.ProcedureProtos$1);
    Code:
       0: aload_0
       1: aload_1
       2: invokespecial #22                 // Method "<init>":(Lorg/apache/hbase/thirdparty/com/google/protobuf/GeneratedMessageV3$Builder;)V
       5: return

  static java.lang.Object access$602(org.apache.hadoop.hbase.shaded.protobuf.generated.ProcedureProtos$Procedure, java.lang.Object);
    Code:
       0: aload_0
       1: aload_1
       2: dup_x1
       3: putfield      #21                 // Field className_:Ljava/lang/Object;
       6: areturn

  static long access$702(org.apache.hadoop.hbase.shaded.protobuf.generated.ProcedureProtos$Procedure, long);
    Code:
       0: aload_0
       1: lload_1
       2: dup2_x1
       3: putfield      #20                 // Field parentId_:J
       6: lreturn

  static long access$802(org.apache.hadoop.hbase.shaded.protobuf.generated.ProcedureProtos$Procedure, long);
    Code:
       0: aload_0
       1: lload_1
       2: dup2_x1
       3: putfield      #19                 // Field procId_:J
       6: lreturn

  static long access$902(org.apache.hadoop.hbase.shaded.protobuf.generated.ProcedureProtos$Procedure, long);
    Code:
       0: aload_0
       1: lload_1
       2: dup2_x1
       3: putfield      #18                 // Field submittedTime_:J
       6: lreturn

  static java.lang.Object access$1002(org.apache.hadoop.hbase.shaded.protobuf.generated.ProcedureProtos$Procedure, java.lang.Object);
    Code:
       0: aload_0
       1: aload_1
       2: dup_x1
       3: putfield      #17                 // Field owner_:Ljava/lang/Object;
       6: areturn

  static int access$1102(org.apache.hadoop.hbase.shaded.protobuf.generated.ProcedureProtos$Procedure, int);
    Code:
       0: aload_0
       1: iload_1
       2: dup_x1
       3: putfield      #16                 // Field state_:I
       6: ireturn

  static java.util.List access$1202(org.apache.hadoop.hbase.shaded.protobuf.generated.ProcedureProtos$Procedure, java.util.List);
    Code:
       0: aload_0
       1: aload_1
       2: dup_x1
       3: putfield      #15                 // Field stackId_:Ljava/util/List;
       6: areturn

  static long access$1302(org.apache.hadoop.hbase.shaded.protobuf.generated.ProcedureProtos$Procedure, long);
    Code:
       0: aload_0
       1: lload_1
       2: dup2_x1
       3: putfield      #14                 // Field lastUpdate_:J
       6: lreturn

  static int access$1402(org.apache.hadoop.hbase.shaded.protobuf.generated.ProcedureProtos$Procedure, int);
    Code:
       0: aload_0
       1: iload_1
       2: dup_x1
       3: putfield      #13                 // Field timeout_:I
       6: ireturn

  static org.apache.hadoop.hbase.shaded.protobuf.generated.ErrorHandlingProtos$ForeignExceptionMessage access$1502(org.apache.hadoop.hbase.shaded.protobuf.generated.ProcedureProtos$Procedure, org.apache.hadoop.hbase.shaded.protobuf.generated.ErrorHandlingProtos$ForeignExceptionMessage);
    Code:
       0: aload_0
       1: aload_1
       2: dup_x1
       3: putfield      #12                 // Field exception_:Lorg/apache/hadoop/hbase/shaded/protobuf/generated/ErrorHandlingProtos$ForeignExceptionMessage;
       6: areturn

  static org.apache.hbase.thirdparty.com.google.protobuf.ByteString access$1602(org.apache.hadoop.hbase.shaded.protobuf.generated.ProcedureProtos$Procedure, org.apache.hbase.thirdparty.com.google.protobuf.ByteString);
    Code:
       0: aload_0
       1: aload_1
       2: dup_x1
       3: putfield      #11                 // Field result_:Lorg/apache/hbase/thirdparty/com/google/protobuf/ByteString;
       6: areturn

  static org.apache.hbase.thirdparty.com.google.protobuf.ByteString access$1702(org.apache.hadoop.hbase.shaded.protobuf.generated.ProcedureProtos$Procedure, org.apache.hbase.thirdparty.com.google.protobuf.ByteString);
    Code:
       0: aload_0
       1: aload_1
       2: dup_x1
       3: putfield      #10                 // Field stateData_:Lorg/apache/hbase/thirdparty/com/google/protobuf/ByteString;
       6: areturn

  static java.util.List access$1802(org.apache.hadoop.hbase.shaded.protobuf.generated.ProcedureProtos$Procedure, java.util.List);
    Code:
       0: aload_0
       1: aload_1
       2: dup_x1
       3: putfield      #9                  // Field stateMessage_:Ljava/util/List;
       6: areturn

  static long access$1902(org.apache.hadoop.hbase.shaded.protobuf.generated.ProcedureProtos$Procedure, long);
    Code:
       0: aload_0
       1: lload_1
       2: dup2_x1
       3: putfield      #8                  // Field nonceGroup_:J
       6: lreturn

  static long access$2002(org.apache.hadoop.hbase.shaded.protobuf.generated.ProcedureProtos$Procedure, long);
    Code:
       0: aload_0
       1: lload_1
       2: dup2_x1
       3: putfield      #7                  // Field nonce_:J
       6: lreturn

  static boolean access$2102(org.apache.hadoop.hbase.shaded.protobuf.generated.ProcedureProtos$Procedure, boolean);
    Code:
       0: aload_0
       1: iload_1
       2: dup_x1
       3: putfield      #6                  // Field locked_:Z
       6: ireturn

  static boolean access$2202(org.apache.hadoop.hbase.shaded.protobuf.generated.ProcedureProtos$Procedure, boolean);
    Code:
       0: aload_0
       1: iload_1
       2: dup_x1
       3: putfield      #5                  // Field bypass_:Z
       6: ireturn

  static int access$2302(org.apache.hadoop.hbase.shaded.protobuf.generated.ProcedureProtos$Procedure, int);
    Code:
       0: aload_0
       1: iload_1
       2: dup_x1
       3: putfield      #4                  // Field bitField0_:I
       6: ireturn

  static java.lang.Object access$600(org.apache.hadoop.hbase.shaded.protobuf.generated.ProcedureProtos$Procedure);
    Code:
       0: aload_0
       1: getfield      #21                 // Field className_:Ljava/lang/Object;
       4: areturn

  static java.lang.Object access$1000(org.apache.hadoop.hbase.shaded.protobuf.generated.ProcedureProtos$Procedure);
    Code:
       0: aload_0
       1: getfield      #17                 // Field owner_:Ljava/lang/Object;
       4: areturn

  static java.util.List access$1200(org.apache.hadoop.hbase.shaded.protobuf.generated.ProcedureProtos$Procedure);
    Code:
       0: aload_0
       1: getfield      #15                 // Field stackId_:Ljava/util/List;
       4: areturn

  static java.util.List access$1800(org.apache.hadoop.hbase.shaded.protobuf.generated.ProcedureProtos$Procedure);
    Code:
       0: aload_0
       1: getfield      #9                  // Field stateMessage_:Ljava/util/List;
       4: areturn

  static boolean access$2400();
    Code:
       0: getstatic     #3                  // Field alwaysUseFieldBuilders:Z
       3: ireturn

  static org.apache.hbase.thirdparty.com.google.protobuf.UnknownFieldSet access$2500(org.apache.hadoop.hbase.shaded.protobuf.generated.ProcedureProtos$Procedure);
    Code:
       0: aload_0
       1: getfield      #2                  // Field unknownFields:Lorg/apache/hbase/thirdparty/com/google/protobuf/UnknownFieldSet;
       4: areturn

  org.apache.hadoop.hbase.shaded.protobuf.generated.ProcedureProtos$Procedure(org.apache.hbase.thirdparty.com.google.protobuf.CodedInputStream, org.apache.hbase.thirdparty.com.google.protobuf.ExtensionRegistryLite, org.apache.hadoop.hbase.shaded.protobuf.generated.ProcedureProtos$1) throws org.apache.hbase.thirdparty.com.google.protobuf.InvalidProtocolBufferException;
    Code:
       0: aload_0
       1: aload_1
       2: aload_2
       3: invokespecial #1                  // Method "<init>":(Lorg/apache/hbase/thirdparty/com/google/protobuf/CodedInputStream;Lorg/apache/hbase/thirdparty/com/google/protobuf/ExtensionRegistryLite;)V
       6: return

  static {};
    Code:
       0: new           #66                 // class org/apache/hadoop/hbase/shaded/protobuf/generated/ProcedureProtos$Procedure
       3: dup
       4: invokespecial #29                 // Method "<init>":()V
       7: putstatic     #164                // Field DEFAULT_INSTANCE:Lorg/apache/hadoop/hbase/shaded/protobuf/generated/ProcedureProtos$Procedure;
      10: new           #172                // class org/apache/hadoop/hbase/shaded/protobuf/generated/ProcedureProtos$Procedure$1
      13: dup
      14: invokespecial #173                // Method org/apache/hadoop/hbase/shaded/protobuf/generated/ProcedureProtos$Procedure$1."<init>":()V
      17: putstatic     #150                // Field PARSER:Lorg/apache/hbase/thirdparty/com/google/protobuf/Parser;
      20: return
}
