Compiled from "ProcedureStoreTracker.java"
public class org.apache.hadoop.hbase.procedure2.store.ProcedureStoreTracker {
  boolean partial;

  static final boolean $assertionsDisabled;

  public org.apache.hadoop.hbase.procedure2.store.ProcedureStoreTracker();
    Code:
       0: aload_0
       1: invokespecial #1                  // Method java/lang/Object."<init>":()V
       4: aload_0
       5: new           #2                  // class java/util/TreeMap
       8: dup
       9: invokespecial #3                  // Method java/util/TreeMap."<init>":()V
      12: putfield      #4                  // Field map:Ljava/util/TreeMap;
      15: aload_0
      16: iconst_0
      17: putfield      #5                  // Field keepDeletes:Z
      20: aload_0
      21: iconst_0
      22: putfield      #6                  // Field partial:Z
      25: aload_0
      26: ldc2_w        #8                  // long 9223372036854775807l
      29: putfield      #10                 // Field minModifiedProcId:J
      32: aload_0
      33: ldc2_w        #11                 // long -9223372036854775808l
      36: putfield      #13                 // Field maxModifiedProcId:J
      39: return

  public void resetToProto(org.apache.hadoop.hbase.shaded.protobuf.generated.ProcedureProtos$ProcedureStoreTracker);
    Code:
       0: aload_0
       1: invokevirtual #14                 // Method reset:()V
       4: aload_1
       5: invokevirtual #15                 // Method org/apache/hadoop/hbase/shaded/protobuf/generated/ProcedureProtos$ProcedureStoreTracker.getNodeList:()Ljava/util/List;
       8: invokeinterface #16,  1           // InterfaceMethod java/util/List.iterator:()Ljava/util/Iterator;
      13: astore_2
      14: aload_2
      15: invokeinterface #17,  1           // InterfaceMethod java/util/Iterator.hasNext:()Z
      20: ifeq          64
      23: aload_2
      24: invokeinterface #18,  1           // InterfaceMethod java/util/Iterator.next:()Ljava/lang/Object;
      29: checkcast     #19                 // class org/apache/hadoop/hbase/shaded/protobuf/generated/ProcedureProtos$ProcedureStoreTracker$TrackerNode
      32: astore_3
      33: new           #20                 // class org/apache/hadoop/hbase/procedure2/store/BitSetNode
      36: dup
      37: aload_3
      38: invokespecial #21                 // Method org/apache/hadoop/hbase/procedure2/store/BitSetNode."<init>":(Lorg/apache/hadoop/hbase/shaded/protobuf/generated/ProcedureProtos$ProcedureStoreTracker$TrackerNode;)V
      41: astore        4
      43: aload_0
      44: getfield      #4                  // Field map:Ljava/util/TreeMap;
      47: aload         4
      49: invokevirtual #22                 // Method org/apache/hadoop/hbase/procedure2/store/BitSetNode.getStart:()J
      52: invokestatic  #23                 // Method java/lang/Long.valueOf:(J)Ljava/lang/Long;
      55: aload         4
      57: invokevirtual #24                 // Method java/util/TreeMap.put:(Ljava/lang/Object;Ljava/lang/Object;)Ljava/lang/Object;
      60: pop
      61: goto          14
      64: return

  public void resetTo(org.apache.hadoop.hbase.procedure2.store.ProcedureStoreTracker);
    Code:
       0: aload_0
       1: aload_1
       2: iconst_0
       3: invokevirtual #25                 // Method resetTo:(Lorg/apache/hadoop/hbase/procedure2/store/ProcedureStoreTracker;Z)V
       6: return

  public void resetTo(org.apache.hadoop.hbase.procedure2.store.ProcedureStoreTracker, boolean);
    Code:
       0: aload_0
       1: invokevirtual #14                 // Method reset:()V
       4: aload_0
       5: iload_2
       6: ifeq          13
       9: iconst_0
      10: goto          17
      13: aload_1
      14: getfield      #6                  // Field partial:Z
      17: putfield      #6                  // Field partial:Z
      20: aload_0
      21: aload_1
      22: getfield      #10                 // Field minModifiedProcId:J
      25: putfield      #10                 // Field minModifiedProcId:J
      28: aload_0
      29: aload_1
      30: getfield      #13                 // Field maxModifiedProcId:J
      33: putfield      #13                 // Field maxModifiedProcId:J
      36: aload_0
      37: aload_1
      38: getfield      #5                  // Field keepDeletes:Z
      41: putfield      #5                  // Field keepDeletes:Z
      44: aload_1
      45: getfield      #4                  // Field map:Ljava/util/TreeMap;
      48: invokevirtual #26                 // Method java/util/TreeMap.entrySet:()Ljava/util/Set;
      51: invokeinterface #27,  1           // InterfaceMethod java/util/Set.iterator:()Ljava/util/Iterator;
      56: astore_3
      57: aload_3
      58: invokeinterface #17,  1           // InterfaceMethod java/util/Iterator.hasNext:()Z
      63: ifeq          113
      66: aload_3
      67: invokeinterface #18,  1           // InterfaceMethod java/util/Iterator.next:()Ljava/lang/Object;
      72: checkcast     #28                 // class java/util/Map$Entry
      75: astore        4
      77: aload_0
      78: getfield      #4                  // Field map:Ljava/util/TreeMap;
      81: aload         4
      83: invokeinterface #29,  1           // InterfaceMethod java/util/Map$Entry.getKey:()Ljava/lang/Object;
      88: new           #20                 // class org/apache/hadoop/hbase/procedure2/store/BitSetNode
      91: dup
      92: aload         4
      94: invokeinterface #30,  1           // InterfaceMethod java/util/Map$Entry.getValue:()Ljava/lang/Object;
      99: checkcast     #20                 // class org/apache/hadoop/hbase/procedure2/store/BitSetNode
     102: iload_2
     103: invokespecial #31                 // Method org/apache/hadoop/hbase/procedure2/store/BitSetNode."<init>":(Lorg/apache/hadoop/hbase/procedure2/store/BitSetNode;Z)V
     106: invokevirtual #24                 // Method java/util/TreeMap.put:(Ljava/lang/Object;Ljava/lang/Object;)Ljava/lang/Object;
     109: pop
     110: goto          57
     113: return

  public void insert(long);
    Code:
       0: aload_0
       1: aconst_null
       2: lload_1
       3: invokespecial #32                 // Method insert:(Lorg/apache/hadoop/hbase/procedure2/store/BitSetNode;J)Lorg/apache/hadoop/hbase/procedure2/store/BitSetNode;
       6: pop
       7: return

  public void insert(long[]);
    Code:
       0: iconst_0
       1: istore_2
       2: iload_2
       3: aload_1
       4: arraylength
       5: if_icmpge     21
       8: aload_0
       9: aload_1
      10: iload_2
      11: laload
      12: invokevirtual #33                 // Method insert:(J)V
      15: iinc          2, 1
      18: goto          2
      21: return

  public void insert(long, long[]);
    Code:
       0: aload_0
       1: aconst_null
       2: lload_1
       3: invokespecial #34                 // Method update:(Lorg/apache/hadoop/hbase/procedure2/store/BitSetNode;J)Lorg/apache/hadoop/hbase/procedure2/store/BitSetNode;
       6: astore        4
       8: iconst_0
       9: istore        5
      11: iload         5
      13: aload_3
      14: arraylength
      15: if_icmpge     36
      18: aload_0
      19: aload         4
      21: aload_3
      22: iload         5
      24: laload
      25: invokespecial #32                 // Method insert:(Lorg/apache/hadoop/hbase/procedure2/store/BitSetNode;J)Lorg/apache/hadoop/hbase/procedure2/store/BitSetNode;
      28: astore        4
      30: iinc          5, 1
      33: goto          11
      36: return

  public void update(long);
    Code:
       0: aload_0
       1: aconst_null
       2: lload_1
       3: invokespecial #34                 // Method update:(Lorg/apache/hadoop/hbase/procedure2/store/BitSetNode;J)Lorg/apache/hadoop/hbase/procedure2/store/BitSetNode;
       6: pop
       7: return

  public void delete(long);
    Code:
       0: aload_0
       1: aconst_null
       2: lload_1
       3: invokespecial #51                 // Method delete:(Lorg/apache/hadoop/hbase/procedure2/store/BitSetNode;J)Lorg/apache/hadoop/hbase/procedure2/store/BitSetNode;
       6: pop
       7: return

  public void delete(long[]);
    Code:
       0: aload_1
       1: invokestatic  #52                 // Method java/util/Arrays.sort:([J)V
       4: aconst_null
       5: astore_2
       6: iconst_0
       7: istore_3
       8: iload_3
       9: aload_1
      10: arraylength
      11: if_icmpge     29
      14: aload_0
      15: aload_2
      16: aload_1
      17: iload_3
      18: laload
      19: invokespecial #51                 // Method delete:(Lorg/apache/hadoop/hbase/procedure2/store/BitSetNode;J)Lorg/apache/hadoop/hbase/procedure2/store/BitSetNode;
      22: astore_2
      23: iinc          3, 1
      26: goto          8
      29: return

  public void setMinMaxModifiedProcIds(long, long);
    Code:
       0: aload_0
       1: lload_1
       2: putfield      #10                 // Field minModifiedProcId:J
       5: aload_0
       6: lload_3
       7: putfield      #13                 // Field maxModifiedProcId:J
      10: return

  public void setDeleted(long, boolean);
    Code:
       0: aload_0
       1: lload_1
       2: invokespecial #36                 // Method getOrCreateNode:(J)Lorg/apache/hadoop/hbase/procedure2/store/BitSetNode;
       5: astore        4
       7: getstatic     #40                 // Field $assertionsDisabled:Z
      10: ifne          59
      13: aload         4
      15: lload_1
      16: invokevirtual #35                 // Method org/apache/hadoop/hbase/procedure2/store/BitSetNode.contains:(J)Z
      19: ifne          59
      22: new           #41                 // class java/lang/AssertionError
      25: dup
      26: new           #42                 // class java/lang/StringBuilder
      29: dup
      30: invokespecial #43                 // Method java/lang/StringBuilder."<init>":()V
      33: ldc           #49                 // String expected procId=
      35: invokevirtual #45                 // Method java/lang/StringBuilder.append:(Ljava/lang/String;)Ljava/lang/StringBuilder;
      38: lload_1
      39: invokevirtual #46                 // Method java/lang/StringBuilder.append:(J)Ljava/lang/StringBuilder;
      42: ldc           #59                 // String  in the node=
      44: invokevirtual #45                 // Method java/lang/StringBuilder.append:(Ljava/lang/String;)Ljava/lang/StringBuilder;
      47: aload         4
      49: invokevirtual #60                 // Method java/lang/StringBuilder.append:(Ljava/lang/Object;)Ljava/lang/StringBuilder;
      52: invokevirtual #47                 // Method java/lang/StringBuilder.toString:()Ljava/lang/String;
      55: invokespecial #48                 // Method java/lang/AssertionError."<init>":(Ljava/lang/Object;)V
      58: athrow
      59: aload         4
      61: lload_1
      62: iload_3
      63: invokevirtual #61                 // Method org/apache/hadoop/hbase/procedure2/store/BitSetNode.updateState:(JZ)V
      66: aload_0
      67: lload_1
      68: invokespecial #38                 // Method trackProcIds:(J)V
      71: return

  public void setDeletedIfModified(long...);
    Code:
       0: aconst_null
       1: astore_2
       2: iconst_0
       3: istore_3
       4: iload_3
       5: aload_1
       6: arraylength
       7: if_icmpge     46
      10: aload_0
      11: aload_2
      12: aload_1
      13: iload_3
      14: laload
      15: invokespecial #39                 // Method lookupClosestNode:(Lorg/apache/hadoop/hbase/procedure2/store/BitSetNode;J)Lorg/apache/hadoop/hbase/procedure2/store/BitSetNode;
      18: astore_2
      19: aload_2
      20: ifnull        40
      23: aload_2
      24: aload_1
      25: iload_3
      26: laload
      27: invokevirtual #62                 // Method org/apache/hadoop/hbase/procedure2/store/BitSetNode.isModified:(J)Z
      30: ifeq          40
      33: aload_2
      34: aload_1
      35: iload_3
      36: laload
      37: invokevirtual #56                 // Method org/apache/hadoop/hbase/procedure2/store/BitSetNode.delete:(J)V
      40: iinc          3, 1
      43: goto          4
      46: return

  public void setDeletedIfDeletedByThem(org.apache.hadoop.hbase.procedure2.store.ProcedureStoreTracker);
    Code:
       0: aload_0
       1: aload_1
       2: invokedynamic #69,  0             // InvokeDynamic #0:apply:()Ljava/util/function/BiFunction;
       7: invokespecial #70                 // Method setDeleteIf:(Lorg/apache/hadoop/hbase/procedure2/store/ProcedureStoreTracker;Ljava/util/function/BiFunction;)V
      10: return

  public void setDeletedIfModifiedInBoth(org.apache.hadoop.hbase.procedure2.store.ProcedureStoreTracker);
    Code:
       0: aload_0
       1: aload_1
       2: invokedynamic #71,  0             // InvokeDynamic #1:apply:()Ljava/util/function/BiFunction;
       7: invokespecial #70                 // Method setDeleteIf:(Lorg/apache/hadoop/hbase/procedure2/store/ProcedureStoreTracker;Ljava/util/function/BiFunction;)V
      10: return

  public long getModifiedMinProcId();
    Code:
       0: aload_0
       1: getfield      #10                 // Field minModifiedProcId:J
       4: lreturn

  public long getModifiedMaxProcId();
    Code:
       0: aload_0
       1: getfield      #13                 // Field maxModifiedProcId:J
       4: lreturn

  public void reset();
    Code:
       0: aload_0
       1: iconst_0
       2: putfield      #5                  // Field keepDeletes:Z
       5: aload_0
       6: iconst_0
       7: putfield      #6                  // Field partial:Z
      10: aload_0
      11: getfield      #4                  // Field map:Ljava/util/TreeMap;
      14: invokevirtual #75                 // Method java/util/TreeMap.clear:()V
      17: aload_0
      18: ldc2_w        #8                  // long 9223372036854775807l
      21: putfield      #10                 // Field minModifiedProcId:J
      24: aload_0
      25: ldc2_w        #11                 // long -9223372036854775808l
      28: putfield      #13                 // Field maxModifiedProcId:J
      31: return

  public boolean isModified(long);
    Code:
       0: aload_0
       1: getfield      #4                  // Field map:Ljava/util/TreeMap;
       4: lload_1
       5: invokestatic  #23                 // Method java/lang/Long.valueOf:(J)Ljava/lang/Long;
       8: invokevirtual #72                 // Method java/util/TreeMap.floorEntry:(Ljava/lang/Object;)Ljava/util/Map$Entry;
      11: astore_3
      12: aload_3
      13: ifnull        52
      16: aload_3
      17: invokeinterface #30,  1           // InterfaceMethod java/util/Map$Entry.getValue:()Ljava/lang/Object;
      22: checkcast     #20                 // class org/apache/hadoop/hbase/procedure2/store/BitSetNode
      25: lload_1
      26: invokevirtual #35                 // Method org/apache/hadoop/hbase/procedure2/store/BitSetNode.contains:(J)Z
      29: ifeq          52
      32: aload_3
      33: invokeinterface #30,  1           // InterfaceMethod java/util/Map$Entry.getValue:()Ljava/lang/Object;
      38: checkcast     #20                 // class org/apache/hadoop/hbase/procedure2/store/BitSetNode
      41: lload_1
      42: invokevirtual #62                 // Method org/apache/hadoop/hbase/procedure2/store/BitSetNode.isModified:(J)Z
      45: ifeq          52
      48: iconst_1
      49: goto          53
      52: iconst_0
      53: ireturn

  public org.apache.hadoop.hbase.procedure2.store.ProcedureStoreTracker$DeleteState isDeleted(long);
    Code:
       0: aload_0
       1: getfield      #4                  // Field map:Ljava/util/TreeMap;
       4: lload_1
       5: invokestatic  #23                 // Method java/lang/Long.valueOf:(J)Ljava/lang/Long;
       8: invokevirtual #72                 // Method java/util/TreeMap.floorEntry:(Ljava/lang/Object;)Ljava/util/Map$Entry;
      11: astore_3
      12: aload_3
      13: ifnull        76
      16: aload_3
      17: invokeinterface #30,  1           // InterfaceMethod java/util/Map$Entry.getValue:()Ljava/lang/Object;
      22: checkcast     #20                 // class org/apache/hadoop/hbase/procedure2/store/BitSetNode
      25: lload_1
      26: invokevirtual #35                 // Method org/apache/hadoop/hbase/procedure2/store/BitSetNode.contains:(J)Z
      29: ifeq          76
      32: aload_3
      33: invokeinterface #30,  1           // InterfaceMethod java/util/Map$Entry.getValue:()Ljava/lang/Object;
      38: checkcast     #20                 // class org/apache/hadoop/hbase/procedure2/store/BitSetNode
      41: astore        4
      43: aload         4
      45: lload_1
      46: invokevirtual #76                 // Method org/apache/hadoop/hbase/procedure2/store/BitSetNode.isDeleted:(J)Lorg/apache/hadoop/hbase/procedure2/store/ProcedureStoreTracker$DeleteState;
      49: astore        5
      51: aload_0
      52: getfield      #6                  // Field partial:Z
      55: ifeq          73
      58: aload         4
      60: lload_1
      61: invokevirtual #62                 // Method org/apache/hadoop/hbase/procedure2/store/BitSetNode.isModified:(J)Z
      64: ifne          73
      67: getstatic     #77                 // Field org/apache/hadoop/hbase/procedure2/store/ProcedureStoreTracker$DeleteState.MAYBE:Lorg/apache/hadoop/hbase/procedure2/store/ProcedureStoreTracker$DeleteState;
      70: goto          75
      73: aload         5
      75: areturn
      76: aload_0
      77: getfield      #6                  // Field partial:Z
      80: ifeq          89
      83: getstatic     #77                 // Field org/apache/hadoop/hbase/procedure2/store/ProcedureStoreTracker$DeleteState.MAYBE:Lorg/apache/hadoop/hbase/procedure2/store/ProcedureStoreTracker$DeleteState;
      86: goto          92
      89: getstatic     #78                 // Field org/apache/hadoop/hbase/procedure2/store/ProcedureStoreTracker$DeleteState.YES:Lorg/apache/hadoop/hbase/procedure2/store/ProcedureStoreTracker$DeleteState;
      92: areturn

  public long getActiveMinProcId();
    Code:
       0: aload_0
       1: getfield      #4                  // Field map:Ljava/util/TreeMap;
       4: invokevirtual #79                 // Method java/util/TreeMap.firstEntry:()Ljava/util/Map$Entry;
       7: astore_1
       8: aload_1
       9: ifnonnull     18
      12: ldc2_w        #81                 // long -1l
      15: goto          30
      18: aload_1
      19: invokeinterface #30,  1           // InterfaceMethod java/util/Map$Entry.getValue:()Ljava/lang/Object;
      24: checkcast     #20                 // class org/apache/hadoop/hbase/procedure2/store/BitSetNode
      27: invokevirtual #83                 // Method org/apache/hadoop/hbase/procedure2/store/BitSetNode.getActiveMinProcId:()J
      30: lreturn

  public void setKeepDeletes(boolean);
    Code:
       0: aload_0
       1: iload_1
       2: putfield      #5                  // Field keepDeletes:Z
       5: iload_1
       6: ifne          65
       9: aload_0
      10: getfield      #4                  // Field map:Ljava/util/TreeMap;
      13: invokevirtual #26                 // Method java/util/TreeMap.entrySet:()Ljava/util/Set;
      16: invokeinterface #27,  1           // InterfaceMethod java/util/Set.iterator:()Ljava/util/Iterator;
      21: astore_2
      22: aload_2
      23: invokeinterface #17,  1           // InterfaceMethod java/util/Iterator.hasNext:()Z
      28: ifeq          65
      31: aload_2
      32: invokeinterface #18,  1           // InterfaceMethod java/util/Iterator.next:()Ljava/lang/Object;
      37: checkcast     #28                 // class java/util/Map$Entry
      40: astore_3
      41: aload_3
      42: invokeinterface #30,  1           // InterfaceMethod java/util/Map$Entry.getValue:()Ljava/lang/Object;
      47: checkcast     #20                 // class org/apache/hadoop/hbase/procedure2/store/BitSetNode
      50: invokevirtual #57                 // Method org/apache/hadoop/hbase/procedure2/store/BitSetNode.isEmpty:()Z
      53: ifeq          62
      56: aload_2
      57: invokeinterface #84,  1           // InterfaceMethod java/util/Iterator.remove:()V
      62: goto          22
      65: return

  public boolean isPartial();
    Code:
       0: aload_0
       1: getfield      #6                  // Field partial:Z
       4: ireturn

  public void setPartialFlag(boolean);
    Code:
       0: aload_0
       1: getfield      #6                  // Field partial:Z
       4: ifeq          58
       7: iload_1
       8: ifne          58
      11: aload_0
      12: getfield      #4                  // Field map:Ljava/util/TreeMap;
      15: invokevirtual #26                 // Method java/util/TreeMap.entrySet:()Ljava/util/Set;
      18: invokeinterface #27,  1           // InterfaceMethod java/util/Set.iterator:()Ljava/util/Iterator;
      23: astore_2
      24: aload_2
      25: invokeinterface #17,  1           // InterfaceMethod java/util/Iterator.hasNext:()Z
      30: ifeq          58
      33: aload_2
      34: invokeinterface #18,  1           // InterfaceMethod java/util/Iterator.next:()Ljava/lang/Object;
      39: checkcast     #28                 // class java/util/Map$Entry
      42: astore_3
      43: aload_3
      44: invokeinterface #30,  1           // InterfaceMethod java/util/Map$Entry.getValue:()Ljava/lang/Object;
      49: checkcast     #20                 // class org/apache/hadoop/hbase/procedure2/store/BitSetNode
      52: invokevirtual #85                 // Method org/apache/hadoop/hbase/procedure2/store/BitSetNode.unsetPartialFlag:()V
      55: goto          24
      58: aload_0
      59: iload_1
      60: putfield      #6                  // Field partial:Z
      63: return

  public boolean isEmpty();
    Code:
       0: aload_0
       1: getfield      #4                  // Field map:Ljava/util/TreeMap;
       4: invokevirtual #26                 // Method java/util/TreeMap.entrySet:()Ljava/util/Set;
       7: invokeinterface #27,  1           // InterfaceMethod java/util/Set.iterator:()Ljava/util/Iterator;
      12: astore_1
      13: aload_1
      14: invokeinterface #17,  1           // InterfaceMethod java/util/Iterator.hasNext:()Z
      19: ifeq          52
      22: aload_1
      23: invokeinterface #18,  1           // InterfaceMethod java/util/Iterator.next:()Ljava/lang/Object;
      28: checkcast     #28                 // class java/util/Map$Entry
      31: astore_2
      32: aload_2
      33: invokeinterface #30,  1           // InterfaceMethod java/util/Map$Entry.getValue:()Ljava/lang/Object;
      38: checkcast     #20                 // class org/apache/hadoop/hbase/procedure2/store/BitSetNode
      41: invokevirtual #57                 // Method org/apache/hadoop/hbase/procedure2/store/BitSetNode.isEmpty:()Z
      44: ifne          49
      47: iconst_0
      48: ireturn
      49: goto          13
      52: iconst_1
      53: ireturn

  public boolean isAllModified();
    Code:
       0: aload_0
       1: getfield      #4                  // Field map:Ljava/util/TreeMap;
       4: invokevirtual #26                 // Method java/util/TreeMap.entrySet:()Ljava/util/Set;
       7: invokeinterface #27,  1           // InterfaceMethod java/util/Set.iterator:()Ljava/util/Iterator;
      12: astore_1
      13: aload_1
      14: invokeinterface #17,  1           // InterfaceMethod java/util/Iterator.hasNext:()Z
      19: ifeq          52
      22: aload_1
      23: invokeinterface #18,  1           // InterfaceMethod java/util/Iterator.next:()Ljava/lang/Object;
      28: checkcast     #28                 // class java/util/Map$Entry
      31: astore_2
      32: aload_2
      33: invokeinterface #30,  1           // InterfaceMethod java/util/Map$Entry.getValue:()Ljava/lang/Object;
      38: checkcast     #20                 // class org/apache/hadoop/hbase/procedure2/store/BitSetNode
      41: invokevirtual #86                 // Method org/apache/hadoop/hbase/procedure2/store/BitSetNode.isAllModified:()Z
      44: ifne          49
      47: iconst_0
      48: ireturn
      49: goto          13
      52: iconst_1
      53: ireturn

  public long[] getAllActiveProcIds();
    Code:
       0: aload_0
       1: getfield      #4                  // Field map:Ljava/util/TreeMap;
       4: invokevirtual #63                 // Method java/util/TreeMap.values:()Ljava/util/Collection;
       7: invokeinterface #87,  1           // InterfaceMethod java/util/Collection.stream:()Ljava/util/stream/Stream;
      12: invokedynamic #88,  0             // InvokeDynamic #2:apply:()Ljava/util/function/Function;
      17: invokeinterface #89,  2           // InterfaceMethod java/util/stream/Stream.map:(Ljava/util/function/Function;)Ljava/util/stream/Stream;
      22: invokedynamic #90,  0             // InvokeDynamic #3:test:()Ljava/util/function/Predicate;
      27: invokeinterface #91,  2           // InterfaceMethod java/util/stream/Stream.filter:(Ljava/util/function/Predicate;)Ljava/util/stream/Stream;
      32: invokedynamic #92,  0             // InvokeDynamic #4:apply:()Ljava/util/function/Function;
      37: invokeinterface #93,  2           // InterfaceMethod java/util/stream/Stream.flatMapToLong:(Ljava/util/function/Function;)Ljava/util/stream/LongStream;
      42: invokeinterface #94,  1           // InterfaceMethod java/util/stream/LongStream.toArray:()[J
      47: areturn

  public void resetModified();
    Code:
       0: aload_0
       1: getfield      #4                  // Field map:Ljava/util/TreeMap;
       4: invokevirtual #26                 // Method java/util/TreeMap.entrySet:()Ljava/util/Set;
       7: invokeinterface #27,  1           // InterfaceMethod java/util/Set.iterator:()Ljava/util/Iterator;
      12: astore_1
      13: aload_1
      14: invokeinterface #17,  1           // InterfaceMethod java/util/Iterator.hasNext:()Z
      19: ifeq          47
      22: aload_1
      23: invokeinterface #18,  1           // InterfaceMethod java/util/Iterator.next:()Ljava/lang/Object;
      28: checkcast     #28                 // class java/util/Map$Entry
      31: astore_2
      32: aload_2
      33: invokeinterface #30,  1           // InterfaceMethod java/util/Map$Entry.getValue:()Ljava/lang/Object;
      38: checkcast     #20                 // class org/apache/hadoop/hbase/procedure2/store/BitSetNode
      41: invokevirtual #95                 // Method org/apache/hadoop/hbase/procedure2/store/BitSetNode.resetModified:()V
      44: goto          13
      47: aload_0
      48: ldc2_w        #8                  // long 9223372036854775807l
      51: putfield      #10                 // Field minModifiedProcId:J
      54: aload_0
      55: ldc2_w        #11                 // long -9223372036854775808l
      58: putfield      #13                 // Field maxModifiedProcId:J
      61: return

  public void dump();
    Code:
       0: getstatic     #105                // Field java/lang/System.out:Ljava/io/PrintStream;
       3: new           #42                 // class java/lang/StringBuilder
       6: dup
       7: invokespecial #43                 // Method java/lang/StringBuilder."<init>":()V
      10: ldc           #106                // String map
      12: invokevirtual #45                 // Method java/lang/StringBuilder.append:(Ljava/lang/String;)Ljava/lang/StringBuilder;
      15: aload_0
      16: getfield      #4                  // Field map:Ljava/util/TreeMap;
      19: invokevirtual #107                // Method java/util/TreeMap.size:()I
      22: invokevirtual #108                // Method java/lang/StringBuilder.append:(I)Ljava/lang/StringBuilder;
      25: invokevirtual #47                 // Method java/lang/StringBuilder.toString:()Ljava/lang/String;
      28: invokevirtual #109                // Method java/io/PrintStream.println:(Ljava/lang/String;)V
      31: getstatic     #105                // Field java/lang/System.out:Ljava/io/PrintStream;
      34: new           #42                 // class java/lang/StringBuilder
      37: dup
      38: invokespecial #43                 // Method java/lang/StringBuilder."<init>":()V
      41: ldc           #110                // String isAllModified
      43: invokevirtual #45                 // Method java/lang/StringBuilder.append:(Ljava/lang/String;)Ljava/lang/StringBuilder;
      46: aload_0
      47: invokevirtual #111                // Method isAllModified:()Z
      50: invokevirtual #112                // Method java/lang/StringBuilder.append:(Z)Ljava/lang/StringBuilder;
      53: invokevirtual #47                 // Method java/lang/StringBuilder.toString:()Ljava/lang/String;
      56: invokevirtual #109                // Method java/io/PrintStream.println:(Ljava/lang/String;)V
      59: getstatic     #105                // Field java/lang/System.out:Ljava/io/PrintStream;
      62: new           #42                 // class java/lang/StringBuilder
      65: dup
      66: invokespecial #43                 // Method java/lang/StringBuilder."<init>":()V
      69: ldc           #113                // String isEmpty
      71: invokevirtual #45                 // Method java/lang/StringBuilder.append:(Ljava/lang/String;)Ljava/lang/StringBuilder;
      74: aload_0
      75: invokevirtual #114                // Method isEmpty:()Z
      78: invokevirtual #112                // Method java/lang/StringBuilder.append:(Z)Ljava/lang/StringBuilder;
      81: invokevirtual #47                 // Method java/lang/StringBuilder.toString:()Ljava/lang/String;
      84: invokevirtual #109                // Method java/io/PrintStream.println:(Ljava/lang/String;)V
      87: aload_0
      88: getfield      #4                  // Field map:Ljava/util/TreeMap;
      91: invokevirtual #26                 // Method java/util/TreeMap.entrySet:()Ljava/util/Set;
      94: invokeinterface #27,  1           // InterfaceMethod java/util/Set.iterator:()Ljava/util/Iterator;
      99: astore_1
     100: aload_1
     101: invokeinterface #17,  1           // InterfaceMethod java/util/Iterator.hasNext:()Z
     106: ifeq          134
     109: aload_1
     110: invokeinterface #18,  1           // InterfaceMethod java/util/Iterator.next:()Ljava/lang/Object;
     115: checkcast     #28                 // class java/util/Map$Entry
     118: astore_2
     119: aload_2
     120: invokeinterface #30,  1           // InterfaceMethod java/util/Map$Entry.getValue:()Ljava/lang/Object;
     125: checkcast     #20                 // class org/apache/hadoop/hbase/procedure2/store/BitSetNode
     128: invokevirtual #115                // Method org/apache/hadoop/hbase/procedure2/store/BitSetNode.dump:()V
     131: goto          100
     134: return

  public org.apache.hadoop.hbase.shaded.protobuf.generated.ProcedureProtos$ProcedureStoreTracker toProto() throws java.io.IOException;
    Code:
       0: invokestatic  #116                // Method org/apache/hadoop/hbase/shaded/protobuf/generated/ProcedureProtos$ProcedureStoreTracker.newBuilder:()Lorg/apache/hadoop/hbase/shaded/protobuf/generated/ProcedureProtos$ProcedureStoreTracker$Builder;
       3: astore_1
       4: aload_0
       5: getfield      #4                  // Field map:Ljava/util/TreeMap;
       8: invokevirtual #26                 // Method java/util/TreeMap.entrySet:()Ljava/util/Set;
      11: invokeinterface #27,  1           // InterfaceMethod java/util/Set.iterator:()Ljava/util/Iterator;
      16: astore_2
      17: aload_2
      18: invokeinterface #17,  1           // InterfaceMethod java/util/Iterator.hasNext:()Z
      23: ifeq          56
      26: aload_2
      27: invokeinterface #18,  1           // InterfaceMethod java/util/Iterator.next:()Ljava/lang/Object;
      32: checkcast     #28                 // class java/util/Map$Entry
      35: astore_3
      36: aload_1
      37: aload_3
      38: invokeinterface #30,  1           // InterfaceMethod java/util/Map$Entry.getValue:()Ljava/lang/Object;
      43: checkcast     #20                 // class org/apache/hadoop/hbase/procedure2/store/BitSetNode
      46: invokevirtual #117                // Method org/apache/hadoop/hbase/procedure2/store/BitSetNode.convert:()Lorg/apache/hadoop/hbase/shaded/protobuf/generated/ProcedureProtos$ProcedureStoreTracker$TrackerNode;
      49: invokevirtual #118                // Method org/apache/hadoop/hbase/shaded/protobuf/generated/ProcedureProtos$ProcedureStoreTracker$Builder.addNode:(Lorg/apache/hadoop/hbase/shaded/protobuf/generated/ProcedureProtos$ProcedureStoreTracker$TrackerNode;)Lorg/apache/hadoop/hbase/shaded/protobuf/generated/ProcedureProtos$ProcedureStoreTracker$Builder;
      52: pop
      53: goto          17
      56: aload_1
      57: invokevirtual #119                // Method org/apache/hadoop/hbase/shaded/protobuf/generated/ProcedureProtos$ProcedureStoreTracker$Builder.build:()Lorg/apache/hadoop/hbase/shaded/protobuf/generated/ProcedureProtos$ProcedureStoreTracker;
      60: areturn

  static {};
    Code:
       0: ldc           #122                // class org/apache/hadoop/hbase/procedure2/store/ProcedureStoreTracker
       2: invokevirtual #123                // Method java/lang/Class.desiredAssertionStatus:()Z
       5: ifne          12
       8: iconst_1
       9: goto          13
      12: iconst_0
      13: putstatic     #40                 // Field $assertionsDisabled:Z
      16: ldc           #122                // class org/apache/hadoop/hbase/procedure2/store/ProcedureStoreTracker
      18: invokestatic  #124                // Method org/slf4j/LoggerFactory.getLogger:(Ljava/lang/Class;)Lorg/slf4j/Logger;
      21: putstatic     #53                 // Field LOG:Lorg/slf4j/Logger;
      24: return
}
