Compiled from "ProcedurePrepareLatch.java"
public abstract class org.apache.hadoop.hbase.master.procedure.ProcedurePrepareLatch {
  public org.apache.hadoop.hbase.master.procedure.ProcedurePrepareLatch();
    Code:
       0: aload_0
       1: invokespecial #1                  // Method java/lang/Object."<init>":()V
       4: return

  public static org.apache.hadoop.hbase.master.procedure.ProcedurePrepareLatch createLatch();
    Code:
       0: iconst_1
       1: iconst_1
       2: invokestatic  #2                  // Method createLatch:(II)Lorg/apache/hadoop/hbase/master/procedure/ProcedurePrepareLatch;
       5: areturn

  public static org.apache.hadoop.hbase.master.procedure.ProcedurePrepareLatch createLatch(int, int);
    Code:
       0: iload_0
       1: iload_1
       2: invokestatic  #3                  // Method hasProcedureSupport:(II)Z
       5: ifeq          14
       8: getstatic     #4                  // Field noopLatch:Lorg/apache/hadoop/hbase/master/procedure/ProcedurePrepareLatch$NoopLatch;
      11: goto          21
      14: new           #5                  // class org/apache/hadoop/hbase/master/procedure/ProcedurePrepareLatch$CompatibilityLatch
      17: dup
      18: invokespecial #6                  // Method org/apache/hadoop/hbase/master/procedure/ProcedurePrepareLatch$CompatibilityLatch."<init>":()V
      21: areturn

  public static org.apache.hadoop.hbase.master.procedure.ProcedurePrepareLatch createBlockingLatch();
    Code:
       0: new           #5                  // class org/apache/hadoop/hbase/master/procedure/ProcedurePrepareLatch$CompatibilityLatch
       3: dup
       4: invokespecial #6                  // Method org/apache/hadoop/hbase/master/procedure/ProcedurePrepareLatch$CompatibilityLatch."<init>":()V
       7: areturn

  public static org.apache.hadoop.hbase.master.procedure.ProcedurePrepareLatch getNoopLatch();
    Code:
       0: getstatic     #4                  // Field noopLatch:Lorg/apache/hadoop/hbase/master/procedure/ProcedurePrepareLatch$NoopLatch;
       3: areturn

  protected abstract void countDown(org.apache.hadoop.hbase.procedure2.Procedure);

  public abstract void await() throws java.io.IOException;

  public static void releaseLatch(org.apache.hadoop.hbase.master.procedure.ProcedurePrepareLatch, org.apache.hadoop.hbase.procedure2.Procedure);
    Code:
       0: aload_0
       1: ifnull        9
       4: aload_0
       5: aload_1
       6: invokevirtual #8                  // Method countDown:(Lorg/apache/hadoop/hbase/procedure2/Procedure;)V
       9: return

  static {};
    Code:
       0: new           #9                  // class org/apache/hadoop/hbase/master/procedure/ProcedurePrepareLatch$NoopLatch
       3: dup
       4: aconst_null
       5: invokespecial #10                 // Method org/apache/hadoop/hbase/master/procedure/ProcedurePrepareLatch$NoopLatch."<init>":(Lorg/apache/hadoop/hbase/master/procedure/ProcedurePrepareLatch$1;)V
       8: putstatic     #4                  // Field noopLatch:Lorg/apache/hadoop/hbase/master/procedure/ProcedurePrepareLatch$NoopLatch;
      11: return
}
