Compiled from "ProcedureSyncWait.java"
public final class org.apache.hadoop.hbase.master.procedure.ProcedureSyncWait {
  public static java.util.concurrent.Future<byte[]> submitProcedure(org.apache.hadoop.hbase.procedure2.ProcedureExecutor<org.apache.hadoop.hbase.master.procedure.MasterProcedureEnv>, org.apache.hadoop.hbase.procedure2.Procedure<org.apache.hadoop.hbase.master.procedure.MasterProcedureEnv>);
    Code:
       0: aload_1
       1: invokevirtual #2                  // Method org/apache/hadoop/hbase/procedure2/Procedure.isInitializing:()Z
       4: ifeq          13
       7: aload_0
       8: aload_1
       9: invokevirtual #3                  // Method org/apache/hadoop/hbase/procedure2/ProcedureExecutor.submitProcedure:(Lorg/apache/hadoop/hbase/procedure2/Procedure;)J
      12: pop2
      13: new           #4                  // class org/apache/hadoop/hbase/master/procedure/ProcedureSyncWait$ProcedureFuture
      16: dup
      17: aload_0
      18: aload_1
      19: invokespecial #5                  // Method org/apache/hadoop/hbase/master/procedure/ProcedureSyncWait$ProcedureFuture."<init>":(Lorg/apache/hadoop/hbase/procedure2/ProcedureExecutor;Lorg/apache/hadoop/hbase/procedure2/Procedure;)V
      22: areturn

  public static byte[] submitAndWaitProcedure(org.apache.hadoop.hbase.procedure2.ProcedureExecutor<org.apache.hadoop.hbase.master.procedure.MasterProcedureEnv>, org.apache.hadoop.hbase.procedure2.Procedure<org.apache.hadoop.hbase.master.procedure.MasterProcedureEnv>) throws java.io.IOException;
    Code:
       0: aload_1
       1: invokevirtual #2                  // Method org/apache/hadoop/hbase/procedure2/Procedure.isInitializing:()Z
       4: ifeq          13
       7: aload_0
       8: aload_1
       9: invokevirtual #3                  // Method org/apache/hadoop/hbase/procedure2/ProcedureExecutor.submitProcedure:(Lorg/apache/hadoop/hbase/procedure2/Procedure;)J
      12: pop2
      13: aload_0
      14: aload_1
      15: ldc2_w        #7                  // long 9223372036854775807l
      18: invokestatic  #9                  // Method waitForProcedureToCompleteIOE:(Lorg/apache/hadoop/hbase/procedure2/ProcedureExecutor;Lorg/apache/hadoop/hbase/procedure2/Procedure;J)[B
      21: areturn

  public static byte[] waitForProcedureToCompleteIOE(org.apache.hadoop.hbase.procedure2.ProcedureExecutor<org.apache.hadoop.hbase.master.procedure.MasterProcedureEnv>, org.apache.hadoop.hbase.procedure2.Procedure<?>, long) throws java.io.IOException;
    Code:
       0: aload_0
       1: aload_1
       2: lload_2
       3: invokestatic  #10                 // Method waitForProcedureToComplete:(Lorg/apache/hadoop/hbase/procedure2/ProcedureExecutor;Lorg/apache/hadoop/hbase/procedure2/Procedure;J)[B
       6: areturn
       7: astore        4
       9: aload         4
      11: athrow
      12: astore        4
      14: new           #11                 // class java/io/IOException
      17: dup
      18: aload         4
      20: invokespecial #13                 // Method java/io/IOException."<init>":(Ljava/lang/Throwable;)V
      23: athrow
    Exception table:
       from    to  target type
           0     6     7   Class java/io/IOException
           0     6    12   Class java/lang/Exception

  public static byte[] waitForProcedureToComplete(org.apache.hadoop.hbase.procedure2.ProcedureExecutor<org.apache.hadoop.hbase.master.procedure.MasterProcedureEnv>, org.apache.hadoop.hbase.procedure2.Procedure<?>, long) throws java.io.IOException;
    Code:
       0: aload_0
       1: invokevirtual #14                 // Method org/apache/hadoop/hbase/procedure2/ProcedureExecutor.getEnvironment:()Ljava/lang/Object;
       4: checkcast     #15                 // class org/apache/hadoop/hbase/master/procedure/MasterProcedureEnv
       7: lload_2
       8: new           #16                 // class java/lang/StringBuilder
      11: dup
      12: invokespecial #17                 // Method java/lang/StringBuilder."<init>":()V
      15: ldc           #18                 // String pid=
      17: invokevirtual #19                 // Method java/lang/StringBuilder.append:(Ljava/lang/String;)Ljava/lang/StringBuilder;
      20: aload_1
      21: invokevirtual #20                 // Method org/apache/hadoop/hbase/procedure2/Procedure.getProcId:()J
      24: invokevirtual #21                 // Method java/lang/StringBuilder.append:(J)Ljava/lang/StringBuilder;
      27: invokevirtual #22                 // Method java/lang/StringBuilder.toString:()Ljava/lang/String;
      30: new           #23                 // class org/apache/hadoop/hbase/master/procedure/ProcedureSyncWait$1
      33: dup
      34: aload_0
      35: aload_1
      36: invokespecial #24                 // Method org/apache/hadoop/hbase/master/procedure/ProcedureSyncWait$1."<init>":(Lorg/apache/hadoop/hbase/procedure2/ProcedureExecutor;Lorg/apache/hadoop/hbase/procedure2/Procedure;)V
      39: invokestatic  #25                 // Method waitFor:(Lorg/apache/hadoop/hbase/master/procedure/MasterProcedureEnv;JLjava/lang/String;Lorg/apache/hadoop/hbase/master/procedure/ProcedureSyncWait$Predicate;)Ljava/lang/Object;
      42: pop
      43: aload_0
      44: invokevirtual #26                 // Method org/apache/hadoop/hbase/procedure2/ProcedureExecutor.isRunning:()Z
      47: ifne          60
      50: new           #11                 // class java/io/IOException
      53: dup
      54: ldc           #27                 // String The Master is Aborting
      56: invokespecial #28                 // Method java/io/IOException."<init>":(Ljava/lang/String;)V
      59: athrow
      60: aload_1
      61: invokevirtual #29                 // Method org/apache/hadoop/hbase/procedure2/Procedure.hasException:()Z
      64: ifeq          72
      67: aload_1
      68: invokestatic  #30                 // Method org/apache/hadoop/hbase/master/procedure/MasterProcedureUtil.unwrapRemoteIOException:(Lorg/apache/hadoop/hbase/procedure2/Procedure;)Ljava/io/IOException;
      71: athrow
      72: aload_1
      73: invokevirtual #31                 // Method org/apache/hadoop/hbase/procedure2/Procedure.getResult:()[B
      76: areturn

  public static <T> T waitFor(org.apache.hadoop.hbase.master.procedure.MasterProcedureEnv, java.lang.String, org.apache.hadoop.hbase.master.procedure.ProcedureSyncWait$Predicate<T>) throws java.io.IOException;
    Code:
       0: aload_0
       1: invokevirtual #32                 // Method org/apache/hadoop/hbase/master/procedure/MasterProcedureEnv.getMasterConfiguration:()Lorg/apache/hadoop/conf/Configuration;
       4: astore_3
       5: aload_3
       6: ldc           #33                 // String hbase.master.wait.on.region
       8: ldc2_w        #34                 // long 300000l
      11: invokevirtual #36                 // Method org/apache/hadoop/conf/Configuration.getLong:(Ljava/lang/String;J)J
      14: lstore        4
      16: aload_0
      17: lload         4
      19: aload_1
      20: aload_2
      21: invokestatic  #25                 // Method waitFor:(Lorg/apache/hadoop/hbase/master/procedure/MasterProcedureEnv;JLjava/lang/String;Lorg/apache/hadoop/hbase/master/procedure/ProcedureSyncWait$Predicate;)Ljava/lang/Object;
      24: areturn

  public static <T> T waitFor(org.apache.hadoop.hbase.master.procedure.MasterProcedureEnv, long, java.lang.String, org.apache.hadoop.hbase.master.procedure.ProcedureSyncWait$Predicate<T>) throws java.io.IOException;
    Code:
       0: aload_0
       1: invokevirtual #32                 // Method org/apache/hadoop/hbase/master/procedure/MasterProcedureEnv.getMasterConfiguration:()Lorg/apache/hadoop/conf/Configuration;
       4: astore        5
       6: aload         5
       8: ldc           #37                 // String hbase.master.event.waiting.time
      10: sipush        1000
      13: invokevirtual #38                 // Method org/apache/hadoop/conf/Configuration.getInt:(Ljava/lang/String;I)I
      16: i2l
      17: lstore        6
      19: aload_0
      20: lload_1
      21: lload         6
      23: aload_3
      24: aload         4
      26: invokestatic  #39                 // Method waitFor:(Lorg/apache/hadoop/hbase/master/procedure/MasterProcedureEnv;JJLjava/lang/String;Lorg/apache/hadoop/hbase/master/procedure/ProcedureSyncWait$Predicate;)Ljava/lang/Object;
      29: areturn

  public static <T> T waitFor(org.apache.hadoop.hbase.master.procedure.MasterProcedureEnv, long, long, java.lang.String, org.apache.hadoop.hbase.master.procedure.ProcedureSyncWait$Predicate<T>) throws java.io.IOException;
    Code:
       0: invokestatic  #40                 // Method org/apache/hadoop/hbase/util/EnvironmentEdgeManager.currentTime:()J
       3: lload_1
       4: ladd
       5: lstore        7
       7: lload         7
       9: lconst_0
      10: lcmp
      11: ifgt          19
      14: ldc2_w        #7                  // long 9223372036854775807l
      17: lstore        7
      19: iconst_0
      20: istore        9
      22: aload         6
      24: invokeinterface #41,  1           // InterfaceMethod org/apache/hadoop/hbase/master/procedure/ProcedureSyncWait$Predicate.evaluate:()Ljava/lang/Object;
      29: astore        10
      31: aload         10
      33: ifnull        50
      36: aload         10
      38: getstatic     #42                 // Field java/lang/Boolean.FALSE:Ljava/lang/Boolean;
      41: invokevirtual #43                 // Method java/lang/Object.equals:(Ljava/lang/Object;)Z
      44: ifne          50
      47: aload         10
      49: areturn
      50: lload_3
      51: invokestatic  #44                 // Method java/lang/Thread.sleep:(J)V
      54: goto          103
      57: astore        11
      59: getstatic     #46                 // Field LOG:Lorg/slf4j/Logger;
      62: new           #16                 // class java/lang/StringBuilder
      65: dup
      66: invokespecial #17                 // Method java/lang/StringBuilder."<init>":()V
      69: ldc           #47                 // String Interrupted while sleeping, waiting on
      71: invokevirtual #19                 // Method java/lang/StringBuilder.append:(Ljava/lang/String;)Ljava/lang/StringBuilder;
      74: aload         5
      76: invokevirtual #19                 // Method java/lang/StringBuilder.append:(Ljava/lang/String;)Ljava/lang/StringBuilder;
      79: invokevirtual #22                 // Method java/lang/StringBuilder.toString:()Ljava/lang/String;
      82: invokeinterface #48,  2           // InterfaceMethod org/slf4j/Logger.warn:(Ljava/lang/String;)V
      87: new           #49                 // class java/io/InterruptedIOException
      90: dup
      91: invokespecial #50                 // Method java/io/InterruptedIOException."<init>":()V
      94: aload         11
      96: invokevirtual #51                 // Method java/io/InterruptedIOException.initCause:(Ljava/lang/Throwable;)Ljava/lang/Throwable;
      99: checkcast     #49                 // class java/io/InterruptedIOException
     102: athrow
     103: getstatic     #46                 // Field LOG:Lorg/slf4j/Logger;
     106: invokeinterface #52,  1           // InterfaceMethod org/slf4j/Logger.isTraceEnabled:()Z
     111: ifeq          145
     114: getstatic     #46                 // Field LOG:Lorg/slf4j/Logger;
     117: new           #16                 // class java/lang/StringBuilder
     120: dup
     121: invokespecial #17                 // Method java/lang/StringBuilder."<init>":()V
     124: ldc           #53                 // String waitFor
     126: invokevirtual #19                 // Method java/lang/StringBuilder.append:(Ljava/lang/String;)Ljava/lang/StringBuilder;
     129: aload         5
     131: invokevirtual #19                 // Method java/lang/StringBuilder.append:(Ljava/lang/String;)Ljava/lang/StringBuilder;
     134: invokevirtual #22                 // Method java/lang/StringBuilder.toString:()Ljava/lang/String;
     137: invokeinterface #54,  2           // InterfaceMethod org/slf4j/Logger.trace:(Ljava/lang/String;)V
     142: goto          178
     145: iload         9
     147: ifne          178
     150: getstatic     #46                 // Field LOG:Lorg/slf4j/Logger;
     153: new           #16                 // class java/lang/StringBuilder
     156: dup
     157: invokespecial #17                 // Method java/lang/StringBuilder."<init>":()V
     160: ldc           #53                 // String waitFor
     162: invokevirtual #19                 // Method java/lang/StringBuilder.append:(Ljava/lang/String;)Ljava/lang/StringBuilder;
     165: aload         5
     167: invokevirtual #19                 // Method java/lang/StringBuilder.append:(Ljava/lang/String;)Ljava/lang/StringBuilder;
     170: invokevirtual #22                 // Method java/lang/StringBuilder.toString:()Ljava/lang/String;
     173: invokeinterface #55,  2           // InterfaceMethod org/slf4j/Logger.debug:(Ljava/lang/String;)V
     178: iconst_1
     179: istore        9
     181: invokestatic  #40                 // Method org/apache/hadoop/hbase/util/EnvironmentEdgeManager.currentTime:()J
     184: lload         7
     186: lcmp
     187: ifge          197
     190: aload_0
     191: invokevirtual #56                 // Method org/apache/hadoop/hbase/master/procedure/MasterProcedureEnv.isRunning:()Z
     194: ifne          22
     197: new           #57                 // class org/apache/hadoop/hbase/exceptions/TimeoutIOException
     200: dup
     201: new           #16                 // class java/lang/StringBuilder
     204: dup
     205: invokespecial #17                 // Method java/lang/StringBuilder."<init>":()V
     208: ldc           #58                 // String Timed out while waiting on
     210: invokevirtual #19                 // Method java/lang/StringBuilder.append:(Ljava/lang/String;)Ljava/lang/StringBuilder;
     213: aload         5
     215: invokevirtual #19                 // Method java/lang/StringBuilder.append:(Ljava/lang/String;)Ljava/lang/StringBuilder;
     218: invokevirtual #22                 // Method java/lang/StringBuilder.toString:()Ljava/lang/String;
     221: invokespecial #59                 // Method org/apache/hadoop/hbase/exceptions/TimeoutIOException."<init>":(Ljava/lang/String;)V
     224: athrow
    Exception table:
       from    to  target type
          50    54    57   Class java/lang/InterruptedException

  protected static void waitMetaRegions(org.apache.hadoop.hbase.master.procedure.MasterProcedureEnv) throws java.io.IOException;
    Code:
       0: aload_0
       1: invokevirtual #32                 // Method org/apache/hadoop/hbase/master/procedure/MasterProcedureEnv.getMasterConfiguration:()Lorg/apache/hadoop/conf/Configuration;
       4: ldc           #60                 // String hbase.client.catalog.timeout
       6: sipush        10000
       9: invokevirtual #38                 // Method org/apache/hadoop/conf/Configuration.getInt:(Ljava/lang/String;I)I
      12: istore_1
      13: aload_0
      14: invokevirtual #61                 // Method org/apache/hadoop/hbase/master/procedure/MasterProcedureEnv.getMasterServices:()Lorg/apache/hadoop/hbase/master/MasterServices;
      17: invokeinterface #62,  1           // InterfaceMethod org/apache/hadoop/hbase/master/MasterServices.getZooKeeper:()Lorg/apache/hadoop/hbase/zookeeper/ZKWatcher;
      22: iload_1
      23: i2l
      24: invokestatic  #63                 // Method org/apache/hadoop/hbase/zookeeper/MetaTableLocator.waitMetaRegionLocation:(Lorg/apache/hadoop/hbase/zookeeper/ZKWatcher;J)Lorg/apache/hadoop/hbase/ServerName;
      27: ifnonnull     38
      30: new           #64                 // class org/apache/hadoop/hbase/NotAllMetaRegionsOnlineException
      33: dup
      34: invokespecial #65                 // Method org/apache/hadoop/hbase/NotAllMetaRegionsOnlineException."<init>":()V
      37: athrow
      38: goto          57
      41: astore_2
      42: new           #49                 // class java/io/InterruptedIOException
      45: dup
      46: invokespecial #50                 // Method java/io/InterruptedIOException."<init>":()V
      49: aload_2
      50: invokevirtual #51                 // Method java/io/InterruptedIOException.initCause:(Ljava/lang/Throwable;)Ljava/lang/Throwable;
      53: checkcast     #49                 // class java/io/InterruptedIOException
      56: athrow
      57: return
    Exception table:
       from    to  target type
          13    38    41   Class java/lang/InterruptedException

  protected static void waitRegionInTransition(org.apache.hadoop.hbase.master.procedure.MasterProcedureEnv, java.util.List<org.apache.hadoop.hbase.client.RegionInfo>) throws java.io.IOException;
    Code:
       0: aload_0
       1: invokevirtual #66                 // Method org/apache/hadoop/hbase/master/procedure/MasterProcedureEnv.getAssignmentManager:()Lorg/apache/hadoop/hbase/master/assignment/AssignmentManager;
       4: invokevirtual #67                 // Method org/apache/hadoop/hbase/master/assignment/AssignmentManager.getRegionStates:()Lorg/apache/hadoop/hbase/master/assignment/RegionStates;
       7: astore_2
       8: aload_1
       9: invokeinterface #68,  1           // InterfaceMethod java/util/List.iterator:()Ljava/util/Iterator;
      14: astore_3
      15: aload_3
      16: invokeinterface #69,  1           // InterfaceMethod java/util/Iterator.hasNext:()Z
      21: ifeq          83
      24: aload_3
      25: invokeinterface #70,  1           // InterfaceMethod java/util/Iterator.next:()Ljava/lang/Object;
      30: checkcast     #71                 // class org/apache/hadoop/hbase/client/RegionInfo
      33: astore        4
      35: aload_0
      36: new           #16                 // class java/lang/StringBuilder
      39: dup
      40: invokespecial #17                 // Method java/lang/StringBuilder."<init>":()V
      43: ldc           #72                 // String regions
      45: invokevirtual #19                 // Method java/lang/StringBuilder.append:(Ljava/lang/String;)Ljava/lang/StringBuilder;
      48: aload         4
      50: invokeinterface #73,  1           // InterfaceMethod org/apache/hadoop/hbase/client/RegionInfo.getRegionNameAsString:()Ljava/lang/String;
      55: invokevirtual #19                 // Method java/lang/StringBuilder.append:(Ljava/lang/String;)Ljava/lang/StringBuilder;
      58: ldc           #74                 // String  in transition
      60: invokevirtual #19                 // Method java/lang/StringBuilder.append:(Ljava/lang/String;)Ljava/lang/StringBuilder;
      63: invokevirtual #22                 // Method java/lang/StringBuilder.toString:()Ljava/lang/String;
      66: new           #75                 // class org/apache/hadoop/hbase/master/procedure/ProcedureSyncWait$2
      69: dup
      70: aload_2
      71: aload         4
      73: invokespecial #76                 // Method org/apache/hadoop/hbase/master/procedure/ProcedureSyncWait$2."<init>":(Lorg/apache/hadoop/hbase/master/assignment/RegionStates;Lorg/apache/hadoop/hbase/client/RegionInfo;)V
      76: invokestatic  #77                 // Method waitFor:(Lorg/apache/hadoop/hbase/master/procedure/MasterProcedureEnv;Ljava/lang/String;Lorg/apache/hadoop/hbase/master/procedure/ProcedureSyncWait$Predicate;)Ljava/lang/Object;
      79: pop
      80: goto          15
      83: return

  protected static org.apache.hadoop.hbase.quotas.MasterQuotaManager getMasterQuotaManager(org.apache.hadoop.hbase.master.procedure.MasterProcedureEnv) throws java.io.IOException;
    Code:
       0: aload_0
       1: ldc           #78                 // String quota manager to be available
       3: new           #79                 // class org/apache/hadoop/hbase/master/procedure/ProcedureSyncWait$3
       6: dup
       7: aload_0
       8: invokespecial #80                 // Method org/apache/hadoop/hbase/master/procedure/ProcedureSyncWait$3."<init>":(Lorg/apache/hadoop/hbase/master/procedure/MasterProcedureEnv;)V
      11: invokestatic  #77                 // Method waitFor:(Lorg/apache/hadoop/hbase/master/procedure/MasterProcedureEnv;Ljava/lang/String;Lorg/apache/hadoop/hbase/master/procedure/ProcedureSyncWait$Predicate;)Ljava/lang/Object;
      14: checkcast     #81                 // class org/apache/hadoop/hbase/quotas/MasterQuotaManager
      17: areturn

  static {};
    Code:
       0: ldc           #82                 // class org/apache/hadoop/hbase/master/procedure/ProcedureSyncWait
       2: invokestatic  #83                 // Method org/slf4j/LoggerFactory.getLogger:(Ljava/lang/Class;)Lorg/slf4j/Logger;
       5: putstatic     #46                 // Field LOG:Lorg/slf4j/Logger;
       8: return
}
