Compiled from "ProcedureUtil.java"
class org.apache.hadoop.hbase.procedure2.ProcedureUtil$StateSerializer implements org.apache.hadoop.hbase.procedure2.ProcedureStateSerializer {
  public org.apache.hadoop.hbase.procedure2.ProcedureUtil$StateSerializer(org.apache.hadoop.hbase.shaded.protobuf.generated.ProcedureProtos$Procedure$Builder);
    Code:
       0: aload_0
       1: invokespecial #1                  // Method java/lang/Object."<init>":()V
       4: aload_0
       5: aload_1
       6: putfield      #2                  // Field builder:Lorg/apache/hadoop/hbase/shaded/protobuf/generated/ProcedureProtos$Procedure$Builder;
       9: return

  public void serialize(org.apache.hbase.thirdparty.com.google.protobuf.Message) throws java.io.IOException;
    Code:
       0: aload_1
       1: invokestatic  #3                  // Method org/apache/hbase/thirdparty/com/google/protobuf/Any.pack:(Lorg/apache/hbase/thirdparty/com/google/protobuf/Message;)Lorg/apache/hbase/thirdparty/com/google/protobuf/Any;
       4: astore_2
       5: aload_0
       6: getfield      #2                  // Field builder:Lorg/apache/hadoop/hbase/shaded/protobuf/generated/ProcedureProtos$Procedure$Builder;
       9: aload_2
      10: invokevirtual #4                  // Method org/apache/hadoop/hbase/shaded/protobuf/generated/ProcedureProtos$Procedure$Builder.addStateMessage:(Lorg/apache/hbase/thirdparty/com/google/protobuf/Any;)Lorg/apache/hadoop/hbase/shaded/protobuf/generated/ProcedureProtos$Procedure$Builder;
      13: pop
      14: return

  public <M extends org.apache.hbase.thirdparty.com.google.protobuf.Message> M deserialize(java.lang.Class<M>) throws java.io.IOException;
    Code:
       0: aload_0
       1: getfield      #5                  // Field deserializeIndex:I
       4: aload_0
       5: getfield      #2                  // Field builder:Lorg/apache/hadoop/hbase/shaded/protobuf/generated/ProcedureProtos$Procedure$Builder;
       8: invokevirtual #6                  // Method org/apache/hadoop/hbase/shaded/protobuf/generated/ProcedureProtos$Procedure$Builder.getStateMessageCount:()I
      11: if_icmplt     44
      14: new           #7                  // class java/io/IOException
      17: dup
      18: new           #8                  // class java/lang/StringBuilder
      21: dup
      22: invokespecial #9                  // Method java/lang/StringBuilder."<init>":()V
      25: ldc           #10                 // String Invalid state message index:
      27: invokevirtual #11                 // Method java/lang/StringBuilder.append:(Ljava/lang/String;)Ljava/lang/StringBuilder;
      30: aload_0
      31: getfield      #5                  // Field deserializeIndex:I
      34: invokevirtual #12                 // Method java/lang/StringBuilder.append:(I)Ljava/lang/StringBuilder;
      37: invokevirtual #13                 // Method java/lang/StringBuilder.toString:()Ljava/lang/String;
      40: invokespecial #14                 // Method java/io/IOException."<init>":(Ljava/lang/String;)V
      43: athrow
      44: aload_0
      45: getfield      #2                  // Field builder:Lorg/apache/hadoop/hbase/shaded/protobuf/generated/ProcedureProtos$Procedure$Builder;
      48: aload_0
      49: dup
      50: getfield      #5                  // Field deserializeIndex:I
      53: dup_x1
      54: iconst_1
      55: iadd
      56: putfield      #5                  // Field deserializeIndex:I
      59: invokevirtual #15                 // Method org/apache/hadoop/hbase/shaded/protobuf/generated/ProcedureProtos$Procedure$Builder.getStateMessage:(I)Lorg/apache/hbase/thirdparty/com/google/protobuf/Any;
      62: astore_2
      63: aload_2
      64: aload_1
      65: invokevirtual #16                 // Method org/apache/hbase/thirdparty/com/google/protobuf/Any.unpack:(Ljava/lang/Class;)Lorg/apache/hbase/thirdparty/com/google/protobuf/Message;
      68: areturn
      69: astore_2
      70: aload_2
      71: invokevirtual #18                 // Method org/apache/hbase/thirdparty/com/google/protobuf/InvalidProtocolBufferException.unwrapIOException:()Ljava/io/IOException;
      74: athrow
    Exception table:
       from    to  target type
          44    68    69   Class org/apache/hbase/thirdparty/com/google/protobuf/InvalidProtocolBufferException
}
