Compiled from "ProcedureWALLoaderPerformanceEvaluation.java"
public class org.apache.hadoop.hbase.procedure2.store.wal.ProcedureWALLoaderPerformanceEvaluation extends org.apache.hadoop.hbase.util.AbstractHBaseTool {
  protected static final org.apache.hadoop.hbase.HBaseCommonTestingUtility UTIL;

  public static int DEFAULT_NUM_PROCS;

  public static org.apache.hbase.thirdparty.org.apache.commons.cli.Option NUM_PROCS_OPTION;

  public static int DEFAULT_NUM_WALS;

  public static org.apache.hbase.thirdparty.org.apache.commons.cli.Option NUM_WALS_OPTION;

  public static int DEFAULT_STATE_SIZE;

  public static org.apache.hbase.thirdparty.org.apache.commons.cli.Option STATE_SIZE_OPTION;

  public static int DEFAULT_UPDATES_PER_PROC;

  public static org.apache.hbase.thirdparty.org.apache.commons.cli.Option UPDATES_PER_PROC_OPTION;

  public static double DEFAULT_DELETE_PROCS_FRACTION;

  public static org.apache.hbase.thirdparty.org.apache.commons.cli.Option DELETE_PROCS_FRACTION_OPTION;

  public int numProcs;

  public int updatesPerProc;

  public double deleteProcsFraction;

  public int numWals;

  static byte[] serializedState;

  public org.apache.hadoop.hbase.procedure2.store.wal.ProcedureWALLoaderPerformanceEvaluation();
    Code:
       0: aload_0
       1: invokespecial #1                  // Method org/apache/hadoop/hbase/util/AbstractHBaseTool."<init>":()V
       4: return

  protected void addOptions();
    Code:
       0: aload_0
       1: getstatic     #2                  // Field NUM_PROCS_OPTION:Lorg/apache/hbase/thirdparty/org/apache/commons/cli/Option;
       4: invokevirtual #3                  // Method addOption:(Lorg/apache/hbase/thirdparty/org/apache/commons/cli/Option;)V
       7: aload_0
       8: getstatic     #4                  // Field UPDATES_PER_PROC_OPTION:Lorg/apache/hbase/thirdparty/org/apache/commons/cli/Option;
      11: invokevirtual #3                  // Method addOption:(Lorg/apache/hbase/thirdparty/org/apache/commons/cli/Option;)V
      14: aload_0
      15: getstatic     #5                  // Field DELETE_PROCS_FRACTION_OPTION:Lorg/apache/hbase/thirdparty/org/apache/commons/cli/Option;
      18: invokevirtual #3                  // Method addOption:(Lorg/apache/hbase/thirdparty/org/apache/commons/cli/Option;)V
      21: aload_0
      22: getstatic     #6                  // Field NUM_WALS_OPTION:Lorg/apache/hbase/thirdparty/org/apache/commons/cli/Option;
      25: invokevirtual #3                  // Method addOption:(Lorg/apache/hbase/thirdparty/org/apache/commons/cli/Option;)V
      28: aload_0
      29: getstatic     #7                  // Field STATE_SIZE_OPTION:Lorg/apache/hbase/thirdparty/org/apache/commons/cli/Option;
      32: invokevirtual #3                  // Method addOption:(Lorg/apache/hbase/thirdparty/org/apache/commons/cli/Option;)V
      35: return

  protected void processOptions(org.apache.hbase.thirdparty.org.apache.commons.cli.CommandLine);
    Code:
       0: aload_0
       1: aload_0
       2: aload_1
       3: getstatic     #2                  // Field NUM_PROCS_OPTION:Lorg/apache/hbase/thirdparty/org/apache/commons/cli/Option;
       6: invokevirtual #8                  // Method org/apache/hbase/thirdparty/org/apache/commons/cli/Option.getOpt:()Ljava/lang/String;
       9: getstatic     #9                  // Field DEFAULT_NUM_PROCS:I
      12: invokevirtual #10                 // Method getOptionAsInt:(Lorg/apache/hbase/thirdparty/org/apache/commons/cli/CommandLine;Ljava/lang/String;I)I
      15: putfield      #11                 // Field numProcs:I
      18: aload_0
      19: aload_0
      20: aload_1
      21: getstatic     #6                  // Field NUM_WALS_OPTION:Lorg/apache/hbase/thirdparty/org/apache/commons/cli/Option;
      24: invokevirtual #8                  // Method org/apache/hbase/thirdparty/org/apache/commons/cli/Option.getOpt:()Ljava/lang/String;
      27: getstatic     #12                 // Field DEFAULT_NUM_WALS:I
      30: invokevirtual #10                 // Method getOptionAsInt:(Lorg/apache/hbase/thirdparty/org/apache/commons/cli/CommandLine;Ljava/lang/String;I)I
      33: putfield      #13                 // Field numWals:I
      36: aload_0
      37: aload_1
      38: getstatic     #7                  // Field STATE_SIZE_OPTION:Lorg/apache/hbase/thirdparty/org/apache/commons/cli/Option;
      41: invokevirtual #8                  // Method org/apache/hbase/thirdparty/org/apache/commons/cli/Option.getOpt:()Ljava/lang/String;
      44: getstatic     #14                 // Field DEFAULT_STATE_SIZE:I
      47: invokevirtual #10                 // Method getOptionAsInt:(Lorg/apache/hbase/thirdparty/org/apache/commons/cli/CommandLine;Ljava/lang/String;I)I
      50: istore_2
      51: iload_2
      52: newarray       byte
      54: putstatic     #15                 // Field serializedState:[B
      57: aload_0
      58: aload_0
      59: aload_1
      60: getstatic     #4                  // Field UPDATES_PER_PROC_OPTION:Lorg/apache/hbase/thirdparty/org/apache/commons/cli/Option;
      63: invokevirtual #8                  // Method org/apache/hbase/thirdparty/org/apache/commons/cli/Option.getOpt:()Ljava/lang/String;
      66: getstatic     #16                 // Field DEFAULT_UPDATES_PER_PROC:I
      69: invokevirtual #10                 // Method getOptionAsInt:(Lorg/apache/hbase/thirdparty/org/apache/commons/cli/CommandLine;Ljava/lang/String;I)I
      72: putfield      #17                 // Field updatesPerProc:I
      75: aload_0
      76: aload_0
      77: aload_1
      78: getstatic     #5                  // Field DELETE_PROCS_FRACTION_OPTION:Lorg/apache/hbase/thirdparty/org/apache/commons/cli/Option;
      81: invokevirtual #8                  // Method org/apache/hbase/thirdparty/org/apache/commons/cli/Option.getOpt:()Ljava/lang/String;
      84: getstatic     #18                 // Field DEFAULT_DELETE_PROCS_FRACTION:D
      87: invokevirtual #19                 // Method getOptionAsDouble:(Lorg/apache/hbase/thirdparty/org/apache/commons/cli/CommandLine;Ljava/lang/String;D)D
      90: putfield      #20                 // Field deleteProcsFraction:D
      93: aload_0
      94: invokespecial #21                 // Method setupConf:()V
      97: return

  public void setUpProcedureStore() throws java.io.IOException;
    Code:
       0: getstatic     #29                 // Field UTIL:Lorg/apache/hadoop/hbase/HBaseCommonTestingUtility;
       3: invokevirtual #30                 // Method org/apache/hadoop/hbase/HBaseCommonTestingUtility.getDataTestDir:()Lorg/apache/hadoop/fs/Path;
       6: astore_1
       7: aload_1
       8: aload_0
       9: getfield      #22                 // Field conf:Lorg/apache/hadoop/conf/Configuration;
      12: invokevirtual #31                 // Method org/apache/hadoop/fs/Path.getFileSystem:(Lorg/apache/hadoop/conf/Configuration;)Lorg/apache/hadoop/fs/FileSystem;
      15: astore_2
      16: new           #32                 // class org/apache/hadoop/fs/Path
      19: dup
      20: aload_1
      21: ldc           #33                 // String proc-logs
      23: invokespecial #34                 // Method org/apache/hadoop/fs/Path."<init>":(Lorg/apache/hadoop/fs/Path;Ljava/lang/String;)V
      26: astore_3
      27: getstatic     #35                 // Field java/lang/System.out:Ljava/io/PrintStream;
      30: new           #36                 // class java/lang/StringBuilder
      33: dup
      34: invokespecial #37                 // Method java/lang/StringBuilder."<init>":()V
      37: ldc           #38                 // String \n\nLogs directory :
      39: invokevirtual #39                 // Method java/lang/StringBuilder.append:(Ljava/lang/String;)Ljava/lang/StringBuilder;
      42: aload_3
      43: invokevirtual #40                 // Method org/apache/hadoop/fs/Path.toString:()Ljava/lang/String;
      46: invokevirtual #39                 // Method java/lang/StringBuilder.append:(Ljava/lang/String;)Ljava/lang/StringBuilder;
      49: ldc           #41                 // String \n\n
      51: invokevirtual #39                 // Method java/lang/StringBuilder.append:(Ljava/lang/String;)Ljava/lang/StringBuilder;
      54: invokevirtual #42                 // Method java/lang/StringBuilder.toString:()Ljava/lang/String;
      57: invokevirtual #43                 // Method java/io/PrintStream.println:(Ljava/lang/String;)V
      60: aload_2
      61: aload_3
      62: iconst_1
      63: invokevirtual #44                 // Method org/apache/hadoop/fs/FileSystem.delete:(Lorg/apache/hadoop/fs/Path;Z)Z
      66: pop
      67: aload_0
      68: aload_0
      69: getfield      #22                 // Field conf:Lorg/apache/hadoop/conf/Configuration;
      72: aload_3
      73: invokestatic  #45                 // Method org/apache/hadoop/hbase/procedure2/ProcedureTestingUtility.createWalStore:(Lorg/apache/hadoop/conf/Configuration;Lorg/apache/hadoop/fs/Path;)Lorg/apache/hadoop/hbase/procedure2/store/wal/WALProcedureStore;
      76: putfield      #46                 // Field store:Lorg/apache/hadoop/hbase/procedure2/store/wal/WALProcedureStore;
      79: aload_0
      80: getfield      #46                 // Field store:Lorg/apache/hadoop/hbase/procedure2/store/wal/WALProcedureStore;
      83: iconst_1
      84: invokevirtual #47                 // Method org/apache/hadoop/hbase/procedure2/store/wal/WALProcedureStore.start:(I)V
      87: aload_0
      88: getfield      #46                 // Field store:Lorg/apache/hadoop/hbase/procedure2/store/wal/WALProcedureStore;
      91: invokevirtual #48                 // Method org/apache/hadoop/hbase/procedure2/store/wal/WALProcedureStore.recoverLease:()V
      94: aload_0
      95: getfield      #46                 // Field store:Lorg/apache/hadoop/hbase/procedure2/store/wal/WALProcedureStore;
      98: new           #49                 // class org/apache/hadoop/hbase/procedure2/store/wal/ProcedureWALLoaderPerformanceEvaluation$LoadCounter
     101: dup
     102: invokespecial #50                 // Method org/apache/hadoop/hbase/procedure2/store/wal/ProcedureWALLoaderPerformanceEvaluation$LoadCounter."<init>":()V
     105: invokevirtual #51                 // Method org/apache/hadoop/hbase/procedure2/store/wal/WALProcedureStore.load:(Lorg/apache/hadoop/hbase/procedure2/store/ProcedureStore$ProcedureLoader;)V
     108: return

  public void tearDownProcedureStore();
    Code:
       0: aload_0
       1: getfield      #46                 // Field store:Lorg/apache/hadoop/hbase/procedure2/store/wal/WALProcedureStore;
       4: iconst_0
       5: invokevirtual #92                 // Method org/apache/hadoop/hbase/procedure2/store/wal/WALProcedureStore.stop:(Z)V
       8: aload_0
       9: getfield      #46                 // Field store:Lorg/apache/hadoop/hbase/procedure2/store/wal/WALProcedureStore;
      12: invokevirtual #102                // Method org/apache/hadoop/hbase/procedure2/store/wal/WALProcedureStore.getFileSystem:()Lorg/apache/hadoop/fs/FileSystem;
      15: aload_0
      16: getfield      #46                 // Field store:Lorg/apache/hadoop/hbase/procedure2/store/wal/WALProcedureStore;
      19: invokevirtual #103                // Method org/apache/hadoop/hbase/procedure2/store/wal/WALProcedureStore.getWALDir:()Lorg/apache/hadoop/fs/Path;
      22: iconst_1
      23: invokevirtual #44                 // Method org/apache/hadoop/fs/FileSystem.delete:(Lorg/apache/hadoop/fs/Path;Z)Z
      26: pop
      27: goto          75
      30: astore_1
      31: getstatic     #105                // Field java/lang/System.err:Ljava/io/PrintStream;
      34: new           #36                 // class java/lang/StringBuilder
      37: dup
      38: invokespecial #37                 // Method java/lang/StringBuilder."<init>":()V
      41: ldc           #106                // String Error: Couldn't delete log dir. You can delete it manually to free up disk space. Location:
      43: invokevirtual #39                 // Method java/lang/StringBuilder.append:(Ljava/lang/String;)Ljava/lang/StringBuilder;
      46: aload_0
      47: getfield      #46                 // Field store:Lorg/apache/hadoop/hbase/procedure2/store/wal/WALProcedureStore;
      50: invokevirtual #103                // Method org/apache/hadoop/hbase/procedure2/store/wal/WALProcedureStore.getWALDir:()Lorg/apache/hadoop/fs/Path;
      53: invokevirtual #40                 // Method org/apache/hadoop/fs/Path.toString:()Ljava/lang/String;
      56: invokevirtual #39                 // Method java/lang/StringBuilder.append:(Ljava/lang/String;)Ljava/lang/StringBuilder;
      59: invokevirtual #42                 // Method java/lang/StringBuilder.toString:()Ljava/lang/String;
      62: invokevirtual #43                 // Method java/io/PrintStream.println:(Ljava/lang/String;)V
      65: getstatic     #105                // Field java/lang/System.err:Ljava/io/PrintStream;
      68: aload_1
      69: invokevirtual #107                // Method java/io/IOException.toString:()Ljava/lang/String;
      72: invokevirtual #43                 // Method java/io/PrintStream.println:(Ljava/lang/String;)V
      75: return
    Exception table:
       from    to  target type
           8    27    30   Class java/io/IOException

  protected int doWork();
    Code:
       0: aload_0
       1: invokevirtual #108                // Method setUpProcedureStore:()V
       4: aload_0
       5: invokespecial #109                // Method writeWals:()V
       8: aload_0
       9: new           #49                 // class org/apache/hadoop/hbase/procedure2/store/wal/ProcedureWALLoaderPerformanceEvaluation$LoadCounter
      12: dup
      13: invokespecial #50                 // Method org/apache/hadoop/hbase/procedure2/store/wal/ProcedureWALLoaderPerformanceEvaluation$LoadCounter."<init>":()V
      16: invokespecial #110                // Method storeRestart:(Lorg/apache/hadoop/hbase/procedure2/store/ProcedureStore$ProcedureLoader;)V
      19: iconst_0
      20: istore_1
      21: aload_0
      22: invokevirtual #112                // Method tearDownProcedureStore:()V
      25: iload_1
      26: ireturn
      27: astore_1
      28: aload_1
      29: invokevirtual #113                // Method java/io/IOException.printStackTrace:()V
      32: iconst_1
      33: istore_2
      34: aload_0
      35: invokevirtual #112                // Method tearDownProcedureStore:()V
      38: iload_2
      39: ireturn
      40: astore_3
      41: aload_0
      42: invokevirtual #112                // Method tearDownProcedureStore:()V
      45: aload_3
      46: athrow
    Exception table:
       from    to  target type
           0    21    27   Class java/io/IOException
           0    21    40   any
          27    34    40   any

  public static void main(java.lang.String[]) throws java.io.IOException;
    Code:
       0: new           #114                // class org/apache/hadoop/hbase/procedure2/store/wal/ProcedureWALLoaderPerformanceEvaluation
       3: dup
       4: invokespecial #115                // Method "<init>":()V
       7: astore_1
       8: aload_1
       9: getstatic     #29                 // Field UTIL:Lorg/apache/hadoop/hbase/HBaseCommonTestingUtility;
      12: invokevirtual #116                // Method org/apache/hadoop/hbase/HBaseCommonTestingUtility.getConfiguration:()Lorg/apache/hadoop/conf/Configuration;
      15: invokevirtual #117                // Method setConf:(Lorg/apache/hadoop/conf/Configuration;)V
      18: aload_1
      19: aload_0
      20: invokevirtual #118                // Method run:([Ljava/lang/String;)I
      23: pop
      24: return

  static {};
    Code:
       0: new           #119                // class org/apache/hadoop/hbase/HBaseCommonTestingUtility
       3: dup
       4: invokespecial #120                // Method org/apache/hadoop/hbase/HBaseCommonTestingUtility."<init>":()V
       7: putstatic     #29                 // Field UTIL:Lorg/apache/hadoop/hbase/HBaseCommonTestingUtility;
      10: ldc           #121                // int 1000000
      12: putstatic     #9                  // Field DEFAULT_NUM_PROCS:I
      15: new           #122                // class org/apache/hbase/thirdparty/org/apache/commons/cli/Option
      18: dup
      19: ldc           #123                // String procs
      21: iconst_1
      22: new           #36                 // class java/lang/StringBuilder
      25: dup
      26: invokespecial #37                 // Method java/lang/StringBuilder."<init>":()V
      29: ldc           #124                // String Total number of procedures. Default:
      31: invokevirtual #39                 // Method java/lang/StringBuilder.append:(Ljava/lang/String;)Ljava/lang/StringBuilder;
      34: getstatic     #9                  // Field DEFAULT_NUM_PROCS:I
      37: invokevirtual #88                 // Method java/lang/StringBuilder.append:(I)Ljava/lang/StringBuilder;
      40: invokevirtual #42                 // Method java/lang/StringBuilder.toString:()Ljava/lang/String;
      43: invokespecial #125                // Method org/apache/hbase/thirdparty/org/apache/commons/cli/Option."<init>":(Ljava/lang/String;ZLjava/lang/String;)V
      46: putstatic     #2                  // Field NUM_PROCS_OPTION:Lorg/apache/hbase/thirdparty/org/apache/commons/cli/Option;
      49: iconst_0
      50: putstatic     #12                 // Field DEFAULT_NUM_WALS:I
      53: new           #122                // class org/apache/hbase/thirdparty/org/apache/commons/cli/Option
      56: dup
      57: ldc           #126                // String wals
      59: iconst_1
      60: new           #36                 // class java/lang/StringBuilder
      63: dup
      64: invokespecial #37                 // Method java/lang/StringBuilder."<init>":()V
      67: ldc           #127                // String Number of WALs to write. If -ve or 0, uses hbase.procedure.store.wal.roll.threshold conf to roll the logs. Default:
      69: invokevirtual #39                 // Method java/lang/StringBuilder.append:(Ljava/lang/String;)Ljava/lang/StringBuilder;
      72: getstatic     #12                 // Field DEFAULT_NUM_WALS:I
      75: invokevirtual #88                 // Method java/lang/StringBuilder.append:(I)Ljava/lang/StringBuilder;
      78: invokevirtual #42                 // Method java/lang/StringBuilder.toString:()Ljava/lang/String;
      81: invokespecial #125                // Method org/apache/hbase/thirdparty/org/apache/commons/cli/Option."<init>":(Ljava/lang/String;ZLjava/lang/String;)V
      84: putstatic     #6                  // Field NUM_WALS_OPTION:Lorg/apache/hbase/thirdparty/org/apache/commons/cli/Option;
      87: sipush        1024
      90: putstatic     #14                 // Field DEFAULT_STATE_SIZE:I
      93: new           #122                // class org/apache/hbase/thirdparty/org/apache/commons/cli/Option
      96: dup
      97: ldc           #128                // String state_size
      99: iconst_1
     100: new           #36                 // class java/lang/StringBuilder
     103: dup
     104: invokespecial #37                 // Method java/lang/StringBuilder."<init>":()V
     107: ldc           #129                // String Size of serialized state in bytes to write on update. Default:
     109: invokevirtual #39                 // Method java/lang/StringBuilder.append:(Ljava/lang/String;)Ljava/lang/StringBuilder;
     112: getstatic     #14                 // Field DEFAULT_STATE_SIZE:I
     115: invokevirtual #88                 // Method java/lang/StringBuilder.append:(I)Ljava/lang/StringBuilder;
     118: ldc           #130                // String  bytes
     120: invokevirtual #39                 // Method java/lang/StringBuilder.append:(Ljava/lang/String;)Ljava/lang/StringBuilder;
     123: invokevirtual #42                 // Method java/lang/StringBuilder.toString:()Ljava/lang/String;
     126: invokespecial #125                // Method org/apache/hbase/thirdparty/org/apache/commons/cli/Option."<init>":(Ljava/lang/String;ZLjava/lang/String;)V
     129: putstatic     #7                  // Field STATE_SIZE_OPTION:Lorg/apache/hbase/thirdparty/org/apache/commons/cli/Option;
     132: iconst_5
     133: putstatic     #16                 // Field DEFAULT_UPDATES_PER_PROC:I
     136: new           #122                // class org/apache/hbase/thirdparty/org/apache/commons/cli/Option
     139: dup
     140: ldc           #131                // String updates_per_proc
     142: iconst_1
     143: new           #36                 // class java/lang/StringBuilder
     146: dup
     147: invokespecial #37                 // Method java/lang/StringBuilder."<init>":()V
     150: ldc           #132                // String Number of update states to write for each proc. Default:
     152: invokevirtual #39                 // Method java/lang/StringBuilder.append:(Ljava/lang/String;)Ljava/lang/StringBuilder;
     155: getstatic     #16                 // Field DEFAULT_UPDATES_PER_PROC:I
     158: invokevirtual #88                 // Method java/lang/StringBuilder.append:(I)Ljava/lang/StringBuilder;
     161: invokevirtual #42                 // Method java/lang/StringBuilder.toString:()Ljava/lang/String;
     164: invokespecial #125                // Method org/apache/hbase/thirdparty/org/apache/commons/cli/Option."<init>":(Ljava/lang/String;ZLjava/lang/String;)V
     167: putstatic     #4                  // Field UPDATES_PER_PROC_OPTION:Lorg/apache/hbase/thirdparty/org/apache/commons/cli/Option;
     170: ldc2_w        #133                // double 0.5d
     173: putstatic     #18                 // Field DEFAULT_DELETE_PROCS_FRACTION:D
     176: new           #122                // class org/apache/hbase/thirdparty/org/apache/commons/cli/Option
     179: dup
     180: ldc           #135                // String delete_procs_fraction
     182: iconst_1
     183: new           #36                 // class java/lang/StringBuilder
     186: dup
     187: invokespecial #37                 // Method java/lang/StringBuilder."<init>":()V
     190: ldc           #136                // String Fraction of procs for which to write delete state. Distribution of procs chosen for delete is uniform across all procs. Default:
     192: invokevirtual #39                 // Method java/lang/StringBuilder.append:(Ljava/lang/String;)Ljava/lang/StringBuilder;
     195: getstatic     #18                 // Field DEFAULT_DELETE_PROCS_FRACTION:D
     198: invokevirtual #137                // Method java/lang/StringBuilder.append:(D)Ljava/lang/StringBuilder;
     201: invokevirtual #42                 // Method java/lang/StringBuilder.toString:()Ljava/lang/String;
     204: invokespecial #125                // Method org/apache/hbase/thirdparty/org/apache/commons/cli/Option."<init>":(Ljava/lang/String;ZLjava/lang/String;)V
     207: putstatic     #5                  // Field DELETE_PROCS_FRACTION_OPTION:Lorg/apache/hbase/thirdparty/org/apache/commons/cli/Option;
     210: return
}
