Compiled from "procedures_jsp.java"
public final class org.apache.hadoop.hbase.generated.master.procedures_jsp extends org.apache.jasper.runtime.HttpJspBase implements org.apache.jasper.runtime.JspSourceDependent {
  public org.apache.hadoop.hbase.generated.master.procedures_jsp();
    Code:
       0: aload_0
       1: invokespecial #1                  // Method org/apache/jasper/runtime/HttpJspBase."<init>":()V
       4: return

  public java.util.List<java.lang.String> getDependants();
    Code:
       0: getstatic     #2                  // Field _jspx_dependants:Ljava/util/List;
       3: areturn

  public void _jspService(javax.servlet.http.HttpServletRequest, javax.servlet.http.HttpServletResponse) throws java.io.IOException, javax.servlet.ServletException;
    Code:
       0: aconst_null
       1: astore_3
       2: aconst_null
       3: astore        4
       5: aconst_null
       6: astore        5
       8: aconst_null
       9: astore        6
      11: aconst_null
      12: astore        7
      14: aload_0
      15: astore        8
      17: aconst_null
      18: astore        9
      20: aconst_null
      21: astore        10
      23: aload_2
      24: ldc           #3                  // String text/html;charset=UTF-8
      26: invokeinterface #4,  2            // InterfaceMethod javax/servlet/http/HttpServletResponse.setContentType:(Ljava/lang/String;)V
      31: getstatic     #5                  // Field _jspxFactory:Ljavax/servlet/jsp/JspFactory;
      34: aload_0
      35: aload_1
      36: aload_2
      37: aconst_null
      38: iconst_1
      39: sipush        8192
      42: iconst_1
      43: invokevirtual #6                  // Method javax/servlet/jsp/JspFactory.getPageContext:(Ljavax/servlet/Servlet;Ljavax/servlet/ServletRequest;Ljavax/servlet/ServletResponse;Ljava/lang/String;ZIZ)Ljavax/servlet/jsp/PageContext;
      46: astore_3
      47: aload_3
      48: astore        10
      50: aload_3
      51: invokevirtual #7                  // Method javax/servlet/jsp/PageContext.getServletContext:()Ljavax/servlet/ServletContext;
      54: astore        5
      56: aload_3
      57: invokevirtual #8                  // Method javax/servlet/jsp/PageContext.getServletConfig:()Ljavax/servlet/ServletConfig;
      60: astore        6
      62: aload_3
      63: invokevirtual #9                  // Method javax/servlet/jsp/PageContext.getSession:()Ljavax/servlet/http/HttpSession;
      66: astore        4
      68: aload_3
      69: invokevirtual #10                 // Method javax/servlet/jsp/PageContext.getOut:()Ljavax/servlet/jsp/JspWriter;
      72: astore        7
      74: aload         7
      76: astore        9
      78: aload_0
      79: aload         5
      81: ldc           #11                 // String com.sun.appserv.jsp.resource.injector
      83: invokeinterface #12,  2           // InterfaceMethod javax/servlet/ServletContext.getAttribute:(Ljava/lang/String;)Ljava/lang/Object;
      88: checkcast     #13                 // class org/glassfish/jsp/api/ResourceInjector
      91: putfield      #14                 // Field _jspx_resourceInjector:Lorg/glassfish/jsp/api/ResourceInjector;
      94: aload         7
      96: bipush        10
      98: invokevirtual #15                 // Method javax/servlet/jsp/JspWriter.write:(I)V
     101: aload         7
     103: bipush        10
     105: invokevirtual #15                 // Method javax/servlet/jsp/JspWriter.write:(I)V
     108: aload_0
     109: invokevirtual #16                 // Method getServletContext:()Ljavax/servlet/ServletContext;
     112: ldc           #18                 // String master
     114: invokeinterface #12,  2           // InterfaceMethod javax/servlet/ServletContext.getAttribute:(Ljava/lang/String;)Ljava/lang/Object;
     119: checkcast     #17                 // class org/apache/hadoop/hbase/master/HMaster
     122: astore        11
     124: aload         11
     126: invokevirtual #19                 // Method org/apache/hadoop/hbase/master/HMaster.getMasterProcedureExecutor:()Lorg/apache/hadoop/hbase/procedure2/ProcedureExecutor;
     129: astore        12
     131: aload         11
     133: invokevirtual #20                 // Method org/apache/hadoop/hbase/master/HMaster.getWalProcedureStore:()Lorg/apache/hadoop/hbase/procedure2/store/wal/WALProcedureStore;
     136: astore        13
     138: aload         13
     140: invokevirtual #21                 // Method org/apache/hadoop/hbase/procedure2/store/wal/WALProcedureStore.getSyncMetrics:()Ljava/util/ArrayList;
     143: astore        14
     145: aload         13
     147: invokevirtual #22                 // Method org/apache/hadoop/hbase/procedure2/store/wal/WALProcedureStore.getMillisToNextPeriodicRoll:()J
     150: lstore        15
     152: aload         13
     154: invokevirtual #23                 // Method org/apache/hadoop/hbase/procedure2/store/wal/WALProcedureStore.getMillisFromLastRoll:()J
     157: lstore        17
     159: aload         13
     161: invokevirtual #24                 // Method org/apache/hadoop/hbase/procedure2/store/wal/WALProcedureStore.getActiveLogs:()Ljava/util/ArrayList;
     164: astore        19
     166: aload         13
     168: invokevirtual #25                 // Method org/apache/hadoop/hbase/procedure2/store/wal/WALProcedureStore.getCorruptedLogs:()Ljava/util/Set;
     171: astore        20
     173: aload         12
     175: invokevirtual #26                 // Method org/apache/hadoop/hbase/procedure2/ProcedureExecutor.getProcedures:()Ljava/util/List;
     178: astore        21
     180: aload         21
     182: new           #27                 // class org/apache/hadoop/hbase/generated/master/procedures_jsp$1
     185: dup
     186: aload_0
     187: invokespecial #28                 // Method org/apache/hadoop/hbase/generated/master/procedures_jsp$1."<init>":(Lorg/apache/hadoop/hbase/generated/master/procedures_jsp;)V
     190: invokestatic  #29                 // Method java/util/Collections.sort:(Ljava/util/List;Ljava/util/Comparator;)V
     193: aload         11
     195: invokevirtual #30                 // Method org/apache/hadoop/hbase/master/HMaster.getLocks:()Ljava/util/List;
     198: astore        22
     200: aload_3
     201: ldc           #31                 // String pageTitle
     203: new           #32                 // class java/lang/StringBuilder
     206: dup
     207: invokespecial #33                 // Method java/lang/StringBuilder."<init>":()V
     210: ldc           #34                 // String HBase Master Procedures:
     212: invokevirtual #35                 // Method java/lang/StringBuilder.append:(Ljava/lang/String;)Ljava/lang/StringBuilder;
     215: aload         11
     217: invokevirtual #36                 // Method org/apache/hadoop/hbase/master/HMaster.getServerName:()Lorg/apache/hadoop/hbase/ServerName;
     220: invokevirtual #37                 // Method java/lang/StringBuilder.append:(Ljava/lang/Object;)Ljava/lang/StringBuilder;
     223: invokevirtual #38                 // Method java/lang/StringBuilder.toString:()Ljava/lang/String;
     226: invokevirtual #39                 // Method javax/servlet/jsp/PageContext.setAttribute:(Ljava/lang/String;Ljava/lang/Object;)V
     229: aload         7
     231: bipush        10
     233: invokevirtual #15                 // Method javax/servlet/jsp/JspWriter.write:(I)V
     236: aload_1
     237: aload_2
     238: new           #32                 // class java/lang/StringBuilder
     241: dup
     242: invokespecial #33                 // Method java/lang/StringBuilder."<init>":()V
     245: ldc           #40                 // String header.jsp?
     247: invokevirtual #35                 // Method java/lang/StringBuilder.append:(Ljava/lang/String;)Ljava/lang/StringBuilder;
     250: ldc           #31                 // String pageTitle
     252: aload_1
     253: invokeinterface #41,  1           // InterfaceMethod javax/servlet/http/HttpServletRequest.getCharacterEncoding:()Ljava/lang/String;
     258: invokestatic  #42                 // Method org/apache/jasper/runtime/JspRuntimeLibrary.URLEncode:(Ljava/lang/String;Ljava/lang/String;)Ljava/lang/String;
     261: invokevirtual #35                 // Method java/lang/StringBuilder.append:(Ljava/lang/String;)Ljava/lang/StringBuilder;
     264: ldc           #43                 // String =
     266: invokevirtual #35                 // Method java/lang/StringBuilder.append:(Ljava/lang/String;)Ljava/lang/StringBuilder;
     269: ldc           #44                 // String ${pageTitle}
     271: ldc           #45                 // class java/lang/String
     273: aload         10
     275: aconst_null
     276: invokestatic  #46                 // Method org/apache/jasper/runtime/PageContextImpl.evaluateExpression:(Ljava/lang/String;Ljava/lang/Class;Ljavax/servlet/jsp/PageContext;Lorg/apache/jasper/runtime/ProtectedFunctionMapper;)Ljava/lang/Object;
     279: checkcast     #45                 // class java/lang/String
     282: aload_1
     283: invokeinterface #41,  1           // InterfaceMethod javax/servlet/http/HttpServletRequest.getCharacterEncoding:()Ljava/lang/String;
     288: invokestatic  #42                 // Method org/apache/jasper/runtime/JspRuntimeLibrary.URLEncode:(Ljava/lang/String;Ljava/lang/String;)Ljava/lang/String;
     291: invokevirtual #35                 // Method java/lang/StringBuilder.append:(Ljava/lang/String;)Ljava/lang/StringBuilder;
     294: invokevirtual #38                 // Method java/lang/StringBuilder.toString:()Ljava/lang/String;
     297: aload         7
     299: iconst_0
     300: invokestatic  #47                 // Method org/apache/jasper/runtime/JspRuntimeLibrary.include:(Ljavax/servlet/ServletRequest;Ljavax/servlet/ServletResponse;Ljava/lang/String;Ljavax/servlet/jsp/JspWriter;Z)V
     303: aload         7
     305: ldc           #48                 // String \n\n<div class=\"container-fluid content\">\n  <div class=\"row\">\n      <div class=\"page-header\">\n          <h1>Procedures</h1>\n      </div>\n  </div>\n  <table class=\"table table-striped\" width=\"90%\" >\n    <tr>\n        <th>Id</th>\n        <th>Parent</th>\n        <th>State</th>\n        <th>Owner</th>\n        <th>Type</th>\n        <th>Start Time</th>\n        <th>Last Update</th>\n        <th>Errors</th>\n        <th>Parameters</th>\n    </tr>\n
     307: invokevirtual #49                 // Method javax/servlet/jsp/JspWriter.write:(Ljava/lang/String;)V
     310: aload         21
     312: invokeinterface #50,  1           // InterfaceMethod java/util/List.iterator:()Ljava/util/Iterator;
     317: astore        23
     319: aload         23
     321: invokeinterface #51,  1           // InterfaceMethod java/util/Iterator.hasNext:()Z
     326: ifeq          615
     329: aload         23
     331: invokeinterface #52,  1           // InterfaceMethod java/util/Iterator.next:()Ljava/lang/Object;
     336: checkcast     #53                 // class org/apache/hadoop/hbase/procedure2/Procedure
     339: astore        24
     341: aload         7
     343: ldc           #54                 // String \n      <tr>\n        <td>
     345: invokevirtual #49                 // Method javax/servlet/jsp/JspWriter.write:(Ljava/lang/String;)V
     348: aload         7
     350: aload         24
     352: invokevirtual #55                 // Method org/apache/hadoop/hbase/procedure2/Procedure.getProcId:()J
     355: invokevirtual #56                 // Method javax/servlet/jsp/JspWriter.print:(J)V
     358: aload         7
     360: ldc           #57                 // String </td>\n        <td>
     362: invokevirtual #49                 // Method javax/servlet/jsp/JspWriter.write:(Ljava/lang/String;)V
     365: aload         7
     367: aload         24
     369: invokevirtual #58                 // Method org/apache/hadoop/hbase/procedure2/Procedure.hasParent:()Z
     372: ifeq          386
     375: aload         24
     377: invokevirtual #59                 // Method org/apache/hadoop/hbase/procedure2/Procedure.getParentProcId:()J
     380: invokestatic  #60                 // Method java/lang/Long.valueOf:(J)Ljava/lang/Long;
     383: goto          388
     386: ldc           #61                 // String
     388: invokevirtual #62                 // Method javax/servlet/jsp/JspWriter.print:(Ljava/lang/Object;)V
     391: aload         7
     393: ldc           #57                 // String </td>\n        <td>
     395: invokevirtual #49                 // Method javax/servlet/jsp/JspWriter.write:(Ljava/lang/String;)V
     398: aload         7
     400: new           #32                 // class java/lang/StringBuilder
     403: dup
     404: invokespecial #33                 // Method java/lang/StringBuilder."<init>":()V
     407: aload         24
     409: invokevirtual #63                 // Method org/apache/hadoop/hbase/procedure2/Procedure.getState:()Lorg/apache/hadoop/hbase/shaded/protobuf/generated/ProcedureProtos$ProcedureState;
     412: invokevirtual #64                 // Method org/apache/hadoop/hbase/shaded/protobuf/generated/ProcedureProtos$ProcedureState.toString:()Ljava/lang/String;
     415: invokevirtual #35                 // Method java/lang/StringBuilder.append:(Ljava/lang/String;)Ljava/lang/StringBuilder;
     418: aload         24
     420: invokevirtual #65                 // Method org/apache/hadoop/hbase/procedure2/Procedure.isBypass:()Z
     423: ifeq          431
     426: ldc           #66                 // String (Bypass)
     428: goto          433
     431: ldc           #61                 // String
     433: invokevirtual #35                 // Method java/lang/StringBuilder.append:(Ljava/lang/String;)Ljava/lang/StringBuilder;
     436: invokevirtual #38                 // Method java/lang/StringBuilder.toString:()Ljava/lang/String;
     439: invokestatic  #67                 // Method org/apache/commons/lang3/StringEscapeUtils.escapeXml:(Ljava/lang/String;)Ljava/lang/String;
     442: invokevirtual #68                 // Method javax/servlet/jsp/JspWriter.print:(Ljava/lang/String;)V
     445: aload         7
     447: ldc           #57                 // String </td>\n        <td>
     449: invokevirtual #49                 // Method javax/servlet/jsp/JspWriter.write:(Ljava/lang/String;)V
     452: aload         7
     454: aload         24
     456: invokevirtual #69                 // Method org/apache/hadoop/hbase/procedure2/Procedure.hasOwner:()Z
     459: ifeq          473
     462: aload         24
     464: invokevirtual #70                 // Method org/apache/hadoop/hbase/procedure2/Procedure.getOwner:()Ljava/lang/String;
     467: invokestatic  #67                 // Method org/apache/commons/lang3/StringEscapeUtils.escapeXml:(Ljava/lang/String;)Ljava/lang/String;
     470: goto          475
     473: ldc           #61                 // String
     475: invokevirtual #68                 // Method javax/servlet/jsp/JspWriter.print:(Ljava/lang/String;)V
     478: aload         7
     480: ldc           #57                 // String </td>\n        <td>
     482: invokevirtual #49                 // Method javax/servlet/jsp/JspWriter.write:(Ljava/lang/String;)V
     485: aload         7
     487: aload         24
     489: invokevirtual #71                 // Method org/apache/hadoop/hbase/procedure2/Procedure.getProcName:()Ljava/lang/String;
     492: invokestatic  #67                 // Method org/apache/commons/lang3/StringEscapeUtils.escapeXml:(Ljava/lang/String;)Ljava/lang/String;
     495: invokevirtual #68                 // Method javax/servlet/jsp/JspWriter.print:(Ljava/lang/String;)V
     498: aload         7
     500: ldc           #57                 // String </td>\n        <td>
     502: invokevirtual #49                 // Method javax/servlet/jsp/JspWriter.write:(Ljava/lang/String;)V
     505: aload         7
     507: new           #72                 // class java/util/Date
     510: dup
     511: aload         24
     513: invokevirtual #73                 // Method org/apache/hadoop/hbase/procedure2/Procedure.getSubmittedTime:()J
     516: invokespecial #74                 // Method java/util/Date."<init>":(J)V
     519: invokevirtual #62                 // Method javax/servlet/jsp/JspWriter.print:(Ljava/lang/Object;)V
     522: aload         7
     524: ldc           #57                 // String </td>\n        <td>
     526: invokevirtual #49                 // Method javax/servlet/jsp/JspWriter.write:(Ljava/lang/String;)V
     529: aload         7
     531: new           #72                 // class java/util/Date
     534: dup
     535: aload         24
     537: invokevirtual #75                 // Method org/apache/hadoop/hbase/procedure2/Procedure.getLastUpdate:()J
     540: invokespecial #74                 // Method java/util/Date."<init>":(J)V
     543: invokevirtual #62                 // Method javax/servlet/jsp/JspWriter.print:(Ljava/lang/Object;)V
     546: aload         7
     548: ldc           #57                 // String </td>\n        <td>
     550: invokevirtual #49                 // Method javax/servlet/jsp/JspWriter.write:(Ljava/lang/String;)V
     553: aload         7
     555: aload         24
     557: invokevirtual #76                 // Method org/apache/hadoop/hbase/procedure2/Procedure.isFailed:()Z
     560: ifeq          577
     563: aload         24
     565: invokevirtual #77                 // Method org/apache/hadoop/hbase/procedure2/Procedure.getException:()Lorg/apache/hadoop/hbase/procedure2/RemoteProcedureException;
     568: invokevirtual #78                 // Method org/apache/hadoop/hbase/procedure2/RemoteProcedureException.unwrapRemoteIOException:()Ljava/io/IOException;
     571: invokevirtual #79                 // Method java/io/IOException.getMessage:()Ljava/lang/String;
     574: goto          579
     577: ldc           #61                 // String
     579: invokestatic  #67                 // Method org/apache/commons/lang3/StringEscapeUtils.escapeXml:(Ljava/lang/String;)Ljava/lang/String;
     582: invokevirtual #68                 // Method javax/servlet/jsp/JspWriter.print:(Ljava/lang/String;)V
     585: aload         7
     587: ldc           #57                 // String </td>\n        <td>
     589: invokevirtual #49                 // Method javax/servlet/jsp/JspWriter.write:(Ljava/lang/String;)V
     592: aload         7
     594: aload         24
     596: invokestatic  #80                 // Method org/apache/hadoop/hbase/master/procedure/ProcedureDescriber.describeParameters:(Lorg/apache/hadoop/hbase/procedure2/Procedure;)Ljava/lang/String;
     599: invokestatic  #67                 // Method org/apache/commons/lang3/StringEscapeUtils.escapeXml:(Ljava/lang/String;)Ljava/lang/String;
     602: invokevirtual #68                 // Method javax/servlet/jsp/JspWriter.print:(Ljava/lang/String;)V
     605: aload         7
     607: ldc           #81                 // String </td>\n      </tr>\n
     609: invokevirtual #49                 // Method javax/servlet/jsp/JspWriter.write:(Ljava/lang/String;)V
     612: goto          319
     615: aload         7
     617: ldc           #82                 // String \n  </table>\n</div>\n<br />\n<div class=\"container-fluid content\">\n  <div class=\"row\">\n    <div class=\"page-header\">\n      <h2>Procedure WAL State</h2>\n    </div>\n  </div>\n  <div class=\"tabbable\">\n    <ul class=\"nav nav-pills\">\n      <li class=\"active\">\n        <a href=\"#tab_WALFiles\" data-toggle=\"tab\">WAL files</a>\n      </li>\n      <li class=\"\">\n        <a href=\"#tab_WALFilesCorrupted\" data-toggle=\"tab\">Corrupted WAL files</a>\n      </li>\n      <li class=\"\">\n        <a href=\"#tab_WALRollTime\" data-toggle=\"tab\">WAL roll time</a>\n      </li>\n      <li class=\"\">\n        <a href=\"#tab_SyncStats\" data-toggle=\"tab\">Sync stats</a>\n      </li>\n    </ul>\n    <div class=\"tab-content\" style=\"padding-bottom: 9px; border-bottom: 1px solid #ddd;\">\n      <div class=\"tab-pane active\" id=\"tab_WALFiles\">\n
     619: invokevirtual #49                 // Method javax/servlet/jsp/JspWriter.write:(Ljava/lang/String;)V
     622: aload         19
     624: ifnull        782
     627: aload         19
     629: invokevirtual #83                 // Method java/util/ArrayList.size:()I
     632: ifle          782
     635: aload         7
     637: ldc           #84                 // String \n          <table class=\"table table-striped\">\n            <tr>\n              <th>LogID</th>\n              <th>Size</th>\n              <th>Timestamp</th>\n              <th>Path</th>\n            </tr>\n
     639: invokevirtual #49                 // Method javax/servlet/jsp/JspWriter.write:(Ljava/lang/String;)V
     642: aload         19
     644: invokevirtual #83                 // Method java/util/ArrayList.size:()I
     647: iconst_1
     648: isub
     649: istore        23
     651: iload         23
     653: iflt          772
     656: aload         7
     658: ldc           #85                 // String \n
     660: invokevirtual #49                 // Method javax/servlet/jsp/JspWriter.write:(Ljava/lang/String;)V
     663: aload         19
     665: iload         23
     667: invokevirtual #86                 // Method java/util/ArrayList.get:(I)Ljava/lang/Object;
     670: checkcast     #87                 // class org/apache/hadoop/hbase/procedure2/store/wal/ProcedureWALFile
     673: astore        24
     675: aload         7
     677: ldc           #88                 // String \n            <tr>\n              <td>
     679: invokevirtual #49                 // Method javax/servlet/jsp/JspWriter.write:(Ljava/lang/String;)V
     682: aload         7
     684: aload         24
     686: invokevirtual #89                 // Method org/apache/hadoop/hbase/procedure2/store/wal/ProcedureWALFile.getLogId:()J
     689: invokevirtual #56                 // Method javax/servlet/jsp/JspWriter.print:(J)V
     692: aload         7
     694: ldc           #90                 // String </td>\n              <td>
     696: invokevirtual #49                 // Method javax/servlet/jsp/JspWriter.write:(Ljava/lang/String;)V
     699: aload         7
     701: aload         24
     703: invokevirtual #91                 // Method org/apache/hadoop/hbase/procedure2/store/wal/ProcedureWALFile.getSize:()J
     706: ldc           #92                 // String B
     708: iconst_1
     709: invokestatic  #93                 // Method org/apache/hadoop/util/StringUtils$TraditionalBinaryPrefix.long2String:(JLjava/lang/String;I)Ljava/lang/String;
     712: invokevirtual #68                 // Method javax/servlet/jsp/JspWriter.print:(Ljava/lang/String;)V
     715: aload         7
     717: ldc           #94                 // String  </td>\n              <td>
     719: invokevirtual #49                 // Method javax/servlet/jsp/JspWriter.write:(Ljava/lang/String;)V
     722: aload         7
     724: new           #72                 // class java/util/Date
     727: dup
     728: aload         24
     730: invokevirtual #95                 // Method org/apache/hadoop/hbase/procedure2/store/wal/ProcedureWALFile.getTimestamp:()J
     733: invokespecial #74                 // Method java/util/Date."<init>":(J)V
     736: invokevirtual #62                 // Method javax/servlet/jsp/JspWriter.print:(Ljava/lang/Object;)V
     739: aload         7
     741: ldc           #94                 // String  </td>\n              <td>
     743: invokevirtual #49                 // Method javax/servlet/jsp/JspWriter.write:(Ljava/lang/String;)V
     746: aload         7
     748: aload         24
     750: invokevirtual #96                 // Method org/apache/hadoop/hbase/procedure2/store/wal/ProcedureWALFile.toString:()Ljava/lang/String;
     753: invokestatic  #67                 // Method org/apache/commons/lang3/StringEscapeUtils.escapeXml:(Ljava/lang/String;)Ljava/lang/String;
     756: invokevirtual #68                 // Method javax/servlet/jsp/JspWriter.print:(Ljava/lang/String;)V
     759: aload         7
     761: ldc           #97                 // String  </td>\n            </tr>\n
     763: invokevirtual #49                 // Method javax/servlet/jsp/JspWriter.write:(Ljava/lang/String;)V
     766: iinc          23, -1
     769: goto          651
     772: aload         7
     774: ldc           #98                 // String \n          </table>\n
     776: invokevirtual #49                 // Method javax/servlet/jsp/JspWriter.write:(Ljava/lang/String;)V
     779: goto          789
     782: aload         7
     784: ldc           #99                 // String \n          <p> No WAL files</p>\n
     786: invokevirtual #49                 // Method javax/servlet/jsp/JspWriter.write:(Ljava/lang/String;)V
     789: aload         7
     791: ldc           #100                // String \n      </div>\n      <div class=\"tab-pane\" id=\"tab_WALFilesCorrupted\">\n
     793: invokevirtual #49                 // Method javax/servlet/jsp/JspWriter.write:(Ljava/lang/String;)V
     796: aload         20
     798: ifnull        953
     801: aload         20
     803: invokeinterface #101,  1          // InterfaceMethod java/util/Set.size:()I
     808: ifle          953
     811: aload         7
     813: ldc           #102                // String \n        <table class=\"table table-striped\">\n          <tr>\n            <th>LogID</th>\n            <th>Size</th>\n            <th>Timestamp</th>\n            <th>Path</th>\n          </tr>\n
     815: invokevirtual #49                 // Method javax/servlet/jsp/JspWriter.write:(Ljava/lang/String;)V
     818: aload         20
     820: invokeinterface #103,  1          // InterfaceMethod java/util/Set.iterator:()Ljava/util/Iterator;
     825: astore        23
     827: aload         23
     829: invokeinterface #51,  1           // InterfaceMethod java/util/Iterator.hasNext:()Z
     834: ifeq          943
     837: aload         23
     839: invokeinterface #52,  1           // InterfaceMethod java/util/Iterator.next:()Ljava/lang/Object;
     844: checkcast     #87                 // class org/apache/hadoop/hbase/procedure2/store/wal/ProcedureWALFile
     847: astore        24
     849: aload         7
     851: ldc           #104                // String \n          <tr>\n            <td>
     853: invokevirtual #49                 // Method javax/servlet/jsp/JspWriter.write:(Ljava/lang/String;)V
     856: aload         7
     858: aload         24
     860: invokevirtual #89                 // Method org/apache/hadoop/hbase/procedure2/store/wal/ProcedureWALFile.getLogId:()J
     863: invokevirtual #56                 // Method javax/servlet/jsp/JspWriter.print:(J)V
     866: aload         7
     868: ldc           #105                // String </td>\n            <td>
     870: invokevirtual #49                 // Method javax/servlet/jsp/JspWriter.write:(Ljava/lang/String;)V
     873: aload         7
     875: aload         24
     877: invokevirtual #91                 // Method org/apache/hadoop/hbase/procedure2/store/wal/ProcedureWALFile.getSize:()J
     880: ldc           #92                 // String B
     882: iconst_1
     883: invokestatic  #93                 // Method org/apache/hadoop/util/StringUtils$TraditionalBinaryPrefix.long2String:(JLjava/lang/String;I)Ljava/lang/String;
     886: invokevirtual #68                 // Method javax/servlet/jsp/JspWriter.print:(Ljava/lang/String;)V
     889: aload         7
     891: ldc           #106                // String  </td>\n            <td>
     893: invokevirtual #49                 // Method javax/servlet/jsp/JspWriter.write:(Ljava/lang/String;)V
     896: aload         7
     898: new           #72                 // class java/util/Date
     901: dup
     902: aload         24
     904: invokevirtual #95                 // Method org/apache/hadoop/hbase/procedure2/store/wal/ProcedureWALFile.getTimestamp:()J
     907: invokespecial #74                 // Method java/util/Date."<init>":(J)V
     910: invokevirtual #62                 // Method javax/servlet/jsp/JspWriter.print:(Ljava/lang/Object;)V
     913: aload         7
     915: ldc           #106                // String  </td>\n            <td>
     917: invokevirtual #49                 // Method javax/servlet/jsp/JspWriter.write:(Ljava/lang/String;)V
     920: aload         7
     922: aload         24
     924: invokevirtual #96                 // Method org/apache/hadoop/hbase/procedure2/store/wal/ProcedureWALFile.toString:()Ljava/lang/String;
     927: invokestatic  #67                 // Method org/apache/commons/lang3/StringEscapeUtils.escapeXml:(Ljava/lang/String;)Ljava/lang/String;
     930: invokevirtual #68                 // Method javax/servlet/jsp/JspWriter.print:(Ljava/lang/String;)V
     933: aload         7
     935: ldc           #107                // String  </td>\n          </tr>\n
     937: invokevirtual #49                 // Method javax/servlet/jsp/JspWriter.write:(Ljava/lang/String;)V
     940: goto          827
     943: aload         7
     945: ldc           #108                // String \n          </table>\n
     947: invokevirtual #49                 // Method javax/servlet/jsp/JspWriter.write:(Ljava/lang/String;)V
     950: goto          960
     953: aload         7
     955: ldc           #109                // String \n        <p> No corrupted WAL files</p>\n
     957: invokevirtual #49                 // Method javax/servlet/jsp/JspWriter.write:(Ljava/lang/String;)V
     960: aload         7
     962: ldc           #110                // String \n      </div>\n      <div class=\"tab-pane\" id=\"tab_WALRollTime\">\n        <table class=\"table table-striped\">\n          <tr>\n            <th> Milliseconds to next roll</th>\n            <th> Milliseconds from last roll</th>\n          </tr>\n          <tr>\n            <td>
     964: invokevirtual #49                 // Method javax/servlet/jsp/JspWriter.write:(Ljava/lang/String;)V
     967: aload         7
     969: lload         15
     971: invokestatic  #111                // Method org/apache/hadoop/hbase/procedure2/util/StringUtils.humanTimeDiff:(J)Ljava/lang/String;
     974: invokevirtual #68                 // Method javax/servlet/jsp/JspWriter.print:(Ljava/lang/String;)V
     977: aload         7
     979: ldc           #105                // String </td>\n            <td>
     981: invokevirtual #49                 // Method javax/servlet/jsp/JspWriter.write:(Ljava/lang/String;)V
     984: aload         7
     986: lload         17
     988: invokestatic  #111                // Method org/apache/hadoop/hbase/procedure2/util/StringUtils.humanTimeDiff:(J)Ljava/lang/String;
     991: invokevirtual #68                 // Method javax/servlet/jsp/JspWriter.print:(Ljava/lang/String;)V
     994: aload         7
     996: ldc           #112                // String </td>\n          </tr>\n        </table>\n      </div>\n      <div class=\"tab-pane\" id=\"tab_SyncStats\">\n        <table class=\"table table-striped\">\n          <tr>\n            <th> Time</th>\n            <th> Sync Wait</th>\n            <th> Last num of synced entries</th>\n            <th> Total Synced</th>\n            <th> Synced per second</th>\n          </tr>\n
     998: invokevirtual #49                 // Method javax/servlet/jsp/JspWriter.write:(Ljava/lang/String;)V
    1001: aload         14
    1003: invokevirtual #83                 // Method java/util/ArrayList.size:()I
    1006: iconst_1
    1007: isub
    1008: istore        23
    1010: iload         23
    1012: iflt          1155
    1015: aload         7
    1017: ldc           #113                // String \n
    1019: invokevirtual #49                 // Method javax/servlet/jsp/JspWriter.write:(Ljava/lang/String;)V
    1022: aload         14
    1024: iload         23
    1026: invokevirtual #86                 // Method java/util/ArrayList.get:(I)Ljava/lang/Object;
    1029: checkcast     #114                // class org/apache/hadoop/hbase/procedure2/store/wal/WALProcedureStore$SyncMetrics
    1032: astore        24
    1034: aload         7
    1036: ldc           #104                // String \n          <tr>\n            <td>
    1038: invokevirtual #49                 // Method javax/servlet/jsp/JspWriter.write:(Ljava/lang/String;)V
    1041: aload         7
    1043: new           #72                 // class java/util/Date
    1046: dup
    1047: aload         24
    1049: invokevirtual #115                // Method org/apache/hadoop/hbase/procedure2/store/wal/WALProcedureStore$SyncMetrics.getTimestamp:()J
    1052: invokespecial #74                 // Method java/util/Date."<init>":(J)V
    1055: invokevirtual #62                 // Method javax/servlet/jsp/JspWriter.print:(Ljava/lang/Object;)V
    1058: aload         7
    1060: ldc           #105                // String </td>\n            <td>
    1062: invokevirtual #49                 // Method javax/servlet/jsp/JspWriter.write:(Ljava/lang/String;)V
    1065: aload         7
    1067: aload         24
    1069: invokevirtual #116                // Method org/apache/hadoop/hbase/procedure2/store/wal/WALProcedureStore$SyncMetrics.getSyncWaitMs:()J
    1072: invokestatic  #111                // Method org/apache/hadoop/hbase/procedure2/util/StringUtils.humanTimeDiff:(J)Ljava/lang/String;
    1075: invokevirtual #68                 // Method javax/servlet/jsp/JspWriter.print:(Ljava/lang/String;)V
    1078: aload         7
    1080: ldc           #105                // String </td>\n            <td>
    1082: invokevirtual #49                 // Method javax/servlet/jsp/JspWriter.write:(Ljava/lang/String;)V
    1085: aload         7
    1087: aload         24
    1089: invokevirtual #117                // Method org/apache/hadoop/hbase/procedure2/store/wal/WALProcedureStore$SyncMetrics.getSyncedEntries:()J
    1092: invokevirtual #56                 // Method javax/servlet/jsp/JspWriter.print:(J)V
    1095: aload         7
    1097: ldc           #105                // String </td>\n            <td>
    1099: invokevirtual #49                 // Method javax/servlet/jsp/JspWriter.write:(Ljava/lang/String;)V
    1102: aload         7
    1104: aload         24
    1106: invokevirtual #118                // Method org/apache/hadoop/hbase/procedure2/store/wal/WALProcedureStore$SyncMetrics.getTotalSyncedBytes:()J
    1109: ldc           #92                 // String B
    1111: iconst_1
    1112: invokestatic  #93                 // Method org/apache/hadoop/util/StringUtils$TraditionalBinaryPrefix.long2String:(JLjava/lang/String;I)Ljava/lang/String;
    1115: invokevirtual #68                 // Method javax/servlet/jsp/JspWriter.print:(Ljava/lang/String;)V
    1118: aload         7
    1120: ldc           #105                // String </td>\n            <td>
    1122: invokevirtual #49                 // Method javax/servlet/jsp/JspWriter.write:(Ljava/lang/String;)V
    1125: aload         7
    1127: aload         24
    1129: invokevirtual #119                // Method org/apache/hadoop/hbase/procedure2/store/wal/WALProcedureStore$SyncMetrics.getSyncedPerSec:()F
    1132: f2l
    1133: ldc           #92                 // String B
    1135: iconst_1
    1136: invokestatic  #93                 // Method org/apache/hadoop/util/StringUtils$TraditionalBinaryPrefix.long2String:(JLjava/lang/String;I)Ljava/lang/String;
    1139: invokevirtual #68                 // Method javax/servlet/jsp/JspWriter.print:(Ljava/lang/String;)V
    1142: aload         7
    1144: ldc           #120                // String </td>\n          </tr>\n
    1146: invokevirtual #49                 // Method javax/servlet/jsp/JspWriter.write:(Ljava/lang/String;)V
    1149: iinc          23, -1
    1152: goto          1010
    1155: aload         7
    1157: ldc           #121                // String \n        </table>\n        </div>\n      </div>\n  </div>\n</div>\n<br />\n<div class=\"container-fluid content\">\n  <div class=\"row\">\n      <div class=\"page-header\">\n          <h1>Locks</h1>\n      </div>\n  </div>\n
    1159: invokevirtual #49                 // Method javax/servlet/jsp/JspWriter.write:(Ljava/lang/String;)V
    1162: aload         22
    1164: invokeinterface #50,  1           // InterfaceMethod java/util/List.iterator:()Ljava/util/Iterator;
    1169: astore        23
    1171: aload         23
    1173: invokeinterface #51,  1           // InterfaceMethod java/util/Iterator.hasNext:()Z
    1178: ifeq          1439
    1181: aload         23
    1183: invokeinterface #52,  1           // InterfaceMethod java/util/Iterator.next:()Ljava/lang/Object;
    1188: checkcast     #122                // class org/apache/hadoop/hbase/procedure2/LockedResource
    1191: astore        24
    1193: aload         7
    1195: ldc           #123                // String \n    <h2>
    1197: invokevirtual #49                 // Method javax/servlet/jsp/JspWriter.write:(Ljava/lang/String;)V
    1200: aload         7
    1202: aload         24
    1204: invokevirtual #124                // Method org/apache/hadoop/hbase/procedure2/LockedResource.getResourceType:()Lorg/apache/hadoop/hbase/procedure2/LockedResourceType;
    1207: invokevirtual #62                 // Method javax/servlet/jsp/JspWriter.print:(Ljava/lang/Object;)V
    1210: aload         7
    1212: bipush        58
    1214: invokevirtual #15                 // Method javax/servlet/jsp/JspWriter.write:(I)V
    1217: aload         7
    1219: bipush        32
    1221: invokevirtual #15                 // Method javax/servlet/jsp/JspWriter.write:(I)V
    1224: aload         7
    1226: aload         24
    1228: invokevirtual #125                // Method org/apache/hadoop/hbase/procedure2/LockedResource.getResourceName:()Ljava/lang/String;
    1231: invokevirtual #68                 // Method javax/servlet/jsp/JspWriter.print:(Ljava/lang/String;)V
    1234: aload         7
    1236: ldc           #126                // String </h2>\n
    1238: invokevirtual #49                 // Method javax/servlet/jsp/JspWriter.write:(Ljava/lang/String;)V
    1241: getstatic     #127                // Field org/apache/hadoop/hbase/generated/master/procedures_jsp$2.$SwitchMap$org$apache$hadoop$hbase$procedure2$LockType:[I
    1244: aload         24
    1246: invokevirtual #128                // Method org/apache/hadoop/hbase/procedure2/LockedResource.getLockType:()Lorg/apache/hadoop/hbase/procedure2/LockType;
    1249: invokevirtual #129                // Method org/apache/hadoop/hbase/procedure2/LockType.ordinal:()I
    1252: iaload
    1253: lookupswitch  { // 2
                     1: 1280
                     2: 1313
               default: 1337
          }
    1280: aload         7
    1282: ldc           #130                // String \n    <p>Lock type: EXCLUSIVE</p>\n    <p>Owner procedure:
    1284: invokevirtual #49                 // Method javax/servlet/jsp/JspWriter.write:(Ljava/lang/String;)V
    1287: aload         7
    1289: aload         24
    1291: invokevirtual #131                // Method org/apache/hadoop/hbase/procedure2/LockedResource.getExclusiveLockOwnerProcedure:()Lorg/apache/hadoop/hbase/procedure2/Procedure;
    1294: invokestatic  #132                // Method org/apache/hadoop/hbase/master/procedure/ProcedureDescriber.describe:(Lorg/apache/hadoop/hbase/procedure2/Procedure;)Ljava/lang/String;
    1297: invokestatic  #67                 // Method org/apache/commons/lang3/StringEscapeUtils.escapeXml:(Ljava/lang/String;)Ljava/lang/String;
    1300: invokevirtual #68                 // Method javax/servlet/jsp/JspWriter.print:(Ljava/lang/String;)V
    1303: aload         7
    1305: ldc           #133                // String </p>\n
    1307: invokevirtual #49                 // Method javax/servlet/jsp/JspWriter.write:(Ljava/lang/String;)V
    1310: goto          1337
    1313: aload         7
    1315: ldc           #134                // String \n    <p>Lock type: SHARED</p>\n    <p>Number of shared locks:
    1317: invokevirtual #49                 // Method javax/servlet/jsp/JspWriter.write:(Ljava/lang/String;)V
    1320: aload         7
    1322: aload         24
    1324: invokevirtual #135                // Method org/apache/hadoop/hbase/procedure2/LockedResource.getSharedLockCount:()I
    1327: invokevirtual #136                // Method javax/servlet/jsp/JspWriter.print:(I)V
    1330: aload         7
    1332: ldc           #133                // String </p>\n
    1334: invokevirtual #49                 // Method javax/servlet/jsp/JspWriter.write:(Ljava/lang/String;)V
    1337: aload         24
    1339: invokevirtual #137                // Method org/apache/hadoop/hbase/procedure2/LockedResource.getWaitingProcedures:()Ljava/util/List;
    1342: astore        25
    1344: aload         25
    1346: invokeinterface #138,  1          // InterfaceMethod java/util/List.isEmpty:()Z
    1351: ifne          1429
    1354: aload         7
    1356: ldc           #139                // String \n        <h3>Waiting procedures</h3>\n        <table class=\"table table-striped\" width=\"90%\" >\n
    1358: invokevirtual #49                 // Method javax/servlet/jsp/JspWriter.write:(Ljava/lang/String;)V
    1361: aload         21
    1363: invokeinterface #50,  1           // InterfaceMethod java/util/List.iterator:()Ljava/util/Iterator;
    1368: astore        26
    1370: aload         26
    1372: invokeinterface #51,  1           // InterfaceMethod java/util/Iterator.hasNext:()Z
    1377: ifeq          1422
    1380: aload         26
    1382: invokeinterface #52,  1           // InterfaceMethod java/util/Iterator.next:()Ljava/lang/Object;
    1387: checkcast     #53                 // class org/apache/hadoop/hbase/procedure2/Procedure
    1390: astore        27
    1392: aload         7
    1394: ldc           #140                // String \n         <tr>\n            <td>
    1396: invokevirtual #49                 // Method javax/servlet/jsp/JspWriter.write:(Ljava/lang/String;)V
    1399: aload         7
    1401: aload         27
    1403: invokestatic  #132                // Method org/apache/hadoop/hbase/master/procedure/ProcedureDescriber.describe:(Lorg/apache/hadoop/hbase/procedure2/Procedure;)Ljava/lang/String;
    1406: invokestatic  #67                 // Method org/apache/commons/lang3/StringEscapeUtils.escapeXml:(Ljava/lang/String;)Ljava/lang/String;
    1409: invokevirtual #68                 // Method javax/servlet/jsp/JspWriter.print:(Ljava/lang/String;)V
    1412: aload         7
    1414: ldc           #141                // String </td>\n          </tr>\n
    1416: invokevirtual #49                 // Method javax/servlet/jsp/JspWriter.write:(Ljava/lang/String;)V
    1419: goto          1370
    1422: aload         7
    1424: ldc           #142                // String \n        </table>\n
    1426: invokevirtual #49                 // Method javax/servlet/jsp/JspWriter.write:(Ljava/lang/String;)V
    1429: aload         7
    1431: ldc           #143                // String \n
    1433: invokevirtual #49                 // Method javax/servlet/jsp/JspWriter.write:(Ljava/lang/String;)V
    1436: goto          1171
    1439: aload         7
    1441: ldc           #144                // String \n</div>\n\n
    1443: invokevirtual #49                 // Method javax/servlet/jsp/JspWriter.write:(Ljava/lang/String;)V
    1446: aload_1
    1447: aload_2
    1448: ldc           #145                // String footer.jsp
    1450: aload         7
    1452: iconst_0
    1453: invokestatic  #47                 // Method org/apache/jasper/runtime/JspRuntimeLibrary.include:(Ljavax/servlet/ServletRequest;Ljavax/servlet/ServletResponse;Ljava/lang/String;Ljavax/servlet/jsp/JspWriter;Z)V
    1456: aload         7
    1458: bipush        10
    1460: invokevirtual #15                 // Method javax/servlet/jsp/JspWriter.write:(I)V
    1463: getstatic     #5                  // Field _jspxFactory:Ljavax/servlet/jsp/JspFactory;
    1466: aload         10
    1468: invokevirtual #146                // Method javax/servlet/jsp/JspFactory.releasePageContext:(Ljavax/servlet/jsp/PageContext;)V
    1471: goto          1555
    1474: astore        11
    1476: aload         11
    1478: instanceof    #148                // class javax/servlet/jsp/SkipPageException
    1481: ifne          1531
    1484: aload         9
    1486: astore        7
    1488: aload         7
    1490: ifnull        1506
    1493: aload         7
    1495: invokevirtual #149                // Method javax/servlet/jsp/JspWriter.getBufferSize:()I
    1498: ifeq          1506
    1501: aload         7
    1503: invokevirtual #150                // Method javax/servlet/jsp/JspWriter.clearBuffer:()V
    1506: aload         10
    1508: ifnull        1521
    1511: aload         10
    1513: aload         11
    1515: invokevirtual #151                // Method javax/servlet/jsp/PageContext.handlePageException:(Ljava/lang/Throwable;)V
    1518: goto          1531
    1521: new           #152                // class javax/servlet/ServletException
    1524: dup
    1525: aload         11
    1527: invokespecial #153                // Method javax/servlet/ServletException."<init>":(Ljava/lang/Throwable;)V
    1530: athrow
    1531: getstatic     #5                  // Field _jspxFactory:Ljavax/servlet/jsp/JspFactory;
    1534: aload         10
    1536: invokevirtual #146                // Method javax/servlet/jsp/JspFactory.releasePageContext:(Ljavax/servlet/jsp/PageContext;)V
    1539: goto          1555
    1542: astore        28
    1544: getstatic     #5                  // Field _jspxFactory:Ljavax/servlet/jsp/JspFactory;
    1547: aload         10
    1549: invokevirtual #146                // Method javax/servlet/jsp/JspFactory.releasePageContext:(Ljavax/servlet/jsp/PageContext;)V
    1552: aload         28
    1554: athrow
    1555: return
    Exception table:
       from    to  target type
          23  1463  1474   Class java/lang/Throwable
          23  1463  1542   any
        1474  1531  1542   any
        1542  1544  1542   any

  static {};
    Code:
       0: invokestatic  #154                // Method javax/servlet/jsp/JspFactory.getDefaultFactory:()Ljavax/servlet/jsp/JspFactory;
       3: putstatic     #5                  // Field _jspxFactory:Ljavax/servlet/jsp/JspFactory;
       6: return
}
