Compiled from "processRS_jsp.java"
public final class org.apache.hadoop.hbase.generated.regionserver.processRS_jsp extends org.apache.jasper.runtime.HttpJspBase implements org.apache.jasper.runtime.JspSourceDependent {
  public org.apache.hadoop.hbase.generated.regionserver.processRS_jsp();
    Code:
       0: aload_0
       1: invokespecial #1                  // Method org/apache/jasper/runtime/HttpJspBase."<init>":()V
       4: return

  public java.util.List<java.lang.String> getDependants();
    Code:
       0: getstatic     #2                  // Field _jspx_dependants:Ljava/util/List;
       3: areturn

  public void _jspService(javax.servlet.http.HttpServletRequest, javax.servlet.http.HttpServletResponse) throws java.io.IOException, javax.servlet.ServletException;
    Code:
       0: aconst_null
       1: astore_3
       2: aconst_null
       3: astore        4
       5: aconst_null
       6: astore        5
       8: aconst_null
       9: astore        6
      11: aconst_null
      12: astore        7
      14: aload_0
      15: astore        8
      17: aconst_null
      18: astore        9
      20: aconst_null
      21: astore        10
      23: aload_2
      24: ldc           #3                  // String text/html;charset=UTF-8
      26: invokeinterface #4,  2            // InterfaceMethod javax/servlet/http/HttpServletResponse.setContentType:(Ljava/lang/String;)V
      31: getstatic     #5                  // Field _jspxFactory:Ljavax/servlet/jsp/JspFactory;
      34: aload_0
      35: aload_1
      36: aload_2
      37: aconst_null
      38: iconst_1
      39: sipush        8192
      42: iconst_1
      43: invokevirtual #6                  // Method javax/servlet/jsp/JspFactory.getPageContext:(Ljavax/servlet/Servlet;Ljavax/servlet/ServletRequest;Ljavax/servlet/ServletResponse;Ljava/lang/String;ZIZ)Ljavax/servlet/jsp/PageContext;
      46: astore_3
      47: aload_3
      48: astore        10
      50: aload_3
      51: invokevirtual #7                  // Method javax/servlet/jsp/PageContext.getServletContext:()Ljavax/servlet/ServletContext;
      54: astore        5
      56: aload_3
      57: invokevirtual #8                  // Method javax/servlet/jsp/PageContext.getServletConfig:()Ljavax/servlet/ServletConfig;
      60: astore        6
      62: aload_3
      63: invokevirtual #9                  // Method javax/servlet/jsp/PageContext.getSession:()Ljavax/servlet/http/HttpSession;
      66: astore        4
      68: aload_3
      69: invokevirtual #10                 // Method javax/servlet/jsp/PageContext.getOut:()Ljavax/servlet/jsp/JspWriter;
      72: astore        7
      74: aload         7
      76: astore        9
      78: aload_0
      79: aload         5
      81: ldc           #11                 // String com.sun.appserv.jsp.resource.injector
      83: invokeinterface #12,  2           // InterfaceMethod javax/servlet/ServletContext.getAttribute:(Ljava/lang/String;)Ljava/lang/Object;
      88: checkcast     #13                 // class org/glassfish/jsp/api/ResourceInjector
      91: putfield      #14                 // Field _jspx_resourceInjector:Lorg/glassfish/jsp/api/ResourceInjector;
      94: aload         7
      96: bipush        10
      98: invokevirtual #15                 // Method javax/servlet/jsp/JspWriter.write:(I)V
     101: aload         7
     103: bipush        10
     105: invokevirtual #15                 // Method javax/servlet/jsp/JspWriter.write:(I)V
     108: invokestatic  #16                 // Method java/lang/management/ManagementFactory.getRuntimeMXBean:()Ljava/lang/management/RuntimeMXBean;
     111: astore        11
     113: new           #17                 // class javax/management/ObjectName
     116: dup
     117: ldc           #18                 // String Hadoop:service=HBase,name=JvmMetrics
     119: invokespecial #19                 // Method javax/management/ObjectName."<init>":(Ljava/lang/String;)V
     122: astore        12
     124: new           #17                 // class javax/management/ObjectName
     127: dup
     128: ldc           #20                 // String Hadoop:service=HBase,name=RegionServer,sub=Server
     130: invokespecial #19                 // Method javax/management/ObjectName."<init>":(Ljava/lang/String;)V
     133: astore        13
     135: invokestatic  #21                 // Method org/apache/hadoop/hbase/util/JSONMetricUtil.getGcCollectorBeans:()Ljava/util/List;
     138: astore        14
     140: aconst_null
     141: astore        15
     143: aconst_null
     144: astore        16
     146: aload         14
     148: iconst_0
     149: invokeinterface #22,  2           // InterfaceMethod java/util/List.get:(I)Ljava/lang/Object;
     154: checkcast     #23                 // class java/lang/management/GarbageCollectorMXBean
     157: astore        15
     159: aload         14
     161: iconst_1
     162: invokeinterface #22,  2           // InterfaceMethod java/util/List.get:(I)Ljava/lang/Object;
     167: checkcast     #23                 // class java/lang/management/GarbageCollectorMXBean
     170: astore        16
     172: goto          177
     175: astore        17
     177: invokestatic  #25                 // Method org/apache/hadoop/hbase/util/JSONMetricUtil.getMemoryPools:()Ljava/util/List;
     180: astore        17
     182: aload_3
     183: ldc           #26                 // String pageTitle
     185: new           #27                 // class java/lang/StringBuilder
     188: dup
     189: invokespecial #28                 // Method java/lang/StringBuilder."<init>":()V
     192: ldc           #29                 // String Process info for PID:
     194: invokevirtual #30                 // Method java/lang/StringBuilder.append:(Ljava/lang/String;)Ljava/lang/StringBuilder;
     197: invokestatic  #31                 // Method org/apache/hadoop/hbase/util/JSONMetricUtil.getProcessPID:()Ljava/lang/String;
     200: invokevirtual #30                 // Method java/lang/StringBuilder.append:(Ljava/lang/String;)Ljava/lang/StringBuilder;
     203: invokevirtual #32                 // Method java/lang/StringBuilder.toString:()Ljava/lang/String;
     206: invokevirtual #33                 // Method javax/servlet/jsp/PageContext.setAttribute:(Ljava/lang/String;Ljava/lang/Object;)V
     209: aload         7
     211: bipush        10
     213: invokevirtual #15                 // Method javax/servlet/jsp/JspWriter.write:(I)V
     216: aload_1
     217: aload_2
     218: new           #27                 // class java/lang/StringBuilder
     221: dup
     222: invokespecial #28                 // Method java/lang/StringBuilder."<init>":()V
     225: ldc           #34                 // String header.jsp?
     227: invokevirtual #30                 // Method java/lang/StringBuilder.append:(Ljava/lang/String;)Ljava/lang/StringBuilder;
     230: ldc           #26                 // String pageTitle
     232: aload_1
     233: invokeinterface #35,  1           // InterfaceMethod javax/servlet/http/HttpServletRequest.getCharacterEncoding:()Ljava/lang/String;
     238: invokestatic  #36                 // Method org/apache/jasper/runtime/JspRuntimeLibrary.URLEncode:(Ljava/lang/String;Ljava/lang/String;)Ljava/lang/String;
     241: invokevirtual #30                 // Method java/lang/StringBuilder.append:(Ljava/lang/String;)Ljava/lang/StringBuilder;
     244: ldc           #37                 // String =
     246: invokevirtual #30                 // Method java/lang/StringBuilder.append:(Ljava/lang/String;)Ljava/lang/StringBuilder;
     249: ldc           #38                 // String ${pageTitle}
     251: ldc           #39                 // class java/lang/String
     253: aload         10
     255: aconst_null
     256: invokestatic  #40                 // Method org/apache/jasper/runtime/PageContextImpl.evaluateExpression:(Ljava/lang/String;Ljava/lang/Class;Ljavax/servlet/jsp/PageContext;Lorg/apache/jasper/runtime/ProtectedFunctionMapper;)Ljava/lang/Object;
     259: checkcast     #39                 // class java/lang/String
     262: aload_1
     263: invokeinterface #35,  1           // InterfaceMethod javax/servlet/http/HttpServletRequest.getCharacterEncoding:()Ljava/lang/String;
     268: invokestatic  #36                 // Method org/apache/jasper/runtime/JspRuntimeLibrary.URLEncode:(Ljava/lang/String;Ljava/lang/String;)Ljava/lang/String;
     271: invokevirtual #30                 // Method java/lang/StringBuilder.append:(Ljava/lang/String;)Ljava/lang/StringBuilder;
     274: invokevirtual #32                 // Method java/lang/StringBuilder.toString:()Ljava/lang/String;
     277: aload         7
     279: iconst_0
     280: invokestatic  #41                 // Method org/apache/jasper/runtime/JspRuntimeLibrary.include:(Ljavax/servlet/ServletRequest;Ljavax/servlet/ServletResponse;Ljava/lang/String;Ljavax/servlet/jsp/JspWriter;Z)V
     283: aload         7
     285: ldc           #42                 // String \n\n<div class=\"container-fluid content\">\n  <div class=\"row\">\n      <div class=\"page-header\">\n          <h1>
     287: invokevirtual #43                 // Method javax/servlet/jsp/JspWriter.write:(Ljava/lang/String;)V
     290: aload         7
     292: invokestatic  #44                 // Method org/apache/hadoop/hbase/util/JSONMetricUtil.getCommmand:()Ljava/lang/String;
     295: ldc           #45                 // String
     297: invokevirtual #46                 // Method java/lang/String.split:(Ljava/lang/String;)[Ljava/lang/String;
     300: iconst_0
     301: aaload
     302: invokevirtual #47                 // Method javax/servlet/jsp/JspWriter.print:(Ljava/lang/String;)V
     305: aload         7
     307: ldc           #48                 // String </h1>\n      </div>\n  </div>\n  <table class=\"table table-striped\" width=\"90%\" >\n    <tr>\n        <th>Started</th>\n        <th>Uptime</th>\n        <th>PID</th>\n        <th>JvmPauseMonitor Count </th>\n        <th>Owner</th>\n    </tr>\n    <tr>\n      <tr>\n        <td>
     309: invokevirtual #43                 // Method javax/servlet/jsp/JspWriter.write:(Ljava/lang/String;)V
     312: aload         7
     314: new           #49                 // class java/util/Date
     317: dup
     318: aload         11
     320: invokeinterface #50,  1           // InterfaceMethod java/lang/management/RuntimeMXBean.getStartTime:()J
     325: invokespecial #51                 // Method java/util/Date."<init>":(J)V
     328: invokevirtual #52                 // Method javax/servlet/jsp/JspWriter.print:(Ljava/lang/Object;)V
     331: aload         7
     333: ldc           #53                 // String </td>\n        <td>
     335: invokevirtual #43                 // Method javax/servlet/jsp/JspWriter.write:(Ljava/lang/String;)V
     338: aload         7
     340: aload         11
     342: invokeinterface #54,  1           // InterfaceMethod java/lang/management/RuntimeMXBean.getUptime:()J
     347: invokestatic  #55                 // Method org/apache/hadoop/hbase/procedure2/util/StringUtils.humanTimeDiff:(J)Ljava/lang/String;
     350: invokevirtual #47                 // Method javax/servlet/jsp/JspWriter.print:(Ljava/lang/String;)V
     353: aload         7
     355: ldc           #53                 // String </td>\n        <td>
     357: invokevirtual #43                 // Method javax/servlet/jsp/JspWriter.write:(Ljava/lang/String;)V
     360: aload         7
     362: invokestatic  #31                 // Method org/apache/hadoop/hbase/util/JSONMetricUtil.getProcessPID:()Ljava/lang/String;
     365: invokevirtual #47                 // Method javax/servlet/jsp/JspWriter.print:(Ljava/lang/String;)V
     368: aload         7
     370: ldc           #53                 // String </td>\n        <td>
     372: invokevirtual #43                 // Method javax/servlet/jsp/JspWriter.write:(Ljava/lang/String;)V
     375: aload         7
     377: aload         13
     379: ldc           #56                 // String pauseWarnThresholdExceeded
     381: invokestatic  #57                 // Method org/apache/hadoop/hbase/util/JSONMetricUtil.getValueFromMBean:(Ljavax/management/ObjectName;Ljava/lang/String;)Ljava/lang/Object;
     384: checkcast     #58                 // class java/lang/Long
     387: invokevirtual #59                 // Method java/lang/Long.longValue:()J
     390: aload         13
     392: ldc           #60                 // String pauseInfoThresholdExceeded
     394: invokestatic  #57                 // Method org/apache/hadoop/hbase/util/JSONMetricUtil.getValueFromMBean:(Ljavax/management/ObjectName;Ljava/lang/String;)Ljava/lang/Object;
     397: checkcast     #58                 // class java/lang/Long
     400: invokevirtual #59                 // Method java/lang/Long.longValue:()J
     403: ladd
     404: invokevirtual #61                 // Method javax/servlet/jsp/JspWriter.print:(J)V
     407: aload         7
     409: ldc           #53                 // String </td>\n        <td>
     411: invokevirtual #43                 // Method javax/servlet/jsp/JspWriter.write:(Ljava/lang/String;)V
     414: aload         7
     416: aload         11
     418: invokeinterface #62,  1           // InterfaceMethod java/lang/management/RuntimeMXBean.getSystemProperties:()Ljava/util/Map;
     423: ldc           #63                 // String user.name
     425: invokeinterface #64,  2           // InterfaceMethod java/util/Map.get:(Ljava/lang/Object;)Ljava/lang/Object;
     430: checkcast     #39                 // class java/lang/String
     433: invokevirtual #47                 // Method javax/servlet/jsp/JspWriter.print:(Ljava/lang/String;)V
     436: aload         7
     438: ldc           #65                 // String </td>\n      </tr>\n  </table>\n</div>\n<div class=\"container-fluid content\">\n  <div class=\"row\">\n    <div class=\"page-header\">\n    <h2>Threads</h2>\n    </div>\n    </div>\n  <table class=\"table table-striped\" width=\"90%\" >\n    <tr>\n        <th>ThreadsNew</th>\n        <th>ThreadsRunable</th>\n        <th>ThreadsBlocked</th>\n        <th>ThreadsWaiting</th>\n        <th>ThreadsTimeWaiting</th>\n        <th>ThreadsTerminated</th>\n    </tr>\n    <tr>\n      <tr>\n        <td>
     440: invokevirtual #43                 // Method javax/servlet/jsp/JspWriter.write:(Ljava/lang/String;)V
     443: aload         7
     445: aload         12
     447: ldc           #66                 // String ThreadsNew
     449: invokestatic  #57                 // Method org/apache/hadoop/hbase/util/JSONMetricUtil.getValueFromMBean:(Ljavax/management/ObjectName;Ljava/lang/String;)Ljava/lang/Object;
     452: invokevirtual #52                 // Method javax/servlet/jsp/JspWriter.print:(Ljava/lang/Object;)V
     455: aload         7
     457: ldc           #53                 // String </td>\n        <td>
     459: invokevirtual #43                 // Method javax/servlet/jsp/JspWriter.write:(Ljava/lang/String;)V
     462: aload         7
     464: aload         12
     466: ldc           #67                 // String ThreadsRunnable
     468: invokestatic  #57                 // Method org/apache/hadoop/hbase/util/JSONMetricUtil.getValueFromMBean:(Ljavax/management/ObjectName;Ljava/lang/String;)Ljava/lang/Object;
     471: invokevirtual #52                 // Method javax/servlet/jsp/JspWriter.print:(Ljava/lang/Object;)V
     474: aload         7
     476: ldc           #53                 // String </td>\n        <td>
     478: invokevirtual #43                 // Method javax/servlet/jsp/JspWriter.write:(Ljava/lang/String;)V
     481: aload         7
     483: aload         12
     485: ldc           #68                 // String ThreadsBlocked
     487: invokestatic  #57                 // Method org/apache/hadoop/hbase/util/JSONMetricUtil.getValueFromMBean:(Ljavax/management/ObjectName;Ljava/lang/String;)Ljava/lang/Object;
     490: invokevirtual #52                 // Method javax/servlet/jsp/JspWriter.print:(Ljava/lang/Object;)V
     493: aload         7
     495: ldc           #53                 // String </td>\n        <td>
     497: invokevirtual #43                 // Method javax/servlet/jsp/JspWriter.write:(Ljava/lang/String;)V
     500: aload         7
     502: aload         12
     504: ldc           #69                 // String ThreadsWaiting
     506: invokestatic  #57                 // Method org/apache/hadoop/hbase/util/JSONMetricUtil.getValueFromMBean:(Ljavax/management/ObjectName;Ljava/lang/String;)Ljava/lang/Object;
     509: invokevirtual #52                 // Method javax/servlet/jsp/JspWriter.print:(Ljava/lang/Object;)V
     512: aload         7
     514: ldc           #53                 // String </td>\n        <td>
     516: invokevirtual #43                 // Method javax/servlet/jsp/JspWriter.write:(Ljava/lang/String;)V
     519: aload         7
     521: aload         12
     523: ldc           #70                 // String ThreadsTimedWaiting
     525: invokestatic  #57                 // Method org/apache/hadoop/hbase/util/JSONMetricUtil.getValueFromMBean:(Ljavax/management/ObjectName;Ljava/lang/String;)Ljava/lang/Object;
     528: invokevirtual #52                 // Method javax/servlet/jsp/JspWriter.print:(Ljava/lang/Object;)V
     531: aload         7
     533: ldc           #53                 // String </td>\n        <td>
     535: invokevirtual #43                 // Method javax/servlet/jsp/JspWriter.write:(Ljava/lang/String;)V
     538: aload         7
     540: aload         12
     542: ldc           #71                 // String ThreadsTerminated
     544: invokestatic  #57                 // Method org/apache/hadoop/hbase/util/JSONMetricUtil.getValueFromMBean:(Ljavax/management/ObjectName;Ljava/lang/String;)Ljava/lang/Object;
     547: invokevirtual #52                 // Method javax/servlet/jsp/JspWriter.print:(Ljava/lang/Object;)V
     550: aload         7
     552: ldc           #72                 // String </td>\n      </tr>\n  </table>\n</div>\n<div class=\"container-fluid content\">\n  <div class=\"row\">\n    <div class=\"page-header\">\n    <h2>GC Collectors</h2>\n    </div>\n    </div>\n
     554: invokevirtual #43                 // Method javax/servlet/jsp/JspWriter.write:(Ljava/lang/String;)V
     557: aload         14
     559: invokeinterface #73,  1           // InterfaceMethod java/util/List.size:()I
     564: iconst_2
     565: if_icmpne     748
     568: aload         7
     570: ldc           #74                 // String \n<div class=\"tabbable\">\n  <ul class=\"nav nav-pills\">\n    <li class=\"active\">\n      <a href=\"#tab_gc1\" data-toggle=\"tab\">
     572: invokevirtual #43                 // Method javax/servlet/jsp/JspWriter.write:(Ljava/lang/String;)V
     575: aload         7
     577: aload         15
     579: invokeinterface #75,  1           // InterfaceMethod java/lang/management/GarbageCollectorMXBean.getName:()Ljava/lang/String;
     584: invokevirtual #47                 // Method javax/servlet/jsp/JspWriter.print:(Ljava/lang/String;)V
     587: aload         7
     589: ldc           #76                 // String </a>\n    </li>\n    <li class=\"\">\n      <a href=\"#tab_gc2\" data-toggle=\"tab\">
     591: invokevirtual #43                 // Method javax/servlet/jsp/JspWriter.write:(Ljava/lang/String;)V
     594: aload         7
     596: aload         16
     598: invokeinterface #75,  1           // InterfaceMethod java/lang/management/GarbageCollectorMXBean.getName:()Ljava/lang/String;
     603: invokevirtual #47                 // Method javax/servlet/jsp/JspWriter.print:(Ljava/lang/String;)V
     606: aload         7
     608: ldc           #77                 // String </a>\n     </li>\n  </ul>\n    <div class=\"tab-content\" style=\"padding-bottom: 9px; border-bottom: 1px solid #ddd;\">\n      <div class=\"tab-pane active\" id=\"tab_gc1\">\n          <table class=\"table table-striped\">\n            <tr>\n              <th>Collection Count</th>\n              <th>Collection Time</th>\n              <th>Last duration</th>\n            </tr>\n            <tr>\n              <td>
     610: invokevirtual #43                 // Method javax/servlet/jsp/JspWriter.write:(Ljava/lang/String;)V
     613: aload         7
     615: aload         15
     617: invokeinterface #78,  1           // InterfaceMethod java/lang/management/GarbageCollectorMXBean.getCollectionCount:()J
     622: invokevirtual #61                 // Method javax/servlet/jsp/JspWriter.print:(J)V
     625: aload         7
     627: ldc           #79                 // String </td>\n              <td>
     629: invokevirtual #43                 // Method javax/servlet/jsp/JspWriter.write:(Ljava/lang/String;)V
     632: aload         7
     634: aload         15
     636: invokeinterface #80,  1           // InterfaceMethod java/lang/management/GarbageCollectorMXBean.getCollectionTime:()J
     641: invokestatic  #55                 // Method org/apache/hadoop/hbase/procedure2/util/StringUtils.humanTimeDiff:(J)Ljava/lang/String;
     644: invokevirtual #47                 // Method javax/servlet/jsp/JspWriter.print:(Ljava/lang/String;)V
     647: aload         7
     649: ldc           #81                 // String  </td>\n              <td>
     651: invokevirtual #43                 // Method javax/servlet/jsp/JspWriter.write:(Ljava/lang/String;)V
     654: aload         7
     656: aload         15
     658: invokeinterface #82,  1           // InterfaceMethod java/lang/management/GarbageCollectorMXBean.getObjectName:()Ljavax/management/ObjectName;
     663: invokestatic  #83                 // Method org/apache/hadoop/hbase/util/JSONMetricUtil.getLastGcDuration:(Ljavax/management/ObjectName;)J
     666: invokestatic  #55                 // Method org/apache/hadoop/hbase/procedure2/util/StringUtils.humanTimeDiff:(J)Ljava/lang/String;
     669: invokevirtual #47                 // Method javax/servlet/jsp/JspWriter.print:(Ljava/lang/String;)V
     672: aload         7
     674: ldc           #84                 // String </td>\n            </tr>\n          </table>\n      </div>\n      <div class=\"tab-pane\" id=\"tab_gc2\">\n        <table class=\"table table-striped\">\n          <tr>\n            <th>Collection Count</th>\n            <th>Collection Time</th>\n             <th>Last duration</th>\n          </tr>\n          <tr>\n            <td>
     676: invokevirtual #43                 // Method javax/servlet/jsp/JspWriter.write:(Ljava/lang/String;)V
     679: aload         7
     681: aload         16
     683: invokeinterface #78,  1           // InterfaceMethod java/lang/management/GarbageCollectorMXBean.getCollectionCount:()J
     688: invokevirtual #61                 // Method javax/servlet/jsp/JspWriter.print:(J)V
     691: aload         7
     693: ldc           #85                 // String </td>\n            <td>
     695: invokevirtual #43                 // Method javax/servlet/jsp/JspWriter.write:(Ljava/lang/String;)V
     698: aload         7
     700: aload         16
     702: invokeinterface #80,  1           // InterfaceMethod java/lang/management/GarbageCollectorMXBean.getCollectionTime:()J
     707: invokestatic  #55                 // Method org/apache/hadoop/hbase/procedure2/util/StringUtils.humanTimeDiff:(J)Ljava/lang/String;
     710: invokevirtual #47                 // Method javax/servlet/jsp/JspWriter.print:(Ljava/lang/String;)V
     713: aload         7
     715: ldc           #86                 // String  </td>\n            <td>
     717: invokevirtual #43                 // Method javax/servlet/jsp/JspWriter.write:(Ljava/lang/String;)V
     720: aload         7
     722: aload         16
     724: invokeinterface #82,  1           // InterfaceMethod java/lang/management/GarbageCollectorMXBean.getObjectName:()Ljavax/management/ObjectName;
     729: invokestatic  #83                 // Method org/apache/hadoop/hbase/util/JSONMetricUtil.getLastGcDuration:(Ljavax/management/ObjectName;)J
     732: invokestatic  #55                 // Method org/apache/hadoop/hbase/procedure2/util/StringUtils.humanTimeDiff:(J)Ljava/lang/String;
     735: invokevirtual #47                 // Method javax/servlet/jsp/JspWriter.print:(Ljava/lang/String;)V
     738: aload         7
     740: ldc           #87                 // String </td>\n          </tr>\n          </table>\n      </div>\n      </div>\n  </div>\n
     742: invokevirtual #43                 // Method javax/servlet/jsp/JspWriter.write:(Ljava/lang/String;)V
     745: goto          755
     748: aload         7
     750: ldc           #88                 // String \n  <p> Can not display GC Collector stats.</p>\n
     752: invokevirtual #43                 // Method javax/servlet/jsp/JspWriter.write:(Ljava/lang/String;)V
     755: aload         7
     757: ldc           #89                 // String \n  Total GC Collection time:
     759: invokevirtual #43                 // Method javax/servlet/jsp/JspWriter.write:(Ljava/lang/String;)V
     762: aload         7
     764: aload         15
     766: invokeinterface #80,  1           // InterfaceMethod java/lang/management/GarbageCollectorMXBean.getCollectionTime:()J
     771: aload         16
     773: invokeinterface #80,  1           // InterfaceMethod java/lang/management/GarbageCollectorMXBean.getCollectionTime:()J
     778: ladd
     779: invokestatic  #55                 // Method org/apache/hadoop/hbase/procedure2/util/StringUtils.humanTimeDiff:(J)Ljava/lang/String;
     782: invokevirtual #47                 // Method javax/servlet/jsp/JspWriter.print:(Ljava/lang/String;)V
     785: aload         7
     787: ldc           #90                 // String \n</div>\n
     789: invokevirtual #43                 // Method javax/servlet/jsp/JspWriter.write:(Ljava/lang/String;)V
     792: aload         17
     794: invokeinterface #91,  1           // InterfaceMethod java/util/List.iterator:()Ljava/util/Iterator;
     799: astore        18
     801: aload         18
     803: invokeinterface #92,  1           // InterfaceMethod java/util/Iterator.hasNext:()Z
     808: ifeq          1017
     811: aload         18
     813: invokeinterface #93,  1           // InterfaceMethod java/util/Iterator.next:()Ljava/lang/Object;
     818: checkcast     #94                 // class java/lang/management/MemoryPoolMXBean
     821: astore        19
     823: aload         19
     825: invokeinterface #95,  1           // InterfaceMethod java/lang/management/MemoryPoolMXBean.getName:()Ljava/lang/String;
     830: ldc           #96                 // String Cache
     832: invokevirtual #97                 // Method java/lang/String.contains:(Ljava/lang/CharSequence;)Z
     835: ifeq          841
     838: goto          801
     841: aload         7
     843: ldc           #98                 // String \n<div class=\"container-fluid content\">\n  <div class=\"row\">\n      <div class=\"page-header\">\n          <h2>
     845: invokevirtual #43                 // Method javax/servlet/jsp/JspWriter.write:(Ljava/lang/String;)V
     848: aload         7
     850: aload         19
     852: invokeinterface #95,  1           // InterfaceMethod java/lang/management/MemoryPoolMXBean.getName:()Ljava/lang/String;
     857: invokevirtual #47                 // Method javax/servlet/jsp/JspWriter.print:(Ljava/lang/String;)V
     860: aload         7
     862: ldc           #99                 // String </h2>\n      </div>\n  </div>\n  <table class=\"table table-striped\" width=\"90%\" >\n    <tr>\n        <th>Commited</th>\n        <th>Init</th>\n        <th>Max</th>\n        <th>Used</th>\n        <th>Utilization [%]</th>\n    </tr>\n    <tr>\n      <tr>\n        <td>
     864: invokevirtual #43                 // Method javax/servlet/jsp/JspWriter.write:(Ljava/lang/String;)V
     867: aload         7
     869: aload         19
     871: invokeinterface #100,  1          // InterfaceMethod java/lang/management/MemoryPoolMXBean.getUsage:()Ljava/lang/management/MemoryUsage;
     876: invokevirtual #101                // Method java/lang/management/MemoryUsage.getCommitted:()J
     879: ldc           #102                // String B
     881: iconst_1
     882: invokestatic  #103                // Method org/apache/hadoop/util/StringUtils$TraditionalBinaryPrefix.long2String:(JLjava/lang/String;I)Ljava/lang/String;
     885: invokevirtual #47                 // Method javax/servlet/jsp/JspWriter.print:(Ljava/lang/String;)V
     888: aload         7
     890: ldc           #53                 // String </td>\n        <td>
     892: invokevirtual #43                 // Method javax/servlet/jsp/JspWriter.write:(Ljava/lang/String;)V
     895: aload         7
     897: aload         19
     899: invokeinterface #100,  1          // InterfaceMethod java/lang/management/MemoryPoolMXBean.getUsage:()Ljava/lang/management/MemoryUsage;
     904: invokevirtual #104                // Method java/lang/management/MemoryUsage.getInit:()J
     907: ldc           #102                // String B
     909: iconst_1
     910: invokestatic  #103                // Method org/apache/hadoop/util/StringUtils$TraditionalBinaryPrefix.long2String:(JLjava/lang/String;I)Ljava/lang/String;
     913: invokevirtual #47                 // Method javax/servlet/jsp/JspWriter.print:(Ljava/lang/String;)V
     916: aload         7
     918: ldc           #53                 // String </td>\n        <td>
     920: invokevirtual #43                 // Method javax/servlet/jsp/JspWriter.write:(Ljava/lang/String;)V
     923: aload         7
     925: aload         19
     927: invokeinterface #100,  1          // InterfaceMethod java/lang/management/MemoryPoolMXBean.getUsage:()Ljava/lang/management/MemoryUsage;
     932: invokevirtual #105                // Method java/lang/management/MemoryUsage.getMax:()J
     935: ldc           #102                // String B
     937: iconst_1
     938: invokestatic  #103                // Method org/apache/hadoop/util/StringUtils$TraditionalBinaryPrefix.long2String:(JLjava/lang/String;I)Ljava/lang/String;
     941: invokevirtual #47                 // Method javax/servlet/jsp/JspWriter.print:(Ljava/lang/String;)V
     944: aload         7
     946: ldc           #53                 // String </td>\n        <td>
     948: invokevirtual #43                 // Method javax/servlet/jsp/JspWriter.write:(Ljava/lang/String;)V
     951: aload         7
     953: aload         19
     955: invokeinterface #100,  1          // InterfaceMethod java/lang/management/MemoryPoolMXBean.getUsage:()Ljava/lang/management/MemoryUsage;
     960: invokevirtual #106                // Method java/lang/management/MemoryUsage.getUsed:()J
     963: ldc           #102                // String B
     965: iconst_1
     966: invokestatic  #103                // Method org/apache/hadoop/util/StringUtils$TraditionalBinaryPrefix.long2String:(JLjava/lang/String;I)Ljava/lang/String;
     969: invokevirtual #47                 // Method javax/servlet/jsp/JspWriter.print:(Ljava/lang/String;)V
     972: aload         7
     974: ldc           #53                 // String </td>\n        <td>
     976: invokevirtual #43                 // Method javax/servlet/jsp/JspWriter.write:(Ljava/lang/String;)V
     979: aload         7
     981: aload         19
     983: invokeinterface #100,  1          // InterfaceMethod java/lang/management/MemoryPoolMXBean.getUsage:()Ljava/lang/management/MemoryUsage;
     988: invokevirtual #106                // Method java/lang/management/MemoryUsage.getUsed:()J
     991: aload         19
     993: invokeinterface #100,  1          // InterfaceMethod java/lang/management/MemoryPoolMXBean.getUsage:()Ljava/lang/management/MemoryUsage;
     998: invokevirtual #101                // Method java/lang/management/MemoryUsage.getCommitted:()J
    1001: invokestatic  #107                // Method org/apache/hadoop/hbase/util/JSONMetricUtil.calcPercentage:(JJ)F
    1004: invokevirtual #108                // Method javax/servlet/jsp/JspWriter.print:(F)V
    1007: aload         7
    1009: ldc           #109                // String </td>\n      </tr>\n  </table>\n</div>\n
    1011: invokevirtual #43                 // Method javax/servlet/jsp/JspWriter.write:(Ljava/lang/String;)V
    1014: goto          801
    1017: aload         7
    1019: bipush        10
    1021: invokevirtual #15                 // Method javax/servlet/jsp/JspWriter.write:(I)V
    1024: aload         7
    1026: bipush        10
    1028: invokevirtual #15                 // Method javax/servlet/jsp/JspWriter.write:(I)V
    1031: aload_1
    1032: aload_2
    1033: ldc           #110                // String footer.jsp
    1035: aload         7
    1037: iconst_0
    1038: invokestatic  #41                 // Method org/apache/jasper/runtime/JspRuntimeLibrary.include:(Ljavax/servlet/ServletRequest;Ljavax/servlet/ServletResponse;Ljava/lang/String;Ljavax/servlet/jsp/JspWriter;Z)V
    1041: aload         7
    1043: bipush        10
    1045: invokevirtual #15                 // Method javax/servlet/jsp/JspWriter.write:(I)V
    1048: getstatic     #5                  // Field _jspxFactory:Ljavax/servlet/jsp/JspFactory;
    1051: aload         10
    1053: invokevirtual #111                // Method javax/servlet/jsp/JspFactory.releasePageContext:(Ljavax/servlet/jsp/PageContext;)V
    1056: goto          1140
    1059: astore        11
    1061: aload         11
    1063: instanceof    #113                // class javax/servlet/jsp/SkipPageException
    1066: ifne          1116
    1069: aload         9
    1071: astore        7
    1073: aload         7
    1075: ifnull        1091
    1078: aload         7
    1080: invokevirtual #114                // Method javax/servlet/jsp/JspWriter.getBufferSize:()I
    1083: ifeq          1091
    1086: aload         7
    1088: invokevirtual #115                // Method javax/servlet/jsp/JspWriter.clearBuffer:()V
    1091: aload         10
    1093: ifnull        1106
    1096: aload         10
    1098: aload         11
    1100: invokevirtual #116                // Method javax/servlet/jsp/PageContext.handlePageException:(Ljava/lang/Throwable;)V
    1103: goto          1116
    1106: new           #117                // class javax/servlet/ServletException
    1109: dup
    1110: aload         11
    1112: invokespecial #118                // Method javax/servlet/ServletException."<init>":(Ljava/lang/Throwable;)V
    1115: athrow
    1116: getstatic     #5                  // Field _jspxFactory:Ljavax/servlet/jsp/JspFactory;
    1119: aload         10
    1121: invokevirtual #111                // Method javax/servlet/jsp/JspFactory.releasePageContext:(Ljavax/servlet/jsp/PageContext;)V
    1124: goto          1140
    1127: astore        20
    1129: getstatic     #5                  // Field _jspxFactory:Ljavax/servlet/jsp/JspFactory;
    1132: aload         10
    1134: invokevirtual #111                // Method javax/servlet/jsp/JspFactory.releasePageContext:(Ljavax/servlet/jsp/PageContext;)V
    1137: aload         20
    1139: athrow
    1140: return
    Exception table:
       from    to  target type
         146   172   175   Class java/lang/IndexOutOfBoundsException
          23  1048  1059   Class java/lang/Throwable
          23  1048  1127   any
        1059  1116  1127   any
        1127  1129  1127   any

  static {};
    Code:
       0: invokestatic  #119                // Method javax/servlet/jsp/JspFactory.getDefaultFactory:()Ljavax/servlet/jsp/JspFactory;
       3: putstatic     #5                  // Field _jspxFactory:Ljavax/servlet/jsp/JspFactory;
       6: return
}
