Compiled from "ProcedureWALFormat.java"
public class org.apache.hadoop.hbase.procedure2.store.wal.ProcedureWALFormat$InvalidWALDataException extends java.io.IOException {
  public org.apache.hadoop.hbase.procedure2.store.wal.ProcedureWALFormat$InvalidWALDataException(java.lang.String);
    Code:
       0: aload_0
       1: aload_1
       2: invokespecial #1                  // Method java/io/IOException."<init>":(Ljava/lang/String;)V
       5: return

  public org.apache.hadoop.hbase.procedure2.store.wal.ProcedureWALFormat$InvalidWALDataException(java.lang.Throwable);
    Code:
       0: aload_0
       1: aload_1
       2: invokespecial #2                  // Method java/io/IOException."<init>":(Ljava/lang/Throwable;)V
       5: return
}
