Compiled from "ProcedureExecutor.java"
final class org.apache.hadoop.hbase.procedure2.ProcedureExecutor$KeepAliveWorkerThread extends org.apache.hadoop.hbase.procedure2.ProcedureExecutor<TEnvironment>.WorkerThread {
  final org.apache.hadoop.hbase.procedure2.ProcedureExecutor this$0;

  public org.apache.hadoop.hbase.procedure2.ProcedureExecutor$KeepAliveWorkerThread(org.apache.hadoop.hbase.procedure2.ProcedureExecutor, java.lang.ThreadGroup);
    Code:
       0: aload_0
       1: aload_1
       2: putfield      #1                  // Field this$0:Lorg/apache/hadoop/hbase/procedure2/ProcedureExecutor;
       5: aload_0
       6: aload_1
       7: aload_2
       8: ldc           #2                  // String KeepAlivePEWorker-
      10: invokespecial #3                  // Method org/apache/hadoop/hbase/procedure2/ProcedureExecutor$WorkerThread."<init>":(Lorg/apache/hadoop/hbase/procedure2/ProcedureExecutor;Ljava/lang/ThreadGroup;Ljava/lang/String;)V
      13: return

  protected boolean keepAlive(long);
    Code:
       0: invokestatic  #4                  // Method org/apache/hadoop/hbase/util/EnvironmentEdgeManager.currentTime:()J
       3: lload_1
       4: lsub
       5: aload_0
       6: getfield      #1                  // Field this$0:Lorg/apache/hadoop/hbase/procedure2/ProcedureExecutor;
       9: invokestatic  #5                  // Method org/apache/hadoop/hbase/procedure2/ProcedureExecutor.access$700:(Lorg/apache/hadoop/hbase/procedure2/ProcedureExecutor;)J
      12: lcmp
      13: ifge          20
      16: iconst_1
      17: goto          21
      20: iconst_0
      21: ireturn
}
