Compiled from "ProfileServlet.java"
public class org.apache.hadoop.hbase.http.ProfileServlet$DisabledServlet extends javax.servlet.http.HttpServlet {
  public org.apache.hadoop.hbase.http.ProfileServlet$DisabledServlet();
    Code:
       0: aload_0
       1: invokespecial #1                  // Method javax/servlet/http/HttpServlet."<init>":()V
       4: return

  protected void doGet(javax.servlet.http.HttpServletRequest, javax.servlet.http.HttpServletResponse) throws java.io.IOException;
    Code:
       0: aload_2
       1: sipush        500
       4: invokeinterface #3,  2            // InterfaceMethod javax/servlet/http/HttpServletResponse.setStatus:(I)V
       9: aload_2
      10: invokestatic  #4                  // Method org/apache/hadoop/hbase/http/ProfileServlet.setResponseHeader:(Ljavax/servlet/http/HttpServletResponse;)V
      13: aload_2
      14: invokeinterface #5,  1            // InterfaceMethod javax/servlet/http/HttpServletResponse.getWriter:()Ljava/io/PrintWriter;
      19: ldc           #6                  // String The profiler servlet was disabled at startup.\n\nPlease ensure the prerequsites for the Profiler Servlet have been installed and the\nenvironment is properly configured. For more information please see\nhttp://hbase.apache.org/book.html#profiler\n
      21: invokevirtual #7                  // Method java/io/PrintWriter.write:(Ljava/lang/String;)V
      24: return
}
