Compiled from "QuotaSettingsFactory.java"
public class org.apache.hadoop.hbase.quotas.QuotaSettingsFactory {
  public org.apache.hadoop.hbase.quotas.QuotaSettingsFactory();
    Code:
       0: aload_0
       1: invokespecial #1                  // Method java/lang/Object."<init>":()V
       4: return

  static java.util.List<org.apache.hadoop.hbase.quotas.QuotaSettings> fromUserQuotas(java.lang.String, org.apache.hadoop.hbase.shaded.protobuf.generated.QuotaProtos$Quotas);
    Code:
       0: aload_0
       1: aconst_null
       2: aconst_null
       3: aconst_null
       4: aload_1
       5: invokestatic  #2                  // Method fromQuotas:(Ljava/lang/String;Lorg/apache/hadoop/hbase/TableName;Ljava/lang/String;Ljava/lang/String;Lorg/apache/hadoop/hbase/shaded/protobuf/generated/QuotaProtos$Quotas;)Ljava/util/List;
       8: areturn

  static java.util.List<org.apache.hadoop.hbase.quotas.QuotaSettings> fromUserQuotas(java.lang.String, org.apache.hadoop.hbase.TableName, org.apache.hadoop.hbase.shaded.protobuf.generated.QuotaProtos$Quotas);
    Code:
       0: aload_0
       1: aload_1
       2: aconst_null
       3: aconst_null
       4: aload_2
       5: invokestatic  #2                  // Method fromQuotas:(Ljava/lang/String;Lorg/apache/hadoop/hbase/TableName;Ljava/lang/String;Ljava/lang/String;Lorg/apache/hadoop/hbase/shaded/protobuf/generated/QuotaProtos$Quotas;)Ljava/util/List;
       8: areturn

  static java.util.List<org.apache.hadoop.hbase.quotas.QuotaSettings> fromUserQuotas(java.lang.String, java.lang.String, org.apache.hadoop.hbase.shaded.protobuf.generated.QuotaProtos$Quotas);
    Code:
       0: aload_0
       1: aconst_null
       2: aload_1
       3: aconst_null
       4: aload_2
       5: invokestatic  #2                  // Method fromQuotas:(Ljava/lang/String;Lorg/apache/hadoop/hbase/TableName;Ljava/lang/String;Ljava/lang/String;Lorg/apache/hadoop/hbase/shaded/protobuf/generated/QuotaProtos$Quotas;)Ljava/util/List;
       8: areturn

  static java.util.List<org.apache.hadoop.hbase.quotas.QuotaSettings> fromTableQuotas(org.apache.hadoop.hbase.TableName, org.apache.hadoop.hbase.shaded.protobuf.generated.QuotaProtos$Quotas);
    Code:
       0: aconst_null
       1: aload_0
       2: aconst_null
       3: aconst_null
       4: aload_1
       5: invokestatic  #2                  // Method fromQuotas:(Ljava/lang/String;Lorg/apache/hadoop/hbase/TableName;Ljava/lang/String;Ljava/lang/String;Lorg/apache/hadoop/hbase/shaded/protobuf/generated/QuotaProtos$Quotas;)Ljava/util/List;
       8: areturn

  static java.util.List<org.apache.hadoop.hbase.quotas.QuotaSettings> fromNamespaceQuotas(java.lang.String, org.apache.hadoop.hbase.shaded.protobuf.generated.QuotaProtos$Quotas);
    Code:
       0: aconst_null
       1: aconst_null
       2: aload_0
       3: aconst_null
       4: aload_1
       5: invokestatic  #2                  // Method fromQuotas:(Ljava/lang/String;Lorg/apache/hadoop/hbase/TableName;Ljava/lang/String;Ljava/lang/String;Lorg/apache/hadoop/hbase/shaded/protobuf/generated/QuotaProtos$Quotas;)Ljava/util/List;
       8: areturn

  static java.util.List<org.apache.hadoop.hbase.quotas.QuotaSettings> fromRegionServerQuotas(java.lang.String, org.apache.hadoop.hbase.shaded.protobuf.generated.QuotaProtos$Quotas);
    Code:
       0: aconst_null
       1: aconst_null
       2: aconst_null
       3: aload_0
       4: aload_1
       5: invokestatic  #2                  // Method fromQuotas:(Ljava/lang/String;Lorg/apache/hadoop/hbase/TableName;Ljava/lang/String;Ljava/lang/String;Lorg/apache/hadoop/hbase/shaded/protobuf/generated/QuotaProtos$Quotas;)Ljava/util/List;
       8: areturn

  protected static java.util.List<org.apache.hadoop.hbase.quotas.QuotaSettings> fromThrottle(java.lang.String, org.apache.hadoop.hbase.TableName, java.lang.String, java.lang.String, org.apache.hadoop.hbase.shaded.protobuf.generated.QuotaProtos$Throttle);
    Code:
       0: new           #3                  // class java/util/ArrayList
       3: dup
       4: invokespecial #4                  // Method java/util/ArrayList."<init>":()V
       7: astore        5
       9: aload         4
      11: invokevirtual #16                 // Method org/apache/hadoop/hbase/shaded/protobuf/generated/QuotaProtos$Throttle.hasReqNum:()Z
      14: ifeq          40
      17: aload         5
      19: aload_0
      20: aload_1
      21: aload_2
      22: aload_3
      23: getstatic     #17                 // Field org/apache/hadoop/hbase/quotas/ThrottleType.REQUEST_NUMBER:Lorg/apache/hadoop/hbase/quotas/ThrottleType;
      26: aload         4
      28: invokevirtual #18                 // Method org/apache/hadoop/hbase/shaded/protobuf/generated/QuotaProtos$Throttle.getReqNum:()Lorg/apache/hadoop/hbase/shaded/protobuf/generated/QuotaProtos$TimedQuota;
      31: invokestatic  #19                 // Method org/apache/hadoop/hbase/quotas/ThrottleSettings.fromTimedQuota:(Ljava/lang/String;Lorg/apache/hadoop/hbase/TableName;Ljava/lang/String;Ljava/lang/String;Lorg/apache/hadoop/hbase/quotas/ThrottleType;Lorg/apache/hadoop/hbase/shaded/protobuf/generated/QuotaProtos$TimedQuota;)Lorg/apache/hadoop/hbase/quotas/ThrottleSettings;
      34: invokeinterface #12,  2           // InterfaceMethod java/util/List.add:(Ljava/lang/Object;)Z
      39: pop
      40: aload         4
      42: invokevirtual #20                 // Method org/apache/hadoop/hbase/shaded/protobuf/generated/QuotaProtos$Throttle.hasReqSize:()Z
      45: ifeq          71
      48: aload         5
      50: aload_0
      51: aload_1
      52: aload_2
      53: aload_3
      54: getstatic     #21                 // Field org/apache/hadoop/hbase/quotas/ThrottleType.REQUEST_SIZE:Lorg/apache/hadoop/hbase/quotas/ThrottleType;
      57: aload         4
      59: invokevirtual #22                 // Method org/apache/hadoop/hbase/shaded/protobuf/generated/QuotaProtos$Throttle.getReqSize:()Lorg/apache/hadoop/hbase/shaded/protobuf/generated/QuotaProtos$TimedQuota;
      62: invokestatic  #19                 // Method org/apache/hadoop/hbase/quotas/ThrottleSettings.fromTimedQuota:(Ljava/lang/String;Lorg/apache/hadoop/hbase/TableName;Ljava/lang/String;Ljava/lang/String;Lorg/apache/hadoop/hbase/quotas/ThrottleType;Lorg/apache/hadoop/hbase/shaded/protobuf/generated/QuotaProtos$TimedQuota;)Lorg/apache/hadoop/hbase/quotas/ThrottleSettings;
      65: invokeinterface #12,  2           // InterfaceMethod java/util/List.add:(Ljava/lang/Object;)Z
      70: pop
      71: aload         4
      73: invokevirtual #23                 // Method org/apache/hadoop/hbase/shaded/protobuf/generated/QuotaProtos$Throttle.hasWriteNum:()Z
      76: ifeq          102
      79: aload         5
      81: aload_0
      82: aload_1
      83: aload_2
      84: aload_3
      85: getstatic     #24                 // Field org/apache/hadoop/hbase/quotas/ThrottleType.WRITE_NUMBER:Lorg/apache/hadoop/hbase/quotas/ThrottleType;
      88: aload         4
      90: invokevirtual #25                 // Method org/apache/hadoop/hbase/shaded/protobuf/generated/QuotaProtos$Throttle.getWriteNum:()Lorg/apache/hadoop/hbase/shaded/protobuf/generated/QuotaProtos$TimedQuota;
      93: invokestatic  #19                 // Method org/apache/hadoop/hbase/quotas/ThrottleSettings.fromTimedQuota:(Ljava/lang/String;Lorg/apache/hadoop/hbase/TableName;Ljava/lang/String;Ljava/lang/String;Lorg/apache/hadoop/hbase/quotas/ThrottleType;Lorg/apache/hadoop/hbase/shaded/protobuf/generated/QuotaProtos$TimedQuota;)Lorg/apache/hadoop/hbase/quotas/ThrottleSettings;
      96: invokeinterface #12,  2           // InterfaceMethod java/util/List.add:(Ljava/lang/Object;)Z
     101: pop
     102: aload         4
     104: invokevirtual #26                 // Method org/apache/hadoop/hbase/shaded/protobuf/generated/QuotaProtos$Throttle.hasWriteSize:()Z
     107: ifeq          133
     110: aload         5
     112: aload_0
     113: aload_1
     114: aload_2
     115: aload_3
     116: getstatic     #27                 // Field org/apache/hadoop/hbase/quotas/ThrottleType.WRITE_SIZE:Lorg/apache/hadoop/hbase/quotas/ThrottleType;
     119: aload         4
     121: invokevirtual #28                 // Method org/apache/hadoop/hbase/shaded/protobuf/generated/QuotaProtos$Throttle.getWriteSize:()Lorg/apache/hadoop/hbase/shaded/protobuf/generated/QuotaProtos$TimedQuota;
     124: invokestatic  #19                 // Method org/apache/hadoop/hbase/quotas/ThrottleSettings.fromTimedQuota:(Ljava/lang/String;Lorg/apache/hadoop/hbase/TableName;Ljava/lang/String;Ljava/lang/String;Lorg/apache/hadoop/hbase/quotas/ThrottleType;Lorg/apache/hadoop/hbase/shaded/protobuf/generated/QuotaProtos$TimedQuota;)Lorg/apache/hadoop/hbase/quotas/ThrottleSettings;
     127: invokeinterface #12,  2           // InterfaceMethod java/util/List.add:(Ljava/lang/Object;)Z
     132: pop
     133: aload         4
     135: invokevirtual #29                 // Method org/apache/hadoop/hbase/shaded/protobuf/generated/QuotaProtos$Throttle.hasReadNum:()Z
     138: ifeq          164
     141: aload         5
     143: aload_0
     144: aload_1
     145: aload_2
     146: aload_3
     147: getstatic     #30                 // Field org/apache/hadoop/hbase/quotas/ThrottleType.READ_NUMBER:Lorg/apache/hadoop/hbase/quotas/ThrottleType;
     150: aload         4
     152: invokevirtual #31                 // Method org/apache/hadoop/hbase/shaded/protobuf/generated/QuotaProtos$Throttle.getReadNum:()Lorg/apache/hadoop/hbase/shaded/protobuf/generated/QuotaProtos$TimedQuota;
     155: invokestatic  #19                 // Method org/apache/hadoop/hbase/quotas/ThrottleSettings.fromTimedQuota:(Ljava/lang/String;Lorg/apache/hadoop/hbase/TableName;Ljava/lang/String;Ljava/lang/String;Lorg/apache/hadoop/hbase/quotas/ThrottleType;Lorg/apache/hadoop/hbase/shaded/protobuf/generated/QuotaProtos$TimedQuota;)Lorg/apache/hadoop/hbase/quotas/ThrottleSettings;
     158: invokeinterface #12,  2           // InterfaceMethod java/util/List.add:(Ljava/lang/Object;)Z
     163: pop
     164: aload         4
     166: invokevirtual #32                 // Method org/apache/hadoop/hbase/shaded/protobuf/generated/QuotaProtos$Throttle.hasReadSize:()Z
     169: ifeq          195
     172: aload         5
     174: aload_0
     175: aload_1
     176: aload_2
     177: aload_3
     178: getstatic     #33                 // Field org/apache/hadoop/hbase/quotas/ThrottleType.READ_SIZE:Lorg/apache/hadoop/hbase/quotas/ThrottleType;
     181: aload         4
     183: invokevirtual #34                 // Method org/apache/hadoop/hbase/shaded/protobuf/generated/QuotaProtos$Throttle.getReadSize:()Lorg/apache/hadoop/hbase/shaded/protobuf/generated/QuotaProtos$TimedQuota;
     186: invokestatic  #19                 // Method org/apache/hadoop/hbase/quotas/ThrottleSettings.fromTimedQuota:(Ljava/lang/String;Lorg/apache/hadoop/hbase/TableName;Ljava/lang/String;Ljava/lang/String;Lorg/apache/hadoop/hbase/quotas/ThrottleType;Lorg/apache/hadoop/hbase/shaded/protobuf/generated/QuotaProtos$TimedQuota;)Lorg/apache/hadoop/hbase/quotas/ThrottleSettings;
     189: invokeinterface #12,  2           // InterfaceMethod java/util/List.add:(Ljava/lang/Object;)Z
     194: pop
     195: aload         4
     197: invokevirtual #35                 // Method org/apache/hadoop/hbase/shaded/protobuf/generated/QuotaProtos$Throttle.hasReqCapacityUnit:()Z
     200: ifeq          226
     203: aload         5
     205: aload_0
     206: aload_1
     207: aload_2
     208: aload_3
     209: getstatic     #36                 // Field org/apache/hadoop/hbase/quotas/ThrottleType.REQUEST_CAPACITY_UNIT:Lorg/apache/hadoop/hbase/quotas/ThrottleType;
     212: aload         4
     214: invokevirtual #37                 // Method org/apache/hadoop/hbase/shaded/protobuf/generated/QuotaProtos$Throttle.getReqCapacityUnit:()Lorg/apache/hadoop/hbase/shaded/protobuf/generated/QuotaProtos$TimedQuota;
     217: invokestatic  #19                 // Method org/apache/hadoop/hbase/quotas/ThrottleSettings.fromTimedQuota:(Ljava/lang/String;Lorg/apache/hadoop/hbase/TableName;Ljava/lang/String;Ljava/lang/String;Lorg/apache/hadoop/hbase/quotas/ThrottleType;Lorg/apache/hadoop/hbase/shaded/protobuf/generated/QuotaProtos$TimedQuota;)Lorg/apache/hadoop/hbase/quotas/ThrottleSettings;
     220: invokeinterface #12,  2           // InterfaceMethod java/util/List.add:(Ljava/lang/Object;)Z
     225: pop
     226: aload         4
     228: invokevirtual #38                 // Method org/apache/hadoop/hbase/shaded/protobuf/generated/QuotaProtos$Throttle.hasReadCapacityUnit:()Z
     231: ifeq          257
     234: aload         5
     236: aload_0
     237: aload_1
     238: aload_2
     239: aload_3
     240: getstatic     #39                 // Field org/apache/hadoop/hbase/quotas/ThrottleType.READ_CAPACITY_UNIT:Lorg/apache/hadoop/hbase/quotas/ThrottleType;
     243: aload         4
     245: invokevirtual #40                 // Method org/apache/hadoop/hbase/shaded/protobuf/generated/QuotaProtos$Throttle.getReadCapacityUnit:()Lorg/apache/hadoop/hbase/shaded/protobuf/generated/QuotaProtos$TimedQuota;
     248: invokestatic  #19                 // Method org/apache/hadoop/hbase/quotas/ThrottleSettings.fromTimedQuota:(Ljava/lang/String;Lorg/apache/hadoop/hbase/TableName;Ljava/lang/String;Ljava/lang/String;Lorg/apache/hadoop/hbase/quotas/ThrottleType;Lorg/apache/hadoop/hbase/shaded/protobuf/generated/QuotaProtos$TimedQuota;)Lorg/apache/hadoop/hbase/quotas/ThrottleSettings;
     251: invokeinterface #12,  2           // InterfaceMethod java/util/List.add:(Ljava/lang/Object;)Z
     256: pop
     257: aload         4
     259: invokevirtual #41                 // Method org/apache/hadoop/hbase/shaded/protobuf/generated/QuotaProtos$Throttle.hasWriteCapacityUnit:()Z
     262: ifeq          288
     265: aload         5
     267: aload_0
     268: aload_1
     269: aload_2
     270: aload_3
     271: getstatic     #42                 // Field org/apache/hadoop/hbase/quotas/ThrottleType.WRITE_CAPACITY_UNIT:Lorg/apache/hadoop/hbase/quotas/ThrottleType;
     274: aload         4
     276: invokevirtual #43                 // Method org/apache/hadoop/hbase/shaded/protobuf/generated/QuotaProtos$Throttle.getWriteCapacityUnit:()Lorg/apache/hadoop/hbase/shaded/protobuf/generated/QuotaProtos$TimedQuota;
     279: invokestatic  #19                 // Method org/apache/hadoop/hbase/quotas/ThrottleSettings.fromTimedQuota:(Ljava/lang/String;Lorg/apache/hadoop/hbase/TableName;Ljava/lang/String;Ljava/lang/String;Lorg/apache/hadoop/hbase/quotas/ThrottleType;Lorg/apache/hadoop/hbase/shaded/protobuf/generated/QuotaProtos$TimedQuota;)Lorg/apache/hadoop/hbase/quotas/ThrottleSettings;
     282: invokeinterface #12,  2           // InterfaceMethod java/util/List.add:(Ljava/lang/Object;)Z
     287: pop
     288: aload         5
     290: areturn

  static org.apache.hadoop.hbase.quotas.QuotaSettings fromSpace(org.apache.hadoop.hbase.TableName, java.lang.String, org.apache.hadoop.hbase.shaded.protobuf.generated.QuotaProtos$SpaceQuota);
    Code:
       0: aload_2
       1: ifnonnull     6
       4: aconst_null
       5: areturn
       6: aload_0
       7: ifnonnull     14
      10: aload_1
      11: ifnull        22
      14: aload_0
      15: ifnull        32
      18: aload_1
      19: ifnull        32
      22: new           #44                 // class java/lang/IllegalArgumentException
      25: dup
      26: ldc           #45                 // String Can only construct SpaceLimitSettings for a table or namespace.
      28: invokespecial #46                 // Method java/lang/IllegalArgumentException."<init>":(Ljava/lang/String;)V
      31: athrow
      32: aload_0
      33: ifnull        58
      36: aload_2
      37: invokevirtual #47                 // Method org/apache/hadoop/hbase/shaded/protobuf/generated/QuotaProtos$SpaceQuota.getRemove:()Z
      40: ifeq          52
      43: new           #48                 // class org/apache/hadoop/hbase/quotas/SpaceLimitSettings
      46: dup
      47: aload_0
      48: invokespecial #49                 // Method org/apache/hadoop/hbase/quotas/SpaceLimitSettings."<init>":(Lorg/apache/hadoop/hbase/TableName;)V
      51: areturn
      52: aload_0
      53: aload_2
      54: invokestatic  #50                 // Method org/apache/hadoop/hbase/quotas/SpaceLimitSettings.fromSpaceQuota:(Lorg/apache/hadoop/hbase/TableName;Lorg/apache/hadoop/hbase/shaded/protobuf/generated/QuotaProtos$SpaceQuota;)Lorg/apache/hadoop/hbase/quotas/SpaceLimitSettings;
      57: areturn
      58: aload_2
      59: invokevirtual #47                 // Method org/apache/hadoop/hbase/shaded/protobuf/generated/QuotaProtos$SpaceQuota.getRemove:()Z
      62: ifeq          74
      65: new           #48                 // class org/apache/hadoop/hbase/quotas/SpaceLimitSettings
      68: dup
      69: aload_1
      70: invokespecial #51                 // Method org/apache/hadoop/hbase/quotas/SpaceLimitSettings."<init>":(Ljava/lang/String;)V
      73: areturn
      74: aload_1
      75: aload_2
      76: invokestatic  #52                 // Method org/apache/hadoop/hbase/quotas/SpaceLimitSettings.fromSpaceQuota:(Ljava/lang/String;Lorg/apache/hadoop/hbase/shaded/protobuf/generated/QuotaProtos$SpaceQuota;)Lorg/apache/hadoop/hbase/quotas/SpaceLimitSettings;
      79: areturn

  public static org.apache.hadoop.hbase.quotas.QuotaSettings throttleUser(java.lang.String, org.apache.hadoop.hbase.quotas.ThrottleType, long, java.util.concurrent.TimeUnit);
    Code:
       0: aload_0
       1: aload_1
       2: lload_2
       3: aload         4
       5: getstatic     #53                 // Field org/apache/hadoop/hbase/quotas/QuotaScope.MACHINE:Lorg/apache/hadoop/hbase/quotas/QuotaScope;
       8: invokestatic  #54                 // Method throttleUser:(Ljava/lang/String;Lorg/apache/hadoop/hbase/quotas/ThrottleType;JLjava/util/concurrent/TimeUnit;Lorg/apache/hadoop/hbase/quotas/QuotaScope;)Lorg/apache/hadoop/hbase/quotas/QuotaSettings;
      11: areturn

  public static org.apache.hadoop.hbase.quotas.QuotaSettings throttleUser(java.lang.String, org.apache.hadoop.hbase.quotas.ThrottleType, long, java.util.concurrent.TimeUnit, org.apache.hadoop.hbase.quotas.QuotaScope);
    Code:
       0: aload_0
       1: aconst_null
       2: aconst_null
       3: aconst_null
       4: aload_1
       5: lload_2
       6: aload         4
       8: aload         5
      10: invokestatic  #55                 // Method throttle:(Ljava/lang/String;Lorg/apache/hadoop/hbase/TableName;Ljava/lang/String;Ljava/lang/String;Lorg/apache/hadoop/hbase/quotas/ThrottleType;JLjava/util/concurrent/TimeUnit;Lorg/apache/hadoop/hbase/quotas/QuotaScope;)Lorg/apache/hadoop/hbase/quotas/QuotaSettings;
      13: areturn

  public static org.apache.hadoop.hbase.quotas.QuotaSettings throttleUser(java.lang.String, org.apache.hadoop.hbase.TableName, org.apache.hadoop.hbase.quotas.ThrottleType, long, java.util.concurrent.TimeUnit);
    Code:
       0: aload_0
       1: aload_1
       2: aload_2
       3: lload_3
       4: aload         5
       6: getstatic     #53                 // Field org/apache/hadoop/hbase/quotas/QuotaScope.MACHINE:Lorg/apache/hadoop/hbase/quotas/QuotaScope;
       9: invokestatic  #56                 // Method throttleUser:(Ljava/lang/String;Lorg/apache/hadoop/hbase/TableName;Lorg/apache/hadoop/hbase/quotas/ThrottleType;JLjava/util/concurrent/TimeUnit;Lorg/apache/hadoop/hbase/quotas/QuotaScope;)Lorg/apache/hadoop/hbase/quotas/QuotaSettings;
      12: areturn

  public static org.apache.hadoop.hbase.quotas.QuotaSettings throttleUser(java.lang.String, org.apache.hadoop.hbase.TableName, org.apache.hadoop.hbase.quotas.ThrottleType, long, java.util.concurrent.TimeUnit, org.apache.hadoop.hbase.quotas.QuotaScope);
    Code:
       0: aload_0
       1: aload_1
       2: aconst_null
       3: aconst_null
       4: aload_2
       5: lload_3
       6: aload         5
       8: aload         6
      10: invokestatic  #55                 // Method throttle:(Ljava/lang/String;Lorg/apache/hadoop/hbase/TableName;Ljava/lang/String;Ljava/lang/String;Lorg/apache/hadoop/hbase/quotas/ThrottleType;JLjava/util/concurrent/TimeUnit;Lorg/apache/hadoop/hbase/quotas/QuotaScope;)Lorg/apache/hadoop/hbase/quotas/QuotaSettings;
      13: areturn

  public static org.apache.hadoop.hbase.quotas.QuotaSettings throttleUser(java.lang.String, java.lang.String, org.apache.hadoop.hbase.quotas.ThrottleType, long, java.util.concurrent.TimeUnit);
    Code:
       0: aload_0
       1: aload_1
       2: aload_2
       3: lload_3
       4: aload         5
       6: getstatic     #53                 // Field org/apache/hadoop/hbase/quotas/QuotaScope.MACHINE:Lorg/apache/hadoop/hbase/quotas/QuotaScope;
       9: invokestatic  #57                 // Method throttleUser:(Ljava/lang/String;Ljava/lang/String;Lorg/apache/hadoop/hbase/quotas/ThrottleType;JLjava/util/concurrent/TimeUnit;Lorg/apache/hadoop/hbase/quotas/QuotaScope;)Lorg/apache/hadoop/hbase/quotas/QuotaSettings;
      12: areturn

  public static org.apache.hadoop.hbase.quotas.QuotaSettings throttleUser(java.lang.String, java.lang.String, org.apache.hadoop.hbase.quotas.ThrottleType, long, java.util.concurrent.TimeUnit, org.apache.hadoop.hbase.quotas.QuotaScope);
    Code:
       0: aload_0
       1: aconst_null
       2: aload_1
       3: aconst_null
       4: aload_2
       5: lload_3
       6: aload         5
       8: aload         6
      10: invokestatic  #55                 // Method throttle:(Ljava/lang/String;Lorg/apache/hadoop/hbase/TableName;Ljava/lang/String;Ljava/lang/String;Lorg/apache/hadoop/hbase/quotas/ThrottleType;JLjava/util/concurrent/TimeUnit;Lorg/apache/hadoop/hbase/quotas/QuotaScope;)Lorg/apache/hadoop/hbase/quotas/QuotaSettings;
      13: areturn

  public static org.apache.hadoop.hbase.quotas.QuotaSettings unthrottleUser(java.lang.String);
    Code:
       0: aload_0
       1: aconst_null
       2: aconst_null
       3: aconst_null
       4: aconst_null
       5: lconst_0
       6: aconst_null
       7: getstatic     #53                 // Field org/apache/hadoop/hbase/quotas/QuotaScope.MACHINE:Lorg/apache/hadoop/hbase/quotas/QuotaScope;
      10: invokestatic  #55                 // Method throttle:(Ljava/lang/String;Lorg/apache/hadoop/hbase/TableName;Ljava/lang/String;Ljava/lang/String;Lorg/apache/hadoop/hbase/quotas/ThrottleType;JLjava/util/concurrent/TimeUnit;Lorg/apache/hadoop/hbase/quotas/QuotaScope;)Lorg/apache/hadoop/hbase/quotas/QuotaSettings;
      13: areturn

  public static org.apache.hadoop.hbase.quotas.QuotaSettings unthrottleUserByThrottleType(java.lang.String, org.apache.hadoop.hbase.quotas.ThrottleType);
    Code:
       0: aload_0
       1: aconst_null
       2: aconst_null
       3: aconst_null
       4: aload_1
       5: lconst_0
       6: aconst_null
       7: getstatic     #53                 // Field org/apache/hadoop/hbase/quotas/QuotaScope.MACHINE:Lorg/apache/hadoop/hbase/quotas/QuotaScope;
      10: invokestatic  #55                 // Method throttle:(Ljava/lang/String;Lorg/apache/hadoop/hbase/TableName;Ljava/lang/String;Ljava/lang/String;Lorg/apache/hadoop/hbase/quotas/ThrottleType;JLjava/util/concurrent/TimeUnit;Lorg/apache/hadoop/hbase/quotas/QuotaScope;)Lorg/apache/hadoop/hbase/quotas/QuotaSettings;
      13: areturn

  public static org.apache.hadoop.hbase.quotas.QuotaSettings unthrottleUser(java.lang.String, org.apache.hadoop.hbase.TableName);
    Code:
       0: aload_0
       1: aload_1
       2: aconst_null
       3: aconst_null
       4: aconst_null
       5: lconst_0
       6: aconst_null
       7: getstatic     #53                 // Field org/apache/hadoop/hbase/quotas/QuotaScope.MACHINE:Lorg/apache/hadoop/hbase/quotas/QuotaScope;
      10: invokestatic  #55                 // Method throttle:(Ljava/lang/String;Lorg/apache/hadoop/hbase/TableName;Ljava/lang/String;Ljava/lang/String;Lorg/apache/hadoop/hbase/quotas/ThrottleType;JLjava/util/concurrent/TimeUnit;Lorg/apache/hadoop/hbase/quotas/QuotaScope;)Lorg/apache/hadoop/hbase/quotas/QuotaSettings;
      13: areturn

  public static org.apache.hadoop.hbase.quotas.QuotaSettings unthrottleUserByThrottleType(java.lang.String, org.apache.hadoop.hbase.TableName, org.apache.hadoop.hbase.quotas.ThrottleType);
    Code:
       0: aload_0
       1: aload_1
       2: aconst_null
       3: aconst_null
       4: aload_2
       5: lconst_0
       6: aconst_null
       7: getstatic     #53                 // Field org/apache/hadoop/hbase/quotas/QuotaScope.MACHINE:Lorg/apache/hadoop/hbase/quotas/QuotaScope;
      10: invokestatic  #55                 // Method throttle:(Ljava/lang/String;Lorg/apache/hadoop/hbase/TableName;Ljava/lang/String;Ljava/lang/String;Lorg/apache/hadoop/hbase/quotas/ThrottleType;JLjava/util/concurrent/TimeUnit;Lorg/apache/hadoop/hbase/quotas/QuotaScope;)Lorg/apache/hadoop/hbase/quotas/QuotaSettings;
      13: areturn

  public static org.apache.hadoop.hbase.quotas.QuotaSettings unthrottleUser(java.lang.String, java.lang.String);
    Code:
       0: aload_0
       1: aconst_null
       2: aload_1
       3: aconst_null
       4: aconst_null
       5: lconst_0
       6: aconst_null
       7: getstatic     #53                 // Field org/apache/hadoop/hbase/quotas/QuotaScope.MACHINE:Lorg/apache/hadoop/hbase/quotas/QuotaScope;
      10: invokestatic  #55                 // Method throttle:(Ljava/lang/String;Lorg/apache/hadoop/hbase/TableName;Ljava/lang/String;Ljava/lang/String;Lorg/apache/hadoop/hbase/quotas/ThrottleType;JLjava/util/concurrent/TimeUnit;Lorg/apache/hadoop/hbase/quotas/QuotaScope;)Lorg/apache/hadoop/hbase/quotas/QuotaSettings;
      13: areturn

  public static org.apache.hadoop.hbase.quotas.QuotaSettings unthrottleUserByThrottleType(java.lang.String, java.lang.String, org.apache.hadoop.hbase.quotas.ThrottleType);
    Code:
       0: aload_0
       1: aconst_null
       2: aload_1
       3: aconst_null
       4: aload_2
       5: lconst_0
       6: aconst_null
       7: getstatic     #53                 // Field org/apache/hadoop/hbase/quotas/QuotaScope.MACHINE:Lorg/apache/hadoop/hbase/quotas/QuotaScope;
      10: invokestatic  #55                 // Method throttle:(Ljava/lang/String;Lorg/apache/hadoop/hbase/TableName;Ljava/lang/String;Ljava/lang/String;Lorg/apache/hadoop/hbase/quotas/ThrottleType;JLjava/util/concurrent/TimeUnit;Lorg/apache/hadoop/hbase/quotas/QuotaScope;)Lorg/apache/hadoop/hbase/quotas/QuotaSettings;
      13: areturn

  public static org.apache.hadoop.hbase.quotas.QuotaSettings throttleTable(org.apache.hadoop.hbase.TableName, org.apache.hadoop.hbase.quotas.ThrottleType, long, java.util.concurrent.TimeUnit);
    Code:
       0: aload_0
       1: aload_1
       2: lload_2
       3: aload         4
       5: getstatic     #53                 // Field org/apache/hadoop/hbase/quotas/QuotaScope.MACHINE:Lorg/apache/hadoop/hbase/quotas/QuotaScope;
       8: invokestatic  #58                 // Method throttleTable:(Lorg/apache/hadoop/hbase/TableName;Lorg/apache/hadoop/hbase/quotas/ThrottleType;JLjava/util/concurrent/TimeUnit;Lorg/apache/hadoop/hbase/quotas/QuotaScope;)Lorg/apache/hadoop/hbase/quotas/QuotaSettings;
      11: areturn

  public static org.apache.hadoop.hbase.quotas.QuotaSettings throttleTable(org.apache.hadoop.hbase.TableName, org.apache.hadoop.hbase.quotas.ThrottleType, long, java.util.concurrent.TimeUnit, org.apache.hadoop.hbase.quotas.QuotaScope);
    Code:
       0: aconst_null
       1: aload_0
       2: aconst_null
       3: aconst_null
       4: aload_1
       5: lload_2
       6: aload         4
       8: aload         5
      10: invokestatic  #55                 // Method throttle:(Ljava/lang/String;Lorg/apache/hadoop/hbase/TableName;Ljava/lang/String;Ljava/lang/String;Lorg/apache/hadoop/hbase/quotas/ThrottleType;JLjava/util/concurrent/TimeUnit;Lorg/apache/hadoop/hbase/quotas/QuotaScope;)Lorg/apache/hadoop/hbase/quotas/QuotaSettings;
      13: areturn

  public static org.apache.hadoop.hbase.quotas.QuotaSettings unthrottleTable(org.apache.hadoop.hbase.TableName);
    Code:
       0: aconst_null
       1: aload_0
       2: aconst_null
       3: aconst_null
       4: aconst_null
       5: lconst_0
       6: aconst_null
       7: getstatic     #53                 // Field org/apache/hadoop/hbase/quotas/QuotaScope.MACHINE:Lorg/apache/hadoop/hbase/quotas/QuotaScope;
      10: invokestatic  #55                 // Method throttle:(Ljava/lang/String;Lorg/apache/hadoop/hbase/TableName;Ljava/lang/String;Ljava/lang/String;Lorg/apache/hadoop/hbase/quotas/ThrottleType;JLjava/util/concurrent/TimeUnit;Lorg/apache/hadoop/hbase/quotas/QuotaScope;)Lorg/apache/hadoop/hbase/quotas/QuotaSettings;
      13: areturn

  public static org.apache.hadoop.hbase.quotas.QuotaSettings unthrottleTableByThrottleType(org.apache.hadoop.hbase.TableName, org.apache.hadoop.hbase.quotas.ThrottleType);
    Code:
       0: aconst_null
       1: aload_0
       2: aconst_null
       3: aconst_null
       4: aload_1
       5: lconst_0
       6: aconst_null
       7: getstatic     #53                 // Field org/apache/hadoop/hbase/quotas/QuotaScope.MACHINE:Lorg/apache/hadoop/hbase/quotas/QuotaScope;
      10: invokestatic  #55                 // Method throttle:(Ljava/lang/String;Lorg/apache/hadoop/hbase/TableName;Ljava/lang/String;Ljava/lang/String;Lorg/apache/hadoop/hbase/quotas/ThrottleType;JLjava/util/concurrent/TimeUnit;Lorg/apache/hadoop/hbase/quotas/QuotaScope;)Lorg/apache/hadoop/hbase/quotas/QuotaSettings;
      13: areturn

  public static org.apache.hadoop.hbase.quotas.QuotaSettings throttleNamespace(java.lang.String, org.apache.hadoop.hbase.quotas.ThrottleType, long, java.util.concurrent.TimeUnit);
    Code:
       0: aload_0
       1: aload_1
       2: lload_2
       3: aload         4
       5: getstatic     #53                 // Field org/apache/hadoop/hbase/quotas/QuotaScope.MACHINE:Lorg/apache/hadoop/hbase/quotas/QuotaScope;
       8: invokestatic  #59                 // Method throttleNamespace:(Ljava/lang/String;Lorg/apache/hadoop/hbase/quotas/ThrottleType;JLjava/util/concurrent/TimeUnit;Lorg/apache/hadoop/hbase/quotas/QuotaScope;)Lorg/apache/hadoop/hbase/quotas/QuotaSettings;
      11: areturn

  public static org.apache.hadoop.hbase.quotas.QuotaSettings throttleNamespace(java.lang.String, org.apache.hadoop.hbase.quotas.ThrottleType, long, java.util.concurrent.TimeUnit, org.apache.hadoop.hbase.quotas.QuotaScope);
    Code:
       0: aconst_null
       1: aconst_null
       2: aload_0
       3: aconst_null
       4: aload_1
       5: lload_2
       6: aload         4
       8: aload         5
      10: invokestatic  #55                 // Method throttle:(Ljava/lang/String;Lorg/apache/hadoop/hbase/TableName;Ljava/lang/String;Ljava/lang/String;Lorg/apache/hadoop/hbase/quotas/ThrottleType;JLjava/util/concurrent/TimeUnit;Lorg/apache/hadoop/hbase/quotas/QuotaScope;)Lorg/apache/hadoop/hbase/quotas/QuotaSettings;
      13: areturn

  public static org.apache.hadoop.hbase.quotas.QuotaSettings unthrottleNamespace(java.lang.String);
    Code:
       0: aconst_null
       1: aconst_null
       2: aload_0
       3: aconst_null
       4: aconst_null
       5: lconst_0
       6: aconst_null
       7: getstatic     #53                 // Field org/apache/hadoop/hbase/quotas/QuotaScope.MACHINE:Lorg/apache/hadoop/hbase/quotas/QuotaScope;
      10: invokestatic  #55                 // Method throttle:(Ljava/lang/String;Lorg/apache/hadoop/hbase/TableName;Ljava/lang/String;Ljava/lang/String;Lorg/apache/hadoop/hbase/quotas/ThrottleType;JLjava/util/concurrent/TimeUnit;Lorg/apache/hadoop/hbase/quotas/QuotaScope;)Lorg/apache/hadoop/hbase/quotas/QuotaSettings;
      13: areturn

  public static org.apache.hadoop.hbase.quotas.QuotaSettings unthrottleNamespaceByThrottleType(java.lang.String, org.apache.hadoop.hbase.quotas.ThrottleType);
    Code:
       0: aconst_null
       1: aconst_null
       2: aload_0
       3: aconst_null
       4: aload_1
       5: lconst_0
       6: aconst_null
       7: getstatic     #53                 // Field org/apache/hadoop/hbase/quotas/QuotaScope.MACHINE:Lorg/apache/hadoop/hbase/quotas/QuotaScope;
      10: invokestatic  #55                 // Method throttle:(Ljava/lang/String;Lorg/apache/hadoop/hbase/TableName;Ljava/lang/String;Ljava/lang/String;Lorg/apache/hadoop/hbase/quotas/ThrottleType;JLjava/util/concurrent/TimeUnit;Lorg/apache/hadoop/hbase/quotas/QuotaScope;)Lorg/apache/hadoop/hbase/quotas/QuotaSettings;
      13: areturn

  public static org.apache.hadoop.hbase.quotas.QuotaSettings throttleRegionServer(java.lang.String, org.apache.hadoop.hbase.quotas.ThrottleType, long, java.util.concurrent.TimeUnit);
    Code:
       0: aconst_null
       1: aconst_null
       2: aconst_null
       3: aload_0
       4: aload_1
       5: lload_2
       6: aload         4
       8: getstatic     #53                 // Field org/apache/hadoop/hbase/quotas/QuotaScope.MACHINE:Lorg/apache/hadoop/hbase/quotas/QuotaScope;
      11: invokestatic  #55                 // Method throttle:(Ljava/lang/String;Lorg/apache/hadoop/hbase/TableName;Ljava/lang/String;Ljava/lang/String;Lorg/apache/hadoop/hbase/quotas/ThrottleType;JLjava/util/concurrent/TimeUnit;Lorg/apache/hadoop/hbase/quotas/QuotaScope;)Lorg/apache/hadoop/hbase/quotas/QuotaSettings;
      14: areturn

  public static org.apache.hadoop.hbase.quotas.QuotaSettings unthrottleRegionServer(java.lang.String);
    Code:
       0: aconst_null
       1: aconst_null
       2: aconst_null
       3: aload_0
       4: aconst_null
       5: lconst_0
       6: aconst_null
       7: getstatic     #53                 // Field org/apache/hadoop/hbase/quotas/QuotaScope.MACHINE:Lorg/apache/hadoop/hbase/quotas/QuotaScope;
      10: invokestatic  #55                 // Method throttle:(Ljava/lang/String;Lorg/apache/hadoop/hbase/TableName;Ljava/lang/String;Ljava/lang/String;Lorg/apache/hadoop/hbase/quotas/ThrottleType;JLjava/util/concurrent/TimeUnit;Lorg/apache/hadoop/hbase/quotas/QuotaScope;)Lorg/apache/hadoop/hbase/quotas/QuotaSettings;
      13: areturn

  public static org.apache.hadoop.hbase.quotas.QuotaSettings unthrottleRegionServerByThrottleType(java.lang.String, org.apache.hadoop.hbase.quotas.ThrottleType);
    Code:
       0: aconst_null
       1: aconst_null
       2: aconst_null
       3: aload_0
       4: aload_1
       5: lconst_0
       6: aconst_null
       7: getstatic     #53                 // Field org/apache/hadoop/hbase/quotas/QuotaScope.MACHINE:Lorg/apache/hadoop/hbase/quotas/QuotaScope;
      10: invokestatic  #55                 // Method throttle:(Ljava/lang/String;Lorg/apache/hadoop/hbase/TableName;Ljava/lang/String;Ljava/lang/String;Lorg/apache/hadoop/hbase/quotas/ThrottleType;JLjava/util/concurrent/TimeUnit;Lorg/apache/hadoop/hbase/quotas/QuotaScope;)Lorg/apache/hadoop/hbase/quotas/QuotaSettings;
      13: areturn

  public static org.apache.hadoop.hbase.quotas.QuotaSettings bypassGlobals(java.lang.String, boolean);
    Code:
       0: new           #10                 // class org/apache/hadoop/hbase/quotas/QuotaSettingsFactory$QuotaGlobalsSettingsBypass
       3: dup
       4: aload_0
       5: aconst_null
       6: aconst_null
       7: aconst_null
       8: iload_1
       9: invokespecial #11                 // Method org/apache/hadoop/hbase/quotas/QuotaSettingsFactory$QuotaGlobalsSettingsBypass."<init>":(Ljava/lang/String;Lorg/apache/hadoop/hbase/TableName;Ljava/lang/String;Ljava/lang/String;Z)V
      12: areturn

  public static org.apache.hadoop.hbase.quotas.QuotaSettings limitTableSpace(org.apache.hadoop.hbase.TableName, long, org.apache.hadoop.hbase.quotas.SpaceViolationPolicy);
    Code:
       0: new           #48                 // class org/apache/hadoop/hbase/quotas/SpaceLimitSettings
       3: dup
       4: aload_0
       5: lload_1
       6: aload_3
       7: invokespecial #68                 // Method org/apache/hadoop/hbase/quotas/SpaceLimitSettings."<init>":(Lorg/apache/hadoop/hbase/TableName;JLorg/apache/hadoop/hbase/quotas/SpaceViolationPolicy;)V
      10: areturn

  public static org.apache.hadoop.hbase.quotas.QuotaSettings removeTableSpaceLimit(org.apache.hadoop.hbase.TableName);
    Code:
       0: new           #48                 // class org/apache/hadoop/hbase/quotas/SpaceLimitSettings
       3: dup
       4: aload_0
       5: invokespecial #49                 // Method org/apache/hadoop/hbase/quotas/SpaceLimitSettings."<init>":(Lorg/apache/hadoop/hbase/TableName;)V
       8: areturn

  public static org.apache.hadoop.hbase.quotas.QuotaSettings limitNamespaceSpace(java.lang.String, long, org.apache.hadoop.hbase.quotas.SpaceViolationPolicy);
    Code:
       0: new           #48                 // class org/apache/hadoop/hbase/quotas/SpaceLimitSettings
       3: dup
       4: aload_0
       5: lload_1
       6: aload_3
       7: invokespecial #69                 // Method org/apache/hadoop/hbase/quotas/SpaceLimitSettings."<init>":(Ljava/lang/String;JLorg/apache/hadoop/hbase/quotas/SpaceViolationPolicy;)V
      10: areturn

  public static org.apache.hadoop.hbase.quotas.QuotaSettings removeNamespaceSpaceLimit(java.lang.String);
    Code:
       0: new           #48                 // class org/apache/hadoop/hbase/quotas/SpaceLimitSettings
       3: dup
       4: aload_0
       5: invokespecial #51                 // Method org/apache/hadoop/hbase/quotas/SpaceLimitSettings."<init>":(Ljava/lang/String;)V
       8: areturn
}
