Compiled from "QuotaSnapshotStore.java"
public interface org.apache.hadoop.hbase.quotas.QuotaSnapshotStore<T> {
  public static final org.apache.hadoop.hbase.quotas.SpaceQuotaSnapshot NO_QUOTA;

  public abstract org.apache.hadoop.hbase.shaded.protobuf.generated.QuotaProtos$SpaceQuota getSpaceQuota(T) throws java.io.IOException;

  public abstract org.apache.hadoop.hbase.quotas.SpaceQuotaSnapshot getCurrentState(T);

  public abstract org.apache.hadoop.hbase.quotas.SpaceQuotaSnapshot getTargetState(T, org.apache.hadoop.hbase.shaded.protobuf.generated.QuotaProtos$SpaceQuota) throws java.io.IOException;

  public abstract java.lang.Iterable<java.util.Map$Entry<org.apache.hadoop.hbase.client.RegionInfo, java.lang.Long>> filterBySubject(T);

  public abstract void setCurrentState(T, org.apache.hadoop.hbase.quotas.SpaceQuotaSnapshot);

  public abstract void setRegionUsage(java.util.Map<org.apache.hadoop.hbase.client.RegionInfo, java.lang.Long>);

  static {};
    Code:
       0: new           #1                  // class org/apache/hadoop/hbase/quotas/SpaceQuotaSnapshot
       3: dup
       4: invokestatic  #2                  // Method org/apache/hadoop/hbase/quotas/SpaceQuotaSnapshot$SpaceQuotaStatus.notInViolation:()Lorg/apache/hadoop/hbase/quotas/SpaceQuotaSnapshot$SpaceQuotaStatus;
       7: ldc2_w        #3                  // long -1l
      10: ldc2_w        #3                  // long -1l
      13: invokespecial #5                  // Method org/apache/hadoop/hbase/quotas/SpaceQuotaSnapshot."<init>":(Lorg/apache/hadoop/hbase/quotas/SpaceQuotaSnapshot$SpaceQuotaStatus;JJ)V
      16: putstatic     #6                  // Field NO_QUOTA:Lorg/apache/hadoop/hbase/quotas/SpaceQuotaSnapshot;
      19: return
}
