Compiled from "QuotaProtos.java"
public final class org.apache.hadoop.hbase.protobuf.generated.QuotaProtos$Throttle$Builder extends com.google.protobuf.GeneratedMessage$Builder<org.apache.hadoop.hbase.protobuf.generated.QuotaProtos$Throttle$Builder> implements org.apache.hadoop.hbase.protobuf.generated.QuotaProtos$ThrottleOrBuilder {
  public static final com.google.protobuf.Descriptors$Descriptor getDescriptor();
    Code:
       0: invokestatic  #3                  // Method org/apache/hadoop/hbase/protobuf/generated/QuotaProtos.access$1200:()Lcom/google/protobuf/Descriptors$Descriptor;
       3: areturn

  protected com.google.protobuf.GeneratedMessage$FieldAccessorTable internalGetFieldAccessorTable();
    Code:
       0: invokestatic  #4                  // Method org/apache/hadoop/hbase/protobuf/generated/QuotaProtos.access$1300:()Lcom/google/protobuf/GeneratedMessage$FieldAccessorTable;
       3: ldc           #5                  // class org/apache/hadoop/hbase/protobuf/generated/QuotaProtos$Throttle
       5: ldc           #6                  // class org/apache/hadoop/hbase/protobuf/generated/QuotaProtos$Throttle$Builder
       7: invokevirtual #7                  // Method com/google/protobuf/GeneratedMessage$FieldAccessorTable.ensureFieldAccessorsInitialized:(Ljava/lang/Class;Ljava/lang/Class;)Lcom/google/protobuf/GeneratedMessage$FieldAccessorTable;
      10: areturn

  public org.apache.hadoop.hbase.protobuf.generated.QuotaProtos$Throttle$Builder clear();
    Code:
       0: aload_0
       1: invokespecial #26                 // Method com/google/protobuf/GeneratedMessage$Builder.clear:()Lcom/google/protobuf/GeneratedMessage$Builder;
       4: pop
       5: aload_0
       6: getfield      #27                 // Field reqNumBuilder_:Lcom/google/protobuf/SingleFieldBuilder;
       9: ifnonnull     22
      12: aload_0
      13: invokestatic  #9                  // Method org/apache/hadoop/hbase/protobuf/generated/QuotaProtos$TimedQuota.getDefaultInstance:()Lorg/apache/hadoop/hbase/protobuf/generated/QuotaProtos$TimedQuota;
      16: putfield      #10                 // Field reqNum_:Lorg/apache/hadoop/hbase/protobuf/generated/QuotaProtos$TimedQuota;
      19: goto          30
      22: aload_0
      23: getfield      #27                 // Field reqNumBuilder_:Lcom/google/protobuf/SingleFieldBuilder;
      26: invokevirtual #28                 // Method com/google/protobuf/SingleFieldBuilder.clear:()Lcom/google/protobuf/SingleFieldBuilder;
      29: pop
      30: aload_0
      31: aload_0
      32: getfield      #29                 // Field bitField0_:I
      35: bipush        -2
      37: iand
      38: putfield      #29                 // Field bitField0_:I
      41: aload_0
      42: getfield      #30                 // Field reqSizeBuilder_:Lcom/google/protobuf/SingleFieldBuilder;
      45: ifnonnull     58
      48: aload_0
      49: invokestatic  #9                  // Method org/apache/hadoop/hbase/protobuf/generated/QuotaProtos$TimedQuota.getDefaultInstance:()Lorg/apache/hadoop/hbase/protobuf/generated/QuotaProtos$TimedQuota;
      52: putfield      #11                 // Field reqSize_:Lorg/apache/hadoop/hbase/protobuf/generated/QuotaProtos$TimedQuota;
      55: goto          66
      58: aload_0
      59: getfield      #30                 // Field reqSizeBuilder_:Lcom/google/protobuf/SingleFieldBuilder;
      62: invokevirtual #28                 // Method com/google/protobuf/SingleFieldBuilder.clear:()Lcom/google/protobuf/SingleFieldBuilder;
      65: pop
      66: aload_0
      67: aload_0
      68: getfield      #29                 // Field bitField0_:I
      71: bipush        -3
      73: iand
      74: putfield      #29                 // Field bitField0_:I
      77: aload_0
      78: getfield      #31                 // Field writeNumBuilder_:Lcom/google/protobuf/SingleFieldBuilder;
      81: ifnonnull     94
      84: aload_0
      85: invokestatic  #9                  // Method org/apache/hadoop/hbase/protobuf/generated/QuotaProtos$TimedQuota.getDefaultInstance:()Lorg/apache/hadoop/hbase/protobuf/generated/QuotaProtos$TimedQuota;
      88: putfield      #12                 // Field writeNum_:Lorg/apache/hadoop/hbase/protobuf/generated/QuotaProtos$TimedQuota;
      91: goto          102
      94: aload_0
      95: getfield      #31                 // Field writeNumBuilder_:Lcom/google/protobuf/SingleFieldBuilder;
      98: invokevirtual #28                 // Method com/google/protobuf/SingleFieldBuilder.clear:()Lcom/google/protobuf/SingleFieldBuilder;
     101: pop
     102: aload_0
     103: aload_0
     104: getfield      #29                 // Field bitField0_:I
     107: bipush        -5
     109: iand
     110: putfield      #29                 // Field bitField0_:I
     113: aload_0
     114: getfield      #32                 // Field writeSizeBuilder_:Lcom/google/protobuf/SingleFieldBuilder;
     117: ifnonnull     130
     120: aload_0
     121: invokestatic  #9                  // Method org/apache/hadoop/hbase/protobuf/generated/QuotaProtos$TimedQuota.getDefaultInstance:()Lorg/apache/hadoop/hbase/protobuf/generated/QuotaProtos$TimedQuota;
     124: putfield      #13                 // Field writeSize_:Lorg/apache/hadoop/hbase/protobuf/generated/QuotaProtos$TimedQuota;
     127: goto          138
     130: aload_0
     131: getfield      #32                 // Field writeSizeBuilder_:Lcom/google/protobuf/SingleFieldBuilder;
     134: invokevirtual #28                 // Method com/google/protobuf/SingleFieldBuilder.clear:()Lcom/google/protobuf/SingleFieldBuilder;
     137: pop
     138: aload_0
     139: aload_0
     140: getfield      #29                 // Field bitField0_:I
     143: bipush        -9
     145: iand
     146: putfield      #29                 // Field bitField0_:I
     149: aload_0
     150: getfield      #33                 // Field readNumBuilder_:Lcom/google/protobuf/SingleFieldBuilder;
     153: ifnonnull     166
     156: aload_0
     157: invokestatic  #9                  // Method org/apache/hadoop/hbase/protobuf/generated/QuotaProtos$TimedQuota.getDefaultInstance:()Lorg/apache/hadoop/hbase/protobuf/generated/QuotaProtos$TimedQuota;
     160: putfield      #14                 // Field readNum_:Lorg/apache/hadoop/hbase/protobuf/generated/QuotaProtos$TimedQuota;
     163: goto          174
     166: aload_0
     167: getfield      #33                 // Field readNumBuilder_:Lcom/google/protobuf/SingleFieldBuilder;
     170: invokevirtual #28                 // Method com/google/protobuf/SingleFieldBuilder.clear:()Lcom/google/protobuf/SingleFieldBuilder;
     173: pop
     174: aload_0
     175: aload_0
     176: getfield      #29                 // Field bitField0_:I
     179: bipush        -17
     181: iand
     182: putfield      #29                 // Field bitField0_:I
     185: aload_0
     186: getfield      #34                 // Field readSizeBuilder_:Lcom/google/protobuf/SingleFieldBuilder;
     189: ifnonnull     202
     192: aload_0
     193: invokestatic  #9                  // Method org/apache/hadoop/hbase/protobuf/generated/QuotaProtos$TimedQuota.getDefaultInstance:()Lorg/apache/hadoop/hbase/protobuf/generated/QuotaProtos$TimedQuota;
     196: putfield      #15                 // Field readSize_:Lorg/apache/hadoop/hbase/protobuf/generated/QuotaProtos$TimedQuota;
     199: goto          210
     202: aload_0
     203: getfield      #34                 // Field readSizeBuilder_:Lcom/google/protobuf/SingleFieldBuilder;
     206: invokevirtual #28                 // Method com/google/protobuf/SingleFieldBuilder.clear:()Lcom/google/protobuf/SingleFieldBuilder;
     209: pop
     210: aload_0
     211: aload_0
     212: getfield      #29                 // Field bitField0_:I
     215: bipush        -33
     217: iand
     218: putfield      #29                 // Field bitField0_:I
     221: aload_0
     222: areturn

  public org.apache.hadoop.hbase.protobuf.generated.QuotaProtos$Throttle$Builder clone();
    Code:
       0: invokestatic  #2                  // Method create:()Lorg/apache/hadoop/hbase/protobuf/generated/QuotaProtos$Throttle$Builder;
       3: aload_0
       4: invokevirtual #35                 // Method buildPartial:()Lorg/apache/hadoop/hbase/protobuf/generated/QuotaProtos$Throttle;
       7: invokevirtual #36                 // Method mergeFrom:(Lorg/apache/hadoop/hbase/protobuf/generated/QuotaProtos$Throttle;)Lorg/apache/hadoop/hbase/protobuf/generated/QuotaProtos$Throttle$Builder;
      10: areturn

  public com.google.protobuf.Descriptors$Descriptor getDescriptorForType();
    Code:
       0: invokestatic  #3                  // Method org/apache/hadoop/hbase/protobuf/generated/QuotaProtos.access$1200:()Lcom/google/protobuf/Descriptors$Descriptor;
       3: areturn

  public org.apache.hadoop.hbase.protobuf.generated.QuotaProtos$Throttle getDefaultInstanceForType();
    Code:
       0: invokestatic  #37                 // Method org/apache/hadoop/hbase/protobuf/generated/QuotaProtos$Throttle.getDefaultInstance:()Lorg/apache/hadoop/hbase/protobuf/generated/QuotaProtos$Throttle;
       3: areturn

  public org.apache.hadoop.hbase.protobuf.generated.QuotaProtos$Throttle build();
    Code:
       0: aload_0
       1: invokevirtual #35                 // Method buildPartial:()Lorg/apache/hadoop/hbase/protobuf/generated/QuotaProtos$Throttle;
       4: astore_1
       5: aload_1
       6: invokevirtual #38                 // Method org/apache/hadoop/hbase/protobuf/generated/QuotaProtos$Throttle.isInitialized:()Z
       9: ifne          17
      12: aload_1
      13: invokestatic  #39                 // Method newUninitializedMessageException:(Lcom/google/protobuf/Message;)Lcom/google/protobuf/UninitializedMessageException;
      16: athrow
      17: aload_1
      18: areturn

  public org.apache.hadoop.hbase.protobuf.generated.QuotaProtos$Throttle buildPartial();
    Code:
       0: new           #5                  // class org/apache/hadoop/hbase/protobuf/generated/QuotaProtos$Throttle
       3: dup
       4: aload_0
       5: aconst_null
       6: invokespecial #40                 // Method org/apache/hadoop/hbase/protobuf/generated/QuotaProtos$Throttle."<init>":(Lcom/google/protobuf/GeneratedMessage$Builder;Lorg/apache/hadoop/hbase/protobuf/generated/QuotaProtos$1;)V
       9: astore_1
      10: aload_0
      11: getfield      #29                 // Field bitField0_:I
      14: istore_2
      15: iconst_0
      16: istore_3
      17: iload_2
      18: iconst_1
      19: iand
      20: iconst_1
      21: if_icmpne     28
      24: iload_3
      25: iconst_1
      26: ior
      27: istore_3
      28: aload_0
      29: getfield      #27                 // Field reqNumBuilder_:Lcom/google/protobuf/SingleFieldBuilder;
      32: ifnonnull     47
      35: aload_1
      36: aload_0
      37: getfield      #10                 // Field reqNum_:Lorg/apache/hadoop/hbase/protobuf/generated/QuotaProtos$TimedQuota;
      40: invokestatic  #41                 // Method org/apache/hadoop/hbase/protobuf/generated/QuotaProtos$Throttle.access$1902:(Lorg/apache/hadoop/hbase/protobuf/generated/QuotaProtos$Throttle;Lorg/apache/hadoop/hbase/protobuf/generated/QuotaProtos$TimedQuota;)Lorg/apache/hadoop/hbase/protobuf/generated/QuotaProtos$TimedQuota;
      43: pop
      44: goto          62
      47: aload_1
      48: aload_0
      49: getfield      #27                 // Field reqNumBuilder_:Lcom/google/protobuf/SingleFieldBuilder;
      52: invokevirtual #42                 // Method com/google/protobuf/SingleFieldBuilder.build:()Lcom/google/protobuf/GeneratedMessage;
      55: checkcast     #43                 // class org/apache/hadoop/hbase/protobuf/generated/QuotaProtos$TimedQuota
      58: invokestatic  #41                 // Method org/apache/hadoop/hbase/protobuf/generated/QuotaProtos$Throttle.access$1902:(Lorg/apache/hadoop/hbase/protobuf/generated/QuotaProtos$Throttle;Lorg/apache/hadoop/hbase/protobuf/generated/QuotaProtos$TimedQuota;)Lorg/apache/hadoop/hbase/protobuf/generated/QuotaProtos$TimedQuota;
      61: pop
      62: iload_2
      63: iconst_2
      64: iand
      65: iconst_2
      66: if_icmpne     73
      69: iload_3
      70: iconst_2
      71: ior
      72: istore_3
      73: aload_0
      74: getfield      #30                 // Field reqSizeBuilder_:Lcom/google/protobuf/SingleFieldBuilder;
      77: ifnonnull     92
      80: aload_1
      81: aload_0
      82: getfield      #11                 // Field reqSize_:Lorg/apache/hadoop/hbase/protobuf/generated/QuotaProtos$TimedQuota;
      85: invokestatic  #44                 // Method org/apache/hadoop/hbase/protobuf/generated/QuotaProtos$Throttle.access$2002:(Lorg/apache/hadoop/hbase/protobuf/generated/QuotaProtos$Throttle;Lorg/apache/hadoop/hbase/protobuf/generated/QuotaProtos$TimedQuota;)Lorg/apache/hadoop/hbase/protobuf/generated/QuotaProtos$TimedQuota;
      88: pop
      89: goto          107
      92: aload_1
      93: aload_0
      94: getfield      #30                 // Field reqSizeBuilder_:Lcom/google/protobuf/SingleFieldBuilder;
      97: invokevirtual #42                 // Method com/google/protobuf/SingleFieldBuilder.build:()Lcom/google/protobuf/GeneratedMessage;
     100: checkcast     #43                 // class org/apache/hadoop/hbase/protobuf/generated/QuotaProtos$TimedQuota
     103: invokestatic  #44                 // Method org/apache/hadoop/hbase/protobuf/generated/QuotaProtos$Throttle.access$2002:(Lorg/apache/hadoop/hbase/protobuf/generated/QuotaProtos$Throttle;Lorg/apache/hadoop/hbase/protobuf/generated/QuotaProtos$TimedQuota;)Lorg/apache/hadoop/hbase/protobuf/generated/QuotaProtos$TimedQuota;
     106: pop
     107: iload_2
     108: iconst_4
     109: iand
     110: iconst_4
     111: if_icmpne     118
     114: iload_3
     115: iconst_4
     116: ior
     117: istore_3
     118: aload_0
     119: getfield      #31                 // Field writeNumBuilder_:Lcom/google/protobuf/SingleFieldBuilder;
     122: ifnonnull     137
     125: aload_1
     126: aload_0
     127: getfield      #12                 // Field writeNum_:Lorg/apache/hadoop/hbase/protobuf/generated/QuotaProtos$TimedQuota;
     130: invokestatic  #45                 // Method org/apache/hadoop/hbase/protobuf/generated/QuotaProtos$Throttle.access$2102:(Lorg/apache/hadoop/hbase/protobuf/generated/QuotaProtos$Throttle;Lorg/apache/hadoop/hbase/protobuf/generated/QuotaProtos$TimedQuota;)Lorg/apache/hadoop/hbase/protobuf/generated/QuotaProtos$TimedQuota;
     133: pop
     134: goto          152
     137: aload_1
     138: aload_0
     139: getfield      #31                 // Field writeNumBuilder_:Lcom/google/protobuf/SingleFieldBuilder;
     142: invokevirtual #42                 // Method com/google/protobuf/SingleFieldBuilder.build:()Lcom/google/protobuf/GeneratedMessage;
     145: checkcast     #43                 // class org/apache/hadoop/hbase/protobuf/generated/QuotaProtos$TimedQuota
     148: invokestatic  #45                 // Method org/apache/hadoop/hbase/protobuf/generated/QuotaProtos$Throttle.access$2102:(Lorg/apache/hadoop/hbase/protobuf/generated/QuotaProtos$Throttle;Lorg/apache/hadoop/hbase/protobuf/generated/QuotaProtos$TimedQuota;)Lorg/apache/hadoop/hbase/protobuf/generated/QuotaProtos$TimedQuota;
     151: pop
     152: iload_2
     153: bipush        8
     155: iand
     156: bipush        8
     158: if_icmpne     166
     161: iload_3
     162: bipush        8
     164: ior
     165: istore_3
     166: aload_0
     167: getfield      #32                 // Field writeSizeBuilder_:Lcom/google/protobuf/SingleFieldBuilder;
     170: ifnonnull     185
     173: aload_1
     174: aload_0
     175: getfield      #13                 // Field writeSize_:Lorg/apache/hadoop/hbase/protobuf/generated/QuotaProtos$TimedQuota;
     178: invokestatic  #46                 // Method org/apache/hadoop/hbase/protobuf/generated/QuotaProtos$Throttle.access$2202:(Lorg/apache/hadoop/hbase/protobuf/generated/QuotaProtos$Throttle;Lorg/apache/hadoop/hbase/protobuf/generated/QuotaProtos$TimedQuota;)Lorg/apache/hadoop/hbase/protobuf/generated/QuotaProtos$TimedQuota;
     181: pop
     182: goto          200
     185: aload_1
     186: aload_0
     187: getfield      #32                 // Field writeSizeBuilder_:Lcom/google/protobuf/SingleFieldBuilder;
     190: invokevirtual #42                 // Method com/google/protobuf/SingleFieldBuilder.build:()Lcom/google/protobuf/GeneratedMessage;
     193: checkcast     #43                 // class org/apache/hadoop/hbase/protobuf/generated/QuotaProtos$TimedQuota
     196: invokestatic  #46                 // Method org/apache/hadoop/hbase/protobuf/generated/QuotaProtos$Throttle.access$2202:(Lorg/apache/hadoop/hbase/protobuf/generated/QuotaProtos$Throttle;Lorg/apache/hadoop/hbase/protobuf/generated/QuotaProtos$TimedQuota;)Lorg/apache/hadoop/hbase/protobuf/generated/QuotaProtos$TimedQuota;
     199: pop
     200: iload_2
     201: bipush        16
     203: iand
     204: bipush        16
     206: if_icmpne     214
     209: iload_3
     210: bipush        16
     212: ior
     213: istore_3
     214: aload_0
     215: getfield      #33                 // Field readNumBuilder_:Lcom/google/protobuf/SingleFieldBuilder;
     218: ifnonnull     233
     221: aload_1
     222: aload_0
     223: getfield      #14                 // Field readNum_:Lorg/apache/hadoop/hbase/protobuf/generated/QuotaProtos$TimedQuota;
     226: invokestatic  #47                 // Method org/apache/hadoop/hbase/protobuf/generated/QuotaProtos$Throttle.access$2302:(Lorg/apache/hadoop/hbase/protobuf/generated/QuotaProtos$Throttle;Lorg/apache/hadoop/hbase/protobuf/generated/QuotaProtos$TimedQuota;)Lorg/apache/hadoop/hbase/protobuf/generated/QuotaProtos$TimedQuota;
     229: pop
     230: goto          248
     233: aload_1
     234: aload_0
     235: getfield      #33                 // Field readNumBuilder_:Lcom/google/protobuf/SingleFieldBuilder;
     238: invokevirtual #42                 // Method com/google/protobuf/SingleFieldBuilder.build:()Lcom/google/protobuf/GeneratedMessage;
     241: checkcast     #43                 // class org/apache/hadoop/hbase/protobuf/generated/QuotaProtos$TimedQuota
     244: invokestatic  #47                 // Method org/apache/hadoop/hbase/protobuf/generated/QuotaProtos$Throttle.access$2302:(Lorg/apache/hadoop/hbase/protobuf/generated/QuotaProtos$Throttle;Lorg/apache/hadoop/hbase/protobuf/generated/QuotaProtos$TimedQuota;)Lorg/apache/hadoop/hbase/protobuf/generated/QuotaProtos$TimedQuota;
     247: pop
     248: iload_2
     249: bipush        32
     251: iand
     252: bipush        32
     254: if_icmpne     262
     257: iload_3
     258: bipush        32
     260: ior
     261: istore_3
     262: aload_0
     263: getfield      #34                 // Field readSizeBuilder_:Lcom/google/protobuf/SingleFieldBuilder;
     266: ifnonnull     281
     269: aload_1
     270: aload_0
     271: getfield      #15                 // Field readSize_:Lorg/apache/hadoop/hbase/protobuf/generated/QuotaProtos$TimedQuota;
     274: invokestatic  #48                 // Method org/apache/hadoop/hbase/protobuf/generated/QuotaProtos$Throttle.access$2402:(Lorg/apache/hadoop/hbase/protobuf/generated/QuotaProtos$Throttle;Lorg/apache/hadoop/hbase/protobuf/generated/QuotaProtos$TimedQuota;)Lorg/apache/hadoop/hbase/protobuf/generated/QuotaProtos$TimedQuota;
     277: pop
     278: goto          296
     281: aload_1
     282: aload_0
     283: getfield      #34                 // Field readSizeBuilder_:Lcom/google/protobuf/SingleFieldBuilder;
     286: invokevirtual #42                 // Method com/google/protobuf/SingleFieldBuilder.build:()Lcom/google/protobuf/GeneratedMessage;
     289: checkcast     #43                 // class org/apache/hadoop/hbase/protobuf/generated/QuotaProtos$TimedQuota
     292: invokestatic  #48                 // Method org/apache/hadoop/hbase/protobuf/generated/QuotaProtos$Throttle.access$2402:(Lorg/apache/hadoop/hbase/protobuf/generated/QuotaProtos$Throttle;Lorg/apache/hadoop/hbase/protobuf/generated/QuotaProtos$TimedQuota;)Lorg/apache/hadoop/hbase/protobuf/generated/QuotaProtos$TimedQuota;
     295: pop
     296: aload_1
     297: iload_3
     298: invokestatic  #49                 // Method org/apache/hadoop/hbase/protobuf/generated/QuotaProtos$Throttle.access$2502:(Lorg/apache/hadoop/hbase/protobuf/generated/QuotaProtos$Throttle;I)I
     301: pop
     302: aload_0
     303: invokevirtual #50                 // Method onBuilt:()V
     306: aload_1
     307: areturn

  public org.apache.hadoop.hbase.protobuf.generated.QuotaProtos$Throttle$Builder mergeFrom(com.google.protobuf.Message);
    Code:
       0: aload_1
       1: instanceof    #5                  // class org/apache/hadoop/hbase/protobuf/generated/QuotaProtos$Throttle
       4: ifeq          16
       7: aload_0
       8: aload_1
       9: checkcast     #5                  // class org/apache/hadoop/hbase/protobuf/generated/QuotaProtos$Throttle
      12: invokevirtual #36                 // Method mergeFrom:(Lorg/apache/hadoop/hbase/protobuf/generated/QuotaProtos$Throttle;)Lorg/apache/hadoop/hbase/protobuf/generated/QuotaProtos$Throttle$Builder;
      15: areturn
      16: aload_0
      17: aload_1
      18: invokespecial #51                 // Method com/google/protobuf/GeneratedMessage$Builder.mergeFrom:(Lcom/google/protobuf/Message;)Lcom/google/protobuf/AbstractMessage$Builder;
      21: pop
      22: aload_0
      23: areturn

  public org.apache.hadoop.hbase.protobuf.generated.QuotaProtos$Throttle$Builder mergeFrom(org.apache.hadoop.hbase.protobuf.generated.QuotaProtos$Throttle);
    Code:
       0: aload_1
       1: invokestatic  #37                 // Method org/apache/hadoop/hbase/protobuf/generated/QuotaProtos$Throttle.getDefaultInstance:()Lorg/apache/hadoop/hbase/protobuf/generated/QuotaProtos$Throttle;
       4: if_acmpne     9
       7: aload_0
       8: areturn
       9: aload_1
      10: invokevirtual #52                 // Method org/apache/hadoop/hbase/protobuf/generated/QuotaProtos$Throttle.hasReqNum:()Z
      13: ifeq          25
      16: aload_0
      17: aload_1
      18: invokevirtual #53                 // Method org/apache/hadoop/hbase/protobuf/generated/QuotaProtos$Throttle.getReqNum:()Lorg/apache/hadoop/hbase/protobuf/generated/QuotaProtos$TimedQuota;
      21: invokevirtual #54                 // Method mergeReqNum:(Lorg/apache/hadoop/hbase/protobuf/generated/QuotaProtos$TimedQuota;)Lorg/apache/hadoop/hbase/protobuf/generated/QuotaProtos$Throttle$Builder;
      24: pop
      25: aload_1
      26: invokevirtual #55                 // Method org/apache/hadoop/hbase/protobuf/generated/QuotaProtos$Throttle.hasReqSize:()Z
      29: ifeq          41
      32: aload_0
      33: aload_1
      34: invokevirtual #56                 // Method org/apache/hadoop/hbase/protobuf/generated/QuotaProtos$Throttle.getReqSize:()Lorg/apache/hadoop/hbase/protobuf/generated/QuotaProtos$TimedQuota;
      37: invokevirtual #57                 // Method mergeReqSize:(Lorg/apache/hadoop/hbase/protobuf/generated/QuotaProtos$TimedQuota;)Lorg/apache/hadoop/hbase/protobuf/generated/QuotaProtos$Throttle$Builder;
      40: pop
      41: aload_1
      42: invokevirtual #58                 // Method org/apache/hadoop/hbase/protobuf/generated/QuotaProtos$Throttle.hasWriteNum:()Z
      45: ifeq          57
      48: aload_0
      49: aload_1
      50: invokevirtual #59                 // Method org/apache/hadoop/hbase/protobuf/generated/QuotaProtos$Throttle.getWriteNum:()Lorg/apache/hadoop/hbase/protobuf/generated/QuotaProtos$TimedQuota;
      53: invokevirtual #60                 // Method mergeWriteNum:(Lorg/apache/hadoop/hbase/protobuf/generated/QuotaProtos$TimedQuota;)Lorg/apache/hadoop/hbase/protobuf/generated/QuotaProtos$Throttle$Builder;
      56: pop
      57: aload_1
      58: invokevirtual #61                 // Method org/apache/hadoop/hbase/protobuf/generated/QuotaProtos$Throttle.hasWriteSize:()Z
      61: ifeq          73
      64: aload_0
      65: aload_1
      66: invokevirtual #62                 // Method org/apache/hadoop/hbase/protobuf/generated/QuotaProtos$Throttle.getWriteSize:()Lorg/apache/hadoop/hbase/protobuf/generated/QuotaProtos$TimedQuota;
      69: invokevirtual #63                 // Method mergeWriteSize:(Lorg/apache/hadoop/hbase/protobuf/generated/QuotaProtos$TimedQuota;)Lorg/apache/hadoop/hbase/protobuf/generated/QuotaProtos$Throttle$Builder;
      72: pop
      73: aload_1
      74: invokevirtual #64                 // Method org/apache/hadoop/hbase/protobuf/generated/QuotaProtos$Throttle.hasReadNum:()Z
      77: ifeq          89
      80: aload_0
      81: aload_1
      82: invokevirtual #65                 // Method org/apache/hadoop/hbase/protobuf/generated/QuotaProtos$Throttle.getReadNum:()Lorg/apache/hadoop/hbase/protobuf/generated/QuotaProtos$TimedQuota;
      85: invokevirtual #66                 // Method mergeReadNum:(Lorg/apache/hadoop/hbase/protobuf/generated/QuotaProtos$TimedQuota;)Lorg/apache/hadoop/hbase/protobuf/generated/QuotaProtos$Throttle$Builder;
      88: pop
      89: aload_1
      90: invokevirtual #67                 // Method org/apache/hadoop/hbase/protobuf/generated/QuotaProtos$Throttle.hasReadSize:()Z
      93: ifeq          105
      96: aload_0
      97: aload_1
      98: invokevirtual #68                 // Method org/apache/hadoop/hbase/protobuf/generated/QuotaProtos$Throttle.getReadSize:()Lorg/apache/hadoop/hbase/protobuf/generated/QuotaProtos$TimedQuota;
     101: invokevirtual #69                 // Method mergeReadSize:(Lorg/apache/hadoop/hbase/protobuf/generated/QuotaProtos$TimedQuota;)Lorg/apache/hadoop/hbase/protobuf/generated/QuotaProtos$Throttle$Builder;
     104: pop
     105: aload_0
     106: aload_1
     107: invokevirtual #70                 // Method org/apache/hadoop/hbase/protobuf/generated/QuotaProtos$Throttle.getUnknownFields:()Lcom/google/protobuf/UnknownFieldSet;
     110: invokevirtual #71                 // Method mergeUnknownFields:(Lcom/google/protobuf/UnknownFieldSet;)Lcom/google/protobuf/GeneratedMessage$Builder;
     113: pop
     114: aload_0
     115: areturn

  public final boolean isInitialized();
    Code:
       0: aload_0
       1: invokevirtual #72                 // Method hasReqNum:()Z
       4: ifeq          19
       7: aload_0
       8: invokevirtual #73                 // Method getReqNum:()Lorg/apache/hadoop/hbase/protobuf/generated/QuotaProtos$TimedQuota;
      11: invokevirtual #74                 // Method org/apache/hadoop/hbase/protobuf/generated/QuotaProtos$TimedQuota.isInitialized:()Z
      14: ifne          19
      17: iconst_0
      18: ireturn
      19: aload_0
      20: invokevirtual #75                 // Method hasReqSize:()Z
      23: ifeq          38
      26: aload_0
      27: invokevirtual #76                 // Method getReqSize:()Lorg/apache/hadoop/hbase/protobuf/generated/QuotaProtos$TimedQuota;
      30: invokevirtual #74                 // Method org/apache/hadoop/hbase/protobuf/generated/QuotaProtos$TimedQuota.isInitialized:()Z
      33: ifne          38
      36: iconst_0
      37: ireturn
      38: aload_0
      39: invokevirtual #77                 // Method hasWriteNum:()Z
      42: ifeq          57
      45: aload_0
      46: invokevirtual #78                 // Method getWriteNum:()Lorg/apache/hadoop/hbase/protobuf/generated/QuotaProtos$TimedQuota;
      49: invokevirtual #74                 // Method org/apache/hadoop/hbase/protobuf/generated/QuotaProtos$TimedQuota.isInitialized:()Z
      52: ifne          57
      55: iconst_0
      56: ireturn
      57: aload_0
      58: invokevirtual #79                 // Method hasWriteSize:()Z
      61: ifeq          76
      64: aload_0
      65: invokevirtual #80                 // Method getWriteSize:()Lorg/apache/hadoop/hbase/protobuf/generated/QuotaProtos$TimedQuota;
      68: invokevirtual #74                 // Method org/apache/hadoop/hbase/protobuf/generated/QuotaProtos$TimedQuota.isInitialized:()Z
      71: ifne          76
      74: iconst_0
      75: ireturn
      76: aload_0
      77: invokevirtual #81                 // Method hasReadNum:()Z
      80: ifeq          95
      83: aload_0
      84: invokevirtual #82                 // Method getReadNum:()Lorg/apache/hadoop/hbase/protobuf/generated/QuotaProtos$TimedQuota;
      87: invokevirtual #74                 // Method org/apache/hadoop/hbase/protobuf/generated/QuotaProtos$TimedQuota.isInitialized:()Z
      90: ifne          95
      93: iconst_0
      94: ireturn
      95: aload_0
      96: invokevirtual #83                 // Method hasReadSize:()Z
      99: ifeq          114
     102: aload_0
     103: invokevirtual #84                 // Method getReadSize:()Lorg/apache/hadoop/hbase/protobuf/generated/QuotaProtos$TimedQuota;
     106: invokevirtual #74                 // Method org/apache/hadoop/hbase/protobuf/generated/QuotaProtos$TimedQuota.isInitialized:()Z
     109: ifne          114
     112: iconst_0
     113: ireturn
     114: iconst_1
     115: ireturn

  public org.apache.hadoop.hbase.protobuf.generated.QuotaProtos$Throttle$Builder mergeFrom(com.google.protobuf.CodedInputStream, com.google.protobuf.ExtensionRegistryLite) throws java.io.IOException;
    Code:
       0: aconst_null
       1: astore_3
       2: getstatic     #85                 // Field org/apache/hadoop/hbase/protobuf/generated/QuotaProtos$Throttle.PARSER:Lcom/google/protobuf/Parser;
       5: aload_1
       6: aload_2
       7: invokeinterface #86,  3           // InterfaceMethod com/google/protobuf/Parser.parsePartialFrom:(Lcom/google/protobuf/CodedInputStream;Lcom/google/protobuf/ExtensionRegistryLite;)Ljava/lang/Object;
      12: checkcast     #5                  // class org/apache/hadoop/hbase/protobuf/generated/QuotaProtos$Throttle
      15: astore_3
      16: aload_3
      17: ifnull        58
      20: aload_0
      21: aload_3
      22: invokevirtual #36                 // Method mergeFrom:(Lorg/apache/hadoop/hbase/protobuf/generated/QuotaProtos$Throttle;)Lorg/apache/hadoop/hbase/protobuf/generated/QuotaProtos$Throttle$Builder;
      25: pop
      26: goto          58
      29: astore        4
      31: aload         4
      33: invokevirtual #88                 // Method com/google/protobuf/InvalidProtocolBufferException.getUnfinishedMessage:()Lcom/google/protobuf/MessageLite;
      36: checkcast     #5                  // class org/apache/hadoop/hbase/protobuf/generated/QuotaProtos$Throttle
      39: astore_3
      40: aload         4
      42: athrow
      43: astore        5
      45: aload_3
      46: ifnull        55
      49: aload_0
      50: aload_3
      51: invokevirtual #36                 // Method mergeFrom:(Lorg/apache/hadoop/hbase/protobuf/generated/QuotaProtos$Throttle;)Lorg/apache/hadoop/hbase/protobuf/generated/QuotaProtos$Throttle$Builder;
      54: pop
      55: aload         5
      57: athrow
      58: aload_0
      59: areturn
    Exception table:
       from    to  target type
           2    16    29   Class com/google/protobuf/InvalidProtocolBufferException
           2    16    43   any
          29    45    43   any

  public boolean hasReqNum();
    Code:
       0: aload_0
       1: getfield      #29                 // Field bitField0_:I
       4: iconst_1
       5: iand
       6: iconst_1
       7: if_icmpne     14
      10: iconst_1
      11: goto          15
      14: iconst_0
      15: ireturn

  public org.apache.hadoop.hbase.protobuf.generated.QuotaProtos$TimedQuota getReqNum();
    Code:
       0: aload_0
       1: getfield      #27                 // Field reqNumBuilder_:Lcom/google/protobuf/SingleFieldBuilder;
       4: ifnonnull     12
       7: aload_0
       8: getfield      #10                 // Field reqNum_:Lorg/apache/hadoop/hbase/protobuf/generated/QuotaProtos$TimedQuota;
      11: areturn
      12: aload_0
      13: getfield      #27                 // Field reqNumBuilder_:Lcom/google/protobuf/SingleFieldBuilder;
      16: invokevirtual #89                 // Method com/google/protobuf/SingleFieldBuilder.getMessage:()Lcom/google/protobuf/GeneratedMessage;
      19: checkcast     #43                 // class org/apache/hadoop/hbase/protobuf/generated/QuotaProtos$TimedQuota
      22: areturn

  public org.apache.hadoop.hbase.protobuf.generated.QuotaProtos$Throttle$Builder setReqNum(org.apache.hadoop.hbase.protobuf.generated.QuotaProtos$TimedQuota);
    Code:
       0: aload_0
       1: getfield      #27                 // Field reqNumBuilder_:Lcom/google/protobuf/SingleFieldBuilder;
       4: ifnonnull     31
       7: aload_1
       8: ifnonnull     19
      11: new           #90                 // class java/lang/NullPointerException
      14: dup
      15: invokespecial #91                 // Method java/lang/NullPointerException."<init>":()V
      18: athrow
      19: aload_0
      20: aload_1
      21: putfield      #10                 // Field reqNum_:Lorg/apache/hadoop/hbase/protobuf/generated/QuotaProtos$TimedQuota;
      24: aload_0
      25: invokevirtual #92                 // Method onChanged:()V
      28: goto          40
      31: aload_0
      32: getfield      #27                 // Field reqNumBuilder_:Lcom/google/protobuf/SingleFieldBuilder;
      35: aload_1
      36: invokevirtual #93                 // Method com/google/protobuf/SingleFieldBuilder.setMessage:(Lcom/google/protobuf/GeneratedMessage;)Lcom/google/protobuf/SingleFieldBuilder;
      39: pop
      40: aload_0
      41: dup
      42: getfield      #29                 // Field bitField0_:I
      45: iconst_1
      46: ior
      47: putfield      #29                 // Field bitField0_:I
      50: aload_0
      51: areturn

  public org.apache.hadoop.hbase.protobuf.generated.QuotaProtos$Throttle$Builder setReqNum(org.apache.hadoop.hbase.protobuf.generated.QuotaProtos$TimedQuota$Builder);
    Code:
       0: aload_0
       1: getfield      #27                 // Field reqNumBuilder_:Lcom/google/protobuf/SingleFieldBuilder;
       4: ifnonnull     22
       7: aload_0
       8: aload_1
       9: invokevirtual #94                 // Method org/apache/hadoop/hbase/protobuf/generated/QuotaProtos$TimedQuota$Builder.build:()Lorg/apache/hadoop/hbase/protobuf/generated/QuotaProtos$TimedQuota;
      12: putfield      #10                 // Field reqNum_:Lorg/apache/hadoop/hbase/protobuf/generated/QuotaProtos$TimedQuota;
      15: aload_0
      16: invokevirtual #92                 // Method onChanged:()V
      19: goto          34
      22: aload_0
      23: getfield      #27                 // Field reqNumBuilder_:Lcom/google/protobuf/SingleFieldBuilder;
      26: aload_1
      27: invokevirtual #94                 // Method org/apache/hadoop/hbase/protobuf/generated/QuotaProtos$TimedQuota$Builder.build:()Lorg/apache/hadoop/hbase/protobuf/generated/QuotaProtos$TimedQuota;
      30: invokevirtual #93                 // Method com/google/protobuf/SingleFieldBuilder.setMessage:(Lcom/google/protobuf/GeneratedMessage;)Lcom/google/protobuf/SingleFieldBuilder;
      33: pop
      34: aload_0
      35: dup
      36: getfield      #29                 // Field bitField0_:I
      39: iconst_1
      40: ior
      41: putfield      #29                 // Field bitField0_:I
      44: aload_0
      45: areturn

  public org.apache.hadoop.hbase.protobuf.generated.QuotaProtos$Throttle$Builder mergeReqNum(org.apache.hadoop.hbase.protobuf.generated.QuotaProtos$TimedQuota);
    Code:
       0: aload_0
       1: getfield      #27                 // Field reqNumBuilder_:Lcom/google/protobuf/SingleFieldBuilder;
       4: ifnonnull     60
       7: aload_0
       8: getfield      #29                 // Field bitField0_:I
      11: iconst_1
      12: iand
      13: iconst_1
      14: if_icmpne     48
      17: aload_0
      18: getfield      #10                 // Field reqNum_:Lorg/apache/hadoop/hbase/protobuf/generated/QuotaProtos$TimedQuota;
      21: invokestatic  #9                  // Method org/apache/hadoop/hbase/protobuf/generated/QuotaProtos$TimedQuota.getDefaultInstance:()Lorg/apache/hadoop/hbase/protobuf/generated/QuotaProtos$TimedQuota;
      24: if_acmpeq     48
      27: aload_0
      28: aload_0
      29: getfield      #10                 // Field reqNum_:Lorg/apache/hadoop/hbase/protobuf/generated/QuotaProtos$TimedQuota;
      32: invokestatic  #95                 // Method org/apache/hadoop/hbase/protobuf/generated/QuotaProtos$TimedQuota.newBuilder:(Lorg/apache/hadoop/hbase/protobuf/generated/QuotaProtos$TimedQuota;)Lorg/apache/hadoop/hbase/protobuf/generated/QuotaProtos$TimedQuota$Builder;
      35: aload_1
      36: invokevirtual #96                 // Method org/apache/hadoop/hbase/protobuf/generated/QuotaProtos$TimedQuota$Builder.mergeFrom:(Lorg/apache/hadoop/hbase/protobuf/generated/QuotaProtos$TimedQuota;)Lorg/apache/hadoop/hbase/protobuf/generated/QuotaProtos$TimedQuota$Builder;
      39: invokevirtual #97                 // Method org/apache/hadoop/hbase/protobuf/generated/QuotaProtos$TimedQuota$Builder.buildPartial:()Lorg/apache/hadoop/hbase/protobuf/generated/QuotaProtos$TimedQuota;
      42: putfield      #10                 // Field reqNum_:Lorg/apache/hadoop/hbase/protobuf/generated/QuotaProtos$TimedQuota;
      45: goto          53
      48: aload_0
      49: aload_1
      50: putfield      #10                 // Field reqNum_:Lorg/apache/hadoop/hbase/protobuf/generated/QuotaProtos$TimedQuota;
      53: aload_0
      54: invokevirtual #92                 // Method onChanged:()V
      57: goto          69
      60: aload_0
      61: getfield      #27                 // Field reqNumBuilder_:Lcom/google/protobuf/SingleFieldBuilder;
      64: aload_1
      65: invokevirtual #98                 // Method com/google/protobuf/SingleFieldBuilder.mergeFrom:(Lcom/google/protobuf/GeneratedMessage;)Lcom/google/protobuf/SingleFieldBuilder;
      68: pop
      69: aload_0
      70: dup
      71: getfield      #29                 // Field bitField0_:I
      74: iconst_1
      75: ior
      76: putfield      #29                 // Field bitField0_:I
      79: aload_0
      80: areturn

  public org.apache.hadoop.hbase.protobuf.generated.QuotaProtos$Throttle$Builder clearReqNum();
    Code:
       0: aload_0
       1: getfield      #27                 // Field reqNumBuilder_:Lcom/google/protobuf/SingleFieldBuilder;
       4: ifnonnull     21
       7: aload_0
       8: invokestatic  #9                  // Method org/apache/hadoop/hbase/protobuf/generated/QuotaProtos$TimedQuota.getDefaultInstance:()Lorg/apache/hadoop/hbase/protobuf/generated/QuotaProtos$TimedQuota;
      11: putfield      #10                 // Field reqNum_:Lorg/apache/hadoop/hbase/protobuf/generated/QuotaProtos$TimedQuota;
      14: aload_0
      15: invokevirtual #92                 // Method onChanged:()V
      18: goto          29
      21: aload_0
      22: getfield      #27                 // Field reqNumBuilder_:Lcom/google/protobuf/SingleFieldBuilder;
      25: invokevirtual #28                 // Method com/google/protobuf/SingleFieldBuilder.clear:()Lcom/google/protobuf/SingleFieldBuilder;
      28: pop
      29: aload_0
      30: aload_0
      31: getfield      #29                 // Field bitField0_:I
      34: bipush        -2
      36: iand
      37: putfield      #29                 // Field bitField0_:I
      40: aload_0
      41: areturn

  public org.apache.hadoop.hbase.protobuf.generated.QuotaProtos$TimedQuota$Builder getReqNumBuilder();
    Code:
       0: aload_0
       1: dup
       2: getfield      #29                 // Field bitField0_:I
       5: iconst_1
       6: ior
       7: putfield      #29                 // Field bitField0_:I
      10: aload_0
      11: invokevirtual #92                 // Method onChanged:()V
      14: aload_0
      15: invokespecial #19                 // Method getReqNumFieldBuilder:()Lcom/google/protobuf/SingleFieldBuilder;
      18: invokevirtual #99                 // Method com/google/protobuf/SingleFieldBuilder.getBuilder:()Lcom/google/protobuf/GeneratedMessage$Builder;
      21: checkcast     #100                // class org/apache/hadoop/hbase/protobuf/generated/QuotaProtos$TimedQuota$Builder
      24: areturn

  public org.apache.hadoop.hbase.protobuf.generated.QuotaProtos$TimedQuotaOrBuilder getReqNumOrBuilder();
    Code:
       0: aload_0
       1: getfield      #27                 // Field reqNumBuilder_:Lcom/google/protobuf/SingleFieldBuilder;
       4: ifnull        18
       7: aload_0
       8: getfield      #27                 // Field reqNumBuilder_:Lcom/google/protobuf/SingleFieldBuilder;
      11: invokevirtual #101                // Method com/google/protobuf/SingleFieldBuilder.getMessageOrBuilder:()Lcom/google/protobuf/MessageOrBuilder;
      14: checkcast     #102                // class org/apache/hadoop/hbase/protobuf/generated/QuotaProtos$TimedQuotaOrBuilder
      17: areturn
      18: aload_0
      19: getfield      #10                 // Field reqNum_:Lorg/apache/hadoop/hbase/protobuf/generated/QuotaProtos$TimedQuota;
      22: areturn

  public boolean hasReqSize();
    Code:
       0: aload_0
       1: getfield      #29                 // Field bitField0_:I
       4: iconst_2
       5: iand
       6: iconst_2
       7: if_icmpne     14
      10: iconst_1
      11: goto          15
      14: iconst_0
      15: ireturn

  public org.apache.hadoop.hbase.protobuf.generated.QuotaProtos$TimedQuota getReqSize();
    Code:
       0: aload_0
       1: getfield      #30                 // Field reqSizeBuilder_:Lcom/google/protobuf/SingleFieldBuilder;
       4: ifnonnull     12
       7: aload_0
       8: getfield      #11                 // Field reqSize_:Lorg/apache/hadoop/hbase/protobuf/generated/QuotaProtos$TimedQuota;
      11: areturn
      12: aload_0
      13: getfield      #30                 // Field reqSizeBuilder_:Lcom/google/protobuf/SingleFieldBuilder;
      16: invokevirtual #89                 // Method com/google/protobuf/SingleFieldBuilder.getMessage:()Lcom/google/protobuf/GeneratedMessage;
      19: checkcast     #43                 // class org/apache/hadoop/hbase/protobuf/generated/QuotaProtos$TimedQuota
      22: areturn

  public org.apache.hadoop.hbase.protobuf.generated.QuotaProtos$Throttle$Builder setReqSize(org.apache.hadoop.hbase.protobuf.generated.QuotaProtos$TimedQuota);
    Code:
       0: aload_0
       1: getfield      #30                 // Field reqSizeBuilder_:Lcom/google/protobuf/SingleFieldBuilder;
       4: ifnonnull     31
       7: aload_1
       8: ifnonnull     19
      11: new           #90                 // class java/lang/NullPointerException
      14: dup
      15: invokespecial #91                 // Method java/lang/NullPointerException."<init>":()V
      18: athrow
      19: aload_0
      20: aload_1
      21: putfield      #11                 // Field reqSize_:Lorg/apache/hadoop/hbase/protobuf/generated/QuotaProtos$TimedQuota;
      24: aload_0
      25: invokevirtual #92                 // Method onChanged:()V
      28: goto          40
      31: aload_0
      32: getfield      #30                 // Field reqSizeBuilder_:Lcom/google/protobuf/SingleFieldBuilder;
      35: aload_1
      36: invokevirtual #93                 // Method com/google/protobuf/SingleFieldBuilder.setMessage:(Lcom/google/protobuf/GeneratedMessage;)Lcom/google/protobuf/SingleFieldBuilder;
      39: pop
      40: aload_0
      41: dup
      42: getfield      #29                 // Field bitField0_:I
      45: iconst_2
      46: ior
      47: putfield      #29                 // Field bitField0_:I
      50: aload_0
      51: areturn

  public org.apache.hadoop.hbase.protobuf.generated.QuotaProtos$Throttle$Builder setReqSize(org.apache.hadoop.hbase.protobuf.generated.QuotaProtos$TimedQuota$Builder);
    Code:
       0: aload_0
       1: getfield      #30                 // Field reqSizeBuilder_:Lcom/google/protobuf/SingleFieldBuilder;
       4: ifnonnull     22
       7: aload_0
       8: aload_1
       9: invokevirtual #94                 // Method org/apache/hadoop/hbase/protobuf/generated/QuotaProtos$TimedQuota$Builder.build:()Lorg/apache/hadoop/hbase/protobuf/generated/QuotaProtos$TimedQuota;
      12: putfield      #11                 // Field reqSize_:Lorg/apache/hadoop/hbase/protobuf/generated/QuotaProtos$TimedQuota;
      15: aload_0
      16: invokevirtual #92                 // Method onChanged:()V
      19: goto          34
      22: aload_0
      23: getfield      #30                 // Field reqSizeBuilder_:Lcom/google/protobuf/SingleFieldBuilder;
      26: aload_1
      27: invokevirtual #94                 // Method org/apache/hadoop/hbase/protobuf/generated/QuotaProtos$TimedQuota$Builder.build:()Lorg/apache/hadoop/hbase/protobuf/generated/QuotaProtos$TimedQuota;
      30: invokevirtual #93                 // Method com/google/protobuf/SingleFieldBuilder.setMessage:(Lcom/google/protobuf/GeneratedMessage;)Lcom/google/protobuf/SingleFieldBuilder;
      33: pop
      34: aload_0
      35: dup
      36: getfield      #29                 // Field bitField0_:I
      39: iconst_2
      40: ior
      41: putfield      #29                 // Field bitField0_:I
      44: aload_0
      45: areturn

  public org.apache.hadoop.hbase.protobuf.generated.QuotaProtos$Throttle$Builder mergeReqSize(org.apache.hadoop.hbase.protobuf.generated.QuotaProtos$TimedQuota);
    Code:
       0: aload_0
       1: getfield      #30                 // Field reqSizeBuilder_:Lcom/google/protobuf/SingleFieldBuilder;
       4: ifnonnull     60
       7: aload_0
       8: getfield      #29                 // Field bitField0_:I
      11: iconst_2
      12: iand
      13: iconst_2
      14: if_icmpne     48
      17: aload_0
      18: getfield      #11                 // Field reqSize_:Lorg/apache/hadoop/hbase/protobuf/generated/QuotaProtos$TimedQuota;
      21: invokestatic  #9                  // Method org/apache/hadoop/hbase/protobuf/generated/QuotaProtos$TimedQuota.getDefaultInstance:()Lorg/apache/hadoop/hbase/protobuf/generated/QuotaProtos$TimedQuota;
      24: if_acmpeq     48
      27: aload_0
      28: aload_0
      29: getfield      #11                 // Field reqSize_:Lorg/apache/hadoop/hbase/protobuf/generated/QuotaProtos$TimedQuota;
      32: invokestatic  #95                 // Method org/apache/hadoop/hbase/protobuf/generated/QuotaProtos$TimedQuota.newBuilder:(Lorg/apache/hadoop/hbase/protobuf/generated/QuotaProtos$TimedQuota;)Lorg/apache/hadoop/hbase/protobuf/generated/QuotaProtos$TimedQuota$Builder;
      35: aload_1
      36: invokevirtual #96                 // Method org/apache/hadoop/hbase/protobuf/generated/QuotaProtos$TimedQuota$Builder.mergeFrom:(Lorg/apache/hadoop/hbase/protobuf/generated/QuotaProtos$TimedQuota;)Lorg/apache/hadoop/hbase/protobuf/generated/QuotaProtos$TimedQuota$Builder;
      39: invokevirtual #97                 // Method org/apache/hadoop/hbase/protobuf/generated/QuotaProtos$TimedQuota$Builder.buildPartial:()Lorg/apache/hadoop/hbase/protobuf/generated/QuotaProtos$TimedQuota;
      42: putfield      #11                 // Field reqSize_:Lorg/apache/hadoop/hbase/protobuf/generated/QuotaProtos$TimedQuota;
      45: goto          53
      48: aload_0
      49: aload_1
      50: putfield      #11                 // Field reqSize_:Lorg/apache/hadoop/hbase/protobuf/generated/QuotaProtos$TimedQuota;
      53: aload_0
      54: invokevirtual #92                 // Method onChanged:()V
      57: goto          69
      60: aload_0
      61: getfield      #30                 // Field reqSizeBuilder_:Lcom/google/protobuf/SingleFieldBuilder;
      64: aload_1
      65: invokevirtual #98                 // Method com/google/protobuf/SingleFieldBuilder.mergeFrom:(Lcom/google/protobuf/GeneratedMessage;)Lcom/google/protobuf/SingleFieldBuilder;
      68: pop
      69: aload_0
      70: dup
      71: getfield      #29                 // Field bitField0_:I
      74: iconst_2
      75: ior
      76: putfield      #29                 // Field bitField0_:I
      79: aload_0
      80: areturn

  public org.apache.hadoop.hbase.protobuf.generated.QuotaProtos$Throttle$Builder clearReqSize();
    Code:
       0: aload_0
       1: getfield      #30                 // Field reqSizeBuilder_:Lcom/google/protobuf/SingleFieldBuilder;
       4: ifnonnull     21
       7: aload_0
       8: invokestatic  #9                  // Method org/apache/hadoop/hbase/protobuf/generated/QuotaProtos$TimedQuota.getDefaultInstance:()Lorg/apache/hadoop/hbase/protobuf/generated/QuotaProtos$TimedQuota;
      11: putfield      #11                 // Field reqSize_:Lorg/apache/hadoop/hbase/protobuf/generated/QuotaProtos$TimedQuota;
      14: aload_0
      15: invokevirtual #92                 // Method onChanged:()V
      18: goto          29
      21: aload_0
      22: getfield      #30                 // Field reqSizeBuilder_:Lcom/google/protobuf/SingleFieldBuilder;
      25: invokevirtual #28                 // Method com/google/protobuf/SingleFieldBuilder.clear:()Lcom/google/protobuf/SingleFieldBuilder;
      28: pop
      29: aload_0
      30: aload_0
      31: getfield      #29                 // Field bitField0_:I
      34: bipush        -3
      36: iand
      37: putfield      #29                 // Field bitField0_:I
      40: aload_0
      41: areturn

  public org.apache.hadoop.hbase.protobuf.generated.QuotaProtos$TimedQuota$Builder getReqSizeBuilder();
    Code:
       0: aload_0
       1: dup
       2: getfield      #29                 // Field bitField0_:I
       5: iconst_2
       6: ior
       7: putfield      #29                 // Field bitField0_:I
      10: aload_0
      11: invokevirtual #92                 // Method onChanged:()V
      14: aload_0
      15: invokespecial #20                 // Method getReqSizeFieldBuilder:()Lcom/google/protobuf/SingleFieldBuilder;
      18: invokevirtual #99                 // Method com/google/protobuf/SingleFieldBuilder.getBuilder:()Lcom/google/protobuf/GeneratedMessage$Builder;
      21: checkcast     #100                // class org/apache/hadoop/hbase/protobuf/generated/QuotaProtos$TimedQuota$Builder
      24: areturn

  public org.apache.hadoop.hbase.protobuf.generated.QuotaProtos$TimedQuotaOrBuilder getReqSizeOrBuilder();
    Code:
       0: aload_0
       1: getfield      #30                 // Field reqSizeBuilder_:Lcom/google/protobuf/SingleFieldBuilder;
       4: ifnull        18
       7: aload_0
       8: getfield      #30                 // Field reqSizeBuilder_:Lcom/google/protobuf/SingleFieldBuilder;
      11: invokevirtual #101                // Method com/google/protobuf/SingleFieldBuilder.getMessageOrBuilder:()Lcom/google/protobuf/MessageOrBuilder;
      14: checkcast     #102                // class org/apache/hadoop/hbase/protobuf/generated/QuotaProtos$TimedQuotaOrBuilder
      17: areturn
      18: aload_0
      19: getfield      #11                 // Field reqSize_:Lorg/apache/hadoop/hbase/protobuf/generated/QuotaProtos$TimedQuota;
      22: areturn

  public boolean hasWriteNum();
    Code:
       0: aload_0
       1: getfield      #29                 // Field bitField0_:I
       4: iconst_4
       5: iand
       6: iconst_4
       7: if_icmpne     14
      10: iconst_1
      11: goto          15
      14: iconst_0
      15: ireturn

  public org.apache.hadoop.hbase.protobuf.generated.QuotaProtos$TimedQuota getWriteNum();
    Code:
       0: aload_0
       1: getfield      #31                 // Field writeNumBuilder_:Lcom/google/protobuf/SingleFieldBuilder;
       4: ifnonnull     12
       7: aload_0
       8: getfield      #12                 // Field writeNum_:Lorg/apache/hadoop/hbase/protobuf/generated/QuotaProtos$TimedQuota;
      11: areturn
      12: aload_0
      13: getfield      #31                 // Field writeNumBuilder_:Lcom/google/protobuf/SingleFieldBuilder;
      16: invokevirtual #89                 // Method com/google/protobuf/SingleFieldBuilder.getMessage:()Lcom/google/protobuf/GeneratedMessage;
      19: checkcast     #43                 // class org/apache/hadoop/hbase/protobuf/generated/QuotaProtos$TimedQuota
      22: areturn

  public org.apache.hadoop.hbase.protobuf.generated.QuotaProtos$Throttle$Builder setWriteNum(org.apache.hadoop.hbase.protobuf.generated.QuotaProtos$TimedQuota);
    Code:
       0: aload_0
       1: getfield      #31                 // Field writeNumBuilder_:Lcom/google/protobuf/SingleFieldBuilder;
       4: ifnonnull     31
       7: aload_1
       8: ifnonnull     19
      11: new           #90                 // class java/lang/NullPointerException
      14: dup
      15: invokespecial #91                 // Method java/lang/NullPointerException."<init>":()V
      18: athrow
      19: aload_0
      20: aload_1
      21: putfield      #12                 // Field writeNum_:Lorg/apache/hadoop/hbase/protobuf/generated/QuotaProtos$TimedQuota;
      24: aload_0
      25: invokevirtual #92                 // Method onChanged:()V
      28: goto          40
      31: aload_0
      32: getfield      #31                 // Field writeNumBuilder_:Lcom/google/protobuf/SingleFieldBuilder;
      35: aload_1
      36: invokevirtual #93                 // Method com/google/protobuf/SingleFieldBuilder.setMessage:(Lcom/google/protobuf/GeneratedMessage;)Lcom/google/protobuf/SingleFieldBuilder;
      39: pop
      40: aload_0
      41: dup
      42: getfield      #29                 // Field bitField0_:I
      45: iconst_4
      46: ior
      47: putfield      #29                 // Field bitField0_:I
      50: aload_0
      51: areturn

  public org.apache.hadoop.hbase.protobuf.generated.QuotaProtos$Throttle$Builder setWriteNum(org.apache.hadoop.hbase.protobuf.generated.QuotaProtos$TimedQuota$Builder);
    Code:
       0: aload_0
       1: getfield      #31                 // Field writeNumBuilder_:Lcom/google/protobuf/SingleFieldBuilder;
       4: ifnonnull     22
       7: aload_0
       8: aload_1
       9: invokevirtual #94                 // Method org/apache/hadoop/hbase/protobuf/generated/QuotaProtos$TimedQuota$Builder.build:()Lorg/apache/hadoop/hbase/protobuf/generated/QuotaProtos$TimedQuota;
      12: putfield      #12                 // Field writeNum_:Lorg/apache/hadoop/hbase/protobuf/generated/QuotaProtos$TimedQuota;
      15: aload_0
      16: invokevirtual #92                 // Method onChanged:()V
      19: goto          34
      22: aload_0
      23: getfield      #31                 // Field writeNumBuilder_:Lcom/google/protobuf/SingleFieldBuilder;
      26: aload_1
      27: invokevirtual #94                 // Method org/apache/hadoop/hbase/protobuf/generated/QuotaProtos$TimedQuota$Builder.build:()Lorg/apache/hadoop/hbase/protobuf/generated/QuotaProtos$TimedQuota;
      30: invokevirtual #93                 // Method com/google/protobuf/SingleFieldBuilder.setMessage:(Lcom/google/protobuf/GeneratedMessage;)Lcom/google/protobuf/SingleFieldBuilder;
      33: pop
      34: aload_0
      35: dup
      36: getfield      #29                 // Field bitField0_:I
      39: iconst_4
      40: ior
      41: putfield      #29                 // Field bitField0_:I
      44: aload_0
      45: areturn

  public org.apache.hadoop.hbase.protobuf.generated.QuotaProtos$Throttle$Builder mergeWriteNum(org.apache.hadoop.hbase.protobuf.generated.QuotaProtos$TimedQuota);
    Code:
       0: aload_0
       1: getfield      #31                 // Field writeNumBuilder_:Lcom/google/protobuf/SingleFieldBuilder;
       4: ifnonnull     60
       7: aload_0
       8: getfield      #29                 // Field bitField0_:I
      11: iconst_4
      12: iand
      13: iconst_4
      14: if_icmpne     48
      17: aload_0
      18: getfield      #12                 // Field writeNum_:Lorg/apache/hadoop/hbase/protobuf/generated/QuotaProtos$TimedQuota;
      21: invokestatic  #9                  // Method org/apache/hadoop/hbase/protobuf/generated/QuotaProtos$TimedQuota.getDefaultInstance:()Lorg/apache/hadoop/hbase/protobuf/generated/QuotaProtos$TimedQuota;
      24: if_acmpeq     48
      27: aload_0
      28: aload_0
      29: getfield      #12                 // Field writeNum_:Lorg/apache/hadoop/hbase/protobuf/generated/QuotaProtos$TimedQuota;
      32: invokestatic  #95                 // Method org/apache/hadoop/hbase/protobuf/generated/QuotaProtos$TimedQuota.newBuilder:(Lorg/apache/hadoop/hbase/protobuf/generated/QuotaProtos$TimedQuota;)Lorg/apache/hadoop/hbase/protobuf/generated/QuotaProtos$TimedQuota$Builder;
      35: aload_1
      36: invokevirtual #96                 // Method org/apache/hadoop/hbase/protobuf/generated/QuotaProtos$TimedQuota$Builder.mergeFrom:(Lorg/apache/hadoop/hbase/protobuf/generated/QuotaProtos$TimedQuota;)Lorg/apache/hadoop/hbase/protobuf/generated/QuotaProtos$TimedQuota$Builder;
      39: invokevirtual #97                 // Method org/apache/hadoop/hbase/protobuf/generated/QuotaProtos$TimedQuota$Builder.buildPartial:()Lorg/apache/hadoop/hbase/protobuf/generated/QuotaProtos$TimedQuota;
      42: putfield      #12                 // Field writeNum_:Lorg/apache/hadoop/hbase/protobuf/generated/QuotaProtos$TimedQuota;
      45: goto          53
      48: aload_0
      49: aload_1
      50: putfield      #12                 // Field writeNum_:Lorg/apache/hadoop/hbase/protobuf/generated/QuotaProtos$TimedQuota;
      53: aload_0
      54: invokevirtual #92                 // Method onChanged:()V
      57: goto          69
      60: aload_0
      61: getfield      #31                 // Field writeNumBuilder_:Lcom/google/protobuf/SingleFieldBuilder;
      64: aload_1
      65: invokevirtual #98                 // Method com/google/protobuf/SingleFieldBuilder.mergeFrom:(Lcom/google/protobuf/GeneratedMessage;)Lcom/google/protobuf/SingleFieldBuilder;
      68: pop
      69: aload_0
      70: dup
      71: getfield      #29                 // Field bitField0_:I
      74: iconst_4
      75: ior
      76: putfield      #29                 // Field bitField0_:I
      79: aload_0
      80: areturn

  public org.apache.hadoop.hbase.protobuf.generated.QuotaProtos$Throttle$Builder clearWriteNum();
    Code:
       0: aload_0
       1: getfield      #31                 // Field writeNumBuilder_:Lcom/google/protobuf/SingleFieldBuilder;
       4: ifnonnull     21
       7: aload_0
       8: invokestatic  #9                  // Method org/apache/hadoop/hbase/protobuf/generated/QuotaProtos$TimedQuota.getDefaultInstance:()Lorg/apache/hadoop/hbase/protobuf/generated/QuotaProtos$TimedQuota;
      11: putfield      #12                 // Field writeNum_:Lorg/apache/hadoop/hbase/protobuf/generated/QuotaProtos$TimedQuota;
      14: aload_0
      15: invokevirtual #92                 // Method onChanged:()V
      18: goto          29
      21: aload_0
      22: getfield      #31                 // Field writeNumBuilder_:Lcom/google/protobuf/SingleFieldBuilder;
      25: invokevirtual #28                 // Method com/google/protobuf/SingleFieldBuilder.clear:()Lcom/google/protobuf/SingleFieldBuilder;
      28: pop
      29: aload_0
      30: aload_0
      31: getfield      #29                 // Field bitField0_:I
      34: bipush        -5
      36: iand
      37: putfield      #29                 // Field bitField0_:I
      40: aload_0
      41: areturn

  public org.apache.hadoop.hbase.protobuf.generated.QuotaProtos$TimedQuota$Builder getWriteNumBuilder();
    Code:
       0: aload_0
       1: dup
       2: getfield      #29                 // Field bitField0_:I
       5: iconst_4
       6: ior
       7: putfield      #29                 // Field bitField0_:I
      10: aload_0
      11: invokevirtual #92                 // Method onChanged:()V
      14: aload_0
      15: invokespecial #21                 // Method getWriteNumFieldBuilder:()Lcom/google/protobuf/SingleFieldBuilder;
      18: invokevirtual #99                 // Method com/google/protobuf/SingleFieldBuilder.getBuilder:()Lcom/google/protobuf/GeneratedMessage$Builder;
      21: checkcast     #100                // class org/apache/hadoop/hbase/protobuf/generated/QuotaProtos$TimedQuota$Builder
      24: areturn

  public org.apache.hadoop.hbase.protobuf.generated.QuotaProtos$TimedQuotaOrBuilder getWriteNumOrBuilder();
    Code:
       0: aload_0
       1: getfield      #31                 // Field writeNumBuilder_:Lcom/google/protobuf/SingleFieldBuilder;
       4: ifnull        18
       7: aload_0
       8: getfield      #31                 // Field writeNumBuilder_:Lcom/google/protobuf/SingleFieldBuilder;
      11: invokevirtual #101                // Method com/google/protobuf/SingleFieldBuilder.getMessageOrBuilder:()Lcom/google/protobuf/MessageOrBuilder;
      14: checkcast     #102                // class org/apache/hadoop/hbase/protobuf/generated/QuotaProtos$TimedQuotaOrBuilder
      17: areturn
      18: aload_0
      19: getfield      #12                 // Field writeNum_:Lorg/apache/hadoop/hbase/protobuf/generated/QuotaProtos$TimedQuota;
      22: areturn

  public boolean hasWriteSize();
    Code:
       0: aload_0
       1: getfield      #29                 // Field bitField0_:I
       4: bipush        8
       6: iand
       7: bipush        8
       9: if_icmpne     16
      12: iconst_1
      13: goto          17
      16: iconst_0
      17: ireturn

  public org.apache.hadoop.hbase.protobuf.generated.QuotaProtos$TimedQuota getWriteSize();
    Code:
       0: aload_0
       1: getfield      #32                 // Field writeSizeBuilder_:Lcom/google/protobuf/SingleFieldBuilder;
       4: ifnonnull     12
       7: aload_0
       8: getfield      #13                 // Field writeSize_:Lorg/apache/hadoop/hbase/protobuf/generated/QuotaProtos$TimedQuota;
      11: areturn
      12: aload_0
      13: getfield      #32                 // Field writeSizeBuilder_:Lcom/google/protobuf/SingleFieldBuilder;
      16: invokevirtual #89                 // Method com/google/protobuf/SingleFieldBuilder.getMessage:()Lcom/google/protobuf/GeneratedMessage;
      19: checkcast     #43                 // class org/apache/hadoop/hbase/protobuf/generated/QuotaProtos$TimedQuota
      22: areturn

  public org.apache.hadoop.hbase.protobuf.generated.QuotaProtos$Throttle$Builder setWriteSize(org.apache.hadoop.hbase.protobuf.generated.QuotaProtos$TimedQuota);
    Code:
       0: aload_0
       1: getfield      #32                 // Field writeSizeBuilder_:Lcom/google/protobuf/SingleFieldBuilder;
       4: ifnonnull     31
       7: aload_1
       8: ifnonnull     19
      11: new           #90                 // class java/lang/NullPointerException
      14: dup
      15: invokespecial #91                 // Method java/lang/NullPointerException."<init>":()V
      18: athrow
      19: aload_0
      20: aload_1
      21: putfield      #13                 // Field writeSize_:Lorg/apache/hadoop/hbase/protobuf/generated/QuotaProtos$TimedQuota;
      24: aload_0
      25: invokevirtual #92                 // Method onChanged:()V
      28: goto          40
      31: aload_0
      32: getfield      #32                 // Field writeSizeBuilder_:Lcom/google/protobuf/SingleFieldBuilder;
      35: aload_1
      36: invokevirtual #93                 // Method com/google/protobuf/SingleFieldBuilder.setMessage:(Lcom/google/protobuf/GeneratedMessage;)Lcom/google/protobuf/SingleFieldBuilder;
      39: pop
      40: aload_0
      41: dup
      42: getfield      #29                 // Field bitField0_:I
      45: bipush        8
      47: ior
      48: putfield      #29                 // Field bitField0_:I
      51: aload_0
      52: areturn

  public org.apache.hadoop.hbase.protobuf.generated.QuotaProtos$Throttle$Builder setWriteSize(org.apache.hadoop.hbase.protobuf.generated.QuotaProtos$TimedQuota$Builder);
    Code:
       0: aload_0
       1: getfield      #32                 // Field writeSizeBuilder_:Lcom/google/protobuf/SingleFieldBuilder;
       4: ifnonnull     22
       7: aload_0
       8: aload_1
       9: invokevirtual #94                 // Method org/apache/hadoop/hbase/protobuf/generated/QuotaProtos$TimedQuota$Builder.build:()Lorg/apache/hadoop/hbase/protobuf/generated/QuotaProtos$TimedQuota;
      12: putfield      #13                 // Field writeSize_:Lorg/apache/hadoop/hbase/protobuf/generated/QuotaProtos$TimedQuota;
      15: aload_0
      16: invokevirtual #92                 // Method onChanged:()V
      19: goto          34
      22: aload_0
      23: getfield      #32                 // Field writeSizeBuilder_:Lcom/google/protobuf/SingleFieldBuilder;
      26: aload_1
      27: invokevirtual #94                 // Method org/apache/hadoop/hbase/protobuf/generated/QuotaProtos$TimedQuota$Builder.build:()Lorg/apache/hadoop/hbase/protobuf/generated/QuotaProtos$TimedQuota;
      30: invokevirtual #93                 // Method com/google/protobuf/SingleFieldBuilder.setMessage:(Lcom/google/protobuf/GeneratedMessage;)Lcom/google/protobuf/SingleFieldBuilder;
      33: pop
      34: aload_0
      35: dup
      36: getfield      #29                 // Field bitField0_:I
      39: bipush        8
      41: ior
      42: putfield      #29                 // Field bitField0_:I
      45: aload_0
      46: areturn

  public org.apache.hadoop.hbase.protobuf.generated.QuotaProtos$Throttle$Builder mergeWriteSize(org.apache.hadoop.hbase.protobuf.generated.QuotaProtos$TimedQuota);
    Code:
       0: aload_0
       1: getfield      #32                 // Field writeSizeBuilder_:Lcom/google/protobuf/SingleFieldBuilder;
       4: ifnonnull     62
       7: aload_0
       8: getfield      #29                 // Field bitField0_:I
      11: bipush        8
      13: iand
      14: bipush        8
      16: if_icmpne     50
      19: aload_0
      20: getfield      #13                 // Field writeSize_:Lorg/apache/hadoop/hbase/protobuf/generated/QuotaProtos$TimedQuota;
      23: invokestatic  #9                  // Method org/apache/hadoop/hbase/protobuf/generated/QuotaProtos$TimedQuota.getDefaultInstance:()Lorg/apache/hadoop/hbase/protobuf/generated/QuotaProtos$TimedQuota;
      26: if_acmpeq     50
      29: aload_0
      30: aload_0
      31: getfield      #13                 // Field writeSize_:Lorg/apache/hadoop/hbase/protobuf/generated/QuotaProtos$TimedQuota;
      34: invokestatic  #95                 // Method org/apache/hadoop/hbase/protobuf/generated/QuotaProtos$TimedQuota.newBuilder:(Lorg/apache/hadoop/hbase/protobuf/generated/QuotaProtos$TimedQuota;)Lorg/apache/hadoop/hbase/protobuf/generated/QuotaProtos$TimedQuota$Builder;
      37: aload_1
      38: invokevirtual #96                 // Method org/apache/hadoop/hbase/protobuf/generated/QuotaProtos$TimedQuota$Builder.mergeFrom:(Lorg/apache/hadoop/hbase/protobuf/generated/QuotaProtos$TimedQuota;)Lorg/apache/hadoop/hbase/protobuf/generated/QuotaProtos$TimedQuota$Builder;
      41: invokevirtual #97                 // Method org/apache/hadoop/hbase/protobuf/generated/QuotaProtos$TimedQuota$Builder.buildPartial:()Lorg/apache/hadoop/hbase/protobuf/generated/QuotaProtos$TimedQuota;
      44: putfield      #13                 // Field writeSize_:Lorg/apache/hadoop/hbase/protobuf/generated/QuotaProtos$TimedQuota;
      47: goto          55
      50: aload_0
      51: aload_1
      52: putfield      #13                 // Field writeSize_:Lorg/apache/hadoop/hbase/protobuf/generated/QuotaProtos$TimedQuota;
      55: aload_0
      56: invokevirtual #92                 // Method onChanged:()V
      59: goto          71
      62: aload_0
      63: getfield      #32                 // Field writeSizeBuilder_:Lcom/google/protobuf/SingleFieldBuilder;
      66: aload_1
      67: invokevirtual #98                 // Method com/google/protobuf/SingleFieldBuilder.mergeFrom:(Lcom/google/protobuf/GeneratedMessage;)Lcom/google/protobuf/SingleFieldBuilder;
      70: pop
      71: aload_0
      72: dup
      73: getfield      #29                 // Field bitField0_:I
      76: bipush        8
      78: ior
      79: putfield      #29                 // Field bitField0_:I
      82: aload_0
      83: areturn

  public org.apache.hadoop.hbase.protobuf.generated.QuotaProtos$Throttle$Builder clearWriteSize();
    Code:
       0: aload_0
       1: getfield      #32                 // Field writeSizeBuilder_:Lcom/google/protobuf/SingleFieldBuilder;
       4: ifnonnull     21
       7: aload_0
       8: invokestatic  #9                  // Method org/apache/hadoop/hbase/protobuf/generated/QuotaProtos$TimedQuota.getDefaultInstance:()Lorg/apache/hadoop/hbase/protobuf/generated/QuotaProtos$TimedQuota;
      11: putfield      #13                 // Field writeSize_:Lorg/apache/hadoop/hbase/protobuf/generated/QuotaProtos$TimedQuota;
      14: aload_0
      15: invokevirtual #92                 // Method onChanged:()V
      18: goto          29
      21: aload_0
      22: getfield      #32                 // Field writeSizeBuilder_:Lcom/google/protobuf/SingleFieldBuilder;
      25: invokevirtual #28                 // Method com/google/protobuf/SingleFieldBuilder.clear:()Lcom/google/protobuf/SingleFieldBuilder;
      28: pop
      29: aload_0
      30: aload_0
      31: getfield      #29                 // Field bitField0_:I
      34: bipush        -9
      36: iand
      37: putfield      #29                 // Field bitField0_:I
      40: aload_0
      41: areturn

  public org.apache.hadoop.hbase.protobuf.generated.QuotaProtos$TimedQuota$Builder getWriteSizeBuilder();
    Code:
       0: aload_0
       1: dup
       2: getfield      #29                 // Field bitField0_:I
       5: bipush        8
       7: ior
       8: putfield      #29                 // Field bitField0_:I
      11: aload_0
      12: invokevirtual #92                 // Method onChanged:()V
      15: aload_0
      16: invokespecial #22                 // Method getWriteSizeFieldBuilder:()Lcom/google/protobuf/SingleFieldBuilder;
      19: invokevirtual #99                 // Method com/google/protobuf/SingleFieldBuilder.getBuilder:()Lcom/google/protobuf/GeneratedMessage$Builder;
      22: checkcast     #100                // class org/apache/hadoop/hbase/protobuf/generated/QuotaProtos$TimedQuota$Builder
      25: areturn

  public org.apache.hadoop.hbase.protobuf.generated.QuotaProtos$TimedQuotaOrBuilder getWriteSizeOrBuilder();
    Code:
       0: aload_0
       1: getfield      #32                 // Field writeSizeBuilder_:Lcom/google/protobuf/SingleFieldBuilder;
       4: ifnull        18
       7: aload_0
       8: getfield      #32                 // Field writeSizeBuilder_:Lcom/google/protobuf/SingleFieldBuilder;
      11: invokevirtual #101                // Method com/google/protobuf/SingleFieldBuilder.getMessageOrBuilder:()Lcom/google/protobuf/MessageOrBuilder;
      14: checkcast     #102                // class org/apache/hadoop/hbase/protobuf/generated/QuotaProtos$TimedQuotaOrBuilder
      17: areturn
      18: aload_0
      19: getfield      #13                 // Field writeSize_:Lorg/apache/hadoop/hbase/protobuf/generated/QuotaProtos$TimedQuota;
      22: areturn

  public boolean hasReadNum();
    Code:
       0: aload_0
       1: getfield      #29                 // Field bitField0_:I
       4: bipush        16
       6: iand
       7: bipush        16
       9: if_icmpne     16
      12: iconst_1
      13: goto          17
      16: iconst_0
      17: ireturn

  public org.apache.hadoop.hbase.protobuf.generated.QuotaProtos$TimedQuota getReadNum();
    Code:
       0: aload_0
       1: getfield      #33                 // Field readNumBuilder_:Lcom/google/protobuf/SingleFieldBuilder;
       4: ifnonnull     12
       7: aload_0
       8: getfield      #14                 // Field readNum_:Lorg/apache/hadoop/hbase/protobuf/generated/QuotaProtos$TimedQuota;
      11: areturn
      12: aload_0
      13: getfield      #33                 // Field readNumBuilder_:Lcom/google/protobuf/SingleFieldBuilder;
      16: invokevirtual #89                 // Method com/google/protobuf/SingleFieldBuilder.getMessage:()Lcom/google/protobuf/GeneratedMessage;
      19: checkcast     #43                 // class org/apache/hadoop/hbase/protobuf/generated/QuotaProtos$TimedQuota
      22: areturn

  public org.apache.hadoop.hbase.protobuf.generated.QuotaProtos$Throttle$Builder setReadNum(org.apache.hadoop.hbase.protobuf.generated.QuotaProtos$TimedQuota);
    Code:
       0: aload_0
       1: getfield      #33                 // Field readNumBuilder_:Lcom/google/protobuf/SingleFieldBuilder;
       4: ifnonnull     31
       7: aload_1
       8: ifnonnull     19
      11: new           #90                 // class java/lang/NullPointerException
      14: dup
      15: invokespecial #91                 // Method java/lang/NullPointerException."<init>":()V
      18: athrow
      19: aload_0
      20: aload_1
      21: putfield      #14                 // Field readNum_:Lorg/apache/hadoop/hbase/protobuf/generated/QuotaProtos$TimedQuota;
      24: aload_0
      25: invokevirtual #92                 // Method onChanged:()V
      28: goto          40
      31: aload_0
      32: getfield      #33                 // Field readNumBuilder_:Lcom/google/protobuf/SingleFieldBuilder;
      35: aload_1
      36: invokevirtual #93                 // Method com/google/protobuf/SingleFieldBuilder.setMessage:(Lcom/google/protobuf/GeneratedMessage;)Lcom/google/protobuf/SingleFieldBuilder;
      39: pop
      40: aload_0
      41: dup
      42: getfield      #29                 // Field bitField0_:I
      45: bipush        16
      47: ior
      48: putfield      #29                 // Field bitField0_:I
      51: aload_0
      52: areturn

  public org.apache.hadoop.hbase.protobuf.generated.QuotaProtos$Throttle$Builder setReadNum(org.apache.hadoop.hbase.protobuf.generated.QuotaProtos$TimedQuota$Builder);
    Code:
       0: aload_0
       1: getfield      #33                 // Field readNumBuilder_:Lcom/google/protobuf/SingleFieldBuilder;
       4: ifnonnull     22
       7: aload_0
       8: aload_1
       9: invokevirtual #94                 // Method org/apache/hadoop/hbase/protobuf/generated/QuotaProtos$TimedQuota$Builder.build:()Lorg/apache/hadoop/hbase/protobuf/generated/QuotaProtos$TimedQuota;
      12: putfield      #14                 // Field readNum_:Lorg/apache/hadoop/hbase/protobuf/generated/QuotaProtos$TimedQuota;
      15: aload_0
      16: invokevirtual #92                 // Method onChanged:()V
      19: goto          34
      22: aload_0
      23: getfield      #33                 // Field readNumBuilder_:Lcom/google/protobuf/SingleFieldBuilder;
      26: aload_1
      27: invokevirtual #94                 // Method org/apache/hadoop/hbase/protobuf/generated/QuotaProtos$TimedQuota$Builder.build:()Lorg/apache/hadoop/hbase/protobuf/generated/QuotaProtos$TimedQuota;
      30: invokevirtual #93                 // Method com/google/protobuf/SingleFieldBuilder.setMessage:(Lcom/google/protobuf/GeneratedMessage;)Lcom/google/protobuf/SingleFieldBuilder;
      33: pop
      34: aload_0
      35: dup
      36: getfield      #29                 // Field bitField0_:I
      39: bipush        16
      41: ior
      42: putfield      #29                 // Field bitField0_:I
      45: aload_0
      46: areturn

  public org.apache.hadoop.hbase.protobuf.generated.QuotaProtos$Throttle$Builder mergeReadNum(org.apache.hadoop.hbase.protobuf.generated.QuotaProtos$TimedQuota);
    Code:
       0: aload_0
       1: getfield      #33                 // Field readNumBuilder_:Lcom/google/protobuf/SingleFieldBuilder;
       4: ifnonnull     62
       7: aload_0
       8: getfield      #29                 // Field bitField0_:I
      11: bipush        16
      13: iand
      14: bipush        16
      16: if_icmpne     50
      19: aload_0
      20: getfield      #14                 // Field readNum_:Lorg/apache/hadoop/hbase/protobuf/generated/QuotaProtos$TimedQuota;
      23: invokestatic  #9                  // Method org/apache/hadoop/hbase/protobuf/generated/QuotaProtos$TimedQuota.getDefaultInstance:()Lorg/apache/hadoop/hbase/protobuf/generated/QuotaProtos$TimedQuota;
      26: if_acmpeq     50
      29: aload_0
      30: aload_0
      31: getfield      #14                 // Field readNum_:Lorg/apache/hadoop/hbase/protobuf/generated/QuotaProtos$TimedQuota;
      34: invokestatic  #95                 // Method org/apache/hadoop/hbase/protobuf/generated/QuotaProtos$TimedQuota.newBuilder:(Lorg/apache/hadoop/hbase/protobuf/generated/QuotaProtos$TimedQuota;)Lorg/apache/hadoop/hbase/protobuf/generated/QuotaProtos$TimedQuota$Builder;
      37: aload_1
      38: invokevirtual #96                 // Method org/apache/hadoop/hbase/protobuf/generated/QuotaProtos$TimedQuota$Builder.mergeFrom:(Lorg/apache/hadoop/hbase/protobuf/generated/QuotaProtos$TimedQuota;)Lorg/apache/hadoop/hbase/protobuf/generated/QuotaProtos$TimedQuota$Builder;
      41: invokevirtual #97                 // Method org/apache/hadoop/hbase/protobuf/generated/QuotaProtos$TimedQuota$Builder.buildPartial:()Lorg/apache/hadoop/hbase/protobuf/generated/QuotaProtos$TimedQuota;
      44: putfield      #14                 // Field readNum_:Lorg/apache/hadoop/hbase/protobuf/generated/QuotaProtos$TimedQuota;
      47: goto          55
      50: aload_0
      51: aload_1
      52: putfield      #14                 // Field readNum_:Lorg/apache/hadoop/hbase/protobuf/generated/QuotaProtos$TimedQuota;
      55: aload_0
      56: invokevirtual #92                 // Method onChanged:()V
      59: goto          71
      62: aload_0
      63: getfield      #33                 // Field readNumBuilder_:Lcom/google/protobuf/SingleFieldBuilder;
      66: aload_1
      67: invokevirtual #98                 // Method com/google/protobuf/SingleFieldBuilder.mergeFrom:(Lcom/google/protobuf/GeneratedMessage;)Lcom/google/protobuf/SingleFieldBuilder;
      70: pop
      71: aload_0
      72: dup
      73: getfield      #29                 // Field bitField0_:I
      76: bipush        16
      78: ior
      79: putfield      #29                 // Field bitField0_:I
      82: aload_0
      83: areturn

  public org.apache.hadoop.hbase.protobuf.generated.QuotaProtos$Throttle$Builder clearReadNum();
    Code:
       0: aload_0
       1: getfield      #33                 // Field readNumBuilder_:Lcom/google/protobuf/SingleFieldBuilder;
       4: ifnonnull     21
       7: aload_0
       8: invokestatic  #9                  // Method org/apache/hadoop/hbase/protobuf/generated/QuotaProtos$TimedQuota.getDefaultInstance:()Lorg/apache/hadoop/hbase/protobuf/generated/QuotaProtos$TimedQuota;
      11: putfield      #14                 // Field readNum_:Lorg/apache/hadoop/hbase/protobuf/generated/QuotaProtos$TimedQuota;
      14: aload_0
      15: invokevirtual #92                 // Method onChanged:()V
      18: goto          29
      21: aload_0
      22: getfield      #33                 // Field readNumBuilder_:Lcom/google/protobuf/SingleFieldBuilder;
      25: invokevirtual #28                 // Method com/google/protobuf/SingleFieldBuilder.clear:()Lcom/google/protobuf/SingleFieldBuilder;
      28: pop
      29: aload_0
      30: aload_0
      31: getfield      #29                 // Field bitField0_:I
      34: bipush        -17
      36: iand
      37: putfield      #29                 // Field bitField0_:I
      40: aload_0
      41: areturn

  public org.apache.hadoop.hbase.protobuf.generated.QuotaProtos$TimedQuota$Builder getReadNumBuilder();
    Code:
       0: aload_0
       1: dup
       2: getfield      #29                 // Field bitField0_:I
       5: bipush        16
       7: ior
       8: putfield      #29                 // Field bitField0_:I
      11: aload_0
      12: invokevirtual #92                 // Method onChanged:()V
      15: aload_0
      16: invokespecial #23                 // Method getReadNumFieldBuilder:()Lcom/google/protobuf/SingleFieldBuilder;
      19: invokevirtual #99                 // Method com/google/protobuf/SingleFieldBuilder.getBuilder:()Lcom/google/protobuf/GeneratedMessage$Builder;
      22: checkcast     #100                // class org/apache/hadoop/hbase/protobuf/generated/QuotaProtos$TimedQuota$Builder
      25: areturn

  public org.apache.hadoop.hbase.protobuf.generated.QuotaProtos$TimedQuotaOrBuilder getReadNumOrBuilder();
    Code:
       0: aload_0
       1: getfield      #33                 // Field readNumBuilder_:Lcom/google/protobuf/SingleFieldBuilder;
       4: ifnull        18
       7: aload_0
       8: getfield      #33                 // Field readNumBuilder_:Lcom/google/protobuf/SingleFieldBuilder;
      11: invokevirtual #101                // Method com/google/protobuf/SingleFieldBuilder.getMessageOrBuilder:()Lcom/google/protobuf/MessageOrBuilder;
      14: checkcast     #102                // class org/apache/hadoop/hbase/protobuf/generated/QuotaProtos$TimedQuotaOrBuilder
      17: areturn
      18: aload_0
      19: getfield      #14                 // Field readNum_:Lorg/apache/hadoop/hbase/protobuf/generated/QuotaProtos$TimedQuota;
      22: areturn

  public boolean hasReadSize();
    Code:
       0: aload_0
       1: getfield      #29                 // Field bitField0_:I
       4: bipush        32
       6: iand
       7: bipush        32
       9: if_icmpne     16
      12: iconst_1
      13: goto          17
      16: iconst_0
      17: ireturn

  public org.apache.hadoop.hbase.protobuf.generated.QuotaProtos$TimedQuota getReadSize();
    Code:
       0: aload_0
       1: getfield      #34                 // Field readSizeBuilder_:Lcom/google/protobuf/SingleFieldBuilder;
       4: ifnonnull     12
       7: aload_0
       8: getfield      #15                 // Field readSize_:Lorg/apache/hadoop/hbase/protobuf/generated/QuotaProtos$TimedQuota;
      11: areturn
      12: aload_0
      13: getfield      #34                 // Field readSizeBuilder_:Lcom/google/protobuf/SingleFieldBuilder;
      16: invokevirtual #89                 // Method com/google/protobuf/SingleFieldBuilder.getMessage:()Lcom/google/protobuf/GeneratedMessage;
      19: checkcast     #43                 // class org/apache/hadoop/hbase/protobuf/generated/QuotaProtos$TimedQuota
      22: areturn

  public org.apache.hadoop.hbase.protobuf.generated.QuotaProtos$Throttle$Builder setReadSize(org.apache.hadoop.hbase.protobuf.generated.QuotaProtos$TimedQuota);
    Code:
       0: aload_0
       1: getfield      #34                 // Field readSizeBuilder_:Lcom/google/protobuf/SingleFieldBuilder;
       4: ifnonnull     31
       7: aload_1
       8: ifnonnull     19
      11: new           #90                 // class java/lang/NullPointerException
      14: dup
      15: invokespecial #91                 // Method java/lang/NullPointerException."<init>":()V
      18: athrow
      19: aload_0
      20: aload_1
      21: putfield      #15                 // Field readSize_:Lorg/apache/hadoop/hbase/protobuf/generated/QuotaProtos$TimedQuota;
      24: aload_0
      25: invokevirtual #92                 // Method onChanged:()V
      28: goto          40
      31: aload_0
      32: getfield      #34                 // Field readSizeBuilder_:Lcom/google/protobuf/SingleFieldBuilder;
      35: aload_1
      36: invokevirtual #93                 // Method com/google/protobuf/SingleFieldBuilder.setMessage:(Lcom/google/protobuf/GeneratedMessage;)Lcom/google/protobuf/SingleFieldBuilder;
      39: pop
      40: aload_0
      41: dup
      42: getfield      #29                 // Field bitField0_:I
      45: bipush        32
      47: ior
      48: putfield      #29                 // Field bitField0_:I
      51: aload_0
      52: areturn

  public org.apache.hadoop.hbase.protobuf.generated.QuotaProtos$Throttle$Builder setReadSize(org.apache.hadoop.hbase.protobuf.generated.QuotaProtos$TimedQuota$Builder);
    Code:
       0: aload_0
       1: getfield      #34                 // Field readSizeBuilder_:Lcom/google/protobuf/SingleFieldBuilder;
       4: ifnonnull     22
       7: aload_0
       8: aload_1
       9: invokevirtual #94                 // Method org/apache/hadoop/hbase/protobuf/generated/QuotaProtos$TimedQuota$Builder.build:()Lorg/apache/hadoop/hbase/protobuf/generated/QuotaProtos$TimedQuota;
      12: putfield      #15                 // Field readSize_:Lorg/apache/hadoop/hbase/protobuf/generated/QuotaProtos$TimedQuota;
      15: aload_0
      16: invokevirtual #92                 // Method onChanged:()V
      19: goto          34
      22: aload_0
      23: getfield      #34                 // Field readSizeBuilder_:Lcom/google/protobuf/SingleFieldBuilder;
      26: aload_1
      27: invokevirtual #94                 // Method org/apache/hadoop/hbase/protobuf/generated/QuotaProtos$TimedQuota$Builder.build:()Lorg/apache/hadoop/hbase/protobuf/generated/QuotaProtos$TimedQuota;
      30: invokevirtual #93                 // Method com/google/protobuf/SingleFieldBuilder.setMessage:(Lcom/google/protobuf/GeneratedMessage;)Lcom/google/protobuf/SingleFieldBuilder;
      33: pop
      34: aload_0
      35: dup
      36: getfield      #29                 // Field bitField0_:I
      39: bipush        32
      41: ior
      42: putfield      #29                 // Field bitField0_:I
      45: aload_0
      46: areturn

  public org.apache.hadoop.hbase.protobuf.generated.QuotaProtos$Throttle$Builder mergeReadSize(org.apache.hadoop.hbase.protobuf.generated.QuotaProtos$TimedQuota);
    Code:
       0: aload_0
       1: getfield      #34                 // Field readSizeBuilder_:Lcom/google/protobuf/SingleFieldBuilder;
       4: ifnonnull     62
       7: aload_0
       8: getfield      #29                 // Field bitField0_:I
      11: bipush        32
      13: iand
      14: bipush        32
      16: if_icmpne     50
      19: aload_0
      20: getfield      #15                 // Field readSize_:Lorg/apache/hadoop/hbase/protobuf/generated/QuotaProtos$TimedQuota;
      23: invokestatic  #9                  // Method org/apache/hadoop/hbase/protobuf/generated/QuotaProtos$TimedQuota.getDefaultInstance:()Lorg/apache/hadoop/hbase/protobuf/generated/QuotaProtos$TimedQuota;
      26: if_acmpeq     50
      29: aload_0
      30: aload_0
      31: getfield      #15                 // Field readSize_:Lorg/apache/hadoop/hbase/protobuf/generated/QuotaProtos$TimedQuota;
      34: invokestatic  #95                 // Method org/apache/hadoop/hbase/protobuf/generated/QuotaProtos$TimedQuota.newBuilder:(Lorg/apache/hadoop/hbase/protobuf/generated/QuotaProtos$TimedQuota;)Lorg/apache/hadoop/hbase/protobuf/generated/QuotaProtos$TimedQuota$Builder;
      37: aload_1
      38: invokevirtual #96                 // Method org/apache/hadoop/hbase/protobuf/generated/QuotaProtos$TimedQuota$Builder.mergeFrom:(Lorg/apache/hadoop/hbase/protobuf/generated/QuotaProtos$TimedQuota;)Lorg/apache/hadoop/hbase/protobuf/generated/QuotaProtos$TimedQuota$Builder;
      41: invokevirtual #97                 // Method org/apache/hadoop/hbase/protobuf/generated/QuotaProtos$TimedQuota$Builder.buildPartial:()Lorg/apache/hadoop/hbase/protobuf/generated/QuotaProtos$TimedQuota;
      44: putfield      #15                 // Field readSize_:Lorg/apache/hadoop/hbase/protobuf/generated/QuotaProtos$TimedQuota;
      47: goto          55
      50: aload_0
      51: aload_1
      52: putfield      #15                 // Field readSize_:Lorg/apache/hadoop/hbase/protobuf/generated/QuotaProtos$TimedQuota;
      55: aload_0
      56: invokevirtual #92                 // Method onChanged:()V
      59: goto          71
      62: aload_0
      63: getfield      #34                 // Field readSizeBuilder_:Lcom/google/protobuf/SingleFieldBuilder;
      66: aload_1
      67: invokevirtual #98                 // Method com/google/protobuf/SingleFieldBuilder.mergeFrom:(Lcom/google/protobuf/GeneratedMessage;)Lcom/google/protobuf/SingleFieldBuilder;
      70: pop
      71: aload_0
      72: dup
      73: getfield      #29                 // Field bitField0_:I
      76: bipush        32
      78: ior
      79: putfield      #29                 // Field bitField0_:I
      82: aload_0
      83: areturn

  public org.apache.hadoop.hbase.protobuf.generated.QuotaProtos$Throttle$Builder clearReadSize();
    Code:
       0: aload_0
       1: getfield      #34                 // Field readSizeBuilder_:Lcom/google/protobuf/SingleFieldBuilder;
       4: ifnonnull     21
       7: aload_0
       8: invokestatic  #9                  // Method org/apache/hadoop/hbase/protobuf/generated/QuotaProtos$TimedQuota.getDefaultInstance:()Lorg/apache/hadoop/hbase/protobuf/generated/QuotaProtos$TimedQuota;
      11: putfield      #15                 // Field readSize_:Lorg/apache/hadoop/hbase/protobuf/generated/QuotaProtos$TimedQuota;
      14: aload_0
      15: invokevirtual #92                 // Method onChanged:()V
      18: goto          29
      21: aload_0
      22: getfield      #34                 // Field readSizeBuilder_:Lcom/google/protobuf/SingleFieldBuilder;
      25: invokevirtual #28                 // Method com/google/protobuf/SingleFieldBuilder.clear:()Lcom/google/protobuf/SingleFieldBuilder;
      28: pop
      29: aload_0
      30: aload_0
      31: getfield      #29                 // Field bitField0_:I
      34: bipush        -33
      36: iand
      37: putfield      #29                 // Field bitField0_:I
      40: aload_0
      41: areturn

  public org.apache.hadoop.hbase.protobuf.generated.QuotaProtos$TimedQuota$Builder getReadSizeBuilder();
    Code:
       0: aload_0
       1: dup
       2: getfield      #29                 // Field bitField0_:I
       5: bipush        32
       7: ior
       8: putfield      #29                 // Field bitField0_:I
      11: aload_0
      12: invokevirtual #92                 // Method onChanged:()V
      15: aload_0
      16: invokespecial #24                 // Method getReadSizeFieldBuilder:()Lcom/google/protobuf/SingleFieldBuilder;
      19: invokevirtual #99                 // Method com/google/protobuf/SingleFieldBuilder.getBuilder:()Lcom/google/protobuf/GeneratedMessage$Builder;
      22: checkcast     #100                // class org/apache/hadoop/hbase/protobuf/generated/QuotaProtos$TimedQuota$Builder
      25: areturn

  public org.apache.hadoop.hbase.protobuf.generated.QuotaProtos$TimedQuotaOrBuilder getReadSizeOrBuilder();
    Code:
       0: aload_0
       1: getfield      #34                 // Field readSizeBuilder_:Lcom/google/protobuf/SingleFieldBuilder;
       4: ifnull        18
       7: aload_0
       8: getfield      #34                 // Field readSizeBuilder_:Lcom/google/protobuf/SingleFieldBuilder;
      11: invokevirtual #101                // Method com/google/protobuf/SingleFieldBuilder.getMessageOrBuilder:()Lcom/google/protobuf/MessageOrBuilder;
      14: checkcast     #102                // class org/apache/hadoop/hbase/protobuf/generated/QuotaProtos$TimedQuotaOrBuilder
      17: areturn
      18: aload_0
      19: getfield      #15                 // Field readSize_:Lorg/apache/hadoop/hbase/protobuf/generated/QuotaProtos$TimedQuota;
      22: areturn

  public com.google.protobuf.GeneratedMessage$Builder clear();
    Code:
       0: aload_0
       1: invokevirtual #107                // Method clear:()Lorg/apache/hadoop/hbase/protobuf/generated/QuotaProtos$Throttle$Builder;
       4: areturn

  public com.google.protobuf.GeneratedMessage$Builder clone();
    Code:
       0: aload_0
       1: invokevirtual #108                // Method clone:()Lorg/apache/hadoop/hbase/protobuf/generated/QuotaProtos$Throttle$Builder;
       4: areturn

  public com.google.protobuf.AbstractMessage$Builder mergeFrom(com.google.protobuf.CodedInputStream, com.google.protobuf.ExtensionRegistryLite) throws java.io.IOException;
    Code:
       0: aload_0
       1: aload_1
       2: aload_2
       3: invokevirtual #109                // Method mergeFrom:(Lcom/google/protobuf/CodedInputStream;Lcom/google/protobuf/ExtensionRegistryLite;)Lorg/apache/hadoop/hbase/protobuf/generated/QuotaProtos$Throttle$Builder;
       6: areturn

  public com.google.protobuf.AbstractMessage$Builder mergeFrom(com.google.protobuf.Message);
    Code:
       0: aload_0
       1: aload_1
       2: invokevirtual #110                // Method mergeFrom:(Lcom/google/protobuf/Message;)Lorg/apache/hadoop/hbase/protobuf/generated/QuotaProtos$Throttle$Builder;
       5: areturn

  public com.google.protobuf.AbstractMessage$Builder clear();
    Code:
       0: aload_0
       1: invokevirtual #107                // Method clear:()Lorg/apache/hadoop/hbase/protobuf/generated/QuotaProtos$Throttle$Builder;
       4: areturn

  public com.google.protobuf.AbstractMessage$Builder clone();
    Code:
       0: aload_0
       1: invokevirtual #108                // Method clone:()Lorg/apache/hadoop/hbase/protobuf/generated/QuotaProtos$Throttle$Builder;
       4: areturn

  public com.google.protobuf.Message$Builder mergeFrom(com.google.protobuf.CodedInputStream, com.google.protobuf.ExtensionRegistryLite) throws java.io.IOException;
    Code:
       0: aload_0
       1: aload_1
       2: aload_2
       3: invokevirtual #109                // Method mergeFrom:(Lcom/google/protobuf/CodedInputStream;Lcom/google/protobuf/ExtensionRegistryLite;)Lorg/apache/hadoop/hbase/protobuf/generated/QuotaProtos$Throttle$Builder;
       6: areturn

  public com.google.protobuf.Message$Builder clone();
    Code:
       0: aload_0
       1: invokevirtual #108                // Method clone:()Lorg/apache/hadoop/hbase/protobuf/generated/QuotaProtos$Throttle$Builder;
       4: areturn

  public com.google.protobuf.Message buildPartial();
    Code:
       0: aload_0
       1: invokevirtual #35                 // Method buildPartial:()Lorg/apache/hadoop/hbase/protobuf/generated/QuotaProtos$Throttle;
       4: areturn

  public com.google.protobuf.Message build();
    Code:
       0: aload_0
       1: invokevirtual #111                // Method build:()Lorg/apache/hadoop/hbase/protobuf/generated/QuotaProtos$Throttle;
       4: areturn

  public com.google.protobuf.Message$Builder mergeFrom(com.google.protobuf.Message);
    Code:
       0: aload_0
       1: aload_1
       2: invokevirtual #110                // Method mergeFrom:(Lcom/google/protobuf/Message;)Lorg/apache/hadoop/hbase/protobuf/generated/QuotaProtos$Throttle$Builder;
       5: areturn

  public com.google.protobuf.Message$Builder clear();
    Code:
       0: aload_0
       1: invokevirtual #107                // Method clear:()Lorg/apache/hadoop/hbase/protobuf/generated/QuotaProtos$Throttle$Builder;
       4: areturn

  public com.google.protobuf.MessageLite$Builder mergeFrom(com.google.protobuf.CodedInputStream, com.google.protobuf.ExtensionRegistryLite) throws java.io.IOException;
    Code:
       0: aload_0
       1: aload_1
       2: aload_2
       3: invokevirtual #109                // Method mergeFrom:(Lcom/google/protobuf/CodedInputStream;Lcom/google/protobuf/ExtensionRegistryLite;)Lorg/apache/hadoop/hbase/protobuf/generated/QuotaProtos$Throttle$Builder;
       6: areturn

  public com.google.protobuf.MessageLite$Builder clone();
    Code:
       0: aload_0
       1: invokevirtual #108                // Method clone:()Lorg/apache/hadoop/hbase/protobuf/generated/QuotaProtos$Throttle$Builder;
       4: areturn

  public com.google.protobuf.MessageLite buildPartial();
    Code:
       0: aload_0
       1: invokevirtual #35                 // Method buildPartial:()Lorg/apache/hadoop/hbase/protobuf/generated/QuotaProtos$Throttle;
       4: areturn

  public com.google.protobuf.MessageLite build();
    Code:
       0: aload_0
       1: invokevirtual #111                // Method build:()Lorg/apache/hadoop/hbase/protobuf/generated/QuotaProtos$Throttle;
       4: areturn

  public com.google.protobuf.MessageLite$Builder clear();
    Code:
       0: aload_0
       1: invokevirtual #107                // Method clear:()Lorg/apache/hadoop/hbase/protobuf/generated/QuotaProtos$Throttle$Builder;
       4: areturn

  public com.google.protobuf.MessageLite getDefaultInstanceForType();
    Code:
       0: aload_0
       1: invokevirtual #112                // Method getDefaultInstanceForType:()Lorg/apache/hadoop/hbase/protobuf/generated/QuotaProtos$Throttle;
       4: areturn

  public com.google.protobuf.Message getDefaultInstanceForType();
    Code:
       0: aload_0
       1: invokevirtual #112                // Method getDefaultInstanceForType:()Lorg/apache/hadoop/hbase/protobuf/generated/QuotaProtos$Throttle;
       4: areturn

  public com.google.protobuf.AbstractMessageLite$Builder mergeFrom(com.google.protobuf.CodedInputStream, com.google.protobuf.ExtensionRegistryLite) throws java.io.IOException;
    Code:
       0: aload_0
       1: aload_1
       2: aload_2
       3: invokevirtual #109                // Method mergeFrom:(Lcom/google/protobuf/CodedInputStream;Lcom/google/protobuf/ExtensionRegistryLite;)Lorg/apache/hadoop/hbase/protobuf/generated/QuotaProtos$Throttle$Builder;
       6: areturn

  public com.google.protobuf.AbstractMessageLite$Builder clone();
    Code:
       0: aload_0
       1: invokevirtual #108                // Method clone:()Lorg/apache/hadoop/hbase/protobuf/generated/QuotaProtos$Throttle$Builder;
       4: areturn

  public java.lang.Object clone() throws java.lang.CloneNotSupportedException;
    Code:
       0: aload_0
       1: invokevirtual #108                // Method clone:()Lorg/apache/hadoop/hbase/protobuf/generated/QuotaProtos$Throttle$Builder;
       4: areturn

  static org.apache.hadoop.hbase.protobuf.generated.QuotaProtos$Throttle$Builder access$1500();
    Code:
       0: invokestatic  #2                  // Method create:()Lorg/apache/hadoop/hbase/protobuf/generated/QuotaProtos$Throttle$Builder;
       3: areturn

  org.apache.hadoop.hbase.protobuf.generated.QuotaProtos$Throttle$Builder(com.google.protobuf.GeneratedMessage$BuilderParent, org.apache.hadoop.hbase.protobuf.generated.QuotaProtos$1);
    Code:
       0: aload_0
       1: aload_1
       2: invokespecial #1                  // Method "<init>":(Lcom/google/protobuf/GeneratedMessage$BuilderParent;)V
       5: return
}
