Compiled from "RandomDistribution.java"
public final class org.apache.hadoop.hbase.io.hfile.RandomDistribution$Flat implements org.apache.hadoop.hbase.io.hfile.RandomDistribution$DiscreteRNG {
  public org.apache.hadoop.hbase.io.hfile.RandomDistribution$Flat(java.util.Random, int, int);
    Code:
       0: aload_0
       1: invokespecial #1                  // Method java/lang/Object."<init>":()V
       4: iload_2
       5: iload_3
       6: if_icmplt     19
       9: new           #2                  // class java/lang/IllegalArgumentException
      12: dup
      13: ldc           #3                  // String Invalid range
      15: invokespecial #4                  // Method java/lang/IllegalArgumentException."<init>":(Ljava/lang/String;)V
      18: athrow
      19: aload_0
      20: aload_1
      21: putfield      #5                  // Field random:Ljava/util/Random;
      24: aload_0
      25: iload_2
      26: putfield      #6                  // Field min:I
      29: aload_0
      30: iload_3
      31: putfield      #7                  // Field max:I
      34: return

  public int nextInt();
    Code:
       0: aload_0
       1: getfield      #5                  // Field random:Ljava/util/Random;
       4: aload_0
       5: getfield      #7                  // Field max:I
       8: aload_0
       9: getfield      #6                  // Field min:I
      12: isub
      13: invokevirtual #8                  // Method java/util/Random.nextInt:(I)I
      16: aload_0
      17: getfield      #6                  // Field min:I
      20: iadd
      21: ireturn
}
