Compiled from "RawAsyncTableImpl.java"
class org.apache.hadoop.hbase.client.RawAsyncTableImpl$2 implements org.apache.hbase.thirdparty.com.google.protobuf.RpcCallback<org.apache.hadoop.hbase.shaded.protobuf.generated.ClientProtos$MultiResponse> {
  final org.apache.hadoop.hbase.ipc.HBaseRpcController val$controller;

  final java.util.concurrent.CompletableFuture val$future;

  final org.apache.hadoop.hbase.shaded.protobuf.generated.ClientProtos$MultiRequest val$req;

  final org.apache.hadoop.hbase.HRegionLocation val$loc;

  final byte[] val$regionName;

  final org.apache.hadoop.hbase.client.RowMutations val$mutation;

  final java.util.function.Function val$respConverter;

  final org.apache.hadoop.hbase.client.RawAsyncTableImpl this$0;

  org.apache.hadoop.hbase.client.RawAsyncTableImpl$2(org.apache.hadoop.hbase.client.RawAsyncTableImpl, org.apache.hadoop.hbase.ipc.HBaseRpcController, java.util.concurrent.CompletableFuture, org.apache.hadoop.hbase.shaded.protobuf.generated.ClientProtos$MultiRequest, org.apache.hadoop.hbase.HRegionLocation, byte[], org.apache.hadoop.hbase.client.RowMutations, java.util.function.Function);
    Code:
       0: aload_0
       1: aload_1
       2: putfield      #1                  // Field this$0:Lorg/apache/hadoop/hbase/client/RawAsyncTableImpl;
       5: aload_0
       6: aload_2
       7: putfield      #2                  // Field val$controller:Lorg/apache/hadoop/hbase/ipc/HBaseRpcController;
      10: aload_0
      11: aload_3
      12: putfield      #3                  // Field val$future:Ljava/util/concurrent/CompletableFuture;
      15: aload_0
      16: aload         4
      18: putfield      #4                  // Field val$req:Lorg/apache/hadoop/hbase/shaded/protobuf/generated/ClientProtos$MultiRequest;
      21: aload_0
      22: aload         5
      24: putfield      #5                  // Field val$loc:Lorg/apache/hadoop/hbase/HRegionLocation;
      27: aload_0
      28: aload         6
      30: putfield      #6                  // Field val$regionName:[B
      33: aload_0
      34: aload         7
      36: putfield      #7                  // Field val$mutation:Lorg/apache/hadoop/hbase/client/RowMutations;
      39: aload_0
      40: aload         8
      42: putfield      #8                  // Field val$respConverter:Ljava/util/function/Function;
      45: aload_0
      46: invokespecial #9                  // Method java/lang/Object."<init>":()V
      49: return

  public void run(org.apache.hadoop.hbase.shaded.protobuf.generated.ClientProtos$MultiResponse);
    Code:
       0: aload_0
       1: getfield      #2                  // Field val$controller:Lorg/apache/hadoop/hbase/ipc/HBaseRpcController;
       4: invokeinterface #10,  1           // InterfaceMethod org/apache/hadoop/hbase/ipc/HBaseRpcController.failed:()Z
       9: ifeq          32
      12: aload_0
      13: getfield      #3                  // Field val$future:Ljava/util/concurrent/CompletableFuture;
      16: aload_0
      17: getfield      #2                  // Field val$controller:Lorg/apache/hadoop/hbase/ipc/HBaseRpcController;
      20: invokeinterface #11,  1           // InterfaceMethod org/apache/hadoop/hbase/ipc/HBaseRpcController.getFailed:()Ljava/io/IOException;
      25: invokevirtual #12                 // Method java/util/concurrent/CompletableFuture.completeExceptionally:(Ljava/lang/Throwable;)Z
      28: pop
      29: goto          213
      32: aload_0
      33: getfield      #4                  // Field val$req:Lorg/apache/hadoop/hbase/shaded/protobuf/generated/ClientProtos$MultiRequest;
      36: aload_1
      37: aload_0
      38: getfield      #2                  // Field val$controller:Lorg/apache/hadoop/hbase/ipc/HBaseRpcController;
      41: invokeinterface #13,  1           // InterfaceMethod org/apache/hadoop/hbase/ipc/HBaseRpcController.cellScanner:()Lorg/apache/hadoop/hbase/CellScanner;
      46: invokestatic  #14                 // Method org/apache/hadoop/hbase/shaded/protobuf/ResponseConverter.getResults:(Lorg/apache/hadoop/hbase/shaded/protobuf/generated/ClientProtos$MultiRequest;Lorg/apache/hadoop/hbase/shaded/protobuf/generated/ClientProtos$MultiResponse;Lorg/apache/hadoop/hbase/CellScanner;)Lorg/apache/hadoop/hbase/client/MultiResponse;
      49: astore_2
      50: aload_0
      51: getfield      #1                  // Field this$0:Lorg/apache/hadoop/hbase/client/RawAsyncTableImpl;
      54: invokestatic  #15                 // Method org/apache/hadoop/hbase/client/RawAsyncTableImpl.access$000:(Lorg/apache/hadoop/hbase/client/RawAsyncTableImpl;)Lorg/apache/hadoop/hbase/client/AsyncConnectionImpl;
      57: invokevirtual #16                 // Method org/apache/hadoop/hbase/client/AsyncConnectionImpl.getStatisticsTracker:()Ljava/util/Optional;
      60: aload_0
      61: getfield      #1                  // Field this$0:Lorg/apache/hadoop/hbase/client/RawAsyncTableImpl;
      64: invokestatic  #15                 // Method org/apache/hadoop/hbase/client/RawAsyncTableImpl.access$000:(Lorg/apache/hadoop/hbase/client/RawAsyncTableImpl;)Lorg/apache/hadoop/hbase/client/AsyncConnectionImpl;
      67: invokevirtual #17                 // Method org/apache/hadoop/hbase/client/AsyncConnectionImpl.getConnectionMetrics:()Ljava/util/Optional;
      70: aload_0
      71: getfield      #5                  // Field val$loc:Lorg/apache/hadoop/hbase/HRegionLocation;
      74: invokevirtual #18                 // Method org/apache/hadoop/hbase/HRegionLocation.getServerName:()Lorg/apache/hadoop/hbase/ServerName;
      77: aload_2
      78: invokestatic  #19                 // Method org/apache/hadoop/hbase/client/ConnectionUtils.updateStats:(Ljava/util/Optional;Ljava/util/Optional;Lorg/apache/hadoop/hbase/ServerName;Lorg/apache/hadoop/hbase/client/MultiResponse;)V
      81: aload_2
      82: aload_0
      83: getfield      #6                  // Field val$regionName:[B
      86: invokevirtual #20                 // Method org/apache/hadoop/hbase/client/MultiResponse.getException:([B)Ljava/lang/Throwable;
      89: astore_3
      90: aload_3
      91: ifnull        152
      94: aload_0
      95: getfield      #3                  // Field val$future:Ljava/util/concurrent/CompletableFuture;
      98: aload_3
      99: instanceof    #21                 // class java/io/IOException
     102: ifeq          109
     105: aload_3
     106: goto          145
     109: new           #21                 // class java/io/IOException
     112: dup
     113: new           #22                 // class java/lang/StringBuilder
     116: dup
     117: invokespecial #23                 // Method java/lang/StringBuilder."<init>":()V
     120: ldc           #24                 // String Failed to mutate row:
     122: invokevirtual #25                 // Method java/lang/StringBuilder.append:(Ljava/lang/String;)Ljava/lang/StringBuilder;
     125: aload_0
     126: getfield      #7                  // Field val$mutation:Lorg/apache/hadoop/hbase/client/RowMutations;
     129: invokevirtual #26                 // Method org/apache/hadoop/hbase/client/RowMutations.getRow:()[B
     132: invokestatic  #27                 // Method org/apache/hadoop/hbase/util/Bytes.toStringBinary:([B)Ljava/lang/String;
     135: invokevirtual #25                 // Method java/lang/StringBuilder.append:(Ljava/lang/String;)Ljava/lang/StringBuilder;
     138: invokevirtual #28                 // Method java/lang/StringBuilder.toString:()Ljava/lang/String;
     141: aload_3
     142: invokespecial #29                 // Method java/io/IOException."<init>":(Ljava/lang/String;Ljava/lang/Throwable;)V
     145: invokevirtual #12                 // Method java/util/concurrent/CompletableFuture.completeExceptionally:(Ljava/lang/Throwable;)Z
     148: pop
     149: goto          200
     152: aload_0
     153: getfield      #3                  // Field val$future:Ljava/util/concurrent/CompletableFuture;
     156: aload_0
     157: getfield      #8                  // Field val$respConverter:Ljava/util/function/Function;
     160: aload_2
     161: invokevirtual #30                 // Method org/apache/hadoop/hbase/client/MultiResponse.getResults:()Ljava/util/Map;
     164: aload_0
     165: getfield      #6                  // Field val$regionName:[B
     168: invokeinterface #31,  2           // InterfaceMethod java/util/Map.get:(Ljava/lang/Object;)Ljava/lang/Object;
     173: checkcast     #32                 // class org/apache/hadoop/hbase/client/MultiResponse$RegionResult
     176: getfield      #33                 // Field org/apache/hadoop/hbase/client/MultiResponse$RegionResult.result:Ljava/util/Map;
     179: iconst_0
     180: invokestatic  #34                 // Method java/lang/Integer.valueOf:(I)Ljava/lang/Integer;
     183: invokeinterface #31,  2           // InterfaceMethod java/util/Map.get:(Ljava/lang/Object;)Ljava/lang/Object;
     188: checkcast     #35                 // class org/apache/hadoop/hbase/client/Result
     191: invokeinterface #36,  2           // InterfaceMethod java/util/function/Function.apply:(Ljava/lang/Object;)Ljava/lang/Object;
     196: invokevirtual #37                 // Method java/util/concurrent/CompletableFuture.complete:(Ljava/lang/Object;)Z
     199: pop
     200: goto          213
     203: astore_2
     204: aload_0
     205: getfield      #3                  // Field val$future:Ljava/util/concurrent/CompletableFuture;
     208: aload_2
     209: invokevirtual #12                 // Method java/util/concurrent/CompletableFuture.completeExceptionally:(Ljava/lang/Throwable;)Z
     212: pop
     213: return
    Exception table:
       from    to  target type
          32   200   203   Class java/io/IOException

  public void run(java.lang.Object);
    Code:
       0: aload_0
       1: aload_1
       2: checkcast     #38                 // class org/apache/hadoop/hbase/shaded/protobuf/generated/ClientProtos$MultiResponse
       5: invokevirtual #39                 // Method run:(Lorg/apache/hadoop/hbase/shaded/protobuf/generated/ClientProtos$MultiResponse;)V
       8: return
}
