Compiled from "RawAsyncTableImpl.java"
final class org.apache.hadoop.hbase.client.RawAsyncTableImpl$CheckAndMutateBuilderImpl implements org.apache.hadoop.hbase.client.AsyncTable$CheckAndMutateBuilder {
  final org.apache.hadoop.hbase.client.RawAsyncTableImpl this$0;

  public org.apache.hadoop.hbase.client.RawAsyncTableImpl$CheckAndMutateBuilderImpl(org.apache.hadoop.hbase.client.RawAsyncTableImpl, byte[], byte[]);
    Code:
       0: aload_0
       1: aload_1
       2: putfield      #1                  // Field this$0:Lorg/apache/hadoop/hbase/client/RawAsyncTableImpl;
       5: aload_0
       6: invokespecial #2                  // Method java/lang/Object."<init>":()V
       9: aload_0
      10: aload_2
      11: ldc           #3                  // String row is null
      13: invokestatic  #4                  // Method org/apache/hbase/thirdparty/com/google/common/base/Preconditions.checkNotNull:(Ljava/lang/Object;Ljava/lang/Object;)Ljava/lang/Object;
      16: checkcast     #5                  // class "[B"
      19: putfield      #6                  // Field row:[B
      22: aload_0
      23: aload_3
      24: ldc           #7                  // String family is null
      26: invokestatic  #4                  // Method org/apache/hbase/thirdparty/com/google/common/base/Preconditions.checkNotNull:(Ljava/lang/Object;Ljava/lang/Object;)Ljava/lang/Object;
      29: checkcast     #5                  // class "[B"
      32: putfield      #8                  // Field family:[B
      35: return

  public org.apache.hadoop.hbase.client.AsyncTable$CheckAndMutateBuilder qualifier(byte[]);
    Code:
       0: aload_0
       1: aload_1
       2: ldc           #9                  // String qualifier is null. Consider using an empty byte array, or just do not call this method if you want a null qualifier
       4: invokestatic  #4                  // Method org/apache/hbase/thirdparty/com/google/common/base/Preconditions.checkNotNull:(Ljava/lang/Object;Ljava/lang/Object;)Ljava/lang/Object;
       7: checkcast     #5                  // class "[B"
      10: putfield      #10                 // Field qualifier:[B
      13: aload_0
      14: areturn

  public org.apache.hadoop.hbase.client.AsyncTable$CheckAndMutateBuilder timeRange(org.apache.hadoop.hbase.io.TimeRange);
    Code:
       0: aload_0
       1: aload_1
       2: putfield      #11                 // Field timeRange:Lorg/apache/hadoop/hbase/io/TimeRange;
       5: aload_0
       6: areturn

  public org.apache.hadoop.hbase.client.AsyncTable$CheckAndMutateBuilder ifNotExists();
    Code:
       0: aload_0
       1: getstatic     #12                 // Field org/apache/hadoop/hbase/CompareOperator.EQUAL:Lorg/apache/hadoop/hbase/CompareOperator;
       4: putfield      #13                 // Field op:Lorg/apache/hadoop/hbase/CompareOperator;
       7: aload_0
       8: aconst_null
       9: putfield      #14                 // Field value:[B
      12: aload_0
      13: areturn

  public org.apache.hadoop.hbase.client.AsyncTable$CheckAndMutateBuilder ifMatches(org.apache.hadoop.hbase.CompareOperator, byte[]);
    Code:
       0: aload_0
       1: aload_1
       2: ldc           #15                 // String compareOp is null
       4: invokestatic  #4                  // Method org/apache/hbase/thirdparty/com/google/common/base/Preconditions.checkNotNull:(Ljava/lang/Object;Ljava/lang/Object;)Ljava/lang/Object;
       7: checkcast     #16                 // class org/apache/hadoop/hbase/CompareOperator
      10: putfield      #13                 // Field op:Lorg/apache/hadoop/hbase/CompareOperator;
      13: aload_0
      14: aload_2
      15: ldc           #17                 // String value is null
      17: invokestatic  #4                  // Method org/apache/hbase/thirdparty/com/google/common/base/Preconditions.checkNotNull:(Ljava/lang/Object;Ljava/lang/Object;)Ljava/lang/Object;
      20: checkcast     #5                  // class "[B"
      23: putfield      #14                 // Field value:[B
      26: aload_0
      27: areturn

  public java.util.concurrent.CompletableFuture<java.lang.Boolean> thenPut(org.apache.hadoop.hbase.client.Put);
    Code:
       0: aload_1
       1: aload_0
       2: getfield      #1                  // Field this$0:Lorg/apache/hadoop/hbase/client/RawAsyncTableImpl;
       5: invokestatic  #19                 // Method org/apache/hadoop/hbase/client/RawAsyncTableImpl.access$000:(Lorg/apache/hadoop/hbase/client/RawAsyncTableImpl;)Lorg/apache/hadoop/hbase/client/AsyncConnectionImpl;
       8: getfield      #20                 // Field org/apache/hadoop/hbase/client/AsyncConnectionImpl.connConf:Lorg/apache/hadoop/hbase/client/AsyncConnectionConfiguration;
      11: invokevirtual #21                 // Method org/apache/hadoop/hbase/client/AsyncConnectionConfiguration.getMaxKeyValueSize:()I
      14: invokestatic  #22                 // Method org/apache/hadoop/hbase/client/ConnectionUtils.validatePut:(Lorg/apache/hadoop/hbase/client/Put;I)V
      17: aload_0
      18: invokespecial #23                 // Method preCheck:()V
      21: aload_0
      22: getfield      #1                  // Field this$0:Lorg/apache/hadoop/hbase/client/RawAsyncTableImpl;
      25: aload_0
      26: getfield      #6                  // Field row:[B
      29: aload_1
      30: invokevirtual #24                 // Method org/apache/hadoop/hbase/client/Put.getPriority:()I
      33: aload_0
      34: getfield      #1                  // Field this$0:Lorg/apache/hadoop/hbase/client/RawAsyncTableImpl;
      37: invokestatic  #25                 // Method org/apache/hadoop/hbase/client/RawAsyncTableImpl.access$100:(Lorg/apache/hadoop/hbase/client/RawAsyncTableImpl;)J
      40: invokestatic  #26                 // Method org/apache/hadoop/hbase/client/RawAsyncTableImpl.access$200:(Lorg/apache/hadoop/hbase/client/RawAsyncTableImpl;[BIJ)Lorg/apache/hadoop/hbase/client/AsyncRpcRetryingCallerFactory$SingleRequestCallerBuilder;
      43: aload_0
      44: aload_1
      45: invokedynamic #27,  0             // InvokeDynamic #0:call:(Lorg/apache/hadoop/hbase/client/RawAsyncTableImpl$CheckAndMutateBuilderImpl;Lorg/apache/hadoop/hbase/client/Put;)Lorg/apache/hadoop/hbase/client/AsyncSingleRequestRpcRetryingCaller$Callable;
      50: invokevirtual #28                 // Method org/apache/hadoop/hbase/client/AsyncRpcRetryingCallerFactory$SingleRequestCallerBuilder.action:(Lorg/apache/hadoop/hbase/client/AsyncSingleRequestRpcRetryingCaller$Callable;)Lorg/apache/hadoop/hbase/client/AsyncRpcRetryingCallerFactory$SingleRequestCallerBuilder;
      53: invokevirtual #29                 // Method org/apache/hadoop/hbase/client/AsyncRpcRetryingCallerFactory$SingleRequestCallerBuilder.call:()Ljava/util/concurrent/CompletableFuture;
      56: areturn

  public java.util.concurrent.CompletableFuture<java.lang.Boolean> thenDelete(org.apache.hadoop.hbase.client.Delete);
    Code:
       0: aload_0
       1: invokespecial #23                 // Method preCheck:()V
       4: aload_0
       5: getfield      #1                  // Field this$0:Lorg/apache/hadoop/hbase/client/RawAsyncTableImpl;
       8: aload_0
       9: getfield      #6                  // Field row:[B
      12: aload_1
      13: invokevirtual #30                 // Method org/apache/hadoop/hbase/client/Delete.getPriority:()I
      16: aload_0
      17: getfield      #1                  // Field this$0:Lorg/apache/hadoop/hbase/client/RawAsyncTableImpl;
      20: invokestatic  #25                 // Method org/apache/hadoop/hbase/client/RawAsyncTableImpl.access$100:(Lorg/apache/hadoop/hbase/client/RawAsyncTableImpl;)J
      23: invokestatic  #26                 // Method org/apache/hadoop/hbase/client/RawAsyncTableImpl.access$200:(Lorg/apache/hadoop/hbase/client/RawAsyncTableImpl;[BIJ)Lorg/apache/hadoop/hbase/client/AsyncRpcRetryingCallerFactory$SingleRequestCallerBuilder;
      26: aload_0
      27: aload_1
      28: invokedynamic #31,  0             // InvokeDynamic #1:call:(Lorg/apache/hadoop/hbase/client/RawAsyncTableImpl$CheckAndMutateBuilderImpl;Lorg/apache/hadoop/hbase/client/Delete;)Lorg/apache/hadoop/hbase/client/AsyncSingleRequestRpcRetryingCaller$Callable;
      33: invokevirtual #28                 // Method org/apache/hadoop/hbase/client/AsyncRpcRetryingCallerFactory$SingleRequestCallerBuilder.action:(Lorg/apache/hadoop/hbase/client/AsyncSingleRequestRpcRetryingCaller$Callable;)Lorg/apache/hadoop/hbase/client/AsyncRpcRetryingCallerFactory$SingleRequestCallerBuilder;
      36: invokevirtual #29                 // Method org/apache/hadoop/hbase/client/AsyncRpcRetryingCallerFactory$SingleRequestCallerBuilder.call:()Ljava/util/concurrent/CompletableFuture;
      39: areturn

  public java.util.concurrent.CompletableFuture<java.lang.Boolean> thenMutate(org.apache.hadoop.hbase.client.RowMutations);
    Code:
       0: aload_0
       1: invokespecial #23                 // Method preCheck:()V
       4: aload_0
       5: getfield      #1                  // Field this$0:Lorg/apache/hadoop/hbase/client/RawAsyncTableImpl;
       8: aload_0
       9: getfield      #6                  // Field row:[B
      12: aload_1
      13: invokevirtual #32                 // Method org/apache/hadoop/hbase/client/RowMutations.getMaxPriority:()I
      16: aload_0
      17: getfield      #1                  // Field this$0:Lorg/apache/hadoop/hbase/client/RawAsyncTableImpl;
      20: invokestatic  #25                 // Method org/apache/hadoop/hbase/client/RawAsyncTableImpl.access$100:(Lorg/apache/hadoop/hbase/client/RawAsyncTableImpl;)J
      23: invokestatic  #26                 // Method org/apache/hadoop/hbase/client/RawAsyncTableImpl.access$200:(Lorg/apache/hadoop/hbase/client/RawAsyncTableImpl;[BIJ)Lorg/apache/hadoop/hbase/client/AsyncRpcRetryingCallerFactory$SingleRequestCallerBuilder;
      26: aload_0
      27: aload_1
      28: invokedynamic #33,  0             // InvokeDynamic #2:call:(Lorg/apache/hadoop/hbase/client/RawAsyncTableImpl$CheckAndMutateBuilderImpl;Lorg/apache/hadoop/hbase/client/RowMutations;)Lorg/apache/hadoop/hbase/client/AsyncSingleRequestRpcRetryingCaller$Callable;
      33: invokevirtual #28                 // Method org/apache/hadoop/hbase/client/AsyncRpcRetryingCallerFactory$SingleRequestCallerBuilder.action:(Lorg/apache/hadoop/hbase/client/AsyncSingleRequestRpcRetryingCaller$Callable;)Lorg/apache/hadoop/hbase/client/AsyncRpcRetryingCallerFactory$SingleRequestCallerBuilder;
      36: invokevirtual #29                 // Method org/apache/hadoop/hbase/client/AsyncRpcRetryingCallerFactory$SingleRequestCallerBuilder.call:()Ljava/util/concurrent/CompletableFuture;
      39: areturn
}
