Compiled from "RawAsyncHBaseAdmin.java"
class org.apache.hadoop.hbase.client.RawAsyncHBaseAdmin$4 implements org.apache.hbase.thirdparty.io.netty.util.TimerTask {
  int tries;

  long startTime;

  long endTime;

  long maxPauseTime;

  final java.lang.Long val$expectedTimeout;

  final org.apache.hadoop.hbase.client.SnapshotDescription val$snapshotDesc;

  final java.util.concurrent.CompletableFuture val$future;

  final org.apache.hadoop.hbase.shaded.protobuf.generated.SnapshotProtos$SnapshotDescription val$snapshot;

  final org.apache.hadoop.hbase.client.RawAsyncHBaseAdmin this$0;

  org.apache.hadoop.hbase.client.RawAsyncHBaseAdmin$4(org.apache.hadoop.hbase.client.RawAsyncHBaseAdmin, java.lang.Long, org.apache.hadoop.hbase.client.SnapshotDescription, java.util.concurrent.CompletableFuture, org.apache.hadoop.hbase.shaded.protobuf.generated.SnapshotProtos$SnapshotDescription);
    Code:
       0: aload_0
       1: aload_1
       2: putfield      #1                  // Field this$0:Lorg/apache/hadoop/hbase/client/RawAsyncHBaseAdmin;
       5: aload_0
       6: aload_2
       7: putfield      #2                  // Field val$expectedTimeout:Ljava/lang/Long;
      10: aload_0
      11: aload_3
      12: putfield      #3                  // Field val$snapshotDesc:Lorg/apache/hadoop/hbase/client/SnapshotDescription;
      15: aload_0
      16: aload         4
      18: putfield      #4                  // Field val$future:Ljava/util/concurrent/CompletableFuture;
      21: aload_0
      22: aload         5
      24: putfield      #5                  // Field val$snapshot:Lorg/apache/hadoop/hbase/shaded/protobuf/generated/SnapshotProtos$SnapshotDescription;
      27: aload_0
      28: invokespecial #6                  // Method java/lang/Object."<init>":()V
      31: aload_0
      32: iconst_0
      33: putfield      #7                  // Field tries:I
      36: aload_0
      37: invokestatic  #8                  // Method org/apache/hadoop/hbase/util/EnvironmentEdgeManager.currentTime:()J
      40: putfield      #9                  // Field startTime:J
      43: aload_0
      44: aload_0
      45: getfield      #9                  // Field startTime:J
      48: aload_0
      49: getfield      #2                  // Field val$expectedTimeout:Ljava/lang/Long;
      52: invokevirtual #10                 // Method java/lang/Long.longValue:()J
      55: ladd
      56: putfield      #11                 // Field endTime:J
      59: aload_0
      60: aload_0
      61: getfield      #2                  // Field val$expectedTimeout:Ljava/lang/Long;
      64: invokevirtual #10                 // Method java/lang/Long.longValue:()J
      67: aload_0
      68: getfield      #1                  // Field this$0:Lorg/apache/hadoop/hbase/client/RawAsyncHBaseAdmin;
      71: invokestatic  #12                 // Method org/apache/hadoop/hbase/client/RawAsyncHBaseAdmin.access$300:(Lorg/apache/hadoop/hbase/client/RawAsyncHBaseAdmin;)I
      74: i2l
      75: ldiv
      76: putfield      #13                 // Field maxPauseTime:J
      79: return

  public void run(org.apache.hbase.thirdparty.io.netty.util.Timeout) throws java.lang.Exception;
    Code:
       0: invokestatic  #8                  // Method org/apache/hadoop/hbase/util/EnvironmentEdgeManager.currentTime:()J
       3: aload_0
       4: getfield      #11                 // Field endTime:J
       7: lcmp
       8: ifge          38
      11: aload_0
      12: getfield      #1                  // Field this$0:Lorg/apache/hadoop/hbase/client/RawAsyncHBaseAdmin;
      15: aload_0
      16: getfield      #3                  // Field val$snapshotDesc:Lorg/apache/hadoop/hbase/client/SnapshotDescription;
      19: invokevirtual #14                 // Method org/apache/hadoop/hbase/client/RawAsyncHBaseAdmin.isSnapshotFinished:(Lorg/apache/hadoop/hbase/client/SnapshotDescription;)Ljava/util/concurrent/CompletableFuture;
      22: aload_0
      23: aload_0
      24: getfield      #4                  // Field val$future:Ljava/util/concurrent/CompletableFuture;
      27: invokedynamic #15,  0             // InvokeDynamic #0:accept:(Lorg/apache/hadoop/hbase/client/RawAsyncHBaseAdmin$4;Ljava/util/concurrent/CompletableFuture;)Ljava/util/function/BiConsumer;
      32: invokestatic  #16                 // Method org/apache/hadoop/hbase/util/FutureUtils.addListener:(Ljava/util/concurrent/CompletableFuture;Ljava/util/function/BiConsumer;)V
      35: goto          99
      38: aload_0
      39: getfield      #4                  // Field val$future:Ljava/util/concurrent/CompletableFuture;
      42: new           #17                 // class org/apache/hadoop/hbase/snapshot/SnapshotCreationException
      45: dup
      46: new           #18                 // class java/lang/StringBuilder
      49: dup
      50: invokespecial #19                 // Method java/lang/StringBuilder."<init>":()V
      53: ldc           #20                 // String Snapshot '
      55: invokevirtual #21                 // Method java/lang/StringBuilder.append:(Ljava/lang/String;)Ljava/lang/StringBuilder;
      58: aload_0
      59: getfield      #5                  // Field val$snapshot:Lorg/apache/hadoop/hbase/shaded/protobuf/generated/SnapshotProtos$SnapshotDescription;
      62: invokevirtual #22                 // Method org/apache/hadoop/hbase/shaded/protobuf/generated/SnapshotProtos$SnapshotDescription.getName:()Ljava/lang/String;
      65: invokevirtual #21                 // Method java/lang/StringBuilder.append:(Ljava/lang/String;)Ljava/lang/StringBuilder;
      68: ldc           #23                 // String ' wasn't completed in expectedTime:
      70: invokevirtual #21                 // Method java/lang/StringBuilder.append:(Ljava/lang/String;)Ljava/lang/StringBuilder;
      73: aload_0
      74: getfield      #2                  // Field val$expectedTimeout:Ljava/lang/Long;
      77: invokevirtual #24                 // Method java/lang/StringBuilder.append:(Ljava/lang/Object;)Ljava/lang/StringBuilder;
      80: ldc           #25                 // String  ms
      82: invokevirtual #21                 // Method java/lang/StringBuilder.append:(Ljava/lang/String;)Ljava/lang/StringBuilder;
      85: invokevirtual #26                 // Method java/lang/StringBuilder.toString:()Ljava/lang/String;
      88: aload_0
      89: getfield      #3                  // Field val$snapshotDesc:Lorg/apache/hadoop/hbase/client/SnapshotDescription;
      92: invokespecial #27                 // Method org/apache/hadoop/hbase/snapshot/SnapshotCreationException."<init>":(Ljava/lang/String;Lorg/apache/hadoop/hbase/client/SnapshotDescription;)V
      95: invokevirtual #28                 // Method java/util/concurrent/CompletableFuture.completeExceptionally:(Ljava/lang/Throwable;)Z
      98: pop
      99: return
}
