Compiled from "RawAsyncHBaseAdmin.java"
class org.apache.hadoop.hbase.client.RawAsyncHBaseAdmin$2 implements org.apache.hbase.thirdparty.com.google.protobuf.RpcCallback<PRESP> {
  final org.apache.hadoop.hbase.ipc.HBaseRpcController val$controller;

  final java.util.concurrent.CompletableFuture val$future;

  final org.apache.hadoop.hbase.client.RawAsyncHBaseAdmin$Converter val$respConverter;

  final org.apache.hadoop.hbase.client.RawAsyncHBaseAdmin this$0;

  org.apache.hadoop.hbase.client.RawAsyncHBaseAdmin$2(org.apache.hadoop.hbase.client.RawAsyncHBaseAdmin, org.apache.hadoop.hbase.ipc.HBaseRpcController, java.util.concurrent.CompletableFuture, org.apache.hadoop.hbase.client.RawAsyncHBaseAdmin$Converter);
    Code:
       0: aload_0
       1: aload_1
       2: putfield      #1                  // Field this$0:Lorg/apache/hadoop/hbase/client/RawAsyncHBaseAdmin;
       5: aload_0
       6: aload_2
       7: putfield      #2                  // Field val$controller:Lorg/apache/hadoop/hbase/ipc/HBaseRpcController;
      10: aload_0
      11: aload_3
      12: putfield      #3                  // Field val$future:Ljava/util/concurrent/CompletableFuture;
      15: aload_0
      16: aload         4
      18: putfield      #4                  // Field val$respConverter:Lorg/apache/hadoop/hbase/client/RawAsyncHBaseAdmin$Converter;
      21: aload_0
      22: invokespecial #5                  // Method java/lang/Object."<init>":()V
      25: return

  public void run(PRESP);
    Code:
       0: aload_0
       1: getfield      #2                  // Field val$controller:Lorg/apache/hadoop/hbase/ipc/HBaseRpcController;
       4: invokeinterface #6,  1            // InterfaceMethod org/apache/hadoop/hbase/ipc/HBaseRpcController.failed:()Z
       9: ifeq          32
      12: aload_0
      13: getfield      #3                  // Field val$future:Ljava/util/concurrent/CompletableFuture;
      16: aload_0
      17: getfield      #2                  // Field val$controller:Lorg/apache/hadoop/hbase/ipc/HBaseRpcController;
      20: invokeinterface #7,  1            // InterfaceMethod org/apache/hadoop/hbase/ipc/HBaseRpcController.getFailed:()Ljava/io/IOException;
      25: invokevirtual #8                  // Method java/util/concurrent/CompletableFuture.completeExceptionally:(Ljava/lang/Throwable;)Z
      28: pop
      29: goto          63
      32: aload_0
      33: getfield      #3                  // Field val$future:Ljava/util/concurrent/CompletableFuture;
      36: aload_0
      37: getfield      #4                  // Field val$respConverter:Lorg/apache/hadoop/hbase/client/RawAsyncHBaseAdmin$Converter;
      40: aload_1
      41: invokeinterface #9,  2            // InterfaceMethod org/apache/hadoop/hbase/client/RawAsyncHBaseAdmin$Converter.convert:(Ljava/lang/Object;)Ljava/lang/Object;
      46: invokevirtual #10                 // Method java/util/concurrent/CompletableFuture.complete:(Ljava/lang/Object;)Z
      49: pop
      50: goto          63
      53: astore_2
      54: aload_0
      55: getfield      #3                  // Field val$future:Ljava/util/concurrent/CompletableFuture;
      58: aload_2
      59: invokevirtual #8                  // Method java/util/concurrent/CompletableFuture.completeExceptionally:(Ljava/lang/Throwable;)Z
      62: pop
      63: return
    Exception table:
       from    to  target type
          32    50    53   Class java/io/IOException
}
