Compiled from "RawAsyncHBaseAdmin.java"
abstract class org.apache.hadoop.hbase.client.RawAsyncHBaseAdmin$ProcedureBiConsumer implements java.util.function.BiConsumer<java.lang.Void, java.lang.Throwable> {
  abstract void onFinished();

  abstract void onError(java.lang.Throwable);

  public void accept(java.lang.Void, java.lang.Throwable);
    Code:
       0: aload_2
       1: ifnull        10
       4: aload_0
       5: aload_2
       6: invokevirtual #3                  // Method onError:(Ljava/lang/Throwable;)V
       9: return
      10: aload_0
      11: invokevirtual #4                  // Method onFinished:()V
      14: return

  public void accept(java.lang.Object, java.lang.Object);
    Code:
       0: aload_0
       1: aload_1
       2: checkcast     #5                  // class java/lang/Void
       5: aload_2
       6: checkcast     #6                  // class java/lang/Throwable
       9: invokevirtual #7                  // Method accept:(Ljava/lang/Void;Ljava/lang/Throwable;)V
      12: return

  org.apache.hadoop.hbase.client.RawAsyncHBaseAdmin$ProcedureBiConsumer(org.apache.hadoop.hbase.client.RawAsyncHBaseAdmin$1);
    Code:
       0: aload_0
       1: invokespecial #1                  // Method "<init>":()V
       4: return
}
