Compiled from "RawLong.java"
public class org.apache.hadoop.hbase.types.RawLong implements org.apache.hadoop.hbase.types.DataType<java.lang.Long> {
  public org.apache.hadoop.hbase.types.RawLong();
    Code:
       0: aload_0
       1: invokespecial #1                  // Method java/lang/Object."<init>":()V
       4: return

  public boolean isOrderPreserving();
    Code:
       0: iconst_0
       1: ireturn

  public org.apache.hadoop.hbase.util.Order getOrder();
    Code:
       0: aconst_null
       1: areturn

  public boolean isNullable();
    Code:
       0: iconst_0
       1: ireturn

  public boolean isSkippable();
    Code:
       0: iconst_1
       1: ireturn

  public int encodedLength(java.lang.Long);
    Code:
       0: bipush        8
       2: ireturn

  public java.lang.Class<java.lang.Long> encodedClass();
    Code:
       0: ldc           #3                  // class java/lang/Long
       2: areturn

  public int skip(org.apache.hadoop.hbase.util.PositionedByteRange);
    Code:
       0: aload_1
       1: aload_1
       2: invokeinterface #4,  1            // InterfaceMethod org/apache/hadoop/hbase/util/PositionedByteRange.getPosition:()I
       7: bipush        8
       9: iadd
      10: invokeinterface #5,  2            // InterfaceMethod org/apache/hadoop/hbase/util/PositionedByteRange.setPosition:(I)Lorg/apache/hadoop/hbase/util/PositionedByteRange;
      15: pop
      16: bipush        8
      18: ireturn

  public java.lang.Long decode(org.apache.hadoop.hbase.util.PositionedByteRange);
    Code:
       0: aload_1
       1: invokeinterface #6,  1            // InterfaceMethod org/apache/hadoop/hbase/util/PositionedByteRange.getBytes:()[B
       6: aload_1
       7: invokeinterface #7,  1            // InterfaceMethod org/apache/hadoop/hbase/util/PositionedByteRange.getOffset:()I
      12: aload_1
      13: invokeinterface #4,  1            // InterfaceMethod org/apache/hadoop/hbase/util/PositionedByteRange.getPosition:()I
      18: iadd
      19: invokestatic  #8                  // Method org/apache/hadoop/hbase/util/Bytes.toLong:([BI)J
      22: lstore_2
      23: aload_0
      24: aload_1
      25: invokevirtual #9                  // Method skip:(Lorg/apache/hadoop/hbase/util/PositionedByteRange;)I
      28: pop
      29: lload_2
      30: invokestatic  #10                 // Method java/lang/Long.valueOf:(J)Ljava/lang/Long;
      33: areturn

  public int encode(org.apache.hadoop.hbase.util.PositionedByteRange, java.lang.Long);
    Code:
       0: aload_1
       1: invokeinterface #6,  1            // InterfaceMethod org/apache/hadoop/hbase/util/PositionedByteRange.getBytes:()[B
       6: aload_1
       7: invokeinterface #7,  1            // InterfaceMethod org/apache/hadoop/hbase/util/PositionedByteRange.getOffset:()I
      12: aload_1
      13: invokeinterface #4,  1            // InterfaceMethod org/apache/hadoop/hbase/util/PositionedByteRange.getPosition:()I
      18: iadd
      19: aload_2
      20: invokevirtual #11                 // Method java/lang/Long.longValue:()J
      23: invokestatic  #12                 // Method org/apache/hadoop/hbase/util/Bytes.putLong:([BIJ)I
      26: pop
      27: aload_0
      28: aload_1
      29: invokevirtual #9                  // Method skip:(Lorg/apache/hadoop/hbase/util/PositionedByteRange;)I
      32: ireturn

  public long decodeLong(byte[], int);
    Code:
       0: aload_1
       1: iload_2
       2: invokestatic  #8                  // Method org/apache/hadoop/hbase/util/Bytes.toLong:([BI)J
       5: lreturn

  public int encodeLong(byte[], int, long);
    Code:
       0: aload_1
       1: iload_2
       2: lload_3
       3: invokestatic  #12                 // Method org/apache/hadoop/hbase/util/Bytes.putLong:([BIJ)I
       6: ireturn

  public int encode(org.apache.hadoop.hbase.util.PositionedByteRange, java.lang.Object);
    Code:
       0: aload_0
       1: aload_1
       2: aload_2
       3: checkcast     #3                  // class java/lang/Long
       6: invokevirtual #13                 // Method encode:(Lorg/apache/hadoop/hbase/util/PositionedByteRange;Ljava/lang/Long;)I
       9: ireturn

  public java.lang.Object decode(org.apache.hadoop.hbase.util.PositionedByteRange);
    Code:
       0: aload_0
       1: aload_1
       2: invokevirtual #14                 // Method decode:(Lorg/apache/hadoop/hbase/util/PositionedByteRange;)Ljava/lang/Long;
       5: areturn

  public int encodedLength(java.lang.Object);
    Code:
       0: aload_0
       1: aload_1
       2: checkcast     #3                  // class java/lang/Long
       5: invokevirtual #15                 // Method encodedLength:(Ljava/lang/Long;)I
       8: ireturn
}
