Compiled from "RawString.java"
public class org.apache.hadoop.hbase.types.RawString implements org.apache.hadoop.hbase.types.DataType<java.lang.String> {
  public static final org.apache.hadoop.hbase.types.RawString ASCENDING;

  public static final org.apache.hadoop.hbase.types.RawString DESCENDING;

  protected final org.apache.hadoop.hbase.util.Order order;

  protected org.apache.hadoop.hbase.types.RawString();
    Code:
       0: aload_0
       1: invokespecial #1                  // Method java/lang/Object."<init>":()V
       4: aload_0
       5: getstatic     #2                  // Field org/apache/hadoop/hbase/util/Order.ASCENDING:Lorg/apache/hadoop/hbase/util/Order;
       8: putfield      #3                  // Field order:Lorg/apache/hadoop/hbase/util/Order;
      11: return

  protected org.apache.hadoop.hbase.types.RawString(org.apache.hadoop.hbase.util.Order);
    Code:
       0: aload_0
       1: invokespecial #1                  // Method java/lang/Object."<init>":()V
       4: aload_0
       5: aload_1
       6: putfield      #3                  // Field order:Lorg/apache/hadoop/hbase/util/Order;
       9: return

  public boolean isOrderPreserving();
    Code:
       0: iconst_1
       1: ireturn

  public org.apache.hadoop.hbase.util.Order getOrder();
    Code:
       0: aload_0
       1: getfield      #3                  // Field order:Lorg/apache/hadoop/hbase/util/Order;
       4: areturn

  public boolean isNullable();
    Code:
       0: iconst_0
       1: ireturn

  public boolean isSkippable();
    Code:
       0: iconst_0
       1: ireturn

  public int skip(org.apache.hadoop.hbase.util.PositionedByteRange);
    Code:
       0: aload_1
       1: invokeinterface #4,  1            // InterfaceMethod org/apache/hadoop/hbase/util/PositionedByteRange.getRemaining:()I
       6: istore_2
       7: aload_1
       8: aload_1
       9: invokeinterface #5,  1            // InterfaceMethod org/apache/hadoop/hbase/util/PositionedByteRange.getLength:()I
      14: invokeinterface #6,  2            // InterfaceMethod org/apache/hadoop/hbase/util/PositionedByteRange.setPosition:(I)Lorg/apache/hadoop/hbase/util/PositionedByteRange;
      19: pop
      20: iload_2
      21: ireturn

  public int encodedLength(java.lang.String);
    Code:
       0: aload_1
       1: invokestatic  #7                  // Method org/apache/hadoop/hbase/util/Bytes.toBytes:(Ljava/lang/String;)[B
       4: arraylength
       5: ireturn

  public java.lang.Class<java.lang.String> encodedClass();
    Code:
       0: ldc           #8                  // class java/lang/String
       2: areturn

  public java.lang.String decode(org.apache.hadoop.hbase.util.PositionedByteRange);
    Code:
       0: getstatic     #2                  // Field org/apache/hadoop/hbase/util/Order.ASCENDING:Lorg/apache/hadoop/hbase/util/Order;
       3: aload_0
       4: getfield      #3                  // Field order:Lorg/apache/hadoop/hbase/util/Order;
       7: if_acmpne     54
      10: aload_1
      11: invokeinterface #9,  1            // InterfaceMethod org/apache/hadoop/hbase/util/PositionedByteRange.getBytes:()[B
      16: aload_1
      17: invokeinterface #10,  1           // InterfaceMethod org/apache/hadoop/hbase/util/PositionedByteRange.getOffset:()I
      22: aload_1
      23: invokeinterface #11,  1           // InterfaceMethod org/apache/hadoop/hbase/util/PositionedByteRange.getPosition:()I
      28: iadd
      29: aload_1
      30: invokeinterface #4,  1            // InterfaceMethod org/apache/hadoop/hbase/util/PositionedByteRange.getRemaining:()I
      35: invokestatic  #12                 // Method org/apache/hadoop/hbase/util/Bytes.toString:([BII)Ljava/lang/String;
      38: astore_2
      39: aload_1
      40: aload_1
      41: invokeinterface #5,  1            // InterfaceMethod org/apache/hadoop/hbase/util/PositionedByteRange.getLength:()I
      46: invokeinterface #6,  2            // InterfaceMethod org/apache/hadoop/hbase/util/PositionedByteRange.setPosition:(I)Lorg/apache/hadoop/hbase/util/PositionedByteRange;
      51: pop
      52: aload_2
      53: areturn
      54: aload_1
      55: invokeinterface #4,  1            // InterfaceMethod org/apache/hadoop/hbase/util/PositionedByteRange.getRemaining:()I
      60: newarray       byte
      62: astore_2
      63: aload_1
      64: aload_2
      65: invokeinterface #13,  2           // InterfaceMethod org/apache/hadoop/hbase/util/PositionedByteRange.get:([B)Lorg/apache/hadoop/hbase/util/PositionedByteRange;
      70: pop
      71: aload_0
      72: getfield      #3                  // Field order:Lorg/apache/hadoop/hbase/util/Order;
      75: aload_2
      76: iconst_0
      77: aload_2
      78: arraylength
      79: invokevirtual #14                 // Method org/apache/hadoop/hbase/util/Order.apply:([BII)V
      82: aload_2
      83: invokestatic  #15                 // Method org/apache/hadoop/hbase/util/Bytes.toString:([B)Ljava/lang/String;
      86: areturn

  public int encode(org.apache.hadoop.hbase.util.PositionedByteRange, java.lang.String);
    Code:
       0: aload_2
       1: invokestatic  #7                  // Method org/apache/hadoop/hbase/util/Bytes.toBytes:(Ljava/lang/String;)[B
       4: astore_3
       5: aload_0
       6: getfield      #3                  // Field order:Lorg/apache/hadoop/hbase/util/Order;
       9: aload_3
      10: invokevirtual #16                 // Method org/apache/hadoop/hbase/util/Order.apply:([B)V
      13: aload_1
      14: aload_3
      15: invokeinterface #17,  2           // InterfaceMethod org/apache/hadoop/hbase/util/PositionedByteRange.put:([B)Lorg/apache/hadoop/hbase/util/PositionedByteRange;
      20: pop
      21: aload_3
      22: arraylength
      23: ireturn

  public int encode(org.apache.hadoop.hbase.util.PositionedByteRange, java.lang.Object);
    Code:
       0: aload_0
       1: aload_1
       2: aload_2
       3: checkcast     #8                  // class java/lang/String
       6: invokevirtual #18                 // Method encode:(Lorg/apache/hadoop/hbase/util/PositionedByteRange;Ljava/lang/String;)I
       9: ireturn

  public java.lang.Object decode(org.apache.hadoop.hbase.util.PositionedByteRange);
    Code:
       0: aload_0
       1: aload_1
       2: invokevirtual #19                 // Method decode:(Lorg/apache/hadoop/hbase/util/PositionedByteRange;)Ljava/lang/String;
       5: areturn

  public int encodedLength(java.lang.Object);
    Code:
       0: aload_0
       1: aload_1
       2: checkcast     #8                  // class java/lang/String
       5: invokevirtual #20                 // Method encodedLength:(Ljava/lang/String;)I
       8: ireturn

  static {};
    Code:
       0: new           #21                 // class org/apache/hadoop/hbase/types/RawString
       3: dup
       4: getstatic     #2                  // Field org/apache/hadoop/hbase/util/Order.ASCENDING:Lorg/apache/hadoop/hbase/util/Order;
       7: invokespecial #22                 // Method "<init>":(Lorg/apache/hadoop/hbase/util/Order;)V
      10: putstatic     #23                 // Field ASCENDING:Lorg/apache/hadoop/hbase/types/RawString;
      13: new           #21                 // class org/apache/hadoop/hbase/types/RawString
      16: dup
      17: getstatic     #24                 // Field org/apache/hadoop/hbase/util/Order.DESCENDING:Lorg/apache/hadoop/hbase/util/Order;
      20: invokespecial #22                 // Method "<init>":(Lorg/apache/hadoop/hbase/util/Order;)V
      23: putstatic     #25                 // Field DESCENDING:Lorg/apache/hadoop/hbase/types/RawString;
      26: return
}
