Compiled from "RawStringTerminated.java"
public class org.apache.hadoop.hbase.types.RawStringTerminated extends org.apache.hadoop.hbase.types.TerminatedWrapper<java.lang.String> {
  public org.apache.hadoop.hbase.types.RawStringTerminated(org.apache.hadoop.hbase.util.Order, byte[]);
    Code:
       0: aload_0
       1: new           #1                  // class org/apache/hadoop/hbase/types/RawString
       4: dup
       5: aload_1
       6: invokespecial #2                  // Method org/apache/hadoop/hbase/types/RawString."<init>":(Lorg/apache/hadoop/hbase/util/Order;)V
       9: aload_2
      10: invokespecial #3                  // Method org/apache/hadoop/hbase/types/TerminatedWrapper."<init>":(Lorg/apache/hadoop/hbase/types/DataType;[B)V
      13: return

  public org.apache.hadoop.hbase.types.RawStringTerminated(org.apache.hadoop.hbase.util.Order, java.lang.String);
    Code:
       0: aload_0
       1: new           #1                  // class org/apache/hadoop/hbase/types/RawString
       4: dup
       5: aload_1
       6: invokespecial #2                  // Method org/apache/hadoop/hbase/types/RawString."<init>":(Lorg/apache/hadoop/hbase/util/Order;)V
       9: aload_2
      10: invokespecial #4                  // Method org/apache/hadoop/hbase/types/TerminatedWrapper."<init>":(Lorg/apache/hadoop/hbase/types/DataType;Ljava/lang/String;)V
      13: return

  public org.apache.hadoop.hbase.types.RawStringTerminated(byte[]);
    Code:
       0: aload_0
       1: new           #1                  // class org/apache/hadoop/hbase/types/RawString
       4: dup
       5: invokespecial #5                  // Method org/apache/hadoop/hbase/types/RawString."<init>":()V
       8: aload_1
       9: invokespecial #3                  // Method org/apache/hadoop/hbase/types/TerminatedWrapper."<init>":(Lorg/apache/hadoop/hbase/types/DataType;[B)V
      12: return

  public org.apache.hadoop.hbase.types.RawStringTerminated(java.lang.String);
    Code:
       0: aload_0
       1: new           #1                  // class org/apache/hadoop/hbase/types/RawString
       4: dup
       5: invokespecial #5                  // Method org/apache/hadoop/hbase/types/RawString."<init>":()V
       8: aload_1
       9: invokespecial #4                  // Method org/apache/hadoop/hbase/types/TerminatedWrapper."<init>":(Lorg/apache/hadoop/hbase/types/DataType;Ljava/lang/String;)V
      12: return
}
