Compiled from "ReadOnlyZKClient.java"
abstract class org.apache.hadoop.hbase.zookeeper.ReadOnlyZKClient$Task implements java.util.concurrent.Delayed {
  protected long time;

  public boolean needZk();
    Code:
       0: iconst_0
       1: ireturn

  public void exec(org.apache.zookeeper.ZooKeeper);
    Code:
       0: return

  public void connectFailed(java.io.IOException);
    Code:
       0: return

  public void closed(java.io.IOException);
    Code:
       0: return

  public int compareTo(java.util.concurrent.Delayed);
    Code:
       0: aload_1
       1: checkcast     #5                  // class org/apache/hadoop/hbase/zookeeper/ReadOnlyZKClient$Task
       4: astore_2
       5: aload_0
       6: getfield      #4                  // Field time:J
       9: aload_2
      10: getfield      #4                  // Field time:J
      13: invokestatic  #6                  // Method java/lang/Long.compare:(JJ)I
      16: istore_3
      17: iload_3
      18: ifeq          23
      21: iload_3
      22: ireturn
      23: aload_0
      24: invokestatic  #7                  // Method java/lang/System.identityHashCode:(Ljava/lang/Object;)I
      27: aload_2
      28: invokestatic  #7                  // Method java/lang/System.identityHashCode:(Ljava/lang/Object;)I
      31: invokestatic  #8                  // Method java/lang/Integer.compare:(II)I
      34: ireturn

  public long getDelay(java.util.concurrent.TimeUnit);
    Code:
       0: aload_1
       1: aload_0
       2: getfield      #4                  // Field time:J
       5: invokestatic  #3                  // Method java/lang/System.nanoTime:()J
       8: lsub
       9: getstatic     #9                  // Field java/util/concurrent/TimeUnit.NANOSECONDS:Ljava/util/concurrent/TimeUnit;
      12: invokevirtual #10                 // Method java/util/concurrent/TimeUnit.convert:(JLjava/util/concurrent/TimeUnit;)J
      15: lreturn

  public int compareTo(java.lang.Object);
    Code:
       0: aload_0
       1: aload_1
       2: checkcast     #11                 // class java/util/concurrent/Delayed
       5: invokevirtual #12                 // Method compareTo:(Ljava/util/concurrent/Delayed;)I
       8: ireturn

  org.apache.hadoop.hbase.zookeeper.ReadOnlyZKClient$Task(org.apache.hadoop.hbase.zookeeper.ReadOnlyZKClient$1);
    Code:
       0: aload_0
       1: invokespecial #1                  // Method "<init>":()V
       4: return
}
