Compiled from "RecoverableZooKeeper.java"
class org.apache.hadoop.hbase.zookeeper.RecoverableZooKeeper$1 {
  static final int[] $SwitchMap$org$apache$zookeeper$KeeperException$Code;

  static final int[] $SwitchMap$org$apache$zookeeper$CreateMode;

  static {};
    Code:
       0: invokestatic  #1                  // Method org/apache/zookeeper/CreateMode.values:()[Lorg/apache/zookeeper/CreateMode;
       3: arraylength
       4: newarray       int
       6: putstatic     #2                  // Field $SwitchMap$org$apache$zookeeper$CreateMode:[I
       9: getstatic     #2                  // Field $SwitchMap$org$apache$zookeeper$CreateMode:[I
      12: getstatic     #3                  // Field org/apache/zookeeper/CreateMode.EPHEMERAL:Lorg/apache/zookeeper/CreateMode;
      15: invokevirtual #4                  // Method org/apache/zookeeper/CreateMode.ordinal:()I
      18: iconst_1
      19: iastore
      20: goto          24
      23: astore_0
      24: getstatic     #2                  // Field $SwitchMap$org$apache$zookeeper$CreateMode:[I
      27: getstatic     #6                  // Field org/apache/zookeeper/CreateMode.PERSISTENT:Lorg/apache/zookeeper/CreateMode;
      30: invokevirtual #4                  // Method org/apache/zookeeper/CreateMode.ordinal:()I
      33: iconst_2
      34: iastore
      35: goto          39
      38: astore_0
      39: getstatic     #2                  // Field $SwitchMap$org$apache$zookeeper$CreateMode:[I
      42: getstatic     #7                  // Field org/apache/zookeeper/CreateMode.EPHEMERAL_SEQUENTIAL:Lorg/apache/zookeeper/CreateMode;
      45: invokevirtual #4                  // Method org/apache/zookeeper/CreateMode.ordinal:()I
      48: iconst_3
      49: iastore
      50: goto          54
      53: astore_0
      54: getstatic     #2                  // Field $SwitchMap$org$apache$zookeeper$CreateMode:[I
      57: getstatic     #8                  // Field org/apache/zookeeper/CreateMode.PERSISTENT_SEQUENTIAL:Lorg/apache/zookeeper/CreateMode;
      60: invokevirtual #4                  // Method org/apache/zookeeper/CreateMode.ordinal:()I
      63: iconst_4
      64: iastore
      65: goto          69
      68: astore_0
      69: invokestatic  #9                  // Method org/apache/zookeeper/KeeperException$Code.values:()[Lorg/apache/zookeeper/KeeperException$Code;
      72: arraylength
      73: newarray       int
      75: putstatic     #10                 // Field $SwitchMap$org$apache$zookeeper$KeeperException$Code:[I
      78: getstatic     #10                 // Field $SwitchMap$org$apache$zookeeper$KeeperException$Code:[I
      81: getstatic     #11                 // Field org/apache/zookeeper/KeeperException$Code.NONODE:Lorg/apache/zookeeper/KeeperException$Code;
      84: invokevirtual #12                 // Method org/apache/zookeeper/KeeperException$Code.ordinal:()I
      87: iconst_1
      88: iastore
      89: goto          93
      92: astore_0
      93: getstatic     #10                 // Field $SwitchMap$org$apache$zookeeper$KeeperException$Code:[I
      96: getstatic     #13                 // Field org/apache/zookeeper/KeeperException$Code.CONNECTIONLOSS:Lorg/apache/zookeeper/KeeperException$Code;
      99: invokevirtual #12                 // Method org/apache/zookeeper/KeeperException$Code.ordinal:()I
     102: iconst_2
     103: iastore
     104: goto          108
     107: astore_0
     108: getstatic     #10                 // Field $SwitchMap$org$apache$zookeeper$KeeperException$Code:[I
     111: getstatic     #14                 // Field org/apache/zookeeper/KeeperException$Code.OPERATIONTIMEOUT:Lorg/apache/zookeeper/KeeperException$Code;
     114: invokevirtual #12                 // Method org/apache/zookeeper/KeeperException$Code.ordinal:()I
     117: iconst_3
     118: iastore
     119: goto          123
     122: astore_0
     123: getstatic     #10                 // Field $SwitchMap$org$apache$zookeeper$KeeperException$Code:[I
     126: getstatic     #15                 // Field org/apache/zookeeper/KeeperException$Code.BADVERSION:Lorg/apache/zookeeper/KeeperException$Code;
     129: invokevirtual #12                 // Method org/apache/zookeeper/KeeperException$Code.ordinal:()I
     132: iconst_4
     133: iastore
     134: goto          138
     137: astore_0
     138: getstatic     #10                 // Field $SwitchMap$org$apache$zookeeper$KeeperException$Code:[I
     141: getstatic     #16                 // Field org/apache/zookeeper/KeeperException$Code.NODEEXISTS:Lorg/apache/zookeeper/KeeperException$Code;
     144: invokevirtual #12                 // Method org/apache/zookeeper/KeeperException$Code.ordinal:()I
     147: iconst_5
     148: iastore
     149: goto          153
     152: astore_0
     153: return
    Exception table:
       from    to  target type
           9    20    23   Class java/lang/NoSuchFieldError
          24    35    38   Class java/lang/NoSuchFieldError
          39    50    53   Class java/lang/NoSuchFieldError
          54    65    68   Class java/lang/NoSuchFieldError
          78    89    92   Class java/lang/NoSuchFieldError
          93   104   107   Class java/lang/NoSuchFieldError
         108   119   122   Class java/lang/NoSuchFieldError
         123   134   137   Class java/lang/NoSuchFieldError
         138   149   152   Class java/lang/NoSuchFieldError
}
