Compiled from "RecoverMetaProcedure.java"
public class org.apache.hadoop.hbase.master.procedure.RecoverMetaProcedure extends org.apache.hadoop.hbase.procedure2.StateMachineProcedure<org.apache.hadoop.hbase.master.procedure.MasterProcedureEnv, org.apache.hadoop.hbase.shaded.protobuf.generated.MasterProcedureProtos$RecoverMetaState> implements org.apache.hadoop.hbase.master.procedure.MetaProcedureInterface {
  public org.apache.hadoop.hbase.master.procedure.RecoverMetaProcedure();
    Code:
       0: aload_0
       1: invokespecial #1                  // Method org/apache/hadoop/hbase/procedure2/StateMachineProcedure."<init>":()V
       4: return

  protected org.apache.hadoop.hbase.procedure2.StateMachineProcedure$Flow executeFromState(org.apache.hadoop.hbase.master.procedure.MasterProcedureEnv, org.apache.hadoop.hbase.shaded.protobuf.generated.MasterProcedureProtos$RecoverMetaState) throws org.apache.hadoop.hbase.procedure2.ProcedureSuspendedException, org.apache.hadoop.hbase.procedure2.ProcedureYieldException, java.lang.InterruptedException;
    Code:
       0: getstatic     #2                  // Field org/apache/hadoop/hbase/procedure2/StateMachineProcedure$Flow.NO_MORE_STATE:Lorg/apache/hadoop/hbase/procedure2/StateMachineProcedure$Flow;
       3: areturn

  protected void rollbackState(org.apache.hadoop.hbase.master.procedure.MasterProcedureEnv, org.apache.hadoop.hbase.shaded.protobuf.generated.MasterProcedureProtos$RecoverMetaState) throws java.io.IOException, java.lang.InterruptedException;
    Code:
       0: new           #3                  // class java/lang/UnsupportedOperationException
       3: dup
       4: new           #4                  // class java/lang/StringBuilder
       7: dup
       8: invokespecial #5                  // Method java/lang/StringBuilder."<init>":()V
      11: ldc           #6                  // String unhandled state=
      13: invokevirtual #7                  // Method java/lang/StringBuilder.append:(Ljava/lang/String;)Ljava/lang/StringBuilder;
      16: aload_2
      17: invokevirtual #8                  // Method java/lang/StringBuilder.append:(Ljava/lang/Object;)Ljava/lang/StringBuilder;
      20: invokevirtual #9                  // Method java/lang/StringBuilder.toString:()Ljava/lang/String;
      23: invokespecial #10                 // Method java/lang/UnsupportedOperationException."<init>":(Ljava/lang/String;)V
      26: athrow

  protected org.apache.hadoop.hbase.shaded.protobuf.generated.MasterProcedureProtos$RecoverMetaState getState(int);
    Code:
       0: iload_1
       1: invokestatic  #11                 // Method org/apache/hadoop/hbase/shaded/protobuf/generated/MasterProcedureProtos$RecoverMetaState.forNumber:(I)Lorg/apache/hadoop/hbase/shaded/protobuf/generated/MasterProcedureProtos$RecoverMetaState;
       4: areturn

  protected int getStateId(org.apache.hadoop.hbase.shaded.protobuf.generated.MasterProcedureProtos$RecoverMetaState);
    Code:
       0: aload_1
       1: invokevirtual #12                 // Method org/apache/hadoop/hbase/shaded/protobuf/generated/MasterProcedureProtos$RecoverMetaState.getNumber:()I
       4: ireturn

  protected org.apache.hadoop.hbase.shaded.protobuf.generated.MasterProcedureProtos$RecoverMetaState getInitialState();
    Code:
       0: getstatic     #13                 // Field org/apache/hadoop/hbase/shaded/protobuf/generated/MasterProcedureProtos$RecoverMetaState.RECOVER_META_PREPARE:Lorg/apache/hadoop/hbase/shaded/protobuf/generated/MasterProcedureProtos$RecoverMetaState;
       3: areturn

  protected void toStringClassDetails(java.lang.StringBuilder);
    Code:
       0: aload_1
       1: aload_0
       2: invokevirtual #14                 // Method java/lang/Object.getClass:()Ljava/lang/Class;
       5: invokevirtual #15                 // Method java/lang/Class.getSimpleName:()Ljava/lang/String;
       8: invokevirtual #7                  // Method java/lang/StringBuilder.append:(Ljava/lang/String;)Ljava/lang/StringBuilder;
      11: pop
      12: aload_1
      13: ldc           #16                 // String  failedMetaServer=
      15: invokevirtual #7                  // Method java/lang/StringBuilder.append:(Ljava/lang/String;)Ljava/lang/StringBuilder;
      18: pop
      19: aload_1
      20: aload_0
      21: getfield      #17                 // Field failedMetaServer:Lorg/apache/hadoop/hbase/ServerName;
      24: invokevirtual #8                  // Method java/lang/StringBuilder.append:(Ljava/lang/Object;)Ljava/lang/StringBuilder;
      27: pop
      28: aload_1
      29: ldc           #18                 // String , splitWal=
      31: invokevirtual #7                  // Method java/lang/StringBuilder.append:(Ljava/lang/String;)Ljava/lang/StringBuilder;
      34: pop
      35: aload_1
      36: aload_0
      37: getfield      #19                 // Field shouldSplitWal:Z
      40: invokevirtual #20                 // Method java/lang/StringBuilder.append:(Z)Ljava/lang/StringBuilder;
      43: pop
      44: return

  protected void serializeStateData(org.apache.hadoop.hbase.procedure2.ProcedureStateSerializer) throws java.io.IOException;
    Code:
       0: aload_0
       1: aload_1
       2: invokespecial #21                 // Method org/apache/hadoop/hbase/procedure2/StateMachineProcedure.serializeStateData:(Lorg/apache/hadoop/hbase/procedure2/ProcedureStateSerializer;)V
       5: invokestatic  #22                 // Method org/apache/hadoop/hbase/shaded/protobuf/generated/MasterProcedureProtos$RecoverMetaStateData.newBuilder:()Lorg/apache/hadoop/hbase/shaded/protobuf/generated/MasterProcedureProtos$RecoverMetaStateData$Builder;
       8: aload_0
       9: getfield      #19                 // Field shouldSplitWal:Z
      12: invokevirtual #23                 // Method org/apache/hadoop/hbase/shaded/protobuf/generated/MasterProcedureProtos$RecoverMetaStateData$Builder.setShouldSplitWal:(Z)Lorg/apache/hadoop/hbase/shaded/protobuf/generated/MasterProcedureProtos$RecoverMetaStateData$Builder;
      15: astore_2
      16: aload_0
      17: getfield      #17                 // Field failedMetaServer:Lorg/apache/hadoop/hbase/ServerName;
      20: ifnull        35
      23: aload_2
      24: aload_0
      25: getfield      #17                 // Field failedMetaServer:Lorg/apache/hadoop/hbase/ServerName;
      28: invokestatic  #24                 // Method org/apache/hadoop/hbase/shaded/protobuf/ProtobufUtil.toServerName:(Lorg/apache/hadoop/hbase/ServerName;)Lorg/apache/hadoop/hbase/shaded/protobuf/generated/HBaseProtos$ServerName;
      31: invokevirtual #25                 // Method org/apache/hadoop/hbase/shaded/protobuf/generated/MasterProcedureProtos$RecoverMetaStateData$Builder.setFailedMetaServer:(Lorg/apache/hadoop/hbase/shaded/protobuf/generated/HBaseProtos$ServerName;)Lorg/apache/hadoop/hbase/shaded/protobuf/generated/MasterProcedureProtos$RecoverMetaStateData$Builder;
      34: pop
      35: aload_2
      36: aload_0
      37: getfield      #26                 // Field replicaId:I
      40: invokevirtual #27                 // Method org/apache/hadoop/hbase/shaded/protobuf/generated/MasterProcedureProtos$RecoverMetaStateData$Builder.setReplicaId:(I)Lorg/apache/hadoop/hbase/shaded/protobuf/generated/MasterProcedureProtos$RecoverMetaStateData$Builder;
      43: pop
      44: aload_1
      45: aload_2
      46: invokevirtual #28                 // Method org/apache/hadoop/hbase/shaded/protobuf/generated/MasterProcedureProtos$RecoverMetaStateData$Builder.build:()Lorg/apache/hadoop/hbase/shaded/protobuf/generated/MasterProcedureProtos$RecoverMetaStateData;
      49: invokeinterface #29,  2           // InterfaceMethod org/apache/hadoop/hbase/procedure2/ProcedureStateSerializer.serialize:(Lorg/apache/hbase/thirdparty/com/google/protobuf/Message;)V
      54: return

  protected void deserializeStateData(org.apache.hadoop.hbase.procedure2.ProcedureStateSerializer) throws java.io.IOException;
    Code:
       0: aload_0
       1: aload_1
       2: invokespecial #30                 // Method org/apache/hadoop/hbase/procedure2/StateMachineProcedure.deserializeStateData:(Lorg/apache/hadoop/hbase/procedure2/ProcedureStateSerializer;)V
       5: aload_1
       6: ldc           #31                 // class org/apache/hadoop/hbase/shaded/protobuf/generated/MasterProcedureProtos$RecoverMetaStateData
       8: invokeinterface #32,  2           // InterfaceMethod org/apache/hadoop/hbase/procedure2/ProcedureStateSerializer.deserialize:(Ljava/lang/Class;)Lorg/apache/hbase/thirdparty/com/google/protobuf/Message;
      13: checkcast     #31                 // class org/apache/hadoop/hbase/shaded/protobuf/generated/MasterProcedureProtos$RecoverMetaStateData
      16: astore_2
      17: aload_0
      18: aload_2
      19: invokevirtual #33                 // Method org/apache/hadoop/hbase/shaded/protobuf/generated/MasterProcedureProtos$RecoverMetaStateData.hasShouldSplitWal:()Z
      22: ifeq          36
      25: aload_2
      26: invokevirtual #34                 // Method org/apache/hadoop/hbase/shaded/protobuf/generated/MasterProcedureProtos$RecoverMetaStateData.getShouldSplitWal:()Z
      29: ifeq          36
      32: iconst_1
      33: goto          37
      36: iconst_0
      37: putfield      #19                 // Field shouldSplitWal:Z
      40: aload_0
      41: aload_2
      42: invokevirtual #35                 // Method org/apache/hadoop/hbase/shaded/protobuf/generated/MasterProcedureProtos$RecoverMetaStateData.hasFailedMetaServer:()Z
      45: ifeq          58
      48: aload_2
      49: invokevirtual #36                 // Method org/apache/hadoop/hbase/shaded/protobuf/generated/MasterProcedureProtos$RecoverMetaStateData.getFailedMetaServer:()Lorg/apache/hadoop/hbase/shaded/protobuf/generated/HBaseProtos$ServerName;
      52: invokestatic  #37                 // Method org/apache/hadoop/hbase/shaded/protobuf/ProtobufUtil.toServerName:(Lorg/apache/hadoop/hbase/shaded/protobuf/generated/HBaseProtos$ServerName;)Lorg/apache/hadoop/hbase/ServerName;
      55: goto          59
      58: aconst_null
      59: putfield      #17                 // Field failedMetaServer:Lorg/apache/hadoop/hbase/ServerName;
      62: aload_0
      63: aload_2
      64: invokevirtual #38                 // Method org/apache/hadoop/hbase/shaded/protobuf/generated/MasterProcedureProtos$RecoverMetaStateData.hasReplicaId:()Z
      67: ifeq          77
      70: aload_2
      71: invokevirtual #39                 // Method org/apache/hadoop/hbase/shaded/protobuf/generated/MasterProcedureProtos$RecoverMetaStateData.getReplicaId:()I
      74: goto          78
      77: iconst_0
      78: putfield      #26                 // Field replicaId:I
      81: return

  protected java.lang.Object getInitialState();
    Code:
       0: aload_0
       1: invokevirtual #41                 // Method getInitialState:()Lorg/apache/hadoop/hbase/shaded/protobuf/generated/MasterProcedureProtos$RecoverMetaState;
       4: areturn

  protected int getStateId(java.lang.Object);
    Code:
       0: aload_0
       1: aload_1
       2: checkcast     #42                 // class org/apache/hadoop/hbase/shaded/protobuf/generated/MasterProcedureProtos$RecoverMetaState
       5: invokevirtual #43                 // Method getStateId:(Lorg/apache/hadoop/hbase/shaded/protobuf/generated/MasterProcedureProtos$RecoverMetaState;)I
       8: ireturn

  protected java.lang.Object getState(int);
    Code:
       0: aload_0
       1: iload_1
       2: invokevirtual #44                 // Method getState:(I)Lorg/apache/hadoop/hbase/shaded/protobuf/generated/MasterProcedureProtos$RecoverMetaState;
       5: areturn

  protected void rollbackState(java.lang.Object, java.lang.Object) throws java.io.IOException, java.lang.InterruptedException;
    Code:
       0: aload_0
       1: aload_1
       2: checkcast     #45                 // class org/apache/hadoop/hbase/master/procedure/MasterProcedureEnv
       5: aload_2
       6: checkcast     #42                 // class org/apache/hadoop/hbase/shaded/protobuf/generated/MasterProcedureProtos$RecoverMetaState
       9: invokevirtual #46                 // Method rollbackState:(Lorg/apache/hadoop/hbase/master/procedure/MasterProcedureEnv;Lorg/apache/hadoop/hbase/shaded/protobuf/generated/MasterProcedureProtos$RecoverMetaState;)V
      12: return

  protected org.apache.hadoop.hbase.procedure2.StateMachineProcedure$Flow executeFromState(java.lang.Object, java.lang.Object) throws org.apache.hadoop.hbase.procedure2.ProcedureSuspendedException, org.apache.hadoop.hbase.procedure2.ProcedureYieldException, java.lang.InterruptedException;
    Code:
       0: aload_0
       1: aload_1
       2: checkcast     #45                 // class org/apache/hadoop/hbase/master/procedure/MasterProcedureEnv
       5: aload_2
       6: checkcast     #42                 // class org/apache/hadoop/hbase/shaded/protobuf/generated/MasterProcedureProtos$RecoverMetaState
       9: invokevirtual #47                 // Method executeFromState:(Lorg/apache/hadoop/hbase/master/procedure/MasterProcedureEnv;Lorg/apache/hadoop/hbase/shaded/protobuf/generated/MasterProcedureProtos$RecoverMetaState;)Lorg/apache/hadoop/hbase/procedure2/StateMachineProcedure$Flow;
      12: areturn

  static {};
    Code:
       0: ldc           #48                 // class org/apache/hadoop/hbase/master/procedure/RecoverMetaProcedure
       2: invokestatic  #49                 // Method org/slf4j/LoggerFactory.getLogger:(Ljava/lang/Class;)Lorg/slf4j/Logger;
       5: putstatic     #50                 // Field LOG:Lorg/slf4j/Logger;
       8: return
}
