Compiled from "RecoverStandbyProcedure.java"
public class org.apache.hadoop.hbase.master.replication.RecoverStandbyProcedure extends org.apache.hadoop.hbase.master.replication.AbstractPeerNoLockProcedure<org.apache.hadoop.hbase.shaded.protobuf.generated.MasterProcedureProtos$RecoverStandbyState> {
  public org.apache.hadoop.hbase.master.replication.RecoverStandbyProcedure();
    Code:
       0: aload_0
       1: invokespecial #1                  // Method org/apache/hadoop/hbase/master/replication/AbstractPeerNoLockProcedure."<init>":()V
       4: return

  public org.apache.hadoop.hbase.master.replication.RecoverStandbyProcedure(java.lang.String, boolean);
    Code:
       0: aload_0
       1: aload_1
       2: invokespecial #2                  // Method org/apache/hadoop/hbase/master/replication/AbstractPeerNoLockProcedure."<init>":(Ljava/lang/String;)V
       5: aload_0
       6: iload_2
       7: putfield      #3                  // Field serial:Z
      10: return

  protected org.apache.hadoop.hbase.procedure2.StateMachineProcedure$Flow executeFromState(org.apache.hadoop.hbase.master.procedure.MasterProcedureEnv, org.apache.hadoop.hbase.shaded.protobuf.generated.MasterProcedureProtos$RecoverStandbyState) throws org.apache.hadoop.hbase.procedure2.ProcedureSuspendedException, org.apache.hadoop.hbase.procedure2.ProcedureYieldException, java.lang.InterruptedException;
    Code:
       0: aload_1
       1: invokevirtual #4                  // Method org/apache/hadoop/hbase/master/procedure/MasterProcedureEnv.getMasterServices:()Lorg/apache/hadoop/hbase/master/MasterServices;
       4: invokeinterface #5,  1            // InterfaceMethod org/apache/hadoop/hbase/master/MasterServices.getSyncReplicationReplayWALManager:()Lorg/apache/hadoop/hbase/master/replication/SyncReplicationReplayWALManager;
       9: astore_3
      10: getstatic     #6                  // Field org/apache/hadoop/hbase/master/replication/RecoverStandbyProcedure$1.$SwitchMap$org$apache$hadoop$hbase$shaded$protobuf$generated$MasterProcedureProtos$RecoverStandbyState:[I
      13: aload_2
      14: invokevirtual #7                  // Method org/apache/hadoop/hbase/shaded/protobuf/generated/MasterProcedureProtos$RecoverStandbyState.ordinal:()I
      17: iaload
      18: tableswitch   { // 1 to 5
                     1: 52
                     2: 104
                     3: 123
                     4: 139
                     5: 158
               default: 199
          }
      52: aload_3
      53: aload_0
      54: getfield      #8                  // Field peerId:Ljava/lang/String;
      57: invokevirtual #9                  // Method org/apache/hadoop/hbase/master/replication/SyncReplicationReplayWALManager.renameToPeerReplayWALDir:(Ljava/lang/String;)V
      60: goto          93
      63: astore        4
      65: getstatic     #11                 // Field LOG:Lorg/slf4j/Logger;
      68: ldc           #12                 // String Failed to rename remote wal dir for peer id={}
      70: aload_0
      71: getfield      #8                  // Field peerId:Ljava/lang/String;
      74: aload         4
      76: invokeinterface #13,  4           // InterfaceMethod org/slf4j/Logger.warn:(Ljava/lang/String;Ljava/lang/Object;Ljava/lang/Object;)V
      81: aload_0
      82: ldc           #14                 // String master-recover-standby
      84: aload         4
      86: invokevirtual #15                 // Method setFailure:(Ljava/lang/String;Ljava/lang/Throwable;)V
      89: getstatic     #16                 // Field org/apache/hadoop/hbase/procedure2/StateMachineProcedure$Flow.NO_MORE_STATE:Lorg/apache/hadoop/hbase/procedure2/StateMachineProcedure$Flow;
      92: areturn
      93: aload_0
      94: getstatic     #17                 // Field org/apache/hadoop/hbase/shaded/protobuf/generated/MasterProcedureProtos$RecoverStandbyState.REGISTER_PEER_TO_WORKER_STORAGE:Lorg/apache/hadoop/hbase/shaded/protobuf/generated/MasterProcedureProtos$RecoverStandbyState;
      97: invokevirtual #18                 // Method setNextState:(Ljava/lang/Object;)V
     100: getstatic     #19                 // Field org/apache/hadoop/hbase/procedure2/StateMachineProcedure$Flow.HAS_MORE_STATE:Lorg/apache/hadoop/hbase/procedure2/StateMachineProcedure$Flow;
     103: areturn
     104: aload_3
     105: aload_0
     106: getfield      #8                  // Field peerId:Ljava/lang/String;
     109: invokevirtual #20                 // Method org/apache/hadoop/hbase/master/replication/SyncReplicationReplayWALManager.registerPeer:(Ljava/lang/String;)V
     112: aload_0
     113: getstatic     #21                 // Field org/apache/hadoop/hbase/shaded/protobuf/generated/MasterProcedureProtos$RecoverStandbyState.DISPATCH_WALS:Lorg/apache/hadoop/hbase/shaded/protobuf/generated/MasterProcedureProtos$RecoverStandbyState;
     116: invokevirtual #18                 // Method setNextState:(Ljava/lang/Object;)V
     119: getstatic     #19                 // Field org/apache/hadoop/hbase/procedure2/StateMachineProcedure$Flow.HAS_MORE_STATE:Lorg/apache/hadoop/hbase/procedure2/StateMachineProcedure$Flow;
     122: areturn
     123: aload_0
     124: aload_3
     125: invokespecial #22                 // Method dispathWals:(Lorg/apache/hadoop/hbase/master/replication/SyncReplicationReplayWALManager;)V
     128: aload_0
     129: getstatic     #23                 // Field org/apache/hadoop/hbase/shaded/protobuf/generated/MasterProcedureProtos$RecoverStandbyState.UNREGISTER_PEER_FROM_WORKER_STORAGE:Lorg/apache/hadoop/hbase/shaded/protobuf/generated/MasterProcedureProtos$RecoverStandbyState;
     132: invokevirtual #18                 // Method setNextState:(Ljava/lang/Object;)V
     135: getstatic     #19                 // Field org/apache/hadoop/hbase/procedure2/StateMachineProcedure$Flow.HAS_MORE_STATE:Lorg/apache/hadoop/hbase/procedure2/StateMachineProcedure$Flow;
     138: areturn
     139: aload_3
     140: aload_0
     141: getfield      #8                  // Field peerId:Ljava/lang/String;
     144: invokevirtual #24                 // Method org/apache/hadoop/hbase/master/replication/SyncReplicationReplayWALManager.unregisterPeer:(Ljava/lang/String;)V
     147: aload_0
     148: getstatic     #25                 // Field org/apache/hadoop/hbase/shaded/protobuf/generated/MasterProcedureProtos$RecoverStandbyState.SNAPSHOT_SYNC_REPLICATION_WALS_DIR:Lorg/apache/hadoop/hbase/shaded/protobuf/generated/MasterProcedureProtos$RecoverStandbyState;
     151: invokevirtual #18                 // Method setNextState:(Ljava/lang/Object;)V
     154: getstatic     #19                 // Field org/apache/hadoop/hbase/procedure2/StateMachineProcedure$Flow.HAS_MORE_STATE:Lorg/apache/hadoop/hbase/procedure2/StateMachineProcedure$Flow;
     157: areturn
     158: aload_3
     159: aload_0
     160: getfield      #8                  // Field peerId:Ljava/lang/String;
     163: invokevirtual #26                 // Method org/apache/hadoop/hbase/master/replication/SyncReplicationReplayWALManager.renameToPeerSnapshotWALDir:(Ljava/lang/String;)V
     166: goto          195
     169: astore        4
     171: getstatic     #11                 // Field LOG:Lorg/slf4j/Logger;
     174: ldc           #27                 // String Failed to cleanup replay wals dir for peer id={}, , retry
     176: aload_0
     177: getfield      #8                  // Field peerId:Ljava/lang/String;
     180: aload         4
     182: invokeinterface #13,  4           // InterfaceMethod org/slf4j/Logger.warn:(Ljava/lang/String;Ljava/lang/Object;Ljava/lang/Object;)V
     187: new           #28                 // class org/apache/hadoop/hbase/procedure2/ProcedureYieldException
     190: dup
     191: invokespecial #29                 // Method org/apache/hadoop/hbase/procedure2/ProcedureYieldException."<init>":()V
     194: athrow
     195: getstatic     #16                 // Field org/apache/hadoop/hbase/procedure2/StateMachineProcedure$Flow.NO_MORE_STATE:Lorg/apache/hadoop/hbase/procedure2/StateMachineProcedure$Flow;
     198: areturn
     199: new           #30                 // class java/lang/UnsupportedOperationException
     202: dup
     203: new           #31                 // class java/lang/StringBuilder
     206: dup
     207: invokespecial #32                 // Method java/lang/StringBuilder."<init>":()V
     210: ldc           #33                 // String unhandled state=
     212: invokevirtual #34                 // Method java/lang/StringBuilder.append:(Ljava/lang/String;)Ljava/lang/StringBuilder;
     215: aload_2
     216: invokevirtual #35                 // Method java/lang/StringBuilder.append:(Ljava/lang/Object;)Ljava/lang/StringBuilder;
     219: invokevirtual #36                 // Method java/lang/StringBuilder.toString:()Ljava/lang/String;
     222: invokespecial #37                 // Method java/lang/UnsupportedOperationException."<init>":(Ljava/lang/String;)V
     225: athrow
    Exception table:
       from    to  target type
          52    60    63   Class java/io/IOException
         158   166   169   Class java/io/IOException

  protected org.apache.hadoop.hbase.shaded.protobuf.generated.MasterProcedureProtos$RecoverStandbyState getState(int);
    Code:
       0: iload_1
       1: invokestatic  #47                 // Method org/apache/hadoop/hbase/shaded/protobuf/generated/MasterProcedureProtos$RecoverStandbyState.forNumber:(I)Lorg/apache/hadoop/hbase/shaded/protobuf/generated/MasterProcedureProtos$RecoverStandbyState;
       4: areturn

  protected int getStateId(org.apache.hadoop.hbase.shaded.protobuf.generated.MasterProcedureProtos$RecoverStandbyState);
    Code:
       0: aload_1
       1: invokevirtual #48                 // Method org/apache/hadoop/hbase/shaded/protobuf/generated/MasterProcedureProtos$RecoverStandbyState.getNumber:()I
       4: ireturn

  protected org.apache.hadoop.hbase.shaded.protobuf.generated.MasterProcedureProtos$RecoverStandbyState getInitialState();
    Code:
       0: getstatic     #49                 // Field org/apache/hadoop/hbase/shaded/protobuf/generated/MasterProcedureProtos$RecoverStandbyState.RENAME_SYNC_REPLICATION_WALS_DIR:Lorg/apache/hadoop/hbase/shaded/protobuf/generated/MasterProcedureProtos$RecoverStandbyState;
       3: areturn

  public org.apache.hadoop.hbase.master.procedure.PeerProcedureInterface$PeerOperationType getPeerOperationType();
    Code:
       0: getstatic     #50                 // Field org/apache/hadoop/hbase/master/procedure/PeerProcedureInterface$PeerOperationType.RECOVER_STANDBY:Lorg/apache/hadoop/hbase/master/procedure/PeerProcedureInterface$PeerOperationType;
       3: areturn

  protected void serializeStateData(org.apache.hadoop.hbase.procedure2.ProcedureStateSerializer) throws java.io.IOException;
    Code:
       0: aload_0
       1: aload_1
       2: invokespecial #51                 // Method org/apache/hadoop/hbase/master/replication/AbstractPeerNoLockProcedure.serializeStateData:(Lorg/apache/hadoop/hbase/procedure2/ProcedureStateSerializer;)V
       5: aload_1
       6: invokestatic  #52                 // Method org/apache/hadoop/hbase/shaded/protobuf/generated/MasterProcedureProtos$RecoverStandbyStateData.newBuilder:()Lorg/apache/hadoop/hbase/shaded/protobuf/generated/MasterProcedureProtos$RecoverStandbyStateData$Builder;
       9: aload_0
      10: getfield      #3                  // Field serial:Z
      13: invokevirtual #53                 // Method org/apache/hadoop/hbase/shaded/protobuf/generated/MasterProcedureProtos$RecoverStandbyStateData$Builder.setSerial:(Z)Lorg/apache/hadoop/hbase/shaded/protobuf/generated/MasterProcedureProtos$RecoverStandbyStateData$Builder;
      16: invokevirtual #54                 // Method org/apache/hadoop/hbase/shaded/protobuf/generated/MasterProcedureProtos$RecoverStandbyStateData$Builder.build:()Lorg/apache/hadoop/hbase/shaded/protobuf/generated/MasterProcedureProtos$RecoverStandbyStateData;
      19: invokeinterface #55,  2           // InterfaceMethod org/apache/hadoop/hbase/procedure2/ProcedureStateSerializer.serialize:(Lorg/apache/hbase/thirdparty/com/google/protobuf/Message;)V
      24: return

  protected void deserializeStateData(org.apache.hadoop.hbase.procedure2.ProcedureStateSerializer) throws java.io.IOException;
    Code:
       0: aload_0
       1: aload_1
       2: invokespecial #56                 // Method org/apache/hadoop/hbase/master/replication/AbstractPeerNoLockProcedure.deserializeStateData:(Lorg/apache/hadoop/hbase/procedure2/ProcedureStateSerializer;)V
       5: aload_1
       6: ldc           #57                 // class org/apache/hadoop/hbase/shaded/protobuf/generated/MasterProcedureProtos$RecoverStandbyStateData
       8: invokeinterface #58,  2           // InterfaceMethod org/apache/hadoop/hbase/procedure2/ProcedureStateSerializer.deserialize:(Ljava/lang/Class;)Lorg/apache/hbase/thirdparty/com/google/protobuf/Message;
      13: checkcast     #57                 // class org/apache/hadoop/hbase/shaded/protobuf/generated/MasterProcedureProtos$RecoverStandbyStateData
      16: astore_2
      17: aload_0
      18: aload_2
      19: invokevirtual #59                 // Method org/apache/hadoop/hbase/shaded/protobuf/generated/MasterProcedureProtos$RecoverStandbyStateData.getSerial:()Z
      22: putfield      #3                  // Field serial:Z
      25: return

  protected void afterReplay(org.apache.hadoop.hbase.master.procedure.MasterProcedureEnv);
    Code:
       0: getstatic     #6                  // Field org/apache/hadoop/hbase/master/replication/RecoverStandbyProcedure$1.$SwitchMap$org$apache$hadoop$hbase$shaded$protobuf$generated$MasterProcedureProtos$RecoverStandbyState:[I
       3: aload_0
       4: invokevirtual #60                 // Method getCurrentState:()Ljava/lang/Object;
       7: checkcast     #61                 // class org/apache/hadoop/hbase/shaded/protobuf/generated/MasterProcedureProtos$RecoverStandbyState
      10: invokevirtual #7                  // Method org/apache/hadoop/hbase/shaded/protobuf/generated/MasterProcedureProtos$RecoverStandbyState.ordinal:()I
      13: iaload
      14: lookupswitch  { // 2
                     3: 40
                     4: 40
               default: 59
          }
      40: aload_1
      41: invokevirtual #4                  // Method org/apache/hadoop/hbase/master/procedure/MasterProcedureEnv.getMasterServices:()Lorg/apache/hadoop/hbase/master/MasterServices;
      44: invokeinterface #5,  1            // InterfaceMethod org/apache/hadoop/hbase/master/MasterServices.getSyncReplicationReplayWALManager:()Lorg/apache/hadoop/hbase/master/replication/SyncReplicationReplayWALManager;
      49: aload_0
      50: getfield      #8                  // Field peerId:Ljava/lang/String;
      53: invokevirtual #20                 // Method org/apache/hadoop/hbase/master/replication/SyncReplicationReplayWALManager.registerPeer:(Ljava/lang/String;)V
      56: goto          59
      59: return

  protected java.lang.Object getInitialState();
    Code:
       0: aload_0
       1: invokevirtual #62                 // Method getInitialState:()Lorg/apache/hadoop/hbase/shaded/protobuf/generated/MasterProcedureProtos$RecoverStandbyState;
       4: areturn

  protected int getStateId(java.lang.Object);
    Code:
       0: aload_0
       1: aload_1
       2: checkcast     #61                 // class org/apache/hadoop/hbase/shaded/protobuf/generated/MasterProcedureProtos$RecoverStandbyState
       5: invokevirtual #63                 // Method getStateId:(Lorg/apache/hadoop/hbase/shaded/protobuf/generated/MasterProcedureProtos$RecoverStandbyState;)I
       8: ireturn

  protected java.lang.Object getState(int);
    Code:
       0: aload_0
       1: iload_1
       2: invokevirtual #64                 // Method getState:(I)Lorg/apache/hadoop/hbase/shaded/protobuf/generated/MasterProcedureProtos$RecoverStandbyState;
       5: areturn

  protected org.apache.hadoop.hbase.procedure2.StateMachineProcedure$Flow executeFromState(java.lang.Object, java.lang.Object) throws org.apache.hadoop.hbase.procedure2.ProcedureSuspendedException, org.apache.hadoop.hbase.procedure2.ProcedureYieldException, java.lang.InterruptedException;
    Code:
       0: aload_0
       1: aload_1
       2: checkcast     #65                 // class org/apache/hadoop/hbase/master/procedure/MasterProcedureEnv
       5: aload_2
       6: checkcast     #61                 // class org/apache/hadoop/hbase/shaded/protobuf/generated/MasterProcedureProtos$RecoverStandbyState
       9: invokevirtual #66                 // Method executeFromState:(Lorg/apache/hadoop/hbase/master/procedure/MasterProcedureEnv;Lorg/apache/hadoop/hbase/shaded/protobuf/generated/MasterProcedureProtos$RecoverStandbyState;)Lorg/apache/hadoop/hbase/procedure2/StateMachineProcedure$Flow;
      12: areturn

  protected void afterReplay(java.lang.Object);
    Code:
       0: aload_0
       1: aload_1
       2: checkcast     #65                 // class org/apache/hadoop/hbase/master/procedure/MasterProcedureEnv
       5: invokevirtual #67                 // Method afterReplay:(Lorg/apache/hadoop/hbase/master/procedure/MasterProcedureEnv;)V
       8: return

  static {};
    Code:
       0: ldc           #73                 // class org/apache/hadoop/hbase/master/replication/RecoverStandbyProcedure
       2: invokestatic  #74                 // Method org/slf4j/LoggerFactory.getLogger:(Ljava/lang/Class;)Lorg/slf4j/Logger;
       5: putstatic     #11                 // Field LOG:Lorg/slf4j/Logger;
       8: return
}
