Compiled from "RedundantKVGenerator.java"
public class org.apache.hadoop.hbase.util.RedundantKVGenerator {
  static byte[] DEFAULT_COMMON_PREFIX;

  static int DEFAULT_NUMBER_OF_ROW_PREFIXES;

  static int DEFAULT_AVERAGE_PREFIX_LENGTH;

  static int DEFAULT_PREFIX_LENGTH_VARIANCE;

  static int DEFAULT_AVERAGE_SUFFIX_LENGTH;

  static int DEFAULT_SUFFIX_LENGTH_VARIANCE;

  static int DEFAULT_NUMBER_OF_ROW;

  static float DEFAULT_CHANCE_FOR_SAME_QUALIFIER;

  static float DEFAULT_CHANCE_FOR_SIMILIAR_QUALIFIER;

  static int DEFAULT_AVERAGE_QUALIFIER_LENGTH;

  static int DEFAULT_QUALIFIER_LENGTH_VARIANCE;

  static int DEFAULT_COLUMN_FAMILY_LENGTH;

  static int DEFAULT_VALUE_LENGTH;

  static float DEFAULT_CHANCE_FOR_ZERO_VALUE;

  static int DEFAULT_BASE_TIMESTAMP_DIVIDE;

  static int DEFAULT_TIMESTAMP_DIFF_SIZE;

  public org.apache.hadoop.hbase.util.RedundantKVGenerator();
    Code:
       0: aload_0
       1: new           #1                  // class java/util/Random
       4: dup
       5: ldc2_w        #2                  // long 42l
       8: invokespecial #4                  // Method java/util/Random."<init>":(J)V
      11: getstatic     #5                  // Field DEFAULT_NUMBER_OF_ROW_PREFIXES:I
      14: getstatic     #6                  // Field DEFAULT_AVERAGE_PREFIX_LENGTH:I
      17: getstatic     #7                  // Field DEFAULT_PREFIX_LENGTH_VARIANCE:I
      20: getstatic     #8                  // Field DEFAULT_AVERAGE_SUFFIX_LENGTH:I
      23: getstatic     #9                  // Field DEFAULT_SUFFIX_LENGTH_VARIANCE:I
      26: getstatic     #10                 // Field DEFAULT_NUMBER_OF_ROW:I
      29: getstatic     #11                 // Field DEFAULT_CHANCE_FOR_SAME_QUALIFIER:F
      32: getstatic     #12                 // Field DEFAULT_CHANCE_FOR_SIMILIAR_QUALIFIER:F
      35: getstatic     #13                 // Field DEFAULT_AVERAGE_QUALIFIER_LENGTH:I
      38: getstatic     #14                 // Field DEFAULT_QUALIFIER_LENGTH_VARIANCE:I
      41: getstatic     #15                 // Field DEFAULT_COLUMN_FAMILY_LENGTH:I
      44: getstatic     #16                 // Field DEFAULT_VALUE_LENGTH:I
      47: getstatic     #17                 // Field DEFAULT_CHANCE_FOR_ZERO_VALUE:F
      50: getstatic     #18                 // Field DEFAULT_BASE_TIMESTAMP_DIVIDE:I
      53: getstatic     #19                 // Field DEFAULT_TIMESTAMP_DIFF_SIZE:I
      56: invokespecial #20                 // Method "<init>":(Ljava/util/Random;IIIIIIFFIIIIFII)V
      59: return

  public org.apache.hadoop.hbase.util.RedundantKVGenerator(java.util.Random, int, int, int, int, int, int, float, float, int, int, int, int, float, int, int);
    Code:
       0: aload_0
       1: invokespecial #21                 // Method java/lang/Object."<init>":()V
       4: aload_0
       5: bipush        6
       7: putfield      #22                 // Field averagePrefixLength:I
      10: aload_0
      11: iconst_3
      12: putfield      #23                 // Field prefixLengthVariance:I
      15: aload_0
      16: iconst_3
      17: putfield      #24                 // Field averageSuffixLength:I
      20: aload_0
      21: iconst_3
      22: putfield      #25                 // Field suffixLengthVariance:I
      25: aload_0
      26: sipush        500
      29: putfield      #26                 // Field numberOfRows:I
      32: aload_0
      33: ldc           #27                 // float 0.5f
      35: putfield      #28                 // Field chanceForSameQualifier:F
      38: aload_0
      39: ldc           #29                 // float 0.4f
      41: putfield      #30                 // Field chanceForSimilarQualifier:F
      44: aload_0
      45: bipush        9
      47: putfield      #31                 // Field averageQualifierLength:I
      50: aload_0
      51: iconst_3
      52: putfield      #32                 // Field qualifierLengthVariance:I
      55: aload_0
      56: bipush        9
      58: putfield      #33                 // Field columnFamilyLength:I
      61: aload_0
      62: bipush        8
      64: putfield      #34                 // Field valueLength:I
      67: aload_0
      68: ldc           #27                 // float 0.5f
      70: putfield      #35                 // Field chanceForZeroValue:F
      73: aload_0
      74: ldc           #36                 // int 1000000
      76: putfield      #37                 // Field baseTimestampDivide:I
      79: aload_0
      80: ldc           #38                 // int 100000000
      82: putfield      #39                 // Field timestampDiffSize:I
      85: aload_0
      86: aload_1
      87: putfield      #40                 // Field randomizer:Ljava/util/Random;
      90: aload_0
      91: getstatic     #41                 // Field DEFAULT_COMMON_PREFIX:[B
      94: putfield      #42                 // Field commonPrefix:[B
      97: aload_0
      98: iload_2
      99: putfield      #43                 // Field numberOfRowPrefixes:I
     102: aload_0
     103: iload_3
     104: putfield      #22                 // Field averagePrefixLength:I
     107: aload_0
     108: iload         4
     110: putfield      #23                 // Field prefixLengthVariance:I
     113: aload_0
     114: iload         5
     116: putfield      #24                 // Field averageSuffixLength:I
     119: aload_0
     120: iload         6
     122: putfield      #25                 // Field suffixLengthVariance:I
     125: aload_0
     126: iload         7
     128: putfield      #26                 // Field numberOfRows:I
     131: aload_0
     132: fload         8
     134: putfield      #28                 // Field chanceForSameQualifier:F
     137: aload_0
     138: fload         9
     140: putfield      #30                 // Field chanceForSimilarQualifier:F
     143: aload_0
     144: iload         10
     146: putfield      #31                 // Field averageQualifierLength:I
     149: aload_0
     150: iload         11
     152: putfield      #32                 // Field qualifierLengthVariance:I
     155: aload_0
     156: iload         12
     158: putfield      #33                 // Field columnFamilyLength:I
     161: aload_0
     162: iload         13
     164: putfield      #34                 // Field valueLength:I
     167: aload_0
     168: fload         14
     170: putfield      #35                 // Field chanceForZeroValue:F
     173: aload_0
     174: iload         15
     176: putfield      #37                 // Field baseTimestampDivide:I
     179: aload_0
     180: iload         16
     182: putfield      #39                 // Field timestampDiffSize:I
     185: return

  public java.util.List<org.apache.hadoop.hbase.KeyValue> generateTestKeyValues(int);
    Code:
       0: aload_0
       1: iload_1
       2: iconst_0
       3: invokevirtual #53                 // Method generateTestKeyValues:(IZ)Ljava/util/List;
       6: areturn

  public java.util.List<org.apache.hadoop.hbase.KeyValue> generateTestKeyValues(int, boolean);
    Code:
       0: new           #44                 // class java/util/ArrayList
       3: dup
       4: invokespecial #45                 // Method java/util/ArrayList."<init>":()V
       7: astore_3
       8: aload_0
       9: invokespecial #54                 // Method generateRows:()Ljava/util/List;
      12: astore        4
      14: new           #55                 // class java/util/HashMap
      17: dup
      18: invokespecial #56                 // Method java/util/HashMap."<init>":()V
      21: astore        5
      23: aload_0
      24: getfield      #57                 // Field family:[B
      27: ifnonnull     51
      30: aload_0
      31: aload_0
      32: getfield      #33                 // Field columnFamilyLength:I
      35: newarray       byte
      37: putfield      #57                 // Field family:[B
      40: aload_0
      41: getfield      #40                 // Field randomizer:Ljava/util/Random;
      44: aload_0
      45: getfield      #57                 // Field family:[B
      48: invokevirtual #48                 // Method java/util/Random.nextBytes:([B)V
      51: aload_0
      52: getfield      #40                 // Field randomizer:Ljava/util/Random;
      55: invokevirtual #58                 // Method java/util/Random.nextInt:()I
      58: invokestatic  #59                 // Method java/lang/Math.abs:(I)I
      61: aload_0
      62: getfield      #37                 // Field baseTimestampDivide:I
      65: idiv
      66: i2l
      67: lstore        6
      69: aload_0
      70: getfield      #34                 // Field valueLength:I
      73: newarray       byte
      75: astore        8
      77: iconst_0
      78: istore        9
      80: iload         9
      82: iload_1
      83: if_icmpge     594
      86: lload         6
      88: lstore        10
      90: aload_0
      91: getfield      #39                 // Field timestampDiffSize:I
      94: ifle          114
      97: lload         10
      99: aload_0
     100: getfield      #40                 // Field randomizer:Ljava/util/Random;
     103: aload_0
     104: getfield      #39                 // Field timestampDiffSize:I
     107: invokevirtual #47                 // Method java/util/Random.nextInt:(I)I
     110: i2l
     111: ladd
     112: lstore        10
     114: aload_0
     115: getfield      #40                 // Field randomizer:Ljava/util/Random;
     118: aload         4
     120: invokeinterface #49,  1           // InterfaceMethod java/util/List.size:()I
     125: invokevirtual #47                 // Method java/util/Random.nextInt:(I)I
     128: invokestatic  #60                 // Method java/lang/Integer.valueOf:(I)Ljava/lang/Integer;
     131: astore        12
     133: aload         4
     135: aload         12
     137: invokevirtual #61                 // Method java/lang/Integer.intValue:()I
     140: invokeinterface #50,  2           // InterfaceMethod java/util/List.get:(I)Ljava/lang/Object;
     145: checkcast     #51                 // class "[B"
     148: astore        13
     150: aload_0
     151: getfield      #40                 // Field randomizer:Ljava/util/Random;
     154: invokevirtual #62                 // Method java/util/Random.nextFloat:()F
     157: fstore        15
     159: aload         5
     161: aload         12
     163: invokeinterface #63,  2           // InterfaceMethod java/util/Map.containsKey:(Ljava/lang/Object;)Z
     168: ifeq          186
     171: fload         15
     173: aload_0
     174: getfield      #28                 // Field chanceForSameQualifier:F
     177: aload_0
     178: getfield      #30                 // Field chanceForSimilarQualifier:F
     181: fadd
     182: fcmpl
     183: ifle          284
     186: aload_0
     187: getfield      #31                 // Field averageQualifierLength:I
     190: istore        16
     192: iload         16
     194: aload_0
     195: getfield      #40                 // Field randomizer:Ljava/util/Random;
     198: iconst_2
     199: aload_0
     200: getfield      #32                 // Field qualifierLengthVariance:I
     203: imul
     204: iconst_1
     205: iadd
     206: invokevirtual #47                 // Method java/util/Random.nextInt:(I)I
     209: aload_0
     210: getfield      #32                 // Field qualifierLengthVariance:I
     213: isub
     214: iadd
     215: istore        16
     217: iload         16
     219: newarray       byte
     221: astore        14
     223: aload_0
     224: getfield      #40                 // Field randomizer:Ljava/util/Random;
     227: aload         14
     229: invokevirtual #48                 // Method java/util/Random.nextBytes:([B)V
     232: aload         5
     234: aload         12
     236: invokeinterface #63,  2           // InterfaceMethod java/util/Map.containsKey:(Ljava/lang/Object;)Z
     241: ifne          261
     244: aload         5
     246: aload         12
     248: new           #44                 // class java/util/ArrayList
     251: dup
     252: invokespecial #45                 // Method java/util/ArrayList."<init>":()V
     255: invokeinterface #64,  3           // InterfaceMethod java/util/Map.put:(Ljava/lang/Object;Ljava/lang/Object;)Ljava/lang/Object;
     260: pop
     261: aload         5
     263: aload         12
     265: invokeinterface #65,  2           // InterfaceMethod java/util/Map.get:(Ljava/lang/Object;)Ljava/lang/Object;
     270: checkcast     #66                 // class java/util/List
     273: aload         14
     275: invokeinterface #46,  2           // InterfaceMethod java/util/List.add:(Ljava/lang/Object;)Z
     280: pop
     281: goto          462
     284: fload         15
     286: aload_0
     287: getfield      #28                 // Field chanceForSameQualifier:F
     290: fcmpl
     291: ifle          422
     294: aload         5
     296: aload         12
     298: invokeinterface #65,  2           // InterfaceMethod java/util/Map.get:(Ljava/lang/Object;)Ljava/lang/Object;
     303: checkcast     #66                 // class java/util/List
     306: astore        16
     308: aload         16
     310: aload_0
     311: getfield      #40                 // Field randomizer:Ljava/util/Random;
     314: aload         16
     316: invokeinterface #49,  1           // InterfaceMethod java/util/List.size:()I
     321: invokevirtual #47                 // Method java/util/Random.nextInt:(I)I
     324: invokeinterface #50,  2           // InterfaceMethod java/util/List.get:(I)Ljava/lang/Object;
     329: checkcast     #51                 // class "[B"
     332: astore        17
     334: aload         17
     336: arraylength
     337: newarray       byte
     339: astore        14
     341: aload_0
     342: getfield      #40                 // Field randomizer:Ljava/util/Random;
     345: aload         14
     347: arraylength
     348: invokevirtual #47                 // Method java/util/Random.nextInt:(I)I
     351: istore        18
     353: aload         17
     355: iconst_0
     356: aload         14
     358: iconst_0
     359: iload         18
     361: invokestatic  #67                 // Method java/lang/System.arraycopy:(Ljava/lang/Object;ILjava/lang/Object;II)V
     364: iload         18
     366: istore        19
     368: iload         19
     370: aload         14
     372: arraylength
     373: if_icmpge     399
     376: aload         14
     378: iload         19
     380: aload_0
     381: getfield      #40                 // Field randomizer:Ljava/util/Random;
     384: invokevirtual #58                 // Method java/util/Random.nextInt:()I
     387: sipush        255
     390: iand
     391: i2b
     392: bastore
     393: iinc          19, 1
     396: goto          368
     399: aload         5
     401: aload         12
     403: invokeinterface #65,  2           // InterfaceMethod java/util/Map.get:(Ljava/lang/Object;)Ljava/lang/Object;
     408: checkcast     #66                 // class java/util/List
     411: aload         14
     413: invokeinterface #46,  2           // InterfaceMethod java/util/List.add:(Ljava/lang/Object;)Z
     418: pop
     419: goto          462
     422: aload         5
     424: aload         12
     426: invokeinterface #65,  2           // InterfaceMethod java/util/Map.get:(Ljava/lang/Object;)Ljava/lang/Object;
     431: checkcast     #66                 // class java/util/List
     434: astore        16
     436: aload         16
     438: aload_0
     439: getfield      #40                 // Field randomizer:Ljava/util/Random;
     442: aload         16
     444: invokeinterface #49,  1           // InterfaceMethod java/util/List.size:()I
     449: invokevirtual #47                 // Method java/util/Random.nextInt:(I)I
     452: invokeinterface #50,  2           // InterfaceMethod java/util/List.get:(I)Ljava/lang/Object;
     457: checkcast     #51                 // class "[B"
     460: astore        14
     462: aload_0
     463: getfield      #40                 // Field randomizer:Ljava/util/Random;
     466: invokevirtual #62                 // Method java/util/Random.nextFloat:()F
     469: aload_0
     470: getfield      #35                 // Field chanceForZeroValue:F
     473: fcmpg
     474: ifge          503
     477: iconst_0
     478: istore        16
     480: iload         16
     482: aload         8
     484: arraylength
     485: if_icmpge     500
     488: aload         8
     490: iload         16
     492: iconst_0
     493: bastore
     494: iinc          16, 1
     497: goto          480
     500: goto          512
     503: aload_0
     504: getfield      #40                 // Field randomizer:Ljava/util/Random;
     507: aload         8
     509: invokevirtual #48                 // Method java/util/Random.nextBytes:([B)V
     512: iload_2
     513: ifeq          562
     516: aload_3
     517: new           #68                 // class org/apache/hadoop/hbase/KeyValue
     520: dup
     521: aload         13
     523: aload_0
     524: getfield      #57                 // Field family:[B
     527: aload         14
     529: lload         10
     531: aload         8
     533: iconst_1
     534: anewarray     #69                 // class org/apache/hadoop/hbase/Tag
     537: dup
     538: iconst_0
     539: new           #70                 // class org/apache/hadoop/hbase/ArrayBackedTag
     542: dup
     543: iconst_1
     544: ldc           #71                 // String value1
     546: invokespecial #72                 // Method org/apache/hadoop/hbase/ArrayBackedTag."<init>":(BLjava/lang/String;)V
     549: aastore
     550: invokespecial #73                 // Method org/apache/hadoop/hbase/KeyValue."<init>":([B[B[BJ[B[Lorg/apache/hadoop/hbase/Tag;)V
     553: invokeinterface #46,  2           // InterfaceMethod java/util/List.add:(Ljava/lang/Object;)Z
     558: pop
     559: goto          588
     562: aload_3
     563: new           #68                 // class org/apache/hadoop/hbase/KeyValue
     566: dup
     567: aload         13
     569: aload_0
     570: getfield      #57                 // Field family:[B
     573: aload         14
     575: lload         10
     577: aload         8
     579: invokespecial #74                 // Method org/apache/hadoop/hbase/KeyValue."<init>":([B[B[BJ[B)V
     582: invokeinterface #46,  2           // InterfaceMethod java/util/List.add:(Ljava/lang/Object;)Z
     587: pop
     588: iinc          9, 1
     591: goto          80
     594: aload_3
     595: invokestatic  #75                 // InterfaceMethod org/apache/hadoop/hbase/CellComparator.getInstance:()Lorg/apache/hadoop/hbase/CellComparator;
     598: invokestatic  #76                 // Method java/util/Collections.sort:(Ljava/util/List;Ljava/util/Comparator;)V
     601: aload_3
     602: areturn

  public java.util.List<org.apache.hadoop.hbase.Cell> generateTestExtendedOffheapKeyValues(int, boolean);
    Code:
       0: new           #44                 // class java/util/ArrayList
       3: dup
       4: invokespecial #45                 // Method java/util/ArrayList."<init>":()V
       7: astore_3
       8: aload_0
       9: invokespecial #54                 // Method generateRows:()Ljava/util/List;
      12: astore        4
      14: new           #55                 // class java/util/HashMap
      17: dup
      18: invokespecial #56                 // Method java/util/HashMap."<init>":()V
      21: astore        5
      23: aload_0
      24: getfield      #57                 // Field family:[B
      27: ifnonnull     51
      30: aload_0
      31: aload_0
      32: getfield      #33                 // Field columnFamilyLength:I
      35: newarray       byte
      37: putfield      #57                 // Field family:[B
      40: aload_0
      41: getfield      #40                 // Field randomizer:Ljava/util/Random;
      44: aload_0
      45: getfield      #57                 // Field family:[B
      48: invokevirtual #48                 // Method java/util/Random.nextBytes:([B)V
      51: aload_0
      52: getfield      #40                 // Field randomizer:Ljava/util/Random;
      55: invokevirtual #58                 // Method java/util/Random.nextInt:()I
      58: invokestatic  #59                 // Method java/lang/Math.abs:(I)I
      61: aload_0
      62: getfield      #37                 // Field baseTimestampDivide:I
      65: idiv
      66: i2l
      67: lstore        6
      69: aload_0
      70: getfield      #34                 // Field valueLength:I
      73: newarray       byte
      75: astore        8
      77: iconst_0
      78: istore        9
      80: iload         9
      82: iload_1
      83: if_icmpge     698
      86: lload         6
      88: lstore        10
      90: aload_0
      91: getfield      #39                 // Field timestampDiffSize:I
      94: ifle          114
      97: lload         10
      99: aload_0
     100: getfield      #40                 // Field randomizer:Ljava/util/Random;
     103: aload_0
     104: getfield      #39                 // Field timestampDiffSize:I
     107: invokevirtual #47                 // Method java/util/Random.nextInt:(I)I
     110: i2l
     111: ladd
     112: lstore        10
     114: aload_0
     115: getfield      #40                 // Field randomizer:Ljava/util/Random;
     118: aload         4
     120: invokeinterface #49,  1           // InterfaceMethod java/util/List.size:()I
     125: invokevirtual #47                 // Method java/util/Random.nextInt:(I)I
     128: invokestatic  #60                 // Method java/lang/Integer.valueOf:(I)Ljava/lang/Integer;
     131: astore        12
     133: aload         4
     135: aload         12
     137: invokevirtual #61                 // Method java/lang/Integer.intValue:()I
     140: invokeinterface #50,  2           // InterfaceMethod java/util/List.get:(I)Ljava/lang/Object;
     145: checkcast     #51                 // class "[B"
     148: astore        13
     150: aload_0
     151: getfield      #40                 // Field randomizer:Ljava/util/Random;
     154: invokevirtual #62                 // Method java/util/Random.nextFloat:()F
     157: fstore        15
     159: aload         5
     161: aload         12
     163: invokeinterface #63,  2           // InterfaceMethod java/util/Map.containsKey:(Ljava/lang/Object;)Z
     168: ifeq          186
     171: fload         15
     173: aload_0
     174: getfield      #28                 // Field chanceForSameQualifier:F
     177: aload_0
     178: getfield      #30                 // Field chanceForSimilarQualifier:F
     181: fadd
     182: fcmpl
     183: ifle          284
     186: aload_0
     187: getfield      #31                 // Field averageQualifierLength:I
     190: istore        16
     192: iload         16
     194: aload_0
     195: getfield      #40                 // Field randomizer:Ljava/util/Random;
     198: iconst_2
     199: aload_0
     200: getfield      #32                 // Field qualifierLengthVariance:I
     203: imul
     204: iconst_1
     205: iadd
     206: invokevirtual #47                 // Method java/util/Random.nextInt:(I)I
     209: aload_0
     210: getfield      #32                 // Field qualifierLengthVariance:I
     213: isub
     214: iadd
     215: istore        16
     217: iload         16
     219: newarray       byte
     221: astore        14
     223: aload_0
     224: getfield      #40                 // Field randomizer:Ljava/util/Random;
     227: aload         14
     229: invokevirtual #48                 // Method java/util/Random.nextBytes:([B)V
     232: aload         5
     234: aload         12
     236: invokeinterface #63,  2           // InterfaceMethod java/util/Map.containsKey:(Ljava/lang/Object;)Z
     241: ifne          261
     244: aload         5
     246: aload         12
     248: new           #44                 // class java/util/ArrayList
     251: dup
     252: invokespecial #45                 // Method java/util/ArrayList."<init>":()V
     255: invokeinterface #64,  3           // InterfaceMethod java/util/Map.put:(Ljava/lang/Object;Ljava/lang/Object;)Ljava/lang/Object;
     260: pop
     261: aload         5
     263: aload         12
     265: invokeinterface #65,  2           // InterfaceMethod java/util/Map.get:(Ljava/lang/Object;)Ljava/lang/Object;
     270: checkcast     #66                 // class java/util/List
     273: aload         14
     275: invokeinterface #46,  2           // InterfaceMethod java/util/List.add:(Ljava/lang/Object;)Z
     280: pop
     281: goto          462
     284: fload         15
     286: aload_0
     287: getfield      #28                 // Field chanceForSameQualifier:F
     290: fcmpl
     291: ifle          422
     294: aload         5
     296: aload         12
     298: invokeinterface #65,  2           // InterfaceMethod java/util/Map.get:(Ljava/lang/Object;)Ljava/lang/Object;
     303: checkcast     #66                 // class java/util/List
     306: astore        16
     308: aload         16
     310: aload_0
     311: getfield      #40                 // Field randomizer:Ljava/util/Random;
     314: aload         16
     316: invokeinterface #49,  1           // InterfaceMethod java/util/List.size:()I
     321: invokevirtual #47                 // Method java/util/Random.nextInt:(I)I
     324: invokeinterface #50,  2           // InterfaceMethod java/util/List.get:(I)Ljava/lang/Object;
     329: checkcast     #51                 // class "[B"
     332: astore        17
     334: aload         17
     336: arraylength
     337: newarray       byte
     339: astore        14
     341: aload_0
     342: getfield      #40                 // Field randomizer:Ljava/util/Random;
     345: aload         14
     347: arraylength
     348: invokevirtual #47                 // Method java/util/Random.nextInt:(I)I
     351: istore        18
     353: aload         17
     355: iconst_0
     356: aload         14
     358: iconst_0
     359: iload         18
     361: invokestatic  #67                 // Method java/lang/System.arraycopy:(Ljava/lang/Object;ILjava/lang/Object;II)V
     364: iload         18
     366: istore        19
     368: iload         19
     370: aload         14
     372: arraylength
     373: if_icmpge     399
     376: aload         14
     378: iload         19
     380: aload_0
     381: getfield      #40                 // Field randomizer:Ljava/util/Random;
     384: invokevirtual #58                 // Method java/util/Random.nextInt:()I
     387: sipush        255
     390: iand
     391: i2b
     392: bastore
     393: iinc          19, 1
     396: goto          368
     399: aload         5
     401: aload         12
     403: invokeinterface #65,  2           // InterfaceMethod java/util/Map.get:(Ljava/lang/Object;)Ljava/lang/Object;
     408: checkcast     #66                 // class java/util/List
     411: aload         14
     413: invokeinterface #46,  2           // InterfaceMethod java/util/List.add:(Ljava/lang/Object;)Z
     418: pop
     419: goto          462
     422: aload         5
     424: aload         12
     426: invokeinterface #65,  2           // InterfaceMethod java/util/Map.get:(Ljava/lang/Object;)Ljava/lang/Object;
     431: checkcast     #66                 // class java/util/List
     434: astore        16
     436: aload         16
     438: aload_0
     439: getfield      #40                 // Field randomizer:Ljava/util/Random;
     442: aload         16
     444: invokeinterface #49,  1           // InterfaceMethod java/util/List.size:()I
     449: invokevirtual #47                 // Method java/util/Random.nextInt:(I)I
     452: invokeinterface #50,  2           // InterfaceMethod java/util/List.get:(I)Ljava/lang/Object;
     457: checkcast     #51                 // class "[B"
     460: astore        14
     462: aload_0
     463: getfield      #40                 // Field randomizer:Ljava/util/Random;
     466: invokevirtual #62                 // Method java/util/Random.nextFloat:()F
     469: aload_0
     470: getfield      #35                 // Field chanceForZeroValue:F
     473: fcmpg
     474: ifge          503
     477: iconst_0
     478: istore        16
     480: iload         16
     482: aload         8
     484: arraylength
     485: if_icmpge     500
     488: aload         8
     490: iload         16
     492: iconst_0
     493: bastore
     494: iinc          16, 1
     497: goto          480
     500: goto          512
     503: aload_0
     504: getfield      #40                 // Field randomizer:Ljava/util/Random;
     507: aload         8
     509: invokevirtual #48                 // Method java/util/Random.nextBytes:([B)V
     512: iload_2
     513: ifeq          614
     516: new           #68                 // class org/apache/hadoop/hbase/KeyValue
     519: dup
     520: aload         13
     522: aload_0
     523: getfield      #57                 // Field family:[B
     526: aload         14
     528: lload         10
     530: aload         8
     532: iconst_1
     533: anewarray     #69                 // class org/apache/hadoop/hbase/Tag
     536: dup
     537: iconst_0
     538: new           #70                 // class org/apache/hadoop/hbase/ArrayBackedTag
     541: dup
     542: iconst_1
     543: ldc           #71                 // String value1
     545: invokespecial #72                 // Method org/apache/hadoop/hbase/ArrayBackedTag."<init>":(BLjava/lang/String;)V
     548: aastore
     549: invokespecial #73                 // Method org/apache/hadoop/hbase/KeyValue."<init>":([B[B[BJ[B[Lorg/apache/hadoop/hbase/Tag;)V
     552: astore        16
     554: aload         16
     556: invokevirtual #77                 // Method org/apache/hadoop/hbase/KeyValue.getLength:()I
     559: invokestatic  #78                 // Method java/nio/ByteBuffer.allocateDirect:(I)Ljava/nio/ByteBuffer;
     562: astore        17
     564: aload         17
     566: aload         16
     568: invokevirtual #79                 // Method org/apache/hadoop/hbase/KeyValue.getBuffer:()[B
     571: aload         16
     573: invokevirtual #80                 // Method org/apache/hadoop/hbase/KeyValue.getOffset:()I
     576: aload         16
     578: invokevirtual #77                 // Method org/apache/hadoop/hbase/KeyValue.getLength:()I
     581: invokestatic  #81                 // Method org/apache/hadoop/hbase/util/ByteBufferUtils.copyFromArrayToBuffer:(Ljava/nio/ByteBuffer;[BII)V
     584: new           #82                 // class org/apache/hadoop/hbase/util/RedundantKVGenerator$ExtendedOffheapKeyValue
     587: dup
     588: aload         17
     590: iconst_0
     591: aload         16
     593: invokevirtual #77                 // Method org/apache/hadoop/hbase/KeyValue.getLength:()I
     596: lconst_0
     597: invokespecial #83                 // Method org/apache/hadoop/hbase/util/RedundantKVGenerator$ExtendedOffheapKeyValue."<init>":(Ljava/nio/ByteBuffer;IIJ)V
     600: astore        18
     602: aload_3
     603: aload         18
     605: invokeinterface #46,  2           // InterfaceMethod java/util/List.add:(Ljava/lang/Object;)Z
     610: pop
     611: goto          692
     614: new           #68                 // class org/apache/hadoop/hbase/KeyValue
     617: dup
     618: aload         13
     620: aload_0
     621: getfield      #57                 // Field family:[B
     624: aload         14
     626: lload         10
     628: aload         8
     630: invokespecial #74                 // Method org/apache/hadoop/hbase/KeyValue."<init>":([B[B[BJ[B)V
     633: astore        16
     635: aload         16
     637: invokevirtual #77                 // Method org/apache/hadoop/hbase/KeyValue.getLength:()I
     640: invokestatic  #78                 // Method java/nio/ByteBuffer.allocateDirect:(I)Ljava/nio/ByteBuffer;
     643: astore        17
     645: aload         17
     647: aload         16
     649: invokevirtual #79                 // Method org/apache/hadoop/hbase/KeyValue.getBuffer:()[B
     652: aload         16
     654: invokevirtual #80                 // Method org/apache/hadoop/hbase/KeyValue.getOffset:()I
     657: aload         16
     659: invokevirtual #77                 // Method org/apache/hadoop/hbase/KeyValue.getLength:()I
     662: invokestatic  #81                 // Method org/apache/hadoop/hbase/util/ByteBufferUtils.copyFromArrayToBuffer:(Ljava/nio/ByteBuffer;[BII)V
     665: new           #82                 // class org/apache/hadoop/hbase/util/RedundantKVGenerator$ExtendedOffheapKeyValue
     668: dup
     669: aload         17
     671: iconst_0
     672: aload         16
     674: invokevirtual #77                 // Method org/apache/hadoop/hbase/KeyValue.getLength:()I
     677: lconst_0
     678: invokespecial #83                 // Method org/apache/hadoop/hbase/util/RedundantKVGenerator$ExtendedOffheapKeyValue."<init>":(Ljava/nio/ByteBuffer;IIJ)V
     681: astore        18
     683: aload_3
     684: aload         18
     686: invokeinterface #46,  2           // InterfaceMethod java/util/List.add:(Ljava/lang/Object;)Z
     691: pop
     692: iinc          9, 1
     695: goto          80
     698: aload_3
     699: invokestatic  #75                 // InterfaceMethod org/apache/hadoop/hbase/CellComparator.getInstance:()Lorg/apache/hadoop/hbase/CellComparator;
     702: invokestatic  #76                 // Method java/util/Collections.sort:(Ljava/util/List;Ljava/util/Comparator;)V
     705: aload_3
     706: areturn

  public static java.nio.ByteBuffer convertKvToByteBuffer(java.util.List<org.apache.hadoop.hbase.KeyValue>, boolean);
    Code:
       0: iconst_0
       1: istore_2
       2: aload_0
       3: invokeinterface #84,  1           // InterfaceMethod java/util/List.iterator:()Ljava/util/Iterator;
       8: astore_3
       9: aload_3
      10: invokeinterface #85,  1           // InterfaceMethod java/util/Iterator.hasNext:()Z
      15: ifeq          55
      18: aload_3
      19: invokeinterface #86,  1           // InterfaceMethod java/util/Iterator.next:()Ljava/lang/Object;
      24: checkcast     #68                 // class org/apache/hadoop/hbase/KeyValue
      27: astore        4
      29: iload_2
      30: aload         4
      32: invokevirtual #77                 // Method org/apache/hadoop/hbase/KeyValue.getLength:()I
      35: iadd
      36: istore_2
      37: iload_1
      38: ifeq          52
      41: iload_2
      42: aload         4
      44: invokevirtual #87                 // Method org/apache/hadoop/hbase/KeyValue.getSequenceId:()J
      47: invokestatic  #88                 // Method org/apache/hadoop/io/WritableUtils.getVIntSize:(J)I
      50: iadd
      51: istore_2
      52: goto          9
      55: iload_2
      56: invokestatic  #89                 // Method java/nio/ByteBuffer.allocate:(I)Ljava/nio/ByteBuffer;
      59: astore_3
      60: aload_0
      61: invokeinterface #84,  1           // InterfaceMethod java/util/List.iterator:()Ljava/util/Iterator;
      66: astore        4
      68: aload         4
      70: invokeinterface #85,  1           // InterfaceMethod java/util/Iterator.hasNext:()Z
      75: ifeq          126
      78: aload         4
      80: invokeinterface #86,  1           // InterfaceMethod java/util/Iterator.next:()Ljava/lang/Object;
      85: checkcast     #68                 // class org/apache/hadoop/hbase/KeyValue
      88: astore        5
      90: aload_3
      91: aload         5
      93: invokevirtual #79                 // Method org/apache/hadoop/hbase/KeyValue.getBuffer:()[B
      96: aload         5
      98: invokevirtual #80                 // Method org/apache/hadoop/hbase/KeyValue.getOffset:()I
     101: aload         5
     103: invokevirtual #77                 // Method org/apache/hadoop/hbase/KeyValue.getLength:()I
     106: invokevirtual #90                 // Method java/nio/ByteBuffer.put:([BII)Ljava/nio/ByteBuffer;
     109: pop
     110: iload_1
     111: ifeq          123
     114: aload_3
     115: aload         5
     117: invokevirtual #87                 // Method org/apache/hadoop/hbase/KeyValue.getSequenceId:()J
     120: invokestatic  #91                 // Method org/apache/hadoop/hbase/util/ByteBufferUtils.writeVLong:(Ljava/nio/ByteBuffer;J)V
     123: goto          68
     126: aload_3
     127: areturn

  public org.apache.hadoop.hbase.util.RedundantKVGenerator setCommonPrefix(byte[]);
    Code:
       0: aload_0
       1: aload_1
       2: putfield      #42                 // Field commonPrefix:[B
       5: aload_0
       6: areturn

  public org.apache.hadoop.hbase.util.RedundantKVGenerator setRandomizer(java.util.Random);
    Code:
       0: aload_0
       1: aload_1
       2: putfield      #40                 // Field randomizer:Ljava/util/Random;
       5: aload_0
       6: areturn

  public org.apache.hadoop.hbase.util.RedundantKVGenerator setNumberOfRowPrefixes(int);
    Code:
       0: aload_0
       1: iload_1
       2: putfield      #43                 // Field numberOfRowPrefixes:I
       5: aload_0
       6: areturn

  public org.apache.hadoop.hbase.util.RedundantKVGenerator setAveragePrefixLength(int);
    Code:
       0: aload_0
       1: iload_1
       2: putfield      #22                 // Field averagePrefixLength:I
       5: aload_0
       6: areturn

  public org.apache.hadoop.hbase.util.RedundantKVGenerator setPrefixLengthVariance(int);
    Code:
       0: aload_0
       1: iload_1
       2: putfield      #23                 // Field prefixLengthVariance:I
       5: aload_0
       6: areturn

  public org.apache.hadoop.hbase.util.RedundantKVGenerator setAverageSuffixLength(int);
    Code:
       0: aload_0
       1: iload_1
       2: putfield      #24                 // Field averageSuffixLength:I
       5: aload_0
       6: areturn

  public org.apache.hadoop.hbase.util.RedundantKVGenerator setSuffixLengthVariance(int);
    Code:
       0: aload_0
       1: iload_1
       2: putfield      #25                 // Field suffixLengthVariance:I
       5: aload_0
       6: areturn

  public org.apache.hadoop.hbase.util.RedundantKVGenerator setNumberOfRows(int);
    Code:
       0: aload_0
       1: iload_1
       2: putfield      #26                 // Field numberOfRows:I
       5: aload_0
       6: areturn

  public org.apache.hadoop.hbase.util.RedundantKVGenerator setChanceForSameQualifier(float);
    Code:
       0: aload_0
       1: fload_1
       2: putfield      #28                 // Field chanceForSameQualifier:F
       5: aload_0
       6: areturn

  public org.apache.hadoop.hbase.util.RedundantKVGenerator setChanceForSimilarQualifier(float);
    Code:
       0: aload_0
       1: fload_1
       2: putfield      #30                 // Field chanceForSimilarQualifier:F
       5: aload_0
       6: areturn

  public org.apache.hadoop.hbase.util.RedundantKVGenerator setAverageQualifierLength(int);
    Code:
       0: aload_0
       1: iload_1
       2: putfield      #31                 // Field averageQualifierLength:I
       5: aload_0
       6: areturn

  public org.apache.hadoop.hbase.util.RedundantKVGenerator setQualifierLengthVariance(int);
    Code:
       0: aload_0
       1: iload_1
       2: putfield      #32                 // Field qualifierLengthVariance:I
       5: aload_0
       6: areturn

  public org.apache.hadoop.hbase.util.RedundantKVGenerator setColumnFamilyLength(int);
    Code:
       0: aload_0
       1: iload_1
       2: putfield      #33                 // Field columnFamilyLength:I
       5: aload_0
       6: areturn

  public org.apache.hadoop.hbase.util.RedundantKVGenerator setFamily(byte[]);
    Code:
       0: aload_0
       1: aload_1
       2: putfield      #57                 // Field family:[B
       5: aload_0
       6: aload_1
       7: arraylength
       8: putfield      #33                 // Field columnFamilyLength:I
      11: aload_0
      12: areturn

  public org.apache.hadoop.hbase.util.RedundantKVGenerator setValueLength(int);
    Code:
       0: aload_0
       1: iload_1
       2: putfield      #34                 // Field valueLength:I
       5: aload_0
       6: areturn

  public org.apache.hadoop.hbase.util.RedundantKVGenerator setChanceForZeroValue(float);
    Code:
       0: aload_0
       1: fload_1
       2: putfield      #35                 // Field chanceForZeroValue:F
       5: aload_0
       6: areturn

  public org.apache.hadoop.hbase.util.RedundantKVGenerator setBaseTimestampDivide(int);
    Code:
       0: aload_0
       1: iload_1
       2: putfield      #37                 // Field baseTimestampDivide:I
       5: aload_0
       6: areturn

  public org.apache.hadoop.hbase.util.RedundantKVGenerator setTimestampDiffSize(int);
    Code:
       0: aload_0
       1: iload_1
       2: putfield      #39                 // Field timestampDiffSize:I
       5: aload_0
       6: areturn

  static {};
    Code:
       0: iconst_0
       1: newarray       byte
       3: putstatic     #41                 // Field DEFAULT_COMMON_PREFIX:[B
       6: bipush        10
       8: putstatic     #5                  // Field DEFAULT_NUMBER_OF_ROW_PREFIXES:I
      11: bipush        6
      13: putstatic     #6                  // Field DEFAULT_AVERAGE_PREFIX_LENGTH:I
      16: iconst_3
      17: putstatic     #7                  // Field DEFAULT_PREFIX_LENGTH_VARIANCE:I
      20: iconst_3
      21: putstatic     #8                  // Field DEFAULT_AVERAGE_SUFFIX_LENGTH:I
      24: iconst_3
      25: putstatic     #9                  // Field DEFAULT_SUFFIX_LENGTH_VARIANCE:I
      28: sipush        500
      31: putstatic     #10                 // Field DEFAULT_NUMBER_OF_ROW:I
      34: ldc           #27                 // float 0.5f
      36: putstatic     #11                 // Field DEFAULT_CHANCE_FOR_SAME_QUALIFIER:F
      39: ldc           #29                 // float 0.4f
      41: putstatic     #12                 // Field DEFAULT_CHANCE_FOR_SIMILIAR_QUALIFIER:F
      44: bipush        9
      46: putstatic     #13                 // Field DEFAULT_AVERAGE_QUALIFIER_LENGTH:I
      49: iconst_3
      50: putstatic     #14                 // Field DEFAULT_QUALIFIER_LENGTH_VARIANCE:I
      53: bipush        9
      55: putstatic     #15                 // Field DEFAULT_COLUMN_FAMILY_LENGTH:I
      58: bipush        8
      60: putstatic     #16                 // Field DEFAULT_VALUE_LENGTH:I
      63: ldc           #27                 // float 0.5f
      65: putstatic     #17                 // Field DEFAULT_CHANCE_FOR_ZERO_VALUE:F
      68: ldc           #36                 // int 1000000
      70: putstatic     #18                 // Field DEFAULT_BASE_TIMESTAMP_DIVIDE:I
      73: ldc           #38                 // int 100000000
      75: putstatic     #19                 // Field DEFAULT_TIMESTAMP_DIFF_SIZE:I
      78: return
}
