Compiled from "RefCountingMap.java"
class org.apache.hadoop.hbase.metrics.impl.RefCountingMap$Payload<V> {
  V v;

  int refCount;

  org.apache.hadoop.hbase.metrics.impl.RefCountingMap$Payload(V);
    Code:
       0: aload_0
       1: invokespecial #1                  // Method java/lang/Object."<init>":()V
       4: aload_0
       5: aload_1
       6: putfield      #2                  // Field v:Ljava/lang/Object;
       9: aload_0
      10: iconst_1
      11: putfield      #3                  // Field refCount:I
      14: return
}
