Compiled from "RegionCoprocessorHost.java"
class org.apache.hadoop.hbase.regionserver.RegionCoprocessorHost$RegionEnvironment extends org.apache.hadoop.hbase.coprocessor.BaseEnvironment<org.apache.hadoop.hbase.coprocessor.RegionCoprocessor> implements org.apache.hadoop.hbase.coprocessor.RegionCoprocessorEnvironment {
  java.util.concurrent.ConcurrentMap<java.lang.String, java.lang.Object> sharedData;

  public org.apache.hadoop.hbase.regionserver.RegionCoprocessorHost$RegionEnvironment(org.apache.hadoop.hbase.coprocessor.RegionCoprocessor, int, int, org.apache.hadoop.conf.Configuration, org.apache.hadoop.hbase.regionserver.Region, org.apache.hadoop.hbase.regionserver.RegionServerServices, java.util.concurrent.ConcurrentMap<java.lang.String, java.lang.Object>);
    Code:
       0: aload_0
       1: aload_1
       2: iload_2
       3: iload_3
       4: aload         4
       6: invokespecial #1                  // Method org/apache/hadoop/hbase/coprocessor/BaseEnvironment."<init>":(Lorg/apache/hadoop/hbase/Coprocessor;IILorg/apache/hadoop/conf/Configuration;)V
       9: aload_0
      10: aload         5
      12: putfield      #2                  // Field region:Lorg/apache/hadoop/hbase/regionserver/Region;
      15: aload_0
      16: aload         7
      18: putfield      #3                  // Field sharedData:Ljava/util/concurrent/ConcurrentMap;
      21: aload_0
      22: aload         6
      24: putfield      #4                  // Field services:Lorg/apache/hadoop/hbase/regionserver/RegionServerServices;
      27: aload_0
      28: aload_1
      29: invokevirtual #5                  // Method java/lang/Object.getClass:()Ljava/lang/Class;
      32: invokevirtual #6                  // Method java/lang/Class.getName:()Ljava/lang/String;
      35: invokestatic  #7                  // Method org/apache/hadoop/hbase/coprocessor/MetricsCoprocessor.createRegistryForRegionCoprocessor:(Ljava/lang/String;)Lorg/apache/hadoop/hbase/metrics/MetricRegistry;
      38: putfield      #8                  // Field metricRegistry:Lorg/apache/hadoop/hbase/metrics/MetricRegistry;
      41: return

  public org.apache.hadoop.hbase.regionserver.Region getRegion();
    Code:
       0: aload_0
       1: getfield      #2                  // Field region:Lorg/apache/hadoop/hbase/regionserver/Region;
       4: areturn

  public org.apache.hadoop.hbase.regionserver.OnlineRegions getOnlineRegions();
    Code:
       0: aload_0
       1: getfield      #4                  // Field services:Lorg/apache/hadoop/hbase/regionserver/RegionServerServices;
       4: areturn

  public org.apache.hadoop.hbase.client.Connection getConnection();
    Code:
       0: aload_0
       1: getfield      #4                  // Field services:Lorg/apache/hadoop/hbase/regionserver/RegionServerServices;
       4: ifnull        26
       7: new           #9                  // class org/apache/hadoop/hbase/SharedConnection
      10: dup
      11: aload_0
      12: getfield      #4                  // Field services:Lorg/apache/hadoop/hbase/regionserver/RegionServerServices;
      15: invokeinterface #10,  1           // InterfaceMethod org/apache/hadoop/hbase/regionserver/RegionServerServices.getConnection:()Lorg/apache/hadoop/hbase/client/Connection;
      20: invokespecial #11                 // Method org/apache/hadoop/hbase/SharedConnection."<init>":(Lorg/apache/hadoop/hbase/client/Connection;)V
      23: goto          27
      26: aconst_null
      27: areturn

  public org.apache.hadoop.hbase.client.Connection createConnection(org.apache.hadoop.conf.Configuration) throws java.io.IOException;
    Code:
       0: aload_0
       1: getfield      #4                  // Field services:Lorg/apache/hadoop/hbase/regionserver/RegionServerServices;
       4: ifnull        20
       7: aload_0
       8: getfield      #4                  // Field services:Lorg/apache/hadoop/hbase/regionserver/RegionServerServices;
      11: aload_1
      12: invokeinterface #12,  2           // InterfaceMethod org/apache/hadoop/hbase/regionserver/RegionServerServices.createConnection:(Lorg/apache/hadoop/conf/Configuration;)Lorg/apache/hadoop/hbase/client/Connection;
      17: goto          21
      20: aconst_null
      21: areturn

  public org.apache.hadoop.hbase.ServerName getServerName();
    Code:
       0: aload_0
       1: getfield      #4                  // Field services:Lorg/apache/hadoop/hbase/regionserver/RegionServerServices;
       4: ifnull        19
       7: aload_0
       8: getfield      #4                  // Field services:Lorg/apache/hadoop/hbase/regionserver/RegionServerServices;
      11: invokeinterface #13,  1           // InterfaceMethod org/apache/hadoop/hbase/regionserver/RegionServerServices.getServerName:()Lorg/apache/hadoop/hbase/ServerName;
      16: goto          20
      19: aconst_null
      20: areturn

  public void shutdown();
    Code:
       0: aload_0
       1: invokespecial #14                 // Method org/apache/hadoop/hbase/coprocessor/BaseEnvironment.shutdown:()V
       4: aload_0
       5: getfield      #8                  // Field metricRegistry:Lorg/apache/hadoop/hbase/metrics/MetricRegistry;
       8: invokestatic  #15                 // Method org/apache/hadoop/hbase/coprocessor/MetricsCoprocessor.removeRegistry:(Lorg/apache/hadoop/hbase/metrics/MetricRegistry;)V
      11: return

  public java.util.concurrent.ConcurrentMap<java.lang.String, java.lang.Object> getSharedData();
    Code:
       0: aload_0
       1: getfield      #3                  // Field sharedData:Ljava/util/concurrent/ConcurrentMap;
       4: areturn

  public org.apache.hadoop.hbase.client.RegionInfo getRegionInfo();
    Code:
       0: aload_0
       1: getfield      #2                  // Field region:Lorg/apache/hadoop/hbase/regionserver/Region;
       4: invokeinterface #16,  1           // InterfaceMethod org/apache/hadoop/hbase/regionserver/Region.getRegionInfo:()Lorg/apache/hadoop/hbase/client/RegionInfo;
       9: areturn

  public org.apache.hadoop.hbase.metrics.MetricRegistry getMetricRegistryForRegionServer();
    Code:
       0: aload_0
       1: getfield      #8                  // Field metricRegistry:Lorg/apache/hadoop/hbase/metrics/MetricRegistry;
       4: areturn

  public org.apache.hadoop.hbase.RawCellBuilder getCellBuilder();
    Code:
       0: invokestatic  #17                 // Method org/apache/hadoop/hbase/RawCellBuilderFactory.create:()Lorg/apache/hadoop/hbase/RawCellBuilder;
       3: areturn
}
