Compiled from "RegionCoprocessorHost.java"
class org.apache.hadoop.hbase.regionserver.RegionCoprocessorHost$7 extends org.apache.hadoop.hbase.regionserver.RegionCoprocessorHost$RegionObserverOperationWithoutResult {
  final org.apache.hadoop.hbase.regionserver.HStore val$store;

  final org.apache.hadoop.hbase.regionserver.ScanType val$scanType;

  final org.apache.hadoop.hbase.regionserver.CustomizedScanInfoBuilder val$builder;

  final org.apache.hadoop.hbase.regionserver.compactions.CompactionLifeCycleTracker val$tracker;

  final org.apache.hadoop.hbase.regionserver.compactions.CompactionRequest val$request;

  final org.apache.hadoop.hbase.regionserver.RegionCoprocessorHost this$0;

  org.apache.hadoop.hbase.regionserver.RegionCoprocessorHost$7(org.apache.hadoop.hbase.regionserver.RegionCoprocessorHost, org.apache.hadoop.hbase.security.User, org.apache.hadoop.hbase.regionserver.HStore, org.apache.hadoop.hbase.regionserver.ScanType, org.apache.hadoop.hbase.regionserver.CustomizedScanInfoBuilder, org.apache.hadoop.hbase.regionserver.compactions.CompactionLifeCycleTracker, org.apache.hadoop.hbase.regionserver.compactions.CompactionRequest);
    Code:
       0: aload_0
       1: aload_1
       2: putfield      #1                  // Field this$0:Lorg/apache/hadoop/hbase/regionserver/RegionCoprocessorHost;
       5: aload_0
       6: aload_3
       7: putfield      #2                  // Field val$store:Lorg/apache/hadoop/hbase/regionserver/HStore;
      10: aload_0
      11: aload         4
      13: putfield      #3                  // Field val$scanType:Lorg/apache/hadoop/hbase/regionserver/ScanType;
      16: aload_0
      17: aload         5
      19: putfield      #4                  // Field val$builder:Lorg/apache/hadoop/hbase/regionserver/CustomizedScanInfoBuilder;
      22: aload_0
      23: aload         6
      25: putfield      #5                  // Field val$tracker:Lorg/apache/hadoop/hbase/regionserver/compactions/CompactionLifeCycleTracker;
      28: aload_0
      29: aload         7
      31: putfield      #6                  // Field val$request:Lorg/apache/hadoop/hbase/regionserver/compactions/CompactionRequest;
      34: aload_0
      35: aload_1
      36: aload_2
      37: invokespecial #7                  // Method org/apache/hadoop/hbase/regionserver/RegionCoprocessorHost$RegionObserverOperationWithoutResult."<init>":(Lorg/apache/hadoop/hbase/regionserver/RegionCoprocessorHost;Lorg/apache/hadoop/hbase/security/User;)V
      40: return

  public void call(org.apache.hadoop.hbase.coprocessor.RegionObserver) throws java.io.IOException;
    Code:
       0: aload_1
       1: aload_0
       2: aload_0
       3: getfield      #2                  // Field val$store:Lorg/apache/hadoop/hbase/regionserver/HStore;
       6: aload_0
       7: getfield      #3                  // Field val$scanType:Lorg/apache/hadoop/hbase/regionserver/ScanType;
      10: aload_0
      11: getfield      #4                  // Field val$builder:Lorg/apache/hadoop/hbase/regionserver/CustomizedScanInfoBuilder;
      14: aload_0
      15: getfield      #5                  // Field val$tracker:Lorg/apache/hadoop/hbase/regionserver/compactions/CompactionLifeCycleTracker;
      18: aload_0
      19: getfield      #6                  // Field val$request:Lorg/apache/hadoop/hbase/regionserver/compactions/CompactionRequest;
      22: invokeinterface #8,  7            // InterfaceMethod org/apache/hadoop/hbase/coprocessor/RegionObserver.preCompactScannerOpen:(Lorg/apache/hadoop/hbase/coprocessor/ObserverContext;Lorg/apache/hadoop/hbase/regionserver/Store;Lorg/apache/hadoop/hbase/regionserver/ScanType;Lorg/apache/hadoop/hbase/regionserver/ScanOptions;Lorg/apache/hadoop/hbase/regionserver/compactions/CompactionLifeCycleTracker;Lorg/apache/hadoop/hbase/regionserver/compactions/CompactionRequest;)V
      27: return

  public void call(java.lang.Object) throws java.io.IOException;
    Code:
       0: aload_0
       1: aload_1
       2: checkcast     #9                  // class org/apache/hadoop/hbase/coprocessor/RegionObserver
       5: invokevirtual #10                 // Method call:(Lorg/apache/hadoop/hbase/coprocessor/RegionObserver;)V
       8: return
}
