Compiled from "RegionCoprocessorRpcChannelImpl.java"
class org.apache.hadoop.hbase.client.RegionCoprocessorRpcChannelImpl implements com.google.protobuf.RpcChannel {
  org.apache.hadoop.hbase.client.RegionCoprocessorRpcChannelImpl(org.apache.hadoop.hbase.client.AsyncConnectionImpl, org.apache.hadoop.hbase.TableName, org.apache.hadoop.hbase.client.RegionInfo, byte[], long, long);
    Code:
       0: aload_0
       1: invokespecial #1                  // Method java/lang/Object."<init>":()V
       4: aload_0
       5: aload_1
       6: putfield      #2                  // Field conn:Lorg/apache/hadoop/hbase/client/AsyncConnectionImpl;
       9: aload_0
      10: aload_2
      11: putfield      #3                  // Field tableName:Lorg/apache/hadoop/hbase/TableName;
      14: aload_0
      15: aload_3
      16: putfield      #4                  // Field region:Lorg/apache/hadoop/hbase/client/RegionInfo;
      19: aload_0
      20: aload         4
      22: putfield      #5                  // Field row:[B
      25: aload_0
      26: lload         5
      28: putfield      #6                  // Field rpcTimeoutNs:J
      31: aload_0
      32: lload         7
      34: putfield      #7                  // Field operationTimeoutNs:J
      37: return

  public void callMethod(com.google.protobuf.Descriptors$MethodDescriptor, com.google.protobuf.RpcController, com.google.protobuf.Message, com.google.protobuf.Message, com.google.protobuf.RpcCallback<com.google.protobuf.Message>);
    Code:
       0: aload_0
       1: getfield      #2                  // Field conn:Lorg/apache/hadoop/hbase/client/AsyncConnectionImpl;
       4: getfield      #29                 // Field org/apache/hadoop/hbase/client/AsyncConnectionImpl.callerFactory:Lorg/apache/hadoop/hbase/client/AsyncRpcRetryingCallerFactory;
       7: invokevirtual #30                 // Method org/apache/hadoop/hbase/client/AsyncRpcRetryingCallerFactory.single:()Lorg/apache/hadoop/hbase/client/AsyncRpcRetryingCallerFactory$SingleRequestCallerBuilder;
      10: aload_0
      11: getfield      #3                  // Field tableName:Lorg/apache/hadoop/hbase/TableName;
      14: invokevirtual #31                 // Method org/apache/hadoop/hbase/client/AsyncRpcRetryingCallerFactory$SingleRequestCallerBuilder.table:(Lorg/apache/hadoop/hbase/TableName;)Lorg/apache/hadoop/hbase/client/AsyncRpcRetryingCallerFactory$SingleRequestCallerBuilder;
      17: aload_0
      18: getfield      #5                  // Field row:[B
      21: invokevirtual #32                 // Method org/apache/hadoop/hbase/client/AsyncRpcRetryingCallerFactory$SingleRequestCallerBuilder.row:([B)Lorg/apache/hadoop/hbase/client/AsyncRpcRetryingCallerFactory$SingleRequestCallerBuilder;
      24: getstatic     #33                 // Field org/apache/hadoop/hbase/client/RegionLocateType.CURRENT:Lorg/apache/hadoop/hbase/client/RegionLocateType;
      27: invokevirtual #34                 // Method org/apache/hadoop/hbase/client/AsyncRpcRetryingCallerFactory$SingleRequestCallerBuilder.locateType:(Lorg/apache/hadoop/hbase/client/RegionLocateType;)Lorg/apache/hadoop/hbase/client/AsyncRpcRetryingCallerFactory$SingleRequestCallerBuilder;
      30: aload_0
      31: getfield      #6                  // Field rpcTimeoutNs:J
      34: getstatic     #35                 // Field java/util/concurrent/TimeUnit.NANOSECONDS:Ljava/util/concurrent/TimeUnit;
      37: invokevirtual #36                 // Method org/apache/hadoop/hbase/client/AsyncRpcRetryingCallerFactory$SingleRequestCallerBuilder.rpcTimeout:(JLjava/util/concurrent/TimeUnit;)Lorg/apache/hadoop/hbase/client/AsyncRpcRetryingCallerFactory$SingleRequestCallerBuilder;
      40: aload_0
      41: getfield      #7                  // Field operationTimeoutNs:J
      44: getstatic     #35                 // Field java/util/concurrent/TimeUnit.NANOSECONDS:Ljava/util/concurrent/TimeUnit;
      47: invokevirtual #37                 // Method org/apache/hadoop/hbase/client/AsyncRpcRetryingCallerFactory$SingleRequestCallerBuilder.operationTimeout:(JLjava/util/concurrent/TimeUnit;)Lorg/apache/hadoop/hbase/client/AsyncRpcRetryingCallerFactory$SingleRequestCallerBuilder;
      50: aload_0
      51: aload_1
      52: aload_3
      53: aload         4
      55: invokedynamic #38,  0             // InvokeDynamic #0:call:(Lorg/apache/hadoop/hbase/client/RegionCoprocessorRpcChannelImpl;Lcom/google/protobuf/Descriptors$MethodDescriptor;Lcom/google/protobuf/Message;Lcom/google/protobuf/Message;)Lorg/apache/hadoop/hbase/client/AsyncSingleRequestRpcRetryingCaller$Callable;
      60: invokevirtual #39                 // Method org/apache/hadoop/hbase/client/AsyncRpcRetryingCallerFactory$SingleRequestCallerBuilder.action:(Lorg/apache/hadoop/hbase/client/AsyncSingleRequestRpcRetryingCaller$Callable;)Lorg/apache/hadoop/hbase/client/AsyncRpcRetryingCallerFactory$SingleRequestCallerBuilder;
      63: invokevirtual #40                 // Method org/apache/hadoop/hbase/client/AsyncRpcRetryingCallerFactory$SingleRequestCallerBuilder.call:()Ljava/util/concurrent/CompletableFuture;
      66: aload_2
      67: aload         5
      69: invokedynamic #41,  0             // InvokeDynamic #1:accept:(Lcom/google/protobuf/RpcController;Lcom/google/protobuf/RpcCallback;)Ljava/util/function/BiConsumer;
      74: invokestatic  #42                 // Method org/apache/hadoop/hbase/util/FutureUtils.addListener:(Ljava/util/concurrent/CompletableFuture;Ljava/util/function/BiConsumer;)V
      77: return
}
