Compiled from "RegionReplicaReplicationEndpoint.java"
class org.apache.hadoop.hbase.replication.regionserver.RegionReplicaReplicationEndpoint$RegionReplicaOutputSink extends org.apache.hadoop.hbase.wal.OutputSink {
  public org.apache.hadoop.hbase.replication.regionserver.RegionReplicaReplicationEndpoint$RegionReplicaOutputSink(org.apache.hadoop.hbase.wal.WALSplitter$PipelineController, org.apache.hadoop.hbase.TableDescriptors, org.apache.hadoop.hbase.wal.EntryBuffers, org.apache.hadoop.hbase.client.ClusterConnection, java.util.concurrent.ExecutorService, int, int);
    Code:
       0: aload_0
       1: aload_1
       2: aload_3
       3: iload         6
       5: invokespecial #1                  // Method org/apache/hadoop/hbase/wal/OutputSink."<init>":(Lorg/apache/hadoop/hbase/wal/WALSplitter$PipelineController;Lorg/apache/hadoop/hbase/wal/EntryBuffers;I)V
       8: aload_0
       9: new           #2                  // class org/apache/hadoop/hbase/replication/regionserver/RegionReplicaReplicationEndpoint$RegionReplicaSinkWriter
      12: dup
      13: aload_0
      14: aload         4
      16: aload         5
      18: iload         7
      20: aload_2
      21: invokespecial #3                  // Method org/apache/hadoop/hbase/replication/regionserver/RegionReplicaReplicationEndpoint$RegionReplicaSinkWriter."<init>":(Lorg/apache/hadoop/hbase/replication/regionserver/RegionReplicaReplicationEndpoint$RegionReplicaOutputSink;Lorg/apache/hadoop/hbase/client/ClusterConnection;Ljava/util/concurrent/ExecutorService;ILorg/apache/hadoop/hbase/TableDescriptors;)V
      24: putfield      #4                  // Field sinkWriter:Lorg/apache/hadoop/hbase/replication/regionserver/RegionReplicaReplicationEndpoint$RegionReplicaSinkWriter;
      27: aload_0
      28: aload_2
      29: putfield      #5                  // Field tableDescriptors:Lorg/apache/hadoop/hbase/TableDescriptors;
      32: aload         4
      34: invokeinterface #6,  1            // InterfaceMethod org/apache/hadoop/hbase/client/ClusterConnection.getConfiguration:()Lorg/apache/hadoop/conf/Configuration;
      39: ldc           #7                  // String hbase.region.replica.replication.cache.memstoreReplicationEnabled.expiryMs
      41: sipush        5000
      44: invokevirtual #8                  // Method org/apache/hadoop/conf/Configuration.getInt:(Ljava/lang/String;I)I
      47: istore        8
      49: aload_0
      50: invokestatic  #9                  // Method org/apache/hbase/thirdparty/com/google/common/cache/CacheBuilder.newBuilder:()Lorg/apache/hbase/thirdparty/com/google/common/cache/CacheBuilder;
      53: iload         8
      55: i2l
      56: getstatic     #10                 // Field java/util/concurrent/TimeUnit.MILLISECONDS:Ljava/util/concurrent/TimeUnit;
      59: invokevirtual #11                 // Method org/apache/hbase/thirdparty/com/google/common/cache/CacheBuilder.expireAfterWrite:(JLjava/util/concurrent/TimeUnit;)Lorg/apache/hbase/thirdparty/com/google/common/cache/CacheBuilder;
      62: bipush        10
      64: invokevirtual #12                 // Method org/apache/hbase/thirdparty/com/google/common/cache/CacheBuilder.initialCapacity:(I)Lorg/apache/hbase/thirdparty/com/google/common/cache/CacheBuilder;
      67: ldc2_w        #13                 // long 1000l
      70: invokevirtual #15                 // Method org/apache/hbase/thirdparty/com/google/common/cache/CacheBuilder.maximumSize:(J)Lorg/apache/hbase/thirdparty/com/google/common/cache/CacheBuilder;
      73: invokevirtual #16                 // Method org/apache/hbase/thirdparty/com/google/common/cache/CacheBuilder.build:()Lorg/apache/hbase/thirdparty/com/google/common/cache/Cache;
      76: putfield      #17                 // Field memstoreReplicationEnabled:Lorg/apache/hbase/thirdparty/com/google/common/cache/Cache;
      79: return

  public void append(org.apache.hadoop.hbase.wal.WALSplitter$RegionEntryBuffer) throws java.io.IOException;
    Code:
       0: aload_1
       1: invokevirtual #18                 // Method org/apache/hadoop/hbase/wal/WALSplitter$RegionEntryBuffer.getEntryBuffer:()Ljava/util/List;
       4: astore_2
       5: aload_2
       6: invokeinterface #19,  1           // InterfaceMethod java/util/List.isEmpty:()Z
      11: ifne          36
      14: aload_2
      15: iconst_0
      16: invokeinterface #20,  2           // InterfaceMethod java/util/List.get:(I)Ljava/lang/Object;
      21: checkcast     #21                 // class org/apache/hadoop/hbase/wal/WAL$Entry
      24: invokevirtual #22                 // Method org/apache/hadoop/hbase/wal/WAL$Entry.getEdit:()Lorg/apache/hadoop/hbase/wal/WALEdit;
      27: invokevirtual #23                 // Method org/apache/hadoop/hbase/wal/WALEdit.getCells:()Ljava/util/ArrayList;
      30: invokevirtual #24                 // Method java/util/ArrayList.isEmpty:()Z
      33: ifeq          37
      36: return
      37: aload_0
      38: aload_1
      39: invokevirtual #25                 // Method org/apache/hadoop/hbase/wal/WALSplitter$RegionEntryBuffer.getTableName:()Lorg/apache/hadoop/hbase/TableName;
      42: aload_2
      43: invokespecial #26                 // Method requiresReplication:(Lorg/apache/hadoop/hbase/TableName;Ljava/util/List;)Z
      46: ifne          50
      49: return
      50: aload_0
      51: getfield      #4                  // Field sinkWriter:Lorg/apache/hadoop/hbase/replication/regionserver/RegionReplicaReplicationEndpoint$RegionReplicaSinkWriter;
      54: aload_1
      55: invokevirtual #25                 // Method org/apache/hadoop/hbase/wal/WALSplitter$RegionEntryBuffer.getTableName:()Lorg/apache/hadoop/hbase/TableName;
      58: aload_1
      59: invokevirtual #27                 // Method org/apache/hadoop/hbase/wal/WALSplitter$RegionEntryBuffer.getEncodedRegionName:()[B
      62: aload_2
      63: iconst_0
      64: invokeinterface #20,  2           // InterfaceMethod java/util/List.get:(I)Ljava/lang/Object;
      69: checkcast     #21                 // class org/apache/hadoop/hbase/wal/WAL$Entry
      72: invokevirtual #22                 // Method org/apache/hadoop/hbase/wal/WAL$Entry.getEdit:()Lorg/apache/hadoop/hbase/wal/WALEdit;
      75: invokevirtual #23                 // Method org/apache/hadoop/hbase/wal/WALEdit.getCells:()Ljava/util/ArrayList;
      78: iconst_0
      79: invokevirtual #28                 // Method java/util/ArrayList.get:(I)Ljava/lang/Object;
      82: checkcast     #29                 // class org/apache/hadoop/hbase/Cell
      85: invokestatic  #30                 // Method org/apache/hadoop/hbase/CellUtil.cloneRow:(Lorg/apache/hadoop/hbase/Cell;)[B
      88: aload_2
      89: invokevirtual #31                 // Method org/apache/hadoop/hbase/replication/regionserver/RegionReplicaReplicationEndpoint$RegionReplicaSinkWriter.append:(Lorg/apache/hadoop/hbase/TableName;[B[BLjava/util/List;)V
      92: return

  public boolean flush() throws java.io.IOException;
    Code:
       0: aload_0
       1: getfield      #32                 // Field entryBuffers:Lorg/apache/hadoop/hbase/wal/EntryBuffers;
       4: invokevirtual #33                 // Method org/apache/hadoop/hbase/wal/EntryBuffers.waitUntilDrained:()V
       7: aload_0
       8: invokespecial #34                 // Method org/apache/hadoop/hbase/wal/OutputSink.flush:()Z
      11: ireturn

  public boolean keepRegionEvent(org.apache.hadoop.hbase.wal.WAL$Entry);
    Code:
       0: iconst_1
       1: ireturn

  public java.util.List<org.apache.hadoop.fs.Path> finishWritingAndClose() throws java.io.IOException;
    Code:
       0: aload_0
       1: iconst_1
       2: invokevirtual #35                 // Method finishWriting:(Z)Z
       5: pop
       6: aconst_null
       7: areturn

  public java.util.Map<byte[], java.lang.Long> getOutputCounts();
    Code:
       0: aconst_null
       1: areturn

  public int getNumberOfRecoveredRegions();
    Code:
       0: iconst_0
       1: ireturn

  java.util.concurrent.atomic.AtomicLong getSkippedEditsCounter();
    Code:
       0: aload_0
       1: getfield      #36                 // Field skippedEdits:Ljava/util/concurrent/atomic/AtomicLong;
       4: areturn
}
