Compiled from "RegionReplicaTestHelper.java"
final class org.apache.hadoop.hbase.client.RegionReplicaTestHelper$2 implements org.apache.hadoop.hbase.Waiter$ExplainingPredicate<java.lang.Exception> {
  final org.apache.hadoop.hbase.HBaseTestingUtility val$util;

  final org.apache.hadoop.hbase.TableName val$tableName;

  final int val$replicaId;

  final org.apache.hadoop.hbase.ServerName val$serverName;

  final org.apache.hadoop.hbase.client.RegionInfo val$regionInfo;

  org.apache.hadoop.hbase.client.RegionReplicaTestHelper$2(org.apache.hadoop.hbase.HBaseTestingUtility, org.apache.hadoop.hbase.TableName, int, org.apache.hadoop.hbase.ServerName, org.apache.hadoop.hbase.client.RegionInfo);
    Code:
       0: aload_0
       1: aload_1
       2: putfield      #1                  // Field val$util:Lorg/apache/hadoop/hbase/HBaseTestingUtility;
       5: aload_0
       6: aload_2
       7: putfield      #2                  // Field val$tableName:Lorg/apache/hadoop/hbase/TableName;
      10: aload_0
      11: iload_3
      12: putfield      #3                  // Field val$replicaId:I
      15: aload_0
      16: aload         4
      18: putfield      #4                  // Field val$serverName:Lorg/apache/hadoop/hbase/ServerName;
      21: aload_0
      22: aload         5
      24: putfield      #5                  // Field val$regionInfo:Lorg/apache/hadoop/hbase/client/RegionInfo;
      27: aload_0
      28: invokespecial #6                  // Method java/lang/Object."<init>":()V
      31: return

  public boolean evaluate() throws java.lang.Exception;
    Code:
       0: aload_0
       1: getfield      #1                  // Field val$util:Lorg/apache/hadoop/hbase/HBaseTestingUtility;
       4: aload_0
       5: getfield      #2                  // Field val$tableName:Lorg/apache/hadoop/hbase/TableName;
       8: aload_0
       9: getfield      #3                  // Field val$replicaId:I
      12: invokestatic  #7                  // Method org/apache/hadoop/hbase/client/RegionReplicaTestHelper.getRSCarryingReplica:(Lorg/apache/hadoop/hbase/HBaseTestingUtility;Lorg/apache/hadoop/hbase/TableName;I)Ljava/util/Optional;
      15: astore_1
      16: aload_1
      17: invokevirtual #8                  // Method java/util/Optional.isPresent:()Z
      20: ifeq          44
      23: aload_1
      24: invokevirtual #9                  // Method java/util/Optional.get:()Ljava/lang/Object;
      27: checkcast     #10                 // class org/apache/hadoop/hbase/ServerName
      30: aload_0
      31: getfield      #4                  // Field val$serverName:Lorg/apache/hadoop/hbase/ServerName;
      34: invokevirtual #11                 // Method org/apache/hadoop/hbase/ServerName.equals:(Ljava/lang/Object;)Z
      37: ifne          44
      40: iconst_1
      41: goto          45
      44: iconst_0
      45: ireturn

  public java.lang.String explainFailure() throws java.lang.Exception;
    Code:
       0: new           #12                 // class java/lang/StringBuilder
       3: dup
       4: invokespecial #13                 // Method java/lang/StringBuilder."<init>":()V
       7: aload_0
       8: getfield      #5                  // Field val$regionInfo:Lorg/apache/hadoop/hbase/client/RegionInfo;
      11: invokeinterface #14,  1           // InterfaceMethod org/apache/hadoop/hbase/client/RegionInfo.getRegionNameAsString:()Ljava/lang/String;
      16: invokevirtual #15                 // Method java/lang/StringBuilder.append:(Ljava/lang/String;)Ljava/lang/StringBuilder;
      19: ldc           #16                 // String  is still on
      21: invokevirtual #15                 // Method java/lang/StringBuilder.append:(Ljava/lang/String;)Ljava/lang/StringBuilder;
      24: aload_0
      25: getfield      #4                  // Field val$serverName:Lorg/apache/hadoop/hbase/ServerName;
      28: invokevirtual #17                 // Method java/lang/StringBuilder.append:(Ljava/lang/Object;)Ljava/lang/StringBuilder;
      31: invokevirtual #18                 // Method java/lang/StringBuilder.toString:()Ljava/lang/String;
      34: areturn
}
