Compiled from "RegionCoprocessorRpcChannel.java"
class org.apache.hadoop.hbase.client.RegionCoprocessorRpcChannel extends org.apache.hadoop.hbase.client.SyncCoprocessorRpcChannel {
  org.apache.hadoop.hbase.client.RegionCoprocessorRpcChannel(org.apache.hadoop.hbase.client.ClusterConnection, org.apache.hadoop.hbase.TableName, byte[]);
    Code:
       0: aload_0
       1: invokespecial #2                  // Method org/apache/hadoop/hbase/client/SyncCoprocessorRpcChannel."<init>":()V
       4: aload_0
       5: aload_2
       6: putfield      #3                  // Field table:Lorg/apache/hadoop/hbase/TableName;
       9: aload_0
      10: aload_3
      11: putfield      #1                  // Field row:[B
      14: aload_0
      15: aload_1
      16: putfield      #4                  // Field conn:Lorg/apache/hadoop/hbase/client/ClusterConnection;
      19: aload_0
      20: aload_1
      21: invokeinterface #5,  1            // InterfaceMethod org/apache/hadoop/hbase/client/ClusterConnection.getConnectionConfiguration:()Lorg/apache/hadoop/hbase/client/ConnectionConfiguration;
      26: invokevirtual #6                  // Method org/apache/hadoop/hbase/client/ConnectionConfiguration.getOperationTimeout:()I
      29: putfield      #7                  // Field operationTimeout:I
      32: aload_0
      33: aload_1
      34: invokeinterface #8,  1            // InterfaceMethod org/apache/hadoop/hbase/client/ClusterConnection.getRpcRetryingCallerFactory:()Lorg/apache/hadoop/hbase/client/RpcRetryingCallerFactory;
      39: putfield      #9                  // Field rpcCallerFactory:Lorg/apache/hadoop/hbase/client/RpcRetryingCallerFactory;
      42: return

  protected com.google.protobuf.Message callExecService(com.google.protobuf.RpcController, com.google.protobuf.Descriptors$MethodDescriptor, com.google.protobuf.Message, com.google.protobuf.Message) throws java.io.IOException;
    Code:
       0: getstatic     #10                 // Field LOG:Lorg/slf4j/Logger;
       3: invokeinterface #11,  1           // InterfaceMethod org/slf4j/Logger.isTraceEnabled:()Z
       8: ifeq          55
      11: getstatic     #10                 // Field LOG:Lorg/slf4j/Logger;
      14: new           #12                 // class java/lang/StringBuilder
      17: dup
      18: invokespecial #13                 // Method java/lang/StringBuilder."<init>":()V
      21: ldc           #14                 // String Call:
      23: invokevirtual #15                 // Method java/lang/StringBuilder.append:(Ljava/lang/String;)Ljava/lang/StringBuilder;
      26: aload_2
      27: invokevirtual #16                 // Method com/google/protobuf/Descriptors$MethodDescriptor.getName:()Ljava/lang/String;
      30: invokevirtual #15                 // Method java/lang/StringBuilder.append:(Ljava/lang/String;)Ljava/lang/StringBuilder;
      33: ldc           #17                 // String ,
      35: invokevirtual #15                 // Method java/lang/StringBuilder.append:(Ljava/lang/String;)Ljava/lang/StringBuilder;
      38: aload_3
      39: invokeinterface #18,  1           // InterfaceMethod com/google/protobuf/Message.toString:()Ljava/lang/String;
      44: invokevirtual #15                 // Method java/lang/StringBuilder.append:(Ljava/lang/String;)Ljava/lang/StringBuilder;
      47: invokevirtual #19                 // Method java/lang/StringBuilder.toString:()Ljava/lang/String;
      50: invokeinterface #20,  2           // InterfaceMethod org/slf4j/Logger.trace:(Ljava/lang/String;)V
      55: aload_0
      56: getfield      #1                  // Field row:[B
      59: ifnonnull     72
      62: new           #21                 // class java/lang/NullPointerException
      65: dup
      66: ldc           #22                 // String Can't be null!
      68: invokespecial #23                 // Method java/lang/NullPointerException."<init>":(Ljava/lang/String;)V
      71: athrow
      72: new           #24                 // class org/apache/hadoop/hbase/client/RegionCoprocessorRpcChannel$1
      75: dup
      76: aload_0
      77: aload_0
      78: getfield      #4                  // Field conn:Lorg/apache/hadoop/hbase/client/ClusterConnection;
      81: aload_0
      82: getfield      #3                  // Field table:Lorg/apache/hadoop/hbase/TableName;
      85: aload_0
      86: getfield      #1                  // Field row:[B
      89: aload_0
      90: getfield      #4                  // Field conn:Lorg/apache/hadoop/hbase/client/ClusterConnection;
      93: invokeinterface #25,  1           // InterfaceMethod org/apache/hadoop/hbase/client/ClusterConnection.getRpcControllerFactory:()Lorg/apache/hadoop/hbase/ipc/RpcControllerFactory;
      98: invokevirtual #26                 // Method org/apache/hadoop/hbase/ipc/RpcControllerFactory.newController:()Lorg/apache/hadoop/hbase/ipc/HBaseRpcController;
     101: iconst_m1
     102: aload_2
     103: aload_3
     104: invokespecial #28                 // Method org/apache/hadoop/hbase/client/RegionCoprocessorRpcChannel$1."<init>":(Lorg/apache/hadoop/hbase/client/RegionCoprocessorRpcChannel;Lorg/apache/hadoop/hbase/client/Connection;Lorg/apache/hadoop/hbase/TableName;[BLorg/apache/hbase/thirdparty/com/google/protobuf/RpcController;ILcom/google/protobuf/Descriptors$MethodDescriptor;Lcom/google/protobuf/Message;)V
     107: astore        5
     109: aload_0
     110: getfield      #9                  // Field rpcCallerFactory:Lorg/apache/hadoop/hbase/client/RpcRetryingCallerFactory;
     113: invokevirtual #29                 // Method org/apache/hadoop/hbase/client/RpcRetryingCallerFactory.newCaller:()Lorg/apache/hadoop/hbase/client/RpcRetryingCaller;
     116: aload         5
     118: aload_0
     119: getfield      #7                  // Field operationTimeout:I
     122: invokeinterface #30,  3           // InterfaceMethod org/apache/hadoop/hbase/client/RpcRetryingCaller.callWithRetries:(Lorg/apache/hadoop/hbase/client/RetryingCallable;I)Ljava/lang/Object;
     127: checkcast     #31                 // class org/apache/hadoop/hbase/shaded/protobuf/generated/ClientProtos$CoprocessorServiceResponse
     130: astore        6
     132: aload_0
     133: aload         6
     135: invokevirtual #32                 // Method org/apache/hadoop/hbase/shaded/protobuf/generated/ClientProtos$CoprocessorServiceResponse.getRegion:()Lorg/apache/hadoop/hbase/shaded/protobuf/generated/HBaseProtos$RegionSpecifier;
     138: invokevirtual #33                 // Method org/apache/hadoop/hbase/shaded/protobuf/generated/HBaseProtos$RegionSpecifier.getValue:()Lorg/apache/hbase/thirdparty/com/google/protobuf/ByteString;
     141: invokevirtual #34                 // Method org/apache/hbase/thirdparty/com/google/protobuf/ByteString.toByteArray:()[B
     144: putfield      #35                 // Field lastRegion:[B
     147: aload         6
     149: aload         4
     151: invokestatic  #36                 // Method org/apache/hadoop/hbase/ipc/CoprocessorRpcUtils.getResponse:(Lorg/apache/hadoop/hbase/shaded/protobuf/generated/ClientProtos$CoprocessorServiceResponse;Lcom/google/protobuf/Message;)Lcom/google/protobuf/Message;
     154: areturn

  public byte[] getLastRegion();
    Code:
       0: aload_0
       1: getfield      #35                 // Field lastRegion:[B
       4: areturn

  static byte[] access$000(org.apache.hadoop.hbase.client.RegionCoprocessorRpcChannel);
    Code:
       0: aload_0
       1: getfield      #1                  // Field row:[B
       4: areturn

  static {};
    Code:
       0: ldc           #37                 // class org/apache/hadoop/hbase/client/RegionCoprocessorRpcChannel
       2: invokestatic  #38                 // Method org/slf4j/LoggerFactory.getLogger:(Ljava/lang/Class;)Lorg/slf4j/Logger;
       5: putstatic     #10                 // Field LOG:Lorg/slf4j/Logger;
       8: return
}
