Compiled from "RegionServerTableMetrics.java"
public class org.apache.hadoop.hbase.regionserver.RegionServerTableMetrics {
  public org.apache.hadoop.hbase.regionserver.RegionServerTableMetrics();
    Code:
       0: aload_0
       1: invokespecial #1                  // Method java/lang/Object."<init>":()V
       4: aload_0
       5: ldc           #2                  // class org/apache/hadoop/hbase/regionserver/MetricsTableLatencies
       7: invokestatic  #3                  // Method org/apache/hadoop/hbase/CompatibilitySingletonFactory.getInstance:(Ljava/lang/Class;)Ljava/lang/Object;
      10: checkcast     #2                  // class org/apache/hadoop/hbase/regionserver/MetricsTableLatencies
      13: putfield      #4                  // Field latencies:Lorg/apache/hadoop/hbase/regionserver/MetricsTableLatencies;
      16: return

  public void updatePut(org.apache.hadoop.hbase.TableName, long);
    Code:
       0: aload_0
       1: getfield      #4                  // Field latencies:Lorg/apache/hadoop/hbase/regionserver/MetricsTableLatencies;
       4: aload_1
       5: invokevirtual #5                  // Method org/apache/hadoop/hbase/TableName.getNameAsString:()Ljava/lang/String;
       8: lload_2
       9: invokeinterface #6,  4            // InterfaceMethod org/apache/hadoop/hbase/regionserver/MetricsTableLatencies.updatePut:(Ljava/lang/String;J)V
      14: return

  public void updatePutBatch(org.apache.hadoop.hbase.TableName, long);
    Code:
       0: aload_0
       1: getfield      #4                  // Field latencies:Lorg/apache/hadoop/hbase/regionserver/MetricsTableLatencies;
       4: aload_1
       5: invokevirtual #5                  // Method org/apache/hadoop/hbase/TableName.getNameAsString:()Ljava/lang/String;
       8: lload_2
       9: invokeinterface #7,  4            // InterfaceMethod org/apache/hadoop/hbase/regionserver/MetricsTableLatencies.updatePutBatch:(Ljava/lang/String;J)V
      14: return

  public void updateGet(org.apache.hadoop.hbase.TableName, long);
    Code:
       0: aload_0
       1: getfield      #4                  // Field latencies:Lorg/apache/hadoop/hbase/regionserver/MetricsTableLatencies;
       4: aload_1
       5: invokevirtual #5                  // Method org/apache/hadoop/hbase/TableName.getNameAsString:()Ljava/lang/String;
       8: lload_2
       9: invokeinterface #8,  4            // InterfaceMethod org/apache/hadoop/hbase/regionserver/MetricsTableLatencies.updateGet:(Ljava/lang/String;J)V
      14: return

  public void updateIncrement(org.apache.hadoop.hbase.TableName, long);
    Code:
       0: aload_0
       1: getfield      #4                  // Field latencies:Lorg/apache/hadoop/hbase/regionserver/MetricsTableLatencies;
       4: aload_1
       5: invokevirtual #5                  // Method org/apache/hadoop/hbase/TableName.getNameAsString:()Ljava/lang/String;
       8: lload_2
       9: invokeinterface #9,  4            // InterfaceMethod org/apache/hadoop/hbase/regionserver/MetricsTableLatencies.updateIncrement:(Ljava/lang/String;J)V
      14: return

  public void updateAppend(org.apache.hadoop.hbase.TableName, long);
    Code:
       0: aload_0
       1: getfield      #4                  // Field latencies:Lorg/apache/hadoop/hbase/regionserver/MetricsTableLatencies;
       4: aload_1
       5: invokevirtual #5                  // Method org/apache/hadoop/hbase/TableName.getNameAsString:()Ljava/lang/String;
       8: lload_2
       9: invokeinterface #10,  4           // InterfaceMethod org/apache/hadoop/hbase/regionserver/MetricsTableLatencies.updateAppend:(Ljava/lang/String;J)V
      14: return

  public void updateDelete(org.apache.hadoop.hbase.TableName, long);
    Code:
       0: aload_0
       1: getfield      #4                  // Field latencies:Lorg/apache/hadoop/hbase/regionserver/MetricsTableLatencies;
       4: aload_1
       5: invokevirtual #5                  // Method org/apache/hadoop/hbase/TableName.getNameAsString:()Ljava/lang/String;
       8: lload_2
       9: invokeinterface #11,  4           // InterfaceMethod org/apache/hadoop/hbase/regionserver/MetricsTableLatencies.updateDelete:(Ljava/lang/String;J)V
      14: return

  public void updateDeleteBatch(org.apache.hadoop.hbase.TableName, long);
    Code:
       0: aload_0
       1: getfield      #4                  // Field latencies:Lorg/apache/hadoop/hbase/regionserver/MetricsTableLatencies;
       4: aload_1
       5: invokevirtual #5                  // Method org/apache/hadoop/hbase/TableName.getNameAsString:()Ljava/lang/String;
       8: lload_2
       9: invokeinterface #12,  4           // InterfaceMethod org/apache/hadoop/hbase/regionserver/MetricsTableLatencies.updateDeleteBatch:(Ljava/lang/String;J)V
      14: return

  public void updateScanTime(org.apache.hadoop.hbase.TableName, long);
    Code:
       0: aload_0
       1: getfield      #4                  // Field latencies:Lorg/apache/hadoop/hbase/regionserver/MetricsTableLatencies;
       4: aload_1
       5: invokevirtual #5                  // Method org/apache/hadoop/hbase/TableName.getNameAsString:()Ljava/lang/String;
       8: lload_2
       9: invokeinterface #13,  4           // InterfaceMethod org/apache/hadoop/hbase/regionserver/MetricsTableLatencies.updateScanTime:(Ljava/lang/String;J)V
      14: return

  public void updateScanSize(org.apache.hadoop.hbase.TableName, long);
    Code:
       0: aload_0
       1: getfield      #4                  // Field latencies:Lorg/apache/hadoop/hbase/regionserver/MetricsTableLatencies;
       4: aload_1
       5: invokevirtual #5                  // Method org/apache/hadoop/hbase/TableName.getNameAsString:()Ljava/lang/String;
       8: lload_2
       9: invokeinterface #14,  4           // InterfaceMethod org/apache/hadoop/hbase/regionserver/MetricsTableLatencies.updateScanSize:(Ljava/lang/String;J)V
      14: return
}
