Compiled from "RegionServerStatusProtos.java"
final class org.apache.hadoop.hbase.shaded.protobuf.generated.RegionServerStatusProtos$RegionServerStatusService$1 extends org.apache.hadoop.hbase.shaded.protobuf.generated.RegionServerStatusProtos$RegionServerStatusService {
  final org.apache.hadoop.hbase.shaded.protobuf.generated.RegionServerStatusProtos$RegionServerStatusService$Interface val$impl;

  org.apache.hadoop.hbase.shaded.protobuf.generated.RegionServerStatusProtos$RegionServerStatusService$1(org.apache.hadoop.hbase.shaded.protobuf.generated.RegionServerStatusProtos$RegionServerStatusService$Interface);
    Code:
       0: aload_0
       1: aload_1
       2: putfield      #1                  // Field val$impl:Lorg/apache/hadoop/hbase/shaded/protobuf/generated/RegionServerStatusProtos$RegionServerStatusService$Interface;
       5: aload_0
       6: invokespecial #2                  // Method org/apache/hadoop/hbase/shaded/protobuf/generated/RegionServerStatusProtos$RegionServerStatusService."<init>":()V
       9: return

  public void regionServerStartup(org.apache.hbase.thirdparty.com.google.protobuf.RpcController, org.apache.hadoop.hbase.shaded.protobuf.generated.RegionServerStatusProtos$RegionServerStartupRequest, org.apache.hbase.thirdparty.com.google.protobuf.RpcCallback<org.apache.hadoop.hbase.shaded.protobuf.generated.RegionServerStatusProtos$RegionServerStartupResponse>);
    Code:
       0: aload_0
       1: getfield      #1                  // Field val$impl:Lorg/apache/hadoop/hbase/shaded/protobuf/generated/RegionServerStatusProtos$RegionServerStatusService$Interface;
       4: aload_1
       5: aload_2
       6: aload_3
       7: invokeinterface #3,  4            // InterfaceMethod org/apache/hadoop/hbase/shaded/protobuf/generated/RegionServerStatusProtos$RegionServerStatusService$Interface.regionServerStartup:(Lorg/apache/hbase/thirdparty/com/google/protobuf/RpcController;Lorg/apache/hadoop/hbase/shaded/protobuf/generated/RegionServerStatusProtos$RegionServerStartupRequest;Lorg/apache/hbase/thirdparty/com/google/protobuf/RpcCallback;)V
      12: return

  public void regionServerReport(org.apache.hbase.thirdparty.com.google.protobuf.RpcController, org.apache.hadoop.hbase.shaded.protobuf.generated.RegionServerStatusProtos$RegionServerReportRequest, org.apache.hbase.thirdparty.com.google.protobuf.RpcCallback<org.apache.hadoop.hbase.shaded.protobuf.generated.RegionServerStatusProtos$RegionServerReportResponse>);
    Code:
       0: aload_0
       1: getfield      #1                  // Field val$impl:Lorg/apache/hadoop/hbase/shaded/protobuf/generated/RegionServerStatusProtos$RegionServerStatusService$Interface;
       4: aload_1
       5: aload_2
       6: aload_3
       7: invokeinterface #4,  4            // InterfaceMethod org/apache/hadoop/hbase/shaded/protobuf/generated/RegionServerStatusProtos$RegionServerStatusService$Interface.regionServerReport:(Lorg/apache/hbase/thirdparty/com/google/protobuf/RpcController;Lorg/apache/hadoop/hbase/shaded/protobuf/generated/RegionServerStatusProtos$RegionServerReportRequest;Lorg/apache/hbase/thirdparty/com/google/protobuf/RpcCallback;)V
      12: return

  public void reportRSFatalError(org.apache.hbase.thirdparty.com.google.protobuf.RpcController, org.apache.hadoop.hbase.shaded.protobuf.generated.RegionServerStatusProtos$ReportRSFatalErrorRequest, org.apache.hbase.thirdparty.com.google.protobuf.RpcCallback<org.apache.hadoop.hbase.shaded.protobuf.generated.RegionServerStatusProtos$ReportRSFatalErrorResponse>);
    Code:
       0: aload_0
       1: getfield      #1                  // Field val$impl:Lorg/apache/hadoop/hbase/shaded/protobuf/generated/RegionServerStatusProtos$RegionServerStatusService$Interface;
       4: aload_1
       5: aload_2
       6: aload_3
       7: invokeinterface #5,  4            // InterfaceMethod org/apache/hadoop/hbase/shaded/protobuf/generated/RegionServerStatusProtos$RegionServerStatusService$Interface.reportRSFatalError:(Lorg/apache/hbase/thirdparty/com/google/protobuf/RpcController;Lorg/apache/hadoop/hbase/shaded/protobuf/generated/RegionServerStatusProtos$ReportRSFatalErrorRequest;Lorg/apache/hbase/thirdparty/com/google/protobuf/RpcCallback;)V
      12: return

  public void getLastFlushedSequenceId(org.apache.hbase.thirdparty.com.google.protobuf.RpcController, org.apache.hadoop.hbase.shaded.protobuf.generated.RegionServerStatusProtos$GetLastFlushedSequenceIdRequest, org.apache.hbase.thirdparty.com.google.protobuf.RpcCallback<org.apache.hadoop.hbase.shaded.protobuf.generated.RegionServerStatusProtos$GetLastFlushedSequenceIdResponse>);
    Code:
       0: aload_0
       1: getfield      #1                  // Field val$impl:Lorg/apache/hadoop/hbase/shaded/protobuf/generated/RegionServerStatusProtos$RegionServerStatusService$Interface;
       4: aload_1
       5: aload_2
       6: aload_3
       7: invokeinterface #6,  4            // InterfaceMethod org/apache/hadoop/hbase/shaded/protobuf/generated/RegionServerStatusProtos$RegionServerStatusService$Interface.getLastFlushedSequenceId:(Lorg/apache/hbase/thirdparty/com/google/protobuf/RpcController;Lorg/apache/hadoop/hbase/shaded/protobuf/generated/RegionServerStatusProtos$GetLastFlushedSequenceIdRequest;Lorg/apache/hbase/thirdparty/com/google/protobuf/RpcCallback;)V
      12: return

  public void reportRegionStateTransition(org.apache.hbase.thirdparty.com.google.protobuf.RpcController, org.apache.hadoop.hbase.shaded.protobuf.generated.RegionServerStatusProtos$ReportRegionStateTransitionRequest, org.apache.hbase.thirdparty.com.google.protobuf.RpcCallback<org.apache.hadoop.hbase.shaded.protobuf.generated.RegionServerStatusProtos$ReportRegionStateTransitionResponse>);
    Code:
       0: aload_0
       1: getfield      #1                  // Field val$impl:Lorg/apache/hadoop/hbase/shaded/protobuf/generated/RegionServerStatusProtos$RegionServerStatusService$Interface;
       4: aload_1
       5: aload_2
       6: aload_3
       7: invokeinterface #7,  4            // InterfaceMethod org/apache/hadoop/hbase/shaded/protobuf/generated/RegionServerStatusProtos$RegionServerStatusService$Interface.reportRegionStateTransition:(Lorg/apache/hbase/thirdparty/com/google/protobuf/RpcController;Lorg/apache/hadoop/hbase/shaded/protobuf/generated/RegionServerStatusProtos$ReportRegionStateTransitionRequest;Lorg/apache/hbase/thirdparty/com/google/protobuf/RpcCallback;)V
      12: return

  public void reportRegionSpaceUse(org.apache.hbase.thirdparty.com.google.protobuf.RpcController, org.apache.hadoop.hbase.shaded.protobuf.generated.RegionServerStatusProtos$RegionSpaceUseReportRequest, org.apache.hbase.thirdparty.com.google.protobuf.RpcCallback<org.apache.hadoop.hbase.shaded.protobuf.generated.RegionServerStatusProtos$RegionSpaceUseReportResponse>);
    Code:
       0: aload_0
       1: getfield      #1                  // Field val$impl:Lorg/apache/hadoop/hbase/shaded/protobuf/generated/RegionServerStatusProtos$RegionServerStatusService$Interface;
       4: aload_1
       5: aload_2
       6: aload_3
       7: invokeinterface #8,  4            // InterfaceMethod org/apache/hadoop/hbase/shaded/protobuf/generated/RegionServerStatusProtos$RegionServerStatusService$Interface.reportRegionSpaceUse:(Lorg/apache/hbase/thirdparty/com/google/protobuf/RpcController;Lorg/apache/hadoop/hbase/shaded/protobuf/generated/RegionServerStatusProtos$RegionSpaceUseReportRequest;Lorg/apache/hbase/thirdparty/com/google/protobuf/RpcCallback;)V
      12: return

  public void reportProcedureDone(org.apache.hbase.thirdparty.com.google.protobuf.RpcController, org.apache.hadoop.hbase.shaded.protobuf.generated.RegionServerStatusProtos$ReportProcedureDoneRequest, org.apache.hbase.thirdparty.com.google.protobuf.RpcCallback<org.apache.hadoop.hbase.shaded.protobuf.generated.RegionServerStatusProtos$ReportProcedureDoneResponse>);
    Code:
       0: aload_0
       1: getfield      #1                  // Field val$impl:Lorg/apache/hadoop/hbase/shaded/protobuf/generated/RegionServerStatusProtos$RegionServerStatusService$Interface;
       4: aload_1
       5: aload_2
       6: aload_3
       7: invokeinterface #9,  4            // InterfaceMethod org/apache/hadoop/hbase/shaded/protobuf/generated/RegionServerStatusProtos$RegionServerStatusService$Interface.reportProcedureDone:(Lorg/apache/hbase/thirdparty/com/google/protobuf/RpcController;Lorg/apache/hadoop/hbase/shaded/protobuf/generated/RegionServerStatusProtos$ReportProcedureDoneRequest;Lorg/apache/hbase/thirdparty/com/google/protobuf/RpcCallback;)V
      12: return

  public void reportFileArchival(org.apache.hbase.thirdparty.com.google.protobuf.RpcController, org.apache.hadoop.hbase.shaded.protobuf.generated.RegionServerStatusProtos$FileArchiveNotificationRequest, org.apache.hbase.thirdparty.com.google.protobuf.RpcCallback<org.apache.hadoop.hbase.shaded.protobuf.generated.RegionServerStatusProtos$FileArchiveNotificationResponse>);
    Code:
       0: aload_0
       1: getfield      #1                  // Field val$impl:Lorg/apache/hadoop/hbase/shaded/protobuf/generated/RegionServerStatusProtos$RegionServerStatusService$Interface;
       4: aload_1
       5: aload_2
       6: aload_3
       7: invokeinterface #10,  4           // InterfaceMethod org/apache/hadoop/hbase/shaded/protobuf/generated/RegionServerStatusProtos$RegionServerStatusService$Interface.reportFileArchival:(Lorg/apache/hbase/thirdparty/com/google/protobuf/RpcController;Lorg/apache/hadoop/hbase/shaded/protobuf/generated/RegionServerStatusProtos$FileArchiveNotificationRequest;Lorg/apache/hbase/thirdparty/com/google/protobuf/RpcCallback;)V
      12: return
}
