Compiled from "RegionServerListTmpl.java"
public class org.apache.hadoop.hbase.tmpl.master.RegionServerListTmpl$ImplData extends org.jamon.AbstractTemplateProxy$ImplData {
  public org.apache.hadoop.hbase.tmpl.master.RegionServerListTmpl$ImplData();
    Code:
       0: aload_0
       1: invokespecial #1                  // Method org/jamon/AbstractTemplateProxy$ImplData."<init>":()V
       4: return

  public void setMaster(org.apache.hadoop.hbase.master.HMaster);
    Code:
       0: aload_0
       1: aload_1
       2: putfield      #2                  // Field m_master:Lorg/apache/hadoop/hbase/master/HMaster;
       5: return

  public org.apache.hadoop.hbase.master.HMaster getMaster();
    Code:
       0: aload_0
       1: getfield      #2                  // Field m_master:Lorg/apache/hadoop/hbase/master/HMaster;
       4: areturn

  public void setServers(java.util.List<org.apache.hadoop.hbase.ServerName>);
    Code:
       0: aload_0
       1: aload_1
       2: putfield      #3                  // Field m_servers:Ljava/util/List;
       5: aload_0
       6: iconst_1
       7: putfield      #4                  // Field m_servers__IsNotDefault:Z
      10: return

  public java.util.List<org.apache.hadoop.hbase.ServerName> getServers();
    Code:
       0: aload_0
       1: getfield      #3                  // Field m_servers:Ljava/util/List;
       4: areturn

  public boolean getServers__IsNotDefault();
    Code:
       0: aload_0
       1: getfield      #4                  // Field m_servers__IsNotDefault:Z
       4: ireturn
}
