Compiled from "RegionMetricsBuilder.java"
public final class org.apache.hadoop.hbase.RegionMetricsBuilder {
  public static java.util.List<org.apache.hadoop.hbase.RegionMetrics> toRegionMetrics(org.apache.hadoop.hbase.shaded.protobuf.generated.AdminProtos$GetRegionLoadResponse);
    Code:
       0: aload_0
       1: invokevirtual #1                  // Method org/apache/hadoop/hbase/shaded/protobuf/generated/AdminProtos$GetRegionLoadResponse.getRegionLoadsList:()Ljava/util/List;
       4: invokeinterface #2,  1            // InterfaceMethod java/util/List.stream:()Ljava/util/stream/Stream;
       9: invokedynamic #3,  0              // InvokeDynamic #0:apply:()Ljava/util/function/Function;
      14: invokeinterface #4,  2            // InterfaceMethod java/util/stream/Stream.map:(Ljava/util/function/Function;)Ljava/util/stream/Stream;
      19: invokestatic  #5                  // Method java/util/stream/Collectors.toList:()Ljava/util/stream/Collector;
      22: invokeinterface #6,  2            // InterfaceMethod java/util/stream/Stream.collect:(Ljava/util/stream/Collector;)Ljava/lang/Object;
      27: checkcast     #7                  // class java/util/List
      30: areturn

  public static org.apache.hadoop.hbase.RegionMetrics toRegionMetrics(org.apache.hadoop.hbase.shaded.protobuf.generated.ClusterStatusProtos$RegionLoad);
    Code:
       0: aload_0
       1: invokevirtual #8                  // Method org/apache/hadoop/hbase/shaded/protobuf/generated/ClusterStatusProtos$RegionLoad.getRegionSpecifier:()Lorg/apache/hadoop/hbase/shaded/protobuf/generated/HBaseProtos$RegionSpecifier;
       4: invokevirtual #9                  // Method org/apache/hadoop/hbase/shaded/protobuf/generated/HBaseProtos$RegionSpecifier.getValue:()Lorg/apache/hbase/thirdparty/com/google/protobuf/ByteString;
       7: invokevirtual #10                 // Method org/apache/hbase/thirdparty/com/google/protobuf/ByteString.toByteArray:()[B
      10: invokestatic  #11                 // Method newBuilder:([B)Lorg/apache/hadoop/hbase/RegionMetricsBuilder;
      13: new           #12                 // class org/apache/hadoop/hbase/Size
      16: dup
      17: aload_0
      18: invokevirtual #13                 // Method org/apache/hadoop/hbase/shaded/protobuf/generated/ClusterStatusProtos$RegionLoad.getTotalStaticBloomSizeKB:()I
      21: i2d
      22: getstatic     #14                 // Field org/apache/hadoop/hbase/Size$Unit.KILOBYTE:Lorg/apache/hadoop/hbase/Size$Unit;
      25: invokespecial #15                 // Method org/apache/hadoop/hbase/Size."<init>":(DLorg/apache/hadoop/hbase/Size$Unit;)V
      28: invokevirtual #16                 // Method setBloomFilterSize:(Lorg/apache/hadoop/hbase/Size;)Lorg/apache/hadoop/hbase/RegionMetricsBuilder;
      31: aload_0
      32: invokevirtual #17                 // Method org/apache/hadoop/hbase/shaded/protobuf/generated/ClusterStatusProtos$RegionLoad.getCurrentCompactedKVs:()J
      35: invokevirtual #18                 // Method setCompactedCellCount:(J)Lorg/apache/hadoop/hbase/RegionMetricsBuilder;
      38: aload_0
      39: invokevirtual #19                 // Method org/apache/hadoop/hbase/shaded/protobuf/generated/ClusterStatusProtos$RegionLoad.getTotalCompactingKVs:()J
      42: invokevirtual #20                 // Method setCompactingCellCount:(J)Lorg/apache/hadoop/hbase/RegionMetricsBuilder;
      45: aload_0
      46: invokevirtual #21                 // Method org/apache/hadoop/hbase/shaded/protobuf/generated/ClusterStatusProtos$RegionLoad.getCompleteSequenceId:()J
      49: invokevirtual #22                 // Method setCompletedSequenceId:(J)Lorg/apache/hadoop/hbase/RegionMetricsBuilder;
      52: aload_0
      53: invokevirtual #23                 // Method org/apache/hadoop/hbase/shaded/protobuf/generated/ClusterStatusProtos$RegionLoad.hasDataLocality:()Z
      56: ifeq          66
      59: aload_0
      60: invokevirtual #24                 // Method org/apache/hadoop/hbase/shaded/protobuf/generated/ClusterStatusProtos$RegionLoad.getDataLocality:()F
      63: goto          67
      66: fconst_0
      67: invokevirtual #25                 // Method setDataLocality:(F)Lorg/apache/hadoop/hbase/RegionMetricsBuilder;
      70: aload_0
      71: invokevirtual #26                 // Method org/apache/hadoop/hbase/shaded/protobuf/generated/ClusterStatusProtos$RegionLoad.getFilteredReadRequestsCount:()J
      74: invokevirtual #27                 // Method setFilteredReadRequestCount:(J)Lorg/apache/hadoop/hbase/RegionMetricsBuilder;
      77: new           #12                 // class org/apache/hadoop/hbase/Size
      80: dup
      81: aload_0
      82: invokevirtual #28                 // Method org/apache/hadoop/hbase/shaded/protobuf/generated/ClusterStatusProtos$RegionLoad.getTotalStaticIndexSizeKB:()I
      85: i2d
      86: getstatic     #14                 // Field org/apache/hadoop/hbase/Size$Unit.KILOBYTE:Lorg/apache/hadoop/hbase/Size$Unit;
      89: invokespecial #15                 // Method org/apache/hadoop/hbase/Size."<init>":(DLorg/apache/hadoop/hbase/Size$Unit;)V
      92: invokevirtual #29                 // Method setStoreFileUncompressedDataIndexSize:(Lorg/apache/hadoop/hbase/Size;)Lorg/apache/hadoop/hbase/RegionMetricsBuilder;
      95: aload_0
      96: invokevirtual #30                 // Method org/apache/hadoop/hbase/shaded/protobuf/generated/ClusterStatusProtos$RegionLoad.getLastMajorCompactionTs:()J
      99: invokevirtual #31                 // Method setLastMajorCompactionTimestamp:(J)Lorg/apache/hadoop/hbase/RegionMetricsBuilder;
     102: new           #12                 // class org/apache/hadoop/hbase/Size
     105: dup
     106: aload_0
     107: invokevirtual #32                 // Method org/apache/hadoop/hbase/shaded/protobuf/generated/ClusterStatusProtos$RegionLoad.getMemStoreSizeMB:()I
     110: i2d
     111: getstatic     #33                 // Field org/apache/hadoop/hbase/Size$Unit.MEGABYTE:Lorg/apache/hadoop/hbase/Size$Unit;
     114: invokespecial #15                 // Method org/apache/hadoop/hbase/Size."<init>":(DLorg/apache/hadoop/hbase/Size$Unit;)V
     117: invokevirtual #34                 // Method setMemStoreSize:(Lorg/apache/hadoop/hbase/Size;)Lorg/apache/hadoop/hbase/RegionMetricsBuilder;
     120: aload_0
     121: invokevirtual #35                 // Method org/apache/hadoop/hbase/shaded/protobuf/generated/ClusterStatusProtos$RegionLoad.getReadRequestsCount:()J
     124: invokevirtual #36                 // Method setReadRequestCount:(J)Lorg/apache/hadoop/hbase/RegionMetricsBuilder;
     127: aload_0
     128: invokevirtual #37                 // Method org/apache/hadoop/hbase/shaded/protobuf/generated/ClusterStatusProtos$RegionLoad.getCpRequestsCount:()J
     131: invokevirtual #38                 // Method setCpRequestCount:(J)Lorg/apache/hadoop/hbase/RegionMetricsBuilder;
     134: aload_0
     135: invokevirtual #39                 // Method org/apache/hadoop/hbase/shaded/protobuf/generated/ClusterStatusProtos$RegionLoad.getWriteRequestsCount:()J
     138: invokevirtual #40                 // Method setWriteRequestCount:(J)Lorg/apache/hadoop/hbase/RegionMetricsBuilder;
     141: new           #12                 // class org/apache/hadoop/hbase/Size
     144: dup
     145: aload_0
     146: invokevirtual #41                 // Method org/apache/hadoop/hbase/shaded/protobuf/generated/ClusterStatusProtos$RegionLoad.getStorefileIndexSizeKB:()J
     149: l2d
     150: getstatic     #14                 // Field org/apache/hadoop/hbase/Size$Unit.KILOBYTE:Lorg/apache/hadoop/hbase/Size$Unit;
     153: invokespecial #15                 // Method org/apache/hadoop/hbase/Size."<init>":(DLorg/apache/hadoop/hbase/Size$Unit;)V
     156: invokevirtual #42                 // Method setStoreFileIndexSize:(Lorg/apache/hadoop/hbase/Size;)Lorg/apache/hadoop/hbase/RegionMetricsBuilder;
     159: new           #12                 // class org/apache/hadoop/hbase/Size
     162: dup
     163: aload_0
     164: invokevirtual #43                 // Method org/apache/hadoop/hbase/shaded/protobuf/generated/ClusterStatusProtos$RegionLoad.getRootIndexSizeKB:()I
     167: i2d
     168: getstatic     #14                 // Field org/apache/hadoop/hbase/Size$Unit.KILOBYTE:Lorg/apache/hadoop/hbase/Size$Unit;
     171: invokespecial #15                 // Method org/apache/hadoop/hbase/Size."<init>":(DLorg/apache/hadoop/hbase/Size$Unit;)V
     174: invokevirtual #44                 // Method setStoreFileRootLevelIndexSize:(Lorg/apache/hadoop/hbase/Size;)Lorg/apache/hadoop/hbase/RegionMetricsBuilder;
     177: aload_0
     178: invokevirtual #45                 // Method org/apache/hadoop/hbase/shaded/protobuf/generated/ClusterStatusProtos$RegionLoad.getStores:()I
     181: invokevirtual #46                 // Method setStoreCount:(I)Lorg/apache/hadoop/hbase/RegionMetricsBuilder;
     184: aload_0
     185: invokevirtual #47                 // Method org/apache/hadoop/hbase/shaded/protobuf/generated/ClusterStatusProtos$RegionLoad.getStorefiles:()I
     188: invokevirtual #48                 // Method setStoreFileCount:(I)Lorg/apache/hadoop/hbase/RegionMetricsBuilder;
     191: aload_0
     192: invokevirtual #49                 // Method org/apache/hadoop/hbase/shaded/protobuf/generated/ClusterStatusProtos$RegionLoad.getStoreRefCount:()I
     195: invokevirtual #50                 // Method setStoreRefCount:(I)Lorg/apache/hadoop/hbase/RegionMetricsBuilder;
     198: new           #12                 // class org/apache/hadoop/hbase/Size
     201: dup
     202: aload_0
     203: invokevirtual #51                 // Method org/apache/hadoop/hbase/shaded/protobuf/generated/ClusterStatusProtos$RegionLoad.getStorefileSizeMB:()I
     206: i2d
     207: getstatic     #33                 // Field org/apache/hadoop/hbase/Size$Unit.MEGABYTE:Lorg/apache/hadoop/hbase/Size$Unit;
     210: invokespecial #15                 // Method org/apache/hadoop/hbase/Size."<init>":(DLorg/apache/hadoop/hbase/Size$Unit;)V
     213: invokevirtual #52                 // Method setStoreFileSize:(Lorg/apache/hadoop/hbase/Size;)Lorg/apache/hadoop/hbase/RegionMetricsBuilder;
     216: aload_0
     217: invokevirtual #53                 // Method org/apache/hadoop/hbase/shaded/protobuf/generated/ClusterStatusProtos$RegionLoad.getStoreCompleteSequenceIdList:()Ljava/util/List;
     220: invokeinterface #2,  1            // InterfaceMethod java/util/List.stream:()Ljava/util/stream/Stream;
     225: invokedynamic #54,  0             // InvokeDynamic #1:apply:()Ljava/util/function/Function;
     230: invokedynamic #55,  0             // InvokeDynamic #2:apply:()Ljava/util/function/Function;
     235: invokestatic  #56                 // Method java/util/stream/Collectors.toMap:(Ljava/util/function/Function;Ljava/util/function/Function;)Ljava/util/stream/Collector;
     238: invokeinterface #6,  2            // InterfaceMethod java/util/stream/Stream.collect:(Ljava/util/stream/Collector;)Ljava/lang/Object;
     243: checkcast     #57                 // class java/util/Map
     246: invokevirtual #58                 // Method setStoreSequenceIds:(Ljava/util/Map;)Lorg/apache/hadoop/hbase/RegionMetricsBuilder;
     249: new           #12                 // class org/apache/hadoop/hbase/Size
     252: dup
     253: aload_0
     254: invokevirtual #59                 // Method org/apache/hadoop/hbase/shaded/protobuf/generated/ClusterStatusProtos$RegionLoad.getStoreUncompressedSizeMB:()I
     257: i2d
     258: getstatic     #33                 // Field org/apache/hadoop/hbase/Size$Unit.MEGABYTE:Lorg/apache/hadoop/hbase/Size$Unit;
     261: invokespecial #15                 // Method org/apache/hadoop/hbase/Size."<init>":(DLorg/apache/hadoop/hbase/Size$Unit;)V
     264: invokevirtual #60                 // Method setUncompressedStoreFileSize:(Lorg/apache/hadoop/hbase/Size;)Lorg/apache/hadoop/hbase/RegionMetricsBuilder;
     267: invokevirtual #61                 // Method build:()Lorg/apache/hadoop/hbase/RegionMetrics;
     270: areturn

  public static org.apache.hadoop.hbase.shaded.protobuf.generated.ClusterStatusProtos$RegionLoad toRegionLoad(org.apache.hadoop.hbase.RegionMetrics);
    Code:
       0: invokestatic  #65                 // Method org/apache/hadoop/hbase/shaded/protobuf/generated/ClusterStatusProtos$RegionLoad.newBuilder:()Lorg/apache/hadoop/hbase/shaded/protobuf/generated/ClusterStatusProtos$RegionLoad$Builder;
       3: invokestatic  #66                 // Method org/apache/hadoop/hbase/shaded/protobuf/generated/HBaseProtos$RegionSpecifier.newBuilder:()Lorg/apache/hadoop/hbase/shaded/protobuf/generated/HBaseProtos$RegionSpecifier$Builder;
       6: getstatic     #67                 // Field org/apache/hadoop/hbase/shaded/protobuf/generated/HBaseProtos$RegionSpecifier$RegionSpecifierType.REGION_NAME:Lorg/apache/hadoop/hbase/shaded/protobuf/generated/HBaseProtos$RegionSpecifier$RegionSpecifierType;
       9: invokevirtual #68                 // Method org/apache/hadoop/hbase/shaded/protobuf/generated/HBaseProtos$RegionSpecifier$Builder.setType:(Lorg/apache/hadoop/hbase/shaded/protobuf/generated/HBaseProtos$RegionSpecifier$RegionSpecifierType;)Lorg/apache/hadoop/hbase/shaded/protobuf/generated/HBaseProtos$RegionSpecifier$Builder;
      12: aload_0
      13: invokeinterface #69,  1           // InterfaceMethod org/apache/hadoop/hbase/RegionMetrics.getRegionName:()[B
      18: invokestatic  #70                 // Method org/apache/hbase/thirdparty/com/google/protobuf/UnsafeByteOperations.unsafeWrap:([B)Lorg/apache/hbase/thirdparty/com/google/protobuf/ByteString;
      21: invokevirtual #71                 // Method org/apache/hadoop/hbase/shaded/protobuf/generated/HBaseProtos$RegionSpecifier$Builder.setValue:(Lorg/apache/hbase/thirdparty/com/google/protobuf/ByteString;)Lorg/apache/hadoop/hbase/shaded/protobuf/generated/HBaseProtos$RegionSpecifier$Builder;
      24: invokevirtual #72                 // Method org/apache/hadoop/hbase/shaded/protobuf/generated/HBaseProtos$RegionSpecifier$Builder.build:()Lorg/apache/hadoop/hbase/shaded/protobuf/generated/HBaseProtos$RegionSpecifier;
      27: invokevirtual #73                 // Method org/apache/hadoop/hbase/shaded/protobuf/generated/ClusterStatusProtos$RegionLoad$Builder.setRegionSpecifier:(Lorg/apache/hadoop/hbase/shaded/protobuf/generated/HBaseProtos$RegionSpecifier;)Lorg/apache/hadoop/hbase/shaded/protobuf/generated/ClusterStatusProtos$RegionLoad$Builder;
      30: aload_0
      31: invokeinterface #74,  1           // InterfaceMethod org/apache/hadoop/hbase/RegionMetrics.getBloomFilterSize:()Lorg/apache/hadoop/hbase/Size;
      36: getstatic     #14                 // Field org/apache/hadoop/hbase/Size$Unit.KILOBYTE:Lorg/apache/hadoop/hbase/Size$Unit;
      39: invokevirtual #75                 // Method org/apache/hadoop/hbase/Size.get:(Lorg/apache/hadoop/hbase/Size$Unit;)D
      42: d2i
      43: invokevirtual #76                 // Method org/apache/hadoop/hbase/shaded/protobuf/generated/ClusterStatusProtos$RegionLoad$Builder.setTotalStaticBloomSizeKB:(I)Lorg/apache/hadoop/hbase/shaded/protobuf/generated/ClusterStatusProtos$RegionLoad$Builder;
      46: aload_0
      47: invokeinterface #77,  1           // InterfaceMethod org/apache/hadoop/hbase/RegionMetrics.getCompactedCellCount:()J
      52: invokevirtual #78                 // Method org/apache/hadoop/hbase/shaded/protobuf/generated/ClusterStatusProtos$RegionLoad$Builder.setCurrentCompactedKVs:(J)Lorg/apache/hadoop/hbase/shaded/protobuf/generated/ClusterStatusProtos$RegionLoad$Builder;
      55: aload_0
      56: invokeinterface #79,  1           // InterfaceMethod org/apache/hadoop/hbase/RegionMetrics.getCompactingCellCount:()J
      61: invokevirtual #80                 // Method org/apache/hadoop/hbase/shaded/protobuf/generated/ClusterStatusProtos$RegionLoad$Builder.setTotalCompactingKVs:(J)Lorg/apache/hadoop/hbase/shaded/protobuf/generated/ClusterStatusProtos$RegionLoad$Builder;
      64: aload_0
      65: invokeinterface #81,  1           // InterfaceMethod org/apache/hadoop/hbase/RegionMetrics.getCompletedSequenceId:()J
      70: invokevirtual #82                 // Method org/apache/hadoop/hbase/shaded/protobuf/generated/ClusterStatusProtos$RegionLoad$Builder.setCompleteSequenceId:(J)Lorg/apache/hadoop/hbase/shaded/protobuf/generated/ClusterStatusProtos$RegionLoad$Builder;
      73: aload_0
      74: invokeinterface #83,  1           // InterfaceMethod org/apache/hadoop/hbase/RegionMetrics.getDataLocality:()F
      79: invokevirtual #84                 // Method org/apache/hadoop/hbase/shaded/protobuf/generated/ClusterStatusProtos$RegionLoad$Builder.setDataLocality:(F)Lorg/apache/hadoop/hbase/shaded/protobuf/generated/ClusterStatusProtos$RegionLoad$Builder;
      82: aload_0
      83: invokeinterface #85,  1           // InterfaceMethod org/apache/hadoop/hbase/RegionMetrics.getFilteredReadRequestCount:()J
      88: invokevirtual #86                 // Method org/apache/hadoop/hbase/shaded/protobuf/generated/ClusterStatusProtos$RegionLoad$Builder.setFilteredReadRequestsCount:(J)Lorg/apache/hadoop/hbase/shaded/protobuf/generated/ClusterStatusProtos$RegionLoad$Builder;
      91: aload_0
      92: invokeinterface #87,  1           // InterfaceMethod org/apache/hadoop/hbase/RegionMetrics.getStoreFileUncompressedDataIndexSize:()Lorg/apache/hadoop/hbase/Size;
      97: getstatic     #14                 // Field org/apache/hadoop/hbase/Size$Unit.KILOBYTE:Lorg/apache/hadoop/hbase/Size$Unit;
     100: invokevirtual #75                 // Method org/apache/hadoop/hbase/Size.get:(Lorg/apache/hadoop/hbase/Size$Unit;)D
     103: d2i
     104: invokevirtual #88                 // Method org/apache/hadoop/hbase/shaded/protobuf/generated/ClusterStatusProtos$RegionLoad$Builder.setTotalStaticIndexSizeKB:(I)Lorg/apache/hadoop/hbase/shaded/protobuf/generated/ClusterStatusProtos$RegionLoad$Builder;
     107: aload_0
     108: invokeinterface #89,  1           // InterfaceMethod org/apache/hadoop/hbase/RegionMetrics.getLastMajorCompactionTimestamp:()J
     113: invokevirtual #90                 // Method org/apache/hadoop/hbase/shaded/protobuf/generated/ClusterStatusProtos$RegionLoad$Builder.setLastMajorCompactionTs:(J)Lorg/apache/hadoop/hbase/shaded/protobuf/generated/ClusterStatusProtos$RegionLoad$Builder;
     116: aload_0
     117: invokeinterface #91,  1           // InterfaceMethod org/apache/hadoop/hbase/RegionMetrics.getMemStoreSize:()Lorg/apache/hadoop/hbase/Size;
     122: getstatic     #33                 // Field org/apache/hadoop/hbase/Size$Unit.MEGABYTE:Lorg/apache/hadoop/hbase/Size$Unit;
     125: invokevirtual #75                 // Method org/apache/hadoop/hbase/Size.get:(Lorg/apache/hadoop/hbase/Size$Unit;)D
     128: d2i
     129: invokevirtual #92                 // Method org/apache/hadoop/hbase/shaded/protobuf/generated/ClusterStatusProtos$RegionLoad$Builder.setMemStoreSizeMB:(I)Lorg/apache/hadoop/hbase/shaded/protobuf/generated/ClusterStatusProtos$RegionLoad$Builder;
     132: aload_0
     133: invokeinterface #93,  1           // InterfaceMethod org/apache/hadoop/hbase/RegionMetrics.getReadRequestCount:()J
     138: invokevirtual #94                 // Method org/apache/hadoop/hbase/shaded/protobuf/generated/ClusterStatusProtos$RegionLoad$Builder.setReadRequestsCount:(J)Lorg/apache/hadoop/hbase/shaded/protobuf/generated/ClusterStatusProtos$RegionLoad$Builder;
     141: aload_0
     142: invokeinterface #95,  1           // InterfaceMethod org/apache/hadoop/hbase/RegionMetrics.getCpRequestCount:()J
     147: invokevirtual #96                 // Method org/apache/hadoop/hbase/shaded/protobuf/generated/ClusterStatusProtos$RegionLoad$Builder.setCpRequestsCount:(J)Lorg/apache/hadoop/hbase/shaded/protobuf/generated/ClusterStatusProtos$RegionLoad$Builder;
     150: aload_0
     151: invokeinterface #97,  1           // InterfaceMethod org/apache/hadoop/hbase/RegionMetrics.getWriteRequestCount:()J
     156: invokevirtual #98                 // Method org/apache/hadoop/hbase/shaded/protobuf/generated/ClusterStatusProtos$RegionLoad$Builder.setWriteRequestsCount:(J)Lorg/apache/hadoop/hbase/shaded/protobuf/generated/ClusterStatusProtos$RegionLoad$Builder;
     159: aload_0
     160: invokeinterface #99,  1           // InterfaceMethod org/apache/hadoop/hbase/RegionMetrics.getStoreFileIndexSize:()Lorg/apache/hadoop/hbase/Size;
     165: getstatic     #14                 // Field org/apache/hadoop/hbase/Size$Unit.KILOBYTE:Lorg/apache/hadoop/hbase/Size$Unit;
     168: invokevirtual #75                 // Method org/apache/hadoop/hbase/Size.get:(Lorg/apache/hadoop/hbase/Size$Unit;)D
     171: d2l
     172: invokevirtual #100                // Method org/apache/hadoop/hbase/shaded/protobuf/generated/ClusterStatusProtos$RegionLoad$Builder.setStorefileIndexSizeKB:(J)Lorg/apache/hadoop/hbase/shaded/protobuf/generated/ClusterStatusProtos$RegionLoad$Builder;
     175: aload_0
     176: invokeinterface #101,  1          // InterfaceMethod org/apache/hadoop/hbase/RegionMetrics.getStoreFileRootLevelIndexSize:()Lorg/apache/hadoop/hbase/Size;
     181: getstatic     #14                 // Field org/apache/hadoop/hbase/Size$Unit.KILOBYTE:Lorg/apache/hadoop/hbase/Size$Unit;
     184: invokevirtual #75                 // Method org/apache/hadoop/hbase/Size.get:(Lorg/apache/hadoop/hbase/Size$Unit;)D
     187: d2i
     188: invokevirtual #102                // Method org/apache/hadoop/hbase/shaded/protobuf/generated/ClusterStatusProtos$RegionLoad$Builder.setRootIndexSizeKB:(I)Lorg/apache/hadoop/hbase/shaded/protobuf/generated/ClusterStatusProtos$RegionLoad$Builder;
     191: aload_0
     192: invokeinterface #103,  1          // InterfaceMethod org/apache/hadoop/hbase/RegionMetrics.getStoreCount:()I
     197: invokevirtual #104                // Method org/apache/hadoop/hbase/shaded/protobuf/generated/ClusterStatusProtos$RegionLoad$Builder.setStores:(I)Lorg/apache/hadoop/hbase/shaded/protobuf/generated/ClusterStatusProtos$RegionLoad$Builder;
     200: aload_0
     201: invokeinterface #103,  1          // InterfaceMethod org/apache/hadoop/hbase/RegionMetrics.getStoreCount:()I
     206: invokevirtual #105                // Method org/apache/hadoop/hbase/shaded/protobuf/generated/ClusterStatusProtos$RegionLoad$Builder.setStorefiles:(I)Lorg/apache/hadoop/hbase/shaded/protobuf/generated/ClusterStatusProtos$RegionLoad$Builder;
     209: aload_0
     210: invokeinterface #106,  1          // InterfaceMethod org/apache/hadoop/hbase/RegionMetrics.getStoreRefCount:()I
     215: invokevirtual #107                // Method org/apache/hadoop/hbase/shaded/protobuf/generated/ClusterStatusProtos$RegionLoad$Builder.setStoreRefCount:(I)Lorg/apache/hadoop/hbase/shaded/protobuf/generated/ClusterStatusProtos$RegionLoad$Builder;
     218: aload_0
     219: invokeinterface #108,  1          // InterfaceMethod org/apache/hadoop/hbase/RegionMetrics.getStoreFileSize:()Lorg/apache/hadoop/hbase/Size;
     224: getstatic     #33                 // Field org/apache/hadoop/hbase/Size$Unit.MEGABYTE:Lorg/apache/hadoop/hbase/Size$Unit;
     227: invokevirtual #75                 // Method org/apache/hadoop/hbase/Size.get:(Lorg/apache/hadoop/hbase/Size$Unit;)D
     230: d2i
     231: invokevirtual #109                // Method org/apache/hadoop/hbase/shaded/protobuf/generated/ClusterStatusProtos$RegionLoad$Builder.setStorefileSizeMB:(I)Lorg/apache/hadoop/hbase/shaded/protobuf/generated/ClusterStatusProtos$RegionLoad$Builder;
     234: aload_0
     235: invokeinterface #110,  1          // InterfaceMethod org/apache/hadoop/hbase/RegionMetrics.getStoreSequenceId:()Ljava/util/Map;
     240: invokestatic  #111                // Method toStoreSequenceId:(Ljava/util/Map;)Ljava/util/List;
     243: invokevirtual #112                // Method org/apache/hadoop/hbase/shaded/protobuf/generated/ClusterStatusProtos$RegionLoad$Builder.addAllStoreCompleteSequenceId:(Ljava/lang/Iterable;)Lorg/apache/hadoop/hbase/shaded/protobuf/generated/ClusterStatusProtos$RegionLoad$Builder;
     246: aload_0
     247: invokeinterface #113,  1          // InterfaceMethod org/apache/hadoop/hbase/RegionMetrics.getUncompressedStoreFileSize:()Lorg/apache/hadoop/hbase/Size;
     252: getstatic     #33                 // Field org/apache/hadoop/hbase/Size$Unit.MEGABYTE:Lorg/apache/hadoop/hbase/Size$Unit;
     255: invokevirtual #75                 // Method org/apache/hadoop/hbase/Size.get:(Lorg/apache/hadoop/hbase/Size$Unit;)D
     258: d2i
     259: invokevirtual #114                // Method org/apache/hadoop/hbase/shaded/protobuf/generated/ClusterStatusProtos$RegionLoad$Builder.setStoreUncompressedSizeMB:(I)Lorg/apache/hadoop/hbase/shaded/protobuf/generated/ClusterStatusProtos$RegionLoad$Builder;
     262: invokevirtual #115                // Method org/apache/hadoop/hbase/shaded/protobuf/generated/ClusterStatusProtos$RegionLoad$Builder.build:()Lorg/apache/hadoop/hbase/shaded/protobuf/generated/ClusterStatusProtos$RegionLoad;
     265: areturn

  public static org.apache.hadoop.hbase.RegionMetricsBuilder newBuilder(byte[]);
    Code:
       0: new           #116                // class org/apache/hadoop/hbase/RegionMetricsBuilder
       3: dup
       4: aload_0
       5: invokespecial #117                // Method "<init>":([B)V
       8: areturn

  public org.apache.hadoop.hbase.RegionMetricsBuilder setStoreCount(int);
    Code:
       0: aload_0
       1: iload_1
       2: putfield      #130                // Field storeCount:I
       5: aload_0
       6: areturn

  public org.apache.hadoop.hbase.RegionMetricsBuilder setStoreFileCount(int);
    Code:
       0: aload_0
       1: iload_1
       2: putfield      #131                // Field storeFileCount:I
       5: aload_0
       6: areturn

  public org.apache.hadoop.hbase.RegionMetricsBuilder setStoreRefCount(int);
    Code:
       0: aload_0
       1: iload_1
       2: putfield      #132                // Field storeRefCount:I
       5: aload_0
       6: areturn

  public org.apache.hadoop.hbase.RegionMetricsBuilder setCompactingCellCount(long);
    Code:
       0: aload_0
       1: lload_1
       2: putfield      #133                // Field compactingCellCount:J
       5: aload_0
       6: areturn

  public org.apache.hadoop.hbase.RegionMetricsBuilder setCompactedCellCount(long);
    Code:
       0: aload_0
       1: lload_1
       2: putfield      #134                // Field compactedCellCount:J
       5: aload_0
       6: areturn

  public org.apache.hadoop.hbase.RegionMetricsBuilder setStoreFileSize(org.apache.hadoop.hbase.Size);
    Code:
       0: aload_0
       1: aload_1
       2: putfield      #120                // Field storeFileSize:Lorg/apache/hadoop/hbase/Size;
       5: aload_0
       6: areturn

  public org.apache.hadoop.hbase.RegionMetricsBuilder setMemStoreSize(org.apache.hadoop.hbase.Size);
    Code:
       0: aload_0
       1: aload_1
       2: putfield      #121                // Field memStoreSize:Lorg/apache/hadoop/hbase/Size;
       5: aload_0
       6: areturn

  public org.apache.hadoop.hbase.RegionMetricsBuilder setStoreFileIndexSize(org.apache.hadoop.hbase.Size);
    Code:
       0: aload_0
       1: aload_1
       2: putfield      #122                // Field indexSize:Lorg/apache/hadoop/hbase/Size;
       5: aload_0
       6: areturn

  public org.apache.hadoop.hbase.RegionMetricsBuilder setStoreFileRootLevelIndexSize(org.apache.hadoop.hbase.Size);
    Code:
       0: aload_0
       1: aload_1
       2: putfield      #123                // Field rootLevelIndexSize:Lorg/apache/hadoop/hbase/Size;
       5: aload_0
       6: areturn

  public org.apache.hadoop.hbase.RegionMetricsBuilder setStoreFileUncompressedDataIndexSize(org.apache.hadoop.hbase.Size);
    Code:
       0: aload_0
       1: aload_1
       2: putfield      #124                // Field uncompressedDataIndexSize:Lorg/apache/hadoop/hbase/Size;
       5: aload_0
       6: areturn

  public org.apache.hadoop.hbase.RegionMetricsBuilder setBloomFilterSize(org.apache.hadoop.hbase.Size);
    Code:
       0: aload_0
       1: aload_1
       2: putfield      #125                // Field bloomFilterSize:Lorg/apache/hadoop/hbase/Size;
       5: aload_0
       6: areturn

  public org.apache.hadoop.hbase.RegionMetricsBuilder setUncompressedStoreFileSize(org.apache.hadoop.hbase.Size);
    Code:
       0: aload_0
       1: aload_1
       2: putfield      #126                // Field uncompressedStoreFileSize:Lorg/apache/hadoop/hbase/Size;
       5: aload_0
       6: areturn

  public org.apache.hadoop.hbase.RegionMetricsBuilder setWriteRequestCount(long);
    Code:
       0: aload_0
       1: lload_1
       2: putfield      #135                // Field writeRequestCount:J
       5: aload_0
       6: areturn

  public org.apache.hadoop.hbase.RegionMetricsBuilder setReadRequestCount(long);
    Code:
       0: aload_0
       1: lload_1
       2: putfield      #136                // Field readRequestCount:J
       5: aload_0
       6: areturn

  public org.apache.hadoop.hbase.RegionMetricsBuilder setCpRequestCount(long);
    Code:
       0: aload_0
       1: lload_1
       2: putfield      #137                // Field cpRequestCount:J
       5: aload_0
       6: areturn

  public org.apache.hadoop.hbase.RegionMetricsBuilder setFilteredReadRequestCount(long);
    Code:
       0: aload_0
       1: lload_1
       2: putfield      #138                // Field filteredReadRequestCount:J
       5: aload_0
       6: areturn

  public org.apache.hadoop.hbase.RegionMetricsBuilder setCompletedSequenceId(long);
    Code:
       0: aload_0
       1: lload_1
       2: putfield      #139                // Field completedSequenceId:J
       5: aload_0
       6: areturn

  public org.apache.hadoop.hbase.RegionMetricsBuilder setStoreSequenceIds(java.util.Map<byte[], java.lang.Long>);
    Code:
       0: aload_0
       1: aload_1
       2: putfield      #128                // Field storeSequenceIds:Ljava/util/Map;
       5: aload_0
       6: areturn

  public org.apache.hadoop.hbase.RegionMetricsBuilder setDataLocality(float);
    Code:
       0: aload_0
       1: fload_1
       2: putfield      #140                // Field dataLocality:F
       5: aload_0
       6: areturn

  public org.apache.hadoop.hbase.RegionMetricsBuilder setLastMajorCompactionTimestamp(long);
    Code:
       0: aload_0
       1: lload_1
       2: putfield      #141                // Field lastMajorCompactionTimestamp:J
       5: aload_0
       6: areturn

  public org.apache.hadoop.hbase.RegionMetrics build();
    Code:
       0: new           #142                // class org/apache/hadoop/hbase/RegionMetricsBuilder$RegionMetricsImpl
       3: dup
       4: aload_0
       5: getfield      #129                // Field name:[B
       8: aload_0
       9: getfield      #130                // Field storeCount:I
      12: aload_0
      13: getfield      #131                // Field storeFileCount:I
      16: aload_0
      17: getfield      #132                // Field storeRefCount:I
      20: aload_0
      21: getfield      #133                // Field compactingCellCount:J
      24: aload_0
      25: getfield      #134                // Field compactedCellCount:J
      28: aload_0
      29: getfield      #120                // Field storeFileSize:Lorg/apache/hadoop/hbase/Size;
      32: aload_0
      33: getfield      #121                // Field memStoreSize:Lorg/apache/hadoop/hbase/Size;
      36: aload_0
      37: getfield      #122                // Field indexSize:Lorg/apache/hadoop/hbase/Size;
      40: aload_0
      41: getfield      #123                // Field rootLevelIndexSize:Lorg/apache/hadoop/hbase/Size;
      44: aload_0
      45: getfield      #124                // Field uncompressedDataIndexSize:Lorg/apache/hadoop/hbase/Size;
      48: aload_0
      49: getfield      #125                // Field bloomFilterSize:Lorg/apache/hadoop/hbase/Size;
      52: aload_0
      53: getfield      #126                // Field uncompressedStoreFileSize:Lorg/apache/hadoop/hbase/Size;
      56: aload_0
      57: getfield      #135                // Field writeRequestCount:J
      60: aload_0
      61: getfield      #136                // Field readRequestCount:J
      64: aload_0
      65: getfield      #137                // Field cpRequestCount:J
      68: aload_0
      69: getfield      #138                // Field filteredReadRequestCount:J
      72: aload_0
      73: getfield      #139                // Field completedSequenceId:J
      76: aload_0
      77: getfield      #128                // Field storeSequenceIds:Ljava/util/Map;
      80: aload_0
      81: getfield      #140                // Field dataLocality:F
      84: aload_0
      85: getfield      #141                // Field lastMajorCompactionTimestamp:J
      88: invokespecial #143                // Method org/apache/hadoop/hbase/RegionMetricsBuilder$RegionMetricsImpl."<init>":([BIIIJJLorg/apache/hadoop/hbase/Size;Lorg/apache/hadoop/hbase/Size;Lorg/apache/hadoop/hbase/Size;Lorg/apache/hadoop/hbase/Size;Lorg/apache/hadoop/hbase/Size;Lorg/apache/hadoop/hbase/Size;Lorg/apache/hadoop/hbase/Size;JJJJJLjava/util/Map;FJ)V
      91: areturn
}
