Compiled from "RegionPlan.java"
public class org.apache.hadoop.hbase.master.RegionPlan implements java.lang.Comparable<org.apache.hadoop.hbase.master.RegionPlan> {
  public org.apache.hadoop.hbase.master.RegionPlan(org.apache.hadoop.hbase.client.RegionInfo, org.apache.hadoop.hbase.ServerName, org.apache.hadoop.hbase.ServerName);
    Code:
       0: aload_0
       1: invokespecial #2                  // Method java/lang/Object."<init>":()V
       4: aload_0
       5: aload_1
       6: putfield      #3                  // Field hri:Lorg/apache/hadoop/hbase/client/RegionInfo;
       9: aload_0
      10: aload_2
      11: putfield      #4                  // Field source:Lorg/apache/hadoop/hbase/ServerName;
      14: aload_0
      15: aload_3
      16: putfield      #5                  // Field dest:Lorg/apache/hadoop/hbase/ServerName;
      19: return

  public void setDestination(org.apache.hadoop.hbase.ServerName);
    Code:
       0: aload_0
       1: aload_1
       2: putfield      #5                  // Field dest:Lorg/apache/hadoop/hbase/ServerName;
       5: return

  public org.apache.hadoop.hbase.ServerName getSource();
    Code:
       0: aload_0
       1: getfield      #4                  // Field source:Lorg/apache/hadoop/hbase/ServerName;
       4: areturn

  public org.apache.hadoop.hbase.ServerName getDestination();
    Code:
       0: aload_0
       1: getfield      #5                  // Field dest:Lorg/apache/hadoop/hbase/ServerName;
       4: areturn

  public java.lang.String getRegionName();
    Code:
       0: aload_0
       1: getfield      #3                  // Field hri:Lorg/apache/hadoop/hbase/client/RegionInfo;
       4: invokeinterface #6,  1            // InterfaceMethod org/apache/hadoop/hbase/client/RegionInfo.getEncodedName:()Ljava/lang/String;
       9: areturn

  public org.apache.hadoop.hbase.client.RegionInfo getRegionInfo();
    Code:
       0: aload_0
       1: getfield      #3                  // Field hri:Lorg/apache/hadoop/hbase/client/RegionInfo;
       4: areturn

  public int compareTo(org.apache.hadoop.hbase.master.RegionPlan);
    Code:
       0: aload_0
       1: aload_1
       2: invokestatic  #1                  // Method compareTo:(Lorg/apache/hadoop/hbase/master/RegionPlan;Lorg/apache/hadoop/hbase/master/RegionPlan;)I
       5: ireturn

  public int hashCode();
    Code:
       0: bipush        31
       2: istore_1
       3: iconst_1
       4: istore_2
       5: bipush        31
       7: iload_2
       8: imul
       9: aload_0
      10: getfield      #5                  // Field dest:Lorg/apache/hadoop/hbase/ServerName;
      13: ifnonnull     20
      16: iconst_0
      17: goto          27
      20: aload_0
      21: getfield      #5                  // Field dest:Lorg/apache/hadoop/hbase/ServerName;
      24: invokevirtual #11                 // Method org/apache/hadoop/hbase/ServerName.hashCode:()I
      27: iadd
      28: istore_2
      29: bipush        31
      31: iload_2
      32: imul
      33: aload_0
      34: getfield      #3                  // Field hri:Lorg/apache/hadoop/hbase/client/RegionInfo;
      37: ifnonnull     44
      40: iconst_0
      41: goto          51
      44: aload_0
      45: getfield      #3                  // Field hri:Lorg/apache/hadoop/hbase/client/RegionInfo;
      48: invokevirtual #12                 // Method java/lang/Object.hashCode:()I
      51: iadd
      52: istore_2
      53: bipush        31
      55: iload_2
      56: imul
      57: aload_0
      58: getfield      #4                  // Field source:Lorg/apache/hadoop/hbase/ServerName;
      61: ifnonnull     68
      64: iconst_0
      65: goto          75
      68: aload_0
      69: getfield      #4                  // Field source:Lorg/apache/hadoop/hbase/ServerName;
      72: invokevirtual #11                 // Method org/apache/hadoop/hbase/ServerName.hashCode:()I
      75: iadd
      76: istore_2
      77: iload_2
      78: ireturn

  public boolean equals(java.lang.Object);
    Code:
       0: aload_0
       1: aload_1
       2: if_acmpne     7
       5: iconst_1
       6: ireturn
       7: aload_1
       8: ifnonnull     13
      11: iconst_0
      12: ireturn
      13: aload_0
      14: invokevirtual #13                 // Method java/lang/Object.getClass:()Ljava/lang/Class;
      17: aload_1
      18: invokevirtual #13                 // Method java/lang/Object.getClass:()Ljava/lang/Class;
      21: if_acmpeq     26
      24: iconst_0
      25: ireturn
      26: aload_1
      27: checkcast     #14                 // class org/apache/hadoop/hbase/master/RegionPlan
      30: astore_2
      31: aload_0
      32: getfield      #5                  // Field dest:Lorg/apache/hadoop/hbase/ServerName;
      35: ifnonnull     47
      38: aload_2
      39: getfield      #5                  // Field dest:Lorg/apache/hadoop/hbase/ServerName;
      42: ifnull        63
      45: iconst_0
      46: ireturn
      47: aload_0
      48: getfield      #5                  // Field dest:Lorg/apache/hadoop/hbase/ServerName;
      51: aload_2
      52: getfield      #5                  // Field dest:Lorg/apache/hadoop/hbase/ServerName;
      55: invokevirtual #15                 // Method org/apache/hadoop/hbase/ServerName.equals:(Ljava/lang/Object;)Z
      58: ifne          63
      61: iconst_0
      62: ireturn
      63: aload_0
      64: getfield      #3                  // Field hri:Lorg/apache/hadoop/hbase/client/RegionInfo;
      67: ifnonnull     79
      70: aload_2
      71: getfield      #3                  // Field hri:Lorg/apache/hadoop/hbase/client/RegionInfo;
      74: ifnull        95
      77: iconst_0
      78: ireturn
      79: aload_0
      80: getfield      #3                  // Field hri:Lorg/apache/hadoop/hbase/client/RegionInfo;
      83: aload_2
      84: getfield      #3                  // Field hri:Lorg/apache/hadoop/hbase/client/RegionInfo;
      87: invokevirtual #16                 // Method java/lang/Object.equals:(Ljava/lang/Object;)Z
      90: ifne          95
      93: iconst_0
      94: ireturn
      95: aload_0
      96: getfield      #4                  // Field source:Lorg/apache/hadoop/hbase/ServerName;
      99: ifnonnull     111
     102: aload_2
     103: getfield      #4                  // Field source:Lorg/apache/hadoop/hbase/ServerName;
     106: ifnull        127
     109: iconst_0
     110: ireturn
     111: aload_0
     112: getfield      #4                  // Field source:Lorg/apache/hadoop/hbase/ServerName;
     115: aload_2
     116: getfield      #4                  // Field source:Lorg/apache/hadoop/hbase/ServerName;
     119: invokevirtual #15                 // Method org/apache/hadoop/hbase/ServerName.equals:(Ljava/lang/Object;)Z
     122: ifne          127
     125: iconst_0
     126: ireturn
     127: iconst_1
     128: ireturn

  public java.lang.String toString();
    Code:
       0: new           #17                 // class java/lang/StringBuilder
       3: dup
       4: invokespecial #18                 // Method java/lang/StringBuilder."<init>":()V
       7: ldc           #19                 // String hri=
       9: invokevirtual #20                 // Method java/lang/StringBuilder.append:(Ljava/lang/String;)Ljava/lang/StringBuilder;
      12: aload_0
      13: getfield      #3                  // Field hri:Lorg/apache/hadoop/hbase/client/RegionInfo;
      16: invokeinterface #6,  1            // InterfaceMethod org/apache/hadoop/hbase/client/RegionInfo.getEncodedName:()Ljava/lang/String;
      21: invokevirtual #20                 // Method java/lang/StringBuilder.append:(Ljava/lang/String;)Ljava/lang/StringBuilder;
      24: ldc           #21                 // String , source=
      26: invokevirtual #20                 // Method java/lang/StringBuilder.append:(Ljava/lang/String;)Ljava/lang/StringBuilder;
      29: aload_0
      30: getfield      #4                  // Field source:Lorg/apache/hadoop/hbase/ServerName;
      33: ifnonnull     41
      36: ldc           #22                 // String
      38: goto          48
      41: aload_0
      42: getfield      #4                  // Field source:Lorg/apache/hadoop/hbase/ServerName;
      45: invokevirtual #23                 // Method org/apache/hadoop/hbase/ServerName.toString:()Ljava/lang/String;
      48: invokevirtual #20                 // Method java/lang/StringBuilder.append:(Ljava/lang/String;)Ljava/lang/StringBuilder;
      51: ldc           #24                 // String , destination=
      53: invokevirtual #20                 // Method java/lang/StringBuilder.append:(Ljava/lang/String;)Ljava/lang/StringBuilder;
      56: aload_0
      57: getfield      #5                  // Field dest:Lorg/apache/hadoop/hbase/ServerName;
      60: ifnonnull     68
      63: ldc           #22                 // String
      65: goto          75
      68: aload_0
      69: getfield      #5                  // Field dest:Lorg/apache/hadoop/hbase/ServerName;
      72: invokevirtual #23                 // Method org/apache/hadoop/hbase/ServerName.toString:()Ljava/lang/String;
      75: invokevirtual #20                 // Method java/lang/StringBuilder.append:(Ljava/lang/String;)Ljava/lang/StringBuilder;
      78: invokevirtual #25                 // Method java/lang/StringBuilder.toString:()Ljava/lang/String;
      81: areturn

  public int compareTo(java.lang.Object);
    Code:
       0: aload_0
       1: aload_1
       2: checkcast     #14                 // class org/apache/hadoop/hbase/master/RegionPlan
       5: invokevirtual #26                 // Method compareTo:(Lorg/apache/hadoop/hbase/master/RegionPlan;)I
       8: ireturn

  static int access$000(org.apache.hadoop.hbase.master.RegionPlan, org.apache.hadoop.hbase.master.RegionPlan);
    Code:
       0: aload_0
       1: aload_1
       2: invokestatic  #1                  // Method compareTo:(Lorg/apache/hadoop/hbase/master/RegionPlan;Lorg/apache/hadoop/hbase/master/RegionPlan;)I
       5: ireturn
}
