Compiled from "RegionStates.java"
public class org.apache.hadoop.hbase.master.assignment.RegionStates {
  public static final org.apache.hadoop.hbase.master.assignment.RegionStates$RegionStateStampComparator REGION_STATE_STAMP_COMPARATOR;

  public org.apache.hadoop.hbase.master.assignment.RegionStates();
    Code:
       0: aload_0
       1: invokespecial #1                  // Method java/lang/Object."<init>":()V
       4: aload_0
       5: new           #2                  // class java/util/concurrent/ConcurrentSkipListMap
       8: dup
       9: getstatic     #3                  // Field org/apache/hadoop/hbase/util/Bytes.BYTES_COMPARATOR:Ljava/util/Comparator;
      12: invokespecial #4                  // Method java/util/concurrent/ConcurrentSkipListMap."<init>":(Ljava/util/Comparator;)V
      15: putfield      #5                  // Field regionsMap:Ljava/util/concurrent/ConcurrentSkipListMap;
      18: aload_0
      19: new           #2                  // class java/util/concurrent/ConcurrentSkipListMap
      22: dup
      23: getstatic     #6                  // Field org/apache/hadoop/hbase/client/RegionInfo.COMPARATOR:Ljava/util/Comparator;
      26: invokespecial #4                  // Method java/util/concurrent/ConcurrentSkipListMap."<init>":(Ljava/util/Comparator;)V
      29: putfield      #7                  // Field regionInTransition:Ljava/util/concurrent/ConcurrentSkipListMap;
      32: aload_0
      33: new           #2                  // class java/util/concurrent/ConcurrentSkipListMap
      36: dup
      37: invokespecial #8                  // Method java/util/concurrent/ConcurrentSkipListMap."<init>":()V
      40: putfield      #9                  // Field regionOffline:Ljava/util/concurrent/ConcurrentSkipListMap;
      43: aload_0
      44: new           #2                  // class java/util/concurrent/ConcurrentSkipListMap
      47: dup
      48: getstatic     #3                  // Field org/apache/hadoop/hbase/util/Bytes.BYTES_COMPARATOR:Ljava/util/Comparator;
      51: invokespecial #4                  // Method java/util/concurrent/ConcurrentSkipListMap."<init>":(Ljava/util/Comparator;)V
      54: putfield      #10                 // Field regionFailedOpen:Ljava/util/concurrent/ConcurrentSkipListMap;
      57: aload_0
      58: new           #11                 // class java/util/concurrent/ConcurrentHashMap
      61: dup
      62: invokespecial #12                 // Method java/util/concurrent/ConcurrentHashMap."<init>":()V
      65: putfield      #13                 // Field serverMap:Ljava/util/concurrent/ConcurrentHashMap;
      68: return

  public void clear();
    Code:
       0: aload_0
       1: getfield      #5                  // Field regionsMap:Ljava/util/concurrent/ConcurrentSkipListMap;
       4: invokevirtual #14                 // Method java/util/concurrent/ConcurrentSkipListMap.clear:()V
       7: aload_0
       8: getfield      #7                  // Field regionInTransition:Ljava/util/concurrent/ConcurrentSkipListMap;
      11: invokevirtual #14                 // Method java/util/concurrent/ConcurrentSkipListMap.clear:()V
      14: aload_0
      15: getfield      #9                  // Field regionOffline:Ljava/util/concurrent/ConcurrentSkipListMap;
      18: invokevirtual #14                 // Method java/util/concurrent/ConcurrentSkipListMap.clear:()V
      21: aload_0
      22: getfield      #13                 // Field serverMap:Ljava/util/concurrent/ConcurrentHashMap;
      25: invokevirtual #15                 // Method java/util/concurrent/ConcurrentHashMap.clear:()V
      28: return

  public boolean isRegionInRegionStates(org.apache.hadoop.hbase.client.RegionInfo);
    Code:
       0: aload_0
       1: getfield      #5                  // Field regionsMap:Ljava/util/concurrent/ConcurrentSkipListMap;
       4: aload_1
       5: invokeinterface #16,  1           // InterfaceMethod org/apache/hadoop/hbase/client/RegionInfo.getRegionName:()[B
      10: invokevirtual #17                 // Method java/util/concurrent/ConcurrentSkipListMap.containsKey:(Ljava/lang/Object;)Z
      13: ifne          38
      16: aload_0
      17: getfield      #7                  // Field regionInTransition:Ljava/util/concurrent/ConcurrentSkipListMap;
      20: aload_1
      21: invokevirtual #17                 // Method java/util/concurrent/ConcurrentSkipListMap.containsKey:(Ljava/lang/Object;)Z
      24: ifne          38
      27: aload_0
      28: getfield      #9                  // Field regionOffline:Ljava/util/concurrent/ConcurrentSkipListMap;
      31: aload_1
      32: invokevirtual #17                 // Method java/util/concurrent/ConcurrentSkipListMap.containsKey:(Ljava/lang/Object;)Z
      35: ifeq          42
      38: iconst_1
      39: goto          43
      42: iconst_0
      43: ireturn

  org.apache.hadoop.hbase.master.assignment.RegionStateNode createRegionStateNode(org.apache.hadoop.hbase.client.RegionInfo);
    Code:
       0: new           #18                 // class org/apache/hadoop/hbase/master/assignment/RegionStateNode
       3: dup
       4: aload_1
       5: aload_0
       6: getfield      #7                  // Field regionInTransition:Ljava/util/concurrent/ConcurrentSkipListMap;
       9: invokespecial #19                 // Method org/apache/hadoop/hbase/master/assignment/RegionStateNode."<init>":(Lorg/apache/hadoop/hbase/client/RegionInfo;Ljava/util/concurrent/ConcurrentMap;)V
      12: astore_2
      13: aload_0
      14: getfield      #5                  // Field regionsMap:Ljava/util/concurrent/ConcurrentSkipListMap;
      17: aload_1
      18: invokeinterface #16,  1           // InterfaceMethod org/apache/hadoop/hbase/client/RegionInfo.getRegionName:()[B
      23: aload_2
      24: invokevirtual #20                 // Method java/util/concurrent/ConcurrentSkipListMap.putIfAbsent:(Ljava/lang/Object;Ljava/lang/Object;)Ljava/lang/Object;
      27: checkcast     #18                 // class org/apache/hadoop/hbase/master/assignment/RegionStateNode
      30: astore_3
      31: aload_3
      32: ifnull        39
      35: aload_3
      36: goto          40
      39: aload_2
      40: areturn

  public org.apache.hadoop.hbase.master.assignment.RegionStateNode getOrCreateRegionStateNode(org.apache.hadoop.hbase.client.RegionInfo);
    Code:
       0: aload_0
       1: aload_1
       2: invokeinterface #16,  1           // InterfaceMethod org/apache/hadoop/hbase/client/RegionInfo.getRegionName:()[B
       7: invokevirtual #21                 // Method getRegionStateNodeFromName:([B)Lorg/apache/hadoop/hbase/master/assignment/RegionStateNode;
      10: astore_2
      11: aload_2
      12: ifnull        19
      15: aload_2
      16: goto          24
      19: aload_0
      20: aload_1
      21: invokevirtual #22                 // Method createRegionStateNode:(Lorg/apache/hadoop/hbase/client/RegionInfo;)Lorg/apache/hadoop/hbase/master/assignment/RegionStateNode;
      24: areturn

  org.apache.hadoop.hbase.master.assignment.RegionStateNode getRegionStateNodeFromName(byte[]);
    Code:
       0: aload_0
       1: getfield      #5                  // Field regionsMap:Ljava/util/concurrent/ConcurrentSkipListMap;
       4: aload_1
       5: invokevirtual #23                 // Method java/util/concurrent/ConcurrentSkipListMap.get:(Ljava/lang/Object;)Ljava/lang/Object;
       8: checkcast     #18                 // class org/apache/hadoop/hbase/master/assignment/RegionStateNode
      11: areturn

  public org.apache.hadoop.hbase.master.assignment.RegionStateNode getRegionStateNode(org.apache.hadoop.hbase.client.RegionInfo);
    Code:
       0: aload_0
       1: aload_1
       2: invokeinterface #16,  1           // InterfaceMethod org/apache/hadoop/hbase/client/RegionInfo.getRegionName:()[B
       7: invokevirtual #21                 // Method getRegionStateNodeFromName:([B)Lorg/apache/hadoop/hbase/master/assignment/RegionStateNode;
      10: areturn

  public void deleteRegion(org.apache.hadoop.hbase.client.RegionInfo);
    Code:
       0: aload_0
       1: getfield      #5                  // Field regionsMap:Ljava/util/concurrent/ConcurrentSkipListMap;
       4: aload_1
       5: invokeinterface #16,  1           // InterfaceMethod org/apache/hadoop/hbase/client/RegionInfo.getRegionName:()[B
      10: invokevirtual #24                 // Method java/util/concurrent/ConcurrentSkipListMap.remove:(Ljava/lang/Object;)Ljava/lang/Object;
      13: pop
      14: aload_0
      15: getfield      #7                  // Field regionInTransition:Ljava/util/concurrent/ConcurrentSkipListMap;
      18: aload_1
      19: invokevirtual #17                 // Method java/util/concurrent/ConcurrentSkipListMap.containsKey:(Ljava/lang/Object;)Z
      22: ifeq          34
      25: aload_0
      26: getfield      #7                  // Field regionInTransition:Ljava/util/concurrent/ConcurrentSkipListMap;
      29: aload_1
      30: invokevirtual #24                 // Method java/util/concurrent/ConcurrentSkipListMap.remove:(Ljava/lang/Object;)Ljava/lang/Object;
      33: pop
      34: aload_0
      35: getfield      #9                  // Field regionOffline:Ljava/util/concurrent/ConcurrentSkipListMap;
      38: aload_1
      39: invokevirtual #17                 // Method java/util/concurrent/ConcurrentSkipListMap.containsKey:(Ljava/lang/Object;)Z
      42: ifeq          92
      45: getstatic     #25                 // Field LOG:Lorg/slf4j/Logger;
      48: invokeinterface #26,  1           // InterfaceMethod org/slf4j/Logger.isTraceEnabled:()Z
      53: ifeq          83
      56: getstatic     #25                 // Field LOG:Lorg/slf4j/Logger;
      59: new           #27                 // class java/lang/StringBuilder
      62: dup
      63: invokespecial #28                 // Method java/lang/StringBuilder."<init>":()V
      66: ldc           #29                 // String Removing from regionOffline Map:
      68: invokevirtual #30                 // Method java/lang/StringBuilder.append:(Ljava/lang/String;)Ljava/lang/StringBuilder;
      71: aload_1
      72: invokevirtual #31                 // Method java/lang/StringBuilder.append:(Ljava/lang/Object;)Ljava/lang/StringBuilder;
      75: invokevirtual #32                 // Method java/lang/StringBuilder.toString:()Ljava/lang/String;
      78: invokeinterface #33,  2           // InterfaceMethod org/slf4j/Logger.trace:(Ljava/lang/String;)V
      83: aload_0
      84: getfield      #9                  // Field regionOffline:Ljava/util/concurrent/ConcurrentSkipListMap;
      87: aload_1
      88: invokevirtual #24                 // Method java/util/concurrent/ConcurrentSkipListMap.remove:(Ljava/lang/Object;)Ljava/lang/Object;
      91: pop
      92: return

  public void deleteRegions(java.util.List<org.apache.hadoop.hbase.client.RegionInfo>);
    Code:
       0: aload_1
       1: aload_0
       2: invokedynamic #34,  0             // InvokeDynamic #0:accept:(Lorg/apache/hadoop/hbase/master/assignment/RegionStates;)Ljava/util/function/Consumer;
       7: invokeinterface #35,  2           // InterfaceMethod java/util/List.forEach:(Ljava/util/function/Consumer;)V
      12: return

  java.util.ArrayList<org.apache.hadoop.hbase.master.assignment.RegionStateNode> getTableRegionStateNodes(org.apache.hadoop.hbase.TableName);
    Code:
       0: new           #36                 // class java/util/ArrayList
       3: dup
       4: invokespecial #37                 // Method java/util/ArrayList."<init>":()V
       7: astore_2
       8: aload_0
       9: getfield      #5                  // Field regionsMap:Ljava/util/concurrent/ConcurrentSkipListMap;
      12: aload_1
      13: invokevirtual #38                 // Method org/apache/hadoop/hbase/TableName.getName:()[B
      16: invokevirtual #39                 // Method java/util/concurrent/ConcurrentSkipListMap.tailMap:(Ljava/lang/Object;)Ljava/util/concurrent/ConcurrentNavigableMap;
      19: invokeinterface #40,  1           // InterfaceMethod java/util/concurrent/ConcurrentNavigableMap.values:()Ljava/util/Collection;
      24: invokeinterface #41,  1           // InterfaceMethod java/util/Collection.iterator:()Ljava/util/Iterator;
      29: astore_3
      30: aload_3
      31: invokeinterface #42,  1           // InterfaceMethod java/util/Iterator.hasNext:()Z
      36: ifeq          75
      39: aload_3
      40: invokeinterface #43,  1           // InterfaceMethod java/util/Iterator.next:()Ljava/lang/Object;
      45: checkcast     #18                 // class org/apache/hadoop/hbase/master/assignment/RegionStateNode
      48: astore        4
      50: aload         4
      52: invokevirtual #44                 // Method org/apache/hadoop/hbase/master/assignment/RegionStateNode.getTable:()Lorg/apache/hadoop/hbase/TableName;
      55: aload_1
      56: invokevirtual #45                 // Method org/apache/hadoop/hbase/TableName.equals:(Ljava/lang/Object;)Z
      59: ifne          65
      62: goto          75
      65: aload_2
      66: aload         4
      68: invokevirtual #46                 // Method java/util/ArrayList.add:(Ljava/lang/Object;)Z
      71: pop
      72: goto          30
      75: aload_2
      76: areturn

  java.util.ArrayList<org.apache.hadoop.hbase.master.RegionState> getTableRegionStates(org.apache.hadoop.hbase.TableName);
    Code:
       0: new           #36                 // class java/util/ArrayList
       3: dup
       4: invokespecial #37                 // Method java/util/ArrayList."<init>":()V
       7: astore_2
       8: aload_0
       9: getfield      #5                  // Field regionsMap:Ljava/util/concurrent/ConcurrentSkipListMap;
      12: aload_1
      13: invokevirtual #38                 // Method org/apache/hadoop/hbase/TableName.getName:()[B
      16: invokevirtual #39                 // Method java/util/concurrent/ConcurrentSkipListMap.tailMap:(Ljava/lang/Object;)Ljava/util/concurrent/ConcurrentNavigableMap;
      19: invokeinterface #40,  1           // InterfaceMethod java/util/concurrent/ConcurrentNavigableMap.values:()Ljava/util/Collection;
      24: invokeinterface #41,  1           // InterfaceMethod java/util/Collection.iterator:()Ljava/util/Iterator;
      29: astore_3
      30: aload_3
      31: invokeinterface #42,  1           // InterfaceMethod java/util/Iterator.hasNext:()Z
      36: ifeq          78
      39: aload_3
      40: invokeinterface #43,  1           // InterfaceMethod java/util/Iterator.next:()Ljava/lang/Object;
      45: checkcast     #18                 // class org/apache/hadoop/hbase/master/assignment/RegionStateNode
      48: astore        4
      50: aload         4
      52: invokevirtual #44                 // Method org/apache/hadoop/hbase/master/assignment/RegionStateNode.getTable:()Lorg/apache/hadoop/hbase/TableName;
      55: aload_1
      56: invokevirtual #45                 // Method org/apache/hadoop/hbase/TableName.equals:(Ljava/lang/Object;)Z
      59: ifne          65
      62: goto          78
      65: aload_2
      66: aload         4
      68: invokevirtual #47                 // Method org/apache/hadoop/hbase/master/assignment/RegionStateNode.toRegionState:()Lorg/apache/hadoop/hbase/master/RegionState;
      71: invokevirtual #46                 // Method java/util/ArrayList.add:(Ljava/lang/Object;)Z
      74: pop
      75: goto          30
      78: aload_2
      79: areturn

  java.util.ArrayList<org.apache.hadoop.hbase.client.RegionInfo> getTableRegionsInfo(org.apache.hadoop.hbase.TableName);
    Code:
       0: new           #36                 // class java/util/ArrayList
       3: dup
       4: invokespecial #37                 // Method java/util/ArrayList."<init>":()V
       7: astore_2
       8: aload_0
       9: getfield      #5                  // Field regionsMap:Ljava/util/concurrent/ConcurrentSkipListMap;
      12: aload_1
      13: invokevirtual #38                 // Method org/apache/hadoop/hbase/TableName.getName:()[B
      16: invokevirtual #39                 // Method java/util/concurrent/ConcurrentSkipListMap.tailMap:(Ljava/lang/Object;)Ljava/util/concurrent/ConcurrentNavigableMap;
      19: invokeinterface #40,  1           // InterfaceMethod java/util/concurrent/ConcurrentNavigableMap.values:()Ljava/util/Collection;
      24: invokeinterface #41,  1           // InterfaceMethod java/util/Collection.iterator:()Ljava/util/Iterator;
      29: astore_3
      30: aload_3
      31: invokeinterface #42,  1           // InterfaceMethod java/util/Iterator.hasNext:()Z
      36: ifeq          78
      39: aload_3
      40: invokeinterface #43,  1           // InterfaceMethod java/util/Iterator.next:()Ljava/lang/Object;
      45: checkcast     #18                 // class org/apache/hadoop/hbase/master/assignment/RegionStateNode
      48: astore        4
      50: aload         4
      52: invokevirtual #44                 // Method org/apache/hadoop/hbase/master/assignment/RegionStateNode.getTable:()Lorg/apache/hadoop/hbase/TableName;
      55: aload_1
      56: invokevirtual #45                 // Method org/apache/hadoop/hbase/TableName.equals:(Ljava/lang/Object;)Z
      59: ifne          65
      62: goto          78
      65: aload_2
      66: aload         4
      68: invokevirtual #48                 // Method org/apache/hadoop/hbase/master/assignment/RegionStateNode.getRegionInfo:()Lorg/apache/hadoop/hbase/client/RegionInfo;
      71: invokevirtual #46                 // Method java/util/ArrayList.add:(Ljava/lang/Object;)Z
      74: pop
      75: goto          30
      78: aload_2
      79: areturn

  java.util.Collection<org.apache.hadoop.hbase.master.assignment.RegionStateNode> getRegionStateNodes();
    Code:
       0: aload_0
       1: getfield      #5                  // Field regionsMap:Ljava/util/concurrent/ConcurrentSkipListMap;
       4: invokevirtual #49                 // Method java/util/concurrent/ConcurrentSkipListMap.values:()Ljava/util/Collection;
       7: areturn

  public java.util.ArrayList<org.apache.hadoop.hbase.master.RegionState> getRegionStates();
    Code:
       0: new           #36                 // class java/util/ArrayList
       3: dup
       4: aload_0
       5: getfield      #5                  // Field regionsMap:Ljava/util/concurrent/ConcurrentSkipListMap;
       8: invokevirtual #50                 // Method java/util/concurrent/ConcurrentSkipListMap.size:()I
      11: invokespecial #51                 // Method java/util/ArrayList."<init>":(I)V
      14: astore_1
      15: aload_0
      16: getfield      #5                  // Field regionsMap:Ljava/util/concurrent/ConcurrentSkipListMap;
      19: invokevirtual #49                 // Method java/util/concurrent/ConcurrentSkipListMap.values:()Ljava/util/Collection;
      22: invokeinterface #41,  1           // InterfaceMethod java/util/Collection.iterator:()Ljava/util/Iterator;
      27: astore_2
      28: aload_2
      29: invokeinterface #42,  1           // InterfaceMethod java/util/Iterator.hasNext:()Z
      34: ifeq          59
      37: aload_2
      38: invokeinterface #43,  1           // InterfaceMethod java/util/Iterator.next:()Ljava/lang/Object;
      43: checkcast     #18                 // class org/apache/hadoop/hbase/master/assignment/RegionStateNode
      46: astore_3
      47: aload_1
      48: aload_3
      49: invokevirtual #47                 // Method org/apache/hadoop/hbase/master/assignment/RegionStateNode.toRegionState:()Lorg/apache/hadoop/hbase/master/RegionState;
      52: invokevirtual #46                 // Method java/util/ArrayList.add:(Ljava/lang/Object;)Z
      55: pop
      56: goto          28
      59: aload_1
      60: areturn

  public org.apache.hadoop.hbase.master.RegionState getRegionState(org.apache.hadoop.hbase.client.RegionInfo);
    Code:
       0: aload_0
       1: aload_1
       2: invokevirtual #52                 // Method getRegionStateNode:(Lorg/apache/hadoop/hbase/client/RegionInfo;)Lorg/apache/hadoop/hbase/master/assignment/RegionStateNode;
       5: astore_2
       6: aload_2
       7: ifnonnull     14
      10: aconst_null
      11: goto          18
      14: aload_2
      15: invokevirtual #47                 // Method org/apache/hadoop/hbase/master/assignment/RegionStateNode.toRegionState:()Lorg/apache/hadoop/hbase/master/RegionState;
      18: areturn

  public org.apache.hadoop.hbase.master.RegionState getRegionState(java.lang.String);
    Code:
       0: aload_0
       1: getfield      #5                  // Field regionsMap:Ljava/util/concurrent/ConcurrentSkipListMap;
       4: invokevirtual #49                 // Method java/util/concurrent/ConcurrentSkipListMap.values:()Ljava/util/Collection;
       7: invokeinterface #41,  1           // InterfaceMethod java/util/Collection.iterator:()Ljava/util/Iterator;
      12: astore_2
      13: aload_2
      14: invokeinterface #42,  1           // InterfaceMethod java/util/Iterator.hasNext:()Z
      19: ifeq          56
      22: aload_2
      23: invokeinterface #43,  1           // InterfaceMethod java/util/Iterator.next:()Ljava/lang/Object;
      28: checkcast     #18                 // class org/apache/hadoop/hbase/master/assignment/RegionStateNode
      31: astore_3
      32: aload_3
      33: invokevirtual #48                 // Method org/apache/hadoop/hbase/master/assignment/RegionStateNode.getRegionInfo:()Lorg/apache/hadoop/hbase/client/RegionInfo;
      36: invokeinterface #53,  1           // InterfaceMethod org/apache/hadoop/hbase/client/RegionInfo.getEncodedName:()Ljava/lang/String;
      41: aload_1
      42: invokevirtual #54                 // Method java/lang/String.equals:(Ljava/lang/Object;)Z
      45: ifeq          53
      48: aload_3
      49: invokevirtual #47                 // Method org/apache/hadoop/hbase/master/assignment/RegionStateNode.toRegionState:()Lorg/apache/hadoop/hbase/master/RegionState;
      52: areturn
      53: goto          13
      56: aconst_null
      57: areturn

  public boolean hasTableRegionStates(org.apache.hadoop.hbase.TableName);
    Code:
       0: aload_0
       1: aload_1
       2: invokevirtual #55                 // Method getTableRegionStates:(Lorg/apache/hadoop/hbase/TableName;)Ljava/util/ArrayList;
       5: invokevirtual #56                 // Method java/util/ArrayList.isEmpty:()Z
       8: ifne          15
      11: iconst_1
      12: goto          16
      15: iconst_0
      16: ireturn

  public java.util.List<org.apache.hadoop.hbase.client.RegionInfo> getRegionsOfTable(org.apache.hadoop.hbase.TableName);
    Code:
       0: aload_0
       1: aload_1
       2: iconst_0
       3: invokevirtual #57                 // Method getRegionsOfTable:(Lorg/apache/hadoop/hbase/TableName;Z)Ljava/util/List;
       6: areturn

  public java.util.List<org.apache.hadoop.hbase.HRegionLocation> getRegionsOfTableForReopen(org.apache.hadoop.hbase.TableName);
    Code:
       0: aload_0
       1: aload_1
       2: invokevirtual #71                 // Method getTableRegionStateNodes:(Lorg/apache/hadoop/hbase/TableName;)Ljava/util/ArrayList;
       5: invokevirtual #72                 // Method java/util/ArrayList.stream:()Ljava/util/stream/Stream;
       8: aload_0
       9: invokedynamic #73,  0             // InvokeDynamic #1:apply:(Lorg/apache/hadoop/hbase/master/assignment/RegionStates;)Ljava/util/function/Function;
      14: invokeinterface #74,  2           // InterfaceMethod java/util/stream/Stream.map:(Ljava/util/function/Function;)Ljava/util/stream/Stream;
      19: invokedynamic #75,  0             // InvokeDynamic #2:test:()Ljava/util/function/Predicate;
      24: invokeinterface #76,  2           // InterfaceMethod java/util/stream/Stream.filter:(Ljava/util/function/Predicate;)Ljava/util/stream/Stream;
      29: invokestatic  #77                 // Method java/util/stream/Collectors.toList:()Ljava/util/stream/Collector;
      32: invokeinterface #78,  2           // InterfaceMethod java/util/stream/Stream.collect:(Ljava/util/stream/Collector;)Ljava/lang/Object;
      37: checkcast     #79                 // class java/util/List
      40: areturn

  public org.apache.hadoop.hbase.HRegionLocation checkReopened(org.apache.hadoop.hbase.HRegionLocation);
    Code:
       0: aload_0
       1: aload_1
       2: invokevirtual #80                 // Method org/apache/hadoop/hbase/HRegionLocation.getRegion:()Lorg/apache/hadoop/hbase/client/RegionInfo;
       5: invokevirtual #52                 // Method getRegionStateNode:(Lorg/apache/hadoop/hbase/client/RegionInfo;)Lorg/apache/hadoop/hbase/master/assignment/RegionStateNode;
       8: astore_2
       9: aload_2
      10: ifnonnull     15
      13: aconst_null
      14: areturn
      15: aload_2
      16: invokevirtual #58                 // Method org/apache/hadoop/hbase/master/assignment/RegionStateNode.lock:()V
      19: aload_1
      20: invokevirtual #81                 // Method org/apache/hadoop/hbase/HRegionLocation.getSeqNum:()J
      23: lconst_0
      24: lcmp
      25: iflt          99
      28: aload_2
      29: iconst_1
      30: anewarray     #61                 // class org/apache/hadoop/hbase/master/RegionState$State
      33: dup
      34: iconst_0
      35: getstatic     #62                 // Field org/apache/hadoop/hbase/master/RegionState$State.OPEN:Lorg/apache/hadoop/hbase/master/RegionState$State;
      38: aastore
      39: invokevirtual #63                 // Method org/apache/hadoop/hbase/master/assignment/RegionStateNode.isInState:([Lorg/apache/hadoop/hbase/master/RegionState$State;)Z
      42: ifeq          91
      45: aload_2
      46: invokevirtual #66                 // Method org/apache/hadoop/hbase/master/assignment/RegionStateNode.getOpenSeqNum:()J
      49: aload_1
      50: invokevirtual #81                 // Method org/apache/hadoop/hbase/HRegionLocation.getSeqNum:()J
      53: lcmp
      54: ifle          65
      57: aconst_null
      58: astore_3
      59: aload_2
      60: invokevirtual #60                 // Method org/apache/hadoop/hbase/master/assignment/RegionStateNode.unlock:()V
      63: aload_3
      64: areturn
      65: new           #64                 // class org/apache/hadoop/hbase/HRegionLocation
      68: dup
      69: aload_2
      70: invokevirtual #48                 // Method org/apache/hadoop/hbase/master/assignment/RegionStateNode.getRegionInfo:()Lorg/apache/hadoop/hbase/client/RegionInfo;
      73: aload_2
      74: invokevirtual #65                 // Method org/apache/hadoop/hbase/master/assignment/RegionStateNode.getRegionLocation:()Lorg/apache/hadoop/hbase/ServerName;
      77: aload_2
      78: invokevirtual #66                 // Method org/apache/hadoop/hbase/master/assignment/RegionStateNode.getOpenSeqNum:()J
      81: invokespecial #67                 // Method org/apache/hadoop/hbase/HRegionLocation."<init>":(Lorg/apache/hadoop/hbase/client/RegionInfo;Lorg/apache/hadoop/hbase/ServerName;J)V
      84: astore_3
      85: aload_2
      86: invokevirtual #60                 // Method org/apache/hadoop/hbase/master/assignment/RegionStateNode.unlock:()V
      89: aload_3
      90: areturn
      91: aconst_null
      92: astore_3
      93: aload_2
      94: invokevirtual #60                 // Method org/apache/hadoop/hbase/master/assignment/RegionStateNode.unlock:()V
      97: aload_3
      98: areturn
      99: aload_2
     100: iconst_2
     101: anewarray     #61                 // class org/apache/hadoop/hbase/master/RegionState$State
     104: dup
     105: iconst_0
     106: getstatic     #62                 // Field org/apache/hadoop/hbase/master/RegionState$State.OPEN:Lorg/apache/hadoop/hbase/master/RegionState$State;
     109: aastore
     110: dup
     111: iconst_1
     112: getstatic     #68                 // Field org/apache/hadoop/hbase/master/RegionState$State.OPENING:Lorg/apache/hadoop/hbase/master/RegionState$State;
     115: aastore
     116: invokevirtual #63                 // Method org/apache/hadoop/hbase/master/assignment/RegionStateNode.isInState:([Lorg/apache/hadoop/hbase/master/RegionState$State;)Z
     119: ifne          130
     122: aconst_null
     123: astore_3
     124: aload_2
     125: invokevirtual #60                 // Method org/apache/hadoop/hbase/master/assignment/RegionStateNode.unlock:()V
     128: aload_3
     129: areturn
     130: aload_2
     131: invokevirtual #65                 // Method org/apache/hadoop/hbase/master/assignment/RegionStateNode.getRegionLocation:()Lorg/apache/hadoop/hbase/ServerName;
     134: aload_1
     135: invokevirtual #82                 // Method org/apache/hadoop/hbase/HRegionLocation.getServerName:()Lorg/apache/hadoop/hbase/ServerName;
     138: invokevirtual #83                 // Method org/apache/hadoop/hbase/ServerName.equals:(Ljava/lang/Object;)Z
     141: ifne          152
     144: aconst_null
     145: astore_3
     146: aload_2
     147: invokevirtual #60                 // Method org/apache/hadoop/hbase/master/assignment/RegionStateNode.unlock:()V
     150: aload_3
     151: areturn
     152: aload_2
     153: iconst_1
     154: anewarray     #61                 // class org/apache/hadoop/hbase/master/RegionState$State
     157: dup
     158: iconst_0
     159: getstatic     #62                 // Field org/apache/hadoop/hbase/master/RegionState$State.OPEN:Lorg/apache/hadoop/hbase/master/RegionState$State;
     162: aastore
     163: invokevirtual #63                 // Method org/apache/hadoop/hbase/master/assignment/RegionStateNode.isInState:([Lorg/apache/hadoop/hbase/master/RegionState$State;)Z
     166: ifeq          176
     169: aload_2
     170: invokevirtual #66                 // Method org/apache/hadoop/hbase/master/assignment/RegionStateNode.getOpenSeqNum:()J
     173: goto          179
     176: ldc2_w        #69                 // long -1l
     179: lstore_3
     180: new           #64                 // class org/apache/hadoop/hbase/HRegionLocation
     183: dup
     184: aload_2
     185: invokevirtual #48                 // Method org/apache/hadoop/hbase/master/assignment/RegionStateNode.getRegionInfo:()Lorg/apache/hadoop/hbase/client/RegionInfo;
     188: aload_2
     189: invokevirtual #65                 // Method org/apache/hadoop/hbase/master/assignment/RegionStateNode.getRegionLocation:()Lorg/apache/hadoop/hbase/ServerName;
     192: lload_3
     193: invokespecial #67                 // Method org/apache/hadoop/hbase/HRegionLocation."<init>":(Lorg/apache/hadoop/hbase/client/RegionInfo;Lorg/apache/hadoop/hbase/ServerName;J)V
     196: astore        5
     198: aload_2
     199: invokevirtual #60                 // Method org/apache/hadoop/hbase/master/assignment/RegionStateNode.unlock:()V
     202: aload         5
     204: areturn
     205: astore        6
     207: aload_2
     208: invokevirtual #60                 // Method org/apache/hadoop/hbase/master/assignment/RegionStateNode.unlock:()V
     211: aload         6
     213: athrow
    Exception table:
       from    to  target type
          19    59   205   any
          65    85   205   any
          91    93   205   any
          99   124   205   any
         130   146   205   any
         152   198   205   any
         205   207   205   any

  public java.util.List<org.apache.hadoop.hbase.client.RegionInfo> getRegionsOfTable(org.apache.hadoop.hbase.TableName, boolean);
    Code:
       0: aload_0
       1: aload_1
       2: aload_0
       3: iload_2
       4: invokedynamic #84,  0             // InvokeDynamic #3:test:(Lorg/apache/hadoop/hbase/master/assignment/RegionStates;Z)Ljava/util/function/Predicate;
       9: invokespecial #85                 // Method getRegionsOfTable:(Lorg/apache/hadoop/hbase/TableName;Ljava/util/function/Predicate;)Ljava/util/List;
      12: areturn

  boolean include(org.apache.hadoop.hbase.master.assignment.RegionStateNode, boolean);
    Code:
       0: getstatic     #25                 // Field LOG:Lorg/slf4j/Logger;
       3: invokeinterface #26,  1           // InterfaceMethod org/slf4j/Logger.isTraceEnabled:()Z
       8: ifeq          50
      11: getstatic     #25                 // Field LOG:Lorg/slf4j/Logger;
      14: new           #27                 // class java/lang/StringBuilder
      17: dup
      18: invokespecial #28                 // Method java/lang/StringBuilder."<init>":()V
      21: ldc           #87                 // String WORKING ON
      23: invokevirtual #30                 // Method java/lang/StringBuilder.append:(Ljava/lang/String;)Ljava/lang/StringBuilder;
      26: aload_1
      27: invokevirtual #31                 // Method java/lang/StringBuilder.append:(Ljava/lang/Object;)Ljava/lang/StringBuilder;
      30: ldc           #88                 // String
      32: invokevirtual #30                 // Method java/lang/StringBuilder.append:(Ljava/lang/String;)Ljava/lang/StringBuilder;
      35: aload_1
      36: invokevirtual #48                 // Method org/apache/hadoop/hbase/master/assignment/RegionStateNode.getRegionInfo:()Lorg/apache/hadoop/hbase/client/RegionInfo;
      39: invokevirtual #31                 // Method java/lang/StringBuilder.append:(Ljava/lang/Object;)Ljava/lang/StringBuilder;
      42: invokevirtual #32                 // Method java/lang/StringBuilder.toString:()Ljava/lang/String;
      45: invokeinterface #33,  2           // InterfaceMethod org/slf4j/Logger.trace:(Ljava/lang/String;)V
      50: aload_1
      51: iconst_1
      52: anewarray     #61                 // class org/apache/hadoop/hbase/master/RegionState$State
      55: dup
      56: iconst_0
      57: getstatic     #89                 // Field org/apache/hadoop/hbase/master/RegionState$State.SPLIT:Lorg/apache/hadoop/hbase/master/RegionState$State;
      60: aastore
      61: invokevirtual #63                 // Method org/apache/hadoop/hbase/master/assignment/RegionStateNode.isInState:([Lorg/apache/hadoop/hbase/master/RegionState$State;)Z
      64: ifeq          69
      67: iconst_0
      68: ireturn
      69: aload_1
      70: iconst_1
      71: anewarray     #61                 // class org/apache/hadoop/hbase/master/RegionState$State
      74: dup
      75: iconst_0
      76: getstatic     #90                 // Field org/apache/hadoop/hbase/master/RegionState$State.OFFLINE:Lorg/apache/hadoop/hbase/master/RegionState$State;
      79: aastore
      80: invokevirtual #63                 // Method org/apache/hadoop/hbase/master/assignment/RegionStateNode.isInState:([Lorg/apache/hadoop/hbase/master/RegionState$State;)Z
      83: ifeq          92
      86: iload_2
      87: ifne          92
      90: iconst_0
      91: ireturn
      92: aload_1
      93: invokevirtual #48                 // Method org/apache/hadoop/hbase/master/assignment/RegionStateNode.getRegionInfo:()Lorg/apache/hadoop/hbase/client/RegionInfo;
      96: astore_3
      97: aload_3
      98: invokeinterface #91,  1           // InterfaceMethod org/apache/hadoop/hbase/client/RegionInfo.isOffline:()Z
     103: ifne          115
     106: aload_3
     107: invokeinterface #92,  1           // InterfaceMethod org/apache/hadoop/hbase/client/RegionInfo.isSplit:()Z
     112: ifeq          137
     115: aload_3
     116: invokeinterface #91,  1           // InterfaceMethod org/apache/hadoop/hbase/client/RegionInfo.isOffline:()Z
     121: ifne          133
     124: aload_3
     125: invokeinterface #92,  1           // InterfaceMethod org/apache/hadoop/hbase/client/RegionInfo.isSplit:()Z
     130: ifeq          141
     133: iload_2
     134: ifeq          141
     137: iconst_1
     138: goto          142
     141: iconst_0
     142: ireturn

  public void metaLogSplitting(org.apache.hadoop.hbase.ServerName);
    Code:
       0: aload_0
       1: aload_1
       2: getstatic     #95                 // Field org/apache/hadoop/hbase/master/assignment/ServerState.SPLITTING_META:Lorg/apache/hadoop/hbase/master/assignment/ServerState;
       5: invokespecial #96                 // Method setServerState:(Lorg/apache/hadoop/hbase/ServerName;Lorg/apache/hadoop/hbase/master/assignment/ServerState;)V
       8: return

  public void metaLogSplit(org.apache.hadoop.hbase.ServerName);
    Code:
       0: aload_0
       1: aload_1
       2: getstatic     #97                 // Field org/apache/hadoop/hbase/master/assignment/ServerState.SPLITTING_META_DONE:Lorg/apache/hadoop/hbase/master/assignment/ServerState;
       5: invokespecial #96                 // Method setServerState:(Lorg/apache/hadoop/hbase/ServerName;Lorg/apache/hadoop/hbase/master/assignment/ServerState;)V
       8: return

  public void logSplitting(org.apache.hadoop.hbase.ServerName);
    Code:
       0: aload_0
       1: aload_1
       2: getstatic     #98                 // Field org/apache/hadoop/hbase/master/assignment/ServerState.SPLITTING:Lorg/apache/hadoop/hbase/master/assignment/ServerState;
       5: invokespecial #96                 // Method setServerState:(Lorg/apache/hadoop/hbase/ServerName;Lorg/apache/hadoop/hbase/master/assignment/ServerState;)V
       8: return

  public void logSplit(org.apache.hadoop.hbase.ServerName);
    Code:
       0: aload_0
       1: aload_1
       2: getstatic     #99                 // Field org/apache/hadoop/hbase/master/assignment/ServerState.OFFLINE:Lorg/apache/hadoop/hbase/master/assignment/ServerState;
       5: invokespecial #96                 // Method setServerState:(Lorg/apache/hadoop/hbase/ServerName;Lorg/apache/hadoop/hbase/master/assignment/ServerState;)V
       8: return

  public void updateRegionState(org.apache.hadoop.hbase.client.RegionInfo, org.apache.hadoop.hbase.master.RegionState$State);
    Code:
       0: aload_0
       1: aload_1
       2: invokevirtual #100                // Method getOrCreateRegionStateNode:(Lorg/apache/hadoop/hbase/client/RegionInfo;)Lorg/apache/hadoop/hbase/master/assignment/RegionStateNode;
       5: astore_3
       6: aload_3
       7: invokevirtual #58                 // Method org/apache/hadoop/hbase/master/assignment/RegionStateNode.lock:()V
      10: aload_3
      11: aload_2
      12: iconst_0
      13: anewarray     #61                 // class org/apache/hadoop/hbase/master/RegionState$State
      16: invokevirtual #101                // Method org/apache/hadoop/hbase/master/assignment/RegionStateNode.setState:(Lorg/apache/hadoop/hbase/master/RegionState$State;[Lorg/apache/hadoop/hbase/master/RegionState$State;)Z
      19: pop
      20: aload_3
      21: invokevirtual #60                 // Method org/apache/hadoop/hbase/master/assignment/RegionStateNode.unlock:()V
      24: goto          36
      27: astore        4
      29: aload_3
      30: invokevirtual #60                 // Method org/apache/hadoop/hbase/master/assignment/RegionStateNode.unlock:()V
      33: aload         4
      35: athrow
      36: return
    Exception table:
       from    to  target type
          10    20    27   any
          27    29    27   any

  public java.util.List<org.apache.hadoop.hbase.client.RegionInfo> getAssignedRegions();
    Code:
       0: new           #36                 // class java/util/ArrayList
       3: dup
       4: invokespecial #37                 // Method java/util/ArrayList."<init>":()V
       7: astore_1
       8: aload_0
       9: getfield      #5                  // Field regionsMap:Ljava/util/concurrent/ConcurrentSkipListMap;
      12: invokevirtual #49                 // Method java/util/concurrent/ConcurrentSkipListMap.values:()Ljava/util/Collection;
      15: invokeinterface #41,  1           // InterfaceMethod java/util/Collection.iterator:()Ljava/util/Iterator;
      20: astore_2
      21: aload_2
      22: invokeinterface #42,  1           // InterfaceMethod java/util/Iterator.hasNext:()Z
      27: ifeq          61
      30: aload_2
      31: invokeinterface #43,  1           // InterfaceMethod java/util/Iterator.next:()Ljava/lang/Object;
      36: checkcast     #18                 // class org/apache/hadoop/hbase/master/assignment/RegionStateNode
      39: astore_3
      40: aload_3
      41: invokevirtual #102                // Method org/apache/hadoop/hbase/master/assignment/RegionStateNode.isInTransition:()Z
      44: ifne          58
      47: aload_1
      48: aload_3
      49: invokevirtual #48                 // Method org/apache/hadoop/hbase/master/assignment/RegionStateNode.getRegionInfo:()Lorg/apache/hadoop/hbase/client/RegionInfo;
      52: invokeinterface #103,  2          // InterfaceMethod java/util/List.add:(Ljava/lang/Object;)Z
      57: pop
      58: goto          21
      61: aload_1
      62: areturn

  public boolean isRegionInState(org.apache.hadoop.hbase.client.RegionInfo, org.apache.hadoop.hbase.master.RegionState$State...);
    Code:
       0: aload_0
       1: aload_1
       2: invokevirtual #52                 // Method getRegionStateNode:(Lorg/apache/hadoop/hbase/client/RegionInfo;)Lorg/apache/hadoop/hbase/master/assignment/RegionStateNode;
       5: astore_3
       6: aload_3
       7: ifnull        37
      10: aload_3
      11: invokevirtual #58                 // Method org/apache/hadoop/hbase/master/assignment/RegionStateNode.lock:()V
      14: aload_3
      15: aload_2
      16: invokevirtual #63                 // Method org/apache/hadoop/hbase/master/assignment/RegionStateNode.isInState:([Lorg/apache/hadoop/hbase/master/RegionState$State;)Z
      19: istore        4
      21: aload_3
      22: invokevirtual #60                 // Method org/apache/hadoop/hbase/master/assignment/RegionStateNode.unlock:()V
      25: iload         4
      27: ireturn
      28: astore        5
      30: aload_3
      31: invokevirtual #60                 // Method org/apache/hadoop/hbase/master/assignment/RegionStateNode.unlock:()V
      34: aload         5
      36: athrow
      37: iconst_0
      38: ireturn
    Exception table:
       from    to  target type
          14    21    28   any
          28    30    28   any

  public boolean isRegionOnline(org.apache.hadoop.hbase.client.RegionInfo);
    Code:
       0: aload_0
       1: aload_1
       2: iconst_1
       3: anewarray     #61                 // class org/apache/hadoop/hbase/master/RegionState$State
       6: dup
       7: iconst_0
       8: getstatic     #62                 // Field org/apache/hadoop/hbase/master/RegionState$State.OPEN:Lorg/apache/hadoop/hbase/master/RegionState$State;
      11: aastore
      12: invokevirtual #104                // Method isRegionInState:(Lorg/apache/hadoop/hbase/client/RegionInfo;[Lorg/apache/hadoop/hbase/master/RegionState$State;)Z
      15: ireturn

  public boolean isRegionOffline(org.apache.hadoop.hbase.client.RegionInfo);
    Code:
       0: aload_0
       1: aload_1
       2: iconst_2
       3: anewarray     #61                 // class org/apache/hadoop/hbase/master/RegionState$State
       6: dup
       7: iconst_0
       8: getstatic     #90                 // Field org/apache/hadoop/hbase/master/RegionState$State.OFFLINE:Lorg/apache/hadoop/hbase/master/RegionState$State;
      11: aastore
      12: dup
      13: iconst_1
      14: getstatic     #105                // Field org/apache/hadoop/hbase/master/RegionState$State.CLOSED:Lorg/apache/hadoop/hbase/master/RegionState$State;
      17: aastore
      18: invokevirtual #104                // Method isRegionInState:(Lorg/apache/hadoop/hbase/client/RegionInfo;[Lorg/apache/hadoop/hbase/master/RegionState$State;)Z
      21: ireturn

  public java.util.Map<org.apache.hadoop.hbase.ServerName, java.util.List<org.apache.hadoop.hbase.client.RegionInfo>> getSnapShotOfAssignment(java.util.Collection<org.apache.hadoop.hbase.client.RegionInfo>);
    Code:
       0: new           #106                // class java/util/HashMap
       3: dup
       4: invokespecial #107                // Method java/util/HashMap."<init>":()V
       7: astore_2
       8: aload_1
       9: ifnull        68
      12: aload_1
      13: invokeinterface #41,  1           // InterfaceMethod java/util/Collection.iterator:()Ljava/util/Iterator;
      18: astore_3
      19: aload_3
      20: invokeinterface #42,  1           // InterfaceMethod java/util/Iterator.hasNext:()Z
      25: ifeq          65
      28: aload_3
      29: invokeinterface #43,  1           // InterfaceMethod java/util/Iterator.next:()Ljava/lang/Object;
      34: checkcast     #108                // class org/apache/hadoop/hbase/client/RegionInfo
      37: astore        4
      39: aload_0
      40: aload         4
      42: invokevirtual #52                 // Method getRegionStateNode:(Lorg/apache/hadoop/hbase/client/RegionInfo;)Lorg/apache/hadoop/hbase/master/assignment/RegionStateNode;
      45: astore        5
      47: aload         5
      49: ifnonnull     55
      52: goto          19
      55: aload_0
      56: aload         5
      58: aload_2
      59: invokespecial #109                // Method createSnapshot:(Lorg/apache/hadoop/hbase/master/assignment/RegionStateNode;Ljava/util/Map;)V
      62: goto          19
      65: goto          119
      68: aload_0
      69: getfield      #5                  // Field regionsMap:Ljava/util/concurrent/ConcurrentSkipListMap;
      72: invokevirtual #49                 // Method java/util/concurrent/ConcurrentSkipListMap.values:()Ljava/util/Collection;
      75: invokeinterface #41,  1           // InterfaceMethod java/util/Collection.iterator:()Ljava/util/Iterator;
      80: astore_3
      81: aload_3
      82: invokeinterface #42,  1           // InterfaceMethod java/util/Iterator.hasNext:()Z
      87: ifeq          119
      90: aload_3
      91: invokeinterface #43,  1           // InterfaceMethod java/util/Iterator.next:()Ljava/lang/Object;
      96: checkcast     #18                 // class org/apache/hadoop/hbase/master/assignment/RegionStateNode
      99: astore        4
     101: aload         4
     103: ifnonnull     109
     106: goto          81
     109: aload_0
     110: aload         4
     112: aload_2
     113: invokespecial #109                // Method createSnapshot:(Lorg/apache/hadoop/hbase/master/assignment/RegionStateNode;Ljava/util/Map;)V
     116: goto          81
     119: aload_2
     120: areturn

  public java.util.Map<org.apache.hadoop.hbase.client.RegionInfo, org.apache.hadoop.hbase.ServerName> getRegionAssignments();
    Code:
       0: new           #106                // class java/util/HashMap
       3: dup
       4: invokespecial #107                // Method java/util/HashMap."<init>":()V
       7: astore_1
       8: aload_0
       9: getfield      #5                  // Field regionsMap:Ljava/util/concurrent/ConcurrentSkipListMap;
      12: invokevirtual #49                 // Method java/util/concurrent/ConcurrentSkipListMap.values:()Ljava/util/Collection;
      15: invokeinterface #41,  1           // InterfaceMethod java/util/Collection.iterator:()Ljava/util/Iterator;
      20: astore_2
      21: aload_2
      22: invokeinterface #42,  1           // InterfaceMethod java/util/Iterator.hasNext:()Z
      27: ifeq          56
      30: aload_2
      31: invokeinterface #43,  1           // InterfaceMethod java/util/Iterator.next:()Ljava/lang/Object;
      36: checkcast     #18                 // class org/apache/hadoop/hbase/master/assignment/RegionStateNode
      39: astore_3
      40: aload_1
      41: aload_3
      42: invokevirtual #48                 // Method org/apache/hadoop/hbase/master/assignment/RegionStateNode.getRegionInfo:()Lorg/apache/hadoop/hbase/client/RegionInfo;
      45: aload_3
      46: invokevirtual #65                 // Method org/apache/hadoop/hbase/master/assignment/RegionStateNode.getRegionLocation:()Lorg/apache/hadoop/hbase/ServerName;
      49: invokevirtual #112                // Method java/util/HashMap.put:(Ljava/lang/Object;Ljava/lang/Object;)Ljava/lang/Object;
      52: pop
      53: goto          21
      56: aload_1
      57: areturn

  public java.util.Map<org.apache.hadoop.hbase.master.RegionState$State, java.util.List<org.apache.hadoop.hbase.client.RegionInfo>> getRegionByStateOfTable(org.apache.hadoop.hbase.TableName);
    Code:
       0: invokestatic  #113                // Method org/apache/hadoop/hbase/master/RegionState$State.values:()[Lorg/apache/hadoop/hbase/master/RegionState$State;
       3: astore_2
       4: new           #106                // class java/util/HashMap
       7: dup
       8: aload_2
       9: arraylength
      10: invokespecial #114                // Method java/util/HashMap."<init>":(I)V
      13: astore_3
      14: iconst_0
      15: istore        4
      17: iload         4
      19: aload_2
      20: arraylength
      21: if_icmpge     48
      24: aload_3
      25: aload_2
      26: iload         4
      28: aaload
      29: new           #36                 // class java/util/ArrayList
      32: dup
      33: invokespecial #37                 // Method java/util/ArrayList."<init>":()V
      36: invokeinterface #111,  3          // InterfaceMethod java/util/Map.put:(Ljava/lang/Object;Ljava/lang/Object;)Ljava/lang/Object;
      41: pop
      42: iinc          4, 1
      45: goto          17
      48: aload_0
      49: getfield      #5                  // Field regionsMap:Ljava/util/concurrent/ConcurrentSkipListMap;
      52: invokevirtual #49                 // Method java/util/concurrent/ConcurrentSkipListMap.values:()Ljava/util/Collection;
      55: invokeinterface #41,  1           // InterfaceMethod java/util/Collection.iterator:()Ljava/util/Iterator;
      60: astore        4
      62: aload         4
      64: invokeinterface #42,  1           // InterfaceMethod java/util/Iterator.hasNext:()Z
      69: ifeq          124
      72: aload         4
      74: invokeinterface #43,  1           // InterfaceMethod java/util/Iterator.next:()Ljava/lang/Object;
      79: checkcast     #18                 // class org/apache/hadoop/hbase/master/assignment/RegionStateNode
      82: astore        5
      84: aload         5
      86: invokevirtual #44                 // Method org/apache/hadoop/hbase/master/assignment/RegionStateNode.getTable:()Lorg/apache/hadoop/hbase/TableName;
      89: aload_1
      90: invokevirtual #45                 // Method org/apache/hadoop/hbase/TableName.equals:(Ljava/lang/Object;)Z
      93: ifeq          121
      96: aload_3
      97: aload         5
      99: invokevirtual #115                // Method org/apache/hadoop/hbase/master/assignment/RegionStateNode.getState:()Lorg/apache/hadoop/hbase/master/RegionState$State;
     102: invokeinterface #110,  2          // InterfaceMethod java/util/Map.get:(Ljava/lang/Object;)Ljava/lang/Object;
     107: checkcast     #79                 // class java/util/List
     110: aload         5
     112: invokevirtual #48                 // Method org/apache/hadoop/hbase/master/assignment/RegionStateNode.getRegionInfo:()Lorg/apache/hadoop/hbase/client/RegionInfo;
     115: invokeinterface #103,  2          // InterfaceMethod java/util/List.add:(Ljava/lang/Object;)Z
     120: pop
     121: goto          62
     124: aload_3
     125: areturn

  public org.apache.hadoop.hbase.ServerName getRegionServerOfRegion(org.apache.hadoop.hbase.client.RegionInfo);
    Code:
       0: aload_0
       1: aload_1
       2: invokevirtual #52                 // Method getRegionStateNode:(Lorg/apache/hadoop/hbase/client/RegionInfo;)Lorg/apache/hadoop/hbase/master/assignment/RegionStateNode;
       5: astore_2
       6: aload_2
       7: ifnull        49
      10: aload_2
      11: invokevirtual #58                 // Method org/apache/hadoop/hbase/master/assignment/RegionStateNode.lock:()V
      14: aload_2
      15: invokevirtual #65                 // Method org/apache/hadoop/hbase/master/assignment/RegionStateNode.getRegionLocation:()Lorg/apache/hadoop/hbase/ServerName;
      18: astore_3
      19: aload_3
      20: ifnull        27
      23: aload_3
      24: goto          31
      27: aload_2
      28: invokevirtual #116                // Method org/apache/hadoop/hbase/master/assignment/RegionStateNode.getLastHost:()Lorg/apache/hadoop/hbase/ServerName;
      31: astore        4
      33: aload_2
      34: invokevirtual #60                 // Method org/apache/hadoop/hbase/master/assignment/RegionStateNode.unlock:()V
      37: aload         4
      39: areturn
      40: astore        5
      42: aload_2
      43: invokevirtual #60                 // Method org/apache/hadoop/hbase/master/assignment/RegionStateNode.unlock:()V
      46: aload         5
      48: athrow
      49: aconst_null
      50: areturn
    Exception table:
       from    to  target type
          14    33    40   any
          40    42    40   any

  public java.util.Map<org.apache.hadoop.hbase.TableName, java.util.Map<org.apache.hadoop.hbase.ServerName, java.util.List<org.apache.hadoop.hbase.client.RegionInfo>>> getAssignmentsForBalancer(boolean);
    Code:
       0: new           #106                // class java/util/HashMap
       3: dup
       4: invokespecial #107                // Method java/util/HashMap."<init>":()V
       7: astore_2
       8: iload_1
       9: ifeq          236
      12: aload_0
      13: getfield      #5                  // Field regionsMap:Ljava/util/concurrent/ConcurrentSkipListMap;
      16: invokevirtual #49                 // Method java/util/concurrent/ConcurrentSkipListMap.values:()Ljava/util/Collection;
      19: invokeinterface #41,  1           // InterfaceMethod java/util/Collection.iterator:()Ljava/util/Iterator;
      24: astore_3
      25: aload_3
      26: invokeinterface #42,  1           // InterfaceMethod java/util/Iterator.hasNext:()Z
      31: ifeq          144
      34: aload_3
      35: invokeinterface #43,  1           // InterfaceMethod java/util/Iterator.next:()Ljava/lang/Object;
      40: checkcast     #18                 // class org/apache/hadoop/hbase/master/assignment/RegionStateNode
      43: astore        4
      45: aload_2
      46: aload         4
      48: invokevirtual #44                 // Method org/apache/hadoop/hbase/master/assignment/RegionStateNode.getTable:()Lorg/apache/hadoop/hbase/TableName;
      51: invokedynamic #117,  0            // InvokeDynamic #5:apply:()Ljava/util/function/Function;
      56: invokeinterface #118,  3          // InterfaceMethod java/util/Map.computeIfAbsent:(Ljava/lang/Object;Ljava/util/function/Function;)Ljava/lang/Object;
      61: checkcast     #119                // class java/util/Map
      64: astore        5
      66: aload         4
      68: invokevirtual #65                 // Method org/apache/hadoop/hbase/master/assignment/RegionStateNode.getRegionLocation:()Lorg/apache/hadoop/hbase/ServerName;
      71: astore        6
      73: aload         6
      75: ifnonnull     109
      78: getstatic     #25                 // Field LOG:Lorg/slf4j/Logger;
      81: new           #27                 // class java/lang/StringBuilder
      84: dup
      85: invokespecial #28                 // Method java/lang/StringBuilder."<init>":()V
      88: ldc           #120                // String Skipping, no server for
      90: invokevirtual #30                 // Method java/lang/StringBuilder.append:(Ljava/lang/String;)Ljava/lang/StringBuilder;
      93: aload         4
      95: invokevirtual #31                 // Method java/lang/StringBuilder.append:(Ljava/lang/Object;)Ljava/lang/StringBuilder;
      98: invokevirtual #32                 // Method java/lang/StringBuilder.toString:()Ljava/lang/String;
     101: invokeinterface #121,  2          // InterfaceMethod org/slf4j/Logger.info:(Ljava/lang/String;)V
     106: goto          25
     109: aload         5
     111: aload         6
     113: invokedynamic #122,  0            // InvokeDynamic #6:apply:()Ljava/util/function/Function;
     118: invokeinterface #118,  3          // InterfaceMethod java/util/Map.computeIfAbsent:(Ljava/lang/Object;Ljava/util/function/Function;)Ljava/lang/Object;
     123: checkcast     #79                 // class java/util/List
     126: astore        7
     128: aload         7
     130: aload         4
     132: invokevirtual #48                 // Method org/apache/hadoop/hbase/master/assignment/RegionStateNode.getRegionInfo:()Lorg/apache/hadoop/hbase/client/RegionInfo;
     135: invokeinterface #103,  2          // InterfaceMethod java/util/List.add:(Ljava/lang/Object;)Z
     140: pop
     141: goto          25
     144: aload_2
     145: invokeinterface #123,  1          // InterfaceMethod java/util/Map.values:()Ljava/util/Collection;
     150: invokeinterface #41,  1           // InterfaceMethod java/util/Collection.iterator:()Ljava/util/Iterator;
     155: astore_3
     156: aload_3
     157: invokeinterface #42,  1           // InterfaceMethod java/util/Iterator.hasNext:()Z
     162: ifeq          233
     165: aload_3
     166: invokeinterface #43,  1           // InterfaceMethod java/util/Iterator.next:()Ljava/lang/Object;
     171: checkcast     #119                // class java/util/Map
     174: astore        4
     176: aload_0
     177: getfield      #13                 // Field serverMap:Ljava/util/concurrent/ConcurrentHashMap;
     180: invokevirtual #124                // Method java/util/concurrent/ConcurrentHashMap.keySet:()Ljava/util/concurrent/ConcurrentHashMap$KeySetView;
     183: invokevirtual #125                // Method java/util/concurrent/ConcurrentHashMap$KeySetView.iterator:()Ljava/util/Iterator;
     186: astore        5
     188: aload         5
     190: invokeinterface #42,  1           // InterfaceMethod java/util/Iterator.hasNext:()Z
     195: ifeq          230
     198: aload         5
     200: invokeinterface #43,  1           // InterfaceMethod java/util/Iterator.next:()Ljava/lang/Object;
     205: checkcast     #126                // class org/apache/hadoop/hbase/ServerName
     208: astore        6
     210: aload         4
     212: aload         6
     214: new           #36                 // class java/util/ArrayList
     217: dup
     218: invokespecial #37                 // Method java/util/ArrayList."<init>":()V
     221: invokeinterface #127,  3          // InterfaceMethod java/util/Map.putIfAbsent:(Ljava/lang/Object;Ljava/lang/Object;)Ljava/lang/Object;
     226: pop
     227: goto          188
     230: goto          156
     233: goto          316
     236: new           #106                // class java/util/HashMap
     239: dup
     240: aload_0
     241: getfield      #13                 // Field serverMap:Ljava/util/concurrent/ConcurrentHashMap;
     244: invokevirtual #128                // Method java/util/concurrent/ConcurrentHashMap.size:()I
     247: invokespecial #114                // Method java/util/HashMap."<init>":(I)V
     250: astore_3
     251: aload_0
     252: getfield      #13                 // Field serverMap:Ljava/util/concurrent/ConcurrentHashMap;
     255: invokevirtual #129                // Method java/util/concurrent/ConcurrentHashMap.values:()Ljava/util/Collection;
     258: invokeinterface #41,  1           // InterfaceMethod java/util/Collection.iterator:()Ljava/util/Iterator;
     263: astore        4
     265: aload         4
     267: invokeinterface #42,  1           // InterfaceMethod java/util/Iterator.hasNext:()Z
     272: ifeq          305
     275: aload         4
     277: invokeinterface #43,  1           // InterfaceMethod java/util/Iterator.next:()Ljava/lang/Object;
     282: checkcast     #130                // class org/apache/hadoop/hbase/master/assignment/ServerStateNode
     285: astore        5
     287: aload_3
     288: aload         5
     290: invokevirtual #131                // Method org/apache/hadoop/hbase/master/assignment/ServerStateNode.getServerName:()Lorg/apache/hadoop/hbase/ServerName;
     293: aload         5
     295: invokevirtual #132                // Method org/apache/hadoop/hbase/master/assignment/ServerStateNode.getRegionInfoList:()Ljava/util/List;
     298: invokevirtual #112                // Method java/util/HashMap.put:(Ljava/lang/Object;Ljava/lang/Object;)Ljava/lang/Object;
     301: pop
     302: goto          265
     305: aload_2
     306: getstatic     #133                // Field org/apache/hadoop/hbase/HConstants.ENSEMBLE_TABLE_NAME:Lorg/apache/hadoop/hbase/TableName;
     309: aload_3
     310: invokeinterface #111,  3          // InterfaceMethod java/util/Map.put:(Ljava/lang/Object;Ljava/lang/Object;)Ljava/lang/Object;
     315: pop
     316: aload_2
     317: areturn

  public boolean hasRegionsInTransition();
    Code:
       0: aload_0
       1: getfield      #7                  // Field regionInTransition:Ljava/util/concurrent/ConcurrentSkipListMap;
       4: invokevirtual #134                // Method java/util/concurrent/ConcurrentSkipListMap.isEmpty:()Z
       7: ifne          14
      10: iconst_1
      11: goto          15
      14: iconst_0
      15: ireturn

  public boolean isRegionInTransition(org.apache.hadoop.hbase.client.RegionInfo);
    Code:
       0: aload_0
       1: getfield      #7                  // Field regionInTransition:Ljava/util/concurrent/ConcurrentSkipListMap;
       4: aload_1
       5: invokevirtual #23                 // Method java/util/concurrent/ConcurrentSkipListMap.get:(Ljava/lang/Object;)Ljava/lang/Object;
       8: checkcast     #18                 // class org/apache/hadoop/hbase/master/assignment/RegionStateNode
      11: astore_2
      12: aload_2
      13: ifnull        23
      16: aload_2
      17: invokevirtual #102                // Method org/apache/hadoop/hbase/master/assignment/RegionStateNode.isInTransition:()Z
      20: goto          24
      23: iconst_0
      24: ireturn

  public org.apache.hadoop.hbase.master.RegionState getRegionTransitionState(org.apache.hadoop.hbase.client.RegionInfo);
    Code:
       0: aload_0
       1: getfield      #7                  // Field regionInTransition:Ljava/util/concurrent/ConcurrentSkipListMap;
       4: aload_1
       5: invokevirtual #23                 // Method java/util/concurrent/ConcurrentSkipListMap.get:(Ljava/lang/Object;)Ljava/lang/Object;
       8: checkcast     #18                 // class org/apache/hadoop/hbase/master/assignment/RegionStateNode
      11: astore_2
      12: aload_2
      13: ifnonnull     18
      16: aconst_null
      17: areturn
      18: aload_2
      19: invokevirtual #58                 // Method org/apache/hadoop/hbase/master/assignment/RegionStateNode.lock:()V
      22: aload_2
      23: invokevirtual #102                // Method org/apache/hadoop/hbase/master/assignment/RegionStateNode.isInTransition:()Z
      26: ifeq          36
      29: aload_2
      30: invokevirtual #47                 // Method org/apache/hadoop/hbase/master/assignment/RegionStateNode.toRegionState:()Lorg/apache/hadoop/hbase/master/RegionState;
      33: goto          37
      36: aconst_null
      37: astore_3
      38: aload_2
      39: invokevirtual #60                 // Method org/apache/hadoop/hbase/master/assignment/RegionStateNode.unlock:()V
      42: aload_3
      43: areturn
      44: astore        4
      46: aload_2
      47: invokevirtual #60                 // Method org/apache/hadoop/hbase/master/assignment/RegionStateNode.unlock:()V
      50: aload         4
      52: athrow
    Exception table:
       from    to  target type
          22    38    44   any
          44    46    44   any

  public java.util.List<org.apache.hadoop.hbase.master.assignment.RegionStateNode> getRegionsInTransition();
    Code:
       0: new           #36                 // class java/util/ArrayList
       3: dup
       4: aload_0
       5: getfield      #7                  // Field regionInTransition:Ljava/util/concurrent/ConcurrentSkipListMap;
       8: invokevirtual #49                 // Method java/util/concurrent/ConcurrentSkipListMap.values:()Ljava/util/Collection;
      11: invokespecial #135                // Method java/util/ArrayList."<init>":(Ljava/util/Collection;)V
      14: areturn

  public int getRegionsInTransitionCount();
    Code:
       0: aload_0
       1: getfield      #7                  // Field regionInTransition:Ljava/util/concurrent/ConcurrentSkipListMap;
       4: invokevirtual #50                 // Method java/util/concurrent/ConcurrentSkipListMap.size:()I
       7: ireturn

  public java.util.List<org.apache.hadoop.hbase.master.RegionState> getRegionsStateInTransition();
    Code:
       0: new           #36                 // class java/util/ArrayList
       3: dup
       4: aload_0
       5: getfield      #7                  // Field regionInTransition:Ljava/util/concurrent/ConcurrentSkipListMap;
       8: invokevirtual #50                 // Method java/util/concurrent/ConcurrentSkipListMap.size:()I
      11: invokespecial #51                 // Method java/util/ArrayList."<init>":(I)V
      14: astore_1
      15: aload_0
      16: getfield      #7                  // Field regionInTransition:Ljava/util/concurrent/ConcurrentSkipListMap;
      19: invokevirtual #49                 // Method java/util/concurrent/ConcurrentSkipListMap.values:()Ljava/util/Collection;
      22: invokeinterface #41,  1           // InterfaceMethod java/util/Collection.iterator:()Ljava/util/Iterator;
      27: astore_2
      28: aload_2
      29: invokeinterface #42,  1           // InterfaceMethod java/util/Iterator.hasNext:()Z
      34: ifeq          61
      37: aload_2
      38: invokeinterface #43,  1           // InterfaceMethod java/util/Iterator.next:()Ljava/lang/Object;
      43: checkcast     #18                 // class org/apache/hadoop/hbase/master/assignment/RegionStateNode
      46: astore_3
      47: aload_1
      48: aload_3
      49: invokevirtual #47                 // Method org/apache/hadoop/hbase/master/assignment/RegionStateNode.toRegionState:()Lorg/apache/hadoop/hbase/master/RegionState;
      52: invokeinterface #103,  2          // InterfaceMethod java/util/List.add:(Ljava/lang/Object;)Z
      57: pop
      58: goto          28
      61: aload_1
      62: areturn

  public java.util.SortedSet<org.apache.hadoop.hbase.master.RegionState> getRegionsInTransitionOrderedByTimestamp();
    Code:
       0: new           #136                // class java/util/TreeSet
       3: dup
       4: getstatic     #137                // Field REGION_STATE_STAMP_COMPARATOR:Lorg/apache/hadoop/hbase/master/assignment/RegionStates$RegionStateStampComparator;
       7: invokespecial #138                // Method java/util/TreeSet."<init>":(Ljava/util/Comparator;)V
      10: astore_1
      11: aload_0
      12: getfield      #7                  // Field regionInTransition:Ljava/util/concurrent/ConcurrentSkipListMap;
      15: invokevirtual #49                 // Method java/util/concurrent/ConcurrentSkipListMap.values:()Ljava/util/Collection;
      18: invokeinterface #41,  1           // InterfaceMethod java/util/Collection.iterator:()Ljava/util/Iterator;
      23: astore_2
      24: aload_2
      25: invokeinterface #42,  1           // InterfaceMethod java/util/Iterator.hasNext:()Z
      30: ifeq          57
      33: aload_2
      34: invokeinterface #43,  1           // InterfaceMethod java/util/Iterator.next:()Ljava/lang/Object;
      39: checkcast     #18                 // class org/apache/hadoop/hbase/master/assignment/RegionStateNode
      42: astore_3
      43: aload_1
      44: aload_3
      45: invokevirtual #47                 // Method org/apache/hadoop/hbase/master/assignment/RegionStateNode.toRegionState:()Lorg/apache/hadoop/hbase/master/RegionState;
      48: invokeinterface #139,  2          // InterfaceMethod java/util/SortedSet.add:(Ljava/lang/Object;)Z
      53: pop
      54: goto          24
      57: aload_1
      58: areturn

  public void addToOfflineRegions(org.apache.hadoop.hbase.master.assignment.RegionStateNode);
    Code:
       0: getstatic     #25                 // Field LOG:Lorg/slf4j/Logger;
       3: new           #27                 // class java/lang/StringBuilder
       6: dup
       7: invokespecial #28                 // Method java/lang/StringBuilder."<init>":()V
      10: ldc           #140                // String Added to offline, CURRENTLY NEVER CLEARED!!!
      12: invokevirtual #30                 // Method java/lang/StringBuilder.append:(Ljava/lang/String;)Ljava/lang/StringBuilder;
      15: aload_1
      16: invokevirtual #31                 // Method java/lang/StringBuilder.append:(Ljava/lang/Object;)Ljava/lang/StringBuilder;
      19: invokevirtual #32                 // Method java/lang/StringBuilder.toString:()Ljava/lang/String;
      22: invokeinterface #121,  2          // InterfaceMethod org/slf4j/Logger.info:(Ljava/lang/String;)V
      27: aload_0
      28: getfield      #9                  // Field regionOffline:Ljava/util/concurrent/ConcurrentSkipListMap;
      31: aload_1
      32: invokevirtual #48                 // Method org/apache/hadoop/hbase/master/assignment/RegionStateNode.getRegionInfo:()Lorg/apache/hadoop/hbase/client/RegionInfo;
      35: aload_1
      36: invokevirtual #141                // Method java/util/concurrent/ConcurrentSkipListMap.put:(Ljava/lang/Object;Ljava/lang/Object;)Ljava/lang/Object;
      39: pop
      40: return

  public void removeFromOfflineRegions(org.apache.hadoop.hbase.client.RegionInfo);
    Code:
       0: aload_0
       1: getfield      #9                  // Field regionOffline:Ljava/util/concurrent/ConcurrentSkipListMap;
       4: aload_1
       5: invokevirtual #24                 // Method java/util/concurrent/ConcurrentSkipListMap.remove:(Ljava/lang/Object;)Ljava/lang/Object;
       8: pop
       9: return

  public org.apache.hadoop.hbase.master.assignment.RegionStates$RegionFailedOpen addToFailedOpen(org.apache.hadoop.hbase.master.assignment.RegionStateNode);
    Code:
       0: aload_1
       1: invokevirtual #48                 // Method org/apache/hadoop/hbase/master/assignment/RegionStateNode.getRegionInfo:()Lorg/apache/hadoop/hbase/client/RegionInfo;
       4: invokeinterface #16,  1           // InterfaceMethod org/apache/hadoop/hbase/client/RegionInfo.getRegionName:()[B
       9: astore_2
      10: aload_0
      11: getfield      #10                 // Field regionFailedOpen:Ljava/util/concurrent/ConcurrentSkipListMap;
      14: aload_2
      15: invokevirtual #23                 // Method java/util/concurrent/ConcurrentSkipListMap.get:(Ljava/lang/Object;)Ljava/lang/Object;
      18: checkcast     #142                // class org/apache/hadoop/hbase/master/assignment/RegionStates$RegionFailedOpen
      21: astore_3
      22: aload_3
      23: ifnonnull     64
      26: new           #142                // class org/apache/hadoop/hbase/master/assignment/RegionStates$RegionFailedOpen
      29: dup
      30: aload_1
      31: invokespecial #143                // Method org/apache/hadoop/hbase/master/assignment/RegionStates$RegionFailedOpen."<init>":(Lorg/apache/hadoop/hbase/master/assignment/RegionStateNode;)V
      34: astore        4
      36: aload_0
      37: getfield      #10                 // Field regionFailedOpen:Ljava/util/concurrent/ConcurrentSkipListMap;
      40: aload_2
      41: aload         4
      43: invokevirtual #20                 // Method java/util/concurrent/ConcurrentSkipListMap.putIfAbsent:(Ljava/lang/Object;Ljava/lang/Object;)Ljava/lang/Object;
      46: checkcast     #142                // class org/apache/hadoop/hbase/master/assignment/RegionStates$RegionFailedOpen
      49: astore        5
      51: aload         5
      53: ifnull        61
      56: aload         5
      58: goto          63
      61: aload         4
      63: astore_3
      64: aload_3
      65: areturn

  public org.apache.hadoop.hbase.master.assignment.RegionStates$RegionFailedOpen getFailedOpen(org.apache.hadoop.hbase.client.RegionInfo);
    Code:
       0: aload_0
       1: getfield      #10                 // Field regionFailedOpen:Ljava/util/concurrent/ConcurrentSkipListMap;
       4: aload_1
       5: invokeinterface #16,  1           // InterfaceMethod org/apache/hadoop/hbase/client/RegionInfo.getRegionName:()[B
      10: invokevirtual #23                 // Method java/util/concurrent/ConcurrentSkipListMap.get:(Ljava/lang/Object;)Ljava/lang/Object;
      13: checkcast     #142                // class org/apache/hadoop/hbase/master/assignment/RegionStates$RegionFailedOpen
      16: areturn

  public void removeFromFailedOpen(org.apache.hadoop.hbase.client.RegionInfo);
    Code:
       0: aload_0
       1: getfield      #10                 // Field regionFailedOpen:Ljava/util/concurrent/ConcurrentSkipListMap;
       4: aload_1
       5: invokeinterface #16,  1           // InterfaceMethod org/apache/hadoop/hbase/client/RegionInfo.getRegionName:()[B
      10: invokevirtual #24                 // Method java/util/concurrent/ConcurrentSkipListMap.remove:(Ljava/lang/Object;)Ljava/lang/Object;
      13: pop
      14: return

  public java.util.List<org.apache.hadoop.hbase.master.RegionState> getRegionFailedOpen();
    Code:
       0: aload_0
       1: getfield      #10                 // Field regionFailedOpen:Ljava/util/concurrent/ConcurrentSkipListMap;
       4: invokevirtual #134                // Method java/util/concurrent/ConcurrentSkipListMap.isEmpty:()Z
       7: ifeq          14
      10: invokestatic  #144                // Method java/util/Collections.emptyList:()Ljava/util/List;
      13: areturn
      14: new           #36                 // class java/util/ArrayList
      17: dup
      18: aload_0
      19: getfield      #10                 // Field regionFailedOpen:Ljava/util/concurrent/ConcurrentSkipListMap;
      22: invokevirtual #50                 // Method java/util/concurrent/ConcurrentSkipListMap.size:()I
      25: invokespecial #51                 // Method java/util/ArrayList."<init>":(I)V
      28: astore_1
      29: aload_0
      30: getfield      #10                 // Field regionFailedOpen:Ljava/util/concurrent/ConcurrentSkipListMap;
      33: invokevirtual #49                 // Method java/util/concurrent/ConcurrentSkipListMap.values:()Ljava/util/Collection;
      36: invokeinterface #41,  1           // InterfaceMethod java/util/Collection.iterator:()Ljava/util/Iterator;
      41: astore_2
      42: aload_2
      43: invokeinterface #42,  1           // InterfaceMethod java/util/Iterator.hasNext:()Z
      48: ifeq          76
      51: aload_2
      52: invokeinterface #43,  1           // InterfaceMethod java/util/Iterator.next:()Ljava/lang/Object;
      57: checkcast     #142                // class org/apache/hadoop/hbase/master/assignment/RegionStates$RegionFailedOpen
      60: astore_3
      61: aload_1
      62: aload_3
      63: invokevirtual #145                // Method org/apache/hadoop/hbase/master/assignment/RegionStates$RegionFailedOpen.getRegionStateNode:()Lorg/apache/hadoop/hbase/master/assignment/RegionStateNode;
      66: invokevirtual #47                 // Method org/apache/hadoop/hbase/master/assignment/RegionStateNode.toRegionState:()Lorg/apache/hadoop/hbase/master/RegionState;
      69: invokevirtual #46                 // Method java/util/ArrayList.add:(Ljava/lang/Object;)Z
      72: pop
      73: goto          42
      76: aload_1
      77: areturn

  public org.apache.hadoop.hbase.master.assignment.ServerStateNode getOrCreateServer(org.apache.hadoop.hbase.ServerName);
    Code:
       0: aload_0
       1: getfield      #13                 // Field serverMap:Ljava/util/concurrent/ConcurrentHashMap;
       4: aload_1
       5: invokevirtual #146                // Method java/util/concurrent/ConcurrentHashMap.get:(Ljava/lang/Object;)Ljava/lang/Object;
       8: checkcast     #130                // class org/apache/hadoop/hbase/master/assignment/ServerStateNode
      11: astore_2
      12: aload_2
      13: ifnonnull     48
      16: new           #130                // class org/apache/hadoop/hbase/master/assignment/ServerStateNode
      19: dup
      20: aload_1
      21: invokespecial #147                // Method org/apache/hadoop/hbase/master/assignment/ServerStateNode."<init>":(Lorg/apache/hadoop/hbase/ServerName;)V
      24: astore_2
      25: aload_0
      26: getfield      #13                 // Field serverMap:Ljava/util/concurrent/ConcurrentHashMap;
      29: aload_1
      30: aload_2
      31: invokevirtual #148                // Method java/util/concurrent/ConcurrentHashMap.putIfAbsent:(Ljava/lang/Object;Ljava/lang/Object;)Ljava/lang/Object;
      34: checkcast     #130                // class org/apache/hadoop/hbase/master/assignment/ServerStateNode
      37: astore_3
      38: aload_3
      39: ifnull        46
      42: aload_3
      43: goto          47
      46: aload_2
      47: astore_2
      48: aload_2
      49: areturn

  public void removeServer(org.apache.hadoop.hbase.ServerName);
    Code:
       0: aload_0
       1: getfield      #13                 // Field serverMap:Ljava/util/concurrent/ConcurrentHashMap;
       4: aload_1
       5: invokevirtual #149                // Method java/util/concurrent/ConcurrentHashMap.remove:(Ljava/lang/Object;)Ljava/lang/Object;
       8: pop
       9: return

  public org.apache.hadoop.hbase.master.assignment.ServerStateNode getServerNode(org.apache.hadoop.hbase.ServerName);
    Code:
       0: aload_0
       1: getfield      #13                 // Field serverMap:Ljava/util/concurrent/ConcurrentHashMap;
       4: aload_1
       5: invokevirtual #146                // Method java/util/concurrent/ConcurrentHashMap.get:(Ljava/lang/Object;)Ljava/lang/Object;
       8: checkcast     #130                // class org/apache/hadoop/hbase/master/assignment/ServerStateNode
      11: areturn

  public double getAverageLoad();
    Code:
       0: iconst_0
       1: istore_1
       2: iconst_0
       3: istore_2
       4: aload_0
       5: getfield      #13                 // Field serverMap:Ljava/util/concurrent/ConcurrentHashMap;
       8: invokevirtual #129                // Method java/util/concurrent/ConcurrentHashMap.values:()Ljava/util/Collection;
      11: invokeinterface #41,  1           // InterfaceMethod java/util/Collection.iterator:()Ljava/util/Iterator;
      16: astore_3
      17: aload_3
      18: invokeinterface #42,  1           // InterfaceMethod java/util/Iterator.hasNext:()Z
      23: ifeq          51
      26: aload_3
      27: invokeinterface #43,  1           // InterfaceMethod java/util/Iterator.next:()Ljava/lang/Object;
      32: checkcast     #130                // class org/apache/hadoop/hbase/master/assignment/ServerStateNode
      35: astore        4
      37: iload_2
      38: aload         4
      40: invokevirtual #150                // Method org/apache/hadoop/hbase/master/assignment/ServerStateNode.getRegionCount:()I
      43: iadd
      44: istore_2
      45: iinc          1, 1
      48: goto          17
      51: iload_1
      52: ifne          59
      55: dconst_0
      56: goto          64
      59: iload_2
      60: i2d
      61: iload_1
      62: i2d
      63: ddiv
      64: dreturn

  public org.apache.hadoop.hbase.master.assignment.ServerStateNode addRegionToServer(org.apache.hadoop.hbase.master.assignment.RegionStateNode);
    Code:
       0: aload_0
       1: aload_1
       2: invokevirtual #65                 // Method org/apache/hadoop/hbase/master/assignment/RegionStateNode.getRegionLocation:()Lorg/apache/hadoop/hbase/ServerName;
       5: invokevirtual #93                 // Method getOrCreateServer:(Lorg/apache/hadoop/hbase/ServerName;)Lorg/apache/hadoop/hbase/master/assignment/ServerStateNode;
       8: astore_2
       9: aload_2
      10: aload_1
      11: invokevirtual #151                // Method org/apache/hadoop/hbase/master/assignment/ServerStateNode.addRegion:(Lorg/apache/hadoop/hbase/master/assignment/RegionStateNode;)V
      14: aload_2
      15: areturn

  public boolean isReplicaAvailableForRegion(org.apache.hadoop.hbase.client.RegionInfo);
    Code:
       0: aload_1
       1: invokestatic  #152                // Method org/apache/hadoop/hbase/client/RegionReplicaUtil.isDefaultReplica:(Lorg/apache/hadoop/hbase/client/RegionInfo;)Z
       4: ifne          9
       7: iconst_1
       8: ireturn
       9: aload_0
      10: getfield      #5                  // Field regionsMap:Ljava/util/concurrent/ConcurrentSkipListMap;
      13: aload_1
      14: invokeinterface #16,  1           // InterfaceMethod org/apache/hadoop/hbase/client/RegionInfo.getRegionName:()[B
      19: invokevirtual #39                 // Method java/util/concurrent/ConcurrentSkipListMap.tailMap:(Ljava/lang/Object;)Ljava/util/concurrent/ConcurrentNavigableMap;
      22: invokeinterface #40,  1           // InterfaceMethod java/util/concurrent/ConcurrentNavigableMap.values:()Ljava/util/Collection;
      27: invokeinterface #41,  1           // InterfaceMethod java/util/Collection.iterator:()Ljava/util/Iterator;
      32: astore_2
      33: aload_2
      34: invokeinterface #42,  1           // InterfaceMethod java/util/Iterator.hasNext:()Z
      39: ifeq          97
      42: aload_2
      43: invokeinterface #43,  1           // InterfaceMethod java/util/Iterator.next:()Ljava/lang/Object;
      48: checkcast     #18                 // class org/apache/hadoop/hbase/master/assignment/RegionStateNode
      51: astore_3
      52: aload_3
      53: invokevirtual #44                 // Method org/apache/hadoop/hbase/master/assignment/RegionStateNode.getTable:()Lorg/apache/hadoop/hbase/TableName;
      56: aload_1
      57: invokeinterface #153,  1          // InterfaceMethod org/apache/hadoop/hbase/client/RegionInfo.getTable:()Lorg/apache/hadoop/hbase/TableName;
      62: invokevirtual #45                 // Method org/apache/hadoop/hbase/TableName.equals:(Ljava/lang/Object;)Z
      65: ifeq          97
      68: aload_1
      69: aload_3
      70: invokevirtual #48                 // Method org/apache/hadoop/hbase/master/assignment/RegionStateNode.getRegionInfo:()Lorg/apache/hadoop/hbase/client/RegionInfo;
      73: invokestatic  #154                // Method org/apache/hadoop/hbase/util/ServerRegionReplicaUtil.isReplicasForSameRegion:(Lorg/apache/hadoop/hbase/client/RegionInfo;Lorg/apache/hadoop/hbase/client/RegionInfo;)Z
      76: ifne          82
      79: goto          97
      82: aload_3
      83: invokevirtual #48                 // Method org/apache/hadoop/hbase/master/assignment/RegionStateNode.getRegionInfo:()Lorg/apache/hadoop/hbase/client/RegionInfo;
      86: invokestatic  #152                // Method org/apache/hadoop/hbase/client/RegionReplicaUtil.isDefaultReplica:(Lorg/apache/hadoop/hbase/client/RegionInfo;)Z
      89: ifne          94
      92: iconst_1
      93: ireturn
      94: goto          33
      97: iconst_0
      98: ireturn

  public org.apache.hadoop.hbase.master.assignment.ServerStateNode removeRegionFromServer(org.apache.hadoop.hbase.ServerName, org.apache.hadoop.hbase.master.assignment.RegionStateNode);
    Code:
       0: aload_0
       1: aload_1
       2: invokevirtual #93                 // Method getOrCreateServer:(Lorg/apache/hadoop/hbase/ServerName;)Lorg/apache/hadoop/hbase/master/assignment/ServerStateNode;
       5: astore_3
       6: aload_3
       7: aload_2
       8: invokevirtual #155                // Method org/apache/hadoop/hbase/master/assignment/ServerStateNode.removeRegion:(Lorg/apache/hadoop/hbase/master/assignment/RegionStateNode;)V
      11: aload_3
      12: areturn

  public static java.lang.String regionNamesToString(java.util.Collection<byte[]>);
    Code:
       0: new           #27                 // class java/lang/StringBuilder
       3: dup
       4: invokespecial #28                 // Method java/lang/StringBuilder."<init>":()V
       7: astore_1
       8: aload_0
       9: invokeinterface #41,  1           // InterfaceMethod java/util/Collection.iterator:()Ljava/util/Iterator;
      14: astore_2
      15: aload_1
      16: ldc           #156                // String [
      18: invokevirtual #30                 // Method java/lang/StringBuilder.append:(Ljava/lang/String;)Ljava/lang/StringBuilder;
      21: pop
      22: aload_2
      23: invokeinterface #42,  1           // InterfaceMethod java/util/Iterator.hasNext:()Z
      28: ifeq          84
      31: aload_1
      32: aload_2
      33: invokeinterface #43,  1           // InterfaceMethod java/util/Iterator.next:()Ljava/lang/Object;
      38: checkcast     #157                // class "[B"
      41: invokestatic  #158                // Method org/apache/hadoop/hbase/util/Bytes.toStringBinary:([B)Ljava/lang/String;
      44: invokevirtual #30                 // Method java/lang/StringBuilder.append:(Ljava/lang/String;)Ljava/lang/StringBuilder;
      47: pop
      48: aload_2
      49: invokeinterface #42,  1           // InterfaceMethod java/util/Iterator.hasNext:()Z
      54: ifeq          84
      57: aload_1
      58: ldc           #159                // String ,
      60: invokevirtual #30                 // Method java/lang/StringBuilder.append:(Ljava/lang/String;)Ljava/lang/StringBuilder;
      63: pop
      64: aload_1
      65: aload_2
      66: invokeinterface #43,  1           // InterfaceMethod java/util/Iterator.next:()Ljava/lang/Object;
      71: checkcast     #157                // class "[B"
      74: invokestatic  #158                // Method org/apache/hadoop/hbase/util/Bytes.toStringBinary:([B)Ljava/lang/String;
      77: invokevirtual #30                 // Method java/lang/StringBuilder.append:(Ljava/lang/String;)Ljava/lang/StringBuilder;
      80: pop
      81: goto          48
      84: aload_1
      85: ldc           #160                // String ]
      87: invokevirtual #30                 // Method java/lang/StringBuilder.append:(Ljava/lang/String;)Ljava/lang/StringBuilder;
      90: pop
      91: aload_1
      92: invokevirtual #32                 // Method java/lang/StringBuilder.toString:()Ljava/lang/String;
      95: areturn

  static {};
    Code:
       0: ldc           #161                // class org/apache/hadoop/hbase/master/assignment/RegionStates
       2: invokestatic  #162                // Method org/slf4j/LoggerFactory.getLogger:(Ljava/lang/Class;)Lorg/slf4j/Logger;
       5: putstatic     #25                 // Field LOG:Lorg/slf4j/Logger;
       8: new           #163                // class org/apache/hadoop/hbase/master/assignment/RegionStates$RegionStateStampComparator
      11: dup
      12: aconst_null
      13: invokespecial #164                // Method org/apache/hadoop/hbase/master/assignment/RegionStates$RegionStateStampComparator."<init>":(Lorg/apache/hadoop/hbase/master/assignment/RegionStates$1;)V
      16: putstatic     #137                // Field REGION_STATE_STAMP_COMPARATOR:Lorg/apache/hadoop/hbase/master/assignment/RegionStates$RegionStateStampComparator;
      19: return
}
