Compiled from "RegionInfoBuilder.java"
class org.apache.hadoop.hbase.client.RegionInfoBuilder$MutableRegionInfo implements org.apache.hadoop.hbase.client.RegionInfo, java.lang.Comparable<org.apache.hadoop.hbase.client.RegionInfo> {
  org.apache.hadoop.hbase.client.RegionInfoBuilder$MutableRegionInfo(org.apache.hadoop.hbase.TableName, byte[], byte[], boolean, long, int, boolean, byte[]);
    Code:
       0: aload_0
       1: aload_1
       2: invokestatic  #18                 // Method checkTableName:(Lorg/apache/hadoop/hbase/TableName;)Lorg/apache/hadoop/hbase/TableName;
       5: aload_2
       6: invokestatic  #4                  // Method checkStartKey:([B)[B
       9: aload_3
      10: invokestatic  #5                  // Method checkEndKey:([B)[B
      13: iload         4
      15: lload         5
      17: iload         7
      19: invokestatic  #19                 // Method checkReplicaId:(I)I
      22: iload         8
      24: aload         9
      26: aload         9
      28: invokestatic  #20                 // InterfaceMethod org/apache/hadoop/hbase/client/RegionInfo.encodeRegionName:([B)Ljava/lang/String;
      31: invokespecial #21                 // Method "<init>":(Lorg/apache/hadoop/hbase/TableName;[B[BZJIZ[BLjava/lang/String;)V
      34: return

  org.apache.hadoop.hbase.client.RegionInfoBuilder$MutableRegionInfo(org.apache.hadoop.hbase.TableName, byte[], byte[], boolean, long, int, boolean, byte[], java.lang.String);
    Code:
       0: aload_0
       1: invokespecial #22                 // Method java/lang/Object."<init>":()V
       4: aload_0
       5: iconst_0
       6: putfield      #23                 // Field offLine:Z
       9: aload_0
      10: iconst_0
      11: putfield      #24                 // Field split:Z
      14: aload_0
      15: aload_1
      16: invokestatic  #18                 // Method checkTableName:(Lorg/apache/hadoop/hbase/TableName;)Lorg/apache/hadoop/hbase/TableName;
      19: putfield      #25                 // Field tableName:Lorg/apache/hadoop/hbase/TableName;
      22: aload_0
      23: aload_2
      24: invokestatic  #4                  // Method checkStartKey:([B)[B
      27: putfield      #26                 // Field startKey:[B
      30: aload_0
      31: aload_3
      32: invokestatic  #5                  // Method checkEndKey:([B)[B
      35: putfield      #27                 // Field endKey:[B
      38: aload_0
      39: iload         4
      41: putfield      #24                 // Field split:Z
      44: aload_0
      45: lload         5
      47: putfield      #28                 // Field regionId:J
      50: aload_0
      51: iload         7
      53: invokestatic  #19                 // Method checkReplicaId:(I)I
      56: putfield      #29                 // Field replicaId:I
      59: aload_0
      60: iload         8
      62: putfield      #23                 // Field offLine:Z
      65: aload         9
      67: invokestatic  #30                 // Method org/apache/commons/lang3/ArrayUtils.isEmpty:([B)Z
      70: ifeq          128
      73: aload_0
      74: aload_0
      75: getfield      #25                 // Field tableName:Lorg/apache/hadoop/hbase/TableName;
      78: aload_0
      79: getfield      #26                 // Field startKey:[B
      82: aload_0
      83: getfield      #28                 // Field regionId:J
      86: aload_0
      87: getfield      #29                 // Field replicaId:I
      90: aload_0
      91: getfield      #25                 // Field tableName:Lorg/apache/hadoop/hbase/TableName;
      94: getstatic     #31                 // Field org/apache/hadoop/hbase/TableName.META_TABLE_NAME:Lorg/apache/hadoop/hbase/TableName;
      97: invokevirtual #32                 // Method org/apache/hadoop/hbase/TableName.equals:(Ljava/lang/Object;)Z
     100: ifne          107
     103: iconst_1
     104: goto          108
     107: iconst_0
     108: invokestatic  #16                 // InterfaceMethod org/apache/hadoop/hbase/client/RegionInfo.createRegionName:(Lorg/apache/hadoop/hbase/TableName;[BJIZ)[B
     111: putfield      #33                 // Field regionName:[B
     114: aload_0
     115: aload_0
     116: getfield      #33                 // Field regionName:[B
     119: invokestatic  #20                 // InterfaceMethod org/apache/hadoop/hbase/client/RegionInfo.encodeRegionName:([B)Ljava/lang/String;
     122: putfield      #34                 // Field encodedName:Ljava/lang/String;
     125: goto          140
     128: aload_0
     129: aload         9
     131: putfield      #33                 // Field regionName:[B
     134: aload_0
     135: aload         10
     137: putfield      #34                 // Field encodedName:Ljava/lang/String;
     140: aload_0
     141: aload_0
     142: getfield      #25                 // Field tableName:Lorg/apache/hadoop/hbase/TableName;
     145: aload_0
     146: getfield      #26                 // Field startKey:[B
     149: aload_0
     150: getfield      #27                 // Field endKey:[B
     153: aload_0
     154: getfield      #28                 // Field regionId:J
     157: aload_0
     158: getfield      #29                 // Field replicaId:I
     161: aload_0
     162: getfield      #23                 // Field offLine:Z
     165: aload_0
     166: getfield      #33                 // Field regionName:[B
     169: invokestatic  #35                 // Method generateHashCode:(Lorg/apache/hadoop/hbase/TableName;[B[BJIZ[B)I
     172: putfield      #36                 // Field hashCode:I
     175: aload_0
     176: aload_0
     177: getfield      #34                 // Field encodedName:Ljava/lang/String;
     180: invokestatic  #37                 // Method org/apache/hadoop/hbase/util/Bytes.toBytes:(Ljava/lang/String;)[B
     183: putfield      #38                 // Field encodedNameAsBytes:[B
     186: return

  public java.lang.String getShortNameToLog();
    Code:
       0: aload_0
       1: invokevirtual #39                 // Method getEncodedName:()Ljava/lang/String;
       4: invokestatic  #40                 // InterfaceMethod org/apache/hadoop/hbase/client/RegionInfo.prettyPrint:(Ljava/lang/String;)Ljava/lang/String;
       7: areturn

  public long getRegionId();
    Code:
       0: aload_0
       1: getfield      #28                 // Field regionId:J
       4: lreturn

  public byte[] getRegionName();
    Code:
       0: aload_0
       1: getfield      #33                 // Field regionName:[B
       4: areturn

  public java.lang.String getRegionNameAsString();
    Code:
       0: aload_0
       1: aload_0
       2: getfield      #33                 // Field regionName:[B
       5: invokestatic  #41                 // InterfaceMethod org/apache/hadoop/hbase/client/RegionInfo.getRegionNameAsString:(Lorg/apache/hadoop/hbase/client/RegionInfo;[B)Ljava/lang/String;
       8: areturn

  public java.lang.String getEncodedName();
    Code:
       0: aload_0
       1: getfield      #34                 // Field encodedName:Ljava/lang/String;
       4: areturn

  public byte[] getEncodedNameAsBytes();
    Code:
       0: aload_0
       1: getfield      #38                 // Field encodedNameAsBytes:[B
       4: areturn

  public byte[] getStartKey();
    Code:
       0: aload_0
       1: getfield      #26                 // Field startKey:[B
       4: areturn

  public byte[] getEndKey();
    Code:
       0: aload_0
       1: getfield      #27                 // Field endKey:[B
       4: areturn

  public org.apache.hadoop.hbase.TableName getTable();
    Code:
       0: aload_0
       1: getfield      #25                 // Field tableName:Lorg/apache/hadoop/hbase/TableName;
       4: areturn

  public boolean containsRange(byte[], byte[]);
    Code:
       0: aload_1
       1: aload_2
       2: invokestatic  #42                 // Method org/apache/hadoop/hbase/util/Bytes.compareTo:([B[B)I
       5: ifle          50
       8: new           #11                 // class java/lang/IllegalArgumentException
      11: dup
      12: new           #43                 // class java/lang/StringBuilder
      15: dup
      16: invokespecial #44                 // Method java/lang/StringBuilder."<init>":()V
      19: ldc           #45                 // String Invalid range:
      21: invokevirtual #46                 // Method java/lang/StringBuilder.append:(Ljava/lang/String;)Ljava/lang/StringBuilder;
      24: aload_1
      25: invokestatic  #47                 // Method org/apache/hadoop/hbase/util/Bytes.toStringBinary:([B)Ljava/lang/String;
      28: invokevirtual #46                 // Method java/lang/StringBuilder.append:(Ljava/lang/String;)Ljava/lang/StringBuilder;
      31: ldc           #48                 // String  >
      33: invokevirtual #46                 // Method java/lang/StringBuilder.append:(Ljava/lang/String;)Ljava/lang/StringBuilder;
      36: aload_2
      37: invokestatic  #47                 // Method org/apache/hadoop/hbase/util/Bytes.toStringBinary:([B)Ljava/lang/String;
      40: invokevirtual #46                 // Method java/lang/StringBuilder.append:(Ljava/lang/String;)Ljava/lang/StringBuilder;
      43: invokevirtual #49                 // Method java/lang/StringBuilder.toString:()Ljava/lang/String;
      46: invokespecial #13                 // Method java/lang/IllegalArgumentException."<init>":(Ljava/lang/String;)V
      49: athrow
      50: aload_1
      51: aload_0
      52: getfield      #26                 // Field startKey:[B
      55: invokestatic  #42                 // Method org/apache/hadoop/hbase/util/Bytes.compareTo:([B[B)I
      58: iflt          65
      61: iconst_1
      62: goto          66
      65: iconst_0
      66: istore_3
      67: aload_2
      68: aload_0
      69: getfield      #27                 // Field endKey:[B
      72: invokestatic  #42                 // Method org/apache/hadoop/hbase/util/Bytes.compareTo:([B[B)I
      75: iflt          91
      78: aload_0
      79: getfield      #27                 // Field endKey:[B
      82: getstatic     #50                 // Field org/apache/hadoop/hbase/HConstants.EMPTY_BYTE_ARRAY:[B
      85: invokestatic  #51                 // Method org/apache/hadoop/hbase/util/Bytes.equals:([B[B)Z
      88: ifeq          95
      91: iconst_1
      92: goto          96
      95: iconst_0
      96: istore        4
      98: iload_3
      99: ifeq          111
     102: iload         4
     104: ifeq          111
     107: iconst_1
     108: goto          112
     111: iconst_0
     112: ireturn

  public boolean containsRow(byte[]);
    Code:
       0: aload_1
       1: aload_0
       2: getfield      #26                 // Field startKey:[B
       5: invokestatic  #42                 // Method org/apache/hadoop/hbase/util/Bytes.compareTo:([B[B)I
       8: iflt          39
      11: aload_1
      12: aload_0
      13: getfield      #27                 // Field endKey:[B
      16: invokestatic  #42                 // Method org/apache/hadoop/hbase/util/Bytes.compareTo:([B[B)I
      19: iflt          35
      22: aload_0
      23: getfield      #27                 // Field endKey:[B
      26: getstatic     #50                 // Field org/apache/hadoop/hbase/HConstants.EMPTY_BYTE_ARRAY:[B
      29: invokestatic  #51                 // Method org/apache/hadoop/hbase/util/Bytes.equals:([B[B)Z
      32: ifeq          39
      35: iconst_1
      36: goto          40
      39: iconst_0
      40: ireturn

  public boolean isMetaRegion();
    Code:
       0: aload_0
       1: getfield      #25                 // Field tableName:Lorg/apache/hadoop/hbase/TableName;
       4: getstatic     #52                 // Field org/apache/hadoop/hbase/client/RegionInfoBuilder.FIRST_META_REGIONINFO:Lorg/apache/hadoop/hbase/client/RegionInfo;
       7: invokeinterface #53,  1           // InterfaceMethod org/apache/hadoop/hbase/client/RegionInfo.getTable:()Lorg/apache/hadoop/hbase/TableName;
      12: invokevirtual #32                 // Method org/apache/hadoop/hbase/TableName.equals:(Ljava/lang/Object;)Z
      15: ireturn

  public boolean isSplit();
    Code:
       0: aload_0
       1: getfield      #24                 // Field split:Z
       4: ireturn

  public org.apache.hadoop.hbase.client.RegionInfoBuilder$MutableRegionInfo setSplit(boolean);
    Code:
       0: aload_0
       1: iload_1
       2: putfield      #24                 // Field split:Z
       5: aload_0
       6: areturn

  public boolean isOffline();
    Code:
       0: aload_0
       1: getfield      #23                 // Field offLine:Z
       4: ireturn

  public org.apache.hadoop.hbase.client.RegionInfoBuilder$MutableRegionInfo setOffline(boolean);
    Code:
       0: aload_0
       1: iload_1
       2: putfield      #23                 // Field offLine:Z
       5: aload_0
       6: areturn

  public boolean isSplitParent();
    Code:
       0: aload_0
       1: invokevirtual #54                 // Method isSplit:()Z
       4: ifne          9
       7: iconst_0
       8: ireturn
       9: aload_0
      10: invokevirtual #55                 // Method isOffline:()Z
      13: ifne          46
      16: invokestatic  #56                 // Method org/apache/hadoop/hbase/client/RegionInfoBuilder.access$100:()Lorg/slf4j/Logger;
      19: new           #43                 // class java/lang/StringBuilder
      22: dup
      23: invokespecial #44                 // Method java/lang/StringBuilder."<init>":()V
      26: ldc           #57                 // String Region is split but NOT offline:
      28: invokevirtual #46                 // Method java/lang/StringBuilder.append:(Ljava/lang/String;)Ljava/lang/StringBuilder;
      31: aload_0
      32: invokevirtual #58                 // Method getRegionNameAsString:()Ljava/lang/String;
      35: invokevirtual #46                 // Method java/lang/StringBuilder.append:(Ljava/lang/String;)Ljava/lang/StringBuilder;
      38: invokevirtual #49                 // Method java/lang/StringBuilder.toString:()Ljava/lang/String;
      41: invokeinterface #59,  2           // InterfaceMethod org/slf4j/Logger.warn:(Ljava/lang/String;)V
      46: iconst_1
      47: ireturn

  public int getReplicaId();
    Code:
       0: aload_0
       1: getfield      #29                 // Field replicaId:I
       4: ireturn

  public java.lang.String toString();
    Code:
       0: new           #43                 // class java/lang/StringBuilder
       3: dup
       4: invokespecial #44                 // Method java/lang/StringBuilder."<init>":()V
       7: ldc           #60                 // String {ENCODED =>
       9: invokevirtual #46                 // Method java/lang/StringBuilder.append:(Ljava/lang/String;)Ljava/lang/StringBuilder;
      12: aload_0
      13: invokevirtual #39                 // Method getEncodedName:()Ljava/lang/String;
      16: invokevirtual #46                 // Method java/lang/StringBuilder.append:(Ljava/lang/String;)Ljava/lang/StringBuilder;
      19: ldc           #61                 // String ,
      21: invokevirtual #46                 // Method java/lang/StringBuilder.append:(Ljava/lang/String;)Ljava/lang/StringBuilder;
      24: ldc           #63                 // String NAME
      26: invokevirtual #46                 // Method java/lang/StringBuilder.append:(Ljava/lang/String;)Ljava/lang/StringBuilder;
      29: ldc           #64                 // String  => '
      31: invokevirtual #46                 // Method java/lang/StringBuilder.append:(Ljava/lang/String;)Ljava/lang/StringBuilder;
      34: aload_0
      35: getfield      #33                 // Field regionName:[B
      38: invokestatic  #47                 // Method org/apache/hadoop/hbase/util/Bytes.toStringBinary:([B)Ljava/lang/String;
      41: invokevirtual #46                 // Method java/lang/StringBuilder.append:(Ljava/lang/String;)Ljava/lang/StringBuilder;
      44: ldc           #65                 // String ', STARTKEY => '
      46: invokevirtual #46                 // Method java/lang/StringBuilder.append:(Ljava/lang/String;)Ljava/lang/StringBuilder;
      49: aload_0
      50: getfield      #26                 // Field startKey:[B
      53: invokestatic  #47                 // Method org/apache/hadoop/hbase/util/Bytes.toStringBinary:([B)Ljava/lang/String;
      56: invokevirtual #46                 // Method java/lang/StringBuilder.append:(Ljava/lang/String;)Ljava/lang/StringBuilder;
      59: ldc           #66                 // String ', ENDKEY => '
      61: invokevirtual #46                 // Method java/lang/StringBuilder.append:(Ljava/lang/String;)Ljava/lang/StringBuilder;
      64: aload_0
      65: getfield      #27                 // Field endKey:[B
      68: invokestatic  #47                 // Method org/apache/hadoop/hbase/util/Bytes.toStringBinary:([B)Ljava/lang/String;
      71: invokevirtual #46                 // Method java/lang/StringBuilder.append:(Ljava/lang/String;)Ljava/lang/StringBuilder;
      74: ldc           #67                 // String '
      76: invokevirtual #46                 // Method java/lang/StringBuilder.append:(Ljava/lang/String;)Ljava/lang/StringBuilder;
      79: aload_0
      80: invokevirtual #55                 // Method isOffline:()Z
      83: ifeq          91
      86: ldc           #68                 // String , OFFLINE => true
      88: goto          93
      91: ldc           #69                 // String
      93: invokevirtual #46                 // Method java/lang/StringBuilder.append:(Ljava/lang/String;)Ljava/lang/StringBuilder;
      96: aload_0
      97: invokevirtual #54                 // Method isSplit:()Z
     100: ifeq          108
     103: ldc           #70                 // String , SPLIT => true
     105: goto          110
     108: ldc           #69                 // String
     110: invokevirtual #46                 // Method java/lang/StringBuilder.append:(Ljava/lang/String;)Ljava/lang/StringBuilder;
     113: aload_0
     114: getfield      #29                 // Field replicaId:I
     117: ifle          145
     120: new           #43                 // class java/lang/StringBuilder
     123: dup
     124: invokespecial #44                 // Method java/lang/StringBuilder."<init>":()V
     127: ldc           #71                 // String , REPLICA_ID =>
     129: invokevirtual #46                 // Method java/lang/StringBuilder.append:(Ljava/lang/String;)Ljava/lang/StringBuilder;
     132: aload_0
     133: getfield      #29                 // Field replicaId:I
     136: invokevirtual #72                 // Method java/lang/StringBuilder.append:(I)Ljava/lang/StringBuilder;
     139: invokevirtual #49                 // Method java/lang/StringBuilder.toString:()Ljava/lang/String;
     142: goto          147
     145: ldc           #69                 // String
     147: invokevirtual #46                 // Method java/lang/StringBuilder.append:(Ljava/lang/String;)Ljava/lang/StringBuilder;
     150: ldc           #73                 // String }
     152: invokevirtual #46                 // Method java/lang/StringBuilder.append:(Ljava/lang/String;)Ljava/lang/StringBuilder;
     155: invokevirtual #49                 // Method java/lang/StringBuilder.toString:()Ljava/lang/String;
     158: areturn

  public boolean equals(java.lang.Object);
    Code:
       0: aload_0
       1: aload_1
       2: if_acmpne     7
       5: iconst_1
       6: ireturn
       7: aload_1
       8: ifnonnull     13
      11: iconst_0
      12: ireturn
      13: aload_1
      14: instanceof    #74                 // class org/apache/hadoop/hbase/client/RegionInfo
      17: ifne          22
      20: iconst_0
      21: ireturn
      22: aload_0
      23: aload_1
      24: checkcast     #74                 // class org/apache/hadoop/hbase/client/RegionInfo
      27: invokevirtual #75                 // Method compareTo:(Lorg/apache/hadoop/hbase/client/RegionInfo;)I
      30: ifne          37
      33: iconst_1
      34: goto          38
      37: iconst_0
      38: ireturn

  public int hashCode();
    Code:
       0: aload_0
       1: getfield      #36                 // Field hashCode:I
       4: ireturn

  public int compareTo(org.apache.hadoop.hbase.client.RegionInfo);
    Code:
       0: getstatic     #76                 // Field org/apache/hadoop/hbase/client/RegionInfo.COMPARATOR:Ljava/util/Comparator;
       3: aload_0
       4: aload_1
       5: invokeinterface #77,  3           // InterfaceMethod java/util/Comparator.compare:(Ljava/lang/Object;Ljava/lang/Object;)I
      10: ireturn

  public int compareTo(java.lang.Object);
    Code:
       0: aload_0
       1: aload_1
       2: checkcast     #74                 // class org/apache/hadoop/hbase/client/RegionInfo
       5: invokevirtual #75                 // Method compareTo:(Lorg/apache/hadoop/hbase/client/RegionInfo;)I
       8: ireturn

  org.apache.hadoop.hbase.client.RegionInfoBuilder$MutableRegionInfo(long, org.apache.hadoop.hbase.TableName, int, org.apache.hadoop.hbase.client.RegionInfoBuilder$1);
    Code:
       0: aload_0
       1: lload_1
       2: aload_3
       3: iload         4
       5: invokespecial #2                  // Method "<init>":(JLorg/apache/hadoop/hbase/TableName;I)V
       8: return
}
