Compiled from "RegionPlacementMaintainer.java"
public class org.apache.hadoop.hbase.master.RegionPlacementMaintainer {
  public org.apache.hadoop.hbase.master.RegionPlacementMaintainer(org.apache.hadoop.conf.Configuration);
    Code:
       0: aload_0
       1: aload_1
       2: iconst_1
       3: iconst_1
       4: invokespecial #2                  // Method "<init>":(Lorg/apache/hadoop/conf/Configuration;ZZ)V
       7: return

  public org.apache.hadoop.hbase.master.RegionPlacementMaintainer(org.apache.hadoop.conf.Configuration, boolean, boolean);
    Code:
       0: aload_0
       1: invokespecial #3                  // Method java/lang/Object."<init>":()V
       4: aload_0
       5: aload_1
       6: putfield      #4                  // Field conf:Lorg/apache/hadoop/conf/Configuration;
       9: aload_0
      10: iload_2
      11: putfield      #5                  // Field enforceLocality:Z
      14: aload_0
      15: iload_3
      16: putfield      #6                  // Field enforceMinAssignmentMove:Z
      19: aload_0
      20: new           #7                  // class java/util/HashSet
      23: dup
      24: invokespecial #8                  // Method java/util/HashSet."<init>":()V
      27: putfield      #9                  // Field targetTableSet:Ljava/util/Set;
      30: aload_0
      31: new           #10                 // class org/apache/hadoop/hbase/master/RackManager
      34: dup
      35: aload_1
      36: invokespecial #11                 // Method org/apache/hadoop/hbase/master/RackManager."<init>":(Lorg/apache/hadoop/conf/Configuration;)V
      39: putfield      #12                 // Field rackManager:Lorg/apache/hadoop/hbase/master/RackManager;
      42: aload_0
      43: aload_0
      44: getfield      #4                  // Field conf:Lorg/apache/hadoop/conf/Configuration;
      47: invokestatic  #13                 // Method org/apache/hadoop/hbase/client/ConnectionFactory.createConnection:(Lorg/apache/hadoop/conf/Configuration;)Lorg/apache/hadoop/hbase/client/Connection;
      50: putfield      #14                 // Field connection:Lorg/apache/hadoop/hbase/client/Connection;
      53: goto          68
      56: astore        4
      58: new           #16                 // class java/lang/RuntimeException
      61: dup
      62: aload         4
      64: invokespecial #17                 // Method java/lang/RuntimeException."<init>":(Ljava/lang/Throwable;)V
      67: athrow
      68: return
    Exception table:
       from    to  target type
          42    53    56   Class java/io/IOException

  public void setTargetTableName(java.lang.String[]);
    Code:
       0: aload_1
       1: ifnull        45
       4: aload_1
       5: astore_2
       6: aload_2
       7: arraylength
       8: istore_3
       9: iconst_0
      10: istore        4
      12: iload         4
      14: iload_3
      15: if_icmpge     45
      18: aload_2
      19: iload         4
      21: aaload
      22: astore        5
      24: aload_0
      25: getfield      #9                  // Field targetTableSet:Ljava/util/Set;
      28: aload         5
      30: invokestatic  #22                 // Method org/apache/hadoop/hbase/TableName.valueOf:(Ljava/lang/String;)Lorg/apache/hadoop/hbase/TableName;
      33: invokeinterface #23,  2           // InterfaceMethod java/util/Set.add:(Ljava/lang/Object;)Z
      38: pop
      39: iinc          4, 1
      42: goto          12
      45: return

  public org.apache.hadoop.hbase.master.SnapshotOfRegionAssignmentFromMeta getRegionAssignmentSnapshot() throws java.io.IOException;
    Code:
       0: new           #24                 // class org/apache/hadoop/hbase/master/SnapshotOfRegionAssignmentFromMeta
       3: dup
       4: aload_0
       5: getfield      #4                  // Field conf:Lorg/apache/hadoop/conf/Configuration;
       8: invokestatic  #13                 // Method org/apache/hadoop/hbase/client/ConnectionFactory.createConnection:(Lorg/apache/hadoop/conf/Configuration;)Lorg/apache/hadoop/hbase/client/Connection;
      11: invokespecial #25                 // Method org/apache/hadoop/hbase/master/SnapshotOfRegionAssignmentFromMeta."<init>":(Lorg/apache/hadoop/hbase/client/Connection;)V
      14: astore_1
      15: aload_1
      16: invokevirtual #26                 // Method org/apache/hadoop/hbase/master/SnapshotOfRegionAssignmentFromMeta.initialize:()V
      19: aload_1
      20: areturn

  public java.util.List<org.apache.hadoop.hbase.master.AssignmentVerificationReport> verifyRegionPlacement(boolean) throws java.io.IOException;
    Code:
       0: getstatic     #27                 // Field java/lang/System.out:Ljava/io/PrintStream;
       3: ldc           #28                 // String Start to verify the region assignment and generate the verification report
       5: invokevirtual #29                 // Method java/io/PrintStream.println:(Ljava/lang/String;)V
       8: aload_0
       9: invokevirtual #30                 // Method getRegionAssignmentSnapshot:()Lorg/apache/hadoop/hbase/master/SnapshotOfRegionAssignmentFromMeta;
      12: astore_2
      13: aload_2
      14: invokevirtual #31                 // Method org/apache/hadoop/hbase/master/SnapshotOfRegionAssignmentFromMeta.getTableSet:()Ljava/util/Set;
      17: astore_3
      18: aconst_null
      19: astore        4
      21: aload_0
      22: getfield      #5                  // Field enforceLocality:Z
      25: iconst_1
      26: if_icmpne     38
      29: aload_0
      30: getfield      #4                  // Field conf:Lorg/apache/hadoop/conf/Configuration;
      33: invokestatic  #32                 // Method org/apache/hadoop/hbase/util/FSUtils.getRegionDegreeLocalityMappingFromFS:(Lorg/apache/hadoop/conf/Configuration;)Ljava/util/Map;
      36: astore        4
      38: new           #33                 // class java/util/ArrayList
      41: dup
      42: invokespecial #34                 // Method java/util/ArrayList."<init>":()V
      45: astore        5
      47: aload_3
      48: invokeinterface #35,  1           // InterfaceMethod java/util/Set.iterator:()Ljava/util/Iterator;
      53: astore        6
      55: aload         6
      57: invokeinterface #36,  1           // InterfaceMethod java/util/Iterator.hasNext:()Z
      62: ifeq          144
      65: aload         6
      67: invokeinterface #37,  1           // InterfaceMethod java/util/Iterator.next:()Ljava/lang/Object;
      72: checkcast     #38                 // class org/apache/hadoop/hbase/TableName
      75: astore        7
      77: aload_0
      78: getfield      #9                  // Field targetTableSet:Ljava/util/Set;
      81: invokeinterface #39,  1           // InterfaceMethod java/util/Set.isEmpty:()Z
      86: ifne          106
      89: aload_0
      90: getfield      #9                  // Field targetTableSet:Ljava/util/Set;
      93: aload         7
      95: invokeinterface #40,  2           // InterfaceMethod java/util/Set.contains:(Ljava/lang/Object;)Z
     100: ifne          106
     103: goto          55
     106: new           #41                 // class org/apache/hadoop/hbase/master/AssignmentVerificationReport
     109: dup
     110: invokespecial #42                 // Method org/apache/hadoop/hbase/master/AssignmentVerificationReport."<init>":()V
     113: astore        8
     115: aload         8
     117: aload         7
     119: aload_2
     120: aload         4
     122: invokevirtual #43                 // Method org/apache/hadoop/hbase/master/AssignmentVerificationReport.fillUp:(Lorg/apache/hadoop/hbase/TableName;Lorg/apache/hadoop/hbase/master/SnapshotOfRegionAssignmentFromMeta;Ljava/util/Map;)V
     125: aload         8
     127: iload_1
     128: invokevirtual #44                 // Method org/apache/hadoop/hbase/master/AssignmentVerificationReport.print:(Z)V
     131: aload         5
     133: aload         8
     135: invokeinterface #45,  2           // InterfaceMethod java/util/List.add:(Ljava/lang/Object;)Z
     140: pop
     141: goto          55
     144: aload         5
     146: areturn

  public org.apache.hadoop.hbase.favored.FavoredNodesPlan getNewAssignmentPlan() throws java.io.IOException;
    Code:
       0: aload_0
       1: invokevirtual #30                 // Method getRegionAssignmentSnapshot:()Lorg/apache/hadoop/hbase/master/SnapshotOfRegionAssignmentFromMeta;
       4: astore_1
       5: aconst_null
       6: astore_2
       7: aload_0
       8: getfield      #5                  // Field enforceLocality:Z
      11: ifeq          22
      14: aload_0
      15: getfield      #4                  // Field conf:Lorg/apache/hadoop/conf/Configuration;
      18: invokestatic  #32                 // Method org/apache/hadoop/hbase/util/FSUtils.getRegionDegreeLocalityMappingFromFS:(Lorg/apache/hadoop/conf/Configuration;)Ljava/util/Map;
      21: astore_2
      22: new           #115                // class org/apache/hadoop/hbase/favored/FavoredNodesPlan
      25: dup
      26: invokespecial #116                // Method org/apache/hadoop/hbase/favored/FavoredNodesPlan."<init>":()V
      29: astore_3
      30: aload_1
      31: invokevirtual #46                 // Method org/apache/hadoop/hbase/master/SnapshotOfRegionAssignmentFromMeta.getTableToRegionMap:()Ljava/util/Map;
      34: astore        4
      36: getstatic     #61                 // Field LOG:Lorg/slf4j/Logger;
      39: new           #62                 // class java/lang/StringBuilder
      42: dup
      43: invokespecial #63                 // Method java/lang/StringBuilder."<init>":()V
      46: ldc           #117                // String Start to generate the new assignment plan for the
      48: invokevirtual #65                 // Method java/lang/StringBuilder.append:(Ljava/lang/String;)Ljava/lang/StringBuilder;
      51: aload         4
      53: invokeinterface #56,  1           // InterfaceMethod java/util/Map.keySet:()Ljava/util/Set;
      58: invokeinterface #118,  1          // InterfaceMethod java/util/Set.size:()I
      63: invokevirtual #66                 // Method java/lang/StringBuilder.append:(I)Ljava/lang/StringBuilder;
      66: ldc           #119                // String  tables
      68: invokevirtual #65                 // Method java/lang/StringBuilder.append:(Ljava/lang/String;)Ljava/lang/StringBuilder;
      71: invokevirtual #71                 // Method java/lang/StringBuilder.toString:()Ljava/lang/String;
      74: invokeinterface #72,  2           // InterfaceMethod org/slf4j/Logger.info:(Ljava/lang/String;)V
      79: aload         4
      81: invokeinterface #56,  1           // InterfaceMethod java/util/Map.keySet:()Ljava/util/Set;
      86: invokeinterface #35,  1           // InterfaceMethod java/util/Set.iterator:()Ljava/util/Iterator;
      91: astore        5
      93: aload         5
      95: invokeinterface #36,  1           // InterfaceMethod java/util/Iterator.hasNext:()Z
     100: ifeq          202
     103: aload         5
     105: invokeinterface #37,  1           // InterfaceMethod java/util/Iterator.next:()Ljava/lang/Object;
     110: checkcast     #38                 // class org/apache/hadoop/hbase/TableName
     113: astore        6
     115: aload_0
     116: getfield      #9                  // Field targetTableSet:Ljava/util/Set;
     119: invokeinterface #39,  1           // InterfaceMethod java/util/Set.isEmpty:()Z
     124: ifne          144
     127: aload_0
     128: getfield      #9                  // Field targetTableSet:Ljava/util/Set;
     131: aload         6
     133: invokeinterface #40,  2           // InterfaceMethod java/util/Set.contains:(Ljava/lang/Object;)Z
     138: ifne          144
     141: goto          93
     144: aload_0
     145: aload         6
     147: aload_1
     148: aload_2
     149: aload_3
     150: getstatic     #120                // Field USE_MUNKRES_FOR_PLACING_SECONDARY_AND_TERTIARY:Z
     153: invokespecial #121                // Method genAssignmentPlan:(Lorg/apache/hadoop/hbase/TableName;Lorg/apache/hadoop/hbase/master/SnapshotOfRegionAssignmentFromMeta;Ljava/util/Map;Lorg/apache/hadoop/hbase/favored/FavoredNodesPlan;Z)V
     156: goto          199
     159: astore        7
     161: getstatic     #61                 // Field LOG:Lorg/slf4j/Logger;
     164: new           #62                 // class java/lang/StringBuilder
     167: dup
     168: invokespecial #63                 // Method java/lang/StringBuilder."<init>":()V
     171: ldc           #123                // String Get some exceptions for placing primary region serverfor table
     173: invokevirtual #65                 // Method java/lang/StringBuilder.append:(Ljava/lang/String;)Ljava/lang/StringBuilder;
     176: aload         6
     178: invokevirtual #68                 // Method java/lang/StringBuilder.append:(Ljava/lang/Object;)Ljava/lang/StringBuilder;
     181: ldc           #124                // String  because
     183: invokevirtual #65                 // Method java/lang/StringBuilder.append:(Ljava/lang/String;)Ljava/lang/StringBuilder;
     186: aload         7
     188: invokevirtual #68                 // Method java/lang/StringBuilder.append:(Ljava/lang/Object;)Ljava/lang/StringBuilder;
     191: invokevirtual #71                 // Method java/lang/StringBuilder.toString:()Ljava/lang/String;
     194: invokeinterface #125,  2          // InterfaceMethod org/slf4j/Logger.error:(Ljava/lang/String;)V
     199: goto          93
     202: getstatic     #61                 // Field LOG:Lorg/slf4j/Logger;
     205: new           #62                 // class java/lang/StringBuilder
     208: dup
     209: invokespecial #63                 // Method java/lang/StringBuilder."<init>":()V
     212: ldc           #126                // String Finish to generate the new assignment plan for the
     214: invokevirtual #65                 // Method java/lang/StringBuilder.append:(Ljava/lang/String;)Ljava/lang/StringBuilder;
     217: aload         4
     219: invokeinterface #56,  1           // InterfaceMethod java/util/Map.keySet:()Ljava/util/Set;
     224: invokeinterface #118,  1          // InterfaceMethod java/util/Set.size:()I
     229: invokevirtual #66                 // Method java/lang/StringBuilder.append:(I)Ljava/lang/StringBuilder;
     232: ldc           #119                // String  tables
     234: invokevirtual #65                 // Method java/lang/StringBuilder.append:(Ljava/lang/String;)Ljava/lang/StringBuilder;
     237: invokevirtual #71                 // Method java/lang/StringBuilder.toString:()Ljava/lang/String;
     240: invokeinterface #72,  2           // InterfaceMethod org/slf4j/Logger.info:(Ljava/lang/String;)V
     245: aload_3
     246: areturn
    Exception table:
       from    to  target type
         115   141   159   Class java/lang/Exception
         144   156   159   Class java/lang/Exception

  public static void printAssignmentPlan(org.apache.hadoop.hbase.favored.FavoredNodesPlan);
    Code:
       0: aload_0
       1: ifnonnull     5
       4: return
       5: getstatic     #61                 // Field LOG:Lorg/slf4j/Logger;
       8: ldc           #127                // String ========== Start to print the assignment plan ================
      10: invokeinterface #72,  2           // InterfaceMethod org/slf4j/Logger.info:(Ljava/lang/String;)V
      15: new           #128                // class java/util/TreeMap
      18: dup
      19: aload_0
      20: invokevirtual #129                // Method org/apache/hadoop/hbase/favored/FavoredNodesPlan.getAssignmentMap:()Ljava/util/Map;
      23: invokespecial #130                // Method java/util/TreeMap."<init>":(Ljava/util/Map;)V
      26: astore_1
      27: aload_1
      28: invokeinterface #131,  1          // InterfaceMethod java/util/Map.entrySet:()Ljava/util/Set;
      33: invokeinterface #35,  1           // InterfaceMethod java/util/Set.iterator:()Ljava/util/Iterator;
      38: astore_2
      39: aload_2
      40: invokeinterface #36,  1           // InterfaceMethod java/util/Iterator.hasNext:()Z
      45: ifeq          142
      48: aload_2
      49: invokeinterface #37,  1           // InterfaceMethod java/util/Iterator.next:()Ljava/lang/Object;
      54: checkcast     #132                // class java/util/Map$Entry
      57: astore_3
      58: aload_3
      59: invokeinterface #133,  1          // InterfaceMethod java/util/Map$Entry.getValue:()Ljava/lang/Object;
      64: checkcast     #48                 // class java/util/List
      67: invokestatic  #134                // Method org/apache/hadoop/hbase/favored/FavoredNodeAssignmentHelper.getFavoredNodesAsString:(Ljava/util/List;)Ljava/lang/String;
      70: astore        4
      72: aload_3
      73: invokeinterface #135,  1          // InterfaceMethod java/util/Map$Entry.getKey:()Ljava/lang/Object;
      78: checkcast     #136                // class java/lang/String
      81: astore        5
      83: getstatic     #61                 // Field LOG:Lorg/slf4j/Logger;
      86: new           #62                 // class java/lang/StringBuilder
      89: dup
      90: invokespecial #63                 // Method java/lang/StringBuilder."<init>":()V
      93: ldc           #137                // String Region:
      95: invokevirtual #65                 // Method java/lang/StringBuilder.append:(Ljava/lang/String;)Ljava/lang/StringBuilder;
      98: aload         5
     100: invokevirtual #65                 // Method java/lang/StringBuilder.append:(Ljava/lang/String;)Ljava/lang/StringBuilder;
     103: invokevirtual #71                 // Method java/lang/StringBuilder.toString:()Ljava/lang/String;
     106: invokeinterface #72,  2           // InterfaceMethod org/slf4j/Logger.info:(Ljava/lang/String;)V
     111: getstatic     #61                 // Field LOG:Lorg/slf4j/Logger;
     114: new           #62                 // class java/lang/StringBuilder
     117: dup
     118: invokespecial #63                 // Method java/lang/StringBuilder."<init>":()V
     121: ldc           #138                // String Its favored nodes:
     123: invokevirtual #65                 // Method java/lang/StringBuilder.append:(Ljava/lang/String;)Ljava/lang/StringBuilder;
     126: aload         4
     128: invokevirtual #65                 // Method java/lang/StringBuilder.append:(Ljava/lang/String;)Ljava/lang/StringBuilder;
     131: invokevirtual #71                 // Method java/lang/StringBuilder.toString:()Ljava/lang/String;
     134: invokeinterface #72,  2           // InterfaceMethod org/slf4j/Logger.info:(Ljava/lang/String;)V
     139: goto          39
     142: getstatic     #61                 // Field LOG:Lorg/slf4j/Logger;
     145: ldc           #139                // String ========== Finish to print the assignment plan ================
     147: invokeinterface #72,  2           // InterfaceMethod org/slf4j/Logger.info:(Ljava/lang/String;)V
     152: return

  public void updateAssignmentPlanToMeta(org.apache.hadoop.hbase.favored.FavoredNodesPlan) throws java.io.IOException;
    Code:
       0: getstatic     #61                 // Field LOG:Lorg/slf4j/Logger;
       3: ldc           #140                // String Start to update the hbase:meta with the new assignment plan
       5: invokeinterface #72,  2           // InterfaceMethod org/slf4j/Logger.info:(Ljava/lang/String;)V
      10: aload_1
      11: invokevirtual #129                // Method org/apache/hadoop/hbase/favored/FavoredNodesPlan.getAssignmentMap:()Ljava/util/Map;
      14: astore_2
      15: new           #82                 // class java/util/HashMap
      18: dup
      19: aload_2
      20: invokeinterface #141,  1          // InterfaceMethod java/util/Map.size:()I
      25: invokespecial #142                // Method java/util/HashMap."<init>":(I)V
      28: astore_3
      29: aload_0
      30: invokevirtual #30                 // Method getRegionAssignmentSnapshot:()Lorg/apache/hadoop/hbase/master/SnapshotOfRegionAssignmentFromMeta;
      33: invokevirtual #143                // Method org/apache/hadoop/hbase/master/SnapshotOfRegionAssignmentFromMeta.getRegionNameToRegionInfoMap:()Ljava/util/Map;
      36: astore        4
      38: aload_2
      39: invokeinterface #131,  1          // InterfaceMethod java/util/Map.entrySet:()Ljava/util/Set;
      44: invokeinterface #35,  1           // InterfaceMethod java/util/Set.iterator:()Ljava/util/Iterator;
      49: astore        5
      51: aload         5
      53: invokeinterface #36,  1           // InterfaceMethod java/util/Iterator.hasNext:()Z
      58: ifeq          104
      61: aload         5
      63: invokeinterface #37,  1           // InterfaceMethod java/util/Iterator.next:()Ljava/lang/Object;
      68: checkcast     #132                // class java/util/Map$Entry
      71: astore        6
      73: aload_3
      74: aload         4
      76: aload         6
      78: invokeinterface #135,  1          // InterfaceMethod java/util/Map$Entry.getKey:()Ljava/lang/Object;
      83: invokeinterface #47,  2           // InterfaceMethod java/util/Map.get:(Ljava/lang/Object;)Ljava/lang/Object;
      88: aload         6
      90: invokeinterface #133,  1          // InterfaceMethod java/util/Map$Entry.getValue:()Ljava/lang/Object;
      95: invokeinterface #85,  3           // InterfaceMethod java/util/Map.put:(Ljava/lang/Object;Ljava/lang/Object;)Ljava/lang/Object;
     100: pop
     101: goto          51
     104: aload_3
     105: aload_0
     106: getfield      #4                  // Field conf:Lorg/apache/hadoop/conf/Configuration;
     109: invokestatic  #144                // Method org/apache/hadoop/hbase/favored/FavoredNodeAssignmentHelper.updateMetaWithFavoredNodesInfo:(Ljava/util/Map;Lorg/apache/hadoop/conf/Configuration;)V
     112: getstatic     #61                 // Field LOG:Lorg/slf4j/Logger;
     115: ldc           #145                // String Updated the hbase:meta with the new assignment plan
     117: invokeinterface #72,  2           // InterfaceMethod org/slf4j/Logger.info:(Ljava/lang/String;)V
     122: goto          156
     125: astore_2
     126: getstatic     #61                 // Field LOG:Lorg/slf4j/Logger;
     129: new           #62                 // class java/lang/StringBuilder
     132: dup
     133: invokespecial #63                 // Method java/lang/StringBuilder."<init>":()V
     136: ldc           #146                // String Failed to update hbase:meta with the new assignmentplan because
     138: invokevirtual #65                 // Method java/lang/StringBuilder.append:(Ljava/lang/String;)Ljava/lang/StringBuilder;
     141: aload_2
     142: invokevirtual #147                // Method java/lang/Exception.getMessage:()Ljava/lang/String;
     145: invokevirtual #65                 // Method java/lang/StringBuilder.append:(Ljava/lang/String;)Ljava/lang/StringBuilder;
     148: invokevirtual #71                 // Method java/lang/StringBuilder.toString:()Ljava/lang/String;
     151: invokeinterface #125,  2          // InterfaceMethod org/slf4j/Logger.error:(Ljava/lang/String;)V
     156: return
    Exception table:
       from    to  target type
           0   122   125   Class java/lang/Exception

  public void updateAssignmentPlan(org.apache.hadoop.hbase.favored.FavoredNodesPlan) throws java.io.IOException;
    Code:
       0: getstatic     #61                 // Field LOG:Lorg/slf4j/Logger;
       3: ldc           #172                // String Start to update the new assignment plan for the hbase:meta table and the region servers
       5: invokeinterface #72,  2           // InterfaceMethod org/slf4j/Logger.info:(Ljava/lang/String;)V
      10: aload_0
      11: aload_1
      12: invokevirtual #173                // Method updateAssignmentPlanToMeta:(Lorg/apache/hadoop/hbase/favored/FavoredNodesPlan;)V
      15: aload_0
      16: aload_1
      17: invokespecial #174                // Method updateAssignmentPlanToRegionServers:(Lorg/apache/hadoop/hbase/favored/FavoredNodesPlan;)V
      20: getstatic     #61                 // Field LOG:Lorg/slf4j/Logger;
      23: ldc           #175                // String Finish to update the new assignment plan for the hbase:meta table and the region servers
      25: invokeinterface #72,  2           // InterfaceMethod org/slf4j/Logger.info:(Ljava/lang/String;)V
      30: return

  public java.util.Map<org.apache.hadoop.hbase.TableName, java.lang.Integer> getRegionsMovement(org.apache.hadoop.hbase.favored.FavoredNodesPlan) throws java.io.IOException;
    Code:
       0: new           #82                 // class java/util/HashMap
       3: dup
       4: invokespecial #83                 // Method java/util/HashMap."<init>":()V
       7: astore_2
       8: aload_0
       9: invokevirtual #30                 // Method getRegionAssignmentSnapshot:()Lorg/apache/hadoop/hbase/master/SnapshotOfRegionAssignmentFromMeta;
      12: astore_3
      13: aload_3
      14: invokevirtual #46                 // Method org/apache/hadoop/hbase/master/SnapshotOfRegionAssignmentFromMeta.getTableToRegionMap:()Ljava/util/Map;
      17: astore        4
      19: aload_3
      20: invokevirtual #176                // Method org/apache/hadoop/hbase/master/SnapshotOfRegionAssignmentFromMeta.getExistingAssignmentPlan:()Lorg/apache/hadoop/hbase/favored/FavoredNodesPlan;
      23: astore        5
      25: aload_3
      26: invokevirtual #31                 // Method org/apache/hadoop/hbase/master/SnapshotOfRegionAssignmentFromMeta.getTableSet:()Ljava/util/Set;
      29: astore        6
      31: aload         6
      33: invokeinterface #35,  1           // InterfaceMethod java/util/Set.iterator:()Ljava/util/Iterator;
      38: astore        7
      40: aload         7
      42: invokeinterface #36,  1           // InterfaceMethod java/util/Iterator.hasNext:()Z
      47: ifeq          225
      50: aload         7
      52: invokeinterface #37,  1           // InterfaceMethod java/util/Iterator.next:()Ljava/lang/Object;
      57: checkcast     #38                 // class org/apache/hadoop/hbase/TableName
      60: astore        8
      62: iconst_0
      63: istore        9
      65: aload_0
      66: getfield      #9                  // Field targetTableSet:Ljava/util/Set;
      69: invokeinterface #39,  1           // InterfaceMethod java/util/Set.isEmpty:()Z
      74: ifne          94
      77: aload_0
      78: getfield      #9                  // Field targetTableSet:Ljava/util/Set;
      81: aload         8
      83: invokeinterface #40,  2           // InterfaceMethod java/util/Set.contains:(Ljava/lang/Object;)Z
      88: ifne          94
      91: goto          40
      94: aload         4
      96: aload         8
      98: invokeinterface #47,  2           // InterfaceMethod java/util/Map.get:(Ljava/lang/Object;)Ljava/lang/Object;
     103: checkcast     #48                 // class java/util/List
     106: astore        10
     108: aload         10
     110: invokeinterface #150,  1          // InterfaceMethod java/util/List.iterator:()Ljava/util/Iterator;
     115: astore        11
     117: aload         11
     119: invokeinterface #36,  1           // InterfaceMethod java/util/Iterator.hasNext:()Z
     124: ifeq          208
     127: aload         11
     129: invokeinterface #37,  1           // InterfaceMethod java/util/Iterator.next:()Ljava/lang/Object;
     134: checkcast     #76                 // class org/apache/hadoop/hbase/client/RegionInfo
     137: astore        12
     139: aload         5
     141: aload         12
     143: invokevirtual #151                // Method org/apache/hadoop/hbase/favored/FavoredNodesPlan.getFavoredNodes:(Lorg/apache/hadoop/hbase/client/RegionInfo;)Ljava/util/List;
     146: astore        13
     148: aload_1
     149: aload         12
     151: invokevirtual #151                // Method org/apache/hadoop/hbase/favored/FavoredNodesPlan.getFavoredNodes:(Lorg/apache/hadoop/hbase/client/RegionInfo;)Ljava/util/List;
     154: astore        14
     156: aload         13
     158: ifnull        205
     161: aload         14
     163: ifnull        205
     166: aload         13
     168: iconst_0
     169: invokeinterface #75,  2           // InterfaceMethod java/util/List.get:(I)Ljava/lang/Object;
     174: checkcast     #79                 // class org/apache/hadoop/hbase/ServerName
     177: astore        15
     179: aload         14
     181: iconst_0
     182: invokeinterface #75,  2           // InterfaceMethod java/util/List.get:(I)Ljava/lang/Object;
     187: checkcast     #79                 // class org/apache/hadoop/hbase/ServerName
     190: astore        16
     192: aload         15
     194: aload         16
     196: invokevirtual #177                // Method org/apache/hadoop/hbase/ServerName.compareTo:(Lorg/apache/hadoop/hbase/ServerName;)I
     199: ifeq          205
     202: iinc          9, 1
     205: goto          117
     208: aload_2
     209: aload         8
     211: iload         9
     213: invokestatic  #178                // Method java/lang/Integer.valueOf:(I)Ljava/lang/Integer;
     216: invokeinterface #85,  3           // InterfaceMethod java/util/Map.put:(Ljava/lang/Object;Ljava/lang/Object;)Ljava/lang/Object;
     221: pop
     222: goto          40
     225: aload_2
     226: areturn

  public void checkDifferencesWithOldPlan(java.util.Map<org.apache.hadoop.hbase.TableName, java.lang.Integer>, java.util.Map<java.lang.String, java.util.Map<java.lang.String, java.lang.Float>>, org.apache.hadoop.hbase.favored.FavoredNodesPlan) throws java.io.IOException;
    Code:
       0: aload_0
       1: invokevirtual #30                 // Method getRegionAssignmentSnapshot:()Lorg/apache/hadoop/hbase/master/SnapshotOfRegionAssignmentFromMeta;
       4: astore        4
       6: aload         4
       8: invokevirtual #176                // Method org/apache/hadoop/hbase/master/SnapshotOfRegionAssignmentFromMeta.getExistingAssignmentPlan:()Lorg/apache/hadoop/hbase/favored/FavoredNodesPlan;
      11: astore        5
      13: aload         4
      15: invokevirtual #31                 // Method org/apache/hadoop/hbase/master/SnapshotOfRegionAssignmentFromMeta.getTableSet:()Ljava/util/Set;
      18: astore        6
      20: aload         4
      22: invokevirtual #46                 // Method org/apache/hadoop/hbase/master/SnapshotOfRegionAssignmentFromMeta.getTableToRegionMap:()Ljava/util/Map;
      25: astore        7
      27: aload         6
      29: invokeinterface #35,  1           // InterfaceMethod java/util/Set.iterator:()Ljava/util/Iterator;
      34: astore        8
      36: aload         8
      38: invokeinterface #36,  1           // InterfaceMethod java/util/Iterator.hasNext:()Z
      43: ifeq          710
      46: aload         8
      48: invokeinterface #37,  1           // InterfaceMethod java/util/Iterator.next:()Ljava/lang/Object;
      53: checkcast     #38                 // class org/apache/hadoop/hbase/TableName
      56: astore        9
      58: iconst_3
      59: newarray       float
      61: astore        10
      63: iconst_3
      64: newarray       float
      66: astore        11
      68: aload_0
      69: getfield      #9                  // Field targetTableSet:Ljava/util/Set;
      72: invokeinterface #39,  1           // InterfaceMethod java/util/Set.isEmpty:()Z
      77: ifne          97
      80: aload_0
      81: getfield      #9                  // Field targetTableSet:Ljava/util/Set;
      84: aload         9
      86: invokeinterface #40,  2           // InterfaceMethod java/util/Set.contains:(Ljava/lang/Object;)Z
      91: ifne          97
      94: goto          36
      97: aload         7
      99: aload         9
     101: invokeinterface #47,  2           // InterfaceMethod java/util/Map.get:(Ljava/lang/Object;)Ljava/lang/Object;
     106: checkcast     #48                 // class java/util/List
     109: astore        12
     111: getstatic     #27                 // Field java/lang/System.out:Ljava/io/PrintStream;
     114: ldc           #179                // String ==================================================
     116: invokevirtual #29                 // Method java/io/PrintStream.println:(Ljava/lang/String;)V
     119: getstatic     #27                 // Field java/lang/System.out:Ljava/io/PrintStream;
     122: new           #62                 // class java/lang/StringBuilder
     125: dup
     126: invokespecial #63                 // Method java/lang/StringBuilder."<init>":()V
     129: ldc           #180                // String Assignment Plan Projection Report For Table:
     131: invokevirtual #65                 // Method java/lang/StringBuilder.append:(Ljava/lang/String;)Ljava/lang/StringBuilder;
     134: aload         9
     136: invokevirtual #68                 // Method java/lang/StringBuilder.append:(Ljava/lang/Object;)Ljava/lang/StringBuilder;
     139: invokevirtual #71                 // Method java/lang/StringBuilder.toString:()Ljava/lang/String;
     142: invokevirtual #29                 // Method java/io/PrintStream.println:(Ljava/lang/String;)V
     145: getstatic     #27                 // Field java/lang/System.out:Ljava/io/PrintStream;
     148: new           #62                 // class java/lang/StringBuilder
     151: dup
     152: invokespecial #63                 // Method java/lang/StringBuilder."<init>":()V
     155: ldc           #181                // String \t Total regions:
     157: invokevirtual #65                 // Method java/lang/StringBuilder.append:(Ljava/lang/String;)Ljava/lang/StringBuilder;
     160: aload         12
     162: invokeinterface #49,  1           // InterfaceMethod java/util/List.size:()I
     167: invokevirtual #66                 // Method java/lang/StringBuilder.append:(I)Ljava/lang/StringBuilder;
     170: invokevirtual #71                 // Method java/lang/StringBuilder.toString:()Ljava/lang/String;
     173: invokevirtual #29                 // Method java/io/PrintStream.println:(Ljava/lang/String;)V
     176: getstatic     #27                 // Field java/lang/System.out:Ljava/io/PrintStream;
     179: new           #62                 // class java/lang/StringBuilder
     182: dup
     183: invokespecial #63                 // Method java/lang/StringBuilder."<init>":()V
     186: ldc           #182                // String \t
     188: invokevirtual #65                 // Method java/lang/StringBuilder.append:(Ljava/lang/String;)Ljava/lang/StringBuilder;
     191: aload_1
     192: aload         9
     194: invokeinterface #47,  2           // InterfaceMethod java/util/Map.get:(Ljava/lang/Object;)Ljava/lang/Object;
     199: invokevirtual #68                 // Method java/lang/StringBuilder.append:(Ljava/lang/Object;)Ljava/lang/StringBuilder;
     202: ldc           #183                // String  primaries will move due to their primary has changed
     204: invokevirtual #65                 // Method java/lang/StringBuilder.append:(Ljava/lang/String;)Ljava/lang/StringBuilder;
     207: invokevirtual #71                 // Method java/lang/StringBuilder.toString:()Ljava/lang/String;
     210: invokevirtual #29                 // Method java/io/PrintStream.println:(Ljava/lang/String;)V
     213: aload         12
     215: invokeinterface #150,  1          // InterfaceMethod java/util/List.iterator:()Ljava/util/Iterator;
     220: astore        13
     222: aload         13
     224: invokeinterface #36,  1           // InterfaceMethod java/util/Iterator.hasNext:()Z
     229: ifeq          472
     232: aload         13
     234: invokeinterface #37,  1           // InterfaceMethod java/util/Iterator.next:()Ljava/lang/Object;
     239: checkcast     #76                 // class org/apache/hadoop/hbase/client/RegionInfo
     242: astore        14
     244: aload_2
     245: aload         14
     247: invokeinterface #77,  1           // InterfaceMethod org/apache/hadoop/hbase/client/RegionInfo.getEncodedName:()Ljava/lang/String;
     252: invokeinterface #47,  2           // InterfaceMethod java/util/Map.get:(Ljava/lang/Object;)Ljava/lang/Object;
     257: checkcast     #78                 // class java/util/Map
     260: astore        15
     262: aload         15
     264: ifnonnull     270
     267: goto          222
     270: aload         5
     272: aload         14
     274: invokevirtual #151                // Method org/apache/hadoop/hbase/favored/FavoredNodesPlan.getFavoredNodes:(Lorg/apache/hadoop/hbase/client/RegionInfo;)Ljava/util/List;
     277: astore        16
     279: aload_3
     280: aload         14
     282: invokevirtual #151                // Method org/apache/hadoop/hbase/favored/FavoredNodesPlan.getFavoredNodes:(Lorg/apache/hadoop/hbase/client/RegionInfo;)Ljava/util/List;
     285: astore        17
     287: aload         17
     289: ifnull        469
     292: aload         16
     294: ifnull        469
     297: iconst_0
     298: istore        18
     300: invokestatic  #184                // Method org/apache/hadoop/hbase/favored/FavoredNodesPlan$Position.values:()[Lorg/apache/hadoop/hbase/favored/FavoredNodesPlan$Position;
     303: astore        19
     305: aload         19
     307: arraylength
     308: istore        20
     310: iconst_0
     311: istore        21
     313: iload         21
     315: iload         20
     317: if_icmpge     469
     320: aload         19
     322: iload         21
     324: aaload
     325: astore        22
     327: aload         17
     329: aload         22
     331: invokevirtual #185                // Method org/apache/hadoop/hbase/favored/FavoredNodesPlan$Position.ordinal:()I
     334: invokeinterface #75,  2           // InterfaceMethod java/util/List.get:(I)Ljava/lang/Object;
     339: checkcast     #79                 // class org/apache/hadoop/hbase/ServerName
     342: astore        23
     344: aload         16
     346: aload         22
     348: invokevirtual #185                // Method org/apache/hadoop/hbase/favored/FavoredNodesPlan$Position.ordinal:()I
     351: invokeinterface #75,  2           // InterfaceMethod java/util/List.get:(I)Ljava/lang/Object;
     356: checkcast     #79                 // class org/apache/hadoop/hbase/ServerName
     359: astore        24
     361: fconst_0
     362: invokestatic  #86                 // Method java/lang/Float.valueOf:(F)Ljava/lang/Float;
     365: astore        25
     367: aload         16
     369: ifnull        413
     372: aload         15
     374: aload         24
     376: invokevirtual #80                 // Method org/apache/hadoop/hbase/ServerName.getHostname:()Ljava/lang/String;
     379: invokeinterface #47,  2           // InterfaceMethod java/util/Map.get:(Ljava/lang/Object;)Ljava/lang/Object;
     384: checkcast     #1                  // class java/lang/Float
     387: astore        25
     389: aload         25
     391: ifnonnull     400
     394: fconst_0
     395: invokestatic  #86                 // Method java/lang/Float.valueOf:(F)Ljava/lang/Float;
     398: astore        25
     400: aload         11
     402: iload         18
     404: dup2
     405: faload
     406: aload         25
     408: invokevirtual #81                 // Method java/lang/Float.floatValue:()F
     411: fadd
     412: fastore
     413: aload         15
     415: aload         23
     417: invokevirtual #80                 // Method org/apache/hadoop/hbase/ServerName.getHostname:()Ljava/lang/String;
     420: invokeinterface #47,  2           // InterfaceMethod java/util/Map.get:(Ljava/lang/Object;)Ljava/lang/Object;
     425: checkcast     #1                  // class java/lang/Float
     428: astore        26
     430: aload         26
     432: ifnonnull     441
     435: fconst_0
     436: invokestatic  #86                 // Method java/lang/Float.valueOf:(F)Ljava/lang/Float;
     439: astore        26
     441: aload         10
     443: iload         18
     445: dup2
     446: faload
     447: aload         26
     449: invokevirtual #81                 // Method java/lang/Float.floatValue:()F
     452: aload         25
     454: invokevirtual #81                 // Method java/lang/Float.floatValue:()F
     457: fsub
     458: fadd
     459: fastore
     460: iinc          18, 1
     463: iinc          21, 1
     466: goto          313
     469: goto          222
     472: new           #186                // class java/text/DecimalFormat
     475: dup
     476: ldc           #187                // String #.##
     478: invokespecial #188                // Method java/text/DecimalFormat."<init>":(Ljava/lang/String;)V
     481: astore        13
     483: iconst_0
     484: istore        14
     486: iload         14
     488: aload         10
     490: arraylength
     491: if_icmpge     657
     494: getstatic     #27                 // Field java/lang/System.out:Ljava/io/PrintStream;
     497: ldc           #189                // String \t\t Baseline locality for
     499: invokevirtual #190                // Method java/io/PrintStream.print:(Ljava/lang/String;)V
     502: iload         14
     504: ifne          518
     507: getstatic     #27                 // Field java/lang/System.out:Ljava/io/PrintStream;
     510: ldc           #191                // String primary
     512: invokevirtual #190                // Method java/io/PrintStream.print:(Ljava/lang/String;)V
     515: goto          549
     518: iload         14
     520: iconst_1
     521: if_icmpne     535
     524: getstatic     #27                 // Field java/lang/System.out:Ljava/io/PrintStream;
     527: ldc           #192                // String secondary
     529: invokevirtual #190                // Method java/io/PrintStream.print:(Ljava/lang/String;)V
     532: goto          549
     535: iload         14
     537: iconst_2
     538: if_icmpne     549
     541: getstatic     #27                 // Field java/lang/System.out:Ljava/io/PrintStream;
     544: ldc           #193                // String tertiary
     546: invokevirtual #190                // Method java/io/PrintStream.print:(Ljava/lang/String;)V
     549: getstatic     #27                 // Field java/lang/System.out:Ljava/io/PrintStream;
     552: new           #62                 // class java/lang/StringBuilder
     555: dup
     556: invokespecial #63                 // Method java/lang/StringBuilder."<init>":()V
     559: aload         13
     561: ldc           #194                // float 100.0f
     563: aload         11
     565: iload         14
     567: faload
     568: fmul
     569: aload         12
     571: invokeinterface #49,  1           // InterfaceMethod java/util/List.size:()I
     576: i2f
     577: fdiv
     578: f2d
     579: invokevirtual #195                // Method java/text/DecimalFormat.format:(D)Ljava/lang/String;
     582: invokevirtual #65                 // Method java/lang/StringBuilder.append:(Ljava/lang/String;)Ljava/lang/StringBuilder;
     585: ldc           #196                // String %
     587: invokevirtual #65                 // Method java/lang/StringBuilder.append:(Ljava/lang/String;)Ljava/lang/StringBuilder;
     590: invokevirtual #71                 // Method java/lang/StringBuilder.toString:()Ljava/lang/String;
     593: invokevirtual #29                 // Method java/io/PrintStream.println:(Ljava/lang/String;)V
     596: getstatic     #27                 // Field java/lang/System.out:Ljava/io/PrintStream;
     599: ldc           #197                // String \t\t Locality will change with the new plan:
     601: invokevirtual #190                // Method java/io/PrintStream.print:(Ljava/lang/String;)V
     604: getstatic     #27                 // Field java/lang/System.out:Ljava/io/PrintStream;
     607: new           #62                 // class java/lang/StringBuilder
     610: dup
     611: invokespecial #63                 // Method java/lang/StringBuilder."<init>":()V
     614: aload         13
     616: ldc           #194                // float 100.0f
     618: aload         10
     620: iload         14
     622: faload
     623: fmul
     624: aload         12
     626: invokeinterface #49,  1           // InterfaceMethod java/util/List.size:()I
     631: i2f
     632: fdiv
     633: f2d
     634: invokevirtual #195                // Method java/text/DecimalFormat.format:(D)Ljava/lang/String;
     637: invokevirtual #65                 // Method java/lang/StringBuilder.append:(Ljava/lang/String;)Ljava/lang/StringBuilder;
     640: ldc           #196                // String %
     642: invokevirtual #65                 // Method java/lang/StringBuilder.append:(Ljava/lang/String;)Ljava/lang/StringBuilder;
     645: invokevirtual #71                 // Method java/lang/StringBuilder.toString:()Ljava/lang/String;
     648: invokevirtual #29                 // Method java/io/PrintStream.println:(Ljava/lang/String;)V
     651: iinc          14, 1
     654: goto          486
     657: getstatic     #27                 // Field java/lang/System.out:Ljava/io/PrintStream;
     660: ldc           #198                // String \t Baseline dispersion
     662: invokevirtual #29                 // Method java/io/PrintStream.println:(Ljava/lang/String;)V
     665: aload_0
     666: aload         9
     668: aload         4
     670: aload         12
     672: invokeinterface #49,  1           // InterfaceMethod java/util/List.size:()I
     677: aconst_null
     678: iconst_1
     679: invokevirtual #199                // Method printDispersionScores:(Lorg/apache/hadoop/hbase/TableName;Lorg/apache/hadoop/hbase/master/SnapshotOfRegionAssignmentFromMeta;ILorg/apache/hadoop/hbase/favored/FavoredNodesPlan;Z)V
     682: getstatic     #27                 // Field java/lang/System.out:Ljava/io/PrintStream;
     685: ldc           #200                // String \t Projected dispersion
     687: invokevirtual #29                 // Method java/io/PrintStream.println:(Ljava/lang/String;)V
     690: aload_0
     691: aload         9
     693: aload         4
     695: aload         12
     697: invokeinterface #49,  1           // InterfaceMethod java/util/List.size:()I
     702: aload_3
     703: iconst_1
     704: invokevirtual #199                // Method printDispersionScores:(Lorg/apache/hadoop/hbase/TableName;Lorg/apache/hadoop/hbase/master/SnapshotOfRegionAssignmentFromMeta;ILorg/apache/hadoop/hbase/favored/FavoredNodesPlan;Z)V
     707: goto          36
     710: return

  public void printDispersionScores(org.apache.hadoop.hbase.TableName, org.apache.hadoop.hbase.master.SnapshotOfRegionAssignmentFromMeta, int, org.apache.hadoop.hbase.favored.FavoredNodesPlan, boolean);
    Code:
       0: aload_0
       1: getfield      #9                  // Field targetTableSet:Ljava/util/Set;
       4: invokeinterface #39,  1           // InterfaceMethod java/util/Set.isEmpty:()Z
       9: ifne          26
      12: aload_0
      13: getfield      #9                  // Field targetTableSet:Ljava/util/Set;
      16: aload_1
      17: invokeinterface #40,  2           // InterfaceMethod java/util/Set.contains:(Ljava/lang/Object;)Z
      22: ifne          26
      25: return
      26: new           #41                 // class org/apache/hadoop/hbase/master/AssignmentVerificationReport
      29: dup
      30: invokespecial #42                 // Method org/apache/hadoop/hbase/master/AssignmentVerificationReport."<init>":()V
      33: astore        6
      35: aload         6
      37: aload_1
      38: aload_2
      39: aload         4
      41: invokevirtual #201                // Method org/apache/hadoop/hbase/master/AssignmentVerificationReport.fillUpDispersion:(Lorg/apache/hadoop/hbase/TableName;Lorg/apache/hadoop/hbase/master/SnapshotOfRegionAssignmentFromMeta;Lorg/apache/hadoop/hbase/favored/FavoredNodesPlan;)V
      44: aload         6
      46: invokevirtual #202                // Method org/apache/hadoop/hbase/master/AssignmentVerificationReport.getDispersionInformation:()Ljava/util/List;
      49: astore        7
      51: iload         5
      53: ifeq          154
      56: new           #186                // class java/text/DecimalFormat
      59: dup
      60: ldc           #187                // String #.##
      62: invokespecial #188                // Method java/text/DecimalFormat."<init>":(Ljava/lang/String;)V
      65: astore        8
      67: getstatic     #27                 // Field java/lang/System.out:Ljava/io/PrintStream;
      70: new           #62                 // class java/lang/StringBuilder
      73: dup
      74: invokespecial #63                 // Method java/lang/StringBuilder."<init>":()V
      77: ldc           #203                // String \tAvg dispersion score:
      79: invokevirtual #65                 // Method java/lang/StringBuilder.append:(Ljava/lang/String;)Ljava/lang/StringBuilder;
      82: aload         8
      84: aload         7
      86: iconst_0
      87: invokeinterface #75,  2           // InterfaceMethod java/util/List.get:(I)Ljava/lang/Object;
      92: invokevirtual #204                // Method java/text/DecimalFormat.format:(Ljava/lang/Object;)Ljava/lang/String;
      95: invokevirtual #65                 // Method java/lang/StringBuilder.append:(Ljava/lang/String;)Ljava/lang/StringBuilder;
      98: ldc           #205                // String  hosts;\tMax dispersion score:
     100: invokevirtual #65                 // Method java/lang/StringBuilder.append:(Ljava/lang/String;)Ljava/lang/StringBuilder;
     103: aload         8
     105: aload         7
     107: iconst_1
     108: invokeinterface #75,  2           // InterfaceMethod java/util/List.get:(I)Ljava/lang/Object;
     113: invokevirtual #204                // Method java/text/DecimalFormat.format:(Ljava/lang/Object;)Ljava/lang/String;
     116: invokevirtual #65                 // Method java/lang/StringBuilder.append:(Ljava/lang/String;)Ljava/lang/StringBuilder;
     119: ldc           #206                // String  hosts;\tMin dispersion score:
     121: invokevirtual #65                 // Method java/lang/StringBuilder.append:(Ljava/lang/String;)Ljava/lang/StringBuilder;
     124: aload         8
     126: aload         7
     128: iconst_2
     129: invokeinterface #75,  2           // InterfaceMethod java/util/List.get:(I)Ljava/lang/Object;
     134: invokevirtual #204                // Method java/text/DecimalFormat.format:(Ljava/lang/Object;)Ljava/lang/String;
     137: invokevirtual #65                 // Method java/lang/StringBuilder.append:(Ljava/lang/String;)Ljava/lang/StringBuilder;
     140: ldc           #207                // String  hosts;
     142: invokevirtual #65                 // Method java/lang/StringBuilder.append:(Ljava/lang/String;)Ljava/lang/StringBuilder;
     145: invokevirtual #71                 // Method java/lang/StringBuilder.toString:()Ljava/lang/String;
     148: invokevirtual #29                 // Method java/io/PrintStream.println:(Ljava/lang/String;)V
     151: goto          206
     154: getstatic     #61                 // Field LOG:Lorg/slf4j/Logger;
     157: new           #62                 // class java/lang/StringBuilder
     160: dup
     161: invokespecial #63                 // Method java/lang/StringBuilder."<init>":()V
     164: ldc           #208                // String For Table:
     166: invokevirtual #65                 // Method java/lang/StringBuilder.append:(Ljava/lang/String;)Ljava/lang/StringBuilder;
     169: aload_1
     170: invokevirtual #68                 // Method java/lang/StringBuilder.append:(Ljava/lang/Object;)Ljava/lang/StringBuilder;
     173: ldc           #209                // String  ; #Total Regions:
     175: invokevirtual #65                 // Method java/lang/StringBuilder.append:(Ljava/lang/String;)Ljava/lang/StringBuilder;
     178: iload_3
     179: invokevirtual #66                 // Method java/lang/StringBuilder.append:(I)Ljava/lang/StringBuilder;
     182: ldc           #210                // String  ; The average dispersion score is
     184: invokevirtual #65                 // Method java/lang/StringBuilder.append:(Ljava/lang/String;)Ljava/lang/StringBuilder;
     187: aload         7
     189: iconst_0
     190: invokeinterface #75,  2           // InterfaceMethod java/util/List.get:(I)Ljava/lang/Object;
     195: invokevirtual #68                 // Method java/lang/StringBuilder.append:(Ljava/lang/Object;)Ljava/lang/StringBuilder;
     198: invokevirtual #71                 // Method java/lang/StringBuilder.toString:()Ljava/lang/String;
     201: invokeinterface #72,  2           // InterfaceMethod org/slf4j/Logger.info:(Ljava/lang/String;)V
     206: return

  public void printLocalityAndDispersionForCurrentPlan(java.util.Map<java.lang.String, java.util.Map<java.lang.String, java.lang.Float>>) throws java.io.IOException;
    Code:
       0: aload_0
       1: invokevirtual #30                 // Method getRegionAssignmentSnapshot:()Lorg/apache/hadoop/hbase/master/SnapshotOfRegionAssignmentFromMeta;
       4: astore_2
       5: aload_2
       6: invokevirtual #176                // Method org/apache/hadoop/hbase/master/SnapshotOfRegionAssignmentFromMeta.getExistingAssignmentPlan:()Lorg/apache/hadoop/hbase/favored/FavoredNodesPlan;
       9: astore_3
      10: aload_2
      11: invokevirtual #31                 // Method org/apache/hadoop/hbase/master/SnapshotOfRegionAssignmentFromMeta.getTableSet:()Ljava/util/Set;
      14: astore        4
      16: aload_2
      17: invokevirtual #46                 // Method org/apache/hadoop/hbase/master/SnapshotOfRegionAssignmentFromMeta.getTableToRegionMap:()Ljava/util/Map;
      20: astore        5
      22: aload         4
      24: invokeinterface #35,  1           // InterfaceMethod java/util/Set.iterator:()Ljava/util/Iterator;
      29: astore        6
      31: aload         6
      33: invokeinterface #36,  1           // InterfaceMethod java/util/Iterator.hasNext:()Z
      38: ifeq          443
      41: aload         6
      43: invokeinterface #37,  1           // InterfaceMethod java/util/Iterator.next:()Ljava/lang/Object;
      48: checkcast     #38                 // class org/apache/hadoop/hbase/TableName
      51: astore        7
      53: iconst_3
      54: newarray       float
      56: astore        8
      58: aload_0
      59: getfield      #9                  // Field targetTableSet:Ljava/util/Set;
      62: invokeinterface #39,  1           // InterfaceMethod java/util/Set.isEmpty:()Z
      67: ifne          87
      70: aload_0
      71: getfield      #9                  // Field targetTableSet:Ljava/util/Set;
      74: aload         7
      76: invokeinterface #40,  2           // InterfaceMethod java/util/Set.contains:(Ljava/lang/Object;)Z
      81: ifne          87
      84: goto          31
      87: aload         5
      89: aload         7
      91: invokeinterface #47,  2           // InterfaceMethod java/util/Map.get:(Ljava/lang/Object;)Ljava/lang/Object;
      96: checkcast     #48                 // class java/util/List
      99: astore        9
     101: aload         9
     103: invokeinterface #150,  1          // InterfaceMethod java/util/List.iterator:()Ljava/util/Iterator;
     108: astore        10
     110: aload         10
     112: invokeinterface #36,  1           // InterfaceMethod java/util/Iterator.hasNext:()Z
     117: ifeq          282
     120: aload         10
     122: invokeinterface #37,  1           // InterfaceMethod java/util/Iterator.next:()Ljava/lang/Object;
     127: checkcast     #76                 // class org/apache/hadoop/hbase/client/RegionInfo
     130: astore        11
     132: aload_1
     133: aload         11
     135: invokeinterface #77,  1           // InterfaceMethod org/apache/hadoop/hbase/client/RegionInfo.getEncodedName:()Ljava/lang/String;
     140: invokeinterface #47,  2           // InterfaceMethod java/util/Map.get:(Ljava/lang/Object;)Ljava/lang/Object;
     145: checkcast     #78                 // class java/util/Map
     148: astore        12
     150: aload         12
     152: ifnonnull     158
     155: goto          110
     158: aload_3
     159: aload         11
     161: invokevirtual #151                // Method org/apache/hadoop/hbase/favored/FavoredNodesPlan.getFavoredNodes:(Lorg/apache/hadoop/hbase/client/RegionInfo;)Ljava/util/List;
     164: astore        13
     166: aload         13
     168: ifnull        279
     171: iconst_0
     172: istore        14
     174: invokestatic  #184                // Method org/apache/hadoop/hbase/favored/FavoredNodesPlan$Position.values:()[Lorg/apache/hadoop/hbase/favored/FavoredNodesPlan$Position;
     177: astore        15
     179: aload         15
     181: arraylength
     182: istore        16
     184: iconst_0
     185: istore        17
     187: iload         17
     189: iload         16
     191: if_icmpge     279
     194: aload         15
     196: iload         17
     198: aaload
     199: astore        18
     201: aload         13
     203: aload         18
     205: invokevirtual #185                // Method org/apache/hadoop/hbase/favored/FavoredNodesPlan$Position.ordinal:()I
     208: invokeinterface #75,  2           // InterfaceMethod java/util/List.get:(I)Ljava/lang/Object;
     213: checkcast     #79                 // class org/apache/hadoop/hbase/ServerName
     216: astore        19
     218: fconst_0
     219: invokestatic  #86                 // Method java/lang/Float.valueOf:(F)Ljava/lang/Float;
     222: astore        20
     224: aload         13
     226: ifnull        270
     229: aload         12
     231: aload         19
     233: invokevirtual #80                 // Method org/apache/hadoop/hbase/ServerName.getHostname:()Ljava/lang/String;
     236: invokeinterface #47,  2           // InterfaceMethod java/util/Map.get:(Ljava/lang/Object;)Ljava/lang/Object;
     241: checkcast     #1                  // class java/lang/Float
     244: astore        20
     246: aload         20
     248: ifnonnull     257
     251: fconst_0
     252: invokestatic  #86                 // Method java/lang/Float.valueOf:(F)Ljava/lang/Float;
     255: astore        20
     257: aload         8
     259: iload         14
     261: dup2
     262: faload
     263: aload         20
     265: invokevirtual #81                 // Method java/lang/Float.floatValue:()F
     268: fadd
     269: fastore
     270: iinc          14, 1
     273: iinc          17, 1
     276: goto          187
     279: goto          110
     282: iconst_0
     283: istore        10
     285: iload         10
     287: aload         8
     289: arraylength
     290: if_icmpge     424
     293: aconst_null
     294: astore        11
     296: iload         10
     298: ifne          308
     301: ldc           #211                // String primary
     303: astore        11
     305: goto          331
     308: iload         10
     310: iconst_1
     311: if_icmpne     321
     314: ldc           #212                // String secondary
     316: astore        11
     318: goto          331
     321: iload         10
     323: iconst_2
     324: if_icmpne     331
     327: ldc           #213                // String tertiary
     329: astore        11
     331: ldc           #194                // float 100.0f
     333: aload         8
     335: iload         10
     337: faload
     338: fmul
     339: aload         9
     341: invokeinterface #49,  1           // InterfaceMethod java/util/List.size:()I
     346: i2f
     347: fdiv
     348: fstore        12
     350: getstatic     #61                 // Field LOG:Lorg/slf4j/Logger;
     353: new           #62                 // class java/lang/StringBuilder
     356: dup
     357: invokespecial #63                 // Method java/lang/StringBuilder."<init>":()V
     360: ldc           #208                // String For Table:
     362: invokevirtual #65                 // Method java/lang/StringBuilder.append:(Ljava/lang/String;)Ljava/lang/StringBuilder;
     365: aload         7
     367: invokevirtual #68                 // Method java/lang/StringBuilder.append:(Ljava/lang/Object;)Ljava/lang/StringBuilder;
     370: ldc           #209                // String  ; #Total Regions:
     372: invokevirtual #65                 // Method java/lang/StringBuilder.append:(Ljava/lang/String;)Ljava/lang/StringBuilder;
     375: aload         9
     377: invokeinterface #49,  1           // InterfaceMethod java/util/List.size:()I
     382: invokevirtual #66                 // Method java/lang/StringBuilder.append:(I)Ljava/lang/StringBuilder;
     385: ldc           #214                // String  ; The average locality for
     387: invokevirtual #65                 // Method java/lang/StringBuilder.append:(Ljava/lang/String;)Ljava/lang/StringBuilder;
     390: aload         11
     392: invokevirtual #65                 // Method java/lang/StringBuilder.append:(Ljava/lang/String;)Ljava/lang/StringBuilder;
     395: ldc           #215                // String  is
     397: invokevirtual #65                 // Method java/lang/StringBuilder.append:(Ljava/lang/String;)Ljava/lang/StringBuilder;
     400: fload         12
     402: invokevirtual #216                // Method java/lang/StringBuilder.append:(F)Ljava/lang/StringBuilder;
     405: ldc           #217                // String  %
     407: invokevirtual #65                 // Method java/lang/StringBuilder.append:(Ljava/lang/String;)Ljava/lang/StringBuilder;
     410: invokevirtual #71                 // Method java/lang/StringBuilder.toString:()Ljava/lang/String;
     413: invokeinterface #72,  2           // InterfaceMethod org/slf4j/Logger.info:(Ljava/lang/String;)V
     418: iinc          10, 1
     421: goto          285
     424: aload_0
     425: aload         7
     427: aload_2
     428: aload         9
     430: invokeinterface #49,  1           // InterfaceMethod java/util/List.size:()I
     435: aconst_null
     436: iconst_0
     437: invokevirtual #199                // Method printDispersionScores:(Lorg/apache/hadoop/hbase/TableName;Lorg/apache/hadoop/hbase/master/SnapshotOfRegionAssignmentFromMeta;ILorg/apache/hadoop/hbase/favored/FavoredNodesPlan;Z)V
     440: goto          31
     443: return

  public static java.util.List<org.apache.hadoop.hbase.ServerName> getFavoredNodeList(java.lang.String);
    Code:
       0: aload_0
       1: ldc           #218                // String ,
       3: invokestatic  #219                // Method org/apache/commons/lang3/StringUtils.split:(Ljava/lang/String;Ljava/lang/String;)[Ljava/lang/String;
       6: astore_1
       7: aload_1
       8: ifnonnull     13
      11: aconst_null
      12: areturn
      13: new           #33                 // class java/util/ArrayList
      16: dup
      17: invokespecial #34                 // Method java/util/ArrayList."<init>":()V
      20: astore_2
      21: aload_1
      22: astore_3
      23: aload_3
      24: arraylength
      25: istore        4
      27: iconst_0
      28: istore        5
      30: iload         5
      32: iload         4
      34: if_icmpge     64
      37: aload_3
      38: iload         5
      40: aaload
      41: astore        6
      43: aload_2
      44: aload         6
      46: ldc2_w        #104                // long -1l
      49: invokestatic  #220                // Method org/apache/hadoop/hbase/ServerName.valueOf:(Ljava/lang/String;J)Lorg/apache/hadoop/hbase/ServerName;
      52: invokeinterface #45,  2           // InterfaceMethod java/util/List.add:(Ljava/lang/Object;)Z
      57: pop
      58: iinc          5, 1
      61: goto          30
      64: aload_2
      65: areturn

  public static void main(java.lang.String[]) throws java.io.IOException;
    Code:
       0: new           #221                // class org/apache/hbase/thirdparty/org/apache/commons/cli/Options
       3: dup
       4: invokespecial #222                // Method org/apache/hbase/thirdparty/org/apache/commons/cli/Options."<init>":()V
       7: astore_1
       8: aload_1
       9: ldc           #223                // String w
      11: ldc           #224                // String write
      13: iconst_0
      14: ldc           #225                // String write the assignments to hbase:meta only
      16: invokevirtual #226                // Method org/apache/hbase/thirdparty/org/apache/commons/cli/Options.addOption:(Ljava/lang/String;Ljava/lang/String;ZLjava/lang/String;)Lorg/apache/hbase/thirdparty/org/apache/commons/cli/Options;
      19: pop
      20: aload_1
      21: ldc           #227                // String u
      23: ldc           #228                // String update
      25: iconst_0
      26: ldc           #229                // String update the assignments to hbase:meta and RegionServers together
      28: invokevirtual #226                // Method org/apache/hbase/thirdparty/org/apache/commons/cli/Options.addOption:(Ljava/lang/String;Ljava/lang/String;ZLjava/lang/String;)Lorg/apache/hbase/thirdparty/org/apache/commons/cli/Options;
      31: pop
      32: aload_1
      33: ldc           #230                // String n
      35: ldc           #231                // String dry-run
      37: iconst_0
      38: ldc           #232                // String do not write assignments to META
      40: invokevirtual #226                // Method org/apache/hbase/thirdparty/org/apache/commons/cli/Options.addOption:(Ljava/lang/String;Ljava/lang/String;ZLjava/lang/String;)Lorg/apache/hbase/thirdparty/org/apache/commons/cli/Options;
      43: pop
      44: aload_1
      45: ldc           #233                // String v
      47: ldc           #234                // String verify
      49: iconst_0
      50: ldc           #235                // String verify current assignments against META
      52: invokevirtual #226                // Method org/apache/hbase/thirdparty/org/apache/commons/cli/Options.addOption:(Ljava/lang/String;Ljava/lang/String;ZLjava/lang/String;)Lorg/apache/hbase/thirdparty/org/apache/commons/cli/Options;
      55: pop
      56: aload_1
      57: ldc           #236                // String p
      59: ldc           #237                // String print
      61: iconst_0
      62: ldc           #238                // String print the current assignment plan in META
      64: invokevirtual #226                // Method org/apache/hbase/thirdparty/org/apache/commons/cli/Options.addOption:(Ljava/lang/String;Ljava/lang/String;ZLjava/lang/String;)Lorg/apache/hbase/thirdparty/org/apache/commons/cli/Options;
      67: pop
      68: aload_1
      69: ldc           #239                // String h
      71: ldc           #240                // String help
      73: iconst_0
      74: ldc           #241                // String print usage
      76: invokevirtual #226                // Method org/apache/hbase/thirdparty/org/apache/commons/cli/Options.addOption:(Ljava/lang/String;Ljava/lang/String;ZLjava/lang/String;)Lorg/apache/hbase/thirdparty/org/apache/commons/cli/Options;
      79: pop
      80: aload_1
      81: ldc           #242                // String d
      83: ldc           #243                // String verification-details
      85: iconst_0
      86: ldc           #244                // String print the details of verification report
      88: invokevirtual #226                // Method org/apache/hbase/thirdparty/org/apache/commons/cli/Options.addOption:(Ljava/lang/String;Ljava/lang/String;ZLjava/lang/String;)Lorg/apache/hbase/thirdparty/org/apache/commons/cli/Options;
      91: pop
      92: aload_1
      93: ldc           #245                // String zk
      95: iconst_1
      96: ldc           #246                // String to set the zookeeper quorum
      98: invokevirtual #247                // Method org/apache/hbase/thirdparty/org/apache/commons/cli/Options.addOption:(Ljava/lang/String;ZLjava/lang/String;)Lorg/apache/hbase/thirdparty/org/apache/commons/cli/Options;
     101: pop
     102: aload_1
     103: ldc           #248                // String fs
     105: iconst_1
     106: ldc           #249                // String to set HDFS
     108: invokevirtual #247                // Method org/apache/hbase/thirdparty/org/apache/commons/cli/Options.addOption:(Ljava/lang/String;ZLjava/lang/String;)Lorg/apache/hbase/thirdparty/org/apache/commons/cli/Options;
     111: pop
     112: aload_1
     113: ldc           #250                // String hbase_root
     115: iconst_1
     116: ldc           #251                // String to set hbase_root directory
     118: invokevirtual #247                // Method org/apache/hbase/thirdparty/org/apache/commons/cli/Options.addOption:(Ljava/lang/String;ZLjava/lang/String;)Lorg/apache/hbase/thirdparty/org/apache/commons/cli/Options;
     121: pop
     122: aload_1
     123: ldc           #252                // String overwrite
     125: iconst_0
     126: ldc           #253                // String overwrite the favored nodes for a single region,for example: -update -r regionName -f server1:port,server2:port,server3:port
     128: invokevirtual #247                // Method org/apache/hbase/thirdparty/org/apache/commons/cli/Options.addOption:(Ljava/lang/String;ZLjava/lang/String;)Lorg/apache/hbase/thirdparty/org/apache/commons/cli/Options;
     131: pop
     132: aload_1
     133: ldc           #254                // String r
     135: iconst_1
     136: ldc           #255                // String The region name that needs to be updated
     138: invokevirtual #247                // Method org/apache/hbase/thirdparty/org/apache/commons/cli/Options.addOption:(Ljava/lang/String;ZLjava/lang/String;)Lorg/apache/hbase/thirdparty/org/apache/commons/cli/Options;
     141: pop
     142: aload_1
     143: ldc_w         #256                // String f
     146: iconst_1
     147: ldc_w         #257                // String The new favored nodes
     150: invokevirtual #247                // Method org/apache/hbase/thirdparty/org/apache/commons/cli/Options.addOption:(Ljava/lang/String;ZLjava/lang/String;)Lorg/apache/hbase/thirdparty/org/apache/commons/cli/Options;
     153: pop
     154: aload_1
     155: ldc_w         #258                // String tables
     158: iconst_1
     159: ldc_w         #259                // String The list of table names splitted by ',' ;For example: -tables: t1,t2,...,tn
     162: invokevirtual #247                // Method org/apache/hbase/thirdparty/org/apache/commons/cli/Options.addOption:(Ljava/lang/String;ZLjava/lang/String;)Lorg/apache/hbase/thirdparty/org/apache/commons/cli/Options;
     165: pop
     166: aload_1
     167: ldc_w         #260                // String l
     170: ldc_w         #261                // String locality
     173: iconst_1
     174: ldc_w         #262                // String enforce the maximum locality
     177: invokevirtual #226                // Method org/apache/hbase/thirdparty/org/apache/commons/cli/Options.addOption:(Ljava/lang/String;Ljava/lang/String;ZLjava/lang/String;)Lorg/apache/hbase/thirdparty/org/apache/commons/cli/Options;
     180: pop
     181: aload_1
     182: ldc_w         #263                // String m
     185: ldc_w         #264                // String min-move
     188: iconst_1
     189: ldc_w         #265                // String enforce minimum assignment move
     192: invokevirtual #226                // Method org/apache/hbase/thirdparty/org/apache/commons/cli/Options.addOption:(Ljava/lang/String;Ljava/lang/String;ZLjava/lang/String;)Lorg/apache/hbase/thirdparty/org/apache/commons/cli/Options;
     195: pop
     196: aload_1
     197: ldc_w         #266                // String diff
     200: iconst_0
     201: ldc_w         #267                // String calculate difference between assignment plans
     204: invokevirtual #247                // Method org/apache/hbase/thirdparty/org/apache/commons/cli/Options.addOption:(Ljava/lang/String;ZLjava/lang/String;)Lorg/apache/hbase/thirdparty/org/apache/commons/cli/Options;
     207: pop
     208: aload_1
     209: ldc_w         #268                // String munkres
     212: iconst_0
     213: ldc_w         #269                // String use munkres to place secondaries and tertiaries
     216: invokevirtual #247                // Method org/apache/hbase/thirdparty/org/apache/commons/cli/Options.addOption:(Ljava/lang/String;ZLjava/lang/String;)Lorg/apache/hbase/thirdparty/org/apache/commons/cli/Options;
     219: pop
     220: aload_1
     221: ldc_w         #270                // String ld
     224: ldc_w         #271                // String locality-dispersion
     227: iconst_0
     228: ldc_w         #272                // String print locality and dispersion information for current plan
     231: invokevirtual #226                // Method org/apache/hbase/thirdparty/org/apache/commons/cli/Options.addOption:(Ljava/lang/String;Ljava/lang/String;ZLjava/lang/String;)Lorg/apache/hbase/thirdparty/org/apache/commons/cli/Options;
     234: pop
     235: new           #273                // class org/apache/hbase/thirdparty/org/apache/commons/cli/GnuParser
     238: dup
     239: invokespecial #274                // Method org/apache/hbase/thirdparty/org/apache/commons/cli/GnuParser."<init>":()V
     242: aload_1
     243: aload_0
     244: invokevirtual #275                // Method org/apache/hbase/thirdparty/org/apache/commons/cli/GnuParser.parse:(Lorg/apache/hbase/thirdparty/org/apache/commons/cli/Options;[Ljava/lang/String;)Lorg/apache/hbase/thirdparty/org/apache/commons/cli/CommandLine;
     247: astore_2
     248: invokestatic  #276                // Method org/apache/hadoop/hbase/HBaseConfiguration.create:()Lorg/apache/hadoop/conf/Configuration;
     251: astore_3
     252: iconst_1
     253: istore        4
     255: iconst_1
     256: istore        5
     258: iconst_0
     259: istore        6
     261: aload_2
     262: ldc_w         #260                // String l
     265: invokevirtual #277                // Method org/apache/hbase/thirdparty/org/apache/commons/cli/CommandLine.hasOption:(Ljava/lang/String;)Z
     268: ifeq          287
     271: aload_2
     272: ldc_w         #260                // String l
     275: invokevirtual #278                // Method org/apache/hbase/thirdparty/org/apache/commons/cli/CommandLine.getOptionValue:(Ljava/lang/String;)Ljava/lang/String;
     278: ldc_w         #279                // String false
     281: invokevirtual #280                // Method java/lang/String.equalsIgnoreCase:(Ljava/lang/String;)Z
     284: ifne          313
     287: aload_2
     288: ldc_w         #261                // String locality
     291: invokevirtual #277                // Method org/apache/hbase/thirdparty/org/apache/commons/cli/CommandLine.hasOption:(Ljava/lang/String;)Z
     294: ifeq          316
     297: aload_2
     298: ldc_w         #261                // String locality
     301: invokevirtual #278                // Method org/apache/hbase/thirdparty/org/apache/commons/cli/CommandLine.getOptionValue:(Ljava/lang/String;)Ljava/lang/String;
     304: ldc_w         #279                // String false
     307: invokevirtual #280                // Method java/lang/String.equalsIgnoreCase:(Ljava/lang/String;)Z
     310: ifeq          316
     313: iconst_0
     314: istore        5
     316: aload_2
     317: ldc_w         #263                // String m
     320: invokevirtual #277                // Method org/apache/hbase/thirdparty/org/apache/commons/cli/CommandLine.hasOption:(Ljava/lang/String;)Z
     323: ifeq          342
     326: aload_2
     327: ldc_w         #263                // String m
     330: invokevirtual #278                // Method org/apache/hbase/thirdparty/org/apache/commons/cli/CommandLine.getOptionValue:(Ljava/lang/String;)Ljava/lang/String;
     333: ldc_w         #279                // String false
     336: invokevirtual #280                // Method java/lang/String.equalsIgnoreCase:(Ljava/lang/String;)Z
     339: ifne          368
     342: aload_2
     343: ldc_w         #264                // String min-move
     346: invokevirtual #277                // Method org/apache/hbase/thirdparty/org/apache/commons/cli/CommandLine.hasOption:(Ljava/lang/String;)Z
     349: ifeq          371
     352: aload_2
     353: ldc_w         #264                // String min-move
     356: invokevirtual #278                // Method org/apache/hbase/thirdparty/org/apache/commons/cli/CommandLine.getOptionValue:(Ljava/lang/String;)Ljava/lang/String;
     359: ldc_w         #279                // String false
     362: invokevirtual #280                // Method java/lang/String.equalsIgnoreCase:(Ljava/lang/String;)Z
     365: ifeq          371
     368: iconst_0
     369: istore        4
     371: aload_2
     372: ldc           #245                // String zk
     374: invokevirtual #277                // Method org/apache/hbase/thirdparty/org/apache/commons/cli/CommandLine.hasOption:(Ljava/lang/String;)Z
     377: ifeq          427
     380: aload_3
     381: ldc_w         #282                // String hbase.zookeeper.quorum
     384: aload_2
     385: ldc           #245                // String zk
     387: invokevirtual #278                // Method org/apache/hbase/thirdparty/org/apache/commons/cli/CommandLine.getOptionValue:(Ljava/lang/String;)Ljava/lang/String;
     390: invokevirtual #283                // Method org/apache/hadoop/conf/Configuration.set:(Ljava/lang/String;Ljava/lang/String;)V
     393: getstatic     #61                 // Field LOG:Lorg/slf4j/Logger;
     396: new           #62                 // class java/lang/StringBuilder
     399: dup
     400: invokespecial #63                 // Method java/lang/StringBuilder."<init>":()V
     403: ldc_w         #284                // String Setting the zk quorum:
     406: invokevirtual #65                 // Method java/lang/StringBuilder.append:(Ljava/lang/String;)Ljava/lang/StringBuilder;
     409: aload_3
     410: ldc_w         #282                // String hbase.zookeeper.quorum
     413: invokevirtual #285                // Method org/apache/hadoop/conf/Configuration.get:(Ljava/lang/String;)Ljava/lang/String;
     416: invokevirtual #65                 // Method java/lang/StringBuilder.append:(Ljava/lang/String;)Ljava/lang/StringBuilder;
     419: invokevirtual #71                 // Method java/lang/StringBuilder.toString:()Ljava/lang/String;
     422: invokeinterface #72,  2           // InterfaceMethod org/slf4j/Logger.info:(Ljava/lang/String;)V
     427: aload_2
     428: ldc           #248                // String fs
     430: invokevirtual #277                // Method org/apache/hbase/thirdparty/org/apache/commons/cli/CommandLine.hasOption:(Ljava/lang/String;)Z
     433: ifeq          483
     436: aload_3
     437: ldc_w         #287                // String fs.defaultFS
     440: aload_2
     441: ldc           #248                // String fs
     443: invokevirtual #278                // Method org/apache/hbase/thirdparty/org/apache/commons/cli/CommandLine.getOptionValue:(Ljava/lang/String;)Ljava/lang/String;
     446: invokevirtual #283                // Method org/apache/hadoop/conf/Configuration.set:(Ljava/lang/String;Ljava/lang/String;)V
     449: getstatic     #61                 // Field LOG:Lorg/slf4j/Logger;
     452: new           #62                 // class java/lang/StringBuilder
     455: dup
     456: invokespecial #63                 // Method java/lang/StringBuilder."<init>":()V
     459: ldc_w         #288                // String Setting the HDFS:
     462: invokevirtual #65                 // Method java/lang/StringBuilder.append:(Ljava/lang/String;)Ljava/lang/StringBuilder;
     465: aload_3
     466: ldc_w         #287                // String fs.defaultFS
     469: invokevirtual #285                // Method org/apache/hadoop/conf/Configuration.get:(Ljava/lang/String;)Ljava/lang/String;
     472: invokevirtual #65                 // Method java/lang/StringBuilder.append:(Ljava/lang/String;)Ljava/lang/StringBuilder;
     475: invokevirtual #71                 // Method java/lang/StringBuilder.toString:()Ljava/lang/String;
     478: invokeinterface #72,  2           // InterfaceMethod org/slf4j/Logger.info:(Ljava/lang/String;)V
     483: aload_2
     484: ldc           #250                // String hbase_root
     486: invokevirtual #277                // Method org/apache/hbase/thirdparty/org/apache/commons/cli/CommandLine.hasOption:(Ljava/lang/String;)Z
     489: ifeq          539
     492: aload_3
     493: ldc_w         #289                // String hbase.rootdir
     496: aload_2
     497: ldc           #250                // String hbase_root
     499: invokevirtual #278                // Method org/apache/hbase/thirdparty/org/apache/commons/cli/CommandLine.getOptionValue:(Ljava/lang/String;)Ljava/lang/String;
     502: invokevirtual #283                // Method org/apache/hadoop/conf/Configuration.set:(Ljava/lang/String;Ljava/lang/String;)V
     505: getstatic     #61                 // Field LOG:Lorg/slf4j/Logger;
     508: new           #62                 // class java/lang/StringBuilder
     511: dup
     512: invokespecial #63                 // Method java/lang/StringBuilder."<init>":()V
     515: ldc_w         #290                // String Setting the hbase root directory:
     518: invokevirtual #65                 // Method java/lang/StringBuilder.append:(Ljava/lang/String;)Ljava/lang/StringBuilder;
     521: aload_3
     522: ldc_w         #289                // String hbase.rootdir
     525: invokevirtual #285                // Method org/apache/hadoop/conf/Configuration.get:(Ljava/lang/String;)Ljava/lang/String;
     528: invokevirtual #65                 // Method java/lang/StringBuilder.append:(Ljava/lang/String;)Ljava/lang/StringBuilder;
     531: invokevirtual #71                 // Method java/lang/StringBuilder.toString:()Ljava/lang/String;
     534: invokeinterface #72,  2           // InterfaceMethod org/slf4j/Logger.info:(Ljava/lang/String;)V
     539: new           #88                 // class org/apache/hadoop/hbase/master/RegionPlacementMaintainer
     542: dup
     543: aload_3
     544: iload         5
     546: iload         4
     548: invokespecial #2                  // Method "<init>":(Lorg/apache/hadoop/conf/Configuration;ZZ)V
     551: astore        7
     553: aload_2
     554: ldc           #242                // String d
     556: invokevirtual #277                // Method org/apache/hbase/thirdparty/org/apache/commons/cli/CommandLine.hasOption:(Ljava/lang/String;)Z
     559: ifne          571
     562: aload_2
     563: ldc           #243                // String verification-details
     565: invokevirtual #277                // Method org/apache/hbase/thirdparty/org/apache/commons/cli/CommandLine.hasOption:(Ljava/lang/String;)Z
     568: ifeq          574
     571: iconst_1
     572: istore        6
     574: aload_2
     575: ldc_w         #258                // String tables
     578: invokevirtual #277                // Method org/apache/hbase/thirdparty/org/apache/commons/cli/CommandLine.hasOption:(Ljava/lang/String;)Z
     581: ifeq          609
     584: aload_2
     585: ldc_w         #258                // String tables
     588: invokevirtual #278                // Method org/apache/hbase/thirdparty/org/apache/commons/cli/CommandLine.getOptionValue:(Ljava/lang/String;)Ljava/lang/String;
     591: astore        8
     593: aload         8
     595: ldc           #218                // String ,
     597: invokestatic  #219                // Method org/apache/commons/lang3/StringUtils.split:(Ljava/lang/String;Ljava/lang/String;)[Ljava/lang/String;
     600: astore        9
     602: aload         7
     604: aload         9
     606: invokevirtual #291                // Method setTargetTableName:([Ljava/lang/String;)V
     609: aload_2
     610: ldc_w         #268                // String munkres
     613: invokevirtual #277                // Method org/apache/hbase/thirdparty/org/apache/commons/cli/CommandLine.hasOption:(Ljava/lang/String;)Z
     616: ifeq          623
     619: iconst_1
     620: putstatic     #120                // Field USE_MUNKRES_FOR_PLACING_SECONDARY_AND_TERTIARY:Z
     623: aload_2
     624: ldc           #233                // String v
     626: invokevirtual #277                // Method org/apache/hbase/thirdparty/org/apache/commons/cli/CommandLine.hasOption:(Ljava/lang/String;)Z
     629: ifne          641
     632: aload_2
     633: ldc           #234                // String verify
     635: invokevirtual #277                // Method org/apache/hbase/thirdparty/org/apache/commons/cli/CommandLine.hasOption:(Ljava/lang/String;)Z
     638: ifeq          652
     641: aload         7
     643: iload         6
     645: invokevirtual #292                // Method verifyRegionPlacement:(Z)Ljava/util/List;
     648: pop
     649: goto          1171
     652: aload_2
     653: ldc           #230                // String n
     655: invokevirtual #277                // Method org/apache/hbase/thirdparty/org/apache/commons/cli/CommandLine.hasOption:(Ljava/lang/String;)Z
     658: ifne          670
     661: aload_2
     662: ldc           #231                // String dry-run
     664: invokevirtual #277                // Method org/apache/hbase/thirdparty/org/apache/commons/cli/CommandLine.hasOption:(Ljava/lang/String;)Z
     667: ifeq          685
     670: aload         7
     672: invokevirtual #293                // Method getNewAssignmentPlan:()Lorg/apache/hadoop/hbase/favored/FavoredNodesPlan;
     675: astore        8
     677: aload         8
     679: invokestatic  #294                // Method printAssignmentPlan:(Lorg/apache/hadoop/hbase/favored/FavoredNodesPlan;)V
     682: goto          1171
     685: aload_2
     686: ldc           #223                // String w
     688: invokevirtual #277                // Method org/apache/hbase/thirdparty/org/apache/commons/cli/CommandLine.hasOption:(Ljava/lang/String;)Z
     691: ifne          703
     694: aload_2
     695: ldc           #224                // String write
     697: invokevirtual #277                // Method org/apache/hbase/thirdparty/org/apache/commons/cli/CommandLine.hasOption:(Ljava/lang/String;)Z
     700: ifeq          725
     703: aload         7
     705: invokevirtual #293                // Method getNewAssignmentPlan:()Lorg/apache/hadoop/hbase/favored/FavoredNodesPlan;
     708: astore        8
     710: aload         8
     712: invokestatic  #294                // Method printAssignmentPlan:(Lorg/apache/hadoop/hbase/favored/FavoredNodesPlan;)V
     715: aload         7
     717: aload         8
     719: invokevirtual #173                // Method updateAssignmentPlanToMeta:(Lorg/apache/hadoop/hbase/favored/FavoredNodesPlan;)V
     722: goto          1171
     725: aload_2
     726: ldc           #227                // String u
     728: invokevirtual #277                // Method org/apache/hbase/thirdparty/org/apache/commons/cli/CommandLine.hasOption:(Ljava/lang/String;)Z
     731: ifne          743
     734: aload_2
     735: ldc           #228                // String update
     737: invokevirtual #277                // Method org/apache/hbase/thirdparty/org/apache/commons/cli/CommandLine.hasOption:(Ljava/lang/String;)Z
     740: ifeq          765
     743: aload         7
     745: invokevirtual #293                // Method getNewAssignmentPlan:()Lorg/apache/hadoop/hbase/favored/FavoredNodesPlan;
     748: astore        8
     750: aload         8
     752: invokestatic  #294                // Method printAssignmentPlan:(Lorg/apache/hadoop/hbase/favored/FavoredNodesPlan;)V
     755: aload         7
     757: aload         8
     759: invokevirtual #295                // Method updateAssignmentPlan:(Lorg/apache/hadoop/hbase/favored/FavoredNodesPlan;)V
     762: goto          1171
     765: aload_2
     766: ldc_w         #266                // String diff
     769: invokevirtual #277                // Method org/apache/hbase/thirdparty/org/apache/commons/cli/CommandLine.hasOption:(Ljava/lang/String;)Z
     772: ifeq          874
     775: aload         7
     777: invokevirtual #293                // Method getNewAssignmentPlan:()Lorg/apache/hadoop/hbase/favored/FavoredNodesPlan;
     780: astore        8
     782: aload_3
     783: invokestatic  #32                 // Method org/apache/hadoop/hbase/util/FSUtils.getRegionDegreeLocalityMappingFromFS:(Lorg/apache/hadoop/conf/Configuration;)Ljava/util/Map;
     786: astore        9
     788: aload         7
     790: aload         8
     792: invokevirtual #296                // Method getRegionsMovement:(Lorg/apache/hadoop/hbase/favored/FavoredNodesPlan;)Ljava/util/Map;
     795: astore        10
     797: aload         7
     799: aload         10
     801: aload         9
     803: aload         8
     805: invokevirtual #297                // Method checkDifferencesWithOldPlan:(Ljava/util/Map;Ljava/util/Map;Lorg/apache/hadoop/hbase/favored/FavoredNodesPlan;)V
     808: getstatic     #27                 // Field java/lang/System.out:Ljava/io/PrintStream;
     811: ldc_w         #298                // String Do you want to update the assignment plan? [y/n]
     814: invokevirtual #29                 // Method java/io/PrintStream.println:(Ljava/lang/String;)V
     817: new           #299                // class java/util/Scanner
     820: dup
     821: getstatic     #300                // Field java/lang/System.in:Ljava/io/InputStream;
     824: invokespecial #301                // Method java/util/Scanner."<init>":(Ljava/io/InputStream;)V
     827: astore        11
     829: aload         11
     831: invokevirtual #302                // Method java/util/Scanner.nextLine:()Ljava/lang/String;
     834: invokevirtual #303                // Method java/lang/String.trim:()Ljava/lang/String;
     837: astore        12
     839: aload         12
     841: ldc_w         #304                // String y
     844: invokevirtual #98                 // Method java/lang/String.equals:(Ljava/lang/Object;)Z
     847: ifeq          866
     850: getstatic     #27                 // Field java/lang/System.out:Ljava/io/PrintStream;
     853: ldc_w         #305                // String Updating assignment plan...
     856: invokevirtual #29                 // Method java/io/PrintStream.println:(Ljava/lang/String;)V
     859: aload         7
     861: aload         8
     863: invokevirtual #295                // Method updateAssignmentPlan:(Lorg/apache/hadoop/hbase/favored/FavoredNodesPlan;)V
     866: aload         11
     868: invokevirtual #306                // Method java/util/Scanner.close:()V
     871: goto          1171
     874: aload_2
     875: ldc_w         #270                // String ld
     878: invokevirtual #277                // Method org/apache/hbase/thirdparty/org/apache/commons/cli/CommandLine.hasOption:(Ljava/lang/String;)Z
     881: ifeq          900
     884: aload_3
     885: invokestatic  #32                 // Method org/apache/hadoop/hbase/util/FSUtils.getRegionDegreeLocalityMappingFromFS:(Lorg/apache/hadoop/conf/Configuration;)Ljava/util/Map;
     888: astore        8
     890: aload         7
     892: aload         8
     894: invokevirtual #307                // Method printLocalityAndDispersionForCurrentPlan:(Ljava/util/Map;)V
     897: goto          1171
     900: aload_2
     901: ldc           #236                // String p
     903: invokevirtual #277                // Method org/apache/hbase/thirdparty/org/apache/commons/cli/CommandLine.hasOption:(Ljava/lang/String;)Z
     906: ifne          918
     909: aload_2
     910: ldc           #237                // String print
     912: invokevirtual #277                // Method org/apache/hbase/thirdparty/org/apache/commons/cli/CommandLine.hasOption:(Ljava/lang/String;)Z
     915: ifeq          936
     918: aload         7
     920: invokevirtual #30                 // Method getRegionAssignmentSnapshot:()Lorg/apache/hadoop/hbase/master/SnapshotOfRegionAssignmentFromMeta;
     923: invokevirtual #176                // Method org/apache/hadoop/hbase/master/SnapshotOfRegionAssignmentFromMeta.getExistingAssignmentPlan:()Lorg/apache/hadoop/hbase/favored/FavoredNodesPlan;
     926: astore        8
     928: aload         8
     930: invokestatic  #294                // Method printAssignmentPlan:(Lorg/apache/hadoop/hbase/favored/FavoredNodesPlan;)V
     933: goto          1171
     936: aload_2
     937: ldc           #252                // String overwrite
     939: invokevirtual #277                // Method org/apache/hbase/thirdparty/org/apache/commons/cli/CommandLine.hasOption:(Ljava/lang/String;)Z
     942: ifeq          1167
     945: aload_2
     946: ldc_w         #256                // String f
     949: invokevirtual #277                // Method org/apache/hbase/thirdparty/org/apache/commons/cli/CommandLine.hasOption:(Ljava/lang/String;)Z
     952: ifeq          964
     955: aload_2
     956: ldc           #254                // String r
     958: invokevirtual #277                // Method org/apache/hbase/thirdparty/org/apache/commons/cli/CommandLine.hasOption:(Ljava/lang/String;)Z
     961: ifne          975
     964: new           #308                // class java/lang/IllegalArgumentException
     967: dup
     968: ldc_w         #309                // String Please specify:  -update -r regionName -f server1:port,server2:port,server3:port
     971: invokespecial #310                // Method java/lang/IllegalArgumentException."<init>":(Ljava/lang/String;)V
     974: athrow
     975: aload_2
     976: ldc           #254                // String r
     978: invokevirtual #278                // Method org/apache/hbase/thirdparty/org/apache/commons/cli/CommandLine.getOptionValue:(Ljava/lang/String;)Ljava/lang/String;
     981: astore        8
     983: aload_2
     984: ldc_w         #256                // String f
     987: invokevirtual #278                // Method org/apache/hbase/thirdparty/org/apache/commons/cli/CommandLine.getOptionValue:(Ljava/lang/String;)Ljava/lang/String;
     990: astore        9
     992: getstatic     #61                 // Field LOG:Lorg/slf4j/Logger;
     995: new           #62                 // class java/lang/StringBuilder
     998: dup
     999: invokespecial #63                 // Method java/lang/StringBuilder."<init>":()V
    1002: ldc_w         #311                // String Going to update the region
    1005: invokevirtual #65                 // Method java/lang/StringBuilder.append:(Ljava/lang/String;)Ljava/lang/StringBuilder;
    1008: aload         8
    1010: invokevirtual #65                 // Method java/lang/StringBuilder.append:(Ljava/lang/String;)Ljava/lang/StringBuilder;
    1013: ldc_w         #312                // String  with the new favored nodes
    1016: invokevirtual #65                 // Method java/lang/StringBuilder.append:(Ljava/lang/String;)Ljava/lang/StringBuilder;
    1019: aload         9
    1021: invokevirtual #65                 // Method java/lang/StringBuilder.append:(Ljava/lang/String;)Ljava/lang/StringBuilder;
    1024: invokevirtual #71                 // Method java/lang/StringBuilder.toString:()Ljava/lang/String;
    1027: invokeinterface #72,  2           // InterfaceMethod org/slf4j/Logger.info:(Ljava/lang/String;)V
    1032: aconst_null
    1033: astore        10
    1035: aload         7
    1037: invokevirtual #30                 // Method getRegionAssignmentSnapshot:()Lorg/apache/hadoop/hbase/master/SnapshotOfRegionAssignmentFromMeta;
    1040: invokevirtual #143                // Method org/apache/hadoop/hbase/master/SnapshotOfRegionAssignmentFromMeta.getRegionNameToRegionInfoMap:()Ljava/util/Map;
    1043: aload         8
    1045: invokeinterface #47,  2           // InterfaceMethod java/util/Map.get:(Ljava/lang/Object;)Ljava/lang/Object;
    1050: checkcast     #76                 // class org/apache/hadoop/hbase/client/RegionInfo
    1053: astore        11
    1055: aload         11
    1057: ifnonnull     1098
    1060: getstatic     #61                 // Field LOG:Lorg/slf4j/Logger;
    1063: new           #62                 // class java/lang/StringBuilder
    1066: dup
    1067: invokespecial #63                 // Method java/lang/StringBuilder."<init>":()V
    1070: ldc_w         #313                // String Cannot find the region
    1073: invokevirtual #65                 // Method java/lang/StringBuilder.append:(Ljava/lang/String;)Ljava/lang/StringBuilder;
    1076: aload         8
    1078: invokevirtual #65                 // Method java/lang/StringBuilder.append:(Ljava/lang/String;)Ljava/lang/StringBuilder;
    1081: ldc_w         #314                // String  from the META
    1084: invokevirtual #65                 // Method java/lang/StringBuilder.append:(Ljava/lang/String;)Ljava/lang/StringBuilder;
    1087: invokevirtual #71                 // Method java/lang/StringBuilder.toString:()Ljava/lang/String;
    1090: invokeinterface #125,  2          // InterfaceMethod org/slf4j/Logger.error:(Ljava/lang/String;)V
    1095: goto          1164
    1098: aload         9
    1100: invokestatic  #315                // Method getFavoredNodeList:(Ljava/lang/String;)Ljava/util/List;
    1103: astore        10
    1105: goto          1139
    1108: astore        12
    1110: getstatic     #61                 // Field LOG:Lorg/slf4j/Logger;
    1113: new           #62                 // class java/lang/StringBuilder
    1116: dup
    1117: invokespecial #63                 // Method java/lang/StringBuilder."<init>":()V
    1120: ldc_w         #316                // String Cannot parse the invalid favored nodes because
    1123: invokevirtual #65                 // Method java/lang/StringBuilder.append:(Ljava/lang/String;)Ljava/lang/StringBuilder;
    1126: aload         12
    1128: invokevirtual #68                 // Method java/lang/StringBuilder.append:(Ljava/lang/Object;)Ljava/lang/StringBuilder;
    1131: invokevirtual #71                 // Method java/lang/StringBuilder.toString:()Ljava/lang/String;
    1134: invokeinterface #125,  2          // InterfaceMethod org/slf4j/Logger.error:(Ljava/lang/String;)V
    1139: new           #115                // class org/apache/hadoop/hbase/favored/FavoredNodesPlan
    1142: dup
    1143: invokespecial #116                // Method org/apache/hadoop/hbase/favored/FavoredNodesPlan."<init>":()V
    1146: astore        12
    1148: aload         12
    1150: aload         11
    1152: aload         10
    1154: invokevirtual #107                // Method org/apache/hadoop/hbase/favored/FavoredNodesPlan.updateFavoredNodesMap:(Lorg/apache/hadoop/hbase/client/RegionInfo;Ljava/util/List;)V
    1157: aload         7
    1159: aload         12
    1161: invokevirtual #295                // Method updateAssignmentPlan:(Lorg/apache/hadoop/hbase/favored/FavoredNodesPlan;)V
    1164: goto          1171
    1167: aload_1
    1168: invokestatic  #317                // Method printHelp:(Lorg/apache/hbase/thirdparty/org/apache/commons/cli/Options;)V
    1171: goto          1179
    1174: astore_2
    1175: aload_1
    1176: invokestatic  #317                // Method printHelp:(Lorg/apache/hbase/thirdparty/org/apache/commons/cli/Options;)V
    1179: return
    Exception table:
       from    to  target type
        1098  1105  1108   Class java/lang/IllegalArgumentException
         235  1171  1174   Class org/apache/hbase/thirdparty/org/apache/commons/cli/ParseException

  static {};
    Code:
       0: ldc           #88                 // class org/apache/hadoop/hbase/master/RegionPlacementMaintainer
       2: invokevirtual #319                // Method java/lang/Class.getName:()Ljava/lang/String;
       5: invokestatic  #320                // Method org/slf4j/LoggerFactory.getLogger:(Ljava/lang/String;)Lorg/slf4j/Logger;
       8: putstatic     #61                 // Field LOG:Lorg/slf4j/Logger;
      11: iconst_0
      12: putstatic     #120                // Field USE_MUNKRES_FOR_PLACING_SECONDARY_AND_TERTIARY:Z
      15: return
}
