Compiled from "RegionSizeReportingChore.java"
public class org.apache.hadoop.hbase.quotas.RegionSizeReportingChore extends org.apache.hadoop.hbase.ScheduledChore {
  static final java.lang.String REGION_SIZE_REPORTING_CHORE_PERIOD_KEY;

  static final int REGION_SIZE_REPORTING_CHORE_PERIOD_DEFAULT;

  static final java.lang.String REGION_SIZE_REPORTING_CHORE_DELAY_KEY;

  static final long REGION_SIZE_REPORTING_CHORE_DELAY_DEFAULT;

  static final java.lang.String REGION_SIZE_REPORTING_CHORE_TIMEUNIT_KEY;

  static final java.lang.String REGION_SIZE_REPORTING_CHORE_TIMEUNIT_DEFAULT;

  public org.apache.hadoop.hbase.quotas.RegionSizeReportingChore(org.apache.hadoop.hbase.regionserver.RegionServerServices);
    Code:
       0: aload_0
       1: ldc           #1                  // class org/apache/hadoop/hbase/quotas/RegionSizeReportingChore
       3: invokevirtual #2                  // Method java/lang/Class.getSimpleName:()Ljava/lang/String;
       6: aload_1
       7: aload_1
       8: invokeinterface #3,  1            // InterfaceMethod org/apache/hadoop/hbase/regionserver/RegionServerServices.getConfiguration:()Lorg/apache/hadoop/conf/Configuration;
      13: invokestatic  #4                  // Method getPeriod:(Lorg/apache/hadoop/conf/Configuration;)I
      16: aload_1
      17: invokeinterface #3,  1            // InterfaceMethod org/apache/hadoop/hbase/regionserver/RegionServerServices.getConfiguration:()Lorg/apache/hadoop/conf/Configuration;
      22: invokestatic  #5                  // Method getInitialDelay:(Lorg/apache/hadoop/conf/Configuration;)J
      25: aload_1
      26: invokeinterface #3,  1            // InterfaceMethod org/apache/hadoop/hbase/regionserver/RegionServerServices.getConfiguration:()Lorg/apache/hadoop/conf/Configuration;
      31: invokestatic  #6                  // Method getTimeUnit:(Lorg/apache/hadoop/conf/Configuration;)Ljava/util/concurrent/TimeUnit;
      34: invokespecial #7                  // Method org/apache/hadoop/hbase/ScheduledChore."<init>":(Ljava/lang/String;Lorg/apache/hadoop/hbase/Stoppable;IJLjava/util/concurrent/TimeUnit;)V
      37: aload_0
      38: aload_1
      39: putfield      #8                  // Field rsServices:Lorg/apache/hadoop/hbase/regionserver/RegionServerServices;
      42: aload_0
      43: aload_1
      44: invokeinterface #9,  1            // InterfaceMethod org/apache/hadoop/hbase/regionserver/RegionServerServices.getMetrics:()Lorg/apache/hadoop/hbase/regionserver/MetricsRegionServer;
      49: putfield      #10                 // Field metrics:Lorg/apache/hadoop/hbase/regionserver/MetricsRegionServer;
      52: return

  protected void chore();
    Code:
       0: invokestatic  #11                 // Method java/lang/System.nanoTime:()J
       3: lstore_1
       4: aload_0
       5: invokevirtual #12                 // Method _chore:()V
       8: aload_0
       9: getfield      #10                 // Field metrics:Lorg/apache/hadoop/hbase/regionserver/MetricsRegionServer;
      12: ifnull        70
      15: aload_0
      16: getfield      #10                 // Field metrics:Lorg/apache/hadoop/hbase/regionserver/MetricsRegionServer;
      19: getstatic     #13                 // Field java/util/concurrent/TimeUnit.MILLISECONDS:Ljava/util/concurrent/TimeUnit;
      22: invokestatic  #11                 // Method java/lang/System.nanoTime:()J
      25: lload_1
      26: lsub
      27: getstatic     #14                 // Field java/util/concurrent/TimeUnit.NANOSECONDS:Ljava/util/concurrent/TimeUnit;
      30: invokevirtual #15                 // Method java/util/concurrent/TimeUnit.convert:(JLjava/util/concurrent/TimeUnit;)J
      33: invokevirtual #16                 // Method org/apache/hadoop/hbase/regionserver/MetricsRegionServer.incrementRegionSizeReportingChoreTime:(J)V
      36: goto          70
      39: astore_3
      40: aload_0
      41: getfield      #10                 // Field metrics:Lorg/apache/hadoop/hbase/regionserver/MetricsRegionServer;
      44: ifnull        68
      47: aload_0
      48: getfield      #10                 // Field metrics:Lorg/apache/hadoop/hbase/regionserver/MetricsRegionServer;
      51: getstatic     #13                 // Field java/util/concurrent/TimeUnit.MILLISECONDS:Ljava/util/concurrent/TimeUnit;
      54: invokestatic  #11                 // Method java/lang/System.nanoTime:()J
      57: lload_1
      58: lsub
      59: getstatic     #14                 // Field java/util/concurrent/TimeUnit.NANOSECONDS:Ljava/util/concurrent/TimeUnit;
      62: invokevirtual #15                 // Method java/util/concurrent/TimeUnit.convert:(JLjava/util/concurrent/TimeUnit;)J
      65: invokevirtual #16                 // Method org/apache/hadoop/hbase/regionserver/MetricsRegionServer.incrementRegionSizeReportingChoreTime:(J)V
      68: aload_3
      69: athrow
      70: return
    Exception table:
       from    to  target type
           4     8    39   any

  void _chore();
    Code:
       0: aload_0
       1: getfield      #8                  // Field rsServices:Lorg/apache/hadoop/hbase/regionserver/RegionServerServices;
       4: invokeinterface #17,  1           // InterfaceMethod org/apache/hadoop/hbase/regionserver/RegionServerServices.getRegionServerSpaceQuotaManager:()Lorg/apache/hadoop/hbase/quotas/RegionServerSpaceQuotaManager;
       9: astore_1
      10: aload_0
      11: aload_0
      12: getfield      #8                  // Field rsServices:Lorg/apache/hadoop/hbase/regionserver/RegionServerServices;
      15: invokeinterface #18,  1           // InterfaceMethod org/apache/hadoop/hbase/regionserver/RegionServerServices.getRegions:()Ljava/util/List;
      20: invokevirtual #19                 // Method getOnlineRegionInfos:(Ljava/util/List;)Ljava/util/HashSet;
      23: astore_2
      24: aload_1
      25: invokevirtual #20                 // Method org/apache/hadoop/hbase/quotas/RegionServerSpaceQuotaManager.getRegionSizeStore:()Lorg/apache/hadoop/hbase/quotas/RegionSizeStore;
      28: astore_3
      29: aload_0
      30: aload_3
      31: aload_2
      32: invokevirtual #21                 // Method removeNonOnlineRegions:(Lorg/apache/hadoop/hbase/quotas/RegionSizeStore;Ljava/util/Set;)V
      35: aload_0
      36: getfield      #8                  // Field rsServices:Lorg/apache/hadoop/hbase/regionserver/RegionServerServices;
      39: aload_3
      40: invokeinterface #22,  2           // InterfaceMethod org/apache/hadoop/hbase/regionserver/RegionServerServices.reportRegionSizesForQuotas:(Lorg/apache/hadoop/hbase/quotas/RegionSizeStore;)Z
      45: pop
      46: return

  java.util.HashSet<org.apache.hadoop.hbase.client.RegionInfo> getOnlineRegionInfos(java.util.List<? extends org.apache.hadoop.hbase.regionserver.Region>);
    Code:
       0: new           #23                 // class java/util/HashSet
       3: dup
       4: invokespecial #24                 // Method java/util/HashSet."<init>":()V
       7: astore_2
       8: aload_1
       9: aload_2
      10: invokedynamic #25,  0             // InvokeDynamic #0:accept:(Ljava/util/HashSet;)Ljava/util/function/Consumer;
      15: invokeinterface #26,  2           // InterfaceMethod java/util/List.forEach:(Ljava/util/function/Consumer;)V
      20: aload_2
      21: areturn

  void removeNonOnlineRegions(org.apache.hadoop.hbase.quotas.RegionSizeStore, java.util.Set<org.apache.hadoop.hbase.client.RegionInfo>);
    Code:
       0: aload_2
       1: invokeinterface #27,  1           // InterfaceMethod java/util/Set.isEmpty:()Z
       6: ifeq          16
       9: aload_1
      10: invokeinterface #28,  1           // InterfaceMethod org/apache/hadoop/hbase/quotas/RegionSizeStore.clear:()V
      15: return
      16: aload_1
      17: invokeinterface #29,  1           // InterfaceMethod org/apache/hadoop/hbase/quotas/RegionSizeStore.iterator:()Ljava/util/Iterator;
      22: astore_3
      23: iconst_0
      24: istore        4
      26: aload_3
      27: invokeinterface #30,  1           // InterfaceMethod java/util/Iterator.hasNext:()Z
      32: ifeq          81
      35: aload_3
      36: invokeinterface #31,  1           // InterfaceMethod java/util/Iterator.next:()Ljava/lang/Object;
      41: checkcast     #32                 // class java/util/Map$Entry
      44: astore        5
      46: aload         5
      48: invokeinterface #33,  1           // InterfaceMethod java/util/Map$Entry.getKey:()Ljava/lang/Object;
      53: checkcast     #34                 // class org/apache/hadoop/hbase/client/RegionInfo
      56: astore        6
      58: aload_2
      59: aload         6
      61: invokeinterface #35,  2           // InterfaceMethod java/util/Set.contains:(Ljava/lang/Object;)Z
      66: ifne          78
      69: iinc          4, 1
      72: aload_3
      73: invokeinterface #36,  1           // InterfaceMethod java/util/Iterator.remove:()V
      78: goto          26
      81: getstatic     #37                 // Field LOG:Lorg/slf4j/Logger;
      84: invokeinterface #38,  1           // InterfaceMethod org/slf4j/Logger.isTraceEnabled:()Z
      89: ifeq          125
      92: getstatic     #37                 // Field LOG:Lorg/slf4j/Logger;
      95: new           #39                 // class java/lang/StringBuilder
      98: dup
      99: invokespecial #40                 // Method java/lang/StringBuilder."<init>":()V
     102: ldc           #41                 // String Removed
     104: invokevirtual #42                 // Method java/lang/StringBuilder.append:(Ljava/lang/String;)Ljava/lang/StringBuilder;
     107: iload         4
     109: invokevirtual #43                 // Method java/lang/StringBuilder.append:(I)Ljava/lang/StringBuilder;
     112: ldc           #44                 // String  region sizes before reporting to Master because they are for non-online regions.
     114: invokevirtual #42                 // Method java/lang/StringBuilder.append:(Ljava/lang/String;)Ljava/lang/StringBuilder;
     117: invokevirtual #45                 // Method java/lang/StringBuilder.toString:()Ljava/lang/String;
     120: invokeinterface #46,  2           // InterfaceMethod org/slf4j/Logger.trace:(Ljava/lang/String;)V
     125: return

  static int getPeriod(org.apache.hadoop.conf.Configuration);
    Code:
       0: aload_0
       1: ldc           #47                 // String hbase.regionserver.quotas.region.size.reporting.chore.period
       3: ldc           #48                 // int 60000
       5: invokevirtual #49                 // Method org/apache/hadoop/conf/Configuration.getInt:(Ljava/lang/String;I)I
       8: ireturn

  static long getInitialDelay(org.apache.hadoop.conf.Configuration);
    Code:
       0: aload_0
       1: ldc           #50                 // String hbase.regionserver.quotas.region.size.reporting.chore.delay
       3: ldc2_w        #51                 // long 30000l
       6: invokevirtual #53                 // Method org/apache/hadoop/conf/Configuration.getLong:(Ljava/lang/String;J)J
       9: lreturn

  static java.util.concurrent.TimeUnit getTimeUnit(org.apache.hadoop.conf.Configuration);
    Code:
       0: aload_0
       1: ldc           #54                 // String hbase.regionserver.quotas.region.size.reporting.chore.timeunit
       3: getstatic     #55                 // Field REGION_SIZE_REPORTING_CHORE_TIMEUNIT_DEFAULT:Ljava/lang/String;
       6: invokevirtual #56                 // Method org/apache/hadoop/conf/Configuration.get:(Ljava/lang/String;Ljava/lang/String;)Ljava/lang/String;
       9: invokestatic  #57                 // Method java/util/concurrent/TimeUnit.valueOf:(Ljava/lang/String;)Ljava/util/concurrent/TimeUnit;
      12: areturn

  static {};
    Code:
       0: ldc           #1                  // class org/apache/hadoop/hbase/quotas/RegionSizeReportingChore
       2: invokestatic  #60                 // Method org/slf4j/LoggerFactory.getLogger:(Ljava/lang/Class;)Lorg/slf4j/Logger;
       5: putstatic     #37                 // Field LOG:Lorg/slf4j/Logger;
       8: getstatic     #13                 // Field java/util/concurrent/TimeUnit.MILLISECONDS:Ljava/util/concurrent/TimeUnit;
      11: invokevirtual #61                 // Method java/util/concurrent/TimeUnit.name:()Ljava/lang/String;
      14: putstatic     #55                 // Field REGION_SIZE_REPORTING_CHORE_TIMEUNIT_DEFAULT:Ljava/lang/String;
      17: return
}
