Compiled from "RegionAsTable.java"
class org.apache.hadoop.hbase.regionserver.RegionAsTable$RegionScannerToResultScannerAdaptor implements org.apache.hadoop.hbase.client.ResultScanner {
  org.apache.hadoop.hbase.regionserver.RegionAsTable$RegionScannerToResultScannerAdaptor(org.apache.hadoop.hbase.regionserver.RegionScanner);
    Code:
       0: aload_0
       1: invokespecial #1                  // Method java/lang/Object."<init>":()V
       4: aload_0
       5: aload_1
       6: putfield      #2                  // Field regionScanner:Lorg/apache/hadoop/hbase/regionserver/RegionScanner;
       9: return

  public java.util.Iterator<org.apache.hadoop.hbase.client.Result> iterator();
    Code:
       0: new           #3                  // class java/lang/UnsupportedOperationException
       3: dup
       4: invokespecial #4                  // Method java/lang/UnsupportedOperationException."<init>":()V
       7: athrow

  public org.apache.hadoop.hbase.client.Result next() throws java.io.IOException;
    Code:
       0: new           #5                  // class java/util/ArrayList
       3: dup
       4: invokespecial #6                  // Method java/util/ArrayList."<init>":()V
       7: astore_1
       8: aload_0
       9: getfield      #2                  // Field regionScanner:Lorg/apache/hadoop/hbase/regionserver/RegionScanner;
      12: aload_1
      13: invokeinterface #7,  2            // InterfaceMethod org/apache/hadoop/hbase/regionserver/RegionScanner.next:(Ljava/util/List;)Z
      18: ifeq          28
      21: aload_1
      22: invokestatic  #8                  // Method org/apache/hadoop/hbase/client/Result.create:(Ljava/util/List;)Lorg/apache/hadoop/hbase/client/Result;
      25: goto          29
      28: aconst_null
      29: areturn

  public org.apache.hadoop.hbase.client.Result[] next(int) throws java.io.IOException;
    Code:
       0: new           #5                  // class java/util/ArrayList
       3: dup
       4: iload_1
       5: invokespecial #9                  // Method java/util/ArrayList."<init>":(I)V
       8: astore_2
       9: iconst_0
      10: istore_3
      11: iload_3
      12: iload_1
      13: if_icmpge     45
      16: aload_0
      17: invokevirtual #10                 // Method next:()Lorg/apache/hadoop/hbase/client/Result;
      20: astore        4
      22: aload         4
      24: ifnonnull     30
      27: goto          45
      30: aload_2
      31: aload         4
      33: invokeinterface #11,  2           // InterfaceMethod java/util/List.add:(Ljava/lang/Object;)Z
      38: pop
      39: iinc          3, 1
      42: goto          11
      45: aload_2
      46: getstatic     #12                 // Field EMPTY_RESULT_ARRAY:[Lorg/apache/hadoop/hbase/client/Result;
      49: invokeinterface #13,  2           // InterfaceMethod java/util/List.toArray:([Ljava/lang/Object;)[Ljava/lang/Object;
      54: checkcast     #14                 // class "[Lorg/apache/hadoop/hbase/client/Result;"
      57: areturn

  public void close();
    Code:
       0: aload_0
       1: getfield      #2                  // Field regionScanner:Lorg/apache/hadoop/hbase/regionserver/RegionScanner;
       4: invokeinterface #15,  1           // InterfaceMethod org/apache/hadoop/hbase/regionserver/RegionScanner.close:()V
       9: goto          22
      12: astore_1
      13: new           #17                 // class java/lang/RuntimeException
      16: dup
      17: aload_1
      18: invokespecial #18                 // Method java/lang/RuntimeException."<init>":(Ljava/lang/Throwable;)V
      21: athrow
      22: return
    Exception table:
       from    to  target type
           0     9    12   Class java/io/IOException

  public boolean renewLease();
    Code:
       0: new           #3                  // class java/lang/UnsupportedOperationException
       3: dup
       4: invokespecial #4                  // Method java/lang/UnsupportedOperationException."<init>":()V
       7: athrow

  public org.apache.hadoop.hbase.client.metrics.ScanMetrics getScanMetrics();
    Code:
       0: new           #3                  // class java/lang/UnsupportedOperationException
       3: dup
       4: invokespecial #4                  // Method java/lang/UnsupportedOperationException."<init>":()V
       7: athrow

  static {};
    Code:
       0: iconst_0
       1: anewarray     #19                 // class org/apache/hadoop/hbase/client/Result
       4: putstatic     #12                 // Field EMPTY_RESULT_ARRAY:[Lorg/apache/hadoop/hbase/client/Result;
       7: return
}
