Compiled from "RegionServerStatusProtos.java"
final class org.apache.hadoop.hbase.shaded.protobuf.generated.RegionServerStatusProtos$RegionServerStatusService$2 implements org.apache.hbase.thirdparty.com.google.protobuf.BlockingService {
  final org.apache.hadoop.hbase.shaded.protobuf.generated.RegionServerStatusProtos$RegionServerStatusService$BlockingInterface val$impl;

  org.apache.hadoop.hbase.shaded.protobuf.generated.RegionServerStatusProtos$RegionServerStatusService$2(org.apache.hadoop.hbase.shaded.protobuf.generated.RegionServerStatusProtos$RegionServerStatusService$BlockingInterface);
    Code:
       0: aload_0
       1: aload_1
       2: putfield      #1                  // Field val$impl:Lorg/apache/hadoop/hbase/shaded/protobuf/generated/RegionServerStatusProtos$RegionServerStatusService$BlockingInterface;
       5: aload_0
       6: invokespecial #2                  // Method java/lang/Object."<init>":()V
       9: return

  public final org.apache.hbase.thirdparty.com.google.protobuf.Descriptors$ServiceDescriptor getDescriptorForType();
    Code:
       0: invokestatic  #3                  // Method org/apache/hadoop/hbase/shaded/protobuf/generated/RegionServerStatusProtos$RegionServerStatusService.getDescriptor:()Lorg/apache/hbase/thirdparty/com/google/protobuf/Descriptors$ServiceDescriptor;
       3: areturn

  public final org.apache.hbase.thirdparty.com.google.protobuf.Message callBlockingMethod(org.apache.hbase.thirdparty.com.google.protobuf.Descriptors$MethodDescriptor, org.apache.hbase.thirdparty.com.google.protobuf.RpcController, org.apache.hbase.thirdparty.com.google.protobuf.Message) throws org.apache.hbase.thirdparty.com.google.protobuf.ServiceException;
    Code:
       0: aload_1
       1: invokevirtual #4                  // Method org/apache/hbase/thirdparty/com/google/protobuf/Descriptors$MethodDescriptor.getService:()Lorg/apache/hbase/thirdparty/com/google/protobuf/Descriptors$ServiceDescriptor;
       4: invokestatic  #3                  // Method org/apache/hadoop/hbase/shaded/protobuf/generated/RegionServerStatusProtos$RegionServerStatusService.getDescriptor:()Lorg/apache/hbase/thirdparty/com/google/protobuf/Descriptors$ServiceDescriptor;
       7: if_acmpeq     20
      10: new           #5                  // class java/lang/IllegalArgumentException
      13: dup
      14: ldc           #6                  // String Service.callBlockingMethod() given method descriptor for wrong service type.
      16: invokespecial #7                  // Method java/lang/IllegalArgumentException."<init>":(Ljava/lang/String;)V
      19: athrow
      20: aload_1
      21: invokevirtual #8                  // Method org/apache/hbase/thirdparty/com/google/protobuf/Descriptors$MethodDescriptor.getIndex:()I
      24: tableswitch   { // 0 to 7
                     0: 72
                     1: 87
                     2: 102
                     3: 117
                     4: 132
                     5: 147
                     6: 162
                     7: 177
               default: 192
          }
      72: aload_0
      73: getfield      #1                  // Field val$impl:Lorg/apache/hadoop/hbase/shaded/protobuf/generated/RegionServerStatusProtos$RegionServerStatusService$BlockingInterface;
      76: aload_2
      77: aload_3
      78: checkcast     #9                  // class org/apache/hadoop/hbase/shaded/protobuf/generated/RegionServerStatusProtos$RegionServerStartupRequest
      81: invokeinterface #10,  3           // InterfaceMethod org/apache/hadoop/hbase/shaded/protobuf/generated/RegionServerStatusProtos$RegionServerStatusService$BlockingInterface.regionServerStartup:(Lorg/apache/hbase/thirdparty/com/google/protobuf/RpcController;Lorg/apache/hadoop/hbase/shaded/protobuf/generated/RegionServerStatusProtos$RegionServerStartupRequest;)Lorg/apache/hadoop/hbase/shaded/protobuf/generated/RegionServerStatusProtos$RegionServerStartupResponse;
      86: areturn
      87: aload_0
      88: getfield      #1                  // Field val$impl:Lorg/apache/hadoop/hbase/shaded/protobuf/generated/RegionServerStatusProtos$RegionServerStatusService$BlockingInterface;
      91: aload_2
      92: aload_3
      93: checkcast     #11                 // class org/apache/hadoop/hbase/shaded/protobuf/generated/RegionServerStatusProtos$RegionServerReportRequest
      96: invokeinterface #12,  3           // InterfaceMethod org/apache/hadoop/hbase/shaded/protobuf/generated/RegionServerStatusProtos$RegionServerStatusService$BlockingInterface.regionServerReport:(Lorg/apache/hbase/thirdparty/com/google/protobuf/RpcController;Lorg/apache/hadoop/hbase/shaded/protobuf/generated/RegionServerStatusProtos$RegionServerReportRequest;)Lorg/apache/hadoop/hbase/shaded/protobuf/generated/RegionServerStatusProtos$RegionServerReportResponse;
     101: areturn
     102: aload_0
     103: getfield      #1                  // Field val$impl:Lorg/apache/hadoop/hbase/shaded/protobuf/generated/RegionServerStatusProtos$RegionServerStatusService$BlockingInterface;
     106: aload_2
     107: aload_3
     108: checkcast     #13                 // class org/apache/hadoop/hbase/shaded/protobuf/generated/RegionServerStatusProtos$ReportRSFatalErrorRequest
     111: invokeinterface #14,  3           // InterfaceMethod org/apache/hadoop/hbase/shaded/protobuf/generated/RegionServerStatusProtos$RegionServerStatusService$BlockingInterface.reportRSFatalError:(Lorg/apache/hbase/thirdparty/com/google/protobuf/RpcController;Lorg/apache/hadoop/hbase/shaded/protobuf/generated/RegionServerStatusProtos$ReportRSFatalErrorRequest;)Lorg/apache/hadoop/hbase/shaded/protobuf/generated/RegionServerStatusProtos$ReportRSFatalErrorResponse;
     116: areturn
     117: aload_0
     118: getfield      #1                  // Field val$impl:Lorg/apache/hadoop/hbase/shaded/protobuf/generated/RegionServerStatusProtos$RegionServerStatusService$BlockingInterface;
     121: aload_2
     122: aload_3
     123: checkcast     #15                 // class org/apache/hadoop/hbase/shaded/protobuf/generated/RegionServerStatusProtos$GetLastFlushedSequenceIdRequest
     126: invokeinterface #16,  3           // InterfaceMethod org/apache/hadoop/hbase/shaded/protobuf/generated/RegionServerStatusProtos$RegionServerStatusService$BlockingInterface.getLastFlushedSequenceId:(Lorg/apache/hbase/thirdparty/com/google/protobuf/RpcController;Lorg/apache/hadoop/hbase/shaded/protobuf/generated/RegionServerStatusProtos$GetLastFlushedSequenceIdRequest;)Lorg/apache/hadoop/hbase/shaded/protobuf/generated/RegionServerStatusProtos$GetLastFlushedSequenceIdResponse;
     131: areturn
     132: aload_0
     133: getfield      #1                  // Field val$impl:Lorg/apache/hadoop/hbase/shaded/protobuf/generated/RegionServerStatusProtos$RegionServerStatusService$BlockingInterface;
     136: aload_2
     137: aload_3
     138: checkcast     #17                 // class org/apache/hadoop/hbase/shaded/protobuf/generated/RegionServerStatusProtos$ReportRegionStateTransitionRequest
     141: invokeinterface #18,  3           // InterfaceMethod org/apache/hadoop/hbase/shaded/protobuf/generated/RegionServerStatusProtos$RegionServerStatusService$BlockingInterface.reportRegionStateTransition:(Lorg/apache/hbase/thirdparty/com/google/protobuf/RpcController;Lorg/apache/hadoop/hbase/shaded/protobuf/generated/RegionServerStatusProtos$ReportRegionStateTransitionRequest;)Lorg/apache/hadoop/hbase/shaded/protobuf/generated/RegionServerStatusProtos$ReportRegionStateTransitionResponse;
     146: areturn
     147: aload_0
     148: getfield      #1                  // Field val$impl:Lorg/apache/hadoop/hbase/shaded/protobuf/generated/RegionServerStatusProtos$RegionServerStatusService$BlockingInterface;
     151: aload_2
     152: aload_3
     153: checkcast     #19                 // class org/apache/hadoop/hbase/shaded/protobuf/generated/RegionServerStatusProtos$RegionSpaceUseReportRequest
     156: invokeinterface #20,  3           // InterfaceMethod org/apache/hadoop/hbase/shaded/protobuf/generated/RegionServerStatusProtos$RegionServerStatusService$BlockingInterface.reportRegionSpaceUse:(Lorg/apache/hbase/thirdparty/com/google/protobuf/RpcController;Lorg/apache/hadoop/hbase/shaded/protobuf/generated/RegionServerStatusProtos$RegionSpaceUseReportRequest;)Lorg/apache/hadoop/hbase/shaded/protobuf/generated/RegionServerStatusProtos$RegionSpaceUseReportResponse;
     161: areturn
     162: aload_0
     163: getfield      #1                  // Field val$impl:Lorg/apache/hadoop/hbase/shaded/protobuf/generated/RegionServerStatusProtos$RegionServerStatusService$BlockingInterface;
     166: aload_2
     167: aload_3
     168: checkcast     #21                 // class org/apache/hadoop/hbase/shaded/protobuf/generated/RegionServerStatusProtos$ReportProcedureDoneRequest
     171: invokeinterface #22,  3           // InterfaceMethod org/apache/hadoop/hbase/shaded/protobuf/generated/RegionServerStatusProtos$RegionServerStatusService$BlockingInterface.reportProcedureDone:(Lorg/apache/hbase/thirdparty/com/google/protobuf/RpcController;Lorg/apache/hadoop/hbase/shaded/protobuf/generated/RegionServerStatusProtos$ReportProcedureDoneRequest;)Lorg/apache/hadoop/hbase/shaded/protobuf/generated/RegionServerStatusProtos$ReportProcedureDoneResponse;
     176: areturn
     177: aload_0
     178: getfield      #1                  // Field val$impl:Lorg/apache/hadoop/hbase/shaded/protobuf/generated/RegionServerStatusProtos$RegionServerStatusService$BlockingInterface;
     181: aload_2
     182: aload_3
     183: checkcast     #23                 // class org/apache/hadoop/hbase/shaded/protobuf/generated/RegionServerStatusProtos$FileArchiveNotificationRequest
     186: invokeinterface #24,  3           // InterfaceMethod org/apache/hadoop/hbase/shaded/protobuf/generated/RegionServerStatusProtos$RegionServerStatusService$BlockingInterface.reportFileArchival:(Lorg/apache/hbase/thirdparty/com/google/protobuf/RpcController;Lorg/apache/hadoop/hbase/shaded/protobuf/generated/RegionServerStatusProtos$FileArchiveNotificationRequest;)Lorg/apache/hadoop/hbase/shaded/protobuf/generated/RegionServerStatusProtos$FileArchiveNotificationResponse;
     191: areturn
     192: new           #25                 // class java/lang/AssertionError
     195: dup
     196: ldc           #26                 // String Can't get here.
     198: invokespecial #27                 // Method java/lang/AssertionError."<init>":(Ljava/lang/Object;)V
     201: athrow

  public final org.apache.hbase.thirdparty.com.google.protobuf.Message getRequestPrototype(org.apache.hbase.thirdparty.com.google.protobuf.Descriptors$MethodDescriptor);
    Code:
       0: aload_1
       1: invokevirtual #4                  // Method org/apache/hbase/thirdparty/com/google/protobuf/Descriptors$MethodDescriptor.getService:()Lorg/apache/hbase/thirdparty/com/google/protobuf/Descriptors$ServiceDescriptor;
       4: invokestatic  #3                  // Method org/apache/hadoop/hbase/shaded/protobuf/generated/RegionServerStatusProtos$RegionServerStatusService.getDescriptor:()Lorg/apache/hbase/thirdparty/com/google/protobuf/Descriptors$ServiceDescriptor;
       7: if_acmpeq     20
      10: new           #5                  // class java/lang/IllegalArgumentException
      13: dup
      14: ldc           #28                 // String Service.getRequestPrototype() given method descriptor for wrong service type.
      16: invokespecial #7                  // Method java/lang/IllegalArgumentException."<init>":(Ljava/lang/String;)V
      19: athrow
      20: aload_1
      21: invokevirtual #8                  // Method org/apache/hbase/thirdparty/com/google/protobuf/Descriptors$MethodDescriptor.getIndex:()I
      24: tableswitch   { // 0 to 7
                     0: 72
                     1: 76
                     2: 80
                     3: 84
                     4: 88
                     5: 92
                     6: 96
                     7: 100
               default: 104
          }
      72: invokestatic  #29                 // Method org/apache/hadoop/hbase/shaded/protobuf/generated/RegionServerStatusProtos$RegionServerStartupRequest.getDefaultInstance:()Lorg/apache/hadoop/hbase/shaded/protobuf/generated/RegionServerStatusProtos$RegionServerStartupRequest;
      75: areturn
      76: invokestatic  #30                 // Method org/apache/hadoop/hbase/shaded/protobuf/generated/RegionServerStatusProtos$RegionServerReportRequest.getDefaultInstance:()Lorg/apache/hadoop/hbase/shaded/protobuf/generated/RegionServerStatusProtos$RegionServerReportRequest;
      79: areturn
      80: invokestatic  #31                 // Method org/apache/hadoop/hbase/shaded/protobuf/generated/RegionServerStatusProtos$ReportRSFatalErrorRequest.getDefaultInstance:()Lorg/apache/hadoop/hbase/shaded/protobuf/generated/RegionServerStatusProtos$ReportRSFatalErrorRequest;
      83: areturn
      84: invokestatic  #32                 // Method org/apache/hadoop/hbase/shaded/protobuf/generated/RegionServerStatusProtos$GetLastFlushedSequenceIdRequest.getDefaultInstance:()Lorg/apache/hadoop/hbase/shaded/protobuf/generated/RegionServerStatusProtos$GetLastFlushedSequenceIdRequest;
      87: areturn
      88: invokestatic  #33                 // Method org/apache/hadoop/hbase/shaded/protobuf/generated/RegionServerStatusProtos$ReportRegionStateTransitionRequest.getDefaultInstance:()Lorg/apache/hadoop/hbase/shaded/protobuf/generated/RegionServerStatusProtos$ReportRegionStateTransitionRequest;
      91: areturn
      92: invokestatic  #34                 // Method org/apache/hadoop/hbase/shaded/protobuf/generated/RegionServerStatusProtos$RegionSpaceUseReportRequest.getDefaultInstance:()Lorg/apache/hadoop/hbase/shaded/protobuf/generated/RegionServerStatusProtos$RegionSpaceUseReportRequest;
      95: areturn
      96: invokestatic  #35                 // Method org/apache/hadoop/hbase/shaded/protobuf/generated/RegionServerStatusProtos$ReportProcedureDoneRequest.getDefaultInstance:()Lorg/apache/hadoop/hbase/shaded/protobuf/generated/RegionServerStatusProtos$ReportProcedureDoneRequest;
      99: areturn
     100: invokestatic  #36                 // Method org/apache/hadoop/hbase/shaded/protobuf/generated/RegionServerStatusProtos$FileArchiveNotificationRequest.getDefaultInstance:()Lorg/apache/hadoop/hbase/shaded/protobuf/generated/RegionServerStatusProtos$FileArchiveNotificationRequest;
     103: areturn
     104: new           #25                 // class java/lang/AssertionError
     107: dup
     108: ldc           #26                 // String Can't get here.
     110: invokespecial #27                 // Method java/lang/AssertionError."<init>":(Ljava/lang/Object;)V
     113: athrow

  public final org.apache.hbase.thirdparty.com.google.protobuf.Message getResponsePrototype(org.apache.hbase.thirdparty.com.google.protobuf.Descriptors$MethodDescriptor);
    Code:
       0: aload_1
       1: invokevirtual #4                  // Method org/apache/hbase/thirdparty/com/google/protobuf/Descriptors$MethodDescriptor.getService:()Lorg/apache/hbase/thirdparty/com/google/protobuf/Descriptors$ServiceDescriptor;
       4: invokestatic  #3                  // Method org/apache/hadoop/hbase/shaded/protobuf/generated/RegionServerStatusProtos$RegionServerStatusService.getDescriptor:()Lorg/apache/hbase/thirdparty/com/google/protobuf/Descriptors$ServiceDescriptor;
       7: if_acmpeq     20
      10: new           #5                  // class java/lang/IllegalArgumentException
      13: dup
      14: ldc           #37                 // String Service.getResponsePrototype() given method descriptor for wrong service type.
      16: invokespecial #7                  // Method java/lang/IllegalArgumentException."<init>":(Ljava/lang/String;)V
      19: athrow
      20: aload_1
      21: invokevirtual #8                  // Method org/apache/hbase/thirdparty/com/google/protobuf/Descriptors$MethodDescriptor.getIndex:()I
      24: tableswitch   { // 0 to 7
                     0: 72
                     1: 76
                     2: 80
                     3: 84
                     4: 88
                     5: 92
                     6: 96
                     7: 100
               default: 104
          }
      72: invokestatic  #38                 // Method org/apache/hadoop/hbase/shaded/protobuf/generated/RegionServerStatusProtos$RegionServerStartupResponse.getDefaultInstance:()Lorg/apache/hadoop/hbase/shaded/protobuf/generated/RegionServerStatusProtos$RegionServerStartupResponse;
      75: areturn
      76: invokestatic  #39                 // Method org/apache/hadoop/hbase/shaded/protobuf/generated/RegionServerStatusProtos$RegionServerReportResponse.getDefaultInstance:()Lorg/apache/hadoop/hbase/shaded/protobuf/generated/RegionServerStatusProtos$RegionServerReportResponse;
      79: areturn
      80: invokestatic  #40                 // Method org/apache/hadoop/hbase/shaded/protobuf/generated/RegionServerStatusProtos$ReportRSFatalErrorResponse.getDefaultInstance:()Lorg/apache/hadoop/hbase/shaded/protobuf/generated/RegionServerStatusProtos$ReportRSFatalErrorResponse;
      83: areturn
      84: invokestatic  #41                 // Method org/apache/hadoop/hbase/shaded/protobuf/generated/RegionServerStatusProtos$GetLastFlushedSequenceIdResponse.getDefaultInstance:()Lorg/apache/hadoop/hbase/shaded/protobuf/generated/RegionServerStatusProtos$GetLastFlushedSequenceIdResponse;
      87: areturn
      88: invokestatic  #42                 // Method org/apache/hadoop/hbase/shaded/protobuf/generated/RegionServerStatusProtos$ReportRegionStateTransitionResponse.getDefaultInstance:()Lorg/apache/hadoop/hbase/shaded/protobuf/generated/RegionServerStatusProtos$ReportRegionStateTransitionResponse;
      91: areturn
      92: invokestatic  #43                 // Method org/apache/hadoop/hbase/shaded/protobuf/generated/RegionServerStatusProtos$RegionSpaceUseReportResponse.getDefaultInstance:()Lorg/apache/hadoop/hbase/shaded/protobuf/generated/RegionServerStatusProtos$RegionSpaceUseReportResponse;
      95: areturn
      96: invokestatic  #44                 // Method org/apache/hadoop/hbase/shaded/protobuf/generated/RegionServerStatusProtos$ReportProcedureDoneResponse.getDefaultInstance:()Lorg/apache/hadoop/hbase/shaded/protobuf/generated/RegionServerStatusProtos$ReportProcedureDoneResponse;
      99: areturn
     100: invokestatic  #45                 // Method org/apache/hadoop/hbase/shaded/protobuf/generated/RegionServerStatusProtos$FileArchiveNotificationResponse.getDefaultInstance:()Lorg/apache/hadoop/hbase/shaded/protobuf/generated/RegionServerStatusProtos$FileArchiveNotificationResponse;
     103: areturn
     104: new           #25                 // class java/lang/AssertionError
     107: dup
     108: ldc           #26                 // String Can't get here.
     110: invokespecial #27                 // Method java/lang/AssertionError."<init>":(Ljava/lang/Object;)V
     113: athrow
}
