Compiled from "RegionListTmpl.java"
public class org.apache.hadoop.hbase.tmpl.regionserver.RegionListTmpl$ImplData extends org.jamon.AbstractTemplateProxy$ImplData {
  public org.apache.hadoop.hbase.tmpl.regionserver.RegionListTmpl$ImplData();
    Code:
       0: aload_0
       1: invokespecial #1                  // Method org/jamon/AbstractTemplateProxy$ImplData."<init>":()V
       4: return

  public void setRegionServer(org.apache.hadoop.hbase.regionserver.HRegionServer);
    Code:
       0: aload_0
       1: aload_1
       2: putfield      #2                  // Field m_regionServer:Lorg/apache/hadoop/hbase/regionserver/HRegionServer;
       5: return

  public org.apache.hadoop.hbase.regionserver.HRegionServer getRegionServer();
    Code:
       0: aload_0
       1: getfield      #2                  // Field m_regionServer:Lorg/apache/hadoop/hbase/regionserver/HRegionServer;
       4: areturn

  public void setOnlineRegions(java.util.List<org.apache.hadoop.hbase.client.RegionInfo>);
    Code:
       0: aload_0
       1: aload_1
       2: putfield      #3                  // Field m_onlineRegions:Ljava/util/List;
       5: return

  public java.util.List<org.apache.hadoop.hbase.client.RegionInfo> getOnlineRegions();
    Code:
       0: aload_0
       1: getfield      #3                  // Field m_onlineRegions:Ljava/util/List;
       4: areturn
}
