Compiled from "RegionServerTracker.java"
public class org.apache.hadoop.hbase.master.RegionServerTracker extends org.apache.hadoop.hbase.zookeeper.ZKListener {
  public org.apache.hadoop.hbase.master.RegionServerTracker(org.apache.hadoop.hbase.zookeeper.ZKWatcher, org.apache.hadoop.hbase.master.MasterServices, org.apache.hadoop.hbase.master.ServerManager);
    Code:
       0: aload_0
       1: aload_1
       2: invokespecial #1                  // Method org/apache/hadoop/hbase/zookeeper/ZKListener."<init>":(Lorg/apache/hadoop/hbase/zookeeper/ZKWatcher;)V
       5: aload_0
       6: new           #2                  // class java/util/HashSet
       9: dup
      10: invokespecial #3                  // Method java/util/HashSet."<init>":()V
      13: putfield      #4                  // Field regionServers:Ljava/util/Set;
      16: aload_0
      17: aload_2
      18: putfield      #5                  // Field server:Lorg/apache/hadoop/hbase/master/MasterServices;
      21: aload_0
      22: aload_3
      23: putfield      #6                  // Field serverManager:Lorg/apache/hadoop/hbase/master/ServerManager;
      26: aload_0
      27: new           #7                  // class org/apache/hbase/thirdparty/com/google/common/util/concurrent/ThreadFactoryBuilder
      30: dup
      31: invokespecial #8                  // Method org/apache/hbase/thirdparty/com/google/common/util/concurrent/ThreadFactoryBuilder."<init>":()V
      34: iconst_1
      35: invokevirtual #9                  // Method org/apache/hbase/thirdparty/com/google/common/util/concurrent/ThreadFactoryBuilder.setDaemon:(Z)Lorg/apache/hbase/thirdparty/com/google/common/util/concurrent/ThreadFactoryBuilder;
      38: ldc           #10                 // String RegionServerTracker-%d
      40: invokevirtual #11                 // Method org/apache/hbase/thirdparty/com/google/common/util/concurrent/ThreadFactoryBuilder.setNameFormat:(Ljava/lang/String;)Lorg/apache/hbase/thirdparty/com/google/common/util/concurrent/ThreadFactoryBuilder;
      43: invokevirtual #12                 // Method org/apache/hbase/thirdparty/com/google/common/util/concurrent/ThreadFactoryBuilder.build:()Ljava/util/concurrent/ThreadFactory;
      46: invokestatic  #13                 // Method java/util/concurrent/Executors.newSingleThreadExecutor:(Ljava/util/concurrent/ThreadFactory;)Ljava/util/concurrent/ExecutorService;
      49: putfield      #14                 // Field executor:Ljava/util/concurrent/ExecutorService;
      52: return

  public void start(java.util.Set<org.apache.hadoop.hbase.ServerName>, java.util.Set<org.apache.hadoop.hbase.ServerName>, java.util.Set<org.apache.hadoop.hbase.ServerName>) throws org.apache.zookeeper.KeeperException, java.io.IOException;
    Code:
       0: getstatic     #25                 // Field LOG:Lorg/slf4j/Logger;
       3: ldc           #37                 // String Starting RegionServerTracker; {} have existing ServerCrashProcedures, {} possibly 'live' servers, and {} 'splitting'.
       5: iconst_3
       6: anewarray     #38                 // class java/lang/Object
       9: dup
      10: iconst_0
      11: aload_1
      12: invokeinterface #39,  1           // InterfaceMethod java/util/Set.size:()I
      17: invokestatic  #31                 // Method java/lang/Integer.valueOf:(I)Ljava/lang/Integer;
      20: aastore
      21: dup
      22: iconst_1
      23: aload_2
      24: invokeinterface #39,  1           // InterfaceMethod java/util/Set.size:()I
      29: invokestatic  #31                 // Method java/lang/Integer.valueOf:(I)Ljava/lang/Integer;
      32: aastore
      33: dup
      34: iconst_2
      35: aload_3
      36: invokeinterface #39,  1           // InterfaceMethod java/util/Set.size:()I
      41: invokestatic  #31                 // Method java/lang/Integer.valueOf:(I)Ljava/lang/Integer;
      44: aastore
      45: invokeinterface #40,  3           // InterfaceMethod org/slf4j/Logger.info:(Ljava/lang/String;[Ljava/lang/Object;)V
      50: aload_3
      51: invokeinterface #41,  1           // InterfaceMethod java/util/Set.stream:()Ljava/util/stream/Stream;
      56: aload_1
      57: invokedynamic #42,  0             // InvokeDynamic #0:test:(Ljava/util/Set;)Ljava/util/function/Predicate;
      62: invokeinterface #43,  2           // InterfaceMethod java/util/stream/Stream.filter:(Ljava/util/function/Predicate;)Ljava/util/stream/Stream;
      67: invokedynamic #44,  0             // InvokeDynamic #1:accept:()Ljava/util/function/Consumer;
      72: invokeinterface #45,  2           // InterfaceMethod java/util/stream/Stream.forEach:(Ljava/util/function/Consumer;)V
      77: aload_2
      78: invokeinterface #41,  1           // InterfaceMethod java/util/Set.stream:()Ljava/util/stream/Stream;
      83: aload_0
      84: invokedynamic #46,  0             // InvokeDynamic #2:accept:(Lorg/apache/hadoop/hbase/master/RegionServerTracker;)Ljava/util/function/Consumer;
      89: invokeinterface #45,  2           // InterfaceMethod java/util/stream/Stream.forEach:(Ljava/util/function/Consumer;)V
      94: aload_0
      95: getfield      #16                 // Field watcher:Lorg/apache/hadoop/hbase/zookeeper/ZKWatcher;
      98: aload_0
      99: invokevirtual #47                 // Method org/apache/hadoop/hbase/zookeeper/ZKWatcher.registerListener:(Lorg/apache/hadoop/hbase/zookeeper/ZKListener;)V
     102: aload_0
     103: dup
     104: astore        4
     106: monitorenter
     107: aload_0
     108: getfield      #16                 // Field watcher:Lorg/apache/hadoop/hbase/zookeeper/ZKWatcher;
     111: aload_0
     112: getfield      #16                 // Field watcher:Lorg/apache/hadoop/hbase/zookeeper/ZKWatcher;
     115: invokevirtual #17                 // Method org/apache/hadoop/hbase/zookeeper/ZKWatcher.getZNodePaths:()Lorg/apache/hadoop/hbase/zookeeper/ZNodePaths;
     118: getfield      #18                 // Field org/apache/hadoop/hbase/zookeeper/ZNodePaths.rsZNode:Ljava/lang/String;
     121: invokestatic  #48                 // Method org/apache/hadoop/hbase/zookeeper/ZKUtil.listChildrenAndWatchForNewChildren:(Lorg/apache/hadoop/hbase/zookeeper/ZKWatcher;Ljava/lang/String;)Ljava/util/List;
     124: astore        5
     126: aload         5
     128: invokeinterface #49,  1           // InterfaceMethod java/util/List.iterator:()Ljava/util/Iterator;
     133: astore        6
     135: aload         6
     137: invokeinterface #50,  1           // InterfaceMethod java/util/Iterator.hasNext:()Z
     142: ifeq          248
     145: aload         6
     147: invokeinterface #51,  1           // InterfaceMethod java/util/Iterator.next:()Ljava/lang/Object;
     152: checkcast     #52                 // class java/lang/String
     155: astore        7
     157: aload_0
     158: aload         7
     160: invokespecial #53                 // Method getServerInfo:(Ljava/lang/String;)Lorg/apache/hadoop/hbase/util/Pair;
     163: astore        8
     165: aload         8
     167: invokevirtual #54                 // Method org/apache/hadoop/hbase/util/Pair.getFirst:()Ljava/lang/Object;
     170: checkcast     #55                 // class org/apache/hadoop/hbase/ServerName
     173: astore        9
     175: aload         8
     177: invokevirtual #56                 // Method org/apache/hadoop/hbase/util/Pair.getSecond:()Ljava/lang/Object;
     180: checkcast     #57                 // class org/apache/hadoop/hbase/shaded/protobuf/generated/HBaseProtos$RegionServerInfo
     183: astore        10
     185: aload_0
     186: getfield      #4                  // Field regionServers:Ljava/util/Set;
     189: aload         9
     191: invokeinterface #58,  2           // InterfaceMethod java/util/Set.add:(Ljava/lang/Object;)Z
     196: pop
     197: aload         10
     199: ifnull        226
     202: aload         9
     204: aload         10
     206: invokevirtual #59                 // Method org/apache/hadoop/hbase/shaded/protobuf/generated/HBaseProtos$RegionServerInfo.getVersionInfo:()Lorg/apache/hadoop/hbase/shaded/protobuf/generated/HBaseProtos$VersionInfo;
     209: invokestatic  #60                 // Method org/apache/hadoop/hbase/client/VersionInfoUtil.getVersionNumber:(Lorg/apache/hadoop/hbase/shaded/protobuf/generated/HBaseProtos$VersionInfo;)I
     212: aload         10
     214: invokevirtual #59                 // Method org/apache/hadoop/hbase/shaded/protobuf/generated/HBaseProtos$RegionServerInfo.getVersionInfo:()Lorg/apache/hadoop/hbase/shaded/protobuf/generated/HBaseProtos$VersionInfo;
     217: invokevirtual #61                 // Method org/apache/hadoop/hbase/shaded/protobuf/generated/HBaseProtos$VersionInfo.getVersion:()Ljava/lang/String;
     220: invokestatic  #62                 // Method org/apache/hadoop/hbase/ServerMetricsBuilder.of:(Lorg/apache/hadoop/hbase/ServerName;ILjava/lang/String;)Lorg/apache/hadoop/hbase/ServerMetrics;
     223: goto          231
     226: aload         9
     228: invokestatic  #63                 // Method org/apache/hadoop/hbase/ServerMetricsBuilder.of:(Lorg/apache/hadoop/hbase/ServerName;)Lorg/apache/hadoop/hbase/ServerMetrics;
     231: astore        11
     233: aload_0
     234: getfield      #6                  // Field serverManager:Lorg/apache/hadoop/hbase/master/ServerManager;
     237: aload         9
     239: aload         11
     241: invokevirtual #64                 // Method org/apache/hadoop/hbase/master/ServerManager.checkAndRecordNewServer:(Lorg/apache/hadoop/hbase/ServerName;Lorg/apache/hadoop/hbase/ServerMetrics;)Z
     244: pop
     245: goto          135
     248: aload_0
     249: getfield      #6                  // Field serverManager:Lorg/apache/hadoop/hbase/master/ServerManager;
     252: aload_1
     253: aload_2
     254: invokevirtual #65                 // Method org/apache/hadoop/hbase/master/ServerManager.findDeadServersAndProcess:(Ljava/util/Set;Ljava/util/Set;)V
     257: aload         4
     259: monitorexit
     260: goto          271
     263: astore        12
     265: aload         4
     267: monitorexit
     268: aload         12
     270: athrow
     271: return
    Exception table:
       from    to  target type
         107   260   263   any
         263   268   263   any

  public void stop();
    Code:
       0: aload_0
       1: getfield      #14                 // Field executor:Ljava/util/concurrent/ExecutorService;
       4: invokeinterface #66,  1           // InterfaceMethod java/util/concurrent/ExecutorService.shutdownNow:()Ljava/util/List;
       9: pop
      10: return

  public void nodeChildrenChanged(java.lang.String);
    Code:
       0: aload_1
       1: aload_0
       2: getfield      #16                 // Field watcher:Lorg/apache/hadoop/hbase/zookeeper/ZKWatcher;
       5: invokevirtual #17                 // Method org/apache/hadoop/hbase/zookeeper/ZKWatcher.getZNodePaths:()Lorg/apache/hadoop/hbase/zookeeper/ZNodePaths;
       8: getfield      #18                 // Field org/apache/hadoop/hbase/zookeeper/ZNodePaths.rsZNode:Ljava/lang/String;
      11: invokevirtual #92                 // Method java/lang/String.equals:(Ljava/lang/Object;)Z
      14: ifeq          56
      17: aload_0
      18: getfield      #5                  // Field server:Lorg/apache/hadoop/hbase/master/MasterServices;
      21: invokeinterface #93,  1           // InterfaceMethod org/apache/hadoop/hbase/master/MasterServices.isAborted:()Z
      26: ifne          56
      29: aload_0
      30: getfield      #5                  // Field server:Lorg/apache/hadoop/hbase/master/MasterServices;
      33: invokeinterface #94,  1           // InterfaceMethod org/apache/hadoop/hbase/master/MasterServices.isStopped:()Z
      38: ifne          56
      41: aload_0
      42: getfield      #14                 // Field executor:Ljava/util/concurrent/ExecutorService;
      45: aload_0
      46: invokedynamic #95,  0             // InvokeDynamic #4:run:(Lorg/apache/hadoop/hbase/master/RegionServerTracker;)Ljava/lang/Runnable;
      51: invokeinterface #96,  2           // InterfaceMethod java/util/concurrent/ExecutorService.execute:(Ljava/lang/Runnable;)V
      56: return

  static {};
    Code:
       0: ldc           #102                // class org/apache/hadoop/hbase/master/RegionServerTracker
       2: invokestatic  #103                // Method org/slf4j/LoggerFactory.getLogger:(Ljava/lang/Class;)Lorg/slf4j/Logger;
       5: putstatic     #25                 // Field LOG:Lorg/slf4j/Logger;
       8: return
}
