Compiled from "RegionServerCoprocessorHost.java"
class org.apache.hadoop.hbase.regionserver.RegionServerCoprocessorHost$6 extends org.apache.hadoop.hbase.coprocessor.CoprocessorHost<org.apache.hadoop.hbase.coprocessor.RegionServerCoprocessor, org.apache.hadoop.hbase.coprocessor.RegionServerCoprocessorEnvironment>.ObserverOperationWithResult<org.apache.hadoop.hbase.coprocessor.RegionServerObserver, org.apache.hadoop.hbase.replication.ReplicationEndpoint> {
  final org.apache.hadoop.hbase.regionserver.RegionServerCoprocessorHost this$0;

  org.apache.hadoop.hbase.regionserver.RegionServerCoprocessorHost$6(org.apache.hadoop.hbase.regionserver.RegionServerCoprocessorHost, org.apache.hadoop.hbase.coprocessor.CoprocessorHost$ObserverGetter, org.apache.hadoop.hbase.replication.ReplicationEndpoint);
    Code:
       0: aload_0
       1: aload_1
       2: putfield      #1                  // Field this$0:Lorg/apache/hadoop/hbase/regionserver/RegionServerCoprocessorHost;
       5: aload_0
       6: aload_1
       7: aload_2
       8: aload_3
       9: invokespecial #2                  // Method org/apache/hadoop/hbase/coprocessor/CoprocessorHost$ObserverOperationWithResult."<init>":(Lorg/apache/hadoop/hbase/coprocessor/CoprocessorHost;Lorg/apache/hadoop/hbase/coprocessor/CoprocessorHost$ObserverGetter;Ljava/lang/Object;)V
      12: return

  public org.apache.hadoop.hbase.replication.ReplicationEndpoint call(org.apache.hadoop.hbase.coprocessor.RegionServerObserver) throws java.io.IOException;
    Code:
       0: aload_1
       1: aload_0
       2: aload_0
       3: invokevirtual #3                  // Method getResult:()Ljava/lang/Object;
       6: checkcast     #4                  // class org/apache/hadoop/hbase/replication/ReplicationEndpoint
       9: invokeinterface #5,  3            // InterfaceMethod org/apache/hadoop/hbase/coprocessor/RegionServerObserver.postCreateReplicationEndPoint:(Lorg/apache/hadoop/hbase/coprocessor/ObserverContext;Lorg/apache/hadoop/hbase/replication/ReplicationEndpoint;)Lorg/apache/hadoop/hbase/replication/ReplicationEndpoint;
      14: areturn

  public java.lang.Object call(java.lang.Object) throws java.io.IOException;
    Code:
       0: aload_0
       1: aload_1
       2: checkcast     #6                  // class org/apache/hadoop/hbase/coprocessor/RegionServerObserver
       5: invokevirtual #7                  // Method call:(Lorg/apache/hadoop/hbase/coprocessor/RegionServerObserver;)Lorg/apache/hadoop/hbase/replication/ReplicationEndpoint;
       8: areturn
}
