Compiled from "RegionReplicaReplicationEndpoint.java"
class org.apache.hadoop.hbase.replication.regionserver.RegionReplicaReplicationEndpoint$RetryingRpcCallable<V> implements java.util.concurrent.Callable<V> {
  org.apache.hadoop.hbase.client.RpcRetryingCallerFactory factory;

  org.apache.hadoop.hbase.client.RetryingCallable<V> callable;

  int timeout;

  public org.apache.hadoop.hbase.replication.regionserver.RegionReplicaReplicationEndpoint$RetryingRpcCallable(org.apache.hadoop.hbase.client.RpcRetryingCallerFactory, org.apache.hadoop.hbase.client.RetryingCallable<V>, int);
    Code:
       0: aload_0
       1: invokespecial #1                  // Method java/lang/Object."<init>":()V
       4: aload_0
       5: aload_1
       6: putfield      #2                  // Field factory:Lorg/apache/hadoop/hbase/client/RpcRetryingCallerFactory;
       9: aload_0
      10: aload_2
      11: putfield      #3                  // Field callable:Lorg/apache/hadoop/hbase/client/RetryingCallable;
      14: aload_0
      15: iload_3
      16: putfield      #4                  // Field timeout:I
      19: return

  public V call() throws java.lang.Exception;
    Code:
       0: aload_0
       1: getfield      #2                  // Field factory:Lorg/apache/hadoop/hbase/client/RpcRetryingCallerFactory;
       4: invokevirtual #5                  // Method org/apache/hadoop/hbase/client/RpcRetryingCallerFactory.newCaller:()Lorg/apache/hadoop/hbase/client/RpcRetryingCaller;
       7: aload_0
       8: getfield      #3                  // Field callable:Lorg/apache/hadoop/hbase/client/RetryingCallable;
      11: aload_0
      12: getfield      #4                  // Field timeout:I
      15: invokeinterface #6,  3            // InterfaceMethod org/apache/hadoop/hbase/client/RpcRetryingCaller.callWithRetries:(Lorg/apache/hadoop/hbase/client/RetryingCallable;I)Ljava/lang/Object;
      20: areturn
}
