Compiled from "RegionLocator.java"
public interface org.apache.hadoop.hbase.client.RegionLocator extends java.io.Closeable {
  public org.apache.hadoop.hbase.HRegionLocation getRegionLocation(byte[]) throws java.io.IOException;
    Code:
       0: aload_0
       1: aload_1
       2: iconst_0
       3: invokeinterface #1,  3            // InterfaceMethod getRegionLocation:([BZ)Lorg/apache/hadoop/hbase/HRegionLocation;
       8: areturn

  public org.apache.hadoop.hbase.HRegionLocation getRegionLocation(byte[], boolean) throws java.io.IOException;
    Code:
       0: aload_0
       1: aload_1
       2: iconst_0
       3: iload_2
       4: invokeinterface #3,  4            // InterfaceMethod getRegionLocation:([BIZ)Lorg/apache/hadoop/hbase/HRegionLocation;
       9: areturn

  public org.apache.hadoop.hbase.HRegionLocation getRegionLocation(byte[], int) throws java.io.IOException;
    Code:
       0: aload_0
       1: aload_1
       2: iload_2
       3: iconst_0
       4: invokeinterface #3,  4            // InterfaceMethod getRegionLocation:([BIZ)Lorg/apache/hadoop/hbase/HRegionLocation;
       9: areturn

  public abstract org.apache.hadoop.hbase.HRegionLocation getRegionLocation(byte[], int, boolean) throws java.io.IOException;

  public java.util.List<org.apache.hadoop.hbase.HRegionLocation> getRegionLocations(byte[]) throws java.io.IOException;
    Code:
       0: aload_0
       1: aload_1
       2: iconst_0
       3: invokeinterface #4,  3            // InterfaceMethod getRegionLocations:([BZ)Ljava/util/List;
       8: areturn

  public abstract java.util.List<org.apache.hadoop.hbase.HRegionLocation> getRegionLocations(byte[], boolean) throws java.io.IOException;

  public abstract void clearRegionLocationCache();

  public abstract java.util.List<org.apache.hadoop.hbase.HRegionLocation> getAllRegionLocations() throws java.io.IOException;

  public byte[][] getStartKeys() throws java.io.IOException;
    Code:
       0: aload_0
       1: invokeinterface #5,  1            // InterfaceMethod getStartEndKeys:()Lorg/apache/hadoop/hbase/util/Pair;
       6: invokevirtual #6                  // Method org/apache/hadoop/hbase/util/Pair.getFirst:()Ljava/lang/Object;
       9: checkcast     #7                  // class "[[B"
      12: areturn

  public byte[][] getEndKeys() throws java.io.IOException;
    Code:
       0: aload_0
       1: invokeinterface #5,  1            // InterfaceMethod getStartEndKeys:()Lorg/apache/hadoop/hbase/util/Pair;
       6: invokevirtual #8                  // Method org/apache/hadoop/hbase/util/Pair.getSecond:()Ljava/lang/Object;
       9: checkcast     #7                  // class "[[B"
      12: areturn

  public org.apache.hadoop.hbase.util.Pair<byte[][], byte[][]> getStartEndKeys() throws java.io.IOException;
    Code:
       0: aload_0
       1: invokeinterface #9,  1            // InterfaceMethod getAllRegionLocations:()Ljava/util/List;
       6: invokeinterface #10,  1           // InterfaceMethod java/util/List.stream:()Ljava/util/stream/Stream;
      11: invokedynamic #11,  0             // InvokeDynamic #0:test:()Ljava/util/function/Predicate;
      16: invokeinterface #12,  2           // InterfaceMethod java/util/stream/Stream.filter:(Ljava/util/function/Predicate;)Ljava/util/stream/Stream;
      21: invokestatic  #13                 // Method java/util/stream/Collectors.toList:()Ljava/util/stream/Collector;
      24: invokeinterface #14,  2           // InterfaceMethod java/util/stream/Stream.collect:(Ljava/util/stream/Collector;)Ljava/lang/Object;
      29: checkcast     #15                 // class java/util/List
      32: astore_1
      33: aload_1
      34: invokeinterface #16,  1           // InterfaceMethod java/util/List.size:()I
      39: anewarray     #17                 // class "[B"
      42: astore_2
      43: aload_1
      44: invokeinterface #16,  1           // InterfaceMethod java/util/List.size:()I
      49: anewarray     #17                 // class "[B"
      52: astore_3
      53: iconst_0
      54: istore        4
      56: aload_1
      57: invokeinterface #16,  1           // InterfaceMethod java/util/List.size:()I
      62: istore        5
      64: iload         4
      66: iload         5
      68: if_icmpge     115
      71: aload_1
      72: iload         4
      74: invokeinterface #18,  2           // InterfaceMethod java/util/List.get:(I)Ljava/lang/Object;
      79: checkcast     #19                 // class org/apache/hadoop/hbase/HRegionLocation
      82: invokevirtual #20                 // Method org/apache/hadoop/hbase/HRegionLocation.getRegion:()Lorg/apache/hadoop/hbase/client/RegionInfo;
      85: astore        6
      87: aload_2
      88: iload         4
      90: aload         6
      92: invokeinterface #21,  1           // InterfaceMethod org/apache/hadoop/hbase/client/RegionInfo.getStartKey:()[B
      97: aastore
      98: aload_3
      99: iload         4
     101: aload         6
     103: invokeinterface #22,  1           // InterfaceMethod org/apache/hadoop/hbase/client/RegionInfo.getEndKey:()[B
     108: aastore
     109: iinc          4, 1
     112: goto          64
     115: aload_2
     116: aload_3
     117: invokestatic  #23                 // Method org/apache/hadoop/hbase/util/Pair.newPair:(Ljava/lang/Object;Ljava/lang/Object;)Lorg/apache/hadoop/hbase/util/Pair;
     120: areturn

  public abstract org.apache.hadoop.hbase.TableName getName();
}
