Compiled from "RegionPlan.java"
public class org.apache.hadoop.hbase.master.RegionPlan$RegionPlanComparator implements java.util.Comparator<org.apache.hadoop.hbase.master.RegionPlan>, java.io.Serializable {
  public org.apache.hadoop.hbase.master.RegionPlan$RegionPlanComparator();
    Code:
       0: aload_0
       1: invokespecial #1                  // Method java/lang/Object."<init>":()V
       4: return

  public int compare(org.apache.hadoop.hbase.master.RegionPlan, org.apache.hadoop.hbase.master.RegionPlan);
    Code:
       0: aload_1
       1: aload_2
       2: invokestatic  #2                  // Method org/apache/hadoop/hbase/master/RegionPlan.access$000:(Lorg/apache/hadoop/hbase/master/RegionPlan;Lorg/apache/hadoop/hbase/master/RegionPlan;)I
       5: ireturn

  public int compare(java.lang.Object, java.lang.Object);
    Code:
       0: aload_0
       1: aload_1
       2: checkcast     #3                  // class org/apache/hadoop/hbase/master/RegionPlan
       5: aload_2
       6: checkcast     #3                  // class org/apache/hadoop/hbase/master/RegionPlan
       9: invokevirtual #4                  // Method compare:(Lorg/apache/hadoop/hbase/master/RegionPlan;Lorg/apache/hadoop/hbase/master/RegionPlan;)I
      12: ireturn
}
