Compiled from "RegionGroupingProvider.java"
public class org.apache.hadoop.hbase.wal.RegionGroupingProvider implements org.apache.hadoop.hbase.wal.WALProvider {
  public static final java.lang.String REGION_GROUPING_STRATEGY;

  public static final java.lang.String DEFAULT_REGION_GROUPING_STRATEGY;

  public static final java.lang.String DELEGATE_PROVIDER;

  public static final java.lang.String DEFAULT_DELEGATE_PROVIDER;

  public org.apache.hadoop.hbase.wal.RegionGroupingProvider();
    Code:
       0: aload_0
       1: invokespecial #2                  // Method java/lang/Object."<init>":()V
       4: aload_0
       5: new           #3                  // class java/util/concurrent/ConcurrentHashMap
       8: dup
       9: invokespecial #4                  // Method java/util/concurrent/ConcurrentHashMap."<init>":()V
      12: putfield      #5                  // Field cached:Ljava/util/concurrent/ConcurrentMap;
      15: aload_0
      16: new           #6                  // class org/apache/hadoop/hbase/util/KeyLocker
      19: dup
      20: invokespecial #7                  // Method org/apache/hadoop/hbase/util/KeyLocker."<init>":()V
      23: putfield      #8                  // Field createLock:Lorg/apache/hadoop/hbase/util/KeyLocker;
      26: aload_0
      27: new           #9                  // class java/util/ArrayList
      30: dup
      31: invokespecial #10                 // Method java/util/ArrayList."<init>":()V
      34: putfield      #11                 // Field listeners:Ljava/util/List;
      37: return

  org.apache.hadoop.hbase.wal.RegionGroupingProvider$RegionGroupingStrategy getStrategy(org.apache.hadoop.conf.Configuration, java.lang.String, java.lang.String) throws java.io.IOException;
    Code:
       0: aload_1
       1: aload_2
       2: aload_3
       3: invokevirtual #12                 // Method org/apache/hadoop/conf/Configuration.get:(Ljava/lang/String;Ljava/lang/String;)Ljava/lang/String;
       6: invokestatic  #13                 // Method org/apache/hadoop/hbase/wal/RegionGroupingProvider$Strategies.valueOf:(Ljava/lang/String;)Lorg/apache/hadoop/hbase/wal/RegionGroupingProvider$Strategies;
       9: getfield      #14                 // Field org/apache/hadoop/hbase/wal/RegionGroupingProvider$Strategies.clazz:Ljava/lang/Class;
      12: astore        4
      14: goto          30
      17: astore        5
      19: aload_1
      20: aload_2
      21: ldc           #16                 // class org/apache/hadoop/hbase/wal/RegionGroupingProvider$IdentityGroupingStrategy
      23: ldc           #17                 // class org/apache/hadoop/hbase/wal/RegionGroupingProvider$RegionGroupingStrategy
      25: invokevirtual #18                 // Method org/apache/hadoop/conf/Configuration.getClass:(Ljava/lang/String;Ljava/lang/Class;Ljava/lang/Class;)Ljava/lang/Class;
      28: astore        4
      30: getstatic     #19                 // Field LOG:Lorg/slf4j/Logger;
      33: new           #20                 // class java/lang/StringBuilder
      36: dup
      37: invokespecial #21                 // Method java/lang/StringBuilder."<init>":()V
      40: ldc           #22                 // String Instantiating RegionGroupingStrategy of type
      42: invokevirtual #23                 // Method java/lang/StringBuilder.append:(Ljava/lang/String;)Ljava/lang/StringBuilder;
      45: aload         4
      47: invokevirtual #24                 // Method java/lang/StringBuilder.append:(Ljava/lang/Object;)Ljava/lang/StringBuilder;
      50: invokevirtual #25                 // Method java/lang/StringBuilder.toString:()Ljava/lang/String;
      53: invokeinterface #26,  2           // InterfaceMethod org/slf4j/Logger.info:(Ljava/lang/String;)V
      58: aload         4
      60: iconst_0
      61: anewarray     #27                 // class java/lang/Class
      64: invokevirtual #28                 // Method java/lang/Class.getDeclaredConstructor:([Ljava/lang/Class;)Ljava/lang/reflect/Constructor;
      67: iconst_0
      68: anewarray     #29                 // class java/lang/Object
      71: invokevirtual #30                 // Method java/lang/reflect/Constructor.newInstance:([Ljava/lang/Object;)Ljava/lang/Object;
      74: checkcast     #17                 // class org/apache/hadoop/hbase/wal/RegionGroupingProvider$RegionGroupingStrategy
      77: astore        5
      79: aload         5
      81: aload_1
      82: aload_0
      83: getfield      #31                 // Field providerId:Ljava/lang/String;
      86: invokeinterface #32,  3           // InterfaceMethod org/apache/hadoop/hbase/wal/RegionGroupingProvider$RegionGroupingStrategy.init:(Lorg/apache/hadoop/conf/Configuration;Ljava/lang/String;)V
      91: aload         5
      93: areturn
      94: astore        5
      96: getstatic     #19                 // Field LOG:Lorg/slf4j/Logger;
      99: ldc           #35                 // String couldn't set up region grouping strategy, check config key hbase.wal.regiongrouping.strategy
     101: invokeinterface #36,  2           // InterfaceMethod org/slf4j/Logger.error:(Ljava/lang/String;)V
     106: getstatic     #19                 // Field LOG:Lorg/slf4j/Logger;
     109: ldc           #37                 // String Exception details for failure to load region grouping strategy.
     111: aload         5
     113: invokeinterface #38,  3           // InterfaceMethod org/slf4j/Logger.debug:(Ljava/lang/String;Ljava/lang/Throwable;)V
     118: new           #39                 // class java/io/IOException
     121: dup
     122: ldc           #40                 // String couldn't set up region grouping strategy
     124: aload         5
     126: invokespecial #41                 // Method java/io/IOException."<init>":(Ljava/lang/String;Ljava/lang/Throwable;)V
     129: athrow
    Exception table:
       from    to  target type
           0    14    17   Class java/lang/IllegalArgumentException
          58    93    94   Class java/lang/Exception

  public void init(org.apache.hadoop.hbase.wal.WALFactory, org.apache.hadoop.conf.Configuration, java.lang.String) throws java.io.IOException;
    Code:
       0: aconst_null
       1: aload_0
       2: getfield      #42                 // Field strategy:Lorg/apache/hadoop/hbase/wal/RegionGroupingProvider$RegionGroupingStrategy;
       5: if_acmpeq     18
       8: new           #43                 // class java/lang/IllegalStateException
      11: dup
      12: ldc           #44                 // String WALProvider.init should only be called once.
      14: invokespecial #45                 // Method java/lang/IllegalStateException."<init>":(Ljava/lang/String;)V
      17: athrow
      18: aload_0
      19: aload_2
      20: putfield      #46                 // Field conf:Lorg/apache/hadoop/conf/Configuration;
      23: aload_0
      24: aload_1
      25: putfield      #47                 // Field factory:Lorg/apache/hadoop/hbase/wal/WALFactory;
      28: ldc           #48                 // String .meta
      30: aload_3
      31: invokevirtual #49                 // Method java/lang/String.equals:(Ljava/lang/Object;)Z
      34: ifeq          45
      37: aload_0
      38: aload_3
      39: putfield      #31                 // Field providerId:Ljava/lang/String;
      42: goto          105
      45: new           #20                 // class java/lang/StringBuilder
      48: dup
      49: invokespecial #21                 // Method java/lang/StringBuilder."<init>":()V
      52: aload_1
      53: getfield      #50                 // Field org/apache/hadoop/hbase/wal/WALFactory.factoryId:Ljava/lang/String;
      56: invokevirtual #23                 // Method java/lang/StringBuilder.append:(Ljava/lang/String;)Ljava/lang/StringBuilder;
      59: astore        4
      61: aload_3
      62: ifnull        96
      65: aload_3
      66: ldc           #51                 // String .
      68: invokevirtual #52                 // Method java/lang/String.startsWith:(Ljava/lang/String;)Z
      71: ifeq          84
      74: aload         4
      76: aload_3
      77: invokevirtual #23                 // Method java/lang/StringBuilder.append:(Ljava/lang/String;)Ljava/lang/StringBuilder;
      80: pop
      81: goto          96
      84: aload         4
      86: ldc           #51                 // String .
      88: invokevirtual #23                 // Method java/lang/StringBuilder.append:(Ljava/lang/String;)Ljava/lang/StringBuilder;
      91: aload_3
      92: invokevirtual #23                 // Method java/lang/StringBuilder.append:(Ljava/lang/String;)Ljava/lang/StringBuilder;
      95: pop
      96: aload_0
      97: aload         4
      99: invokevirtual #25                 // Method java/lang/StringBuilder.toString:()Ljava/lang/String;
     102: putfield      #31                 // Field providerId:Ljava/lang/String;
     105: aload_0
     106: aload_0
     107: aload_2
     108: ldc           #53                 // String hbase.wal.regiongrouping.strategy
     110: getstatic     #54                 // Field DEFAULT_REGION_GROUPING_STRATEGY:Ljava/lang/String;
     113: invokevirtual #55                 // Method getStrategy:(Lorg/apache/hadoop/conf/Configuration;Ljava/lang/String;Ljava/lang/String;)Lorg/apache/hadoop/hbase/wal/RegionGroupingProvider$RegionGroupingStrategy;
     116: putfield      #42                 // Field strategy:Lorg/apache/hadoop/hbase/wal/RegionGroupingProvider$RegionGroupingStrategy;
     119: aload_0
     120: aload_1
     121: ldc           #56                 // String hbase.wal.regiongrouping.delegate.provider
     123: getstatic     #57                 // Field DEFAULT_DELEGATE_PROVIDER:Ljava/lang/String;
     126: invokevirtual #58                 // Method org/apache/hadoop/hbase/wal/WALFactory.getProviderClass:(Ljava/lang/String;Ljava/lang/String;)Ljava/lang/Class;
     129: putfield      #59                 // Field providerClass:Ljava/lang/Class;
     132: return

  public java.util.List<org.apache.hadoop.hbase.wal.WAL> getWALs();
    Code:
       0: aload_0
       1: getfield      #5                  // Field cached:Ljava/util/concurrent/ConcurrentMap;
       4: invokeinterface #65,  1           // InterfaceMethod java/util/concurrent/ConcurrentMap.values:()Ljava/util/Collection;
       9: invokeinterface #66,  1           // InterfaceMethod java/util/Collection.stream:()Ljava/util/stream/Stream;
      14: invokedynamic #67,  0             // InvokeDynamic #0:apply:()Ljava/util/function/Function;
      19: invokeinterface #68,  2           // InterfaceMethod java/util/stream/Stream.flatMap:(Ljava/util/function/Function;)Ljava/util/stream/Stream;
      24: invokestatic  #69                 // Method java/util/stream/Collectors.toList:()Ljava/util/stream/Collector;
      27: invokeinterface #70,  2           // InterfaceMethod java/util/stream/Stream.collect:(Ljava/util/stream/Collector;)Ljava/lang/Object;
      32: checkcast     #71                 // class java/util/List
      35: areturn

  public org.apache.hadoop.hbase.wal.WAL getWAL(org.apache.hadoop.hbase.client.RegionInfo) throws java.io.IOException;
    Code:
       0: ldc           #48                 // String .meta
       2: aload_0
       3: getfield      #31                 // Field providerId:Ljava/lang/String;
       6: invokevirtual #49                 // Method java/lang/String.equals:(Ljava/lang/Object;)Z
       9: ifeq          18
      12: ldc           #82                 // String meta
      14: astore_2
      15: goto          63
      18: aload_1
      19: ifnull        43
      22: aload_1
      23: invokeinterface #83,  1           // InterfaceMethod org/apache/hadoop/hbase/client/RegionInfo.getEncodedNameAsBytes:()[B
      28: astore_3
      29: aload_1
      30: invokeinterface #84,  1           // InterfaceMethod org/apache/hadoop/hbase/client/RegionInfo.getTable:()Lorg/apache/hadoop/hbase/TableName;
      35: invokevirtual #85                 // Method org/apache/hadoop/hbase/TableName.getNamespace:()[B
      38: astore        4
      40: goto          50
      43: getstatic     #86                 // Field org/apache/hadoop/hbase/HConstants.EMPTY_BYTE_ARRAY:[B
      46: astore_3
      47: aconst_null
      48: astore        4
      50: aload_0
      51: getfield      #42                 // Field strategy:Lorg/apache/hadoop/hbase/wal/RegionGroupingProvider$RegionGroupingStrategy;
      54: aload_3
      55: aload         4
      57: invokeinterface #87,  3           // InterfaceMethod org/apache/hadoop/hbase/wal/RegionGroupingProvider$RegionGroupingStrategy.group:([B[B)Ljava/lang/String;
      62: astore_2
      63: aload_0
      64: aload_2
      65: invokespecial #88                 // Method getWAL:(Ljava/lang/String;)Lorg/apache/hadoop/hbase/wal/WAL;
      68: areturn

  public void shutdown() throws java.io.IOException;
    Code:
       0: aconst_null
       1: astore_1
       2: aload_0
       3: getfield      #5                  // Field cached:Ljava/util/concurrent/ConcurrentMap;
       6: invokeinterface #65,  1           // InterfaceMethod java/util/concurrent/ConcurrentMap.values:()Ljava/util/Collection;
      11: invokeinterface #89,  1           // InterfaceMethod java/util/Collection.iterator:()Ljava/util/Iterator;
      16: astore_2
      17: aload_2
      18: invokeinterface #90,  1           // InterfaceMethod java/util/Iterator.hasNext:()Z
      23: ifeq          138
      26: aload_2
      27: invokeinterface #91,  1           // InterfaceMethod java/util/Iterator.next:()Ljava/lang/Object;
      32: checkcast     #73                 // class org/apache/hadoop/hbase/wal/WALProvider
      35: astore_3
      36: aload_3
      37: invokeinterface #92,  1           // InterfaceMethod org/apache/hadoop/hbase/wal/WALProvider.shutdown:()V
      42: goto          135
      45: astore        4
      47: getstatic     #19                 // Field LOG:Lorg/slf4j/Logger;
      50: new           #20                 // class java/lang/StringBuilder
      53: dup
      54: invokespecial #21                 // Method java/lang/StringBuilder."<init>":()V
      57: ldc           #93                 // String Problem shutting down wal provider '
      59: invokevirtual #23                 // Method java/lang/StringBuilder.append:(Ljava/lang/String;)Ljava/lang/StringBuilder;
      62: aload_3
      63: invokevirtual #24                 // Method java/lang/StringBuilder.append:(Ljava/lang/Object;)Ljava/lang/StringBuilder;
      66: ldc           #94                 // String ':
      68: invokevirtual #23                 // Method java/lang/StringBuilder.append:(Ljava/lang/String;)Ljava/lang/StringBuilder;
      71: aload         4
      73: invokevirtual #95                 // Method java/io/IOException.getMessage:()Ljava/lang/String;
      76: invokevirtual #23                 // Method java/lang/StringBuilder.append:(Ljava/lang/String;)Ljava/lang/StringBuilder;
      79: invokevirtual #25                 // Method java/lang/StringBuilder.toString:()Ljava/lang/String;
      82: invokeinterface #36,  2           // InterfaceMethod org/slf4j/Logger.error:(Ljava/lang/String;)V
      87: getstatic     #19                 // Field LOG:Lorg/slf4j/Logger;
      90: invokeinterface #96,  1           // InterfaceMethod org/slf4j/Logger.isDebugEnabled:()Z
      95: ifeq          132
      98: getstatic     #19                 // Field LOG:Lorg/slf4j/Logger;
     101: new           #20                 // class java/lang/StringBuilder
     104: dup
     105: invokespecial #21                 // Method java/lang/StringBuilder."<init>":()V
     108: ldc           #97                 // String Details of problem shutting down wal provider '
     110: invokevirtual #23                 // Method java/lang/StringBuilder.append:(Ljava/lang/String;)Ljava/lang/StringBuilder;
     113: aload_3
     114: invokevirtual #24                 // Method java/lang/StringBuilder.append:(Ljava/lang/Object;)Ljava/lang/StringBuilder;
     117: ldc           #98                 // String '
     119: invokevirtual #23                 // Method java/lang/StringBuilder.append:(Ljava/lang/String;)Ljava/lang/StringBuilder;
     122: invokevirtual #25                 // Method java/lang/StringBuilder.toString:()Ljava/lang/String;
     125: aload         4
     127: invokeinterface #38,  3           // InterfaceMethod org/slf4j/Logger.debug:(Ljava/lang/String;Ljava/lang/Throwable;)V
     132: aload         4
     134: astore_1
     135: goto          17
     138: aload_1
     139: ifnull        144
     142: aload_1
     143: athrow
     144: return
    Exception table:
       from    to  target type
          36    42    45   Class java/io/IOException

  public void close() throws java.io.IOException;
    Code:
       0: aconst_null
       1: astore_1
       2: aload_0
       3: getfield      #5                  // Field cached:Ljava/util/concurrent/ConcurrentMap;
       6: invokeinterface #65,  1           // InterfaceMethod java/util/concurrent/ConcurrentMap.values:()Ljava/util/Collection;
      11: invokeinterface #89,  1           // InterfaceMethod java/util/Collection.iterator:()Ljava/util/Iterator;
      16: astore_2
      17: aload_2
      18: invokeinterface #90,  1           // InterfaceMethod java/util/Iterator.hasNext:()Z
      23: ifeq          138
      26: aload_2
      27: invokeinterface #91,  1           // InterfaceMethod java/util/Iterator.next:()Ljava/lang/Object;
      32: checkcast     #73                 // class org/apache/hadoop/hbase/wal/WALProvider
      35: astore_3
      36: aload_3
      37: invokeinterface #99,  1           // InterfaceMethod org/apache/hadoop/hbase/wal/WALProvider.close:()V
      42: goto          135
      45: astore        4
      47: getstatic     #19                 // Field LOG:Lorg/slf4j/Logger;
      50: new           #20                 // class java/lang/StringBuilder
      53: dup
      54: invokespecial #21                 // Method java/lang/StringBuilder."<init>":()V
      57: ldc           #100                // String Problem closing wal provider '
      59: invokevirtual #23                 // Method java/lang/StringBuilder.append:(Ljava/lang/String;)Ljava/lang/StringBuilder;
      62: aload_3
      63: invokevirtual #24                 // Method java/lang/StringBuilder.append:(Ljava/lang/Object;)Ljava/lang/StringBuilder;
      66: ldc           #94                 // String ':
      68: invokevirtual #23                 // Method java/lang/StringBuilder.append:(Ljava/lang/String;)Ljava/lang/StringBuilder;
      71: aload         4
      73: invokevirtual #95                 // Method java/io/IOException.getMessage:()Ljava/lang/String;
      76: invokevirtual #23                 // Method java/lang/StringBuilder.append:(Ljava/lang/String;)Ljava/lang/StringBuilder;
      79: invokevirtual #25                 // Method java/lang/StringBuilder.toString:()Ljava/lang/String;
      82: invokeinterface #36,  2           // InterfaceMethod org/slf4j/Logger.error:(Ljava/lang/String;)V
      87: getstatic     #19                 // Field LOG:Lorg/slf4j/Logger;
      90: invokeinterface #96,  1           // InterfaceMethod org/slf4j/Logger.isDebugEnabled:()Z
      95: ifeq          132
      98: getstatic     #19                 // Field LOG:Lorg/slf4j/Logger;
     101: new           #20                 // class java/lang/StringBuilder
     104: dup
     105: invokespecial #21                 // Method java/lang/StringBuilder."<init>":()V
     108: ldc           #101                // String Details of problem closing wal provider '
     110: invokevirtual #23                 // Method java/lang/StringBuilder.append:(Ljava/lang/String;)Ljava/lang/StringBuilder;
     113: aload_3
     114: invokevirtual #24                 // Method java/lang/StringBuilder.append:(Ljava/lang/Object;)Ljava/lang/StringBuilder;
     117: ldc           #98                 // String '
     119: invokevirtual #23                 // Method java/lang/StringBuilder.append:(Ljava/lang/String;)Ljava/lang/StringBuilder;
     122: invokevirtual #25                 // Method java/lang/StringBuilder.toString:()Ljava/lang/String;
     125: aload         4
     127: invokeinterface #38,  3           // InterfaceMethod org/slf4j/Logger.debug:(Ljava/lang/String;Ljava/lang/Throwable;)V
     132: aload         4
     134: astore_1
     135: goto          17
     138: aload_1
     139: ifnull        144
     142: aload_1
     143: athrow
     144: return
    Exception table:
       from    to  target type
          36    42    45   Class java/io/IOException

  public long getNumLogFiles();
    Code:
       0: lconst_0
       1: lstore_1
       2: aload_0
       3: getfield      #5                  // Field cached:Ljava/util/concurrent/ConcurrentMap;
       6: invokeinterface #65,  1           // InterfaceMethod java/util/concurrent/ConcurrentMap.values:()Ljava/util/Collection;
      11: invokeinterface #89,  1           // InterfaceMethod java/util/Collection.iterator:()Ljava/util/Iterator;
      16: astore_3
      17: aload_3
      18: invokeinterface #90,  1           // InterfaceMethod java/util/Iterator.hasNext:()Z
      23: ifeq          50
      26: aload_3
      27: invokeinterface #91,  1           // InterfaceMethod java/util/Iterator.next:()Ljava/lang/Object;
      32: checkcast     #73                 // class org/apache/hadoop/hbase/wal/WALProvider
      35: astore        4
      37: lload_1
      38: aload         4
      40: invokeinterface #102,  1          // InterfaceMethod org/apache/hadoop/hbase/wal/WALProvider.getNumLogFiles:()J
      45: ladd
      46: lstore_1
      47: goto          17
      50: lload_1
      51: lreturn

  public long getLogFileSize();
    Code:
       0: lconst_0
       1: lstore_1
       2: aload_0
       3: getfield      #5                  // Field cached:Ljava/util/concurrent/ConcurrentMap;
       6: invokeinterface #65,  1           // InterfaceMethod java/util/concurrent/ConcurrentMap.values:()Ljava/util/Collection;
      11: invokeinterface #89,  1           // InterfaceMethod java/util/Collection.iterator:()Ljava/util/Iterator;
      16: astore_3
      17: aload_3
      18: invokeinterface #90,  1           // InterfaceMethod java/util/Iterator.hasNext:()Z
      23: ifeq          50
      26: aload_3
      27: invokeinterface #91,  1           // InterfaceMethod java/util/Iterator.next:()Ljava/lang/Object;
      32: checkcast     #73                 // class org/apache/hadoop/hbase/wal/WALProvider
      35: astore        4
      37: lload_1
      38: aload         4
      40: invokeinterface #103,  1          // InterfaceMethod org/apache/hadoop/hbase/wal/WALProvider.getLogFileSize:()J
      45: ladd
      46: lstore_1
      47: goto          17
      50: lload_1
      51: lreturn

  public void addWALActionsListener(org.apache.hadoop.hbase.regionserver.wal.WALActionsListener);
    Code:
       0: aload_0
       1: getfield      #11                 // Field listeners:Ljava/util/List;
       4: aload_1
       5: invokeinterface #104,  2          // InterfaceMethod java/util/List.add:(Ljava/lang/Object;)Z
      10: pop
      11: return

  static {};
    Code:
       0: ldc           #34                 // class org/apache/hadoop/hbase/wal/RegionGroupingProvider
       2: invokestatic  #107                // Method org/slf4j/LoggerFactory.getLogger:(Ljava/lang/Class;)Lorg/slf4j/Logger;
       5: putstatic     #19                 // Field LOG:Lorg/slf4j/Logger;
       8: getstatic     #108                // Field org/apache/hadoop/hbase/wal/RegionGroupingProvider$Strategies.defaultStrategy:Lorg/apache/hadoop/hbase/wal/RegionGroupingProvider$Strategies;
      11: invokevirtual #109                // Method org/apache/hadoop/hbase/wal/RegionGroupingProvider$Strategies.name:()Ljava/lang/String;
      14: putstatic     #54                 // Field DEFAULT_REGION_GROUPING_STRATEGY:Ljava/lang/String;
      17: getstatic     #110                // Field org/apache/hadoop/hbase/wal/WALFactory$Providers.defaultProvider:Lorg/apache/hadoop/hbase/wal/WALFactory$Providers;
      20: invokevirtual #111                // Method org/apache/hadoop/hbase/wal/WALFactory$Providers.name:()Ljava/lang/String;
      23: putstatic     #57                 // Field DEFAULT_DELEGATE_PROVIDER:Ljava/lang/String;
      26: return
}
