Compiled from "RegionServerServices.java"
public class org.apache.hadoop.hbase.regionserver.RegionServerServices$RegionStateTransitionContext {
  public org.apache.hadoop.hbase.regionserver.RegionServerServices$RegionStateTransitionContext(org.apache.hadoop.hbase.shaded.protobuf.generated.RegionServerStatusProtos$RegionStateTransition$TransitionCode, long, long, org.apache.hadoop.hbase.client.RegionInfo...);
    Code:
       0: aload_0
       1: invokespecial #1                  // Method java/lang/Object."<init>":()V
       4: aload_0
       5: aload_1
       6: putfield      #2                  // Field code:Lorg/apache/hadoop/hbase/shaded/protobuf/generated/RegionServerStatusProtos$RegionStateTransition$TransitionCode;
       9: aload_0
      10: lload_2
      11: putfield      #3                  // Field openSeqNum:J
      14: aload_0
      15: lload         4
      17: putfield      #4                  // Field masterSystemTime:J
      20: aload_0
      21: aload         6
      23: putfield      #5                  // Field hris:[Lorg/apache/hadoop/hbase/client/RegionInfo;
      26: aload_0
      27: aload         6
      29: arraylength
      30: newarray       long
      32: putfield      #6                  // Field procIds:[J
      35: return

  public org.apache.hadoop.hbase.regionserver.RegionServerServices$RegionStateTransitionContext(org.apache.hadoop.hbase.shaded.protobuf.generated.RegionServerStatusProtos$RegionStateTransition$TransitionCode, long, long, long, org.apache.hadoop.hbase.client.RegionInfo);
    Code:
       0: aload_0
       1: invokespecial #1                  // Method java/lang/Object."<init>":()V
       4: aload_0
       5: aload_1
       6: putfield      #2                  // Field code:Lorg/apache/hadoop/hbase/shaded/protobuf/generated/RegionServerStatusProtos$RegionStateTransition$TransitionCode;
       9: aload_0
      10: lload_2
      11: putfield      #3                  // Field openSeqNum:J
      14: aload_0
      15: lload         6
      17: putfield      #4                  // Field masterSystemTime:J
      20: aload_0
      21: iconst_1
      22: anewarray     #7                  // class org/apache/hadoop/hbase/client/RegionInfo
      25: dup
      26: iconst_0
      27: aload         8
      29: aastore
      30: putfield      #5                  // Field hris:[Lorg/apache/hadoop/hbase/client/RegionInfo;
      33: aload_0
      34: iconst_1
      35: newarray       long
      37: dup
      38: iconst_0
      39: lload         4
      41: lastore
      42: putfield      #6                  // Field procIds:[J
      45: return

  public org.apache.hadoop.hbase.shaded.protobuf.generated.RegionServerStatusProtos$RegionStateTransition$TransitionCode getCode();
    Code:
       0: aload_0
       1: getfield      #2                  // Field code:Lorg/apache/hadoop/hbase/shaded/protobuf/generated/RegionServerStatusProtos$RegionStateTransition$TransitionCode;
       4: areturn

  public long getOpenSeqNum();
    Code:
       0: aload_0
       1: getfield      #3                  // Field openSeqNum:J
       4: lreturn

  public long getMasterSystemTime();
    Code:
       0: aload_0
       1: getfield      #4                  // Field masterSystemTime:J
       4: lreturn

  public org.apache.hadoop.hbase.client.RegionInfo[] getHris();
    Code:
       0: aload_0
       1: getfield      #5                  // Field hris:[Lorg/apache/hadoop/hbase/client/RegionInfo;
       4: areturn

  public long[] getProcIds();
    Code:
       0: aload_0
       1: getfield      #6                  // Field procIds:[J
       4: areturn
}
