Compiled from "RegionReplicaReplicationEndpoint.java"
public class org.apache.hadoop.hbase.replication.regionserver.RegionReplicaReplicationEndpoint extends org.apache.hadoop.hbase.replication.HBaseReplicationEndpoint {
  public org.apache.hadoop.hbase.replication.regionserver.RegionReplicaReplicationEndpoint();
    Code:
       0: aload_0
       1: invokespecial #2                  // Method org/apache/hadoop/hbase/replication/HBaseReplicationEndpoint."<init>":()V
       4: return

  public void init(org.apache.hadoop.hbase.replication.ReplicationEndpoint$Context) throws java.io.IOException;
    Code:
       0: aload_0
       1: aload_1
       2: invokespecial #3                  // Method org/apache/hadoop/hbase/replication/HBaseReplicationEndpoint.init:(Lorg/apache/hadoop/hbase/replication/ReplicationEndpoint$Context;)V
       5: aload_0
       6: aload_1
       7: invokevirtual #4                  // Method org/apache/hadoop/hbase/replication/ReplicationEndpoint$Context.getConfiguration:()Lorg/apache/hadoop/conf/Configuration;
      10: invokestatic  #5                  // Method org/apache/hadoop/hbase/HBaseConfiguration.create:(Lorg/apache/hadoop/conf/Configuration;)Lorg/apache/hadoop/conf/Configuration;
      13: putfield      #6                  // Field conf:Lorg/apache/hadoop/conf/Configuration;
      16: aload_0
      17: aload_1
      18: invokevirtual #7                  // Method org/apache/hadoop/hbase/replication/ReplicationEndpoint$Context.getTableDescriptors:()Lorg/apache/hadoop/hbase/TableDescriptors;
      21: putfield      #8                  // Field tableDescriptors:Lorg/apache/hadoop/hbase/TableDescriptors;
      24: aload_0
      25: getfield      #6                  // Field conf:Lorg/apache/hadoop/conf/Configuration;
      28: ldc           #10                 // String hbase.client.retries.number
      30: bipush        15
      32: invokevirtual #11                 // Method org/apache/hadoop/conf/Configuration.getInt:(Ljava/lang/String;I)I
      35: istore_2
      36: iload_2
      37: bipush        10
      39: if_icmple     57
      42: aload_0
      43: getfield      #6                  // Field conf:Lorg/apache/hadoop/conf/Configuration;
      46: ldc           #12                 // String hbase.client.serverside.retries.multiplier
      48: iconst_3
      49: invokevirtual #11                 // Method org/apache/hadoop/conf/Configuration.getInt:(Ljava/lang/String;I)I
      52: istore_3
      53: iload_2
      54: iload_3
      55: idiv
      56: istore_2
      57: aload_0
      58: getfield      #6                  // Field conf:Lorg/apache/hadoop/conf/Configuration;
      61: ldc           #12                 // String hbase.client.serverside.retries.multiplier
      63: iconst_1
      64: invokevirtual #13                 // Method org/apache/hadoop/conf/Configuration.setInt:(Ljava/lang/String;I)V
      67: aload_0
      68: getfield      #6                  // Field conf:Lorg/apache/hadoop/conf/Configuration;
      71: getstatic     #14                 // Field CLIENT_RETRIES_NUMBER:Ljava/lang/String;
      74: iload_2
      75: invokevirtual #11                 // Method org/apache/hadoop/conf/Configuration.getInt:(Ljava/lang/String;I)I
      78: istore_3
      79: aload_0
      80: getfield      #6                  // Field conf:Lorg/apache/hadoop/conf/Configuration;
      83: ldc           #10                 // String hbase.client.retries.number
      85: iload_3
      86: invokevirtual #13                 // Method org/apache/hadoop/conf/Configuration.setInt:(Ljava/lang/String;I)V
      89: aload_0
      90: aload_0
      91: getfield      #6                  // Field conf:Lorg/apache/hadoop/conf/Configuration;
      94: ldc           #15                 // String hbase.region.replica.replication.writer.threads
      96: iconst_3
      97: invokevirtual #11                 // Method org/apache/hadoop/conf/Configuration.getInt:(Ljava/lang/String;I)I
     100: putfield      #16                 // Field numWriterThreads:I
     103: aload_0
     104: new           #17                 // class org/apache/hadoop/hbase/wal/WALSplitter$PipelineController
     107: dup
     108: invokespecial #18                 // Method org/apache/hadoop/hbase/wal/WALSplitter$PipelineController."<init>":()V
     111: putfield      #19                 // Field controller:Lorg/apache/hadoop/hbase/wal/WALSplitter$PipelineController;
     114: aload_0
     115: new           #20                 // class org/apache/hadoop/hbase/wal/EntryBuffers
     118: dup
     119: aload_0
     120: getfield      #19                 // Field controller:Lorg/apache/hadoop/hbase/wal/WALSplitter$PipelineController;
     123: aload_0
     124: getfield      #6                  // Field conf:Lorg/apache/hadoop/conf/Configuration;
     127: ldc           #21                 // String hbase.region.replica.replication.buffersize
     129: ldc2_w        #22                 // long 134217728l
     132: invokevirtual #24                 // Method org/apache/hadoop/conf/Configuration.getLong:(Ljava/lang/String;J)J
     135: invokespecial #25                 // Method org/apache/hadoop/hbase/wal/EntryBuffers."<init>":(Lorg/apache/hadoop/hbase/wal/WALSplitter$PipelineController;J)V
     138: putfield      #26                 // Field entryBuffers:Lorg/apache/hadoop/hbase/wal/EntryBuffers;
     141: aload_0
     142: aload_0
     143: getfield      #6                  // Field conf:Lorg/apache/hadoop/conf/Configuration;
     146: ldc           #27                 // String hbase.client.operation.timeout
     148: ldc           #28                 // int 1200000
     150: invokevirtual #11                 // Method org/apache/hadoop/conf/Configuration.getInt:(Ljava/lang/String;I)I
     153: putfield      #29                 // Field operationTimeout:I
     156: return

  protected void doStart();
    Code:
       0: aload_0
       1: aload_0
       2: getfield      #6                  // Field conf:Lorg/apache/hadoop/conf/Configuration;
       5: invokestatic  #30                 // Method org/apache/hadoop/hbase/client/ConnectionFactory.createConnection:(Lorg/apache/hadoop/conf/Configuration;)Lorg/apache/hadoop/hbase/client/Connection;
       8: checkcast     #31                 // class org/apache/hadoop/hbase/client/ClusterConnection
      11: putfield      #32                 // Field connection:Lorg/apache/hadoop/hbase/client/ClusterConnection;
      14: aload_0
      15: aload_0
      16: aload_0
      17: getfield      #6                  // Field conf:Lorg/apache/hadoop/conf/Configuration;
      20: invokespecial #33                 // Method getDefaultThreadPool:(Lorg/apache/hadoop/conf/Configuration;)Ljava/util/concurrent/ExecutorService;
      23: putfield      #34                 // Field pool:Ljava/util/concurrent/ExecutorService;
      26: aload_0
      27: new           #35                 // class org/apache/hadoop/hbase/replication/regionserver/RegionReplicaReplicationEndpoint$RegionReplicaOutputSink
      30: dup
      31: aload_0
      32: getfield      #19                 // Field controller:Lorg/apache/hadoop/hbase/wal/WALSplitter$PipelineController;
      35: aload_0
      36: getfield      #8                  // Field tableDescriptors:Lorg/apache/hadoop/hbase/TableDescriptors;
      39: aload_0
      40: getfield      #26                 // Field entryBuffers:Lorg/apache/hadoop/hbase/wal/EntryBuffers;
      43: aload_0
      44: getfield      #32                 // Field connection:Lorg/apache/hadoop/hbase/client/ClusterConnection;
      47: aload_0
      48: getfield      #34                 // Field pool:Ljava/util/concurrent/ExecutorService;
      51: aload_0
      52: getfield      #16                 // Field numWriterThreads:I
      55: aload_0
      56: getfield      #29                 // Field operationTimeout:I
      59: invokespecial #36                 // Method org/apache/hadoop/hbase/replication/regionserver/RegionReplicaReplicationEndpoint$RegionReplicaOutputSink."<init>":(Lorg/apache/hadoop/hbase/wal/WALSplitter$PipelineController;Lorg/apache/hadoop/hbase/TableDescriptors;Lorg/apache/hadoop/hbase/wal/EntryBuffers;Lorg/apache/hadoop/hbase/client/ClusterConnection;Ljava/util/concurrent/ExecutorService;II)V
      62: putfield      #37                 // Field outputSink:Lorg/apache/hadoop/hbase/replication/regionserver/RegionReplicaReplicationEndpoint$RegionReplicaOutputSink;
      65: aload_0
      66: getfield      #37                 // Field outputSink:Lorg/apache/hadoop/hbase/replication/regionserver/RegionReplicaReplicationEndpoint$RegionReplicaOutputSink;
      69: invokevirtual #38                 // Method org/apache/hadoop/hbase/replication/regionserver/RegionReplicaReplicationEndpoint$RegionReplicaOutputSink.startWriterThreads:()V
      72: aload_0
      73: invokespecial #39                 // Method org/apache/hadoop/hbase/replication/HBaseReplicationEndpoint.doStart:()V
      76: goto          112
      79: astore_1
      80: getstatic     #1                  // Field LOG:Lorg/slf4j/Logger;
      83: new           #41                 // class java/lang/StringBuilder
      86: dup
      87: invokespecial #42                 // Method java/lang/StringBuilder."<init>":()V
      90: ldc           #43                 // String Received exception while creating connection :
      92: invokevirtual #44                 // Method java/lang/StringBuilder.append:(Ljava/lang/String;)Ljava/lang/StringBuilder;
      95: aload_1
      96: invokevirtual #45                 // Method java/lang/StringBuilder.append:(Ljava/lang/Object;)Ljava/lang/StringBuilder;
      99: invokevirtual #46                 // Method java/lang/StringBuilder.toString:()Ljava/lang/String;
     102: invokeinterface #47,  2           // InterfaceMethod org/slf4j/Logger.warn:(Ljava/lang/String;)V
     107: aload_0
     108: aload_1
     109: invokevirtual #48                 // Method notifyFailed:(Ljava/lang/Throwable;)V
     112: return
    Exception table:
       from    to  target type
           0    76    79   Class java/io/IOException

  protected void doStop();
    Code:
       0: aload_0
       1: getfield      #37                 // Field outputSink:Lorg/apache/hadoop/hbase/replication/regionserver/RegionReplicaReplicationEndpoint$RegionReplicaOutputSink;
       4: ifnull        30
       7: aload_0
       8: getfield      #37                 // Field outputSink:Lorg/apache/hadoop/hbase/replication/regionserver/RegionReplicaReplicationEndpoint$RegionReplicaOutputSink;
      11: invokevirtual #49                 // Method org/apache/hadoop/hbase/replication/regionserver/RegionReplicaReplicationEndpoint$RegionReplicaOutputSink.finishWritingAndClose:()Ljava/util/List;
      14: pop
      15: goto          30
      18: astore_1
      19: getstatic     #1                  // Field LOG:Lorg/slf4j/Logger;
      22: ldc           #50                 // String Got exception while trying to close OutputSink
      24: aload_1
      25: invokeinterface #51,  3           // InterfaceMethod org/slf4j/Logger.warn:(Ljava/lang/String;Ljava/lang/Throwable;)V
      30: aload_0
      31: getfield      #34                 // Field pool:Ljava/util/concurrent/ExecutorService;
      34: ifnull        108
      37: aload_0
      38: getfield      #34                 // Field pool:Ljava/util/concurrent/ExecutorService;
      41: invokeinterface #52,  1           // InterfaceMethod java/util/concurrent/ExecutorService.shutdownNow:()Ljava/util/List;
      46: pop
      47: aload_0
      48: getfield      #34                 // Field pool:Ljava/util/concurrent/ExecutorService;
      51: ldc2_w        #53                 // long 10000l
      54: getstatic     #55                 // Field java/util/concurrent/TimeUnit.MILLISECONDS:Ljava/util/concurrent/TimeUnit;
      57: invokeinterface #56,  4           // InterfaceMethod java/util/concurrent/ExecutorService.awaitTermination:(JLjava/util/concurrent/TimeUnit;)Z
      62: istore_1
      63: iload_1
      64: ifne          77
      67: getstatic     #1                  // Field LOG:Lorg/slf4j/Logger;
      70: ldc           #57                 // String Failed to shutdown the thread pool after 10 seconds
      72: invokeinterface #47,  2           // InterfaceMethod org/slf4j/Logger.warn:(Ljava/lang/String;)V
      77: goto          108
      80: astore_1
      81: getstatic     #1                  // Field LOG:Lorg/slf4j/Logger;
      84: new           #41                 // class java/lang/StringBuilder
      87: dup
      88: invokespecial #42                 // Method java/lang/StringBuilder."<init>":()V
      91: ldc           #59                 // String Got interrupted while waiting for the thread pool to shut down
      93: invokevirtual #44                 // Method java/lang/StringBuilder.append:(Ljava/lang/String;)Ljava/lang/StringBuilder;
      96: aload_1
      97: invokevirtual #45                 // Method java/lang/StringBuilder.append:(Ljava/lang/Object;)Ljava/lang/StringBuilder;
     100: invokevirtual #46                 // Method java/lang/StringBuilder.toString:()Ljava/lang/String;
     103: invokeinterface #47,  2           // InterfaceMethod org/slf4j/Logger.warn:(Ljava/lang/String;)V
     108: aload_0
     109: getfield      #32                 // Field connection:Lorg/apache/hadoop/hbase/client/ClusterConnection;
     112: ifnull        155
     115: aload_0
     116: getfield      #32                 // Field connection:Lorg/apache/hadoop/hbase/client/ClusterConnection;
     119: invokeinterface #60,  1           // InterfaceMethod org/apache/hadoop/hbase/client/ClusterConnection.close:()V
     124: goto          155
     127: astore_1
     128: getstatic     #1                  // Field LOG:Lorg/slf4j/Logger;
     131: new           #41                 // class java/lang/StringBuilder
     134: dup
     135: invokespecial #42                 // Method java/lang/StringBuilder."<init>":()V
     138: ldc           #61                 // String Got exception closing connection :
     140: invokevirtual #44                 // Method java/lang/StringBuilder.append:(Ljava/lang/String;)Ljava/lang/StringBuilder;
     143: aload_1
     144: invokevirtual #45                 // Method java/lang/StringBuilder.append:(Ljava/lang/Object;)Ljava/lang/StringBuilder;
     147: invokevirtual #46                 // Method java/lang/StringBuilder.toString:()Ljava/lang/String;
     150: invokeinterface #47,  2           // InterfaceMethod org/slf4j/Logger.warn:(Ljava/lang/String;)V
     155: aload_0
     156: invokespecial #62                 // Method org/apache/hadoop/hbase/replication/HBaseReplicationEndpoint.doStop:()V
     159: return
    Exception table:
       from    to  target type
           7    15    18   Class java/io/IOException
          47    77    80   Class java/lang/InterruptedException
         115   124   127   Class java/io/IOException

  public boolean replicate(org.apache.hadoop.hbase.replication.ReplicationEndpoint$ReplicateContext);
    Code:
       0: aload_0
       1: invokevirtual #80                 // Method isRunning:()Z
       4: ifeq          121
       7: aload_1
       8: invokevirtual #81                 // Method org/apache/hadoop/hbase/replication/ReplicationEndpoint$ReplicateContext.getEntries:()Ljava/util/List;
      11: invokeinterface #82,  1           // InterfaceMethod java/util/List.iterator:()Ljava/util/Iterator;
      16: astore_2
      17: aload_2
      18: invokeinterface #83,  1           // InterfaceMethod java/util/Iterator.hasNext:()Z
      23: ifeq          47
      26: aload_2
      27: invokeinterface #84,  1           // InterfaceMethod java/util/Iterator.next:()Ljava/lang/Object;
      32: checkcast     #85                 // class org/apache/hadoop/hbase/wal/WAL$Entry
      35: astore_3
      36: aload_0
      37: getfield      #26                 // Field entryBuffers:Lorg/apache/hadoop/hbase/wal/EntryBuffers;
      40: aload_3
      41: invokevirtual #86                 // Method org/apache/hadoop/hbase/wal/EntryBuffers.appendEntry:(Lorg/apache/hadoop/hbase/wal/WAL$Entry;)V
      44: goto          17
      47: aload_0
      48: getfield      #37                 // Field outputSink:Lorg/apache/hadoop/hbase/replication/regionserver/RegionReplicaReplicationEndpoint$RegionReplicaOutputSink;
      51: invokevirtual #87                 // Method org/apache/hadoop/hbase/replication/regionserver/RegionReplicaReplicationEndpoint$RegionReplicaOutputSink.flush:()Z
      54: pop
      55: aload_0
      56: getfield      #88                 // Field ctx:Lorg/apache/hadoop/hbase/replication/ReplicationEndpoint$Context;
      59: invokevirtual #89                 // Method org/apache/hadoop/hbase/replication/ReplicationEndpoint$Context.getMetrics:()Lorg/apache/hadoop/hbase/replication/regionserver/MetricsSource;
      62: aload_0
      63: getfield      #37                 // Field outputSink:Lorg/apache/hadoop/hbase/replication/regionserver/RegionReplicaReplicationEndpoint$RegionReplicaOutputSink;
      66: invokevirtual #90                 // Method org/apache/hadoop/hbase/replication/regionserver/RegionReplicaReplicationEndpoint$RegionReplicaOutputSink.getSkippedEditsCounter:()Ljava/util/concurrent/atomic/AtomicLong;
      69: lconst_0
      70: invokevirtual #91                 // Method java/util/concurrent/atomic/AtomicLong.getAndSet:(J)J
      73: invokevirtual #92                 // Method org/apache/hadoop/hbase/replication/regionserver/MetricsSource.incrLogEditsFiltered:(J)V
      76: iconst_1
      77: ireturn
      78: astore_2
      79: invokestatic  #93                 // Method java/lang/Thread.currentThread:()Ljava/lang/Thread;
      82: invokevirtual #94                 // Method java/lang/Thread.interrupt:()V
      85: iconst_0
      86: ireturn
      87: astore_2
      88: getstatic     #1                  // Field LOG:Lorg/slf4j/Logger;
      91: new           #41                 // class java/lang/StringBuilder
      94: dup
      95: invokespecial #42                 // Method java/lang/StringBuilder."<init>":()V
      98: ldc           #95                 // String Received IOException while trying to replicate
     100: invokevirtual #44                 // Method java/lang/StringBuilder.append:(Ljava/lang/String;)Ljava/lang/StringBuilder;
     103: aload_2
     104: invokestatic  #96                 // Method org/apache/hadoop/util/StringUtils.stringifyException:(Ljava/lang/Throwable;)Ljava/lang/String;
     107: invokevirtual #44                 // Method java/lang/StringBuilder.append:(Ljava/lang/String;)Ljava/lang/StringBuilder;
     110: invokevirtual #46                 // Method java/lang/StringBuilder.toString:()Ljava/lang/String;
     113: invokeinterface #47,  2           // InterfaceMethod org/slf4j/Logger.warn:(Ljava/lang/String;)V
     118: goto          0
     121: iconst_0
     122: ireturn
    Exception table:
       from    to  target type
           7    77    78   Class java/lang/InterruptedException
           7    77    87   Class java/io/IOException

  public boolean canReplicateToSameCluster();
    Code:
       0: iconst_1
       1: ireturn

  protected org.apache.hadoop.hbase.replication.WALEntryFilter getScopeWALEntryFilter();
    Code:
       0: aconst_null
       1: areturn

  static org.slf4j.Logger access$000();
    Code:
       0: getstatic     #1                  // Field LOG:Lorg/slf4j/Logger;
       3: areturn

  static {};
    Code:
       0: ldc           #97                 // class org/apache/hadoop/hbase/replication/regionserver/RegionReplicaReplicationEndpoint
       2: invokestatic  #98                 // Method org/slf4j/LoggerFactory.getLogger:(Ljava/lang/Class;)Lorg/slf4j/Logger;
       5: putstatic     #1                  // Field LOG:Lorg/slf4j/Logger;
       8: ldc           #99                 // String hbase.region.replica.replication.client.retries.number
      10: putstatic     #14                 // Field CLIENT_RETRIES_NUMBER:Ljava/lang/String;
      13: return
}
