Compiled from "RegionServerStatusProtos.java"
public final class org.apache.hadoop.hbase.shaded.protobuf.generated.RegionServerStatusProtos$RegionServerStatusService$Stub extends org.apache.hadoop.hbase.shaded.protobuf.generated.RegionServerStatusProtos$RegionServerStatusService implements org.apache.hadoop.hbase.shaded.protobuf.generated.RegionServerStatusProtos$RegionServerStatusService$Interface {
  public org.apache.hbase.thirdparty.com.google.protobuf.RpcChannel getChannel();
    Code:
       0: aload_0
       1: getfield      #3                  // Field channel:Lorg/apache/hbase/thirdparty/com/google/protobuf/RpcChannel;
       4: areturn

  public void regionServerStartup(org.apache.hbase.thirdparty.com.google.protobuf.RpcController, org.apache.hadoop.hbase.shaded.protobuf.generated.RegionServerStatusProtos$RegionServerStartupRequest, org.apache.hbase.thirdparty.com.google.protobuf.RpcCallback<org.apache.hadoop.hbase.shaded.protobuf.generated.RegionServerStatusProtos$RegionServerStartupResponse>);
    Code:
       0: aload_0
       1: getfield      #3                  // Field channel:Lorg/apache/hbase/thirdparty/com/google/protobuf/RpcChannel;
       4: invokestatic  #4                  // Method getDescriptor:()Lorg/apache/hbase/thirdparty/com/google/protobuf/Descriptors$ServiceDescriptor;
       7: invokevirtual #5                  // Method org/apache/hbase/thirdparty/com/google/protobuf/Descriptors$ServiceDescriptor.getMethods:()Ljava/util/List;
      10: iconst_0
      11: invokeinterface #6,  2            // InterfaceMethod java/util/List.get:(I)Ljava/lang/Object;
      16: checkcast     #7                  // class org/apache/hbase/thirdparty/com/google/protobuf/Descriptors$MethodDescriptor
      19: aload_1
      20: aload_2
      21: invokestatic  #8                  // Method org/apache/hadoop/hbase/shaded/protobuf/generated/RegionServerStatusProtos$RegionServerStartupResponse.getDefaultInstance:()Lorg/apache/hadoop/hbase/shaded/protobuf/generated/RegionServerStatusProtos$RegionServerStartupResponse;
      24: aload_3
      25: ldc           #9                  // class org/apache/hadoop/hbase/shaded/protobuf/generated/RegionServerStatusProtos$RegionServerStartupResponse
      27: invokestatic  #8                  // Method org/apache/hadoop/hbase/shaded/protobuf/generated/RegionServerStatusProtos$RegionServerStartupResponse.getDefaultInstance:()Lorg/apache/hadoop/hbase/shaded/protobuf/generated/RegionServerStatusProtos$RegionServerStartupResponse;
      30: invokestatic  #10                 // Method org/apache/hbase/thirdparty/com/google/protobuf/RpcUtil.generalizeCallback:(Lorg/apache/hbase/thirdparty/com/google/protobuf/RpcCallback;Ljava/lang/Class;Lorg/apache/hbase/thirdparty/com/google/protobuf/Message;)Lorg/apache/hbase/thirdparty/com/google/protobuf/RpcCallback;
      33: invokeinterface #11,  6           // InterfaceMethod org/apache/hbase/thirdparty/com/google/protobuf/RpcChannel.callMethod:(Lorg/apache/hbase/thirdparty/com/google/protobuf/Descriptors$MethodDescriptor;Lorg/apache/hbase/thirdparty/com/google/protobuf/RpcController;Lorg/apache/hbase/thirdparty/com/google/protobuf/Message;Lorg/apache/hbase/thirdparty/com/google/protobuf/Message;Lorg/apache/hbase/thirdparty/com/google/protobuf/RpcCallback;)V
      38: return

  public void regionServerReport(org.apache.hbase.thirdparty.com.google.protobuf.RpcController, org.apache.hadoop.hbase.shaded.protobuf.generated.RegionServerStatusProtos$RegionServerReportRequest, org.apache.hbase.thirdparty.com.google.protobuf.RpcCallback<org.apache.hadoop.hbase.shaded.protobuf.generated.RegionServerStatusProtos$RegionServerReportResponse>);
    Code:
       0: aload_0
       1: getfield      #3                  // Field channel:Lorg/apache/hbase/thirdparty/com/google/protobuf/RpcChannel;
       4: invokestatic  #4                  // Method getDescriptor:()Lorg/apache/hbase/thirdparty/com/google/protobuf/Descriptors$ServiceDescriptor;
       7: invokevirtual #5                  // Method org/apache/hbase/thirdparty/com/google/protobuf/Descriptors$ServiceDescriptor.getMethods:()Ljava/util/List;
      10: iconst_1
      11: invokeinterface #6,  2            // InterfaceMethod java/util/List.get:(I)Ljava/lang/Object;
      16: checkcast     #7                  // class org/apache/hbase/thirdparty/com/google/protobuf/Descriptors$MethodDescriptor
      19: aload_1
      20: aload_2
      21: invokestatic  #12                 // Method org/apache/hadoop/hbase/shaded/protobuf/generated/RegionServerStatusProtos$RegionServerReportResponse.getDefaultInstance:()Lorg/apache/hadoop/hbase/shaded/protobuf/generated/RegionServerStatusProtos$RegionServerReportResponse;
      24: aload_3
      25: ldc           #13                 // class org/apache/hadoop/hbase/shaded/protobuf/generated/RegionServerStatusProtos$RegionServerReportResponse
      27: invokestatic  #12                 // Method org/apache/hadoop/hbase/shaded/protobuf/generated/RegionServerStatusProtos$RegionServerReportResponse.getDefaultInstance:()Lorg/apache/hadoop/hbase/shaded/protobuf/generated/RegionServerStatusProtos$RegionServerReportResponse;
      30: invokestatic  #10                 // Method org/apache/hbase/thirdparty/com/google/protobuf/RpcUtil.generalizeCallback:(Lorg/apache/hbase/thirdparty/com/google/protobuf/RpcCallback;Ljava/lang/Class;Lorg/apache/hbase/thirdparty/com/google/protobuf/Message;)Lorg/apache/hbase/thirdparty/com/google/protobuf/RpcCallback;
      33: invokeinterface #11,  6           // InterfaceMethod org/apache/hbase/thirdparty/com/google/protobuf/RpcChannel.callMethod:(Lorg/apache/hbase/thirdparty/com/google/protobuf/Descriptors$MethodDescriptor;Lorg/apache/hbase/thirdparty/com/google/protobuf/RpcController;Lorg/apache/hbase/thirdparty/com/google/protobuf/Message;Lorg/apache/hbase/thirdparty/com/google/protobuf/Message;Lorg/apache/hbase/thirdparty/com/google/protobuf/RpcCallback;)V
      38: return

  public void reportRSFatalError(org.apache.hbase.thirdparty.com.google.protobuf.RpcController, org.apache.hadoop.hbase.shaded.protobuf.generated.RegionServerStatusProtos$ReportRSFatalErrorRequest, org.apache.hbase.thirdparty.com.google.protobuf.RpcCallback<org.apache.hadoop.hbase.shaded.protobuf.generated.RegionServerStatusProtos$ReportRSFatalErrorResponse>);
    Code:
       0: aload_0
       1: getfield      #3                  // Field channel:Lorg/apache/hbase/thirdparty/com/google/protobuf/RpcChannel;
       4: invokestatic  #4                  // Method getDescriptor:()Lorg/apache/hbase/thirdparty/com/google/protobuf/Descriptors$ServiceDescriptor;
       7: invokevirtual #5                  // Method org/apache/hbase/thirdparty/com/google/protobuf/Descriptors$ServiceDescriptor.getMethods:()Ljava/util/List;
      10: iconst_2
      11: invokeinterface #6,  2            // InterfaceMethod java/util/List.get:(I)Ljava/lang/Object;
      16: checkcast     #7                  // class org/apache/hbase/thirdparty/com/google/protobuf/Descriptors$MethodDescriptor
      19: aload_1
      20: aload_2
      21: invokestatic  #14                 // Method org/apache/hadoop/hbase/shaded/protobuf/generated/RegionServerStatusProtos$ReportRSFatalErrorResponse.getDefaultInstance:()Lorg/apache/hadoop/hbase/shaded/protobuf/generated/RegionServerStatusProtos$ReportRSFatalErrorResponse;
      24: aload_3
      25: ldc           #15                 // class org/apache/hadoop/hbase/shaded/protobuf/generated/RegionServerStatusProtos$ReportRSFatalErrorResponse
      27: invokestatic  #14                 // Method org/apache/hadoop/hbase/shaded/protobuf/generated/RegionServerStatusProtos$ReportRSFatalErrorResponse.getDefaultInstance:()Lorg/apache/hadoop/hbase/shaded/protobuf/generated/RegionServerStatusProtos$ReportRSFatalErrorResponse;
      30: invokestatic  #10                 // Method org/apache/hbase/thirdparty/com/google/protobuf/RpcUtil.generalizeCallback:(Lorg/apache/hbase/thirdparty/com/google/protobuf/RpcCallback;Ljava/lang/Class;Lorg/apache/hbase/thirdparty/com/google/protobuf/Message;)Lorg/apache/hbase/thirdparty/com/google/protobuf/RpcCallback;
      33: invokeinterface #11,  6           // InterfaceMethod org/apache/hbase/thirdparty/com/google/protobuf/RpcChannel.callMethod:(Lorg/apache/hbase/thirdparty/com/google/protobuf/Descriptors$MethodDescriptor;Lorg/apache/hbase/thirdparty/com/google/protobuf/RpcController;Lorg/apache/hbase/thirdparty/com/google/protobuf/Message;Lorg/apache/hbase/thirdparty/com/google/protobuf/Message;Lorg/apache/hbase/thirdparty/com/google/protobuf/RpcCallback;)V
      38: return

  public void getLastFlushedSequenceId(org.apache.hbase.thirdparty.com.google.protobuf.RpcController, org.apache.hadoop.hbase.shaded.protobuf.generated.RegionServerStatusProtos$GetLastFlushedSequenceIdRequest, org.apache.hbase.thirdparty.com.google.protobuf.RpcCallback<org.apache.hadoop.hbase.shaded.protobuf.generated.RegionServerStatusProtos$GetLastFlushedSequenceIdResponse>);
    Code:
       0: aload_0
       1: getfield      #3                  // Field channel:Lorg/apache/hbase/thirdparty/com/google/protobuf/RpcChannel;
       4: invokestatic  #4                  // Method getDescriptor:()Lorg/apache/hbase/thirdparty/com/google/protobuf/Descriptors$ServiceDescriptor;
       7: invokevirtual #5                  // Method org/apache/hbase/thirdparty/com/google/protobuf/Descriptors$ServiceDescriptor.getMethods:()Ljava/util/List;
      10: iconst_3
      11: invokeinterface #6,  2            // InterfaceMethod java/util/List.get:(I)Ljava/lang/Object;
      16: checkcast     #7                  // class org/apache/hbase/thirdparty/com/google/protobuf/Descriptors$MethodDescriptor
      19: aload_1
      20: aload_2
      21: invokestatic  #16                 // Method org/apache/hadoop/hbase/shaded/protobuf/generated/RegionServerStatusProtos$GetLastFlushedSequenceIdResponse.getDefaultInstance:()Lorg/apache/hadoop/hbase/shaded/protobuf/generated/RegionServerStatusProtos$GetLastFlushedSequenceIdResponse;
      24: aload_3
      25: ldc           #17                 // class org/apache/hadoop/hbase/shaded/protobuf/generated/RegionServerStatusProtos$GetLastFlushedSequenceIdResponse
      27: invokestatic  #16                 // Method org/apache/hadoop/hbase/shaded/protobuf/generated/RegionServerStatusProtos$GetLastFlushedSequenceIdResponse.getDefaultInstance:()Lorg/apache/hadoop/hbase/shaded/protobuf/generated/RegionServerStatusProtos$GetLastFlushedSequenceIdResponse;
      30: invokestatic  #10                 // Method org/apache/hbase/thirdparty/com/google/protobuf/RpcUtil.generalizeCallback:(Lorg/apache/hbase/thirdparty/com/google/protobuf/RpcCallback;Ljava/lang/Class;Lorg/apache/hbase/thirdparty/com/google/protobuf/Message;)Lorg/apache/hbase/thirdparty/com/google/protobuf/RpcCallback;
      33: invokeinterface #11,  6           // InterfaceMethod org/apache/hbase/thirdparty/com/google/protobuf/RpcChannel.callMethod:(Lorg/apache/hbase/thirdparty/com/google/protobuf/Descriptors$MethodDescriptor;Lorg/apache/hbase/thirdparty/com/google/protobuf/RpcController;Lorg/apache/hbase/thirdparty/com/google/protobuf/Message;Lorg/apache/hbase/thirdparty/com/google/protobuf/Message;Lorg/apache/hbase/thirdparty/com/google/protobuf/RpcCallback;)V
      38: return

  public void reportRegionStateTransition(org.apache.hbase.thirdparty.com.google.protobuf.RpcController, org.apache.hadoop.hbase.shaded.protobuf.generated.RegionServerStatusProtos$ReportRegionStateTransitionRequest, org.apache.hbase.thirdparty.com.google.protobuf.RpcCallback<org.apache.hadoop.hbase.shaded.protobuf.generated.RegionServerStatusProtos$ReportRegionStateTransitionResponse>);
    Code:
       0: aload_0
       1: getfield      #3                  // Field channel:Lorg/apache/hbase/thirdparty/com/google/protobuf/RpcChannel;
       4: invokestatic  #4                  // Method getDescriptor:()Lorg/apache/hbase/thirdparty/com/google/protobuf/Descriptors$ServiceDescriptor;
       7: invokevirtual #5                  // Method org/apache/hbase/thirdparty/com/google/protobuf/Descriptors$ServiceDescriptor.getMethods:()Ljava/util/List;
      10: iconst_4
      11: invokeinterface #6,  2            // InterfaceMethod java/util/List.get:(I)Ljava/lang/Object;
      16: checkcast     #7                  // class org/apache/hbase/thirdparty/com/google/protobuf/Descriptors$MethodDescriptor
      19: aload_1
      20: aload_2
      21: invokestatic  #18                 // Method org/apache/hadoop/hbase/shaded/protobuf/generated/RegionServerStatusProtos$ReportRegionStateTransitionResponse.getDefaultInstance:()Lorg/apache/hadoop/hbase/shaded/protobuf/generated/RegionServerStatusProtos$ReportRegionStateTransitionResponse;
      24: aload_3
      25: ldc           #19                 // class org/apache/hadoop/hbase/shaded/protobuf/generated/RegionServerStatusProtos$ReportRegionStateTransitionResponse
      27: invokestatic  #18                 // Method org/apache/hadoop/hbase/shaded/protobuf/generated/RegionServerStatusProtos$ReportRegionStateTransitionResponse.getDefaultInstance:()Lorg/apache/hadoop/hbase/shaded/protobuf/generated/RegionServerStatusProtos$ReportRegionStateTransitionResponse;
      30: invokestatic  #10                 // Method org/apache/hbase/thirdparty/com/google/protobuf/RpcUtil.generalizeCallback:(Lorg/apache/hbase/thirdparty/com/google/protobuf/RpcCallback;Ljava/lang/Class;Lorg/apache/hbase/thirdparty/com/google/protobuf/Message;)Lorg/apache/hbase/thirdparty/com/google/protobuf/RpcCallback;
      33: invokeinterface #11,  6           // InterfaceMethod org/apache/hbase/thirdparty/com/google/protobuf/RpcChannel.callMethod:(Lorg/apache/hbase/thirdparty/com/google/protobuf/Descriptors$MethodDescriptor;Lorg/apache/hbase/thirdparty/com/google/protobuf/RpcController;Lorg/apache/hbase/thirdparty/com/google/protobuf/Message;Lorg/apache/hbase/thirdparty/com/google/protobuf/Message;Lorg/apache/hbase/thirdparty/com/google/protobuf/RpcCallback;)V
      38: return

  public void reportRegionSpaceUse(org.apache.hbase.thirdparty.com.google.protobuf.RpcController, org.apache.hadoop.hbase.shaded.protobuf.generated.RegionServerStatusProtos$RegionSpaceUseReportRequest, org.apache.hbase.thirdparty.com.google.protobuf.RpcCallback<org.apache.hadoop.hbase.shaded.protobuf.generated.RegionServerStatusProtos$RegionSpaceUseReportResponse>);
    Code:
       0: aload_0
       1: getfield      #3                  // Field channel:Lorg/apache/hbase/thirdparty/com/google/protobuf/RpcChannel;
       4: invokestatic  #4                  // Method getDescriptor:()Lorg/apache/hbase/thirdparty/com/google/protobuf/Descriptors$ServiceDescriptor;
       7: invokevirtual #5                  // Method org/apache/hbase/thirdparty/com/google/protobuf/Descriptors$ServiceDescriptor.getMethods:()Ljava/util/List;
      10: iconst_5
      11: invokeinterface #6,  2            // InterfaceMethod java/util/List.get:(I)Ljava/lang/Object;
      16: checkcast     #7                  // class org/apache/hbase/thirdparty/com/google/protobuf/Descriptors$MethodDescriptor
      19: aload_1
      20: aload_2
      21: invokestatic  #20                 // Method org/apache/hadoop/hbase/shaded/protobuf/generated/RegionServerStatusProtos$RegionSpaceUseReportResponse.getDefaultInstance:()Lorg/apache/hadoop/hbase/shaded/protobuf/generated/RegionServerStatusProtos$RegionSpaceUseReportResponse;
      24: aload_3
      25: ldc           #21                 // class org/apache/hadoop/hbase/shaded/protobuf/generated/RegionServerStatusProtos$RegionSpaceUseReportResponse
      27: invokestatic  #20                 // Method org/apache/hadoop/hbase/shaded/protobuf/generated/RegionServerStatusProtos$RegionSpaceUseReportResponse.getDefaultInstance:()Lorg/apache/hadoop/hbase/shaded/protobuf/generated/RegionServerStatusProtos$RegionSpaceUseReportResponse;
      30: invokestatic  #10                 // Method org/apache/hbase/thirdparty/com/google/protobuf/RpcUtil.generalizeCallback:(Lorg/apache/hbase/thirdparty/com/google/protobuf/RpcCallback;Ljava/lang/Class;Lorg/apache/hbase/thirdparty/com/google/protobuf/Message;)Lorg/apache/hbase/thirdparty/com/google/protobuf/RpcCallback;
      33: invokeinterface #11,  6           // InterfaceMethod org/apache/hbase/thirdparty/com/google/protobuf/RpcChannel.callMethod:(Lorg/apache/hbase/thirdparty/com/google/protobuf/Descriptors$MethodDescriptor;Lorg/apache/hbase/thirdparty/com/google/protobuf/RpcController;Lorg/apache/hbase/thirdparty/com/google/protobuf/Message;Lorg/apache/hbase/thirdparty/com/google/protobuf/Message;Lorg/apache/hbase/thirdparty/com/google/protobuf/RpcCallback;)V
      38: return

  public void reportProcedureDone(org.apache.hbase.thirdparty.com.google.protobuf.RpcController, org.apache.hadoop.hbase.shaded.protobuf.generated.RegionServerStatusProtos$ReportProcedureDoneRequest, org.apache.hbase.thirdparty.com.google.protobuf.RpcCallback<org.apache.hadoop.hbase.shaded.protobuf.generated.RegionServerStatusProtos$ReportProcedureDoneResponse>);
    Code:
       0: aload_0
       1: getfield      #3                  // Field channel:Lorg/apache/hbase/thirdparty/com/google/protobuf/RpcChannel;
       4: invokestatic  #4                  // Method getDescriptor:()Lorg/apache/hbase/thirdparty/com/google/protobuf/Descriptors$ServiceDescriptor;
       7: invokevirtual #5                  // Method org/apache/hbase/thirdparty/com/google/protobuf/Descriptors$ServiceDescriptor.getMethods:()Ljava/util/List;
      10: bipush        6
      12: invokeinterface #6,  2            // InterfaceMethod java/util/List.get:(I)Ljava/lang/Object;
      17: checkcast     #7                  // class org/apache/hbase/thirdparty/com/google/protobuf/Descriptors$MethodDescriptor
      20: aload_1
      21: aload_2
      22: invokestatic  #22                 // Method org/apache/hadoop/hbase/shaded/protobuf/generated/RegionServerStatusProtos$ReportProcedureDoneResponse.getDefaultInstance:()Lorg/apache/hadoop/hbase/shaded/protobuf/generated/RegionServerStatusProtos$ReportProcedureDoneResponse;
      25: aload_3
      26: ldc           #23                 // class org/apache/hadoop/hbase/shaded/protobuf/generated/RegionServerStatusProtos$ReportProcedureDoneResponse
      28: invokestatic  #22                 // Method org/apache/hadoop/hbase/shaded/protobuf/generated/RegionServerStatusProtos$ReportProcedureDoneResponse.getDefaultInstance:()Lorg/apache/hadoop/hbase/shaded/protobuf/generated/RegionServerStatusProtos$ReportProcedureDoneResponse;
      31: invokestatic  #10                 // Method org/apache/hbase/thirdparty/com/google/protobuf/RpcUtil.generalizeCallback:(Lorg/apache/hbase/thirdparty/com/google/protobuf/RpcCallback;Ljava/lang/Class;Lorg/apache/hbase/thirdparty/com/google/protobuf/Message;)Lorg/apache/hbase/thirdparty/com/google/protobuf/RpcCallback;
      34: invokeinterface #11,  6           // InterfaceMethod org/apache/hbase/thirdparty/com/google/protobuf/RpcChannel.callMethod:(Lorg/apache/hbase/thirdparty/com/google/protobuf/Descriptors$MethodDescriptor;Lorg/apache/hbase/thirdparty/com/google/protobuf/RpcController;Lorg/apache/hbase/thirdparty/com/google/protobuf/Message;Lorg/apache/hbase/thirdparty/com/google/protobuf/Message;Lorg/apache/hbase/thirdparty/com/google/protobuf/RpcCallback;)V
      39: return

  public void reportFileArchival(org.apache.hbase.thirdparty.com.google.protobuf.RpcController, org.apache.hadoop.hbase.shaded.protobuf.generated.RegionServerStatusProtos$FileArchiveNotificationRequest, org.apache.hbase.thirdparty.com.google.protobuf.RpcCallback<org.apache.hadoop.hbase.shaded.protobuf.generated.RegionServerStatusProtos$FileArchiveNotificationResponse>);
    Code:
       0: aload_0
       1: getfield      #3                  // Field channel:Lorg/apache/hbase/thirdparty/com/google/protobuf/RpcChannel;
       4: invokestatic  #4                  // Method getDescriptor:()Lorg/apache/hbase/thirdparty/com/google/protobuf/Descriptors$ServiceDescriptor;
       7: invokevirtual #5                  // Method org/apache/hbase/thirdparty/com/google/protobuf/Descriptors$ServiceDescriptor.getMethods:()Ljava/util/List;
      10: bipush        7
      12: invokeinterface #6,  2            // InterfaceMethod java/util/List.get:(I)Ljava/lang/Object;
      17: checkcast     #7                  // class org/apache/hbase/thirdparty/com/google/protobuf/Descriptors$MethodDescriptor
      20: aload_1
      21: aload_2
      22: invokestatic  #24                 // Method org/apache/hadoop/hbase/shaded/protobuf/generated/RegionServerStatusProtos$FileArchiveNotificationResponse.getDefaultInstance:()Lorg/apache/hadoop/hbase/shaded/protobuf/generated/RegionServerStatusProtos$FileArchiveNotificationResponse;
      25: aload_3
      26: ldc           #25                 // class org/apache/hadoop/hbase/shaded/protobuf/generated/RegionServerStatusProtos$FileArchiveNotificationResponse
      28: invokestatic  #24                 // Method org/apache/hadoop/hbase/shaded/protobuf/generated/RegionServerStatusProtos$FileArchiveNotificationResponse.getDefaultInstance:()Lorg/apache/hadoop/hbase/shaded/protobuf/generated/RegionServerStatusProtos$FileArchiveNotificationResponse;
      31: invokestatic  #10                 // Method org/apache/hbase/thirdparty/com/google/protobuf/RpcUtil.generalizeCallback:(Lorg/apache/hbase/thirdparty/com/google/protobuf/RpcCallback;Ljava/lang/Class;Lorg/apache/hbase/thirdparty/com/google/protobuf/Message;)Lorg/apache/hbase/thirdparty/com/google/protobuf/RpcCallback;
      34: invokeinterface #11,  6           // InterfaceMethod org/apache/hbase/thirdparty/com/google/protobuf/RpcChannel.callMethod:(Lorg/apache/hbase/thirdparty/com/google/protobuf/Descriptors$MethodDescriptor;Lorg/apache/hbase/thirdparty/com/google/protobuf/RpcController;Lorg/apache/hbase/thirdparty/com/google/protobuf/Message;Lorg/apache/hbase/thirdparty/com/google/protobuf/Message;Lorg/apache/hbase/thirdparty/com/google/protobuf/RpcCallback;)V
      39: return

  org.apache.hadoop.hbase.shaded.protobuf.generated.RegionServerStatusProtos$RegionServerStatusService$Stub(org.apache.hbase.thirdparty.com.google.protobuf.RpcChannel, org.apache.hadoop.hbase.shaded.protobuf.generated.RegionServerStatusProtos$1);
    Code:
       0: aload_0
       1: aload_1
       2: invokespecial #1                  // Method "<init>":(Lorg/apache/hbase/thirdparty/com/google/protobuf/RpcChannel;)V
       5: return
}
