Compiled from "RegionCoprocessorHost.java"
class org.apache.hadoop.hbase.regionserver.RegionCoprocessorHost$66 extends org.apache.hadoop.hbase.coprocessor.CoprocessorHost<org.apache.hadoop.hbase.coprocessor.RegionCoprocessor, org.apache.hadoop.hbase.coprocessor.RegionCoprocessorEnvironment>.ObserverOperationWithoutResult<org.apache.hadoop.hbase.coprocessor.EndpointObserver> {
  final com.google.protobuf.Service val$service;

  final java.lang.String val$methodName;

  final com.google.protobuf.Message val$request;

  final com.google.protobuf.Message$Builder val$responseBuilder;

  final org.apache.hadoop.hbase.regionserver.RegionCoprocessorHost this$0;

  org.apache.hadoop.hbase.regionserver.RegionCoprocessorHost$66(org.apache.hadoop.hbase.regionserver.RegionCoprocessorHost, org.apache.hadoop.hbase.coprocessor.CoprocessorHost$ObserverGetter, com.google.protobuf.Service, java.lang.String, com.google.protobuf.Message, com.google.protobuf.Message$Builder);
    Code:
       0: aload_0
       1: aload_1
       2: putfield      #1                  // Field this$0:Lorg/apache/hadoop/hbase/regionserver/RegionCoprocessorHost;
       5: aload_0
       6: aload_3
       7: putfield      #2                  // Field val$service:Lcom/google/protobuf/Service;
      10: aload_0
      11: aload         4
      13: putfield      #3                  // Field val$methodName:Ljava/lang/String;
      16: aload_0
      17: aload         5
      19: putfield      #4                  // Field val$request:Lcom/google/protobuf/Message;
      22: aload_0
      23: aload         6
      25: putfield      #5                  // Field val$responseBuilder:Lcom/google/protobuf/Message$Builder;
      28: aload_0
      29: aload_1
      30: aload_2
      31: invokespecial #6                  // Method org/apache/hadoop/hbase/coprocessor/CoprocessorHost$ObserverOperationWithoutResult."<init>":(Lorg/apache/hadoop/hbase/coprocessor/CoprocessorHost;Lorg/apache/hadoop/hbase/coprocessor/CoprocessorHost$ObserverGetter;)V
      34: return

  public void call(org.apache.hadoop.hbase.coprocessor.EndpointObserver) throws java.io.IOException;
    Code:
       0: aload_1
       1: aload_0
       2: aload_0
       3: getfield      #2                  // Field val$service:Lcom/google/protobuf/Service;
       6: aload_0
       7: getfield      #3                  // Field val$methodName:Ljava/lang/String;
      10: aload_0
      11: getfield      #4                  // Field val$request:Lcom/google/protobuf/Message;
      14: aload_0
      15: getfield      #5                  // Field val$responseBuilder:Lcom/google/protobuf/Message$Builder;
      18: invokeinterface #7,  6            // InterfaceMethod org/apache/hadoop/hbase/coprocessor/EndpointObserver.postEndpointInvocation:(Lorg/apache/hadoop/hbase/coprocessor/ObserverContext;Lcom/google/protobuf/Service;Ljava/lang/String;Lcom/google/protobuf/Message;Lcom/google/protobuf/Message$Builder;)V
      23: return

  public void call(java.lang.Object) throws java.io.IOException;
    Code:
       0: aload_0
       1: aload_1
       2: checkcast     #8                  // class org/apache/hadoop/hbase/coprocessor/EndpointObserver
       5: invokevirtual #9                  // Method call:(Lorg/apache/hadoop/hbase/coprocessor/EndpointObserver;)V
       8: return
}
