Compiled from "RemoteProcedureException.java"
public class org.apache.hadoop.hbase.procedure2.RemoteProcedureException extends org.apache.hadoop.hbase.procedure2.ProcedureException {
  static final boolean $assertionsDisabled;

  public org.apache.hadoop.hbase.procedure2.RemoteProcedureException(java.lang.String, java.lang.Throwable);
    Code:
       0: aload_0
       1: aload_2
       2: invokespecial #1                  // Method org/apache/hadoop/hbase/procedure2/ProcedureException."<init>":(Ljava/lang/Throwable;)V
       5: getstatic     #2                  // Field $assertionsDisabled:Z
       8: ifne          23
      11: aload_1
      12: ifnonnull     23
      15: new           #3                  // class java/lang/AssertionError
      18: dup
      19: invokespecial #4                  // Method java/lang/AssertionError."<init>":()V
      22: athrow
      23: getstatic     #2                  // Field $assertionsDisabled:Z
      26: ifne          41
      29: aload_2
      30: ifnonnull     41
      33: new           #3                  // class java/lang/AssertionError
      36: dup
      37: invokespecial #4                  // Method java/lang/AssertionError."<init>":()V
      40: athrow
      41: aload_0
      42: aload_1
      43: putfield      #5                  // Field source:Ljava/lang/String;
      46: return

  public java.lang.String getSource();
    Code:
       0: aload_0
       1: getfield      #5                  // Field source:Ljava/lang/String;
       4: areturn

  public java.lang.Exception unwrapRemoteException();
    Code:
       0: aload_0
       1: invokevirtual #6                  // Method getCause:()Ljava/lang/Throwable;
       4: astore_1
       5: aload_1
       6: instanceof    #7                  // class org/apache/hadoop/ipc/RemoteException
       9: ifeq          20
      12: aload_1
      13: checkcast     #7                  // class org/apache/hadoop/ipc/RemoteException
      16: invokevirtual #8                  // Method org/apache/hadoop/ipc/RemoteException.unwrapRemoteException:()Ljava/io/IOException;
      19: areturn
      20: aload_1
      21: instanceof    #9                  // class java/lang/Exception
      24: ifeq          32
      27: aload_1
      28: checkcast     #9                  // class java/lang/Exception
      31: areturn
      32: new           #9                  // class java/lang/Exception
      35: dup
      36: aload_1
      37: invokespecial #10                 // Method java/lang/Exception."<init>":(Ljava/lang/Throwable;)V
      40: areturn

  public java.io.IOException unwrapRemoteIOException();
    Code:
       0: aload_0
       1: invokevirtual #11                 // Method unwrapRemoteException:()Ljava/lang/Exception;
       4: astore_1
       5: aload_1
       6: instanceof    #12                 // class java/io/IOException
       9: ifeq          17
      12: aload_1
      13: checkcast     #12                 // class java/io/IOException
      16: areturn
      17: new           #12                 // class java/io/IOException
      20: dup
      21: aload_1
      22: invokespecial #13                 // Method java/io/IOException."<init>":(Ljava/lang/Throwable;)V
      25: areturn

  public java.lang.String toString();
    Code:
       0: aload_0
       1: invokevirtual #6                  // Method getCause:()Ljava/lang/Throwable;
       4: invokevirtual #14                 // Method java/lang/Object.getClass:()Ljava/lang/Class;
       7: invokevirtual #15                 // Method java/lang/Class.getName:()Ljava/lang/String;
      10: astore_1
      11: new           #16                 // class java/lang/StringBuilder
      14: dup
      15: invokespecial #17                 // Method java/lang/StringBuilder."<init>":()V
      18: aload_1
      19: invokevirtual #18                 // Method java/lang/StringBuilder.append:(Ljava/lang/String;)Ljava/lang/StringBuilder;
      22: ldc           #19                 // String  via
      24: invokevirtual #18                 // Method java/lang/StringBuilder.append:(Ljava/lang/String;)Ljava/lang/StringBuilder;
      27: aload_0
      28: invokevirtual #20                 // Method getSource:()Ljava/lang/String;
      31: invokevirtual #18                 // Method java/lang/StringBuilder.append:(Ljava/lang/String;)Ljava/lang/StringBuilder;
      34: ldc           #21                 // String :
      36: invokevirtual #18                 // Method java/lang/StringBuilder.append:(Ljava/lang/String;)Ljava/lang/StringBuilder;
      39: aload_0
      40: invokevirtual #22                 // Method getLocalizedMessage:()Ljava/lang/String;
      43: invokevirtual #18                 // Method java/lang/StringBuilder.append:(Ljava/lang/String;)Ljava/lang/StringBuilder;
      46: invokevirtual #23                 // Method java/lang/StringBuilder.toString:()Ljava/lang/String;
      49: areturn

  public static byte[] serialize(java.lang.String, java.lang.Throwable);
    Code:
       0: aload_0
       1: aload_1
       2: invokestatic  #24                 // Method toProto:(Ljava/lang/String;Ljava/lang/Throwable;)Lorg/apache/hadoop/hbase/shaded/protobuf/generated/ErrorHandlingProtos$ForeignExceptionMessage;
       5: invokevirtual #25                 // Method org/apache/hadoop/hbase/shaded/protobuf/generated/ErrorHandlingProtos$ForeignExceptionMessage.toByteArray:()[B
       8: areturn

  public static org.apache.hadoop.hbase.procedure2.RemoteProcedureException deserialize(byte[]) throws java.io.IOException;
    Code:
       0: aload_0
       1: invokestatic  #26                 // Method org/apache/hadoop/hbase/shaded/protobuf/generated/ErrorHandlingProtos$ForeignExceptionMessage.parseFrom:([B)Lorg/apache/hadoop/hbase/shaded/protobuf/generated/ErrorHandlingProtos$ForeignExceptionMessage;
       4: invokestatic  #27                 // Method fromProto:(Lorg/apache/hadoop/hbase/shaded/protobuf/generated/ErrorHandlingProtos$ForeignExceptionMessage;)Lorg/apache/hadoop/hbase/procedure2/RemoteProcedureException;
       7: areturn

  public org.apache.hadoop.hbase.shaded.protobuf.generated.ErrorHandlingProtos$ForeignExceptionMessage convert();
    Code:
       0: aload_0
       1: invokevirtual #20                 // Method getSource:()Ljava/lang/String;
       4: aload_0
       5: invokevirtual #6                  // Method getCause:()Ljava/lang/Throwable;
       8: invokestatic  #28                 // Method org/apache/hadoop/hbase/util/ForeignExceptionUtil.toProtoForeignException:(Ljava/lang/String;Ljava/lang/Throwable;)Lorg/apache/hadoop/hbase/shaded/protobuf/generated/ErrorHandlingProtos$ForeignExceptionMessage;
      11: areturn

  public static org.apache.hadoop.hbase.shaded.protobuf.generated.ErrorHandlingProtos$ForeignExceptionMessage toProto(java.lang.String, java.lang.Throwable);
    Code:
       0: aload_0
       1: aload_1
       2: invokestatic  #28                 // Method org/apache/hadoop/hbase/util/ForeignExceptionUtil.toProtoForeignException:(Ljava/lang/String;Ljava/lang/Throwable;)Lorg/apache/hadoop/hbase/shaded/protobuf/generated/ErrorHandlingProtos$ForeignExceptionMessage;
       5: areturn

  public static org.apache.hadoop.hbase.procedure2.RemoteProcedureException fromProto(org.apache.hadoop.hbase.shaded.protobuf.generated.ErrorHandlingProtos$ForeignExceptionMessage);
    Code:
       0: new           #29                 // class org/apache/hadoop/hbase/procedure2/RemoteProcedureException
       3: dup
       4: aload_0
       5: invokevirtual #30                 // Method org/apache/hadoop/hbase/shaded/protobuf/generated/ErrorHandlingProtos$ForeignExceptionMessage.getSource:()Ljava/lang/String;
       8: aload_0
       9: invokestatic  #31                 // Method org/apache/hadoop/hbase/util/ForeignExceptionUtil.toException:(Lorg/apache/hadoop/hbase/shaded/protobuf/generated/ErrorHandlingProtos$ForeignExceptionMessage;)Ljava/lang/Exception;
      12: invokespecial #32                 // Method "<init>":(Ljava/lang/String;Ljava/lang/Throwable;)V
      15: areturn

  static {};
    Code:
       0: ldc           #29                 // class org/apache/hadoop/hbase/procedure2/RemoteProcedureException
       2: invokevirtual #33                 // Method java/lang/Class.desiredAssertionStatus:()Z
       5: ifne          12
       8: iconst_1
       9: goto          13
      12: iconst_0
      13: putstatic     #2                  // Field $assertionsDisabled:Z
      16: return
}
