Compiled from "RemovePeerProcedure.java"
public class org.apache.hadoop.hbase.master.replication.RemovePeerProcedure extends org.apache.hadoop.hbase.master.replication.ModifyPeerProcedure {
  public org.apache.hadoop.hbase.master.replication.RemovePeerProcedure();
    Code:
       0: aload_0
       1: invokespecial #1                  // Method org/apache/hadoop/hbase/master/replication/ModifyPeerProcedure."<init>":()V
       4: return

  public org.apache.hadoop.hbase.master.replication.RemovePeerProcedure(java.lang.String);
    Code:
       0: aload_0
       1: aload_1
       2: invokespecial #2                  // Method org/apache/hadoop/hbase/master/replication/ModifyPeerProcedure."<init>":(Ljava/lang/String;)V
       5: return

  public org.apache.hadoop.hbase.master.procedure.PeerProcedureInterface$PeerOperationType getPeerOperationType();
    Code:
       0: getstatic     #3                  // Field org/apache/hadoop/hbase/master/procedure/PeerProcedureInterface$PeerOperationType.REMOVE:Lorg/apache/hadoop/hbase/master/procedure/PeerProcedureInterface$PeerOperationType;
       3: areturn

  protected void prePeerModification(org.apache.hadoop.hbase.master.procedure.MasterProcedureEnv) throws java.io.IOException;
    Code:
       0: aload_1
       1: invokevirtual #4                  // Method org/apache/hadoop/hbase/master/procedure/MasterProcedureEnv.getMasterCoprocessorHost:()Lorg/apache/hadoop/hbase/master/MasterCoprocessorHost;
       4: astore_2
       5: aload_2
       6: ifnull        17
       9: aload_2
      10: aload_0
      11: getfield      #5                  // Field peerId:Ljava/lang/String;
      14: invokevirtual #6                  // Method org/apache/hadoop/hbase/master/MasterCoprocessorHost.preRemoveReplicationPeer:(Ljava/lang/String;)V
      17: aload_0
      18: aload_1
      19: invokevirtual #7                  // Method org/apache/hadoop/hbase/master/procedure/MasterProcedureEnv.getReplicationPeerManager:()Lorg/apache/hadoop/hbase/master/replication/ReplicationPeerManager;
      22: aload_0
      23: getfield      #5                  // Field peerId:Ljava/lang/String;
      26: invokevirtual #8                  // Method org/apache/hadoop/hbase/master/replication/ReplicationPeerManager.preRemovePeer:(Ljava/lang/String;)Lorg/apache/hadoop/hbase/replication/ReplicationPeerConfig;
      29: putfield      #9                  // Field peerConfig:Lorg/apache/hadoop/hbase/replication/ReplicationPeerConfig;
      32: return

  protected void updatePeerStorage(org.apache.hadoop.hbase.master.procedure.MasterProcedureEnv) throws org.apache.hadoop.hbase.replication.ReplicationException;
    Code:
       0: aload_1
       1: invokevirtual #7                  // Method org/apache/hadoop/hbase/master/procedure/MasterProcedureEnv.getReplicationPeerManager:()Lorg/apache/hadoop/hbase/master/replication/ReplicationPeerManager;
       4: aload_0
       5: getfield      #5                  // Field peerId:Ljava/lang/String;
       8: invokevirtual #10                 // Method org/apache/hadoop/hbase/master/replication/ReplicationPeerManager.removePeer:(Ljava/lang/String;)V
      11: return

  protected void postPeerModification(org.apache.hadoop.hbase.master.procedure.MasterProcedureEnv) throws java.io.IOException, org.apache.hadoop.hbase.replication.ReplicationException;
    Code:
       0: aload_0
       1: getfield      #9                  // Field peerConfig:Lorg/apache/hadoop/hbase/replication/ReplicationPeerConfig;
       4: invokevirtual #14                 // Method org/apache/hadoop/hbase/replication/ReplicationPeerConfig.isSyncReplication:()Z
       7: ifeq          15
      10: aload_0
      11: aload_1
      12: invokespecial #15                 // Method removeRemoteWALs:(Lorg/apache/hadoop/hbase/master/procedure/MasterProcedureEnv;)V
      15: aload_1
      16: invokevirtual #7                  // Method org/apache/hadoop/hbase/master/procedure/MasterProcedureEnv.getReplicationPeerManager:()Lorg/apache/hadoop/hbase/master/replication/ReplicationPeerManager;
      19: aload_0
      20: getfield      #5                  // Field peerId:Ljava/lang/String;
      23: invokevirtual #16                 // Method org/apache/hadoop/hbase/master/replication/ReplicationPeerManager.removeAllQueuesAndHFileRefs:(Ljava/lang/String;)V
      26: aload_0
      27: getfield      #9                  // Field peerConfig:Lorg/apache/hadoop/hbase/replication/ReplicationPeerConfig;
      30: invokevirtual #17                 // Method org/apache/hadoop/hbase/replication/ReplicationPeerConfig.isSerial:()Z
      33: ifeq          47
      36: aload_1
      37: invokevirtual #7                  // Method org/apache/hadoop/hbase/master/procedure/MasterProcedureEnv.getReplicationPeerManager:()Lorg/apache/hadoop/hbase/master/replication/ReplicationPeerManager;
      40: aload_0
      41: getfield      #5                  // Field peerId:Ljava/lang/String;
      44: invokevirtual #18                 // Method org/apache/hadoop/hbase/master/replication/ReplicationPeerManager.removeAllLastPushedSeqIds:(Ljava/lang/String;)V
      47: getstatic     #19                 // Field LOG:Lorg/slf4j/Logger;
      50: ldc           #20                 // String Successfully removed peer {}
      52: aload_0
      53: getfield      #5                  // Field peerId:Ljava/lang/String;
      56: invokeinterface #21,  3           // InterfaceMethod org/slf4j/Logger.info:(Ljava/lang/String;Ljava/lang/Object;)V
      61: aload_1
      62: invokevirtual #4                  // Method org/apache/hadoop/hbase/master/procedure/MasterProcedureEnv.getMasterCoprocessorHost:()Lorg/apache/hadoop/hbase/master/MasterCoprocessorHost;
      65: astore_2
      66: aload_2
      67: ifnull        78
      70: aload_2
      71: aload_0
      72: getfield      #5                  // Field peerId:Ljava/lang/String;
      75: invokevirtual #22                 // Method org/apache/hadoop/hbase/master/MasterCoprocessorHost.postRemoveReplicationPeer:(Ljava/lang/String;)V
      78: return

  protected void serializeStateData(org.apache.hadoop.hbase.procedure2.ProcedureStateSerializer) throws java.io.IOException;
    Code:
       0: aload_0
       1: aload_1
       2: invokespecial #23                 // Method org/apache/hadoop/hbase/master/replication/ModifyPeerProcedure.serializeStateData:(Lorg/apache/hadoop/hbase/procedure2/ProcedureStateSerializer;)V
       5: invokestatic  #24                 // Method org/apache/hadoop/hbase/shaded/protobuf/generated/MasterProcedureProtos$RemovePeerStateData.newBuilder:()Lorg/apache/hadoop/hbase/shaded/protobuf/generated/MasterProcedureProtos$RemovePeerStateData$Builder;
       8: astore_2
       9: aload_0
      10: getfield      #9                  // Field peerConfig:Lorg/apache/hadoop/hbase/replication/ReplicationPeerConfig;
      13: ifnull        28
      16: aload_2
      17: aload_0
      18: getfield      #9                  // Field peerConfig:Lorg/apache/hadoop/hbase/replication/ReplicationPeerConfig;
      21: invokestatic  #25                 // Method org/apache/hadoop/hbase/client/replication/ReplicationPeerConfigUtil.convert:(Lorg/apache/hadoop/hbase/replication/ReplicationPeerConfig;)Lorg/apache/hadoop/hbase/shaded/protobuf/generated/ReplicationProtos$ReplicationPeer;
      24: invokevirtual #26                 // Method org/apache/hadoop/hbase/shaded/protobuf/generated/MasterProcedureProtos$RemovePeerStateData$Builder.setPeerConfig:(Lorg/apache/hadoop/hbase/shaded/protobuf/generated/ReplicationProtos$ReplicationPeer;)Lorg/apache/hadoop/hbase/shaded/protobuf/generated/MasterProcedureProtos$RemovePeerStateData$Builder;
      27: pop
      28: aload_1
      29: aload_2
      30: invokevirtual #27                 // Method org/apache/hadoop/hbase/shaded/protobuf/generated/MasterProcedureProtos$RemovePeerStateData$Builder.build:()Lorg/apache/hadoop/hbase/shaded/protobuf/generated/MasterProcedureProtos$RemovePeerStateData;
      33: invokeinterface #28,  2           // InterfaceMethod org/apache/hadoop/hbase/procedure2/ProcedureStateSerializer.serialize:(Lorg/apache/hbase/thirdparty/com/google/protobuf/Message;)V
      38: return

  protected void deserializeStateData(org.apache.hadoop.hbase.procedure2.ProcedureStateSerializer) throws java.io.IOException;
    Code:
       0: aload_0
       1: aload_1
       2: invokespecial #29                 // Method org/apache/hadoop/hbase/master/replication/ModifyPeerProcedure.deserializeStateData:(Lorg/apache/hadoop/hbase/procedure2/ProcedureStateSerializer;)V
       5: aload_1
       6: ldc           #30                 // class org/apache/hadoop/hbase/shaded/protobuf/generated/MasterProcedureProtos$RemovePeerStateData
       8: invokeinterface #31,  2           // InterfaceMethod org/apache/hadoop/hbase/procedure2/ProcedureStateSerializer.deserialize:(Ljava/lang/Class;)Lorg/apache/hbase/thirdparty/com/google/protobuf/Message;
      13: checkcast     #30                 // class org/apache/hadoop/hbase/shaded/protobuf/generated/MasterProcedureProtos$RemovePeerStateData
      16: astore_2
      17: aload_2
      18: invokevirtual #32                 // Method org/apache/hadoop/hbase/shaded/protobuf/generated/MasterProcedureProtos$RemovePeerStateData.hasPeerConfig:()Z
      21: ifeq          35
      24: aload_0
      25: aload_2
      26: invokevirtual #33                 // Method org/apache/hadoop/hbase/shaded/protobuf/generated/MasterProcedureProtos$RemovePeerStateData.getPeerConfig:()Lorg/apache/hadoop/hbase/shaded/protobuf/generated/ReplicationProtos$ReplicationPeer;
      29: invokestatic  #34                 // Method org/apache/hadoop/hbase/client/replication/ReplicationPeerConfigUtil.convert:(Lorg/apache/hadoop/hbase/shaded/protobuf/generated/ReplicationProtos$ReplicationPeer;)Lorg/apache/hadoop/hbase/replication/ReplicationPeerConfig;
      32: putfield      #9                  // Field peerConfig:Lorg/apache/hadoop/hbase/replication/ReplicationPeerConfig;
      35: return

  static {};
    Code:
       0: ldc           #35                 // class org/apache/hadoop/hbase/master/replication/RemovePeerProcedure
       2: invokestatic  #36                 // Method org/slf4j/LoggerFactory.getLogger:(Ljava/lang/Class;)Lorg/slf4j/Logger;
       5: putstatic     #19                 // Field LOG:Lorg/slf4j/Logger;
       8: return
}
