Compiled from "ReopenTableRegionsProcedure.java"
public class org.apache.hadoop.hbase.master.procedure.ReopenTableRegionsProcedure extends org.apache.hadoop.hbase.master.procedure.AbstractStateMachineTableProcedure<org.apache.hadoop.hbase.shaded.protobuf.generated.MasterProcedureProtos$ReopenTableRegionsState> {
  public org.apache.hadoop.hbase.master.procedure.ReopenTableRegionsProcedure();
    Code:
       0: aload_0
       1: invokespecial #1                  // Method org/apache/hadoop/hbase/master/procedure/AbstractStateMachineTableProcedure."<init>":()V
       4: aload_0
       5: invokestatic  #2                  // Method java/util/Collections.emptyList:()Ljava/util/List;
       8: putfield      #3                  // Field regions:Ljava/util/List;
      11: return

  public org.apache.hadoop.hbase.master.procedure.ReopenTableRegionsProcedure(org.apache.hadoop.hbase.TableName);
    Code:
       0: aload_0
       1: invokespecial #1                  // Method org/apache/hadoop/hbase/master/procedure/AbstractStateMachineTableProcedure."<init>":()V
       4: aload_0
       5: invokestatic  #2                  // Method java/util/Collections.emptyList:()Ljava/util/List;
       8: putfield      #3                  // Field regions:Ljava/util/List;
      11: aload_0
      12: aload_1
      13: putfield      #4                  // Field tableName:Lorg/apache/hadoop/hbase/TableName;
      16: return

  public org.apache.hadoop.hbase.TableName getTableName();
    Code:
       0: aload_0
       1: getfield      #4                  // Field tableName:Lorg/apache/hadoop/hbase/TableName;
       4: areturn

  public org.apache.hadoop.hbase.master.procedure.TableProcedureInterface$TableOperationType getTableOperationType();
    Code:
       0: getstatic     #5                  // Field org/apache/hadoop/hbase/master/procedure/TableProcedureInterface$TableOperationType.REGION_EDIT:Lorg/apache/hadoop/hbase/master/procedure/TableProcedureInterface$TableOperationType;
       3: areturn

  protected org.apache.hadoop.hbase.procedure2.StateMachineProcedure$Flow executeFromState(org.apache.hadoop.hbase.master.procedure.MasterProcedureEnv, org.apache.hadoop.hbase.shaded.protobuf.generated.MasterProcedureProtos$ReopenTableRegionsState) throws org.apache.hadoop.hbase.procedure2.ProcedureSuspendedException, org.apache.hadoop.hbase.procedure2.ProcedureYieldException, java.lang.InterruptedException;
    Code:
       0: getstatic     #12                 // Field org/apache/hadoop/hbase/master/procedure/ReopenTableRegionsProcedure$1.$SwitchMap$org$apache$hadoop$hbase$shaded$protobuf$generated$MasterProcedureProtos$ReopenTableRegionsState:[I
       3: aload_2
       4: invokevirtual #13                 // Method org/apache/hadoop/hbase/shaded/protobuf/generated/MasterProcedureProtos$ReopenTableRegionsState.ordinal:()I
       7: iaload
       8: tableswitch   { // 1 to 3
                     1: 36
                     2: 97
                     3: 236
               default: 448
          }
      36: aload_1
      37: invokevirtual #7                  // Method org/apache/hadoop/hbase/master/procedure/MasterProcedureEnv.getAssignmentManager:()Lorg/apache/hadoop/hbase/master/assignment/AssignmentManager;
      40: aload_0
      41: getfield      #4                  // Field tableName:Lorg/apache/hadoop/hbase/TableName;
      44: invokevirtual #14                 // Method org/apache/hadoop/hbase/master/assignment/AssignmentManager.isTableEnabled:(Lorg/apache/hadoop/hbase/TableName;)Z
      47: ifne          68
      50: getstatic     #15                 // Field LOG:Lorg/slf4j/Logger;
      53: ldc           #16                 // String Table {} is disabled, give up reopening its regions
      55: aload_0
      56: getfield      #4                  // Field tableName:Lorg/apache/hadoop/hbase/TableName;
      59: invokeinterface #17,  3           // InterfaceMethod org/slf4j/Logger.info:(Ljava/lang/String;Ljava/lang/Object;)V
      64: getstatic     #18                 // Field org/apache/hadoop/hbase/procedure2/StateMachineProcedure$Flow.NO_MORE_STATE:Lorg/apache/hadoop/hbase/procedure2/StateMachineProcedure$Flow;
      67: areturn
      68: aload_0
      69: aload_1
      70: invokevirtual #7                  // Method org/apache/hadoop/hbase/master/procedure/MasterProcedureEnv.getAssignmentManager:()Lorg/apache/hadoop/hbase/master/assignment/AssignmentManager;
      73: invokevirtual #8                  // Method org/apache/hadoop/hbase/master/assignment/AssignmentManager.getRegionStates:()Lorg/apache/hadoop/hbase/master/assignment/RegionStates;
      76: aload_0
      77: getfield      #4                  // Field tableName:Lorg/apache/hadoop/hbase/TableName;
      80: invokevirtual #19                 // Method org/apache/hadoop/hbase/master/assignment/RegionStates.getRegionsOfTableForReopen:(Lorg/apache/hadoop/hbase/TableName;)Ljava/util/List;
      83: putfield      #3                  // Field regions:Ljava/util/List;
      86: aload_0
      87: getstatic     #20                 // Field org/apache/hadoop/hbase/shaded/protobuf/generated/MasterProcedureProtos$ReopenTableRegionsState.REOPEN_TABLE_REGIONS_REOPEN_REGIONS:Lorg/apache/hadoop/hbase/shaded/protobuf/generated/MasterProcedureProtos$ReopenTableRegionsState;
      90: invokevirtual #21                 // Method setNextState:(Ljava/lang/Object;)V
      93: getstatic     #22                 // Field org/apache/hadoop/hbase/procedure2/StateMachineProcedure$Flow.HAS_MORE_STATE:Lorg/apache/hadoop/hbase/procedure2/StateMachineProcedure$Flow;
      96: areturn
      97: aload_0
      98: getfield      #3                  // Field regions:Ljava/util/List;
     101: invokeinterface #23,  1           // InterfaceMethod java/util/List.iterator:()Ljava/util/Iterator;
     106: astore_3
     107: aload_3
     108: invokeinterface #24,  1           // InterfaceMethod java/util/Iterator.hasNext:()Z
     113: ifeq          225
     116: aload_3
     117: invokeinterface #25,  1           // InterfaceMethod java/util/Iterator.next:()Ljava/lang/Object;
     122: checkcast     #26                 // class org/apache/hadoop/hbase/HRegionLocation
     125: astore        4
     127: aload_1
     128: invokevirtual #7                  // Method org/apache/hadoop/hbase/master/procedure/MasterProcedureEnv.getAssignmentManager:()Lorg/apache/hadoop/hbase/master/assignment/AssignmentManager;
     131: invokevirtual #8                  // Method org/apache/hadoop/hbase/master/assignment/AssignmentManager.getRegionStates:()Lorg/apache/hadoop/hbase/master/assignment/RegionStates;
     134: aload         4
     136: invokevirtual #9                  // Method org/apache/hadoop/hbase/HRegionLocation.getRegion:()Lorg/apache/hadoop/hbase/client/RegionInfo;
     139: invokevirtual #10                 // Method org/apache/hadoop/hbase/master/assignment/RegionStates.getRegionStateNode:(Lorg/apache/hadoop/hbase/client/RegionInfo;)Lorg/apache/hadoop/hbase/master/assignment/RegionStateNode;
     142: astore        5
     144: aload         5
     146: ifnonnull     152
     149: goto          107
     152: aload         5
     154: invokevirtual #27                 // Method org/apache/hadoop/hbase/master/assignment/RegionStateNode.lock:()V
     157: aload         5
     159: invokevirtual #28                 // Method org/apache/hadoop/hbase/master/assignment/RegionStateNode.getProcedure:()Lorg/apache/hadoop/hbase/master/assignment/TransitRegionStateProcedure;
     162: ifnull        173
     165: aload         5
     167: invokevirtual #29                 // Method org/apache/hadoop/hbase/master/assignment/RegionStateNode.unlock:()V
     170: goto          107
     173: aload_1
     174: aload         5
     176: invokevirtual #30                 // Method org/apache/hadoop/hbase/master/assignment/RegionStateNode.getRegionInfo:()Lorg/apache/hadoop/hbase/client/RegionInfo;
     179: invokestatic  #31                 // Method org/apache/hadoop/hbase/master/assignment/TransitRegionStateProcedure.reopen:(Lorg/apache/hadoop/hbase/master/procedure/MasterProcedureEnv;Lorg/apache/hadoop/hbase/client/RegionInfo;)Lorg/apache/hadoop/hbase/master/assignment/TransitRegionStateProcedure;
     182: astore        6
     184: aload         5
     186: aload         6
     188: invokevirtual #32                 // Method org/apache/hadoop/hbase/master/assignment/RegionStateNode.setProcedure:(Lorg/apache/hadoop/hbase/master/assignment/TransitRegionStateProcedure;)V
     191: aload         5
     193: invokevirtual #29                 // Method org/apache/hadoop/hbase/master/assignment/RegionStateNode.unlock:()V
     196: goto          209
     199: astore        7
     201: aload         5
     203: invokevirtual #29                 // Method org/apache/hadoop/hbase/master/assignment/RegionStateNode.unlock:()V
     206: aload         7
     208: athrow
     209: aload_0
     210: iconst_1
     211: anewarray     #33                 // class org/apache/hadoop/hbase/master/assignment/TransitRegionStateProcedure
     214: dup
     215: iconst_0
     216: aload         6
     218: aastore
     219: invokevirtual #34                 // Method addChildProcedure:([Lorg/apache/hadoop/hbase/procedure2/Procedure;)V
     222: goto          107
     225: aload_0
     226: getstatic     #35                 // Field org/apache/hadoop/hbase/shaded/protobuf/generated/MasterProcedureProtos$ReopenTableRegionsState.REOPEN_TABLE_REGIONS_CONFIRM_REOPENED:Lorg/apache/hadoop/hbase/shaded/protobuf/generated/MasterProcedureProtos$ReopenTableRegionsState;
     229: invokevirtual #21                 // Method setNextState:(Ljava/lang/Object;)V
     232: getstatic     #22                 // Field org/apache/hadoop/hbase/procedure2/StateMachineProcedure$Flow.HAS_MORE_STATE:Lorg/apache/hadoop/hbase/procedure2/StateMachineProcedure$Flow;
     235: areturn
     236: aload_0
     237: aload_0
     238: getfield      #3                  // Field regions:Ljava/util/List;
     241: invokeinterface #36,  1           // InterfaceMethod java/util/List.stream:()Ljava/util/stream/Stream;
     246: aload_1
     247: invokevirtual #7                  // Method org/apache/hadoop/hbase/master/procedure/MasterProcedureEnv.getAssignmentManager:()Lorg/apache/hadoop/hbase/master/assignment/AssignmentManager;
     250: invokevirtual #8                  // Method org/apache/hadoop/hbase/master/assignment/AssignmentManager.getRegionStates:()Lorg/apache/hadoop/hbase/master/assignment/RegionStates;
     253: dup
     254: invokevirtual #37                 // Method java/lang/Object.getClass:()Ljava/lang/Class;
     257: pop
     258: invokedynamic #38,  0             // InvokeDynamic #0:apply:(Lorg/apache/hadoop/hbase/master/assignment/RegionStates;)Ljava/util/function/Function;
     263: invokeinterface #39,  2           // InterfaceMethod java/util/stream/Stream.map:(Ljava/util/function/Function;)Ljava/util/stream/Stream;
     268: invokedynamic #40,  0             // InvokeDynamic #1:test:()Ljava/util/function/Predicate;
     273: invokeinterface #41,  2           // InterfaceMethod java/util/stream/Stream.filter:(Ljava/util/function/Predicate;)Ljava/util/stream/Stream;
     278: invokestatic  #42                 // Method java/util/stream/Collectors.toList:()Ljava/util/stream/Collector;
     281: invokeinterface #43,  2           // InterfaceMethod java/util/stream/Stream.collect:(Ljava/util/stream/Collector;)Ljava/lang/Object;
     286: checkcast     #44                 // class java/util/List
     289: putfield      #3                  // Field regions:Ljava/util/List;
     292: aload_0
     293: getfield      #3                  // Field regions:Ljava/util/List;
     296: invokeinterface #45,  1           // InterfaceMethod java/util/List.isEmpty:()Z
     301: ifeq          308
     304: getstatic     #18                 // Field org/apache/hadoop/hbase/procedure2/StateMachineProcedure$Flow.NO_MORE_STATE:Lorg/apache/hadoop/hbase/procedure2/StateMachineProcedure$Flow;
     307: areturn
     308: aload_0
     309: getfield      #3                  // Field regions:Ljava/util/List;
     312: invokeinterface #36,  1           // InterfaceMethod java/util/List.stream:()Ljava/util/stream/Stream;
     317: aload_0
     318: aload_1
     319: invokedynamic #46,  0             // InvokeDynamic #2:test:(Lorg/apache/hadoop/hbase/master/procedure/ReopenTableRegionsProcedure;Lorg/apache/hadoop/hbase/master/procedure/MasterProcedureEnv;)Ljava/util/function/Predicate;
     324: invokeinterface #47,  2           // InterfaceMethod java/util/stream/Stream.anyMatch:(Ljava/util/function/Predicate;)Z
     329: ifeq          348
     332: aload_0
     333: aconst_null
     334: putfield      #48                 // Field retryCounter:Lorg/apache/hadoop/hbase/util/RetryCounter;
     337: aload_0
     338: getstatic     #20                 // Field org/apache/hadoop/hbase/shaded/protobuf/generated/MasterProcedureProtos$ReopenTableRegionsState.REOPEN_TABLE_REGIONS_REOPEN_REGIONS:Lorg/apache/hadoop/hbase/shaded/protobuf/generated/MasterProcedureProtos$ReopenTableRegionsState;
     341: invokevirtual #21                 // Method setNextState:(Ljava/lang/Object;)V
     344: getstatic     #22                 // Field org/apache/hadoop/hbase/procedure2/StateMachineProcedure$Flow.HAS_MORE_STATE:Lorg/apache/hadoop/hbase/procedure2/StateMachineProcedure$Flow;
     347: areturn
     348: aload_0
     349: getfield      #48                 // Field retryCounter:Lorg/apache/hadoop/hbase/util/RetryCounter;
     352: ifnonnull     366
     355: aload_0
     356: aload_1
     357: invokevirtual #49                 // Method org/apache/hadoop/hbase/master/procedure/MasterProcedureEnv.getMasterConfiguration:()Lorg/apache/hadoop/conf/Configuration;
     360: invokestatic  #50                 // Method org/apache/hadoop/hbase/procedure2/ProcedureUtil.createRetryCounter:(Lorg/apache/hadoop/conf/Configuration;)Lorg/apache/hadoop/hbase/util/RetryCounter;
     363: putfield      #48                 // Field retryCounter:Lorg/apache/hadoop/hbase/util/RetryCounter;
     366: aload_0
     367: getfield      #48                 // Field retryCounter:Lorg/apache/hadoop/hbase/util/RetryCounter;
     370: invokevirtual #51                 // Method org/apache/hadoop/hbase/util/RetryCounter.getBackoffTimeAndIncrementAttempts:()J
     373: lstore_3
     374: getstatic     #15                 // Field LOG:Lorg/slf4j/Logger;
     377: ldc           #52                 // String There are still {} region(s) which need to be reopened for table {} are in OPENING state, suspend {}secs and try again later
     379: iconst_3
     380: anewarray     #53                 // class java/lang/Object
     383: dup
     384: iconst_0
     385: aload_0
     386: getfield      #3                  // Field regions:Ljava/util/List;
     389: invokeinterface #54,  1           // InterfaceMethod java/util/List.size:()I
     394: invokestatic  #55                 // Method java/lang/Integer.valueOf:(I)Ljava/lang/Integer;
     397: aastore
     398: dup
     399: iconst_1
     400: aload_0
     401: getfield      #4                  // Field tableName:Lorg/apache/hadoop/hbase/TableName;
     404: aastore
     405: dup
     406: iconst_2
     407: lload_3
     408: ldc2_w        #56                 // long 1000l
     411: ldiv
     412: invokestatic  #58                 // Method java/lang/Long.valueOf:(J)Ljava/lang/Long;
     415: aastore
     416: invokeinterface #59,  3           // InterfaceMethod org/slf4j/Logger.info:(Ljava/lang/String;[Ljava/lang/Object;)V
     421: aload_0
     422: lload_3
     423: invokestatic  #60                 // Method java/lang/Math.toIntExact:(J)I
     426: invokevirtual #61                 // Method setTimeout:(I)V
     429: aload_0
     430: getstatic     #62                 // Field org/apache/hadoop/hbase/shaded/protobuf/generated/ProcedureProtos$ProcedureState.WAITING_TIMEOUT:Lorg/apache/hadoop/hbase/shaded/protobuf/generated/ProcedureProtos$ProcedureState;
     433: invokevirtual #63                 // Method setState:(Lorg/apache/hadoop/hbase/shaded/protobuf/generated/ProcedureProtos$ProcedureState;)V
     436: aload_0
     437: invokevirtual #64                 // Method skipPersistence:()V
     440: new           #65                 // class org/apache/hadoop/hbase/procedure2/ProcedureSuspendedException
     443: dup
     444: invokespecial #66                 // Method org/apache/hadoop/hbase/procedure2/ProcedureSuspendedException."<init>":()V
     447: athrow
     448: new           #67                 // class java/lang/UnsupportedOperationException
     451: dup
     452: new           #68                 // class java/lang/StringBuilder
     455: dup
     456: invokespecial #69                 // Method java/lang/StringBuilder."<init>":()V
     459: ldc           #70                 // String unhandled state=
     461: invokevirtual #71                 // Method java/lang/StringBuilder.append:(Ljava/lang/String;)Ljava/lang/StringBuilder;
     464: aload_2
     465: invokevirtual #72                 // Method java/lang/StringBuilder.append:(Ljava/lang/Object;)Ljava/lang/StringBuilder;
     468: invokevirtual #73                 // Method java/lang/StringBuilder.toString:()Ljava/lang/String;
     471: invokespecial #74                 // Method java/lang/UnsupportedOperationException."<init>":(Ljava/lang/String;)V
     474: athrow
    Exception table:
       from    to  target type
         157   165   199   any
         173   191   199   any
         199   201   199   any

  protected synchronized boolean setTimeoutFailure(org.apache.hadoop.hbase.master.procedure.MasterProcedureEnv);
    Code:
       0: aload_0
       1: getstatic     #75                 // Field org/apache/hadoop/hbase/shaded/protobuf/generated/ProcedureProtos$ProcedureState.RUNNABLE:Lorg/apache/hadoop/hbase/shaded/protobuf/generated/ProcedureProtos$ProcedureState;
       4: invokevirtual #63                 // Method setState:(Lorg/apache/hadoop/hbase/shaded/protobuf/generated/ProcedureProtos$ProcedureState;)V
       7: aload_1
       8: invokevirtual #76                 // Method org/apache/hadoop/hbase/master/procedure/MasterProcedureEnv.getProcedureScheduler:()Lorg/apache/hadoop/hbase/master/procedure/MasterProcedureScheduler;
      11: aload_0
      12: invokevirtual #77                 // Method org/apache/hadoop/hbase/master/procedure/MasterProcedureScheduler.addFront:(Lorg/apache/hadoop/hbase/procedure2/Procedure;)V
      15: iconst_0
      16: ireturn

  protected void rollbackState(org.apache.hadoop.hbase.master.procedure.MasterProcedureEnv, org.apache.hadoop.hbase.shaded.protobuf.generated.MasterProcedureProtos$ReopenTableRegionsState) throws java.io.IOException, java.lang.InterruptedException;
    Code:
       0: new           #67                 // class java/lang/UnsupportedOperationException
       3: dup
       4: new           #68                 // class java/lang/StringBuilder
       7: dup
       8: invokespecial #69                 // Method java/lang/StringBuilder."<init>":()V
      11: ldc           #70                 // String unhandled state=
      13: invokevirtual #71                 // Method java/lang/StringBuilder.append:(Ljava/lang/String;)Ljava/lang/StringBuilder;
      16: aload_2
      17: invokevirtual #72                 // Method java/lang/StringBuilder.append:(Ljava/lang/Object;)Ljava/lang/StringBuilder;
      20: invokevirtual #73                 // Method java/lang/StringBuilder.toString:()Ljava/lang/String;
      23: invokespecial #74                 // Method java/lang/UnsupportedOperationException."<init>":(Ljava/lang/String;)V
      26: athrow

  protected org.apache.hadoop.hbase.shaded.protobuf.generated.MasterProcedureProtos$ReopenTableRegionsState getState(int);
    Code:
       0: iload_1
       1: invokestatic  #78                 // Method org/apache/hadoop/hbase/shaded/protobuf/generated/MasterProcedureProtos$ReopenTableRegionsState.forNumber:(I)Lorg/apache/hadoop/hbase/shaded/protobuf/generated/MasterProcedureProtos$ReopenTableRegionsState;
       4: areturn

  protected int getStateId(org.apache.hadoop.hbase.shaded.protobuf.generated.MasterProcedureProtos$ReopenTableRegionsState);
    Code:
       0: aload_1
       1: invokevirtual #79                 // Method org/apache/hadoop/hbase/shaded/protobuf/generated/MasterProcedureProtos$ReopenTableRegionsState.getNumber:()I
       4: ireturn

  protected org.apache.hadoop.hbase.shaded.protobuf.generated.MasterProcedureProtos$ReopenTableRegionsState getInitialState();
    Code:
       0: getstatic     #80                 // Field org/apache/hadoop/hbase/shaded/protobuf/generated/MasterProcedureProtos$ReopenTableRegionsState.REOPEN_TABLE_REGIONS_GET_REGIONS:Lorg/apache/hadoop/hbase/shaded/protobuf/generated/MasterProcedureProtos$ReopenTableRegionsState;
       3: areturn

  protected void serializeStateData(org.apache.hadoop.hbase.procedure2.ProcedureStateSerializer) throws java.io.IOException;
    Code:
       0: aload_0
       1: aload_1
       2: invokespecial #81                 // Method org/apache/hadoop/hbase/master/procedure/AbstractStateMachineTableProcedure.serializeStateData:(Lorg/apache/hadoop/hbase/procedure2/ProcedureStateSerializer;)V
       5: invokestatic  #82                 // Method org/apache/hadoop/hbase/shaded/protobuf/generated/MasterProcedureProtos$ReopenTableRegionsStateData.newBuilder:()Lorg/apache/hadoop/hbase/shaded/protobuf/generated/MasterProcedureProtos$ReopenTableRegionsStateData$Builder;
       8: aload_0
       9: getfield      #4                  // Field tableName:Lorg/apache/hadoop/hbase/TableName;
      12: invokestatic  #83                 // Method org/apache/hadoop/hbase/shaded/protobuf/ProtobufUtil.toProtoTableName:(Lorg/apache/hadoop/hbase/TableName;)Lorg/apache/hadoop/hbase/shaded/protobuf/generated/HBaseProtos$TableName;
      15: invokevirtual #84                 // Method org/apache/hadoop/hbase/shaded/protobuf/generated/MasterProcedureProtos$ReopenTableRegionsStateData$Builder.setTableName:(Lorg/apache/hadoop/hbase/shaded/protobuf/generated/HBaseProtos$TableName;)Lorg/apache/hadoop/hbase/shaded/protobuf/generated/MasterProcedureProtos$ReopenTableRegionsStateData$Builder;
      18: astore_2
      19: aload_0
      20: getfield      #3                  // Field regions:Ljava/util/List;
      23: invokeinterface #36,  1           // InterfaceMethod java/util/List.stream:()Ljava/util/stream/Stream;
      28: invokedynamic #85,  0             // InvokeDynamic #3:apply:()Ljava/util/function/Function;
      33: invokeinterface #39,  2           // InterfaceMethod java/util/stream/Stream.map:(Ljava/util/function/Function;)Ljava/util/stream/Stream;
      38: aload_2
      39: dup
      40: invokevirtual #37                 // Method java/lang/Object.getClass:()Ljava/lang/Class;
      43: pop
      44: invokedynamic #86,  0             // InvokeDynamic #4:accept:(Lorg/apache/hadoop/hbase/shaded/protobuf/generated/MasterProcedureProtos$ReopenTableRegionsStateData$Builder;)Ljava/util/function/Consumer;
      49: invokeinterface #87,  2           // InterfaceMethod java/util/stream/Stream.forEachOrdered:(Ljava/util/function/Consumer;)V
      54: aload_1
      55: aload_2
      56: invokevirtual #88                 // Method org/apache/hadoop/hbase/shaded/protobuf/generated/MasterProcedureProtos$ReopenTableRegionsStateData$Builder.build:()Lorg/apache/hadoop/hbase/shaded/protobuf/generated/MasterProcedureProtos$ReopenTableRegionsStateData;
      59: invokeinterface #89,  2           // InterfaceMethod org/apache/hadoop/hbase/procedure2/ProcedureStateSerializer.serialize:(Lorg/apache/hbase/thirdparty/com/google/protobuf/Message;)V
      64: return

  protected void deserializeStateData(org.apache.hadoop.hbase.procedure2.ProcedureStateSerializer) throws java.io.IOException;
    Code:
       0: aload_0
       1: aload_1
       2: invokespecial #90                 // Method org/apache/hadoop/hbase/master/procedure/AbstractStateMachineTableProcedure.deserializeStateData:(Lorg/apache/hadoop/hbase/procedure2/ProcedureStateSerializer;)V
       5: aload_1
       6: ldc           #91                 // class org/apache/hadoop/hbase/shaded/protobuf/generated/MasterProcedureProtos$ReopenTableRegionsStateData
       8: invokeinterface #92,  2           // InterfaceMethod org/apache/hadoop/hbase/procedure2/ProcedureStateSerializer.deserialize:(Ljava/lang/Class;)Lorg/apache/hbase/thirdparty/com/google/protobuf/Message;
      13: checkcast     #91                 // class org/apache/hadoop/hbase/shaded/protobuf/generated/MasterProcedureProtos$ReopenTableRegionsStateData
      16: astore_2
      17: aload_0
      18: aload_2
      19: invokevirtual #93                 // Method org/apache/hadoop/hbase/shaded/protobuf/generated/MasterProcedureProtos$ReopenTableRegionsStateData.getTableName:()Lorg/apache/hadoop/hbase/shaded/protobuf/generated/HBaseProtos$TableName;
      22: invokestatic  #94                 // Method org/apache/hadoop/hbase/shaded/protobuf/ProtobufUtil.toTableName:(Lorg/apache/hadoop/hbase/shaded/protobuf/generated/HBaseProtos$TableName;)Lorg/apache/hadoop/hbase/TableName;
      25: putfield      #4                  // Field tableName:Lorg/apache/hadoop/hbase/TableName;
      28: aload_0
      29: aload_2
      30: invokevirtual #95                 // Method org/apache/hadoop/hbase/shaded/protobuf/generated/MasterProcedureProtos$ReopenTableRegionsStateData.getRegionList:()Ljava/util/List;
      33: invokeinterface #36,  1           // InterfaceMethod java/util/List.stream:()Ljava/util/stream/Stream;
      38: invokedynamic #96,  0             // InvokeDynamic #5:apply:()Ljava/util/function/Function;
      43: invokeinterface #39,  2           // InterfaceMethod java/util/stream/Stream.map:(Ljava/util/function/Function;)Ljava/util/stream/Stream;
      48: invokestatic  #42                 // Method java/util/stream/Collectors.toList:()Ljava/util/stream/Collector;
      51: invokeinterface #43,  2           // InterfaceMethod java/util/stream/Stream.collect:(Ljava/util/stream/Collector;)Ljava/lang/Object;
      56: checkcast     #44                 // class java/util/List
      59: putfield      #3                  // Field regions:Ljava/util/List;
      62: return

  protected java.lang.Object getInitialState();
    Code:
       0: aload_0
       1: invokevirtual #97                 // Method getInitialState:()Lorg/apache/hadoop/hbase/shaded/protobuf/generated/MasterProcedureProtos$ReopenTableRegionsState;
       4: areturn

  protected int getStateId(java.lang.Object);
    Code:
       0: aload_0
       1: aload_1
       2: checkcast     #98                 // class org/apache/hadoop/hbase/shaded/protobuf/generated/MasterProcedureProtos$ReopenTableRegionsState
       5: invokevirtual #99                 // Method getStateId:(Lorg/apache/hadoop/hbase/shaded/protobuf/generated/MasterProcedureProtos$ReopenTableRegionsState;)I
       8: ireturn

  protected java.lang.Object getState(int);
    Code:
       0: aload_0
       1: iload_1
       2: invokevirtual #100                // Method getState:(I)Lorg/apache/hadoop/hbase/shaded/protobuf/generated/MasterProcedureProtos$ReopenTableRegionsState;
       5: areturn

  protected void rollbackState(java.lang.Object, java.lang.Object) throws java.io.IOException, java.lang.InterruptedException;
    Code:
       0: aload_0
       1: aload_1
       2: checkcast     #101                // class org/apache/hadoop/hbase/master/procedure/MasterProcedureEnv
       5: aload_2
       6: checkcast     #98                 // class org/apache/hadoop/hbase/shaded/protobuf/generated/MasterProcedureProtos$ReopenTableRegionsState
       9: invokevirtual #102                // Method rollbackState:(Lorg/apache/hadoop/hbase/master/procedure/MasterProcedureEnv;Lorg/apache/hadoop/hbase/shaded/protobuf/generated/MasterProcedureProtos$ReopenTableRegionsState;)V
      12: return

  protected org.apache.hadoop.hbase.procedure2.StateMachineProcedure$Flow executeFromState(java.lang.Object, java.lang.Object) throws org.apache.hadoop.hbase.procedure2.ProcedureSuspendedException, org.apache.hadoop.hbase.procedure2.ProcedureYieldException, java.lang.InterruptedException;
    Code:
       0: aload_0
       1: aload_1
       2: checkcast     #101                // class org/apache/hadoop/hbase/master/procedure/MasterProcedureEnv
       5: aload_2
       6: checkcast     #98                 // class org/apache/hadoop/hbase/shaded/protobuf/generated/MasterProcedureProtos$ReopenTableRegionsState
       9: invokevirtual #103                // Method executeFromState:(Lorg/apache/hadoop/hbase/master/procedure/MasterProcedureEnv;Lorg/apache/hadoop/hbase/shaded/protobuf/generated/MasterProcedureProtos$ReopenTableRegionsState;)Lorg/apache/hadoop/hbase/procedure2/StateMachineProcedure$Flow;
      12: areturn

  protected boolean setTimeoutFailure(java.lang.Object);
    Code:
       0: aload_0
       1: aload_1
       2: checkcast     #101                // class org/apache/hadoop/hbase/master/procedure/MasterProcedureEnv
       5: invokevirtual #104                // Method setTimeoutFailure:(Lorg/apache/hadoop/hbase/master/procedure/MasterProcedureEnv;)Z
       8: ireturn

  static {};
    Code:
       0: ldc           #106                // class org/apache/hadoop/hbase/master/procedure/ReopenTableRegionsProcedure
       2: invokestatic  #107                // Method org/slf4j/LoggerFactory.getLogger:(Ljava/lang/Class;)Lorg/slf4j/Logger;
       5: putstatic     #15                 // Field LOG:Lorg/slf4j/Logger;
       8: return
}
