Compiled from "ReplicationLoad.java"
public class org.apache.hadoop.hbase.replication.regionserver.ReplicationLoad {
  public static final org.apache.hadoop.hbase.replication.regionserver.ReplicationLoad EMPTY_REPLICATIONLOAD;

  public org.apache.hadoop.hbase.replication.regionserver.ReplicationLoad();
    Code:
       0: aload_0
       1: invokespecial #1                  // Method java/lang/Object."<init>":()V
       4: return

  public void buildReplicationLoad(java.util.List<org.apache.hadoop.hbase.replication.regionserver.ReplicationSourceInterface>, org.apache.hadoop.hbase.replication.regionserver.MetricsSink);
    Code:
       0: aload_0
       1: aload_2
       2: putfield      #2                  // Field sinkMetrics:Lorg/apache/hadoop/hbase/replication/regionserver/MetricsSink;
       5: invokestatic  #3                  // Method org/apache/hadoop/hbase/shaded/protobuf/generated/ClusterStatusProtos$ReplicationLoadSink.newBuilder:()Lorg/apache/hadoop/hbase/shaded/protobuf/generated/ClusterStatusProtos$ReplicationLoadSink$Builder;
       8: astore_3
       9: aload_3
      10: aload_0
      11: getfield      #2                  // Field sinkMetrics:Lorg/apache/hadoop/hbase/replication/regionserver/MetricsSink;
      14: invokevirtual #4                  // Method org/apache/hadoop/hbase/replication/regionserver/MetricsSink.getAgeOfLastAppliedOp:()J
      17: invokevirtual #5                  // Method org/apache/hadoop/hbase/shaded/protobuf/generated/ClusterStatusProtos$ReplicationLoadSink$Builder.setAgeOfLastAppliedOp:(J)Lorg/apache/hadoop/hbase/shaded/protobuf/generated/ClusterStatusProtos$ReplicationLoadSink$Builder;
      20: pop
      21: aload_3
      22: aload_0
      23: getfield      #2                  // Field sinkMetrics:Lorg/apache/hadoop/hbase/replication/regionserver/MetricsSink;
      26: invokevirtual #6                  // Method org/apache/hadoop/hbase/replication/regionserver/MetricsSink.getTimestampOfLastAppliedOp:()J
      29: invokevirtual #7                  // Method org/apache/hadoop/hbase/shaded/protobuf/generated/ClusterStatusProtos$ReplicationLoadSink$Builder.setTimeStampsOfLastAppliedOp:(J)Lorg/apache/hadoop/hbase/shaded/protobuf/generated/ClusterStatusProtos$ReplicationLoadSink$Builder;
      32: pop
      33: aload_0
      34: aload_3
      35: invokevirtual #8                  // Method org/apache/hadoop/hbase/shaded/protobuf/generated/ClusterStatusProtos$ReplicationLoadSink$Builder.build:()Lorg/apache/hadoop/hbase/shaded/protobuf/generated/ClusterStatusProtos$ReplicationLoadSink;
      38: putfield      #9                  // Field replicationLoadSink:Lorg/apache/hadoop/hbase/shaded/protobuf/generated/ClusterStatusProtos$ReplicationLoadSink;
      41: aload_0
      42: new           #10                 // class java/util/ArrayList
      45: dup
      46: invokespecial #11                 // Method java/util/ArrayList."<init>":()V
      49: putfield      #12                 // Field replicationLoadSourceEntries:Ljava/util/List;
      52: aload_1
      53: invokeinterface #13,  1           // InterfaceMethod java/util/List.iterator:()Ljava/util/Iterator;
      58: astore        4
      60: aload         4
      62: invokeinterface #14,  1           // InterfaceMethod java/util/Iterator.hasNext:()Z
      67: ifeq          337
      70: aload         4
      72: invokeinterface #15,  1           // InterfaceMethod java/util/Iterator.next:()Ljava/lang/Object;
      77: checkcast     #16                 // class org/apache/hadoop/hbase/replication/regionserver/ReplicationSourceInterface
      80: astore        5
      82: aload         5
      84: invokeinterface #17,  1           // InterfaceMethod org/apache/hadoop/hbase/replication/regionserver/ReplicationSourceInterface.getSourceMetrics:()Lorg/apache/hadoop/hbase/replication/regionserver/MetricsSource;
      89: astore        6
      91: aload         6
      93: invokevirtual #18                 // Method org/apache/hadoop/hbase/replication/regionserver/MetricsSource.getPeerID:()Ljava/lang/String;
      96: astore        7
      98: aload         7
     100: ldc           #19                 // String -
     102: iconst_2
     103: invokevirtual #20                 // Method java/lang/String.split:(Ljava/lang/String;I)[Ljava/lang/String;
     106: astore        8
     108: aload         8
     110: arraylength
     111: iconst_1
     112: if_icmpeq     122
     115: aload         8
     117: iconst_0
     118: aaload
     119: goto          124
     122: aload         7
     124: astore        7
     126: aload         6
     128: invokevirtual #21                 // Method org/apache/hadoop/hbase/replication/regionserver/MetricsSource.getAgeOfLastShippedOp:()Ljava/lang/Long;
     131: invokevirtual #22                 // Method java/lang/Long.longValue:()J
     134: lstore        9
     136: aload         6
     138: invokevirtual #23                 // Method org/apache/hadoop/hbase/replication/regionserver/MetricsSource.getSizeOfLogQueue:()I
     141: istore        11
     143: aload         6
     145: invokevirtual #24                 // Method org/apache/hadoop/hbase/replication/regionserver/MetricsSource.getReplicableEdits:()J
     148: lstore        12
     150: aload         6
     152: invokevirtual #25                 // Method org/apache/hadoop/hbase/replication/regionserver/MetricsSource.getOpsShipped:()J
     155: lstore        14
     157: aload         6
     159: invokevirtual #26                 // Method org/apache/hadoop/hbase/replication/regionserver/MetricsSource.getTimestampOfLastShippedOp:()J
     162: lstore        16
     164: aload         6
     166: invokevirtual #27                 // Method org/apache/hadoop/hbase/replication/regionserver/MetricsSource.getTimeStampNextToReplicate:()J
     169: lstore        18
     171: aload         6
     173: invokevirtual #28                 // Method org/apache/hadoop/hbase/replication/regionserver/MetricsSource.getReplicationDelay:()J
     176: lstore        20
     178: invokestatic  #29                 // Method org/apache/hadoop/hbase/shaded/protobuf/generated/ClusterStatusProtos$ReplicationLoadSource.newBuilder:()Lorg/apache/hadoop/hbase/shaded/protobuf/generated/ClusterStatusProtos$ReplicationLoadSource$Builder;
     181: astore        22
     183: aload         22
     185: aload         7
     187: invokevirtual #30                 // Method org/apache/hadoop/hbase/shaded/protobuf/generated/ClusterStatusProtos$ReplicationLoadSource$Builder.setPeerID:(Ljava/lang/String;)Lorg/apache/hadoop/hbase/shaded/protobuf/generated/ClusterStatusProtos$ReplicationLoadSource$Builder;
     190: pop
     191: aload         22
     193: lload         9
     195: invokevirtual #31                 // Method org/apache/hadoop/hbase/shaded/protobuf/generated/ClusterStatusProtos$ReplicationLoadSource$Builder.setAgeOfLastShippedOp:(J)Lorg/apache/hadoop/hbase/shaded/protobuf/generated/ClusterStatusProtos$ReplicationLoadSource$Builder;
     198: pop
     199: aload         22
     201: iload         11
     203: invokevirtual #32                 // Method org/apache/hadoop/hbase/shaded/protobuf/generated/ClusterStatusProtos$ReplicationLoadSource$Builder.setSizeOfLogQueue:(I)Lorg/apache/hadoop/hbase/shaded/protobuf/generated/ClusterStatusProtos$ReplicationLoadSource$Builder;
     206: pop
     207: aload         22
     209: lload         16
     211: invokevirtual #33                 // Method org/apache/hadoop/hbase/shaded/protobuf/generated/ClusterStatusProtos$ReplicationLoadSource$Builder.setTimeStampOfLastShippedOp:(J)Lorg/apache/hadoop/hbase/shaded/protobuf/generated/ClusterStatusProtos$ReplicationLoadSource$Builder;
     214: pop
     215: aload         22
     217: lload         20
     219: invokevirtual #34                 // Method org/apache/hadoop/hbase/shaded/protobuf/generated/ClusterStatusProtos$ReplicationLoadSource$Builder.setReplicationLag:(J)Lorg/apache/hadoop/hbase/shaded/protobuf/generated/ClusterStatusProtos$ReplicationLoadSource$Builder;
     222: pop
     223: aload         22
     225: lload         18
     227: invokevirtual #35                 // Method org/apache/hadoop/hbase/shaded/protobuf/generated/ClusterStatusProtos$ReplicationLoadSource$Builder.setTimeStampOfNextToReplicate:(J)Lorg/apache/hadoop/hbase/shaded/protobuf/generated/ClusterStatusProtos$ReplicationLoadSource$Builder;
     230: pop
     231: aload         22
     233: lload         12
     235: invokevirtual #36                 // Method org/apache/hadoop/hbase/shaded/protobuf/generated/ClusterStatusProtos$ReplicationLoadSource$Builder.setEditsRead:(J)Lorg/apache/hadoop/hbase/shaded/protobuf/generated/ClusterStatusProtos$ReplicationLoadSource$Builder;
     238: pop
     239: aload         22
     241: lload         14
     243: invokevirtual #37                 // Method org/apache/hadoop/hbase/shaded/protobuf/generated/ClusterStatusProtos$ReplicationLoadSource$Builder.setOPsShipped:(J)Lorg/apache/hadoop/hbase/shaded/protobuf/generated/ClusterStatusProtos$ReplicationLoadSource$Builder;
     246: pop
     247: aload         5
     249: instanceof    #38                 // class org/apache/hadoop/hbase/replication/regionserver/ReplicationSource
     252: ifeq          319
     255: aload         5
     257: checkcast     #38                 // class org/apache/hadoop/hbase/replication/regionserver/ReplicationSource
     260: astore        23
     262: aload         22
     264: aload         23
     266: invokevirtual #39                 // Method org/apache/hadoop/hbase/replication/regionserver/ReplicationSource.getReplicationQueueInfo:()Lorg/apache/hadoop/hbase/replication/ReplicationQueueInfo;
     269: invokevirtual #40                 // Method org/apache/hadoop/hbase/replication/ReplicationQueueInfo.isQueueRecovered:()Z
     272: invokevirtual #41                 // Method org/apache/hadoop/hbase/shaded/protobuf/generated/ClusterStatusProtos$ReplicationLoadSource$Builder.setRecovered:(Z)Lorg/apache/hadoop/hbase/shaded/protobuf/generated/ClusterStatusProtos$ReplicationLoadSource$Builder;
     275: pop
     276: aload         22
     278: aload         23
     280: invokevirtual #39                 // Method org/apache/hadoop/hbase/replication/regionserver/ReplicationSource.getReplicationQueueInfo:()Lorg/apache/hadoop/hbase/replication/ReplicationQueueInfo;
     283: invokevirtual #42                 // Method org/apache/hadoop/hbase/replication/ReplicationQueueInfo.getQueueId:()Ljava/lang/String;
     286: invokevirtual #43                 // Method org/apache/hadoop/hbase/shaded/protobuf/generated/ClusterStatusProtos$ReplicationLoadSource$Builder.setQueueId:(Ljava/lang/String;)Lorg/apache/hadoop/hbase/shaded/protobuf/generated/ClusterStatusProtos$ReplicationLoadSource$Builder;
     289: pop
     290: aload         22
     292: aload         23
     294: invokevirtual #44                 // Method org/apache/hadoop/hbase/replication/regionserver/ReplicationSource.isWorkerRunning:()Z
     297: invokevirtual #45                 // Method org/apache/hadoop/hbase/shaded/protobuf/generated/ClusterStatusProtos$ReplicationLoadSource$Builder.setRunning:(Z)Lorg/apache/hadoop/hbase/shaded/protobuf/generated/ClusterStatusProtos$ReplicationLoadSource$Builder;
     300: pop
     301: aload         22
     303: lload         18
     305: lconst_0
     306: lcmp
     307: ifle          314
     310: iconst_1
     311: goto          315
     314: iconst_0
     315: invokevirtual #46                 // Method org/apache/hadoop/hbase/shaded/protobuf/generated/ClusterStatusProtos$ReplicationLoadSource$Builder.setEditsSinceRestart:(Z)Lorg/apache/hadoop/hbase/shaded/protobuf/generated/ClusterStatusProtos$ReplicationLoadSource$Builder;
     318: pop
     319: aload_0
     320: getfield      #12                 // Field replicationLoadSourceEntries:Ljava/util/List;
     323: aload         22
     325: invokevirtual #47                 // Method org/apache/hadoop/hbase/shaded/protobuf/generated/ClusterStatusProtos$ReplicationLoadSource$Builder.build:()Lorg/apache/hadoop/hbase/shaded/protobuf/generated/ClusterStatusProtos$ReplicationLoadSource;
     328: invokeinterface #48,  2           // InterfaceMethod java/util/List.add:(Ljava/lang/Object;)Z
     333: pop
     334: goto          60
     337: return

  public java.lang.String sourceToString();
    Code:
       0: new           #49                 // class java/lang/StringBuilder
       3: dup
       4: invokespecial #50                 // Method java/lang/StringBuilder."<init>":()V
       7: astore_1
       8: aload_0
       9: getfield      #12                 // Field replicationLoadSourceEntries:Ljava/util/List;
      12: invokeinterface #13,  1           // InterfaceMethod java/util/List.iterator:()Ljava/util/Iterator;
      17: astore_2
      18: aload_2
      19: invokeinterface #14,  1           // InterfaceMethod java/util/Iterator.hasNext:()Z
      24: ifeq          114
      27: aload_2
      28: invokeinterface #15,  1           // InterfaceMethod java/util/Iterator.next:()Ljava/lang/Object;
      33: checkcast     #51                 // class org/apache/hadoop/hbase/shaded/protobuf/generated/ClusterStatusProtos$ReplicationLoadSource
      36: astore_3
      37: aload_1
      38: ldc           #52                 // String \n           PeerID
      40: aload_3
      41: invokevirtual #53                 // Method org/apache/hadoop/hbase/shaded/protobuf/generated/ClusterStatusProtos$ReplicationLoadSource.getPeerID:()Ljava/lang/String;
      44: invokestatic  #54                 // Method org/apache/hadoop/hbase/util/Strings.appendKeyValue:(Ljava/lang/StringBuilder;Ljava/lang/String;Ljava/lang/Object;)Ljava/lang/StringBuilder;
      47: astore_1
      48: aload_1
      49: ldc           #55                 // String AgeOfLastShippedOp
      51: aload_3
      52: invokevirtual #56                 // Method org/apache/hadoop/hbase/shaded/protobuf/generated/ClusterStatusProtos$ReplicationLoadSource.getAgeOfLastShippedOp:()J
      55: invokestatic  #57                 // Method java/lang/Long.valueOf:(J)Ljava/lang/Long;
      58: invokestatic  #54                 // Method org/apache/hadoop/hbase/util/Strings.appendKeyValue:(Ljava/lang/StringBuilder;Ljava/lang/String;Ljava/lang/Object;)Ljava/lang/StringBuilder;
      61: astore_1
      62: aload_1
      63: ldc           #58                 // String SizeOfLogQueue
      65: aload_3
      66: invokevirtual #59                 // Method org/apache/hadoop/hbase/shaded/protobuf/generated/ClusterStatusProtos$ReplicationLoadSource.getSizeOfLogQueue:()I
      69: invokestatic  #60                 // Method java/lang/Integer.valueOf:(I)Ljava/lang/Integer;
      72: invokestatic  #54                 // Method org/apache/hadoop/hbase/util/Strings.appendKeyValue:(Ljava/lang/StringBuilder;Ljava/lang/String;Ljava/lang/Object;)Ljava/lang/StringBuilder;
      75: astore_1
      76: aload_1
      77: ldc           #61                 // String TimestampsOfLastShippedOp
      79: new           #62                 // class java/util/Date
      82: dup
      83: aload_3
      84: invokevirtual #63                 // Method org/apache/hadoop/hbase/shaded/protobuf/generated/ClusterStatusProtos$ReplicationLoadSource.getTimeStampOfLastShippedOp:()J
      87: invokespecial #64                 // Method java/util/Date."<init>":(J)V
      90: invokevirtual #65                 // Method java/util/Date.toString:()Ljava/lang/String;
      93: invokestatic  #54                 // Method org/apache/hadoop/hbase/util/Strings.appendKeyValue:(Ljava/lang/StringBuilder;Ljava/lang/String;Ljava/lang/Object;)Ljava/lang/StringBuilder;
      96: astore_1
      97: aload_1
      98: ldc           #66                 // String Replication Lag
     100: aload_3
     101: invokevirtual #67                 // Method org/apache/hadoop/hbase/shaded/protobuf/generated/ClusterStatusProtos$ReplicationLoadSource.getReplicationLag:()J
     104: invokestatic  #57                 // Method java/lang/Long.valueOf:(J)Ljava/lang/Long;
     107: invokestatic  #54                 // Method org/apache/hadoop/hbase/util/Strings.appendKeyValue:(Ljava/lang/StringBuilder;Ljava/lang/String;Ljava/lang/Object;)Ljava/lang/StringBuilder;
     110: astore_1
     111: goto          18
     114: aload_1
     115: invokevirtual #68                 // Method java/lang/StringBuilder.toString:()Ljava/lang/String;
     118: areturn

  public java.lang.String sinkToString();
    Code:
       0: aload_0
       1: getfield      #9                  // Field replicationLoadSink:Lorg/apache/hadoop/hbase/shaded/protobuf/generated/ClusterStatusProtos$ReplicationLoadSink;
       4: ifnonnull     9
       7: aconst_null
       8: areturn
       9: new           #49                 // class java/lang/StringBuilder
      12: dup
      13: invokespecial #50                 // Method java/lang/StringBuilder."<init>":()V
      16: astore_1
      17: aload_1
      18: ldc           #69                 // String AgeOfLastAppliedOp
      20: aload_0
      21: getfield      #9                  // Field replicationLoadSink:Lorg/apache/hadoop/hbase/shaded/protobuf/generated/ClusterStatusProtos$ReplicationLoadSink;
      24: invokevirtual #70                 // Method org/apache/hadoop/hbase/shaded/protobuf/generated/ClusterStatusProtos$ReplicationLoadSink.getAgeOfLastAppliedOp:()J
      27: invokestatic  #57                 // Method java/lang/Long.valueOf:(J)Ljava/lang/Long;
      30: invokestatic  #54                 // Method org/apache/hadoop/hbase/util/Strings.appendKeyValue:(Ljava/lang/StringBuilder;Ljava/lang/String;Ljava/lang/Object;)Ljava/lang/StringBuilder;
      33: astore_1
      34: aload_1
      35: ldc           #71                 // String TimestampsOfLastAppliedOp
      37: new           #62                 // class java/util/Date
      40: dup
      41: aload_0
      42: getfield      #9                  // Field replicationLoadSink:Lorg/apache/hadoop/hbase/shaded/protobuf/generated/ClusterStatusProtos$ReplicationLoadSink;
      45: invokevirtual #72                 // Method org/apache/hadoop/hbase/shaded/protobuf/generated/ClusterStatusProtos$ReplicationLoadSink.getTimeStampsOfLastAppliedOp:()J
      48: invokespecial #64                 // Method java/util/Date."<init>":(J)V
      51: invokevirtual #65                 // Method java/util/Date.toString:()Ljava/lang/String;
      54: invokestatic  #54                 // Method org/apache/hadoop/hbase/util/Strings.appendKeyValue:(Ljava/lang/StringBuilder;Ljava/lang/String;Ljava/lang/Object;)Ljava/lang/StringBuilder;
      57: astore_1
      58: aload_1
      59: invokevirtual #68                 // Method java/lang/StringBuilder.toString:()Ljava/lang/String;
      62: areturn

  public org.apache.hadoop.hbase.shaded.protobuf.generated.ClusterStatusProtos$ReplicationLoadSink getReplicationLoadSink();
    Code:
       0: aload_0
       1: getfield      #9                  // Field replicationLoadSink:Lorg/apache/hadoop/hbase/shaded/protobuf/generated/ClusterStatusProtos$ReplicationLoadSink;
       4: areturn

  public java.util.List<org.apache.hadoop.hbase.shaded.protobuf.generated.ClusterStatusProtos$ReplicationLoadSource> getReplicationLoadSourceEntries();
    Code:
       0: aload_0
       1: getfield      #12                 // Field replicationLoadSourceEntries:Ljava/util/List;
       4: areturn

  public java.lang.String toString();
    Code:
       0: new           #49                 // class java/lang/StringBuilder
       3: dup
       4: invokespecial #50                 // Method java/lang/StringBuilder."<init>":()V
       7: aload_0
       8: invokevirtual #73                 // Method sourceToString:()Ljava/lang/String;
      11: invokevirtual #74                 // Method java/lang/StringBuilder.append:(Ljava/lang/String;)Ljava/lang/StringBuilder;
      14: ldc           #75                 // String line.separator
      16: invokestatic  #76                 // Method java/lang/System.getProperty:(Ljava/lang/String;)Ljava/lang/String;
      19: invokevirtual #74                 // Method java/lang/StringBuilder.append:(Ljava/lang/String;)Ljava/lang/StringBuilder;
      22: aload_0
      23: invokevirtual #77                 // Method sinkToString:()Ljava/lang/String;
      26: invokevirtual #74                 // Method java/lang/StringBuilder.append:(Ljava/lang/String;)Ljava/lang/StringBuilder;
      29: invokevirtual #68                 // Method java/lang/StringBuilder.toString:()Ljava/lang/String;
      32: areturn

  static {};
    Code:
       0: new           #78                 // class org/apache/hadoop/hbase/replication/regionserver/ReplicationLoad
       3: dup
       4: invokespecial #79                 // Method "<init>":()V
       7: putstatic     #80                 // Field EMPTY_REPLICATIONLOAD:Lorg/apache/hadoop/hbase/replication/regionserver/ReplicationLoad;
      10: return
}
