Compiled from "ReplicationPeerConfigUtil.java"
public final class org.apache.hadoop.hbase.client.replication.ReplicationPeerConfigUtil {
  public static java.lang.String convertToString(java.util.Set<java.lang.String>);
    Code:
       0: aload_0
       1: ifnonnull     6
       4: aconst_null
       5: areturn
       6: aload_0
       7: bipush        59
       9: invokestatic  #2                  // Method org/apache/commons/lang3/StringUtils.join:(Ljava/lang/Iterable;C)Ljava/lang/String;
      12: areturn

  public static org.apache.hadoop.hbase.shaded.protobuf.generated.ReplicationProtos$TableCF[] convert(java.util.Map<org.apache.hadoop.hbase.TableName, ? extends java.util.Collection<java.lang.String>>);
    Code:
       0: aload_0
       1: ifnonnull     6
       4: aconst_null
       5: areturn
       6: new           #3                  // class java/util/ArrayList
       9: dup
      10: aload_0
      11: invokeinterface #4,  1            // InterfaceMethod java/util/Map.entrySet:()Ljava/util/Set;
      16: invokeinterface #5,  1            // InterfaceMethod java/util/Set.size:()I
      21: invokespecial #6                  // Method java/util/ArrayList."<init>":(I)V
      24: astore_1
      25: invokestatic  #7                  // Method org/apache/hadoop/hbase/shaded/protobuf/generated/ReplicationProtos$TableCF.newBuilder:()Lorg/apache/hadoop/hbase/shaded/protobuf/generated/ReplicationProtos$TableCF$Builder;
      28: astore_2
      29: aload_0
      30: invokeinterface #4,  1            // InterfaceMethod java/util/Map.entrySet:()Ljava/util/Set;
      35: invokeinterface #8,  1            // InterfaceMethod java/util/Set.iterator:()Ljava/util/Iterator;
      40: astore_3
      41: aload_3
      42: invokeinterface #9,  1            // InterfaceMethod java/util/Iterator.hasNext:()Z
      47: ifeq          177
      50: aload_3
      51: invokeinterface #10,  1           // InterfaceMethod java/util/Iterator.next:()Ljava/lang/Object;
      56: checkcast     #11                 // class java/util/Map$Entry
      59: astore        4
      61: aload_2
      62: invokevirtual #12                 // Method org/apache/hadoop/hbase/shaded/protobuf/generated/ReplicationProtos$TableCF$Builder.clear:()Lorg/apache/hadoop/hbase/shaded/protobuf/generated/ReplicationProtos$TableCF$Builder;
      65: pop
      66: aload_2
      67: aload         4
      69: invokeinterface #13,  1           // InterfaceMethod java/util/Map$Entry.getKey:()Ljava/lang/Object;
      74: checkcast     #14                 // class org/apache/hadoop/hbase/TableName
      77: invokestatic  #15                 // Method org/apache/hadoop/hbase/shaded/protobuf/ProtobufUtil.toProtoTableName:(Lorg/apache/hadoop/hbase/TableName;)Lorg/apache/hadoop/hbase/shaded/protobuf/generated/HBaseProtos$TableName;
      80: invokevirtual #16                 // Method org/apache/hadoop/hbase/shaded/protobuf/generated/ReplicationProtos$TableCF$Builder.setTableName:(Lorg/apache/hadoop/hbase/shaded/protobuf/generated/HBaseProtos$TableName;)Lorg/apache/hadoop/hbase/shaded/protobuf/generated/ReplicationProtos$TableCF$Builder;
      83: pop
      84: aload         4
      86: invokeinterface #17,  1           // InterfaceMethod java/util/Map$Entry.getValue:()Ljava/lang/Object;
      91: checkcast     #18                 // class java/util/Collection
      94: astore        5
      96: aload         5
      98: ifnull        163
     101: aload         5
     103: invokeinterface #19,  1           // InterfaceMethod java/util/Collection.isEmpty:()Z
     108: ifne          163
     111: aload         4
     113: invokeinterface #17,  1           // InterfaceMethod java/util/Map$Entry.getValue:()Ljava/lang/Object;
     118: checkcast     #18                 // class java/util/Collection
     121: invokeinterface #20,  1           // InterfaceMethod java/util/Collection.iterator:()Ljava/util/Iterator;
     126: astore        6
     128: aload         6
     130: invokeinterface #9,  1            // InterfaceMethod java/util/Iterator.hasNext:()Z
     135: ifeq          163
     138: aload         6
     140: invokeinterface #10,  1           // InterfaceMethod java/util/Iterator.next:()Ljava/lang/Object;
     145: checkcast     #21                 // class java/lang/String
     148: astore        7
     150: aload_2
     151: aload         7
     153: invokestatic  #22                 // Method org/apache/hbase/thirdparty/com/google/protobuf/ByteString.copyFromUtf8:(Ljava/lang/String;)Lorg/apache/hbase/thirdparty/com/google/protobuf/ByteString;
     156: invokevirtual #23                 // Method org/apache/hadoop/hbase/shaded/protobuf/generated/ReplicationProtos$TableCF$Builder.addFamilies:(Lorg/apache/hbase/thirdparty/com/google/protobuf/ByteString;)Lorg/apache/hadoop/hbase/shaded/protobuf/generated/ReplicationProtos$TableCF$Builder;
     159: pop
     160: goto          128
     163: aload_1
     164: aload_2
     165: invokevirtual #24                 // Method org/apache/hadoop/hbase/shaded/protobuf/generated/ReplicationProtos$TableCF$Builder.build:()Lorg/apache/hadoop/hbase/shaded/protobuf/generated/ReplicationProtos$TableCF;
     168: invokeinterface #25,  2           // InterfaceMethod java/util/List.add:(Ljava/lang/Object;)Z
     173: pop
     174: goto          41
     177: aload_1
     178: aload_1
     179: invokeinterface #26,  1           // InterfaceMethod java/util/List.size:()I
     184: anewarray     #27                 // class org/apache/hadoop/hbase/shaded/protobuf/generated/ReplicationProtos$TableCF
     187: invokeinterface #28,  2           // InterfaceMethod java/util/List.toArray:([Ljava/lang/Object;)[Ljava/lang/Object;
     192: checkcast     #29                 // class "[Lorg/apache/hadoop/hbase/shaded/protobuf/generated/ReplicationProtos$TableCF;"
     195: areturn

  public static java.lang.String convertToString(java.util.Map<org.apache.hadoop.hbase.TableName, ? extends java.util.Collection<java.lang.String>>);
    Code:
       0: aload_0
       1: ifnonnull     6
       4: aconst_null
       5: areturn
       6: aload_0
       7: invokestatic  #30                 // Method convert:(Ljava/util/Map;)[Lorg/apache/hadoop/hbase/shaded/protobuf/generated/ReplicationProtos$TableCF;
      10: invokestatic  #31                 // Method convert:([Lorg/apache/hadoop/hbase/shaded/protobuf/generated/ReplicationProtos$TableCF;)Ljava/lang/String;
      13: areturn

  public static org.apache.hadoop.hbase.shaded.protobuf.generated.ReplicationProtos$TableCF[] convert(java.lang.String);
    Code:
       0: aload_0
       1: ifnull        14
       4: aload_0
       5: invokevirtual #32                 // Method java/lang/String.trim:()Ljava/lang/String;
       8: invokevirtual #33                 // Method java/lang/String.length:()I
      11: ifne          16
      14: aconst_null
      15: areturn
      16: invokestatic  #7                  // Method org/apache/hadoop/hbase/shaded/protobuf/generated/ReplicationProtos$TableCF.newBuilder:()Lorg/apache/hadoop/hbase/shaded/protobuf/generated/ReplicationProtos$TableCF$Builder;
      19: astore_1
      20: aload_0
      21: ldc           #34                 // String ;
      23: invokevirtual #35                 // Method java/lang/String.split:(Ljava/lang/String;)[Ljava/lang/String;
      26: astore_2
      27: new           #3                  // class java/util/ArrayList
      30: dup
      31: aload_2
      32: arraylength
      33: invokespecial #6                  // Method java/util/ArrayList."<init>":(I)V
      36: astore_3
      37: aload_2
      38: astore        4
      40: aload         4
      42: arraylength
      43: istore        5
      45: iconst_0
      46: istore        6
      48: iload         6
      50: iload         5
      52: if_icmpge     296
      55: aload         4
      57: iload         6
      59: aaload
      60: astore        7
      62: aload         7
      64: invokevirtual #32                 // Method java/lang/String.trim:()Ljava/lang/String;
      67: astore        7
      69: aload         7
      71: invokevirtual #33                 // Method java/lang/String.length:()I
      74: ifne          80
      77: goto          290
      80: aload         7
      82: ldc           #36                 // String :
      84: invokevirtual #35                 // Method java/lang/String.split:(Ljava/lang/String;)[Ljava/lang/String;
      87: astore        8
      89: aload         8
      91: iconst_0
      92: aaload
      93: invokevirtual #32                 // Method java/lang/String.trim:()Ljava/lang/String;
      96: astore        9
      98: aload         8
     100: arraylength
     101: iconst_2
     102: if_icmpgt     113
     105: aload         9
     107: invokevirtual #33                 // Method java/lang/String.length:()I
     110: ifne          143
     113: getstatic     #37                 // Field LOG:Lorg/slf4j/Logger;
     116: new           #38                 // class java/lang/StringBuilder
     119: dup
     120: invokespecial #39                 // Method java/lang/StringBuilder."<init>":()V
     123: ldc           #40                 // String incorrect format:
     125: invokevirtual #41                 // Method java/lang/StringBuilder.append:(Ljava/lang/String;)Ljava/lang/StringBuilder;
     128: aload_0
     129: invokevirtual #41                 // Method java/lang/StringBuilder.append:(Ljava/lang/String;)Ljava/lang/StringBuilder;
     132: invokevirtual #42                 // Method java/lang/StringBuilder.toString:()Ljava/lang/String;
     135: invokeinterface #43,  2           // InterfaceMethod org/slf4j/Logger.info:(Ljava/lang/String;)V
     140: goto          290
     143: aload_1
     144: invokevirtual #12                 // Method org/apache/hadoop/hbase/shaded/protobuf/generated/ReplicationProtos$TableCF$Builder.clear:()Lorg/apache/hadoop/hbase/shaded/protobuf/generated/ReplicationProtos$TableCF$Builder;
     147: pop
     148: ldc           #44                 // String default
     150: astore        10
     152: aload         9
     154: astore        11
     156: aload         9
     158: ldc           #45                 // String \.
     160: invokevirtual #35                 // Method java/lang/String.split:(Ljava/lang/String;)[Ljava/lang/String;
     163: astore        12
     165: aload         12
     167: ifnull        189
     170: aload         12
     172: arraylength
     173: iconst_2
     174: if_icmpne     189
     177: aload         12
     179: iconst_0
     180: aaload
     181: astore        10
     183: aload         12
     185: iconst_1
     186: aaload
     187: astore        11
     189: aload_1
     190: aload         10
     192: aload         11
     194: invokestatic  #46                 // Method org/apache/hadoop/hbase/TableName.valueOf:(Ljava/lang/String;Ljava/lang/String;)Lorg/apache/hadoop/hbase/TableName;
     197: invokestatic  #15                 // Method org/apache/hadoop/hbase/shaded/protobuf/ProtobufUtil.toProtoTableName:(Lorg/apache/hadoop/hbase/TableName;)Lorg/apache/hadoop/hbase/shaded/protobuf/generated/HBaseProtos$TableName;
     200: invokevirtual #16                 // Method org/apache/hadoop/hbase/shaded/protobuf/generated/ReplicationProtos$TableCF$Builder.setTableName:(Lorg/apache/hadoop/hbase/shaded/protobuf/generated/HBaseProtos$TableName;)Lorg/apache/hadoop/hbase/shaded/protobuf/generated/ReplicationProtos$TableCF$Builder;
     203: pop
     204: aload         8
     206: arraylength
     207: iconst_2
     208: if_icmpne     279
     211: aload         8
     213: iconst_1
     214: aaload
     215: ldc           #47                 // String ,
     217: invokevirtual #35                 // Method java/lang/String.split:(Ljava/lang/String;)[Ljava/lang/String;
     220: astore        13
     222: aload         13
     224: astore        14
     226: aload         14
     228: arraylength
     229: istore        15
     231: iconst_0
     232: istore        16
     234: iload         16
     236: iload         15
     238: if_icmpge     279
     241: aload         14
     243: iload         16
     245: aaload
     246: astore        17
     248: aload         17
     250: invokevirtual #32                 // Method java/lang/String.trim:()Ljava/lang/String;
     253: astore        18
     255: aload         18
     257: invokevirtual #33                 // Method java/lang/String.length:()I
     260: ifle          273
     263: aload_1
     264: aload         18
     266: invokestatic  #22                 // Method org/apache/hbase/thirdparty/com/google/protobuf/ByteString.copyFromUtf8:(Ljava/lang/String;)Lorg/apache/hbase/thirdparty/com/google/protobuf/ByteString;
     269: invokevirtual #23                 // Method org/apache/hadoop/hbase/shaded/protobuf/generated/ReplicationProtos$TableCF$Builder.addFamilies:(Lorg/apache/hbase/thirdparty/com/google/protobuf/ByteString;)Lorg/apache/hadoop/hbase/shaded/protobuf/generated/ReplicationProtos$TableCF$Builder;
     272: pop
     273: iinc          16, 1
     276: goto          234
     279: aload_3
     280: aload_1
     281: invokevirtual #24                 // Method org/apache/hadoop/hbase/shaded/protobuf/generated/ReplicationProtos$TableCF$Builder.build:()Lorg/apache/hadoop/hbase/shaded/protobuf/generated/ReplicationProtos$TableCF;
     284: invokeinterface #25,  2           // InterfaceMethod java/util/List.add:(Ljava/lang/Object;)Z
     289: pop
     290: iinc          6, 1
     293: goto          48
     296: aload_3
     297: aload_3
     298: invokeinterface #26,  1           // InterfaceMethod java/util/List.size:()I
     303: anewarray     #27                 // class org/apache/hadoop/hbase/shaded/protobuf/generated/ReplicationProtos$TableCF
     306: invokeinterface #28,  2           // InterfaceMethod java/util/List.toArray:([Ljava/lang/Object;)[Ljava/lang/Object;
     311: checkcast     #29                 // class "[Lorg/apache/hadoop/hbase/shaded/protobuf/generated/ReplicationProtos$TableCF;"
     314: areturn

  public static java.lang.String convert(org.apache.hadoop.hbase.shaded.protobuf.generated.ReplicationProtos$TableCF[]);
    Code:
       0: new           #38                 // class java/lang/StringBuilder
       3: dup
       4: invokespecial #39                 // Method java/lang/StringBuilder."<init>":()V
       7: astore_1
       8: iconst_0
       9: istore_2
      10: aload_0
      11: arraylength
      12: istore_3
      13: iload_2
      14: iload_3
      15: if_icmpge     157
      18: aload_0
      19: iload_2
      20: aaload
      21: astore        4
      23: aload         4
      25: invokevirtual #48                 // Method org/apache/hadoop/hbase/shaded/protobuf/generated/ReplicationProtos$TableCF.getTableName:()Lorg/apache/hadoop/hbase/shaded/protobuf/generated/HBaseProtos$TableName;
      28: invokevirtual #49                 // Method org/apache/hadoop/hbase/shaded/protobuf/generated/HBaseProtos$TableName.getNamespace:()Lorg/apache/hbase/thirdparty/com/google/protobuf/ByteString;
      31: invokevirtual #50                 // Method org/apache/hbase/thirdparty/com/google/protobuf/ByteString.toStringUtf8:()Ljava/lang/String;
      34: astore        5
      36: aload         5
      38: invokestatic  #51                 // Method org/apache/commons/lang3/StringUtils.isNotEmpty:(Ljava/lang/CharSequence;)Z
      41: ifeq          78
      44: aload_1
      45: aload         5
      47: invokevirtual #41                 // Method java/lang/StringBuilder.append:(Ljava/lang/String;)Ljava/lang/StringBuilder;
      50: ldc           #52                 // String .
      52: invokevirtual #41                 // Method java/lang/StringBuilder.append:(Ljava/lang/String;)Ljava/lang/StringBuilder;
      55: aload         4
      57: invokevirtual #48                 // Method org/apache/hadoop/hbase/shaded/protobuf/generated/ReplicationProtos$TableCF.getTableName:()Lorg/apache/hadoop/hbase/shaded/protobuf/generated/HBaseProtos$TableName;
      60: invokevirtual #53                 // Method org/apache/hadoop/hbase/shaded/protobuf/generated/HBaseProtos$TableName.getQualifier:()Lorg/apache/hbase/thirdparty/com/google/protobuf/ByteString;
      63: invokevirtual #50                 // Method org/apache/hbase/thirdparty/com/google/protobuf/ByteString.toStringUtf8:()Ljava/lang/String;
      66: invokevirtual #41                 // Method java/lang/StringBuilder.append:(Ljava/lang/String;)Ljava/lang/StringBuilder;
      69: ldc           #36                 // String :
      71: invokevirtual #41                 // Method java/lang/StringBuilder.append:(Ljava/lang/String;)Ljava/lang/StringBuilder;
      74: pop
      75: goto          96
      78: aload_1
      79: aload         4
      81: invokevirtual #48                 // Method org/apache/hadoop/hbase/shaded/protobuf/generated/ReplicationProtos$TableCF.getTableName:()Lorg/apache/hadoop/hbase/shaded/protobuf/generated/HBaseProtos$TableName;
      84: invokevirtual #54                 // Method org/apache/hadoop/hbase/shaded/protobuf/generated/HBaseProtos$TableName.toString:()Ljava/lang/String;
      87: invokevirtual #41                 // Method java/lang/StringBuilder.append:(Ljava/lang/String;)Ljava/lang/StringBuilder;
      90: ldc           #36                 // String :
      92: invokevirtual #41                 // Method java/lang/StringBuilder.append:(Ljava/lang/String;)Ljava/lang/StringBuilder;
      95: pop
      96: iconst_0
      97: istore        6
      99: iload         6
     101: aload         4
     103: invokevirtual #55                 // Method org/apache/hadoop/hbase/shaded/protobuf/generated/ReplicationProtos$TableCF.getFamiliesCount:()I
     106: if_icmpge     135
     109: aload_1
     110: aload         4
     112: iload         6
     114: invokevirtual #56                 // Method org/apache/hadoop/hbase/shaded/protobuf/generated/ReplicationProtos$TableCF.getFamilies:(I)Lorg/apache/hbase/thirdparty/com/google/protobuf/ByteString;
     117: invokevirtual #50                 // Method org/apache/hbase/thirdparty/com/google/protobuf/ByteString.toStringUtf8:()Ljava/lang/String;
     120: invokevirtual #41                 // Method java/lang/StringBuilder.append:(Ljava/lang/String;)Ljava/lang/StringBuilder;
     123: ldc           #47                 // String ,
     125: invokevirtual #41                 // Method java/lang/StringBuilder.append:(Ljava/lang/String;)Ljava/lang/StringBuilder;
     128: pop
     129: iinc          6, 1
     132: goto          99
     135: aload_1
     136: aload_1
     137: invokevirtual #57                 // Method java/lang/StringBuilder.length:()I
     140: iconst_1
     141: isub
     142: invokevirtual #58                 // Method java/lang/StringBuilder.deleteCharAt:(I)Ljava/lang/StringBuilder;
     145: ldc           #34                 // String ;
     147: invokevirtual #41                 // Method java/lang/StringBuilder.append:(Ljava/lang/String;)Ljava/lang/StringBuilder;
     150: pop
     151: iinc          2, 1
     154: goto          13
     157: aload_1
     158: invokevirtual #57                 // Method java/lang/StringBuilder.length:()I
     161: ifle          175
     164: aload_1
     165: aload_1
     166: invokevirtual #57                 // Method java/lang/StringBuilder.length:()I
     169: iconst_1
     170: isub
     171: invokevirtual #58                 // Method java/lang/StringBuilder.deleteCharAt:(I)Ljava/lang/StringBuilder;
     174: pop
     175: aload_1
     176: invokevirtual #42                 // Method java/lang/StringBuilder.toString:()Ljava/lang/String;
     179: areturn

  public static org.apache.hadoop.hbase.shaded.protobuf.generated.ReplicationProtos$TableCF getTableCF(org.apache.hadoop.hbase.shaded.protobuf.generated.ReplicationProtos$TableCF[], java.lang.String);
    Code:
       0: iconst_0
       1: istore_2
       2: aload_0
       3: arraylength
       4: istore_3
       5: iload_2
       6: iload_3
       7: if_icmpge     42
      10: aload_0
      11: iload_2
      12: aaload
      13: astore        4
      15: aload         4
      17: invokevirtual #48                 // Method org/apache/hadoop/hbase/shaded/protobuf/generated/ReplicationProtos$TableCF.getTableName:()Lorg/apache/hadoop/hbase/shaded/protobuf/generated/HBaseProtos$TableName;
      20: invokevirtual #53                 // Method org/apache/hadoop/hbase/shaded/protobuf/generated/HBaseProtos$TableName.getQualifier:()Lorg/apache/hbase/thirdparty/com/google/protobuf/ByteString;
      23: invokevirtual #50                 // Method org/apache/hbase/thirdparty/com/google/protobuf/ByteString.toStringUtf8:()Ljava/lang/String;
      26: aload_1
      27: invokevirtual #59                 // Method java/lang/String.equals:(Ljava/lang/Object;)Z
      30: ifeq          36
      33: aload         4
      35: areturn
      36: iinc          2, 1
      39: goto          5
      42: aconst_null
      43: areturn

  public static org.apache.hadoop.hbase.shaded.protobuf.generated.ReplicationProtos$TableCF[] parseTableCFs(byte[]) throws java.io.IOException;
    Code:
       0: aload_0
       1: ifnonnull     6
       4: aconst_null
       5: areturn
       6: aload_0
       7: invokestatic  #60                 // Method org/apache/hadoop/hbase/util/Bytes.toString:([B)Ljava/lang/String;
      10: invokestatic  #61                 // Method convert:(Ljava/lang/String;)[Lorg/apache/hadoop/hbase/shaded/protobuf/generated/ReplicationProtos$TableCF;
      13: areturn

  public static java.util.Map<org.apache.hadoop.hbase.TableName, java.util.List<java.lang.String>> parseTableCFsFromConfig(java.lang.String);
    Code:
       0: aload_0
       1: invokestatic  #61                 // Method convert:(Ljava/lang/String;)[Lorg/apache/hadoop/hbase/shaded/protobuf/generated/ReplicationProtos$TableCF;
       4: astore_1
       5: aload_1
       6: invokestatic  #62                 // Method convert2Map:([Lorg/apache/hadoop/hbase/shaded/protobuf/generated/ReplicationProtos$TableCF;)Ljava/util/Map;
       9: areturn

  public static java.util.Map<org.apache.hadoop.hbase.TableName, java.util.List<java.lang.String>> convert2Map(org.apache.hadoop.hbase.shaded.protobuf.generated.ReplicationProtos$TableCF[]);
    Code:
       0: aload_0
       1: ifnull        9
       4: aload_0
       5: arraylength
       6: ifne          11
       9: aconst_null
      10: areturn
      11: new           #63                 // class java/util/HashMap
      14: dup
      15: invokespecial #64                 // Method java/util/HashMap."<init>":()V
      18: astore_1
      19: iconst_0
      20: istore_2
      21: aload_0
      22: arraylength
      23: istore_3
      24: iload_2
      25: iload_3
      26: if_icmpge     136
      29: aload_0
      30: iload_2
      31: aaload
      32: astore        4
      34: new           #3                  // class java/util/ArrayList
      37: dup
      38: invokespecial #65                 // Method java/util/ArrayList."<init>":()V
      41: astore        5
      43: iconst_0
      44: istore        6
      46: aload         4
      48: invokevirtual #55                 // Method org/apache/hadoop/hbase/shaded/protobuf/generated/ReplicationProtos$TableCF.getFamiliesCount:()I
      51: istore        7
      53: iload         6
      55: iload         7
      57: if_icmpge     84
      60: aload         5
      62: aload         4
      64: iload         6
      66: invokevirtual #56                 // Method org/apache/hadoop/hbase/shaded/protobuf/generated/ReplicationProtos$TableCF.getFamilies:(I)Lorg/apache/hbase/thirdparty/com/google/protobuf/ByteString;
      69: invokevirtual #50                 // Method org/apache/hbase/thirdparty/com/google/protobuf/ByteString.toStringUtf8:()Ljava/lang/String;
      72: invokeinterface #25,  2           // InterfaceMethod java/util/List.add:(Ljava/lang/Object;)Z
      77: pop
      78: iinc          6, 1
      81: goto          53
      84: aload         5
      86: invokeinterface #26,  1           // InterfaceMethod java/util/List.size:()I
      91: ifle          114
      94: aload_1
      95: aload         4
      97: invokevirtual #48                 // Method org/apache/hadoop/hbase/shaded/protobuf/generated/ReplicationProtos$TableCF.getTableName:()Lorg/apache/hadoop/hbase/shaded/protobuf/generated/HBaseProtos$TableName;
     100: invokestatic  #66                 // Method org/apache/hadoop/hbase/shaded/protobuf/ProtobufUtil.toTableName:(Lorg/apache/hadoop/hbase/shaded/protobuf/generated/HBaseProtos$TableName;)Lorg/apache/hadoop/hbase/TableName;
     103: aload         5
     105: invokeinterface #67,  3           // InterfaceMethod java/util/Map.put:(Ljava/lang/Object;Ljava/lang/Object;)Ljava/lang/Object;
     110: pop
     111: goto          130
     114: aload_1
     115: aload         4
     117: invokevirtual #48                 // Method org/apache/hadoop/hbase/shaded/protobuf/generated/ReplicationProtos$TableCF.getTableName:()Lorg/apache/hadoop/hbase/shaded/protobuf/generated/HBaseProtos$TableName;
     120: invokestatic  #66                 // Method org/apache/hadoop/hbase/shaded/protobuf/ProtobufUtil.toTableName:(Lorg/apache/hadoop/hbase/shaded/protobuf/generated/HBaseProtos$TableName;)Lorg/apache/hadoop/hbase/TableName;
     123: aconst_null
     124: invokeinterface #67,  3           // InterfaceMethod java/util/Map.put:(Ljava/lang/Object;Ljava/lang/Object;)Ljava/lang/Object;
     129: pop
     130: iinc          2, 1
     133: goto          24
     136: aload_1
     137: areturn

  public static org.apache.hadoop.hbase.replication.ReplicationPeerConfig parsePeerFrom(byte[]) throws org.apache.hadoop.hbase.exceptions.DeserializationException;
    Code:
       0: aload_0
       1: invokestatic  #68                 // Method org/apache/hadoop/hbase/shaded/protobuf/ProtobufUtil.isPBMagicPrefix:([B)Z
       4: ifeq          50
       7: invokestatic  #69                 // Method org/apache/hadoop/hbase/shaded/protobuf/ProtobufUtil.lengthOfPBMagic:()I
      10: istore_1
      11: invokestatic  #70                 // Method org/apache/hadoop/hbase/shaded/protobuf/generated/ReplicationProtos$ReplicationPeer.newBuilder:()Lorg/apache/hadoop/hbase/shaded/protobuf/generated/ReplicationProtos$ReplicationPeer$Builder;
      14: astore_2
      15: aload_2
      16: aload_0
      17: iload_1
      18: aload_0
      19: arraylength
      20: iload_1
      21: isub
      22: invokestatic  #71                 // Method org/apache/hadoop/hbase/shaded/protobuf/ProtobufUtil.mergeFrom:(Lorg/apache/hbase/thirdparty/com/google/protobuf/Message$Builder;[BII)V
      25: aload_2
      26: invokevirtual #72                 // Method org/apache/hadoop/hbase/shaded/protobuf/generated/ReplicationProtos$ReplicationPeer$Builder.build:()Lorg/apache/hadoop/hbase/shaded/protobuf/generated/ReplicationProtos$ReplicationPeer;
      29: astore_3
      30: goto          45
      33: astore        4
      35: new           #74                 // class org/apache/hadoop/hbase/exceptions/DeserializationException
      38: dup
      39: aload         4
      41: invokespecial #75                 // Method org/apache/hadoop/hbase/exceptions/DeserializationException."<init>":(Ljava/lang/Throwable;)V
      44: athrow
      45: aload_3
      46: invokestatic  #76                 // Method convert:(Lorg/apache/hadoop/hbase/shaded/protobuf/generated/ReplicationProtos$ReplicationPeer;)Lorg/apache/hadoop/hbase/replication/ReplicationPeerConfig;
      49: areturn
      50: aload_0
      51: ifnull        59
      54: aload_0
      55: arraylength
      56: ifgt          69
      59: new           #74                 // class org/apache/hadoop/hbase/exceptions/DeserializationException
      62: dup
      63: ldc           #77                 // String Bytes to deserialize should not be empty.
      65: invokespecial #78                 // Method org/apache/hadoop/hbase/exceptions/DeserializationException."<init>":(Ljava/lang/String;)V
      68: athrow
      69: invokestatic  #79                 // Method org/apache/hadoop/hbase/replication/ReplicationPeerConfig.newBuilder:()Lorg/apache/hadoop/hbase/replication/ReplicationPeerConfigBuilder;
      72: aload_0
      73: invokestatic  #60                 // Method org/apache/hadoop/hbase/util/Bytes.toString:([B)Ljava/lang/String;
      76: invokeinterface #80,  2           // InterfaceMethod org/apache/hadoop/hbase/replication/ReplicationPeerConfigBuilder.setClusterKey:(Ljava/lang/String;)Lorg/apache/hadoop/hbase/replication/ReplicationPeerConfigBuilder;
      81: invokeinterface #81,  1           // InterfaceMethod org/apache/hadoop/hbase/replication/ReplicationPeerConfigBuilder.build:()Lorg/apache/hadoop/hbase/replication/ReplicationPeerConfig;
      86: areturn
    Exception table:
       from    to  target type
          15    30    33   Class java/io/IOException

  public static org.apache.hadoop.hbase.replication.ReplicationPeerConfig convert(org.apache.hadoop.hbase.shaded.protobuf.generated.ReplicationProtos$ReplicationPeer);
    Code:
       0: invokestatic  #79                 // Method org/apache/hadoop/hbase/replication/ReplicationPeerConfig.newBuilder:()Lorg/apache/hadoop/hbase/replication/ReplicationPeerConfigBuilder;
       3: astore_1
       4: aload_0
       5: invokevirtual #82                 // Method org/apache/hadoop/hbase/shaded/protobuf/generated/ReplicationProtos$ReplicationPeer.hasClusterkey:()Z
       8: ifeq          22
      11: aload_1
      12: aload_0
      13: invokevirtual #83                 // Method org/apache/hadoop/hbase/shaded/protobuf/generated/ReplicationProtos$ReplicationPeer.getClusterkey:()Ljava/lang/String;
      16: invokeinterface #80,  2           // InterfaceMethod org/apache/hadoop/hbase/replication/ReplicationPeerConfigBuilder.setClusterKey:(Ljava/lang/String;)Lorg/apache/hadoop/hbase/replication/ReplicationPeerConfigBuilder;
      21: pop
      22: aload_0
      23: invokevirtual #84                 // Method org/apache/hadoop/hbase/shaded/protobuf/generated/ReplicationProtos$ReplicationPeer.hasReplicationEndpointImpl:()Z
      26: ifeq          40
      29: aload_1
      30: aload_0
      31: invokevirtual #85                 // Method org/apache/hadoop/hbase/shaded/protobuf/generated/ReplicationProtos$ReplicationPeer.getReplicationEndpointImpl:()Ljava/lang/String;
      34: invokeinterface #86,  2           // InterfaceMethod org/apache/hadoop/hbase/replication/ReplicationPeerConfigBuilder.setReplicationEndpointImpl:(Ljava/lang/String;)Lorg/apache/hadoop/hbase/replication/ReplicationPeerConfigBuilder;
      39: pop
      40: aload_0
      41: invokevirtual #87                 // Method org/apache/hadoop/hbase/shaded/protobuf/generated/ReplicationProtos$ReplicationPeer.getDataList:()Ljava/util/List;
      44: invokeinterface #88,  1           // InterfaceMethod java/util/List.iterator:()Ljava/util/Iterator;
      49: astore_2
      50: aload_2
      51: invokeinterface #9,  1            // InterfaceMethod java/util/Iterator.hasNext:()Z
      56: ifeq          93
      59: aload_2
      60: invokeinterface #10,  1           // InterfaceMethod java/util/Iterator.next:()Ljava/lang/Object;
      65: checkcast     #89                 // class org/apache/hadoop/hbase/shaded/protobuf/generated/HBaseProtos$BytesBytesPair
      68: astore_3
      69: aload_1
      70: aload_3
      71: invokevirtual #90                 // Method org/apache/hadoop/hbase/shaded/protobuf/generated/HBaseProtos$BytesBytesPair.getFirst:()Lorg/apache/hbase/thirdparty/com/google/protobuf/ByteString;
      74: invokevirtual #91                 // Method org/apache/hbase/thirdparty/com/google/protobuf/ByteString.toByteArray:()[B
      77: aload_3
      78: invokevirtual #92                 // Method org/apache/hadoop/hbase/shaded/protobuf/generated/HBaseProtos$BytesBytesPair.getSecond:()Lorg/apache/hbase/thirdparty/com/google/protobuf/ByteString;
      81: invokevirtual #91                 // Method org/apache/hbase/thirdparty/com/google/protobuf/ByteString.toByteArray:()[B
      84: invokeinterface #93,  3           // InterfaceMethod org/apache/hadoop/hbase/replication/ReplicationPeerConfigBuilder.putPeerData:([B[B)Lorg/apache/hadoop/hbase/replication/ReplicationPeerConfigBuilder;
      89: pop
      90: goto          50
      93: aload_0
      94: invokevirtual #94                 // Method org/apache/hadoop/hbase/shaded/protobuf/generated/ReplicationProtos$ReplicationPeer.getConfigurationList:()Ljava/util/List;
      97: invokeinterface #88,  1           // InterfaceMethod java/util/List.iterator:()Ljava/util/Iterator;
     102: astore_2
     103: aload_2
     104: invokeinterface #9,  1            // InterfaceMethod java/util/Iterator.hasNext:()Z
     109: ifeq          140
     112: aload_2
     113: invokeinterface #10,  1           // InterfaceMethod java/util/Iterator.next:()Ljava/lang/Object;
     118: checkcast     #95                 // class org/apache/hadoop/hbase/shaded/protobuf/generated/HBaseProtos$NameStringPair
     121: astore_3
     122: aload_1
     123: aload_3
     124: invokevirtual #96                 // Method org/apache/hadoop/hbase/shaded/protobuf/generated/HBaseProtos$NameStringPair.getName:()Ljava/lang/String;
     127: aload_3
     128: invokevirtual #97                 // Method org/apache/hadoop/hbase/shaded/protobuf/generated/HBaseProtos$NameStringPair.getValue:()Ljava/lang/String;
     131: invokeinterface #98,  3           // InterfaceMethod org/apache/hadoop/hbase/replication/ReplicationPeerConfigBuilder.putConfiguration:(Ljava/lang/String;Ljava/lang/String;)Lorg/apache/hadoop/hbase/replication/ReplicationPeerConfigBuilder;
     136: pop
     137: goto          103
     140: aload_0
     141: invokevirtual #99                 // Method org/apache/hadoop/hbase/shaded/protobuf/generated/ReplicationProtos$ReplicationPeer.getTableCfsList:()Ljava/util/List;
     144: aload_0
     145: invokevirtual #100                // Method org/apache/hadoop/hbase/shaded/protobuf/generated/ReplicationProtos$ReplicationPeer.getTableCfsCount:()I
     148: anewarray     #27                 // class org/apache/hadoop/hbase/shaded/protobuf/generated/ReplicationProtos$TableCF
     151: invokeinterface #28,  2           // InterfaceMethod java/util/List.toArray:([Ljava/lang/Object;)[Ljava/lang/Object;
     156: checkcast     #29                 // class "[Lorg/apache/hadoop/hbase/shaded/protobuf/generated/ReplicationProtos$TableCF;"
     159: invokestatic  #62                 // Method convert2Map:([Lorg/apache/hadoop/hbase/shaded/protobuf/generated/ReplicationProtos$TableCF;)Ljava/util/Map;
     162: astore_2
     163: aload_2
     164: ifnull        175
     167: aload_1
     168: aload_2
     169: invokeinterface #101,  2          // InterfaceMethod org/apache/hadoop/hbase/replication/ReplicationPeerConfigBuilder.setTableCFsMap:(Ljava/util/Map;)Lorg/apache/hadoop/hbase/replication/ReplicationPeerConfigBuilder;
     174: pop
     175: aload_0
     176: invokevirtual #102                // Method org/apache/hadoop/hbase/shaded/protobuf/generated/ReplicationProtos$ReplicationPeer.getNamespacesList:()Ljava/util/List;
     179: astore_3
     180: aload_3
     181: ifnull        227
     184: aload_3
     185: invokeinterface #26,  1           // InterfaceMethod java/util/List.size:()I
     190: ifeq          227
     193: aload_1
     194: aload_3
     195: invokeinterface #103,  1          // InterfaceMethod java/util/List.stream:()Ljava/util/stream/Stream;
     200: invokedynamic #104,  0            // InvokeDynamic #0:apply:()Ljava/util/function/Function;
     205: invokeinterface #105,  2          // InterfaceMethod java/util/stream/Stream.map:(Ljava/util/function/Function;)Ljava/util/stream/Stream;
     210: invokestatic  #106                // Method java/util/stream/Collectors.toSet:()Ljava/util/stream/Collector;
     213: invokeinterface #107,  2          // InterfaceMethod java/util/stream/Stream.collect:(Ljava/util/stream/Collector;)Ljava/lang/Object;
     218: checkcast     #108                // class java/util/Set
     221: invokeinterface #109,  2          // InterfaceMethod org/apache/hadoop/hbase/replication/ReplicationPeerConfigBuilder.setNamespaces:(Ljava/util/Set;)Lorg/apache/hadoop/hbase/replication/ReplicationPeerConfigBuilder;
     226: pop
     227: aload_0
     228: invokevirtual #110                // Method org/apache/hadoop/hbase/shaded/protobuf/generated/ReplicationProtos$ReplicationPeer.hasBandwidth:()Z
     231: ifeq          245
     234: aload_1
     235: aload_0
     236: invokevirtual #111                // Method org/apache/hadoop/hbase/shaded/protobuf/generated/ReplicationProtos$ReplicationPeer.getBandwidth:()J
     239: invokeinterface #112,  3          // InterfaceMethod org/apache/hadoop/hbase/replication/ReplicationPeerConfigBuilder.setBandwidth:(J)Lorg/apache/hadoop/hbase/replication/ReplicationPeerConfigBuilder;
     244: pop
     245: aload_0
     246: invokevirtual #113                // Method org/apache/hadoop/hbase/shaded/protobuf/generated/ReplicationProtos$ReplicationPeer.hasReplicateAll:()Z
     249: ifeq          263
     252: aload_1
     253: aload_0
     254: invokevirtual #114                // Method org/apache/hadoop/hbase/shaded/protobuf/generated/ReplicationProtos$ReplicationPeer.getReplicateAll:()Z
     257: invokeinterface #115,  2          // InterfaceMethod org/apache/hadoop/hbase/replication/ReplicationPeerConfigBuilder.setReplicateAllUserTables:(Z)Lorg/apache/hadoop/hbase/replication/ReplicationPeerConfigBuilder;
     262: pop
     263: aload_0
     264: invokevirtual #116                // Method org/apache/hadoop/hbase/shaded/protobuf/generated/ReplicationProtos$ReplicationPeer.hasSerial:()Z
     267: ifeq          281
     270: aload_1
     271: aload_0
     272: invokevirtual #117                // Method org/apache/hadoop/hbase/shaded/protobuf/generated/ReplicationProtos$ReplicationPeer.getSerial:()Z
     275: invokeinterface #118,  2          // InterfaceMethod org/apache/hadoop/hbase/replication/ReplicationPeerConfigBuilder.setSerial:(Z)Lorg/apache/hadoop/hbase/replication/ReplicationPeerConfigBuilder;
     280: pop
     281: aload_0
     282: invokevirtual #119                // Method org/apache/hadoop/hbase/shaded/protobuf/generated/ReplicationProtos$ReplicationPeer.getExcludeTableCfsList:()Ljava/util/List;
     285: aload_0
     286: invokevirtual #120                // Method org/apache/hadoop/hbase/shaded/protobuf/generated/ReplicationProtos$ReplicationPeer.getExcludeTableCfsCount:()I
     289: anewarray     #27                 // class org/apache/hadoop/hbase/shaded/protobuf/generated/ReplicationProtos$TableCF
     292: invokeinterface #28,  2           // InterfaceMethod java/util/List.toArray:([Ljava/lang/Object;)[Ljava/lang/Object;
     297: checkcast     #29                 // class "[Lorg/apache/hadoop/hbase/shaded/protobuf/generated/ReplicationProtos$TableCF;"
     300: invokestatic  #62                 // Method convert2Map:([Lorg/apache/hadoop/hbase/shaded/protobuf/generated/ReplicationProtos$TableCF;)Ljava/util/Map;
     303: astore        4
     305: aload         4
     307: ifnull        319
     310: aload_1
     311: aload         4
     313: invokeinterface #121,  2          // InterfaceMethod org/apache/hadoop/hbase/replication/ReplicationPeerConfigBuilder.setExcludeTableCFsMap:(Ljava/util/Map;)Lorg/apache/hadoop/hbase/replication/ReplicationPeerConfigBuilder;
     318: pop
     319: aload_0
     320: invokevirtual #122                // Method org/apache/hadoop/hbase/shaded/protobuf/generated/ReplicationProtos$ReplicationPeer.getExcludeNamespacesList:()Ljava/util/List;
     323: astore        5
     325: aload         5
     327: ifnull        375
     330: aload         5
     332: invokeinterface #26,  1           // InterfaceMethod java/util/List.size:()I
     337: ifeq          375
     340: aload_1
     341: aload         5
     343: invokeinterface #103,  1          // InterfaceMethod java/util/List.stream:()Ljava/util/stream/Stream;
     348: invokedynamic #104,  0            // InvokeDynamic #0:apply:()Ljava/util/function/Function;
     353: invokeinterface #105,  2          // InterfaceMethod java/util/stream/Stream.map:(Ljava/util/function/Function;)Ljava/util/stream/Stream;
     358: invokestatic  #106                // Method java/util/stream/Collectors.toSet:()Ljava/util/stream/Collector;
     361: invokeinterface #107,  2          // InterfaceMethod java/util/stream/Stream.collect:(Ljava/util/stream/Collector;)Ljava/lang/Object;
     366: checkcast     #108                // class java/util/Set
     369: invokeinterface #123,  2          // InterfaceMethod org/apache/hadoop/hbase/replication/ReplicationPeerConfigBuilder.setExcludeNamespaces:(Ljava/util/Set;)Lorg/apache/hadoop/hbase/replication/ReplicationPeerConfigBuilder;
     374: pop
     375: aload_0
     376: invokevirtual #124                // Method org/apache/hadoop/hbase/shaded/protobuf/generated/ReplicationProtos$ReplicationPeer.hasRemoteWALDir:()Z
     379: ifeq          393
     382: aload_1
     383: aload_0
     384: invokevirtual #125                // Method org/apache/hadoop/hbase/shaded/protobuf/generated/ReplicationProtos$ReplicationPeer.getRemoteWALDir:()Ljava/lang/String;
     387: invokeinterface #126,  2          // InterfaceMethod org/apache/hadoop/hbase/replication/ReplicationPeerConfigBuilder.setRemoteWALDir:(Ljava/lang/String;)Lorg/apache/hadoop/hbase/replication/ReplicationPeerConfigBuilder;
     392: pop
     393: aload_1
     394: invokeinterface #81,  1           // InterfaceMethod org/apache/hadoop/hbase/replication/ReplicationPeerConfigBuilder.build:()Lorg/apache/hadoop/hbase/replication/ReplicationPeerConfig;
     399: areturn

  public static org.apache.hadoop.hbase.shaded.protobuf.generated.ReplicationProtos$ReplicationPeer convert(org.apache.hadoop.hbase.replication.ReplicationPeerConfig);
    Code:
       0: invokestatic  #70                 // Method org/apache/hadoop/hbase/shaded/protobuf/generated/ReplicationProtos$ReplicationPeer.newBuilder:()Lorg/apache/hadoop/hbase/shaded/protobuf/generated/ReplicationProtos$ReplicationPeer$Builder;
       3: astore_1
       4: aload_1
       5: aload_0
       6: invokevirtual #127                // Method org/apache/hadoop/hbase/replication/ReplicationPeerConfig.getClusterKey:()Ljava/lang/String;
       9: ifnull        19
      12: aload_0
      13: invokevirtual #127                // Method org/apache/hadoop/hbase/replication/ReplicationPeerConfig.getClusterKey:()Ljava/lang/String;
      16: goto          21
      19: ldc           #128                // String
      21: invokevirtual #129                // Method org/apache/hadoop/hbase/shaded/protobuf/generated/ReplicationProtos$ReplicationPeer$Builder.setClusterkey:(Ljava/lang/String;)Lorg/apache/hadoop/hbase/shaded/protobuf/generated/ReplicationProtos$ReplicationPeer$Builder;
      24: pop
      25: aload_0
      26: invokevirtual #130                // Method org/apache/hadoop/hbase/replication/ReplicationPeerConfig.getReplicationEndpointImpl:()Ljava/lang/String;
      29: ifnull        41
      32: aload_1
      33: aload_0
      34: invokevirtual #130                // Method org/apache/hadoop/hbase/replication/ReplicationPeerConfig.getReplicationEndpointImpl:()Ljava/lang/String;
      37: invokevirtual #131                // Method org/apache/hadoop/hbase/shaded/protobuf/generated/ReplicationProtos$ReplicationPeer$Builder.setReplicationEndpointImpl:(Ljava/lang/String;)Lorg/apache/hadoop/hbase/shaded/protobuf/generated/ReplicationProtos$ReplicationPeer$Builder;
      40: pop
      41: aload_0
      42: invokevirtual #132                // Method org/apache/hadoop/hbase/replication/ReplicationPeerConfig.getPeerData:()Ljava/util/Map;
      45: invokeinterface #4,  1            // InterfaceMethod java/util/Map.entrySet:()Ljava/util/Set;
      50: invokeinterface #8,  1            // InterfaceMethod java/util/Set.iterator:()Ljava/util/Iterator;
      55: astore_2
      56: aload_2
      57: invokeinterface #9,  1            // InterfaceMethod java/util/Iterator.hasNext:()Z
      62: ifeq          119
      65: aload_2
      66: invokeinterface #10,  1           // InterfaceMethod java/util/Iterator.next:()Ljava/lang/Object;
      71: checkcast     #11                 // class java/util/Map$Entry
      74: astore_3
      75: aload_1
      76: invokestatic  #133                // Method org/apache/hadoop/hbase/shaded/protobuf/generated/HBaseProtos$BytesBytesPair.newBuilder:()Lorg/apache/hadoop/hbase/shaded/protobuf/generated/HBaseProtos$BytesBytesPair$Builder;
      79: aload_3
      80: invokeinterface #13,  1           // InterfaceMethod java/util/Map$Entry.getKey:()Ljava/lang/Object;
      85: checkcast     #134                // class "[B"
      88: invokestatic  #135                // Method org/apache/hbase/thirdparty/com/google/protobuf/UnsafeByteOperations.unsafeWrap:([B)Lorg/apache/hbase/thirdparty/com/google/protobuf/ByteString;
      91: invokevirtual #136                // Method org/apache/hadoop/hbase/shaded/protobuf/generated/HBaseProtos$BytesBytesPair$Builder.setFirst:(Lorg/apache/hbase/thirdparty/com/google/protobuf/ByteString;)Lorg/apache/hadoop/hbase/shaded/protobuf/generated/HBaseProtos$BytesBytesPair$Builder;
      94: aload_3
      95: invokeinterface #17,  1           // InterfaceMethod java/util/Map$Entry.getValue:()Ljava/lang/Object;
     100: checkcast     #134                // class "[B"
     103: invokestatic  #135                // Method org/apache/hbase/thirdparty/com/google/protobuf/UnsafeByteOperations.unsafeWrap:([B)Lorg/apache/hbase/thirdparty/com/google/protobuf/ByteString;
     106: invokevirtual #137                // Method org/apache/hadoop/hbase/shaded/protobuf/generated/HBaseProtos$BytesBytesPair$Builder.setSecond:(Lorg/apache/hbase/thirdparty/com/google/protobuf/ByteString;)Lorg/apache/hadoop/hbase/shaded/protobuf/generated/HBaseProtos$BytesBytesPair$Builder;
     109: invokevirtual #138                // Method org/apache/hadoop/hbase/shaded/protobuf/generated/HBaseProtos$BytesBytesPair$Builder.build:()Lorg/apache/hadoop/hbase/shaded/protobuf/generated/HBaseProtos$BytesBytesPair;
     112: invokevirtual #139                // Method org/apache/hadoop/hbase/shaded/protobuf/generated/ReplicationProtos$ReplicationPeer$Builder.addData:(Lorg/apache/hadoop/hbase/shaded/protobuf/generated/HBaseProtos$BytesBytesPair;)Lorg/apache/hadoop/hbase/shaded/protobuf/generated/ReplicationProtos$ReplicationPeer$Builder;
     115: pop
     116: goto          56
     119: aload_0
     120: invokevirtual #140                // Method org/apache/hadoop/hbase/replication/ReplicationPeerConfig.getConfiguration:()Ljava/util/Map;
     123: invokeinterface #4,  1            // InterfaceMethod java/util/Map.entrySet:()Ljava/util/Set;
     128: invokeinterface #8,  1            // InterfaceMethod java/util/Set.iterator:()Ljava/util/Iterator;
     133: astore_2
     134: aload_2
     135: invokeinterface #9,  1            // InterfaceMethod java/util/Iterator.hasNext:()Z
     140: ifeq          191
     143: aload_2
     144: invokeinterface #10,  1           // InterfaceMethod java/util/Iterator.next:()Ljava/lang/Object;
     149: checkcast     #11                 // class java/util/Map$Entry
     152: astore_3
     153: aload_1
     154: invokestatic  #141                // Method org/apache/hadoop/hbase/shaded/protobuf/generated/HBaseProtos$NameStringPair.newBuilder:()Lorg/apache/hadoop/hbase/shaded/protobuf/generated/HBaseProtos$NameStringPair$Builder;
     157: aload_3
     158: invokeinterface #13,  1           // InterfaceMethod java/util/Map$Entry.getKey:()Ljava/lang/Object;
     163: checkcast     #21                 // class java/lang/String
     166: invokevirtual #142                // Method org/apache/hadoop/hbase/shaded/protobuf/generated/HBaseProtos$NameStringPair$Builder.setName:(Ljava/lang/String;)Lorg/apache/hadoop/hbase/shaded/protobuf/generated/HBaseProtos$NameStringPair$Builder;
     169: aload_3
     170: invokeinterface #17,  1           // InterfaceMethod java/util/Map$Entry.getValue:()Ljava/lang/Object;
     175: checkcast     #21                 // class java/lang/String
     178: invokevirtual #143                // Method org/apache/hadoop/hbase/shaded/protobuf/generated/HBaseProtos$NameStringPair$Builder.setValue:(Ljava/lang/String;)Lorg/apache/hadoop/hbase/shaded/protobuf/generated/HBaseProtos$NameStringPair$Builder;
     181: invokevirtual #144                // Method org/apache/hadoop/hbase/shaded/protobuf/generated/HBaseProtos$NameStringPair$Builder.build:()Lorg/apache/hadoop/hbase/shaded/protobuf/generated/HBaseProtos$NameStringPair;
     184: invokevirtual #145                // Method org/apache/hadoop/hbase/shaded/protobuf/generated/ReplicationProtos$ReplicationPeer$Builder.addConfiguration:(Lorg/apache/hadoop/hbase/shaded/protobuf/generated/HBaseProtos$NameStringPair;)Lorg/apache/hadoop/hbase/shaded/protobuf/generated/ReplicationProtos$ReplicationPeer$Builder;
     187: pop
     188: goto          134
     191: aload_0
     192: invokevirtual #146                // Method org/apache/hadoop/hbase/replication/ReplicationPeerConfig.getTableCFsMap:()Ljava/util/Map;
     195: invokestatic  #30                 // Method convert:(Ljava/util/Map;)[Lorg/apache/hadoop/hbase/shaded/protobuf/generated/ReplicationProtos$TableCF;
     198: astore_2
     199: aload_2
     200: ifnull        225
     203: iconst_0
     204: istore_3
     205: iload_3
     206: aload_2
     207: arraylength
     208: if_icmpge     225
     211: aload_1
     212: aload_2
     213: iload_3
     214: aaload
     215: invokevirtual #147                // Method org/apache/hadoop/hbase/shaded/protobuf/generated/ReplicationProtos$ReplicationPeer$Builder.addTableCfs:(Lorg/apache/hadoop/hbase/shaded/protobuf/generated/ReplicationProtos$TableCF;)Lorg/apache/hadoop/hbase/shaded/protobuf/generated/ReplicationProtos$ReplicationPeer$Builder;
     218: pop
     219: iinc          3, 1
     222: goto          205
     225: aload_0
     226: invokevirtual #148                // Method org/apache/hadoop/hbase/replication/ReplicationPeerConfig.getNamespaces:()Ljava/util/Set;
     229: astore_3
     230: aload_3
     231: ifnull        277
     234: aload_3
     235: invokeinterface #8,  1            // InterfaceMethod java/util/Set.iterator:()Ljava/util/Iterator;
     240: astore        4
     242: aload         4
     244: invokeinterface #9,  1            // InterfaceMethod java/util/Iterator.hasNext:()Z
     249: ifeq          277
     252: aload         4
     254: invokeinterface #10,  1           // InterfaceMethod java/util/Iterator.next:()Ljava/lang/Object;
     259: checkcast     #21                 // class java/lang/String
     262: astore        5
     264: aload_1
     265: aload         5
     267: invokestatic  #22                 // Method org/apache/hbase/thirdparty/com/google/protobuf/ByteString.copyFromUtf8:(Ljava/lang/String;)Lorg/apache/hbase/thirdparty/com/google/protobuf/ByteString;
     270: invokevirtual #149                // Method org/apache/hadoop/hbase/shaded/protobuf/generated/ReplicationProtos$ReplicationPeer$Builder.addNamespaces:(Lorg/apache/hbase/thirdparty/com/google/protobuf/ByteString;)Lorg/apache/hadoop/hbase/shaded/protobuf/generated/ReplicationProtos$ReplicationPeer$Builder;
     273: pop
     274: goto          242
     277: aload_1
     278: aload_0
     279: invokevirtual #150                // Method org/apache/hadoop/hbase/replication/ReplicationPeerConfig.getBandwidth:()J
     282: invokevirtual #151                // Method org/apache/hadoop/hbase/shaded/protobuf/generated/ReplicationProtos$ReplicationPeer$Builder.setBandwidth:(J)Lorg/apache/hadoop/hbase/shaded/protobuf/generated/ReplicationProtos$ReplicationPeer$Builder;
     285: pop
     286: aload_1
     287: aload_0
     288: invokevirtual #152                // Method org/apache/hadoop/hbase/replication/ReplicationPeerConfig.replicateAllUserTables:()Z
     291: invokevirtual #153                // Method org/apache/hadoop/hbase/shaded/protobuf/generated/ReplicationProtos$ReplicationPeer$Builder.setReplicateAll:(Z)Lorg/apache/hadoop/hbase/shaded/protobuf/generated/ReplicationProtos$ReplicationPeer$Builder;
     294: pop
     295: aload_1
     296: aload_0
     297: invokevirtual #154                // Method org/apache/hadoop/hbase/replication/ReplicationPeerConfig.isSerial:()Z
     300: invokevirtual #155                // Method org/apache/hadoop/hbase/shaded/protobuf/generated/ReplicationProtos$ReplicationPeer$Builder.setSerial:(Z)Lorg/apache/hadoop/hbase/shaded/protobuf/generated/ReplicationProtos$ReplicationPeer$Builder;
     303: pop
     304: aload_0
     305: invokevirtual #156                // Method org/apache/hadoop/hbase/replication/ReplicationPeerConfig.getExcludeTableCFsMap:()Ljava/util/Map;
     308: invokestatic  #30                 // Method convert:(Ljava/util/Map;)[Lorg/apache/hadoop/hbase/shaded/protobuf/generated/ReplicationProtos$TableCF;
     311: astore        4
     313: aload         4
     315: ifnull        345
     318: iconst_0
     319: istore        5
     321: iload         5
     323: aload         4
     325: arraylength
     326: if_icmpge     345
     329: aload_1
     330: aload         4
     332: iload         5
     334: aaload
     335: invokevirtual #157                // Method org/apache/hadoop/hbase/shaded/protobuf/generated/ReplicationProtos$ReplicationPeer$Builder.addExcludeTableCfs:(Lorg/apache/hadoop/hbase/shaded/protobuf/generated/ReplicationProtos$TableCF;)Lorg/apache/hadoop/hbase/shaded/protobuf/generated/ReplicationProtos$ReplicationPeer$Builder;
     338: pop
     339: iinc          5, 1
     342: goto          321
     345: aload_0
     346: invokevirtual #158                // Method org/apache/hadoop/hbase/replication/ReplicationPeerConfig.getExcludeNamespaces:()Ljava/util/Set;
     349: astore        5
     351: aload         5
     353: ifnull        400
     356: aload         5
     358: invokeinterface #8,  1            // InterfaceMethod java/util/Set.iterator:()Ljava/util/Iterator;
     363: astore        6
     365: aload         6
     367: invokeinterface #9,  1            // InterfaceMethod java/util/Iterator.hasNext:()Z
     372: ifeq          400
     375: aload         6
     377: invokeinterface #10,  1           // InterfaceMethod java/util/Iterator.next:()Ljava/lang/Object;
     382: checkcast     #21                 // class java/lang/String
     385: astore        7
     387: aload_1
     388: aload         7
     390: invokestatic  #22                 // Method org/apache/hbase/thirdparty/com/google/protobuf/ByteString.copyFromUtf8:(Ljava/lang/String;)Lorg/apache/hbase/thirdparty/com/google/protobuf/ByteString;
     393: invokevirtual #159                // Method org/apache/hadoop/hbase/shaded/protobuf/generated/ReplicationProtos$ReplicationPeer$Builder.addExcludeNamespaces:(Lorg/apache/hbase/thirdparty/com/google/protobuf/ByteString;)Lorg/apache/hadoop/hbase/shaded/protobuf/generated/ReplicationProtos$ReplicationPeer$Builder;
     396: pop
     397: goto          365
     400: aload_0
     401: invokevirtual #160                // Method org/apache/hadoop/hbase/replication/ReplicationPeerConfig.getRemoteWALDir:()Ljava/lang/String;
     404: ifnull        416
     407: aload_1
     408: aload_0
     409: invokevirtual #160                // Method org/apache/hadoop/hbase/replication/ReplicationPeerConfig.getRemoteWALDir:()Ljava/lang/String;
     412: invokevirtual #161                // Method org/apache/hadoop/hbase/shaded/protobuf/generated/ReplicationProtos$ReplicationPeer$Builder.setRemoteWALDir:(Ljava/lang/String;)Lorg/apache/hadoop/hbase/shaded/protobuf/generated/ReplicationProtos$ReplicationPeer$Builder;
     415: pop
     416: aload_1
     417: invokevirtual #72                 // Method org/apache/hadoop/hbase/shaded/protobuf/generated/ReplicationProtos$ReplicationPeer$Builder.build:()Lorg/apache/hadoop/hbase/shaded/protobuf/generated/ReplicationProtos$ReplicationPeer;
     420: areturn

  public static byte[] toByteArray(org.apache.hadoop.hbase.replication.ReplicationPeerConfig);
    Code:
       0: aload_0
       1: invokestatic  #162                // Method convert:(Lorg/apache/hadoop/hbase/replication/ReplicationPeerConfig;)Lorg/apache/hadoop/hbase/shaded/protobuf/generated/ReplicationProtos$ReplicationPeer;
       4: invokevirtual #163                // Method org/apache/hadoop/hbase/shaded/protobuf/generated/ReplicationProtos$ReplicationPeer.toByteArray:()[B
       7: astore_1
       8: aload_1
       9: invokestatic  #164                // Method org/apache/hadoop/hbase/shaded/protobuf/ProtobufUtil.prependPBMagic:([B)[B
      12: areturn

  public static org.apache.hadoop.hbase.replication.ReplicationPeerDescription toReplicationPeerDescription(org.apache.hadoop.hbase.shaded.protobuf.generated.ReplicationProtos$ReplicationPeerDescription);
    Code:
       0: getstatic     #165                // Field org/apache/hadoop/hbase/shaded/protobuf/generated/ReplicationProtos$ReplicationState$State.ENABLED:Lorg/apache/hadoop/hbase/shaded/protobuf/generated/ReplicationProtos$ReplicationState$State;
       3: aload_0
       4: invokevirtual #166                // Method org/apache/hadoop/hbase/shaded/protobuf/generated/ReplicationProtos$ReplicationPeerDescription.getState:()Lorg/apache/hadoop/hbase/shaded/protobuf/generated/ReplicationProtos$ReplicationState;
       7: invokevirtual #167                // Method org/apache/hadoop/hbase/shaded/protobuf/generated/ReplicationProtos$ReplicationState.getState:()Lorg/apache/hadoop/hbase/shaded/protobuf/generated/ReplicationProtos$ReplicationState$State;
      10: if_acmpne     17
      13: iconst_1
      14: goto          18
      17: iconst_0
      18: istore_1
      19: aload_0
      20: invokevirtual #168                // Method org/apache/hadoop/hbase/shaded/protobuf/generated/ReplicationProtos$ReplicationPeerDescription.getConfig:()Lorg/apache/hadoop/hbase/shaded/protobuf/generated/ReplicationProtos$ReplicationPeer;
      23: invokestatic  #76                 // Method convert:(Lorg/apache/hadoop/hbase/shaded/protobuf/generated/ReplicationProtos$ReplicationPeer;)Lorg/apache/hadoop/hbase/replication/ReplicationPeerConfig;
      26: astore_2
      27: new           #169                // class org/apache/hadoop/hbase/replication/ReplicationPeerDescription
      30: dup
      31: aload_0
      32: invokevirtual #170                // Method org/apache/hadoop/hbase/shaded/protobuf/generated/ReplicationProtos$ReplicationPeerDescription.getId:()Ljava/lang/String;
      35: iload_1
      36: aload_2
      37: aload_0
      38: invokevirtual #171                // Method org/apache/hadoop/hbase/shaded/protobuf/generated/ReplicationProtos$ReplicationPeerDescription.getSyncReplicationState:()Lorg/apache/hadoop/hbase/shaded/protobuf/generated/ReplicationProtos$SyncReplicationState;
      41: invokestatic  #172                // Method toSyncReplicationState:(Lorg/apache/hadoop/hbase/shaded/protobuf/generated/ReplicationProtos$SyncReplicationState;)Lorg/apache/hadoop/hbase/replication/SyncReplicationState;
      44: invokespecial #173                // Method org/apache/hadoop/hbase/replication/ReplicationPeerDescription."<init>":(Ljava/lang/String;ZLorg/apache/hadoop/hbase/replication/ReplicationPeerConfig;Lorg/apache/hadoop/hbase/replication/SyncReplicationState;)V
      47: areturn

  public static org.apache.hadoop.hbase.shaded.protobuf.generated.ReplicationProtos$ReplicationPeerDescription toProtoReplicationPeerDescription(org.apache.hadoop.hbase.replication.ReplicationPeerDescription);
    Code:
       0: invokestatic  #174                // Method org/apache/hadoop/hbase/shaded/protobuf/generated/ReplicationProtos$ReplicationPeerDescription.newBuilder:()Lorg/apache/hadoop/hbase/shaded/protobuf/generated/ReplicationProtos$ReplicationPeerDescription$Builder;
       3: astore_1
       4: aload_1
       5: aload_0
       6: invokevirtual #175                // Method org/apache/hadoop/hbase/replication/ReplicationPeerDescription.getPeerId:()Ljava/lang/String;
       9: invokevirtual #176                // Method org/apache/hadoop/hbase/shaded/protobuf/generated/ReplicationProtos$ReplicationPeerDescription$Builder.setId:(Ljava/lang/String;)Lorg/apache/hadoop/hbase/shaded/protobuf/generated/ReplicationProtos$ReplicationPeerDescription$Builder;
      12: pop
      13: invokestatic  #177                // Method org/apache/hadoop/hbase/shaded/protobuf/generated/ReplicationProtos$ReplicationState.newBuilder:()Lorg/apache/hadoop/hbase/shaded/protobuf/generated/ReplicationProtos$ReplicationState$Builder;
      16: astore_2
      17: aload_2
      18: aload_0
      19: invokevirtual #178                // Method org/apache/hadoop/hbase/replication/ReplicationPeerDescription.isEnabled:()Z
      22: ifeq          31
      25: getstatic     #165                // Field org/apache/hadoop/hbase/shaded/protobuf/generated/ReplicationProtos$ReplicationState$State.ENABLED:Lorg/apache/hadoop/hbase/shaded/protobuf/generated/ReplicationProtos$ReplicationState$State;
      28: goto          34
      31: getstatic     #179                // Field org/apache/hadoop/hbase/shaded/protobuf/generated/ReplicationProtos$ReplicationState$State.DISABLED:Lorg/apache/hadoop/hbase/shaded/protobuf/generated/ReplicationProtos$ReplicationState$State;
      34: invokevirtual #180                // Method org/apache/hadoop/hbase/shaded/protobuf/generated/ReplicationProtos$ReplicationState$Builder.setState:(Lorg/apache/hadoop/hbase/shaded/protobuf/generated/ReplicationProtos$ReplicationState$State;)Lorg/apache/hadoop/hbase/shaded/protobuf/generated/ReplicationProtos$ReplicationState$Builder;
      37: pop
      38: aload_1
      39: aload_2
      40: invokevirtual #181                // Method org/apache/hadoop/hbase/shaded/protobuf/generated/ReplicationProtos$ReplicationState$Builder.build:()Lorg/apache/hadoop/hbase/shaded/protobuf/generated/ReplicationProtos$ReplicationState;
      43: invokevirtual #182                // Method org/apache/hadoop/hbase/shaded/protobuf/generated/ReplicationProtos$ReplicationPeerDescription$Builder.setState:(Lorg/apache/hadoop/hbase/shaded/protobuf/generated/ReplicationProtos$ReplicationState;)Lorg/apache/hadoop/hbase/shaded/protobuf/generated/ReplicationProtos$ReplicationPeerDescription$Builder;
      46: pop
      47: aload_1
      48: aload_0
      49: invokevirtual #183                // Method org/apache/hadoop/hbase/replication/ReplicationPeerDescription.getPeerConfig:()Lorg/apache/hadoop/hbase/replication/ReplicationPeerConfig;
      52: invokestatic  #162                // Method convert:(Lorg/apache/hadoop/hbase/replication/ReplicationPeerConfig;)Lorg/apache/hadoop/hbase/shaded/protobuf/generated/ReplicationProtos$ReplicationPeer;
      55: invokevirtual #184                // Method org/apache/hadoop/hbase/shaded/protobuf/generated/ReplicationProtos$ReplicationPeerDescription$Builder.setConfig:(Lorg/apache/hadoop/hbase/shaded/protobuf/generated/ReplicationProtos$ReplicationPeer;)Lorg/apache/hadoop/hbase/shaded/protobuf/generated/ReplicationProtos$ReplicationPeerDescription$Builder;
      58: pop
      59: aload_1
      60: aload_0
      61: invokevirtual #185                // Method org/apache/hadoop/hbase/replication/ReplicationPeerDescription.getSyncReplicationState:()Lorg/apache/hadoop/hbase/replication/SyncReplicationState;
      64: invokestatic  #186                // Method toSyncReplicationState:(Lorg/apache/hadoop/hbase/replication/SyncReplicationState;)Lorg/apache/hadoop/hbase/shaded/protobuf/generated/ReplicationProtos$SyncReplicationState;
      67: invokevirtual #187                // Method org/apache/hadoop/hbase/shaded/protobuf/generated/ReplicationProtos$ReplicationPeerDescription$Builder.setSyncReplicationState:(Lorg/apache/hadoop/hbase/shaded/protobuf/generated/ReplicationProtos$SyncReplicationState;)Lorg/apache/hadoop/hbase/shaded/protobuf/generated/ReplicationProtos$ReplicationPeerDescription$Builder;
      70: pop
      71: aload_1
      72: invokevirtual #188                // Method org/apache/hadoop/hbase/shaded/protobuf/generated/ReplicationProtos$ReplicationPeerDescription$Builder.build:()Lorg/apache/hadoop/hbase/shaded/protobuf/generated/ReplicationProtos$ReplicationPeerDescription;
      75: areturn

  public static org.apache.hadoop.hbase.shaded.protobuf.generated.ReplicationProtos$SyncReplicationState toSyncReplicationState(org.apache.hadoop.hbase.replication.SyncReplicationState);
    Code:
       0: invokestatic  #189                // Method org/apache/hadoop/hbase/shaded/protobuf/generated/ReplicationProtos$SyncReplicationState.newBuilder:()Lorg/apache/hadoop/hbase/shaded/protobuf/generated/ReplicationProtos$SyncReplicationState$Builder;
       3: astore_1
       4: aload_1
       5: aload_0
       6: invokevirtual #190                // Method org/apache/hadoop/hbase/replication/SyncReplicationState.ordinal:()I
       9: invokestatic  #191                // Method org/apache/hadoop/hbase/shaded/protobuf/generated/ReplicationProtos$SyncReplicationState$State.forNumber:(I)Lorg/apache/hadoop/hbase/shaded/protobuf/generated/ReplicationProtos$SyncReplicationState$State;
      12: invokevirtual #192                // Method org/apache/hadoop/hbase/shaded/protobuf/generated/ReplicationProtos$SyncReplicationState$Builder.setState:(Lorg/apache/hadoop/hbase/shaded/protobuf/generated/ReplicationProtos$SyncReplicationState$State;)Lorg/apache/hadoop/hbase/shaded/protobuf/generated/ReplicationProtos$SyncReplicationState$Builder;
      15: pop
      16: aload_1
      17: invokevirtual #193                // Method org/apache/hadoop/hbase/shaded/protobuf/generated/ReplicationProtos$SyncReplicationState$Builder.build:()Lorg/apache/hadoop/hbase/shaded/protobuf/generated/ReplicationProtos$SyncReplicationState;
      20: areturn

  public static org.apache.hadoop.hbase.replication.SyncReplicationState toSyncReplicationState(org.apache.hadoop.hbase.shaded.protobuf.generated.ReplicationProtos$SyncReplicationState);
    Code:
       0: aload_0
       1: invokevirtual #194                // Method org/apache/hadoop/hbase/shaded/protobuf/generated/ReplicationProtos$SyncReplicationState.getState:()Lorg/apache/hadoop/hbase/shaded/protobuf/generated/ReplicationProtos$SyncReplicationState$State;
       4: invokevirtual #195                // Method org/apache/hadoop/hbase/shaded/protobuf/generated/ReplicationProtos$SyncReplicationState$State.getNumber:()I
       7: invokestatic  #196                // Method org/apache/hadoop/hbase/replication/SyncReplicationState.valueOf:(I)Lorg/apache/hadoop/hbase/replication/SyncReplicationState;
      10: areturn

  public static org.apache.hadoop.hbase.replication.ReplicationPeerConfig appendTableCFsToReplicationPeerConfig(java.util.Map<org.apache.hadoop.hbase.TableName, java.util.List<java.lang.String>>, org.apache.hadoop.hbase.replication.ReplicationPeerConfig);
    Code:
       0: aload_1
       1: invokestatic  #197                // Method org/apache/hadoop/hbase/replication/ReplicationPeerConfig.newBuilder:(Lorg/apache/hadoop/hbase/replication/ReplicationPeerConfig;)Lorg/apache/hadoop/hbase/replication/ReplicationPeerConfigBuilder;
       4: astore_2
       5: aload_1
       6: invokevirtual #146                // Method org/apache/hadoop/hbase/replication/ReplicationPeerConfig.getTableCFsMap:()Ljava/util/Map;
       9: astore_3
      10: aload_3
      11: ifnonnull     25
      14: aload_2
      15: aload_0
      16: invokeinterface #101,  2          // InterfaceMethod org/apache/hadoop/hbase/replication/ReplicationPeerConfigBuilder.setTableCFsMap:(Ljava/util/Map;)Lorg/apache/hadoop/hbase/replication/ReplicationPeerConfigBuilder;
      21: pop
      22: goto          37
      25: aload_2
      26: aload_3
      27: aload_0
      28: invokestatic  #198                // Method mergeTableCFs:(Ljava/util/Map;Ljava/util/Map;)Ljava/util/Map;
      31: invokeinterface #101,  2          // InterfaceMethod org/apache/hadoop/hbase/replication/ReplicationPeerConfigBuilder.setTableCFsMap:(Ljava/util/Map;)Lorg/apache/hadoop/hbase/replication/ReplicationPeerConfigBuilder;
      36: pop
      37: aload_2
      38: invokeinterface #81,  1           // InterfaceMethod org/apache/hadoop/hbase/replication/ReplicationPeerConfigBuilder.build:()Lorg/apache/hadoop/hbase/replication/ReplicationPeerConfig;
      43: areturn

  public static org.apache.hadoop.hbase.replication.ReplicationPeerConfig appendExcludeTableCFsToReplicationPeerConfig(java.util.Map<org.apache.hadoop.hbase.TableName, java.util.List<java.lang.String>>, org.apache.hadoop.hbase.replication.ReplicationPeerConfig) throws org.apache.hadoop.hbase.replication.ReplicationException;
    Code:
       0: aload_0
       1: ifnonnull     14
       4: new           #199                // class org/apache/hadoop/hbase/replication/ReplicationException
       7: dup
       8: ldc           #200                // String exclude tableCfs is null
      10: invokespecial #201                // Method org/apache/hadoop/hbase/replication/ReplicationException."<init>":(Ljava/lang/String;)V
      13: athrow
      14: aload_1
      15: invokestatic  #197                // Method org/apache/hadoop/hbase/replication/ReplicationPeerConfig.newBuilder:(Lorg/apache/hadoop/hbase/replication/ReplicationPeerConfig;)Lorg/apache/hadoop/hbase/replication/ReplicationPeerConfigBuilder;
      18: astore_2
      19: aload_1
      20: invokevirtual #156                // Method org/apache/hadoop/hbase/replication/ReplicationPeerConfig.getExcludeTableCFsMap:()Ljava/util/Map;
      23: astore_3
      24: aload_3
      25: ifnonnull     39
      28: aload_2
      29: aload_0
      30: invokeinterface #121,  2          // InterfaceMethod org/apache/hadoop/hbase/replication/ReplicationPeerConfigBuilder.setExcludeTableCFsMap:(Ljava/util/Map;)Lorg/apache/hadoop/hbase/replication/ReplicationPeerConfigBuilder;
      35: pop
      36: goto          51
      39: aload_2
      40: aload_3
      41: aload_0
      42: invokestatic  #198                // Method mergeTableCFs:(Ljava/util/Map;Ljava/util/Map;)Ljava/util/Map;
      45: invokeinterface #121,  2          // InterfaceMethod org/apache/hadoop/hbase/replication/ReplicationPeerConfigBuilder.setExcludeTableCFsMap:(Ljava/util/Map;)Lorg/apache/hadoop/hbase/replication/ReplicationPeerConfigBuilder;
      50: pop
      51: aload_2
      52: invokeinterface #81,  1           // InterfaceMethod org/apache/hadoop/hbase/replication/ReplicationPeerConfigBuilder.build:()Lorg/apache/hadoop/hbase/replication/ReplicationPeerConfig;
      57: areturn

  public static org.apache.hadoop.hbase.replication.ReplicationPeerConfig removeTableCFsFromReplicationPeerConfig(java.util.Map<org.apache.hadoop.hbase.TableName, java.util.List<java.lang.String>>, org.apache.hadoop.hbase.replication.ReplicationPeerConfig, java.lang.String) throws org.apache.hadoop.hbase.replication.ReplicationException;
    Code:
       0: aload_1
       1: invokevirtual #146                // Method org/apache/hadoop/hbase/replication/ReplicationPeerConfig.getTableCFsMap:()Ljava/util/Map;
       4: astore_3
       5: aload_3
       6: ifnonnull     41
       9: new           #199                // class org/apache/hadoop/hbase/replication/ReplicationException
      12: dup
      13: new           #38                 // class java/lang/StringBuilder
      16: dup
      17: invokespecial #39                 // Method java/lang/StringBuilder."<init>":()V
      20: ldc           #212                // String Table-Cfs for peer:
      22: invokevirtual #41                 // Method java/lang/StringBuilder.append:(Ljava/lang/String;)Ljava/lang/StringBuilder;
      25: aload_2
      26: invokevirtual #41                 // Method java/lang/StringBuilder.append:(Ljava/lang/String;)Ljava/lang/StringBuilder;
      29: ldc           #213                // String  is null
      31: invokevirtual #41                 // Method java/lang/StringBuilder.append:(Ljava/lang/String;)Ljava/lang/StringBuilder;
      34: invokevirtual #42                 // Method java/lang/StringBuilder.toString:()Ljava/lang/String;
      37: invokespecial #201                // Method org/apache/hadoop/hbase/replication/ReplicationException."<init>":(Ljava/lang/String;)V
      40: athrow
      41: aload_3
      42: invokestatic  #202                // Method copyTableCFsMap:(Ljava/util/Map;)Ljava/util/Map;
      45: astore        4
      47: aload_0
      48: invokeinterface #4,  1            // InterfaceMethod java/util/Map.entrySet:()Ljava/util/Set;
      53: invokeinterface #8,  1            // InterfaceMethod java/util/Set.iterator:()Ljava/util/Iterator;
      58: astore        5
      60: aload         5
      62: invokeinterface #9,  1            // InterfaceMethod java/util/Iterator.hasNext:()Z
      67: ifeq          404
      70: aload         5
      72: invokeinterface #10,  1           // InterfaceMethod java/util/Iterator.next:()Ljava/lang/Object;
      77: checkcast     #11                 // class java/util/Map$Entry
      80: astore        6
      82: aload         6
      84: invokeinterface #13,  1           // InterfaceMethod java/util/Map$Entry.getKey:()Ljava/lang/Object;
      89: checkcast     #14                 // class org/apache/hadoop/hbase/TableName
      92: astore        7
      94: aload         6
      96: invokeinterface #17,  1           // InterfaceMethod java/util/Map$Entry.getValue:()Ljava/lang/Object;
     101: checkcast     #18                 // class java/util/Collection
     104: astore        8
     106: aload         4
     108: aload         7
     110: invokeinterface #203,  2          // InterfaceMethod java/util/Map.containsKey:(Ljava/lang/Object;)Z
     115: ifeq          364
     118: aload         4
     120: aload         7
     122: invokeinterface #204,  2          // InterfaceMethod java/util/Map.get:(Ljava/lang/Object;)Ljava/lang/Object;
     127: checkcast     #205                // class java/util/List
     130: astore        9
     132: aload         9
     134: ifnonnull     165
     137: aload         8
     139: ifnull        152
     142: aload         8
     144: invokeinterface #19,  1           // InterfaceMethod java/util/Collection.isEmpty:()Z
     149: ifeq          165
     152: aload         4
     154: aload         7
     156: invokeinterface #214,  2          // InterfaceMethod java/util/Map.remove:(Ljava/lang/Object;)Ljava/lang/Object;
     161: pop
     162: goto          361
     165: aload         9
     167: ifnull        247
     170: aload         8
     172: ifnull        247
     175: aload         8
     177: invokeinterface #19,  1           // InterfaceMethod java/util/Collection.isEmpty:()Z
     182: ifne          247
     185: new           #206                // class java/util/HashSet
     188: dup
     189: aload         9
     191: invokespecial #207                // Method java/util/HashSet."<init>":(Ljava/util/Collection;)V
     194: astore        10
     196: aload         10
     198: aload         8
     200: invokeinterface #215,  2          // InterfaceMethod java/util/Set.removeAll:(Ljava/util/Collection;)Z
     205: pop
     206: aload         10
     208: invokeinterface #216,  1          // InterfaceMethod java/util/Set.isEmpty:()Z
     213: ifeq          229
     216: aload         4
     218: aload         7
     220: invokeinterface #214,  2          // InterfaceMethod java/util/Map.remove:(Ljava/lang/Object;)Ljava/lang/Object;
     225: pop
     226: goto          244
     229: aload         4
     231: aload         7
     233: aload         10
     235: invokestatic  #209                // Method org/apache/hbase/thirdparty/com/google/common/collect/Lists.newArrayList:(Ljava/lang/Iterable;)Ljava/util/ArrayList;
     238: invokeinterface #67,  3           // InterfaceMethod java/util/Map.put:(Ljava/lang/Object;Ljava/lang/Object;)Ljava/lang/Object;
     243: pop
     244: goto          361
     247: aload         9
     249: ifnonnull     304
     252: aload         8
     254: ifnull        304
     257: aload         8
     259: invokeinterface #19,  1           // InterfaceMethod java/util/Collection.isEmpty:()Z
     264: ifne          304
     267: new           #199                // class org/apache/hadoop/hbase/replication/ReplicationException
     270: dup
     271: new           #38                 // class java/lang/StringBuilder
     274: dup
     275: invokespecial #39                 // Method java/lang/StringBuilder."<init>":()V
     278: ldc           #217                // String Cannot remove cf of table:
     280: invokevirtual #41                 // Method java/lang/StringBuilder.append:(Ljava/lang/String;)Ljava/lang/StringBuilder;
     283: aload         7
     285: invokevirtual #218                // Method java/lang/StringBuilder.append:(Ljava/lang/Object;)Ljava/lang/StringBuilder;
     288: ldc           #219                // String  which doesn't specify cfs from table-cfs config in peer:
     290: invokevirtual #41                 // Method java/lang/StringBuilder.append:(Ljava/lang/String;)Ljava/lang/StringBuilder;
     293: aload_2
     294: invokevirtual #41                 // Method java/lang/StringBuilder.append:(Ljava/lang/String;)Ljava/lang/StringBuilder;
     297: invokevirtual #42                 // Method java/lang/StringBuilder.toString:()Ljava/lang/String;
     300: invokespecial #201                // Method org/apache/hadoop/hbase/replication/ReplicationException."<init>":(Ljava/lang/String;)V
     303: athrow
     304: aload         9
     306: ifnull        361
     309: aload         8
     311: ifnull        324
     314: aload         8
     316: invokeinterface #19,  1           // InterfaceMethod java/util/Collection.isEmpty:()Z
     321: ifeq          361
     324: new           #199                // class org/apache/hadoop/hbase/replication/ReplicationException
     327: dup
     328: new           #38                 // class java/lang/StringBuilder
     331: dup
     332: invokespecial #39                 // Method java/lang/StringBuilder."<init>":()V
     335: ldc           #220                // String Cannot remove table:
     337: invokevirtual #41                 // Method java/lang/StringBuilder.append:(Ljava/lang/String;)Ljava/lang/StringBuilder;
     340: aload         7
     342: invokevirtual #218                // Method java/lang/StringBuilder.append:(Ljava/lang/Object;)Ljava/lang/StringBuilder;
     345: ldc           #221                // String  which has specified cfs from table-cfs config in peer:
     347: invokevirtual #41                 // Method java/lang/StringBuilder.append:(Ljava/lang/String;)Ljava/lang/StringBuilder;
     350: aload_2
     351: invokevirtual #41                 // Method java/lang/StringBuilder.append:(Ljava/lang/String;)Ljava/lang/StringBuilder;
     354: invokevirtual #42                 // Method java/lang/StringBuilder.toString:()Ljava/lang/String;
     357: invokespecial #201                // Method org/apache/hadoop/hbase/replication/ReplicationException."<init>":(Ljava/lang/String;)V
     360: athrow
     361: goto          401
     364: new           #199                // class org/apache/hadoop/hbase/replication/ReplicationException
     367: dup
     368: new           #38                 // class java/lang/StringBuilder
     371: dup
     372: invokespecial #39                 // Method java/lang/StringBuilder."<init>":()V
     375: ldc           #222                // String No table:
     377: invokevirtual #41                 // Method java/lang/StringBuilder.append:(Ljava/lang/String;)Ljava/lang/StringBuilder;
     380: aload         7
     382: invokevirtual #218                // Method java/lang/StringBuilder.append:(Ljava/lang/Object;)Ljava/lang/StringBuilder;
     385: ldc           #223                // String  in table-cfs config of peer:
     387: invokevirtual #41                 // Method java/lang/StringBuilder.append:(Ljava/lang/String;)Ljava/lang/StringBuilder;
     390: aload_2
     391: invokevirtual #41                 // Method java/lang/StringBuilder.append:(Ljava/lang/String;)Ljava/lang/StringBuilder;
     394: invokevirtual #42                 // Method java/lang/StringBuilder.toString:()Ljava/lang/String;
     397: invokespecial #201                // Method org/apache/hadoop/hbase/replication/ReplicationException."<init>":(Ljava/lang/String;)V
     400: athrow
     401: goto          60
     404: aload_1
     405: invokestatic  #197                // Method org/apache/hadoop/hbase/replication/ReplicationPeerConfig.newBuilder:(Lorg/apache/hadoop/hbase/replication/ReplicationPeerConfig;)Lorg/apache/hadoop/hbase/replication/ReplicationPeerConfigBuilder;
     408: astore        5
     410: aload         5
     412: aload         4
     414: invokeinterface #101,  2          // InterfaceMethod org/apache/hadoop/hbase/replication/ReplicationPeerConfigBuilder.setTableCFsMap:(Ljava/util/Map;)Lorg/apache/hadoop/hbase/replication/ReplicationPeerConfigBuilder;
     419: pop
     420: aload         5
     422: invokeinterface #81,  1           // InterfaceMethod org/apache/hadoop/hbase/replication/ReplicationPeerConfigBuilder.build:()Lorg/apache/hadoop/hbase/replication/ReplicationPeerConfig;
     427: areturn

  public static org.apache.hadoop.hbase.replication.ReplicationPeerConfig removeExcludeTableCFsFromReplicationPeerConfig(java.util.Map<org.apache.hadoop.hbase.TableName, java.util.List<java.lang.String>>, org.apache.hadoop.hbase.replication.ReplicationPeerConfig, java.lang.String) throws org.apache.hadoop.hbase.replication.ReplicationException;
    Code:
       0: aload_0
       1: ifnonnull     14
       4: new           #199                // class org/apache/hadoop/hbase/replication/ReplicationException
       7: dup
       8: ldc           #200                // String exclude tableCfs is null
      10: invokespecial #201                // Method org/apache/hadoop/hbase/replication/ReplicationException."<init>":(Ljava/lang/String;)V
      13: athrow
      14: aload_1
      15: invokevirtual #156                // Method org/apache/hadoop/hbase/replication/ReplicationPeerConfig.getExcludeTableCFsMap:()Ljava/util/Map;
      18: astore_3
      19: aload_3
      20: ifnonnull     55
      23: new           #199                // class org/apache/hadoop/hbase/replication/ReplicationException
      26: dup
      27: new           #38                 // class java/lang/StringBuilder
      30: dup
      31: invokespecial #39                 // Method java/lang/StringBuilder."<init>":()V
      34: ldc           #224                // String exclude-Table-Cfs for peer:
      36: invokevirtual #41                 // Method java/lang/StringBuilder.append:(Ljava/lang/String;)Ljava/lang/StringBuilder;
      39: aload_2
      40: invokevirtual #41                 // Method java/lang/StringBuilder.append:(Ljava/lang/String;)Ljava/lang/StringBuilder;
      43: ldc           #213                // String  is null
      45: invokevirtual #41                 // Method java/lang/StringBuilder.append:(Ljava/lang/String;)Ljava/lang/StringBuilder;
      48: invokevirtual #42                 // Method java/lang/StringBuilder.toString:()Ljava/lang/String;
      51: invokespecial #201                // Method org/apache/hadoop/hbase/replication/ReplicationException."<init>":(Ljava/lang/String;)V
      54: athrow
      55: aload_3
      56: invokestatic  #202                // Method copyTableCFsMap:(Ljava/util/Map;)Ljava/util/Map;
      59: astore        4
      61: aload_0
      62: invokeinterface #4,  1            // InterfaceMethod java/util/Map.entrySet:()Ljava/util/Set;
      67: invokeinterface #8,  1            // InterfaceMethod java/util/Set.iterator:()Ljava/util/Iterator;
      72: astore        5
      74: aload         5
      76: invokeinterface #9,  1            // InterfaceMethod java/util/Iterator.hasNext:()Z
      81: ifeq          418
      84: aload         5
      86: invokeinterface #10,  1           // InterfaceMethod java/util/Iterator.next:()Ljava/lang/Object;
      91: checkcast     #11                 // class java/util/Map$Entry
      94: astore        6
      96: aload         6
      98: invokeinterface #13,  1           // InterfaceMethod java/util/Map$Entry.getKey:()Ljava/lang/Object;
     103: checkcast     #14                 // class org/apache/hadoop/hbase/TableName
     106: astore        7
     108: aload         6
     110: invokeinterface #17,  1           // InterfaceMethod java/util/Map$Entry.getValue:()Ljava/lang/Object;
     115: checkcast     #18                 // class java/util/Collection
     118: astore        8
     120: aload         4
     122: aload         7
     124: invokeinterface #203,  2          // InterfaceMethod java/util/Map.containsKey:(Ljava/lang/Object;)Z
     129: ifeq          378
     132: aload         4
     134: aload         7
     136: invokeinterface #204,  2          // InterfaceMethod java/util/Map.get:(Ljava/lang/Object;)Ljava/lang/Object;
     141: checkcast     #205                // class java/util/List
     144: astore        9
     146: aload         9
     148: ifnonnull     179
     151: aload         8
     153: ifnull        166
     156: aload         8
     158: invokeinterface #19,  1           // InterfaceMethod java/util/Collection.isEmpty:()Z
     163: ifeq          179
     166: aload         4
     168: aload         7
     170: invokeinterface #214,  2          // InterfaceMethod java/util/Map.remove:(Ljava/lang/Object;)Ljava/lang/Object;
     175: pop
     176: goto          375
     179: aload         9
     181: ifnull        261
     184: aload         8
     186: ifnull        261
     189: aload         8
     191: invokeinterface #19,  1           // InterfaceMethod java/util/Collection.isEmpty:()Z
     196: ifne          261
     199: new           #206                // class java/util/HashSet
     202: dup
     203: aload         9
     205: invokespecial #207                // Method java/util/HashSet."<init>":(Ljava/util/Collection;)V
     208: astore        10
     210: aload         10
     212: aload         8
     214: invokeinterface #215,  2          // InterfaceMethod java/util/Set.removeAll:(Ljava/util/Collection;)Z
     219: pop
     220: aload         10
     222: invokeinterface #216,  1          // InterfaceMethod java/util/Set.isEmpty:()Z
     227: ifeq          243
     230: aload         4
     232: aload         7
     234: invokeinterface #214,  2          // InterfaceMethod java/util/Map.remove:(Ljava/lang/Object;)Ljava/lang/Object;
     239: pop
     240: goto          258
     243: aload         4
     245: aload         7
     247: aload         10
     249: invokestatic  #209                // Method org/apache/hbase/thirdparty/com/google/common/collect/Lists.newArrayList:(Ljava/lang/Iterable;)Ljava/util/ArrayList;
     252: invokeinterface #67,  3           // InterfaceMethod java/util/Map.put:(Ljava/lang/Object;Ljava/lang/Object;)Ljava/lang/Object;
     257: pop
     258: goto          375
     261: aload         9
     263: ifnonnull     318
     266: aload         8
     268: ifnull        318
     271: aload         8
     273: invokeinterface #19,  1           // InterfaceMethod java/util/Collection.isEmpty:()Z
     278: ifne          318
     281: new           #199                // class org/apache/hadoop/hbase/replication/ReplicationException
     284: dup
     285: new           #38                 // class java/lang/StringBuilder
     288: dup
     289: invokespecial #39                 // Method java/lang/StringBuilder."<init>":()V
     292: ldc           #217                // String Cannot remove cf of table:
     294: invokevirtual #41                 // Method java/lang/StringBuilder.append:(Ljava/lang/String;)Ljava/lang/StringBuilder;
     297: aload         7
     299: invokevirtual #218                // Method java/lang/StringBuilder.append:(Ljava/lang/Object;)Ljava/lang/StringBuilder;
     302: ldc           #225                // String  which doesn't specify cfs from exclude-table-cfs config in peer:
     304: invokevirtual #41                 // Method java/lang/StringBuilder.append:(Ljava/lang/String;)Ljava/lang/StringBuilder;
     307: aload_2
     308: invokevirtual #41                 // Method java/lang/StringBuilder.append:(Ljava/lang/String;)Ljava/lang/StringBuilder;
     311: invokevirtual #42                 // Method java/lang/StringBuilder.toString:()Ljava/lang/String;
     314: invokespecial #201                // Method org/apache/hadoop/hbase/replication/ReplicationException."<init>":(Ljava/lang/String;)V
     317: athrow
     318: aload         9
     320: ifnull        375
     323: aload         8
     325: ifnull        338
     328: aload         8
     330: invokeinterface #19,  1           // InterfaceMethod java/util/Collection.isEmpty:()Z
     335: ifeq          375
     338: new           #199                // class org/apache/hadoop/hbase/replication/ReplicationException
     341: dup
     342: new           #38                 // class java/lang/StringBuilder
     345: dup
     346: invokespecial #39                 // Method java/lang/StringBuilder."<init>":()V
     349: ldc           #220                // String Cannot remove table:
     351: invokevirtual #41                 // Method java/lang/StringBuilder.append:(Ljava/lang/String;)Ljava/lang/StringBuilder;
     354: aload         7
     356: invokevirtual #218                // Method java/lang/StringBuilder.append:(Ljava/lang/Object;)Ljava/lang/StringBuilder;
     359: ldc           #226                // String  which has specified cfs from exclude-table-cfs config in peer:
     361: invokevirtual #41                 // Method java/lang/StringBuilder.append:(Ljava/lang/String;)Ljava/lang/StringBuilder;
     364: aload_2
     365: invokevirtual #41                 // Method java/lang/StringBuilder.append:(Ljava/lang/String;)Ljava/lang/StringBuilder;
     368: invokevirtual #42                 // Method java/lang/StringBuilder.toString:()Ljava/lang/String;
     371: invokespecial #201                // Method org/apache/hadoop/hbase/replication/ReplicationException."<init>":(Ljava/lang/String;)V
     374: athrow
     375: goto          415
     378: new           #199                // class org/apache/hadoop/hbase/replication/ReplicationException
     381: dup
     382: new           #38                 // class java/lang/StringBuilder
     385: dup
     386: invokespecial #39                 // Method java/lang/StringBuilder."<init>":()V
     389: ldc           #222                // String No table:
     391: invokevirtual #41                 // Method java/lang/StringBuilder.append:(Ljava/lang/String;)Ljava/lang/StringBuilder;
     394: aload         7
     396: invokevirtual #218                // Method java/lang/StringBuilder.append:(Ljava/lang/Object;)Ljava/lang/StringBuilder;
     399: ldc           #227                // String  in exclude-table-cfs config of peer:
     401: invokevirtual #41                 // Method java/lang/StringBuilder.append:(Ljava/lang/String;)Ljava/lang/StringBuilder;
     404: aload_2
     405: invokevirtual #41                 // Method java/lang/StringBuilder.append:(Ljava/lang/String;)Ljava/lang/StringBuilder;
     408: invokevirtual #42                 // Method java/lang/StringBuilder.toString:()Ljava/lang/String;
     411: invokespecial #201                // Method org/apache/hadoop/hbase/replication/ReplicationException."<init>":(Ljava/lang/String;)V
     414: athrow
     415: goto          74
     418: aload_1
     419: invokestatic  #197                // Method org/apache/hadoop/hbase/replication/ReplicationPeerConfig.newBuilder:(Lorg/apache/hadoop/hbase/replication/ReplicationPeerConfig;)Lorg/apache/hadoop/hbase/replication/ReplicationPeerConfigBuilder;
     422: astore        5
     424: aload         5
     426: aload         4
     428: invokeinterface #121,  2          // InterfaceMethod org/apache/hadoop/hbase/replication/ReplicationPeerConfigBuilder.setExcludeTableCFsMap:(Ljava/util/Map;)Lorg/apache/hadoop/hbase/replication/ReplicationPeerConfigBuilder;
     433: pop
     434: aload         5
     436: invokeinterface #81,  1           // InterfaceMethod org/apache/hadoop/hbase/replication/ReplicationPeerConfigBuilder.build:()Lorg/apache/hadoop/hbase/replication/ReplicationPeerConfig;
     441: areturn

  public static org.apache.hadoop.conf.Configuration getPeerClusterConfiguration(org.apache.hadoop.conf.Configuration, org.apache.hadoop.hbase.replication.ReplicationPeerDescription) throws java.io.IOException;
    Code:
       0: aload_1
       1: invokevirtual #183                // Method org/apache/hadoop/hbase/replication/ReplicationPeerDescription.getPeerConfig:()Lorg/apache/hadoop/hbase/replication/ReplicationPeerConfig;
       4: astore_2
       5: aload_0
       6: aload_2
       7: invokevirtual #127                // Method org/apache/hadoop/hbase/replication/ReplicationPeerConfig.getClusterKey:()Ljava/lang/String;
      10: invokestatic  #228                // Method org/apache/hadoop/hbase/HBaseConfiguration.createClusterConf:(Lorg/apache/hadoop/conf/Configuration;Ljava/lang/String;)Lorg/apache/hadoop/conf/Configuration;
      13: astore_3
      14: goto          51
      17: astore        4
      19: new           #73                 // class java/io/IOException
      22: dup
      23: new           #38                 // class java/lang/StringBuilder
      26: dup
      27: invokespecial #39                 // Method java/lang/StringBuilder."<init>":()V
      30: ldc           #229                // String Can't get peer configuration for peerId=
      32: invokevirtual #41                 // Method java/lang/StringBuilder.append:(Ljava/lang/String;)Ljava/lang/StringBuilder;
      35: aload_1
      36: invokevirtual #175                // Method org/apache/hadoop/hbase/replication/ReplicationPeerDescription.getPeerId:()Ljava/lang/String;
      39: invokevirtual #41                 // Method java/lang/StringBuilder.append:(Ljava/lang/String;)Ljava/lang/StringBuilder;
      42: invokevirtual #42                 // Method java/lang/StringBuilder.toString:()Ljava/lang/String;
      45: aload         4
      47: invokespecial #230                // Method java/io/IOException."<init>":(Ljava/lang/String;Ljava/lang/Throwable;)V
      50: athrow
      51: aload_2
      52: invokevirtual #140                // Method org/apache/hadoop/hbase/replication/ReplicationPeerConfig.getConfiguration:()Ljava/util/Map;
      55: invokeinterface #231,  1          // InterfaceMethod java/util/Map.isEmpty:()Z
      60: ifne          92
      63: new           #232                // class org/apache/hadoop/hbase/CompoundConfiguration
      66: dup
      67: invokespecial #233                // Method org/apache/hadoop/hbase/CompoundConfiguration."<init>":()V
      70: astore        4
      72: aload         4
      74: aload_3
      75: invokevirtual #234                // Method org/apache/hadoop/hbase/CompoundConfiguration.add:(Lorg/apache/hadoop/conf/Configuration;)Lorg/apache/hadoop/hbase/CompoundConfiguration;
      78: pop
      79: aload         4
      81: aload_2
      82: invokevirtual #140                // Method org/apache/hadoop/hbase/replication/ReplicationPeerConfig.getConfiguration:()Ljava/util/Map;
      85: invokevirtual #235                // Method org/apache/hadoop/hbase/CompoundConfiguration.addStringMap:(Ljava/util/Map;)Lorg/apache/hadoop/hbase/CompoundConfiguration;
      88: pop
      89: aload         4
      91: areturn
      92: aload_3
      93: areturn
    Exception table:
       from    to  target type
           5    14    17   Class java/io/IOException

  static {};
    Code:
       0: ldc           #236                // class org/apache/hadoop/hbase/client/replication/ReplicationPeerConfigUtil
       2: invokestatic  #237                // Method org/slf4j/LoggerFactory.getLogger:(Ljava/lang/Class;)Lorg/slf4j/Logger;
       5: putstatic     #37                 // Field LOG:Lorg/slf4j/Logger;
       8: return
}
