Compiled from "ReplicationPeerConfigUpgrader.java"
public class org.apache.hadoop.hbase.replication.master.ReplicationPeerConfigUpgrader {
  public org.apache.hadoop.hbase.replication.master.ReplicationPeerConfigUpgrader(org.apache.hadoop.hbase.zookeeper.ZKWatcher, org.apache.hadoop.conf.Configuration);
    Code:
       0: aload_0
       1: invokespecial #3                  // Method java/lang/Object."<init>":()V
       4: aload_0
       5: aload_1
       6: putfield      #4                  // Field zookeeper:Lorg/apache/hadoop/hbase/zookeeper/ZKWatcher;
       9: aload_0
      10: aload_2
      11: putfield      #5                  // Field conf:Lorg/apache/hadoop/conf/Configuration;
      14: aload_0
      15: aload_1
      16: aload_2
      17: invokestatic  #6                  // Method org/apache/hadoop/hbase/replication/ReplicationStorageFactory.getReplicationPeerStorage:(Lorg/apache/hadoop/hbase/zookeeper/ZKWatcher;Lorg/apache/hadoop/conf/Configuration;)Lorg/apache/hadoop/hbase/replication/ReplicationPeerStorage;
      20: putfield      #7                  // Field peerStorage:Lorg/apache/hadoop/hbase/replication/ReplicationPeerStorage;
      23: return

  public void upgrade() throws java.lang.Exception;
    Code:
       0: aload_0
       1: getfield      #5                  // Field conf:Lorg/apache/hadoop/conf/Configuration;
       4: invokestatic  #8                  // Method org/apache/hadoop/hbase/client/ConnectionFactory.createConnection:(Lorg/apache/hadoop/conf/Configuration;)Lorg/apache/hadoop/hbase/client/Connection;
       7: astore_1
       8: aconst_null
       9: astore_2
      10: aload_1
      11: invokeinterface #9,  1            // InterfaceMethod org/apache/hadoop/hbase/client/Connection.getAdmin:()Lorg/apache/hadoop/hbase/client/Admin;
      16: astore_3
      17: aload_3
      18: invokeinterface #10,  1           // InterfaceMethod org/apache/hadoop/hbase/client/Admin.listReplicationPeers:()Ljava/util/List;
      23: aload_3
      24: invokedynamic #11,  0             // InvokeDynamic #0:accept:(Lorg/apache/hadoop/hbase/client/Admin;)Ljava/util/function/Consumer;
      29: invokeinterface #12,  2           // InterfaceMethod java/util/List.forEach:(Ljava/util/function/Consumer;)V
      34: aload_1
      35: ifnull        113
      38: aload_2
      39: ifnull        60
      42: aload_1
      43: invokeinterface #13,  1           // InterfaceMethod org/apache/hadoop/hbase/client/Connection.close:()V
      48: goto          113
      51: astore_3
      52: aload_2
      53: aload_3
      54: invokevirtual #15                 // Method java/lang/Throwable.addSuppressed:(Ljava/lang/Throwable;)V
      57: goto          113
      60: aload_1
      61: invokeinterface #13,  1           // InterfaceMethod org/apache/hadoop/hbase/client/Connection.close:()V
      66: goto          113
      69: astore_3
      70: aload_3
      71: astore_2
      72: aload_3
      73: athrow
      74: astore        4
      76: aload_1
      77: ifnull        110
      80: aload_2
      81: ifnull        104
      84: aload_1
      85: invokeinterface #13,  1           // InterfaceMethod org/apache/hadoop/hbase/client/Connection.close:()V
      90: goto          110
      93: astore        5
      95: aload_2
      96: aload         5
      98: invokevirtual #15                 // Method java/lang/Throwable.addSuppressed:(Ljava/lang/Throwable;)V
     101: goto          110
     104: aload_1
     105: invokeinterface #13,  1           // InterfaceMethod org/apache/hadoop/hbase/client/Connection.close:()V
     110: aload         4
     112: athrow
     113: return
    Exception table:
       from    to  target type
          42    48    51   Class java/lang/Throwable
          10    34    69   Class java/lang/Throwable
          10    34    74   any
          84    90    93   Class java/lang/Throwable
          69    76    74   any

  public void copyTableCFs() throws org.apache.hadoop.hbase.replication.ReplicationException;
    Code:
       0: aload_0
       1: getfield      #7                  // Field peerStorage:Lorg/apache/hadoop/hbase/replication/ReplicationPeerStorage;
       4: invokeinterface #16,  1           // InterfaceMethod org/apache/hadoop/hbase/replication/ReplicationPeerStorage.listPeerIds:()Ljava/util/List;
       9: invokeinterface #17,  1           // InterfaceMethod java/util/List.iterator:()Ljava/util/Iterator;
      14: astore_1
      15: aload_1
      16: invokeinterface #18,  1           // InterfaceMethod java/util/Iterator.hasNext:()Z
      21: ifeq          72
      24: aload_1
      25: invokeinterface #19,  1           // InterfaceMethod java/util/Iterator.next:()Ljava/lang/Object;
      30: checkcast     #20                 // class java/lang/String
      33: astore_2
      34: aload_0
      35: aload_2
      36: invokevirtual #21                 // Method copyTableCFs:(Ljava/lang/String;)Z
      39: ifne          69
      42: getstatic     #22                 // Field LOG:Lorg/slf4j/Logger;
      45: new           #23                 // class java/lang/StringBuilder
      48: dup
      49: invokespecial #24                 // Method java/lang/StringBuilder."<init>":()V
      52: ldc           #25                 // String upgrade tableCFs failed for peerId=
      54: invokevirtual #26                 // Method java/lang/StringBuilder.append:(Ljava/lang/String;)Ljava/lang/StringBuilder;
      57: aload_2
      58: invokevirtual #26                 // Method java/lang/StringBuilder.append:(Ljava/lang/String;)Ljava/lang/StringBuilder;
      61: invokevirtual #27                 // Method java/lang/StringBuilder.toString:()Ljava/lang/String;
      64: invokeinterface #28,  2           // InterfaceMethod org/slf4j/Logger.error:(Ljava/lang/String;)V
      69: goto          15
      72: return

  protected java.lang.String getTableCFsNode(java.lang.String);
    Code:
       0: aload_0
       1: getfield      #4                  // Field zookeeper:Lorg/apache/hadoop/hbase/zookeeper/ZKWatcher;
       4: invokevirtual #29                 // Method org/apache/hadoop/hbase/zookeeper/ZKWatcher.getZNodePaths:()Lorg/apache/hadoop/hbase/zookeeper/ZNodePaths;
       7: getfield      #30                 // Field org/apache/hadoop/hbase/zookeeper/ZNodePaths.baseZNode:Ljava/lang/String;
      10: aload_0
      11: getfield      #5                  // Field conf:Lorg/apache/hadoop/conf/Configuration;
      14: ldc           #31                 // String zookeeper.znode.replication
      16: ldc           #32                 // String replication
      18: invokevirtual #33                 // Method org/apache/hadoop/conf/Configuration.get:(Ljava/lang/String;Ljava/lang/String;)Ljava/lang/String;
      21: invokestatic  #34                 // Method org/apache/hadoop/hbase/zookeeper/ZNodePaths.joinZNode:(Ljava/lang/String;Ljava/lang/String;)Ljava/lang/String;
      24: astore_2
      25: aload_2
      26: aload_0
      27: getfield      #5                  // Field conf:Lorg/apache/hadoop/conf/Configuration;
      30: ldc           #35                 // String zookeeper.znode.replication.peers
      32: ldc           #36                 // String peers
      34: invokevirtual #33                 // Method org/apache/hadoop/conf/Configuration.get:(Ljava/lang/String;Ljava/lang/String;)Ljava/lang/String;
      37: invokestatic  #34                 // Method org/apache/hadoop/hbase/zookeeper/ZNodePaths.joinZNode:(Ljava/lang/String;Ljava/lang/String;)Ljava/lang/String;
      40: astore_3
      41: aload_3
      42: aload_1
      43: aload_0
      44: getfield      #5                  // Field conf:Lorg/apache/hadoop/conf/Configuration;
      47: ldc           #38                 // String zookeeper.znode.replication.peers.tableCFs
      49: ldc           #39                 // String tableCFs
      51: invokevirtual #33                 // Method org/apache/hadoop/conf/Configuration.get:(Ljava/lang/String;Ljava/lang/String;)Ljava/lang/String;
      54: invokestatic  #34                 // Method org/apache/hadoop/hbase/zookeeper/ZNodePaths.joinZNode:(Ljava/lang/String;Ljava/lang/String;)Ljava/lang/String;
      57: invokestatic  #34                 // Method org/apache/hadoop/hbase/zookeeper/ZNodePaths.joinZNode:(Ljava/lang/String;Ljava/lang/String;)Ljava/lang/String;
      60: areturn

  public boolean copyTableCFs(java.lang.String) throws org.apache.hadoop.hbase.replication.ReplicationException;
    Code:
       0: aload_0
       1: aload_1
       2: invokevirtual #40                 // Method getTableCFsNode:(Ljava/lang/String;)Ljava/lang/String;
       5: astore_2
       6: aload_0
       7: getfield      #4                  // Field zookeeper:Lorg/apache/hadoop/hbase/zookeeper/ZKWatcher;
      10: aload_2
      11: invokestatic  #41                 // Method org/apache/hadoop/hbase/zookeeper/ZKUtil.checkExists:(Lorg/apache/hadoop/hbase/zookeeper/ZKWatcher;Ljava/lang/String;)I
      14: iconst_m1
      15: if_icmpeq     150
      18: aload_0
      19: getfield      #7                  // Field peerStorage:Lorg/apache/hadoop/hbase/replication/ReplicationPeerStorage;
      22: aload_1
      23: invokeinterface #42,  2           // InterfaceMethod org/apache/hadoop/hbase/replication/ReplicationPeerStorage.getPeerConfig:(Ljava/lang/String;)Lorg/apache/hadoop/hbase/replication/ReplicationPeerConfig;
      28: astore_3
      29: aload_3
      30: invokevirtual #43                 // Method org/apache/hadoop/hbase/replication/ReplicationPeerConfig.getTableCFsMap:()Ljava/util/Map;
      33: ifnull        48
      36: aload_3
      37: invokevirtual #43                 // Method org/apache/hadoop/hbase/replication/ReplicationPeerConfig.getTableCFsMap:()Ljava/util/Map;
      40: invokeinterface #44,  1           // InterfaceMethod java/util/Map.isEmpty:()Z
      45: ifeq          123
      48: getstatic     #22                 // Field LOG:Lorg/slf4j/Logger;
      51: new           #23                 // class java/lang/StringBuilder
      54: dup
      55: invokespecial #24                 // Method java/lang/StringBuilder."<init>":()V
      58: ldc           #45                 // String Copy table ColumnFamilies into peer=
      60: invokevirtual #26                 // Method java/lang/StringBuilder.append:(Ljava/lang/String;)Ljava/lang/StringBuilder;
      63: aload_1
      64: invokevirtual #26                 // Method java/lang/StringBuilder.append:(Ljava/lang/String;)Ljava/lang/StringBuilder;
      67: invokevirtual #27                 // Method java/lang/StringBuilder.toString:()Ljava/lang/String;
      70: invokeinterface #46,  2           // InterfaceMethod org/slf4j/Logger.info:(Ljava/lang/String;)V
      75: aload_0
      76: getfield      #4                  // Field zookeeper:Lorg/apache/hadoop/hbase/zookeeper/ZKWatcher;
      79: aload_2
      80: invokestatic  #47                 // Method org/apache/hadoop/hbase/zookeeper/ZKUtil.getData:(Lorg/apache/hadoop/hbase/zookeeper/ZKWatcher;Ljava/lang/String;)[B
      83: invokestatic  #48                 // Method org/apache/hadoop/hbase/client/replication/ReplicationPeerConfigUtil.parseTableCFs:([B)[Lorg/apache/hadoop/hbase/shaded/protobuf/generated/ReplicationProtos$TableCF;
      86: astore        4
      88: aload         4
      90: ifnull        120
      93: aload         4
      95: arraylength
      96: ifle          120
      99: aload_3
     100: aload         4
     102: invokestatic  #49                 // Method org/apache/hadoop/hbase/client/replication/ReplicationPeerConfigUtil.convert2Map:([Lorg/apache/hadoop/hbase/shaded/protobuf/generated/ReplicationProtos$TableCF;)Ljava/util/Map;
     105: invokevirtual #50                 // Method org/apache/hadoop/hbase/replication/ReplicationPeerConfig.setTableCFsMap:(Ljava/util/Map;)Lorg/apache/hadoop/hbase/replication/ReplicationPeerConfig;
     108: pop
     109: aload_0
     110: getfield      #7                  // Field peerStorage:Lorg/apache/hadoop/hbase/replication/ReplicationPeerStorage;
     113: aload_1
     114: aload_3
     115: invokeinterface #51,  3           // InterfaceMethod org/apache/hadoop/hbase/replication/ReplicationPeerStorage.updatePeerConfig:(Ljava/lang/String;Lorg/apache/hadoop/hbase/replication/ReplicationPeerConfig;)V
     120: goto          150
     123: getstatic     #22                 // Field LOG:Lorg/slf4j/Logger;
     126: new           #23                 // class java/lang/StringBuilder
     129: dup
     130: invokespecial #24                 // Method java/lang/StringBuilder."<init>":()V
     133: ldc           #52                 // String No tableCFs in peerNode:
     135: invokevirtual #26                 // Method java/lang/StringBuilder.append:(Ljava/lang/String;)Ljava/lang/StringBuilder;
     138: aload_1
     139: invokevirtual #26                 // Method java/lang/StringBuilder.append:(Ljava/lang/String;)Ljava/lang/StringBuilder;
     142: invokevirtual #27                 // Method java/lang/StringBuilder.toString:()Ljava/lang/String;
     145: invokeinterface #46,  2           // InterfaceMethod org/slf4j/Logger.info:(Ljava/lang/String;)V
     150: goto          246
     153: astore_3
     154: getstatic     #22                 // Field LOG:Lorg/slf4j/Logger;
     157: new           #23                 // class java/lang/StringBuilder
     160: dup
     161: invokespecial #24                 // Method java/lang/StringBuilder."<init>":()V
     164: ldc           #54                 // String NOTICE!! Update peerId failed, peerId=
     166: invokevirtual #26                 // Method java/lang/StringBuilder.append:(Ljava/lang/String;)Ljava/lang/StringBuilder;
     169: aload_1
     170: invokevirtual #26                 // Method java/lang/StringBuilder.append:(Ljava/lang/String;)Ljava/lang/StringBuilder;
     173: invokevirtual #27                 // Method java/lang/StringBuilder.toString:()Ljava/lang/String;
     176: aload_3
     177: invokeinterface #55,  3           // InterfaceMethod org/slf4j/Logger.warn:(Ljava/lang/String;Ljava/lang/Throwable;)V
     182: iconst_0
     183: ireturn
     184: astore_3
     185: getstatic     #22                 // Field LOG:Lorg/slf4j/Logger;
     188: new           #23                 // class java/lang/StringBuilder
     191: dup
     192: invokespecial #24                 // Method java/lang/StringBuilder."<init>":()V
     195: ldc           #54                 // String NOTICE!! Update peerId failed, peerId=
     197: invokevirtual #26                 // Method java/lang/StringBuilder.append:(Ljava/lang/String;)Ljava/lang/StringBuilder;
     200: aload_1
     201: invokevirtual #26                 // Method java/lang/StringBuilder.append:(Ljava/lang/String;)Ljava/lang/StringBuilder;
     204: invokevirtual #27                 // Method java/lang/StringBuilder.toString:()Ljava/lang/String;
     207: aload_3
     208: invokeinterface #55,  3           // InterfaceMethod org/slf4j/Logger.warn:(Ljava/lang/String;Ljava/lang/Throwable;)V
     213: iconst_0
     214: ireturn
     215: astore_3
     216: getstatic     #22                 // Field LOG:Lorg/slf4j/Logger;
     219: new           #23                 // class java/lang/StringBuilder
     222: dup
     223: invokespecial #24                 // Method java/lang/StringBuilder."<init>":()V
     226: ldc           #54                 // String NOTICE!! Update peerId failed, peerId=
     228: invokevirtual #26                 // Method java/lang/StringBuilder.append:(Ljava/lang/String;)Ljava/lang/StringBuilder;
     231: aload_1
     232: invokevirtual #26                 // Method java/lang/StringBuilder.append:(Ljava/lang/String;)Ljava/lang/StringBuilder;
     235: invokevirtual #27                 // Method java/lang/StringBuilder.toString:()Ljava/lang/String;
     238: aload_3
     239: invokeinterface #55,  3           // InterfaceMethod org/slf4j/Logger.warn:(Ljava/lang/String;Ljava/lang/Throwable;)V
     244: iconst_0
     245: ireturn
     246: iconst_1
     247: ireturn
    Exception table:
       from    to  target type
           6   150   153   Class org/apache/zookeeper/KeeperException
           6   150   184   Class java/lang/InterruptedException
           6   150   215   Class java/io/IOException

  public static void main(java.lang.String[]) throws java.lang.Exception;
    Code:
       0: aload_0
       1: arraylength
       2: iconst_1
       3: if_icmpeq     9
       6: invokestatic  #69                 // Method printUsageAndExit:()V
       9: aload_0
      10: iconst_0
      11: aaload
      12: ldc           #70                 // String -help
      14: invokevirtual #71                 // Method java/lang/String.equals:(Ljava/lang/Object;)Z
      17: ifne          31
      20: aload_0
      21: iconst_0
      22: aaload
      23: ldc           #72                 // String -h
      25: invokevirtual #71                 // Method java/lang/String.equals:(Ljava/lang/Object;)Z
      28: ifeq          37
      31: invokestatic  #69                 // Method printUsageAndExit:()V
      34: goto          288
      37: aload_0
      38: iconst_0
      39: aaload
      40: ldc           #73                 // String copyTableCFs
      42: invokevirtual #71                 // Method java/lang/String.equals:(Ljava/lang/Object;)Z
      45: ifeq          161
      48: invokestatic  #74                 // Method org/apache/hadoop/hbase/HBaseConfiguration.create:()Lorg/apache/hadoop/conf/Configuration;
      51: astore_1
      52: new           #75                 // class org/apache/hadoop/hbase/zookeeper/ZKWatcher
      55: dup
      56: aload_1
      57: ldc           #76                 // String ReplicationPeerConfigUpgrader
      59: aconst_null
      60: invokespecial #77                 // Method org/apache/hadoop/hbase/zookeeper/ZKWatcher."<init>":(Lorg/apache/hadoop/conf/Configuration;Ljava/lang/String;Lorg/apache/hadoop/hbase/Abortable;)V
      63: astore_2
      64: aconst_null
      65: astore_3
      66: new           #37                 // class org/apache/hadoop/hbase/replication/master/ReplicationPeerConfigUpgrader
      69: dup
      70: aload_2
      71: aload_1
      72: invokespecial #78                 // Method "<init>":(Lorg/apache/hadoop/hbase/zookeeper/ZKWatcher;Lorg/apache/hadoop/conf/Configuration;)V
      75: astore        4
      77: aload         4
      79: invokevirtual #79                 // Method copyTableCFs:()V
      82: aload_2
      83: ifnull        158
      86: aload_3
      87: ifnull        108
      90: aload_2
      91: invokevirtual #80                 // Method org/apache/hadoop/hbase/zookeeper/ZKWatcher.close:()V
      94: goto          158
      97: astore        4
      99: aload_3
     100: aload         4
     102: invokevirtual #15                 // Method java/lang/Throwable.addSuppressed:(Ljava/lang/Throwable;)V
     105: goto          158
     108: aload_2
     109: invokevirtual #80                 // Method org/apache/hadoop/hbase/zookeeper/ZKWatcher.close:()V
     112: goto          158
     115: astore        4
     117: aload         4
     119: astore_3
     120: aload         4
     122: athrow
     123: astore        5
     125: aload_2
     126: ifnull        155
     129: aload_3
     130: ifnull        151
     133: aload_2
     134: invokevirtual #80                 // Method org/apache/hadoop/hbase/zookeeper/ZKWatcher.close:()V
     137: goto          155
     140: astore        6
     142: aload_3
     143: aload         6
     145: invokevirtual #15                 // Method java/lang/Throwable.addSuppressed:(Ljava/lang/Throwable;)V
     148: goto          155
     151: aload_2
     152: invokevirtual #80                 // Method org/apache/hadoop/hbase/zookeeper/ZKWatcher.close:()V
     155: aload         5
     157: athrow
     158: goto          288
     161: aload_0
     162: iconst_0
     163: aaload
     164: ldc           #81                 // String upgrade
     166: invokevirtual #71                 // Method java/lang/String.equals:(Ljava/lang/Object;)Z
     169: ifeq          285
     172: invokestatic  #74                 // Method org/apache/hadoop/hbase/HBaseConfiguration.create:()Lorg/apache/hadoop/conf/Configuration;
     175: astore_1
     176: new           #75                 // class org/apache/hadoop/hbase/zookeeper/ZKWatcher
     179: dup
     180: aload_1
     181: ldc           #76                 // String ReplicationPeerConfigUpgrader
     183: aconst_null
     184: invokespecial #77                 // Method org/apache/hadoop/hbase/zookeeper/ZKWatcher."<init>":(Lorg/apache/hadoop/conf/Configuration;Ljava/lang/String;Lorg/apache/hadoop/hbase/Abortable;)V
     187: astore_2
     188: aconst_null
     189: astore_3
     190: new           #37                 // class org/apache/hadoop/hbase/replication/master/ReplicationPeerConfigUpgrader
     193: dup
     194: aload_2
     195: aload_1
     196: invokespecial #78                 // Method "<init>":(Lorg/apache/hadoop/hbase/zookeeper/ZKWatcher;Lorg/apache/hadoop/conf/Configuration;)V
     199: astore        4
     201: aload         4
     203: invokevirtual #82                 // Method upgrade:()V
     206: aload_2
     207: ifnull        282
     210: aload_3
     211: ifnull        232
     214: aload_2
     215: invokevirtual #80                 // Method org/apache/hadoop/hbase/zookeeper/ZKWatcher.close:()V
     218: goto          282
     221: astore        4
     223: aload_3
     224: aload         4
     226: invokevirtual #15                 // Method java/lang/Throwable.addSuppressed:(Ljava/lang/Throwable;)V
     229: goto          282
     232: aload_2
     233: invokevirtual #80                 // Method org/apache/hadoop/hbase/zookeeper/ZKWatcher.close:()V
     236: goto          282
     239: astore        4
     241: aload         4
     243: astore_3
     244: aload         4
     246: athrow
     247: astore        7
     249: aload_2
     250: ifnull        279
     253: aload_3
     254: ifnull        275
     257: aload_2
     258: invokevirtual #80                 // Method org/apache/hadoop/hbase/zookeeper/ZKWatcher.close:()V
     261: goto          279
     264: astore        8
     266: aload_3
     267: aload         8
     269: invokevirtual #15                 // Method java/lang/Throwable.addSuppressed:(Ljava/lang/Throwable;)V
     272: goto          279
     275: aload_2
     276: invokevirtual #80                 // Method org/apache/hadoop/hbase/zookeeper/ZKWatcher.close:()V
     279: aload         7
     281: athrow
     282: goto          288
     285: invokestatic  #69                 // Method printUsageAndExit:()V
     288: return
    Exception table:
       from    to  target type
          90    94    97   Class java/lang/Throwable
          66    82   115   Class java/lang/Throwable
          66    82   123   any
         133   137   140   Class java/lang/Throwable
         115   125   123   any
         214   218   221   Class java/lang/Throwable
         190   206   239   Class java/lang/Throwable
         190   206   247   any
         257   261   264   Class java/lang/Throwable
         239   249   247   any

  static {};
    Code:
       0: ldc           #37                 // class org/apache/hadoop/hbase/replication/master/ReplicationPeerConfigUpgrader
       2: invokestatic  #92                 // Method org/slf4j/LoggerFactory.getLogger:(Ljava/lang/Class;)Lorg/slf4j/Logger;
       5: putstatic     #22                 // Field LOG:Lorg/slf4j/Logger;
       8: return
}
