Compiled from "ReplicationPeerConfigBuilder.java"
public interface org.apache.hadoop.hbase.replication.ReplicationPeerConfigBuilder {
  public abstract org.apache.hadoop.hbase.replication.ReplicationPeerConfigBuilder setClusterKey(java.lang.String);

  public abstract org.apache.hadoop.hbase.replication.ReplicationPeerConfigBuilder setReplicationEndpointImpl(java.lang.String);

  public abstract org.apache.hadoop.hbase.replication.ReplicationPeerConfigBuilder putConfiguration(java.lang.String, java.lang.String);

  public org.apache.hadoop.hbase.replication.ReplicationPeerConfigBuilder putAllConfiguration(java.util.Map<java.lang.String, java.lang.String>);
    Code:
       0: aload_1
       1: aload_0
       2: invokedynamic #1,  0              // InvokeDynamic #0:accept:(Lorg/apache/hadoop/hbase/replication/ReplicationPeerConfigBuilder;)Ljava/util/function/BiConsumer;
       7: invokeinterface #2,  2            // InterfaceMethod java/util/Map.forEach:(Ljava/util/function/BiConsumer;)V
      12: aload_0
      13: areturn

  public abstract org.apache.hadoop.hbase.replication.ReplicationPeerConfigBuilder putPeerData(byte[], byte[]);

  public org.apache.hadoop.hbase.replication.ReplicationPeerConfigBuilder putAllPeerData(java.util.Map<byte[], byte[]>);
    Code:
       0: aload_1
       1: aload_0
       2: invokedynamic #3,  0              // InvokeDynamic #1:accept:(Lorg/apache/hadoop/hbase/replication/ReplicationPeerConfigBuilder;)Ljava/util/function/BiConsumer;
       7: invokeinterface #2,  2            // InterfaceMethod java/util/Map.forEach:(Ljava/util/function/BiConsumer;)V
      12: aload_0
      13: areturn

  public abstract org.apache.hadoop.hbase.replication.ReplicationPeerConfigBuilder setTableCFsMap(java.util.Map<org.apache.hadoop.hbase.TableName, java.util.List<java.lang.String>>);

  public abstract org.apache.hadoop.hbase.replication.ReplicationPeerConfigBuilder setNamespaces(java.util.Set<java.lang.String>);

  public abstract org.apache.hadoop.hbase.replication.ReplicationPeerConfigBuilder setBandwidth(long);

  public abstract org.apache.hadoop.hbase.replication.ReplicationPeerConfigBuilder setReplicateAllUserTables(boolean);

  public abstract org.apache.hadoop.hbase.replication.ReplicationPeerConfigBuilder setExcludeTableCFsMap(java.util.Map<org.apache.hadoop.hbase.TableName, java.util.List<java.lang.String>>);

  public abstract org.apache.hadoop.hbase.replication.ReplicationPeerConfigBuilder setExcludeNamespaces(java.util.Set<java.lang.String>);

  public abstract org.apache.hadoop.hbase.replication.ReplicationPeerConfigBuilder setSerial(boolean);

  public abstract org.apache.hadoop.hbase.replication.ReplicationPeerConfigBuilder setRemoteWALDir(java.lang.String);

  public abstract org.apache.hadoop.hbase.replication.ReplicationPeerConfig build();
}
