Compiled from "ReplicationProtos.java"
public final class org.apache.hadoop.hbase.shaded.protobuf.generated.ReplicationProtos$ReplicationPeerDescription extends org.apache.hbase.thirdparty.com.google.protobuf.GeneratedMessageV3 implements org.apache.hadoop.hbase.shaded.protobuf.generated.ReplicationProtos$ReplicationPeerDescriptionOrBuilder {
  public static final int ID_FIELD_NUMBER;

  public static final int STATE_FIELD_NUMBER;

  public static final int CONFIG_FIELD_NUMBER;

  public static final int SYNCREPLICATIONSTATE_FIELD_NUMBER;

  public static final org.apache.hbase.thirdparty.com.google.protobuf.Parser<org.apache.hadoop.hbase.shaded.protobuf.generated.ReplicationProtos$ReplicationPeerDescription> PARSER;

  public final org.apache.hbase.thirdparty.com.google.protobuf.UnknownFieldSet getUnknownFields();
    Code:
       0: aload_0
       1: getfield      #2                  // Field unknownFields:Lorg/apache/hbase/thirdparty/com/google/protobuf/UnknownFieldSet;
       4: areturn

  public static final org.apache.hbase.thirdparty.com.google.protobuf.Descriptors$Descriptor getDescriptor();
    Code:
       0: invokestatic  #43                 // Method org/apache/hadoop/hbase/shaded/protobuf/generated/ReplicationProtos.access$5600:()Lorg/apache/hbase/thirdparty/com/google/protobuf/Descriptors$Descriptor;
       3: areturn

  protected org.apache.hbase.thirdparty.com.google.protobuf.GeneratedMessageV3$FieldAccessorTable internalGetFieldAccessorTable();
    Code:
       0: invokestatic  #44                 // Method org/apache/hadoop/hbase/shaded/protobuf/generated/ReplicationProtos.access$5700:()Lorg/apache/hbase/thirdparty/com/google/protobuf/GeneratedMessageV3$FieldAccessorTable;
       3: ldc           #45                 // class org/apache/hadoop/hbase/shaded/protobuf/generated/ReplicationProtos$ReplicationPeerDescription
       5: ldc           #46                 // class org/apache/hadoop/hbase/shaded/protobuf/generated/ReplicationProtos$ReplicationPeerDescription$Builder
       7: invokevirtual #47                 // Method org/apache/hbase/thirdparty/com/google/protobuf/GeneratedMessageV3$FieldAccessorTable.ensureFieldAccessorsInitialized:(Ljava/lang/Class;Ljava/lang/Class;)Lorg/apache/hbase/thirdparty/com/google/protobuf/GeneratedMessageV3$FieldAccessorTable;
      10: areturn

  public boolean hasId();
    Code:
       0: aload_0
       1: getfield      #3                  // Field bitField0_:I
       4: iconst_1
       5: iand
       6: iconst_1
       7: if_icmpne     14
      10: iconst_1
      11: goto          15
      14: iconst_0
      15: ireturn

  public java.lang.String getId();
    Code:
       0: aload_0
       1: getfield      #7                  // Field id_:Ljava/lang/Object;
       4: astore_1
       5: aload_1
       6: instanceof    #48                 // class java/lang/String
       9: ifeq          17
      12: aload_1
      13: checkcast     #48                 // class java/lang/String
      16: areturn
      17: aload_1
      18: checkcast     #49                 // class org/apache/hbase/thirdparty/com/google/protobuf/ByteString
      21: astore_2
      22: aload_2
      23: invokevirtual #50                 // Method org/apache/hbase/thirdparty/com/google/protobuf/ByteString.toStringUtf8:()Ljava/lang/String;
      26: astore_3
      27: aload_2
      28: invokevirtual #51                 // Method org/apache/hbase/thirdparty/com/google/protobuf/ByteString.isValidUtf8:()Z
      31: ifeq          39
      34: aload_0
      35: aload_3
      36: putfield      #7                  // Field id_:Ljava/lang/Object;
      39: aload_3
      40: areturn

  public org.apache.hbase.thirdparty.com.google.protobuf.ByteString getIdBytes();
    Code:
       0: aload_0
       1: getfield      #7                  // Field id_:Ljava/lang/Object;
       4: astore_1
       5: aload_1
       6: instanceof    #48                 // class java/lang/String
       9: ifeq          27
      12: aload_1
      13: checkcast     #48                 // class java/lang/String
      16: invokestatic  #52                 // Method org/apache/hbase/thirdparty/com/google/protobuf/ByteString.copyFromUtf8:(Ljava/lang/String;)Lorg/apache/hbase/thirdparty/com/google/protobuf/ByteString;
      19: astore_2
      20: aload_0
      21: aload_2
      22: putfield      #7                  // Field id_:Ljava/lang/Object;
      25: aload_2
      26: areturn
      27: aload_1
      28: checkcast     #49                 // class org/apache/hbase/thirdparty/com/google/protobuf/ByteString
      31: areturn

  public boolean hasState();
    Code:
       0: aload_0
       1: getfield      #3                  // Field bitField0_:I
       4: iconst_2
       5: iand
       6: iconst_2
       7: if_icmpne     14
      10: iconst_1
      11: goto          15
      14: iconst_0
      15: ireturn

  public org.apache.hadoop.hbase.shaded.protobuf.generated.ReplicationProtos$ReplicationState getState();
    Code:
       0: aload_0
       1: getfield      #6                  // Field state_:Lorg/apache/hadoop/hbase/shaded/protobuf/generated/ReplicationProtos$ReplicationState;
       4: ifnonnull     13
       7: invokestatic  #53                 // Method org/apache/hadoop/hbase/shaded/protobuf/generated/ReplicationProtos$ReplicationState.getDefaultInstance:()Lorg/apache/hadoop/hbase/shaded/protobuf/generated/ReplicationProtos$ReplicationState;
      10: goto          17
      13: aload_0
      14: getfield      #6                  // Field state_:Lorg/apache/hadoop/hbase/shaded/protobuf/generated/ReplicationProtos$ReplicationState;
      17: areturn

  public org.apache.hadoop.hbase.shaded.protobuf.generated.ReplicationProtos$ReplicationStateOrBuilder getStateOrBuilder();
    Code:
       0: aload_0
       1: getfield      #6                  // Field state_:Lorg/apache/hadoop/hbase/shaded/protobuf/generated/ReplicationProtos$ReplicationState;
       4: ifnonnull     13
       7: invokestatic  #53                 // Method org/apache/hadoop/hbase/shaded/protobuf/generated/ReplicationProtos$ReplicationState.getDefaultInstance:()Lorg/apache/hadoop/hbase/shaded/protobuf/generated/ReplicationProtos$ReplicationState;
      10: goto          17
      13: aload_0
      14: getfield      #6                  // Field state_:Lorg/apache/hadoop/hbase/shaded/protobuf/generated/ReplicationProtos$ReplicationState;
      17: areturn

  public boolean hasConfig();
    Code:
       0: aload_0
       1: getfield      #3                  // Field bitField0_:I
       4: iconst_4
       5: iand
       6: iconst_4
       7: if_icmpne     14
      10: iconst_1
      11: goto          15
      14: iconst_0
      15: ireturn

  public org.apache.hadoop.hbase.shaded.protobuf.generated.ReplicationProtos$ReplicationPeer getConfig();
    Code:
       0: aload_0
       1: getfield      #5                  // Field config_:Lorg/apache/hadoop/hbase/shaded/protobuf/generated/ReplicationProtos$ReplicationPeer;
       4: ifnonnull     13
       7: invokestatic  #54                 // Method org/apache/hadoop/hbase/shaded/protobuf/generated/ReplicationProtos$ReplicationPeer.getDefaultInstance:()Lorg/apache/hadoop/hbase/shaded/protobuf/generated/ReplicationProtos$ReplicationPeer;
      10: goto          17
      13: aload_0
      14: getfield      #5                  // Field config_:Lorg/apache/hadoop/hbase/shaded/protobuf/generated/ReplicationProtos$ReplicationPeer;
      17: areturn

  public org.apache.hadoop.hbase.shaded.protobuf.generated.ReplicationProtos$ReplicationPeerOrBuilder getConfigOrBuilder();
    Code:
       0: aload_0
       1: getfield      #5                  // Field config_:Lorg/apache/hadoop/hbase/shaded/protobuf/generated/ReplicationProtos$ReplicationPeer;
       4: ifnonnull     13
       7: invokestatic  #54                 // Method org/apache/hadoop/hbase/shaded/protobuf/generated/ReplicationProtos$ReplicationPeer.getDefaultInstance:()Lorg/apache/hadoop/hbase/shaded/protobuf/generated/ReplicationProtos$ReplicationPeer;
      10: goto          17
      13: aload_0
      14: getfield      #5                  // Field config_:Lorg/apache/hadoop/hbase/shaded/protobuf/generated/ReplicationProtos$ReplicationPeer;
      17: areturn

  public boolean hasSyncReplicationState();
    Code:
       0: aload_0
       1: getfield      #3                  // Field bitField0_:I
       4: bipush        8
       6: iand
       7: bipush        8
       9: if_icmpne     16
      12: iconst_1
      13: goto          17
      16: iconst_0
      17: ireturn

  public org.apache.hadoop.hbase.shaded.protobuf.generated.ReplicationProtos$SyncReplicationState getSyncReplicationState();
    Code:
       0: aload_0
       1: getfield      #4                  // Field syncReplicationState_:Lorg/apache/hadoop/hbase/shaded/protobuf/generated/ReplicationProtos$SyncReplicationState;
       4: ifnonnull     13
       7: invokestatic  #55                 // Method org/apache/hadoop/hbase/shaded/protobuf/generated/ReplicationProtos$SyncReplicationState.getDefaultInstance:()Lorg/apache/hadoop/hbase/shaded/protobuf/generated/ReplicationProtos$SyncReplicationState;
      10: goto          17
      13: aload_0
      14: getfield      #4                  // Field syncReplicationState_:Lorg/apache/hadoop/hbase/shaded/protobuf/generated/ReplicationProtos$SyncReplicationState;
      17: areturn

  public org.apache.hadoop.hbase.shaded.protobuf.generated.ReplicationProtos$SyncReplicationStateOrBuilder getSyncReplicationStateOrBuilder();
    Code:
       0: aload_0
       1: getfield      #4                  // Field syncReplicationState_:Lorg/apache/hadoop/hbase/shaded/protobuf/generated/ReplicationProtos$SyncReplicationState;
       4: ifnonnull     13
       7: invokestatic  #55                 // Method org/apache/hadoop/hbase/shaded/protobuf/generated/ReplicationProtos$SyncReplicationState.getDefaultInstance:()Lorg/apache/hadoop/hbase/shaded/protobuf/generated/ReplicationProtos$SyncReplicationState;
      10: goto          17
      13: aload_0
      14: getfield      #4                  // Field syncReplicationState_:Lorg/apache/hadoop/hbase/shaded/protobuf/generated/ReplicationProtos$SyncReplicationState;
      17: areturn

  public final boolean isInitialized();
    Code:
       0: aload_0
       1: getfield      #11                 // Field memoizedIsInitialized:B
       4: istore_1
       5: iload_1
       6: iconst_1
       7: if_icmpne     12
      10: iconst_1
      11: ireturn
      12: iload_1
      13: ifne          18
      16: iconst_0
      17: ireturn
      18: aload_0
      19: invokevirtual #56                 // Method hasId:()Z
      22: ifne          32
      25: aload_0
      26: iconst_0
      27: putfield      #11                 // Field memoizedIsInitialized:B
      30: iconst_0
      31: ireturn
      32: aload_0
      33: invokevirtual #57                 // Method hasState:()Z
      36: ifne          46
      39: aload_0
      40: iconst_0
      41: putfield      #11                 // Field memoizedIsInitialized:B
      44: iconst_0
      45: ireturn
      46: aload_0
      47: invokevirtual #58                 // Method hasConfig:()Z
      50: ifne          60
      53: aload_0
      54: iconst_0
      55: putfield      #11                 // Field memoizedIsInitialized:B
      58: iconst_0
      59: ireturn
      60: aload_0
      61: invokevirtual #59                 // Method getState:()Lorg/apache/hadoop/hbase/shaded/protobuf/generated/ReplicationProtos$ReplicationState;
      64: invokevirtual #60                 // Method org/apache/hadoop/hbase/shaded/protobuf/generated/ReplicationProtos$ReplicationState.isInitialized:()Z
      67: ifne          77
      70: aload_0
      71: iconst_0
      72: putfield      #11                 // Field memoizedIsInitialized:B
      75: iconst_0
      76: ireturn
      77: aload_0
      78: invokevirtual #61                 // Method getConfig:()Lorg/apache/hadoop/hbase/shaded/protobuf/generated/ReplicationProtos$ReplicationPeer;
      81: invokevirtual #62                 // Method org/apache/hadoop/hbase/shaded/protobuf/generated/ReplicationProtos$ReplicationPeer.isInitialized:()Z
      84: ifne          94
      87: aload_0
      88: iconst_0
      89: putfield      #11                 // Field memoizedIsInitialized:B
      92: iconst_0
      93: ireturn
      94: aload_0
      95: invokevirtual #63                 // Method hasSyncReplicationState:()Z
      98: ifeq          118
     101: aload_0
     102: invokevirtual #64                 // Method getSyncReplicationState:()Lorg/apache/hadoop/hbase/shaded/protobuf/generated/ReplicationProtos$SyncReplicationState;
     105: invokevirtual #65                 // Method org/apache/hadoop/hbase/shaded/protobuf/generated/ReplicationProtos$SyncReplicationState.isInitialized:()Z
     108: ifne          118
     111: aload_0
     112: iconst_0
     113: putfield      #11                 // Field memoizedIsInitialized:B
     116: iconst_0
     117: ireturn
     118: aload_0
     119: iconst_1
     120: putfield      #11                 // Field memoizedIsInitialized:B
     123: iconst_1
     124: ireturn

  public void writeTo(org.apache.hbase.thirdparty.com.google.protobuf.CodedOutputStream) throws java.io.IOException;
    Code:
       0: aload_0
       1: getfield      #3                  // Field bitField0_:I
       4: iconst_1
       5: iand
       6: iconst_1
       7: if_icmpne     19
      10: aload_1
      11: iconst_1
      12: aload_0
      13: getfield      #7                  // Field id_:Ljava/lang/Object;
      16: invokestatic  #66                 // Method org/apache/hbase/thirdparty/com/google/protobuf/GeneratedMessageV3.writeString:(Lorg/apache/hbase/thirdparty/com/google/protobuf/CodedOutputStream;ILjava/lang/Object;)V
      19: aload_0
      20: getfield      #3                  // Field bitField0_:I
      23: iconst_2
      24: iand
      25: iconst_2
      26: if_icmpne     38
      29: aload_1
      30: iconst_2
      31: aload_0
      32: invokevirtual #59                 // Method getState:()Lorg/apache/hadoop/hbase/shaded/protobuf/generated/ReplicationProtos$ReplicationState;
      35: invokevirtual #67                 // Method org/apache/hbase/thirdparty/com/google/protobuf/CodedOutputStream.writeMessage:(ILorg/apache/hbase/thirdparty/com/google/protobuf/MessageLite;)V
      38: aload_0
      39: getfield      #3                  // Field bitField0_:I
      42: iconst_4
      43: iand
      44: iconst_4
      45: if_icmpne     57
      48: aload_1
      49: iconst_3
      50: aload_0
      51: invokevirtual #61                 // Method getConfig:()Lorg/apache/hadoop/hbase/shaded/protobuf/generated/ReplicationProtos$ReplicationPeer;
      54: invokevirtual #67                 // Method org/apache/hbase/thirdparty/com/google/protobuf/CodedOutputStream.writeMessage:(ILorg/apache/hbase/thirdparty/com/google/protobuf/MessageLite;)V
      57: aload_0
      58: getfield      #3                  // Field bitField0_:I
      61: bipush        8
      63: iand
      64: bipush        8
      66: if_icmpne     78
      69: aload_1
      70: iconst_4
      71: aload_0
      72: invokevirtual #64                 // Method getSyncReplicationState:()Lorg/apache/hadoop/hbase/shaded/protobuf/generated/ReplicationProtos$SyncReplicationState;
      75: invokevirtual #67                 // Method org/apache/hbase/thirdparty/com/google/protobuf/CodedOutputStream.writeMessage:(ILorg/apache/hbase/thirdparty/com/google/protobuf/MessageLite;)V
      78: aload_0
      79: getfield      #2                  // Field unknownFields:Lorg/apache/hbase/thirdparty/com/google/protobuf/UnknownFieldSet;
      82: aload_1
      83: invokevirtual #68                 // Method org/apache/hbase/thirdparty/com/google/protobuf/UnknownFieldSet.writeTo:(Lorg/apache/hbase/thirdparty/com/google/protobuf/CodedOutputStream;)V
      86: return

  public int getSerializedSize();
    Code:
       0: aload_0
       1: getfield      #69                 // Field memoizedSize:I
       4: istore_1
       5: iload_1
       6: iconst_m1
       7: if_icmpeq     12
      10: iload_1
      11: ireturn
      12: iconst_0
      13: istore_1
      14: aload_0
      15: getfield      #3                  // Field bitField0_:I
      18: iconst_1
      19: iand
      20: iconst_1
      21: if_icmpne     35
      24: iload_1
      25: iconst_1
      26: aload_0
      27: getfield      #7                  // Field id_:Ljava/lang/Object;
      30: invokestatic  #70                 // Method org/apache/hbase/thirdparty/com/google/protobuf/GeneratedMessageV3.computeStringSize:(ILjava/lang/Object;)I
      33: iadd
      34: istore_1
      35: aload_0
      36: getfield      #3                  // Field bitField0_:I
      39: iconst_2
      40: iand
      41: iconst_2
      42: if_icmpne     56
      45: iload_1
      46: iconst_2
      47: aload_0
      48: invokevirtual #59                 // Method getState:()Lorg/apache/hadoop/hbase/shaded/protobuf/generated/ReplicationProtos$ReplicationState;
      51: invokestatic  #71                 // Method org/apache/hbase/thirdparty/com/google/protobuf/CodedOutputStream.computeMessageSize:(ILorg/apache/hbase/thirdparty/com/google/protobuf/MessageLite;)I
      54: iadd
      55: istore_1
      56: aload_0
      57: getfield      #3                  // Field bitField0_:I
      60: iconst_4
      61: iand
      62: iconst_4
      63: if_icmpne     77
      66: iload_1
      67: iconst_3
      68: aload_0
      69: invokevirtual #61                 // Method getConfig:()Lorg/apache/hadoop/hbase/shaded/protobuf/generated/ReplicationProtos$ReplicationPeer;
      72: invokestatic  #71                 // Method org/apache/hbase/thirdparty/com/google/protobuf/CodedOutputStream.computeMessageSize:(ILorg/apache/hbase/thirdparty/com/google/protobuf/MessageLite;)I
      75: iadd
      76: istore_1
      77: aload_0
      78: getfield      #3                  // Field bitField0_:I
      81: bipush        8
      83: iand
      84: bipush        8
      86: if_icmpne     100
      89: iload_1
      90: iconst_4
      91: aload_0
      92: invokevirtual #64                 // Method getSyncReplicationState:()Lorg/apache/hadoop/hbase/shaded/protobuf/generated/ReplicationProtos$SyncReplicationState;
      95: invokestatic  #71                 // Method org/apache/hbase/thirdparty/com/google/protobuf/CodedOutputStream.computeMessageSize:(ILorg/apache/hbase/thirdparty/com/google/protobuf/MessageLite;)I
      98: iadd
      99: istore_1
     100: iload_1
     101: aload_0
     102: getfield      #2                  // Field unknownFields:Lorg/apache/hbase/thirdparty/com/google/protobuf/UnknownFieldSet;
     105: invokevirtual #72                 // Method org/apache/hbase/thirdparty/com/google/protobuf/UnknownFieldSet.getSerializedSize:()I
     108: iadd
     109: istore_1
     110: aload_0
     111: iload_1
     112: putfield      #69                 // Field memoizedSize:I
     115: iload_1
     116: ireturn

  public boolean equals(java.lang.Object);
    Code:
       0: aload_1
       1: aload_0
       2: if_acmpne     7
       5: iconst_1
       6: ireturn
       7: aload_1
       8: instanceof    #45                 // class org/apache/hadoop/hbase/shaded/protobuf/generated/ReplicationProtos$ReplicationPeerDescription
      11: ifne          20
      14: aload_0
      15: aload_1
      16: invokespecial #73                 // Method org/apache/hbase/thirdparty/com/google/protobuf/GeneratedMessageV3.equals:(Ljava/lang/Object;)Z
      19: ireturn
      20: aload_1
      21: checkcast     #45                 // class org/apache/hadoop/hbase/shaded/protobuf/generated/ReplicationProtos$ReplicationPeerDescription
      24: astore_2
      25: iconst_1
      26: istore_3
      27: iload_3
      28: ifeq          46
      31: aload_0
      32: invokevirtual #56                 // Method hasId:()Z
      35: aload_2
      36: invokevirtual #56                 // Method hasId:()Z
      39: if_icmpne     46
      42: iconst_1
      43: goto          47
      46: iconst_0
      47: istore_3
      48: aload_0
      49: invokevirtual #56                 // Method hasId:()Z
      52: ifeq          79
      55: iload_3
      56: ifeq          77
      59: aload_0
      60: invokevirtual #74                 // Method getId:()Ljava/lang/String;
      63: aload_2
      64: invokevirtual #74                 // Method getId:()Ljava/lang/String;
      67: invokevirtual #75                 // Method java/lang/String.equals:(Ljava/lang/Object;)Z
      70: ifeq          77
      73: iconst_1
      74: goto          78
      77: iconst_0
      78: istore_3
      79: iload_3
      80: ifeq          98
      83: aload_0
      84: invokevirtual #57                 // Method hasState:()Z
      87: aload_2
      88: invokevirtual #57                 // Method hasState:()Z
      91: if_icmpne     98
      94: iconst_1
      95: goto          99
      98: iconst_0
      99: istore_3
     100: aload_0
     101: invokevirtual #57                 // Method hasState:()Z
     104: ifeq          131
     107: iload_3
     108: ifeq          129
     111: aload_0
     112: invokevirtual #59                 // Method getState:()Lorg/apache/hadoop/hbase/shaded/protobuf/generated/ReplicationProtos$ReplicationState;
     115: aload_2
     116: invokevirtual #59                 // Method getState:()Lorg/apache/hadoop/hbase/shaded/protobuf/generated/ReplicationProtos$ReplicationState;
     119: invokevirtual #76                 // Method org/apache/hadoop/hbase/shaded/protobuf/generated/ReplicationProtos$ReplicationState.equals:(Ljava/lang/Object;)Z
     122: ifeq          129
     125: iconst_1
     126: goto          130
     129: iconst_0
     130: istore_3
     131: iload_3
     132: ifeq          150
     135: aload_0
     136: invokevirtual #58                 // Method hasConfig:()Z
     139: aload_2
     140: invokevirtual #58                 // Method hasConfig:()Z
     143: if_icmpne     150
     146: iconst_1
     147: goto          151
     150: iconst_0
     151: istore_3
     152: aload_0
     153: invokevirtual #58                 // Method hasConfig:()Z
     156: ifeq          183
     159: iload_3
     160: ifeq          181
     163: aload_0
     164: invokevirtual #61                 // Method getConfig:()Lorg/apache/hadoop/hbase/shaded/protobuf/generated/ReplicationProtos$ReplicationPeer;
     167: aload_2
     168: invokevirtual #61                 // Method getConfig:()Lorg/apache/hadoop/hbase/shaded/protobuf/generated/ReplicationProtos$ReplicationPeer;
     171: invokevirtual #77                 // Method org/apache/hadoop/hbase/shaded/protobuf/generated/ReplicationProtos$ReplicationPeer.equals:(Ljava/lang/Object;)Z
     174: ifeq          181
     177: iconst_1
     178: goto          182
     181: iconst_0
     182: istore_3
     183: iload_3
     184: ifeq          202
     187: aload_0
     188: invokevirtual #63                 // Method hasSyncReplicationState:()Z
     191: aload_2
     192: invokevirtual #63                 // Method hasSyncReplicationState:()Z
     195: if_icmpne     202
     198: iconst_1
     199: goto          203
     202: iconst_0
     203: istore_3
     204: aload_0
     205: invokevirtual #63                 // Method hasSyncReplicationState:()Z
     208: ifeq          235
     211: iload_3
     212: ifeq          233
     215: aload_0
     216: invokevirtual #64                 // Method getSyncReplicationState:()Lorg/apache/hadoop/hbase/shaded/protobuf/generated/ReplicationProtos$SyncReplicationState;
     219: aload_2
     220: invokevirtual #64                 // Method getSyncReplicationState:()Lorg/apache/hadoop/hbase/shaded/protobuf/generated/ReplicationProtos$SyncReplicationState;
     223: invokevirtual #78                 // Method org/apache/hadoop/hbase/shaded/protobuf/generated/ReplicationProtos$SyncReplicationState.equals:(Ljava/lang/Object;)Z
     226: ifeq          233
     229: iconst_1
     230: goto          234
     233: iconst_0
     234: istore_3
     235: iload_3
     236: ifeq          257
     239: aload_0
     240: getfield      #2                  // Field unknownFields:Lorg/apache/hbase/thirdparty/com/google/protobuf/UnknownFieldSet;
     243: aload_2
     244: getfield      #2                  // Field unknownFields:Lorg/apache/hbase/thirdparty/com/google/protobuf/UnknownFieldSet;
     247: invokevirtual #79                 // Method org/apache/hbase/thirdparty/com/google/protobuf/UnknownFieldSet.equals:(Ljava/lang/Object;)Z
     250: ifeq          257
     253: iconst_1
     254: goto          258
     257: iconst_0
     258: istore_3
     259: iload_3
     260: ireturn

  public int hashCode();
    Code:
       0: aload_0
       1: getfield      #80                 // Field memoizedHashCode:I
       4: ifeq          12
       7: aload_0
       8: getfield      #80                 // Field memoizedHashCode:I
      11: ireturn
      12: bipush        41
      14: istore_1
      15: bipush        19
      17: iload_1
      18: imul
      19: invokestatic  #81                 // Method getDescriptor:()Lorg/apache/hbase/thirdparty/com/google/protobuf/Descriptors$Descriptor;
      22: invokevirtual #82                 // Method java/lang/Object.hashCode:()I
      25: iadd
      26: istore_1
      27: aload_0
      28: invokevirtual #56                 // Method hasId:()Z
      31: ifeq          54
      34: bipush        37
      36: iload_1
      37: imul
      38: iconst_1
      39: iadd
      40: istore_1
      41: bipush        53
      43: iload_1
      44: imul
      45: aload_0
      46: invokevirtual #74                 // Method getId:()Ljava/lang/String;
      49: invokevirtual #83                 // Method java/lang/String.hashCode:()I
      52: iadd
      53: istore_1
      54: aload_0
      55: invokevirtual #57                 // Method hasState:()Z
      58: ifeq          81
      61: bipush        37
      63: iload_1
      64: imul
      65: iconst_2
      66: iadd
      67: istore_1
      68: bipush        53
      70: iload_1
      71: imul
      72: aload_0
      73: invokevirtual #59                 // Method getState:()Lorg/apache/hadoop/hbase/shaded/protobuf/generated/ReplicationProtos$ReplicationState;
      76: invokevirtual #84                 // Method org/apache/hadoop/hbase/shaded/protobuf/generated/ReplicationProtos$ReplicationState.hashCode:()I
      79: iadd
      80: istore_1
      81: aload_0
      82: invokevirtual #58                 // Method hasConfig:()Z
      85: ifeq          108
      88: bipush        37
      90: iload_1
      91: imul
      92: iconst_3
      93: iadd
      94: istore_1
      95: bipush        53
      97: iload_1
      98: imul
      99: aload_0
     100: invokevirtual #61                 // Method getConfig:()Lorg/apache/hadoop/hbase/shaded/protobuf/generated/ReplicationProtos$ReplicationPeer;
     103: invokevirtual #85                 // Method org/apache/hadoop/hbase/shaded/protobuf/generated/ReplicationProtos$ReplicationPeer.hashCode:()I
     106: iadd
     107: istore_1
     108: aload_0
     109: invokevirtual #63                 // Method hasSyncReplicationState:()Z
     112: ifeq          135
     115: bipush        37
     117: iload_1
     118: imul
     119: iconst_4
     120: iadd
     121: istore_1
     122: bipush        53
     124: iload_1
     125: imul
     126: aload_0
     127: invokevirtual #64                 // Method getSyncReplicationState:()Lorg/apache/hadoop/hbase/shaded/protobuf/generated/ReplicationProtos$SyncReplicationState;
     130: invokevirtual #86                 // Method org/apache/hadoop/hbase/shaded/protobuf/generated/ReplicationProtos$SyncReplicationState.hashCode:()I
     133: iadd
     134: istore_1
     135: bipush        29
     137: iload_1
     138: imul
     139: aload_0
     140: getfield      #2                  // Field unknownFields:Lorg/apache/hbase/thirdparty/com/google/protobuf/UnknownFieldSet;
     143: invokevirtual #87                 // Method org/apache/hbase/thirdparty/com/google/protobuf/UnknownFieldSet.hashCode:()I
     146: iadd
     147: istore_1
     148: aload_0
     149: iload_1
     150: putfield      #80                 // Field memoizedHashCode:I
     153: iload_1
     154: ireturn

  public static org.apache.hadoop.hbase.shaded.protobuf.generated.ReplicationProtos$ReplicationPeerDescription parseFrom(java.nio.ByteBuffer) throws org.apache.hbase.thirdparty.com.google.protobuf.InvalidProtocolBufferException;
    Code:
       0: getstatic     #88                 // Field PARSER:Lorg/apache/hbase/thirdparty/com/google/protobuf/Parser;
       3: aload_0
       4: invokeinterface #89,  2           // InterfaceMethod org/apache/hbase/thirdparty/com/google/protobuf/Parser.parseFrom:(Ljava/nio/ByteBuffer;)Ljava/lang/Object;
       9: checkcast     #45                 // class org/apache/hadoop/hbase/shaded/protobuf/generated/ReplicationProtos$ReplicationPeerDescription
      12: areturn

  public static org.apache.hadoop.hbase.shaded.protobuf.generated.ReplicationProtos$ReplicationPeerDescription parseFrom(java.nio.ByteBuffer, org.apache.hbase.thirdparty.com.google.protobuf.ExtensionRegistryLite) throws org.apache.hbase.thirdparty.com.google.protobuf.InvalidProtocolBufferException;
    Code:
       0: getstatic     #88                 // Field PARSER:Lorg/apache/hbase/thirdparty/com/google/protobuf/Parser;
       3: aload_0
       4: aload_1
       5: invokeinterface #90,  3           // InterfaceMethod org/apache/hbase/thirdparty/com/google/protobuf/Parser.parseFrom:(Ljava/nio/ByteBuffer;Lorg/apache/hbase/thirdparty/com/google/protobuf/ExtensionRegistryLite;)Ljava/lang/Object;
      10: checkcast     #45                 // class org/apache/hadoop/hbase/shaded/protobuf/generated/ReplicationProtos$ReplicationPeerDescription
      13: areturn

  public static org.apache.hadoop.hbase.shaded.protobuf.generated.ReplicationProtos$ReplicationPeerDescription parseFrom(org.apache.hbase.thirdparty.com.google.protobuf.ByteString) throws org.apache.hbase.thirdparty.com.google.protobuf.InvalidProtocolBufferException;
    Code:
       0: getstatic     #88                 // Field PARSER:Lorg/apache/hbase/thirdparty/com/google/protobuf/Parser;
       3: aload_0
       4: invokeinterface #91,  2           // InterfaceMethod org/apache/hbase/thirdparty/com/google/protobuf/Parser.parseFrom:(Lorg/apache/hbase/thirdparty/com/google/protobuf/ByteString;)Ljava/lang/Object;
       9: checkcast     #45                 // class org/apache/hadoop/hbase/shaded/protobuf/generated/ReplicationProtos$ReplicationPeerDescription
      12: areturn

  public static org.apache.hadoop.hbase.shaded.protobuf.generated.ReplicationProtos$ReplicationPeerDescription parseFrom(org.apache.hbase.thirdparty.com.google.protobuf.ByteString, org.apache.hbase.thirdparty.com.google.protobuf.ExtensionRegistryLite) throws org.apache.hbase.thirdparty.com.google.protobuf.InvalidProtocolBufferException;
    Code:
       0: getstatic     #88                 // Field PARSER:Lorg/apache/hbase/thirdparty/com/google/protobuf/Parser;
       3: aload_0
       4: aload_1
       5: invokeinterface #92,  3           // InterfaceMethod org/apache/hbase/thirdparty/com/google/protobuf/Parser.parseFrom:(Lorg/apache/hbase/thirdparty/com/google/protobuf/ByteString;Lorg/apache/hbase/thirdparty/com/google/protobuf/ExtensionRegistryLite;)Ljava/lang/Object;
      10: checkcast     #45                 // class org/apache/hadoop/hbase/shaded/protobuf/generated/ReplicationProtos$ReplicationPeerDescription
      13: areturn

  public static org.apache.hadoop.hbase.shaded.protobuf.generated.ReplicationProtos$ReplicationPeerDescription parseFrom(byte[]) throws org.apache.hbase.thirdparty.com.google.protobuf.InvalidProtocolBufferException;
    Code:
       0: getstatic     #88                 // Field PARSER:Lorg/apache/hbase/thirdparty/com/google/protobuf/Parser;
       3: aload_0
       4: invokeinterface #93,  2           // InterfaceMethod org/apache/hbase/thirdparty/com/google/protobuf/Parser.parseFrom:([B)Ljava/lang/Object;
       9: checkcast     #45                 // class org/apache/hadoop/hbase/shaded/protobuf/generated/ReplicationProtos$ReplicationPeerDescription
      12: areturn

  public static org.apache.hadoop.hbase.shaded.protobuf.generated.ReplicationProtos$ReplicationPeerDescription parseFrom(byte[], org.apache.hbase.thirdparty.com.google.protobuf.ExtensionRegistryLite) throws org.apache.hbase.thirdparty.com.google.protobuf.InvalidProtocolBufferException;
    Code:
       0: getstatic     #88                 // Field PARSER:Lorg/apache/hbase/thirdparty/com/google/protobuf/Parser;
       3: aload_0
       4: aload_1
       5: invokeinterface #94,  3           // InterfaceMethod org/apache/hbase/thirdparty/com/google/protobuf/Parser.parseFrom:([BLorg/apache/hbase/thirdparty/com/google/protobuf/ExtensionRegistryLite;)Ljava/lang/Object;
      10: checkcast     #45                 // class org/apache/hadoop/hbase/shaded/protobuf/generated/ReplicationProtos$ReplicationPeerDescription
      13: areturn

  public static org.apache.hadoop.hbase.shaded.protobuf.generated.ReplicationProtos$ReplicationPeerDescription parseFrom(java.io.InputStream) throws java.io.IOException;
    Code:
       0: getstatic     #88                 // Field PARSER:Lorg/apache/hbase/thirdparty/com/google/protobuf/Parser;
       3: aload_0
       4: invokestatic  #95                 // Method org/apache/hbase/thirdparty/com/google/protobuf/GeneratedMessageV3.parseWithIOException:(Lorg/apache/hbase/thirdparty/com/google/protobuf/Parser;Ljava/io/InputStream;)Lorg/apache/hbase/thirdparty/com/google/protobuf/Message;
       7: checkcast     #45                 // class org/apache/hadoop/hbase/shaded/protobuf/generated/ReplicationProtos$ReplicationPeerDescription
      10: areturn

  public static org.apache.hadoop.hbase.shaded.protobuf.generated.ReplicationProtos$ReplicationPeerDescription parseFrom(java.io.InputStream, org.apache.hbase.thirdparty.com.google.protobuf.ExtensionRegistryLite) throws java.io.IOException;
    Code:
       0: getstatic     #88                 // Field PARSER:Lorg/apache/hbase/thirdparty/com/google/protobuf/Parser;
       3: aload_0
       4: aload_1
       5: invokestatic  #96                 // Method org/apache/hbase/thirdparty/com/google/protobuf/GeneratedMessageV3.parseWithIOException:(Lorg/apache/hbase/thirdparty/com/google/protobuf/Parser;Ljava/io/InputStream;Lorg/apache/hbase/thirdparty/com/google/protobuf/ExtensionRegistryLite;)Lorg/apache/hbase/thirdparty/com/google/protobuf/Message;
       8: checkcast     #45                 // class org/apache/hadoop/hbase/shaded/protobuf/generated/ReplicationProtos$ReplicationPeerDescription
      11: areturn

  public static org.apache.hadoop.hbase.shaded.protobuf.generated.ReplicationProtos$ReplicationPeerDescription parseDelimitedFrom(java.io.InputStream) throws java.io.IOException;
    Code:
       0: getstatic     #88                 // Field PARSER:Lorg/apache/hbase/thirdparty/com/google/protobuf/Parser;
       3: aload_0
       4: invokestatic  #97                 // Method org/apache/hbase/thirdparty/com/google/protobuf/GeneratedMessageV3.parseDelimitedWithIOException:(Lorg/apache/hbase/thirdparty/com/google/protobuf/Parser;Ljava/io/InputStream;)Lorg/apache/hbase/thirdparty/com/google/protobuf/Message;
       7: checkcast     #45                 // class org/apache/hadoop/hbase/shaded/protobuf/generated/ReplicationProtos$ReplicationPeerDescription
      10: areturn

  public static org.apache.hadoop.hbase.shaded.protobuf.generated.ReplicationProtos$ReplicationPeerDescription parseDelimitedFrom(java.io.InputStream, org.apache.hbase.thirdparty.com.google.protobuf.ExtensionRegistryLite) throws java.io.IOException;
    Code:
       0: getstatic     #88                 // Field PARSER:Lorg/apache/hbase/thirdparty/com/google/protobuf/Parser;
       3: aload_0
       4: aload_1
       5: invokestatic  #98                 // Method org/apache/hbase/thirdparty/com/google/protobuf/GeneratedMessageV3.parseDelimitedWithIOException:(Lorg/apache/hbase/thirdparty/com/google/protobuf/Parser;Ljava/io/InputStream;Lorg/apache/hbase/thirdparty/com/google/protobuf/ExtensionRegistryLite;)Lorg/apache/hbase/thirdparty/com/google/protobuf/Message;
       8: checkcast     #45                 // class org/apache/hadoop/hbase/shaded/protobuf/generated/ReplicationProtos$ReplicationPeerDescription
      11: areturn

  public static org.apache.hadoop.hbase.shaded.protobuf.generated.ReplicationProtos$ReplicationPeerDescription parseFrom(org.apache.hbase.thirdparty.com.google.protobuf.CodedInputStream) throws java.io.IOException;
    Code:
       0: getstatic     #88                 // Field PARSER:Lorg/apache/hbase/thirdparty/com/google/protobuf/Parser;
       3: aload_0
       4: invokestatic  #99                 // Method org/apache/hbase/thirdparty/com/google/protobuf/GeneratedMessageV3.parseWithIOException:(Lorg/apache/hbase/thirdparty/com/google/protobuf/Parser;Lorg/apache/hbase/thirdparty/com/google/protobuf/CodedInputStream;)Lorg/apache/hbase/thirdparty/com/google/protobuf/Message;
       7: checkcast     #45                 // class org/apache/hadoop/hbase/shaded/protobuf/generated/ReplicationProtos$ReplicationPeerDescription
      10: areturn

  public static org.apache.hadoop.hbase.shaded.protobuf.generated.ReplicationProtos$ReplicationPeerDescription parseFrom(org.apache.hbase.thirdparty.com.google.protobuf.CodedInputStream, org.apache.hbase.thirdparty.com.google.protobuf.ExtensionRegistryLite) throws java.io.IOException;
    Code:
       0: getstatic     #88                 // Field PARSER:Lorg/apache/hbase/thirdparty/com/google/protobuf/Parser;
       3: aload_0
       4: aload_1
       5: invokestatic  #100                // Method org/apache/hbase/thirdparty/com/google/protobuf/GeneratedMessageV3.parseWithIOException:(Lorg/apache/hbase/thirdparty/com/google/protobuf/Parser;Lorg/apache/hbase/thirdparty/com/google/protobuf/CodedInputStream;Lorg/apache/hbase/thirdparty/com/google/protobuf/ExtensionRegistryLite;)Lorg/apache/hbase/thirdparty/com/google/protobuf/Message;
       8: checkcast     #45                 // class org/apache/hadoop/hbase/shaded/protobuf/generated/ReplicationProtos$ReplicationPeerDescription
      11: areturn

  public org.apache.hadoop.hbase.shaded.protobuf.generated.ReplicationProtos$ReplicationPeerDescription$Builder newBuilderForType();
    Code:
       0: invokestatic  #101                // Method newBuilder:()Lorg/apache/hadoop/hbase/shaded/protobuf/generated/ReplicationProtos$ReplicationPeerDescription$Builder;
       3: areturn

  public static org.apache.hadoop.hbase.shaded.protobuf.generated.ReplicationProtos$ReplicationPeerDescription$Builder newBuilder();
    Code:
       0: getstatic     #102                // Field DEFAULT_INSTANCE:Lorg/apache/hadoop/hbase/shaded/protobuf/generated/ReplicationProtos$ReplicationPeerDescription;
       3: invokevirtual #103                // Method toBuilder:()Lorg/apache/hadoop/hbase/shaded/protobuf/generated/ReplicationProtos$ReplicationPeerDescription$Builder;
       6: areturn

  public static org.apache.hadoop.hbase.shaded.protobuf.generated.ReplicationProtos$ReplicationPeerDescription$Builder newBuilder(org.apache.hadoop.hbase.shaded.protobuf.generated.ReplicationProtos$ReplicationPeerDescription);
    Code:
       0: getstatic     #102                // Field DEFAULT_INSTANCE:Lorg/apache/hadoop/hbase/shaded/protobuf/generated/ReplicationProtos$ReplicationPeerDescription;
       3: invokevirtual #103                // Method toBuilder:()Lorg/apache/hadoop/hbase/shaded/protobuf/generated/ReplicationProtos$ReplicationPeerDescription$Builder;
       6: aload_0
       7: invokevirtual #104                // Method org/apache/hadoop/hbase/shaded/protobuf/generated/ReplicationProtos$ReplicationPeerDescription$Builder.mergeFrom:(Lorg/apache/hadoop/hbase/shaded/protobuf/generated/ReplicationProtos$ReplicationPeerDescription;)Lorg/apache/hadoop/hbase/shaded/protobuf/generated/ReplicationProtos$ReplicationPeerDescription$Builder;
      10: areturn

  public org.apache.hadoop.hbase.shaded.protobuf.generated.ReplicationProtos$ReplicationPeerDescription$Builder toBuilder();
    Code:
       0: aload_0
       1: getstatic     #102                // Field DEFAULT_INSTANCE:Lorg/apache/hadoop/hbase/shaded/protobuf/generated/ReplicationProtos$ReplicationPeerDescription;
       4: if_acmpne     18
       7: new           #46                 // class org/apache/hadoop/hbase/shaded/protobuf/generated/ReplicationProtos$ReplicationPeerDescription$Builder
      10: dup
      11: aconst_null
      12: invokespecial #105                // Method org/apache/hadoop/hbase/shaded/protobuf/generated/ReplicationProtos$ReplicationPeerDescription$Builder."<init>":(Lorg/apache/hadoop/hbase/shaded/protobuf/generated/ReplicationProtos$1;)V
      15: goto          30
      18: new           #46                 // class org/apache/hadoop/hbase/shaded/protobuf/generated/ReplicationProtos$ReplicationPeerDescription$Builder
      21: dup
      22: aconst_null
      23: invokespecial #105                // Method org/apache/hadoop/hbase/shaded/protobuf/generated/ReplicationProtos$ReplicationPeerDescription$Builder."<init>":(Lorg/apache/hadoop/hbase/shaded/protobuf/generated/ReplicationProtos$1;)V
      26: aload_0
      27: invokevirtual #104                // Method org/apache/hadoop/hbase/shaded/protobuf/generated/ReplicationProtos$ReplicationPeerDescription$Builder.mergeFrom:(Lorg/apache/hadoop/hbase/shaded/protobuf/generated/ReplicationProtos$ReplicationPeerDescription;)Lorg/apache/hadoop/hbase/shaded/protobuf/generated/ReplicationProtos$ReplicationPeerDescription$Builder;
      30: areturn

  protected org.apache.hadoop.hbase.shaded.protobuf.generated.ReplicationProtos$ReplicationPeerDescription$Builder newBuilderForType(org.apache.hbase.thirdparty.com.google.protobuf.GeneratedMessageV3$BuilderParent);
    Code:
       0: new           #46                 // class org/apache/hadoop/hbase/shaded/protobuf/generated/ReplicationProtos$ReplicationPeerDescription$Builder
       3: dup
       4: aload_1
       5: aconst_null
       6: invokespecial #106                // Method org/apache/hadoop/hbase/shaded/protobuf/generated/ReplicationProtos$ReplicationPeerDescription$Builder."<init>":(Lorg/apache/hbase/thirdparty/com/google/protobuf/GeneratedMessageV3$BuilderParent;Lorg/apache/hadoop/hbase/shaded/protobuf/generated/ReplicationProtos$1;)V
       9: astore_2
      10: aload_2
      11: areturn

  public static org.apache.hadoop.hbase.shaded.protobuf.generated.ReplicationProtos$ReplicationPeerDescription getDefaultInstance();
    Code:
       0: getstatic     #102                // Field DEFAULT_INSTANCE:Lorg/apache/hadoop/hbase/shaded/protobuf/generated/ReplicationProtos$ReplicationPeerDescription;
       3: areturn

  public static org.apache.hbase.thirdparty.com.google.protobuf.Parser<org.apache.hadoop.hbase.shaded.protobuf.generated.ReplicationProtos$ReplicationPeerDescription> parser();
    Code:
       0: getstatic     #88                 // Field PARSER:Lorg/apache/hbase/thirdparty/com/google/protobuf/Parser;
       3: areturn

  public org.apache.hbase.thirdparty.com.google.protobuf.Parser<org.apache.hadoop.hbase.shaded.protobuf.generated.ReplicationProtos$ReplicationPeerDescription> getParserForType();
    Code:
       0: getstatic     #88                 // Field PARSER:Lorg/apache/hbase/thirdparty/com/google/protobuf/Parser;
       3: areturn

  public org.apache.hadoop.hbase.shaded.protobuf.generated.ReplicationProtos$ReplicationPeerDescription getDefaultInstanceForType();
    Code:
       0: getstatic     #102                // Field DEFAULT_INSTANCE:Lorg/apache/hadoop/hbase/shaded/protobuf/generated/ReplicationProtos$ReplicationPeerDescription;
       3: areturn

  protected org.apache.hbase.thirdparty.com.google.protobuf.Message$Builder newBuilderForType(org.apache.hbase.thirdparty.com.google.protobuf.GeneratedMessageV3$BuilderParent);
    Code:
       0: aload_0
       1: aload_1
       2: invokevirtual #107                // Method newBuilderForType:(Lorg/apache/hbase/thirdparty/com/google/protobuf/GeneratedMessageV3$BuilderParent;)Lorg/apache/hadoop/hbase/shaded/protobuf/generated/ReplicationProtos$ReplicationPeerDescription$Builder;
       5: areturn

  public org.apache.hbase.thirdparty.com.google.protobuf.Message$Builder toBuilder();
    Code:
       0: aload_0
       1: invokevirtual #103                // Method toBuilder:()Lorg/apache/hadoop/hbase/shaded/protobuf/generated/ReplicationProtos$ReplicationPeerDescription$Builder;
       4: areturn

  public org.apache.hbase.thirdparty.com.google.protobuf.Message$Builder newBuilderForType();
    Code:
       0: aload_0
       1: invokevirtual #108                // Method newBuilderForType:()Lorg/apache/hadoop/hbase/shaded/protobuf/generated/ReplicationProtos$ReplicationPeerDescription$Builder;
       4: areturn

  public org.apache.hbase.thirdparty.com.google.protobuf.MessageLite$Builder toBuilder();
    Code:
       0: aload_0
       1: invokevirtual #103                // Method toBuilder:()Lorg/apache/hadoop/hbase/shaded/protobuf/generated/ReplicationProtos$ReplicationPeerDescription$Builder;
       4: areturn

  public org.apache.hbase.thirdparty.com.google.protobuf.MessageLite$Builder newBuilderForType();
    Code:
       0: aload_0
       1: invokevirtual #108                // Method newBuilderForType:()Lorg/apache/hadoop/hbase/shaded/protobuf/generated/ReplicationProtos$ReplicationPeerDescription$Builder;
       4: areturn

  public org.apache.hbase.thirdparty.com.google.protobuf.MessageLite getDefaultInstanceForType();
    Code:
       0: aload_0
       1: invokevirtual #109                // Method getDefaultInstanceForType:()Lorg/apache/hadoop/hbase/shaded/protobuf/generated/ReplicationProtos$ReplicationPeerDescription;
       4: areturn

  public org.apache.hbase.thirdparty.com.google.protobuf.Message getDefaultInstanceForType();
    Code:
       0: aload_0
       1: invokevirtual #109                // Method getDefaultInstanceForType:()Lorg/apache/hadoop/hbase/shaded/protobuf/generated/ReplicationProtos$ReplicationPeerDescription;
       4: areturn

  static boolean access$6000();
    Code:
       0: getstatic     #9                  // Field alwaysUseFieldBuilders:Z
       3: ireturn

  org.apache.hadoop.hbase.shaded.protobuf.generated.ReplicationProtos$ReplicationPeerDescription(org.apache.hbase.thirdparty.com.google.protobuf.GeneratedMessageV3$Builder, org.apache.hadoop.hbase.shaded.protobuf.generated.ReplicationProtos$1);
    Code:
       0: aload_0
       1: aload_1
       2: invokespecial #8                  // Method "<init>":(Lorg/apache/hbase/thirdparty/com/google/protobuf/GeneratedMessageV3$Builder;)V
       5: return

  static java.lang.Object access$6202(org.apache.hadoop.hbase.shaded.protobuf.generated.ReplicationProtos$ReplicationPeerDescription, java.lang.Object);
    Code:
       0: aload_0
       1: aload_1
       2: dup_x1
       3: putfield      #7                  // Field id_:Ljava/lang/Object;
       6: areturn

  static org.apache.hadoop.hbase.shaded.protobuf.generated.ReplicationProtos$ReplicationState access$6302(org.apache.hadoop.hbase.shaded.protobuf.generated.ReplicationProtos$ReplicationPeerDescription, org.apache.hadoop.hbase.shaded.protobuf.generated.ReplicationProtos$ReplicationState);
    Code:
       0: aload_0
       1: aload_1
       2: dup_x1
       3: putfield      #6                  // Field state_:Lorg/apache/hadoop/hbase/shaded/protobuf/generated/ReplicationProtos$ReplicationState;
       6: areturn

  static org.apache.hadoop.hbase.shaded.protobuf.generated.ReplicationProtos$ReplicationPeer access$6402(org.apache.hadoop.hbase.shaded.protobuf.generated.ReplicationProtos$ReplicationPeerDescription, org.apache.hadoop.hbase.shaded.protobuf.generated.ReplicationProtos$ReplicationPeer);
    Code:
       0: aload_0
       1: aload_1
       2: dup_x1
       3: putfield      #5                  // Field config_:Lorg/apache/hadoop/hbase/shaded/protobuf/generated/ReplicationProtos$ReplicationPeer;
       6: areturn

  static org.apache.hadoop.hbase.shaded.protobuf.generated.ReplicationProtos$SyncReplicationState access$6502(org.apache.hadoop.hbase.shaded.protobuf.generated.ReplicationProtos$ReplicationPeerDescription, org.apache.hadoop.hbase.shaded.protobuf.generated.ReplicationProtos$SyncReplicationState);
    Code:
       0: aload_0
       1: aload_1
       2: dup_x1
       3: putfield      #4                  // Field syncReplicationState_:Lorg/apache/hadoop/hbase/shaded/protobuf/generated/ReplicationProtos$SyncReplicationState;
       6: areturn

  static int access$6602(org.apache.hadoop.hbase.shaded.protobuf.generated.ReplicationProtos$ReplicationPeerDescription, int);
    Code:
       0: aload_0
       1: iload_1
       2: dup_x1
       3: putfield      #3                  // Field bitField0_:I
       6: ireturn

  static java.lang.Object access$6200(org.apache.hadoop.hbase.shaded.protobuf.generated.ReplicationProtos$ReplicationPeerDescription);
    Code:
       0: aload_0
       1: getfield      #7                  // Field id_:Ljava/lang/Object;
       4: areturn

  static org.apache.hbase.thirdparty.com.google.protobuf.UnknownFieldSet access$6700(org.apache.hadoop.hbase.shaded.protobuf.generated.ReplicationProtos$ReplicationPeerDescription);
    Code:
       0: aload_0
       1: getfield      #2                  // Field unknownFields:Lorg/apache/hbase/thirdparty/com/google/protobuf/UnknownFieldSet;
       4: areturn

  org.apache.hadoop.hbase.shaded.protobuf.generated.ReplicationProtos$ReplicationPeerDescription(org.apache.hbase.thirdparty.com.google.protobuf.CodedInputStream, org.apache.hbase.thirdparty.com.google.protobuf.ExtensionRegistryLite, org.apache.hadoop.hbase.shaded.protobuf.generated.ReplicationProtos$1) throws org.apache.hbase.thirdparty.com.google.protobuf.InvalidProtocolBufferException;
    Code:
       0: aload_0
       1: aload_1
       2: aload_2
       3: invokespecial #1                  // Method "<init>":(Lorg/apache/hbase/thirdparty/com/google/protobuf/CodedInputStream;Lorg/apache/hbase/thirdparty/com/google/protobuf/ExtensionRegistryLite;)V
       6: return

  static {};
    Code:
       0: new           #45                 // class org/apache/hadoop/hbase/shaded/protobuf/generated/ReplicationProtos$ReplicationPeerDescription
       3: dup
       4: invokespecial #14                 // Method "<init>":()V
       7: putstatic     #102                // Field DEFAULT_INSTANCE:Lorg/apache/hadoop/hbase/shaded/protobuf/generated/ReplicationProtos$ReplicationPeerDescription;
      10: new           #110                // class org/apache/hadoop/hbase/shaded/protobuf/generated/ReplicationProtos$ReplicationPeerDescription$1
      13: dup
      14: invokespecial #111                // Method org/apache/hadoop/hbase/shaded/protobuf/generated/ReplicationProtos$ReplicationPeerDescription$1."<init>":()V
      17: putstatic     #88                 // Field PARSER:Lorg/apache/hbase/thirdparty/com/google/protobuf/Parser;
      20: return
}
