Compiled from "ReplicationHFileCleaner.java"
class org.apache.hadoop.hbase.replication.master.ReplicationHFileCleaner$1 implements org.apache.hbase.thirdparty.com.google.common.base.Predicate<org.apache.hadoop.fs.FileStatus> {
  final java.util.Set val$hfileRefs;

  final org.apache.hadoop.hbase.replication.master.ReplicationHFileCleaner this$0;

  org.apache.hadoop.hbase.replication.master.ReplicationHFileCleaner$1(org.apache.hadoop.hbase.replication.master.ReplicationHFileCleaner, java.util.Set);
    Code:
       0: aload_0
       1: aload_1
       2: putfield      #1                  // Field this$0:Lorg/apache/hadoop/hbase/replication/master/ReplicationHFileCleaner;
       5: aload_0
       6: aload_2
       7: putfield      #2                  // Field val$hfileRefs:Ljava/util/Set;
      10: aload_0
      11: invokespecial #3                  // Method java/lang/Object."<init>":()V
      14: return

  public boolean apply(org.apache.hadoop.fs.FileStatus);
    Code:
       0: aload_1
       1: ifnonnull     6
       4: iconst_0
       5: ireturn
       6: aload_1
       7: invokevirtual #4                  // Method org/apache/hadoop/fs/FileStatus.getPath:()Lorg/apache/hadoop/fs/Path;
      10: invokevirtual #5                  // Method org/apache/hadoop/fs/Path.getName:()Ljava/lang/String;
      13: astore_2
      14: aload_0
      15: getfield      #2                  // Field val$hfileRefs:Ljava/util/Set;
      18: aload_2
      19: invokeinterface #6,  2            // InterfaceMethod java/util/Set.contains:(Ljava/lang/Object;)Z
      24: istore_3
      25: invokestatic  #7                  // Method org/apache/hadoop/hbase/replication/master/ReplicationHFileCleaner.access$000:()Lorg/slf4j/Logger;
      28: invokeinterface #8,  1            // InterfaceMethod org/slf4j/Logger.isDebugEnabled:()Z
      33: ifeq          97
      36: iload_3
      37: ifeq          70
      40: invokestatic  #7                  // Method org/apache/hadoop/hbase/replication/master/ReplicationHFileCleaner.access$000:()Lorg/slf4j/Logger;
      43: new           #9                  // class java/lang/StringBuilder
      46: dup
      47: invokespecial #10                 // Method java/lang/StringBuilder."<init>":()V
      50: ldc           #11                 // String Found hfile reference in ZK, keeping:
      52: invokevirtual #12                 // Method java/lang/StringBuilder.append:(Ljava/lang/String;)Ljava/lang/StringBuilder;
      55: aload_2
      56: invokevirtual #12                 // Method java/lang/StringBuilder.append:(Ljava/lang/String;)Ljava/lang/StringBuilder;
      59: invokevirtual #13                 // Method java/lang/StringBuilder.toString:()Ljava/lang/String;
      62: invokeinterface #14,  2           // InterfaceMethod org/slf4j/Logger.debug:(Ljava/lang/String;)V
      67: goto          97
      70: invokestatic  #7                  // Method org/apache/hadoop/hbase/replication/master/ReplicationHFileCleaner.access$000:()Lorg/slf4j/Logger;
      73: new           #9                  // class java/lang/StringBuilder
      76: dup
      77: invokespecial #10                 // Method java/lang/StringBuilder."<init>":()V
      80: ldc           #15                 // String Did not find hfile reference in ZK, deleting:
      82: invokevirtual #12                 // Method java/lang/StringBuilder.append:(Ljava/lang/String;)Ljava/lang/StringBuilder;
      85: aload_2
      86: invokevirtual #12                 // Method java/lang/StringBuilder.append:(Ljava/lang/String;)Ljava/lang/StringBuilder;
      89: invokevirtual #13                 // Method java/lang/StringBuilder.toString:()Ljava/lang/String;
      92: invokeinterface #14,  2           // InterfaceMethod org/slf4j/Logger.debug:(Ljava/lang/String;)V
      97: iload_3
      98: ifne          105
     101: iconst_1
     102: goto          106
     105: iconst_0
     106: ireturn

  public boolean apply(java.lang.Object);
    Code:
       0: aload_0
       1: aload_1
       2: checkcast     #16                 // class org/apache/hadoop/fs/FileStatus
       5: invokevirtual #17                 // Method apply:(Lorg/apache/hadoop/fs/FileStatus;)Z
       8: ireturn
}
