Compiled from "ReplicationSourceManager.java"
class org.apache.hadoop.hbase.replication.regionserver.ReplicationSourceManager$NodeFailoverWorker extends java.lang.Thread {
  final org.apache.hadoop.hbase.replication.regionserver.ReplicationSourceManager this$0;

  public org.apache.hadoop.hbase.replication.regionserver.ReplicationSourceManager$NodeFailoverWorker(org.apache.hadoop.hbase.replication.regionserver.ReplicationSourceManager, org.apache.hadoop.hbase.ServerName);
    Code:
       0: aload_0
       1: aload_1
       2: putfield      #1                  // Field this$0:Lorg/apache/hadoop/hbase/replication/regionserver/ReplicationSourceManager;
       5: aload_0
       6: new           #2                  // class java/lang/StringBuilder
       9: dup
      10: invokespecial #3                  // Method java/lang/StringBuilder."<init>":()V
      13: ldc           #4                  // String Failover-for-
      15: invokevirtual #5                  // Method java/lang/StringBuilder.append:(Ljava/lang/String;)Ljava/lang/StringBuilder;
      18: aload_2
      19: invokevirtual #6                  // Method java/lang/StringBuilder.append:(Ljava/lang/Object;)Ljava/lang/StringBuilder;
      22: invokevirtual #7                  // Method java/lang/StringBuilder.toString:()Ljava/lang/String;
      25: invokespecial #8                  // Method java/lang/Thread."<init>":(Ljava/lang/String;)V
      28: aload_0
      29: aload_2
      30: putfield      #9                  // Field deadRS:Lorg/apache/hadoop/hbase/ServerName;
      33: aload_0
      34: new           #10                 // class java/util/HashMap
      37: dup
      38: aload_1
      39: invokestatic  #11                 // Method org/apache/hadoop/hbase/replication/regionserver/ReplicationSourceManager.access$000:(Lorg/apache/hadoop/hbase/replication/regionserver/ReplicationSourceManager;)Lorg/apache/hadoop/hbase/replication/ReplicationPeers;
      42: invokevirtual #12                 // Method org/apache/hadoop/hbase/replication/ReplicationPeers.getPeerCache:()Ljava/util/Map;
      45: invokespecial #13                 // Method java/util/HashMap."<init>":(Ljava/util/Map;)V
      48: putfield      #14                 // Field peersSnapshot:Ljava/util/Map;
      51: return

  public void run();
    Code:
       0: aload_0
       1: getfield      #1                  // Field this$0:Lorg/apache/hadoop/hbase/replication/regionserver/ReplicationSourceManager;
       4: invokestatic  #17                 // Method org/apache/hadoop/hbase/replication/regionserver/ReplicationSourceManager.access$100:(Lorg/apache/hadoop/hbase/replication/regionserver/ReplicationSourceManager;)J
       7: invokestatic  #18                 // Method java/util/concurrent/ThreadLocalRandom.current:()Ljava/util/concurrent/ThreadLocalRandom;
      10: invokevirtual #19                 // Method java/util/concurrent/ThreadLocalRandom.nextFloat:()F
      13: aload_0
      14: getfield      #1                  // Field this$0:Lorg/apache/hadoop/hbase/replication/regionserver/ReplicationSourceManager;
      17: invokestatic  #17                 // Method org/apache/hadoop/hbase/replication/regionserver/ReplicationSourceManager.access$100:(Lorg/apache/hadoop/hbase/replication/regionserver/ReplicationSourceManager;)J
      20: l2f
      21: fmul
      22: f2l
      23: ladd
      24: invokestatic  #20                 // Method java/lang/Thread.sleep:(J)V
      27: goto          47
      30: astore_1
      31: invokestatic  #22                 // Method org/apache/hadoop/hbase/replication/regionserver/ReplicationSourceManager.access$200:()Lorg/slf4j/Logger;
      34: ldc           #23                 // String Interrupted while waiting before transferring a queue.
      36: invokeinterface #24,  2           // InterfaceMethod org/slf4j/Logger.warn:(Ljava/lang/String;)V
      41: invokestatic  #25                 // Method java/lang/Thread.currentThread:()Ljava/lang/Thread;
      44: invokevirtual #26                 // Method java/lang/Thread.interrupt:()V
      47: aload_0
      48: getfield      #1                  // Field this$0:Lorg/apache/hadoop/hbase/replication/regionserver/ReplicationSourceManager;
      51: invokestatic  #27                 // Method org/apache/hadoop/hbase/replication/regionserver/ReplicationSourceManager.access$300:(Lorg/apache/hadoop/hbase/replication/regionserver/ReplicationSourceManager;)Lorg/apache/hadoop/hbase/Server;
      54: invokeinterface #28,  1           // InterfaceMethod org/apache/hadoop/hbase/Server.isStopped:()Z
      59: ifeq          73
      62: invokestatic  #22                 // Method org/apache/hadoop/hbase/replication/regionserver/ReplicationSourceManager.access$200:()Lorg/slf4j/Logger;
      65: ldc           #29                 // String Not transferring queue since we are shutting down
      67: invokeinterface #30,  2           // InterfaceMethod org/slf4j/Logger.info:(Ljava/lang/String;)V
      72: return
      73: new           #10                 // class java/util/HashMap
      76: dup
      77: invokespecial #31                 // Method java/util/HashMap."<init>":()V
      80: astore_1
      81: aload_0
      82: getfield      #1                  // Field this$0:Lorg/apache/hadoop/hbase/replication/regionserver/ReplicationSourceManager;
      85: invokestatic  #32                 // Method org/apache/hadoop/hbase/replication/regionserver/ReplicationSourceManager.access$400:(Lorg/apache/hadoop/hbase/replication/regionserver/ReplicationSourceManager;)Lorg/apache/hadoop/hbase/replication/ReplicationQueueStorage;
      88: aload_0
      89: getfield      #9                  // Field deadRS:Lorg/apache/hadoop/hbase/ServerName;
      92: invokeinterface #33,  2           // InterfaceMethod org/apache/hadoop/hbase/replication/ReplicationQueueStorage.getAllQueues:(Lorg/apache/hadoop/hbase/ServerName;)Ljava/util/List;
      97: astore_2
      98: aload_2
      99: invokeinterface #34,  1           // InterfaceMethod java/util/List.isEmpty:()Z
     104: ifne          255
     107: aload_0
     108: getfield      #1                  // Field this$0:Lorg/apache/hadoop/hbase/replication/regionserver/ReplicationSourceManager;
     111: invokestatic  #32                 // Method org/apache/hadoop/hbase/replication/regionserver/ReplicationSourceManager.access$400:(Lorg/apache/hadoop/hbase/replication/regionserver/ReplicationSourceManager;)Lorg/apache/hadoop/hbase/replication/ReplicationQueueStorage;
     114: aload_0
     115: getfield      #9                  // Field deadRS:Lorg/apache/hadoop/hbase/ServerName;
     118: aload_2
     119: invokestatic  #18                 // Method java/util/concurrent/ThreadLocalRandom.current:()Ljava/util/concurrent/ThreadLocalRandom;
     122: aload_2
     123: invokeinterface #35,  1           // InterfaceMethod java/util/List.size:()I
     128: invokevirtual #36                 // Method java/util/concurrent/ThreadLocalRandom.nextInt:(I)I
     131: invokeinterface #37,  2           // InterfaceMethod java/util/List.get:(I)Ljava/lang/Object;
     136: checkcast     #38                 // class java/lang/String
     139: aload_0
     140: getfield      #1                  // Field this$0:Lorg/apache/hadoop/hbase/replication/regionserver/ReplicationSourceManager;
     143: invokestatic  #27                 // Method org/apache/hadoop/hbase/replication/regionserver/ReplicationSourceManager.access$300:(Lorg/apache/hadoop/hbase/replication/regionserver/ReplicationSourceManager;)Lorg/apache/hadoop/hbase/Server;
     146: invokeinterface #39,  1           // InterfaceMethod org/apache/hadoop/hbase/Server.getServerName:()Lorg/apache/hadoop/hbase/ServerName;
     151: invokeinterface #40,  4           // InterfaceMethod org/apache/hadoop/hbase/replication/ReplicationQueueStorage.claimQueue:(Lorg/apache/hadoop/hbase/ServerName;Ljava/lang/String;Lorg/apache/hadoop/hbase/ServerName;)Lorg/apache/hadoop/hbase/util/Pair;
     156: astore_3
     157: aload_0
     158: getfield      #1                  // Field this$0:Lorg/apache/hadoop/hbase/replication/regionserver/ReplicationSourceManager;
     161: invokestatic  #17                 // Method org/apache/hadoop/hbase/replication/regionserver/ReplicationSourceManager.access$100:(Lorg/apache/hadoop/hbase/replication/regionserver/ReplicationSourceManager;)J
     164: ldc2_w        #41                 // long 2l
     167: ldiv
     168: lstore        4
     170: aload_3
     171: invokevirtual #43                 // Method org/apache/hadoop/hbase/util/Pair.getSecond:()Ljava/lang/Object;
     174: checkcast     #44                 // class java/util/SortedSet
     177: invokeinterface #45,  1           // InterfaceMethod java/util/SortedSet.isEmpty:()Z
     182: ifne          209
     185: aload_1
     186: aload_3
     187: invokevirtual #46                 // Method org/apache/hadoop/hbase/util/Pair.getFirst:()Ljava/lang/Object;
     190: aload_3
     191: invokevirtual #43                 // Method org/apache/hadoop/hbase/util/Pair.getSecond:()Ljava/lang/Object;
     194: invokeinterface #47,  3           // InterfaceMethod java/util/Map.put:(Ljava/lang/Object;Ljava/lang/Object;)Ljava/lang/Object;
     199: pop
     200: aload_0
     201: getfield      #1                  // Field this$0:Lorg/apache/hadoop/hbase/replication/regionserver/ReplicationSourceManager;
     204: invokestatic  #17                 // Method org/apache/hadoop/hbase/replication/regionserver/ReplicationSourceManager.access$100:(Lorg/apache/hadoop/hbase/replication/regionserver/ReplicationSourceManager;)J
     207: lstore        4
     209: lload         4
     211: invokestatic  #20                 // Method java/lang/Thread.sleep:(J)V
     214: goto          235
     217: astore        6
     219: invokestatic  #22                 // Method org/apache/hadoop/hbase/replication/regionserver/ReplicationSourceManager.access$200:()Lorg/slf4j/Logger;
     222: ldc           #23                 // String Interrupted while waiting before transferring a queue.
     224: invokeinterface #24,  2           // InterfaceMethod org/slf4j/Logger.warn:(Ljava/lang/String;)V
     229: invokestatic  #25                 // Method java/lang/Thread.currentThread:()Ljava/lang/Thread;
     232: invokevirtual #26                 // Method java/lang/Thread.interrupt:()V
     235: aload_0
     236: getfield      #1                  // Field this$0:Lorg/apache/hadoop/hbase/replication/regionserver/ReplicationSourceManager;
     239: invokestatic  #32                 // Method org/apache/hadoop/hbase/replication/regionserver/ReplicationSourceManager.access$400:(Lorg/apache/hadoop/hbase/replication/regionserver/ReplicationSourceManager;)Lorg/apache/hadoop/hbase/replication/ReplicationQueueStorage;
     242: aload_0
     243: getfield      #9                  // Field deadRS:Lorg/apache/hadoop/hbase/ServerName;
     246: invokeinterface #33,  2           // InterfaceMethod org/apache/hadoop/hbase/replication/ReplicationQueueStorage.getAllQueues:(Lorg/apache/hadoop/hbase/ServerName;)Ljava/util/List;
     251: astore_2
     252: goto          98
     255: aload_2
     256: invokeinterface #34,  1           // InterfaceMethod java/util/List.isEmpty:()Z
     261: ifeq          280
     264: aload_0
     265: getfield      #1                  // Field this$0:Lorg/apache/hadoop/hbase/replication/regionserver/ReplicationSourceManager;
     268: invokestatic  #32                 // Method org/apache/hadoop/hbase/replication/regionserver/ReplicationSourceManager.access$400:(Lorg/apache/hadoop/hbase/replication/regionserver/ReplicationSourceManager;)Lorg/apache/hadoop/hbase/replication/ReplicationQueueStorage;
     271: aload_0
     272: getfield      #9                  // Field deadRS:Lorg/apache/hadoop/hbase/ServerName;
     275: invokeinterface #48,  2           // InterfaceMethod org/apache/hadoop/hbase/replication/ReplicationQueueStorage.removeReplicatorIfQueueIsEmpty:(Lorg/apache/hadoop/hbase/ServerName;)V
     280: goto          354
     283: astore_2
     284: invokestatic  #22                 // Method org/apache/hadoop/hbase/replication/regionserver/ReplicationSourceManager.access$200:()Lorg/slf4j/Logger;
     287: new           #2                  // class java/lang/StringBuilder
     290: dup
     291: invokespecial #3                  // Method java/lang/StringBuilder."<init>":()V
     294: ldc           #50                 // String ReplicationException: cannot claim dead region (%s)'s replication queue. Znode : (%s) Possible solution: check if znode size exceeds jute.maxBuffer value.  If so, increase it for both client and server side.
     296: invokevirtual #5                  // Method java/lang/StringBuilder.append:(Ljava/lang/String;)Ljava/lang/StringBuilder;
     299: aload_2
     300: invokevirtual #6                  // Method java/lang/StringBuilder.append:(Ljava/lang/Object;)Ljava/lang/StringBuilder;
     303: invokevirtual #7                  // Method java/lang/StringBuilder.toString:()Ljava/lang/String;
     306: iconst_0
     307: anewarray     #51                 // class java/lang/Object
     310: invokestatic  #52                 // Method java/lang/String.format:(Ljava/lang/String;[Ljava/lang/Object;)Ljava/lang/String;
     313: aload_0
     314: getfield      #9                  // Field deadRS:Lorg/apache/hadoop/hbase/ServerName;
     317: aload_0
     318: getfield      #1                  // Field this$0:Lorg/apache/hadoop/hbase/replication/regionserver/ReplicationSourceManager;
     321: invokestatic  #32                 // Method org/apache/hadoop/hbase/replication/regionserver/ReplicationSourceManager.access$400:(Lorg/apache/hadoop/hbase/replication/regionserver/ReplicationSourceManager;)Lorg/apache/hadoop/hbase/replication/ReplicationQueueStorage;
     324: aload_0
     325: getfield      #9                  // Field deadRS:Lorg/apache/hadoop/hbase/ServerName;
     328: invokeinterface #53,  2           // InterfaceMethod org/apache/hadoop/hbase/replication/ReplicationQueueStorage.getRsNode:(Lorg/apache/hadoop/hbase/ServerName;)Ljava/lang/String;
     333: invokeinterface #54,  4           // InterfaceMethod org/slf4j/Logger.error:(Ljava/lang/String;Ljava/lang/Object;Ljava/lang/Object;)V
     338: aload_0
     339: getfield      #1                  // Field this$0:Lorg/apache/hadoop/hbase/replication/regionserver/ReplicationSourceManager;
     342: invokestatic  #27                 // Method org/apache/hadoop/hbase/replication/regionserver/ReplicationSourceManager.access$300:(Lorg/apache/hadoop/hbase/replication/regionserver/ReplicationSourceManager;)Lorg/apache/hadoop/hbase/Server;
     345: ldc           #55                 // String Failed to claim queue from dead regionserver.
     347: aload_2
     348: invokeinterface #56,  3           // InterfaceMethod org/apache/hadoop/hbase/Server.abort:(Ljava/lang/String;Ljava/lang/Throwable;)V
     353: return
     354: aload_1
     355: invokeinterface #57,  1           // InterfaceMethod java/util/Map.isEmpty:()Z
     360: ifeq          364
     363: return
     364: aload_1
     365: invokeinterface #58,  1           // InterfaceMethod java/util/Map.entrySet:()Ljava/util/Set;
     370: invokeinterface #59,  1           // InterfaceMethod java/util/Set.iterator:()Ljava/util/Iterator;
     375: astore_2
     376: aload_2
     377: invokeinterface #60,  1           // InterfaceMethod java/util/Iterator.hasNext:()Z
     382: ifeq          1018
     385: aload_2
     386: invokeinterface #61,  1           // InterfaceMethod java/util/Iterator.next:()Ljava/lang/Object;
     391: checkcast     #62                 // class java/util/Map$Entry
     394: astore_3
     395: aload_3
     396: invokeinterface #63,  1           // InterfaceMethod java/util/Map$Entry.getKey:()Ljava/lang/Object;
     401: checkcast     #38                 // class java/lang/String
     404: astore        4
     406: aload_3
     407: invokeinterface #64,  1           // InterfaceMethod java/util/Map$Entry.getValue:()Ljava/lang/Object;
     412: checkcast     #65                 // class java/util/Set
     415: astore        5
     417: new           #66                 // class org/apache/hadoop/hbase/replication/ReplicationQueueInfo
     420: dup
     421: aload         4
     423: invokespecial #67                 // Method org/apache/hadoop/hbase/replication/ReplicationQueueInfo."<init>":(Ljava/lang/String;)V
     426: astore        6
     428: aload         6
     430: invokevirtual #68                 // Method org/apache/hadoop/hbase/replication/ReplicationQueueInfo.getPeerId:()Ljava/lang/String;
     433: astore        7
     435: aload_0
     436: getfield      #1                  // Field this$0:Lorg/apache/hadoop/hbase/replication/regionserver/ReplicationSourceManager;
     439: invokestatic  #11                 // Method org/apache/hadoop/hbase/replication/regionserver/ReplicationSourceManager.access$000:(Lorg/apache/hadoop/hbase/replication/regionserver/ReplicationSourceManager;)Lorg/apache/hadoop/hbase/replication/ReplicationPeers;
     442: aload         7
     444: invokevirtual #69                 // Method org/apache/hadoop/hbase/replication/ReplicationPeers.getPeer:(Ljava/lang/String;)Lorg/apache/hadoop/hbase/replication/ReplicationPeerImpl;
     447: astore        8
     449: aload         8
     451: ifnull        465
     454: aload_0
     455: aload         7
     457: aload         8
     459: invokespecial #70                 // Method isOldPeer:(Ljava/lang/String;Lorg/apache/hadoop/hbase/replication/ReplicationPeerImpl;)Z
     462: ifne          499
     465: invokestatic  #22                 // Method org/apache/hadoop/hbase/replication/regionserver/ReplicationSourceManager.access$200:()Lorg/slf4j/Logger;
     468: ldc           #71                 // String Skipping failover for peer {} of node {}, peer is null
     470: aload         7
     472: aload_0
     473: getfield      #9                  // Field deadRS:Lorg/apache/hadoop/hbase/ServerName;
     476: invokeinterface #72,  4           // InterfaceMethod org/slf4j/Logger.warn:(Ljava/lang/String;Ljava/lang/Object;Ljava/lang/Object;)V
     481: aload_0
     482: getfield      #1                  // Field this$0:Lorg/apache/hadoop/hbase/replication/regionserver/ReplicationSourceManager;
     485: aload_0
     486: aload         4
     488: invokedynamic #73,  0             // InvokeDynamic #0:exec:(Lorg/apache/hadoop/hbase/replication/regionserver/ReplicationSourceManager$NodeFailoverWorker;Ljava/lang/String;)Lorg/apache/hadoop/hbase/replication/regionserver/ReplicationSourceManager$ReplicationQueueOperation;
     493: invokestatic  #74                 // Method org/apache/hadoop/hbase/replication/regionserver/ReplicationSourceManager.access$500:(Lorg/apache/hadoop/hbase/replication/regionserver/ReplicationSourceManager;Lorg/apache/hadoop/hbase/replication/regionserver/ReplicationSourceManager$ReplicationQueueOperation;)V
     496: goto          376
     499: aload_0
     500: getfield      #1                  // Field this$0:Lorg/apache/hadoop/hbase/replication/regionserver/ReplicationSourceManager;
     503: invokestatic  #27                 // Method org/apache/hadoop/hbase/replication/regionserver/ReplicationSourceManager.access$300:(Lorg/apache/hadoop/hbase/replication/regionserver/ReplicationSourceManager;)Lorg/apache/hadoop/hbase/Server;
     506: instanceof    #75                 // class org/apache/hadoop/hbase/replication/regionserver/ReplicationSyncUp$DummyServer
     509: ifeq          541
     512: aload         8
     514: invokevirtual #76                 // Method org/apache/hadoop/hbase/replication/ReplicationPeerImpl.getPeerState:()Lorg/apache/hadoop/hbase/replication/ReplicationPeer$PeerState;
     517: getstatic     #77                 // Field org/apache/hadoop/hbase/replication/ReplicationPeer$PeerState.DISABLED:Lorg/apache/hadoop/hbase/replication/ReplicationPeer$PeerState;
     520: invokevirtual #78                 // Method org/apache/hadoop/hbase/replication/ReplicationPeer$PeerState.equals:(Ljava/lang/Object;)Z
     523: ifeq          541
     526: invokestatic  #22                 // Method org/apache/hadoop/hbase/replication/regionserver/ReplicationSourceManager.access$200:()Lorg/slf4j/Logger;
     529: ldc           #79                 // String Peer {} is disabled. ReplicationSyncUp tool will skip replicating data to this peer.
     531: aload         7
     533: invokeinterface #80,  3           // InterfaceMethod org/slf4j/Logger.warn:(Ljava/lang/String;Ljava/lang/Object;)V
     538: goto          376
     541: aload_0
     542: getfield      #1                  // Field this$0:Lorg/apache/hadoop/hbase/replication/regionserver/ReplicationSourceManager;
     545: aload         4
     547: aload         8
     549: invokestatic  #81                 // Method org/apache/hadoop/hbase/replication/regionserver/ReplicationSourceManager.access$600:(Lorg/apache/hadoop/hbase/replication/regionserver/ReplicationSourceManager;Ljava/lang/String;Lorg/apache/hadoop/hbase/replication/ReplicationPeer;)Lorg/apache/hadoop/hbase/replication/regionserver/ReplicationSourceInterface;
     552: astore        9
     554: aload_0
     555: getfield      #1                  // Field this$0:Lorg/apache/hadoop/hbase/replication/regionserver/ReplicationSourceManager;
     558: invokestatic  #82                 // Method org/apache/hadoop/hbase/replication/regionserver/ReplicationSourceManager.access$700:(Lorg/apache/hadoop/hbase/replication/regionserver/ReplicationSourceManager;)Ljava/util/List;
     561: dup
     562: astore        10
     564: monitorenter
     565: aload_0
     566: getfield      #1                  // Field this$0:Lorg/apache/hadoop/hbase/replication/regionserver/ReplicationSourceManager;
     569: invokestatic  #11                 // Method org/apache/hadoop/hbase/replication/regionserver/ReplicationSourceManager.access$000:(Lorg/apache/hadoop/hbase/replication/regionserver/ReplicationSourceManager;)Lorg/apache/hadoop/hbase/replication/ReplicationPeers;
     572: aload         9
     574: invokeinterface #83,  1           // InterfaceMethod org/apache/hadoop/hbase/replication/regionserver/ReplicationSourceInterface.getPeerId:()Ljava/lang/String;
     579: invokevirtual #69                 // Method org/apache/hadoop/hbase/replication/ReplicationPeers.getPeer:(Ljava/lang/String;)Lorg/apache/hadoop/hbase/replication/ReplicationPeerImpl;
     582: astore        8
     584: aload         8
     586: ifnull        605
     589: aload_0
     590: aload         9
     592: invokeinterface #83,  1           // InterfaceMethod org/apache/hadoop/hbase/replication/regionserver/ReplicationSourceInterface.getPeerId:()Ljava/lang/String;
     597: aload         8
     599: invokespecial #70                 // Method isOldPeer:(Ljava/lang/String;Lorg/apache/hadoop/hbase/replication/ReplicationPeerImpl;)Z
     602: ifne          629
     605: aload         9
     607: ldc           #84                 // String Recovered queue doesn't belong to any current peer
     609: invokeinterface #85,  2           // InterfaceMethod org/apache/hadoop/hbase/replication/regionserver/ReplicationSourceInterface.terminate:(Ljava/lang/String;)V
     614: aload_0
     615: getfield      #1                  // Field this$0:Lorg/apache/hadoop/hbase/replication/regionserver/ReplicationSourceManager;
     618: aload         4
     620: invokestatic  #86                 // Method org/apache/hadoop/hbase/replication/regionserver/ReplicationSourceManager.access$800:(Lorg/apache/hadoop/hbase/replication/regionserver/ReplicationSourceManager;Ljava/lang/String;)V
     623: aload         10
     625: monitorexit
     626: goto          376
     629: aload         8
     631: invokevirtual #87                 // Method org/apache/hadoop/hbase/replication/ReplicationPeerImpl.getPeerConfig:()Lorg/apache/hadoop/hbase/replication/ReplicationPeerConfig;
     634: invokevirtual #88                 // Method org/apache/hadoop/hbase/replication/ReplicationPeerConfig.isSyncReplication:()Z
     637: ifeq          722
     640: aload         8
     642: invokevirtual #89                 // Method org/apache/hadoop/hbase/replication/ReplicationPeerImpl.getSyncReplicationStateAndNewState:()Lorg/apache/hadoop/hbase/util/Pair;
     645: astore        11
     647: aload         11
     649: invokevirtual #46                 // Method org/apache/hadoop/hbase/util/Pair.getFirst:()Ljava/lang/Object;
     652: checkcast     #90                 // class org/apache/hadoop/hbase/replication/SyncReplicationState
     655: getstatic     #91                 // Field org/apache/hadoop/hbase/replication/SyncReplicationState.STANDBY:Lorg/apache/hadoop/hbase/replication/SyncReplicationState;
     658: invokevirtual #92                 // Method org/apache/hadoop/hbase/replication/SyncReplicationState.equals:(Ljava/lang/Object;)Z
     661: ifeq          681
     664: aload         11
     666: invokevirtual #43                 // Method org/apache/hadoop/hbase/util/Pair.getSecond:()Ljava/lang/Object;
     669: checkcast     #90                 // class org/apache/hadoop/hbase/replication/SyncReplicationState
     672: getstatic     #93                 // Field org/apache/hadoop/hbase/replication/SyncReplicationState.NONE:Lorg/apache/hadoop/hbase/replication/SyncReplicationState;
     675: invokevirtual #92                 // Method org/apache/hadoop/hbase/replication/SyncReplicationState.equals:(Ljava/lang/Object;)Z
     678: ifne          698
     681: aload         11
     683: invokevirtual #43                 // Method org/apache/hadoop/hbase/util/Pair.getSecond:()Ljava/lang/Object;
     686: checkcast     #90                 // class org/apache/hadoop/hbase/replication/SyncReplicationState
     689: getstatic     #91                 // Field org/apache/hadoop/hbase/replication/SyncReplicationState.STANDBY:Lorg/apache/hadoop/hbase/replication/SyncReplicationState;
     692: invokevirtual #92                 // Method org/apache/hadoop/hbase/replication/SyncReplicationState.equals:(Ljava/lang/Object;)Z
     695: ifeq          722
     698: aload         9
     700: ldc           #94                 // String Sync replication peer is in STANDBY state
     702: invokeinterface #85,  2           // InterfaceMethod org/apache/hadoop/hbase/replication/regionserver/ReplicationSourceInterface.terminate:(Ljava/lang/String;)V
     707: aload_0
     708: getfield      #1                  // Field this$0:Lorg/apache/hadoop/hbase/replication/regionserver/ReplicationSourceManager;
     711: aload         4
     713: invokestatic  #86                 // Method org/apache/hadoop/hbase/replication/regionserver/ReplicationSourceManager.access$800:(Lorg/apache/hadoop/hbase/replication/regionserver/ReplicationSourceManager;Ljava/lang/String;)V
     716: aload         10
     718: monitorexit
     719: goto          376
     722: new           #10                 // class java/util/HashMap
     725: dup
     726: invokespecial #31                 // Method java/util/HashMap."<init>":()V
     729: astore        11
     731: aload_0
     732: getfield      #1                  // Field this$0:Lorg/apache/hadoop/hbase/replication/regionserver/ReplicationSourceManager;
     735: invokestatic  #95                 // Method org/apache/hadoop/hbase/replication/regionserver/ReplicationSourceManager.access$900:(Lorg/apache/hadoop/hbase/replication/regionserver/ReplicationSourceManager;)Ljava/util/concurrent/ConcurrentMap;
     738: aload         4
     740: aload         11
     742: invokeinterface #96,  3           // InterfaceMethod java/util/concurrent/ConcurrentMap.put:(Ljava/lang/Object;Ljava/lang/Object;)Ljava/lang/Object;
     747: pop
     748: aload         5
     750: invokeinterface #59,  1           // InterfaceMethod java/util/Set.iterator:()Ljava/util/Iterator;
     755: astore        12
     757: aload         12
     759: invokeinterface #60,  1           // InterfaceMethod java/util/Iterator.hasNext:()Z
     764: ifeq          839
     767: aload         12
     769: invokeinterface #61,  1           // InterfaceMethod java/util/Iterator.next:()Ljava/lang/Object;
     774: checkcast     #38                 // class java/lang/String
     777: astore        13
     779: aload         13
     781: invokestatic  #97                 // Method org/apache/hadoop/hbase/wal/AbstractFSWALProvider.getWALPrefixFromWALName:(Ljava/lang/String;)Ljava/lang/String;
     784: astore        14
     786: aload         11
     788: aload         14
     790: invokeinterface #15,  2           // InterfaceMethod java/util/Map.get:(Ljava/lang/Object;)Ljava/lang/Object;
     795: checkcast     #98                 // class java/util/NavigableSet
     798: astore        15
     800: aload         15
     802: ifnonnull     826
     805: new           #99                 // class java/util/TreeSet
     808: dup
     809: invokespecial #100                // Method java/util/TreeSet."<init>":()V
     812: astore        15
     814: aload         11
     816: aload         14
     818: aload         15
     820: invokeinterface #47,  3           // InterfaceMethod java/util/Map.put:(Ljava/lang/Object;Ljava/lang/Object;)Ljava/lang/Object;
     825: pop
     826: aload         15
     828: aload         13
     830: invokeinterface #101,  2          // InterfaceMethod java/util/NavigableSet.add:(Ljava/lang/Object;)Z
     835: pop
     836: goto          757
     839: aload_0
     840: getfield      #1                  // Field this$0:Lorg/apache/hadoop/hbase/replication/regionserver/ReplicationSourceManager;
     843: invokestatic  #82                 // Method org/apache/hadoop/hbase/replication/regionserver/ReplicationSourceManager.access$700:(Lorg/apache/hadoop/hbase/replication/regionserver/ReplicationSourceManager;)Ljava/util/List;
     846: aload         9
     848: invokeinterface #102,  2          // InterfaceMethod java/util/List.add:(Ljava/lang/Object;)Z
     853: pop
     854: invokestatic  #22                 // Method org/apache/hadoop/hbase/replication/regionserver/ReplicationSourceManager.access$200:()Lorg/slf4j/Logger;
     857: new           #2                  // class java/lang/StringBuilder
     860: dup
     861: invokespecial #3                  // Method java/lang/StringBuilder."<init>":()V
     864: ldc           #103                // String Added source for recovered queue:
     866: invokevirtual #5                  // Method java/lang/StringBuilder.append:(Ljava/lang/String;)Ljava/lang/StringBuilder;
     869: aload         9
     871: invokeinterface #104,  1          // InterfaceMethod org/apache/hadoop/hbase/replication/regionserver/ReplicationSourceInterface.getQueueId:()Ljava/lang/String;
     876: invokevirtual #5                  // Method java/lang/StringBuilder.append:(Ljava/lang/String;)Ljava/lang/StringBuilder;
     879: invokevirtual #7                  // Method java/lang/StringBuilder.toString:()Ljava/lang/String;
     882: invokeinterface #105,  2          // InterfaceMethod org/slf4j/Logger.trace:(Ljava/lang/String;)V
     887: aload         5
     889: invokeinterface #59,  1           // InterfaceMethod java/util/Set.iterator:()Ljava/util/Iterator;
     894: astore        12
     896: aload         12
     898: invokeinterface #60,  1           // InterfaceMethod java/util/Iterator.hasNext:()Z
     903: ifeq          977
     906: aload         12
     908: invokeinterface #61,  1           // InterfaceMethod java/util/Iterator.next:()Ljava/lang/Object;
     913: checkcast     #38                 // class java/lang/String
     916: astore        13
     918: invokestatic  #22                 // Method org/apache/hadoop/hbase/replication/regionserver/ReplicationSourceManager.access$200:()Lorg/slf4j/Logger;
     921: new           #2                  // class java/lang/StringBuilder
     924: dup
     925: invokespecial #3                  // Method java/lang/StringBuilder."<init>":()V
     928: ldc           #106                // String Enqueueing log from recovered queue for source:
     930: invokevirtual #5                  // Method java/lang/StringBuilder.append:(Ljava/lang/String;)Ljava/lang/StringBuilder;
     933: aload         9
     935: invokeinterface #104,  1          // InterfaceMethod org/apache/hadoop/hbase/replication/regionserver/ReplicationSourceInterface.getQueueId:()Ljava/lang/String;
     940: invokevirtual #5                  // Method java/lang/StringBuilder.append:(Ljava/lang/String;)Ljava/lang/StringBuilder;
     943: invokevirtual #7                  // Method java/lang/StringBuilder.toString:()Ljava/lang/String;
     946: invokeinterface #105,  2          // InterfaceMethod org/slf4j/Logger.trace:(Ljava/lang/String;)V
     951: aload         9
     953: new           #107                // class org/apache/hadoop/fs/Path
     956: dup
     957: aload_0
     958: getfield      #1                  // Field this$0:Lorg/apache/hadoop/hbase/replication/regionserver/ReplicationSourceManager;
     961: invokestatic  #108                // Method org/apache/hadoop/hbase/replication/regionserver/ReplicationSourceManager.access$1000:(Lorg/apache/hadoop/hbase/replication/regionserver/ReplicationSourceManager;)Lorg/apache/hadoop/fs/Path;
     964: aload         13
     966: invokespecial #109                // Method org/apache/hadoop/fs/Path."<init>":(Lorg/apache/hadoop/fs/Path;Ljava/lang/String;)V
     969: invokeinterface #110,  2          // InterfaceMethod org/apache/hadoop/hbase/replication/regionserver/ReplicationSourceInterface.enqueueLog:(Lorg/apache/hadoop/fs/Path;)V
     974: goto          896
     977: aload         9
     979: invokeinterface #111,  1          // InterfaceMethod org/apache/hadoop/hbase/replication/regionserver/ReplicationSourceInterface.startup:()V
     984: aload         10
     986: monitorexit
     987: goto          998
     990: astore        16
     992: aload         10
     994: monitorexit
     995: aload         16
     997: athrow
     998: goto          1015
    1001: astore        6
    1003: invokestatic  #22                 // Method org/apache/hadoop/hbase/replication/regionserver/ReplicationSourceManager.access$200:()Lorg/slf4j/Logger;
    1006: ldc           #113                // String Failed creating a source
    1008: aload         6
    1010: invokeinterface #114,  3          // InterfaceMethod org/slf4j/Logger.error:(Ljava/lang/String;Ljava/lang/Throwable;)V
    1015: goto          376
    1018: return
    Exception table:
       from    to  target type
           0    27    30   Class java/lang/InterruptedException
         209   214   217   Class java/lang/InterruptedException
          81   280   283   Class org/apache/hadoop/hbase/replication/ReplicationException
         565   626   990   any
         629   719   990   any
         722   987   990   any
         990   995   990   any
         417   496  1001   Class java/io/IOException
         499   538  1001   Class java/io/IOException
         541   626  1001   Class java/io/IOException
         629   719  1001   Class java/io/IOException
         722   998  1001   Class java/io/IOException
}
