Compiled from "ReplicationPeerImpl.java"
public class org.apache.hadoop.hbase.replication.ReplicationPeerImpl implements org.apache.hadoop.hbase.replication.ReplicationPeer {
  public org.apache.hadoop.hbase.replication.ReplicationPeerImpl(org.apache.hadoop.conf.Configuration, java.lang.String, org.apache.hadoop.hbase.replication.ReplicationPeerConfig, boolean, org.apache.hadoop.hbase.replication.SyncReplicationState, org.apache.hadoop.hbase.replication.SyncReplicationState);
    Code:
       0: aload_0
       1: invokespecial #1                  // Method java/lang/Object."<init>":()V
       4: aload_0
       5: aload_1
       6: putfield      #2                  // Field conf:Lorg/apache/hadoop/conf/Configuration;
       9: aload_0
      10: aload_2
      11: putfield      #3                  // Field id:Ljava/lang/String;
      14: aload_0
      15: iload         4
      17: ifeq          26
      20: getstatic     #4                  // Field org/apache/hadoop/hbase/replication/ReplicationPeer$PeerState.ENABLED:Lorg/apache/hadoop/hbase/replication/ReplicationPeer$PeerState;
      23: goto          29
      26: getstatic     #5                  // Field org/apache/hadoop/hbase/replication/ReplicationPeer$PeerState.DISABLED:Lorg/apache/hadoop/hbase/replication/ReplicationPeer$PeerState;
      29: putfield      #6                  // Field peerState:Lorg/apache/hadoop/hbase/replication/ReplicationPeer$PeerState;
      32: aload_0
      33: aload_3
      34: putfield      #7                  // Field peerConfig:Lorg/apache/hadoop/hbase/replication/ReplicationPeerConfig;
      37: aload_0
      38: aload         5
      40: invokevirtual #8                  // Method org/apache/hadoop/hbase/replication/SyncReplicationState.value:()I
      43: aload         6
      45: invokevirtual #8                  // Method org/apache/hadoop/hbase/replication/SyncReplicationState.value:()I
      48: bipush        16
      50: ishl
      51: ior
      52: putfield      #10                 // Field syncReplicationStateBits:I
      55: aload_0
      56: new           #11                 // class java/util/ArrayList
      59: dup
      60: invokespecial #12                 // Method java/util/ArrayList."<init>":()V
      63: putfield      #13                 // Field peerConfigListeners:Ljava/util/List;
      66: return

  public void setPeerState(boolean);
    Code:
       0: aload_0
       1: iload_1
       2: ifeq          11
       5: getstatic     #4                  // Field org/apache/hadoop/hbase/replication/ReplicationPeer$PeerState.ENABLED:Lorg/apache/hadoop/hbase/replication/ReplicationPeer$PeerState;
       8: goto          14
      11: getstatic     #5                  // Field org/apache/hadoop/hbase/replication/ReplicationPeer$PeerState.DISABLED:Lorg/apache/hadoop/hbase/replication/ReplicationPeer$PeerState;
      14: putfield      #6                  // Field peerState:Lorg/apache/hadoop/hbase/replication/ReplicationPeer$PeerState;
      17: return

  public void setPeerConfig(org.apache.hadoop.hbase.replication.ReplicationPeerConfig);
    Code:
       0: aload_0
       1: aload_1
       2: putfield      #7                  // Field peerConfig:Lorg/apache/hadoop/hbase/replication/ReplicationPeerConfig;
       5: aload_0
       6: getfield      #13                 // Field peerConfigListeners:Ljava/util/List;
       9: aload_1
      10: invokedynamic #14,  0             // InvokeDynamic #0:accept:(Lorg/apache/hadoop/hbase/replication/ReplicationPeerConfig;)Ljava/util/function/Consumer;
      15: invokeinterface #15,  2           // InterfaceMethod java/util/List.forEach:(Ljava/util/function/Consumer;)V
      20: return

  public void setNewSyncReplicationState(org.apache.hadoop.hbase.replication.SyncReplicationState);
    Code:
       0: aload_0
       1: aload_0
       2: getfield      #10                 // Field syncReplicationStateBits:I
       5: ldc           #16                 // int 65535
       7: iand
       8: aload_1
       9: invokevirtual #8                  // Method org/apache/hadoop/hbase/replication/SyncReplicationState.value:()I
      12: bipush        16
      14: ishl
      15: ior
      16: putfield      #10                 // Field syncReplicationStateBits:I
      19: return

  public void transitSyncReplicationState();
    Code:
       0: aload_0
       1: aload_0
       2: getfield      #10                 // Field syncReplicationStateBits:I
       5: bipush        16
       7: iushr
       8: getstatic     #17                 // Field org/apache/hadoop/hbase/replication/SyncReplicationState.NONE:Lorg/apache/hadoop/hbase/replication/SyncReplicationState;
      11: invokevirtual #8                  // Method org/apache/hadoop/hbase/replication/SyncReplicationState.value:()I
      14: bipush        16
      16: ishl
      17: ior
      18: putfield      #10                 // Field syncReplicationStateBits:I
      21: return

  public java.lang.String getId();
    Code:
       0: aload_0
       1: getfield      #3                  // Field id:Ljava/lang/String;
       4: areturn

  public org.apache.hadoop.hbase.replication.ReplicationPeer$PeerState getPeerState();
    Code:
       0: aload_0
       1: getfield      #6                  // Field peerState:Lorg/apache/hadoop/hbase/replication/ReplicationPeer$PeerState;
       4: areturn

  public org.apache.hadoop.hbase.util.Pair<org.apache.hadoop.hbase.replication.SyncReplicationState, org.apache.hadoop.hbase.replication.SyncReplicationState> getSyncReplicationStateAndNewState();
    Code:
       0: aload_0
       1: getfield      #10                 // Field syncReplicationStateBits:I
       4: istore_1
       5: iload_1
       6: invokestatic  #19                 // Method getSyncReplicationState:(I)Lorg/apache/hadoop/hbase/replication/SyncReplicationState;
       9: iload_1
      10: invokestatic  #20                 // Method getNewSyncReplicationState:(I)Lorg/apache/hadoop/hbase/replication/SyncReplicationState;
      13: invokestatic  #21                 // Method org/apache/hadoop/hbase/util/Pair.newPair:(Ljava/lang/Object;Ljava/lang/Object;)Lorg/apache/hadoop/hbase/util/Pair;
      16: areturn

  public org.apache.hadoop.hbase.replication.SyncReplicationState getNewSyncReplicationState();
    Code:
       0: aload_0
       1: getfield      #10                 // Field syncReplicationStateBits:I
       4: invokestatic  #20                 // Method getNewSyncReplicationState:(I)Lorg/apache/hadoop/hbase/replication/SyncReplicationState;
       7: areturn

  public org.apache.hadoop.hbase.replication.SyncReplicationState getSyncReplicationState();
    Code:
       0: aload_0
       1: getfield      #10                 // Field syncReplicationStateBits:I
       4: invokestatic  #19                 // Method getSyncReplicationState:(I)Lorg/apache/hadoop/hbase/replication/SyncReplicationState;
       7: areturn

  public org.apache.hadoop.hbase.replication.ReplicationPeerConfig getPeerConfig();
    Code:
       0: aload_0
       1: getfield      #7                  // Field peerConfig:Lorg/apache/hadoop/hbase/replication/ReplicationPeerConfig;
       4: areturn

  public org.apache.hadoop.conf.Configuration getConfiguration();
    Code:
       0: aload_0
       1: getfield      #2                  // Field conf:Lorg/apache/hadoop/conf/Configuration;
       4: areturn

  public java.util.Map<org.apache.hadoop.hbase.TableName, java.util.List<java.lang.String>> getTableCFs();
    Code:
       0: aload_0
       1: getfield      #7                  // Field peerConfig:Lorg/apache/hadoop/hbase/replication/ReplicationPeerConfig;
       4: invokevirtual #22                 // Method org/apache/hadoop/hbase/replication/ReplicationPeerConfig.getTableCFsMap:()Ljava/util/Map;
       7: areturn

  public java.util.Set<java.lang.String> getNamespaces();
    Code:
       0: aload_0
       1: getfield      #7                  // Field peerConfig:Lorg/apache/hadoop/hbase/replication/ReplicationPeerConfig;
       4: invokevirtual #23                 // Method org/apache/hadoop/hbase/replication/ReplicationPeerConfig.getNamespaces:()Ljava/util/Set;
       7: areturn

  public long getPeerBandwidth();
    Code:
       0: aload_0
       1: getfield      #7                  // Field peerConfig:Lorg/apache/hadoop/hbase/replication/ReplicationPeerConfig;
       4: invokevirtual #24                 // Method org/apache/hadoop/hbase/replication/ReplicationPeerConfig.getBandwidth:()J
       7: lreturn

  public void registerPeerConfigListener(org.apache.hadoop.hbase.replication.ReplicationPeerConfigListener);
    Code:
       0: aload_0
       1: getfield      #13                 // Field peerConfigListeners:Ljava/util/List;
       4: aload_1
       5: invokeinterface #25,  2           // InterfaceMethod java/util/List.add:(Ljava/lang/Object;)Z
      10: pop
      11: return
}
