Compiled from "ReplicationSourceShipper.java"
public final class org.apache.hadoop.hbase.replication.regionserver.ReplicationSourceShipper$WorkerState extends java.lang.Enum<org.apache.hadoop.hbase.replication.regionserver.ReplicationSourceShipper$WorkerState> {
  public static final org.apache.hadoop.hbase.replication.regionserver.ReplicationSourceShipper$WorkerState RUNNING;

  public static final org.apache.hadoop.hbase.replication.regionserver.ReplicationSourceShipper$WorkerState STOPPED;

  public static final org.apache.hadoop.hbase.replication.regionserver.ReplicationSourceShipper$WorkerState FINISHED;

  public static org.apache.hadoop.hbase.replication.regionserver.ReplicationSourceShipper$WorkerState[] values();
    Code:
       0: getstatic     #1                  // Field $VALUES:[Lorg/apache/hadoop/hbase/replication/regionserver/ReplicationSourceShipper$WorkerState;
       3: invokevirtual #2                  // Method "[Lorg/apache/hadoop/hbase/replication/regionserver/ReplicationSourceShipper$WorkerState;".clone:()Ljava/lang/Object;
       6: checkcast     #3                  // class "[Lorg/apache/hadoop/hbase/replication/regionserver/ReplicationSourceShipper$WorkerState;"
       9: areturn

  public static org.apache.hadoop.hbase.replication.regionserver.ReplicationSourceShipper$WorkerState valueOf(java.lang.String);
    Code:
       0: ldc           #4                  // class org/apache/hadoop/hbase/replication/regionserver/ReplicationSourceShipper$WorkerState
       2: aload_0
       3: invokestatic  #5                  // Method java/lang/Enum.valueOf:(Ljava/lang/Class;Ljava/lang/String;)Ljava/lang/Enum;
       6: checkcast     #4                  // class org/apache/hadoop/hbase/replication/regionserver/ReplicationSourceShipper$WorkerState
       9: areturn

  static {};
    Code:
       0: new           #4                  // class org/apache/hadoop/hbase/replication/regionserver/ReplicationSourceShipper$WorkerState
       3: dup
       4: ldc           #7                  // String RUNNING
       6: iconst_0
       7: invokespecial #8                  // Method "<init>":(Ljava/lang/String;I)V
      10: putstatic     #9                  // Field RUNNING:Lorg/apache/hadoop/hbase/replication/regionserver/ReplicationSourceShipper$WorkerState;
      13: new           #4                  // class org/apache/hadoop/hbase/replication/regionserver/ReplicationSourceShipper$WorkerState
      16: dup
      17: ldc           #10                 // String STOPPED
      19: iconst_1
      20: invokespecial #8                  // Method "<init>":(Ljava/lang/String;I)V
      23: putstatic     #11                 // Field STOPPED:Lorg/apache/hadoop/hbase/replication/regionserver/ReplicationSourceShipper$WorkerState;
      26: new           #4                  // class org/apache/hadoop/hbase/replication/regionserver/ReplicationSourceShipper$WorkerState
      29: dup
      30: ldc           #12                 // String FINISHED
      32: iconst_2
      33: invokespecial #8                  // Method "<init>":(Ljava/lang/String;I)V
      36: putstatic     #13                 // Field FINISHED:Lorg/apache/hadoop/hbase/replication/regionserver/ReplicationSourceShipper$WorkerState;
      39: iconst_3
      40: anewarray     #4                  // class org/apache/hadoop/hbase/replication/regionserver/ReplicationSourceShipper$WorkerState
      43: dup
      44: iconst_0
      45: getstatic     #9                  // Field RUNNING:Lorg/apache/hadoop/hbase/replication/regionserver/ReplicationSourceShipper$WorkerState;
      48: aastore
      49: dup
      50: iconst_1
      51: getstatic     #11                 // Field STOPPED:Lorg/apache/hadoop/hbase/replication/regionserver/ReplicationSourceShipper$WorkerState;
      54: aastore
      55: dup
      56: iconst_2
      57: getstatic     #13                 // Field FINISHED:Lorg/apache/hadoop/hbase/replication/regionserver/ReplicationSourceShipper$WorkerState;
      60: aastore
      61: putstatic     #1                  // Field $VALUES:[Lorg/apache/hadoop/hbase/replication/regionserver/ReplicationSourceShipper$WorkerState;
      64: return
}
