Compiled from "ReplicationProtos.java"
public final class org.apache.hadoop.hbase.shaded.protobuf.generated.ReplicationProtos$ReplicationPeer$Builder extends org.apache.hbase.thirdparty.com.google.protobuf.GeneratedMessageV3$Builder<org.apache.hadoop.hbase.shaded.protobuf.generated.ReplicationProtos$ReplicationPeer$Builder> implements org.apache.hadoop.hbase.shaded.protobuf.generated.ReplicationProtos$ReplicationPeerOrBuilder {
  public static final org.apache.hbase.thirdparty.com.google.protobuf.Descriptors$Descriptor getDescriptor();
    Code:
       0: invokestatic  #3                  // Method org/apache/hadoop/hbase/shaded/protobuf/generated/ReplicationProtos.access$1100:()Lorg/apache/hbase/thirdparty/com/google/protobuf/Descriptors$Descriptor;
       3: areturn

  protected org.apache.hbase.thirdparty.com.google.protobuf.GeneratedMessageV3$FieldAccessorTable internalGetFieldAccessorTable();
    Code:
       0: invokestatic  #4                  // Method org/apache/hadoop/hbase/shaded/protobuf/generated/ReplicationProtos.access$1200:()Lorg/apache/hbase/thirdparty/com/google/protobuf/GeneratedMessageV3$FieldAccessorTable;
       3: ldc           #5                  // class org/apache/hadoop/hbase/shaded/protobuf/generated/ReplicationProtos$ReplicationPeer
       5: ldc           #6                  // class org/apache/hadoop/hbase/shaded/protobuf/generated/ReplicationProtos$ReplicationPeer$Builder
       7: invokevirtual #7                  // Method org/apache/hbase/thirdparty/com/google/protobuf/GeneratedMessageV3$FieldAccessorTable.ensureFieldAccessorsInitialized:(Ljava/lang/Class;Ljava/lang/Class;)Lorg/apache/hbase/thirdparty/com/google/protobuf/GeneratedMessageV3$FieldAccessorTable;
      10: areturn

  public org.apache.hadoop.hbase.shaded.protobuf.generated.ReplicationProtos$ReplicationPeer$Builder clear();
    Code:
       0: aload_0
       1: invokespecial #27                 // Method org/apache/hbase/thirdparty/com/google/protobuf/GeneratedMessageV3$Builder.clear:()Lorg/apache/hbase/thirdparty/com/google/protobuf/GeneratedMessageV3$Builder;
       4: pop
       5: aload_0
       6: ldc           #9                  // String
       8: putfield      #10                 // Field clusterkey_:Ljava/lang/Object;
      11: aload_0
      12: aload_0
      13: getfield      #28                 // Field bitField0_:I
      16: bipush        -2
      18: iand
      19: putfield      #28                 // Field bitField0_:I
      22: aload_0
      23: ldc           #9                  // String
      25: putfield      #11                 // Field replicationEndpointImpl_:Ljava/lang/Object;
      28: aload_0
      29: aload_0
      30: getfield      #28                 // Field bitField0_:I
      33: bipush        -3
      35: iand
      36: putfield      #28                 // Field bitField0_:I
      39: aload_0
      40: getfield      #29                 // Field dataBuilder_:Lorg/apache/hbase/thirdparty/com/google/protobuf/RepeatedFieldBuilderV3;
      43: ifnonnull     67
      46: aload_0
      47: invokestatic  #12                 // Method java/util/Collections.emptyList:()Ljava/util/List;
      50: putfield      #13                 // Field data_:Ljava/util/List;
      53: aload_0
      54: aload_0
      55: getfield      #28                 // Field bitField0_:I
      58: bipush        -5
      60: iand
      61: putfield      #28                 // Field bitField0_:I
      64: goto          74
      67: aload_0
      68: getfield      #29                 // Field dataBuilder_:Lorg/apache/hbase/thirdparty/com/google/protobuf/RepeatedFieldBuilderV3;
      71: invokevirtual #30                 // Method org/apache/hbase/thirdparty/com/google/protobuf/RepeatedFieldBuilderV3.clear:()V
      74: aload_0
      75: getfield      #31                 // Field configurationBuilder_:Lorg/apache/hbase/thirdparty/com/google/protobuf/RepeatedFieldBuilderV3;
      78: ifnonnull     102
      81: aload_0
      82: invokestatic  #12                 // Method java/util/Collections.emptyList:()Ljava/util/List;
      85: putfield      #14                 // Field configuration_:Ljava/util/List;
      88: aload_0
      89: aload_0
      90: getfield      #28                 // Field bitField0_:I
      93: bipush        -9
      95: iand
      96: putfield      #28                 // Field bitField0_:I
      99: goto          109
     102: aload_0
     103: getfield      #31                 // Field configurationBuilder_:Lorg/apache/hbase/thirdparty/com/google/protobuf/RepeatedFieldBuilderV3;
     106: invokevirtual #30                 // Method org/apache/hbase/thirdparty/com/google/protobuf/RepeatedFieldBuilderV3.clear:()V
     109: aload_0
     110: getfield      #32                 // Field tableCfsBuilder_:Lorg/apache/hbase/thirdparty/com/google/protobuf/RepeatedFieldBuilderV3;
     113: ifnonnull     137
     116: aload_0
     117: invokestatic  #12                 // Method java/util/Collections.emptyList:()Ljava/util/List;
     120: putfield      #15                 // Field tableCfs_:Ljava/util/List;
     123: aload_0
     124: aload_0
     125: getfield      #28                 // Field bitField0_:I
     128: bipush        -17
     130: iand
     131: putfield      #28                 // Field bitField0_:I
     134: goto          144
     137: aload_0
     138: getfield      #32                 // Field tableCfsBuilder_:Lorg/apache/hbase/thirdparty/com/google/protobuf/RepeatedFieldBuilderV3;
     141: invokevirtual #30                 // Method org/apache/hbase/thirdparty/com/google/protobuf/RepeatedFieldBuilderV3.clear:()V
     144: aload_0
     145: invokestatic  #12                 // Method java/util/Collections.emptyList:()Ljava/util/List;
     148: putfield      #16                 // Field namespaces_:Ljava/util/List;
     151: aload_0
     152: aload_0
     153: getfield      #28                 // Field bitField0_:I
     156: bipush        -33
     158: iand
     159: putfield      #28                 // Field bitField0_:I
     162: aload_0
     163: lconst_0
     164: putfield      #33                 // Field bandwidth_:J
     167: aload_0
     168: aload_0
     169: getfield      #28                 // Field bitField0_:I
     172: bipush        -65
     174: iand
     175: putfield      #28                 // Field bitField0_:I
     178: aload_0
     179: iconst_0
     180: putfield      #34                 // Field replicateAll_:Z
     183: aload_0
     184: aload_0
     185: getfield      #28                 // Field bitField0_:I
     188: sipush        -129
     191: iand
     192: putfield      #28                 // Field bitField0_:I
     195: aload_0
     196: getfield      #35                 // Field excludeTableCfsBuilder_:Lorg/apache/hbase/thirdparty/com/google/protobuf/RepeatedFieldBuilderV3;
     199: ifnonnull     224
     202: aload_0
     203: invokestatic  #12                 // Method java/util/Collections.emptyList:()Ljava/util/List;
     206: putfield      #17                 // Field excludeTableCfs_:Ljava/util/List;
     209: aload_0
     210: aload_0
     211: getfield      #28                 // Field bitField0_:I
     214: sipush        -257
     217: iand
     218: putfield      #28                 // Field bitField0_:I
     221: goto          231
     224: aload_0
     225: getfield      #35                 // Field excludeTableCfsBuilder_:Lorg/apache/hbase/thirdparty/com/google/protobuf/RepeatedFieldBuilderV3;
     228: invokevirtual #30                 // Method org/apache/hbase/thirdparty/com/google/protobuf/RepeatedFieldBuilderV3.clear:()V
     231: aload_0
     232: invokestatic  #12                 // Method java/util/Collections.emptyList:()Ljava/util/List;
     235: putfield      #18                 // Field excludeNamespaces_:Ljava/util/List;
     238: aload_0
     239: aload_0
     240: getfield      #28                 // Field bitField0_:I
     243: sipush        -513
     246: iand
     247: putfield      #28                 // Field bitField0_:I
     250: aload_0
     251: iconst_0
     252: putfield      #36                 // Field serial_:Z
     255: aload_0
     256: aload_0
     257: getfield      #28                 // Field bitField0_:I
     260: sipush        -1025
     263: iand
     264: putfield      #28                 // Field bitField0_:I
     267: aload_0
     268: ldc           #9                  // String
     270: putfield      #19                 // Field remoteWALDir_:Ljava/lang/Object;
     273: aload_0
     274: aload_0
     275: getfield      #28                 // Field bitField0_:I
     278: sipush        -2049
     281: iand
     282: putfield      #28                 // Field bitField0_:I
     285: aload_0
     286: areturn

  public org.apache.hbase.thirdparty.com.google.protobuf.Descriptors$Descriptor getDescriptorForType();
    Code:
       0: invokestatic  #3                  // Method org/apache/hadoop/hbase/shaded/protobuf/generated/ReplicationProtos.access$1100:()Lorg/apache/hbase/thirdparty/com/google/protobuf/Descriptors$Descriptor;
       3: areturn

  public org.apache.hadoop.hbase.shaded.protobuf.generated.ReplicationProtos$ReplicationPeer getDefaultInstanceForType();
    Code:
       0: invokestatic  #37                 // Method org/apache/hadoop/hbase/shaded/protobuf/generated/ReplicationProtos$ReplicationPeer.getDefaultInstance:()Lorg/apache/hadoop/hbase/shaded/protobuf/generated/ReplicationProtos$ReplicationPeer;
       3: areturn

  public org.apache.hadoop.hbase.shaded.protobuf.generated.ReplicationProtos$ReplicationPeer build();
    Code:
       0: aload_0
       1: invokevirtual #38                 // Method buildPartial:()Lorg/apache/hadoop/hbase/shaded/protobuf/generated/ReplicationProtos$ReplicationPeer;
       4: astore_1
       5: aload_1
       6: invokevirtual #39                 // Method org/apache/hadoop/hbase/shaded/protobuf/generated/ReplicationProtos$ReplicationPeer.isInitialized:()Z
       9: ifne          17
      12: aload_1
      13: invokestatic  #40                 // Method newUninitializedMessageException:(Lorg/apache/hbase/thirdparty/com/google/protobuf/Message;)Lorg/apache/hbase/thirdparty/com/google/protobuf/UninitializedMessageException;
      16: athrow
      17: aload_1
      18: areturn

  public org.apache.hadoop.hbase.shaded.protobuf.generated.ReplicationProtos$ReplicationPeer buildPartial();
    Code:
       0: new           #5                  // class org/apache/hadoop/hbase/shaded/protobuf/generated/ReplicationProtos$ReplicationPeer
       3: dup
       4: aload_0
       5: aconst_null
       6: invokespecial #41                 // Method org/apache/hadoop/hbase/shaded/protobuf/generated/ReplicationProtos$ReplicationPeer."<init>":(Lorg/apache/hbase/thirdparty/com/google/protobuf/GeneratedMessageV3$Builder;Lorg/apache/hadoop/hbase/shaded/protobuf/generated/ReplicationProtos$1;)V
       9: astore_1
      10: aload_0
      11: getfield      #28                 // Field bitField0_:I
      14: istore_2
      15: iconst_0
      16: istore_3
      17: iload_2
      18: iconst_1
      19: iand
      20: iconst_1
      21: if_icmpne     28
      24: iload_3
      25: iconst_1
      26: ior
      27: istore_3
      28: aload_1
      29: aload_0
      30: getfield      #10                 // Field clusterkey_:Ljava/lang/Object;
      33: invokestatic  #42                 // Method org/apache/hadoop/hbase/shaded/protobuf/generated/ReplicationProtos$ReplicationPeer.access$1702:(Lorg/apache/hadoop/hbase/shaded/protobuf/generated/ReplicationProtos$ReplicationPeer;Ljava/lang/Object;)Ljava/lang/Object;
      36: pop
      37: iload_2
      38: iconst_2
      39: iand
      40: iconst_2
      41: if_icmpne     48
      44: iload_3
      45: iconst_2
      46: ior
      47: istore_3
      48: aload_1
      49: aload_0
      50: getfield      #11                 // Field replicationEndpointImpl_:Ljava/lang/Object;
      53: invokestatic  #43                 // Method org/apache/hadoop/hbase/shaded/protobuf/generated/ReplicationProtos$ReplicationPeer.access$1802:(Lorg/apache/hadoop/hbase/shaded/protobuf/generated/ReplicationProtos$ReplicationPeer;Ljava/lang/Object;)Ljava/lang/Object;
      56: pop
      57: aload_0
      58: getfield      #29                 // Field dataBuilder_:Lorg/apache/hbase/thirdparty/com/google/protobuf/RepeatedFieldBuilderV3;
      61: ifnonnull     108
      64: aload_0
      65: getfield      #28                 // Field bitField0_:I
      68: iconst_4
      69: iand
      70: iconst_4
      71: if_icmpne     96
      74: aload_0
      75: aload_0
      76: getfield      #13                 // Field data_:Ljava/util/List;
      79: invokestatic  #44                 // Method java/util/Collections.unmodifiableList:(Ljava/util/List;)Ljava/util/List;
      82: putfield      #13                 // Field data_:Ljava/util/List;
      85: aload_0
      86: aload_0
      87: getfield      #28                 // Field bitField0_:I
      90: bipush        -5
      92: iand
      93: putfield      #28                 // Field bitField0_:I
      96: aload_1
      97: aload_0
      98: getfield      #13                 // Field data_:Ljava/util/List;
     101: invokestatic  #45                 // Method org/apache/hadoop/hbase/shaded/protobuf/generated/ReplicationProtos$ReplicationPeer.access$1902:(Lorg/apache/hadoop/hbase/shaded/protobuf/generated/ReplicationProtos$ReplicationPeer;Ljava/util/List;)Ljava/util/List;
     104: pop
     105: goto          120
     108: aload_1
     109: aload_0
     110: getfield      #29                 // Field dataBuilder_:Lorg/apache/hbase/thirdparty/com/google/protobuf/RepeatedFieldBuilderV3;
     113: invokevirtual #46                 // Method org/apache/hbase/thirdparty/com/google/protobuf/RepeatedFieldBuilderV3.build:()Ljava/util/List;
     116: invokestatic  #45                 // Method org/apache/hadoop/hbase/shaded/protobuf/generated/ReplicationProtos$ReplicationPeer.access$1902:(Lorg/apache/hadoop/hbase/shaded/protobuf/generated/ReplicationProtos$ReplicationPeer;Ljava/util/List;)Ljava/util/List;
     119: pop
     120: aload_0
     121: getfield      #31                 // Field configurationBuilder_:Lorg/apache/hbase/thirdparty/com/google/protobuf/RepeatedFieldBuilderV3;
     124: ifnonnull     173
     127: aload_0
     128: getfield      #28                 // Field bitField0_:I
     131: bipush        8
     133: iand
     134: bipush        8
     136: if_icmpne     161
     139: aload_0
     140: aload_0
     141: getfield      #14                 // Field configuration_:Ljava/util/List;
     144: invokestatic  #44                 // Method java/util/Collections.unmodifiableList:(Ljava/util/List;)Ljava/util/List;
     147: putfield      #14                 // Field configuration_:Ljava/util/List;
     150: aload_0
     151: aload_0
     152: getfield      #28                 // Field bitField0_:I
     155: bipush        -9
     157: iand
     158: putfield      #28                 // Field bitField0_:I
     161: aload_1
     162: aload_0
     163: getfield      #14                 // Field configuration_:Ljava/util/List;
     166: invokestatic  #47                 // Method org/apache/hadoop/hbase/shaded/protobuf/generated/ReplicationProtos$ReplicationPeer.access$2002:(Lorg/apache/hadoop/hbase/shaded/protobuf/generated/ReplicationProtos$ReplicationPeer;Ljava/util/List;)Ljava/util/List;
     169: pop
     170: goto          185
     173: aload_1
     174: aload_0
     175: getfield      #31                 // Field configurationBuilder_:Lorg/apache/hbase/thirdparty/com/google/protobuf/RepeatedFieldBuilderV3;
     178: invokevirtual #46                 // Method org/apache/hbase/thirdparty/com/google/protobuf/RepeatedFieldBuilderV3.build:()Ljava/util/List;
     181: invokestatic  #47                 // Method org/apache/hadoop/hbase/shaded/protobuf/generated/ReplicationProtos$ReplicationPeer.access$2002:(Lorg/apache/hadoop/hbase/shaded/protobuf/generated/ReplicationProtos$ReplicationPeer;Ljava/util/List;)Ljava/util/List;
     184: pop
     185: aload_0
     186: getfield      #32                 // Field tableCfsBuilder_:Lorg/apache/hbase/thirdparty/com/google/protobuf/RepeatedFieldBuilderV3;
     189: ifnonnull     238
     192: aload_0
     193: getfield      #28                 // Field bitField0_:I
     196: bipush        16
     198: iand
     199: bipush        16
     201: if_icmpne     226
     204: aload_0
     205: aload_0
     206: getfield      #15                 // Field tableCfs_:Ljava/util/List;
     209: invokestatic  #44                 // Method java/util/Collections.unmodifiableList:(Ljava/util/List;)Ljava/util/List;
     212: putfield      #15                 // Field tableCfs_:Ljava/util/List;
     215: aload_0
     216: aload_0
     217: getfield      #28                 // Field bitField0_:I
     220: bipush        -17
     222: iand
     223: putfield      #28                 // Field bitField0_:I
     226: aload_1
     227: aload_0
     228: getfield      #15                 // Field tableCfs_:Ljava/util/List;
     231: invokestatic  #48                 // Method org/apache/hadoop/hbase/shaded/protobuf/generated/ReplicationProtos$ReplicationPeer.access$2102:(Lorg/apache/hadoop/hbase/shaded/protobuf/generated/ReplicationProtos$ReplicationPeer;Ljava/util/List;)Ljava/util/List;
     234: pop
     235: goto          250
     238: aload_1
     239: aload_0
     240: getfield      #32                 // Field tableCfsBuilder_:Lorg/apache/hbase/thirdparty/com/google/protobuf/RepeatedFieldBuilderV3;
     243: invokevirtual #46                 // Method org/apache/hbase/thirdparty/com/google/protobuf/RepeatedFieldBuilderV3.build:()Ljava/util/List;
     246: invokestatic  #48                 // Method org/apache/hadoop/hbase/shaded/protobuf/generated/ReplicationProtos$ReplicationPeer.access$2102:(Lorg/apache/hadoop/hbase/shaded/protobuf/generated/ReplicationProtos$ReplicationPeer;Ljava/util/List;)Ljava/util/List;
     249: pop
     250: aload_0
     251: getfield      #28                 // Field bitField0_:I
     254: bipush        32
     256: iand
     257: bipush        32
     259: if_icmpne     284
     262: aload_0
     263: aload_0
     264: getfield      #16                 // Field namespaces_:Ljava/util/List;
     267: invokestatic  #44                 // Method java/util/Collections.unmodifiableList:(Ljava/util/List;)Ljava/util/List;
     270: putfield      #16                 // Field namespaces_:Ljava/util/List;
     273: aload_0
     274: aload_0
     275: getfield      #28                 // Field bitField0_:I
     278: bipush        -33
     280: iand
     281: putfield      #28                 // Field bitField0_:I
     284: aload_1
     285: aload_0
     286: getfield      #16                 // Field namespaces_:Ljava/util/List;
     289: invokestatic  #49                 // Method org/apache/hadoop/hbase/shaded/protobuf/generated/ReplicationProtos$ReplicationPeer.access$2202:(Lorg/apache/hadoop/hbase/shaded/protobuf/generated/ReplicationProtos$ReplicationPeer;Ljava/util/List;)Ljava/util/List;
     292: pop
     293: iload_2
     294: bipush        64
     296: iand
     297: bipush        64
     299: if_icmpne     306
     302: iload_3
     303: iconst_4
     304: ior
     305: istore_3
     306: aload_1
     307: aload_0
     308: getfield      #33                 // Field bandwidth_:J
     311: invokestatic  #50                 // Method org/apache/hadoop/hbase/shaded/protobuf/generated/ReplicationProtos$ReplicationPeer.access$2302:(Lorg/apache/hadoop/hbase/shaded/protobuf/generated/ReplicationProtos$ReplicationPeer;J)J
     314: pop2
     315: iload_2
     316: sipush        128
     319: iand
     320: sipush        128
     323: if_icmpne     331
     326: iload_3
     327: bipush        8
     329: ior
     330: istore_3
     331: aload_1
     332: aload_0
     333: getfield      #34                 // Field replicateAll_:Z
     336: invokestatic  #51                 // Method org/apache/hadoop/hbase/shaded/protobuf/generated/ReplicationProtos$ReplicationPeer.access$2402:(Lorg/apache/hadoop/hbase/shaded/protobuf/generated/ReplicationProtos$ReplicationPeer;Z)Z
     339: pop
     340: aload_0
     341: getfield      #35                 // Field excludeTableCfsBuilder_:Lorg/apache/hbase/thirdparty/com/google/protobuf/RepeatedFieldBuilderV3;
     344: ifnonnull     396
     347: aload_0
     348: getfield      #28                 // Field bitField0_:I
     351: sipush        256
     354: iand
     355: sipush        256
     358: if_icmpne     384
     361: aload_0
     362: aload_0
     363: getfield      #17                 // Field excludeTableCfs_:Ljava/util/List;
     366: invokestatic  #44                 // Method java/util/Collections.unmodifiableList:(Ljava/util/List;)Ljava/util/List;
     369: putfield      #17                 // Field excludeTableCfs_:Ljava/util/List;
     372: aload_0
     373: aload_0
     374: getfield      #28                 // Field bitField0_:I
     377: sipush        -257
     380: iand
     381: putfield      #28                 // Field bitField0_:I
     384: aload_1
     385: aload_0
     386: getfield      #17                 // Field excludeTableCfs_:Ljava/util/List;
     389: invokestatic  #52                 // Method org/apache/hadoop/hbase/shaded/protobuf/generated/ReplicationProtos$ReplicationPeer.access$2502:(Lorg/apache/hadoop/hbase/shaded/protobuf/generated/ReplicationProtos$ReplicationPeer;Ljava/util/List;)Ljava/util/List;
     392: pop
     393: goto          408
     396: aload_1
     397: aload_0
     398: getfield      #35                 // Field excludeTableCfsBuilder_:Lorg/apache/hbase/thirdparty/com/google/protobuf/RepeatedFieldBuilderV3;
     401: invokevirtual #46                 // Method org/apache/hbase/thirdparty/com/google/protobuf/RepeatedFieldBuilderV3.build:()Ljava/util/List;
     404: invokestatic  #52                 // Method org/apache/hadoop/hbase/shaded/protobuf/generated/ReplicationProtos$ReplicationPeer.access$2502:(Lorg/apache/hadoop/hbase/shaded/protobuf/generated/ReplicationProtos$ReplicationPeer;Ljava/util/List;)Ljava/util/List;
     407: pop
     408: aload_0
     409: getfield      #28                 // Field bitField0_:I
     412: sipush        512
     415: iand
     416: sipush        512
     419: if_icmpne     445
     422: aload_0
     423: aload_0
     424: getfield      #18                 // Field excludeNamespaces_:Ljava/util/List;
     427: invokestatic  #44                 // Method java/util/Collections.unmodifiableList:(Ljava/util/List;)Ljava/util/List;
     430: putfield      #18                 // Field excludeNamespaces_:Ljava/util/List;
     433: aload_0
     434: aload_0
     435: getfield      #28                 // Field bitField0_:I
     438: sipush        -513
     441: iand
     442: putfield      #28                 // Field bitField0_:I
     445: aload_1
     446: aload_0
     447: getfield      #18                 // Field excludeNamespaces_:Ljava/util/List;
     450: invokestatic  #53                 // Method org/apache/hadoop/hbase/shaded/protobuf/generated/ReplicationProtos$ReplicationPeer.access$2602:(Lorg/apache/hadoop/hbase/shaded/protobuf/generated/ReplicationProtos$ReplicationPeer;Ljava/util/List;)Ljava/util/List;
     453: pop
     454: iload_2
     455: sipush        1024
     458: iand
     459: sipush        1024
     462: if_icmpne     470
     465: iload_3
     466: bipush        16
     468: ior
     469: istore_3
     470: aload_1
     471: aload_0
     472: getfield      #36                 // Field serial_:Z
     475: invokestatic  #54                 // Method org/apache/hadoop/hbase/shaded/protobuf/generated/ReplicationProtos$ReplicationPeer.access$2702:(Lorg/apache/hadoop/hbase/shaded/protobuf/generated/ReplicationProtos$ReplicationPeer;Z)Z
     478: pop
     479: iload_2
     480: sipush        2048
     483: iand
     484: sipush        2048
     487: if_icmpne     495
     490: iload_3
     491: bipush        32
     493: ior
     494: istore_3
     495: aload_1
     496: aload_0
     497: getfield      #19                 // Field remoteWALDir_:Ljava/lang/Object;
     500: invokestatic  #55                 // Method org/apache/hadoop/hbase/shaded/protobuf/generated/ReplicationProtos$ReplicationPeer.access$2802:(Lorg/apache/hadoop/hbase/shaded/protobuf/generated/ReplicationProtos$ReplicationPeer;Ljava/lang/Object;)Ljava/lang/Object;
     503: pop
     504: aload_1
     505: iload_3
     506: invokestatic  #56                 // Method org/apache/hadoop/hbase/shaded/protobuf/generated/ReplicationProtos$ReplicationPeer.access$2902:(Lorg/apache/hadoop/hbase/shaded/protobuf/generated/ReplicationProtos$ReplicationPeer;I)I
     509: pop
     510: aload_0
     511: invokevirtual #57                 // Method onBuilt:()V
     514: aload_1
     515: areturn

  public org.apache.hadoop.hbase.shaded.protobuf.generated.ReplicationProtos$ReplicationPeer$Builder clone();
    Code:
       0: aload_0
       1: invokespecial #58                 // Method org/apache/hbase/thirdparty/com/google/protobuf/GeneratedMessageV3$Builder.clone:()Lorg/apache/hbase/thirdparty/com/google/protobuf/GeneratedMessageV3$Builder;
       4: checkcast     #6                  // class org/apache/hadoop/hbase/shaded/protobuf/generated/ReplicationProtos$ReplicationPeer$Builder
       7: areturn

  public org.apache.hadoop.hbase.shaded.protobuf.generated.ReplicationProtos$ReplicationPeer$Builder setField(org.apache.hbase.thirdparty.com.google.protobuf.Descriptors$FieldDescriptor, java.lang.Object);
    Code:
       0: aload_0
       1: aload_1
       2: aload_2
       3: invokespecial #59                 // Method org/apache/hbase/thirdparty/com/google/protobuf/GeneratedMessageV3$Builder.setField:(Lorg/apache/hbase/thirdparty/com/google/protobuf/Descriptors$FieldDescriptor;Ljava/lang/Object;)Lorg/apache/hbase/thirdparty/com/google/protobuf/GeneratedMessageV3$Builder;
       6: checkcast     #6                  // class org/apache/hadoop/hbase/shaded/protobuf/generated/ReplicationProtos$ReplicationPeer$Builder
       9: areturn

  public org.apache.hadoop.hbase.shaded.protobuf.generated.ReplicationProtos$ReplicationPeer$Builder clearField(org.apache.hbase.thirdparty.com.google.protobuf.Descriptors$FieldDescriptor);
    Code:
       0: aload_0
       1: aload_1
       2: invokespecial #60                 // Method org/apache/hbase/thirdparty/com/google/protobuf/GeneratedMessageV3$Builder.clearField:(Lorg/apache/hbase/thirdparty/com/google/protobuf/Descriptors$FieldDescriptor;)Lorg/apache/hbase/thirdparty/com/google/protobuf/GeneratedMessageV3$Builder;
       5: checkcast     #6                  // class org/apache/hadoop/hbase/shaded/protobuf/generated/ReplicationProtos$ReplicationPeer$Builder
       8: areturn

  public org.apache.hadoop.hbase.shaded.protobuf.generated.ReplicationProtos$ReplicationPeer$Builder clearOneof(org.apache.hbase.thirdparty.com.google.protobuf.Descriptors$OneofDescriptor);
    Code:
       0: aload_0
       1: aload_1
       2: invokespecial #61                 // Method org/apache/hbase/thirdparty/com/google/protobuf/GeneratedMessageV3$Builder.clearOneof:(Lorg/apache/hbase/thirdparty/com/google/protobuf/Descriptors$OneofDescriptor;)Lorg/apache/hbase/thirdparty/com/google/protobuf/GeneratedMessageV3$Builder;
       5: checkcast     #6                  // class org/apache/hadoop/hbase/shaded/protobuf/generated/ReplicationProtos$ReplicationPeer$Builder
       8: areturn

  public org.apache.hadoop.hbase.shaded.protobuf.generated.ReplicationProtos$ReplicationPeer$Builder setRepeatedField(org.apache.hbase.thirdparty.com.google.protobuf.Descriptors$FieldDescriptor, int, java.lang.Object);
    Code:
       0: aload_0
       1: aload_1
       2: iload_2
       3: aload_3
       4: invokespecial #62                 // Method org/apache/hbase/thirdparty/com/google/protobuf/GeneratedMessageV3$Builder.setRepeatedField:(Lorg/apache/hbase/thirdparty/com/google/protobuf/Descriptors$FieldDescriptor;ILjava/lang/Object;)Lorg/apache/hbase/thirdparty/com/google/protobuf/GeneratedMessageV3$Builder;
       7: checkcast     #6                  // class org/apache/hadoop/hbase/shaded/protobuf/generated/ReplicationProtos$ReplicationPeer$Builder
      10: areturn

  public org.apache.hadoop.hbase.shaded.protobuf.generated.ReplicationProtos$ReplicationPeer$Builder addRepeatedField(org.apache.hbase.thirdparty.com.google.protobuf.Descriptors$FieldDescriptor, java.lang.Object);
    Code:
       0: aload_0
       1: aload_1
       2: aload_2
       3: invokespecial #63                 // Method org/apache/hbase/thirdparty/com/google/protobuf/GeneratedMessageV3$Builder.addRepeatedField:(Lorg/apache/hbase/thirdparty/com/google/protobuf/Descriptors$FieldDescriptor;Ljava/lang/Object;)Lorg/apache/hbase/thirdparty/com/google/protobuf/GeneratedMessageV3$Builder;
       6: checkcast     #6                  // class org/apache/hadoop/hbase/shaded/protobuf/generated/ReplicationProtos$ReplicationPeer$Builder
       9: areturn

  public org.apache.hadoop.hbase.shaded.protobuf.generated.ReplicationProtos$ReplicationPeer$Builder mergeFrom(org.apache.hbase.thirdparty.com.google.protobuf.Message);
    Code:
       0: aload_1
       1: instanceof    #5                  // class org/apache/hadoop/hbase/shaded/protobuf/generated/ReplicationProtos$ReplicationPeer
       4: ifeq          16
       7: aload_0
       8: aload_1
       9: checkcast     #5                  // class org/apache/hadoop/hbase/shaded/protobuf/generated/ReplicationProtos$ReplicationPeer
      12: invokevirtual #64                 // Method mergeFrom:(Lorg/apache/hadoop/hbase/shaded/protobuf/generated/ReplicationProtos$ReplicationPeer;)Lorg/apache/hadoop/hbase/shaded/protobuf/generated/ReplicationProtos$ReplicationPeer$Builder;
      15: areturn
      16: aload_0
      17: aload_1
      18: invokespecial #65                 // Method org/apache/hbase/thirdparty/com/google/protobuf/GeneratedMessageV3$Builder.mergeFrom:(Lorg/apache/hbase/thirdparty/com/google/protobuf/Message;)Lorg/apache/hbase/thirdparty/com/google/protobuf/AbstractMessage$Builder;
      21: pop
      22: aload_0
      23: areturn

  public org.apache.hadoop.hbase.shaded.protobuf.generated.ReplicationProtos$ReplicationPeer$Builder mergeFrom(org.apache.hadoop.hbase.shaded.protobuf.generated.ReplicationProtos$ReplicationPeer);
    Code:
       0: aload_1
       1: invokestatic  #37                 // Method org/apache/hadoop/hbase/shaded/protobuf/generated/ReplicationProtos$ReplicationPeer.getDefaultInstance:()Lorg/apache/hadoop/hbase/shaded/protobuf/generated/ReplicationProtos$ReplicationPeer;
       4: if_acmpne     9
       7: aload_0
       8: areturn
       9: aload_1
      10: invokevirtual #66                 // Method org/apache/hadoop/hbase/shaded/protobuf/generated/ReplicationProtos$ReplicationPeer.hasClusterkey:()Z
      13: ifeq          38
      16: aload_0
      17: dup
      18: getfield      #28                 // Field bitField0_:I
      21: iconst_1
      22: ior
      23: putfield      #28                 // Field bitField0_:I
      26: aload_0
      27: aload_1
      28: invokestatic  #67                 // Method org/apache/hadoop/hbase/shaded/protobuf/generated/ReplicationProtos$ReplicationPeer.access$1700:(Lorg/apache/hadoop/hbase/shaded/protobuf/generated/ReplicationProtos$ReplicationPeer;)Ljava/lang/Object;
      31: putfield      #10                 // Field clusterkey_:Ljava/lang/Object;
      34: aload_0
      35: invokevirtual #68                 // Method onChanged:()V
      38: aload_1
      39: invokevirtual #69                 // Method org/apache/hadoop/hbase/shaded/protobuf/generated/ReplicationProtos$ReplicationPeer.hasReplicationEndpointImpl:()Z
      42: ifeq          67
      45: aload_0
      46: dup
      47: getfield      #28                 // Field bitField0_:I
      50: iconst_2
      51: ior
      52: putfield      #28                 // Field bitField0_:I
      55: aload_0
      56: aload_1
      57: invokestatic  #70                 // Method org/apache/hadoop/hbase/shaded/protobuf/generated/ReplicationProtos$ReplicationPeer.access$1800:(Lorg/apache/hadoop/hbase/shaded/protobuf/generated/ReplicationProtos$ReplicationPeer;)Ljava/lang/Object;
      60: putfield      #11                 // Field replicationEndpointImpl_:Ljava/lang/Object;
      63: aload_0
      64: invokevirtual #68                 // Method onChanged:()V
      67: aload_0
      68: getfield      #29                 // Field dataBuilder_:Lorg/apache/hbase/thirdparty/com/google/protobuf/RepeatedFieldBuilderV3;
      71: ifnonnull     145
      74: aload_1
      75: invokestatic  #71                 // Method org/apache/hadoop/hbase/shaded/protobuf/generated/ReplicationProtos$ReplicationPeer.access$1900:(Lorg/apache/hadoop/hbase/shaded/protobuf/generated/ReplicationProtos$ReplicationPeer;)Ljava/util/List;
      78: invokeinterface #72,  1           // InterfaceMethod java/util/List.isEmpty:()Z
      83: ifne          231
      86: aload_0
      87: getfield      #13                 // Field data_:Ljava/util/List;
      90: invokeinterface #72,  1           // InterfaceMethod java/util/List.isEmpty:()Z
      95: ifeq          120
      98: aload_0
      99: aload_1
     100: invokestatic  #71                 // Method org/apache/hadoop/hbase/shaded/protobuf/generated/ReplicationProtos$ReplicationPeer.access$1900:(Lorg/apache/hadoop/hbase/shaded/protobuf/generated/ReplicationProtos$ReplicationPeer;)Ljava/util/List;
     103: putfield      #13                 // Field data_:Ljava/util/List;
     106: aload_0
     107: aload_0
     108: getfield      #28                 // Field bitField0_:I
     111: bipush        -5
     113: iand
     114: putfield      #28                 // Field bitField0_:I
     117: goto          138
     120: aload_0
     121: invokespecial #73                 // Method ensureDataIsMutable:()V
     124: aload_0
     125: getfield      #13                 // Field data_:Ljava/util/List;
     128: aload_1
     129: invokestatic  #71                 // Method org/apache/hadoop/hbase/shaded/protobuf/generated/ReplicationProtos$ReplicationPeer.access$1900:(Lorg/apache/hadoop/hbase/shaded/protobuf/generated/ReplicationProtos$ReplicationPeer;)Ljava/util/List;
     132: invokeinterface #74,  2           // InterfaceMethod java/util/List.addAll:(Ljava/util/Collection;)Z
     137: pop
     138: aload_0
     139: invokevirtual #68                 // Method onChanged:()V
     142: goto          231
     145: aload_1
     146: invokestatic  #71                 // Method org/apache/hadoop/hbase/shaded/protobuf/generated/ReplicationProtos$ReplicationPeer.access$1900:(Lorg/apache/hadoop/hbase/shaded/protobuf/generated/ReplicationProtos$ReplicationPeer;)Ljava/util/List;
     149: invokeinterface #72,  1           // InterfaceMethod java/util/List.isEmpty:()Z
     154: ifne          231
     157: aload_0
     158: getfield      #29                 // Field dataBuilder_:Lorg/apache/hbase/thirdparty/com/google/protobuf/RepeatedFieldBuilderV3;
     161: invokevirtual #75                 // Method org/apache/hbase/thirdparty/com/google/protobuf/RepeatedFieldBuilderV3.isEmpty:()Z
     164: ifeq          219
     167: aload_0
     168: getfield      #29                 // Field dataBuilder_:Lorg/apache/hbase/thirdparty/com/google/protobuf/RepeatedFieldBuilderV3;
     171: invokevirtual #76                 // Method org/apache/hbase/thirdparty/com/google/protobuf/RepeatedFieldBuilderV3.dispose:()V
     174: aload_0
     175: aconst_null
     176: putfield      #29                 // Field dataBuilder_:Lorg/apache/hbase/thirdparty/com/google/protobuf/RepeatedFieldBuilderV3;
     179: aload_0
     180: aload_1
     181: invokestatic  #71                 // Method org/apache/hadoop/hbase/shaded/protobuf/generated/ReplicationProtos$ReplicationPeer.access$1900:(Lorg/apache/hadoop/hbase/shaded/protobuf/generated/ReplicationProtos$ReplicationPeer;)Ljava/util/List;
     184: putfield      #13                 // Field data_:Ljava/util/List;
     187: aload_0
     188: aload_0
     189: getfield      #28                 // Field bitField0_:I
     192: bipush        -5
     194: iand
     195: putfield      #28                 // Field bitField0_:I
     198: aload_0
     199: invokestatic  #77                 // Method org/apache/hadoop/hbase/shaded/protobuf/generated/ReplicationProtos$ReplicationPeer.access$3000:()Z
     202: ifeq          212
     205: aload_0
     206: invokespecial #23                 // Method getDataFieldBuilder:()Lorg/apache/hbase/thirdparty/com/google/protobuf/RepeatedFieldBuilderV3;
     209: goto          213
     212: aconst_null
     213: putfield      #29                 // Field dataBuilder_:Lorg/apache/hbase/thirdparty/com/google/protobuf/RepeatedFieldBuilderV3;
     216: goto          231
     219: aload_0
     220: getfield      #29                 // Field dataBuilder_:Lorg/apache/hbase/thirdparty/com/google/protobuf/RepeatedFieldBuilderV3;
     223: aload_1
     224: invokestatic  #71                 // Method org/apache/hadoop/hbase/shaded/protobuf/generated/ReplicationProtos$ReplicationPeer.access$1900:(Lorg/apache/hadoop/hbase/shaded/protobuf/generated/ReplicationProtos$ReplicationPeer;)Ljava/util/List;
     227: invokevirtual #78                 // Method org/apache/hbase/thirdparty/com/google/protobuf/RepeatedFieldBuilderV3.addAllMessages:(Ljava/lang/Iterable;)Lorg/apache/hbase/thirdparty/com/google/protobuf/RepeatedFieldBuilderV3;
     230: pop
     231: aload_0
     232: getfield      #31                 // Field configurationBuilder_:Lorg/apache/hbase/thirdparty/com/google/protobuf/RepeatedFieldBuilderV3;
     235: ifnonnull     309
     238: aload_1
     239: invokestatic  #79                 // Method org/apache/hadoop/hbase/shaded/protobuf/generated/ReplicationProtos$ReplicationPeer.access$2000:(Lorg/apache/hadoop/hbase/shaded/protobuf/generated/ReplicationProtos$ReplicationPeer;)Ljava/util/List;
     242: invokeinterface #72,  1           // InterfaceMethod java/util/List.isEmpty:()Z
     247: ifne          395
     250: aload_0
     251: getfield      #14                 // Field configuration_:Ljava/util/List;
     254: invokeinterface #72,  1           // InterfaceMethod java/util/List.isEmpty:()Z
     259: ifeq          284
     262: aload_0
     263: aload_1
     264: invokestatic  #79                 // Method org/apache/hadoop/hbase/shaded/protobuf/generated/ReplicationProtos$ReplicationPeer.access$2000:(Lorg/apache/hadoop/hbase/shaded/protobuf/generated/ReplicationProtos$ReplicationPeer;)Ljava/util/List;
     267: putfield      #14                 // Field configuration_:Ljava/util/List;
     270: aload_0
     271: aload_0
     272: getfield      #28                 // Field bitField0_:I
     275: bipush        -9
     277: iand
     278: putfield      #28                 // Field bitField0_:I
     281: goto          302
     284: aload_0
     285: invokespecial #80                 // Method ensureConfigurationIsMutable:()V
     288: aload_0
     289: getfield      #14                 // Field configuration_:Ljava/util/List;
     292: aload_1
     293: invokestatic  #79                 // Method org/apache/hadoop/hbase/shaded/protobuf/generated/ReplicationProtos$ReplicationPeer.access$2000:(Lorg/apache/hadoop/hbase/shaded/protobuf/generated/ReplicationProtos$ReplicationPeer;)Ljava/util/List;
     296: invokeinterface #74,  2           // InterfaceMethod java/util/List.addAll:(Ljava/util/Collection;)Z
     301: pop
     302: aload_0
     303: invokevirtual #68                 // Method onChanged:()V
     306: goto          395
     309: aload_1
     310: invokestatic  #79                 // Method org/apache/hadoop/hbase/shaded/protobuf/generated/ReplicationProtos$ReplicationPeer.access$2000:(Lorg/apache/hadoop/hbase/shaded/protobuf/generated/ReplicationProtos$ReplicationPeer;)Ljava/util/List;
     313: invokeinterface #72,  1           // InterfaceMethod java/util/List.isEmpty:()Z
     318: ifne          395
     321: aload_0
     322: getfield      #31                 // Field configurationBuilder_:Lorg/apache/hbase/thirdparty/com/google/protobuf/RepeatedFieldBuilderV3;
     325: invokevirtual #75                 // Method org/apache/hbase/thirdparty/com/google/protobuf/RepeatedFieldBuilderV3.isEmpty:()Z
     328: ifeq          383
     331: aload_0
     332: getfield      #31                 // Field configurationBuilder_:Lorg/apache/hbase/thirdparty/com/google/protobuf/RepeatedFieldBuilderV3;
     335: invokevirtual #76                 // Method org/apache/hbase/thirdparty/com/google/protobuf/RepeatedFieldBuilderV3.dispose:()V
     338: aload_0
     339: aconst_null
     340: putfield      #31                 // Field configurationBuilder_:Lorg/apache/hbase/thirdparty/com/google/protobuf/RepeatedFieldBuilderV3;
     343: aload_0
     344: aload_1
     345: invokestatic  #79                 // Method org/apache/hadoop/hbase/shaded/protobuf/generated/ReplicationProtos$ReplicationPeer.access$2000:(Lorg/apache/hadoop/hbase/shaded/protobuf/generated/ReplicationProtos$ReplicationPeer;)Ljava/util/List;
     348: putfield      #14                 // Field configuration_:Ljava/util/List;
     351: aload_0
     352: aload_0
     353: getfield      #28                 // Field bitField0_:I
     356: bipush        -9
     358: iand
     359: putfield      #28                 // Field bitField0_:I
     362: aload_0
     363: invokestatic  #81                 // Method org/apache/hadoop/hbase/shaded/protobuf/generated/ReplicationProtos$ReplicationPeer.access$3100:()Z
     366: ifeq          376
     369: aload_0
     370: invokespecial #24                 // Method getConfigurationFieldBuilder:()Lorg/apache/hbase/thirdparty/com/google/protobuf/RepeatedFieldBuilderV3;
     373: goto          377
     376: aconst_null
     377: putfield      #31                 // Field configurationBuilder_:Lorg/apache/hbase/thirdparty/com/google/protobuf/RepeatedFieldBuilderV3;
     380: goto          395
     383: aload_0
     384: getfield      #31                 // Field configurationBuilder_:Lorg/apache/hbase/thirdparty/com/google/protobuf/RepeatedFieldBuilderV3;
     387: aload_1
     388: invokestatic  #79                 // Method org/apache/hadoop/hbase/shaded/protobuf/generated/ReplicationProtos$ReplicationPeer.access$2000:(Lorg/apache/hadoop/hbase/shaded/protobuf/generated/ReplicationProtos$ReplicationPeer;)Ljava/util/List;
     391: invokevirtual #78                 // Method org/apache/hbase/thirdparty/com/google/protobuf/RepeatedFieldBuilderV3.addAllMessages:(Ljava/lang/Iterable;)Lorg/apache/hbase/thirdparty/com/google/protobuf/RepeatedFieldBuilderV3;
     394: pop
     395: aload_0
     396: getfield      #32                 // Field tableCfsBuilder_:Lorg/apache/hbase/thirdparty/com/google/protobuf/RepeatedFieldBuilderV3;
     399: ifnonnull     473
     402: aload_1
     403: invokestatic  #82                 // Method org/apache/hadoop/hbase/shaded/protobuf/generated/ReplicationProtos$ReplicationPeer.access$2100:(Lorg/apache/hadoop/hbase/shaded/protobuf/generated/ReplicationProtos$ReplicationPeer;)Ljava/util/List;
     406: invokeinterface #72,  1           // InterfaceMethod java/util/List.isEmpty:()Z
     411: ifne          559
     414: aload_0
     415: getfield      #15                 // Field tableCfs_:Ljava/util/List;
     418: invokeinterface #72,  1           // InterfaceMethod java/util/List.isEmpty:()Z
     423: ifeq          448
     426: aload_0
     427: aload_1
     428: invokestatic  #82                 // Method org/apache/hadoop/hbase/shaded/protobuf/generated/ReplicationProtos$ReplicationPeer.access$2100:(Lorg/apache/hadoop/hbase/shaded/protobuf/generated/ReplicationProtos$ReplicationPeer;)Ljava/util/List;
     431: putfield      #15                 // Field tableCfs_:Ljava/util/List;
     434: aload_0
     435: aload_0
     436: getfield      #28                 // Field bitField0_:I
     439: bipush        -17
     441: iand
     442: putfield      #28                 // Field bitField0_:I
     445: goto          466
     448: aload_0
     449: invokespecial #83                 // Method ensureTableCfsIsMutable:()V
     452: aload_0
     453: getfield      #15                 // Field tableCfs_:Ljava/util/List;
     456: aload_1
     457: invokestatic  #82                 // Method org/apache/hadoop/hbase/shaded/protobuf/generated/ReplicationProtos$ReplicationPeer.access$2100:(Lorg/apache/hadoop/hbase/shaded/protobuf/generated/ReplicationProtos$ReplicationPeer;)Ljava/util/List;
     460: invokeinterface #74,  2           // InterfaceMethod java/util/List.addAll:(Ljava/util/Collection;)Z
     465: pop
     466: aload_0
     467: invokevirtual #68                 // Method onChanged:()V
     470: goto          559
     473: aload_1
     474: invokestatic  #82                 // Method org/apache/hadoop/hbase/shaded/protobuf/generated/ReplicationProtos$ReplicationPeer.access$2100:(Lorg/apache/hadoop/hbase/shaded/protobuf/generated/ReplicationProtos$ReplicationPeer;)Ljava/util/List;
     477: invokeinterface #72,  1           // InterfaceMethod java/util/List.isEmpty:()Z
     482: ifne          559
     485: aload_0
     486: getfield      #32                 // Field tableCfsBuilder_:Lorg/apache/hbase/thirdparty/com/google/protobuf/RepeatedFieldBuilderV3;
     489: invokevirtual #75                 // Method org/apache/hbase/thirdparty/com/google/protobuf/RepeatedFieldBuilderV3.isEmpty:()Z
     492: ifeq          547
     495: aload_0
     496: getfield      #32                 // Field tableCfsBuilder_:Lorg/apache/hbase/thirdparty/com/google/protobuf/RepeatedFieldBuilderV3;
     499: invokevirtual #76                 // Method org/apache/hbase/thirdparty/com/google/protobuf/RepeatedFieldBuilderV3.dispose:()V
     502: aload_0
     503: aconst_null
     504: putfield      #32                 // Field tableCfsBuilder_:Lorg/apache/hbase/thirdparty/com/google/protobuf/RepeatedFieldBuilderV3;
     507: aload_0
     508: aload_1
     509: invokestatic  #82                 // Method org/apache/hadoop/hbase/shaded/protobuf/generated/ReplicationProtos$ReplicationPeer.access$2100:(Lorg/apache/hadoop/hbase/shaded/protobuf/generated/ReplicationProtos$ReplicationPeer;)Ljava/util/List;
     512: putfield      #15                 // Field tableCfs_:Ljava/util/List;
     515: aload_0
     516: aload_0
     517: getfield      #28                 // Field bitField0_:I
     520: bipush        -17
     522: iand
     523: putfield      #28                 // Field bitField0_:I
     526: aload_0
     527: invokestatic  #84                 // Method org/apache/hadoop/hbase/shaded/protobuf/generated/ReplicationProtos$ReplicationPeer.access$3200:()Z
     530: ifeq          540
     533: aload_0
     534: invokespecial #25                 // Method getTableCfsFieldBuilder:()Lorg/apache/hbase/thirdparty/com/google/protobuf/RepeatedFieldBuilderV3;
     537: goto          541
     540: aconst_null
     541: putfield      #32                 // Field tableCfsBuilder_:Lorg/apache/hbase/thirdparty/com/google/protobuf/RepeatedFieldBuilderV3;
     544: goto          559
     547: aload_0
     548: getfield      #32                 // Field tableCfsBuilder_:Lorg/apache/hbase/thirdparty/com/google/protobuf/RepeatedFieldBuilderV3;
     551: aload_1
     552: invokestatic  #82                 // Method org/apache/hadoop/hbase/shaded/protobuf/generated/ReplicationProtos$ReplicationPeer.access$2100:(Lorg/apache/hadoop/hbase/shaded/protobuf/generated/ReplicationProtos$ReplicationPeer;)Ljava/util/List;
     555: invokevirtual #78                 // Method org/apache/hbase/thirdparty/com/google/protobuf/RepeatedFieldBuilderV3.addAllMessages:(Ljava/lang/Iterable;)Lorg/apache/hbase/thirdparty/com/google/protobuf/RepeatedFieldBuilderV3;
     558: pop
     559: aload_1
     560: invokestatic  #85                 // Method org/apache/hadoop/hbase/shaded/protobuf/generated/ReplicationProtos$ReplicationPeer.access$2200:(Lorg/apache/hadoop/hbase/shaded/protobuf/generated/ReplicationProtos$ReplicationPeer;)Ljava/util/List;
     563: invokeinterface #72,  1           // InterfaceMethod java/util/List.isEmpty:()Z
     568: ifne          627
     571: aload_0
     572: getfield      #16                 // Field namespaces_:Ljava/util/List;
     575: invokeinterface #72,  1           // InterfaceMethod java/util/List.isEmpty:()Z
     580: ifeq          605
     583: aload_0
     584: aload_1
     585: invokestatic  #85                 // Method org/apache/hadoop/hbase/shaded/protobuf/generated/ReplicationProtos$ReplicationPeer.access$2200:(Lorg/apache/hadoop/hbase/shaded/protobuf/generated/ReplicationProtos$ReplicationPeer;)Ljava/util/List;
     588: putfield      #16                 // Field namespaces_:Ljava/util/List;
     591: aload_0
     592: aload_0
     593: getfield      #28                 // Field bitField0_:I
     596: bipush        -33
     598: iand
     599: putfield      #28                 // Field bitField0_:I
     602: goto          623
     605: aload_0
     606: invokespecial #86                 // Method ensureNamespacesIsMutable:()V
     609: aload_0
     610: getfield      #16                 // Field namespaces_:Ljava/util/List;
     613: aload_1
     614: invokestatic  #85                 // Method org/apache/hadoop/hbase/shaded/protobuf/generated/ReplicationProtos$ReplicationPeer.access$2200:(Lorg/apache/hadoop/hbase/shaded/protobuf/generated/ReplicationProtos$ReplicationPeer;)Ljava/util/List;
     617: invokeinterface #74,  2           // InterfaceMethod java/util/List.addAll:(Ljava/util/Collection;)Z
     622: pop
     623: aload_0
     624: invokevirtual #68                 // Method onChanged:()V
     627: aload_1
     628: invokevirtual #87                 // Method org/apache/hadoop/hbase/shaded/protobuf/generated/ReplicationProtos$ReplicationPeer.hasBandwidth:()Z
     631: ifeq          643
     634: aload_0
     635: aload_1
     636: invokevirtual #88                 // Method org/apache/hadoop/hbase/shaded/protobuf/generated/ReplicationProtos$ReplicationPeer.getBandwidth:()J
     639: invokevirtual #89                 // Method setBandwidth:(J)Lorg/apache/hadoop/hbase/shaded/protobuf/generated/ReplicationProtos$ReplicationPeer$Builder;
     642: pop
     643: aload_1
     644: invokevirtual #90                 // Method org/apache/hadoop/hbase/shaded/protobuf/generated/ReplicationProtos$ReplicationPeer.hasReplicateAll:()Z
     647: ifeq          659
     650: aload_0
     651: aload_1
     652: invokevirtual #91                 // Method org/apache/hadoop/hbase/shaded/protobuf/generated/ReplicationProtos$ReplicationPeer.getReplicateAll:()Z
     655: invokevirtual #92                 // Method setReplicateAll:(Z)Lorg/apache/hadoop/hbase/shaded/protobuf/generated/ReplicationProtos$ReplicationPeer$Builder;
     658: pop
     659: aload_0
     660: getfield      #35                 // Field excludeTableCfsBuilder_:Lorg/apache/hbase/thirdparty/com/google/protobuf/RepeatedFieldBuilderV3;
     663: ifnonnull     738
     666: aload_1
     667: invokestatic  #93                 // Method org/apache/hadoop/hbase/shaded/protobuf/generated/ReplicationProtos$ReplicationPeer.access$2500:(Lorg/apache/hadoop/hbase/shaded/protobuf/generated/ReplicationProtos$ReplicationPeer;)Ljava/util/List;
     670: invokeinterface #72,  1           // InterfaceMethod java/util/List.isEmpty:()Z
     675: ifne          825
     678: aload_0
     679: getfield      #17                 // Field excludeTableCfs_:Ljava/util/List;
     682: invokeinterface #72,  1           // InterfaceMethod java/util/List.isEmpty:()Z
     687: ifeq          713
     690: aload_0
     691: aload_1
     692: invokestatic  #93                 // Method org/apache/hadoop/hbase/shaded/protobuf/generated/ReplicationProtos$ReplicationPeer.access$2500:(Lorg/apache/hadoop/hbase/shaded/protobuf/generated/ReplicationProtos$ReplicationPeer;)Ljava/util/List;
     695: putfield      #17                 // Field excludeTableCfs_:Ljava/util/List;
     698: aload_0
     699: aload_0
     700: getfield      #28                 // Field bitField0_:I
     703: sipush        -257
     706: iand
     707: putfield      #28                 // Field bitField0_:I
     710: goto          731
     713: aload_0
     714: invokespecial #94                 // Method ensureExcludeTableCfsIsMutable:()V
     717: aload_0
     718: getfield      #17                 // Field excludeTableCfs_:Ljava/util/List;
     721: aload_1
     722: invokestatic  #93                 // Method org/apache/hadoop/hbase/shaded/protobuf/generated/ReplicationProtos$ReplicationPeer.access$2500:(Lorg/apache/hadoop/hbase/shaded/protobuf/generated/ReplicationProtos$ReplicationPeer;)Ljava/util/List;
     725: invokeinterface #74,  2           // InterfaceMethod java/util/List.addAll:(Ljava/util/Collection;)Z
     730: pop
     731: aload_0
     732: invokevirtual #68                 // Method onChanged:()V
     735: goto          825
     738: aload_1
     739: invokestatic  #93                 // Method org/apache/hadoop/hbase/shaded/protobuf/generated/ReplicationProtos$ReplicationPeer.access$2500:(Lorg/apache/hadoop/hbase/shaded/protobuf/generated/ReplicationProtos$ReplicationPeer;)Ljava/util/List;
     742: invokeinterface #72,  1           // InterfaceMethod java/util/List.isEmpty:()Z
     747: ifne          825
     750: aload_0
     751: getfield      #35                 // Field excludeTableCfsBuilder_:Lorg/apache/hbase/thirdparty/com/google/protobuf/RepeatedFieldBuilderV3;
     754: invokevirtual #75                 // Method org/apache/hbase/thirdparty/com/google/protobuf/RepeatedFieldBuilderV3.isEmpty:()Z
     757: ifeq          813
     760: aload_0
     761: getfield      #35                 // Field excludeTableCfsBuilder_:Lorg/apache/hbase/thirdparty/com/google/protobuf/RepeatedFieldBuilderV3;
     764: invokevirtual #76                 // Method org/apache/hbase/thirdparty/com/google/protobuf/RepeatedFieldBuilderV3.dispose:()V
     767: aload_0
     768: aconst_null
     769: putfield      #35                 // Field excludeTableCfsBuilder_:Lorg/apache/hbase/thirdparty/com/google/protobuf/RepeatedFieldBuilderV3;
     772: aload_0
     773: aload_1
     774: invokestatic  #93                 // Method org/apache/hadoop/hbase/shaded/protobuf/generated/ReplicationProtos$ReplicationPeer.access$2500:(Lorg/apache/hadoop/hbase/shaded/protobuf/generated/ReplicationProtos$ReplicationPeer;)Ljava/util/List;
     777: putfield      #17                 // Field excludeTableCfs_:Ljava/util/List;
     780: aload_0
     781: aload_0
     782: getfield      #28                 // Field bitField0_:I
     785: sipush        -257
     788: iand
     789: putfield      #28                 // Field bitField0_:I
     792: aload_0
     793: invokestatic  #95                 // Method org/apache/hadoop/hbase/shaded/protobuf/generated/ReplicationProtos$ReplicationPeer.access$3300:()Z
     796: ifeq          806
     799: aload_0
     800: invokespecial #26                 // Method getExcludeTableCfsFieldBuilder:()Lorg/apache/hbase/thirdparty/com/google/protobuf/RepeatedFieldBuilderV3;
     803: goto          807
     806: aconst_null
     807: putfield      #35                 // Field excludeTableCfsBuilder_:Lorg/apache/hbase/thirdparty/com/google/protobuf/RepeatedFieldBuilderV3;
     810: goto          825
     813: aload_0
     814: getfield      #35                 // Field excludeTableCfsBuilder_:Lorg/apache/hbase/thirdparty/com/google/protobuf/RepeatedFieldBuilderV3;
     817: aload_1
     818: invokestatic  #93                 // Method org/apache/hadoop/hbase/shaded/protobuf/generated/ReplicationProtos$ReplicationPeer.access$2500:(Lorg/apache/hadoop/hbase/shaded/protobuf/generated/ReplicationProtos$ReplicationPeer;)Ljava/util/List;
     821: invokevirtual #78                 // Method org/apache/hbase/thirdparty/com/google/protobuf/RepeatedFieldBuilderV3.addAllMessages:(Ljava/lang/Iterable;)Lorg/apache/hbase/thirdparty/com/google/protobuf/RepeatedFieldBuilderV3;
     824: pop
     825: aload_1
     826: invokestatic  #96                 // Method org/apache/hadoop/hbase/shaded/protobuf/generated/ReplicationProtos$ReplicationPeer.access$2600:(Lorg/apache/hadoop/hbase/shaded/protobuf/generated/ReplicationProtos$ReplicationPeer;)Ljava/util/List;
     829: invokeinterface #72,  1           // InterfaceMethod java/util/List.isEmpty:()Z
     834: ifne          894
     837: aload_0
     838: getfield      #18                 // Field excludeNamespaces_:Ljava/util/List;
     841: invokeinterface #72,  1           // InterfaceMethod java/util/List.isEmpty:()Z
     846: ifeq          872
     849: aload_0
     850: aload_1
     851: invokestatic  #96                 // Method org/apache/hadoop/hbase/shaded/protobuf/generated/ReplicationProtos$ReplicationPeer.access$2600:(Lorg/apache/hadoop/hbase/shaded/protobuf/generated/ReplicationProtos$ReplicationPeer;)Ljava/util/List;
     854: putfield      #18                 // Field excludeNamespaces_:Ljava/util/List;
     857: aload_0
     858: aload_0
     859: getfield      #28                 // Field bitField0_:I
     862: sipush        -513
     865: iand
     866: putfield      #28                 // Field bitField0_:I
     869: goto          890
     872: aload_0
     873: invokespecial #97                 // Method ensureExcludeNamespacesIsMutable:()V
     876: aload_0
     877: getfield      #18                 // Field excludeNamespaces_:Ljava/util/List;
     880: aload_1
     881: invokestatic  #96                 // Method org/apache/hadoop/hbase/shaded/protobuf/generated/ReplicationProtos$ReplicationPeer.access$2600:(Lorg/apache/hadoop/hbase/shaded/protobuf/generated/ReplicationProtos$ReplicationPeer;)Ljava/util/List;
     884: invokeinterface #74,  2           // InterfaceMethod java/util/List.addAll:(Ljava/util/Collection;)Z
     889: pop
     890: aload_0
     891: invokevirtual #68                 // Method onChanged:()V
     894: aload_1
     895: invokevirtual #98                 // Method org/apache/hadoop/hbase/shaded/protobuf/generated/ReplicationProtos$ReplicationPeer.hasSerial:()Z
     898: ifeq          910
     901: aload_0
     902: aload_1
     903: invokevirtual #99                 // Method org/apache/hadoop/hbase/shaded/protobuf/generated/ReplicationProtos$ReplicationPeer.getSerial:()Z
     906: invokevirtual #100                // Method setSerial:(Z)Lorg/apache/hadoop/hbase/shaded/protobuf/generated/ReplicationProtos$ReplicationPeer$Builder;
     909: pop
     910: aload_1
     911: invokevirtual #101                // Method org/apache/hadoop/hbase/shaded/protobuf/generated/ReplicationProtos$ReplicationPeer.hasRemoteWALDir:()Z
     914: ifeq          941
     917: aload_0
     918: dup
     919: getfield      #28                 // Field bitField0_:I
     922: sipush        2048
     925: ior
     926: putfield      #28                 // Field bitField0_:I
     929: aload_0
     930: aload_1
     931: invokestatic  #102                // Method org/apache/hadoop/hbase/shaded/protobuf/generated/ReplicationProtos$ReplicationPeer.access$2800:(Lorg/apache/hadoop/hbase/shaded/protobuf/generated/ReplicationProtos$ReplicationPeer;)Ljava/lang/Object;
     934: putfield      #19                 // Field remoteWALDir_:Ljava/lang/Object;
     937: aload_0
     938: invokevirtual #68                 // Method onChanged:()V
     941: aload_0
     942: aload_1
     943: invokestatic  #103                // Method org/apache/hadoop/hbase/shaded/protobuf/generated/ReplicationProtos$ReplicationPeer.access$3400:(Lorg/apache/hadoop/hbase/shaded/protobuf/generated/ReplicationProtos$ReplicationPeer;)Lorg/apache/hbase/thirdparty/com/google/protobuf/UnknownFieldSet;
     946: invokevirtual #104                // Method mergeUnknownFields:(Lorg/apache/hbase/thirdparty/com/google/protobuf/UnknownFieldSet;)Lorg/apache/hadoop/hbase/shaded/protobuf/generated/ReplicationProtos$ReplicationPeer$Builder;
     949: pop
     950: aload_0
     951: invokevirtual #68                 // Method onChanged:()V
     954: aload_0
     955: areturn

  public final boolean isInitialized();
    Code:
       0: iconst_0
       1: istore_1
       2: iload_1
       3: aload_0
       4: invokevirtual #105                // Method getDataCount:()I
       7: if_icmpge     29
      10: aload_0
      11: iload_1
      12: invokevirtual #106                // Method getData:(I)Lorg/apache/hadoop/hbase/shaded/protobuf/generated/HBaseProtos$BytesBytesPair;
      15: invokevirtual #107                // Method org/apache/hadoop/hbase/shaded/protobuf/generated/HBaseProtos$BytesBytesPair.isInitialized:()Z
      18: ifne          23
      21: iconst_0
      22: ireturn
      23: iinc          1, 1
      26: goto          2
      29: iconst_0
      30: istore_1
      31: iload_1
      32: aload_0
      33: invokevirtual #108                // Method getConfigurationCount:()I
      36: if_icmpge     58
      39: aload_0
      40: iload_1
      41: invokevirtual #109                // Method getConfiguration:(I)Lorg/apache/hadoop/hbase/shaded/protobuf/generated/HBaseProtos$NameStringPair;
      44: invokevirtual #110                // Method org/apache/hadoop/hbase/shaded/protobuf/generated/HBaseProtos$NameStringPair.isInitialized:()Z
      47: ifne          52
      50: iconst_0
      51: ireturn
      52: iinc          1, 1
      55: goto          31
      58: iconst_0
      59: istore_1
      60: iload_1
      61: aload_0
      62: invokevirtual #111                // Method getTableCfsCount:()I
      65: if_icmpge     87
      68: aload_0
      69: iload_1
      70: invokevirtual #112                // Method getTableCfs:(I)Lorg/apache/hadoop/hbase/shaded/protobuf/generated/ReplicationProtos$TableCF;
      73: invokevirtual #113                // Method org/apache/hadoop/hbase/shaded/protobuf/generated/ReplicationProtos$TableCF.isInitialized:()Z
      76: ifne          81
      79: iconst_0
      80: ireturn
      81: iinc          1, 1
      84: goto          60
      87: iconst_0
      88: istore_1
      89: iload_1
      90: aload_0
      91: invokevirtual #114                // Method getExcludeTableCfsCount:()I
      94: if_icmpge     116
      97: aload_0
      98: iload_1
      99: invokevirtual #115                // Method getExcludeTableCfs:(I)Lorg/apache/hadoop/hbase/shaded/protobuf/generated/ReplicationProtos$TableCF;
     102: invokevirtual #113                // Method org/apache/hadoop/hbase/shaded/protobuf/generated/ReplicationProtos$TableCF.isInitialized:()Z
     105: ifne          110
     108: iconst_0
     109: ireturn
     110: iinc          1, 1
     113: goto          89
     116: iconst_1
     117: ireturn

  public org.apache.hadoop.hbase.shaded.protobuf.generated.ReplicationProtos$ReplicationPeer$Builder mergeFrom(org.apache.hbase.thirdparty.com.google.protobuf.CodedInputStream, org.apache.hbase.thirdparty.com.google.protobuf.ExtensionRegistryLite) throws java.io.IOException;
    Code:
       0: aconst_null
       1: astore_3
       2: getstatic     #116                // Field org/apache/hadoop/hbase/shaded/protobuf/generated/ReplicationProtos$ReplicationPeer.PARSER:Lorg/apache/hbase/thirdparty/com/google/protobuf/Parser;
       5: aload_1
       6: aload_2
       7: invokeinterface #117,  3          // InterfaceMethod org/apache/hbase/thirdparty/com/google/protobuf/Parser.parsePartialFrom:(Lorg/apache/hbase/thirdparty/com/google/protobuf/CodedInputStream;Lorg/apache/hbase/thirdparty/com/google/protobuf/ExtensionRegistryLite;)Ljava/lang/Object;
      12: checkcast     #5                  // class org/apache/hadoop/hbase/shaded/protobuf/generated/ReplicationProtos$ReplicationPeer
      15: astore_3
      16: aload_3
      17: ifnull        61
      20: aload_0
      21: aload_3
      22: invokevirtual #64                 // Method mergeFrom:(Lorg/apache/hadoop/hbase/shaded/protobuf/generated/ReplicationProtos$ReplicationPeer;)Lorg/apache/hadoop/hbase/shaded/protobuf/generated/ReplicationProtos$ReplicationPeer$Builder;
      25: pop
      26: goto          61
      29: astore        4
      31: aload         4
      33: invokevirtual #119                // Method org/apache/hbase/thirdparty/com/google/protobuf/InvalidProtocolBufferException.getUnfinishedMessage:()Lorg/apache/hbase/thirdparty/com/google/protobuf/MessageLite;
      36: checkcast     #5                  // class org/apache/hadoop/hbase/shaded/protobuf/generated/ReplicationProtos$ReplicationPeer
      39: astore_3
      40: aload         4
      42: invokevirtual #120                // Method org/apache/hbase/thirdparty/com/google/protobuf/InvalidProtocolBufferException.unwrapIOException:()Ljava/io/IOException;
      45: athrow
      46: astore        5
      48: aload_3
      49: ifnull        58
      52: aload_0
      53: aload_3
      54: invokevirtual #64                 // Method mergeFrom:(Lorg/apache/hadoop/hbase/shaded/protobuf/generated/ReplicationProtos$ReplicationPeer;)Lorg/apache/hadoop/hbase/shaded/protobuf/generated/ReplicationProtos$ReplicationPeer$Builder;
      57: pop
      58: aload         5
      60: athrow
      61: aload_0
      62: areturn
    Exception table:
       from    to  target type
           2    16    29   Class org/apache/hbase/thirdparty/com/google/protobuf/InvalidProtocolBufferException
           2    16    46   any
          29    48    46   any

  public boolean hasClusterkey();
    Code:
       0: aload_0
       1: getfield      #28                 // Field bitField0_:I
       4: iconst_1
       5: iand
       6: iconst_1
       7: if_icmpne     14
      10: iconst_1
      11: goto          15
      14: iconst_0
      15: ireturn

  public java.lang.String getClusterkey();
    Code:
       0: aload_0
       1: getfield      #10                 // Field clusterkey_:Ljava/lang/Object;
       4: astore_1
       5: aload_1
       6: instanceof    #121                // class java/lang/String
       9: ifne          36
      12: aload_1
      13: checkcast     #122                // class org/apache/hbase/thirdparty/com/google/protobuf/ByteString
      16: astore_2
      17: aload_2
      18: invokevirtual #123                // Method org/apache/hbase/thirdparty/com/google/protobuf/ByteString.toStringUtf8:()Ljava/lang/String;
      21: astore_3
      22: aload_2
      23: invokevirtual #124                // Method org/apache/hbase/thirdparty/com/google/protobuf/ByteString.isValidUtf8:()Z
      26: ifeq          34
      29: aload_0
      30: aload_3
      31: putfield      #10                 // Field clusterkey_:Ljava/lang/Object;
      34: aload_3
      35: areturn
      36: aload_1
      37: checkcast     #121                // class java/lang/String
      40: areturn

  public org.apache.hbase.thirdparty.com.google.protobuf.ByteString getClusterkeyBytes();
    Code:
       0: aload_0
       1: getfield      #10                 // Field clusterkey_:Ljava/lang/Object;
       4: astore_1
       5: aload_1
       6: instanceof    #121                // class java/lang/String
       9: ifeq          27
      12: aload_1
      13: checkcast     #121                // class java/lang/String
      16: invokestatic  #125                // Method org/apache/hbase/thirdparty/com/google/protobuf/ByteString.copyFromUtf8:(Ljava/lang/String;)Lorg/apache/hbase/thirdparty/com/google/protobuf/ByteString;
      19: astore_2
      20: aload_0
      21: aload_2
      22: putfield      #10                 // Field clusterkey_:Ljava/lang/Object;
      25: aload_2
      26: areturn
      27: aload_1
      28: checkcast     #122                // class org/apache/hbase/thirdparty/com/google/protobuf/ByteString
      31: areturn

  public org.apache.hadoop.hbase.shaded.protobuf.generated.ReplicationProtos$ReplicationPeer$Builder setClusterkey(java.lang.String);
    Code:
       0: aload_1
       1: ifnonnull     12
       4: new           #126                // class java/lang/NullPointerException
       7: dup
       8: invokespecial #127                // Method java/lang/NullPointerException."<init>":()V
      11: athrow
      12: aload_0
      13: dup
      14: getfield      #28                 // Field bitField0_:I
      17: iconst_1
      18: ior
      19: putfield      #28                 // Field bitField0_:I
      22: aload_0
      23: aload_1
      24: putfield      #10                 // Field clusterkey_:Ljava/lang/Object;
      27: aload_0
      28: invokevirtual #68                 // Method onChanged:()V
      31: aload_0
      32: areturn

  public org.apache.hadoop.hbase.shaded.protobuf.generated.ReplicationProtos$ReplicationPeer$Builder clearClusterkey();
    Code:
       0: aload_0
       1: aload_0
       2: getfield      #28                 // Field bitField0_:I
       5: bipush        -2
       7: iand
       8: putfield      #28                 // Field bitField0_:I
      11: aload_0
      12: invokestatic  #37                 // Method org/apache/hadoop/hbase/shaded/protobuf/generated/ReplicationProtos$ReplicationPeer.getDefaultInstance:()Lorg/apache/hadoop/hbase/shaded/protobuf/generated/ReplicationProtos$ReplicationPeer;
      15: invokevirtual #128                // Method org/apache/hadoop/hbase/shaded/protobuf/generated/ReplicationProtos$ReplicationPeer.getClusterkey:()Ljava/lang/String;
      18: putfield      #10                 // Field clusterkey_:Ljava/lang/Object;
      21: aload_0
      22: invokevirtual #68                 // Method onChanged:()V
      25: aload_0
      26: areturn

  public org.apache.hadoop.hbase.shaded.protobuf.generated.ReplicationProtos$ReplicationPeer$Builder setClusterkeyBytes(org.apache.hbase.thirdparty.com.google.protobuf.ByteString);
    Code:
       0: aload_1
       1: ifnonnull     12
       4: new           #126                // class java/lang/NullPointerException
       7: dup
       8: invokespecial #127                // Method java/lang/NullPointerException."<init>":()V
      11: athrow
      12: aload_0
      13: dup
      14: getfield      #28                 // Field bitField0_:I
      17: iconst_1
      18: ior
      19: putfield      #28                 // Field bitField0_:I
      22: aload_0
      23: aload_1
      24: putfield      #10                 // Field clusterkey_:Ljava/lang/Object;
      27: aload_0
      28: invokevirtual #68                 // Method onChanged:()V
      31: aload_0
      32: areturn

  public boolean hasReplicationEndpointImpl();
    Code:
       0: aload_0
       1: getfield      #28                 // Field bitField0_:I
       4: iconst_2
       5: iand
       6: iconst_2
       7: if_icmpne     14
      10: iconst_1
      11: goto          15
      14: iconst_0
      15: ireturn

  public java.lang.String getReplicationEndpointImpl();
    Code:
       0: aload_0
       1: getfield      #11                 // Field replicationEndpointImpl_:Ljava/lang/Object;
       4: astore_1
       5: aload_1
       6: instanceof    #121                // class java/lang/String
       9: ifne          36
      12: aload_1
      13: checkcast     #122                // class org/apache/hbase/thirdparty/com/google/protobuf/ByteString
      16: astore_2
      17: aload_2
      18: invokevirtual #123                // Method org/apache/hbase/thirdparty/com/google/protobuf/ByteString.toStringUtf8:()Ljava/lang/String;
      21: astore_3
      22: aload_2
      23: invokevirtual #124                // Method org/apache/hbase/thirdparty/com/google/protobuf/ByteString.isValidUtf8:()Z
      26: ifeq          34
      29: aload_0
      30: aload_3
      31: putfield      #11                 // Field replicationEndpointImpl_:Ljava/lang/Object;
      34: aload_3
      35: areturn
      36: aload_1
      37: checkcast     #121                // class java/lang/String
      40: areturn

  public org.apache.hbase.thirdparty.com.google.protobuf.ByteString getReplicationEndpointImplBytes();
    Code:
       0: aload_0
       1: getfield      #11                 // Field replicationEndpointImpl_:Ljava/lang/Object;
       4: astore_1
       5: aload_1
       6: instanceof    #121                // class java/lang/String
       9: ifeq          27
      12: aload_1
      13: checkcast     #121                // class java/lang/String
      16: invokestatic  #125                // Method org/apache/hbase/thirdparty/com/google/protobuf/ByteString.copyFromUtf8:(Ljava/lang/String;)Lorg/apache/hbase/thirdparty/com/google/protobuf/ByteString;
      19: astore_2
      20: aload_0
      21: aload_2
      22: putfield      #11                 // Field replicationEndpointImpl_:Ljava/lang/Object;
      25: aload_2
      26: areturn
      27: aload_1
      28: checkcast     #122                // class org/apache/hbase/thirdparty/com/google/protobuf/ByteString
      31: areturn

  public org.apache.hadoop.hbase.shaded.protobuf.generated.ReplicationProtos$ReplicationPeer$Builder setReplicationEndpointImpl(java.lang.String);
    Code:
       0: aload_1
       1: ifnonnull     12
       4: new           #126                // class java/lang/NullPointerException
       7: dup
       8: invokespecial #127                // Method java/lang/NullPointerException."<init>":()V
      11: athrow
      12: aload_0
      13: dup
      14: getfield      #28                 // Field bitField0_:I
      17: iconst_2
      18: ior
      19: putfield      #28                 // Field bitField0_:I
      22: aload_0
      23: aload_1
      24: putfield      #11                 // Field replicationEndpointImpl_:Ljava/lang/Object;
      27: aload_0
      28: invokevirtual #68                 // Method onChanged:()V
      31: aload_0
      32: areturn

  public org.apache.hadoop.hbase.shaded.protobuf.generated.ReplicationProtos$ReplicationPeer$Builder clearReplicationEndpointImpl();
    Code:
       0: aload_0
       1: aload_0
       2: getfield      #28                 // Field bitField0_:I
       5: bipush        -3
       7: iand
       8: putfield      #28                 // Field bitField0_:I
      11: aload_0
      12: invokestatic  #37                 // Method org/apache/hadoop/hbase/shaded/protobuf/generated/ReplicationProtos$ReplicationPeer.getDefaultInstance:()Lorg/apache/hadoop/hbase/shaded/protobuf/generated/ReplicationProtos$ReplicationPeer;
      15: invokevirtual #129                // Method org/apache/hadoop/hbase/shaded/protobuf/generated/ReplicationProtos$ReplicationPeer.getReplicationEndpointImpl:()Ljava/lang/String;
      18: putfield      #11                 // Field replicationEndpointImpl_:Ljava/lang/Object;
      21: aload_0
      22: invokevirtual #68                 // Method onChanged:()V
      25: aload_0
      26: areturn

  public org.apache.hadoop.hbase.shaded.protobuf.generated.ReplicationProtos$ReplicationPeer$Builder setReplicationEndpointImplBytes(org.apache.hbase.thirdparty.com.google.protobuf.ByteString);
    Code:
       0: aload_1
       1: ifnonnull     12
       4: new           #126                // class java/lang/NullPointerException
       7: dup
       8: invokespecial #127                // Method java/lang/NullPointerException."<init>":()V
      11: athrow
      12: aload_0
      13: dup
      14: getfield      #28                 // Field bitField0_:I
      17: iconst_2
      18: ior
      19: putfield      #28                 // Field bitField0_:I
      22: aload_0
      23: aload_1
      24: putfield      #11                 // Field replicationEndpointImpl_:Ljava/lang/Object;
      27: aload_0
      28: invokevirtual #68                 // Method onChanged:()V
      31: aload_0
      32: areturn

  public java.util.List<org.apache.hadoop.hbase.shaded.protobuf.generated.HBaseProtos$BytesBytesPair> getDataList();
    Code:
       0: aload_0
       1: getfield      #29                 // Field dataBuilder_:Lorg/apache/hbase/thirdparty/com/google/protobuf/RepeatedFieldBuilderV3;
       4: ifnonnull     15
       7: aload_0
       8: getfield      #13                 // Field data_:Ljava/util/List;
      11: invokestatic  #44                 // Method java/util/Collections.unmodifiableList:(Ljava/util/List;)Ljava/util/List;
      14: areturn
      15: aload_0
      16: getfield      #29                 // Field dataBuilder_:Lorg/apache/hbase/thirdparty/com/google/protobuf/RepeatedFieldBuilderV3;
      19: invokevirtual #132                // Method org/apache/hbase/thirdparty/com/google/protobuf/RepeatedFieldBuilderV3.getMessageList:()Ljava/util/List;
      22: areturn

  public int getDataCount();
    Code:
       0: aload_0
       1: getfield      #29                 // Field dataBuilder_:Lorg/apache/hbase/thirdparty/com/google/protobuf/RepeatedFieldBuilderV3;
       4: ifnonnull     17
       7: aload_0
       8: getfield      #13                 // Field data_:Ljava/util/List;
      11: invokeinterface #133,  1          // InterfaceMethod java/util/List.size:()I
      16: ireturn
      17: aload_0
      18: getfield      #29                 // Field dataBuilder_:Lorg/apache/hbase/thirdparty/com/google/protobuf/RepeatedFieldBuilderV3;
      21: invokevirtual #134                // Method org/apache/hbase/thirdparty/com/google/protobuf/RepeatedFieldBuilderV3.getCount:()I
      24: ireturn

  public org.apache.hadoop.hbase.shaded.protobuf.generated.HBaseProtos$BytesBytesPair getData(int);
    Code:
       0: aload_0
       1: getfield      #29                 // Field dataBuilder_:Lorg/apache/hbase/thirdparty/com/google/protobuf/RepeatedFieldBuilderV3;
       4: ifnonnull     21
       7: aload_0
       8: getfield      #13                 // Field data_:Ljava/util/List;
      11: iload_1
      12: invokeinterface #135,  2          // InterfaceMethod java/util/List.get:(I)Ljava/lang/Object;
      17: checkcast     #136                // class org/apache/hadoop/hbase/shaded/protobuf/generated/HBaseProtos$BytesBytesPair
      20: areturn
      21: aload_0
      22: getfield      #29                 // Field dataBuilder_:Lorg/apache/hbase/thirdparty/com/google/protobuf/RepeatedFieldBuilderV3;
      25: iload_1
      26: invokevirtual #137                // Method org/apache/hbase/thirdparty/com/google/protobuf/RepeatedFieldBuilderV3.getMessage:(I)Lorg/apache/hbase/thirdparty/com/google/protobuf/AbstractMessage;
      29: checkcast     #136                // class org/apache/hadoop/hbase/shaded/protobuf/generated/HBaseProtos$BytesBytesPair
      32: areturn

  public org.apache.hadoop.hbase.shaded.protobuf.generated.ReplicationProtos$ReplicationPeer$Builder setData(int, org.apache.hadoop.hbase.shaded.protobuf.generated.HBaseProtos$BytesBytesPair);
    Code:
       0: aload_0
       1: getfield      #29                 // Field dataBuilder_:Lorg/apache/hbase/thirdparty/com/google/protobuf/RepeatedFieldBuilderV3;
       4: ifnonnull     42
       7: aload_2
       8: ifnonnull     19
      11: new           #126                // class java/lang/NullPointerException
      14: dup
      15: invokespecial #127                // Method java/lang/NullPointerException."<init>":()V
      18: athrow
      19: aload_0
      20: invokespecial #73                 // Method ensureDataIsMutable:()V
      23: aload_0
      24: getfield      #13                 // Field data_:Ljava/util/List;
      27: iload_1
      28: aload_2
      29: invokeinterface #138,  3          // InterfaceMethod java/util/List.set:(ILjava/lang/Object;)Ljava/lang/Object;
      34: pop
      35: aload_0
      36: invokevirtual #68                 // Method onChanged:()V
      39: goto          52
      42: aload_0
      43: getfield      #29                 // Field dataBuilder_:Lorg/apache/hbase/thirdparty/com/google/protobuf/RepeatedFieldBuilderV3;
      46: iload_1
      47: aload_2
      48: invokevirtual #139                // Method org/apache/hbase/thirdparty/com/google/protobuf/RepeatedFieldBuilderV3.setMessage:(ILorg/apache/hbase/thirdparty/com/google/protobuf/AbstractMessage;)Lorg/apache/hbase/thirdparty/com/google/protobuf/RepeatedFieldBuilderV3;
      51: pop
      52: aload_0
      53: areturn

  public org.apache.hadoop.hbase.shaded.protobuf.generated.ReplicationProtos$ReplicationPeer$Builder setData(int, org.apache.hadoop.hbase.shaded.protobuf.generated.HBaseProtos$BytesBytesPair$Builder);
    Code:
       0: aload_0
       1: getfield      #29                 // Field dataBuilder_:Lorg/apache/hbase/thirdparty/com/google/protobuf/RepeatedFieldBuilderV3;
       4: ifnonnull     33
       7: aload_0
       8: invokespecial #73                 // Method ensureDataIsMutable:()V
      11: aload_0
      12: getfield      #13                 // Field data_:Ljava/util/List;
      15: iload_1
      16: aload_2
      17: invokevirtual #140                // Method org/apache/hadoop/hbase/shaded/protobuf/generated/HBaseProtos$BytesBytesPair$Builder.build:()Lorg/apache/hadoop/hbase/shaded/protobuf/generated/HBaseProtos$BytesBytesPair;
      20: invokeinterface #138,  3          // InterfaceMethod java/util/List.set:(ILjava/lang/Object;)Ljava/lang/Object;
      25: pop
      26: aload_0
      27: invokevirtual #68                 // Method onChanged:()V
      30: goto          46
      33: aload_0
      34: getfield      #29                 // Field dataBuilder_:Lorg/apache/hbase/thirdparty/com/google/protobuf/RepeatedFieldBuilderV3;
      37: iload_1
      38: aload_2
      39: invokevirtual #140                // Method org/apache/hadoop/hbase/shaded/protobuf/generated/HBaseProtos$BytesBytesPair$Builder.build:()Lorg/apache/hadoop/hbase/shaded/protobuf/generated/HBaseProtos$BytesBytesPair;
      42: invokevirtual #139                // Method org/apache/hbase/thirdparty/com/google/protobuf/RepeatedFieldBuilderV3.setMessage:(ILorg/apache/hbase/thirdparty/com/google/protobuf/AbstractMessage;)Lorg/apache/hbase/thirdparty/com/google/protobuf/RepeatedFieldBuilderV3;
      45: pop
      46: aload_0
      47: areturn

  public org.apache.hadoop.hbase.shaded.protobuf.generated.ReplicationProtos$ReplicationPeer$Builder addData(org.apache.hadoop.hbase.shaded.protobuf.generated.HBaseProtos$BytesBytesPair);
    Code:
       0: aload_0
       1: getfield      #29                 // Field dataBuilder_:Lorg/apache/hbase/thirdparty/com/google/protobuf/RepeatedFieldBuilderV3;
       4: ifnonnull     41
       7: aload_1
       8: ifnonnull     19
      11: new           #126                // class java/lang/NullPointerException
      14: dup
      15: invokespecial #127                // Method java/lang/NullPointerException."<init>":()V
      18: athrow
      19: aload_0
      20: invokespecial #73                 // Method ensureDataIsMutable:()V
      23: aload_0
      24: getfield      #13                 // Field data_:Ljava/util/List;
      27: aload_1
      28: invokeinterface #141,  2          // InterfaceMethod java/util/List.add:(Ljava/lang/Object;)Z
      33: pop
      34: aload_0
      35: invokevirtual #68                 // Method onChanged:()V
      38: goto          50
      41: aload_0
      42: getfield      #29                 // Field dataBuilder_:Lorg/apache/hbase/thirdparty/com/google/protobuf/RepeatedFieldBuilderV3;
      45: aload_1
      46: invokevirtual #142                // Method org/apache/hbase/thirdparty/com/google/protobuf/RepeatedFieldBuilderV3.addMessage:(Lorg/apache/hbase/thirdparty/com/google/protobuf/AbstractMessage;)Lorg/apache/hbase/thirdparty/com/google/protobuf/RepeatedFieldBuilderV3;
      49: pop
      50: aload_0
      51: areturn

  public org.apache.hadoop.hbase.shaded.protobuf.generated.ReplicationProtos$ReplicationPeer$Builder addData(int, org.apache.hadoop.hbase.shaded.protobuf.generated.HBaseProtos$BytesBytesPair);
    Code:
       0: aload_0
       1: getfield      #29                 // Field dataBuilder_:Lorg/apache/hbase/thirdparty/com/google/protobuf/RepeatedFieldBuilderV3;
       4: ifnonnull     41
       7: aload_2
       8: ifnonnull     19
      11: new           #126                // class java/lang/NullPointerException
      14: dup
      15: invokespecial #127                // Method java/lang/NullPointerException."<init>":()V
      18: athrow
      19: aload_0
      20: invokespecial #73                 // Method ensureDataIsMutable:()V
      23: aload_0
      24: getfield      #13                 // Field data_:Ljava/util/List;
      27: iload_1
      28: aload_2
      29: invokeinterface #143,  3          // InterfaceMethod java/util/List.add:(ILjava/lang/Object;)V
      34: aload_0
      35: invokevirtual #68                 // Method onChanged:()V
      38: goto          51
      41: aload_0
      42: getfield      #29                 // Field dataBuilder_:Lorg/apache/hbase/thirdparty/com/google/protobuf/RepeatedFieldBuilderV3;
      45: iload_1
      46: aload_2
      47: invokevirtual #144                // Method org/apache/hbase/thirdparty/com/google/protobuf/RepeatedFieldBuilderV3.addMessage:(ILorg/apache/hbase/thirdparty/com/google/protobuf/AbstractMessage;)Lorg/apache/hbase/thirdparty/com/google/protobuf/RepeatedFieldBuilderV3;
      50: pop
      51: aload_0
      52: areturn

  public org.apache.hadoop.hbase.shaded.protobuf.generated.ReplicationProtos$ReplicationPeer$Builder addData(org.apache.hadoop.hbase.shaded.protobuf.generated.HBaseProtos$BytesBytesPair$Builder);
    Code:
       0: aload_0
       1: getfield      #29                 // Field dataBuilder_:Lorg/apache/hbase/thirdparty/com/google/protobuf/RepeatedFieldBuilderV3;
       4: ifnonnull     32
       7: aload_0
       8: invokespecial #73                 // Method ensureDataIsMutable:()V
      11: aload_0
      12: getfield      #13                 // Field data_:Ljava/util/List;
      15: aload_1
      16: invokevirtual #140                // Method org/apache/hadoop/hbase/shaded/protobuf/generated/HBaseProtos$BytesBytesPair$Builder.build:()Lorg/apache/hadoop/hbase/shaded/protobuf/generated/HBaseProtos$BytesBytesPair;
      19: invokeinterface #141,  2          // InterfaceMethod java/util/List.add:(Ljava/lang/Object;)Z
      24: pop
      25: aload_0
      26: invokevirtual #68                 // Method onChanged:()V
      29: goto          44
      32: aload_0
      33: getfield      #29                 // Field dataBuilder_:Lorg/apache/hbase/thirdparty/com/google/protobuf/RepeatedFieldBuilderV3;
      36: aload_1
      37: invokevirtual #140                // Method org/apache/hadoop/hbase/shaded/protobuf/generated/HBaseProtos$BytesBytesPair$Builder.build:()Lorg/apache/hadoop/hbase/shaded/protobuf/generated/HBaseProtos$BytesBytesPair;
      40: invokevirtual #142                // Method org/apache/hbase/thirdparty/com/google/protobuf/RepeatedFieldBuilderV3.addMessage:(Lorg/apache/hbase/thirdparty/com/google/protobuf/AbstractMessage;)Lorg/apache/hbase/thirdparty/com/google/protobuf/RepeatedFieldBuilderV3;
      43: pop
      44: aload_0
      45: areturn

  public org.apache.hadoop.hbase.shaded.protobuf.generated.ReplicationProtos$ReplicationPeer$Builder addData(int, org.apache.hadoop.hbase.shaded.protobuf.generated.HBaseProtos$BytesBytesPair$Builder);
    Code:
       0: aload_0
       1: getfield      #29                 // Field dataBuilder_:Lorg/apache/hbase/thirdparty/com/google/protobuf/RepeatedFieldBuilderV3;
       4: ifnonnull     32
       7: aload_0
       8: invokespecial #73                 // Method ensureDataIsMutable:()V
      11: aload_0
      12: getfield      #13                 // Field data_:Ljava/util/List;
      15: iload_1
      16: aload_2
      17: invokevirtual #140                // Method org/apache/hadoop/hbase/shaded/protobuf/generated/HBaseProtos$BytesBytesPair$Builder.build:()Lorg/apache/hadoop/hbase/shaded/protobuf/generated/HBaseProtos$BytesBytesPair;
      20: invokeinterface #143,  3          // InterfaceMethod java/util/List.add:(ILjava/lang/Object;)V
      25: aload_0
      26: invokevirtual #68                 // Method onChanged:()V
      29: goto          45
      32: aload_0
      33: getfield      #29                 // Field dataBuilder_:Lorg/apache/hbase/thirdparty/com/google/protobuf/RepeatedFieldBuilderV3;
      36: iload_1
      37: aload_2
      38: invokevirtual #140                // Method org/apache/hadoop/hbase/shaded/protobuf/generated/HBaseProtos$BytesBytesPair$Builder.build:()Lorg/apache/hadoop/hbase/shaded/protobuf/generated/HBaseProtos$BytesBytesPair;
      41: invokevirtual #144                // Method org/apache/hbase/thirdparty/com/google/protobuf/RepeatedFieldBuilderV3.addMessage:(ILorg/apache/hbase/thirdparty/com/google/protobuf/AbstractMessage;)Lorg/apache/hbase/thirdparty/com/google/protobuf/RepeatedFieldBuilderV3;
      44: pop
      45: aload_0
      46: areturn

  public org.apache.hadoop.hbase.shaded.protobuf.generated.ReplicationProtos$ReplicationPeer$Builder addAllData(java.lang.Iterable<? extends org.apache.hadoop.hbase.shaded.protobuf.generated.HBaseProtos$BytesBytesPair>);
    Code:
       0: aload_0
       1: getfield      #29                 // Field dataBuilder_:Lorg/apache/hbase/thirdparty/com/google/protobuf/RepeatedFieldBuilderV3;
       4: ifnonnull     26
       7: aload_0
       8: invokespecial #73                 // Method ensureDataIsMutable:()V
      11: aload_1
      12: aload_0
      13: getfield      #13                 // Field data_:Ljava/util/List;
      16: invokestatic  #145                // Method org/apache/hbase/thirdparty/com/google/protobuf/AbstractMessageLite$Builder.addAll:(Ljava/lang/Iterable;Ljava/util/List;)V
      19: aload_0
      20: invokevirtual #68                 // Method onChanged:()V
      23: goto          35
      26: aload_0
      27: getfield      #29                 // Field dataBuilder_:Lorg/apache/hbase/thirdparty/com/google/protobuf/RepeatedFieldBuilderV3;
      30: aload_1
      31: invokevirtual #78                 // Method org/apache/hbase/thirdparty/com/google/protobuf/RepeatedFieldBuilderV3.addAllMessages:(Ljava/lang/Iterable;)Lorg/apache/hbase/thirdparty/com/google/protobuf/RepeatedFieldBuilderV3;
      34: pop
      35: aload_0
      36: areturn

  public org.apache.hadoop.hbase.shaded.protobuf.generated.ReplicationProtos$ReplicationPeer$Builder clearData();
    Code:
       0: aload_0
       1: getfield      #29                 // Field dataBuilder_:Lorg/apache/hbase/thirdparty/com/google/protobuf/RepeatedFieldBuilderV3;
       4: ifnonnull     32
       7: aload_0
       8: invokestatic  #12                 // Method java/util/Collections.emptyList:()Ljava/util/List;
      11: putfield      #13                 // Field data_:Ljava/util/List;
      14: aload_0
      15: aload_0
      16: getfield      #28                 // Field bitField0_:I
      19: bipush        -5
      21: iand
      22: putfield      #28                 // Field bitField0_:I
      25: aload_0
      26: invokevirtual #68                 // Method onChanged:()V
      29: goto          39
      32: aload_0
      33: getfield      #29                 // Field dataBuilder_:Lorg/apache/hbase/thirdparty/com/google/protobuf/RepeatedFieldBuilderV3;
      36: invokevirtual #30                 // Method org/apache/hbase/thirdparty/com/google/protobuf/RepeatedFieldBuilderV3.clear:()V
      39: aload_0
      40: areturn

  public org.apache.hadoop.hbase.shaded.protobuf.generated.ReplicationProtos$ReplicationPeer$Builder removeData(int);
    Code:
       0: aload_0
       1: getfield      #29                 // Field dataBuilder_:Lorg/apache/hbase/thirdparty/com/google/protobuf/RepeatedFieldBuilderV3;
       4: ifnonnull     29
       7: aload_0
       8: invokespecial #73                 // Method ensureDataIsMutable:()V
      11: aload_0
      12: getfield      #13                 // Field data_:Ljava/util/List;
      15: iload_1
      16: invokeinterface #146,  2          // InterfaceMethod java/util/List.remove:(I)Ljava/lang/Object;
      21: pop
      22: aload_0
      23: invokevirtual #68                 // Method onChanged:()V
      26: goto          37
      29: aload_0
      30: getfield      #29                 // Field dataBuilder_:Lorg/apache/hbase/thirdparty/com/google/protobuf/RepeatedFieldBuilderV3;
      33: iload_1
      34: invokevirtual #147                // Method org/apache/hbase/thirdparty/com/google/protobuf/RepeatedFieldBuilderV3.remove:(I)V
      37: aload_0
      38: areturn

  public org.apache.hadoop.hbase.shaded.protobuf.generated.HBaseProtos$BytesBytesPair$Builder getDataBuilder(int);
    Code:
       0: aload_0
       1: invokespecial #23                 // Method getDataFieldBuilder:()Lorg/apache/hbase/thirdparty/com/google/protobuf/RepeatedFieldBuilderV3;
       4: iload_1
       5: invokevirtual #148                // Method org/apache/hbase/thirdparty/com/google/protobuf/RepeatedFieldBuilderV3.getBuilder:(I)Lorg/apache/hbase/thirdparty/com/google/protobuf/AbstractMessage$Builder;
       8: checkcast     #149                // class org/apache/hadoop/hbase/shaded/protobuf/generated/HBaseProtos$BytesBytesPair$Builder
      11: areturn

  public org.apache.hadoop.hbase.shaded.protobuf.generated.HBaseProtos$BytesBytesPairOrBuilder getDataOrBuilder(int);
    Code:
       0: aload_0
       1: getfield      #29                 // Field dataBuilder_:Lorg/apache/hbase/thirdparty/com/google/protobuf/RepeatedFieldBuilderV3;
       4: ifnonnull     21
       7: aload_0
       8: getfield      #13                 // Field data_:Ljava/util/List;
      11: iload_1
      12: invokeinterface #135,  2          // InterfaceMethod java/util/List.get:(I)Ljava/lang/Object;
      17: checkcast     #150                // class org/apache/hadoop/hbase/shaded/protobuf/generated/HBaseProtos$BytesBytesPairOrBuilder
      20: areturn
      21: aload_0
      22: getfield      #29                 // Field dataBuilder_:Lorg/apache/hbase/thirdparty/com/google/protobuf/RepeatedFieldBuilderV3;
      25: iload_1
      26: invokevirtual #151                // Method org/apache/hbase/thirdparty/com/google/protobuf/RepeatedFieldBuilderV3.getMessageOrBuilder:(I)Lorg/apache/hbase/thirdparty/com/google/protobuf/MessageOrBuilder;
      29: checkcast     #150                // class org/apache/hadoop/hbase/shaded/protobuf/generated/HBaseProtos$BytesBytesPairOrBuilder
      32: areturn

  public java.util.List<? extends org.apache.hadoop.hbase.shaded.protobuf.generated.HBaseProtos$BytesBytesPairOrBuilder> getDataOrBuilderList();
    Code:
       0: aload_0
       1: getfield      #29                 // Field dataBuilder_:Lorg/apache/hbase/thirdparty/com/google/protobuf/RepeatedFieldBuilderV3;
       4: ifnull        15
       7: aload_0
       8: getfield      #29                 // Field dataBuilder_:Lorg/apache/hbase/thirdparty/com/google/protobuf/RepeatedFieldBuilderV3;
      11: invokevirtual #152                // Method org/apache/hbase/thirdparty/com/google/protobuf/RepeatedFieldBuilderV3.getMessageOrBuilderList:()Ljava/util/List;
      14: areturn
      15: aload_0
      16: getfield      #13                 // Field data_:Ljava/util/List;
      19: invokestatic  #44                 // Method java/util/Collections.unmodifiableList:(Ljava/util/List;)Ljava/util/List;
      22: areturn

  public org.apache.hadoop.hbase.shaded.protobuf.generated.HBaseProtos$BytesBytesPair$Builder addDataBuilder();
    Code:
       0: aload_0
       1: invokespecial #23                 // Method getDataFieldBuilder:()Lorg/apache/hbase/thirdparty/com/google/protobuf/RepeatedFieldBuilderV3;
       4: invokestatic  #153                // Method org/apache/hadoop/hbase/shaded/protobuf/generated/HBaseProtos$BytesBytesPair.getDefaultInstance:()Lorg/apache/hadoop/hbase/shaded/protobuf/generated/HBaseProtos$BytesBytesPair;
       7: invokevirtual #154                // Method org/apache/hbase/thirdparty/com/google/protobuf/RepeatedFieldBuilderV3.addBuilder:(Lorg/apache/hbase/thirdparty/com/google/protobuf/AbstractMessage;)Lorg/apache/hbase/thirdparty/com/google/protobuf/AbstractMessage$Builder;
      10: checkcast     #149                // class org/apache/hadoop/hbase/shaded/protobuf/generated/HBaseProtos$BytesBytesPair$Builder
      13: areturn

  public org.apache.hadoop.hbase.shaded.protobuf.generated.HBaseProtos$BytesBytesPair$Builder addDataBuilder(int);
    Code:
       0: aload_0
       1: invokespecial #23                 // Method getDataFieldBuilder:()Lorg/apache/hbase/thirdparty/com/google/protobuf/RepeatedFieldBuilderV3;
       4: iload_1
       5: invokestatic  #153                // Method org/apache/hadoop/hbase/shaded/protobuf/generated/HBaseProtos$BytesBytesPair.getDefaultInstance:()Lorg/apache/hadoop/hbase/shaded/protobuf/generated/HBaseProtos$BytesBytesPair;
       8: invokevirtual #155                // Method org/apache/hbase/thirdparty/com/google/protobuf/RepeatedFieldBuilderV3.addBuilder:(ILorg/apache/hbase/thirdparty/com/google/protobuf/AbstractMessage;)Lorg/apache/hbase/thirdparty/com/google/protobuf/AbstractMessage$Builder;
      11: checkcast     #149                // class org/apache/hadoop/hbase/shaded/protobuf/generated/HBaseProtos$BytesBytesPair$Builder
      14: areturn

  public java.util.List<org.apache.hadoop.hbase.shaded.protobuf.generated.HBaseProtos$BytesBytesPair$Builder> getDataBuilderList();
    Code:
       0: aload_0
       1: invokespecial #23                 // Method getDataFieldBuilder:()Lorg/apache/hbase/thirdparty/com/google/protobuf/RepeatedFieldBuilderV3;
       4: invokevirtual #156                // Method org/apache/hbase/thirdparty/com/google/protobuf/RepeatedFieldBuilderV3.getBuilderList:()Ljava/util/List;
       7: areturn

  public java.util.List<org.apache.hadoop.hbase.shaded.protobuf.generated.HBaseProtos$NameStringPair> getConfigurationList();
    Code:
       0: aload_0
       1: getfield      #31                 // Field configurationBuilder_:Lorg/apache/hbase/thirdparty/com/google/protobuf/RepeatedFieldBuilderV3;
       4: ifnonnull     15
       7: aload_0
       8: getfield      #14                 // Field configuration_:Ljava/util/List;
      11: invokestatic  #44                 // Method java/util/Collections.unmodifiableList:(Ljava/util/List;)Ljava/util/List;
      14: areturn
      15: aload_0
      16: getfield      #31                 // Field configurationBuilder_:Lorg/apache/hbase/thirdparty/com/google/protobuf/RepeatedFieldBuilderV3;
      19: invokevirtual #132                // Method org/apache/hbase/thirdparty/com/google/protobuf/RepeatedFieldBuilderV3.getMessageList:()Ljava/util/List;
      22: areturn

  public int getConfigurationCount();
    Code:
       0: aload_0
       1: getfield      #31                 // Field configurationBuilder_:Lorg/apache/hbase/thirdparty/com/google/protobuf/RepeatedFieldBuilderV3;
       4: ifnonnull     17
       7: aload_0
       8: getfield      #14                 // Field configuration_:Ljava/util/List;
      11: invokeinterface #133,  1          // InterfaceMethod java/util/List.size:()I
      16: ireturn
      17: aload_0
      18: getfield      #31                 // Field configurationBuilder_:Lorg/apache/hbase/thirdparty/com/google/protobuf/RepeatedFieldBuilderV3;
      21: invokevirtual #134                // Method org/apache/hbase/thirdparty/com/google/protobuf/RepeatedFieldBuilderV3.getCount:()I
      24: ireturn

  public org.apache.hadoop.hbase.shaded.protobuf.generated.HBaseProtos$NameStringPair getConfiguration(int);
    Code:
       0: aload_0
       1: getfield      #31                 // Field configurationBuilder_:Lorg/apache/hbase/thirdparty/com/google/protobuf/RepeatedFieldBuilderV3;
       4: ifnonnull     21
       7: aload_0
       8: getfield      #14                 // Field configuration_:Ljava/util/List;
      11: iload_1
      12: invokeinterface #135,  2          // InterfaceMethod java/util/List.get:(I)Ljava/lang/Object;
      17: checkcast     #161                // class org/apache/hadoop/hbase/shaded/protobuf/generated/HBaseProtos$NameStringPair
      20: areturn
      21: aload_0
      22: getfield      #31                 // Field configurationBuilder_:Lorg/apache/hbase/thirdparty/com/google/protobuf/RepeatedFieldBuilderV3;
      25: iload_1
      26: invokevirtual #137                // Method org/apache/hbase/thirdparty/com/google/protobuf/RepeatedFieldBuilderV3.getMessage:(I)Lorg/apache/hbase/thirdparty/com/google/protobuf/AbstractMessage;
      29: checkcast     #161                // class org/apache/hadoop/hbase/shaded/protobuf/generated/HBaseProtos$NameStringPair
      32: areturn

  public org.apache.hadoop.hbase.shaded.protobuf.generated.ReplicationProtos$ReplicationPeer$Builder setConfiguration(int, org.apache.hadoop.hbase.shaded.protobuf.generated.HBaseProtos$NameStringPair);
    Code:
       0: aload_0
       1: getfield      #31                 // Field configurationBuilder_:Lorg/apache/hbase/thirdparty/com/google/protobuf/RepeatedFieldBuilderV3;
       4: ifnonnull     42
       7: aload_2
       8: ifnonnull     19
      11: new           #126                // class java/lang/NullPointerException
      14: dup
      15: invokespecial #127                // Method java/lang/NullPointerException."<init>":()V
      18: athrow
      19: aload_0
      20: invokespecial #80                 // Method ensureConfigurationIsMutable:()V
      23: aload_0
      24: getfield      #14                 // Field configuration_:Ljava/util/List;
      27: iload_1
      28: aload_2
      29: invokeinterface #138,  3          // InterfaceMethod java/util/List.set:(ILjava/lang/Object;)Ljava/lang/Object;
      34: pop
      35: aload_0
      36: invokevirtual #68                 // Method onChanged:()V
      39: goto          52
      42: aload_0
      43: getfield      #31                 // Field configurationBuilder_:Lorg/apache/hbase/thirdparty/com/google/protobuf/RepeatedFieldBuilderV3;
      46: iload_1
      47: aload_2
      48: invokevirtual #139                // Method org/apache/hbase/thirdparty/com/google/protobuf/RepeatedFieldBuilderV3.setMessage:(ILorg/apache/hbase/thirdparty/com/google/protobuf/AbstractMessage;)Lorg/apache/hbase/thirdparty/com/google/protobuf/RepeatedFieldBuilderV3;
      51: pop
      52: aload_0
      53: areturn

  public org.apache.hadoop.hbase.shaded.protobuf.generated.ReplicationProtos$ReplicationPeer$Builder setConfiguration(int, org.apache.hadoop.hbase.shaded.protobuf.generated.HBaseProtos$NameStringPair$Builder);
    Code:
       0: aload_0
       1: getfield      #31                 // Field configurationBuilder_:Lorg/apache/hbase/thirdparty/com/google/protobuf/RepeatedFieldBuilderV3;
       4: ifnonnull     33
       7: aload_0
       8: invokespecial #80                 // Method ensureConfigurationIsMutable:()V
      11: aload_0
      12: getfield      #14                 // Field configuration_:Ljava/util/List;
      15: iload_1
      16: aload_2
      17: invokevirtual #162                // Method org/apache/hadoop/hbase/shaded/protobuf/generated/HBaseProtos$NameStringPair$Builder.build:()Lorg/apache/hadoop/hbase/shaded/protobuf/generated/HBaseProtos$NameStringPair;
      20: invokeinterface #138,  3          // InterfaceMethod java/util/List.set:(ILjava/lang/Object;)Ljava/lang/Object;
      25: pop
      26: aload_0
      27: invokevirtual #68                 // Method onChanged:()V
      30: goto          46
      33: aload_0
      34: getfield      #31                 // Field configurationBuilder_:Lorg/apache/hbase/thirdparty/com/google/protobuf/RepeatedFieldBuilderV3;
      37: iload_1
      38: aload_2
      39: invokevirtual #162                // Method org/apache/hadoop/hbase/shaded/protobuf/generated/HBaseProtos$NameStringPair$Builder.build:()Lorg/apache/hadoop/hbase/shaded/protobuf/generated/HBaseProtos$NameStringPair;
      42: invokevirtual #139                // Method org/apache/hbase/thirdparty/com/google/protobuf/RepeatedFieldBuilderV3.setMessage:(ILorg/apache/hbase/thirdparty/com/google/protobuf/AbstractMessage;)Lorg/apache/hbase/thirdparty/com/google/protobuf/RepeatedFieldBuilderV3;
      45: pop
      46: aload_0
      47: areturn

  public org.apache.hadoop.hbase.shaded.protobuf.generated.ReplicationProtos$ReplicationPeer$Builder addConfiguration(org.apache.hadoop.hbase.shaded.protobuf.generated.HBaseProtos$NameStringPair);
    Code:
       0: aload_0
       1: getfield      #31                 // Field configurationBuilder_:Lorg/apache/hbase/thirdparty/com/google/protobuf/RepeatedFieldBuilderV3;
       4: ifnonnull     41
       7: aload_1
       8: ifnonnull     19
      11: new           #126                // class java/lang/NullPointerException
      14: dup
      15: invokespecial #127                // Method java/lang/NullPointerException."<init>":()V
      18: athrow
      19: aload_0
      20: invokespecial #80                 // Method ensureConfigurationIsMutable:()V
      23: aload_0
      24: getfield      #14                 // Field configuration_:Ljava/util/List;
      27: aload_1
      28: invokeinterface #141,  2          // InterfaceMethod java/util/List.add:(Ljava/lang/Object;)Z
      33: pop
      34: aload_0
      35: invokevirtual #68                 // Method onChanged:()V
      38: goto          50
      41: aload_0
      42: getfield      #31                 // Field configurationBuilder_:Lorg/apache/hbase/thirdparty/com/google/protobuf/RepeatedFieldBuilderV3;
      45: aload_1
      46: invokevirtual #142                // Method org/apache/hbase/thirdparty/com/google/protobuf/RepeatedFieldBuilderV3.addMessage:(Lorg/apache/hbase/thirdparty/com/google/protobuf/AbstractMessage;)Lorg/apache/hbase/thirdparty/com/google/protobuf/RepeatedFieldBuilderV3;
      49: pop
      50: aload_0
      51: areturn

  public org.apache.hadoop.hbase.shaded.protobuf.generated.ReplicationProtos$ReplicationPeer$Builder addConfiguration(int, org.apache.hadoop.hbase.shaded.protobuf.generated.HBaseProtos$NameStringPair);
    Code:
       0: aload_0
       1: getfield      #31                 // Field configurationBuilder_:Lorg/apache/hbase/thirdparty/com/google/protobuf/RepeatedFieldBuilderV3;
       4: ifnonnull     41
       7: aload_2
       8: ifnonnull     19
      11: new           #126                // class java/lang/NullPointerException
      14: dup
      15: invokespecial #127                // Method java/lang/NullPointerException."<init>":()V
      18: athrow
      19: aload_0
      20: invokespecial #80                 // Method ensureConfigurationIsMutable:()V
      23: aload_0
      24: getfield      #14                 // Field configuration_:Ljava/util/List;
      27: iload_1
      28: aload_2
      29: invokeinterface #143,  3          // InterfaceMethod java/util/List.add:(ILjava/lang/Object;)V
      34: aload_0
      35: invokevirtual #68                 // Method onChanged:()V
      38: goto          51
      41: aload_0
      42: getfield      #31                 // Field configurationBuilder_:Lorg/apache/hbase/thirdparty/com/google/protobuf/RepeatedFieldBuilderV3;
      45: iload_1
      46: aload_2
      47: invokevirtual #144                // Method org/apache/hbase/thirdparty/com/google/protobuf/RepeatedFieldBuilderV3.addMessage:(ILorg/apache/hbase/thirdparty/com/google/protobuf/AbstractMessage;)Lorg/apache/hbase/thirdparty/com/google/protobuf/RepeatedFieldBuilderV3;
      50: pop
      51: aload_0
      52: areturn

  public org.apache.hadoop.hbase.shaded.protobuf.generated.ReplicationProtos$ReplicationPeer$Builder addConfiguration(org.apache.hadoop.hbase.shaded.protobuf.generated.HBaseProtos$NameStringPair$Builder);
    Code:
       0: aload_0
       1: getfield      #31                 // Field configurationBuilder_:Lorg/apache/hbase/thirdparty/com/google/protobuf/RepeatedFieldBuilderV3;
       4: ifnonnull     32
       7: aload_0
       8: invokespecial #80                 // Method ensureConfigurationIsMutable:()V
      11: aload_0
      12: getfield      #14                 // Field configuration_:Ljava/util/List;
      15: aload_1
      16: invokevirtual #162                // Method org/apache/hadoop/hbase/shaded/protobuf/generated/HBaseProtos$NameStringPair$Builder.build:()Lorg/apache/hadoop/hbase/shaded/protobuf/generated/HBaseProtos$NameStringPair;
      19: invokeinterface #141,  2          // InterfaceMethod java/util/List.add:(Ljava/lang/Object;)Z
      24: pop
      25: aload_0
      26: invokevirtual #68                 // Method onChanged:()V
      29: goto          44
      32: aload_0
      33: getfield      #31                 // Field configurationBuilder_:Lorg/apache/hbase/thirdparty/com/google/protobuf/RepeatedFieldBuilderV3;
      36: aload_1
      37: invokevirtual #162                // Method org/apache/hadoop/hbase/shaded/protobuf/generated/HBaseProtos$NameStringPair$Builder.build:()Lorg/apache/hadoop/hbase/shaded/protobuf/generated/HBaseProtos$NameStringPair;
      40: invokevirtual #142                // Method org/apache/hbase/thirdparty/com/google/protobuf/RepeatedFieldBuilderV3.addMessage:(Lorg/apache/hbase/thirdparty/com/google/protobuf/AbstractMessage;)Lorg/apache/hbase/thirdparty/com/google/protobuf/RepeatedFieldBuilderV3;
      43: pop
      44: aload_0
      45: areturn

  public org.apache.hadoop.hbase.shaded.protobuf.generated.ReplicationProtos$ReplicationPeer$Builder addConfiguration(int, org.apache.hadoop.hbase.shaded.protobuf.generated.HBaseProtos$NameStringPair$Builder);
    Code:
       0: aload_0
       1: getfield      #31                 // Field configurationBuilder_:Lorg/apache/hbase/thirdparty/com/google/protobuf/RepeatedFieldBuilderV3;
       4: ifnonnull     32
       7: aload_0
       8: invokespecial #80                 // Method ensureConfigurationIsMutable:()V
      11: aload_0
      12: getfield      #14                 // Field configuration_:Ljava/util/List;
      15: iload_1
      16: aload_2
      17: invokevirtual #162                // Method org/apache/hadoop/hbase/shaded/protobuf/generated/HBaseProtos$NameStringPair$Builder.build:()Lorg/apache/hadoop/hbase/shaded/protobuf/generated/HBaseProtos$NameStringPair;
      20: invokeinterface #143,  3          // InterfaceMethod java/util/List.add:(ILjava/lang/Object;)V
      25: aload_0
      26: invokevirtual #68                 // Method onChanged:()V
      29: goto          45
      32: aload_0
      33: getfield      #31                 // Field configurationBuilder_:Lorg/apache/hbase/thirdparty/com/google/protobuf/RepeatedFieldBuilderV3;
      36: iload_1
      37: aload_2
      38: invokevirtual #162                // Method org/apache/hadoop/hbase/shaded/protobuf/generated/HBaseProtos$NameStringPair$Builder.build:()Lorg/apache/hadoop/hbase/shaded/protobuf/generated/HBaseProtos$NameStringPair;
      41: invokevirtual #144                // Method org/apache/hbase/thirdparty/com/google/protobuf/RepeatedFieldBuilderV3.addMessage:(ILorg/apache/hbase/thirdparty/com/google/protobuf/AbstractMessage;)Lorg/apache/hbase/thirdparty/com/google/protobuf/RepeatedFieldBuilderV3;
      44: pop
      45: aload_0
      46: areturn

  public org.apache.hadoop.hbase.shaded.protobuf.generated.ReplicationProtos$ReplicationPeer$Builder addAllConfiguration(java.lang.Iterable<? extends org.apache.hadoop.hbase.shaded.protobuf.generated.HBaseProtos$NameStringPair>);
    Code:
       0: aload_0
       1: getfield      #31                 // Field configurationBuilder_:Lorg/apache/hbase/thirdparty/com/google/protobuf/RepeatedFieldBuilderV3;
       4: ifnonnull     26
       7: aload_0
       8: invokespecial #80                 // Method ensureConfigurationIsMutable:()V
      11: aload_1
      12: aload_0
      13: getfield      #14                 // Field configuration_:Ljava/util/List;
      16: invokestatic  #145                // Method org/apache/hbase/thirdparty/com/google/protobuf/AbstractMessageLite$Builder.addAll:(Ljava/lang/Iterable;Ljava/util/List;)V
      19: aload_0
      20: invokevirtual #68                 // Method onChanged:()V
      23: goto          35
      26: aload_0
      27: getfield      #31                 // Field configurationBuilder_:Lorg/apache/hbase/thirdparty/com/google/protobuf/RepeatedFieldBuilderV3;
      30: aload_1
      31: invokevirtual #78                 // Method org/apache/hbase/thirdparty/com/google/protobuf/RepeatedFieldBuilderV3.addAllMessages:(Ljava/lang/Iterable;)Lorg/apache/hbase/thirdparty/com/google/protobuf/RepeatedFieldBuilderV3;
      34: pop
      35: aload_0
      36: areturn

  public org.apache.hadoop.hbase.shaded.protobuf.generated.ReplicationProtos$ReplicationPeer$Builder clearConfiguration();
    Code:
       0: aload_0
       1: getfield      #31                 // Field configurationBuilder_:Lorg/apache/hbase/thirdparty/com/google/protobuf/RepeatedFieldBuilderV3;
       4: ifnonnull     32
       7: aload_0
       8: invokestatic  #12                 // Method java/util/Collections.emptyList:()Ljava/util/List;
      11: putfield      #14                 // Field configuration_:Ljava/util/List;
      14: aload_0
      15: aload_0
      16: getfield      #28                 // Field bitField0_:I
      19: bipush        -9
      21: iand
      22: putfield      #28                 // Field bitField0_:I
      25: aload_0
      26: invokevirtual #68                 // Method onChanged:()V
      29: goto          39
      32: aload_0
      33: getfield      #31                 // Field configurationBuilder_:Lorg/apache/hbase/thirdparty/com/google/protobuf/RepeatedFieldBuilderV3;
      36: invokevirtual #30                 // Method org/apache/hbase/thirdparty/com/google/protobuf/RepeatedFieldBuilderV3.clear:()V
      39: aload_0
      40: areturn

  public org.apache.hadoop.hbase.shaded.protobuf.generated.ReplicationProtos$ReplicationPeer$Builder removeConfiguration(int);
    Code:
       0: aload_0
       1: getfield      #31                 // Field configurationBuilder_:Lorg/apache/hbase/thirdparty/com/google/protobuf/RepeatedFieldBuilderV3;
       4: ifnonnull     29
       7: aload_0
       8: invokespecial #80                 // Method ensureConfigurationIsMutable:()V
      11: aload_0
      12: getfield      #14                 // Field configuration_:Ljava/util/List;
      15: iload_1
      16: invokeinterface #146,  2          // InterfaceMethod java/util/List.remove:(I)Ljava/lang/Object;
      21: pop
      22: aload_0
      23: invokevirtual #68                 // Method onChanged:()V
      26: goto          37
      29: aload_0
      30: getfield      #31                 // Field configurationBuilder_:Lorg/apache/hbase/thirdparty/com/google/protobuf/RepeatedFieldBuilderV3;
      33: iload_1
      34: invokevirtual #147                // Method org/apache/hbase/thirdparty/com/google/protobuf/RepeatedFieldBuilderV3.remove:(I)V
      37: aload_0
      38: areturn

  public org.apache.hadoop.hbase.shaded.protobuf.generated.HBaseProtos$NameStringPair$Builder getConfigurationBuilder(int);
    Code:
       0: aload_0
       1: invokespecial #24                 // Method getConfigurationFieldBuilder:()Lorg/apache/hbase/thirdparty/com/google/protobuf/RepeatedFieldBuilderV3;
       4: iload_1
       5: invokevirtual #148                // Method org/apache/hbase/thirdparty/com/google/protobuf/RepeatedFieldBuilderV3.getBuilder:(I)Lorg/apache/hbase/thirdparty/com/google/protobuf/AbstractMessage$Builder;
       8: checkcast     #163                // class org/apache/hadoop/hbase/shaded/protobuf/generated/HBaseProtos$NameStringPair$Builder
      11: areturn

  public org.apache.hadoop.hbase.shaded.protobuf.generated.HBaseProtos$NameStringPairOrBuilder getConfigurationOrBuilder(int);
    Code:
       0: aload_0
       1: getfield      #31                 // Field configurationBuilder_:Lorg/apache/hbase/thirdparty/com/google/protobuf/RepeatedFieldBuilderV3;
       4: ifnonnull     21
       7: aload_0
       8: getfield      #14                 // Field configuration_:Ljava/util/List;
      11: iload_1
      12: invokeinterface #135,  2          // InterfaceMethod java/util/List.get:(I)Ljava/lang/Object;
      17: checkcast     #164                // class org/apache/hadoop/hbase/shaded/protobuf/generated/HBaseProtos$NameStringPairOrBuilder
      20: areturn
      21: aload_0
      22: getfield      #31                 // Field configurationBuilder_:Lorg/apache/hbase/thirdparty/com/google/protobuf/RepeatedFieldBuilderV3;
      25: iload_1
      26: invokevirtual #151                // Method org/apache/hbase/thirdparty/com/google/protobuf/RepeatedFieldBuilderV3.getMessageOrBuilder:(I)Lorg/apache/hbase/thirdparty/com/google/protobuf/MessageOrBuilder;
      29: checkcast     #164                // class org/apache/hadoop/hbase/shaded/protobuf/generated/HBaseProtos$NameStringPairOrBuilder
      32: areturn

  public java.util.List<? extends org.apache.hadoop.hbase.shaded.protobuf.generated.HBaseProtos$NameStringPairOrBuilder> getConfigurationOrBuilderList();
    Code:
       0: aload_0
       1: getfield      #31                 // Field configurationBuilder_:Lorg/apache/hbase/thirdparty/com/google/protobuf/RepeatedFieldBuilderV3;
       4: ifnull        15
       7: aload_0
       8: getfield      #31                 // Field configurationBuilder_:Lorg/apache/hbase/thirdparty/com/google/protobuf/RepeatedFieldBuilderV3;
      11: invokevirtual #152                // Method org/apache/hbase/thirdparty/com/google/protobuf/RepeatedFieldBuilderV3.getMessageOrBuilderList:()Ljava/util/List;
      14: areturn
      15: aload_0
      16: getfield      #14                 // Field configuration_:Ljava/util/List;
      19: invokestatic  #44                 // Method java/util/Collections.unmodifiableList:(Ljava/util/List;)Ljava/util/List;
      22: areturn

  public org.apache.hadoop.hbase.shaded.protobuf.generated.HBaseProtos$NameStringPair$Builder addConfigurationBuilder();
    Code:
       0: aload_0
       1: invokespecial #24                 // Method getConfigurationFieldBuilder:()Lorg/apache/hbase/thirdparty/com/google/protobuf/RepeatedFieldBuilderV3;
       4: invokestatic  #165                // Method org/apache/hadoop/hbase/shaded/protobuf/generated/HBaseProtos$NameStringPair.getDefaultInstance:()Lorg/apache/hadoop/hbase/shaded/protobuf/generated/HBaseProtos$NameStringPair;
       7: invokevirtual #154                // Method org/apache/hbase/thirdparty/com/google/protobuf/RepeatedFieldBuilderV3.addBuilder:(Lorg/apache/hbase/thirdparty/com/google/protobuf/AbstractMessage;)Lorg/apache/hbase/thirdparty/com/google/protobuf/AbstractMessage$Builder;
      10: checkcast     #163                // class org/apache/hadoop/hbase/shaded/protobuf/generated/HBaseProtos$NameStringPair$Builder
      13: areturn

  public org.apache.hadoop.hbase.shaded.protobuf.generated.HBaseProtos$NameStringPair$Builder addConfigurationBuilder(int);
    Code:
       0: aload_0
       1: invokespecial #24                 // Method getConfigurationFieldBuilder:()Lorg/apache/hbase/thirdparty/com/google/protobuf/RepeatedFieldBuilderV3;
       4: iload_1
       5: invokestatic  #165                // Method org/apache/hadoop/hbase/shaded/protobuf/generated/HBaseProtos$NameStringPair.getDefaultInstance:()Lorg/apache/hadoop/hbase/shaded/protobuf/generated/HBaseProtos$NameStringPair;
       8: invokevirtual #155                // Method org/apache/hbase/thirdparty/com/google/protobuf/RepeatedFieldBuilderV3.addBuilder:(ILorg/apache/hbase/thirdparty/com/google/protobuf/AbstractMessage;)Lorg/apache/hbase/thirdparty/com/google/protobuf/AbstractMessage$Builder;
      11: checkcast     #163                // class org/apache/hadoop/hbase/shaded/protobuf/generated/HBaseProtos$NameStringPair$Builder
      14: areturn

  public java.util.List<org.apache.hadoop.hbase.shaded.protobuf.generated.HBaseProtos$NameStringPair$Builder> getConfigurationBuilderList();
    Code:
       0: aload_0
       1: invokespecial #24                 // Method getConfigurationFieldBuilder:()Lorg/apache/hbase/thirdparty/com/google/protobuf/RepeatedFieldBuilderV3;
       4: invokevirtual #156                // Method org/apache/hbase/thirdparty/com/google/protobuf/RepeatedFieldBuilderV3.getBuilderList:()Ljava/util/List;
       7: areturn

  public java.util.List<org.apache.hadoop.hbase.shaded.protobuf.generated.ReplicationProtos$TableCF> getTableCfsList();
    Code:
       0: aload_0
       1: getfield      #32                 // Field tableCfsBuilder_:Lorg/apache/hbase/thirdparty/com/google/protobuf/RepeatedFieldBuilderV3;
       4: ifnonnull     15
       7: aload_0
       8: getfield      #15                 // Field tableCfs_:Ljava/util/List;
      11: invokestatic  #44                 // Method java/util/Collections.unmodifiableList:(Ljava/util/List;)Ljava/util/List;
      14: areturn
      15: aload_0
      16: getfield      #32                 // Field tableCfsBuilder_:Lorg/apache/hbase/thirdparty/com/google/protobuf/RepeatedFieldBuilderV3;
      19: invokevirtual #132                // Method org/apache/hbase/thirdparty/com/google/protobuf/RepeatedFieldBuilderV3.getMessageList:()Ljava/util/List;
      22: areturn

  public int getTableCfsCount();
    Code:
       0: aload_0
       1: getfield      #32                 // Field tableCfsBuilder_:Lorg/apache/hbase/thirdparty/com/google/protobuf/RepeatedFieldBuilderV3;
       4: ifnonnull     17
       7: aload_0
       8: getfield      #15                 // Field tableCfs_:Ljava/util/List;
      11: invokeinterface #133,  1          // InterfaceMethod java/util/List.size:()I
      16: ireturn
      17: aload_0
      18: getfield      #32                 // Field tableCfsBuilder_:Lorg/apache/hbase/thirdparty/com/google/protobuf/RepeatedFieldBuilderV3;
      21: invokevirtual #134                // Method org/apache/hbase/thirdparty/com/google/protobuf/RepeatedFieldBuilderV3.getCount:()I
      24: ireturn

  public org.apache.hadoop.hbase.shaded.protobuf.generated.ReplicationProtos$TableCF getTableCfs(int);
    Code:
       0: aload_0
       1: getfield      #32                 // Field tableCfsBuilder_:Lorg/apache/hbase/thirdparty/com/google/protobuf/RepeatedFieldBuilderV3;
       4: ifnonnull     21
       7: aload_0
       8: getfield      #15                 // Field tableCfs_:Ljava/util/List;
      11: iload_1
      12: invokeinterface #135,  2          // InterfaceMethod java/util/List.get:(I)Ljava/lang/Object;
      17: checkcast     #166                // class org/apache/hadoop/hbase/shaded/protobuf/generated/ReplicationProtos$TableCF
      20: areturn
      21: aload_0
      22: getfield      #32                 // Field tableCfsBuilder_:Lorg/apache/hbase/thirdparty/com/google/protobuf/RepeatedFieldBuilderV3;
      25: iload_1
      26: invokevirtual #137                // Method org/apache/hbase/thirdparty/com/google/protobuf/RepeatedFieldBuilderV3.getMessage:(I)Lorg/apache/hbase/thirdparty/com/google/protobuf/AbstractMessage;
      29: checkcast     #166                // class org/apache/hadoop/hbase/shaded/protobuf/generated/ReplicationProtos$TableCF
      32: areturn

  public org.apache.hadoop.hbase.shaded.protobuf.generated.ReplicationProtos$ReplicationPeer$Builder setTableCfs(int, org.apache.hadoop.hbase.shaded.protobuf.generated.ReplicationProtos$TableCF);
    Code:
       0: aload_0
       1: getfield      #32                 // Field tableCfsBuilder_:Lorg/apache/hbase/thirdparty/com/google/protobuf/RepeatedFieldBuilderV3;
       4: ifnonnull     42
       7: aload_2
       8: ifnonnull     19
      11: new           #126                // class java/lang/NullPointerException
      14: dup
      15: invokespecial #127                // Method java/lang/NullPointerException."<init>":()V
      18: athrow
      19: aload_0
      20: invokespecial #83                 // Method ensureTableCfsIsMutable:()V
      23: aload_0
      24: getfield      #15                 // Field tableCfs_:Ljava/util/List;
      27: iload_1
      28: aload_2
      29: invokeinterface #138,  3          // InterfaceMethod java/util/List.set:(ILjava/lang/Object;)Ljava/lang/Object;
      34: pop
      35: aload_0
      36: invokevirtual #68                 // Method onChanged:()V
      39: goto          52
      42: aload_0
      43: getfield      #32                 // Field tableCfsBuilder_:Lorg/apache/hbase/thirdparty/com/google/protobuf/RepeatedFieldBuilderV3;
      46: iload_1
      47: aload_2
      48: invokevirtual #139                // Method org/apache/hbase/thirdparty/com/google/protobuf/RepeatedFieldBuilderV3.setMessage:(ILorg/apache/hbase/thirdparty/com/google/protobuf/AbstractMessage;)Lorg/apache/hbase/thirdparty/com/google/protobuf/RepeatedFieldBuilderV3;
      51: pop
      52: aload_0
      53: areturn

  public org.apache.hadoop.hbase.shaded.protobuf.generated.ReplicationProtos$ReplicationPeer$Builder setTableCfs(int, org.apache.hadoop.hbase.shaded.protobuf.generated.ReplicationProtos$TableCF$Builder);
    Code:
       0: aload_0
       1: getfield      #32                 // Field tableCfsBuilder_:Lorg/apache/hbase/thirdparty/com/google/protobuf/RepeatedFieldBuilderV3;
       4: ifnonnull     33
       7: aload_0
       8: invokespecial #83                 // Method ensureTableCfsIsMutable:()V
      11: aload_0
      12: getfield      #15                 // Field tableCfs_:Ljava/util/List;
      15: iload_1
      16: aload_2
      17: invokevirtual #167                // Method org/apache/hadoop/hbase/shaded/protobuf/generated/ReplicationProtos$TableCF$Builder.build:()Lorg/apache/hadoop/hbase/shaded/protobuf/generated/ReplicationProtos$TableCF;
      20: invokeinterface #138,  3          // InterfaceMethod java/util/List.set:(ILjava/lang/Object;)Ljava/lang/Object;
      25: pop
      26: aload_0
      27: invokevirtual #68                 // Method onChanged:()V
      30: goto          46
      33: aload_0
      34: getfield      #32                 // Field tableCfsBuilder_:Lorg/apache/hbase/thirdparty/com/google/protobuf/RepeatedFieldBuilderV3;
      37: iload_1
      38: aload_2
      39: invokevirtual #167                // Method org/apache/hadoop/hbase/shaded/protobuf/generated/ReplicationProtos$TableCF$Builder.build:()Lorg/apache/hadoop/hbase/shaded/protobuf/generated/ReplicationProtos$TableCF;
      42: invokevirtual #139                // Method org/apache/hbase/thirdparty/com/google/protobuf/RepeatedFieldBuilderV3.setMessage:(ILorg/apache/hbase/thirdparty/com/google/protobuf/AbstractMessage;)Lorg/apache/hbase/thirdparty/com/google/protobuf/RepeatedFieldBuilderV3;
      45: pop
      46: aload_0
      47: areturn

  public org.apache.hadoop.hbase.shaded.protobuf.generated.ReplicationProtos$ReplicationPeer$Builder addTableCfs(org.apache.hadoop.hbase.shaded.protobuf.generated.ReplicationProtos$TableCF);
    Code:
       0: aload_0
       1: getfield      #32                 // Field tableCfsBuilder_:Lorg/apache/hbase/thirdparty/com/google/protobuf/RepeatedFieldBuilderV3;
       4: ifnonnull     41
       7: aload_1
       8: ifnonnull     19
      11: new           #126                // class java/lang/NullPointerException
      14: dup
      15: invokespecial #127                // Method java/lang/NullPointerException."<init>":()V
      18: athrow
      19: aload_0
      20: invokespecial #83                 // Method ensureTableCfsIsMutable:()V
      23: aload_0
      24: getfield      #15                 // Field tableCfs_:Ljava/util/List;
      27: aload_1
      28: invokeinterface #141,  2          // InterfaceMethod java/util/List.add:(Ljava/lang/Object;)Z
      33: pop
      34: aload_0
      35: invokevirtual #68                 // Method onChanged:()V
      38: goto          50
      41: aload_0
      42: getfield      #32                 // Field tableCfsBuilder_:Lorg/apache/hbase/thirdparty/com/google/protobuf/RepeatedFieldBuilderV3;
      45: aload_1
      46: invokevirtual #142                // Method org/apache/hbase/thirdparty/com/google/protobuf/RepeatedFieldBuilderV3.addMessage:(Lorg/apache/hbase/thirdparty/com/google/protobuf/AbstractMessage;)Lorg/apache/hbase/thirdparty/com/google/protobuf/RepeatedFieldBuilderV3;
      49: pop
      50: aload_0
      51: areturn

  public org.apache.hadoop.hbase.shaded.protobuf.generated.ReplicationProtos$ReplicationPeer$Builder addTableCfs(int, org.apache.hadoop.hbase.shaded.protobuf.generated.ReplicationProtos$TableCF);
    Code:
       0: aload_0
       1: getfield      #32                 // Field tableCfsBuilder_:Lorg/apache/hbase/thirdparty/com/google/protobuf/RepeatedFieldBuilderV3;
       4: ifnonnull     41
       7: aload_2
       8: ifnonnull     19
      11: new           #126                // class java/lang/NullPointerException
      14: dup
      15: invokespecial #127                // Method java/lang/NullPointerException."<init>":()V
      18: athrow
      19: aload_0
      20: invokespecial #83                 // Method ensureTableCfsIsMutable:()V
      23: aload_0
      24: getfield      #15                 // Field tableCfs_:Ljava/util/List;
      27: iload_1
      28: aload_2
      29: invokeinterface #143,  3          // InterfaceMethod java/util/List.add:(ILjava/lang/Object;)V
      34: aload_0
      35: invokevirtual #68                 // Method onChanged:()V
      38: goto          51
      41: aload_0
      42: getfield      #32                 // Field tableCfsBuilder_:Lorg/apache/hbase/thirdparty/com/google/protobuf/RepeatedFieldBuilderV3;
      45: iload_1
      46: aload_2
      47: invokevirtual #144                // Method org/apache/hbase/thirdparty/com/google/protobuf/RepeatedFieldBuilderV3.addMessage:(ILorg/apache/hbase/thirdparty/com/google/protobuf/AbstractMessage;)Lorg/apache/hbase/thirdparty/com/google/protobuf/RepeatedFieldBuilderV3;
      50: pop
      51: aload_0
      52: areturn

  public org.apache.hadoop.hbase.shaded.protobuf.generated.ReplicationProtos$ReplicationPeer$Builder addTableCfs(org.apache.hadoop.hbase.shaded.protobuf.generated.ReplicationProtos$TableCF$Builder);
    Code:
       0: aload_0
       1: getfield      #32                 // Field tableCfsBuilder_:Lorg/apache/hbase/thirdparty/com/google/protobuf/RepeatedFieldBuilderV3;
       4: ifnonnull     32
       7: aload_0
       8: invokespecial #83                 // Method ensureTableCfsIsMutable:()V
      11: aload_0
      12: getfield      #15                 // Field tableCfs_:Ljava/util/List;
      15: aload_1
      16: invokevirtual #167                // Method org/apache/hadoop/hbase/shaded/protobuf/generated/ReplicationProtos$TableCF$Builder.build:()Lorg/apache/hadoop/hbase/shaded/protobuf/generated/ReplicationProtos$TableCF;
      19: invokeinterface #141,  2          // InterfaceMethod java/util/List.add:(Ljava/lang/Object;)Z
      24: pop
      25: aload_0
      26: invokevirtual #68                 // Method onChanged:()V
      29: goto          44
      32: aload_0
      33: getfield      #32                 // Field tableCfsBuilder_:Lorg/apache/hbase/thirdparty/com/google/protobuf/RepeatedFieldBuilderV3;
      36: aload_1
      37: invokevirtual #167                // Method org/apache/hadoop/hbase/shaded/protobuf/generated/ReplicationProtos$TableCF$Builder.build:()Lorg/apache/hadoop/hbase/shaded/protobuf/generated/ReplicationProtos$TableCF;
      40: invokevirtual #142                // Method org/apache/hbase/thirdparty/com/google/protobuf/RepeatedFieldBuilderV3.addMessage:(Lorg/apache/hbase/thirdparty/com/google/protobuf/AbstractMessage;)Lorg/apache/hbase/thirdparty/com/google/protobuf/RepeatedFieldBuilderV3;
      43: pop
      44: aload_0
      45: areturn

  public org.apache.hadoop.hbase.shaded.protobuf.generated.ReplicationProtos$ReplicationPeer$Builder addTableCfs(int, org.apache.hadoop.hbase.shaded.protobuf.generated.ReplicationProtos$TableCF$Builder);
    Code:
       0: aload_0
       1: getfield      #32                 // Field tableCfsBuilder_:Lorg/apache/hbase/thirdparty/com/google/protobuf/RepeatedFieldBuilderV3;
       4: ifnonnull     32
       7: aload_0
       8: invokespecial #83                 // Method ensureTableCfsIsMutable:()V
      11: aload_0
      12: getfield      #15                 // Field tableCfs_:Ljava/util/List;
      15: iload_1
      16: aload_2
      17: invokevirtual #167                // Method org/apache/hadoop/hbase/shaded/protobuf/generated/ReplicationProtos$TableCF$Builder.build:()Lorg/apache/hadoop/hbase/shaded/protobuf/generated/ReplicationProtos$TableCF;
      20: invokeinterface #143,  3          // InterfaceMethod java/util/List.add:(ILjava/lang/Object;)V
      25: aload_0
      26: invokevirtual #68                 // Method onChanged:()V
      29: goto          45
      32: aload_0
      33: getfield      #32                 // Field tableCfsBuilder_:Lorg/apache/hbase/thirdparty/com/google/protobuf/RepeatedFieldBuilderV3;
      36: iload_1
      37: aload_2
      38: invokevirtual #167                // Method org/apache/hadoop/hbase/shaded/protobuf/generated/ReplicationProtos$TableCF$Builder.build:()Lorg/apache/hadoop/hbase/shaded/protobuf/generated/ReplicationProtos$TableCF;
      41: invokevirtual #144                // Method org/apache/hbase/thirdparty/com/google/protobuf/RepeatedFieldBuilderV3.addMessage:(ILorg/apache/hbase/thirdparty/com/google/protobuf/AbstractMessage;)Lorg/apache/hbase/thirdparty/com/google/protobuf/RepeatedFieldBuilderV3;
      44: pop
      45: aload_0
      46: areturn

  public org.apache.hadoop.hbase.shaded.protobuf.generated.ReplicationProtos$ReplicationPeer$Builder addAllTableCfs(java.lang.Iterable<? extends org.apache.hadoop.hbase.shaded.protobuf.generated.ReplicationProtos$TableCF>);
    Code:
       0: aload_0
       1: getfield      #32                 // Field tableCfsBuilder_:Lorg/apache/hbase/thirdparty/com/google/protobuf/RepeatedFieldBuilderV3;
       4: ifnonnull     26
       7: aload_0
       8: invokespecial #83                 // Method ensureTableCfsIsMutable:()V
      11: aload_1
      12: aload_0
      13: getfield      #15                 // Field tableCfs_:Ljava/util/List;
      16: invokestatic  #145                // Method org/apache/hbase/thirdparty/com/google/protobuf/AbstractMessageLite$Builder.addAll:(Ljava/lang/Iterable;Ljava/util/List;)V
      19: aload_0
      20: invokevirtual #68                 // Method onChanged:()V
      23: goto          35
      26: aload_0
      27: getfield      #32                 // Field tableCfsBuilder_:Lorg/apache/hbase/thirdparty/com/google/protobuf/RepeatedFieldBuilderV3;
      30: aload_1
      31: invokevirtual #78                 // Method org/apache/hbase/thirdparty/com/google/protobuf/RepeatedFieldBuilderV3.addAllMessages:(Ljava/lang/Iterable;)Lorg/apache/hbase/thirdparty/com/google/protobuf/RepeatedFieldBuilderV3;
      34: pop
      35: aload_0
      36: areturn

  public org.apache.hadoop.hbase.shaded.protobuf.generated.ReplicationProtos$ReplicationPeer$Builder clearTableCfs();
    Code:
       0: aload_0
       1: getfield      #32                 // Field tableCfsBuilder_:Lorg/apache/hbase/thirdparty/com/google/protobuf/RepeatedFieldBuilderV3;
       4: ifnonnull     32
       7: aload_0
       8: invokestatic  #12                 // Method java/util/Collections.emptyList:()Ljava/util/List;
      11: putfield      #15                 // Field tableCfs_:Ljava/util/List;
      14: aload_0
      15: aload_0
      16: getfield      #28                 // Field bitField0_:I
      19: bipush        -17
      21: iand
      22: putfield      #28                 // Field bitField0_:I
      25: aload_0
      26: invokevirtual #68                 // Method onChanged:()V
      29: goto          39
      32: aload_0
      33: getfield      #32                 // Field tableCfsBuilder_:Lorg/apache/hbase/thirdparty/com/google/protobuf/RepeatedFieldBuilderV3;
      36: invokevirtual #30                 // Method org/apache/hbase/thirdparty/com/google/protobuf/RepeatedFieldBuilderV3.clear:()V
      39: aload_0
      40: areturn

  public org.apache.hadoop.hbase.shaded.protobuf.generated.ReplicationProtos$ReplicationPeer$Builder removeTableCfs(int);
    Code:
       0: aload_0
       1: getfield      #32                 // Field tableCfsBuilder_:Lorg/apache/hbase/thirdparty/com/google/protobuf/RepeatedFieldBuilderV3;
       4: ifnonnull     29
       7: aload_0
       8: invokespecial #83                 // Method ensureTableCfsIsMutable:()V
      11: aload_0
      12: getfield      #15                 // Field tableCfs_:Ljava/util/List;
      15: iload_1
      16: invokeinterface #146,  2          // InterfaceMethod java/util/List.remove:(I)Ljava/lang/Object;
      21: pop
      22: aload_0
      23: invokevirtual #68                 // Method onChanged:()V
      26: goto          37
      29: aload_0
      30: getfield      #32                 // Field tableCfsBuilder_:Lorg/apache/hbase/thirdparty/com/google/protobuf/RepeatedFieldBuilderV3;
      33: iload_1
      34: invokevirtual #147                // Method org/apache/hbase/thirdparty/com/google/protobuf/RepeatedFieldBuilderV3.remove:(I)V
      37: aload_0
      38: areturn

  public org.apache.hadoop.hbase.shaded.protobuf.generated.ReplicationProtos$TableCF$Builder getTableCfsBuilder(int);
    Code:
       0: aload_0
       1: invokespecial #25                 // Method getTableCfsFieldBuilder:()Lorg/apache/hbase/thirdparty/com/google/protobuf/RepeatedFieldBuilderV3;
       4: iload_1
       5: invokevirtual #148                // Method org/apache/hbase/thirdparty/com/google/protobuf/RepeatedFieldBuilderV3.getBuilder:(I)Lorg/apache/hbase/thirdparty/com/google/protobuf/AbstractMessage$Builder;
       8: checkcast     #168                // class org/apache/hadoop/hbase/shaded/protobuf/generated/ReplicationProtos$TableCF$Builder
      11: areturn

  public org.apache.hadoop.hbase.shaded.protobuf.generated.ReplicationProtos$TableCFOrBuilder getTableCfsOrBuilder(int);
    Code:
       0: aload_0
       1: getfield      #32                 // Field tableCfsBuilder_:Lorg/apache/hbase/thirdparty/com/google/protobuf/RepeatedFieldBuilderV3;
       4: ifnonnull     21
       7: aload_0
       8: getfield      #15                 // Field tableCfs_:Ljava/util/List;
      11: iload_1
      12: invokeinterface #135,  2          // InterfaceMethod java/util/List.get:(I)Ljava/lang/Object;
      17: checkcast     #169                // class org/apache/hadoop/hbase/shaded/protobuf/generated/ReplicationProtos$TableCFOrBuilder
      20: areturn
      21: aload_0
      22: getfield      #32                 // Field tableCfsBuilder_:Lorg/apache/hbase/thirdparty/com/google/protobuf/RepeatedFieldBuilderV3;
      25: iload_1
      26: invokevirtual #151                // Method org/apache/hbase/thirdparty/com/google/protobuf/RepeatedFieldBuilderV3.getMessageOrBuilder:(I)Lorg/apache/hbase/thirdparty/com/google/protobuf/MessageOrBuilder;
      29: checkcast     #169                // class org/apache/hadoop/hbase/shaded/protobuf/generated/ReplicationProtos$TableCFOrBuilder
      32: areturn

  public java.util.List<? extends org.apache.hadoop.hbase.shaded.protobuf.generated.ReplicationProtos$TableCFOrBuilder> getTableCfsOrBuilderList();
    Code:
       0: aload_0
       1: getfield      #32                 // Field tableCfsBuilder_:Lorg/apache/hbase/thirdparty/com/google/protobuf/RepeatedFieldBuilderV3;
       4: ifnull        15
       7: aload_0
       8: getfield      #32                 // Field tableCfsBuilder_:Lorg/apache/hbase/thirdparty/com/google/protobuf/RepeatedFieldBuilderV3;
      11: invokevirtual #152                // Method org/apache/hbase/thirdparty/com/google/protobuf/RepeatedFieldBuilderV3.getMessageOrBuilderList:()Ljava/util/List;
      14: areturn
      15: aload_0
      16: getfield      #15                 // Field tableCfs_:Ljava/util/List;
      19: invokestatic  #44                 // Method java/util/Collections.unmodifiableList:(Ljava/util/List;)Ljava/util/List;
      22: areturn

  public org.apache.hadoop.hbase.shaded.protobuf.generated.ReplicationProtos$TableCF$Builder addTableCfsBuilder();
    Code:
       0: aload_0
       1: invokespecial #25                 // Method getTableCfsFieldBuilder:()Lorg/apache/hbase/thirdparty/com/google/protobuf/RepeatedFieldBuilderV3;
       4: invokestatic  #170                // Method org/apache/hadoop/hbase/shaded/protobuf/generated/ReplicationProtos$TableCF.getDefaultInstance:()Lorg/apache/hadoop/hbase/shaded/protobuf/generated/ReplicationProtos$TableCF;
       7: invokevirtual #154                // Method org/apache/hbase/thirdparty/com/google/protobuf/RepeatedFieldBuilderV3.addBuilder:(Lorg/apache/hbase/thirdparty/com/google/protobuf/AbstractMessage;)Lorg/apache/hbase/thirdparty/com/google/protobuf/AbstractMessage$Builder;
      10: checkcast     #168                // class org/apache/hadoop/hbase/shaded/protobuf/generated/ReplicationProtos$TableCF$Builder
      13: areturn

  public org.apache.hadoop.hbase.shaded.protobuf.generated.ReplicationProtos$TableCF$Builder addTableCfsBuilder(int);
    Code:
       0: aload_0
       1: invokespecial #25                 // Method getTableCfsFieldBuilder:()Lorg/apache/hbase/thirdparty/com/google/protobuf/RepeatedFieldBuilderV3;
       4: iload_1
       5: invokestatic  #170                // Method org/apache/hadoop/hbase/shaded/protobuf/generated/ReplicationProtos$TableCF.getDefaultInstance:()Lorg/apache/hadoop/hbase/shaded/protobuf/generated/ReplicationProtos$TableCF;
       8: invokevirtual #155                // Method org/apache/hbase/thirdparty/com/google/protobuf/RepeatedFieldBuilderV3.addBuilder:(ILorg/apache/hbase/thirdparty/com/google/protobuf/AbstractMessage;)Lorg/apache/hbase/thirdparty/com/google/protobuf/AbstractMessage$Builder;
      11: checkcast     #168                // class org/apache/hadoop/hbase/shaded/protobuf/generated/ReplicationProtos$TableCF$Builder
      14: areturn

  public java.util.List<org.apache.hadoop.hbase.shaded.protobuf.generated.ReplicationProtos$TableCF$Builder> getTableCfsBuilderList();
    Code:
       0: aload_0
       1: invokespecial #25                 // Method getTableCfsFieldBuilder:()Lorg/apache/hbase/thirdparty/com/google/protobuf/RepeatedFieldBuilderV3;
       4: invokevirtual #156                // Method org/apache/hbase/thirdparty/com/google/protobuf/RepeatedFieldBuilderV3.getBuilderList:()Ljava/util/List;
       7: areturn

  public java.util.List<org.apache.hbase.thirdparty.com.google.protobuf.ByteString> getNamespacesList();
    Code:
       0: aload_0
       1: getfield      #16                 // Field namespaces_:Ljava/util/List;
       4: invokestatic  #44                 // Method java/util/Collections.unmodifiableList:(Ljava/util/List;)Ljava/util/List;
       7: areturn

  public int getNamespacesCount();
    Code:
       0: aload_0
       1: getfield      #16                 // Field namespaces_:Ljava/util/List;
       4: invokeinterface #133,  1          // InterfaceMethod java/util/List.size:()I
       9: ireturn

  public org.apache.hbase.thirdparty.com.google.protobuf.ByteString getNamespaces(int);
    Code:
       0: aload_0
       1: getfield      #16                 // Field namespaces_:Ljava/util/List;
       4: iload_1
       5: invokeinterface #135,  2          // InterfaceMethod java/util/List.get:(I)Ljava/lang/Object;
      10: checkcast     #122                // class org/apache/hbase/thirdparty/com/google/protobuf/ByteString
      13: areturn

  public org.apache.hadoop.hbase.shaded.protobuf.generated.ReplicationProtos$ReplicationPeer$Builder setNamespaces(int, org.apache.hbase.thirdparty.com.google.protobuf.ByteString);
    Code:
       0: aload_2
       1: ifnonnull     12
       4: new           #126                // class java/lang/NullPointerException
       7: dup
       8: invokespecial #127                // Method java/lang/NullPointerException."<init>":()V
      11: athrow
      12: aload_0
      13: invokespecial #86                 // Method ensureNamespacesIsMutable:()V
      16: aload_0
      17: getfield      #16                 // Field namespaces_:Ljava/util/List;
      20: iload_1
      21: aload_2
      22: invokeinterface #138,  3          // InterfaceMethod java/util/List.set:(ILjava/lang/Object;)Ljava/lang/Object;
      27: pop
      28: aload_0
      29: invokevirtual #68                 // Method onChanged:()V
      32: aload_0
      33: areturn

  public org.apache.hadoop.hbase.shaded.protobuf.generated.ReplicationProtos$ReplicationPeer$Builder addNamespaces(org.apache.hbase.thirdparty.com.google.protobuf.ByteString);
    Code:
       0: aload_1
       1: ifnonnull     12
       4: new           #126                // class java/lang/NullPointerException
       7: dup
       8: invokespecial #127                // Method java/lang/NullPointerException."<init>":()V
      11: athrow
      12: aload_0
      13: invokespecial #86                 // Method ensureNamespacesIsMutable:()V
      16: aload_0
      17: getfield      #16                 // Field namespaces_:Ljava/util/List;
      20: aload_1
      21: invokeinterface #141,  2          // InterfaceMethod java/util/List.add:(Ljava/lang/Object;)Z
      26: pop
      27: aload_0
      28: invokevirtual #68                 // Method onChanged:()V
      31: aload_0
      32: areturn

  public org.apache.hadoop.hbase.shaded.protobuf.generated.ReplicationProtos$ReplicationPeer$Builder addAllNamespaces(java.lang.Iterable<? extends org.apache.hbase.thirdparty.com.google.protobuf.ByteString>);
    Code:
       0: aload_0
       1: invokespecial #86                 // Method ensureNamespacesIsMutable:()V
       4: aload_1
       5: aload_0
       6: getfield      #16                 // Field namespaces_:Ljava/util/List;
       9: invokestatic  #145                // Method org/apache/hbase/thirdparty/com/google/protobuf/AbstractMessageLite$Builder.addAll:(Ljava/lang/Iterable;Ljava/util/List;)V
      12: aload_0
      13: invokevirtual #68                 // Method onChanged:()V
      16: aload_0
      17: areturn

  public org.apache.hadoop.hbase.shaded.protobuf.generated.ReplicationProtos$ReplicationPeer$Builder clearNamespaces();
    Code:
       0: aload_0
       1: invokestatic  #12                 // Method java/util/Collections.emptyList:()Ljava/util/List;
       4: putfield      #16                 // Field namespaces_:Ljava/util/List;
       7: aload_0
       8: aload_0
       9: getfield      #28                 // Field bitField0_:I
      12: bipush        -33
      14: iand
      15: putfield      #28                 // Field bitField0_:I
      18: aload_0
      19: invokevirtual #68                 // Method onChanged:()V
      22: aload_0
      23: areturn

  public boolean hasBandwidth();
    Code:
       0: aload_0
       1: getfield      #28                 // Field bitField0_:I
       4: bipush        64
       6: iand
       7: bipush        64
       9: if_icmpne     16
      12: iconst_1
      13: goto          17
      16: iconst_0
      17: ireturn

  public long getBandwidth();
    Code:
       0: aload_0
       1: getfield      #33                 // Field bandwidth_:J
       4: lreturn

  public org.apache.hadoop.hbase.shaded.protobuf.generated.ReplicationProtos$ReplicationPeer$Builder setBandwidth(long);
    Code:
       0: aload_0
       1: dup
       2: getfield      #28                 // Field bitField0_:I
       5: bipush        64
       7: ior
       8: putfield      #28                 // Field bitField0_:I
      11: aload_0
      12: lload_1
      13: putfield      #33                 // Field bandwidth_:J
      16: aload_0
      17: invokevirtual #68                 // Method onChanged:()V
      20: aload_0
      21: areturn

  public org.apache.hadoop.hbase.shaded.protobuf.generated.ReplicationProtos$ReplicationPeer$Builder clearBandwidth();
    Code:
       0: aload_0
       1: aload_0
       2: getfield      #28                 // Field bitField0_:I
       5: bipush        -65
       7: iand
       8: putfield      #28                 // Field bitField0_:I
      11: aload_0
      12: lconst_0
      13: putfield      #33                 // Field bandwidth_:J
      16: aload_0
      17: invokevirtual #68                 // Method onChanged:()V
      20: aload_0
      21: areturn

  public boolean hasReplicateAll();
    Code:
       0: aload_0
       1: getfield      #28                 // Field bitField0_:I
       4: sipush        128
       7: iand
       8: sipush        128
      11: if_icmpne     18
      14: iconst_1
      15: goto          19
      18: iconst_0
      19: ireturn

  public boolean getReplicateAll();
    Code:
       0: aload_0
       1: getfield      #34                 // Field replicateAll_:Z
       4: ireturn

  public org.apache.hadoop.hbase.shaded.protobuf.generated.ReplicationProtos$ReplicationPeer$Builder setReplicateAll(boolean);
    Code:
       0: aload_0
       1: dup
       2: getfield      #28                 // Field bitField0_:I
       5: sipush        128
       8: ior
       9: putfield      #28                 // Field bitField0_:I
      12: aload_0
      13: iload_1
      14: putfield      #34                 // Field replicateAll_:Z
      17: aload_0
      18: invokevirtual #68                 // Method onChanged:()V
      21: aload_0
      22: areturn

  public org.apache.hadoop.hbase.shaded.protobuf.generated.ReplicationProtos$ReplicationPeer$Builder clearReplicateAll();
    Code:
       0: aload_0
       1: aload_0
       2: getfield      #28                 // Field bitField0_:I
       5: sipush        -129
       8: iand
       9: putfield      #28                 // Field bitField0_:I
      12: aload_0
      13: iconst_0
      14: putfield      #34                 // Field replicateAll_:Z
      17: aload_0
      18: invokevirtual #68                 // Method onChanged:()V
      21: aload_0
      22: areturn

  public java.util.List<org.apache.hadoop.hbase.shaded.protobuf.generated.ReplicationProtos$TableCF> getExcludeTableCfsList();
    Code:
       0: aload_0
       1: getfield      #35                 // Field excludeTableCfsBuilder_:Lorg/apache/hbase/thirdparty/com/google/protobuf/RepeatedFieldBuilderV3;
       4: ifnonnull     15
       7: aload_0
       8: getfield      #17                 // Field excludeTableCfs_:Ljava/util/List;
      11: invokestatic  #44                 // Method java/util/Collections.unmodifiableList:(Ljava/util/List;)Ljava/util/List;
      14: areturn
      15: aload_0
      16: getfield      #35                 // Field excludeTableCfsBuilder_:Lorg/apache/hbase/thirdparty/com/google/protobuf/RepeatedFieldBuilderV3;
      19: invokevirtual #132                // Method org/apache/hbase/thirdparty/com/google/protobuf/RepeatedFieldBuilderV3.getMessageList:()Ljava/util/List;
      22: areturn

  public int getExcludeTableCfsCount();
    Code:
       0: aload_0
       1: getfield      #35                 // Field excludeTableCfsBuilder_:Lorg/apache/hbase/thirdparty/com/google/protobuf/RepeatedFieldBuilderV3;
       4: ifnonnull     17
       7: aload_0
       8: getfield      #17                 // Field excludeTableCfs_:Ljava/util/List;
      11: invokeinterface #133,  1          // InterfaceMethod java/util/List.size:()I
      16: ireturn
      17: aload_0
      18: getfield      #35                 // Field excludeTableCfsBuilder_:Lorg/apache/hbase/thirdparty/com/google/protobuf/RepeatedFieldBuilderV3;
      21: invokevirtual #134                // Method org/apache/hbase/thirdparty/com/google/protobuf/RepeatedFieldBuilderV3.getCount:()I
      24: ireturn

  public org.apache.hadoop.hbase.shaded.protobuf.generated.ReplicationProtos$TableCF getExcludeTableCfs(int);
    Code:
       0: aload_0
       1: getfield      #35                 // Field excludeTableCfsBuilder_:Lorg/apache/hbase/thirdparty/com/google/protobuf/RepeatedFieldBuilderV3;
       4: ifnonnull     21
       7: aload_0
       8: getfield      #17                 // Field excludeTableCfs_:Ljava/util/List;
      11: iload_1
      12: invokeinterface #135,  2          // InterfaceMethod java/util/List.get:(I)Ljava/lang/Object;
      17: checkcast     #166                // class org/apache/hadoop/hbase/shaded/protobuf/generated/ReplicationProtos$TableCF
      20: areturn
      21: aload_0
      22: getfield      #35                 // Field excludeTableCfsBuilder_:Lorg/apache/hbase/thirdparty/com/google/protobuf/RepeatedFieldBuilderV3;
      25: iload_1
      26: invokevirtual #137                // Method org/apache/hbase/thirdparty/com/google/protobuf/RepeatedFieldBuilderV3.getMessage:(I)Lorg/apache/hbase/thirdparty/com/google/protobuf/AbstractMessage;
      29: checkcast     #166                // class org/apache/hadoop/hbase/shaded/protobuf/generated/ReplicationProtos$TableCF
      32: areturn

  public org.apache.hadoop.hbase.shaded.protobuf.generated.ReplicationProtos$ReplicationPeer$Builder setExcludeTableCfs(int, org.apache.hadoop.hbase.shaded.protobuf.generated.ReplicationProtos$TableCF);
    Code:
       0: aload_0
       1: getfield      #35                 // Field excludeTableCfsBuilder_:Lorg/apache/hbase/thirdparty/com/google/protobuf/RepeatedFieldBuilderV3;
       4: ifnonnull     42
       7: aload_2
       8: ifnonnull     19
      11: new           #126                // class java/lang/NullPointerException
      14: dup
      15: invokespecial #127                // Method java/lang/NullPointerException."<init>":()V
      18: athrow
      19: aload_0
      20: invokespecial #94                 // Method ensureExcludeTableCfsIsMutable:()V
      23: aload_0
      24: getfield      #17                 // Field excludeTableCfs_:Ljava/util/List;
      27: iload_1
      28: aload_2
      29: invokeinterface #138,  3          // InterfaceMethod java/util/List.set:(ILjava/lang/Object;)Ljava/lang/Object;
      34: pop
      35: aload_0
      36: invokevirtual #68                 // Method onChanged:()V
      39: goto          52
      42: aload_0
      43: getfield      #35                 // Field excludeTableCfsBuilder_:Lorg/apache/hbase/thirdparty/com/google/protobuf/RepeatedFieldBuilderV3;
      46: iload_1
      47: aload_2
      48: invokevirtual #139                // Method org/apache/hbase/thirdparty/com/google/protobuf/RepeatedFieldBuilderV3.setMessage:(ILorg/apache/hbase/thirdparty/com/google/protobuf/AbstractMessage;)Lorg/apache/hbase/thirdparty/com/google/protobuf/RepeatedFieldBuilderV3;
      51: pop
      52: aload_0
      53: areturn

  public org.apache.hadoop.hbase.shaded.protobuf.generated.ReplicationProtos$ReplicationPeer$Builder setExcludeTableCfs(int, org.apache.hadoop.hbase.shaded.protobuf.generated.ReplicationProtos$TableCF$Builder);
    Code:
       0: aload_0
       1: getfield      #35                 // Field excludeTableCfsBuilder_:Lorg/apache/hbase/thirdparty/com/google/protobuf/RepeatedFieldBuilderV3;
       4: ifnonnull     33
       7: aload_0
       8: invokespecial #94                 // Method ensureExcludeTableCfsIsMutable:()V
      11: aload_0
      12: getfield      #17                 // Field excludeTableCfs_:Ljava/util/List;
      15: iload_1
      16: aload_2
      17: invokevirtual #167                // Method org/apache/hadoop/hbase/shaded/protobuf/generated/ReplicationProtos$TableCF$Builder.build:()Lorg/apache/hadoop/hbase/shaded/protobuf/generated/ReplicationProtos$TableCF;
      20: invokeinterface #138,  3          // InterfaceMethod java/util/List.set:(ILjava/lang/Object;)Ljava/lang/Object;
      25: pop
      26: aload_0
      27: invokevirtual #68                 // Method onChanged:()V
      30: goto          46
      33: aload_0
      34: getfield      #35                 // Field excludeTableCfsBuilder_:Lorg/apache/hbase/thirdparty/com/google/protobuf/RepeatedFieldBuilderV3;
      37: iload_1
      38: aload_2
      39: invokevirtual #167                // Method org/apache/hadoop/hbase/shaded/protobuf/generated/ReplicationProtos$TableCF$Builder.build:()Lorg/apache/hadoop/hbase/shaded/protobuf/generated/ReplicationProtos$TableCF;
      42: invokevirtual #139                // Method org/apache/hbase/thirdparty/com/google/protobuf/RepeatedFieldBuilderV3.setMessage:(ILorg/apache/hbase/thirdparty/com/google/protobuf/AbstractMessage;)Lorg/apache/hbase/thirdparty/com/google/protobuf/RepeatedFieldBuilderV3;
      45: pop
      46: aload_0
      47: areturn

  public org.apache.hadoop.hbase.shaded.protobuf.generated.ReplicationProtos$ReplicationPeer$Builder addExcludeTableCfs(org.apache.hadoop.hbase.shaded.protobuf.generated.ReplicationProtos$TableCF);
    Code:
       0: aload_0
       1: getfield      #35                 // Field excludeTableCfsBuilder_:Lorg/apache/hbase/thirdparty/com/google/protobuf/RepeatedFieldBuilderV3;
       4: ifnonnull     41
       7: aload_1
       8: ifnonnull     19
      11: new           #126                // class java/lang/NullPointerException
      14: dup
      15: invokespecial #127                // Method java/lang/NullPointerException."<init>":()V
      18: athrow
      19: aload_0
      20: invokespecial #94                 // Method ensureExcludeTableCfsIsMutable:()V
      23: aload_0
      24: getfield      #17                 // Field excludeTableCfs_:Ljava/util/List;
      27: aload_1
      28: invokeinterface #141,  2          // InterfaceMethod java/util/List.add:(Ljava/lang/Object;)Z
      33: pop
      34: aload_0
      35: invokevirtual #68                 // Method onChanged:()V
      38: goto          50
      41: aload_0
      42: getfield      #35                 // Field excludeTableCfsBuilder_:Lorg/apache/hbase/thirdparty/com/google/protobuf/RepeatedFieldBuilderV3;
      45: aload_1
      46: invokevirtual #142                // Method org/apache/hbase/thirdparty/com/google/protobuf/RepeatedFieldBuilderV3.addMessage:(Lorg/apache/hbase/thirdparty/com/google/protobuf/AbstractMessage;)Lorg/apache/hbase/thirdparty/com/google/protobuf/RepeatedFieldBuilderV3;
      49: pop
      50: aload_0
      51: areturn

  public org.apache.hadoop.hbase.shaded.protobuf.generated.ReplicationProtos$ReplicationPeer$Builder addExcludeTableCfs(int, org.apache.hadoop.hbase.shaded.protobuf.generated.ReplicationProtos$TableCF);
    Code:
       0: aload_0
       1: getfield      #35                 // Field excludeTableCfsBuilder_:Lorg/apache/hbase/thirdparty/com/google/protobuf/RepeatedFieldBuilderV3;
       4: ifnonnull     41
       7: aload_2
       8: ifnonnull     19
      11: new           #126                // class java/lang/NullPointerException
      14: dup
      15: invokespecial #127                // Method java/lang/NullPointerException."<init>":()V
      18: athrow
      19: aload_0
      20: invokespecial #94                 // Method ensureExcludeTableCfsIsMutable:()V
      23: aload_0
      24: getfield      #17                 // Field excludeTableCfs_:Ljava/util/List;
      27: iload_1
      28: aload_2
      29: invokeinterface #143,  3          // InterfaceMethod java/util/List.add:(ILjava/lang/Object;)V
      34: aload_0
      35: invokevirtual #68                 // Method onChanged:()V
      38: goto          51
      41: aload_0
      42: getfield      #35                 // Field excludeTableCfsBuilder_:Lorg/apache/hbase/thirdparty/com/google/protobuf/RepeatedFieldBuilderV3;
      45: iload_1
      46: aload_2
      47: invokevirtual #144                // Method org/apache/hbase/thirdparty/com/google/protobuf/RepeatedFieldBuilderV3.addMessage:(ILorg/apache/hbase/thirdparty/com/google/protobuf/AbstractMessage;)Lorg/apache/hbase/thirdparty/com/google/protobuf/RepeatedFieldBuilderV3;
      50: pop
      51: aload_0
      52: areturn

  public org.apache.hadoop.hbase.shaded.protobuf.generated.ReplicationProtos$ReplicationPeer$Builder addExcludeTableCfs(org.apache.hadoop.hbase.shaded.protobuf.generated.ReplicationProtos$TableCF$Builder);
    Code:
       0: aload_0
       1: getfield      #35                 // Field excludeTableCfsBuilder_:Lorg/apache/hbase/thirdparty/com/google/protobuf/RepeatedFieldBuilderV3;
       4: ifnonnull     32
       7: aload_0
       8: invokespecial #94                 // Method ensureExcludeTableCfsIsMutable:()V
      11: aload_0
      12: getfield      #17                 // Field excludeTableCfs_:Ljava/util/List;
      15: aload_1
      16: invokevirtual #167                // Method org/apache/hadoop/hbase/shaded/protobuf/generated/ReplicationProtos$TableCF$Builder.build:()Lorg/apache/hadoop/hbase/shaded/protobuf/generated/ReplicationProtos$TableCF;
      19: invokeinterface #141,  2          // InterfaceMethod java/util/List.add:(Ljava/lang/Object;)Z
      24: pop
      25: aload_0
      26: invokevirtual #68                 // Method onChanged:()V
      29: goto          44
      32: aload_0
      33: getfield      #35                 // Field excludeTableCfsBuilder_:Lorg/apache/hbase/thirdparty/com/google/protobuf/RepeatedFieldBuilderV3;
      36: aload_1
      37: invokevirtual #167                // Method org/apache/hadoop/hbase/shaded/protobuf/generated/ReplicationProtos$TableCF$Builder.build:()Lorg/apache/hadoop/hbase/shaded/protobuf/generated/ReplicationProtos$TableCF;
      40: invokevirtual #142                // Method org/apache/hbase/thirdparty/com/google/protobuf/RepeatedFieldBuilderV3.addMessage:(Lorg/apache/hbase/thirdparty/com/google/protobuf/AbstractMessage;)Lorg/apache/hbase/thirdparty/com/google/protobuf/RepeatedFieldBuilderV3;
      43: pop
      44: aload_0
      45: areturn

  public org.apache.hadoop.hbase.shaded.protobuf.generated.ReplicationProtos$ReplicationPeer$Builder addExcludeTableCfs(int, org.apache.hadoop.hbase.shaded.protobuf.generated.ReplicationProtos$TableCF$Builder);
    Code:
       0: aload_0
       1: getfield      #35                 // Field excludeTableCfsBuilder_:Lorg/apache/hbase/thirdparty/com/google/protobuf/RepeatedFieldBuilderV3;
       4: ifnonnull     32
       7: aload_0
       8: invokespecial #94                 // Method ensureExcludeTableCfsIsMutable:()V
      11: aload_0
      12: getfield      #17                 // Field excludeTableCfs_:Ljava/util/List;
      15: iload_1
      16: aload_2
      17: invokevirtual #167                // Method org/apache/hadoop/hbase/shaded/protobuf/generated/ReplicationProtos$TableCF$Builder.build:()Lorg/apache/hadoop/hbase/shaded/protobuf/generated/ReplicationProtos$TableCF;
      20: invokeinterface #143,  3          // InterfaceMethod java/util/List.add:(ILjava/lang/Object;)V
      25: aload_0
      26: invokevirtual #68                 // Method onChanged:()V
      29: goto          45
      32: aload_0
      33: getfield      #35                 // Field excludeTableCfsBuilder_:Lorg/apache/hbase/thirdparty/com/google/protobuf/RepeatedFieldBuilderV3;
      36: iload_1
      37: aload_2
      38: invokevirtual #167                // Method org/apache/hadoop/hbase/shaded/protobuf/generated/ReplicationProtos$TableCF$Builder.build:()Lorg/apache/hadoop/hbase/shaded/protobuf/generated/ReplicationProtos$TableCF;
      41: invokevirtual #144                // Method org/apache/hbase/thirdparty/com/google/protobuf/RepeatedFieldBuilderV3.addMessage:(ILorg/apache/hbase/thirdparty/com/google/protobuf/AbstractMessage;)Lorg/apache/hbase/thirdparty/com/google/protobuf/RepeatedFieldBuilderV3;
      44: pop
      45: aload_0
      46: areturn

  public org.apache.hadoop.hbase.shaded.protobuf.generated.ReplicationProtos$ReplicationPeer$Builder addAllExcludeTableCfs(java.lang.Iterable<? extends org.apache.hadoop.hbase.shaded.protobuf.generated.ReplicationProtos$TableCF>);
    Code:
       0: aload_0
       1: getfield      #35                 // Field excludeTableCfsBuilder_:Lorg/apache/hbase/thirdparty/com/google/protobuf/RepeatedFieldBuilderV3;
       4: ifnonnull     26
       7: aload_0
       8: invokespecial #94                 // Method ensureExcludeTableCfsIsMutable:()V
      11: aload_1
      12: aload_0
      13: getfield      #17                 // Field excludeTableCfs_:Ljava/util/List;
      16: invokestatic  #145                // Method org/apache/hbase/thirdparty/com/google/protobuf/AbstractMessageLite$Builder.addAll:(Ljava/lang/Iterable;Ljava/util/List;)V
      19: aload_0
      20: invokevirtual #68                 // Method onChanged:()V
      23: goto          35
      26: aload_0
      27: getfield      #35                 // Field excludeTableCfsBuilder_:Lorg/apache/hbase/thirdparty/com/google/protobuf/RepeatedFieldBuilderV3;
      30: aload_1
      31: invokevirtual #78                 // Method org/apache/hbase/thirdparty/com/google/protobuf/RepeatedFieldBuilderV3.addAllMessages:(Ljava/lang/Iterable;)Lorg/apache/hbase/thirdparty/com/google/protobuf/RepeatedFieldBuilderV3;
      34: pop
      35: aload_0
      36: areturn

  public org.apache.hadoop.hbase.shaded.protobuf.generated.ReplicationProtos$ReplicationPeer$Builder clearExcludeTableCfs();
    Code:
       0: aload_0
       1: getfield      #35                 // Field excludeTableCfsBuilder_:Lorg/apache/hbase/thirdparty/com/google/protobuf/RepeatedFieldBuilderV3;
       4: ifnonnull     33
       7: aload_0
       8: invokestatic  #12                 // Method java/util/Collections.emptyList:()Ljava/util/List;
      11: putfield      #17                 // Field excludeTableCfs_:Ljava/util/List;
      14: aload_0
      15: aload_0
      16: getfield      #28                 // Field bitField0_:I
      19: sipush        -257
      22: iand
      23: putfield      #28                 // Field bitField0_:I
      26: aload_0
      27: invokevirtual #68                 // Method onChanged:()V
      30: goto          40
      33: aload_0
      34: getfield      #35                 // Field excludeTableCfsBuilder_:Lorg/apache/hbase/thirdparty/com/google/protobuf/RepeatedFieldBuilderV3;
      37: invokevirtual #30                 // Method org/apache/hbase/thirdparty/com/google/protobuf/RepeatedFieldBuilderV3.clear:()V
      40: aload_0
      41: areturn

  public org.apache.hadoop.hbase.shaded.protobuf.generated.ReplicationProtos$ReplicationPeer$Builder removeExcludeTableCfs(int);
    Code:
       0: aload_0
       1: getfield      #35                 // Field excludeTableCfsBuilder_:Lorg/apache/hbase/thirdparty/com/google/protobuf/RepeatedFieldBuilderV3;
       4: ifnonnull     29
       7: aload_0
       8: invokespecial #94                 // Method ensureExcludeTableCfsIsMutable:()V
      11: aload_0
      12: getfield      #17                 // Field excludeTableCfs_:Ljava/util/List;
      15: iload_1
      16: invokeinterface #146,  2          // InterfaceMethod java/util/List.remove:(I)Ljava/lang/Object;
      21: pop
      22: aload_0
      23: invokevirtual #68                 // Method onChanged:()V
      26: goto          37
      29: aload_0
      30: getfield      #35                 // Field excludeTableCfsBuilder_:Lorg/apache/hbase/thirdparty/com/google/protobuf/RepeatedFieldBuilderV3;
      33: iload_1
      34: invokevirtual #147                // Method org/apache/hbase/thirdparty/com/google/protobuf/RepeatedFieldBuilderV3.remove:(I)V
      37: aload_0
      38: areturn

  public org.apache.hadoop.hbase.shaded.protobuf.generated.ReplicationProtos$TableCF$Builder getExcludeTableCfsBuilder(int);
    Code:
       0: aload_0
       1: invokespecial #26                 // Method getExcludeTableCfsFieldBuilder:()Lorg/apache/hbase/thirdparty/com/google/protobuf/RepeatedFieldBuilderV3;
       4: iload_1
       5: invokevirtual #148                // Method org/apache/hbase/thirdparty/com/google/protobuf/RepeatedFieldBuilderV3.getBuilder:(I)Lorg/apache/hbase/thirdparty/com/google/protobuf/AbstractMessage$Builder;
       8: checkcast     #168                // class org/apache/hadoop/hbase/shaded/protobuf/generated/ReplicationProtos$TableCF$Builder
      11: areturn

  public org.apache.hadoop.hbase.shaded.protobuf.generated.ReplicationProtos$TableCFOrBuilder getExcludeTableCfsOrBuilder(int);
    Code:
       0: aload_0
       1: getfield      #35                 // Field excludeTableCfsBuilder_:Lorg/apache/hbase/thirdparty/com/google/protobuf/RepeatedFieldBuilderV3;
       4: ifnonnull     21
       7: aload_0
       8: getfield      #17                 // Field excludeTableCfs_:Ljava/util/List;
      11: iload_1
      12: invokeinterface #135,  2          // InterfaceMethod java/util/List.get:(I)Ljava/lang/Object;
      17: checkcast     #169                // class org/apache/hadoop/hbase/shaded/protobuf/generated/ReplicationProtos$TableCFOrBuilder
      20: areturn
      21: aload_0
      22: getfield      #35                 // Field excludeTableCfsBuilder_:Lorg/apache/hbase/thirdparty/com/google/protobuf/RepeatedFieldBuilderV3;
      25: iload_1
      26: invokevirtual #151                // Method org/apache/hbase/thirdparty/com/google/protobuf/RepeatedFieldBuilderV3.getMessageOrBuilder:(I)Lorg/apache/hbase/thirdparty/com/google/protobuf/MessageOrBuilder;
      29: checkcast     #169                // class org/apache/hadoop/hbase/shaded/protobuf/generated/ReplicationProtos$TableCFOrBuilder
      32: areturn

  public java.util.List<? extends org.apache.hadoop.hbase.shaded.protobuf.generated.ReplicationProtos$TableCFOrBuilder> getExcludeTableCfsOrBuilderList();
    Code:
       0: aload_0
       1: getfield      #35                 // Field excludeTableCfsBuilder_:Lorg/apache/hbase/thirdparty/com/google/protobuf/RepeatedFieldBuilderV3;
       4: ifnull        15
       7: aload_0
       8: getfield      #35                 // Field excludeTableCfsBuilder_:Lorg/apache/hbase/thirdparty/com/google/protobuf/RepeatedFieldBuilderV3;
      11: invokevirtual #152                // Method org/apache/hbase/thirdparty/com/google/protobuf/RepeatedFieldBuilderV3.getMessageOrBuilderList:()Ljava/util/List;
      14: areturn
      15: aload_0
      16: getfield      #17                 // Field excludeTableCfs_:Ljava/util/List;
      19: invokestatic  #44                 // Method java/util/Collections.unmodifiableList:(Ljava/util/List;)Ljava/util/List;
      22: areturn

  public org.apache.hadoop.hbase.shaded.protobuf.generated.ReplicationProtos$TableCF$Builder addExcludeTableCfsBuilder();
    Code:
       0: aload_0
       1: invokespecial #26                 // Method getExcludeTableCfsFieldBuilder:()Lorg/apache/hbase/thirdparty/com/google/protobuf/RepeatedFieldBuilderV3;
       4: invokestatic  #170                // Method org/apache/hadoop/hbase/shaded/protobuf/generated/ReplicationProtos$TableCF.getDefaultInstance:()Lorg/apache/hadoop/hbase/shaded/protobuf/generated/ReplicationProtos$TableCF;
       7: invokevirtual #154                // Method org/apache/hbase/thirdparty/com/google/protobuf/RepeatedFieldBuilderV3.addBuilder:(Lorg/apache/hbase/thirdparty/com/google/protobuf/AbstractMessage;)Lorg/apache/hbase/thirdparty/com/google/protobuf/AbstractMessage$Builder;
      10: checkcast     #168                // class org/apache/hadoop/hbase/shaded/protobuf/generated/ReplicationProtos$TableCF$Builder
      13: areturn

  public org.apache.hadoop.hbase.shaded.protobuf.generated.ReplicationProtos$TableCF$Builder addExcludeTableCfsBuilder(int);
    Code:
       0: aload_0
       1: invokespecial #26                 // Method getExcludeTableCfsFieldBuilder:()Lorg/apache/hbase/thirdparty/com/google/protobuf/RepeatedFieldBuilderV3;
       4: iload_1
       5: invokestatic  #170                // Method org/apache/hadoop/hbase/shaded/protobuf/generated/ReplicationProtos$TableCF.getDefaultInstance:()Lorg/apache/hadoop/hbase/shaded/protobuf/generated/ReplicationProtos$TableCF;
       8: invokevirtual #155                // Method org/apache/hbase/thirdparty/com/google/protobuf/RepeatedFieldBuilderV3.addBuilder:(ILorg/apache/hbase/thirdparty/com/google/protobuf/AbstractMessage;)Lorg/apache/hbase/thirdparty/com/google/protobuf/AbstractMessage$Builder;
      11: checkcast     #168                // class org/apache/hadoop/hbase/shaded/protobuf/generated/ReplicationProtos$TableCF$Builder
      14: areturn

  public java.util.List<org.apache.hadoop.hbase.shaded.protobuf.generated.ReplicationProtos$TableCF$Builder> getExcludeTableCfsBuilderList();
    Code:
       0: aload_0
       1: invokespecial #26                 // Method getExcludeTableCfsFieldBuilder:()Lorg/apache/hbase/thirdparty/com/google/protobuf/RepeatedFieldBuilderV3;
       4: invokevirtual #156                // Method org/apache/hbase/thirdparty/com/google/protobuf/RepeatedFieldBuilderV3.getBuilderList:()Ljava/util/List;
       7: areturn

  public java.util.List<org.apache.hbase.thirdparty.com.google.protobuf.ByteString> getExcludeNamespacesList();
    Code:
       0: aload_0
       1: getfield      #18                 // Field excludeNamespaces_:Ljava/util/List;
       4: invokestatic  #44                 // Method java/util/Collections.unmodifiableList:(Ljava/util/List;)Ljava/util/List;
       7: areturn

  public int getExcludeNamespacesCount();
    Code:
       0: aload_0
       1: getfield      #18                 // Field excludeNamespaces_:Ljava/util/List;
       4: invokeinterface #133,  1          // InterfaceMethod java/util/List.size:()I
       9: ireturn

  public org.apache.hbase.thirdparty.com.google.protobuf.ByteString getExcludeNamespaces(int);
    Code:
       0: aload_0
       1: getfield      #18                 // Field excludeNamespaces_:Ljava/util/List;
       4: iload_1
       5: invokeinterface #135,  2          // InterfaceMethod java/util/List.get:(I)Ljava/lang/Object;
      10: checkcast     #122                // class org/apache/hbase/thirdparty/com/google/protobuf/ByteString
      13: areturn

  public org.apache.hadoop.hbase.shaded.protobuf.generated.ReplicationProtos$ReplicationPeer$Builder setExcludeNamespaces(int, org.apache.hbase.thirdparty.com.google.protobuf.ByteString);
    Code:
       0: aload_2
       1: ifnonnull     12
       4: new           #126                // class java/lang/NullPointerException
       7: dup
       8: invokespecial #127                // Method java/lang/NullPointerException."<init>":()V
      11: athrow
      12: aload_0
      13: invokespecial #97                 // Method ensureExcludeNamespacesIsMutable:()V
      16: aload_0
      17: getfield      #18                 // Field excludeNamespaces_:Ljava/util/List;
      20: iload_1
      21: aload_2
      22: invokeinterface #138,  3          // InterfaceMethod java/util/List.set:(ILjava/lang/Object;)Ljava/lang/Object;
      27: pop
      28: aload_0
      29: invokevirtual #68                 // Method onChanged:()V
      32: aload_0
      33: areturn

  public org.apache.hadoop.hbase.shaded.protobuf.generated.ReplicationProtos$ReplicationPeer$Builder addExcludeNamespaces(org.apache.hbase.thirdparty.com.google.protobuf.ByteString);
    Code:
       0: aload_1
       1: ifnonnull     12
       4: new           #126                // class java/lang/NullPointerException
       7: dup
       8: invokespecial #127                // Method java/lang/NullPointerException."<init>":()V
      11: athrow
      12: aload_0
      13: invokespecial #97                 // Method ensureExcludeNamespacesIsMutable:()V
      16: aload_0
      17: getfield      #18                 // Field excludeNamespaces_:Ljava/util/List;
      20: aload_1
      21: invokeinterface #141,  2          // InterfaceMethod java/util/List.add:(Ljava/lang/Object;)Z
      26: pop
      27: aload_0
      28: invokevirtual #68                 // Method onChanged:()V
      31: aload_0
      32: areturn

  public org.apache.hadoop.hbase.shaded.protobuf.generated.ReplicationProtos$ReplicationPeer$Builder addAllExcludeNamespaces(java.lang.Iterable<? extends org.apache.hbase.thirdparty.com.google.protobuf.ByteString>);
    Code:
       0: aload_0
       1: invokespecial #97                 // Method ensureExcludeNamespacesIsMutable:()V
       4: aload_1
       5: aload_0
       6: getfield      #18                 // Field excludeNamespaces_:Ljava/util/List;
       9: invokestatic  #145                // Method org/apache/hbase/thirdparty/com/google/protobuf/AbstractMessageLite$Builder.addAll:(Ljava/lang/Iterable;Ljava/util/List;)V
      12: aload_0
      13: invokevirtual #68                 // Method onChanged:()V
      16: aload_0
      17: areturn

  public org.apache.hadoop.hbase.shaded.protobuf.generated.ReplicationProtos$ReplicationPeer$Builder clearExcludeNamespaces();
    Code:
       0: aload_0
       1: invokestatic  #12                 // Method java/util/Collections.emptyList:()Ljava/util/List;
       4: putfield      #18                 // Field excludeNamespaces_:Ljava/util/List;
       7: aload_0
       8: aload_0
       9: getfield      #28                 // Field bitField0_:I
      12: sipush        -513
      15: iand
      16: putfield      #28                 // Field bitField0_:I
      19: aload_0
      20: invokevirtual #68                 // Method onChanged:()V
      23: aload_0
      24: areturn

  public boolean hasSerial();
    Code:
       0: aload_0
       1: getfield      #28                 // Field bitField0_:I
       4: sipush        1024
       7: iand
       8: sipush        1024
      11: if_icmpne     18
      14: iconst_1
      15: goto          19
      18: iconst_0
      19: ireturn

  public boolean getSerial();
    Code:
       0: aload_0
       1: getfield      #36                 // Field serial_:Z
       4: ireturn

  public org.apache.hadoop.hbase.shaded.protobuf.generated.ReplicationProtos$ReplicationPeer$Builder setSerial(boolean);
    Code:
       0: aload_0
       1: dup
       2: getfield      #28                 // Field bitField0_:I
       5: sipush        1024
       8: ior
       9: putfield      #28                 // Field bitField0_:I
      12: aload_0
      13: iload_1
      14: putfield      #36                 // Field serial_:Z
      17: aload_0
      18: invokevirtual #68                 // Method onChanged:()V
      21: aload_0
      22: areturn

  public org.apache.hadoop.hbase.shaded.protobuf.generated.ReplicationProtos$ReplicationPeer$Builder clearSerial();
    Code:
       0: aload_0
       1: aload_0
       2: getfield      #28                 // Field bitField0_:I
       5: sipush        -1025
       8: iand
       9: putfield      #28                 // Field bitField0_:I
      12: aload_0
      13: iconst_0
      14: putfield      #36                 // Field serial_:Z
      17: aload_0
      18: invokevirtual #68                 // Method onChanged:()V
      21: aload_0
      22: areturn

  public boolean hasRemoteWALDir();
    Code:
       0: aload_0
       1: getfield      #28                 // Field bitField0_:I
       4: sipush        2048
       7: iand
       8: sipush        2048
      11: if_icmpne     18
      14: iconst_1
      15: goto          19
      18: iconst_0
      19: ireturn

  public java.lang.String getRemoteWALDir();
    Code:
       0: aload_0
       1: getfield      #19                 // Field remoteWALDir_:Ljava/lang/Object;
       4: astore_1
       5: aload_1
       6: instanceof    #121                // class java/lang/String
       9: ifne          36
      12: aload_1
      13: checkcast     #122                // class org/apache/hbase/thirdparty/com/google/protobuf/ByteString
      16: astore_2
      17: aload_2
      18: invokevirtual #123                // Method org/apache/hbase/thirdparty/com/google/protobuf/ByteString.toStringUtf8:()Ljava/lang/String;
      21: astore_3
      22: aload_2
      23: invokevirtual #124                // Method org/apache/hbase/thirdparty/com/google/protobuf/ByteString.isValidUtf8:()Z
      26: ifeq          34
      29: aload_0
      30: aload_3
      31: putfield      #19                 // Field remoteWALDir_:Ljava/lang/Object;
      34: aload_3
      35: areturn
      36: aload_1
      37: checkcast     #121                // class java/lang/String
      40: areturn

  public org.apache.hbase.thirdparty.com.google.protobuf.ByteString getRemoteWALDirBytes();
    Code:
       0: aload_0
       1: getfield      #19                 // Field remoteWALDir_:Ljava/lang/Object;
       4: astore_1
       5: aload_1
       6: instanceof    #121                // class java/lang/String
       9: ifeq          27
      12: aload_1
      13: checkcast     #121                // class java/lang/String
      16: invokestatic  #125                // Method org/apache/hbase/thirdparty/com/google/protobuf/ByteString.copyFromUtf8:(Ljava/lang/String;)Lorg/apache/hbase/thirdparty/com/google/protobuf/ByteString;
      19: astore_2
      20: aload_0
      21: aload_2
      22: putfield      #19                 // Field remoteWALDir_:Ljava/lang/Object;
      25: aload_2
      26: areturn
      27: aload_1
      28: checkcast     #122                // class org/apache/hbase/thirdparty/com/google/protobuf/ByteString
      31: areturn

  public org.apache.hadoop.hbase.shaded.protobuf.generated.ReplicationProtos$ReplicationPeer$Builder setRemoteWALDir(java.lang.String);
    Code:
       0: aload_1
       1: ifnonnull     12
       4: new           #126                // class java/lang/NullPointerException
       7: dup
       8: invokespecial #127                // Method java/lang/NullPointerException."<init>":()V
      11: athrow
      12: aload_0
      13: dup
      14: getfield      #28                 // Field bitField0_:I
      17: sipush        2048
      20: ior
      21: putfield      #28                 // Field bitField0_:I
      24: aload_0
      25: aload_1
      26: putfield      #19                 // Field remoteWALDir_:Ljava/lang/Object;
      29: aload_0
      30: invokevirtual #68                 // Method onChanged:()V
      33: aload_0
      34: areturn

  public org.apache.hadoop.hbase.shaded.protobuf.generated.ReplicationProtos$ReplicationPeer$Builder clearRemoteWALDir();
    Code:
       0: aload_0
       1: aload_0
       2: getfield      #28                 // Field bitField0_:I
       5: sipush        -2049
       8: iand
       9: putfield      #28                 // Field bitField0_:I
      12: aload_0
      13: invokestatic  #37                 // Method org/apache/hadoop/hbase/shaded/protobuf/generated/ReplicationProtos$ReplicationPeer.getDefaultInstance:()Lorg/apache/hadoop/hbase/shaded/protobuf/generated/ReplicationProtos$ReplicationPeer;
      16: invokevirtual #171                // Method org/apache/hadoop/hbase/shaded/protobuf/generated/ReplicationProtos$ReplicationPeer.getRemoteWALDir:()Ljava/lang/String;
      19: putfield      #19                 // Field remoteWALDir_:Ljava/lang/Object;
      22: aload_0
      23: invokevirtual #68                 // Method onChanged:()V
      26: aload_0
      27: areturn

  public org.apache.hadoop.hbase.shaded.protobuf.generated.ReplicationProtos$ReplicationPeer$Builder setRemoteWALDirBytes(org.apache.hbase.thirdparty.com.google.protobuf.ByteString);
    Code:
       0: aload_1
       1: ifnonnull     12
       4: new           #126                // class java/lang/NullPointerException
       7: dup
       8: invokespecial #127                // Method java/lang/NullPointerException."<init>":()V
      11: athrow
      12: aload_0
      13: dup
      14: getfield      #28                 // Field bitField0_:I
      17: sipush        2048
      20: ior
      21: putfield      #28                 // Field bitField0_:I
      24: aload_0
      25: aload_1
      26: putfield      #19                 // Field remoteWALDir_:Ljava/lang/Object;
      29: aload_0
      30: invokevirtual #68                 // Method onChanged:()V
      33: aload_0
      34: areturn

  public final org.apache.hadoop.hbase.shaded.protobuf.generated.ReplicationProtos$ReplicationPeer$Builder setUnknownFields(org.apache.hbase.thirdparty.com.google.protobuf.UnknownFieldSet);
    Code:
       0: aload_0
       1: aload_1
       2: invokespecial #172                // Method org/apache/hbase/thirdparty/com/google/protobuf/GeneratedMessageV3$Builder.setUnknownFields:(Lorg/apache/hbase/thirdparty/com/google/protobuf/UnknownFieldSet;)Lorg/apache/hbase/thirdparty/com/google/protobuf/GeneratedMessageV3$Builder;
       5: checkcast     #6                  // class org/apache/hadoop/hbase/shaded/protobuf/generated/ReplicationProtos$ReplicationPeer$Builder
       8: areturn

  public final org.apache.hadoop.hbase.shaded.protobuf.generated.ReplicationProtos$ReplicationPeer$Builder mergeUnknownFields(org.apache.hbase.thirdparty.com.google.protobuf.UnknownFieldSet);
    Code:
       0: aload_0
       1: aload_1
       2: invokespecial #173                // Method org/apache/hbase/thirdparty/com/google/protobuf/GeneratedMessageV3$Builder.mergeUnknownFields:(Lorg/apache/hbase/thirdparty/com/google/protobuf/UnknownFieldSet;)Lorg/apache/hbase/thirdparty/com/google/protobuf/GeneratedMessageV3$Builder;
       5: checkcast     #6                  // class org/apache/hadoop/hbase/shaded/protobuf/generated/ReplicationProtos$ReplicationPeer$Builder
       8: areturn

  public org.apache.hbase.thirdparty.com.google.protobuf.GeneratedMessageV3$Builder mergeUnknownFields(org.apache.hbase.thirdparty.com.google.protobuf.UnknownFieldSet);
    Code:
       0: aload_0
       1: aload_1
       2: invokevirtual #104                // Method mergeUnknownFields:(Lorg/apache/hbase/thirdparty/com/google/protobuf/UnknownFieldSet;)Lorg/apache/hadoop/hbase/shaded/protobuf/generated/ReplicationProtos$ReplicationPeer$Builder;
       5: areturn

  public org.apache.hbase.thirdparty.com.google.protobuf.GeneratedMessageV3$Builder setUnknownFields(org.apache.hbase.thirdparty.com.google.protobuf.UnknownFieldSet);
    Code:
       0: aload_0
       1: aload_1
       2: invokevirtual #174                // Method setUnknownFields:(Lorg/apache/hbase/thirdparty/com/google/protobuf/UnknownFieldSet;)Lorg/apache/hadoop/hbase/shaded/protobuf/generated/ReplicationProtos$ReplicationPeer$Builder;
       5: areturn

  public org.apache.hbase.thirdparty.com.google.protobuf.GeneratedMessageV3$Builder addRepeatedField(org.apache.hbase.thirdparty.com.google.protobuf.Descriptors$FieldDescriptor, java.lang.Object);
    Code:
       0: aload_0
       1: aload_1
       2: aload_2
       3: invokevirtual #175                // Method addRepeatedField:(Lorg/apache/hbase/thirdparty/com/google/protobuf/Descriptors$FieldDescriptor;Ljava/lang/Object;)Lorg/apache/hadoop/hbase/shaded/protobuf/generated/ReplicationProtos$ReplicationPeer$Builder;
       6: areturn

  public org.apache.hbase.thirdparty.com.google.protobuf.GeneratedMessageV3$Builder setRepeatedField(org.apache.hbase.thirdparty.com.google.protobuf.Descriptors$FieldDescriptor, int, java.lang.Object);
    Code:
       0: aload_0
       1: aload_1
       2: iload_2
       3: aload_3
       4: invokevirtual #176                // Method setRepeatedField:(Lorg/apache/hbase/thirdparty/com/google/protobuf/Descriptors$FieldDescriptor;ILjava/lang/Object;)Lorg/apache/hadoop/hbase/shaded/protobuf/generated/ReplicationProtos$ReplicationPeer$Builder;
       7: areturn

  public org.apache.hbase.thirdparty.com.google.protobuf.GeneratedMessageV3$Builder clearOneof(org.apache.hbase.thirdparty.com.google.protobuf.Descriptors$OneofDescriptor);
    Code:
       0: aload_0
       1: aload_1
       2: invokevirtual #177                // Method clearOneof:(Lorg/apache/hbase/thirdparty/com/google/protobuf/Descriptors$OneofDescriptor;)Lorg/apache/hadoop/hbase/shaded/protobuf/generated/ReplicationProtos$ReplicationPeer$Builder;
       5: areturn

  public org.apache.hbase.thirdparty.com.google.protobuf.GeneratedMessageV3$Builder clearField(org.apache.hbase.thirdparty.com.google.protobuf.Descriptors$FieldDescriptor);
    Code:
       0: aload_0
       1: aload_1
       2: invokevirtual #178                // Method clearField:(Lorg/apache/hbase/thirdparty/com/google/protobuf/Descriptors$FieldDescriptor;)Lorg/apache/hadoop/hbase/shaded/protobuf/generated/ReplicationProtos$ReplicationPeer$Builder;
       5: areturn

  public org.apache.hbase.thirdparty.com.google.protobuf.GeneratedMessageV3$Builder setField(org.apache.hbase.thirdparty.com.google.protobuf.Descriptors$FieldDescriptor, java.lang.Object);
    Code:
       0: aload_0
       1: aload_1
       2: aload_2
       3: invokevirtual #179                // Method setField:(Lorg/apache/hbase/thirdparty/com/google/protobuf/Descriptors$FieldDescriptor;Ljava/lang/Object;)Lorg/apache/hadoop/hbase/shaded/protobuf/generated/ReplicationProtos$ReplicationPeer$Builder;
       6: areturn

  public org.apache.hbase.thirdparty.com.google.protobuf.GeneratedMessageV3$Builder clear();
    Code:
       0: aload_0
       1: invokevirtual #180                // Method clear:()Lorg/apache/hadoop/hbase/shaded/protobuf/generated/ReplicationProtos$ReplicationPeer$Builder;
       4: areturn

  public org.apache.hbase.thirdparty.com.google.protobuf.GeneratedMessageV3$Builder clone();
    Code:
       0: aload_0
       1: invokevirtual #181                // Method clone:()Lorg/apache/hadoop/hbase/shaded/protobuf/generated/ReplicationProtos$ReplicationPeer$Builder;
       4: areturn

  public org.apache.hbase.thirdparty.com.google.protobuf.AbstractMessage$Builder mergeUnknownFields(org.apache.hbase.thirdparty.com.google.protobuf.UnknownFieldSet);
    Code:
       0: aload_0
       1: aload_1
       2: invokevirtual #104                // Method mergeUnknownFields:(Lorg/apache/hbase/thirdparty/com/google/protobuf/UnknownFieldSet;)Lorg/apache/hadoop/hbase/shaded/protobuf/generated/ReplicationProtos$ReplicationPeer$Builder;
       5: areturn

  public org.apache.hbase.thirdparty.com.google.protobuf.AbstractMessage$Builder mergeFrom(org.apache.hbase.thirdparty.com.google.protobuf.CodedInputStream, org.apache.hbase.thirdparty.com.google.protobuf.ExtensionRegistryLite) throws java.io.IOException;
    Code:
       0: aload_0
       1: aload_1
       2: aload_2
       3: invokevirtual #182                // Method mergeFrom:(Lorg/apache/hbase/thirdparty/com/google/protobuf/CodedInputStream;Lorg/apache/hbase/thirdparty/com/google/protobuf/ExtensionRegistryLite;)Lorg/apache/hadoop/hbase/shaded/protobuf/generated/ReplicationProtos$ReplicationPeer$Builder;
       6: areturn

  public org.apache.hbase.thirdparty.com.google.protobuf.AbstractMessage$Builder mergeFrom(org.apache.hbase.thirdparty.com.google.protobuf.Message);
    Code:
       0: aload_0
       1: aload_1
       2: invokevirtual #183                // Method mergeFrom:(Lorg/apache/hbase/thirdparty/com/google/protobuf/Message;)Lorg/apache/hadoop/hbase/shaded/protobuf/generated/ReplicationProtos$ReplicationPeer$Builder;
       5: areturn

  public org.apache.hbase.thirdparty.com.google.protobuf.AbstractMessage$Builder clear();
    Code:
       0: aload_0
       1: invokevirtual #180                // Method clear:()Lorg/apache/hadoop/hbase/shaded/protobuf/generated/ReplicationProtos$ReplicationPeer$Builder;
       4: areturn

  public org.apache.hbase.thirdparty.com.google.protobuf.AbstractMessage$Builder clearOneof(org.apache.hbase.thirdparty.com.google.protobuf.Descriptors$OneofDescriptor);
    Code:
       0: aload_0
       1: aload_1
       2: invokevirtual #177                // Method clearOneof:(Lorg/apache/hbase/thirdparty/com/google/protobuf/Descriptors$OneofDescriptor;)Lorg/apache/hadoop/hbase/shaded/protobuf/generated/ReplicationProtos$ReplicationPeer$Builder;
       5: areturn

  public org.apache.hbase.thirdparty.com.google.protobuf.AbstractMessage$Builder clone();
    Code:
       0: aload_0
       1: invokevirtual #181                // Method clone:()Lorg/apache/hadoop/hbase/shaded/protobuf/generated/ReplicationProtos$ReplicationPeer$Builder;
       4: areturn

  public org.apache.hbase.thirdparty.com.google.protobuf.Message$Builder mergeUnknownFields(org.apache.hbase.thirdparty.com.google.protobuf.UnknownFieldSet);
    Code:
       0: aload_0
       1: aload_1
       2: invokevirtual #104                // Method mergeUnknownFields:(Lorg/apache/hbase/thirdparty/com/google/protobuf/UnknownFieldSet;)Lorg/apache/hadoop/hbase/shaded/protobuf/generated/ReplicationProtos$ReplicationPeer$Builder;
       5: areturn

  public org.apache.hbase.thirdparty.com.google.protobuf.Message$Builder setUnknownFields(org.apache.hbase.thirdparty.com.google.protobuf.UnknownFieldSet);
    Code:
       0: aload_0
       1: aload_1
       2: invokevirtual #174                // Method setUnknownFields:(Lorg/apache/hbase/thirdparty/com/google/protobuf/UnknownFieldSet;)Lorg/apache/hadoop/hbase/shaded/protobuf/generated/ReplicationProtos$ReplicationPeer$Builder;
       5: areturn

  public org.apache.hbase.thirdparty.com.google.protobuf.Message$Builder addRepeatedField(org.apache.hbase.thirdparty.com.google.protobuf.Descriptors$FieldDescriptor, java.lang.Object);
    Code:
       0: aload_0
       1: aload_1
       2: aload_2
       3: invokevirtual #175                // Method addRepeatedField:(Lorg/apache/hbase/thirdparty/com/google/protobuf/Descriptors$FieldDescriptor;Ljava/lang/Object;)Lorg/apache/hadoop/hbase/shaded/protobuf/generated/ReplicationProtos$ReplicationPeer$Builder;
       6: areturn

  public org.apache.hbase.thirdparty.com.google.protobuf.Message$Builder setRepeatedField(org.apache.hbase.thirdparty.com.google.protobuf.Descriptors$FieldDescriptor, int, java.lang.Object);
    Code:
       0: aload_0
       1: aload_1
       2: iload_2
       3: aload_3
       4: invokevirtual #176                // Method setRepeatedField:(Lorg/apache/hbase/thirdparty/com/google/protobuf/Descriptors$FieldDescriptor;ILjava/lang/Object;)Lorg/apache/hadoop/hbase/shaded/protobuf/generated/ReplicationProtos$ReplicationPeer$Builder;
       7: areturn

  public org.apache.hbase.thirdparty.com.google.protobuf.Message$Builder clearOneof(org.apache.hbase.thirdparty.com.google.protobuf.Descriptors$OneofDescriptor);
    Code:
       0: aload_0
       1: aload_1
       2: invokevirtual #177                // Method clearOneof:(Lorg/apache/hbase/thirdparty/com/google/protobuf/Descriptors$OneofDescriptor;)Lorg/apache/hadoop/hbase/shaded/protobuf/generated/ReplicationProtos$ReplicationPeer$Builder;
       5: areturn

  public org.apache.hbase.thirdparty.com.google.protobuf.Message$Builder clearField(org.apache.hbase.thirdparty.com.google.protobuf.Descriptors$FieldDescriptor);
    Code:
       0: aload_0
       1: aload_1
       2: invokevirtual #178                // Method clearField:(Lorg/apache/hbase/thirdparty/com/google/protobuf/Descriptors$FieldDescriptor;)Lorg/apache/hadoop/hbase/shaded/protobuf/generated/ReplicationProtos$ReplicationPeer$Builder;
       5: areturn

  public org.apache.hbase.thirdparty.com.google.protobuf.Message$Builder setField(org.apache.hbase.thirdparty.com.google.protobuf.Descriptors$FieldDescriptor, java.lang.Object);
    Code:
       0: aload_0
       1: aload_1
       2: aload_2
       3: invokevirtual #179                // Method setField:(Lorg/apache/hbase/thirdparty/com/google/protobuf/Descriptors$FieldDescriptor;Ljava/lang/Object;)Lorg/apache/hadoop/hbase/shaded/protobuf/generated/ReplicationProtos$ReplicationPeer$Builder;
       6: areturn

  public org.apache.hbase.thirdparty.com.google.protobuf.Message$Builder mergeFrom(org.apache.hbase.thirdparty.com.google.protobuf.CodedInputStream, org.apache.hbase.thirdparty.com.google.protobuf.ExtensionRegistryLite) throws java.io.IOException;
    Code:
       0: aload_0
       1: aload_1
       2: aload_2
       3: invokevirtual #182                // Method mergeFrom:(Lorg/apache/hbase/thirdparty/com/google/protobuf/CodedInputStream;Lorg/apache/hbase/thirdparty/com/google/protobuf/ExtensionRegistryLite;)Lorg/apache/hadoop/hbase/shaded/protobuf/generated/ReplicationProtos$ReplicationPeer$Builder;
       6: areturn

  public org.apache.hbase.thirdparty.com.google.protobuf.Message$Builder clone();
    Code:
       0: aload_0
       1: invokevirtual #181                // Method clone:()Lorg/apache/hadoop/hbase/shaded/protobuf/generated/ReplicationProtos$ReplicationPeer$Builder;
       4: areturn

  public org.apache.hbase.thirdparty.com.google.protobuf.Message buildPartial();
    Code:
       0: aload_0
       1: invokevirtual #38                 // Method buildPartial:()Lorg/apache/hadoop/hbase/shaded/protobuf/generated/ReplicationProtos$ReplicationPeer;
       4: areturn

  public org.apache.hbase.thirdparty.com.google.protobuf.Message build();
    Code:
       0: aload_0
       1: invokevirtual #184                // Method build:()Lorg/apache/hadoop/hbase/shaded/protobuf/generated/ReplicationProtos$ReplicationPeer;
       4: areturn

  public org.apache.hbase.thirdparty.com.google.protobuf.Message$Builder mergeFrom(org.apache.hbase.thirdparty.com.google.protobuf.Message);
    Code:
       0: aload_0
       1: aload_1
       2: invokevirtual #183                // Method mergeFrom:(Lorg/apache/hbase/thirdparty/com/google/protobuf/Message;)Lorg/apache/hadoop/hbase/shaded/protobuf/generated/ReplicationProtos$ReplicationPeer$Builder;
       5: areturn

  public org.apache.hbase.thirdparty.com.google.protobuf.Message$Builder clear();
    Code:
       0: aload_0
       1: invokevirtual #180                // Method clear:()Lorg/apache/hadoop/hbase/shaded/protobuf/generated/ReplicationProtos$ReplicationPeer$Builder;
       4: areturn

  public org.apache.hbase.thirdparty.com.google.protobuf.MessageLite$Builder mergeFrom(org.apache.hbase.thirdparty.com.google.protobuf.CodedInputStream, org.apache.hbase.thirdparty.com.google.protobuf.ExtensionRegistryLite) throws java.io.IOException;
    Code:
       0: aload_0
       1: aload_1
       2: aload_2
       3: invokevirtual #182                // Method mergeFrom:(Lorg/apache/hbase/thirdparty/com/google/protobuf/CodedInputStream;Lorg/apache/hbase/thirdparty/com/google/protobuf/ExtensionRegistryLite;)Lorg/apache/hadoop/hbase/shaded/protobuf/generated/ReplicationProtos$ReplicationPeer$Builder;
       6: areturn

  public org.apache.hbase.thirdparty.com.google.protobuf.MessageLite$Builder clone();
    Code:
       0: aload_0
       1: invokevirtual #181                // Method clone:()Lorg/apache/hadoop/hbase/shaded/protobuf/generated/ReplicationProtos$ReplicationPeer$Builder;
       4: areturn

  public org.apache.hbase.thirdparty.com.google.protobuf.MessageLite buildPartial();
    Code:
       0: aload_0
       1: invokevirtual #38                 // Method buildPartial:()Lorg/apache/hadoop/hbase/shaded/protobuf/generated/ReplicationProtos$ReplicationPeer;
       4: areturn

  public org.apache.hbase.thirdparty.com.google.protobuf.MessageLite build();
    Code:
       0: aload_0
       1: invokevirtual #184                // Method build:()Lorg/apache/hadoop/hbase/shaded/protobuf/generated/ReplicationProtos$ReplicationPeer;
       4: areturn

  public org.apache.hbase.thirdparty.com.google.protobuf.MessageLite$Builder clear();
    Code:
       0: aload_0
       1: invokevirtual #180                // Method clear:()Lorg/apache/hadoop/hbase/shaded/protobuf/generated/ReplicationProtos$ReplicationPeer$Builder;
       4: areturn

  public org.apache.hbase.thirdparty.com.google.protobuf.MessageLite getDefaultInstanceForType();
    Code:
       0: aload_0
       1: invokevirtual #185                // Method getDefaultInstanceForType:()Lorg/apache/hadoop/hbase/shaded/protobuf/generated/ReplicationProtos$ReplicationPeer;
       4: areturn

  public org.apache.hbase.thirdparty.com.google.protobuf.Message getDefaultInstanceForType();
    Code:
       0: aload_0
       1: invokevirtual #185                // Method getDefaultInstanceForType:()Lorg/apache/hadoop/hbase/shaded/protobuf/generated/ReplicationProtos$ReplicationPeer;
       4: areturn

  public org.apache.hbase.thirdparty.com.google.protobuf.AbstractMessageLite$Builder mergeFrom(org.apache.hbase.thirdparty.com.google.protobuf.CodedInputStream, org.apache.hbase.thirdparty.com.google.protobuf.ExtensionRegistryLite) throws java.io.IOException;
    Code:
       0: aload_0
       1: aload_1
       2: aload_2
       3: invokevirtual #182                // Method mergeFrom:(Lorg/apache/hbase/thirdparty/com/google/protobuf/CodedInputStream;Lorg/apache/hbase/thirdparty/com/google/protobuf/ExtensionRegistryLite;)Lorg/apache/hadoop/hbase/shaded/protobuf/generated/ReplicationProtos$ReplicationPeer$Builder;
       6: areturn

  public org.apache.hbase.thirdparty.com.google.protobuf.AbstractMessageLite$Builder clone();
    Code:
       0: aload_0
       1: invokevirtual #181                // Method clone:()Lorg/apache/hadoop/hbase/shaded/protobuf/generated/ReplicationProtos$ReplicationPeer$Builder;
       4: areturn

  public java.lang.Object clone() throws java.lang.CloneNotSupportedException;
    Code:
       0: aload_0
       1: invokevirtual #181                // Method clone:()Lorg/apache/hadoop/hbase/shaded/protobuf/generated/ReplicationProtos$ReplicationPeer$Builder;
       4: areturn

  org.apache.hadoop.hbase.shaded.protobuf.generated.ReplicationProtos$ReplicationPeer$Builder(org.apache.hadoop.hbase.shaded.protobuf.generated.ReplicationProtos$1);
    Code:
       0: aload_0
       1: invokespecial #2                  // Method "<init>":()V
       4: return

  org.apache.hadoop.hbase.shaded.protobuf.generated.ReplicationProtos$ReplicationPeer$Builder(org.apache.hbase.thirdparty.com.google.protobuf.GeneratedMessageV3$BuilderParent, org.apache.hadoop.hbase.shaded.protobuf.generated.ReplicationProtos$1);
    Code:
       0: aload_0
       1: aload_1
       2: invokespecial #1                  // Method "<init>":(Lorg/apache/hbase/thirdparty/com/google/protobuf/GeneratedMessageV3$BuilderParent;)V
       5: return
}
