Compiled from "ReplicationLogCleaner.java"
public class org.apache.hadoop.hbase.replication.master.ReplicationLogCleaner extends org.apache.hadoop.hbase.master.cleaner.BaseLogCleanerDelegate {
  public org.apache.hadoop.hbase.replication.master.ReplicationLogCleaner();
    Code:
       0: aload_0
       1: invokespecial #4                  // Method org/apache/hadoop/hbase/master/cleaner/BaseLogCleanerDelegate."<init>":()V
       4: aload_0
       5: iconst_0
       6: putfield      #5                  // Field stopped:Z
       9: aload_0
      10: lconst_0
      11: putfield      #1                  // Field readZKTimestamp:J
      14: return

  public void preClean();
    Code:
       0: aload_0
       1: invokestatic  #6                  // Method org/apache/hadoop/hbase/util/EnvironmentEdgeManager.currentTime:()J
       4: putfield      #1                  // Field readZKTimestamp:J
       7: aload_0
       8: aload_0
       9: getfield      #7                  // Field queueStorage:Lorg/apache/hadoop/hbase/replication/ReplicationQueueStorage;
      12: invokeinterface #8,  1            // InterfaceMethod org/apache/hadoop/hbase/replication/ReplicationQueueStorage.getAllWALs:()Ljava/util/Set;
      17: putfield      #3                  // Field wals:Ljava/util/Set;
      20: goto          39
      23: astore_1
      24: getstatic     #2                  // Field LOG:Lorg/slf4j/Logger;
      27: ldc           #10                 // String Failed to read zookeeper, skipping checking deletable files
      29: invokeinterface #11,  2           // InterfaceMethod org/slf4j/Logger.warn:(Ljava/lang/String;)V
      34: aload_0
      35: aconst_null
      36: putfield      #3                  // Field wals:Ljava/util/Set;
      39: return
    Exception table:
       from    to  target type
           7    20    23   Class org/apache/hadoop/hbase/replication/ReplicationException

  public java.lang.Iterable<org.apache.hadoop.fs.FileStatus> getDeletableFiles(java.lang.Iterable<org.apache.hadoop.fs.FileStatus>);
    Code:
       0: aload_0
       1: invokevirtual #12                 // Method getConf:()Lorg/apache/hadoop/conf/Configuration;
       4: ifnonnull     9
       7: aload_1
       8: areturn
       9: aload_0
      10: getfield      #3                  // Field wals:Ljava/util/Set;
      13: ifnonnull     20
      16: invokestatic  #13                 // Method java/util/Collections.emptyList:()Ljava/util/List;
      19: areturn
      20: aload_1
      21: new           #14                 // class org/apache/hadoop/hbase/replication/master/ReplicationLogCleaner$1
      24: dup
      25: aload_0
      26: invokespecial #15                 // Method org/apache/hadoop/hbase/replication/master/ReplicationLogCleaner$1."<init>":(Lorg/apache/hadoop/hbase/replication/master/ReplicationLogCleaner;)V
      29: invokestatic  #16                 // Method org/apache/hbase/thirdparty/com/google/common/collect/Iterables.filter:(Ljava/lang/Iterable;Lorg/apache/hbase/thirdparty/com/google/common/base/Predicate;)Ljava/lang/Iterable;
      32: areturn

  public void setConf(org.apache.hadoop.conf.Configuration);
    Code:
       0: new           #17                 // class org/apache/hadoop/conf/Configuration
       3: dup
       4: aload_1
       5: invokespecial #18                 // Method org/apache/hadoop/conf/Configuration."<init>":(Lorg/apache/hadoop/conf/Configuration;)V
       8: astore_2
       9: aload_0
      10: aload_2
      11: new           #19                 // class org/apache/hadoop/hbase/zookeeper/ZKWatcher
      14: dup
      15: aload_2
      16: ldc           #20                 // String replicationLogCleaner
      18: aconst_null
      19: invokespecial #21                 // Method org/apache/hadoop/hbase/zookeeper/ZKWatcher."<init>":(Lorg/apache/hadoop/conf/Configuration;Ljava/lang/String;Lorg/apache/hadoop/hbase/Abortable;)V
      22: invokevirtual #22                 // Method setConf:(Lorg/apache/hadoop/conf/Configuration;Lorg/apache/hadoop/hbase/zookeeper/ZKWatcher;)V
      25: goto          63
      28: astore_3
      29: getstatic     #2                  // Field LOG:Lorg/slf4j/Logger;
      32: new           #24                 // class java/lang/StringBuilder
      35: dup
      36: invokespecial #25                 // Method java/lang/StringBuilder."<init>":()V
      39: ldc           #26                 // String Error while configuring
      41: invokevirtual #27                 // Method java/lang/StringBuilder.append:(Ljava/lang/String;)Ljava/lang/StringBuilder;
      44: aload_0
      45: invokevirtual #28                 // Method java/lang/Object.getClass:()Ljava/lang/Class;
      48: invokevirtual #29                 // Method java/lang/Class.getName:()Ljava/lang/String;
      51: invokevirtual #27                 // Method java/lang/StringBuilder.append:(Ljava/lang/String;)Ljava/lang/StringBuilder;
      54: invokevirtual #30                 // Method java/lang/StringBuilder.toString:()Ljava/lang/String;
      57: aload_3
      58: invokeinterface #31,  3           // InterfaceMethod org/slf4j/Logger.error:(Ljava/lang/String;Ljava/lang/Throwable;)V
      63: return
    Exception table:
       from    to  target type
           9    25    28   Class java/io/IOException

  public void setConf(org.apache.hadoop.conf.Configuration, org.apache.hadoop.hbase.zookeeper.ZKWatcher);
    Code:
       0: aload_0
       1: aload_1
       2: invokespecial #32                 // Method org/apache/hadoop/hbase/master/cleaner/BaseLogCleanerDelegate.setConf:(Lorg/apache/hadoop/conf/Configuration;)V
       5: aload_0
       6: aload_2
       7: putfield      #33                 // Field zkw:Lorg/apache/hadoop/hbase/zookeeper/ZKWatcher;
      10: aload_0
      11: aload_2
      12: aload_1
      13: invokestatic  #34                 // Method org/apache/hadoop/hbase/replication/ReplicationStorageFactory.getReplicationQueueStorage:(Lorg/apache/hadoop/hbase/zookeeper/ZKWatcher;Lorg/apache/hadoop/conf/Configuration;)Lorg/apache/hadoop/hbase/replication/ReplicationQueueStorage;
      16: putfield      #7                  // Field queueStorage:Lorg/apache/hadoop/hbase/replication/ReplicationQueueStorage;
      19: goto          57
      22: astore_3
      23: getstatic     #2                  // Field LOG:Lorg/slf4j/Logger;
      26: new           #24                 // class java/lang/StringBuilder
      29: dup
      30: invokespecial #25                 // Method java/lang/StringBuilder."<init>":()V
      33: ldc           #26                 // String Error while configuring
      35: invokevirtual #27                 // Method java/lang/StringBuilder.append:(Ljava/lang/String;)Ljava/lang/StringBuilder;
      38: aload_0
      39: invokevirtual #28                 // Method java/lang/Object.getClass:()Ljava/lang/Class;
      42: invokevirtual #29                 // Method java/lang/Class.getName:()Ljava/lang/String;
      45: invokevirtual #27                 // Method java/lang/StringBuilder.append:(Ljava/lang/String;)Ljava/lang/StringBuilder;
      48: invokevirtual #30                 // Method java/lang/StringBuilder.toString:()Ljava/lang/String;
      51: aload_3
      52: invokeinterface #31,  3           // InterfaceMethod org/slf4j/Logger.error:(Ljava/lang/String;Ljava/lang/Throwable;)V
      57: return
    Exception table:
       from    to  target type
           5    19    22   Class java/lang/Exception

  public void setConf(org.apache.hadoop.conf.Configuration, org.apache.hadoop.hbase.zookeeper.ZKWatcher, org.apache.hadoop.hbase.replication.ReplicationQueueStorage);
    Code:
       0: aload_0
       1: aload_1
       2: invokespecial #32                 // Method org/apache/hadoop/hbase/master/cleaner/BaseLogCleanerDelegate.setConf:(Lorg/apache/hadoop/conf/Configuration;)V
       5: aload_0
       6: aload_2
       7: putfield      #33                 // Field zkw:Lorg/apache/hadoop/hbase/zookeeper/ZKWatcher;
      10: aload_0
      11: aload_3
      12: putfield      #7                  // Field queueStorage:Lorg/apache/hadoop/hbase/replication/ReplicationQueueStorage;
      15: return

  public void stop(java.lang.String);
    Code:
       0: aload_0
       1: getfield      #5                  // Field stopped:Z
       4: ifeq          8
       7: return
       8: aload_0
       9: iconst_1
      10: putfield      #5                  // Field stopped:Z
      13: aload_0
      14: getfield      #33                 // Field zkw:Lorg/apache/hadoop/hbase/zookeeper/ZKWatcher;
      17: ifnull        57
      20: getstatic     #2                  // Field LOG:Lorg/slf4j/Logger;
      23: new           #24                 // class java/lang/StringBuilder
      26: dup
      27: invokespecial #25                 // Method java/lang/StringBuilder."<init>":()V
      30: ldc           #36                 // String Stopping
      32: invokevirtual #27                 // Method java/lang/StringBuilder.append:(Ljava/lang/String;)Ljava/lang/StringBuilder;
      35: aload_0
      36: getfield      #33                 // Field zkw:Lorg/apache/hadoop/hbase/zookeeper/ZKWatcher;
      39: invokevirtual #37                 // Method java/lang/StringBuilder.append:(Ljava/lang/Object;)Ljava/lang/StringBuilder;
      42: invokevirtual #30                 // Method java/lang/StringBuilder.toString:()Ljava/lang/String;
      45: invokeinterface #38,  2           // InterfaceMethod org/slf4j/Logger.info:(Ljava/lang/String;)V
      50: aload_0
      51: getfield      #33                 // Field zkw:Lorg/apache/hadoop/hbase/zookeeper/ZKWatcher;
      54: invokevirtual #39                 // Method org/apache/hadoop/hbase/zookeeper/ZKWatcher.close:()V
      57: return

  public boolean isStopped();
    Code:
       0: aload_0
       1: getfield      #5                  // Field stopped:Z
       4: ireturn

  static java.util.Set access$000(org.apache.hadoop.hbase.replication.master.ReplicationLogCleaner);
    Code:
       0: aload_0
       1: getfield      #3                  // Field wals:Ljava/util/Set;
       4: areturn

  static org.slf4j.Logger access$100();
    Code:
       0: getstatic     #2                  // Field LOG:Lorg/slf4j/Logger;
       3: areturn

  static long access$200(org.apache.hadoop.hbase.replication.master.ReplicationLogCleaner);
    Code:
       0: aload_0
       1: getfield      #1                  // Field readZKTimestamp:J
       4: lreturn

  static {};
    Code:
       0: ldc           #40                 // class org/apache/hadoop/hbase/replication/master/ReplicationLogCleaner
       2: invokestatic  #41                 // Method org/slf4j/LoggerFactory.getLogger:(Ljava/lang/Class;)Lorg/slf4j/Logger;
       5: putstatic     #2                  // Field LOG:Lorg/slf4j/Logger;
       8: return
}
