Compiled from "ReplicationPeer.java"
public interface org.apache.hadoop.hbase.replication.ReplicationPeer {
  public abstract java.lang.String getId();

  public abstract org.apache.hadoop.hbase.replication.ReplicationPeer$PeerState getPeerState();

  public abstract org.apache.hadoop.hbase.replication.SyncReplicationState getSyncReplicationState();

  public boolean isPeerEnabled();
    Code:
       0: aload_0
       1: invokeinterface #1,  1            // InterfaceMethod getPeerState:()Lorg/apache/hadoop/hbase/replication/ReplicationPeer$PeerState;
       6: getstatic     #2                  // Field org/apache/hadoop/hbase/replication/ReplicationPeer$PeerState.ENABLED:Lorg/apache/hadoop/hbase/replication/ReplicationPeer$PeerState;
       9: if_acmpne     16
      12: iconst_1
      13: goto          17
      16: iconst_0
      17: ireturn

  public abstract org.apache.hadoop.hbase.replication.ReplicationPeerConfig getPeerConfig();

  public abstract org.apache.hadoop.conf.Configuration getConfiguration();

  public abstract java.util.Map<org.apache.hadoop.hbase.TableName, java.util.List<java.lang.String>> getTableCFs();

  public abstract java.util.Set<java.lang.String> getNamespaces();

  public abstract long getPeerBandwidth();

  public abstract void registerPeerConfigListener(org.apache.hadoop.hbase.replication.ReplicationPeerConfigListener);

  public void trackPeerConfigChanges(org.apache.hadoop.hbase.replication.ReplicationPeerConfigListener);
    Code:
       0: aload_0
       1: aload_1
       2: invokeinterface #3,  2            // InterfaceMethod registerPeerConfigListener:(Lorg/apache/hadoop/hbase/replication/ReplicationPeerConfigListener;)V
       7: return
}
