Compiled from "ResourceChecker.java"
abstract class org.apache.hadoop.hbase.ResourceChecker$ResourceAnalyzer {
  org.apache.hadoop.hbase.ResourceChecker$ResourceAnalyzer();
    Code:
       0: aload_0
       1: invokespecial #1                  // Method java/lang/Object."<init>":()V
       4: return

  public int getMax();
    Code:
       0: ldc           #3                  // int 2147483647
       2: ireturn

  public int getMin();
    Code:
       0: ldc           #4                  // int -2147483648
       2: ireturn

  public java.lang.String getName();
    Code:
       0: aload_0
       1: invokevirtual #5                  // Method java/lang/Object.getClass:()Ljava/lang/Class;
       4: invokevirtual #6                  // Method java/lang/Class.getSimpleName:()Ljava/lang/String;
       7: astore_1
       8: ldc           #7                  // class org/apache/hadoop/hbase/ResourceChecker$ResourceAnalyzer
      10: invokevirtual #6                  // Method java/lang/Class.getSimpleName:()Ljava/lang/String;
      13: astore_2
      14: aload_1
      15: aload_2
      16: invokevirtual #8                  // Method java/lang/String.endsWith:(Ljava/lang/String;)Z
      19: ifeq          37
      22: aload_1
      23: iconst_0
      24: aload_1
      25: invokevirtual #9                  // Method java/lang/String.length:()I
      28: aload_2
      29: invokevirtual #9                  // Method java/lang/String.length:()I
      32: isub
      33: invokevirtual #10                 // Method java/lang/String.substring:(II)Ljava/lang/String;
      36: areturn
      37: aload_1
      38: areturn

  public abstract int getVal(org.apache.hadoop.hbase.ResourceChecker$Phase);

  public java.util.List<java.lang.String> getStringsToLog();
    Code:
       0: aconst_null
       1: areturn
}
