Compiled from "ResourceCheckerJUnitListener.java"
class org.apache.hadoop.hbase.ResourceCheckerJUnitListener$AvailableMemoryMBResourceAnalyzer extends org.apache.hadoop.hbase.ResourceChecker$ResourceAnalyzer {
  org.apache.hadoop.hbase.ResourceCheckerJUnitListener$AvailableMemoryMBResourceAnalyzer();
    Code:
       0: aload_0
       1: invokespecial #1                  // Method org/apache/hadoop/hbase/ResourceChecker$ResourceAnalyzer."<init>":()V
       4: return

  public int getVal(org.apache.hadoop.hbase.ResourceChecker$Phase);
    Code:
       0: invokestatic  #2                  // Method org/apache/hadoop/hbase/util/JVM.isUnix:()Z
       3: ifne          8
       6: iconst_0
       7: ireturn
       8: new           #3                  // class org/apache/hadoop/hbase/util/JVM
      11: dup
      12: invokespecial #4                  // Method org/apache/hadoop/hbase/util/JVM."<init>":()V
      15: invokevirtual #5                  // Method org/apache/hadoop/hbase/util/JVM.getFreeMemory:()J
      18: ldc2_w        #6                  // long 1048576l
      21: ldiv
      22: l2i
      23: ireturn
}
