Compiled from "ResourceChecker.java"
public class org.apache.hadoop.hbase.ResourceChecker {
  static final boolean $assertionsDisabled;

  public org.apache.hadoop.hbase.ResourceChecker(java.lang.String);
    Code:
       0: aload_0
       1: invokespecial #1                  // Method java/lang/Object."<init>":()V
       4: aload_0
       5: new           #2                  // class java/util/ArrayList
       8: dup
       9: invokespecial #3                  // Method java/util/ArrayList."<init>":()V
      12: putfield      #4                  // Field ras:Ljava/util/List;
      15: aload_0
      16: aload_1
      17: putfield      #5                  // Field tagLine:Ljava/lang/String;
      20: return

  public void checkInit();
    Code:
       0: aload_0
       1: aload_0
       2: getfield      #7                  // Field initialValues:[I
       5: invokespecial #17                 // Method check:([I)V
       8: return

  public void start();
    Code:
       0: aload_0
       1: getfield      #4                  // Field ras:Ljava/util/List;
       4: invokeinterface #47,  1           // InterfaceMethod java/util/List.isEmpty:()Z
       9: ifeq          23
      12: getstatic     #19                 // Field LOG:Lorg/slf4j/Logger;
      15: ldc           #48                 // String No resource analyzer
      17: invokeinterface #36,  2           // InterfaceMethod org/slf4j/Logger.info:(Ljava/lang/String;)V
      22: return
      23: aload_0
      24: invokespecial #49                 // Method fillInit:()V
      27: aload_0
      28: invokespecial #50                 // Method logInit:()V
      31: aload_0
      32: invokevirtual #51                 // Method checkInit:()V
      35: return

  public void end();
    Code:
       0: aload_0
       1: getfield      #4                  // Field ras:Ljava/util/List;
       4: invokeinterface #47,  1           // InterfaceMethod java/util/List.isEmpty:()Z
       9: ifeq          23
      12: getstatic     #19                 // Field LOG:Lorg/slf4j/Logger;
      15: ldc           #48                 // String No resource analyzer
      17: invokeinterface #36,  2           // InterfaceMethod org/slf4j/Logger.info:(Ljava/lang/String;)V
      22: return
      23: aload_0
      24: getfield      #7                  // Field initialValues:[I
      27: ifnonnull     41
      30: getstatic     #19                 // Field LOG:Lorg/slf4j/Logger;
      33: ldc           #52                 // String No initial values
      35: invokeinterface #28,  2           // InterfaceMethod org/slf4j/Logger.warn:(Ljava/lang/String;)V
      40: return
      41: aload_0
      42: invokespecial #53                 // Method fillEndings:()V
      45: aload_0
      46: invokespecial #54                 // Method logEndings:()V
      49: aload_0
      50: invokespecial #55                 // Method checkEndings:()V
      53: return

  public void addResourceAnalyzer(org.apache.hadoop.hbase.ResourceChecker$ResourceAnalyzer);
    Code:
       0: aload_0
       1: getfield      #4                  // Field ras:Ljava/util/List;
       4: aload_1
       5: invokeinterface #56,  2           // InterfaceMethod java/util/List.add:(Ljava/lang/Object;)Z
      10: pop
      11: return

  static {};
    Code:
       0: ldc           #57                 // class org/apache/hadoop/hbase/ResourceChecker
       2: invokevirtual #58                 // Method java/lang/Class.desiredAssertionStatus:()Z
       5: ifne          12
       8: iconst_1
       9: goto          13
      12: iconst_0
      13: putstatic     #37                 // Field $assertionsDisabled:Z
      16: ldc           #57                 // class org/apache/hadoop/hbase/ResourceChecker
      18: invokestatic  #59                 // Method org/slf4j/LoggerFactory.getLogger:(Ljava/lang/Class;)Lorg/slf4j/Logger;
      21: putstatic     #19                 // Field LOG:Lorg/slf4j/Logger;
      24: return
}
