Compiled from "RestoreSnapshotHelper.java"
class org.apache.hadoop.hbase.snapshot.RestoreSnapshotHelper$4 implements org.apache.hadoop.hbase.util.ModifyRegionUtils$RegionFillTask {
  final java.util.Map val$snapshotRegions;

  final java.util.Map val$regionManifests;

  final org.apache.hadoop.hbase.snapshot.RestoreSnapshotHelper this$0;

  org.apache.hadoop.hbase.snapshot.RestoreSnapshotHelper$4(org.apache.hadoop.hbase.snapshot.RestoreSnapshotHelper, java.util.Map, java.util.Map);
    Code:
       0: aload_0
       1: aload_1
       2: putfield      #1                  // Field this$0:Lorg/apache/hadoop/hbase/snapshot/RestoreSnapshotHelper;
       5: aload_0
       6: aload_2
       7: putfield      #2                  // Field val$snapshotRegions:Ljava/util/Map;
      10: aload_0
      11: aload_3
      12: putfield      #3                  // Field val$regionManifests:Ljava/util/Map;
      15: aload_0
      16: invokespecial #4                  // Method java/lang/Object."<init>":()V
      19: return

  public void fillRegion(org.apache.hadoop.hbase.regionserver.HRegion) throws java.io.IOException;
    Code:
       0: aload_0
       1: getfield      #2                  // Field val$snapshotRegions:Ljava/util/Map;
       4: aload_1
       5: invokevirtual #5                  // Method org/apache/hadoop/hbase/regionserver/HRegion.getRegionInfo:()Lorg/apache/hadoop/hbase/client/RegionInfo;
       8: invokeinterface #6,  1            // InterfaceMethod org/apache/hadoop/hbase/client/RegionInfo.getEncodedName:()Ljava/lang/String;
      13: invokeinterface #7,  2            // InterfaceMethod java/util/Map.get:(Ljava/lang/Object;)Ljava/lang/Object;
      18: checkcast     #8                  // class org/apache/hadoop/hbase/client/RegionInfo
      21: astore_2
      22: aload_0
      23: getfield      #1                  // Field this$0:Lorg/apache/hadoop/hbase/snapshot/RestoreSnapshotHelper;
      26: aload_1
      27: aload_2
      28: aload_0
      29: getfield      #3                  // Field val$regionManifests:Ljava/util/Map;
      32: aload_2
      33: invokeinterface #6,  1            // InterfaceMethod org/apache/hadoop/hbase/client/RegionInfo.getEncodedName:()Ljava/lang/String;
      38: invokeinterface #7,  2            // InterfaceMethod java/util/Map.get:(Ljava/lang/Object;)Ljava/lang/Object;
      43: checkcast     #9                  // class org/apache/hadoop/hbase/shaded/protobuf/generated/SnapshotProtos$SnapshotRegionManifest
      46: invokestatic  #10                 // Method org/apache/hadoop/hbase/snapshot/RestoreSnapshotHelper.access$500:(Lorg/apache/hadoop/hbase/snapshot/RestoreSnapshotHelper;Lorg/apache/hadoop/hbase/regionserver/HRegion;Lorg/apache/hadoop/hbase/client/RegionInfo;Lorg/apache/hadoop/hbase/shaded/protobuf/generated/SnapshotProtos$SnapshotRegionManifest;)V
      49: return
}
