Compiled from "RestoreSnapshotFromClientAfterTruncateTestBase.java"
public class org.apache.hadoop.hbase.client.RestoreSnapshotFromClientAfterTruncateTestBase extends org.apache.hadoop.hbase.client.RestoreSnapshotFromClientTestBase {
  public org.apache.hadoop.hbase.client.RestoreSnapshotFromClientAfterTruncateTestBase();
    Code:
       0: aload_0
       1: invokespecial #1                  // Method org/apache/hadoop/hbase/client/RestoreSnapshotFromClientTestBase."<init>":()V
       4: return

  public void testRestoreSnapshotAfterTruncate() throws java.lang.Exception;
    Code:
       0: aload_0
       1: invokevirtual #2                  // Method getValidMethodName:()Ljava/lang/String;
       4: invokestatic  #3                  // Method org/apache/hadoop/hbase/TableName.valueOf:(Ljava/lang/String;)Lorg/apache/hadoop/hbase/TableName;
       7: astore_1
       8: getstatic     #4                  // Field TEST_UTIL:Lorg/apache/hadoop/hbase/HBaseTestingUtility;
      11: aload_1
      12: aload_0
      13: invokevirtual #5                  // Method getNumReplicas:()I
      16: iconst_1
      17: anewarray     #6                  // class "[B"
      20: dup
      21: iconst_0
      22: aload_0
      23: getfield      #7                  // Field FAMILY:[B
      26: aastore
      27: invokestatic  #8                  // Method org/apache/hadoop/hbase/snapshot/SnapshotTestingUtils.createTable:(Lorg/apache/hadoop/hbase/HBaseTestingUtility;Lorg/apache/hadoop/hbase/TableName;I[[B)V
      30: getstatic     #4                  // Field TEST_UTIL:Lorg/apache/hadoop/hbase/HBaseTestingUtility;
      33: aload_1
      34: sipush        500
      37: iconst_1
      38: anewarray     #6                  // class "[B"
      41: dup
      42: iconst_0
      43: aload_0
      44: getfield      #7                  // Field FAMILY:[B
      47: aastore
      48: invokestatic  #9                  // Method org/apache/hadoop/hbase/snapshot/SnapshotTestingUtils.loadData:(Lorg/apache/hadoop/hbase/HBaseTestingUtility;Lorg/apache/hadoop/hbase/TableName;I[[B)V
      51: iconst_0
      52: istore_2
      53: getstatic     #4                  // Field TEST_UTIL:Lorg/apache/hadoop/hbase/HBaseTestingUtility;
      56: invokevirtual #10                 // Method org/apache/hadoop/hbase/HBaseTestingUtility.getConnection:()Lorg/apache/hadoop/hbase/client/Connection;
      59: aload_1
      60: invokeinterface #11,  2           // InterfaceMethod org/apache/hadoop/hbase/client/Connection.getTable:(Lorg/apache/hadoop/hbase/TableName;)Lorg/apache/hadoop/hbase/client/Table;
      65: astore_3
      66: aconst_null
      67: astore        4
      69: aload_0
      70: aload_3
      71: iconst_0
      72: anewarray     #6                  // class "[B"
      75: invokevirtual #12                 // Method countRows:(Lorg/apache/hadoop/hbase/client/Table;[[B)I
      78: istore_2
      79: aload_3
      80: ifnull        168
      83: aload         4
      85: ifnull        109
      88: aload_3
      89: invokeinterface #13,  1           // InterfaceMethod org/apache/hadoop/hbase/client/Table.close:()V
      94: goto          168
      97: astore        5
      99: aload         4
     101: aload         5
     103: invokevirtual #15                 // Method java/lang/Throwable.addSuppressed:(Ljava/lang/Throwable;)V
     106: goto          168
     109: aload_3
     110: invokeinterface #13,  1           // InterfaceMethod org/apache/hadoop/hbase/client/Table.close:()V
     115: goto          168
     118: astore        5
     120: aload         5
     122: astore        4
     124: aload         5
     126: athrow
     127: astore        6
     129: aload_3
     130: ifnull        165
     133: aload         4
     135: ifnull        159
     138: aload_3
     139: invokeinterface #13,  1           // InterfaceMethod org/apache/hadoop/hbase/client/Table.close:()V
     144: goto          165
     147: astore        7
     149: aload         4
     151: aload         7
     153: invokevirtual #15                 // Method java/lang/Throwable.addSuppressed:(Ljava/lang/Throwable;)V
     156: goto          165
     159: aload_3
     160: invokeinterface #13,  1           // InterfaceMethod org/apache/hadoop/hbase/client/Table.close:()V
     165: aload         6
     167: athrow
     168: aload_0
     169: getfield      #16                 // Field admin:Lorg/apache/hadoop/hbase/client/Admin;
     172: ldc           #17                 // String snap
     174: aload_1
     175: invokeinterface #18,  3           // InterfaceMethod org/apache/hadoop/hbase/client/Admin.snapshot:(Ljava/lang/String;Lorg/apache/hadoop/hbase/TableName;)V
     180: aload_0
     181: getfield      #16                 // Field admin:Lorg/apache/hadoop/hbase/client/Admin;
     184: aload_1
     185: invokeinterface #19,  2           // InterfaceMethod org/apache/hadoop/hbase/client/Admin.disableTable:(Lorg/apache/hadoop/hbase/TableName;)V
     190: aload_0
     191: getfield      #16                 // Field admin:Lorg/apache/hadoop/hbase/client/Admin;
     194: aload_1
     195: iconst_0
     196: invokeinterface #20,  3           // InterfaceMethod org/apache/hadoop/hbase/client/Admin.truncateTable:(Lorg/apache/hadoop/hbase/TableName;Z)V
     201: aload_0
     202: getfield      #16                 // Field admin:Lorg/apache/hadoop/hbase/client/Admin;
     205: aload_1
     206: invokeinterface #19,  2           // InterfaceMethod org/apache/hadoop/hbase/client/Admin.disableTable:(Lorg/apache/hadoop/hbase/TableName;)V
     211: aload_0
     212: getfield      #16                 // Field admin:Lorg/apache/hadoop/hbase/client/Admin;
     215: ldc           #17                 // String snap
     217: invokeinterface #21,  2           // InterfaceMethod org/apache/hadoop/hbase/client/Admin.restoreSnapshot:(Ljava/lang/String;)V
     222: aload_0
     223: getfield      #16                 // Field admin:Lorg/apache/hadoop/hbase/client/Admin;
     226: aload_1
     227: invokeinterface #22,  2           // InterfaceMethod org/apache/hadoop/hbase/client/Admin.enableTable:(Lorg/apache/hadoop/hbase/TableName;)V
     232: aload_0
     233: getstatic     #4                  // Field TEST_UTIL:Lorg/apache/hadoop/hbase/HBaseTestingUtility;
     236: aload_1
     237: iload_2
     238: i2l
     239: invokevirtual #23                 // Method verifyRowCount:(Lorg/apache/hadoop/hbase/HBaseTestingUtility;Lorg/apache/hadoop/hbase/TableName;J)V
     242: aload_1
     243: aload_0
     244: getfield      #16                 // Field admin:Lorg/apache/hadoop/hbase/client/Admin;
     247: aload_0
     248: invokevirtual #5                  // Method getNumReplicas:()I
     251: invokestatic  #24                 // Method org/apache/hadoop/hbase/snapshot/SnapshotTestingUtils.verifyReplicasCameOnline:(Lorg/apache/hadoop/hbase/TableName;Lorg/apache/hadoop/hbase/client/Admin;I)V
     254: return
    Exception table:
       from    to  target type
          88    94    97   Class java/lang/Throwable
          69    79   118   Class java/lang/Throwable
          69    79   127   any
         138   144   147   Class java/lang/Throwable
         118   129   127   any
}
