Compiled from "RestoreSnapshotHelper.java"
public class org.apache.hadoop.hbase.snapshot.RestoreSnapshotHelper$RestoreMetaChanges {
  public org.apache.hadoop.hbase.snapshot.RestoreSnapshotHelper$RestoreMetaChanges(org.apache.hadoop.hbase.client.TableDescriptor, java.util.Map<java.lang.String, org.apache.hadoop.hbase.util.Pair<java.lang.String, java.lang.String>>);
    Code:
       0: aload_0
       1: invokespecial #1                  // Method java/lang/Object."<init>":()V
       4: aload_0
       5: aconst_null
       6: putfield      #2                  // Field regionsToRestore:Ljava/util/List;
       9: aload_0
      10: aconst_null
      11: putfield      #3                  // Field regionsToRemove:Ljava/util/List;
      14: aload_0
      15: aconst_null
      16: putfield      #4                  // Field regionsToAdd:Ljava/util/List;
      19: aload_0
      20: aload_2
      21: putfield      #5                  // Field parentsMap:Ljava/util/Map;
      24: aload_0
      25: aload_1
      26: putfield      #6                  // Field htd:Lorg/apache/hadoop/hbase/client/TableDescriptor;
      29: return

  public org.apache.hadoop.hbase.client.TableDescriptor getTableDescriptor();
    Code:
       0: aload_0
       1: getfield      #6                  // Field htd:Lorg/apache/hadoop/hbase/client/TableDescriptor;
       4: areturn

  public java.util.Map<java.lang.String, org.apache.hadoop.hbase.util.Pair<java.lang.String, java.lang.String>> getParentToChildrenPairMap();
    Code:
       0: aload_0
       1: getfield      #5                  // Field parentsMap:Ljava/util/Map;
       4: areturn

  public boolean hasRegionsToAdd();
    Code:
       0: aload_0
       1: getfield      #4                  // Field regionsToAdd:Ljava/util/List;
       4: ifnull        23
       7: aload_0
       8: getfield      #4                  // Field regionsToAdd:Ljava/util/List;
      11: invokeinterface #7,  1            // InterfaceMethod java/util/List.size:()I
      16: ifle          23
      19: iconst_1
      20: goto          24
      23: iconst_0
      24: ireturn

  public java.util.List<org.apache.hadoop.hbase.client.RegionInfo> getRegionsToAdd();
    Code:
       0: aload_0
       1: getfield      #4                  // Field regionsToAdd:Ljava/util/List;
       4: areturn

  public boolean hasRegionsToRestore();
    Code:
       0: aload_0
       1: getfield      #2                  // Field regionsToRestore:Ljava/util/List;
       4: ifnull        23
       7: aload_0
       8: getfield      #2                  // Field regionsToRestore:Ljava/util/List;
      11: invokeinterface #7,  1            // InterfaceMethod java/util/List.size:()I
      16: ifle          23
      19: iconst_1
      20: goto          24
      23: iconst_0
      24: ireturn

  public java.util.List<org.apache.hadoop.hbase.client.RegionInfo> getRegionsToRestore();
    Code:
       0: aload_0
       1: getfield      #2                  // Field regionsToRestore:Ljava/util/List;
       4: areturn

  public boolean hasRegionsToRemove();
    Code:
       0: aload_0
       1: getfield      #3                  // Field regionsToRemove:Ljava/util/List;
       4: ifnull        23
       7: aload_0
       8: getfield      #3                  // Field regionsToRemove:Ljava/util/List;
      11: invokeinterface #7,  1            // InterfaceMethod java/util/List.size:()I
      16: ifle          23
      19: iconst_1
      20: goto          24
      23: iconst_0
      24: ireturn

  public java.util.List<org.apache.hadoop.hbase.client.RegionInfo> getRegionsToRemove();
    Code:
       0: aload_0
       1: getfield      #3                  // Field regionsToRemove:Ljava/util/List;
       4: areturn

  void setNewRegions(org.apache.hadoop.hbase.client.RegionInfo[]);
    Code:
       0: aload_1
       1: ifnull        15
       4: aload_0
       5: aload_1
       6: invokestatic  #8                  // Method java/util/Arrays.asList:([Ljava/lang/Object;)Ljava/util/List;
       9: putfield      #4                  // Field regionsToAdd:Ljava/util/List;
      12: goto          20
      15: aload_0
      16: aconst_null
      17: putfield      #4                  // Field regionsToAdd:Ljava/util/List;
      20: return

  void addRegionToRemove(org.apache.hadoop.hbase.client.RegionInfo);
    Code:
       0: aload_0
       1: getfield      #3                  // Field regionsToRemove:Ljava/util/List;
       4: ifnonnull     18
       7: aload_0
       8: new           #9                  // class java/util/LinkedList
      11: dup
      12: invokespecial #10                 // Method java/util/LinkedList."<init>":()V
      15: putfield      #3                  // Field regionsToRemove:Ljava/util/List;
      18: aload_0
      19: getfield      #3                  // Field regionsToRemove:Ljava/util/List;
      22: aload_1
      23: invokeinterface #11,  2           // InterfaceMethod java/util/List.add:(Ljava/lang/Object;)Z
      28: pop
      29: return

  void addRegionToRestore(org.apache.hadoop.hbase.client.RegionInfo);
    Code:
       0: aload_0
       1: getfield      #2                  // Field regionsToRestore:Ljava/util/List;
       4: ifnonnull     18
       7: aload_0
       8: new           #9                  // class java/util/LinkedList
      11: dup
      12: invokespecial #10                 // Method java/util/LinkedList."<init>":()V
      15: putfield      #2                  // Field regionsToRestore:Ljava/util/List;
      18: aload_0
      19: getfield      #2                  // Field regionsToRestore:Ljava/util/List;
      22: aload_1
      23: invokeinterface #11,  2           // InterfaceMethod java/util/List.add:(Ljava/lang/Object;)Z
      28: pop
      29: return

  public void updateMetaParentRegions(org.apache.hadoop.hbase.client.Connection, java.util.List<org.apache.hadoop.hbase.client.RegionInfo>) throws java.io.IOException;
    Code:
       0: aload_2
       1: ifnull        16
       4: aload_0
       5: getfield      #5                  // Field parentsMap:Ljava/util/Map;
       8: invokeinterface #12,  1           // InterfaceMethod java/util/Map.isEmpty:()Z
      13: ifeq          17
      16: return
      17: new           #13                 // class java/util/HashMap
      20: dup
      21: aload_2
      22: invokeinterface #7,  1            // InterfaceMethod java/util/List.size:()I
      27: invokespecial #14                 // Method java/util/HashMap."<init>":(I)V
      30: astore_3
      31: new           #9                  // class java/util/LinkedList
      34: dup
      35: invokespecial #10                 // Method java/util/LinkedList."<init>":()V
      38: astore        4
      40: aload_2
      41: invokeinterface #15,  1           // InterfaceMethod java/util/List.iterator:()Ljava/util/Iterator;
      46: astore        5
      48: aload         5
      50: invokeinterface #16,  1           // InterfaceMethod java/util/Iterator.hasNext:()Z
      55: ifeq          112
      58: aload         5
      60: invokeinterface #17,  1           // InterfaceMethod java/util/Iterator.next:()Ljava/lang/Object;
      65: checkcast     #18                 // class org/apache/hadoop/hbase/client/RegionInfo
      68: astore        6
      70: aload         6
      72: invokeinterface #19,  1           // InterfaceMethod org/apache/hadoop/hbase/client/RegionInfo.isSplitParent:()Z
      77: ifeq          93
      80: aload         4
      82: aload         6
      84: invokeinterface #11,  2           // InterfaceMethod java/util/List.add:(Ljava/lang/Object;)Z
      89: pop
      90: goto          109
      93: aload_3
      94: aload         6
      96: invokeinterface #20,  1           // InterfaceMethod org/apache/hadoop/hbase/client/RegionInfo.getEncodedName:()Ljava/lang/String;
     101: aload         6
     103: invokeinterface #21,  3           // InterfaceMethod java/util/Map.put:(Ljava/lang/Object;Ljava/lang/Object;)Ljava/lang/Object;
     108: pop
     109: goto          48
     112: aload         4
     114: invokeinterface #15,  1           // InterfaceMethod java/util/List.iterator:()Ljava/util/Iterator;
     119: astore        5
     121: aload         5
     123: invokeinterface #16,  1           // InterfaceMethod java/util/Iterator.hasNext:()Z
     128: ifeq          298
     131: aload         5
     133: invokeinterface #17,  1           // InterfaceMethod java/util/Iterator.next:()Ljava/lang/Object;
     138: checkcast     #18                 // class org/apache/hadoop/hbase/client/RegionInfo
     141: astore        6
     143: aload_0
     144: getfield      #5                  // Field parentsMap:Ljava/util/Map;
     147: aload         6
     149: invokeinterface #20,  1           // InterfaceMethod org/apache/hadoop/hbase/client/RegionInfo.getEncodedName:()Ljava/lang/String;
     154: invokeinterface #22,  2           // InterfaceMethod java/util/Map.get:(Ljava/lang/Object;)Ljava/lang/Object;
     159: checkcast     #23                 // class org/apache/hadoop/hbase/util/Pair
     162: astore        7
     164: aload         7
     166: ifnonnull     200
     169: invokestatic  #24                 // Method org/apache/hadoop/hbase/snapshot/RestoreSnapshotHelper.access$000:()Lorg/slf4j/Logger;
     172: new           #25                 // class java/lang/StringBuilder
     175: dup
     176: invokespecial #26                 // Method java/lang/StringBuilder."<init>":()V
     179: ldc           #27                 // String Skip update of unreferenced offline parent:
     181: invokevirtual #28                 // Method java/lang/StringBuilder.append:(Ljava/lang/String;)Ljava/lang/StringBuilder;
     184: aload         6
     186: invokevirtual #29                 // Method java/lang/StringBuilder.append:(Ljava/lang/Object;)Ljava/lang/StringBuilder;
     189: invokevirtual #30                 // Method java/lang/StringBuilder.toString:()Ljava/lang/String;
     192: invokeinterface #31,  2           // InterfaceMethod org/slf4j/Logger.warn:(Ljava/lang/String;)V
     197: goto          121
     200: aload         7
     202: invokevirtual #32                 // Method org/apache/hadoop/hbase/util/Pair.getSecond:()Ljava/lang/Object;
     205: ifnonnull     218
     208: aload         7
     210: aload         7
     212: invokevirtual #33                 // Method org/apache/hadoop/hbase/util/Pair.getFirst:()Ljava/lang/Object;
     215: invokevirtual #34                 // Method org/apache/hadoop/hbase/util/Pair.setSecond:(Ljava/lang/Object;)V
     218: invokestatic  #24                 // Method org/apache/hadoop/hbase/snapshot/RestoreSnapshotHelper.access$000:()Lorg/slf4j/Logger;
     221: new           #25                 // class java/lang/StringBuilder
     224: dup
     225: invokespecial #26                 // Method java/lang/StringBuilder."<init>":()V
     228: ldc           #35                 // String Update splits parent
     230: invokevirtual #28                 // Method java/lang/StringBuilder.append:(Ljava/lang/String;)Ljava/lang/StringBuilder;
     233: aload         6
     235: invokeinterface #20,  1           // InterfaceMethod org/apache/hadoop/hbase/client/RegionInfo.getEncodedName:()Ljava/lang/String;
     240: invokevirtual #28                 // Method java/lang/StringBuilder.append:(Ljava/lang/String;)Ljava/lang/StringBuilder;
     243: ldc           #36                 // String  ->
     245: invokevirtual #28                 // Method java/lang/StringBuilder.append:(Ljava/lang/String;)Ljava/lang/StringBuilder;
     248: aload         7
     250: invokevirtual #29                 // Method java/lang/StringBuilder.append:(Ljava/lang/Object;)Ljava/lang/StringBuilder;
     253: invokevirtual #30                 // Method java/lang/StringBuilder.toString:()Ljava/lang/String;
     256: invokeinterface #37,  2           // InterfaceMethod org/slf4j/Logger.debug:(Ljava/lang/String;)V
     261: aload_1
     262: aload         6
     264: aload_3
     265: aload         7
     267: invokevirtual #33                 // Method org/apache/hadoop/hbase/util/Pair.getFirst:()Ljava/lang/Object;
     270: invokeinterface #22,  2           // InterfaceMethod java/util/Map.get:(Ljava/lang/Object;)Ljava/lang/Object;
     275: checkcast     #18                 // class org/apache/hadoop/hbase/client/RegionInfo
     278: aload_3
     279: aload         7
     281: invokevirtual #32                 // Method org/apache/hadoop/hbase/util/Pair.getSecond:()Ljava/lang/Object;
     284: invokeinterface #22,  2           // InterfaceMethod java/util/Map.get:(Ljava/lang/Object;)Ljava/lang/Object;
     289: checkcast     #18                 // class org/apache/hadoop/hbase/client/RegionInfo
     292: invokestatic  #38                 // Method org/apache/hadoop/hbase/MetaTableAccessor.addSplitsToParent:(Lorg/apache/hadoop/hbase/client/Connection;Lorg/apache/hadoop/hbase/client/RegionInfo;Lorg/apache/hadoop/hbase/client/RegionInfo;Lorg/apache/hadoop/hbase/client/RegionInfo;)V
     295: goto          121
     298: return
}
