Compiled from "ResultBoundedCompletionService.java"
public class org.apache.hadoop.hbase.client.ResultBoundedCompletionService<V> {
  public org.apache.hadoop.hbase.client.ResultBoundedCompletionService(org.apache.hadoop.hbase.client.RpcRetryingCallerFactory, java.util.concurrent.Executor, int);
    Code:
       0: aload_0
       1: invokespecial #4                  // Method java/lang/Object."<init>":()V
       4: aload_0
       5: iconst_0
       6: putfield      #5                  // Field cancelled:Z
       9: aload_0
      10: aload_1
      11: putfield      #3                  // Field retryingCallerFactory:Lorg/apache/hadoop/hbase/client/RpcRetryingCallerFactory;
      14: aload_0
      15: aload_2
      16: putfield      #6                  // Field executor:Ljava/util/concurrent/Executor;
      19: aload_0
      20: iload_3
      21: anewarray     #7                  // class org/apache/hadoop/hbase/client/ResultBoundedCompletionService$QueueingFuture
      24: putfield      #2                  // Field tasks:[Lorg/apache/hadoop/hbase/client/ResultBoundedCompletionService$QueueingFuture;
      27: aload_0
      28: new           #8                  // class java/util/ArrayList
      31: dup
      32: iload_3
      33: invokespecial #9                  // Method java/util/ArrayList."<init>":(I)V
      36: putfield      #1                  // Field completedTasks:Ljava/util/ArrayList;
      39: return

  public void submit(org.apache.hadoop.hbase.client.RetryingCallable<V>, int, int);
    Code:
       0: new           #7                  // class org/apache/hadoop/hbase/client/ResultBoundedCompletionService$QueueingFuture
       3: dup
       4: aload_0
       5: aload_1
       6: iload_2
       7: iload_3
       8: invokespecial #10                 // Method org/apache/hadoop/hbase/client/ResultBoundedCompletionService$QueueingFuture."<init>":(Lorg/apache/hadoop/hbase/client/ResultBoundedCompletionService;Lorg/apache/hadoop/hbase/client/RetryingCallable;II)V
      11: astore        4
      13: aload_0
      14: getfield      #6                  // Field executor:Ljava/util/concurrent/Executor;
      17: aload         4
      19: ldc           #11                 // String ResultBoundedCompletionService.submit
      21: invokestatic  #12                 // Method org/apache/hadoop/hbase/trace/TraceUtil.wrap:(Ljava/lang/Runnable;Ljava/lang/String;)Ljava/lang/Runnable;
      24: invokeinterface #13,  2           // InterfaceMethod java/util/concurrent/Executor.execute:(Ljava/lang/Runnable;)V
      29: aload_0
      30: getfield      #2                  // Field tasks:[Lorg/apache/hadoop/hbase/client/ResultBoundedCompletionService$QueueingFuture;
      33: iload_3
      34: aload         4
      36: aastore
      37: return

  public org.apache.hadoop.hbase.client.ResultBoundedCompletionService<V>.QueueingFuture<V> take() throws java.lang.InterruptedException;
    Code:
       0: aload_0
       1: getfield      #2                  // Field tasks:[Lorg/apache/hadoop/hbase/client/ResultBoundedCompletionService$QueueingFuture;
       4: dup
       5: astore_1
       6: monitorenter
       7: aload_0
       8: getfield      #5                  // Field cancelled:Z
      11: ifne          35
      14: aload_0
      15: getfield      #1                  // Field completedTasks:Ljava/util/ArrayList;
      18: invokevirtual #14                 // Method java/util/ArrayList.size:()I
      21: iconst_1
      22: if_icmpge     35
      25: aload_0
      26: getfield      #2                  // Field tasks:[Lorg/apache/hadoop/hbase/client/ResultBoundedCompletionService$QueueingFuture;
      29: invokevirtual #15                 // Method java/lang/Object.wait:()V
      32: goto          7
      35: aload_1
      36: monitorexit
      37: goto          45
      40: astore_2
      41: aload_1
      42: monitorexit
      43: aload_2
      44: athrow
      45: aload_0
      46: getfield      #1                  // Field completedTasks:Ljava/util/ArrayList;
      49: iconst_0
      50: invokevirtual #16                 // Method java/util/ArrayList.get:(I)Ljava/lang/Object;
      53: checkcast     #7                  // class org/apache/hadoop/hbase/client/ResultBoundedCompletionService$QueueingFuture
      56: areturn
    Exception table:
       from    to  target type
           7    37    40   any
          40    43    40   any

  public org.apache.hadoop.hbase.client.ResultBoundedCompletionService<V>.QueueingFuture<V> poll(long, java.util.concurrent.TimeUnit) throws java.lang.InterruptedException;
    Code:
       0: aload_0
       1: lload_1
       2: aload_3
       3: iconst_0
       4: invokespecial #17                 // Method pollForSpecificCompletedTask:(JLjava/util/concurrent/TimeUnit;I)Lorg/apache/hadoop/hbase/client/ResultBoundedCompletionService$QueueingFuture;
       7: areturn

  public org.apache.hadoop.hbase.client.ResultBoundedCompletionService<V>.QueueingFuture<V> pollForFirstSuccessfullyCompletedTask(long, java.util.concurrent.TimeUnit, int, int) throws java.lang.InterruptedException, java.util.concurrent.CancellationException, java.util.concurrent.ExecutionException;
    Code:
       0: iload         4
       2: istore        11
       4: iload         11
       6: iload         5
       8: if_icmpge     145
      11: invokestatic  #18                 // Method org/apache/hadoop/hbase/util/EnvironmentEdgeManager.currentTime:()J
      14: lstore        7
      16: aload_0
      17: lload_1
      18: aload_3
      19: iload         11
      21: invokespecial #17                 // Method pollForSpecificCompletedTask:(JLjava/util/concurrent/TimeUnit;I)Lorg/apache/hadoop/hbase/client/ResultBoundedCompletionService$QueueingFuture;
      24: astore        6
      26: invokestatic  #18                 // Method org/apache/hadoop/hbase/util/EnvironmentEdgeManager.currentTime:()J
      29: lload         7
      31: lsub
      32: lstore        9
      34: lload_1
      35: lload         9
      37: lsub
      38: lstore_1
      39: aload         6
      41: ifnonnull     46
      44: aconst_null
      45: areturn
      46: aload         6
      48: invokevirtual #19                 // Method org/apache/hadoop/hbase/client/ResultBoundedCompletionService$QueueingFuture.getExeEx:()Ljava/util/concurrent/ExecutionException;
      51: ifnull        136
      54: getstatic     #20                 // Field LOG:Lorg/slf4j/Logger;
      57: invokeinterface #21,  1           // InterfaceMethod org/slf4j/Logger.isDebugEnabled:()Z
      62: ifeq          121
      65: getstatic     #20                 // Field LOG:Lorg/slf4j/Logger;
      68: new           #22                 // class java/lang/StringBuilder
      71: dup
      72: invokespecial #23                 // Method java/lang/StringBuilder."<init>":()V
      75: ldc           #24                 // String Replica
      77: invokevirtual #25                 // Method java/lang/StringBuilder.append:(Ljava/lang/String;)Ljava/lang/StringBuilder;
      80: aload         6
      82: ifnonnull     89
      85: iconst_0
      86: goto          94
      89: aload         6
      91: invokevirtual #26                 // Method org/apache/hadoop/hbase/client/ResultBoundedCompletionService$QueueingFuture.getReplicaId:()I
      94: invokevirtual #27                 // Method java/lang/StringBuilder.append:(I)Ljava/lang/StringBuilder;
      97: ldc           #28                 // String  returns
      99: invokevirtual #25                 // Method java/lang/StringBuilder.append:(Ljava/lang/String;)Ljava/lang/StringBuilder;
     102: aload         6
     104: invokevirtual #19                 // Method org/apache/hadoop/hbase/client/ResultBoundedCompletionService$QueueingFuture.getExeEx:()Ljava/util/concurrent/ExecutionException;
     107: invokevirtual #29                 // Method java/util/concurrent/ExecutionException.getCause:()Ljava/lang/Throwable;
     110: invokevirtual #30                 // Method java/lang/StringBuilder.append:(Ljava/lang/Object;)Ljava/lang/StringBuilder;
     113: invokevirtual #31                 // Method java/lang/StringBuilder.toString:()Ljava/lang/String;
     116: invokeinterface #32,  2           // InterfaceMethod org/slf4j/Logger.debug:(Ljava/lang/String;)V
     121: iload         11
     123: iload         5
     125: iconst_1
     126: isub
     127: if_icmpne     139
     130: aload         6
     132: invokevirtual #19                 // Method org/apache/hadoop/hbase/client/ResultBoundedCompletionService$QueueingFuture.getExeEx:()Ljava/util/concurrent/ExecutionException;
     135: athrow
     136: aload         6
     138: areturn
     139: iinc          11, 1
     142: goto          4
     145: aconst_null
     146: areturn

  public void cancelAll();
    Code:
       0: aload_0
       1: getfield      #2                  // Field tasks:[Lorg/apache/hadoop/hbase/client/ResultBoundedCompletionService$QueueingFuture;
       4: dup
       5: astore_1
       6: monitorenter
       7: aload_0
       8: iconst_1
       9: putfield      #5                  // Field cancelled:Z
      12: aload_1
      13: monitorexit
      14: goto          22
      17: astore_2
      18: aload_1
      19: monitorexit
      20: aload_2
      21: athrow
      22: aload_0
      23: getfield      #2                  // Field tasks:[Lorg/apache/hadoop/hbase/client/ResultBoundedCompletionService$QueueingFuture;
      26: astore_1
      27: aload_1
      28: arraylength
      29: istore_2
      30: iconst_0
      31: istore_3
      32: iload_3
      33: iload_2
      34: if_icmpge     60
      37: aload_1
      38: iload_3
      39: aaload
      40: astore        4
      42: aload         4
      44: ifnull        54
      47: aload         4
      49: iconst_1
      50: invokevirtual #34                 // Method org/apache/hadoop/hbase/client/ResultBoundedCompletionService$QueueingFuture.cancel:(Z)Z
      53: pop
      54: iinc          3, 1
      57: goto          32
      60: return
    Exception table:
       from    to  target type
           7    14    17   any
          17    20    17   any

  static org.apache.hadoop.hbase.client.RpcRetryingCallerFactory access$000(org.apache.hadoop.hbase.client.ResultBoundedCompletionService);
    Code:
       0: aload_0
       1: getfield      #3                  // Field retryingCallerFactory:Lorg/apache/hadoop/hbase/client/RpcRetryingCallerFactory;
       4: areturn

  static org.apache.hadoop.hbase.client.ResultBoundedCompletionService$QueueingFuture[] access$100(org.apache.hadoop.hbase.client.ResultBoundedCompletionService);
    Code:
       0: aload_0
       1: getfield      #2                  // Field tasks:[Lorg/apache/hadoop/hbase/client/ResultBoundedCompletionService$QueueingFuture;
       4: areturn

  static java.util.ArrayList access$200(org.apache.hadoop.hbase.client.ResultBoundedCompletionService);
    Code:
       0: aload_0
       1: getfield      #1                  // Field completedTasks:Ljava/util/ArrayList;
       4: areturn

  static {};
    Code:
       0: ldc           #35                 // class org/apache/hadoop/hbase/client/ResultBoundedCompletionService
       2: invokestatic  #36                 // Method org/slf4j/LoggerFactory.getLogger:(Ljava/lang/Class;)Lorg/slf4j/Logger;
       5: putstatic     #20                 // Field LOG:Lorg/slf4j/Logger;
       8: return
}
