Compiled from "ResultBoundedCompletionService.java"
class org.apache.hadoop.hbase.client.ResultBoundedCompletionService$QueueingFuture<T> implements java.util.concurrent.RunnableFuture<T> {
  final org.apache.hadoop.hbase.client.ResultBoundedCompletionService this$0;

  public org.apache.hadoop.hbase.client.ResultBoundedCompletionService$QueueingFuture(org.apache.hadoop.hbase.client.RetryingCallable<T>, int, int);
    Code:
       0: aload_0
       1: aload_1
       2: putfield      #1                  // Field this$0:Lorg/apache/hadoop/hbase/client/ResultBoundedCompletionService;
       5: aload_0
       6: invokespecial #2                  // Method java/lang/Object."<init>":()V
       9: aload_0
      10: aconst_null
      11: putfield      #3                  // Field result:Ljava/lang/Object;
      14: aload_0
      15: aconst_null
      16: putfield      #4                  // Field exeEx:Ljava/util/concurrent/ExecutionException;
      19: aload_0
      20: iconst_0
      21: putfield      #5                  // Field cancelled:Z
      24: aload_0
      25: iconst_0
      26: putfield      #6                  // Field resultObtained:Z
      29: aload_0
      30: aload_2
      31: putfield      #7                  // Field future:Lorg/apache/hadoop/hbase/client/RetryingCallable;
      34: aload_0
      35: iload_3
      36: putfield      #8                  // Field callTimeout:I
      39: aload_0
      40: aload_1
      41: invokestatic  #9                  // Method org/apache/hadoop/hbase/client/ResultBoundedCompletionService.access$000:(Lorg/apache/hadoop/hbase/client/ResultBoundedCompletionService;)Lorg/apache/hadoop/hbase/client/RpcRetryingCallerFactory;
      44: invokevirtual #10                 // Method org/apache/hadoop/hbase/client/RpcRetryingCallerFactory.newCaller:()Lorg/apache/hadoop/hbase/client/RpcRetryingCaller;
      47: putfield      #11                 // Field retryingCaller:Lorg/apache/hadoop/hbase/client/RpcRetryingCaller;
      50: aload_0
      51: iload         4
      53: putfield      #12                 // Field replicaId:I
      56: return

  public void run();
    Code:
       0: aload_0
       1: getfield      #5                  // Field cancelled:Z
       4: ifne          33
       7: aload_0
       8: aload_0
       9: getfield      #11                 // Field retryingCaller:Lorg/apache/hadoop/hbase/client/RpcRetryingCaller;
      12: aload_0
      13: getfield      #7                  // Field future:Lorg/apache/hadoop/hbase/client/RetryingCallable;
      16: aload_0
      17: getfield      #8                  // Field callTimeout:I
      20: invokeinterface #13,  3           // InterfaceMethod org/apache/hadoop/hbase/client/RpcRetryingCaller.callWithRetries:(Lorg/apache/hadoop/hbase/client/RetryingCallable;I)Ljava/lang/Object;
      25: putfield      #3                  // Field result:Ljava/lang/Object;
      28: aload_0
      29: iconst_1
      30: putfield      #6                  // Field resultObtained:Z
      33: aload_0
      34: getfield      #1                  // Field this$0:Lorg/apache/hadoop/hbase/client/ResultBoundedCompletionService;
      37: invokestatic  #14                 // Method org/apache/hadoop/hbase/client/ResultBoundedCompletionService.access$100:(Lorg/apache/hadoop/hbase/client/ResultBoundedCompletionService;)[Lorg/apache/hadoop/hbase/client/ResultBoundedCompletionService$QueueingFuture;
      40: dup
      41: astore_1
      42: monitorenter
      43: aload_0
      44: getfield      #5                  // Field cancelled:Z
      47: ifne          62
      50: aload_0
      51: getfield      #1                  // Field this$0:Lorg/apache/hadoop/hbase/client/ResultBoundedCompletionService;
      54: invokestatic  #15                 // Method org/apache/hadoop/hbase/client/ResultBoundedCompletionService.access$200:(Lorg/apache/hadoop/hbase/client/ResultBoundedCompletionService;)Ljava/util/ArrayList;
      57: aload_0
      58: invokevirtual #16                 // Method java/util/ArrayList.add:(Ljava/lang/Object;)Z
      61: pop
      62: aload_0
      63: getfield      #1                  // Field this$0:Lorg/apache/hadoop/hbase/client/ResultBoundedCompletionService;
      66: invokestatic  #14                 // Method org/apache/hadoop/hbase/client/ResultBoundedCompletionService.access$100:(Lorg/apache/hadoop/hbase/client/ResultBoundedCompletionService;)[Lorg/apache/hadoop/hbase/client/ResultBoundedCompletionService$QueueingFuture;
      69: invokevirtual #17                 // Method java/lang/Object.notify:()V
      72: aload_1
      73: monitorexit
      74: goto          82
      77: astore_2
      78: aload_1
      79: monitorexit
      80: aload_2
      81: athrow
      82: goto          209
      85: astore_1
      86: aload_0
      87: new           #19                 // class java/util/concurrent/ExecutionException
      90: dup
      91: aload_1
      92: invokespecial #20                 // Method java/util/concurrent/ExecutionException."<init>":(Ljava/lang/Throwable;)V
      95: putfield      #4                  // Field exeEx:Ljava/util/concurrent/ExecutionException;
      98: aload_0
      99: getfield      #1                  // Field this$0:Lorg/apache/hadoop/hbase/client/ResultBoundedCompletionService;
     102: invokestatic  #14                 // Method org/apache/hadoop/hbase/client/ResultBoundedCompletionService.access$100:(Lorg/apache/hadoop/hbase/client/ResultBoundedCompletionService;)[Lorg/apache/hadoop/hbase/client/ResultBoundedCompletionService$QueueingFuture;
     105: dup
     106: astore_1
     107: monitorenter
     108: aload_0
     109: getfield      #5                  // Field cancelled:Z
     112: ifne          127
     115: aload_0
     116: getfield      #1                  // Field this$0:Lorg/apache/hadoop/hbase/client/ResultBoundedCompletionService;
     119: invokestatic  #15                 // Method org/apache/hadoop/hbase/client/ResultBoundedCompletionService.access$200:(Lorg/apache/hadoop/hbase/client/ResultBoundedCompletionService;)Ljava/util/ArrayList;
     122: aload_0
     123: invokevirtual #16                 // Method java/util/ArrayList.add:(Ljava/lang/Object;)Z
     126: pop
     127: aload_0
     128: getfield      #1                  // Field this$0:Lorg/apache/hadoop/hbase/client/ResultBoundedCompletionService;
     131: invokestatic  #14                 // Method org/apache/hadoop/hbase/client/ResultBoundedCompletionService.access$100:(Lorg/apache/hadoop/hbase/client/ResultBoundedCompletionService;)[Lorg/apache/hadoop/hbase/client/ResultBoundedCompletionService$QueueingFuture;
     134: invokevirtual #17                 // Method java/lang/Object.notify:()V
     137: aload_1
     138: monitorexit
     139: goto          147
     142: astore_3
     143: aload_1
     144: monitorexit
     145: aload_3
     146: athrow
     147: goto          209
     150: astore        4
     152: aload_0
     153: getfield      #1                  // Field this$0:Lorg/apache/hadoop/hbase/client/ResultBoundedCompletionService;
     156: invokestatic  #14                 // Method org/apache/hadoop/hbase/client/ResultBoundedCompletionService.access$100:(Lorg/apache/hadoop/hbase/client/ResultBoundedCompletionService;)[Lorg/apache/hadoop/hbase/client/ResultBoundedCompletionService$QueueingFuture;
     159: dup
     160: astore        5
     162: monitorenter
     163: aload_0
     164: getfield      #5                  // Field cancelled:Z
     167: ifne          182
     170: aload_0
     171: getfield      #1                  // Field this$0:Lorg/apache/hadoop/hbase/client/ResultBoundedCompletionService;
     174: invokestatic  #15                 // Method org/apache/hadoop/hbase/client/ResultBoundedCompletionService.access$200:(Lorg/apache/hadoop/hbase/client/ResultBoundedCompletionService;)Ljava/util/ArrayList;
     177: aload_0
     178: invokevirtual #16                 // Method java/util/ArrayList.add:(Ljava/lang/Object;)Z
     181: pop
     182: aload_0
     183: getfield      #1                  // Field this$0:Lorg/apache/hadoop/hbase/client/ResultBoundedCompletionService;
     186: invokestatic  #14                 // Method org/apache/hadoop/hbase/client/ResultBoundedCompletionService.access$100:(Lorg/apache/hadoop/hbase/client/ResultBoundedCompletionService;)[Lorg/apache/hadoop/hbase/client/ResultBoundedCompletionService$QueueingFuture;
     189: invokevirtual #17                 // Method java/lang/Object.notify:()V
     192: aload         5
     194: monitorexit
     195: goto          206
     198: astore        6
     200: aload         5
     202: monitorexit
     203: aload         6
     205: athrow
     206: aload         4
     208: athrow
     209: return
    Exception table:
       from    to  target type
          43    74    77   any
          77    80    77   any
           0    33    85   Class java/lang/Throwable
         108   139   142   any
         142   145   142   any
           0    33   150   any
          85    98   150   any
         163   195   198   any
         198   203   198   any
         150   152   150   any

  public boolean cancel(boolean);
    Code:
       0: aload_0
       1: getfield      #6                  // Field resultObtained:Z
       4: ifne          14
       7: aload_0
       8: getfield      #4                  // Field exeEx:Ljava/util/concurrent/ExecutionException;
      11: ifnull        16
      14: iconst_0
      15: ireturn
      16: aload_0
      17: getfield      #11                 // Field retryingCaller:Lorg/apache/hadoop/hbase/client/RpcRetryingCaller;
      20: invokeinterface #21,  1           // InterfaceMethod org/apache/hadoop/hbase/client/RpcRetryingCaller.cancel:()V
      25: aload_0
      26: getfield      #7                  // Field future:Lorg/apache/hadoop/hbase/client/RetryingCallable;
      29: instanceof    #22                 // class org/apache/hadoop/hbase/client/Cancellable
      32: ifeq          47
      35: aload_0
      36: getfield      #7                  // Field future:Lorg/apache/hadoop/hbase/client/RetryingCallable;
      39: checkcast     #22                 // class org/apache/hadoop/hbase/client/Cancellable
      42: invokeinterface #23,  1           // InterfaceMethod org/apache/hadoop/hbase/client/Cancellable.cancel:()V
      47: aload_0
      48: iconst_1
      49: putfield      #5                  // Field cancelled:Z
      52: iconst_1
      53: ireturn

  public boolean isCancelled();
    Code:
       0: aload_0
       1: getfield      #5                  // Field cancelled:Z
       4: ireturn

  public boolean isDone();
    Code:
       0: aload_0
       1: getfield      #6                  // Field resultObtained:Z
       4: ifne          14
       7: aload_0
       8: getfield      #4                  // Field exeEx:Ljava/util/concurrent/ExecutionException;
      11: ifnull        18
      14: iconst_1
      15: goto          19
      18: iconst_0
      19: ireturn

  public T get() throws java.lang.InterruptedException, java.util.concurrent.ExecutionException;
    Code:
       0: aload_0
       1: ldc2_w        #24                 // long 1000l
       4: getstatic     #26                 // Field java/util/concurrent/TimeUnit.DAYS:Ljava/util/concurrent/TimeUnit;
       7: invokevirtual #27                 // Method get:(JLjava/util/concurrent/TimeUnit;)Ljava/lang/Object;
      10: areturn
      11: astore_1
      12: new           #29                 // class java/lang/RuntimeException
      15: dup
      16: ldc           #30                 // String You did wait for 1000 days here?
      18: aload_1
      19: invokespecial #31                 // Method java/lang/RuntimeException."<init>":(Ljava/lang/String;Ljava/lang/Throwable;)V
      22: athrow
    Exception table:
       from    to  target type
           0    10    11   Class java/util/concurrent/TimeoutException

  public T get(long, java.util.concurrent.TimeUnit) throws java.lang.InterruptedException, java.util.concurrent.ExecutionException, java.util.concurrent.TimeoutException;
    Code:
       0: aload_0
       1: getfield      #1                  // Field this$0:Lorg/apache/hadoop/hbase/client/ResultBoundedCompletionService;
       4: invokestatic  #14                 // Method org/apache/hadoop/hbase/client/ResultBoundedCompletionService.access$100:(Lorg/apache/hadoop/hbase/client/ResultBoundedCompletionService;)[Lorg/apache/hadoop/hbase/client/ResultBoundedCompletionService$QueueingFuture;
       7: dup
       8: astore        4
      10: monitorenter
      11: aload_0
      12: getfield      #6                  // Field resultObtained:Z
      15: ifeq          26
      18: aload_0
      19: getfield      #3                  // Field result:Ljava/lang/Object;
      22: aload         4
      24: monitorexit
      25: areturn
      26: aload_0
      27: getfield      #4                  // Field exeEx:Ljava/util/concurrent/ExecutionException;
      30: ifnull        38
      33: aload_0
      34: getfield      #4                  // Field exeEx:Ljava/util/concurrent/ExecutionException;
      37: athrow
      38: aload_3
      39: aload_0
      40: getfield      #1                  // Field this$0:Lorg/apache/hadoop/hbase/client/ResultBoundedCompletionService;
      43: invokestatic  #14                 // Method org/apache/hadoop/hbase/client/ResultBoundedCompletionService.access$100:(Lorg/apache/hadoop/hbase/client/ResultBoundedCompletionService;)[Lorg/apache/hadoop/hbase/client/ResultBoundedCompletionService$QueueingFuture;
      46: lload_1
      47: invokevirtual #32                 // Method java/util/concurrent/TimeUnit.timedWait:(Ljava/lang/Object;J)V
      50: aload         4
      52: monitorexit
      53: goto          64
      56: astore        5
      58: aload         4
      60: monitorexit
      61: aload         5
      63: athrow
      64: aload_0
      65: getfield      #6                  // Field resultObtained:Z
      68: ifeq          76
      71: aload_0
      72: getfield      #3                  // Field result:Ljava/lang/Object;
      75: areturn
      76: aload_0
      77: getfield      #4                  // Field exeEx:Ljava/util/concurrent/ExecutionException;
      80: ifnull        88
      83: aload_0
      84: getfield      #4                  // Field exeEx:Ljava/util/concurrent/ExecutionException;
      87: athrow
      88: new           #28                 // class java/util/concurrent/TimeoutException
      91: dup
      92: new           #33                 // class java/lang/StringBuilder
      95: dup
      96: invokespecial #34                 // Method java/lang/StringBuilder."<init>":()V
      99: ldc           #35                 // String timeout=
     101: invokevirtual #36                 // Method java/lang/StringBuilder.append:(Ljava/lang/String;)Ljava/lang/StringBuilder;
     104: lload_1
     105: invokevirtual #37                 // Method java/lang/StringBuilder.append:(J)Ljava/lang/StringBuilder;
     108: ldc           #38                 // String ,
     110: invokevirtual #36                 // Method java/lang/StringBuilder.append:(Ljava/lang/String;)Ljava/lang/StringBuilder;
     113: aload_3
     114: invokevirtual #39                 // Method java/lang/StringBuilder.append:(Ljava/lang/Object;)Ljava/lang/StringBuilder;
     117: invokevirtual #40                 // Method java/lang/StringBuilder.toString:()Ljava/lang/String;
     120: invokespecial #41                 // Method java/util/concurrent/TimeoutException."<init>":(Ljava/lang/String;)V
     123: athrow
    Exception table:
       from    to  target type
          11    25    56   any
          26    53    56   any
          56    61    56   any

  public int getReplicaId();
    Code:
       0: aload_0
       1: getfield      #12                 // Field replicaId:I
       4: ireturn

  public java.util.concurrent.ExecutionException getExeEx();
    Code:
       0: aload_0
       1: getfield      #4                  // Field exeEx:Ljava/util/concurrent/ExecutionException;
       4: areturn
}
