Compiled from "Result.java"
public class org.apache.hadoop.hbase.client.Result implements org.apache.hadoop.hbase.CellScannable,org.apache.hadoop.hbase.CellScanner {
  public static final org.apache.hadoop.hbase.client.Result EMPTY_RESULT;

  public org.apache.hadoop.hbase.client.Result();
    Code:
       0: aload_0
       1: iconst_0
       2: invokespecial #1                  // Method "<init>":(Z)V
       5: return

  public static org.apache.hadoop.hbase.client.Result create(java.util.List<org.apache.hadoop.hbase.Cell>);
    Code:
       0: aload_0
       1: aconst_null
       2: invokestatic  #11                 // Method create:(Ljava/util/List;Ljava/lang/Boolean;)Lorg/apache/hadoop/hbase/client/Result;
       5: areturn

  public static org.apache.hadoop.hbase.client.Result create(java.util.List<org.apache.hadoop.hbase.Cell>, java.lang.Boolean);
    Code:
       0: aload_0
       1: aload_1
       2: iconst_0
       3: invokestatic  #12                 // Method create:(Ljava/util/List;Ljava/lang/Boolean;Z)Lorg/apache/hadoop/hbase/client/Result;
       6: areturn

  public static org.apache.hadoop.hbase.client.Result create(java.util.List<org.apache.hadoop.hbase.Cell>, java.lang.Boolean, boolean);
    Code:
       0: aload_0
       1: aload_1
       2: iload_2
       3: iconst_0
       4: invokestatic  #13                 // Method create:(Ljava/util/List;Ljava/lang/Boolean;ZZ)Lorg/apache/hadoop/hbase/client/Result;
       7: areturn

  public static org.apache.hadoop.hbase.client.Result create(java.util.List<org.apache.hadoop.hbase.Cell>, java.lang.Boolean, boolean, boolean);
    Code:
       0: aload_1
       1: ifnull        16
       4: new           #7                  // class org/apache/hadoop/hbase/client/Result
       7: dup
       8: aconst_null
       9: aload_1
      10: iload_2
      11: iload_3
      12: invokespecial #14                 // Method "<init>":([Lorg/apache/hadoop/hbase/Cell;Ljava/lang/Boolean;ZZ)V
      15: areturn
      16: new           #7                  // class org/apache/hadoop/hbase/client/Result
      19: dup
      20: aload_0
      21: aload_0
      22: invokeinterface #15,  1           // InterfaceMethod java/util/List.size:()I
      27: anewarray     #16                 // class org/apache/hadoop/hbase/Cell
      30: invokeinterface #17,  2           // InterfaceMethod java/util/List.toArray:([Ljava/lang/Object;)[Ljava/lang/Object;
      35: checkcast     #18                 // class "[Lorg/apache/hadoop/hbase/Cell;"
      38: aconst_null
      39: iload_2
      40: iload_3
      41: invokespecial #14                 // Method "<init>":([Lorg/apache/hadoop/hbase/Cell;Ljava/lang/Boolean;ZZ)V
      44: areturn

  public static org.apache.hadoop.hbase.client.Result create(org.apache.hadoop.hbase.Cell[]);
    Code:
       0: aload_0
       1: aconst_null
       2: iconst_0
       3: invokestatic  #19                 // Method create:([Lorg/apache/hadoop/hbase/Cell;Ljava/lang/Boolean;Z)Lorg/apache/hadoop/hbase/client/Result;
       6: areturn

  public static org.apache.hadoop.hbase.client.Result create(org.apache.hadoop.hbase.Cell[], java.lang.Boolean, boolean);
    Code:
       0: aload_0
       1: aload_1
       2: iload_2
       3: iconst_0
       4: invokestatic  #20                 // Method create:([Lorg/apache/hadoop/hbase/Cell;Ljava/lang/Boolean;ZZ)Lorg/apache/hadoop/hbase/client/Result;
       7: areturn

  public static org.apache.hadoop.hbase.client.Result create(org.apache.hadoop.hbase.Cell[], java.lang.Boolean, boolean, boolean);
    Code:
       0: aload_1
       1: ifnull        16
       4: new           #7                  // class org/apache/hadoop/hbase/client/Result
       7: dup
       8: aconst_null
       9: aload_1
      10: iload_2
      11: iload_3
      12: invokespecial #14                 // Method "<init>":([Lorg/apache/hadoop/hbase/Cell;Ljava/lang/Boolean;ZZ)V
      15: areturn
      16: new           #7                  // class org/apache/hadoop/hbase/client/Result
      19: dup
      20: aload_0
      21: aconst_null
      22: iload_2
      23: iload_3
      24: invokespecial #14                 // Method "<init>":([Lorg/apache/hadoop/hbase/Cell;Ljava/lang/Boolean;ZZ)V
      27: areturn

  public static org.apache.hadoop.hbase.client.Result createCursorResult(org.apache.hadoop.hbase.client.Cursor);
    Code:
       0: new           #7                  // class org/apache/hadoop/hbase/client/Result
       3: dup
       4: aload_0
       5: invokespecial #21                 // Method "<init>":(Lorg/apache/hadoop/hbase/client/Cursor;)V
       8: areturn

  public byte[] getRow();
    Code:
       0: aload_0
       1: getfield      #5                  // Field row:[B
       4: ifnonnull     39
       7: aload_0
       8: aload_0
       9: getfield      #22                 // Field cells:[Lorg/apache/hadoop/hbase/Cell;
      12: ifnull        23
      15: aload_0
      16: getfield      #22                 // Field cells:[Lorg/apache/hadoop/hbase/Cell;
      19: arraylength
      20: ifne          27
      23: aconst_null
      24: goto          36
      27: aload_0
      28: getfield      #22                 // Field cells:[Lorg/apache/hadoop/hbase/Cell;
      31: iconst_0
      32: aaload
      33: invokestatic  #24                 // Method org/apache/hadoop/hbase/CellUtil.cloneRow:(Lorg/apache/hadoop/hbase/Cell;)[B
      36: putfield      #5                  // Field row:[B
      39: aload_0
      40: getfield      #5                  // Field row:[B
      43: areturn

  public org.apache.hadoop.hbase.Cell[] rawCells();
    Code:
       0: aload_0
       1: getfield      #22                 // Field cells:[Lorg/apache/hadoop/hbase/Cell;
       4: areturn

  public java.util.List<org.apache.hadoop.hbase.Cell> listCells();
    Code:
       0: aload_0
       1: invokevirtual #25                 // Method isEmpty:()Z
       4: ifeq          11
       7: aconst_null
       8: goto          18
      11: aload_0
      12: invokevirtual #26                 // Method rawCells:()[Lorg/apache/hadoop/hbase/Cell;
      15: invokestatic  #27                 // Method java/util/Arrays.asList:([Ljava/lang/Object;)Ljava/util/List;
      18: areturn

  public java.util.List<org.apache.hadoop.hbase.Cell> getColumnCells(byte[], byte[]);
    Code:
       0: new           #28                 // class java/util/ArrayList
       3: dup
       4: invokespecial #29                 // Method java/util/ArrayList."<init>":()V
       7: astore_3
       8: aload_0
       9: invokevirtual #26                 // Method rawCells:()[Lorg/apache/hadoop/hbase/Cell;
      12: astore        4
      14: aload         4
      16: ifnull        25
      19: aload         4
      21: arraylength
      22: ifne          27
      25: aload_3
      26: areturn
      27: aload_0
      28: aload         4
      30: aload_1
      31: aload_2
      32: invokevirtual #30                 // Method binarySearch:([Lorg/apache/hadoop/hbase/Cell;[B[B)I
      35: istore        5
      37: iload         5
      39: iconst_m1
      40: if_icmpne     45
      43: aload_3
      44: areturn
      45: iload         5
      47: istore        6
      49: iload         6
      51: aload         4
      53: arraylength
      54: if_icmpge     88
      57: aload         4
      59: iload         6
      61: aaload
      62: aload_1
      63: aload_2
      64: invokestatic  #31                 // Method org/apache/hadoop/hbase/CellUtil.matchingColumn:(Lorg/apache/hadoop/hbase/Cell;[B[B)Z
      67: ifeq          88
      70: aload_3
      71: aload         4
      73: iload         6
      75: aaload
      76: invokeinterface #32,  2           // InterfaceMethod java/util/List.add:(Ljava/lang/Object;)Z
      81: pop
      82: iinc          6, 1
      85: goto          49
      88: aload_3
      89: areturn

  protected int binarySearch(org.apache.hadoop.hbase.Cell[], byte[], byte[]);
    Code:
       0: aload_0
       1: aload_2
       2: invokespecial #34                 // Method notNullBytes:([B)[B
       5: astore        4
       7: aload_0
       8: aload_3
       9: invokespecial #34                 // Method notNullBytes:([B)[B
      12: astore        5
      14: aload_1
      15: iconst_0
      16: aaload
      17: invokeinterface #35,  1           // InterfaceMethod org/apache/hadoop/hbase/Cell.getRowArray:()[B
      22: aload_1
      23: iconst_0
      24: aaload
      25: invokeinterface #36,  1           // InterfaceMethod org/apache/hadoop/hbase/Cell.getRowOffset:()I
      30: aload_1
      31: iconst_0
      32: aaload
      33: invokeinterface #37,  1           // InterfaceMethod org/apache/hadoop/hbase/Cell.getRowLength:()S
      38: aload         4
      40: iconst_0
      41: aload         4
      43: arraylength
      44: i2b
      45: aload         5
      47: iconst_0
      48: aload         5
      50: arraylength
      51: invokestatic  #38                 // Method org/apache/hadoop/hbase/PrivateCellUtil.createFirstOnRow:([BIS[BIB[BII)Lorg/apache/hadoop/hbase/Cell;
      54: astore        6
      56: aload_1
      57: aload         6
      59: invokestatic  #39                 // InterfaceMethod org/apache/hadoop/hbase/CellComparator.getInstance:()Lorg/apache/hadoop/hbase/CellComparator;
      62: invokestatic  #40                 // Method java/util/Arrays.binarySearch:([Ljava/lang/Object;Ljava/lang/Object;Ljava/util/Comparator;)I
      65: istore        7
      67: iload         7
      69: ifge          80
      72: iload         7
      74: iconst_1
      75: iadd
      76: iconst_m1
      77: imul
      78: istore        7
      80: iload         7
      82: aload_1
      83: arraylength
      84: if_icmpne     89
      87: iconst_m1
      88: ireturn
      89: iload         7
      91: ireturn

  protected int binarySearch(org.apache.hadoop.hbase.Cell[], byte[], int, int, byte[], int, int);
    Code:
       0: aload_1
       1: iconst_0
       2: aaload
       3: invokeinterface #37,  1           // InterfaceMethod org/apache/hadoop/hbase/Cell.getRowLength:()S
       8: iload         4
      10: iload         7
      12: iconst_0
      13: invokestatic  #41                 // Method org/apache/hadoop/hbase/KeyValue.getKeyValueDataStructureSize:(IIII)J
      16: l2d
      17: dstore        8
      19: getstatic     #42                 // Field localBuffer:Ljava/lang/ThreadLocal;
      22: invokevirtual #43                 // Method java/lang/ThreadLocal.get:()Ljava/lang/Object;
      25: checkcast     #44                 // class "[B"
      28: astore        10
      30: aload         10
      32: ifnull        45
      35: dload         8
      37: aload         10
      39: arraylength
      40: i2d
      41: dcmpl
      42: ifle          71
      45: dload         8
      47: ldc2_w        #45                 // double 128.0d
      50: ddiv
      51: invokestatic  #47                 // Method java/lang/Math.ceil:(D)D
      54: d2i
      55: sipush        128
      58: imul
      59: newarray       byte
      61: astore        10
      63: getstatic     #42                 // Field localBuffer:Ljava/lang/ThreadLocal;
      66: aload         10
      68: invokevirtual #48                 // Method java/lang/ThreadLocal.set:(Ljava/lang/Object;)V
      71: aload         10
      73: iconst_0
      74: aload_1
      75: iconst_0
      76: aaload
      77: invokeinterface #35,  1           // InterfaceMethod org/apache/hadoop/hbase/Cell.getRowArray:()[B
      82: aload_1
      83: iconst_0
      84: aaload
      85: invokeinterface #36,  1           // InterfaceMethod org/apache/hadoop/hbase/Cell.getRowOffset:()I
      90: aload_1
      91: iconst_0
      92: aaload
      93: invokeinterface #37,  1           // InterfaceMethod org/apache/hadoop/hbase/Cell.getRowLength:()S
      98: aload_2
      99: iload_3
     100: iload         4
     102: aload         5
     104: iload         6
     106: iload         7
     108: invokestatic  #49                 // Method org/apache/hadoop/hbase/KeyValueUtil.createFirstOnRow:([BI[BII[BII[BII)Lorg/apache/hadoop/hbase/KeyValue;
     111: astore        11
     113: aload_1
     114: aload         11
     116: invokestatic  #39                 // InterfaceMethod org/apache/hadoop/hbase/CellComparator.getInstance:()Lorg/apache/hadoop/hbase/CellComparator;
     119: invokestatic  #40                 // Method java/util/Arrays.binarySearch:([Ljava/lang/Object;Ljava/lang/Object;Ljava/util/Comparator;)I
     122: istore        12
     124: iload         12
     126: ifge          137
     129: iload         12
     131: iconst_1
     132: iadd
     133: iconst_m1
     134: imul
     135: istore        12
     137: iload         12
     139: aload_1
     140: arraylength
     141: if_icmpne     146
     144: iconst_m1
     145: ireturn
     146: iload         12
     148: ireturn

  public org.apache.hadoop.hbase.Cell getColumnLatestCell(byte[], byte[]);
    Code:
       0: aload_0
       1: invokevirtual #26                 // Method rawCells:()[Lorg/apache/hadoop/hbase/Cell;
       4: astore_3
       5: aload_3
       6: ifnull        14
       9: aload_3
      10: arraylength
      11: ifne          16
      14: aconst_null
      15: areturn
      16: aload_0
      17: aload_3
      18: aload_1
      19: aload_2
      20: invokevirtual #30                 // Method binarySearch:([Lorg/apache/hadoop/hbase/Cell;[B[B)I
      23: istore        4
      25: iload         4
      27: iconst_m1
      28: if_icmpne     33
      31: aconst_null
      32: areturn
      33: aload_3
      34: iload         4
      36: aaload
      37: aload_1
      38: aload_2
      39: invokestatic  #31                 // Method org/apache/hadoop/hbase/CellUtil.matchingColumn:(Lorg/apache/hadoop/hbase/Cell;[B[B)Z
      42: ifeq          50
      45: aload_3
      46: iload         4
      48: aaload
      49: areturn
      50: aconst_null
      51: areturn

  public org.apache.hadoop.hbase.Cell getColumnLatestCell(byte[], int, int, byte[], int, int);
    Code:
       0: aload_0
       1: invokevirtual #26                 // Method rawCells:()[Lorg/apache/hadoop/hbase/Cell;
       4: astore        7
       6: aload         7
       8: ifnull        17
      11: aload         7
      13: arraylength
      14: ifne          19
      17: aconst_null
      18: areturn
      19: aload_0
      20: aload         7
      22: aload_1
      23: iload_2
      24: iload_3
      25: aload         4
      27: iload         5
      29: iload         6
      31: invokevirtual #50                 // Method binarySearch:([Lorg/apache/hadoop/hbase/Cell;[BII[BII)I
      34: istore        8
      36: iload         8
      38: iconst_m1
      39: if_icmpne     44
      42: aconst_null
      43: areturn
      44: aload         7
      46: iload         8
      48: aaload
      49: aload_1
      50: iload_2
      51: iload_3
      52: aload         4
      54: iload         5
      56: iload         6
      58: invokestatic  #51                 // Method org/apache/hadoop/hbase/PrivateCellUtil.matchingColumn:(Lorg/apache/hadoop/hbase/Cell;[BII[BII)Z
      61: ifeq          70
      64: aload         7
      66: iload         8
      68: aaload
      69: areturn
      70: aconst_null
      71: areturn

  public byte[] getValue(byte[], byte[]);
    Code:
       0: aload_0
       1: aload_1
       2: aload_2
       3: invokevirtual #52                 // Method getColumnLatestCell:([B[B)Lorg/apache/hadoop/hbase/Cell;
       6: astore_3
       7: aload_3
       8: ifnonnull     13
      11: aconst_null
      12: areturn
      13: aload_3
      14: invokestatic  #53                 // Method org/apache/hadoop/hbase/CellUtil.cloneValue:(Lorg/apache/hadoop/hbase/Cell;)[B
      17: areturn

  public java.nio.ByteBuffer getValueAsByteBuffer(byte[], byte[]);
    Code:
       0: aload_0
       1: aload_1
       2: iconst_0
       3: aload_1
       4: arraylength
       5: aload_2
       6: iconst_0
       7: aload_2
       8: arraylength
       9: invokevirtual #54                 // Method getColumnLatestCell:([BII[BII)Lorg/apache/hadoop/hbase/Cell;
      12: astore_3
      13: aload_3
      14: ifnonnull     19
      17: aconst_null
      18: areturn
      19: aload_3
      20: invokeinterface #55,  1           // InterfaceMethod org/apache/hadoop/hbase/Cell.getValueArray:()[B
      25: aload_3
      26: invokeinterface #56,  1           // InterfaceMethod org/apache/hadoop/hbase/Cell.getValueOffset:()I
      31: aload_3
      32: invokeinterface #57,  1           // InterfaceMethod org/apache/hadoop/hbase/Cell.getValueLength:()I
      37: invokestatic  #58                 // Method java/nio/ByteBuffer.wrap:([BII)Ljava/nio/ByteBuffer;
      40: invokevirtual #59                 // Method java/nio/ByteBuffer.asReadOnlyBuffer:()Ljava/nio/ByteBuffer;
      43: areturn

  public java.nio.ByteBuffer getValueAsByteBuffer(byte[], int, int, byte[], int, int);
    Code:
       0: aload_0
       1: aload_1
       2: iload_2
       3: iload_3
       4: aload         4
       6: iload         5
       8: iload         6
      10: invokevirtual #54                 // Method getColumnLatestCell:([BII[BII)Lorg/apache/hadoop/hbase/Cell;
      13: astore        7
      15: aload         7
      17: ifnonnull     22
      20: aconst_null
      21: areturn
      22: aload         7
      24: invokeinterface #55,  1           // InterfaceMethod org/apache/hadoop/hbase/Cell.getValueArray:()[B
      29: aload         7
      31: invokeinterface #56,  1           // InterfaceMethod org/apache/hadoop/hbase/Cell.getValueOffset:()I
      36: aload         7
      38: invokeinterface #57,  1           // InterfaceMethod org/apache/hadoop/hbase/Cell.getValueLength:()I
      43: invokestatic  #58                 // Method java/nio/ByteBuffer.wrap:([BII)Ljava/nio/ByteBuffer;
      46: invokevirtual #59                 // Method java/nio/ByteBuffer.asReadOnlyBuffer:()Ljava/nio/ByteBuffer;
      49: areturn

  public boolean loadValue(byte[], byte[], java.nio.ByteBuffer) throws java.nio.BufferOverflowException;
    Code:
       0: aload_0
       1: aload_1
       2: iconst_0
       3: aload_1
       4: arraylength
       5: aload_2
       6: iconst_0
       7: aload_2
       8: arraylength
       9: aload_3
      10: invokevirtual #60                 // Method loadValue:([BII[BIILjava/nio/ByteBuffer;)Z
      13: ireturn

  public boolean loadValue(byte[], int, int, byte[], int, int, java.nio.ByteBuffer) throws java.nio.BufferOverflowException;
    Code:
       0: aload_0
       1: aload_1
       2: iload_2
       3: iload_3
       4: aload         4
       6: iload         5
       8: iload         6
      10: invokevirtual #54                 // Method getColumnLatestCell:([BII[BII)Lorg/apache/hadoop/hbase/Cell;
      13: astore        8
      15: aload         8
      17: ifnonnull     22
      20: iconst_0
      21: ireturn
      22: aload         7
      24: aload         8
      26: invokeinterface #55,  1           // InterfaceMethod org/apache/hadoop/hbase/Cell.getValueArray:()[B
      31: aload         8
      33: invokeinterface #56,  1           // InterfaceMethod org/apache/hadoop/hbase/Cell.getValueOffset:()I
      38: aload         8
      40: invokeinterface #57,  1           // InterfaceMethod org/apache/hadoop/hbase/Cell.getValueLength:()I
      45: invokevirtual #61                 // Method java/nio/ByteBuffer.put:([BII)Ljava/nio/ByteBuffer;
      48: pop
      49: iconst_1
      50: ireturn

  public boolean containsNonEmptyColumn(byte[], byte[]);
    Code:
       0: aload_0
       1: aload_1
       2: iconst_0
       3: aload_1
       4: arraylength
       5: aload_2
       6: iconst_0
       7: aload_2
       8: arraylength
       9: invokevirtual #62                 // Method containsNonEmptyColumn:([BII[BII)Z
      12: ireturn

  public boolean containsNonEmptyColumn(byte[], int, int, byte[], int, int);
    Code:
       0: aload_0
       1: aload_1
       2: iload_2
       3: iload_3
       4: aload         4
       6: iload         5
       8: iload         6
      10: invokevirtual #54                 // Method getColumnLatestCell:([BII[BII)Lorg/apache/hadoop/hbase/Cell;
      13: astore        7
      15: aload         7
      17: ifnull        34
      20: aload         7
      22: invokeinterface #57,  1           // InterfaceMethod org/apache/hadoop/hbase/Cell.getValueLength:()I
      27: ifle          34
      30: iconst_1
      31: goto          35
      34: iconst_0
      35: ireturn

  public boolean containsEmptyColumn(byte[], byte[]);
    Code:
       0: aload_0
       1: aload_1
       2: iconst_0
       3: aload_1
       4: arraylength
       5: aload_2
       6: iconst_0
       7: aload_2
       8: arraylength
       9: invokevirtual #63                 // Method containsEmptyColumn:([BII[BII)Z
      12: ireturn

  public boolean containsEmptyColumn(byte[], int, int, byte[], int, int);
    Code:
       0: aload_0
       1: aload_1
       2: iload_2
       3: iload_3
       4: aload         4
       6: iload         5
       8: iload         6
      10: invokevirtual #54                 // Method getColumnLatestCell:([BII[BII)Lorg/apache/hadoop/hbase/Cell;
      13: astore        7
      15: aload         7
      17: ifnull        34
      20: aload         7
      22: invokeinterface #57,  1           // InterfaceMethod org/apache/hadoop/hbase/Cell.getValueLength:()I
      27: ifne          34
      30: iconst_1
      31: goto          35
      34: iconst_0
      35: ireturn

  public boolean containsColumn(byte[], byte[]);
    Code:
       0: aload_0
       1: aload_1
       2: aload_2
       3: invokevirtual #52                 // Method getColumnLatestCell:([B[B)Lorg/apache/hadoop/hbase/Cell;
       6: astore_3
       7: aload_3
       8: ifnull        15
      11: iconst_1
      12: goto          16
      15: iconst_0
      16: ireturn

  public boolean containsColumn(byte[], int, int, byte[], int, int);
    Code:
       0: aload_0
       1: aload_1
       2: iload_2
       3: iload_3
       4: aload         4
       6: iload         5
       8: iload         6
      10: invokevirtual #54                 // Method getColumnLatestCell:([BII[BII)Lorg/apache/hadoop/hbase/Cell;
      13: ifnull        20
      16: iconst_1
      17: goto          21
      20: iconst_0
      21: ireturn

  public java.util.NavigableMap<byte[], java.util.NavigableMap<byte[], java.util.NavigableMap<java.lang.Long, byte[]>>> getMap();
    Code:
       0: aload_0
       1: getfield      #6                  // Field familyMap:Ljava/util/NavigableMap;
       4: ifnull        12
       7: aload_0
       8: getfield      #6                  // Field familyMap:Ljava/util/NavigableMap;
      11: areturn
      12: aload_0
      13: invokevirtual #25                 // Method isEmpty:()Z
      16: ifeq          21
      19: aconst_null
      20: areturn
      21: aload_0
      22: new           #64                 // class java/util/TreeMap
      25: dup
      26: getstatic     #65                 // Field org/apache/hadoop/hbase/util/Bytes.BYTES_COMPARATOR:Ljava/util/Comparator;
      29: invokespecial #66                 // Method java/util/TreeMap."<init>":(Ljava/util/Comparator;)V
      32: putfield      #6                  // Field familyMap:Ljava/util/NavigableMap;
      35: aload_0
      36: getfield      #22                 // Field cells:[Lorg/apache/hadoop/hbase/Cell;
      39: astore_1
      40: aload_1
      41: arraylength
      42: istore_2
      43: iconst_0
      44: istore_3
      45: iload_3
      46: iload_2
      47: if_icmpge     201
      50: aload_1
      51: iload_3
      52: aaload
      53: astore        4
      55: aload         4
      57: invokestatic  #67                 // Method org/apache/hadoop/hbase/CellUtil.cloneFamily:(Lorg/apache/hadoop/hbase/Cell;)[B
      60: astore        5
      62: aload_0
      63: getfield      #6                  // Field familyMap:Ljava/util/NavigableMap;
      66: aload         5
      68: invokeinterface #68,  2           // InterfaceMethod java/util/NavigableMap.get:(Ljava/lang/Object;)Ljava/lang/Object;
      73: checkcast     #69                 // class java/util/NavigableMap
      76: astore        6
      78: aload         6
      80: ifnonnull     109
      83: new           #64                 // class java/util/TreeMap
      86: dup
      87: getstatic     #65                 // Field org/apache/hadoop/hbase/util/Bytes.BYTES_COMPARATOR:Ljava/util/Comparator;
      90: invokespecial #66                 // Method java/util/TreeMap."<init>":(Ljava/util/Comparator;)V
      93: astore        6
      95: aload_0
      96: getfield      #6                  // Field familyMap:Ljava/util/NavigableMap;
      99: aload         5
     101: aload         6
     103: invokeinterface #70,  3           // InterfaceMethod java/util/NavigableMap.put:(Ljava/lang/Object;Ljava/lang/Object;)Ljava/lang/Object;
     108: pop
     109: aload         4
     111: invokestatic  #71                 // Method org/apache/hadoop/hbase/CellUtil.cloneQualifier:(Lorg/apache/hadoop/hbase/Cell;)[B
     114: astore        7
     116: aload         6
     118: aload         7
     120: invokeinterface #68,  2           // InterfaceMethod java/util/NavigableMap.get:(Ljava/lang/Object;)Ljava/lang/Object;
     125: checkcast     #69                 // class java/util/NavigableMap
     128: astore        8
     130: aload         8
     132: ifnonnull     164
     135: new           #64                 // class java/util/TreeMap
     138: dup
     139: new           #72                 // class org/apache/hadoop/hbase/client/Result$1
     142: dup
     143: aload_0
     144: invokespecial #73                 // Method org/apache/hadoop/hbase/client/Result$1."<init>":(Lorg/apache/hadoop/hbase/client/Result;)V
     147: invokespecial #66                 // Method java/util/TreeMap."<init>":(Ljava/util/Comparator;)V
     150: astore        8
     152: aload         6
     154: aload         7
     156: aload         8
     158: invokeinterface #70,  3           // InterfaceMethod java/util/NavigableMap.put:(Ljava/lang/Object;Ljava/lang/Object;)Ljava/lang/Object;
     163: pop
     164: aload         4
     166: invokeinterface #74,  1           // InterfaceMethod org/apache/hadoop/hbase/Cell.getTimestamp:()J
     171: invokestatic  #75                 // Method java/lang/Long.valueOf:(J)Ljava/lang/Long;
     174: astore        9
     176: aload         4
     178: invokestatic  #53                 // Method org/apache/hadoop/hbase/CellUtil.cloneValue:(Lorg/apache/hadoop/hbase/Cell;)[B
     181: astore        10
     183: aload         8
     185: aload         9
     187: aload         10
     189: invokeinterface #70,  3           // InterfaceMethod java/util/NavigableMap.put:(Ljava/lang/Object;Ljava/lang/Object;)Ljava/lang/Object;
     194: pop
     195: iinc          3, 1
     198: goto          45
     201: aload_0
     202: getfield      #6                  // Field familyMap:Ljava/util/NavigableMap;
     205: areturn

  public java.util.NavigableMap<byte[], java.util.NavigableMap<byte[], byte[]>> getNoVersionMap();
    Code:
       0: aload_0
       1: getfield      #6                  // Field familyMap:Ljava/util/NavigableMap;
       4: ifnonnull     12
       7: aload_0
       8: invokevirtual #76                 // Method getMap:()Ljava/util/NavigableMap;
      11: pop
      12: aload_0
      13: invokevirtual #25                 // Method isEmpty:()Z
      16: ifeq          21
      19: aconst_null
      20: areturn
      21: new           #64                 // class java/util/TreeMap
      24: dup
      25: getstatic     #65                 // Field org/apache/hadoop/hbase/util/Bytes.BYTES_COMPARATOR:Ljava/util/Comparator;
      28: invokespecial #66                 // Method java/util/TreeMap."<init>":(Ljava/util/Comparator;)V
      31: astore_1
      32: aload_0
      33: getfield      #6                  // Field familyMap:Ljava/util/NavigableMap;
      36: invokeinterface #77,  1           // InterfaceMethod java/util/NavigableMap.entrySet:()Ljava/util/Set;
      41: invokeinterface #78,  1           // InterfaceMethod java/util/Set.iterator:()Ljava/util/Iterator;
      46: astore_2
      47: aload_2
      48: invokeinterface #79,  1           // InterfaceMethod java/util/Iterator.hasNext:()Z
      53: ifeq          194
      56: aload_2
      57: invokeinterface #80,  1           // InterfaceMethod java/util/Iterator.next:()Ljava/lang/Object;
      62: checkcast     #81                 // class java/util/Map$Entry
      65: astore_3
      66: new           #64                 // class java/util/TreeMap
      69: dup
      70: getstatic     #65                 // Field org/apache/hadoop/hbase/util/Bytes.BYTES_COMPARATOR:Ljava/util/Comparator;
      73: invokespecial #66                 // Method java/util/TreeMap."<init>":(Ljava/util/Comparator;)V
      76: astore        4
      78: aload_3
      79: invokeinterface #82,  1           // InterfaceMethod java/util/Map$Entry.getValue:()Ljava/lang/Object;
      84: checkcast     #69                 // class java/util/NavigableMap
      87: invokeinterface #77,  1           // InterfaceMethod java/util/NavigableMap.entrySet:()Ljava/util/Set;
      92: invokeinterface #78,  1           // InterfaceMethod java/util/Set.iterator:()Ljava/util/Iterator;
      97: astore        5
      99: aload         5
     101: invokeinterface #79,  1           // InterfaceMethod java/util/Iterator.hasNext:()Z
     106: ifeq          176
     109: aload         5
     111: invokeinterface #80,  1           // InterfaceMethod java/util/Iterator.next:()Ljava/lang/Object;
     116: checkcast     #81                 // class java/util/Map$Entry
     119: astore        6
     121: aload         6
     123: invokeinterface #82,  1           // InterfaceMethod java/util/Map$Entry.getValue:()Ljava/lang/Object;
     128: checkcast     #69                 // class java/util/NavigableMap
     131: aload         6
     133: invokeinterface #82,  1           // InterfaceMethod java/util/Map$Entry.getValue:()Ljava/lang/Object;
     138: checkcast     #69                 // class java/util/NavigableMap
     141: invokeinterface #83,  1           // InterfaceMethod java/util/NavigableMap.firstKey:()Ljava/lang/Object;
     146: invokeinterface #68,  2           // InterfaceMethod java/util/NavigableMap.get:(Ljava/lang/Object;)Ljava/lang/Object;
     151: checkcast     #44                 // class "[B"
     154: astore        7
     156: aload         4
     158: aload         6
     160: invokeinterface #84,  1           // InterfaceMethod java/util/Map$Entry.getKey:()Ljava/lang/Object;
     165: aload         7
     167: invokeinterface #70,  3           // InterfaceMethod java/util/NavigableMap.put:(Ljava/lang/Object;Ljava/lang/Object;)Ljava/lang/Object;
     172: pop
     173: goto          99
     176: aload_1
     177: aload_3
     178: invokeinterface #84,  1           // InterfaceMethod java/util/Map$Entry.getKey:()Ljava/lang/Object;
     183: aload         4
     185: invokeinterface #70,  3           // InterfaceMethod java/util/NavigableMap.put:(Ljava/lang/Object;Ljava/lang/Object;)Ljava/lang/Object;
     190: pop
     191: goto          47
     194: aload_1
     195: areturn

  public java.util.NavigableMap<byte[], byte[]> getFamilyMap(byte[]);
    Code:
       0: aload_0
       1: getfield      #6                  // Field familyMap:Ljava/util/NavigableMap;
       4: ifnonnull     12
       7: aload_0
       8: invokevirtual #76                 // Method getMap:()Ljava/util/NavigableMap;
      11: pop
      12: aload_0
      13: invokevirtual #25                 // Method isEmpty:()Z
      16: ifeq          21
      19: aconst_null
      20: areturn
      21: new           #64                 // class java/util/TreeMap
      24: dup
      25: getstatic     #65                 // Field org/apache/hadoop/hbase/util/Bytes.BYTES_COMPARATOR:Ljava/util/Comparator;
      28: invokespecial #66                 // Method java/util/TreeMap."<init>":(Ljava/util/Comparator;)V
      31: astore_2
      32: aload_0
      33: getfield      #6                  // Field familyMap:Ljava/util/NavigableMap;
      36: aload_1
      37: invokeinterface #68,  2           // InterfaceMethod java/util/NavigableMap.get:(Ljava/lang/Object;)Ljava/lang/Object;
      42: checkcast     #69                 // class java/util/NavigableMap
      45: astore_3
      46: aload_3
      47: ifnonnull     52
      50: aload_2
      51: areturn
      52: aload_3
      53: invokeinterface #77,  1           // InterfaceMethod java/util/NavigableMap.entrySet:()Ljava/util/Set;
      58: invokeinterface #78,  1           // InterfaceMethod java/util/Set.iterator:()Ljava/util/Iterator;
      63: astore        4
      65: aload         4
      67: invokeinterface #79,  1           // InterfaceMethod java/util/Iterator.hasNext:()Z
      72: ifeq          141
      75: aload         4
      77: invokeinterface #80,  1           // InterfaceMethod java/util/Iterator.next:()Ljava/lang/Object;
      82: checkcast     #81                 // class java/util/Map$Entry
      85: astore        5
      87: aload         5
      89: invokeinterface #82,  1           // InterfaceMethod java/util/Map$Entry.getValue:()Ljava/lang/Object;
      94: checkcast     #69                 // class java/util/NavigableMap
      97: aload         5
      99: invokeinterface #82,  1           // InterfaceMethod java/util/Map$Entry.getValue:()Ljava/lang/Object;
     104: checkcast     #69                 // class java/util/NavigableMap
     107: invokeinterface #83,  1           // InterfaceMethod java/util/NavigableMap.firstKey:()Ljava/lang/Object;
     112: invokeinterface #68,  2           // InterfaceMethod java/util/NavigableMap.get:(Ljava/lang/Object;)Ljava/lang/Object;
     117: checkcast     #44                 // class "[B"
     120: astore        6
     122: aload_2
     123: aload         5
     125: invokeinterface #84,  1           // InterfaceMethod java/util/Map$Entry.getKey:()Ljava/lang/Object;
     130: aload         6
     132: invokeinterface #70,  3           // InterfaceMethod java/util/NavigableMap.put:(Ljava/lang/Object;Ljava/lang/Object;)Ljava/lang/Object;
     137: pop
     138: goto          65
     141: aload_2
     142: areturn

  public byte[] value();
    Code:
       0: aload_0
       1: invokevirtual #25                 // Method isEmpty:()Z
       4: ifeq          9
       7: aconst_null
       8: areturn
       9: aload_0
      10: getfield      #22                 // Field cells:[Lorg/apache/hadoop/hbase/Cell;
      13: iconst_0
      14: aaload
      15: invokestatic  #53                 // Method org/apache/hadoop/hbase/CellUtil.cloneValue:(Lorg/apache/hadoop/hbase/Cell;)[B
      18: areturn

  public boolean isEmpty();
    Code:
       0: aload_0
       1: getfield      #22                 // Field cells:[Lorg/apache/hadoop/hbase/Cell;
       4: ifnull        15
       7: aload_0
       8: getfield      #22                 // Field cells:[Lorg/apache/hadoop/hbase/Cell;
      11: arraylength
      12: ifne          19
      15: iconst_1
      16: goto          20
      19: iconst_0
      20: ireturn

  public int size();
    Code:
       0: aload_0
       1: getfield      #22                 // Field cells:[Lorg/apache/hadoop/hbase/Cell;
       4: ifnonnull     11
       7: iconst_0
       8: goto          16
      11: aload_0
      12: getfield      #22                 // Field cells:[Lorg/apache/hadoop/hbase/Cell;
      15: arraylength
      16: ireturn

  public java.lang.String toString();
    Code:
       0: new           #85                 // class java/lang/StringBuilder
       3: dup
       4: invokespecial #86                 // Method java/lang/StringBuilder."<init>":()V
       7: astore_1
       8: aload_1
       9: ldc           #87                 // String keyvalues=
      11: invokevirtual #88                 // Method java/lang/StringBuilder.append:(Ljava/lang/String;)Ljava/lang/StringBuilder;
      14: pop
      15: aload_0
      16: invokevirtual #25                 // Method isEmpty:()Z
      19: ifeq          34
      22: aload_1
      23: ldc           #89                 // String NONE
      25: invokevirtual #88                 // Method java/lang/StringBuilder.append:(Ljava/lang/String;)Ljava/lang/StringBuilder;
      28: pop
      29: aload_1
      30: invokevirtual #90                 // Method java/lang/StringBuilder.toString:()Ljava/lang/String;
      33: areturn
      34: aload_1
      35: ldc           #91                 // String {
      37: invokevirtual #88                 // Method java/lang/StringBuilder.append:(Ljava/lang/String;)Ljava/lang/StringBuilder;
      40: pop
      41: iconst_0
      42: istore_2
      43: aload_0
      44: getfield      #22                 // Field cells:[Lorg/apache/hadoop/hbase/Cell;
      47: astore_3
      48: aload_3
      49: arraylength
      50: istore        4
      52: iconst_0
      53: istore        5
      55: iload         5
      57: iload         4
      59: if_icmpge     100
      62: aload_3
      63: iload         5
      65: aaload
      66: astore        6
      68: iload_2
      69: ifeq          82
      72: aload_1
      73: ldc           #92                 // String ,
      75: invokevirtual #88                 // Method java/lang/StringBuilder.append:(Ljava/lang/String;)Ljava/lang/StringBuilder;
      78: pop
      79: goto          84
      82: iconst_1
      83: istore_2
      84: aload_1
      85: aload         6
      87: invokevirtual #93                 // Method java/lang/Object.toString:()Ljava/lang/String;
      90: invokevirtual #88                 // Method java/lang/StringBuilder.append:(Ljava/lang/String;)Ljava/lang/StringBuilder;
      93: pop
      94: iinc          5, 1
      97: goto          55
     100: aload_1
     101: ldc           #94                 // String }
     103: invokevirtual #88                 // Method java/lang/StringBuilder.append:(Ljava/lang/String;)Ljava/lang/StringBuilder;
     106: pop
     107: aload_1
     108: invokevirtual #90                 // Method java/lang/StringBuilder.toString:()Ljava/lang/String;
     111: areturn

  public static void compareResults(org.apache.hadoop.hbase.client.Result, org.apache.hadoop.hbase.client.Result) throws java.lang.Exception;
    Code:
       0: aload_1
       1: ifnonnull     37
       4: new           #95                 // class java/lang/Exception
       7: dup
       8: new           #85                 // class java/lang/StringBuilder
      11: dup
      12: invokespecial #86                 // Method java/lang/StringBuilder."<init>":()V
      15: ldc           #96                 // String There wasn't enough rows, we stopped at
      17: invokevirtual #88                 // Method java/lang/StringBuilder.append:(Ljava/lang/String;)Ljava/lang/StringBuilder;
      20: aload_0
      21: invokevirtual #97                 // Method getRow:()[B
      24: invokestatic  #98                 // Method org/apache/hadoop/hbase/util/Bytes.toStringBinary:([B)Ljava/lang/String;
      27: invokevirtual #88                 // Method java/lang/StringBuilder.append:(Ljava/lang/String;)Ljava/lang/StringBuilder;
      30: invokevirtual #90                 // Method java/lang/StringBuilder.toString:()Ljava/lang/String;
      33: invokespecial #99                 // Method java/lang/Exception."<init>":(Ljava/lang/String;)V
      36: athrow
      37: aload_0
      38: invokevirtual #100                // Method size:()I
      41: aload_1
      42: invokevirtual #100                // Method size:()I
      45: if_icmpeq     90
      48: new           #95                 // class java/lang/Exception
      51: dup
      52: new           #85                 // class java/lang/StringBuilder
      55: dup
      56: invokespecial #86                 // Method java/lang/StringBuilder."<init>":()V
      59: ldc           #101                // String This row doesn't have the same number of KVs:
      61: invokevirtual #88                 // Method java/lang/StringBuilder.append:(Ljava/lang/String;)Ljava/lang/StringBuilder;
      64: aload_0
      65: invokevirtual #102                // Method toString:()Ljava/lang/String;
      68: invokevirtual #88                 // Method java/lang/StringBuilder.append:(Ljava/lang/String;)Ljava/lang/StringBuilder;
      71: ldc           #103                // String  compared to
      73: invokevirtual #88                 // Method java/lang/StringBuilder.append:(Ljava/lang/String;)Ljava/lang/StringBuilder;
      76: aload_1
      77: invokevirtual #102                // Method toString:()Ljava/lang/String;
      80: invokevirtual #88                 // Method java/lang/StringBuilder.append:(Ljava/lang/String;)Ljava/lang/StringBuilder;
      83: invokevirtual #90                 // Method java/lang/StringBuilder.toString:()Ljava/lang/String;
      86: invokespecial #99                 // Method java/lang/Exception."<init>":(Ljava/lang/String;)V
      89: athrow
      90: aload_0
      91: invokevirtual #26                 // Method rawCells:()[Lorg/apache/hadoop/hbase/Cell;
      94: astore_2
      95: aload_1
      96: invokevirtual #26                 // Method rawCells:()[Lorg/apache/hadoop/hbase/Cell;
      99: astore_3
     100: iconst_0
     101: istore        4
     103: iload         4
     105: aload_0
     106: invokevirtual #100                // Method size:()I
     109: if_icmpge     188
     112: aload_2
     113: iload         4
     115: aaload
     116: aload_3
     117: iload         4
     119: aaload
     120: invokevirtual #104                // Method java/lang/Object.equals:(Ljava/lang/Object;)Z
     123: ifeq          140
     126: aload_2
     127: iload         4
     129: aaload
     130: aload_3
     131: iload         4
     133: aaload
     134: invokestatic  #105                // Method org/apache/hadoop/hbase/CellUtil.matchingValue:(Lorg/apache/hadoop/hbase/Cell;Lorg/apache/hadoop/hbase/Cell;)Z
     137: ifne          182
     140: new           #95                 // class java/lang/Exception
     143: dup
     144: new           #85                 // class java/lang/StringBuilder
     147: dup
     148: invokespecial #86                 // Method java/lang/StringBuilder."<init>":()V
     151: ldc           #106                // String This result was different:
     153: invokevirtual #88                 // Method java/lang/StringBuilder.append:(Ljava/lang/String;)Ljava/lang/StringBuilder;
     156: aload_0
     157: invokevirtual #102                // Method toString:()Ljava/lang/String;
     160: invokevirtual #88                 // Method java/lang/StringBuilder.append:(Ljava/lang/String;)Ljava/lang/StringBuilder;
     163: ldc           #103                // String  compared to
     165: invokevirtual #88                 // Method java/lang/StringBuilder.append:(Ljava/lang/String;)Ljava/lang/StringBuilder;
     168: aload_1
     169: invokevirtual #102                // Method toString:()Ljava/lang/String;
     172: invokevirtual #88                 // Method java/lang/StringBuilder.append:(Ljava/lang/String;)Ljava/lang/StringBuilder;
     175: invokevirtual #90                 // Method java/lang/StringBuilder.toString:()Ljava/lang/String;
     178: invokespecial #99                 // Method java/lang/Exception."<init>":(Ljava/lang/String;)V
     181: athrow
     182: iinc          4, 1
     185: goto          103
     188: return

  public static org.apache.hadoop.hbase.client.Result createCompleteResult(java.lang.Iterable<org.apache.hadoop.hbase.client.Result>) throws java.io.IOException;
    Code:
       0: aload_0
       1: ifnonnull     13
       4: invokestatic  #107                // Method java/util/Collections.emptyList:()Ljava/util/List;
       7: aconst_null
       8: iconst_0
       9: invokestatic  #12                 // Method create:(Ljava/util/List;Ljava/lang/Boolean;Z)Lorg/apache/hadoop/hbase/client/Result;
      12: areturn
      13: new           #28                 // class java/util/ArrayList
      16: dup
      17: invokespecial #29                 // Method java/util/ArrayList."<init>":()V
      20: astore_1
      21: iconst_0
      22: istore_2
      23: aconst_null
      24: astore_3
      25: aconst_null
      26: astore        4
      28: aload_0
      29: invokeinterface #108,  1          // InterfaceMethod java/lang/Iterable.iterator:()Ljava/util/Iterator;
      34: astore        5
      36: aload         5
      38: invokeinterface #79,  1           // InterfaceMethod java/util/Iterator.hasNext:()Z
      43: ifeq          218
      46: aload         5
      48: invokeinterface #80,  1           // InterfaceMethod java/util/Iterator.next:()Ljava/lang/Object;
      53: checkcast     #7                  // class org/apache/hadoop/hbase/client/Result
      56: astore        6
      58: aload         6
      60: invokevirtual #97                 // Method getRow:()[B
      63: astore        4
      65: aload_3
      66: ifnull        105
      69: aload_3
      70: aload         4
      72: invokestatic  #109                // Method org/apache/hadoop/hbase/util/Bytes.equals:([B[B)Z
      75: ifne          105
      78: new           #110                // class java/io/IOException
      81: dup
      82: new           #85                 // class java/lang/StringBuilder
      85: dup
      86: invokespecial #86                 // Method java/lang/StringBuilder."<init>":()V
      89: ldc           #111                // String Cannot form complete result. Rows of partial results do not match. Partial Results:
      91: invokevirtual #88                 // Method java/lang/StringBuilder.append:(Ljava/lang/String;)Ljava/lang/StringBuilder;
      94: aload_0
      95: invokevirtual #112                // Method java/lang/StringBuilder.append:(Ljava/lang/Object;)Ljava/lang/StringBuilder;
      98: invokevirtual #90                 // Method java/lang/StringBuilder.toString:()Ljava/lang/String;
     101: invokespecial #113                // Method java/io/IOException."<init>":(Ljava/lang/String;)V
     104: athrow
     105: aload         5
     107: invokeinterface #79,  1           // InterfaceMethod java/util/Iterator.hasNext:()Z
     112: ifeq          150
     115: aload         6
     117: invokevirtual #114                // Method mayHaveMoreCellsInRow:()Z
     120: ifne          150
     123: new           #110                // class java/io/IOException
     126: dup
     127: new           #85                 // class java/lang/StringBuilder
     130: dup
     131: invokespecial #86                 // Method java/lang/StringBuilder."<init>":()V
     134: ldc           #115                // String Cannot form complete result. Result is missing partial flag. Partial Results:
     136: invokevirtual #88                 // Method java/lang/StringBuilder.append:(Ljava/lang/String;)Ljava/lang/StringBuilder;
     139: aload_0
     140: invokevirtual #112                // Method java/lang/StringBuilder.append:(Ljava/lang/Object;)Ljava/lang/StringBuilder;
     143: invokevirtual #90                 // Method java/lang/StringBuilder.toString:()Ljava/lang/String;
     146: invokespecial #113                // Method java/io/IOException."<init>":(Ljava/lang/String;)V
     149: athrow
     150: aload         4
     152: astore_3
     153: iload_2
     154: ifne          165
     157: aload         6
     159: invokevirtual #116                // Method isStale:()Z
     162: ifeq          169
     165: iconst_1
     166: goto          170
     169: iconst_0
     170: istore_2
     171: aload         6
     173: invokevirtual #26                 // Method rawCells:()[Lorg/apache/hadoop/hbase/Cell;
     176: astore        7
     178: aload         7
     180: arraylength
     181: istore        8
     183: iconst_0
     184: istore        9
     186: iload         9
     188: iload         8
     190: if_icmpge     215
     193: aload         7
     195: iload         9
     197: aaload
     198: astore        10
     200: aload_1
     201: aload         10
     203: invokeinterface #32,  2           // InterfaceMethod java/util/List.add:(Ljava/lang/Object;)Z
     208: pop
     209: iinc          9, 1
     212: goto          186
     215: goto          36
     218: aload_1
     219: aconst_null
     220: iload_2
     221: invokestatic  #12                 // Method create:(Ljava/util/List;Ljava/lang/Boolean;Z)Lorg/apache/hadoop/hbase/client/Result;
     224: areturn

  public static long getTotalSizeOfCells(org.apache.hadoop.hbase.client.Result);
    Code:
       0: lconst_0
       1: lstore_1
       2: aload_0
       3: invokevirtual #25                 // Method isEmpty:()Z
       6: ifeq          11
       9: lload_1
      10: lreturn
      11: aload_0
      12: invokevirtual #26                 // Method rawCells:()[Lorg/apache/hadoop/hbase/Cell;
      15: astore_3
      16: aload_3
      17: arraylength
      18: istore        4
      20: iconst_0
      21: istore        5
      23: iload         5
      25: iload         4
      27: if_icmpge     52
      30: aload_3
      31: iload         5
      33: aaload
      34: astore        6
      36: lload_1
      37: aload         6
      39: invokeinterface #117,  1          // InterfaceMethod org/apache/hadoop/hbase/Cell.heapSize:()J
      44: ladd
      45: lstore_1
      46: iinc          5, 1
      49: goto          23
      52: lload_1
      53: lreturn

  public void copyFrom(org.apache.hadoop.hbase.client.Result);
    Code:
       0: aload_0
       1: invokespecial #118                // Method checkReadonly:()V
       4: aload_0
       5: aconst_null
       6: putfield      #5                  // Field row:[B
       9: aload_0
      10: aconst_null
      11: putfield      #6                  // Field familyMap:Ljava/util/NavigableMap;
      14: aload_0
      15: aload_1
      16: getfield      #22                 // Field cells:[Lorg/apache/hadoop/hbase/Cell;
      19: putfield      #22                 // Field cells:[Lorg/apache/hadoop/hbase/Cell;
      22: return

  public org.apache.hadoop.hbase.CellScanner cellScanner();
    Code:
       0: aload_0
       1: iconst_m1
       2: putfield      #8                  // Field cellScannerIndex:I
       5: aload_0
       6: areturn

  public org.apache.hadoop.hbase.Cell current();
    Code:
       0: aload_0
       1: getfield      #22                 // Field cells:[Lorg/apache/hadoop/hbase/Cell;
       4: ifnull        27
       7: aload_0
       8: getfield      #8                  // Field cellScannerIndex:I
      11: iconst_m1
      12: if_icmpeq     27
      15: aload_0
      16: getfield      #8                  // Field cellScannerIndex:I
      19: aload_0
      20: getfield      #22                 // Field cells:[Lorg/apache/hadoop/hbase/Cell;
      23: arraylength
      24: if_icmplt     29
      27: aconst_null
      28: areturn
      29: aload_0
      30: getfield      #22                 // Field cells:[Lorg/apache/hadoop/hbase/Cell;
      33: aload_0
      34: getfield      #8                  // Field cellScannerIndex:I
      37: aaload
      38: areturn

  public boolean advance();
    Code:
       0: aload_0
       1: getfield      #22                 // Field cells:[Lorg/apache/hadoop/hbase/Cell;
       4: ifnonnull     9
       7: iconst_0
       8: ireturn
       9: aload_0
      10: dup
      11: getfield      #8                  // Field cellScannerIndex:I
      14: iconst_1
      15: iadd
      16: putfield      #8                  // Field cellScannerIndex:I
      19: aload_0
      20: getfield      #8                  // Field cellScannerIndex:I
      23: aload_0
      24: getfield      #22                 // Field cells:[Lorg/apache/hadoop/hbase/Cell;
      27: arraylength
      28: if_icmpge     33
      31: iconst_1
      32: ireturn
      33: aload_0
      34: getfield      #8                  // Field cellScannerIndex:I
      37: aload_0
      38: getfield      #22                 // Field cells:[Lorg/apache/hadoop/hbase/Cell;
      41: arraylength
      42: if_icmpne     47
      45: iconst_0
      46: ireturn
      47: new           #119                // class java/util/NoSuchElementException
      50: dup
      51: ldc           #120                // String Cannot advance beyond the last cell
      53: invokespecial #121                // Method java/util/NoSuchElementException."<init>":(Ljava/lang/String;)V
      56: athrow

  public java.lang.Boolean getExists();
    Code:
       0: aload_0
       1: getfield      #23                 // Field exists:Ljava/lang/Boolean;
       4: areturn

  public void setExists(java.lang.Boolean);
    Code:
       0: aload_0
       1: invokespecial #118                // Method checkReadonly:()V
       4: aload_0
       5: aload_1
       6: putfield      #23                 // Field exists:Ljava/lang/Boolean;
       9: return

  public boolean isStale();
    Code:
       0: aload_0
       1: getfield      #3                  // Field stale:Z
       4: ireturn

  public boolean mayHaveMoreCellsInRow();
    Code:
       0: aload_0
       1: getfield      #4                  // Field mayHaveMoreCellsInRow:Z
       4: ireturn

  public void setStatistics(org.apache.hadoop.hbase.client.RegionLoadStats);
    Code:
       0: aload_0
       1: aload_1
       2: putfield      #122                // Field stats:Lorg/apache/hadoop/hbase/client/RegionLoadStats;
       5: return

  public org.apache.hadoop.hbase.client.RegionLoadStats getStats();
    Code:
       0: aload_0
       1: getfield      #122                // Field stats:Lorg/apache/hadoop/hbase/client/RegionLoadStats;
       4: areturn

  public boolean isCursor();
    Code:
       0: aload_0
       1: getfield      #9                  // Field cursor:Lorg/apache/hadoop/hbase/client/Cursor;
       4: ifnull        11
       7: iconst_1
       8: goto          12
      11: iconst_0
      12: ireturn

  public org.apache.hadoop.hbase.client.Cursor getCursor();
    Code:
       0: aload_0
       1: getfield      #9                  // Field cursor:Lorg/apache/hadoop/hbase/client/Cursor;
       4: areturn

  static {};
    Code:
       0: new           #126                // class java/lang/ThreadLocal
       3: dup
       4: invokespecial #127                // Method java/lang/ThreadLocal."<init>":()V
       7: putstatic     #42                 // Field localBuffer:Ljava/lang/ThreadLocal;
      10: new           #7                  // class org/apache/hadoop/hbase/client/Result
      13: dup
      14: iconst_1
      15: invokespecial #1                  // Method "<init>":(Z)V
      18: putstatic     #128                // Field EMPTY_RESULT:Lorg/apache/hadoop/hbase/client/Result;
      21: return
}
