Compiled from "ResultScanner.java"
public interface org.apache.hadoop.hbase.client.ResultScanner extends java.io.Closeable, java.lang.Iterable<org.apache.hadoop.hbase.client.Result> {
  public java.util.Iterator<org.apache.hadoop.hbase.client.Result> iterator();
    Code:
       0: new           #1                  // class org/apache/hadoop/hbase/client/ResultScanner$1
       3: dup
       4: aload_0
       5: invokespecial #2                  // Method org/apache/hadoop/hbase/client/ResultScanner$1."<init>":(Lorg/apache/hadoop/hbase/client/ResultScanner;)V
       8: areturn

  public abstract org.apache.hadoop.hbase.client.Result next() throws java.io.IOException;

  public org.apache.hadoop.hbase.client.Result[] next(int) throws java.io.IOException;
    Code:
       0: new           #3                  // class java/util/ArrayList
       3: dup
       4: iload_1
       5: invokespecial #4                  // Method java/util/ArrayList."<init>":(I)V
       8: astore_2
       9: iconst_0
      10: istore_3
      11: iload_3
      12: iload_1
      13: if_icmpge     44
      16: aload_0
      17: invokeinterface #5,  1            // InterfaceMethod next:()Lorg/apache/hadoop/hbase/client/Result;
      22: astore        4
      24: aload         4
      26: ifnull        44
      29: aload_2
      30: aload         4
      32: invokeinterface #6,  2            // InterfaceMethod java/util/List.add:(Ljava/lang/Object;)Z
      37: pop
      38: iinc          3, 1
      41: goto          11
      44: aload_2
      45: iconst_0
      46: anewarray     #7                  // class org/apache/hadoop/hbase/client/Result
      49: invokeinterface #8,  2            // InterfaceMethod java/util/List.toArray:([Ljava/lang/Object;)[Ljava/lang/Object;
      54: checkcast     #9                  // class "[Lorg/apache/hadoop/hbase/client/Result;"
      57: areturn

  public abstract void close();

  public abstract boolean renewLease();

  public abstract org.apache.hadoop.hbase.client.metrics.ScanMetrics getScanMetrics();
}
