Compiled from "RetryCounter.java"
public class org.apache.hadoop.hbase.util.RetryCounter$ExponentialBackoffPolicyWithLimit extends org.apache.hadoop.hbase.util.RetryCounter$ExponentialBackoffPolicy {
  public org.apache.hadoop.hbase.util.RetryCounter$ExponentialBackoffPolicyWithLimit();
    Code:
       0: aload_0
       1: invokespecial #1                  // Method org/apache/hadoop/hbase/util/RetryCounter$ExponentialBackoffPolicy."<init>":()V
       4: return

  public long getBackoffTime(org.apache.hadoop.hbase.util.RetryCounter$RetryConfig, int);
    Code:
       0: aload_0
       1: aload_1
       2: iload_2
       3: invokespecial #2                  // Method org/apache/hadoop/hbase/util/RetryCounter$ExponentialBackoffPolicy.getBackoffTime:(Lorg/apache/hadoop/hbase/util/RetryCounter$RetryConfig;I)J
       6: lstore_3
       7: aload_1
       8: invokevirtual #3                  // Method org/apache/hadoop/hbase/util/RetryCounter$RetryConfig.getMaxSleepTime:()J
      11: lconst_0
      12: lcmp
      13: ifle          27
      16: lload_3
      17: aload_1
      18: invokevirtual #3                  // Method org/apache/hadoop/hbase/util/RetryCounter$RetryConfig.getMaxSleepTime:()J
      21: invokestatic  #4                  // Method java/lang/Math.min:(JJ)J
      24: goto          28
      27: lload_3
      28: lreturn
}
