Compiled from "ReusableStreamGzipCodec.java"
public class org.apache.hadoop.hbase.io.compress.ReusableStreamGzipCodec extends org.apache.hadoop.io.compress.GzipCodec {
  public org.apache.hadoop.hbase.io.compress.ReusableStreamGzipCodec();
    Code:
       0: aload_0
       1: invokespecial #2                  // Method org/apache/hadoop/io/compress/GzipCodec."<init>":()V
       4: return

  public org.apache.hadoop.io.compress.CompressionOutputStream createOutputStream(java.io.OutputStream) throws java.io.IOException;
    Code:
       0: aload_0
       1: invokevirtual #3                  // Method getConf:()Lorg/apache/hadoop/conf/Configuration;
       4: invokestatic  #4                  // Method org/apache/hadoop/io/compress/zlib/ZlibFactory.isNativeZlibLoaded:(Lorg/apache/hadoop/conf/Configuration;)Z
       7: ifeq          16
      10: aload_0
      11: aload_1
      12: invokespecial #5                  // Method org/apache/hadoop/io/compress/GzipCodec.createOutputStream:(Ljava/io/OutputStream;)Lorg/apache/hadoop/io/compress/CompressionOutputStream;
      15: areturn
      16: new           #6                  // class org/apache/hadoop/hbase/io/compress/ReusableStreamGzipCodec$ReusableGzipOutputStream
      19: dup
      20: aload_1
      21: invokespecial #7                  // Method org/apache/hadoop/hbase/io/compress/ReusableStreamGzipCodec$ReusableGzipOutputStream."<init>":(Ljava/io/OutputStream;)V
      24: areturn

  static org.slf4j.Logger access$000();
    Code:
       0: getstatic     #1                  // Field LOG:Lorg/slf4j/Logger;
       3: areturn

  static {};
    Code:
       0: ldc           #8                  // class org/apache/hadoop/hbase/io/compress/Compression
       2: invokestatic  #9                  // Method org/slf4j/LoggerFactory.getLogger:(Ljava/lang/Class;)Lorg/slf4j/Logger;
       5: putstatic     #1                  // Field LOG:Lorg/slf4j/Logger;
       8: return
}
