Compiled from "ReversedKeyValueHeap.java"
public class org.apache.hadoop.hbase.regionserver.ReversedKeyValueHeap extends org.apache.hadoop.hbase.regionserver.KeyValueHeap {
  public org.apache.hadoop.hbase.regionserver.ReversedKeyValueHeap(java.util.List<? extends org.apache.hadoop.hbase.regionserver.KeyValueScanner>, org.apache.hadoop.hbase.CellComparator) throws java.io.IOException;
    Code:
       0: aload_0
       1: aload_1
       2: new           #1                  // class org/apache/hadoop/hbase/regionserver/ReversedKeyValueHeap$ReversedKVScannerComparator
       5: dup
       6: aload_2
       7: invokespecial #2                  // Method org/apache/hadoop/hbase/regionserver/ReversedKeyValueHeap$ReversedKVScannerComparator."<init>":(Lorg/apache/hadoop/hbase/CellComparator;)V
      10: invokespecial #3                  // Method org/apache/hadoop/hbase/regionserver/KeyValueHeap."<init>":(Ljava/util/List;Lorg/apache/hadoop/hbase/regionserver/KeyValueHeap$KVScannerComparator;)V
      13: return

  public boolean seek(org.apache.hadoop.hbase.Cell) throws java.io.IOException;
    Code:
       0: new           #4                  // class java/lang/IllegalStateException
       3: dup
       4: ldc           #5                  // String seek cannot be called on ReversedKeyValueHeap
       6: invokespecial #6                  // Method java/lang/IllegalStateException."<init>":(Ljava/lang/String;)V
       9: athrow

  public boolean reseek(org.apache.hadoop.hbase.Cell) throws java.io.IOException;
    Code:
       0: new           #4                  // class java/lang/IllegalStateException
       3: dup
       4: ldc           #7                  // String reseek cannot be called on ReversedKeyValueHeap
       6: invokespecial #6                  // Method java/lang/IllegalStateException."<init>":(Ljava/lang/String;)V
       9: athrow

  public boolean requestSeek(org.apache.hadoop.hbase.Cell, boolean, boolean) throws java.io.IOException;
    Code:
       0: new           #4                  // class java/lang/IllegalStateException
       3: dup
       4: ldc           #8                  // String requestSeek cannot be called on ReversedKeyValueHeap
       6: invokespecial #6                  // Method java/lang/IllegalStateException."<init>":(Ljava/lang/String;)V
       9: athrow

  public boolean seekToPreviousRow(org.apache.hadoop.hbase.Cell) throws java.io.IOException;
    Code:
       0: aload_0
       1: getfield      #9                  // Field current:Lorg/apache/hadoop/hbase/regionserver/KeyValueScanner;
       4: ifnonnull     9
       7: iconst_0
       8: ireturn
       9: aload_0
      10: getfield      #10                 // Field heap:Ljava/util/PriorityQueue;
      13: aload_0
      14: getfield      #9                  // Field current:Lorg/apache/hadoop/hbase/regionserver/KeyValueScanner;
      17: invokevirtual #11                 // Method java/util/PriorityQueue.add:(Ljava/lang/Object;)Z
      20: pop
      21: aload_0
      22: aconst_null
      23: putfield      #9                  // Field current:Lorg/apache/hadoop/hbase/regionserver/KeyValueScanner;
      26: aload_0
      27: getfield      #10                 // Field heap:Ljava/util/PriorityQueue;
      30: invokevirtual #12                 // Method java/util/PriorityQueue.poll:()Ljava/lang/Object;
      33: checkcast     #13                 // class org/apache/hadoop/hbase/regionserver/KeyValueScanner
      36: dup
      37: astore_2
      38: ifnull        131
      41: aload_2
      42: invokeinterface #14,  1           // InterfaceMethod org/apache/hadoop/hbase/regionserver/KeyValueScanner.peek:()Lorg/apache/hadoop/hbase/Cell;
      47: astore_3
      48: aload_0
      49: getfield      #15                 // Field comparator:Lorg/apache/hadoop/hbase/regionserver/KeyValueHeap$KVScannerComparator;
      52: invokevirtual #16                 // Method org/apache/hadoop/hbase/regionserver/KeyValueHeap$KVScannerComparator.getComparator:()Lorg/apache/hadoop/hbase/CellComparator;
      55: aload_3
      56: aload_1
      57: invokeinterface #17,  3           // InterfaceMethod org/apache/hadoop/hbase/CellComparator.compareRows:(Lorg/apache/hadoop/hbase/Cell;Lorg/apache/hadoop/hbase/Cell;)I
      62: ifge          95
      65: aload_0
      66: getfield      #10                 // Field heap:Ljava/util/PriorityQueue;
      69: aload_2
      70: invokevirtual #11                 // Method java/util/PriorityQueue.add:(Ljava/lang/Object;)Z
      73: pop
      74: aload_0
      75: aload_0
      76: invokevirtual #18                 // Method pollRealKV:()Lorg/apache/hadoop/hbase/regionserver/KeyValueScanner;
      79: putfield      #9                  // Field current:Lorg/apache/hadoop/hbase/regionserver/KeyValueScanner;
      82: aload_0
      83: getfield      #9                  // Field current:Lorg/apache/hadoop/hbase/regionserver/KeyValueScanner;
      86: ifnull        93
      89: iconst_1
      90: goto          94
      93: iconst_0
      94: ireturn
      95: aload_2
      96: aload_1
      97: invokeinterface #19,  2           // InterfaceMethod org/apache/hadoop/hbase/regionserver/KeyValueScanner.seekToPreviousRow:(Lorg/apache/hadoop/hbase/Cell;)Z
     102: ifne          119
     105: aload_0
     106: getfield      #20                 // Field scannersForDelayedClose:Ljava/util/List;
     109: aload_2
     110: invokeinterface #21,  2           // InterfaceMethod java/util/List.add:(Ljava/lang/Object;)Z
     115: pop
     116: goto          128
     119: aload_0
     120: getfield      #10                 // Field heap:Ljava/util/PriorityQueue;
     123: aload_2
     124: invokevirtual #11                 // Method java/util/PriorityQueue.add:(Ljava/lang/Object;)Z
     127: pop
     128: goto          26
     131: iconst_0
     132: ireturn

  public boolean backwardSeek(org.apache.hadoop.hbase.Cell) throws java.io.IOException;
    Code:
       0: aload_0
       1: getfield      #9                  // Field current:Lorg/apache/hadoop/hbase/regionserver/KeyValueScanner;
       4: ifnonnull     9
       7: iconst_0
       8: ireturn
       9: aload_0
      10: getfield      #10                 // Field heap:Ljava/util/PriorityQueue;
      13: aload_0
      14: getfield      #9                  // Field current:Lorg/apache/hadoop/hbase/regionserver/KeyValueScanner;
      17: invokevirtual #11                 // Method java/util/PriorityQueue.add:(Ljava/lang/Object;)Z
      20: pop
      21: aload_0
      22: aconst_null
      23: putfield      #9                  // Field current:Lorg/apache/hadoop/hbase/regionserver/KeyValueScanner;
      26: aload_0
      27: getfield      #10                 // Field heap:Ljava/util/PriorityQueue;
      30: invokevirtual #12                 // Method java/util/PriorityQueue.poll:()Ljava/lang/Object;
      33: checkcast     #13                 // class org/apache/hadoop/hbase/regionserver/KeyValueScanner
      36: dup
      37: astore_2
      38: ifnull        156
      41: aload_2
      42: invokeinterface #14,  1           // InterfaceMethod org/apache/hadoop/hbase/regionserver/KeyValueScanner.peek:()Lorg/apache/hadoop/hbase/Cell;
      47: astore_3
      48: aload_1
      49: aload_3
      50: invokestatic  #22                 // Method org/apache/hadoop/hbase/CellUtil.matchingRows:(Lorg/apache/hadoop/hbase/Cell;Lorg/apache/hadoop/hbase/Cell;)Z
      53: ifeq          73
      56: aload_0
      57: getfield      #15                 // Field comparator:Lorg/apache/hadoop/hbase/regionserver/KeyValueHeap$KVScannerComparator;
      60: invokevirtual #16                 // Method org/apache/hadoop/hbase/regionserver/KeyValueHeap$KVScannerComparator.getComparator:()Lorg/apache/hadoop/hbase/CellComparator;
      63: aload_1
      64: aload_3
      65: invokeinterface #23,  3           // InterfaceMethod org/apache/hadoop/hbase/CellComparator.compare:(Lorg/apache/hadoop/hbase/Cell;Lorg/apache/hadoop/hbase/Cell;)I
      70: ifle          90
      73: aload_0
      74: getfield      #15                 // Field comparator:Lorg/apache/hadoop/hbase/regionserver/KeyValueHeap$KVScannerComparator;
      77: invokevirtual #16                 // Method org/apache/hadoop/hbase/regionserver/KeyValueHeap$KVScannerComparator.getComparator:()Lorg/apache/hadoop/hbase/CellComparator;
      80: aload_1
      81: aload_3
      82: invokeinterface #17,  3           // InterfaceMethod org/apache/hadoop/hbase/CellComparator.compareRows:(Lorg/apache/hadoop/hbase/Cell;Lorg/apache/hadoop/hbase/Cell;)I
      87: ifle          120
      90: aload_0
      91: getfield      #10                 // Field heap:Ljava/util/PriorityQueue;
      94: aload_2
      95: invokevirtual #11                 // Method java/util/PriorityQueue.add:(Ljava/lang/Object;)Z
      98: pop
      99: aload_0
     100: aload_0
     101: invokevirtual #18                 // Method pollRealKV:()Lorg/apache/hadoop/hbase/regionserver/KeyValueScanner;
     104: putfield      #9                  // Field current:Lorg/apache/hadoop/hbase/regionserver/KeyValueScanner;
     107: aload_0
     108: getfield      #9                  // Field current:Lorg/apache/hadoop/hbase/regionserver/KeyValueScanner;
     111: ifnull        118
     114: iconst_1
     115: goto          119
     118: iconst_0
     119: ireturn
     120: aload_2
     121: aload_1
     122: invokeinterface #24,  2           // InterfaceMethod org/apache/hadoop/hbase/regionserver/KeyValueScanner.backwardSeek:(Lorg/apache/hadoop/hbase/Cell;)Z
     127: ifne          144
     130: aload_0
     131: getfield      #20                 // Field scannersForDelayedClose:Ljava/util/List;
     134: aload_2
     135: invokeinterface #21,  2           // InterfaceMethod java/util/List.add:(Ljava/lang/Object;)Z
     140: pop
     141: goto          153
     144: aload_0
     145: getfield      #10                 // Field heap:Ljava/util/PriorityQueue;
     148: aload_2
     149: invokevirtual #11                 // Method java/util/PriorityQueue.add:(Ljava/lang/Object;)Z
     152: pop
     153: goto          26
     156: iconst_0
     157: ireturn

  public org.apache.hadoop.hbase.Cell next() throws java.io.IOException;
    Code:
       0: aload_0
       1: getfield      #9                  // Field current:Lorg/apache/hadoop/hbase/regionserver/KeyValueScanner;
       4: ifnonnull     9
       7: aconst_null
       8: areturn
       9: aload_0
      10: getfield      #9                  // Field current:Lorg/apache/hadoop/hbase/regionserver/KeyValueScanner;
      13: invokeinterface #25,  1           // InterfaceMethod org/apache/hadoop/hbase/regionserver/KeyValueScanner.next:()Lorg/apache/hadoop/hbase/Cell;
      18: astore_1
      19: aload_0
      20: getfield      #9                  // Field current:Lorg/apache/hadoop/hbase/regionserver/KeyValueScanner;
      23: invokeinterface #14,  1           // InterfaceMethod org/apache/hadoop/hbase/regionserver/KeyValueScanner.peek:()Lorg/apache/hadoop/hbase/Cell;
      28: astore_2
      29: aload_2
      30: ifnull        50
      33: aload_0
      34: getfield      #15                 // Field comparator:Lorg/apache/hadoop/hbase/regionserver/KeyValueHeap$KVScannerComparator;
      37: getfield      #26                 // Field org/apache/hadoop/hbase/regionserver/KeyValueHeap$KVScannerComparator.kvComparator:Lorg/apache/hadoop/hbase/CellComparator;
      40: aload_2
      41: aload_1
      42: invokeinterface #17,  3           // InterfaceMethod org/apache/hadoop/hbase/CellComparator.compareRows:(Lorg/apache/hadoop/hbase/Cell;Lorg/apache/hadoop/hbase/Cell;)I
      47: ifle          108
      50: aload_0
      51: getfield      #9                  // Field current:Lorg/apache/hadoop/hbase/regionserver/KeyValueScanner;
      54: aload_1
      55: invokeinterface #19,  2           // InterfaceMethod org/apache/hadoop/hbase/regionserver/KeyValueScanner.seekToPreviousRow:(Lorg/apache/hadoop/hbase/Cell;)Z
      60: ifeq          78
      63: aload_0
      64: getfield      #10                 // Field heap:Ljava/util/PriorityQueue;
      67: aload_0
      68: getfield      #9                  // Field current:Lorg/apache/hadoop/hbase/regionserver/KeyValueScanner;
      71: invokevirtual #11                 // Method java/util/PriorityQueue.add:(Ljava/lang/Object;)Z
      74: pop
      75: goto          92
      78: aload_0
      79: getfield      #20                 // Field scannersForDelayedClose:Ljava/util/List;
      82: aload_0
      83: getfield      #9                  // Field current:Lorg/apache/hadoop/hbase/regionserver/KeyValueScanner;
      86: invokeinterface #21,  2           // InterfaceMethod java/util/List.add:(Ljava/lang/Object;)Z
      91: pop
      92: aload_0
      93: aconst_null
      94: putfield      #9                  // Field current:Lorg/apache/hadoop/hbase/regionserver/KeyValueScanner;
      97: aload_0
      98: aload_0
      99: invokevirtual #18                 // Method pollRealKV:()Lorg/apache/hadoop/hbase/regionserver/KeyValueScanner;
     102: putfield      #9                  // Field current:Lorg/apache/hadoop/hbase/regionserver/KeyValueScanner;
     105: goto          163
     108: aload_0
     109: getfield      #10                 // Field heap:Ljava/util/PriorityQueue;
     112: invokevirtual #27                 // Method java/util/PriorityQueue.peek:()Ljava/lang/Object;
     115: checkcast     #13                 // class org/apache/hadoop/hbase/regionserver/KeyValueScanner
     118: astore_3
     119: aload_3
     120: ifnull        163
     123: aload_0
     124: getfield      #15                 // Field comparator:Lorg/apache/hadoop/hbase/regionserver/KeyValueHeap$KVScannerComparator;
     127: aload_0
     128: getfield      #9                  // Field current:Lorg/apache/hadoop/hbase/regionserver/KeyValueScanner;
     131: aload_3
     132: invokevirtual #28                 // Method org/apache/hadoop/hbase/regionserver/KeyValueHeap$KVScannerComparator.compare:(Lorg/apache/hadoop/hbase/regionserver/KeyValueScanner;Lorg/apache/hadoop/hbase/regionserver/KeyValueScanner;)I
     135: ifle          163
     138: aload_0
     139: getfield      #10                 // Field heap:Ljava/util/PriorityQueue;
     142: aload_0
     143: getfield      #9                  // Field current:Lorg/apache/hadoop/hbase/regionserver/KeyValueScanner;
     146: invokevirtual #11                 // Method java/util/PriorityQueue.add:(Ljava/lang/Object;)Z
     149: pop
     150: aload_0
     151: aconst_null
     152: putfield      #9                  // Field current:Lorg/apache/hadoop/hbase/regionserver/KeyValueScanner;
     155: aload_0
     156: aload_0
     157: invokevirtual #18                 // Method pollRealKV:()Lorg/apache/hadoop/hbase/regionserver/KeyValueScanner;
     160: putfield      #9                  // Field current:Lorg/apache/hadoop/hbase/regionserver/KeyValueScanner;
     163: aload_1
     164: areturn

  public boolean seekToLastRow() throws java.io.IOException;
    Code:
       0: new           #29                 // class org/apache/commons/lang3/NotImplementedException
       3: dup
       4: ldc           #31                 // String Not implemented
       6: invokespecial #32                 // Method org/apache/commons/lang3/NotImplementedException."<init>":(Ljava/lang/String;)V
       9: athrow
}
