Compiled from "ReversedMobStoreScanner.java"
public class org.apache.hadoop.hbase.regionserver.ReversedMobStoreScanner extends org.apache.hadoop.hbase.regionserver.ReversedStoreScanner {
  protected final org.apache.hadoop.hbase.regionserver.HMobStore mobStore;

  org.apache.hadoop.hbase.regionserver.ReversedMobStoreScanner(org.apache.hadoop.hbase.regionserver.HStore, org.apache.hadoop.hbase.regionserver.ScanInfo, org.apache.hadoop.hbase.client.Scan, java.util.NavigableSet<byte[]>, long) throws java.io.IOException;
    Code:
       0: aload_0
       1: aload_1
       2: aload_2
       3: aload_3
       4: aload         4
       6: lload         5
       8: invokespecial #1                  // Method org/apache/hadoop/hbase/regionserver/ReversedStoreScanner."<init>":(Lorg/apache/hadoop/hbase/regionserver/HStore;Lorg/apache/hadoop/hbase/regionserver/ScanInfo;Lorg/apache/hadoop/hbase/client/Scan;Ljava/util/NavigableSet;J)V
      11: aload_0
      12: iconst_0
      13: putfield      #2                  // Field cacheMobBlocks:Z
      16: aload_0
      17: iconst_0
      18: putfield      #3                  // Field rawMobScan:Z
      21: aload_0
      22: iconst_0
      23: putfield      #4                  // Field readEmptyValueOnMobCellMiss:Z
      26: aload_0
      27: aload_3
      28: invokestatic  #5                  // Method org/apache/hadoop/hbase/mob/MobUtils.isCacheMobBlocks:(Lorg/apache/hadoop/hbase/client/Scan;)Z
      31: putfield      #2                  // Field cacheMobBlocks:Z
      34: aload_0
      35: aload_3
      36: invokestatic  #6                  // Method org/apache/hadoop/hbase/mob/MobUtils.isRawMobScan:(Lorg/apache/hadoop/hbase/client/Scan;)Z
      39: putfield      #3                  // Field rawMobScan:Z
      42: aload_0
      43: aload_3
      44: invokestatic  #7                  // Method org/apache/hadoop/hbase/mob/MobUtils.isReadEmptyValueOnMobCellMiss:(Lorg/apache/hadoop/hbase/client/Scan;)Z
      47: putfield      #4                  // Field readEmptyValueOnMobCellMiss:Z
      50: aload_1
      51: instanceof    #8                  // class org/apache/hadoop/hbase/regionserver/HMobStore
      54: ifne          89
      57: new           #9                  // class java/lang/IllegalArgumentException
      60: dup
      61: new           #10                 // class java/lang/StringBuilder
      64: dup
      65: invokespecial #11                 // Method java/lang/StringBuilder."<init>":()V
      68: ldc           #12                 // String The store
      70: invokevirtual #13                 // Method java/lang/StringBuilder.append:(Ljava/lang/String;)Ljava/lang/StringBuilder;
      73: aload_1
      74: invokevirtual #14                 // Method java/lang/StringBuilder.append:(Ljava/lang/Object;)Ljava/lang/StringBuilder;
      77: ldc           #15                 // String  is not a HMobStore
      79: invokevirtual #13                 // Method java/lang/StringBuilder.append:(Ljava/lang/String;)Ljava/lang/StringBuilder;
      82: invokevirtual #16                 // Method java/lang/StringBuilder.toString:()Ljava/lang/String;
      85: invokespecial #17                 // Method java/lang/IllegalArgumentException."<init>":(Ljava/lang/String;)V
      88: athrow
      89: aload_0
      90: aload_1
      91: checkcast     #8                  // class org/apache/hadoop/hbase/regionserver/HMobStore
      94: putfield      #18                 // Field mobStore:Lorg/apache/hadoop/hbase/regionserver/HMobStore;
      97: return

  public boolean next(java.util.List<org.apache.hadoop.hbase.Cell>, org.apache.hadoop.hbase.regionserver.ScannerContext) throws java.io.IOException;
    Code:
       0: aload_0
       1: aload_1
       2: aload_2
       3: invokespecial #19                 // Method org/apache/hadoop/hbase/regionserver/ReversedStoreScanner.next:(Ljava/util/List;Lorg/apache/hadoop/hbase/regionserver/ScannerContext;)Z
       6: istore_3
       7: aload_0
       8: getfield      #3                  // Field rawMobScan:Z
      11: ifne          143
      14: aload_1
      15: invokeinterface #20,  1           // InterfaceMethod java/util/List.isEmpty:()Z
      20: ifeq          25
      23: iload_3
      24: ireturn
      25: lconst_0
      26: lstore        4
      28: lconst_0
      29: lstore        6
      31: iconst_0
      32: istore        8
      34: iload         8
      36: aload_1
      37: invokeinterface #21,  1           // InterfaceMethod java/util/List.size:()I
      42: if_icmpge     125
      45: aload_1
      46: iload         8
      48: invokeinterface #22,  2           // InterfaceMethod java/util/List.get:(I)Ljava/lang/Object;
      53: checkcast     #23                 // class org/apache/hadoop/hbase/Cell
      56: astore        9
      58: aload         9
      60: invokestatic  #24                 // Method org/apache/hadoop/hbase/mob/MobUtils.isMobReferenceCell:(Lorg/apache/hadoop/hbase/Cell;)Z
      63: ifeq          119
      66: aload_0
      67: getfield      #18                 // Field mobStore:Lorg/apache/hadoop/hbase/regionserver/HMobStore;
      70: aload         9
      72: aload_0
      73: getfield      #2                  // Field cacheMobBlocks:Z
      76: aload_0
      77: getfield      #25                 // Field readPt:J
      80: aload_0
      81: getfield      #4                  // Field readEmptyValueOnMobCellMiss:Z
      84: invokevirtual #26                 // Method org/apache/hadoop/hbase/regionserver/HMobStore.resolve:(Lorg/apache/hadoop/hbase/Cell;ZJZ)Lorg/apache/hadoop/hbase/Cell;
      87: astore        10
      89: lload         4
      91: lconst_1
      92: ladd
      93: lstore        4
      95: lload         6
      97: aload         10
      99: invokeinterface #27,  1           // InterfaceMethod org/apache/hadoop/hbase/Cell.getValueLength:()I
     104: i2l
     105: ladd
     106: lstore        6
     108: aload_1
     109: iload         8
     111: aload         10
     113: invokeinterface #28,  3           // InterfaceMethod java/util/List.set:(ILjava/lang/Object;)Ljava/lang/Object;
     118: pop
     119: iinc          8, 1
     122: goto          34
     125: aload_0
     126: getfield      #18                 // Field mobStore:Lorg/apache/hadoop/hbase/regionserver/HMobStore;
     129: lload         4
     131: invokevirtual #29                 // Method org/apache/hadoop/hbase/regionserver/HMobStore.updateMobScanCellsCount:(J)V
     134: aload_0
     135: getfield      #18                 // Field mobStore:Lorg/apache/hadoop/hbase/regionserver/HMobStore;
     138: lload         6
     140: invokevirtual #30                 // Method org/apache/hadoop/hbase/regionserver/HMobStore.updateMobScanCellsSize:(J)V
     143: iload_3
     144: ireturn
}
