Compiled from "RootProcedureState.java"
class org.apache.hadoop.hbase.procedure2.RootProcedureState<TEnvironment> {
  static final boolean $assertionsDisabled;

  org.apache.hadoop.hbase.procedure2.RootProcedureState();
    Code:
       0: aload_0
       1: invokespecial #1                  // Method java/lang/Object."<init>":()V
       4: aload_0
       5: aconst_null
       6: putfield      #2                  // Field subprocs:Ljava/util/Set;
       9: aload_0
      10: aconst_null
      11: putfield      #3                  // Field subprocStack:Ljava/util/ArrayList;
      14: aload_0
      15: getstatic     #4                  // Field org/apache/hadoop/hbase/procedure2/RootProcedureState$State.RUNNING:Lorg/apache/hadoop/hbase/procedure2/RootProcedureState$State;
      18: putfield      #5                  // Field state:Lorg/apache/hadoop/hbase/procedure2/RootProcedureState$State;
      21: aload_0
      22: iconst_0
      23: putfield      #6                  // Field running:I
      26: return

  public synchronized boolean isFailed();
    Code:
       0: getstatic     #7                  // Field org/apache/hadoop/hbase/procedure2/RootProcedureState$1.$SwitchMap$org$apache$hadoop$hbase$procedure2$RootProcedureState$State:[I
       3: aload_0
       4: getfield      #5                  // Field state:Lorg/apache/hadoop/hbase/procedure2/RootProcedureState$State;
       7: invokevirtual #8                  // Method org/apache/hadoop/hbase/procedure2/RootProcedureState$State.ordinal:()I
      10: iaload
      11: lookupswitch  { // 2
                     1: 36
                     2: 36
               default: 38
          }
      36: iconst_1
      37: ireturn
      38: iconst_0
      39: ireturn

  public synchronized boolean isRollingback();
    Code:
       0: aload_0
       1: getfield      #5                  // Field state:Lorg/apache/hadoop/hbase/procedure2/RootProcedureState$State;
       4: getstatic     #9                  // Field org/apache/hadoop/hbase/procedure2/RootProcedureState$State.ROLLINGBACK:Lorg/apache/hadoop/hbase/procedure2/RootProcedureState$State;
       7: if_acmpne     14
      10: iconst_1
      11: goto          15
      14: iconst_0
      15: ireturn

  protected synchronized boolean setRollback();
    Code:
       0: aload_0
       1: getfield      #6                  // Field running:I
       4: ifne          26
       7: aload_0
       8: getfield      #5                  // Field state:Lorg/apache/hadoop/hbase/procedure2/RootProcedureState$State;
      11: getstatic     #10                 // Field org/apache/hadoop/hbase/procedure2/RootProcedureState$State.FAILED:Lorg/apache/hadoop/hbase/procedure2/RootProcedureState$State;
      14: if_acmpne     26
      17: aload_0
      18: getstatic     #9                  // Field org/apache/hadoop/hbase/procedure2/RootProcedureState$State.ROLLINGBACK:Lorg/apache/hadoop/hbase/procedure2/RootProcedureState$State;
      21: putfield      #5                  // Field state:Lorg/apache/hadoop/hbase/procedure2/RootProcedureState$State;
      24: iconst_1
      25: ireturn
      26: iconst_0
      27: ireturn

  protected synchronized void unsetRollback();
    Code:
       0: getstatic     #11                 // Field $assertionsDisabled:Z
       3: ifne          24
       6: aload_0
       7: getfield      #5                  // Field state:Lorg/apache/hadoop/hbase/procedure2/RootProcedureState$State;
      10: getstatic     #9                  // Field org/apache/hadoop/hbase/procedure2/RootProcedureState$State.ROLLINGBACK:Lorg/apache/hadoop/hbase/procedure2/RootProcedureState$State;
      13: if_acmpeq     24
      16: new           #12                 // class java/lang/AssertionError
      19: dup
      20: invokespecial #13                 // Method java/lang/AssertionError."<init>":()V
      23: athrow
      24: aload_0
      25: getstatic     #10                 // Field org/apache/hadoop/hbase/procedure2/RootProcedureState$State.FAILED:Lorg/apache/hadoop/hbase/procedure2/RootProcedureState$State;
      28: putfield      #5                  // Field state:Lorg/apache/hadoop/hbase/procedure2/RootProcedureState$State;
      31: return

  protected synchronized long[] getSubprocedureIds();
    Code:
       0: aload_0
       1: getfield      #2                  // Field subprocs:Ljava/util/Set;
       4: ifnonnull     9
       7: aconst_null
       8: areturn
       9: aload_0
      10: getfield      #2                  // Field subprocs:Ljava/util/Set;
      13: invokeinterface #14,  1           // InterfaceMethod java/util/Set.stream:()Ljava/util/stream/Stream;
      18: invokedynamic #15,  0             // InvokeDynamic #0:applyAsLong:()Ljava/util/function/ToLongFunction;
      23: invokeinterface #16,  2           // InterfaceMethod java/util/stream/Stream.mapToLong:(Ljava/util/function/ToLongFunction;)Ljava/util/stream/LongStream;
      28: invokeinterface #17,  1           // InterfaceMethod java/util/stream/LongStream.toArray:()[J
      33: areturn

  protected synchronized java.util.List<org.apache.hadoop.hbase.procedure2.Procedure<TEnvironment>> getSubproceduresStack();
    Code:
       0: aload_0
       1: getfield      #3                  // Field subprocStack:Ljava/util/ArrayList;
       4: areturn

  protected synchronized org.apache.hadoop.hbase.procedure2.RemoteProcedureException getException();
    Code:
       0: aload_0
       1: getfield      #3                  // Field subprocStack:Ljava/util/ArrayList;
       4: ifnull        49
       7: aload_0
       8: getfield      #3                  // Field subprocStack:Ljava/util/ArrayList;
      11: invokevirtual #18                 // Method java/util/ArrayList.iterator:()Ljava/util/Iterator;
      14: astore_1
      15: aload_1
      16: invokeinterface #19,  1           // InterfaceMethod java/util/Iterator.hasNext:()Z
      21: ifeq          49
      24: aload_1
      25: invokeinterface #20,  1           // InterfaceMethod java/util/Iterator.next:()Ljava/lang/Object;
      30: checkcast     #21                 // class org/apache/hadoop/hbase/procedure2/Procedure
      33: astore_2
      34: aload_2
      35: invokevirtual #22                 // Method org/apache/hadoop/hbase/procedure2/Procedure.hasException:()Z
      38: ifeq          46
      41: aload_2
      42: invokevirtual #23                 // Method org/apache/hadoop/hbase/procedure2/Procedure.getException:()Lorg/apache/hadoop/hbase/procedure2/RemoteProcedureException;
      45: areturn
      46: goto          15
      49: aconst_null
      50: areturn

  protected synchronized boolean acquire(org.apache.hadoop.hbase.procedure2.Procedure<TEnvironment>);
    Code:
       0: aload_0
       1: getfield      #5                  // Field state:Lorg/apache/hadoop/hbase/procedure2/RootProcedureState$State;
       4: getstatic     #4                  // Field org/apache/hadoop/hbase/procedure2/RootProcedureState$State.RUNNING:Lorg/apache/hadoop/hbase/procedure2/RootProcedureState$State;
       7: if_acmpeq     12
      10: iconst_0
      11: ireturn
      12: aload_0
      13: dup
      14: getfield      #6                  // Field running:I
      17: iconst_1
      18: iadd
      19: putfield      #6                  // Field running:I
      22: iconst_1
      23: ireturn

  protected synchronized void release(org.apache.hadoop.hbase.procedure2.Procedure<TEnvironment>);
    Code:
       0: aload_0
       1: dup
       2: getfield      #6                  // Field running:I
       5: iconst_1
       6: isub
       7: putfield      #6                  // Field running:I
      10: return

  protected synchronized void abort();
    Code:
       0: aload_0
       1: getfield      #5                  // Field state:Lorg/apache/hadoop/hbase/procedure2/RootProcedureState$State;
       4: getstatic     #4                  // Field org/apache/hadoop/hbase/procedure2/RootProcedureState$State.RUNNING:Lorg/apache/hadoop/hbase/procedure2/RootProcedureState$State;
       7: if_acmpne     17
      10: aload_0
      11: getstatic     #10                 // Field org/apache/hadoop/hbase/procedure2/RootProcedureState$State.FAILED:Lorg/apache/hadoop/hbase/procedure2/RootProcedureState$State;
      14: putfield      #5                  // Field state:Lorg/apache/hadoop/hbase/procedure2/RootProcedureState$State;
      17: return

  protected synchronized void addRollbackStep(org.apache.hadoop.hbase.procedure2.Procedure<TEnvironment>);
    Code:
       0: aload_1
       1: invokevirtual #24                 // Method org/apache/hadoop/hbase/procedure2/Procedure.isFailed:()Z
       4: ifeq          14
       7: aload_0
       8: getstatic     #10                 // Field org/apache/hadoop/hbase/procedure2/RootProcedureState$State.FAILED:Lorg/apache/hadoop/hbase/procedure2/RootProcedureState$State;
      11: putfield      #5                  // Field state:Lorg/apache/hadoop/hbase/procedure2/RootProcedureState$State;
      14: aload_0
      15: getfield      #3                  // Field subprocStack:Ljava/util/ArrayList;
      18: ifnonnull     32
      21: aload_0
      22: new           #25                 // class java/util/ArrayList
      25: dup
      26: invokespecial #26                 // Method java/util/ArrayList."<init>":()V
      29: putfield      #3                  // Field subprocStack:Ljava/util/ArrayList;
      32: aload_1
      33: aload_0
      34: getfield      #3                  // Field subprocStack:Ljava/util/ArrayList;
      37: invokevirtual #27                 // Method java/util/ArrayList.size:()I
      40: invokevirtual #28                 // Method org/apache/hadoop/hbase/procedure2/Procedure.addStackIndex:(I)V
      43: getstatic     #29                 // Field LOG:Lorg/slf4j/Logger;
      46: ldc           #30                 // String Add procedure {} as the {}th rollback step
      48: aload_1
      49: aload_0
      50: getfield      #3                  // Field subprocStack:Ljava/util/ArrayList;
      53: invokevirtual #27                 // Method java/util/ArrayList.size:()I
      56: invokestatic  #31                 // Method java/lang/Integer.valueOf:(I)Ljava/lang/Integer;
      59: invokeinterface #32,  4           // InterfaceMethod org/slf4j/Logger.debug:(Ljava/lang/String;Ljava/lang/Object;Ljava/lang/Object;)V
      64: aload_0
      65: getfield      #3                  // Field subprocStack:Ljava/util/ArrayList;
      68: aload_1
      69: invokevirtual #33                 // Method java/util/ArrayList.add:(Ljava/lang/Object;)Z
      72: pop
      73: return

  protected synchronized void addSubProcedure(org.apache.hadoop.hbase.procedure2.Procedure<TEnvironment>);
    Code:
       0: aload_1
       1: invokevirtual #34                 // Method org/apache/hadoop/hbase/procedure2/Procedure.hasParent:()Z
       4: ifne          8
       7: return
       8: aload_0
       9: getfield      #2                  // Field subprocs:Ljava/util/Set;
      12: ifnonnull     26
      15: aload_0
      16: new           #35                 // class java/util/HashSet
      19: dup
      20: invokespecial #36                 // Method java/util/HashSet."<init>":()V
      23: putfield      #2                  // Field subprocs:Ljava/util/Set;
      26: aload_0
      27: getfield      #2                  // Field subprocs:Ljava/util/Set;
      30: aload_1
      31: invokeinterface #37,  2           // InterfaceMethod java/util/Set.add:(Ljava/lang/Object;)Z
      36: pop
      37: return

  protected synchronized void loadStack(org.apache.hadoop.hbase.procedure2.Procedure<TEnvironment>);
    Code:
       0: aload_0
       1: aload_1
       2: invokevirtual #38                 // Method addSubProcedure:(Lorg/apache/hadoop/hbase/procedure2/Procedure;)V
       5: aload_1
       6: invokevirtual #39                 // Method org/apache/hadoop/hbase/procedure2/Procedure.getStackIndexes:()[I
       9: astore_2
      10: aload_2
      11: ifnull        116
      14: aload_0
      15: getfield      #3                  // Field subprocStack:Ljava/util/ArrayList;
      18: ifnonnull     32
      21: aload_0
      22: new           #25                 // class java/util/ArrayList
      25: dup
      26: invokespecial #26                 // Method java/util/ArrayList."<init>":()V
      29: putfield      #3                  // Field subprocStack:Ljava/util/ArrayList;
      32: iconst_1
      33: aload_2
      34: aload_2
      35: arraylength
      36: iconst_1
      37: isub
      38: iaload
      39: iadd
      40: aload_0
      41: getfield      #3                  // Field subprocStack:Ljava/util/ArrayList;
      44: invokevirtual #27                 // Method java/util/ArrayList.size:()I
      47: isub
      48: istore_3
      49: iload_3
      50: ifle          87
      53: aload_0
      54: getfield      #3                  // Field subprocStack:Ljava/util/ArrayList;
      57: iconst_1
      58: aload_2
      59: aload_2
      60: arraylength
      61: iconst_1
      62: isub
      63: iaload
      64: iadd
      65: invokevirtual #40                 // Method java/util/ArrayList.ensureCapacity:(I)V
      68: iload_3
      69: iinc          3, -1
      72: ifle          87
      75: aload_0
      76: getfield      #3                  // Field subprocStack:Ljava/util/ArrayList;
      79: aconst_null
      80: invokevirtual #33                 // Method java/util/ArrayList.add:(Ljava/lang/Object;)Z
      83: pop
      84: goto          68
      87: iconst_0
      88: istore        4
      90: iload         4
      92: aload_2
      93: arraylength
      94: if_icmpge     116
      97: aload_0
      98: getfield      #3                  // Field subprocStack:Ljava/util/ArrayList;
     101: aload_2
     102: iload         4
     104: iaload
     105: aload_1
     106: invokevirtual #41                 // Method java/util/ArrayList.set:(ILjava/lang/Object;)Ljava/lang/Object;
     109: pop
     110: iinc          4, 1
     113: goto          90
     116: aload_1
     117: invokevirtual #42                 // Method org/apache/hadoop/hbase/procedure2/Procedure.getState:()Lorg/apache/hadoop/hbase/shaded/protobuf/generated/ProcedureProtos$ProcedureState;
     120: getstatic     #43                 // Field org/apache/hadoop/hbase/shaded/protobuf/generated/ProcedureProtos$ProcedureState.ROLLEDBACK:Lorg/apache/hadoop/hbase/shaded/protobuf/generated/ProcedureProtos$ProcedureState;
     123: if_acmpne     136
     126: aload_0
     127: getstatic     #9                  // Field org/apache/hadoop/hbase/procedure2/RootProcedureState$State.ROLLINGBACK:Lorg/apache/hadoop/hbase/procedure2/RootProcedureState$State;
     130: putfield      #5                  // Field state:Lorg/apache/hadoop/hbase/procedure2/RootProcedureState$State;
     133: goto          150
     136: aload_1
     137: invokevirtual #24                 // Method org/apache/hadoop/hbase/procedure2/Procedure.isFailed:()Z
     140: ifeq          150
     143: aload_0
     144: getstatic     #10                 // Field org/apache/hadoop/hbase/procedure2/RootProcedureState$State.FAILED:Lorg/apache/hadoop/hbase/procedure2/RootProcedureState$State;
     147: putfield      #5                  // Field state:Lorg/apache/hadoop/hbase/procedure2/RootProcedureState$State;
     150: return

  protected synchronized boolean isValid();
    Code:
       0: aload_0
       1: getfield      #3                  // Field subprocStack:Ljava/util/ArrayList;
       4: ifnull        43
       7: aload_0
       8: getfield      #3                  // Field subprocStack:Ljava/util/ArrayList;
      11: invokevirtual #18                 // Method java/util/ArrayList.iterator:()Ljava/util/Iterator;
      14: astore_1
      15: aload_1
      16: invokeinterface #19,  1           // InterfaceMethod java/util/Iterator.hasNext:()Z
      21: ifeq          43
      24: aload_1
      25: invokeinterface #20,  1           // InterfaceMethod java/util/Iterator.next:()Ljava/lang/Object;
      30: checkcast     #21                 // class org/apache/hadoop/hbase/procedure2/Procedure
      33: astore_2
      34: aload_2
      35: ifnonnull     40
      38: iconst_0
      39: ireturn
      40: goto          15
      43: iconst_1
      44: ireturn

  static {};
    Code:
       0: ldc           #44                 // class org/apache/hadoop/hbase/procedure2/RootProcedureState
       2: invokevirtual #45                 // Method java/lang/Class.desiredAssertionStatus:()Z
       5: ifne          12
       8: iconst_1
       9: goto          13
      12: iconst_0
      13: putstatic     #11                 // Field $assertionsDisabled:Z
      16: ldc           #44                 // class org/apache/hadoop/hbase/procedure2/RootProcedureState
      18: invokestatic  #46                 // Method org/slf4j/LoggerFactory.getLogger:(Ljava/lang/Class;)Lorg/slf4j/Logger;
      21: putstatic     #29                 // Field LOG:Lorg/slf4j/Logger;
      24: return
}
