Compiled from "RpcConnection.java"
class org.apache.hadoop.hbase.ipc.RpcConnection$1 implements org.apache.hbase.thirdparty.io.netty.util.TimerTask {
  final org.apache.hadoop.hbase.ipc.Call val$call;

  final org.apache.hadoop.hbase.ipc.RpcConnection this$0;

  org.apache.hadoop.hbase.ipc.RpcConnection$1(org.apache.hadoop.hbase.ipc.RpcConnection, org.apache.hadoop.hbase.ipc.Call);
    Code:
       0: aload_0
       1: aload_1
       2: putfield      #1                  // Field this$0:Lorg/apache/hadoop/hbase/ipc/RpcConnection;
       5: aload_0
       6: aload_2
       7: putfield      #2                  // Field val$call:Lorg/apache/hadoop/hbase/ipc/Call;
      10: aload_0
      11: invokespecial #3                  // Method java/lang/Object."<init>":()V
      14: return

  public void run(org.apache.hbase.thirdparty.io.netty.util.Timeout) throws java.lang.Exception;
    Code:
       0: aload_0
       1: getfield      #2                  // Field val$call:Lorg/apache/hadoop/hbase/ipc/Call;
       4: new           #4                  // class org/apache/hadoop/hbase/ipc/CallTimeoutException
       7: dup
       8: new           #5                  // class java/lang/StringBuilder
      11: dup
      12: invokespecial #6                  // Method java/lang/StringBuilder."<init>":()V
      15: ldc           #7                  // String Call id=
      17: invokevirtual #8                  // Method java/lang/StringBuilder.append:(Ljava/lang/String;)Ljava/lang/StringBuilder;
      20: aload_0
      21: getfield      #2                  // Field val$call:Lorg/apache/hadoop/hbase/ipc/Call;
      24: getfield      #9                  // Field org/apache/hadoop/hbase/ipc/Call.id:I
      27: invokevirtual #10                 // Method java/lang/StringBuilder.append:(I)Ljava/lang/StringBuilder;
      30: ldc           #11                 // String , waitTime=
      32: invokevirtual #8                  // Method java/lang/StringBuilder.append:(Ljava/lang/String;)Ljava/lang/StringBuilder;
      35: invokestatic  #12                 // Method org/apache/hadoop/hbase/util/EnvironmentEdgeManager.currentTime:()J
      38: aload_0
      39: getfield      #2                  // Field val$call:Lorg/apache/hadoop/hbase/ipc/Call;
      42: invokevirtual #13                 // Method org/apache/hadoop/hbase/ipc/Call.getStartTime:()J
      45: lsub
      46: invokevirtual #14                 // Method java/lang/StringBuilder.append:(J)Ljava/lang/StringBuilder;
      49: ldc           #15                 // String , rpcTimeout=
      51: invokevirtual #8                  // Method java/lang/StringBuilder.append:(Ljava/lang/String;)Ljava/lang/StringBuilder;
      54: aload_0
      55: getfield      #2                  // Field val$call:Lorg/apache/hadoop/hbase/ipc/Call;
      58: getfield      #16                 // Field org/apache/hadoop/hbase/ipc/Call.timeout:I
      61: invokevirtual #10                 // Method java/lang/StringBuilder.append:(I)Ljava/lang/StringBuilder;
      64: invokevirtual #17                 // Method java/lang/StringBuilder.toString:()Ljava/lang/String;
      67: invokespecial #18                 // Method org/apache/hadoop/hbase/ipc/CallTimeoutException."<init>":(Ljava/lang/String;)V
      70: invokevirtual #19                 // Method org/apache/hadoop/hbase/ipc/Call.setTimeout:(Ljava/io/IOException;)V
      73: aload_0
      74: getfield      #1                  // Field this$0:Lorg/apache/hadoop/hbase/ipc/RpcConnection;
      77: aload_0
      78: getfield      #2                  // Field val$call:Lorg/apache/hadoop/hbase/ipc/Call;
      81: invokevirtual #20                 // Method org/apache/hadoop/hbase/ipc/RpcConnection.callTimeout:(Lorg/apache/hadoop/hbase/ipc/Call;)V
      84: return
}
