Compiled from "RpcExecutor.java"
class org.apache.hadoop.hbase.ipc.RpcExecutor$CallPriorityComparator implements java.util.Comparator<org.apache.hadoop.hbase.ipc.CallRunner> {
  public org.apache.hadoop.hbase.ipc.RpcExecutor$CallPriorityComparator(org.apache.hadoop.conf.Configuration, org.apache.hadoop.hbase.ipc.PriorityFunction);
    Code:
       0: aload_0
       1: invokespecial #2                  // Method java/lang/Object."<init>":()V
       4: aload_0
       5: aload_2
       6: putfield      #3                  // Field priority:Lorg/apache/hadoop/hbase/ipc/PriorityFunction;
       9: aload_0
      10: aload_1
      11: ldc           #4                  // String hbase.ipc.server.queue.max.call.delay
      13: sipush        5000
      16: invokevirtual #6                  // Method org/apache/hadoop/conf/Configuration.getInt:(Ljava/lang/String;I)I
      19: putfield      #7                  // Field maxDelay:I
      22: return

  public int compare(org.apache.hadoop.hbase.ipc.CallRunner, org.apache.hadoop.hbase.ipc.CallRunner);
    Code:
       0: aload_1
       1: invokevirtual #8                  // Method org/apache/hadoop/hbase/ipc/CallRunner.getRpcCall:()Lorg/apache/hadoop/hbase/ipc/RpcCall;
       4: astore_3
       5: aload_2
       6: invokevirtual #8                  // Method org/apache/hadoop/hbase/ipc/CallRunner.getRpcCall:()Lorg/apache/hadoop/hbase/ipc/RpcCall;
       9: astore        4
      11: aload_0
      12: getfield      #3                  // Field priority:Lorg/apache/hadoop/hbase/ipc/PriorityFunction;
      15: aload_3
      16: invokeinterface #9,  1            // InterfaceMethod org/apache/hadoop/hbase/ipc/RpcCall.getHeader:()Lorg/apache/hadoop/hbase/shaded/protobuf/generated/RPCProtos$RequestHeader;
      21: aload_3
      22: invokeinterface #10,  1           // InterfaceMethod org/apache/hadoop/hbase/ipc/RpcCall.getParam:()Lorg/apache/hbase/thirdparty/com/google/protobuf/Message;
      27: invokeinterface #11,  3           // InterfaceMethod org/apache/hadoop/hbase/ipc/PriorityFunction.getDeadline:(Lorg/apache/hadoop/hbase/shaded/protobuf/generated/RPCProtos$RequestHeader;Lorg/apache/hbase/thirdparty/com/google/protobuf/Message;)J
      32: lstore        5
      34: aload_0
      35: getfield      #3                  // Field priority:Lorg/apache/hadoop/hbase/ipc/PriorityFunction;
      38: aload         4
      40: invokeinterface #9,  1            // InterfaceMethod org/apache/hadoop/hbase/ipc/RpcCall.getHeader:()Lorg/apache/hadoop/hbase/shaded/protobuf/generated/RPCProtos$RequestHeader;
      45: aload         4
      47: invokeinterface #10,  1           // InterfaceMethod org/apache/hadoop/hbase/ipc/RpcCall.getParam:()Lorg/apache/hbase/thirdparty/com/google/protobuf/Message;
      52: invokeinterface #11,  3           // InterfaceMethod org/apache/hadoop/hbase/ipc/PriorityFunction.getDeadline:(Lorg/apache/hadoop/hbase/shaded/protobuf/generated/RPCProtos$RequestHeader;Lorg/apache/hbase/thirdparty/com/google/protobuf/Message;)J
      57: lstore        7
      59: aload_3
      60: invokeinterface #12,  1           // InterfaceMethod org/apache/hadoop/hbase/ipc/RpcCall.getReceiveTime:()J
      65: lload         5
      67: aload_0
      68: getfield      #7                  // Field maxDelay:I
      71: i2l
      72: invokestatic  #13                 // Method java/lang/Math.min:(JJ)J
      75: ladd
      76: lstore        5
      78: aload         4
      80: invokeinterface #12,  1           // InterfaceMethod org/apache/hadoop/hbase/ipc/RpcCall.getReceiveTime:()J
      85: lload         7
      87: aload_0
      88: getfield      #7                  // Field maxDelay:I
      91: i2l
      92: invokestatic  #13                 // Method java/lang/Math.min:(JJ)J
      95: ladd
      96: lstore        7
      98: lload         5
     100: lload         7
     102: invokestatic  #14                 // Method java/lang/Long.compare:(JJ)I
     105: ireturn

  public int compare(java.lang.Object, java.lang.Object);
    Code:
       0: aload_0
       1: aload_1
       2: checkcast     #15                 // class org/apache/hadoop/hbase/ipc/CallRunner
       5: aload_2
       6: checkcast     #15                 // class org/apache/hadoop/hbase/ipc/CallRunner
       9: invokevirtual #16                 // Method compare:(Lorg/apache/hadoop/hbase/ipc/CallRunner;Lorg/apache/hadoop/hbase/ipc/CallRunner;)I
      12: ireturn
}
