Compiled from "RPCProtos.java"
public final class org.apache.hadoop.hbase.protobuf.generated.RPCProtos$RequestHeader$Builder extends com.google.protobuf.GeneratedMessage$Builder<org.apache.hadoop.hbase.protobuf.generated.RPCProtos$RequestHeader$Builder> implements org.apache.hadoop.hbase.protobuf.generated.RPCProtos$RequestHeaderOrBuilder {
  public static final com.google.protobuf.Descriptors$Descriptor getDescriptor();
    Code:
       0: invokestatic  #3                  // Method org/apache/hadoop/hbase/protobuf/generated/RPCProtos.access$4500:()Lcom/google/protobuf/Descriptors$Descriptor;
       3: areturn

  protected com.google.protobuf.GeneratedMessage$FieldAccessorTable internalGetFieldAccessorTable();
    Code:
       0: invokestatic  #4                  // Method org/apache/hadoop/hbase/protobuf/generated/RPCProtos.access$4600:()Lcom/google/protobuf/GeneratedMessage$FieldAccessorTable;
       3: ldc           #5                  // class org/apache/hadoop/hbase/protobuf/generated/RPCProtos$RequestHeader
       5: ldc           #6                  // class org/apache/hadoop/hbase/protobuf/generated/RPCProtos$RequestHeader$Builder
       7: invokevirtual #7                  // Method com/google/protobuf/GeneratedMessage$FieldAccessorTable.ensureFieldAccessorsInitialized:(Ljava/lang/Class;Ljava/lang/Class;)Lcom/google/protobuf/GeneratedMessage$FieldAccessorTable;
      10: areturn

  public org.apache.hadoop.hbase.protobuf.generated.RPCProtos$RequestHeader$Builder clear();
    Code:
       0: aload_0
       1: invokespecial #21                 // Method com/google/protobuf/GeneratedMessage$Builder.clear:()Lcom/google/protobuf/GeneratedMessage$Builder;
       4: pop
       5: aload_0
       6: iconst_0
       7: putfield      #22                 // Field callId_:I
      10: aload_0
      11: aload_0
      12: getfield      #23                 // Field bitField0_:I
      15: bipush        -2
      17: iand
      18: putfield      #23                 // Field bitField0_:I
      21: aload_0
      22: getfield      #24                 // Field traceInfoBuilder_:Lcom/google/protobuf/SingleFieldBuilder;
      25: ifnonnull     38
      28: aload_0
      29: invokestatic  #9                  // Method org/apache/hadoop/hbase/protobuf/generated/TracingProtos$RPCTInfo.getDefaultInstance:()Lorg/apache/hadoop/hbase/protobuf/generated/TracingProtos$RPCTInfo;
      32: putfield      #10                 // Field traceInfo_:Lorg/apache/hadoop/hbase/protobuf/generated/TracingProtos$RPCTInfo;
      35: goto          46
      38: aload_0
      39: getfield      #24                 // Field traceInfoBuilder_:Lcom/google/protobuf/SingleFieldBuilder;
      42: invokevirtual #25                 // Method com/google/protobuf/SingleFieldBuilder.clear:()Lcom/google/protobuf/SingleFieldBuilder;
      45: pop
      46: aload_0
      47: aload_0
      48: getfield      #23                 // Field bitField0_:I
      51: bipush        -3
      53: iand
      54: putfield      #23                 // Field bitField0_:I
      57: aload_0
      58: ldc           #11                 // String
      60: putfield      #12                 // Field methodName_:Ljava/lang/Object;
      63: aload_0
      64: aload_0
      65: getfield      #23                 // Field bitField0_:I
      68: bipush        -5
      70: iand
      71: putfield      #23                 // Field bitField0_:I
      74: aload_0
      75: iconst_0
      76: putfield      #26                 // Field requestParam_:Z
      79: aload_0
      80: aload_0
      81: getfield      #23                 // Field bitField0_:I
      84: bipush        -9
      86: iand
      87: putfield      #23                 // Field bitField0_:I
      90: aload_0
      91: getfield      #27                 // Field cellBlockMetaBuilder_:Lcom/google/protobuf/SingleFieldBuilder;
      94: ifnonnull     107
      97: aload_0
      98: invokestatic  #13                 // Method org/apache/hadoop/hbase/protobuf/generated/RPCProtos$CellBlockMeta.getDefaultInstance:()Lorg/apache/hadoop/hbase/protobuf/generated/RPCProtos$CellBlockMeta;
     101: putfield      #14                 // Field cellBlockMeta_:Lorg/apache/hadoop/hbase/protobuf/generated/RPCProtos$CellBlockMeta;
     104: goto          115
     107: aload_0
     108: getfield      #27                 // Field cellBlockMetaBuilder_:Lcom/google/protobuf/SingleFieldBuilder;
     111: invokevirtual #25                 // Method com/google/protobuf/SingleFieldBuilder.clear:()Lcom/google/protobuf/SingleFieldBuilder;
     114: pop
     115: aload_0
     116: aload_0
     117: getfield      #23                 // Field bitField0_:I
     120: bipush        -17
     122: iand
     123: putfield      #23                 // Field bitField0_:I
     126: aload_0
     127: iconst_0
     128: putfield      #28                 // Field priority_:I
     131: aload_0
     132: aload_0
     133: getfield      #23                 // Field bitField0_:I
     136: bipush        -33
     138: iand
     139: putfield      #23                 // Field bitField0_:I
     142: aload_0
     143: iconst_0
     144: putfield      #29                 // Field timeout_:I
     147: aload_0
     148: aload_0
     149: getfield      #23                 // Field bitField0_:I
     152: bipush        -65
     154: iand
     155: putfield      #23                 // Field bitField0_:I
     158: aload_0
     159: areturn

  public org.apache.hadoop.hbase.protobuf.generated.RPCProtos$RequestHeader$Builder clone();
    Code:
       0: invokestatic  #2                  // Method create:()Lorg/apache/hadoop/hbase/protobuf/generated/RPCProtos$RequestHeader$Builder;
       3: aload_0
       4: invokevirtual #30                 // Method buildPartial:()Lorg/apache/hadoop/hbase/protobuf/generated/RPCProtos$RequestHeader;
       7: invokevirtual #31                 // Method mergeFrom:(Lorg/apache/hadoop/hbase/protobuf/generated/RPCProtos$RequestHeader;)Lorg/apache/hadoop/hbase/protobuf/generated/RPCProtos$RequestHeader$Builder;
      10: areturn

  public com.google.protobuf.Descriptors$Descriptor getDescriptorForType();
    Code:
       0: invokestatic  #3                  // Method org/apache/hadoop/hbase/protobuf/generated/RPCProtos.access$4500:()Lcom/google/protobuf/Descriptors$Descriptor;
       3: areturn

  public org.apache.hadoop.hbase.protobuf.generated.RPCProtos$RequestHeader getDefaultInstanceForType();
    Code:
       0: invokestatic  #32                 // Method org/apache/hadoop/hbase/protobuf/generated/RPCProtos$RequestHeader.getDefaultInstance:()Lorg/apache/hadoop/hbase/protobuf/generated/RPCProtos$RequestHeader;
       3: areturn

  public org.apache.hadoop.hbase.protobuf.generated.RPCProtos$RequestHeader build();
    Code:
       0: aload_0
       1: invokevirtual #30                 // Method buildPartial:()Lorg/apache/hadoop/hbase/protobuf/generated/RPCProtos$RequestHeader;
       4: astore_1
       5: aload_1
       6: invokevirtual #33                 // Method org/apache/hadoop/hbase/protobuf/generated/RPCProtos$RequestHeader.isInitialized:()Z
       9: ifne          17
      12: aload_1
      13: invokestatic  #34                 // Method newUninitializedMessageException:(Lcom/google/protobuf/Message;)Lcom/google/protobuf/UninitializedMessageException;
      16: athrow
      17: aload_1
      18: areturn

  public org.apache.hadoop.hbase.protobuf.generated.RPCProtos$RequestHeader buildPartial();
    Code:
       0: new           #5                  // class org/apache/hadoop/hbase/protobuf/generated/RPCProtos$RequestHeader
       3: dup
       4: aload_0
       5: aconst_null
       6: invokespecial #35                 // Method org/apache/hadoop/hbase/protobuf/generated/RPCProtos$RequestHeader."<init>":(Lcom/google/protobuf/GeneratedMessage$Builder;Lorg/apache/hadoop/hbase/protobuf/generated/RPCProtos$1;)V
       9: astore_1
      10: aload_0
      11: getfield      #23                 // Field bitField0_:I
      14: istore_2
      15: iconst_0
      16: istore_3
      17: iload_2
      18: iconst_1
      19: iand
      20: iconst_1
      21: if_icmpne     28
      24: iload_3
      25: iconst_1
      26: ior
      27: istore_3
      28: aload_1
      29: aload_0
      30: getfield      #22                 // Field callId_:I
      33: invokestatic  #36                 // Method org/apache/hadoop/hbase/protobuf/generated/RPCProtos$RequestHeader.access$5202:(Lorg/apache/hadoop/hbase/protobuf/generated/RPCProtos$RequestHeader;I)I
      36: pop
      37: iload_2
      38: iconst_2
      39: iand
      40: iconst_2
      41: if_icmpne     48
      44: iload_3
      45: iconst_2
      46: ior
      47: istore_3
      48: aload_0
      49: getfield      #24                 // Field traceInfoBuilder_:Lcom/google/protobuf/SingleFieldBuilder;
      52: ifnonnull     67
      55: aload_1
      56: aload_0
      57: getfield      #10                 // Field traceInfo_:Lorg/apache/hadoop/hbase/protobuf/generated/TracingProtos$RPCTInfo;
      60: invokestatic  #37                 // Method org/apache/hadoop/hbase/protobuf/generated/RPCProtos$RequestHeader.access$5302:(Lorg/apache/hadoop/hbase/protobuf/generated/RPCProtos$RequestHeader;Lorg/apache/hadoop/hbase/protobuf/generated/TracingProtos$RPCTInfo;)Lorg/apache/hadoop/hbase/protobuf/generated/TracingProtos$RPCTInfo;
      63: pop
      64: goto          82
      67: aload_1
      68: aload_0
      69: getfield      #24                 // Field traceInfoBuilder_:Lcom/google/protobuf/SingleFieldBuilder;
      72: invokevirtual #38                 // Method com/google/protobuf/SingleFieldBuilder.build:()Lcom/google/protobuf/GeneratedMessage;
      75: checkcast     #39                 // class org/apache/hadoop/hbase/protobuf/generated/TracingProtos$RPCTInfo
      78: invokestatic  #37                 // Method org/apache/hadoop/hbase/protobuf/generated/RPCProtos$RequestHeader.access$5302:(Lorg/apache/hadoop/hbase/protobuf/generated/RPCProtos$RequestHeader;Lorg/apache/hadoop/hbase/protobuf/generated/TracingProtos$RPCTInfo;)Lorg/apache/hadoop/hbase/protobuf/generated/TracingProtos$RPCTInfo;
      81: pop
      82: iload_2
      83: iconst_4
      84: iand
      85: iconst_4
      86: if_icmpne     93
      89: iload_3
      90: iconst_4
      91: ior
      92: istore_3
      93: aload_1
      94: aload_0
      95: getfield      #12                 // Field methodName_:Ljava/lang/Object;
      98: invokestatic  #40                 // Method org/apache/hadoop/hbase/protobuf/generated/RPCProtos$RequestHeader.access$5402:(Lorg/apache/hadoop/hbase/protobuf/generated/RPCProtos$RequestHeader;Ljava/lang/Object;)Ljava/lang/Object;
     101: pop
     102: iload_2
     103: bipush        8
     105: iand
     106: bipush        8
     108: if_icmpne     116
     111: iload_3
     112: bipush        8
     114: ior
     115: istore_3
     116: aload_1
     117: aload_0
     118: getfield      #26                 // Field requestParam_:Z
     121: invokestatic  #41                 // Method org/apache/hadoop/hbase/protobuf/generated/RPCProtos$RequestHeader.access$5502:(Lorg/apache/hadoop/hbase/protobuf/generated/RPCProtos$RequestHeader;Z)Z
     124: pop
     125: iload_2
     126: bipush        16
     128: iand
     129: bipush        16
     131: if_icmpne     139
     134: iload_3
     135: bipush        16
     137: ior
     138: istore_3
     139: aload_0
     140: getfield      #27                 // Field cellBlockMetaBuilder_:Lcom/google/protobuf/SingleFieldBuilder;
     143: ifnonnull     158
     146: aload_1
     147: aload_0
     148: getfield      #14                 // Field cellBlockMeta_:Lorg/apache/hadoop/hbase/protobuf/generated/RPCProtos$CellBlockMeta;
     151: invokestatic  #42                 // Method org/apache/hadoop/hbase/protobuf/generated/RPCProtos$RequestHeader.access$5602:(Lorg/apache/hadoop/hbase/protobuf/generated/RPCProtos$RequestHeader;Lorg/apache/hadoop/hbase/protobuf/generated/RPCProtos$CellBlockMeta;)Lorg/apache/hadoop/hbase/protobuf/generated/RPCProtos$CellBlockMeta;
     154: pop
     155: goto          173
     158: aload_1
     159: aload_0
     160: getfield      #27                 // Field cellBlockMetaBuilder_:Lcom/google/protobuf/SingleFieldBuilder;
     163: invokevirtual #38                 // Method com/google/protobuf/SingleFieldBuilder.build:()Lcom/google/protobuf/GeneratedMessage;
     166: checkcast     #43                 // class org/apache/hadoop/hbase/protobuf/generated/RPCProtos$CellBlockMeta
     169: invokestatic  #42                 // Method org/apache/hadoop/hbase/protobuf/generated/RPCProtos$RequestHeader.access$5602:(Lorg/apache/hadoop/hbase/protobuf/generated/RPCProtos$RequestHeader;Lorg/apache/hadoop/hbase/protobuf/generated/RPCProtos$CellBlockMeta;)Lorg/apache/hadoop/hbase/protobuf/generated/RPCProtos$CellBlockMeta;
     172: pop
     173: iload_2
     174: bipush        32
     176: iand
     177: bipush        32
     179: if_icmpne     187
     182: iload_3
     183: bipush        32
     185: ior
     186: istore_3
     187: aload_1
     188: aload_0
     189: getfield      #28                 // Field priority_:I
     192: invokestatic  #44                 // Method org/apache/hadoop/hbase/protobuf/generated/RPCProtos$RequestHeader.access$5702:(Lorg/apache/hadoop/hbase/protobuf/generated/RPCProtos$RequestHeader;I)I
     195: pop
     196: iload_2
     197: bipush        64
     199: iand
     200: bipush        64
     202: if_icmpne     210
     205: iload_3
     206: bipush        64
     208: ior
     209: istore_3
     210: aload_1
     211: aload_0
     212: getfield      #29                 // Field timeout_:I
     215: invokestatic  #45                 // Method org/apache/hadoop/hbase/protobuf/generated/RPCProtos$RequestHeader.access$5802:(Lorg/apache/hadoop/hbase/protobuf/generated/RPCProtos$RequestHeader;I)I
     218: pop
     219: aload_1
     220: iload_3
     221: invokestatic  #46                 // Method org/apache/hadoop/hbase/protobuf/generated/RPCProtos$RequestHeader.access$5902:(Lorg/apache/hadoop/hbase/protobuf/generated/RPCProtos$RequestHeader;I)I
     224: pop
     225: aload_0
     226: invokevirtual #47                 // Method onBuilt:()V
     229: aload_1
     230: areturn

  public org.apache.hadoop.hbase.protobuf.generated.RPCProtos$RequestHeader$Builder mergeFrom(com.google.protobuf.Message);
    Code:
       0: aload_1
       1: instanceof    #5                  // class org/apache/hadoop/hbase/protobuf/generated/RPCProtos$RequestHeader
       4: ifeq          16
       7: aload_0
       8: aload_1
       9: checkcast     #5                  // class org/apache/hadoop/hbase/protobuf/generated/RPCProtos$RequestHeader
      12: invokevirtual #31                 // Method mergeFrom:(Lorg/apache/hadoop/hbase/protobuf/generated/RPCProtos$RequestHeader;)Lorg/apache/hadoop/hbase/protobuf/generated/RPCProtos$RequestHeader$Builder;
      15: areturn
      16: aload_0
      17: aload_1
      18: invokespecial #48                 // Method com/google/protobuf/GeneratedMessage$Builder.mergeFrom:(Lcom/google/protobuf/Message;)Lcom/google/protobuf/AbstractMessage$Builder;
      21: pop
      22: aload_0
      23: areturn

  public org.apache.hadoop.hbase.protobuf.generated.RPCProtos$RequestHeader$Builder mergeFrom(org.apache.hadoop.hbase.protobuf.generated.RPCProtos$RequestHeader);
    Code:
       0: aload_1
       1: invokestatic  #32                 // Method org/apache/hadoop/hbase/protobuf/generated/RPCProtos$RequestHeader.getDefaultInstance:()Lorg/apache/hadoop/hbase/protobuf/generated/RPCProtos$RequestHeader;
       4: if_acmpne     9
       7: aload_0
       8: areturn
       9: aload_1
      10: invokevirtual #49                 // Method org/apache/hadoop/hbase/protobuf/generated/RPCProtos$RequestHeader.hasCallId:()Z
      13: ifeq          25
      16: aload_0
      17: aload_1
      18: invokevirtual #50                 // Method org/apache/hadoop/hbase/protobuf/generated/RPCProtos$RequestHeader.getCallId:()I
      21: invokevirtual #51                 // Method setCallId:(I)Lorg/apache/hadoop/hbase/protobuf/generated/RPCProtos$RequestHeader$Builder;
      24: pop
      25: aload_1
      26: invokevirtual #52                 // Method org/apache/hadoop/hbase/protobuf/generated/RPCProtos$RequestHeader.hasTraceInfo:()Z
      29: ifeq          41
      32: aload_0
      33: aload_1
      34: invokevirtual #53                 // Method org/apache/hadoop/hbase/protobuf/generated/RPCProtos$RequestHeader.getTraceInfo:()Lorg/apache/hadoop/hbase/protobuf/generated/TracingProtos$RPCTInfo;
      37: invokevirtual #54                 // Method mergeTraceInfo:(Lorg/apache/hadoop/hbase/protobuf/generated/TracingProtos$RPCTInfo;)Lorg/apache/hadoop/hbase/protobuf/generated/RPCProtos$RequestHeader$Builder;
      40: pop
      41: aload_1
      42: invokevirtual #55                 // Method org/apache/hadoop/hbase/protobuf/generated/RPCProtos$RequestHeader.hasMethodName:()Z
      45: ifeq          70
      48: aload_0
      49: dup
      50: getfield      #23                 // Field bitField0_:I
      53: iconst_4
      54: ior
      55: putfield      #23                 // Field bitField0_:I
      58: aload_0
      59: aload_1
      60: invokestatic  #56                 // Method org/apache/hadoop/hbase/protobuf/generated/RPCProtos$RequestHeader.access$5400:(Lorg/apache/hadoop/hbase/protobuf/generated/RPCProtos$RequestHeader;)Ljava/lang/Object;
      63: putfield      #12                 // Field methodName_:Ljava/lang/Object;
      66: aload_0
      67: invokevirtual #57                 // Method onChanged:()V
      70: aload_1
      71: invokevirtual #58                 // Method org/apache/hadoop/hbase/protobuf/generated/RPCProtos$RequestHeader.hasRequestParam:()Z
      74: ifeq          86
      77: aload_0
      78: aload_1
      79: invokevirtual #59                 // Method org/apache/hadoop/hbase/protobuf/generated/RPCProtos$RequestHeader.getRequestParam:()Z
      82: invokevirtual #60                 // Method setRequestParam:(Z)Lorg/apache/hadoop/hbase/protobuf/generated/RPCProtos$RequestHeader$Builder;
      85: pop
      86: aload_1
      87: invokevirtual #61                 // Method org/apache/hadoop/hbase/protobuf/generated/RPCProtos$RequestHeader.hasCellBlockMeta:()Z
      90: ifeq          102
      93: aload_0
      94: aload_1
      95: invokevirtual #62                 // Method org/apache/hadoop/hbase/protobuf/generated/RPCProtos$RequestHeader.getCellBlockMeta:()Lorg/apache/hadoop/hbase/protobuf/generated/RPCProtos$CellBlockMeta;
      98: invokevirtual #63                 // Method mergeCellBlockMeta:(Lorg/apache/hadoop/hbase/protobuf/generated/RPCProtos$CellBlockMeta;)Lorg/apache/hadoop/hbase/protobuf/generated/RPCProtos$RequestHeader$Builder;
     101: pop
     102: aload_1
     103: invokevirtual #64                 // Method org/apache/hadoop/hbase/protobuf/generated/RPCProtos$RequestHeader.hasPriority:()Z
     106: ifeq          118
     109: aload_0
     110: aload_1
     111: invokevirtual #65                 // Method org/apache/hadoop/hbase/protobuf/generated/RPCProtos$RequestHeader.getPriority:()I
     114: invokevirtual #66                 // Method setPriority:(I)Lorg/apache/hadoop/hbase/protobuf/generated/RPCProtos$RequestHeader$Builder;
     117: pop
     118: aload_1
     119: invokevirtual #67                 // Method org/apache/hadoop/hbase/protobuf/generated/RPCProtos$RequestHeader.hasTimeout:()Z
     122: ifeq          134
     125: aload_0
     126: aload_1
     127: invokevirtual #68                 // Method org/apache/hadoop/hbase/protobuf/generated/RPCProtos$RequestHeader.getTimeout:()I
     130: invokevirtual #69                 // Method setTimeout:(I)Lorg/apache/hadoop/hbase/protobuf/generated/RPCProtos$RequestHeader$Builder;
     133: pop
     134: aload_0
     135: aload_1
     136: invokevirtual #70                 // Method org/apache/hadoop/hbase/protobuf/generated/RPCProtos$RequestHeader.getUnknownFields:()Lcom/google/protobuf/UnknownFieldSet;
     139: invokevirtual #71                 // Method mergeUnknownFields:(Lcom/google/protobuf/UnknownFieldSet;)Lcom/google/protobuf/GeneratedMessage$Builder;
     142: pop
     143: aload_0
     144: areturn

  public final boolean isInitialized();
    Code:
       0: iconst_1
       1: ireturn

  public org.apache.hadoop.hbase.protobuf.generated.RPCProtos$RequestHeader$Builder mergeFrom(com.google.protobuf.CodedInputStream, com.google.protobuf.ExtensionRegistryLite) throws java.io.IOException;
    Code:
       0: aconst_null
       1: astore_3
       2: getstatic     #72                 // Field org/apache/hadoop/hbase/protobuf/generated/RPCProtos$RequestHeader.PARSER:Lcom/google/protobuf/Parser;
       5: aload_1
       6: aload_2
       7: invokeinterface #73,  3           // InterfaceMethod com/google/protobuf/Parser.parsePartialFrom:(Lcom/google/protobuf/CodedInputStream;Lcom/google/protobuf/ExtensionRegistryLite;)Ljava/lang/Object;
      12: checkcast     #5                  // class org/apache/hadoop/hbase/protobuf/generated/RPCProtos$RequestHeader
      15: astore_3
      16: aload_3
      17: ifnull        58
      20: aload_0
      21: aload_3
      22: invokevirtual #31                 // Method mergeFrom:(Lorg/apache/hadoop/hbase/protobuf/generated/RPCProtos$RequestHeader;)Lorg/apache/hadoop/hbase/protobuf/generated/RPCProtos$RequestHeader$Builder;
      25: pop
      26: goto          58
      29: astore        4
      31: aload         4
      33: invokevirtual #75                 // Method com/google/protobuf/InvalidProtocolBufferException.getUnfinishedMessage:()Lcom/google/protobuf/MessageLite;
      36: checkcast     #5                  // class org/apache/hadoop/hbase/protobuf/generated/RPCProtos$RequestHeader
      39: astore_3
      40: aload         4
      42: athrow
      43: astore        5
      45: aload_3
      46: ifnull        55
      49: aload_0
      50: aload_3
      51: invokevirtual #31                 // Method mergeFrom:(Lorg/apache/hadoop/hbase/protobuf/generated/RPCProtos$RequestHeader;)Lorg/apache/hadoop/hbase/protobuf/generated/RPCProtos$RequestHeader$Builder;
      54: pop
      55: aload         5
      57: athrow
      58: aload_0
      59: areturn
    Exception table:
       from    to  target type
           2    16    29   Class com/google/protobuf/InvalidProtocolBufferException
           2    16    43   any
          29    45    43   any

  public boolean hasCallId();
    Code:
       0: aload_0
       1: getfield      #23                 // Field bitField0_:I
       4: iconst_1
       5: iand
       6: iconst_1
       7: if_icmpne     14
      10: iconst_1
      11: goto          15
      14: iconst_0
      15: ireturn

  public int getCallId();
    Code:
       0: aload_0
       1: getfield      #22                 // Field callId_:I
       4: ireturn

  public org.apache.hadoop.hbase.protobuf.generated.RPCProtos$RequestHeader$Builder setCallId(int);
    Code:
       0: aload_0
       1: dup
       2: getfield      #23                 // Field bitField0_:I
       5: iconst_1
       6: ior
       7: putfield      #23                 // Field bitField0_:I
      10: aload_0
      11: iload_1
      12: putfield      #22                 // Field callId_:I
      15: aload_0
      16: invokevirtual #57                 // Method onChanged:()V
      19: aload_0
      20: areturn

  public org.apache.hadoop.hbase.protobuf.generated.RPCProtos$RequestHeader$Builder clearCallId();
    Code:
       0: aload_0
       1: aload_0
       2: getfield      #23                 // Field bitField0_:I
       5: bipush        -2
       7: iand
       8: putfield      #23                 // Field bitField0_:I
      11: aload_0
      12: iconst_0
      13: putfield      #22                 // Field callId_:I
      16: aload_0
      17: invokevirtual #57                 // Method onChanged:()V
      20: aload_0
      21: areturn

  public boolean hasTraceInfo();
    Code:
       0: aload_0
       1: getfield      #23                 // Field bitField0_:I
       4: iconst_2
       5: iand
       6: iconst_2
       7: if_icmpne     14
      10: iconst_1
      11: goto          15
      14: iconst_0
      15: ireturn

  public org.apache.hadoop.hbase.protobuf.generated.TracingProtos$RPCTInfo getTraceInfo();
    Code:
       0: aload_0
       1: getfield      #24                 // Field traceInfoBuilder_:Lcom/google/protobuf/SingleFieldBuilder;
       4: ifnonnull     12
       7: aload_0
       8: getfield      #10                 // Field traceInfo_:Lorg/apache/hadoop/hbase/protobuf/generated/TracingProtos$RPCTInfo;
      11: areturn
      12: aload_0
      13: getfield      #24                 // Field traceInfoBuilder_:Lcom/google/protobuf/SingleFieldBuilder;
      16: invokevirtual #76                 // Method com/google/protobuf/SingleFieldBuilder.getMessage:()Lcom/google/protobuf/GeneratedMessage;
      19: checkcast     #39                 // class org/apache/hadoop/hbase/protobuf/generated/TracingProtos$RPCTInfo
      22: areturn

  public org.apache.hadoop.hbase.protobuf.generated.RPCProtos$RequestHeader$Builder setTraceInfo(org.apache.hadoop.hbase.protobuf.generated.TracingProtos$RPCTInfo);
    Code:
       0: aload_0
       1: getfield      #24                 // Field traceInfoBuilder_:Lcom/google/protobuf/SingleFieldBuilder;
       4: ifnonnull     31
       7: aload_1
       8: ifnonnull     19
      11: new           #77                 // class java/lang/NullPointerException
      14: dup
      15: invokespecial #78                 // Method java/lang/NullPointerException."<init>":()V
      18: athrow
      19: aload_0
      20: aload_1
      21: putfield      #10                 // Field traceInfo_:Lorg/apache/hadoop/hbase/protobuf/generated/TracingProtos$RPCTInfo;
      24: aload_0
      25: invokevirtual #57                 // Method onChanged:()V
      28: goto          40
      31: aload_0
      32: getfield      #24                 // Field traceInfoBuilder_:Lcom/google/protobuf/SingleFieldBuilder;
      35: aload_1
      36: invokevirtual #79                 // Method com/google/protobuf/SingleFieldBuilder.setMessage:(Lcom/google/protobuf/GeneratedMessage;)Lcom/google/protobuf/SingleFieldBuilder;
      39: pop
      40: aload_0
      41: dup
      42: getfield      #23                 // Field bitField0_:I
      45: iconst_2
      46: ior
      47: putfield      #23                 // Field bitField0_:I
      50: aload_0
      51: areturn

  public org.apache.hadoop.hbase.protobuf.generated.RPCProtos$RequestHeader$Builder setTraceInfo(org.apache.hadoop.hbase.protobuf.generated.TracingProtos$RPCTInfo$Builder);
    Code:
       0: aload_0
       1: getfield      #24                 // Field traceInfoBuilder_:Lcom/google/protobuf/SingleFieldBuilder;
       4: ifnonnull     22
       7: aload_0
       8: aload_1
       9: invokevirtual #80                 // Method org/apache/hadoop/hbase/protobuf/generated/TracingProtos$RPCTInfo$Builder.build:()Lorg/apache/hadoop/hbase/protobuf/generated/TracingProtos$RPCTInfo;
      12: putfield      #10                 // Field traceInfo_:Lorg/apache/hadoop/hbase/protobuf/generated/TracingProtos$RPCTInfo;
      15: aload_0
      16: invokevirtual #57                 // Method onChanged:()V
      19: goto          34
      22: aload_0
      23: getfield      #24                 // Field traceInfoBuilder_:Lcom/google/protobuf/SingleFieldBuilder;
      26: aload_1
      27: invokevirtual #80                 // Method org/apache/hadoop/hbase/protobuf/generated/TracingProtos$RPCTInfo$Builder.build:()Lorg/apache/hadoop/hbase/protobuf/generated/TracingProtos$RPCTInfo;
      30: invokevirtual #79                 // Method com/google/protobuf/SingleFieldBuilder.setMessage:(Lcom/google/protobuf/GeneratedMessage;)Lcom/google/protobuf/SingleFieldBuilder;
      33: pop
      34: aload_0
      35: dup
      36: getfield      #23                 // Field bitField0_:I
      39: iconst_2
      40: ior
      41: putfield      #23                 // Field bitField0_:I
      44: aload_0
      45: areturn

  public org.apache.hadoop.hbase.protobuf.generated.RPCProtos$RequestHeader$Builder mergeTraceInfo(org.apache.hadoop.hbase.protobuf.generated.TracingProtos$RPCTInfo);
    Code:
       0: aload_0
       1: getfield      #24                 // Field traceInfoBuilder_:Lcom/google/protobuf/SingleFieldBuilder;
       4: ifnonnull     60
       7: aload_0
       8: getfield      #23                 // Field bitField0_:I
      11: iconst_2
      12: iand
      13: iconst_2
      14: if_icmpne     48
      17: aload_0
      18: getfield      #10                 // Field traceInfo_:Lorg/apache/hadoop/hbase/protobuf/generated/TracingProtos$RPCTInfo;
      21: invokestatic  #9                  // Method org/apache/hadoop/hbase/protobuf/generated/TracingProtos$RPCTInfo.getDefaultInstance:()Lorg/apache/hadoop/hbase/protobuf/generated/TracingProtos$RPCTInfo;
      24: if_acmpeq     48
      27: aload_0
      28: aload_0
      29: getfield      #10                 // Field traceInfo_:Lorg/apache/hadoop/hbase/protobuf/generated/TracingProtos$RPCTInfo;
      32: invokestatic  #81                 // Method org/apache/hadoop/hbase/protobuf/generated/TracingProtos$RPCTInfo.newBuilder:(Lorg/apache/hadoop/hbase/protobuf/generated/TracingProtos$RPCTInfo;)Lorg/apache/hadoop/hbase/protobuf/generated/TracingProtos$RPCTInfo$Builder;
      35: aload_1
      36: invokevirtual #82                 // Method org/apache/hadoop/hbase/protobuf/generated/TracingProtos$RPCTInfo$Builder.mergeFrom:(Lorg/apache/hadoop/hbase/protobuf/generated/TracingProtos$RPCTInfo;)Lorg/apache/hadoop/hbase/protobuf/generated/TracingProtos$RPCTInfo$Builder;
      39: invokevirtual #83                 // Method org/apache/hadoop/hbase/protobuf/generated/TracingProtos$RPCTInfo$Builder.buildPartial:()Lorg/apache/hadoop/hbase/protobuf/generated/TracingProtos$RPCTInfo;
      42: putfield      #10                 // Field traceInfo_:Lorg/apache/hadoop/hbase/protobuf/generated/TracingProtos$RPCTInfo;
      45: goto          53
      48: aload_0
      49: aload_1
      50: putfield      #10                 // Field traceInfo_:Lorg/apache/hadoop/hbase/protobuf/generated/TracingProtos$RPCTInfo;
      53: aload_0
      54: invokevirtual #57                 // Method onChanged:()V
      57: goto          69
      60: aload_0
      61: getfield      #24                 // Field traceInfoBuilder_:Lcom/google/protobuf/SingleFieldBuilder;
      64: aload_1
      65: invokevirtual #84                 // Method com/google/protobuf/SingleFieldBuilder.mergeFrom:(Lcom/google/protobuf/GeneratedMessage;)Lcom/google/protobuf/SingleFieldBuilder;
      68: pop
      69: aload_0
      70: dup
      71: getfield      #23                 // Field bitField0_:I
      74: iconst_2
      75: ior
      76: putfield      #23                 // Field bitField0_:I
      79: aload_0
      80: areturn

  public org.apache.hadoop.hbase.protobuf.generated.RPCProtos$RequestHeader$Builder clearTraceInfo();
    Code:
       0: aload_0
       1: getfield      #24                 // Field traceInfoBuilder_:Lcom/google/protobuf/SingleFieldBuilder;
       4: ifnonnull     21
       7: aload_0
       8: invokestatic  #9                  // Method org/apache/hadoop/hbase/protobuf/generated/TracingProtos$RPCTInfo.getDefaultInstance:()Lorg/apache/hadoop/hbase/protobuf/generated/TracingProtos$RPCTInfo;
      11: putfield      #10                 // Field traceInfo_:Lorg/apache/hadoop/hbase/protobuf/generated/TracingProtos$RPCTInfo;
      14: aload_0
      15: invokevirtual #57                 // Method onChanged:()V
      18: goto          29
      21: aload_0
      22: getfield      #24                 // Field traceInfoBuilder_:Lcom/google/protobuf/SingleFieldBuilder;
      25: invokevirtual #25                 // Method com/google/protobuf/SingleFieldBuilder.clear:()Lcom/google/protobuf/SingleFieldBuilder;
      28: pop
      29: aload_0
      30: aload_0
      31: getfield      #23                 // Field bitField0_:I
      34: bipush        -3
      36: iand
      37: putfield      #23                 // Field bitField0_:I
      40: aload_0
      41: areturn

  public org.apache.hadoop.hbase.protobuf.generated.TracingProtos$RPCTInfo$Builder getTraceInfoBuilder();
    Code:
       0: aload_0
       1: dup
       2: getfield      #23                 // Field bitField0_:I
       5: iconst_2
       6: ior
       7: putfield      #23                 // Field bitField0_:I
      10: aload_0
      11: invokevirtual #57                 // Method onChanged:()V
      14: aload_0
      15: invokespecial #18                 // Method getTraceInfoFieldBuilder:()Lcom/google/protobuf/SingleFieldBuilder;
      18: invokevirtual #85                 // Method com/google/protobuf/SingleFieldBuilder.getBuilder:()Lcom/google/protobuf/GeneratedMessage$Builder;
      21: checkcast     #86                 // class org/apache/hadoop/hbase/protobuf/generated/TracingProtos$RPCTInfo$Builder
      24: areturn

  public org.apache.hadoop.hbase.protobuf.generated.TracingProtos$RPCTInfoOrBuilder getTraceInfoOrBuilder();
    Code:
       0: aload_0
       1: getfield      #24                 // Field traceInfoBuilder_:Lcom/google/protobuf/SingleFieldBuilder;
       4: ifnull        18
       7: aload_0
       8: getfield      #24                 // Field traceInfoBuilder_:Lcom/google/protobuf/SingleFieldBuilder;
      11: invokevirtual #87                 // Method com/google/protobuf/SingleFieldBuilder.getMessageOrBuilder:()Lcom/google/protobuf/MessageOrBuilder;
      14: checkcast     #88                 // class org/apache/hadoop/hbase/protobuf/generated/TracingProtos$RPCTInfoOrBuilder
      17: areturn
      18: aload_0
      19: getfield      #10                 // Field traceInfo_:Lorg/apache/hadoop/hbase/protobuf/generated/TracingProtos$RPCTInfo;
      22: areturn

  public boolean hasMethodName();
    Code:
       0: aload_0
       1: getfield      #23                 // Field bitField0_:I
       4: iconst_4
       5: iand
       6: iconst_4
       7: if_icmpne     14
      10: iconst_1
      11: goto          15
      14: iconst_0
      15: ireturn

  public java.lang.String getMethodName();
    Code:
       0: aload_0
       1: getfield      #12                 // Field methodName_:Ljava/lang/Object;
       4: astore_1
       5: aload_1
       6: instanceof    #93                 // class java/lang/String
       9: ifne          27
      12: aload_1
      13: checkcast     #94                 // class com/google/protobuf/ByteString
      16: invokevirtual #95                 // Method com/google/protobuf/ByteString.toStringUtf8:()Ljava/lang/String;
      19: astore_2
      20: aload_0
      21: aload_2
      22: putfield      #12                 // Field methodName_:Ljava/lang/Object;
      25: aload_2
      26: areturn
      27: aload_1
      28: checkcast     #93                 // class java/lang/String
      31: areturn

  public com.google.protobuf.ByteString getMethodNameBytes();
    Code:
       0: aload_0
       1: getfield      #12                 // Field methodName_:Ljava/lang/Object;
       4: astore_1
       5: aload_1
       6: instanceof    #93                 // class java/lang/String
       9: ifeq          27
      12: aload_1
      13: checkcast     #93                 // class java/lang/String
      16: invokestatic  #96                 // Method com/google/protobuf/ByteString.copyFromUtf8:(Ljava/lang/String;)Lcom/google/protobuf/ByteString;
      19: astore_2
      20: aload_0
      21: aload_2
      22: putfield      #12                 // Field methodName_:Ljava/lang/Object;
      25: aload_2
      26: areturn
      27: aload_1
      28: checkcast     #94                 // class com/google/protobuf/ByteString
      31: areturn

  public org.apache.hadoop.hbase.protobuf.generated.RPCProtos$RequestHeader$Builder setMethodName(java.lang.String);
    Code:
       0: aload_1
       1: ifnonnull     12
       4: new           #77                 // class java/lang/NullPointerException
       7: dup
       8: invokespecial #78                 // Method java/lang/NullPointerException."<init>":()V
      11: athrow
      12: aload_0
      13: dup
      14: getfield      #23                 // Field bitField0_:I
      17: iconst_4
      18: ior
      19: putfield      #23                 // Field bitField0_:I
      22: aload_0
      23: aload_1
      24: putfield      #12                 // Field methodName_:Ljava/lang/Object;
      27: aload_0
      28: invokevirtual #57                 // Method onChanged:()V
      31: aload_0
      32: areturn

  public org.apache.hadoop.hbase.protobuf.generated.RPCProtos$RequestHeader$Builder clearMethodName();
    Code:
       0: aload_0
       1: aload_0
       2: getfield      #23                 // Field bitField0_:I
       5: bipush        -5
       7: iand
       8: putfield      #23                 // Field bitField0_:I
      11: aload_0
      12: invokestatic  #32                 // Method org/apache/hadoop/hbase/protobuf/generated/RPCProtos$RequestHeader.getDefaultInstance:()Lorg/apache/hadoop/hbase/protobuf/generated/RPCProtos$RequestHeader;
      15: invokevirtual #97                 // Method org/apache/hadoop/hbase/protobuf/generated/RPCProtos$RequestHeader.getMethodName:()Ljava/lang/String;
      18: putfield      #12                 // Field methodName_:Ljava/lang/Object;
      21: aload_0
      22: invokevirtual #57                 // Method onChanged:()V
      25: aload_0
      26: areturn

  public org.apache.hadoop.hbase.protobuf.generated.RPCProtos$RequestHeader$Builder setMethodNameBytes(com.google.protobuf.ByteString);
    Code:
       0: aload_1
       1: ifnonnull     12
       4: new           #77                 // class java/lang/NullPointerException
       7: dup
       8: invokespecial #78                 // Method java/lang/NullPointerException."<init>":()V
      11: athrow
      12: aload_0
      13: dup
      14: getfield      #23                 // Field bitField0_:I
      17: iconst_4
      18: ior
      19: putfield      #23                 // Field bitField0_:I
      22: aload_0
      23: aload_1
      24: putfield      #12                 // Field methodName_:Ljava/lang/Object;
      27: aload_0
      28: invokevirtual #57                 // Method onChanged:()V
      31: aload_0
      32: areturn

  public boolean hasRequestParam();
    Code:
       0: aload_0
       1: getfield      #23                 // Field bitField0_:I
       4: bipush        8
       6: iand
       7: bipush        8
       9: if_icmpne     16
      12: iconst_1
      13: goto          17
      16: iconst_0
      17: ireturn

  public boolean getRequestParam();
    Code:
       0: aload_0
       1: getfield      #26                 // Field requestParam_:Z
       4: ireturn

  public org.apache.hadoop.hbase.protobuf.generated.RPCProtos$RequestHeader$Builder setRequestParam(boolean);
    Code:
       0: aload_0
       1: dup
       2: getfield      #23                 // Field bitField0_:I
       5: bipush        8
       7: ior
       8: putfield      #23                 // Field bitField0_:I
      11: aload_0
      12: iload_1
      13: putfield      #26                 // Field requestParam_:Z
      16: aload_0
      17: invokevirtual #57                 // Method onChanged:()V
      20: aload_0
      21: areturn

  public org.apache.hadoop.hbase.protobuf.generated.RPCProtos$RequestHeader$Builder clearRequestParam();
    Code:
       0: aload_0
       1: aload_0
       2: getfield      #23                 // Field bitField0_:I
       5: bipush        -9
       7: iand
       8: putfield      #23                 // Field bitField0_:I
      11: aload_0
      12: iconst_0
      13: putfield      #26                 // Field requestParam_:Z
      16: aload_0
      17: invokevirtual #57                 // Method onChanged:()V
      20: aload_0
      21: areturn

  public boolean hasCellBlockMeta();
    Code:
       0: aload_0
       1: getfield      #23                 // Field bitField0_:I
       4: bipush        16
       6: iand
       7: bipush        16
       9: if_icmpne     16
      12: iconst_1
      13: goto          17
      16: iconst_0
      17: ireturn

  public org.apache.hadoop.hbase.protobuf.generated.RPCProtos$CellBlockMeta getCellBlockMeta();
    Code:
       0: aload_0
       1: getfield      #27                 // Field cellBlockMetaBuilder_:Lcom/google/protobuf/SingleFieldBuilder;
       4: ifnonnull     12
       7: aload_0
       8: getfield      #14                 // Field cellBlockMeta_:Lorg/apache/hadoop/hbase/protobuf/generated/RPCProtos$CellBlockMeta;
      11: areturn
      12: aload_0
      13: getfield      #27                 // Field cellBlockMetaBuilder_:Lcom/google/protobuf/SingleFieldBuilder;
      16: invokevirtual #76                 // Method com/google/protobuf/SingleFieldBuilder.getMessage:()Lcom/google/protobuf/GeneratedMessage;
      19: checkcast     #43                 // class org/apache/hadoop/hbase/protobuf/generated/RPCProtos$CellBlockMeta
      22: areturn

  public org.apache.hadoop.hbase.protobuf.generated.RPCProtos$RequestHeader$Builder setCellBlockMeta(org.apache.hadoop.hbase.protobuf.generated.RPCProtos$CellBlockMeta);
    Code:
       0: aload_0
       1: getfield      #27                 // Field cellBlockMetaBuilder_:Lcom/google/protobuf/SingleFieldBuilder;
       4: ifnonnull     31
       7: aload_1
       8: ifnonnull     19
      11: new           #77                 // class java/lang/NullPointerException
      14: dup
      15: invokespecial #78                 // Method java/lang/NullPointerException."<init>":()V
      18: athrow
      19: aload_0
      20: aload_1
      21: putfield      #14                 // Field cellBlockMeta_:Lorg/apache/hadoop/hbase/protobuf/generated/RPCProtos$CellBlockMeta;
      24: aload_0
      25: invokevirtual #57                 // Method onChanged:()V
      28: goto          40
      31: aload_0
      32: getfield      #27                 // Field cellBlockMetaBuilder_:Lcom/google/protobuf/SingleFieldBuilder;
      35: aload_1
      36: invokevirtual #79                 // Method com/google/protobuf/SingleFieldBuilder.setMessage:(Lcom/google/protobuf/GeneratedMessage;)Lcom/google/protobuf/SingleFieldBuilder;
      39: pop
      40: aload_0
      41: dup
      42: getfield      #23                 // Field bitField0_:I
      45: bipush        16
      47: ior
      48: putfield      #23                 // Field bitField0_:I
      51: aload_0
      52: areturn

  public org.apache.hadoop.hbase.protobuf.generated.RPCProtos$RequestHeader$Builder setCellBlockMeta(org.apache.hadoop.hbase.protobuf.generated.RPCProtos$CellBlockMeta$Builder);
    Code:
       0: aload_0
       1: getfield      #27                 // Field cellBlockMetaBuilder_:Lcom/google/protobuf/SingleFieldBuilder;
       4: ifnonnull     22
       7: aload_0
       8: aload_1
       9: invokevirtual #98                 // Method org/apache/hadoop/hbase/protobuf/generated/RPCProtos$CellBlockMeta$Builder.build:()Lorg/apache/hadoop/hbase/protobuf/generated/RPCProtos$CellBlockMeta;
      12: putfield      #14                 // Field cellBlockMeta_:Lorg/apache/hadoop/hbase/protobuf/generated/RPCProtos$CellBlockMeta;
      15: aload_0
      16: invokevirtual #57                 // Method onChanged:()V
      19: goto          34
      22: aload_0
      23: getfield      #27                 // Field cellBlockMetaBuilder_:Lcom/google/protobuf/SingleFieldBuilder;
      26: aload_1
      27: invokevirtual #98                 // Method org/apache/hadoop/hbase/protobuf/generated/RPCProtos$CellBlockMeta$Builder.build:()Lorg/apache/hadoop/hbase/protobuf/generated/RPCProtos$CellBlockMeta;
      30: invokevirtual #79                 // Method com/google/protobuf/SingleFieldBuilder.setMessage:(Lcom/google/protobuf/GeneratedMessage;)Lcom/google/protobuf/SingleFieldBuilder;
      33: pop
      34: aload_0
      35: dup
      36: getfield      #23                 // Field bitField0_:I
      39: bipush        16
      41: ior
      42: putfield      #23                 // Field bitField0_:I
      45: aload_0
      46: areturn

  public org.apache.hadoop.hbase.protobuf.generated.RPCProtos$RequestHeader$Builder mergeCellBlockMeta(org.apache.hadoop.hbase.protobuf.generated.RPCProtos$CellBlockMeta);
    Code:
       0: aload_0
       1: getfield      #27                 // Field cellBlockMetaBuilder_:Lcom/google/protobuf/SingleFieldBuilder;
       4: ifnonnull     62
       7: aload_0
       8: getfield      #23                 // Field bitField0_:I
      11: bipush        16
      13: iand
      14: bipush        16
      16: if_icmpne     50
      19: aload_0
      20: getfield      #14                 // Field cellBlockMeta_:Lorg/apache/hadoop/hbase/protobuf/generated/RPCProtos$CellBlockMeta;
      23: invokestatic  #13                 // Method org/apache/hadoop/hbase/protobuf/generated/RPCProtos$CellBlockMeta.getDefaultInstance:()Lorg/apache/hadoop/hbase/protobuf/generated/RPCProtos$CellBlockMeta;
      26: if_acmpeq     50
      29: aload_0
      30: aload_0
      31: getfield      #14                 // Field cellBlockMeta_:Lorg/apache/hadoop/hbase/protobuf/generated/RPCProtos$CellBlockMeta;
      34: invokestatic  #99                 // Method org/apache/hadoop/hbase/protobuf/generated/RPCProtos$CellBlockMeta.newBuilder:(Lorg/apache/hadoop/hbase/protobuf/generated/RPCProtos$CellBlockMeta;)Lorg/apache/hadoop/hbase/protobuf/generated/RPCProtos$CellBlockMeta$Builder;
      37: aload_1
      38: invokevirtual #100                // Method org/apache/hadoop/hbase/protobuf/generated/RPCProtos$CellBlockMeta$Builder.mergeFrom:(Lorg/apache/hadoop/hbase/protobuf/generated/RPCProtos$CellBlockMeta;)Lorg/apache/hadoop/hbase/protobuf/generated/RPCProtos$CellBlockMeta$Builder;
      41: invokevirtual #101                // Method org/apache/hadoop/hbase/protobuf/generated/RPCProtos$CellBlockMeta$Builder.buildPartial:()Lorg/apache/hadoop/hbase/protobuf/generated/RPCProtos$CellBlockMeta;
      44: putfield      #14                 // Field cellBlockMeta_:Lorg/apache/hadoop/hbase/protobuf/generated/RPCProtos$CellBlockMeta;
      47: goto          55
      50: aload_0
      51: aload_1
      52: putfield      #14                 // Field cellBlockMeta_:Lorg/apache/hadoop/hbase/protobuf/generated/RPCProtos$CellBlockMeta;
      55: aload_0
      56: invokevirtual #57                 // Method onChanged:()V
      59: goto          71
      62: aload_0
      63: getfield      #27                 // Field cellBlockMetaBuilder_:Lcom/google/protobuf/SingleFieldBuilder;
      66: aload_1
      67: invokevirtual #84                 // Method com/google/protobuf/SingleFieldBuilder.mergeFrom:(Lcom/google/protobuf/GeneratedMessage;)Lcom/google/protobuf/SingleFieldBuilder;
      70: pop
      71: aload_0
      72: dup
      73: getfield      #23                 // Field bitField0_:I
      76: bipush        16
      78: ior
      79: putfield      #23                 // Field bitField0_:I
      82: aload_0
      83: areturn

  public org.apache.hadoop.hbase.protobuf.generated.RPCProtos$RequestHeader$Builder clearCellBlockMeta();
    Code:
       0: aload_0
       1: getfield      #27                 // Field cellBlockMetaBuilder_:Lcom/google/protobuf/SingleFieldBuilder;
       4: ifnonnull     21
       7: aload_0
       8: invokestatic  #13                 // Method org/apache/hadoop/hbase/protobuf/generated/RPCProtos$CellBlockMeta.getDefaultInstance:()Lorg/apache/hadoop/hbase/protobuf/generated/RPCProtos$CellBlockMeta;
      11: putfield      #14                 // Field cellBlockMeta_:Lorg/apache/hadoop/hbase/protobuf/generated/RPCProtos$CellBlockMeta;
      14: aload_0
      15: invokevirtual #57                 // Method onChanged:()V
      18: goto          29
      21: aload_0
      22: getfield      #27                 // Field cellBlockMetaBuilder_:Lcom/google/protobuf/SingleFieldBuilder;
      25: invokevirtual #25                 // Method com/google/protobuf/SingleFieldBuilder.clear:()Lcom/google/protobuf/SingleFieldBuilder;
      28: pop
      29: aload_0
      30: aload_0
      31: getfield      #23                 // Field bitField0_:I
      34: bipush        -17
      36: iand
      37: putfield      #23                 // Field bitField0_:I
      40: aload_0
      41: areturn

  public org.apache.hadoop.hbase.protobuf.generated.RPCProtos$CellBlockMeta$Builder getCellBlockMetaBuilder();
    Code:
       0: aload_0
       1: dup
       2: getfield      #23                 // Field bitField0_:I
       5: bipush        16
       7: ior
       8: putfield      #23                 // Field bitField0_:I
      11: aload_0
      12: invokevirtual #57                 // Method onChanged:()V
      15: aload_0
      16: invokespecial #19                 // Method getCellBlockMetaFieldBuilder:()Lcom/google/protobuf/SingleFieldBuilder;
      19: invokevirtual #85                 // Method com/google/protobuf/SingleFieldBuilder.getBuilder:()Lcom/google/protobuf/GeneratedMessage$Builder;
      22: checkcast     #102                // class org/apache/hadoop/hbase/protobuf/generated/RPCProtos$CellBlockMeta$Builder
      25: areturn

  public org.apache.hadoop.hbase.protobuf.generated.RPCProtos$CellBlockMetaOrBuilder getCellBlockMetaOrBuilder();
    Code:
       0: aload_0
       1: getfield      #27                 // Field cellBlockMetaBuilder_:Lcom/google/protobuf/SingleFieldBuilder;
       4: ifnull        18
       7: aload_0
       8: getfield      #27                 // Field cellBlockMetaBuilder_:Lcom/google/protobuf/SingleFieldBuilder;
      11: invokevirtual #87                 // Method com/google/protobuf/SingleFieldBuilder.getMessageOrBuilder:()Lcom/google/protobuf/MessageOrBuilder;
      14: checkcast     #103                // class org/apache/hadoop/hbase/protobuf/generated/RPCProtos$CellBlockMetaOrBuilder
      17: areturn
      18: aload_0
      19: getfield      #14                 // Field cellBlockMeta_:Lorg/apache/hadoop/hbase/protobuf/generated/RPCProtos$CellBlockMeta;
      22: areturn

  public boolean hasPriority();
    Code:
       0: aload_0
       1: getfield      #23                 // Field bitField0_:I
       4: bipush        32
       6: iand
       7: bipush        32
       9: if_icmpne     16
      12: iconst_1
      13: goto          17
      16: iconst_0
      17: ireturn

  public int getPriority();
    Code:
       0: aload_0
       1: getfield      #28                 // Field priority_:I
       4: ireturn

  public org.apache.hadoop.hbase.protobuf.generated.RPCProtos$RequestHeader$Builder setPriority(int);
    Code:
       0: aload_0
       1: dup
       2: getfield      #23                 // Field bitField0_:I
       5: bipush        32
       7: ior
       8: putfield      #23                 // Field bitField0_:I
      11: aload_0
      12: iload_1
      13: putfield      #28                 // Field priority_:I
      16: aload_0
      17: invokevirtual #57                 // Method onChanged:()V
      20: aload_0
      21: areturn

  public org.apache.hadoop.hbase.protobuf.generated.RPCProtos$RequestHeader$Builder clearPriority();
    Code:
       0: aload_0
       1: aload_0
       2: getfield      #23                 // Field bitField0_:I
       5: bipush        -33
       7: iand
       8: putfield      #23                 // Field bitField0_:I
      11: aload_0
      12: iconst_0
      13: putfield      #28                 // Field priority_:I
      16: aload_0
      17: invokevirtual #57                 // Method onChanged:()V
      20: aload_0
      21: areturn

  public boolean hasTimeout();
    Code:
       0: aload_0
       1: getfield      #23                 // Field bitField0_:I
       4: bipush        64
       6: iand
       7: bipush        64
       9: if_icmpne     16
      12: iconst_1
      13: goto          17
      16: iconst_0
      17: ireturn

  public int getTimeout();
    Code:
       0: aload_0
       1: getfield      #29                 // Field timeout_:I
       4: ireturn

  public org.apache.hadoop.hbase.protobuf.generated.RPCProtos$RequestHeader$Builder setTimeout(int);
    Code:
       0: aload_0
       1: dup
       2: getfield      #23                 // Field bitField0_:I
       5: bipush        64
       7: ior
       8: putfield      #23                 // Field bitField0_:I
      11: aload_0
      12: iload_1
      13: putfield      #29                 // Field timeout_:I
      16: aload_0
      17: invokevirtual #57                 // Method onChanged:()V
      20: aload_0
      21: areturn

  public org.apache.hadoop.hbase.protobuf.generated.RPCProtos$RequestHeader$Builder clearTimeout();
    Code:
       0: aload_0
       1: aload_0
       2: getfield      #23                 // Field bitField0_:I
       5: bipush        -65
       7: iand
       8: putfield      #23                 // Field bitField0_:I
      11: aload_0
      12: iconst_0
      13: putfield      #29                 // Field timeout_:I
      16: aload_0
      17: invokevirtual #57                 // Method onChanged:()V
      20: aload_0
      21: areturn

  public com.google.protobuf.GeneratedMessage$Builder clear();
    Code:
       0: aload_0
       1: invokevirtual #104                // Method clear:()Lorg/apache/hadoop/hbase/protobuf/generated/RPCProtos$RequestHeader$Builder;
       4: areturn

  public com.google.protobuf.GeneratedMessage$Builder clone();
    Code:
       0: aload_0
       1: invokevirtual #105                // Method clone:()Lorg/apache/hadoop/hbase/protobuf/generated/RPCProtos$RequestHeader$Builder;
       4: areturn

  public com.google.protobuf.AbstractMessage$Builder mergeFrom(com.google.protobuf.CodedInputStream, com.google.protobuf.ExtensionRegistryLite) throws java.io.IOException;
    Code:
       0: aload_0
       1: aload_1
       2: aload_2
       3: invokevirtual #106                // Method mergeFrom:(Lcom/google/protobuf/CodedInputStream;Lcom/google/protobuf/ExtensionRegistryLite;)Lorg/apache/hadoop/hbase/protobuf/generated/RPCProtos$RequestHeader$Builder;
       6: areturn

  public com.google.protobuf.AbstractMessage$Builder mergeFrom(com.google.protobuf.Message);
    Code:
       0: aload_0
       1: aload_1
       2: invokevirtual #107                // Method mergeFrom:(Lcom/google/protobuf/Message;)Lorg/apache/hadoop/hbase/protobuf/generated/RPCProtos$RequestHeader$Builder;
       5: areturn

  public com.google.protobuf.AbstractMessage$Builder clear();
    Code:
       0: aload_0
       1: invokevirtual #104                // Method clear:()Lorg/apache/hadoop/hbase/protobuf/generated/RPCProtos$RequestHeader$Builder;
       4: areturn

  public com.google.protobuf.AbstractMessage$Builder clone();
    Code:
       0: aload_0
       1: invokevirtual #105                // Method clone:()Lorg/apache/hadoop/hbase/protobuf/generated/RPCProtos$RequestHeader$Builder;
       4: areturn

  public com.google.protobuf.Message$Builder mergeFrom(com.google.protobuf.CodedInputStream, com.google.protobuf.ExtensionRegistryLite) throws java.io.IOException;
    Code:
       0: aload_0
       1: aload_1
       2: aload_2
       3: invokevirtual #106                // Method mergeFrom:(Lcom/google/protobuf/CodedInputStream;Lcom/google/protobuf/ExtensionRegistryLite;)Lorg/apache/hadoop/hbase/protobuf/generated/RPCProtos$RequestHeader$Builder;
       6: areturn

  public com.google.protobuf.Message$Builder clone();
    Code:
       0: aload_0
       1: invokevirtual #105                // Method clone:()Lorg/apache/hadoop/hbase/protobuf/generated/RPCProtos$RequestHeader$Builder;
       4: areturn

  public com.google.protobuf.Message buildPartial();
    Code:
       0: aload_0
       1: invokevirtual #30                 // Method buildPartial:()Lorg/apache/hadoop/hbase/protobuf/generated/RPCProtos$RequestHeader;
       4: areturn

  public com.google.protobuf.Message build();
    Code:
       0: aload_0
       1: invokevirtual #108                // Method build:()Lorg/apache/hadoop/hbase/protobuf/generated/RPCProtos$RequestHeader;
       4: areturn

  public com.google.protobuf.Message$Builder mergeFrom(com.google.protobuf.Message);
    Code:
       0: aload_0
       1: aload_1
       2: invokevirtual #107                // Method mergeFrom:(Lcom/google/protobuf/Message;)Lorg/apache/hadoop/hbase/protobuf/generated/RPCProtos$RequestHeader$Builder;
       5: areturn

  public com.google.protobuf.Message$Builder clear();
    Code:
       0: aload_0
       1: invokevirtual #104                // Method clear:()Lorg/apache/hadoop/hbase/protobuf/generated/RPCProtos$RequestHeader$Builder;
       4: areturn

  public com.google.protobuf.MessageLite$Builder mergeFrom(com.google.protobuf.CodedInputStream, com.google.protobuf.ExtensionRegistryLite) throws java.io.IOException;
    Code:
       0: aload_0
       1: aload_1
       2: aload_2
       3: invokevirtual #106                // Method mergeFrom:(Lcom/google/protobuf/CodedInputStream;Lcom/google/protobuf/ExtensionRegistryLite;)Lorg/apache/hadoop/hbase/protobuf/generated/RPCProtos$RequestHeader$Builder;
       6: areturn

  public com.google.protobuf.MessageLite$Builder clone();
    Code:
       0: aload_0
       1: invokevirtual #105                // Method clone:()Lorg/apache/hadoop/hbase/protobuf/generated/RPCProtos$RequestHeader$Builder;
       4: areturn

  public com.google.protobuf.MessageLite buildPartial();
    Code:
       0: aload_0
       1: invokevirtual #30                 // Method buildPartial:()Lorg/apache/hadoop/hbase/protobuf/generated/RPCProtos$RequestHeader;
       4: areturn

  public com.google.protobuf.MessageLite build();
    Code:
       0: aload_0
       1: invokevirtual #108                // Method build:()Lorg/apache/hadoop/hbase/protobuf/generated/RPCProtos$RequestHeader;
       4: areturn

  public com.google.protobuf.MessageLite$Builder clear();
    Code:
       0: aload_0
       1: invokevirtual #104                // Method clear:()Lorg/apache/hadoop/hbase/protobuf/generated/RPCProtos$RequestHeader$Builder;
       4: areturn

  public com.google.protobuf.MessageLite getDefaultInstanceForType();
    Code:
       0: aload_0
       1: invokevirtual #109                // Method getDefaultInstanceForType:()Lorg/apache/hadoop/hbase/protobuf/generated/RPCProtos$RequestHeader;
       4: areturn

  public com.google.protobuf.Message getDefaultInstanceForType();
    Code:
       0: aload_0
       1: invokevirtual #109                // Method getDefaultInstanceForType:()Lorg/apache/hadoop/hbase/protobuf/generated/RPCProtos$RequestHeader;
       4: areturn

  public com.google.protobuf.AbstractMessageLite$Builder mergeFrom(com.google.protobuf.CodedInputStream, com.google.protobuf.ExtensionRegistryLite) throws java.io.IOException;
    Code:
       0: aload_0
       1: aload_1
       2: aload_2
       3: invokevirtual #106                // Method mergeFrom:(Lcom/google/protobuf/CodedInputStream;Lcom/google/protobuf/ExtensionRegistryLite;)Lorg/apache/hadoop/hbase/protobuf/generated/RPCProtos$RequestHeader$Builder;
       6: areturn

  public com.google.protobuf.AbstractMessageLite$Builder clone();
    Code:
       0: aload_0
       1: invokevirtual #105                // Method clone:()Lorg/apache/hadoop/hbase/protobuf/generated/RPCProtos$RequestHeader$Builder;
       4: areturn

  public java.lang.Object clone() throws java.lang.CloneNotSupportedException;
    Code:
       0: aload_0
       1: invokevirtual #105                // Method clone:()Lorg/apache/hadoop/hbase/protobuf/generated/RPCProtos$RequestHeader$Builder;
       4: areturn

  static org.apache.hadoop.hbase.protobuf.generated.RPCProtos$RequestHeader$Builder access$4800();
    Code:
       0: invokestatic  #2                  // Method create:()Lorg/apache/hadoop/hbase/protobuf/generated/RPCProtos$RequestHeader$Builder;
       3: areturn

  org.apache.hadoop.hbase.protobuf.generated.RPCProtos$RequestHeader$Builder(com.google.protobuf.GeneratedMessage$BuilderParent, org.apache.hadoop.hbase.protobuf.generated.RPCProtos$1);
    Code:
       0: aload_0
       1: aload_1
       2: invokespecial #1                  // Method "<init>":(Lcom/google/protobuf/GeneratedMessage$BuilderParent;)V
       5: return
}
