Compiled from "RpcThrottleStorage.java"
public class org.apache.hadoop.hbase.quotas.RpcThrottleStorage {
  public static final java.lang.String RPC_THROTTLE_ZNODE;

  public static final java.lang.String RPC_THROTTLE_ZNODE_DEFAULT;

  public org.apache.hadoop.hbase.quotas.RpcThrottleStorage(org.apache.hadoop.hbase.zookeeper.ZKWatcher, org.apache.hadoop.conf.Configuration);
    Code:
       0: aload_0
       1: invokespecial #1                  // Method java/lang/Object."<init>":()V
       4: aload_0
       5: aload_1
       6: putfield      #2                  // Field zookeeper:Lorg/apache/hadoop/hbase/zookeeper/ZKWatcher;
       9: aload_0
      10: aload_1
      11: invokevirtual #3                  // Method org/apache/hadoop/hbase/zookeeper/ZKWatcher.getZNodePaths:()Lorg/apache/hadoop/hbase/zookeeper/ZNodePaths;
      14: getfield      #4                  // Field org/apache/hadoop/hbase/zookeeper/ZNodePaths.baseZNode:Ljava/lang/String;
      17: aload_2
      18: ldc           #6                  // String zookeeper.znode.quota.rpc.throttle
      20: ldc           #7                  // String rpc-throttle
      22: invokevirtual #8                  // Method org/apache/hadoop/conf/Configuration.get:(Ljava/lang/String;Ljava/lang/String;)Ljava/lang/String;
      25: invokestatic  #9                  // Method org/apache/hadoop/hbase/zookeeper/ZNodePaths.joinZNode:(Ljava/lang/String;Ljava/lang/String;)Ljava/lang/String;
      28: putfield      #10                 // Field rpcThrottleZNode:Ljava/lang/String;
      31: return

  public boolean isRpcThrottleEnabled() throws java.io.IOException;
    Code:
       0: aload_0
       1: getfield      #2                  // Field zookeeper:Lorg/apache/hadoop/hbase/zookeeper/ZKWatcher;
       4: aload_0
       5: getfield      #10                 // Field rpcThrottleZNode:Ljava/lang/String;
       8: invokestatic  #11                 // Method org/apache/hadoop/hbase/zookeeper/ZKUtil.getData:(Lorg/apache/hadoop/hbase/zookeeper/ZKWatcher;Ljava/lang/String;)[B
      11: astore_1
      12: aload_1
      13: ifnull        23
      16: aload_1
      17: invokestatic  #12                 // Method org/apache/hadoop/hbase/util/Bytes.toBoolean:([B)Z
      20: ifeq          27
      23: iconst_1
      24: goto          28
      27: iconst_0
      28: ireturn
      29: astore_1
      30: new           #15                 // class java/io/IOException
      33: dup
      34: ldc           #16                 // String Failed to get rpc throttle
      36: aload_1
      37: invokespecial #17                 // Method java/io/IOException."<init>":(Ljava/lang/String;Ljava/lang/Throwable;)V
      40: athrow
    Exception table:
       from    to  target type
           0    28    29   Class org/apache/zookeeper/KeeperException
           0    28    29   Class java/lang/InterruptedException

  public void switchRpcThrottle(boolean) throws java.io.IOException;
    Code:
       0: iload_1
       1: invokestatic  #18                 // Method org/apache/hadoop/hbase/util/Bytes.toBytes:(Z)[B
       4: astore_2
       5: aload_0
       6: getfield      #2                  // Field zookeeper:Lorg/apache/hadoop/hbase/zookeeper/ZKWatcher;
       9: aload_0
      10: getfield      #10                 // Field rpcThrottleZNode:Ljava/lang/String;
      13: aload_2
      14: invokestatic  #19                 // Method org/apache/hadoop/hbase/zookeeper/ZKUtil.createSetData:(Lorg/apache/hadoop/hbase/zookeeper/ZKWatcher;Ljava/lang/String;[B)V
      17: goto          32
      20: astore_2
      21: new           #15                 // class java/io/IOException
      24: dup
      25: ldc           #20                 // String Failed to store rpc throttle
      27: aload_2
      28: invokespecial #17                 // Method java/io/IOException."<init>":(Ljava/lang/String;Ljava/lang/Throwable;)V
      31: athrow
      32: return
    Exception table:
       from    to  target type
           0    17    20   Class org/apache/zookeeper/KeeperException
}
