Compiled from "RSGroupListTmpl.java"
class org.apache.hadoop.hbase.tmpl.master.RSGroupListTmpl$1 extends org.jamon.AbstractRenderer {
  final org.apache.hadoop.hbase.master.HMaster val$master;

  final org.apache.hadoop.hbase.master.ServerManager val$serverManager;

  final org.apache.hadoop.hbase.tmpl.master.RSGroupListTmpl this$0;

  org.apache.hadoop.hbase.tmpl.master.RSGroupListTmpl$1(org.apache.hadoop.hbase.tmpl.master.RSGroupListTmpl, org.apache.hadoop.hbase.master.HMaster, org.apache.hadoop.hbase.master.ServerManager);
    Code:
       0: aload_0
       1: aload_1
       2: putfield      #1                  // Field this$0:Lorg/apache/hadoop/hbase/tmpl/master/RSGroupListTmpl;
       5: aload_0
       6: aload_2
       7: putfield      #2                  // Field val$master:Lorg/apache/hadoop/hbase/master/HMaster;
      10: aload_0
      11: aload_3
      12: putfield      #3                  // Field val$serverManager:Lorg/apache/hadoop/hbase/master/ServerManager;
      15: aload_0
      16: invokespecial #4                  // Method org/jamon/AbstractRenderer."<init>":()V
      19: return

  public void renderTo(java.io.Writer) throws java.io.IOException;
    Code:
       0: aload_0
       1: getfield      #1                  // Field this$0:Lorg/apache/hadoop/hbase/tmpl/master/RSGroupListTmpl;
       4: aload_1
       5: aload_0
       6: getfield      #2                  // Field val$master:Lorg/apache/hadoop/hbase/master/HMaster;
       9: aload_0
      10: getfield      #3                  // Field val$serverManager:Lorg/apache/hadoop/hbase/master/ServerManager;
      13: invokevirtual #5                  // Method org/apache/hadoop/hbase/tmpl/master/RSGroupListTmpl.render:(Ljava/io/Writer;Lorg/apache/hadoop/hbase/master/HMaster;Lorg/apache/hadoop/hbase/master/ServerManager;)V
      16: return
}
