Compiled from "rsgroup_jsp.java"
public final class org.apache.hadoop.hbase.generated.master.rsgroup_jsp extends org.apache.jasper.runtime.HttpJspBase implements org.apache.jasper.runtime.JspSourceDependent {
  public org.apache.hadoop.hbase.generated.master.rsgroup_jsp();
    Code:
       0: aload_0
       1: invokespecial #1                  // Method org/apache/jasper/runtime/HttpJspBase."<init>":()V
       4: return

  public java.util.List<java.lang.String> getDependants();
    Code:
       0: getstatic     #2                  // Field _jspx_dependants:Ljava/util/List;
       3: areturn

  public void _jspService(javax.servlet.http.HttpServletRequest, javax.servlet.http.HttpServletResponse) throws java.io.IOException, javax.servlet.ServletException;
    Code:
       0: aconst_null
       1: astore_3
       2: aconst_null
       3: astore        4
       5: aconst_null
       6: astore        5
       8: aconst_null
       9: astore        6
      11: aconst_null
      12: astore        7
      14: aload_0
      15: astore        8
      17: aconst_null
      18: astore        9
      20: aconst_null
      21: astore        10
      23: aload_2
      24: ldc           #3                  // String text/html;charset=UTF-8
      26: invokeinterface #4,  2            // InterfaceMethod javax/servlet/http/HttpServletResponse.setContentType:(Ljava/lang/String;)V
      31: getstatic     #5                  // Field _jspxFactory:Ljavax/servlet/jsp/JspFactory;
      34: aload_0
      35: aload_1
      36: aload_2
      37: aconst_null
      38: iconst_1
      39: sipush        8192
      42: iconst_1
      43: invokevirtual #6                  // Method javax/servlet/jsp/JspFactory.getPageContext:(Ljavax/servlet/Servlet;Ljavax/servlet/ServletRequest;Ljavax/servlet/ServletResponse;Ljava/lang/String;ZIZ)Ljavax/servlet/jsp/PageContext;
      46: astore_3
      47: aload_3
      48: astore        10
      50: aload_3
      51: invokevirtual #7                  // Method javax/servlet/jsp/PageContext.getServletContext:()Ljavax/servlet/ServletContext;
      54: astore        5
      56: aload_3
      57: invokevirtual #8                  // Method javax/servlet/jsp/PageContext.getServletConfig:()Ljavax/servlet/ServletConfig;
      60: astore        6
      62: aload_3
      63: invokevirtual #9                  // Method javax/servlet/jsp/PageContext.getSession:()Ljavax/servlet/http/HttpSession;
      66: astore        4
      68: aload_3
      69: invokevirtual #10                 // Method javax/servlet/jsp/PageContext.getOut:()Ljavax/servlet/jsp/JspWriter;
      72: astore        7
      74: aload         7
      76: astore        9
      78: aload_0
      79: aload         5
      81: ldc           #11                 // String com.sun.appserv.jsp.resource.injector
      83: invokeinterface #12,  2           // InterfaceMethod javax/servlet/ServletContext.getAttribute:(Ljava/lang/String;)Ljava/lang/Object;
      88: checkcast     #13                 // class org/glassfish/jsp/api/ResourceInjector
      91: putfield      #14                 // Field _jspx_resourceInjector:Lorg/glassfish/jsp/api/ResourceInjector;
      94: aload         7
      96: ldc           #15                 // String \n\n\n\n\n
      98: invokevirtual #16                 // Method javax/servlet/jsp/JspWriter.write:(Ljava/lang/String;)V
     101: aload_1
     102: ldc           #17                 // String name
     104: invokeinterface #18,  2           // InterfaceMethod javax/servlet/http/HttpServletRequest.getParameter:(Ljava/lang/String;)Ljava/lang/String;
     109: astore        11
     111: aload_3
     112: ldc           #19                 // String pageTitle
     114: new           #20                 // class java/lang/StringBuilder
     117: dup
     118: invokespecial #21                 // Method java/lang/StringBuilder."<init>":()V
     121: ldc           #22                 // String RSGroup:
     123: invokevirtual #23                 // Method java/lang/StringBuilder.append:(Ljava/lang/String;)Ljava/lang/StringBuilder;
     126: aload         11
     128: invokevirtual #23                 // Method java/lang/StringBuilder.append:(Ljava/lang/String;)Ljava/lang/StringBuilder;
     131: invokevirtual #24                 // Method java/lang/StringBuilder.toString:()Ljava/lang/String;
     134: invokevirtual #25                 // Method javax/servlet/jsp/PageContext.setAttribute:(Ljava/lang/String;Ljava/lang/Object;)V
     137: aload         7
     139: bipush        10
     141: invokevirtual #26                 // Method javax/servlet/jsp/JspWriter.write:(I)V
     144: aload_1
     145: aload_2
     146: new           #20                 // class java/lang/StringBuilder
     149: dup
     150: invokespecial #21                 // Method java/lang/StringBuilder."<init>":()V
     153: ldc           #27                 // String header.jsp?
     155: invokevirtual #23                 // Method java/lang/StringBuilder.append:(Ljava/lang/String;)Ljava/lang/StringBuilder;
     158: ldc           #19                 // String pageTitle
     160: aload_1
     161: invokeinterface #28,  1           // InterfaceMethod javax/servlet/http/HttpServletRequest.getCharacterEncoding:()Ljava/lang/String;
     166: invokestatic  #29                 // Method org/apache/jasper/runtime/JspRuntimeLibrary.URLEncode:(Ljava/lang/String;Ljava/lang/String;)Ljava/lang/String;
     169: invokevirtual #23                 // Method java/lang/StringBuilder.append:(Ljava/lang/String;)Ljava/lang/StringBuilder;
     172: ldc           #30                 // String =
     174: invokevirtual #23                 // Method java/lang/StringBuilder.append:(Ljava/lang/String;)Ljava/lang/StringBuilder;
     177: ldc           #31                 // String ${pageTitle}
     179: ldc           #32                 // class java/lang/String
     181: aload         10
     183: aconst_null
     184: invokestatic  #33                 // Method org/apache/jasper/runtime/PageContextImpl.evaluateExpression:(Ljava/lang/String;Ljava/lang/Class;Ljavax/servlet/jsp/PageContext;Lorg/apache/jasper/runtime/ProtectedFunctionMapper;)Ljava/lang/Object;
     187: checkcast     #32                 // class java/lang/String
     190: aload_1
     191: invokeinterface #28,  1           // InterfaceMethod javax/servlet/http/HttpServletRequest.getCharacterEncoding:()Ljava/lang/String;
     196: invokestatic  #29                 // Method org/apache/jasper/runtime/JspRuntimeLibrary.URLEncode:(Ljava/lang/String;Ljava/lang/String;)Ljava/lang/String;
     199: invokevirtual #23                 // Method java/lang/StringBuilder.append:(Ljava/lang/String;)Ljava/lang/StringBuilder;
     202: invokevirtual #24                 // Method java/lang/StringBuilder.toString:()Ljava/lang/String;
     205: aload         7
     207: iconst_0
     208: invokestatic  #34                 // Method org/apache/jasper/runtime/JspRuntimeLibrary.include:(Ljavax/servlet/ServletRequest;Ljavax/servlet/ServletResponse;Ljava/lang/String;Ljavax/servlet/jsp/JspWriter;Z)V
     211: aload         7
     213: ldc           #35                 // String \n<div class=\"container-fluid content\">\n
     215: invokevirtual #16                 // Method javax/servlet/jsp/JspWriter.write:(Ljava/lang/String;)V
     218: aload_0
     219: invokevirtual #36                 // Method getServletContext:()Ljavax/servlet/ServletContext;
     222: ldc           #38                 // String master
     224: invokeinterface #12,  2           // InterfaceMethod javax/servlet/ServletContext.getAttribute:(Ljava/lang/String;)Ljava/lang/Object;
     229: checkcast     #37                 // class org/apache/hadoop/hbase/master/HMaster
     232: astore        12
     234: aconst_null
     235: astore        13
     237: aload         12
     239: invokevirtual #39                 // Method org/apache/hadoop/hbase/master/HMaster.getConnection:()Lorg/apache/hadoop/hbase/client/Connection;
     242: invokestatic  #40                 // Method org/apache/hadoop/hbase/RSGroupTableAccessor.isRSGroupsEnabled:(Lorg/apache/hadoop/hbase/client/Connection;)Z
     245: ifne          275
     248: aload         7
     250: ldc           #41                 // String \n  <div class=\"row inner_header\">\n    <div class=\"page-header\">\n      <h1>RSGroups are not enabled</h1>\n    </div>\n  </div>\n
     252: invokevirtual #16                 // Method javax/servlet/jsp/JspWriter.write:(Ljava/lang/String;)V
     255: aload_1
     256: aload_2
     257: ldc           #42                 // String redirect.jsp
     259: aload         7
     261: iconst_0
     262: invokestatic  #34                 // Method org/apache/jasper/runtime/JspRuntimeLibrary.include:(Ljavax/servlet/ServletRequest;Ljavax/servlet/ServletResponse;Ljava/lang/String;Ljavax/servlet/jsp/JspWriter;Z)V
     265: aload         7
     267: bipush        10
     269: invokevirtual #26                 // Method javax/servlet/jsp/JspWriter.write:(I)V
     272: goto          3407
     275: aload         11
     277: ifnull        307
     280: aload         11
     282: invokevirtual #43                 // Method java/lang/String.isEmpty:()Z
     285: ifne          307
     288: aload         12
     290: invokevirtual #39                 // Method org/apache/hadoop/hbase/master/HMaster.getConnection:()Lorg/apache/hadoop/hbase/client/Connection;
     293: aload         11
     295: invokestatic  #44                 // Method org/apache/hadoop/hbase/util/Bytes.toBytes:(Ljava/lang/String;)[B
     298: invokestatic  #45                 // Method org/apache/hadoop/hbase/RSGroupTableAccessor.getRSGroupInfo:(Lorg/apache/hadoop/hbase/client/Connection;[B)Lorg/apache/hadoop/hbase/rsgroup/RSGroupInfo;
     301: dup
     302: astore        13
     304: ifnonnull     348
     307: aload         7
     309: ldc           #46                 // String \n  <div class=\"row inner_header\">\n    <div class=\"page-header\">\n      <h1>RSGroup:
     311: invokevirtual #16                 // Method javax/servlet/jsp/JspWriter.write:(Ljava/lang/String;)V
     314: aload         7
     316: aload         11
     318: invokevirtual #47                 // Method javax/servlet/jsp/JspWriter.print:(Ljava/lang/String;)V
     321: aload         7
     323: ldc           #48                 // String  does not exist</h1>\n    </div>\n  </div>\n
     325: invokevirtual #16                 // Method javax/servlet/jsp/JspWriter.write:(Ljava/lang/String;)V
     328: aload_1
     329: aload_2
     330: ldc           #42                 // String redirect.jsp
     332: aload         7
     334: iconst_0
     335: invokestatic  #34                 // Method org/apache/jasper/runtime/JspRuntimeLibrary.include:(Ljavax/servlet/ServletRequest;Ljavax/servlet/ServletResponse;Ljava/lang/String;Ljavax/servlet/jsp/JspWriter;Z)V
     338: aload         7
     340: bipush        10
     342: invokevirtual #26                 // Method javax/servlet/jsp/JspWriter.write:(I)V
     345: goto          3407
     348: new           #49                 // class java/util/ArrayList
     351: dup
     352: invokespecial #50                 // Method java/util/ArrayList."<init>":()V
     355: astore        14
     357: new           #49                 // class java/util/ArrayList
     360: dup
     361: invokespecial #50                 // Method java/util/ArrayList."<init>":()V
     364: astore        15
     366: aload         14
     368: aload         13
     370: invokevirtual #51                 // Method org/apache/hadoop/hbase/rsgroup/RSGroupInfo.getServers:()Ljava/util/Set;
     373: invokeinterface #52,  2           // InterfaceMethod java/util/List.addAll:(Ljava/util/Collection;)Z
     378: pop
     379: aload         15
     381: aload         13
     383: invokevirtual #53                 // Method org/apache/hadoop/hbase/rsgroup/RSGroupInfo.getTables:()Ljava/util/SortedSet;
     386: invokeinterface #52,  2           // InterfaceMethod java/util/List.addAll:(Ljava/util/Collection;)Z
     391: pop
     392: aload         14
     394: invokestatic  #54                 // Method java/util/Collections.sort:(Ljava/util/List;)V
     397: aload         15
     399: invokedynamic #55,  0             // InvokeDynamic #0:compare:()Ljava/util/Comparator;
     404: invokeinterface #56,  2           // InterfaceMethod java/util/List.sort:(Ljava/util/Comparator;)V
     409: invokestatic  #57                 // Method java/util/Collections.emptyMap:()Ljava/util/Map;
     412: astore        16
     414: invokestatic  #57                 // Method java/util/Collections.emptyMap:()Ljava/util/Map;
     417: astore        17
     419: aload         12
     421: invokevirtual #58                 // Method org/apache/hadoop/hbase/master/HMaster.getServerManager:()Lorg/apache/hadoop/hbase/master/ServerManager;
     424: ifnull        509
     427: aload         12
     429: invokevirtual #58                 // Method org/apache/hadoop/hbase/master/HMaster.getServerManager:()Lorg/apache/hadoop/hbase/master/ServerManager;
     432: invokevirtual #59                 // Method org/apache/hadoop/hbase/master/ServerManager.getOnlineServers:()Ljava/util/Map;
     435: invokeinterface #60,  1           // InterfaceMethod java/util/Map.entrySet:()Ljava/util/Set;
     440: invokeinterface #61,  1           // InterfaceMethod java/util/Set.stream:()Ljava/util/stream/Stream;
     445: invokedynamic #62,  0             // InvokeDynamic #1:apply:()Ljava/util/function/Function;
     450: invokedynamic #63,  0             // InvokeDynamic #2:apply:()Ljava/util/function/Function;
     455: invokestatic  #64                 // Method java/util/stream/Collectors.toMap:(Ljava/util/function/Function;Ljava/util/function/Function;)Ljava/util/stream/Collector;
     458: invokeinterface #65,  2           // InterfaceMethod java/util/stream/Stream.collect:(Ljava/util/stream/Collector;)Ljava/lang/Object;
     463: checkcast     #66                 // class java/util/Map
     466: astore        16
     468: aload         12
     470: invokevirtual #58                 // Method org/apache/hadoop/hbase/master/HMaster.getServerManager:()Lorg/apache/hadoop/hbase/master/ServerManager;
     473: invokevirtual #59                 // Method org/apache/hadoop/hbase/master/ServerManager.getOnlineServers:()Ljava/util/Map;
     476: invokeinterface #60,  1           // InterfaceMethod java/util/Map.entrySet:()Ljava/util/Set;
     481: invokeinterface #61,  1           // InterfaceMethod java/util/Set.stream:()Ljava/util/stream/Stream;
     486: invokedynamic #67,  0             // InvokeDynamic #3:apply:()Ljava/util/function/Function;
     491: invokedynamic #68,  0             // InvokeDynamic #4:apply:()Ljava/util/function/Function;
     496: invokestatic  #64                 // Method java/util/stream/Collectors.toMap:(Ljava/util/function/Function;Ljava/util/function/Function;)Ljava/util/stream/Collector;
     499: invokeinterface #65,  2           // InterfaceMethod java/util/stream/Stream.collect:(Ljava/util/stream/Collector;)Ljava/lang/Object;
     504: checkcast     #66                 // class java/util/Map
     507: astore        17
     509: aload         7
     511: ldc           #69                 // String \n  <div class=\"container-fluid content\">\n    <div class=\"row\">\n      <div class=\"page-header\">\n        <h1>RSGroup:
     513: invokevirtual #16                 // Method javax/servlet/jsp/JspWriter.write:(Ljava/lang/String;)V
     516: aload         7
     518: aload         11
     520: invokevirtual #47                 // Method javax/servlet/jsp/JspWriter.print:(Ljava/lang/String;)V
     523: aload         7
     525: ldc           #70                 // String </h1>\n      </div>\n    </div>\n  </div>\n  <div class=\"container-fluid content\">\n    <div class=\"row\">\n      <div class=\"inner_header\">\n        <h1>Region Servers</h1>\n      </div>\n    </div>\n    <div class=\"tabbable\">\n
     527: invokevirtual #16                 // Method javax/servlet/jsp/JspWriter.write:(Ljava/lang/String;)V
     530: aload         14
     532: ifnull        2624
     535: aload         14
     537: invokeinterface #71,  1           // InterfaceMethod java/util/List.size:()I
     542: ifle          2624
     545: aload         7
     547: ldc           #72                 // String \n        <ul class=\"nav nav-pills\">\n          <li class=\"active\">\n            <a href=\"#tab_baseStats\" data-toggle=\"tab\">Base Stats</a>\n          </li>\n          <li class=\"\">\n            <a href=\"#tab_memoryStats\" data-toggle=\"tab\">Memory</a>\n          </li>\n          <li class=\"\">\n            <a href=\"#tab_requestStats\" data-toggle=\"tab\">Requests</a>\n          </li>\n          <li class=\"\">\n            <a href=\"#tab_storeStats\" data-toggle=\"tab\">Storefiles</a>\n          </li>\n          <li class=\"\">\n            <a href=\"#tab_compactStats\" data-toggle=\"tab\">Compactions</a>\n          </li>\n        </ul>\n\n      <div class=\"tab-content\" style=\"padding-bottom: 9px; border-bottom: 1px solid #ddd;\">\n        <div class=\"tab-pane active\" id=\"tab_baseStats\">\n          <table class=\"table table-striped\">\n            <tr>\n              <th>ServerName</th>\n              <th>Start time</th>\n              <th>Last contact</th>\n              <th>Version</th>\n              <th>Requests Per Second</th>\n              <th>Num. Regions</th>\n
     549: invokevirtual #16                 // Method javax/servlet/jsp/JspWriter.write:(Ljava/lang/String;)V
     552: aload         7
     554: ldc           #73                 // String             </tr>\n
     556: invokevirtual #16                 // Method javax/servlet/jsp/JspWriter.write:(Ljava/lang/String;)V
     559: iconst_0
     560: istore        18
     562: iconst_0
     563: istore        19
     565: iconst_0
     566: istore        20
     568: invokestatic  #74                 // Method org/apache/hadoop/hbase/util/VersionInfo.getVersion:()Ljava/lang/String;
     571: astore        21
     573: aload         14
     575: invokeinterface #75,  1           // InterfaceMethod java/util/List.iterator:()Ljava/util/Iterator;
     580: astore        22
     582: aload         22
     584: invokeinterface #76,  1           // InterfaceMethod java/util/Iterator.hasNext:()Z
     589: ifeq          986
     592: aload         22
     594: invokeinterface #77,  1           // InterfaceMethod java/util/Iterator.next:()Ljava/lang/Object;
     599: checkcast     #78                 // class org/apache/hadoop/hbase/net/Address
     602: astore        23
     604: aload         17
     606: aload         23
     608: invokeinterface #79,  2           // InterfaceMethod java/util/Map.get:(Ljava/lang/Object;)Ljava/lang/Object;
     613: checkcast     #80                 // class org/apache/hadoop/hbase/ServerName
     616: astore        24
     618: aload         24
     620: ifnull        941
     623: aload         16
     625: aload         23
     627: invokeinterface #79,  2           // InterfaceMethod java/util/Map.get:(Ljava/lang/Object;)Ljava/lang/Object;
     632: checkcast     #81                 // class org/apache/hadoop/hbase/ServerMetrics
     635: astore        25
     637: aload         12
     639: aload         24
     641: invokevirtual #82                 // Method org/apache/hadoop/hbase/master/HMaster.getRegionServerVersion:(Lorg/apache/hadoop/hbase/ServerName;)Ljava/lang/String;
     644: astore        26
     646: aload         21
     648: aload         26
     650: invokevirtual #83                 // Method java/lang/String.equals:(Ljava/lang/Object;)Z
     653: ifne          659
     656: iinc          20, 1
     659: dconst_0
     660: dstore        27
     662: iconst_0
     663: istore        29
     665: lconst_0
     666: lstore        30
     668: aload         25
     670: ifnull        745
     673: aload         25
     675: invokeinterface #84,  1           // InterfaceMethod org/apache/hadoop/hbase/ServerMetrics.getRequestCountPerSecond:()J
     680: l2d
     681: dstore        27
     683: aload         25
     685: invokeinterface #85,  1           // InterfaceMethod org/apache/hadoop/hbase/ServerMetrics.getRegionMetrics:()Ljava/util/Map;
     690: invokeinterface #86,  1           // InterfaceMethod java/util/Map.size:()I
     695: istore        29
     697: iload         18
     699: aload         25
     701: invokeinterface #85,  1           // InterfaceMethod org/apache/hadoop/hbase/ServerMetrics.getRegionMetrics:()Ljava/util/Map;
     706: invokeinterface #86,  1           // InterfaceMethod java/util/Map.size:()I
     711: iadd
     712: istore        18
     714: iload         19
     716: i2l
     717: aload         25
     719: invokeinterface #84,  1           // InterfaceMethod org/apache/hadoop/hbase/ServerMetrics.getRequestCountPerSecond:()J
     724: ladd
     725: l2i
     726: istore        19
     728: invokestatic  #87                 // Method java/lang/System.currentTimeMillis:()J
     731: aload         25
     733: invokeinterface #88,  1           // InterfaceMethod org/apache/hadoop/hbase/ServerMetrics.getReportTimestamp:()J
     738: lsub
     739: ldc2_w        #89                 // long 1000l
     742: ldiv
     743: lstore        30
     745: aload         24
     747: invokevirtual #91                 // Method org/apache/hadoop/hbase/ServerName.getStartcode:()J
     750: lstore        32
     752: aload         12
     754: aload         24
     756: invokevirtual #92                 // Method org/apache/hadoop/hbase/master/HMaster.getRegionServerInfoPort:(Lorg/apache/hadoop/hbase/ServerName;)I
     759: istore        34
     761: new           #20                 // class java/lang/StringBuilder
     764: dup
     765: invokespecial #21                 // Method java/lang/StringBuilder."<init>":()V
     768: ldc           #93                 // String //
     770: invokevirtual #23                 // Method java/lang/StringBuilder.append:(Ljava/lang/String;)Ljava/lang/StringBuilder;
     773: aload         24
     775: invokevirtual #94                 // Method org/apache/hadoop/hbase/ServerName.getHostname:()Ljava/lang/String;
     778: invokevirtual #23                 // Method java/lang/StringBuilder.append:(Ljava/lang/String;)Ljava/lang/StringBuilder;
     781: ldc           #95                 // String :
     783: invokevirtual #23                 // Method java/lang/StringBuilder.append:(Ljava/lang/String;)Ljava/lang/StringBuilder;
     786: iload         34
     788: invokevirtual #96                 // Method java/lang/StringBuilder.append:(I)Ljava/lang/StringBuilder;
     791: ldc           #97                 // String /rs-status
     793: invokevirtual #23                 // Method java/lang/StringBuilder.append:(Ljava/lang/String;)Ljava/lang/StringBuilder;
     796: invokevirtual #24                 // Method java/lang/StringBuilder.toString:()Ljava/lang/String;
     799: astore        35
     801: aload         7
     803: ldc           #98                 // String \n                   <tr>\n                     <td><a href=\"
     805: invokevirtual #16                 // Method javax/servlet/jsp/JspWriter.write:(Ljava/lang/String;)V
     808: aload         7
     810: aload         35
     812: invokevirtual #47                 // Method javax/servlet/jsp/JspWriter.print:(Ljava/lang/String;)V
     815: aload         7
     817: bipush        34
     819: invokevirtual #26                 // Method javax/servlet/jsp/JspWriter.write:(I)V
     822: aload         7
     824: bipush        62
     826: invokevirtual #26                 // Method javax/servlet/jsp/JspWriter.write:(I)V
     829: aload         7
     831: aload         24
     833: invokevirtual #99                 // Method org/apache/hadoop/hbase/ServerName.getServerName:()Ljava/lang/String;
     836: invokevirtual #47                 // Method javax/servlet/jsp/JspWriter.print:(Ljava/lang/String;)V
     839: aload         7
     841: ldc           #100                // String </a></td>\n                     <td>
     843: invokevirtual #16                 // Method javax/servlet/jsp/JspWriter.write:(Ljava/lang/String;)V
     846: aload         7
     848: new           #101                // class java/util/Date
     851: dup
     852: lload         32
     854: invokespecial #102                // Method java/util/Date."<init>":(J)V
     857: invokevirtual #103                // Method javax/servlet/jsp/JspWriter.print:(Ljava/lang/Object;)V
     860: aload         7
     862: ldc           #104                // String </td>\n                     <td>
     864: invokevirtual #16                 // Method javax/servlet/jsp/JspWriter.write:(Ljava/lang/String;)V
     867: aload         7
     869: lload         30
     871: invokevirtual #105                // Method javax/servlet/jsp/JspWriter.print:(J)V
     874: aload         7
     876: ldc           #104                // String </td>\n                     <td>
     878: invokevirtual #16                 // Method javax/servlet/jsp/JspWriter.write:(Ljava/lang/String;)V
     881: aload         7
     883: aload         26
     885: invokevirtual #47                 // Method javax/servlet/jsp/JspWriter.print:(Ljava/lang/String;)V
     888: aload         7
     890: ldc           #104                // String </td>\n                     <td>
     892: invokevirtual #16                 // Method javax/servlet/jsp/JspWriter.write:(Ljava/lang/String;)V
     895: aload         7
     897: ldc           #106                // String %.0f
     899: iconst_1
     900: anewarray     #107                // class java/lang/Object
     903: dup
     904: iconst_0
     905: dload         27
     907: invokestatic  #108                // Method java/lang/Double.valueOf:(D)Ljava/lang/Double;
     910: aastore
     911: invokestatic  #109                // Method java/lang/String.format:(Ljava/lang/String;[Ljava/lang/Object;)Ljava/lang/String;
     914: invokevirtual #47                 // Method javax/servlet/jsp/JspWriter.print:(Ljava/lang/String;)V
     917: aload         7
     919: ldc           #104                // String </td>\n                     <td>
     921: invokevirtual #16                 // Method javax/servlet/jsp/JspWriter.write:(Ljava/lang/String;)V
     924: aload         7
     926: iload         29
     928: invokevirtual #110                // Method javax/servlet/jsp/JspWriter.print:(I)V
     931: aload         7
     933: ldc           #111                // String </td>\n                   </tr>\n
     935: invokevirtual #16                 // Method javax/servlet/jsp/JspWriter.write:(Ljava/lang/String;)V
     938: goto          976
     941: aload         7
     943: ldc           #112                // String \n                   <tr>\n                     <td style=\"color:rgb(192,192,192);\">
     945: invokevirtual #16                 // Method javax/servlet/jsp/JspWriter.write:(Ljava/lang/String;)V
     948: aload         7
     950: aload         23
     952: invokevirtual #103                // Method javax/servlet/jsp/JspWriter.print:(Ljava/lang/Object;)V
     955: aload         7
     957: ldc           #113                // String </td>\n                     <td style=\"color:rgb(192,192,192);\">
     959: invokevirtual #16                 // Method javax/servlet/jsp/JspWriter.write:(Ljava/lang/String;)V
     962: aload         7
     964: ldc           #114                // String Dead
     966: invokevirtual #47                 // Method javax/servlet/jsp/JspWriter.print:(Ljava/lang/String;)V
     969: aload         7
     971: ldc           #115                // String </td>\n                     <td></td>\n                     <td></td>\n                     <td></td>\n                     <td></td>\n                   </tr>\n
     973: invokevirtual #16                 // Method javax/servlet/jsp/JspWriter.write:(Ljava/lang/String;)V
     976: aload         7
     978: ldc           #116                // String \n
     980: invokevirtual #16                 // Method javax/servlet/jsp/JspWriter.write:(Ljava/lang/String;)V
     983: goto          582
     986: aload         7
     988: ldc           #117                // String \n            <tr><td>Total:
     990: invokevirtual #16                 // Method javax/servlet/jsp/JspWriter.write:(Ljava/lang/String;)V
     993: aload         7
     995: aload         14
     997: invokeinterface #71,  1           // InterfaceMethod java/util/List.size:()I
    1002: invokevirtual #110                // Method javax/servlet/jsp/JspWriter.print:(I)V
    1005: aload         7
    1007: ldc           #118                // String </td>\n            <td></td>\n            <td></td>\n
    1009: invokevirtual #16                 // Method javax/servlet/jsp/JspWriter.write:(Ljava/lang/String;)V
    1012: iload         20
    1014: ifle          1041
    1017: aload         7
    1019: ldc           #119                // String \n                <td style=\"color:red;\">
    1021: invokevirtual #16                 // Method javax/servlet/jsp/JspWriter.write:(Ljava/lang/String;)V
    1024: aload         7
    1026: iload         20
    1028: invokevirtual #110                // Method javax/servlet/jsp/JspWriter.print:(I)V
    1031: aload         7
    1033: ldc           #120                // String  nodes with inconsistent version</td>\n
    1035: invokevirtual #16                 // Method javax/servlet/jsp/JspWriter.write:(Ljava/lang/String;)V
    1038: goto          1048
    1041: aload         7
    1043: ldc           #121                // String \n                <td></td>\n
    1045: invokevirtual #16                 // Method javax/servlet/jsp/JspWriter.write:(Ljava/lang/String;)V
    1048: aload         7
    1050: ldc           #122                // String \n            <td>
    1052: invokevirtual #16                 // Method javax/servlet/jsp/JspWriter.write:(Ljava/lang/String;)V
    1055: aload         7
    1057: iload         19
    1059: invokevirtual #110                // Method javax/servlet/jsp/JspWriter.print:(I)V
    1062: aload         7
    1064: ldc           #123                // String </td>\n            <td>
    1066: invokevirtual #16                 // Method javax/servlet/jsp/JspWriter.write:(Ljava/lang/String;)V
    1069: aload         7
    1071: iload         18
    1073: invokevirtual #110                // Method javax/servlet/jsp/JspWriter.print:(I)V
    1076: aload         7
    1078: ldc           #124                // String </td>\n            </tr>\n          </table>\n        </div>\n        <div class=\"tab-pane\" id=\"tab_memoryStats\">\n          <table class=\"table table-striped\">\n            <tr>\n              <th>ServerName</th>\n              <th>Used Heap</th>\n              <th>Max Heap</th>\n              <th>Memstore Size</th>\n            </tr>\n
    1080: invokevirtual #16                 // Method javax/servlet/jsp/JspWriter.write:(Ljava/lang/String;)V
    1083: aload         14
    1085: invokeinterface #75,  1           // InterfaceMethod java/util/List.iterator:()Ljava/util/Iterator;
    1090: astore        22
    1092: aload         22
    1094: invokeinterface #76,  1           // InterfaceMethod java/util/Iterator.hasNext:()Z
    1099: ifeq          1413
    1102: aload         22
    1104: invokeinterface #77,  1           // InterfaceMethod java/util/Iterator.next:()Ljava/lang/Object;
    1109: checkcast     #78                 // class org/apache/hadoop/hbase/net/Address
    1112: astore        23
    1114: aload         17
    1116: aload         23
    1118: invokeinterface #79,  2           // InterfaceMethod java/util/Map.get:(Ljava/lang/Object;)Ljava/lang/Object;
    1123: checkcast     #80                 // class org/apache/hadoop/hbase/ServerName
    1126: astore        24
    1128: aload         16
    1130: aload         23
    1132: invokeinterface #79,  2           // InterfaceMethod java/util/Map.get:(Ljava/lang/Object;)Ljava/lang/Object;
    1137: checkcast     #81                 // class org/apache/hadoop/hbase/ServerMetrics
    1140: astore        25
    1142: aload         25
    1144: ifnull        1389
    1147: aload         24
    1149: ifnull        1389
    1152: aload         25
    1154: invokeinterface #85,  1           // InterfaceMethod org/apache/hadoop/hbase/ServerMetrics.getRegionMetrics:()Ljava/util/Map;
    1159: invokeinterface #125,  1          // InterfaceMethod java/util/Map.values:()Ljava/util/Collection;
    1164: invokeinterface #126,  1          // InterfaceMethod java/util/Collection.stream:()Ljava/util/stream/Stream;
    1169: invokedynamic #127,  0            // InvokeDynamic #5:applyAsDouble:()Ljava/util/function/ToDoubleFunction;
    1174: invokeinterface #128,  2          // InterfaceMethod java/util/stream/Stream.mapToDouble:(Ljava/util/function/ToDoubleFunction;)Ljava/util/stream/DoubleStream;
    1179: invokeinterface #129,  1          // InterfaceMethod java/util/stream/DoubleStream.sum:()D
    1184: dstore        26
    1186: aload         12
    1188: aload         24
    1190: invokevirtual #92                 // Method org/apache/hadoop/hbase/master/HMaster.getRegionServerInfoPort:(Lorg/apache/hadoop/hbase/ServerName;)I
    1193: istore        28
    1195: new           #20                 // class java/lang/StringBuilder
    1198: dup
    1199: invokespecial #21                 // Method java/lang/StringBuilder."<init>":()V
    1202: ldc           #93                 // String //
    1204: invokevirtual #23                 // Method java/lang/StringBuilder.append:(Ljava/lang/String;)Ljava/lang/StringBuilder;
    1207: aload         24
    1209: invokevirtual #94                 // Method org/apache/hadoop/hbase/ServerName.getHostname:()Ljava/lang/String;
    1212: invokevirtual #23                 // Method java/lang/StringBuilder.append:(Ljava/lang/String;)Ljava/lang/StringBuilder;
    1215: ldc           #95                 // String :
    1217: invokevirtual #23                 // Method java/lang/StringBuilder.append:(Ljava/lang/String;)Ljava/lang/StringBuilder;
    1220: iload         28
    1222: invokevirtual #96                 // Method java/lang/StringBuilder.append:(I)Ljava/lang/StringBuilder;
    1225: ldc           #97                 // String /rs-status
    1227: invokevirtual #23                 // Method java/lang/StringBuilder.append:(Ljava/lang/String;)Ljava/lang/StringBuilder;
    1230: invokevirtual #24                 // Method java/lang/StringBuilder.toString:()Ljava/lang/String;
    1233: astore        29
    1235: aload         7
    1237: ldc           #98                 // String \n                   <tr>\n                     <td><a href=\"
    1239: invokevirtual #16                 // Method javax/servlet/jsp/JspWriter.write:(Ljava/lang/String;)V
    1242: aload         7
    1244: aload         29
    1246: invokevirtual #47                 // Method javax/servlet/jsp/JspWriter.print:(Ljava/lang/String;)V
    1249: aload         7
    1251: bipush        34
    1253: invokevirtual #26                 // Method javax/servlet/jsp/JspWriter.write:(I)V
    1256: aload         7
    1258: bipush        62
    1260: invokevirtual #26                 // Method javax/servlet/jsp/JspWriter.write:(I)V
    1263: aload         7
    1265: aload         24
    1267: invokevirtual #99                 // Method org/apache/hadoop/hbase/ServerName.getServerName:()Ljava/lang/String;
    1270: invokevirtual #47                 // Method javax/servlet/jsp/JspWriter.print:(Ljava/lang/String;)V
    1273: aload         7
    1275: ldc           #100                // String </a></td>\n                     <td>
    1277: invokevirtual #16                 // Method javax/servlet/jsp/JspWriter.write:(Ljava/lang/String;)V
    1280: aload         7
    1282: aload         25
    1284: invokeinterface #130,  1          // InterfaceMethod org/apache/hadoop/hbase/ServerMetrics.getUsedHeapSize:()Lorg/apache/hadoop/hbase/Size;
    1289: getstatic     #131                // Field org/apache/hadoop/hbase/Size$Unit.MEGABYTE:Lorg/apache/hadoop/hbase/Size$Unit;
    1292: invokevirtual #132                // Method org/apache/hadoop/hbase/Size.get:(Lorg/apache/hadoop/hbase/Size$Unit;)D
    1295: d2l
    1296: getstatic     #133                // Field org/apache/hadoop/util/StringUtils$TraditionalBinaryPrefix.MEGA:Lorg/apache/hadoop/util/StringUtils$TraditionalBinaryPrefix;
    1299: getfield      #134                // Field org/apache/hadoop/util/StringUtils$TraditionalBinaryPrefix.value:J
    1302: lmul
    1303: ldc           #135                // String B
    1305: iconst_1
    1306: invokestatic  #136                // Method org/apache/hadoop/util/StringUtils$TraditionalBinaryPrefix.long2String:(JLjava/lang/String;I)Ljava/lang/String;
    1309: invokevirtual #47                 // Method javax/servlet/jsp/JspWriter.print:(Ljava/lang/String;)V
    1312: aload         7
    1314: ldc           #104                // String </td>\n                     <td>
    1316: invokevirtual #16                 // Method javax/servlet/jsp/JspWriter.write:(Ljava/lang/String;)V
    1319: aload         7
    1321: aload         25
    1323: invokeinterface #137,  1          // InterfaceMethod org/apache/hadoop/hbase/ServerMetrics.getMaxHeapSize:()Lorg/apache/hadoop/hbase/Size;
    1328: getstatic     #131                // Field org/apache/hadoop/hbase/Size$Unit.MEGABYTE:Lorg/apache/hadoop/hbase/Size$Unit;
    1331: invokevirtual #132                // Method org/apache/hadoop/hbase/Size.get:(Lorg/apache/hadoop/hbase/Size$Unit;)D
    1334: d2l
    1335: getstatic     #133                // Field org/apache/hadoop/util/StringUtils$TraditionalBinaryPrefix.MEGA:Lorg/apache/hadoop/util/StringUtils$TraditionalBinaryPrefix;
    1338: getfield      #134                // Field org/apache/hadoop/util/StringUtils$TraditionalBinaryPrefix.value:J
    1341: lmul
    1342: ldc           #135                // String B
    1344: iconst_1
    1345: invokestatic  #136                // Method org/apache/hadoop/util/StringUtils$TraditionalBinaryPrefix.long2String:(JLjava/lang/String;I)Ljava/lang/String;
    1348: invokevirtual #47                 // Method javax/servlet/jsp/JspWriter.print:(Ljava/lang/String;)V
    1351: aload         7
    1353: ldc           #104                // String </td>\n                     <td>
    1355: invokevirtual #16                 // Method javax/servlet/jsp/JspWriter.write:(Ljava/lang/String;)V
    1358: aload         7
    1360: dload         26
    1362: d2l
    1363: getstatic     #133                // Field org/apache/hadoop/util/StringUtils$TraditionalBinaryPrefix.MEGA:Lorg/apache/hadoop/util/StringUtils$TraditionalBinaryPrefix;
    1366: getfield      #134                // Field org/apache/hadoop/util/StringUtils$TraditionalBinaryPrefix.value:J
    1369: lmul
    1370: ldc           #135                // String B
    1372: iconst_1
    1373: invokestatic  #136                // Method org/apache/hadoop/util/StringUtils$TraditionalBinaryPrefix.long2String:(JLjava/lang/String;I)Ljava/lang/String;
    1376: invokevirtual #47                 // Method javax/servlet/jsp/JspWriter.print:(Ljava/lang/String;)V
    1379: aload         7
    1381: ldc           #111                // String </td>\n                   </tr>\n
    1383: invokevirtual #16                 // Method javax/servlet/jsp/JspWriter.write:(Ljava/lang/String;)V
    1386: goto          1410
    1389: aload         7
    1391: ldc           #112                // String \n                   <tr>\n                     <td style=\"color:rgb(192,192,192);\">
    1393: invokevirtual #16                 // Method javax/servlet/jsp/JspWriter.write:(Ljava/lang/String;)V
    1396: aload         7
    1398: aload         23
    1400: invokevirtual #103                // Method javax/servlet/jsp/JspWriter.print:(Ljava/lang/Object;)V
    1403: aload         7
    1405: ldc           #138                // String </td>\n                     <td></td>\n                     <td></td>\n                     <td></td>\n                   </tr>\n
    1407: invokevirtual #16                 // Method javax/servlet/jsp/JspWriter.write:(Ljava/lang/String;)V
    1410: goto          1092
    1413: aload         7
    1415: ldc           #139                // String \n          </table>\n        </div>\n        <div class=\"tab-pane\" id=\"tab_requestStats\">\n          <table class=\"table table-striped\">\n            <tr>\n                <th>ServerName</th>\n                <th>Request Per Second</th>\n                <th>Read Request Count</th>\n                <th>Write Request Count</th>\n            </tr>\n
    1417: invokevirtual #16                 // Method javax/servlet/jsp/JspWriter.write:(Ljava/lang/String;)V
    1420: aload         14
    1422: invokeinterface #75,  1           // InterfaceMethod java/util/List.iterator:()Ljava/util/Iterator;
    1427: astore        22
    1429: aload         22
    1431: invokeinterface #76,  1           // InterfaceMethod java/util/Iterator.hasNext:()Z
    1436: ifeq          1731
    1439: aload         22
    1441: invokeinterface #77,  1           // InterfaceMethod java/util/Iterator.next:()Ljava/lang/Object;
    1446: checkcast     #78                 // class org/apache/hadoop/hbase/net/Address
    1449: astore        23
    1451: aload         17
    1453: aload         23
    1455: invokeinterface #79,  2           // InterfaceMethod java/util/Map.get:(Ljava/lang/Object;)Ljava/lang/Object;
    1460: checkcast     #80                 // class org/apache/hadoop/hbase/ServerName
    1463: astore        24
    1465: aload         16
    1467: aload         23
    1469: invokeinterface #79,  2           // InterfaceMethod java/util/Map.get:(Ljava/lang/Object;)Ljava/lang/Object;
    1474: checkcast     #81                 // class org/apache/hadoop/hbase/ServerMetrics
    1477: astore        25
    1479: aload         25
    1481: ifnull        1707
    1484: aload         24
    1486: ifnull        1707
    1489: aload         12
    1491: aload         24
    1493: invokevirtual #92                 // Method org/apache/hadoop/hbase/master/HMaster.getRegionServerInfoPort:(Lorg/apache/hadoop/hbase/ServerName;)I
    1496: istore        26
    1498: lconst_0
    1499: lstore        27
    1501: lconst_0
    1502: lstore        29
    1504: aload         25
    1506: invokeinterface #85,  1           // InterfaceMethod org/apache/hadoop/hbase/ServerMetrics.getRegionMetrics:()Ljava/util/Map;
    1511: invokeinterface #125,  1          // InterfaceMethod java/util/Map.values:()Ljava/util/Collection;
    1516: invokeinterface #140,  1          // InterfaceMethod java/util/Collection.iterator:()Ljava/util/Iterator;
    1521: astore        31
    1523: aload         31
    1525: invokeinterface #76,  1           // InterfaceMethod java/util/Iterator.hasNext:()Z
    1530: ifeq          1572
    1533: aload         31
    1535: invokeinterface #77,  1           // InterfaceMethod java/util/Iterator.next:()Ljava/lang/Object;
    1540: checkcast     #141                // class org/apache/hadoop/hbase/RegionMetrics
    1543: astore        32
    1545: lload         27
    1547: aload         32
    1549: invokeinterface #142,  1          // InterfaceMethod org/apache/hadoop/hbase/RegionMetrics.getReadRequestCount:()J
    1554: ladd
    1555: lstore        27
    1557: lload         29
    1559: aload         32
    1561: invokeinterface #143,  1          // InterfaceMethod org/apache/hadoop/hbase/RegionMetrics.getWriteRequestCount:()J
    1566: ladd
    1567: lstore        29
    1569: goto          1523
    1572: new           #20                 // class java/lang/StringBuilder
    1575: dup
    1576: invokespecial #21                 // Method java/lang/StringBuilder."<init>":()V
    1579: ldc           #93                 // String //
    1581: invokevirtual #23                 // Method java/lang/StringBuilder.append:(Ljava/lang/String;)Ljava/lang/StringBuilder;
    1584: aload         24
    1586: invokevirtual #94                 // Method org/apache/hadoop/hbase/ServerName.getHostname:()Ljava/lang/String;
    1589: invokevirtual #23                 // Method java/lang/StringBuilder.append:(Ljava/lang/String;)Ljava/lang/StringBuilder;
    1592: ldc           #95                 // String :
    1594: invokevirtual #23                 // Method java/lang/StringBuilder.append:(Ljava/lang/String;)Ljava/lang/StringBuilder;
    1597: iload         26
    1599: invokevirtual #96                 // Method java/lang/StringBuilder.append:(I)Ljava/lang/StringBuilder;
    1602: ldc           #97                 // String /rs-status
    1604: invokevirtual #23                 // Method java/lang/StringBuilder.append:(Ljava/lang/String;)Ljava/lang/StringBuilder;
    1607: invokevirtual #24                 // Method java/lang/StringBuilder.toString:()Ljava/lang/String;
    1610: astore        31
    1612: aload         7
    1614: ldc           #98                 // String \n                   <tr>\n                     <td><a href=\"
    1616: invokevirtual #16                 // Method javax/servlet/jsp/JspWriter.write:(Ljava/lang/String;)V
    1619: aload         7
    1621: aload         31
    1623: invokevirtual #47                 // Method javax/servlet/jsp/JspWriter.print:(Ljava/lang/String;)V
    1626: aload         7
    1628: bipush        34
    1630: invokevirtual #26                 // Method javax/servlet/jsp/JspWriter.write:(I)V
    1633: aload         7
    1635: bipush        62
    1637: invokevirtual #26                 // Method javax/servlet/jsp/JspWriter.write:(I)V
    1640: aload         7
    1642: aload         24
    1644: invokevirtual #99                 // Method org/apache/hadoop/hbase/ServerName.getServerName:()Ljava/lang/String;
    1647: invokevirtual #47                 // Method javax/servlet/jsp/JspWriter.print:(Ljava/lang/String;)V
    1650: aload         7
    1652: ldc           #100                // String </a></td>\n                     <td>
    1654: invokevirtual #16                 // Method javax/servlet/jsp/JspWriter.write:(Ljava/lang/String;)V
    1657: aload         7
    1659: aload         25
    1661: invokeinterface #84,  1           // InterfaceMethod org/apache/hadoop/hbase/ServerMetrics.getRequestCountPerSecond:()J
    1666: invokevirtual #105                // Method javax/servlet/jsp/JspWriter.print:(J)V
    1669: aload         7
    1671: ldc           #104                // String </td>\n                     <td>
    1673: invokevirtual #16                 // Method javax/servlet/jsp/JspWriter.write:(Ljava/lang/String;)V
    1676: aload         7
    1678: lload         27
    1680: invokevirtual #105                // Method javax/servlet/jsp/JspWriter.print:(J)V
    1683: aload         7
    1685: ldc           #104                // String </td>\n                     <td>
    1687: invokevirtual #16                 // Method javax/servlet/jsp/JspWriter.write:(Ljava/lang/String;)V
    1690: aload         7
    1692: lload         29
    1694: invokevirtual #105                // Method javax/servlet/jsp/JspWriter.print:(J)V
    1697: aload         7
    1699: ldc           #111                // String </td>\n                   </tr>\n
    1701: invokevirtual #16                 // Method javax/servlet/jsp/JspWriter.write:(Ljava/lang/String;)V
    1704: goto          1728
    1707: aload         7
    1709: ldc           #112                // String \n                   <tr>\n                     <td style=\"color:rgb(192,192,192);\">
    1711: invokevirtual #16                 // Method javax/servlet/jsp/JspWriter.write:(Ljava/lang/String;)V
    1714: aload         7
    1716: aload         23
    1718: invokevirtual #103                // Method javax/servlet/jsp/JspWriter.print:(Ljava/lang/Object;)V
    1721: aload         7
    1723: ldc           #138                // String </td>\n                     <td></td>\n                     <td></td>\n                     <td></td>\n                   </tr>\n
    1725: invokevirtual #16                 // Method javax/servlet/jsp/JspWriter.write:(Ljava/lang/String;)V
    1728: goto          1429
    1731: aload         7
    1733: ldc           #144                // String \n          </table>\n        </div>\n        <div class=\"tab-pane\" id=\"tab_storeStats\">\n          <table class=\"table table-striped\">\n            <tr>\n                <th>ServerName</th>\n                <th>Num. Stores</th>\n                <th>Num. Storefiles</th>\n                <th>Storefile Size Uncompressed</th>\n                <th>Storefile Size</th>\n                <th>Index Size</th>\n                <th>Bloom Size</th>\n            </tr>\n
    1735: invokevirtual #16                 // Method javax/servlet/jsp/JspWriter.write:(Ljava/lang/String;)V
    1738: aload         14
    1740: invokeinterface #75,  1           // InterfaceMethod java/util/List.iterator:()Ljava/util/Iterator;
    1745: astore        22
    1747: aload         22
    1749: invokeinterface #76,  1           // InterfaceMethod java/util/Iterator.hasNext:()Z
    1754: ifeq          2228
    1757: aload         22
    1759: invokeinterface #77,  1           // InterfaceMethod java/util/Iterator.next:()Ljava/lang/Object;
    1764: checkcast     #78                 // class org/apache/hadoop/hbase/net/Address
    1767: astore        23
    1769: aload         17
    1771: aload         23
    1773: invokeinterface #79,  2           // InterfaceMethod java/util/Map.get:(Ljava/lang/Object;)Ljava/lang/Object;
    1778: checkcast     #80                 // class org/apache/hadoop/hbase/ServerName
    1781: astore        24
    1783: aload         16
    1785: aload         23
    1787: invokeinterface #79,  2           // InterfaceMethod java/util/Map.get:(Ljava/lang/Object;)Ljava/lang/Object;
    1792: checkcast     #81                 // class org/apache/hadoop/hbase/ServerMetrics
    1795: astore        25
    1797: aload         25
    1799: ifnull        2204
    1802: aload         24
    1804: ifnull        2204
    1807: lconst_0
    1808: lstore        26
    1810: lconst_0
    1811: lstore        28
    1813: dconst_0
    1814: dstore        30
    1816: dconst_0
    1817: dstore        32
    1819: dconst_0
    1820: dstore        34
    1822: dconst_0
    1823: dstore        36
    1825: aload         25
    1827: invokeinterface #85,  1           // InterfaceMethod org/apache/hadoop/hbase/ServerMetrics.getRegionMetrics:()Ljava/util/Map;
    1832: invokeinterface #125,  1          // InterfaceMethod java/util/Map.values:()Ljava/util/Collection;
    1837: invokeinterface #140,  1          // InterfaceMethod java/util/Collection.iterator:()Ljava/util/Iterator;
    1842: astore        38
    1844: aload         38
    1846: invokeinterface #76,  1           // InterfaceMethod java/util/Iterator.hasNext:()Z
    1851: ifeq          1967
    1854: aload         38
    1856: invokeinterface #77,  1           // InterfaceMethod java/util/Iterator.next:()Ljava/lang/Object;
    1861: checkcast     #141                // class org/apache/hadoop/hbase/RegionMetrics
    1864: astore        39
    1866: lload         26
    1868: aload         39
    1870: invokeinterface #145,  1          // InterfaceMethod org/apache/hadoop/hbase/RegionMetrics.getStoreCount:()I
    1875: i2l
    1876: ladd
    1877: lstore        26
    1879: lload         28
    1881: aload         39
    1883: invokeinterface #146,  1          // InterfaceMethod org/apache/hadoop/hbase/RegionMetrics.getStoreFileCount:()I
    1888: i2l
    1889: ladd
    1890: lstore        28
    1892: dload         30
    1894: aload         39
    1896: invokeinterface #147,  1          // InterfaceMethod org/apache/hadoop/hbase/RegionMetrics.getUncompressedStoreFileSize:()Lorg/apache/hadoop/hbase/Size;
    1901: getstatic     #131                // Field org/apache/hadoop/hbase/Size$Unit.MEGABYTE:Lorg/apache/hadoop/hbase/Size$Unit;
    1904: invokevirtual #132                // Method org/apache/hadoop/hbase/Size.get:(Lorg/apache/hadoop/hbase/Size$Unit;)D
    1907: dadd
    1908: dstore        30
    1910: dload         32
    1912: aload         39
    1914: invokeinterface #148,  1          // InterfaceMethod org/apache/hadoop/hbase/RegionMetrics.getStoreFileSize:()Lorg/apache/hadoop/hbase/Size;
    1919: getstatic     #131                // Field org/apache/hadoop/hbase/Size$Unit.MEGABYTE:Lorg/apache/hadoop/hbase/Size$Unit;
    1922: invokevirtual #132                // Method org/apache/hadoop/hbase/Size.get:(Lorg/apache/hadoop/hbase/Size$Unit;)D
    1925: dadd
    1926: dstore        32
    1928: dload         34
    1930: aload         39
    1932: invokeinterface #149,  1          // InterfaceMethod org/apache/hadoop/hbase/RegionMetrics.getStoreFileUncompressedDataIndexSize:()Lorg/apache/hadoop/hbase/Size;
    1937: getstatic     #150                // Field org/apache/hadoop/hbase/Size$Unit.KILOBYTE:Lorg/apache/hadoop/hbase/Size$Unit;
    1940: invokevirtual #132                // Method org/apache/hadoop/hbase/Size.get:(Lorg/apache/hadoop/hbase/Size$Unit;)D
    1943: dadd
    1944: dstore        34
    1946: dload         36
    1948: aload         39
    1950: invokeinterface #151,  1          // InterfaceMethod org/apache/hadoop/hbase/RegionMetrics.getBloomFilterSize:()Lorg/apache/hadoop/hbase/Size;
    1955: getstatic     #150                // Field org/apache/hadoop/hbase/Size$Unit.KILOBYTE:Lorg/apache/hadoop/hbase/Size$Unit;
    1958: invokevirtual #132                // Method org/apache/hadoop/hbase/Size.get:(Lorg/apache/hadoop/hbase/Size$Unit;)D
    1961: dadd
    1962: dstore        36
    1964: goto          1844
    1967: aload         12
    1969: aload         24
    1971: invokevirtual #92                 // Method org/apache/hadoop/hbase/master/HMaster.getRegionServerInfoPort:(Lorg/apache/hadoop/hbase/ServerName;)I
    1974: istore        38
    1976: new           #20                 // class java/lang/StringBuilder
    1979: dup
    1980: invokespecial #21                 // Method java/lang/StringBuilder."<init>":()V
    1983: ldc           #93                 // String //
    1985: invokevirtual #23                 // Method java/lang/StringBuilder.append:(Ljava/lang/String;)Ljava/lang/StringBuilder;
    1988: aload         24
    1990: invokevirtual #94                 // Method org/apache/hadoop/hbase/ServerName.getHostname:()Ljava/lang/String;
    1993: invokevirtual #23                 // Method java/lang/StringBuilder.append:(Ljava/lang/String;)Ljava/lang/StringBuilder;
    1996: ldc           #95                 // String :
    1998: invokevirtual #23                 // Method java/lang/StringBuilder.append:(Ljava/lang/String;)Ljava/lang/StringBuilder;
    2001: iload         38
    2003: invokevirtual #96                 // Method java/lang/StringBuilder.append:(I)Ljava/lang/StringBuilder;
    2006: ldc           #97                 // String /rs-status
    2008: invokevirtual #23                 // Method java/lang/StringBuilder.append:(Ljava/lang/String;)Ljava/lang/StringBuilder;
    2011: invokevirtual #24                 // Method java/lang/StringBuilder.toString:()Ljava/lang/String;
    2014: astore        39
    2016: aload         7
    2018: ldc           #152                // String \n                    <tr>\n                      <td><a href=\"
    2020: invokevirtual #16                 // Method javax/servlet/jsp/JspWriter.write:(Ljava/lang/String;)V
    2023: aload         7
    2025: aload         39
    2027: invokevirtual #47                 // Method javax/servlet/jsp/JspWriter.print:(Ljava/lang/String;)V
    2030: aload         7
    2032: bipush        34
    2034: invokevirtual #26                 // Method javax/servlet/jsp/JspWriter.write:(I)V
    2037: aload         7
    2039: bipush        62
    2041: invokevirtual #26                 // Method javax/servlet/jsp/JspWriter.write:(I)V
    2044: aload         7
    2046: aload         24
    2048: invokevirtual #99                 // Method org/apache/hadoop/hbase/ServerName.getServerName:()Ljava/lang/String;
    2051: invokevirtual #47                 // Method javax/servlet/jsp/JspWriter.print:(Ljava/lang/String;)V
    2054: aload         7
    2056: ldc           #153                // String </a></td>\n                      <td>
    2058: invokevirtual #16                 // Method javax/servlet/jsp/JspWriter.write:(Ljava/lang/String;)V
    2061: aload         7
    2063: lload         26
    2065: invokevirtual #105                // Method javax/servlet/jsp/JspWriter.print:(J)V
    2068: aload         7
    2070: ldc           #154                // String </td>\n                      <td>
    2072: invokevirtual #16                 // Method javax/servlet/jsp/JspWriter.write:(Ljava/lang/String;)V
    2075: aload         7
    2077: lload         28
    2079: invokevirtual #105                // Method javax/servlet/jsp/JspWriter.print:(J)V
    2082: aload         7
    2084: ldc           #154                // String </td>\n                      <td>
    2086: invokevirtual #16                 // Method javax/servlet/jsp/JspWriter.write:(Ljava/lang/String;)V
    2089: aload         7
    2091: dload         30
    2093: d2l
    2094: getstatic     #133                // Field org/apache/hadoop/util/StringUtils$TraditionalBinaryPrefix.MEGA:Lorg/apache/hadoop/util/StringUtils$TraditionalBinaryPrefix;
    2097: getfield      #134                // Field org/apache/hadoop/util/StringUtils$TraditionalBinaryPrefix.value:J
    2100: lmul
    2101: ldc           #135                // String B
    2103: iconst_1
    2104: invokestatic  #136                // Method org/apache/hadoop/util/StringUtils$TraditionalBinaryPrefix.long2String:(JLjava/lang/String;I)Ljava/lang/String;
    2107: invokevirtual #47                 // Method javax/servlet/jsp/JspWriter.print:(Ljava/lang/String;)V
    2110: aload         7
    2112: ldc           #154                // String </td>\n                      <td>
    2114: invokevirtual #16                 // Method javax/servlet/jsp/JspWriter.write:(Ljava/lang/String;)V
    2117: aload         7
    2119: dload         32
    2121: d2l
    2122: getstatic     #133                // Field org/apache/hadoop/util/StringUtils$TraditionalBinaryPrefix.MEGA:Lorg/apache/hadoop/util/StringUtils$TraditionalBinaryPrefix;
    2125: getfield      #134                // Field org/apache/hadoop/util/StringUtils$TraditionalBinaryPrefix.value:J
    2128: lmul
    2129: ldc           #135                // String B
    2131: iconst_1
    2132: invokestatic  #136                // Method org/apache/hadoop/util/StringUtils$TraditionalBinaryPrefix.long2String:(JLjava/lang/String;I)Ljava/lang/String;
    2135: invokevirtual #47                 // Method javax/servlet/jsp/JspWriter.print:(Ljava/lang/String;)V
    2138: aload         7
    2140: ldc           #154                // String </td>\n                      <td>
    2142: invokevirtual #16                 // Method javax/servlet/jsp/JspWriter.write:(Ljava/lang/String;)V
    2145: aload         7
    2147: dload         34
    2149: d2l
    2150: getstatic     #155                // Field org/apache/hadoop/util/StringUtils$TraditionalBinaryPrefix.KILO:Lorg/apache/hadoop/util/StringUtils$TraditionalBinaryPrefix;
    2153: getfield      #134                // Field org/apache/hadoop/util/StringUtils$TraditionalBinaryPrefix.value:J
    2156: lmul
    2157: ldc           #135                // String B
    2159: iconst_1
    2160: invokestatic  #136                // Method org/apache/hadoop/util/StringUtils$TraditionalBinaryPrefix.long2String:(JLjava/lang/String;I)Ljava/lang/String;
    2163: invokevirtual #47                 // Method javax/servlet/jsp/JspWriter.print:(Ljava/lang/String;)V
    2166: aload         7
    2168: ldc           #154                // String </td>\n                      <td>
    2170: invokevirtual #16                 // Method javax/servlet/jsp/JspWriter.write:(Ljava/lang/String;)V
    2173: aload         7
    2175: dload         36
    2177: d2l
    2178: getstatic     #155                // Field org/apache/hadoop/util/StringUtils$TraditionalBinaryPrefix.KILO:Lorg/apache/hadoop/util/StringUtils$TraditionalBinaryPrefix;
    2181: getfield      #134                // Field org/apache/hadoop/util/StringUtils$TraditionalBinaryPrefix.value:J
    2184: lmul
    2185: ldc           #135                // String B
    2187: iconst_1
    2188: invokestatic  #136                // Method org/apache/hadoop/util/StringUtils$TraditionalBinaryPrefix.long2String:(JLjava/lang/String;I)Ljava/lang/String;
    2191: invokevirtual #47                 // Method javax/servlet/jsp/JspWriter.print:(Ljava/lang/String;)V
    2194: aload         7
    2196: ldc           #156                // String </td>\n                    </tr>\n
    2198: invokevirtual #16                 // Method javax/servlet/jsp/JspWriter.write:(Ljava/lang/String;)V
    2201: goto          2225
    2204: aload         7
    2206: ldc           #157                // String \n                    <tr>\n                      <td style=\"color:rgb(192,192,192);\">
    2208: invokevirtual #16                 // Method javax/servlet/jsp/JspWriter.write:(Ljava/lang/String;)V
    2211: aload         7
    2213: aload         23
    2215: invokevirtual #103                // Method javax/servlet/jsp/JspWriter.print:(Ljava/lang/Object;)V
    2218: aload         7
    2220: ldc           #158                // String </td>\n                      <td></td>\n                      <td></td>\n                      <td></td>\n                      <td></td>\n                      <td></td>\n                      <td></td>\n                    </tr>\n
    2222: invokevirtual #16                 // Method javax/servlet/jsp/JspWriter.write:(Ljava/lang/String;)V
    2225: goto          1747
    2228: aload         7
    2230: ldc           #159                // String \n          </table>\n        </div>\n        <div class=\"tab-pane\" id=\"tab_compactStats\">\n          <table class=\"table table-striped\">\n            <tr>\n              <th>ServerName</th>\n              <th>Num. Compacting KVs</th>\n              <th>Num. Compacted KVs</th>\n              <th>Remaining KVs</th>\n              <th>Compaction Progress</th>\n            </tr>\n
    2232: invokevirtual #16                 // Method javax/servlet/jsp/JspWriter.write:(Ljava/lang/String;)V
    2235: aload         14
    2237: invokeinterface #75,  1           // InterfaceMethod java/util/List.iterator:()Ljava/util/Iterator;
    2242: astore        22
    2244: aload         22
    2246: invokeinterface #76,  1           // InterfaceMethod java/util/Iterator.hasNext:()Z
    2251: ifeq          2614
    2254: aload         22
    2256: invokeinterface #77,  1           // InterfaceMethod java/util/Iterator.next:()Ljava/lang/Object;
    2261: checkcast     #78                 // class org/apache/hadoop/hbase/net/Address
    2264: astore        23
    2266: aload         17
    2268: aload         23
    2270: invokeinterface #79,  2           // InterfaceMethod java/util/Map.get:(Ljava/lang/Object;)Ljava/lang/Object;
    2275: checkcast     #80                 // class org/apache/hadoop/hbase/ServerName
    2278: astore        24
    2280: aload         16
    2282: aload         23
    2284: invokeinterface #79,  2           // InterfaceMethod java/util/Map.get:(Ljava/lang/Object;)Ljava/lang/Object;
    2289: checkcast     #81                 // class org/apache/hadoop/hbase/ServerMetrics
    2292: astore        25
    2294: aload         25
    2296: ifnull        2590
    2299: aload         24
    2301: ifnull        2590
    2304: lconst_0
    2305: lstore        26
    2307: lconst_0
    2308: lstore        28
    2310: aload         25
    2312: invokeinterface #85,  1           // InterfaceMethod org/apache/hadoop/hbase/ServerMetrics.getRegionMetrics:()Ljava/util/Map;
    2317: invokeinterface #125,  1          // InterfaceMethod java/util/Map.values:()Ljava/util/Collection;
    2322: invokeinterface #140,  1          // InterfaceMethod java/util/Collection.iterator:()Ljava/util/Iterator;
    2327: astore        30
    2329: aload         30
    2331: invokeinterface #76,  1           // InterfaceMethod java/util/Iterator.hasNext:()Z
    2336: ifeq          2378
    2339: aload         30
    2341: invokeinterface #77,  1           // InterfaceMethod java/util/Iterator.next:()Ljava/lang/Object;
    2346: checkcast     #141                // class org/apache/hadoop/hbase/RegionMetrics
    2349: astore        31
    2351: lload         26
    2353: aload         31
    2355: invokeinterface #160,  1          // InterfaceMethod org/apache/hadoop/hbase/RegionMetrics.getCompactingCellCount:()J
    2360: ladd
    2361: lstore        26
    2363: lload         28
    2365: aload         31
    2367: invokeinterface #161,  1          // InterfaceMethod org/apache/hadoop/hbase/RegionMetrics.getCompactedCellCount:()J
    2372: ladd
    2373: lstore        28
    2375: goto          2329
    2378: ldc           #162                // String
    2380: astore        30
    2382: lload         26
    2384: lconst_0
    2385: lcmp
    2386: ifle          2434
    2389: new           #20                 // class java/lang/StringBuilder
    2392: dup
    2393: invokespecial #21                 // Method java/lang/StringBuilder."<init>":()V
    2396: ldc           #163                // String %.2f
    2398: iconst_1
    2399: anewarray     #107                // class java/lang/Object
    2402: dup
    2403: iconst_0
    2404: ldc           #164                // float 100.0f
    2406: lload         28
    2408: l2f
    2409: lload         26
    2411: l2f
    2412: fdiv
    2413: fmul
    2414: invokestatic  #165                // Method java/lang/Float.valueOf:(F)Ljava/lang/Float;
    2417: aastore
    2418: invokestatic  #109                // Method java/lang/String.format:(Ljava/lang/String;[Ljava/lang/Object;)Ljava/lang/String;
    2421: invokevirtual #23                 // Method java/lang/StringBuilder.append:(Ljava/lang/String;)Ljava/lang/StringBuilder;
    2424: ldc           #166                // String %
    2426: invokevirtual #23                 // Method java/lang/StringBuilder.append:(Ljava/lang/String;)Ljava/lang/StringBuilder;
    2429: invokevirtual #24                 // Method java/lang/StringBuilder.toString:()Ljava/lang/String;
    2432: astore        30
    2434: aload         12
    2436: aload         24
    2438: invokevirtual #92                 // Method org/apache/hadoop/hbase/master/HMaster.getRegionServerInfoPort:(Lorg/apache/hadoop/hbase/ServerName;)I
    2441: istore        31
    2443: new           #20                 // class java/lang/StringBuilder
    2446: dup
    2447: invokespecial #21                 // Method java/lang/StringBuilder."<init>":()V
    2450: ldc           #93                 // String //
    2452: invokevirtual #23                 // Method java/lang/StringBuilder.append:(Ljava/lang/String;)Ljava/lang/StringBuilder;
    2455: aload         24
    2457: invokevirtual #94                 // Method org/apache/hadoop/hbase/ServerName.getHostname:()Ljava/lang/String;
    2460: invokevirtual #23                 // Method java/lang/StringBuilder.append:(Ljava/lang/String;)Ljava/lang/StringBuilder;
    2463: ldc           #95                 // String :
    2465: invokevirtual #23                 // Method java/lang/StringBuilder.append:(Ljava/lang/String;)Ljava/lang/StringBuilder;
    2468: iload         31
    2470: invokevirtual #96                 // Method java/lang/StringBuilder.append:(I)Ljava/lang/StringBuilder;
    2473: ldc           #97                 // String /rs-status
    2475: invokevirtual #23                 // Method java/lang/StringBuilder.append:(Ljava/lang/String;)Ljava/lang/StringBuilder;
    2478: invokevirtual #24                 // Method java/lang/StringBuilder.toString:()Ljava/lang/String;
    2481: astore        32
    2483: aload         7
    2485: ldc           #152                // String \n                    <tr>\n                      <td><a href=\"
    2487: invokevirtual #16                 // Method javax/servlet/jsp/JspWriter.write:(Ljava/lang/String;)V
    2490: aload         7
    2492: aload         32
    2494: invokevirtual #47                 // Method javax/servlet/jsp/JspWriter.print:(Ljava/lang/String;)V
    2497: aload         7
    2499: bipush        34
    2501: invokevirtual #26                 // Method javax/servlet/jsp/JspWriter.write:(I)V
    2504: aload         7
    2506: bipush        62
    2508: invokevirtual #26                 // Method javax/servlet/jsp/JspWriter.write:(I)V
    2511: aload         7
    2513: aload         24
    2515: invokevirtual #99                 // Method org/apache/hadoop/hbase/ServerName.getServerName:()Ljava/lang/String;
    2518: invokevirtual #47                 // Method javax/servlet/jsp/JspWriter.print:(Ljava/lang/String;)V
    2521: aload         7
    2523: ldc           #153                // String </a></td>\n                      <td>
    2525: invokevirtual #16                 // Method javax/servlet/jsp/JspWriter.write:(Ljava/lang/String;)V
    2528: aload         7
    2530: lload         26
    2532: invokevirtual #105                // Method javax/servlet/jsp/JspWriter.print:(J)V
    2535: aload         7
    2537: ldc           #154                // String </td>\n                      <td>
    2539: invokevirtual #16                 // Method javax/servlet/jsp/JspWriter.write:(Ljava/lang/String;)V
    2542: aload         7
    2544: lload         28
    2546: invokevirtual #105                // Method javax/servlet/jsp/JspWriter.print:(J)V
    2549: aload         7
    2551: ldc           #154                // String </td>\n                      <td>
    2553: invokevirtual #16                 // Method javax/servlet/jsp/JspWriter.write:(Ljava/lang/String;)V
    2556: aload         7
    2558: lload         26
    2560: lload         28
    2562: lsub
    2563: invokevirtual #105                // Method javax/servlet/jsp/JspWriter.print:(J)V
    2566: aload         7
    2568: ldc           #154                // String </td>\n                      <td>
    2570: invokevirtual #16                 // Method javax/servlet/jsp/JspWriter.write:(Ljava/lang/String;)V
    2573: aload         7
    2575: aload         30
    2577: invokevirtual #47                 // Method javax/servlet/jsp/JspWriter.print:(Ljava/lang/String;)V
    2580: aload         7
    2582: ldc           #156                // String </td>\n                    </tr>\n
    2584: invokevirtual #16                 // Method javax/servlet/jsp/JspWriter.write:(Ljava/lang/String;)V
    2587: goto          2611
    2590: aload         7
    2592: ldc           #157                // String \n                    <tr>\n                      <td style=\"color:rgb(192,192,192);\">
    2594: invokevirtual #16                 // Method javax/servlet/jsp/JspWriter.write:(Ljava/lang/String;)V
    2597: aload         7
    2599: aload         23
    2601: invokevirtual #103                // Method javax/servlet/jsp/JspWriter.print:(Ljava/lang/Object;)V
    2604: aload         7
    2606: ldc           #167                // String </td>\n                      <td></td>\n                      <td></td>\n                      <td></td>\n                      <td></td>\n                    </tr>\n
    2608: invokevirtual #16                 // Method javax/servlet/jsp/JspWriter.write:(Ljava/lang/String;)V
    2611: goto          2244
    2614: aload         7
    2616: ldc           #168                // String \n          </table>\n        </div>\n      </div>\n
    2618: invokevirtual #16                 // Method javax/servlet/jsp/JspWriter.write:(Ljava/lang/String;)V
    2621: goto          2631
    2624: aload         7
    2626: ldc           #169                // String \n      <p> No Region Servers</p>\n
    2628: invokevirtual #16                 // Method javax/servlet/jsp/JspWriter.write:(Ljava/lang/String;)V
    2631: aload         7
    2633: ldc           #170                // String \n    </div>\n  </div>\n  <br />\n\n  <div class=\"container-fluid content\">\n    <div class=\"row inner_header\">\n        <div class=\"page-header\">\n            <h1>Tables</h1>\n        </div>\n    </div>\n\n
    2635: invokevirtual #16                 // Method javax/servlet/jsp/JspWriter.write:(Ljava/lang/String;)V
    2638: aload         15
    2640: ifnull        3393
    2643: aload         15
    2645: invokeinterface #71,  1           // InterfaceMethod java/util/List.size:()I
    2650: ifle          3393
    2653: aload         12
    2655: invokevirtual #39                 // Method org/apache/hadoop/hbase/master/HMaster.getConnection:()Lorg/apache/hadoop/hbase/client/Connection;
    2658: invokeinterface #171,  1          // InterfaceMethod org/apache/hadoop/hbase/client/Connection.getAdmin:()Lorg/apache/hadoop/hbase/client/Admin;
    2663: astore        19
    2665: aconst_null
    2666: astore        20
    2668: aload         12
    2670: invokevirtual #172                // Method org/apache/hadoop/hbase/master/HMaster.isInitialized:()Z
    2673: ifeq          2691
    2676: aload         19
    2678: aconst_null
    2679: checkcast     #173                // class java/util/regex/Pattern
    2682: iconst_1
    2683: invokeinterface #174,  3          // InterfaceMethod org/apache/hadoop/hbase/client/Admin.listTableDescriptors:(Ljava/util/regex/Pattern;Z)Ljava/util/List;
    2688: goto          2692
    2691: aconst_null
    2692: astore        18
    2694: aload         19
    2696: ifnull        2789
    2699: aload         20
    2701: ifnull        2726
    2704: aload         19
    2706: invokeinterface #175,  1          // InterfaceMethod org/apache/hadoop/hbase/client/Admin.close:()V
    2711: goto          2789
    2714: astore        21
    2716: aload         20
    2718: aload         21
    2720: invokevirtual #177                // Method java/lang/Throwable.addSuppressed:(Ljava/lang/Throwable;)V
    2723: goto          2789
    2726: aload         19
    2728: invokeinterface #175,  1          // InterfaceMethod org/apache/hadoop/hbase/client/Admin.close:()V
    2733: goto          2789
    2736: astore        21
    2738: aload         21
    2740: astore        20
    2742: aload         21
    2744: athrow
    2745: astore        40
    2747: aload         19
    2749: ifnull        2786
    2752: aload         20
    2754: ifnull        2779
    2757: aload         19
    2759: invokeinterface #175,  1          // InterfaceMethod org/apache/hadoop/hbase/client/Admin.close:()V
    2764: goto          2786
    2767: astore        41
    2769: aload         20
    2771: aload         41
    2773: invokevirtual #177                // Method java/lang/Throwable.addSuppressed:(Ljava/lang/Throwable;)V
    2776: goto          2786
    2779: aload         19
    2781: invokeinterface #175,  1          // InterfaceMethod org/apache/hadoop/hbase/client/Admin.close:()V
    2786: aload         40
    2788: athrow
    2789: aload         18
    2791: invokeinterface #178,  1          // InterfaceMethod java/util/List.stream:()Ljava/util/stream/Stream;
    2796: invokedynamic #179,  0            // InvokeDynamic #6:apply:()Ljava/util/function/Function;
    2801: invokedynamic #180,  0            // InvokeDynamic #7:apply:()Ljava/util/function/Function;
    2806: invokestatic  #64                 // Method java/util/stream/Collectors.toMap:(Ljava/util/function/Function;Ljava/util/function/Function;)Ljava/util/stream/Collector;
    2809: invokeinterface #65,  2           // InterfaceMethod java/util/stream/Stream.collect:(Ljava/util/stream/Collector;)Ljava/lang/Object;
    2814: checkcast     #66                 // class java/util/Map
    2817: astore        19
    2819: aload         7
    2821: ldc           #181                // String \n         <table class=\"table table-striped\">\n         <tr>\n             <th>Namespace</th>\n             <th>Table</th>\n             <th>Stats</th>\n             <th>Online Regions</th>\n             <th>Offline Regions</th>\n             <th>Failed Regions</th>\n             <th>Split Regions</th>\n             <th>Other Regions</th>\n             <th>Description</th>\n         </tr>\n
    2823: invokevirtual #16                 // Method javax/servlet/jsp/JspWriter.write:(Ljava/lang/String;)V
    2826: aload         15
    2828: invokeinterface #75,  1           // InterfaceMethod java/util/List.iterator:()Ljava/util/Iterator;
    2833: astore        20
    2835: aload         20
    2837: invokeinterface #76,  1           // InterfaceMethod java/util/Iterator.hasNext:()Z
    2842: ifeq          3364
    2845: aload         20
    2847: invokeinterface #77,  1           // InterfaceMethod java/util/Iterator.next:()Ljava/lang/Object;
    2852: checkcast     #182                // class org/apache/hadoop/hbase/TableName
    2855: astore        21
    2857: aload         19
    2859: aload         21
    2861: invokeinterface #79,  2           // InterfaceMethod java/util/Map.get:(Ljava/lang/Object;)Ljava/lang/Object;
    2866: checkcast     #183                // class org/apache/hadoop/hbase/HTableDescriptor
    2869: astore        22
    2871: aload         22
    2873: ifnonnull     2934
    2876: aload         7
    2878: ldc           #184                // String \n               <tr>\n                 <td>
    2880: invokevirtual #16                 // Method javax/servlet/jsp/JspWriter.write:(Ljava/lang/String;)V
    2883: aload         7
    2885: aload         21
    2887: invokevirtual #185                // Method org/apache/hadoop/hbase/TableName.getNamespaceAsString:()Ljava/lang/String;
    2890: invokevirtual #47                 // Method javax/servlet/jsp/JspWriter.print:(Ljava/lang/String;)V
    2893: aload         7
    2895: ldc           #186                // String </td>\n                 <td>
    2897: invokevirtual #16                 // Method javax/servlet/jsp/JspWriter.write:(Ljava/lang/String;)V
    2900: aload         7
    2902: aload         21
    2904: invokevirtual #187                // Method org/apache/hadoop/hbase/TableName.getQualifierAsString:()Ljava/lang/String;
    2907: invokevirtual #47                 // Method javax/servlet/jsp/JspWriter.print:(Ljava/lang/String;)V
    2910: aload         7
    2912: ldc           #188                // String </td>\n                 <td style=\"color:rgb(0,0,255);\">
    2914: invokevirtual #16                 // Method javax/servlet/jsp/JspWriter.write:(Ljava/lang/String;)V
    2917: aload         7
    2919: ldc           #189                // String DELETED
    2921: invokevirtual #47                 // Method javax/servlet/jsp/JspWriter.print:(Ljava/lang/String;)V
    2924: aload         7
    2926: ldc           #190                // String </td>\n                 <td></td>\n                 <td></td>\n                 <td></td>\n                 <td></td>\n                 <td></td>\n                 <td></td>\n               </tr>\n
    2928: invokevirtual #16                 // Method javax/servlet/jsp/JspWriter.write:(Ljava/lang/String;)V
    2931: goto          3361
    2934: aload         7
    2936: ldc           #191                // String \n                <tr>\n                  <td>
    2938: invokevirtual #16                 // Method javax/servlet/jsp/JspWriter.write:(Ljava/lang/String;)V
    2941: aload         7
    2943: aload         21
    2945: invokevirtual #185                // Method org/apache/hadoop/hbase/TableName.getNamespaceAsString:()Ljava/lang/String;
    2948: invokevirtual #47                 // Method javax/servlet/jsp/JspWriter.print:(Ljava/lang/String;)V
    2951: aload         7
    2953: ldc           #192                // String </td>\n                  <td><a href=\"/table.jsp?name=
    2955: invokevirtual #16                 // Method javax/servlet/jsp/JspWriter.write:(Ljava/lang/String;)V
    2958: aload         7
    2960: aload         21
    2962: invokevirtual #193                // Method org/apache/hadoop/hbase/TableName.getNameAsString:()Ljava/lang/String;
    2965: invokevirtual #47                 // Method javax/servlet/jsp/JspWriter.print:(Ljava/lang/String;)V
    2968: aload         7
    2970: bipush        34
    2972: invokevirtual #26                 // Method javax/servlet/jsp/JspWriter.write:(I)V
    2975: aload         7
    2977: bipush        62
    2979: invokevirtual #26                 // Method javax/servlet/jsp/JspWriter.write:(I)V
    2982: aload         7
    2984: aload         21
    2986: invokevirtual #187                // Method org/apache/hadoop/hbase/TableName.getQualifierAsString:()Ljava/lang/String;
    2989: invokevirtual #47                 // Method javax/servlet/jsp/JspWriter.print:(Ljava/lang/String;)V
    2992: aload         7
    2994: ldc           #194                // String </a></td>\n
    2996: invokevirtual #16                 // Method javax/servlet/jsp/JspWriter.write:(Ljava/lang/String;)V
    2999: aload         12
    3001: invokevirtual #195                // Method org/apache/hadoop/hbase/master/HMaster.getTableStateManager:()Lorg/apache/hadoop/hbase/master/TableStateManager;
    3004: aload         21
    3006: invokevirtual #196                // Method org/apache/hadoop/hbase/master/TableStateManager.getTableState:(Lorg/apache/hadoop/hbase/TableName;)Lorg/apache/hadoop/hbase/client/TableState;
    3009: astore        23
    3011: aload         23
    3013: invokevirtual #197                // Method org/apache/hadoop/hbase/client/TableState.isDisabledOrDisabling:()Z
    3016: ifeq          3049
    3019: aload         7
    3021: ldc           #198                // String \n                  <td style=\"color:red;\">
    3023: invokevirtual #16                 // Method javax/servlet/jsp/JspWriter.write:(Ljava/lang/String;)V
    3026: aload         7
    3028: aload         23
    3030: invokevirtual #199                // Method org/apache/hadoop/hbase/client/TableState.getState:()Lorg/apache/hadoop/hbase/client/TableState$State;
    3033: invokevirtual #200                // Method org/apache/hadoop/hbase/client/TableState$State.name:()Ljava/lang/String;
    3036: invokevirtual #47                 // Method javax/servlet/jsp/JspWriter.print:(Ljava/lang/String;)V
    3039: aload         7
    3041: ldc           #201                // String </td>\n
    3043: invokevirtual #16                 // Method javax/servlet/jsp/JspWriter.write:(Ljava/lang/String;)V
    3046: goto          3076
    3049: aload         7
    3051: ldc           #202                // String \n                  <td>
    3053: invokevirtual #16                 // Method javax/servlet/jsp/JspWriter.write:(Ljava/lang/String;)V
    3056: aload         7
    3058: aload         23
    3060: invokevirtual #199                // Method org/apache/hadoop/hbase/client/TableState.getState:()Lorg/apache/hadoop/hbase/client/TableState$State;
    3063: invokevirtual #200                // Method org/apache/hadoop/hbase/client/TableState$State.name:()Ljava/lang/String;
    3066: invokevirtual #47                 // Method javax/servlet/jsp/JspWriter.print:(Ljava/lang/String;)V
    3069: aload         7
    3071: ldc           #201                // String </td>\n
    3073: invokevirtual #16                 // Method javax/servlet/jsp/JspWriter.write:(Ljava/lang/String;)V
    3076: aload         7
    3078: ldc           #203                // String \n
    3080: invokevirtual #16                 // Method javax/servlet/jsp/JspWriter.write:(Ljava/lang/String;)V
    3083: aload         12
    3085: invokevirtual #204                // Method org/apache/hadoop/hbase/master/HMaster.getAssignmentManager:()Lorg/apache/hadoop/hbase/master/assignment/AssignmentManager;
    3088: invokevirtual #205                // Method org/apache/hadoop/hbase/master/assignment/AssignmentManager.getRegionStates:()Lorg/apache/hadoop/hbase/master/assignment/RegionStates;
    3091: aload         21
    3093: invokevirtual #206                // Method org/apache/hadoop/hbase/master/assignment/RegionStates.getRegionByStateOfTable:(Lorg/apache/hadoop/hbase/TableName;)Ljava/util/Map;
    3096: astore        24
    3098: aload         24
    3100: getstatic     #207                // Field org/apache/hadoop/hbase/master/RegionState$State.OPEN:Lorg/apache/hadoop/hbase/master/RegionState$State;
    3103: invokeinterface #79,  2           // InterfaceMethod java/util/Map.get:(Ljava/lang/Object;)Ljava/lang/Object;
    3108: checkcast     #208                // class java/util/List
    3111: invokeinterface #71,  1           // InterfaceMethod java/util/List.size:()I
    3116: istore        25
    3118: aload         24
    3120: getstatic     #209                // Field org/apache/hadoop/hbase/master/RegionState$State.OFFLINE:Lorg/apache/hadoop/hbase/master/RegionState$State;
    3123: invokeinterface #79,  2           // InterfaceMethod java/util/Map.get:(Ljava/lang/Object;)Ljava/lang/Object;
    3128: checkcast     #208                // class java/util/List
    3131: invokeinterface #71,  1           // InterfaceMethod java/util/List.size:()I
    3136: istore        26
    3138: aload         24
    3140: getstatic     #210                // Field org/apache/hadoop/hbase/master/RegionState$State.SPLIT:Lorg/apache/hadoop/hbase/master/RegionState$State;
    3143: invokeinterface #79,  2           // InterfaceMethod java/util/Map.get:(Ljava/lang/Object;)Ljava/lang/Object;
    3148: checkcast     #208                // class java/util/List
    3151: invokeinterface #71,  1           // InterfaceMethod java/util/List.size:()I
    3156: istore        27
    3158: aload         24
    3160: getstatic     #211                // Field org/apache/hadoop/hbase/master/RegionState$State.FAILED_OPEN:Lorg/apache/hadoop/hbase/master/RegionState$State;
    3163: invokeinterface #79,  2           // InterfaceMethod java/util/Map.get:(Ljava/lang/Object;)Ljava/lang/Object;
    3168: checkcast     #208                // class java/util/List
    3171: invokeinterface #71,  1           // InterfaceMethod java/util/List.size:()I
    3176: aload         24
    3178: getstatic     #212                // Field org/apache/hadoop/hbase/master/RegionState$State.FAILED_CLOSE:Lorg/apache/hadoop/hbase/master/RegionState$State;
    3181: invokeinterface #79,  2           // InterfaceMethod java/util/Map.get:(Ljava/lang/Object;)Ljava/lang/Object;
    3186: checkcast     #208                // class java/util/List
    3189: invokeinterface #71,  1           // InterfaceMethod java/util/List.size:()I
    3194: iadd
    3195: istore        28
    3197: iconst_0
    3198: istore        29
    3200: aload         24
    3202: invokeinterface #125,  1          // InterfaceMethod java/util/Map.values:()Ljava/util/Collection;
    3207: invokeinterface #140,  1          // InterfaceMethod java/util/Collection.iterator:()Ljava/util/Iterator;
    3212: astore        30
    3214: aload         30
    3216: invokeinterface #76,  1           // InterfaceMethod java/util/Iterator.hasNext:()Z
    3221: ifeq          3251
    3224: aload         30
    3226: invokeinterface #77,  1           // InterfaceMethod java/util/Iterator.next:()Ljava/lang/Object;
    3231: checkcast     #208                // class java/util/List
    3234: astore        31
    3236: iload         29
    3238: aload         31
    3240: invokeinterface #71,  1           // InterfaceMethod java/util/List.size:()I
    3245: iadd
    3246: istore        29
    3248: goto          3214
    3251: iload         29
    3253: iload         25
    3255: isub
    3256: iload         28
    3258: isub
    3259: iload         26
    3261: isub
    3262: iload         27
    3264: isub
    3265: istore        29
    3267: aload         7
    3269: ldc           #202                // String \n                  <td>
    3271: invokevirtual #16                 // Method javax/servlet/jsp/JspWriter.write:(Ljava/lang/String;)V
    3274: aload         7
    3276: iload         25
    3278: invokevirtual #110                // Method javax/servlet/jsp/JspWriter.print:(I)V
    3281: aload         7
    3283: ldc           #213                // String </td>\n                  <td>
    3285: invokevirtual #16                 // Method javax/servlet/jsp/JspWriter.write:(Ljava/lang/String;)V
    3288: aload         7
    3290: iload         26
    3292: invokevirtual #110                // Method javax/servlet/jsp/JspWriter.print:(I)V
    3295: aload         7
    3297: ldc           #213                // String </td>\n                  <td>
    3299: invokevirtual #16                 // Method javax/servlet/jsp/JspWriter.write:(Ljava/lang/String;)V
    3302: aload         7
    3304: iload         28
    3306: invokevirtual #110                // Method javax/servlet/jsp/JspWriter.print:(I)V
    3309: aload         7
    3311: ldc           #213                // String </td>\n                  <td>
    3313: invokevirtual #16                 // Method javax/servlet/jsp/JspWriter.write:(Ljava/lang/String;)V
    3316: aload         7
    3318: iload         27
    3320: invokevirtual #110                // Method javax/servlet/jsp/JspWriter.print:(I)V
    3323: aload         7
    3325: ldc           #213                // String </td>\n                  <td>
    3327: invokevirtual #16                 // Method javax/servlet/jsp/JspWriter.write:(Ljava/lang/String;)V
    3330: aload         7
    3332: iload         29
    3334: invokevirtual #110                // Method javax/servlet/jsp/JspWriter.print:(I)V
    3337: aload         7
    3339: ldc           #213                // String </td>\n                  <td>
    3341: invokevirtual #16                 // Method javax/servlet/jsp/JspWriter.write:(Ljava/lang/String;)V
    3344: aload         7
    3346: aload         22
    3348: invokevirtual #214                // Method org/apache/hadoop/hbase/HTableDescriptor.toStringCustomizedValues:()Ljava/lang/String;
    3351: invokevirtual #47                 // Method javax/servlet/jsp/JspWriter.print:(Ljava/lang/String;)V
    3354: aload         7
    3356: ldc           #215                // String </td>\n                </tr>\n
    3358: invokevirtual #16                 // Method javax/servlet/jsp/JspWriter.write:(Ljava/lang/String;)V
    3361: goto          2835
    3364: aload         7
    3366: ldc           #216                // String \n           <p>
    3368: invokevirtual #16                 // Method javax/servlet/jsp/JspWriter.write:(Ljava/lang/String;)V
    3371: aload         7
    3373: aload         15
    3375: invokeinterface #71,  1           // InterfaceMethod java/util/List.size:()I
    3380: invokevirtual #110                // Method javax/servlet/jsp/JspWriter.print:(I)V
    3383: aload         7
    3385: ldc           #217                // String  table(s) in set.</p>\n         </table>\n
    3387: invokevirtual #16                 // Method javax/servlet/jsp/JspWriter.write:(Ljava/lang/String;)V
    3390: goto          3400
    3393: aload         7
    3395: ldc           #218                // String \n      <p> No Tables</p>\n
    3397: invokevirtual #16                 // Method javax/servlet/jsp/JspWriter.write:(Ljava/lang/String;)V
    3400: aload         7
    3402: ldc           #219                // String \n  </div>\n
    3404: invokevirtual #16                 // Method javax/servlet/jsp/JspWriter.write:(Ljava/lang/String;)V
    3407: aload         7
    3409: ldc           #220                // String \n</div>\n
    3411: invokevirtual #16                 // Method javax/servlet/jsp/JspWriter.write:(Ljava/lang/String;)V
    3414: aload_1
    3415: aload_2
    3416: ldc           #221                // String footer.jsp
    3418: aload         7
    3420: iconst_0
    3421: invokestatic  #34                 // Method org/apache/jasper/runtime/JspRuntimeLibrary.include:(Ljavax/servlet/ServletRequest;Ljavax/servlet/ServletResponse;Ljava/lang/String;Ljavax/servlet/jsp/JspWriter;Z)V
    3424: aload         7
    3426: bipush        10
    3428: invokevirtual #26                 // Method javax/servlet/jsp/JspWriter.write:(I)V
    3431: getstatic     #5                  // Field _jspxFactory:Ljavax/servlet/jsp/JspFactory;
    3434: aload         10
    3436: invokevirtual #222                // Method javax/servlet/jsp/JspFactory.releasePageContext:(Ljavax/servlet/jsp/PageContext;)V
    3439: goto          3523
    3442: astore        11
    3444: aload         11
    3446: instanceof    #223                // class javax/servlet/jsp/SkipPageException
    3449: ifne          3499
    3452: aload         9
    3454: astore        7
    3456: aload         7
    3458: ifnull        3474
    3461: aload         7
    3463: invokevirtual #224                // Method javax/servlet/jsp/JspWriter.getBufferSize:()I
    3466: ifeq          3474
    3469: aload         7
    3471: invokevirtual #225                // Method javax/servlet/jsp/JspWriter.clearBuffer:()V
    3474: aload         10
    3476: ifnull        3489
    3479: aload         10
    3481: aload         11
    3483: invokevirtual #226                // Method javax/servlet/jsp/PageContext.handlePageException:(Ljava/lang/Throwable;)V
    3486: goto          3499
    3489: new           #227                // class javax/servlet/ServletException
    3492: dup
    3493: aload         11
    3495: invokespecial #228                // Method javax/servlet/ServletException."<init>":(Ljava/lang/Throwable;)V
    3498: athrow
    3499: getstatic     #5                  // Field _jspxFactory:Ljavax/servlet/jsp/JspFactory;
    3502: aload         10
    3504: invokevirtual #222                // Method javax/servlet/jsp/JspFactory.releasePageContext:(Ljavax/servlet/jsp/PageContext;)V
    3507: goto          3523
    3510: astore        42
    3512: getstatic     #5                  // Field _jspxFactory:Ljavax/servlet/jsp/JspFactory;
    3515: aload         10
    3517: invokevirtual #222                // Method javax/servlet/jsp/JspFactory.releasePageContext:(Ljavax/servlet/jsp/PageContext;)V
    3520: aload         42
    3522: athrow
    3523: return
    Exception table:
       from    to  target type
        2704  2711  2714   Class java/lang/Throwable
        2668  2694  2736   Class java/lang/Throwable
        2668  2694  2745   any
        2757  2764  2767   Class java/lang/Throwable
        2736  2747  2745   any
          23  3431  3442   Class java/lang/Throwable
          23  3431  3510   any
        3442  3499  3510   any
        3510  3512  3510   any

  static {};
    Code:
       0: invokestatic  #236                // Method javax/servlet/jsp/JspFactory.getDefaultFactory:()Ljavax/servlet/jsp/JspFactory;
       3: putstatic     #5                  // Field _jspxFactory:Ljavax/servlet/jsp/JspFactory;
       6: return
}
