Compiled from "ScannerContext.java"
public final class org.apache.hadoop.hbase.regionserver.ScannerContext$Builder {
  boolean keepProgress;

  boolean trackMetrics;

  org.apache.hadoop.hbase.regionserver.ScannerContext$LimitFields limits;

  public org.apache.hadoop.hbase.regionserver.ScannerContext$Builder setKeepProgress(boolean);
    Code:
       0: aload_0
       1: iload_1
       2: putfield      #5                  // Field keepProgress:Z
       5: aload_0
       6: areturn

  public org.apache.hadoop.hbase.regionserver.ScannerContext$Builder setTrackMetrics(boolean);
    Code:
       0: aload_0
       1: iload_1
       2: putfield      #6                  // Field trackMetrics:Z
       5: aload_0
       6: areturn

  public org.apache.hadoop.hbase.regionserver.ScannerContext$Builder setSizeLimit(org.apache.hadoop.hbase.regionserver.ScannerContext$LimitScope, long, long);
    Code:
       0: aload_0
       1: getfield      #9                  // Field limits:Lorg/apache/hadoop/hbase/regionserver/ScannerContext$LimitFields;
       4: lload_2
       5: invokevirtual #10                 // Method org/apache/hadoop/hbase/regionserver/ScannerContext$LimitFields.setDataSize:(J)V
       8: aload_0
       9: getfield      #9                  // Field limits:Lorg/apache/hadoop/hbase/regionserver/ScannerContext$LimitFields;
      12: lload         4
      14: invokevirtual #11                 // Method org/apache/hadoop/hbase/regionserver/ScannerContext$LimitFields.setHeapSize:(J)V
      17: aload_0
      18: getfield      #9                  // Field limits:Lorg/apache/hadoop/hbase/regionserver/ScannerContext$LimitFields;
      21: aload_1
      22: invokevirtual #12                 // Method org/apache/hadoop/hbase/regionserver/ScannerContext$LimitFields.setSizeScope:(Lorg/apache/hadoop/hbase/regionserver/ScannerContext$LimitScope;)V
      25: aload_0
      26: areturn

  public org.apache.hadoop.hbase.regionserver.ScannerContext$Builder setTimeLimit(org.apache.hadoop.hbase.regionserver.ScannerContext$LimitScope, long);
    Code:
       0: aload_0
       1: getfield      #9                  // Field limits:Lorg/apache/hadoop/hbase/regionserver/ScannerContext$LimitFields;
       4: lload_2
       5: invokevirtual #13                 // Method org/apache/hadoop/hbase/regionserver/ScannerContext$LimitFields.setTime:(J)V
       8: aload_0
       9: getfield      #9                  // Field limits:Lorg/apache/hadoop/hbase/regionserver/ScannerContext$LimitFields;
      12: aload_1
      13: invokevirtual #14                 // Method org/apache/hadoop/hbase/regionserver/ScannerContext$LimitFields.setTimeScope:(Lorg/apache/hadoop/hbase/regionserver/ScannerContext$LimitScope;)V
      16: aload_0
      17: areturn

  public org.apache.hadoop.hbase.regionserver.ScannerContext$Builder setBatchLimit(int);
    Code:
       0: aload_0
       1: getfield      #9                  // Field limits:Lorg/apache/hadoop/hbase/regionserver/ScannerContext$LimitFields;
       4: iload_1
       5: invokevirtual #15                 // Method org/apache/hadoop/hbase/regionserver/ScannerContext$LimitFields.setBatch:(I)V
       8: aload_0
       9: areturn

  public org.apache.hadoop.hbase.regionserver.ScannerContext build();
    Code:
       0: new           #16                 // class org/apache/hadoop/hbase/regionserver/ScannerContext
       3: dup
       4: aload_0
       5: getfield      #5                  // Field keepProgress:Z
       8: aload_0
       9: getfield      #9                  // Field limits:Lorg/apache/hadoop/hbase/regionserver/ScannerContext$LimitFields;
      12: aload_0
      13: getfield      #6                  // Field trackMetrics:Z
      16: invokespecial #17                 // Method org/apache/hadoop/hbase/regionserver/ScannerContext."<init>":(ZLorg/apache/hadoop/hbase/regionserver/ScannerContext$LimitFields;Z)V
      19: areturn

  org.apache.hadoop.hbase.regionserver.ScannerContext$Builder(org.apache.hadoop.hbase.regionserver.ScannerContext$1);
    Code:
       0: aload_0
       1: invokespecial #2                  // Method "<init>":()V
       4: return

  org.apache.hadoop.hbase.regionserver.ScannerContext$Builder(boolean, org.apache.hadoop.hbase.regionserver.ScannerContext$1);
    Code:
       0: aload_0
       1: iload_1
       2: invokespecial #1                  // Method "<init>":(Z)V
       5: return
}
