Compiled from "Scan.java"
public final class org.apache.hadoop.hbase.client.Scan$ReadType extends java.lang.Enum<org.apache.hadoop.hbase.client.Scan$ReadType> {
  public static final org.apache.hadoop.hbase.client.Scan$ReadType DEFAULT;

  public static final org.apache.hadoop.hbase.client.Scan$ReadType STREAM;

  public static final org.apache.hadoop.hbase.client.Scan$ReadType PREAD;

  public static org.apache.hadoop.hbase.client.Scan$ReadType[] values();
    Code:
       0: getstatic     #1                  // Field $VALUES:[Lorg/apache/hadoop/hbase/client/Scan$ReadType;
       3: invokevirtual #2                  // Method "[Lorg/apache/hadoop/hbase/client/Scan$ReadType;".clone:()Ljava/lang/Object;
       6: checkcast     #3                  // class "[Lorg/apache/hadoop/hbase/client/Scan$ReadType;"
       9: areturn

  public static org.apache.hadoop.hbase.client.Scan$ReadType valueOf(java.lang.String);
    Code:
       0: ldc           #4                  // class org/apache/hadoop/hbase/client/Scan$ReadType
       2: aload_0
       3: invokestatic  #5                  // Method java/lang/Enum.valueOf:(Ljava/lang/Class;Ljava/lang/String;)Ljava/lang/Enum;
       6: checkcast     #4                  // class org/apache/hadoop/hbase/client/Scan$ReadType
       9: areturn

  static {};
    Code:
       0: new           #4                  // class org/apache/hadoop/hbase/client/Scan$ReadType
       3: dup
       4: ldc           #7                  // String DEFAULT
       6: iconst_0
       7: invokespecial #8                  // Method "<init>":(Ljava/lang/String;I)V
      10: putstatic     #9                  // Field DEFAULT:Lorg/apache/hadoop/hbase/client/Scan$ReadType;
      13: new           #4                  // class org/apache/hadoop/hbase/client/Scan$ReadType
      16: dup
      17: ldc           #10                 // String STREAM
      19: iconst_1
      20: invokespecial #8                  // Method "<init>":(Ljava/lang/String;I)V
      23: putstatic     #11                 // Field STREAM:Lorg/apache/hadoop/hbase/client/Scan$ReadType;
      26: new           #4                  // class org/apache/hadoop/hbase/client/Scan$ReadType
      29: dup
      30: ldc           #12                 // String PREAD
      32: iconst_2
      33: invokespecial #8                  // Method "<init>":(Ljava/lang/String;I)V
      36: putstatic     #13                 // Field PREAD:Lorg/apache/hadoop/hbase/client/Scan$ReadType;
      39: iconst_3
      40: anewarray     #4                  // class org/apache/hadoop/hbase/client/Scan$ReadType
      43: dup
      44: iconst_0
      45: getstatic     #9                  // Field DEFAULT:Lorg/apache/hadoop/hbase/client/Scan$ReadType;
      48: aastore
      49: dup
      50: iconst_1
      51: getstatic     #11                 // Field STREAM:Lorg/apache/hadoop/hbase/client/Scan$ReadType;
      54: aastore
      55: dup
      56: iconst_2
      57: getstatic     #13                 // Field PREAD:Lorg/apache/hadoop/hbase/client/Scan$ReadType;
      60: aastore
      61: putstatic     #1                  // Field $VALUES:[Lorg/apache/hadoop/hbase/client/Scan$ReadType;
      64: return
}
