Compiled from "SchemaLocking.java"
class org.apache.hadoop.hbase.master.procedure.SchemaLocking {
  public org.apache.hadoop.hbase.master.procedure.SchemaLocking(java.util.function.Function<java.lang.Long, org.apache.hadoop.hbase.procedure2.Procedure<?>>);
    Code:
       0: aload_0
       1: invokespecial #1                  // Method java/lang/Object."<init>":()V
       4: aload_0
       5: new           #2                  // class java/util/HashMap
       8: dup
       9: invokespecial #3                  // Method java/util/HashMap."<init>":()V
      12: putfield      #4                  // Field serverLocks:Ljava/util/Map;
      15: aload_0
      16: new           #2                  // class java/util/HashMap
      19: dup
      20: invokespecial #3                  // Method java/util/HashMap."<init>":()V
      23: putfield      #5                  // Field namespaceLocks:Ljava/util/Map;
      26: aload_0
      27: new           #2                  // class java/util/HashMap
      30: dup
      31: invokespecial #3                  // Method java/util/HashMap."<init>":()V
      34: putfield      #6                  // Field tableLocks:Ljava/util/Map;
      37: aload_0
      38: new           #2                  // class java/util/HashMap
      41: dup
      42: invokespecial #3                  // Method java/util/HashMap."<init>":()V
      45: putfield      #7                  // Field regionLocks:Ljava/util/Map;
      48: aload_0
      49: new           #2                  // class java/util/HashMap
      52: dup
      53: invokespecial #3                  // Method java/util/HashMap."<init>":()V
      56: putfield      #8                  // Field peerLocks:Ljava/util/Map;
      59: aload_0
      60: aload_1
      61: putfield      #9                  // Field procedureRetriever:Ljava/util/function/Function;
      64: aload_0
      65: new           #10                 // class org/apache/hadoop/hbase/procedure2/LockAndQueue
      68: dup
      69: aload_1
      70: invokespecial #11                 // Method org/apache/hadoop/hbase/procedure2/LockAndQueue."<init>":(Ljava/util/function/Function;)V
      73: putfield      #12                 // Field metaLock:Lorg/apache/hadoop/hbase/procedure2/LockAndQueue;
      76: return

  org.apache.hadoop.hbase.procedure2.LockAndQueue getTableLock(org.apache.hadoop.hbase.TableName);
    Code:
       0: aload_0
       1: aload_0
       2: getfield      #6                  // Field tableLocks:Ljava/util/Map;
       5: aload_1
       6: invokespecial #15                 // Method getLock:(Ljava/util/Map;Ljava/lang/Object;)Lorg/apache/hadoop/hbase/procedure2/LockAndQueue;
       9: areturn

  org.apache.hadoop.hbase.procedure2.LockAndQueue removeTableLock(org.apache.hadoop.hbase.TableName);
    Code:
       0: aload_0
       1: getfield      #6                  // Field tableLocks:Ljava/util/Map;
       4: aload_1
       5: invokeinterface #16,  2           // InterfaceMethod java/util/Map.remove:(Ljava/lang/Object;)Ljava/lang/Object;
      10: checkcast     #10                 // class org/apache/hadoop/hbase/procedure2/LockAndQueue
      13: areturn

  org.apache.hadoop.hbase.procedure2.LockAndQueue getNamespaceLock(java.lang.String);
    Code:
       0: aload_0
       1: aload_0
       2: getfield      #5                  // Field namespaceLocks:Ljava/util/Map;
       5: aload_1
       6: invokespecial #15                 // Method getLock:(Ljava/util/Map;Ljava/lang/Object;)Lorg/apache/hadoop/hbase/procedure2/LockAndQueue;
       9: areturn

  org.apache.hadoop.hbase.procedure2.LockAndQueue getRegionLock(java.lang.String);
    Code:
       0: aload_0
       1: aload_0
       2: getfield      #7                  // Field regionLocks:Ljava/util/Map;
       5: aload_1
       6: invokespecial #15                 // Method getLock:(Ljava/util/Map;Ljava/lang/Object;)Lorg/apache/hadoop/hbase/procedure2/LockAndQueue;
       9: areturn

  org.apache.hadoop.hbase.procedure2.LockAndQueue getMetaLock();
    Code:
       0: aload_0
       1: getfield      #12                 // Field metaLock:Lorg/apache/hadoop/hbase/procedure2/LockAndQueue;
       4: areturn

  org.apache.hadoop.hbase.procedure2.LockAndQueue removeRegionLock(java.lang.String);
    Code:
       0: aload_0
       1: getfield      #7                  // Field regionLocks:Ljava/util/Map;
       4: aload_1
       5: invokeinterface #16,  2           // InterfaceMethod java/util/Map.remove:(Ljava/lang/Object;)Ljava/lang/Object;
      10: checkcast     #10                 // class org/apache/hadoop/hbase/procedure2/LockAndQueue
      13: areturn

  org.apache.hadoop.hbase.procedure2.LockAndQueue getServerLock(org.apache.hadoop.hbase.ServerName);
    Code:
       0: aload_0
       1: aload_0
       2: getfield      #4                  // Field serverLocks:Ljava/util/Map;
       5: aload_1
       6: invokespecial #15                 // Method getLock:(Ljava/util/Map;Ljava/lang/Object;)Lorg/apache/hadoop/hbase/procedure2/LockAndQueue;
       9: areturn

  org.apache.hadoop.hbase.procedure2.LockAndQueue removeServerLock(org.apache.hadoop.hbase.ServerName);
    Code:
       0: aload_0
       1: getfield      #4                  // Field serverLocks:Ljava/util/Map;
       4: aload_1
       5: invokeinterface #16,  2           // InterfaceMethod java/util/Map.remove:(Ljava/lang/Object;)Ljava/lang/Object;
      10: checkcast     #10                 // class org/apache/hadoop/hbase/procedure2/LockAndQueue
      13: areturn

  org.apache.hadoop.hbase.procedure2.LockAndQueue getPeerLock(java.lang.String);
    Code:
       0: aload_0
       1: aload_0
       2: getfield      #8                  // Field peerLocks:Ljava/util/Map;
       5: aload_1
       6: invokespecial #15                 // Method getLock:(Ljava/util/Map;Ljava/lang/Object;)Lorg/apache/hadoop/hbase/procedure2/LockAndQueue;
       9: areturn

  org.apache.hadoop.hbase.procedure2.LockAndQueue removePeerLock(java.lang.String);
    Code:
       0: aload_0
       1: getfield      #8                  // Field peerLocks:Ljava/util/Map;
       4: aload_1
       5: invokeinterface #16,  2           // InterfaceMethod java/util/Map.remove:(Ljava/lang/Object;)Ljava/lang/Object;
      10: checkcast     #10                 // class org/apache/hadoop/hbase/procedure2/LockAndQueue
      13: areturn

  java.util.List<org.apache.hadoop.hbase.procedure2.LockedResource> getLocks();
    Code:
       0: new           #22                 // class java/util/ArrayList
       3: dup
       4: invokespecial #23                 // Method java/util/ArrayList."<init>":()V
       7: astore_1
       8: aload_0
       9: aload_1
      10: aload_0
      11: getfield      #4                  // Field serverLocks:Ljava/util/Map;
      14: invokedynamic #38,  0             // InvokeDynamic #5:apply:()Ljava/util/function/Function;
      19: getstatic     #39                 // Field org/apache/hadoop/hbase/procedure2/LockedResourceType.SERVER:Lorg/apache/hadoop/hbase/procedure2/LockedResourceType;
      22: invokespecial #40                 // Method addToLockedResources:(Ljava/util/List;Ljava/util/Map;Ljava/util/function/Function;Lorg/apache/hadoop/hbase/procedure2/LockedResourceType;)V
      25: aload_0
      26: aload_1
      27: aload_0
      28: getfield      #5                  // Field namespaceLocks:Ljava/util/Map;
      31: invokestatic  #41                 // InterfaceMethod java/util/function/Function.identity:()Ljava/util/function/Function;
      34: getstatic     #42                 // Field org/apache/hadoop/hbase/procedure2/LockedResourceType.NAMESPACE:Lorg/apache/hadoop/hbase/procedure2/LockedResourceType;
      37: invokespecial #40                 // Method addToLockedResources:(Ljava/util/List;Ljava/util/Map;Ljava/util/function/Function;Lorg/apache/hadoop/hbase/procedure2/LockedResourceType;)V
      40: aload_0
      41: aload_1
      42: aload_0
      43: getfield      #6                  // Field tableLocks:Ljava/util/Map;
      46: invokedynamic #43,  0             // InvokeDynamic #6:apply:()Ljava/util/function/Function;
      51: getstatic     #44                 // Field org/apache/hadoop/hbase/procedure2/LockedResourceType.TABLE:Lorg/apache/hadoop/hbase/procedure2/LockedResourceType;
      54: invokespecial #40                 // Method addToLockedResources:(Ljava/util/List;Ljava/util/Map;Ljava/util/function/Function;Lorg/apache/hadoop/hbase/procedure2/LockedResourceType;)V
      57: aload_0
      58: aload_1
      59: aload_0
      60: getfield      #7                  // Field regionLocks:Ljava/util/Map;
      63: invokestatic  #41                 // InterfaceMethod java/util/function/Function.identity:()Ljava/util/function/Function;
      66: getstatic     #45                 // Field org/apache/hadoop/hbase/procedure2/LockedResourceType.REGION:Lorg/apache/hadoop/hbase/procedure2/LockedResourceType;
      69: invokespecial #40                 // Method addToLockedResources:(Ljava/util/List;Ljava/util/Map;Ljava/util/function/Function;Lorg/apache/hadoop/hbase/procedure2/LockedResourceType;)V
      72: aload_0
      73: aload_1
      74: aload_0
      75: getfield      #8                  // Field peerLocks:Ljava/util/Map;
      78: invokestatic  #41                 // InterfaceMethod java/util/function/Function.identity:()Ljava/util/function/Function;
      81: getstatic     #46                 // Field org/apache/hadoop/hbase/procedure2/LockedResourceType.PEER:Lorg/apache/hadoop/hbase/procedure2/LockedResourceType;
      84: invokespecial #40                 // Method addToLockedResources:(Ljava/util/List;Ljava/util/Map;Ljava/util/function/Function;Lorg/apache/hadoop/hbase/procedure2/LockedResourceType;)V
      87: aload_0
      88: aload_1
      89: getstatic     #47                 // Field org/apache/hadoop/hbase/TableName.META_TABLE_NAME:Lorg/apache/hadoop/hbase/TableName;
      92: aload_0
      93: getfield      #12                 // Field metaLock:Lorg/apache/hadoop/hbase/procedure2/LockAndQueue;
      96: invokestatic  #48                 // Method org/apache/hbase/thirdparty/com/google/common/collect/ImmutableMap.of:(Ljava/lang/Object;Ljava/lang/Object;)Lorg/apache/hbase/thirdparty/com/google/common/collect/ImmutableMap;
      99: invokedynamic #49,  0             // InvokeDynamic #7:apply:()Ljava/util/function/Function;
     104: getstatic     #50                 // Field org/apache/hadoop/hbase/procedure2/LockedResourceType.META:Lorg/apache/hadoop/hbase/procedure2/LockedResourceType;
     107: invokespecial #40                 // Method addToLockedResources:(Ljava/util/List;Ljava/util/Map;Ljava/util/function/Function;Lorg/apache/hadoop/hbase/procedure2/LockedResourceType;)V
     110: aload_1
     111: areturn

  org.apache.hadoop.hbase.procedure2.LockedResource getLockResource(org.apache.hadoop.hbase.procedure2.LockedResourceType, java.lang.String);
    Code:
       0: getstatic     #51                 // Field org/apache/hadoop/hbase/master/procedure/SchemaLocking$1.$SwitchMap$org$apache$hadoop$hbase$procedure2$LockedResourceType:[I
       3: aload_1
       4: invokevirtual #52                 // Method org/apache/hadoop/hbase/procedure2/LockedResourceType.ordinal:()I
       7: iaload
       8: tableswitch   { // 1 to 6
                     1: 48
                     2: 68
                     3: 85
                     4: 105
                     5: 122
                     6: 139
               default: 144
          }
      48: aload_0
      49: getfield      #4                  // Field serverLocks:Ljava/util/Map;
      52: aload_2
      53: invokestatic  #53                 // Method org/apache/hadoop/hbase/ServerName.valueOf:(Ljava/lang/String;)Lorg/apache/hadoop/hbase/ServerName;
      56: invokeinterface #13,  2           // InterfaceMethod java/util/Map.get:(Ljava/lang/Object;)Ljava/lang/Object;
      61: checkcast     #10                 // class org/apache/hadoop/hbase/procedure2/LockAndQueue
      64: astore_3
      65: goto          146
      68: aload_0
      69: getfield      #5                  // Field namespaceLocks:Ljava/util/Map;
      72: aload_2
      73: invokeinterface #13,  2           // InterfaceMethod java/util/Map.get:(Ljava/lang/Object;)Ljava/lang/Object;
      78: checkcast     #10                 // class org/apache/hadoop/hbase/procedure2/LockAndQueue
      81: astore_3
      82: goto          146
      85: aload_0
      86: getfield      #6                  // Field tableLocks:Ljava/util/Map;
      89: aload_2
      90: invokestatic  #54                 // Method org/apache/hadoop/hbase/TableName.valueOf:(Ljava/lang/String;)Lorg/apache/hadoop/hbase/TableName;
      93: invokeinterface #13,  2           // InterfaceMethod java/util/Map.get:(Ljava/lang/Object;)Ljava/lang/Object;
      98: checkcast     #10                 // class org/apache/hadoop/hbase/procedure2/LockAndQueue
     101: astore_3
     102: goto          146
     105: aload_0
     106: getfield      #7                  // Field regionLocks:Ljava/util/Map;
     109: aload_2
     110: invokeinterface #13,  2           // InterfaceMethod java/util/Map.get:(Ljava/lang/Object;)Ljava/lang/Object;
     115: checkcast     #10                 // class org/apache/hadoop/hbase/procedure2/LockAndQueue
     118: astore_3
     119: goto          146
     122: aload_0
     123: getfield      #8                  // Field peerLocks:Ljava/util/Map;
     126: aload_2
     127: invokeinterface #13,  2           // InterfaceMethod java/util/Map.get:(Ljava/lang/Object;)Ljava/lang/Object;
     132: checkcast     #10                 // class org/apache/hadoop/hbase/procedure2/LockAndQueue
     135: astore_3
     136: goto          146
     139: aload_0
     140: getfield      #12                 // Field metaLock:Lorg/apache/hadoop/hbase/procedure2/LockAndQueue;
     143: astore_3
     144: aconst_null
     145: astore_3
     146: aload_3
     147: ifnull        160
     150: aload_0
     151: aload_1
     152: aload_2
     153: aload_3
     154: invokespecial #55                 // Method createLockedResource:(Lorg/apache/hadoop/hbase/procedure2/LockedResourceType;Ljava/lang/String;Lorg/apache/hadoop/hbase/procedure2/LockAndQueue;)Lorg/apache/hadoop/hbase/procedure2/LockedResource;
     157: goto          161
     160: aconst_null
     161: areturn

  void clear();
    Code:
       0: aload_0
       1: getfield      #4                  // Field serverLocks:Ljava/util/Map;
       4: invokeinterface #56,  1           // InterfaceMethod java/util/Map.clear:()V
       9: aload_0
      10: getfield      #5                  // Field namespaceLocks:Ljava/util/Map;
      13: invokeinterface #56,  1           // InterfaceMethod java/util/Map.clear:()V
      18: aload_0
      19: getfield      #6                  // Field tableLocks:Ljava/util/Map;
      22: invokeinterface #56,  1           // InterfaceMethod java/util/Map.clear:()V
      27: aload_0
      28: getfield      #7                  // Field regionLocks:Ljava/util/Map;
      31: invokeinterface #56,  1           // InterfaceMethod java/util/Map.clear:()V
      36: aload_0
      37: getfield      #8                  // Field peerLocks:Ljava/util/Map;
      40: invokeinterface #56,  1           // InterfaceMethod java/util/Map.clear:()V
      45: return

  public java.lang.String toString();
    Code:
       0: new           #57                 // class java/lang/StringBuilder
       3: dup
       4: invokespecial #58                 // Method java/lang/StringBuilder."<init>":()V
       7: ldc           #59                 // String serverLocks=
       9: invokevirtual #60                 // Method java/lang/StringBuilder.append:(Ljava/lang/String;)Ljava/lang/StringBuilder;
      12: aload_0
      13: aload_0
      14: getfield      #4                  // Field serverLocks:Ljava/util/Map;
      17: invokespecial #61                 // Method filterUnlocked:(Ljava/util/Map;)Ljava/lang/String;
      20: invokevirtual #60                 // Method java/lang/StringBuilder.append:(Ljava/lang/String;)Ljava/lang/StringBuilder;
      23: ldc           #62                 // String , namespaceLocks=
      25: invokevirtual #60                 // Method java/lang/StringBuilder.append:(Ljava/lang/String;)Ljava/lang/StringBuilder;
      28: aload_0
      29: aload_0
      30: getfield      #5                  // Field namespaceLocks:Ljava/util/Map;
      33: invokespecial #61                 // Method filterUnlocked:(Ljava/util/Map;)Ljava/lang/String;
      36: invokevirtual #60                 // Method java/lang/StringBuilder.append:(Ljava/lang/String;)Ljava/lang/StringBuilder;
      39: ldc           #63                 // String , tableLocks=
      41: invokevirtual #60                 // Method java/lang/StringBuilder.append:(Ljava/lang/String;)Ljava/lang/StringBuilder;
      44: aload_0
      45: aload_0
      46: getfield      #6                  // Field tableLocks:Ljava/util/Map;
      49: invokespecial #61                 // Method filterUnlocked:(Ljava/util/Map;)Ljava/lang/String;
      52: invokevirtual #60                 // Method java/lang/StringBuilder.append:(Ljava/lang/String;)Ljava/lang/StringBuilder;
      55: ldc           #64                 // String , regionLocks=
      57: invokevirtual #60                 // Method java/lang/StringBuilder.append:(Ljava/lang/String;)Ljava/lang/StringBuilder;
      60: aload_0
      61: aload_0
      62: getfield      #7                  // Field regionLocks:Ljava/util/Map;
      65: invokespecial #61                 // Method filterUnlocked:(Ljava/util/Map;)Ljava/lang/String;
      68: invokevirtual #60                 // Method java/lang/StringBuilder.append:(Ljava/lang/String;)Ljava/lang/StringBuilder;
      71: ldc           #65                 // String , peerLocks=
      73: invokevirtual #60                 // Method java/lang/StringBuilder.append:(Ljava/lang/String;)Ljava/lang/StringBuilder;
      76: aload_0
      77: aload_0
      78: getfield      #8                  // Field peerLocks:Ljava/util/Map;
      81: invokespecial #61                 // Method filterUnlocked:(Ljava/util/Map;)Ljava/lang/String;
      84: invokevirtual #60                 // Method java/lang/StringBuilder.append:(Ljava/lang/String;)Ljava/lang/StringBuilder;
      87: ldc           #66                 // String , metaLocks=
      89: invokevirtual #60                 // Method java/lang/StringBuilder.append:(Ljava/lang/String;)Ljava/lang/StringBuilder;
      92: aload_0
      93: getstatic     #47                 // Field org/apache/hadoop/hbase/TableName.META_TABLE_NAME:Lorg/apache/hadoop/hbase/TableName;
      96: aload_0
      97: getfield      #12                 // Field metaLock:Lorg/apache/hadoop/hbase/procedure2/LockAndQueue;
     100: invokestatic  #48                 // Method org/apache/hbase/thirdparty/com/google/common/collect/ImmutableMap.of:(Ljava/lang/Object;Ljava/lang/Object;)Lorg/apache/hbase/thirdparty/com/google/common/collect/ImmutableMap;
     103: invokespecial #61                 // Method filterUnlocked:(Ljava/util/Map;)Ljava/lang/String;
     106: invokevirtual #60                 // Method java/lang/StringBuilder.append:(Ljava/lang/String;)Ljava/lang/StringBuilder;
     109: invokevirtual #67                 // Method java/lang/StringBuilder.toString:()Ljava/lang/String;
     112: areturn
}
