Compiled from "SecureWALCellCodec.java"
class org.apache.hadoop.hbase.regionserver.wal.SecureWALCellCodec$EncryptedKvEncoder extends org.apache.hadoop.hbase.codec.KeyValueCodecWithTags$KeyValueEncoder {
  protected byte[] nextIv();
    Code:
       0: aload_0
       1: getfield      #2                  // Field iv:Ljava/lang/ThreadLocal;
       4: invokevirtual #3                  // Method java/lang/ThreadLocal.get:()Ljava/lang/Object;
       7: checkcast     #4                  // class "[B"
      10: astore_1
      11: aload_1
      12: arraylength
      13: newarray       byte
      15: astore_2
      16: aload_1
      17: iconst_0
      18: aload_2
      19: iconst_0
      20: aload_1
      21: arraylength
      22: invokestatic  #5                  // Method java/lang/System.arraycopy:(Ljava/lang/Object;ILjava/lang/Object;II)V
      25: aload_2
      26: areturn

  protected void incrementIv(int);
    Code:
       0: aload_0
       1: getfield      #2                  // Field iv:Ljava/lang/ThreadLocal;
       4: invokevirtual #3                  // Method java/lang/ThreadLocal.get:()Ljava/lang/Object;
       7: checkcast     #4                  // class "[B"
      10: iconst_1
      11: iload_1
      12: aload_0
      13: getfield      #1                  // Field encryptor:Lorg/apache/hadoop/hbase/io/crypto/Encryptor;
      16: invokeinterface #6,  1            // InterfaceMethod org/apache/hadoop/hbase/io/crypto/Encryptor.getBlockSize:()I
      21: idiv
      22: iadd
      23: invokestatic  #7                  // Method org/apache/hadoop/hbase/io/crypto/Encryption.incrementIv:([BI)V
      26: return

  public org.apache.hadoop.hbase.regionserver.wal.SecureWALCellCodec$EncryptedKvEncoder(java.io.OutputStream);
    Code:
       0: aload_0
       1: aload_1
       2: invokespecial #8                  // Method org/apache/hadoop/hbase/codec/KeyValueCodecWithTags$KeyValueEncoder."<init>":(Ljava/io/OutputStream;)V
       5: aload_0
       6: new           #9                  // class org/apache/hadoop/hbase/regionserver/wal/SecureWALCellCodec$EncryptedKvEncoder$1
       9: dup
      10: aload_0
      11: invokespecial #10                 // Method org/apache/hadoop/hbase/regionserver/wal/SecureWALCellCodec$EncryptedKvEncoder$1."<init>":(Lorg/apache/hadoop/hbase/regionserver/wal/SecureWALCellCodec$EncryptedKvEncoder;)V
      14: putfield      #2                  // Field iv:Ljava/lang/ThreadLocal;
      17: return

  public org.apache.hadoop.hbase.regionserver.wal.SecureWALCellCodec$EncryptedKvEncoder(java.io.OutputStream, org.apache.hadoop.hbase.io.crypto.Encryptor);
    Code:
       0: aload_0
       1: aload_1
       2: invokespecial #8                  // Method org/apache/hadoop/hbase/codec/KeyValueCodecWithTags$KeyValueEncoder."<init>":(Ljava/io/OutputStream;)V
       5: aload_0
       6: new           #9                  // class org/apache/hadoop/hbase/regionserver/wal/SecureWALCellCodec$EncryptedKvEncoder$1
       9: dup
      10: aload_0
      11: invokespecial #10                 // Method org/apache/hadoop/hbase/regionserver/wal/SecureWALCellCodec$EncryptedKvEncoder$1."<init>":(Lorg/apache/hadoop/hbase/regionserver/wal/SecureWALCellCodec$EncryptedKvEncoder;)V
      14: putfield      #2                  // Field iv:Ljava/lang/ThreadLocal;
      17: aload_0
      18: aload_2
      19: putfield      #1                  // Field encryptor:Lorg/apache/hadoop/hbase/io/crypto/Encryptor;
      22: return

  public void write(org.apache.hadoop.hbase.Cell) throws java.io.IOException;
    Code:
       0: aload_0
       1: getfield      #1                  // Field encryptor:Lorg/apache/hadoop/hbase/io/crypto/Encryptor;
       4: ifnonnull     13
       7: aload_0
       8: aload_1
       9: invokespecial #11                 // Method org/apache/hadoop/hbase/codec/KeyValueCodecWithTags$KeyValueEncoder.write:(Lorg/apache/hadoop/hbase/Cell;)V
      12: return
      13: aload_0
      14: invokevirtual #12                 // Method nextIv:()[B
      17: astore_2
      18: aload_0
      19: getfield      #1                  // Field encryptor:Lorg/apache/hadoop/hbase/io/crypto/Encryptor;
      22: aload_2
      23: invokeinterface #13,  2           // InterfaceMethod org/apache/hadoop/hbase/io/crypto/Encryptor.setIv:([B)V
      28: aload_0
      29: getfield      #1                  // Field encryptor:Lorg/apache/hadoop/hbase/io/crypto/Encryptor;
      32: invokeinterface #14,  1           // InterfaceMethod org/apache/hadoop/hbase/io/crypto/Encryptor.reset:()V
      37: aload_0
      38: getfield      #15                 // Field out:Ljava/io/OutputStream;
      41: aload_2
      42: arraylength
      43: invokestatic  #16                 // Method org/apache/hadoop/hbase/io/util/StreamUtils.writeRawVInt32:(Ljava/io/OutputStream;I)V
      46: aload_0
      47: getfield      #15                 // Field out:Ljava/io/OutputStream;
      50: aload_2
      51: invokevirtual #17                 // Method java/io/OutputStream.write:([B)V
      54: new           #18                 // class java/io/ByteArrayOutputStream
      57: dup
      58: invokespecial #19                 // Method java/io/ByteArrayOutputStream."<init>":()V
      61: astore_3
      62: aload_0
      63: getfield      #1                  // Field encryptor:Lorg/apache/hadoop/hbase/io/crypto/Encryptor;
      66: aload_3
      67: invokeinterface #20,  2           // InterfaceMethod org/apache/hadoop/hbase/io/crypto/Encryptor.createEncryptionStream:(Ljava/io/OutputStream;)Ljava/io/OutputStream;
      72: astore        4
      74: new           #21                 // class org/apache/hadoop/hbase/io/ByteBufferWriterOutputStream
      77: dup
      78: aload         4
      80: invokespecial #22                 // Method org/apache/hadoop/hbase/io/ByteBufferWriterOutputStream."<init>":(Ljava/io/OutputStream;)V
      83: astore        5
      85: aload_1
      86: invokeinterface #23,  1           // InterfaceMethod org/apache/hadoop/hbase/Cell.getTagsLength:()I
      91: istore        6
      93: aload         5
      95: aload_1
      96: invokestatic  #24                 // Method org/apache/hadoop/hbase/KeyValueUtil.keyLength:(Lorg/apache/hadoop/hbase/Cell;)I
      99: invokestatic  #16                 // Method org/apache/hadoop/hbase/io/util/StreamUtils.writeRawVInt32:(Ljava/io/OutputStream;I)V
     102: aload         5
     104: aload_1
     105: invokeinterface #25,  1           // InterfaceMethod org/apache/hadoop/hbase/Cell.getValueLength:()I
     110: invokestatic  #16                 // Method org/apache/hadoop/hbase/io/util/StreamUtils.writeRawVInt32:(Ljava/io/OutputStream;I)V
     113: aload         5
     115: iload         6
     117: invokestatic  #16                 // Method org/apache/hadoop/hbase/io/util/StreamUtils.writeRawVInt32:(Ljava/io/OutputStream;I)V
     120: aload_1
     121: invokeinterface #26,  1           // InterfaceMethod org/apache/hadoop/hbase/Cell.getRowLength:()S
     126: istore        7
     128: aload         5
     130: iload         7
     132: invokestatic  #16                 // Method org/apache/hadoop/hbase/io/util/StreamUtils.writeRawVInt32:(Ljava/io/OutputStream;I)V
     135: aload         5
     137: aload_1
     138: iload         7
     140: invokestatic  #27                 // Method org/apache/hadoop/hbase/PrivateCellUtil.writeRow:(Ljava/io/OutputStream;Lorg/apache/hadoop/hbase/Cell;S)V
     143: aload_1
     144: invokeinterface #28,  1           // InterfaceMethod org/apache/hadoop/hbase/Cell.getFamilyLength:()B
     149: istore        8
     151: aload         5
     153: iload         8
     155: invokestatic  #16                 // Method org/apache/hadoop/hbase/io/util/StreamUtils.writeRawVInt32:(Ljava/io/OutputStream;I)V
     158: aload         5
     160: aload_1
     161: iload         8
     163: invokestatic  #29                 // Method org/apache/hadoop/hbase/PrivateCellUtil.writeFamily:(Ljava/io/OutputStream;Lorg/apache/hadoop/hbase/Cell;B)V
     166: aload_1
     167: invokeinterface #30,  1           // InterfaceMethod org/apache/hadoop/hbase/Cell.getQualifierLength:()I
     172: istore        9
     174: aload         5
     176: iload         9
     178: invokestatic  #16                 // Method org/apache/hadoop/hbase/io/util/StreamUtils.writeRawVInt32:(Ljava/io/OutputStream;I)V
     181: aload         5
     183: aload_1
     184: iload         9
     186: invokestatic  #31                 // Method org/apache/hadoop/hbase/PrivateCellUtil.writeQualifier:(Ljava/io/OutputStream;Lorg/apache/hadoop/hbase/Cell;I)V
     189: aload         5
     191: aload_1
     192: invokeinterface #32,  1           // InterfaceMethod org/apache/hadoop/hbase/Cell.getTimestamp:()J
     197: invokestatic  #33                 // Method org/apache/hadoop/hbase/io/util/StreamUtils.writeLong:(Ljava/io/OutputStream;J)V
     200: aload         5
     202: aload_1
     203: invokeinterface #34,  1           // InterfaceMethod org/apache/hadoop/hbase/Cell.getTypeByte:()B
     208: invokevirtual #35                 // Method org/apache/hadoop/hbase/io/ByteBufferWriterOutputStream.write:(I)V
     211: aload         5
     213: aload_1
     214: aload_1
     215: invokeinterface #25,  1           // InterfaceMethod org/apache/hadoop/hbase/Cell.getValueLength:()I
     220: invokestatic  #36                 // Method org/apache/hadoop/hbase/PrivateCellUtil.writeValue:(Ljava/io/OutputStream;Lorg/apache/hadoop/hbase/Cell;I)V
     223: iload         6
     225: ifle          236
     228: aload         5
     230: aload_1
     231: iload         6
     233: invokestatic  #37                 // Method org/apache/hadoop/hbase/PrivateCellUtil.writeTags:(Ljava/io/OutputStream;Lorg/apache/hadoop/hbase/Cell;I)V
     236: aload         5
     238: invokevirtual #38                 // Method org/apache/hadoop/hbase/io/ByteBufferWriterOutputStream.close:()V
     241: aload_0
     242: getfield      #15                 // Field out:Ljava/io/OutputStream;
     245: aload_3
     246: invokevirtual #39                 // Method java/io/ByteArrayOutputStream.size:()I
     249: invokestatic  #16                 // Method org/apache/hadoop/hbase/io/util/StreamUtils.writeRawVInt32:(Ljava/io/OutputStream;I)V
     252: aload_3
     253: aload_0
     254: getfield      #15                 // Field out:Ljava/io/OutputStream;
     257: invokevirtual #40                 // Method java/io/ByteArrayOutputStream.writeTo:(Ljava/io/OutputStream;)V
     260: aload_0
     261: aload_3
     262: invokevirtual #39                 // Method java/io/ByteArrayOutputStream.size:()I
     265: invokevirtual #41                 // Method incrementIv:(I)V
     268: return

  static org.apache.hadoop.hbase.io.crypto.Encryptor access$000(org.apache.hadoop.hbase.regionserver.wal.SecureWALCellCodec$EncryptedKvEncoder);
    Code:
       0: aload_0
       1: getfield      #1                  // Field encryptor:Lorg/apache/hadoop/hbase/io/crypto/Encryptor;
       4: areturn
}
