Compiled from "SecureBulkLoadClient.java"
class org.apache.hadoop.hbase.client.SecureBulkLoadClient$1 extends org.apache.hadoop.hbase.client.ClientServiceCallable<java.lang.String> {
  final org.apache.hadoop.hbase.client.SecureBulkLoadClient this$0;

  org.apache.hadoop.hbase.client.SecureBulkLoadClient$1(org.apache.hadoop.hbase.client.SecureBulkLoadClient, org.apache.hadoop.hbase.client.Connection, org.apache.hadoop.hbase.TableName, byte[], org.apache.hbase.thirdparty.com.google.protobuf.RpcController, int);
    Code:
       0: aload_0
       1: aload_1
       2: putfield      #1                  // Field this$0:Lorg/apache/hadoop/hbase/client/SecureBulkLoadClient;
       5: aload_0
       6: aload_2
       7: aload_3
       8: aload         4
      10: aload         5
      12: iload         6
      14: invokespecial #2                  // Method org/apache/hadoop/hbase/client/ClientServiceCallable."<init>":(Lorg/apache/hadoop/hbase/client/Connection;Lorg/apache/hadoop/hbase/TableName;[BLorg/apache/hbase/thirdparty/com/google/protobuf/RpcController;I)V
      17: return

  protected java.lang.String rpcCall() throws java.lang.Exception;
    Code:
       0: aload_0
       1: invokevirtual #3                  // Method getLocation:()Lorg/apache/hadoop/hbase/HRegionLocation;
       4: invokevirtual #4                  // Method org/apache/hadoop/hbase/HRegionLocation.getRegionInfo:()Lorg/apache/hadoop/hbase/HRegionInfo;
       7: invokevirtual #5                  // Method org/apache/hadoop/hbase/HRegionInfo.getRegionName:()[B
      10: astore_1
      11: getstatic     #6                  // Field org/apache/hadoop/hbase/shaded/protobuf/generated/HBaseProtos$RegionSpecifier$RegionSpecifierType.REGION_NAME:Lorg/apache/hadoop/hbase/shaded/protobuf/generated/HBaseProtos$RegionSpecifier$RegionSpecifierType;
      14: aload_1
      15: invokestatic  #7                  // Method org/apache/hadoop/hbase/shaded/protobuf/RequestConverter.buildRegionSpecifier:(Lorg/apache/hadoop/hbase/shaded/protobuf/generated/HBaseProtos$RegionSpecifier$RegionSpecifierType;[B)Lorg/apache/hadoop/hbase/shaded/protobuf/generated/HBaseProtos$RegionSpecifier;
      18: astore_2
      19: invokestatic  #8                  // Method org/apache/hadoop/hbase/shaded/protobuf/generated/ClientProtos$PrepareBulkLoadRequest.newBuilder:()Lorg/apache/hadoop/hbase/shaded/protobuf/generated/ClientProtos$PrepareBulkLoadRequest$Builder;
      22: aload_0
      23: getfield      #1                  // Field this$0:Lorg/apache/hadoop/hbase/client/SecureBulkLoadClient;
      26: invokestatic  #9                  // Method org/apache/hadoop/hbase/client/SecureBulkLoadClient.access$000:(Lorg/apache/hadoop/hbase/client/SecureBulkLoadClient;)Lorg/apache/hadoop/hbase/client/Table;
      29: invokeinterface #10,  1           // InterfaceMethod org/apache/hadoop/hbase/client/Table.getName:()Lorg/apache/hadoop/hbase/TableName;
      34: invokestatic  #11                 // Method org/apache/hadoop/hbase/shaded/protobuf/ProtobufUtil.toProtoTableName:(Lorg/apache/hadoop/hbase/TableName;)Lorg/apache/hadoop/hbase/shaded/protobuf/generated/HBaseProtos$TableName;
      37: invokevirtual #12                 // Method org/apache/hadoop/hbase/shaded/protobuf/generated/ClientProtos$PrepareBulkLoadRequest$Builder.setTableName:(Lorg/apache/hadoop/hbase/shaded/protobuf/generated/HBaseProtos$TableName;)Lorg/apache/hadoop/hbase/shaded/protobuf/generated/ClientProtos$PrepareBulkLoadRequest$Builder;
      40: aload_2
      41: invokevirtual #13                 // Method org/apache/hadoop/hbase/shaded/protobuf/generated/ClientProtos$PrepareBulkLoadRequest$Builder.setRegion:(Lorg/apache/hadoop/hbase/shaded/protobuf/generated/HBaseProtos$RegionSpecifier;)Lorg/apache/hadoop/hbase/shaded/protobuf/generated/ClientProtos$PrepareBulkLoadRequest$Builder;
      44: invokevirtual #14                 // Method org/apache/hadoop/hbase/shaded/protobuf/generated/ClientProtos$PrepareBulkLoadRequest$Builder.build:()Lorg/apache/hadoop/hbase/shaded/protobuf/generated/ClientProtos$PrepareBulkLoadRequest;
      47: astore_3
      48: aload_0
      49: invokevirtual #15                 // Method getStub:()Ljava/lang/Object;
      52: checkcast     #16                 // class org/apache/hadoop/hbase/shaded/protobuf/generated/ClientProtos$ClientService$BlockingInterface
      55: aconst_null
      56: aload_3
      57: invokeinterface #17,  3           // InterfaceMethod org/apache/hadoop/hbase/shaded/protobuf/generated/ClientProtos$ClientService$BlockingInterface.prepareBulkLoad:(Lorg/apache/hbase/thirdparty/com/google/protobuf/RpcController;Lorg/apache/hadoop/hbase/shaded/protobuf/generated/ClientProtos$PrepareBulkLoadRequest;)Lorg/apache/hadoop/hbase/shaded/protobuf/generated/ClientProtos$PrepareBulkLoadResponse;
      62: astore        4
      64: aload         4
      66: invokevirtual #18                 // Method org/apache/hadoop/hbase/shaded/protobuf/generated/ClientProtos$PrepareBulkLoadResponse.getBulkToken:()Ljava/lang/String;
      69: areturn

  protected java.lang.Object rpcCall() throws java.lang.Exception;
    Code:
       0: aload_0
       1: invokevirtual #19                 // Method rpcCall:()Ljava/lang/String;
       4: areturn
}
