Compiled from "SecureTestUtil.java"
public class org.apache.hadoop.hbase.security.access.SecureTestUtil {
  public org.apache.hadoop.hbase.security.access.SecureTestUtil();
    Code:
       0: aload_0
       1: invokespecial #3                  // Method java/lang/Object."<init>":()V
       4: return

  public static void configureSuperuser(org.apache.hadoop.conf.Configuration) throws java.io.IOException;
    Code:
       0: invokestatic  #4                  // Method org/apache/hadoop/hbase/security/User.getCurrent:()Lorg/apache/hadoop/hbase/security/User;
       3: invokevirtual #5                  // Method org/apache/hadoop/hbase/security/User.getName:()Ljava/lang/String;
       6: astore_1
       7: new           #6                  // class java/lang/StringBuilder
      10: dup
      11: invokespecial #7                  // Method java/lang/StringBuilder."<init>":()V
      14: astore_2
      15: aload_2
      16: ldc           #8                  // String admin,
      18: invokevirtual #9                  // Method java/lang/StringBuilder.append:(Ljava/lang/String;)Ljava/lang/StringBuilder;
      21: pop
      22: aload_2
      23: aload_1
      24: invokevirtual #9                  // Method java/lang/StringBuilder.append:(Ljava/lang/String;)Ljava/lang/StringBuilder;
      27: pop
      28: iconst_0
      29: istore_3
      30: iload_3
      31: iconst_5
      32: if_icmpge     67
      35: aload_2
      36: bipush        44
      38: invokevirtual #10                 // Method java/lang/StringBuilder.append:(C)Ljava/lang/StringBuilder;
      41: pop
      42: aload_2
      43: aload_1
      44: invokevirtual #9                  // Method java/lang/StringBuilder.append:(Ljava/lang/String;)Ljava/lang/StringBuilder;
      47: pop
      48: aload_2
      49: ldc           #11                 // String .hfs.
      51: invokevirtual #9                  // Method java/lang/StringBuilder.append:(Ljava/lang/String;)Ljava/lang/StringBuilder;
      54: pop
      55: aload_2
      56: iload_3
      57: invokevirtual #12                 // Method java/lang/StringBuilder.append:(I)Ljava/lang/StringBuilder;
      60: pop
      61: iinc          3, 1
      64: goto          30
      67: aload_2
      68: bipush        44
      70: invokevirtual #10                 // Method java/lang/StringBuilder.append:(C)Ljava/lang/StringBuilder;
      73: ldc           #13                 // String @supergroup
      75: invokevirtual #9                  // Method java/lang/StringBuilder.append:(Ljava/lang/String;)Ljava/lang/StringBuilder;
      78: pop
      79: aload_0
      80: ldc           #14                 // String hbase.superuser
      82: aload_2
      83: invokevirtual #15                 // Method java/lang/StringBuilder.toString:()Ljava/lang/String;
      86: invokevirtual #16                 // Method org/apache/hadoop/conf/Configuration.set:(Ljava/lang/String;Ljava/lang/String;)V
      89: aload_0
      90: ldc           #18                 // String hbase.group.service.for.test.only
      92: ldc           #19                 // String true
      94: invokevirtual #16                 // Method org/apache/hadoop/conf/Configuration.set:(Ljava/lang/String;Ljava/lang/String;)V
      97: return

  public static void enableSecurity(org.apache.hadoop.conf.Configuration) throws java.io.IOException;
    Code:
       0: aload_0
       1: ldc           #20                 // String hadoop.security.authorization
       3: ldc           #21                 // String false
       5: invokevirtual #16                 // Method org/apache/hadoop/conf/Configuration.set:(Ljava/lang/String;Ljava/lang/String;)V
       8: aload_0
       9: ldc           #22                 // String hadoop.security.authentication
      11: ldc           #23                 // String simple
      13: invokevirtual #16                 // Method org/apache/hadoop/conf/Configuration.set:(Ljava/lang/String;Ljava/lang/String;)V
      16: aload_0
      17: ldc           #25                 // String hbase.coprocessor.master.classes
      19: new           #6                  // class java/lang/StringBuilder
      22: dup
      23: invokespecial #7                  // Method java/lang/StringBuilder."<init>":()V
      26: ldc           #26                 // class org/apache/hadoop/hbase/security/access/AccessController
      28: invokevirtual #27                 // Method java/lang/Class.getName:()Ljava/lang/String;
      31: invokevirtual #9                  // Method java/lang/StringBuilder.append:(Ljava/lang/String;)Ljava/lang/StringBuilder;
      34: ldc           #28                 // String ,
      36: invokevirtual #9                  // Method java/lang/StringBuilder.append:(Ljava/lang/String;)Ljava/lang/StringBuilder;
      39: ldc           #29                 // class org/apache/hadoop/hbase/security/access/SecureTestUtil$MasterSyncObserver
      41: invokevirtual #27                 // Method java/lang/Class.getName:()Ljava/lang/String;
      44: invokevirtual #9                  // Method java/lang/StringBuilder.append:(Ljava/lang/String;)Ljava/lang/StringBuilder;
      47: invokevirtual #15                 // Method java/lang/StringBuilder.toString:()Ljava/lang/String;
      50: invokevirtual #16                 // Method org/apache/hadoop/conf/Configuration.set:(Ljava/lang/String;Ljava/lang/String;)V
      53: aload_0
      54: ldc           #30                 // String hbase.coprocessor.region.classes
      56: ldc           #26                 // class org/apache/hadoop/hbase/security/access/AccessController
      58: invokevirtual #27                 // Method java/lang/Class.getName:()Ljava/lang/String;
      61: invokevirtual #16                 // Method org/apache/hadoop/conf/Configuration.set:(Ljava/lang/String;Ljava/lang/String;)V
      64: aload_0
      65: ldc           #31                 // String hbase.coprocessor.regionserver.classes
      67: ldc           #26                 // class org/apache/hadoop/hbase/security/access/AccessController
      69: invokevirtual #27                 // Method java/lang/Class.getName:()Ljava/lang/String;
      72: invokevirtual #16                 // Method org/apache/hadoop/conf/Configuration.set:(Ljava/lang/String;Ljava/lang/String;)V
      75: aload_0
      76: ldc           #33                 // String hfile.format.version
      78: iconst_3
      79: invokevirtual #34                 // Method org/apache/hadoop/conf/Configuration.setInt:(Ljava/lang/String;I)V
      82: aload_0
      83: ldc           #36                 // String hbase.security.authorization
      85: ldc           #19                 // String true
      87: invokevirtual #16                 // Method org/apache/hadoop/conf/Configuration.set:(Ljava/lang/String;Ljava/lang/String;)V
      90: aload_0
      91: invokestatic  #37                 // Method configureSuperuser:(Lorg/apache/hadoop/conf/Configuration;)V
      94: return

  public static void verifyConfiguration(org.apache.hadoop.conf.Configuration);
    Code:
       0: aload_0
       1: ldc           #30                 // String hbase.coprocessor.region.classes
       3: invokevirtual #38                 // Method org/apache/hadoop/conf/Configuration.get:(Ljava/lang/String;)Ljava/lang/String;
       6: astore_1
       7: iconst_0
       8: istore_2
       9: aload_1
      10: ldc           #28                 // String ,
      12: invokevirtual #39                 // Method java/lang/String.split:(Ljava/lang/String;)[Ljava/lang/String;
      15: astore_3
      16: aload_3
      17: arraylength
      18: istore        4
      20: iconst_0
      21: istore        5
      23: iload         5
      25: iload         4
      27: if_icmpge     65
      30: aload_3
      31: iload         5
      33: aaload
      34: astore        6
      36: ldc           #26                 // class org/apache/hadoop/hbase/security/access/AccessController
      38: aload         6
      40: invokestatic  #40                 // Method java/lang/Class.forName:(Ljava/lang/String;)Ljava/lang/Class;
      43: invokevirtual #41                 // Method java/lang/Class.isAssignableFrom:(Ljava/lang/Class;)Z
      46: istore_2
      47: iload_2
      48: ifeq          54
      51: goto          65
      54: goto          59
      57: astore        7
      59: iinc          5, 1
      62: goto          23
      65: aload_0
      66: ldc           #25                 // String hbase.coprocessor.master.classes
      68: invokevirtual #38                 // Method org/apache/hadoop/conf/Configuration.get:(Ljava/lang/String;)Ljava/lang/String;
      71: ldc           #26                 // class org/apache/hadoop/hbase/security/access/AccessController
      73: invokevirtual #27                 // Method java/lang/Class.getName:()Ljava/lang/String;
      76: invokevirtual #43                 // Method java/lang/String.contains:(Ljava/lang/CharSequence;)Z
      79: ifeq          103
      82: iload_2
      83: ifeq          103
      86: aload_0
      87: ldc           #31                 // String hbase.coprocessor.regionserver.classes
      89: invokevirtual #38                 // Method org/apache/hadoop/conf/Configuration.get:(Ljava/lang/String;)Ljava/lang/String;
      92: ldc           #26                 // class org/apache/hadoop/hbase/security/access/AccessController
      94: invokevirtual #27                 // Method java/lang/Class.getName:()Ljava/lang/String;
      97: invokevirtual #43                 // Method java/lang/String.contains:(Ljava/lang/CharSequence;)Z
     100: ifne          113
     103: new           #44                 // class java/lang/RuntimeException
     106: dup
     107: ldc           #45                 // String AccessController is missing from a system coprocessor list
     109: invokespecial #46                 // Method java/lang/RuntimeException."<init>":(Ljava/lang/String;)V
     112: athrow
     113: aload_0
     114: ldc           #33                 // String hfile.format.version
     116: iconst_2
     117: invokevirtual #47                 // Method org/apache/hadoop/conf/Configuration.getInt:(Ljava/lang/String;I)I
     120: iconst_3
     121: if_icmpge     134
     124: new           #44                 // class java/lang/RuntimeException
     127: dup
     128: ldc           #48                 // String Post 0.96 security features require HFile version >= 3
     130: invokespecial #46                 // Method java/lang/RuntimeException."<init>":(Ljava/lang/String;)V
     133: athrow
     134: aload_0
     135: ldc           #36                 // String hbase.security.authorization
     137: iconst_0
     138: invokevirtual #49                 // Method org/apache/hadoop/conf/Configuration.getBoolean:(Ljava/lang/String;Z)Z
     141: ifne          154
     144: new           #44                 // class java/lang/RuntimeException
     147: dup
     148: ldc           #50                 // String Post 2.0.0 security features require set hbase.security.authorization to true
     150: invokespecial #46                 // Method java/lang/RuntimeException."<init>":(Ljava/lang/String;)V
     153: athrow
     154: return
    Exception table:
       from    to  target type
          36    51    57   Class java/lang/ClassNotFoundException

  public static void verifyAllowed(org.apache.hadoop.hbase.security.User, org.apache.hadoop.hbase.security.access.SecureTestUtil$AccessTestAction...) throws java.lang.Exception;
    Code:
       0: aload_1
       1: astore_2
       2: aload_2
       3: arraylength
       4: istore_3
       5: iconst_0
       6: istore        4
       8: iload         4
      10: iload_3
      11: if_icmpge     134
      14: aload_2
      15: iload         4
      17: aaload
      18: astore        5
      20: aload_0
      21: aload         5
      23: invokevirtual #51                 // Method org/apache/hadoop/hbase/security/User.runAs:(Ljava/security/PrivilegedExceptionAction;)Ljava/lang/Object;
      26: astore        6
      28: aload         6
      30: ifnull        93
      33: aload         6
      35: instanceof    #52                 // class java/util/List
      38: ifeq          93
      41: aload         6
      43: checkcast     #52                 // class java/util/List
      46: astore        7
      48: aload         7
      50: ifnull        93
      53: aload         7
      55: invokeinterface #53,  1           // InterfaceMethod java/util/List.isEmpty:()Z
      60: ifeq          93
      63: new           #6                  // class java/lang/StringBuilder
      66: dup
      67: invokespecial #7                  // Method java/lang/StringBuilder."<init>":()V
      70: ldc           #54                 // String Empty non null results from action for user '
      72: invokevirtual #9                  // Method java/lang/StringBuilder.append:(Ljava/lang/String;)Ljava/lang/StringBuilder;
      75: aload_0
      76: invokevirtual #55                 // Method org/apache/hadoop/hbase/security/User.getShortName:()Ljava/lang/String;
      79: invokevirtual #9                  // Method java/lang/StringBuilder.append:(Ljava/lang/String;)Ljava/lang/StringBuilder;
      82: ldc           #56                 // String '
      84: invokevirtual #9                  // Method java/lang/StringBuilder.append:(Ljava/lang/String;)Ljava/lang/StringBuilder;
      87: invokevirtual #15                 // Method java/lang/StringBuilder.toString:()Ljava/lang/String;
      90: invokestatic  #57                 // Method org/junit/Assert.fail:(Ljava/lang/String;)V
      93: goto          128
      96: astore        6
      98: new           #6                  // class java/lang/StringBuilder
     101: dup
     102: invokespecial #7                  // Method java/lang/StringBuilder."<init>":()V
     105: ldc           #59                 // String Expected action to pass for user '
     107: invokevirtual #9                  // Method java/lang/StringBuilder.append:(Ljava/lang/String;)Ljava/lang/StringBuilder;
     110: aload_0
     111: invokevirtual #55                 // Method org/apache/hadoop/hbase/security/User.getShortName:()Ljava/lang/String;
     114: invokevirtual #9                  // Method java/lang/StringBuilder.append:(Ljava/lang/String;)Ljava/lang/StringBuilder;
     117: ldc           #60                 // String ' but was denied
     119: invokevirtual #9                  // Method java/lang/StringBuilder.append:(Ljava/lang/String;)Ljava/lang/StringBuilder;
     122: invokevirtual #15                 // Method java/lang/StringBuilder.toString:()Ljava/lang/String;
     125: invokestatic  #57                 // Method org/junit/Assert.fail:(Ljava/lang/String;)V
     128: iinc          4, 1
     131: goto          8
     134: return
    Exception table:
       from    to  target type
          20    93    96   Class org/apache/hadoop/hbase/security/AccessDeniedException

  public static void verifyAllowed(org.apache.hadoop.hbase.security.access.SecureTestUtil$AccessTestAction, org.apache.hadoop.hbase.security.User...) throws java.lang.Exception;
    Code:
       0: aload_1
       1: astore_2
       2: aload_2
       3: arraylength
       4: istore_3
       5: iconst_0
       6: istore        4
       8: iload         4
      10: iload_3
      11: if_icmpge     39
      14: aload_2
      15: iload         4
      17: aaload
      18: astore        5
      20: aload         5
      22: iconst_1
      23: anewarray     #61                 // class org/apache/hadoop/hbase/security/access/SecureTestUtil$AccessTestAction
      26: dup
      27: iconst_0
      28: aload_0
      29: aastore
      30: invokestatic  #62                 // Method verifyAllowed:(Lorg/apache/hadoop/hbase/security/User;[Lorg/apache/hadoop/hbase/security/access/SecureTestUtil$AccessTestAction;)V
      33: iinc          4, 1
      36: goto          8
      39: return

  public static void verifyAllowed(org.apache.hadoop.hbase.security.User, org.apache.hadoop.hbase.security.access.SecureTestUtil$AccessTestAction, int) throws java.lang.Exception;
    Code:
       0: aload_0
       1: aload_1
       2: invokevirtual #51                 // Method org/apache/hadoop/hbase/security/User.runAs:(Ljava/security/PrivilegedExceptionAction;)Ljava/lang/Object;
       5: astore_3
       6: aload_3
       7: ifnull        81
      10: aload_3
      11: instanceof    #52                 // class java/util/List
      14: ifeq          81
      17: aload_3
      18: checkcast     #52                 // class java/util/List
      21: astore        4
      23: aload         4
      25: ifnull        68
      28: aload         4
      30: invokeinterface #53,  1           // InterfaceMethod java/util/List.isEmpty:()Z
      35: ifeq          68
      38: new           #6                  // class java/lang/StringBuilder
      41: dup
      42: invokespecial #7                  // Method java/lang/StringBuilder."<init>":()V
      45: ldc           #54                 // String Empty non null results from action for user '
      47: invokevirtual #9                  // Method java/lang/StringBuilder.append:(Ljava/lang/String;)Ljava/lang/StringBuilder;
      50: aload_0
      51: invokevirtual #55                 // Method org/apache/hadoop/hbase/security/User.getShortName:()Ljava/lang/String;
      54: invokevirtual #9                  // Method java/lang/StringBuilder.append:(Ljava/lang/String;)Ljava/lang/StringBuilder;
      57: ldc           #56                 // String '
      59: invokevirtual #9                  // Method java/lang/StringBuilder.append:(Ljava/lang/String;)Ljava/lang/StringBuilder;
      62: invokevirtual #15                 // Method java/lang/StringBuilder.toString:()Ljava/lang/String;
      65: invokestatic  #57                 // Method org/junit/Assert.fail:(Ljava/lang/String;)V
      68: iload_2
      69: i2l
      70: aload         4
      72: invokeinterface #63,  1           // InterfaceMethod java/util/List.size:()I
      77: i2l
      78: invokestatic  #64                 // Method org/junit/Assert.assertEquals:(JJ)V
      81: goto          115
      84: astore_3
      85: new           #6                  // class java/lang/StringBuilder
      88: dup
      89: invokespecial #7                  // Method java/lang/StringBuilder."<init>":()V
      92: ldc           #59                 // String Expected action to pass for user '
      94: invokevirtual #9                  // Method java/lang/StringBuilder.append:(Ljava/lang/String;)Ljava/lang/StringBuilder;
      97: aload_0
      98: invokevirtual #55                 // Method org/apache/hadoop/hbase/security/User.getShortName:()Ljava/lang/String;
     101: invokevirtual #9                  // Method java/lang/StringBuilder.append:(Ljava/lang/String;)Ljava/lang/StringBuilder;
     104: ldc           #60                 // String ' but was denied
     106: invokevirtual #9                  // Method java/lang/StringBuilder.append:(Ljava/lang/String;)Ljava/lang/StringBuilder;
     109: invokevirtual #15                 // Method java/lang/StringBuilder.toString:()Ljava/lang/String;
     112: invokestatic  #57                 // Method org/junit/Assert.fail:(Ljava/lang/String;)V
     115: return
    Exception table:
       from    to  target type
           0    81    84   Class org/apache/hadoop/hbase/security/AccessDeniedException

  public static void verifyDenied(org.apache.hadoop.hbase.security.access.SecureTestUtil$AccessTestAction, org.apache.hadoop.hbase.security.User...) throws java.lang.Exception;
    Code:
       0: aload_1
       1: astore_2
       2: aload_2
       3: arraylength
       4: istore_3
       5: iconst_0
       6: istore        4
       8: iload         4
      10: iload_3
      11: if_icmpge     39
      14: aload_2
      15: iload         4
      17: aaload
      18: astore        5
      20: aload         5
      22: iconst_1
      23: anewarray     #61                 // class org/apache/hadoop/hbase/security/access/SecureTestUtil$AccessTestAction
      26: dup
      27: iconst_0
      28: aload_0
      29: aastore
      30: invokestatic  #65                 // Method verifyDenied:(Lorg/apache/hadoop/hbase/security/User;[Lorg/apache/hadoop/hbase/security/access/SecureTestUtil$AccessTestAction;)V
      33: iinc          4, 1
      36: goto          8
      39: return

  public static void verifyIfEmptyList(org.apache.hadoop.hbase.security.access.SecureTestUtil$AccessTestAction, org.apache.hadoop.hbase.security.User...) throws java.lang.Exception;
    Code:
       0: aload_1
       1: astore_2
       2: aload_2
       3: arraylength
       4: istore_3
       5: iconst_0
       6: istore        4
       8: iload         4
      10: iload_3
      11: if_icmpge     180
      14: aload_2
      15: iload         4
      17: aaload
      18: astore        5
      20: aload         5
      22: aload_0
      23: invokevirtual #51                 // Method org/apache/hadoop/hbase/security/User.runAs:(Ljava/security/PrivilegedExceptionAction;)Ljava/lang/Object;
      26: astore        6
      28: aload         6
      30: ifnull        107
      33: aload         6
      35: instanceof    #52                 // class java/util/List
      38: ifeq          107
      41: aload         6
      43: checkcast     #52                 // class java/util/List
      46: astore        7
      48: aload         7
      50: ifnull        104
      53: aload         7
      55: invokeinterface #53,  1           // InterfaceMethod java/util/List.isEmpty:()Z
      60: ifne          104
      63: new           #6                  // class java/lang/StringBuilder
      66: dup
      67: invokespecial #7                  // Method java/lang/StringBuilder."<init>":()V
      70: ldc           #66                 // String Unexpected action results:
      72: invokevirtual #9                  // Method java/lang/StringBuilder.append:(Ljava/lang/String;)Ljava/lang/StringBuilder;
      75: aload         7
      77: invokevirtual #67                 // Method java/lang/StringBuilder.append:(Ljava/lang/Object;)Ljava/lang/StringBuilder;
      80: ldc           #68                 // String  for user '
      82: invokevirtual #9                  // Method java/lang/StringBuilder.append:(Ljava/lang/String;)Ljava/lang/StringBuilder;
      85: aload         5
      87: invokevirtual #55                 // Method org/apache/hadoop/hbase/security/User.getShortName:()Ljava/lang/String;
      90: invokevirtual #9                  // Method java/lang/StringBuilder.append:(Ljava/lang/String;)Ljava/lang/StringBuilder;
      93: ldc           #56                 // String '
      95: invokevirtual #9                  // Method java/lang/StringBuilder.append:(Ljava/lang/String;)Ljava/lang/StringBuilder;
      98: invokevirtual #15                 // Method java/lang/StringBuilder.toString:()Ljava/lang/String;
     101: invokestatic  #57                 // Method org/junit/Assert.fail:(Ljava/lang/String;)V
     104: goto          138
     107: new           #6                  // class java/lang/StringBuilder
     110: dup
     111: invokespecial #7                  // Method java/lang/StringBuilder."<init>":()V
     114: ldc           #69                 // String Unexpected results for user '
     116: invokevirtual #9                  // Method java/lang/StringBuilder.append:(Ljava/lang/String;)Ljava/lang/StringBuilder;
     119: aload         5
     121: invokevirtual #55                 // Method org/apache/hadoop/hbase/security/User.getShortName:()Ljava/lang/String;
     124: invokevirtual #9                  // Method java/lang/StringBuilder.append:(Ljava/lang/String;)Ljava/lang/StringBuilder;
     127: ldc           #56                 // String '
     129: invokevirtual #9                  // Method java/lang/StringBuilder.append:(Ljava/lang/String;)Ljava/lang/StringBuilder;
     132: invokevirtual #15                 // Method java/lang/StringBuilder.toString:()Ljava/lang/String;
     135: invokestatic  #57                 // Method org/junit/Assert.fail:(Ljava/lang/String;)V
     138: goto          174
     141: astore        6
     143: new           #6                  // class java/lang/StringBuilder
     146: dup
     147: invokespecial #7                  // Method java/lang/StringBuilder."<init>":()V
     150: ldc           #59                 // String Expected action to pass for user '
     152: invokevirtual #9                  // Method java/lang/StringBuilder.append:(Ljava/lang/String;)Ljava/lang/StringBuilder;
     155: aload         5
     157: invokevirtual #55                 // Method org/apache/hadoop/hbase/security/User.getShortName:()Ljava/lang/String;
     160: invokevirtual #9                  // Method java/lang/StringBuilder.append:(Ljava/lang/String;)Ljava/lang/StringBuilder;
     163: ldc           #60                 // String ' but was denied
     165: invokevirtual #9                  // Method java/lang/StringBuilder.append:(Ljava/lang/String;)Ljava/lang/StringBuilder;
     168: invokevirtual #15                 // Method java/lang/StringBuilder.toString:()Ljava/lang/String;
     171: invokestatic  #57                 // Method org/junit/Assert.fail:(Ljava/lang/String;)V
     174: iinc          4, 1
     177: goto          8
     180: return
    Exception table:
       from    to  target type
          20   138   141   Class org/apache/hadoop/hbase/security/AccessDeniedException

  public static void verifyIfNull(org.apache.hadoop.hbase.security.access.SecureTestUtil$AccessTestAction, org.apache.hadoop.hbase.security.User...) throws java.lang.Exception;
    Code:
       0: aload_1
       1: astore_2
       2: aload_2
       3: arraylength
       4: istore_3
       5: iconst_0
       6: istore        4
       8: iload         4
      10: iload_3
      11: if_icmpge     111
      14: aload_2
      15: iload         4
      17: aaload
      18: astore        5
      20: aload         5
      22: aload_0
      23: invokevirtual #51                 // Method org/apache/hadoop/hbase/security/User.runAs:(Ljava/security/PrivilegedExceptionAction;)Ljava/lang/Object;
      26: astore        6
      28: aload         6
      30: ifnull        69
      33: new           #6                  // class java/lang/StringBuilder
      36: dup
      37: invokespecial #7                  // Method java/lang/StringBuilder."<init>":()V
      40: ldc           #70                 // String Non null results from action for user '
      42: invokevirtual #9                  // Method java/lang/StringBuilder.append:(Ljava/lang/String;)Ljava/lang/StringBuilder;
      45: aload         5
      47: invokevirtual #55                 // Method org/apache/hadoop/hbase/security/User.getShortName:()Ljava/lang/String;
      50: invokevirtual #9                  // Method java/lang/StringBuilder.append:(Ljava/lang/String;)Ljava/lang/StringBuilder;
      53: ldc           #71                 // String ' :
      55: invokevirtual #9                  // Method java/lang/StringBuilder.append:(Ljava/lang/String;)Ljava/lang/StringBuilder;
      58: aload         6
      60: invokevirtual #67                 // Method java/lang/StringBuilder.append:(Ljava/lang/Object;)Ljava/lang/StringBuilder;
      63: invokevirtual #15                 // Method java/lang/StringBuilder.toString:()Ljava/lang/String;
      66: invokestatic  #57                 // Method org/junit/Assert.fail:(Ljava/lang/String;)V
      69: goto          105
      72: astore        6
      74: new           #6                  // class java/lang/StringBuilder
      77: dup
      78: invokespecial #7                  // Method java/lang/StringBuilder."<init>":()V
      81: ldc           #59                 // String Expected action to pass for user '
      83: invokevirtual #9                  // Method java/lang/StringBuilder.append:(Ljava/lang/String;)Ljava/lang/StringBuilder;
      86: aload         5
      88: invokevirtual #55                 // Method org/apache/hadoop/hbase/security/User.getShortName:()Ljava/lang/String;
      91: invokevirtual #9                  // Method java/lang/StringBuilder.append:(Ljava/lang/String;)Ljava/lang/StringBuilder;
      94: ldc           #60                 // String ' but was denied
      96: invokevirtual #9                  // Method java/lang/StringBuilder.append:(Ljava/lang/String;)Ljava/lang/StringBuilder;
      99: invokevirtual #15                 // Method java/lang/StringBuilder.toString:()Ljava/lang/String;
     102: invokestatic  #57                 // Method org/junit/Assert.fail:(Ljava/lang/String;)V
     105: iinc          4, 1
     108: goto          8
     111: return
    Exception table:
       from    to  target type
          20    69    72   Class org/apache/hadoop/hbase/security/AccessDeniedException

  public static void verifyDenied(org.apache.hadoop.hbase.security.User, org.apache.hadoop.hbase.security.access.SecureTestUtil$AccessTestAction...) throws java.lang.Exception;
    Code:
       0: aload_1
       1: astore_2
       2: aload_2
       3: arraylength
       4: istore_3
       5: iconst_0
       6: istore        4
       8: iload         4
      10: iload_3
      11: if_icmpge     295
      14: aload_2
      15: iload         4
      17: aaload
      18: astore        5
      20: aload_0
      21: aload         5
      23: invokevirtual #51                 // Method org/apache/hadoop/hbase/security/User.runAs:(Ljava/security/PrivilegedExceptionAction;)Ljava/lang/Object;
      26: pop
      27: new           #6                  // class java/lang/StringBuilder
      30: dup
      31: invokespecial #7                  // Method java/lang/StringBuilder."<init>":()V
      34: ldc           #72                 // String Expected exception was not thrown for user '
      36: invokevirtual #9                  // Method java/lang/StringBuilder.append:(Ljava/lang/String;)Ljava/lang/StringBuilder;
      39: aload_0
      40: invokevirtual #55                 // Method org/apache/hadoop/hbase/security/User.getShortName:()Ljava/lang/String;
      43: invokevirtual #9                  // Method java/lang/StringBuilder.append:(Ljava/lang/String;)Ljava/lang/StringBuilder;
      46: ldc           #56                 // String '
      48: invokevirtual #9                  // Method java/lang/StringBuilder.append:(Ljava/lang/String;)Ljava/lang/StringBuilder;
      51: invokevirtual #15                 // Method java/lang/StringBuilder.toString:()Ljava/lang/String;
      54: invokestatic  #57                 // Method org/junit/Assert.fail:(Ljava/lang/String;)V
      57: goto          289
      60: astore        6
      62: iconst_0
      63: istore        7
      65: aload         6
      67: instanceof    #74                 // class org/apache/hadoop/hbase/client/RetriesExhaustedWithDetailsException
      70: ifeq          130
      73: aload         6
      75: checkcast     #74                 // class org/apache/hadoop/hbase/client/RetriesExhaustedWithDetailsException
      78: invokevirtual #75                 // Method org/apache/hadoop/hbase/client/RetriesExhaustedWithDetailsException.getCauses:()Ljava/util/List;
      81: invokeinterface #76,  1           // InterfaceMethod java/util/List.iterator:()Ljava/util/Iterator;
      86: astore        8
      88: aload         8
      90: invokeinterface #77,  1           // InterfaceMethod java/util/Iterator.hasNext:()Z
      95: ifeq          127
      98: aload         8
     100: invokeinterface #78,  1           // InterfaceMethod java/util/Iterator.next:()Ljava/lang/Object;
     105: checkcast     #79                 // class java/lang/Throwable
     108: astore        9
     110: aload         9
     112: instanceof    #58                 // class org/apache/hadoop/hbase/security/AccessDeniedException
     115: ifeq          124
     118: iconst_1
     119: istore        7
     121: goto          127
     124: goto          88
     127: goto          159
     130: aload         6
     132: astore        8
     134: aload         8
     136: instanceof    #58                 // class org/apache/hadoop/hbase/security/AccessDeniedException
     139: ifeq          148
     142: iconst_1
     143: istore        7
     145: goto          159
     148: aload         8
     150: invokevirtual #80                 // Method java/lang/Throwable.getCause:()Ljava/lang/Throwable;
     153: dup
     154: astore        8
     156: ifnonnull     134
     159: iload         7
     161: ifne          194
     164: new           #6                  // class java/lang/StringBuilder
     167: dup
     168: invokespecial #7                  // Method java/lang/StringBuilder."<init>":()V
     171: ldc           #72                 // String Expected exception was not thrown for user '
     173: invokevirtual #9                  // Method java/lang/StringBuilder.append:(Ljava/lang/String;)Ljava/lang/StringBuilder;
     176: aload_0
     177: invokevirtual #55                 // Method org/apache/hadoop/hbase/security/User.getShortName:()Ljava/lang/String;
     180: invokevirtual #9                  // Method java/lang/StringBuilder.append:(Ljava/lang/String;)Ljava/lang/StringBuilder;
     183: ldc           #56                 // String '
     185: invokevirtual #9                  // Method java/lang/StringBuilder.append:(Ljava/lang/String;)Ljava/lang/StringBuilder;
     188: invokevirtual #15                 // Method java/lang/StringBuilder.toString:()Ljava/lang/String;
     191: invokestatic  #57                 // Method org/junit/Assert.fail:(Ljava/lang/String;)V
     194: goto          289
     197: astore        6
     199: aload         6
     201: invokevirtual #82                 // Method java/lang/reflect/UndeclaredThrowableException.getUndeclaredThrowable:()Ljava/lang/Throwable;
     204: astore        7
     206: aload         7
     208: instanceof    #83                 // class java/security/PrivilegedActionException
     211: ifeq          224
     214: aload         7
     216: checkcast     #83                 // class java/security/PrivilegedActionException
     219: invokevirtual #84                 // Method java/security/PrivilegedActionException.getException:()Ljava/lang/Exception;
     222: astore        7
     224: aload         7
     226: instanceof    #85                 // class com/google/protobuf/ServiceException
     229: ifeq          259
     232: aload         7
     234: checkcast     #85                 // class com/google/protobuf/ServiceException
     237: astore        8
     239: aload         8
     241: invokevirtual #86                 // Method com/google/protobuf/ServiceException.getCause:()Ljava/lang/Throwable;
     244: ifnull        259
     247: aload         8
     249: invokevirtual #86                 // Method com/google/protobuf/ServiceException.getCause:()Ljava/lang/Throwable;
     252: instanceof    #58                 // class org/apache/hadoop/hbase/security/AccessDeniedException
     255: ifeq          259
     258: return
     259: new           #6                  // class java/lang/StringBuilder
     262: dup
     263: invokespecial #7                  // Method java/lang/StringBuilder."<init>":()V
     266: ldc           #72                 // String Expected exception was not thrown for user '
     268: invokevirtual #9                  // Method java/lang/StringBuilder.append:(Ljava/lang/String;)Ljava/lang/StringBuilder;
     271: aload_0
     272: invokevirtual #55                 // Method org/apache/hadoop/hbase/security/User.getShortName:()Ljava/lang/String;
     275: invokevirtual #9                  // Method java/lang/StringBuilder.append:(Ljava/lang/String;)Ljava/lang/StringBuilder;
     278: ldc           #56                 // String '
     280: invokevirtual #9                  // Method java/lang/StringBuilder.append:(Ljava/lang/String;)Ljava/lang/StringBuilder;
     283: invokevirtual #15                 // Method java/lang/StringBuilder.toString:()Ljava/lang/String;
     286: invokestatic  #57                 // Method org/junit/Assert.fail:(Ljava/lang/String;)V
     289: iinc          4, 1
     292: goto          8
     295: return
    Exception table:
       from    to  target type
          20    57    60   Class java/io/IOException
          20    57   197   Class java/lang/reflect/UndeclaredThrowableException

  public static void grantGlobal(org.apache.hadoop.hbase.HBaseTestingUtility, java.lang.String, org.apache.hadoop.hbase.security.access.Permission$Action...) throws java.lang.Exception;
    Code:
       0: aload_0
       1: new           #113                // class org/apache/hadoop/hbase/security/access/SecureTestUtil$2
       4: dup
       5: aload_0
       6: aload_1
       7: aload_2
       8: invokespecial #114                // Method org/apache/hadoop/hbase/security/access/SecureTestUtil$2."<init>":(Lorg/apache/hadoop/hbase/HBaseTestingUtility;Ljava/lang/String;[Lorg/apache/hadoop/hbase/security/access/Permission$Action;)V
      11: invokestatic  #115                // Method updateACLs:(Lorg/apache/hadoop/hbase/HBaseTestingUtility;Ljava/util/concurrent/Callable;)V
      14: return

  public static void grantGlobal(org.apache.hadoop.hbase.security.User, org.apache.hadoop.hbase.HBaseTestingUtility, java.lang.String, org.apache.hadoop.hbase.security.access.Permission$Action...) throws java.lang.Exception;
    Code:
       0: aload_1
       1: new           #116                // class org/apache/hadoop/hbase/security/access/SecureTestUtil$3
       4: dup
       5: aload_1
       6: aload_0
       7: aload_2
       8: aload_3
       9: invokespecial #117                // Method org/apache/hadoop/hbase/security/access/SecureTestUtil$3."<init>":(Lorg/apache/hadoop/hbase/HBaseTestingUtility;Lorg/apache/hadoop/hbase/security/User;Ljava/lang/String;[Lorg/apache/hadoop/hbase/security/access/Permission$Action;)V
      12: invokestatic  #115                // Method updateACLs:(Lorg/apache/hadoop/hbase/HBaseTestingUtility;Ljava/util/concurrent/Callable;)V
      15: return

  public static void revokeGlobal(org.apache.hadoop.hbase.HBaseTestingUtility, java.lang.String, org.apache.hadoop.hbase.security.access.Permission$Action...) throws java.lang.Exception;
    Code:
       0: aload_0
       1: new           #118                // class org/apache/hadoop/hbase/security/access/SecureTestUtil$4
       4: dup
       5: aload_0
       6: aload_1
       7: aload_2
       8: invokespecial #119                // Method org/apache/hadoop/hbase/security/access/SecureTestUtil$4."<init>":(Lorg/apache/hadoop/hbase/HBaseTestingUtility;Ljava/lang/String;[Lorg/apache/hadoop/hbase/security/access/Permission$Action;)V
      11: invokestatic  #115                // Method updateACLs:(Lorg/apache/hadoop/hbase/HBaseTestingUtility;Ljava/util/concurrent/Callable;)V
      14: return

  public static void revokeGlobal(org.apache.hadoop.hbase.security.User, org.apache.hadoop.hbase.HBaseTestingUtility, java.lang.String, org.apache.hadoop.hbase.security.access.Permission$Action...) throws java.lang.Exception;
    Code:
       0: aload_1
       1: new           #120                // class org/apache/hadoop/hbase/security/access/SecureTestUtil$5
       4: dup
       5: aload_1
       6: aload_0
       7: aload_2
       8: aload_3
       9: invokespecial #121                // Method org/apache/hadoop/hbase/security/access/SecureTestUtil$5."<init>":(Lorg/apache/hadoop/hbase/HBaseTestingUtility;Lorg/apache/hadoop/hbase/security/User;Ljava/lang/String;[Lorg/apache/hadoop/hbase/security/access/Permission$Action;)V
      12: invokestatic  #115                // Method updateACLs:(Lorg/apache/hadoop/hbase/HBaseTestingUtility;Ljava/util/concurrent/Callable;)V
      15: return

  public static void grantOnNamespace(org.apache.hadoop.hbase.HBaseTestingUtility, java.lang.String, java.lang.String, org.apache.hadoop.hbase.security.access.Permission$Action...) throws java.lang.Exception;
    Code:
       0: aload_0
       1: new           #122                // class org/apache/hadoop/hbase/security/access/SecureTestUtil$6
       4: dup
       5: aload_0
       6: aload_1
       7: aload_2
       8: aload_3
       9: invokespecial #123                // Method org/apache/hadoop/hbase/security/access/SecureTestUtil$6."<init>":(Lorg/apache/hadoop/hbase/HBaseTestingUtility;Ljava/lang/String;Ljava/lang/String;[Lorg/apache/hadoop/hbase/security/access/Permission$Action;)V
      12: invokestatic  #115                // Method updateACLs:(Lorg/apache/hadoop/hbase/HBaseTestingUtility;Ljava/util/concurrent/Callable;)V
      15: return

  public static void grantOnNamespace(org.apache.hadoop.hbase.security.User, org.apache.hadoop.hbase.HBaseTestingUtility, java.lang.String, java.lang.String, org.apache.hadoop.hbase.security.access.Permission$Action...) throws java.lang.Exception;
    Code:
       0: aload_1
       1: new           #124                // class org/apache/hadoop/hbase/security/access/SecureTestUtil$7
       4: dup
       5: aload_1
       6: aload_0
       7: aload_2
       8: aload_3
       9: aload         4
      11: invokespecial #125                // Method org/apache/hadoop/hbase/security/access/SecureTestUtil$7."<init>":(Lorg/apache/hadoop/hbase/HBaseTestingUtility;Lorg/apache/hadoop/hbase/security/User;Ljava/lang/String;Ljava/lang/String;[Lorg/apache/hadoop/hbase/security/access/Permission$Action;)V
      14: invokestatic  #115                // Method updateACLs:(Lorg/apache/hadoop/hbase/HBaseTestingUtility;Ljava/util/concurrent/Callable;)V
      17: return

  public static void grantOnNamespaceUsingAccessControlClient(org.apache.hadoop.hbase.HBaseTestingUtility, org.apache.hadoop.hbase.client.Connection, java.lang.String, java.lang.String, org.apache.hadoop.hbase.security.access.Permission$Action...) throws java.lang.Exception;
    Code:
       0: aload_0
       1: new           #126                // class org/apache/hadoop/hbase/security/access/SecureTestUtil$8
       4: dup
       5: aload_1
       6: aload_3
       7: aload_2
       8: aload         4
      10: invokespecial #127                // Method org/apache/hadoop/hbase/security/access/SecureTestUtil$8."<init>":(Lorg/apache/hadoop/hbase/client/Connection;Ljava/lang/String;Ljava/lang/String;[Lorg/apache/hadoop/hbase/security/access/Permission$Action;)V
      13: invokestatic  #115                // Method updateACLs:(Lorg/apache/hadoop/hbase/HBaseTestingUtility;Ljava/util/concurrent/Callable;)V
      16: return

  public static void revokeFromNamespaceUsingAccessControlClient(org.apache.hadoop.hbase.HBaseTestingUtility, org.apache.hadoop.hbase.client.Connection, java.lang.String, java.lang.String, org.apache.hadoop.hbase.security.access.Permission$Action...) throws java.lang.Exception;
    Code:
       0: aload_0
       1: new           #128                // class org/apache/hadoop/hbase/security/access/SecureTestUtil$9
       4: dup
       5: aload_1
       6: aload_3
       7: aload_2
       8: aload         4
      10: invokespecial #129                // Method org/apache/hadoop/hbase/security/access/SecureTestUtil$9."<init>":(Lorg/apache/hadoop/hbase/client/Connection;Ljava/lang/String;Ljava/lang/String;[Lorg/apache/hadoop/hbase/security/access/Permission$Action;)V
      13: invokestatic  #115                // Method updateACLs:(Lorg/apache/hadoop/hbase/HBaseTestingUtility;Ljava/util/concurrent/Callable;)V
      16: return

  public static void revokeFromNamespace(org.apache.hadoop.hbase.HBaseTestingUtility, java.lang.String, java.lang.String, org.apache.hadoop.hbase.security.access.Permission$Action...) throws java.lang.Exception;
    Code:
       0: aload_0
       1: new           #130                // class org/apache/hadoop/hbase/security/access/SecureTestUtil$10
       4: dup
       5: aload_0
       6: aload_1
       7: aload_2
       8: aload_3
       9: invokespecial #131                // Method org/apache/hadoop/hbase/security/access/SecureTestUtil$10."<init>":(Lorg/apache/hadoop/hbase/HBaseTestingUtility;Ljava/lang/String;Ljava/lang/String;[Lorg/apache/hadoop/hbase/security/access/Permission$Action;)V
      12: invokestatic  #115                // Method updateACLs:(Lorg/apache/hadoop/hbase/HBaseTestingUtility;Ljava/util/concurrent/Callable;)V
      15: return

  public static void revokeFromNamespace(org.apache.hadoop.hbase.security.User, org.apache.hadoop.hbase.HBaseTestingUtility, java.lang.String, java.lang.String, org.apache.hadoop.hbase.security.access.Permission$Action...) throws java.lang.Exception;
    Code:
       0: aload_1
       1: new           #132                // class org/apache/hadoop/hbase/security/access/SecureTestUtil$11
       4: dup
       5: aload_1
       6: aload_0
       7: aload_2
       8: aload_3
       9: aload         4
      11: invokespecial #133                // Method org/apache/hadoop/hbase/security/access/SecureTestUtil$11."<init>":(Lorg/apache/hadoop/hbase/HBaseTestingUtility;Lorg/apache/hadoop/hbase/security/User;Ljava/lang/String;Ljava/lang/String;[Lorg/apache/hadoop/hbase/security/access/Permission$Action;)V
      14: invokestatic  #115                // Method updateACLs:(Lorg/apache/hadoop/hbase/HBaseTestingUtility;Ljava/util/concurrent/Callable;)V
      17: return

  public static void grantOnTable(org.apache.hadoop.hbase.HBaseTestingUtility, java.lang.String, org.apache.hadoop.hbase.TableName, byte[], byte[], org.apache.hadoop.hbase.security.access.Permission$Action...) throws java.lang.Exception;
    Code:
       0: aload_0
       1: new           #134                // class org/apache/hadoop/hbase/security/access/SecureTestUtil$12
       4: dup
       5: aload_0
       6: aload_1
       7: aload_2
       8: aload_3
       9: aload         4
      11: aload         5
      13: invokespecial #135                // Method org/apache/hadoop/hbase/security/access/SecureTestUtil$12."<init>":(Lorg/apache/hadoop/hbase/HBaseTestingUtility;Ljava/lang/String;Lorg/apache/hadoop/hbase/TableName;[B[B[Lorg/apache/hadoop/hbase/security/access/Permission$Action;)V
      16: invokestatic  #115                // Method updateACLs:(Lorg/apache/hadoop/hbase/HBaseTestingUtility;Ljava/util/concurrent/Callable;)V
      19: return

  public static void grantOnTable(org.apache.hadoop.hbase.security.User, org.apache.hadoop.hbase.HBaseTestingUtility, java.lang.String, org.apache.hadoop.hbase.TableName, byte[], byte[], org.apache.hadoop.hbase.security.access.Permission$Action...) throws java.lang.Exception;
    Code:
       0: aload_1
       1: new           #136                // class org/apache/hadoop/hbase/security/access/SecureTestUtil$13
       4: dup
       5: aload_1
       6: aload_0
       7: aload_2
       8: aload_3
       9: aload         4
      11: aload         5
      13: aload         6
      15: invokespecial #137                // Method org/apache/hadoop/hbase/security/access/SecureTestUtil$13."<init>":(Lorg/apache/hadoop/hbase/HBaseTestingUtility;Lorg/apache/hadoop/hbase/security/User;Ljava/lang/String;Lorg/apache/hadoop/hbase/TableName;[B[B[Lorg/apache/hadoop/hbase/security/access/Permission$Action;)V
      18: invokestatic  #115                // Method updateACLs:(Lorg/apache/hadoop/hbase/HBaseTestingUtility;Ljava/util/concurrent/Callable;)V
      21: return

  public static void grantOnTableUsingAccessControlClient(org.apache.hadoop.hbase.HBaseTestingUtility, org.apache.hadoop.hbase.client.Connection, java.lang.String, org.apache.hadoop.hbase.TableName, byte[], byte[], org.apache.hadoop.hbase.security.access.Permission$Action...) throws java.lang.Exception;
    Code:
       0: aload_0
       1: new           #138                // class org/apache/hadoop/hbase/security/access/SecureTestUtil$14
       4: dup
       5: aload_1
       6: aload_3
       7: aload_2
       8: aload         4
      10: aload         5
      12: aload         6
      14: invokespecial #139                // Method org/apache/hadoop/hbase/security/access/SecureTestUtil$14."<init>":(Lorg/apache/hadoop/hbase/client/Connection;Lorg/apache/hadoop/hbase/TableName;Ljava/lang/String;[B[B[Lorg/apache/hadoop/hbase/security/access/Permission$Action;)V
      17: invokestatic  #115                // Method updateACLs:(Lorg/apache/hadoop/hbase/HBaseTestingUtility;Ljava/util/concurrent/Callable;)V
      20: return

  public static void grantGlobalUsingAccessControlClient(org.apache.hadoop.hbase.HBaseTestingUtility, org.apache.hadoop.hbase.client.Connection, java.lang.String, org.apache.hadoop.hbase.security.access.Permission$Action...) throws java.lang.Exception;
    Code:
       0: aload_0
       1: new           #140                // class org/apache/hadoop/hbase/security/access/SecureTestUtil$15
       4: dup
       5: aload_1
       6: aload_2
       7: aload_3
       8: invokespecial #141                // Method org/apache/hadoop/hbase/security/access/SecureTestUtil$15."<init>":(Lorg/apache/hadoop/hbase/client/Connection;Ljava/lang/String;[Lorg/apache/hadoop/hbase/security/access/Permission$Action;)V
      11: invokestatic  #115                // Method updateACLs:(Lorg/apache/hadoop/hbase/HBaseTestingUtility;Ljava/util/concurrent/Callable;)V
      14: return

  public static void revokeFromTable(org.apache.hadoop.hbase.HBaseTestingUtility, java.lang.String, org.apache.hadoop.hbase.TableName, byte[], byte[], org.apache.hadoop.hbase.security.access.Permission$Action...) throws java.lang.Exception;
    Code:
       0: aload_0
       1: new           #142                // class org/apache/hadoop/hbase/security/access/SecureTestUtil$16
       4: dup
       5: aload_0
       6: aload_1
       7: aload_2
       8: aload_3
       9: aload         4
      11: aload         5
      13: invokespecial #143                // Method org/apache/hadoop/hbase/security/access/SecureTestUtil$16."<init>":(Lorg/apache/hadoop/hbase/HBaseTestingUtility;Ljava/lang/String;Lorg/apache/hadoop/hbase/TableName;[B[B[Lorg/apache/hadoop/hbase/security/access/Permission$Action;)V
      16: invokestatic  #115                // Method updateACLs:(Lorg/apache/hadoop/hbase/HBaseTestingUtility;Ljava/util/concurrent/Callable;)V
      19: return

  public static void revokeFromTable(org.apache.hadoop.hbase.security.User, org.apache.hadoop.hbase.HBaseTestingUtility, java.lang.String, org.apache.hadoop.hbase.TableName, byte[], byte[], org.apache.hadoop.hbase.security.access.Permission$Action...) throws java.lang.Exception;
    Code:
       0: aload_1
       1: new           #144                // class org/apache/hadoop/hbase/security/access/SecureTestUtil$17
       4: dup
       5: aload_1
       6: aload_0
       7: aload_2
       8: aload_3
       9: aload         4
      11: aload         5
      13: aload         6
      15: invokespecial #145                // Method org/apache/hadoop/hbase/security/access/SecureTestUtil$17."<init>":(Lorg/apache/hadoop/hbase/HBaseTestingUtility;Lorg/apache/hadoop/hbase/security/User;Ljava/lang/String;Lorg/apache/hadoop/hbase/TableName;[B[B[Lorg/apache/hadoop/hbase/security/access/Permission$Action;)V
      18: invokestatic  #115                // Method updateACLs:(Lorg/apache/hadoop/hbase/HBaseTestingUtility;Ljava/util/concurrent/Callable;)V
      21: return

  public static void revokeFromTableUsingAccessControlClient(org.apache.hadoop.hbase.HBaseTestingUtility, org.apache.hadoop.hbase.client.Connection, java.lang.String, org.apache.hadoop.hbase.TableName, byte[], byte[], org.apache.hadoop.hbase.security.access.Permission$Action...) throws java.lang.Exception;
    Code:
       0: aload_0
       1: new           #146                // class org/apache/hadoop/hbase/security/access/SecureTestUtil$18
       4: dup
       5: aload_1
       6: aload_3
       7: aload_2
       8: aload         4
      10: aload         5
      12: aload         6
      14: invokespecial #147                // Method org/apache/hadoop/hbase/security/access/SecureTestUtil$18."<init>":(Lorg/apache/hadoop/hbase/client/Connection;Lorg/apache/hadoop/hbase/TableName;Ljava/lang/String;[B[B[Lorg/apache/hadoop/hbase/security/access/Permission$Action;)V
      17: invokestatic  #115                // Method updateACLs:(Lorg/apache/hadoop/hbase/HBaseTestingUtility;Ljava/util/concurrent/Callable;)V
      20: return

  public static void revokeGlobalUsingAccessControlClient(org.apache.hadoop.hbase.HBaseTestingUtility, org.apache.hadoop.hbase.client.Connection, java.lang.String, org.apache.hadoop.hbase.security.access.Permission$Action...) throws java.lang.Exception;
    Code:
       0: aload_0
       1: new           #148                // class org/apache/hadoop/hbase/security/access/SecureTestUtil$19
       4: dup
       5: aload_1
       6: aload_2
       7: aload_3
       8: invokespecial #149                // Method org/apache/hadoop/hbase/security/access/SecureTestUtil$19."<init>":(Lorg/apache/hadoop/hbase/client/Connection;Ljava/lang/String;[Lorg/apache/hadoop/hbase/security/access/Permission$Action;)V
      11: invokestatic  #115                // Method updateACLs:(Lorg/apache/hadoop/hbase/HBaseTestingUtility;Ljava/util/concurrent/Callable;)V
      14: return

  public static org.apache.hadoop.hbase.client.Table createTable(org.apache.hadoop.hbase.HBaseTestingUtility, org.apache.hadoop.hbase.TableName, byte[][]) throws java.lang.Exception;
    Code:
       0: aload_1
       1: invokestatic  #150                // Method org/apache/hadoop/hbase/client/TableDescriptorBuilder.newBuilder:(Lorg/apache/hadoop/hbase/TableName;)Lorg/apache/hadoop/hbase/client/TableDescriptorBuilder;
       4: astore_3
       5: aload_2
       6: astore        4
       8: aload         4
      10: arraylength
      11: istore        5
      13: iconst_0
      14: istore        6
      16: iload         6
      18: iload         5
      20: if_icmpge     46
      23: aload         4
      25: iload         6
      27: aaload
      28: astore        7
      30: aload_3
      31: aload         7
      33: invokestatic  #151                // Method org/apache/hadoop/hbase/client/ColumnFamilyDescriptorBuilder.of:([B)Lorg/apache/hadoop/hbase/client/ColumnFamilyDescriptor;
      36: invokevirtual #152                // Method org/apache/hadoop/hbase/client/TableDescriptorBuilder.setColumnFamily:(Lorg/apache/hadoop/hbase/client/ColumnFamilyDescriptor;)Lorg/apache/hadoop/hbase/client/TableDescriptorBuilder;
      39: pop
      40: iinc          6, 1
      43: goto          16
      46: aload_0
      47: aload_0
      48: invokevirtual #153                // Method org/apache/hadoop/hbase/HBaseTestingUtility.getAdmin:()Lorg/apache/hadoop/hbase/client/Admin;
      51: aload_3
      52: invokevirtual #154                // Method org/apache/hadoop/hbase/client/TableDescriptorBuilder.build:()Lorg/apache/hadoop/hbase/client/TableDescriptor;
      55: invokestatic  #155                // Method createTable:(Lorg/apache/hadoop/hbase/HBaseTestingUtility;Lorg/apache/hadoop/hbase/client/Admin;Lorg/apache/hadoop/hbase/client/TableDescriptor;)V
      58: aload_0
      59: invokevirtual #156                // Method org/apache/hadoop/hbase/HBaseTestingUtility.getConnection:()Lorg/apache/hadoop/hbase/client/Connection;
      62: aload_1
      63: invokeinterface #157,  2          // InterfaceMethod org/apache/hadoop/hbase/client/Connection.getTable:(Lorg/apache/hadoop/hbase/TableName;)Lorg/apache/hadoop/hbase/client/Table;
      68: areturn

  public static void createTable(org.apache.hadoop.hbase.HBaseTestingUtility, org.apache.hadoop.hbase.client.TableDescriptor) throws java.lang.Exception;
    Code:
       0: aload_0
       1: aload_0
       2: invokevirtual #153                // Method org/apache/hadoop/hbase/HBaseTestingUtility.getAdmin:()Lorg/apache/hadoop/hbase/client/Admin;
       5: aload_1
       6: invokestatic  #155                // Method createTable:(Lorg/apache/hadoop/hbase/HBaseTestingUtility;Lorg/apache/hadoop/hbase/client/Admin;Lorg/apache/hadoop/hbase/client/TableDescriptor;)V
       9: return

  public static void createTable(org.apache.hadoop.hbase.HBaseTestingUtility, org.apache.hadoop.hbase.client.TableDescriptor, byte[][]) throws java.lang.Exception;
    Code:
       0: aload_0
       1: aload_0
       2: invokevirtual #153                // Method org/apache/hadoop/hbase/HBaseTestingUtility.getAdmin:()Lorg/apache/hadoop/hbase/client/Admin;
       5: aload_1
       6: aload_2
       7: invokestatic  #158                // Method createTable:(Lorg/apache/hadoop/hbase/HBaseTestingUtility;Lorg/apache/hadoop/hbase/client/Admin;Lorg/apache/hadoop/hbase/client/TableDescriptor;[[B)V
      10: return

  public static void createTable(org.apache.hadoop.hbase.HBaseTestingUtility, org.apache.hadoop.hbase.client.Admin, org.apache.hadoop.hbase.client.TableDescriptor) throws java.lang.Exception;
    Code:
       0: aload_0
       1: aload_1
       2: aload_2
       3: aconst_null
       4: checkcast     #159                // class "[[B"
       7: invokestatic  #158                // Method createTable:(Lorg/apache/hadoop/hbase/HBaseTestingUtility;Lorg/apache/hadoop/hbase/client/Admin;Lorg/apache/hadoop/hbase/client/TableDescriptor;[[B)V
      10: return

  public static void createTable(org.apache.hadoop.hbase.HBaseTestingUtility, org.apache.hadoop.hbase.client.Admin, org.apache.hadoop.hbase.client.TableDescriptor, byte[][]) throws java.lang.Exception;
    Code:
       0: aload_0
       1: invokevirtual #103                // Method org/apache/hadoop/hbase/HBaseTestingUtility.getHBaseCluster:()Lorg/apache/hadoop/hbase/MiniHBaseCluster;
       4: invokevirtual #160                // Method org/apache/hadoop/hbase/MiniHBaseCluster.getMaster:()Lorg/apache/hadoop/hbase/master/HMaster;
       7: invokevirtual #161                // Method org/apache/hadoop/hbase/master/HMaster.getMasterCoprocessorHost:()Lorg/apache/hadoop/hbase/master/MasterCoprocessorHost;
      10: ldc           #29                 // class org/apache/hadoop/hbase/security/access/SecureTestUtil$MasterSyncObserver
      12: invokevirtual #162                // Method org/apache/hadoop/hbase/master/MasterCoprocessorHost.findCoprocessor:(Ljava/lang/Class;)Lorg/apache/hadoop/hbase/Coprocessor;
      15: checkcast     #29                 // class org/apache/hadoop/hbase/security/access/SecureTestUtil$MasterSyncObserver
      18: astore        4
      20: aload         4
      22: new           #163                // class java/util/concurrent/CountDownLatch
      25: dup
      26: iconst_1
      27: invokespecial #164                // Method java/util/concurrent/CountDownLatch."<init>":(I)V
      30: putfield      #165                // Field org/apache/hadoop/hbase/security/access/SecureTestUtil$MasterSyncObserver.tableCreationLatch:Ljava/util/concurrent/CountDownLatch;
      33: aload_3
      34: ifnull        48
      37: aload_1
      38: aload_2
      39: aload_3
      40: invokeinterface #166,  3          // InterfaceMethod org/apache/hadoop/hbase/client/Admin.createTable:(Lorg/apache/hadoop/hbase/client/TableDescriptor;[[B)V
      45: goto          55
      48: aload_1
      49: aload_2
      50: invokeinterface #167,  2          // InterfaceMethod org/apache/hadoop/hbase/client/Admin.createTable:(Lorg/apache/hadoop/hbase/client/TableDescriptor;)V
      55: aload         4
      57: getfield      #165                // Field org/apache/hadoop/hbase/security/access/SecureTestUtil$MasterSyncObserver.tableCreationLatch:Ljava/util/concurrent/CountDownLatch;
      60: invokevirtual #168                // Method java/util/concurrent/CountDownLatch.await:()V
      63: aload         4
      65: aconst_null
      66: putfield      #165                // Field org/apache/hadoop/hbase/security/access/SecureTestUtil$MasterSyncObserver.tableCreationLatch:Ljava/util/concurrent/CountDownLatch;
      69: aload_0
      70: aload_2
      71: invokeinterface #169,  1          // InterfaceMethod org/apache/hadoop/hbase/client/TableDescriptor.getTableName:()Lorg/apache/hadoop/hbase/TableName;
      76: invokevirtual #170                // Method org/apache/hadoop/hbase/HBaseTestingUtility.waitUntilAllRegionsAssigned:(Lorg/apache/hadoop/hbase/TableName;)V
      79: return

  public static void deleteTable(org.apache.hadoop.hbase.HBaseTestingUtility, org.apache.hadoop.hbase.TableName) throws java.lang.Exception;
    Code:
       0: aload_0
       1: aload_0
       2: invokevirtual #153                // Method org/apache/hadoop/hbase/HBaseTestingUtility.getAdmin:()Lorg/apache/hadoop/hbase/client/Admin;
       5: aload_1
       6: invokestatic  #171                // Method deleteTable:(Lorg/apache/hadoop/hbase/HBaseTestingUtility;Lorg/apache/hadoop/hbase/client/Admin;Lorg/apache/hadoop/hbase/TableName;)V
       9: return

  public static void createNamespace(org.apache.hadoop.hbase.HBaseTestingUtility, org.apache.hadoop.hbase.NamespaceDescriptor) throws java.lang.Exception;
    Code:
       0: aload_0
       1: invokevirtual #153                // Method org/apache/hadoop/hbase/HBaseTestingUtility.getAdmin:()Lorg/apache/hadoop/hbase/client/Admin;
       4: aload_1
       5: invokeinterface #172,  2          // InterfaceMethod org/apache/hadoop/hbase/client/Admin.createNamespace:(Lorg/apache/hadoop/hbase/NamespaceDescriptor;)V
      10: return

  public static void deleteNamespace(org.apache.hadoop.hbase.HBaseTestingUtility, java.lang.String) throws java.lang.Exception;
    Code:
       0: aload_0
       1: invokevirtual #153                // Method org/apache/hadoop/hbase/HBaseTestingUtility.getAdmin:()Lorg/apache/hadoop/hbase/client/Admin;
       4: aload_1
       5: invokeinterface #173,  2          // InterfaceMethod org/apache/hadoop/hbase/client/Admin.deleteNamespace:(Ljava/lang/String;)V
      10: return

  public static void deleteTable(org.apache.hadoop.hbase.HBaseTestingUtility, org.apache.hadoop.hbase.client.Admin, org.apache.hadoop.hbase.TableName) throws java.lang.Exception;
    Code:
       0: aload_0
       1: invokevirtual #103                // Method org/apache/hadoop/hbase/HBaseTestingUtility.getHBaseCluster:()Lorg/apache/hadoop/hbase/MiniHBaseCluster;
       4: invokevirtual #160                // Method org/apache/hadoop/hbase/MiniHBaseCluster.getMaster:()Lorg/apache/hadoop/hbase/master/HMaster;
       7: invokevirtual #161                // Method org/apache/hadoop/hbase/master/HMaster.getMasterCoprocessorHost:()Lorg/apache/hadoop/hbase/master/MasterCoprocessorHost;
      10: ldc           #29                 // class org/apache/hadoop/hbase/security/access/SecureTestUtil$MasterSyncObserver
      12: invokevirtual #162                // Method org/apache/hadoop/hbase/master/MasterCoprocessorHost.findCoprocessor:(Ljava/lang/Class;)Lorg/apache/hadoop/hbase/Coprocessor;
      15: checkcast     #29                 // class org/apache/hadoop/hbase/security/access/SecureTestUtil$MasterSyncObserver
      18: astore_3
      19: aload_3
      20: new           #163                // class java/util/concurrent/CountDownLatch
      23: dup
      24: iconst_1
      25: invokespecial #164                // Method java/util/concurrent/CountDownLatch."<init>":(I)V
      28: putfield      #174                // Field org/apache/hadoop/hbase/security/access/SecureTestUtil$MasterSyncObserver.tableDeletionLatch:Ljava/util/concurrent/CountDownLatch;
      31: aload_1
      32: aload_2
      33: invokeinterface #175,  2          // InterfaceMethod org/apache/hadoop/hbase/client/Admin.disableTable:(Lorg/apache/hadoop/hbase/TableName;)V
      38: goto          75
      41: astore        4
      43: getstatic     #1                  // Field LOG:Lorg/slf4j/Logger;
      46: new           #6                  // class java/lang/StringBuilder
      49: dup
      50: invokespecial #7                  // Method java/lang/StringBuilder."<init>":()V
      53: ldc           #177                // String Table:
      55: invokevirtual #9                  // Method java/lang/StringBuilder.append:(Ljava/lang/String;)Ljava/lang/StringBuilder;
      58: aload_2
      59: invokevirtual #67                 // Method java/lang/StringBuilder.append:(Ljava/lang/Object;)Ljava/lang/StringBuilder;
      62: ldc           #178                // String  already disabled, so just deleting it.
      64: invokevirtual #9                  // Method java/lang/StringBuilder.append:(Ljava/lang/String;)Ljava/lang/StringBuilder;
      67: invokevirtual #15                 // Method java/lang/StringBuilder.toString:()Ljava/lang/String;
      70: invokeinterface #179,  2          // InterfaceMethod org/slf4j/Logger.debug:(Ljava/lang/String;)V
      75: aload_1
      76: aload_2
      77: invokeinterface #180,  2          // InterfaceMethod org/apache/hadoop/hbase/client/Admin.deleteTable:(Lorg/apache/hadoop/hbase/TableName;)V
      82: aload_3
      83: getfield      #174                // Field org/apache/hadoop/hbase/security/access/SecureTestUtil$MasterSyncObserver.tableDeletionLatch:Ljava/util/concurrent/CountDownLatch;
      86: invokevirtual #168                // Method java/util/concurrent/CountDownLatch.await:()V
      89: aload_3
      90: aconst_null
      91: putfield      #174                // Field org/apache/hadoop/hbase/security/access/SecureTestUtil$MasterSyncObserver.tableDeletionLatch:Ljava/util/concurrent/CountDownLatch;
      94: return
    Exception table:
       from    to  target type
          31    38    41   Class org/apache/hadoop/hbase/TableNotEnabledException

  public static java.lang.String convertToNamespace(java.lang.String);
    Code:
       0: new           #6                  // class java/lang/StringBuilder
       3: dup
       4: invokespecial #7                  // Method java/lang/StringBuilder."<init>":()V
       7: bipush        64
       9: invokevirtual #10                 // Method java/lang/StringBuilder.append:(C)Ljava/lang/StringBuilder;
      12: aload_0
      13: invokevirtual #9                  // Method java/lang/StringBuilder.append:(Ljava/lang/String;)Ljava/lang/StringBuilder;
      16: invokevirtual #15                 // Method java/lang/StringBuilder.toString:()Ljava/lang/String;
      19: areturn

  public static void checkGlobalPerms(org.apache.hadoop.hbase.HBaseTestingUtility, org.apache.hadoop.hbase.security.access.Permission$Action...) throws java.io.IOException;
    Code:
       0: aload_1
       1: arraylength
       2: anewarray     #182                // class org/apache/hadoop/hbase/security/access/Permission
       5: astore_2
       6: iconst_0
       7: istore_3
       8: iload_3
       9: aload_1
      10: arraylength
      11: if_icmpge     40
      14: aload_2
      15: iload_3
      16: new           #182                // class org/apache/hadoop/hbase/security/access/Permission
      19: dup
      20: iconst_1
      21: anewarray     #183                // class org/apache/hadoop/hbase/security/access/Permission$Action
      24: dup
      25: iconst_0
      26: aload_1
      27: iload_3
      28: aaload
      29: aastore
      30: invokespecial #184                // Method org/apache/hadoop/hbase/security/access/Permission."<init>":([Lorg/apache/hadoop/hbase/security/access/Permission$Action;)V
      33: aastore
      34: iinc          3, 1
      37: goto          8
      40: aload_0
      41: invokevirtual #185                // Method org/apache/hadoop/hbase/HBaseTestingUtility.getConfiguration:()Lorg/apache/hadoop/conf/Configuration;
      44: aload_2
      45: invokestatic  #186                // Method checkPermissions:(Lorg/apache/hadoop/conf/Configuration;[Lorg/apache/hadoop/hbase/security/access/Permission;)V
      48: return

  public static void checkTablePerms(org.apache.hadoop.hbase.HBaseTestingUtility, org.apache.hadoop.hbase.TableName, byte[], byte[], org.apache.hadoop.hbase.security.access.Permission$Action...) throws java.io.IOException;
    Code:
       0: aload         4
       2: arraylength
       3: anewarray     #182                // class org/apache/hadoop/hbase/security/access/Permission
       6: astore        5
       8: iconst_0
       9: istore        6
      11: iload         6
      13: aload         4
      15: arraylength
      16: if_icmpge     60
      19: aload         5
      21: iload         6
      23: aload_1
      24: invokestatic  #187                // Method org/apache/hadoop/hbase/security/access/Permission.newBuilder:(Lorg/apache/hadoop/hbase/TableName;)Lorg/apache/hadoop/hbase/security/access/Permission$Builder;
      27: aload_2
      28: invokevirtual #188                // Method org/apache/hadoop/hbase/security/access/Permission$Builder.withFamily:([B)Lorg/apache/hadoop/hbase/security/access/Permission$Builder;
      31: aload_3
      32: invokevirtual #189                // Method org/apache/hadoop/hbase/security/access/Permission$Builder.withQualifier:([B)Lorg/apache/hadoop/hbase/security/access/Permission$Builder;
      35: iconst_1
      36: anewarray     #183                // class org/apache/hadoop/hbase/security/access/Permission$Action
      39: dup
      40: iconst_0
      41: aload         4
      43: iload         6
      45: aaload
      46: aastore
      47: invokevirtual #190                // Method org/apache/hadoop/hbase/security/access/Permission$Builder.withActions:([Lorg/apache/hadoop/hbase/security/access/Permission$Action;)Lorg/apache/hadoop/hbase/security/access/Permission$Builder;
      50: invokevirtual #191                // Method org/apache/hadoop/hbase/security/access/Permission$Builder.build:()Lorg/apache/hadoop/hbase/security/access/Permission;
      53: aastore
      54: iinc          6, 1
      57: goto          11
      60: aload_0
      61: aload         5
      63: invokestatic  #192                // Method checkTablePerms:(Lorg/apache/hadoop/hbase/HBaseTestingUtility;[Lorg/apache/hadoop/hbase/security/access/Permission;)V
      66: return

  public static void checkTablePerms(org.apache.hadoop.hbase.HBaseTestingUtility, org.apache.hadoop.hbase.security.access.Permission...) throws java.io.IOException;
    Code:
       0: aload_0
       1: invokevirtual #185                // Method org/apache/hadoop/hbase/HBaseTestingUtility.getConfiguration:()Lorg/apache/hadoop/conf/Configuration;
       4: aload_1
       5: invokestatic  #186                // Method checkPermissions:(Lorg/apache/hadoop/conf/Configuration;[Lorg/apache/hadoop/hbase/security/access/Permission;)V
       8: return

  static java.util.Map access$000(org.apache.hadoop.hbase.MiniHBaseCluster);
    Code:
       0: aload_0
       1: invokestatic  #2                  // Method getAuthManagerMTimes:(Lorg/apache/hadoop/hbase/MiniHBaseCluster;)Ljava/util/Map;
       4: areturn

  static org.slf4j.Logger access$100();
    Code:
       0: getstatic     #1                  // Field LOG:Lorg/slf4j/Logger;
       3: areturn

  static {};
    Code:
       0: ldc           #105                // class org/apache/hadoop/hbase/security/access/SecureTestUtil
       2: invokestatic  #204                // Method org/slf4j/LoggerFactory.getLogger:(Ljava/lang/Class;)Lorg/slf4j/Logger;
       5: putstatic     #1                  // Field LOG:Lorg/slf4j/Logger;
       8: return
}
