Compiled from "SecurityCapability.java"
public final class org.apache.hadoop.hbase.client.security.SecurityCapability extends java.lang.Enum<org.apache.hadoop.hbase.client.security.SecurityCapability> {
  public static final org.apache.hadoop.hbase.client.security.SecurityCapability SIMPLE_AUTHENTICATION;

  public static final org.apache.hadoop.hbase.client.security.SecurityCapability SECURE_AUTHENTICATION;

  public static final org.apache.hadoop.hbase.client.security.SecurityCapability AUTHORIZATION;

  public static final org.apache.hadoop.hbase.client.security.SecurityCapability CELL_AUTHORIZATION;

  public static final org.apache.hadoop.hbase.client.security.SecurityCapability CELL_VISIBILITY;

  public static org.apache.hadoop.hbase.client.security.SecurityCapability[] values();
    Code:
       0: getstatic     #1                  // Field $VALUES:[Lorg/apache/hadoop/hbase/client/security/SecurityCapability;
       3: invokevirtual #2                  // Method "[Lorg/apache/hadoop/hbase/client/security/SecurityCapability;".clone:()Ljava/lang/Object;
       6: checkcast     #3                  // class "[Lorg/apache/hadoop/hbase/client/security/SecurityCapability;"
       9: areturn

  public static org.apache.hadoop.hbase.client.security.SecurityCapability valueOf(java.lang.String);
    Code:
       0: ldc           #4                  // class org/apache/hadoop/hbase/client/security/SecurityCapability
       2: aload_0
       3: invokestatic  #5                  // Method java/lang/Enum.valueOf:(Ljava/lang/Class;Ljava/lang/String;)Ljava/lang/Enum;
       6: checkcast     #4                  // class org/apache/hadoop/hbase/client/security/SecurityCapability
       9: areturn

  public int getValue();
    Code:
       0: aload_0
       1: getfield      #6                  // Field value:I
       4: ireturn

  public java.lang.String getName();
    Code:
       0: aload_0
       1: invokevirtual #7                  // Method toString:()Ljava/lang/String;
       4: areturn

  public static org.apache.hadoop.hbase.client.security.SecurityCapability valueOf(int);
    Code:
       0: iload_0
       1: tableswitch   { // 0 to 4
                     0: 36
                     1: 40
                     2: 44
                     3: 48
                     4: 52
               default: 56
          }
      36: getstatic     #9                  // Field SIMPLE_AUTHENTICATION:Lorg/apache/hadoop/hbase/client/security/SecurityCapability;
      39: areturn
      40: getstatic     #10                 // Field SECURE_AUTHENTICATION:Lorg/apache/hadoop/hbase/client/security/SecurityCapability;
      43: areturn
      44: getstatic     #11                 // Field AUTHORIZATION:Lorg/apache/hadoop/hbase/client/security/SecurityCapability;
      47: areturn
      48: getstatic     #12                 // Field CELL_AUTHORIZATION:Lorg/apache/hadoop/hbase/client/security/SecurityCapability;
      51: areturn
      52: getstatic     #13                 // Field CELL_VISIBILITY:Lorg/apache/hadoop/hbase/client/security/SecurityCapability;
      55: areturn
      56: new           #14                 // class java/lang/IllegalArgumentException
      59: dup
      60: new           #15                 // class java/lang/StringBuilder
      63: dup
      64: invokespecial #16                 // Method java/lang/StringBuilder."<init>":()V
      67: ldc           #17                 // String Unknown SecurityCapability value
      69: invokevirtual #18                 // Method java/lang/StringBuilder.append:(Ljava/lang/String;)Ljava/lang/StringBuilder;
      72: iload_0
      73: invokevirtual #19                 // Method java/lang/StringBuilder.append:(I)Ljava/lang/StringBuilder;
      76: invokevirtual #20                 // Method java/lang/StringBuilder.toString:()Ljava/lang/String;
      79: invokespecial #21                 // Method java/lang/IllegalArgumentException."<init>":(Ljava/lang/String;)V
      82: athrow

  static {};
    Code:
       0: new           #4                  // class org/apache/hadoop/hbase/client/security/SecurityCapability
       3: dup
       4: ldc           #22                 // String SIMPLE_AUTHENTICATION
       6: iconst_0
       7: iconst_0
       8: invokespecial #23                 // Method "<init>":(Ljava/lang/String;II)V
      11: putstatic     #9                  // Field SIMPLE_AUTHENTICATION:Lorg/apache/hadoop/hbase/client/security/SecurityCapability;
      14: new           #4                  // class org/apache/hadoop/hbase/client/security/SecurityCapability
      17: dup
      18: ldc           #24                 // String SECURE_AUTHENTICATION
      20: iconst_1
      21: iconst_1
      22: invokespecial #23                 // Method "<init>":(Ljava/lang/String;II)V
      25: putstatic     #10                 // Field SECURE_AUTHENTICATION:Lorg/apache/hadoop/hbase/client/security/SecurityCapability;
      28: new           #4                  // class org/apache/hadoop/hbase/client/security/SecurityCapability
      31: dup
      32: ldc           #25                 // String AUTHORIZATION
      34: iconst_2
      35: iconst_2
      36: invokespecial #23                 // Method "<init>":(Ljava/lang/String;II)V
      39: putstatic     #11                 // Field AUTHORIZATION:Lorg/apache/hadoop/hbase/client/security/SecurityCapability;
      42: new           #4                  // class org/apache/hadoop/hbase/client/security/SecurityCapability
      45: dup
      46: ldc           #26                 // String CELL_AUTHORIZATION
      48: iconst_3
      49: iconst_3
      50: invokespecial #23                 // Method "<init>":(Ljava/lang/String;II)V
      53: putstatic     #12                 // Field CELL_AUTHORIZATION:Lorg/apache/hadoop/hbase/client/security/SecurityCapability;
      56: new           #4                  // class org/apache/hadoop/hbase/client/security/SecurityCapability
      59: dup
      60: ldc           #27                 // String CELL_VISIBILITY
      62: iconst_4
      63: iconst_4
      64: invokespecial #23                 // Method "<init>":(Ljava/lang/String;II)V
      67: putstatic     #13                 // Field CELL_VISIBILITY:Lorg/apache/hadoop/hbase/client/security/SecurityCapability;
      70: iconst_5
      71: anewarray     #4                  // class org/apache/hadoop/hbase/client/security/SecurityCapability
      74: dup
      75: iconst_0
      76: getstatic     #9                  // Field SIMPLE_AUTHENTICATION:Lorg/apache/hadoop/hbase/client/security/SecurityCapability;
      79: aastore
      80: dup
      81: iconst_1
      82: getstatic     #10                 // Field SECURE_AUTHENTICATION:Lorg/apache/hadoop/hbase/client/security/SecurityCapability;
      85: aastore
      86: dup
      87: iconst_2
      88: getstatic     #11                 // Field AUTHORIZATION:Lorg/apache/hadoop/hbase/client/security/SecurityCapability;
      91: aastore
      92: dup
      93: iconst_3
      94: getstatic     #12                 // Field CELL_AUTHORIZATION:Lorg/apache/hadoop/hbase/client/security/SecurityCapability;
      97: aastore
      98: dup
      99: iconst_4
     100: getstatic     #13                 // Field CELL_VISIBILITY:Lorg/apache/hadoop/hbase/client/security/SecurityCapability;
     103: aastore
     104: putstatic     #1                  // Field $VALUES:[Lorg/apache/hadoop/hbase/client/security/SecurityCapability;
     107: return
}
