Compiled from "SecureBulkLoadClient.java"
public class org.apache.hadoop.hbase.client.SecureBulkLoadClient {
  public org.apache.hadoop.hbase.client.SecureBulkLoadClient(org.apache.hadoop.conf.Configuration, org.apache.hadoop.hbase.client.Table);
    Code:
       0: aload_0
       1: invokespecial #3                  // Method java/lang/Object."<init>":()V
       4: aload_0
       5: aload_2
       6: putfield      #2                  // Field table:Lorg/apache/hadoop/hbase/client/Table;
       9: aload_0
      10: new           #4                  // class org/apache/hadoop/hbase/ipc/RpcControllerFactory
      13: dup
      14: aload_1
      15: invokespecial #5                  // Method org/apache/hadoop/hbase/ipc/RpcControllerFactory."<init>":(Lorg/apache/hadoop/conf/Configuration;)V
      18: putfield      #6                  // Field rpcControllerFactory:Lorg/apache/hadoop/hbase/ipc/RpcControllerFactory;
      21: return

  public java.lang.String prepareBulkLoad(org.apache.hadoop.hbase.client.Connection) throws java.io.IOException;
    Code:
       0: new           #7                  // class org/apache/hadoop/hbase/client/SecureBulkLoadClient$1
       3: dup
       4: aload_0
       5: aload_1
       6: aload_0
       7: getfield      #2                  // Field table:Lorg/apache/hadoop/hbase/client/Table;
      10: invokeinterface #8,  1            // InterfaceMethod org/apache/hadoop/hbase/client/Table.getName:()Lorg/apache/hadoop/hbase/TableName;
      15: getstatic     #9                  // Field org/apache/hadoop/hbase/HConstants.EMPTY_START_ROW:[B
      18: aload_0
      19: getfield      #6                  // Field rpcControllerFactory:Lorg/apache/hadoop/hbase/ipc/RpcControllerFactory;
      22: invokevirtual #10                 // Method org/apache/hadoop/hbase/ipc/RpcControllerFactory.newController:()Lorg/apache/hadoop/hbase/ipc/HBaseRpcController;
      25: iconst_m1
      26: invokespecial #11                 // Method org/apache/hadoop/hbase/client/SecureBulkLoadClient$1."<init>":(Lorg/apache/hadoop/hbase/client/SecureBulkLoadClient;Lorg/apache/hadoop/hbase/client/Connection;Lorg/apache/hadoop/hbase/TableName;[BLorg/apache/hbase/thirdparty/com/google/protobuf/RpcController;I)V
      29: astore_2
      30: aload_1
      31: invokeinterface #12,  1           // InterfaceMethod org/apache/hadoop/hbase/client/Connection.getConfiguration:()Lorg/apache/hadoop/conf/Configuration;
      36: aconst_null
      37: invokestatic  #13                 // Method org/apache/hadoop/hbase/client/RpcRetryingCallerFactory.instantiate:(Lorg/apache/hadoop/conf/Configuration;Lorg/apache/hadoop/hbase/client/ServerStatisticTracker;)Lorg/apache/hadoop/hbase/client/RpcRetryingCallerFactory;
      40: invokevirtual #14                 // Method org/apache/hadoop/hbase/client/RpcRetryingCallerFactory.newCaller:()Lorg/apache/hadoop/hbase/client/RpcRetryingCaller;
      43: aload_2
      44: ldc           #16                 // int 2147483647
      46: invokeinterface #17,  3           // InterfaceMethod org/apache/hadoop/hbase/client/RpcRetryingCaller.callWithRetries:(Lorg/apache/hadoop/hbase/client/RetryingCallable;I)Ljava/lang/Object;
      51: checkcast     #18                 // class java/lang/String
      54: areturn
      55: astore_2
      56: new           #20                 // class java/io/IOException
      59: dup
      60: aload_2
      61: invokespecial #21                 // Method java/io/IOException."<init>":(Ljava/lang/Throwable;)V
      64: athrow
    Exception table:
       from    to  target type
           0    54    55   Class java/lang/Throwable

  public void cleanupBulkLoad(org.apache.hadoop.hbase.client.Connection, java.lang.String) throws java.io.IOException;
    Code:
       0: new           #22                 // class org/apache/hadoop/hbase/client/SecureBulkLoadClient$2
       3: dup
       4: aload_0
       5: aload_1
       6: aload_0
       7: getfield      #2                  // Field table:Lorg/apache/hadoop/hbase/client/Table;
      10: invokeinterface #8,  1            // InterfaceMethod org/apache/hadoop/hbase/client/Table.getName:()Lorg/apache/hadoop/hbase/TableName;
      15: getstatic     #9                  // Field org/apache/hadoop/hbase/HConstants.EMPTY_START_ROW:[B
      18: aload_0
      19: getfield      #6                  // Field rpcControllerFactory:Lorg/apache/hadoop/hbase/ipc/RpcControllerFactory;
      22: invokevirtual #10                 // Method org/apache/hadoop/hbase/ipc/RpcControllerFactory.newController:()Lorg/apache/hadoop/hbase/ipc/HBaseRpcController;
      25: iconst_m1
      26: aload_2
      27: invokespecial #23                 // Method org/apache/hadoop/hbase/client/SecureBulkLoadClient$2."<init>":(Lorg/apache/hadoop/hbase/client/SecureBulkLoadClient;Lorg/apache/hadoop/hbase/client/Connection;Lorg/apache/hadoop/hbase/TableName;[BLorg/apache/hbase/thirdparty/com/google/protobuf/RpcController;ILjava/lang/String;)V
      30: astore_3
      31: aload_1
      32: invokeinterface #12,  1           // InterfaceMethod org/apache/hadoop/hbase/client/Connection.getConfiguration:()Lorg/apache/hadoop/conf/Configuration;
      37: aconst_null
      38: invokestatic  #13                 // Method org/apache/hadoop/hbase/client/RpcRetryingCallerFactory.instantiate:(Lorg/apache/hadoop/conf/Configuration;Lorg/apache/hadoop/hbase/client/ServerStatisticTracker;)Lorg/apache/hadoop/hbase/client/RpcRetryingCallerFactory;
      41: invokevirtual #14                 // Method org/apache/hadoop/hbase/client/RpcRetryingCallerFactory.newCaller:()Lorg/apache/hadoop/hbase/client/RpcRetryingCaller;
      44: aload_3
      45: ldc           #16                 // int 2147483647
      47: invokeinterface #17,  3           // InterfaceMethod org/apache/hadoop/hbase/client/RpcRetryingCaller.callWithRetries:(Lorg/apache/hadoop/hbase/client/RetryingCallable;I)Ljava/lang/Object;
      52: pop
      53: goto          66
      56: astore_3
      57: new           #20                 // class java/io/IOException
      60: dup
      61: aload_3
      62: invokespecial #21                 // Method java/io/IOException."<init>":(Ljava/lang/Throwable;)V
      65: athrow
      66: return
    Exception table:
       from    to  target type
           0    53    56   Class java/lang/Throwable

  public boolean secureBulkLoadHFiles(org.apache.hadoop.hbase.shaded.protobuf.generated.ClientProtos$ClientService$BlockingInterface, java.util.List<org.apache.hadoop.hbase.util.Pair<byte[], java.lang.String>>, byte[], boolean, org.apache.hadoop.security.token.Token<?>, java.lang.String) throws java.io.IOException;
    Code:
       0: aload_0
       1: aload_1
       2: aload_2
       3: aload_3
       4: iload         4
       6: aload         5
       8: aload         6
      10: iconst_0
      11: invokevirtual #24                 // Method secureBulkLoadHFiles:(Lorg/apache/hadoop/hbase/shaded/protobuf/generated/ClientProtos$ClientService$BlockingInterface;Ljava/util/List;[BZLorg/apache/hadoop/security/token/Token;Ljava/lang/String;Z)Z
      14: ireturn

  public boolean secureBulkLoadHFiles(org.apache.hadoop.hbase.shaded.protobuf.generated.ClientProtos$ClientService$BlockingInterface, java.util.List<org.apache.hadoop.hbase.util.Pair<byte[], java.lang.String>>, byte[], boolean, org.apache.hadoop.security.token.Token<?>, java.lang.String, boolean) throws java.io.IOException;
    Code:
       0: aload_2
       1: aload_3
       2: iload         4
       4: aload         5
       6: aload         6
       8: iload         7
      10: invokestatic  #25                 // Method org/apache/hadoop/hbase/shaded/protobuf/RequestConverter.buildBulkLoadHFileRequest:(Ljava/util/List;[BZLorg/apache/hadoop/security/token/Token;Ljava/lang/String;Z)Lorg/apache/hadoop/hbase/shaded/protobuf/generated/ClientProtos$BulkLoadHFileRequest;
      13: astore        8
      15: aload_1
      16: aconst_null
      17: aload         8
      19: invokeinterface #26,  3           // InterfaceMethod org/apache/hadoop/hbase/shaded/protobuf/generated/ClientProtos$ClientService$BlockingInterface.bulkLoadHFile:(Lorg/apache/hbase/thirdparty/com/google/protobuf/RpcController;Lorg/apache/hadoop/hbase/shaded/protobuf/generated/ClientProtos$BulkLoadHFileRequest;)Lorg/apache/hadoop/hbase/shaded/protobuf/generated/ClientProtos$BulkLoadHFileResponse;
      24: astore        9
      26: aload         9
      28: invokevirtual #27                 // Method org/apache/hadoop/hbase/shaded/protobuf/generated/ClientProtos$BulkLoadHFileResponse.getLoaded:()Z
      31: ireturn
      32: astore        9
      34: aload         9
      36: invokestatic  #29                 // Method org/apache/hadoop/hbase/shaded/protobuf/ProtobufUtil.handleRemoteException:(Ljava/lang/Exception;)Ljava/io/IOException;
      39: athrow
    Exception table:
       from    to  target type
          15    31    32   Class java/lang/Exception

  static org.apache.hadoop.hbase.client.Table access$000(org.apache.hadoop.hbase.client.SecureBulkLoadClient);
    Code:
       0: aload_0
       1: getfield      #2                  // Field table:Lorg/apache/hadoop/hbase/client/Table;
       4: areturn
}
