Compiled from "SegmentFactory.java"
public final class org.apache.hadoop.hbase.regionserver.SegmentFactory {
  static final boolean $assertionsDisabled;

  public static org.apache.hadoop.hbase.regionserver.SegmentFactory instance();
    Code:
       0: getstatic     #2                  // Field instance:Lorg/apache/hadoop/hbase/regionserver/SegmentFactory;
       3: areturn

  public org.apache.hadoop.hbase.regionserver.CompositeImmutableSegment createCompositeImmutableSegment(org.apache.hadoop.hbase.CellComparator, java.util.List<org.apache.hadoop.hbase.regionserver.ImmutableSegment>);
    Code:
       0: new           #3                  // class org/apache/hadoop/hbase/regionserver/CompositeImmutableSegment
       3: dup
       4: aload_1
       5: aload_2
       6: invokespecial #4                  // Method org/apache/hadoop/hbase/regionserver/CompositeImmutableSegment."<init>":(Lorg/apache/hadoop/hbase/CellComparator;Ljava/util/List;)V
       9: areturn

  public org.apache.hadoop.hbase.regionserver.ImmutableSegment createImmutableSegmentByCompaction(org.apache.hadoop.conf.Configuration, org.apache.hadoop.hbase.CellComparator, org.apache.hadoop.hbase.regionserver.MemStoreSegmentsIterator, int, org.apache.hadoop.hbase.regionserver.CompactingMemStore$IndexType, org.apache.hadoop.hbase.regionserver.MemStoreCompactionStrategy$Action) throws java.io.IOException;
    Code:
       0: aload_1
       1: invokestatic  #5                  // InterfaceMethod org/apache/hadoop/hbase/regionserver/MemStoreLAB.newInstance:(Lorg/apache/hadoop/conf/Configuration;)Lorg/apache/hadoop/hbase/regionserver/MemStoreLAB;
       4: astore        7
       6: aload_0
       7: aload_1
       8: aload_2
       9: aload_3
      10: aload         7
      12: iload         4
      14: aload         6
      16: aload         5
      18: invokespecial #6                  // Method createImmutableSegment:(Lorg/apache/hadoop/conf/Configuration;Lorg/apache/hadoop/hbase/CellComparator;Lorg/apache/hadoop/hbase/regionserver/MemStoreSegmentsIterator;Lorg/apache/hadoop/hbase/regionserver/MemStoreLAB;ILorg/apache/hadoop/hbase/regionserver/MemStoreCompactionStrategy$Action;Lorg/apache/hadoop/hbase/regionserver/CompactingMemStore$IndexType;)Lorg/apache/hadoop/hbase/regionserver/ImmutableSegment;
      21: areturn

  public org.apache.hadoop.hbase.regionserver.ImmutableSegment createImmutableSegment(org.apache.hadoop.hbase.CellComparator);
    Code:
       0: aload_0
       1: aconst_null
       2: aload_1
       3: aconst_null
       4: aconst_null
       5: invokespecial #7                  // Method generateMutableSegment:(Lorg/apache/hadoop/conf/Configuration;Lorg/apache/hadoop/hbase/CellComparator;Lorg/apache/hadoop/hbase/regionserver/MemStoreLAB;Lorg/apache/hadoop/hbase/regionserver/MemStoreSizing;)Lorg/apache/hadoop/hbase/regionserver/MutableSegment;
       8: astore_2
       9: aload_0
      10: aload_2
      11: aconst_null
      12: invokevirtual #8                  // Method createImmutableSegment:(Lorg/apache/hadoop/hbase/regionserver/MutableSegment;Lorg/apache/hadoop/hbase/regionserver/MemStoreSizing;)Lorg/apache/hadoop/hbase/regionserver/ImmutableSegment;
      15: areturn

  public org.apache.hadoop.hbase.regionserver.ImmutableSegment createImmutableSegment(org.apache.hadoop.hbase.regionserver.MutableSegment, org.apache.hadoop.hbase.regionserver.MemStoreSizing);
    Code:
       0: new           #9                  // class org/apache/hadoop/hbase/regionserver/CSLMImmutableSegment
       3: dup
       4: aload_1
       5: aload_2
       6: invokespecial #10                 // Method org/apache/hadoop/hbase/regionserver/CSLMImmutableSegment."<init>":(Lorg/apache/hadoop/hbase/regionserver/Segment;Lorg/apache/hadoop/hbase/regionserver/MemStoreSizing;)V
       9: areturn

  public org.apache.hadoop.hbase.regionserver.MutableSegment createMutableSegment(org.apache.hadoop.conf.Configuration, org.apache.hadoop.hbase.CellComparator, org.apache.hadoop.hbase.regionserver.MemStoreSizing);
    Code:
       0: aload_1
       1: invokestatic  #5                  // InterfaceMethod org/apache/hadoop/hbase/regionserver/MemStoreLAB.newInstance:(Lorg/apache/hadoop/conf/Configuration;)Lorg/apache/hadoop/hbase/regionserver/MemStoreLAB;
       4: astore        4
       6: aload_0
       7: aload_1
       8: aload_2
       9: aload         4
      11: aload_3
      12: invokespecial #7                  // Method generateMutableSegment:(Lorg/apache/hadoop/conf/Configuration;Lorg/apache/hadoop/hbase/CellComparator;Lorg/apache/hadoop/hbase/regionserver/MemStoreLAB;Lorg/apache/hadoop/hbase/regionserver/MemStoreSizing;)Lorg/apache/hadoop/hbase/regionserver/MutableSegment;
      15: areturn

  public org.apache.hadoop.hbase.regionserver.ImmutableSegment createImmutableSegmentByMerge(org.apache.hadoop.conf.Configuration, org.apache.hadoop.hbase.CellComparator, org.apache.hadoop.hbase.regionserver.MemStoreSegmentsIterator, int, java.util.List<org.apache.hadoop.hbase.regionserver.ImmutableSegment>, org.apache.hadoop.hbase.regionserver.CompactingMemStore$IndexType, org.apache.hadoop.hbase.regionserver.MemStoreCompactionStrategy$Action) throws java.io.IOException;
    Code:
       0: aload_0
       1: aload_1
       2: aload         5
       4: invokespecial #11                 // Method getMergedMemStoreLAB:(Lorg/apache/hadoop/conf/Configuration;Ljava/util/List;)Lorg/apache/hadoop/hbase/regionserver/MemStoreLAB;
       7: astore        8
       9: aload_0
      10: aload_1
      11: aload_2
      12: aload_3
      13: aload         8
      15: iload         4
      17: aload         7
      19: aload         6
      21: invokespecial #6                  // Method createImmutableSegment:(Lorg/apache/hadoop/conf/Configuration;Lorg/apache/hadoop/hbase/CellComparator;Lorg/apache/hadoop/hbase/regionserver/MemStoreSegmentsIterator;Lorg/apache/hadoop/hbase/regionserver/MemStoreLAB;ILorg/apache/hadoop/hbase/regionserver/MemStoreCompactionStrategy$Action;Lorg/apache/hadoop/hbase/regionserver/CompactingMemStore$IndexType;)Lorg/apache/hadoop/hbase/regionserver/ImmutableSegment;
      24: areturn

  public org.apache.hadoop.hbase.regionserver.ImmutableSegment createImmutableSegmentByFlattening(org.apache.hadoop.hbase.regionserver.CSLMImmutableSegment, org.apache.hadoop.hbase.regionserver.CompactingMemStore$IndexType, org.apache.hadoop.hbase.regionserver.MemStoreSizing, org.apache.hadoop.hbase.regionserver.MemStoreCompactionStrategy$Action);
    Code:
       0: aconst_null
       1: astore        5
       3: getstatic     #12                 // Field org/apache/hadoop/hbase/regionserver/SegmentFactory$1.$SwitchMap$org$apache$hadoop$hbase$regionserver$CompactingMemStore$IndexType:[I
       6: aload_2
       7: invokevirtual #13                 // Method org/apache/hadoop/hbase/regionserver/CompactingMemStore$IndexType.ordinal:()I
      10: iaload
      11: tableswitch   { // 1 to 3
                     1: 36
                     2: 52
                     3: 66
               default: 79
          }
      36: new           #14                 // class org/apache/hadoop/hbase/regionserver/CellChunkImmutableSegment
      39: dup
      40: aload_1
      41: aload_3
      42: aload         4
      44: invokespecial #15                 // Method org/apache/hadoop/hbase/regionserver/CellChunkImmutableSegment."<init>":(Lorg/apache/hadoop/hbase/regionserver/CSLMImmutableSegment;Lorg/apache/hadoop/hbase/regionserver/MemStoreSizing;Lorg/apache/hadoop/hbase/regionserver/MemStoreCompactionStrategy$Action;)V
      47: astore        5
      49: goto          79
      52: getstatic     #16                 // Field $assertionsDisabled:Z
      55: ifne          79
      58: new           #17                 // class java/lang/AssertionError
      61: dup
      62: invokespecial #18                 // Method java/lang/AssertionError."<init>":()V
      65: athrow
      66: new           #19                 // class org/apache/hadoop/hbase/regionserver/CellArrayImmutableSegment
      69: dup
      70: aload_1
      71: aload_3
      72: aload         4
      74: invokespecial #20                 // Method org/apache/hadoop/hbase/regionserver/CellArrayImmutableSegment."<init>":(Lorg/apache/hadoop/hbase/regionserver/CSLMImmutableSegment;Lorg/apache/hadoop/hbase/regionserver/MemStoreSizing;Lorg/apache/hadoop/hbase/regionserver/MemStoreCompactionStrategy$Action;)V
      77: astore        5
      79: aload         5
      81: areturn

  static {};
    Code:
       0: ldc           #40                 // class org/apache/hadoop/hbase/regionserver/SegmentFactory
       2: invokevirtual #41                 // Method java/lang/Class.desiredAssertionStatus:()Z
       5: ifne          12
       8: iconst_1
       9: goto          13
      12: iconst_0
      13: putstatic     #16                 // Field $assertionsDisabled:Z
      16: new           #40                 // class org/apache/hadoop/hbase/regionserver/SegmentFactory
      19: dup
      20: invokespecial #42                 // Method "<init>":()V
      23: putstatic     #2                  // Field instance:Lorg/apache/hadoop/hbase/regionserver/SegmentFactory;
      26: return
}
