Compiled from "SerialReplicationChecker.java"
class org.apache.hadoop.hbase.replication.regionserver.SerialReplicationChecker {
  public static final java.lang.String REPLICATION_SERIALLY_WAITING_KEY;

  public static final long REPLICATION_SERIALLY_WAITING_DEFAULT;

  public org.apache.hadoop.hbase.replication.regionserver.SerialReplicationChecker(org.apache.hadoop.conf.Configuration, org.apache.hadoop.hbase.replication.regionserver.ReplicationSource);
    Code:
       0: aload_0
       1: invokespecial #1                  // Method java/lang/Object."<init>":()V
       4: aload_0
       5: invokestatic  #2                  // Method org/apache/hbase/thirdparty/com/google/common/cache/CacheBuilder.newBuilder:()Lorg/apache/hbase/thirdparty/com/google/common/cache/CacheBuilder;
       8: lconst_1
       9: getstatic     #3                  // Field java/util/concurrent/TimeUnit.DAYS:Ljava/util/concurrent/TimeUnit;
      12: invokevirtual #4                  // Method org/apache/hbase/thirdparty/com/google/common/cache/CacheBuilder.expireAfterAccess:(JLjava/util/concurrent/TimeUnit;)Lorg/apache/hbase/thirdparty/com/google/common/cache/CacheBuilder;
      15: new           #5                  // class org/apache/hadoop/hbase/replication/regionserver/SerialReplicationChecker$1
      18: dup
      19: aload_0
      20: invokespecial #6                  // Method org/apache/hadoop/hbase/replication/regionserver/SerialReplicationChecker$1."<init>":(Lorg/apache/hadoop/hbase/replication/regionserver/SerialReplicationChecker;)V
      23: invokevirtual #7                  // Method org/apache/hbase/thirdparty/com/google/common/cache/CacheBuilder.build:(Lorg/apache/hbase/thirdparty/com/google/common/cache/CacheLoader;)Lorg/apache/hbase/thirdparty/com/google/common/cache/LoadingCache;
      26: putfield      #8                  // Field pushed:Lorg/apache/hbase/thirdparty/com/google/common/cache/LoadingCache;
      29: aload_0
      30: invokestatic  #2                  // Method org/apache/hbase/thirdparty/com/google/common/cache/CacheBuilder.newBuilder:()Lorg/apache/hbase/thirdparty/com/google/common/cache/CacheBuilder;
      33: lconst_1
      34: getstatic     #3                  // Field java/util/concurrent/TimeUnit.DAYS:Ljava/util/concurrent/TimeUnit;
      37: invokevirtual #4                  // Method org/apache/hbase/thirdparty/com/google/common/cache/CacheBuilder.expireAfterAccess:(JLjava/util/concurrent/TimeUnit;)Lorg/apache/hbase/thirdparty/com/google/common/cache/CacheBuilder;
      40: invokevirtual #9                  // Method org/apache/hbase/thirdparty/com/google/common/cache/CacheBuilder.build:()Lorg/apache/hbase/thirdparty/com/google/common/cache/Cache;
      43: putfield      #10                 // Field canPushUnder:Lorg/apache/hbase/thirdparty/com/google/common/cache/Cache;
      46: aload_0
      47: aload_2
      48: invokevirtual #11                 // Method org/apache/hadoop/hbase/replication/regionserver/ReplicationSource.getPeerId:()Ljava/lang/String;
      51: putfield      #12                 // Field peerId:Ljava/lang/String;
      54: aload_0
      55: aload_2
      56: invokevirtual #13                 // Method org/apache/hadoop/hbase/replication/regionserver/ReplicationSource.getQueueStorage:()Lorg/apache/hadoop/hbase/replication/ReplicationQueueStorage;
      59: putfield      #14                 // Field storage:Lorg/apache/hadoop/hbase/replication/ReplicationQueueStorage;
      62: aload_0
      63: aload_2
      64: invokevirtual #15                 // Method org/apache/hadoop/hbase/replication/regionserver/ReplicationSource.getServer:()Lorg/apache/hadoop/hbase/Server;
      67: invokeinterface #16,  1           // InterfaceMethod org/apache/hadoop/hbase/Server.getConnection:()Lorg/apache/hadoop/hbase/client/Connection;
      72: putfield      #17                 // Field conn:Lorg/apache/hadoop/hbase/client/Connection;
      75: aload_0
      76: aload_1
      77: ldc           #19                 // String hbase.serial.replication.waiting.ms
      79: ldc2_w        #20                 // long 10000l
      82: invokevirtual #22                 // Method org/apache/hadoop/conf/Configuration.getLong:(Ljava/lang/String;J)J
      85: putfield      #23                 // Field waitTimeMs:J
      88: return

  public boolean canPush(org.apache.hadoop.hbase.wal.WAL$Entry, org.apache.hadoop.hbase.Cell) throws java.io.IOException;
    Code:
       0: aload_1
       1: invokevirtual #45                 // Method org/apache/hadoop/hbase/wal/WAL$Entry.getKey:()Lorg/apache/hadoop/hbase/wal/WALKeyImpl;
       4: invokevirtual #46                 // Method org/apache/hadoop/hbase/wal/WALKeyImpl.getEncodedRegionName:()[B
       7: invokestatic  #47                 // Method org/apache/hadoop/hbase/util/Bytes.toString:([B)Ljava/lang/String;
      10: astore_3
      11: aload_1
      12: invokevirtual #45                 // Method org/apache/hadoop/hbase/wal/WAL$Entry.getKey:()Lorg/apache/hadoop/hbase/wal/WALKeyImpl;
      15: invokevirtual #48                 // Method org/apache/hadoop/hbase/wal/WALKeyImpl.getSequenceId:()J
      18: lstore        4
      20: aload_0
      21: getfield      #10                 // Field canPushUnder:Lorg/apache/hbase/thirdparty/com/google/common/cache/Cache;
      24: aload_3
      25: invokeinterface #71,  2           // InterfaceMethod org/apache/hbase/thirdparty/com/google/common/cache/Cache.getIfPresent:(Ljava/lang/Object;)Ljava/lang/Object;
      30: checkcast     #72                 // class java/lang/Long
      33: astore        6
      35: aload         6
      37: ifnull        89
      40: lload         4
      42: aload         6
      44: invokevirtual #73                 // Method java/lang/Long.longValue:()J
      47: lcmp
      48: ifge          66
      51: getstatic     #51                 // Field LOG:Lorg/slf4j/Logger;
      54: ldc           #74                 // String {} is before the end barrier {}, pass
      56: aload_1
      57: aload         6
      59: invokeinterface #75,  4           // InterfaceMethod org/slf4j/Logger.trace:(Ljava/lang/String;Ljava/lang/Object;Ljava/lang/Object;)V
      64: iconst_1
      65: ireturn
      66: getstatic     #51                 // Field LOG:Lorg/slf4j/Logger;
      69: ldc           #76                 // String {} is beyond the previous end barrier {}, remove from cache
      71: aload_1
      72: aload         6
      74: invokeinterface #53,  4           // InterfaceMethod org/slf4j/Logger.debug:(Ljava/lang/String;Ljava/lang/Object;Ljava/lang/Object;)V
      79: aload_0
      80: getfield      #10                 // Field canPushUnder:Lorg/apache/hbase/thirdparty/com/google/common/cache/Cache;
      83: aload_3
      84: invokeinterface #77,  2           // InterfaceMethod org/apache/hbase/thirdparty/com/google/common/cache/Cache.invalidate:(Ljava/lang/Object;)V
      89: aload_0
      90: getfield      #8                  // Field pushed:Lorg/apache/hbase/thirdparty/com/google/common/cache/LoadingCache;
      93: aload_3
      94: invokeinterface #42,  2           // InterfaceMethod org/apache/hbase/thirdparty/com/google/common/cache/LoadingCache.getUnchecked:(Ljava/lang/Object;)Ljava/lang/Object;
      99: checkcast     #43                 // class org/apache/commons/lang3/mutable/MutableLong
     102: astore        7
     104: lload         4
     106: aload         7
     108: invokevirtual #78                 // Method org/apache/commons/lang3/mutable/MutableLong.longValue:()J
     111: lconst_1
     112: ladd
     113: lcmp
     114: ifne          135
     117: getstatic     #51                 // Field LOG:Lorg/slf4j/Logger;
     120: ldc           #79                 // String The sequence id for {} is continuous, pass
     122: aload_1
     123: invokeinterface #80,  3           // InterfaceMethod org/slf4j/Logger.trace:(Ljava/lang/String;Ljava/lang/Object;)V
     128: aload         7
     130: invokevirtual #81                 // Method org/apache/commons/lang3/mutable/MutableLong.increment:()V
     133: iconst_1
     134: ireturn
     135: aload_0
     136: aload_1
     137: aload_2
     138: invokestatic  #82                 // Method org/apache/hadoop/hbase/CellUtil.cloneRow:(Lorg/apache/hadoop/hbase/Cell;)[B
     141: invokespecial #83                 // Method canPush:(Lorg/apache/hadoop/hbase/wal/WAL$Entry;[B)Z
     144: ireturn

  public void waitUntilCanPush(org.apache.hadoop.hbase.wal.WAL$Entry, org.apache.hadoop.hbase.Cell) throws java.io.IOException, java.lang.InterruptedException;
    Code:
       0: aload_2
       1: invokestatic  #82                 // Method org/apache/hadoop/hbase/CellUtil.cloneRow:(Lorg/apache/hadoop/hbase/Cell;)[B
       4: astore_3
       5: aload_0
       6: aload_1
       7: aload_3
       8: invokespecial #83                 // Method canPush:(Lorg/apache/hadoop/hbase/wal/WAL$Entry;[B)Z
      11: ifne          35
      14: getstatic     #51                 // Field LOG:Lorg/slf4j/Logger;
      17: ldc           #84                 // String Can not push {}, wait
      19: aload_1
      20: invokeinterface #56,  3           // InterfaceMethod org/slf4j/Logger.debug:(Ljava/lang/String;Ljava/lang/Object;)V
      25: aload_0
      26: getfield      #23                 // Field waitTimeMs:J
      29: invokestatic  #85                 // Method java/lang/Thread.sleep:(J)V
      32: goto          5
      35: return

  static {};
    Code:
       0: ldc           #18                 // class org/apache/hadoop/hbase/replication/regionserver/SerialReplicationChecker
       2: invokestatic  #86                 // Method org/slf4j/LoggerFactory.getLogger:(Ljava/lang/Class;)Lorg/slf4j/Logger;
       5: putstatic     #51                 // Field LOG:Lorg/slf4j/Logger;
       8: return
}
