Compiled from "ServerStatisticTracker.java"
public class org.apache.hadoop.hbase.client.ServerStatisticTracker implements org.apache.hadoop.hbase.client.StatisticTrackable {
  public org.apache.hadoop.hbase.client.ServerStatisticTracker();
    Code:
       0: aload_0
       1: invokespecial #1                  // Method java/lang/Object."<init>":()V
       4: aload_0
       5: new           #2                  // class java/util/concurrent/ConcurrentHashMap
       8: dup
       9: invokespecial #3                  // Method java/util/concurrent/ConcurrentHashMap."<init>":()V
      12: putfield      #4                  // Field stats:Ljava/util/concurrent/ConcurrentHashMap;
      15: return

  public void updateRegionStats(org.apache.hadoop.hbase.ServerName, byte[], org.apache.hadoop.hbase.client.RegionLoadStats);
    Code:
       0: aload_0
       1: getfield      #4                  // Field stats:Ljava/util/concurrent/ConcurrentHashMap;
       4: aload_1
       5: invokedynamic #5,  0              // InvokeDynamic #0:get:()Ljava/util/function/Supplier;
      10: invokestatic  #6                  // Method org/apache/hadoop/hbase/util/ConcurrentMapUtils.computeIfAbsent:(Ljava/util/concurrent/ConcurrentMap;Ljava/lang/Object;Ljava/util/function/Supplier;)Ljava/lang/Object;
      13: checkcast     #7                  // class org/apache/hadoop/hbase/client/backoff/ServerStatistics
      16: aload_2
      17: aload_3
      18: invokevirtual #8                  // Method org/apache/hadoop/hbase/client/backoff/ServerStatistics.update:([BLorg/apache/hadoop/hbase/client/RegionLoadStats;)V
      21: return

  public org.apache.hadoop.hbase.client.backoff.ServerStatistics getStats(org.apache.hadoop.hbase.ServerName);
    Code:
       0: aload_0
       1: getfield      #4                  // Field stats:Ljava/util/concurrent/ConcurrentHashMap;
       4: aload_1
       5: invokevirtual #9                  // Method java/util/concurrent/ConcurrentHashMap.get:(Ljava/lang/Object;)Ljava/lang/Object;
       8: checkcast     #7                  // class org/apache/hadoop/hbase/client/backoff/ServerStatistics
      11: areturn

  public static org.apache.hadoop.hbase.client.ServerStatisticTracker create(org.apache.hadoop.conf.Configuration);
    Code:
       0: aload_0
       1: ldc           #11                 // String hbase.client.backpressure.enabled
       3: iconst_0
       4: invokevirtual #12                 // Method org/apache/hadoop/conf/Configuration.getBoolean:(Ljava/lang/String;Z)Z
       7: ifne          12
      10: aconst_null
      11: areturn
      12: new           #13                 // class org/apache/hadoop/hbase/client/ServerStatisticTracker
      15: dup
      16: invokespecial #14                 // Method "<init>":()V
      19: areturn
}
