Compiled from "ServerMetricsTmplImpl.java"
public class org.apache.hadoop.hbase.tmpl.regionserver.ServerMetricsTmplImpl extends org.jamon.AbstractTemplateImpl implements org.apache.hadoop.hbase.tmpl.regionserver.ServerMetricsTmpl$Intf {
  protected static org.apache.hadoop.hbase.tmpl.regionserver.ServerMetricsTmpl$ImplData __jamon_setOptionalArguments(org.apache.hadoop.hbase.tmpl.regionserver.ServerMetricsTmpl$ImplData);
    Code:
       0: aload_0
       1: areturn

  public org.apache.hadoop.hbase.tmpl.regionserver.ServerMetricsTmplImpl(org.jamon.TemplateManager, org.apache.hadoop.hbase.tmpl.regionserver.ServerMetricsTmpl$ImplData);
    Code:
       0: aload_0
       1: aload_1
       2: aload_2
       3: invokestatic  #1                  // Method __jamon_setOptionalArguments:(Lorg/apache/hadoop/hbase/tmpl/regionserver/ServerMetricsTmpl$ImplData;)Lorg/apache/hadoop/hbase/tmpl/regionserver/ServerMetricsTmpl$ImplData;
       6: invokespecial #2                  // Method org/jamon/AbstractTemplateImpl."<init>":(Lorg/jamon/TemplateManager;Lorg/jamon/AbstractTemplateProxy$ImplData;)V
       9: aload_0
      10: aload_2
      11: invokevirtual #3                  // Method org/apache/hadoop/hbase/tmpl/regionserver/ServerMetricsTmpl$ImplData.getMWrap:()Lorg/apache/hadoop/hbase/regionserver/MetricsRegionServerWrapper;
      14: putfield      #4                  // Field mWrap:Lorg/apache/hadoop/hbase/regionserver/MetricsRegionServerWrapper;
      17: aload_0
      18: aload_2
      19: invokevirtual #5                  // Method org/apache/hadoop/hbase/tmpl/regionserver/ServerMetricsTmpl$ImplData.getMServerWrap:()Lorg/apache/hadoop/hbase/ipc/MetricsHBaseServerWrapper;
      22: putfield      #6                  // Field mServerWrap:Lorg/apache/hadoop/hbase/ipc/MetricsHBaseServerWrapper;
      25: return

  public void renderNoFlush(java.io.Writer) throws java.io.IOException;
    Code:
       0: aload_1
       1: ldc           #7                  // String <div class=\"tabbable\">\n    <ul class=\"nav nav-pills\">\n        <li class=\"active\"><a href=\"#tab_baseStats\" data-toggle=\"tab\">Base Stats</a></li>\n        <li class=\"\"><a href=\"#tab_memoryStats\" data-toggle=\"tab\">Memory</a></li>\n        <li class=\"\"><a href=\"#tab_requestStats\" data-toggle=\"tab\">Requests</a></li>\n        <li class=\"\"><a href=\"#tab_walStats\" data-toggle=\"tab\">WALs</a></li>\n        <li class=\"\"><a href=\"#tab_storeStats\" data-toggle=\"tab\">Storefiles</a></li>\n        <li class=\"\"><a href=\"#tab_queueStats\" data-toggle=\"tab\">Queues</a></li>\n    </ul>\n    <div class=\"tab-content\" style=\"padding-bottom: 9px; border-bottom: 1px solid #ddd;\">\n        <div class=\"tab-pane active\" id=\"tab_baseStats\">\n
       3: invokevirtual #8                  // Method java/io/Writer.write:(Ljava/lang/String;)V
       6: aload_0
       7: aload_1
       8: aload_0
       9: getfield      #4                  // Field mWrap:Lorg/apache/hadoop/hbase/regionserver/MetricsRegionServerWrapper;
      12: invokespecial #9                  // Method __jamon_innerUnit__baseStats:(Ljava/io/Writer;Lorg/apache/hadoop/hbase/regionserver/MetricsRegionServerWrapper;)V
      15: aload_1
      16: ldc           #10                 // String \n        </div>\n        <div class=\"tab-pane\" id=\"tab_memoryStats\">\n
      18: invokevirtual #8                  // Method java/io/Writer.write:(Ljava/lang/String;)V
      21: aload_0
      22: aload_1
      23: aload_0
      24: getfield      #4                  // Field mWrap:Lorg/apache/hadoop/hbase/regionserver/MetricsRegionServerWrapper;
      27: invokespecial #11                 // Method __jamon_innerUnit__memoryStats:(Ljava/io/Writer;Lorg/apache/hadoop/hbase/regionserver/MetricsRegionServerWrapper;)V
      30: aload_1
      31: ldc           #12                 // String \n        </div>\n        <div class=\"tab-pane\" id=\"tab_requestStats\">\n
      33: invokevirtual #8                  // Method java/io/Writer.write:(Ljava/lang/String;)V
      36: aload_0
      37: aload_1
      38: aload_0
      39: getfield      #4                  // Field mWrap:Lorg/apache/hadoop/hbase/regionserver/MetricsRegionServerWrapper;
      42: invokespecial #13                 // Method __jamon_innerUnit__requestStats:(Ljava/io/Writer;Lorg/apache/hadoop/hbase/regionserver/MetricsRegionServerWrapper;)V
      45: aload_1
      46: ldc           #14                 // String \n        </div>\n        <div class=\"tab-pane\" id=\"tab_walStats\">\n
      48: invokevirtual #8                  // Method java/io/Writer.write:(Ljava/lang/String;)V
      51: aload_0
      52: aload_1
      53: aload_0
      54: getfield      #4                  // Field mWrap:Lorg/apache/hadoop/hbase/regionserver/MetricsRegionServerWrapper;
      57: invokespecial #15                 // Method __jamon_innerUnit__walStats:(Ljava/io/Writer;Lorg/apache/hadoop/hbase/regionserver/MetricsRegionServerWrapper;)V
      60: aload_1
      61: ldc           #16                 // String \n        </div>\n        <div class=\"tab-pane\" id=\"tab_storeStats\">\n
      63: invokevirtual #8                  // Method java/io/Writer.write:(Ljava/lang/String;)V
      66: aload_0
      67: aload_1
      68: aload_0
      69: getfield      #4                  // Field mWrap:Lorg/apache/hadoop/hbase/regionserver/MetricsRegionServerWrapper;
      72: invokespecial #17                 // Method __jamon_innerUnit__storeStats:(Ljava/io/Writer;Lorg/apache/hadoop/hbase/regionserver/MetricsRegionServerWrapper;)V
      75: aload_1
      76: ldc           #18                 // String \n        </div>\n        <div class=\"tab-pane\" id=\"tab_queueStats\">\n
      78: invokevirtual #8                  // Method java/io/Writer.write:(Ljava/lang/String;)V
      81: aload_0
      82: aload_1
      83: aload_0
      84: getfield      #4                  // Field mWrap:Lorg/apache/hadoop/hbase/regionserver/MetricsRegionServerWrapper;
      87: aload_0
      88: getfield      #6                  // Field mServerWrap:Lorg/apache/hadoop/hbase/ipc/MetricsHBaseServerWrapper;
      91: invokespecial #19                 // Method __jamon_innerUnit__queueStats:(Ljava/io/Writer;Lorg/apache/hadoop/hbase/regionserver/MetricsRegionServerWrapper;Lorg/apache/hadoop/hbase/ipc/MetricsHBaseServerWrapper;)V
      94: aload_1
      95: ldc           #20                 // String \n        </div>\n    </div>\n</div>\n\n
      97: invokevirtual #8                  // Method java/io/Writer.write:(Ljava/lang/String;)V
     100: return
}
