Compiled from "Server.java"
public interface org.apache.hadoop.hbase.Server extends org.apache.hadoop.hbase.Abortable,org.apache.hadoop.hbase.Stoppable {
  public abstract org.apache.hadoop.conf.Configuration getConfiguration();

  public abstract org.apache.hadoop.hbase.zookeeper.ZKWatcher getZooKeeper();

  public abstract org.apache.hadoop.hbase.client.Connection getConnection();

  public abstract org.apache.hadoop.hbase.client.Connection createConnection(org.apache.hadoop.conf.Configuration) throws java.io.IOException;

  public abstract org.apache.hadoop.hbase.client.ClusterConnection getClusterConnection();

  public abstract org.apache.hadoop.hbase.ServerName getServerName();

  public abstract org.apache.hadoop.hbase.CoordinatedStateManager getCoordinatedStateManager();

  public abstract org.apache.hadoop.hbase.ChoreService getChoreService();

  public org.apache.hadoop.fs.FileSystem getFileSystem();
    Code:
       0: aload_0
       1: invokeinterface #1,  1            // InterfaceMethod getConfiguration:()Lorg/apache/hadoop/conf/Configuration;
       6: astore_1
       7: aconst_null
       8: astore_2
       9: aload_1
      10: ifnull        18
      13: aload_1
      14: invokestatic  #2                  // Method org/apache/hadoop/fs/FileSystem.get:(Lorg/apache/hadoop/conf/Configuration;)Lorg/apache/hadoop/fs/FileSystem;
      17: astore_2
      18: goto          22
      21: astore_3
      22: aload_2
      23: areturn
    Exception table:
       from    to  target type
           9    18    21   Class java/io/IOException

  public boolean isStopping();
    Code:
       0: iconst_0
       1: ireturn
}
