Compiled from "ServerCommandLine.java"
public abstract class org.apache.hadoop.hbase.util.ServerCommandLine extends org.apache.hadoop.conf.Configured implements org.apache.hadoop.util.Tool {
  public org.apache.hadoop.hbase.util.ServerCommandLine();
    Code:
       0: aload_0
       1: invokespecial #1                  // Method org/apache/hadoop/conf/Configured."<init>":()V
       4: return

  protected abstract java.lang.String getUsage();

  protected void usage(java.lang.String);
    Code:
       0: aload_1
       1: ifnull        19
       4: getstatic     #2                  // Field java/lang/System.err:Ljava/io/PrintStream;
       7: aload_1
       8: invokevirtual #3                  // Method java/io/PrintStream.println:(Ljava/lang/String;)V
      11: getstatic     #2                  // Field java/lang/System.err:Ljava/io/PrintStream;
      14: ldc           #4                  // String
      16: invokevirtual #3                  // Method java/io/PrintStream.println:(Ljava/lang/String;)V
      19: getstatic     #2                  // Field java/lang/System.err:Ljava/io/PrintStream;
      22: aload_0
      23: invokevirtual #5                  // Method getUsage:()Ljava/lang/String;
      26: invokevirtual #3                  // Method java/io/PrintStream.println:(Ljava/lang/String;)V
      29: return

  public static void logJVMInfo();
    Code:
       0: invokestatic  #6                  // Method java/lang/management/ManagementFactory.getRuntimeMXBean:()Ljava/lang/management/RuntimeMXBean;
       3: astore_0
       4: aload_0
       5: ifnull        100
       8: getstatic     #7                  // Field LOG:Lorg/slf4j/Logger;
      11: new           #8                  // class java/lang/StringBuilder
      14: dup
      15: invokespecial #9                  // Method java/lang/StringBuilder."<init>":()V
      18: ldc           #10                 // String vmName=
      20: invokevirtual #11                 // Method java/lang/StringBuilder.append:(Ljava/lang/String;)Ljava/lang/StringBuilder;
      23: aload_0
      24: invokeinterface #12,  1           // InterfaceMethod java/lang/management/RuntimeMXBean.getVmName:()Ljava/lang/String;
      29: invokevirtual #11                 // Method java/lang/StringBuilder.append:(Ljava/lang/String;)Ljava/lang/StringBuilder;
      32: ldc           #13                 // String , vmVendor=
      34: invokevirtual #11                 // Method java/lang/StringBuilder.append:(Ljava/lang/String;)Ljava/lang/StringBuilder;
      37: aload_0
      38: invokeinterface #14,  1           // InterfaceMethod java/lang/management/RuntimeMXBean.getVmVendor:()Ljava/lang/String;
      43: invokevirtual #11                 // Method java/lang/StringBuilder.append:(Ljava/lang/String;)Ljava/lang/StringBuilder;
      46: ldc           #15                 // String , vmVersion=
      48: invokevirtual #11                 // Method java/lang/StringBuilder.append:(Ljava/lang/String;)Ljava/lang/StringBuilder;
      51: aload_0
      52: invokeinterface #16,  1           // InterfaceMethod java/lang/management/RuntimeMXBean.getVmVersion:()Ljava/lang/String;
      57: invokevirtual #11                 // Method java/lang/StringBuilder.append:(Ljava/lang/String;)Ljava/lang/StringBuilder;
      60: invokevirtual #17                 // Method java/lang/StringBuilder.toString:()Ljava/lang/String;
      63: invokeinterface #18,  2           // InterfaceMethod org/slf4j/Logger.info:(Ljava/lang/String;)V
      68: getstatic     #7                  // Field LOG:Lorg/slf4j/Logger;
      71: new           #8                  // class java/lang/StringBuilder
      74: dup
      75: invokespecial #9                  // Method java/lang/StringBuilder."<init>":()V
      78: ldc           #19                 // String vmInputArguments=
      80: invokevirtual #11                 // Method java/lang/StringBuilder.append:(Ljava/lang/String;)Ljava/lang/StringBuilder;
      83: aload_0
      84: invokeinterface #20,  1           // InterfaceMethod java/lang/management/RuntimeMXBean.getInputArguments:()Ljava/util/List;
      89: invokevirtual #21                 // Method java/lang/StringBuilder.append:(Ljava/lang/Object;)Ljava/lang/StringBuilder;
      92: invokevirtual #17                 // Method java/lang/StringBuilder.toString:()Ljava/lang/String;
      95: invokeinterface #18,  2           // InterfaceMethod org/slf4j/Logger.info:(Ljava/lang/String;)V
     100: return

  public static void logProcessInfo(org.apache.hadoop.conf.Configuration);
    Code:
       0: aload_0
       1: invokestatic  #30                 // Method logHBaseConfigs:(Lorg/apache/hadoop/conf/Configuration;)V
       4: aload_0
       5: ifnull        18
       8: aload_0
       9: ldc           #31                 // String hbase.envvars.logging.disabled
      11: iconst_0
      12: invokevirtual #32                 // Method org/apache/hadoop/conf/Configuration.getBoolean:(Ljava/lang/String;Z)Z
      15: ifne          208
      18: new           #33                 // class java/util/HashSet
      21: dup
      22: getstatic     #34                 // Field DEFAULT_SKIP_WORDS:Ljava/util/Set;
      25: invokespecial #35                 // Method java/util/HashSet."<init>":(Ljava/util/Collection;)V
      28: astore_1
      29: aload_0
      30: ifnull        55
      33: aload_0
      34: ldc           #36                 // String hbase.envvars.logging.skipwords
      36: invokevirtual #37                 // Method org/apache/hadoop/conf/Configuration.getStrings:(Ljava/lang/String;)[Ljava/lang/String;
      39: astore_2
      40: aload_2
      41: ifnull        55
      44: aload_1
      45: aload_2
      46: invokestatic  #38                 // Method java/util/Arrays.asList:([Ljava/lang/Object;)Ljava/util/List;
      49: invokeinterface #39,  2           // InterfaceMethod java/util/Set.addAll:(Ljava/util/Collection;)Z
      54: pop
      55: invokestatic  #40                 // Method java/lang/System.getenv:()Ljava/util/Map;
      58: invokeinterface #41,  1           // InterfaceMethod java/util/Map.entrySet:()Ljava/util/Set;
      63: invokeinterface #42,  1           // InterfaceMethod java/util/Set.iterator:()Ljava/util/Iterator;
      68: astore_2
      69: aload_2
      70: invokeinterface #43,  1           // InterfaceMethod java/util/Iterator.hasNext:()Z
      75: ifeq          208
      78: aload_2
      79: invokeinterface #44,  1           // InterfaceMethod java/util/Iterator.next:()Ljava/lang/Object;
      84: checkcast     #45                 // class java/util/Map$Entry
      87: astore_3
      88: aload_3
      89: invokeinterface #46,  1           // InterfaceMethod java/util/Map$Entry.getKey:()Ljava/lang/Object;
      94: checkcast     #22                 // class java/lang/String
      97: getstatic     #47                 // Field java/util/Locale.ROOT:Ljava/util/Locale;
     100: invokevirtual #48                 // Method java/lang/String.toLowerCase:(Ljava/util/Locale;)Ljava/lang/String;
     103: astore        4
     105: aload_3
     106: invokeinterface #49,  1           // InterfaceMethod java/util/Map$Entry.getValue:()Ljava/lang/Object;
     111: checkcast     #22                 // class java/lang/String
     114: getstatic     #47                 // Field java/util/Locale.ROOT:Ljava/util/Locale;
     117: invokevirtual #48                 // Method java/lang/String.toLowerCase:(Ljava/util/Locale;)Ljava/lang/String;
     120: astore        5
     122: aload_1
     123: invokeinterface #42,  1           // InterfaceMethod java/util/Set.iterator:()Ljava/util/Iterator;
     128: astore        6
     130: aload         6
     132: invokeinterface #43,  1           // InterfaceMethod java/util/Iterator.hasNext:()Z
     137: ifeq          178
     140: aload         6
     142: invokeinterface #44,  1           // InterfaceMethod java/util/Iterator.next:()Ljava/lang/Object;
     147: checkcast     #22                 // class java/lang/String
     150: astore        7
     152: aload         4
     154: aload         7
     156: invokevirtual #50                 // Method java/lang/String.contains:(Ljava/lang/CharSequence;)Z
     159: ifne          69
     162: aload         5
     164: aload         7
     166: invokevirtual #50                 // Method java/lang/String.contains:(Ljava/lang/CharSequence;)Z
     169: ifeq          175
     172: goto          69
     175: goto          130
     178: getstatic     #7                  // Field LOG:Lorg/slf4j/Logger;
     181: new           #8                  // class java/lang/StringBuilder
     184: dup
     185: invokespecial #9                  // Method java/lang/StringBuilder."<init>":()V
     188: ldc           #51                 // String env:
     190: invokevirtual #11                 // Method java/lang/StringBuilder.append:(Ljava/lang/String;)Ljava/lang/StringBuilder;
     193: aload_3
     194: invokevirtual #21                 // Method java/lang/StringBuilder.append:(Ljava/lang/Object;)Ljava/lang/StringBuilder;
     197: invokevirtual #17                 // Method java/lang/StringBuilder.toString:()Ljava/lang/String;
     200: invokeinterface #18,  2           // InterfaceMethod org/slf4j/Logger.info:(Ljava/lang/String;)V
     205: goto          69
     208: invokestatic  #52                 // Method logJVMInfo:()V
     211: return

  public void doMain(java.lang.String[]);
    Code:
       0: invokestatic  #53                 // Method org/apache/hadoop/hbase/HBaseConfiguration.create:()Lorg/apache/hadoop/conf/Configuration;
       3: aload_0
       4: aload_1
       5: invokestatic  #54                 // Method org/apache/hadoop/util/ToolRunner.run:(Lorg/apache/hadoop/conf/Configuration;Lorg/apache/hadoop/util/Tool;[Ljava/lang/String;)I
       8: istore_2
       9: iload_2
      10: ifeq          17
      13: iload_2
      14: invokestatic  #55                 // Method java/lang/System.exit:(I)V
      17: goto          36
      20: astore_2
      21: getstatic     #7                  // Field LOG:Lorg/slf4j/Logger;
      24: ldc           #57                 // String Failed to run
      26: aload_2
      27: invokeinterface #58,  3           // InterfaceMethod org/slf4j/Logger.error:(Ljava/lang/String;Ljava/lang/Throwable;)V
      32: iconst_m1
      33: invokestatic  #55                 // Method java/lang/System.exit:(I)V
      36: return
    Exception table:
       from    to  target type
           0    17    20   Class java/lang/Exception

  static {};
    Code:
       0: ldc           #59                 // class org/apache/hadoop/hbase/util/ServerCommandLine
       2: invokestatic  #60                 // Method org/slf4j/LoggerFactory.getLogger:(Ljava/lang/Class;)Lorg/slf4j/Logger;
       5: putstatic     #7                  // Field LOG:Lorg/slf4j/Logger;
       8: new           #61                 // class org/apache/hadoop/hbase/util/ServerCommandLine$1
      11: dup
      12: invokespecial #62                 // Method org/apache/hadoop/hbase/util/ServerCommandLine$1."<init>":()V
      15: putstatic     #34                 // Field DEFAULT_SKIP_WORDS:Ljava/util/Set;
      18: return
}
