Compiled from "ServerRpcConnection.java"
abstract class org.apache.hadoop.hbase.ipc.ServerRpcConnection implements java.io.Closeable {
  protected final org.apache.hadoop.hbase.ipc.RpcServer rpcServer;

  protected boolean connectionHeaderRead;

  protected org.apache.hadoop.hbase.ipc.RpcServer$CallCleanup callCleanup;

  protected java.lang.String hostAddress;

  protected int remotePort;

  protected java.net.InetAddress addr;

  protected org.apache.hadoop.hbase.shaded.protobuf.generated.RPCProtos$ConnectionHeader connectionHeader;

  protected org.apache.hadoop.hbase.codec.Codec codec;

  protected org.apache.hadoop.io.compress.CompressionCodec compressionCodec;

  protected org.apache.hbase.thirdparty.com.google.protobuf.BlockingService service;

  protected org.apache.hadoop.hbase.security.AuthMethod authMethod;

  protected boolean saslContextEstablished;

  protected boolean skipInitialSaslHandshake;

  protected boolean useSasl;

  protected org.apache.hadoop.hbase.security.HBaseSaslRpcServer saslServer;

  protected org.apache.hadoop.hbase.io.crypto.aes.CryptoAES cryptoAES;

  protected boolean useWrap;

  protected boolean useCryptoAesWrap;

  protected boolean authenticatedWithFallback;

  protected boolean retryImmediatelySupported;

  protected org.apache.hadoop.hbase.security.User user;

  protected org.apache.hadoop.security.UserGroupInformation ugi;

  static final boolean $assertionsDisabled;

  public org.apache.hadoop.hbase.ipc.ServerRpcConnection(org.apache.hadoop.hbase.ipc.RpcServer);
    Code:
       0: aload_0
       1: invokespecial #1                  // Method java/lang/Object."<init>":()V
       4: aload_0
       5: iconst_0
       6: putfield      #2                  // Field connectionHeaderRead:Z
       9: aload_0
      10: iconst_4
      11: invokestatic  #3                  // Method java/nio/ByteBuffer.allocate:(I)Ljava/nio/ByteBuffer;
      14: putfield      #4                  // Field unwrappedDataLengthBuffer:Ljava/nio/ByteBuffer;
      17: aload_0
      18: iconst_0
      19: putfield      #5                  // Field useWrap:Z
      22: aload_0
      23: iconst_0
      24: putfield      #6                  // Field useCryptoAesWrap:Z
      27: aload_0
      28: iconst_0
      29: putfield      #7                  // Field retryImmediatelySupported:Z
      32: aload_0
      33: aconst_null
      34: putfield      #8                  // Field user:Lorg/apache/hadoop/hbase/security/User;
      37: aload_0
      38: aconst_null
      39: putfield      #9                  // Field ugi:Lorg/apache/hadoop/security/UserGroupInformation;
      42: aload_0
      43: aload_1
      44: putfield      #10                 // Field rpcServer:Lorg/apache/hadoop/hbase/ipc/RpcServer;
      47: aload_0
      48: aconst_null
      49: putfield      #11                 // Field callCleanup:Lorg/apache/hadoop/hbase/ipc/RpcServer$CallCleanup;
      52: return

  public java.lang.String toString();
    Code:
       0: new           #12                 // class java/lang/StringBuilder
       3: dup
       4: invokespecial #13                 // Method java/lang/StringBuilder."<init>":()V
       7: aload_0
       8: invokevirtual #14                 // Method getHostAddress:()Ljava/lang/String;
      11: invokevirtual #15                 // Method java/lang/StringBuilder.append:(Ljava/lang/String;)Ljava/lang/StringBuilder;
      14: ldc           #16                 // String :
      16: invokevirtual #15                 // Method java/lang/StringBuilder.append:(Ljava/lang/String;)Ljava/lang/StringBuilder;
      19: aload_0
      20: getfield      #17                 // Field remotePort:I
      23: invokevirtual #18                 // Method java/lang/StringBuilder.append:(I)Ljava/lang/StringBuilder;
      26: invokevirtual #19                 // Method java/lang/StringBuilder.toString:()Ljava/lang/String;
      29: areturn

  public java.lang.String getHostAddress();
    Code:
       0: aload_0
       1: getfield      #20                 // Field hostAddress:Ljava/lang/String;
       4: areturn

  public java.net.InetAddress getHostInetAddress();
    Code:
       0: aload_0
       1: getfield      #21                 // Field addr:Ljava/net/InetAddress;
       4: areturn

  public int getRemotePort();
    Code:
       0: aload_0
       1: getfield      #17                 // Field remotePort:I
       4: ireturn

  public org.apache.hadoop.hbase.shaded.protobuf.generated.HBaseProtos$VersionInfo getVersionInfo();
    Code:
       0: aload_0
       1: getfield      #22                 // Field connectionHeader:Lorg/apache/hadoop/hbase/shaded/protobuf/generated/RPCProtos$ConnectionHeader;
       4: invokevirtual #23                 // Method org/apache/hadoop/hbase/shaded/protobuf/generated/RPCProtos$ConnectionHeader.hasVersionInfo:()Z
       7: ifeq          18
      10: aload_0
      11: getfield      #22                 // Field connectionHeader:Lorg/apache/hadoop/hbase/shaded/protobuf/generated/RPCProtos$ConnectionHeader;
      14: invokevirtual #24                 // Method org/apache/hadoop/hbase/shaded/protobuf/generated/RPCProtos$ConnectionHeader.getVersionInfo:()Lorg/apache/hadoop/hbase/shaded/protobuf/generated/HBaseProtos$VersionInfo;
      17: areturn
      18: aconst_null
      19: areturn

  protected final void disposeSasl();
    Code:
       0: aload_0
       1: getfield      #64                 // Field saslServer:Lorg/apache/hadoop/hbase/security/HBaseSaslRpcServer;
       4: ifnull        19
       7: aload_0
       8: getfield      #64                 // Field saslServer:Lorg/apache/hadoop/hbase/security/HBaseSaslRpcServer;
      11: invokevirtual #118                // Method org/apache/hadoop/hbase/security/HBaseSaslRpcServer.dispose:()V
      14: aload_0
      15: aconst_null
      16: putfield      #64                 // Field saslServer:Lorg/apache/hadoop/hbase/security/HBaseSaslRpcServer;
      19: return

  protected final void doRawSaslReply(org.apache.hadoop.hbase.security.SaslStatus, org.apache.hadoop.io.Writable, java.lang.String, java.lang.String) throws java.io.IOException;
    Code:
       0: new           #119                // class org/apache/hadoop/hbase/io/ByteBufferOutputStream
       3: dup
       4: sipush        256
       7: invokespecial #120                // Method org/apache/hadoop/hbase/io/ByteBufferOutputStream."<init>":(I)V
      10: astore        6
      12: aconst_null
      13: astore        7
      15: new           #121                // class java/io/DataOutputStream
      18: dup
      19: aload         6
      21: invokespecial #122                // Method java/io/DataOutputStream."<init>":(Ljava/io/OutputStream;)V
      24: astore        8
      26: aconst_null
      27: astore        9
      29: aload         8
      31: aload_1
      32: getfield      #123                // Field org/apache/hadoop/hbase/security/SaslStatus.state:I
      35: invokevirtual #124                // Method java/io/DataOutputStream.writeInt:(I)V
      38: aload_1
      39: getstatic     #125                // Field org/apache/hadoop/hbase/security/SaslStatus.SUCCESS:Lorg/apache/hadoop/hbase/security/SaslStatus;
      42: if_acmpne     56
      45: aload_2
      46: aload         8
      48: invokeinterface #126,  2          // InterfaceMethod org/apache/hadoop/io/Writable.write:(Ljava/io/DataOutput;)V
      53: goto          69
      56: aload         8
      58: aload_3
      59: invokestatic  #127                // Method org/apache/hadoop/io/WritableUtils.writeString:(Ljava/io/DataOutput;Ljava/lang/String;)V
      62: aload         8
      64: aload         4
      66: invokestatic  #127                // Method org/apache/hadoop/io/WritableUtils.writeString:(Ljava/io/DataOutput;Ljava/lang/String;)V
      69: new           #128                // class org/apache/hadoop/hbase/ipc/BufferChain
      72: dup
      73: iconst_1
      74: anewarray     #129                // class java/nio/ByteBuffer
      77: dup
      78: iconst_0
      79: aload         6
      81: invokevirtual #130                // Method org/apache/hadoop/hbase/io/ByteBufferOutputStream.getByteBuffer:()Ljava/nio/ByteBuffer;
      84: aastore
      85: invokespecial #131                // Method org/apache/hadoop/hbase/ipc/BufferChain."<init>":([Ljava/nio/ByteBuffer;)V
      88: astore        5
      90: aload         8
      92: ifnull        177
      95: aload         9
      97: ifnull        120
     100: aload         8
     102: invokevirtual #132                // Method java/io/DataOutputStream.close:()V
     105: goto          177
     108: astore        10
     110: aload         9
     112: aload         10
     114: invokevirtual #134                // Method java/lang/Throwable.addSuppressed:(Ljava/lang/Throwable;)V
     117: goto          177
     120: aload         8
     122: invokevirtual #132                // Method java/io/DataOutputStream.close:()V
     125: goto          177
     128: astore        10
     130: aload         10
     132: astore        9
     134: aload         10
     136: athrow
     137: astore        11
     139: aload         8
     141: ifnull        174
     144: aload         9
     146: ifnull        169
     149: aload         8
     151: invokevirtual #132                // Method java/io/DataOutputStream.close:()V
     154: goto          174
     157: astore        12
     159: aload         9
     161: aload         12
     163: invokevirtual #134                // Method java/lang/Throwable.addSuppressed:(Ljava/lang/Throwable;)V
     166: goto          174
     169: aload         8
     171: invokevirtual #132                // Method java/io/DataOutputStream.close:()V
     174: aload         11
     176: athrow
     177: aload         6
     179: ifnull        264
     182: aload         7
     184: ifnull        207
     187: aload         6
     189: invokevirtual #135                // Method org/apache/hadoop/hbase/io/ByteBufferOutputStream.close:()V
     192: goto          264
     195: astore        8
     197: aload         7
     199: aload         8
     201: invokevirtual #134                // Method java/lang/Throwable.addSuppressed:(Ljava/lang/Throwable;)V
     204: goto          264
     207: aload         6
     209: invokevirtual #135                // Method org/apache/hadoop/hbase/io/ByteBufferOutputStream.close:()V
     212: goto          264
     215: astore        8
     217: aload         8
     219: astore        7
     221: aload         8
     223: athrow
     224: astore        13
     226: aload         6
     228: ifnull        261
     231: aload         7
     233: ifnull        256
     236: aload         6
     238: invokevirtual #135                // Method org/apache/hadoop/hbase/io/ByteBufferOutputStream.close:()V
     241: goto          261
     244: astore        14
     246: aload         7
     248: aload         14
     250: invokevirtual #134                // Method java/lang/Throwable.addSuppressed:(Ljava/lang/Throwable;)V
     253: goto          261
     256: aload         6
     258: invokevirtual #135                // Method org/apache/hadoop/hbase/io/ByteBufferOutputStream.close:()V
     261: aload         13
     263: athrow
     264: aload_0
     265: aload         5
     267: invokedynamic #136,  0            // InvokeDynamic #0:getResponse:(Lorg/apache/hadoop/hbase/ipc/BufferChain;)Lorg/apache/hadoop/hbase/ipc/RpcResponse;
     272: invokevirtual #137                // Method doRespond:(Lorg/apache/hadoop/hbase/ipc/RpcResponse;)V
     275: return
    Exception table:
       from    to  target type
         100   105   108   Class java/lang/Throwable
          29    90   128   Class java/lang/Throwable
          29    90   137   any
         149   154   157   Class java/lang/Throwable
         128   139   137   any
         187   192   195   Class java/lang/Throwable
          15   177   215   Class java/lang/Throwable
          15   177   224   any
         236   241   244   Class java/lang/Throwable
         215   226   224   any

  public void saslReadAndProcess(org.apache.hadoop.hbase.nio.ByteBuff) throws java.io.IOException, java.lang.InterruptedException;
    Code:
       0: aload_0
       1: getfield      #138                // Field saslContextEstablished:Z
       4: ifeq          100
       7: getstatic     #139                // Field org/apache/hadoop/hbase/ipc/RpcServer.LOG:Lorg/slf4j/Logger;
      10: ldc           #140                // String Read input token of size={} for processing by saslServer.unwrap()
      12: aload_1
      13: invokevirtual #141                // Method org/apache/hadoop/hbase/nio/ByteBuff.limit:()I
      16: invokestatic  #142                // Method java/lang/Integer.valueOf:(I)Ljava/lang/Integer;
      19: invokeinterface #143,  3          // InterfaceMethod org/slf4j/Logger.trace:(Ljava/lang/String;Ljava/lang/Object;)V
      24: aload_0
      25: getfield      #5                  // Field useWrap:Z
      28: ifne          39
      31: aload_0
      32: aload_1
      33: invokevirtual #144                // Method processOneRpc:(Lorg/apache/hadoop/hbase/nio/ByteBuff;)V
      36: goto          536
      39: aload_1
      40: invokevirtual #145                // Method org/apache/hadoop/hbase/nio/ByteBuff.hasArray:()Z
      43: ifeq          53
      46: aload_1
      47: invokevirtual #146                // Method org/apache/hadoop/hbase/nio/ByteBuff.array:()[B
      50: goto          57
      53: aload_1
      54: invokevirtual #147                // Method org/apache/hadoop/hbase/nio/ByteBuff.toBytes:()[B
      57: astore_2
      58: aload_0
      59: getfield      #6                  // Field useCryptoAesWrap:Z
      62: ifeq          80
      65: aload_0
      66: getfield      #95                 // Field cryptoAES:Lorg/apache/hadoop/hbase/io/crypto/aes/CryptoAES;
      69: aload_2
      70: iconst_0
      71: aload_2
      72: arraylength
      73: invokevirtual #148                // Method org/apache/hadoop/hbase/io/crypto/aes/CryptoAES.unwrap:([BII)[B
      76: astore_3
      77: goto          92
      80: aload_0
      81: getfield      #64                 // Field saslServer:Lorg/apache/hadoop/hbase/security/HBaseSaslRpcServer;
      84: aload_2
      85: iconst_0
      86: aload_2
      87: arraylength
      88: invokevirtual #149                // Method org/apache/hadoop/hbase/security/HBaseSaslRpcServer.unwrap:([BII)[B
      91: astore_3
      92: aload_0
      93: aload_3
      94: invokespecial #150                // Method processUnwrappedData:([B)V
      97: goto          536
     100: aload_0
     101: getfield      #64                 // Field saslServer:Lorg/apache/hadoop/hbase/security/HBaseSaslRpcServer;
     104: ifnonnull     153
     107: aload_0
     108: new           #151                // class org/apache/hadoop/hbase/security/HBaseSaslRpcServer
     111: dup
     112: aload_0
     113: getfield      #29                 // Field authMethod:Lorg/apache/hadoop/hbase/security/AuthMethod;
     116: aload_0
     117: getfield      #10                 // Field rpcServer:Lorg/apache/hadoop/hbase/ipc/RpcServer;
     120: getfield      #152                // Field org/apache/hadoop/hbase/ipc/RpcServer.saslProps:Ljava/util/Map;
     123: aload_0
     124: getfield      #10                 // Field rpcServer:Lorg/apache/hadoop/hbase/ipc/RpcServer;
     127: getfield      #34                 // Field org/apache/hadoop/hbase/ipc/RpcServer.secretManager:Lorg/apache/hadoop/security/token/SecretManager;
     130: invokespecial #153                // Method org/apache/hadoop/hbase/security/HBaseSaslRpcServer."<init>":(Lorg/apache/hadoop/hbase/security/AuthMethod;Ljava/util/Map;Lorg/apache/hadoop/security/token/SecretManager;)V
     133: putfield      #64                 // Field saslServer:Lorg/apache/hadoop/hbase/security/HBaseSaslRpcServer;
     136: getstatic     #139                // Field org/apache/hadoop/hbase/ipc/RpcServer.LOG:Lorg/slf4j/Logger;
     139: ldc           #154                // String Created SASL server with mechanism={}
     141: aload_0
     142: getfield      #29                 // Field authMethod:Lorg/apache/hadoop/hbase/security/AuthMethod;
     145: invokevirtual #155                // Method org/apache/hadoop/hbase/security/AuthMethod.getMechanismName:()Ljava/lang/String;
     148: invokeinterface #156,  3          // InterfaceMethod org/slf4j/Logger.debug:(Ljava/lang/String;Ljava/lang/Object;)V
     153: getstatic     #139                // Field org/apache/hadoop/hbase/ipc/RpcServer.LOG:Lorg/slf4j/Logger;
     156: ldc           #157                // String Read input token of size={} for processing by saslServer.evaluateResponse()
     158: aload_1
     159: invokevirtual #141                // Method org/apache/hadoop/hbase/nio/ByteBuff.limit:()I
     162: invokestatic  #142                // Method java/lang/Integer.valueOf:(I)Ljava/lang/Integer;
     165: invokeinterface #156,  3          // InterfaceMethod org/slf4j/Logger.debug:(Ljava/lang/String;Ljava/lang/Object;)V
     170: aload_0
     171: getfield      #64                 // Field saslServer:Lorg/apache/hadoop/hbase/security/HBaseSaslRpcServer;
     174: aload_1
     175: invokevirtual #145                // Method org/apache/hadoop/hbase/nio/ByteBuff.hasArray:()Z
     178: ifeq          188
     181: aload_1
     182: invokevirtual #146                // Method org/apache/hadoop/hbase/nio/ByteBuff.array:()[B
     185: goto          192
     188: aload_1
     189: invokevirtual #147                // Method org/apache/hadoop/hbase/nio/ByteBuff.toBytes:()[B
     192: invokevirtual #158                // Method org/apache/hadoop/hbase/security/HBaseSaslRpcServer.evaluateResponse:([B)[B
     195: astore_2
     196: goto          321
     199: astore_3
     200: aload_3
     201: astore        4
     203: aload_3
     204: astore        5
     206: aload         5
     208: ifnull        239
     211: aload         5
     213: instanceof    #159                // class org/apache/hadoop/security/token/SecretManager$InvalidToken
     216: ifeq          229
     219: aload         5
     221: checkcast     #159                // class org/apache/hadoop/security/token/SecretManager$InvalidToken
     224: astore        4
     226: goto          239
     229: aload         5
     231: invokevirtual #160                // Method java/lang/Throwable.getCause:()Ljava/lang/Throwable;
     234: astore        5
     236: goto          206
     239: aload_0
     240: getstatic     #161                // Field org/apache/hadoop/hbase/security/SaslStatus.ERROR:Lorg/apache/hadoop/hbase/security/SaslStatus;
     243: aconst_null
     244: aload         4
     246: invokevirtual #162                // Method java/lang/Object.getClass:()Ljava/lang/Class;
     249: invokevirtual #163                // Method java/lang/Class.getName:()Ljava/lang/String;
     252: aload         4
     254: invokevirtual #164                // Method java/io/IOException.getLocalizedMessage:()Ljava/lang/String;
     257: invokevirtual #165                // Method doRawSaslReply:(Lorg/apache/hadoop/hbase/security/SaslStatus;Lorg/apache/hadoop/io/Writable;Ljava/lang/String;Ljava/lang/String;)V
     260: aload_0
     261: getfield      #10                 // Field rpcServer:Lorg/apache/hadoop/hbase/ipc/RpcServer;
     264: getfield      #166                // Field org/apache/hadoop/hbase/ipc/RpcServer.metrics:Lorg/apache/hadoop/hbase/ipc/MetricsHBaseServer;
     267: invokevirtual #167                // Method org/apache/hadoop/hbase/ipc/MetricsHBaseServer.authenticationFailure:()V
     270: aload_0
     271: invokevirtual #32                 // Method toString:()Ljava/lang/String;
     274: astore        6
     276: getstatic     #168                // Field org/apache/hadoop/hbase/ipc/RpcServer.AUDITLOG:Lorg/slf4j/Logger;
     279: new           #12                 // class java/lang/StringBuilder
     282: dup
     283: invokespecial #13                 // Method java/lang/StringBuilder."<init>":()V
     286: ldc           #169                // String Auth failed for
     288: invokevirtual #15                 // Method java/lang/StringBuilder.append:(Ljava/lang/String;)Ljava/lang/StringBuilder;
     291: aload         6
     293: invokevirtual #15                 // Method java/lang/StringBuilder.append:(Ljava/lang/String;)Ljava/lang/StringBuilder;
     296: ldc           #16                 // String :
     298: invokevirtual #15                 // Method java/lang/StringBuilder.append:(Ljava/lang/String;)Ljava/lang/StringBuilder;
     301: aload_0
     302: getfield      #64                 // Field saslServer:Lorg/apache/hadoop/hbase/security/HBaseSaslRpcServer;
     305: invokevirtual #170                // Method org/apache/hadoop/hbase/security/HBaseSaslRpcServer.getAttemptingUser:()Lorg/apache/hadoop/security/UserGroupInformation;
     308: invokevirtual #171                // Method java/lang/StringBuilder.append:(Ljava/lang/Object;)Ljava/lang/StringBuilder;
     311: invokevirtual #19                 // Method java/lang/StringBuilder.toString:()Ljava/lang/String;
     314: invokeinterface #172,  2          // InterfaceMethod org/slf4j/Logger.warn:(Ljava/lang/String;)V
     319: aload_3
     320: athrow
     321: aload_2
     322: ifnull        386
     325: getstatic     #139                // Field org/apache/hadoop/hbase/ipc/RpcServer.LOG:Lorg/slf4j/Logger;
     328: invokeinterface #173,  1          // InterfaceMethod org/slf4j/Logger.isDebugEnabled:()Z
     333: ifeq          369
     336: getstatic     #139                // Field org/apache/hadoop/hbase/ipc/RpcServer.LOG:Lorg/slf4j/Logger;
     339: new           #12                 // class java/lang/StringBuilder
     342: dup
     343: invokespecial #13                 // Method java/lang/StringBuilder."<init>":()V
     346: ldc           #174                // String Will send token of size
     348: invokevirtual #15                 // Method java/lang/StringBuilder.append:(Ljava/lang/String;)Ljava/lang/StringBuilder;
     351: aload_2
     352: arraylength
     353: invokevirtual #18                 // Method java/lang/StringBuilder.append:(I)Ljava/lang/StringBuilder;
     356: ldc           #175                // String  from saslServer.
     358: invokevirtual #15                 // Method java/lang/StringBuilder.append:(Ljava/lang/String;)Ljava/lang/StringBuilder;
     361: invokevirtual #19                 // Method java/lang/StringBuilder.toString:()Ljava/lang/String;
     364: invokeinterface #176,  2          // InterfaceMethod org/slf4j/Logger.debug:(Ljava/lang/String;)V
     369: aload_0
     370: getstatic     #125                // Field org/apache/hadoop/hbase/security/SaslStatus.SUCCESS:Lorg/apache/hadoop/hbase/security/SaslStatus;
     373: new           #177                // class org/apache/hadoop/io/BytesWritable
     376: dup
     377: aload_2
     378: invokespecial #178                // Method org/apache/hadoop/io/BytesWritable."<init>":([B)V
     381: aconst_null
     382: aconst_null
     383: invokevirtual #165                // Method doRawSaslReply:(Lorg/apache/hadoop/hbase/security/SaslStatus;Lorg/apache/hadoop/io/Writable;Ljava/lang/String;Ljava/lang/String;)V
     386: aload_0
     387: getfield      #64                 // Field saslServer:Lorg/apache/hadoop/hbase/security/HBaseSaslRpcServer;
     390: invokevirtual #179                // Method org/apache/hadoop/hbase/security/HBaseSaslRpcServer.isComplete:()Z
     393: ifeq          536
     396: aload_0
     397: getfield      #64                 // Field saslServer:Lorg/apache/hadoop/hbase/security/HBaseSaslRpcServer;
     400: invokevirtual #65                 // Method org/apache/hadoop/hbase/security/HBaseSaslRpcServer.getNegotiatedQop:()Ljava/lang/String;
     403: astore_3
     404: aload_0
     405: aload_3
     406: ifnull        422
     409: ldc           #180                // String auth
     411: aload_3
     412: invokevirtual #68                 // Method java/lang/String.equalsIgnoreCase:(Ljava/lang/String;)Z
     415: ifne          422
     418: iconst_1
     419: goto          423
     422: iconst_0
     423: putfield      #5                  // Field useWrap:Z
     426: aload_0
     427: aload_0
     428: aload_0
     429: getfield      #64                 // Field saslServer:Lorg/apache/hadoop/hbase/security/HBaseSaslRpcServer;
     432: invokevirtual #181                // Method org/apache/hadoop/hbase/security/HBaseSaslRpcServer.getAuthorizationID:()Ljava/lang/String;
     435: invokespecial #182                // Method getAuthorizedUgi:(Ljava/lang/String;)Lorg/apache/hadoop/security/UserGroupInformation;
     438: putfield      #9                  // Field ugi:Lorg/apache/hadoop/security/UserGroupInformation;
     441: getstatic     #139                // Field org/apache/hadoop/hbase/ipc/RpcServer.LOG:Lorg/slf4j/Logger;
     444: invokeinterface #173,  1          // InterfaceMethod org/slf4j/Logger.isDebugEnabled:()Z
     449: ifeq          491
     452: getstatic     #139                // Field org/apache/hadoop/hbase/ipc/RpcServer.LOG:Lorg/slf4j/Logger;
     455: new           #12                 // class java/lang/StringBuilder
     458: dup
     459: invokespecial #13                 // Method java/lang/StringBuilder."<init>":()V
     462: ldc           #183                // String SASL server context established. Authenticated client:
     464: invokevirtual #15                 // Method java/lang/StringBuilder.append:(Ljava/lang/String;)Ljava/lang/StringBuilder;
     467: aload_0
     468: getfield      #9                  // Field ugi:Lorg/apache/hadoop/security/UserGroupInformation;
     471: invokevirtual #171                // Method java/lang/StringBuilder.append:(Ljava/lang/Object;)Ljava/lang/StringBuilder;
     474: ldc           #184                // String . Negotiated QoP is
     476: invokevirtual #15                 // Method java/lang/StringBuilder.append:(Ljava/lang/String;)Ljava/lang/StringBuilder;
     479: aload_3
     480: invokevirtual #15                 // Method java/lang/StringBuilder.append:(Ljava/lang/String;)Ljava/lang/StringBuilder;
     483: invokevirtual #19                 // Method java/lang/StringBuilder.toString:()Ljava/lang/String;
     486: invokeinterface #176,  2          // InterfaceMethod org/slf4j/Logger.debug:(Ljava/lang/String;)V
     491: aload_0
     492: getfield      #10                 // Field rpcServer:Lorg/apache/hadoop/hbase/ipc/RpcServer;
     495: getfield      #166                // Field org/apache/hadoop/hbase/ipc/RpcServer.metrics:Lorg/apache/hadoop/hbase/ipc/MetricsHBaseServer;
     498: invokevirtual #185                // Method org/apache/hadoop/hbase/ipc/MetricsHBaseServer.authenticationSuccess:()V
     501: getstatic     #168                // Field org/apache/hadoop/hbase/ipc/RpcServer.AUDITLOG:Lorg/slf4j/Logger;
     504: new           #12                 // class java/lang/StringBuilder
     507: dup
     508: invokespecial #13                 // Method java/lang/StringBuilder."<init>":()V
     511: ldc           #186                // String Auth successful for
     513: invokevirtual #15                 // Method java/lang/StringBuilder.append:(Ljava/lang/String;)Ljava/lang/StringBuilder;
     516: aload_0
     517: getfield      #9                  // Field ugi:Lorg/apache/hadoop/security/UserGroupInformation;
     520: invokevirtual #171                // Method java/lang/StringBuilder.append:(Ljava/lang/Object;)Ljava/lang/StringBuilder;
     523: invokevirtual #19                 // Method java/lang/StringBuilder.toString:()Ljava/lang/String;
     526: invokeinterface #187,  2          // InterfaceMethod org/slf4j/Logger.info:(Ljava/lang/String;)V
     531: aload_0
     532: iconst_1
     533: putfield      #138                // Field saslContextEstablished:Z
     536: return
    Exception table:
       from    to  target type
         100   196   199   Class java/io/IOException

  public void processOneRpc(org.apache.hadoop.hbase.nio.ByteBuff) throws java.io.IOException, java.lang.InterruptedException;
    Code:
       0: aload_0
       1: getfield      #2                  // Field connectionHeaderRead:Z
       4: ifeq          15
       7: aload_0
       8: aload_1
       9: invokevirtual #201                // Method processRequest:(Lorg/apache/hadoop/hbase/nio/ByteBuff;)V
      12: goto          104
      15: aload_0
      16: aload_1
      17: invokespecial #202                // Method processConnectionHeader:(Lorg/apache/hadoop/hbase/nio/ByteBuff;)V
      20: aload_0
      21: iconst_1
      22: putfield      #2                  // Field connectionHeaderRead:Z
      25: aload_0
      26: invokespecial #203                // Method authorizeConnection:()Z
      29: ifne          86
      32: new           #37                 // class org/apache/hadoop/hbase/security/AccessDeniedException
      35: dup
      36: new           #12                 // class java/lang/StringBuilder
      39: dup
      40: invokespecial #13                 // Method java/lang/StringBuilder."<init>":()V
      43: ldc           #204                // String Connection from
      45: invokevirtual #15                 // Method java/lang/StringBuilder.append:(Ljava/lang/String;)Ljava/lang/StringBuilder;
      48: aload_0
      49: invokevirtual #171                // Method java/lang/StringBuilder.append:(Ljava/lang/Object;)Ljava/lang/StringBuilder;
      52: ldc           #205                // String  for service
      54: invokevirtual #15                 // Method java/lang/StringBuilder.append:(Ljava/lang/String;)Ljava/lang/StringBuilder;
      57: aload_0
      58: getfield      #22                 // Field connectionHeader:Lorg/apache/hadoop/hbase/shaded/protobuf/generated/RPCProtos$ConnectionHeader;
      61: invokevirtual #206                // Method org/apache/hadoop/hbase/shaded/protobuf/generated/RPCProtos$ConnectionHeader.getServiceName:()Ljava/lang/String;
      64: invokevirtual #15                 // Method java/lang/StringBuilder.append:(Ljava/lang/String;)Ljava/lang/StringBuilder;
      67: ldc           #207                // String  is unauthorized for user:
      69: invokevirtual #15                 // Method java/lang/StringBuilder.append:(Ljava/lang/String;)Ljava/lang/StringBuilder;
      72: aload_0
      73: getfield      #9                  // Field ugi:Lorg/apache/hadoop/security/UserGroupInformation;
      76: invokevirtual #171                // Method java/lang/StringBuilder.append:(Ljava/lang/Object;)Ljava/lang/StringBuilder;
      79: invokevirtual #19                 // Method java/lang/StringBuilder.toString:()Ljava/lang/String;
      82: invokespecial #39                 // Method org/apache/hadoop/hbase/security/AccessDeniedException."<init>":(Ljava/lang/String;)V
      85: athrow
      86: aload_0
      87: aload_0
      88: getfield      #10                 // Field rpcServer:Lorg/apache/hadoop/hbase/ipc/RpcServer;
      91: getfield      #208                // Field org/apache/hadoop/hbase/ipc/RpcServer.userProvider:Lorg/apache/hadoop/hbase/security/UserProvider;
      94: aload_0
      95: getfield      #9                  // Field ugi:Lorg/apache/hadoop/security/UserGroupInformation;
      98: invokevirtual #209                // Method org/apache/hadoop/hbase/security/UserProvider.create:(Lorg/apache/hadoop/security/UserGroupInformation;)Lorg/apache/hadoop/hbase/security/User;
     101: putfield      #8                  // Field user:Lorg/apache/hadoop/hbase/security/User;
     104: return

  protected abstract void doRespond(org.apache.hadoop.hbase.ipc.RpcResponse) throws java.io.IOException;

  protected void processRequest(org.apache.hadoop.hbase.nio.ByteBuff) throws java.io.IOException, java.lang.InterruptedException;
    Code:
       0: aload_1
       1: invokevirtual #141                // Method org/apache/hadoop/hbase/nio/ByteBuff.limit:()I
       4: i2l
       5: lstore_2
       6: iconst_0
       7: istore        4
       9: aload_1
      10: invokevirtual #145                // Method org/apache/hadoop/hbase/nio/ByteBuff.hasArray:()Z
      13: ifeq          36
      16: aload_1
      17: invokevirtual #146                // Method org/apache/hadoop/hbase/nio/ByteBuff.array:()[B
      20: iconst_0
      21: aload_1
      22: invokevirtual #141                // Method org/apache/hadoop/hbase/nio/ByteBuff.limit:()I
      25: invokestatic  #269                // Method org/apache/hbase/thirdparty/com/google/protobuf/UnsafeByteOperations.unsafeWrap:([BII)Lorg/apache/hbase/thirdparty/com/google/protobuf/ByteString;
      28: invokevirtual #226                // Method org/apache/hbase/thirdparty/com/google/protobuf/ByteString.newCodedInput:()Lorg/apache/hbase/thirdparty/com/google/protobuf/CodedInputStream;
      31: astore        5
      33: goto          62
      36: new           #223                // class org/apache/hadoop/hbase/ipc/ServerRpcConnection$ByteBuffByteInput
      39: dup
      40: aload_1
      41: iconst_0
      42: aload_1
      43: invokevirtual #141                // Method org/apache/hadoop/hbase/nio/ByteBuff.limit:()I
      46: invokespecial #224                // Method org/apache/hadoop/hbase/ipc/ServerRpcConnection$ByteBuffByteInput."<init>":(Lorg/apache/hadoop/hbase/nio/ByteBuff;II)V
      49: iconst_0
      50: aload_1
      51: invokevirtual #141                // Method org/apache/hadoop/hbase/nio/ByteBuff.limit:()I
      54: invokestatic  #225                // Method org/apache/hbase/thirdparty/com/google/protobuf/UnsafeByteOperations.unsafeWrap:(Lorg/apache/hbase/thirdparty/com/google/protobuf/ByteInput;II)Lorg/apache/hbase/thirdparty/com/google/protobuf/ByteString;
      57: invokevirtual #226                // Method org/apache/hbase/thirdparty/com/google/protobuf/ByteString.newCodedInput:()Lorg/apache/hbase/thirdparty/com/google/protobuf/CodedInputStream;
      60: astore        5
      62: aload         5
      64: iconst_1
      65: invokevirtual #227                // Method org/apache/hbase/thirdparty/com/google/protobuf/CodedInputStream.enableAliasing:(Z)V
      68: aload         5
      70: invokevirtual #270                // Method org/apache/hbase/thirdparty/com/google/protobuf/CodedInputStream.readRawVarint32:()I
      73: istore        6
      75: aload         5
      77: invokevirtual #271                // Method org/apache/hbase/thirdparty/com/google/protobuf/CodedInputStream.getTotalBytesRead:()I
      80: istore        4
      82: invokestatic  #272                // Method org/apache/hadoop/hbase/shaded/protobuf/generated/RPCProtos$RequestHeader.newBuilder:()Lorg/apache/hadoop/hbase/shaded/protobuf/generated/RPCProtos$RequestHeader$Builder;
      85: astore        7
      87: aload         7
      89: aload         5
      91: iload         6
      93: invokestatic  #273                // Method org/apache/hadoop/hbase/shaded/protobuf/ProtobufUtil.mergeFrom:(Lorg/apache/hbase/thirdparty/com/google/protobuf/Message$Builder;Lorg/apache/hbase/thirdparty/com/google/protobuf/CodedInputStream;I)V
      96: aload         7
      98: invokeinterface #274,  1          // InterfaceMethod org/apache/hbase/thirdparty/com/google/protobuf/Message$Builder.build:()Lorg/apache/hbase/thirdparty/com/google/protobuf/Message;
     103: checkcast     #275                // class org/apache/hadoop/hbase/shaded/protobuf/generated/RPCProtos$RequestHeader
     106: astore        8
     108: iload         4
     110: iload         6
     112: iadd
     113: istore        4
     115: aload         8
     117: invokevirtual #276                // Method org/apache/hadoop/hbase/shaded/protobuf/generated/RPCProtos$RequestHeader.getCallId:()I
     120: istore        9
     122: getstatic     #139                // Field org/apache/hadoop/hbase/ipc/RpcServer.LOG:Lorg/slf4j/Logger;
     125: invokeinterface #277,  1          // InterfaceMethod org/slf4j/Logger.isTraceEnabled:()Z
     130: ifeq          181
     133: getstatic     #139                // Field org/apache/hadoop/hbase/ipc/RpcServer.LOG:Lorg/slf4j/Logger;
     136: new           #12                 // class java/lang/StringBuilder
     139: dup
     140: invokespecial #13                 // Method java/lang/StringBuilder."<init>":()V
     143: ldc_w         #278                // String RequestHeader
     146: invokevirtual #15                 // Method java/lang/StringBuilder.append:(Ljava/lang/String;)Ljava/lang/StringBuilder;
     149: aload         8
     151: invokestatic  #279                // Method org/apache/hbase/thirdparty/com/google/protobuf/TextFormat.shortDebugString:(Lorg/apache/hbase/thirdparty/com/google/protobuf/MessageOrBuilder;)Ljava/lang/String;
     154: invokevirtual #15                 // Method java/lang/StringBuilder.append:(Ljava/lang/String;)Ljava/lang/StringBuilder;
     157: ldc_w         #280                // String  totalRequestSize:
     160: invokevirtual #15                 // Method java/lang/StringBuilder.append:(Ljava/lang/String;)Ljava/lang/StringBuilder;
     163: lload_2
     164: invokevirtual #281                // Method java/lang/StringBuilder.append:(J)Ljava/lang/StringBuilder;
     167: ldc_w         #282                // String  bytes
     170: invokevirtual #15                 // Method java/lang/StringBuilder.append:(Ljava/lang/String;)Ljava/lang/StringBuilder;
     173: invokevirtual #19                 // Method java/lang/StringBuilder.toString:()Ljava/lang/String;
     176: invokeinterface #283,  2          // InterfaceMethod org/slf4j/Logger.trace:(Ljava/lang/String;)V
     181: lload_2
     182: aload_0
     183: getfield      #10                 // Field rpcServer:Lorg/apache/hadoop/hbase/ipc/RpcServer;
     186: getfield      #284                // Field org/apache/hadoop/hbase/ipc/RpcServer.callQueueSizeInBytes:Ljava/util/concurrent/atomic/LongAdder;
     189: invokevirtual #285                // Method java/util/concurrent/atomic/LongAdder.sum:()J
     192: ladd
     193: aload_0
     194: getfield      #10                 // Field rpcServer:Lorg/apache/hadoop/hbase/ipc/RpcServer;
     197: getfield      #286                // Field org/apache/hadoop/hbase/ipc/RpcServer.maxQueueSizeInBytes:J
     200: lcmp
     201: ifle          293
     204: aload_0
     205: iload         9
     207: aload_0
     208: getfield      #233                // Field service:Lorg/apache/hbase/thirdparty/com/google/protobuf/BlockingService;
     211: aconst_null
     212: aconst_null
     213: aconst_null
     214: aconst_null
     215: lload_2
     216: aconst_null
     217: iconst_0
     218: aload_0
     219: getfield      #11                 // Field callCleanup:Lorg/apache/hadoop/hbase/ipc/RpcServer$CallCleanup;
     222: invokevirtual #287                // Method createCall:(ILorg/apache/hbase/thirdparty/com/google/protobuf/BlockingService;Lorg/apache/hbase/thirdparty/com/google/protobuf/Descriptors$MethodDescriptor;Lorg/apache/hadoop/hbase/shaded/protobuf/generated/RPCProtos$RequestHeader;Lorg/apache/hbase/thirdparty/com/google/protobuf/Message;Lorg/apache/hadoop/hbase/CellScanner;JLjava/net/InetAddress;ILorg/apache/hadoop/hbase/ipc/RpcServer$CallCleanup;)Lorg/apache/hadoop/hbase/ipc/ServerCall;
     225: astore        10
     227: aload_0
     228: getfield      #10                 // Field rpcServer:Lorg/apache/hadoop/hbase/ipc/RpcServer;
     231: getfield      #166                // Field org/apache/hadoop/hbase/ipc/RpcServer.metrics:Lorg/apache/hadoop/hbase/ipc/MetricsHBaseServer;
     234: getstatic     #288                // Field org/apache/hadoop/hbase/ipc/RpcServer.CALL_QUEUE_TOO_BIG_EXCEPTION:Lorg/apache/hadoop/hbase/CallQueueTooBigException;
     237: invokevirtual #289                // Method org/apache/hadoop/hbase/ipc/MetricsHBaseServer.exception:(Ljava/lang/Throwable;)V
     240: aload         10
     242: aconst_null
     243: aconst_null
     244: getstatic     #288                // Field org/apache/hadoop/hbase/ipc/RpcServer.CALL_QUEUE_TOO_BIG_EXCEPTION:Lorg/apache/hadoop/hbase/CallQueueTooBigException;
     247: new           #12                 // class java/lang/StringBuilder
     250: dup
     251: invokespecial #13                 // Method java/lang/StringBuilder."<init>":()V
     254: ldc_w         #290                // String Call queue is full on
     257: invokevirtual #15                 // Method java/lang/StringBuilder.append:(Ljava/lang/String;)Ljava/lang/StringBuilder;
     260: aload_0
     261: getfield      #10                 // Field rpcServer:Lorg/apache/hadoop/hbase/ipc/RpcServer;
     264: getfield      #291                // Field org/apache/hadoop/hbase/ipc/RpcServer.server:Lorg/apache/hadoop/hbase/Server;
     267: invokeinterface #292,  1          // InterfaceMethod org/apache/hadoop/hbase/Server.getServerName:()Lorg/apache/hadoop/hbase/ServerName;
     272: invokevirtual #171                // Method java/lang/StringBuilder.append:(Ljava/lang/Object;)Ljava/lang/StringBuilder;
     275: ldc_w         #293                // String , is hbase.ipc.server.max.callqueue.size too small?
     278: invokevirtual #15                 // Method java/lang/StringBuilder.append:(Ljava/lang/String;)Ljava/lang/StringBuilder;
     281: invokevirtual #19                 // Method java/lang/StringBuilder.toString:()Ljava/lang/String;
     284: invokevirtual #294                // Method org/apache/hadoop/hbase/ipc/ServerCall.setResponse:(Lorg/apache/hbase/thirdparty/com/google/protobuf/Message;Lorg/apache/hadoop/hbase/CellScanner;Ljava/lang/Throwable;Ljava/lang/String;)V
     287: aload         10
     289: invokevirtual #295                // Method org/apache/hadoop/hbase/ipc/ServerCall.sendResponseIfReady:()V
     292: return
     293: aconst_null
     294: astore        10
     296: aconst_null
     297: astore        11
     299: aconst_null
     300: astore        12
     302: aload         8
     304: invokevirtual #296                // Method org/apache/hadoop/hbase/shaded/protobuf/generated/RPCProtos$RequestHeader.hasRequestParam:()Z
     307: ifeq          428
     310: aload         8
     312: invokevirtual #297                // Method org/apache/hadoop/hbase/shaded/protobuf/generated/RPCProtos$RequestHeader.getRequestParam:()Z
     315: ifeq          428
     318: aload_0
     319: getfield      #233                // Field service:Lorg/apache/hbase/thirdparty/com/google/protobuf/BlockingService;
     322: invokeinterface #298,  1          // InterfaceMethod org/apache/hbase/thirdparty/com/google/protobuf/BlockingService.getDescriptorForType:()Lorg/apache/hbase/thirdparty/com/google/protobuf/Descriptors$ServiceDescriptor;
     327: aload         8
     329: invokevirtual #299                // Method org/apache/hadoop/hbase/shaded/protobuf/generated/RPCProtos$RequestHeader.getMethodName:()Ljava/lang/String;
     332: invokevirtual #300                // Method org/apache/hbase/thirdparty/com/google/protobuf/Descriptors$ServiceDescriptor.findMethodByName:(Ljava/lang/String;)Lorg/apache/hbase/thirdparty/com/google/protobuf/Descriptors$MethodDescriptor;
     335: astore        10
     337: aload         10
     339: ifnonnull     355
     342: new           #301                // class java/lang/UnsupportedOperationException
     345: dup
     346: aload         8
     348: invokevirtual #299                // Method org/apache/hadoop/hbase/shaded/protobuf/generated/RPCProtos$RequestHeader.getMethodName:()Ljava/lang/String;
     351: invokespecial #302                // Method java/lang/UnsupportedOperationException."<init>":(Ljava/lang/String;)V
     354: athrow
     355: aload_0
     356: getfield      #233                // Field service:Lorg/apache/hbase/thirdparty/com/google/protobuf/BlockingService;
     359: aload         10
     361: invokeinterface #303,  2          // InterfaceMethod org/apache/hbase/thirdparty/com/google/protobuf/BlockingService.getRequestPrototype:(Lorg/apache/hbase/thirdparty/com/google/protobuf/Descriptors$MethodDescriptor;)Lorg/apache/hbase/thirdparty/com/google/protobuf/Message;
     366: invokeinterface #304,  1          // InterfaceMethod org/apache/hbase/thirdparty/com/google/protobuf/Message.newBuilderForType:()Lorg/apache/hbase/thirdparty/com/google/protobuf/Message$Builder;
     371: astore        7
     373: aload         5
     375: invokevirtual #305                // Method org/apache/hbase/thirdparty/com/google/protobuf/CodedInputStream.resetSizeCounter:()V
     378: aload         5
     380: invokevirtual #270                // Method org/apache/hbase/thirdparty/com/google/protobuf/CodedInputStream.readRawVarint32:()I
     383: istore        13
     385: iload         4
     387: aload         5
     389: invokevirtual #271                // Method org/apache/hbase/thirdparty/com/google/protobuf/CodedInputStream.getTotalBytesRead:()I
     392: iadd
     393: istore        4
     395: aload         7
     397: ifnull        418
     400: aload         7
     402: aload         5
     404: iload         13
     406: invokestatic  #273                // Method org/apache/hadoop/hbase/shaded/protobuf/ProtobufUtil.mergeFrom:(Lorg/apache/hbase/thirdparty/com/google/protobuf/Message$Builder;Lorg/apache/hbase/thirdparty/com/google/protobuf/CodedInputStream;I)V
     409: aload         7
     411: invokeinterface #274,  1          // InterfaceMethod org/apache/hbase/thirdparty/com/google/protobuf/Message$Builder.build:()Lorg/apache/hbase/thirdparty/com/google/protobuf/Message;
     416: astore        11
     418: iload         4
     420: iload         13
     422: iadd
     423: istore        4
     425: goto          480
     428: new           #12                 // class java/lang/StringBuilder
     431: dup
     432: invokespecial #13                 // Method java/lang/StringBuilder."<init>":()V
     435: ldc_w         #306                // String Invalid request header:
     438: invokevirtual #15                 // Method java/lang/StringBuilder.append:(Ljava/lang/String;)Ljava/lang/StringBuilder;
     441: aload         8
     443: invokestatic  #279                // Method org/apache/hbase/thirdparty/com/google/protobuf/TextFormat.shortDebugString:(Lorg/apache/hbase/thirdparty/com/google/protobuf/MessageOrBuilder;)Ljava/lang/String;
     446: invokevirtual #15                 // Method java/lang/StringBuilder.append:(Ljava/lang/String;)Ljava/lang/StringBuilder;
     449: ldc_w         #307                // String , should have param set in it
     452: invokevirtual #15                 // Method java/lang/StringBuilder.append:(Ljava/lang/String;)Ljava/lang/StringBuilder;
     455: invokevirtual #19                 // Method java/lang/StringBuilder.toString:()Ljava/lang/String;
     458: astore        13
     460: getstatic     #139                // Field org/apache/hadoop/hbase/ipc/RpcServer.LOG:Lorg/slf4j/Logger;
     463: aload         13
     465: invokeinterface #172,  2          // InterfaceMethod org/slf4j/Logger.warn:(Ljava/lang/String;)V
     470: new           #308                // class org/apache/hadoop/hbase/DoNotRetryIOException
     473: dup
     474: aload         13
     476: invokespecial #309                // Method org/apache/hadoop/hbase/DoNotRetryIOException."<init>":(Ljava/lang/String;)V
     479: athrow
     480: aload         8
     482: invokevirtual #310                // Method org/apache/hadoop/hbase/shaded/protobuf/generated/RPCProtos$RequestHeader.hasCellBlockMeta:()Z
     485: ifeq          540
     488: aload_1
     489: iload         4
     491: invokevirtual #311                // Method org/apache/hadoop/hbase/nio/ByteBuff.position:(I)Lorg/apache/hadoop/hbase/nio/ByteBuff;
     494: pop
     495: aload_1
     496: invokevirtual #312                // Method org/apache/hadoop/hbase/nio/ByteBuff.duplicate:()Lorg/apache/hadoop/hbase/nio/ByteBuff;
     499: astore        13
     501: aload         13
     503: iload         4
     505: aload         8
     507: invokevirtual #313                // Method org/apache/hadoop/hbase/shaded/protobuf/generated/RPCProtos$RequestHeader.getCellBlockMeta:()Lorg/apache/hadoop/hbase/shaded/protobuf/generated/RPCProtos$CellBlockMeta;
     510: invokevirtual #314                // Method org/apache/hadoop/hbase/shaded/protobuf/generated/RPCProtos$CellBlockMeta.getLength:()I
     513: iadd
     514: invokevirtual #315                // Method org/apache/hadoop/hbase/nio/ByteBuff.limit:(I)Lorg/apache/hadoop/hbase/nio/ByteBuff;
     517: pop
     518: aload_0
     519: getfield      #10                 // Field rpcServer:Lorg/apache/hadoop/hbase/ipc/RpcServer;
     522: getfield      #316                // Field org/apache/hadoop/hbase/ipc/RpcServer.cellBlockBuilder:Lorg/apache/hadoop/hbase/ipc/CellBlockBuilder;
     525: aload_0
     526: getfield      #54                 // Field codec:Lorg/apache/hadoop/hbase/codec/Codec;
     529: aload_0
     530: getfield      #61                 // Field compressionCodec:Lorg/apache/hadoop/io/compress/CompressionCodec;
     533: aload         13
     535: invokevirtual #317                // Method org/apache/hadoop/hbase/ipc/CellBlockBuilder.createCellScannerReusingBuffers:(Lorg/apache/hadoop/hbase/codec/Codec;Lorg/apache/hadoop/io/compress/CompressionCodec;Lorg/apache/hadoop/hbase/nio/ByteBuff;)Lorg/apache/hadoop/hbase/CellScanner;
     538: astore        12
     540: goto          724
     543: astore        13
     545: aload_0
     546: getfield      #10                 // Field rpcServer:Lorg/apache/hadoop/hbase/ipc/RpcServer;
     549: invokevirtual #318                // Method org/apache/hadoop/hbase/ipc/RpcServer.getListenerAddress:()Ljava/net/InetSocketAddress;
     552: astore        14
     554: new           #12                 // class java/lang/StringBuilder
     557: dup
     558: invokespecial #13                 // Method java/lang/StringBuilder."<init>":()V
     561: aload         14
     563: ifnull        571
     566: aload         14
     568: goto          574
     571: ldc_w         #319                // String (channel closed)
     574: invokevirtual #171                // Method java/lang/StringBuilder.append:(Ljava/lang/Object;)Ljava/lang/StringBuilder;
     577: ldc_w         #320                // String  is unable to read call parameter from client
     580: invokevirtual #15                 // Method java/lang/StringBuilder.append:(Ljava/lang/String;)Ljava/lang/StringBuilder;
     583: aload_0
     584: invokevirtual #14                 // Method getHostAddress:()Ljava/lang/String;
     587: invokevirtual #15                 // Method java/lang/StringBuilder.append:(Ljava/lang/String;)Ljava/lang/StringBuilder;
     590: invokevirtual #19                 // Method java/lang/StringBuilder.toString:()Ljava/lang/String;
     593: astore        15
     595: getstatic     #139                // Field org/apache/hadoop/hbase/ipc/RpcServer.LOG:Lorg/slf4j/Logger;
     598: aload         15
     600: aload         13
     602: invokeinterface #321,  3          // InterfaceMethod org/slf4j/Logger.warn:(Ljava/lang/String;Ljava/lang/Throwable;)V
     607: aload_0
     608: getfield      #10                 // Field rpcServer:Lorg/apache/hadoop/hbase/ipc/RpcServer;
     611: getfield      #166                // Field org/apache/hadoop/hbase/ipc/RpcServer.metrics:Lorg/apache/hadoop/hbase/ipc/MetricsHBaseServer;
     614: aload         13
     616: invokevirtual #289                // Method org/apache/hadoop/hbase/ipc/MetricsHBaseServer.exception:(Ljava/lang/Throwable;)V
     619: aload         13
     621: instanceof    #322                // class java/lang/LinkageError
     624: ifeq          638
     627: new           #308                // class org/apache/hadoop/hbase/DoNotRetryIOException
     630: dup
     631: aload         13
     633: invokespecial #323                // Method org/apache/hadoop/hbase/DoNotRetryIOException."<init>":(Ljava/lang/Throwable;)V
     636: astore        13
     638: aload         13
     640: instanceof    #301                // class java/lang/UnsupportedOperationException
     643: ifeq          657
     646: new           #308                // class org/apache/hadoop/hbase/DoNotRetryIOException
     649: dup
     650: aload         13
     652: invokespecial #323                // Method org/apache/hadoop/hbase/DoNotRetryIOException."<init>":(Ljava/lang/Throwable;)V
     655: astore        13
     657: aload_0
     658: iload         9
     660: aload_0
     661: getfield      #233                // Field service:Lorg/apache/hbase/thirdparty/com/google/protobuf/BlockingService;
     664: aconst_null
     665: aconst_null
     666: aconst_null
     667: aconst_null
     668: lload_2
     669: aconst_null
     670: iconst_0
     671: aload_0
     672: getfield      #11                 // Field callCleanup:Lorg/apache/hadoop/hbase/ipc/RpcServer$CallCleanup;
     675: invokevirtual #287                // Method createCall:(ILorg/apache/hbase/thirdparty/com/google/protobuf/BlockingService;Lorg/apache/hbase/thirdparty/com/google/protobuf/Descriptors$MethodDescriptor;Lorg/apache/hadoop/hbase/shaded/protobuf/generated/RPCProtos$RequestHeader;Lorg/apache/hbase/thirdparty/com/google/protobuf/Message;Lorg/apache/hadoop/hbase/CellScanner;JLjava/net/InetAddress;ILorg/apache/hadoop/hbase/ipc/RpcServer$CallCleanup;)Lorg/apache/hadoop/hbase/ipc/ServerCall;
     678: astore        16
     680: aload         16
     682: aconst_null
     683: aconst_null
     684: aload         13
     686: new           #12                 // class java/lang/StringBuilder
     689: dup
     690: invokespecial #13                 // Method java/lang/StringBuilder."<init>":()V
     693: aload         15
     695: invokevirtual #15                 // Method java/lang/StringBuilder.append:(Ljava/lang/String;)Ljava/lang/StringBuilder;
     698: ldc_w         #324                // String ;
     701: invokevirtual #15                 // Method java/lang/StringBuilder.append:(Ljava/lang/String;)Ljava/lang/StringBuilder;
     704: aload         13
     706: invokevirtual #325                // Method java/lang/Throwable.getMessage:()Ljava/lang/String;
     709: invokevirtual #15                 // Method java/lang/StringBuilder.append:(Ljava/lang/String;)Ljava/lang/StringBuilder;
     712: invokevirtual #19                 // Method java/lang/StringBuilder.toString:()Ljava/lang/String;
     715: invokevirtual #294                // Method org/apache/hadoop/hbase/ipc/ServerCall.setResponse:(Lorg/apache/hbase/thirdparty/com/google/protobuf/Message;Lorg/apache/hadoop/hbase/CellScanner;Ljava/lang/Throwable;Ljava/lang/String;)V
     718: aload         16
     720: invokevirtual #295                // Method org/apache/hadoop/hbase/ipc/ServerCall.sendResponseIfReady:()V
     723: return
     724: iconst_0
     725: istore        13
     727: aload         8
     729: invokevirtual #326                // Method org/apache/hadoop/hbase/shaded/protobuf/generated/RPCProtos$RequestHeader.hasTimeout:()Z
     732: ifeq          760
     735: aload         8
     737: invokevirtual #327                // Method org/apache/hadoop/hbase/shaded/protobuf/generated/RPCProtos$RequestHeader.getTimeout:()I
     740: ifle          760
     743: aload_0
     744: getfield      #10                 // Field rpcServer:Lorg/apache/hadoop/hbase/ipc/RpcServer;
     747: getfield      #328                // Field org/apache/hadoop/hbase/ipc/RpcServer.minClientRequestTimeout:I
     750: aload         8
     752: invokevirtual #327                // Method org/apache/hadoop/hbase/shaded/protobuf/generated/RPCProtos$RequestHeader.getTimeout:()I
     755: invokestatic  #329                // Method java/lang/Math.max:(II)I
     758: istore        13
     760: aload_0
     761: iload         9
     763: aload_0
     764: getfield      #233                // Field service:Lorg/apache/hbase/thirdparty/com/google/protobuf/BlockingService;
     767: aload         10
     769: aload         8
     771: aload         11
     773: aload         12
     775: lload_2
     776: aload_0
     777: getfield      #21                 // Field addr:Ljava/net/InetAddress;
     780: iload         13
     782: aload_0
     783: getfield      #11                 // Field callCleanup:Lorg/apache/hadoop/hbase/ipc/RpcServer$CallCleanup;
     786: invokevirtual #287                // Method createCall:(ILorg/apache/hbase/thirdparty/com/google/protobuf/BlockingService;Lorg/apache/hbase/thirdparty/com/google/protobuf/Descriptors$MethodDescriptor;Lorg/apache/hadoop/hbase/shaded/protobuf/generated/RPCProtos$RequestHeader;Lorg/apache/hbase/thirdparty/com/google/protobuf/Message;Lorg/apache/hadoop/hbase/CellScanner;JLjava/net/InetAddress;ILorg/apache/hadoop/hbase/ipc/RpcServer$CallCleanup;)Lorg/apache/hadoop/hbase/ipc/ServerCall;
     789: astore        14
     791: aload_0
     792: getfield      #10                 // Field rpcServer:Lorg/apache/hadoop/hbase/ipc/RpcServer;
     795: getfield      #330                // Field org/apache/hadoop/hbase/ipc/RpcServer.scheduler:Lorg/apache/hadoop/hbase/ipc/RpcScheduler;
     798: new           #331                // class org/apache/hadoop/hbase/ipc/CallRunner
     801: dup
     802: aload_0
     803: getfield      #10                 // Field rpcServer:Lorg/apache/hadoop/hbase/ipc/RpcServer;
     806: aload         14
     808: invokespecial #332                // Method org/apache/hadoop/hbase/ipc/CallRunner."<init>":(Lorg/apache/hadoop/hbase/ipc/RpcServerInterface;Lorg/apache/hadoop/hbase/ipc/RpcCall;)V
     811: invokevirtual #333                // Method org/apache/hadoop/hbase/ipc/RpcScheduler.dispatch:(Lorg/apache/hadoop/hbase/ipc/CallRunner;)Z
     814: ifne          901
     817: aload_0
     818: getfield      #10                 // Field rpcServer:Lorg/apache/hadoop/hbase/ipc/RpcServer;
     821: getfield      #284                // Field org/apache/hadoop/hbase/ipc/RpcServer.callQueueSizeInBytes:Ljava/util/concurrent/atomic/LongAdder;
     824: ldc2_w        #334                // long -1l
     827: aload         14
     829: invokevirtual #336                // Method org/apache/hadoop/hbase/ipc/ServerCall.getSize:()J
     832: lmul
     833: invokevirtual #337                // Method java/util/concurrent/atomic/LongAdder.add:(J)V
     836: aload_0
     837: getfield      #10                 // Field rpcServer:Lorg/apache/hadoop/hbase/ipc/RpcServer;
     840: getfield      #166                // Field org/apache/hadoop/hbase/ipc/RpcServer.metrics:Lorg/apache/hadoop/hbase/ipc/MetricsHBaseServer;
     843: getstatic     #288                // Field org/apache/hadoop/hbase/ipc/RpcServer.CALL_QUEUE_TOO_BIG_EXCEPTION:Lorg/apache/hadoop/hbase/CallQueueTooBigException;
     846: invokevirtual #289                // Method org/apache/hadoop/hbase/ipc/MetricsHBaseServer.exception:(Ljava/lang/Throwable;)V
     849: aload         14
     851: aconst_null
     852: aconst_null
     853: getstatic     #288                // Field org/apache/hadoop/hbase/ipc/RpcServer.CALL_QUEUE_TOO_BIG_EXCEPTION:Lorg/apache/hadoop/hbase/CallQueueTooBigException;
     856: new           #12                 // class java/lang/StringBuilder
     859: dup
     860: invokespecial #13                 // Method java/lang/StringBuilder."<init>":()V
     863: ldc_w         #290                // String Call queue is full on
     866: invokevirtual #15                 // Method java/lang/StringBuilder.append:(Ljava/lang/String;)Ljava/lang/StringBuilder;
     869: aload_0
     870: getfield      #10                 // Field rpcServer:Lorg/apache/hadoop/hbase/ipc/RpcServer;
     873: getfield      #291                // Field org/apache/hadoop/hbase/ipc/RpcServer.server:Lorg/apache/hadoop/hbase/Server;
     876: invokeinterface #292,  1          // InterfaceMethod org/apache/hadoop/hbase/Server.getServerName:()Lorg/apache/hadoop/hbase/ServerName;
     881: invokevirtual #171                // Method java/lang/StringBuilder.append:(Ljava/lang/Object;)Ljava/lang/StringBuilder;
     884: ldc_w         #338                // String , too many items queued ?
     887: invokevirtual #15                 // Method java/lang/StringBuilder.append:(Ljava/lang/String;)Ljava/lang/StringBuilder;
     890: invokevirtual #19                 // Method java/lang/StringBuilder.toString:()Ljava/lang/String;
     893: invokevirtual #294                // Method org/apache/hadoop/hbase/ipc/ServerCall.setResponse:(Lorg/apache/hbase/thirdparty/com/google/protobuf/Message;Lorg/apache/hadoop/hbase/CellScanner;Ljava/lang/Throwable;Ljava/lang/String;)V
     896: aload         14
     898: invokevirtual #295                // Method org/apache/hadoop/hbase/ipc/ServerCall.sendResponseIfReady:()V
     901: return
    Exception table:
       from    to  target type
         302   540   543   Class java/lang/Throwable

  protected final org.apache.hadoop.hbase.ipc.RpcResponse getErrorResponse(java.lang.String, java.lang.Exception) throws java.io.IOException;
    Code:
       0: invokestatic  #339                // Method org/apache/hadoop/hbase/shaded/protobuf/generated/RPCProtos$ResponseHeader.newBuilder:()Lorg/apache/hadoop/hbase/shaded/protobuf/generated/RPCProtos$ResponseHeader$Builder;
       3: iconst_m1
       4: invokevirtual #340                // Method org/apache/hadoop/hbase/shaded/protobuf/generated/RPCProtos$ResponseHeader$Builder.setCallId:(I)Lorg/apache/hadoop/hbase/shaded/protobuf/generated/RPCProtos$ResponseHeader$Builder;
       7: astore_3
       8: aload_2
       9: aload_1
      10: aload_3
      11: invokestatic  #341                // Method org/apache/hadoop/hbase/ipc/ServerCall.setExceptionResponse:(Ljava/lang/Throwable;Ljava/lang/String;Lorg/apache/hadoop/hbase/shaded/protobuf/generated/RPCProtos$ResponseHeader$Builder;)V
      14: aconst_null
      15: aload_3
      16: invokevirtual #342                // Method org/apache/hadoop/hbase/shaded/protobuf/generated/RPCProtos$ResponseHeader$Builder.build:()Lorg/apache/hadoop/hbase/shaded/protobuf/generated/RPCProtos$ResponseHeader;
      19: iconst_0
      20: aconst_null
      21: invokestatic  #343                // Method org/apache/hadoop/hbase/ipc/ServerCall.createHeaderAndMessageBytes:(Lorg/apache/hbase/thirdparty/com/google/protobuf/Message;Lorg/apache/hbase/thirdparty/com/google/protobuf/Message;ILjava/util/List;)Ljava/nio/ByteBuffer;
      24: astore        4
      26: new           #128                // class org/apache/hadoop/hbase/ipc/BufferChain
      29: dup
      30: iconst_1
      31: anewarray     #129                // class java/nio/ByteBuffer
      34: dup
      35: iconst_0
      36: aload         4
      38: aastore
      39: invokespecial #131                // Method org/apache/hadoop/hbase/ipc/BufferChain."<init>":([Ljava/nio/ByteBuffer;)V
      42: astore        5
      44: aload         5
      46: invokedynamic #344,  0            // InvokeDynamic #2:getResponse:(Lorg/apache/hadoop/hbase/ipc/BufferChain;)Lorg/apache/hadoop/hbase/ipc/RpcResponse;
      51: areturn

  protected final boolean processPreamble(java.nio.ByteBuffer) throws java.io.IOException;
    Code:
       0: getstatic     #349                // Field $assertionsDisabled:Z
       3: ifne          23
       6: aload_1
       7: invokevirtual #191                // Method java/nio/ByteBuffer.remaining:()I
      10: bipush        6
      12: if_icmpeq     23
      15: new           #350                // class java/lang/AssertionError
      18: dup
      19: invokespecial #351                // Method java/lang/AssertionError."<init>":()V
      22: athrow
      23: iconst_0
      24: istore_2
      25: iload_2
      26: getstatic     #352                // Field org/apache/hadoop/hbase/HConstants.RPC_HEADER:[B
      29: arraylength
      30: if_icmpge     115
      33: getstatic     #352                // Field org/apache/hadoop/hbase/HConstants.RPC_HEADER:[B
      36: iload_2
      37: baload
      38: aload_1
      39: invokevirtual #353                // Method java/nio/ByteBuffer.get:()B
      42: if_icmpeq     109
      45: aload_0
      46: new           #12                 // class java/lang/StringBuilder
      49: dup
      50: invokespecial #13                 // Method java/lang/StringBuilder."<init>":()V
      53: ldc_w         #354                // String Expected HEADER=
      56: invokevirtual #15                 // Method java/lang/StringBuilder.append:(Ljava/lang/String;)Ljava/lang/StringBuilder;
      59: getstatic     #352                // Field org/apache/hadoop/hbase/HConstants.RPC_HEADER:[B
      62: invokestatic  #355                // Method org/apache/hadoop/hbase/util/Bytes.toStringBinary:([B)Ljava/lang/String;
      65: invokevirtual #15                 // Method java/lang/StringBuilder.append:(Ljava/lang/String;)Ljava/lang/StringBuilder;
      68: ldc_w         #356                // String  but received HEADER=
      71: invokevirtual #15                 // Method java/lang/StringBuilder.append:(Ljava/lang/String;)Ljava/lang/StringBuilder;
      74: aload_1
      75: invokevirtual #357                // Method java/nio/ByteBuffer.array:()[B
      78: iconst_0
      79: getstatic     #352                // Field org/apache/hadoop/hbase/HConstants.RPC_HEADER:[B
      82: arraylength
      83: invokestatic  #358                // Method org/apache/hadoop/hbase/util/Bytes.toStringBinary:([BII)Ljava/lang/String;
      86: invokevirtual #15                 // Method java/lang/StringBuilder.append:(Ljava/lang/String;)Ljava/lang/StringBuilder;
      89: ldc           #31                 // String  from
      91: invokevirtual #15                 // Method java/lang/StringBuilder.append:(Ljava/lang/String;)Ljava/lang/StringBuilder;
      94: aload_0
      95: invokevirtual #32                 // Method toString:()Ljava/lang/String;
      98: invokevirtual #15                 // Method java/lang/StringBuilder.append:(Ljava/lang/String;)Ljava/lang/StringBuilder;
     101: invokevirtual #19                 // Method java/lang/StringBuilder.toString:()Ljava/lang/String;
     104: invokespecial #359                // Method doBadPreambleHandling:(Ljava/lang/String;)V
     107: iconst_0
     108: ireturn
     109: iinc          2, 1
     112: goto          25
     115: aload_1
     116: invokevirtual #353                // Method java/nio/ByteBuffer.get:()B
     119: sipush        255
     122: iand
     123: istore_2
     124: aload_1
     125: invokevirtual #353                // Method java/nio/ByteBuffer.get:()B
     128: istore_3
     129: aload_0
     130: iload_3
     131: invokestatic  #360                // Method org/apache/hadoop/hbase/security/AuthMethod.valueOf:(B)Lorg/apache/hadoop/hbase/security/AuthMethod;
     134: putfield      #29                 // Field authMethod:Lorg/apache/hadoop/hbase/security/AuthMethod;
     137: iload_2
     138: ifeq          166
     141: aload_0
     142: iload_2
     143: iload_3
     144: invokespecial #361                // Method getFatalConnectionString:(IB)Ljava/lang/String;
     147: astore        4
     149: aload_0
     150: aload         4
     152: new           #362                // class org/apache/hadoop/hbase/ipc/WrongVersionException
     155: dup
     156: aload         4
     158: invokespecial #363                // Method org/apache/hadoop/hbase/ipc/WrongVersionException."<init>":(Ljava/lang/String;)V
     161: invokespecial #347                // Method doBadPreambleHandling:(Ljava/lang/String;Ljava/lang/Exception;)V
     164: iconst_0
     165: ireturn
     166: aload_0
     167: getfield      #29                 // Field authMethod:Lorg/apache/hadoop/hbase/security/AuthMethod;
     170: ifnonnull     198
     173: aload_0
     174: iload_2
     175: iload_3
     176: invokespecial #361                // Method getFatalConnectionString:(IB)Ljava/lang/String;
     179: astore        4
     181: aload_0
     182: aload         4
     184: new           #364                // class org/apache/hadoop/hbase/ipc/BadAuthException
     187: dup
     188: aload         4
     190: invokespecial #365                // Method org/apache/hadoop/hbase/ipc/BadAuthException."<init>":(Ljava/lang/String;)V
     193: invokespecial #347                // Method doBadPreambleHandling:(Ljava/lang/String;Ljava/lang/Exception;)V
     196: iconst_0
     197: ireturn
     198: aload_0
     199: getfield      #10                 // Field rpcServer:Lorg/apache/hadoop/hbase/ipc/RpcServer;
     202: getfield      #366                // Field org/apache/hadoop/hbase/ipc/RpcServer.isSecurityEnabled:Z
     205: ifeq          275
     208: aload_0
     209: getfield      #29                 // Field authMethod:Lorg/apache/hadoop/hbase/security/AuthMethod;
     212: getstatic     #242                // Field org/apache/hadoop/hbase/security/AuthMethod.SIMPLE:Lorg/apache/hadoop/hbase/security/AuthMethod;
     215: if_acmpne     275
     218: aload_0
     219: getfield      #10                 // Field rpcServer:Lorg/apache/hadoop/hbase/ipc/RpcServer;
     222: getfield      #367                // Field org/apache/hadoop/hbase/ipc/RpcServer.allowFallbackToSimpleAuth:Z
     225: ifeq          246
     228: aload_0
     229: getfield      #10                 // Field rpcServer:Lorg/apache/hadoop/hbase/ipc/RpcServer;
     232: getfield      #166                // Field org/apache/hadoop/hbase/ipc/RpcServer.metrics:Lorg/apache/hadoop/hbase/ipc/MetricsHBaseServer;
     235: invokevirtual #368                // Method org/apache/hadoop/hbase/ipc/MetricsHBaseServer.authenticationFallback:()V
     238: aload_0
     239: iconst_1
     240: putfield      #244                // Field authenticatedWithFallback:Z
     243: goto          275
     246: new           #37                 // class org/apache/hadoop/hbase/security/AccessDeniedException
     249: dup
     250: ldc_w         #369                // String Authentication is required
     253: invokespecial #39                 // Method org/apache/hadoop/hbase/security/AccessDeniedException."<init>":(Ljava/lang/String;)V
     256: astore        4
     258: aload_0
     259: aload_0
     260: aload         4
     262: invokevirtual #370                // Method org/apache/hadoop/hbase/security/AccessDeniedException.getMessage:()Ljava/lang/String;
     265: aload         4
     267: invokevirtual #221                // Method getErrorResponse:(Ljava/lang/String;Ljava/lang/Exception;)Lorg/apache/hadoop/hbase/ipc/RpcResponse;
     270: invokevirtual #137                // Method doRespond:(Lorg/apache/hadoop/hbase/ipc/RpcResponse;)V
     273: iconst_0
     274: ireturn
     275: aload_0
     276: getfield      #10                 // Field rpcServer:Lorg/apache/hadoop/hbase/ipc/RpcServer;
     279: getfield      #366                // Field org/apache/hadoop/hbase/ipc/RpcServer.isSecurityEnabled:Z
     282: ifne          325
     285: aload_0
     286: getfield      #29                 // Field authMethod:Lorg/apache/hadoop/hbase/security/AuthMethod;
     289: getstatic     #242                // Field org/apache/hadoop/hbase/security/AuthMethod.SIMPLE:Lorg/apache/hadoop/hbase/security/AuthMethod;
     292: if_acmpeq     325
     295: aload_0
     296: getstatic     #125                // Field org/apache/hadoop/hbase/security/SaslStatus.SUCCESS:Lorg/apache/hadoop/hbase/security/SaslStatus;
     299: new           #371                // class org/apache/hadoop/io/IntWritable
     302: dup
     303: bipush        -88
     305: invokespecial #373                // Method org/apache/hadoop/io/IntWritable."<init>":(I)V
     308: aconst_null
     309: aconst_null
     310: invokevirtual #165                // Method doRawSaslReply:(Lorg/apache/hadoop/hbase/security/SaslStatus;Lorg/apache/hadoop/io/Writable;Ljava/lang/String;Ljava/lang/String;)V
     313: aload_0
     314: getstatic     #242                // Field org/apache/hadoop/hbase/security/AuthMethod.SIMPLE:Lorg/apache/hadoop/hbase/security/AuthMethod;
     317: putfield      #29                 // Field authMethod:Lorg/apache/hadoop/hbase/security/AuthMethod;
     320: aload_0
     321: iconst_1
     322: putfield      #374                // Field skipInitialSaslHandshake:Z
     325: aload_0
     326: getfield      #29                 // Field authMethod:Lorg/apache/hadoop/hbase/security/AuthMethod;
     329: getstatic     #242                // Field org/apache/hadoop/hbase/security/AuthMethod.SIMPLE:Lorg/apache/hadoop/hbase/security/AuthMethod;
     332: if_acmpeq     340
     335: aload_0
     336: iconst_1
     337: putfield      #241                // Field useSasl:Z
     340: iconst_1
     341: ireturn

  public abstract boolean isConnectionOpen();

  public abstract org.apache.hadoop.hbase.ipc.ServerCall<?> createCall(int, org.apache.hbase.thirdparty.com.google.protobuf.BlockingService, org.apache.hbase.thirdparty.com.google.protobuf.Descriptors$MethodDescriptor, org.apache.hadoop.hbase.shaded.protobuf.generated.RPCProtos$RequestHeader, org.apache.hbase.thirdparty.com.google.protobuf.Message, org.apache.hadoop.hbase.CellScanner, long, java.net.InetAddress, int, org.apache.hadoop.hbase.ipc.RpcServer$CallCleanup);

  static {};
    Code:
       0: ldc_w         #375                // class org/apache/hadoop/hbase/ipc/ServerRpcConnection
       3: invokevirtual #376                // Method java/lang/Class.desiredAssertionStatus:()Z
       6: ifne          13
       9: iconst_1
      10: goto          14
      13: iconst_0
      14: putstatic     #349                // Field $assertionsDisabled:Z
      17: return
}
