Compiled from "ServerLoad.java"
public class org.apache.hadoop.hbase.ServerLoad implements org.apache.hadoop.hbase.ServerMetrics {
  protected org.apache.hadoop.hbase.shaded.protobuf.generated.ClusterStatusProtos$ServerLoad serverLoad;

  public static final org.apache.hadoop.hbase.ServerLoad EMPTY_SERVERLOAD;

  public org.apache.hadoop.hbase.ServerLoad(org.apache.hadoop.hbase.shaded.protobuf.generated.ClusterStatusProtos$ServerLoad);
    Code:
       0: aload_0
       1: ldc           #1                  // String localhost,1,1
       3: invokestatic  #2                  // Method org/apache/hadoop/hbase/ServerName.valueOf:(Ljava/lang/String;)Lorg/apache/hadoop/hbase/ServerName;
       6: aload_1
       7: invokespecial #3                  // Method "<init>":(Lorg/apache/hadoop/hbase/ServerName;Lorg/apache/hadoop/hbase/shaded/protobuf/generated/ClusterStatusProtos$ServerLoad;)V
      10: return

  public org.apache.hadoop.hbase.ServerLoad(org.apache.hadoop.hbase.ServerName, org.apache.hadoop.hbase.shaded.protobuf.generated.ClusterStatusProtos$ServerLoad);
    Code:
       0: aload_0
       1: aload_1
       2: aload_2
       3: invokestatic  #4                  // Method org/apache/hadoop/hbase/ServerMetricsBuilder.toServerMetrics:(Lorg/apache/hadoop/hbase/ServerName;Lorg/apache/hadoop/hbase/shaded/protobuf/generated/ClusterStatusProtos$ServerLoad;)Lorg/apache/hadoop/hbase/ServerMetrics;
       6: invokespecial #5                  // Method "<init>":(Lorg/apache/hadoop/hbase/ServerMetrics;)V
       9: aload_0
      10: aload_2
      11: putfield      #6                  // Field serverLoad:Lorg/apache/hadoop/hbase/shaded/protobuf/generated/ClusterStatusProtos$ServerLoad;
      14: return

  public org.apache.hadoop.hbase.ServerLoad(org.apache.hadoop.hbase.ServerMetrics);
    Code:
       0: aload_0
       1: invokespecial #7                  // Method java/lang/Object."<init>":()V
       4: aload_0
       5: iconst_0
       6: putfield      #8                  // Field stores:I
       9: aload_0
      10: iconst_0
      11: putfield      #9                  // Field storefiles:I
      14: aload_0
      15: iconst_0
      16: putfield      #10                 // Field storeUncompressedSizeMB:I
      19: aload_0
      20: iconst_0
      21: putfield      #11                 // Field storefileSizeMB:I
      24: aload_0
      25: iconst_0
      26: putfield      #12                 // Field memstoreSizeMB:I
      29: aload_0
      30: lconst_0
      31: putfield      #13                 // Field storefileIndexSizeKB:J
      34: aload_0
      35: lconst_0
      36: putfield      #14                 // Field readRequestsCount:J
      39: aload_0
      40: lconst_0
      41: putfield      #15                 // Field cpRequestsCount:J
      44: aload_0
      45: lconst_0
      46: putfield      #16                 // Field filteredReadRequestsCount:J
      49: aload_0
      50: lconst_0
      51: putfield      #17                 // Field writeRequestsCount:J
      54: aload_0
      55: iconst_0
      56: putfield      #18                 // Field rootIndexSizeKB:I
      59: aload_0
      60: iconst_0
      61: putfield      #19                 // Field totalStaticIndexSizeKB:I
      64: aload_0
      65: iconst_0
      66: putfield      #20                 // Field totalStaticBloomSizeKB:I
      69: aload_0
      70: lconst_0
      71: putfield      #21                 // Field totalCompactingKVs:J
      74: aload_0
      75: lconst_0
      76: putfield      #22                 // Field currentCompactedKVs:J
      79: aload_0
      80: aload_1
      81: putfield      #23                 // Field metrics:Lorg/apache/hadoop/hbase/ServerMetrics;
      84: aload_0
      85: aload_1
      86: invokestatic  #24                 // Method org/apache/hadoop/hbase/ServerMetricsBuilder.toServerLoad:(Lorg/apache/hadoop/hbase/ServerMetrics;)Lorg/apache/hadoop/hbase/shaded/protobuf/generated/ClusterStatusProtos$ServerLoad;
      89: putfield      #6                  // Field serverLoad:Lorg/apache/hadoop/hbase/shaded/protobuf/generated/ClusterStatusProtos$ServerLoad;
      92: aload_1
      93: invokeinterface #25,  1           // InterfaceMethod org/apache/hadoop/hbase/ServerMetrics.getRegionMetrics:()Ljava/util/Map;
      98: invokeinterface #26,  1           // InterfaceMethod java/util/Map.values:()Ljava/util/Collection;
     103: invokeinterface #27,  1           // InterfaceMethod java/util/Collection.iterator:()Ljava/util/Iterator;
     108: astore_2
     109: aload_2
     110: invokeinterface #28,  1           // InterfaceMethod java/util/Iterator.hasNext:()Z
     115: ifeq          412
     118: aload_2
     119: invokeinterface #29,  1           // InterfaceMethod java/util/Iterator.next:()Ljava/lang/Object;
     124: checkcast     #30                 // class org/apache/hadoop/hbase/RegionMetrics
     127: astore_3
     128: aload_0
     129: dup
     130: getfield      #8                  // Field stores:I
     133: aload_3
     134: invokeinterface #31,  1           // InterfaceMethod org/apache/hadoop/hbase/RegionMetrics.getStoreCount:()I
     139: iadd
     140: putfield      #8                  // Field stores:I
     143: aload_0
     144: dup
     145: getfield      #9                  // Field storefiles:I
     148: aload_3
     149: invokeinterface #32,  1           // InterfaceMethod org/apache/hadoop/hbase/RegionMetrics.getStoreFileCount:()I
     154: iadd
     155: putfield      #9                  // Field storefiles:I
     158: aload_0
     159: dup
     160: getfield      #10                 // Field storeUncompressedSizeMB:I
     163: i2d
     164: aload_3
     165: invokeinterface #33,  1           // InterfaceMethod org/apache/hadoop/hbase/RegionMetrics.getUncompressedStoreFileSize:()Lorg/apache/hadoop/hbase/Size;
     170: getstatic     #34                 // Field org/apache/hadoop/hbase/Size$Unit.MEGABYTE:Lorg/apache/hadoop/hbase/Size$Unit;
     173: invokevirtual #35                 // Method org/apache/hadoop/hbase/Size.get:(Lorg/apache/hadoop/hbase/Size$Unit;)D
     176: dadd
     177: d2i
     178: putfield      #10                 // Field storeUncompressedSizeMB:I
     181: aload_0
     182: dup
     183: getfield      #11                 // Field storefileSizeMB:I
     186: i2d
     187: aload_3
     188: invokeinterface #36,  1           // InterfaceMethod org/apache/hadoop/hbase/RegionMetrics.getStoreFileSize:()Lorg/apache/hadoop/hbase/Size;
     193: getstatic     #34                 // Field org/apache/hadoop/hbase/Size$Unit.MEGABYTE:Lorg/apache/hadoop/hbase/Size$Unit;
     196: invokevirtual #35                 // Method org/apache/hadoop/hbase/Size.get:(Lorg/apache/hadoop/hbase/Size$Unit;)D
     199: dadd
     200: d2i
     201: putfield      #11                 // Field storefileSizeMB:I
     204: aload_0
     205: dup
     206: getfield      #12                 // Field memstoreSizeMB:I
     209: i2d
     210: aload_3
     211: invokeinterface #37,  1           // InterfaceMethod org/apache/hadoop/hbase/RegionMetrics.getMemStoreSize:()Lorg/apache/hadoop/hbase/Size;
     216: getstatic     #34                 // Field org/apache/hadoop/hbase/Size$Unit.MEGABYTE:Lorg/apache/hadoop/hbase/Size$Unit;
     219: invokevirtual #35                 // Method org/apache/hadoop/hbase/Size.get:(Lorg/apache/hadoop/hbase/Size$Unit;)D
     222: dadd
     223: d2i
     224: putfield      #12                 // Field memstoreSizeMB:I
     227: aload_0
     228: dup
     229: getfield      #14                 // Field readRequestsCount:J
     232: aload_3
     233: invokeinterface #38,  1           // InterfaceMethod org/apache/hadoop/hbase/RegionMetrics.getReadRequestCount:()J
     238: ladd
     239: putfield      #14                 // Field readRequestsCount:J
     242: aload_0
     243: dup
     244: getfield      #15                 // Field cpRequestsCount:J
     247: aload_3
     248: invokeinterface #39,  1           // InterfaceMethod org/apache/hadoop/hbase/RegionMetrics.getCpRequestCount:()J
     253: ladd
     254: putfield      #15                 // Field cpRequestsCount:J
     257: aload_0
     258: dup
     259: getfield      #16                 // Field filteredReadRequestsCount:J
     262: aload_3
     263: invokeinterface #40,  1           // InterfaceMethod org/apache/hadoop/hbase/RegionMetrics.getFilteredReadRequestCount:()J
     268: ladd
     269: putfield      #16                 // Field filteredReadRequestsCount:J
     272: aload_0
     273: dup
     274: getfield      #17                 // Field writeRequestsCount:J
     277: aload_3
     278: invokeinterface #41,  1           // InterfaceMethod org/apache/hadoop/hbase/RegionMetrics.getWriteRequestCount:()J
     283: ladd
     284: putfield      #17                 // Field writeRequestsCount:J
     287: aload_0
     288: dup
     289: getfield      #13                 // Field storefileIndexSizeKB:J
     292: l2d
     293: aload_3
     294: invokeinterface #42,  1           // InterfaceMethod org/apache/hadoop/hbase/RegionMetrics.getStoreFileIndexSize:()Lorg/apache/hadoop/hbase/Size;
     299: getstatic     #43                 // Field org/apache/hadoop/hbase/Size$Unit.KILOBYTE:Lorg/apache/hadoop/hbase/Size$Unit;
     302: invokevirtual #35                 // Method org/apache/hadoop/hbase/Size.get:(Lorg/apache/hadoop/hbase/Size$Unit;)D
     305: dadd
     306: d2l
     307: putfield      #13                 // Field storefileIndexSizeKB:J
     310: aload_0
     311: dup
     312: getfield      #18                 // Field rootIndexSizeKB:I
     315: i2d
     316: aload_3
     317: invokeinterface #44,  1           // InterfaceMethod org/apache/hadoop/hbase/RegionMetrics.getStoreFileRootLevelIndexSize:()Lorg/apache/hadoop/hbase/Size;
     322: getstatic     #43                 // Field org/apache/hadoop/hbase/Size$Unit.KILOBYTE:Lorg/apache/hadoop/hbase/Size$Unit;
     325: invokevirtual #35                 // Method org/apache/hadoop/hbase/Size.get:(Lorg/apache/hadoop/hbase/Size$Unit;)D
     328: dadd
     329: d2i
     330: putfield      #18                 // Field rootIndexSizeKB:I
     333: aload_0
     334: dup
     335: getfield      #19                 // Field totalStaticIndexSizeKB:I
     338: i2d
     339: aload_3
     340: invokeinterface #45,  1           // InterfaceMethod org/apache/hadoop/hbase/RegionMetrics.getStoreFileUncompressedDataIndexSize:()Lorg/apache/hadoop/hbase/Size;
     345: getstatic     #43                 // Field org/apache/hadoop/hbase/Size$Unit.KILOBYTE:Lorg/apache/hadoop/hbase/Size$Unit;
     348: invokevirtual #35                 // Method org/apache/hadoop/hbase/Size.get:(Lorg/apache/hadoop/hbase/Size$Unit;)D
     351: dadd
     352: d2i
     353: putfield      #19                 // Field totalStaticIndexSizeKB:I
     356: aload_0
     357: dup
     358: getfield      #20                 // Field totalStaticBloomSizeKB:I
     361: i2d
     362: aload_3
     363: invokeinterface #46,  1           // InterfaceMethod org/apache/hadoop/hbase/RegionMetrics.getBloomFilterSize:()Lorg/apache/hadoop/hbase/Size;
     368: getstatic     #43                 // Field org/apache/hadoop/hbase/Size$Unit.KILOBYTE:Lorg/apache/hadoop/hbase/Size$Unit;
     371: invokevirtual #35                 // Method org/apache/hadoop/hbase/Size.get:(Lorg/apache/hadoop/hbase/Size$Unit;)D
     374: dadd
     375: d2i
     376: putfield      #20                 // Field totalStaticBloomSizeKB:I
     379: aload_0
     380: dup
     381: getfield      #21                 // Field totalCompactingKVs:J
     384: aload_3
     385: invokeinterface #47,  1           // InterfaceMethod org/apache/hadoop/hbase/RegionMetrics.getCompactingCellCount:()J
     390: ladd
     391: putfield      #21                 // Field totalCompactingKVs:J
     394: aload_0
     395: dup
     396: getfield      #22                 // Field currentCompactedKVs:J
     399: aload_3
     400: invokeinterface #48,  1           // InterfaceMethod org/apache/hadoop/hbase/RegionMetrics.getCompactedCellCount:()J
     405: ladd
     406: putfield      #22                 // Field currentCompactedKVs:J
     409: goto          109
     412: return

  public org.apache.hadoop.hbase.shaded.protobuf.generated.ClusterStatusProtos$ServerLoad obtainServerLoadPB();
    Code:
       0: aload_0
       1: getfield      #6                  // Field serverLoad:Lorg/apache/hadoop/hbase/shaded/protobuf/generated/ClusterStatusProtos$ServerLoad;
       4: areturn

  public long getNumberOfRequests();
    Code:
       0: aload_0
       1: invokevirtual #49                 // Method getRequestCountPerSecond:()J
       4: lreturn

  public boolean hasNumberOfRequests();
    Code:
       0: iconst_1
       1: ireturn

  public long getTotalNumberOfRequests();
    Code:
       0: aload_0
       1: invokevirtual #50                 // Method getRequestCount:()J
       4: lreturn

  public boolean hasTotalNumberOfRequests();
    Code:
       0: iconst_1
       1: ireturn

  public int getUsedHeapMB();
    Code:
       0: aload_0
       1: invokevirtual #51                 // Method getUsedHeapSize:()Lorg/apache/hadoop/hbase/Size;
       4: getstatic     #34                 // Field org/apache/hadoop/hbase/Size$Unit.MEGABYTE:Lorg/apache/hadoop/hbase/Size$Unit;
       7: invokevirtual #35                 // Method org/apache/hadoop/hbase/Size.get:(Lorg/apache/hadoop/hbase/Size$Unit;)D
      10: d2i
      11: ireturn

  public boolean hasUsedHeapMB();
    Code:
       0: iconst_1
       1: ireturn

  public int getMaxHeapMB();
    Code:
       0: aload_0
       1: invokevirtual #52                 // Method getMaxHeapSize:()Lorg/apache/hadoop/hbase/Size;
       4: getstatic     #34                 // Field org/apache/hadoop/hbase/Size$Unit.MEGABYTE:Lorg/apache/hadoop/hbase/Size$Unit;
       7: invokevirtual #35                 // Method org/apache/hadoop/hbase/Size.get:(Lorg/apache/hadoop/hbase/Size$Unit;)D
      10: d2i
      11: ireturn

  public boolean hasMaxHeapMB();
    Code:
       0: iconst_1
       1: ireturn

  public int getStores();
    Code:
       0: aload_0
       1: getfield      #8                  // Field stores:I
       4: ireturn

  public int getStorefiles();
    Code:
       0: aload_0
       1: getfield      #9                  // Field storefiles:I
       4: ireturn

  public int getStoreUncompressedSizeMB();
    Code:
       0: aload_0
       1: getfield      #10                 // Field storeUncompressedSizeMB:I
       4: ireturn

  public int getStorefileSizeInMB();
    Code:
       0: aload_0
       1: getfield      #11                 // Field storefileSizeMB:I
       4: ireturn

  public int getStorefileSizeMB();
    Code:
       0: aload_0
       1: getfield      #11                 // Field storefileSizeMB:I
       4: ireturn

  public int getMemstoreSizeInMB();
    Code:
       0: aload_0
       1: getfield      #12                 // Field memstoreSizeMB:I
       4: ireturn

  public int getMemStoreSizeMB();
    Code:
       0: aload_0
       1: getfield      #12                 // Field memstoreSizeMB:I
       4: ireturn

  public int getStorefileIndexSizeInMB();
    Code:
       0: aload_0
       1: invokevirtual #53                 // Method getStorefileIndexSizeKB:()J
       4: bipush        10
       6: lshr
       7: l2i
       8: ireturn

  public long getStorefileIndexSizeKB();
    Code:
       0: aload_0
       1: getfield      #13                 // Field storefileIndexSizeKB:J
       4: lreturn

  public long getReadRequestsCount();
    Code:
       0: aload_0
       1: getfield      #14                 // Field readRequestsCount:J
       4: lreturn

  public long getCpRequestsCount();
    Code:
       0: aload_0
       1: getfield      #15                 // Field cpRequestsCount:J
       4: lreturn

  public long getFilteredReadRequestsCount();
    Code:
       0: aload_0
       1: getfield      #16                 // Field filteredReadRequestsCount:J
       4: lreturn

  public long getWriteRequestsCount();
    Code:
       0: aload_0
       1: getfield      #17                 // Field writeRequestsCount:J
       4: lreturn

  public int getRootIndexSizeKB();
    Code:
       0: aload_0
       1: getfield      #18                 // Field rootIndexSizeKB:I
       4: ireturn

  public int getTotalStaticIndexSizeKB();
    Code:
       0: aload_0
       1: getfield      #19                 // Field totalStaticIndexSizeKB:I
       4: ireturn

  public int getTotalStaticBloomSizeKB();
    Code:
       0: aload_0
       1: getfield      #20                 // Field totalStaticBloomSizeKB:I
       4: ireturn

  public long getTotalCompactingKVs();
    Code:
       0: aload_0
       1: getfield      #21                 // Field totalCompactingKVs:J
       4: lreturn

  public long getCurrentCompactedKVs();
    Code:
       0: aload_0
       1: getfield      #22                 // Field currentCompactedKVs:J
       4: lreturn

  public int getNumberOfRegions();
    Code:
       0: aload_0
       1: getfield      #23                 // Field metrics:Lorg/apache/hadoop/hbase/ServerMetrics;
       4: invokeinterface #25,  1           // InterfaceMethod org/apache/hadoop/hbase/ServerMetrics.getRegionMetrics:()Ljava/util/Map;
       9: invokeinterface #54,  1           // InterfaceMethod java/util/Map.size:()I
      14: ireturn

  public org.apache.hadoop.hbase.ServerName getServerName();
    Code:
       0: aload_0
       1: getfield      #23                 // Field metrics:Lorg/apache/hadoop/hbase/ServerMetrics;
       4: invokeinterface #55,  1           // InterfaceMethod org/apache/hadoop/hbase/ServerMetrics.getServerName:()Lorg/apache/hadoop/hbase/ServerName;
       9: areturn

  public long getRequestCountPerSecond();
    Code:
       0: aload_0
       1: getfield      #23                 // Field metrics:Lorg/apache/hadoop/hbase/ServerMetrics;
       4: invokeinterface #56,  1           // InterfaceMethod org/apache/hadoop/hbase/ServerMetrics.getRequestCountPerSecond:()J
       9: lreturn

  public long getRequestCount();
    Code:
       0: aload_0
       1: getfield      #23                 // Field metrics:Lorg/apache/hadoop/hbase/ServerMetrics;
       4: invokeinterface #57,  1           // InterfaceMethod org/apache/hadoop/hbase/ServerMetrics.getRequestCount:()J
       9: lreturn

  public org.apache.hadoop.hbase.Size getUsedHeapSize();
    Code:
       0: aload_0
       1: getfield      #23                 // Field metrics:Lorg/apache/hadoop/hbase/ServerMetrics;
       4: invokeinterface #58,  1           // InterfaceMethod org/apache/hadoop/hbase/ServerMetrics.getUsedHeapSize:()Lorg/apache/hadoop/hbase/Size;
       9: areturn

  public org.apache.hadoop.hbase.Size getMaxHeapSize();
    Code:
       0: aload_0
       1: getfield      #23                 // Field metrics:Lorg/apache/hadoop/hbase/ServerMetrics;
       4: invokeinterface #59,  1           // InterfaceMethod org/apache/hadoop/hbase/ServerMetrics.getMaxHeapSize:()Lorg/apache/hadoop/hbase/Size;
       9: areturn

  public int getInfoServerPort();
    Code:
       0: aload_0
       1: getfield      #23                 // Field metrics:Lorg/apache/hadoop/hbase/ServerMetrics;
       4: invokeinterface #60,  1           // InterfaceMethod org/apache/hadoop/hbase/ServerMetrics.getInfoServerPort:()I
       9: ireturn

  public java.util.List<org.apache.hadoop.hbase.replication.ReplicationLoadSource> getReplicationLoadSourceList();
    Code:
       0: aload_0
       1: getfield      #23                 // Field metrics:Lorg/apache/hadoop/hbase/ServerMetrics;
       4: invokeinterface #61,  1           // InterfaceMethod org/apache/hadoop/hbase/ServerMetrics.getReplicationLoadSourceList:()Ljava/util/List;
       9: areturn

  public java.util.Map<java.lang.String, java.util.List<org.apache.hadoop.hbase.replication.ReplicationLoadSource>> getReplicationLoadSourceMap();
    Code:
       0: aload_0
       1: getfield      #23                 // Field metrics:Lorg/apache/hadoop/hbase/ServerMetrics;
       4: invokeinterface #62,  1           // InterfaceMethod org/apache/hadoop/hbase/ServerMetrics.getReplicationLoadSourceMap:()Ljava/util/Map;
       9: areturn

  public org.apache.hadoop.hbase.replication.ReplicationLoadSink getReplicationLoadSink();
    Code:
       0: aload_0
       1: getfield      #23                 // Field metrics:Lorg/apache/hadoop/hbase/ServerMetrics;
       4: invokeinterface #63,  1           // InterfaceMethod org/apache/hadoop/hbase/ServerMetrics.getReplicationLoadSink:()Lorg/apache/hadoop/hbase/replication/ReplicationLoadSink;
       9: areturn

  public java.util.Map<byte[], org.apache.hadoop.hbase.RegionMetrics> getRegionMetrics();
    Code:
       0: aload_0
       1: getfield      #23                 // Field metrics:Lorg/apache/hadoop/hbase/ServerMetrics;
       4: invokeinterface #25,  1           // InterfaceMethod org/apache/hadoop/hbase/ServerMetrics.getRegionMetrics:()Ljava/util/Map;
       9: areturn

  public java.util.Set<java.lang.String> getCoprocessorNames();
    Code:
       0: aload_0
       1: getfield      #23                 // Field metrics:Lorg/apache/hadoop/hbase/ServerMetrics;
       4: invokeinterface #64,  1           // InterfaceMethod org/apache/hadoop/hbase/ServerMetrics.getCoprocessorNames:()Ljava/util/Set;
       9: areturn

  public long getReportTimestamp();
    Code:
       0: aload_0
       1: getfield      #23                 // Field metrics:Lorg/apache/hadoop/hbase/ServerMetrics;
       4: invokeinterface #65,  1           // InterfaceMethod org/apache/hadoop/hbase/ServerMetrics.getReportTimestamp:()J
       9: lreturn

  public long getLastReportTimestamp();
    Code:
       0: aload_0
       1: getfield      #23                 // Field metrics:Lorg/apache/hadoop/hbase/ServerMetrics;
       4: invokeinterface #66,  1           // InterfaceMethod org/apache/hadoop/hbase/ServerMetrics.getLastReportTimestamp:()J
       9: lreturn

  public int getLoad();
    Code:
       0: aload_0
       1: invokevirtual #67                 // Method getNumberOfRegions:()I
       4: ireturn

  public java.util.Map<byte[], org.apache.hadoop.hbase.RegionLoad> getRegionsLoad();
    Code:
       0: aload_0
       1: invokevirtual #68                 // Method getRegionMetrics:()Ljava/util/Map;
       4: invokeinterface #69,  1           // InterfaceMethod java/util/Map.entrySet:()Ljava/util/Set;
       9: invokeinterface #70,  1           // InterfaceMethod java/util/Set.stream:()Ljava/util/stream/Stream;
      14: invokedynamic #71,  0             // InvokeDynamic #0:apply:()Ljava/util/function/Function;
      19: invokedynamic #72,  0             // InvokeDynamic #1:apply:()Ljava/util/function/Function;
      24: invokedynamic #73,  0             // InvokeDynamic #2:apply:()Ljava/util/function/BinaryOperator;
      29: invokedynamic #74,  0             // InvokeDynamic #3:get:()Ljava/util/function/Supplier;
      34: invokestatic  #75                 // Method java/util/stream/Collectors.toMap:(Ljava/util/function/Function;Ljava/util/function/Function;Ljava/util/function/BinaryOperator;Ljava/util/function/Supplier;)Ljava/util/stream/Collector;
      37: invokeinterface #76,  2           // InterfaceMethod java/util/stream/Stream.collect:(Ljava/util/stream/Collector;)Ljava/lang/Object;
      42: checkcast     #77                 // class java/util/Map
      45: areturn

  public java.lang.String[] getRegionServerCoprocessors();
    Code:
       0: aload_0
       1: invokevirtual #78                 // Method getCoprocessorNames:()Ljava/util/Set;
       4: aload_0
       5: invokevirtual #78                 // Method getCoprocessorNames:()Ljava/util/Set;
       8: invokeinterface #79,  1           // InterfaceMethod java/util/Set.size:()I
      13: anewarray     #80                 // class java/lang/String
      16: invokeinterface #81,  2           // InterfaceMethod java/util/Set.toArray:([Ljava/lang/Object;)[Ljava/lang/Object;
      21: checkcast     #82                 // class "[Ljava/lang/String;"
      24: areturn

  public java.lang.String[] getRsCoprocessors();
    Code:
       0: aload_0
       1: invokevirtual #83                 // Method getRegionServerCoprocessors:()[Ljava/lang/String;
       4: areturn

  public double getRequestsPerSecond();
    Code:
       0: aload_0
       1: invokevirtual #49                 // Method getRequestCountPerSecond:()J
       4: l2d
       5: dreturn

  public java.lang.String toString();
    Code:
       0: new           #84                 // class java/lang/StringBuilder
       3: dup
       4: invokespecial #85                 // Method java/lang/StringBuilder."<init>":()V
       7: ldc           #86                 // String requestsPerSecond
       9: aload_0
      10: invokevirtual #87                 // Method getRequestsPerSecond:()D
      13: invokestatic  #88                 // Method java/lang/Double.valueOf:(D)Ljava/lang/Double;
      16: invokestatic  #89                 // Method org/apache/hadoop/hbase/util/Strings.appendKeyValue:(Ljava/lang/StringBuilder;Ljava/lang/String;Ljava/lang/Object;)Ljava/lang/StringBuilder;
      19: astore_1
      20: aload_1
      21: ldc           #90                 // String numberOfOnlineRegions
      23: aload_0
      24: invokevirtual #67                 // Method getNumberOfRegions:()I
      27: invokestatic  #91                 // Method java/lang/Integer.valueOf:(I)Ljava/lang/Integer;
      30: invokestatic  #89                 // Method org/apache/hadoop/hbase/util/Strings.appendKeyValue:(Ljava/lang/StringBuilder;Ljava/lang/String;Ljava/lang/Object;)Ljava/lang/StringBuilder;
      33: pop
      34: aload_1
      35: ldc           #92                 // String usedHeapMB
      37: aload_0
      38: invokevirtual #93                 // Method getUsedHeapMB:()I
      41: invokestatic  #91                 // Method java/lang/Integer.valueOf:(I)Ljava/lang/Integer;
      44: invokestatic  #89                 // Method org/apache/hadoop/hbase/util/Strings.appendKeyValue:(Ljava/lang/StringBuilder;Ljava/lang/String;Ljava/lang/Object;)Ljava/lang/StringBuilder;
      47: pop
      48: aload_1
      49: ldc           #94                 // String maxHeapMB
      51: aload_0
      52: invokevirtual #95                 // Method getMaxHeapMB:()I
      55: invokestatic  #91                 // Method java/lang/Integer.valueOf:(I)Ljava/lang/Integer;
      58: invokestatic  #89                 // Method org/apache/hadoop/hbase/util/Strings.appendKeyValue:(Ljava/lang/StringBuilder;Ljava/lang/String;Ljava/lang/Object;)Ljava/lang/StringBuilder;
      61: pop
      62: aload_1
      63: ldc           #96                 // String numberOfStores
      65: aload_0
      66: getfield      #8                  // Field stores:I
      69: invokestatic  #91                 // Method java/lang/Integer.valueOf:(I)Ljava/lang/Integer;
      72: invokestatic  #89                 // Method org/apache/hadoop/hbase/util/Strings.appendKeyValue:(Ljava/lang/StringBuilder;Ljava/lang/String;Ljava/lang/Object;)Ljava/lang/StringBuilder;
      75: pop
      76: aload_1
      77: ldc           #97                 // String numberOfStorefiles
      79: aload_0
      80: getfield      #9                  // Field storefiles:I
      83: invokestatic  #91                 // Method java/lang/Integer.valueOf:(I)Ljava/lang/Integer;
      86: invokestatic  #89                 // Method org/apache/hadoop/hbase/util/Strings.appendKeyValue:(Ljava/lang/StringBuilder;Ljava/lang/String;Ljava/lang/Object;)Ljava/lang/StringBuilder;
      89: pop
      90: aload_1
      91: ldc           #98                 // String storefileUncompressedSizeMB
      93: aload_0
      94: getfield      #10                 // Field storeUncompressedSizeMB:I
      97: invokestatic  #91                 // Method java/lang/Integer.valueOf:(I)Ljava/lang/Integer;
     100: invokestatic  #89                 // Method org/apache/hadoop/hbase/util/Strings.appendKeyValue:(Ljava/lang/StringBuilder;Ljava/lang/String;Ljava/lang/Object;)Ljava/lang/StringBuilder;
     103: pop
     104: aload_1
     105: ldc           #99                 // String storefileSizeMB
     107: aload_0
     108: getfield      #11                 // Field storefileSizeMB:I
     111: invokestatic  #91                 // Method java/lang/Integer.valueOf:(I)Ljava/lang/Integer;
     114: invokestatic  #89                 // Method org/apache/hadoop/hbase/util/Strings.appendKeyValue:(Ljava/lang/StringBuilder;Ljava/lang/String;Ljava/lang/Object;)Ljava/lang/StringBuilder;
     117: pop
     118: aload_0
     119: getfield      #10                 // Field storeUncompressedSizeMB:I
     122: ifeq          158
     125: aload_1
     126: ldc           #100                // String compressionRatio
     128: ldc           #101                // String %.4f
     130: iconst_1
     131: anewarray     #102                // class java/lang/Object
     134: dup
     135: iconst_0
     136: aload_0
     137: getfield      #11                 // Field storefileSizeMB:I
     140: i2f
     141: aload_0
     142: getfield      #10                 // Field storeUncompressedSizeMB:I
     145: i2f
     146: fdiv
     147: invokestatic  #103                // Method java/lang/Float.valueOf:(F)Ljava/lang/Float;
     150: aastore
     151: invokestatic  #104                // Method java/lang/String.format:(Ljava/lang/String;[Ljava/lang/Object;)Ljava/lang/String;
     154: invokestatic  #89                 // Method org/apache/hadoop/hbase/util/Strings.appendKeyValue:(Ljava/lang/StringBuilder;Ljava/lang/String;Ljava/lang/Object;)Ljava/lang/StringBuilder;
     157: pop
     158: aload_1
     159: ldc           #105                // String memstoreSizeMB
     161: aload_0
     162: getfield      #12                 // Field memstoreSizeMB:I
     165: invokestatic  #91                 // Method java/lang/Integer.valueOf:(I)Ljava/lang/Integer;
     168: invokestatic  #89                 // Method org/apache/hadoop/hbase/util/Strings.appendKeyValue:(Ljava/lang/StringBuilder;Ljava/lang/String;Ljava/lang/Object;)Ljava/lang/StringBuilder;
     171: pop
     172: aload_1
     173: ldc           #106                // String storefileIndexSizeKB
     175: aload_0
     176: getfield      #13                 // Field storefileIndexSizeKB:J
     179: invokestatic  #107                // Method java/lang/Long.valueOf:(J)Ljava/lang/Long;
     182: invokestatic  #89                 // Method org/apache/hadoop/hbase/util/Strings.appendKeyValue:(Ljava/lang/StringBuilder;Ljava/lang/String;Ljava/lang/Object;)Ljava/lang/StringBuilder;
     185: pop
     186: aload_1
     187: ldc           #108                // String readRequestsCount
     189: aload_0
     190: getfield      #14                 // Field readRequestsCount:J
     193: invokestatic  #107                // Method java/lang/Long.valueOf:(J)Ljava/lang/Long;
     196: invokestatic  #89                 // Method org/apache/hadoop/hbase/util/Strings.appendKeyValue:(Ljava/lang/StringBuilder;Ljava/lang/String;Ljava/lang/Object;)Ljava/lang/StringBuilder;
     199: pop
     200: aload_1
     201: ldc           #109                // String cpRequestsCount
     203: aload_0
     204: getfield      #15                 // Field cpRequestsCount:J
     207: invokestatic  #107                // Method java/lang/Long.valueOf:(J)Ljava/lang/Long;
     210: invokestatic  #89                 // Method org/apache/hadoop/hbase/util/Strings.appendKeyValue:(Ljava/lang/StringBuilder;Ljava/lang/String;Ljava/lang/Object;)Ljava/lang/StringBuilder;
     213: pop
     214: aload_1
     215: ldc           #110                // String filteredReadRequestsCount
     217: aload_0
     218: getfield      #16                 // Field filteredReadRequestsCount:J
     221: invokestatic  #107                // Method java/lang/Long.valueOf:(J)Ljava/lang/Long;
     224: invokestatic  #89                 // Method org/apache/hadoop/hbase/util/Strings.appendKeyValue:(Ljava/lang/StringBuilder;Ljava/lang/String;Ljava/lang/Object;)Ljava/lang/StringBuilder;
     227: pop
     228: aload_1
     229: ldc           #111                // String writeRequestsCount
     231: aload_0
     232: getfield      #17                 // Field writeRequestsCount:J
     235: invokestatic  #107                // Method java/lang/Long.valueOf:(J)Ljava/lang/Long;
     238: invokestatic  #89                 // Method org/apache/hadoop/hbase/util/Strings.appendKeyValue:(Ljava/lang/StringBuilder;Ljava/lang/String;Ljava/lang/Object;)Ljava/lang/StringBuilder;
     241: pop
     242: aload_1
     243: ldc           #112                // String rootIndexSizeKB
     245: aload_0
     246: getfield      #18                 // Field rootIndexSizeKB:I
     249: invokestatic  #91                 // Method java/lang/Integer.valueOf:(I)Ljava/lang/Integer;
     252: invokestatic  #89                 // Method org/apache/hadoop/hbase/util/Strings.appendKeyValue:(Ljava/lang/StringBuilder;Ljava/lang/String;Ljava/lang/Object;)Ljava/lang/StringBuilder;
     255: pop
     256: aload_1
     257: ldc           #113                // String totalStaticIndexSizeKB
     259: aload_0
     260: getfield      #19                 // Field totalStaticIndexSizeKB:I
     263: invokestatic  #91                 // Method java/lang/Integer.valueOf:(I)Ljava/lang/Integer;
     266: invokestatic  #89                 // Method org/apache/hadoop/hbase/util/Strings.appendKeyValue:(Ljava/lang/StringBuilder;Ljava/lang/String;Ljava/lang/Object;)Ljava/lang/StringBuilder;
     269: pop
     270: aload_1
     271: ldc           #114                // String totalStaticBloomSizeKB
     273: aload_0
     274: getfield      #20                 // Field totalStaticBloomSizeKB:I
     277: invokestatic  #91                 // Method java/lang/Integer.valueOf:(I)Ljava/lang/Integer;
     280: invokestatic  #89                 // Method org/apache/hadoop/hbase/util/Strings.appendKeyValue:(Ljava/lang/StringBuilder;Ljava/lang/String;Ljava/lang/Object;)Ljava/lang/StringBuilder;
     283: pop
     284: aload_1
     285: ldc           #115                // String totalCompactingKVs
     287: aload_0
     288: getfield      #21                 // Field totalCompactingKVs:J
     291: invokestatic  #107                // Method java/lang/Long.valueOf:(J)Ljava/lang/Long;
     294: invokestatic  #89                 // Method org/apache/hadoop/hbase/util/Strings.appendKeyValue:(Ljava/lang/StringBuilder;Ljava/lang/String;Ljava/lang/Object;)Ljava/lang/StringBuilder;
     297: pop
     298: aload_1
     299: ldc           #116                // String currentCompactedKVs
     301: aload_0
     302: getfield      #22                 // Field currentCompactedKVs:J
     305: invokestatic  #107                // Method java/lang/Long.valueOf:(J)Ljava/lang/Long;
     308: invokestatic  #89                 // Method org/apache/hadoop/hbase/util/Strings.appendKeyValue:(Ljava/lang/StringBuilder;Ljava/lang/String;Ljava/lang/Object;)Ljava/lang/StringBuilder;
     311: pop
     312: ldc           #118                // float NaNf
     314: fstore_2
     315: aload_0
     316: getfield      #21                 // Field totalCompactingKVs:J
     319: lconst_0
     320: lcmp
     321: ifle          342
     324: aload_0
     325: getfield      #22                 // Field currentCompactedKVs:J
     328: l2f
     329: aload_0
     330: getfield      #21                 // Field totalCompactingKVs:J
     333: l2f
     334: fdiv
     335: invokestatic  #103                // Method java/lang/Float.valueOf:(F)Ljava/lang/Float;
     338: invokevirtual #119                // Method java/lang/Float.floatValue:()F
     341: fstore_2
     342: aload_1
     343: ldc           #120                // String compactionProgressPct
     345: fload_2
     346: invokestatic  #103                // Method java/lang/Float.valueOf:(F)Ljava/lang/Float;
     349: invokestatic  #89                 // Method org/apache/hadoop/hbase/util/Strings.appendKeyValue:(Ljava/lang/StringBuilder;Ljava/lang/String;Ljava/lang/Object;)Ljava/lang/StringBuilder;
     352: pop
     353: aload_0
     354: invokevirtual #121                // Method getRsCoprocessors:()[Ljava/lang/String;
     357: astore_3
     358: aload_3
     359: ifnull        373
     362: aload_1
     363: ldc           #122                // String coprocessors
     365: aload_3
     366: invokestatic  #123                // Method java/util/Arrays.toString:([Ljava/lang/Object;)Ljava/lang/String;
     369: invokestatic  #89                 // Method org/apache/hadoop/hbase/util/Strings.appendKeyValue:(Ljava/lang/StringBuilder;Ljava/lang/String;Ljava/lang/Object;)Ljava/lang/StringBuilder;
     372: pop
     373: aload_1
     374: invokevirtual #124                // Method java/lang/StringBuilder.toString:()Ljava/lang/String;
     377: areturn

  public long getReportTime();
    Code:
       0: aload_0
       1: invokevirtual #125                // Method getReportTimestamp:()J
       4: lreturn

  public int hashCode();
    Code:
       0: bipush        15
       2: anewarray     #102                // class java/lang/Object
       5: dup
       6: iconst_0
       7: aload_0
       8: getfield      #8                  // Field stores:I
      11: invokestatic  #91                 // Method java/lang/Integer.valueOf:(I)Ljava/lang/Integer;
      14: aastore
      15: dup
      16: iconst_1
      17: aload_0
      18: getfield      #9                  // Field storefiles:I
      21: invokestatic  #91                 // Method java/lang/Integer.valueOf:(I)Ljava/lang/Integer;
      24: aastore
      25: dup
      26: iconst_2
      27: aload_0
      28: getfield      #10                 // Field storeUncompressedSizeMB:I
      31: invokestatic  #91                 // Method java/lang/Integer.valueOf:(I)Ljava/lang/Integer;
      34: aastore
      35: dup
      36: iconst_3
      37: aload_0
      38: getfield      #11                 // Field storefileSizeMB:I
      41: invokestatic  #91                 // Method java/lang/Integer.valueOf:(I)Ljava/lang/Integer;
      44: aastore
      45: dup
      46: iconst_4
      47: aload_0
      48: getfield      #12                 // Field memstoreSizeMB:I
      51: invokestatic  #91                 // Method java/lang/Integer.valueOf:(I)Ljava/lang/Integer;
      54: aastore
      55: dup
      56: iconst_5
      57: aload_0
      58: getfield      #13                 // Field storefileIndexSizeKB:J
      61: invokestatic  #107                // Method java/lang/Long.valueOf:(J)Ljava/lang/Long;
      64: aastore
      65: dup
      66: bipush        6
      68: aload_0
      69: getfield      #14                 // Field readRequestsCount:J
      72: invokestatic  #107                // Method java/lang/Long.valueOf:(J)Ljava/lang/Long;
      75: aastore
      76: dup
      77: bipush        7
      79: aload_0
      80: getfield      #15                 // Field cpRequestsCount:J
      83: invokestatic  #107                // Method java/lang/Long.valueOf:(J)Ljava/lang/Long;
      86: aastore
      87: dup
      88: bipush        8
      90: aload_0
      91: getfield      #16                 // Field filteredReadRequestsCount:J
      94: invokestatic  #107                // Method java/lang/Long.valueOf:(J)Ljava/lang/Long;
      97: aastore
      98: dup
      99: bipush        9
     101: aload_0
     102: getfield      #17                 // Field writeRequestsCount:J
     105: invokestatic  #107                // Method java/lang/Long.valueOf:(J)Ljava/lang/Long;
     108: aastore
     109: dup
     110: bipush        10
     112: aload_0
     113: getfield      #18                 // Field rootIndexSizeKB:I
     116: invokestatic  #91                 // Method java/lang/Integer.valueOf:(I)Ljava/lang/Integer;
     119: aastore
     120: dup
     121: bipush        11
     123: aload_0
     124: getfield      #19                 // Field totalStaticIndexSizeKB:I
     127: invokestatic  #91                 // Method java/lang/Integer.valueOf:(I)Ljava/lang/Integer;
     130: aastore
     131: dup
     132: bipush        12
     134: aload_0
     135: getfield      #20                 // Field totalStaticBloomSizeKB:I
     138: invokestatic  #91                 // Method java/lang/Integer.valueOf:(I)Ljava/lang/Integer;
     141: aastore
     142: dup
     143: bipush        13
     145: aload_0
     146: getfield      #21                 // Field totalCompactingKVs:J
     149: invokestatic  #107                // Method java/lang/Long.valueOf:(J)Ljava/lang/Long;
     152: aastore
     153: dup
     154: bipush        14
     156: aload_0
     157: getfield      #22                 // Field currentCompactedKVs:J
     160: invokestatic  #107                // Method java/lang/Long.valueOf:(J)Ljava/lang/Long;
     163: aastore
     164: invokestatic  #126                // Method org/apache/hbase/thirdparty/com/google/common/base/Objects.hashCode:([Ljava/lang/Object;)I
     167: ireturn

  public boolean equals(java.lang.Object);
    Code:
       0: aload_1
       1: aload_0
       2: if_acmpne     7
       5: iconst_1
       6: ireturn
       7: aload_1
       8: instanceof    #127                // class org/apache/hadoop/hbase/ServerLoad
      11: ifeq          197
      14: aload_1
      15: checkcast     #127                // class org/apache/hadoop/hbase/ServerLoad
      18: astore_2
      19: aload_0
      20: getfield      #8                  // Field stores:I
      23: aload_2
      24: getfield      #8                  // Field stores:I
      27: if_icmpne     195
      30: aload_0
      31: getfield      #9                  // Field storefiles:I
      34: aload_2
      35: getfield      #9                  // Field storefiles:I
      38: if_icmpne     195
      41: aload_0
      42: getfield      #10                 // Field storeUncompressedSizeMB:I
      45: aload_2
      46: getfield      #10                 // Field storeUncompressedSizeMB:I
      49: if_icmpne     195
      52: aload_0
      53: getfield      #11                 // Field storefileSizeMB:I
      56: aload_2
      57: getfield      #11                 // Field storefileSizeMB:I
      60: if_icmpne     195
      63: aload_0
      64: getfield      #12                 // Field memstoreSizeMB:I
      67: aload_2
      68: getfield      #12                 // Field memstoreSizeMB:I
      71: if_icmpne     195
      74: aload_0
      75: getfield      #13                 // Field storefileIndexSizeKB:J
      78: aload_2
      79: getfield      #13                 // Field storefileIndexSizeKB:J
      82: lcmp
      83: ifne          195
      86: aload_0
      87: getfield      #14                 // Field readRequestsCount:J
      90: aload_2
      91: getfield      #14                 // Field readRequestsCount:J
      94: lcmp
      95: ifne          195
      98: aload_0
      99: getfield      #15                 // Field cpRequestsCount:J
     102: aload_2
     103: getfield      #15                 // Field cpRequestsCount:J
     106: lcmp
     107: ifne          195
     110: aload_0
     111: getfield      #16                 // Field filteredReadRequestsCount:J
     114: aload_2
     115: getfield      #16                 // Field filteredReadRequestsCount:J
     118: lcmp
     119: ifne          195
     122: aload_0
     123: getfield      #17                 // Field writeRequestsCount:J
     126: aload_2
     127: getfield      #17                 // Field writeRequestsCount:J
     130: lcmp
     131: ifne          195
     134: aload_0
     135: getfield      #18                 // Field rootIndexSizeKB:I
     138: aload_2
     139: getfield      #18                 // Field rootIndexSizeKB:I
     142: if_icmpne     195
     145: aload_0
     146: getfield      #19                 // Field totalStaticIndexSizeKB:I
     149: aload_2
     150: getfield      #19                 // Field totalStaticIndexSizeKB:I
     153: if_icmpne     195
     156: aload_0
     157: getfield      #20                 // Field totalStaticBloomSizeKB:I
     160: aload_2
     161: getfield      #20                 // Field totalStaticBloomSizeKB:I
     164: if_icmpne     195
     167: aload_0
     168: getfield      #21                 // Field totalCompactingKVs:J
     171: aload_2
     172: getfield      #21                 // Field totalCompactingKVs:J
     175: lcmp
     176: ifne          195
     179: aload_0
     180: getfield      #22                 // Field currentCompactedKVs:J
     183: aload_2
     184: getfield      #22                 // Field currentCompactedKVs:J
     187: lcmp
     188: ifne          195
     191: iconst_1
     192: goto          196
     195: iconst_0
     196: ireturn
     197: iconst_0
     198: ireturn

  static {};
    Code:
       0: new           #127                // class org/apache/hadoop/hbase/ServerLoad
       3: dup
       4: ldc           #1                  // String localhost,1,1
       6: invokestatic  #2                  // Method org/apache/hadoop/hbase/ServerName.valueOf:(Ljava/lang/String;)Lorg/apache/hadoop/hbase/ServerName;
       9: invokestatic  #137                // Method org/apache/hadoop/hbase/shaded/protobuf/generated/ClusterStatusProtos$ServerLoad.newBuilder:()Lorg/apache/hadoop/hbase/shaded/protobuf/generated/ClusterStatusProtos$ServerLoad$Builder;
      12: invokevirtual #138                // Method org/apache/hadoop/hbase/shaded/protobuf/generated/ClusterStatusProtos$ServerLoad$Builder.build:()Lorg/apache/hadoop/hbase/shaded/protobuf/generated/ClusterStatusProtos$ServerLoad;
      15: invokespecial #3                  // Method "<init>":(Lorg/apache/hadoop/hbase/ServerName;Lorg/apache/hadoop/hbase/shaded/protobuf/generated/ClusterStatusProtos$ServerLoad;)V
      18: putstatic     #139                // Field EMPTY_SERVERLOAD:Lorg/apache/hadoop/hbase/ServerLoad;
      21: return
}
