Compiled from "ShadedAccessControlUtil.java"
public class org.apache.hadoop.hbase.security.access.ShadedAccessControlUtil {
  public org.apache.hadoop.hbase.security.access.ShadedAccessControlUtil();
    Code:
       0: aload_0
       1: invokespecial #1                  // Method java/lang/Object."<init>":()V
       4: return

  public static org.apache.hadoop.hbase.shaded.protobuf.generated.AccessControlProtos$Permission$Action toPermissionAction(org.apache.hadoop.hbase.security.access.Permission$Action);
    Code:
       0: getstatic     #2                  // Field org/apache/hadoop/hbase/security/access/ShadedAccessControlUtil$1.$SwitchMap$org$apache$hadoop$hbase$security$access$Permission$Action:[I
       3: aload_0
       4: invokevirtual #3                  // Method org/apache/hadoop/hbase/security/access/Permission$Action.ordinal:()I
       7: iaload
       8: tableswitch   { // 1 to 5
                     1: 44
                     2: 48
                     3: 52
                     4: 56
                     5: 60
               default: 64
          }
      44: getstatic     #4                  // Field org/apache/hadoop/hbase/shaded/protobuf/generated/AccessControlProtos$Permission$Action.READ:Lorg/apache/hadoop/hbase/shaded/protobuf/generated/AccessControlProtos$Permission$Action;
      47: areturn
      48: getstatic     #5                  // Field org/apache/hadoop/hbase/shaded/protobuf/generated/AccessControlProtos$Permission$Action.WRITE:Lorg/apache/hadoop/hbase/shaded/protobuf/generated/AccessControlProtos$Permission$Action;
      51: areturn
      52: getstatic     #6                  // Field org/apache/hadoop/hbase/shaded/protobuf/generated/AccessControlProtos$Permission$Action.EXEC:Lorg/apache/hadoop/hbase/shaded/protobuf/generated/AccessControlProtos$Permission$Action;
      55: areturn
      56: getstatic     #7                  // Field org/apache/hadoop/hbase/shaded/protobuf/generated/AccessControlProtos$Permission$Action.CREATE:Lorg/apache/hadoop/hbase/shaded/protobuf/generated/AccessControlProtos$Permission$Action;
      59: areturn
      60: getstatic     #8                  // Field org/apache/hadoop/hbase/shaded/protobuf/generated/AccessControlProtos$Permission$Action.ADMIN:Lorg/apache/hadoop/hbase/shaded/protobuf/generated/AccessControlProtos$Permission$Action;
      63: areturn
      64: new           #9                  // class java/lang/IllegalArgumentException
      67: dup
      68: new           #10                 // class java/lang/StringBuilder
      71: dup
      72: invokespecial #11                 // Method java/lang/StringBuilder."<init>":()V
      75: ldc           #12                 // String Unknown action value
      77: invokevirtual #13                 // Method java/lang/StringBuilder.append:(Ljava/lang/String;)Ljava/lang/StringBuilder;
      80: aload_0
      81: invokevirtual #14                 // Method org/apache/hadoop/hbase/security/access/Permission$Action.name:()Ljava/lang/String;
      84: invokevirtual #13                 // Method java/lang/StringBuilder.append:(Ljava/lang/String;)Ljava/lang/StringBuilder;
      87: invokevirtual #15                 // Method java/lang/StringBuilder.toString:()Ljava/lang/String;
      90: invokespecial #16                 // Method java/lang/IllegalArgumentException."<init>":(Ljava/lang/String;)V
      93: athrow

  public static org.apache.hadoop.hbase.security.access.Permission$Action toPermissionAction(org.apache.hadoop.hbase.shaded.protobuf.generated.AccessControlProtos$Permission$Action);
    Code:
       0: getstatic     #17                 // Field org/apache/hadoop/hbase/security/access/ShadedAccessControlUtil$1.$SwitchMap$org$apache$hadoop$hbase$shaded$protobuf$generated$AccessControlProtos$Permission$Action:[I
       3: aload_0
       4: invokevirtual #18                 // Method org/apache/hadoop/hbase/shaded/protobuf/generated/AccessControlProtos$Permission$Action.ordinal:()I
       7: iaload
       8: tableswitch   { // 1 to 5
                     1: 44
                     2: 48
                     3: 52
                     4: 56
                     5: 60
               default: 64
          }
      44: getstatic     #19                 // Field org/apache/hadoop/hbase/security/access/Permission$Action.READ:Lorg/apache/hadoop/hbase/security/access/Permission$Action;
      47: areturn
      48: getstatic     #20                 // Field org/apache/hadoop/hbase/security/access/Permission$Action.WRITE:Lorg/apache/hadoop/hbase/security/access/Permission$Action;
      51: areturn
      52: getstatic     #21                 // Field org/apache/hadoop/hbase/security/access/Permission$Action.EXEC:Lorg/apache/hadoop/hbase/security/access/Permission$Action;
      55: areturn
      56: getstatic     #22                 // Field org/apache/hadoop/hbase/security/access/Permission$Action.CREATE:Lorg/apache/hadoop/hbase/security/access/Permission$Action;
      59: areturn
      60: getstatic     #23                 // Field org/apache/hadoop/hbase/security/access/Permission$Action.ADMIN:Lorg/apache/hadoop/hbase/security/access/Permission$Action;
      63: areturn
      64: new           #9                  // class java/lang/IllegalArgumentException
      67: dup
      68: new           #10                 // class java/lang/StringBuilder
      71: dup
      72: invokespecial #11                 // Method java/lang/StringBuilder."<init>":()V
      75: ldc           #12                 // String Unknown action value
      77: invokevirtual #13                 // Method java/lang/StringBuilder.append:(Ljava/lang/String;)Ljava/lang/StringBuilder;
      80: aload_0
      81: invokevirtual #24                 // Method org/apache/hadoop/hbase/shaded/protobuf/generated/AccessControlProtos$Permission$Action.name:()Ljava/lang/String;
      84: invokevirtual #13                 // Method java/lang/StringBuilder.append:(Ljava/lang/String;)Ljava/lang/StringBuilder;
      87: invokevirtual #15                 // Method java/lang/StringBuilder.toString:()Ljava/lang/String;
      90: invokespecial #16                 // Method java/lang/IllegalArgumentException."<init>":(Ljava/lang/String;)V
      93: athrow

  public static org.apache.hadoop.hbase.security.access.Permission$Action[] toPermissionActions(java.util.List<org.apache.hadoop.hbase.shaded.protobuf.generated.AccessControlProtos$Permission$Action>);
    Code:
       0: aload_0
       1: invokeinterface #25,  1           // InterfaceMethod java/util/List.size:()I
       6: anewarray     #26                 // class org/apache/hadoop/hbase/security/access/Permission$Action
       9: astore_1
      10: iconst_0
      11: istore_2
      12: iload_2
      13: aload_0
      14: invokeinterface #25,  1           // InterfaceMethod java/util/List.size:()I
      19: if_icmpge     44
      22: aload_1
      23: iload_2
      24: aload_0
      25: iload_2
      26: invokeinterface #27,  2           // InterfaceMethod java/util/List.get:(I)Ljava/lang/Object;
      31: checkcast     #28                 // class org/apache/hadoop/hbase/shaded/protobuf/generated/AccessControlProtos$Permission$Action
      34: invokestatic  #29                 // Method toPermissionAction:(Lorg/apache/hadoop/hbase/shaded/protobuf/generated/AccessControlProtos$Permission$Action;)Lorg/apache/hadoop/hbase/security/access/Permission$Action;
      37: aastore
      38: iinc          2, 1
      41: goto          12
      44: aload_1
      45: areturn

  public static org.apache.hadoop.hbase.TableName toTableName(org.apache.hadoop.hbase.shaded.protobuf.generated.HBaseProtos$TableName);
    Code:
       0: aload_0
       1: invokevirtual #30                 // Method org/apache/hadoop/hbase/shaded/protobuf/generated/HBaseProtos$TableName.getNamespace:()Lorg/apache/hbase/thirdparty/com/google/protobuf/ByteString;
       4: invokevirtual #31                 // Method org/apache/hbase/thirdparty/com/google/protobuf/ByteString.asReadOnlyByteBuffer:()Ljava/nio/ByteBuffer;
       7: aload_0
       8: invokevirtual #32                 // Method org/apache/hadoop/hbase/shaded/protobuf/generated/HBaseProtos$TableName.getQualifier:()Lorg/apache/hbase/thirdparty/com/google/protobuf/ByteString;
      11: invokevirtual #31                 // Method org/apache/hbase/thirdparty/com/google/protobuf/ByteString.asReadOnlyByteBuffer:()Ljava/nio/ByteBuffer;
      14: invokestatic  #33                 // Method org/apache/hadoop/hbase/TableName.valueOf:(Ljava/nio/ByteBuffer;Ljava/nio/ByteBuffer;)Lorg/apache/hadoop/hbase/TableName;
      17: areturn

  public static org.apache.hadoop.hbase.shaded.protobuf.generated.HBaseProtos$TableName toProtoTableName(org.apache.hadoop.hbase.TableName);
    Code:
       0: invokestatic  #34                 // Method org/apache/hadoop/hbase/shaded/protobuf/generated/HBaseProtos$TableName.newBuilder:()Lorg/apache/hadoop/hbase/shaded/protobuf/generated/HBaseProtos$TableName$Builder;
       3: aload_0
       4: invokevirtual #35                 // Method org/apache/hadoop/hbase/TableName.getNamespace:()[B
       7: invokestatic  #36                 // Method org/apache/hbase/thirdparty/com/google/protobuf/ByteString.copyFrom:([B)Lorg/apache/hbase/thirdparty/com/google/protobuf/ByteString;
      10: invokevirtual #37                 // Method org/apache/hadoop/hbase/shaded/protobuf/generated/HBaseProtos$TableName$Builder.setNamespace:(Lorg/apache/hbase/thirdparty/com/google/protobuf/ByteString;)Lorg/apache/hadoop/hbase/shaded/protobuf/generated/HBaseProtos$TableName$Builder;
      13: aload_0
      14: invokevirtual #38                 // Method org/apache/hadoop/hbase/TableName.getQualifier:()[B
      17: invokestatic  #36                 // Method org/apache/hbase/thirdparty/com/google/protobuf/ByteString.copyFrom:([B)Lorg/apache/hbase/thirdparty/com/google/protobuf/ByteString;
      20: invokevirtual #39                 // Method org/apache/hadoop/hbase/shaded/protobuf/generated/HBaseProtos$TableName$Builder.setQualifier:(Lorg/apache/hbase/thirdparty/com/google/protobuf/ByteString;)Lorg/apache/hadoop/hbase/shaded/protobuf/generated/HBaseProtos$TableName$Builder;
      23: invokevirtual #40                 // Method org/apache/hadoop/hbase/shaded/protobuf/generated/HBaseProtos$TableName$Builder.build:()Lorg/apache/hadoop/hbase/shaded/protobuf/generated/HBaseProtos$TableName;
      26: areturn

  public static org.apache.hadoop.hbase.security.access.Permission toPermission(org.apache.hadoop.hbase.shaded.protobuf.generated.AccessControlProtos$Permission);
    Code:
       0: aload_0
       1: invokevirtual #41                 // Method org/apache/hadoop/hbase/shaded/protobuf/generated/AccessControlProtos$Permission.getType:()Lorg/apache/hadoop/hbase/shaded/protobuf/generated/AccessControlProtos$Permission$Type;
       4: getstatic     #42                 // Field org/apache/hadoop/hbase/shaded/protobuf/generated/AccessControlProtos$Permission$Type.Global:Lorg/apache/hadoop/hbase/shaded/protobuf/generated/AccessControlProtos$Permission$Type;
       7: if_acmpne     34
      10: aload_0
      11: invokevirtual #43                 // Method org/apache/hadoop/hbase/shaded/protobuf/generated/AccessControlProtos$Permission.getGlobalPermission:()Lorg/apache/hadoop/hbase/shaded/protobuf/generated/AccessControlProtos$GlobalPermission;
      14: astore_1
      15: aload_1
      16: invokevirtual #44                 // Method org/apache/hadoop/hbase/shaded/protobuf/generated/AccessControlProtos$GlobalPermission.getActionList:()Ljava/util/List;
      19: invokestatic  #45                 // Method toPermissionActions:(Ljava/util/List;)[Lorg/apache/hadoop/hbase/security/access/Permission$Action;
      22: astore_2
      23: invokestatic  #46                 // Method org/apache/hadoop/hbase/security/access/Permission.newBuilder:()Lorg/apache/hadoop/hbase/security/access/Permission$Builder;
      26: aload_2
      27: invokevirtual #47                 // Method org/apache/hadoop/hbase/security/access/Permission$Builder.withActions:([Lorg/apache/hadoop/hbase/security/access/Permission$Action;)Lorg/apache/hadoop/hbase/security/access/Permission$Builder;
      30: invokevirtual #48                 // Method org/apache/hadoop/hbase/security/access/Permission$Builder.build:()Lorg/apache/hadoop/hbase/security/access/Permission;
      33: areturn
      34: aload_0
      35: invokevirtual #41                 // Method org/apache/hadoop/hbase/shaded/protobuf/generated/AccessControlProtos$Permission.getType:()Lorg/apache/hadoop/hbase/shaded/protobuf/generated/AccessControlProtos$Permission$Type;
      38: getstatic     #49                 // Field org/apache/hadoop/hbase/shaded/protobuf/generated/AccessControlProtos$Permission$Type.Namespace:Lorg/apache/hadoop/hbase/shaded/protobuf/generated/AccessControlProtos$Permission$Type;
      41: if_acmpne     94
      44: aload_0
      45: invokevirtual #50                 // Method org/apache/hadoop/hbase/shaded/protobuf/generated/AccessControlProtos$Permission.getNamespacePermission:()Lorg/apache/hadoop/hbase/shaded/protobuf/generated/AccessControlProtos$NamespacePermission;
      48: astore_1
      49: aload_1
      50: invokevirtual #51                 // Method org/apache/hadoop/hbase/shaded/protobuf/generated/AccessControlProtos$NamespacePermission.getActionList:()Ljava/util/List;
      53: invokestatic  #45                 // Method toPermissionActions:(Ljava/util/List;)[Lorg/apache/hadoop/hbase/security/access/Permission$Action;
      56: astore_2
      57: aload_0
      58: invokevirtual #52                 // Method org/apache/hadoop/hbase/shaded/protobuf/generated/AccessControlProtos$Permission.hasNamespacePermission:()Z
      61: ifne          74
      64: new           #53                 // class java/lang/IllegalStateException
      67: dup
      68: ldc           #54                 // String Namespace must not be empty in NamespacePermission
      70: invokespecial #55                 // Method java/lang/IllegalStateException."<init>":(Ljava/lang/String;)V
      73: athrow
      74: aload_1
      75: invokevirtual #56                 // Method org/apache/hadoop/hbase/shaded/protobuf/generated/AccessControlProtos$NamespacePermission.getNamespaceName:()Lorg/apache/hbase/thirdparty/com/google/protobuf/ByteString;
      78: invokevirtual #57                 // Method org/apache/hbase/thirdparty/com/google/protobuf/ByteString.toStringUtf8:()Ljava/lang/String;
      81: astore_3
      82: aload_3
      83: invokestatic  #58                 // Method org/apache/hadoop/hbase/security/access/Permission.newBuilder:(Ljava/lang/String;)Lorg/apache/hadoop/hbase/security/access/Permission$Builder;
      86: aload_2
      87: invokevirtual #47                 // Method org/apache/hadoop/hbase/security/access/Permission$Builder.withActions:([Lorg/apache/hadoop/hbase/security/access/Permission$Action;)Lorg/apache/hadoop/hbase/security/access/Permission$Builder;
      90: invokevirtual #48                 // Method org/apache/hadoop/hbase/security/access/Permission$Builder.build:()Lorg/apache/hadoop/hbase/security/access/Permission;
      93: areturn
      94: aload_0
      95: invokevirtual #41                 // Method org/apache/hadoop/hbase/shaded/protobuf/generated/AccessControlProtos$Permission.getType:()Lorg/apache/hadoop/hbase/shaded/protobuf/generated/AccessControlProtos$Permission$Type;
      98: getstatic     #59                 // Field org/apache/hadoop/hbase/shaded/protobuf/generated/AccessControlProtos$Permission$Type.Table:Lorg/apache/hadoop/hbase/shaded/protobuf/generated/AccessControlProtos$Permission$Type;
     101: if_acmpne     201
     104: aload_0
     105: invokevirtual #60                 // Method org/apache/hadoop/hbase/shaded/protobuf/generated/AccessControlProtos$Permission.getTablePermission:()Lorg/apache/hadoop/hbase/shaded/protobuf/generated/AccessControlProtos$TablePermission;
     108: astore_1
     109: aload_1
     110: invokevirtual #61                 // Method org/apache/hadoop/hbase/shaded/protobuf/generated/AccessControlProtos$TablePermission.getActionList:()Ljava/util/List;
     113: invokestatic  #45                 // Method toPermissionActions:(Ljava/util/List;)[Lorg/apache/hadoop/hbase/security/access/Permission$Action;
     116: astore_2
     117: aconst_null
     118: astore_3
     119: aconst_null
     120: astore        4
     122: aload_1
     123: invokevirtual #62                 // Method org/apache/hadoop/hbase/shaded/protobuf/generated/AccessControlProtos$TablePermission.hasTableName:()Z
     126: ifne          139
     129: new           #53                 // class java/lang/IllegalStateException
     132: dup
     133: ldc           #63                 // String TableName cannot be empty
     135: invokespecial #55                 // Method java/lang/IllegalStateException."<init>":(Ljava/lang/String;)V
     138: athrow
     139: aload_1
     140: invokevirtual #64                 // Method org/apache/hadoop/hbase/shaded/protobuf/generated/AccessControlProtos$TablePermission.getTableName:()Lorg/apache/hadoop/hbase/shaded/protobuf/generated/HBaseProtos$TableName;
     143: invokestatic  #65                 // Method toTableName:(Lorg/apache/hadoop/hbase/shaded/protobuf/generated/HBaseProtos$TableName;)Lorg/apache/hadoop/hbase/TableName;
     146: astore        5
     148: aload_1
     149: invokevirtual #66                 // Method org/apache/hadoop/hbase/shaded/protobuf/generated/AccessControlProtos$TablePermission.hasFamily:()Z
     152: ifeq          164
     155: aload_1
     156: invokevirtual #67                 // Method org/apache/hadoop/hbase/shaded/protobuf/generated/AccessControlProtos$TablePermission.getFamily:()Lorg/apache/hbase/thirdparty/com/google/protobuf/ByteString;
     159: invokevirtual #68                 // Method org/apache/hbase/thirdparty/com/google/protobuf/ByteString.toByteArray:()[B
     162: astore        4
     164: aload_1
     165: invokevirtual #69                 // Method org/apache/hadoop/hbase/shaded/protobuf/generated/AccessControlProtos$TablePermission.hasQualifier:()Z
     168: ifeq          179
     171: aload_1
     172: invokevirtual #70                 // Method org/apache/hadoop/hbase/shaded/protobuf/generated/AccessControlProtos$TablePermission.getQualifier:()Lorg/apache/hbase/thirdparty/com/google/protobuf/ByteString;
     175: invokevirtual #68                 // Method org/apache/hbase/thirdparty/com/google/protobuf/ByteString.toByteArray:()[B
     178: astore_3
     179: aload         5
     181: invokestatic  #71                 // Method org/apache/hadoop/hbase/security/access/Permission.newBuilder:(Lorg/apache/hadoop/hbase/TableName;)Lorg/apache/hadoop/hbase/security/access/Permission$Builder;
     184: aload         4
     186: invokevirtual #72                 // Method org/apache/hadoop/hbase/security/access/Permission$Builder.withFamily:([B)Lorg/apache/hadoop/hbase/security/access/Permission$Builder;
     189: aload_3
     190: invokevirtual #73                 // Method org/apache/hadoop/hbase/security/access/Permission$Builder.withQualifier:([B)Lorg/apache/hadoop/hbase/security/access/Permission$Builder;
     193: aload_2
     194: invokevirtual #47                 // Method org/apache/hadoop/hbase/security/access/Permission$Builder.withActions:([Lorg/apache/hadoop/hbase/security/access/Permission$Action;)Lorg/apache/hadoop/hbase/security/access/Permission$Builder;
     197: invokevirtual #48                 // Method org/apache/hadoop/hbase/security/access/Permission$Builder.build:()Lorg/apache/hadoop/hbase/security/access/Permission;
     200: areturn
     201: new           #53                 // class java/lang/IllegalStateException
     204: dup
     205: new           #10                 // class java/lang/StringBuilder
     208: dup
     209: invokespecial #11                 // Method java/lang/StringBuilder."<init>":()V
     212: ldc           #74                 // String Unrecognize Perm Type:
     214: invokevirtual #13                 // Method java/lang/StringBuilder.append:(Ljava/lang/String;)Ljava/lang/StringBuilder;
     217: aload_0
     218: invokevirtual #41                 // Method org/apache/hadoop/hbase/shaded/protobuf/generated/AccessControlProtos$Permission.getType:()Lorg/apache/hadoop/hbase/shaded/protobuf/generated/AccessControlProtos$Permission$Type;
     221: invokevirtual #75                 // Method java/lang/StringBuilder.append:(Ljava/lang/Object;)Ljava/lang/StringBuilder;
     224: invokevirtual #15                 // Method java/lang/StringBuilder.toString:()Ljava/lang/String;
     227: invokespecial #55                 // Method java/lang/IllegalStateException."<init>":(Ljava/lang/String;)V
     230: athrow

  public static org.apache.hadoop.hbase.shaded.protobuf.generated.AccessControlProtos$Permission toPermission(org.apache.hadoop.hbase.security.access.Permission);
    Code:
       0: invokestatic  #76                 // Method org/apache/hadoop/hbase/shaded/protobuf/generated/AccessControlProtos$Permission.newBuilder:()Lorg/apache/hadoop/hbase/shaded/protobuf/generated/AccessControlProtos$Permission$Builder;
       3: astore_1
       4: aload_0
       5: instanceof    #77                 // class org/apache/hadoop/hbase/security/access/NamespacePermission
       8: ifeq          102
      11: aload_0
      12: checkcast     #77                 // class org/apache/hadoop/hbase/security/access/NamespacePermission
      15: astore_2
      16: aload_1
      17: getstatic     #49                 // Field org/apache/hadoop/hbase/shaded/protobuf/generated/AccessControlProtos$Permission$Type.Namespace:Lorg/apache/hadoop/hbase/shaded/protobuf/generated/AccessControlProtos$Permission$Type;
      20: invokevirtual #78                 // Method org/apache/hadoop/hbase/shaded/protobuf/generated/AccessControlProtos$Permission$Builder.setType:(Lorg/apache/hadoop/hbase/shaded/protobuf/generated/AccessControlProtos$Permission$Type;)Lorg/apache/hadoop/hbase/shaded/protobuf/generated/AccessControlProtos$Permission$Builder;
      23: pop
      24: invokestatic  #79                 // Method org/apache/hadoop/hbase/shaded/protobuf/generated/AccessControlProtos$NamespacePermission.newBuilder:()Lorg/apache/hadoop/hbase/shaded/protobuf/generated/AccessControlProtos$NamespacePermission$Builder;
      27: astore_3
      28: aload_3
      29: aload_2
      30: invokevirtual #80                 // Method org/apache/hadoop/hbase/security/access/NamespacePermission.getNamespace:()Ljava/lang/String;
      33: invokestatic  #81                 // Method org/apache/hbase/thirdparty/com/google/protobuf/ByteString.copyFromUtf8:(Ljava/lang/String;)Lorg/apache/hbase/thirdparty/com/google/protobuf/ByteString;
      36: invokevirtual #82                 // Method org/apache/hadoop/hbase/shaded/protobuf/generated/AccessControlProtos$NamespacePermission$Builder.setNamespaceName:(Lorg/apache/hbase/thirdparty/com/google/protobuf/ByteString;)Lorg/apache/hadoop/hbase/shaded/protobuf/generated/AccessControlProtos$NamespacePermission$Builder;
      39: pop
      40: aload_0
      41: invokevirtual #83                 // Method org/apache/hadoop/hbase/security/access/Permission.getActions:()[Lorg/apache/hadoop/hbase/security/access/Permission$Action;
      44: astore        4
      46: aload         4
      48: ifnull        93
      51: aload         4
      53: astore        5
      55: aload         5
      57: arraylength
      58: istore        6
      60: iconst_0
      61: istore        7
      63: iload         7
      65: iload         6
      67: if_icmpge     93
      70: aload         5
      72: iload         7
      74: aaload
      75: astore        8
      77: aload_3
      78: aload         8
      80: invokestatic  #84                 // Method toPermissionAction:(Lorg/apache/hadoop/hbase/security/access/Permission$Action;)Lorg/apache/hadoop/hbase/shaded/protobuf/generated/AccessControlProtos$Permission$Action;
      83: invokevirtual #85                 // Method org/apache/hadoop/hbase/shaded/protobuf/generated/AccessControlProtos$NamespacePermission$Builder.addAction:(Lorg/apache/hadoop/hbase/shaded/protobuf/generated/AccessControlProtos$Permission$Action;)Lorg/apache/hadoop/hbase/shaded/protobuf/generated/AccessControlProtos$NamespacePermission$Builder;
      86: pop
      87: iinc          7, 1
      90: goto          63
      93: aload_1
      94: aload_3
      95: invokevirtual #86                 // Method org/apache/hadoop/hbase/shaded/protobuf/generated/AccessControlProtos$Permission$Builder.setNamespacePermission:(Lorg/apache/hadoop/hbase/shaded/protobuf/generated/AccessControlProtos$NamespacePermission$Builder;)Lorg/apache/hadoop/hbase/shaded/protobuf/generated/AccessControlProtos$Permission$Builder;
      98: pop
      99: goto          306
     102: aload_0
     103: instanceof    #87                 // class org/apache/hadoop/hbase/security/access/TablePermission
     106: ifeq          238
     109: aload_0
     110: checkcast     #87                 // class org/apache/hadoop/hbase/security/access/TablePermission
     113: astore_2
     114: aload_1
     115: getstatic     #59                 // Field org/apache/hadoop/hbase/shaded/protobuf/generated/AccessControlProtos$Permission$Type.Table:Lorg/apache/hadoop/hbase/shaded/protobuf/generated/AccessControlProtos$Permission$Type;
     118: invokevirtual #78                 // Method org/apache/hadoop/hbase/shaded/protobuf/generated/AccessControlProtos$Permission$Builder.setType:(Lorg/apache/hadoop/hbase/shaded/protobuf/generated/AccessControlProtos$Permission$Type;)Lorg/apache/hadoop/hbase/shaded/protobuf/generated/AccessControlProtos$Permission$Builder;
     121: pop
     122: invokestatic  #88                 // Method org/apache/hadoop/hbase/shaded/protobuf/generated/AccessControlProtos$TablePermission.newBuilder:()Lorg/apache/hadoop/hbase/shaded/protobuf/generated/AccessControlProtos$TablePermission$Builder;
     125: astore_3
     126: aload_3
     127: aload_2
     128: invokevirtual #89                 // Method org/apache/hadoop/hbase/security/access/TablePermission.getTableName:()Lorg/apache/hadoop/hbase/TableName;
     131: invokestatic  #90                 // Method toProtoTableName:(Lorg/apache/hadoop/hbase/TableName;)Lorg/apache/hadoop/hbase/shaded/protobuf/generated/HBaseProtos$TableName;
     134: invokevirtual #91                 // Method org/apache/hadoop/hbase/shaded/protobuf/generated/AccessControlProtos$TablePermission$Builder.setTableName:(Lorg/apache/hadoop/hbase/shaded/protobuf/generated/HBaseProtos$TableName;)Lorg/apache/hadoop/hbase/shaded/protobuf/generated/AccessControlProtos$TablePermission$Builder;
     137: pop
     138: aload_2
     139: invokevirtual #92                 // Method org/apache/hadoop/hbase/security/access/TablePermission.hasFamily:()Z
     142: ifeq          157
     145: aload_3
     146: aload_2
     147: invokevirtual #93                 // Method org/apache/hadoop/hbase/security/access/TablePermission.getFamily:()[B
     150: invokestatic  #36                 // Method org/apache/hbase/thirdparty/com/google/protobuf/ByteString.copyFrom:([B)Lorg/apache/hbase/thirdparty/com/google/protobuf/ByteString;
     153: invokevirtual #94                 // Method org/apache/hadoop/hbase/shaded/protobuf/generated/AccessControlProtos$TablePermission$Builder.setFamily:(Lorg/apache/hbase/thirdparty/com/google/protobuf/ByteString;)Lorg/apache/hadoop/hbase/shaded/protobuf/generated/AccessControlProtos$TablePermission$Builder;
     156: pop
     157: aload_2
     158: invokevirtual #95                 // Method org/apache/hadoop/hbase/security/access/TablePermission.hasQualifier:()Z
     161: ifeq          176
     164: aload_3
     165: aload_2
     166: invokevirtual #96                 // Method org/apache/hadoop/hbase/security/access/TablePermission.getQualifier:()[B
     169: invokestatic  #36                 // Method org/apache/hbase/thirdparty/com/google/protobuf/ByteString.copyFrom:([B)Lorg/apache/hbase/thirdparty/com/google/protobuf/ByteString;
     172: invokevirtual #97                 // Method org/apache/hadoop/hbase/shaded/protobuf/generated/AccessControlProtos$TablePermission$Builder.setQualifier:(Lorg/apache/hbase/thirdparty/com/google/protobuf/ByteString;)Lorg/apache/hadoop/hbase/shaded/protobuf/generated/AccessControlProtos$TablePermission$Builder;
     175: pop
     176: aload_0
     177: invokevirtual #83                 // Method org/apache/hadoop/hbase/security/access/Permission.getActions:()[Lorg/apache/hadoop/hbase/security/access/Permission$Action;
     180: astore        4
     182: aload         4
     184: ifnull        229
     187: aload         4
     189: astore        5
     191: aload         5
     193: arraylength
     194: istore        6
     196: iconst_0
     197: istore        7
     199: iload         7
     201: iload         6
     203: if_icmpge     229
     206: aload         5
     208: iload         7
     210: aaload
     211: astore        8
     213: aload_3
     214: aload         8
     216: invokestatic  #84                 // Method toPermissionAction:(Lorg/apache/hadoop/hbase/security/access/Permission$Action;)Lorg/apache/hadoop/hbase/shaded/protobuf/generated/AccessControlProtos$Permission$Action;
     219: invokevirtual #98                 // Method org/apache/hadoop/hbase/shaded/protobuf/generated/AccessControlProtos$TablePermission$Builder.addAction:(Lorg/apache/hadoop/hbase/shaded/protobuf/generated/AccessControlProtos$Permission$Action;)Lorg/apache/hadoop/hbase/shaded/protobuf/generated/AccessControlProtos$TablePermission$Builder;
     222: pop
     223: iinc          7, 1
     226: goto          199
     229: aload_1
     230: aload_3
     231: invokevirtual #99                 // Method org/apache/hadoop/hbase/shaded/protobuf/generated/AccessControlProtos$Permission$Builder.setTablePermission:(Lorg/apache/hadoop/hbase/shaded/protobuf/generated/AccessControlProtos$TablePermission$Builder;)Lorg/apache/hadoop/hbase/shaded/protobuf/generated/AccessControlProtos$Permission$Builder;
     234: pop
     235: goto          306
     238: aload_1
     239: getstatic     #42                 // Field org/apache/hadoop/hbase/shaded/protobuf/generated/AccessControlProtos$Permission$Type.Global:Lorg/apache/hadoop/hbase/shaded/protobuf/generated/AccessControlProtos$Permission$Type;
     242: invokevirtual #78                 // Method org/apache/hadoop/hbase/shaded/protobuf/generated/AccessControlProtos$Permission$Builder.setType:(Lorg/apache/hadoop/hbase/shaded/protobuf/generated/AccessControlProtos$Permission$Type;)Lorg/apache/hadoop/hbase/shaded/protobuf/generated/AccessControlProtos$Permission$Builder;
     245: pop
     246: invokestatic  #100                // Method org/apache/hadoop/hbase/shaded/protobuf/generated/AccessControlProtos$GlobalPermission.newBuilder:()Lorg/apache/hadoop/hbase/shaded/protobuf/generated/AccessControlProtos$GlobalPermission$Builder;
     249: astore_2
     250: aload_0
     251: invokevirtual #83                 // Method org/apache/hadoop/hbase/security/access/Permission.getActions:()[Lorg/apache/hadoop/hbase/security/access/Permission$Action;
     254: astore_3
     255: aload_3
     256: ifnull        300
     259: aload_3
     260: astore        4
     262: aload         4
     264: arraylength
     265: istore        5
     267: iconst_0
     268: istore        6
     270: iload         6
     272: iload         5
     274: if_icmpge     300
     277: aload         4
     279: iload         6
     281: aaload
     282: astore        7
     284: aload_2
     285: aload         7
     287: invokestatic  #84                 // Method toPermissionAction:(Lorg/apache/hadoop/hbase/security/access/Permission$Action;)Lorg/apache/hadoop/hbase/shaded/protobuf/generated/AccessControlProtos$Permission$Action;
     290: invokevirtual #101                // Method org/apache/hadoop/hbase/shaded/protobuf/generated/AccessControlProtos$GlobalPermission$Builder.addAction:(Lorg/apache/hadoop/hbase/shaded/protobuf/generated/AccessControlProtos$Permission$Action;)Lorg/apache/hadoop/hbase/shaded/protobuf/generated/AccessControlProtos$GlobalPermission$Builder;
     293: pop
     294: iinc          6, 1
     297: goto          270
     300: aload_1
     301: aload_2
     302: invokevirtual #102                // Method org/apache/hadoop/hbase/shaded/protobuf/generated/AccessControlProtos$Permission$Builder.setGlobalPermission:(Lorg/apache/hadoop/hbase/shaded/protobuf/generated/AccessControlProtos$GlobalPermission$Builder;)Lorg/apache/hadoop/hbase/shaded/protobuf/generated/AccessControlProtos$Permission$Builder;
     305: pop
     306: aload_1
     307: invokevirtual #103                // Method org/apache/hadoop/hbase/shaded/protobuf/generated/AccessControlProtos$Permission$Builder.build:()Lorg/apache/hadoop/hbase/shaded/protobuf/generated/AccessControlProtos$Permission;
     310: areturn

  public static org.apache.hbase.thirdparty.com.google.common.collect.ListMultimap<java.lang.String, org.apache.hadoop.hbase.security.access.Permission> toUserTablePermissions(org.apache.hadoop.hbase.shaded.protobuf.generated.AccessControlProtos$UsersAndPermissions);
    Code:
       0: invokestatic  #104                // Method org/apache/hbase/thirdparty/com/google/common/collect/ArrayListMultimap.create:()Lorg/apache/hbase/thirdparty/com/google/common/collect/ArrayListMultimap;
       3: astore_1
       4: iconst_0
       5: istore_3
       6: iload_3
       7: aload_0
       8: invokevirtual #105                // Method org/apache/hadoop/hbase/shaded/protobuf/generated/AccessControlProtos$UsersAndPermissions.getUserPermissionsCount:()I
      11: if_icmpge     71
      14: aload_0
      15: iload_3
      16: invokevirtual #106                // Method org/apache/hadoop/hbase/shaded/protobuf/generated/AccessControlProtos$UsersAndPermissions.getUserPermissions:(I)Lorg/apache/hadoop/hbase/shaded/protobuf/generated/AccessControlProtos$UsersAndPermissions$UserPermissions;
      19: astore_2
      20: iconst_0
      21: istore        4
      23: iload         4
      25: aload_2
      26: invokevirtual #107                // Method org/apache/hadoop/hbase/shaded/protobuf/generated/AccessControlProtos$UsersAndPermissions$UserPermissions.getPermissionsCount:()I
      29: if_icmpge     65
      32: aload_2
      33: iload         4
      35: invokevirtual #108                // Method org/apache/hadoop/hbase/shaded/protobuf/generated/AccessControlProtos$UsersAndPermissions$UserPermissions.getPermissions:(I)Lorg/apache/hadoop/hbase/shaded/protobuf/generated/AccessControlProtos$Permission;
      38: invokestatic  #109                // Method toPermission:(Lorg/apache/hadoop/hbase/shaded/protobuf/generated/AccessControlProtos$Permission;)Lorg/apache/hadoop/hbase/security/access/Permission;
      41: astore        5
      43: aload_1
      44: aload_2
      45: invokevirtual #110                // Method org/apache/hadoop/hbase/shaded/protobuf/generated/AccessControlProtos$UsersAndPermissions$UserPermissions.getUser:()Lorg/apache/hbase/thirdparty/com/google/protobuf/ByteString;
      48: invokevirtual #57                 // Method org/apache/hbase/thirdparty/com/google/protobuf/ByteString.toStringUtf8:()Ljava/lang/String;
      51: aload         5
      53: invokeinterface #111,  3          // InterfaceMethod org/apache/hbase/thirdparty/com/google/common/collect/ListMultimap.put:(Ljava/lang/Object;Ljava/lang/Object;)Z
      58: pop
      59: iinc          4, 1
      62: goto          23
      65: iinc          3, 1
      68: goto          6
      71: aload_1
      72: areturn

  public static org.apache.hadoop.hbase.shaded.protobuf.generated.AccessControlProtos$UsersAndPermissions toUserTablePermissions(org.apache.hbase.thirdparty.com.google.common.collect.ListMultimap<java.lang.String, org.apache.hadoop.hbase.security.access.UserPermission>);
    Code:
       0: invokestatic  #112                // Method org/apache/hadoop/hbase/shaded/protobuf/generated/AccessControlProtos$UsersAndPermissions.newBuilder:()Lorg/apache/hadoop/hbase/shaded/protobuf/generated/AccessControlProtos$UsersAndPermissions$Builder;
       3: astore_1
       4: aload_0
       5: invokeinterface #113,  1          // InterfaceMethod org/apache/hbase/thirdparty/com/google/common/collect/ListMultimap.asMap:()Ljava/util/Map;
      10: invokeinterface #114,  1          // InterfaceMethod java/util/Map.entrySet:()Ljava/util/Set;
      15: invokeinterface #115,  1          // InterfaceMethod java/util/Set.iterator:()Ljava/util/Iterator;
      20: astore_2
      21: aload_2
      22: invokeinterface #116,  1          // InterfaceMethod java/util/Iterator.hasNext:()Z
      27: ifeq          131
      30: aload_2
      31: invokeinterface #117,  1          // InterfaceMethod java/util/Iterator.next:()Ljava/lang/Object;
      36: checkcast     #118                // class java/util/Map$Entry
      39: astore_3
      40: invokestatic  #119                // Method org/apache/hadoop/hbase/shaded/protobuf/generated/AccessControlProtos$UsersAndPermissions$UserPermissions.newBuilder:()Lorg/apache/hadoop/hbase/shaded/protobuf/generated/AccessControlProtos$UsersAndPermissions$UserPermissions$Builder;
      43: astore        4
      45: aload         4
      47: aload_3
      48: invokeinterface #120,  1          // InterfaceMethod java/util/Map$Entry.getKey:()Ljava/lang/Object;
      53: checkcast     #121                // class java/lang/String
      56: invokestatic  #81                 // Method org/apache/hbase/thirdparty/com/google/protobuf/ByteString.copyFromUtf8:(Ljava/lang/String;)Lorg/apache/hbase/thirdparty/com/google/protobuf/ByteString;
      59: invokevirtual #122                // Method org/apache/hadoop/hbase/shaded/protobuf/generated/AccessControlProtos$UsersAndPermissions$UserPermissions$Builder.setUser:(Lorg/apache/hbase/thirdparty/com/google/protobuf/ByteString;)Lorg/apache/hadoop/hbase/shaded/protobuf/generated/AccessControlProtos$UsersAndPermissions$UserPermissions$Builder;
      62: pop
      63: aload_3
      64: invokeinterface #123,  1          // InterfaceMethod java/util/Map$Entry.getValue:()Ljava/lang/Object;
      69: checkcast     #124                // class java/util/Collection
      72: invokeinterface #125,  1          // InterfaceMethod java/util/Collection.iterator:()Ljava/util/Iterator;
      77: astore        5
      79: aload         5
      81: invokeinterface #116,  1          // InterfaceMethod java/util/Iterator.hasNext:()Z
      86: ifeq          118
      89: aload         5
      91: invokeinterface #117,  1          // InterfaceMethod java/util/Iterator.next:()Ljava/lang/Object;
      96: checkcast     #126                // class org/apache/hadoop/hbase/security/access/UserPermission
      99: astore        6
     101: aload         4
     103: aload         6
     105: invokevirtual #127                // Method org/apache/hadoop/hbase/security/access/UserPermission.getPermission:()Lorg/apache/hadoop/hbase/security/access/Permission;
     108: invokestatic  #128                // Method toPermission:(Lorg/apache/hadoop/hbase/security/access/Permission;)Lorg/apache/hadoop/hbase/shaded/protobuf/generated/AccessControlProtos$Permission;
     111: invokevirtual #129                // Method org/apache/hadoop/hbase/shaded/protobuf/generated/AccessControlProtos$UsersAndPermissions$UserPermissions$Builder.addPermissions:(Lorg/apache/hadoop/hbase/shaded/protobuf/generated/AccessControlProtos$Permission;)Lorg/apache/hadoop/hbase/shaded/protobuf/generated/AccessControlProtos$UsersAndPermissions$UserPermissions$Builder;
     114: pop
     115: goto          79
     118: aload_1
     119: aload         4
     121: invokevirtual #130                // Method org/apache/hadoop/hbase/shaded/protobuf/generated/AccessControlProtos$UsersAndPermissions$UserPermissions$Builder.build:()Lorg/apache/hadoop/hbase/shaded/protobuf/generated/AccessControlProtos$UsersAndPermissions$UserPermissions;
     124: invokevirtual #131                // Method org/apache/hadoop/hbase/shaded/protobuf/generated/AccessControlProtos$UsersAndPermissions$Builder.addUserPermissions:(Lorg/apache/hadoop/hbase/shaded/protobuf/generated/AccessControlProtos$UsersAndPermissions$UserPermissions;)Lorg/apache/hadoop/hbase/shaded/protobuf/generated/AccessControlProtos$UsersAndPermissions$Builder;
     127: pop
     128: goto          21
     131: aload_1
     132: invokevirtual #132                // Method org/apache/hadoop/hbase/shaded/protobuf/generated/AccessControlProtos$UsersAndPermissions$Builder.build:()Lorg/apache/hadoop/hbase/shaded/protobuf/generated/AccessControlProtos$UsersAndPermissions;
     135: areturn

  public static org.apache.hadoop.hbase.security.access.UserPermission toUserPermission(org.apache.hadoop.hbase.shaded.protobuf.generated.AccessControlProtos$UserPermission);
    Code:
       0: new           #126                // class org/apache/hadoop/hbase/security/access/UserPermission
       3: dup
       4: aload_0
       5: invokevirtual #133                // Method org/apache/hadoop/hbase/shaded/protobuf/generated/AccessControlProtos$UserPermission.getUser:()Lorg/apache/hbase/thirdparty/com/google/protobuf/ByteString;
       8: invokevirtual #57                 // Method org/apache/hbase/thirdparty/com/google/protobuf/ByteString.toStringUtf8:()Ljava/lang/String;
      11: aload_0
      12: invokevirtual #134                // Method org/apache/hadoop/hbase/shaded/protobuf/generated/AccessControlProtos$UserPermission.getPermission:()Lorg/apache/hadoop/hbase/shaded/protobuf/generated/AccessControlProtos$Permission;
      15: invokestatic  #109                // Method toPermission:(Lorg/apache/hadoop/hbase/shaded/protobuf/generated/AccessControlProtos$Permission;)Lorg/apache/hadoop/hbase/security/access/Permission;
      18: invokespecial #135                // Method org/apache/hadoop/hbase/security/access/UserPermission."<init>":(Ljava/lang/String;Lorg/apache/hadoop/hbase/security/access/Permission;)V
      21: areturn

  public static org.apache.hadoop.hbase.shaded.protobuf.generated.AccessControlProtos$UserPermission toUserPermission(org.apache.hadoop.hbase.security.access.UserPermission);
    Code:
       0: invokestatic  #136                // Method org/apache/hadoop/hbase/shaded/protobuf/generated/AccessControlProtos$UserPermission.newBuilder:()Lorg/apache/hadoop/hbase/shaded/protobuf/generated/AccessControlProtos$UserPermission$Builder;
       3: aload_0
       4: invokevirtual #137                // Method org/apache/hadoop/hbase/security/access/UserPermission.getUser:()Ljava/lang/String;
       7: invokestatic  #81                 // Method org/apache/hbase/thirdparty/com/google/protobuf/ByteString.copyFromUtf8:(Ljava/lang/String;)Lorg/apache/hbase/thirdparty/com/google/protobuf/ByteString;
      10: invokevirtual #138                // Method org/apache/hadoop/hbase/shaded/protobuf/generated/AccessControlProtos$UserPermission$Builder.setUser:(Lorg/apache/hbase/thirdparty/com/google/protobuf/ByteString;)Lorg/apache/hadoop/hbase/shaded/protobuf/generated/AccessControlProtos$UserPermission$Builder;
      13: aload_0
      14: invokevirtual #127                // Method org/apache/hadoop/hbase/security/access/UserPermission.getPermission:()Lorg/apache/hadoop/hbase/security/access/Permission;
      17: invokestatic  #128                // Method toPermission:(Lorg/apache/hadoop/hbase/security/access/Permission;)Lorg/apache/hadoop/hbase/shaded/protobuf/generated/AccessControlProtos$Permission;
      20: invokevirtual #139                // Method org/apache/hadoop/hbase/shaded/protobuf/generated/AccessControlProtos$UserPermission$Builder.setPermission:(Lorg/apache/hadoop/hbase/shaded/protobuf/generated/AccessControlProtos$Permission;)Lorg/apache/hadoop/hbase/shaded/protobuf/generated/AccessControlProtos$UserPermission$Builder;
      23: invokevirtual #140                // Method org/apache/hadoop/hbase/shaded/protobuf/generated/AccessControlProtos$UserPermission$Builder.build:()Lorg/apache/hadoop/hbase/shaded/protobuf/generated/AccessControlProtos$UserPermission;
      26: areturn

  public static org.apache.hadoop.hbase.shaded.protobuf.generated.AccessControlProtos$GrantRequest buildGrantRequest(org.apache.hadoop.hbase.security.access.UserPermission, boolean);
    Code:
       0: invokestatic  #141                // Method org/apache/hadoop/hbase/shaded/protobuf/generated/AccessControlProtos$GrantRequest.newBuilder:()Lorg/apache/hadoop/hbase/shaded/protobuf/generated/AccessControlProtos$GrantRequest$Builder;
       3: aload_0
       4: invokestatic  #142                // Method toUserPermission:(Lorg/apache/hadoop/hbase/security/access/UserPermission;)Lorg/apache/hadoop/hbase/shaded/protobuf/generated/AccessControlProtos$UserPermission;
       7: invokevirtual #143                // Method org/apache/hadoop/hbase/shaded/protobuf/generated/AccessControlProtos$GrantRequest$Builder.setUserPermission:(Lorg/apache/hadoop/hbase/shaded/protobuf/generated/AccessControlProtos$UserPermission;)Lorg/apache/hadoop/hbase/shaded/protobuf/generated/AccessControlProtos$GrantRequest$Builder;
      10: iload_1
      11: invokevirtual #144                // Method org/apache/hadoop/hbase/shaded/protobuf/generated/AccessControlProtos$GrantRequest$Builder.setMergeExistingPermissions:(Z)Lorg/apache/hadoop/hbase/shaded/protobuf/generated/AccessControlProtos$GrantRequest$Builder;
      14: invokevirtual #145                // Method org/apache/hadoop/hbase/shaded/protobuf/generated/AccessControlProtos$GrantRequest$Builder.build:()Lorg/apache/hadoop/hbase/shaded/protobuf/generated/AccessControlProtos$GrantRequest;
      17: areturn

  public static org.apache.hadoop.hbase.shaded.protobuf.generated.AccessControlProtos$RevokeRequest buildRevokeRequest(org.apache.hadoop.hbase.security.access.UserPermission);
    Code:
       0: invokestatic  #146                // Method org/apache/hadoop/hbase/shaded/protobuf/generated/AccessControlProtos$RevokeRequest.newBuilder:()Lorg/apache/hadoop/hbase/shaded/protobuf/generated/AccessControlProtos$RevokeRequest$Builder;
       3: aload_0
       4: invokestatic  #142                // Method toUserPermission:(Lorg/apache/hadoop/hbase/security/access/UserPermission;)Lorg/apache/hadoop/hbase/shaded/protobuf/generated/AccessControlProtos$UserPermission;
       7: invokevirtual #147                // Method org/apache/hadoop/hbase/shaded/protobuf/generated/AccessControlProtos$RevokeRequest$Builder.setUserPermission:(Lorg/apache/hadoop/hbase/shaded/protobuf/generated/AccessControlProtos$UserPermission;)Lorg/apache/hadoop/hbase/shaded/protobuf/generated/AccessControlProtos$RevokeRequest$Builder;
      10: invokevirtual #148                // Method org/apache/hadoop/hbase/shaded/protobuf/generated/AccessControlProtos$RevokeRequest$Builder.build:()Lorg/apache/hadoop/hbase/shaded/protobuf/generated/AccessControlProtos$RevokeRequest;
      13: areturn

  public static org.apache.hadoop.hbase.shaded.protobuf.generated.AccessControlProtos$GetUserPermissionsRequest buildGetUserPermissionsRequest(org.apache.hadoop.hbase.security.access.GetUserPermissionsRequest);
    Code:
       0: invokestatic  #149                // Method org/apache/hadoop/hbase/shaded/protobuf/generated/AccessControlProtos$GetUserPermissionsRequest.newBuilder:()Lorg/apache/hadoop/hbase/shaded/protobuf/generated/AccessControlProtos$GetUserPermissionsRequest$Builder;
       3: astore_1
       4: aload_0
       5: invokevirtual #150                // Method org/apache/hadoop/hbase/security/access/GetUserPermissionsRequest.getUserName:()Ljava/lang/String;
       8: ifnull        33
      11: aload_0
      12: invokevirtual #150                // Method org/apache/hadoop/hbase/security/access/GetUserPermissionsRequest.getUserName:()Ljava/lang/String;
      15: invokevirtual #151                // Method java/lang/String.isEmpty:()Z
      18: ifne          33
      21: aload_1
      22: aload_0
      23: invokevirtual #150                // Method org/apache/hadoop/hbase/security/access/GetUserPermissionsRequest.getUserName:()Ljava/lang/String;
      26: invokestatic  #81                 // Method org/apache/hbase/thirdparty/com/google/protobuf/ByteString.copyFromUtf8:(Ljava/lang/String;)Lorg/apache/hbase/thirdparty/com/google/protobuf/ByteString;
      29: invokevirtual #152                // Method org/apache/hadoop/hbase/shaded/protobuf/generated/AccessControlProtos$GetUserPermissionsRequest$Builder.setUserName:(Lorg/apache/hbase/thirdparty/com/google/protobuf/ByteString;)Lorg/apache/hadoop/hbase/shaded/protobuf/generated/AccessControlProtos$GetUserPermissionsRequest$Builder;
      32: pop
      33: aload_0
      34: invokevirtual #153                // Method org/apache/hadoop/hbase/security/access/GetUserPermissionsRequest.getNamespace:()Ljava/lang/String;
      37: ifnull        70
      40: aload_0
      41: invokevirtual #153                // Method org/apache/hadoop/hbase/security/access/GetUserPermissionsRequest.getNamespace:()Ljava/lang/String;
      44: invokevirtual #151                // Method java/lang/String.isEmpty:()Z
      47: ifne          70
      50: aload_1
      51: aload_0
      52: invokevirtual #153                // Method org/apache/hadoop/hbase/security/access/GetUserPermissionsRequest.getNamespace:()Ljava/lang/String;
      55: invokestatic  #81                 // Method org/apache/hbase/thirdparty/com/google/protobuf/ByteString.copyFromUtf8:(Ljava/lang/String;)Lorg/apache/hbase/thirdparty/com/google/protobuf/ByteString;
      58: invokevirtual #154                // Method org/apache/hadoop/hbase/shaded/protobuf/generated/AccessControlProtos$GetUserPermissionsRequest$Builder.setNamespaceName:(Lorg/apache/hbase/thirdparty/com/google/protobuf/ByteString;)Lorg/apache/hadoop/hbase/shaded/protobuf/generated/AccessControlProtos$GetUserPermissionsRequest$Builder;
      61: pop
      62: aload_1
      63: getstatic     #49                 // Field org/apache/hadoop/hbase/shaded/protobuf/generated/AccessControlProtos$Permission$Type.Namespace:Lorg/apache/hadoop/hbase/shaded/protobuf/generated/AccessControlProtos$Permission$Type;
      66: invokevirtual #155                // Method org/apache/hadoop/hbase/shaded/protobuf/generated/AccessControlProtos$GetUserPermissionsRequest$Builder.setType:(Lorg/apache/hadoop/hbase/shaded/protobuf/generated/AccessControlProtos$Permission$Type;)Lorg/apache/hadoop/hbase/shaded/protobuf/generated/AccessControlProtos$GetUserPermissionsRequest$Builder;
      69: pop
      70: aload_0
      71: invokevirtual #156                // Method org/apache/hadoop/hbase/security/access/GetUserPermissionsRequest.getTableName:()Lorg/apache/hadoop/hbase/TableName;
      74: ifnull        97
      77: aload_1
      78: aload_0
      79: invokevirtual #156                // Method org/apache/hadoop/hbase/security/access/GetUserPermissionsRequest.getTableName:()Lorg/apache/hadoop/hbase/TableName;
      82: invokestatic  #90                 // Method toProtoTableName:(Lorg/apache/hadoop/hbase/TableName;)Lorg/apache/hadoop/hbase/shaded/protobuf/generated/HBaseProtos$TableName;
      85: invokevirtual #157                // Method org/apache/hadoop/hbase/shaded/protobuf/generated/AccessControlProtos$GetUserPermissionsRequest$Builder.setTableName:(Lorg/apache/hadoop/hbase/shaded/protobuf/generated/HBaseProtos$TableName;)Lorg/apache/hadoop/hbase/shaded/protobuf/generated/AccessControlProtos$GetUserPermissionsRequest$Builder;
      88: pop
      89: aload_1
      90: getstatic     #59                 // Field org/apache/hadoop/hbase/shaded/protobuf/generated/AccessControlProtos$Permission$Type.Table:Lorg/apache/hadoop/hbase/shaded/protobuf/generated/AccessControlProtos$Permission$Type;
      93: invokevirtual #155                // Method org/apache/hadoop/hbase/shaded/protobuf/generated/AccessControlProtos$GetUserPermissionsRequest$Builder.setType:(Lorg/apache/hadoop/hbase/shaded/protobuf/generated/AccessControlProtos$Permission$Type;)Lorg/apache/hadoop/hbase/shaded/protobuf/generated/AccessControlProtos$GetUserPermissionsRequest$Builder;
      96: pop
      97: aload_1
      98: invokevirtual #158                // Method org/apache/hadoop/hbase/shaded/protobuf/generated/AccessControlProtos$GetUserPermissionsRequest$Builder.hasType:()Z
     101: ifne          112
     104: aload_1
     105: getstatic     #42                 // Field org/apache/hadoop/hbase/shaded/protobuf/generated/AccessControlProtos$Permission$Type.Global:Lorg/apache/hadoop/hbase/shaded/protobuf/generated/AccessControlProtos$Permission$Type;
     108: invokevirtual #155                // Method org/apache/hadoop/hbase/shaded/protobuf/generated/AccessControlProtos$GetUserPermissionsRequest$Builder.setType:(Lorg/apache/hadoop/hbase/shaded/protobuf/generated/AccessControlProtos$Permission$Type;)Lorg/apache/hadoop/hbase/shaded/protobuf/generated/AccessControlProtos$GetUserPermissionsRequest$Builder;
     111: pop
     112: aload_0
     113: invokevirtual #159                // Method org/apache/hadoop/hbase/security/access/GetUserPermissionsRequest.getFamily:()[B
     116: ifnull        139
     119: aload_0
     120: invokevirtual #159                // Method org/apache/hadoop/hbase/security/access/GetUserPermissionsRequest.getFamily:()[B
     123: arraylength
     124: ifle          139
     127: aload_1
     128: aload_0
     129: invokevirtual #159                // Method org/apache/hadoop/hbase/security/access/GetUserPermissionsRequest.getFamily:()[B
     132: invokestatic  #36                 // Method org/apache/hbase/thirdparty/com/google/protobuf/ByteString.copyFrom:([B)Lorg/apache/hbase/thirdparty/com/google/protobuf/ByteString;
     135: invokevirtual #160                // Method org/apache/hadoop/hbase/shaded/protobuf/generated/AccessControlProtos$GetUserPermissionsRequest$Builder.setColumnFamily:(Lorg/apache/hbase/thirdparty/com/google/protobuf/ByteString;)Lorg/apache/hadoop/hbase/shaded/protobuf/generated/AccessControlProtos$GetUserPermissionsRequest$Builder;
     138: pop
     139: aload_0
     140: invokevirtual #161                // Method org/apache/hadoop/hbase/security/access/GetUserPermissionsRequest.getQualifier:()[B
     143: ifnull        166
     146: aload_0
     147: invokevirtual #161                // Method org/apache/hadoop/hbase/security/access/GetUserPermissionsRequest.getQualifier:()[B
     150: arraylength
     151: ifle          166
     154: aload_1
     155: aload_0
     156: invokevirtual #161                // Method org/apache/hadoop/hbase/security/access/GetUserPermissionsRequest.getQualifier:()[B
     159: invokestatic  #36                 // Method org/apache/hbase/thirdparty/com/google/protobuf/ByteString.copyFrom:([B)Lorg/apache/hbase/thirdparty/com/google/protobuf/ByteString;
     162: invokevirtual #162                // Method org/apache/hadoop/hbase/shaded/protobuf/generated/AccessControlProtos$GetUserPermissionsRequest$Builder.setColumnQualifier:(Lorg/apache/hbase/thirdparty/com/google/protobuf/ByteString;)Lorg/apache/hadoop/hbase/shaded/protobuf/generated/AccessControlProtos$GetUserPermissionsRequest$Builder;
     165: pop
     166: aload_1
     167: invokevirtual #163                // Method org/apache/hadoop/hbase/shaded/protobuf/generated/AccessControlProtos$GetUserPermissionsRequest$Builder.build:()Lorg/apache/hadoop/hbase/shaded/protobuf/generated/AccessControlProtos$GetUserPermissionsRequest;
     170: areturn

  public static org.apache.hadoop.hbase.shaded.protobuf.generated.AccessControlProtos$GetUserPermissionsResponse buildGetUserPermissionsResponse(java.util.List<org.apache.hadoop.hbase.security.access.UserPermission>);
    Code:
       0: invokestatic  #164                // Method org/apache/hadoop/hbase/shaded/protobuf/generated/AccessControlProtos$GetUserPermissionsResponse.newBuilder:()Lorg/apache/hadoop/hbase/shaded/protobuf/generated/AccessControlProtos$GetUserPermissionsResponse$Builder;
       3: astore_1
       4: aload_0
       5: invokeinterface #165,  1          // InterfaceMethod java/util/List.iterator:()Ljava/util/Iterator;
      10: astore_2
      11: aload_2
      12: invokeinterface #116,  1          // InterfaceMethod java/util/Iterator.hasNext:()Z
      17: ifeq          42
      20: aload_2
      21: invokeinterface #117,  1          // InterfaceMethod java/util/Iterator.next:()Ljava/lang/Object;
      26: checkcast     #126                // class org/apache/hadoop/hbase/security/access/UserPermission
      29: astore_3
      30: aload_1
      31: aload_3
      32: invokestatic  #142                // Method toUserPermission:(Lorg/apache/hadoop/hbase/security/access/UserPermission;)Lorg/apache/hadoop/hbase/shaded/protobuf/generated/AccessControlProtos$UserPermission;
      35: invokevirtual #166                // Method org/apache/hadoop/hbase/shaded/protobuf/generated/AccessControlProtos$GetUserPermissionsResponse$Builder.addUserPermission:(Lorg/apache/hadoop/hbase/shaded/protobuf/generated/AccessControlProtos$UserPermission;)Lorg/apache/hadoop/hbase/shaded/protobuf/generated/AccessControlProtos$GetUserPermissionsResponse$Builder;
      38: pop
      39: goto          11
      42: aload_1
      43: invokevirtual #167                // Method org/apache/hadoop/hbase/shaded/protobuf/generated/AccessControlProtos$GetUserPermissionsResponse$Builder.build:()Lorg/apache/hadoop/hbase/shaded/protobuf/generated/AccessControlProtos$GetUserPermissionsResponse;
      46: areturn

  public static org.apache.hadoop.hbase.shaded.protobuf.generated.AccessControlProtos$HasUserPermissionsRequest buildHasUserPermissionsRequest(java.lang.String, java.util.List<org.apache.hadoop.hbase.security.access.Permission>);
    Code:
       0: invokestatic  #168                // Method org/apache/hadoop/hbase/shaded/protobuf/generated/AccessControlProtos$HasUserPermissionsRequest.newBuilder:()Lorg/apache/hadoop/hbase/shaded/protobuf/generated/AccessControlProtos$HasUserPermissionsRequest$Builder;
       3: astore_2
       4: aload_0
       5: ifnull        24
       8: aload_0
       9: invokevirtual #151                // Method java/lang/String.isEmpty:()Z
      12: ifne          24
      15: aload_2
      16: aload_0
      17: invokestatic  #81                 // Method org/apache/hbase/thirdparty/com/google/protobuf/ByteString.copyFromUtf8:(Ljava/lang/String;)Lorg/apache/hbase/thirdparty/com/google/protobuf/ByteString;
      20: invokevirtual #169                // Method org/apache/hadoop/hbase/shaded/protobuf/generated/AccessControlProtos$HasUserPermissionsRequest$Builder.setUserName:(Lorg/apache/hbase/thirdparty/com/google/protobuf/ByteString;)Lorg/apache/hadoop/hbase/shaded/protobuf/generated/AccessControlProtos$HasUserPermissionsRequest$Builder;
      23: pop
      24: aload_1
      25: invokeinterface #165,  1          // InterfaceMethod java/util/List.iterator:()Ljava/util/Iterator;
      30: astore_3
      31: aload_3
      32: invokeinterface #116,  1          // InterfaceMethod java/util/Iterator.hasNext:()Z
      37: ifeq          64
      40: aload_3
      41: invokeinterface #117,  1          // InterfaceMethod java/util/Iterator.next:()Ljava/lang/Object;
      46: checkcast     #170                // class org/apache/hadoop/hbase/security/access/Permission
      49: astore        4
      51: aload_2
      52: aload         4
      54: invokestatic  #128                // Method toPermission:(Lorg/apache/hadoop/hbase/security/access/Permission;)Lorg/apache/hadoop/hbase/shaded/protobuf/generated/AccessControlProtos$Permission;
      57: invokevirtual #171                // Method org/apache/hadoop/hbase/shaded/protobuf/generated/AccessControlProtos$HasUserPermissionsRequest$Builder.addPermission:(Lorg/apache/hadoop/hbase/shaded/protobuf/generated/AccessControlProtos$Permission;)Lorg/apache/hadoop/hbase/shaded/protobuf/generated/AccessControlProtos$HasUserPermissionsRequest$Builder;
      60: pop
      61: goto          31
      64: aload_2
      65: invokevirtual #172                // Method org/apache/hadoop/hbase/shaded/protobuf/generated/AccessControlProtos$HasUserPermissionsRequest$Builder.build:()Lorg/apache/hadoop/hbase/shaded/protobuf/generated/AccessControlProtos$HasUserPermissionsRequest;
      68: areturn
}
