Compiled from "ShutdownHookManager.java"
class org.apache.hadoop.hbase.util.ShutdownHookManager$ShutdownHookManagerV2 extends org.apache.hadoop.hbase.util.ShutdownHookManager {
  public void addShutdownHook(java.lang.Thread, int);
    Code:
       0: getstatic     #3                  // Field shutdownHookManagerClass:Ljava/lang/Class;
       3: getstatic     #3                  // Field shutdownHookManagerClass:Ljava/lang/Class;
       6: aconst_null
       7: ldc           #4                  // String get
       9: aconst_null
      10: aconst_null
      11: invokestatic  #5                  // Method org/apache/hadoop/hbase/util/Methods.call:(Ljava/lang/Class;Ljava/lang/Object;Ljava/lang/String;[Ljava/lang/Class;[Ljava/lang/Object;)Ljava/lang/Object;
      14: ldc           #6                  // String addShutdownHook
      16: iconst_2
      17: anewarray     #7                  // class java/lang/Class
      20: dup
      21: iconst_0
      22: ldc           #8                  // class java/lang/Runnable
      24: aastore
      25: dup
      26: iconst_1
      27: getstatic     #9                  // Field java/lang/Integer.TYPE:Ljava/lang/Class;
      30: aastore
      31: iconst_2
      32: anewarray     #10                 // class java/lang/Object
      35: dup
      36: iconst_0
      37: aload_1
      38: aastore
      39: dup
      40: iconst_1
      41: iload_2
      42: invokestatic  #11                 // Method java/lang/Integer.valueOf:(I)Ljava/lang/Integer;
      45: aastore
      46: invokestatic  #5                  // Method org/apache/hadoop/hbase/util/Methods.call:(Ljava/lang/Class;Ljava/lang/Object;Ljava/lang/String;[Ljava/lang/Class;[Ljava/lang/Object;)Ljava/lang/Object;
      49: pop
      50: goto          65
      53: astore_3
      54: new           #13                 // class java/lang/RuntimeException
      57: dup
      58: ldc           #14                 // String we could not use ShutdownHookManager.addShutdownHook
      60: aload_3
      61: invokespecial #15                 // Method java/lang/RuntimeException."<init>":(Ljava/lang/String;Ljava/lang/Throwable;)V
      64: athrow
      65: return
    Exception table:
       from    to  target type
           0    50    53   Class java/lang/Exception

  public boolean removeShutdownHook(java.lang.Runnable);
    Code:
       0: getstatic     #3                  // Field shutdownHookManagerClass:Ljava/lang/Class;
       3: getstatic     #3                  // Field shutdownHookManagerClass:Ljava/lang/Class;
       6: aconst_null
       7: ldc           #4                  // String get
       9: aconst_null
      10: aconst_null
      11: invokestatic  #5                  // Method org/apache/hadoop/hbase/util/Methods.call:(Ljava/lang/Class;Ljava/lang/Object;Ljava/lang/String;[Ljava/lang/Class;[Ljava/lang/Object;)Ljava/lang/Object;
      14: ldc           #16                 // String removeShutdownHook
      16: iconst_1
      17: anewarray     #7                  // class java/lang/Class
      20: dup
      21: iconst_0
      22: ldc           #8                  // class java/lang/Runnable
      24: aastore
      25: iconst_1
      26: anewarray     #10                 // class java/lang/Object
      29: dup
      30: iconst_0
      31: aload_1
      32: aastore
      33: invokestatic  #5                  // Method org/apache/hadoop/hbase/util/Methods.call:(Ljava/lang/Class;Ljava/lang/Object;Ljava/lang/String;[Ljava/lang/Class;[Ljava/lang/Object;)Ljava/lang/Object;
      36: checkcast     #17                 // class java/lang/Boolean
      39: invokevirtual #18                 // Method java/lang/Boolean.booleanValue:()Z
      42: ireturn
      43: astore_2
      44: new           #13                 // class java/lang/RuntimeException
      47: dup
      48: ldc           #19                 // String we could not use ShutdownHookManager
      50: aload_2
      51: invokespecial #15                 // Method java/lang/RuntimeException."<init>":(Ljava/lang/String;Ljava/lang/Throwable;)V
      54: athrow
    Exception table:
       from    to  target type
           0    42    43   Class java/lang/Exception

  org.apache.hadoop.hbase.util.ShutdownHookManager$ShutdownHookManagerV2(org.apache.hadoop.hbase.util.ShutdownHookManager$1);
    Code:
       0: aload_0
       1: invokespecial #1                  // Method "<init>":()V
       4: return
}
