Compiled from "ShutdownHook.java"
public class org.apache.hadoop.hbase.regionserver.ShutdownHook {
  public static final java.lang.String RUN_SHUTDOWN_HOOK;

  public static final java.lang.String FS_SHUTDOWN_HOOK_WAIT;

  public org.apache.hadoop.hbase.regionserver.ShutdownHook();
    Code:
       0: aload_0
       1: invokespecial #3                  // Method java/lang/Object."<init>":()V
       4: return

  public static void install(org.apache.hadoop.conf.Configuration, org.apache.hadoop.fs.FileSystem, org.apache.hadoop.hbase.Stoppable, java.lang.Thread);
    Code:
       0: aload_1
       1: invokestatic  #4                  // Method suppressHdfsShutdownHook:(Lorg/apache/hadoop/fs/FileSystem;)Ljava/lang/Runnable;
       4: astore        4
       6: new           #5                  // class org/apache/hadoop/hbase/regionserver/ShutdownHook$ShutdownHookThread
       9: dup
      10: aload_0
      11: aload_2
      12: aload_3
      13: aload         4
      15: invokespecial #6                  // Method org/apache/hadoop/hbase/regionserver/ShutdownHook$ShutdownHookThread."<init>":(Lorg/apache/hadoop/conf/Configuration;Lorg/apache/hadoop/hbase/Stoppable;Ljava/lang/Thread;Ljava/lang/Runnable;)V
      18: astore        5
      20: aload         5
      22: iconst_0
      23: invokestatic  #7                  // Method org/apache/hadoop/hbase/util/ShutdownHookManager.affixShutdownHook:(Ljava/lang/Thread;I)V
      26: getstatic     #2                  // Field LOG:Lorg/slf4j/Logger;
      29: new           #8                  // class java/lang/StringBuilder
      32: dup
      33: invokespecial #9                  // Method java/lang/StringBuilder."<init>":()V
      36: ldc           #10                 // String Installed shutdown hook thread:
      38: invokevirtual #11                 // Method java/lang/StringBuilder.append:(Ljava/lang/String;)Ljava/lang/StringBuilder;
      41: aload         5
      43: invokevirtual #12                 // Method java/lang/Thread.getName:()Ljava/lang/String;
      46: invokevirtual #11                 // Method java/lang/StringBuilder.append:(Ljava/lang/String;)Ljava/lang/StringBuilder;
      49: invokevirtual #13                 // Method java/lang/StringBuilder.toString:()Ljava/lang/String;
      52: invokeinterface #14,  2           // InterfaceMethod org/slf4j/Logger.debug:(Ljava/lang/String;)V
      57: return

  public static void main(java.lang.String[]) throws java.io.IOException;
    Code:
       0: invokestatic  #50                 // Method org/apache/hadoop/hbase/HBaseConfiguration.create:()Lorg/apache/hadoop/conf/Configuration;
       3: astore_1
       4: ldc           #51                 // String hbase.shutdown.hook
       6: invokestatic  #52                 // Method java/lang/System.getProperty:(Ljava/lang/String;)Ljava/lang/String;
       9: astore_2
      10: aload_2
      11: ifnull        24
      14: aload_1
      15: ldc           #51                 // String hbase.shutdown.hook
      17: aload_2
      18: invokestatic  #53                 // Method java/lang/Boolean.parseBoolean:(Ljava/lang/String;)Z
      21: invokevirtual #54                 // Method org/apache/hadoop/conf/Configuration.setBoolean:(Ljava/lang/String;Z)V
      24: aload_1
      25: invokestatic  #55                 // Method org/apache/hadoop/fs/FileSystem.get:(Lorg/apache/hadoop/conf/Configuration;)Lorg/apache/hadoop/fs/FileSystem;
      28: astore_3
      29: new           #56                 // class org/apache/hadoop/hbase/regionserver/ShutdownHook$DoNothingThread
      32: dup
      33: invokespecial #57                 // Method org/apache/hadoop/hbase/regionserver/ShutdownHook$DoNothingThread."<init>":()V
      36: astore        4
      38: aload         4
      40: invokevirtual #58                 // Method java/lang/Thread.start:()V
      43: aload_1
      44: aload_3
      45: new           #59                 // class org/apache/hadoop/hbase/regionserver/ShutdownHook$DoNothingStoppable
      48: dup
      49: invokespecial #60                 // Method org/apache/hadoop/hbase/regionserver/ShutdownHook$DoNothingStoppable."<init>":()V
      52: aload         4
      54: invokestatic  #61                 // Method install:(Lorg/apache/hadoop/conf/Configuration;Lorg/apache/hadoop/fs/FileSystem;Lorg/apache/hadoop/hbase/Stoppable;Ljava/lang/Thread;)V
      57: return

  static org.slf4j.Logger access$000();
    Code:
       0: getstatic     #2                  // Field LOG:Lorg/slf4j/Logger;
       3: areturn

  static java.util.Map access$100();
    Code:
       0: getstatic     #1                  // Field fsShutdownHooks:Ljava/util/Map;
       3: areturn

  static {};
    Code:
       0: ldc           #23                 // class org/apache/hadoop/hbase/regionserver/ShutdownHook
       2: invokestatic  #62                 // Method org/slf4j/LoggerFactory.getLogger:(Ljava/lang/Class;)Lorg/slf4j/Logger;
       5: putstatic     #2                  // Field LOG:Lorg/slf4j/Logger;
       8: new           #63                 // class java/util/HashMap
      11: dup
      12: invokespecial #64                 // Method java/util/HashMap."<init>":()V
      15: putstatic     #1                  // Field fsShutdownHooks:Ljava/util/Map;
      18: return
}
