Compiled from "ShutdownHookManager.java"
public abstract class org.apache.hadoop.hbase.util.ShutdownHookManager {
  static java.lang.Class shutdownHookManagerClass;

  public org.apache.hadoop.hbase.util.ShutdownHookManager();
    Code:
       0: aload_0
       1: invokespecial #1                  // Method java/lang/Object."<init>":()V
       4: return

  public abstract void addShutdownHook(java.lang.Thread, int);

  public abstract boolean removeShutdownHook(java.lang.Runnable);

  public static void affixShutdownHook(java.lang.Thread, int);
    Code:
       0: getstatic     #2                  // Field instance:Lorg/apache/hadoop/hbase/util/ShutdownHookManager;
       3: aload_0
       4: iload_1
       5: invokevirtual #3                  // Method addShutdownHook:(Ljava/lang/Thread;I)V
       8: return

  public static boolean deleteShutdownHook(java.lang.Runnable);
    Code:
       0: getstatic     #2                  // Field instance:Lorg/apache/hadoop/hbase/util/ShutdownHookManager;
       3: aload_0
       4: invokevirtual #4                  // Method removeShutdownHook:(Ljava/lang/Runnable;)Z
       7: ireturn

  static {};
    Code:
       0: aconst_null
       1: putstatic     #5                  // Field shutdownHookManagerClass:Ljava/lang/Class;
       4: ldc           #6                  // String org.apache.hadoop.util.ShutdownHookManager
       6: invokestatic  #7                  // Method java/lang/Class.forName:(Ljava/lang/String;)Ljava/lang/Class;
       9: putstatic     #5                  // Field shutdownHookManagerClass:Ljava/lang/Class;
      12: new           #8                  // class org/apache/hadoop/hbase/util/ShutdownHookManager$ShutdownHookManagerV2
      15: dup
      16: aconst_null
      17: invokespecial #9                  // Method org/apache/hadoop/hbase/util/ShutdownHookManager$ShutdownHookManagerV2."<init>":(Lorg/apache/hadoop/hbase/util/ShutdownHookManager$1;)V
      20: putstatic     #2                  // Field instance:Lorg/apache/hadoop/hbase/util/ShutdownHookManager;
      23: goto          38
      26: astore_0
      27: new           #11                 // class org/apache/hadoop/hbase/util/ShutdownHookManager$ShutdownHookManagerV1
      30: dup
      31: aconst_null
      32: invokespecial #12                 // Method org/apache/hadoop/hbase/util/ShutdownHookManager$ShutdownHookManagerV1."<init>":(Lorg/apache/hadoop/hbase/util/ShutdownHookManager$1;)V
      35: putstatic     #2                  // Field instance:Lorg/apache/hadoop/hbase/util/ShutdownHookManager;
      38: return
    Exception table:
       from    to  target type
           4    23    26   Class java/lang/Exception
}
