Compiled from "ShutdownHookManager.java"
class org.apache.hadoop.hbase.util.ShutdownHookManager$ShutdownHookManagerV1 extends org.apache.hadoop.hbase.util.ShutdownHookManager {
  public void addShutdownHook(java.lang.Thread, int);
    Code:
       0: invokestatic  #3                  // Method java/lang/Runtime.getRuntime:()Ljava/lang/Runtime;
       3: aload_1
       4: invokevirtual #4                  // Method java/lang/Runtime.addShutdownHook:(Ljava/lang/Thread;)V
       7: return

  public boolean removeShutdownHook(java.lang.Runnable);
    Code:
       0: aconst_null
       1: astore_2
       2: aload_1
       3: instanceof    #5                  // class java/lang/Thread
       6: ifne          21
       9: new           #5                  // class java/lang/Thread
      12: dup
      13: aload_1
      14: invokespecial #6                  // Method java/lang/Thread."<init>":(Ljava/lang/Runnable;)V
      17: astore_2
      18: goto          26
      21: aload_1
      22: checkcast     #5                  // class java/lang/Thread
      25: astore_2
      26: invokestatic  #3                  // Method java/lang/Runtime.getRuntime:()Ljava/lang/Runtime;
      29: aload_2
      30: invokevirtual #7                  // Method java/lang/Runtime.removeShutdownHook:(Ljava/lang/Thread;)Z
      33: ireturn

  org.apache.hadoop.hbase.util.ShutdownHookManager$ShutdownHookManagerV1(org.apache.hadoop.hbase.util.ShutdownHookManager$1);
    Code:
       0: aload_0
       1: invokespecial #1                  // Method "<init>":()V
       4: return
}
