Compiled from "SimpleScanResultConsumer.java"
final class org.apache.hadoop.hbase.client.SimpleScanResultConsumer implements org.apache.hadoop.hbase.client.ScanResultConsumer {
  org.apache.hadoop.hbase.client.SimpleScanResultConsumer();
    Code:
       0: aload_0
       1: invokespecial #1                  // Method java/lang/Object."<init>":()V
       4: aload_0
       5: new           #2                  // class java/util/ArrayList
       8: dup
       9: invokespecial #3                  // Method java/util/ArrayList."<init>":()V
      12: putfield      #4                  // Field results:Ljava/util/List;
      15: aload_0
      16: iconst_0
      17: putfield      #5                  // Field finished:Z
      20: return

  public void onScanMetricsCreated(org.apache.hadoop.hbase.client.metrics.ScanMetrics);
    Code:
       0: aload_0
       1: aload_1
       2: putfield      #6                  // Field scanMetrics:Lorg/apache/hadoop/hbase/client/metrics/ScanMetrics;
       5: return

  public synchronized boolean onNext(org.apache.hadoop.hbase.client.Result);
    Code:
       0: aload_0
       1: getfield      #4                  // Field results:Ljava/util/List;
       4: aload_1
       5: invokeinterface #7,  2            // InterfaceMethod java/util/List.add:(Ljava/lang/Object;)Z
      10: pop
      11: iconst_1
      12: ireturn

  public synchronized void onError(java.lang.Throwable);
    Code:
       0: aload_0
       1: aload_1
       2: putfield      #8                  // Field error:Ljava/lang/Throwable;
       5: aload_0
       6: iconst_1
       7: putfield      #5                  // Field finished:Z
      10: aload_0
      11: invokevirtual #9                  // Method java/lang/Object.notifyAll:()V
      14: return

  public synchronized void onComplete();
    Code:
       0: aload_0
       1: iconst_1
       2: putfield      #5                  // Field finished:Z
       5: aload_0
       6: invokevirtual #9                  // Method java/lang/Object.notifyAll:()V
       9: return

  public synchronized java.util.List<org.apache.hadoop.hbase.client.Result> getAll() throws java.lang.Exception;
    Code:
       0: aload_0
       1: getfield      #5                  // Field finished:Z
       4: ifne          14
       7: aload_0
       8: invokevirtual #10                 // Method java/lang/Object.wait:()V
      11: goto          0
      14: aload_0
      15: getfield      #8                  // Field error:Ljava/lang/Throwable;
      18: ifnull        42
      21: aload_0
      22: getfield      #8                  // Field error:Ljava/lang/Throwable;
      25: ldc           #11                 // class java/lang/Exception
      27: invokestatic  #12                 // Method org/apache/hbase/thirdparty/com/google/common/base/Throwables.propagateIfPossible:(Ljava/lang/Throwable;Ljava/lang/Class;)V
      30: new           #11                 // class java/lang/Exception
      33: dup
      34: aload_0
      35: getfield      #8                  // Field error:Ljava/lang/Throwable;
      38: invokespecial #13                 // Method java/lang/Exception."<init>":(Ljava/lang/Throwable;)V
      41: athrow
      42: aload_0
      43: getfield      #4                  // Field results:Ljava/util/List;
      46: areturn

  public org.apache.hadoop.hbase.client.metrics.ScanMetrics getScanMetrics();
    Code:
       0: aload_0
       1: getfield      #6                  // Field scanMetrics:Lorg/apache/hadoop/hbase/client/metrics/ScanMetrics;
       4: areturn
}
