Compiled from "SimpleLoadBalancer.java"
class org.apache.hadoop.hbase.master.balancer.SimpleLoadBalancer$1 implements java.util.Comparator<org.apache.hadoop.hbase.master.balancer.ServerAndLoad> {
  final org.apache.hadoop.hbase.master.balancer.SimpleLoadBalancer this$0;

  org.apache.hadoop.hbase.master.balancer.SimpleLoadBalancer$1(org.apache.hadoop.hbase.master.balancer.SimpleLoadBalancer);
    Code:
       0: aload_0
       1: aload_1
       2: putfield      #1                  // Field this$0:Lorg/apache/hadoop/hbase/master/balancer/SimpleLoadBalancer;
       5: aload_0
       6: invokespecial #2                  // Method java/lang/Object."<init>":()V
       9: return

  public int compare(org.apache.hadoop.hbase.master.balancer.ServerAndLoad, org.apache.hadoop.hbase.master.balancer.ServerAndLoad);
    Code:
       0: aload_1
       1: invokevirtual #3                  // Method org/apache/hadoop/hbase/master/balancer/ServerAndLoad.getLoad:()I
       4: aload_2
       5: invokevirtual #3                  // Method org/apache/hadoop/hbase/master/balancer/ServerAndLoad.getLoad:()I
       8: if_icmpne     13
      11: iconst_0
      12: ireturn
      13: aload_1
      14: invokevirtual #3                  // Method org/apache/hadoop/hbase/master/balancer/ServerAndLoad.getLoad:()I
      17: aload_2
      18: invokevirtual #3                  // Method org/apache/hadoop/hbase/master/balancer/ServerAndLoad.getLoad:()I
      21: if_icmple     28
      24: iconst_1
      25: goto          29
      28: iconst_m1
      29: ireturn

  public int compare(java.lang.Object, java.lang.Object);
    Code:
       0: aload_0
       1: aload_1
       2: checkcast     #4                  // class org/apache/hadoop/hbase/master/balancer/ServerAndLoad
       5: aload_2
       6: checkcast     #4                  // class org/apache/hadoop/hbase/master/balancer/ServerAndLoad
       9: invokevirtual #5                  // Method compare:(Lorg/apache/hadoop/hbase/master/balancer/ServerAndLoad;Lorg/apache/hadoop/hbase/master/balancer/ServerAndLoad;)I
      12: ireturn
}
