Compiled from "SimpleRegionNormalizer.java"
public class org.apache.hadoop.hbase.master.normalizer.SimpleRegionNormalizer implements org.apache.hadoop.hbase.master.normalizer.RegionNormalizer {
  public org.apache.hadoop.hbase.master.normalizer.SimpleRegionNormalizer();
    Code:
       0: aload_0
       1: invokespecial #1                  // Method java/lang/Object."<init>":()V
       4: aload_0
       5: new           #2                  // class org/apache/hadoop/hbase/master/normalizer/SimpleRegionNormalizer$PlanComparator
       8: dup
       9: invokespecial #3                  // Method org/apache/hadoop/hbase/master/normalizer/SimpleRegionNormalizer$PlanComparator."<init>":()V
      12: putfield      #4                  // Field planComparator:Ljava/util/Comparator;
      15: aload_0
      16: invokestatic  #5                  // Method org/apache/hadoop/hbase/HBaseConfiguration.create:()Lorg/apache/hadoop/conf/Configuration;
      19: ldc           #6                  // String hbase.normalizer.min.region.count
      21: iconst_3
      22: invokevirtual #7                  // Method org/apache/hadoop/conf/Configuration.getInt:(Ljava/lang/String;I)I
      25: putfield      #8                  // Field minRegionCount:I
      28: return

  public void setMasterServices(org.apache.hadoop.hbase.master.MasterServices);
    Code:
       0: aload_0
       1: aload_1
       2: putfield      #9                  // Field masterServices:Lorg/apache/hadoop/hbase/master/MasterServices;
       5: return

  public void setMasterRpcServices(org.apache.hadoop.hbase.master.MasterRpcServices);
    Code:
       0: aload_0
       1: aload_1
       2: putfield      #10                 // Field masterRpcServices:Lorg/apache/hadoop/hbase/master/MasterRpcServices;
       5: return

  public void planSkipped(org.apache.hadoop.hbase.client.RegionInfo, org.apache.hadoop.hbase.master.normalizer.NormalizationPlan$PlanType);
    Code:
       0: getstatic     #11                 // Field skippedCount:[J
       3: aload_2
       4: invokevirtual #12                 // Method org/apache/hadoop/hbase/master/normalizer/NormalizationPlan$PlanType.ordinal:()I
       7: dup2
       8: laload
       9: lconst_1
      10: ladd
      11: lastore
      12: return

  public long getSkippedCount(org.apache.hadoop.hbase.master.normalizer.NormalizationPlan$PlanType);
    Code:
       0: getstatic     #11                 // Field skippedCount:[J
       3: aload_1
       4: invokevirtual #12                 // Method org/apache/hadoop/hbase/master/normalizer/NormalizationPlan$PlanType.ordinal:()I
       7: laload
       8: lreturn

  public java.util.List<org.apache.hadoop.hbase.master.normalizer.NormalizationPlan> computePlanForTable(org.apache.hadoop.hbase.TableName) throws org.apache.hadoop.hbase.HBaseIOException;
    Code:
       0: aload_1
       1: ifnull        11
       4: aload_1
       5: invokevirtual #13                 // Method org/apache/hadoop/hbase/TableName.isSystemTable:()Z
       8: ifeq          45
      11: getstatic     #14                 // Field LOG:Lorg/slf4j/Logger;
      14: new           #15                 // class java/lang/StringBuilder
      17: dup
      18: invokespecial #16                 // Method java/lang/StringBuilder."<init>":()V
      21: ldc           #17                 // String Normalization of system table
      23: invokevirtual #18                 // Method java/lang/StringBuilder.append:(Ljava/lang/String;)Ljava/lang/StringBuilder;
      26: aload_1
      27: invokevirtual #19                 // Method java/lang/StringBuilder.append:(Ljava/lang/Object;)Ljava/lang/StringBuilder;
      30: ldc           #20                 // String  isn't allowed
      32: invokevirtual #18                 // Method java/lang/StringBuilder.append:(Ljava/lang/String;)Ljava/lang/StringBuilder;
      35: invokevirtual #21                 // Method java/lang/StringBuilder.toString:()Ljava/lang/String;
      38: invokeinterface #22,  2           // InterfaceMethod org/slf4j/Logger.debug:(Ljava/lang/String;)V
      43: aconst_null
      44: areturn
      45: new           #23                 // class java/util/ArrayList
      48: dup
      49: invokespecial #24                 // Method java/util/ArrayList."<init>":()V
      52: astore_2
      53: aload_0
      54: getfield      #9                  // Field masterServices:Lorg/apache/hadoop/hbase/master/MasterServices;
      57: invokeinterface #25,  1           // InterfaceMethod org/apache/hadoop/hbase/master/MasterServices.getAssignmentManager:()Lorg/apache/hadoop/hbase/master/assignment/AssignmentManager;
      62: invokevirtual #26                 // Method org/apache/hadoop/hbase/master/assignment/AssignmentManager.getRegionStates:()Lorg/apache/hadoop/hbase/master/assignment/RegionStates;
      65: aload_1
      66: invokevirtual #27                 // Method org/apache/hadoop/hbase/master/assignment/RegionStates.getRegionsOfTable:(Lorg/apache/hadoop/hbase/TableName;)Ljava/util/List;
      69: astore_3
      70: aload_3
      71: ifnull        87
      74: aload_3
      75: invokeinterface #28,  1           // InterfaceMethod java/util/List.size:()I
      80: aload_0
      81: getfield      #8                  // Field minRegionCount:I
      84: if_icmpge     159
      87: aload_3
      88: ifnonnull     95
      91: iconst_0
      92: goto          101
      95: aload_3
      96: invokeinterface #28,  1           // InterfaceMethod java/util/List.size:()I
     101: istore        4
     103: getstatic     #14                 // Field LOG:Lorg/slf4j/Logger;
     106: new           #15                 // class java/lang/StringBuilder
     109: dup
     110: invokespecial #16                 // Method java/lang/StringBuilder."<init>":()V
     113: ldc           #29                 // String Table
     115: invokevirtual #18                 // Method java/lang/StringBuilder.append:(Ljava/lang/String;)Ljava/lang/StringBuilder;
     118: aload_1
     119: invokevirtual #19                 // Method java/lang/StringBuilder.append:(Ljava/lang/Object;)Ljava/lang/StringBuilder;
     122: ldc           #30                 // String  has
     124: invokevirtual #18                 // Method java/lang/StringBuilder.append:(Ljava/lang/String;)Ljava/lang/StringBuilder;
     127: iload         4
     129: invokevirtual #31                 // Method java/lang/StringBuilder.append:(I)Ljava/lang/StringBuilder;
     132: ldc           #32                 // String  regions, required min number of regions for normalizer to run is
     134: invokevirtual #18                 // Method java/lang/StringBuilder.append:(Ljava/lang/String;)Ljava/lang/StringBuilder;
     137: aload_0
     138: getfield      #8                  // Field minRegionCount:I
     141: invokevirtual #31                 // Method java/lang/StringBuilder.append:(I)Ljava/lang/StringBuilder;
     144: ldc           #33                 // String , not running normalizer
     146: invokevirtual #18                 // Method java/lang/StringBuilder.append:(Ljava/lang/String;)Ljava/lang/StringBuilder;
     149: invokevirtual #21                 // Method java/lang/StringBuilder.toString:()Ljava/lang/String;
     152: invokeinterface #22,  2           // InterfaceMethod org/slf4j/Logger.debug:(Ljava/lang/String;)V
     157: aconst_null
     158: areturn
     159: getstatic     #14                 // Field LOG:Lorg/slf4j/Logger;
     162: new           #15                 // class java/lang/StringBuilder
     165: dup
     166: invokespecial #16                 // Method java/lang/StringBuilder."<init>":()V
     169: ldc           #34                 // String Computing normalization plan for table:
     171: invokevirtual #18                 // Method java/lang/StringBuilder.append:(Ljava/lang/String;)Ljava/lang/StringBuilder;
     174: aload_1
     175: invokevirtual #19                 // Method java/lang/StringBuilder.append:(Ljava/lang/Object;)Ljava/lang/StringBuilder;
     178: ldc           #35                 // String , number of regions:
     180: invokevirtual #18                 // Method java/lang/StringBuilder.append:(Ljava/lang/String;)Ljava/lang/StringBuilder;
     183: aload_3
     184: invokeinterface #28,  1           // InterfaceMethod java/util/List.size:()I
     189: invokevirtual #31                 // Method java/lang/StringBuilder.append:(I)Ljava/lang/StringBuilder;
     192: invokevirtual #21                 // Method java/lang/StringBuilder.toString:()Ljava/lang/String;
     195: invokeinterface #22,  2           // InterfaceMethod org/slf4j/Logger.debug:(Ljava/lang/String;)V
     200: lconst_0
     201: lstore        4
     203: iconst_0
     204: istore        6
     206: iconst_0
     207: istore        7
     209: iload         7
     211: aload_3
     212: invokeinterface #28,  1           // InterfaceMethod java/util/List.size:()I
     217: if_icmpge     264
     220: aload_3
     221: iload         7
     223: invokeinterface #36,  2           // InterfaceMethod java/util/List.get:(I)Ljava/lang/Object;
     228: checkcast     #37                 // class org/apache/hadoop/hbase/client/RegionInfo
     231: astore        8
     233: aload_0
     234: aload         8
     236: invokespecial #38                 // Method getRegionSize:(Lorg/apache/hadoop/hbase/client/RegionInfo;)J
     239: lstore        9
     241: lload         9
     243: lconst_0
     244: lcmp
     245: ifle          258
     248: iinc          6, 1
     251: lload         4
     253: lload         9
     255: ladd
     256: lstore        4
     258: iinc          7, 1
     261: goto          209
     264: iconst_m1
     265: istore        7
     267: ldc2_w        #39                 // long -1l
     270: lstore        8
     272: aload_0
     273: getfield      #9                  // Field masterServices:Lorg/apache/hadoop/hbase/master/MasterServices;
     276: invokeinterface #41,  1           // InterfaceMethod org/apache/hadoop/hbase/master/MasterServices.getTableDescriptors:()Lorg/apache/hadoop/hbase/TableDescriptors;
     281: aload_1
     282: invokeinterface #42,  2           // InterfaceMethod org/apache/hadoop/hbase/TableDescriptors.get:(Lorg/apache/hadoop/hbase/TableName;)Lorg/apache/hadoop/hbase/client/TableDescriptor;
     287: astore        10
     289: aload         10
     291: ifnull        346
     294: aload         10
     296: invokeinterface #43,  1           // InterfaceMethod org/apache/hadoop/hbase/client/TableDescriptor.getNormalizerTargetRegionCount:()I
     301: istore        7
     303: aload         10
     305: invokeinterface #44,  1           // InterfaceMethod org/apache/hadoop/hbase/client/TableDescriptor.getNormalizerTargetRegionSize:()J
     310: lstore        8
     312: getstatic     #14                 // Field LOG:Lorg/slf4j/Logger;
     315: ldc           #45                 // String Table {}:  target region count is {}, target region size is {}
     317: iconst_3
     318: anewarray     #46                 // class java/lang/Object
     321: dup
     322: iconst_0
     323: aload_1
     324: aastore
     325: dup
     326: iconst_1
     327: iload         7
     329: invokestatic  #47                 // Method java/lang/Integer.valueOf:(I)Ljava/lang/Integer;
     332: aastore
     333: dup
     334: iconst_2
     335: lload         8
     337: invokestatic  #48                 // Method java/lang/Long.valueOf:(J)Ljava/lang/Long;
     340: aastore
     341: invokeinterface #49,  3           // InterfaceMethod org/slf4j/Logger.debug:(Ljava/lang/String;[Ljava/lang/Object;)V
     346: goto          362
     349: astore        10
     351: getstatic     #14                 // Field LOG:Lorg/slf4j/Logger;
     354: ldc           #51                 // String cannot get the target number and target size of table {}, they will be default value -1.
     356: aload_1
     357: invokeinterface #52,  3           // InterfaceMethod org/slf4j/Logger.warn:(Ljava/lang/String;Ljava/lang/Object;)V
     362: lload         8
     364: lconst_0
     365: lcmp
     366: ifle          377
     369: lload         8
     371: l2d
     372: dstore        10
     374: goto          412
     377: iload         7
     379: ifle          394
     382: lload         4
     384: l2d
     385: iload         7
     387: i2d
     388: ddiv
     389: dstore        10
     391: goto          412
     394: iload         6
     396: ifne          403
     399: dconst_0
     400: goto          410
     403: lload         4
     405: l2d
     406: iload         6
     408: i2d
     409: ddiv
     410: dstore        10
     412: getstatic     #14                 // Field LOG:Lorg/slf4j/Logger;
     415: new           #15                 // class java/lang/StringBuilder
     418: dup
     419: invokespecial #16                 // Method java/lang/StringBuilder."<init>":()V
     422: ldc           #29                 // String Table
     424: invokevirtual #18                 // Method java/lang/StringBuilder.append:(Ljava/lang/String;)Ljava/lang/StringBuilder;
     427: aload_1
     428: invokevirtual #19                 // Method java/lang/StringBuilder.append:(Ljava/lang/Object;)Ljava/lang/StringBuilder;
     431: ldc           #53                 // String , total aggregated regions size:
     433: invokevirtual #18                 // Method java/lang/StringBuilder.append:(Ljava/lang/String;)Ljava/lang/StringBuilder;
     436: lload         4
     438: invokevirtual #54                 // Method java/lang/StringBuilder.append:(J)Ljava/lang/StringBuilder;
     441: invokevirtual #21                 // Method java/lang/StringBuilder.toString:()Ljava/lang/String;
     444: invokeinterface #22,  2           // InterfaceMethod org/slf4j/Logger.debug:(Ljava/lang/String;)V
     449: getstatic     #14                 // Field LOG:Lorg/slf4j/Logger;
     452: new           #15                 // class java/lang/StringBuilder
     455: dup
     456: invokespecial #16                 // Method java/lang/StringBuilder."<init>":()V
     459: ldc           #29                 // String Table
     461: invokevirtual #18                 // Method java/lang/StringBuilder.append:(Ljava/lang/String;)Ljava/lang/StringBuilder;
     464: aload_1
     465: invokevirtual #19                 // Method java/lang/StringBuilder.append:(Ljava/lang/Object;)Ljava/lang/StringBuilder;
     468: ldc           #55                 // String , average region size:
     470: invokevirtual #18                 // Method java/lang/StringBuilder.append:(Ljava/lang/String;)Ljava/lang/StringBuilder;
     473: dload         10
     475: invokevirtual #56                 // Method java/lang/StringBuilder.append:(D)Ljava/lang/StringBuilder;
     478: invokevirtual #21                 // Method java/lang/StringBuilder.toString:()Ljava/lang/String;
     481: invokeinterface #22,  2           // InterfaceMethod org/slf4j/Logger.debug:(Ljava/lang/String;)V
     486: iconst_0
     487: istore        12
     489: iconst_1
     490: istore        13
     492: iconst_1
     493: istore        14
     495: aload_0
     496: getfield      #10                 // Field masterRpcServices:Lorg/apache/hadoop/hbase/master/MasterRpcServices;
     499: aconst_null
     500: getstatic     #57                 // Field org/apache/hadoop/hbase/client/MasterSwitchType.SPLIT:Lorg/apache/hadoop/hbase/client/MasterSwitchType;
     503: invokestatic  #58                 // Method org/apache/hadoop/hbase/shaded/protobuf/RequestConverter.buildIsSplitOrMergeEnabledRequest:(Lorg/apache/hadoop/hbase/client/MasterSwitchType;)Lorg/apache/hadoop/hbase/shaded/protobuf/generated/MasterProtos$IsSplitOrMergeEnabledRequest;
     506: invokevirtual #59                 // Method org/apache/hadoop/hbase/master/MasterRpcServices.isSplitOrMergeEnabled:(Lorg/apache/hbase/thirdparty/com/google/protobuf/RpcController;Lorg/apache/hadoop/hbase/shaded/protobuf/generated/MasterProtos$IsSplitOrMergeEnabledRequest;)Lorg/apache/hadoop/hbase/shaded/protobuf/generated/MasterProtos$IsSplitOrMergeEnabledResponse;
     509: invokevirtual #60                 // Method org/apache/hadoop/hbase/shaded/protobuf/generated/MasterProtos$IsSplitOrMergeEnabledResponse.getEnabled:()Z
     512: istore        13
     514: goto          531
     517: astore        15
     519: getstatic     #14                 // Field LOG:Lorg/slf4j/Logger;
     522: ldc           #62                 // String Unable to determine whether split is enabled
     524: aload         15
     526: invokeinterface #63,  3           // InterfaceMethod org/slf4j/Logger.debug:(Ljava/lang/String;Ljava/lang/Throwable;)V
     531: aload_0
     532: getfield      #10                 // Field masterRpcServices:Lorg/apache/hadoop/hbase/master/MasterRpcServices;
     535: aconst_null
     536: getstatic     #64                 // Field org/apache/hadoop/hbase/client/MasterSwitchType.MERGE:Lorg/apache/hadoop/hbase/client/MasterSwitchType;
     539: invokestatic  #58                 // Method org/apache/hadoop/hbase/shaded/protobuf/RequestConverter.buildIsSplitOrMergeEnabledRequest:(Lorg/apache/hadoop/hbase/client/MasterSwitchType;)Lorg/apache/hadoop/hbase/shaded/protobuf/generated/MasterProtos$IsSplitOrMergeEnabledRequest;
     542: invokevirtual #59                 // Method org/apache/hadoop/hbase/master/MasterRpcServices.isSplitOrMergeEnabled:(Lorg/apache/hbase/thirdparty/com/google/protobuf/RpcController;Lorg/apache/hadoop/hbase/shaded/protobuf/generated/MasterProtos$IsSplitOrMergeEnabledRequest;)Lorg/apache/hadoop/hbase/shaded/protobuf/generated/MasterProtos$IsSplitOrMergeEnabledResponse;
     545: invokevirtual #60                 // Method org/apache/hadoop/hbase/shaded/protobuf/generated/MasterProtos$IsSplitOrMergeEnabledResponse.getEnabled:()Z
     548: istore        14
     550: goto          567
     553: astore        15
     555: getstatic     #14                 // Field LOG:Lorg/slf4j/Logger;
     558: ldc           #62                 // String Unable to determine whether split is enabled
     560: aload         15
     562: invokeinterface #63,  3           // InterfaceMethod org/slf4j/Logger.debug:(Ljava/lang/String;Ljava/lang/Throwable;)V
     567: iload         12
     569: aload_3
     570: invokeinterface #28,  1           // InterfaceMethod java/util/List.size:()I
     575: if_icmpge     853
     578: aload_3
     579: iload         12
     581: invokeinterface #36,  2           // InterfaceMethod java/util/List.get:(I)Ljava/lang/Object;
     586: checkcast     #37                 // class org/apache/hadoop/hbase/client/RegionInfo
     589: astore        15
     591: aload_0
     592: aload         15
     594: invokespecial #38                 // Method getRegionSize:(Lorg/apache/hadoop/hbase/client/RegionInfo;)J
     597: lstore        16
     599: lload         16
     601: l2d
     602: ldc2_w        #65                 // double 2.0d
     605: dload         10
     607: dmul
     608: dcmpl
     609: ifle          694
     612: iload         13
     614: ifeq          847
     617: getstatic     #14                 // Field LOG:Lorg/slf4j/Logger;
     620: new           #15                 // class java/lang/StringBuilder
     623: dup
     624: invokespecial #16                 // Method java/lang/StringBuilder."<init>":()V
     627: ldc           #29                 // String Table
     629: invokevirtual #18                 // Method java/lang/StringBuilder.append:(Ljava/lang/String;)Ljava/lang/StringBuilder;
     632: aload_1
     633: invokevirtual #19                 // Method java/lang/StringBuilder.append:(Ljava/lang/Object;)Ljava/lang/StringBuilder;
     636: ldc           #67                 // String , large region
     638: invokevirtual #18                 // Method java/lang/StringBuilder.append:(Ljava/lang/String;)Ljava/lang/StringBuilder;
     641: aload         15
     643: invokeinterface #68,  1           // InterfaceMethod org/apache/hadoop/hbase/client/RegionInfo.getRegionNameAsString:()Ljava/lang/String;
     648: invokevirtual #18                 // Method java/lang/StringBuilder.append:(Ljava/lang/String;)Ljava/lang/StringBuilder;
     651: ldc           #69                 // String  has size
     653: invokevirtual #18                 // Method java/lang/StringBuilder.append:(Ljava/lang/String;)Ljava/lang/StringBuilder;
     656: lload         16
     658: invokevirtual #54                 // Method java/lang/StringBuilder.append:(J)Ljava/lang/StringBuilder;
     661: ldc           #70                 // String , more than twice avg size, splitting
     663: invokevirtual #18                 // Method java/lang/StringBuilder.append:(Ljava/lang/String;)Ljava/lang/StringBuilder;
     666: invokevirtual #21                 // Method java/lang/StringBuilder.toString:()Ljava/lang/String;
     669: invokeinterface #71,  2           // InterfaceMethod org/slf4j/Logger.info:(Ljava/lang/String;)V
     674: aload_2
     675: new           #72                 // class org/apache/hadoop/hbase/master/normalizer/SplitNormalizationPlan
     678: dup
     679: aload         15
     681: aconst_null
     682: invokespecial #73                 // Method org/apache/hadoop/hbase/master/normalizer/SplitNormalizationPlan."<init>":(Lorg/apache/hadoop/hbase/client/RegionInfo;[B)V
     685: invokeinterface #74,  2           // InterfaceMethod java/util/List.add:(Ljava/lang/Object;)Z
     690: pop
     691: goto          847
     694: iload         12
     696: aload_3
     697: invokeinterface #28,  1           // InterfaceMethod java/util/List.size:()I
     702: iconst_1
     703: isub
     704: if_icmpne     710
     707: goto          853
     710: iload         14
     712: ifeq          847
     715: aload_3
     716: iload         12
     718: iconst_1
     719: iadd
     720: invokeinterface #36,  2           // InterfaceMethod java/util/List.get:(I)Ljava/lang/Object;
     725: checkcast     #37                 // class org/apache/hadoop/hbase/client/RegionInfo
     728: astore        18
     730: aload_0
     731: aload         18
     733: invokespecial #38                 // Method getRegionSize:(Lorg/apache/hadoop/hbase/client/RegionInfo;)J
     736: lstore        19
     738: lload         16
     740: lconst_0
     741: lcmp
     742: iflt          847
     745: lload         19
     747: lconst_0
     748: lcmp
     749: iflt          847
     752: lload         16
     754: lload         19
     756: ladd
     757: l2d
     758: dload         10
     760: dcmpg
     761: ifge          847
     764: getstatic     #14                 // Field LOG:Lorg/slf4j/Logger;
     767: new           #15                 // class java/lang/StringBuilder
     770: dup
     771: invokespecial #16                 // Method java/lang/StringBuilder."<init>":()V
     774: ldc           #29                 // String Table
     776: invokevirtual #18                 // Method java/lang/StringBuilder.append:(Ljava/lang/String;)Ljava/lang/StringBuilder;
     779: aload_1
     780: invokevirtual #19                 // Method java/lang/StringBuilder.append:(Ljava/lang/Object;)Ljava/lang/StringBuilder;
     783: ldc           #75                 // String , small region size:
     785: invokevirtual #18                 // Method java/lang/StringBuilder.append:(Ljava/lang/String;)Ljava/lang/StringBuilder;
     788: lload         16
     790: invokevirtual #54                 // Method java/lang/StringBuilder.append:(J)Ljava/lang/StringBuilder;
     793: ldc           #76                 // String  plus its neighbor size:
     795: invokevirtual #18                 // Method java/lang/StringBuilder.append:(Ljava/lang/String;)Ljava/lang/StringBuilder;
     798: lload         19
     800: invokevirtual #54                 // Method java/lang/StringBuilder.append:(J)Ljava/lang/StringBuilder;
     803: ldc           #77                 // String , less than the avg size
     805: invokevirtual #18                 // Method java/lang/StringBuilder.append:(Ljava/lang/String;)Ljava/lang/StringBuilder;
     808: dload         10
     810: invokevirtual #56                 // Method java/lang/StringBuilder.append:(D)Ljava/lang/StringBuilder;
     813: ldc           #78                 // String , merging them
     815: invokevirtual #18                 // Method java/lang/StringBuilder.append:(Ljava/lang/String;)Ljava/lang/StringBuilder;
     818: invokevirtual #21                 // Method java/lang/StringBuilder.toString:()Ljava/lang/String;
     821: invokeinterface #71,  2           // InterfaceMethod org/slf4j/Logger.info:(Ljava/lang/String;)V
     826: aload_2
     827: new           #79                 // class org/apache/hadoop/hbase/master/normalizer/MergeNormalizationPlan
     830: dup
     831: aload         15
     833: aload         18
     835: invokespecial #80                 // Method org/apache/hadoop/hbase/master/normalizer/MergeNormalizationPlan."<init>":(Lorg/apache/hadoop/hbase/client/RegionInfo;Lorg/apache/hadoop/hbase/client/RegionInfo;)V
     838: invokeinterface #74,  2           // InterfaceMethod java/util/List.add:(Ljava/lang/Object;)Z
     843: pop
     844: iinc          12, 1
     847: iinc          12, 1
     850: goto          567
     853: aload_2
     854: invokeinterface #81,  1           // InterfaceMethod java/util/List.isEmpty:()Z
     859: ifeq          891
     862: getstatic     #14                 // Field LOG:Lorg/slf4j/Logger;
     865: new           #15                 // class java/lang/StringBuilder
     868: dup
     869: invokespecial #16                 // Method java/lang/StringBuilder."<init>":()V
     872: ldc           #82                 // String No normalization needed, regions look good for table:
     874: invokevirtual #18                 // Method java/lang/StringBuilder.append:(Ljava/lang/String;)Ljava/lang/StringBuilder;
     877: aload_1
     878: invokevirtual #19                 // Method java/lang/StringBuilder.append:(Ljava/lang/Object;)Ljava/lang/StringBuilder;
     881: invokevirtual #21                 // Method java/lang/StringBuilder.toString:()Ljava/lang/String;
     884: invokeinterface #22,  2           // InterfaceMethod org/slf4j/Logger.debug:(Ljava/lang/String;)V
     889: aconst_null
     890: areturn
     891: aload_2
     892: aload_0
     893: getfield      #4                  // Field planComparator:Ljava/util/Comparator;
     896: invokestatic  #83                 // Method java/util/Collections.sort:(Ljava/util/List;Ljava/util/Comparator;)V
     899: aload_2
     900: areturn
    Exception table:
       from    to  target type
         272   346   349   Class java/io/IOException
         495   514   517   Class org/apache/hbase/thirdparty/com/google/protobuf/ServiceException
         531   550   553   Class org/apache/hbase/thirdparty/com/google/protobuf/ServiceException

  static {};
    Code:
       0: ldc           #95                 // class org/apache/hadoop/hbase/master/normalizer/SimpleRegionNormalizer
       2: invokestatic  #96                 // Method org/slf4j/LoggerFactory.getLogger:(Ljava/lang/Class;)Lorg/slf4j/Logger;
       5: putstatic     #14                 // Field LOG:Lorg/slf4j/Logger;
       8: invokestatic  #97                 // Method org/apache/hadoop/hbase/master/normalizer/NormalizationPlan$PlanType.values:()[Lorg/apache/hadoop/hbase/master/normalizer/NormalizationPlan$PlanType;
      11: arraylength
      12: newarray       long
      14: putstatic     #11                 // Field skippedCount:[J
      17: return
}
