Compiled from "SimpleServerRpcConnection.java"
class org.apache.hadoop.hbase.ipc.SimpleServerRpcConnection$1 extends java.io.InputStream {
  final java.nio.ByteBuffer val$buf;

  final org.apache.hadoop.hbase.ipc.SimpleServerRpcConnection this$0;

  org.apache.hadoop.hbase.ipc.SimpleServerRpcConnection$1(org.apache.hadoop.hbase.ipc.SimpleServerRpcConnection, java.nio.ByteBuffer);
    Code:
       0: aload_0
       1: aload_1
       2: putfield      #1                  // Field this$0:Lorg/apache/hadoop/hbase/ipc/SimpleServerRpcConnection;
       5: aload_0
       6: aload_2
       7: putfield      #2                  // Field val$buf:Ljava/nio/ByteBuffer;
      10: aload_0
      11: invokespecial #3                  // Method java/io/InputStream."<init>":()V
      14: return

  public int read() throws java.io.IOException;
    Code:
       0: aload_0
       1: getfield      #1                  // Field this$0:Lorg/apache/hadoop/hbase/ipc/SimpleServerRpcConnection;
       4: getfield      #4                  // Field org/apache/hadoop/hbase/ipc/SimpleServerRpcConnection.rpcServer:Lorg/apache/hadoop/hbase/ipc/RpcServer;
       7: aload_0
       8: getfield      #1                  // Field this$0:Lorg/apache/hadoop/hbase/ipc/SimpleServerRpcConnection;
      11: getfield      #5                  // Field org/apache/hadoop/hbase/ipc/SimpleServerRpcConnection.channel:Ljava/nio/channels/SocketChannel;
      14: aload_0
      15: getfield      #2                  // Field val$buf:Ljava/nio/ByteBuffer;
      18: invokevirtual #6                  // Method org/apache/hadoop/hbase/ipc/RpcServer.channelRead:(Ljava/nio/channels/ReadableByteChannel;Ljava/nio/ByteBuffer;)I
      21: pop
      22: aload_0
      23: getfield      #2                  // Field val$buf:Ljava/nio/ByteBuffer;
      26: invokevirtual #7                  // Method java/nio/ByteBuffer.flip:()Ljava/nio/Buffer;
      29: pop
      30: aload_0
      31: getfield      #2                  // Field val$buf:Ljava/nio/ByteBuffer;
      34: invokevirtual #8                  // Method java/nio/ByteBuffer.get:()B
      37: istore_1
      38: aload_0
      39: getfield      #2                  // Field val$buf:Ljava/nio/ByteBuffer;
      42: invokevirtual #7                  // Method java/nio/ByteBuffer.flip:()Ljava/nio/Buffer;
      45: pop
      46: iload_1
      47: ireturn
}
