Compiled from "SimpleServerCall.java"
class org.apache.hadoop.hbase.ipc.SimpleServerCall extends org.apache.hadoop.hbase.ipc.ServerCall<org.apache.hadoop.hbase.ipc.SimpleServerRpcConnection> {
  final org.apache.hadoop.hbase.ipc.SimpleRpcServerResponder responder;

  org.apache.hadoop.hbase.ipc.SimpleServerCall(int, org.apache.hbase.thirdparty.com.google.protobuf.BlockingService, org.apache.hbase.thirdparty.com.google.protobuf.Descriptors$MethodDescriptor, org.apache.hadoop.hbase.shaded.protobuf.generated.RPCProtos$RequestHeader, org.apache.hbase.thirdparty.com.google.protobuf.Message, org.apache.hadoop.hbase.CellScanner, org.apache.hadoop.hbase.ipc.SimpleServerRpcConnection, long, java.net.InetAddress, long, int, org.apache.hadoop.hbase.io.ByteBufferPool, org.apache.hadoop.hbase.ipc.CellBlockBuilder, org.apache.hadoop.hbase.ipc.RpcServer$CallCleanup, org.apache.hadoop.hbase.ipc.SimpleRpcServerResponder);
    Code:
       0: aload_0
       1: iload_1
       2: aload_2
       3: aload_3
       4: aload         4
       6: aload         5
       8: aload         6
      10: aload         7
      12: lload         8
      14: aload         10
      16: lload         11
      18: iload         13
      20: aload         14
      22: aload         15
      24: aload         16
      26: invokespecial #1                  // Method org/apache/hadoop/hbase/ipc/ServerCall."<init>":(ILorg/apache/hbase/thirdparty/com/google/protobuf/BlockingService;Lorg/apache/hbase/thirdparty/com/google/protobuf/Descriptors$MethodDescriptor;Lorg/apache/hadoop/hbase/shaded/protobuf/generated/RPCProtos$RequestHeader;Lorg/apache/hbase/thirdparty/com/google/protobuf/Message;Lorg/apache/hadoop/hbase/CellScanner;Lorg/apache/hadoop/hbase/ipc/ServerRpcConnection;JLjava/net/InetAddress;JILorg/apache/hadoop/hbase/io/ByteBufferPool;Lorg/apache/hadoop/hbase/ipc/CellBlockBuilder;Lorg/apache/hadoop/hbase/ipc/RpcServer$CallCleanup;)V
      29: aload_0
      30: aload         17
      32: putfield      #2                  // Field responder:Lorg/apache/hadoop/hbase/ipc/SimpleRpcServerResponder;
      35: return

  public void done();
    Code:
       0: aload_0
       1: invokespecial #3                  // Method org/apache/hadoop/hbase/ipc/ServerCall.done:()V
       4: aload_0
       5: invokevirtual #4                  // Method getConnection:()Lorg/apache/hadoop/hbase/ipc/SimpleServerRpcConnection;
       8: invokevirtual #5                  // Method org/apache/hadoop/hbase/ipc/SimpleServerRpcConnection.decRpcCount:()V
      11: return

  public synchronized void sendResponseIfReady() throws java.io.IOException;
    Code:
       0: aload_0
       1: aconst_null
       2: putfield      #6                  // Field param:Lorg/apache/hbase/thirdparty/com/google/protobuf/Message;
       5: aload_0
       6: getfield      #2                  // Field responder:Lorg/apache/hadoop/hbase/ipc/SimpleRpcServerResponder;
       9: aload_0
      10: invokevirtual #4                  // Method getConnection:()Lorg/apache/hadoop/hbase/ipc/SimpleServerRpcConnection;
      13: aload_0
      14: invokevirtual #7                  // Method org/apache/hadoop/hbase/ipc/SimpleRpcServerResponder.doRespond:(Lorg/apache/hadoop/hbase/ipc/SimpleServerRpcConnection;Lorg/apache/hadoop/hbase/ipc/RpcResponse;)V
      17: return

  org.apache.hadoop.hbase.ipc.SimpleServerRpcConnection getConnection();
    Code:
       0: aload_0
       1: getfield      #8                  // Field connection:Lorg/apache/hadoop/hbase/ipc/ServerRpcConnection;
       4: checkcast     #9                  // class org/apache/hadoop/hbase/ipc/SimpleServerRpcConnection
       7: areturn
}
