Compiled from "SimpleMasterProcedureManager.java"
public class org.apache.hadoop.hbase.procedure.SimpleMasterProcedureManager extends org.apache.hadoop.hbase.procedure.MasterProcedureManager {
  public static final java.lang.String SIMPLE_SIGNATURE;

  public static final java.lang.String SIMPLE_DATA;

  public org.apache.hadoop.hbase.procedure.SimpleMasterProcedureManager();
    Code:
       0: aload_0
       1: invokespecial #1                  // Method org/apache/hadoop/hbase/procedure/MasterProcedureManager."<init>":()V
       4: return

  public void stop(java.lang.String);
    Code:
       0: getstatic     #2                  // Field LOG:Lorg/slf4j/Logger;
       3: new           #3                  // class java/lang/StringBuilder
       6: dup
       7: invokespecial #4                  // Method java/lang/StringBuilder."<init>":()V
      10: ldc           #5                  // String stop:
      12: invokevirtual #6                  // Method java/lang/StringBuilder.append:(Ljava/lang/String;)Ljava/lang/StringBuilder;
      15: aload_1
      16: invokevirtual #6                  // Method java/lang/StringBuilder.append:(Ljava/lang/String;)Ljava/lang/StringBuilder;
      19: invokevirtual #7                  // Method java/lang/StringBuilder.toString:()Ljava/lang/String;
      22: invokeinterface #8,  2            // InterfaceMethod org/slf4j/Logger.info:(Ljava/lang/String;)V
      27: return

  public boolean isStopped();
    Code:
       0: iconst_0
       1: ireturn

  public void initialize(org.apache.hadoop.hbase.master.MasterServices, org.apache.hadoop.hbase.master.MetricsMaster) throws org.apache.zookeeper.KeeperException, java.io.IOException, java.lang.UnsupportedOperationException;
    Code:
       0: aload_0
       1: aload_1
       2: putfield      #9                  // Field master:Lorg/apache/hadoop/hbase/master/MasterServices;
       5: aload_0
       6: iconst_0
       7: putfield      #10                 // Field done:Z
      10: aload_1
      11: invokeinterface #11,  1           // InterfaceMethod org/apache/hadoop/hbase/master/MasterServices.getServerName:()Lorg/apache/hadoop/hbase/ServerName;
      16: invokevirtual #12                 // Method org/apache/hadoop/hbase/ServerName.toString:()Ljava/lang/String;
      19: astore_3
      20: aload_3
      21: iconst_1
      22: invokestatic  #13                 // Method org/apache/hadoop/hbase/procedure/ProcedureCoordinator.defaultPool:(Ljava/lang/String;I)Ljava/util/concurrent/ThreadPoolExecutor;
      25: astore        4
      27: new           #14                 // class org/apache/hadoop/hbase/procedure/ZKProcedureCoordinator
      30: dup
      31: aload_1
      32: invokeinterface #15,  1           // InterfaceMethod org/apache/hadoop/hbase/master/MasterServices.getZooKeeper:()Lorg/apache/hadoop/hbase/zookeeper/ZKWatcher;
      37: aload_0
      38: invokevirtual #16                 // Method getProcedureSignature:()Ljava/lang/String;
      41: aload_3
      42: invokespecial #17                 // Method org/apache/hadoop/hbase/procedure/ZKProcedureCoordinator."<init>":(Lorg/apache/hadoop/hbase/zookeeper/ZKWatcher;Ljava/lang/String;Ljava/lang/String;)V
      45: astore        5
      47: aload_0
      48: new           #18                 // class org/apache/hadoop/hbase/procedure/ProcedureCoordinator
      51: dup
      52: aload         5
      54: aload         4
      56: invokespecial #19                 // Method org/apache/hadoop/hbase/procedure/ProcedureCoordinator."<init>":(Lorg/apache/hadoop/hbase/procedure/ProcedureCoordinatorRpcs;Ljava/util/concurrent/ThreadPoolExecutor;)V
      59: putfield      #20                 // Field coordinator:Lorg/apache/hadoop/hbase/procedure/ProcedureCoordinator;
      62: return

  public java.lang.String getProcedureSignature();
    Code:
       0: ldc           #22                 // String simple_test
       2: areturn

  public byte[] execProcedureWithRet(org.apache.hadoop.hbase.shaded.protobuf.generated.HBaseProtos$ProcedureDescription) throws java.io.IOException;
    Code:
       0: aload_0
       1: iconst_0
       2: putfield      #10                 // Field done:Z
       5: new           #23                 // class org/apache/hadoop/hbase/errorhandling/ForeignExceptionDispatcher
       8: dup
       9: aload_1
      10: invokevirtual #24                 // Method org/apache/hadoop/hbase/shaded/protobuf/generated/HBaseProtos$ProcedureDescription.getInstance:()Ljava/lang/String;
      13: invokespecial #25                 // Method org/apache/hadoop/hbase/errorhandling/ForeignExceptionDispatcher."<init>":(Ljava/lang/String;)V
      16: astore_2
      17: aload_0
      18: getfield      #9                  // Field master:Lorg/apache/hadoop/hbase/master/MasterServices;
      21: invokeinterface #26,  1           // InterfaceMethod org/apache/hadoop/hbase/master/MasterServices.getServerManager:()Lorg/apache/hadoop/hbase/master/ServerManager;
      26: invokevirtual #27                 // Method org/apache/hadoop/hbase/master/ServerManager.getOnlineServersList:()Ljava/util/List;
      29: astore_3
      30: new           #28                 // class java/util/ArrayList
      33: dup
      34: invokespecial #29                 // Method java/util/ArrayList."<init>":()V
      37: astore        4
      39: aload_3
      40: invokeinterface #30,  1           // InterfaceMethod java/util/List.iterator:()Ljava/util/Iterator;
      45: astore        5
      47: aload         5
      49: invokeinterface #31,  1           // InterfaceMethod java/util/Iterator.hasNext:()Z
      54: ifeq          85
      57: aload         5
      59: invokeinterface #32,  1           // InterfaceMethod java/util/Iterator.next:()Ljava/lang/Object;
      64: checkcast     #33                 // class org/apache/hadoop/hbase/ServerName
      67: astore        6
      69: aload         4
      71: aload         6
      73: invokevirtual #12                 // Method org/apache/hadoop/hbase/ServerName.toString:()Ljava/lang/String;
      76: invokeinterface #34,  2           // InterfaceMethod java/util/List.add:(Ljava/lang/Object;)Z
      81: pop
      82: goto          47
      85: aload_0
      86: getfield      #20                 // Field coordinator:Lorg/apache/hadoop/hbase/procedure/ProcedureCoordinator;
      89: aload_2
      90: aload_1
      91: invokevirtual #24                 // Method org/apache/hadoop/hbase/shaded/protobuf/generated/HBaseProtos$ProcedureDescription.getInstance:()Ljava/lang/String;
      94: iconst_0
      95: newarray       byte
      97: aload         4
      99: invokevirtual #35                 // Method org/apache/hadoop/hbase/procedure/ProcedureCoordinator.startProcedure:(Lorg/apache/hadoop/hbase/errorhandling/ForeignExceptionDispatcher;Ljava/lang/String;[BLjava/util/List;)Lorg/apache/hadoop/hbase/procedure/Procedure;
     102: astore        5
     104: aload         5
     106: ifnonnull     158
     109: new           #3                  // class java/lang/StringBuilder
     112: dup
     113: invokespecial #4                  // Method java/lang/StringBuilder."<init>":()V
     116: ldc           #36                 // String Failed to submit distributed procedure for '
     118: invokevirtual #6                  // Method java/lang/StringBuilder.append:(Ljava/lang/String;)Ljava/lang/StringBuilder;
     121: aload_0
     122: invokevirtual #16                 // Method getProcedureSignature:()Ljava/lang/String;
     125: invokevirtual #6                  // Method java/lang/StringBuilder.append:(Ljava/lang/String;)Ljava/lang/StringBuilder;
     128: ldc           #37                 // String '
     130: invokevirtual #6                  // Method java/lang/StringBuilder.append:(Ljava/lang/String;)Ljava/lang/StringBuilder;
     133: invokevirtual #7                  // Method java/lang/StringBuilder.toString:()Ljava/lang/String;
     136: astore        6
     138: getstatic     #2                  // Field LOG:Lorg/slf4j/Logger;
     141: aload         6
     143: invokeinterface #38,  2           // InterfaceMethod org/slf4j/Logger.error:(Ljava/lang/String;)V
     148: new           #39                 // class java/io/IOException
     151: dup
     152: aload         6
     154: invokespecial #40                 // Method java/io/IOException."<init>":(Ljava/lang/String;)V
     157: athrow
     158: aconst_null
     159: astore        6
     161: aload         5
     163: invokevirtual #41                 // Method org/apache/hadoop/hbase/procedure/Procedure.waitForCompletedWithRet:()Ljava/util/HashMap;
     166: astore        6
     168: getstatic     #2                  // Field LOG:Lorg/slf4j/Logger;
     171: new           #3                  // class java/lang/StringBuilder
     174: dup
     175: invokespecial #4                  // Method java/lang/StringBuilder."<init>":()V
     178: ldc           #42                 // String Done waiting - exec procedure for
     180: invokevirtual #6                  // Method java/lang/StringBuilder.append:(Ljava/lang/String;)Ljava/lang/StringBuilder;
     183: aload_1
     184: invokevirtual #24                 // Method org/apache/hadoop/hbase/shaded/protobuf/generated/HBaseProtos$ProcedureDescription.getInstance:()Ljava/lang/String;
     187: invokevirtual #6                  // Method java/lang/StringBuilder.append:(Ljava/lang/String;)Ljava/lang/StringBuilder;
     190: invokevirtual #7                  // Method java/lang/StringBuilder.toString:()Ljava/lang/String;
     193: invokeinterface #8,  2            // InterfaceMethod org/slf4j/Logger.info:(Ljava/lang/String;)V
     198: aload_0
     199: iconst_1
     200: putfield      #10                 // Field done:Z
     203: goto          244
     206: astore        7
     208: new           #44                 // class org/apache/hadoop/hbase/errorhandling/ForeignException
     211: dup
     212: ldc           #45                 // String Interrupted while waiting for procdure to finish
     214: aload         7
     216: invokespecial #46                 // Method org/apache/hadoop/hbase/errorhandling/ForeignException."<init>":(Ljava/lang/String;Ljava/lang/Throwable;)V
     219: astore        8
     221: aload_2
     222: aload         8
     224: invokevirtual #47                 // Method org/apache/hadoop/hbase/errorhandling/ForeignExceptionDispatcher.receive:(Lorg/apache/hadoop/hbase/errorhandling/ForeignException;)V
     227: invokestatic  #48                 // Method java/lang/Thread.currentThread:()Ljava/lang/Thread;
     230: invokevirtual #49                 // Method java/lang/Thread.interrupt:()V
     233: goto          244
     236: astore        7
     238: aload_2
     239: aload         7
     241: invokevirtual #47                 // Method org/apache/hadoop/hbase/errorhandling/ForeignExceptionDispatcher.receive:(Lorg/apache/hadoop/hbase/errorhandling/ForeignException;)V
     244: aload         6
     246: invokevirtual #50                 // Method java/util/HashMap.values:()Ljava/util/Collection;
     249: invokeinterface #51,  1           // InterfaceMethod java/util/Collection.iterator:()Ljava/util/Iterator;
     254: invokeinterface #32,  1           // InterfaceMethod java/util/Iterator.next:()Ljava/lang/Object;
     259: checkcast     #52                 // class "[B"
     262: areturn
    Exception table:
       from    to  target type
         161   203   206   Class java/lang/InterruptedException
         161   203   236   Class org/apache/hadoop/hbase/errorhandling/ForeignException

  public void checkPermissions(org.apache.hadoop.hbase.shaded.protobuf.generated.HBaseProtos$ProcedureDescription, org.apache.hadoop.hbase.security.access.AccessChecker, org.apache.hadoop.hbase.security.User) throws java.io.IOException;
    Code:
       0: return

  public boolean isProcedureDone(org.apache.hadoop.hbase.shaded.protobuf.generated.HBaseProtos$ProcedureDescription) throws java.io.IOException;
    Code:
       0: aload_0
       1: getfield      #10                 // Field done:Z
       4: ireturn

  static {};
    Code:
       0: ldc           #21                 // class org/apache/hadoop/hbase/procedure/SimpleMasterProcedureManager
       2: invokestatic  #53                 // Method org/slf4j/LoggerFactory.getLogger:(Ljava/lang/Class;)Lorg/slf4j/Logger;
       5: putstatic     #2                  // Field LOG:Lorg/slf4j/Logger;
       8: return
}
