Compiled from "SimpleRequestController.java"
class org.apache.hadoop.hbase.client.SimpleRequestController$SubmittedSizeChecker implements org.apache.hadoop.hbase.client.SimpleRequestController$RowChecker {
  org.apache.hadoop.hbase.client.SimpleRequestController$SubmittedSizeChecker(long);
    Code:
       0: aload_0
       1: invokespecial #1                  // Method java/lang/Object."<init>":()V
       4: aload_0
       5: lconst_0
       6: putfield      #2                  // Field heapSize:J
       9: aload_0
      10: lload_1
      11: putfield      #3                  // Field maxHeapSizeSubmit:J
      14: return

  public org.apache.hadoop.hbase.client.RequestController$ReturnCode canTakeOperation(org.apache.hadoop.hbase.HRegionLocation, long);
    Code:
       0: aload_0
       1: getfield      #2                  // Field heapSize:J
       4: aload_0
       5: getfield      #3                  // Field maxHeapSizeSubmit:J
       8: lcmp
       9: iflt          16
      12: getstatic     #4                  // Field org/apache/hadoop/hbase/client/RequestController$ReturnCode.END:Lorg/apache/hadoop/hbase/client/RequestController$ReturnCode;
      15: areturn
      16: getstatic     #5                  // Field org/apache/hadoop/hbase/client/RequestController$ReturnCode.INCLUDE:Lorg/apache/hadoop/hbase/client/RequestController$ReturnCode;
      19: areturn

  public void notifyFinal(org.apache.hadoop.hbase.client.RequestController$ReturnCode, org.apache.hadoop.hbase.HRegionLocation, long);
    Code:
       0: aload_1
       1: getstatic     #5                  // Field org/apache/hadoop/hbase/client/RequestController$ReturnCode.INCLUDE:Lorg/apache/hadoop/hbase/client/RequestController$ReturnCode;
       4: if_acmpne     17
       7: aload_0
       8: dup
       9: getfield      #2                  // Field heapSize:J
      12: lload_3
      13: ladd
      14: putfield      #2                  // Field heapSize:J
      17: return

  public void reset();
    Code:
       0: aload_0
       1: lconst_0
       2: putfield      #2                  // Field heapSize:J
       5: return
}
