Compiled from "SimpleRpcServer.java"
class org.apache.hadoop.hbase.ipc.SimpleRpcServer$Listener extends java.lang.Thread {
  final org.apache.hadoop.hbase.ipc.SimpleRpcServer this$0;

  public org.apache.hadoop.hbase.ipc.SimpleRpcServer$Listener(org.apache.hadoop.hbase.ipc.SimpleRpcServer, java.lang.String) throws java.io.IOException;
    Code:
       0: aload_0
       1: aload_1
       2: putfield      #2                  // Field this$0:Lorg/apache/hadoop/hbase/ipc/SimpleRpcServer;
       5: aload_0
       6: aload_2
       7: invokespecial #3                  // Method java/lang/Thread."<init>":(Ljava/lang/String;)V
      10: aload_0
      11: aconst_null
      12: putfield      #4                  // Field acceptChannel:Ljava/nio/channels/ServerSocketChannel;
      15: aload_0
      16: aconst_null
      17: putfield      #5                  // Field selector:Ljava/nio/channels/Selector;
      20: aload_0
      21: aconst_null
      22: putfield      #6                  // Field readers:[Lorg/apache/hadoop/hbase/ipc/SimpleRpcServer$Listener$Reader;
      25: aload_0
      26: iconst_0
      27: putfield      #7                  // Field currentReader:I
      30: aload_1
      31: getfield      #8                  // Field org/apache/hadoop/hbase/ipc/SimpleRpcServer.conf:Lorg/apache/hadoop/conf/Configuration;
      34: ldc           #9                  // String hbase.ipc.server.listen.queue.size
      36: sipush        128
      39: invokevirtual #10                 // Method org/apache/hadoop/conf/Configuration.getInt:(Ljava/lang/String;I)I
      42: istore_3
      43: aload_0
      44: aload_1
      45: getfield      #8                  // Field org/apache/hadoop/hbase/ipc/SimpleRpcServer.conf:Lorg/apache/hadoop/conf/Configuration;
      48: ldc           #11                 // String hbase.ipc.server.read.connection-queue.size
      50: bipush        100
      52: invokevirtual #10                 // Method org/apache/hadoop/conf/Configuration.getInt:(Ljava/lang/String;I)I
      55: putfield      #1                  // Field readerPendingConnectionQueueLength:I
      58: aload_0
      59: invokestatic  #12                 // Method java/nio/channels/ServerSocketChannel.open:()Ljava/nio/channels/ServerSocketChannel;
      62: putfield      #4                  // Field acceptChannel:Ljava/nio/channels/ServerSocketChannel;
      65: aload_0
      66: getfield      #4                  // Field acceptChannel:Ljava/nio/channels/ServerSocketChannel;
      69: iconst_0
      70: invokevirtual #13                 // Method java/nio/channels/ServerSocketChannel.configureBlocking:(Z)Ljava/nio/channels/SelectableChannel;
      73: pop
      74: aload_0
      75: getfield      #4                  // Field acceptChannel:Ljava/nio/channels/ServerSocketChannel;
      78: invokevirtual #14                 // Method java/nio/channels/ServerSocketChannel.socket:()Ljava/net/ServerSocket;
      81: aload_1
      82: getfield      #15                 // Field org/apache/hadoop/hbase/ipc/SimpleRpcServer.bindAddress:Ljava/net/InetSocketAddress;
      85: iload_3
      86: invokestatic  #16                 // Method org/apache/hadoop/hbase/ipc/SimpleRpcServer.bind:(Ljava/net/ServerSocket;Ljava/net/InetSocketAddress;I)V
      89: aload_1
      90: aload_0
      91: getfield      #4                  // Field acceptChannel:Ljava/nio/channels/ServerSocketChannel;
      94: invokevirtual #14                 // Method java/nio/channels/ServerSocketChannel.socket:()Ljava/net/ServerSocket;
      97: invokevirtual #17                 // Method java/net/ServerSocket.getLocalPort:()I
     100: putfield      #18                 // Field org/apache/hadoop/hbase/ipc/SimpleRpcServer.port:I
     103: aload_1
     104: aload_0
     105: getfield      #4                  // Field acceptChannel:Ljava/nio/channels/ServerSocketChannel;
     108: invokevirtual #14                 // Method java/nio/channels/ServerSocketChannel.socket:()Ljava/net/ServerSocket;
     111: invokevirtual #19                 // Method java/net/ServerSocket.getLocalSocketAddress:()Ljava/net/SocketAddress;
     114: checkcast     #20                 // class java/net/InetSocketAddress
     117: putfield      #21                 // Field org/apache/hadoop/hbase/ipc/SimpleRpcServer.address:Ljava/net/InetSocketAddress;
     120: aload_0
     121: invokestatic  #22                 // Method java/nio/channels/Selector.open:()Ljava/nio/channels/Selector;
     124: putfield      #5                  // Field selector:Ljava/nio/channels/Selector;
     127: aload_0
     128: aload_1
     129: invokestatic  #23                 // Method org/apache/hadoop/hbase/ipc/SimpleRpcServer.access$000:(Lorg/apache/hadoop/hbase/ipc/SimpleRpcServer;)I
     132: anewarray     #24                 // class org/apache/hadoop/hbase/ipc/SimpleRpcServer$Listener$Reader
     135: putfield      #6                  // Field readers:[Lorg/apache/hadoop/hbase/ipc/SimpleRpcServer$Listener$Reader;
     138: aload_0
     139: aload_1
     140: invokestatic  #23                 // Method org/apache/hadoop/hbase/ipc/SimpleRpcServer.access$000:(Lorg/apache/hadoop/hbase/ipc/SimpleRpcServer;)I
     143: new           #25                 // class org/apache/hbase/thirdparty/com/google/common/util/concurrent/ThreadFactoryBuilder
     146: dup
     147: invokespecial #26                 // Method org/apache/hbase/thirdparty/com/google/common/util/concurrent/ThreadFactoryBuilder."<init>":()V
     150: new           #27                 // class java/lang/StringBuilder
     153: dup
     154: invokespecial #28                 // Method java/lang/StringBuilder."<init>":()V
     157: ldc           #29                 // String Reader=%d,bindAddress=
     159: invokevirtual #30                 // Method java/lang/StringBuilder.append:(Ljava/lang/String;)Ljava/lang/StringBuilder;
     162: aload_1
     163: getfield      #15                 // Field org/apache/hadoop/hbase/ipc/SimpleRpcServer.bindAddress:Ljava/net/InetSocketAddress;
     166: invokevirtual #31                 // Method java/net/InetSocketAddress.getHostName:()Ljava/lang/String;
     169: invokevirtual #30                 // Method java/lang/StringBuilder.append:(Ljava/lang/String;)Ljava/lang/StringBuilder;
     172: ldc           #32                 // String ,port=
     174: invokevirtual #30                 // Method java/lang/StringBuilder.append:(Ljava/lang/String;)Ljava/lang/StringBuilder;
     177: aload_1
     178: getfield      #18                 // Field org/apache/hadoop/hbase/ipc/SimpleRpcServer.port:I
     181: invokevirtual #33                 // Method java/lang/StringBuilder.append:(I)Ljava/lang/StringBuilder;
     184: invokevirtual #34                 // Method java/lang/StringBuilder.toString:()Ljava/lang/String;
     187: invokevirtual #35                 // Method org/apache/hbase/thirdparty/com/google/common/util/concurrent/ThreadFactoryBuilder.setNameFormat:(Ljava/lang/String;)Lorg/apache/hbase/thirdparty/com/google/common/util/concurrent/ThreadFactoryBuilder;
     190: iconst_1
     191: invokevirtual #36                 // Method org/apache/hbase/thirdparty/com/google/common/util/concurrent/ThreadFactoryBuilder.setDaemon:(Z)Lorg/apache/hbase/thirdparty/com/google/common/util/concurrent/ThreadFactoryBuilder;
     194: getstatic     #37                 // Field org/apache/hadoop/hbase/util/Threads.LOGGING_EXCEPTION_HANDLER:Ljava/lang/Thread$UncaughtExceptionHandler;
     197: invokevirtual #38                 // Method org/apache/hbase/thirdparty/com/google/common/util/concurrent/ThreadFactoryBuilder.setUncaughtExceptionHandler:(Ljava/lang/Thread$UncaughtExceptionHandler;)Lorg/apache/hbase/thirdparty/com/google/common/util/concurrent/ThreadFactoryBuilder;
     200: invokevirtual #39                 // Method org/apache/hbase/thirdparty/com/google/common/util/concurrent/ThreadFactoryBuilder.build:()Ljava/util/concurrent/ThreadFactory;
     203: invokestatic  #40                 // Method java/util/concurrent/Executors.newFixedThreadPool:(ILjava/util/concurrent/ThreadFactory;)Ljava/util/concurrent/ExecutorService;
     206: putfield      #41                 // Field readPool:Ljava/util/concurrent/ExecutorService;
     209: iconst_0
     210: istore        4
     212: iload         4
     214: aload_1
     215: invokestatic  #23                 // Method org/apache/hadoop/hbase/ipc/SimpleRpcServer.access$000:(Lorg/apache/hadoop/hbase/ipc/SimpleRpcServer;)I
     218: if_icmpge     257
     221: new           #24                 // class org/apache/hadoop/hbase/ipc/SimpleRpcServer$Listener$Reader
     224: dup
     225: aload_0
     226: invokespecial #42                 // Method org/apache/hadoop/hbase/ipc/SimpleRpcServer$Listener$Reader."<init>":(Lorg/apache/hadoop/hbase/ipc/SimpleRpcServer$Listener;)V
     229: astore        5
     231: aload_0
     232: getfield      #6                  // Field readers:[Lorg/apache/hadoop/hbase/ipc/SimpleRpcServer$Listener$Reader;
     235: iload         4
     237: aload         5
     239: aastore
     240: aload_0
     241: getfield      #41                 // Field readPool:Ljava/util/concurrent/ExecutorService;
     244: aload         5
     246: invokeinterface #43,  2           // InterfaceMethod java/util/concurrent/ExecutorService.execute:(Ljava/lang/Runnable;)V
     251: iinc          4, 1
     254: goto          212
     257: getstatic     #44                 // Field org/apache/hadoop/hbase/ipc/RpcServer.LOG:Lorg/slf4j/Logger;
     260: new           #27                 // class java/lang/StringBuilder
     263: dup
     264: invokespecial #28                 // Method java/lang/StringBuilder."<init>":()V
     267: aload_0
     268: invokevirtual #45                 // Method getName:()Ljava/lang/String;
     271: invokevirtual #30                 // Method java/lang/StringBuilder.append:(Ljava/lang/String;)Ljava/lang/StringBuilder;
     274: ldc           #46                 // String : started
     276: invokevirtual #30                 // Method java/lang/StringBuilder.append:(Ljava/lang/String;)Ljava/lang/StringBuilder;
     279: aload_1
     280: invokestatic  #23                 // Method org/apache/hadoop/hbase/ipc/SimpleRpcServer.access$000:(Lorg/apache/hadoop/hbase/ipc/SimpleRpcServer;)I
     283: invokevirtual #33                 // Method java/lang/StringBuilder.append:(I)Ljava/lang/StringBuilder;
     286: ldc           #47                 // String  reader(s) listening on port=
     288: invokevirtual #30                 // Method java/lang/StringBuilder.append:(Ljava/lang/String;)Ljava/lang/StringBuilder;
     291: aload_1
     292: getfield      #18                 // Field org/apache/hadoop/hbase/ipc/SimpleRpcServer.port:I
     295: invokevirtual #33                 // Method java/lang/StringBuilder.append:(I)Ljava/lang/StringBuilder;
     298: invokevirtual #34                 // Method java/lang/StringBuilder.toString:()Ljava/lang/String;
     301: invokeinterface #48,  2           // InterfaceMethod org/slf4j/Logger.info:(Ljava/lang/String;)V
     306: aload_0
     307: getfield      #4                  // Field acceptChannel:Ljava/nio/channels/ServerSocketChannel;
     310: aload_0
     311: getfield      #5                  // Field selector:Ljava/nio/channels/Selector;
     314: bipush        16
     316: invokevirtual #50                 // Method java/nio/channels/ServerSocketChannel.register:(Ljava/nio/channels/Selector;I)Ljava/nio/channels/SelectionKey;
     319: pop
     320: aload_0
     321: new           #27                 // class java/lang/StringBuilder
     324: dup
     325: invokespecial #28                 // Method java/lang/StringBuilder."<init>":()V
     328: ldc           #51                 // String Listener,port=
     330: invokevirtual #30                 // Method java/lang/StringBuilder.append:(Ljava/lang/String;)Ljava/lang/StringBuilder;
     333: aload_1
     334: getfield      #18                 // Field org/apache/hadoop/hbase/ipc/SimpleRpcServer.port:I
     337: invokevirtual #33                 // Method java/lang/StringBuilder.append:(I)Ljava/lang/StringBuilder;
     340: invokevirtual #34                 // Method java/lang/StringBuilder.toString:()Ljava/lang/String;
     343: invokevirtual #52                 // Method setName:(Ljava/lang/String;)V
     346: aload_0
     347: iconst_1
     348: invokevirtual #53                 // Method setDaemon:(Z)V
     351: return

  public void run();
    Code:
       0: getstatic     #44                 // Field org/apache/hadoop/hbase/ipc/RpcServer.LOG:Lorg/slf4j/Logger;
       3: new           #27                 // class java/lang/StringBuilder
       6: dup
       7: invokespecial #28                 // Method java/lang/StringBuilder."<init>":()V
      10: aload_0
      11: invokevirtual #45                 // Method getName:()Ljava/lang/String;
      14: invokevirtual #30                 // Method java/lang/StringBuilder.append:(Ljava/lang/String;)Ljava/lang/StringBuilder;
      17: ldc           #54                 // String : starting
      19: invokevirtual #30                 // Method java/lang/StringBuilder.append:(Ljava/lang/String;)Ljava/lang/StringBuilder;
      22: invokevirtual #34                 // Method java/lang/StringBuilder.toString:()Ljava/lang/String;
      25: invokeinterface #48,  2           // InterfaceMethod org/slf4j/Logger.info:(Ljava/lang/String;)V
      30: aload_0
      31: getfield      #2                  // Field this$0:Lorg/apache/hadoop/hbase/ipc/SimpleRpcServer;
      34: invokestatic  #55                 // Method org/apache/hadoop/hbase/ipc/SimpleRpcServer.access$200:(Lorg/apache/hadoop/hbase/ipc/SimpleRpcServer;)Lorg/apache/hadoop/hbase/ipc/SimpleRpcServer$ConnectionManager;
      37: invokevirtual #56                 // Method org/apache/hadoop/hbase/ipc/SimpleRpcServer$ConnectionManager.startIdleScan:()V
      40: aload_0
      41: getfield      #2                  // Field this$0:Lorg/apache/hadoop/hbase/ipc/SimpleRpcServer;
      44: getfield      #57                 // Field org/apache/hadoop/hbase/ipc/SimpleRpcServer.running:Z
      47: ifeq          307
      50: aconst_null
      51: astore_1
      52: aload_0
      53: getfield      #5                  // Field selector:Ljava/nio/channels/Selector;
      56: invokevirtual #58                 // Method java/nio/channels/Selector.select:()I
      59: pop
      60: aload_0
      61: getfield      #5                  // Field selector:Ljava/nio/channels/Selector;
      64: invokevirtual #59                 // Method java/nio/channels/Selector.selectedKeys:()Ljava/util/Set;
      67: invokeinterface #60,  1           // InterfaceMethod java/util/Set.iterator:()Ljava/util/Iterator;
      72: astore_2
      73: aload_2
      74: invokeinterface #61,  1           // InterfaceMethod java/util/Iterator.hasNext:()Z
      79: ifeq          148
      82: aload_2
      83: invokeinterface #62,  1           // InterfaceMethod java/util/Iterator.next:()Ljava/lang/Object;
      88: checkcast     #49                 // class java/nio/channels/SelectionKey
      91: astore_1
      92: aload_2
      93: invokeinterface #63,  1           // InterfaceMethod java/util/Iterator.remove:()V
      98: aload_1
      99: invokevirtual #64                 // Method java/nio/channels/SelectionKey.isValid:()Z
     102: ifeq          117
     105: aload_1
     106: invokevirtual #65                 // Method java/nio/channels/SelectionKey.isAcceptable:()Z
     109: ifeq          117
     112: aload_0
     113: aload_1
     114: invokevirtual #66                 // Method doAccept:(Ljava/nio/channels/SelectionKey;)V
     117: goto          143
     120: astore_3
     121: getstatic     #44                 // Field org/apache/hadoop/hbase/ipc/RpcServer.LOG:Lorg/slf4j/Logger;
     124: invokeinterface #68,  1           // InterfaceMethod org/slf4j/Logger.isTraceEnabled:()Z
     129: ifeq          143
     132: getstatic     #44                 // Field org/apache/hadoop/hbase/ipc/RpcServer.LOG:Lorg/slf4j/Logger;
     135: ldc           #69                 // String ignored
     137: aload_3
     138: invokeinterface #70,  3           // InterfaceMethod org/slf4j/Logger.trace:(Ljava/lang/String;Ljava/lang/Throwable;)V
     143: aconst_null
     144: astore_1
     145: goto          73
     148: goto          304
     151: astore_2
     152: aload_0
     153: getfield      #2                  // Field this$0:Lorg/apache/hadoop/hbase/ipc/SimpleRpcServer;
     156: getfield      #72                 // Field org/apache/hadoop/hbase/ipc/SimpleRpcServer.errorHandler:Lorg/apache/hadoop/hbase/ipc/HBaseRPCErrorHandler;
     159: ifnull        226
     162: aload_0
     163: getfield      #2                  // Field this$0:Lorg/apache/hadoop/hbase/ipc/SimpleRpcServer;
     166: getfield      #72                 // Field org/apache/hadoop/hbase/ipc/SimpleRpcServer.errorHandler:Lorg/apache/hadoop/hbase/ipc/HBaseRPCErrorHandler;
     169: aload_2
     170: invokeinterface #73,  2           // InterfaceMethod org/apache/hadoop/hbase/ipc/HBaseRPCErrorHandler.checkOOME:(Ljava/lang/Throwable;)Z
     175: ifeq          294
     178: getstatic     #44                 // Field org/apache/hadoop/hbase/ipc/RpcServer.LOG:Lorg/slf4j/Logger;
     181: new           #27                 // class java/lang/StringBuilder
     184: dup
     185: invokespecial #28                 // Method java/lang/StringBuilder."<init>":()V
     188: aload_0
     189: invokevirtual #45                 // Method getName:()Ljava/lang/String;
     192: invokevirtual #30                 // Method java/lang/StringBuilder.append:(Ljava/lang/String;)Ljava/lang/StringBuilder;
     195: ldc           #74                 // String : exiting on OutOfMemoryError
     197: invokevirtual #30                 // Method java/lang/StringBuilder.append:(Ljava/lang/String;)Ljava/lang/StringBuilder;
     200: invokevirtual #34                 // Method java/lang/StringBuilder.toString:()Ljava/lang/String;
     203: invokeinterface #48,  2           // InterfaceMethod org/slf4j/Logger.info:(Ljava/lang/String;)V
     208: aload_0
     209: aload_1
     210: aload_2
     211: invokespecial #75                 // Method closeCurrentConnection:(Ljava/nio/channels/SelectionKey;Ljava/lang/Throwable;)V
     214: aload_0
     215: getfield      #2                  // Field this$0:Lorg/apache/hadoop/hbase/ipc/SimpleRpcServer;
     218: invokestatic  #55                 // Method org/apache/hadoop/hbase/ipc/SimpleRpcServer.access$200:(Lorg/apache/hadoop/hbase/ipc/SimpleRpcServer;)Lorg/apache/hadoop/hbase/ipc/SimpleRpcServer$ConnectionManager;
     221: iconst_1
     222: invokevirtual #76                 // Method org/apache/hadoop/hbase/ipc/SimpleRpcServer$ConnectionManager.closeIdle:(Z)V
     225: return
     226: getstatic     #44                 // Field org/apache/hadoop/hbase/ipc/RpcServer.LOG:Lorg/slf4j/Logger;
     229: new           #27                 // class java/lang/StringBuilder
     232: dup
     233: invokespecial #28                 // Method java/lang/StringBuilder."<init>":()V
     236: aload_0
     237: invokevirtual #45                 // Method getName:()Ljava/lang/String;
     240: invokevirtual #30                 // Method java/lang/StringBuilder.append:(Ljava/lang/String;)Ljava/lang/StringBuilder;
     243: ldc           #77                 // String : OutOfMemoryError in server select
     245: invokevirtual #30                 // Method java/lang/StringBuilder.append:(Ljava/lang/String;)Ljava/lang/StringBuilder;
     248: invokevirtual #34                 // Method java/lang/StringBuilder.toString:()Ljava/lang/String;
     251: aload_2
     252: invokeinterface #78,  3           // InterfaceMethod org/slf4j/Logger.warn:(Ljava/lang/String;Ljava/lang/Throwable;)V
     257: aload_0
     258: aload_1
     259: aload_2
     260: invokespecial #75                 // Method closeCurrentConnection:(Ljava/nio/channels/SelectionKey;Ljava/lang/Throwable;)V
     263: aload_0
     264: getfield      #2                  // Field this$0:Lorg/apache/hadoop/hbase/ipc/SimpleRpcServer;
     267: invokestatic  #55                 // Method org/apache/hadoop/hbase/ipc/SimpleRpcServer.access$200:(Lorg/apache/hadoop/hbase/ipc/SimpleRpcServer;)Lorg/apache/hadoop/hbase/ipc/SimpleRpcServer$ConnectionManager;
     270: iconst_1
     271: invokevirtual #76                 // Method org/apache/hadoop/hbase/ipc/SimpleRpcServer$ConnectionManager.closeIdle:(Z)V
     274: ldc2_w        #79                 // long 60000l
     277: invokestatic  #81                 // Method java/lang/Thread.sleep:(J)V
     280: goto          294
     283: astore_3
     284: getstatic     #44                 // Field org/apache/hadoop/hbase/ipc/RpcServer.LOG:Lorg/slf4j/Logger;
     287: ldc           #83                 // String Interrupted while sleeping
     289: invokeinterface #84,  2           // InterfaceMethod org/slf4j/Logger.debug:(Ljava/lang/String;)V
     294: goto          304
     297: astore_2
     298: aload_0
     299: aload_1
     300: aload_2
     301: invokespecial #75                 // Method closeCurrentConnection:(Ljava/nio/channels/SelectionKey;Ljava/lang/Throwable;)V
     304: goto          40
     307: getstatic     #44                 // Field org/apache/hadoop/hbase/ipc/RpcServer.LOG:Lorg/slf4j/Logger;
     310: new           #27                 // class java/lang/StringBuilder
     313: dup
     314: invokespecial #28                 // Method java/lang/StringBuilder."<init>":()V
     317: aload_0
     318: invokevirtual #45                 // Method getName:()Ljava/lang/String;
     321: invokevirtual #30                 // Method java/lang/StringBuilder.append:(Ljava/lang/String;)Ljava/lang/StringBuilder;
     324: ldc           #86                 // String : stopping
     326: invokevirtual #30                 // Method java/lang/StringBuilder.append:(Ljava/lang/String;)Ljava/lang/StringBuilder;
     329: invokevirtual #34                 // Method java/lang/StringBuilder.toString:()Ljava/lang/String;
     332: invokeinterface #48,  2           // InterfaceMethod org/slf4j/Logger.info:(Ljava/lang/String;)V
     337: aload_0
     338: dup
     339: astore_1
     340: monitorenter
     341: aload_0
     342: getfield      #4                  // Field acceptChannel:Ljava/nio/channels/ServerSocketChannel;
     345: invokevirtual #87                 // Method java/nio/channels/ServerSocketChannel.close:()V
     348: aload_0
     349: getfield      #5                  // Field selector:Ljava/nio/channels/Selector;
     352: invokevirtual #88                 // Method java/nio/channels/Selector.close:()V
     355: goto          381
     358: astore_2
     359: getstatic     #44                 // Field org/apache/hadoop/hbase/ipc/RpcServer.LOG:Lorg/slf4j/Logger;
     362: invokeinterface #68,  1           // InterfaceMethod org/slf4j/Logger.isTraceEnabled:()Z
     367: ifeq          381
     370: getstatic     #44                 // Field org/apache/hadoop/hbase/ipc/RpcServer.LOG:Lorg/slf4j/Logger;
     373: ldc           #69                 // String ignored
     375: aload_2
     376: invokeinterface #70,  3           // InterfaceMethod org/slf4j/Logger.trace:(Ljava/lang/String;Ljava/lang/Throwable;)V
     381: aload_0
     382: aconst_null
     383: putfield      #5                  // Field selector:Ljava/nio/channels/Selector;
     386: aload_0
     387: aconst_null
     388: putfield      #4                  // Field acceptChannel:Ljava/nio/channels/ServerSocketChannel;
     391: aload_0
     392: getfield      #2                  // Field this$0:Lorg/apache/hadoop/hbase/ipc/SimpleRpcServer;
     395: invokestatic  #55                 // Method org/apache/hadoop/hbase/ipc/SimpleRpcServer.access$200:(Lorg/apache/hadoop/hbase/ipc/SimpleRpcServer;)Lorg/apache/hadoop/hbase/ipc/SimpleRpcServer$ConnectionManager;
     398: invokevirtual #89                 // Method org/apache/hadoop/hbase/ipc/SimpleRpcServer$ConnectionManager.stopIdleScan:()V
     401: aload_0
     402: getfield      #2                  // Field this$0:Lorg/apache/hadoop/hbase/ipc/SimpleRpcServer;
     405: invokestatic  #55                 // Method org/apache/hadoop/hbase/ipc/SimpleRpcServer.access$200:(Lorg/apache/hadoop/hbase/ipc/SimpleRpcServer;)Lorg/apache/hadoop/hbase/ipc/SimpleRpcServer$ConnectionManager;
     408: invokevirtual #90                 // Method org/apache/hadoop/hbase/ipc/SimpleRpcServer$ConnectionManager.closeAll:()V
     411: aload_1
     412: monitorexit
     413: goto          423
     416: astore        4
     418: aload_1
     419: monitorexit
     420: aload         4
     422: athrow
     423: return
    Exception table:
       from    to  target type
          98   117   120   Class java/io/IOException
          52   148   151   Class java/lang/OutOfMemoryError
         274   280   283   Class java/lang/InterruptedException
          52   148   297   Class java/lang/Exception
         341   355   358   Class java/io/IOException
         341   413   416   any
         416   420   416   any

  java.net.InetSocketAddress getAddress();
    Code:
       0: aload_0
       1: getfield      #2                  // Field this$0:Lorg/apache/hadoop/hbase/ipc/SimpleRpcServer;
       4: getfield      #21                 // Field org/apache/hadoop/hbase/ipc/SimpleRpcServer.address:Ljava/net/InetSocketAddress;
       7: areturn

  void doAccept(java.nio.channels.SelectionKey) throws java.lang.InterruptedException, java.io.IOException, java.lang.OutOfMemoryError;
    Code:
       0: aload_1
       1: invokevirtual #95                 // Method java/nio/channels/SelectionKey.channel:()Ljava/nio/channels/SelectableChannel;
       4: checkcast     #96                 // class java/nio/channels/ServerSocketChannel
       7: astore_2
       8: aload_2
       9: invokevirtual #97                 // Method java/nio/channels/ServerSocketChannel.accept:()Ljava/nio/channels/SocketChannel;
      12: dup
      13: astore_3
      14: ifnull        114
      17: aload_3
      18: iconst_0
      19: invokevirtual #98                 // Method java/nio/channels/SocketChannel.configureBlocking:(Z)Ljava/nio/channels/SelectableChannel;
      22: pop
      23: aload_3
      24: invokevirtual #99                 // Method java/nio/channels/SocketChannel.socket:()Ljava/net/Socket;
      27: aload_0
      28: getfield      #2                  // Field this$0:Lorg/apache/hadoop/hbase/ipc/SimpleRpcServer;
      31: getfield      #100                // Field org/apache/hadoop/hbase/ipc/SimpleRpcServer.tcpNoDelay:Z
      34: invokevirtual #101                // Method java/net/Socket.setTcpNoDelay:(Z)V
      37: aload_3
      38: invokevirtual #99                 // Method java/nio/channels/SocketChannel.socket:()Ljava/net/Socket;
      41: aload_0
      42: getfield      #2                  // Field this$0:Lorg/apache/hadoop/hbase/ipc/SimpleRpcServer;
      45: getfield      #102                // Field org/apache/hadoop/hbase/ipc/SimpleRpcServer.tcpKeepAlive:Z
      48: invokevirtual #103                // Method java/net/Socket.setKeepAlive:(Z)V
      51: aload_0
      52: invokevirtual #104                // Method getReader:()Lorg/apache/hadoop/hbase/ipc/SimpleRpcServer$Listener$Reader;
      55: astore        4
      57: aload_0
      58: getfield      #2                  // Field this$0:Lorg/apache/hadoop/hbase/ipc/SimpleRpcServer;
      61: invokestatic  #55                 // Method org/apache/hadoop/hbase/ipc/SimpleRpcServer.access$200:(Lorg/apache/hadoop/hbase/ipc/SimpleRpcServer;)Lorg/apache/hadoop/hbase/ipc/SimpleRpcServer$ConnectionManager;
      64: aload_3
      65: invokevirtual #105                // Method org/apache/hadoop/hbase/ipc/SimpleRpcServer$ConnectionManager.register:(Ljava/nio/channels/SocketChannel;)Lorg/apache/hadoop/hbase/ipc/SimpleServerRpcConnection;
      68: astore        5
      70: aload         5
      72: ifnonnull     97
      75: aload_3
      76: invokevirtual #106                // Method java/nio/channels/SocketChannel.isOpen:()Z
      79: ifeq          8
      82: aconst_null
      83: iconst_1
      84: anewarray     #107                // class java/io/Closeable
      87: dup
      88: iconst_0
      89: aload_3
      90: aastore
      91: invokestatic  #108                // Method org/apache/hadoop/io/IOUtils.cleanup:(Lorg/apache/commons/logging/Log;[Ljava/io/Closeable;)V
      94: goto          8
      97: aload_1
      98: aload         5
     100: invokevirtual #94                 // Method java/nio/channels/SelectionKey.attach:(Ljava/lang/Object;)Ljava/lang/Object;
     103: pop
     104: aload         4
     106: aload         5
     108: invokevirtual #109                // Method org/apache/hadoop/hbase/ipc/SimpleRpcServer$Listener$Reader.addConnection:(Lorg/apache/hadoop/hbase/ipc/SimpleServerRpcConnection;)V
     111: goto          8
     114: return

  void doRead(java.nio.channels.SelectionKey) throws java.lang.InterruptedException;
    Code:
       0: aload_1
       1: invokevirtual #91                 // Method java/nio/channels/SelectionKey.attachment:()Ljava/lang/Object;
       4: checkcast     #92                 // class org/apache/hadoop/hbase/ipc/SimpleServerRpcConnection
       7: astore_3
       8: aload_3
       9: ifnonnull     13
      12: return
      13: aload_3
      14: invokestatic  #110                // Method java/lang/System.currentTimeMillis:()J
      17: invokevirtual #111                // Method org/apache/hadoop/hbase/ipc/SimpleServerRpcConnection.setLastContact:(J)V
      20: aload_3
      21: invokevirtual #112                // Method org/apache/hadoop/hbase/ipc/SimpleServerRpcConnection.readAndProcess:()I
      24: istore_2
      25: goto          94
      28: astore        4
      30: getstatic     #44                 // Field org/apache/hadoop/hbase/ipc/RpcServer.LOG:Lorg/slf4j/Logger;
      33: new           #27                 // class java/lang/StringBuilder
      36: dup
      37: invokespecial #28                 // Method java/lang/StringBuilder."<init>":()V
      40: invokestatic  #113                // Method java/lang/Thread.currentThread:()Ljava/lang/Thread;
      43: invokevirtual #114                // Method java/lang/Thread.getName:()Ljava/lang/String;
      46: invokevirtual #30                 // Method java/lang/StringBuilder.append:(Ljava/lang/String;)Ljava/lang/StringBuilder;
      49: ldc           #115                // String : readAndProcess caught InterruptedException
      51: invokevirtual #30                 // Method java/lang/StringBuilder.append:(Ljava/lang/String;)Ljava/lang/StringBuilder;
      54: invokevirtual #34                 // Method java/lang/StringBuilder.toString:()Ljava/lang/String;
      57: aload         4
      59: invokeinterface #116,  3          // InterfaceMethod org/slf4j/Logger.info:(Ljava/lang/String;Ljava/lang/Throwable;)V
      64: aload         4
      66: athrow
      67: astore        4
      69: getstatic     #44                 // Field org/apache/hadoop/hbase/ipc/RpcServer.LOG:Lorg/slf4j/Logger;
      72: invokeinterface #117,  1          // InterfaceMethod org/slf4j/Logger.isDebugEnabled:()Z
      77: ifeq          92
      80: getstatic     #44                 // Field org/apache/hadoop/hbase/ipc/RpcServer.LOG:Lorg/slf4j/Logger;
      83: ldc           #118                // String Caught exception while reading:
      85: aload         4
      87: invokeinterface #119,  3          // InterfaceMethod org/slf4j/Logger.debug:(Ljava/lang/String;Ljava/lang/Throwable;)V
      92: iconst_m1
      93: istore_2
      94: iload_2
      95: ifge          111
      98: aload_0
      99: getfield      #2                  // Field this$0:Lorg/apache/hadoop/hbase/ipc/SimpleRpcServer;
     102: aload_3
     103: invokevirtual #93                 // Method org/apache/hadoop/hbase/ipc/SimpleRpcServer.closeConnection:(Lorg/apache/hadoop/hbase/ipc/SimpleServerRpcConnection;)V
     106: aconst_null
     107: astore_3
     108: goto          118
     111: aload_3
     112: invokestatic  #110                // Method java/lang/System.currentTimeMillis:()J
     115: invokevirtual #111                // Method org/apache/hadoop/hbase/ipc/SimpleServerRpcConnection.setLastContact:(J)V
     118: return
    Exception table:
       from    to  target type
          20    25    28   Class java/lang/InterruptedException
          20    25    67   Class java/lang/Exception

  synchronized void doStop();
    Code:
       0: aload_0
       1: getfield      #5                  // Field selector:Ljava/nio/channels/Selector;
       4: ifnull        18
       7: aload_0
       8: getfield      #5                  // Field selector:Ljava/nio/channels/Selector;
      11: invokevirtual #120                // Method java/nio/channels/Selector.wakeup:()Ljava/nio/channels/Selector;
      14: pop
      15: invokestatic  #121                // Method java/lang/Thread.yield:()V
      18: aload_0
      19: getfield      #4                  // Field acceptChannel:Ljava/nio/channels/ServerSocketChannel;
      22: ifnull        73
      25: aload_0
      26: getfield      #4                  // Field acceptChannel:Ljava/nio/channels/ServerSocketChannel;
      29: invokevirtual #14                 // Method java/nio/channels/ServerSocketChannel.socket:()Ljava/net/ServerSocket;
      32: invokevirtual #122                // Method java/net/ServerSocket.close:()V
      35: goto          73
      38: astore_1
      39: getstatic     #44                 // Field org/apache/hadoop/hbase/ipc/RpcServer.LOG:Lorg/slf4j/Logger;
      42: new           #27                 // class java/lang/StringBuilder
      45: dup
      46: invokespecial #28                 // Method java/lang/StringBuilder."<init>":()V
      49: aload_0
      50: invokevirtual #45                 // Method getName:()Ljava/lang/String;
      53: invokevirtual #30                 // Method java/lang/StringBuilder.append:(Ljava/lang/String;)Ljava/lang/StringBuilder;
      56: ldc           #123                // String : exception in closing listener socket.
      58: invokevirtual #30                 // Method java/lang/StringBuilder.append:(Ljava/lang/String;)Ljava/lang/StringBuilder;
      61: aload_1
      62: invokevirtual #124                // Method java/lang/StringBuilder.append:(Ljava/lang/Object;)Ljava/lang/StringBuilder;
      65: invokevirtual #34                 // Method java/lang/StringBuilder.toString:()Ljava/lang/String;
      68: invokeinterface #48,  2           // InterfaceMethod org/slf4j/Logger.info:(Ljava/lang/String;)V
      73: aload_0
      74: getfield      #41                 // Field readPool:Ljava/util/concurrent/ExecutorService;
      77: invokeinterface #125,  1          // InterfaceMethod java/util/concurrent/ExecutorService.shutdownNow:()Ljava/util/List;
      82: pop
      83: return
    Exception table:
       from    to  target type
          25    35    38   Class java/io/IOException

  org.apache.hadoop.hbase.ipc.SimpleRpcServer$Listener$Reader getReader();
    Code:
       0: aload_0
       1: aload_0
       2: getfield      #7                  // Field currentReader:I
       5: iconst_1
       6: iadd
       7: aload_0
       8: getfield      #6                  // Field readers:[Lorg/apache/hadoop/hbase/ipc/SimpleRpcServer$Listener$Reader;
      11: arraylength
      12: irem
      13: putfield      #7                  // Field currentReader:I
      16: aload_0
      17: getfield      #6                  // Field readers:[Lorg/apache/hadoop/hbase/ipc/SimpleRpcServer$Listener$Reader;
      20: aload_0
      21: getfield      #7                  // Field currentReader:I
      24: aaload
      25: areturn

  static int access$100(org.apache.hadoop.hbase.ipc.SimpleRpcServer$Listener);
    Code:
       0: aload_0
       1: getfield      #1                  // Field readerPendingConnectionQueueLength:I
       4: ireturn
}
