Compiled from "SimpleRpcServer.java"
class org.apache.hadoop.hbase.ipc.SimpleRpcServer$ConnectionManager$1 extends java.util.TimerTask {
  final org.apache.hadoop.hbase.ipc.SimpleRpcServer$ConnectionManager this$1;

  org.apache.hadoop.hbase.ipc.SimpleRpcServer$ConnectionManager$1(org.apache.hadoop.hbase.ipc.SimpleRpcServer$ConnectionManager);
    Code:
       0: aload_0
       1: aload_1
       2: putfield      #1                  // Field this$1:Lorg/apache/hadoop/hbase/ipc/SimpleRpcServer$ConnectionManager;
       5: aload_0
       6: invokespecial #2                  // Method java/util/TimerTask."<init>":()V
       9: return

  public void run();
    Code:
       0: aload_0
       1: getfield      #1                  // Field this$1:Lorg/apache/hadoop/hbase/ipc/SimpleRpcServer$ConnectionManager;
       4: getfield      #3                  // Field org/apache/hadoop/hbase/ipc/SimpleRpcServer$ConnectionManager.this$0:Lorg/apache/hadoop/hbase/ipc/SimpleRpcServer;
       7: getfield      #4                  // Field org/apache/hadoop/hbase/ipc/SimpleRpcServer.running:Z
      10: ifne          14
      13: return
      14: getstatic     #5                  // Field org/apache/hadoop/hbase/ipc/RpcServer.LOG:Lorg/slf4j/Logger;
      17: invokeinterface #6,  1            // InterfaceMethod org/slf4j/Logger.isTraceEnabled:()Z
      22: ifeq          35
      25: getstatic     #5                  // Field org/apache/hadoop/hbase/ipc/RpcServer.LOG:Lorg/slf4j/Logger;
      28: ldc           #7                  // String running
      30: invokeinterface #8,  2            // InterfaceMethod org/slf4j/Logger.trace:(Ljava/lang/String;)V
      35: aload_0
      36: getfield      #1                  // Field this$1:Lorg/apache/hadoop/hbase/ipc/SimpleRpcServer$ConnectionManager;
      39: iconst_0
      40: invokevirtual #9                  // Method org/apache/hadoop/hbase/ipc/SimpleRpcServer$ConnectionManager.closeIdle:(Z)V
      43: aload_0
      44: getfield      #1                  // Field this$1:Lorg/apache/hadoop/hbase/ipc/SimpleRpcServer$ConnectionManager;
      47: invokestatic  #10                 // Method org/apache/hadoop/hbase/ipc/SimpleRpcServer$ConnectionManager.access$300:(Lorg/apache/hadoop/hbase/ipc/SimpleRpcServer$ConnectionManager;)V
      50: goto          63
      53: astore_1
      54: aload_0
      55: getfield      #1                  // Field this$1:Lorg/apache/hadoop/hbase/ipc/SimpleRpcServer$ConnectionManager;
      58: invokestatic  #10                 // Method org/apache/hadoop/hbase/ipc/SimpleRpcServer$ConnectionManager.access$300:(Lorg/apache/hadoop/hbase/ipc/SimpleRpcServer$ConnectionManager;)V
      61: aload_1
      62: athrow
      63: return
    Exception table:
       from    to  target type
          35    43    53   any
}
