Compiled from "SimpleRequestController.java"
class org.apache.hadoop.hbase.client.SimpleRequestController$RequestHeapSizeChecker implements org.apache.hadoop.hbase.client.SimpleRequestController$RowChecker {
  org.apache.hadoop.hbase.client.SimpleRequestController$RequestHeapSizeChecker(long);
    Code:
       0: aload_0
       1: invokespecial #1                  // Method java/lang/Object."<init>":()V
       4: aload_0
       5: new           #2                  // class java/util/HashMap
       8: dup
       9: invokespecial #3                  // Method java/util/HashMap."<init>":()V
      12: putfield      #4                  // Field serverRequestSizes:Ljava/util/Map;
      15: aload_0
      16: lload_1
      17: putfield      #5                  // Field maxHeapSizePerRequest:J
      20: return

  public void reset();
    Code:
       0: aload_0
       1: getfield      #4                  // Field serverRequestSizes:Ljava/util/Map;
       4: invokeinterface #6,  1            // InterfaceMethod java/util/Map.clear:()V
       9: return

  public org.apache.hadoop.hbase.client.RequestController$ReturnCode canTakeOperation(org.apache.hadoop.hbase.HRegionLocation, long);
    Code:
       0: aload_0
       1: getfield      #4                  // Field serverRequestSizes:Ljava/util/Map;
       4: aload_1
       5: invokevirtual #7                  // Method org/apache/hadoop/hbase/HRegionLocation.getServerName:()Lorg/apache/hadoop/hbase/ServerName;
       8: invokeinterface #8,  2            // InterfaceMethod java/util/Map.containsKey:(Ljava/lang/Object;)Z
      13: ifeq          38
      16: aload_0
      17: getfield      #4                  // Field serverRequestSizes:Ljava/util/Map;
      20: aload_1
      21: invokevirtual #7                  // Method org/apache/hadoop/hbase/HRegionLocation.getServerName:()Lorg/apache/hadoop/hbase/ServerName;
      24: invokeinterface #9,  2            // InterfaceMethod java/util/Map.get:(Ljava/lang/Object;)Ljava/lang/Object;
      29: checkcast     #10                 // class java/lang/Long
      32: invokevirtual #11                 // Method java/lang/Long.longValue:()J
      35: goto          39
      38: lconst_0
      39: lstore        4
      41: lload         4
      43: lconst_0
      44: lcmp
      45: ifeq          60
      48: lload         4
      50: lload_2
      51: ladd
      52: aload_0
      53: getfield      #5                  // Field maxHeapSizePerRequest:J
      56: lcmp
      57: ifgt          64
      60: getstatic     #12                 // Field org/apache/hadoop/hbase/client/RequestController$ReturnCode.INCLUDE:Lorg/apache/hadoop/hbase/client/RequestController$ReturnCode;
      63: areturn
      64: getstatic     #13                 // Field org/apache/hadoop/hbase/client/RequestController$ReturnCode.SKIP:Lorg/apache/hadoop/hbase/client/RequestController$ReturnCode;
      67: areturn

  public void notifyFinal(org.apache.hadoop.hbase.client.RequestController$ReturnCode, org.apache.hadoop.hbase.HRegionLocation, long);
    Code:
       0: aload_1
       1: getstatic     #12                 // Field org/apache/hadoop/hbase/client/RequestController$ReturnCode.INCLUDE:Lorg/apache/hadoop/hbase/client/RequestController$ReturnCode;
       4: if_acmpne     69
       7: aload_0
       8: getfield      #4                  // Field serverRequestSizes:Ljava/util/Map;
      11: aload_2
      12: invokevirtual #7                  // Method org/apache/hadoop/hbase/HRegionLocation.getServerName:()Lorg/apache/hadoop/hbase/ServerName;
      15: invokeinterface #8,  2            // InterfaceMethod java/util/Map.containsKey:(Ljava/lang/Object;)Z
      20: ifeq          45
      23: aload_0
      24: getfield      #4                  // Field serverRequestSizes:Ljava/util/Map;
      27: aload_2
      28: invokevirtual #7                  // Method org/apache/hadoop/hbase/HRegionLocation.getServerName:()Lorg/apache/hadoop/hbase/ServerName;
      31: invokeinterface #9,  2            // InterfaceMethod java/util/Map.get:(Ljava/lang/Object;)Ljava/lang/Object;
      36: checkcast     #10                 // class java/lang/Long
      39: invokevirtual #11                 // Method java/lang/Long.longValue:()J
      42: goto          46
      45: lconst_0
      46: lstore        5
      48: aload_0
      49: getfield      #4                  // Field serverRequestSizes:Ljava/util/Map;
      52: aload_2
      53: invokevirtual #7                  // Method org/apache/hadoop/hbase/HRegionLocation.getServerName:()Lorg/apache/hadoop/hbase/ServerName;
      56: lload         5
      58: lload_3
      59: ladd
      60: invokestatic  #14                 // Method java/lang/Long.valueOf:(J)Ljava/lang/Long;
      63: invokeinterface #15,  3           // InterfaceMethod java/util/Map.put:(Ljava/lang/Object;Ljava/lang/Object;)Ljava/lang/Object;
      68: pop
      69: return
}
