Compiled from "SimplePositionedMutableByteRange.java"
public class org.apache.hadoop.hbase.util.SimplePositionedMutableByteRange extends org.apache.hadoop.hbase.util.AbstractPositionedByteRange {
  public org.apache.hadoop.hbase.util.SimplePositionedMutableByteRange();
    Code:
       0: aload_0
       1: invokespecial #1                  // Method org/apache/hadoop/hbase/util/AbstractPositionedByteRange."<init>":()V
       4: return

  public org.apache.hadoop.hbase.util.SimplePositionedMutableByteRange(int);
    Code:
       0: aload_0
       1: iload_1
       2: newarray       byte
       4: invokespecial #2                  // Method "<init>":([B)V
       7: return

  public org.apache.hadoop.hbase.util.SimplePositionedMutableByteRange(byte[]);
    Code:
       0: aload_0
       1: invokespecial #1                  // Method org/apache/hadoop/hbase/util/AbstractPositionedByteRange."<init>":()V
       4: aload_0
       5: aload_1
       6: invokevirtual #3                  // Method set:([B)Lorg/apache/hadoop/hbase/util/PositionedByteRange;
       9: pop
      10: return

  public org.apache.hadoop.hbase.util.SimplePositionedMutableByteRange(byte[], int, int);
    Code:
       0: aload_0
       1: invokespecial #1                  // Method org/apache/hadoop/hbase/util/AbstractPositionedByteRange."<init>":()V
       4: aload_0
       5: aload_1
       6: iload_2
       7: iload_3
       8: invokevirtual #4                  // Method set:([BII)Lorg/apache/hadoop/hbase/util/PositionedByteRange;
      11: pop
      12: return

  public org.apache.hadoop.hbase.util.PositionedByteRange unset();
    Code:
       0: aload_0
       1: iconst_0
       2: putfield      #5                  // Field position:I
       5: aload_0
       6: invokevirtual #6                  // Method clearHashCache:()V
       9: aload_0
      10: aconst_null
      11: putfield      #7                  // Field bytes:[B
      14: aload_0
      15: iconst_0
      16: putfield      #8                  // Field offset:I
      19: aload_0
      20: iconst_0
      21: putfield      #9                  // Field length:I
      24: aload_0
      25: areturn

  public org.apache.hadoop.hbase.util.PositionedByteRange set(int);
    Code:
       0: aload_0
       1: iconst_0
       2: putfield      #5                  // Field position:I
       5: aload_0
       6: iload_1
       7: invokespecial #10                 // Method org/apache/hadoop/hbase/util/AbstractPositionedByteRange.set:(I)Lorg/apache/hadoop/hbase/util/PositionedByteRange;
      10: pop
      11: aload_0
      12: iload_1
      13: putfield      #11                 // Field limit:I
      16: aload_0
      17: areturn

  public org.apache.hadoop.hbase.util.PositionedByteRange set(byte[]);
    Code:
       0: aload_0
       1: iconst_0
       2: putfield      #5                  // Field position:I
       5: aload_0
       6: aload_1
       7: invokespecial #12                 // Method org/apache/hadoop/hbase/util/AbstractPositionedByteRange.set:([B)Lorg/apache/hadoop/hbase/util/PositionedByteRange;
      10: pop
      11: aload_0
      12: aload_1
      13: arraylength
      14: putfield      #11                 // Field limit:I
      17: aload_0
      18: areturn

  public org.apache.hadoop.hbase.util.PositionedByteRange set(byte[], int, int);
    Code:
       0: aload_0
       1: iconst_0
       2: putfield      #5                  // Field position:I
       5: aload_0
       6: aload_1
       7: iload_2
       8: iload_3
       9: invokespecial #13                 // Method org/apache/hadoop/hbase/util/AbstractPositionedByteRange.set:([BII)Lorg/apache/hadoop/hbase/util/PositionedByteRange;
      12: pop
      13: aload_0
      14: iload_3
      15: putfield      #11                 // Field limit:I
      18: aload_0
      19: areturn

  public org.apache.hadoop.hbase.util.PositionedByteRange setOffset(int);
    Code:
       0: aload_0
       1: iconst_0
       2: putfield      #5                  // Field position:I
       5: aload_0
       6: iload_1
       7: invokespecial #14                 // Method org/apache/hadoop/hbase/util/AbstractPositionedByteRange.setOffset:(I)Lorg/apache/hadoop/hbase/util/PositionedByteRange;
      10: pop
      11: aload_0
      12: areturn

  public org.apache.hadoop.hbase.util.PositionedByteRange setLength(int);
    Code:
       0: aload_0
       1: aload_0
       2: getfield      #5                  // Field position:I
       5: iload_1
       6: invokestatic  #15                 // Method java/lang/Math.min:(II)I
       9: putfield      #5                  // Field position:I
      12: aload_0
      13: iload_1
      14: invokespecial #16                 // Method org/apache/hadoop/hbase/util/AbstractPositionedByteRange.setLength:(I)Lorg/apache/hadoop/hbase/util/PositionedByteRange;
      17: pop
      18: aload_0
      19: areturn

  public org.apache.hadoop.hbase.util.PositionedByteRange put(byte);
    Code:
       0: aload_0
       1: aload_0
       2: dup
       3: getfield      #5                  // Field position:I
       6: dup_x1
       7: iconst_1
       8: iadd
       9: putfield      #5                  // Field position:I
      12: iload_1
      13: invokevirtual #17                 // Method put:(IB)Lorg/apache/hadoop/hbase/util/PositionedByteRange;
      16: pop
      17: aload_0
      18: areturn

  public org.apache.hadoop.hbase.util.PositionedByteRange put(byte[]);
    Code:
       0: iconst_0
       1: aload_1
       2: arraylength
       3: if_icmpne     8
       6: aload_0
       7: areturn
       8: aload_0
       9: aload_1
      10: iconst_0
      11: aload_1
      12: arraylength
      13: invokevirtual #18                 // Method put:([BII)Lorg/apache/hadoop/hbase/util/PositionedByteRange;
      16: areturn

  public org.apache.hadoop.hbase.util.PositionedByteRange put(byte[], int, int);
    Code:
       0: iconst_0
       1: iload_3
       2: if_icmpne     7
       5: aload_0
       6: areturn
       7: aload_0
       8: aload_0
       9: getfield      #5                  // Field position:I
      12: aload_1
      13: iload_2
      14: iload_3
      15: invokevirtual #19                 // Method put:(I[BII)Lorg/apache/hadoop/hbase/util/PositionedByteRange;
      18: pop
      19: aload_0
      20: dup
      21: getfield      #5                  // Field position:I
      24: iload_3
      25: iadd
      26: putfield      #5                  // Field position:I
      29: aload_0
      30: areturn

  public org.apache.hadoop.hbase.util.PositionedByteRange get(int, byte[]);
    Code:
       0: aload_0
       1: iload_1
       2: aload_2
       3: invokespecial #20                 // Method org/apache/hadoop/hbase/util/AbstractPositionedByteRange.get:(I[B)Lorg/apache/hadoop/hbase/util/PositionedByteRange;
       6: pop
       7: aload_0
       8: areturn

  public org.apache.hadoop.hbase.util.PositionedByteRange get(int, byte[], int, int);
    Code:
       0: aload_0
       1: iload_1
       2: aload_2
       3: iload_3
       4: iload         4
       6: invokespecial #21                 // Method org/apache/hadoop/hbase/util/AbstractPositionedByteRange.get:(I[BII)Lorg/apache/hadoop/hbase/util/PositionedByteRange;
       9: pop
      10: aload_0
      11: areturn

  public org.apache.hadoop.hbase.util.PositionedByteRange put(int, byte);
    Code:
       0: aload_0
       1: getfield      #7                  // Field bytes:[B
       4: aload_0
       5: getfield      #8                  // Field offset:I
       8: iload_1
       9: iadd
      10: iload_2
      11: bastore
      12: aload_0
      13: areturn

  public org.apache.hadoop.hbase.util.PositionedByteRange put(int, byte[]);
    Code:
       0: iconst_0
       1: aload_2
       2: arraylength
       3: if_icmpne     8
       6: aload_0
       7: areturn
       8: aload_0
       9: iload_1
      10: aload_2
      11: iconst_0
      12: aload_2
      13: arraylength
      14: invokevirtual #19                 // Method put:(I[BII)Lorg/apache/hadoop/hbase/util/PositionedByteRange;
      17: areturn

  public org.apache.hadoop.hbase.util.PositionedByteRange put(int, byte[], int, int);
    Code:
       0: iconst_0
       1: iload         4
       3: if_icmpne     8
       6: aload_0
       7: areturn
       8: aload_2
       9: iload_3
      10: aload_0
      11: getfield      #7                  // Field bytes:[B
      14: aload_0
      15: getfield      #8                  // Field offset:I
      18: iload_1
      19: iadd
      20: iload         4
      22: invokestatic  #22                 // Method java/lang/System.arraycopy:(Ljava/lang/Object;ILjava/lang/Object;II)V
      25: aload_0
      26: areturn

  public org.apache.hadoop.hbase.util.PositionedByteRange deepCopy();
    Code:
       0: new           #23                 // class org/apache/hadoop/hbase/util/SimplePositionedMutableByteRange
       3: dup
       4: aload_0
       5: invokevirtual #24                 // Method deepCopyToNewArray:()[B
       8: invokespecial #2                  // Method "<init>":([B)V
      11: astore_1
      12: aload_1
      13: aload_0
      14: getfield      #5                  // Field position:I
      17: putfield      #5                  // Field position:I
      20: aload_1
      21: areturn

  public org.apache.hadoop.hbase.util.PositionedByteRange shallowCopy();
    Code:
       0: new           #23                 // class org/apache/hadoop/hbase/util/SimplePositionedMutableByteRange
       3: dup
       4: aload_0
       5: getfield      #7                  // Field bytes:[B
       8: aload_0
       9: getfield      #8                  // Field offset:I
      12: aload_0
      13: getfield      #9                  // Field length:I
      16: invokespecial #25                 // Method "<init>":([BII)V
      19: astore_1
      20: aload_1
      21: aload_0
      22: getfield      #5                  // Field position:I
      25: putfield      #5                  // Field position:I
      28: aload_1
      29: areturn

  public org.apache.hadoop.hbase.util.PositionedByteRange shallowCopySubRange(int, int);
    Code:
       0: new           #23                 // class org/apache/hadoop/hbase/util/SimplePositionedMutableByteRange
       3: dup
       4: aload_0
       5: getfield      #7                  // Field bytes:[B
       8: aload_0
       9: getfield      #8                  // Field offset:I
      12: iload_1
      13: iadd
      14: iload_2
      15: invokespecial #25                 // Method "<init>":([BII)V
      18: astore_3
      19: aload_3
      20: aload_0
      21: getfield      #5                  // Field position:I
      24: putfield      #5                  // Field position:I
      27: aload_3
      28: areturn

  public org.apache.hadoop.hbase.util.PositionedByteRange putShort(short);
    Code:
       0: aload_0
       1: aload_0
       2: getfield      #5                  // Field position:I
       5: iload_1
       6: invokevirtual #26                 // Method putShort:(IS)Lorg/apache/hadoop/hbase/util/PositionedByteRange;
       9: pop
      10: aload_0
      11: dup
      12: getfield      #5                  // Field position:I
      15: iconst_2
      16: iadd
      17: putfield      #5                  // Field position:I
      20: aload_0
      21: areturn

  public org.apache.hadoop.hbase.util.PositionedByteRange putInt(int);
    Code:
       0: aload_0
       1: aload_0
       2: getfield      #5                  // Field position:I
       5: iload_1
       6: invokevirtual #28                 // Method putInt:(II)Lorg/apache/hadoop/hbase/util/PositionedByteRange;
       9: pop
      10: aload_0
      11: dup
      12: getfield      #5                  // Field position:I
      15: iconst_4
      16: iadd
      17: putfield      #5                  // Field position:I
      20: aload_0
      21: areturn

  public org.apache.hadoop.hbase.util.PositionedByteRange putLong(long);
    Code:
       0: aload_0
       1: aload_0
       2: getfield      #5                  // Field position:I
       5: lload_1
       6: invokevirtual #29                 // Method putLong:(IJ)Lorg/apache/hadoop/hbase/util/PositionedByteRange;
       9: pop
      10: aload_0
      11: dup
      12: getfield      #5                  // Field position:I
      15: bipush        8
      17: iadd
      18: putfield      #5                  // Field position:I
      21: aload_0
      22: areturn

  public int putVLong(long);
    Code:
       0: aload_0
       1: aload_0
       2: getfield      #5                  // Field position:I
       5: lload_1
       6: invokevirtual #30                 // Method putVLong:(IJ)I
       9: istore_3
      10: aload_0
      11: dup
      12: getfield      #5                  // Field position:I
      15: iload_3
      16: iadd
      17: putfield      #5                  // Field position:I
      20: iload_3
      21: ireturn

  public org.apache.hadoop.hbase.util.PositionedByteRange putShort(int, short);
    Code:
       0: aload_0
       1: getfield      #7                  // Field bytes:[B
       4: aload_0
       5: getfield      #8                  // Field offset:I
       8: iload_1
       9: iadd
      10: iconst_1
      11: iadd
      12: iload_2
      13: i2b
      14: bastore
      15: iload_2
      16: bipush        8
      18: ishr
      19: i2s
      20: istore_2
      21: aload_0
      22: getfield      #7                  // Field bytes:[B
      25: aload_0
      26: getfield      #8                  // Field offset:I
      29: iload_1
      30: iadd
      31: iload_2
      32: i2b
      33: bastore
      34: aload_0
      35: invokevirtual #6                  // Method clearHashCache:()V
      38: aload_0
      39: areturn

  public org.apache.hadoop.hbase.util.PositionedByteRange putInt(int, int);
    Code:
       0: iconst_3
       1: istore_3
       2: iload_3
       3: ifle          32
       6: aload_0
       7: getfield      #7                  // Field bytes:[B
      10: aload_0
      11: getfield      #8                  // Field offset:I
      14: iload_1
      15: iadd
      16: iload_3
      17: iadd
      18: iload_2
      19: i2b
      20: bastore
      21: iload_2
      22: bipush        8
      24: iushr
      25: istore_2
      26: iinc          3, -1
      29: goto          2
      32: aload_0
      33: getfield      #7                  // Field bytes:[B
      36: aload_0
      37: getfield      #8                  // Field offset:I
      40: iload_1
      41: iadd
      42: iload_2
      43: i2b
      44: bastore
      45: aload_0
      46: invokevirtual #6                  // Method clearHashCache:()V
      49: aload_0
      50: areturn

  public org.apache.hadoop.hbase.util.PositionedByteRange putLong(int, long);
    Code:
       0: bipush        7
       2: istore        4
       4: iload         4
       6: ifle          37
       9: aload_0
      10: getfield      #7                  // Field bytes:[B
      13: aload_0
      14: getfield      #8                  // Field offset:I
      17: iload_1
      18: iadd
      19: iload         4
      21: iadd
      22: lload_2
      23: l2i
      24: i2b
      25: bastore
      26: lload_2
      27: bipush        8
      29: lushr
      30: lstore_2
      31: iinc          4, -1
      34: goto          4
      37: aload_0
      38: getfield      #7                  // Field bytes:[B
      41: aload_0
      42: getfield      #8                  // Field offset:I
      45: iload_1
      46: iadd
      47: lload_2
      48: l2i
      49: i2b
      50: bastore
      51: aload_0
      52: invokevirtual #6                  // Method clearHashCache:()V
      55: aload_0
      56: areturn

  public int putVLong(int, long);
    Code:
       0: iconst_0
       1: istore        4
       3: lload_2
       4: ldc2_w        #31                 // long -128l
       7: land
       8: lconst_0
       9: lcmp
      10: ifne          33
      13: aload_0
      14: getfield      #7                  // Field bytes:[B
      17: aload_0
      18: getfield      #8                  // Field offset:I
      21: iload_1
      22: iadd
      23: iload         4
      25: iadd
      26: lload_2
      27: l2i
      28: i2b
      29: bastore
      30: goto          69
      33: aload_0
      34: getfield      #7                  // Field bytes:[B
      37: aload_0
      38: getfield      #8                  // Field offset:I
      41: iload_1
      42: iadd
      43: iload         4
      45: iadd
      46: lload_2
      47: ldc2_w        #33                 // long 127l
      50: land
      51: ldc2_w        #35                 // long 128l
      54: lor
      55: l2i
      56: i2b
      57: bastore
      58: lload_2
      59: bipush        7
      61: lushr
      62: lstore_2
      63: iinc          4, 1
      66: goto          3
      69: aload_0
      70: invokevirtual #6                  // Method clearHashCache:()V
      73: iload         4
      75: iconst_1
      76: iadd
      77: ireturn

  public org.apache.hadoop.hbase.util.ByteRange shallowCopySubRange(int, int);
    Code:
       0: aload_0
       1: iload_1
       2: iload_2
       3: invokevirtual #37                 // Method shallowCopySubRange:(II)Lorg/apache/hadoop/hbase/util/PositionedByteRange;
       6: areturn

  public org.apache.hadoop.hbase.util.ByteRange shallowCopy();
    Code:
       0: aload_0
       1: invokevirtual #38                 // Method shallowCopy:()Lorg/apache/hadoop/hbase/util/PositionedByteRange;
       4: areturn

  public org.apache.hadoop.hbase.util.ByteRange deepCopy();
    Code:
       0: aload_0
       1: invokevirtual #39                 // Method deepCopy:()Lorg/apache/hadoop/hbase/util/PositionedByteRange;
       4: areturn

  public org.apache.hadoop.hbase.util.ByteRange put(int, byte[], int, int);
    Code:
       0: aload_0
       1: iload_1
       2: aload_2
       3: iload_3
       4: iload         4
       6: invokevirtual #19                 // Method put:(I[BII)Lorg/apache/hadoop/hbase/util/PositionedByteRange;
       9: areturn

  public org.apache.hadoop.hbase.util.ByteRange put(int, byte[]);
    Code:
       0: aload_0
       1: iload_1
       2: aload_2
       3: invokevirtual #40                 // Method put:(I[B)Lorg/apache/hadoop/hbase/util/PositionedByteRange;
       6: areturn

  public org.apache.hadoop.hbase.util.ByteRange putLong(int, long);
    Code:
       0: aload_0
       1: iload_1
       2: lload_2
       3: invokevirtual #29                 // Method putLong:(IJ)Lorg/apache/hadoop/hbase/util/PositionedByteRange;
       6: areturn

  public org.apache.hadoop.hbase.util.ByteRange putInt(int, int);
    Code:
       0: aload_0
       1: iload_1
       2: iload_2
       3: invokevirtual #28                 // Method putInt:(II)Lorg/apache/hadoop/hbase/util/PositionedByteRange;
       6: areturn

  public org.apache.hadoop.hbase.util.ByteRange putShort(int, short);
    Code:
       0: aload_0
       1: iload_1
       2: iload_2
       3: invokevirtual #26                 // Method putShort:(IS)Lorg/apache/hadoop/hbase/util/PositionedByteRange;
       6: areturn

  public org.apache.hadoop.hbase.util.ByteRange put(int, byte);
    Code:
       0: aload_0
       1: iload_1
       2: iload_2
       3: invokevirtual #17                 // Method put:(IB)Lorg/apache/hadoop/hbase/util/PositionedByteRange;
       6: areturn

  public org.apache.hadoop.hbase.util.ByteRange get(int, byte[], int, int);
    Code:
       0: aload_0
       1: iload_1
       2: aload_2
       3: iload_3
       4: iload         4
       6: invokevirtual #41                 // Method get:(I[BII)Lorg/apache/hadoop/hbase/util/PositionedByteRange;
       9: areturn

  public org.apache.hadoop.hbase.util.ByteRange get(int, byte[]);
    Code:
       0: aload_0
       1: iload_1
       2: aload_2
       3: invokevirtual #42                 // Method get:(I[B)Lorg/apache/hadoop/hbase/util/PositionedByteRange;
       6: areturn

  public org.apache.hadoop.hbase.util.ByteRange setLength(int);
    Code:
       0: aload_0
       1: iload_1
       2: invokevirtual #43                 // Method setLength:(I)Lorg/apache/hadoop/hbase/util/PositionedByteRange;
       5: areturn

  public org.apache.hadoop.hbase.util.ByteRange setOffset(int);
    Code:
       0: aload_0
       1: iload_1
       2: invokevirtual #44                 // Method setOffset:(I)Lorg/apache/hadoop/hbase/util/PositionedByteRange;
       5: areturn

  public org.apache.hadoop.hbase.util.ByteRange set(byte[], int, int);
    Code:
       0: aload_0
       1: aload_1
       2: iload_2
       3: iload_3
       4: invokevirtual #4                  // Method set:([BII)Lorg/apache/hadoop/hbase/util/PositionedByteRange;
       7: areturn

  public org.apache.hadoop.hbase.util.ByteRange set(byte[]);
    Code:
       0: aload_0
       1: aload_1
       2: invokevirtual #3                  // Method set:([B)Lorg/apache/hadoop/hbase/util/PositionedByteRange;
       5: areturn

  public org.apache.hadoop.hbase.util.ByteRange set(int);
    Code:
       0: aload_0
       1: iload_1
       2: invokevirtual #45                 // Method set:(I)Lorg/apache/hadoop/hbase/util/PositionedByteRange;
       5: areturn

  public org.apache.hadoop.hbase.util.ByteRange unset();
    Code:
       0: aload_0
       1: invokevirtual #46                 // Method unset:()Lorg/apache/hadoop/hbase/util/PositionedByteRange;
       4: areturn
}
