Compiled from "SimpleRegionNormalizer.java"
class org.apache.hadoop.hbase.master.normalizer.SimpleRegionNormalizer$PlanComparator implements java.util.Comparator<org.apache.hadoop.hbase.master.normalizer.NormalizationPlan> {
  org.apache.hadoop.hbase.master.normalizer.SimpleRegionNormalizer$PlanComparator();
    Code:
       0: aload_0
       1: invokespecial #1                  // Method java/lang/Object."<init>":()V
       4: return

  public int compare(org.apache.hadoop.hbase.master.normalizer.NormalizationPlan, org.apache.hadoop.hbase.master.normalizer.NormalizationPlan);
    Code:
       0: aload_1
       1: instanceof    #2                  // class org/apache/hadoop/hbase/master/normalizer/SplitNormalizationPlan
       4: istore_3
       5: aload_2
       6: instanceof    #2                  // class org/apache/hadoop/hbase/master/normalizer/SplitNormalizationPlan
       9: istore        4
      11: iload_3
      12: ifeq          22
      15: iload         4
      17: ifeq          22
      20: iconst_0
      21: ireturn
      22: iload_3
      23: ifeq          28
      26: iconst_m1
      27: ireturn
      28: iload         4
      30: ifeq          35
      33: iconst_1
      34: ireturn
      35: iconst_0
      36: ireturn

  public int compare(java.lang.Object, java.lang.Object);
    Code:
       0: aload_0
       1: aload_1
       2: checkcast     #3                  // class org/apache/hadoop/hbase/master/normalizer/NormalizationPlan
       5: aload_2
       6: checkcast     #3                  // class org/apache/hadoop/hbase/master/normalizer/NormalizationPlan
       9: invokevirtual #4                  // Method compare:(Lorg/apache/hadoop/hbase/master/normalizer/NormalizationPlan;Lorg/apache/hadoop/hbase/master/normalizer/NormalizationPlan;)I
      12: ireturn
}
