Compiled from "SingleByteBuff.java"
public class org.apache.hadoop.hbase.nio.SingleByteBuff extends org.apache.hadoop.hbase.nio.ByteBuff {
  public org.apache.hadoop.hbase.nio.SingleByteBuff(java.nio.ByteBuffer);
    Code:
       0: aload_0
       1: invokespecial #1                  // Method org/apache/hadoop/hbase/nio/ByteBuff."<init>":()V
       4: aload_0
       5: aconst_null
       6: putfield      #2                  // Field unsafeRef:Ljava/lang/Object;
       9: aload_0
      10: aload_1
      11: putfield      #3                  // Field buf:Ljava/nio/ByteBuffer;
      14: aload_1
      15: invokevirtual #4                  // Method java/nio/ByteBuffer.hasArray:()Z
      18: ifeq          45
      21: aload_0
      22: getstatic     #5                  // Field org/apache/hadoop/hbase/util/UnsafeAccess.BYTE_ARRAY_BASE_OFFSET:J
      25: aload_1
      26: invokevirtual #6                  // Method java/nio/ByteBuffer.arrayOffset:()I
      29: i2l
      30: ladd
      31: putfield      #7                  // Field unsafeOffset:J
      34: aload_0
      35: aload_1
      36: invokevirtual #8                  // Method java/nio/ByteBuffer.array:()[B
      39: putfield      #2                  // Field unsafeRef:Ljava/lang/Object;
      42: goto          58
      45: aload_0
      46: aload_1
      47: checkcast     #9                  // class sun/nio/ch/DirectBuffer
      50: invokeinterface #10,  1           // InterfaceMethod sun/nio/ch/DirectBuffer.address:()J
      55: putfield      #7                  // Field unsafeOffset:J
      58: return

  public int position();
    Code:
       0: aload_0
       1: getfield      #3                  // Field buf:Ljava/nio/ByteBuffer;
       4: invokevirtual #11                 // Method java/nio/ByteBuffer.position:()I
       7: ireturn

  public org.apache.hadoop.hbase.nio.SingleByteBuff position(int);
    Code:
       0: aload_0
       1: getfield      #3                  // Field buf:Ljava/nio/ByteBuffer;
       4: iload_1
       5: invokevirtual #12                 // Method java/nio/ByteBuffer.position:(I)Ljava/nio/Buffer;
       8: pop
       9: aload_0
      10: areturn

  public org.apache.hadoop.hbase.nio.SingleByteBuff skip(int);
    Code:
       0: aload_0
       1: getfield      #3                  // Field buf:Ljava/nio/ByteBuffer;
       4: aload_0
       5: getfield      #3                  // Field buf:Ljava/nio/ByteBuffer;
       8: invokevirtual #11                 // Method java/nio/ByteBuffer.position:()I
      11: iload_1
      12: iadd
      13: invokevirtual #12                 // Method java/nio/ByteBuffer.position:(I)Ljava/nio/Buffer;
      16: pop
      17: aload_0
      18: areturn

  public org.apache.hadoop.hbase.nio.SingleByteBuff moveBack(int);
    Code:
       0: aload_0
       1: getfield      #3                  // Field buf:Ljava/nio/ByteBuffer;
       4: aload_0
       5: getfield      #3                  // Field buf:Ljava/nio/ByteBuffer;
       8: invokevirtual #11                 // Method java/nio/ByteBuffer.position:()I
      11: iload_1
      12: isub
      13: invokevirtual #12                 // Method java/nio/ByteBuffer.position:(I)Ljava/nio/Buffer;
      16: pop
      17: aload_0
      18: areturn

  public int capacity();
    Code:
       0: aload_0
       1: getfield      #3                  // Field buf:Ljava/nio/ByteBuffer;
       4: invokevirtual #13                 // Method java/nio/ByteBuffer.capacity:()I
       7: ireturn

  public int limit();
    Code:
       0: aload_0
       1: getfield      #3                  // Field buf:Ljava/nio/ByteBuffer;
       4: invokevirtual #14                 // Method java/nio/ByteBuffer.limit:()I
       7: ireturn

  public org.apache.hadoop.hbase.nio.SingleByteBuff limit(int);
    Code:
       0: aload_0
       1: getfield      #3                  // Field buf:Ljava/nio/ByteBuffer;
       4: iload_1
       5: invokevirtual #15                 // Method java/nio/ByteBuffer.limit:(I)Ljava/nio/Buffer;
       8: pop
       9: aload_0
      10: areturn

  public org.apache.hadoop.hbase.nio.SingleByteBuff rewind();
    Code:
       0: aload_0
       1: getfield      #3                  // Field buf:Ljava/nio/ByteBuffer;
       4: invokevirtual #16                 // Method java/nio/ByteBuffer.rewind:()Ljava/nio/Buffer;
       7: pop
       8: aload_0
       9: areturn

  public org.apache.hadoop.hbase.nio.SingleByteBuff mark();
    Code:
       0: aload_0
       1: getfield      #3                  // Field buf:Ljava/nio/ByteBuffer;
       4: invokevirtual #17                 // Method java/nio/ByteBuffer.mark:()Ljava/nio/Buffer;
       7: pop
       8: aload_0
       9: areturn

  public java.nio.ByteBuffer asSubByteBuffer(int);
    Code:
       0: aload_0
       1: getfield      #3                  // Field buf:Ljava/nio/ByteBuffer;
       4: areturn

  public void asSubByteBuffer(int, int, org.apache.hadoop.hbase.util.ObjectIntPair<java.nio.ByteBuffer>);
    Code:
       0: aload_3
       1: aload_0
       2: getfield      #3                  // Field buf:Ljava/nio/ByteBuffer;
       5: invokevirtual #18                 // Method org/apache/hadoop/hbase/util/ObjectIntPair.setFirst:(Ljava/lang/Object;)V
       8: aload_3
       9: iload_1
      10: invokevirtual #19                 // Method org/apache/hadoop/hbase/util/ObjectIntPair.setSecond:(I)V
      13: return

  public int remaining();
    Code:
       0: aload_0
       1: getfield      #3                  // Field buf:Ljava/nio/ByteBuffer;
       4: invokevirtual #20                 // Method java/nio/ByteBuffer.remaining:()I
       7: ireturn

  public boolean hasRemaining();
    Code:
       0: aload_0
       1: getfield      #3                  // Field buf:Ljava/nio/ByteBuffer;
       4: invokevirtual #21                 // Method java/nio/ByteBuffer.hasRemaining:()Z
       7: ireturn

  public org.apache.hadoop.hbase.nio.SingleByteBuff reset();
    Code:
       0: aload_0
       1: getfield      #3                  // Field buf:Ljava/nio/ByteBuffer;
       4: invokevirtual #22                 // Method java/nio/ByteBuffer.reset:()Ljava/nio/Buffer;
       7: pop
       8: aload_0
       9: areturn

  public org.apache.hadoop.hbase.nio.SingleByteBuff slice();
    Code:
       0: new           #23                 // class org/apache/hadoop/hbase/nio/SingleByteBuff
       3: dup
       4: aload_0
       5: getfield      #3                  // Field buf:Ljava/nio/ByteBuffer;
       8: invokevirtual #24                 // Method java/nio/ByteBuffer.slice:()Ljava/nio/ByteBuffer;
      11: invokespecial #25                 // Method "<init>":(Ljava/nio/ByteBuffer;)V
      14: areturn

  public org.apache.hadoop.hbase.nio.SingleByteBuff duplicate();
    Code:
       0: new           #23                 // class org/apache/hadoop/hbase/nio/SingleByteBuff
       3: dup
       4: aload_0
       5: getfield      #3                  // Field buf:Ljava/nio/ByteBuffer;
       8: invokevirtual #26                 // Method java/nio/ByteBuffer.duplicate:()Ljava/nio/ByteBuffer;
      11: invokespecial #25                 // Method "<init>":(Ljava/nio/ByteBuffer;)V
      14: areturn

  public byte get();
    Code:
       0: aload_0
       1: getfield      #3                  // Field buf:Ljava/nio/ByteBuffer;
       4: invokevirtual #27                 // Method java/nio/ByteBuffer.get:()B
       7: ireturn

  public byte get(int);
    Code:
       0: getstatic     #28                 // Field UNSAFE_AVAIL:Z
       3: ifeq          21
       6: aload_0
       7: getfield      #2                  // Field unsafeRef:Ljava/lang/Object;
      10: aload_0
      11: getfield      #7                  // Field unsafeOffset:J
      14: iload_1
      15: i2l
      16: ladd
      17: invokestatic  #29                 // Method org/apache/hadoop/hbase/util/UnsafeAccess.toByte:(Ljava/lang/Object;J)B
      20: ireturn
      21: aload_0
      22: getfield      #3                  // Field buf:Ljava/nio/ByteBuffer;
      25: iload_1
      26: invokevirtual #30                 // Method java/nio/ByteBuffer.get:(I)B
      29: ireturn

  public byte getByteAfterPosition(int);
    Code:
       0: aload_0
       1: aload_0
       2: getfield      #3                  // Field buf:Ljava/nio/ByteBuffer;
       5: invokevirtual #11                 // Method java/nio/ByteBuffer.position:()I
       8: iload_1
       9: iadd
      10: invokevirtual #31                 // Method get:(I)B
      13: ireturn

  public org.apache.hadoop.hbase.nio.SingleByteBuff put(byte);
    Code:
       0: aload_0
       1: getfield      #3                  // Field buf:Ljava/nio/ByteBuffer;
       4: iload_1
       5: invokevirtual #32                 // Method java/nio/ByteBuffer.put:(B)Ljava/nio/ByteBuffer;
       8: pop
       9: aload_0
      10: areturn

  public org.apache.hadoop.hbase.nio.SingleByteBuff put(int, byte);
    Code:
       0: aload_0
       1: getfield      #3                  // Field buf:Ljava/nio/ByteBuffer;
       4: iload_1
       5: iload_2
       6: invokevirtual #33                 // Method java/nio/ByteBuffer.put:(IB)Ljava/nio/ByteBuffer;
       9: pop
      10: aload_0
      11: areturn

  public void get(byte[], int, int);
    Code:
       0: aload_1
       1: aload_0
       2: getfield      #3                  // Field buf:Ljava/nio/ByteBuffer;
       5: aload_0
       6: getfield      #3                  // Field buf:Ljava/nio/ByteBuffer;
       9: invokevirtual #11                 // Method java/nio/ByteBuffer.position:()I
      12: iload_2
      13: iload_3
      14: invokestatic  #34                 // Method org/apache/hadoop/hbase/util/ByteBufferUtils.copyFromBufferToArray:([BLjava/nio/ByteBuffer;III)V
      17: aload_0
      18: getfield      #3                  // Field buf:Ljava/nio/ByteBuffer;
      21: aload_0
      22: getfield      #3                  // Field buf:Ljava/nio/ByteBuffer;
      25: invokevirtual #11                 // Method java/nio/ByteBuffer.position:()I
      28: iload_3
      29: iadd
      30: invokevirtual #12                 // Method java/nio/ByteBuffer.position:(I)Ljava/nio/Buffer;
      33: pop
      34: return

  public void get(int, byte[], int, int);
    Code:
       0: aload_2
       1: aload_0
       2: getfield      #3                  // Field buf:Ljava/nio/ByteBuffer;
       5: iload_1
       6: iload_3
       7: iload         4
       9: invokestatic  #34                 // Method org/apache/hadoop/hbase/util/ByteBufferUtils.copyFromBufferToArray:([BLjava/nio/ByteBuffer;III)V
      12: return

  public void get(byte[]);
    Code:
       0: aload_0
       1: aload_1
       2: iconst_0
       3: aload_1
       4: arraylength
       5: invokevirtual #35                 // Method get:([BII)V
       8: return

  public org.apache.hadoop.hbase.nio.SingleByteBuff put(int, org.apache.hadoop.hbase.nio.ByteBuff, int, int);
    Code:
       0: aload_2
       1: instanceof    #23                 // class org/apache/hadoop/hbase/nio/SingleByteBuff
       4: ifeq          28
       7: aload_2
       8: checkcast     #23                 // class org/apache/hadoop/hbase/nio/SingleByteBuff
      11: getfield      #3                  // Field buf:Ljava/nio/ByteBuffer;
      14: aload_0
      15: getfield      #3                  // Field buf:Ljava/nio/ByteBuffer;
      18: iload_3
      19: iload_1
      20: iload         4
      22: invokestatic  #36                 // Method org/apache/hadoop/hbase/util/ByteBufferUtils.copyFromBufferToBuffer:(Ljava/nio/ByteBuffer;Ljava/nio/ByteBuffer;III)V
      25: goto          77
      28: new           #37                 // class org/apache/hadoop/hbase/util/ObjectIntPair
      31: dup
      32: invokespecial #38                 // Method org/apache/hadoop/hbase/util/ObjectIntPair."<init>":()V
      35: astore        5
      37: aload_2
      38: iload_3
      39: iload         4
      41: aload         5
      43: invokevirtual #39                 // Method org/apache/hadoop/hbase/nio/ByteBuff.asSubByteBuffer:(IILorg/apache/hadoop/hbase/util/ObjectIntPair;)V
      46: aload         5
      48: invokevirtual #40                 // Method org/apache/hadoop/hbase/util/ObjectIntPair.getFirst:()Ljava/lang/Object;
      51: ifnull        77
      54: aload         5
      56: invokevirtual #40                 // Method org/apache/hadoop/hbase/util/ObjectIntPair.getFirst:()Ljava/lang/Object;
      59: checkcast     #41                 // class java/nio/ByteBuffer
      62: aload_0
      63: getfield      #3                  // Field buf:Ljava/nio/ByteBuffer;
      66: aload         5
      68: invokevirtual #42                 // Method org/apache/hadoop/hbase/util/ObjectIntPair.getSecond:()I
      71: iload_1
      72: iload         4
      74: invokestatic  #36                 // Method org/apache/hadoop/hbase/util/ByteBufferUtils.copyFromBufferToBuffer:(Ljava/nio/ByteBuffer;Ljava/nio/ByteBuffer;III)V
      77: aload_0
      78: areturn

  public org.apache.hadoop.hbase.nio.SingleByteBuff put(byte[], int, int);
    Code:
       0: aload_0
       1: getfield      #3                  // Field buf:Ljava/nio/ByteBuffer;
       4: aload_1
       5: iload_2
       6: iload_3
       7: invokestatic  #43                 // Method org/apache/hadoop/hbase/util/ByteBufferUtils.copyFromArrayToBuffer:(Ljava/nio/ByteBuffer;[BII)V
      10: aload_0
      11: areturn

  public org.apache.hadoop.hbase.nio.SingleByteBuff put(byte[]);
    Code:
       0: aload_0
       1: aload_1
       2: iconst_0
       3: aload_1
       4: arraylength
       5: invokevirtual #44                 // Method put:([BII)Lorg/apache/hadoop/hbase/nio/SingleByteBuff;
       8: areturn

  public boolean hasArray();
    Code:
       0: aload_0
       1: getfield      #3                  // Field buf:Ljava/nio/ByteBuffer;
       4: invokevirtual #4                  // Method java/nio/ByteBuffer.hasArray:()Z
       7: ireturn

  public byte[] array();
    Code:
       0: aload_0
       1: getfield      #3                  // Field buf:Ljava/nio/ByteBuffer;
       4: invokevirtual #8                  // Method java/nio/ByteBuffer.array:()[B
       7: areturn

  public int arrayOffset();
    Code:
       0: aload_0
       1: getfield      #3                  // Field buf:Ljava/nio/ByteBuffer;
       4: invokevirtual #6                  // Method java/nio/ByteBuffer.arrayOffset:()I
       7: ireturn

  public short getShort();
    Code:
       0: aload_0
       1: getfield      #3                  // Field buf:Ljava/nio/ByteBuffer;
       4: invokevirtual #45                 // Method java/nio/ByteBuffer.getShort:()S
       7: ireturn

  public short getShort(int);
    Code:
       0: getstatic     #46                 // Field UNSAFE_UNALIGNED:Z
       3: ifeq          21
       6: aload_0
       7: getfield      #2                  // Field unsafeRef:Ljava/lang/Object;
      10: aload_0
      11: getfield      #7                  // Field unsafeOffset:J
      14: iload_1
      15: i2l
      16: ladd
      17: invokestatic  #47                 // Method org/apache/hadoop/hbase/util/UnsafeAccess.toShort:(Ljava/lang/Object;J)S
      20: ireturn
      21: aload_0
      22: getfield      #3                  // Field buf:Ljava/nio/ByteBuffer;
      25: iload_1
      26: invokevirtual #48                 // Method java/nio/ByteBuffer.getShort:(I)S
      29: ireturn

  public short getShortAfterPosition(int);
    Code:
       0: aload_0
       1: aload_0
       2: getfield      #3                  // Field buf:Ljava/nio/ByteBuffer;
       5: invokevirtual #11                 // Method java/nio/ByteBuffer.position:()I
       8: iload_1
       9: iadd
      10: invokevirtual #49                 // Method getShort:(I)S
      13: ireturn

  public int getInt();
    Code:
       0: aload_0
       1: getfield      #3                  // Field buf:Ljava/nio/ByteBuffer;
       4: invokevirtual #50                 // Method java/nio/ByteBuffer.getInt:()I
       7: ireturn

  public org.apache.hadoop.hbase.nio.SingleByteBuff putInt(int);
    Code:
       0: aload_0
       1: getfield      #3                  // Field buf:Ljava/nio/ByteBuffer;
       4: iload_1
       5: invokestatic  #51                 // Method org/apache/hadoop/hbase/util/ByteBufferUtils.putInt:(Ljava/nio/ByteBuffer;I)V
       8: aload_0
       9: areturn

  public int getInt(int);
    Code:
       0: getstatic     #46                 // Field UNSAFE_UNALIGNED:Z
       3: ifeq          21
       6: aload_0
       7: getfield      #2                  // Field unsafeRef:Ljava/lang/Object;
      10: aload_0
      11: getfield      #7                  // Field unsafeOffset:J
      14: iload_1
      15: i2l
      16: ladd
      17: invokestatic  #52                 // Method org/apache/hadoop/hbase/util/UnsafeAccess.toInt:(Ljava/lang/Object;J)I
      20: ireturn
      21: aload_0
      22: getfield      #3                  // Field buf:Ljava/nio/ByteBuffer;
      25: iload_1
      26: invokevirtual #53                 // Method java/nio/ByteBuffer.getInt:(I)I
      29: ireturn

  public int getIntAfterPosition(int);
    Code:
       0: aload_0
       1: aload_0
       2: getfield      #3                  // Field buf:Ljava/nio/ByteBuffer;
       5: invokevirtual #11                 // Method java/nio/ByteBuffer.position:()I
       8: iload_1
       9: iadd
      10: invokevirtual #54                 // Method getInt:(I)I
      13: ireturn

  public long getLong();
    Code:
       0: aload_0
       1: getfield      #3                  // Field buf:Ljava/nio/ByteBuffer;
       4: invokevirtual #55                 // Method java/nio/ByteBuffer.getLong:()J
       7: lreturn

  public org.apache.hadoop.hbase.nio.SingleByteBuff putLong(long);
    Code:
       0: aload_0
       1: getfield      #3                  // Field buf:Ljava/nio/ByteBuffer;
       4: lload_1
       5: invokestatic  #56                 // Method org/apache/hadoop/hbase/util/ByteBufferUtils.putLong:(Ljava/nio/ByteBuffer;J)V
       8: aload_0
       9: areturn

  public long getLong(int);
    Code:
       0: getstatic     #46                 // Field UNSAFE_UNALIGNED:Z
       3: ifeq          21
       6: aload_0
       7: getfield      #2                  // Field unsafeRef:Ljava/lang/Object;
      10: aload_0
      11: getfield      #7                  // Field unsafeOffset:J
      14: iload_1
      15: i2l
      16: ladd
      17: invokestatic  #57                 // Method org/apache/hadoop/hbase/util/UnsafeAccess.toLong:(Ljava/lang/Object;J)J
      20: lreturn
      21: aload_0
      22: getfield      #3                  // Field buf:Ljava/nio/ByteBuffer;
      25: iload_1
      26: invokevirtual #58                 // Method java/nio/ByteBuffer.getLong:(I)J
      29: lreturn

  public long getLongAfterPosition(int);
    Code:
       0: aload_0
       1: aload_0
       2: getfield      #3                  // Field buf:Ljava/nio/ByteBuffer;
       5: invokevirtual #11                 // Method java/nio/ByteBuffer.position:()I
       8: iload_1
       9: iadd
      10: invokevirtual #59                 // Method getLong:(I)J
      13: lreturn

  public byte[] toBytes(int, int);
    Code:
       0: iload_2
       1: newarray       byte
       3: astore_3
       4: aload_3
       5: aload_0
       6: getfield      #3                  // Field buf:Ljava/nio/ByteBuffer;
       9: iload_1
      10: iconst_0
      11: iload_2
      12: invokestatic  #34                 // Method org/apache/hadoop/hbase/util/ByteBufferUtils.copyFromBufferToArray:([BLjava/nio/ByteBuffer;III)V
      15: aload_3
      16: areturn

  public void get(java.nio.ByteBuffer, int, int);
    Code:
       0: aload_0
       1: getfield      #3                  // Field buf:Ljava/nio/ByteBuffer;
       4: aload_1
       5: iload_2
       6: iload_3
       7: invokestatic  #60                 // Method org/apache/hadoop/hbase/util/ByteBufferUtils.copyFromBufferToBuffer:(Ljava/nio/ByteBuffer;Ljava/nio/ByteBuffer;II)V
      10: return

  public int read(java.nio.channels.ReadableByteChannel) throws java.io.IOException;
    Code:
       0: aload_1
       1: aload_0
       2: getfield      #3                  // Field buf:Ljava/nio/ByteBuffer;
       5: invokestatic  #61                 // Method channelRead:(Ljava/nio/channels/ReadableByteChannel;Ljava/nio/ByteBuffer;)I
       8: ireturn

  public boolean equals(java.lang.Object);
    Code:
       0: aload_1
       1: instanceof    #23                 // class org/apache/hadoop/hbase/nio/SingleByteBuff
       4: ifne          9
       7: iconst_0
       8: ireturn
       9: aload_0
      10: getfield      #3                  // Field buf:Ljava/nio/ByteBuffer;
      13: aload_1
      14: checkcast     #23                 // class org/apache/hadoop/hbase/nio/SingleByteBuff
      17: getfield      #3                  // Field buf:Ljava/nio/ByteBuffer;
      20: invokevirtual #62                 // Method java/nio/ByteBuffer.equals:(Ljava/lang/Object;)Z
      23: ireturn

  public int hashCode();
    Code:
       0: aload_0
       1: getfield      #3                  // Field buf:Ljava/nio/ByteBuffer;
       4: invokevirtual #63                 // Method java/nio/ByteBuffer.hashCode:()I
       7: ireturn

  public java.nio.ByteBuffer getEnclosingByteBuffer();
    Code:
       0: aload_0
       1: getfield      #3                  // Field buf:Ljava/nio/ByteBuffer;
       4: areturn

  public org.apache.hadoop.hbase.nio.ByteBuff put(int, org.apache.hadoop.hbase.nio.ByteBuff, int, int);
    Code:
       0: aload_0
       1: iload_1
       2: aload_2
       3: iload_3
       4: iload         4
       6: invokevirtual #64                 // Method put:(ILorg/apache/hadoop/hbase/nio/ByteBuff;II)Lorg/apache/hadoop/hbase/nio/SingleByteBuff;
       9: areturn

  public org.apache.hadoop.hbase.nio.ByteBuff putLong(long);
    Code:
       0: aload_0
       1: lload_1
       2: invokevirtual #65                 // Method putLong:(J)Lorg/apache/hadoop/hbase/nio/SingleByteBuff;
       5: areturn

  public org.apache.hadoop.hbase.nio.ByteBuff putInt(int);
    Code:
       0: aload_0
       1: iload_1
       2: invokevirtual #66                 // Method putInt:(I)Lorg/apache/hadoop/hbase/nio/SingleByteBuff;
       5: areturn

  public org.apache.hadoop.hbase.nio.ByteBuff put(byte[]);
    Code:
       0: aload_0
       1: aload_1
       2: invokevirtual #67                 // Method put:([B)Lorg/apache/hadoop/hbase/nio/SingleByteBuff;
       5: areturn

  public org.apache.hadoop.hbase.nio.ByteBuff put(byte[], int, int);
    Code:
       0: aload_0
       1: aload_1
       2: iload_2
       3: iload_3
       4: invokevirtual #44                 // Method put:([BII)Lorg/apache/hadoop/hbase/nio/SingleByteBuff;
       7: areturn

  public org.apache.hadoop.hbase.nio.ByteBuff put(int, byte);
    Code:
       0: aload_0
       1: iload_1
       2: iload_2
       3: invokevirtual #68                 // Method put:(IB)Lorg/apache/hadoop/hbase/nio/SingleByteBuff;
       6: areturn

  public org.apache.hadoop.hbase.nio.ByteBuff put(byte);
    Code:
       0: aload_0
       1: iload_1
       2: invokevirtual #69                 // Method put:(B)Lorg/apache/hadoop/hbase/nio/SingleByteBuff;
       5: areturn

  public org.apache.hadoop.hbase.nio.ByteBuff duplicate();
    Code:
       0: aload_0
       1: invokevirtual #70                 // Method duplicate:()Lorg/apache/hadoop/hbase/nio/SingleByteBuff;
       4: areturn

  public org.apache.hadoop.hbase.nio.ByteBuff slice();
    Code:
       0: aload_0
       1: invokevirtual #71                 // Method slice:()Lorg/apache/hadoop/hbase/nio/SingleByteBuff;
       4: areturn

  public org.apache.hadoop.hbase.nio.ByteBuff reset();
    Code:
       0: aload_0
       1: invokevirtual #72                 // Method reset:()Lorg/apache/hadoop/hbase/nio/SingleByteBuff;
       4: areturn

  public org.apache.hadoop.hbase.nio.ByteBuff mark();
    Code:
       0: aload_0
       1: invokevirtual #73                 // Method mark:()Lorg/apache/hadoop/hbase/nio/SingleByteBuff;
       4: areturn

  public org.apache.hadoop.hbase.nio.ByteBuff rewind();
    Code:
       0: aload_0
       1: invokevirtual #74                 // Method rewind:()Lorg/apache/hadoop/hbase/nio/SingleByteBuff;
       4: areturn

  public org.apache.hadoop.hbase.nio.ByteBuff limit(int);
    Code:
       0: aload_0
       1: iload_1
       2: invokevirtual #75                 // Method limit:(I)Lorg/apache/hadoop/hbase/nio/SingleByteBuff;
       5: areturn

  public org.apache.hadoop.hbase.nio.ByteBuff moveBack(int);
    Code:
       0: aload_0
       1: iload_1
       2: invokevirtual #76                 // Method moveBack:(I)Lorg/apache/hadoop/hbase/nio/SingleByteBuff;
       5: areturn

  public org.apache.hadoop.hbase.nio.ByteBuff skip(int);
    Code:
       0: aload_0
       1: iload_1
       2: invokevirtual #77                 // Method skip:(I)Lorg/apache/hadoop/hbase/nio/SingleByteBuff;
       5: areturn

  public org.apache.hadoop.hbase.nio.ByteBuff position(int);
    Code:
       0: aload_0
       1: iload_1
       2: invokevirtual #78                 // Method position:(I)Lorg/apache/hadoop/hbase/nio/SingleByteBuff;
       5: areturn

  static {};
    Code:
       0: invokestatic  #79                 // Method org/apache/hadoop/hbase/util/UnsafeAvailChecker.isAvailable:()Z
       3: putstatic     #28                 // Field UNSAFE_AVAIL:Z
       6: invokestatic  #80                 // Method org/apache/hadoop/hbase/util/UnsafeAvailChecker.unaligned:()Z
       9: putstatic     #46                 // Field UNSAFE_UNALIGNED:Z
      12: return
}
