Compiled from "Size.java"
public final class org.apache.hadoop.hbase.Size$Unit extends java.lang.Enum<org.apache.hadoop.hbase.Size$Unit> {
  public static final org.apache.hadoop.hbase.Size$Unit PETABYTE;

  public static final org.apache.hadoop.hbase.Size$Unit TERABYTE;

  public static final org.apache.hadoop.hbase.Size$Unit GIGABYTE;

  public static final org.apache.hadoop.hbase.Size$Unit MEGABYTE;

  public static final org.apache.hadoop.hbase.Size$Unit KILOBYTE;

  public static final org.apache.hadoop.hbase.Size$Unit BYTE;

  public static org.apache.hadoop.hbase.Size$Unit[] values();
    Code:
       0: getstatic     #1                  // Field $VALUES:[Lorg/apache/hadoop/hbase/Size$Unit;
       3: invokevirtual #2                  // Method "[Lorg/apache/hadoop/hbase/Size$Unit;".clone:()Ljava/lang/Object;
       6: checkcast     #3                  // class "[Lorg/apache/hadoop/hbase/Size$Unit;"
       9: areturn

  public static org.apache.hadoop.hbase.Size$Unit valueOf(java.lang.String);
    Code:
       0: ldc           #4                  // class org/apache/hadoop/hbase/Size$Unit
       2: aload_0
       3: invokestatic  #5                  // Method java/lang/Enum.valueOf:(Ljava/lang/Class;Ljava/lang/String;)Ljava/lang/Enum;
       6: checkcast     #4                  // class org/apache/hadoop/hbase/Size$Unit
       9: areturn

  public int getOrderOfSize();
    Code:
       0: aload_0
       1: getfield      #7                  // Field orderOfSize:I
       4: ireturn

  public java.lang.String getSimpleName();
    Code:
       0: aload_0
       1: getfield      #8                  // Field simpleName:Ljava/lang/String;
       4: areturn

  static {};
    Code:
       0: new           #4                  // class org/apache/hadoop/hbase/Size$Unit
       3: dup
       4: ldc           #9                  // String PETABYTE
       6: iconst_0
       7: bipush        100
       9: ldc           #10                 // String PB
      11: invokespecial #11                 // Method "<init>":(Ljava/lang/String;IILjava/lang/String;)V
      14: putstatic     #12                 // Field PETABYTE:Lorg/apache/hadoop/hbase/Size$Unit;
      17: new           #4                  // class org/apache/hadoop/hbase/Size$Unit
      20: dup
      21: ldc           #13                 // String TERABYTE
      23: iconst_1
      24: bipush        99
      26: ldc           #14                 // String TB
      28: invokespecial #11                 // Method "<init>":(Ljava/lang/String;IILjava/lang/String;)V
      31: putstatic     #15                 // Field TERABYTE:Lorg/apache/hadoop/hbase/Size$Unit;
      34: new           #4                  // class org/apache/hadoop/hbase/Size$Unit
      37: dup
      38: ldc           #16                 // String GIGABYTE
      40: iconst_2
      41: bipush        98
      43: ldc           #17                 // String GB
      45: invokespecial #11                 // Method "<init>":(Ljava/lang/String;IILjava/lang/String;)V
      48: putstatic     #18                 // Field GIGABYTE:Lorg/apache/hadoop/hbase/Size$Unit;
      51: new           #4                  // class org/apache/hadoop/hbase/Size$Unit
      54: dup
      55: ldc           #19                 // String MEGABYTE
      57: iconst_3
      58: bipush        97
      60: ldc           #20                 // String MB
      62: invokespecial #11                 // Method "<init>":(Ljava/lang/String;IILjava/lang/String;)V
      65: putstatic     #21                 // Field MEGABYTE:Lorg/apache/hadoop/hbase/Size$Unit;
      68: new           #4                  // class org/apache/hadoop/hbase/Size$Unit
      71: dup
      72: ldc           #22                 // String KILOBYTE
      74: iconst_4
      75: bipush        96
      77: ldc           #23                 // String KB
      79: invokespecial #11                 // Method "<init>":(Ljava/lang/String;IILjava/lang/String;)V
      82: putstatic     #24                 // Field KILOBYTE:Lorg/apache/hadoop/hbase/Size$Unit;
      85: new           #4                  // class org/apache/hadoop/hbase/Size$Unit
      88: dup
      89: ldc           #25                 // String BYTE
      91: iconst_5
      92: bipush        95
      94: ldc           #26                 // String B
      96: invokespecial #11                 // Method "<init>":(Ljava/lang/String;IILjava/lang/String;)V
      99: putstatic     #27                 // Field BYTE:Lorg/apache/hadoop/hbase/Size$Unit;
     102: bipush        6
     104: anewarray     #4                  // class org/apache/hadoop/hbase/Size$Unit
     107: dup
     108: iconst_0
     109: getstatic     #12                 // Field PETABYTE:Lorg/apache/hadoop/hbase/Size$Unit;
     112: aastore
     113: dup
     114: iconst_1
     115: getstatic     #15                 // Field TERABYTE:Lorg/apache/hadoop/hbase/Size$Unit;
     118: aastore
     119: dup
     120: iconst_2
     121: getstatic     #18                 // Field GIGABYTE:Lorg/apache/hadoop/hbase/Size$Unit;
     124: aastore
     125: dup
     126: iconst_3
     127: getstatic     #21                 // Field MEGABYTE:Lorg/apache/hadoop/hbase/Size$Unit;
     130: aastore
     131: dup
     132: iconst_4
     133: getstatic     #24                 // Field KILOBYTE:Lorg/apache/hadoop/hbase/Size$Unit;
     136: aastore
     137: dup
     138: iconst_5
     139: getstatic     #27                 // Field BYTE:Lorg/apache/hadoop/hbase/Size$Unit;
     142: aastore
     143: putstatic     #1                  // Field $VALUES:[Lorg/apache/hadoop/hbase/Size$Unit;
     146: return
}
