Compiled from "SnapshotWithAclTestBase.java"
public abstract class org.apache.hadoop.hbase.client.SnapshotWithAclTestBase extends org.apache.hadoop.hbase.security.access.SecureTestUtil {
  protected static org.apache.hadoop.hbase.HBaseTestingUtility TEST_UTIL;

  public org.apache.hadoop.hbase.client.SnapshotWithAclTestBase();
    Code:
       0: aload_0
       1: invokespecial #4                  // Method org/apache/hadoop/hbase/security/access/SecureTestUtil."<init>":()V
       4: aload_0
       5: getstatic     #5                  // Field TEST_UTIL:Lorg/apache/hadoop/hbase/HBaseTestingUtility;
       8: invokevirtual #6                  // Method org/apache/hadoop/hbase/HBaseTestingUtility.getRandomUUID:()Ljava/util/UUID;
      11: invokevirtual #7                  // Method java/util/UUID.toString:()Ljava/lang/String;
      14: invokestatic  #8                  // Method org/apache/hadoop/hbase/TableName.valueOf:(Ljava/lang/String;)Lorg/apache/hadoop/hbase/TableName;
      17: putfield      #9                  // Field TEST_TABLE:Lorg/apache/hadoop/hbase/TableName;
      20: return

  public static void setupBeforeClass() throws java.lang.Exception;
    Code:
       0: getstatic     #5                  // Field TEST_UTIL:Lorg/apache/hadoop/hbase/HBaseTestingUtility;
       3: invokevirtual #10                 // Method org/apache/hadoop/hbase/HBaseTestingUtility.getConfiguration:()Lorg/apache/hadoop/conf/Configuration;
       6: astore_0
       7: aload_0
       8: invokestatic  #11                 // Method enableSecurity:(Lorg/apache/hadoop/conf/Configuration;)V
      11: aload_0
      12: ldc           #13                 // String hbase.coprocessor.region.classes
      14: ldc           #14                 // class org/apache/hadoop/hbase/security/access/AccessController
      16: invokevirtual #15                 // Method java/lang/Class.getName:()Ljava/lang/String;
      19: invokevirtual #16                 // Method org/apache/hadoop/conf/Configuration.set:(Ljava/lang/String;Ljava/lang/String;)V
      22: aload_0
      23: invokestatic  #17                 // Method verifyConfiguration:(Lorg/apache/hadoop/conf/Configuration;)V
      26: aload_0
      27: ldc           #19                 // String hbase.security.exec.permission.checks
      29: iconst_1
      30: invokevirtual #20                 // Method org/apache/hadoop/conf/Configuration.setBoolean:(Ljava/lang/String;Z)V
      33: getstatic     #5                  // Field TEST_UTIL:Lorg/apache/hadoop/hbase/HBaseTestingUtility;
      36: invokevirtual #21                 // Method org/apache/hadoop/hbase/HBaseTestingUtility.startMiniCluster:()Lorg/apache/hadoop/hbase/MiniHBaseCluster;
      39: pop
      40: getstatic     #5                  // Field TEST_UTIL:Lorg/apache/hadoop/hbase/HBaseTestingUtility;
      43: getstatic     #22                 // Field org/apache/hadoop/hbase/security/access/PermissionStorage.ACL_TABLE_NAME:Lorg/apache/hadoop/hbase/TableName;
      46: invokevirtual #23                 // Method org/apache/hadoop/hbase/HBaseTestingUtility.waitUntilAllRegionsAssigned:(Lorg/apache/hadoop/hbase/TableName;)V
      49: getstatic     #5                  // Field TEST_UTIL:Lorg/apache/hadoop/hbase/HBaseTestingUtility;
      52: invokevirtual #24                 // Method org/apache/hadoop/hbase/HBaseTestingUtility.getMiniHBaseCluster:()Lorg/apache/hadoop/hbase/MiniHBaseCluster;
      55: invokevirtual #25                 // Method org/apache/hadoop/hbase/MiniHBaseCluster.getMaster:()Lorg/apache/hadoop/hbase/master/HMaster;
      58: invokevirtual #26                 // Method org/apache/hadoop/hbase/master/HMaster.getMasterCoprocessorHost:()Lorg/apache/hadoop/hbase/master/MasterCoprocessorHost;
      61: astore_1
      62: aload_1
      63: ldc           #14                 // class org/apache/hadoop/hbase/security/access/AccessController
      65: iconst_0
      66: aload_0
      67: invokevirtual #28                 // Method org/apache/hadoop/hbase/master/MasterCoprocessorHost.load:(Ljava/lang/Class;ILorg/apache/hadoop/conf/Configuration;)V
      70: aload_0
      71: ldc           #29                 // String owner
      73: iconst_0
      74: anewarray     #30                 // class java/lang/String
      77: invokestatic  #31                 // Method org/apache/hadoop/hbase/security/User.createUserForTesting:(Lorg/apache/hadoop/conf/Configuration;Ljava/lang/String;[Ljava/lang/String;)Lorg/apache/hadoop/hbase/security/User;
      80: putstatic     #32                 // Field USER_OWNER:Lorg/apache/hadoop/hbase/security/User;
      83: aload_0
      84: ldc           #33                 // String rwuser
      86: iconst_0
      87: anewarray     #30                 // class java/lang/String
      90: invokestatic  #31                 // Method org/apache/hadoop/hbase/security/User.createUserForTesting:(Lorg/apache/hadoop/conf/Configuration;Ljava/lang/String;[Ljava/lang/String;)Lorg/apache/hadoop/hbase/security/User;
      93: putstatic     #34                 // Field USER_RW:Lorg/apache/hadoop/hbase/security/User;
      96: aload_0
      97: ldc           #35                 // String rouser
      99: iconst_0
     100: anewarray     #30                 // class java/lang/String
     103: invokestatic  #31                 // Method org/apache/hadoop/hbase/security/User.createUserForTesting:(Lorg/apache/hadoop/conf/Configuration;Ljava/lang/String;[Ljava/lang/String;)Lorg/apache/hadoop/hbase/security/User;
     106: putstatic     #36                 // Field USER_RO:Lorg/apache/hadoop/hbase/security/User;
     109: aload_0
     110: ldc           #37                 // String usernone
     112: iconst_0
     113: anewarray     #30                 // class java/lang/String
     116: invokestatic  #31                 // Method org/apache/hadoop/hbase/security/User.createUserForTesting:(Lorg/apache/hadoop/conf/Configuration;Ljava/lang/String;[Ljava/lang/String;)Lorg/apache/hadoop/hbase/security/User;
     119: putstatic     #38                 // Field USER_NONE:Lorg/apache/hadoop/hbase/security/User;
     122: return

  public void setUp() throws java.lang.Exception;
    Code:
       0: getstatic     #5                  // Field TEST_UTIL:Lorg/apache/hadoop/hbase/HBaseTestingUtility;
       3: aload_0
       4: getfield      #9                  // Field TEST_TABLE:Lorg/apache/hadoop/hbase/TableName;
       7: invokestatic  #39                 // Method org/apache/hadoop/hbase/client/TableDescriptorBuilder.newBuilder:(Lorg/apache/hadoop/hbase/TableName;)Lorg/apache/hadoop/hbase/client/TableDescriptorBuilder;
      10: getstatic     #2                  // Field TEST_FAMILY:[B
      13: invokestatic  #40                 // Method org/apache/hadoop/hbase/client/ColumnFamilyDescriptorBuilder.newBuilder:([B)Lorg/apache/hadoop/hbase/client/ColumnFamilyDescriptorBuilder;
      16: bipush        100
      18: invokevirtual #41                 // Method org/apache/hadoop/hbase/client/ColumnFamilyDescriptorBuilder.setMaxVersions:(I)Lorg/apache/hadoop/hbase/client/ColumnFamilyDescriptorBuilder;
      21: invokevirtual #42                 // Method org/apache/hadoop/hbase/client/ColumnFamilyDescriptorBuilder.build:()Lorg/apache/hadoop/hbase/client/ColumnFamilyDescriptor;
      24: invokevirtual #43                 // Method org/apache/hadoop/hbase/client/TableDescriptorBuilder.setColumnFamily:(Lorg/apache/hadoop/hbase/client/ColumnFamilyDescriptor;)Lorg/apache/hadoop/hbase/client/TableDescriptorBuilder;
      27: getstatic     #32                 // Field USER_OWNER:Lorg/apache/hadoop/hbase/security/User;
      30: invokevirtual #44                 // Method org/apache/hadoop/hbase/client/TableDescriptorBuilder.setOwner:(Lorg/apache/hadoop/hbase/security/User;)Lorg/apache/hadoop/hbase/client/TableDescriptorBuilder;
      33: invokevirtual #45                 // Method org/apache/hadoop/hbase/client/TableDescriptorBuilder.build:()Lorg/apache/hadoop/hbase/client/TableDescriptor;
      36: iconst_1
      37: anewarray     #46                 // class "[B"
      40: dup
      41: iconst_0
      42: ldc           #47                 // String s
      44: invokestatic  #48                 // Method org/apache/hadoop/hbase/util/Bytes.toBytes:(Ljava/lang/String;)[B
      47: aastore
      48: invokevirtual #49                 // Method org/apache/hadoop/hbase/HBaseTestingUtility.createTable:(Lorg/apache/hadoop/hbase/client/TableDescriptor;[[B)Lorg/apache/hadoop/hbase/client/Table;
      51: pop
      52: getstatic     #5                  // Field TEST_UTIL:Lorg/apache/hadoop/hbase/HBaseTestingUtility;
      55: aload_0
      56: getfield      #9                  // Field TEST_TABLE:Lorg/apache/hadoop/hbase/TableName;
      59: invokevirtual #50                 // Method org/apache/hadoop/hbase/HBaseTestingUtility.waitTableEnabled:(Lorg/apache/hadoop/hbase/TableName;)V
      62: getstatic     #5                  // Field TEST_UTIL:Lorg/apache/hadoop/hbase/HBaseTestingUtility;
      65: getstatic     #34                 // Field USER_RW:Lorg/apache/hadoop/hbase/security/User;
      68: invokevirtual #51                 // Method org/apache/hadoop/hbase/security/User.getShortName:()Ljava/lang/String;
      71: aload_0
      72: getfield      #9                  // Field TEST_TABLE:Lorg/apache/hadoop/hbase/TableName;
      75: getstatic     #2                  // Field TEST_FAMILY:[B
      78: aconst_null
      79: iconst_2
      80: anewarray     #52                 // class org/apache/hadoop/hbase/security/access/Permission$Action
      83: dup
      84: iconst_0
      85: getstatic     #53                 // Field org/apache/hadoop/hbase/security/access/Permission$Action.READ:Lorg/apache/hadoop/hbase/security/access/Permission$Action;
      88: aastore
      89: dup
      90: iconst_1
      91: getstatic     #54                 // Field org/apache/hadoop/hbase/security/access/Permission$Action.WRITE:Lorg/apache/hadoop/hbase/security/access/Permission$Action;
      94: aastore
      95: invokestatic  #55                 // Method grantOnTable:(Lorg/apache/hadoop/hbase/HBaseTestingUtility;Ljava/lang/String;Lorg/apache/hadoop/hbase/TableName;[B[B[Lorg/apache/hadoop/hbase/security/access/Permission$Action;)V
      98: getstatic     #5                  // Field TEST_UTIL:Lorg/apache/hadoop/hbase/HBaseTestingUtility;
     101: getstatic     #36                 // Field USER_RO:Lorg/apache/hadoop/hbase/security/User;
     104: invokevirtual #51                 // Method org/apache/hadoop/hbase/security/User.getShortName:()Ljava/lang/String;
     107: aload_0
     108: getfield      #9                  // Field TEST_TABLE:Lorg/apache/hadoop/hbase/TableName;
     111: getstatic     #2                  // Field TEST_FAMILY:[B
     114: aconst_null
     115: iconst_1
     116: anewarray     #52                 // class org/apache/hadoop/hbase/security/access/Permission$Action
     119: dup
     120: iconst_0
     121: getstatic     #53                 // Field org/apache/hadoop/hbase/security/access/Permission$Action.READ:Lorg/apache/hadoop/hbase/security/access/Permission$Action;
     124: aastore
     125: invokestatic  #55                 // Method grantOnTable:(Lorg/apache/hadoop/hbase/HBaseTestingUtility;Ljava/lang/String;Lorg/apache/hadoop/hbase/TableName;[B[B[Lorg/apache/hadoop/hbase/security/access/Permission$Action;)V
     128: return

  public static void tearDownAfterClass() throws java.lang.Exception;
    Code:
       0: getstatic     #5                  // Field TEST_UTIL:Lorg/apache/hadoop/hbase/HBaseTestingUtility;
       3: invokevirtual #68                 // Method org/apache/hadoop/hbase/HBaseTestingUtility.shutdownMiniCluster:()V
       6: return

  protected abstract void snapshot(java.lang.String, org.apache.hadoop.hbase.TableName) throws java.lang.Exception;

  protected abstract void cloneSnapshot(java.lang.String, org.apache.hadoop.hbase.TableName, boolean) throws java.lang.Exception;

  protected abstract void restoreSnapshot(java.lang.String, boolean) throws java.lang.Exception;

  public void testRestoreSnapshot() throws java.lang.Exception;
    Code:
       0: new           #79                 // class org/apache/hadoop/hbase/client/SnapshotWithAclTestBase$AccessReadAction
       3: dup
       4: aload_0
       5: getfield      #9                  // Field TEST_TABLE:Lorg/apache/hadoop/hbase/TableName;
       8: invokespecial #80                 // Method org/apache/hadoop/hbase/client/SnapshotWithAclTestBase$AccessReadAction."<init>":(Lorg/apache/hadoop/hbase/TableName;)V
      11: iconst_3
      12: anewarray     #81                 // class org/apache/hadoop/hbase/security/User
      15: dup
      16: iconst_0
      17: getstatic     #32                 // Field USER_OWNER:Lorg/apache/hadoop/hbase/security/User;
      20: aastore
      21: dup
      22: iconst_1
      23: getstatic     #36                 // Field USER_RO:Lorg/apache/hadoop/hbase/security/User;
      26: aastore
      27: dup
      28: iconst_2
      29: getstatic     #34                 // Field USER_RW:Lorg/apache/hadoop/hbase/security/User;
      32: aastore
      33: invokestatic  #82                 // Method verifyAllowed:(Lorg/apache/hadoop/hbase/security/access/SecureTestUtil$AccessTestAction;[Lorg/apache/hadoop/hbase/security/User;)V
      36: new           #79                 // class org/apache/hadoop/hbase/client/SnapshotWithAclTestBase$AccessReadAction
      39: dup
      40: aload_0
      41: getfield      #9                  // Field TEST_TABLE:Lorg/apache/hadoop/hbase/TableName;
      44: invokespecial #80                 // Method org/apache/hadoop/hbase/client/SnapshotWithAclTestBase$AccessReadAction."<init>":(Lorg/apache/hadoop/hbase/TableName;)V
      47: iconst_1
      48: anewarray     #81                 // class org/apache/hadoop/hbase/security/User
      51: dup
      52: iconst_0
      53: getstatic     #38                 // Field USER_NONE:Lorg/apache/hadoop/hbase/security/User;
      56: aastore
      57: invokestatic  #83                 // Method verifyDenied:(Lorg/apache/hadoop/hbase/security/access/SecureTestUtil$AccessTestAction;[Lorg/apache/hadoop/hbase/security/User;)V
      60: new           #84                 // class org/apache/hadoop/hbase/client/SnapshotWithAclTestBase$AccessWriteAction
      63: dup
      64: aload_0
      65: getfield      #9                  // Field TEST_TABLE:Lorg/apache/hadoop/hbase/TableName;
      68: invokespecial #85                 // Method org/apache/hadoop/hbase/client/SnapshotWithAclTestBase$AccessWriteAction."<init>":(Lorg/apache/hadoop/hbase/TableName;)V
      71: iconst_2
      72: anewarray     #81                 // class org/apache/hadoop/hbase/security/User
      75: dup
      76: iconst_0
      77: getstatic     #32                 // Field USER_OWNER:Lorg/apache/hadoop/hbase/security/User;
      80: aastore
      81: dup
      82: iconst_1
      83: getstatic     #34                 // Field USER_RW:Lorg/apache/hadoop/hbase/security/User;
      86: aastore
      87: invokestatic  #82                 // Method verifyAllowed:(Lorg/apache/hadoop/hbase/security/access/SecureTestUtil$AccessTestAction;[Lorg/apache/hadoop/hbase/security/User;)V
      90: new           #84                 // class org/apache/hadoop/hbase/client/SnapshotWithAclTestBase$AccessWriteAction
      93: dup
      94: aload_0
      95: getfield      #9                  // Field TEST_TABLE:Lorg/apache/hadoop/hbase/TableName;
      98: invokespecial #85                 // Method org/apache/hadoop/hbase/client/SnapshotWithAclTestBase$AccessWriteAction."<init>":(Lorg/apache/hadoop/hbase/TableName;)V
     101: iconst_2
     102: anewarray     #81                 // class org/apache/hadoop/hbase/security/User
     105: dup
     106: iconst_0
     107: getstatic     #36                 // Field USER_RO:Lorg/apache/hadoop/hbase/security/User;
     110: aastore
     111: dup
     112: iconst_1
     113: getstatic     #38                 // Field USER_NONE:Lorg/apache/hadoop/hbase/security/User;
     116: aastore
     117: invokestatic  #83                 // Method verifyDenied:(Lorg/apache/hadoop/hbase/security/access/SecureTestUtil$AccessTestAction;[Lorg/apache/hadoop/hbase/security/User;)V
     120: aload_0
     121: invokespecial #86                 // Method loadData:()V
     124: aload_0
     125: aload_0
     126: getfield      #9                  // Field TEST_TABLE:Lorg/apache/hadoop/hbase/TableName;
     129: invokespecial #87                 // Method verifyRows:(Lorg/apache/hadoop/hbase/TableName;)V
     132: getstatic     #5                  // Field TEST_UTIL:Lorg/apache/hadoop/hbase/HBaseTestingUtility;
     135: invokevirtual #6                  // Method org/apache/hadoop/hbase/HBaseTestingUtility.getRandomUUID:()Ljava/util/UUID;
     138: invokevirtual #7                  // Method java/util/UUID.toString:()Ljava/lang/String;
     141: astore_1
     142: aload_0
     143: aload_1
     144: aload_0
     145: getfield      #9                  // Field TEST_TABLE:Lorg/apache/hadoop/hbase/TableName;
     148: invokevirtual #88                 // Method snapshot:(Ljava/lang/String;Lorg/apache/hadoop/hbase/TableName;)V
     151: getstatic     #5                  // Field TEST_UTIL:Lorg/apache/hadoop/hbase/HBaseTestingUtility;
     154: invokevirtual #6                  // Method org/apache/hadoop/hbase/HBaseTestingUtility.getRandomUUID:()Ljava/util/UUID;
     157: invokevirtual #7                  // Method java/util/UUID.toString:()Ljava/lang/String;
     160: invokestatic  #8                  // Method org/apache/hadoop/hbase/TableName.valueOf:(Ljava/lang/String;)Lorg/apache/hadoop/hbase/TableName;
     163: astore_2
     164: aload_0
     165: aload_1
     166: aload_2
     167: iconst_1
     168: invokevirtual #89                 // Method cloneSnapshot:(Ljava/lang/String;Lorg/apache/hadoop/hbase/TableName;Z)V
     171: aload_0
     172: aload_2
     173: invokespecial #87                 // Method verifyRows:(Lorg/apache/hadoop/hbase/TableName;)V
     176: new           #79                 // class org/apache/hadoop/hbase/client/SnapshotWithAclTestBase$AccessReadAction
     179: dup
     180: aload_2
     181: invokespecial #80                 // Method org/apache/hadoop/hbase/client/SnapshotWithAclTestBase$AccessReadAction."<init>":(Lorg/apache/hadoop/hbase/TableName;)V
     184: iconst_3
     185: anewarray     #81                 // class org/apache/hadoop/hbase/security/User
     188: dup
     189: iconst_0
     190: getstatic     #32                 // Field USER_OWNER:Lorg/apache/hadoop/hbase/security/User;
     193: aastore
     194: dup
     195: iconst_1
     196: getstatic     #36                 // Field USER_RO:Lorg/apache/hadoop/hbase/security/User;
     199: aastore
     200: dup
     201: iconst_2
     202: getstatic     #34                 // Field USER_RW:Lorg/apache/hadoop/hbase/security/User;
     205: aastore
     206: invokestatic  #82                 // Method verifyAllowed:(Lorg/apache/hadoop/hbase/security/access/SecureTestUtil$AccessTestAction;[Lorg/apache/hadoop/hbase/security/User;)V
     209: new           #79                 // class org/apache/hadoop/hbase/client/SnapshotWithAclTestBase$AccessReadAction
     212: dup
     213: aload_2
     214: invokespecial #80                 // Method org/apache/hadoop/hbase/client/SnapshotWithAclTestBase$AccessReadAction."<init>":(Lorg/apache/hadoop/hbase/TableName;)V
     217: iconst_1
     218: anewarray     #81                 // class org/apache/hadoop/hbase/security/User
     221: dup
     222: iconst_0
     223: getstatic     #38                 // Field USER_NONE:Lorg/apache/hadoop/hbase/security/User;
     226: aastore
     227: invokestatic  #83                 // Method verifyDenied:(Lorg/apache/hadoop/hbase/security/access/SecureTestUtil$AccessTestAction;[Lorg/apache/hadoop/hbase/security/User;)V
     230: new           #84                 // class org/apache/hadoop/hbase/client/SnapshotWithAclTestBase$AccessWriteAction
     233: dup
     234: aload_2
     235: invokespecial #85                 // Method org/apache/hadoop/hbase/client/SnapshotWithAclTestBase$AccessWriteAction."<init>":(Lorg/apache/hadoop/hbase/TableName;)V
     238: iconst_2
     239: anewarray     #81                 // class org/apache/hadoop/hbase/security/User
     242: dup
     243: iconst_0
     244: getstatic     #32                 // Field USER_OWNER:Lorg/apache/hadoop/hbase/security/User;
     247: aastore
     248: dup
     249: iconst_1
     250: getstatic     #34                 // Field USER_RW:Lorg/apache/hadoop/hbase/security/User;
     253: aastore
     254: invokestatic  #82                 // Method verifyAllowed:(Lorg/apache/hadoop/hbase/security/access/SecureTestUtil$AccessTestAction;[Lorg/apache/hadoop/hbase/security/User;)V
     257: new           #84                 // class org/apache/hadoop/hbase/client/SnapshotWithAclTestBase$AccessWriteAction
     260: dup
     261: aload_2
     262: invokespecial #85                 // Method org/apache/hadoop/hbase/client/SnapshotWithAclTestBase$AccessWriteAction."<init>":(Lorg/apache/hadoop/hbase/TableName;)V
     265: iconst_2
     266: anewarray     #81                 // class org/apache/hadoop/hbase/security/User
     269: dup
     270: iconst_0
     271: getstatic     #36                 // Field USER_RO:Lorg/apache/hadoop/hbase/security/User;
     274: aastore
     275: dup
     276: iconst_1
     277: getstatic     #38                 // Field USER_NONE:Lorg/apache/hadoop/hbase/security/User;
     280: aastore
     281: invokestatic  #83                 // Method verifyDenied:(Lorg/apache/hadoop/hbase/security/access/SecureTestUtil$AccessTestAction;[Lorg/apache/hadoop/hbase/security/User;)V
     284: getstatic     #5                  // Field TEST_UTIL:Lorg/apache/hadoop/hbase/HBaseTestingUtility;
     287: invokevirtual #6                  // Method org/apache/hadoop/hbase/HBaseTestingUtility.getRandomUUID:()Ljava/util/UUID;
     290: invokevirtual #7                  // Method java/util/UUID.toString:()Ljava/lang/String;
     293: invokestatic  #8                  // Method org/apache/hadoop/hbase/TableName.valueOf:(Ljava/lang/String;)Lorg/apache/hadoop/hbase/TableName;
     296: astore_3
     297: aload_0
     298: aload_1
     299: aload_3
     300: iconst_0
     301: invokevirtual #89                 // Method cloneSnapshot:(Ljava/lang/String;Lorg/apache/hadoop/hbase/TableName;Z)V
     304: aload_0
     305: aload_3
     306: invokespecial #87                 // Method verifyRows:(Lorg/apache/hadoop/hbase/TableName;)V
     309: new           #79                 // class org/apache/hadoop/hbase/client/SnapshotWithAclTestBase$AccessReadAction
     312: dup
     313: aload_3
     314: invokespecial #80                 // Method org/apache/hadoop/hbase/client/SnapshotWithAclTestBase$AccessReadAction."<init>":(Lorg/apache/hadoop/hbase/TableName;)V
     317: iconst_1
     318: anewarray     #81                 // class org/apache/hadoop/hbase/security/User
     321: dup
     322: iconst_0
     323: getstatic     #32                 // Field USER_OWNER:Lorg/apache/hadoop/hbase/security/User;
     326: aastore
     327: invokestatic  #82                 // Method verifyAllowed:(Lorg/apache/hadoop/hbase/security/access/SecureTestUtil$AccessTestAction;[Lorg/apache/hadoop/hbase/security/User;)V
     330: new           #79                 // class org/apache/hadoop/hbase/client/SnapshotWithAclTestBase$AccessReadAction
     333: dup
     334: aload_3
     335: invokespecial #80                 // Method org/apache/hadoop/hbase/client/SnapshotWithAclTestBase$AccessReadAction."<init>":(Lorg/apache/hadoop/hbase/TableName;)V
     338: iconst_3
     339: anewarray     #81                 // class org/apache/hadoop/hbase/security/User
     342: dup
     343: iconst_0
     344: getstatic     #38                 // Field USER_NONE:Lorg/apache/hadoop/hbase/security/User;
     347: aastore
     348: dup
     349: iconst_1
     350: getstatic     #36                 // Field USER_RO:Lorg/apache/hadoop/hbase/security/User;
     353: aastore
     354: dup
     355: iconst_2
     356: getstatic     #34                 // Field USER_RW:Lorg/apache/hadoop/hbase/security/User;
     359: aastore
     360: invokestatic  #83                 // Method verifyDenied:(Lorg/apache/hadoop/hbase/security/access/SecureTestUtil$AccessTestAction;[Lorg/apache/hadoop/hbase/security/User;)V
     363: new           #84                 // class org/apache/hadoop/hbase/client/SnapshotWithAclTestBase$AccessWriteAction
     366: dup
     367: aload_3
     368: invokespecial #85                 // Method org/apache/hadoop/hbase/client/SnapshotWithAclTestBase$AccessWriteAction."<init>":(Lorg/apache/hadoop/hbase/TableName;)V
     371: iconst_1
     372: anewarray     #81                 // class org/apache/hadoop/hbase/security/User
     375: dup
     376: iconst_0
     377: getstatic     #32                 // Field USER_OWNER:Lorg/apache/hadoop/hbase/security/User;
     380: aastore
     381: invokestatic  #82                 // Method verifyAllowed:(Lorg/apache/hadoop/hbase/security/access/SecureTestUtil$AccessTestAction;[Lorg/apache/hadoop/hbase/security/User;)V
     384: new           #84                 // class org/apache/hadoop/hbase/client/SnapshotWithAclTestBase$AccessWriteAction
     387: dup
     388: aload_3
     389: invokespecial #85                 // Method org/apache/hadoop/hbase/client/SnapshotWithAclTestBase$AccessWriteAction."<init>":(Lorg/apache/hadoop/hbase/TableName;)V
     392: iconst_3
     393: anewarray     #81                 // class org/apache/hadoop/hbase/security/User
     396: dup
     397: iconst_0
     398: getstatic     #36                 // Field USER_RO:Lorg/apache/hadoop/hbase/security/User;
     401: aastore
     402: dup
     403: iconst_1
     404: getstatic     #34                 // Field USER_RW:Lorg/apache/hadoop/hbase/security/User;
     407: aastore
     408: dup
     409: iconst_2
     410: getstatic     #38                 // Field USER_NONE:Lorg/apache/hadoop/hbase/security/User;
     413: aastore
     414: invokestatic  #83                 // Method verifyDenied:(Lorg/apache/hadoop/hbase/security/access/SecureTestUtil$AccessTestAction;[Lorg/apache/hadoop/hbase/security/User;)V
     417: getstatic     #5                  // Field TEST_UTIL:Lorg/apache/hadoop/hbase/HBaseTestingUtility;
     420: getstatic     #36                 // Field USER_RO:Lorg/apache/hadoop/hbase/security/User;
     423: invokevirtual #51                 // Method org/apache/hadoop/hbase/security/User.getShortName:()Ljava/lang/String;
     426: aload_0
     427: getfield      #9                  // Field TEST_TABLE:Lorg/apache/hadoop/hbase/TableName;
     430: getstatic     #2                  // Field TEST_FAMILY:[B
     433: aconst_null
     434: iconst_1
     435: anewarray     #52                 // class org/apache/hadoop/hbase/security/access/Permission$Action
     438: dup
     439: iconst_0
     440: getstatic     #53                 // Field org/apache/hadoop/hbase/security/access/Permission$Action.READ:Lorg/apache/hadoop/hbase/security/access/Permission$Action;
     443: aastore
     444: invokestatic  #90                 // Method revokeFromTable:(Lorg/apache/hadoop/hbase/HBaseTestingUtility;Ljava/lang/String;Lorg/apache/hadoop/hbase/TableName;[B[B[Lorg/apache/hadoop/hbase/security/access/Permission$Action;)V
     447: new           #79                 // class org/apache/hadoop/hbase/client/SnapshotWithAclTestBase$AccessReadAction
     450: dup
     451: aload_0
     452: getfield      #9                  // Field TEST_TABLE:Lorg/apache/hadoop/hbase/TableName;
     455: invokespecial #80                 // Method org/apache/hadoop/hbase/client/SnapshotWithAclTestBase$AccessReadAction."<init>":(Lorg/apache/hadoop/hbase/TableName;)V
     458: iconst_2
     459: anewarray     #81                 // class org/apache/hadoop/hbase/security/User
     462: dup
     463: iconst_0
     464: getstatic     #32                 // Field USER_OWNER:Lorg/apache/hadoop/hbase/security/User;
     467: aastore
     468: dup
     469: iconst_1
     470: getstatic     #34                 // Field USER_RW:Lorg/apache/hadoop/hbase/security/User;
     473: aastore
     474: invokestatic  #82                 // Method verifyAllowed:(Lorg/apache/hadoop/hbase/security/access/SecureTestUtil$AccessTestAction;[Lorg/apache/hadoop/hbase/security/User;)V
     477: new           #79                 // class org/apache/hadoop/hbase/client/SnapshotWithAclTestBase$AccessReadAction
     480: dup
     481: aload_0
     482: getfield      #9                  // Field TEST_TABLE:Lorg/apache/hadoop/hbase/TableName;
     485: invokespecial #80                 // Method org/apache/hadoop/hbase/client/SnapshotWithAclTestBase$AccessReadAction."<init>":(Lorg/apache/hadoop/hbase/TableName;)V
     488: iconst_2
     489: anewarray     #81                 // class org/apache/hadoop/hbase/security/User
     492: dup
     493: iconst_0
     494: getstatic     #36                 // Field USER_RO:Lorg/apache/hadoop/hbase/security/User;
     497: aastore
     498: dup
     499: iconst_1
     500: getstatic     #38                 // Field USER_NONE:Lorg/apache/hadoop/hbase/security/User;
     503: aastore
     504: invokestatic  #83                 // Method verifyDenied:(Lorg/apache/hadoop/hbase/security/access/SecureTestUtil$AccessTestAction;[Lorg/apache/hadoop/hbase/security/User;)V
     507: new           #84                 // class org/apache/hadoop/hbase/client/SnapshotWithAclTestBase$AccessWriteAction
     510: dup
     511: aload_0
     512: getfield      #9                  // Field TEST_TABLE:Lorg/apache/hadoop/hbase/TableName;
     515: invokespecial #85                 // Method org/apache/hadoop/hbase/client/SnapshotWithAclTestBase$AccessWriteAction."<init>":(Lorg/apache/hadoop/hbase/TableName;)V
     518: iconst_2
     519: anewarray     #81                 // class org/apache/hadoop/hbase/security/User
     522: dup
     523: iconst_0
     524: getstatic     #32                 // Field USER_OWNER:Lorg/apache/hadoop/hbase/security/User;
     527: aastore
     528: dup
     529: iconst_1
     530: getstatic     #34                 // Field USER_RW:Lorg/apache/hadoop/hbase/security/User;
     533: aastore
     534: invokestatic  #82                 // Method verifyAllowed:(Lorg/apache/hadoop/hbase/security/access/SecureTestUtil$AccessTestAction;[Lorg/apache/hadoop/hbase/security/User;)V
     537: new           #84                 // class org/apache/hadoop/hbase/client/SnapshotWithAclTestBase$AccessWriteAction
     540: dup
     541: aload_0
     542: getfield      #9                  // Field TEST_TABLE:Lorg/apache/hadoop/hbase/TableName;
     545: invokespecial #85                 // Method org/apache/hadoop/hbase/client/SnapshotWithAclTestBase$AccessWriteAction."<init>":(Lorg/apache/hadoop/hbase/TableName;)V
     548: iconst_2
     549: anewarray     #81                 // class org/apache/hadoop/hbase/security/User
     552: dup
     553: iconst_0
     554: getstatic     #36                 // Field USER_RO:Lorg/apache/hadoop/hbase/security/User;
     557: aastore
     558: dup
     559: iconst_1
     560: getstatic     #38                 // Field USER_NONE:Lorg/apache/hadoop/hbase/security/User;
     563: aastore
     564: invokestatic  #83                 // Method verifyDenied:(Lorg/apache/hadoop/hbase/security/access/SecureTestUtil$AccessTestAction;[Lorg/apache/hadoop/hbase/security/User;)V
     567: getstatic     #5                  // Field TEST_UTIL:Lorg/apache/hadoop/hbase/HBaseTestingUtility;
     570: invokevirtual #91                 // Method org/apache/hadoop/hbase/HBaseTestingUtility.getAdmin:()Lorg/apache/hadoop/hbase/client/Admin;
     573: aload_0
     574: getfield      #9                  // Field TEST_TABLE:Lorg/apache/hadoop/hbase/TableName;
     577: invokeinterface #92,  2           // InterfaceMethod org/apache/hadoop/hbase/client/Admin.disableTable:(Lorg/apache/hadoop/hbase/TableName;)V
     582: aload_0
     583: aload_1
     584: iconst_0
     585: invokevirtual #93                 // Method restoreSnapshot:(Ljava/lang/String;Z)V
     588: getstatic     #5                  // Field TEST_UTIL:Lorg/apache/hadoop/hbase/HBaseTestingUtility;
     591: invokevirtual #91                 // Method org/apache/hadoop/hbase/HBaseTestingUtility.getAdmin:()Lorg/apache/hadoop/hbase/client/Admin;
     594: aload_0
     595: getfield      #9                  // Field TEST_TABLE:Lorg/apache/hadoop/hbase/TableName;
     598: invokeinterface #94,  2           // InterfaceMethod org/apache/hadoop/hbase/client/Admin.enableTable:(Lorg/apache/hadoop/hbase/TableName;)V
     603: new           #79                 // class org/apache/hadoop/hbase/client/SnapshotWithAclTestBase$AccessReadAction
     606: dup
     607: aload_0
     608: getfield      #9                  // Field TEST_TABLE:Lorg/apache/hadoop/hbase/TableName;
     611: invokespecial #80                 // Method org/apache/hadoop/hbase/client/SnapshotWithAclTestBase$AccessReadAction."<init>":(Lorg/apache/hadoop/hbase/TableName;)V
     614: iconst_2
     615: anewarray     #81                 // class org/apache/hadoop/hbase/security/User
     618: dup
     619: iconst_0
     620: getstatic     #32                 // Field USER_OWNER:Lorg/apache/hadoop/hbase/security/User;
     623: aastore
     624: dup
     625: iconst_1
     626: getstatic     #34                 // Field USER_RW:Lorg/apache/hadoop/hbase/security/User;
     629: aastore
     630: invokestatic  #82                 // Method verifyAllowed:(Lorg/apache/hadoop/hbase/security/access/SecureTestUtil$AccessTestAction;[Lorg/apache/hadoop/hbase/security/User;)V
     633: new           #79                 // class org/apache/hadoop/hbase/client/SnapshotWithAclTestBase$AccessReadAction
     636: dup
     637: aload_0
     638: getfield      #9                  // Field TEST_TABLE:Lorg/apache/hadoop/hbase/TableName;
     641: invokespecial #80                 // Method org/apache/hadoop/hbase/client/SnapshotWithAclTestBase$AccessReadAction."<init>":(Lorg/apache/hadoop/hbase/TableName;)V
     644: iconst_2
     645: anewarray     #81                 // class org/apache/hadoop/hbase/security/User
     648: dup
     649: iconst_0
     650: getstatic     #36                 // Field USER_RO:Lorg/apache/hadoop/hbase/security/User;
     653: aastore
     654: dup
     655: iconst_1
     656: getstatic     #38                 // Field USER_NONE:Lorg/apache/hadoop/hbase/security/User;
     659: aastore
     660: invokestatic  #83                 // Method verifyDenied:(Lorg/apache/hadoop/hbase/security/access/SecureTestUtil$AccessTestAction;[Lorg/apache/hadoop/hbase/security/User;)V
     663: new           #84                 // class org/apache/hadoop/hbase/client/SnapshotWithAclTestBase$AccessWriteAction
     666: dup
     667: aload_0
     668: getfield      #9                  // Field TEST_TABLE:Lorg/apache/hadoop/hbase/TableName;
     671: invokespecial #85                 // Method org/apache/hadoop/hbase/client/SnapshotWithAclTestBase$AccessWriteAction."<init>":(Lorg/apache/hadoop/hbase/TableName;)V
     674: iconst_2
     675: anewarray     #81                 // class org/apache/hadoop/hbase/security/User
     678: dup
     679: iconst_0
     680: getstatic     #32                 // Field USER_OWNER:Lorg/apache/hadoop/hbase/security/User;
     683: aastore
     684: dup
     685: iconst_1
     686: getstatic     #34                 // Field USER_RW:Lorg/apache/hadoop/hbase/security/User;
     689: aastore
     690: invokestatic  #82                 // Method verifyAllowed:(Lorg/apache/hadoop/hbase/security/access/SecureTestUtil$AccessTestAction;[Lorg/apache/hadoop/hbase/security/User;)V
     693: new           #84                 // class org/apache/hadoop/hbase/client/SnapshotWithAclTestBase$AccessWriteAction
     696: dup
     697: aload_0
     698: getfield      #9                  // Field TEST_TABLE:Lorg/apache/hadoop/hbase/TableName;
     701: invokespecial #85                 // Method org/apache/hadoop/hbase/client/SnapshotWithAclTestBase$AccessWriteAction."<init>":(Lorg/apache/hadoop/hbase/TableName;)V
     704: iconst_2
     705: anewarray     #81                 // class org/apache/hadoop/hbase/security/User
     708: dup
     709: iconst_0
     710: getstatic     #36                 // Field USER_RO:Lorg/apache/hadoop/hbase/security/User;
     713: aastore
     714: dup
     715: iconst_1
     716: getstatic     #38                 // Field USER_NONE:Lorg/apache/hadoop/hbase/security/User;
     719: aastore
     720: invokestatic  #83                 // Method verifyDenied:(Lorg/apache/hadoop/hbase/security/access/SecureTestUtil$AccessTestAction;[Lorg/apache/hadoop/hbase/security/User;)V
     723: getstatic     #5                  // Field TEST_UTIL:Lorg/apache/hadoop/hbase/HBaseTestingUtility;
     726: invokevirtual #91                 // Method org/apache/hadoop/hbase/HBaseTestingUtility.getAdmin:()Lorg/apache/hadoop/hbase/client/Admin;
     729: aload_0
     730: getfield      #9                  // Field TEST_TABLE:Lorg/apache/hadoop/hbase/TableName;
     733: invokeinterface #92,  2           // InterfaceMethod org/apache/hadoop/hbase/client/Admin.disableTable:(Lorg/apache/hadoop/hbase/TableName;)V
     738: aload_0
     739: aload_1
     740: iconst_1
     741: invokevirtual #93                 // Method restoreSnapshot:(Ljava/lang/String;Z)V
     744: getstatic     #5                  // Field TEST_UTIL:Lorg/apache/hadoop/hbase/HBaseTestingUtility;
     747: invokevirtual #91                 // Method org/apache/hadoop/hbase/HBaseTestingUtility.getAdmin:()Lorg/apache/hadoop/hbase/client/Admin;
     750: aload_0
     751: getfield      #9                  // Field TEST_TABLE:Lorg/apache/hadoop/hbase/TableName;
     754: invokeinterface #94,  2           // InterfaceMethod org/apache/hadoop/hbase/client/Admin.enableTable:(Lorg/apache/hadoop/hbase/TableName;)V
     759: new           #79                 // class org/apache/hadoop/hbase/client/SnapshotWithAclTestBase$AccessReadAction
     762: dup
     763: aload_0
     764: getfield      #9                  // Field TEST_TABLE:Lorg/apache/hadoop/hbase/TableName;
     767: invokespecial #80                 // Method org/apache/hadoop/hbase/client/SnapshotWithAclTestBase$AccessReadAction."<init>":(Lorg/apache/hadoop/hbase/TableName;)V
     770: iconst_3
     771: anewarray     #81                 // class org/apache/hadoop/hbase/security/User
     774: dup
     775: iconst_0
     776: getstatic     #32                 // Field USER_OWNER:Lorg/apache/hadoop/hbase/security/User;
     779: aastore
     780: dup
     781: iconst_1
     782: getstatic     #36                 // Field USER_RO:Lorg/apache/hadoop/hbase/security/User;
     785: aastore
     786: dup
     787: iconst_2
     788: getstatic     #34                 // Field USER_RW:Lorg/apache/hadoop/hbase/security/User;
     791: aastore
     792: invokestatic  #82                 // Method verifyAllowed:(Lorg/apache/hadoop/hbase/security/access/SecureTestUtil$AccessTestAction;[Lorg/apache/hadoop/hbase/security/User;)V
     795: new           #79                 // class org/apache/hadoop/hbase/client/SnapshotWithAclTestBase$AccessReadAction
     798: dup
     799: aload_0
     800: getfield      #9                  // Field TEST_TABLE:Lorg/apache/hadoop/hbase/TableName;
     803: invokespecial #80                 // Method org/apache/hadoop/hbase/client/SnapshotWithAclTestBase$AccessReadAction."<init>":(Lorg/apache/hadoop/hbase/TableName;)V
     806: iconst_1
     807: anewarray     #81                 // class org/apache/hadoop/hbase/security/User
     810: dup
     811: iconst_0
     812: getstatic     #38                 // Field USER_NONE:Lorg/apache/hadoop/hbase/security/User;
     815: aastore
     816: invokestatic  #83                 // Method verifyDenied:(Lorg/apache/hadoop/hbase/security/access/SecureTestUtil$AccessTestAction;[Lorg/apache/hadoop/hbase/security/User;)V
     819: new           #84                 // class org/apache/hadoop/hbase/client/SnapshotWithAclTestBase$AccessWriteAction
     822: dup
     823: aload_0
     824: getfield      #9                  // Field TEST_TABLE:Lorg/apache/hadoop/hbase/TableName;
     827: invokespecial #85                 // Method org/apache/hadoop/hbase/client/SnapshotWithAclTestBase$AccessWriteAction."<init>":(Lorg/apache/hadoop/hbase/TableName;)V
     830: iconst_2
     831: anewarray     #81                 // class org/apache/hadoop/hbase/security/User
     834: dup
     835: iconst_0
     836: getstatic     #32                 // Field USER_OWNER:Lorg/apache/hadoop/hbase/security/User;
     839: aastore
     840: dup
     841: iconst_1
     842: getstatic     #34                 // Field USER_RW:Lorg/apache/hadoop/hbase/security/User;
     845: aastore
     846: invokestatic  #82                 // Method verifyAllowed:(Lorg/apache/hadoop/hbase/security/access/SecureTestUtil$AccessTestAction;[Lorg/apache/hadoop/hbase/security/User;)V
     849: new           #84                 // class org/apache/hadoop/hbase/client/SnapshotWithAclTestBase$AccessWriteAction
     852: dup
     853: aload_0
     854: getfield      #9                  // Field TEST_TABLE:Lorg/apache/hadoop/hbase/TableName;
     857: invokespecial #85                 // Method org/apache/hadoop/hbase/client/SnapshotWithAclTestBase$AccessWriteAction."<init>":(Lorg/apache/hadoop/hbase/TableName;)V
     860: iconst_2
     861: anewarray     #81                 // class org/apache/hadoop/hbase/security/User
     864: dup
     865: iconst_0
     866: getstatic     #36                 // Field USER_RO:Lorg/apache/hadoop/hbase/security/User;
     869: aastore
     870: dup
     871: iconst_1
     872: getstatic     #38                 // Field USER_NONE:Lorg/apache/hadoop/hbase/security/User;
     875: aastore
     876: invokestatic  #83                 // Method verifyDenied:(Lorg/apache/hadoop/hbase/security/access/SecureTestUtil$AccessTestAction;[Lorg/apache/hadoop/hbase/security/User;)V
     879: return

  static byte[] access$000();
    Code:
       0: getstatic     #3                  // Field TEST_ROW:[B
       3: areturn

  static byte[] access$100();
    Code:
       0: getstatic     #2                  // Field TEST_FAMILY:[B
       3: areturn

  static byte[] access$200();
    Code:
       0: getstatic     #1                  // Field TEST_QUALIFIER:[B
       3: areturn

  static {};
    Code:
       0: ldc           #95                 // String f1
       2: invokestatic  #48                 // Method org/apache/hadoop/hbase/util/Bytes.toBytes:(Ljava/lang/String;)[B
       5: putstatic     #2                  // Field TEST_FAMILY:[B
       8: ldc           #96                 // String cq
      10: invokestatic  #48                 // Method org/apache/hadoop/hbase/util/Bytes.toBytes:(Ljava/lang/String;)[B
      13: putstatic     #1                  // Field TEST_QUALIFIER:[B
      16: iconst_0
      17: invokestatic  #60                 // Method org/apache/hadoop/hbase/util/Bytes.toBytes:(I)[B
      20: putstatic     #3                  // Field TEST_ROW:[B
      23: new           #97                 // class org/apache/hadoop/hbase/HBaseTestingUtility
      26: dup
      27: invokespecial #98                 // Method org/apache/hadoop/hbase/HBaseTestingUtility."<init>":()V
      30: putstatic     #5                  // Field TEST_UTIL:Lorg/apache/hadoop/hbase/HBaseTestingUtility;
      33: return
}
