Compiled from "SnapshotManifestV2.java"
final class org.apache.hadoop.hbase.snapshot.SnapshotManifestV2$1 implements org.apache.hadoop.fs.PathFilter {
  org.apache.hadoop.hbase.snapshot.SnapshotManifestV2$1();
    Code:
       0: aload_0
       1: invokespecial #2                  // Method java/lang/Object."<init>":()V
       4: return

  public boolean accept(org.apache.hadoop.fs.Path);
    Code:
       0: aload_1
       1: invokevirtual #3                  // Method org/apache/hadoop/fs/Path.getName:()Ljava/lang/String;
       4: ldc           #4                  // String region-manifest.
       6: invokevirtual #5                  // Method java/lang/String.startsWith:(Ljava/lang/String;)Z
       9: ireturn
}
