Compiled from "SnapshotHFileCleaner.java"
public class org.apache.hadoop.hbase.master.snapshot.SnapshotHFileCleaner extends org.apache.hadoop.hbase.master.cleaner.BaseHFileCleanerDelegate {
  public static final java.lang.String HFILE_CACHE_REFRESH_PERIOD_CONF_KEY;

  public org.apache.hadoop.hbase.master.snapshot.SnapshotHFileCleaner();
    Code:
       0: aload_0
       1: invokespecial #1                  // Method org/apache/hadoop/hbase/master/cleaner/BaseHFileCleanerDelegate."<init>":()V
       4: return

  public synchronized java.lang.Iterable<org.apache.hadoop.fs.FileStatus> getDeletableFiles(java.lang.Iterable<org.apache.hadoop.fs.FileStatus>);
    Code:
       0: aload_0
       1: getfield      #2                  // Field cache:Lorg/apache/hadoop/hbase/master/snapshot/SnapshotFileCache;
       4: aload_1
       5: aload_0
       6: getfield      #3                  // Field master:Lorg/apache/hadoop/hbase/master/MasterServices;
       9: invokeinterface #4,  1            // InterfaceMethod org/apache/hadoop/hbase/master/MasterServices.getSnapshotManager:()Lorg/apache/hadoop/hbase/master/snapshot/SnapshotManager;
      14: invokevirtual #5                  // Method org/apache/hadoop/hbase/master/snapshot/SnapshotFileCache.getUnreferencedFiles:(Ljava/lang/Iterable;Lorg/apache/hadoop/hbase/master/snapshot/SnapshotManager;)Ljava/lang/Iterable;
      17: areturn
      18: astore_2
      19: getstatic     #7                  // Field LOG:Lorg/slf4j/Logger;
      22: ldc           #8                  // String Corrupted in-progress snapshot file exception, ignored
      24: aload_2
      25: invokeinterface #9,  3            // InterfaceMethod org/slf4j/Logger.debug:(Ljava/lang/String;Ljava/lang/Throwable;)V
      30: goto          45
      33: astore_2
      34: getstatic     #7                  // Field LOG:Lorg/slf4j/Logger;
      37: ldc           #11                 // String Exception while checking if files were valid, keeping them just in case.
      39: aload_2
      40: invokeinterface #12,  3           // InterfaceMethod org/slf4j/Logger.error:(Ljava/lang/String;Ljava/lang/Throwable;)V
      45: invokestatic  #13                 // Method java/util/Collections.emptyList:()Ljava/util/List;
      48: areturn
    Exception table:
       from    to  target type
           0    17    18   Class org/apache/hadoop/hbase/snapshot/CorruptedSnapshotException
           0    17    33   Class java/io/IOException

  public void init(java.util.Map<java.lang.String, java.lang.Object>);
    Code:
       0: aload_1
       1: ifnull        30
       4: aload_1
       5: ldc           #15                 // String master
       7: invokeinterface #16,  2           // InterfaceMethod java/util/Map.containsKey:(Ljava/lang/Object;)Z
      12: ifeq          30
      15: aload_0
      16: aload_1
      17: ldc           #15                 // String master
      19: invokeinterface #17,  2           // InterfaceMethod java/util/Map.get:(Ljava/lang/Object;)Ljava/lang/Object;
      24: checkcast     #18                 // class org/apache/hadoop/hbase/master/MasterServices
      27: putfield      #3                  // Field master:Lorg/apache/hadoop/hbase/master/MasterServices;
      30: return

  protected boolean isFileDeletable(org.apache.hadoop.fs.FileStatus);
    Code:
       0: iconst_0
       1: ireturn

  public void setConf(org.apache.hadoop.conf.Configuration);
    Code:
       0: aload_0
       1: aload_1
       2: invokespecial #19                 // Method org/apache/hadoop/hbase/master/cleaner/BaseHFileCleanerDelegate.setConf:(Lorg/apache/hadoop/conf/Configuration;)V
       5: aload_1
       6: ldc           #21                 // String hbase.master.hfilecleaner.plugins.snapshot.period
       8: ldc2_w        #22                 // long 300000l
      11: invokevirtual #24                 // Method org/apache/hadoop/conf/Configuration.getLong:(Ljava/lang/String;J)J
      14: lstore_2
      15: aload_1
      16: invokestatic  #25                 // Method org/apache/hadoop/hbase/util/FSUtils.getCurrentFileSystem:(Lorg/apache/hadoop/conf/Configuration;)Lorg/apache/hadoop/fs/FileSystem;
      19: astore        4
      21: aload_1
      22: invokestatic  #26                 // Method org/apache/hadoop/hbase/util/FSUtils.getRootDir:(Lorg/apache/hadoop/conf/Configuration;)Lorg/apache/hadoop/fs/Path;
      25: astore        5
      27: aload_0
      28: new           #27                 // class org/apache/hadoop/hbase/master/snapshot/SnapshotFileCache
      31: dup
      32: aload         4
      34: aload         5
      36: lload_2
      37: lload_2
      38: ldc           #28                 // String snapshot-hfile-cleaner-cache-refresher
      40: new           #29                 // class org/apache/hadoop/hbase/master/snapshot/SnapshotHFileCleaner$1
      43: dup
      44: aload_0
      45: aload_1
      46: aload         4
      48: invokespecial #30                 // Method org/apache/hadoop/hbase/master/snapshot/SnapshotHFileCleaner$1."<init>":(Lorg/apache/hadoop/hbase/master/snapshot/SnapshotHFileCleaner;Lorg/apache/hadoop/conf/Configuration;Lorg/apache/hadoop/fs/FileSystem;)V
      51: invokespecial #31                 // Method org/apache/hadoop/hbase/master/snapshot/SnapshotFileCache."<init>":(Lorg/apache/hadoop/fs/FileSystem;Lorg/apache/hadoop/fs/Path;JJLjava/lang/String;Lorg/apache/hadoop/hbase/master/snapshot/SnapshotFileCache$SnapshotFileInspector;)V
      54: putfield      #2                  // Field cache:Lorg/apache/hadoop/hbase/master/snapshot/SnapshotFileCache;
      57: goto          72
      60: astore_2
      61: getstatic     #7                  // Field LOG:Lorg/slf4j/Logger;
      64: ldc           #32                 // String Failed to create cleaner util
      66: aload_2
      67: invokeinterface #12,  3           // InterfaceMethod org/slf4j/Logger.error:(Ljava/lang/String;Ljava/lang/Throwable;)V
      72: return
    Exception table:
       from    to  target type
           5    57    60   Class java/io/IOException

  public void stop(java.lang.String);
    Code:
       0: aload_0
       1: getfield      #2                  // Field cache:Lorg/apache/hadoop/hbase/master/snapshot/SnapshotFileCache;
       4: aload_1
       5: invokevirtual #33                 // Method org/apache/hadoop/hbase/master/snapshot/SnapshotFileCache.stop:(Ljava/lang/String;)V
       8: return

  public boolean isStopped();
    Code:
       0: aload_0
       1: getfield      #2                  // Field cache:Lorg/apache/hadoop/hbase/master/snapshot/SnapshotFileCache;
       4: invokevirtual #34                 // Method org/apache/hadoop/hbase/master/snapshot/SnapshotFileCache.isStopped:()Z
       7: ireturn

  public org.apache.hadoop.hbase.master.snapshot.SnapshotFileCache getFileCacheForTesting();
    Code:
       0: aload_0
       1: getfield      #2                  // Field cache:Lorg/apache/hadoop/hbase/master/snapshot/SnapshotFileCache;
       4: areturn

  static {};
    Code:
       0: ldc           #20                 // class org/apache/hadoop/hbase/master/snapshot/SnapshotHFileCleaner
       2: invokestatic  #35                 // Method org/slf4j/LoggerFactory.getLogger:(Ljava/lang/Class;)Lorg/slf4j/Logger;
       5: putstatic     #7                  // Field LOG:Lorg/slf4j/Logger;
       8: return
}
