Compiled from "SnapshotTestingUtils.java"
public final class org.apache.hadoop.hbase.snapshot.SnapshotTestingUtils {
  public static void assertNoSnapshots(org.apache.hadoop.hbase.client.Admin) throws java.io.IOException;
    Code:
       0: ldc           #2                  // String Have some previous snapshots
       2: lconst_0
       3: aload_0
       4: invokeinterface #3,  1            // InterfaceMethod org/apache/hadoop/hbase/client/Admin.listSnapshots:()Ljava/util/List;
       9: invokeinterface #4,  1            // InterfaceMethod java/util/List.size:()I
      14: i2l
      15: invokestatic  #5                  // Method org/junit/Assert.assertEquals:(Ljava/lang/String;JJ)V
      18: return

  public static java.util.List<org.apache.hadoop.hbase.client.SnapshotDescription> assertExistsMatchingSnapshot(org.apache.hadoop.hbase.client.Admin, java.lang.String, org.apache.hadoop.hbase.TableName) throws java.io.IOException;
    Code:
       0: aload_0
       1: invokeinterface #3,  1            // InterfaceMethod org/apache/hadoop/hbase/client/Admin.listSnapshots:()Ljava/util/List;
       6: astore_3
       7: new           #6                  // class java/util/ArrayList
      10: dup
      11: invokespecial #7                  // Method java/util/ArrayList."<init>":()V
      14: astore        4
      16: aload_3
      17: invokeinterface #8,  1            // InterfaceMethod java/util/List.iterator:()Ljava/util/Iterator;
      22: astore        5
      24: aload         5
      26: invokeinterface #9,  1            // InterfaceMethod java/util/Iterator.hasNext:()Z
      31: ifeq          83
      34: aload         5
      36: invokeinterface #10,  1           // InterfaceMethod java/util/Iterator.next:()Ljava/lang/Object;
      41: checkcast     #11                 // class org/apache/hadoop/hbase/client/SnapshotDescription
      44: astore        6
      46: aload_1
      47: aload         6
      49: invokevirtual #12                 // Method org/apache/hadoop/hbase/client/SnapshotDescription.getName:()Ljava/lang/String;
      52: invokevirtual #13                 // Method java/lang/String.equals:(Ljava/lang/Object;)Z
      55: ifeq          80
      58: aload_2
      59: aload         6
      61: invokevirtual #14                 // Method org/apache/hadoop/hbase/client/SnapshotDescription.getTableName:()Lorg/apache/hadoop/hbase/TableName;
      64: invokevirtual #15                 // Method org/apache/hadoop/hbase/TableName.equals:(Ljava/lang/Object;)Z
      67: ifeq          80
      70: aload         4
      72: aload         6
      74: invokeinterface #16,  2           // InterfaceMethod java/util/List.add:(Ljava/lang/Object;)Z
      79: pop
      80: goto          24
      83: ldc           #17                 // String No matching snapshots found.
      85: aload         4
      87: invokeinterface #4,  1            // InterfaceMethod java/util/List.size:()I
      92: ifle          99
      95: iconst_1
      96: goto          100
      99: iconst_0
     100: invokestatic  #18                 // Method org/junit/Assert.assertTrue:(Ljava/lang/String;Z)V
     103: aload         4
     105: areturn

  public static void assertOneSnapshotThatMatches(org.apache.hadoop.hbase.client.Admin, org.apache.hadoop.hbase.shaded.protobuf.generated.SnapshotProtos$SnapshotDescription) throws java.io.IOException;
    Code:
       0: aload_0
       1: aload_1
       2: invokevirtual #19                 // Method org/apache/hadoop/hbase/shaded/protobuf/generated/SnapshotProtos$SnapshotDescription.getName:()Ljava/lang/String;
       5: aload_1
       6: invokevirtual #20                 // Method org/apache/hadoop/hbase/shaded/protobuf/generated/SnapshotProtos$SnapshotDescription.getTable:()Ljava/lang/String;
       9: invokestatic  #21                 // Method org/apache/hadoop/hbase/TableName.valueOf:(Ljava/lang/String;)Lorg/apache/hadoop/hbase/TableName;
      12: invokestatic  #22                 // Method assertOneSnapshotThatMatches:(Lorg/apache/hadoop/hbase/client/Admin;Ljava/lang/String;Lorg/apache/hadoop/hbase/TableName;)Ljava/util/List;
      15: pop
      16: return

  public static java.util.List<org.apache.hadoop.hbase.client.SnapshotDescription> assertOneSnapshotThatMatches(org.apache.hadoop.hbase.client.Admin, java.lang.String, org.apache.hadoop.hbase.TableName) throws java.io.IOException;
    Code:
       0: aload_0
       1: invokeinterface #3,  1            // InterfaceMethod org/apache/hadoop/hbase/client/Admin.listSnapshots:()Ljava/util/List;
       6: astore_3
       7: ldc           #23                 // String Should only have 1 snapshot
       9: lconst_1
      10: aload_3
      11: invokeinterface #4,  1            // InterfaceMethod java/util/List.size:()I
      16: i2l
      17: invokestatic  #5                  // Method org/junit/Assert.assertEquals:(Ljava/lang/String;JJ)V
      20: aload_1
      21: aload_3
      22: iconst_0
      23: invokeinterface #24,  2           // InterfaceMethod java/util/List.get:(I)Ljava/lang/Object;
      28: checkcast     #11                 // class org/apache/hadoop/hbase/client/SnapshotDescription
      31: invokevirtual #12                 // Method org/apache/hadoop/hbase/client/SnapshotDescription.getName:()Ljava/lang/String;
      34: invokestatic  #25                 // Method org/junit/Assert.assertEquals:(Ljava/lang/Object;Ljava/lang/Object;)V
      37: aload_2
      38: aload_3
      39: iconst_0
      40: invokeinterface #24,  2           // InterfaceMethod java/util/List.get:(I)Ljava/lang/Object;
      45: checkcast     #11                 // class org/apache/hadoop/hbase/client/SnapshotDescription
      48: invokevirtual #14                 // Method org/apache/hadoop/hbase/client/SnapshotDescription.getTableName:()Lorg/apache/hadoop/hbase/TableName;
      51: invokestatic  #25                 // Method org/junit/Assert.assertEquals:(Ljava/lang/Object;Ljava/lang/Object;)V
      54: aload_3
      55: areturn

  public static java.util.List<org.apache.hadoop.hbase.client.SnapshotDescription> assertOneSnapshotThatMatches(org.apache.hadoop.hbase.client.Admin, byte[], org.apache.hadoop.hbase.TableName) throws java.io.IOException;
    Code:
       0: aload_0
       1: aload_1
       2: invokestatic  #26                 // Method org/apache/hadoop/hbase/util/Bytes.toString:([B)Ljava/lang/String;
       5: aload_2
       6: invokestatic  #22                 // Method assertOneSnapshotThatMatches:(Lorg/apache/hadoop/hbase/client/Admin;Ljava/lang/String;Lorg/apache/hadoop/hbase/TableName;)Ljava/util/List;
       9: areturn

  public static void confirmSnapshotValid(org.apache.hadoop.hbase.HBaseTestingUtility, org.apache.hadoop.hbase.shaded.protobuf.generated.SnapshotProtos$SnapshotDescription, org.apache.hadoop.hbase.TableName, byte[]) throws java.io.IOException;
    Code:
       0: aload_0
       1: invokevirtual #27                 // Method org/apache/hadoop/hbase/HBaseTestingUtility.getHBaseCluster:()Lorg/apache/hadoop/hbase/MiniHBaseCluster;
       4: invokevirtual #28                 // Method org/apache/hadoop/hbase/MiniHBaseCluster.getMaster:()Lorg/apache/hadoop/hbase/master/HMaster;
       7: invokevirtual #29                 // Method org/apache/hadoop/hbase/master/HMaster.getMasterFileSystem:()Lorg/apache/hadoop/hbase/master/MasterFileSystem;
      10: astore        4
      12: aload_1
      13: aload_2
      14: aload_3
      15: aload         4
      17: invokevirtual #30                 // Method org/apache/hadoop/hbase/master/MasterFileSystem.getRootDir:()Lorg/apache/hadoop/fs/Path;
      20: aload_0
      21: invokevirtual #31                 // Method org/apache/hadoop/hbase/HBaseTestingUtility.getAdmin:()Lorg/apache/hadoop/hbase/client/Admin;
      24: aload         4
      26: invokevirtual #32                 // Method org/apache/hadoop/hbase/master/MasterFileSystem.getFileSystem:()Lorg/apache/hadoop/fs/FileSystem;
      29: invokestatic  #33                 // Method confirmSnapshotValid:(Lorg/apache/hadoop/hbase/shaded/protobuf/generated/SnapshotProtos$SnapshotDescription;Lorg/apache/hadoop/hbase/TableName;[BLorg/apache/hadoop/fs/Path;Lorg/apache/hadoop/hbase/client/Admin;Lorg/apache/hadoop/fs/FileSystem;)V
      32: return

  public static void confirmSnapshotValid(org.apache.hadoop.hbase.shaded.protobuf.generated.SnapshotProtos$SnapshotDescription, org.apache.hadoop.hbase.TableName, byte[], org.apache.hadoop.fs.Path, org.apache.hadoop.hbase.client.Admin, org.apache.hadoop.fs.FileSystem) throws java.io.IOException;
    Code:
       0: new           #6                  // class java/util/ArrayList
       3: dup
       4: iconst_1
       5: invokespecial #34                 // Method java/util/ArrayList."<init>":(I)V
       8: astore        6
      10: aload         6
      12: aload_2
      13: invokevirtual #35                 // Method java/util/ArrayList.add:(Ljava/lang/Object;)Z
      16: pop
      17: aload_0
      18: aload_1
      19: aload         6
      21: aconst_null
      22: aload_3
      23: aload         4
      25: aload         5
      27: invokestatic  #36                 // Method confirmSnapshotValid:(Lorg/apache/hadoop/hbase/shaded/protobuf/generated/SnapshotProtos$SnapshotDescription;Lorg/apache/hadoop/hbase/TableName;Ljava/util/List;Ljava/util/List;Lorg/apache/hadoop/fs/Path;Lorg/apache/hadoop/hbase/client/Admin;Lorg/apache/hadoop/fs/FileSystem;)V
      30: return

  public static void confirmEmptySnapshotValid(org.apache.hadoop.hbase.shaded.protobuf.generated.SnapshotProtos$SnapshotDescription, org.apache.hadoop.hbase.TableName, byte[], org.apache.hadoop.fs.Path, org.apache.hadoop.hbase.client.Admin, org.apache.hadoop.fs.FileSystem) throws java.io.IOException;
    Code:
       0: new           #6                  // class java/util/ArrayList
       3: dup
       4: iconst_1
       5: invokespecial #34                 // Method java/util/ArrayList."<init>":(I)V
       8: astore        6
      10: aload         6
      12: aload_2
      13: invokevirtual #35                 // Method java/util/ArrayList.add:(Ljava/lang/Object;)Z
      16: pop
      17: aload_0
      18: aload_1
      19: aconst_null
      20: aload         6
      22: aload_3
      23: aload         4
      25: aload         5
      27: invokestatic  #36                 // Method confirmSnapshotValid:(Lorg/apache/hadoop/hbase/shaded/protobuf/generated/SnapshotProtos$SnapshotDescription;Lorg/apache/hadoop/hbase/TableName;Ljava/util/List;Ljava/util/List;Lorg/apache/hadoop/fs/Path;Lorg/apache/hadoop/hbase/client/Admin;Lorg/apache/hadoop/fs/FileSystem;)V
      30: return

  public static void confirmSnapshotValid(org.apache.hadoop.hbase.shaded.protobuf.generated.SnapshotProtos$SnapshotDescription, org.apache.hadoop.hbase.TableName, java.util.List<byte[]>, java.util.List<byte[]>, org.apache.hadoop.fs.Path, org.apache.hadoop.hbase.client.Admin, org.apache.hadoop.fs.FileSystem) throws java.io.IOException;
    Code:
       0: aload         5
       2: invokeinterface #37,  1           // InterfaceMethod org/apache/hadoop/hbase/client/Admin.getConfiguration:()Lorg/apache/hadoop/conf/Configuration;
       7: astore        7
       9: aload_0
      10: aload         4
      12: invokestatic  #38                 // Method org/apache/hadoop/hbase/snapshot/SnapshotDescriptionUtils.getCompletedSnapshotDir:(Lorg/apache/hadoop/hbase/shaded/protobuf/generated/SnapshotProtos$SnapshotDescription;Lorg/apache/hadoop/fs/Path;)Lorg/apache/hadoop/fs/Path;
      15: astore        8
      17: new           #39                 // class java/lang/StringBuilder
      20: dup
      21: invokespecial #40                 // Method java/lang/StringBuilder."<init>":()V
      24: ldc           #41                 // String target snapshot directory, '
      26: invokevirtual #42                 // Method java/lang/StringBuilder.append:(Ljava/lang/String;)Ljava/lang/StringBuilder;
      29: aload         8
      31: invokevirtual #43                 // Method java/lang/StringBuilder.append:(Ljava/lang/Object;)Ljava/lang/StringBuilder;
      34: ldc           #44                 // String ', doesn't exist.
      36: invokevirtual #42                 // Method java/lang/StringBuilder.append:(Ljava/lang/String;)Ljava/lang/StringBuilder;
      39: invokevirtual #45                 // Method java/lang/StringBuilder.toString:()Ljava/lang/String;
      42: aload         6
      44: aload         8
      46: invokevirtual #46                 // Method org/apache/hadoop/fs/FileSystem.exists:(Lorg/apache/hadoop/fs/Path;)Z
      49: invokestatic  #18                 // Method org/junit/Assert.assertTrue:(Ljava/lang/String;Z)V
      52: aload         6
      54: aload         8
      56: invokestatic  #47                 // Method org/apache/hadoop/hbase/snapshot/SnapshotDescriptionUtils.readSnapshotInfo:(Lorg/apache/hadoop/fs/FileSystem;Lorg/apache/hadoop/fs/Path;)Lorg/apache/hadoop/hbase/shaded/protobuf/generated/SnapshotProtos$SnapshotDescription;
      59: astore        9
      61: new           #48                 // class java/util/TreeSet
      64: dup
      65: getstatic     #49                 // Field org/apache/hadoop/hbase/util/Bytes.BYTES_COMPARATOR:Ljava/util/Comparator;
      68: invokespecial #50                 // Method java/util/TreeSet."<init>":(Ljava/util/Comparator;)V
      71: astore        10
      73: aload         7
      75: aload         6
      77: aload         8
      79: aload         9
      81: invokestatic  #51                 // Method org/apache/hadoop/hbase/snapshot/SnapshotManifest.open:(Lorg/apache/hadoop/conf/Configuration;Lorg/apache/hadoop/fs/FileSystem;Lorg/apache/hadoop/fs/Path;Lorg/apache/hadoop/hbase/shaded/protobuf/generated/SnapshotProtos$SnapshotDescription;)Lorg/apache/hadoop/hbase/snapshot/SnapshotManifest;
      84: astore        11
      86: aload         11
      88: invokevirtual #52                 // Method org/apache/hadoop/hbase/snapshot/SnapshotManifest.getRegionManifestsMap:()Ljava/util/Map;
      91: astore        12
      93: aload         12
      95: invokeinterface #53,  1           // InterfaceMethod java/util/Map.values:()Ljava/util/Collection;
     100: invokeinterface #54,  1           // InterfaceMethod java/util/Collection.iterator:()Ljava/util/Iterator;
     105: astore        13
     107: aload         13
     109: invokeinterface #9,  1            // InterfaceMethod java/util/Iterator.hasNext:()Z
     114: ifeq          146
     117: aload         13
     119: invokeinterface #10,  1           // InterfaceMethod java/util/Iterator.next:()Ljava/lang/Object;
     124: checkcast     #55                 // class org/apache/hadoop/hbase/shaded/protobuf/generated/SnapshotProtos$SnapshotRegionManifest
     127: astore        14
     129: aload         14
     131: new           #56                 // class org/apache/hadoop/hbase/snapshot/SnapshotTestingUtils$1
     134: dup
     135: aload         10
     137: invokespecial #57                 // Method org/apache/hadoop/hbase/snapshot/SnapshotTestingUtils$1."<init>":(Ljava/util/Set;)V
     140: invokestatic  #58                 // Method org/apache/hadoop/hbase/snapshot/SnapshotReferenceUtil.visitRegionStoreFiles:(Lorg/apache/hadoop/hbase/shaded/protobuf/generated/SnapshotProtos$SnapshotRegionManifest;Lorg/apache/hadoop/hbase/snapshot/SnapshotReferenceUtil$StoreFileVisitor;)V
     143: goto          107
     146: aload_2
     147: ifnull        223
     150: aload_2
     151: invokeinterface #8,  1            // InterfaceMethod java/util/List.iterator:()Ljava/util/Iterator;
     156: astore        13
     158: aload         13
     160: invokeinterface #9,  1            // InterfaceMethod java/util/Iterator.hasNext:()Z
     165: ifeq          223
     168: aload         13
     170: invokeinterface #10,  1           // InterfaceMethod java/util/Iterator.next:()Ljava/lang/Object;
     175: checkcast     #59                 // class "[B"
     178: astore        14
     180: new           #39                 // class java/lang/StringBuilder
     183: dup
     184: invokespecial #40                 // Method java/lang/StringBuilder."<init>":()V
     187: ldc           #60                 // String Expected snapshot to contain family '
     189: invokevirtual #42                 // Method java/lang/StringBuilder.append:(Ljava/lang/String;)Ljava/lang/StringBuilder;
     192: aload         14
     194: invokestatic  #26                 // Method org/apache/hadoop/hbase/util/Bytes.toString:([B)Ljava/lang/String;
     197: invokevirtual #42                 // Method java/lang/StringBuilder.append:(Ljava/lang/String;)Ljava/lang/StringBuilder;
     200: ldc           #61                 // String ', but it does not.
     202: invokevirtual #42                 // Method java/lang/StringBuilder.append:(Ljava/lang/String;)Ljava/lang/StringBuilder;
     205: invokevirtual #45                 // Method java/lang/StringBuilder.toString:()Ljava/lang/String;
     208: aload         10
     210: aload         14
     212: invokeinterface #62,  2           // InterfaceMethod java/util/Set.contains:(Ljava/lang/Object;)Z
     217: invokestatic  #18                 // Method org/junit/Assert.assertTrue:(Ljava/lang/String;Z)V
     220: goto          158
     223: aload_3
     224: ifnull        300
     227: aload_3
     228: invokeinterface #8,  1            // InterfaceMethod java/util/List.iterator:()Ljava/util/Iterator;
     233: astore        13
     235: aload         13
     237: invokeinterface #9,  1            // InterfaceMethod java/util/Iterator.hasNext:()Z
     242: ifeq          300
     245: aload         13
     247: invokeinterface #10,  1           // InterfaceMethod java/util/Iterator.next:()Ljava/lang/Object;
     252: checkcast     #59                 // class "[B"
     255: astore        14
     257: new           #39                 // class java/lang/StringBuilder
     260: dup
     261: invokespecial #40                 // Method java/lang/StringBuilder."<init>":()V
     264: ldc           #63                 // String Expected snapshot to skip empty family '
     266: invokevirtual #42                 // Method java/lang/StringBuilder.append:(Ljava/lang/String;)Ljava/lang/StringBuilder;
     269: aload         14
     271: invokestatic  #26                 // Method org/apache/hadoop/hbase/util/Bytes.toString:([B)Ljava/lang/String;
     274: invokevirtual #42                 // Method java/lang/StringBuilder.append:(Ljava/lang/String;)Ljava/lang/StringBuilder;
     277: ldc           #64                 // String ', but it is present.
     279: invokevirtual #42                 // Method java/lang/StringBuilder.append:(Ljava/lang/String;)Ljava/lang/StringBuilder;
     282: invokevirtual #45                 // Method java/lang/StringBuilder.toString:()Ljava/lang/String;
     285: aload         10
     287: aload         14
     289: invokeinterface #62,  2           // InterfaceMethod java/util/Set.contains:(Ljava/lang/Object;)Z
     294: invokestatic  #65                 // Method org/junit/Assert.assertFalse:(Ljava/lang/String;Z)V
     297: goto          235
     300: aload         5
     302: aload_1
     303: invokeinterface #66,  2           // InterfaceMethod org/apache/hadoop/hbase/client/Admin.getRegions:(Lorg/apache/hadoop/hbase/TableName;)Ljava/util/List;
     308: astore        13
     310: aload         13
     312: invokestatic  #67                 // Method org/apache/hadoop/hbase/client/RegionReplicaUtil.removeNonDefaultRegions:(Ljava/util/Collection;)V
     315: aload         12
     317: aload_1
     318: invokestatic  #68                 // Method org/apache/hadoop/hbase/mob/MobUtils.getMobRegionInfo:(Lorg/apache/hadoop/hbase/TableName;)Lorg/apache/hadoop/hbase/client/RegionInfo;
     321: invokeinterface #69,  1           // InterfaceMethod org/apache/hadoop/hbase/client/RegionInfo.getEncodedName:()Ljava/lang/String;
     326: invokeinterface #70,  2           // InterfaceMethod java/util/Map.containsKey:(Ljava/lang/Object;)Z
     331: istore        14
     333: iload         14
     335: ifeq          364
     338: ldc           #71                 // String Wrong number of regions.
     340: aload         13
     342: invokeinterface #4,  1            // InterfaceMethod java/util/List.size:()I
     347: i2l
     348: aload         12
     350: invokeinterface #72,  1           // InterfaceMethod java/util/Map.size:()I
     355: iconst_1
     356: isub
     357: i2l
     358: invokestatic  #5                  // Method org/junit/Assert.assertEquals:(Ljava/lang/String;JJ)V
     361: goto          468
     364: iconst_0
     365: istore        15
     367: aload         12
     369: invokeinterface #53,  1           // InterfaceMethod java/util/Map.values:()Ljava/util/Collection;
     374: invokeinterface #54,  1           // InterfaceMethod java/util/Collection.iterator:()Ljava/util/Iterator;
     379: astore        16
     381: aload         16
     383: invokeinterface #9,  1            // InterfaceMethod java/util/Iterator.hasNext:()Z
     388: ifeq          452
     391: aload         16
     393: invokeinterface #10,  1           // InterfaceMethod java/util/Iterator.next:()Ljava/lang/Object;
     398: checkcast     #55                 // class org/apache/hadoop/hbase/shaded/protobuf/generated/SnapshotProtos$SnapshotRegionManifest
     401: astore        17
     403: aload         17
     405: invokevirtual #73                 // Method org/apache/hadoop/hbase/shaded/protobuf/generated/SnapshotProtos$SnapshotRegionManifest.getRegionInfo:()Lorg/apache/hadoop/hbase/shaded/protobuf/generated/HBaseProtos$RegionInfo;
     408: invokestatic  #74                 // Method org/apache/hadoop/hbase/shaded/protobuf/ProtobufUtil.toRegionInfo:(Lorg/apache/hadoop/hbase/shaded/protobuf/generated/HBaseProtos$RegionInfo;)Lorg/apache/hadoop/hbase/client/RegionInfo;
     411: astore        18
     413: aload         18
     415: invokeinterface #75,  1           // InterfaceMethod org/apache/hadoop/hbase/client/RegionInfo.isOffline:()Z
     420: ifeq          446
     423: aload         18
     425: invokeinterface #76,  1           // InterfaceMethod org/apache/hadoop/hbase/client/RegionInfo.isSplit:()Z
     430: ifne          381
     433: aload         18
     435: invokeinterface #77,  1           // InterfaceMethod org/apache/hadoop/hbase/client/RegionInfo.isSplitParent:()Z
     440: ifeq          446
     443: goto          381
     446: iinc          15, 1
     449: goto          381
     452: ldc           #71                 // String Wrong number of regions.
     454: aload         13
     456: invokeinterface #4,  1            // InterfaceMethod java/util/List.size:()I
     461: i2l
     462: iload         15
     464: i2l
     465: invokestatic  #5                  // Method org/junit/Assert.assertEquals:(Ljava/lang/String;JJ)V
     468: aload         13
     470: invokeinterface #8,  1            // InterfaceMethod java/util/List.iterator:()Ljava/util/Iterator;
     475: astore        15
     477: aload         15
     479: invokeinterface #9,  1            // InterfaceMethod java/util/Iterator.hasNext:()Z
     484: ifeq          548
     487: aload         15
     489: invokeinterface #10,  1           // InterfaceMethod java/util/Iterator.next:()Ljava/lang/Object;
     494: checkcast     #78                 // class org/apache/hadoop/hbase/client/RegionInfo
     497: astore        16
     499: aload         16
     501: invokeinterface #69,  1           // InterfaceMethod org/apache/hadoop/hbase/client/RegionInfo.getEncodedName:()Ljava/lang/String;
     506: astore        17
     508: new           #39                 // class java/lang/StringBuilder
     511: dup
     512: invokespecial #40                 // Method java/lang/StringBuilder."<init>":()V
     515: ldc           #79                 // String Missing region name: '
     517: invokevirtual #42                 // Method java/lang/StringBuilder.append:(Ljava/lang/String;)Ljava/lang/StringBuilder;
     520: aload         17
     522: invokevirtual #42                 // Method java/lang/StringBuilder.append:(Ljava/lang/String;)Ljava/lang/StringBuilder;
     525: ldc           #80                 // String '
     527: invokevirtual #42                 // Method java/lang/StringBuilder.append:(Ljava/lang/String;)Ljava/lang/StringBuilder;
     530: invokevirtual #45                 // Method java/lang/StringBuilder.toString:()Ljava/lang/String;
     533: aload         12
     535: aload         17
     537: invokeinterface #70,  2           // InterfaceMethod java/util/Map.containsKey:(Ljava/lang/Object;)Z
     542: invokestatic  #18                 // Method org/junit/Assert.assertTrue:(Ljava/lang/String;Z)V
     545: goto          477
     548: return

  public static void waitForSnapshotToComplete(org.apache.hadoop.hbase.master.HMaster, org.apache.hadoop.hbase.shaded.protobuf.generated.SnapshotProtos$SnapshotDescription, long) throws org.apache.hbase.thirdparty.com.google.protobuf.ServiceException;
    Code:
       0: invokestatic  #81                 // Method org/apache/hadoop/hbase/shaded/protobuf/generated/MasterProtos$IsSnapshotDoneRequest.newBuilder:()Lorg/apache/hadoop/hbase/shaded/protobuf/generated/MasterProtos$IsSnapshotDoneRequest$Builder;
       3: aload_1
       4: invokevirtual #82                 // Method org/apache/hadoop/hbase/shaded/protobuf/generated/MasterProtos$IsSnapshotDoneRequest$Builder.setSnapshot:(Lorg/apache/hadoop/hbase/shaded/protobuf/generated/SnapshotProtos$SnapshotDescription;)Lorg/apache/hadoop/hbase/shaded/protobuf/generated/MasterProtos$IsSnapshotDoneRequest$Builder;
       7: invokevirtual #83                 // Method org/apache/hadoop/hbase/shaded/protobuf/generated/MasterProtos$IsSnapshotDoneRequest$Builder.build:()Lorg/apache/hadoop/hbase/shaded/protobuf/generated/MasterProtos$IsSnapshotDoneRequest;
      10: astore        4
      12: invokestatic  #84                 // Method org/apache/hadoop/hbase/shaded/protobuf/generated/MasterProtos$IsSnapshotDoneResponse.newBuilder:()Lorg/apache/hadoop/hbase/shaded/protobuf/generated/MasterProtos$IsSnapshotDoneResponse$Builder;
      15: invokevirtual #85                 // Method org/apache/hadoop/hbase/shaded/protobuf/generated/MasterProtos$IsSnapshotDoneResponse$Builder.buildPartial:()Lorg/apache/hadoop/hbase/shaded/protobuf/generated/MasterProtos$IsSnapshotDoneResponse;
      18: astore        5
      20: aload         5
      22: invokevirtual #86                 // Method org/apache/hadoop/hbase/shaded/protobuf/generated/MasterProtos$IsSnapshotDoneResponse.getDone:()Z
      25: ifne          59
      28: aload_0
      29: invokevirtual #87                 // Method org/apache/hadoop/hbase/master/HMaster.getMasterRpcServices:()Lorg/apache/hadoop/hbase/master/MasterRpcServices;
      32: aconst_null
      33: aload         4
      35: invokevirtual #88                 // Method org/apache/hadoop/hbase/master/MasterRpcServices.isSnapshotDone:(Lorg/apache/hbase/thirdparty/com/google/protobuf/RpcController;Lorg/apache/hadoop/hbase/shaded/protobuf/generated/MasterProtos$IsSnapshotDoneRequest;)Lorg/apache/hadoop/hbase/shaded/protobuf/generated/MasterProtos$IsSnapshotDoneResponse;
      38: astore        5
      40: lload_2
      41: invokestatic  #89                 // Method java/lang/Thread.sleep:(J)V
      44: goto          20
      47: astore        6
      49: new           #91                 // class org/apache/hbase/thirdparty/com/google/protobuf/ServiceException
      52: dup
      53: aload         6
      55: invokespecial #92                 // Method org/apache/hbase/thirdparty/com/google/protobuf/ServiceException."<init>":(Ljava/lang/Throwable;)V
      58: athrow
      59: return
    Exception table:
       from    to  target type
          40    44    47   Class java/lang/InterruptedException

  public static void snapshot(org.apache.hadoop.hbase.client.Admin, java.lang.String, org.apache.hadoop.hbase.TableName, org.apache.hadoop.hbase.client.SnapshotType, int) throws java.io.IOException;
    Code:
       0: iconst_0
       1: istore        5
       3: aconst_null
       4: astore        6
       6: iload         5
       8: iinc          5, 1
      11: iload         4
      13: if_icmpge     47
      16: aload_0
      17: aload_1
      18: aload_2
      19: aload_3
      20: invokeinterface #93,  4           // InterfaceMethod org/apache/hadoop/hbase/client/Admin.snapshot:(Ljava/lang/String;Lorg/apache/hadoop/hbase/TableName;Lorg/apache/hadoop/hbase/client/SnapshotType;)V
      25: return
      26: astore        7
      28: getstatic     #95                 // Field LOG:Lorg/slf4j/Logger;
      31: ldc           #96                 // String Got CorruptedSnapshotException
      33: aload         7
      35: invokeinterface #97,  3           // InterfaceMethod org/slf4j/Logger.warn:(Ljava/lang/String;Ljava/lang/Throwable;)V
      40: aload         7
      42: astore        6
      44: goto          6
      47: aload         6
      49: athrow
    Exception table:
       from    to  target type
          16    25    26   Class org/apache/hadoop/hbase/snapshot/CorruptedSnapshotException

  public static void cleanupSnapshot(org.apache.hadoop.hbase.client.Admin, byte[]) throws java.io.IOException;
    Code:
       0: aload_0
       1: aload_1
       2: invokestatic  #26                 // Method org/apache/hadoop/hbase/util/Bytes.toString:([B)Ljava/lang/String;
       5: invokestatic  #98                 // Method cleanupSnapshot:(Lorg/apache/hadoop/hbase/client/Admin;Ljava/lang/String;)V
       8: return

  public static void cleanupSnapshot(org.apache.hadoop.hbase.client.Admin, java.lang.String) throws java.io.IOException;
    Code:
       0: aload_0
       1: aload_1
       2: invokeinterface #99,  2           // InterfaceMethod org/apache/hadoop/hbase/client/Admin.deleteSnapshot:(Ljava/lang/String;)V
       7: aload_0
       8: invokestatic  #100                // Method assertNoSnapshots:(Lorg/apache/hadoop/hbase/client/Admin;)V
      11: return

  public static void expectSnapshotDoneException(org.apache.hadoop.hbase.master.HMaster, org.apache.hadoop.hbase.shaded.protobuf.generated.MasterProtos$IsSnapshotDoneRequest, java.lang.Class<? extends org.apache.hadoop.hbase.snapshot.HBaseSnapshotException>);
    Code:
       0: aload_0
       1: invokevirtual #87                 // Method org/apache/hadoop/hbase/master/HMaster.getMasterRpcServices:()Lorg/apache/hadoop/hbase/master/MasterRpcServices;
       4: aconst_null
       5: aload_1
       6: invokevirtual #88                 // Method org/apache/hadoop/hbase/master/MasterRpcServices.isSnapshotDone:(Lorg/apache/hbase/thirdparty/com/google/protobuf/RpcController;Lorg/apache/hadoop/hbase/shaded/protobuf/generated/MasterProtos$IsSnapshotDoneRequest;)Lorg/apache/hadoop/hbase/shaded/protobuf/generated/MasterProtos$IsSnapshotDoneResponse;
       9: pop
      10: ldc           #101                // String didn't fail to lookup a snapshot
      12: invokestatic  #102                // Method org/junit/Assert.fail:(Ljava/lang/String;)V
      15: goto          65
      18: astore_3
      19: aload_3
      20: invokestatic  #103                // Method org/apache/hadoop/hbase/shaded/protobuf/ProtobufUtil.handleRemoteException:(Ljava/lang/Exception;)Ljava/io/IOException;
      23: athrow
      24: astore        4
      26: ldc           #105                // String Threw wrong snapshot exception!
      28: aload_2
      29: aload         4
      31: invokevirtual #106                // Method java/lang/Object.getClass:()Ljava/lang/Class;
      34: invokestatic  #107                // Method org/junit/Assert.assertEquals:(Ljava/lang/String;Ljava/lang/Object;Ljava/lang/Object;)V
      37: goto          65
      40: astore        4
      42: new           #39                 // class java/lang/StringBuilder
      45: dup
      46: invokespecial #40                 // Method java/lang/StringBuilder."<init>":()V
      49: ldc           #109                // String Threw an unexpected exception:
      51: invokevirtual #42                 // Method java/lang/StringBuilder.append:(Ljava/lang/String;)Ljava/lang/StringBuilder;
      54: aload         4
      56: invokevirtual #43                 // Method java/lang/StringBuilder.append:(Ljava/lang/Object;)Ljava/lang/StringBuilder;
      59: invokevirtual #45                 // Method java/lang/StringBuilder.toString:()Ljava/lang/String;
      62: invokestatic  #102                // Method org/junit/Assert.fail:(Ljava/lang/String;)V
      65: return
    Exception table:
       from    to  target type
           0    15    18   Class org/apache/hbase/thirdparty/com/google/protobuf/ServiceException
          19    24    24   Class org/apache/hadoop/hbase/snapshot/HBaseSnapshotException
          19    24    40   Class java/lang/Throwable

  public static java.util.ArrayList<java.lang.String> listHFileNames(org.apache.hadoop.fs.FileSystem, org.apache.hadoop.fs.Path) throws java.io.IOException;
    Code:
       0: new           #6                  // class java/util/ArrayList
       3: dup
       4: invokespecial #7                  // Method java/util/ArrayList."<init>":()V
       7: astore_2
       8: aload_0
       9: aload_1
      10: new           #110                // class org/apache/hadoop/hbase/snapshot/SnapshotTestingUtils$2
      13: dup
      14: aload_2
      15: invokespecial #111                // Method org/apache/hadoop/hbase/snapshot/SnapshotTestingUtils$2."<init>":(Ljava/util/ArrayList;)V
      18: invokestatic  #112                // Method org/apache/hadoop/hbase/util/FSVisitor.visitTableStoreFiles:(Lorg/apache/hadoop/fs/FileSystem;Lorg/apache/hadoop/fs/Path;Lorg/apache/hadoop/hbase/util/FSVisitor$StoreFileVisitor;)V
      21: aload_2
      22: invokestatic  #113                // Method java/util/Collections.sort:(Ljava/util/List;)V
      25: aload_2
      26: areturn

  public static void createSnapshotAndValidate(org.apache.hadoop.hbase.client.Admin, org.apache.hadoop.hbase.TableName, java.lang.String, java.lang.String, org.apache.hadoop.fs.Path, org.apache.hadoop.fs.FileSystem, boolean) throws java.lang.Exception;
    Code:
       0: new           #6                  // class java/util/ArrayList
       3: dup
       4: iconst_1
       5: invokespecial #34                 // Method java/util/ArrayList."<init>":(I)V
       8: astore        7
      10: aload         7
      12: aload_2
      13: invokestatic  #114                // Method org/apache/hadoop/hbase/util/Bytes.toBytes:(Ljava/lang/String;)[B
      16: invokevirtual #35                 // Method java/util/ArrayList.add:(Ljava/lang/Object;)Z
      19: pop
      20: aload_0
      21: aload_1
      22: aload         7
      24: aconst_null
      25: aload_3
      26: aload         4
      28: aload         5
      30: iload         6
      32: invokestatic  #115                // Method createSnapshotAndValidate:(Lorg/apache/hadoop/hbase/client/Admin;Lorg/apache/hadoop/hbase/TableName;Ljava/util/List;Ljava/util/List;Ljava/lang/String;Lorg/apache/hadoop/fs/Path;Lorg/apache/hadoop/fs/FileSystem;Z)V
      35: return

  public static void createSnapshotAndValidate(org.apache.hadoop.hbase.client.Admin, org.apache.hadoop.hbase.TableName, java.util.List<byte[]>, java.util.List<byte[]>, java.lang.String, org.apache.hadoop.fs.Path, org.apache.hadoop.fs.FileSystem, boolean) throws java.lang.Exception;
    Code:
       0: iload         7
       2: ifne          59
       5: getstatic     #95                 // Field LOG:Lorg/slf4j/Logger;
       8: ldc           #116                // String prepping for offline snapshot.
      10: invokeinterface #117,  2          // InterfaceMethod org/slf4j/Logger.info:(Ljava/lang/String;)V
      15: aload_0
      16: aload_1
      17: invokeinterface #118,  2          // InterfaceMethod org/apache/hadoop/hbase/client/Admin.disableTable:(Lorg/apache/hadoop/hbase/TableName;)V
      22: goto          59
      25: astore        8
      27: getstatic     #95                 // Field LOG:Lorg/slf4j/Logger;
      30: new           #39                 // class java/lang/StringBuilder
      33: dup
      34: invokespecial #40                 // Method java/lang/StringBuilder."<init>":()V
      37: ldc           #120                // String In attempting to disable
      39: invokevirtual #42                 // Method java/lang/StringBuilder.append:(Ljava/lang/String;)Ljava/lang/StringBuilder;
      42: aload_1
      43: invokevirtual #43                 // Method java/lang/StringBuilder.append:(Ljava/lang/Object;)Ljava/lang/StringBuilder;
      46: ldc           #121                // String  it turns out that the this table is already disabled.
      48: invokevirtual #42                 // Method java/lang/StringBuilder.append:(Ljava/lang/String;)Ljava/lang/StringBuilder;
      51: invokevirtual #45                 // Method java/lang/StringBuilder.toString:()Ljava/lang/String;
      54: invokeinterface #117,  2          // InterfaceMethod org/slf4j/Logger.info:(Ljava/lang/String;)V
      59: getstatic     #95                 // Field LOG:Lorg/slf4j/Logger;
      62: ldc           #122                // String taking snapshot.
      64: invokeinterface #117,  2          // InterfaceMethod org/slf4j/Logger.info:(Ljava/lang/String;)V
      69: aload_0
      70: aload         4
      72: aload_1
      73: invokeinterface #123,  3          // InterfaceMethod org/apache/hadoop/hbase/client/Admin.snapshot:(Ljava/lang/String;Lorg/apache/hadoop/hbase/TableName;)V
      78: getstatic     #95                 // Field LOG:Lorg/slf4j/Logger;
      81: ldc           #124                // String Confirming snapshot exists.
      83: invokeinterface #117,  2          // InterfaceMethod org/slf4j/Logger.info:(Ljava/lang/String;)V
      88: aload_0
      89: aload         4
      91: aload_1
      92: invokestatic  #125                // Method assertExistsMatchingSnapshot:(Lorg/apache/hadoop/hbase/client/Admin;Ljava/lang/String;Lorg/apache/hadoop/hbase/TableName;)Ljava/util/List;
      95: astore        8
      97: aload         8
      99: ifnull        113
     102: aload         8
     104: invokeinterface #4,  1            // InterfaceMethod java/util/List.size:()I
     109: iconst_1
     110: if_icmpeq     135
     113: new           #39                 // class java/lang/StringBuilder
     116: dup
     117: invokespecial #40                 // Method java/lang/StringBuilder."<init>":()V
     120: ldc           #126                // String Incorrect number of snapshots for table
     122: invokevirtual #42                 // Method java/lang/StringBuilder.append:(Ljava/lang/String;)Ljava/lang/StringBuilder;
     125: aload_1
     126: invokevirtual #43                 // Method java/lang/StringBuilder.append:(Ljava/lang/Object;)Ljava/lang/StringBuilder;
     129: invokevirtual #45                 // Method java/lang/StringBuilder.toString:()Ljava/lang/String;
     132: invokestatic  #102                // Method org/junit/Assert.fail:(Ljava/lang/String;)V
     135: getstatic     #95                 // Field LOG:Lorg/slf4j/Logger;
     138: ldc           #127                // String validating snapshot.
     140: invokeinterface #117,  2          // InterfaceMethod org/slf4j/Logger.info:(Ljava/lang/String;)V
     145: aload         8
     147: iconst_0
     148: invokeinterface #24,  2           // InterfaceMethod java/util/List.get:(I)Ljava/lang/Object;
     153: checkcast     #11                 // class org/apache/hadoop/hbase/client/SnapshotDescription
     156: invokestatic  #128                // Method org/apache/hadoop/hbase/shaded/protobuf/ProtobufUtil.createHBaseProtosSnapshotDesc:(Lorg/apache/hadoop/hbase/client/SnapshotDescription;)Lorg/apache/hadoop/hbase/shaded/protobuf/generated/SnapshotProtos$SnapshotDescription;
     159: aload_1
     160: aload_2
     161: aload_3
     162: aload         5
     164: aload_0
     165: aload         6
     167: invokestatic  #36                 // Method confirmSnapshotValid:(Lorg/apache/hadoop/hbase/shaded/protobuf/generated/SnapshotProtos$SnapshotDescription;Lorg/apache/hadoop/hbase/TableName;Ljava/util/List;Ljava/util/List;Lorg/apache/hadoop/fs/Path;Lorg/apache/hadoop/hbase/client/Admin;Lorg/apache/hadoop/fs/FileSystem;)V
     170: return
    Exception table:
       from    to  target type
           5    22    25   Class org/apache/hadoop/hbase/TableNotEnabledException

  public static java.util.ArrayList corruptSnapshot(org.apache.hadoop.hbase.HBaseTestingUtility, java.lang.String) throws java.io.IOException;
    Code:
       0: aload_0
       1: invokevirtual #27                 // Method org/apache/hadoop/hbase/HBaseTestingUtility.getHBaseCluster:()Lorg/apache/hadoop/hbase/MiniHBaseCluster;
       4: invokevirtual #28                 // Method org/apache/hadoop/hbase/MiniHBaseCluster.getMaster:()Lorg/apache/hadoop/hbase/master/HMaster;
       7: invokevirtual #29                 // Method org/apache/hadoop/hbase/master/HMaster.getMasterFileSystem:()Lorg/apache/hadoop/hbase/master/MasterFileSystem;
      10: astore_2
      11: aload_2
      12: invokevirtual #32                 // Method org/apache/hadoop/hbase/master/MasterFileSystem.getFileSystem:()Lorg/apache/hadoop/fs/FileSystem;
      15: astore_3
      16: aload_1
      17: aload_2
      18: invokevirtual #30                 // Method org/apache/hadoop/hbase/master/MasterFileSystem.getRootDir:()Lorg/apache/hadoop/fs/Path;
      21: invokestatic  #129                // Method org/apache/hadoop/hbase/snapshot/SnapshotDescriptionUtils.getCompletedSnapshotDir:(Ljava/lang/String;Lorg/apache/hadoop/fs/Path;)Lorg/apache/hadoop/fs/Path;
      24: astore        4
      26: aload_3
      27: aload         4
      29: invokestatic  #47                 // Method org/apache/hadoop/hbase/snapshot/SnapshotDescriptionUtils.readSnapshotInfo:(Lorg/apache/hadoop/fs/FileSystem;Lorg/apache/hadoop/fs/Path;)Lorg/apache/hadoop/hbase/shaded/protobuf/generated/SnapshotProtos$SnapshotDescription;
      32: astore        5
      34: aload         5
      36: invokevirtual #20                 // Method org/apache/hadoop/hbase/shaded/protobuf/generated/SnapshotProtos$SnapshotDescription.getTable:()Ljava/lang/String;
      39: invokestatic  #21                 // Method org/apache/hadoop/hbase/TableName.valueOf:(Ljava/lang/String;)Lorg/apache/hadoop/hbase/TableName;
      42: astore        6
      44: new           #6                  // class java/util/ArrayList
      47: dup
      48: invokespecial #7                  // Method java/util/ArrayList."<init>":()V
      51: astore        7
      53: aload_0
      54: invokevirtual #130                // Method org/apache/hadoop/hbase/HBaseTestingUtility.getConfiguration:()Lorg/apache/hadoop/conf/Configuration;
      57: astore        8
      59: aload         8
      61: aload_3
      62: aload         4
      64: aload         5
      66: new           #131                // class org/apache/hadoop/hbase/snapshot/SnapshotTestingUtils$3
      69: dup
      70: aload         8
      72: aload         6
      74: aload         7
      76: aload_3
      77: invokespecial #132                // Method org/apache/hadoop/hbase/snapshot/SnapshotTestingUtils$3."<init>":(Lorg/apache/hadoop/conf/Configuration;Lorg/apache/hadoop/hbase/TableName;Ljava/util/ArrayList;Lorg/apache/hadoop/fs/FileSystem;)V
      80: invokestatic  #133                // Method org/apache/hadoop/hbase/snapshot/SnapshotReferenceUtil.visitTableStoreFiles:(Lorg/apache/hadoop/conf/Configuration;Lorg/apache/hadoop/fs/FileSystem;Lorg/apache/hadoop/fs/Path;Lorg/apache/hadoop/hbase/shaded/protobuf/generated/SnapshotProtos$SnapshotDescription;Lorg/apache/hadoop/hbase/snapshot/SnapshotReferenceUtil$StoreFileVisitor;)V
      83: aload         7
      85: invokevirtual #134                // Method java/util/ArrayList.size:()I
      88: ifle          95
      91: iconst_1
      92: goto          96
      95: iconst_0
      96: invokestatic  #135                // Method org/junit/Assert.assertTrue:(Z)V
      99: aload         7
     101: areturn

  public static void waitForTableToBeOnline(org.apache.hadoop.hbase.HBaseTestingUtility, org.apache.hadoop.hbase.TableName) throws java.io.IOException, java.lang.InterruptedException;
    Code:
       0: aload_0
       1: aload_1
       2: invokevirtual #136                // Method org/apache/hadoop/hbase/HBaseTestingUtility.getRSForFirstRegionInTable:(Lorg/apache/hadoop/hbase/TableName;)Lorg/apache/hadoop/hbase/regionserver/HRegionServer;
       5: astore_2
       6: aload_2
       7: aload_1
       8: invokevirtual #137                // Method org/apache/hadoop/hbase/regionserver/HRegionServer.getRegions:(Lorg/apache/hadoop/hbase/TableName;)Ljava/util/List;
      11: astore_3
      12: aload_3
      13: invokeinterface #8,  1            // InterfaceMethod java/util/List.iterator:()Ljava/util/Iterator;
      18: astore        4
      20: aload         4
      22: invokeinterface #9,  1            // InterfaceMethod java/util/Iterator.hasNext:()Z
      27: ifeq          50
      30: aload         4
      32: invokeinterface #10,  1           // InterfaceMethod java/util/Iterator.next:()Ljava/lang/Object;
      37: checkcast     #138                // class org/apache/hadoop/hbase/regionserver/HRegion
      40: astore        5
      42: aload         5
      44: invokevirtual #139                // Method org/apache/hadoop/hbase/regionserver/HRegion.waitForFlushesAndCompactions:()V
      47: goto          20
      50: aload_0
      51: ldc2_w        #140                // long 60000l
      54: aload_0
      55: aload_1
      56: invokevirtual #142                // Method org/apache/hadoop/hbase/HBaseTestingUtility.predicateTableAvailable:(Lorg/apache/hadoop/hbase/TableName;)Lorg/apache/hadoop/hbase/Waiter$Predicate;
      59: invokevirtual #143                // Method org/apache/hadoop/hbase/HBaseTestingUtility.waitFor:(JLorg/apache/hadoop/hbase/Waiter$Predicate;)J
      62: pop2
      63: return

  public static void createTable(org.apache.hadoop.hbase.HBaseTestingUtility, org.apache.hadoop.hbase.TableName, int, int, byte[]...) throws java.io.IOException, java.lang.InterruptedException;
    Code:
       0: aload_1
       1: invokestatic  #144                // Method org/apache/hadoop/hbase/client/TableDescriptorBuilder.newBuilder:(Lorg/apache/hadoop/hbase/TableName;)Lorg/apache/hadoop/hbase/client/TableDescriptorBuilder;
       4: iload_2
       5: invokevirtual #145                // Method org/apache/hadoop/hbase/client/TableDescriptorBuilder.setRegionReplication:(I)Lorg/apache/hadoop/hbase/client/TableDescriptorBuilder;
       8: astore        5
      10: aload         4
      12: astore        6
      14: aload         6
      16: arraylength
      17: istore        7
      19: iconst_0
      20: istore        8
      22: iload         8
      24: iload         7
      26: if_icmpge     53
      29: aload         6
      31: iload         8
      33: aaload
      34: astore        9
      36: aload         5
      38: aload         9
      40: invokestatic  #146                // Method org/apache/hadoop/hbase/client/ColumnFamilyDescriptorBuilder.of:([B)Lorg/apache/hadoop/hbase/client/ColumnFamilyDescriptor;
      43: invokevirtual #147                // Method org/apache/hadoop/hbase/client/TableDescriptorBuilder.setColumnFamily:(Lorg/apache/hadoop/hbase/client/ColumnFamilyDescriptor;)Lorg/apache/hadoop/hbase/client/TableDescriptorBuilder;
      46: pop
      47: iinc          8, 1
      50: goto          22
      53: iload_3
      54: invokestatic  #148                // Method getSplitKeys:(I)[[B
      57: astore        6
      59: aload_0
      60: aload         5
      62: invokevirtual #149                // Method org/apache/hadoop/hbase/client/TableDescriptorBuilder.build:()Lorg/apache/hadoop/hbase/client/TableDescriptor;
      65: aload         6
      67: invokevirtual #150                // Method org/apache/hadoop/hbase/HBaseTestingUtility.createTable:(Lorg/apache/hadoop/hbase/client/TableDescriptor;[[B)Lorg/apache/hadoop/hbase/client/Table;
      70: pop
      71: aload         6
      73: arraylength
      74: iconst_1
      75: iadd
      76: iload_2
      77: imul
      78: i2l
      79: aload_0
      80: invokevirtual #31                 // Method org/apache/hadoop/hbase/HBaseTestingUtility.getAdmin:()Lorg/apache/hadoop/hbase/client/Admin;
      83: aload_1
      84: invokeinterface #66,  2           // InterfaceMethod org/apache/hadoop/hbase/client/Admin.getRegions:(Lorg/apache/hadoop/hbase/TableName;)Ljava/util/List;
      89: invokeinterface #4,  1            // InterfaceMethod java/util/List.size:()I
      94: i2l
      95: invokestatic  #151                // Method org/junit/Assert.assertEquals:(JJ)V
      98: return

  public static byte[][] getSplitKeys();
    Code:
       0: getstatic     #152                // Field KEYS:[B
       3: arraylength
       4: invokestatic  #148                // Method getSplitKeys:(I)[[B
       7: areturn

  public static byte[][] getSplitKeys(int);
    Code:
       0: iload_0
       1: getstatic     #152                // Field KEYS:[B
       4: arraylength
       5: if_icmpge     12
       8: iload_0
       9: goto          18
      12: getstatic     #152                // Field KEYS:[B
      15: arraylength
      16: iconst_1
      17: isub
      18: istore_0
      19: iload_0
      20: iconst_1
      21: isub
      22: anewarray     #59                 // class "[B"
      25: astore_1
      26: getstatic     #152                // Field KEYS:[B
      29: arraylength
      30: iload_0
      31: idiv
      32: istore_2
      33: iconst_1
      34: istore_3
      35: iconst_0
      36: istore        4
      38: iload         4
      40: aload_1
      41: arraylength
      42: if_icmpge     70
      45: aload_1
      46: iload         4
      48: iconst_1
      49: newarray       byte
      51: dup
      52: iconst_0
      53: getstatic     #152                // Field KEYS:[B
      56: iload_3
      57: baload
      58: bastore
      59: aastore
      60: iload_3
      61: iload_2
      62: iadd
      63: istore_3
      64: iinc          4, 1
      67: goto          38
      70: aload_1
      71: areturn

  public static void createTable(org.apache.hadoop.hbase.HBaseTestingUtility, org.apache.hadoop.hbase.TableName, byte[]...) throws java.io.IOException, java.lang.InterruptedException;
    Code:
       0: aload_0
       1: aload_1
       2: iconst_1
       3: aload_2
       4: invokestatic  #153                // Method createTable:(Lorg/apache/hadoop/hbase/HBaseTestingUtility;Lorg/apache/hadoop/hbase/TableName;I[[B)V
       7: return

  public static void createTable(org.apache.hadoop.hbase.HBaseTestingUtility, org.apache.hadoop.hbase.TableName, int, byte[]...) throws java.io.IOException, java.lang.InterruptedException;
    Code:
       0: aload_0
       1: aload_1
       2: iload_2
       3: getstatic     #152                // Field KEYS:[B
       6: arraylength
       7: aload_3
       8: invokestatic  #154                // Method createTable:(Lorg/apache/hadoop/hbase/HBaseTestingUtility;Lorg/apache/hadoop/hbase/TableName;II[[B)V
      11: return

  public static void createPreSplitTable(org.apache.hadoop.hbase.HBaseTestingUtility, org.apache.hadoop.hbase.TableName, int, byte[]...) throws java.io.IOException, java.lang.InterruptedException;
    Code:
       0: aload_0
       1: aload_1
       2: iconst_1
       3: iload_2
       4: aload_3
       5: invokestatic  #154                // Method createTable:(Lorg/apache/hadoop/hbase/HBaseTestingUtility;Lorg/apache/hadoop/hbase/TableName;II[[B)V
       8: return

  public static void loadData(org.apache.hadoop.hbase.HBaseTestingUtility, org.apache.hadoop.hbase.TableName, int, byte[]...) throws java.io.IOException, java.lang.InterruptedException;
    Code:
       0: aload_0
       1: invokevirtual #155                // Method org/apache/hadoop/hbase/HBaseTestingUtility.getConnection:()Lorg/apache/hadoop/hbase/client/Connection;
       4: aload_1
       5: invokeinterface #156,  2          // InterfaceMethod org/apache/hadoop/hbase/client/Connection.getBufferedMutator:(Lorg/apache/hadoop/hbase/TableName;)Lorg/apache/hadoop/hbase/client/BufferedMutator;
      10: astore        4
      12: aload_0
      13: aload         4
      15: iload_2
      16: aload_3
      17: invokestatic  #157                // Method loadData:(Lorg/apache/hadoop/hbase/HBaseTestingUtility;Lorg/apache/hadoop/hbase/client/BufferedMutator;I[[B)V
      20: return

  public static void loadData(org.apache.hadoop.hbase.HBaseTestingUtility, org.apache.hadoop.hbase.client.BufferedMutator, int, byte[]...) throws java.io.IOException, java.lang.InterruptedException;
    Code:
       0: iload_2
       1: getstatic     #152                // Field KEYS:[B
       4: arraylength
       5: if_icmplt     12
       8: iconst_1
       9: goto          13
      12: iconst_0
      13: invokestatic  #135                // Method org/junit/Assert.assertTrue:(Z)V
      16: getstatic     #152                // Field KEYS:[B
      19: astore        4
      21: aload         4
      23: arraylength
      24: istore        5
      26: iconst_0
      27: istore        6
      29: iload         6
      31: iload         5
      33: if_icmpge     116
      36: aload         4
      38: iload         6
      40: baload
      41: istore        7
      43: iconst_1
      44: newarray       byte
      46: dup
      47: iconst_0
      48: iload         7
      50: bastore
      51: astore        8
      53: invokestatic  #158                // Method java/lang/System.currentTimeMillis:()J
      56: invokestatic  #159                // Method org/apache/hadoop/hbase/util/Bytes.toBytes:(J)[B
      59: aload         8
      61: invokestatic  #160                // Method org/apache/hadoop/hbase/util/Bytes.add:([B[B)[B
      64: astore        9
      66: aload         8
      68: aload         9
      70: invokestatic  #161                // Method org/apache/hadoop/hbase/util/MD5Hash.getMD5AsHex:([B)Ljava/lang/String;
      73: invokestatic  #114                // Method org/apache/hadoop/hbase/util/Bytes.toBytes:(Ljava/lang/String;)[B
      76: invokestatic  #160                // Method org/apache/hadoop/hbase/util/Bytes.add:([B[B)[B
      79: astore        10
      81: aload_3
      82: astore        11
      84: aload         10
      86: astore        12
      88: aload         9
      90: astore        13
      92: aload_1
      93: aload         11
      95: aload         12
      97: aload         13
      99: invokestatic  #162                // Method createPut:([[B[B[B)Lorg/apache/hadoop/hbase/client/Put;
     102: invokeinterface #163,  2          // InterfaceMethod org/apache/hadoop/hbase/client/BufferedMutator.mutate:(Lorg/apache/hadoop/hbase/client/Mutation;)V
     107: iinc          2, -1
     110: iinc          6, 1
     113: goto          29
     116: iload_2
     117: iinc          2, -1
     120: ifle          177
     123: invokestatic  #158                // Method java/lang/System.currentTimeMillis:()J
     126: invokestatic  #159                // Method org/apache/hadoop/hbase/util/Bytes.toBytes:(J)[B
     129: iload_2
     130: invokestatic  #164                // Method org/apache/hadoop/hbase/util/Bytes.toBytes:(I)[B
     133: invokestatic  #160                // Method org/apache/hadoop/hbase/util/Bytes.add:([B[B)[B
     136: astore        4
     138: aload         4
     140: invokestatic  #161                // Method org/apache/hadoop/hbase/util/MD5Hash.getMD5AsHex:([B)Ljava/lang/String;
     143: invokestatic  #114                // Method org/apache/hadoop/hbase/util/Bytes.toBytes:(Ljava/lang/String;)[B
     146: astore        5
     148: aload_3
     149: astore        6
     151: aload         5
     153: astore        7
     155: aload         4
     157: astore        8
     159: aload_1
     160: aload         6
     162: aload         7
     164: aload         8
     166: invokestatic  #162                // Method createPut:([[B[B[B)Lorg/apache/hadoop/hbase/client/Put;
     169: invokeinterface #163,  2          // InterfaceMethod org/apache/hadoop/hbase/client/BufferedMutator.mutate:(Lorg/apache/hadoop/hbase/client/Mutation;)V
     174: goto          116
     177: aload_1
     178: invokeinterface #165,  1          // InterfaceMethod org/apache/hadoop/hbase/client/BufferedMutator.flush:()V
     183: aload_0
     184: aload_1
     185: invokeinterface #166,  1          // InterfaceMethod org/apache/hadoop/hbase/client/BufferedMutator.getName:()Lorg/apache/hadoop/hbase/TableName;
     190: invokestatic  #167                // Method waitForTableToBeOnline:(Lorg/apache/hadoop/hbase/HBaseTestingUtility;Lorg/apache/hadoop/hbase/TableName;)V
     193: return

  public static void deleteAllSnapshots(org.apache.hadoop.hbase.client.Admin) throws java.io.IOException;
    Code:
       0: aload_0
       1: invokeinterface #3,  1            // InterfaceMethod org/apache/hadoop/hbase/client/Admin.listSnapshots:()Ljava/util/List;
       6: invokeinterface #8,  1            // InterfaceMethod java/util/List.iterator:()Ljava/util/Iterator;
      11: astore_1
      12: aload_1
      13: invokeinterface #9,  1            // InterfaceMethod java/util/Iterator.hasNext:()Z
      18: ifeq          44
      21: aload_1
      22: invokeinterface #10,  1           // InterfaceMethod java/util/Iterator.next:()Ljava/lang/Object;
      27: checkcast     #11                 // class org/apache/hadoop/hbase/client/SnapshotDescription
      30: astore_2
      31: aload_0
      32: aload_2
      33: invokevirtual #12                 // Method org/apache/hadoop/hbase/client/SnapshotDescription.getName:()Ljava/lang/String;
      36: invokeinterface #99,  2           // InterfaceMethod org/apache/hadoop/hbase/client/Admin.deleteSnapshot:(Ljava/lang/String;)V
      41: goto          12
      44: aload_0
      45: invokestatic  #100                // Method assertNoSnapshots:(Lorg/apache/hadoop/hbase/client/Admin;)V
      48: return

  public static void deleteArchiveDirectory(org.apache.hadoop.hbase.HBaseTestingUtility) throws java.io.IOException;
    Code:
       0: aload_0
       1: invokevirtual #174                // Method org/apache/hadoop/hbase/HBaseTestingUtility.getMiniHBaseCluster:()Lorg/apache/hadoop/hbase/MiniHBaseCluster;
       4: invokevirtual #28                 // Method org/apache/hadoop/hbase/MiniHBaseCluster.getMaster:()Lorg/apache/hadoop/hbase/master/HMaster;
       7: invokevirtual #29                 // Method org/apache/hadoop/hbase/master/HMaster.getMasterFileSystem:()Lorg/apache/hadoop/hbase/master/MasterFileSystem;
      10: astore_1
      11: new           #175                // class org/apache/hadoop/fs/Path
      14: dup
      15: aload_1
      16: invokevirtual #30                 // Method org/apache/hadoop/hbase/master/MasterFileSystem.getRootDir:()Lorg/apache/hadoop/fs/Path;
      19: ldc           #177                // String archive
      21: invokespecial #178                // Method org/apache/hadoop/fs/Path."<init>":(Lorg/apache/hadoop/fs/Path;Ljava/lang/String;)V
      24: astore_2
      25: aload_1
      26: invokevirtual #32                 // Method org/apache/hadoop/hbase/master/MasterFileSystem.getFileSystem:()Lorg/apache/hadoop/fs/FileSystem;
      29: aload_2
      30: iconst_1
      31: invokevirtual #179                // Method org/apache/hadoop/fs/FileSystem.delete:(Lorg/apache/hadoop/fs/Path;Z)Z
      34: pop
      35: return

  public static void verifyRowCount(org.apache.hadoop.hbase.HBaseTestingUtility, org.apache.hadoop.hbase.TableName, long) throws java.io.IOException;
    Code:
       0: aload_0
       1: invokevirtual #155                // Method org/apache/hadoop/hbase/HBaseTestingUtility.getConnection:()Lorg/apache/hadoop/hbase/client/Connection;
       4: aload_1
       5: invokeinterface #180,  2          // InterfaceMethod org/apache/hadoop/hbase/client/Connection.getTable:(Lorg/apache/hadoop/hbase/TableName;)Lorg/apache/hadoop/hbase/client/Table;
      10: astore        4
      12: lload_2
      13: aload_0
      14: pop
      15: aload         4
      17: invokestatic  #181                // Method org/apache/hadoop/hbase/HBaseTestingUtility.countRows:(Lorg/apache/hadoop/hbase/client/Table;)I
      20: i2l
      21: invokestatic  #151                // Method org/junit/Assert.assertEquals:(JJ)V
      24: aload         4
      26: invokeinterface #182,  1          // InterfaceMethod org/apache/hadoop/hbase/client/Table.close:()V
      31: goto          46
      34: astore        5
      36: aload         4
      38: invokeinterface #182,  1          // InterfaceMethod org/apache/hadoop/hbase/client/Table.close:()V
      43: aload         5
      45: athrow
      46: return
    Exception table:
       from    to  target type
          12    24    34   any
          34    36    34   any

  public static void verifyReplicasCameOnline(org.apache.hadoop.hbase.TableName, org.apache.hadoop.hbase.client.Admin, int) throws java.io.IOException;
    Code:
       0: aload_1
       1: aload_0
       2: invokeinterface #66,  2           // InterfaceMethod org/apache/hadoop/hbase/client/Admin.getRegions:(Lorg/apache/hadoop/hbase/TableName;)Ljava/util/List;
       7: astore_3
       8: new           #183                // class java/util/HashSet
      11: dup
      12: invokespecial #184                // Method java/util/HashSet."<init>":()V
      15: astore        4
      17: aload_3
      18: invokeinterface #8,  1            // InterfaceMethod java/util/List.iterator:()Ljava/util/Iterator;
      23: astore        5
      25: aload         5
      27: invokeinterface #9,  1            // InterfaceMethod java/util/Iterator.hasNext:()Z
      32: ifeq          119
      35: aload         5
      37: invokeinterface #10,  1           // InterfaceMethod java/util/Iterator.next:()Ljava/lang/Object;
      42: checkcast     #78                 // class org/apache/hadoop/hbase/client/RegionInfo
      45: astore        6
      47: aload         4
      49: aload         6
      51: invokestatic  #185                // Method org/apache/hadoop/hbase/client/RegionReplicaUtil.getRegionInfoForDefaultReplica:(Lorg/apache/hadoop/hbase/client/RegionInfo;)Lorg/apache/hadoop/hbase/client/RegionInfo;
      54: invokevirtual #186                // Method java/util/HashSet.add:(Ljava/lang/Object;)Z
      57: pop
      58: iconst_0
      59: istore        7
      61: iload         7
      63: iload_2
      64: if_icmpge     116
      67: aload         6
      69: iload         7
      71: invokestatic  #187                // Method org/apache/hadoop/hbase/client/RegionReplicaUtil.getRegionInfoForReplica:(Lorg/apache/hadoop/hbase/client/RegionInfo;I)Lorg/apache/hadoop/hbase/client/RegionInfo;
      74: astore        8
      76: aload_3
      77: aload         8
      79: invokeinterface #188,  2          // InterfaceMethod java/util/List.contains:(Ljava/lang/Object;)Z
      84: ifne          110
      87: new           #39                 // class java/lang/StringBuilder
      90: dup
      91: invokespecial #40                 // Method java/lang/StringBuilder."<init>":()V
      94: aload         8
      96: invokevirtual #43                 // Method java/lang/StringBuilder.append:(Ljava/lang/Object;)Ljava/lang/StringBuilder;
      99: ldc           #189                // String  is not contained in the list of online regions
     101: invokevirtual #42                 // Method java/lang/StringBuilder.append:(Ljava/lang/String;)Ljava/lang/StringBuilder;
     104: invokevirtual #45                 // Method java/lang/StringBuilder.toString:()Ljava/lang/String;
     107: invokestatic  #102                // Method org/junit/Assert.fail:(Ljava/lang/String;)V
     110: iinc          7, 1
     113: goto          61
     116: goto          25
     119: invokestatic  #190                // Method getSplitKeys:()[[B
     122: arraylength
     123: iconst_1
     124: iadd
     125: i2l
     126: aload         4
     128: invokevirtual #191                // Method java/util/HashSet.size:()I
     131: i2l
     132: invokestatic  #151                // Method org/junit/Assert.assertEquals:(JJ)V
     135: return

  static {};
    Code:
       0: ldc           #192                // class org/apache/hadoop/hbase/snapshot/SnapshotTestingUtils
       2: invokestatic  #193                // Method org/slf4j/LoggerFactory.getLogger:(Ljava/lang/Class;)Lorg/slf4j/Logger;
       5: putstatic     #95                 // Field LOG:Lorg/slf4j/Logger;
       8: ldc           #194                // String 0123456
      10: invokestatic  #114                // Method org/apache/hadoop/hbase/util/Bytes.toBytes:(Ljava/lang/String;)[B
      13: putstatic     #152                // Field KEYS:[B
      16: return
}
