Compiled from "SnapshotDescriptionUtils.java"
final class org.apache.hadoop.hbase.snapshot.SnapshotDescriptionUtils$1 implements java.security.PrivilegedExceptionAction<org.apache.hbase.thirdparty.com.google.common.collect.ListMultimap<java.lang.String, org.apache.hadoop.hbase.security.access.UserPermission>> {
  final org.apache.hadoop.conf.Configuration val$conf;

  final org.apache.hadoop.hbase.shaded.protobuf.generated.SnapshotProtos$SnapshotDescription val$snapshot;

  org.apache.hadoop.hbase.snapshot.SnapshotDescriptionUtils$1(org.apache.hadoop.conf.Configuration, org.apache.hadoop.hbase.shaded.protobuf.generated.SnapshotProtos$SnapshotDescription);
    Code:
       0: aload_0
       1: aload_1
       2: putfield      #1                  // Field val$conf:Lorg/apache/hadoop/conf/Configuration;
       5: aload_0
       6: aload_2
       7: putfield      #2                  // Field val$snapshot:Lorg/apache/hadoop/hbase/shaded/protobuf/generated/SnapshotProtos$SnapshotDescription;
      10: aload_0
      11: invokespecial #3                  // Method java/lang/Object."<init>":()V
      14: return

  public org.apache.hbase.thirdparty.com.google.common.collect.ListMultimap<java.lang.String, org.apache.hadoop.hbase.security.access.UserPermission> run() throws java.lang.Exception;
    Code:
       0: aload_0
       1: getfield      #1                  // Field val$conf:Lorg/apache/hadoop/conf/Configuration;
       4: aload_0
       5: getfield      #2                  // Field val$snapshot:Lorg/apache/hadoop/hbase/shaded/protobuf/generated/SnapshotProtos$SnapshotDescription;
       8: invokevirtual #4                  // Method org/apache/hadoop/hbase/shaded/protobuf/generated/SnapshotProtos$SnapshotDescription.getTable:()Ljava/lang/String;
      11: invokestatic  #5                  // Method org/apache/hadoop/hbase/TableName.valueOf:(Ljava/lang/String;)Lorg/apache/hadoop/hbase/TableName;
      14: invokestatic  #6                  // Method org/apache/hadoop/hbase/security/access/PermissionStorage.getTablePermissions:(Lorg/apache/hadoop/conf/Configuration;Lorg/apache/hadoop/hbase/TableName;)Lorg/apache/hbase/thirdparty/com/google/common/collect/ListMultimap;
      17: areturn

  public java.lang.Object run() throws java.lang.Exception;
    Code:
       0: aload_0
       1: invokevirtual #7                  // Method run:()Lorg/apache/hbase/thirdparty/com/google/common/collect/ListMultimap;
       4: areturn
}
