Compiled from "SoftObjectPool.java"
public class org.apache.hadoop.hbase.util.SoftObjectPool<K, V> extends org.apache.hadoop.hbase.util.ObjectPool<K, V> {
  public org.apache.hadoop.hbase.util.SoftObjectPool(org.apache.hadoop.hbase.util.ObjectPool$ObjectFactory<K, V>);
    Code:
       0: aload_0
       1: aload_1
       2: invokespecial #1                  // Method org/apache/hadoop/hbase/util/ObjectPool."<init>":(Lorg/apache/hadoop/hbase/util/ObjectPool$ObjectFactory;)V
       5: return

  public org.apache.hadoop.hbase.util.SoftObjectPool(org.apache.hadoop.hbase.util.ObjectPool$ObjectFactory<K, V>, int);
    Code:
       0: aload_0
       1: aload_1
       2: iload_2
       3: invokespecial #2                  // Method org/apache/hadoop/hbase/util/ObjectPool."<init>":(Lorg/apache/hadoop/hbase/util/ObjectPool$ObjectFactory;I)V
       6: return

  public org.apache.hadoop.hbase.util.SoftObjectPool(org.apache.hadoop.hbase.util.ObjectPool$ObjectFactory<K, V>, int, int);
    Code:
       0: aload_0
       1: aload_1
       2: iload_2
       3: iload_3
       4: invokespecial #3                  // Method org/apache/hadoop/hbase/util/ObjectPool."<init>":(Lorg/apache/hadoop/hbase/util/ObjectPool$ObjectFactory;II)V
       7: return

  public java.lang.ref.Reference<V> createReference(K, V);
    Code:
       0: new           #4                  // class org/apache/hadoop/hbase/util/SoftObjectPool$SoftObjectReference
       3: dup
       4: aload_0
       5: aload_1
       6: aload_2
       7: invokespecial #5                  // Method org/apache/hadoop/hbase/util/SoftObjectPool$SoftObjectReference."<init>":(Lorg/apache/hadoop/hbase/util/SoftObjectPool;Ljava/lang/Object;Ljava/lang/Object;)V
      10: areturn

  public K getReferenceKey(java.lang.ref.Reference<V>);
    Code:
       0: aload_1
       1: checkcast     #4                  // class org/apache/hadoop/hbase/util/SoftObjectPool$SoftObjectReference
       4: getfield      #6                  // Field org/apache/hadoop/hbase/util/SoftObjectPool$SoftObjectReference.key:Ljava/lang/Object;
       7: areturn
}
