Compiled from "SpaceQuotaHelperForTests.java"
abstract class org.apache.hadoop.hbase.quotas.SpaceQuotaHelperForTests$SpaceQuotaSnapshotPredicate implements org.apache.hadoop.hbase.Waiter$Predicate<java.lang.Exception> {
  org.apache.hadoop.hbase.quotas.SpaceQuotaHelperForTests$SpaceQuotaSnapshotPredicate(org.apache.hadoop.hbase.client.Connection, org.apache.hadoop.hbase.TableName);
    Code:
       0: aload_0
       1: aload_1
       2: invokestatic  #1                  // Method java/util/Objects.requireNonNull:(Ljava/lang/Object;)Ljava/lang/Object;
       5: checkcast     #2                  // class org/apache/hadoop/hbase/client/Connection
       8: aload_2
       9: invokestatic  #1                  // Method java/util/Objects.requireNonNull:(Ljava/lang/Object;)Ljava/lang/Object;
      12: checkcast     #3                  // class org/apache/hadoop/hbase/TableName
      15: aconst_null
      16: invokespecial #4                  // Method "<init>":(Lorg/apache/hadoop/hbase/client/Connection;Lorg/apache/hadoop/hbase/TableName;Ljava/lang/String;)V
      19: return

  org.apache.hadoop.hbase.quotas.SpaceQuotaHelperForTests$SpaceQuotaSnapshotPredicate(org.apache.hadoop.hbase.client.Connection, java.lang.String);
    Code:
       0: aload_0
       1: aload_1
       2: invokestatic  #1                  // Method java/util/Objects.requireNonNull:(Ljava/lang/Object;)Ljava/lang/Object;
       5: checkcast     #2                  // class org/apache/hadoop/hbase/client/Connection
       8: aconst_null
       9: aload_2
      10: invokestatic  #1                  // Method java/util/Objects.requireNonNull:(Ljava/lang/Object;)Ljava/lang/Object;
      13: checkcast     #5                  // class java/lang/String
      16: invokespecial #4                  // Method "<init>":(Lorg/apache/hadoop/hbase/client/Connection;Lorg/apache/hadoop/hbase/TableName;Ljava/lang/String;)V
      19: return

  org.apache.hadoop.hbase.quotas.SpaceQuotaHelperForTests$SpaceQuotaSnapshotPredicate(org.apache.hadoop.hbase.client.Connection, org.apache.hadoop.hbase.TableName, java.lang.String);
    Code:
       0: aload_0
       1: invokespecial #6                  // Method java/lang/Object."<init>":()V
       4: aconst_null
       5: aload_2
       6: if_acmpeq     14
       9: aconst_null
      10: aload_3
      11: if_acmpne     24
      14: aconst_null
      15: aload_2
      16: if_acmpne     34
      19: aconst_null
      20: aload_3
      21: if_acmpne     34
      24: new           #7                  // class java/lang/IllegalArgumentException
      27: dup
      28: ldc           #8                  // String One of TableName and Namespace must be non-null, and the other null
      30: invokespecial #9                  // Method java/lang/IllegalArgumentException."<init>":(Ljava/lang/String;)V
      33: athrow
      34: aload_0
      35: aload_1
      36: putfield      #10                 // Field conn:Lorg/apache/hadoop/hbase/client/Connection;
      39: aload_0
      40: aload_2
      41: putfield      #11                 // Field tn:Lorg/apache/hadoop/hbase/TableName;
      44: aload_0
      45: aload_3
      46: putfield      #12                 // Field ns:Ljava/lang/String;
      49: return

  public boolean evaluate() throws java.lang.Exception;
    Code:
       0: aconst_null
       1: aload_0
       2: getfield      #12                 // Field ns:Ljava/lang/String;
       5: if_acmpne     33
       8: aload_0
       9: getfield      #10                 // Field conn:Lorg/apache/hadoop/hbase/client/Connection;
      12: invokeinterface #13,  1           // InterfaceMethod org/apache/hadoop/hbase/client/Connection.getAdmin:()Lorg/apache/hadoop/hbase/client/Admin;
      17: aload_0
      18: getfield      #11                 // Field tn:Lorg/apache/hadoop/hbase/TableName;
      21: invokeinterface #14,  2           // InterfaceMethod org/apache/hadoop/hbase/client/Admin.getCurrentSpaceQuotaSnapshot:(Lorg/apache/hadoop/hbase/TableName;)Lorg/apache/hadoop/hbase/quotas/SpaceQuotaSnapshotView;
      26: checkcast     #15                 // class org/apache/hadoop/hbase/quotas/SpaceQuotaSnapshot
      29: astore_1
      30: goto          55
      33: aload_0
      34: getfield      #10                 // Field conn:Lorg/apache/hadoop/hbase/client/Connection;
      37: invokeinterface #13,  1           // InterfaceMethod org/apache/hadoop/hbase/client/Connection.getAdmin:()Lorg/apache/hadoop/hbase/client/Admin;
      42: aload_0
      43: getfield      #12                 // Field ns:Ljava/lang/String;
      46: invokeinterface #16,  2           // InterfaceMethod org/apache/hadoop/hbase/client/Admin.getCurrentSpaceQuotaSnapshot:(Ljava/lang/String;)Lorg/apache/hadoop/hbase/quotas/SpaceQuotaSnapshotView;
      51: checkcast     #15                 // class org/apache/hadoop/hbase/quotas/SpaceQuotaSnapshot
      54: astore_1
      55: invokestatic  #17                 // Method org/apache/hadoop/hbase/quotas/SpaceQuotaHelperForTests.access$000:()Lorg/slf4j/Logger;
      58: new           #18                 // class java/lang/StringBuilder
      61: dup
      62: invokespecial #19                 // Method java/lang/StringBuilder."<init>":()V
      65: ldc           #20                 // String Saw quota snapshot for
      67: invokevirtual #21                 // Method java/lang/StringBuilder.append:(Ljava/lang/String;)Ljava/lang/StringBuilder;
      70: aconst_null
      71: aload_0
      72: getfield      #11                 // Field tn:Lorg/apache/hadoop/hbase/TableName;
      75: if_acmpne     85
      78: aload_0
      79: getfield      #12                 // Field ns:Ljava/lang/String;
      82: goto          89
      85: aload_0
      86: getfield      #11                 // Field tn:Lorg/apache/hadoop/hbase/TableName;
      89: invokevirtual #22                 // Method java/lang/StringBuilder.append:(Ljava/lang/Object;)Ljava/lang/StringBuilder;
      92: ldc           #23                 // String :
      94: invokevirtual #21                 // Method java/lang/StringBuilder.append:(Ljava/lang/String;)Ljava/lang/StringBuilder;
      97: aload_1
      98: invokevirtual #22                 // Method java/lang/StringBuilder.append:(Ljava/lang/Object;)Ljava/lang/StringBuilder;
     101: invokevirtual #24                 // Method java/lang/StringBuilder.toString:()Ljava/lang/String;
     104: invokeinterface #25,  2           // InterfaceMethod org/slf4j/Logger.debug:(Ljava/lang/String;)V
     109: aconst_null
     110: aload_1
     111: if_acmpne     116
     114: iconst_0
     115: ireturn
     116: aload_0
     117: aload_1
     118: invokevirtual #26                 // Method evaluate:(Lorg/apache/hadoop/hbase/quotas/SpaceQuotaSnapshot;)Z
     121: ireturn

  abstract boolean evaluate(org.apache.hadoop.hbase.quotas.SpaceQuotaSnapshot) throws java.lang.Exception;
}
