Compiled from "SpaceQuotaSnapshot.java"
public class org.apache.hadoop.hbase.quotas.SpaceQuotaSnapshot$SpaceQuotaStatus implements org.apache.hadoop.hbase.quotas.SpaceQuotaSnapshotView$SpaceQuotaStatusView {
  final java.util.Optional<org.apache.hadoop.hbase.quotas.SpaceViolationPolicy> policy;

  final boolean inViolation;

  public org.apache.hadoop.hbase.quotas.SpaceQuotaSnapshot$SpaceQuotaStatus(org.apache.hadoop.hbase.quotas.SpaceViolationPolicy);
    Code:
       0: aload_0
       1: aload_1
       2: invokestatic  #1                  // Method java/util/Objects.requireNonNull:(Ljava/lang/Object;)Ljava/lang/Object;
       5: checkcast     #2                  // class org/apache/hadoop/hbase/quotas/SpaceViolationPolicy
       8: iconst_1
       9: invokespecial #3                  // Method "<init>":(Lorg/apache/hadoop/hbase/quotas/SpaceViolationPolicy;Z)V
      12: return

  public java.util.Optional<org.apache.hadoop.hbase.quotas.SpaceViolationPolicy> getPolicy();
    Code:
       0: aload_0
       1: getfield      #6                  // Field policy:Ljava/util/Optional;
       4: areturn

  public boolean isInViolation();
    Code:
       0: aload_0
       1: getfield      #7                  // Field inViolation:Z
       4: ireturn

  public static org.apache.hadoop.hbase.quotas.SpaceQuotaSnapshot$SpaceQuotaStatus notInViolation();
    Code:
       0: getstatic     #8                  // Field NOT_IN_VIOLATION:Lorg/apache/hadoop/hbase/quotas/SpaceQuotaSnapshot$SpaceQuotaStatus;
       3: areturn

  public int hashCode();
    Code:
       0: new           #9                  // class org/apache/commons/lang3/builder/HashCodeBuilder
       3: dup
       4: invokespecial #10                 // Method org/apache/commons/lang3/builder/HashCodeBuilder."<init>":()V
       7: aload_0
       8: getfield      #6                  // Field policy:Ljava/util/Optional;
      11: ifnonnull     18
      14: iconst_0
      15: goto          25
      18: aload_0
      19: getfield      #6                  // Field policy:Ljava/util/Optional;
      22: invokevirtual #11                 // Method java/util/Optional.hashCode:()I
      25: invokevirtual #12                 // Method org/apache/commons/lang3/builder/HashCodeBuilder.append:(I)Lorg/apache/commons/lang3/builder/HashCodeBuilder;
      28: aload_0
      29: getfield      #7                  // Field inViolation:Z
      32: invokevirtual #13                 // Method org/apache/commons/lang3/builder/HashCodeBuilder.append:(Z)Lorg/apache/commons/lang3/builder/HashCodeBuilder;
      35: invokevirtual #14                 // Method org/apache/commons/lang3/builder/HashCodeBuilder.toHashCode:()I
      38: ireturn

  public boolean equals(java.lang.Object);
    Code:
       0: aload_1
       1: instanceof    #15                 // class org/apache/hadoop/hbase/quotas/SpaceQuotaSnapshot$SpaceQuotaStatus
       4: ifeq          43
       7: aload_1
       8: checkcast     #15                 // class org/apache/hadoop/hbase/quotas/SpaceQuotaSnapshot$SpaceQuotaStatus
      11: astore_2
      12: aload_0
      13: getfield      #6                  // Field policy:Ljava/util/Optional;
      16: aload_2
      17: getfield      #6                  // Field policy:Ljava/util/Optional;
      20: invokestatic  #16                 // Method java/util/Objects.equals:(Ljava/lang/Object;Ljava/lang/Object;)Z
      23: ifeq          41
      26: aload_0
      27: getfield      #7                  // Field inViolation:Z
      30: aload_2
      31: getfield      #7                  // Field inViolation:Z
      34: if_icmpne     41
      37: iconst_1
      38: goto          42
      41: iconst_0
      42: ireturn
      43: iconst_0
      44: ireturn

  public java.lang.String toString();
    Code:
       0: new           #17                 // class java/lang/StringBuilder
       3: dup
       4: aload_0
       5: invokevirtual #18                 // Method java/lang/Object.getClass:()Ljava/lang/Class;
       8: invokevirtual #19                 // Method java/lang/Class.getSimpleName:()Ljava/lang/String;
      11: invokespecial #20                 // Method java/lang/StringBuilder."<init>":(Ljava/lang/String;)V
      14: astore_1
      15: aload_1
      16: ldc           #21                 // String [policy=
      18: invokevirtual #22                 // Method java/lang/StringBuilder.append:(Ljava/lang/String;)Ljava/lang/StringBuilder;
      21: aload_0
      22: getfield      #6                  // Field policy:Ljava/util/Optional;
      25: invokevirtual #23                 // Method java/lang/StringBuilder.append:(Ljava/lang/Object;)Ljava/lang/StringBuilder;
      28: pop
      29: aload_1
      30: ldc           #24                 // String , inViolation=
      32: invokevirtual #22                 // Method java/lang/StringBuilder.append:(Ljava/lang/String;)Ljava/lang/StringBuilder;
      35: aload_0
      36: getfield      #7                  // Field inViolation:Z
      39: invokevirtual #25                 // Method java/lang/StringBuilder.append:(Z)Ljava/lang/StringBuilder;
      42: ldc           #26                 // String ]
      44: invokevirtual #22                 // Method java/lang/StringBuilder.append:(Ljava/lang/String;)Ljava/lang/StringBuilder;
      47: pop
      48: aload_1
      49: invokevirtual #27                 // Method java/lang/StringBuilder.toString:()Ljava/lang/String;
      52: areturn

  public static org.apache.hadoop.hbase.shaded.protobuf.generated.QuotaProtos$SpaceQuotaStatus toProto(org.apache.hadoop.hbase.quotas.SpaceQuotaSnapshot$SpaceQuotaStatus);
    Code:
       0: invokestatic  #28                 // Method org/apache/hadoop/hbase/shaded/protobuf/generated/QuotaProtos$SpaceQuotaStatus.newBuilder:()Lorg/apache/hadoop/hbase/shaded/protobuf/generated/QuotaProtos$SpaceQuotaStatus$Builder;
       3: astore_1
       4: aload_1
       5: aload_0
       6: getfield      #7                  // Field inViolation:Z
       9: invokevirtual #29                 // Method org/apache/hadoop/hbase/shaded/protobuf/generated/QuotaProtos$SpaceQuotaStatus$Builder.setInViolation:(Z)Lorg/apache/hadoop/hbase/shaded/protobuf/generated/QuotaProtos$SpaceQuotaStatus$Builder;
      12: pop
      13: aload_0
      14: invokevirtual #30                 // Method isInViolation:()Z
      17: ifeq          38
      20: aload_1
      21: aload_0
      22: invokevirtual #31                 // Method getPolicy:()Ljava/util/Optional;
      25: invokevirtual #32                 // Method java/util/Optional.get:()Ljava/lang/Object;
      28: checkcast     #2                  // class org/apache/hadoop/hbase/quotas/SpaceViolationPolicy
      31: invokestatic  #33                 // Method org/apache/hadoop/hbase/shaded/protobuf/ProtobufUtil.toProtoViolationPolicy:(Lorg/apache/hadoop/hbase/quotas/SpaceViolationPolicy;)Lorg/apache/hadoop/hbase/shaded/protobuf/generated/QuotaProtos$SpaceViolationPolicy;
      34: invokevirtual #34                 // Method org/apache/hadoop/hbase/shaded/protobuf/generated/QuotaProtos$SpaceQuotaStatus$Builder.setViolationPolicy:(Lorg/apache/hadoop/hbase/shaded/protobuf/generated/QuotaProtos$SpaceViolationPolicy;)Lorg/apache/hadoop/hbase/shaded/protobuf/generated/QuotaProtos$SpaceQuotaStatus$Builder;
      37: pop
      38: aload_1
      39: invokevirtual #35                 // Method org/apache/hadoop/hbase/shaded/protobuf/generated/QuotaProtos$SpaceQuotaStatus$Builder.build:()Lorg/apache/hadoop/hbase/shaded/protobuf/generated/QuotaProtos$SpaceQuotaStatus;
      42: areturn

  public static org.apache.hadoop.hbase.quotas.SpaceQuotaSnapshot$SpaceQuotaStatus toStatus(org.apache.hadoop.hbase.shaded.protobuf.generated.QuotaProtos$SpaceQuotaStatus);
    Code:
       0: aload_0
       1: invokevirtual #36                 // Method org/apache/hadoop/hbase/shaded/protobuf/generated/QuotaProtos$SpaceQuotaStatus.getInViolation:()Z
       4: ifeq          22
       7: new           #15                 // class org/apache/hadoop/hbase/quotas/SpaceQuotaSnapshot$SpaceQuotaStatus
      10: dup
      11: aload_0
      12: invokevirtual #37                 // Method org/apache/hadoop/hbase/shaded/protobuf/generated/QuotaProtos$SpaceQuotaStatus.getViolationPolicy:()Lorg/apache/hadoop/hbase/shaded/protobuf/generated/QuotaProtos$SpaceViolationPolicy;
      15: invokestatic  #38                 // Method org/apache/hadoop/hbase/shaded/protobuf/ProtobufUtil.toViolationPolicy:(Lorg/apache/hadoop/hbase/shaded/protobuf/generated/QuotaProtos$SpaceViolationPolicy;)Lorg/apache/hadoop/hbase/quotas/SpaceViolationPolicy;
      18: invokespecial #39                 // Method "<init>":(Lorg/apache/hadoop/hbase/quotas/SpaceViolationPolicy;)V
      21: areturn
      22: getstatic     #8                  // Field NOT_IN_VIOLATION:Lorg/apache/hadoop/hbase/quotas/SpaceQuotaSnapshot$SpaceQuotaStatus;
      25: areturn

  static {};
    Code:
       0: new           #15                 // class org/apache/hadoop/hbase/quotas/SpaceQuotaSnapshot$SpaceQuotaStatus
       3: dup
       4: aconst_null
       5: iconst_0
       6: invokespecial #3                  // Method "<init>":(Lorg/apache/hadoop/hbase/quotas/SpaceViolationPolicy;Z)V
       9: putstatic     #8                  // Field NOT_IN_VIOLATION:Lorg/apache/hadoop/hbase/quotas/SpaceQuotaSnapshot$SpaceQuotaStatus;
      12: return
}
