Compiled from "SpaceViolationPolicy.java"
public final class org.apache.hadoop.hbase.quotas.SpaceViolationPolicy extends java.lang.Enum<org.apache.hadoop.hbase.quotas.SpaceViolationPolicy> {
  public static final org.apache.hadoop.hbase.quotas.SpaceViolationPolicy DISABLE;

  public static final org.apache.hadoop.hbase.quotas.SpaceViolationPolicy NO_WRITES_COMPACTIONS;

  public static final org.apache.hadoop.hbase.quotas.SpaceViolationPolicy NO_WRITES;

  public static final org.apache.hadoop.hbase.quotas.SpaceViolationPolicy NO_INSERTS;

  public static org.apache.hadoop.hbase.quotas.SpaceViolationPolicy[] values();
    Code:
       0: getstatic     #1                  // Field $VALUES:[Lorg/apache/hadoop/hbase/quotas/SpaceViolationPolicy;
       3: invokevirtual #2                  // Method "[Lorg/apache/hadoop/hbase/quotas/SpaceViolationPolicy;".clone:()Ljava/lang/Object;
       6: checkcast     #3                  // class "[Lorg/apache/hadoop/hbase/quotas/SpaceViolationPolicy;"
       9: areturn

  public static org.apache.hadoop.hbase.quotas.SpaceViolationPolicy valueOf(java.lang.String);
    Code:
       0: ldc           #4                  // class org/apache/hadoop/hbase/quotas/SpaceViolationPolicy
       2: aload_0
       3: invokestatic  #5                  // Method java/lang/Enum.valueOf:(Ljava/lang/Class;Ljava/lang/String;)Ljava/lang/Enum;
       6: checkcast     #4                  // class org/apache/hadoop/hbase/quotas/SpaceViolationPolicy
       9: areturn

  static {};
    Code:
       0: new           #4                  // class org/apache/hadoop/hbase/quotas/SpaceViolationPolicy
       3: dup
       4: ldc           #7                  // String DISABLE
       6: iconst_0
       7: invokespecial #8                  // Method "<init>":(Ljava/lang/String;I)V
      10: putstatic     #9                  // Field DISABLE:Lorg/apache/hadoop/hbase/quotas/SpaceViolationPolicy;
      13: new           #4                  // class org/apache/hadoop/hbase/quotas/SpaceViolationPolicy
      16: dup
      17: ldc           #10                 // String NO_WRITES_COMPACTIONS
      19: iconst_1
      20: invokespecial #8                  // Method "<init>":(Ljava/lang/String;I)V
      23: putstatic     #11                 // Field NO_WRITES_COMPACTIONS:Lorg/apache/hadoop/hbase/quotas/SpaceViolationPolicy;
      26: new           #4                  // class org/apache/hadoop/hbase/quotas/SpaceViolationPolicy
      29: dup
      30: ldc           #12                 // String NO_WRITES
      32: iconst_2
      33: invokespecial #8                  // Method "<init>":(Ljava/lang/String;I)V
      36: putstatic     #13                 // Field NO_WRITES:Lorg/apache/hadoop/hbase/quotas/SpaceViolationPolicy;
      39: new           #4                  // class org/apache/hadoop/hbase/quotas/SpaceViolationPolicy
      42: dup
      43: ldc           #14                 // String NO_INSERTS
      45: iconst_3
      46: invokespecial #8                  // Method "<init>":(Ljava/lang/String;I)V
      49: putstatic     #15                 // Field NO_INSERTS:Lorg/apache/hadoop/hbase/quotas/SpaceViolationPolicy;
      52: iconst_4
      53: anewarray     #4                  // class org/apache/hadoop/hbase/quotas/SpaceViolationPolicy
      56: dup
      57: iconst_0
      58: getstatic     #9                  // Field DISABLE:Lorg/apache/hadoop/hbase/quotas/SpaceViolationPolicy;
      61: aastore
      62: dup
      63: iconst_1
      64: getstatic     #11                 // Field NO_WRITES_COMPACTIONS:Lorg/apache/hadoop/hbase/quotas/SpaceViolationPolicy;
      67: aastore
      68: dup
      69: iconst_2
      70: getstatic     #13                 // Field NO_WRITES:Lorg/apache/hadoop/hbase/quotas/SpaceViolationPolicy;
      73: aastore
      74: dup
      75: iconst_3
      76: getstatic     #15                 // Field NO_INSERTS:Lorg/apache/hadoop/hbase/quotas/SpaceViolationPolicy;
      79: aastore
      80: putstatic     #1                  // Field $VALUES:[Lorg/apache/hadoop/hbase/quotas/SpaceViolationPolicy;
      83: return
}
