Compiled from "SpanReceiverHost.java"
public class org.apache.hadoop.hbase.trace.SpanReceiverHost {
  public static final java.lang.String SPAN_RECEIVERS_CONF_KEY;

  public static org.apache.hadoop.hbase.trace.SpanReceiverHost getInstance(org.apache.hadoop.conf.Configuration);
    Code:
       0: getstatic     #1                  // Field org/apache/hadoop/hbase/trace/SpanReceiverHost$SingletonHolder.INSTANCE:Lorg/apache/hadoop/hbase/trace/SpanReceiverHost$SingletonHolder;
       3: getfield      #2                  // Field org/apache/hadoop/hbase/trace/SpanReceiverHost$SingletonHolder.lock:Ljava/lang/Object;
       6: dup
       7: astore_1
       8: monitorenter
       9: getstatic     #1                  // Field org/apache/hadoop/hbase/trace/SpanReceiverHost$SingletonHolder.INSTANCE:Lorg/apache/hadoop/hbase/trace/SpanReceiverHost$SingletonHolder;
      12: getfield      #3                  // Field org/apache/hadoop/hbase/trace/SpanReceiverHost$SingletonHolder.host:Lorg/apache/hadoop/hbase/trace/SpanReceiverHost;
      15: ifnull        27
      18: getstatic     #1                  // Field org/apache/hadoop/hbase/trace/SpanReceiverHost$SingletonHolder.INSTANCE:Lorg/apache/hadoop/hbase/trace/SpanReceiverHost$SingletonHolder;
      21: getfield      #3                  // Field org/apache/hadoop/hbase/trace/SpanReceiverHost$SingletonHolder.host:Lorg/apache/hadoop/hbase/trace/SpanReceiverHost;
      24: aload_1
      25: monitorexit
      26: areturn
      27: new           #4                  // class org/apache/hadoop/hbase/trace/SpanReceiverHost
      30: dup
      31: aload_0
      32: invokespecial #5                  // Method "<init>":(Lorg/apache/hadoop/conf/Configuration;)V
      35: astore_2
      36: aload_2
      37: invokevirtual #6                  // Method loadSpanReceivers:()V
      40: getstatic     #1                  // Field org/apache/hadoop/hbase/trace/SpanReceiverHost$SingletonHolder.INSTANCE:Lorg/apache/hadoop/hbase/trace/SpanReceiverHost$SingletonHolder;
      43: aload_2
      44: putfield      #3                  // Field org/apache/hadoop/hbase/trace/SpanReceiverHost$SingletonHolder.host:Lorg/apache/hadoop/hbase/trace/SpanReceiverHost;
      47: getstatic     #1                  // Field org/apache/hadoop/hbase/trace/SpanReceiverHost$SingletonHolder.INSTANCE:Lorg/apache/hadoop/hbase/trace/SpanReceiverHost$SingletonHolder;
      50: getfield      #3                  // Field org/apache/hadoop/hbase/trace/SpanReceiverHost$SingletonHolder.host:Lorg/apache/hadoop/hbase/trace/SpanReceiverHost;
      53: aload_1
      54: monitorexit
      55: areturn
      56: astore_3
      57: aload_1
      58: monitorexit
      59: aload_3
      60: athrow
    Exception table:
       from    to  target type
           9    26    56   any
          27    55    56   any
          56    59    56   any

  public static org.apache.hadoop.conf.Configuration getConfiguration();
    Code:
       0: getstatic     #1                  // Field org/apache/hadoop/hbase/trace/SpanReceiverHost$SingletonHolder.INSTANCE:Lorg/apache/hadoop/hbase/trace/SpanReceiverHost$SingletonHolder;
       3: getfield      #2                  // Field org/apache/hadoop/hbase/trace/SpanReceiverHost$SingletonHolder.lock:Ljava/lang/Object;
       6: dup
       7: astore_0
       8: monitorenter
       9: getstatic     #1                  // Field org/apache/hadoop/hbase/trace/SpanReceiverHost$SingletonHolder.INSTANCE:Lorg/apache/hadoop/hbase/trace/SpanReceiverHost$SingletonHolder;
      12: getfield      #3                  // Field org/apache/hadoop/hbase/trace/SpanReceiverHost$SingletonHolder.host:Lorg/apache/hadoop/hbase/trace/SpanReceiverHost;
      15: ifnull        30
      18: getstatic     #1                  // Field org/apache/hadoop/hbase/trace/SpanReceiverHost$SingletonHolder.INSTANCE:Lorg/apache/hadoop/hbase/trace/SpanReceiverHost$SingletonHolder;
      21: getfield      #3                  // Field org/apache/hadoop/hbase/trace/SpanReceiverHost$SingletonHolder.host:Lorg/apache/hadoop/hbase/trace/SpanReceiverHost;
      24: getfield      #7                  // Field conf:Lorg/apache/hadoop/conf/Configuration;
      27: ifnonnull     34
      30: aconst_null
      31: aload_0
      32: monitorexit
      33: areturn
      34: getstatic     #1                  // Field org/apache/hadoop/hbase/trace/SpanReceiverHost$SingletonHolder.INSTANCE:Lorg/apache/hadoop/hbase/trace/SpanReceiverHost$SingletonHolder;
      37: getfield      #3                  // Field org/apache/hadoop/hbase/trace/SpanReceiverHost$SingletonHolder.host:Lorg/apache/hadoop/hbase/trace/SpanReceiverHost;
      40: getfield      #7                  // Field conf:Lorg/apache/hadoop/conf/Configuration;
      43: aload_0
      44: monitorexit
      45: areturn
      46: astore_1
      47: aload_0
      48: monitorexit
      49: aload_1
      50: athrow
    Exception table:
       from    to  target type
           9    33    46   any
          34    45    46   any
          46    49    46   any

  org.apache.hadoop.hbase.trace.SpanReceiverHost(org.apache.hadoop.conf.Configuration);
    Code:
       0: aload_0
       1: invokespecial #8                  // Method java/lang/Object."<init>":()V
       4: aload_0
       5: iconst_0
       6: putfield      #9                  // Field closed:Z
       9: aload_0
      10: new           #10                 // class java/util/HashSet
      13: dup
      14: invokespecial #11                 // Method java/util/HashSet."<init>":()V
      17: putfield      #12                 // Field receivers:Ljava/util/Collection;
      20: aload_0
      21: aload_1
      22: putfield      #7                  // Field conf:Lorg/apache/hadoop/conf/Configuration;
      25: return

  public void loadSpanReceivers();
    Code:
       0: aload_0
       1: getfield      #7                  // Field conf:Lorg/apache/hadoop/conf/Configuration;
       4: ldc           #13                 // String hbase.trace.spanreceiver.classes
       6: invokevirtual #14                 // Method org/apache/hadoop/conf/Configuration.getStrings:(Ljava/lang/String;)[Ljava/lang/String;
       9: astore_1
      10: aload_1
      11: ifnull        19
      14: aload_1
      15: arraylength
      16: ifne          20
      19: return
      20: new           #15                 // class org/apache/htrace/core/SpanReceiver$Builder
      23: dup
      24: new           #16                 // class org/apache/hadoop/hbase/trace/HBaseHTraceConfiguration
      27: dup
      28: aload_0
      29: getfield      #7                  // Field conf:Lorg/apache/hadoop/conf/Configuration;
      32: invokespecial #17                 // Method org/apache/hadoop/hbase/trace/HBaseHTraceConfiguration."<init>":(Lorg/apache/hadoop/conf/Configuration;)V
      35: invokespecial #18                 // Method org/apache/htrace/core/SpanReceiver$Builder."<init>":(Lorg/apache/htrace/core/HTraceConfiguration;)V
      38: astore_2
      39: aload_1
      40: astore_3
      41: aload_3
      42: arraylength
      43: istore        4
      45: iconst_0
      46: istore        5
      48: iload         5
      50: iload         4
      52: if_icmpge     135
      55: aload_3
      56: iload         5
      58: aaload
      59: astore        6
      61: aload         6
      63: invokevirtual #19                 // Method java/lang/String.trim:()Ljava/lang/String;
      66: astore        6
      68: aload_2
      69: aload         6
      71: invokevirtual #20                 // Method org/apache/htrace/core/SpanReceiver$Builder.className:(Ljava/lang/String;)Lorg/apache/htrace/core/SpanReceiver$Builder;
      74: invokevirtual #21                 // Method org/apache/htrace/core/SpanReceiver$Builder.build:()Lorg/apache/htrace/core/SpanReceiver;
      77: astore        7
      79: aload         7
      81: ifnull        129
      84: aload_0
      85: getfield      #12                 // Field receivers:Ljava/util/Collection;
      88: aload         7
      90: invokeinterface #22,  2           // InterfaceMethod java/util/Collection.add:(Ljava/lang/Object;)Z
      95: pop
      96: getstatic     #23                 // Field LOG:Lorg/slf4j/Logger;
      99: new           #24                 // class java/lang/StringBuilder
     102: dup
     103: invokespecial #25                 // Method java/lang/StringBuilder."<init>":()V
     106: ldc           #26                 // String SpanReceiver
     108: invokevirtual #27                 // Method java/lang/StringBuilder.append:(Ljava/lang/String;)Ljava/lang/StringBuilder;
     111: aload         6
     113: invokevirtual #27                 // Method java/lang/StringBuilder.append:(Ljava/lang/String;)Ljava/lang/StringBuilder;
     116: ldc           #28                 // String  was loaded successfully.
     118: invokevirtual #27                 // Method java/lang/StringBuilder.append:(Ljava/lang/String;)Ljava/lang/StringBuilder;
     121: invokevirtual #29                 // Method java/lang/StringBuilder.toString:()Ljava/lang/String;
     124: invokeinterface #30,  2           // InterfaceMethod org/slf4j/Logger.info:(Ljava/lang/String;)V
     129: iinc          5, 1
     132: goto          48
     135: aload_0
     136: getfield      #12                 // Field receivers:Ljava/util/Collection;
     139: invokeinterface #31,  1           // InterfaceMethod java/util/Collection.iterator:()Ljava/util/Iterator;
     144: astore_3
     145: aload_3
     146: invokeinterface #32,  1           // InterfaceMethod java/util/Iterator.hasNext:()Z
     151: ifeq          174
     154: aload_3
     155: invokeinterface #33,  1           // InterfaceMethod java/util/Iterator.next:()Ljava/lang/Object;
     160: checkcast     #34                 // class org/apache/htrace/core/SpanReceiver
     163: astore        4
     165: aload         4
     167: invokestatic  #35                 // Method org/apache/hadoop/hbase/trace/TraceUtil.addReceiver:(Lorg/apache/htrace/core/SpanReceiver;)Z
     170: pop
     171: goto          145
     174: return

  public synchronized void closeReceivers();
    Code:
       0: aload_0
       1: getfield      #9                  // Field closed:Z
       4: ifeq          8
       7: return
       8: aload_0
       9: iconst_1
      10: putfield      #9                  // Field closed:Z
      13: aload_0
      14: getfield      #12                 // Field receivers:Ljava/util/Collection;
      17: invokeinterface #31,  1           // InterfaceMethod java/util/Collection.iterator:()Ljava/util/Iterator;
      22: astore_1
      23: aload_1
      24: invokeinterface #32,  1           // InterfaceMethod java/util/Iterator.hasNext:()Z
      29: ifeq          84
      32: aload_1
      33: invokeinterface #33,  1           // InterfaceMethod java/util/Iterator.next:()Ljava/lang/Object;
      38: checkcast     #34                 // class org/apache/htrace/core/SpanReceiver
      41: astore_2
      42: aload_2
      43: invokevirtual #36                 // Method org/apache/htrace/core/SpanReceiver.close:()V
      46: goto          81
      49: astore_3
      50: getstatic     #23                 // Field LOG:Lorg/slf4j/Logger;
      53: new           #24                 // class java/lang/StringBuilder
      56: dup
      57: invokespecial #25                 // Method java/lang/StringBuilder."<init>":()V
      60: ldc           #38                 // String Unable to close SpanReceiver correctly:
      62: invokevirtual #27                 // Method java/lang/StringBuilder.append:(Ljava/lang/String;)Ljava/lang/StringBuilder;
      65: aload_3
      66: invokevirtual #39                 // Method java/io/IOException.getMessage:()Ljava/lang/String;
      69: invokevirtual #27                 // Method java/lang/StringBuilder.append:(Ljava/lang/String;)Ljava/lang/StringBuilder;
      72: invokevirtual #29                 // Method java/lang/StringBuilder.toString:()Ljava/lang/String;
      75: aload_3
      76: invokeinterface #40,  3           // InterfaceMethod org/slf4j/Logger.warn:(Ljava/lang/String;Ljava/lang/Throwable;)V
      81: goto          23
      84: return
    Exception table:
       from    to  target type
          42    46    49   Class java/io/IOException

  static {};
    Code:
       0: ldc           #4                  // class org/apache/hadoop/hbase/trace/SpanReceiverHost
       2: invokestatic  #41                 // Method org/slf4j/LoggerFactory.getLogger:(Ljava/lang/Class;)Lorg/slf4j/Logger;
       5: putstatic     #23                 // Field LOG:Lorg/slf4j/Logger;
       8: return
}
