Compiled from "SplitLogManager.java"
public final class org.apache.hadoop.hbase.master.SplitLogManager$TerminationStatus extends java.lang.Enum<org.apache.hadoop.hbase.master.SplitLogManager$TerminationStatus> {
  public static final org.apache.hadoop.hbase.master.SplitLogManager$TerminationStatus IN_PROGRESS;

  public static final org.apache.hadoop.hbase.master.SplitLogManager$TerminationStatus SUCCESS;

  public static final org.apache.hadoop.hbase.master.SplitLogManager$TerminationStatus FAILURE;

  public static final org.apache.hadoop.hbase.master.SplitLogManager$TerminationStatus DELETED;

  final java.lang.String statusMsg;

  public static org.apache.hadoop.hbase.master.SplitLogManager$TerminationStatus[] values();
    Code:
       0: getstatic     #1                  // Field $VALUES:[Lorg/apache/hadoop/hbase/master/SplitLogManager$TerminationStatus;
       3: invokevirtual #2                  // Method "[Lorg/apache/hadoop/hbase/master/SplitLogManager$TerminationStatus;".clone:()Ljava/lang/Object;
       6: checkcast     #3                  // class "[Lorg/apache/hadoop/hbase/master/SplitLogManager$TerminationStatus;"
       9: areturn

  public static org.apache.hadoop.hbase.master.SplitLogManager$TerminationStatus valueOf(java.lang.String);
    Code:
       0: ldc           #4                  // class org/apache/hadoop/hbase/master/SplitLogManager$TerminationStatus
       2: aload_0
       3: invokestatic  #5                  // Method java/lang/Enum.valueOf:(Ljava/lang/Class;Ljava/lang/String;)Ljava/lang/Enum;
       6: checkcast     #4                  // class org/apache/hadoop/hbase/master/SplitLogManager$TerminationStatus
       9: areturn

  public java.lang.String toString();
    Code:
       0: aload_0
       1: getfield      #7                  // Field statusMsg:Ljava/lang/String;
       4: areturn

  static {};
    Code:
       0: new           #4                  // class org/apache/hadoop/hbase/master/SplitLogManager$TerminationStatus
       3: dup
       4: ldc           #8                  // String IN_PROGRESS
       6: iconst_0
       7: ldc           #9                  // String in_progress
       9: invokespecial #10                 // Method "<init>":(Ljava/lang/String;ILjava/lang/String;)V
      12: putstatic     #11                 // Field IN_PROGRESS:Lorg/apache/hadoop/hbase/master/SplitLogManager$TerminationStatus;
      15: new           #4                  // class org/apache/hadoop/hbase/master/SplitLogManager$TerminationStatus
      18: dup
      19: ldc           #12                 // String SUCCESS
      21: iconst_1
      22: ldc           #13                 // String success
      24: invokespecial #10                 // Method "<init>":(Ljava/lang/String;ILjava/lang/String;)V
      27: putstatic     #14                 // Field SUCCESS:Lorg/apache/hadoop/hbase/master/SplitLogManager$TerminationStatus;
      30: new           #4                  // class org/apache/hadoop/hbase/master/SplitLogManager$TerminationStatus
      33: dup
      34: ldc           #15                 // String FAILURE
      36: iconst_2
      37: ldc           #16                 // String failure
      39: invokespecial #10                 // Method "<init>":(Ljava/lang/String;ILjava/lang/String;)V
      42: putstatic     #17                 // Field FAILURE:Lorg/apache/hadoop/hbase/master/SplitLogManager$TerminationStatus;
      45: new           #4                  // class org/apache/hadoop/hbase/master/SplitLogManager$TerminationStatus
      48: dup
      49: ldc           #18                 // String DELETED
      51: iconst_3
      52: ldc           #19                 // String deleted
      54: invokespecial #10                 // Method "<init>":(Ljava/lang/String;ILjava/lang/String;)V
      57: putstatic     #20                 // Field DELETED:Lorg/apache/hadoop/hbase/master/SplitLogManager$TerminationStatus;
      60: iconst_4
      61: anewarray     #4                  // class org/apache/hadoop/hbase/master/SplitLogManager$TerminationStatus
      64: dup
      65: iconst_0
      66: getstatic     #11                 // Field IN_PROGRESS:Lorg/apache/hadoop/hbase/master/SplitLogManager$TerminationStatus;
      69: aastore
      70: dup
      71: iconst_1
      72: getstatic     #14                 // Field SUCCESS:Lorg/apache/hadoop/hbase/master/SplitLogManager$TerminationStatus;
      75: aastore
      76: dup
      77: iconst_2
      78: getstatic     #17                 // Field FAILURE:Lorg/apache/hadoop/hbase/master/SplitLogManager$TerminationStatus;
      81: aastore
      82: dup
      83: iconst_3
      84: getstatic     #20                 // Field DELETED:Lorg/apache/hadoop/hbase/master/SplitLogManager$TerminationStatus;
      87: aastore
      88: putstatic     #1                  // Field $VALUES:[Lorg/apache/hadoop/hbase/master/SplitLogManager$TerminationStatus;
      91: return
}
