Compiled from "SplitWALCallable.java"
public class org.apache.hadoop.hbase.regionserver.SplitWALCallable implements org.apache.hadoop.hbase.procedure2.RSProcedureCallable {
  public org.apache.hadoop.hbase.regionserver.SplitWALCallable();
    Code:
       0: aload_0
       1: invokespecial #1                  // Method java/lang/Object."<init>":()V
       4: aload_0
       5: new           #2                  // class org/apache/hadoop/hbase/util/KeyLocker
       8: dup
       9: invokespecial #3                  // Method org/apache/hadoop/hbase/util/KeyLocker."<init>":()V
      12: putfield      #4                  // Field splitWALLocks:Lorg/apache/hadoop/hbase/util/KeyLocker;
      15: aload_0
      16: aconst_null
      17: putfield      #5                  // Field splitWALLock:Ljava/util/concurrent/locks/Lock;
      20: return

  public void init(byte[], org.apache.hadoop.hbase.regionserver.HRegionServer);
    Code:
       0: aload_0
       1: aload_2
       2: putfield      #6                  // Field rs:Lorg/apache/hadoop/hbase/regionserver/HRegionServer;
       5: aload_1
       6: invokestatic  #7                  // Method org/apache/hadoop/hbase/shaded/protobuf/generated/MasterProcedureProtos$SplitWALParameter.parseFrom:([B)Lorg/apache/hadoop/hbase/shaded/protobuf/generated/MasterProcedureProtos$SplitWALParameter;
       9: astore_3
      10: aload_0
      11: aload_3
      12: invokevirtual #8                  // Method org/apache/hadoop/hbase/shaded/protobuf/generated/MasterProcedureProtos$SplitWALParameter.getWalPath:()Ljava/lang/String;
      15: putfield      #9                  // Field walPath:Ljava/lang/String;
      18: goto          38
      21: astore_3
      22: getstatic     #11                 // Field LOG:Lorg/slf4j/Logger;
      25: ldc           #12                 // String parse proto buffer of split WAL request failed
      27: aload_3
      28: invokeinterface #13,  3           // InterfaceMethod org/slf4j/Logger.error:(Ljava/lang/String;Ljava/lang/Throwable;)V
      33: aload_0
      34: aload_3
      35: putfield      #14                 // Field initError:Ljava/lang/Exception;
      38: return
    Exception table:
       from    to  target type
           0    18    21   Class org/apache/hbase/thirdparty/com/google/protobuf/InvalidProtocolBufferException

  public org.apache.hadoop.hbase.executor.EventType getEventType();
    Code:
       0: getstatic     #15                 // Field org/apache/hadoop/hbase/executor/EventType.RS_LOG_REPLAY:Lorg/apache/hadoop/hbase/executor/EventType;
       3: areturn

  public java.lang.Void call() throws java.lang.Exception;
    Code:
       0: aload_0
       1: getfield      #14                 // Field initError:Ljava/lang/Exception;
       4: ifnull        12
       7: aload_0
       8: getfield      #14                 // Field initError:Ljava/lang/Exception;
      11: athrow
      12: aload_0
      13: aload_0
      14: getfield      #4                  // Field splitWALLocks:Lorg/apache/hadoop/hbase/util/KeyLocker;
      17: aload_0
      18: getfield      #9                  // Field walPath:Ljava/lang/String;
      21: invokevirtual #16                 // Method org/apache/hadoop/hbase/util/KeyLocker.acquireLock:(Ljava/lang/Object;)Ljava/util/concurrent/locks/ReentrantLock;
      24: putfield      #5                  // Field splitWALLock:Ljava/util/concurrent/locks/Lock;
      27: aload_0
      28: invokespecial #17                 // Method splitWal:()V
      31: getstatic     #11                 // Field LOG:Lorg/slf4j/Logger;
      34: ldc           #18                 // String split WAL {} succeed.
      36: aload_0
      37: getfield      #9                  // Field walPath:Ljava/lang/String;
      40: invokeinterface #19,  3           // InterfaceMethod org/slf4j/Logger.info:(Ljava/lang/String;Ljava/lang/Object;)V
      45: aload_0
      46: getfield      #5                  // Field splitWALLock:Ljava/util/concurrent/locks/Lock;
      49: invokeinterface #20,  1           // InterfaceMethod java/util/concurrent/locks/Lock.unlock:()V
      54: goto          87
      57: astore_1
      58: getstatic     #11                 // Field LOG:Lorg/slf4j/Logger;
      61: ldc           #22                 // String failed to split WAL {}.
      63: aload_0
      64: getfield      #9                  // Field walPath:Ljava/lang/String;
      67: aload_1
      68: invokeinterface #23,  4           // InterfaceMethod org/slf4j/Logger.warn:(Ljava/lang/String;Ljava/lang/Object;Ljava/lang/Object;)V
      73: aload_1
      74: athrow
      75: astore_2
      76: aload_0
      77: getfield      #5                  // Field splitWALLock:Ljava/util/concurrent/locks/Lock;
      80: invokeinterface #20,  1           // InterfaceMethod java/util/concurrent/locks/Lock.unlock:()V
      85: aload_2
      86: athrow
      87: aconst_null
      88: areturn
    Exception table:
       from    to  target type
          27    45    57   Class java/io/IOException
          27    45    75   any
          57    76    75   any

  public java.lang.String getWalPath();
    Code:
       0: aload_0
       1: getfield      #9                  // Field walPath:Ljava/lang/String;
       4: areturn

  public java.lang.Object call() throws java.lang.Exception;
    Code:
       0: aload_0
       1: invokevirtual #35                 // Method call:()Ljava/lang/Void;
       4: areturn

  static {};
    Code:
       0: ldc           #36                 // class org/apache/hadoop/hbase/regionserver/SplitWALCallable
       2: invokestatic  #37                 // Method org/slf4j/LoggerFactory.getLogger:(Ljava/lang/Class;)Lorg/slf4j/Logger;
       5: putstatic     #11                 // Field LOG:Lorg/slf4j/Logger;
       8: return
}
