Compiled from "SplitLogCounters.java"
public class org.apache.hadoop.hbase.SplitLogCounters {
  public static final java.util.concurrent.atomic.LongAdder tot_mgr_log_split_batch_start;

  public static final java.util.concurrent.atomic.LongAdder tot_mgr_log_split_batch_success;

  public static final java.util.concurrent.atomic.LongAdder tot_mgr_log_split_batch_err;

  public static final java.util.concurrent.atomic.LongAdder tot_mgr_new_unexpected_wals;

  public static final java.util.concurrent.atomic.LongAdder tot_mgr_log_split_start;

  public static final java.util.concurrent.atomic.LongAdder tot_mgr_log_split_success;

  public static final java.util.concurrent.atomic.LongAdder tot_mgr_log_split_err;

  public static final java.util.concurrent.atomic.LongAdder tot_mgr_node_create_queued;

  public static final java.util.concurrent.atomic.LongAdder tot_mgr_node_create_result;

  public static final java.util.concurrent.atomic.LongAdder tot_mgr_node_already_exists;

  public static final java.util.concurrent.atomic.LongAdder tot_mgr_node_create_err;

  public static final java.util.concurrent.atomic.LongAdder tot_mgr_node_create_retry;

  public static final java.util.concurrent.atomic.LongAdder tot_mgr_get_data_queued;

  public static final java.util.concurrent.atomic.LongAdder tot_mgr_get_data_result;

  public static final java.util.concurrent.atomic.LongAdder tot_mgr_get_data_nonode;

  public static final java.util.concurrent.atomic.LongAdder tot_mgr_get_data_err;

  public static final java.util.concurrent.atomic.LongAdder tot_mgr_get_data_retry;

  public static final java.util.concurrent.atomic.LongAdder tot_mgr_node_delete_queued;

  public static final java.util.concurrent.atomic.LongAdder tot_mgr_node_delete_result;

  public static final java.util.concurrent.atomic.LongAdder tot_mgr_node_delete_err;

  public static final java.util.concurrent.atomic.LongAdder tot_mgr_resubmit;

  public static final java.util.concurrent.atomic.LongAdder tot_mgr_resubmit_failed;

  public static final java.util.concurrent.atomic.LongAdder tot_mgr_null_data;

  public static final java.util.concurrent.atomic.LongAdder tot_mgr_orphan_task_acquired;

  public static final java.util.concurrent.atomic.LongAdder tot_mgr_wait_for_zk_delete;

  public static final java.util.concurrent.atomic.LongAdder tot_mgr_unacquired_orphan_done;

  public static final java.util.concurrent.atomic.LongAdder tot_mgr_resubmit_threshold_reached;

  public static final java.util.concurrent.atomic.LongAdder tot_mgr_missing_state_in_delete;

  public static final java.util.concurrent.atomic.LongAdder tot_mgr_heartbeat;

  public static final java.util.concurrent.atomic.LongAdder tot_mgr_rescan;

  public static final java.util.concurrent.atomic.LongAdder tot_mgr_rescan_deleted;

  public static final java.util.concurrent.atomic.LongAdder tot_mgr_task_deleted;

  public static final java.util.concurrent.atomic.LongAdder tot_mgr_resubmit_unassigned;

  public static final java.util.concurrent.atomic.LongAdder tot_mgr_relist_logdir;

  public static final java.util.concurrent.atomic.LongAdder tot_mgr_resubmit_dead_server_task;

  public static final java.util.concurrent.atomic.LongAdder tot_mgr_resubmit_force;

  public static final java.util.concurrent.atomic.LongAdder tot_wkr_failed_to_grab_task_no_data;

  public static final java.util.concurrent.atomic.LongAdder tot_wkr_failed_to_grab_task_exception;

  public static final java.util.concurrent.atomic.LongAdder tot_wkr_failed_to_grab_task_owned;

  public static final java.util.concurrent.atomic.LongAdder tot_wkr_failed_to_grab_task_lost_race;

  public static final java.util.concurrent.atomic.LongAdder tot_wkr_task_acquired;

  public static final java.util.concurrent.atomic.LongAdder tot_wkr_task_resigned;

  public static final java.util.concurrent.atomic.LongAdder tot_wkr_task_done;

  public static final java.util.concurrent.atomic.LongAdder tot_wkr_task_err;

  public static final java.util.concurrent.atomic.LongAdder tot_wkr_task_heartbeat;

  public static final java.util.concurrent.atomic.LongAdder tot_wkr_task_acquired_rescan;

  public static final java.util.concurrent.atomic.LongAdder tot_wkr_get_data_queued;

  public static final java.util.concurrent.atomic.LongAdder tot_wkr_get_data_result;

  public static final java.util.concurrent.atomic.LongAdder tot_wkr_get_data_retry;

  public static final java.util.concurrent.atomic.LongAdder tot_wkr_preempt_task;

  public static final java.util.concurrent.atomic.LongAdder tot_wkr_task_heartbeat_failed;

  public static final java.util.concurrent.atomic.LongAdder tot_wkr_final_transition_failed;

  public static final java.util.concurrent.atomic.LongAdder tot_wkr_task_grabing;

  public org.apache.hadoop.hbase.SplitLogCounters();
    Code:
       0: aload_0
       1: invokespecial #1                  // Method java/lang/Object."<init>":()V
       4: return

  public static void resetCounters() throws java.lang.Exception;
    Code:
       0: ldc           #2                  // class org/apache/hadoop/hbase/SplitLogCounters
       2: astore_0
       3: aload_0
       4: invokevirtual #3                  // Method java/lang/Class.getDeclaredFields:()[Ljava/lang/reflect/Field;
       7: astore_1
       8: aload_1
       9: arraylength
      10: istore_2
      11: iconst_0
      12: istore_3
      13: iload_3
      14: iload_2
      15: if_icmpge     62
      18: aload_1
      19: iload_3
      20: aaload
      21: astore        4
      23: aload         4
      25: invokevirtual #4                  // Method java/lang/reflect/Field.isSynthetic:()Z
      28: ifne          56
      31: ldc           #5                  // class java/util/concurrent/atomic/LongAdder
      33: aload         4
      35: invokevirtual #6                  // Method java/lang/reflect/Field.getType:()Ljava/lang/Class;
      38: invokevirtual #7                  // Method java/lang/Class.isAssignableFrom:(Ljava/lang/Class;)Z
      41: ifeq          56
      44: aload         4
      46: aconst_null
      47: invokevirtual #8                  // Method java/lang/reflect/Field.get:(Ljava/lang/Object;)Ljava/lang/Object;
      50: checkcast     #5                  // class java/util/concurrent/atomic/LongAdder
      53: invokevirtual #9                  // Method java/util/concurrent/atomic/LongAdder.reset:()V
      56: iinc          3, 1
      59: goto          13
      62: return

  static {};
    Code:
       0: new           #5                  // class java/util/concurrent/atomic/LongAdder
       3: dup
       4: invokespecial #10                 // Method java/util/concurrent/atomic/LongAdder."<init>":()V
       7: putstatic     #11                 // Field tot_mgr_log_split_batch_start:Ljava/util/concurrent/atomic/LongAdder;
      10: new           #5                  // class java/util/concurrent/atomic/LongAdder
      13: dup
      14: invokespecial #10                 // Method java/util/concurrent/atomic/LongAdder."<init>":()V
      17: putstatic     #12                 // Field tot_mgr_log_split_batch_success:Ljava/util/concurrent/atomic/LongAdder;
      20: new           #5                  // class java/util/concurrent/atomic/LongAdder
      23: dup
      24: invokespecial #10                 // Method java/util/concurrent/atomic/LongAdder."<init>":()V
      27: putstatic     #13                 // Field tot_mgr_log_split_batch_err:Ljava/util/concurrent/atomic/LongAdder;
      30: new           #5                  // class java/util/concurrent/atomic/LongAdder
      33: dup
      34: invokespecial #10                 // Method java/util/concurrent/atomic/LongAdder."<init>":()V
      37: putstatic     #14                 // Field tot_mgr_new_unexpected_wals:Ljava/util/concurrent/atomic/LongAdder;
      40: new           #5                  // class java/util/concurrent/atomic/LongAdder
      43: dup
      44: invokespecial #10                 // Method java/util/concurrent/atomic/LongAdder."<init>":()V
      47: putstatic     #15                 // Field tot_mgr_log_split_start:Ljava/util/concurrent/atomic/LongAdder;
      50: new           #5                  // class java/util/concurrent/atomic/LongAdder
      53: dup
      54: invokespecial #10                 // Method java/util/concurrent/atomic/LongAdder."<init>":()V
      57: putstatic     #16                 // Field tot_mgr_log_split_success:Ljava/util/concurrent/atomic/LongAdder;
      60: new           #5                  // class java/util/concurrent/atomic/LongAdder
      63: dup
      64: invokespecial #10                 // Method java/util/concurrent/atomic/LongAdder."<init>":()V
      67: putstatic     #17                 // Field tot_mgr_log_split_err:Ljava/util/concurrent/atomic/LongAdder;
      70: new           #5                  // class java/util/concurrent/atomic/LongAdder
      73: dup
      74: invokespecial #10                 // Method java/util/concurrent/atomic/LongAdder."<init>":()V
      77: putstatic     #18                 // Field tot_mgr_node_create_queued:Ljava/util/concurrent/atomic/LongAdder;
      80: new           #5                  // class java/util/concurrent/atomic/LongAdder
      83: dup
      84: invokespecial #10                 // Method java/util/concurrent/atomic/LongAdder."<init>":()V
      87: putstatic     #19                 // Field tot_mgr_node_create_result:Ljava/util/concurrent/atomic/LongAdder;
      90: new           #5                  // class java/util/concurrent/atomic/LongAdder
      93: dup
      94: invokespecial #10                 // Method java/util/concurrent/atomic/LongAdder."<init>":()V
      97: putstatic     #20                 // Field tot_mgr_node_already_exists:Ljava/util/concurrent/atomic/LongAdder;
     100: new           #5                  // class java/util/concurrent/atomic/LongAdder
     103: dup
     104: invokespecial #10                 // Method java/util/concurrent/atomic/LongAdder."<init>":()V
     107: putstatic     #21                 // Field tot_mgr_node_create_err:Ljava/util/concurrent/atomic/LongAdder;
     110: new           #5                  // class java/util/concurrent/atomic/LongAdder
     113: dup
     114: invokespecial #10                 // Method java/util/concurrent/atomic/LongAdder."<init>":()V
     117: putstatic     #22                 // Field tot_mgr_node_create_retry:Ljava/util/concurrent/atomic/LongAdder;
     120: new           #5                  // class java/util/concurrent/atomic/LongAdder
     123: dup
     124: invokespecial #10                 // Method java/util/concurrent/atomic/LongAdder."<init>":()V
     127: putstatic     #23                 // Field tot_mgr_get_data_queued:Ljava/util/concurrent/atomic/LongAdder;
     130: new           #5                  // class java/util/concurrent/atomic/LongAdder
     133: dup
     134: invokespecial #10                 // Method java/util/concurrent/atomic/LongAdder."<init>":()V
     137: putstatic     #24                 // Field tot_mgr_get_data_result:Ljava/util/concurrent/atomic/LongAdder;
     140: new           #5                  // class java/util/concurrent/atomic/LongAdder
     143: dup
     144: invokespecial #10                 // Method java/util/concurrent/atomic/LongAdder."<init>":()V
     147: putstatic     #25                 // Field tot_mgr_get_data_nonode:Ljava/util/concurrent/atomic/LongAdder;
     150: new           #5                  // class java/util/concurrent/atomic/LongAdder
     153: dup
     154: invokespecial #10                 // Method java/util/concurrent/atomic/LongAdder."<init>":()V
     157: putstatic     #26                 // Field tot_mgr_get_data_err:Ljava/util/concurrent/atomic/LongAdder;
     160: new           #5                  // class java/util/concurrent/atomic/LongAdder
     163: dup
     164: invokespecial #10                 // Method java/util/concurrent/atomic/LongAdder."<init>":()V
     167: putstatic     #27                 // Field tot_mgr_get_data_retry:Ljava/util/concurrent/atomic/LongAdder;
     170: new           #5                  // class java/util/concurrent/atomic/LongAdder
     173: dup
     174: invokespecial #10                 // Method java/util/concurrent/atomic/LongAdder."<init>":()V
     177: putstatic     #28                 // Field tot_mgr_node_delete_queued:Ljava/util/concurrent/atomic/LongAdder;
     180: new           #5                  // class java/util/concurrent/atomic/LongAdder
     183: dup
     184: invokespecial #10                 // Method java/util/concurrent/atomic/LongAdder."<init>":()V
     187: putstatic     #29                 // Field tot_mgr_node_delete_result:Ljava/util/concurrent/atomic/LongAdder;
     190: new           #5                  // class java/util/concurrent/atomic/LongAdder
     193: dup
     194: invokespecial #10                 // Method java/util/concurrent/atomic/LongAdder."<init>":()V
     197: putstatic     #30                 // Field tot_mgr_node_delete_err:Ljava/util/concurrent/atomic/LongAdder;
     200: new           #5                  // class java/util/concurrent/atomic/LongAdder
     203: dup
     204: invokespecial #10                 // Method java/util/concurrent/atomic/LongAdder."<init>":()V
     207: putstatic     #31                 // Field tot_mgr_resubmit:Ljava/util/concurrent/atomic/LongAdder;
     210: new           #5                  // class java/util/concurrent/atomic/LongAdder
     213: dup
     214: invokespecial #10                 // Method java/util/concurrent/atomic/LongAdder."<init>":()V
     217: putstatic     #32                 // Field tot_mgr_resubmit_failed:Ljava/util/concurrent/atomic/LongAdder;
     220: new           #5                  // class java/util/concurrent/atomic/LongAdder
     223: dup
     224: invokespecial #10                 // Method java/util/concurrent/atomic/LongAdder."<init>":()V
     227: putstatic     #33                 // Field tot_mgr_null_data:Ljava/util/concurrent/atomic/LongAdder;
     230: new           #5                  // class java/util/concurrent/atomic/LongAdder
     233: dup
     234: invokespecial #10                 // Method java/util/concurrent/atomic/LongAdder."<init>":()V
     237: putstatic     #34                 // Field tot_mgr_orphan_task_acquired:Ljava/util/concurrent/atomic/LongAdder;
     240: new           #5                  // class java/util/concurrent/atomic/LongAdder
     243: dup
     244: invokespecial #10                 // Method java/util/concurrent/atomic/LongAdder."<init>":()V
     247: putstatic     #35                 // Field tot_mgr_wait_for_zk_delete:Ljava/util/concurrent/atomic/LongAdder;
     250: new           #5                  // class java/util/concurrent/atomic/LongAdder
     253: dup
     254: invokespecial #10                 // Method java/util/concurrent/atomic/LongAdder."<init>":()V
     257: putstatic     #36                 // Field tot_mgr_unacquired_orphan_done:Ljava/util/concurrent/atomic/LongAdder;
     260: new           #5                  // class java/util/concurrent/atomic/LongAdder
     263: dup
     264: invokespecial #10                 // Method java/util/concurrent/atomic/LongAdder."<init>":()V
     267: putstatic     #37                 // Field tot_mgr_resubmit_threshold_reached:Ljava/util/concurrent/atomic/LongAdder;
     270: new           #5                  // class java/util/concurrent/atomic/LongAdder
     273: dup
     274: invokespecial #10                 // Method java/util/concurrent/atomic/LongAdder."<init>":()V
     277: putstatic     #38                 // Field tot_mgr_missing_state_in_delete:Ljava/util/concurrent/atomic/LongAdder;
     280: new           #5                  // class java/util/concurrent/atomic/LongAdder
     283: dup
     284: invokespecial #10                 // Method java/util/concurrent/atomic/LongAdder."<init>":()V
     287: putstatic     #39                 // Field tot_mgr_heartbeat:Ljava/util/concurrent/atomic/LongAdder;
     290: new           #5                  // class java/util/concurrent/atomic/LongAdder
     293: dup
     294: invokespecial #10                 // Method java/util/concurrent/atomic/LongAdder."<init>":()V
     297: putstatic     #40                 // Field tot_mgr_rescan:Ljava/util/concurrent/atomic/LongAdder;
     300: new           #5                  // class java/util/concurrent/atomic/LongAdder
     303: dup
     304: invokespecial #10                 // Method java/util/concurrent/atomic/LongAdder."<init>":()V
     307: putstatic     #41                 // Field tot_mgr_rescan_deleted:Ljava/util/concurrent/atomic/LongAdder;
     310: new           #5                  // class java/util/concurrent/atomic/LongAdder
     313: dup
     314: invokespecial #10                 // Method java/util/concurrent/atomic/LongAdder."<init>":()V
     317: putstatic     #42                 // Field tot_mgr_task_deleted:Ljava/util/concurrent/atomic/LongAdder;
     320: new           #5                  // class java/util/concurrent/atomic/LongAdder
     323: dup
     324: invokespecial #10                 // Method java/util/concurrent/atomic/LongAdder."<init>":()V
     327: putstatic     #43                 // Field tot_mgr_resubmit_unassigned:Ljava/util/concurrent/atomic/LongAdder;
     330: new           #5                  // class java/util/concurrent/atomic/LongAdder
     333: dup
     334: invokespecial #10                 // Method java/util/concurrent/atomic/LongAdder."<init>":()V
     337: putstatic     #44                 // Field tot_mgr_relist_logdir:Ljava/util/concurrent/atomic/LongAdder;
     340: new           #5                  // class java/util/concurrent/atomic/LongAdder
     343: dup
     344: invokespecial #10                 // Method java/util/concurrent/atomic/LongAdder."<init>":()V
     347: putstatic     #45                 // Field tot_mgr_resubmit_dead_server_task:Ljava/util/concurrent/atomic/LongAdder;
     350: new           #5                  // class java/util/concurrent/atomic/LongAdder
     353: dup
     354: invokespecial #10                 // Method java/util/concurrent/atomic/LongAdder."<init>":()V
     357: putstatic     #46                 // Field tot_mgr_resubmit_force:Ljava/util/concurrent/atomic/LongAdder;
     360: new           #5                  // class java/util/concurrent/atomic/LongAdder
     363: dup
     364: invokespecial #10                 // Method java/util/concurrent/atomic/LongAdder."<init>":()V
     367: putstatic     #47                 // Field tot_wkr_failed_to_grab_task_no_data:Ljava/util/concurrent/atomic/LongAdder;
     370: new           #5                  // class java/util/concurrent/atomic/LongAdder
     373: dup
     374: invokespecial #10                 // Method java/util/concurrent/atomic/LongAdder."<init>":()V
     377: putstatic     #48                 // Field tot_wkr_failed_to_grab_task_exception:Ljava/util/concurrent/atomic/LongAdder;
     380: new           #5                  // class java/util/concurrent/atomic/LongAdder
     383: dup
     384: invokespecial #10                 // Method java/util/concurrent/atomic/LongAdder."<init>":()V
     387: putstatic     #49                 // Field tot_wkr_failed_to_grab_task_owned:Ljava/util/concurrent/atomic/LongAdder;
     390: new           #5                  // class java/util/concurrent/atomic/LongAdder
     393: dup
     394: invokespecial #10                 // Method java/util/concurrent/atomic/LongAdder."<init>":()V
     397: putstatic     #50                 // Field tot_wkr_failed_to_grab_task_lost_race:Ljava/util/concurrent/atomic/LongAdder;
     400: new           #5                  // class java/util/concurrent/atomic/LongAdder
     403: dup
     404: invokespecial #10                 // Method java/util/concurrent/atomic/LongAdder."<init>":()V
     407: putstatic     #51                 // Field tot_wkr_task_acquired:Ljava/util/concurrent/atomic/LongAdder;
     410: new           #5                  // class java/util/concurrent/atomic/LongAdder
     413: dup
     414: invokespecial #10                 // Method java/util/concurrent/atomic/LongAdder."<init>":()V
     417: putstatic     #52                 // Field tot_wkr_task_resigned:Ljava/util/concurrent/atomic/LongAdder;
     420: new           #5                  // class java/util/concurrent/atomic/LongAdder
     423: dup
     424: invokespecial #10                 // Method java/util/concurrent/atomic/LongAdder."<init>":()V
     427: putstatic     #53                 // Field tot_wkr_task_done:Ljava/util/concurrent/atomic/LongAdder;
     430: new           #5                  // class java/util/concurrent/atomic/LongAdder
     433: dup
     434: invokespecial #10                 // Method java/util/concurrent/atomic/LongAdder."<init>":()V
     437: putstatic     #54                 // Field tot_wkr_task_err:Ljava/util/concurrent/atomic/LongAdder;
     440: new           #5                  // class java/util/concurrent/atomic/LongAdder
     443: dup
     444: invokespecial #10                 // Method java/util/concurrent/atomic/LongAdder."<init>":()V
     447: putstatic     #55                 // Field tot_wkr_task_heartbeat:Ljava/util/concurrent/atomic/LongAdder;
     450: new           #5                  // class java/util/concurrent/atomic/LongAdder
     453: dup
     454: invokespecial #10                 // Method java/util/concurrent/atomic/LongAdder."<init>":()V
     457: putstatic     #56                 // Field tot_wkr_task_acquired_rescan:Ljava/util/concurrent/atomic/LongAdder;
     460: new           #5                  // class java/util/concurrent/atomic/LongAdder
     463: dup
     464: invokespecial #10                 // Method java/util/concurrent/atomic/LongAdder."<init>":()V
     467: putstatic     #57                 // Field tot_wkr_get_data_queued:Ljava/util/concurrent/atomic/LongAdder;
     470: new           #5                  // class java/util/concurrent/atomic/LongAdder
     473: dup
     474: invokespecial #10                 // Method java/util/concurrent/atomic/LongAdder."<init>":()V
     477: putstatic     #58                 // Field tot_wkr_get_data_result:Ljava/util/concurrent/atomic/LongAdder;
     480: new           #5                  // class java/util/concurrent/atomic/LongAdder
     483: dup
     484: invokespecial #10                 // Method java/util/concurrent/atomic/LongAdder."<init>":()V
     487: putstatic     #59                 // Field tot_wkr_get_data_retry:Ljava/util/concurrent/atomic/LongAdder;
     490: new           #5                  // class java/util/concurrent/atomic/LongAdder
     493: dup
     494: invokespecial #10                 // Method java/util/concurrent/atomic/LongAdder."<init>":()V
     497: putstatic     #60                 // Field tot_wkr_preempt_task:Ljava/util/concurrent/atomic/LongAdder;
     500: new           #5                  // class java/util/concurrent/atomic/LongAdder
     503: dup
     504: invokespecial #10                 // Method java/util/concurrent/atomic/LongAdder."<init>":()V
     507: putstatic     #61                 // Field tot_wkr_task_heartbeat_failed:Ljava/util/concurrent/atomic/LongAdder;
     510: new           #5                  // class java/util/concurrent/atomic/LongAdder
     513: dup
     514: invokespecial #10                 // Method java/util/concurrent/atomic/LongAdder."<init>":()V
     517: putstatic     #62                 // Field tot_wkr_final_transition_failed:Ljava/util/concurrent/atomic/LongAdder;
     520: new           #5                  // class java/util/concurrent/atomic/LongAdder
     523: dup
     524: invokespecial #10                 // Method java/util/concurrent/atomic/LongAdder."<init>":()V
     527: putstatic     #63                 // Field tot_wkr_task_grabing:Ljava/util/concurrent/atomic/LongAdder;
     530: return
}
