Compiled from "SplitRequest.java"
class org.apache.hadoop.hbase.regionserver.SplitRequest implements java.lang.Runnable {
  org.apache.hadoop.hbase.regionserver.SplitRequest(org.apache.hadoop.hbase.regionserver.Region, byte[], org.apache.hadoop.hbase.regionserver.HRegionServer, org.apache.hadoop.hbase.security.User);
    Code:
       0: aload_0
       1: invokespecial #2                  // Method java/lang/Object."<init>":()V
       4: aload_3
       5: invokestatic  #3                  // Method org/apache/hbase/thirdparty/com/google/common/base/Preconditions.checkNotNull:(Ljava/lang/Object;)Ljava/lang/Object;
       8: pop
       9: aload_0
      10: aload_1
      11: invokeinterface #4,  1            // InterfaceMethod org/apache/hadoop/hbase/regionserver/Region.getRegionInfo:()Lorg/apache/hadoop/hbase/client/RegionInfo;
      16: putfield      #5                  // Field parent:Lorg/apache/hadoop/hbase/client/RegionInfo;
      19: aload_0
      20: aload_2
      21: putfield      #6                  // Field midKey:[B
      24: aload_0
      25: aload_3
      26: putfield      #7                  // Field server:Lorg/apache/hadoop/hbase/regionserver/HRegionServer;
      29: aload_0
      30: aload         4
      32: putfield      #8                  // Field user:Lorg/apache/hadoop/hbase/security/User;
      35: return

  public java.lang.String toString();
    Code:
       0: new           #9                  // class java/lang/StringBuilder
       3: dup
       4: invokespecial #10                 // Method java/lang/StringBuilder."<init>":()V
       7: ldc           #11                 // String regionName=
       9: invokevirtual #12                 // Method java/lang/StringBuilder.append:(Ljava/lang/String;)Ljava/lang/StringBuilder;
      12: aload_0
      13: getfield      #5                  // Field parent:Lorg/apache/hadoop/hbase/client/RegionInfo;
      16: invokevirtual #13                 // Method java/lang/StringBuilder.append:(Ljava/lang/Object;)Ljava/lang/StringBuilder;
      19: ldc           #14                 // String , midKey=
      21: invokevirtual #12                 // Method java/lang/StringBuilder.append:(Ljava/lang/String;)Ljava/lang/StringBuilder;
      24: aload_0
      25: getfield      #6                  // Field midKey:[B
      28: invokestatic  #15                 // Method org/apache/hadoop/hbase/util/Bytes.toStringBinary:([B)Ljava/lang/String;
      31: invokevirtual #12                 // Method java/lang/StringBuilder.append:(Ljava/lang/String;)Ljava/lang/StringBuilder;
      34: invokevirtual #16                 // Method java/lang/StringBuilder.toString:()Ljava/lang/String;
      37: areturn

  public void run();
    Code:
       0: aload_0
       1: getfield      #7                  // Field server:Lorg/apache/hadoop/hbase/regionserver/HRegionServer;
       4: invokevirtual #42                 // Method org/apache/hadoop/hbase/regionserver/HRegionServer.isStopping:()Z
       7: ifne          20
      10: aload_0
      11: getfield      #7                  // Field server:Lorg/apache/hadoop/hbase/regionserver/HRegionServer;
      14: invokevirtual #43                 // Method org/apache/hadoop/hbase/regionserver/HRegionServer.isStopped:()Z
      17: ifeq          69
      20: getstatic     #38                 // Field LOG:Lorg/slf4j/Logger;
      23: new           #9                  // class java/lang/StringBuilder
      26: dup
      27: invokespecial #10                 // Method java/lang/StringBuilder."<init>":()V
      30: ldc           #44                 // String Skipping split because server is stopping=
      32: invokevirtual #12                 // Method java/lang/StringBuilder.append:(Ljava/lang/String;)Ljava/lang/StringBuilder;
      35: aload_0
      36: getfield      #7                  // Field server:Lorg/apache/hadoop/hbase/regionserver/HRegionServer;
      39: invokevirtual #42                 // Method org/apache/hadoop/hbase/regionserver/HRegionServer.isStopping:()Z
      42: invokevirtual #45                 // Method java/lang/StringBuilder.append:(Z)Ljava/lang/StringBuilder;
      45: ldc           #46                 // String  or stopped=
      47: invokevirtual #12                 // Method java/lang/StringBuilder.append:(Ljava/lang/String;)Ljava/lang/StringBuilder;
      50: aload_0
      51: getfield      #7                  // Field server:Lorg/apache/hadoop/hbase/regionserver/HRegionServer;
      54: invokevirtual #43                 // Method org/apache/hadoop/hbase/regionserver/HRegionServer.isStopped:()Z
      57: invokevirtual #45                 // Method java/lang/StringBuilder.append:(Z)Ljava/lang/StringBuilder;
      60: invokevirtual #16                 // Method java/lang/StringBuilder.toString:()Ljava/lang/String;
      63: invokeinterface #47,  2           // InterfaceMethod org/slf4j/Logger.debug:(Ljava/lang/String;)V
      68: return
      69: aload_0
      70: invokespecial #48                 // Method doSplitting:()V
      73: return

  static void access$000(org.apache.hadoop.hbase.regionserver.SplitRequest);
    Code:
       0: aload_0
       1: invokespecial #1                  // Method requestRegionSplit:()V
       4: return

  static {};
    Code:
       0: ldc           #49                 // class org/apache/hadoop/hbase/regionserver/SplitRequest
       2: invokestatic  #50                 // Method org/slf4j/LoggerFactory.getLogger:(Ljava/lang/Class;)Lorg/slf4j/Logger;
       5: putstatic     #38                 // Field LOG:Lorg/slf4j/Logger;
       8: return
}
