Compiled from "SplitTableRegionProcedure.java"
class org.apache.hadoop.hbase.master.assignment.SplitTableRegionProcedure$StoreFileSplitter implements java.util.concurrent.Callable<org.apache.hadoop.hbase.util.Pair<org.apache.hadoop.fs.Path, org.apache.hadoop.fs.Path>> {
  final org.apache.hadoop.hbase.master.assignment.SplitTableRegionProcedure this$0;

  public org.apache.hadoop.hbase.master.assignment.SplitTableRegionProcedure$StoreFileSplitter(org.apache.hadoop.hbase.master.assignment.SplitTableRegionProcedure, org.apache.hadoop.hbase.regionserver.HRegionFileSystem, byte[], org.apache.hadoop.hbase.regionserver.HStoreFile);
    Code:
       0: aload_0
       1: aload_1
       2: putfield      #1                  // Field this$0:Lorg/apache/hadoop/hbase/master/assignment/SplitTableRegionProcedure;
       5: aload_0
       6: invokespecial #2                  // Method java/lang/Object."<init>":()V
       9: aload_0
      10: aload_2
      11: putfield      #3                  // Field regionFs:Lorg/apache/hadoop/hbase/regionserver/HRegionFileSystem;
      14: aload_0
      15: aload         4
      17: putfield      #4                  // Field sf:Lorg/apache/hadoop/hbase/regionserver/HStoreFile;
      20: aload_0
      21: aload_3
      22: putfield      #5                  // Field family:[B
      25: return

  public org.apache.hadoop.hbase.util.Pair<org.apache.hadoop.fs.Path, org.apache.hadoop.fs.Path> call() throws java.io.IOException;
    Code:
       0: aload_0
       1: getfield      #1                  // Field this$0:Lorg/apache/hadoop/hbase/master/assignment/SplitTableRegionProcedure;
       4: aload_0
       5: getfield      #3                  // Field regionFs:Lorg/apache/hadoop/hbase/regionserver/HRegionFileSystem;
       8: aload_0
       9: getfield      #5                  // Field family:[B
      12: aload_0
      13: getfield      #4                  // Field sf:Lorg/apache/hadoop/hbase/regionserver/HStoreFile;
      16: invokestatic  #6                  // Method org/apache/hadoop/hbase/master/assignment/SplitTableRegionProcedure.access$000:(Lorg/apache/hadoop/hbase/master/assignment/SplitTableRegionProcedure;Lorg/apache/hadoop/hbase/regionserver/HRegionFileSystem;[BLorg/apache/hadoop/hbase/regionserver/HStoreFile;)Lorg/apache/hadoop/hbase/util/Pair;
      19: areturn

  public java.lang.Object call() throws java.lang.Exception;
    Code:
       0: aload_0
       1: invokevirtual #7                  // Method call:()Lorg/apache/hadoop/hbase/util/Pair;
       4: areturn
}
