Compiled from "SslRMIServerSocketFactorySecure.java"
public class org.apache.hadoop.hbase.SslRMIServerSocketFactorySecure extends javax.rmi.ssl.SslRMIServerSocketFactory {
  public org.apache.hadoop.hbase.SslRMIServerSocketFactorySecure();
    Code:
       0: aload_0
       1: invokespecial #1                  // Method javax/rmi/ssl/SslRMIServerSocketFactory."<init>":()V
       4: return

  public java.net.ServerSocket createServerSocket(int) throws java.io.IOException;
    Code:
       0: new           #2                  // class org/apache/hadoop/hbase/SslRMIServerSocketFactorySecure$1
       3: dup
       4: aload_0
       5: iload_1
       6: invokespecial #3                  // Method org/apache/hadoop/hbase/SslRMIServerSocketFactorySecure$1."<init>":(Lorg/apache/hadoop/hbase/SslRMIServerSocketFactorySecure;I)V
       9: areturn
}
