Compiled from "SslRMIServerSocketFactorySecure.java"
class org.apache.hadoop.hbase.SslRMIServerSocketFactorySecure$1 extends java.net.ServerSocket {
  final org.apache.hadoop.hbase.SslRMIServerSocketFactorySecure this$0;

  org.apache.hadoop.hbase.SslRMIServerSocketFactorySecure$1(org.apache.hadoop.hbase.SslRMIServerSocketFactorySecure, int);
    Code:
       0: aload_0
       1: aload_1
       2: putfield      #1                  // Field this$0:Lorg/apache/hadoop/hbase/SslRMIServerSocketFactorySecure;
       5: aload_0
       6: iload_2
       7: invokespecial #2                  // Method java/net/ServerSocket."<init>":(I)V
      10: return

  public java.net.Socket accept() throws java.io.IOException;
    Code:
       0: aload_0
       1: invokespecial #3                  // Method java/net/ServerSocket.accept:()Ljava/net/Socket;
       4: astore_1
       5: invokestatic  #4                  // Method javax/net/ssl/SSLSocketFactory.getDefault:()Ljavax/net/SocketFactory;
       8: checkcast     #5                  // class javax/net/ssl/SSLSocketFactory
      11: astore_2
      12: aload_2
      13: aload_1
      14: aload_1
      15: invokevirtual #6                  // Method java/net/Socket.getInetAddress:()Ljava/net/InetAddress;
      18: invokevirtual #7                  // Method java/net/InetAddress.getHostName:()Ljava/lang/String;
      21: aload_1
      22: invokevirtual #8                  // Method java/net/Socket.getPort:()I
      25: iconst_1
      26: invokevirtual #9                  // Method javax/net/ssl/SSLSocketFactory.createSocket:(Ljava/net/Socket;Ljava/lang/String;IZ)Ljava/net/Socket;
      29: checkcast     #10                 // class javax/net/ssl/SSLSocket
      32: astore_3
      33: aload_3
      34: iconst_0
      35: invokevirtual #11                 // Method javax/net/ssl/SSLSocket.setUseClientMode:(Z)V
      38: aload_3
      39: iconst_0
      40: invokevirtual #12                 // Method javax/net/ssl/SSLSocket.setNeedClientAuth:(Z)V
      43: new           #13                 // class java/util/ArrayList
      46: dup
      47: invokespecial #14                 // Method java/util/ArrayList."<init>":()V
      50: astore        4
      52: aload_3
      53: invokevirtual #15                 // Method javax/net/ssl/SSLSocket.getEnabledProtocols:()[Ljava/lang/String;
      56: astore        5
      58: aload         5
      60: arraylength
      61: istore        6
      63: iconst_0
      64: istore        7
      66: iload         7
      68: iload         6
      70: if_icmpge     104
      73: aload         5
      75: iload         7
      77: aaload
      78: astore        8
      80: aload         8
      82: ldc           #16                 // String SSLv3
      84: invokevirtual #17                 // Method java/lang/String.contains:(Ljava/lang/CharSequence;)Z
      87: ifne          98
      90: aload         4
      92: aload         8
      94: invokevirtual #18                 // Method java/util/ArrayList.add:(Ljava/lang/Object;)Z
      97: pop
      98: iinc          7, 1
     101: goto          66
     104: aload_3
     105: aload         4
     107: aload         4
     109: invokevirtual #19                 // Method java/util/ArrayList.size:()I
     112: anewarray     #20                 // class java/lang/String
     115: invokevirtual #21                 // Method java/util/ArrayList.toArray:([Ljava/lang/Object;)[Ljava/lang/Object;
     118: checkcast     #22                 // class "[Ljava/lang/String;"
     121: invokevirtual #23                 // Method javax/net/ssl/SSLSocket.setEnabledProtocols:([Ljava/lang/String;)V
     124: aload_3
     125: areturn
}
