Compiled from "StartMiniClusterOption.java"
public final class org.apache.hadoop.hbase.StartMiniClusterOption$Builder {
  public org.apache.hadoop.hbase.StartMiniClusterOption build();
    Code:
       0: aload_0
       1: getfield      #9                  // Field dataNodeHosts:[Ljava/lang/String;
       4: ifnull        24
       7: aload_0
       8: getfield      #9                  // Field dataNodeHosts:[Ljava/lang/String;
      11: arraylength
      12: ifeq          24
      15: aload_0
      16: aload_0
      17: getfield      #9                  // Field dataNodeHosts:[Ljava/lang/String;
      20: arraylength
      21: putfield      #8                  // Field numDataNodes:I
      24: new           #13                 // class org/apache/hadoop/hbase/StartMiniClusterOption
      27: dup
      28: aload_0
      29: getfield      #3                  // Field numMasters:I
      32: aload_0
      33: getfield      #4                  // Field masterClass:Ljava/lang/Class;
      36: aload_0
      37: getfield      #5                  // Field numRegionServers:I
      40: aload_0
      41: getfield      #6                  // Field rsPorts:Ljava/util/List;
      44: aload_0
      45: getfield      #7                  // Field rsClass:Ljava/lang/Class;
      48: aload_0
      49: getfield      #8                  // Field numDataNodes:I
      52: aload_0
      53: getfield      #9                  // Field dataNodeHosts:[Ljava/lang/String;
      56: aload_0
      57: getfield      #10                 // Field numZkServers:I
      60: aload_0
      61: getfield      #11                 // Field createRootDir:Z
      64: aload_0
      65: getfield      #12                 // Field createWALDir:Z
      68: aconst_null
      69: invokespecial #14                 // Method org/apache/hadoop/hbase/StartMiniClusterOption."<init>":(ILjava/lang/Class;ILjava/util/List;Ljava/lang/Class;I[Ljava/lang/String;IZZLorg/apache/hadoop/hbase/StartMiniClusterOption$1;)V
      72: areturn

  public org.apache.hadoop.hbase.StartMiniClusterOption$Builder numMasters(int);
    Code:
       0: aload_0
       1: iload_1
       2: putfield      #3                  // Field numMasters:I
       5: aload_0
       6: areturn

  public org.apache.hadoop.hbase.StartMiniClusterOption$Builder masterClass(java.lang.Class<? extends org.apache.hadoop.hbase.master.HMaster>);
    Code:
       0: aload_0
       1: aload_1
       2: putfield      #4                  // Field masterClass:Ljava/lang/Class;
       5: aload_0
       6: areturn

  public org.apache.hadoop.hbase.StartMiniClusterOption$Builder numRegionServers(int);
    Code:
       0: aload_0
       1: iload_1
       2: putfield      #5                  // Field numRegionServers:I
       5: aload_0
       6: areturn

  public org.apache.hadoop.hbase.StartMiniClusterOption$Builder rsPorts(java.util.List<java.lang.Integer>);
    Code:
       0: aload_0
       1: aload_1
       2: putfield      #6                  // Field rsPorts:Ljava/util/List;
       5: aload_0
       6: areturn

  public org.apache.hadoop.hbase.StartMiniClusterOption$Builder rsClass(java.lang.Class<? extends org.apache.hadoop.hbase.MiniHBaseCluster$MiniHBaseClusterRegionServer>);
    Code:
       0: aload_0
       1: aload_1
       2: putfield      #7                  // Field rsClass:Ljava/lang/Class;
       5: aload_0
       6: areturn

  public org.apache.hadoop.hbase.StartMiniClusterOption$Builder numDataNodes(int);
    Code:
       0: aload_0
       1: iload_1
       2: putfield      #8                  // Field numDataNodes:I
       5: aload_0
       6: areturn

  public org.apache.hadoop.hbase.StartMiniClusterOption$Builder dataNodeHosts(java.lang.String[]);
    Code:
       0: aload_0
       1: aload_1
       2: putfield      #9                  // Field dataNodeHosts:[Ljava/lang/String;
       5: aload_0
       6: areturn

  public org.apache.hadoop.hbase.StartMiniClusterOption$Builder numZkServers(int);
    Code:
       0: aload_0
       1: iload_1
       2: putfield      #10                 // Field numZkServers:I
       5: aload_0
       6: areturn

  public org.apache.hadoop.hbase.StartMiniClusterOption$Builder createRootDir(boolean);
    Code:
       0: aload_0
       1: iload_1
       2: putfield      #11                 // Field createRootDir:Z
       5: aload_0
       6: areturn

  public org.apache.hadoop.hbase.StartMiniClusterOption$Builder createWALDir(boolean);
    Code:
       0: aload_0
       1: iload_1
       2: putfield      #12                 // Field createWALDir:Z
       5: aload_0
       6: areturn

  org.apache.hadoop.hbase.StartMiniClusterOption$Builder(org.apache.hadoop.hbase.StartMiniClusterOption$1);
    Code:
       0: aload_0
       1: invokespecial #1                  // Method "<init>":()V
       4: return
}
