Compiled from "SteppingSplitPolicy.java"
public class org.apache.hadoop.hbase.regionserver.SteppingSplitPolicy extends org.apache.hadoop.hbase.regionserver.IncreasingToUpperBoundRegionSplitPolicy {
  public org.apache.hadoop.hbase.regionserver.SteppingSplitPolicy();
    Code:
       0: aload_0
       1: invokespecial #1                  // Method org/apache/hadoop/hbase/regionserver/IncreasingToUpperBoundRegionSplitPolicy."<init>":()V
       4: return

  protected long getSizeToCheck(int);
    Code:
       0: iload_1
       1: iconst_1
       2: if_icmpne     12
       5: aload_0
       6: getfield      #2                  // Field initialSize:J
       9: goto          16
      12: aload_0
      13: invokevirtual #3                  // Method getDesiredMaxFileSize:()J
      16: lreturn
}
