Compiled from "StochasticLoadBalancer.java"
class org.apache.hadoop.hbase.master.balancer.StochasticLoadBalancer$ServerLocalityCostFunction extends org.apache.hadoop.hbase.master.balancer.StochasticLoadBalancer$LocalityBasedCostFunction {
  org.apache.hadoop.hbase.master.balancer.StochasticLoadBalancer$ServerLocalityCostFunction(org.apache.hadoop.conf.Configuration, org.apache.hadoop.hbase.master.MasterServices);
    Code:
       0: aload_0
       1: aload_1
       2: aload_2
       3: getstatic     #1                  // Field org/apache/hadoop/hbase/master/balancer/BaseLoadBalancer$Cluster$LocalityType.SERVER:Lorg/apache/hadoop/hbase/master/balancer/BaseLoadBalancer$Cluster$LocalityType;
       6: ldc           #3                  // String hbase.master.balancer.stochastic.localityCost
       8: ldc           #4                  // float 25.0f
      10: invokespecial #5                  // Method org/apache/hadoop/hbase/master/balancer/StochasticLoadBalancer$LocalityBasedCostFunction."<init>":(Lorg/apache/hadoop/conf/Configuration;Lorg/apache/hadoop/hbase/master/MasterServices;Lorg/apache/hadoop/hbase/master/balancer/BaseLoadBalancer$Cluster$LocalityType;Ljava/lang/String;F)V
      13: return

  int regionIndexToEntityIndex(int);
    Code:
       0: aload_0
       1: getfield      #6                  // Field cluster:Lorg/apache/hadoop/hbase/master/balancer/BaseLoadBalancer$Cluster;
       4: getfield      #7                  // Field org/apache/hadoop/hbase/master/balancer/BaseLoadBalancer$Cluster.regionIndexToServerIndex:[I
       7: iload_1
       8: iaload
       9: ireturn
}
