Compiled from "StochasticLoadBalancer.java"
class org.apache.hadoop.hbase.master.balancer.StochasticLoadBalancer$RandomCandidateGenerator extends org.apache.hadoop.hbase.master.balancer.StochasticLoadBalancer$CandidateGenerator {
  org.apache.hadoop.hbase.master.balancer.StochasticLoadBalancer$RandomCandidateGenerator();
    Code:
       0: aload_0
       1: invokespecial #1                  // Method org/apache/hadoop/hbase/master/balancer/StochasticLoadBalancer$CandidateGenerator."<init>":()V
       4: return

  org.apache.hadoop.hbase.master.balancer.BaseLoadBalancer$Cluster$Action generate(org.apache.hadoop.hbase.master.balancer.BaseLoadBalancer$Cluster);
    Code:
       0: aload_0
       1: aload_1
       2: invokevirtual #2                  // Method pickRandomServer:(Lorg/apache/hadoop/hbase/master/balancer/BaseLoadBalancer$Cluster;)I
       5: istore_2
       6: aload_0
       7: aload_1
       8: iload_2
       9: invokevirtual #3                  // Method pickOtherRandomServer:(Lorg/apache/hadoop/hbase/master/balancer/BaseLoadBalancer$Cluster;I)I
      12: istore_3
      13: aload_0
      14: aload_1
      15: iload_2
      16: iload_3
      17: invokevirtual #4                  // Method pickRandomRegions:(Lorg/apache/hadoop/hbase/master/balancer/BaseLoadBalancer$Cluster;II)Lorg/apache/hadoop/hbase/master/balancer/BaseLoadBalancer$Cluster$Action;
      20: areturn
}
