Compiled from "StochasticLoadBalancer.java"
abstract class org.apache.hadoop.hbase.master.balancer.StochasticLoadBalancer$CostFunction {
  protected org.apache.hadoop.hbase.master.balancer.BaseLoadBalancer$Cluster cluster;

  org.apache.hadoop.hbase.master.balancer.StochasticLoadBalancer$CostFunction(org.apache.hadoop.conf.Configuration);
    Code:
       0: aload_0
       1: invokespecial #1                  // Method java/lang/Object."<init>":()V
       4: aload_0
       5: fconst_0
       6: putfield      #2                  // Field multiplier:F
       9: return

  boolean isNeeded();
    Code:
       0: iconst_1
       1: ireturn

  float getMultiplier();
    Code:
       0: aload_0
       1: getfield      #2                  // Field multiplier:F
       4: freturn

  void setMultiplier(float);
    Code:
       0: aload_0
       1: fload_1
       2: putfield      #2                  // Field multiplier:F
       5: return

  void init(org.apache.hadoop.hbase.master.balancer.BaseLoadBalancer$Cluster);
    Code:
       0: aload_0
       1: aload_1
       2: putfield      #3                  // Field cluster:Lorg/apache/hadoop/hbase/master/balancer/BaseLoadBalancer$Cluster;
       5: return

  void postAction(org.apache.hadoop.hbase.master.balancer.BaseLoadBalancer$Cluster$Action);
    Code:
       0: getstatic     #4                  // Field org/apache/hadoop/hbase/master/balancer/StochasticLoadBalancer$1.$SwitchMap$org$apache$hadoop$hbase$master$balancer$BaseLoadBalancer$Cluster$Action$Type:[I
       3: aload_1
       4: getfield      #5                  // Field org/apache/hadoop/hbase/master/balancer/BaseLoadBalancer$Cluster$Action.type:Lorg/apache/hadoop/hbase/master/balancer/BaseLoadBalancer$Cluster$Action$Type;
       7: invokevirtual #6                  // Method org/apache/hadoop/hbase/master/balancer/BaseLoadBalancer$Cluster$Action$Type.ordinal:()I
      10: iaload
      11: tableswitch   { // 1 to 4
                     1: 40
                     2: 43
                     3: 64
                     4: 88
               default: 135
          }
      40: goto          165
      43: aload_1
      44: checkcast     #7                  // class org/apache/hadoop/hbase/master/balancer/BaseLoadBalancer$Cluster$AssignRegionAction
      47: astore_2
      48: aload_0
      49: aload_2
      50: getfield      #8                  // Field org/apache/hadoop/hbase/master/balancer/BaseLoadBalancer$Cluster$AssignRegionAction.region:I
      53: iconst_m1
      54: aload_2
      55: getfield      #9                  // Field org/apache/hadoop/hbase/master/balancer/BaseLoadBalancer$Cluster$AssignRegionAction.server:I
      58: invokevirtual #10                 // Method regionMoved:(III)V
      61: goto          165
      64: aload_1
      65: checkcast     #11                 // class org/apache/hadoop/hbase/master/balancer/BaseLoadBalancer$Cluster$MoveRegionAction
      68: astore_3
      69: aload_0
      70: aload_3
      71: getfield      #12                 // Field org/apache/hadoop/hbase/master/balancer/BaseLoadBalancer$Cluster$MoveRegionAction.region:I
      74: aload_3
      75: getfield      #13                 // Field org/apache/hadoop/hbase/master/balancer/BaseLoadBalancer$Cluster$MoveRegionAction.fromServer:I
      78: aload_3
      79: getfield      #14                 // Field org/apache/hadoop/hbase/master/balancer/BaseLoadBalancer$Cluster$MoveRegionAction.toServer:I
      82: invokevirtual #10                 // Method regionMoved:(III)V
      85: goto          165
      88: aload_1
      89: checkcast     #15                 // class org/apache/hadoop/hbase/master/balancer/BaseLoadBalancer$Cluster$SwapRegionsAction
      92: astore        4
      94: aload_0
      95: aload         4
      97: getfield      #16                 // Field org/apache/hadoop/hbase/master/balancer/BaseLoadBalancer$Cluster$SwapRegionsAction.fromRegion:I
     100: aload         4
     102: getfield      #17                 // Field org/apache/hadoop/hbase/master/balancer/BaseLoadBalancer$Cluster$SwapRegionsAction.fromServer:I
     105: aload         4
     107: getfield      #18                 // Field org/apache/hadoop/hbase/master/balancer/BaseLoadBalancer$Cluster$SwapRegionsAction.toServer:I
     110: invokevirtual #10                 // Method regionMoved:(III)V
     113: aload_0
     114: aload         4
     116: getfield      #19                 // Field org/apache/hadoop/hbase/master/balancer/BaseLoadBalancer$Cluster$SwapRegionsAction.toRegion:I
     119: aload         4
     121: getfield      #18                 // Field org/apache/hadoop/hbase/master/balancer/BaseLoadBalancer$Cluster$SwapRegionsAction.toServer:I
     124: aload         4
     126: getfield      #17                 // Field org/apache/hadoop/hbase/master/balancer/BaseLoadBalancer$Cluster$SwapRegionsAction.fromServer:I
     129: invokevirtual #10                 // Method regionMoved:(III)V
     132: goto          165
     135: new           #20                 // class java/lang/RuntimeException
     138: dup
     139: new           #21                 // class java/lang/StringBuilder
     142: dup
     143: invokespecial #22                 // Method java/lang/StringBuilder."<init>":()V
     146: ldc           #23                 // String Uknown action:
     148: invokevirtual #24                 // Method java/lang/StringBuilder.append:(Ljava/lang/String;)Ljava/lang/StringBuilder;
     151: aload_1
     152: getfield      #5                  // Field org/apache/hadoop/hbase/master/balancer/BaseLoadBalancer$Cluster$Action.type:Lorg/apache/hadoop/hbase/master/balancer/BaseLoadBalancer$Cluster$Action$Type;
     155: invokevirtual #25                 // Method java/lang/StringBuilder.append:(Ljava/lang/Object;)Ljava/lang/StringBuilder;
     158: invokevirtual #26                 // Method java/lang/StringBuilder.toString:()Ljava/lang/String;
     161: invokespecial #27                 // Method java/lang/RuntimeException."<init>":(Ljava/lang/String;)V
     164: athrow
     165: return

  protected void regionMoved(int, int, int);
    Code:
       0: return

  abstract double cost();

  protected double costFromArray(double[]);
    Code:
       0: dconst_0
       1: dstore_2
       2: aload_0
       3: aload_1
       4: invokespecial #28                 // Method getSum:([D)D
       7: dstore        4
       9: aload_1
      10: arraylength
      11: i2d
      12: dstore        6
      14: dload         4
      16: dload         6
      18: ddiv
      19: dstore        8
      21: dload         6
      23: dconst_1
      24: dsub
      25: dload         8
      27: dmul
      28: dload         4
      30: dload         8
      32: dsub
      33: dadd
      34: dstore        10
      36: dload         6
      38: dload         4
      40: dcmpl
      41: ifle          65
      44: dload         6
      46: dload         4
      48: dsub
      49: dload         8
      51: dmul
      52: dconst_1
      53: dload         8
      55: dsub
      56: dload         4
      58: dmul
      59: dadd
      60: dstore        12
      62: goto          115
      65: dload         4
      67: dload         8
      69: invokestatic  #29                 // Method java/lang/Math.floor:(D)D
      72: dload         6
      74: dmul
      75: dsub
      76: d2i
      77: istore        14
      79: dload         6
      81: iload         14
      83: i2d
      84: dsub
      85: d2i
      86: istore        15
      88: iload         14
      90: i2d
      91: dload         8
      93: invokestatic  #30                 // Method java/lang/Math.ceil:(D)D
      96: dload         8
      98: dsub
      99: dmul
     100: iload         15
     102: i2d
     103: dload         8
     105: dload         8
     107: invokestatic  #29                 // Method java/lang/Math.floor:(D)D
     110: dsub
     111: dmul
     112: dadd
     113: dstore        12
     115: dconst_0
     116: dload         12
     118: invokestatic  #31                 // Method java/lang/Math.max:(DD)D
     121: dstore        12
     123: iconst_0
     124: istore        14
     126: iload         14
     128: aload_1
     129: arraylength
     130: if_icmpge     160
     133: aload_1
     134: iload         14
     136: daload
     137: dstore        15
     139: dload         8
     141: dload         15
     143: dsub
     144: invokestatic  #32                 // Method java/lang/Math.abs:(D)D
     147: dstore        17
     149: dload_2
     150: dload         17
     152: dadd
     153: dstore_2
     154: iinc          14, 1
     157: goto          126
     160: aload_0
     161: dload         12
     163: dload         10
     165: dload_2
     166: invokevirtual #33                 // Method scale:(DDD)D
     169: dstore        14
     171: dload         14
     173: dreturn

  protected double scale(double, double, double);
    Code:
       0: dload_3
       1: dload_1
       2: dcmpg
       3: ifle          13
       6: dload         5
       8: dload_1
       9: dcmpg
      10: ifgt          15
      13: dconst_0
      14: dreturn
      15: dload_3
      16: dload_1
      17: dsub
      18: dconst_0
      19: dcmpl
      20: ifne          25
      23: dconst_0
      24: dreturn
      25: dconst_0
      26: dconst_1
      27: dload         5
      29: dload_1
      30: dsub
      31: dload_3
      32: dload_1
      33: dsub
      34: ddiv
      35: invokestatic  #34                 // Method java/lang/Math.min:(DD)D
      38: invokestatic  #31                 // Method java/lang/Math.max:(DD)D
      41: dreturn
}
