Compiled from "StoppableImplementation.java"
public class org.apache.hadoop.hbase.util.StoppableImplementation implements org.apache.hadoop.hbase.Stoppable {
  volatile boolean stopped;

  public org.apache.hadoop.hbase.util.StoppableImplementation();
    Code:
       0: aload_0
       1: invokespecial #1                  // Method java/lang/Object."<init>":()V
       4: aload_0
       5: iconst_0
       6: putfield      #2                  // Field stopped:Z
       9: return

  public void stop(java.lang.String);
    Code:
       0: aload_0
       1: iconst_1
       2: putfield      #2                  // Field stopped:Z
       5: return

  public boolean isStopped();
    Code:
       0: aload_0
       1: getfield      #2                  // Field stopped:Z
       4: ireturn
}
