Compiled from "StoreFileReader.java"
public class org.apache.hadoop.hbase.regionserver.StoreFileReader {
  protected org.apache.hadoop.hbase.util.BloomFilter generalBloomFilter;

  protected org.apache.hadoop.hbase.util.BloomFilter deleteFamilyBloomFilter;

  protected org.apache.hadoop.hbase.regionserver.BloomType bloomFilterType;

  protected long sequenceID;

  protected org.apache.hadoop.hbase.io.TimeRange timeRange;

  final boolean shared;

  public org.apache.hadoop.hbase.regionserver.StoreFileReader(org.apache.hadoop.fs.FileSystem, org.apache.hadoop.fs.Path, org.apache.hadoop.hbase.io.hfile.CacheConfig, boolean, java.util.concurrent.atomic.AtomicInteger, boolean, org.apache.hadoop.conf.Configuration) throws java.io.IOException;
    Code:
       0: aload_0
       1: aload_1
       2: aload_2
       3: aload_3
       4: iload         4
       6: aload         7
       8: invokestatic  #18                 // Method org/apache/hadoop/hbase/io/hfile/HFile.createReader:(Lorg/apache/hadoop/fs/FileSystem;Lorg/apache/hadoop/fs/Path;Lorg/apache/hadoop/hbase/io/hfile/CacheConfig;ZLorg/apache/hadoop/conf/Configuration;)Lorg/apache/hadoop/hbase/io/hfile/HFile$Reader;
      11: aload         5
      13: iload         6
      15: invokespecial #19                 // Method "<init>":(Lorg/apache/hadoop/hbase/io/hfile/HFile$Reader;Ljava/util/concurrent/atomic/AtomicInteger;Z)V
      18: return

  public org.apache.hadoop.hbase.regionserver.StoreFileReader(org.apache.hadoop.fs.FileSystem, org.apache.hadoop.fs.Path, org.apache.hadoop.hbase.io.FSDataInputStreamWrapper, long, org.apache.hadoop.hbase.io.hfile.CacheConfig, boolean, java.util.concurrent.atomic.AtomicInteger, boolean, org.apache.hadoop.conf.Configuration) throws java.io.IOException;
    Code:
       0: aload_0
       1: aload_1
       2: aload_2
       3: aload_3
       4: lload         4
       6: aload         6
       8: iload         7
      10: aload         10
      12: invokestatic  #20                 // Method org/apache/hadoop/hbase/io/hfile/HFile.createReader:(Lorg/apache/hadoop/fs/FileSystem;Lorg/apache/hadoop/fs/Path;Lorg/apache/hadoop/hbase/io/FSDataInputStreamWrapper;JLorg/apache/hadoop/hbase/io/hfile/CacheConfig;ZLorg/apache/hadoop/conf/Configuration;)Lorg/apache/hadoop/hbase/io/hfile/HFile$Reader;
      15: aload         8
      17: iload         9
      19: invokespecial #19                 // Method "<init>":(Lorg/apache/hadoop/hbase/io/hfile/HFile$Reader;Ljava/util/concurrent/atomic/AtomicInteger;Z)V
      22: return

  void copyFields(org.apache.hadoop.hbase.regionserver.StoreFileReader);
    Code:
       0: aload_0
       1: aload_1
       2: getfield      #2                  // Field generalBloomFilter:Lorg/apache/hadoop/hbase/util/BloomFilter;
       5: putfield      #2                  // Field generalBloomFilter:Lorg/apache/hadoop/hbase/util/BloomFilter;
       8: aload_0
       9: aload_1
      10: getfield      #3                  // Field deleteFamilyBloomFilter:Lorg/apache/hadoop/hbase/util/BloomFilter;
      13: putfield      #3                  // Field deleteFamilyBloomFilter:Lorg/apache/hadoop/hbase/util/BloomFilter;
      16: aload_0
      17: aload_1
      18: getfield      #15                 // Field bloomFilterType:Lorg/apache/hadoop/hbase/regionserver/BloomType;
      21: putfield      #15                 // Field bloomFilterType:Lorg/apache/hadoop/hbase/regionserver/BloomType;
      24: aload_0
      25: aload_1
      26: getfield      #6                  // Field sequenceID:J
      29: putfield      #6                  // Field sequenceID:J
      32: aload_0
      33: aload_1
      34: getfield      #7                  // Field timeRange:Lorg/apache/hadoop/hbase/io/TimeRange;
      37: putfield      #7                  // Field timeRange:Lorg/apache/hadoop/hbase/io/TimeRange;
      40: aload_0
      41: aload_1
      42: getfield      #21                 // Field lastBloomKey:[B
      45: putfield      #21                 // Field lastBloomKey:[B
      48: aload_0
      49: aload_1
      50: getfield      #9                  // Field bulkLoadResult:Z
      53: putfield      #9                  // Field bulkLoadResult:Z
      56: aload_0
      57: aload_1
      58: getfield      #10                 // Field lastBloomKeyOnlyKV:Lorg/apache/hadoop/hbase/KeyValue$KeyOnlyKeyValue;
      61: putfield      #10                 // Field lastBloomKeyOnlyKV:Lorg/apache/hadoop/hbase/KeyValue$KeyOnlyKeyValue;
      64: aload_0
      65: aload_1
      66: getfield      #11                 // Field skipResetSeqId:Z
      69: putfield      #11                 // Field skipResetSeqId:Z
      72: aload_0
      73: aload_1
      74: getfield      #12                 // Field prefixLength:I
      77: putfield      #12                 // Field prefixLength:I
      80: return

  public boolean isPrimaryReplicaReader();
    Code:
       0: aload_0
       1: getfield      #13                 // Field reader:Lorg/apache/hadoop/hbase/io/hfile/HFile$Reader;
       4: invokeinterface #22,  1           // InterfaceMethod org/apache/hadoop/hbase/io/hfile/HFile$Reader.isPrimaryReplicaReader:()Z
       9: ireturn

  org.apache.hadoop.hbase.regionserver.StoreFileReader();
    Code:
       0: aload_0
       1: invokespecial #1                  // Method java/lang/Object."<init>":()V
       4: aload_0
       5: aconst_null
       6: putfield      #2                  // Field generalBloomFilter:Lorg/apache/hadoop/hbase/util/BloomFilter;
       9: aload_0
      10: aconst_null
      11: putfield      #3                  // Field deleteFamilyBloomFilter:Lorg/apache/hadoop/hbase/util/BloomFilter;
      14: aload_0
      15: ldc2_w        #4                  // long -1l
      18: putfield      #6                  // Field sequenceID:J
      21: aload_0
      22: aconst_null
      23: putfield      #7                  // Field timeRange:Lorg/apache/hadoop/hbase/io/TimeRange;
      26: aload_0
      27: ldc2_w        #4                  // long -1l
      30: putfield      #8                  // Field deleteFamilyCnt:J
      33: aload_0
      34: iconst_0
      35: putfield      #9                  // Field bulkLoadResult:Z
      38: aload_0
      39: aconst_null
      40: putfield      #10                 // Field lastBloomKeyOnlyKV:Lorg/apache/hadoop/hbase/KeyValue$KeyOnlyKeyValue;
      43: aload_0
      44: iconst_1
      45: putfield      #11                 // Field skipResetSeqId:Z
      48: aload_0
      49: iconst_m1
      50: putfield      #12                 // Field prefixLength:I
      53: aload_0
      54: new           #23                 // class java/util/concurrent/atomic/AtomicInteger
      57: dup
      58: iconst_0
      59: invokespecial #24                 // Method java/util/concurrent/atomic/AtomicInteger."<init>":(I)V
      62: putfield      #16                 // Field refCount:Ljava/util/concurrent/atomic/AtomicInteger;
      65: aload_0
      66: aconst_null
      67: putfield      #13                 // Field reader:Lorg/apache/hadoop/hbase/io/hfile/HFile$Reader;
      70: aload_0
      71: iconst_0
      72: putfield      #17                 // Field shared:Z
      75: return

  public org.apache.hadoop.hbase.CellComparator getComparator();
    Code:
       0: aload_0
       1: getfield      #13                 // Field reader:Lorg/apache/hadoop/hbase/io/hfile/HFile$Reader;
       4: invokeinterface #25,  1           // InterfaceMethod org/apache/hadoop/hbase/io/hfile/HFile$Reader.getComparator:()Lorg/apache/hadoop/hbase/CellComparator;
       9: areturn

  public org.apache.hadoop.hbase.regionserver.StoreFileScanner getStoreFileScanner(boolean, boolean, boolean, long, long, boolean);
    Code:
       0: new           #26                 // class org/apache/hadoop/hbase/regionserver/StoreFileScanner
       3: dup
       4: aload_0
       5: aload_0
       6: iload_1
       7: iload_2
       8: iload_3
       9: invokevirtual #27                 // Method getScanner:(ZZZ)Lorg/apache/hadoop/hbase/io/hfile/HFileScanner;
      12: iload_3
      13: ifne          20
      16: iconst_1
      17: goto          21
      20: iconst_0
      21: aload_0
      22: getfield      #13                 // Field reader:Lorg/apache/hadoop/hbase/io/hfile/HFile$Reader;
      25: invokeinterface #28,  1           // InterfaceMethod org/apache/hadoop/hbase/io/hfile/HFile$Reader.hasMVCCInfo:()Z
      30: lload         4
      32: lload         6
      34: iload         8
      36: invokespecial #29                 // Method org/apache/hadoop/hbase/regionserver/StoreFileScanner."<init>":(Lorg/apache/hadoop/hbase/regionserver/StoreFileReader;Lorg/apache/hadoop/hbase/io/hfile/HFileScanner;ZZJJZ)V
      39: areturn

  int getRefCount();
    Code:
       0: aload_0
       1: getfield      #16                 // Field refCount:Ljava/util/concurrent/atomic/AtomicInteger;
       4: invokevirtual #30                 // Method java/util/concurrent/atomic/AtomicInteger.get:()I
       7: ireturn

  void incrementRefCount();
    Code:
       0: aload_0
       1: getfield      #16                 // Field refCount:Ljava/util/concurrent/atomic/AtomicInteger;
       4: invokevirtual #31                 // Method java/util/concurrent/atomic/AtomicInteger.incrementAndGet:()I
       7: pop
       8: return

  void readCompleted();
    Code:
       0: aload_0
       1: getfield      #16                 // Field refCount:Ljava/util/concurrent/atomic/AtomicInteger;
       4: invokevirtual #32                 // Method java/util/concurrent/atomic/AtomicInteger.decrementAndGet:()I
       7: pop
       8: aload_0
       9: getfield      #17                 // Field shared:Z
      12: ifne          40
      15: aload_0
      16: getfield      #13                 // Field reader:Lorg/apache/hadoop/hbase/io/hfile/HFile$Reader;
      19: iconst_0
      20: invokeinterface #33,  2           // InterfaceMethod org/apache/hadoop/hbase/io/hfile/HFile$Reader.close:(Z)V
      25: goto          40
      28: astore_1
      29: getstatic     #35                 // Field LOG:Lorg/slf4j/Logger;
      32: ldc           #36                 // String failed to close stream reader
      34: aload_1
      35: invokeinterface #37,  3           // InterfaceMethod org/slf4j/Logger.warn:(Ljava/lang/String;Ljava/lang/Throwable;)V
      40: return
    Exception table:
       from    to  target type
          15    25    28   Class java/io/IOException

  public org.apache.hadoop.hbase.io.hfile.HFileScanner getScanner(boolean, boolean);
    Code:
       0: aload_0
       1: iload_1
       2: iload_2
       3: iconst_0
       4: invokevirtual #27                 // Method getScanner:(ZZZ)Lorg/apache/hadoop/hbase/io/hfile/HFileScanner;
       7: areturn

  public org.apache.hadoop.hbase.io.hfile.HFileScanner getScanner(boolean, boolean, boolean);
    Code:
       0: aload_0
       1: getfield      #13                 // Field reader:Lorg/apache/hadoop/hbase/io/hfile/HFile$Reader;
       4: iload_1
       5: iload_2
       6: iload_3
       7: invokeinterface #38,  4           // InterfaceMethod org/apache/hadoop/hbase/io/hfile/HFile$Reader.getScanner:(ZZZ)Lorg/apache/hadoop/hbase/io/hfile/HFileScanner;
      12: areturn

  public void close(boolean) throws java.io.IOException;
    Code:
       0: aload_0
       1: getfield      #13                 // Field reader:Lorg/apache/hadoop/hbase/io/hfile/HFile$Reader;
       4: iload_1
       5: invokeinterface #33,  2           // InterfaceMethod org/apache/hadoop/hbase/io/hfile/HFile$Reader.close:(Z)V
      10: return

  boolean passesTimerangeFilter(org.apache.hadoop.hbase.io.TimeRange, long);
    Code:
       0: aload_0
       1: getfield      #7                  // Field timeRange:Lorg/apache/hadoop/hbase/io/TimeRange;
       4: ifnonnull     11
       7: iconst_1
       8: goto          39
      11: aload_0
      12: getfield      #7                  // Field timeRange:Lorg/apache/hadoop/hbase/io/TimeRange;
      15: aload_1
      16: invokevirtual #39                 // Method org/apache/hadoop/hbase/io/TimeRange.includesTimeRange:(Lorg/apache/hadoop/hbase/io/TimeRange;)Z
      19: ifeq          38
      22: aload_0
      23: getfield      #7                  // Field timeRange:Lorg/apache/hadoop/hbase/io/TimeRange;
      26: invokevirtual #40                 // Method org/apache/hadoop/hbase/io/TimeRange.getMax:()J
      29: lload_2
      30: lcmp
      31: iflt          38
      34: iconst_1
      35: goto          39
      38: iconst_0
      39: ireturn

  boolean passesBloomFilter(org.apache.hadoop.hbase.client.Scan, java.util.SortedSet<byte[]>);
    Code:
       0: aload_1
       1: invokevirtual #41                 // Method org/apache/hadoop/hbase/client/Scan.getStartRow:()[B
       4: astore_3
       5: getstatic     #42                 // Field org/apache/hadoop/hbase/regionserver/StoreFileReader$1.$SwitchMap$org$apache$hadoop$hbase$regionserver$BloomType:[I
       8: aload_0
       9: getfield      #15                 // Field bloomFilterType:Lorg/apache/hadoop/hbase/regionserver/BloomType;
      12: invokevirtual #43                 // Method org/apache/hadoop/hbase/regionserver/BloomType.ordinal:()I
      15: iaload
      16: tableswitch   { // 1 to 3
                     1: 44
                     2: 62
                     3: 116
               default: 122
          }
      44: aload_1
      45: invokevirtual #44                 // Method org/apache/hadoop/hbase/client/Scan.isGetScan:()Z
      48: ifne          53
      51: iconst_1
      52: ireturn
      53: aload_0
      54: aload_3
      55: iconst_0
      56: aload_3
      57: arraylength
      58: invokespecial #45                 // Method passesGeneralRowBloomFilter:([BII)Z
      61: ireturn
      62: aload_1
      63: invokevirtual #44                 // Method org/apache/hadoop/hbase/client/Scan.isGetScan:()Z
      66: ifne          71
      69: iconst_1
      70: ireturn
      71: aload_2
      72: ifnull        114
      75: aload_2
      76: invokeinterface #46,  1           // InterfaceMethod java/util/SortedSet.size:()I
      81: iconst_1
      82: if_icmpne     114
      85: aload_2
      86: invokeinterface #47,  1           // InterfaceMethod java/util/SortedSet.first:()Ljava/lang/Object;
      91: checkcast     #48                 // class "[B"
      94: astore        4
      96: aload_3
      97: getstatic     #49                 // Field org/apache/hadoop/hbase/HConstants.EMPTY_BYTE_ARRAY:[B
     100: aload         4
     102: invokestatic  #50                 // Method org/apache/hadoop/hbase/PrivateCellUtil.createFirstOnRow:([B[B[B)Lorg/apache/hadoop/hbase/Cell;
     105: astore        5
     107: aload_0
     108: aload         5
     110: invokevirtual #51                 // Method passesGeneralRowColBloomFilter:(Lorg/apache/hadoop/hbase/Cell;)Z
     113: ireturn
     114: iconst_1
     115: ireturn
     116: aload_0
     117: aload_1
     118: invokespecial #52                 // Method passesGeneralRowPrefixBloomFilter:(Lorg/apache/hadoop/hbase/client/Scan;)Z
     121: ireturn
     122: iconst_1
     123: ireturn

  public boolean passesDeleteFamilyBloomFilter(byte[], int, int);
    Code:
       0: aload_0
       1: getfield      #3                  // Field deleteFamilyBloomFilter:Lorg/apache/hadoop/hbase/util/BloomFilter;
       4: astore        4
       6: aload_0
       7: getfield      #13                 // Field reader:Lorg/apache/hadoop/hbase/io/hfile/HFile$Reader;
      10: invokeinterface #53,  1           // InterfaceMethod org/apache/hadoop/hbase/io/hfile/HFile$Reader.getTrailer:()Lorg/apache/hadoop/hbase/io/hfile/FixedFileTrailer;
      15: invokevirtual #54                 // Method org/apache/hadoop/hbase/io/hfile/FixedFileTrailer.getEntryCount:()J
      18: lconst_0
      19: lcmp
      20: ifeq          32
      23: aload_0
      24: getfield      #8                  // Field deleteFamilyCnt:J
      27: lconst_0
      28: lcmp
      29: ifne          34
      32: iconst_0
      33: ireturn
      34: aload         4
      36: ifnonnull     41
      39: iconst_1
      40: ireturn
      41: aload         4
      43: invokeinterface #55,  1           // InterfaceMethod org/apache/hadoop/hbase/util/BloomFilter.supportsAutoLoading:()Z
      48: ifne          53
      51: iconst_1
      52: ireturn
      53: aload         4
      55: aload_1
      56: iload_2
      57: iload_3
      58: aconst_null
      59: invokeinterface #56,  5           // InterfaceMethod org/apache/hadoop/hbase/util/BloomFilter.contains:([BIILorg/apache/hadoop/hbase/nio/ByteBuff;)Z
      64: ireturn
      65: astore        5
      67: getstatic     #35                 // Field LOG:Lorg/slf4j/Logger;
      70: ldc           #58                 // String Bad Delete Family bloom filter data -- proceeding without
      72: aload         5
      74: invokeinterface #59,  3           // InterfaceMethod org/slf4j/Logger.error:(Ljava/lang/String;Ljava/lang/Throwable;)V
      79: aload_0
      80: invokevirtual #60                 // Method setDeleteFamilyBloomFilterFaulty:()V
      83: iconst_1
      84: ireturn
    Exception table:
       from    to  target type
          41    52    65   Class java/lang/IllegalArgumentException
          53    64    65   Class java/lang/IllegalArgumentException

  public boolean passesGeneralRowColBloomFilter(org.apache.hadoop.hbase.Cell);
    Code:
       0: aload_0
       1: getfield      #2                  // Field generalBloomFilter:Lorg/apache/hadoop/hbase/util/BloomFilter;
       4: astore_2
       5: aload_2
       6: ifnonnull     11
       9: iconst_1
      10: ireturn
      11: aconst_null
      12: astore_3
      13: aload_1
      14: invokeinterface #65,  1           // InterfaceMethod org/apache/hadoop/hbase/Cell.getTypeByte:()B
      19: getstatic     #66                 // Field org/apache/hadoop/hbase/KeyValue$Type.Maximum:Lorg/apache/hadoop/hbase/KeyValue$Type;
      22: invokevirtual #67                 // Method org/apache/hadoop/hbase/KeyValue$Type.getCode:()B
      25: if_icmpne     42
      28: aload_1
      29: invokeinterface #68,  1           // InterfaceMethod org/apache/hadoop/hbase/Cell.getFamilyLength:()B
      34: ifne          42
      37: aload_1
      38: astore_3
      39: goto          47
      42: aload_1
      43: invokestatic  #69                 // Method org/apache/hadoop/hbase/PrivateCellUtil.createFirstOnRowCol:(Lorg/apache/hadoop/hbase/Cell;)Lorg/apache/hadoop/hbase/Cell;
      46: astore_3
      47: aload_0
      48: aconst_null
      49: aload_3
      50: aload_2
      51: invokespecial #64                 // Method checkGeneralBloomFilter:([BLorg/apache/hadoop/hbase/Cell;Lorg/apache/hadoop/hbase/util/BloomFilter;)Z
      54: ireturn

  public boolean passesKeyRangeFilter(org.apache.hadoop.hbase.client.Scan);
    Code:
       0: aload_0
       1: invokevirtual #89                 // Method getFirstKey:()Ljava/util/Optional;
       4: astore_2
       5: aload_0
       6: invokevirtual #90                 // Method getLastKey:()Ljava/util/Optional;
       9: astore_3
      10: aload_2
      11: invokevirtual #91                 // Method java/util/Optional.isPresent:()Z
      14: ifeq          24
      17: aload_3
      18: invokevirtual #91                 // Method java/util/Optional.isPresent:()Z
      21: ifne          26
      24: iconst_0
      25: ireturn
      26: aload_1
      27: invokevirtual #41                 // Method org/apache/hadoop/hbase/client/Scan.getStartRow:()[B
      30: getstatic     #92                 // Field org/apache/hadoop/hbase/HConstants.EMPTY_START_ROW:[B
      33: invokestatic  #93                 // Method org/apache/hadoop/hbase/util/Bytes.equals:([B[B)Z
      36: ifeq          54
      39: aload_1
      40: invokevirtual #72                 // Method org/apache/hadoop/hbase/client/Scan.getStopRow:()[B
      43: getstatic     #94                 // Field org/apache/hadoop/hbase/HConstants.EMPTY_END_ROW:[B
      46: invokestatic  #93                 // Method org/apache/hadoop/hbase/util/Bytes.equals:([B[B)Z
      49: ifeq          54
      52: iconst_1
      53: ireturn
      54: aload_1
      55: invokevirtual #95                 // Method org/apache/hadoop/hbase/client/Scan.isReversed:()Z
      58: ifeq          68
      61: aload_1
      62: invokevirtual #72                 // Method org/apache/hadoop/hbase/client/Scan.getStopRow:()[B
      65: goto          72
      68: aload_1
      69: invokevirtual #41                 // Method org/apache/hadoop/hbase/client/Scan.getStartRow:()[B
      72: astore        4
      74: aload_1
      75: invokevirtual #95                 // Method org/apache/hadoop/hbase/client/Scan.isReversed:()Z
      78: ifeq          88
      81: aload_1
      82: invokevirtual #41                 // Method org/apache/hadoop/hbase/client/Scan.getStartRow:()[B
      85: goto          92
      88: aload_1
      89: invokevirtual #72                 // Method org/apache/hadoop/hbase/client/Scan.getStopRow:()[B
      92: astore        5
      94: aload_0
      95: invokevirtual #96                 // Method getComparator:()Lorg/apache/hadoop/hbase/CellComparator;
      98: aload_2
      99: invokevirtual #97                 // Method java/util/Optional.get:()Ljava/lang/Object;
     102: checkcast     #98                 // class org/apache/hadoop/hbase/Cell
     105: aload         5
     107: iconst_0
     108: aload         5
     110: arraylength
     111: invokeinterface #99,  5           // InterfaceMethod org/apache/hadoop/hbase/CellComparator.compareRows:(Lorg/apache/hadoop/hbase/Cell;[BII)I
     116: ifle          146
     119: aload_1
     120: invokevirtual #95                 // Method org/apache/hadoop/hbase/client/Scan.isReversed:()Z
     123: ifeq          133
     126: aload_1
     127: invokevirtual #41                 // Method org/apache/hadoop/hbase/client/Scan.getStartRow:()[B
     130: goto          137
     133: aload_1
     134: invokevirtual #72                 // Method org/apache/hadoop/hbase/client/Scan.getStopRow:()[B
     137: getstatic     #94                 // Field org/apache/hadoop/hbase/HConstants.EMPTY_END_ROW:[B
     140: invokestatic  #93                 // Method org/apache/hadoop/hbase/util/Bytes.equals:([B[B)Z
     143: ifeq          171
     146: aload_0
     147: invokevirtual #96                 // Method getComparator:()Lorg/apache/hadoop/hbase/CellComparator;
     150: aload_3
     151: invokevirtual #97                 // Method java/util/Optional.get:()Ljava/lang/Object;
     154: checkcast     #98                 // class org/apache/hadoop/hbase/Cell
     157: aload         4
     159: iconst_0
     160: aload         4
     162: arraylength
     163: invokeinterface #99,  5           // InterfaceMethod org/apache/hadoop/hbase/CellComparator.compareRows:(Lorg/apache/hadoop/hbase/Cell;[BII)I
     168: ifge          175
     171: iconst_1
     172: goto          176
     175: iconst_0
     176: istore        6
     178: iload         6
     180: ifne          187
     183: iconst_1
     184: goto          188
     187: iconst_0
     188: ireturn

  public java.util.Map<byte[], byte[]> loadFileInfo() throws java.io.IOException;
    Code:
       0: aload_0
       1: getfield      #13                 // Field reader:Lorg/apache/hadoop/hbase/io/hfile/HFile$Reader;
       4: invokeinterface #100,  1          // InterfaceMethod org/apache/hadoop/hbase/io/hfile/HFile$Reader.loadFileInfo:()Ljava/util/Map;
       9: astore_1
      10: aload_1
      11: getstatic     #101                // Field org/apache/hadoop/hbase/regionserver/HStoreFile.BLOOM_FILTER_TYPE_KEY:[B
      14: invokeinterface #102,  2          // InterfaceMethod java/util/Map.get:(Ljava/lang/Object;)Ljava/lang/Object;
      19: checkcast     #48                 // class "[B"
      22: astore_2
      23: aload_2
      24: ifnull        38
      27: aload_0
      28: aload_2
      29: invokestatic  #103                // Method org/apache/hadoop/hbase/util/Bytes.toString:([B)Ljava/lang/String;
      32: invokestatic  #104                // Method org/apache/hadoop/hbase/regionserver/BloomType.valueOf:(Ljava/lang/String;)Lorg/apache/hadoop/hbase/regionserver/BloomType;
      35: putfield      #15                 // Field bloomFilterType:Lorg/apache/hadoop/hbase/regionserver/BloomType;
      38: aload_1
      39: getstatic     #105                // Field org/apache/hadoop/hbase/regionserver/HStoreFile.BLOOM_FILTER_PARAM_KEY:[B
      42: invokeinterface #102,  2          // InterfaceMethod java/util/Map.get:(Ljava/lang/Object;)Ljava/lang/Object;
      47: checkcast     #48                 // class "[B"
      50: astore_3
      51: aload_0
      52: getfield      #15                 // Field bloomFilterType:Lorg/apache/hadoop/hbase/regionserver/BloomType;
      55: getstatic     #106                // Field org/apache/hadoop/hbase/regionserver/BloomType.ROWPREFIX_FIXED_LENGTH:Lorg/apache/hadoop/hbase/regionserver/BloomType;
      58: if_acmpne     69
      61: aload_0
      62: aload_3
      63: invokestatic  #107                // Method org/apache/hadoop/hbase/util/Bytes.toInt:([B)I
      66: putfield      #12                 // Field prefixLength:I
      69: aload_0
      70: aload_1
      71: getstatic     #108                // Field org/apache/hadoop/hbase/regionserver/HStoreFile.LAST_BLOOM_KEY:[B
      74: invokeinterface #102,  2          // InterfaceMethod java/util/Map.get:(Ljava/lang/Object;)Ljava/lang/Object;
      79: checkcast     #48                 // class "[B"
      82: putfield      #21                 // Field lastBloomKey:[B
      85: aload_0
      86: getfield      #15                 // Field bloomFilterType:Lorg/apache/hadoop/hbase/regionserver/BloomType;
      89: getstatic     #78                 // Field org/apache/hadoop/hbase/regionserver/BloomType.ROWCOL:Lorg/apache/hadoop/hbase/regionserver/BloomType;
      92: if_acmpne     116
      95: aload_0
      96: new           #109                // class org/apache/hadoop/hbase/KeyValue$KeyOnlyKeyValue
      99: dup
     100: aload_0
     101: getfield      #21                 // Field lastBloomKey:[B
     104: iconst_0
     105: aload_0
     106: getfield      #21                 // Field lastBloomKey:[B
     109: arraylength
     110: invokespecial #110                // Method org/apache/hadoop/hbase/KeyValue$KeyOnlyKeyValue."<init>":([BII)V
     113: putfield      #10                 // Field lastBloomKeyOnlyKV:Lorg/apache/hadoop/hbase/KeyValue$KeyOnlyKeyValue;
     116: aload_1
     117: getstatic     #111                // Field org/apache/hadoop/hbase/regionserver/HStoreFile.DELETE_FAMILY_COUNT:[B
     120: invokeinterface #102,  2          // InterfaceMethod java/util/Map.get:(Ljava/lang/Object;)Ljava/lang/Object;
     125: checkcast     #48                 // class "[B"
     128: astore        4
     130: aload         4
     132: ifnull        144
     135: aload_0
     136: aload         4
     138: invokestatic  #112                // Method org/apache/hadoop/hbase/util/Bytes.toLong:([B)J
     141: putfield      #8                  // Field deleteFamilyCnt:J
     144: aload_1
     145: areturn

  public void loadBloomfilter();
    Code:
       0: aload_0
       1: getstatic     #113                // Field org/apache/hadoop/hbase/io/hfile/BlockType.GENERAL_BLOOM_META:Lorg/apache/hadoop/hbase/io/hfile/BlockType;
       4: invokevirtual #114                // Method loadBloomfilter:(Lorg/apache/hadoop/hbase/io/hfile/BlockType;)V
       7: aload_0
       8: getstatic     #115                // Field org/apache/hadoop/hbase/io/hfile/BlockType.DELETE_FAMILY_BLOOM_META:Lorg/apache/hadoop/hbase/io/hfile/BlockType;
      11: invokevirtual #114                // Method loadBloomfilter:(Lorg/apache/hadoop/hbase/io/hfile/BlockType;)V
      14: return

  public void loadBloomfilter(org.apache.hadoop.hbase.io.hfile.BlockType);
    Code:
       0: aload_1
       1: getstatic     #113                // Field org/apache/hadoop/hbase/io/hfile/BlockType.GENERAL_BLOOM_META:Lorg/apache/hadoop/hbase/io/hfile/BlockType;
       4: if_acmpne     143
       7: aload_0
       8: getfield      #2                  // Field generalBloomFilter:Lorg/apache/hadoop/hbase/util/BloomFilter;
      11: ifnull        15
      14: return
      15: aload_0
      16: getfield      #13                 // Field reader:Lorg/apache/hadoop/hbase/io/hfile/HFile$Reader;
      19: invokeinterface #116,  1          // InterfaceMethod org/apache/hadoop/hbase/io/hfile/HFile$Reader.getGeneralBloomFilterMetadata:()Ljava/io/DataInput;
      24: astore_2
      25: aload_2
      26: ifnull        140
      29: aload_0
      30: getfield      #15                 // Field bloomFilterType:Lorg/apache/hadoop/hbase/regionserver/BloomType;
      33: getstatic     #14                 // Field org/apache/hadoop/hbase/regionserver/BloomType.NONE:Lorg/apache/hadoop/hbase/regionserver/BloomType;
      36: if_acmpne     49
      39: new           #34                 // class java/io/IOException
      42: dup
      43: ldc           #117                // String valid bloom filter type not found in FileInfo
      45: invokespecial #118                // Method java/io/IOException."<init>":(Ljava/lang/String;)V
      48: athrow
      49: aload_0
      50: aload_2
      51: aload_0
      52: getfield      #13                 // Field reader:Lorg/apache/hadoop/hbase/io/hfile/HFile$Reader;
      55: invokestatic  #119                // Method org/apache/hadoop/hbase/util/BloomFilterFactory.createFromMeta:(Ljava/io/DataInput;Lorg/apache/hadoop/hbase/io/hfile/HFile$Reader;)Lorg/apache/hadoop/hbase/util/BloomFilter;
      58: putfield      #2                  // Field generalBloomFilter:Lorg/apache/hadoop/hbase/util/BloomFilter;
      61: getstatic     #35                 // Field LOG:Lorg/slf4j/Logger;
      64: invokeinterface #120,  1          // InterfaceMethod org/slf4j/Logger.isTraceEnabled:()Z
      69: ifeq          140
      72: getstatic     #35                 // Field LOG:Lorg/slf4j/Logger;
      75: new           #121                // class java/lang/StringBuilder
      78: dup
      79: invokespecial #122                // Method java/lang/StringBuilder."<init>":()V
      82: ldc           #123                // String Loaded
      84: invokevirtual #124                // Method java/lang/StringBuilder.append:(Ljava/lang/String;)Ljava/lang/StringBuilder;
      87: aload_0
      88: getfield      #15                 // Field bloomFilterType:Lorg/apache/hadoop/hbase/regionserver/BloomType;
      91: invokevirtual #125                // Method org/apache/hadoop/hbase/regionserver/BloomType.toString:()Ljava/lang/String;
      94: invokevirtual #124                // Method java/lang/StringBuilder.append:(Ljava/lang/String;)Ljava/lang/StringBuilder;
      97: ldc           #126                // String
      99: invokevirtual #124                // Method java/lang/StringBuilder.append:(Ljava/lang/String;)Ljava/lang/StringBuilder;
     102: aload_0
     103: getfield      #2                  // Field generalBloomFilter:Lorg/apache/hadoop/hbase/util/BloomFilter;
     106: invokevirtual #127                // Method java/lang/Object.getClass:()Ljava/lang/Class;
     109: invokevirtual #128                // Method java/lang/Class.getSimpleName:()Ljava/lang/String;
     112: invokevirtual #124                // Method java/lang/StringBuilder.append:(Ljava/lang/String;)Ljava/lang/StringBuilder;
     115: ldc           #129                // String  metadata for
     117: invokevirtual #124                // Method java/lang/StringBuilder.append:(Ljava/lang/String;)Ljava/lang/StringBuilder;
     120: aload_0
     121: getfield      #13                 // Field reader:Lorg/apache/hadoop/hbase/io/hfile/HFile$Reader;
     124: invokeinterface #130,  1          // InterfaceMethod org/apache/hadoop/hbase/io/hfile/HFile$Reader.getName:()Ljava/lang/String;
     129: invokevirtual #124                // Method java/lang/StringBuilder.append:(Ljava/lang/String;)Ljava/lang/StringBuilder;
     132: invokevirtual #131                // Method java/lang/StringBuilder.toString:()Ljava/lang/String;
     135: invokeinterface #132,  2          // InterfaceMethod org/slf4j/Logger.trace:(Ljava/lang/String;)V
     140: goto          275
     143: aload_1
     144: getstatic     #115                // Field org/apache/hadoop/hbase/io/hfile/BlockType.DELETE_FAMILY_BLOOM_META:Lorg/apache/hadoop/hbase/io/hfile/BlockType;
     147: if_acmpne     240
     150: aload_0
     151: getfield      #3                  // Field deleteFamilyBloomFilter:Lorg/apache/hadoop/hbase/util/BloomFilter;
     154: ifnull        158
     157: return
     158: aload_0
     159: getfield      #13                 // Field reader:Lorg/apache/hadoop/hbase/io/hfile/HFile$Reader;
     162: invokeinterface #133,  1          // InterfaceMethod org/apache/hadoop/hbase/io/hfile/HFile$Reader.getDeleteBloomFilterMetadata:()Ljava/io/DataInput;
     167: astore_2
     168: aload_2
     169: ifnull        237
     172: aload_0
     173: aload_2
     174: aload_0
     175: getfield      #13                 // Field reader:Lorg/apache/hadoop/hbase/io/hfile/HFile$Reader;
     178: invokestatic  #119                // Method org/apache/hadoop/hbase/util/BloomFilterFactory.createFromMeta:(Ljava/io/DataInput;Lorg/apache/hadoop/hbase/io/hfile/HFile$Reader;)Lorg/apache/hadoop/hbase/util/BloomFilter;
     181: putfield      #3                  // Field deleteFamilyBloomFilter:Lorg/apache/hadoop/hbase/util/BloomFilter;
     184: getstatic     #35                 // Field LOG:Lorg/slf4j/Logger;
     187: new           #121                // class java/lang/StringBuilder
     190: dup
     191: invokespecial #122                // Method java/lang/StringBuilder."<init>":()V
     194: ldc           #134                // String Loaded Delete Family Bloom (
     196: invokevirtual #124                // Method java/lang/StringBuilder.append:(Ljava/lang/String;)Ljava/lang/StringBuilder;
     199: aload_0
     200: getfield      #3                  // Field deleteFamilyBloomFilter:Lorg/apache/hadoop/hbase/util/BloomFilter;
     203: invokevirtual #127                // Method java/lang/Object.getClass:()Ljava/lang/Class;
     206: invokevirtual #128                // Method java/lang/Class.getSimpleName:()Ljava/lang/String;
     209: invokevirtual #124                // Method java/lang/StringBuilder.append:(Ljava/lang/String;)Ljava/lang/StringBuilder;
     212: ldc           #135                // String ) metadata for
     214: invokevirtual #124                // Method java/lang/StringBuilder.append:(Ljava/lang/String;)Ljava/lang/StringBuilder;
     217: aload_0
     218: getfield      #13                 // Field reader:Lorg/apache/hadoop/hbase/io/hfile/HFile$Reader;
     221: invokeinterface #130,  1          // InterfaceMethod org/apache/hadoop/hbase/io/hfile/HFile$Reader.getName:()Ljava/lang/String;
     226: invokevirtual #124                // Method java/lang/StringBuilder.append:(Ljava/lang/String;)Ljava/lang/StringBuilder;
     229: invokevirtual #131                // Method java/lang/StringBuilder.toString:()Ljava/lang/String;
     232: invokeinterface #136,  2          // InterfaceMethod org/slf4j/Logger.info:(Ljava/lang/String;)V
     237: goto          275
     240: new           #137                // class java/lang/RuntimeException
     243: dup
     244: new           #121                // class java/lang/StringBuilder
     247: dup
     248: invokespecial #122                // Method java/lang/StringBuilder."<init>":()V
     251: ldc           #138                // String Block Type:
     253: invokevirtual #124                // Method java/lang/StringBuilder.append:(Ljava/lang/String;)Ljava/lang/StringBuilder;
     256: aload_1
     257: invokevirtual #139                // Method org/apache/hadoop/hbase/io/hfile/BlockType.toString:()Ljava/lang/String;
     260: invokevirtual #124                // Method java/lang/StringBuilder.append:(Ljava/lang/String;)Ljava/lang/StringBuilder;
     263: ldc           #140                // String is not supported for Bloom filter
     265: invokevirtual #124                // Method java/lang/StringBuilder.append:(Ljava/lang/String;)Ljava/lang/StringBuilder;
     268: invokevirtual #131                // Method java/lang/StringBuilder.toString:()Ljava/lang/String;
     271: invokespecial #141                // Method java/lang/RuntimeException."<init>":(Ljava/lang/String;)V
     274: athrow
     275: goto          359
     278: astore_2
     279: getstatic     #35                 // Field LOG:Lorg/slf4j/Logger;
     282: new           #121                // class java/lang/StringBuilder
     285: dup
     286: invokespecial #122                // Method java/lang/StringBuilder."<init>":()V
     289: ldc           #142                // String Error reading bloom filter meta for
     291: invokevirtual #124                // Method java/lang/StringBuilder.append:(Ljava/lang/String;)Ljava/lang/StringBuilder;
     294: aload_1
     295: invokevirtual #143                // Method java/lang/StringBuilder.append:(Ljava/lang/Object;)Ljava/lang/StringBuilder;
     298: ldc           #144                // String  -- proceeding without
     300: invokevirtual #124                // Method java/lang/StringBuilder.append:(Ljava/lang/String;)Ljava/lang/StringBuilder;
     303: invokevirtual #131                // Method java/lang/StringBuilder.toString:()Ljava/lang/String;
     306: aload_2
     307: invokeinterface #59,  3           // InterfaceMethod org/slf4j/Logger.error:(Ljava/lang/String;Ljava/lang/Throwable;)V
     312: aload_0
     313: aload_1
     314: invokespecial #145                // Method setBloomFilterFaulty:(Lorg/apache/hadoop/hbase/io/hfile/BlockType;)V
     317: goto          359
     320: astore_2
     321: getstatic     #35                 // Field LOG:Lorg/slf4j/Logger;
     324: new           #121                // class java/lang/StringBuilder
     327: dup
     328: invokespecial #122                // Method java/lang/StringBuilder."<init>":()V
     331: ldc           #146                // String Bad bloom filter meta
     333: invokevirtual #124                // Method java/lang/StringBuilder.append:(Ljava/lang/String;)Ljava/lang/StringBuilder;
     336: aload_1
     337: invokevirtual #143                // Method java/lang/StringBuilder.append:(Ljava/lang/Object;)Ljava/lang/StringBuilder;
     340: ldc           #144                // String  -- proceeding without
     342: invokevirtual #124                // Method java/lang/StringBuilder.append:(Ljava/lang/String;)Ljava/lang/StringBuilder;
     345: invokevirtual #131                // Method java/lang/StringBuilder.toString:()Ljava/lang/String;
     348: aload_2
     349: invokeinterface #59,  3           // InterfaceMethod org/slf4j/Logger.error:(Ljava/lang/String;Ljava/lang/Throwable;)V
     354: aload_0
     355: aload_1
     356: invokespecial #145                // Method setBloomFilterFaulty:(Lorg/apache/hadoop/hbase/io/hfile/BlockType;)V
     359: return
    Exception table:
       from    to  target type
           0    14   278   Class java/io/IOException
          15   157   278   Class java/io/IOException
         158   275   278   Class java/io/IOException
           0    14   320   Class java/lang/IllegalArgumentException
          15   157   320   Class java/lang/IllegalArgumentException
         158   275   320   Class java/lang/IllegalArgumentException

  public long getFilterEntries();
    Code:
       0: aload_0
       1: getfield      #2                  // Field generalBloomFilter:Lorg/apache/hadoop/hbase/util/BloomFilter;
       4: ifnull        19
       7: aload_0
       8: getfield      #2                  // Field generalBloomFilter:Lorg/apache/hadoop/hbase/util/BloomFilter;
      11: invokeinterface #147,  1          // InterfaceMethod org/apache/hadoop/hbase/util/BloomFilter.getKeyCount:()J
      16: goto          28
      19: aload_0
      20: getfield      #13                 // Field reader:Lorg/apache/hadoop/hbase/io/hfile/HFile$Reader;
      23: invokeinterface #148,  1          // InterfaceMethod org/apache/hadoop/hbase/io/hfile/HFile$Reader.getEntries:()J
      28: lreturn

  public void setGeneralBloomFilterFaulty();
    Code:
       0: aload_0
       1: aconst_null
       2: putfield      #2                  // Field generalBloomFilter:Lorg/apache/hadoop/hbase/util/BloomFilter;
       5: return

  public void setDeleteFamilyBloomFilterFaulty();
    Code:
       0: aload_0
       1: aconst_null
       2: putfield      #3                  // Field deleteFamilyBloomFilter:Lorg/apache/hadoop/hbase/util/BloomFilter;
       5: return

  public java.util.Optional<org.apache.hadoop.hbase.Cell> getLastKey();
    Code:
       0: aload_0
       1: getfield      #13                 // Field reader:Lorg/apache/hadoop/hbase/io/hfile/HFile$Reader;
       4: invokeinterface #149,  1          // InterfaceMethod org/apache/hadoop/hbase/io/hfile/HFile$Reader.getLastKey:()Ljava/util/Optional;
       9: areturn

  public java.util.Optional<byte[]> getLastRowKey();
    Code:
       0: aload_0
       1: getfield      #13                 // Field reader:Lorg/apache/hadoop/hbase/io/hfile/HFile$Reader;
       4: invokeinterface #150,  1          // InterfaceMethod org/apache/hadoop/hbase/io/hfile/HFile$Reader.getLastRowKey:()Ljava/util/Optional;
       9: areturn

  public java.util.Optional<org.apache.hadoop.hbase.Cell> midKey() throws java.io.IOException;
    Code:
       0: aload_0
       1: getfield      #13                 // Field reader:Lorg/apache/hadoop/hbase/io/hfile/HFile$Reader;
       4: invokeinterface #151,  1          // InterfaceMethod org/apache/hadoop/hbase/io/hfile/HFile$Reader.midKey:()Ljava/util/Optional;
       9: areturn

  public long length();
    Code:
       0: aload_0
       1: getfield      #13                 // Field reader:Lorg/apache/hadoop/hbase/io/hfile/HFile$Reader;
       4: invokeinterface #152,  1          // InterfaceMethod org/apache/hadoop/hbase/io/hfile/HFile$Reader.length:()J
       9: lreturn

  public long getTotalUncompressedBytes();
    Code:
       0: aload_0
       1: getfield      #13                 // Field reader:Lorg/apache/hadoop/hbase/io/hfile/HFile$Reader;
       4: invokeinterface #53,  1           // InterfaceMethod org/apache/hadoop/hbase/io/hfile/HFile$Reader.getTrailer:()Lorg/apache/hadoop/hbase/io/hfile/FixedFileTrailer;
       9: invokevirtual #153                // Method org/apache/hadoop/hbase/io/hfile/FixedFileTrailer.getTotalUncompressedBytes:()J
      12: lreturn

  public long getEntries();
    Code:
       0: aload_0
       1: getfield      #13                 // Field reader:Lorg/apache/hadoop/hbase/io/hfile/HFile$Reader;
       4: invokeinterface #148,  1          // InterfaceMethod org/apache/hadoop/hbase/io/hfile/HFile$Reader.getEntries:()J
       9: lreturn

  public long getDeleteFamilyCnt();
    Code:
       0: aload_0
       1: getfield      #8                  // Field deleteFamilyCnt:J
       4: lreturn

  public java.util.Optional<org.apache.hadoop.hbase.Cell> getFirstKey();
    Code:
       0: aload_0
       1: getfield      #13                 // Field reader:Lorg/apache/hadoop/hbase/io/hfile/HFile$Reader;
       4: invokeinterface #154,  1          // InterfaceMethod org/apache/hadoop/hbase/io/hfile/HFile$Reader.getFirstKey:()Ljava/util/Optional;
       9: areturn

  public long indexSize();
    Code:
       0: aload_0
       1: getfield      #13                 // Field reader:Lorg/apache/hadoop/hbase/io/hfile/HFile$Reader;
       4: invokeinterface #155,  1          // InterfaceMethod org/apache/hadoop/hbase/io/hfile/HFile$Reader.indexSize:()J
       9: lreturn

  public org.apache.hadoop.hbase.regionserver.BloomType getBloomFilterType();
    Code:
       0: aload_0
       1: getfield      #15                 // Field bloomFilterType:Lorg/apache/hadoop/hbase/regionserver/BloomType;
       4: areturn

  public long getSequenceID();
    Code:
       0: aload_0
       1: getfield      #6                  // Field sequenceID:J
       4: lreturn

  public void setSequenceID(long);
    Code:
       0: aload_0
       1: lload_1
       2: putfield      #6                  // Field sequenceID:J
       5: return

  public void setBulkLoaded(boolean);
    Code:
       0: aload_0
       1: iload_1
       2: putfield      #9                  // Field bulkLoadResult:Z
       5: return

  public boolean isBulkLoaded();
    Code:
       0: aload_0
       1: getfield      #9                  // Field bulkLoadResult:Z
       4: ireturn

  org.apache.hadoop.hbase.util.BloomFilter getGeneralBloomFilter();
    Code:
       0: aload_0
       1: getfield      #2                  // Field generalBloomFilter:Lorg/apache/hadoop/hbase/util/BloomFilter;
       4: areturn

  long getUncompressedDataIndexSize();
    Code:
       0: aload_0
       1: getfield      #13                 // Field reader:Lorg/apache/hadoop/hbase/io/hfile/HFile$Reader;
       4: invokeinterface #53,  1           // InterfaceMethod org/apache/hadoop/hbase/io/hfile/HFile$Reader.getTrailer:()Lorg/apache/hadoop/hbase/io/hfile/FixedFileTrailer;
       9: invokevirtual #156                // Method org/apache/hadoop/hbase/io/hfile/FixedFileTrailer.getUncompressedDataIndexSize:()J
      12: lreturn

  public long getTotalBloomSize();
    Code:
       0: aload_0
       1: getfield      #2                  // Field generalBloomFilter:Lorg/apache/hadoop/hbase/util/BloomFilter;
       4: ifnonnull     9
       7: lconst_0
       8: lreturn
       9: aload_0
      10: getfield      #2                  // Field generalBloomFilter:Lorg/apache/hadoop/hbase/util/BloomFilter;
      13: invokeinterface #157,  1          // InterfaceMethod org/apache/hadoop/hbase/util/BloomFilter.getByteSize:()J
      18: lreturn

  public int getHFileVersion();
    Code:
       0: aload_0
       1: getfield      #13                 // Field reader:Lorg/apache/hadoop/hbase/io/hfile/HFile$Reader;
       4: invokeinterface #53,  1           // InterfaceMethod org/apache/hadoop/hbase/io/hfile/HFile$Reader.getTrailer:()Lorg/apache/hadoop/hbase/io/hfile/FixedFileTrailer;
       9: invokevirtual #158                // Method org/apache/hadoop/hbase/io/hfile/FixedFileTrailer.getMajorVersion:()I
      12: ireturn

  public int getHFileMinorVersion();
    Code:
       0: aload_0
       1: getfield      #13                 // Field reader:Lorg/apache/hadoop/hbase/io/hfile/HFile$Reader;
       4: invokeinterface #53,  1           // InterfaceMethod org/apache/hadoop/hbase/io/hfile/HFile$Reader.getTrailer:()Lorg/apache/hadoop/hbase/io/hfile/FixedFileTrailer;
       9: invokevirtual #159                // Method org/apache/hadoop/hbase/io/hfile/FixedFileTrailer.getMinorVersion:()I
      12: ireturn

  public org.apache.hadoop.hbase.io.hfile.HFile$Reader getHFileReader();
    Code:
       0: aload_0
       1: getfield      #13                 // Field reader:Lorg/apache/hadoop/hbase/io/hfile/HFile$Reader;
       4: areturn

  void disableBloomFilterForTesting();
    Code:
       0: aload_0
       1: aconst_null
       2: putfield      #2                  // Field generalBloomFilter:Lorg/apache/hadoop/hbase/util/BloomFilter;
       5: aload_0
       6: aconst_null
       7: putfield      #3                  // Field deleteFamilyBloomFilter:Lorg/apache/hadoop/hbase/util/BloomFilter;
      10: return

  public long getMaxTimestamp();
    Code:
       0: aload_0
       1: getfield      #7                  // Field timeRange:Lorg/apache/hadoop/hbase/io/TimeRange;
       4: ifnonnull     13
       7: ldc2_w        #161                // long 9223372036854775807l
      10: goto          20
      13: aload_0
      14: getfield      #7                  // Field timeRange:Lorg/apache/hadoop/hbase/io/TimeRange;
      17: invokevirtual #40                 // Method org/apache/hadoop/hbase/io/TimeRange.getMax:()J
      20: lreturn

  boolean isSkipResetSeqId();
    Code:
       0: aload_0
       1: getfield      #11                 // Field skipResetSeqId:Z
       4: ireturn

  void setSkipResetSeqId(boolean);
    Code:
       0: aload_0
       1: iload_1
       2: putfield      #11                 // Field skipResetSeqId:Z
       5: return

  public int getPrefixLength();
    Code:
       0: aload_0
       1: getfield      #12                 // Field prefixLength:I
       4: ireturn

  static {};
    Code:
       0: ldc           #163                // class org/apache/hadoop/hbase/regionserver/StoreFileReader
       2: invokevirtual #164                // Method java/lang/Class.getName:()Ljava/lang/String;
       5: invokestatic  #165                // Method org/slf4j/LoggerFactory.getLogger:(Ljava/lang/String;)Lorg/slf4j/Logger;
       8: putstatic     #35                 // Field LOG:Lorg/slf4j/Logger;
      11: return
}
