Compiled from "StoreFlusher.java"
abstract class org.apache.hadoop.hbase.regionserver.StoreFlusher {
  protected org.apache.hadoop.conf.Configuration conf;

  protected org.apache.hadoop.hbase.regionserver.HStore store;

  static final boolean $assertionsDisabled;

  public org.apache.hadoop.hbase.regionserver.StoreFlusher(org.apache.hadoop.conf.Configuration, org.apache.hadoop.hbase.regionserver.HStore);
    Code:
       0: aload_0
       1: invokespecial #1                  // Method java/lang/Object."<init>":()V
       4: aload_0
       5: aload_1
       6: putfield      #2                  // Field conf:Lorg/apache/hadoop/conf/Configuration;
       9: aload_0
      10: aload_2
      11: putfield      #3                  // Field store:Lorg/apache/hadoop/hbase/regionserver/HStore;
      14: return

  public abstract java.util.List<org.apache.hadoop.fs.Path> flushSnapshot(org.apache.hadoop.hbase.regionserver.MemStoreSnapshot, long, org.apache.hadoop.hbase.monitoring.MonitoredTask, org.apache.hadoop.hbase.regionserver.throttle.ThroughputController, org.apache.hadoop.hbase.regionserver.FlushLifeCycleTracker) throws java.io.IOException;

  protected void finalizeWriter(org.apache.hadoop.hbase.regionserver.StoreFileWriter, long, org.apache.hadoop.hbase.monitoring.MonitoredTask) throws java.io.IOException;
    Code:
       0: aload         4
       2: new           #4                  // class java/lang/StringBuilder
       5: dup
       6: invokespecial #5                  // Method java/lang/StringBuilder."<init>":()V
       9: ldc           #6                  // String Flushing
      11: invokevirtual #7                  // Method java/lang/StringBuilder.append:(Ljava/lang/String;)Ljava/lang/StringBuilder;
      14: aload_0
      15: getfield      #3                  // Field store:Lorg/apache/hadoop/hbase/regionserver/HStore;
      18: invokevirtual #8                  // Method java/lang/StringBuilder.append:(Ljava/lang/Object;)Ljava/lang/StringBuilder;
      21: ldc           #9                  // String : appending metadata
      23: invokevirtual #7                  // Method java/lang/StringBuilder.append:(Ljava/lang/String;)Ljava/lang/StringBuilder;
      26: invokevirtual #10                 // Method java/lang/StringBuilder.toString:()Ljava/lang/String;
      29: invokeinterface #11,  2           // InterfaceMethod org/apache/hadoop/hbase/monitoring/MonitoredTask.setStatus:(Ljava/lang/String;)V
      34: aload_1
      35: lload_2
      36: iconst_0
      37: invokevirtual #12                 // Method org/apache/hadoop/hbase/regionserver/StoreFileWriter.appendMetadata:(JZ)V
      40: aload         4
      42: new           #4                  // class java/lang/StringBuilder
      45: dup
      46: invokespecial #5                  // Method java/lang/StringBuilder."<init>":()V
      49: ldc           #6                  // String Flushing
      51: invokevirtual #7                  // Method java/lang/StringBuilder.append:(Ljava/lang/String;)Ljava/lang/StringBuilder;
      54: aload_0
      55: getfield      #3                  // Field store:Lorg/apache/hadoop/hbase/regionserver/HStore;
      58: invokevirtual #8                  // Method java/lang/StringBuilder.append:(Ljava/lang/Object;)Ljava/lang/StringBuilder;
      61: ldc           #13                 // String : closing flushed file
      63: invokevirtual #7                  // Method java/lang/StringBuilder.append:(Ljava/lang/String;)Ljava/lang/StringBuilder;
      66: invokevirtual #10                 // Method java/lang/StringBuilder.toString:()Ljava/lang/String;
      69: invokeinterface #11,  2           // InterfaceMethod org/apache/hadoop/hbase/monitoring/MonitoredTask.setStatus:(Ljava/lang/String;)V
      74: aload_1
      75: invokevirtual #14                 // Method org/apache/hadoop/hbase/regionserver/StoreFileWriter.close:()V
      78: return

  protected final org.apache.hadoop.hbase.regionserver.InternalScanner createScanner(java.util.List<org.apache.hadoop.hbase.regionserver.KeyValueScanner>, long, org.apache.hadoop.hbase.regionserver.FlushLifeCycleTracker) throws java.io.IOException;
    Code:
       0: aload_0
       1: getfield      #3                  // Field store:Lorg/apache/hadoop/hbase/regionserver/HStore;
       4: invokevirtual #15                 // Method org/apache/hadoop/hbase/regionserver/HStore.getCoprocessorHost:()Lorg/apache/hadoop/hbase/regionserver/RegionCoprocessorHost;
       7: ifnull        31
      10: aload_0
      11: getfield      #3                  // Field store:Lorg/apache/hadoop/hbase/regionserver/HStore;
      14: invokevirtual #15                 // Method org/apache/hadoop/hbase/regionserver/HStore.getCoprocessorHost:()Lorg/apache/hadoop/hbase/regionserver/RegionCoprocessorHost;
      17: aload_0
      18: getfield      #3                  // Field store:Lorg/apache/hadoop/hbase/regionserver/HStore;
      21: aload         4
      23: invokevirtual #16                 // Method org/apache/hadoop/hbase/regionserver/RegionCoprocessorHost.preFlushScannerOpen:(Lorg/apache/hadoop/hbase/regionserver/HStore;Lorg/apache/hadoop/hbase/regionserver/FlushLifeCycleTracker;)Lorg/apache/hadoop/hbase/regionserver/ScanInfo;
      26: astore        5
      28: goto          40
      31: aload_0
      32: getfield      #3                  // Field store:Lorg/apache/hadoop/hbase/regionserver/HStore;
      35: invokevirtual #17                 // Method org/apache/hadoop/hbase/regionserver/HStore.getScanInfo:()Lorg/apache/hadoop/hbase/regionserver/ScanInfo;
      38: astore        5
      40: new           #18                 // class org/apache/hadoop/hbase/regionserver/StoreScanner
      43: dup
      44: aload_0
      45: getfield      #3                  // Field store:Lorg/apache/hadoop/hbase/regionserver/HStore;
      48: aload         5
      50: aload_1
      51: getstatic     #19                 // Field org/apache/hadoop/hbase/regionserver/ScanType.COMPACT_RETAIN_DELETES:Lorg/apache/hadoop/hbase/regionserver/ScanType;
      54: lload_2
      55: ldc2_w        #21                 // long -9223372036854775808l
      58: invokespecial #23                 // Method org/apache/hadoop/hbase/regionserver/StoreScanner."<init>":(Lorg/apache/hadoop/hbase/regionserver/HStore;Lorg/apache/hadoop/hbase/regionserver/ScanInfo;Ljava/util/List;Lorg/apache/hadoop/hbase/regionserver/ScanType;JJ)V
      61: astore        6
      63: getstatic     #24                 // Field $assertionsDisabled:Z
      66: ifne          82
      69: aload         6
      71: ifnonnull     82
      74: new           #25                 // class java/lang/AssertionError
      77: dup
      78: invokespecial #26                 // Method java/lang/AssertionError."<init>":()V
      81: athrow
      82: aload_0
      83: getfield      #3                  // Field store:Lorg/apache/hadoop/hbase/regionserver/HStore;
      86: invokevirtual #15                 // Method org/apache/hadoop/hbase/regionserver/HStore.getCoprocessorHost:()Lorg/apache/hadoop/hbase/regionserver/RegionCoprocessorHost;
      89: ifnull        123
      92: aload_0
      93: getfield      #3                  // Field store:Lorg/apache/hadoop/hbase/regionserver/HStore;
      96: invokevirtual #15                 // Method org/apache/hadoop/hbase/regionserver/HStore.getCoprocessorHost:()Lorg/apache/hadoop/hbase/regionserver/RegionCoprocessorHost;
      99: aload_0
     100: getfield      #3                  // Field store:Lorg/apache/hadoop/hbase/regionserver/HStore;
     103: aload         6
     105: aload         4
     107: invokevirtual #27                 // Method org/apache/hadoop/hbase/regionserver/RegionCoprocessorHost.preFlush:(Lorg/apache/hadoop/hbase/regionserver/HStore;Lorg/apache/hadoop/hbase/regionserver/InternalScanner;Lorg/apache/hadoop/hbase/regionserver/FlushLifeCycleTracker;)Lorg/apache/hadoop/hbase/regionserver/InternalScanner;
     110: areturn
     111: astore        7
     113: aload         6
     115: invokeinterface #29,  1           // InterfaceMethod org/apache/hadoop/hbase/regionserver/InternalScanner.close:()V
     120: aload         7
     122: athrow
     123: aload         6
     125: areturn
    Exception table:
       from    to  target type
          92   110   111   Class java/io/IOException

  protected void performFlush(org.apache.hadoop.hbase.regionserver.InternalScanner, org.apache.hadoop.hbase.regionserver.CellSink, long, org.apache.hadoop.hbase.regionserver.throttle.ThroughputController) throws java.io.IOException;
    Code:
       0: aload_0
       1: getfield      #2                  // Field conf:Lorg/apache/hadoop/conf/Configuration;
       4: ldc           #30                 // String hbase.hstore.compaction.kv.max
       6: bipush        10
       8: invokevirtual #31                 // Method org/apache/hadoop/conf/Configuration.getInt:(Ljava/lang/String;I)I
      11: istore        6
      13: invokestatic  #32                 // Method org/apache/hadoop/hbase/regionserver/ScannerContext.newBuilder:()Lorg/apache/hadoop/hbase/regionserver/ScannerContext$Builder;
      16: iload         6
      18: invokevirtual #33                 // Method org/apache/hadoop/hbase/regionserver/ScannerContext$Builder.setBatchLimit:(I)Lorg/apache/hadoop/hbase/regionserver/ScannerContext$Builder;
      21: invokevirtual #34                 // Method org/apache/hadoop/hbase/regionserver/ScannerContext$Builder.build:()Lorg/apache/hadoop/hbase/regionserver/ScannerContext;
      24: astore        7
      26: new           #35                 // class java/util/ArrayList
      29: dup
      30: invokespecial #36                 // Method java/util/ArrayList."<init>":()V
      33: astore        8
      35: aload_0
      36: getfield      #3                  // Field store:Lorg/apache/hadoop/hbase/regionserver/HStore;
      39: ldc           #37                 // String flush
      41: invokestatic  #38                 // Method org/apache/hadoop/hbase/regionserver/throttle/ThroughputControlUtil.getNameForThrottling:(Lorg/apache/hadoop/hbase/regionserver/HStore;Ljava/lang/String;)Ljava/lang/String;
      44: astore        10
      46: aload         5
      48: ifnull        73
      51: aload_0
      52: getfield      #3                  // Field store:Lorg/apache/hadoop/hbase/regionserver/HStore;
      55: invokevirtual #39                 // Method org/apache/hadoop/hbase/regionserver/HStore.getRegionInfo:()Lorg/apache/hadoop/hbase/client/RegionInfo;
      58: invokeinterface #40,  1           // InterfaceMethod org/apache/hadoop/hbase/client/RegionInfo.getTable:()Lorg/apache/hadoop/hbase/TableName;
      63: invokevirtual #41                 // Method org/apache/hadoop/hbase/TableName.isSystemTable:()Z
      66: ifne          73
      69: iconst_1
      70: goto          74
      73: iconst_0
      74: istore        11
      76: iload         11
      78: ifeq          90
      81: aload         5
      83: aload         10
      85: invokeinterface #42,  2           // InterfaceMethod org/apache/hadoop/hbase/regionserver/throttle/ThroughputController.start:(Ljava/lang/String;)V
      90: aload_1
      91: aload         8
      93: aload         7
      95: invokeinterface #43,  3           // InterfaceMethod org/apache/hadoop/hbase/regionserver/InternalScanner.next:(Ljava/util/List;Lorg/apache/hadoop/hbase/regionserver/ScannerContext;)Z
     100: istore        9
     102: aload         8
     104: invokeinterface #44,  1           // InterfaceMethod java/util/List.isEmpty:()Z
     109: ifne          184
     112: aload         8
     114: invokeinterface #45,  1           // InterfaceMethod java/util/List.iterator:()Ljava/util/Iterator;
     119: astore        12
     121: aload         12
     123: invokeinterface #46,  1           // InterfaceMethod java/util/Iterator.hasNext:()Z
     128: ifeq          177
     131: aload         12
     133: invokeinterface #47,  1           // InterfaceMethod java/util/Iterator.next:()Ljava/lang/Object;
     138: checkcast     #48                 // class org/apache/hadoop/hbase/Cell
     141: astore        13
     143: aload_2
     144: aload         13
     146: invokeinterface #49,  2           // InterfaceMethod org/apache/hadoop/hbase/regionserver/CellSink.append:(Lorg/apache/hadoop/hbase/Cell;)V
     151: iload         11
     153: ifeq          174
     156: aload         5
     158: aload         10
     160: aload         13
     162: invokeinterface #50,  1           // InterfaceMethod org/apache/hadoop/hbase/Cell.getSerializedSize:()I
     167: i2l
     168: invokeinterface #51,  4           // InterfaceMethod org/apache/hadoop/hbase/regionserver/throttle/ThroughputController.control:(Ljava/lang/String;J)J
     173: pop2
     174: goto          121
     177: aload         8
     179: invokeinterface #52,  1           // InterfaceMethod java/util/List.clear:()V
     184: iload         9
     186: ifne          90
     189: iload         11
     191: ifeq          255
     194: aload         5
     196: aload         10
     198: invokeinterface #53,  2           // InterfaceMethod org/apache/hadoop/hbase/regionserver/throttle/ThroughputController.finish:(Ljava/lang/String;)V
     203: goto          255
     206: astore        12
     208: new           #55                 // class java/io/InterruptedIOException
     211: dup
     212: new           #4                  // class java/lang/StringBuilder
     215: dup
     216: invokespecial #5                  // Method java/lang/StringBuilder."<init>":()V
     219: ldc           #56                 // String Interrupted while control throughput of flushing
     221: invokevirtual #7                  // Method java/lang/StringBuilder.append:(Ljava/lang/String;)Ljava/lang/StringBuilder;
     224: aload         10
     226: invokevirtual #7                  // Method java/lang/StringBuilder.append:(Ljava/lang/String;)Ljava/lang/StringBuilder;
     229: invokevirtual #10                 // Method java/lang/StringBuilder.toString:()Ljava/lang/String;
     232: invokespecial #57                 // Method java/io/InterruptedIOException."<init>":(Ljava/lang/String;)V
     235: athrow
     236: astore        14
     238: iload         11
     240: ifeq          252
     243: aload         5
     245: aload         10
     247: invokeinterface #53,  2           // InterfaceMethod org/apache/hadoop/hbase/regionserver/throttle/ThroughputController.finish:(Ljava/lang/String;)V
     252: aload         14
     254: athrow
     255: return
    Exception table:
       from    to  target type
          90   189   206   Class java/lang/InterruptedException
          90   189   236   any
         206   238   236   any

  static {};
    Code:
       0: ldc           #58                 // class org/apache/hadoop/hbase/regionserver/StoreFlusher
       2: invokevirtual #59                 // Method java/lang/Class.desiredAssertionStatus:()Z
       5: ifne          12
       8: iconst_1
       9: goto          13
      12: iconst_0
      13: putstatic     #24                 // Field $assertionsDisabled:Z
      16: return
}
