Compiled from "StoreScanner.java"
public class org.apache.hadoop.hbase.regionserver.StoreScanner extends org.apache.hadoop.hbase.regionserver.NonReversedNonLazyKeyValueScanner implements org.apache.hadoop.hbase.regionserver.KeyValueScanner,org.apache.hadoop.hbase.regionserver.InternalScanner,org.apache.hadoop.hbase.regionserver.ChangedReadersObserver {
  protected final org.apache.hadoop.hbase.regionserver.HStore store;

  protected org.apache.hadoop.hbase.regionserver.KeyValueHeap heap;

  static final boolean LAZY_SEEK_ENABLED_BY_DEFAULT;

  public static final java.lang.String STORESCANNER_PARALLEL_SEEK_ENABLE;

  public static final java.lang.String HBASE_CELLS_SCANNED_PER_HEARTBEAT_CHECK;

  public static final long DEFAULT_HBASE_CELLS_SCANNED_PER_HEARTBEAT_CHECK;

  public static final java.lang.String STORESCANNER_PREAD_MAX_BYTES;

  final java.util.List<org.apache.hadoop.hbase.regionserver.KeyValueScanner> currentScanners;

  protected final long readPt;

  static final boolean $assertionsDisabled;

  public org.apache.hadoop.hbase.regionserver.StoreScanner(org.apache.hadoop.hbase.regionserver.HStore, org.apache.hadoop.hbase.regionserver.ScanInfo, org.apache.hadoop.hbase.client.Scan, java.util.NavigableSet<byte[]>, long) throws java.io.IOException;
    Code:
       0: aload_0
       1: aload_1
       2: aload_3
       3: aload_2
       4: aload         4
       6: ifnull        19
       9: aload         4
      11: invokeinterface #62,  1           // InterfaceMethod java/util/NavigableSet.size:()I
      16: goto          20
      19: iconst_0
      20: lload         5
      22: aload_3
      23: invokevirtual #63                 // Method org/apache/hadoop/hbase/client/Scan.getCacheBlocks:()Z
      26: getstatic     #46                 // Field org/apache/hadoop/hbase/regionserver/ScanType.USER_SCAN:Lorg/apache/hadoop/hbase/regionserver/ScanType;
      29: invokespecial #64                 // Method "<init>":(Lorg/apache/hadoop/hbase/regionserver/HStore;Lorg/apache/hadoop/hbase/client/Scan;Lorg/apache/hadoop/hbase/regionserver/ScanInfo;IJZLorg/apache/hadoop/hbase/regionserver/ScanType;)V
      32: aload         4
      34: ifnull        54
      37: aload_3
      38: invokevirtual #35                 // Method org/apache/hadoop/hbase/client/Scan.isRaw:()Z
      41: ifeq          54
      44: new           #65                 // class org/apache/hadoop/hbase/DoNotRetryIOException
      47: dup
      48: ldc           #66                 // String Cannot specify any column for a raw scan
      50: invokespecial #67                 // Method org/apache/hadoop/hbase/DoNotRetryIOException."<init>":(Ljava/lang/String;)V
      53: athrow
      54: aload_0
      55: aload_3
      56: aload_2
      57: aload         4
      59: aload_0
      60: getfield      #37                 // Field oldestUnexpiredTS:J
      63: aload_0
      64: getfield      #34                 // Field now:J
      67: aload_1
      68: invokevirtual #68                 // Method org/apache/hadoop/hbase/regionserver/HStore.getCoprocessorHost:()Lorg/apache/hadoop/hbase/regionserver/RegionCoprocessorHost;
      71: invokestatic  #69                 // Method org/apache/hadoop/hbase/regionserver/querymatcher/UserScanQueryMatcher.create:(Lorg/apache/hadoop/hbase/client/Scan;Lorg/apache/hadoop/hbase/regionserver/ScanInfo;Ljava/util/NavigableSet;JJLorg/apache/hadoop/hbase/regionserver/RegionCoprocessorHost;)Lorg/apache/hadoop/hbase/regionserver/querymatcher/UserScanQueryMatcher;
      74: putfield      #70                 // Field matcher:Lorg/apache/hadoop/hbase/regionserver/querymatcher/ScanQueryMatcher;
      77: aload_1
      78: aload_0
      79: invokevirtual #71                 // Method org/apache/hadoop/hbase/regionserver/HStore.addChangedReaderObserver:(Lorg/apache/hadoop/hbase/regionserver/ChangedReadersObserver;)V
      82: aload_0
      83: aload_1
      84: aload_1
      85: aload_0
      86: getfield      #24                 // Field cacheBlocks:Z
      89: aload_0
      90: getfield      #45                 // Field scanUsePread:Z
      93: iconst_0
      94: aload_0
      95: getfield      #70                 // Field matcher:Lorg/apache/hadoop/hbase/regionserver/querymatcher/ScanQueryMatcher;
      98: aload_3
      99: invokevirtual #72                 // Method org/apache/hadoop/hbase/client/Scan.getStartRow:()[B
     102: aload_3
     103: invokevirtual #73                 // Method org/apache/hadoop/hbase/client/Scan.includeStartRow:()Z
     106: aload_3
     107: invokevirtual #74                 // Method org/apache/hadoop/hbase/client/Scan.getStopRow:()[B
     110: aload_3
     111: invokevirtual #75                 // Method org/apache/hadoop/hbase/client/Scan.includeStopRow:()Z
     114: aload_0
     115: getfield      #22                 // Field readPt:J
     118: invokevirtual #76                 // Method org/apache/hadoop/hbase/regionserver/HStore.getScanners:(ZZZLorg/apache/hadoop/hbase/regionserver/querymatcher/ScanQueryMatcher;[BZ[BZJ)Ljava/util/List;
     121: invokevirtual #77                 // Method selectScannersFrom:(Lorg/apache/hadoop/hbase/regionserver/HStore;Ljava/util/List;)Ljava/util/List;
     124: astore        7
     126: aload_0
     127: aload         7
     129: aload_0
     130: getfield      #70                 // Field matcher:Lorg/apache/hadoop/hbase/regionserver/querymatcher/ScanQueryMatcher;
     133: invokevirtual #78                 // Method org/apache/hadoop/hbase/regionserver/querymatcher/ScanQueryMatcher.getStartKey:()Lorg/apache/hadoop/hbase/Cell;
     136: aload_0
     137: getfield      #31                 // Field explicitColumnQuery:Z
     140: ifeq          153
     143: getstatic     #79                 // Field lazySeekEnabledGlobally:Z
     146: ifeq          153
     149: iconst_1
     150: goto          154
     153: iconst_0
     154: aload_0
     155: getfield      #6                  // Field parallelSeekEnabled:Z
     158: invokevirtual #80                 // Method seekScanners:(Ljava/util/List;Lorg/apache/hadoop/hbase/Cell;ZZ)V
     161: aload_0
     162: aload_3
     163: invokevirtual #81                 // Method org/apache/hadoop/hbase/client/Scan.getMaxResultsPerColumnFamily:()I
     166: putfield      #3                  // Field storeLimit:I
     169: aload_0
     170: aload_3
     171: invokevirtual #82                 // Method org/apache/hadoop/hbase/client/Scan.getRowOffsetPerColumnFamily:()I
     174: putfield      #4                  // Field storeOffset:I
     177: aload_0
     178: aload         7
     180: invokespecial #83                 // Method addCurrentScanners:(Ljava/util/List;)V
     183: aload_0
     184: aload         7
     186: aload_0
     187: getfield      #28                 // Field comparator:Lorg/apache/hadoop/hbase/CellComparator;
     190: invokevirtual #84                 // Method resetKVHeap:(Ljava/util/List;Lorg/apache/hadoop/hbase/CellComparator;)V
     193: goto          206
     196: astore        7
     198: aload_1
     199: aload_0
     200: invokevirtual #86                 // Method org/apache/hadoop/hbase/regionserver/HStore.deleteChangedReaderObserver:(Lorg/apache/hadoop/hbase/regionserver/ChangedReadersObserver;)V
     203: aload         7
     205: athrow
     206: return
    Exception table:
       from    to  target type
          82   193   196   Class java/io/IOException

  public org.apache.hadoop.hbase.regionserver.StoreScanner(org.apache.hadoop.hbase.regionserver.HStore, org.apache.hadoop.hbase.regionserver.ScanInfo, java.util.List<? extends org.apache.hadoop.hbase.regionserver.KeyValueScanner>, org.apache.hadoop.hbase.regionserver.ScanType, long, long) throws java.io.IOException;
    Code:
       0: aload_0
       1: aload_1
       2: aload_2
       3: aload_3
       4: aload         4
       6: lload         5
       8: lload         7
      10: aconst_null
      11: aconst_null
      12: invokespecial #87                 // Method "<init>":(Lorg/apache/hadoop/hbase/regionserver/HStore;Lorg/apache/hadoop/hbase/regionserver/ScanInfo;Ljava/util/List;Lorg/apache/hadoop/hbase/regionserver/ScanType;JJ[B[B)V
      15: return

  public org.apache.hadoop.hbase.regionserver.StoreScanner(org.apache.hadoop.hbase.regionserver.HStore, org.apache.hadoop.hbase.regionserver.ScanInfo, java.util.List<? extends org.apache.hadoop.hbase.regionserver.KeyValueScanner>, long, long, byte[], byte[]) throws java.io.IOException;
    Code:
       0: aload_0
       1: aload_1
       2: aload_2
       3: aload_3
       4: getstatic     #88                 // Field org/apache/hadoop/hbase/regionserver/ScanType.COMPACT_RETAIN_DELETES:Lorg/apache/hadoop/hbase/regionserver/ScanType;
       7: lload         4
       9: lload         6
      11: aload         8
      13: aload         9
      15: invokespecial #87                 // Method "<init>":(Lorg/apache/hadoop/hbase/regionserver/HStore;Lorg/apache/hadoop/hbase/regionserver/ScanInfo;Ljava/util/List;Lorg/apache/hadoop/hbase/regionserver/ScanType;JJ[B[B)V
      18: return

  public org.apache.hadoop.hbase.regionserver.StoreScanner(org.apache.hadoop.hbase.regionserver.ScanInfo, org.apache.hadoop.hbase.regionserver.ScanType, java.util.List<? extends org.apache.hadoop.hbase.regionserver.KeyValueScanner>) throws java.io.IOException;
    Code:
       0: aload_0
       1: aconst_null
       2: getstatic     #89                 // Field SCAN_FOR_COMPACTION:Lorg/apache/hadoop/hbase/client/Scan;
       5: aload_1
       6: iconst_0
       7: ldc2_w        #97                 // long 9223372036854775807l
      10: iconst_0
      11: aload_2
      12: invokespecial #64                 // Method "<init>":(Lorg/apache/hadoop/hbase/regionserver/HStore;Lorg/apache/hadoop/hbase/client/Scan;Lorg/apache/hadoop/hbase/regionserver/ScanInfo;IJZLorg/apache/hadoop/hbase/regionserver/ScanType;)V
      15: getstatic     #92                 // Field $assertionsDisabled:Z
      18: ifne          36
      21: aload_2
      22: getstatic     #46                 // Field org/apache/hadoop/hbase/regionserver/ScanType.USER_SCAN:Lorg/apache/hadoop/hbase/regionserver/ScanType;
      25: if_acmpne     36
      28: new           #93                 // class java/lang/AssertionError
      31: dup
      32: invokespecial #94                 // Method java/lang/AssertionError."<init>":()V
      35: athrow
      36: aload_0
      37: aload_1
      38: aload_2
      39: ldc2_w        #97                 // long 9223372036854775807l
      42: lconst_0
      43: aload_0
      44: getfield      #37                 // Field oldestUnexpiredTS:J
      47: aload_0
      48: getfield      #34                 // Field now:J
      51: aconst_null
      52: aconst_null
      53: aconst_null
      54: invokestatic  #95                 // Method org/apache/hadoop/hbase/regionserver/querymatcher/CompactionScanQueryMatcher.create:(Lorg/apache/hadoop/hbase/regionserver/ScanInfo;Lorg/apache/hadoop/hbase/regionserver/ScanType;JJJJ[B[BLorg/apache/hadoop/hbase/regionserver/RegionCoprocessorHost;)Lorg/apache/hadoop/hbase/regionserver/querymatcher/CompactionScanQueryMatcher;
      57: putfield      #70                 // Field matcher:Lorg/apache/hadoop/hbase/regionserver/querymatcher/ScanQueryMatcher;
      60: aload_0
      61: aload_1
      62: aload_3
      63: invokespecial #99                 // Method seekAllScanner:(Lorg/apache/hadoop/hbase/regionserver/ScanInfo;Ljava/util/List;)V
      66: return

  org.apache.hadoop.hbase.regionserver.StoreScanner(org.apache.hadoop.hbase.client.Scan, org.apache.hadoop.hbase.regionserver.ScanInfo, java.util.NavigableSet<byte[]>, java.util.List<? extends org.apache.hadoop.hbase.regionserver.KeyValueScanner>) throws java.io.IOException;
    Code:
       0: aload_0
       1: aconst_null
       2: aload_1
       3: aload_2
       4: aload_3
       5: ifnull        17
       8: aload_3
       9: invokeinterface #62,  1           // InterfaceMethod java/util/NavigableSet.size:()I
      14: goto          18
      17: iconst_0
      18: lconst_0
      19: aload_1
      20: invokevirtual #63                 // Method org/apache/hadoop/hbase/client/Scan.getCacheBlocks:()Z
      23: getstatic     #46                 // Field org/apache/hadoop/hbase/regionserver/ScanType.USER_SCAN:Lorg/apache/hadoop/hbase/regionserver/ScanType;
      26: invokespecial #64                 // Method "<init>":(Lorg/apache/hadoop/hbase/regionserver/HStore;Lorg/apache/hadoop/hbase/client/Scan;Lorg/apache/hadoop/hbase/regionserver/ScanInfo;IJZLorg/apache/hadoop/hbase/regionserver/ScanType;)V
      29: aload_0
      30: aload_1
      31: aload_2
      32: aload_3
      33: aload_0
      34: getfield      #37                 // Field oldestUnexpiredTS:J
      37: aload_0
      38: getfield      #34                 // Field now:J
      41: aconst_null
      42: invokestatic  #69                 // Method org/apache/hadoop/hbase/regionserver/querymatcher/UserScanQueryMatcher.create:(Lorg/apache/hadoop/hbase/client/Scan;Lorg/apache/hadoop/hbase/regionserver/ScanInfo;Ljava/util/NavigableSet;JJLorg/apache/hadoop/hbase/regionserver/RegionCoprocessorHost;)Lorg/apache/hadoop/hbase/regionserver/querymatcher/UserScanQueryMatcher;
      45: putfield      #70                 // Field matcher:Lorg/apache/hadoop/hbase/regionserver/querymatcher/ScanQueryMatcher;
      48: aload_0
      49: aload_2
      50: aload         4
      52: invokespecial #99                 // Method seekAllScanner:(Lorg/apache/hadoop/hbase/regionserver/ScanInfo;Ljava/util/List;)V
      55: return

  org.apache.hadoop.hbase.regionserver.StoreScanner(org.apache.hadoop.hbase.regionserver.ScanInfo, java.util.OptionalInt, org.apache.hadoop.hbase.regionserver.ScanType, java.util.List<? extends org.apache.hadoop.hbase.regionserver.KeyValueScanner>) throws java.io.IOException;
    Code:
       0: aload_0
       1: aconst_null
       2: aload_2
       3: invokevirtual #100                // Method java/util/OptionalInt.isPresent:()Z
       6: ifeq          26
       9: new           #101                // class org/apache/hadoop/hbase/client/Scan
      12: dup
      13: invokespecial #102                // Method org/apache/hadoop/hbase/client/Scan."<init>":()V
      16: aload_2
      17: invokevirtual #103                // Method java/util/OptionalInt.getAsInt:()I
      20: invokevirtual #104                // Method org/apache/hadoop/hbase/client/Scan.readVersions:(I)Lorg/apache/hadoop/hbase/client/Scan;
      23: goto          29
      26: getstatic     #89                 // Field SCAN_FOR_COMPACTION:Lorg/apache/hadoop/hbase/client/Scan;
      29: aload_1
      30: iconst_0
      31: lconst_0
      32: iconst_0
      33: aload_3
      34: invokespecial #64                 // Method "<init>":(Lorg/apache/hadoop/hbase/regionserver/HStore;Lorg/apache/hadoop/hbase/client/Scan;Lorg/apache/hadoop/hbase/regionserver/ScanInfo;IJZLorg/apache/hadoop/hbase/regionserver/ScanType;)V
      37: aload_0
      38: aload_1
      39: aload_3
      40: ldc2_w        #97                 // long 9223372036854775807l
      43: ldc2_w        #106                // long -9223372036854775808l
      46: aload_0
      47: getfield      #37                 // Field oldestUnexpiredTS:J
      50: aload_0
      51: getfield      #34                 // Field now:J
      54: aconst_null
      55: aconst_null
      56: aconst_null
      57: invokestatic  #95                 // Method org/apache/hadoop/hbase/regionserver/querymatcher/CompactionScanQueryMatcher.create:(Lorg/apache/hadoop/hbase/regionserver/ScanInfo;Lorg/apache/hadoop/hbase/regionserver/ScanType;JJJJ[B[BLorg/apache/hadoop/hbase/regionserver/RegionCoprocessorHost;)Lorg/apache/hadoop/hbase/regionserver/querymatcher/CompactionScanQueryMatcher;
      60: putfield      #70                 // Field matcher:Lorg/apache/hadoop/hbase/regionserver/querymatcher/ScanQueryMatcher;
      63: aload_0
      64: aload_1
      65: aload         4
      67: invokespecial #99                 // Method seekAllScanner:(Lorg/apache/hadoop/hbase/regionserver/ScanInfo;Ljava/util/List;)V
      70: return

  boolean isScanUsePread();
    Code:
       0: aload_0
       1: getfield      #45                 // Field scanUsePread:Z
       4: ireturn

  protected void seekScanners(java.util.List<? extends org.apache.hadoop.hbase.regionserver.KeyValueScanner>, org.apache.hadoop.hbase.Cell, boolean, boolean) throws java.io.IOException;
    Code:
       0: iload_3
       1: ifeq          51
       4: aload_1
       5: invokeinterface #108,  1          // InterfaceMethod java/util/List.iterator:()Ljava/util/Iterator;
      10: astore        5
      12: aload         5
      14: invokeinterface #109,  1          // InterfaceMethod java/util/Iterator.hasNext:()Z
      19: ifeq          48
      22: aload         5
      24: invokeinterface #110,  1          // InterfaceMethod java/util/Iterator.next:()Ljava/lang/Object;
      29: checkcast     #111                // class org/apache/hadoop/hbase/regionserver/KeyValueScanner
      32: astore        6
      34: aload         6
      36: aload_2
      37: iconst_0
      38: iconst_1
      39: invokeinterface #112,  4          // InterfaceMethod org/apache/hadoop/hbase/regionserver/KeyValueScanner.requestSeek:(Lorg/apache/hadoop/hbase/Cell;ZZ)Z
      44: pop
      45: goto          12
      48: goto          190
      51: iload         4
      53: ifne          184
      56: lconst_0
      57: lstore        5
      59: aload_1
      60: invokeinterface #108,  1          // InterfaceMethod java/util/List.iterator:()Ljava/util/Iterator;
      65: astore        7
      67: aload         7
      69: invokeinterface #109,  1          // InterfaceMethod java/util/Iterator.hasNext:()Z
      74: ifeq          181
      77: aload         7
      79: invokeinterface #110,  1          // InterfaceMethod java/util/Iterator.next:()Ljava/lang/Object;
      84: checkcast     #111                // class org/apache/hadoop/hbase/regionserver/KeyValueScanner
      87: astore        8
      89: aload_0
      90: getfield      #70                 // Field matcher:Lorg/apache/hadoop/hbase/regionserver/querymatcher/ScanQueryMatcher;
      93: invokevirtual #113                // Method org/apache/hadoop/hbase/regionserver/querymatcher/ScanQueryMatcher.isUserScan:()Z
      96: ifeq          144
      99: lload         5
     101: aload_0
     102: getfield      #42                 // Field maxRowSize:J
     105: lcmp
     106: iflt          144
     109: new           #114                // class org/apache/hadoop/hbase/regionserver/RowTooBigException
     112: dup
     113: new           #115                // class java/lang/StringBuilder
     116: dup
     117: invokespecial #116                // Method java/lang/StringBuilder."<init>":()V
     120: ldc           #117                // String Max row size allowed:
     122: invokevirtual #118                // Method java/lang/StringBuilder.append:(Ljava/lang/String;)Ljava/lang/StringBuilder;
     125: aload_0
     126: getfield      #42                 // Field maxRowSize:J
     129: invokevirtual #119                // Method java/lang/StringBuilder.append:(J)Ljava/lang/StringBuilder;
     132: ldc           #120                // String , but row is bigger than that
     134: invokevirtual #118                // Method java/lang/StringBuilder.append:(Ljava/lang/String;)Ljava/lang/StringBuilder;
     137: invokevirtual #121                // Method java/lang/StringBuilder.toString:()Ljava/lang/String;
     140: invokespecial #122                // Method org/apache/hadoop/hbase/regionserver/RowTooBigException."<init>":(Ljava/lang/String;)V
     143: athrow
     144: aload         8
     146: aload_2
     147: invokeinterface #123,  2          // InterfaceMethod org/apache/hadoop/hbase/regionserver/KeyValueScanner.seek:(Lorg/apache/hadoop/hbase/Cell;)Z
     152: pop
     153: aload         8
     155: invokeinterface #124,  1          // InterfaceMethod org/apache/hadoop/hbase/regionserver/KeyValueScanner.peek:()Lorg/apache/hadoop/hbase/Cell;
     160: astore        9
     162: aload         9
     164: ifnull        178
     167: lload         5
     169: aload         9
     171: invokestatic  #125                // Method org/apache/hadoop/hbase/PrivateCellUtil.estimatedSerializedSizeOf:(Lorg/apache/hadoop/hbase/Cell;)I
     174: i2l
     175: ladd
     176: lstore        5
     178: goto          67
     181: goto          190
     184: aload_0
     185: aload_1
     186: aload_2
     187: invokespecial #126                // Method parallelSeek:(Ljava/util/List;Lorg/apache/hadoop/hbase/Cell;)V
     190: return

  protected void resetKVHeap(java.util.List<? extends org.apache.hadoop.hbase.regionserver.KeyValueScanner>, org.apache.hadoop.hbase.CellComparator) throws java.io.IOException;
    Code:
       0: aload_0
       1: aload_0
       2: aload_1
       3: aload_2
       4: invokevirtual #127                // Method newKVHeap:(Ljava/util/List;Lorg/apache/hadoop/hbase/CellComparator;)Lorg/apache/hadoop/hbase/regionserver/KeyValueHeap;
       7: putfield      #128                // Field heap:Lorg/apache/hadoop/hbase/regionserver/KeyValueHeap;
      10: return

  protected org.apache.hadoop.hbase.regionserver.KeyValueHeap newKVHeap(java.util.List<? extends org.apache.hadoop.hbase.regionserver.KeyValueScanner>, org.apache.hadoop.hbase.CellComparator) throws java.io.IOException;
    Code:
       0: new           #129                // class org/apache/hadoop/hbase/regionserver/KeyValueHeap
       3: dup
       4: aload_1
       5: aload_2
       6: invokespecial #130                // Method org/apache/hadoop/hbase/regionserver/KeyValueHeap."<init>":(Ljava/util/List;Lorg/apache/hadoop/hbase/CellComparator;)V
       9: areturn

  protected java.util.List<org.apache.hadoop.hbase.regionserver.KeyValueScanner> selectScannersFrom(org.apache.hadoop.hbase.regionserver.HStore, java.util.List<? extends org.apache.hadoop.hbase.regionserver.KeyValueScanner>);
    Code:
       0: aload_0
       1: getfield      #32                 // Field scan:Lorg/apache/hadoop/hbase/client/Scan;
       4: instanceof    #131                // class org/apache/hadoop/hbase/regionserver/InternalScan
       7: ifeq          35
      10: aload_0
      11: getfield      #32                 // Field scan:Lorg/apache/hadoop/hbase/client/Scan;
      14: checkcast     #131                // class org/apache/hadoop/hbase/regionserver/InternalScan
      17: astore        5
      19: aload         5
      21: invokevirtual #132                // Method org/apache/hadoop/hbase/regionserver/InternalScan.isCheckOnlyMemStore:()Z
      24: istore_3
      25: aload         5
      27: invokevirtual #133                // Method org/apache/hadoop/hbase/regionserver/InternalScan.isCheckOnlyStoreFiles:()Z
      30: istore        4
      32: goto          40
      35: iconst_0
      36: istore_3
      37: iconst_0
      38: istore        4
      40: new           #7                  // class java/util/ArrayList
      43: dup
      44: aload_2
      45: invokeinterface #134,  1          // InterfaceMethod java/util/List.size:()I
      50: invokespecial #13                 // Method java/util/ArrayList."<init>":(I)V
      53: astore        5
      55: aload_0
      56: getfield      #39                 // Field minVersions:I
      59: ifne          69
      62: aload_0
      63: getfield      #37                 // Field oldestUnexpiredTS:J
      66: goto          72
      69: ldc2_w        #106                // long -9223372036854775808l
      72: lstore        6
      74: aload_2
      75: invokeinterface #108,  1          // InterfaceMethod java/util/List.iterator:()Ljava/util/Iterator;
      80: astore        8
      82: aload         8
      84: invokeinterface #109,  1          // InterfaceMethod java/util/Iterator.hasNext:()Z
      89: ifeq          175
      92: aload         8
      94: invokeinterface #110,  1          // InterfaceMethod java/util/Iterator.next:()Ljava/lang/Object;
      99: checkcast     #111                // class org/apache/hadoop/hbase/regionserver/KeyValueScanner
     102: astore        9
     104: aload         9
     106: invokeinterface #135,  1          // InterfaceMethod org/apache/hadoop/hbase/regionserver/KeyValueScanner.isFileScanner:()Z
     111: istore        10
     113: iload         10
     115: ifne          123
     118: iload         4
     120: ifne          82
     123: iload         10
     125: ifeq          135
     128: iload_3
     129: ifeq          135
     132: goto          82
     135: aload         9
     137: aload_0
     138: getfield      #32                 // Field scan:Lorg/apache/hadoop/hbase/client/Scan;
     141: aload_1
     142: lload         6
     144: invokeinterface #136,  5          // InterfaceMethod org/apache/hadoop/hbase/regionserver/KeyValueScanner.shouldUseScanner:(Lorg/apache/hadoop/hbase/client/Scan;Lorg/apache/hadoop/hbase/regionserver/HStore;J)Z
     149: ifeq          165
     152: aload         5
     154: aload         9
     156: invokeinterface #137,  2          // InterfaceMethod java/util/List.add:(Ljava/lang/Object;)Z
     161: pop
     162: goto          172
     165: aload         9
     167: invokeinterface #138,  1          // InterfaceMethod org/apache/hadoop/hbase/regionserver/KeyValueScanner.close:()V
     172: goto          82
     175: aload         5
     177: areturn

  public org.apache.hadoop.hbase.Cell peek();
    Code:
       0: aload_0
       1: getfield      #128                // Field heap:Lorg/apache/hadoop/hbase/regionserver/KeyValueHeap;
       4: ifnull        17
       7: aload_0
       8: getfield      #128                // Field heap:Lorg/apache/hadoop/hbase/regionserver/KeyValueHeap;
      11: invokevirtual #139                // Method org/apache/hadoop/hbase/regionserver/KeyValueHeap.peek:()Lorg/apache/hadoop/hbase/Cell;
      14: goto          18
      17: aconst_null
      18: areturn

  public org.apache.hadoop.hbase.KeyValue next();
    Code:
       0: new           #140                // class java/lang/RuntimeException
       3: dup
       4: ldc           #141                // String Never call StoreScanner.next()
       6: invokespecial #142                // Method java/lang/RuntimeException."<init>":(Ljava/lang/String;)V
       9: athrow

  public void close();
    Code:
       0: aload_0
       1: iconst_1
       2: invokespecial #143                // Method close:(Z)V
       5: return

  public boolean seek(org.apache.hadoop.hbase.Cell) throws java.io.IOException;
    Code:
       0: aload_0
       1: invokevirtual #149                // Method checkFlushed:()Z
       4: ifeq          12
       7: aload_0
       8: invokevirtual #150                // Method reopenAfterFlush:()Z
      11: pop
      12: aload_0
      13: getfield      #128                // Field heap:Lorg/apache/hadoop/hbase/regionserver/KeyValueHeap;
      16: aload_1
      17: invokevirtual #151                // Method org/apache/hadoop/hbase/regionserver/KeyValueHeap.seek:(Lorg/apache/hadoop/hbase/Cell;)Z
      20: ireturn

  public boolean next(java.util.List<org.apache.hadoop.hbase.Cell>, org.apache.hadoop.hbase.regionserver.ScannerContext) throws java.io.IOException;
    Code:
       0: aload_2
       1: ifnonnull     14
       4: new           #152                // class java/lang/IllegalArgumentException
       7: dup
       8: ldc           #153                // String Scanner context cannot be null
      10: invokespecial #154                // Method java/lang/IllegalArgumentException."<init>":(Ljava/lang/String;)V
      13: athrow
      14: aload_0
      15: invokevirtual #149                // Method checkFlushed:()Z
      18: ifeq          39
      21: aload_0
      22: invokevirtual #150                // Method reopenAfterFlush:()Z
      25: ifeq          39
      28: aload_2
      29: getstatic     #155                // Field org/apache/hadoop/hbase/regionserver/ScannerContext$NextState.MORE_VALUES:Lorg/apache/hadoop/hbase/regionserver/ScannerContext$NextState;
      32: invokevirtual #156                // Method org/apache/hadoop/hbase/regionserver/ScannerContext.setScannerState:(Lorg/apache/hadoop/hbase/regionserver/ScannerContext$NextState;)Lorg/apache/hadoop/hbase/regionserver/ScannerContext$NextState;
      35: invokevirtual #157                // Method org/apache/hadoop/hbase/regionserver/ScannerContext$NextState.hasMoreValues:()Z
      38: ireturn
      39: aload_0
      40: getfield      #128                // Field heap:Lorg/apache/hadoop/hbase/regionserver/KeyValueHeap;
      43: ifnonnull     62
      46: aload_0
      47: iconst_0
      48: invokespecial #143                // Method close:(Z)V
      51: aload_2
      52: getstatic     #158                // Field org/apache/hadoop/hbase/regionserver/ScannerContext$NextState.NO_MORE_VALUES:Lorg/apache/hadoop/hbase/regionserver/ScannerContext$NextState;
      55: invokevirtual #156                // Method org/apache/hadoop/hbase/regionserver/ScannerContext.setScannerState:(Lorg/apache/hadoop/hbase/regionserver/ScannerContext$NextState;)Lorg/apache/hadoop/hbase/regionserver/ScannerContext$NextState;
      58: invokevirtual #157                // Method org/apache/hadoop/hbase/regionserver/ScannerContext$NextState.hasMoreValues:()Z
      61: ireturn
      62: aload_0
      63: getfield      #128                // Field heap:Lorg/apache/hadoop/hbase/regionserver/KeyValueHeap;
      66: invokevirtual #139                // Method org/apache/hadoop/hbase/regionserver/KeyValueHeap.peek:()Lorg/apache/hadoop/hbase/Cell;
      69: astore_3
      70: aload_3
      71: ifnonnull     90
      74: aload_0
      75: iconst_0
      76: invokespecial #143                // Method close:(Z)V
      79: aload_2
      80: getstatic     #158                // Field org/apache/hadoop/hbase/regionserver/ScannerContext$NextState.NO_MORE_VALUES:Lorg/apache/hadoop/hbase/regionserver/ScannerContext$NextState;
      83: invokevirtual #156                // Method org/apache/hadoop/hbase/regionserver/ScannerContext.setScannerState:(Lorg/apache/hadoop/hbase/regionserver/ScannerContext$NextState;)Lorg/apache/hadoop/hbase/regionserver/ScannerContext$NextState;
      86: invokevirtual #157                // Method org/apache/hadoop/hbase/regionserver/ScannerContext$NextState.hasMoreValues:()Z
      89: ireturn
      90: aload_2
      91: getstatic     #159                // Field org/apache/hadoop/hbase/regionserver/ScannerContext$LimitScope.BETWEEN_CELLS:Lorg/apache/hadoop/hbase/regionserver/ScannerContext$LimitScope;
      94: invokevirtual #160                // Method org/apache/hadoop/hbase/regionserver/ScannerContext.hasAnyLimit:(Lorg/apache/hadoop/hbase/regionserver/ScannerContext$LimitScope;)Z
      97: ifeq          110
     100: aload_0
     101: getfield      #70                 // Field matcher:Lorg/apache/hadoop/hbase/regionserver/querymatcher/ScanQueryMatcher;
     104: invokevirtual #161                // Method org/apache/hadoop/hbase/regionserver/querymatcher/ScanQueryMatcher.currentRow:()Lorg/apache/hadoop/hbase/Cell;
     107: ifnonnull     123
     110: aload_0
     111: lconst_0
     112: putfield      #2                  // Field countPerRow:J
     115: aload_0
     116: getfield      #70                 // Field matcher:Lorg/apache/hadoop/hbase/regionserver/querymatcher/ScanQueryMatcher;
     119: aload_3
     120: invokevirtual #162                // Method org/apache/hadoop/hbase/regionserver/querymatcher/ScanQueryMatcher.setToNewRow:(Lorg/apache/hadoop/hbase/Cell;)V
     123: aload_2
     124: invokevirtual #163                // Method org/apache/hadoop/hbase/regionserver/ScannerContext.getKeepProgress:()Z
     127: ifne          134
     130: aload_2
     131: invokevirtual #164                // Method org/apache/hadoop/hbase/regionserver/ScannerContext.clearProgress:()V
     134: iconst_0
     135: istore        4
     137: lconst_0
     138: lstore        5
     140: aload_0
     141: getfield      #10                 // Field kvsScanned:J
     144: aload_0
     145: getfield      #54                 // Field cellsPerHeartbeatCheck:J
     148: lrem
     149: lconst_0
     150: lcmp
     151: ifeq          183
     154: aload_0
     155: getfield      #45                 // Field scanUsePread:Z
     158: ifeq          204
     161: aload_0
     162: getfield      #44                 // Field readType:Lorg/apache/hadoop/hbase/client/Scan$ReadType;
     165: getstatic     #49                 // Field org/apache/hadoop/hbase/client/Scan$ReadType.DEFAULT:Lorg/apache/hadoop/hbase/client/Scan$ReadType;
     168: if_acmpne     204
     171: aload_0
     172: getfield      #165                // Field bytesRead:J
     175: aload_0
     176: getfield      #52                 // Field preadMaxBytes:J
     179: lcmp
     180: ifle          204
     183: aload_2
     184: getstatic     #159                // Field org/apache/hadoop/hbase/regionserver/ScannerContext$LimitScope.BETWEEN_CELLS:Lorg/apache/hadoop/hbase/regionserver/ScannerContext$LimitScope;
     187: invokevirtual #166                // Method org/apache/hadoop/hbase/regionserver/ScannerContext.checkTimeLimit:(Lorg/apache/hadoop/hbase/regionserver/ScannerContext$LimitScope;)Z
     190: ifeq          204
     193: aload_2
     194: getstatic     #167                // Field org/apache/hadoop/hbase/regionserver/ScannerContext$NextState.TIME_LIMIT_REACHED:Lorg/apache/hadoop/hbase/regionserver/ScannerContext$NextState;
     197: invokevirtual #156                // Method org/apache/hadoop/hbase/regionserver/ScannerContext.setScannerState:(Lorg/apache/hadoop/hbase/regionserver/ScannerContext$NextState;)Lorg/apache/hadoop/hbase/regionserver/ScannerContext$NextState;
     200: invokevirtual #157                // Method org/apache/hadoop/hbase/regionserver/ScannerContext$NextState.hasMoreValues:()Z
     203: ireturn
     204: aload_0
     205: getfield      #11                 // Field prevCell:Lorg/apache/hadoop/hbase/Cell;
     208: aload_3
     209: if_acmpeq     222
     212: aload_0
     213: dup
     214: getfield      #10                 // Field kvsScanned:J
     217: lconst_1
     218: ladd
     219: putfield      #10                 // Field kvsScanned:J
     222: aload_0
     223: aload_0
     224: getfield      #11                 // Field prevCell:Lorg/apache/hadoop/hbase/Cell;
     227: aload_3
     228: aload_0
     229: getfield      #28                 // Field comparator:Lorg/apache/hadoop/hbase/CellComparator;
     232: invokevirtual #168                // Method checkScanOrder:(Lorg/apache/hadoop/hbase/Cell;Lorg/apache/hadoop/hbase/Cell;Lorg/apache/hadoop/hbase/CellComparator;)V
     235: aload_3
     236: invokestatic  #125                // Method org/apache/hadoop/hbase/PrivateCellUtil.estimatedSerializedSizeOf:(Lorg/apache/hadoop/hbase/Cell;)I
     239: istore        7
     241: aload_0
     242: dup
     243: getfield      #165                // Field bytesRead:J
     246: iload         7
     248: i2l
     249: ladd
     250: putfield      #165                // Field bytesRead:J
     253: aload_0
     254: getfield      #45                 // Field scanUsePread:Z
     257: ifeq          286
     260: aload_0
     261: getfield      #44                 // Field readType:Lorg/apache/hadoop/hbase/client/Scan$ReadType;
     264: getstatic     #49                 // Field org/apache/hadoop/hbase/client/Scan$ReadType.DEFAULT:Lorg/apache/hadoop/hbase/client/Scan$ReadType;
     267: if_acmpne     286
     270: aload_0
     271: getfield      #165                // Field bytesRead:J
     274: aload_0
     275: getfield      #52                 // Field preadMaxBytes:J
     278: lcmp
     279: ifle          286
     282: aload_2
     283: invokevirtual #169                // Method org/apache/hadoop/hbase/regionserver/ScannerContext.returnImmediately:()V
     286: aload_0
     287: aload_3
     288: putfield      #11                 // Field prevCell:Lorg/apache/hadoop/hbase/Cell;
     291: aload_2
     292: aload_3
     293: invokevirtual #170                // Method org/apache/hadoop/hbase/regionserver/ScannerContext.setLastPeekedCell:(Lorg/apache/hadoop/hbase/Cell;)V
     296: aload_0
     297: iconst_0
     298: putfield      #21                 // Field topChanged:Z
     301: aload_0
     302: getfield      #70                 // Field matcher:Lorg/apache/hadoop/hbase/regionserver/querymatcher/ScanQueryMatcher;
     305: aload_3
     306: invokevirtual #171                // Method org/apache/hadoop/hbase/regionserver/querymatcher/ScanQueryMatcher.match:(Lorg/apache/hadoop/hbase/Cell;)Lorg/apache/hadoop/hbase/regionserver/querymatcher/ScanQueryMatcher$MatchCode;
     309: astore        8
     311: getstatic     #172                // Field org/apache/hadoop/hbase/regionserver/StoreScanner$1.$SwitchMap$org$apache$hadoop$hbase$regionserver$querymatcher$ScanQueryMatcher$MatchCode:[I
     314: aload         8
     316: invokevirtual #173                // Method org/apache/hadoop/hbase/regionserver/querymatcher/ScanQueryMatcher$MatchCode.ordinal:()I
     319: iaload
     320: tableswitch   { // 1 to 9
                     1: 372
                     2: 372
                     3: 372
                     4: 677
                     5: 718
                     6: 734
                     7: 795
                     8: 822
                     9: 833
               default: 906
          }
     372: aload_0
     373: getfield      #70                 // Field matcher:Lorg/apache/hadoop/hbase/regionserver/querymatcher/ScanQueryMatcher;
     376: invokevirtual #174                // Method org/apache/hadoop/hbase/regionserver/querymatcher/ScanQueryMatcher.getFilter:()Lorg/apache/hadoop/hbase/filter/Filter;
     379: astore        9
     381: aload         9
     383: ifnull        393
     386: aload         9
     388: aload_3
     389: invokevirtual #175                // Method org/apache/hadoop/hbase/filter/Filter.transformCell:(Lorg/apache/hadoop/hbase/Cell;)Lorg/apache/hadoop/hbase/Cell;
     392: astore_3
     393: aload_0
     394: dup
     395: getfield      #2                  // Field countPerRow:J
     398: lconst_1
     399: ladd
     400: putfield      #2                  // Field countPerRow:J
     403: aload_0
     404: getfield      #3                  // Field storeLimit:I
     407: iconst_m1
     408: if_icmple     472
     411: aload_0
     412: getfield      #2                  // Field countPerRow:J
     415: aload_0
     416: getfield      #3                  // Field storeLimit:I
     419: aload_0
     420: getfield      #4                  // Field storeOffset:I
     423: iadd
     424: i2l
     425: lcmp
     426: ifle          472
     429: aload_0
     430: getfield      #70                 // Field matcher:Lorg/apache/hadoop/hbase/regionserver/querymatcher/ScanQueryMatcher;
     433: aload_3
     434: invokevirtual #176                // Method org/apache/hadoop/hbase/regionserver/querymatcher/ScanQueryMatcher.moreRowsMayExistAfter:(Lorg/apache/hadoop/hbase/Cell;)Z
     437: ifne          456
     440: aload_0
     441: iconst_0
     442: invokespecial #143                // Method close:(Z)V
     445: aload_2
     446: getstatic     #158                // Field org/apache/hadoop/hbase/regionserver/ScannerContext$NextState.NO_MORE_VALUES:Lorg/apache/hadoop/hbase/regionserver/ScannerContext$NextState;
     449: invokevirtual #156                // Method org/apache/hadoop/hbase/regionserver/ScannerContext.setScannerState:(Lorg/apache/hadoop/hbase/regionserver/ScannerContext$NextState;)Lorg/apache/hadoop/hbase/regionserver/ScannerContext$NextState;
     452: invokevirtual #157                // Method org/apache/hadoop/hbase/regionserver/ScannerContext$NextState.hasMoreValues:()Z
     455: ireturn
     456: aload_0
     457: getfield      #70                 // Field matcher:Lorg/apache/hadoop/hbase/regionserver/querymatcher/ScanQueryMatcher;
     460: invokevirtual #177                // Method org/apache/hadoop/hbase/regionserver/querymatcher/ScanQueryMatcher.clearCurrentRow:()V
     463: aload_0
     464: aload_3
     465: invokevirtual #178                // Method seekToNextRow:(Lorg/apache/hadoop/hbase/Cell;)Z
     468: pop
     469: goto          928
     472: aload_0
     473: getfield      #2                  // Field countPerRow:J
     476: aload_0
     477: getfield      #4                  // Field storeOffset:I
     480: i2l
     481: lcmp
     482: ifle          577
     485: aload_1
     486: aload_3
     487: invokeinterface #137,  2          // InterfaceMethod java/util/List.add:(Ljava/lang/Object;)Z
     492: pop
     493: iinc          4, 1
     496: lload         5
     498: iload         7
     500: i2l
     501: ladd
     502: lstore        5
     504: aload_2
     505: iload         7
     507: i2l
     508: aload_3
     509: invokeinterface #179,  1          // InterfaceMethod org/apache/hadoop/hbase/Cell.heapSize:()J
     514: invokevirtual #180                // Method org/apache/hadoop/hbase/regionserver/ScannerContext.incrementSizeProgress:(JJ)V
     517: aload_2
     518: iconst_1
     519: invokevirtual #181                // Method org/apache/hadoop/hbase/regionserver/ScannerContext.incrementBatchProgress:(I)V
     522: aload_0
     523: getfield      #70                 // Field matcher:Lorg/apache/hadoop/hbase/regionserver/querymatcher/ScanQueryMatcher;
     526: invokevirtual #113                // Method org/apache/hadoop/hbase/regionserver/querymatcher/ScanQueryMatcher.isUserScan:()Z
     529: ifeq          577
     532: lload         5
     534: aload_0
     535: getfield      #42                 // Field maxRowSize:J
     538: lcmp
     539: ifle          577
     542: new           #114                // class org/apache/hadoop/hbase/regionserver/RowTooBigException
     545: dup
     546: new           #115                // class java/lang/StringBuilder
     549: dup
     550: invokespecial #116                // Method java/lang/StringBuilder."<init>":()V
     553: ldc           #117                // String Max row size allowed:
     555: invokevirtual #118                // Method java/lang/StringBuilder.append:(Ljava/lang/String;)Ljava/lang/StringBuilder;
     558: aload_0
     559: getfield      #42                 // Field maxRowSize:J
     562: invokevirtual #119                // Method java/lang/StringBuilder.append:(J)Ljava/lang/StringBuilder;
     565: ldc           #182                // String , but the row is bigger than that.
     567: invokevirtual #118                // Method java/lang/StringBuilder.append:(Ljava/lang/String;)Ljava/lang/StringBuilder;
     570: invokevirtual #121                // Method java/lang/StringBuilder.toString:()Ljava/lang/String;
     573: invokespecial #122                // Method org/apache/hadoop/hbase/regionserver/RowTooBigException."<init>":(Ljava/lang/String;)V
     576: athrow
     577: aload         8
     579: getstatic     #183                // Field org/apache/hadoop/hbase/regionserver/querymatcher/ScanQueryMatcher$MatchCode.INCLUDE_AND_SEEK_NEXT_ROW:Lorg/apache/hadoop/hbase/regionserver/querymatcher/ScanQueryMatcher$MatchCode;
     582: if_acmpne     627
     585: aload_0
     586: getfield      #70                 // Field matcher:Lorg/apache/hadoop/hbase/regionserver/querymatcher/ScanQueryMatcher;
     589: aload_3
     590: invokevirtual #176                // Method org/apache/hadoop/hbase/regionserver/querymatcher/ScanQueryMatcher.moreRowsMayExistAfter:(Lorg/apache/hadoop/hbase/Cell;)Z
     593: ifne          612
     596: aload_0
     597: iconst_0
     598: invokespecial #143                // Method close:(Z)V
     601: aload_2
     602: getstatic     #158                // Field org/apache/hadoop/hbase/regionserver/ScannerContext$NextState.NO_MORE_VALUES:Lorg/apache/hadoop/hbase/regionserver/ScannerContext$NextState;
     605: invokevirtual #156                // Method org/apache/hadoop/hbase/regionserver/ScannerContext.setScannerState:(Lorg/apache/hadoop/hbase/regionserver/ScannerContext$NextState;)Lorg/apache/hadoop/hbase/regionserver/ScannerContext$NextState;
     608: invokevirtual #157                // Method org/apache/hadoop/hbase/regionserver/ScannerContext$NextState.hasMoreValues:()Z
     611: ireturn
     612: aload_0
     613: getfield      #70                 // Field matcher:Lorg/apache/hadoop/hbase/regionserver/querymatcher/ScanQueryMatcher;
     616: invokevirtual #177                // Method org/apache/hadoop/hbase/regionserver/querymatcher/ScanQueryMatcher.clearCurrentRow:()V
     619: aload_0
     620: aload_3
     621: invokespecial #184                // Method seekOrSkipToNextRow:(Lorg/apache/hadoop/hbase/Cell;)V
     624: goto          651
     627: aload         8
     629: getstatic     #185                // Field org/apache/hadoop/hbase/regionserver/querymatcher/ScanQueryMatcher$MatchCode.INCLUDE_AND_SEEK_NEXT_COL:Lorg/apache/hadoop/hbase/regionserver/querymatcher/ScanQueryMatcher$MatchCode;
     632: if_acmpne     643
     635: aload_0
     636: aload_3
     637: invokespecial #186                // Method seekOrSkipToNextColumn:(Lorg/apache/hadoop/hbase/Cell;)V
     640: goto          651
     643: aload_0
     644: getfield      #128                // Field heap:Lorg/apache/hadoop/hbase/regionserver/KeyValueHeap;
     647: invokevirtual #187                // Method org/apache/hadoop/hbase/regionserver/KeyValueHeap.next:()Lorg/apache/hadoop/hbase/Cell;
     650: pop
     651: aload_2
     652: getstatic     #159                // Field org/apache/hadoop/hbase/regionserver/ScannerContext$LimitScope.BETWEEN_CELLS:Lorg/apache/hadoop/hbase/regionserver/ScannerContext$LimitScope;
     655: invokevirtual #188                // Method org/apache/hadoop/hbase/regionserver/ScannerContext.checkBatchLimit:(Lorg/apache/hadoop/hbase/regionserver/ScannerContext$LimitScope;)Z
     658: ifeq          664
     661: goto          928
     664: aload_2
     665: getstatic     #159                // Field org/apache/hadoop/hbase/regionserver/ScannerContext$LimitScope.BETWEEN_CELLS:Lorg/apache/hadoop/hbase/regionserver/ScannerContext$LimitScope;
     668: invokevirtual #189                // Method org/apache/hadoop/hbase/regionserver/ScannerContext.checkSizeLimit:(Lorg/apache/hadoop/hbase/regionserver/ScannerContext$LimitScope;)Z
     671: ifeq          916
     674: goto          928
     677: aload_0
     678: getfield      #30                 // Field get:Z
     681: ifeq          700
     684: aload_0
     685: iconst_0
     686: invokespecial #143                // Method close:(Z)V
     689: aload_2
     690: getstatic     #158                // Field org/apache/hadoop/hbase/regionserver/ScannerContext$NextState.NO_MORE_VALUES:Lorg/apache/hadoop/hbase/regionserver/ScannerContext$NextState;
     693: invokevirtual #156                // Method org/apache/hadoop/hbase/regionserver/ScannerContext.setScannerState:(Lorg/apache/hadoop/hbase/regionserver/ScannerContext$NextState;)Lorg/apache/hadoop/hbase/regionserver/ScannerContext$NextState;
     696: invokevirtual #157                // Method org/apache/hadoop/hbase/regionserver/ScannerContext$NextState.hasMoreValues:()Z
     699: ireturn
     700: aload_0
     701: getfield      #70                 // Field matcher:Lorg/apache/hadoop/hbase/regionserver/querymatcher/ScanQueryMatcher;
     704: invokevirtual #177                // Method org/apache/hadoop/hbase/regionserver/querymatcher/ScanQueryMatcher.clearCurrentRow:()V
     707: aload_2
     708: getstatic     #155                // Field org/apache/hadoop/hbase/regionserver/ScannerContext$NextState.MORE_VALUES:Lorg/apache/hadoop/hbase/regionserver/ScannerContext$NextState;
     711: invokevirtual #156                // Method org/apache/hadoop/hbase/regionserver/ScannerContext.setScannerState:(Lorg/apache/hadoop/hbase/regionserver/ScannerContext$NextState;)Lorg/apache/hadoop/hbase/regionserver/ScannerContext$NextState;
     714: invokevirtual #157                // Method org/apache/hadoop/hbase/regionserver/ScannerContext$NextState.hasMoreValues:()Z
     717: ireturn
     718: aload_0
     719: iconst_0
     720: invokespecial #143                // Method close:(Z)V
     723: aload_2
     724: getstatic     #158                // Field org/apache/hadoop/hbase/regionserver/ScannerContext$NextState.NO_MORE_VALUES:Lorg/apache/hadoop/hbase/regionserver/ScannerContext$NextState;
     727: invokevirtual #156                // Method org/apache/hadoop/hbase/regionserver/ScannerContext.setScannerState:(Lorg/apache/hadoop/hbase/regionserver/ScannerContext$NextState;)Lorg/apache/hadoop/hbase/regionserver/ScannerContext$NextState;
     730: invokevirtual #157                // Method org/apache/hadoop/hbase/regionserver/ScannerContext$NextState.hasMoreValues:()Z
     733: ireturn
     734: aload_0
     735: getfield      #70                 // Field matcher:Lorg/apache/hadoop/hbase/regionserver/querymatcher/ScanQueryMatcher;
     738: aload_3
     739: invokevirtual #176                // Method org/apache/hadoop/hbase/regionserver/querymatcher/ScanQueryMatcher.moreRowsMayExistAfter:(Lorg/apache/hadoop/hbase/Cell;)Z
     742: ifne          761
     745: aload_0
     746: iconst_0
     747: invokespecial #143                // Method close:(Z)V
     750: aload_2
     751: getstatic     #158                // Field org/apache/hadoop/hbase/regionserver/ScannerContext$NextState.NO_MORE_VALUES:Lorg/apache/hadoop/hbase/regionserver/ScannerContext$NextState;
     754: invokevirtual #156                // Method org/apache/hadoop/hbase/regionserver/ScannerContext.setScannerState:(Lorg/apache/hadoop/hbase/regionserver/ScannerContext$NextState;)Lorg/apache/hadoop/hbase/regionserver/ScannerContext$NextState;
     757: invokevirtual #157                // Method org/apache/hadoop/hbase/regionserver/ScannerContext$NextState.hasMoreValues:()Z
     760: ireturn
     761: aload_0
     762: getfield      #70                 // Field matcher:Lorg/apache/hadoop/hbase/regionserver/querymatcher/ScanQueryMatcher;
     765: invokevirtual #177                // Method org/apache/hadoop/hbase/regionserver/querymatcher/ScanQueryMatcher.clearCurrentRow:()V
     768: aload_0
     769: aload_3
     770: invokespecial #184                // Method seekOrSkipToNextRow:(Lorg/apache/hadoop/hbase/Cell;)V
     773: aload_0
     774: aload_1
     775: invokespecial #190                // Method needToReturn:(Ljava/util/List;)Lorg/apache/hadoop/hbase/regionserver/ScannerContext$NextState;
     778: astore        10
     780: aload         10
     782: ifnull        916
     785: aload_2
     786: aload         10
     788: invokevirtual #156                // Method org/apache/hadoop/hbase/regionserver/ScannerContext.setScannerState:(Lorg/apache/hadoop/hbase/regionserver/ScannerContext$NextState;)Lorg/apache/hadoop/hbase/regionserver/ScannerContext$NextState;
     791: invokevirtual #157                // Method org/apache/hadoop/hbase/regionserver/ScannerContext$NextState.hasMoreValues:()Z
     794: ireturn
     795: aload_0
     796: aload_3
     797: invokespecial #186                // Method seekOrSkipToNextColumn:(Lorg/apache/hadoop/hbase/Cell;)V
     800: aload_0
     801: aload_1
     802: invokespecial #190                // Method needToReturn:(Ljava/util/List;)Lorg/apache/hadoop/hbase/regionserver/ScannerContext$NextState;
     805: astore        11
     807: aload         11
     809: ifnull        916
     812: aload_2
     813: aload         11
     815: invokevirtual #156                // Method org/apache/hadoop/hbase/regionserver/ScannerContext.setScannerState:(Lorg/apache/hadoop/hbase/regionserver/ScannerContext$NextState;)Lorg/apache/hadoop/hbase/regionserver/ScannerContext$NextState;
     818: invokevirtual #157                // Method org/apache/hadoop/hbase/regionserver/ScannerContext$NextState.hasMoreValues:()Z
     821: ireturn
     822: aload_0
     823: getfield      #128                // Field heap:Lorg/apache/hadoop/hbase/regionserver/KeyValueHeap;
     826: invokevirtual #187                // Method org/apache/hadoop/hbase/regionserver/KeyValueHeap.next:()Lorg/apache/hadoop/hbase/Cell;
     829: pop
     830: goto          916
     833: aload_0
     834: getfield      #70                 // Field matcher:Lorg/apache/hadoop/hbase/regionserver/querymatcher/ScanQueryMatcher;
     837: aload_3
     838: invokevirtual #191                // Method org/apache/hadoop/hbase/regionserver/querymatcher/ScanQueryMatcher.getNextKeyHint:(Lorg/apache/hadoop/hbase/Cell;)Lorg/apache/hadoop/hbase/Cell;
     841: astore        12
     843: aload         12
     845: ifnull        895
     848: aload_0
     849: getfield      #28                 // Field comparator:Lorg/apache/hadoop/hbase/CellComparator;
     852: aload         12
     854: aload_3
     855: invokeinterface #192,  3          // InterfaceMethod org/apache/hadoop/hbase/CellComparator.compare:(Lorg/apache/hadoop/hbase/Cell;Lorg/apache/hadoop/hbase/Cell;)I
     860: ifle          895
     863: aload_0
     864: aload         12
     866: invokevirtual #193                // Method seekAsDirection:(Lorg/apache/hadoop/hbase/Cell;)Z
     869: pop
     870: aload_0
     871: aload_1
     872: invokespecial #190                // Method needToReturn:(Ljava/util/List;)Lorg/apache/hadoop/hbase/regionserver/ScannerContext$NextState;
     875: astore        13
     877: aload         13
     879: ifnull        892
     882: aload_2
     883: aload         13
     885: invokevirtual #156                // Method org/apache/hadoop/hbase/regionserver/ScannerContext.setScannerState:(Lorg/apache/hadoop/hbase/regionserver/ScannerContext$NextState;)Lorg/apache/hadoop/hbase/regionserver/ScannerContext$NextState;
     888: invokevirtual #157                // Method org/apache/hadoop/hbase/regionserver/ScannerContext$NextState.hasMoreValues:()Z
     891: ireturn
     892: goto          916
     895: aload_0
     896: getfield      #128                // Field heap:Lorg/apache/hadoop/hbase/regionserver/KeyValueHeap;
     899: invokevirtual #187                // Method org/apache/hadoop/hbase/regionserver/KeyValueHeap.next:()Lorg/apache/hadoop/hbase/Cell;
     902: pop
     903: goto          916
     906: new           #140                // class java/lang/RuntimeException
     909: dup
     910: ldc           #194                // String UNEXPECTED
     912: invokespecial #142                // Method java/lang/RuntimeException."<init>":(Ljava/lang/String;)V
     915: athrow
     916: aload_0
     917: getfield      #128                // Field heap:Lorg/apache/hadoop/hbase/regionserver/KeyValueHeap;
     920: invokevirtual #139                // Method org/apache/hadoop/hbase/regionserver/KeyValueHeap.peek:()Lorg/apache/hadoop/hbase/Cell;
     923: dup
     924: astore_3
     925: ifnonnull     140
     928: iload         4
     930: ifle          944
     933: aload_2
     934: getstatic     #155                // Field org/apache/hadoop/hbase/regionserver/ScannerContext$NextState.MORE_VALUES:Lorg/apache/hadoop/hbase/regionserver/ScannerContext$NextState;
     937: invokevirtual #156                // Method org/apache/hadoop/hbase/regionserver/ScannerContext.setScannerState:(Lorg/apache/hadoop/hbase/regionserver/ScannerContext$NextState;)Lorg/apache/hadoop/hbase/regionserver/ScannerContext$NextState;
     940: invokevirtual #157                // Method org/apache/hadoop/hbase/regionserver/ScannerContext$NextState.hasMoreValues:()Z
     943: ireturn
     944: aload_0
     945: iconst_0
     946: invokespecial #143                // Method close:(Z)V
     949: aload_2
     950: getstatic     #158                // Field org/apache/hadoop/hbase/regionserver/ScannerContext$NextState.NO_MORE_VALUES:Lorg/apache/hadoop/hbase/regionserver/ScannerContext$NextState;
     953: invokevirtual #156                // Method org/apache/hadoop/hbase/regionserver/ScannerContext.setScannerState:(Lorg/apache/hadoop/hbase/regionserver/ScannerContext$NextState;)Lorg/apache/hadoop/hbase/regionserver/ScannerContext$NextState;
     956: invokevirtual #157                // Method org/apache/hadoop/hbase/regionserver/ScannerContext$NextState.hasMoreValues:()Z
     959: ireturn

  protected boolean trySkipToNextRow(org.apache.hadoop.hbase.Cell) throws java.io.IOException;
    Code:
       0: aconst_null
       1: astore_2
       2: aconst_null
       3: astore_3
       4: aload_0
       5: invokevirtual #199                // Method getNextIndexedKey:()Lorg/apache/hadoop/hbase/Cell;
       8: astore        4
      10: aload         4
      12: ifnull        66
      15: aload         4
      17: getstatic     #200                // Field org/apache/hadoop/hbase/regionserver/KeyValueScanner.NO_NEXT_INDEXED_KEY:Lorg/apache/hadoop/hbase/Cell;
      20: if_acmpeq     66
      23: aload         4
      25: aload_3
      26: if_acmpeq     42
      29: aload_0
      30: getfield      #70                 // Field matcher:Lorg/apache/hadoop/hbase/regionserver/querymatcher/ScanQueryMatcher;
      33: aload         4
      35: aload_1
      36: invokevirtual #201                // Method org/apache/hadoop/hbase/regionserver/querymatcher/ScanQueryMatcher.compareKeyForNextRow:(Lorg/apache/hadoop/hbase/Cell;Lorg/apache/hadoop/hbase/Cell;)I
      39: iflt          66
      42: aload_0
      43: getfield      #128                // Field heap:Lorg/apache/hadoop/hbase/regionserver/KeyValueHeap;
      46: invokevirtual #187                // Method org/apache/hadoop/hbase/regionserver/KeyValueHeap.next:()Lorg/apache/hadoop/hbase/Cell;
      49: pop
      50: aload_0
      51: dup
      52: getfield      #10                 // Field kvsScanned:J
      55: lconst_1
      56: ladd
      57: putfield      #10                 // Field kvsScanned:J
      60: aload         4
      62: astore_3
      63: goto          68
      66: iconst_0
      67: ireturn
      68: aload_0
      69: getfield      #128                // Field heap:Lorg/apache/hadoop/hbase/regionserver/KeyValueHeap;
      72: invokevirtual #139                // Method org/apache/hadoop/hbase/regionserver/KeyValueHeap.peek:()Lorg/apache/hadoop/hbase/Cell;
      75: dup
      76: astore_2
      77: ifnull        88
      80: aload_1
      81: aload_2
      82: invokestatic  #202                // Method org/apache/hadoop/hbase/CellUtil.matchingRows:(Lorg/apache/hadoop/hbase/Cell;Lorg/apache/hadoop/hbase/Cell;)Z
      85: ifne          4
      88: iconst_1
      89: ireturn

  protected boolean trySkipToNextColumn(org.apache.hadoop.hbase.Cell) throws java.io.IOException;
    Code:
       0: aconst_null
       1: astore_2
       2: aconst_null
       3: astore_3
       4: aload_0
       5: invokevirtual #199                // Method getNextIndexedKey:()Lorg/apache/hadoop/hbase/Cell;
       8: astore        4
      10: aload         4
      12: ifnull        66
      15: aload         4
      17: getstatic     #200                // Field org/apache/hadoop/hbase/regionserver/KeyValueScanner.NO_NEXT_INDEXED_KEY:Lorg/apache/hadoop/hbase/Cell;
      20: if_acmpeq     66
      23: aload         4
      25: aload_3
      26: if_acmpeq     42
      29: aload_0
      30: getfield      #70                 // Field matcher:Lorg/apache/hadoop/hbase/regionserver/querymatcher/ScanQueryMatcher;
      33: aload         4
      35: aload_1
      36: invokevirtual #203                // Method org/apache/hadoop/hbase/regionserver/querymatcher/ScanQueryMatcher.compareKeyForNextColumn:(Lorg/apache/hadoop/hbase/Cell;Lorg/apache/hadoop/hbase/Cell;)I
      39: iflt          66
      42: aload_0
      43: getfield      #128                // Field heap:Lorg/apache/hadoop/hbase/regionserver/KeyValueHeap;
      46: invokevirtual #187                // Method org/apache/hadoop/hbase/regionserver/KeyValueHeap.next:()Lorg/apache/hadoop/hbase/Cell;
      49: pop
      50: aload_0
      51: dup
      52: getfield      #10                 // Field kvsScanned:J
      55: lconst_1
      56: ladd
      57: putfield      #10                 // Field kvsScanned:J
      60: aload         4
      62: astore_3
      63: goto          68
      66: iconst_0
      67: ireturn
      68: aload_0
      69: getfield      #128                // Field heap:Lorg/apache/hadoop/hbase/regionserver/KeyValueHeap;
      72: invokevirtual #139                // Method org/apache/hadoop/hbase/regionserver/KeyValueHeap.peek:()Lorg/apache/hadoop/hbase/Cell;
      75: dup
      76: astore_2
      77: ifnull        88
      80: aload_1
      81: aload_2
      82: invokestatic  #204                // Method org/apache/hadoop/hbase/CellUtil.matchingRowColumn:(Lorg/apache/hadoop/hbase/Cell;Lorg/apache/hadoop/hbase/Cell;)Z
      85: ifne          4
      88: aload_2
      89: ifnull        106
      92: aload_0
      93: getfield      #70                 // Field matcher:Lorg/apache/hadoop/hbase/regionserver/querymatcher/ScanQueryMatcher;
      96: aload_2
      97: aload_1
      98: invokevirtual #203                // Method org/apache/hadoop/hbase/regionserver/querymatcher/ScanQueryMatcher.compareKeyForNextColumn:(Lorg/apache/hadoop/hbase/Cell;Lorg/apache/hadoop/hbase/Cell;)I
     101: ifge          106
     104: iconst_0
     105: ireturn
     106: iconst_1
     107: ireturn

  public long getReadPoint();
    Code:
       0: aload_0
       1: getfield      #22                 // Field readPt:J
       4: lreturn

  public void updateReaders(java.util.List<org.apache.hadoop.hbase.regionserver.HStoreFile>, java.util.List<org.apache.hadoop.hbase.regionserver.KeyValueScanner>) throws java.io.IOException;
    Code:
       0: aload_1
       1: invokestatic  #205                // Method org/apache/hbase/thirdparty/org/apache/commons/collections4/CollectionUtils.isEmpty:(Ljava/util/Collection;)Z
       4: ifeq          15
       7: aload_2
       8: invokestatic  #205                // Method org/apache/hbase/thirdparty/org/apache/commons/collections4/CollectionUtils.isEmpty:(Ljava/util/Collection;)Z
      11: ifeq          15
      14: return
      15: iconst_0
      16: istore_3
      17: aload_0
      18: getfield      #19                 // Field flushLock:Ljava/util/concurrent/locks/ReentrantLock;
      21: invokevirtual #144                // Method java/util/concurrent/locks/ReentrantLock.lock:()V
      24: aload_0
      25: getfield      #20                 // Field closeLock:Ljava/util/concurrent/locks/ReentrantLock;
      28: invokevirtual #206                // Method java/util/concurrent/locks/ReentrantLock.tryLock:()Z
      31: ifne          63
      34: getstatic     #207                // Field LOG:Lorg/slf4j/Logger;
      37: ldc           #208                // String StoreScanner already has the close lock. There is no need to updateReaders
      39: invokeinterface #209,  2          // InterfaceMethod org/slf4j/Logger.debug:(Ljava/lang/String;)V
      44: aload_0
      45: getfield      #19                 // Field flushLock:Ljava/util/concurrent/locks/ReentrantLock;
      48: invokevirtual #145                // Method java/util/concurrent/locks/ReentrantLock.unlock:()V
      51: iload_3
      52: ifeq          62
      55: aload_0
      56: getfield      #20                 // Field closeLock:Ljava/util/concurrent/locks/ReentrantLock;
      59: invokevirtual #145                // Method java/util/concurrent/locks/ReentrantLock.unlock:()V
      62: return
      63: iconst_1
      64: istore_3
      65: aload_0
      66: getfield      #5                  // Field closing:Z
      69: ifeq          101
      72: getstatic     #207                // Field LOG:Lorg/slf4j/Logger;
      75: ldc           #210                // String StoreScanner already closing. There is no need to updateReaders
      77: invokeinterface #209,  2          // InterfaceMethod org/slf4j/Logger.debug:(Ljava/lang/String;)V
      82: aload_0
      83: getfield      #19                 // Field flushLock:Ljava/util/concurrent/locks/ReentrantLock;
      86: invokevirtual #145                // Method java/util/concurrent/locks/ReentrantLock.unlock:()V
      89: iload_3
      90: ifeq          100
      93: aload_0
      94: getfield      #20                 // Field closeLock:Ljava/util/concurrent/locks/ReentrantLock;
      97: invokevirtual #145                // Method java/util/concurrent/locks/ReentrantLock.unlock:()V
     100: return
     101: aload_0
     102: iconst_1
     103: putfield      #12                 // Field flushed:Z
     106: iconst_0
     107: istore        4
     109: aload_0
     110: getfield      #30                 // Field get:Z
     113: ifne          123
     116: aload_0
     117: getfield      #45                 // Field scanUsePread:Z
     120: ifeq          127
     123: iconst_1
     124: goto          128
     127: iconst_0
     128: istore        5
     130: aload_0
     131: getfield      #23                 // Field store:Lorg/apache/hadoop/hbase/regionserver/HStore;
     134: aload_1
     135: aload_0
     136: getfield      #24                 // Field cacheBlocks:Z
     139: aload_0
     140: getfield      #30                 // Field get:Z
     143: iload         5
     145: iconst_0
     146: aload_0
     147: getfield      #70                 // Field matcher:Lorg/apache/hadoop/hbase/regionserver/querymatcher/ScanQueryMatcher;
     150: aload_0
     151: getfield      #32                 // Field scan:Lorg/apache/hadoop/hbase/client/Scan;
     154: invokevirtual #72                 // Method org/apache/hadoop/hbase/client/Scan.getStartRow:()[B
     157: aload_0
     158: getfield      #32                 // Field scan:Lorg/apache/hadoop/hbase/client/Scan;
     161: invokevirtual #74                 // Method org/apache/hadoop/hbase/client/Scan.getStopRow:()[B
     164: aload_0
     165: getfield      #22                 // Field readPt:J
     168: iconst_0
     169: invokevirtual #211                // Method org/apache/hadoop/hbase/regionserver/HStore.getScanners:(Ljava/util/List;ZZZZLorg/apache/hadoop/hbase/regionserver/querymatcher/ScanQueryMatcher;[B[BJZ)Ljava/util/List;
     172: astore        6
     174: aload_0
     175: getfield      #14                 // Field flushedstoreFileScanners:Ljava/util/List;
     178: aload         6
     180: invokeinterface #61,  2           // InterfaceMethod java/util/List.addAll:(Ljava/util/Collection;)Z
     185: pop
     186: aload_2
     187: invokestatic  #205                // Method org/apache/hbase/thirdparty/org/apache/commons/collections4/CollectionUtils.isEmpty:(Ljava/util/Collection;)Z
     190: ifne          211
     193: aload_0
     194: getfield      #15                 // Field memStoreScannersAfterFlush:Ljava/util/List;
     197: invokestatic  #146                // Method clearAndClose:(Ljava/util/List;)V
     200: aload_0
     201: getfield      #15                 // Field memStoreScannersAfterFlush:Ljava/util/List;
     204: aload_2
     205: invokeinterface #61,  2           // InterfaceMethod java/util/List.addAll:(Ljava/util/Collection;)Z
     210: pop
     211: aload_0
     212: getfield      #19                 // Field flushLock:Ljava/util/concurrent/locks/ReentrantLock;
     215: invokevirtual #145                // Method java/util/concurrent/locks/ReentrantLock.unlock:()V
     218: iload_3
     219: ifeq          255
     222: aload_0
     223: getfield      #20                 // Field closeLock:Ljava/util/concurrent/locks/ReentrantLock;
     226: invokevirtual #145                // Method java/util/concurrent/locks/ReentrantLock.unlock:()V
     229: goto          255
     232: astore        7
     234: aload_0
     235: getfield      #19                 // Field flushLock:Ljava/util/concurrent/locks/ReentrantLock;
     238: invokevirtual #145                // Method java/util/concurrent/locks/ReentrantLock.unlock:()V
     241: iload_3
     242: ifeq          252
     245: aload_0
     246: getfield      #20                 // Field closeLock:Ljava/util/concurrent/locks/ReentrantLock;
     249: invokevirtual #145                // Method java/util/concurrent/locks/ReentrantLock.unlock:()V
     252: aload         7
     254: athrow
     255: return
    Exception table:
       from    to  target type
          24    44   232   any
          63    82   232   any
         101   211   232   any
         232   234   232   any

  protected final boolean reopenAfterFlush() throws java.io.IOException;
    Code:
       0: aload_0
       1: getfield      #128                // Field heap:Lorg/apache/hadoop/hbase/regionserver/KeyValueHeap;
       4: invokevirtual #139                // Method org/apache/hadoop/hbase/regionserver/KeyValueHeap.peek:()Lorg/apache/hadoop/hbase/Cell;
       7: astore_1
       8: aload_0
       9: getfield      #19                 // Field flushLock:Ljava/util/concurrent/locks/ReentrantLock;
      12: invokevirtual #144                // Method java/util/concurrent/locks/ReentrantLock.lock:()V
      15: new           #7                  // class java/util/ArrayList
      18: dup
      19: aload_0
      20: getfield      #14                 // Field flushedstoreFileScanners:Ljava/util/List;
      23: invokeinterface #134,  1          // InterfaceMethod java/util/List.size:()I
      28: aload_0
      29: getfield      #15                 // Field memStoreScannersAfterFlush:Ljava/util/List;
      32: invokeinterface #134,  1          // InterfaceMethod java/util/List.size:()I
      37: iadd
      38: invokespecial #13                 // Method java/util/ArrayList."<init>":(I)V
      41: astore_3
      42: aload_3
      43: aload_0
      44: getfield      #14                 // Field flushedstoreFileScanners:Ljava/util/List;
      47: invokeinterface #61,  2           // InterfaceMethod java/util/List.addAll:(Ljava/util/Collection;)Z
      52: pop
      53: aload_3
      54: aload_0
      55: getfield      #15                 // Field memStoreScannersAfterFlush:Ljava/util/List;
      58: invokeinterface #61,  2           // InterfaceMethod java/util/List.addAll:(Ljava/util/Collection;)Z
      63: pop
      64: aload_0
      65: aload_0
      66: getfield      #23                 // Field store:Lorg/apache/hadoop/hbase/regionserver/HStore;
      69: aload_3
      70: invokevirtual #77                 // Method selectScannersFrom:(Lorg/apache/hadoop/hbase/regionserver/HStore;Ljava/util/List;)Ljava/util/List;
      73: astore_2
      74: aload_0
      75: getfield      #14                 // Field flushedstoreFileScanners:Ljava/util/List;
      78: invokeinterface #148,  1          // InterfaceMethod java/util/List.clear:()V
      83: aload_0
      84: getfield      #15                 // Field memStoreScannersAfterFlush:Ljava/util/List;
      87: invokeinterface #148,  1          // InterfaceMethod java/util/List.clear:()V
      92: aload_0
      93: getfield      #19                 // Field flushLock:Ljava/util/concurrent/locks/ReentrantLock;
      96: invokevirtual #145                // Method java/util/concurrent/locks/ReentrantLock.unlock:()V
      99: goto          114
     102: astore        4
     104: aload_0
     105: getfield      #19                 // Field flushLock:Ljava/util/concurrent/locks/ReentrantLock;
     108: invokevirtual #145                // Method java/util/concurrent/locks/ReentrantLock.unlock:()V
     111: aload         4
     113: athrow
     114: aload_0
     115: aload_2
     116: aload_1
     117: iconst_0
     118: aload_0
     119: getfield      #6                  // Field parallelSeekEnabled:Z
     122: invokevirtual #80                 // Method seekScanners:(Ljava/util/List;Lorg/apache/hadoop/hbase/Cell;ZZ)V
     125: aload_0
     126: getfield      #16                 // Field currentScanners:Ljava/util/List;
     129: invokeinterface #134,  1          // InterfaceMethod java/util/List.size:()I
     134: iconst_1
     135: isub
     136: istore_3
     137: iload_3
     138: iflt          188
     141: aload_0
     142: getfield      #16                 // Field currentScanners:Ljava/util/List;
     145: iload_3
     146: invokeinterface #212,  2          // InterfaceMethod java/util/List.get:(I)Ljava/lang/Object;
     151: checkcast     #111                // class org/apache/hadoop/hbase/regionserver/KeyValueScanner
     154: invokeinterface #135,  1          // InterfaceMethod org/apache/hadoop/hbase/regionserver/KeyValueScanner.isFileScanner:()Z
     159: ifne          188
     162: aload_0
     163: getfield      #9                  // Field scannersForDelayedClose:Ljava/util/List;
     166: aload_0
     167: getfield      #16                 // Field currentScanners:Ljava/util/List;
     170: iload_3
     171: invokeinterface #213,  2          // InterfaceMethod java/util/List.remove:(I)Ljava/lang/Object;
     176: invokeinterface #137,  2          // InterfaceMethod java/util/List.add:(Ljava/lang/Object;)Z
     181: pop
     182: iinc          3, -1
     185: goto          137
     188: aload_0
     189: aload_2
     190: invokespecial #83                 // Method addCurrentScanners:(Ljava/util/List;)V
     193: aload_0
     194: aload_0
     195: getfield      #16                 // Field currentScanners:Ljava/util/List;
     198: aload_0
     199: getfield      #23                 // Field store:Lorg/apache/hadoop/hbase/regionserver/HStore;
     202: invokevirtual #214                // Method org/apache/hadoop/hbase/regionserver/HStore.getComparator:()Lorg/apache/hadoop/hbase/CellComparator;
     205: invokevirtual #84                 // Method resetKVHeap:(Ljava/util/List;Lorg/apache/hadoop/hbase/CellComparator;)V
     208: aload_0
     209: aload_1
     210: invokespecial #215                // Method resetQueryMatcher:(Lorg/apache/hadoop/hbase/Cell;)V
     213: aload_0
     214: getfield      #128                // Field heap:Lorg/apache/hadoop/hbase/regionserver/KeyValueHeap;
     217: invokevirtual #139                // Method org/apache/hadoop/hbase/regionserver/KeyValueHeap.peek:()Lorg/apache/hadoop/hbase/Cell;
     220: ifnull        246
     223: aload_0
     224: getfield      #23                 // Field store:Lorg/apache/hadoop/hbase/regionserver/HStore;
     227: invokevirtual #214                // Method org/apache/hadoop/hbase/regionserver/HStore.getComparator:()Lorg/apache/hadoop/hbase/CellComparator;
     230: aload_1
     231: aload_0
     232: getfield      #128                // Field heap:Lorg/apache/hadoop/hbase/regionserver/KeyValueHeap;
     235: invokevirtual #139                // Method org/apache/hadoop/hbase/regionserver/KeyValueHeap.peek:()Lorg/apache/hadoop/hbase/Cell;
     238: invokeinterface #216,  3          // InterfaceMethod org/apache/hadoop/hbase/CellComparator.compareRows:(Lorg/apache/hadoop/hbase/Cell;Lorg/apache/hadoop/hbase/Cell;)I
     243: ifeq          299
     246: getstatic     #207                // Field LOG:Lorg/slf4j/Logger;
     249: new           #115                // class java/lang/StringBuilder
     252: dup
     253: invokespecial #116                // Method java/lang/StringBuilder."<init>":()V
     256: ldc           #217                // String Storescanner.peek() is changed where before =
     258: invokevirtual #118                // Method java/lang/StringBuilder.append:(Ljava/lang/String;)Ljava/lang/StringBuilder;
     261: aload_1
     262: invokevirtual #218                // Method java/lang/Object.toString:()Ljava/lang/String;
     265: invokevirtual #118                // Method java/lang/StringBuilder.append:(Ljava/lang/String;)Ljava/lang/StringBuilder;
     268: ldc           #219                // String ,and after =
     270: invokevirtual #118                // Method java/lang/StringBuilder.append:(Ljava/lang/String;)Ljava/lang/StringBuilder;
     273: aload_0
     274: getfield      #128                // Field heap:Lorg/apache/hadoop/hbase/regionserver/KeyValueHeap;
     277: invokevirtual #139                // Method org/apache/hadoop/hbase/regionserver/KeyValueHeap.peek:()Lorg/apache/hadoop/hbase/Cell;
     280: invokevirtual #220                // Method java/lang/StringBuilder.append:(Ljava/lang/Object;)Ljava/lang/StringBuilder;
     283: invokevirtual #121                // Method java/lang/StringBuilder.toString:()Ljava/lang/String;
     286: invokeinterface #221,  2          // InterfaceMethod org/slf4j/Logger.info:(Ljava/lang/String;)V
     291: aload_0
     292: iconst_1
     293: putfield      #21                 // Field topChanged:Z
     296: goto          304
     299: aload_0
     300: iconst_0
     301: putfield      #21                 // Field topChanged:Z
     304: aload_0
     305: getfield      #21                 // Field topChanged:Z
     308: ireturn
    Exception table:
       from    to  target type
          15    92   102   any
         102   104   102   any

  protected void checkScanOrder(org.apache.hadoop.hbase.Cell, org.apache.hadoop.hbase.Cell, org.apache.hadoop.hbase.CellComparator) throws java.io.IOException;
    Code:
       0: getstatic     #92                 // Field $assertionsDisabled:Z
       3: ifne          73
       6: aload_1
       7: ifnull        73
      10: aload_3
      11: ifnull        73
      14: aload_3
      15: aload_1
      16: aload_2
      17: invokeinterface #192,  3          // InterfaceMethod org/apache/hadoop/hbase/CellComparator.compare:(Lorg/apache/hadoop/hbase/Cell;Lorg/apache/hadoop/hbase/Cell;)I
      22: ifle          73
      25: new           #93                 // class java/lang/AssertionError
      28: dup
      29: new           #115                // class java/lang/StringBuilder
      32: dup
      33: invokespecial #116                // Method java/lang/StringBuilder."<init>":()V
      36: ldc           #222                // String Key
      38: invokevirtual #118                // Method java/lang/StringBuilder.append:(Ljava/lang/String;)Ljava/lang/StringBuilder;
      41: aload_1
      42: invokevirtual #220                // Method java/lang/StringBuilder.append:(Ljava/lang/Object;)Ljava/lang/StringBuilder;
      45: ldc           #223                // String  followed by a smaller key
      47: invokevirtual #118                // Method java/lang/StringBuilder.append:(Ljava/lang/String;)Ljava/lang/StringBuilder;
      50: aload_2
      51: invokevirtual #220                // Method java/lang/StringBuilder.append:(Ljava/lang/Object;)Ljava/lang/StringBuilder;
      54: ldc           #224                // String  in cf
      56: invokevirtual #118                // Method java/lang/StringBuilder.append:(Ljava/lang/String;)Ljava/lang/StringBuilder;
      59: aload_0
      60: getfield      #23                 // Field store:Lorg/apache/hadoop/hbase/regionserver/HStore;
      63: invokevirtual #220                // Method java/lang/StringBuilder.append:(Ljava/lang/Object;)Ljava/lang/StringBuilder;
      66: invokevirtual #121                // Method java/lang/StringBuilder.toString:()Ljava/lang/String;
      69: invokespecial #225                // Method java/lang/AssertionError."<init>":(Ljava/lang/Object;)V
      72: athrow
      73: return

  protected boolean seekToNextRow(org.apache.hadoop.hbase.Cell) throws java.io.IOException;
    Code:
       0: aload_0
       1: aload_1
       2: invokestatic  #226                // Method org/apache/hadoop/hbase/PrivateCellUtil.createLastOnRow:(Lorg/apache/hadoop/hbase/Cell;)Lorg/apache/hadoop/hbase/Cell;
       5: invokevirtual #227                // Method reseek:(Lorg/apache/hadoop/hbase/Cell;)Z
       8: ireturn

  protected boolean seekAsDirection(org.apache.hadoop.hbase.Cell) throws java.io.IOException;
    Code:
       0: aload_0
       1: aload_1
       2: invokevirtual #227                // Method reseek:(Lorg/apache/hadoop/hbase/Cell;)Z
       5: ireturn

  public boolean reseek(org.apache.hadoop.hbase.Cell) throws java.io.IOException;
    Code:
       0: aload_0
       1: invokevirtual #149                // Method checkFlushed:()Z
       4: ifeq          12
       7: aload_0
       8: invokevirtual #150                // Method reopenAfterFlush:()Z
      11: pop
      12: aload_0
      13: getfield      #31                 // Field explicitColumnQuery:Z
      16: ifeq          39
      19: getstatic     #79                 // Field lazySeekEnabledGlobally:Z
      22: ifeq          39
      25: aload_0
      26: getfield      #128                // Field heap:Lorg/apache/hadoop/hbase/regionserver/KeyValueHeap;
      29: aload_1
      30: iconst_1
      31: aload_0
      32: getfield      #40                 // Field useRowColBloom:Z
      35: invokevirtual #228                // Method org/apache/hadoop/hbase/regionserver/KeyValueHeap.requestSeek:(Lorg/apache/hadoop/hbase/Cell;ZZ)Z
      38: ireturn
      39: aload_0
      40: getfield      #128                // Field heap:Lorg/apache/hadoop/hbase/regionserver/KeyValueHeap;
      43: aload_1
      44: invokevirtual #229                // Method org/apache/hadoop/hbase/regionserver/KeyValueHeap.reseek:(Lorg/apache/hadoop/hbase/Cell;)Z
      47: ireturn

  void trySwitchToStreamRead();
    Code:
       0: aload_0
       1: getfield      #44                 // Field readType:Lorg/apache/hadoop/hbase/client/Scan$ReadType;
       4: getstatic     #49                 // Field org/apache/hadoop/hbase/client/Scan$ReadType.DEFAULT:Lorg/apache/hadoop/hbase/client/Scan$ReadType;
       7: if_acmpne     46
      10: aload_0
      11: getfield      #45                 // Field scanUsePread:Z
      14: ifeq          46
      17: aload_0
      18: getfield      #5                  // Field closing:Z
      21: ifne          46
      24: aload_0
      25: getfield      #128                // Field heap:Lorg/apache/hadoop/hbase/regionserver/KeyValueHeap;
      28: invokevirtual #139                // Method org/apache/hadoop/hbase/regionserver/KeyValueHeap.peek:()Lorg/apache/hadoop/hbase/Cell;
      31: ifnull        46
      34: aload_0
      35: getfield      #165                // Field bytesRead:J
      38: aload_0
      39: getfield      #52                 // Field preadMaxBytes:J
      42: lcmp
      43: ifge          47
      46: return
      47: getstatic     #207                // Field LOG:Lorg/slf4j/Logger;
      50: ldc           #230                // String Switch to stream read (scanned={} bytes) of {}
      52: aload_0
      53: getfield      #165                // Field bytesRead:J
      56: invokestatic  #231                // Method java/lang/Long.valueOf:(J)Ljava/lang/Long;
      59: aload_0
      60: getfield      #23                 // Field store:Lorg/apache/hadoop/hbase/regionserver/HStore;
      63: invokevirtual #232                // Method org/apache/hadoop/hbase/regionserver/HStore.getColumnFamilyName:()Ljava/lang/String;
      66: invokeinterface #233,  4          // InterfaceMethod org/slf4j/Logger.debug:(Ljava/lang/String;Ljava/lang/Object;Ljava/lang/Object;)V
      71: aload_0
      72: iconst_0
      73: putfield      #45                 // Field scanUsePread:Z
      76: aload_0
      77: getfield      #128                // Field heap:Lorg/apache/hadoop/hbase/regionserver/KeyValueHeap;
      80: invokevirtual #139                // Method org/apache/hadoop/hbase/regionserver/KeyValueHeap.peek:()Lorg/apache/hadoop/hbase/Cell;
      83: astore_1
      84: new           #7                  // class java/util/ArrayList
      87: dup
      88: invokespecial #8                  // Method java/util/ArrayList."<init>":()V
      91: astore_2
      92: new           #7                  // class java/util/ArrayList
      95: dup
      96: invokespecial #8                  // Method java/util/ArrayList."<init>":()V
      99: astore_3
     100: aload_0
     101: getfield      #16                 // Field currentScanners:Ljava/util/List;
     104: invokeinterface #108,  1          // InterfaceMethod java/util/List.iterator:()Ljava/util/Iterator;
     109: astore        4
     111: aload         4
     113: invokeinterface #109,  1          // InterfaceMethod java/util/Iterator.hasNext:()Z
     118: ifeq          167
     121: aload         4
     123: invokeinterface #110,  1          // InterfaceMethod java/util/Iterator.next:()Ljava/lang/Object;
     128: checkcast     #111                // class org/apache/hadoop/hbase/regionserver/KeyValueScanner
     131: astore        5
     133: aload         5
     135: invokeinterface #135,  1          // InterfaceMethod org/apache/hadoop/hbase/regionserver/KeyValueScanner.isFileScanner:()Z
     140: ifne          155
     143: aload_2
     144: aload         5
     146: invokeinterface #137,  2          // InterfaceMethod java/util/List.add:(Ljava/lang/Object;)Z
     151: pop
     152: goto          164
     155: aload_3
     156: aload         5
     158: invokeinterface #137,  2          // InterfaceMethod java/util/List.add:(Ljava/lang/Object;)Z
     163: pop
     164: goto          111
     167: aconst_null
     168: astore        4
     170: aload_0
     171: getfield      #23                 // Field store:Lorg/apache/hadoop/hbase/regionserver/HStore;
     174: aload_3
     175: aload_0
     176: getfield      #24                 // Field cacheBlocks:Z
     179: iconst_0
     180: iconst_0
     181: aload_0
     182: getfield      #70                 // Field matcher:Lorg/apache/hadoop/hbase/regionserver/querymatcher/ScanQueryMatcher;
     185: aload_0
     186: getfield      #32                 // Field scan:Lorg/apache/hadoop/hbase/client/Scan;
     189: invokevirtual #72                 // Method org/apache/hadoop/hbase/client/Scan.getStartRow:()[B
     192: aload_0
     193: getfield      #32                 // Field scan:Lorg/apache/hadoop/hbase/client/Scan;
     196: invokevirtual #73                 // Method org/apache/hadoop/hbase/client/Scan.includeStartRow:()Z
     199: aload_0
     200: getfield      #32                 // Field scan:Lorg/apache/hadoop/hbase/client/Scan;
     203: invokevirtual #74                 // Method org/apache/hadoop/hbase/client/Scan.getStopRow:()[B
     206: aload_0
     207: getfield      #32                 // Field scan:Lorg/apache/hadoop/hbase/client/Scan;
     210: invokevirtual #75                 // Method org/apache/hadoop/hbase/client/Scan.includeStopRow:()Z
     213: aload_0
     214: getfield      #22                 // Field readPt:J
     217: iconst_0
     218: invokevirtual #234                // Method org/apache/hadoop/hbase/regionserver/HStore.recreateScanners:(Ljava/util/List;ZZZLorg/apache/hadoop/hbase/regionserver/querymatcher/ScanQueryMatcher;[BZ[BZJZ)Ljava/util/List;
     221: astore        4
     223: aload         4
     225: ifnonnull     229
     228: return
     229: aload_0
     230: aload         4
     232: aload_1
     233: iconst_0
     234: aload_0
     235: getfield      #6                  // Field parallelSeekEnabled:Z
     238: invokevirtual #80                 // Method seekScanners:(Ljava/util/List;Lorg/apache/hadoop/hbase/Cell;ZZ)V
     241: new           #7                  // class java/util/ArrayList
     244: dup
     245: aload         4
     247: invokeinterface #134,  1          // InterfaceMethod java/util/List.size:()I
     252: aload_2
     253: invokeinterface #134,  1          // InterfaceMethod java/util/List.size:()I
     258: iadd
     259: invokespecial #13                 // Method java/util/ArrayList."<init>":(I)V
     262: astore        5
     264: aload         5
     266: aload         4
     268: invokeinterface #61,  2           // InterfaceMethod java/util/List.addAll:(Ljava/util/Collection;)Z
     273: pop
     274: aload         5
     276: aload_2
     277: invokeinterface #61,  2           // InterfaceMethod java/util/List.addAll:(Ljava/util/Collection;)Z
     282: pop
     283: aload_0
     284: aload         5
     286: aload_0
     287: getfield      #28                 // Field comparator:Lorg/apache/hadoop/hbase/CellComparator;
     290: invokevirtual #127                // Method newKVHeap:(Ljava/util/List;Lorg/apache/hadoop/hbase/CellComparator;)Lorg/apache/hadoop/hbase/regionserver/KeyValueHeap;
     293: astore        6
     295: goto          330
     298: astore        7
     300: getstatic     #207                // Field LOG:Lorg/slf4j/Logger;
     303: ldc           #236                // String failed to switch to stream read
     305: aload         7
     307: invokeinterface #237,  3          // InterfaceMethod org/slf4j/Logger.warn:(Ljava/lang/String;Ljava/lang/Throwable;)V
     312: aload         4
     314: ifnull        329
     317: aload         4
     319: invokedynamic #238,  0            // InvokeDynamic #0:accept:()Ljava/util/function/Consumer;
     324: invokeinterface #239,  2          // InterfaceMethod java/util/List.forEach:(Ljava/util/function/Consumer;)V
     329: return
     330: aload_0
     331: getfield      #16                 // Field currentScanners:Ljava/util/List;
     334: invokeinterface #148,  1          // InterfaceMethod java/util/List.clear:()V
     339: aload_0
     340: aload         5
     342: invokespecial #83                 // Method addCurrentScanners:(Ljava/util/List;)V
     345: aload_0
     346: aload         6
     348: putfield      #128                // Field heap:Lorg/apache/hadoop/hbase/regionserver/KeyValueHeap;
     351: aload_0
     352: aload_1
     353: invokespecial #215                // Method resetQueryMatcher:(Lorg/apache/hadoop/hbase/Cell;)V
     356: aload_3
     357: invokedynamic #238,  0            // InvokeDynamic #0:accept:()Ljava/util/function/Consumer;
     362: invokeinterface #239,  2          // InterfaceMethod java/util/List.forEach:(Ljava/util/function/Consumer;)V
     367: return
    Exception table:
       from    to  target type
         170   228   298   Class java/lang/Exception
         229   295   298   Class java/lang/Exception

  protected final boolean checkFlushed();
    Code:
       0: aload_0
       1: getfield      #12                 // Field flushed:Z
       4: ifeq          23
       7: aload_0
       8: getfield      #5                  // Field closing:Z
      11: ifeq          16
      14: iconst_0
      15: ireturn
      16: aload_0
      17: iconst_0
      18: putfield      #12                 // Field flushed:Z
      21: iconst_1
      22: ireturn
      23: iconst_0
      24: ireturn

  java.util.List<org.apache.hadoop.hbase.regionserver.KeyValueScanner> getAllScannersForTesting();
    Code:
       0: new           #7                  // class java/util/ArrayList
       3: dup
       4: invokespecial #8                  // Method java/util/ArrayList."<init>":()V
       7: astore_1
       8: aload_0
       9: getfield      #128                // Field heap:Lorg/apache/hadoop/hbase/regionserver/KeyValueHeap;
      12: invokevirtual #254                // Method org/apache/hadoop/hbase/regionserver/KeyValueHeap.getCurrentForTesting:()Lorg/apache/hadoop/hbase/regionserver/KeyValueScanner;
      15: astore_2
      16: aload_2
      17: ifnull        28
      20: aload_1
      21: aload_2
      22: invokeinterface #137,  2          // InterfaceMethod java/util/List.add:(Ljava/lang/Object;)Z
      27: pop
      28: aload_0
      29: getfield      #128                // Field heap:Lorg/apache/hadoop/hbase/regionserver/KeyValueHeap;
      32: invokevirtual #255                // Method org/apache/hadoop/hbase/regionserver/KeyValueHeap.getHeap:()Ljava/util/PriorityQueue;
      35: invokevirtual #256                // Method java/util/PriorityQueue.iterator:()Ljava/util/Iterator;
      38: astore_3
      39: aload_3
      40: invokeinterface #109,  1          // InterfaceMethod java/util/Iterator.hasNext:()Z
      45: ifeq          71
      48: aload_3
      49: invokeinterface #110,  1          // InterfaceMethod java/util/Iterator.next:()Ljava/lang/Object;
      54: checkcast     #111                // class org/apache/hadoop/hbase/regionserver/KeyValueScanner
      57: astore        4
      59: aload_1
      60: aload         4
      62: invokeinterface #137,  2          // InterfaceMethod java/util/List.add:(Ljava/lang/Object;)Z
      67: pop
      68: goto          39
      71: aload_1
      72: areturn

  static void enableLazySeekGlobally(boolean);
    Code:
       0: iload_0
       1: putstatic     #79                 // Field lazySeekEnabledGlobally:Z
       4: return

  public long getEstimatedNumberOfKvsScanned();
    Code:
       0: aload_0
       1: getfield      #10                 // Field kvsScanned:J
       4: lreturn

  public org.apache.hadoop.hbase.Cell getNextIndexedKey();
    Code:
       0: aload_0
       1: getfield      #128                // Field heap:Lorg/apache/hadoop/hbase/regionserver/KeyValueHeap;
       4: invokevirtual #257                // Method org/apache/hadoop/hbase/regionserver/KeyValueHeap.getNextIndexedKey:()Lorg/apache/hadoop/hbase/Cell;
       7: areturn

  public void shipped() throws java.io.IOException;
    Code:
       0: aload_0
       1: getfield      #11                 // Field prevCell:Lorg/apache/hadoop/hbase/Cell;
       4: ifnull        18
       7: aload_0
       8: aload_0
       9: getfield      #11                 // Field prevCell:Lorg/apache/hadoop/hbase/Cell;
      12: invokestatic  #258                // Method org/apache/hadoop/hbase/KeyValueUtil.toNewKeyCell:(Lorg/apache/hadoop/hbase/Cell;)Lorg/apache/hadoop/hbase/KeyValue;
      15: putfield      #11                 // Field prevCell:Lorg/apache/hadoop/hbase/Cell;
      18: aload_0
      19: getfield      #70                 // Field matcher:Lorg/apache/hadoop/hbase/regionserver/querymatcher/ScanQueryMatcher;
      22: invokevirtual #259                // Method org/apache/hadoop/hbase/regionserver/querymatcher/ScanQueryMatcher.beforeShipped:()V
      25: aload_0
      26: getfield      #9                  // Field scannersForDelayedClose:Ljava/util/List;
      29: invokestatic  #146                // Method clearAndClose:(Ljava/util/List;)V
      32: aload_0
      33: getfield      #128                // Field heap:Lorg/apache/hadoop/hbase/regionserver/KeyValueHeap;
      36: ifnull        50
      39: aload_0
      40: getfield      #128                // Field heap:Lorg/apache/hadoop/hbase/regionserver/KeyValueHeap;
      43: invokevirtual #260                // Method org/apache/hadoop/hbase/regionserver/KeyValueHeap.shipped:()V
      46: aload_0
      47: invokevirtual #261                // Method trySwitchToStreamRead:()V
      50: return

  public org.apache.hadoop.hbase.Cell next() throws java.io.IOException;
    Code:
       0: aload_0
       1: invokevirtual #262                // Method next:()Lorg/apache/hadoop/hbase/KeyValue;
       4: areturn

  static {};
    Code:
       0: ldc_w         #263                // class org/apache/hadoop/hbase/regionserver/StoreScanner
       3: invokevirtual #264                // Method java/lang/Class.desiredAssertionStatus:()Z
       6: ifne          13
       9: iconst_1
      10: goto          14
      13: iconst_0
      14: putstatic     #92                 // Field $assertionsDisabled:Z
      17: ldc_w         #263                // class org/apache/hadoop/hbase/regionserver/StoreScanner
      20: invokestatic  #265                // Method org/slf4j/LoggerFactory.getLogger:(Ljava/lang/Class;)Lorg/slf4j/Logger;
      23: putstatic     #207                // Field LOG:Lorg/slf4j/Logger;
      26: iconst_1
      27: putstatic     #79                 // Field lazySeekEnabledGlobally:Z
      30: new           #101                // class org/apache/hadoop/hbase/client/Scan
      33: dup
      34: invokespecial #102                // Method org/apache/hadoop/hbase/client/Scan."<init>":()V
      37: putstatic     #89                 // Field SCAN_FOR_COMPACTION:Lorg/apache/hadoop/hbase/client/Scan;
      40: return
}
