Compiled from "StoreEngine.java"
public abstract class org.apache.hadoop.hbase.regionserver.StoreEngine<SF extends org.apache.hadoop.hbase.regionserver.StoreFlusher, CP extends org.apache.hadoop.hbase.regionserver.compactions.CompactionPolicy, C extends org.apache.hadoop.hbase.regionserver.compactions.Compactor, SFM extends org.apache.hadoop.hbase.regionserver.StoreFileManager> {
  protected SF storeFlusher;

  protected CP compactionPolicy;

  protected C compactor;

  protected SFM storeFileManager;

  public static final java.lang.String STORE_ENGINE_CLASS_KEY;

  static final boolean $assertionsDisabled;

  public org.apache.hadoop.hbase.regionserver.StoreEngine();
    Code:
       0: aload_0
       1: invokespecial #1                  // Method java/lang/Object."<init>":()V
       4: return

  public org.apache.hadoop.hbase.regionserver.compactions.CompactionPolicy getCompactionPolicy();
    Code:
       0: aload_0
       1: getfield      #2                  // Field compactionPolicy:Lorg/apache/hadoop/hbase/regionserver/compactions/CompactionPolicy;
       4: areturn

  public org.apache.hadoop.hbase.regionserver.compactions.Compactor getCompactor();
    Code:
       0: aload_0
       1: getfield      #3                  // Field compactor:Lorg/apache/hadoop/hbase/regionserver/compactions/Compactor;
       4: areturn

  public org.apache.hadoop.hbase.regionserver.StoreFileManager getStoreFileManager();
    Code:
       0: aload_0
       1: getfield      #4                  // Field storeFileManager:Lorg/apache/hadoop/hbase/regionserver/StoreFileManager;
       4: areturn

  public org.apache.hadoop.hbase.regionserver.StoreFlusher getStoreFlusher();
    Code:
       0: aload_0
       1: getfield      #5                  // Field storeFlusher:Lorg/apache/hadoop/hbase/regionserver/StoreFlusher;
       4: areturn

  public abstract boolean needsCompaction(java.util.List<org.apache.hadoop.hbase.regionserver.HStoreFile>);

  public abstract org.apache.hadoop.hbase.regionserver.compactions.CompactionContext createCompaction() throws java.io.IOException;

  protected abstract void createComponents(org.apache.hadoop.conf.Configuration, org.apache.hadoop.hbase.regionserver.HStore, org.apache.hadoop.hbase.CellComparator) throws java.io.IOException;

  public static org.apache.hadoop.hbase.regionserver.StoreEngine<?, ?, ?, ?> create(org.apache.hadoop.hbase.regionserver.HStore, org.apache.hadoop.conf.Configuration, org.apache.hadoop.hbase.CellComparator) throws java.io.IOException;
    Code:
       0: aload_1
       1: ldc           #11                 // String hbase.hstore.engine.class
       3: getstatic     #12                 // Field DEFAULT_STORE_ENGINE_CLASS:Ljava/lang/Class;
       6: invokevirtual #13                 // Method java/lang/Class.getName:()Ljava/lang/String;
       9: invokevirtual #14                 // Method org/apache/hadoop/conf/Configuration.get:(Ljava/lang/String;Ljava/lang/String;)Ljava/lang/String;
      12: astore_3
      13: aload_3
      14: iconst_0
      15: anewarray     #15                 // class java/lang/Class
      18: iconst_0
      19: anewarray     #16                 // class java/lang/Object
      22: invokestatic  #17                 // Method org/apache/hadoop/hbase/util/ReflectionUtils.instantiateWithCustomCtor:(Ljava/lang/String;[Ljava/lang/Class;[Ljava/lang/Object;)Ljava/lang/Object;
      25: checkcast     #10                 // class org/apache/hadoop/hbase/regionserver/StoreEngine
      28: astore        4
      30: aload         4
      32: aload_1
      33: aload_0
      34: aload_2
      35: invokespecial #18                 // Method createComponentsOnce:(Lorg/apache/hadoop/conf/Configuration;Lorg/apache/hadoop/hbase/regionserver/HStore;Lorg/apache/hadoop/hbase/CellComparator;)V
      38: aload         4
      40: areturn
      41: astore        4
      43: new           #20                 // class java/io/IOException
      46: dup
      47: new           #21                 // class java/lang/StringBuilder
      50: dup
      51: invokespecial #22                 // Method java/lang/StringBuilder."<init>":()V
      54: ldc           #23                 // String Unable to load configured store engine '
      56: invokevirtual #24                 // Method java/lang/StringBuilder.append:(Ljava/lang/String;)Ljava/lang/StringBuilder;
      59: aload_3
      60: invokevirtual #24                 // Method java/lang/StringBuilder.append:(Ljava/lang/String;)Ljava/lang/StringBuilder;
      63: ldc           #25                 // String '
      65: invokevirtual #24                 // Method java/lang/StringBuilder.append:(Ljava/lang/String;)Ljava/lang/StringBuilder;
      68: invokevirtual #26                 // Method java/lang/StringBuilder.toString:()Ljava/lang/String;
      71: aload         4
      73: invokespecial #27                 // Method java/io/IOException."<init>":(Ljava/lang/String;Ljava/lang/Throwable;)V
      76: athrow
    Exception table:
       from    to  target type
          13    40    41   Class java/lang/Exception

  static {};
    Code:
       0: ldc           #10                 // class org/apache/hadoop/hbase/regionserver/StoreEngine
       2: invokevirtual #28                 // Method java/lang/Class.desiredAssertionStatus:()Z
       5: ifne          12
       8: iconst_1
       9: goto          13
      12: iconst_0
      13: putstatic     #6                  // Field $assertionsDisabled:Z
      16: ldc           #29                 // class org/apache/hadoop/hbase/regionserver/DefaultStoreEngine
      18: putstatic     #12                 // Field DEFAULT_STORE_ENGINE_CLASS:Ljava/lang/Class;
      21: return
}
