Compiled from "StripeStoreFlusher.java"
class org.apache.hadoop.hbase.regionserver.StripeStoreFlusher$1 implements org.apache.hadoop.hbase.regionserver.AbstractMultiFileWriter$WriterFactory {
  final long val$kvCount;

  final org.apache.hadoop.hbase.regionserver.StripeStoreFlusher this$0;

  org.apache.hadoop.hbase.regionserver.StripeStoreFlusher$1(org.apache.hadoop.hbase.regionserver.StripeStoreFlusher, long);
    Code:
       0: aload_0
       1: aload_1
       2: putfield      #1                  // Field this$0:Lorg/apache/hadoop/hbase/regionserver/StripeStoreFlusher;
       5: aload_0
       6: lload_2
       7: putfield      #2                  // Field val$kvCount:J
      10: aload_0
      11: invokespecial #3                  // Method java/lang/Object."<init>":()V
      14: return

  public org.apache.hadoop.hbase.regionserver.StoreFileWriter createWriter() throws java.io.IOException;
    Code:
       0: aload_0
       1: getfield      #1                  // Field this$0:Lorg/apache/hadoop/hbase/regionserver/StripeStoreFlusher;
       4: getfield      #4                  // Field org/apache/hadoop/hbase/regionserver/StripeStoreFlusher.store:Lorg/apache/hadoop/hbase/regionserver/HStore;
       7: aload_0
       8: getfield      #2                  // Field val$kvCount:J
      11: aload_0
      12: getfield      #1                  // Field this$0:Lorg/apache/hadoop/hbase/regionserver/StripeStoreFlusher;
      15: getfield      #4                  // Field org/apache/hadoop/hbase/regionserver/StripeStoreFlusher.store:Lorg/apache/hadoop/hbase/regionserver/HStore;
      18: invokevirtual #5                  // Method org/apache/hadoop/hbase/regionserver/HStore.getColumnFamilyDescriptor:()Lorg/apache/hadoop/hbase/client/ColumnFamilyDescriptor;
      21: invokeinterface #6,  1            // InterfaceMethod org/apache/hadoop/hbase/client/ColumnFamilyDescriptor.getCompressionType:()Lorg/apache/hadoop/hbase/io/compress/Compression$Algorithm;
      26: iconst_0
      27: iconst_1
      28: iconst_1
      29: iconst_0
      30: invokevirtual #7                  // Method org/apache/hadoop/hbase/regionserver/HStore.createWriterInTmp:(JLorg/apache/hadoop/hbase/io/compress/Compression$Algorithm;ZZZZ)Lorg/apache/hadoop/hbase/regionserver/StoreFileWriter;
      33: astore_1
      34: aload_1
      35: areturn
}
