Compiled from "StripeCompactionPolicy.java"
class org.apache.hadoop.hbase.regionserver.compactions.StripeCompactionPolicy$BoundaryStripeCompactionRequest extends org.apache.hadoop.hbase.regionserver.compactions.StripeCompactionPolicy$StripeCompactionRequest {
  public org.apache.hadoop.hbase.regionserver.compactions.StripeCompactionPolicy$BoundaryStripeCompactionRequest(org.apache.hadoop.hbase.regionserver.compactions.CompactionRequestImpl, java.util.List<byte[]>);
    Code:
       0: aload_0
       1: aload_1
       2: invokespecial #1                  // Method org/apache/hadoop/hbase/regionserver/compactions/StripeCompactionPolicy$StripeCompactionRequest."<init>":(Lorg/apache/hadoop/hbase/regionserver/compactions/CompactionRequestImpl;)V
       5: aload_0
       6: aload_2
       7: putfield      #2                  // Field targetBoundaries:Ljava/util/List;
      10: return

  public org.apache.hadoop.hbase.regionserver.compactions.StripeCompactionPolicy$BoundaryStripeCompactionRequest(java.util.Collection<org.apache.hadoop.hbase.regionserver.HStoreFile>, java.util.List<byte[]>);
    Code:
       0: aload_0
       1: new           #3                  // class org/apache/hadoop/hbase/regionserver/compactions/CompactionRequestImpl
       4: dup
       5: aload_1
       6: invokespecial #4                  // Method org/apache/hadoop/hbase/regionserver/compactions/CompactionRequestImpl."<init>":(Ljava/util/Collection;)V
       9: aload_2
      10: invokespecial #5                  // Method "<init>":(Lorg/apache/hadoop/hbase/regionserver/compactions/CompactionRequestImpl;Ljava/util/List;)V
      13: return

  public java.util.List<org.apache.hadoop.fs.Path> execute(org.apache.hadoop.hbase.regionserver.compactions.StripeCompactor, org.apache.hadoop.hbase.regionserver.throttle.ThroughputController, org.apache.hadoop.hbase.security.User) throws java.io.IOException;
    Code:
       0: aload_1
       1: aload_0
       2: getfield      #6                  // Field request:Lorg/apache/hadoop/hbase/regionserver/compactions/CompactionRequestImpl;
       5: aload_0
       6: getfield      #2                  // Field targetBoundaries:Ljava/util/List;
       9: aload_0
      10: getfield      #7                  // Field majorRangeFromRow:[B
      13: aload_0
      14: getfield      #8                  // Field majorRangeToRow:[B
      17: aload_2
      18: aload_3
      19: invokevirtual #9                  // Method org/apache/hadoop/hbase/regionserver/compactions/StripeCompactor.compact:(Lorg/apache/hadoop/hbase/regionserver/compactions/CompactionRequestImpl;Ljava/util/List;[B[BLorg/apache/hadoop/hbase/regionserver/throttle/ThroughputController;Lorg/apache/hadoop/hbase/security/User;)Ljava/util/List;
      22: areturn
}
