Compiled from "Strings.java"
public class org.apache.hadoop.hbase.util.Strings {
  public static final java.lang.String DEFAULT_SEPARATOR;

  public static final java.lang.String DEFAULT_KEYVALUE_SEPARATOR;

  public org.apache.hadoop.hbase.util.Strings();
    Code:
       0: aload_0
       1: invokespecial #1                  // Method java/lang/Object."<init>":()V
       4: return

  public static java.lang.StringBuilder appendKeyValue(java.lang.StringBuilder, java.lang.String, java.lang.Object);
    Code:
       0: aload_0
       1: aload_1
       2: aload_2
       3: ldc           #3                  // String =
       5: ldc           #4                  // String ,
       7: invokestatic  #5                  // Method appendKeyValue:(Ljava/lang/StringBuilder;Ljava/lang/String;Ljava/lang/Object;Ljava/lang/String;Ljava/lang/String;)Ljava/lang/StringBuilder;
      10: areturn

  public static java.lang.StringBuilder appendKeyValue(java.lang.StringBuilder, java.lang.String, java.lang.Object, java.lang.String, java.lang.String);
    Code:
       0: aload_0
       1: invokevirtual #6                  // Method java/lang/StringBuilder.length:()I
       4: ifle          14
       7: aload_0
       8: aload         4
      10: invokevirtual #7                  // Method java/lang/StringBuilder.append:(Ljava/lang/String;)Ljava/lang/StringBuilder;
      13: pop
      14: aload_0
      15: aload_1
      16: invokevirtual #7                  // Method java/lang/StringBuilder.append:(Ljava/lang/String;)Ljava/lang/StringBuilder;
      19: aload_3
      20: invokevirtual #7                  // Method java/lang/StringBuilder.append:(Ljava/lang/String;)Ljava/lang/StringBuilder;
      23: aload_2
      24: invokevirtual #8                  // Method java/lang/StringBuilder.append:(Ljava/lang/Object;)Ljava/lang/StringBuilder;
      27: areturn

  public static java.lang.String domainNamePointerToHostName(java.lang.String);
    Code:
       0: aload_0
       1: ifnonnull     6
       4: aconst_null
       5: areturn
       6: aload_0
       7: ldc           #9                  // String .
       9: invokevirtual #10                 // Method java/lang/String.endsWith:(Ljava/lang/String;)Z
      12: ifeq          29
      15: aload_0
      16: iconst_0
      17: aload_0
      18: invokevirtual #11                 // Method java/lang/String.length:()I
      21: iconst_1
      22: isub
      23: invokevirtual #12                 // Method java/lang/String.substring:(II)Ljava/lang/String;
      26: goto          30
      29: aload_0
      30: areturn

  public static java.lang.String padFront(java.lang.String, char, int);
    Code:
       0: aload_0
       1: invokevirtual #11                 // Method java/lang/String.length:()I
       4: iload_2
       5: if_icmple     44
       8: new           #13                 // class java/lang/IllegalArgumentException
      11: dup
      12: new           #14                 // class java/lang/StringBuilder
      15: dup
      16: invokespecial #15                 // Method java/lang/StringBuilder."<init>":()V
      19: ldc           #16                 // String input \"
      21: invokevirtual #7                  // Method java/lang/StringBuilder.append:(Ljava/lang/String;)Ljava/lang/StringBuilder;
      24: aload_0
      25: invokevirtual #7                  // Method java/lang/StringBuilder.append:(Ljava/lang/String;)Ljava/lang/StringBuilder;
      28: ldc           #17                 // String \" longer than maxLength=
      30: invokevirtual #7                  // Method java/lang/StringBuilder.append:(Ljava/lang/String;)Ljava/lang/StringBuilder;
      33: iload_2
      34: invokevirtual #18                 // Method java/lang/StringBuilder.append:(I)Ljava/lang/StringBuilder;
      37: invokevirtual #19                 // Method java/lang/StringBuilder.toString:()Ljava/lang/String;
      40: invokespecial #20                 // Method java/lang/IllegalArgumentException."<init>":(Ljava/lang/String;)V
      43: athrow
      44: iload_2
      45: aload_0
      46: invokevirtual #11                 // Method java/lang/String.length:()I
      49: isub
      50: istore_3
      51: new           #14                 // class java/lang/StringBuilder
      54: dup
      55: invokespecial #15                 // Method java/lang/StringBuilder."<init>":()V
      58: iload_1
      59: iload_3
      60: invokestatic  #21                 // Method org/apache/commons/lang3/StringUtils.repeat:(CI)Ljava/lang/String;
      63: invokevirtual #7                  // Method java/lang/StringBuilder.append:(Ljava/lang/String;)Ljava/lang/StringBuilder;
      66: aload_0
      67: invokevirtual #7                  // Method java/lang/StringBuilder.append:(Ljava/lang/String;)Ljava/lang/StringBuilder;
      70: invokevirtual #19                 // Method java/lang/StringBuilder.toString:()Ljava/lang/String;
      73: areturn
}
