Compiled from "StripeStoreConfig.java"
public class org.apache.hadoop.hbase.regionserver.StripeStoreConfig {
  public static final java.lang.String MAX_FILES_KEY;

  public static final java.lang.String MIN_FILES_KEY;

  public static final java.lang.String MIN_FILES_L0_KEY;

  public static final java.lang.String SIZE_TO_SPLIT_KEY;

  public static final java.lang.String SPLIT_PARTS_KEY;

  public static final java.lang.String INITIAL_STRIPE_COUNT_KEY;

  public static final java.lang.String FLUSH_TO_L0_KEY;

  public static final java.lang.String MAX_REGION_SPLIT_IMBALANCE_KEY;

  public org.apache.hadoop.hbase.regionserver.StripeStoreConfig(org.apache.hadoop.conf.Configuration, org.apache.hadoop.hbase.regionserver.StoreConfigInformation);
    Code:
       0: aload_0
       1: invokespecial #1                  // Method java/lang/Object."<init>":()V
       4: aload_0
       5: aload_1
       6: ldc           #3                  // String hbase.store.stripe.compaction.minFilesL0
       8: iconst_4
       9: invokevirtual #4                  // Method org/apache/hadoop/conf/Configuration.getInt:(Ljava/lang/String;I)I
      12: putfield      #5                  // Field level0CompactMinFiles:I
      15: aload_0
      16: aload_1
      17: ldc           #6                  // String hbase.store.stripe.compaction.flushToL0
      19: iconst_0
      20: invokevirtual #7                  // Method org/apache/hadoop/conf/Configuration.getBoolean:(Ljava/lang/String;Z)Z
      23: putfield      #8                  // Field flushIntoL0:Z
      26: aload_0
      27: getfield      #8                  // Field flushIntoL0:Z
      30: ifeq          37
      33: iconst_3
      34: goto          38
      37: iconst_4
      38: istore_3
      39: aload_1
      40: ldc           #10                 // String hbase.hstore.compaction.min
      42: iconst_m1
      43: invokevirtual #4                  // Method org/apache/hadoop/conf/Configuration.getInt:(Ljava/lang/String;I)I
      46: istore        4
      48: aload_0
      49: aload_1
      50: ldc           #11                 // String hbase.store.stripe.compaction.minFiles
      52: iload_3
      53: iload         4
      55: invokestatic  #12                 // Method java/lang/Math.max:(II)I
      58: invokevirtual #4                  // Method org/apache/hadoop/conf/Configuration.getInt:(Ljava/lang/String;I)I
      61: putfield      #13                 // Field stripeCompactMinFiles:I
      64: aload_0
      65: aload_1
      66: ldc           #14                 // String hbase.store.stripe.compaction.maxFiles
      68: aload_1
      69: ldc           #15                 // String hbase.hstore.compaction.max
      71: bipush        10
      73: invokevirtual #4                  // Method org/apache/hadoop/conf/Configuration.getInt:(Ljava/lang/String;I)I
      76: invokevirtual #4                  // Method org/apache/hadoop/conf/Configuration.getInt:(Ljava/lang/String;I)I
      79: putfield      #16                 // Field stripeCompactMaxFiles:I
      82: aload_0
      83: aload_1
      84: ldc           #17                 // String hbase.store.stripe.region.split.max.imbalance
      86: ldc           #18                 // float 1.5f
      88: iconst_1
      89: invokestatic  #19                 // Method getFloat:(Lorg/apache/hadoop/conf/Configuration;Ljava/lang/String;FZ)F
      92: putfield      #20                 // Field maxRegionSplitImbalance:F
      95: aload_1
      96: ldc           #21                 // String hbase.store.stripe.splitPartCount
      98: fconst_2
      99: iconst_1
     100: invokestatic  #19                 // Method getFloat:(Lorg/apache/hadoop/conf/Configuration;Ljava/lang/String;FZ)F
     103: fstore        5
     105: fload         5
     107: f2d
     108: dconst_1
     109: dsub
     110: invokestatic  #22                 // Method java/lang/Math.abs:(D)D
     113: ldc2_w        #23                 // double 0.001d
     116: dcmpg
     117: ifge          156
     120: getstatic     #25                 // Field LOG:Lorg/slf4j/Logger;
     123: new           #26                 // class java/lang/StringBuilder
     126: dup
     127: invokespecial #27                 // Method java/lang/StringBuilder."<init>":()V
     130: ldc           #28                 // String Split part count cannot be 1 (
     132: invokevirtual #29                 // Method java/lang/StringBuilder.append:(Ljava/lang/String;)Ljava/lang/StringBuilder;
     135: fload         5
     137: invokevirtual #30                 // Method java/lang/StringBuilder.append:(F)Ljava/lang/StringBuilder;
     140: ldc           #31                 // String ), using the default
     142: invokevirtual #29                 // Method java/lang/StringBuilder.append:(Ljava/lang/String;)Ljava/lang/StringBuilder;
     145: invokevirtual #32                 // Method java/lang/StringBuilder.toString:()Ljava/lang/String;
     148: invokeinterface #33,  2           // InterfaceMethod org/slf4j/Logger.error:(Ljava/lang/String;)V
     153: fconst_2
     154: fstore        5
     156: aload_0
     157: fload         5
     159: putfield      #34                 // Field splitPartCount:F
     162: aload_2
     163: invokeinterface #35,  1           // InterfaceMethod org/apache/hadoop/hbase/regionserver/StoreConfigInformation.getMemStoreFlushSize:()J
     168: l2d
     169: dstore        6
     171: dload         6
     173: dconst_0
     174: dcmpl
     175: ifne          183
     178: ldc2_w        #36                 // double 1.34217728E8d
     181: dstore        6
     183: dload         6
     185: aload_0
     186: invokevirtual #38                 // Method getLevel0MinFiles:()I
     189: i2d
     190: dmul
     191: ldc2_w        #39                 // double 4.0d
     194: dmul
     195: fload         5
     197: f2d
     198: dmul
     199: d2l
     200: lstore        8
     202: aload_0
     203: aload_1
     204: ldc           #41                 // String hbase.store.stripe.sizeToSplit
     206: lload         8
     208: invokevirtual #42                 // Method org/apache/hadoop/conf/Configuration.getLong:(Ljava/lang/String;J)J
     211: putfield      #43                 // Field sizeToSplitAt:J
     214: aload_1
     215: ldc           #44                 // String hbase.store.stripe.initialStripeCount
     217: iconst_1
     218: invokevirtual #4                  // Method org/apache/hadoop/conf/Configuration.getInt:(Ljava/lang/String;I)I
     221: istore        10
     223: iload         10
     225: ifne          241
     228: getstatic     #25                 // Field LOG:Lorg/slf4j/Logger;
     231: ldc           #45                 // String Initial stripe count is 0, using the default
     233: invokeinterface #33,  2           // InterfaceMethod org/slf4j/Logger.error:(Ljava/lang/String;)V
     238: iconst_1
     239: istore        10
     241: aload_0
     242: iload         10
     244: putfield      #46                 // Field initialCount:I
     247: aload_0
     248: aload_0
     249: getfield      #43                 // Field sizeToSplitAt:J
     252: l2f
     253: aload_0
     254: getfield      #34                 // Field splitPartCount:F
     257: fdiv
     258: f2l
     259: putfield      #47                 // Field splitPartSize:J
     262: return

  public float getMaxSplitImbalance();
    Code:
       0: aload_0
       1: getfield      #20                 // Field maxRegionSplitImbalance:F
       4: freturn

  public int getLevel0MinFiles();
    Code:
       0: aload_0
       1: getfield      #5                  // Field level0CompactMinFiles:I
       4: ireturn

  public int getStripeCompactMinFiles();
    Code:
       0: aload_0
       1: getfield      #13                 // Field stripeCompactMinFiles:I
       4: ireturn

  public int getStripeCompactMaxFiles();
    Code:
       0: aload_0
       1: getfield      #16                 // Field stripeCompactMaxFiles:I
       4: ireturn

  public boolean isUsingL0Flush();
    Code:
       0: aload_0
       1: getfield      #8                  // Field flushIntoL0:Z
       4: ireturn

  public long getSplitSize();
    Code:
       0: aload_0
       1: getfield      #43                 // Field sizeToSplitAt:J
       4: lreturn

  public int getInitialCount();
    Code:
       0: aload_0
       1: getfield      #46                 // Field initialCount:I
       4: ireturn

  public float getSplitCount();
    Code:
       0: aload_0
       1: getfield      #34                 // Field splitPartCount:F
       4: freturn

  public long getSplitPartSize();
    Code:
       0: aload_0
       1: getfield      #47                 // Field splitPartSize:J
       4: lreturn

  static {};
    Code:
       0: ldc           #2                  // class org/apache/hadoop/hbase/regionserver/StripeStoreConfig
       2: invokestatic  #54                 // Method org/slf4j/LoggerFactory.getLogger:(Ljava/lang/Class;)Lorg/slf4j/Logger;
       5: putstatic     #25                 // Field LOG:Lorg/slf4j/Logger;
       8: return
}
