Compiled from "StripeStoreFlusher.java"
public class org.apache.hadoop.hbase.regionserver.StripeStoreFlusher$BoundaryStripeFlushRequest extends org.apache.hadoop.hbase.regionserver.StripeStoreFlusher$StripeFlushRequest {
  public org.apache.hadoop.hbase.regionserver.StripeStoreFlusher$BoundaryStripeFlushRequest(org.apache.hadoop.hbase.CellComparator, java.util.List<byte[]>);
    Code:
       0: aload_0
       1: aload_1
       2: invokespecial #1                  // Method org/apache/hadoop/hbase/regionserver/StripeStoreFlusher$StripeFlushRequest."<init>":(Lorg/apache/hadoop/hbase/CellComparator;)V
       5: aload_0
       6: aload_2
       7: putfield      #2                  // Field targetBoundaries:Ljava/util/List;
      10: return

  public org.apache.hadoop.hbase.regionserver.StripeMultiFileWriter createWriter() throws java.io.IOException;
    Code:
       0: new           #3                  // class org/apache/hadoop/hbase/regionserver/StripeMultiFileWriter$BoundaryMultiWriter
       3: dup
       4: aload_0
       5: getfield      #4                  // Field comparator:Lorg/apache/hadoop/hbase/CellComparator;
       8: aload_0
       9: getfield      #2                  // Field targetBoundaries:Ljava/util/List;
      12: aconst_null
      13: aconst_null
      14: invokespecial #5                  // Method org/apache/hadoop/hbase/regionserver/StripeMultiFileWriter$BoundaryMultiWriter."<init>":(Lorg/apache/hadoop/hbase/CellComparator;Ljava/util/List;[B[B)V
      17: areturn
}
