Compiled from "StructIterator.java"
public class org.apache.hadoop.hbase.types.StructIterator implements java.util.Iterator<java.lang.Object> {
  protected final org.apache.hadoop.hbase.util.PositionedByteRange src;

  protected int idx;

  protected final org.apache.hadoop.hbase.types.DataType[] types;

  public org.apache.hadoop.hbase.types.StructIterator(org.apache.hadoop.hbase.util.PositionedByteRange, org.apache.hadoop.hbase.types.DataType[]);
    Code:
       0: aload_0
       1: invokespecial #1                  // Method java/lang/Object."<init>":()V
       4: aload_0
       5: iconst_0
       6: putfield      #2                  // Field idx:I
       9: aload_0
      10: aload_1
      11: putfield      #3                  // Field src:Lorg/apache/hadoop/hbase/util/PositionedByteRange;
      14: aload_0
      15: aload_2
      16: putfield      #4                  // Field types:[Lorg/apache/hadoop/hbase/types/DataType;
      19: return

  public boolean hasNext();
    Code:
       0: aload_0
       1: getfield      #2                  // Field idx:I
       4: aload_0
       5: getfield      #4                  // Field types:[Lorg/apache/hadoop/hbase/types/DataType;
       8: arraylength
       9: if_icmpge     37
      12: aload_0
      13: getfield      #3                  // Field src:Lorg/apache/hadoop/hbase/util/PositionedByteRange;
      16: invokeinterface #5,  1            // InterfaceMethod org/apache/hadoop/hbase/util/PositionedByteRange.getPosition:()I
      21: aload_0
      22: getfield      #3                  // Field src:Lorg/apache/hadoop/hbase/util/PositionedByteRange;
      25: invokeinterface #6,  1            // InterfaceMethod org/apache/hadoop/hbase/util/PositionedByteRange.getLength:()I
      30: if_icmpgt     37
      33: iconst_1
      34: goto          38
      37: iconst_0
      38: ireturn

  public void remove();
    Code:
       0: new           #7                  // class java/lang/UnsupportedOperationException
       3: dup
       4: invokespecial #8                  // Method java/lang/UnsupportedOperationException."<init>":()V
       7: athrow

  public java.lang.Object next();
    Code:
       0: aload_0
       1: invokevirtual #9                  // Method hasNext:()Z
       4: ifne          15
       7: new           #10                 // class java/util/NoSuchElementException
      10: dup
      11: invokespecial #11                 // Method java/util/NoSuchElementException."<init>":()V
      14: athrow
      15: aload_0
      16: getfield      #4                  // Field types:[Lorg/apache/hadoop/hbase/types/DataType;
      19: aload_0
      20: dup
      21: getfield      #2                  // Field idx:I
      24: dup_x1
      25: iconst_1
      26: iadd
      27: putfield      #2                  // Field idx:I
      30: aaload
      31: astore_1
      32: aload_0
      33: getfield      #3                  // Field src:Lorg/apache/hadoop/hbase/util/PositionedByteRange;
      36: invokeinterface #5,  1            // InterfaceMethod org/apache/hadoop/hbase/util/PositionedByteRange.getPosition:()I
      41: aload_0
      42: getfield      #3                  // Field src:Lorg/apache/hadoop/hbase/util/PositionedByteRange;
      45: invokeinterface #6,  1            // InterfaceMethod org/apache/hadoop/hbase/util/PositionedByteRange.getLength:()I
      50: if_icmpne     64
      53: aload_1
      54: invokeinterface #12,  1           // InterfaceMethod org/apache/hadoop/hbase/types/DataType.isNullable:()Z
      59: ifeq          64
      62: aconst_null
      63: areturn
      64: aload_1
      65: aload_0
      66: getfield      #3                  // Field src:Lorg/apache/hadoop/hbase/util/PositionedByteRange;
      69: invokeinterface #13,  2           // InterfaceMethod org/apache/hadoop/hbase/types/DataType.decode:(Lorg/apache/hadoop/hbase/util/PositionedByteRange;)Ljava/lang/Object;
      74: areturn

  public int skip();
    Code:
       0: aload_0
       1: invokevirtual #9                  // Method hasNext:()Z
       4: ifne          15
       7: new           #10                 // class java/util/NoSuchElementException
      10: dup
      11: invokespecial #11                 // Method java/util/NoSuchElementException."<init>":()V
      14: athrow
      15: aload_0
      16: getfield      #4                  // Field types:[Lorg/apache/hadoop/hbase/types/DataType;
      19: aload_0
      20: dup
      21: getfield      #2                  // Field idx:I
      24: dup_x1
      25: iconst_1
      26: iadd
      27: putfield      #2                  // Field idx:I
      30: aaload
      31: astore_1
      32: aload_0
      33: getfield      #3                  // Field src:Lorg/apache/hadoop/hbase/util/PositionedByteRange;
      36: invokeinterface #5,  1            // InterfaceMethod org/apache/hadoop/hbase/util/PositionedByteRange.getPosition:()I
      41: aload_0
      42: getfield      #3                  // Field src:Lorg/apache/hadoop/hbase/util/PositionedByteRange;
      45: invokeinterface #6,  1            // InterfaceMethod org/apache/hadoop/hbase/util/PositionedByteRange.getLength:()I
      50: if_icmpne     64
      53: aload_1
      54: invokeinterface #12,  1           // InterfaceMethod org/apache/hadoop/hbase/types/DataType.isNullable:()Z
      59: ifeq          64
      62: iconst_0
      63: ireturn
      64: aload_1
      65: aload_0
      66: getfield      #3                  // Field src:Lorg/apache/hadoop/hbase/util/PositionedByteRange;
      69: invokeinterface #14,  2           // InterfaceMethod org/apache/hadoop/hbase/types/DataType.skip:(Lorg/apache/hadoop/hbase/util/PositionedByteRange;)I
      74: ireturn
}
