Compiled from "SubstringComparator.java"
public class org.apache.hadoop.hbase.filter.SubstringComparator extends org.apache.hadoop.hbase.filter.ByteArrayComparable {
  public org.apache.hadoop.hbase.filter.SubstringComparator(java.lang.String);
    Code:
       0: aload_0
       1: aload_1
       2: getstatic     #1                  // Field java/util/Locale.ROOT:Ljava/util/Locale;
       5: invokevirtual #2                  // Method java/lang/String.toLowerCase:(Ljava/util/Locale;)Ljava/lang/String;
       8: invokestatic  #3                  // Method org/apache/hadoop/hbase/util/Bytes.toBytes:(Ljava/lang/String;)[B
      11: invokespecial #4                  // Method org/apache/hadoop/hbase/filter/ByteArrayComparable."<init>":([B)V
      14: aload_0
      15: aload_1
      16: getstatic     #1                  // Field java/util/Locale.ROOT:Ljava/util/Locale;
      19: invokevirtual #2                  // Method java/lang/String.toLowerCase:(Ljava/util/Locale;)Ljava/lang/String;
      22: putfield      #5                  // Field substr:Ljava/lang/String;
      25: return

  public byte[] getValue();
    Code:
       0: aload_0
       1: getfield      #5                  // Field substr:Ljava/lang/String;
       4: invokestatic  #3                  // Method org/apache/hadoop/hbase/util/Bytes.toBytes:(Ljava/lang/String;)[B
       7: areturn

  public int compareTo(byte[], int, int);
    Code:
       0: aload_1
       1: iload_2
       2: iload_3
       3: invokestatic  #6                  // Method org/apache/hadoop/hbase/util/Bytes.toString:([BII)Ljava/lang/String;
       6: getstatic     #1                  // Field java/util/Locale.ROOT:Ljava/util/Locale;
       9: invokevirtual #2                  // Method java/lang/String.toLowerCase:(Ljava/util/Locale;)Ljava/lang/String;
      12: aload_0
      13: getfield      #5                  // Field substr:Ljava/lang/String;
      16: invokevirtual #7                  // Method java/lang/String.contains:(Ljava/lang/CharSequence;)Z
      19: ifeq          26
      22: iconst_0
      23: goto          27
      26: iconst_1
      27: ireturn

  public byte[] toByteArray();
    Code:
       0: invokestatic  #8                  // Method org/apache/hadoop/hbase/shaded/protobuf/generated/ComparatorProtos$SubstringComparator.newBuilder:()Lorg/apache/hadoop/hbase/shaded/protobuf/generated/ComparatorProtos$SubstringComparator$Builder;
       3: astore_1
       4: aload_1
       5: aload_0
       6: getfield      #5                  // Field substr:Ljava/lang/String;
       9: invokevirtual #9                  // Method org/apache/hadoop/hbase/shaded/protobuf/generated/ComparatorProtos$SubstringComparator$Builder.setSubstr:(Ljava/lang/String;)Lorg/apache/hadoop/hbase/shaded/protobuf/generated/ComparatorProtos$SubstringComparator$Builder;
      12: pop
      13: aload_1
      14: invokevirtual #10                 // Method org/apache/hadoop/hbase/shaded/protobuf/generated/ComparatorProtos$SubstringComparator$Builder.build:()Lorg/apache/hadoop/hbase/shaded/protobuf/generated/ComparatorProtos$SubstringComparator;
      17: invokevirtual #11                 // Method org/apache/hadoop/hbase/shaded/protobuf/generated/ComparatorProtos$SubstringComparator.toByteArray:()[B
      20: areturn

  public static org.apache.hadoop.hbase.filter.SubstringComparator parseFrom(byte[]) throws org.apache.hadoop.hbase.exceptions.DeserializationException;
    Code:
       0: aload_0
       1: invokestatic  #12                 // Method org/apache/hadoop/hbase/shaded/protobuf/generated/ComparatorProtos$SubstringComparator.parseFrom:([B)Lorg/apache/hadoop/hbase/shaded/protobuf/generated/ComparatorProtos$SubstringComparator;
       4: astore_1
       5: goto          18
       8: astore_2
       9: new           #14                 // class org/apache/hadoop/hbase/exceptions/DeserializationException
      12: dup
      13: aload_2
      14: invokespecial #15                 // Method org/apache/hadoop/hbase/exceptions/DeserializationException."<init>":(Ljava/lang/Throwable;)V
      17: athrow
      18: new           #16                 // class org/apache/hadoop/hbase/filter/SubstringComparator
      21: dup
      22: aload_1
      23: invokevirtual #17                 // Method org/apache/hadoop/hbase/shaded/protobuf/generated/ComparatorProtos$SubstringComparator.getSubstr:()Ljava/lang/String;
      26: invokespecial #18                 // Method "<init>":(Ljava/lang/String;)V
      29: areturn
    Exception table:
       from    to  target type
           0     5     8   Class org/apache/hbase/thirdparty/com/google/protobuf/InvalidProtocolBufferException

  boolean areSerializedFieldsEqual(org.apache.hadoop.hbase.filter.ByteArrayComparable);
    Code:
       0: aload_1
       1: aload_0
       2: if_acmpne     7
       5: iconst_1
       6: ireturn
       7: aload_1
       8: instanceof    #16                 // class org/apache/hadoop/hbase/filter/SubstringComparator
      11: ifne          16
      14: iconst_0
      15: ireturn
      16: aload_1
      17: checkcast     #16                 // class org/apache/hadoop/hbase/filter/SubstringComparator
      20: astore_2
      21: aload_0
      22: aload_2
      23: invokespecial #19                 // Method org/apache/hadoop/hbase/filter/ByteArrayComparable.areSerializedFieldsEqual:(Lorg/apache/hadoop/hbase/filter/ByteArrayComparable;)Z
      26: ifeq          47
      29: aload_0
      30: getfield      #5                  // Field substr:Ljava/lang/String;
      33: aload_2
      34: getfield      #5                  // Field substr:Ljava/lang/String;
      37: invokevirtual #20                 // Method java/lang/String.equals:(Ljava/lang/Object;)Z
      40: ifeq          47
      43: iconst_1
      44: goto          48
      47: iconst_0
      48: ireturn
}
