Compiled from "SwitchRpcThrottleRemoteProcedure.java"
public class org.apache.hadoop.hbase.master.procedure.SwitchRpcThrottleRemoteProcedure extends org.apache.hadoop.hbase.master.procedure.ServerRemoteProcedure implements org.apache.hadoop.hbase.master.procedure.ServerProcedureInterface {
  static final boolean $assertionsDisabled;

  public org.apache.hadoop.hbase.master.procedure.SwitchRpcThrottleRemoteProcedure();
    Code:
       0: aload_0
       1: invokespecial #1                  // Method org/apache/hadoop/hbase/master/procedure/ServerRemoteProcedure."<init>":()V
       4: return

  public org.apache.hadoop.hbase.master.procedure.SwitchRpcThrottleRemoteProcedure(org.apache.hadoop.hbase.ServerName, boolean);
    Code:
       0: aload_0
       1: invokespecial #1                  // Method org/apache/hadoop/hbase/master/procedure/ServerRemoteProcedure."<init>":()V
       4: aload_0
       5: aload_1
       6: putfield      #2                  // Field targetServer:Lorg/apache/hadoop/hbase/ServerName;
       9: aload_0
      10: iload_2
      11: putfield      #3                  // Field rpcThrottleEnabled:Z
      14: return

  protected void rollback(org.apache.hadoop.hbase.master.procedure.MasterProcedureEnv) throws java.io.IOException, java.lang.InterruptedException;
    Code:
       0: return

  protected boolean abort(org.apache.hadoop.hbase.master.procedure.MasterProcedureEnv);
    Code:
       0: iconst_0
       1: ireturn

  protected void serializeStateData(org.apache.hadoop.hbase.procedure2.ProcedureStateSerializer) throws java.io.IOException;
    Code:
       0: invokestatic  #4                  // Method org/apache/hadoop/hbase/shaded/protobuf/generated/MasterProcedureProtos$SwitchRpcThrottleRemoteStateData.newBuilder:()Lorg/apache/hadoop/hbase/shaded/protobuf/generated/MasterProcedureProtos$SwitchRpcThrottleRemoteStateData$Builder;
       3: aload_0
       4: getfield      #2                  // Field targetServer:Lorg/apache/hadoop/hbase/ServerName;
       7: invokestatic  #5                  // Method org/apache/hadoop/hbase/shaded/protobuf/ProtobufUtil.toServerName:(Lorg/apache/hadoop/hbase/ServerName;)Lorg/apache/hadoop/hbase/shaded/protobuf/generated/HBaseProtos$ServerName;
      10: invokevirtual #6                  // Method org/apache/hadoop/hbase/shaded/protobuf/generated/MasterProcedureProtos$SwitchRpcThrottleRemoteStateData$Builder.setTargetServer:(Lorg/apache/hadoop/hbase/shaded/protobuf/generated/HBaseProtos$ServerName;)Lorg/apache/hadoop/hbase/shaded/protobuf/generated/MasterProcedureProtos$SwitchRpcThrottleRemoteStateData$Builder;
      13: aload_0
      14: getfield      #3                  // Field rpcThrottleEnabled:Z
      17: invokevirtual #7                  // Method org/apache/hadoop/hbase/shaded/protobuf/generated/MasterProcedureProtos$SwitchRpcThrottleRemoteStateData$Builder.setRpcThrottleEnabled:(Z)Lorg/apache/hadoop/hbase/shaded/protobuf/generated/MasterProcedureProtos$SwitchRpcThrottleRemoteStateData$Builder;
      20: invokevirtual #8                  // Method org/apache/hadoop/hbase/shaded/protobuf/generated/MasterProcedureProtos$SwitchRpcThrottleRemoteStateData$Builder.build:()Lorg/apache/hadoop/hbase/shaded/protobuf/generated/MasterProcedureProtos$SwitchRpcThrottleRemoteStateData;
      23: pop
      24: return

  protected void deserializeStateData(org.apache.hadoop.hbase.procedure2.ProcedureStateSerializer) throws java.io.IOException;
    Code:
       0: aload_1
       1: ldc           #9                  // class org/apache/hadoop/hbase/shaded/protobuf/generated/MasterProcedureProtos$SwitchRpcThrottleRemoteStateData
       3: invokeinterface #10,  2           // InterfaceMethod org/apache/hadoop/hbase/procedure2/ProcedureStateSerializer.deserialize:(Ljava/lang/Class;)Lorg/apache/hbase/thirdparty/com/google/protobuf/Message;
       8: checkcast     #9                  // class org/apache/hadoop/hbase/shaded/protobuf/generated/MasterProcedureProtos$SwitchRpcThrottleRemoteStateData
      11: astore_2
      12: aload_0
      13: aload_2
      14: invokevirtual #11                 // Method org/apache/hadoop/hbase/shaded/protobuf/generated/MasterProcedureProtos$SwitchRpcThrottleRemoteStateData.getTargetServer:()Lorg/apache/hadoop/hbase/shaded/protobuf/generated/HBaseProtos$ServerName;
      17: invokestatic  #12                 // Method org/apache/hadoop/hbase/shaded/protobuf/ProtobufUtil.toServerName:(Lorg/apache/hadoop/hbase/shaded/protobuf/generated/HBaseProtos$ServerName;)Lorg/apache/hadoop/hbase/ServerName;
      20: putfield      #2                  // Field targetServer:Lorg/apache/hadoop/hbase/ServerName;
      23: aload_0
      24: aload_2
      25: invokevirtual #13                 // Method org/apache/hadoop/hbase/shaded/protobuf/generated/MasterProcedureProtos$SwitchRpcThrottleRemoteStateData.getRpcThrottleEnabled:()Z
      28: putfield      #3                  // Field rpcThrottleEnabled:Z
      31: return

  public java.util.Optional<org.apache.hadoop.hbase.procedure2.RemoteProcedureDispatcher$RemoteOperation> remoteCallBuild(org.apache.hadoop.hbase.master.procedure.MasterProcedureEnv, org.apache.hadoop.hbase.ServerName);
    Code:
       0: getstatic     #14                 // Field $assertionsDisabled:Z
       3: ifne          25
       6: aload_0
       7: getfield      #2                  // Field targetServer:Lorg/apache/hadoop/hbase/ServerName;
      10: aload_2
      11: invokevirtual #15                 // Method org/apache/hadoop/hbase/ServerName.equals:(Ljava/lang/Object;)Z
      14: ifne          25
      17: new           #16                 // class java/lang/AssertionError
      20: dup
      21: invokespecial #17                 // Method java/lang/AssertionError."<init>":()V
      24: athrow
      25: new           #18                 // class org/apache/hadoop/hbase/master/procedure/RSProcedureDispatcher$ServerOperation
      28: dup
      29: aload_0
      30: aload_0
      31: invokevirtual #19                 // Method getProcId:()J
      34: ldc           #20                 // class org/apache/hadoop/hbase/replication/regionserver/SwitchRpcThrottleRemoteCallable
      36: invokestatic  #4                  // Method org/apache/hadoop/hbase/shaded/protobuf/generated/MasterProcedureProtos$SwitchRpcThrottleRemoteStateData.newBuilder:()Lorg/apache/hadoop/hbase/shaded/protobuf/generated/MasterProcedureProtos$SwitchRpcThrottleRemoteStateData$Builder;
      39: aload_2
      40: invokestatic  #5                  // Method org/apache/hadoop/hbase/shaded/protobuf/ProtobufUtil.toServerName:(Lorg/apache/hadoop/hbase/ServerName;)Lorg/apache/hadoop/hbase/shaded/protobuf/generated/HBaseProtos$ServerName;
      43: invokevirtual #6                  // Method org/apache/hadoop/hbase/shaded/protobuf/generated/MasterProcedureProtos$SwitchRpcThrottleRemoteStateData$Builder.setTargetServer:(Lorg/apache/hadoop/hbase/shaded/protobuf/generated/HBaseProtos$ServerName;)Lorg/apache/hadoop/hbase/shaded/protobuf/generated/MasterProcedureProtos$SwitchRpcThrottleRemoteStateData$Builder;
      46: aload_0
      47: getfield      #3                  // Field rpcThrottleEnabled:Z
      50: invokevirtual #7                  // Method org/apache/hadoop/hbase/shaded/protobuf/generated/MasterProcedureProtos$SwitchRpcThrottleRemoteStateData$Builder.setRpcThrottleEnabled:(Z)Lorg/apache/hadoop/hbase/shaded/protobuf/generated/MasterProcedureProtos$SwitchRpcThrottleRemoteStateData$Builder;
      53: invokevirtual #8                  // Method org/apache/hadoop/hbase/shaded/protobuf/generated/MasterProcedureProtos$SwitchRpcThrottleRemoteStateData$Builder.build:()Lorg/apache/hadoop/hbase/shaded/protobuf/generated/MasterProcedureProtos$SwitchRpcThrottleRemoteStateData;
      56: invokevirtual #21                 // Method org/apache/hadoop/hbase/shaded/protobuf/generated/MasterProcedureProtos$SwitchRpcThrottleRemoteStateData.toByteArray:()[B
      59: invokespecial #22                 // Method org/apache/hadoop/hbase/master/procedure/RSProcedureDispatcher$ServerOperation."<init>":(Lorg/apache/hadoop/hbase/procedure2/RemoteProcedureDispatcher$RemoteProcedure;JLjava/lang/Class;[B)V
      62: invokestatic  #23                 // Method java/util/Optional.of:(Ljava/lang/Object;)Ljava/util/Optional;
      65: areturn

  public org.apache.hadoop.hbase.ServerName getServerName();
    Code:
       0: aload_0
       1: getfield      #2                  // Field targetServer:Lorg/apache/hadoop/hbase/ServerName;
       4: areturn

  public boolean hasMetaTableRegion();
    Code:
       0: iconst_0
       1: ireturn

  public org.apache.hadoop.hbase.master.procedure.ServerProcedureInterface$ServerOperationType getServerOperationType();
    Code:
       0: getstatic     #24                 // Field org/apache/hadoop/hbase/master/procedure/ServerProcedureInterface$ServerOperationType.SWITCH_RPC_THROTTLE:Lorg/apache/hadoop/hbase/master/procedure/ServerProcedureInterface$ServerOperationType;
       3: areturn

  protected void complete(org.apache.hadoop.hbase.master.procedure.MasterProcedureEnv, java.lang.Throwable);
    Code:
       0: aload_2
       1: ifnull        47
       4: getstatic     #25                 // Field LOG:Lorg/slf4j/Logger;
       7: ldc           #26                 // String Failed to switch rpc throttle to {} on server {}
       9: iconst_3
      10: anewarray     #27                 // class java/lang/Object
      13: dup
      14: iconst_0
      15: aload_0
      16: getfield      #3                  // Field rpcThrottleEnabled:Z
      19: invokestatic  #28                 // Method java/lang/Boolean.valueOf:(Z)Ljava/lang/Boolean;
      22: aastore
      23: dup
      24: iconst_1
      25: aload_0
      26: getfield      #2                  // Field targetServer:Lorg/apache/hadoop/hbase/ServerName;
      29: aastore
      30: dup
      31: iconst_2
      32: aload_2
      33: aastore
      34: invokeinterface #29,  3           // InterfaceMethod org/slf4j/Logger.warn:(Ljava/lang/String;[Ljava/lang/Object;)V
      39: aload_0
      40: iconst_0
      41: putfield      #30                 // Field succ:Z
      44: goto          52
      47: aload_0
      48: iconst_1
      49: putfield      #30                 // Field succ:Z
      52: return

  public void toStringClassDetails(java.lang.StringBuilder);
    Code:
       0: aload_1
       1: aload_0
       2: invokevirtual #31                 // Method java/lang/Object.getClass:()Ljava/lang/Class;
       5: invokevirtual #32                 // Method java/lang/Class.getSimpleName:()Ljava/lang/String;
       8: invokevirtual #33                 // Method java/lang/StringBuilder.append:(Ljava/lang/String;)Ljava/lang/StringBuilder;
      11: pop
      12: aload_1
      13: ldc           #34                 // String  server=
      15: invokevirtual #33                 // Method java/lang/StringBuilder.append:(Ljava/lang/String;)Ljava/lang/StringBuilder;
      18: pop
      19: aload_1
      20: aload_0
      21: getfield      #2                  // Field targetServer:Lorg/apache/hadoop/hbase/ServerName;
      24: invokevirtual #35                 // Method java/lang/StringBuilder.append:(Ljava/lang/Object;)Ljava/lang/StringBuilder;
      27: pop
      28: aload_1
      29: ldc           #36                 // String , rpcThrottleEnabled=
      31: invokevirtual #33                 // Method java/lang/StringBuilder.append:(Ljava/lang/String;)Ljava/lang/StringBuilder;
      34: pop
      35: aload_1
      36: aload_0
      37: getfield      #3                  // Field rpcThrottleEnabled:Z
      40: invokevirtual #37                 // Method java/lang/StringBuilder.append:(Z)Ljava/lang/StringBuilder;
      43: pop
      44: return

  public java.util.Optional remoteCallBuild(java.lang.Object, java.lang.Object);
    Code:
       0: aload_0
       1: aload_1
       2: checkcast     #38                 // class org/apache/hadoop/hbase/master/procedure/MasterProcedureEnv
       5: aload_2
       6: checkcast     #39                 // class org/apache/hadoop/hbase/ServerName
       9: invokevirtual #40                 // Method remoteCallBuild:(Lorg/apache/hadoop/hbase/master/procedure/MasterProcedureEnv;Lorg/apache/hadoop/hbase/ServerName;)Ljava/util/Optional;
      12: areturn

  protected boolean abort(java.lang.Object);
    Code:
       0: aload_0
       1: aload_1
       2: checkcast     #38                 // class org/apache/hadoop/hbase/master/procedure/MasterProcedureEnv
       5: invokevirtual #41                 // Method abort:(Lorg/apache/hadoop/hbase/master/procedure/MasterProcedureEnv;)Z
       8: ireturn

  protected void rollback(java.lang.Object) throws java.io.IOException, java.lang.InterruptedException;
    Code:
       0: aload_0
       1: aload_1
       2: checkcast     #38                 // class org/apache/hadoop/hbase/master/procedure/MasterProcedureEnv
       5: invokevirtual #42                 // Method rollback:(Lorg/apache/hadoop/hbase/master/procedure/MasterProcedureEnv;)V
       8: return

  static {};
    Code:
       0: ldc           #43                 // class org/apache/hadoop/hbase/master/procedure/SwitchRpcThrottleRemoteProcedure
       2: invokevirtual #44                 // Method java/lang/Class.desiredAssertionStatus:()Z
       5: ifne          12
       8: iconst_1
       9: goto          13
      12: iconst_0
      13: putstatic     #14                 // Field $assertionsDisabled:Z
      16: ldc           #43                 // class org/apache/hadoop/hbase/master/procedure/SwitchRpcThrottleRemoteProcedure
      18: invokestatic  #45                 // Method org/slf4j/LoggerFactory.getLogger:(Ljava/lang/Class;)Lorg/slf4j/Logger;
      21: putstatic     #25                 // Field LOG:Lorg/slf4j/Logger;
      24: return
}
