Compiled from "SwitchRpcThrottleProcedure.java"
class org.apache.hadoop.hbase.master.procedure.SwitchRpcThrottleProcedure$1 {
  static final int[] $SwitchMap$org$apache$hadoop$hbase$shaded$protobuf$generated$MasterProcedureProtos$SwitchRpcThrottleState;

  static {};
    Code:
       0: invokestatic  #1                  // Method org/apache/hadoop/hbase/shaded/protobuf/generated/MasterProcedureProtos$SwitchRpcThrottleState.values:()[Lorg/apache/hadoop/hbase/shaded/protobuf/generated/MasterProcedureProtos$SwitchRpcThrottleState;
       3: arraylength
       4: newarray       int
       6: putstatic     #2                  // Field $SwitchMap$org$apache$hadoop$hbase$shaded$protobuf$generated$MasterProcedureProtos$SwitchRpcThrottleState:[I
       9: getstatic     #2                  // Field $SwitchMap$org$apache$hadoop$hbase$shaded$protobuf$generated$MasterProcedureProtos$SwitchRpcThrottleState:[I
      12: getstatic     #3                  // Field org/apache/hadoop/hbase/shaded/protobuf/generated/MasterProcedureProtos$SwitchRpcThrottleState.UPDATE_SWITCH_RPC_THROTTLE_STORAGE:Lorg/apache/hadoop/hbase/shaded/protobuf/generated/MasterProcedureProtos$SwitchRpcThrottleState;
      15: invokevirtual #4                  // Method org/apache/hadoop/hbase/shaded/protobuf/generated/MasterProcedureProtos$SwitchRpcThrottleState.ordinal:()I
      18: iconst_1
      19: iastore
      20: goto          24
      23: astore_0
      24: getstatic     #2                  // Field $SwitchMap$org$apache$hadoop$hbase$shaded$protobuf$generated$MasterProcedureProtos$SwitchRpcThrottleState:[I
      27: getstatic     #6                  // Field org/apache/hadoop/hbase/shaded/protobuf/generated/MasterProcedureProtos$SwitchRpcThrottleState.SWITCH_RPC_THROTTLE_ON_RS:Lorg/apache/hadoop/hbase/shaded/protobuf/generated/MasterProcedureProtos$SwitchRpcThrottleState;
      30: invokevirtual #4                  // Method org/apache/hadoop/hbase/shaded/protobuf/generated/MasterProcedureProtos$SwitchRpcThrottleState.ordinal:()I
      33: iconst_2
      34: iastore
      35: goto          39
      38: astore_0
      39: getstatic     #2                  // Field $SwitchMap$org$apache$hadoop$hbase$shaded$protobuf$generated$MasterProcedureProtos$SwitchRpcThrottleState:[I
      42: getstatic     #7                  // Field org/apache/hadoop/hbase/shaded/protobuf/generated/MasterProcedureProtos$SwitchRpcThrottleState.POST_SWITCH_RPC_THROTTLE:Lorg/apache/hadoop/hbase/shaded/protobuf/generated/MasterProcedureProtos$SwitchRpcThrottleState;
      45: invokevirtual #4                  // Method org/apache/hadoop/hbase/shaded/protobuf/generated/MasterProcedureProtos$SwitchRpcThrottleState.ordinal:()I
      48: iconst_3
      49: iastore
      50: goto          54
      53: astore_0
      54: return
    Exception table:
       from    to  target type
           9    20    23   Class java/lang/NoSuchFieldError
          24    35    38   Class java/lang/NoSuchFieldError
          39    50    53   Class java/lang/NoSuchFieldError
}
