Compiled from "SyncReplicationTestBase.java"
class org.apache.hadoop.hbase.replication.SyncReplicationTestBase$2 implements org.apache.hadoop.hbase.Waiter$ExplainingPredicate<java.lang.Exception> {
  final org.apache.hadoop.hbase.master.MasterFileSystem val$mfs;

  final org.apache.hadoop.fs.Path val$remoteWAL;

  final org.apache.hadoop.hbase.replication.SyncReplicationTestBase this$0;

  org.apache.hadoop.hbase.replication.SyncReplicationTestBase$2(org.apache.hadoop.hbase.replication.SyncReplicationTestBase, org.apache.hadoop.hbase.master.MasterFileSystem, org.apache.hadoop.fs.Path);
    Code:
       0: aload_0
       1: aload_1
       2: putfield      #1                  // Field this$0:Lorg/apache/hadoop/hbase/replication/SyncReplicationTestBase;
       5: aload_0
       6: aload_2
       7: putfield      #2                  // Field val$mfs:Lorg/apache/hadoop/hbase/master/MasterFileSystem;
      10: aload_0
      11: aload_3
      12: putfield      #3                  // Field val$remoteWAL:Lorg/apache/hadoop/fs/Path;
      15: aload_0
      16: invokespecial #4                  // Method java/lang/Object."<init>":()V
      19: return

  public boolean evaluate() throws java.lang.Exception;
    Code:
       0: aload_0
       1: getfield      #2                  // Field val$mfs:Lorg/apache/hadoop/hbase/master/MasterFileSystem;
       4: invokevirtual #5                  // Method org/apache/hadoop/hbase/master/MasterFileSystem.getWALFileSystem:()Lorg/apache/hadoop/fs/FileSystem;
       7: aload_0
       8: getfield      #3                  // Field val$remoteWAL:Lorg/apache/hadoop/fs/Path;
      11: invokevirtual #6                  // Method org/apache/hadoop/fs/FileSystem.exists:(Lorg/apache/hadoop/fs/Path;)Z
      14: ifne          21
      17: iconst_1
      18: goto          22
      21: iconst_0
      22: ireturn

  public java.lang.String explainFailure() throws java.lang.Exception;
    Code:
       0: new           #7                  // class java/lang/StringBuilder
       3: dup
       4: invokespecial #8                  // Method java/lang/StringBuilder."<init>":()V
       7: aload_0
       8: getfield      #3                  // Field val$remoteWAL:Lorg/apache/hadoop/fs/Path;
      11: invokevirtual #9                  // Method java/lang/StringBuilder.append:(Ljava/lang/Object;)Ljava/lang/StringBuilder;
      14: ldc           #10                 // String  has not been deleted yet
      16: invokevirtual #11                 // Method java/lang/StringBuilder.append:(Ljava/lang/String;)Ljava/lang/StringBuilder;
      19: invokevirtual #12                 // Method java/lang/StringBuilder.toString:()Ljava/lang/String;
      22: areturn
}
