Compiled from "SyncReplicationReplayWALProcedure.java"
public class org.apache.hadoop.hbase.master.replication.SyncReplicationReplayWALProcedure extends org.apache.hadoop.hbase.master.replication.AbstractPeerNoLockProcedure<org.apache.hadoop.hbase.shaded.protobuf.generated.MasterProcedureProtos$SyncReplicationReplayWALState> {
  public org.apache.hadoop.hbase.master.replication.SyncReplicationReplayWALProcedure();
    Code:
       0: aload_0
       1: invokespecial #1                  // Method org/apache/hadoop/hbase/master/replication/AbstractPeerNoLockProcedure."<init>":()V
       4: aload_0
       5: aconst_null
       6: putfield      #2                  // Field worker:Lorg/apache/hadoop/hbase/ServerName;
       9: return

  public org.apache.hadoop.hbase.master.replication.SyncReplicationReplayWALProcedure(java.lang.String, java.util.List<java.lang.String>);
    Code:
       0: aload_0
       1: invokespecial #1                  // Method org/apache/hadoop/hbase/master/replication/AbstractPeerNoLockProcedure."<init>":()V
       4: aload_0
       5: aconst_null
       6: putfield      #2                  // Field worker:Lorg/apache/hadoop/hbase/ServerName;
       9: aload_0
      10: aload_1
      11: putfield      #3                  // Field peerId:Ljava/lang/String;
      14: aload_0
      15: aload_2
      16: putfield      #4                  // Field wals:Ljava/util/List;
      19: return

  protected org.apache.hadoop.hbase.procedure2.StateMachineProcedure$Flow executeFromState(org.apache.hadoop.hbase.master.procedure.MasterProcedureEnv, org.apache.hadoop.hbase.shaded.protobuf.generated.MasterProcedureProtos$SyncReplicationReplayWALState) throws org.apache.hadoop.hbase.procedure2.ProcedureSuspendedException;
    Code:
       0: aload_1
       1: invokevirtual #5                  // Method org/apache/hadoop/hbase/master/procedure/MasterProcedureEnv.getMasterServices:()Lorg/apache/hadoop/hbase/master/MasterServices;
       4: invokeinterface #6,  1            // InterfaceMethod org/apache/hadoop/hbase/master/MasterServices.getSyncReplicationReplayWALManager:()Lorg/apache/hadoop/hbase/master/replication/SyncReplicationReplayWALManager;
       9: astore_3
      10: getstatic     #7                  // Field org/apache/hadoop/hbase/master/replication/SyncReplicationReplayWALProcedure$1.$SwitchMap$org$apache$hadoop$hbase$shaded$protobuf$generated$MasterProcedureProtos$SyncReplicationReplayWALState:[I
      13: aload_2
      14: invokevirtual #8                  // Method org/apache/hadoop/hbase/shaded/protobuf/generated/MasterProcedureProtos$SyncReplicationReplayWALState.ordinal:()I
      17: iaload
      18: tableswitch   { // 1 to 3
                     1: 44
                     2: 68
                     3: 109
               default: 207
          }
      44: aload_0
      45: aload_3
      46: aload_0
      47: getfield      #3                  // Field peerId:Ljava/lang/String;
      50: aload_0
      51: invokevirtual #9                  // Method org/apache/hadoop/hbase/master/replication/SyncReplicationReplayWALManager.acquirePeerWorker:(Ljava/lang/String;Lorg/apache/hadoop/hbase/procedure2/Procedure;)Lorg/apache/hadoop/hbase/ServerName;
      54: putfield      #2                  // Field worker:Lorg/apache/hadoop/hbase/ServerName;
      57: aload_0
      58: getstatic     #10                 // Field org/apache/hadoop/hbase/shaded/protobuf/generated/MasterProcedureProtos$SyncReplicationReplayWALState.DISPATCH_WALS_TO_WORKER:Lorg/apache/hadoop/hbase/shaded/protobuf/generated/MasterProcedureProtos$SyncReplicationReplayWALState;
      61: invokevirtual #11                 // Method setNextState:(Ljava/lang/Object;)V
      64: getstatic     #12                 // Field org/apache/hadoop/hbase/procedure2/StateMachineProcedure$Flow.HAS_MORE_STATE:Lorg/apache/hadoop/hbase/procedure2/StateMachineProcedure$Flow;
      67: areturn
      68: aload_0
      69: iconst_1
      70: anewarray     #13                 // class org/apache/hadoop/hbase/master/replication/SyncReplicationReplayWALRemoteProcedure
      73: dup
      74: iconst_0
      75: new           #13                 // class org/apache/hadoop/hbase/master/replication/SyncReplicationReplayWALRemoteProcedure
      78: dup
      79: aload_0
      80: getfield      #3                  // Field peerId:Ljava/lang/String;
      83: aload_0
      84: getfield      #4                  // Field wals:Ljava/util/List;
      87: aload_0
      88: getfield      #2                  // Field worker:Lorg/apache/hadoop/hbase/ServerName;
      91: invokespecial #14                 // Method org/apache/hadoop/hbase/master/replication/SyncReplicationReplayWALRemoteProcedure."<init>":(Ljava/lang/String;Ljava/util/List;Lorg/apache/hadoop/hbase/ServerName;)V
      94: aastore
      95: invokevirtual #15                 // Method addChildProcedure:([Lorg/apache/hadoop/hbase/procedure2/Procedure;)V
      98: aload_0
      99: getstatic     #16                 // Field org/apache/hadoop/hbase/shaded/protobuf/generated/MasterProcedureProtos$SyncReplicationReplayWALState.RELEASE_WORKER:Lorg/apache/hadoop/hbase/shaded/protobuf/generated/MasterProcedureProtos$SyncReplicationReplayWALState;
     102: invokevirtual #11                 // Method setNextState:(Ljava/lang/Object;)V
     105: getstatic     #12                 // Field org/apache/hadoop/hbase/procedure2/StateMachineProcedure$Flow.HAS_MORE_STATE:Lorg/apache/hadoop/hbase/procedure2/StateMachineProcedure$Flow;
     108: areturn
     109: iconst_0
     110: istore        4
     112: aload_3
     113: aload_0
     114: getfield      #4                  // Field wals:Ljava/util/List;
     117: iconst_0
     118: invokeinterface #17,  2           // InterfaceMethod java/util/List.get:(I)Ljava/lang/Object;
     123: checkcast     #18                 // class java/lang/String
     126: invokevirtual #19                 // Method org/apache/hadoop/hbase/master/replication/SyncReplicationReplayWALManager.isReplayWALFinished:(Ljava/lang/String;)Z
     129: istore        4
     131: goto          153
     134: astore        5
     136: aload_0
     137: aload_1
     138: invokevirtual #21                 // Method org/apache/hadoop/hbase/master/procedure/MasterProcedureEnv.getMasterConfiguration:()Lorg/apache/hadoop/conf/Configuration;
     141: aload_0
     142: aload         5
     144: invokedynamic #22,  0             // InvokeDynamic #0:accept:(Lorg/apache/hadoop/hbase/master/replication/SyncReplicationReplayWALProcedure;Ljava/io/IOException;)Ljava/util/function/LongConsumer;
     149: invokevirtual #23                 // Method suspend:(Lorg/apache/hadoop/conf/Configuration;Ljava/util/function/LongConsumer;)Lorg/apache/hadoop/hbase/procedure2/ProcedureSuspendedException;
     152: athrow
     153: aload_3
     154: aload_0
     155: getfield      #3                  // Field peerId:Ljava/lang/String;
     158: aload_0
     159: getfield      #2                  // Field worker:Lorg/apache/hadoop/hbase/ServerName;
     162: aload_1
     163: invokevirtual #24                 // Method org/apache/hadoop/hbase/master/procedure/MasterProcedureEnv.getProcedureScheduler:()Lorg/apache/hadoop/hbase/master/procedure/MasterProcedureScheduler;
     166: invokevirtual #25                 // Method org/apache/hadoop/hbase/master/replication/SyncReplicationReplayWALManager.releasePeerWorker:(Ljava/lang/String;Lorg/apache/hadoop/hbase/ServerName;Lorg/apache/hadoop/hbase/master/procedure/MasterProcedureScheduler;)V
     169: iload         4
     171: ifne          203
     174: getstatic     #26                 // Field LOG:Lorg/slf4j/Logger;
     177: ldc           #27                 // String Failed to replay wals {} for peer id={}, retry
     179: aload_0
     180: getfield      #4                  // Field wals:Ljava/util/List;
     183: aload_0
     184: getfield      #3                  // Field peerId:Ljava/lang/String;
     187: invokeinterface #28,  4           // InterfaceMethod org/slf4j/Logger.warn:(Ljava/lang/String;Ljava/lang/Object;Ljava/lang/Object;)V
     192: aload_0
     193: getstatic     #29                 // Field org/apache/hadoop/hbase/shaded/protobuf/generated/MasterProcedureProtos$SyncReplicationReplayWALState.ASSIGN_WORKER:Lorg/apache/hadoop/hbase/shaded/protobuf/generated/MasterProcedureProtos$SyncReplicationReplayWALState;
     196: invokevirtual #11                 // Method setNextState:(Ljava/lang/Object;)V
     199: getstatic     #12                 // Field org/apache/hadoop/hbase/procedure2/StateMachineProcedure$Flow.HAS_MORE_STATE:Lorg/apache/hadoop/hbase/procedure2/StateMachineProcedure$Flow;
     202: areturn
     203: getstatic     #30                 // Field org/apache/hadoop/hbase/procedure2/StateMachineProcedure$Flow.NO_MORE_STATE:Lorg/apache/hadoop/hbase/procedure2/StateMachineProcedure$Flow;
     206: areturn
     207: new           #31                 // class java/lang/UnsupportedOperationException
     210: dup
     211: new           #32                 // class java/lang/StringBuilder
     214: dup
     215: invokespecial #33                 // Method java/lang/StringBuilder."<init>":()V
     218: ldc           #34                 // String unhandled state=
     220: invokevirtual #35                 // Method java/lang/StringBuilder.append:(Ljava/lang/String;)Ljava/lang/StringBuilder;
     223: aload_2
     224: invokevirtual #36                 // Method java/lang/StringBuilder.append:(Ljava/lang/Object;)Ljava/lang/StringBuilder;
     227: invokevirtual #37                 // Method java/lang/StringBuilder.toString:()Ljava/lang/String;
     230: invokespecial #38                 // Method java/lang/UnsupportedOperationException."<init>":(Ljava/lang/String;)V
     233: athrow
    Exception table:
       from    to  target type
         112   131   134   Class java/io/IOException

  protected void rollbackState(org.apache.hadoop.hbase.master.procedure.MasterProcedureEnv, org.apache.hadoop.hbase.shaded.protobuf.generated.MasterProcedureProtos$SyncReplicationReplayWALState) throws java.io.IOException, java.lang.InterruptedException;
    Code:
       0: aload_2
       1: aload_0
       2: invokevirtual #39                 // Method getInitialState:()Lorg/apache/hadoop/hbase/shaded/protobuf/generated/MasterProcedureProtos$SyncReplicationReplayWALState;
       5: if_acmpne     9
       8: return
       9: new           #31                 // class java/lang/UnsupportedOperationException
      12: dup
      13: invokespecial #40                 // Method java/lang/UnsupportedOperationException."<init>":()V
      16: athrow

  protected org.apache.hadoop.hbase.shaded.protobuf.generated.MasterProcedureProtos$SyncReplicationReplayWALState getState(int);
    Code:
       0: iload_1
       1: invokestatic  #41                 // Method org/apache/hadoop/hbase/shaded/protobuf/generated/MasterProcedureProtos$SyncReplicationReplayWALState.forNumber:(I)Lorg/apache/hadoop/hbase/shaded/protobuf/generated/MasterProcedureProtos$SyncReplicationReplayWALState;
       4: areturn

  protected int getStateId(org.apache.hadoop.hbase.shaded.protobuf.generated.MasterProcedureProtos$SyncReplicationReplayWALState);
    Code:
       0: aload_1
       1: invokevirtual #42                 // Method org/apache/hadoop/hbase/shaded/protobuf/generated/MasterProcedureProtos$SyncReplicationReplayWALState.getNumber:()I
       4: ireturn

  protected org.apache.hadoop.hbase.shaded.protobuf.generated.MasterProcedureProtos$SyncReplicationReplayWALState getInitialState();
    Code:
       0: getstatic     #29                 // Field org/apache/hadoop/hbase/shaded/protobuf/generated/MasterProcedureProtos$SyncReplicationReplayWALState.ASSIGN_WORKER:Lorg/apache/hadoop/hbase/shaded/protobuf/generated/MasterProcedureProtos$SyncReplicationReplayWALState;
       3: areturn

  protected void serializeStateData(org.apache.hadoop.hbase.procedure2.ProcedureStateSerializer) throws java.io.IOException;
    Code:
       0: aload_0
       1: aload_1
       2: invokespecial #43                 // Method org/apache/hadoop/hbase/master/replication/AbstractPeerNoLockProcedure.serializeStateData:(Lorg/apache/hadoop/hbase/procedure2/ProcedureStateSerializer;)V
       5: invokestatic  #44                 // Method org/apache/hadoop/hbase/shaded/protobuf/generated/MasterProcedureProtos$SyncReplicationReplayWALStateData.newBuilder:()Lorg/apache/hadoop/hbase/shaded/protobuf/generated/MasterProcedureProtos$SyncReplicationReplayWALStateData$Builder;
       8: aload_0
       9: getfield      #3                  // Field peerId:Ljava/lang/String;
      12: invokevirtual #45                 // Method org/apache/hadoop/hbase/shaded/protobuf/generated/MasterProcedureProtos$SyncReplicationReplayWALStateData$Builder.setPeerId:(Ljava/lang/String;)Lorg/apache/hadoop/hbase/shaded/protobuf/generated/MasterProcedureProtos$SyncReplicationReplayWALStateData$Builder;
      15: aload_0
      16: getfield      #4                  // Field wals:Ljava/util/List;
      19: invokevirtual #46                 // Method org/apache/hadoop/hbase/shaded/protobuf/generated/MasterProcedureProtos$SyncReplicationReplayWALStateData$Builder.addAllWal:(Ljava/lang/Iterable;)Lorg/apache/hadoop/hbase/shaded/protobuf/generated/MasterProcedureProtos$SyncReplicationReplayWALStateData$Builder;
      22: astore_2
      23: aload_0
      24: getfield      #2                  // Field worker:Lorg/apache/hadoop/hbase/ServerName;
      27: ifnull        42
      30: aload_2
      31: aload_0
      32: getfield      #2                  // Field worker:Lorg/apache/hadoop/hbase/ServerName;
      35: invokestatic  #47                 // Method org/apache/hadoop/hbase/shaded/protobuf/ProtobufUtil.toServerName:(Lorg/apache/hadoop/hbase/ServerName;)Lorg/apache/hadoop/hbase/shaded/protobuf/generated/HBaseProtos$ServerName;
      38: invokevirtual #48                 // Method org/apache/hadoop/hbase/shaded/protobuf/generated/MasterProcedureProtos$SyncReplicationReplayWALStateData$Builder.setWorker:(Lorg/apache/hadoop/hbase/shaded/protobuf/generated/HBaseProtos$ServerName;)Lorg/apache/hadoop/hbase/shaded/protobuf/generated/MasterProcedureProtos$SyncReplicationReplayWALStateData$Builder;
      41: pop
      42: aload_1
      43: aload_2
      44: invokevirtual #49                 // Method org/apache/hadoop/hbase/shaded/protobuf/generated/MasterProcedureProtos$SyncReplicationReplayWALStateData$Builder.build:()Lorg/apache/hadoop/hbase/shaded/protobuf/generated/MasterProcedureProtos$SyncReplicationReplayWALStateData;
      47: invokeinterface #50,  2           // InterfaceMethod org/apache/hadoop/hbase/procedure2/ProcedureStateSerializer.serialize:(Lorg/apache/hbase/thirdparty/com/google/protobuf/Message;)V
      52: return

  protected void deserializeStateData(org.apache.hadoop.hbase.procedure2.ProcedureStateSerializer) throws java.io.IOException;
    Code:
       0: aload_0
       1: aload_1
       2: invokespecial #51                 // Method org/apache/hadoop/hbase/master/replication/AbstractPeerNoLockProcedure.deserializeStateData:(Lorg/apache/hadoop/hbase/procedure2/ProcedureStateSerializer;)V
       5: aload_1
       6: ldc           #52                 // class org/apache/hadoop/hbase/shaded/protobuf/generated/MasterProcedureProtos$SyncReplicationReplayWALStateData
       8: invokeinterface #53,  2           // InterfaceMethod org/apache/hadoop/hbase/procedure2/ProcedureStateSerializer.deserialize:(Ljava/lang/Class;)Lorg/apache/hbase/thirdparty/com/google/protobuf/Message;
      13: checkcast     #52                 // class org/apache/hadoop/hbase/shaded/protobuf/generated/MasterProcedureProtos$SyncReplicationReplayWALStateData
      16: astore_2
      17: aload_0
      18: aload_2
      19: invokevirtual #54                 // Method org/apache/hadoop/hbase/shaded/protobuf/generated/MasterProcedureProtos$SyncReplicationReplayWALStateData.getPeerId:()Ljava/lang/String;
      22: putfield      #3                  // Field peerId:Ljava/lang/String;
      25: aload_0
      26: aload_2
      27: invokevirtual #55                 // Method org/apache/hadoop/hbase/shaded/protobuf/generated/MasterProcedureProtos$SyncReplicationReplayWALStateData.getWalList:()Lorg/apache/hbase/thirdparty/com/google/protobuf/ProtocolStringList;
      30: putfield      #4                  // Field wals:Ljava/util/List;
      33: aload_2
      34: invokevirtual #56                 // Method org/apache/hadoop/hbase/shaded/protobuf/generated/MasterProcedureProtos$SyncReplicationReplayWALStateData.hasWorker:()Z
      37: ifeq          51
      40: aload_0
      41: aload_2
      42: invokevirtual #57                 // Method org/apache/hadoop/hbase/shaded/protobuf/generated/MasterProcedureProtos$SyncReplicationReplayWALStateData.getWorker:()Lorg/apache/hadoop/hbase/shaded/protobuf/generated/HBaseProtos$ServerName;
      45: invokestatic  #58                 // Method org/apache/hadoop/hbase/shaded/protobuf/ProtobufUtil.toServerName:(Lorg/apache/hadoop/hbase/shaded/protobuf/generated/HBaseProtos$ServerName;)Lorg/apache/hadoop/hbase/ServerName;
      48: putfield      #2                  // Field worker:Lorg/apache/hadoop/hbase/ServerName;
      51: return

  public org.apache.hadoop.hbase.master.procedure.PeerProcedureInterface$PeerOperationType getPeerOperationType();
    Code:
       0: getstatic     #59                 // Field org/apache/hadoop/hbase/master/procedure/PeerProcedureInterface$PeerOperationType.SYNC_REPLICATION_REPLAY_WAL:Lorg/apache/hadoop/hbase/master/procedure/PeerProcedureInterface$PeerOperationType;
       3: areturn

  protected void afterReplay(org.apache.hadoop.hbase.master.procedure.MasterProcedureEnv);
    Code:
       0: aload_0
       1: getfield      #2                  // Field worker:Lorg/apache/hadoop/hbase/ServerName;
       4: ifnull        34
       7: aload_0
       8: invokevirtual #60                 // Method isFinished:()Z
      11: ifne          34
      14: aload_1
      15: invokevirtual #5                  // Method org/apache/hadoop/hbase/master/procedure/MasterProcedureEnv.getMasterServices:()Lorg/apache/hadoop/hbase/master/MasterServices;
      18: invokeinterface #6,  1            // InterfaceMethod org/apache/hadoop/hbase/master/MasterServices.getSyncReplicationReplayWALManager:()Lorg/apache/hadoop/hbase/master/replication/SyncReplicationReplayWALManager;
      23: aload_0
      24: getfield      #3                  // Field peerId:Ljava/lang/String;
      27: aload_0
      28: getfield      #2                  // Field worker:Lorg/apache/hadoop/hbase/ServerName;
      31: invokevirtual #61                 // Method org/apache/hadoop/hbase/master/replication/SyncReplicationReplayWALManager.addUsedPeerWorker:(Ljava/lang/String;Lorg/apache/hadoop/hbase/ServerName;)V
      34: return

  protected void rollbackState(org.apache.hadoop.hbase.master.procedure.MasterProcedureEnv, java.lang.Object) throws java.io.IOException, java.lang.InterruptedException;
    Code:
       0: aload_0
       1: aload_1
       2: aload_2
       3: checkcast     #62                 // class org/apache/hadoop/hbase/shaded/protobuf/generated/MasterProcedureProtos$SyncReplicationReplayWALState
       6: invokevirtual #63                 // Method rollbackState:(Lorg/apache/hadoop/hbase/master/procedure/MasterProcedureEnv;Lorg/apache/hadoop/hbase/shaded/protobuf/generated/MasterProcedureProtos$SyncReplicationReplayWALState;)V
       9: return

  protected java.lang.Object getInitialState();
    Code:
       0: aload_0
       1: invokevirtual #39                 // Method getInitialState:()Lorg/apache/hadoop/hbase/shaded/protobuf/generated/MasterProcedureProtos$SyncReplicationReplayWALState;
       4: areturn

  protected int getStateId(java.lang.Object);
    Code:
       0: aload_0
       1: aload_1
       2: checkcast     #62                 // class org/apache/hadoop/hbase/shaded/protobuf/generated/MasterProcedureProtos$SyncReplicationReplayWALState
       5: invokevirtual #64                 // Method getStateId:(Lorg/apache/hadoop/hbase/shaded/protobuf/generated/MasterProcedureProtos$SyncReplicationReplayWALState;)I
       8: ireturn

  protected java.lang.Object getState(int);
    Code:
       0: aload_0
       1: iload_1
       2: invokevirtual #65                 // Method getState:(I)Lorg/apache/hadoop/hbase/shaded/protobuf/generated/MasterProcedureProtos$SyncReplicationReplayWALState;
       5: areturn

  protected void rollbackState(java.lang.Object, java.lang.Object) throws java.io.IOException, java.lang.InterruptedException;
    Code:
       0: aload_0
       1: aload_1
       2: checkcast     #66                 // class org/apache/hadoop/hbase/master/procedure/MasterProcedureEnv
       5: aload_2
       6: checkcast     #62                 // class org/apache/hadoop/hbase/shaded/protobuf/generated/MasterProcedureProtos$SyncReplicationReplayWALState
       9: invokevirtual #63                 // Method rollbackState:(Lorg/apache/hadoop/hbase/master/procedure/MasterProcedureEnv;Lorg/apache/hadoop/hbase/shaded/protobuf/generated/MasterProcedureProtos$SyncReplicationReplayWALState;)V
      12: return

  protected org.apache.hadoop.hbase.procedure2.StateMachineProcedure$Flow executeFromState(java.lang.Object, java.lang.Object) throws org.apache.hadoop.hbase.procedure2.ProcedureSuspendedException, org.apache.hadoop.hbase.procedure2.ProcedureYieldException, java.lang.InterruptedException;
    Code:
       0: aload_0
       1: aload_1
       2: checkcast     #66                 // class org/apache/hadoop/hbase/master/procedure/MasterProcedureEnv
       5: aload_2
       6: checkcast     #62                 // class org/apache/hadoop/hbase/shaded/protobuf/generated/MasterProcedureProtos$SyncReplicationReplayWALState
       9: invokevirtual #67                 // Method executeFromState:(Lorg/apache/hadoop/hbase/master/procedure/MasterProcedureEnv;Lorg/apache/hadoop/hbase/shaded/protobuf/generated/MasterProcedureProtos$SyncReplicationReplayWALState;)Lorg/apache/hadoop/hbase/procedure2/StateMachineProcedure$Flow;
      12: areturn

  protected void afterReplay(java.lang.Object);
    Code:
       0: aload_0
       1: aload_1
       2: checkcast     #66                 // class org/apache/hadoop/hbase/master/procedure/MasterProcedureEnv
       5: invokevirtual #68                 // Method afterReplay:(Lorg/apache/hadoop/hbase/master/procedure/MasterProcedureEnv;)V
       8: return

  static {};
    Code:
       0: ldc           #75                 // class org/apache/hadoop/hbase/master/replication/SyncReplicationReplayWALProcedure
       2: invokestatic  #76                 // Method org/slf4j/LoggerFactory.getLogger:(Ljava/lang/Class;)Lorg/slf4j/Logger;
       5: putstatic     #26                 // Field LOG:Lorg/slf4j/Logger;
       8: return
}
