Compiled from "SyncReplicationState.java"
public final class org.apache.hadoop.hbase.replication.SyncReplicationState extends java.lang.Enum<org.apache.hadoop.hbase.replication.SyncReplicationState> {
  public static final org.apache.hadoop.hbase.replication.SyncReplicationState NONE;

  public static final org.apache.hadoop.hbase.replication.SyncReplicationState ACTIVE;

  public static final org.apache.hadoop.hbase.replication.SyncReplicationState DOWNGRADE_ACTIVE;

  public static final org.apache.hadoop.hbase.replication.SyncReplicationState STANDBY;

  public static org.apache.hadoop.hbase.replication.SyncReplicationState[] values();
    Code:
       0: getstatic     #1                  // Field $VALUES:[Lorg/apache/hadoop/hbase/replication/SyncReplicationState;
       3: invokevirtual #2                  // Method "[Lorg/apache/hadoop/hbase/replication/SyncReplicationState;".clone:()Ljava/lang/Object;
       6: checkcast     #3                  // class "[Lorg/apache/hadoop/hbase/replication/SyncReplicationState;"
       9: areturn

  public static org.apache.hadoop.hbase.replication.SyncReplicationState valueOf(java.lang.String);
    Code:
       0: ldc           #4                  // class org/apache/hadoop/hbase/replication/SyncReplicationState
       2: aload_0
       3: invokestatic  #5                  // Method java/lang/Enum.valueOf:(Ljava/lang/Class;Ljava/lang/String;)Ljava/lang/Enum;
       6: checkcast     #4                  // class org/apache/hadoop/hbase/replication/SyncReplicationState
       9: areturn

  public static org.apache.hadoop.hbase.replication.SyncReplicationState valueOf(int);
    Code:
       0: iload_0
       1: tableswitch   { // 0 to 3
                     0: 32
                     1: 36
                     2: 40
                     3: 44
               default: 48
          }
      32: getstatic     #8                  // Field NONE:Lorg/apache/hadoop/hbase/replication/SyncReplicationState;
      35: areturn
      36: getstatic     #9                  // Field ACTIVE:Lorg/apache/hadoop/hbase/replication/SyncReplicationState;
      39: areturn
      40: getstatic     #10                 // Field DOWNGRADE_ACTIVE:Lorg/apache/hadoop/hbase/replication/SyncReplicationState;
      43: areturn
      44: getstatic     #11                 // Field STANDBY:Lorg/apache/hadoop/hbase/replication/SyncReplicationState;
      47: areturn
      48: new           #12                 // class java/lang/IllegalArgumentException
      51: dup
      52: new           #13                 // class java/lang/StringBuilder
      55: dup
      56: invokespecial #14                 // Method java/lang/StringBuilder."<init>":()V
      59: ldc           #15                 // String Unknown synchronous replication state
      61: invokevirtual #16                 // Method java/lang/StringBuilder.append:(Ljava/lang/String;)Ljava/lang/StringBuilder;
      64: iload_0
      65: invokevirtual #17                 // Method java/lang/StringBuilder.append:(I)Ljava/lang/StringBuilder;
      68: invokevirtual #18                 // Method java/lang/StringBuilder.toString:()Ljava/lang/String;
      71: invokespecial #19                 // Method java/lang/IllegalArgumentException."<init>":(Ljava/lang/String;)V
      74: athrow

  public int value();
    Code:
       0: aload_0
       1: getfield      #7                  // Field value:B
       4: sipush        255
       7: iand
       8: ireturn

  public static byte[] toByteArray(org.apache.hadoop.hbase.replication.SyncReplicationState);
    Code:
       0: aload_0
       1: invokestatic  #20                 // Method org/apache/hadoop/hbase/client/replication/ReplicationPeerConfigUtil.toSyncReplicationState:(Lorg/apache/hadoop/hbase/replication/SyncReplicationState;)Lorg/apache/hadoop/hbase/shaded/protobuf/generated/ReplicationProtos$SyncReplicationState;
       4: invokevirtual #21                 // Method org/apache/hadoop/hbase/shaded/protobuf/generated/ReplicationProtos$SyncReplicationState.toByteArray:()[B
       7: invokestatic  #22                 // Method org/apache/hadoop/hbase/shaded/protobuf/ProtobufUtil.prependPBMagic:([B)[B
      10: areturn

  public static org.apache.hadoop.hbase.replication.SyncReplicationState parseFrom(byte[]) throws org.apache.hbase.thirdparty.com.google.protobuf.InvalidProtocolBufferException;
    Code:
       0: aload_0
       1: invokestatic  #23                 // Method org/apache/hadoop/hbase/shaded/protobuf/ProtobufUtil.lengthOfPBMagic:()I
       4: aload_0
       5: arraylength
       6: invokestatic  #24                 // Method java/util/Arrays.copyOfRange:([BII)[B
       9: invokestatic  #25                 // Method org/apache/hadoop/hbase/shaded/protobuf/generated/ReplicationProtos$SyncReplicationState.parseFrom:([B)Lorg/apache/hadoop/hbase/shaded/protobuf/generated/ReplicationProtos$SyncReplicationState;
      12: invokestatic  #26                 // Method org/apache/hadoop/hbase/client/replication/ReplicationPeerConfigUtil.toSyncReplicationState:(Lorg/apache/hadoop/hbase/shaded/protobuf/generated/ReplicationProtos$SyncReplicationState;)Lorg/apache/hadoop/hbase/replication/SyncReplicationState;
      15: areturn

  static {};
    Code:
       0: new           #4                  // class org/apache/hadoop/hbase/replication/SyncReplicationState
       3: dup
       4: ldc           #27                 // String NONE
       6: iconst_0
       7: iconst_0
       8: invokespecial #28                 // Method "<init>":(Ljava/lang/String;II)V
      11: putstatic     #8                  // Field NONE:Lorg/apache/hadoop/hbase/replication/SyncReplicationState;
      14: new           #4                  // class org/apache/hadoop/hbase/replication/SyncReplicationState
      17: dup
      18: ldc           #29                 // String ACTIVE
      20: iconst_1
      21: iconst_1
      22: invokespecial #28                 // Method "<init>":(Ljava/lang/String;II)V
      25: putstatic     #9                  // Field ACTIVE:Lorg/apache/hadoop/hbase/replication/SyncReplicationState;
      28: new           #4                  // class org/apache/hadoop/hbase/replication/SyncReplicationState
      31: dup
      32: ldc           #30                 // String DOWNGRADE_ACTIVE
      34: iconst_2
      35: iconst_2
      36: invokespecial #28                 // Method "<init>":(Ljava/lang/String;II)V
      39: putstatic     #10                 // Field DOWNGRADE_ACTIVE:Lorg/apache/hadoop/hbase/replication/SyncReplicationState;
      42: new           #4                  // class org/apache/hadoop/hbase/replication/SyncReplicationState
      45: dup
      46: ldc           #31                 // String STANDBY
      48: iconst_3
      49: iconst_3
      50: invokespecial #28                 // Method "<init>":(Ljava/lang/String;II)V
      53: putstatic     #11                 // Field STANDBY:Lorg/apache/hadoop/hbase/replication/SyncReplicationState;
      56: iconst_4
      57: anewarray     #4                  // class org/apache/hadoop/hbase/replication/SyncReplicationState
      60: dup
      61: iconst_0
      62: getstatic     #8                  // Field NONE:Lorg/apache/hadoop/hbase/replication/SyncReplicationState;
      65: aastore
      66: dup
      67: iconst_1
      68: getstatic     #9                  // Field ACTIVE:Lorg/apache/hadoop/hbase/replication/SyncReplicationState;
      71: aastore
      72: dup
      73: iconst_2
      74: getstatic     #10                 // Field DOWNGRADE_ACTIVE:Lorg/apache/hadoop/hbase/replication/SyncReplicationState;
      77: aastore
      78: dup
      79: iconst_3
      80: getstatic     #11                 // Field STANDBY:Lorg/apache/hadoop/hbase/replication/SyncReplicationState;
      83: aastore
      84: putstatic     #1                  // Field $VALUES:[Lorg/apache/hadoop/hbase/replication/SyncReplicationState;
      87: return
}
