Compiled from "SyncReplicationReplayWALManager.java"
class org.apache.hadoop.hbase.master.replication.SyncReplicationReplayWALManager$1 implements org.apache.hadoop.hbase.master.ServerListener {
  final org.apache.hadoop.hbase.master.MasterServices val$services;

  final org.apache.hadoop.hbase.master.replication.SyncReplicationReplayWALManager this$0;

  org.apache.hadoop.hbase.master.replication.SyncReplicationReplayWALManager$1(org.apache.hadoop.hbase.master.replication.SyncReplicationReplayWALManager, org.apache.hadoop.hbase.master.MasterServices);
    Code:
       0: aload_0
       1: aload_1
       2: putfield      #1                  // Field this$0:Lorg/apache/hadoop/hbase/master/replication/SyncReplicationReplayWALManager;
       5: aload_0
       6: aload_2
       7: putfield      #2                  // Field val$services:Lorg/apache/hadoop/hbase/master/MasterServices;
      10: aload_0
      11: invokespecial #3                  // Method java/lang/Object."<init>":()V
      14: return

  public void serverAdded(org.apache.hadoop.hbase.ServerName);
    Code:
       0: aload_0
       1: getfield      #2                  // Field val$services:Lorg/apache/hadoop/hbase/master/MasterServices;
       4: invokeinterface #4,  1            // InterfaceMethod org/apache/hadoop/hbase/master/MasterServices.getMasterProcedureExecutor:()Lorg/apache/hadoop/hbase/procedure2/ProcedureExecutor;
       9: invokevirtual #5                  // Method org/apache/hadoop/hbase/procedure2/ProcedureExecutor.getEnvironment:()Ljava/lang/Object;
      12: checkcast     #6                  // class org/apache/hadoop/hbase/master/procedure/MasterProcedureEnv
      15: invokevirtual #7                  // Method org/apache/hadoop/hbase/master/procedure/MasterProcedureEnv.getProcedureScheduler:()Lorg/apache/hadoop/hbase/master/procedure/MasterProcedureScheduler;
      18: astore_2
      19: aload_0
      20: getfield      #1                  // Field this$0:Lorg/apache/hadoop/hbase/master/replication/SyncReplicationReplayWALManager;
      23: invokestatic  #8                  // Method org/apache/hadoop/hbase/master/replication/SyncReplicationReplayWALManager.access$000:(Lorg/apache/hadoop/hbase/master/replication/SyncReplicationReplayWALManager;)Ljava/util/concurrent/ConcurrentMap;
      26: invokeinterface #9,  1            // InterfaceMethod java/util/concurrent/ConcurrentMap.values:()Ljava/util/Collection;
      31: invokeinterface #10,  1           // InterfaceMethod java/util/Collection.iterator:()Ljava/util/Iterator;
      36: astore_3
      37: aload_3
      38: invokeinterface #11,  1           // InterfaceMethod java/util/Iterator.hasNext:()Z
      43: ifeq          86
      46: aload_3
      47: invokeinterface #12,  1           // InterfaceMethod java/util/Iterator.next:()Ljava/lang/Object;
      52: checkcast     #13                 // class org/apache/hadoop/hbase/master/replication/SyncReplicationReplayWALManager$UsedReplayWorkersForPeer
      55: astore        4
      57: aload         4
      59: dup
      60: astore        5
      62: monitorenter
      63: aload         4
      65: aload_2
      66: invokevirtual #14                 // Method org/apache/hadoop/hbase/master/replication/SyncReplicationReplayWALManager$UsedReplayWorkersForPeer.wake:(Lorg/apache/hadoop/hbase/master/procedure/MasterProcedureScheduler;)V
      69: aload         5
      71: monitorexit
      72: goto          83
      75: astore        6
      77: aload         5
      79: monitorexit
      80: aload         6
      82: athrow
      83: goto          37
      86: return
    Exception table:
       from    to  target type
          63    72    75   any
          75    80    75   any
}
