Compiled from "TableSpaceQuotaSnapshotNotifier.java"
public class org.apache.hadoop.hbase.quotas.TableSpaceQuotaSnapshotNotifier implements org.apache.hadoop.hbase.quotas.SpaceQuotaSnapshotNotifier {
  public org.apache.hadoop.hbase.quotas.TableSpaceQuotaSnapshotNotifier();
    Code:
       0: aload_0
       1: invokespecial #1                  // Method java/lang/Object."<init>":()V
       4: return

  public void transitionTable(org.apache.hadoop.hbase.TableName, org.apache.hadoop.hbase.quotas.SpaceQuotaSnapshot) throws java.io.IOException;
    Code:
       0: aload_1
       1: aload_2
       2: invokestatic  #2                  // Method org/apache/hadoop/hbase/quotas/QuotaTableUtil.createPutForSpaceSnapshot:(Lorg/apache/hadoop/hbase/TableName;Lorg/apache/hadoop/hbase/quotas/SpaceQuotaSnapshot;)Lorg/apache/hadoop/hbase/client/Put;
       5: astore_3
       6: aload_0
       7: getfield      #3                  // Field conn:Lorg/apache/hadoop/hbase/client/Connection;
      10: getstatic     #4                  // Field org/apache/hadoop/hbase/quotas/QuotaTableUtil.QUOTA_TABLE_NAME:Lorg/apache/hadoop/hbase/TableName;
      13: invokeinterface #5,  2            // InterfaceMethod org/apache/hadoop/hbase/client/Connection.getTable:(Lorg/apache/hadoop/hbase/TableName;)Lorg/apache/hadoop/hbase/client/Table;
      18: astore        4
      20: aconst_null
      21: astore        5
      23: getstatic     #6                  // Field LOG:Lorg/slf4j/Logger;
      26: invokeinterface #7,  1            // InterfaceMethod org/slf4j/Logger.isTraceEnabled:()Z
      31: ifeq          70
      34: getstatic     #6                  // Field LOG:Lorg/slf4j/Logger;
      37: new           #8                  // class java/lang/StringBuilder
      40: dup
      41: invokespecial #9                  // Method java/lang/StringBuilder."<init>":()V
      44: ldc           #10                 // String Persisting a space quota snapshot
      46: invokevirtual #11                 // Method java/lang/StringBuilder.append:(Ljava/lang/String;)Ljava/lang/StringBuilder;
      49: aload_2
      50: invokevirtual #12                 // Method java/lang/StringBuilder.append:(Ljava/lang/Object;)Ljava/lang/StringBuilder;
      53: ldc           #13                 // String  for
      55: invokevirtual #11                 // Method java/lang/StringBuilder.append:(Ljava/lang/String;)Ljava/lang/StringBuilder;
      58: aload_1
      59: invokevirtual #12                 // Method java/lang/StringBuilder.append:(Ljava/lang/Object;)Ljava/lang/StringBuilder;
      62: invokevirtual #14                 // Method java/lang/StringBuilder.toString:()Ljava/lang/String;
      65: invokeinterface #15,  2           // InterfaceMethod org/slf4j/Logger.trace:(Ljava/lang/String;)V
      70: aload         4
      72: aload_3
      73: invokeinterface #16,  2           // InterfaceMethod org/apache/hadoop/hbase/client/Table.put:(Lorg/apache/hadoop/hbase/client/Put;)V
      78: aload         4
      80: ifnull        173
      83: aload         5
      85: ifnull        110
      88: aload         4
      90: invokeinterface #17,  1           // InterfaceMethod org/apache/hadoop/hbase/client/Table.close:()V
      95: goto          173
      98: astore        6
     100: aload         5
     102: aload         6
     104: invokevirtual #19                 // Method java/lang/Throwable.addSuppressed:(Ljava/lang/Throwable;)V
     107: goto          173
     110: aload         4
     112: invokeinterface #17,  1           // InterfaceMethod org/apache/hadoop/hbase/client/Table.close:()V
     117: goto          173
     120: astore        6
     122: aload         6
     124: astore        5
     126: aload         6
     128: athrow
     129: astore        7
     131: aload         4
     133: ifnull        170
     136: aload         5
     138: ifnull        163
     141: aload         4
     143: invokeinterface #17,  1           // InterfaceMethod org/apache/hadoop/hbase/client/Table.close:()V
     148: goto          170
     151: astore        8
     153: aload         5
     155: aload         8
     157: invokevirtual #19                 // Method java/lang/Throwable.addSuppressed:(Ljava/lang/Throwable;)V
     160: goto          170
     163: aload         4
     165: invokeinterface #17,  1           // InterfaceMethod org/apache/hadoop/hbase/client/Table.close:()V
     170: aload         7
     172: athrow
     173: return
    Exception table:
       from    to  target type
          88    95    98   Class java/lang/Throwable
          23    78   120   Class java/lang/Throwable
          23    78   129   any
         141   148   151   Class java/lang/Throwable
         120   131   129   any

  public void initialize(org.apache.hadoop.hbase.client.Connection);
    Code:
       0: aload_0
       1: aload_1
       2: putfield      #3                  // Field conn:Lorg/apache/hadoop/hbase/client/Connection;
       5: return

  static {};
    Code:
       0: ldc           #20                 // class org/apache/hadoop/hbase/quotas/TableSpaceQuotaSnapshotNotifier
       2: invokestatic  #21                 // Method org/slf4j/LoggerFactory.getLogger:(Ljava/lang/Class;)Lorg/slf4j/Logger;
       5: putstatic     #6                  // Field LOG:Lorg/slf4j/Logger;
       8: return
}
