Compiled from "Table.java"
public interface org.apache.hadoop.hbase.client.Table extends java.io.Closeable {
  public abstract org.apache.hadoop.hbase.TableName getName();

  public abstract org.apache.hadoop.conf.Configuration getConfiguration();

  public org.apache.hadoop.hbase.HTableDescriptor getTableDescriptor() throws java.io.IOException;
    Code:
       0: aload_0
       1: invokeinterface #1,  1            // InterfaceMethod getDescriptor:()Lorg/apache/hadoop/hbase/client/TableDescriptor;
       6: astore_1
       7: aload_1
       8: instanceof    #2                  // class org/apache/hadoop/hbase/HTableDescriptor
      11: ifeq          19
      14: aload_1
      15: checkcast     #2                  // class org/apache/hadoop/hbase/HTableDescriptor
      18: areturn
      19: new           #2                  // class org/apache/hadoop/hbase/HTableDescriptor
      22: dup
      23: aload_1
      24: invokespecial #3                  // Method org/apache/hadoop/hbase/HTableDescriptor."<init>":(Lorg/apache/hadoop/hbase/client/TableDescriptor;)V
      27: areturn

  public abstract org.apache.hadoop.hbase.client.TableDescriptor getDescriptor() throws java.io.IOException;

  public abstract org.apache.hadoop.hbase.client.RegionLocator getRegionLocator() throws java.io.IOException;

  public boolean exists(org.apache.hadoop.hbase.client.Get) throws java.io.IOException;
    Code:
       0: aload_0
       1: aload_1
       2: invokestatic  #4                  // Method java/util/Collections.singletonList:(Ljava/lang/Object;)Ljava/util/List;
       5: invokeinterface #5,  2            // InterfaceMethod exists:(Ljava/util/List;)[Z
      10: iconst_0
      11: baload
      12: ireturn

  public boolean[] exists(java.util.List<org.apache.hadoop.hbase.client.Get>) throws java.io.IOException;
    Code:
       0: new           #6                  // class org/apache/commons/lang3/NotImplementedException
       3: dup
       4: ldc           #7                  // String Add an implementation!
       6: invokespecial #8                  // Method org/apache/commons/lang3/NotImplementedException."<init>":(Ljava/lang/String;)V
       9: athrow

  public boolean[] existsAll(java.util.List<org.apache.hadoop.hbase.client.Get>) throws java.io.IOException;
    Code:
       0: aload_0
       1: aload_1
       2: invokeinterface #5,  2            // InterfaceMethod exists:(Ljava/util/List;)[Z
       7: areturn

  public void batch(java.util.List<? extends org.apache.hadoop.hbase.client.Row>, java.lang.Object[]) throws java.io.IOException, java.lang.InterruptedException;
    Code:
       0: new           #6                  // class org/apache/commons/lang3/NotImplementedException
       3: dup
       4: ldc           #7                  // String Add an implementation!
       6: invokespecial #8                  // Method org/apache/commons/lang3/NotImplementedException."<init>":(Ljava/lang/String;)V
       9: athrow

  public <R> void batchCallback(java.util.List<? extends org.apache.hadoop.hbase.client.Row>, java.lang.Object[], org.apache.hadoop.hbase.client.coprocessor.Batch$Callback<R>) throws java.io.IOException, java.lang.InterruptedException;
    Code:
       0: new           #6                  // class org/apache/commons/lang3/NotImplementedException
       3: dup
       4: ldc           #7                  // String Add an implementation!
       6: invokespecial #8                  // Method org/apache/commons/lang3/NotImplementedException."<init>":(Ljava/lang/String;)V
       9: athrow

  public org.apache.hadoop.hbase.client.Result get(org.apache.hadoop.hbase.client.Get) throws java.io.IOException;
    Code:
       0: aload_0
       1: aload_1
       2: invokestatic  #4                  // Method java/util/Collections.singletonList:(Ljava/lang/Object;)Ljava/util/List;
       5: invokeinterface #9,  2            // InterfaceMethod get:(Ljava/util/List;)[Lorg/apache/hadoop/hbase/client/Result;
      10: iconst_0
      11: aaload
      12: areturn

  public org.apache.hadoop.hbase.client.Result[] get(java.util.List<org.apache.hadoop.hbase.client.Get>) throws java.io.IOException;
    Code:
       0: new           #6                  // class org/apache/commons/lang3/NotImplementedException
       3: dup
       4: ldc           #7                  // String Add an implementation!
       6: invokespecial #8                  // Method org/apache/commons/lang3/NotImplementedException."<init>":(Ljava/lang/String;)V
       9: athrow

  public org.apache.hadoop.hbase.client.ResultScanner getScanner(org.apache.hadoop.hbase.client.Scan) throws java.io.IOException;
    Code:
       0: new           #6                  // class org/apache/commons/lang3/NotImplementedException
       3: dup
       4: ldc           #7                  // String Add an implementation!
       6: invokespecial #8                  // Method org/apache/commons/lang3/NotImplementedException."<init>":(Ljava/lang/String;)V
       9: athrow

  public org.apache.hadoop.hbase.client.ResultScanner getScanner(byte[]) throws java.io.IOException;
    Code:
       0: new           #6                  // class org/apache/commons/lang3/NotImplementedException
       3: dup
       4: ldc           #7                  // String Add an implementation!
       6: invokespecial #8                  // Method org/apache/commons/lang3/NotImplementedException."<init>":(Ljava/lang/String;)V
       9: athrow

  public org.apache.hadoop.hbase.client.ResultScanner getScanner(byte[], byte[]) throws java.io.IOException;
    Code:
       0: new           #6                  // class org/apache/commons/lang3/NotImplementedException
       3: dup
       4: ldc           #7                  // String Add an implementation!
       6: invokespecial #8                  // Method org/apache/commons/lang3/NotImplementedException."<init>":(Ljava/lang/String;)V
       9: athrow

  public void put(org.apache.hadoop.hbase.client.Put) throws java.io.IOException;
    Code:
       0: aload_0
       1: aload_1
       2: invokestatic  #4                  // Method java/util/Collections.singletonList:(Ljava/lang/Object;)Ljava/util/List;
       5: invokeinterface #10,  2           // InterfaceMethod put:(Ljava/util/List;)V
      10: return

  public void put(java.util.List<org.apache.hadoop.hbase.client.Put>) throws java.io.IOException;
    Code:
       0: new           #6                  // class org/apache/commons/lang3/NotImplementedException
       3: dup
       4: ldc           #7                  // String Add an implementation!
       6: invokespecial #8                  // Method org/apache/commons/lang3/NotImplementedException."<init>":(Ljava/lang/String;)V
       9: athrow

  public boolean checkAndPut(byte[], byte[], byte[], byte[], org.apache.hadoop.hbase.client.Put) throws java.io.IOException;
    Code:
       0: aload_0
       1: aload_1
       2: aload_2
       3: aload_3
       4: getstatic     #11                 // Field org/apache/hadoop/hbase/CompareOperator.EQUAL:Lorg/apache/hadoop/hbase/CompareOperator;
       7: aload         4
       9: aload         5
      11: invokeinterface #12,  7           // InterfaceMethod checkAndPut:([B[B[BLorg/apache/hadoop/hbase/CompareOperator;[BLorg/apache/hadoop/hbase/client/Put;)Z
      16: ireturn

  public boolean checkAndPut(byte[], byte[], byte[], org.apache.hadoop.hbase.CompareOperator, byte[], org.apache.hadoop.hbase.client.Put) throws java.io.IOException;
    Code:
       0: new           #13                 // class org/apache/hadoop/hbase/client/RowMutations
       3: dup
       4: aload         6
       6: invokevirtual #14                 // Method org/apache/hadoop/hbase/client/Put.getRow:()[B
       9: iconst_1
      10: invokespecial #15                 // Method org/apache/hadoop/hbase/client/RowMutations."<init>":([BI)V
      13: astore        7
      15: aload         7
      17: aload         6
      19: invokevirtual #16                 // Method org/apache/hadoop/hbase/client/RowMutations.add:(Lorg/apache/hadoop/hbase/client/Put;)V
      22: aload_0
      23: aload_1
      24: aload_2
      25: aload_3
      26: aload         4
      28: aload         5
      30: aload         7
      32: invokeinterface #17,  7           // InterfaceMethod checkAndMutate:([B[B[BLorg/apache/hadoop/hbase/CompareOperator;[BLorg/apache/hadoop/hbase/client/RowMutations;)Z
      37: ireturn

  public void delete(org.apache.hadoop.hbase.client.Delete) throws java.io.IOException;
    Code:
       0: new           #6                  // class org/apache/commons/lang3/NotImplementedException
       3: dup
       4: ldc           #7                  // String Add an implementation!
       6: invokespecial #8                  // Method org/apache/commons/lang3/NotImplementedException."<init>":(Ljava/lang/String;)V
       9: athrow

  public void delete(java.util.List<org.apache.hadoop.hbase.client.Delete>) throws java.io.IOException;
    Code:
       0: new           #6                  // class org/apache/commons/lang3/NotImplementedException
       3: dup
       4: ldc           #7                  // String Add an implementation!
       6: invokespecial #8                  // Method org/apache/commons/lang3/NotImplementedException."<init>":(Ljava/lang/String;)V
       9: athrow

  public boolean checkAndDelete(byte[], byte[], byte[], byte[], org.apache.hadoop.hbase.client.Delete) throws java.io.IOException;
    Code:
       0: aload_0
       1: aload_1
       2: aload_2
       3: aload_3
       4: getstatic     #11                 // Field org/apache/hadoop/hbase/CompareOperator.EQUAL:Lorg/apache/hadoop/hbase/CompareOperator;
       7: aload         4
       9: aload         5
      11: invokeinterface #18,  7           // InterfaceMethod checkAndDelete:([B[B[BLorg/apache/hadoop/hbase/CompareOperator;[BLorg/apache/hadoop/hbase/client/Delete;)Z
      16: ireturn

  public boolean checkAndDelete(byte[], byte[], byte[], org.apache.hadoop.hbase.CompareOperator, byte[], org.apache.hadoop.hbase.client.Delete) throws java.io.IOException;
    Code:
       0: new           #13                 // class org/apache/hadoop/hbase/client/RowMutations
       3: dup
       4: aload         6
       6: invokevirtual #19                 // Method org/apache/hadoop/hbase/client/Delete.getRow:()[B
       9: iconst_1
      10: invokespecial #15                 // Method org/apache/hadoop/hbase/client/RowMutations."<init>":([BI)V
      13: astore        7
      15: aload         7
      17: aload         6
      19: invokevirtual #20                 // Method org/apache/hadoop/hbase/client/RowMutations.add:(Lorg/apache/hadoop/hbase/client/Delete;)V
      22: aload_0
      23: aload_1
      24: aload_2
      25: aload_3
      26: aload         4
      28: aload         5
      30: aload         7
      32: invokeinterface #17,  7           // InterfaceMethod checkAndMutate:([B[B[BLorg/apache/hadoop/hbase/CompareOperator;[BLorg/apache/hadoop/hbase/client/RowMutations;)Z
      37: ireturn

  public org.apache.hadoop.hbase.client.Table$CheckAndMutateBuilder checkAndMutate(byte[], byte[]);
    Code:
       0: new           #6                  // class org/apache/commons/lang3/NotImplementedException
       3: dup
       4: ldc           #7                  // String Add an implementation!
       6: invokespecial #8                  // Method org/apache/commons/lang3/NotImplementedException."<init>":(Ljava/lang/String;)V
       9: athrow

  public void mutateRow(org.apache.hadoop.hbase.client.RowMutations) throws java.io.IOException;
    Code:
       0: new           #6                  // class org/apache/commons/lang3/NotImplementedException
       3: dup
       4: ldc           #7                  // String Add an implementation!
       6: invokespecial #8                  // Method org/apache/commons/lang3/NotImplementedException."<init>":(Ljava/lang/String;)V
       9: athrow

  public org.apache.hadoop.hbase.client.Result append(org.apache.hadoop.hbase.client.Append) throws java.io.IOException;
    Code:
       0: new           #6                  // class org/apache/commons/lang3/NotImplementedException
       3: dup
       4: ldc           #7                  // String Add an implementation!
       6: invokespecial #8                  // Method org/apache/commons/lang3/NotImplementedException."<init>":(Ljava/lang/String;)V
       9: athrow

  public org.apache.hadoop.hbase.client.Result increment(org.apache.hadoop.hbase.client.Increment) throws java.io.IOException;
    Code:
       0: new           #6                  // class org/apache/commons/lang3/NotImplementedException
       3: dup
       4: ldc           #7                  // String Add an implementation!
       6: invokespecial #8                  // Method org/apache/commons/lang3/NotImplementedException."<init>":(Ljava/lang/String;)V
       9: athrow

  public long incrementColumnValue(byte[], byte[], byte[], long) throws java.io.IOException;
    Code:
       0: new           #21                 // class org/apache/hadoop/hbase/client/Increment
       3: dup
       4: aload_1
       5: invokespecial #22                 // Method org/apache/hadoop/hbase/client/Increment."<init>":([B)V
       8: aload_2
       9: aload_3
      10: lload         4
      12: invokevirtual #23                 // Method org/apache/hadoop/hbase/client/Increment.addColumn:([B[BJ)Lorg/apache/hadoop/hbase/client/Increment;
      15: astore        6
      17: aload_0
      18: aload         6
      20: invokeinterface #24,  2           // InterfaceMethod increment:(Lorg/apache/hadoop/hbase/client/Increment;)Lorg/apache/hadoop/hbase/client/Result;
      25: aload_2
      26: aload_3
      27: invokevirtual #25                 // Method org/apache/hadoop/hbase/client/Result.getColumnLatestCell:([B[B)Lorg/apache/hadoop/hbase/Cell;
      30: astore        7
      32: aload         7
      34: invokeinterface #26,  1           // InterfaceMethod org/apache/hadoop/hbase/Cell.getValueArray:()[B
      39: aload         7
      41: invokeinterface #27,  1           // InterfaceMethod org/apache/hadoop/hbase/Cell.getValueOffset:()I
      46: aload         7
      48: invokeinterface #28,  1           // InterfaceMethod org/apache/hadoop/hbase/Cell.getValueLength:()I
      53: invokestatic  #29                 // Method org/apache/hadoop/hbase/util/Bytes.toLong:([BII)J
      56: lreturn

  public long incrementColumnValue(byte[], byte[], byte[], long, org.apache.hadoop.hbase.client.Durability) throws java.io.IOException;
    Code:
       0: new           #21                 // class org/apache/hadoop/hbase/client/Increment
       3: dup
       4: aload_1
       5: invokespecial #22                 // Method org/apache/hadoop/hbase/client/Increment."<init>":([B)V
       8: aload_2
       9: aload_3
      10: lload         4
      12: invokevirtual #23                 // Method org/apache/hadoop/hbase/client/Increment.addColumn:([B[BJ)Lorg/apache/hadoop/hbase/client/Increment;
      15: aload         6
      17: invokevirtual #30                 // Method org/apache/hadoop/hbase/client/Increment.setDurability:(Lorg/apache/hadoop/hbase/client/Durability;)Lorg/apache/hadoop/hbase/client/Increment;
      20: astore        7
      22: aload_0
      23: aload         7
      25: invokeinterface #24,  2           // InterfaceMethod increment:(Lorg/apache/hadoop/hbase/client/Increment;)Lorg/apache/hadoop/hbase/client/Result;
      30: aload_2
      31: aload_3
      32: invokevirtual #25                 // Method org/apache/hadoop/hbase/client/Result.getColumnLatestCell:([B[B)Lorg/apache/hadoop/hbase/Cell;
      35: astore        8
      37: aload         8
      39: invokeinterface #26,  1           // InterfaceMethod org/apache/hadoop/hbase/Cell.getValueArray:()[B
      44: aload         8
      46: invokeinterface #27,  1           // InterfaceMethod org/apache/hadoop/hbase/Cell.getValueOffset:()I
      51: aload         8
      53: invokeinterface #28,  1           // InterfaceMethod org/apache/hadoop/hbase/Cell.getValueLength:()I
      58: invokestatic  #29                 // Method org/apache/hadoop/hbase/util/Bytes.toLong:([BII)J
      61: lreturn

  public void close() throws java.io.IOException;
    Code:
       0: new           #6                  // class org/apache/commons/lang3/NotImplementedException
       3: dup
       4: ldc           #7                  // String Add an implementation!
       6: invokespecial #8                  // Method org/apache/commons/lang3/NotImplementedException."<init>":(Ljava/lang/String;)V
       9: athrow

  public org.apache.hadoop.hbase.ipc.CoprocessorRpcChannel coprocessorService(byte[]);
    Code:
       0: new           #6                  // class org/apache/commons/lang3/NotImplementedException
       3: dup
       4: ldc           #7                  // String Add an implementation!
       6: invokespecial #8                  // Method org/apache/commons/lang3/NotImplementedException."<init>":(Ljava/lang/String;)V
       9: athrow

  public <T extends com.google.protobuf.Service, R> java.util.Map<byte[], R> coprocessorService(java.lang.Class<T>, byte[], byte[], org.apache.hadoop.hbase.client.coprocessor.Batch$Call<T, R>) throws com.google.protobuf.ServiceException, java.lang.Throwable;
    Code:
       0: new           #6                  // class org/apache/commons/lang3/NotImplementedException
       3: dup
       4: ldc           #7                  // String Add an implementation!
       6: invokespecial #8                  // Method org/apache/commons/lang3/NotImplementedException."<init>":(Ljava/lang/String;)V
       9: athrow

  public <T extends com.google.protobuf.Service, R> void coprocessorService(java.lang.Class<T>, byte[], byte[], org.apache.hadoop.hbase.client.coprocessor.Batch$Call<T, R>, org.apache.hadoop.hbase.client.coprocessor.Batch$Callback<R>) throws com.google.protobuf.ServiceException, java.lang.Throwable;
    Code:
       0: new           #6                  // class org/apache/commons/lang3/NotImplementedException
       3: dup
       4: ldc           #7                  // String Add an implementation!
       6: invokespecial #8                  // Method org/apache/commons/lang3/NotImplementedException."<init>":(Ljava/lang/String;)V
       9: athrow

  public <R extends com.google.protobuf.Message> java.util.Map<byte[], R> batchCoprocessorService(com.google.protobuf.Descriptors$MethodDescriptor, com.google.protobuf.Message, byte[], byte[], R) throws com.google.protobuf.ServiceException, java.lang.Throwable;
    Code:
       0: new           #6                  // class org/apache/commons/lang3/NotImplementedException
       3: dup
       4: ldc           #7                  // String Add an implementation!
       6: invokespecial #8                  // Method org/apache/commons/lang3/NotImplementedException."<init>":(Ljava/lang/String;)V
       9: athrow

  public <R extends com.google.protobuf.Message> void batchCoprocessorService(com.google.protobuf.Descriptors$MethodDescriptor, com.google.protobuf.Message, byte[], byte[], R, org.apache.hadoop.hbase.client.coprocessor.Batch$Callback<R>) throws com.google.protobuf.ServiceException, java.lang.Throwable;
    Code:
       0: new           #6                  // class org/apache/commons/lang3/NotImplementedException
       3: dup
       4: ldc           #7                  // String Add an implementation!
       6: invokespecial #8                  // Method org/apache/commons/lang3/NotImplementedException."<init>":(Ljava/lang/String;)V
       9: athrow

  public boolean checkAndMutate(byte[], byte[], byte[], org.apache.hadoop.hbase.CompareOperator, byte[], org.apache.hadoop.hbase.client.RowMutations) throws java.io.IOException;
    Code:
       0: new           #6                  // class org/apache/commons/lang3/NotImplementedException
       3: dup
       4: ldc           #7                  // String Add an implementation!
       6: invokespecial #8                  // Method org/apache/commons/lang3/NotImplementedException."<init>":(Ljava/lang/String;)V
       9: athrow

  public long getRpcTimeout(java.util.concurrent.TimeUnit);
    Code:
       0: new           #6                  // class org/apache/commons/lang3/NotImplementedException
       3: dup
       4: ldc           #7                  // String Add an implementation!
       6: invokespecial #8                  // Method org/apache/commons/lang3/NotImplementedException."<init>":(Ljava/lang/String;)V
       9: athrow

  public int getRpcTimeout();
    Code:
       0: aload_0
       1: getstatic     #31                 // Field java/util/concurrent/TimeUnit.MILLISECONDS:Ljava/util/concurrent/TimeUnit;
       4: invokeinterface #32,  2           // InterfaceMethod getRpcTimeout:(Ljava/util/concurrent/TimeUnit;)J
       9: l2i
      10: ireturn

  public void setRpcTimeout(int);
    Code:
       0: aload_0
       1: iload_1
       2: invokeinterface #33,  2           // InterfaceMethod setReadRpcTimeout:(I)V
       7: aload_0
       8: iload_1
       9: invokeinterface #34,  2           // InterfaceMethod setWriteRpcTimeout:(I)V
      14: return

  public long getReadRpcTimeout(java.util.concurrent.TimeUnit);
    Code:
       0: new           #6                  // class org/apache/commons/lang3/NotImplementedException
       3: dup
       4: ldc           #7                  // String Add an implementation!
       6: invokespecial #8                  // Method org/apache/commons/lang3/NotImplementedException."<init>":(Ljava/lang/String;)V
       9: athrow

  public int getReadRpcTimeout();
    Code:
       0: aload_0
       1: getstatic     #31                 // Field java/util/concurrent/TimeUnit.MILLISECONDS:Ljava/util/concurrent/TimeUnit;
       4: invokeinterface #35,  2           // InterfaceMethod getReadRpcTimeout:(Ljava/util/concurrent/TimeUnit;)J
       9: l2i
      10: ireturn

  public void setReadRpcTimeout(int);
    Code:
       0: new           #6                  // class org/apache/commons/lang3/NotImplementedException
       3: dup
       4: ldc           #7                  // String Add an implementation!
       6: invokespecial #8                  // Method org/apache/commons/lang3/NotImplementedException."<init>":(Ljava/lang/String;)V
       9: athrow

  public long getWriteRpcTimeout(java.util.concurrent.TimeUnit);
    Code:
       0: new           #6                  // class org/apache/commons/lang3/NotImplementedException
       3: dup
       4: ldc           #7                  // String Add an implementation!
       6: invokespecial #8                  // Method org/apache/commons/lang3/NotImplementedException."<init>":(Ljava/lang/String;)V
       9: athrow

  public int getWriteRpcTimeout();
    Code:
       0: aload_0
       1: getstatic     #31                 // Field java/util/concurrent/TimeUnit.MILLISECONDS:Ljava/util/concurrent/TimeUnit;
       4: invokeinterface #36,  2           // InterfaceMethod getWriteRpcTimeout:(Ljava/util/concurrent/TimeUnit;)J
       9: l2i
      10: ireturn

  public void setWriteRpcTimeout(int);
    Code:
       0: new           #6                  // class org/apache/commons/lang3/NotImplementedException
       3: dup
       4: ldc           #7                  // String Add an implementation!
       6: invokespecial #8                  // Method org/apache/commons/lang3/NotImplementedException."<init>":(Ljava/lang/String;)V
       9: athrow

  public long getOperationTimeout(java.util.concurrent.TimeUnit);
    Code:
       0: new           #6                  // class org/apache/commons/lang3/NotImplementedException
       3: dup
       4: ldc           #7                  // String Add an implementation!
       6: invokespecial #8                  // Method org/apache/commons/lang3/NotImplementedException."<init>":(Ljava/lang/String;)V
       9: athrow

  public int getOperationTimeout();
    Code:
       0: aload_0
       1: getstatic     #31                 // Field java/util/concurrent/TimeUnit.MILLISECONDS:Ljava/util/concurrent/TimeUnit;
       4: invokeinterface #37,  2           // InterfaceMethod getOperationTimeout:(Ljava/util/concurrent/TimeUnit;)J
       9: l2i
      10: ireturn

  public void setOperationTimeout(int);
    Code:
       0: new           #6                  // class org/apache/commons/lang3/NotImplementedException
       3: dup
       4: ldc           #7                  // String Add an implementation!
       6: invokespecial #8                  // Method org/apache/commons/lang3/NotImplementedException."<init>":(Ljava/lang/String;)V
       9: athrow
}
