Compiled from "TableSnapshotScanner.java"
public class org.apache.hadoop.hbase.client.TableSnapshotScanner extends org.apache.hadoop.hbase.client.AbstractClientScanner {
  public org.apache.hadoop.hbase.client.TableSnapshotScanner(org.apache.hadoop.conf.Configuration, org.apache.hadoop.fs.Path, java.lang.String, org.apache.hadoop.hbase.client.Scan) throws java.io.IOException;
    Code:
       0: aload_0
       1: aload_1
       2: aload_1
       3: invokestatic  #1                  // Method org/apache/hadoop/hbase/util/FSUtils.getRootDir:(Lorg/apache/hadoop/conf/Configuration;)Lorg/apache/hadoop/fs/Path;
       6: aload_2
       7: aload_3
       8: aload         4
      10: invokespecial #2                  // Method "<init>":(Lorg/apache/hadoop/conf/Configuration;Lorg/apache/hadoop/fs/Path;Lorg/apache/hadoop/fs/Path;Ljava/lang/String;Lorg/apache/hadoop/hbase/client/Scan;)V
      13: return

  public org.apache.hadoop.hbase.client.TableSnapshotScanner(org.apache.hadoop.conf.Configuration, org.apache.hadoop.fs.Path, org.apache.hadoop.fs.Path, java.lang.String, org.apache.hadoop.hbase.client.Scan) throws java.io.IOException;
    Code:
       0: aload_0
       1: aload_1
       2: aload_2
       3: aload_3
       4: aload         4
       6: aload         5
       8: iconst_0
       9: invokespecial #3                  // Method "<init>":(Lorg/apache/hadoop/conf/Configuration;Lorg/apache/hadoop/fs/Path;Lorg/apache/hadoop/fs/Path;Ljava/lang/String;Lorg/apache/hadoop/hbase/client/Scan;Z)V
      12: return

  public org.apache.hadoop.hbase.client.TableSnapshotScanner(org.apache.hadoop.conf.Configuration, org.apache.hadoop.fs.Path, org.apache.hadoop.fs.Path, java.lang.String, org.apache.hadoop.hbase.client.Scan, boolean) throws java.io.IOException;
    Code:
       0: aload_0
       1: invokespecial #4                  // Method org/apache/hadoop/hbase/client/AbstractClientScanner."<init>":()V
       4: aload_0
       5: aconst_null
       6: putfield      #5                  // Field currentRegionScanner:Lorg/apache/hadoop/hbase/client/ClientSideRegionScanner;
       9: aload_0
      10: iconst_m1
      11: putfield      #6                  // Field currentRegion:I
      14: aload_0
      15: aload_1
      16: putfield      #7                  // Field conf:Lorg/apache/hadoop/conf/Configuration;
      19: aload_0
      20: aload         4
      22: putfield      #8                  // Field snapshotName:Ljava/lang/String;
      25: aload_0
      26: aload_2
      27: putfield      #9                  // Field rootDir:Lorg/apache/hadoop/fs/Path;
      30: aload_0
      31: aload         5
      33: putfield      #10                 // Field scan:Lorg/apache/hadoop/hbase/client/Scan;
      36: aload_0
      37: iload         6
      39: putfield      #11                 // Field snapshotAlreadyRestored:Z
      42: aload_0
      43: aload_2
      44: aload_1
      45: invokevirtual #12                 // Method org/apache/hadoop/fs/Path.getFileSystem:(Lorg/apache/hadoop/conf/Configuration;)Lorg/apache/hadoop/fs/FileSystem;
      48: putfield      #13                 // Field fs:Lorg/apache/hadoop/fs/FileSystem;
      51: iload         6
      53: ifeq          68
      56: aload_0
      57: aload_3
      58: putfield      #14                 // Field restoreDir:Lorg/apache/hadoop/fs/Path;
      61: aload_0
      62: invokespecial #15                 // Method openWithoutRestoringSnapshot:()V
      65: goto          90
      68: aload_0
      69: new           #16                 // class org/apache/hadoop/fs/Path
      72: dup
      73: aload_3
      74: invokestatic  #17                 // Method java/util/UUID.randomUUID:()Ljava/util/UUID;
      77: invokevirtual #18                 // Method java/util/UUID.toString:()Ljava/lang/String;
      80: invokespecial #19                 // Method org/apache/hadoop/fs/Path."<init>":(Lorg/apache/hadoop/fs/Path;Ljava/lang/String;)V
      83: putfield      #14                 // Field restoreDir:Lorg/apache/hadoop/fs/Path;
      86: aload_0
      87: invokespecial #20                 // Method openWithRestoringSnapshot:()V
      90: aload_0
      91: aload         5
      93: invokevirtual #21                 // Method initScanMetrics:(Lorg/apache/hadoop/hbase/client/Scan;)V
      96: return

  public org.apache.hadoop.hbase.client.Result next() throws java.io.IOException;
    Code:
       0: aconst_null
       1: astore_1
       2: aload_0
       3: getfield      #5                  // Field currentRegionScanner:Lorg/apache/hadoop/hbase/client/ClientSideRegionScanner;
       6: ifnonnull     104
       9: aload_0
      10: dup
      11: getfield      #6                  // Field currentRegion:I
      14: iconst_1
      15: iadd
      16: putfield      #6                  // Field currentRegion:I
      19: aload_0
      20: getfield      #6                  // Field currentRegion:I
      23: aload_0
      24: getfield      #36                 // Field regions:Ljava/util/ArrayList;
      27: invokevirtual #60                 // Method java/util/ArrayList.size:()I
      30: if_icmplt     35
      33: aconst_null
      34: areturn
      35: aload_0
      36: getfield      #36                 // Field regions:Ljava/util/ArrayList;
      39: aload_0
      40: getfield      #6                  // Field currentRegion:I
      43: invokevirtual #61                 // Method java/util/ArrayList.get:(I)Ljava/lang/Object;
      46: checkcast     #62                 // class org/apache/hadoop/hbase/client/RegionInfo
      49: astore_2
      50: aload_0
      51: new           #63                 // class org/apache/hadoop/hbase/client/ClientSideRegionScanner
      54: dup
      55: aload_0
      56: getfield      #7                  // Field conf:Lorg/apache/hadoop/conf/Configuration;
      59: aload_0
      60: getfield      #13                 // Field fs:Lorg/apache/hadoop/fs/FileSystem;
      63: aload_0
      64: getfield      #14                 // Field restoreDir:Lorg/apache/hadoop/fs/Path;
      67: aload_0
      68: getfield      #46                 // Field htd:Lorg/apache/hadoop/hbase/client/TableDescriptor;
      71: aload_2
      72: aload_0
      73: getfield      #10                 // Field scan:Lorg/apache/hadoop/hbase/client/Scan;
      76: aload_0
      77: getfield      #64                 // Field scanMetrics:Lorg/apache/hadoop/hbase/client/metrics/ScanMetrics;
      80: invokespecial #65                 // Method org/apache/hadoop/hbase/client/ClientSideRegionScanner."<init>":(Lorg/apache/hadoop/conf/Configuration;Lorg/apache/hadoop/fs/FileSystem;Lorg/apache/hadoop/fs/Path;Lorg/apache/hadoop/hbase/client/TableDescriptor;Lorg/apache/hadoop/hbase/client/RegionInfo;Lorg/apache/hadoop/hbase/client/Scan;Lorg/apache/hadoop/hbase/client/metrics/ScanMetrics;)V
      83: putfield      #5                  // Field currentRegionScanner:Lorg/apache/hadoop/hbase/client/ClientSideRegionScanner;
      86: aload_0
      87: getfield      #64                 // Field scanMetrics:Lorg/apache/hadoop/hbase/client/metrics/ScanMetrics;
      90: ifnull        104
      93: aload_0
      94: getfield      #64                 // Field scanMetrics:Lorg/apache/hadoop/hbase/client/metrics/ScanMetrics;
      97: getfield      #66                 // Field org/apache/hadoop/hbase/client/metrics/ScanMetrics.countOfRegions:Ljava/util/concurrent/atomic/AtomicLong;
     100: invokevirtual #67                 // Method java/util/concurrent/atomic/AtomicLong.incrementAndGet:()J
     103: pop2
     104: aload_0
     105: getfield      #5                  // Field currentRegionScanner:Lorg/apache/hadoop/hbase/client/ClientSideRegionScanner;
     108: invokevirtual #68                 // Method org/apache/hadoop/hbase/client/ClientSideRegionScanner.next:()Lorg/apache/hadoop/hbase/client/Result;
     111: astore_1
     112: aload_1
     113: ifnull        136
     116: aload_1
     117: astore_2
     118: aload_1
     119: ifnonnull     134
     122: aload_0
     123: getfield      #5                  // Field currentRegionScanner:Lorg/apache/hadoop/hbase/client/ClientSideRegionScanner;
     126: invokevirtual #69                 // Method org/apache/hadoop/hbase/client/ClientSideRegionScanner.close:()V
     129: aload_0
     130: aconst_null
     131: putfield      #5                  // Field currentRegionScanner:Lorg/apache/hadoop/hbase/client/ClientSideRegionScanner;
     134: aload_2
     135: areturn
     136: aload_1
     137: ifnonnull     174
     140: aload_0
     141: getfield      #5                  // Field currentRegionScanner:Lorg/apache/hadoop/hbase/client/ClientSideRegionScanner;
     144: invokevirtual #69                 // Method org/apache/hadoop/hbase/client/ClientSideRegionScanner.close:()V
     147: aload_0
     148: aconst_null
     149: putfield      #5                  // Field currentRegionScanner:Lorg/apache/hadoop/hbase/client/ClientSideRegionScanner;
     152: goto          174
     155: astore_3
     156: aload_1
     157: ifnonnull     172
     160: aload_0
     161: getfield      #5                  // Field currentRegionScanner:Lorg/apache/hadoop/hbase/client/ClientSideRegionScanner;
     164: invokevirtual #69                 // Method org/apache/hadoop/hbase/client/ClientSideRegionScanner.close:()V
     167: aload_0
     168: aconst_null
     169: putfield      #5                  // Field currentRegionScanner:Lorg/apache/hadoop/hbase/client/ClientSideRegionScanner;
     172: aload_3
     173: athrow
     174: goto          2
    Exception table:
       from    to  target type
         104   118   155   any

  public void close();
    Code:
       0: aload_0
       1: getfield      #5                  // Field currentRegionScanner:Lorg/apache/hadoop/hbase/client/ClientSideRegionScanner;
       4: ifnull        14
       7: aload_0
       8: getfield      #5                  // Field currentRegionScanner:Lorg/apache/hadoop/hbase/client/ClientSideRegionScanner;
      11: invokevirtual #69                 // Method org/apache/hadoop/hbase/client/ClientSideRegionScanner.close:()V
      14: aload_0
      15: getfield      #11                 // Field snapshotAlreadyRestored:Z
      18: ifne          25
      21: aload_0
      22: invokespecial #79                 // Method cleanup:()V
      25: return

  public boolean renewLease();
    Code:
       0: new           #80                 // class java/lang/UnsupportedOperationException
       3: dup
       4: invokespecial #81                 // Method java/lang/UnsupportedOperationException."<init>":()V
       7: athrow

  static {};
    Code:
       0: ldc           #85                 // class org/apache/hadoop/hbase/client/TableSnapshotScanner
       2: invokestatic  #86                 // Method org/slf4j/LoggerFactory.getLogger:(Ljava/lang/Class;)Lorg/slf4j/Logger;
       5: putstatic     #72                 // Field LOG:Lorg/slf4j/Logger;
       8: return
}
