Compiled from "TableStateManager.java"
class org.apache.hadoop.hbase.master.TableStateManager$1 implements org.apache.hadoop.hbase.MetaTableAccessor$Visitor {
  final org.apache.hadoop.hbase.client.TableState$State[] val$states;

  final java.util.Set val$rv;

  final org.apache.hadoop.hbase.master.TableStateManager this$0;

  org.apache.hadoop.hbase.master.TableStateManager$1(org.apache.hadoop.hbase.master.TableStateManager, org.apache.hadoop.hbase.client.TableState$State[], java.util.Set);
    Code:
       0: aload_0
       1: aload_1
       2: putfield      #1                  // Field this$0:Lorg/apache/hadoop/hbase/master/TableStateManager;
       5: aload_0
       6: aload_2
       7: putfield      #2                  // Field val$states:[Lorg/apache/hadoop/hbase/client/TableState$State;
      10: aload_0
      11: aload_3
      12: putfield      #3                  // Field val$rv:Ljava/util/Set;
      15: aload_0
      16: invokespecial #4                  // Method java/lang/Object."<init>":()V
      19: return

  public boolean visit(org.apache.hadoop.hbase.client.Result) throws java.io.IOException;
    Code:
       0: aload_1
       1: invokestatic  #5                  // Method org/apache/hadoop/hbase/MetaTableAccessor.getTableState:(Lorg/apache/hadoop/hbase/client/Result;)Lorg/apache/hadoop/hbase/client/TableState;
       4: astore_2
       5: aload_2
       6: ifnull        34
       9: aload_2
      10: aload_0
      11: getfield      #2                  // Field val$states:[Lorg/apache/hadoop/hbase/client/TableState$State;
      14: invokevirtual #6                  // Method org/apache/hadoop/hbase/client/TableState.inStates:([Lorg/apache/hadoop/hbase/client/TableState$State;)Z
      17: ifeq          34
      20: aload_0
      21: getfield      #3                  // Field val$rv:Ljava/util/Set;
      24: aload_2
      25: invokevirtual #7                  // Method org/apache/hadoop/hbase/client/TableState.getTableName:()Lorg/apache/hadoop/hbase/TableName;
      28: invokeinterface #8,  2            // InterfaceMethod java/util/Set.add:(Ljava/lang/Object;)Z
      33: pop
      34: iconst_1
      35: ireturn
}
