Compiled from "TaskMonitor.java"
class org.apache.hadoop.hbase.monitoring.TaskMonitor$MonitorRunnable implements java.lang.Runnable {
  final org.apache.hadoop.hbase.monitoring.TaskMonitor this$0;

  public void run();
    Code:
       0: aload_0
       1: getfield      #4                  // Field running:Z
       4: ifeq          56
       7: aload_0
       8: getfield      #2                  // Field this$0:Lorg/apache/hadoop/hbase/monitoring/TaskMonitor;
      11: invokestatic  #5                  // Method org/apache/hadoop/hbase/monitoring/TaskMonitor.access$100:(Lorg/apache/hadoop/hbase/monitoring/TaskMonitor;)J
      14: invokestatic  #6                  // Method java/lang/Thread.sleep:(J)V
      17: aload_0
      18: getfield      #2                  // Field this$0:Lorg/apache/hadoop/hbase/monitoring/TaskMonitor;
      21: invokestatic  #7                  // Method org/apache/hadoop/hbase/monitoring/TaskMonitor.access$200:(Lorg/apache/hadoop/hbase/monitoring/TaskMonitor;)Lorg/apache/hbase/thirdparty/org/apache/commons/collections4/queue/CircularFifoQueue;
      24: invokevirtual #8                  // Method org/apache/hbase/thirdparty/org/apache/commons/collections4/queue/CircularFifoQueue.isFull:()Z
      27: ifeq          37
      30: aload_0
      31: getfield      #2                  // Field this$0:Lorg/apache/hadoop/hbase/monitoring/TaskMonitor;
      34: invokestatic  #9                  // Method org/apache/hadoop/hbase/monitoring/TaskMonitor.access$300:(Lorg/apache/hadoop/hbase/monitoring/TaskMonitor;)V
      37: aload_0
      38: getfield      #2                  // Field this$0:Lorg/apache/hadoop/hbase/monitoring/TaskMonitor;
      41: invokestatic  #10                 // Method org/apache/hadoop/hbase/monitoring/TaskMonitor.access$400:(Lorg/apache/hadoop/hbase/monitoring/TaskMonitor;)V
      44: goto          0
      47: astore_1
      48: aload_0
      49: iconst_0
      50: putfield      #4                  // Field running:Z
      53: goto          0
      56: return
    Exception table:
       from    to  target type
           7    44    47   Class java/lang/InterruptedException

  org.apache.hadoop.hbase.monitoring.TaskMonitor$MonitorRunnable(org.apache.hadoop.hbase.monitoring.TaskMonitor, org.apache.hadoop.hbase.monitoring.TaskMonitor$1);
    Code:
       0: aload_0
       1: aload_1
       2: invokespecial #1                  // Method "<init>":(Lorg/apache/hadoop/hbase/monitoring/TaskMonitor;)V
       5: return
}
