Compiled from "TestCleanerChore.java"
class org.apache.hadoop.hbase.master.cleaner.TestCleanerChore$3 implements org.mockito.stubbing.Answer<java.lang.Boolean> {
  final org.apache.hadoop.fs.FileSystem val$fs;

  final org.apache.hadoop.fs.Path val$racyFile;

  final org.apache.hadoop.fs.Path val$testDir;

  final org.apache.hadoop.hbase.master.cleaner.TestCleanerChore this$0;

  org.apache.hadoop.hbase.master.cleaner.TestCleanerChore$3(org.apache.hadoop.hbase.master.cleaner.TestCleanerChore, org.apache.hadoop.fs.FileSystem, org.apache.hadoop.fs.Path, org.apache.hadoop.fs.Path);
    Code:
       0: aload_0
       1: aload_1
       2: putfield      #1                  // Field this$0:Lorg/apache/hadoop/hbase/master/cleaner/TestCleanerChore;
       5: aload_0
       6: aload_2
       7: putfield      #2                  // Field val$fs:Lorg/apache/hadoop/fs/FileSystem;
      10: aload_0
      11: aload_3
      12: putfield      #3                  // Field val$racyFile:Lorg/apache/hadoop/fs/Path;
      15: aload_0
      16: aload         4
      18: putfield      #4                  // Field val$testDir:Lorg/apache/hadoop/fs/Path;
      21: aload_0
      22: invokespecial #5                  // Method java/lang/Object."<init>":()V
      25: return

  public java.lang.Boolean answer(org.mockito.invocation.InvocationOnMock) throws java.lang.Throwable;
    Code:
       0: aload_0
       1: getfield      #2                  // Field val$fs:Lorg/apache/hadoop/fs/FileSystem;
       4: aload_0
       5: getfield      #3                  // Field val$racyFile:Lorg/apache/hadoop/fs/Path;
       8: invokevirtual #6                  // Method org/apache/hadoop/fs/FileSystem.create:(Lorg/apache/hadoop/fs/Path;)Lorg/apache/hadoop/fs/FSDataOutputStream;
      11: invokevirtual #7                  // Method org/apache/hadoop/fs/FSDataOutputStream.close:()V
      14: aload_0
      15: getfield      #2                  // Field val$fs:Lorg/apache/hadoop/fs/FileSystem;
      18: aload_0
      19: getfield      #4                  // Field val$testDir:Lorg/apache/hadoop/fs/Path;
      22: invokestatic  #8                  // Method org/apache/hadoop/hbase/master/cleaner/TestCleanerChore.access$000:()Lorg/slf4j/Logger;
      25: invokestatic  #9                  // Method org/apache/hadoop/hbase/util/FSUtils.logFileSystemState:(Lorg/apache/hadoop/fs/FileSystem;Lorg/apache/hadoop/fs/Path;Lorg/slf4j/Logger;)V
      28: aload_1
      29: invokeinterface #10,  1           // InterfaceMethod org/mockito/invocation/InvocationOnMock.callRealMethod:()Ljava/lang/Object;
      34: checkcast     #11                 // class java/lang/Boolean
      37: areturn

  public java.lang.Object answer(org.mockito.invocation.InvocationOnMock) throws java.lang.Throwable;
    Code:
       0: aload_0
       1: aload_1
       2: invokevirtual #12                 // Method answer:(Lorg/mockito/invocation/InvocationOnMock;)Ljava/lang/Boolean;
       5: areturn
}
