Compiled from "TestCopyOnWriteMaps.java"
class org.apache.hadoop.hbase.types.TestCopyOnWriteMaps$1 implements java.lang.Runnable {
  final org.apache.hadoop.hbase.types.TestCopyOnWriteMaps this$0;

  org.apache.hadoop.hbase.types.TestCopyOnWriteMaps$1(org.apache.hadoop.hbase.types.TestCopyOnWriteMaps);
    Code:
       0: aload_0
       1: aload_1
       2: putfield      #1                  // Field this$0:Lorg/apache/hadoop/hbase/types/TestCopyOnWriteMaps;
       5: aload_0
       6: invokespecial #2                  // Method java/lang/Object."<init>":()V
       9: return

  public void run();
    Code:
       0: iconst_0
       1: istore_1
       2: iload_1
       3: sipush        5000
       6: if_icmpge     46
       9: aload_0
      10: getfield      #1                  // Field this$0:Lorg/apache/hadoop/hbase/types/TestCopyOnWriteMaps;
      13: invokestatic  #3                  // Method org/apache/hadoop/hbase/types/TestCopyOnWriteMaps.access$000:(Lorg/apache/hadoop/hbase/types/TestCopyOnWriteMaps;)Ljava/util/concurrent/ConcurrentNavigableMap;
      16: invokestatic  #4                  // Method java/util/concurrent/ThreadLocalRandom.current:()Ljava/util/concurrent/ThreadLocalRandom;
      19: invokevirtual #5                  // Method java/util/concurrent/ThreadLocalRandom.nextLong:()J
      22: invokestatic  #6                  // Method java/lang/Long.valueOf:(J)Ljava/lang/Long;
      25: invokestatic  #4                  // Method java/util/concurrent/ThreadLocalRandom.current:()Ljava/util/concurrent/ThreadLocalRandom;
      28: invokevirtual #5                  // Method java/util/concurrent/ThreadLocalRandom.nextLong:()J
      31: invokestatic  #6                  // Method java/lang/Long.valueOf:(J)Ljava/lang/Long;
      34: invokeinterface #7,  3            // InterfaceMethod java/util/concurrent/ConcurrentNavigableMap.put:(Ljava/lang/Object;Ljava/lang/Object;)Ljava/lang/Object;
      39: pop
      40: iinc          1, 1
      43: goto          2
      46: return
}
