Compiled from "TestConcatenatedLists.java"
public class org.apache.hadoop.hbase.util.TestConcatenatedLists {
  public static final org.apache.hadoop.hbase.HBaseClassTestRule CLASS_RULE;

  public org.apache.hadoop.hbase.util.TestConcatenatedLists();
    Code:
       0: aload_0
       1: invokespecial #1                  // Method java/lang/Object."<init>":()V
       4: return

  public void testUnsupportedOps();
    Code:
       0: new           #2                  // class org/apache/hadoop/hbase/util/ConcatenatedLists
       3: dup
       4: invokespecial #3                  // Method org/apache/hadoop/hbase/util/ConcatenatedLists."<init>":()V
       7: astore_1
       8: aload_1
       9: iconst_2
      10: anewarray     #4                  // class java/lang/Long
      13: dup
      14: iconst_0
      15: lconst_0
      16: invokestatic  #5                  // Method java/lang/Long.valueOf:(J)Ljava/lang/Long;
      19: aastore
      20: dup
      21: iconst_1
      22: lconst_1
      23: invokestatic  #5                  // Method java/lang/Long.valueOf:(J)Ljava/lang/Long;
      26: aastore
      27: invokestatic  #6                  // Method java/util/Arrays.asList:([Ljava/lang/Object;)Ljava/util/List;
      30: invokevirtual #7                  // Method org/apache/hadoop/hbase/util/ConcatenatedLists.addSublist:(Ljava/util/List;)V
      33: aload_1
      34: ldc2_w        #8                  // long 2l
      37: invokestatic  #5                  // Method java/lang/Long.valueOf:(J)Ljava/lang/Long;
      40: invokevirtual #10                 // Method org/apache/hadoop/hbase/util/ConcatenatedLists.add:(Ljava/lang/Object;)Z
      43: pop
      44: ldc           #11                 // String Should throw
      46: invokestatic  #12                 // Method org/junit/Assert.fail:(Ljava/lang/String;)V
      49: goto          53
      52: astore_2
      53: aload_1
      54: iconst_2
      55: anewarray     #4                  // class java/lang/Long
      58: dup
      59: iconst_0
      60: ldc2_w        #8                  // long 2l
      63: invokestatic  #5                  // Method java/lang/Long.valueOf:(J)Ljava/lang/Long;
      66: aastore
      67: dup
      68: iconst_1
      69: ldc2_w        #14                 // long 3l
      72: invokestatic  #5                  // Method java/lang/Long.valueOf:(J)Ljava/lang/Long;
      75: aastore
      76: invokestatic  #6                  // Method java/util/Arrays.asList:([Ljava/lang/Object;)Ljava/util/List;
      79: invokevirtual #16                 // Method org/apache/hadoop/hbase/util/ConcatenatedLists.addAll:(Ljava/util/Collection;)Z
      82: pop
      83: ldc           #11                 // String Should throw
      85: invokestatic  #12                 // Method org/junit/Assert.fail:(Ljava/lang/String;)V
      88: goto          92
      91: astore_2
      92: aload_1
      93: lconst_0
      94: invokestatic  #5                  // Method java/lang/Long.valueOf:(J)Ljava/lang/Long;
      97: invokevirtual #17                 // Method org/apache/hadoop/hbase/util/ConcatenatedLists.remove:(Ljava/lang/Object;)Z
     100: pop
     101: ldc           #11                 // String Should throw
     103: invokestatic  #12                 // Method org/junit/Assert.fail:(Ljava/lang/String;)V
     106: goto          110
     109: astore_2
     110: aload_1
     111: iconst_2
     112: anewarray     #4                  // class java/lang/Long
     115: dup
     116: iconst_0
     117: lconst_0
     118: invokestatic  #5                  // Method java/lang/Long.valueOf:(J)Ljava/lang/Long;
     121: aastore
     122: dup
     123: iconst_1
     124: lconst_1
     125: invokestatic  #5                  // Method java/lang/Long.valueOf:(J)Ljava/lang/Long;
     128: aastore
     129: invokestatic  #6                  // Method java/util/Arrays.asList:([Ljava/lang/Object;)Ljava/util/List;
     132: invokevirtual #18                 // Method org/apache/hadoop/hbase/util/ConcatenatedLists.removeAll:(Ljava/util/Collection;)Z
     135: pop
     136: ldc           #11                 // String Should throw
     138: invokestatic  #12                 // Method org/junit/Assert.fail:(Ljava/lang/String;)V
     141: goto          145
     144: astore_2
     145: aload_1
     146: invokevirtual #19                 // Method org/apache/hadoop/hbase/util/ConcatenatedLists.clear:()V
     149: ldc           #11                 // String Should throw
     151: invokestatic  #12                 // Method org/junit/Assert.fail:(Ljava/lang/String;)V
     154: goto          158
     157: astore_2
     158: aload_1
     159: iconst_2
     160: anewarray     #4                  // class java/lang/Long
     163: dup
     164: iconst_0
     165: lconst_0
     166: invokestatic  #5                  // Method java/lang/Long.valueOf:(J)Ljava/lang/Long;
     169: aastore
     170: dup
     171: iconst_1
     172: ldc2_w        #8                  // long 2l
     175: invokestatic  #5                  // Method java/lang/Long.valueOf:(J)Ljava/lang/Long;
     178: aastore
     179: invokestatic  #6                  // Method java/util/Arrays.asList:([Ljava/lang/Object;)Ljava/util/List;
     182: invokevirtual #20                 // Method org/apache/hadoop/hbase/util/ConcatenatedLists.retainAll:(Ljava/util/Collection;)Z
     185: pop
     186: ldc           #11                 // String Should throw
     188: invokestatic  #12                 // Method org/junit/Assert.fail:(Ljava/lang/String;)V
     191: goto          195
     194: astore_2
     195: aload_1
     196: invokevirtual #21                 // Method org/apache/hadoop/hbase/util/ConcatenatedLists.iterator:()Ljava/util/Iterator;
     199: astore_2
     200: aload_2
     201: invokeinterface #22,  1           // InterfaceMethod java/util/Iterator.next:()Ljava/lang/Object;
     206: pop
     207: aload_2
     208: invokeinterface #23,  1           // InterfaceMethod java/util/Iterator.remove:()V
     213: ldc           #11                 // String Should throw
     215: invokestatic  #12                 // Method org/junit/Assert.fail:(Ljava/lang/String;)V
     218: goto          222
     221: astore_3
     222: return
    Exception table:
       from    to  target type
          33    49    52   Class java/lang/UnsupportedOperationException
          53    88    91   Class java/lang/UnsupportedOperationException
          92   106   109   Class java/lang/UnsupportedOperationException
         110   141   144   Class java/lang/UnsupportedOperationException
         145   154   157   Class java/lang/UnsupportedOperationException
         158   191   194   Class java/lang/UnsupportedOperationException
         207   218   221   Class java/lang/UnsupportedOperationException

  public void testEmpty();
    Code:
       0: aload_0
       1: new           #2                  // class org/apache/hadoop/hbase/util/ConcatenatedLists
       4: dup
       5: invokespecial #3                  // Method org/apache/hadoop/hbase/util/ConcatenatedLists."<init>":()V
       8: iconst_m1
       9: invokespecial #24                 // Method verify:(Lorg/apache/hadoop/hbase/util/ConcatenatedLists;I)V
      12: return

  public void testOneOne();
    Code:
       0: new           #2                  // class org/apache/hadoop/hbase/util/ConcatenatedLists
       3: dup
       4: invokespecial #3                  // Method org/apache/hadoop/hbase/util/ConcatenatedLists."<init>":()V
       7: astore_1
       8: aload_1
       9: iconst_1
      10: anewarray     #4                  // class java/lang/Long
      13: dup
      14: iconst_0
      15: lconst_0
      16: invokestatic  #5                  // Method java/lang/Long.valueOf:(J)Ljava/lang/Long;
      19: aastore
      20: invokestatic  #6                  // Method java/util/Arrays.asList:([Ljava/lang/Object;)Ljava/util/List;
      23: invokevirtual #7                  // Method org/apache/hadoop/hbase/util/ConcatenatedLists.addSublist:(Ljava/util/List;)V
      26: aload_0
      27: aload_1
      28: iconst_0
      29: invokespecial #24                 // Method verify:(Lorg/apache/hadoop/hbase/util/ConcatenatedLists;I)V
      32: return

  public void testOneMany();
    Code:
       0: new           #2                  // class org/apache/hadoop/hbase/util/ConcatenatedLists
       3: dup
       4: invokespecial #3                  // Method org/apache/hadoop/hbase/util/ConcatenatedLists."<init>":()V
       7: astore_1
       8: aload_1
       9: iconst_3
      10: anewarray     #4                  // class java/lang/Long
      13: dup
      14: iconst_0
      15: lconst_0
      16: invokestatic  #5                  // Method java/lang/Long.valueOf:(J)Ljava/lang/Long;
      19: aastore
      20: dup
      21: iconst_1
      22: lconst_1
      23: invokestatic  #5                  // Method java/lang/Long.valueOf:(J)Ljava/lang/Long;
      26: aastore
      27: dup
      28: iconst_2
      29: ldc2_w        #8                  // long 2l
      32: invokestatic  #5                  // Method java/lang/Long.valueOf:(J)Ljava/lang/Long;
      35: aastore
      36: invokestatic  #6                  // Method java/util/Arrays.asList:([Ljava/lang/Object;)Ljava/util/List;
      39: invokevirtual #7                  // Method org/apache/hadoop/hbase/util/ConcatenatedLists.addSublist:(Ljava/util/List;)V
      42: aload_0
      43: aload_1
      44: iconst_2
      45: invokespecial #24                 // Method verify:(Lorg/apache/hadoop/hbase/util/ConcatenatedLists;I)V
      48: return

  public void testManyOne();
    Code:
       0: new           #2                  // class org/apache/hadoop/hbase/util/ConcatenatedLists
       3: dup
       4: invokespecial #3                  // Method org/apache/hadoop/hbase/util/ConcatenatedLists."<init>":()V
       7: astore_1
       8: aload_1
       9: iconst_1
      10: anewarray     #4                  // class java/lang/Long
      13: dup
      14: iconst_0
      15: lconst_0
      16: invokestatic  #5                  // Method java/lang/Long.valueOf:(J)Ljava/lang/Long;
      19: aastore
      20: invokestatic  #6                  // Method java/util/Arrays.asList:([Ljava/lang/Object;)Ljava/util/List;
      23: invokevirtual #7                  // Method org/apache/hadoop/hbase/util/ConcatenatedLists.addSublist:(Ljava/util/List;)V
      26: aload_1
      27: iconst_2
      28: anewarray     #25                 // class java/util/List
      31: dup
      32: iconst_0
      33: iconst_1
      34: anewarray     #4                  // class java/lang/Long
      37: dup
      38: iconst_0
      39: lconst_1
      40: invokestatic  #5                  // Method java/lang/Long.valueOf:(J)Ljava/lang/Long;
      43: aastore
      44: invokestatic  #6                  // Method java/util/Arrays.asList:([Ljava/lang/Object;)Ljava/util/List;
      47: aastore
      48: dup
      49: iconst_1
      50: iconst_1
      51: anewarray     #4                  // class java/lang/Long
      54: dup
      55: iconst_0
      56: ldc2_w        #8                  // long 2l
      59: invokestatic  #5                  // Method java/lang/Long.valueOf:(J)Ljava/lang/Long;
      62: aastore
      63: invokestatic  #6                  // Method java/util/Arrays.asList:([Ljava/lang/Object;)Ljava/util/List;
      66: aastore
      67: invokestatic  #6                  // Method java/util/Arrays.asList:([Ljava/lang/Object;)Ljava/util/List;
      70: invokevirtual #26                 // Method org/apache/hadoop/hbase/util/ConcatenatedLists.addAllSublists:(Ljava/util/List;)V
      73: aload_0
      74: aload_1
      75: iconst_2
      76: invokespecial #24                 // Method verify:(Lorg/apache/hadoop/hbase/util/ConcatenatedLists;I)V
      79: return

  public void testManyMany();
    Code:
       0: new           #2                  // class org/apache/hadoop/hbase/util/ConcatenatedLists
       3: dup
       4: invokespecial #3                  // Method org/apache/hadoop/hbase/util/ConcatenatedLists."<init>":()V
       7: astore_1
       8: aload_1
       9: iconst_1
      10: anewarray     #25                 // class java/util/List
      13: dup
      14: iconst_0
      15: iconst_2
      16: anewarray     #4                  // class java/lang/Long
      19: dup
      20: iconst_0
      21: lconst_0
      22: invokestatic  #5                  // Method java/lang/Long.valueOf:(J)Ljava/lang/Long;
      25: aastore
      26: dup
      27: iconst_1
      28: lconst_1
      29: invokestatic  #5                  // Method java/lang/Long.valueOf:(J)Ljava/lang/Long;
      32: aastore
      33: invokestatic  #6                  // Method java/util/Arrays.asList:([Ljava/lang/Object;)Ljava/util/List;
      36: aastore
      37: invokestatic  #6                  // Method java/util/Arrays.asList:([Ljava/lang/Object;)Ljava/util/List;
      40: invokevirtual #26                 // Method org/apache/hadoop/hbase/util/ConcatenatedLists.addAllSublists:(Ljava/util/List;)V
      43: aload_1
      44: iconst_3
      45: anewarray     #4                  // class java/lang/Long
      48: dup
      49: iconst_0
      50: ldc2_w        #8                  // long 2l
      53: invokestatic  #5                  // Method java/lang/Long.valueOf:(J)Ljava/lang/Long;
      56: aastore
      57: dup
      58: iconst_1
      59: ldc2_w        #14                 // long 3l
      62: invokestatic  #5                  // Method java/lang/Long.valueOf:(J)Ljava/lang/Long;
      65: aastore
      66: dup
      67: iconst_2
      68: ldc2_w        #27                 // long 4l
      71: invokestatic  #5                  // Method java/lang/Long.valueOf:(J)Ljava/lang/Long;
      74: aastore
      75: invokestatic  #6                  // Method java/util/Arrays.asList:([Ljava/lang/Object;)Ljava/util/List;
      78: invokevirtual #7                  // Method org/apache/hadoop/hbase/util/ConcatenatedLists.addSublist:(Ljava/util/List;)V
      81: aload_1
      82: iconst_2
      83: anewarray     #25                 // class java/util/List
      86: dup
      87: iconst_0
      88: iconst_1
      89: anewarray     #4                  // class java/lang/Long
      92: dup
      93: iconst_0
      94: ldc2_w        #29                 // long 5l
      97: invokestatic  #5                  // Method java/lang/Long.valueOf:(J)Ljava/lang/Long;
     100: aastore
     101: invokestatic  #6                  // Method java/util/Arrays.asList:([Ljava/lang/Object;)Ljava/util/List;
     104: aastore
     105: dup
     106: iconst_1
     107: iconst_2
     108: anewarray     #4                  // class java/lang/Long
     111: dup
     112: iconst_0
     113: ldc2_w        #31                 // long 6l
     116: invokestatic  #5                  // Method java/lang/Long.valueOf:(J)Ljava/lang/Long;
     119: aastore
     120: dup
     121: iconst_1
     122: ldc2_w        #33                 // long 7l
     125: invokestatic  #5                  // Method java/lang/Long.valueOf:(J)Ljava/lang/Long;
     128: aastore
     129: invokestatic  #6                  // Method java/util/Arrays.asList:([Ljava/lang/Object;)Ljava/util/List;
     132: aastore
     133: invokestatic  #6                  // Method java/util/Arrays.asList:([Ljava/lang/Object;)Ljava/util/List;
     136: invokevirtual #26                 // Method org/apache/hadoop/hbase/util/ConcatenatedLists.addAllSublists:(Ljava/util/List;)V
     139: aload_0
     140: aload_1
     141: bipush        7
     143: invokespecial #24                 // Method verify:(Lorg/apache/hadoop/hbase/util/ConcatenatedLists;I)V
     146: return

  static {};
    Code:
       0: ldc           #54                 // class org/apache/hadoop/hbase/util/TestConcatenatedLists
       2: invokestatic  #55                 // Method org/apache/hadoop/hbase/HBaseClassTestRule.forClass:(Ljava/lang/Class;)Lorg/apache/hadoop/hbase/HBaseClassTestRule;
       5: putstatic     #56                 // Field CLASS_RULE:Lorg/apache/hadoop/hbase/HBaseClassTestRule;
       8: return
}
