Compiled from "TestSnapshotFileCache.java"
public class org.apache.hadoop.hbase.master.snapshot.TestSnapshotFileCache {
  public static final org.apache.hadoop.hbase.HBaseClassTestRule CLASS_RULE;

  public org.apache.hadoop.hbase.master.snapshot.TestSnapshotFileCache();
    Code:
       0: aload_0
       1: invokespecial #4                  // Method java/lang/Object."<init>":()V
       4: return

  public static void startCluster() throws java.lang.Exception;
    Code:
       0: getstatic     #3                  // Field UTIL:Lorg/apache/hadoop/hbase/HBaseTestingUtility;
       3: iconst_1
       4: invokevirtual #5                  // Method org/apache/hadoop/hbase/HBaseTestingUtility.startMiniDFSCluster:(I)Lorg/apache/hadoop/hdfs/MiniDFSCluster;
       7: pop
       8: getstatic     #3                  // Field UTIL:Lorg/apache/hadoop/hbase/HBaseTestingUtility;
      11: invokevirtual #6                  // Method org/apache/hadoop/hbase/HBaseTestingUtility.getDFSCluster:()Lorg/apache/hadoop/hdfs/MiniDFSCluster;
      14: invokevirtual #7                  // Method org/apache/hadoop/hdfs/MiniDFSCluster.getFileSystem:()Lorg/apache/hadoop/hdfs/DistributedFileSystem;
      17: putstatic     #2                  // Field fs:Lorg/apache/hadoop/fs/FileSystem;
      20: getstatic     #3                  // Field UTIL:Lorg/apache/hadoop/hbase/HBaseTestingUtility;
      23: invokevirtual #8                  // Method org/apache/hadoop/hbase/HBaseTestingUtility.getDefaultRootDirPath:()Lorg/apache/hadoop/fs/Path;
      26: putstatic     #9                  // Field rootDir:Lorg/apache/hadoop/fs/Path;
      29: getstatic     #9                  // Field rootDir:Lorg/apache/hadoop/fs/Path;
      32: invokestatic  #10                 // Method org/apache/hadoop/hbase/snapshot/SnapshotDescriptionUtils.getSnapshotsDir:(Lorg/apache/hadoop/fs/Path;)Lorg/apache/hadoop/fs/Path;
      35: putstatic     #11                 // Field snapshotDir:Lorg/apache/hadoop/fs/Path;
      38: return

  public static void stopCluster() throws java.lang.Exception;
    Code:
       0: getstatic     #3                  // Field UTIL:Lorg/apache/hadoop/hbase/HBaseTestingUtility;
       3: invokevirtual #12                 // Method org/apache/hadoop/hbase/HBaseTestingUtility.shutdownMiniDFSCluster:()V
       6: return

  public void cleanupFiles() throws java.lang.Exception;
    Code:
       0: getstatic     #2                  // Field fs:Lorg/apache/hadoop/fs/FileSystem;
       3: getstatic     #11                 // Field snapshotDir:Lorg/apache/hadoop/fs/Path;
       6: iconst_1
       7: invokevirtual #13                 // Method org/apache/hadoop/fs/FileSystem.delete:(Lorg/apache/hadoop/fs/Path;Z)Z
      10: pop
      11: return

  public void testLoadAndDelete() throws java.io.IOException;
    Code:
       0: new           #14                 // class org/apache/hadoop/hbase/master/snapshot/SnapshotFileCache
       3: dup
       4: getstatic     #2                  // Field fs:Lorg/apache/hadoop/fs/FileSystem;
       7: getstatic     #9                  // Field rootDir:Lorg/apache/hadoop/fs/Path;
      10: ldc2_w        #16                 // long 9223372036854775807l
      13: ldc2_w        #18                 // long 10000000l
      16: ldc           #20                 // String test-snapshot-file-cache-refresh
      18: new           #21                 // class org/apache/hadoop/hbase/master/snapshot/TestSnapshotFileCache$SnapshotFiles
      21: dup
      22: aload_0
      23: invokespecial #22                 // Method org/apache/hadoop/hbase/master/snapshot/TestSnapshotFileCache$SnapshotFiles."<init>":(Lorg/apache/hadoop/hbase/master/snapshot/TestSnapshotFileCache;)V
      26: invokespecial #23                 // Method org/apache/hadoop/hbase/master/snapshot/SnapshotFileCache."<init>":(Lorg/apache/hadoop/fs/FileSystem;Lorg/apache/hadoop/fs/Path;JJLjava/lang/String;Lorg/apache/hadoop/hbase/master/snapshot/SnapshotFileCache$SnapshotFileInspector;)V
      29: astore_1
      30: aload_0
      31: aload_1
      32: ldc           #24                 // String snapshot1a
      34: iconst_0
      35: iconst_1
      36: iconst_0
      37: invokespecial #25                 // Method createAndTestSnapshotV1:(Lorg/apache/hadoop/hbase/master/snapshot/SnapshotFileCache;Ljava/lang/String;ZZZ)Lorg/apache/hadoop/hbase/snapshot/SnapshotTestingUtils$SnapshotMock$SnapshotBuilder;
      40: pop
      41: aload_0
      42: aload_1
      43: ldc           #26                 // String snapshot2a
      45: iconst_0
      46: iconst_1
      47: iconst_0
      48: invokespecial #27                 // Method createAndTestSnapshotV2:(Lorg/apache/hadoop/hbase/master/snapshot/SnapshotFileCache;Ljava/lang/String;ZZZ)V
      51: return

  public void testReloadModifiedDirectory() throws java.io.IOException;
    Code:
       0: new           #14                 // class org/apache/hadoop/hbase/master/snapshot/SnapshotFileCache
       3: dup
       4: getstatic     #2                  // Field fs:Lorg/apache/hadoop/fs/FileSystem;
       7: getstatic     #9                  // Field rootDir:Lorg/apache/hadoop/fs/Path;
      10: ldc2_w        #16                 // long 9223372036854775807l
      13: ldc2_w        #18                 // long 10000000l
      16: ldc           #20                 // String test-snapshot-file-cache-refresh
      18: new           #21                 // class org/apache/hadoop/hbase/master/snapshot/TestSnapshotFileCache$SnapshotFiles
      21: dup
      22: aload_0
      23: invokespecial #22                 // Method org/apache/hadoop/hbase/master/snapshot/TestSnapshotFileCache$SnapshotFiles."<init>":(Lorg/apache/hadoop/hbase/master/snapshot/TestSnapshotFileCache;)V
      26: invokespecial #23                 // Method org/apache/hadoop/hbase/master/snapshot/SnapshotFileCache."<init>":(Lorg/apache/hadoop/fs/FileSystem;Lorg/apache/hadoop/fs/Path;JJLjava/lang/String;Lorg/apache/hadoop/hbase/master/snapshot/SnapshotFileCache$SnapshotFileInspector;)V
      29: astore_1
      30: aload_0
      31: aload_1
      32: ldc           #28                 // String snapshot1
      34: iconst_0
      35: iconst_1
      36: iconst_0
      37: invokespecial #25                 // Method createAndTestSnapshotV1:(Lorg/apache/hadoop/hbase/master/snapshot/SnapshotFileCache;Ljava/lang/String;ZZZ)Lorg/apache/hadoop/hbase/snapshot/SnapshotTestingUtils$SnapshotMock$SnapshotBuilder;
      40: pop
      41: aload_0
      42: aload_1
      43: ldc           #28                 // String snapshot1
      45: iconst_0
      46: iconst_0
      47: iconst_0
      48: invokespecial #25                 // Method createAndTestSnapshotV1:(Lorg/apache/hadoop/hbase/master/snapshot/SnapshotFileCache;Ljava/lang/String;ZZZ)Lorg/apache/hadoop/hbase/snapshot/SnapshotTestingUtils$SnapshotMock$SnapshotBuilder;
      51: pop
      52: aload_0
      53: aload_1
      54: ldc           #29                 // String snapshot2
      56: iconst_0
      57: iconst_1
      58: iconst_0
      59: invokespecial #27                 // Method createAndTestSnapshotV2:(Lorg/apache/hadoop/hbase/master/snapshot/SnapshotFileCache;Ljava/lang/String;ZZZ)V
      62: aload_0
      63: aload_1
      64: ldc           #29                 // String snapshot2
      66: iconst_0
      67: iconst_0
      68: iconst_0
      69: invokespecial #27                 // Method createAndTestSnapshotV2:(Lorg/apache/hadoop/hbase/master/snapshot/SnapshotFileCache;Ljava/lang/String;ZZZ)V
      72: return

  public void testSnapshotTempDirReload() throws java.io.IOException;
    Code:
       0: new           #14                 // class org/apache/hadoop/hbase/master/snapshot/SnapshotFileCache
       3: dup
       4: getstatic     #2                  // Field fs:Lorg/apache/hadoop/fs/FileSystem;
       7: getstatic     #9                  // Field rootDir:Lorg/apache/hadoop/fs/Path;
      10: ldc2_w        #16                 // long 9223372036854775807l
      13: ldc2_w        #18                 // long 10000000l
      16: ldc           #20                 // String test-snapshot-file-cache-refresh
      18: new           #21                 // class org/apache/hadoop/hbase/master/snapshot/TestSnapshotFileCache$SnapshotFiles
      21: dup
      22: aload_0
      23: invokespecial #22                 // Method org/apache/hadoop/hbase/master/snapshot/TestSnapshotFileCache$SnapshotFiles."<init>":(Lorg/apache/hadoop/hbase/master/snapshot/TestSnapshotFileCache;)V
      26: invokespecial #23                 // Method org/apache/hadoop/hbase/master/snapshot/SnapshotFileCache."<init>":(Lorg/apache/hadoop/fs/FileSystem;Lorg/apache/hadoop/fs/Path;JJLjava/lang/String;Lorg/apache/hadoop/hbase/master/snapshot/SnapshotFileCache$SnapshotFileInspector;)V
      29: astore_1
      30: aload_0
      31: aload_1
      32: ldc           #30                 // String snapshot0v1
      34: iconst_0
      35: iconst_0
      36: iconst_0
      37: invokespecial #25                 // Method createAndTestSnapshotV1:(Lorg/apache/hadoop/hbase/master/snapshot/SnapshotFileCache;Ljava/lang/String;ZZZ)Lorg/apache/hadoop/hbase/snapshot/SnapshotTestingUtils$SnapshotMock$SnapshotBuilder;
      40: pop
      41: aload_0
      42: aload_1
      43: ldc           #31                 // String snapshot0v2
      45: iconst_0
      46: iconst_0
      47: iconst_0
      48: invokespecial #25                 // Method createAndTestSnapshotV1:(Lorg/apache/hadoop/hbase/master/snapshot/SnapshotFileCache;Ljava/lang/String;ZZZ)Lorg/apache/hadoop/hbase/snapshot/SnapshotTestingUtils$SnapshotMock$SnapshotBuilder;
      51: pop
      52: return

  public void testCacheUpdatedWhenLastModifiedOfSnapDirNotUpdated() throws java.io.IOException;
    Code:
       0: new           #14                 // class org/apache/hadoop/hbase/master/snapshot/SnapshotFileCache
       3: dup
       4: getstatic     #2                  // Field fs:Lorg/apache/hadoop/fs/FileSystem;
       7: getstatic     #9                  // Field rootDir:Lorg/apache/hadoop/fs/Path;
      10: ldc2_w        #16                 // long 9223372036854775807l
      13: ldc2_w        #18                 // long 10000000l
      16: ldc           #20                 // String test-snapshot-file-cache-refresh
      18: new           #21                 // class org/apache/hadoop/hbase/master/snapshot/TestSnapshotFileCache$SnapshotFiles
      21: dup
      22: aload_0
      23: invokespecial #22                 // Method org/apache/hadoop/hbase/master/snapshot/TestSnapshotFileCache$SnapshotFiles."<init>":(Lorg/apache/hadoop/hbase/master/snapshot/TestSnapshotFileCache;)V
      26: invokespecial #23                 // Method org/apache/hadoop/hbase/master/snapshot/SnapshotFileCache."<init>":(Lorg/apache/hadoop/fs/FileSystem;Lorg/apache/hadoop/fs/Path;JJLjava/lang/String;Lorg/apache/hadoop/hbase/master/snapshot/SnapshotFileCache$SnapshotFileInspector;)V
      29: astore_1
      30: aload_0
      31: aload_1
      32: ldc           #32                 // String snapshot1v1
      34: iconst_0
      35: iconst_0
      36: iconst_1
      37: invokespecial #25                 // Method createAndTestSnapshotV1:(Lorg/apache/hadoop/hbase/master/snapshot/SnapshotFileCache;Ljava/lang/String;ZZZ)Lorg/apache/hadoop/hbase/snapshot/SnapshotTestingUtils$SnapshotMock$SnapshotBuilder;
      40: pop
      41: aload_0
      42: aload_1
      43: ldc           #33                 // String snapshot1v2
      45: iconst_0
      46: iconst_0
      47: iconst_1
      48: invokespecial #25                 // Method createAndTestSnapshotV1:(Lorg/apache/hadoop/hbase/master/snapshot/SnapshotFileCache;Ljava/lang/String;ZZZ)Lorg/apache/hadoop/hbase/snapshot/SnapshotTestingUtils$SnapshotMock$SnapshotBuilder;
      51: pop
      52: aload_0
      53: aload_1
      54: ldc           #34                 // String snapshot2v1
      56: iconst_1
      57: iconst_0
      58: iconst_1
      59: invokespecial #27                 // Method createAndTestSnapshotV2:(Lorg/apache/hadoop/hbase/master/snapshot/SnapshotFileCache;Ljava/lang/String;ZZZ)V
      62: aload_0
      63: aload_1
      64: ldc           #35                 // String snapshot2v2
      66: iconst_1
      67: iconst_0
      68: iconst_1
      69: invokespecial #27                 // Method createAndTestSnapshotV2:(Lorg/apache/hadoop/hbase/master/snapshot/SnapshotFileCache;Ljava/lang/String;ZZZ)V
      72: return

  static org.apache.hadoop.hbase.HBaseTestingUtility access$000();
    Code:
       0: getstatic     #3                  // Field UTIL:Lorg/apache/hadoop/hbase/HBaseTestingUtility;
       3: areturn

  static org.apache.hadoop.fs.FileSystem access$100();
    Code:
       0: getstatic     #2                  // Field fs:Lorg/apache/hadoop/fs/FileSystem;
       3: areturn

  static {};
    Code:
       0: ldc           #15                 // class org/apache/hadoop/hbase/master/snapshot/TestSnapshotFileCache
       2: invokestatic  #82                 // Method org/apache/hadoop/hbase/HBaseClassTestRule.forClass:(Ljava/lang/Class;)Lorg/apache/hadoop/hbase/HBaseClassTestRule;
       5: putstatic     #83                 // Field CLASS_RULE:Lorg/apache/hadoop/hbase/HBaseClassTestRule;
       8: ldc           #15                 // class org/apache/hadoop/hbase/master/snapshot/TestSnapshotFileCache
      10: invokestatic  #84                 // Method org/slf4j/LoggerFactory.getLogger:(Ljava/lang/Class;)Lorg/slf4j/Logger;
      13: putstatic     #63                 // Field LOG:Lorg/slf4j/Logger;
      16: new           #85                 // class org/apache/hadoop/hbase/HBaseTestingUtility
      19: dup
      20: invokespecial #86                 // Method org/apache/hadoop/hbase/HBaseTestingUtility."<init>":()V
      23: putstatic     #3                  // Field UTIL:Lorg/apache/hadoop/hbase/HBaseTestingUtility;
      26: return
}
