Compiled from "TestStructNullExtension.java"
public class org.apache.hadoop.hbase.types.TestStructNullExtension {
  public static final org.apache.hadoop.hbase.HBaseClassTestRule CLASS_RULE;

  public org.apache.hadoop.hbase.types.TestStructNullExtension();
    Code:
       0: aload_0
       1: invokespecial #1                  // Method java/lang/Object."<init>":()V
       4: return

  public void testNonNullableNullExtension();
    Code:
       0: new           #2                  // class org/apache/hadoop/hbase/types/StructBuilder
       3: dup
       4: invokespecial #3                  // Method org/apache/hadoop/hbase/types/StructBuilder."<init>":()V
       7: new           #4                  // class org/apache/hadoop/hbase/types/RawStringTerminated
      10: dup
      11: ldc           #5                  // String |
      13: invokespecial #6                  // Method org/apache/hadoop/hbase/types/RawStringTerminated."<init>":(Ljava/lang/String;)V
      16: invokevirtual #7                  // Method org/apache/hadoop/hbase/types/StructBuilder.add:(Lorg/apache/hadoop/hbase/types/DataType;)Lorg/apache/hadoop/hbase/types/StructBuilder;
      19: invokevirtual #8                  // Method org/apache/hadoop/hbase/types/StructBuilder.toStruct:()Lorg/apache/hadoop/hbase/types/Struct;
      22: astore_1
      23: new           #9                  // class org/apache/hadoop/hbase/util/SimplePositionedMutableByteRange
      26: dup
      27: iconst_4
      28: invokespecial #10                 // Method org/apache/hadoop/hbase/util/SimplePositionedMutableByteRange."<init>":(I)V
      31: astore_2
      32: aload_1
      33: aload_2
      34: iconst_1
      35: anewarray     #11                 // class java/lang/Object
      38: invokevirtual #12                 // Method org/apache/hadoop/hbase/types/Struct.encode:(Lorg/apache/hadoop/hbase/util/PositionedByteRange;[Ljava/lang/Object;)I
      41: pop
      42: return

  public void testNullableNullExtension();
    Code:
       0: new           #2                  // class org/apache/hadoop/hbase/types/StructBuilder
       3: dup
       4: invokespecial #3                  // Method org/apache/hadoop/hbase/types/StructBuilder."<init>":()V
       7: getstatic     #13                 // Field org/apache/hadoop/hbase/types/OrderedNumeric.ASCENDING:Lorg/apache/hadoop/hbase/types/OrderedNumeric;
      10: invokevirtual #7                  // Method org/apache/hadoop/hbase/types/StructBuilder.add:(Lorg/apache/hadoop/hbase/types/DataType;)Lorg/apache/hadoop/hbase/types/StructBuilder;
      13: getstatic     #14                 // Field org/apache/hadoop/hbase/types/OrderedString.ASCENDING:Lorg/apache/hadoop/hbase/types/OrderedString;
      16: invokevirtual #7                  // Method org/apache/hadoop/hbase/types/StructBuilder.add:(Lorg/apache/hadoop/hbase/types/DataType;)Lorg/apache/hadoop/hbase/types/StructBuilder;
      19: astore_1
      20: aload_1
      21: invokevirtual #8                  // Method org/apache/hadoop/hbase/types/StructBuilder.toStruct:()Lorg/apache/hadoop/hbase/types/Struct;
      24: astore_2
      25: aload_1
      26: new           #15                 // class org/apache/hadoop/hbase/types/TerminatedWrapper
      29: dup
      30: getstatic     #14                 // Field org/apache/hadoop/hbase/types/OrderedString.ASCENDING:Lorg/apache/hadoop/hbase/types/OrderedString;
      33: ldc           #16                 // String /
      35: invokespecial #17                 // Method org/apache/hadoop/hbase/types/TerminatedWrapper."<init>":(Lorg/apache/hadoop/hbase/types/DataType;Ljava/lang/String;)V
      38: invokevirtual #7                  // Method org/apache/hadoop/hbase/types/StructBuilder.add:(Lorg/apache/hadoop/hbase/types/DataType;)Lorg/apache/hadoop/hbase/types/StructBuilder;
      41: getstatic     #13                 // Field org/apache/hadoop/hbase/types/OrderedNumeric.ASCENDING:Lorg/apache/hadoop/hbase/types/OrderedNumeric;
      44: invokevirtual #7                  // Method org/apache/hadoop/hbase/types/StructBuilder.add:(Lorg/apache/hadoop/hbase/types/DataType;)Lorg/apache/hadoop/hbase/types/StructBuilder;
      47: invokevirtual #8                  // Method org/apache/hadoop/hbase/types/StructBuilder.toStruct:()Lorg/apache/hadoop/hbase/types/Struct;
      50: astore_3
      51: new           #9                  // class org/apache/hadoop/hbase/util/SimplePositionedMutableByteRange
      54: dup
      55: bipush        7
      57: invokespecial #10                 // Method org/apache/hadoop/hbase/util/SimplePositionedMutableByteRange."<init>":(I)V
      60: astore        4
      62: iconst_2
      63: anewarray     #11                 // class java/lang/Object
      66: dup
      67: iconst_0
      68: getstatic     #18                 // Field java/math/BigDecimal.ONE:Ljava/math/BigDecimal;
      71: aastore
      72: dup
      73: iconst_1
      74: ldc           #19                 // String foo
      76: aastore
      77: astore        5
      79: ldc           #20                 // String Encoding shorter value wrote a surprising number of bytes.
      81: aload         4
      83: invokeinterface #21,  1           // InterfaceMethod org/apache/hadoop/hbase/util/PositionedByteRange.getLength:()I
      88: i2l
      89: aload_2
      90: aload         4
      92: aload         5
      94: invokevirtual #12                 // Method org/apache/hadoop/hbase/types/Struct.encode:(Lorg/apache/hadoop/hbase/util/PositionedByteRange;[Ljava/lang/Object;)I
      97: i2l
      98: invokestatic  #22                 // Method org/junit/Assert.assertEquals:(Ljava/lang/String;JJ)V
     101: aload         4
     103: invokeinterface #21,  1           // InterfaceMethod org/apache/hadoop/hbase/util/PositionedByteRange.getLength:()I
     108: istore        6
     110: aload         4
     112: iconst_0
     113: invokeinterface #23,  2           // InterfaceMethod org/apache/hadoop/hbase/util/PositionedByteRange.setPosition:(I)Lorg/apache/hadoop/hbase/util/PositionedByteRange;
     118: pop
     119: aload_3
     120: aload         4
     122: invokevirtual #24                 // Method org/apache/hadoop/hbase/types/Struct.iterator:(Lorg/apache/hadoop/hbase/util/PositionedByteRange;)Lorg/apache/hadoop/hbase/types/StructIterator;
     125: astore        7
     127: aload         7
     129: invokevirtual #25                 // Method org/apache/hadoop/hbase/types/StructIterator.skip:()I
     132: pop
     133: aload         7
     135: invokevirtual #25                 // Method org/apache/hadoop/hbase/types/StructIterator.skip:()I
     138: pop
     139: ldc           #26                 // String Position should be at end. Broken test.
     141: aload         4
     143: invokeinterface #21,  1           // InterfaceMethod org/apache/hadoop/hbase/util/PositionedByteRange.getLength:()I
     148: i2l
     149: aload         4
     151: invokeinterface #27,  1           // InterfaceMethod org/apache/hadoop/hbase/util/PositionedByteRange.getPosition:()I
     156: i2l
     157: invokestatic  #22                 // Method org/junit/Assert.assertEquals:(Ljava/lang/String;JJ)V
     160: ldc           #28                 // String Failed to skip null element with extended struct.
     162: lconst_0
     163: aload         7
     165: invokevirtual #25                 // Method org/apache/hadoop/hbase/types/StructIterator.skip:()I
     168: i2l
     169: invokestatic  #22                 // Method org/junit/Assert.assertEquals:(Ljava/lang/String;JJ)V
     172: ldc           #28                 // String Failed to skip null element with extended struct.
     174: lconst_0
     175: aload         7
     177: invokevirtual #25                 // Method org/apache/hadoop/hbase/types/StructIterator.skip:()I
     180: i2l
     181: invokestatic  #22                 // Method org/junit/Assert.assertEquals:(Ljava/lang/String;JJ)V
     184: aload         4
     186: iconst_0
     187: invokeinterface #23,  2           // InterfaceMethod org/apache/hadoop/hbase/util/PositionedByteRange.setPosition:(I)Lorg/apache/hadoop/hbase/util/PositionedByteRange;
     192: pop
     193: aload_3
     194: aload         4
     196: invokevirtual #24                 // Method org/apache/hadoop/hbase/types/Struct.iterator:(Lorg/apache/hadoop/hbase/util/PositionedByteRange;)Lorg/apache/hadoop/hbase/types/StructIterator;
     199: astore        7
     201: getstatic     #18                 // Field java/math/BigDecimal.ONE:Ljava/math/BigDecimal;
     204: aload         7
     206: invokevirtual #29                 // Method org/apache/hadoop/hbase/types/StructIterator.next:()Ljava/lang/Object;
     209: invokestatic  #30                 // Method org/junit/Assert.assertEquals:(Ljava/lang/Object;Ljava/lang/Object;)V
     212: ldc           #19                 // String foo
     214: aload         7
     216: invokevirtual #29                 // Method org/apache/hadoop/hbase/types/StructIterator.next:()Ljava/lang/Object;
     219: invokestatic  #30                 // Method org/junit/Assert.assertEquals:(Ljava/lang/Object;Ljava/lang/Object;)V
     222: ldc           #26                 // String Position should be at end. Broken test.
     224: aload         4
     226: invokeinterface #21,  1           // InterfaceMethod org/apache/hadoop/hbase/util/PositionedByteRange.getLength:()I
     231: i2l
     232: aload         4
     234: invokeinterface #27,  1           // InterfaceMethod org/apache/hadoop/hbase/util/PositionedByteRange.getPosition:()I
     239: i2l
     240: invokestatic  #22                 // Method org/junit/Assert.assertEquals:(Ljava/lang/String;JJ)V
     243: ldc           #28                 // String Failed to skip null element with extended struct.
     245: aload         7
     247: invokevirtual #29                 // Method org/apache/hadoop/hbase/types/StructIterator.next:()Ljava/lang/Object;
     250: invokestatic  #31                 // Method org/junit/Assert.assertNull:(Ljava/lang/String;Ljava/lang/Object;)V
     253: ldc           #28                 // String Failed to skip null element with extended struct.
     255: aload         7
     257: invokevirtual #29                 // Method org/apache/hadoop/hbase/types/StructIterator.next:()Ljava/lang/Object;
     260: invokestatic  #31                 // Method org/junit/Assert.assertNull:(Ljava/lang/String;Ljava/lang/Object;)V
     263: aload         4
     265: iconst_0
     266: invokeinterface #23,  2           // InterfaceMethod org/apache/hadoop/hbase/util/PositionedByteRange.setPosition:(I)Lorg/apache/hadoop/hbase/util/PositionedByteRange;
     271: pop
     272: ldc           #32                 // String Simple struct decoding is broken.
     274: aload         5
     276: aload_2
     277: aload         4
     279: invokevirtual #33                 // Method org/apache/hadoop/hbase/types/Struct.decode:(Lorg/apache/hadoop/hbase/util/PositionedByteRange;)[Ljava/lang/Object;
     282: invokestatic  #34                 // Method org/junit/Assert.assertArrayEquals:(Ljava/lang/String;[Ljava/lang/Object;[Ljava/lang/Object;)V
     285: aload         4
     287: iconst_0
     288: invokeinterface #23,  2           // InterfaceMethod org/apache/hadoop/hbase/util/PositionedByteRange.setPosition:(I)Lorg/apache/hadoop/hbase/util/PositionedByteRange;
     293: pop
     294: ldc           #35                 // String Decoding short value with extended struct should append null elements.
     296: aload         5
     298: iconst_4
     299: invokestatic  #36                 // Method java/util/Arrays.copyOf:([Ljava/lang/Object;I)[Ljava/lang/Object;
     302: aload_3
     303: aload         4
     305: invokevirtual #33                 // Method org/apache/hadoop/hbase/types/Struct.decode:(Lorg/apache/hadoop/hbase/util/PositionedByteRange;)[Ljava/lang/Object;
     308: invokestatic  #34                 // Method org/junit/Assert.assertArrayEquals:(Ljava/lang/String;[Ljava/lang/Object;[Ljava/lang/Object;)V
     311: new           #9                  // class org/apache/hadoop/hbase/util/SimplePositionedMutableByteRange
     314: dup
     315: bipush        7
     317: invokespecial #10                 // Method org/apache/hadoop/hbase/util/SimplePositionedMutableByteRange."<init>":(I)V
     320: astore        8
     322: aload         4
     324: iconst_0
     325: invokeinterface #23,  2           // InterfaceMethod org/apache/hadoop/hbase/util/PositionedByteRange.setPosition:(I)Lorg/apache/hadoop/hbase/util/PositionedByteRange;
     330: pop
     331: ldc           #37                 // String Encoding a short value with extended struct should have same result as using short struct.
     333: iload         6
     335: i2l
     336: aload_3
     337: aload         8
     339: aload         5
     341: invokevirtual #12                 // Method org/apache/hadoop/hbase/types/Struct.encode:(Lorg/apache/hadoop/hbase/util/PositionedByteRange;[Ljava/lang/Object;)I
     344: i2l
     345: invokestatic  #22                 // Method org/junit/Assert.assertEquals:(Ljava/lang/String;JJ)V
     348: ldc           #38                 // String Encoding a short value with extended struct should have same result as using short struct
     350: aload         4
     352: invokeinterface #39,  1           // InterfaceMethod org/apache/hadoop/hbase/util/PositionedByteRange.getBytes:()[B
     357: aload         8
     359: invokeinterface #39,  1           // InterfaceMethod org/apache/hadoop/hbase/util/PositionedByteRange.getBytes:()[B
     364: invokestatic  #40                 // Method org/junit/Assert.assertArrayEquals:(Ljava/lang/String;[B[B)V
     367: iconst_4
     368: anewarray     #11                 // class java/lang/Object
     371: dup
     372: iconst_0
     373: aconst_null
     374: aastore
     375: dup
     376: iconst_1
     377: aconst_null
     378: aastore
     379: dup
     380: iconst_2
     381: aconst_null
     382: aastore
     383: dup
     384: iconst_3
     385: aconst_null
     386: aastore
     387: astore        5
     389: aload         4
     391: iconst_0
     392: invokeinterface #41,  2           // InterfaceMethod org/apache/hadoop/hbase/util/PositionedByteRange.set:(I)Lorg/apache/hadoop/hbase/util/PositionedByteRange;
     397: pop
     398: aload         8
     400: iconst_0
     401: invokeinterface #41,  2           // InterfaceMethod org/apache/hadoop/hbase/util/PositionedByteRange.set:(I)Lorg/apache/hadoop/hbase/util/PositionedByteRange;
     406: pop
     407: ldc           #42                 // String Encoding null-truncated value wrote a surprising number of bytes.
     409: aload         4
     411: invokeinterface #21,  1           // InterfaceMethod org/apache/hadoop/hbase/util/PositionedByteRange.getLength:()I
     416: i2l
     417: aload_3
     418: aload         4
     420: iconst_0
     421: anewarray     #11                 // class java/lang/Object
     424: invokevirtual #12                 // Method org/apache/hadoop/hbase/types/Struct.encode:(Lorg/apache/hadoop/hbase/util/PositionedByteRange;[Ljava/lang/Object;)I
     427: i2l
     428: invokestatic  #22                 // Method org/junit/Assert.assertEquals:(Ljava/lang/String;JJ)V
     431: ldc           #43                 // String Encoding null-extended value wrote a surprising number of bytes.
     433: aload         4
     435: invokeinterface #21,  1           // InterfaceMethod org/apache/hadoop/hbase/util/PositionedByteRange.getLength:()I
     440: i2l
     441: aload_3
     442: aload         4
     444: aload         5
     446: invokevirtual #12                 // Method org/apache/hadoop/hbase/types/Struct.encode:(Lorg/apache/hadoop/hbase/util/PositionedByteRange;[Ljava/lang/Object;)I
     449: i2l
     450: invokestatic  #22                 // Method org/junit/Assert.assertEquals:(Ljava/lang/String;JJ)V
     453: ldc           #44                 // String Encoded unexpected result.
     455: aload         4
     457: invokeinterface #39,  1           // InterfaceMethod org/apache/hadoop/hbase/util/PositionedByteRange.getBytes:()[B
     462: aload         8
     464: invokeinterface #39,  1           // InterfaceMethod org/apache/hadoop/hbase/util/PositionedByteRange.getBytes:()[B
     469: invokestatic  #40                 // Method org/junit/Assert.assertArrayEquals:(Ljava/lang/String;[B[B)V
     472: ldc           #45                 // String Decoded unexpected result.
     474: aload         5
     476: aload_3
     477: aload         8
     479: invokevirtual #33                 // Method org/apache/hadoop/hbase/types/Struct.decode:(Lorg/apache/hadoop/hbase/util/PositionedByteRange;)[Ljava/lang/Object;
     482: invokestatic  #34                 // Method org/junit/Assert.assertArrayEquals:(Ljava/lang/String;[Ljava/lang/Object;[Ljava/lang/Object;)V
     485: iconst_4
     486: anewarray     #11                 // class java/lang/Object
     489: dup
     490: iconst_0
     491: getstatic     #18                 // Field java/math/BigDecimal.ONE:Ljava/math/BigDecimal;
     494: aastore
     495: dup
     496: iconst_1
     497: aconst_null
     498: aastore
     499: dup
     500: iconst_2
     501: aconst_null
     502: aastore
     503: dup
     504: iconst_3
     505: aconst_null
     506: aastore
     507: astore        9
     509: aload         4
     511: iconst_2
     512: invokeinterface #41,  2           // InterfaceMethod org/apache/hadoop/hbase/util/PositionedByteRange.set:(I)Lorg/apache/hadoop/hbase/util/PositionedByteRange;
     517: pop
     518: aload         8
     520: iconst_2
     521: invokeinterface #41,  2           // InterfaceMethod org/apache/hadoop/hbase/util/PositionedByteRange.set:(I)Lorg/apache/hadoop/hbase/util/PositionedByteRange;
     526: pop
     527: ldc           #42                 // String Encoding null-truncated value wrote a surprising number of bytes.
     529: aload         4
     531: invokeinterface #21,  1           // InterfaceMethod org/apache/hadoop/hbase/util/PositionedByteRange.getLength:()I
     536: i2l
     537: aload_3
     538: aload         4
     540: aload         9
     542: iconst_1
     543: invokestatic  #36                 // Method java/util/Arrays.copyOf:([Ljava/lang/Object;I)[Ljava/lang/Object;
     546: invokevirtual #12                 // Method org/apache/hadoop/hbase/types/Struct.encode:(Lorg/apache/hadoop/hbase/util/PositionedByteRange;[Ljava/lang/Object;)I
     549: i2l
     550: invokestatic  #22                 // Method org/junit/Assert.assertEquals:(Ljava/lang/String;JJ)V
     553: ldc           #43                 // String Encoding null-extended value wrote a surprising number of bytes.
     555: aload         8
     557: invokeinterface #21,  1           // InterfaceMethod org/apache/hadoop/hbase/util/PositionedByteRange.getLength:()I
     562: i2l
     563: aload_3
     564: aload         8
     566: aload         9
     568: invokevirtual #12                 // Method org/apache/hadoop/hbase/types/Struct.encode:(Lorg/apache/hadoop/hbase/util/PositionedByteRange;[Ljava/lang/Object;)I
     571: i2l
     572: invokestatic  #22                 // Method org/junit/Assert.assertEquals:(Ljava/lang/String;JJ)V
     575: ldc           #44                 // String Encoded unexpected result.
     577: aload         4
     579: invokeinterface #39,  1           // InterfaceMethod org/apache/hadoop/hbase/util/PositionedByteRange.getBytes:()[B
     584: aload         8
     586: invokeinterface #39,  1           // InterfaceMethod org/apache/hadoop/hbase/util/PositionedByteRange.getBytes:()[B
     591: invokestatic  #40                 // Method org/junit/Assert.assertArrayEquals:(Ljava/lang/String;[B[B)V
     594: aload         8
     596: iconst_0
     597: invokeinterface #23,  2           // InterfaceMethod org/apache/hadoop/hbase/util/PositionedByteRange.setPosition:(I)Lorg/apache/hadoop/hbase/util/PositionedByteRange;
     602: pop
     603: ldc           #45                 // String Decoded unexpected result.
     605: aload         9
     607: aload_3
     608: aload         8
     610: invokevirtual #33                 // Method org/apache/hadoop/hbase/types/Struct.decode:(Lorg/apache/hadoop/hbase/util/PositionedByteRange;)[Ljava/lang/Object;
     613: invokestatic  #34                 // Method org/junit/Assert.assertArrayEquals:(Ljava/lang/String;[Ljava/lang/Object;[Ljava/lang/Object;)V
     616: iconst_4
     617: anewarray     #11                 // class java/lang/Object
     620: dup
     621: iconst_0
     622: getstatic     #18                 // Field java/math/BigDecimal.ONE:Ljava/math/BigDecimal;
     625: aastore
     626: dup
     627: iconst_1
     628: aconst_null
     629: aastore
     630: dup
     631: iconst_2
     632: ldc           #19                 // String foo
     634: aastore
     635: dup
     636: iconst_3
     637: aconst_null
     638: aastore
     639: astore        10
     641: aload         4
     643: bipush        9
     645: invokeinterface #41,  2           // InterfaceMethod org/apache/hadoop/hbase/util/PositionedByteRange.set:(I)Lorg/apache/hadoop/hbase/util/PositionedByteRange;
     650: pop
     651: aload         8
     653: bipush        9
     655: invokeinterface #41,  2           // InterfaceMethod org/apache/hadoop/hbase/util/PositionedByteRange.set:(I)Lorg/apache/hadoop/hbase/util/PositionedByteRange;
     660: pop
     661: ldc           #42                 // String Encoding null-truncated value wrote a surprising number of bytes.
     663: aload         4
     665: invokeinterface #21,  1           // InterfaceMethod org/apache/hadoop/hbase/util/PositionedByteRange.getLength:()I
     670: i2l
     671: aload_3
     672: aload         4
     674: aload         10
     676: iconst_3
     677: invokestatic  #36                 // Method java/util/Arrays.copyOf:([Ljava/lang/Object;I)[Ljava/lang/Object;
     680: invokevirtual #12                 // Method org/apache/hadoop/hbase/types/Struct.encode:(Lorg/apache/hadoop/hbase/util/PositionedByteRange;[Ljava/lang/Object;)I
     683: i2l
     684: invokestatic  #22                 // Method org/junit/Assert.assertEquals:(Ljava/lang/String;JJ)V
     687: ldc           #43                 // String Encoding null-extended value wrote a surprising number of bytes.
     689: aload         8
     691: invokeinterface #21,  1           // InterfaceMethod org/apache/hadoop/hbase/util/PositionedByteRange.getLength:()I
     696: i2l
     697: aload_3
     698: aload         8
     700: aload         10
     702: invokevirtual #12                 // Method org/apache/hadoop/hbase/types/Struct.encode:(Lorg/apache/hadoop/hbase/util/PositionedByteRange;[Ljava/lang/Object;)I
     705: i2l
     706: invokestatic  #22                 // Method org/junit/Assert.assertEquals:(Ljava/lang/String;JJ)V
     709: ldc           #44                 // String Encoded unexpected result.
     711: aload         4
     713: invokeinterface #39,  1           // InterfaceMethod org/apache/hadoop/hbase/util/PositionedByteRange.getBytes:()[B
     718: aload         8
     720: invokeinterface #39,  1           // InterfaceMethod org/apache/hadoop/hbase/util/PositionedByteRange.getBytes:()[B
     725: invokestatic  #40                 // Method org/junit/Assert.assertArrayEquals:(Ljava/lang/String;[B[B)V
     728: aload         8
     730: iconst_0
     731: invokeinterface #23,  2           // InterfaceMethod org/apache/hadoop/hbase/util/PositionedByteRange.setPosition:(I)Lorg/apache/hadoop/hbase/util/PositionedByteRange;
     736: pop
     737: ldc           #45                 // String Decoded unexpected result.
     739: aload         10
     741: aload_3
     742: aload         8
     744: invokevirtual #33                 // Method org/apache/hadoop/hbase/types/Struct.decode:(Lorg/apache/hadoop/hbase/util/PositionedByteRange;)[Ljava/lang/Object;
     747: invokestatic  #34                 // Method org/junit/Assert.assertArrayEquals:(Ljava/lang/String;[Ljava/lang/Object;[Ljava/lang/Object;)V
     750: return

  static {};
    Code:
       0: ldc           #46                 // class org/apache/hadoop/hbase/types/TestStructNullExtension
       2: invokestatic  #47                 // Method org/apache/hadoop/hbase/HBaseClassTestRule.forClass:(Ljava/lang/Class;)Lorg/apache/hadoop/hbase/HBaseClassTestRule;
       5: putstatic     #48                 // Field CLASS_RULE:Lorg/apache/hadoop/hbase/HBaseClassTestRule;
       8: return
}
