Compiled from "TestSecureIPC.java"
public class org.apache.hadoop.hbase.security.TestSecureIPC$TestThread extends java.lang.Thread {
  public org.apache.hadoop.hbase.security.TestSecureIPC$TestThread(org.apache.hadoop.hbase.shaded.ipc.protobuf.generated.TestRpcServiceProtos$TestProtobufRpcProto$BlockingInterface);
    Code:
       0: aload_0
       1: invokespecial #1                  // Method java/lang/Thread."<init>":()V
       4: aload_0
       5: aload_1
       6: putfield      #2                  // Field stub:Lorg/apache/hadoop/hbase/shaded/ipc/protobuf/generated/TestRpcServiceProtos$TestProtobufRpcProto$BlockingInterface;
       9: return

  public void run();
    Code:
       0: iconst_3
       1: newarray       int
       3: dup
       4: iconst_0
       5: bipush        100
       7: iastore
       8: dup
       9: iconst_1
      10: sipush        1000
      13: iastore
      14: dup
      15: iconst_2
      16: sipush        10000
      19: iastore
      20: astore_1
      21: iconst_0
      22: istore_2
      23: iload_2
      24: aload_1
      25: arraylength
      26: if_icmpge     73
      29: aload_1
      30: iload_2
      31: iaload
      32: invokestatic  #3                  // Method org/apache/commons/lang3/RandomStringUtils.random:(I)Ljava/lang/String;
      35: astore_3
      36: aload_0
      37: getfield      #2                  // Field stub:Lorg/apache/hadoop/hbase/shaded/ipc/protobuf/generated/TestRpcServiceProtos$TestProtobufRpcProto$BlockingInterface;
      40: aconst_null
      41: invokestatic  #4                  // Method org/apache/hadoop/hbase/shaded/ipc/protobuf/generated/TestProtos$EchoRequestProto.newBuilder:()Lorg/apache/hadoop/hbase/shaded/ipc/protobuf/generated/TestProtos$EchoRequestProto$Builder;
      44: aload_3
      45: invokevirtual #5                  // Method org/apache/hadoop/hbase/shaded/ipc/protobuf/generated/TestProtos$EchoRequestProto$Builder.setMessage:(Ljava/lang/String;)Lorg/apache/hadoop/hbase/shaded/ipc/protobuf/generated/TestProtos$EchoRequestProto$Builder;
      48: invokevirtual #6                  // Method org/apache/hadoop/hbase/shaded/ipc/protobuf/generated/TestProtos$EchoRequestProto$Builder.build:()Lorg/apache/hadoop/hbase/shaded/ipc/protobuf/generated/TestProtos$EchoRequestProto;
      51: invokeinterface #7,  3            // InterfaceMethod org/apache/hadoop/hbase/shaded/ipc/protobuf/generated/TestRpcServiceProtos$TestProtobufRpcProto$BlockingInterface.echo:(Lorg/apache/hbase/thirdparty/com/google/protobuf/RpcController;Lorg/apache/hadoop/hbase/shaded/ipc/protobuf/generated/TestProtos$EchoRequestProto;)Lorg/apache/hadoop/hbase/shaded/ipc/protobuf/generated/TestProtos$EchoResponseProto;
      56: invokevirtual #8                  // Method org/apache/hadoop/hbase/shaded/ipc/protobuf/generated/TestProtos$EchoResponseProto.getMessage:()Ljava/lang/String;
      59: astore        4
      61: aload_3
      62: aload         4
      64: invokestatic  #9                  // Method org/junit/Assert.assertEquals:(Ljava/lang/Object;Ljava/lang/Object;)V
      67: iinc          2, 1
      70: goto          23
      73: goto          86
      76: astore_1
      77: new           #11                 // class java/lang/RuntimeException
      80: dup
      81: aload_1
      82: invokespecial #12                 // Method java/lang/RuntimeException."<init>":(Ljava/lang/Throwable;)V
      85: athrow
      86: return
    Exception table:
       from    to  target type
           0    73    76   Class org/apache/hbase/thirdparty/com/google/protobuf/ServiceException
}
