Compiled from "TestClassFinder.java"
class org.apache.hadoop.hbase.TestClassFinder$2 implements org.apache.hadoop.hbase.ClassFinder$ClassFilter {
  final org.apache.hadoop.hbase.TestClassFinder this$0;

  org.apache.hadoop.hbase.TestClassFinder$2(org.apache.hadoop.hbase.TestClassFinder);
    Code:
       0: aload_0
       1: aload_1
       2: putfield      #2                  // Field this$0:Lorg/apache/hadoop/hbase/TestClassFinder;
       5: aload_0
       6: invokespecial #3                  // Method java/lang/Object."<init>":()V
       9: return

  public boolean isCandidateClass(java.lang.Class<?>);
    Code:
       0: aload_1
       1: invokevirtual #4                  // Method java/lang/Class.getSimpleName:()Ljava/lang/String;
       4: ldc           #5                  // String Prefix
       6: invokevirtual #6                  // Method java/lang/String.startsWith:(Ljava/lang/String;)Z
       9: ifne          16
      12: iconst_1
      13: goto          17
      16: iconst_0
      17: ireturn
}
