Compiled from "TestSuperUserQuotaPermissions.java"
class org.apache.hadoop.hbase.quotas.TestSuperUserQuotaPermissions$10 implements org.apache.hadoop.hbase.Waiter$Predicate<java.lang.Exception> {
  final org.apache.hadoop.hbase.regionserver.HRegionServer val$rs;

  final org.apache.hadoop.hbase.TableName val$tn;

  final org.apache.hadoop.hbase.quotas.TestSuperUserQuotaPermissions this$0;

  org.apache.hadoop.hbase.quotas.TestSuperUserQuotaPermissions$10(org.apache.hadoop.hbase.quotas.TestSuperUserQuotaPermissions, org.apache.hadoop.hbase.regionserver.HRegionServer, org.apache.hadoop.hbase.TableName);
    Code:
       0: aload_0
       1: aload_1
       2: putfield      #1                  // Field this$0:Lorg/apache/hadoop/hbase/quotas/TestSuperUserQuotaPermissions;
       5: aload_0
       6: aload_2
       7: putfield      #2                  // Field val$rs:Lorg/apache/hadoop/hbase/regionserver/HRegionServer;
      10: aload_0
      11: aload_3
      12: putfield      #3                  // Field val$tn:Lorg/apache/hadoop/hbase/TableName;
      15: aload_0
      16: invokespecial #4                  // Method java/lang/Object."<init>":()V
      19: return

  public boolean evaluate() throws java.lang.Exception;
    Code:
       0: aload_0
       1: getfield      #2                  // Field val$rs:Lorg/apache/hadoop/hbase/regionserver/HRegionServer;
       4: invokevirtual #5                  // Method org/apache/hadoop/hbase/regionserver/HRegionServer.getRegionServerSpaceQuotaManager:()Lorg/apache/hadoop/hbase/quotas/RegionServerSpaceQuotaManager;
       7: invokevirtual #6                  // Method org/apache/hadoop/hbase/quotas/RegionServerSpaceQuotaManager.copyQuotaSnapshots:()Ljava/util/Map;
      10: astore_1
      11: aload_1
      12: aload_0
      13: getfield      #3                  // Field val$tn:Lorg/apache/hadoop/hbase/TableName;
      16: invokeinterface #7,  2            // InterfaceMethod java/util/Map.get:(Ljava/lang/Object;)Ljava/lang/Object;
      21: checkcast     #8                  // class org/apache/hadoop/hbase/quotas/SpaceQuotaSnapshot
      24: astore_2
      25: aload_2
      26: ifnonnull     61
      29: invokestatic  #9                  // Method org/apache/hadoop/hbase/quotas/TestSuperUserQuotaPermissions.access$200:()Lorg/slf4j/Logger;
      32: new           #10                 // class java/lang/StringBuilder
      35: dup
      36: invokespecial #11                 // Method java/lang/StringBuilder."<init>":()V
      39: ldc           #12                 // String Found no snapshot for
      41: invokevirtual #13                 // Method java/lang/StringBuilder.append:(Ljava/lang/String;)Ljava/lang/StringBuilder;
      44: aload_0
      45: getfield      #3                  // Field val$tn:Lorg/apache/hadoop/hbase/TableName;
      48: invokevirtual #14                 // Method java/lang/StringBuilder.append:(Ljava/lang/Object;)Ljava/lang/StringBuilder;
      51: invokevirtual #15                 // Method java/lang/StringBuilder.toString:()Ljava/lang/String;
      54: invokeinterface #16,  2           // InterfaceMethod org/slf4j/Logger.info:(Ljava/lang/String;)V
      59: iconst_0
      60: ireturn
      61: invokestatic  #9                  // Method org/apache/hadoop/hbase/quotas/TestSuperUserQuotaPermissions.access$200:()Lorg/slf4j/Logger;
      64: new           #10                 // class java/lang/StringBuilder
      67: dup
      68: invokespecial #11                 // Method java/lang/StringBuilder."<init>":()V
      71: ldc           #17                 // String Found snapshot
      73: invokevirtual #13                 // Method java/lang/StringBuilder.append:(Ljava/lang/String;)Ljava/lang/StringBuilder;
      76: aload_2
      77: invokevirtual #14                 // Method java/lang/StringBuilder.append:(Ljava/lang/Object;)Ljava/lang/StringBuilder;
      80: invokevirtual #15                 // Method java/lang/StringBuilder.toString:()Ljava/lang/String;
      83: invokeinterface #16,  2           // InterfaceMethod org/slf4j/Logger.info:(Ljava/lang/String;)V
      88: aload_2
      89: invokevirtual #18                 // Method org/apache/hadoop/hbase/quotas/SpaceQuotaSnapshot.getQuotaStatus:()Lorg/apache/hadoop/hbase/quotas/SpaceQuotaSnapshot$SpaceQuotaStatus;
      92: invokevirtual #19                 // Method org/apache/hadoop/hbase/quotas/SpaceQuotaSnapshot$SpaceQuotaStatus.isInViolation:()Z
      95: ireturn
}
