Compiled from "TestLogRoller.java"
public class org.apache.hadoop.hbase.regionserver.TestLogRoller {
  public static final org.apache.hadoop.hbase.HBaseClassTestRule CLASS_RULE;

  public org.apache.hadoop.hbase.regionserver.TestLogRoller();
    Code:
       0: aload_0
       1: invokespecial #1                  // Method java/lang/Object."<init>":()V
       4: return

  public void setup() throws java.lang.Exception;
    Code:
       0: getstatic     #2                  // Field TEST_UTIL:Lorg/apache/hadoop/hbase/HBaseTestingUtility;
       3: invokevirtual #3                  // Method org/apache/hadoop/hbase/HBaseTestingUtility.getConfiguration:()Lorg/apache/hadoop/conf/Configuration;
       6: ldc           #4                  // String hbase.regionserver.logroll.period
       8: sipush        20000
      11: invokevirtual #6                  // Method org/apache/hadoop/conf/Configuration.setInt:(Ljava/lang/String;I)V
      14: getstatic     #2                  // Field TEST_UTIL:Lorg/apache/hadoop/hbase/HBaseTestingUtility;
      17: iconst_1
      18: invokevirtual #7                  // Method org/apache/hadoop/hbase/HBaseTestingUtility.startMiniCluster:(I)Lorg/apache/hadoop/hbase/MiniHBaseCluster;
      21: pop
      22: ldc           #8                  // String Test
      24: invokestatic  #9                  // Method org/apache/hadoop/hbase/TableName.valueOf:(Ljava/lang/String;)Lorg/apache/hadoop/hbase/TableName;
      27: astore_1
      28: getstatic     #2                  // Field TEST_UTIL:Lorg/apache/hadoop/hbase/HBaseTestingUtility;
      31: aload_1
      32: ldc           #10                 // String cf
      34: invokestatic  #11                 // Method org/apache/hadoop/hbase/util/Bytes.toBytes:(Ljava/lang/String;)[B
      37: invokevirtual #12                 // Method org/apache/hadoop/hbase/HBaseTestingUtility.createTable:(Lorg/apache/hadoop/hbase/TableName;[B)Lorg/apache/hadoop/hbase/client/Table;
      40: pop
      41: getstatic     #2                  // Field TEST_UTIL:Lorg/apache/hadoop/hbase/HBaseTestingUtility;
      44: aload_1
      45: invokevirtual #13                 // Method org/apache/hadoop/hbase/HBaseTestingUtility.waitTableAvailable:(Lorg/apache/hadoop/hbase/TableName;)V
      48: return

  public void tearDown() throws java.lang.Exception;
    Code:
       0: getstatic     #2                  // Field TEST_UTIL:Lorg/apache/hadoop/hbase/HBaseTestingUtility;
       3: invokevirtual #14                 // Method org/apache/hadoop/hbase/HBaseTestingUtility.shutdownMiniCluster:()V
       6: return

  public void testRemoveClosedWAL() throws java.lang.Exception;
    Code:
       0: getstatic     #2                  // Field TEST_UTIL:Lorg/apache/hadoop/hbase/HBaseTestingUtility;
       3: invokevirtual #15                 // Method org/apache/hadoop/hbase/HBaseTestingUtility.getMiniHBaseCluster:()Lorg/apache/hadoop/hbase/MiniHBaseCluster;
       6: iconst_0
       7: invokevirtual #16                 // Method org/apache/hadoop/hbase/MiniHBaseCluster.getRegionServer:(I)Lorg/apache/hadoop/hbase/regionserver/HRegionServer;
      10: astore_1
      11: aload_1
      12: invokevirtual #17                 // Method org/apache/hadoop/hbase/regionserver/HRegionServer.getConfiguration:()Lorg/apache/hadoop/conf/Configuration;
      15: astore_2
      16: getstatic     #2                  // Field TEST_UTIL:Lorg/apache/hadoop/hbase/HBaseTestingUtility;
      19: invokevirtual #15                 // Method org/apache/hadoop/hbase/HBaseTestingUtility.getMiniHBaseCluster:()Lorg/apache/hadoop/hbase/MiniHBaseCluster;
      22: iconst_0
      23: invokevirtual #16                 // Method org/apache/hadoop/hbase/MiniHBaseCluster.getRegionServer:(I)Lorg/apache/hadoop/hbase/regionserver/HRegionServer;
      26: invokevirtual #18                 // Method org/apache/hadoop/hbase/regionserver/HRegionServer.getWalRoller:()Lorg/apache/hadoop/hbase/regionserver/LogRoller;
      29: astore_3
      30: aload_3
      31: invokevirtual #19                 // Method org/apache/hadoop/hbase/regionserver/LogRoller.getWalNeedsRoll:()Ljava/util/Map;
      34: invokeinterface #20,  1           // InterfaceMethod java/util/Map.size:()I
      39: istore        4
      41: new           #21                 // class org/apache/hadoop/hbase/regionserver/wal/FSHLog
      44: dup
      45: aload_1
      46: invokevirtual #22                 // Method org/apache/hadoop/hbase/regionserver/HRegionServer.getWALFileSystem:()Lorg/apache/hadoop/fs/FileSystem;
      49: aload_1
      50: invokevirtual #23                 // Method org/apache/hadoop/hbase/regionserver/HRegionServer.getWALRootDir:()Lorg/apache/hadoop/fs/Path;
      53: aload_1
      54: invokevirtual #24                 // Method org/apache/hadoop/hbase/regionserver/HRegionServer.getServerName:()Lorg/apache/hadoop/hbase/ServerName;
      57: invokevirtual #25                 // Method org/apache/hadoop/hbase/ServerName.getServerName:()Ljava/lang/String;
      60: invokestatic  #26                 // Method org/apache/hadoop/hbase/wal/AbstractFSWALProvider.getWALDirectoryName:(Ljava/lang/String;)Ljava/lang/String;
      63: aload_2
      64: invokespecial #27                 // Method org/apache/hadoop/hbase/regionserver/wal/FSHLog."<init>":(Lorg/apache/hadoop/fs/FileSystem;Lorg/apache/hadoop/fs/Path;Ljava/lang/String;Lorg/apache/hadoop/conf/Configuration;)V
      67: astore        5
      69: aload_3
      70: aload         5
      72: invokevirtual #28                 // Method org/apache/hadoop/hbase/regionserver/LogRoller.addWAL:(Lorg/apache/hadoop/hbase/wal/WAL;)V
      75: new           #21                 // class org/apache/hadoop/hbase/regionserver/wal/FSHLog
      78: dup
      79: aload_1
      80: invokevirtual #22                 // Method org/apache/hadoop/hbase/regionserver/HRegionServer.getWALFileSystem:()Lorg/apache/hadoop/fs/FileSystem;
      83: aload_1
      84: invokevirtual #23                 // Method org/apache/hadoop/hbase/regionserver/HRegionServer.getWALRootDir:()Lorg/apache/hadoop/fs/Path;
      87: aload_1
      88: invokevirtual #24                 // Method org/apache/hadoop/hbase/regionserver/HRegionServer.getServerName:()Lorg/apache/hadoop/hbase/ServerName;
      91: invokevirtual #25                 // Method org/apache/hadoop/hbase/ServerName.getServerName:()Ljava/lang/String;
      94: invokestatic  #26                 // Method org/apache/hadoop/hbase/wal/AbstractFSWALProvider.getWALDirectoryName:(Ljava/lang/String;)Ljava/lang/String;
      97: aload_2
      98: invokespecial #27                 // Method org/apache/hadoop/hbase/regionserver/wal/FSHLog."<init>":(Lorg/apache/hadoop/fs/FileSystem;Lorg/apache/hadoop/fs/Path;Ljava/lang/String;Lorg/apache/hadoop/conf/Configuration;)V
     101: astore        6
     103: aload_3
     104: aload         6
     106: invokevirtual #28                 // Method org/apache/hadoop/hbase/regionserver/LogRoller.addWAL:(Lorg/apache/hadoop/hbase/wal/WAL;)V
     109: new           #21                 // class org/apache/hadoop/hbase/regionserver/wal/FSHLog
     112: dup
     113: aload_1
     114: invokevirtual #22                 // Method org/apache/hadoop/hbase/regionserver/HRegionServer.getWALFileSystem:()Lorg/apache/hadoop/fs/FileSystem;
     117: aload_1
     118: invokevirtual #23                 // Method org/apache/hadoop/hbase/regionserver/HRegionServer.getWALRootDir:()Lorg/apache/hadoop/fs/Path;
     121: aload_1
     122: invokevirtual #24                 // Method org/apache/hadoop/hbase/regionserver/HRegionServer.getServerName:()Lorg/apache/hadoop/hbase/ServerName;
     125: invokevirtual #25                 // Method org/apache/hadoop/hbase/ServerName.getServerName:()Ljava/lang/String;
     128: invokestatic  #26                 // Method org/apache/hadoop/hbase/wal/AbstractFSWALProvider.getWALDirectoryName:(Ljava/lang/String;)Ljava/lang/String;
     131: aload_2
     132: invokespecial #27                 // Method org/apache/hadoop/hbase/regionserver/wal/FSHLog."<init>":(Lorg/apache/hadoop/fs/FileSystem;Lorg/apache/hadoop/fs/Path;Ljava/lang/String;Lorg/apache/hadoop/conf/Configuration;)V
     135: astore        7
     137: aload_3
     138: aload         7
     140: invokevirtual #28                 // Method org/apache/hadoop/hbase/regionserver/LogRoller.addWAL:(Lorg/apache/hadoop/hbase/wal/WAL;)V
     143: iload         4
     145: iconst_3
     146: iadd
     147: i2l
     148: aload_3
     149: invokevirtual #19                 // Method org/apache/hadoop/hbase/regionserver/LogRoller.getWalNeedsRoll:()Ljava/util/Map;
     152: invokeinterface #20,  1           // InterfaceMethod java/util/Map.size:()I
     157: i2l
     158: invokestatic  #29                 // Method org/junit/Assert.assertEquals:(JJ)V
     161: aload_3
     162: invokevirtual #19                 // Method org/apache/hadoop/hbase/regionserver/LogRoller.getWalNeedsRoll:()Ljava/util/Map;
     165: aload         5
     167: invokeinterface #30,  2           // InterfaceMethod java/util/Map.containsKey:(Ljava/lang/Object;)Z
     172: invokestatic  #31                 // Method org/junit/Assert.assertTrue:(Z)V
     175: aload         5
     177: invokevirtual #32                 // Method org/apache/hadoop/hbase/regionserver/wal/FSHLog.close:()V
     180: ldc2_w        #33                 // long 40000l
     183: invokestatic  #35                 // Method java/lang/Thread.sleep:(J)V
     186: iload         4
     188: iconst_2
     189: iadd
     190: i2l
     191: aload_3
     192: invokevirtual #19                 // Method org/apache/hadoop/hbase/regionserver/LogRoller.getWalNeedsRoll:()Ljava/util/Map;
     195: invokeinterface #20,  1           // InterfaceMethod java/util/Map.size:()I
     200: i2l
     201: invokestatic  #29                 // Method org/junit/Assert.assertEquals:(JJ)V
     204: aload_3
     205: invokevirtual #19                 // Method org/apache/hadoop/hbase/regionserver/LogRoller.getWalNeedsRoll:()Ljava/util/Map;
     208: aload         5
     210: invokeinterface #30,  2           // InterfaceMethod java/util/Map.containsKey:(Ljava/lang/Object;)Z
     215: invokestatic  #36                 // Method org/junit/Assert.assertFalse:(Z)V
     218: aload         6
     220: invokevirtual #32                 // Method org/apache/hadoop/hbase/regionserver/wal/FSHLog.close:()V
     223: aload         7
     225: invokevirtual #32                 // Method org/apache/hadoop/hbase/regionserver/wal/FSHLog.close:()V
     228: ldc2_w        #33                 // long 40000l
     231: invokestatic  #35                 // Method java/lang/Thread.sleep:(J)V
     234: iload         4
     236: i2l
     237: aload_3
     238: invokevirtual #19                 // Method org/apache/hadoop/hbase/regionserver/LogRoller.getWalNeedsRoll:()Ljava/util/Map;
     241: invokeinterface #20,  1           // InterfaceMethod java/util/Map.size:()I
     246: i2l
     247: invokestatic  #29                 // Method org/junit/Assert.assertEquals:(JJ)V
     250: return

  static {};
    Code:
       0: ldc           #5                  // class org/apache/hadoop/hbase/regionserver/TestLogRoller
       2: invokestatic  #37                 // Method org/apache/hadoop/hbase/HBaseClassTestRule.forClass:(Ljava/lang/Class;)Lorg/apache/hadoop/hbase/HBaseClassTestRule;
       5: putstatic     #38                 // Field CLASS_RULE:Lorg/apache/hadoop/hbase/HBaseClassTestRule;
       8: new           #39                 // class org/apache/hadoop/hbase/HBaseTestingUtility
      11: dup
      12: invokespecial #40                 // Method org/apache/hadoop/hbase/HBaseTestingUtility."<init>":()V
      15: putstatic     #2                  // Field TEST_UTIL:Lorg/apache/hadoop/hbase/HBaseTestingUtility;
      18: return
}
