Compiled from "TestMasterObserver.java"
public class org.apache.hadoop.hbase.coprocessor.TestMasterObserver {
  public static final org.apache.hadoop.hbase.HBaseClassTestRule CLASS_RULE;

  public static java.util.concurrent.CountDownLatch tableCreationLatch;

  public static java.util.concurrent.CountDownLatch tableDeletionLatch;

  public org.junit.rules.TestName name;

  public org.apache.hadoop.hbase.coprocessor.TestMasterObserver();
    Code:
       0: aload_0
       1: invokespecial #1                  // Method java/lang/Object."<init>":()V
       4: aload_0
       5: new           #2                  // class org/junit/rules/TestName
       8: dup
       9: invokespecial #3                  // Method org/junit/rules/TestName."<init>":()V
      12: putfield      #4                  // Field name:Lorg/junit/rules/TestName;
      15: return

  public static void setupBeforeClass() throws java.lang.Exception;
    Code:
       0: getstatic     #5                  // Field UTIL:Lorg/apache/hadoop/hbase/HBaseTestingUtility;
       3: invokevirtual #6                  // Method org/apache/hadoop/hbase/HBaseTestingUtility.getConfiguration:()Lorg/apache/hadoop/conf/Configuration;
       6: astore_0
       7: aload_0
       8: ldc           #8                  // String hbase.coprocessor.master.classes
      10: ldc           #9                  // class org/apache/hadoop/hbase/coprocessor/TestMasterObserver$CPMasterObserver
      12: invokevirtual #10                 // Method java/lang/Class.getName:()Ljava/lang/String;
      15: invokevirtual #11                 // Method org/apache/hadoop/conf/Configuration.set:(Ljava/lang/String;Ljava/lang/String;)V
      18: getstatic     #5                  // Field UTIL:Lorg/apache/hadoop/hbase/HBaseTestingUtility;
      21: iconst_2
      22: invokevirtual #12                 // Method org/apache/hadoop/hbase/HBaseTestingUtility.startMiniCluster:(I)Lorg/apache/hadoop/hbase/MiniHBaseCluster;
      25: pop
      26: return

  public static void tearDownAfterClass() throws java.lang.Exception;
    Code:
       0: getstatic     #5                  // Field UTIL:Lorg/apache/hadoop/hbase/HBaseTestingUtility;
       3: invokevirtual #13                 // Method org/apache/hadoop/hbase/HBaseTestingUtility.shutdownMiniCluster:()V
       6: return

  public void testStarted() throws java.lang.Exception;
    Code:
       0: getstatic     #5                  // Field UTIL:Lorg/apache/hadoop/hbase/HBaseTestingUtility;
       3: invokevirtual #14                 // Method org/apache/hadoop/hbase/HBaseTestingUtility.getHBaseCluster:()Lorg/apache/hadoop/hbase/MiniHBaseCluster;
       6: astore_1
       7: aload_1
       8: invokevirtual #15                 // Method org/apache/hadoop/hbase/MiniHBaseCluster.getMaster:()Lorg/apache/hadoop/hbase/master/HMaster;
      11: astore_2
      12: ldc           #16                 // String Master should be active
      14: aload_2
      15: invokevirtual #17                 // Method org/apache/hadoop/hbase/master/HMaster.isActiveMaster:()Z
      18: invokestatic  #18                 // Method org/junit/Assert.assertTrue:(Ljava/lang/String;Z)V
      21: aload_2
      22: invokevirtual #19                 // Method org/apache/hadoop/hbase/master/HMaster.getMasterCoprocessorHost:()Lorg/apache/hadoop/hbase/master/MasterCoprocessorHost;
      25: astore_3
      26: ldc           #20                 // String CoprocessorHost should not be null
      28: aload_3
      29: invokestatic  #21                 // Method org/junit/Assert.assertNotNull:(Ljava/lang/String;Ljava/lang/Object;)V
      32: aload_3
      33: ldc           #9                  // class org/apache/hadoop/hbase/coprocessor/TestMasterObserver$CPMasterObserver
      35: invokevirtual #22                 // Method org/apache/hadoop/hbase/master/MasterCoprocessorHost.findCoprocessor:(Ljava/lang/Class;)Lorg/apache/hadoop/hbase/Coprocessor;
      38: checkcast     #9                  // class org/apache/hadoop/hbase/coprocessor/TestMasterObserver$CPMasterObserver
      41: astore        4
      43: ldc           #23                 // String CPMasterObserver coprocessor not found or not installed!
      45: aload         4
      47: invokestatic  #21                 // Method org/junit/Assert.assertNotNull:(Ljava/lang/String;Ljava/lang/Object;)V
      50: ldc           #24                 // String MasterObserver should have been started
      52: aload         4
      54: invokevirtual #25                 // Method org/apache/hadoop/hbase/coprocessor/TestMasterObserver$CPMasterObserver.wasStarted:()Z
      57: invokestatic  #18                 // Method org/junit/Assert.assertTrue:(Ljava/lang/String;Z)V
      60: ldc           #26                 // String preMasterInitialization() hook should have been called
      62: aload         4
      64: invokevirtual #27                 // Method org/apache/hadoop/hbase/coprocessor/TestMasterObserver$CPMasterObserver.wasMasterInitializationCalled:()Z
      67: invokestatic  #18                 // Method org/junit/Assert.assertTrue:(Ljava/lang/String;Z)V
      70: ldc           #28                 // String postStartMaster() hook should have been called
      72: aload         4
      74: invokevirtual #29                 // Method org/apache/hadoop/hbase/coprocessor/TestMasterObserver$CPMasterObserver.wasStartMasterCalled:()Z
      77: invokestatic  #18                 // Method org/junit/Assert.assertTrue:(Ljava/lang/String;Z)V
      80: return

  public void testTableOperations() throws java.lang.Exception;
    Code:
       0: getstatic     #5                  // Field UTIL:Lorg/apache/hadoop/hbase/HBaseTestingUtility;
       3: invokevirtual #14                 // Method org/apache/hadoop/hbase/HBaseTestingUtility.getHBaseCluster:()Lorg/apache/hadoop/hbase/MiniHBaseCluster;
       6: astore_1
       7: aload_0
       8: getfield      #4                  // Field name:Lorg/junit/rules/TestName;
      11: invokevirtual #30                 // Method org/junit/rules/TestName.getMethodName:()Ljava/lang/String;
      14: invokestatic  #31                 // Method org/apache/hadoop/hbase/TableName.valueOf:(Ljava/lang/String;)Lorg/apache/hadoop/hbase/TableName;
      17: astore_2
      18: aload_1
      19: invokevirtual #15                 // Method org/apache/hadoop/hbase/MiniHBaseCluster.getMaster:()Lorg/apache/hadoop/hbase/master/HMaster;
      22: astore_3
      23: aload_3
      24: invokevirtual #19                 // Method org/apache/hadoop/hbase/master/HMaster.getMasterCoprocessorHost:()Lorg/apache/hadoop/hbase/master/MasterCoprocessorHost;
      27: astore        4
      29: aload         4
      31: ldc           #9                  // class org/apache/hadoop/hbase/coprocessor/TestMasterObserver$CPMasterObserver
      33: invokevirtual #22                 // Method org/apache/hadoop/hbase/master/MasterCoprocessorHost.findCoprocessor:(Ljava/lang/Class;)Lorg/apache/hadoop/hbase/Coprocessor;
      36: checkcast     #9                  // class org/apache/hadoop/hbase/coprocessor/TestMasterObserver$CPMasterObserver
      39: astore        5
      41: aload         5
      43: invokevirtual #32                 // Method org/apache/hadoop/hbase/coprocessor/TestMasterObserver$CPMasterObserver.resetStates:()V
      46: ldc           #33                 // String No table created yet
      48: aload         5
      50: invokevirtual #34                 // Method org/apache/hadoop/hbase/coprocessor/TestMasterObserver$CPMasterObserver.wasCreateTableCalled:()Z
      53: invokestatic  #35                 // Method org/junit/Assert.assertFalse:(Ljava/lang/String;Z)V
      56: new           #36                 // class org/apache/hadoop/hbase/HTableDescriptor
      59: dup
      60: aload_2
      61: invokespecial #37                 // Method org/apache/hadoop/hbase/HTableDescriptor."<init>":(Lorg/apache/hadoop/hbase/TableName;)V
      64: astore        6
      66: aload         6
      68: new           #38                 // class org/apache/hadoop/hbase/HColumnDescriptor
      71: dup
      72: getstatic     #39                 // Field TEST_FAMILY:[B
      75: invokespecial #40                 // Method org/apache/hadoop/hbase/HColumnDescriptor."<init>":([B)V
      78: invokevirtual #41                 // Method org/apache/hadoop/hbase/HTableDescriptor.addFamily:(Lorg/apache/hadoop/hbase/HColumnDescriptor;)Lorg/apache/hadoop/hbase/HTableDescriptor;
      81: pop
      82: getstatic     #5                  // Field UTIL:Lorg/apache/hadoop/hbase/HBaseTestingUtility;
      85: invokevirtual #6                  // Method org/apache/hadoop/hbase/HBaseTestingUtility.getConfiguration:()Lorg/apache/hadoop/conf/Configuration;
      88: invokestatic  #42                 // Method org/apache/hadoop/hbase/client/ConnectionFactory.createConnection:(Lorg/apache/hadoop/conf/Configuration;)Lorg/apache/hadoop/hbase/client/Connection;
      91: astore        7
      93: aconst_null
      94: astore        8
      96: aload         7
      98: invokeinterface #43,  1           // InterfaceMethod org/apache/hadoop/hbase/client/Connection.getAdmin:()Lorg/apache/hadoop/hbase/client/Admin;
     103: astore        9
     105: aconst_null
     106: astore        10
     108: new           #44                 // class java/util/concurrent/CountDownLatch
     111: dup
     112: iconst_1
     113: invokespecial #45                 // Method java/util/concurrent/CountDownLatch."<init>":(I)V
     116: putstatic     #46                 // Field tableCreationLatch:Ljava/util/concurrent/CountDownLatch;
     119: aload         9
     121: aload         6
     123: getstatic     #47                 // Field org/apache/hadoop/hbase/HBaseTestingUtility.KEYS:[[B
     126: iconst_1
     127: getstatic     #47                 // Field org/apache/hadoop/hbase/HBaseTestingUtility.KEYS:[[B
     130: arraylength
     131: invokestatic  #48                 // Method java/util/Arrays.copyOfRange:([Ljava/lang/Object;II)[Ljava/lang/Object;
     134: checkcast     #49                 // class "[[B"
     137: invokeinterface #50,  3           // InterfaceMethod org/apache/hadoop/hbase/client/Admin.createTable:(Lorg/apache/hadoop/hbase/client/TableDescriptor;[[B)V
     142: ldc           #51                 // String Test table should be created
     144: aload         5
     146: invokevirtual #34                 // Method org/apache/hadoop/hbase/coprocessor/TestMasterObserver$CPMasterObserver.wasCreateTableCalled:()Z
     149: invokestatic  #18                 // Method org/junit/Assert.assertTrue:(Ljava/lang/String;Z)V
     152: getstatic     #46                 // Field tableCreationLatch:Ljava/util/concurrent/CountDownLatch;
     155: invokevirtual #52                 // Method java/util/concurrent/CountDownLatch.await:()V
     158: ldc           #53                 // String Table pre create handler called.
     160: aload         5
     162: invokevirtual #54                 // Method org/apache/hadoop/hbase/coprocessor/TestMasterObserver$CPMasterObserver.wasPreCreateTableActionCalled:()Z
     165: invokestatic  #18                 // Method org/junit/Assert.assertTrue:(Ljava/lang/String;Z)V
     168: ldc           #55                 // String Table create handler should be called.
     170: aload         5
     172: invokevirtual #56                 // Method org/apache/hadoop/hbase/coprocessor/TestMasterObserver$CPMasterObserver.wasCreateTableActionCalled:()Z
     175: invokestatic  #18                 // Method org/junit/Assert.assertTrue:(Ljava/lang/String;Z)V
     178: aload         7
     180: aload         6
     182: invokevirtual #57                 // Method org/apache/hadoop/hbase/HTableDescriptor.getTableName:()Lorg/apache/hadoop/hbase/TableName;
     185: invokeinterface #58,  2           // InterfaceMethod org/apache/hadoop/hbase/client/Connection.getRegionLocator:(Lorg/apache/hadoop/hbase/TableName;)Lorg/apache/hadoop/hbase/client/RegionLocator;
     190: astore        11
     192: aload         11
     194: invokeinterface #59,  1           // InterfaceMethod org/apache/hadoop/hbase/client/RegionLocator.getAllRegionLocations:()Ljava/util/List;
     199: astore        12
     201: aload         9
     203: aload         12
     205: iconst_0
     206: invokeinterface #60,  2           // InterfaceMethod java/util/List.get:(I)Ljava/lang/Object;
     211: checkcast     #61                 // class org/apache/hadoop/hbase/HRegionLocation
     214: invokevirtual #62                 // Method org/apache/hadoop/hbase/HRegionLocation.getRegionInfo:()Lorg/apache/hadoop/hbase/HRegionInfo;
     217: invokevirtual #63                 // Method org/apache/hadoop/hbase/HRegionInfo.getEncodedNameAsBytes:()[B
     220: aload         12
     222: iconst_1
     223: invokeinterface #60,  2           // InterfaceMethod java/util/List.get:(I)Ljava/lang/Object;
     228: checkcast     #61                 // class org/apache/hadoop/hbase/HRegionLocation
     231: invokevirtual #62                 // Method org/apache/hadoop/hbase/HRegionLocation.getRegionInfo:()Lorg/apache/hadoop/hbase/HRegionInfo;
     234: invokevirtual #63                 // Method org/apache/hadoop/hbase/HRegionInfo.getEncodedNameAsBytes:()[B
     237: iconst_1
     238: invokeinterface #64,  4           // InterfaceMethod org/apache/hadoop/hbase/client/Admin.mergeRegionsAsync:([B[BZ)Ljava/util/concurrent/Future;
     243: pop
     244: ldc           #65                 // String Coprocessor should have been called on region merge
     246: aload         5
     248: invokevirtual #66                 // Method org/apache/hadoop/hbase/coprocessor/TestMasterObserver$CPMasterObserver.wasMergeRegionsCalled:()Z
     251: invokestatic  #18                 // Method org/junit/Assert.assertTrue:(Ljava/lang/String;Z)V
     254: new           #44                 // class java/util/concurrent/CountDownLatch
     257: dup
     258: iconst_1
     259: invokespecial #45                 // Method java/util/concurrent/CountDownLatch."<init>":(I)V
     262: putstatic     #46                 // Field tableCreationLatch:Ljava/util/concurrent/CountDownLatch;
     265: aload         9
     267: aload_2
     268: invokeinterface #67,  2           // InterfaceMethod org/apache/hadoop/hbase/client/Admin.disableTable:(Lorg/apache/hadoop/hbase/TableName;)V
     273: aload         9
     275: aload_2
     276: invokeinterface #68,  2           // InterfaceMethod org/apache/hadoop/hbase/client/Admin.isTableDisabled:(Lorg/apache/hadoop/hbase/TableName;)Z
     281: invokestatic  #69                 // Method org/junit/Assert.assertTrue:(Z)V
     284: ldc           #70                 // String Coprocessor should have been called on table disable
     286: aload         5
     288: invokevirtual #71                 // Method org/apache/hadoop/hbase/coprocessor/TestMasterObserver$CPMasterObserver.wasDisableTableCalled:()Z
     291: invokestatic  #18                 // Method org/junit/Assert.assertTrue:(Ljava/lang/String;Z)V
     294: ldc           #72                 // String Disable table handler should be called.
     296: aload         5
     298: invokevirtual #73                 // Method org/apache/hadoop/hbase/coprocessor/TestMasterObserver$CPMasterObserver.wasDisableTableActionCalled:()Z
     301: invokestatic  #18                 // Method org/junit/Assert.assertTrue:(Ljava/lang/String;Z)V
     304: aload         5
     306: invokevirtual #74                 // Method org/apache/hadoop/hbase/coprocessor/TestMasterObserver$CPMasterObserver.wasEnableTableCalled:()Z
     309: invokestatic  #75                 // Method org/junit/Assert.assertFalse:(Z)V
     312: aload         9
     314: aload_2
     315: invokeinterface #76,  2           // InterfaceMethod org/apache/hadoop/hbase/client/Admin.enableTable:(Lorg/apache/hadoop/hbase/TableName;)V
     320: aload         9
     322: aload_2
     323: invokeinterface #77,  2           // InterfaceMethod org/apache/hadoop/hbase/client/Admin.isTableEnabled:(Lorg/apache/hadoop/hbase/TableName;)Z
     328: invokestatic  #69                 // Method org/junit/Assert.assertTrue:(Z)V
     331: ldc           #78                 // String Coprocessor should have been called on table enable
     333: aload         5
     335: invokevirtual #74                 // Method org/apache/hadoop/hbase/coprocessor/TestMasterObserver$CPMasterObserver.wasEnableTableCalled:()Z
     338: invokestatic  #18                 // Method org/junit/Assert.assertTrue:(Ljava/lang/String;Z)V
     341: ldc           #79                 // String Enable table handler should be called.
     343: aload         5
     345: invokevirtual #80                 // Method org/apache/hadoop/hbase/coprocessor/TestMasterObserver$CPMasterObserver.wasEnableTableActionCalled:()Z
     348: invokestatic  #18                 // Method org/junit/Assert.assertTrue:(Ljava/lang/String;Z)V
     351: aload         9
     353: aload_2
     354: invokeinterface #67,  2           // InterfaceMethod org/apache/hadoop/hbase/client/Admin.disableTable:(Lorg/apache/hadoop/hbase/TableName;)V
     359: aload         9
     361: aload_2
     362: invokeinterface #68,  2           // InterfaceMethod org/apache/hadoop/hbase/client/Admin.isTableDisabled:(Lorg/apache/hadoop/hbase/TableName;)Z
     367: invokestatic  #69                 // Method org/junit/Assert.assertTrue:(Z)V
     370: aload         6
     372: ldc2_w        #81                 // long 536870912l
     375: invokevirtual #83                 // Method org/apache/hadoop/hbase/HTableDescriptor.setMaxFileSize:(J)Lorg/apache/hadoop/hbase/HTableDescriptor;
     378: pop
     379: aload_0
     380: aload         9
     382: aload_2
     383: aload         6
     385: invokespecial #84                 // Method modifyTableSync:(Lorg/apache/hadoop/hbase/client/Admin;Lorg/apache/hadoop/hbase/TableName;Lorg/apache/hadoop/hbase/HTableDescriptor;)V
     388: ldc           #85                 // String Test table should have been modified
     390: aload         5
     392: invokevirtual #86                 // Method org/apache/hadoop/hbase/coprocessor/TestMasterObserver$CPMasterObserver.wasModifyTableCalled:()Z
     395: invokestatic  #18                 // Method org/junit/Assert.assertTrue:(Ljava/lang/String;Z)V
     398: aload         9
     400: aload_2
     401: iconst_0
     402: invokeinterface #87,  3           // InterfaceMethod org/apache/hadoop/hbase/client/Admin.truncateTable:(Lorg/apache/hadoop/hbase/TableName;Z)V
     407: aload         9
     409: aload_2
     410: invokeinterface #67,  2           // InterfaceMethod org/apache/hadoop/hbase/client/Admin.disableTable:(Lorg/apache/hadoop/hbase/TableName;)V
     415: aload         9
     417: aload_2
     418: invokeinterface #68,  2           // InterfaceMethod org/apache/hadoop/hbase/client/Admin.isTableDisabled:(Lorg/apache/hadoop/hbase/TableName;)Z
     423: invokestatic  #69                 // Method org/junit/Assert.assertTrue:(Z)V
     426: aload_0
     427: aload         9
     429: aload_2
     430: invokespecial #88                 // Method deleteTable:(Lorg/apache/hadoop/hbase/client/Admin;Lorg/apache/hadoop/hbase/TableName;)V
     433: ldc           #89                 // String Test table should have been deleted
     435: aload         9
     437: aload_2
     438: invokeinterface #90,  2           // InterfaceMethod org/apache/hadoop/hbase/client/Admin.tableExists:(Lorg/apache/hadoop/hbase/TableName;)Z
     443: invokestatic  #35                 // Method org/junit/Assert.assertFalse:(Ljava/lang/String;Z)V
     446: ldc           #91                 // String Coprocessor should have been called on table delete
     448: aload         5
     450: invokevirtual #92                 // Method org/apache/hadoop/hbase/coprocessor/TestMasterObserver$CPMasterObserver.wasDeleteTableCalled:()Z
     453: invokestatic  #18                 // Method org/junit/Assert.assertTrue:(Ljava/lang/String;Z)V
     456: ldc           #93                 // String Delete table handler should be called.
     458: aload         5
     460: invokevirtual #94                 // Method org/apache/hadoop/hbase/coprocessor/TestMasterObserver$CPMasterObserver.wasDeleteTableActionCalled:()Z
     463: invokestatic  #18                 // Method org/junit/Assert.assertTrue:(Ljava/lang/String;Z)V
     466: aload         5
     468: invokevirtual #32                 // Method org/apache/hadoop/hbase/coprocessor/TestMasterObserver$CPMasterObserver.resetStates:()V
     471: aload         9
     473: aload         6
     475: invokeinterface #95,  2           // InterfaceMethod org/apache/hadoop/hbase/client/Admin.createTable:(Lorg/apache/hadoop/hbase/client/TableDescriptor;)V
     480: ldc           #51                 // String Test table should be created
     482: aload         5
     484: invokevirtual #34                 // Method org/apache/hadoop/hbase/coprocessor/TestMasterObserver$CPMasterObserver.wasCreateTableCalled:()Z
     487: invokestatic  #18                 // Method org/junit/Assert.assertTrue:(Ljava/lang/String;Z)V
     490: getstatic     #46                 // Field tableCreationLatch:Ljava/util/concurrent/CountDownLatch;
     493: invokevirtual #52                 // Method java/util/concurrent/CountDownLatch.await:()V
     496: ldc           #53                 // String Table pre create handler called.
     498: aload         5
     500: invokevirtual #54                 // Method org/apache/hadoop/hbase/coprocessor/TestMasterObserver$CPMasterObserver.wasPreCreateTableActionCalled:()Z
     503: invokestatic  #18                 // Method org/junit/Assert.assertTrue:(Ljava/lang/String;Z)V
     506: ldc           #55                 // String Table create handler should be called.
     508: aload         5
     510: invokevirtual #56                 // Method org/apache/hadoop/hbase/coprocessor/TestMasterObserver$CPMasterObserver.wasCreateTableActionCalled:()Z
     513: invokestatic  #18                 // Method org/junit/Assert.assertTrue:(Ljava/lang/String;Z)V
     516: aload         5
     518: invokevirtual #71                 // Method org/apache/hadoop/hbase/coprocessor/TestMasterObserver$CPMasterObserver.wasDisableTableCalled:()Z
     521: invokestatic  #75                 // Method org/junit/Assert.assertFalse:(Z)V
     524: aload         5
     526: invokevirtual #73                 // Method org/apache/hadoop/hbase/coprocessor/TestMasterObserver$CPMasterObserver.wasDisableTableActionCalled:()Z
     529: invokestatic  #75                 // Method org/junit/Assert.assertFalse:(Z)V
     532: aload         9
     534: aload_2
     535: invokeinterface #67,  2           // InterfaceMethod org/apache/hadoop/hbase/client/Admin.disableTable:(Lorg/apache/hadoop/hbase/TableName;)V
     540: aload         9
     542: aload_2
     543: invokeinterface #68,  2           // InterfaceMethod org/apache/hadoop/hbase/client/Admin.isTableDisabled:(Lorg/apache/hadoop/hbase/TableName;)Z
     548: invokestatic  #69                 // Method org/junit/Assert.assertTrue:(Z)V
     551: ldc           #70                 // String Coprocessor should have been called on table disable
     553: aload         5
     555: invokevirtual #71                 // Method org/apache/hadoop/hbase/coprocessor/TestMasterObserver$CPMasterObserver.wasDisableTableCalled:()Z
     558: invokestatic  #18                 // Method org/junit/Assert.assertTrue:(Ljava/lang/String;Z)V
     561: ldc           #72                 // String Disable table handler should be called.
     563: aload         5
     565: invokevirtual #73                 // Method org/apache/hadoop/hbase/coprocessor/TestMasterObserver$CPMasterObserver.wasDisableTableActionCalled:()Z
     568: invokestatic  #18                 // Method org/junit/Assert.assertTrue:(Ljava/lang/String;Z)V
     571: aload         6
     573: ldc2_w        #81                 // long 536870912l
     576: invokevirtual #83                 // Method org/apache/hadoop/hbase/HTableDescriptor.setMaxFileSize:(J)Lorg/apache/hadoop/hbase/HTableDescriptor;
     579: pop
     580: aload_0
     581: aload         9
     583: aload_2
     584: aload         6
     586: invokespecial #84                 // Method modifyTableSync:(Lorg/apache/hadoop/hbase/client/Admin;Lorg/apache/hadoop/hbase/TableName;Lorg/apache/hadoop/hbase/HTableDescriptor;)V
     589: ldc           #85                 // String Test table should have been modified
     591: aload         5
     593: invokevirtual #86                 // Method org/apache/hadoop/hbase/coprocessor/TestMasterObserver$CPMasterObserver.wasModifyTableCalled:()Z
     596: invokestatic  #18                 // Method org/junit/Assert.assertTrue:(Ljava/lang/String;Z)V
     599: aload         5
     601: invokevirtual #74                 // Method org/apache/hadoop/hbase/coprocessor/TestMasterObserver$CPMasterObserver.wasEnableTableCalled:()Z
     604: invokestatic  #75                 // Method org/junit/Assert.assertFalse:(Z)V
     607: aload         5
     609: invokevirtual #80                 // Method org/apache/hadoop/hbase/coprocessor/TestMasterObserver$CPMasterObserver.wasEnableTableActionCalled:()Z
     612: invokestatic  #75                 // Method org/junit/Assert.assertFalse:(Z)V
     615: aload         9
     617: aload_2
     618: invokeinterface #76,  2           // InterfaceMethod org/apache/hadoop/hbase/client/Admin.enableTable:(Lorg/apache/hadoop/hbase/TableName;)V
     623: aload         9
     625: aload_2
     626: invokeinterface #77,  2           // InterfaceMethod org/apache/hadoop/hbase/client/Admin.isTableEnabled:(Lorg/apache/hadoop/hbase/TableName;)Z
     631: invokestatic  #69                 // Method org/junit/Assert.assertTrue:(Z)V
     634: ldc           #78                 // String Coprocessor should have been called on table enable
     636: aload         5
     638: invokevirtual #74                 // Method org/apache/hadoop/hbase/coprocessor/TestMasterObserver$CPMasterObserver.wasEnableTableCalled:()Z
     641: invokestatic  #18                 // Method org/junit/Assert.assertTrue:(Ljava/lang/String;Z)V
     644: ldc           #79                 // String Enable table handler should be called.
     646: aload         5
     648: invokevirtual #80                 // Method org/apache/hadoop/hbase/coprocessor/TestMasterObserver$CPMasterObserver.wasEnableTableActionCalled:()Z
     651: invokestatic  #18                 // Method org/junit/Assert.assertTrue:(Ljava/lang/String;Z)V
     654: aload         9
     656: aload_2
     657: invokeinterface #67,  2           // InterfaceMethod org/apache/hadoop/hbase/client/Admin.disableTable:(Lorg/apache/hadoop/hbase/TableName;)V
     662: aload         9
     664: aload_2
     665: invokeinterface #68,  2           // InterfaceMethod org/apache/hadoop/hbase/client/Admin.isTableDisabled:(Lorg/apache/hadoop/hbase/TableName;)Z
     670: invokestatic  #69                 // Method org/junit/Assert.assertTrue:(Z)V
     673: ldc           #96                 // String No table deleted yet
     675: aload         5
     677: invokevirtual #92                 // Method org/apache/hadoop/hbase/coprocessor/TestMasterObserver$CPMasterObserver.wasDeleteTableCalled:()Z
     680: invokestatic  #35                 // Method org/junit/Assert.assertFalse:(Ljava/lang/String;Z)V
     683: ldc           #97                 // String Delete table handler should not be called.
     685: aload         5
     687: invokevirtual #94                 // Method org/apache/hadoop/hbase/coprocessor/TestMasterObserver$CPMasterObserver.wasDeleteTableActionCalled:()Z
     690: invokestatic  #35                 // Method org/junit/Assert.assertFalse:(Ljava/lang/String;Z)V
     693: aload_0
     694: aload         9
     696: aload_2
     697: invokespecial #88                 // Method deleteTable:(Lorg/apache/hadoop/hbase/client/Admin;Lorg/apache/hadoop/hbase/TableName;)V
     700: ldc           #89                 // String Test table should have been deleted
     702: aload         9
     704: aload_2
     705: invokeinterface #90,  2           // InterfaceMethod org/apache/hadoop/hbase/client/Admin.tableExists:(Lorg/apache/hadoop/hbase/TableName;)Z
     710: invokestatic  #35                 // Method org/junit/Assert.assertFalse:(Ljava/lang/String;Z)V
     713: ldc           #91                 // String Coprocessor should have been called on table delete
     715: aload         5
     717: invokevirtual #92                 // Method org/apache/hadoop/hbase/coprocessor/TestMasterObserver$CPMasterObserver.wasDeleteTableCalled:()Z
     720: invokestatic  #18                 // Method org/junit/Assert.assertTrue:(Ljava/lang/String;Z)V
     723: ldc           #93                 // String Delete table handler should be called.
     725: aload         5
     727: invokevirtual #94                 // Method org/apache/hadoop/hbase/coprocessor/TestMasterObserver$CPMasterObserver.wasDeleteTableActionCalled:()Z
     730: invokestatic  #18                 // Method org/junit/Assert.assertTrue:(Ljava/lang/String;Z)V
     733: aload         9
     735: ifnull        828
     738: aload         10
     740: ifnull        765
     743: aload         9
     745: invokeinterface #98,  1           // InterfaceMethod org/apache/hadoop/hbase/client/Admin.close:()V
     750: goto          828
     753: astore        11
     755: aload         10
     757: aload         11
     759: invokevirtual #100                // Method java/lang/Throwable.addSuppressed:(Ljava/lang/Throwable;)V
     762: goto          828
     765: aload         9
     767: invokeinterface #98,  1           // InterfaceMethod org/apache/hadoop/hbase/client/Admin.close:()V
     772: goto          828
     775: astore        11
     777: aload         11
     779: astore        10
     781: aload         11
     783: athrow
     784: astore        13
     786: aload         9
     788: ifnull        825
     791: aload         10
     793: ifnull        818
     796: aload         9
     798: invokeinterface #98,  1           // InterfaceMethod org/apache/hadoop/hbase/client/Admin.close:()V
     803: goto          825
     806: astore        14
     808: aload         10
     810: aload         14
     812: invokevirtual #100                // Method java/lang/Throwable.addSuppressed:(Ljava/lang/Throwable;)V
     815: goto          825
     818: aload         9
     820: invokeinterface #98,  1           // InterfaceMethod org/apache/hadoop/hbase/client/Admin.close:()V
     825: aload         13
     827: athrow
     828: aload         7
     830: ifnull        923
     833: aload         8
     835: ifnull        860
     838: aload         7
     840: invokeinterface #101,  1          // InterfaceMethod org/apache/hadoop/hbase/client/Connection.close:()V
     845: goto          923
     848: astore        9
     850: aload         8
     852: aload         9
     854: invokevirtual #100                // Method java/lang/Throwable.addSuppressed:(Ljava/lang/Throwable;)V
     857: goto          923
     860: aload         7
     862: invokeinterface #101,  1          // InterfaceMethod org/apache/hadoop/hbase/client/Connection.close:()V
     867: goto          923
     870: astore        9
     872: aload         9
     874: astore        8
     876: aload         9
     878: athrow
     879: astore        15
     881: aload         7
     883: ifnull        920
     886: aload         8
     888: ifnull        913
     891: aload         7
     893: invokeinterface #101,  1          // InterfaceMethod org/apache/hadoop/hbase/client/Connection.close:()V
     898: goto          920
     901: astore        16
     903: aload         8
     905: aload         16
     907: invokevirtual #100                // Method java/lang/Throwable.addSuppressed:(Ljava/lang/Throwable;)V
     910: goto          920
     913: aload         7
     915: invokeinterface #101,  1          // InterfaceMethod org/apache/hadoop/hbase/client/Connection.close:()V
     920: aload         15
     922: athrow
     923: return
    Exception table:
       from    to  target type
         743   750   753   Class java/lang/Throwable
         108   733   775   Class java/lang/Throwable
         108   733   784   any
         796   803   806   Class java/lang/Throwable
         775   786   784   any
         838   845   848   Class java/lang/Throwable
          96   828   870   Class java/lang/Throwable
          96   828   879   any
         891   898   901   Class java/lang/Throwable
         870   881   879   any

  public void testSnapshotOperations() throws java.lang.Exception;
    Code:
       0: aload_0
       1: getfield      #4                  // Field name:Lorg/junit/rules/TestName;
       4: invokevirtual #30                 // Method org/junit/rules/TestName.getMethodName:()Ljava/lang/String;
       7: invokestatic  #31                 // Method org/apache/hadoop/hbase/TableName.valueOf:(Ljava/lang/String;)Lorg/apache/hadoop/hbase/TableName;
      10: astore_1
      11: getstatic     #5                  // Field UTIL:Lorg/apache/hadoop/hbase/HBaseTestingUtility;
      14: invokevirtual #14                 // Method org/apache/hadoop/hbase/HBaseTestingUtility.getHBaseCluster:()Lorg/apache/hadoop/hbase/MiniHBaseCluster;
      17: astore_2
      18: aload_2
      19: invokevirtual #15                 // Method org/apache/hadoop/hbase/MiniHBaseCluster.getMaster:()Lorg/apache/hadoop/hbase/master/HMaster;
      22: astore_3
      23: aload_3
      24: invokevirtual #19                 // Method org/apache/hadoop/hbase/master/HMaster.getMasterCoprocessorHost:()Lorg/apache/hadoop/hbase/master/MasterCoprocessorHost;
      27: astore        4
      29: aload         4
      31: ldc           #9                  // class org/apache/hadoop/hbase/coprocessor/TestMasterObserver$CPMasterObserver
      33: invokevirtual #22                 // Method org/apache/hadoop/hbase/master/MasterCoprocessorHost.findCoprocessor:(Ljava/lang/Class;)Lorg/apache/hadoop/hbase/Coprocessor;
      36: checkcast     #9                  // class org/apache/hadoop/hbase/coprocessor/TestMasterObserver$CPMasterObserver
      39: astore        5
      41: aload         5
      43: invokevirtual #32                 // Method org/apache/hadoop/hbase/coprocessor/TestMasterObserver$CPMasterObserver.resetStates:()V
      46: new           #36                 // class org/apache/hadoop/hbase/HTableDescriptor
      49: dup
      50: aload_1
      51: invokespecial #37                 // Method org/apache/hadoop/hbase/HTableDescriptor."<init>":(Lorg/apache/hadoop/hbase/TableName;)V
      54: astore        6
      56: aload         6
      58: new           #38                 // class org/apache/hadoop/hbase/HColumnDescriptor
      61: dup
      62: getstatic     #39                 // Field TEST_FAMILY:[B
      65: invokespecial #40                 // Method org/apache/hadoop/hbase/HColumnDescriptor."<init>":([B)V
      68: invokevirtual #41                 // Method org/apache/hadoop/hbase/HTableDescriptor.addFamily:(Lorg/apache/hadoop/hbase/HColumnDescriptor;)Lorg/apache/hadoop/hbase/HTableDescriptor;
      71: pop
      72: getstatic     #5                  // Field UTIL:Lorg/apache/hadoop/hbase/HBaseTestingUtility;
      75: invokevirtual #102                // Method org/apache/hadoop/hbase/HBaseTestingUtility.getAdmin:()Lorg/apache/hadoop/hbase/client/Admin;
      78: astore        7
      80: new           #44                 // class java/util/concurrent/CountDownLatch
      83: dup
      84: iconst_1
      85: invokespecial #45                 // Method java/util/concurrent/CountDownLatch."<init>":(I)V
      88: putstatic     #46                 // Field tableCreationLatch:Ljava/util/concurrent/CountDownLatch;
      91: aload         7
      93: aload         6
      95: invokeinterface #95,  2           // InterfaceMethod org/apache/hadoop/hbase/client/Admin.createTable:(Lorg/apache/hadoop/hbase/client/TableDescriptor;)V
     100: getstatic     #46                 // Field tableCreationLatch:Ljava/util/concurrent/CountDownLatch;
     103: invokevirtual #52                 // Method java/util/concurrent/CountDownLatch.await:()V
     106: new           #44                 // class java/util/concurrent/CountDownLatch
     109: dup
     110: iconst_1
     111: invokespecial #45                 // Method java/util/concurrent/CountDownLatch."<init>":(I)V
     114: putstatic     #46                 // Field tableCreationLatch:Ljava/util/concurrent/CountDownLatch;
     117: aload         7
     119: aload_1
     120: invokeinterface #67,  2           // InterfaceMethod org/apache/hadoop/hbase/client/Admin.disableTable:(Lorg/apache/hadoop/hbase/TableName;)V
     125: aload         7
     127: aload_1
     128: invokeinterface #68,  2           // InterfaceMethod org/apache/hadoop/hbase/client/Admin.isTableDisabled:(Lorg/apache/hadoop/hbase/TableName;)Z
     133: invokestatic  #69                 // Method org/junit/Assert.assertTrue:(Z)V
     136: ldc           #103                // String Coprocessor should not have been called yet
     138: aload         5
     140: invokevirtual #104                // Method org/apache/hadoop/hbase/coprocessor/TestMasterObserver$CPMasterObserver.wasSnapshotCalled:()Z
     143: invokestatic  #35                 // Method org/junit/Assert.assertFalse:(Ljava/lang/String;Z)V
     146: aload         7
     148: getstatic     #105                // Field TEST_SNAPSHOT:Ljava/lang/String;
     151: aload_1
     152: invokeinterface #106,  3          // InterfaceMethod org/apache/hadoop/hbase/client/Admin.snapshot:(Ljava/lang/String;Lorg/apache/hadoop/hbase/TableName;)V
     157: ldc           #107                // String Coprocessor should have been called on snapshot
     159: aload         5
     161: invokevirtual #104                // Method org/apache/hadoop/hbase/coprocessor/TestMasterObserver$CPMasterObserver.wasSnapshotCalled:()Z
     164: invokestatic  #18                 // Method org/junit/Assert.assertTrue:(Ljava/lang/String;Z)V
     167: aload         7
     169: invokeinterface #108,  1          // InterfaceMethod org/apache/hadoop/hbase/client/Admin.listSnapshots:()Ljava/util/List;
     174: pop
     175: ldc           #109                // String Coprocessor should have been called on snapshot list
     177: aload         5
     179: invokevirtual #110                // Method org/apache/hadoop/hbase/coprocessor/TestMasterObserver$CPMasterObserver.wasListSnapshotCalled:()Z
     182: invokestatic  #18                 // Method org/junit/Assert.assertTrue:(Ljava/lang/String;Z)V
     185: aload         7
     187: getstatic     #105                // Field TEST_SNAPSHOT:Ljava/lang/String;
     190: getstatic     #111                // Field TEST_CLONE:Lorg/apache/hadoop/hbase/TableName;
     193: invokeinterface #112,  3          // InterfaceMethod org/apache/hadoop/hbase/client/Admin.cloneSnapshot:(Ljava/lang/String;Lorg/apache/hadoop/hbase/TableName;)V
     198: ldc           #113                // String Coprocessor should have been called on snapshot clone
     200: aload         5
     202: invokevirtual #114                // Method org/apache/hadoop/hbase/coprocessor/TestMasterObserver$CPMasterObserver.wasCloneSnapshotCalled:()Z
     205: invokestatic  #18                 // Method org/junit/Assert.assertTrue:(Ljava/lang/String;Z)V
     208: ldc           #115                // String Coprocessor restore should not have been called on snapshot clone
     210: aload         5
     212: invokevirtual #116                // Method org/apache/hadoop/hbase/coprocessor/TestMasterObserver$CPMasterObserver.wasRestoreSnapshotCalled:()Z
     215: invokestatic  #35                 // Method org/junit/Assert.assertFalse:(Ljava/lang/String;Z)V
     218: aload         7
     220: getstatic     #111                // Field TEST_CLONE:Lorg/apache/hadoop/hbase/TableName;
     223: invokeinterface #67,  2           // InterfaceMethod org/apache/hadoop/hbase/client/Admin.disableTable:(Lorg/apache/hadoop/hbase/TableName;)V
     228: aload         7
     230: aload_1
     231: invokeinterface #68,  2           // InterfaceMethod org/apache/hadoop/hbase/client/Admin.isTableDisabled:(Lorg/apache/hadoop/hbase/TableName;)Z
     236: invokestatic  #69                 // Method org/junit/Assert.assertTrue:(Z)V
     239: aload_0
     240: aload         7
     242: getstatic     #111                // Field TEST_CLONE:Lorg/apache/hadoop/hbase/TableName;
     245: invokespecial #88                 // Method deleteTable:(Lorg/apache/hadoop/hbase/client/Admin;Lorg/apache/hadoop/hbase/TableName;)V
     248: aload         5
     250: invokevirtual #32                 // Method org/apache/hadoop/hbase/coprocessor/TestMasterObserver$CPMasterObserver.resetStates:()V
     253: aload         7
     255: getstatic     #105                // Field TEST_SNAPSHOT:Ljava/lang/String;
     258: invokeinterface #117,  2          // InterfaceMethod org/apache/hadoop/hbase/client/Admin.restoreSnapshot:(Ljava/lang/String;)V
     263: ldc           #118                // String Coprocessor should have been called on snapshot restore
     265: aload         5
     267: invokevirtual #116                // Method org/apache/hadoop/hbase/coprocessor/TestMasterObserver$CPMasterObserver.wasRestoreSnapshotCalled:()Z
     270: invokestatic  #18                 // Method org/junit/Assert.assertTrue:(Ljava/lang/String;Z)V
     273: ldc           #119                // String Coprocessor clone should not have been called on snapshot restore
     275: aload         5
     277: invokevirtual #114                // Method org/apache/hadoop/hbase/coprocessor/TestMasterObserver$CPMasterObserver.wasCloneSnapshotCalled:()Z
     280: invokestatic  #35                 // Method org/junit/Assert.assertFalse:(Ljava/lang/String;Z)V
     283: aload         7
     285: getstatic     #105                // Field TEST_SNAPSHOT:Ljava/lang/String;
     288: invokeinterface #120,  2          // InterfaceMethod org/apache/hadoop/hbase/client/Admin.deleteSnapshot:(Ljava/lang/String;)V
     293: ldc           #121                // String Coprocessor should have been called on snapshot delete
     295: aload         5
     297: invokevirtual #122                // Method org/apache/hadoop/hbase/coprocessor/TestMasterObserver$CPMasterObserver.wasDeleteSnapshotCalled:()Z
     300: invokestatic  #18                 // Method org/junit/Assert.assertTrue:(Ljava/lang/String;Z)V
     303: aload_0
     304: aload         7
     306: aload_1
     307: invokespecial #88                 // Method deleteTable:(Lorg/apache/hadoop/hbase/client/Admin;Lorg/apache/hadoop/hbase/TableName;)V
     310: goto          325
     313: astore        8
     315: aload_0
     316: aload         7
     318: aload_1
     319: invokespecial #88                 // Method deleteTable:(Lorg/apache/hadoop/hbase/client/Admin;Lorg/apache/hadoop/hbase/TableName;)V
     322: aload         8
     324: athrow
     325: return
    Exception table:
       from    to  target type
         136   303   313   any
         313   315   313   any

  public void testNamespaceOperations() throws java.lang.Exception;
    Code:
       0: getstatic     #5                  // Field UTIL:Lorg/apache/hadoop/hbase/HBaseTestingUtility;
       3: invokevirtual #14                 // Method org/apache/hadoop/hbase/HBaseTestingUtility.getHBaseCluster:()Lorg/apache/hadoop/hbase/MiniHBaseCluster;
       6: astore_1
       7: ldc           #123                // String observed_ns
       9: astore_2
      10: aload_1
      11: invokevirtual #15                 // Method org/apache/hadoop/hbase/MiniHBaseCluster.getMaster:()Lorg/apache/hadoop/hbase/master/HMaster;
      14: astore_3
      15: aload_3
      16: invokevirtual #19                 // Method org/apache/hadoop/hbase/master/HMaster.getMasterCoprocessorHost:()Lorg/apache/hadoop/hbase/master/MasterCoprocessorHost;
      19: astore        4
      21: aload         4
      23: ldc           #9                  // class org/apache/hadoop/hbase/coprocessor/TestMasterObserver$CPMasterObserver
      25: invokevirtual #22                 // Method org/apache/hadoop/hbase/master/MasterCoprocessorHost.findCoprocessor:(Ljava/lang/Class;)Lorg/apache/hadoop/hbase/Coprocessor;
      28: checkcast     #9                  // class org/apache/hadoop/hbase/coprocessor/TestMasterObserver$CPMasterObserver
      31: astore        5
      33: getstatic     #5                  // Field UTIL:Lorg/apache/hadoop/hbase/HBaseTestingUtility;
      36: invokevirtual #102                // Method org/apache/hadoop/hbase/HBaseTestingUtility.getAdmin:()Lorg/apache/hadoop/hbase/client/Admin;
      39: astore        6
      41: aload         6
      43: invokeinterface #124,  1          // InterfaceMethod org/apache/hadoop/hbase/client/Admin.listNamespaces:()[Ljava/lang/String;
      48: pop
      49: ldc           #125                // String preListNamespaces should have been called
      51: aload         5
      53: invokestatic  #126                // Method org/apache/hadoop/hbase/coprocessor/TestMasterObserver$CPMasterObserver.access$000:(Lorg/apache/hadoop/hbase/coprocessor/TestMasterObserver$CPMasterObserver;)Z
      56: invokestatic  #18                 // Method org/junit/Assert.assertTrue:(Ljava/lang/String;Z)V
      59: ldc           #127                // String postListNamespaces should have been called
      61: aload         5
      63: invokestatic  #128                // Method org/apache/hadoop/hbase/coprocessor/TestMasterObserver$CPMasterObserver.access$100:(Lorg/apache/hadoop/hbase/coprocessor/TestMasterObserver$CPMasterObserver;)Z
      66: invokestatic  #18                 // Method org/junit/Assert.assertTrue:(Ljava/lang/String;Z)V
      69: aload         6
      71: aload_2
      72: invokestatic  #129                // Method org/apache/hadoop/hbase/NamespaceDescriptor.create:(Ljava/lang/String;)Lorg/apache/hadoop/hbase/NamespaceDescriptor$Builder;
      75: invokevirtual #130                // Method org/apache/hadoop/hbase/NamespaceDescriptor$Builder.build:()Lorg/apache/hadoop/hbase/NamespaceDescriptor;
      78: invokeinterface #131,  2          // InterfaceMethod org/apache/hadoop/hbase/client/Admin.createNamespace:(Lorg/apache/hadoop/hbase/NamespaceDescriptor;)V
      83: ldc           #132                // String Test namespace should be created
      85: aload         5
      87: invokevirtual #133                // Method org/apache/hadoop/hbase/coprocessor/TestMasterObserver$CPMasterObserver.wasCreateNamespaceCalled:()Z
      90: invokestatic  #18                 // Method org/junit/Assert.assertTrue:(Ljava/lang/String;Z)V
      93: aload         6
      95: aload_2
      96: invokeinterface #134,  2          // InterfaceMethod org/apache/hadoop/hbase/client/Admin.getNamespaceDescriptor:(Ljava/lang/String;)Lorg/apache/hadoop/hbase/NamespaceDescriptor;
     101: invokestatic  #135                // Method org/junit/Assert.assertNotNull:(Ljava/lang/Object;)V
     104: ldc           #136                // String Test namespace descriptor should have been called
     106: aload         5
     108: invokevirtual #137                // Method org/apache/hadoop/hbase/coprocessor/TestMasterObserver$CPMasterObserver.wasGetNamespaceDescriptorCalled:()Z
     111: invokestatic  #18                 // Method org/junit/Assert.assertTrue:(Ljava/lang/String;Z)V
     114: return

  public void testRegionTransitionOperations() throws java.lang.Exception;
    Code:
       0: aload_0
       1: getfield      #4                  // Field name:Lorg/junit/rules/TestName;
       4: invokevirtual #30                 // Method org/junit/rules/TestName.getMethodName:()Ljava/lang/String;
       7: invokestatic  #31                 // Method org/apache/hadoop/hbase/TableName.valueOf:(Ljava/lang/String;)Lorg/apache/hadoop/hbase/TableName;
      10: astore_1
      11: getstatic     #5                  // Field UTIL:Lorg/apache/hadoop/hbase/HBaseTestingUtility;
      14: invokevirtual #14                 // Method org/apache/hadoop/hbase/HBaseTestingUtility.getHBaseCluster:()Lorg/apache/hadoop/hbase/MiniHBaseCluster;
      17: astore_2
      18: aload_2
      19: invokevirtual #15                 // Method org/apache/hadoop/hbase/MiniHBaseCluster.getMaster:()Lorg/apache/hadoop/hbase/master/HMaster;
      22: astore_3
      23: aload_3
      24: invokevirtual #19                 // Method org/apache/hadoop/hbase/master/HMaster.getMasterCoprocessorHost:()Lorg/apache/hadoop/hbase/master/MasterCoprocessorHost;
      27: astore        4
      29: aload         4
      31: ldc           #9                  // class org/apache/hadoop/hbase/coprocessor/TestMasterObserver$CPMasterObserver
      33: invokevirtual #22                 // Method org/apache/hadoop/hbase/master/MasterCoprocessorHost.findCoprocessor:(Ljava/lang/Class;)Lorg/apache/hadoop/hbase/Coprocessor;
      36: checkcast     #9                  // class org/apache/hadoop/hbase/coprocessor/TestMasterObserver$CPMasterObserver
      39: astore        5
      41: aload         5
      43: invokevirtual #32                 // Method org/apache/hadoop/hbase/coprocessor/TestMasterObserver$CPMasterObserver.resetStates:()V
      46: getstatic     #5                  // Field UTIL:Lorg/apache/hadoop/hbase/HBaseTestingUtility;
      49: aload_1
      50: getstatic     #39                 // Field TEST_FAMILY:[B
      53: invokevirtual #145                // Method org/apache/hadoop/hbase/HBaseTestingUtility.createMultiRegionTable:(Lorg/apache/hadoop/hbase/TableName;[B)Lorg/apache/hadoop/hbase/client/Table;
      56: astore        6
      58: getstatic     #5                  // Field UTIL:Lorg/apache/hadoop/hbase/HBaseTestingUtility;
      61: invokevirtual #146                // Method org/apache/hadoop/hbase/HBaseTestingUtility.getConnection:()Lorg/apache/hadoop/hbase/client/Connection;
      64: aload_1
      65: invokeinterface #58,  2           // InterfaceMethod org/apache/hadoop/hbase/client/Connection.getRegionLocator:(Lorg/apache/hadoop/hbase/TableName;)Lorg/apache/hadoop/hbase/client/RegionLocator;
      70: astore        7
      72: aconst_null
      73: astore        8
      75: getstatic     #5                  // Field UTIL:Lorg/apache/hadoop/hbase/HBaseTestingUtility;
      78: aload_1
      79: invokevirtual #147                // Method org/apache/hadoop/hbase/HBaseTestingUtility.waitUntilAllRegionsAssigned:(Lorg/apache/hadoop/hbase/TableName;)V
      82: aload         7
      84: invokeinterface #59,  1           // InterfaceMethod org/apache/hadoop/hbase/client/RegionLocator.getAllRegionLocations:()Ljava/util/List;
      89: astore        9
      91: aconst_null
      92: astore        10
      94: aload         9
      96: invokeinterface #148,  1          // InterfaceMethod java/util/List.iterator:()Ljava/util/Iterator;
     101: astore        11
     103: aload         11
     105: invokeinterface #149,  1          // InterfaceMethod java/util/Iterator.hasNext:()Z
     110: ifeq          143
     113: aload         11
     115: invokeinterface #150,  1          // InterfaceMethod java/util/Iterator.next:()Ljava/lang/Object;
     120: checkcast     #61                 // class org/apache/hadoop/hbase/HRegionLocation
     123: astore        12
     125: aload         12
     127: invokevirtual #151                // Method org/apache/hadoop/hbase/HRegionLocation.getServerName:()Lorg/apache/hadoop/hbase/ServerName;
     130: ifnull        140
     133: aload         12
     135: astore        10
     137: goto          143
     140: goto          103
     143: ldc           #152                // String Found a non-null entry
     145: aload         10
     147: invokestatic  #21                 // Method org/junit/Assert.assertNotNull:(Ljava/lang/String;Ljava/lang/Object;)V
     150: getstatic     #153                // Field LOG:Lorg/slf4j/Logger;
     153: new           #154                // class java/lang/StringBuilder
     156: dup
     157: invokespecial #155                // Method java/lang/StringBuilder."<init>":()V
     160: ldc           #156                // String Found
     162: invokevirtual #157                // Method java/lang/StringBuilder.append:(Ljava/lang/String;)Ljava/lang/StringBuilder;
     165: aload         10
     167: invokevirtual #158                // Method org/apache/hadoop/hbase/HRegionLocation.toString:()Ljava/lang/String;
     170: invokevirtual #157                // Method java/lang/StringBuilder.append:(Ljava/lang/String;)Ljava/lang/StringBuilder;
     173: invokevirtual #159                // Method java/lang/StringBuilder.toString:()Ljava/lang/String;
     176: invokeinterface #160,  2          // InterfaceMethod org/slf4j/Logger.info:(Ljava/lang/String;)V
     181: aload_3
     182: invokevirtual #161                // Method org/apache/hadoop/hbase/master/HMaster.getClusterMetrics:()Lorg/apache/hadoop/hbase/ClusterMetrics;
     185: invokeinterface #162,  1          // InterfaceMethod org/apache/hadoop/hbase/ClusterMetrics.getLiveServerMetrics:()Ljava/util/Map;
     190: invokeinterface #163,  1          // InterfaceMethod java/util/Map.keySet:()Ljava/util/Set;
     195: astore        11
     197: aconst_null
     198: astore        12
     200: aload         10
     202: invokevirtual #151                // Method org/apache/hadoop/hbase/HRegionLocation.getServerName:()Lorg/apache/hadoop/hbase/ServerName;
     205: invokevirtual #164                // Method org/apache/hadoop/hbase/ServerName.toString:()Ljava/lang/String;
     208: astore        13
     210: getstatic     #153                // Field LOG:Lorg/slf4j/Logger;
     213: new           #154                // class java/lang/StringBuilder
     216: dup
     217: invokespecial #155                // Method java/lang/StringBuilder."<init>":()V
     220: ldc           #165                // String serverNameForFirstRegion=
     222: invokevirtual #157                // Method java/lang/StringBuilder.append:(Ljava/lang/String;)Ljava/lang/StringBuilder;
     225: aload         13
     227: invokevirtual #157                // Method java/lang/StringBuilder.append:(Ljava/lang/String;)Ljava/lang/StringBuilder;
     230: invokevirtual #159                // Method java/lang/StringBuilder.toString:()Ljava/lang/String;
     233: invokeinterface #160,  2          // InterfaceMethod org/slf4j/Logger.info:(Ljava/lang/String;)V
     238: aload_3
     239: invokevirtual #166                // Method org/apache/hadoop/hbase/master/HMaster.getServerName:()Lorg/apache/hadoop/hbase/ServerName;
     242: astore        14
     244: iconst_0
     245: istore        15
     247: aload         11
     249: invokeinterface #167,  1          // InterfaceMethod java/util/Collection.iterator:()Ljava/util/Iterator;
     254: astore        16
     256: aload         16
     258: invokeinterface #149,  1          // InterfaceMethod java/util/Iterator.hasNext:()Z
     263: ifeq          345
     266: aload         16
     268: invokeinterface #150,  1          // InterfaceMethod java/util/Iterator.next:()Ljava/lang/Object;
     273: checkcast     #168                // class org/apache/hadoop/hbase/ServerName
     276: astore        17
     278: getstatic     #153                // Field LOG:Lorg/slf4j/Logger;
     281: new           #154                // class java/lang/StringBuilder
     284: dup
     285: invokespecial #155                // Method java/lang/StringBuilder."<init>":()V
     288: ldc           #169                // String ServerName=
     290: invokevirtual #157                // Method java/lang/StringBuilder.append:(Ljava/lang/String;)Ljava/lang/StringBuilder;
     293: aload         17
     295: invokevirtual #170                // Method java/lang/StringBuilder.append:(Ljava/lang/Object;)Ljava/lang/StringBuilder;
     298: invokevirtual #159                // Method java/lang/StringBuilder.toString:()Ljava/lang/String;
     301: invokeinterface #160,  2          // InterfaceMethod org/slf4j/Logger.info:(Ljava/lang/String;)V
     306: aload         13
     308: aload         17
     310: invokevirtual #171                // Method org/apache/hadoop/hbase/ServerName.getServerName:()Ljava/lang/String;
     313: invokevirtual #172                // Method java/lang/String.equals:(Ljava/lang/Object;)Z
     316: ifne          342
     319: aload         14
     321: aload         17
     323: invokevirtual #173                // Method org/apache/hadoop/hbase/ServerName.equals:(Ljava/lang/Object;)Z
     326: ifne          342
     329: aload         17
     331: invokevirtual #164                // Method org/apache/hadoop/hbase/ServerName.toString:()Ljava/lang/String;
     334: astore        12
     336: iconst_1
     337: istore        15
     339: goto          345
     342: goto          256
     345: ldc           #174                // String Found server
     347: iload         15
     349: invokestatic  #18                 // Method org/junit/Assert.assertTrue:(Ljava/lang/String;Z)V
     352: getstatic     #153                // Field LOG:Lorg/slf4j/Logger;
     355: new           #154                // class java/lang/StringBuilder
     358: dup
     359: invokespecial #155                // Method java/lang/StringBuilder."<init>":()V
     362: ldc           #156                // String Found
     364: invokevirtual #157                // Method java/lang/StringBuilder.append:(Ljava/lang/String;)Ljava/lang/StringBuilder;
     367: aload         12
     369: invokevirtual #157                // Method java/lang/StringBuilder.append:(Ljava/lang/String;)Ljava/lang/StringBuilder;
     372: invokevirtual #159                // Method java/lang/StringBuilder.toString:()Ljava/lang/String;
     375: invokeinterface #160,  2          // InterfaceMethod org/slf4j/Logger.info:(Ljava/lang/String;)V
     380: aload_3
     381: invokevirtual #175                // Method org/apache/hadoop/hbase/master/HMaster.getMasterRpcServices:()Lorg/apache/hadoop/hbase/master/MasterRpcServices;
     384: aconst_null
     385: aload         10
     387: invokevirtual #62                 // Method org/apache/hadoop/hbase/HRegionLocation.getRegionInfo:()Lorg/apache/hadoop/hbase/HRegionInfo;
     390: invokevirtual #63                 // Method org/apache/hadoop/hbase/HRegionInfo.getEncodedNameAsBytes:()[B
     393: aload         12
     395: invokestatic  #176                // Method org/apache/hadoop/hbase/ServerName.valueOf:(Ljava/lang/String;)Lorg/apache/hadoop/hbase/ServerName;
     398: invokestatic  #177                // Method org/apache/hadoop/hbase/shaded/protobuf/RequestConverter.buildMoveRegionRequest:([BLorg/apache/hadoop/hbase/ServerName;)Lorg/apache/hadoop/hbase/shaded/protobuf/generated/MasterProtos$MoveRegionRequest;
     401: invokevirtual #178                // Method org/apache/hadoop/hbase/master/MasterRpcServices.moveRegion:(Lorg/apache/hbase/thirdparty/com/google/protobuf/RpcController;Lorg/apache/hadoop/hbase/shaded/protobuf/generated/MasterProtos$MoveRegionRequest;)Lorg/apache/hadoop/hbase/shaded/protobuf/generated/MasterProtos$MoveRegionResponse;
     404: pop
     405: ldc           #179                // String Coprocessor should have been called on region move
     407: aload         5
     409: invokevirtual #180                // Method org/apache/hadoop/hbase/coprocessor/TestMasterObserver$CPMasterObserver.wasMoveCalled:()Z
     412: invokestatic  #18                 // Method org/junit/Assert.assertTrue:(Ljava/lang/String;Z)V
     415: aload_3
     416: iconst_1
     417: invokevirtual #181                // Method org/apache/hadoop/hbase/master/HMaster.balanceSwitch:(Z)Z
     420: pop
     421: ldc           #182                // String Coprocessor should have been called on balance switch
     423: aload         5
     425: invokevirtual #183                // Method org/apache/hadoop/hbase/coprocessor/TestMasterObserver$CPMasterObserver.wasBalanceSwitchCalled:()Z
     428: invokestatic  #18                 // Method org/junit/Assert.assertTrue:(Ljava/lang/String;Z)V
     431: aload_3
     432: iconst_0
     433: invokevirtual #181                // Method org/apache/hadoop/hbase/master/HMaster.balanceSwitch:(Z)Z
     436: pop
     437: getstatic     #5                  // Field UTIL:Lorg/apache/hadoop/hbase/HBaseTestingUtility;
     440: invokevirtual #184                // Method org/apache/hadoop/hbase/HBaseTestingUtility.waitUntilNoRegionsInTransition:()V
     443: aload_2
     444: iconst_0
     445: invokevirtual #185                // Method org/apache/hadoop/hbase/MiniHBaseCluster.getRegionServer:(I)Lorg/apache/hadoop/hbase/regionserver/HRegionServer;
     448: astore        16
     450: aload_2
     451: iconst_1
     452: invokevirtual #185                // Method org/apache/hadoop/hbase/MiniHBaseCluster.getRegionServer:(I)Lorg/apache/hadoop/hbase/regionserver/HRegionServer;
     455: invokevirtual #186                // Method org/apache/hadoop/hbase/regionserver/HRegionServer.getServerName:()Lorg/apache/hadoop/hbase/ServerName;
     458: invokevirtual #164                // Method org/apache/hadoop/hbase/ServerName.toString:()Ljava/lang/String;
     461: invokestatic  #187                // Method org/apache/hadoop/hbase/util/Bytes.toBytes:(Ljava/lang/String;)[B
     464: astore        17
     466: getstatic     #5                  // Field UTIL:Lorg/apache/hadoop/hbase/HBaseTestingUtility;
     469: invokevirtual #184                // Method org/apache/hadoop/hbase/HBaseTestingUtility.waitUntilNoRegionsInTransition:()V
     472: aload         16
     474: invokevirtual #188                // Method org/apache/hadoop/hbase/regionserver/HRegionServer.getRSRpcServices:()Lorg/apache/hadoop/hbase/regionserver/RSRpcServices;
     477: invokestatic  #189                // Method org/apache/hadoop/hbase/shaded/protobuf/ProtobufUtil.getOnlineRegions:(Lorg/apache/hadoop/hbase/shaded/protobuf/generated/AdminProtos$AdminService$BlockingInterface;)Ljava/util/List;
     480: astore        18
     482: aload         18
     484: invokeinterface #190,  1          // InterfaceMethod java/util/List.size:()I
     489: iconst_2
     490: idiv
     491: istore        19
     493: iconst_0
     494: istore        20
     496: iload         20
     498: iload         19
     500: if_icmpge     570
     503: aload         18
     505: iload         20
     507: invokeinterface #60,  2           // InterfaceMethod java/util/List.get:(I)Ljava/lang/Object;
     512: checkcast     #191                // class org/apache/hadoop/hbase/client/RegionInfo
     515: astore        21
     517: aload         21
     519: invokeinterface #192,  1          // InterfaceMethod org/apache/hadoop/hbase/client/RegionInfo.isMetaRegion:()Z
     524: ifne          564
     527: aload_3
     528: invokevirtual #175                // Method org/apache/hadoop/hbase/master/HMaster.getMasterRpcServices:()Lorg/apache/hadoop/hbase/master/MasterRpcServices;
     531: aconst_null
     532: aload         18
     534: iload         20
     536: invokeinterface #60,  2           // InterfaceMethod java/util/List.get:(I)Ljava/lang/Object;
     541: checkcast     #191                // class org/apache/hadoop/hbase/client/RegionInfo
     544: invokeinterface #193,  1          // InterfaceMethod org/apache/hadoop/hbase/client/RegionInfo.getEncodedNameAsBytes:()[B
     549: aload         17
     551: invokestatic  #194                // Method org/apache/hadoop/hbase/util/Bytes.toString:([B)Ljava/lang/String;
     554: invokestatic  #176                // Method org/apache/hadoop/hbase/ServerName.valueOf:(Ljava/lang/String;)Lorg/apache/hadoop/hbase/ServerName;
     557: invokestatic  #177                // Method org/apache/hadoop/hbase/shaded/protobuf/RequestConverter.buildMoveRegionRequest:([BLorg/apache/hadoop/hbase/ServerName;)Lorg/apache/hadoop/hbase/shaded/protobuf/generated/MasterProtos$MoveRegionRequest;
     560: invokevirtual #178                // Method org/apache/hadoop/hbase/master/MasterRpcServices.moveRegion:(Lorg/apache/hbase/thirdparty/com/google/protobuf/RpcController;Lorg/apache/hadoop/hbase/shaded/protobuf/generated/MasterProtos$MoveRegionRequest;)Lorg/apache/hadoop/hbase/shaded/protobuf/generated/MasterProtos$MoveRegionResponse;
     563: pop
     564: iinc          20, 1
     567: goto          496
     570: getstatic     #5                  // Field UTIL:Lorg/apache/hadoop/hbase/HBaseTestingUtility;
     573: invokevirtual #184                // Method org/apache/hadoop/hbase/HBaseTestingUtility.waitUntilNoRegionsInTransition:()V
     576: aload_3
     577: iconst_1
     578: invokevirtual #181                // Method org/apache/hadoop/hbase/master/HMaster.balanceSwitch:(Z)Z
     581: pop
     582: aload_3
     583: invokevirtual #195                // Method org/apache/hadoop/hbase/master/HMaster.balance:()Z
     586: istore        20
     588: ldc           #196                // String Coprocessor should be called on region rebalancing
     590: aload         5
     592: invokevirtual #197                // Method org/apache/hadoop/hbase/coprocessor/TestMasterObserver$CPMasterObserver.wasBalanceCalled:()Z
     595: invokestatic  #18                 // Method org/junit/Assert.assertTrue:(Ljava/lang/String;Z)V
     598: aload         7
     600: ifnull        693
     603: aload         8
     605: ifnull        630
     608: aload         7
     610: invokeinterface #198,  1          // InterfaceMethod org/apache/hadoop/hbase/client/RegionLocator.close:()V
     615: goto          693
     618: astore        9
     620: aload         8
     622: aload         9
     624: invokevirtual #100                // Method java/lang/Throwable.addSuppressed:(Ljava/lang/Throwable;)V
     627: goto          693
     630: aload         7
     632: invokeinterface #198,  1          // InterfaceMethod org/apache/hadoop/hbase/client/RegionLocator.close:()V
     637: goto          693
     640: astore        9
     642: aload         9
     644: astore        8
     646: aload         9
     648: athrow
     649: astore        22
     651: aload         7
     653: ifnull        690
     656: aload         8
     658: ifnull        683
     661: aload         7
     663: invokeinterface #198,  1          // InterfaceMethod org/apache/hadoop/hbase/client/RegionLocator.close:()V
     668: goto          690
     671: astore        23
     673: aload         8
     675: aload         23
     677: invokevirtual #100                // Method java/lang/Throwable.addSuppressed:(Ljava/lang/Throwable;)V
     680: goto          690
     683: aload         7
     685: invokeinterface #198,  1          // InterfaceMethod org/apache/hadoop/hbase/client/RegionLocator.close:()V
     690: aload         22
     692: athrow
     693: getstatic     #5                  // Field UTIL:Lorg/apache/hadoop/hbase/HBaseTestingUtility;
     696: invokevirtual #102                // Method org/apache/hadoop/hbase/HBaseTestingUtility.getAdmin:()Lorg/apache/hadoop/hbase/client/Admin;
     699: astore        7
     701: aload         7
     703: aload_1
     704: invokeinterface #67,  2           // InterfaceMethod org/apache/hadoop/hbase/client/Admin.disableTable:(Lorg/apache/hadoop/hbase/TableName;)V
     709: aload_0
     710: aload         7
     712: aload_1
     713: invokespecial #88                 // Method deleteTable:(Lorg/apache/hadoop/hbase/client/Admin;Lorg/apache/hadoop/hbase/TableName;)V
     716: goto          747
     719: astore        24
     721: getstatic     #5                  // Field UTIL:Lorg/apache/hadoop/hbase/HBaseTestingUtility;
     724: invokevirtual #102                // Method org/apache/hadoop/hbase/HBaseTestingUtility.getAdmin:()Lorg/apache/hadoop/hbase/client/Admin;
     727: astore        25
     729: aload         25
     731: aload_1
     732: invokeinterface #67,  2           // InterfaceMethod org/apache/hadoop/hbase/client/Admin.disableTable:(Lorg/apache/hadoop/hbase/TableName;)V
     737: aload_0
     738: aload         25
     740: aload_1
     741: invokespecial #88                 // Method deleteTable:(Lorg/apache/hadoop/hbase/client/Admin;Lorg/apache/hadoop/hbase/TableName;)V
     744: aload         24
     746: athrow
     747: return
    Exception table:
       from    to  target type
         608   615   618   Class java/lang/Throwable
          75   598   640   Class java/lang/Throwable
          75   598   649   any
         661   668   671   Class java/lang/Throwable
         640   651   649   any
          58   693   719   any
         719   721   719   any

  public void testTableDescriptorsEnumeration() throws java.lang.Exception;
    Code:
       0: getstatic     #5                  // Field UTIL:Lorg/apache/hadoop/hbase/HBaseTestingUtility;
       3: invokevirtual #14                 // Method org/apache/hadoop/hbase/HBaseTestingUtility.getHBaseCluster:()Lorg/apache/hadoop/hbase/MiniHBaseCluster;
       6: astore_1
       7: aload_1
       8: invokevirtual #15                 // Method org/apache/hadoop/hbase/MiniHBaseCluster.getMaster:()Lorg/apache/hadoop/hbase/master/HMaster;
      11: astore_2
      12: aload_2
      13: invokevirtual #19                 // Method org/apache/hadoop/hbase/master/HMaster.getMasterCoprocessorHost:()Lorg/apache/hadoop/hbase/master/MasterCoprocessorHost;
      16: astore_3
      17: aload_3
      18: ldc           #9                  // class org/apache/hadoop/hbase/coprocessor/TestMasterObserver$CPMasterObserver
      20: invokevirtual #22                 // Method org/apache/hadoop/hbase/master/MasterCoprocessorHost.findCoprocessor:(Ljava/lang/Class;)Lorg/apache/hadoop/hbase/Coprocessor;
      23: checkcast     #9                  // class org/apache/hadoop/hbase/coprocessor/TestMasterObserver$CPMasterObserver
      26: astore        4
      28: aload         4
      30: invokevirtual #32                 // Method org/apache/hadoop/hbase/coprocessor/TestMasterObserver$CPMasterObserver.resetStates:()V
      33: aconst_null
      34: checkcast     #199                // class java/util/List
      37: invokestatic  #200                // Method org/apache/hadoop/hbase/shaded/protobuf/RequestConverter.buildGetTableDescriptorsRequest:(Ljava/util/List;)Lorg/apache/hadoop/hbase/shaded/protobuf/generated/MasterProtos$GetTableDescriptorsRequest;
      40: astore        5
      42: aload_2
      43: invokevirtual #175                // Method org/apache/hadoop/hbase/master/HMaster.getMasterRpcServices:()Lorg/apache/hadoop/hbase/master/MasterRpcServices;
      46: aconst_null
      47: aload         5
      49: invokevirtual #201                // Method org/apache/hadoop/hbase/master/MasterRpcServices.getTableDescriptors:(Lorg/apache/hbase/thirdparty/com/google/protobuf/RpcController;Lorg/apache/hadoop/hbase/shaded/protobuf/generated/MasterProtos$GetTableDescriptorsRequest;)Lorg/apache/hadoop/hbase/shaded/protobuf/generated/MasterProtos$GetTableDescriptorsResponse;
      52: pop
      53: ldc           #202                // String Coprocessor should be called on table descriptors request
      55: aload         4
      57: invokevirtual #203                // Method org/apache/hadoop/hbase/coprocessor/TestMasterObserver$CPMasterObserver.wasGetTableDescriptorsCalled:()Z
      60: invokestatic  #18                 // Method org/junit/Assert.assertTrue:(Ljava/lang/String;Z)V
      63: return

  public void testTableNamesEnumeration() throws java.lang.Exception;
    Code:
       0: getstatic     #5                  // Field UTIL:Lorg/apache/hadoop/hbase/HBaseTestingUtility;
       3: invokevirtual #14                 // Method org/apache/hadoop/hbase/HBaseTestingUtility.getHBaseCluster:()Lorg/apache/hadoop/hbase/MiniHBaseCluster;
       6: astore_1
       7: aload_1
       8: invokevirtual #15                 // Method org/apache/hadoop/hbase/MiniHBaseCluster.getMaster:()Lorg/apache/hadoop/hbase/master/HMaster;
      11: astore_2
      12: aload_2
      13: invokevirtual #19                 // Method org/apache/hadoop/hbase/master/HMaster.getMasterCoprocessorHost:()Lorg/apache/hadoop/hbase/master/MasterCoprocessorHost;
      16: astore_3
      17: aload_3
      18: ldc           #9                  // class org/apache/hadoop/hbase/coprocessor/TestMasterObserver$CPMasterObserver
      20: invokevirtual #22                 // Method org/apache/hadoop/hbase/master/MasterCoprocessorHost.findCoprocessor:(Ljava/lang/Class;)Lorg/apache/hadoop/hbase/Coprocessor;
      23: checkcast     #9                  // class org/apache/hadoop/hbase/coprocessor/TestMasterObserver$CPMasterObserver
      26: astore        4
      28: aload         4
      30: invokevirtual #32                 // Method org/apache/hadoop/hbase/coprocessor/TestMasterObserver$CPMasterObserver.resetStates:()V
      33: aload_2
      34: invokevirtual #175                // Method org/apache/hadoop/hbase/master/HMaster.getMasterRpcServices:()Lorg/apache/hadoop/hbase/master/MasterRpcServices;
      37: aconst_null
      38: invokestatic  #204                // Method org/apache/hadoop/hbase/shaded/protobuf/generated/MasterProtos$GetTableNamesRequest.newBuilder:()Lorg/apache/hadoop/hbase/shaded/protobuf/generated/MasterProtos$GetTableNamesRequest$Builder;
      41: invokevirtual #205                // Method org/apache/hadoop/hbase/shaded/protobuf/generated/MasterProtos$GetTableNamesRequest$Builder.build:()Lorg/apache/hadoop/hbase/shaded/protobuf/generated/MasterProtos$GetTableNamesRequest;
      44: invokevirtual #206                // Method org/apache/hadoop/hbase/master/MasterRpcServices.getTableNames:(Lorg/apache/hbase/thirdparty/com/google/protobuf/RpcController;Lorg/apache/hadoop/hbase/shaded/protobuf/generated/MasterProtos$GetTableNamesRequest;)Lorg/apache/hadoop/hbase/shaded/protobuf/generated/MasterProtos$GetTableNamesResponse;
      47: pop
      48: ldc           #207                // String Coprocessor should be called on table names request
      50: aload         4
      52: invokevirtual #208                // Method org/apache/hadoop/hbase/coprocessor/TestMasterObserver$CPMasterObserver.wasGetTableNamesCalled:()Z
      55: invokestatic  #18                 // Method org/junit/Assert.assertTrue:(Ljava/lang/String;Z)V
      58: return

  public void testAbortProcedureOperation() throws java.lang.Exception;
    Code:
       0: getstatic     #5                  // Field UTIL:Lorg/apache/hadoop/hbase/HBaseTestingUtility;
       3: invokevirtual #14                 // Method org/apache/hadoop/hbase/HBaseTestingUtility.getHBaseCluster:()Lorg/apache/hadoop/hbase/MiniHBaseCluster;
       6: astore_1
       7: aload_1
       8: invokevirtual #15                 // Method org/apache/hadoop/hbase/MiniHBaseCluster.getMaster:()Lorg/apache/hadoop/hbase/master/HMaster;
      11: astore_2
      12: aload_2
      13: invokevirtual #19                 // Method org/apache/hadoop/hbase/master/HMaster.getMasterCoprocessorHost:()Lorg/apache/hadoop/hbase/master/MasterCoprocessorHost;
      16: astore_3
      17: aload_3
      18: ldc           #9                  // class org/apache/hadoop/hbase/coprocessor/TestMasterObserver$CPMasterObserver
      20: invokevirtual #22                 // Method org/apache/hadoop/hbase/master/MasterCoprocessorHost.findCoprocessor:(Ljava/lang/Class;)Lorg/apache/hadoop/hbase/Coprocessor;
      23: checkcast     #9                  // class org/apache/hadoop/hbase/coprocessor/TestMasterObserver$CPMasterObserver
      26: astore        4
      28: aload         4
      30: invokevirtual #32                 // Method org/apache/hadoop/hbase/coprocessor/TestMasterObserver$CPMasterObserver.resetStates:()V
      33: aload_2
      34: lconst_1
      35: iconst_1
      36: invokevirtual #209                // Method org/apache/hadoop/hbase/master/HMaster.abortProcedure:(JZ)Z
      39: pop
      40: ldc           #210                // String Coprocessor should be called on abort procedure request
      42: aload         4
      44: invokevirtual #211                // Method org/apache/hadoop/hbase/coprocessor/TestMasterObserver$CPMasterObserver.wasAbortProcedureCalled:()Z
      47: invokestatic  #18                 // Method org/junit/Assert.assertTrue:(Ljava/lang/String;Z)V
      50: return

  public void testGetProceduresOperation() throws java.lang.Exception;
    Code:
       0: getstatic     #5                  // Field UTIL:Lorg/apache/hadoop/hbase/HBaseTestingUtility;
       3: invokevirtual #14                 // Method org/apache/hadoop/hbase/HBaseTestingUtility.getHBaseCluster:()Lorg/apache/hadoop/hbase/MiniHBaseCluster;
       6: astore_1
       7: aload_1
       8: invokevirtual #15                 // Method org/apache/hadoop/hbase/MiniHBaseCluster.getMaster:()Lorg/apache/hadoop/hbase/master/HMaster;
      11: astore_2
      12: aload_2
      13: invokevirtual #19                 // Method org/apache/hadoop/hbase/master/HMaster.getMasterCoprocessorHost:()Lorg/apache/hadoop/hbase/master/MasterCoprocessorHost;
      16: astore_3
      17: aload_3
      18: ldc           #9                  // class org/apache/hadoop/hbase/coprocessor/TestMasterObserver$CPMasterObserver
      20: invokevirtual #22                 // Method org/apache/hadoop/hbase/master/MasterCoprocessorHost.findCoprocessor:(Ljava/lang/Class;)Lorg/apache/hadoop/hbase/Coprocessor;
      23: checkcast     #9                  // class org/apache/hadoop/hbase/coprocessor/TestMasterObserver$CPMasterObserver
      26: astore        4
      28: aload         4
      30: invokevirtual #32                 // Method org/apache/hadoop/hbase/coprocessor/TestMasterObserver$CPMasterObserver.resetStates:()V
      33: aload_2
      34: invokevirtual #212                // Method org/apache/hadoop/hbase/master/HMaster.getProcedures:()Ljava/util/List;
      37: pop
      38: ldc           #213                // String Coprocessor should be called on get procedures request
      40: aload         4
      42: invokevirtual #214                // Method org/apache/hadoop/hbase/coprocessor/TestMasterObserver$CPMasterObserver.wasGetProceduresCalled:()Z
      45: invokestatic  #18                 // Method org/junit/Assert.assertTrue:(Ljava/lang/String;Z)V
      48: return

  public void testGetLocksOperation() throws java.lang.Exception;
    Code:
       0: getstatic     #5                  // Field UTIL:Lorg/apache/hadoop/hbase/HBaseTestingUtility;
       3: invokevirtual #14                 // Method org/apache/hadoop/hbase/HBaseTestingUtility.getHBaseCluster:()Lorg/apache/hadoop/hbase/MiniHBaseCluster;
       6: astore_1
       7: aload_1
       8: invokevirtual #15                 // Method org/apache/hadoop/hbase/MiniHBaseCluster.getMaster:()Lorg/apache/hadoop/hbase/master/HMaster;
      11: astore_2
      12: aload_2
      13: invokevirtual #19                 // Method org/apache/hadoop/hbase/master/HMaster.getMasterCoprocessorHost:()Lorg/apache/hadoop/hbase/master/MasterCoprocessorHost;
      16: astore_3
      17: aload_3
      18: ldc           #9                  // class org/apache/hadoop/hbase/coprocessor/TestMasterObserver$CPMasterObserver
      20: invokevirtual #22                 // Method org/apache/hadoop/hbase/master/MasterCoprocessorHost.findCoprocessor:(Ljava/lang/Class;)Lorg/apache/hadoop/hbase/Coprocessor;
      23: checkcast     #9                  // class org/apache/hadoop/hbase/coprocessor/TestMasterObserver$CPMasterObserver
      26: astore        4
      28: aload         4
      30: invokevirtual #32                 // Method org/apache/hadoop/hbase/coprocessor/TestMasterObserver$CPMasterObserver.resetStates:()V
      33: aload_2
      34: invokevirtual #215                // Method org/apache/hadoop/hbase/master/HMaster.getLocks:()Ljava/util/List;
      37: pop
      38: ldc           #216                // String Coprocessor should be called on get locks request
      40: aload         4
      42: invokevirtual #217                // Method org/apache/hadoop/hbase/coprocessor/TestMasterObserver$CPMasterObserver.wasGetLocksCalled:()Z
      45: invokestatic  #18                 // Method org/junit/Assert.assertTrue:(Ljava/lang/String;Z)V
      48: return

  public void testQueueLockAndLockHeartbeatOperations() throws java.lang.Exception;
    Code:
       0: getstatic     #5                  // Field UTIL:Lorg/apache/hadoop/hbase/HBaseTestingUtility;
       3: invokevirtual #220                // Method org/apache/hadoop/hbase/HBaseTestingUtility.getMiniHBaseCluster:()Lorg/apache/hadoop/hbase/MiniHBaseCluster;
       6: invokevirtual #15                 // Method org/apache/hadoop/hbase/MiniHBaseCluster.getMaster:()Lorg/apache/hadoop/hbase/master/HMaster;
       9: astore_1
      10: aload_1
      11: invokevirtual #19                 // Method org/apache/hadoop/hbase/master/HMaster.getMasterCoprocessorHost:()Lorg/apache/hadoop/hbase/master/MasterCoprocessorHost;
      14: ldc           #9                  // class org/apache/hadoop/hbase/coprocessor/TestMasterObserver$CPMasterObserver
      16: invokevirtual #22                 // Method org/apache/hadoop/hbase/master/MasterCoprocessorHost.findCoprocessor:(Ljava/lang/Class;)Lorg/apache/hadoop/hbase/Coprocessor;
      19: checkcast     #9                  // class org/apache/hadoop/hbase/coprocessor/TestMasterObserver$CPMasterObserver
      22: astore_2
      23: aload_2
      24: invokevirtual #32                 // Method org/apache/hadoop/hbase/coprocessor/TestMasterObserver$CPMasterObserver.resetStates:()V
      27: ldc           #221                // String testLockedTable
      29: invokestatic  #31                 // Method org/apache/hadoop/hbase/TableName.valueOf:(Ljava/lang/String;)Lorg/apache/hadoop/hbase/TableName;
      32: astore_3
      33: aload_1
      34: invokevirtual #222                // Method org/apache/hadoop/hbase/master/HMaster.getLockManager:()Lorg/apache/hadoop/hbase/master/locking/LockManager;
      37: invokevirtual #223                // Method org/apache/hadoop/hbase/master/locking/LockManager.remoteLocks:()Lorg/apache/hadoop/hbase/master/locking/LockManager$RemoteLocks;
      40: aload_3
      41: getstatic     #224                // Field org/apache/hadoop/hbase/procedure2/LockType.EXCLUSIVE:Lorg/apache/hadoop/hbase/procedure2/LockType;
      44: ldc           #225                // String desc
      46: aconst_null
      47: invokevirtual #226                // Method org/apache/hadoop/hbase/master/locking/LockManager$RemoteLocks.requestTableLock:(Lorg/apache/hadoop/hbase/TableName;Lorg/apache/hadoop/hbase/procedure2/LockType;Ljava/lang/String;Lorg/apache/hadoop/hbase/util/NonceKey;)J
      50: lstore        4
      52: aload_1
      53: invokevirtual #222                // Method org/apache/hadoop/hbase/master/HMaster.getLockManager:()Lorg/apache/hadoop/hbase/master/locking/LockManager;
      56: invokevirtual #223                // Method org/apache/hadoop/hbase/master/locking/LockManager.remoteLocks:()Lorg/apache/hadoop/hbase/master/locking/LockManager$RemoteLocks;
      59: lload         4
      61: iconst_0
      62: invokevirtual #227                // Method org/apache/hadoop/hbase/master/locking/LockManager$RemoteLocks.lockHeartbeat:(JZ)Z
      65: pop
      66: aload_2
      67: invokevirtual #228                // Method org/apache/hadoop/hbase/coprocessor/TestMasterObserver$CPMasterObserver.preAndPostForQueueLockAndHeartbeatLockCalled:()Z
      70: invokestatic  #69                 // Method org/junit/Assert.assertTrue:(Z)V
      73: aload_1
      74: invokevirtual #229                // Method org/apache/hadoop/hbase/master/HMaster.getMasterProcedureExecutor:()Lorg/apache/hadoop/hbase/procedure2/ProcedureExecutor;
      77: invokestatic  #230                // Method org/apache/hadoop/hbase/procedure2/ProcedureTestingUtility.waitNoProcedureRunning:(Lorg/apache/hadoop/hbase/procedure2/ProcedureExecutor;)V
      80: aload_1
      81: invokevirtual #229                // Method org/apache/hadoop/hbase/master/HMaster.getMasterProcedureExecutor:()Lorg/apache/hadoop/hbase/procedure2/ProcedureExecutor;
      84: lload         4
      86: invokestatic  #231                // Method org/apache/hadoop/hbase/procedure2/ProcedureTestingUtility.assertProcNotFailed:(Lorg/apache/hadoop/hbase/procedure2/ProcedureExecutor;J)V
      89: return

  static {};
    Code:
       0: ldc           #232                // class org/apache/hadoop/hbase/coprocessor/TestMasterObserver
       2: invokestatic  #233                // Method org/apache/hadoop/hbase/HBaseClassTestRule.forClass:(Ljava/lang/Class;)Lorg/apache/hadoop/hbase/HBaseClassTestRule;
       5: putstatic     #234                // Field CLASS_RULE:Lorg/apache/hadoop/hbase/HBaseClassTestRule;
       8: ldc           #232                // class org/apache/hadoop/hbase/coprocessor/TestMasterObserver
      10: invokestatic  #235                // Method org/slf4j/LoggerFactory.getLogger:(Ljava/lang/Class;)Lorg/slf4j/Logger;
      13: putstatic     #153                // Field LOG:Lorg/slf4j/Logger;
      16: new           #44                 // class java/util/concurrent/CountDownLatch
      19: dup
      20: iconst_1
      21: invokespecial #45                 // Method java/util/concurrent/CountDownLatch."<init>":(I)V
      24: putstatic     #46                 // Field tableCreationLatch:Ljava/util/concurrent/CountDownLatch;
      27: new           #44                 // class java/util/concurrent/CountDownLatch
      30: dup
      31: iconst_1
      32: invokespecial #45                 // Method java/util/concurrent/CountDownLatch."<init>":(I)V
      35: putstatic     #218                // Field tableDeletionLatch:Ljava/util/concurrent/CountDownLatch;
      38: new           #236                // class org/apache/hadoop/hbase/HBaseTestingUtility
      41: dup
      42: invokespecial #237                // Method org/apache/hadoop/hbase/HBaseTestingUtility."<init>":()V
      45: putstatic     #5                  // Field UTIL:Lorg/apache/hadoop/hbase/HBaseTestingUtility;
      48: ldc           #238                // String observed_snapshot
      50: putstatic     #105                // Field TEST_SNAPSHOT:Ljava/lang/String;
      53: ldc           #239                // String observed_clone
      55: invokestatic  #31                 // Method org/apache/hadoop/hbase/TableName.valueOf:(Ljava/lang/String;)Lorg/apache/hadoop/hbase/TableName;
      58: putstatic     #111                // Field TEST_CLONE:Lorg/apache/hadoop/hbase/TableName;
      61: ldc           #240                // String fam1
      63: invokestatic  #187                // Method org/apache/hadoop/hbase/util/Bytes.toBytes:(Ljava/lang/String;)[B
      66: putstatic     #39                 // Field TEST_FAMILY:[B
      69: return
}
