Compiled from "TestStochasticLoadBalancerRegionReplicaWithRacks.java"
public class org.apache.hadoop.hbase.master.balancer.TestStochasticLoadBalancerRegionReplicaWithRacks extends org.apache.hadoop.hbase.master.balancer.BalancerTestBase {
  public static final org.apache.hadoop.hbase.HBaseClassTestRule CLASS_RULE;

  public org.apache.hadoop.hbase.master.balancer.TestStochasticLoadBalancerRegionReplicaWithRacks();
    Code:
       0: aload_0
       1: invokespecial #1                  // Method org/apache/hadoop/hbase/master/balancer/BalancerTestBase."<init>":()V
       4: return

  public void testRegionReplicationOnMidClusterWithRacks();
    Code:
       0: getstatic     #2                  // Field conf:Lorg/apache/hadoop/conf/Configuration;
       3: ldc           #4                  // String hbase.master.balancer.stochastic.maxSteps
       5: ldc2_w        #5                  // long 10000000l
       8: invokevirtual #7                  // Method org/apache/hadoop/conf/Configuration.setLong:(Ljava/lang/String;J)V
      11: getstatic     #2                  // Field conf:Lorg/apache/hadoop/conf/Configuration;
      14: ldc           #8                  // String hbase.master.balancer.stochastic.maxMovePercent
      16: fconst_1
      17: invokevirtual #9                  // Method org/apache/hadoop/conf/Configuration.setFloat:(Ljava/lang/String;F)V
      20: getstatic     #2                  // Field conf:Lorg/apache/hadoop/conf/Configuration;
      23: ldc           #10                 // String hbase.master.balancer.stochastic.maxRunningTime
      25: ldc2_w        #11                 // long 120000l
      28: invokevirtual #7                  // Method org/apache/hadoop/conf/Configuration.setLong:(Ljava/lang/String;J)V
      31: getstatic     #13                 // Field loadBalancer:Lorg/apache/hadoop/hbase/master/balancer/StochasticLoadBalancer;
      34: getstatic     #2                  // Field conf:Lorg/apache/hadoop/conf/Configuration;
      37: invokevirtual #14                 // Method org/apache/hadoop/hbase/master/balancer/StochasticLoadBalancer.setConf:(Lorg/apache/hadoop/conf/Configuration;)V
      40: bipush        30
      42: istore_1
      43: iload_1
      44: bipush        30
      46: imul
      47: istore_2
      48: iconst_3
      49: istore_3
      50: bipush        28
      52: istore        4
      54: bipush        10
      56: istore        5
      58: iconst_4
      59: istore        6
      61: aload_0
      62: iload_1
      63: iload_2
      64: iload         4
      66: iload_3
      67: iload         5
      69: invokevirtual #15                 // Method createServerMap:(IIIII)Ljava/util/Map;
      72: astore        7
      74: new           #16                 // class org/apache/hadoop/hbase/master/balancer/TestStochasticLoadBalancerRegionReplicaWithRacks$ForTestRackManager
      77: dup
      78: iload         6
      80: invokespecial #17                 // Method org/apache/hadoop/hbase/master/balancer/TestStochasticLoadBalancerRegionReplicaWithRacks$ForTestRackManager."<init>":(I)V
      83: astore        8
      85: aload_0
      86: aload         7
      88: aload         8
      90: iconst_0
      91: iconst_1
      92: invokevirtual #18                 // Method testWithCluster:(Ljava/util/Map;Lorg/apache/hadoop/hbase/master/RackManager;ZZ)V
      95: return

  static {};
    Code:
       0: ldc           #19                 // class org/apache/hadoop/hbase/master/balancer/TestStochasticLoadBalancerRegionReplicaWithRacks
       2: invokestatic  #20                 // Method org/apache/hadoop/hbase/HBaseClassTestRule.forClass:(Ljava/lang/Class;)Lorg/apache/hadoop/hbase/HBaseClassTestRule;
       5: putstatic     #21                 // Field CLASS_RULE:Lorg/apache/hadoop/hbase/HBaseClassTestRule;
       8: return
}
