Compiled from "TestHFileDataBlockEncoder.java"
public class org.apache.hadoop.hbase.io.hfile.TestHFileDataBlockEncoder {
  public static final org.apache.hadoop.hbase.HBaseClassTestRule CLASS_RULE;

  public org.apache.hadoop.hbase.io.hfile.TestHFileDataBlockEncoder(org.apache.hadoop.hbase.io.hfile.HFileDataBlockEncoder, boolean);
    Code:
       0: aload_0
       1: invokespecial #1                  // Method java/lang/Object."<init>":()V
       4: aload_0
       5: new           #2                  // class org/apache/hadoop/hbase/util/RedundantKVGenerator
       8: dup
       9: invokespecial #3                  // Method org/apache/hadoop/hbase/util/RedundantKVGenerator."<init>":()V
      12: putfield      #4                  // Field generator:Lorg/apache/hadoop/hbase/util/RedundantKVGenerator;
      15: aload_0
      16: aload_1
      17: putfield      #5                  // Field blockEncoder:Lorg/apache/hadoop/hbase/io/hfile/HFileDataBlockEncoder;
      20: aload_0
      21: iload_2
      22: putfield      #6                  // Field includesMemstoreTS:Z
      25: getstatic     #7                  // Field java/lang/System.err:Ljava/io/PrintStream;
      28: new           #8                  // class java/lang/StringBuilder
      31: dup
      32: invokespecial #9                  // Method java/lang/StringBuilder."<init>":()V
      35: ldc           #10                 // String Encoding:
      37: invokevirtual #11                 // Method java/lang/StringBuilder.append:(Ljava/lang/String;)Ljava/lang/StringBuilder;
      40: aload_1
      41: invokeinterface #12,  1           // InterfaceMethod org/apache/hadoop/hbase/io/hfile/HFileDataBlockEncoder.getDataBlockEncoding:()Lorg/apache/hadoop/hbase/io/encoding/DataBlockEncoding;
      46: invokevirtual #13                 // Method java/lang/StringBuilder.append:(Ljava/lang/Object;)Ljava/lang/StringBuilder;
      49: ldc           #14                 // String , includesMemstoreTS:
      51: invokevirtual #11                 // Method java/lang/StringBuilder.append:(Ljava/lang/String;)Ljava/lang/StringBuilder;
      54: iload_2
      55: invokevirtual #15                 // Method java/lang/StringBuilder.append:(Z)Ljava/lang/StringBuilder;
      58: invokevirtual #16                 // Method java/lang/StringBuilder.toString:()Ljava/lang/String;
      61: invokevirtual #17                 // Method java/io/PrintStream.println:(Ljava/lang/String;)V
      64: return

  public void testEncodingWithCache() throws java.io.IOException;
    Code:
       0: aload_0
       1: iconst_0
       2: invokespecial #18                 // Method testEncodingWithCacheInternals:(Z)V
       5: aload_0
       6: iconst_1
       7: invokespecial #18                 // Method testEncodingWithCacheInternals:(Z)V
      10: return

  public void testHeaderSizeInCacheWithoutChecksum() throws java.lang.Exception;
    Code:
       0: aload_0
       1: iconst_0
       2: invokespecial #42                 // Method testHeaderSizeInCacheWithoutChecksumInternals:(Z)V
       5: aload_0
       6: iconst_1
       7: invokespecial #42                 // Method testHeaderSizeInCacheWithoutChecksumInternals:(Z)V
      10: return

  public void testEncoding() throws java.io.IOException;
    Code:
       0: aload_0
       1: iconst_0
       2: invokespecial #65                 // Method testEncodingInternals:(Z)V
       5: aload_0
       6: iconst_1
       7: invokespecial #65                 // Method testEncodingInternals:(Z)V
      10: return

  public void testEncodingWithOffheapKeyValue() throws java.io.IOException;
    Code:
       0: aload_0
       1: getfield      #4                  // Field generator:Lorg/apache/hadoop/hbase/util/RedundantKVGenerator;
       4: bipush        60
       6: iconst_1
       7: invokevirtual #66                 // Method org/apache/hadoop/hbase/util/RedundantKVGenerator.generateTestExtendedOffheapKeyValues:(IZ)Ljava/util/List;
      10: astore_1
      11: new           #50                 // class org/apache/hadoop/hbase/io/hfile/HFileContextBuilder
      14: dup
      15: invokespecial #51                 // Method org/apache/hadoop/hbase/io/hfile/HFileContextBuilder."<init>":()V
      18: aload_0
      19: getfield      #6                  // Field includesMemstoreTS:Z
      22: invokevirtual #53                 // Method org/apache/hadoop/hbase/io/hfile/HFileContextBuilder.withIncludesMvcc:(Z)Lorg/apache/hadoop/hbase/io/hfile/HFileContextBuilder;
      25: iconst_1
      26: invokevirtual #54                 // Method org/apache/hadoop/hbase/io/hfile/HFileContextBuilder.withIncludesTags:(Z)Lorg/apache/hadoop/hbase/io/hfile/HFileContextBuilder;
      29: iconst_1
      30: invokevirtual #52                 // Method org/apache/hadoop/hbase/io/hfile/HFileContextBuilder.withHBaseCheckSum:(Z)Lorg/apache/hadoop/hbase/io/hfile/HFileContextBuilder;
      33: getstatic     #67                 // Field org/apache/hadoop/hbase/io/compress/Compression$Algorithm.NONE:Lorg/apache/hadoop/hbase/io/compress/Compression$Algorithm;
      36: invokevirtual #68                 // Method org/apache/hadoop/hbase/io/hfile/HFileContextBuilder.withCompression:(Lorg/apache/hadoop/hbase/io/compress/Compression$Algorithm;)Lorg/apache/hadoop/hbase/io/hfile/HFileContextBuilder;
      39: iconst_0
      40: invokevirtual #55                 // Method org/apache/hadoop/hbase/io/hfile/HFileContextBuilder.withBlockSize:(I)Lorg/apache/hadoop/hbase/io/hfile/HFileContextBuilder;
      43: getstatic     #56                 // Field org/apache/hadoop/hbase/util/ChecksumType.NULL:Lorg/apache/hadoop/hbase/util/ChecksumType;
      46: invokevirtual #57                 // Method org/apache/hadoop/hbase/io/hfile/HFileContextBuilder.withChecksumType:(Lorg/apache/hadoop/hbase/util/ChecksumType;)Lorg/apache/hadoop/hbase/io/hfile/HFileContextBuilder;
      49: invokevirtual #58                 // Method org/apache/hadoop/hbase/io/hfile/HFileContextBuilder.build:()Lorg/apache/hadoop/hbase/io/hfile/HFileContext;
      52: astore_2
      53: aload_0
      54: aload_1
      55: aload_2
      56: iconst_1
      57: invokespecial #69                 // Method writeBlock:(Ljava/util/List;Lorg/apache/hadoop/hbase/io/hfile/HFileContext;Z)V
      60: goto          69
      63: astore_1
      64: ldc           #71                 // String No exception should have been thrown
      66: invokestatic  #72                 // Method org/junit/Assert.fail:(Ljava/lang/String;)V
      69: return
    Exception table:
       from    to  target type
           0    60    63   Class java/lang/IllegalArgumentException

  public static java.util.Collection<java.lang.Object[]> getAllConfigurations();
    Code:
       0: new           #97                 // class java/util/ArrayList
       3: dup
       4: invokespecial #98                 // Method java/util/ArrayList."<init>":()V
       7: astore_0
       8: invokestatic  #99                 // Method org/apache/hadoop/hbase/io/encoding/DataBlockEncoding.values:()[Lorg/apache/hadoop/hbase/io/encoding/DataBlockEncoding;
      11: astore_1
      12: aload_1
      13: arraylength
      14: istore_2
      15: iconst_0
      16: istore_3
      17: iload_3
      18: iload_2
      19: if_icmpge     127
      22: aload_1
      23: iload_3
      24: aaload
      25: astore        4
      27: iconst_2
      28: newarray       boolean
      30: dup
      31: iconst_0
      32: iconst_0
      33: bastore
      34: dup
      35: iconst_1
      36: iconst_1
      37: bastore
      38: astore        5
      40: aload         5
      42: arraylength
      43: istore        6
      45: iconst_0
      46: istore        7
      48: iload         7
      50: iload         6
      52: if_icmpge     121
      55: aload         5
      57: iload         7
      59: baload
      60: istore        8
      62: aload         4
      64: getstatic     #35                 // Field org/apache/hadoop/hbase/io/encoding/DataBlockEncoding.NONE:Lorg/apache/hadoop/hbase/io/encoding/DataBlockEncoding;
      67: if_acmpne     76
      70: getstatic     #100                // Field org/apache/hadoop/hbase/io/hfile/NoOpDataBlockEncoder.INSTANCE:Lorg/apache/hadoop/hbase/io/hfile/NoOpDataBlockEncoder;
      73: goto          85
      76: new           #101                // class org/apache/hadoop/hbase/io/hfile/HFileDataBlockEncoderImpl
      79: dup
      80: aload         4
      82: invokespecial #102                // Method org/apache/hadoop/hbase/io/hfile/HFileDataBlockEncoderImpl."<init>":(Lorg/apache/hadoop/hbase/io/encoding/DataBlockEncoding;)V
      85: astore        9
      87: aload_0
      88: iconst_2
      89: anewarray     #103                // class java/lang/Object
      92: dup
      93: iconst_0
      94: aload         9
      96: aastore
      97: dup
      98: iconst_1
      99: new           #104                // class java/lang/Boolean
     102: dup
     103: iload         8
     105: invokespecial #105                // Method java/lang/Boolean."<init>":(Z)V
     108: aastore
     109: invokeinterface #106,  2          // InterfaceMethod java/util/List.add:(Ljava/lang/Object;)Z
     114: pop
     115: iinc          7, 1
     118: goto          48
     121: iinc          3, 1
     124: goto          17
     127: aload_0
     128: areturn

  static {};
    Code:
       0: ldc           #107                // class org/apache/hadoop/hbase/io/hfile/TestHFileDataBlockEncoder
       2: invokestatic  #108                // Method org/apache/hadoop/hbase/HBaseClassTestRule.forClass:(Ljava/lang/Class;)Lorg/apache/hadoop/hbase/HBaseClassTestRule;
       5: putstatic     #109                // Field CLASS_RULE:Lorg/apache/hadoop/hbase/HBaseClassTestRule;
       8: return
}
