Compiled from "TestRegionServerCoprocessorExceptionWithAbort.java"
public class org.apache.hadoop.hbase.coprocessor.TestRegionServerCoprocessorExceptionWithAbort {
  public static final org.apache.hadoop.hbase.HBaseClassTestRule CLASS_RULE;

  public org.apache.hadoop.hbase.coprocessor.TestRegionServerCoprocessorExceptionWithAbort();
    Code:
       0: aload_0
       1: invokespecial #1                  // Method java/lang/Object."<init>":()V
       4: return

  public void testExceptionDuringInitialization() throws java.lang.Exception;
    Code:
       0: getstatic     #2                  // Field TEST_UTIL:Lorg/apache/hadoop/hbase/HBaseTestingUtility;
       3: invokevirtual #3                  // Method org/apache/hadoop/hbase/HBaseTestingUtility.getConfiguration:()Lorg/apache/hadoop/conf/Configuration;
       6: astore_1
       7: aload_1
       8: ldc           #5                  // String hbase.client.retries.number
      10: iconst_2
      11: invokevirtual #6                  // Method org/apache/hadoop/conf/Configuration.setInt:(Ljava/lang/String;I)V
      14: aload_1
      15: ldc           #8                  // String hbase.coprocessor.abortonerror
      17: iconst_1
      18: invokevirtual #9                  // Method org/apache/hadoop/conf/Configuration.setBoolean:(Ljava/lang/String;Z)V
      21: aload_1
      22: ldc           #10                 // String hbase.coprocessor.region.classes
      24: ldc           #11                 // String
      26: invokevirtual #12                 // Method org/apache/hadoop/conf/Configuration.set:(Ljava/lang/String;Ljava/lang/String;)V
      29: getstatic     #2                  // Field TEST_UTIL:Lorg/apache/hadoop/hbase/HBaseTestingUtility;
      32: iconst_2
      33: invokevirtual #13                 // Method org/apache/hadoop/hbase/HBaseTestingUtility.startMiniCluster:(I)Lorg/apache/hadoop/hbase/MiniHBaseCluster;
      36: pop
      37: getstatic     #2                  // Field TEST_UTIL:Lorg/apache/hadoop/hbase/HBaseTestingUtility;
      40: invokevirtual #14                 // Method org/apache/hadoop/hbase/HBaseTestingUtility.getHBaseCluster:()Lorg/apache/hadoop/hbase/MiniHBaseCluster;
      43: astore_2
      44: aload_2
      45: iconst_0
      46: invokevirtual #15                 // Method org/apache/hadoop/hbase/MiniHBaseCluster.getRegionServer:(I)Lorg/apache/hadoop/hbase/regionserver/HRegionServer;
      49: astore_3
      50: aload_1
      51: ldc           #10                 // String hbase.coprocessor.region.classes
      53: ldc           #16                 // class org/apache/hadoop/hbase/coprocessor/TestRegionServerCoprocessorExceptionWithAbort$FailedInitializationObserver
      55: invokevirtual #17                 // Method java/lang/Class.getName:()Ljava/lang/String;
      58: invokevirtual #12                 // Method org/apache/hadoop/conf/Configuration.set:(Ljava/lang/String;Ljava/lang/String;)V
      61: aload_3
      62: invokevirtual #18                 // Method org/apache/hadoop/hbase/regionserver/HRegionServer.getRegionServerCoprocessorHost:()Lorg/apache/hadoop/hbase/regionserver/RegionServerCoprocessorHost;
      65: aload_1
      66: ldc           #10                 // String hbase.coprocessor.region.classes
      68: invokevirtual #19                 // Method org/apache/hadoop/hbase/regionserver/RegionServerCoprocessorHost.loadSystemCoprocessors:(Lorg/apache/hadoop/conf/Configuration;Ljava/lang/String;)V
      71: getstatic     #2                  // Field TEST_UTIL:Lorg/apache/hadoop/hbase/HBaseTestingUtility;
      74: ldc2_w        #20                 // long 10000l
      77: ldc2_w        #22                 // long 1000l
      80: new           #24                 // class org/apache/hadoop/hbase/coprocessor/TestRegionServerCoprocessorExceptionWithAbort$1
      83: dup
      84: aload_0
      85: aload_3
      86: invokespecial #25                 // Method org/apache/hadoop/hbase/coprocessor/TestRegionServerCoprocessorExceptionWithAbort$1."<init>":(Lorg/apache/hadoop/hbase/coprocessor/TestRegionServerCoprocessorExceptionWithAbort;Lorg/apache/hadoop/hbase/regionserver/HRegionServer;)V
      89: invokevirtual #26                 // Method org/apache/hadoop/hbase/HBaseTestingUtility.waitFor:(JJLorg/apache/hadoop/hbase/Waiter$Predicate;)J
      92: pop2
      93: getstatic     #2                  // Field TEST_UTIL:Lorg/apache/hadoop/hbase/HBaseTestingUtility;
      96: invokevirtual #27                 // Method org/apache/hadoop/hbase/HBaseTestingUtility.shutdownMiniCluster:()V
      99: goto          113
     102: astore        4
     104: getstatic     #2                  // Field TEST_UTIL:Lorg/apache/hadoop/hbase/HBaseTestingUtility;
     107: invokevirtual #27                 // Method org/apache/hadoop/hbase/HBaseTestingUtility.shutdownMiniCluster:()V
     110: aload         4
     112: athrow
     113: return
    Exception table:
       from    to  target type
          37    93   102   any
         102   104   102   any

  public void testExceptionFromCoprocessorDuringPut() throws java.lang.Exception;
    Code:
       0: getstatic     #2                  // Field TEST_UTIL:Lorg/apache/hadoop/hbase/HBaseTestingUtility;
       3: invokevirtual #3                  // Method org/apache/hadoop/hbase/HBaseTestingUtility.getConfiguration:()Lorg/apache/hadoop/conf/Configuration;
       6: astore_1
       7: aload_1
       8: ldc           #5                  // String hbase.client.retries.number
      10: iconst_2
      11: invokevirtual #6                  // Method org/apache/hadoop/conf/Configuration.setInt:(Ljava/lang/String;I)V
      14: aload_1
      15: ldc           #10                 // String hbase.coprocessor.region.classes
      17: ldc           #28                 // class org/apache/hadoop/hbase/coprocessor/TestRegionServerCoprocessorExceptionWithAbort$BuggyRegionObserver
      19: invokevirtual #17                 // Method java/lang/Class.getName:()Ljava/lang/String;
      22: invokevirtual #12                 // Method org/apache/hadoop/conf/Configuration.set:(Ljava/lang/String;Ljava/lang/String;)V
      25: aload_1
      26: ldc           #8                  // String hbase.coprocessor.abortonerror
      28: iconst_1
      29: invokevirtual #9                  // Method org/apache/hadoop/conf/Configuration.setBoolean:(Ljava/lang/String;Z)V
      32: getstatic     #2                  // Field TEST_UTIL:Lorg/apache/hadoop/hbase/HBaseTestingUtility;
      35: iconst_2
      36: invokevirtual #13                 // Method org/apache/hadoop/hbase/HBaseTestingUtility.startMiniCluster:(I)Lorg/apache/hadoop/hbase/MiniHBaseCluster;
      39: pop
      40: ldc           #29                 // String aaa
      42: invokestatic  #30                 // Method org/apache/hadoop/hbase/util/Bytes.toBytes:(Ljava/lang/String;)[B
      45: astore_2
      46: getstatic     #2                  // Field TEST_UTIL:Lorg/apache/hadoop/hbase/HBaseTestingUtility;
      49: getstatic     #31                 // Field TABLE_NAME:Lorg/apache/hadoop/hbase/TableName;
      52: aload_2
      53: invokevirtual #32                 // Method org/apache/hadoop/hbase/HBaseTestingUtility.createMultiRegionTable:(Lorg/apache/hadoop/hbase/TableName;[B)Lorg/apache/hadoop/hbase/client/Table;
      56: astore_3
      57: getstatic     #2                  // Field TEST_UTIL:Lorg/apache/hadoop/hbase/HBaseTestingUtility;
      60: getstatic     #31                 // Field TABLE_NAME:Lorg/apache/hadoop/hbase/TableName;
      63: invokevirtual #33                 // Method org/apache/hadoop/hbase/HBaseTestingUtility.waitUntilAllRegionsAssigned:(Lorg/apache/hadoop/hbase/TableName;)V
      66: getstatic     #2                  // Field TEST_UTIL:Lorg/apache/hadoop/hbase/HBaseTestingUtility;
      69: getstatic     #31                 // Field TABLE_NAME:Lorg/apache/hadoop/hbase/TableName;
      72: invokevirtual #34                 // Method org/apache/hadoop/hbase/HBaseTestingUtility.getRSForFirstRegionInTable:(Lorg/apache/hadoop/hbase/TableName;)Lorg/apache/hadoop/hbase/regionserver/HRegionServer;
      75: astore        4
      77: ldc           #29                 // String aaa
      79: invokestatic  #30                 // Method org/apache/hadoop/hbase/util/Bytes.toBytes:(Ljava/lang/String;)[B
      82: astore        5
      84: new           #35                 // class org/apache/hadoop/hbase/client/Put
      87: dup
      88: aload         5
      90: invokespecial #36                 // Method org/apache/hadoop/hbase/client/Put."<init>":([B)V
      93: astore        6
      95: aload         6
      97: aload_2
      98: aload         5
     100: aload         5
     102: invokevirtual #37                 // Method org/apache/hadoop/hbase/client/Put.addColumn:([B[B[B)Lorg/apache/hadoop/hbase/client/Put;
     105: pop
     106: aload_3
     107: aload         6
     109: invokeinterface #38,  2           // InterfaceMethod org/apache/hadoop/hbase/client/Table.put:(Lorg/apache/hadoop/hbase/client/Put;)V
     114: goto          119
     117: astore        5
     119: iconst_0
     120: istore        5
     122: iconst_0
     123: istore        6
     125: iload         6
     127: bipush        10
     129: if_icmpge     169
     132: aload         4
     134: invokevirtual #40                 // Method org/apache/hadoop/hbase/regionserver/HRegionServer.isAborted:()Z
     137: istore        5
     139: iload         5
     141: ifeq          147
     144: goto          169
     147: ldc2_w        #22                 // long 1000l
     150: invokestatic  #41                 // Method java/lang/Thread.sleep:(J)V
     153: goto          163
     156: astore        7
     158: ldc           #43                 // String InterruptedException while waiting for regionserver zk node to be deleted.
     160: invokestatic  #44                 // Method org/junit/Assert.fail:(Ljava/lang/String;)V
     163: iinc          6, 1
     166: goto          125
     169: ldc           #45                 // String The region server should have aborted
     171: iload         5
     173: invokestatic  #46                 // Method org/junit/Assert.assertTrue:(Ljava/lang/String;Z)V
     176: aload_3
     177: invokeinterface #47,  1           // InterfaceMethod org/apache/hadoop/hbase/client/Table.close:()V
     182: getstatic     #2                  // Field TEST_UTIL:Lorg/apache/hadoop/hbase/HBaseTestingUtility;
     185: invokevirtual #27                 // Method org/apache/hadoop/hbase/HBaseTestingUtility.shutdownMiniCluster:()V
     188: goto          202
     191: astore        8
     193: getstatic     #2                  // Field TEST_UTIL:Lorg/apache/hadoop/hbase/HBaseTestingUtility;
     196: invokevirtual #27                 // Method org/apache/hadoop/hbase/HBaseTestingUtility.shutdownMiniCluster:()V
     199: aload         8
     201: athrow
     202: return
    Exception table:
       from    to  target type
          77   114   117   Class java/io/IOException
         147   153   156   Class java/lang/InterruptedException
          40   182   191   any
         191   193   191   any

  static {};
    Code:
       0: ldc           #48                 // class org/apache/hadoop/hbase/coprocessor/TestRegionServerCoprocessorExceptionWithAbort
       2: invokestatic  #49                 // Method org/apache/hadoop/hbase/HBaseClassTestRule.forClass:(Ljava/lang/Class;)Lorg/apache/hadoop/hbase/HBaseClassTestRule;
       5: putstatic     #50                 // Field CLASS_RULE:Lorg/apache/hadoop/hbase/HBaseClassTestRule;
       8: ldc           #48                 // class org/apache/hadoop/hbase/coprocessor/TestRegionServerCoprocessorExceptionWithAbort
      10: invokestatic  #51                 // Method org/slf4j/LoggerFactory.getLogger:(Ljava/lang/Class;)Lorg/slf4j/Logger;
      13: putstatic     #52                 // Field LOG:Lorg/slf4j/Logger;
      16: new           #53                 // class org/apache/hadoop/hbase/HBaseTestingUtility
      19: dup
      20: invokespecial #54                 // Method org/apache/hadoop/hbase/HBaseTestingUtility."<init>":()V
      23: putstatic     #2                  // Field TEST_UTIL:Lorg/apache/hadoop/hbase/HBaseTestingUtility;
      26: ldc           #55                 // String observed_table
      28: invokestatic  #56                 // Method org/apache/hadoop/hbase/TableName.valueOf:(Ljava/lang/String;)Lorg/apache/hadoop/hbase/TableName;
      31: putstatic     #31                 // Field TABLE_NAME:Lorg/apache/hadoop/hbase/TableName;
      34: return
}
