Compiled from "TestProcedureInMemoryChore.java"
public class org.apache.hadoop.hbase.procedure2.TestProcedureInMemoryChore {
  public static final org.apache.hadoop.hbase.HBaseClassTestRule CLASS_RULE;

  public org.apache.hadoop.hbase.procedure2.TestProcedureInMemoryChore();
    Code:
       0: aload_0
       1: invokespecial #2                  // Method java/lang/Object."<init>":()V
       4: return

  public void setUp() throws java.io.IOException;
    Code:
       0: aload_0
       1: new           #3                  // class org/apache/hadoop/hbase/HBaseCommonTestingUtility
       4: dup
       5: invokespecial #4                  // Method org/apache/hadoop/hbase/HBaseCommonTestingUtility."<init>":()V
       8: putfield      #5                  // Field htu:Lorg/apache/hadoop/hbase/HBaseCommonTestingUtility;
      11: aload_0
      12: new           #6                  // class org/apache/hadoop/hbase/procedure2/TestProcedureInMemoryChore$TestProcEnv
      15: dup
      16: aconst_null
      17: invokespecial #7                  // Method org/apache/hadoop/hbase/procedure2/TestProcedureInMemoryChore$TestProcEnv."<init>":(Lorg/apache/hadoop/hbase/procedure2/TestProcedureInMemoryChore$1;)V
      20: putfield      #8                  // Field procEnv:Lorg/apache/hadoop/hbase/procedure2/TestProcedureInMemoryChore$TestProcEnv;
      23: aload_0
      24: new           #9                  // class org/apache/hadoop/hbase/procedure2/store/NoopProcedureStore
      27: dup
      28: invokespecial #10                 // Method org/apache/hadoop/hbase/procedure2/store/NoopProcedureStore."<init>":()V
      31: putfield      #11                 // Field procStore:Lorg/apache/hadoop/hbase/procedure2/store/NoopProcedureStore;
      34: aload_0
      35: new           #12                 // class org/apache/hadoop/hbase/procedure2/ProcedureExecutor
      38: dup
      39: aload_0
      40: getfield      #5                  // Field htu:Lorg/apache/hadoop/hbase/HBaseCommonTestingUtility;
      43: invokevirtual #13                 // Method org/apache/hadoop/hbase/HBaseCommonTestingUtility.getConfiguration:()Lorg/apache/hadoop/conf/Configuration;
      46: aload_0
      47: getfield      #8                  // Field procEnv:Lorg/apache/hadoop/hbase/procedure2/TestProcedureInMemoryChore$TestProcEnv;
      50: aload_0
      51: getfield      #11                 // Field procStore:Lorg/apache/hadoop/hbase/procedure2/store/NoopProcedureStore;
      54: invokespecial #14                 // Method org/apache/hadoop/hbase/procedure2/ProcedureExecutor."<init>":(Lorg/apache/hadoop/conf/Configuration;Ljava/lang/Object;Lorg/apache/hadoop/hbase/procedure2/store/ProcedureStore;)V
      57: putfield      #15                 // Field procExecutor:Lorg/apache/hadoop/hbase/procedure2/ProcedureExecutor;
      60: aload_0
      61: getfield      #15                 // Field procExecutor:Lorg/apache/hadoop/hbase/procedure2/ProcedureExecutor;
      64: new           #16                 // class org/apache/hadoop/hbase/procedure2/ProcedureExecutor$Testing
      67: dup
      68: invokespecial #17                 // Method org/apache/hadoop/hbase/procedure2/ProcedureExecutor$Testing."<init>":()V
      71: putfield      #18                 // Field org/apache/hadoop/hbase/procedure2/ProcedureExecutor.testing:Lorg/apache/hadoop/hbase/procedure2/ProcedureExecutor$Testing;
      74: aload_0
      75: getfield      #11                 // Field procStore:Lorg/apache/hadoop/hbase/procedure2/store/NoopProcedureStore;
      78: iconst_1
      79: invokevirtual #20                 // Method org/apache/hadoop/hbase/procedure2/store/NoopProcedureStore.start:(I)V
      82: aload_0
      83: getfield      #15                 // Field procExecutor:Lorg/apache/hadoop/hbase/procedure2/ProcedureExecutor;
      86: iconst_1
      87: iconst_1
      88: invokestatic  #21                 // Method org/apache/hadoop/hbase/procedure2/ProcedureTestingUtility.initAndStartWorkers:(Lorg/apache/hadoop/hbase/procedure2/ProcedureExecutor;IZ)V
      91: return

  public void tearDown() throws java.io.IOException;
    Code:
       0: aload_0
       1: getfield      #15                 // Field procExecutor:Lorg/apache/hadoop/hbase/procedure2/ProcedureExecutor;
       4: invokevirtual #22                 // Method org/apache/hadoop/hbase/procedure2/ProcedureExecutor.stop:()V
       7: aload_0
       8: getfield      #11                 // Field procStore:Lorg/apache/hadoop/hbase/procedure2/store/NoopProcedureStore;
      11: iconst_0
      12: invokevirtual #23                 // Method org/apache/hadoop/hbase/procedure2/store/NoopProcedureStore.stop:(Z)V
      15: return

  public void testChoreAddAndRemove() throws java.lang.Exception;
    Code:
       0: bipush        50
       2: istore_1
       3: iconst_5
       4: istore_2
       5: new           #24                 // class java/util/concurrent/CountDownLatch
       8: dup
       9: iconst_5
      10: invokespecial #25                 // Method java/util/concurrent/CountDownLatch."<init>":(I)V
      13: astore_3
      14: new           #26                 // class org/apache/hadoop/hbase/procedure2/TestProcedureInMemoryChore$TestLatchChore
      17: dup
      18: bipush        50
      20: aload_3
      21: invokespecial #27                 // Method org/apache/hadoop/hbase/procedure2/TestProcedureInMemoryChore$TestLatchChore."<init>":(ILjava/util/concurrent/CountDownLatch;)V
      24: astore        4
      26: aload_0
      27: getfield      #15                 // Field procExecutor:Lorg/apache/hadoop/hbase/procedure2/ProcedureExecutor;
      30: aload         4
      32: invokevirtual #28                 // Method org/apache/hadoop/hbase/procedure2/ProcedureExecutor.addChore:(Lorg/apache/hadoop/hbase/procedure2/ProcedureInMemoryChore;)V
      35: aload         4
      37: invokevirtual #29                 // Method org/apache/hadoop/hbase/procedure2/TestProcedureInMemoryChore$TestLatchChore.isWaiting:()Z
      40: invokestatic  #30                 // Method org/junit/Assert.assertTrue:(Z)V
      43: aload_3
      44: invokevirtual #31                 // Method java/util/concurrent/CountDownLatch.await:()V
      47: aload         4
      49: invokevirtual #29                 // Method org/apache/hadoop/hbase/procedure2/TestProcedureInMemoryChore$TestLatchChore.isWaiting:()Z
      52: invokestatic  #30                 // Method org/junit/Assert.assertTrue:(Z)V
      55: aload_0
      56: getfield      #15                 // Field procExecutor:Lorg/apache/hadoop/hbase/procedure2/ProcedureExecutor;
      59: aload         4
      61: invokevirtual #32                 // Method org/apache/hadoop/hbase/procedure2/ProcedureExecutor.removeChore:(Lorg/apache/hadoop/hbase/procedure2/ProcedureInMemoryChore;)Z
      64: pop
      65: new           #24                 // class java/util/concurrent/CountDownLatch
      68: dup
      69: iconst_5
      70: invokespecial #25                 // Method java/util/concurrent/CountDownLatch."<init>":(I)V
      73: astore_3
      74: aload         4
      76: aload_3
      77: invokevirtual #33                 // Method org/apache/hadoop/hbase/procedure2/TestProcedureInMemoryChore$TestLatchChore.setLatch:(Ljava/util/concurrent/CountDownLatch;)V
      80: aload_3
      81: ldc2_w        #34                 // long 250l
      84: getstatic     #36                 // Field java/util/concurrent/TimeUnit.MILLISECONDS:Ljava/util/concurrent/TimeUnit;
      87: invokevirtual #37                 // Method java/util/concurrent/CountDownLatch.await:(JLjava/util/concurrent/TimeUnit;)Z
      90: pop
      91: getstatic     #1                  // Field LOG:Lorg/slf4j/Logger;
      94: new           #38                 // class java/lang/StringBuilder
      97: dup
      98: invokespecial #39                 // Method java/lang/StringBuilder."<init>":()V
     101: ldc           #40                 // String chore latch count=
     103: invokevirtual #41                 // Method java/lang/StringBuilder.append:(Ljava/lang/String;)Ljava/lang/StringBuilder;
     106: aload_3
     107: invokevirtual #42                 // Method java/util/concurrent/CountDownLatch.getCount:()J
     110: invokevirtual #43                 // Method java/lang/StringBuilder.append:(J)Ljava/lang/StringBuilder;
     113: invokevirtual #44                 // Method java/lang/StringBuilder.toString:()Ljava/lang/String;
     116: invokeinterface #45,  2           // InterfaceMethod org/slf4j/Logger.info:(Ljava/lang/String;)V
     121: aload         4
     123: invokevirtual #29                 // Method org/apache/hadoop/hbase/procedure2/TestProcedureInMemoryChore$TestLatchChore.isWaiting:()Z
     126: invokestatic  #46                 // Method org/junit/Assert.assertFalse:(Z)V
     129: new           #38                 // class java/lang/StringBuilder
     132: dup
     133: invokespecial #39                 // Method java/lang/StringBuilder."<init>":()V
     136: ldc           #47                 // String latchCount=
     138: invokevirtual #41                 // Method java/lang/StringBuilder.append:(Ljava/lang/String;)Ljava/lang/StringBuilder;
     141: aload_3
     142: invokevirtual #42                 // Method java/util/concurrent/CountDownLatch.getCount:()J
     145: invokevirtual #43                 // Method java/lang/StringBuilder.append:(J)Ljava/lang/StringBuilder;
     148: invokevirtual #44                 // Method java/lang/StringBuilder.toString:()Ljava/lang/String;
     151: aload_3
     152: invokevirtual #42                 // Method java/util/concurrent/CountDownLatch.getCount:()J
     155: lconst_0
     156: lcmp
     157: ifle          164
     160: iconst_1
     161: goto          165
     164: iconst_0
     165: invokestatic  #48                 // Method org/junit/Assert.assertTrue:(Ljava/lang/String;Z)V
     168: return

  static org.slf4j.Logger access$100();
    Code:
       0: getstatic     #1                  // Field LOG:Lorg/slf4j/Logger;
       3: areturn

  static {};
    Code:
       0: ldc           #19                 // class org/apache/hadoop/hbase/procedure2/TestProcedureInMemoryChore
       2: invokestatic  #49                 // Method org/apache/hadoop/hbase/HBaseClassTestRule.forClass:(Ljava/lang/Class;)Lorg/apache/hadoop/hbase/HBaseClassTestRule;
       5: putstatic     #50                 // Field CLASS_RULE:Lorg/apache/hadoop/hbase/HBaseClassTestRule;
       8: ldc           #19                 // class org/apache/hadoop/hbase/procedure2/TestProcedureInMemoryChore
      10: invokestatic  #51                 // Method org/slf4j/LoggerFactory.getLogger:(Ljava/lang/Class;)Lorg/slf4j/Logger;
      13: putstatic     #1                  // Field LOG:Lorg/slf4j/Logger;
      16: return
}
