Compiled from "TestVisibilityLablesWithGroups.java"
public class org.apache.hadoop.hbase.security.visibility.TestVisibilityLablesWithGroups {
  public static final org.apache.hadoop.hbase.HBaseClassTestRule CLASS_RULE;

  public static final java.lang.String CONFIDENTIAL;

  public static final org.apache.hadoop.hbase.HBaseTestingUtility TEST_UTIL;

  public static org.apache.hadoop.conf.Configuration conf;

  public final org.junit.rules.TestName TEST_NAME;

  public static org.apache.hadoop.hbase.security.User SUPERUSER;

  public static org.apache.hadoop.hbase.security.User TESTUSER;

  public org.apache.hadoop.hbase.security.visibility.TestVisibilityLablesWithGroups();
    Code:
       0: aload_0
       1: invokespecial #9                  // Method java/lang/Object."<init>":()V
       4: aload_0
       5: new           #10                 // class org/junit/rules/TestName
       8: dup
       9: invokespecial #11                 // Method org/junit/rules/TestName."<init>":()V
      12: putfield      #12                 // Field TEST_NAME:Lorg/junit/rules/TestName;
      15: return

  public static void setupBeforeClass() throws java.lang.Exception;
    Code:
       0: getstatic     #13                 // Field TEST_UTIL:Lorg/apache/hadoop/hbase/HBaseTestingUtility;
       3: invokevirtual #14                 // Method org/apache/hadoop/hbase/HBaseTestingUtility.getConfiguration:()Lorg/apache/hadoop/conf/Configuration;
       6: putstatic     #15                 // Field conf:Lorg/apache/hadoop/conf/Configuration;
       9: getstatic     #15                 // Field conf:Lorg/apache/hadoop/conf/Configuration;
      12: invokestatic  #16                 // Method org/apache/hadoop/hbase/security/visibility/VisibilityTestUtil.enableVisiblityLabels:(Lorg/apache/hadoop/conf/Configuration;)V
      15: getstatic     #15                 // Field conf:Lorg/apache/hadoop/conf/Configuration;
      18: ldc           #17                 // String hbase.superuser
      20: ldc           #18                 // String @supergroup
      22: invokevirtual #19                 // Method org/apache/hadoop/conf/Configuration.set:(Ljava/lang/String;Ljava/lang/String;)V
      25: getstatic     #13                 // Field TEST_UTIL:Lorg/apache/hadoop/hbase/HBaseTestingUtility;
      28: iconst_1
      29: invokevirtual #20                 // Method org/apache/hadoop/hbase/HBaseTestingUtility.startMiniCluster:(I)Lorg/apache/hadoop/hbase/MiniHBaseCluster;
      32: pop
      33: getstatic     #15                 // Field conf:Lorg/apache/hadoop/conf/Configuration;
      36: ldc           #21                 // String admin
      38: iconst_1
      39: anewarray     #22                 // class java/lang/String
      42: dup
      43: iconst_0
      44: ldc           #23                 // String supergroup
      46: aastore
      47: invokestatic  #24                 // Method org/apache/hadoop/hbase/security/User.createUserForTesting:(Lorg/apache/hadoop/conf/Configuration;Ljava/lang/String;[Ljava/lang/String;)Lorg/apache/hadoop/hbase/security/User;
      50: putstatic     #25                 // Field SUPERUSER:Lorg/apache/hadoop/hbase/security/User;
      53: getstatic     #15                 // Field conf:Lorg/apache/hadoop/conf/Configuration;
      56: ldc           #26                 // String test
      58: iconst_1
      59: anewarray     #22                 // class java/lang/String
      62: dup
      63: iconst_0
      64: ldc           #27                 // String testgroup
      66: aastore
      67: invokestatic  #24                 // Method org/apache/hadoop/hbase/security/User.createUserForTesting:(Lorg/apache/hadoop/conf/Configuration;Ljava/lang/String;[Ljava/lang/String;)Lorg/apache/hadoop/hbase/security/User;
      70: putstatic     #28                 // Field TESTUSER:Lorg/apache/hadoop/hbase/security/User;
      73: getstatic     #13                 // Field TEST_UTIL:Lorg/apache/hadoop/hbase/HBaseTestingUtility;
      76: getstatic     #29                 // Field org/apache/hadoop/hbase/security/visibility/VisibilityConstants.LABELS_TABLE_NAME:Lorg/apache/hadoop/hbase/TableName;
      79: invokevirtual #30                 // Method org/apache/hadoop/hbase/TableName.getName:()[B
      82: ldc2_w        #31                 // long 50000l
      85: invokevirtual #33                 // Method org/apache/hadoop/hbase/HBaseTestingUtility.waitTableEnabled:([BJ)V
      88: getstatic     #25                 // Field SUPERUSER:Lorg/apache/hadoop/hbase/security/User;
      91: new           #34                 // class org/apache/hadoop/hbase/security/visibility/TestVisibilityLablesWithGroups$1
      94: dup
      95: invokespecial #35                 // Method org/apache/hadoop/hbase/security/visibility/TestVisibilityLablesWithGroups$1."<init>":()V
      98: invokevirtual #36                 // Method org/apache/hadoop/hbase/security/User.runAs:(Ljava/security/PrivilegedExceptionAction;)Ljava/lang/Object;
     101: pop
     102: return

  public void testGroupAuths() throws java.lang.Exception;
    Code:
       0: aload_0
       1: getfield      #12                 // Field TEST_NAME:Lorg/junit/rules/TestName;
       4: invokevirtual #37                 // Method org/junit/rules/TestName.getMethodName:()Ljava/lang/String;
       7: invokestatic  #38                 // Method org/apache/hadoop/hbase/TableName.valueOf:(Ljava/lang/String;)Lorg/apache/hadoop/hbase/TableName;
      10: astore_1
      11: getstatic     #13                 // Field TEST_UTIL:Lorg/apache/hadoop/hbase/HBaseTestingUtility;
      14: aload_1
      15: getstatic     #7                  // Field CF:[B
      18: invokevirtual #39                 // Method org/apache/hadoop/hbase/HBaseTestingUtility.createTable:(Lorg/apache/hadoop/hbase/TableName;[B)Lorg/apache/hadoop/hbase/client/Table;
      21: pop
      22: getstatic     #25                 // Field SUPERUSER:Lorg/apache/hadoop/hbase/security/User;
      25: new           #40                 // class org/apache/hadoop/hbase/security/visibility/TestVisibilityLablesWithGroups$2
      28: dup
      29: aload_0
      30: aload_1
      31: invokespecial #41                 // Method org/apache/hadoop/hbase/security/visibility/TestVisibilityLablesWithGroups$2."<init>":(Lorg/apache/hadoop/hbase/security/visibility/TestVisibilityLablesWithGroups;Lorg/apache/hadoop/hbase/TableName;)V
      34: invokevirtual #36                 // Method org/apache/hadoop/hbase/security/User.runAs:(Ljava/security/PrivilegedExceptionAction;)Ljava/lang/Object;
      37: pop
      38: getstatic     #25                 // Field SUPERUSER:Lorg/apache/hadoop/hbase/security/User;
      41: new           #42                 // class org/apache/hadoop/hbase/security/visibility/TestVisibilityLablesWithGroups$3
      44: dup
      45: aload_0
      46: aload_1
      47: invokespecial #43                 // Method org/apache/hadoop/hbase/security/visibility/TestVisibilityLablesWithGroups$3."<init>":(Lorg/apache/hadoop/hbase/security/visibility/TestVisibilityLablesWithGroups;Lorg/apache/hadoop/hbase/TableName;)V
      50: invokevirtual #36                 // Method org/apache/hadoop/hbase/security/User.runAs:(Ljava/security/PrivilegedExceptionAction;)Ljava/lang/Object;
      53: pop
      54: getstatic     #25                 // Field SUPERUSER:Lorg/apache/hadoop/hbase/security/User;
      57: new           #44                 // class org/apache/hadoop/hbase/security/visibility/TestVisibilityLablesWithGroups$4
      60: dup
      61: aload_0
      62: invokespecial #45                 // Method org/apache/hadoop/hbase/security/visibility/TestVisibilityLablesWithGroups$4."<init>":(Lorg/apache/hadoop/hbase/security/visibility/TestVisibilityLablesWithGroups;)V
      65: invokevirtual #36                 // Method org/apache/hadoop/hbase/security/User.runAs:(Ljava/security/PrivilegedExceptionAction;)Ljava/lang/Object;
      68: pop
      69: getstatic     #28                 // Field TESTUSER:Lorg/apache/hadoop/hbase/security/User;
      72: new           #46                 // class org/apache/hadoop/hbase/security/visibility/TestVisibilityLablesWithGroups$5
      75: dup
      76: aload_0
      77: aload_1
      78: invokespecial #47                 // Method org/apache/hadoop/hbase/security/visibility/TestVisibilityLablesWithGroups$5."<init>":(Lorg/apache/hadoop/hbase/security/visibility/TestVisibilityLablesWithGroups;Lorg/apache/hadoop/hbase/TableName;)V
      81: invokevirtual #36                 // Method org/apache/hadoop/hbase/security/User.runAs:(Ljava/security/PrivilegedExceptionAction;)Ljava/lang/Object;
      84: pop
      85: getstatic     #25                 // Field SUPERUSER:Lorg/apache/hadoop/hbase/security/User;
      88: new           #48                 // class org/apache/hadoop/hbase/security/visibility/TestVisibilityLablesWithGroups$6
      91: dup
      92: aload_0
      93: invokespecial #49                 // Method org/apache/hadoop/hbase/security/visibility/TestVisibilityLablesWithGroups$6."<init>":(Lorg/apache/hadoop/hbase/security/visibility/TestVisibilityLablesWithGroups;)V
      96: invokevirtual #36                 // Method org/apache/hadoop/hbase/security/User.runAs:(Ljava/security/PrivilegedExceptionAction;)Ljava/lang/Object;
      99: pop
     100: getstatic     #25                 // Field SUPERUSER:Lorg/apache/hadoop/hbase/security/User;
     103: new           #50                 // class org/apache/hadoop/hbase/security/visibility/TestVisibilityLablesWithGroups$7
     106: dup
     107: aload_0
     108: invokespecial #51                 // Method org/apache/hadoop/hbase/security/visibility/TestVisibilityLablesWithGroups$7."<init>":(Lorg/apache/hadoop/hbase/security/visibility/TestVisibilityLablesWithGroups;)V
     111: invokevirtual #36                 // Method org/apache/hadoop/hbase/security/User.runAs:(Ljava/security/PrivilegedExceptionAction;)Ljava/lang/Object;
     114: pop
     115: getstatic     #28                 // Field TESTUSER:Lorg/apache/hadoop/hbase/security/User;
     118: new           #52                 // class org/apache/hadoop/hbase/security/visibility/TestVisibilityLablesWithGroups$8
     121: dup
     122: aload_0
     123: aload_1
     124: invokespecial #53                 // Method org/apache/hadoop/hbase/security/visibility/TestVisibilityLablesWithGroups$8."<init>":(Lorg/apache/hadoop/hbase/security/visibility/TestVisibilityLablesWithGroups;Lorg/apache/hadoop/hbase/TableName;)V
     127: invokevirtual #36                 // Method org/apache/hadoop/hbase/security/User.runAs:(Ljava/security/PrivilegedExceptionAction;)Ljava/lang/Object;
     130: pop
     131: return

  public static void tearDownAfterClass() throws java.lang.Exception;
    Code:
       0: getstatic     #13                 // Field TEST_UTIL:Lorg/apache/hadoop/hbase/HBaseTestingUtility;
       3: invokevirtual #54                 // Method org/apache/hadoop/hbase/HBaseTestingUtility.shutdownMiniCluster:()V
       6: return

  static byte[] access$000();
    Code:
       0: getstatic     #8                  // Field ROW_1:[B
       3: areturn

  static byte[] access$100();
    Code:
       0: getstatic     #7                  // Field CF:[B
       3: areturn

  static byte[] access$200();
    Code:
       0: getstatic     #6                  // Field Q1:[B
       3: areturn

  static byte[] access$300();
    Code:
       0: getstatic     #5                  // Field value1:[B
       3: areturn

  static byte[] access$400();
    Code:
       0: getstatic     #4                  // Field Q2:[B
       3: areturn

  static byte[] access$500();
    Code:
       0: getstatic     #3                  // Field value2:[B
       3: areturn

  static byte[] access$600();
    Code:
       0: getstatic     #2                  // Field Q3:[B
       3: areturn

  static byte[] access$700();
    Code:
       0: getstatic     #1                  // Field value3:[B
       3: areturn

  static {};
    Code:
       0: ldc           #55                 // class org/apache/hadoop/hbase/security/visibility/TestVisibilityLablesWithGroups
       2: invokestatic  #56                 // Method org/apache/hadoop/hbase/HBaseClassTestRule.forClass:(Ljava/lang/Class;)Lorg/apache/hadoop/hbase/HBaseClassTestRule;
       5: putstatic     #57                 // Field CLASS_RULE:Lorg/apache/hadoop/hbase/HBaseClassTestRule;
       8: new           #58                 // class org/apache/hadoop/hbase/HBaseTestingUtility
      11: dup
      12: invokespecial #59                 // Method org/apache/hadoop/hbase/HBaseTestingUtility."<init>":()V
      15: putstatic     #13                 // Field TEST_UTIL:Lorg/apache/hadoop/hbase/HBaseTestingUtility;
      18: ldc           #60                 // String row1
      20: invokestatic  #61                 // Method org/apache/hadoop/hbase/util/Bytes.toBytes:(Ljava/lang/String;)[B
      23: putstatic     #8                  // Field ROW_1:[B
      26: ldc           #62                 // String f
      28: invokestatic  #61                 // Method org/apache/hadoop/hbase/util/Bytes.toBytes:(Ljava/lang/String;)[B
      31: putstatic     #7                  // Field CF:[B
      34: ldc           #63                 // String q1
      36: invokestatic  #61                 // Method org/apache/hadoop/hbase/util/Bytes.toBytes:(Ljava/lang/String;)[B
      39: putstatic     #6                  // Field Q1:[B
      42: ldc           #64                 // String q2
      44: invokestatic  #61                 // Method org/apache/hadoop/hbase/util/Bytes.toBytes:(Ljava/lang/String;)[B
      47: putstatic     #4                  // Field Q2:[B
      50: ldc           #65                 // String q3
      52: invokestatic  #61                 // Method org/apache/hadoop/hbase/util/Bytes.toBytes:(Ljava/lang/String;)[B
      55: putstatic     #2                  // Field Q3:[B
      58: ldc           #66                 // String value1
      60: invokestatic  #61                 // Method org/apache/hadoop/hbase/util/Bytes.toBytes:(Ljava/lang/String;)[B
      63: putstatic     #5                  // Field value1:[B
      66: ldc           #67                 // String value2
      68: invokestatic  #61                 // Method org/apache/hadoop/hbase/util/Bytes.toBytes:(Ljava/lang/String;)[B
      71: putstatic     #3                  // Field value2:[B
      74: ldc           #68                 // String value3
      76: invokestatic  #61                 // Method org/apache/hadoop/hbase/util/Bytes.toBytes:(Ljava/lang/String;)[B
      79: putstatic     #1                  // Field value3:[B
      82: return
}
