Compiled from "TestCoprocessorInterface.java"
class org.apache.hadoop.hbase.coprocessor.TestCoprocessorInterface$CoprocessorII$1 implements org.apache.hadoop.hbase.coprocessor.RegionObserver {
  final org.apache.hadoop.hbase.coprocessor.TestCoprocessorInterface$CoprocessorII this$0;

  org.apache.hadoop.hbase.coprocessor.TestCoprocessorInterface$CoprocessorII$1(org.apache.hadoop.hbase.coprocessor.TestCoprocessorInterface$CoprocessorII);
    Code:
       0: aload_0
       1: aload_1
       2: putfield      #1                  // Field this$0:Lorg/apache/hadoop/hbase/coprocessor/TestCoprocessorInterface$CoprocessorII;
       5: aload_0
       6: invokespecial #2                  // Method java/lang/Object."<init>":()V
       9: return

  public void preGetOp(org.apache.hadoop.hbase.coprocessor.ObserverContext<org.apache.hadoop.hbase.coprocessor.RegionCoprocessorEnvironment>, org.apache.hadoop.hbase.client.Get, java.util.List<org.apache.hadoop.hbase.Cell>) throws java.io.IOException;
    Code:
       0: new           #3                  // class java/lang/RuntimeException
       3: dup
       4: invokespecial #4                  // Method java/lang/RuntimeException."<init>":()V
       7: athrow
}
