Compiled from "TestCacheConfig.java"
class org.apache.hadoop.hbase.io.hfile.TestCacheConfig$IndexCacheEntry extends org.apache.hadoop.hbase.io.hfile.TestCacheConfig$DataCacheEntry {
  public org.apache.hadoop.hbase.io.hfile.TestCacheConfig$IndexCacheEntry();
    Code:
       0: aload_0
       1: getstatic     #1                  // Field SINGLETON:Lorg/apache/hadoop/hbase/io/hfile/TestCacheConfig$IndexCacheEntry;
       4: invokespecial #2                  // Method org/apache/hadoop/hbase/io/hfile/TestCacheConfig$DataCacheEntry."<init>":(Lorg/apache/hadoop/hbase/io/hfile/Cacheable;)V
       7: return

  public org.apache.hadoop.hbase.io.hfile.BlockType getBlockType();
    Code:
       0: getstatic     #3                  // Field org/apache/hadoop/hbase/io/hfile/BlockType.ROOT_INDEX:Lorg/apache/hadoop/hbase/io/hfile/BlockType;
       3: areturn

  static {};
    Code:
       0: new           #4                  // class org/apache/hadoop/hbase/io/hfile/TestCacheConfig$IndexCacheEntry
       3: dup
       4: invokespecial #5                  // Method "<init>":()V
       7: putstatic     #1                  // Field SINGLETON:Lorg/apache/hadoop/hbase/io/hfile/TestCacheConfig$IndexCacheEntry;
      10: return
}
