Compiled from "TestSyncReplicationActive.java"
public class org.apache.hadoop.hbase.replication.TestSyncReplicationActive extends org.apache.hadoop.hbase.replication.SyncReplicationTestBase {
  public static final org.apache.hadoop.hbase.HBaseClassTestRule CLASS_RULE;

  public org.apache.hadoop.hbase.replication.TestSyncReplicationActive();
    Code:
       0: aload_0
       1: invokespecial #1                  // Method org/apache/hadoop/hbase/replication/SyncReplicationTestBase."<init>":()V
       4: return

  public void testActive() throws java.lang.Exception;
    Code:
       0: getstatic     #2                  // Field UTIL2:Lorg/apache/hadoop/hbase/HBaseTestingUtility;
       3: invokevirtual #3                  // Method org/apache/hadoop/hbase/HBaseTestingUtility.getAdmin:()Lorg/apache/hadoop/hbase/client/Admin;
       6: getstatic     #4                  // Field PEER_ID:Ljava/lang/String;
       9: getstatic     #5                  // Field org/apache/hadoop/hbase/replication/SyncReplicationState.STANDBY:Lorg/apache/hadoop/hbase/replication/SyncReplicationState;
      12: invokeinterface #6,  3            // InterfaceMethod org/apache/hadoop/hbase/client/Admin.transitReplicationPeerSyncReplicationState:(Ljava/lang/String;Lorg/apache/hadoop/hbase/replication/SyncReplicationState;)V
      17: getstatic     #7                  // Field UTIL1:Lorg/apache/hadoop/hbase/HBaseTestingUtility;
      20: invokevirtual #3                  // Method org/apache/hadoop/hbase/HBaseTestingUtility.getAdmin:()Lorg/apache/hadoop/hbase/client/Admin;
      23: getstatic     #4                  // Field PEER_ID:Ljava/lang/String;
      26: getstatic     #8                  // Field org/apache/hadoop/hbase/replication/SyncReplicationState.ACTIVE:Lorg/apache/hadoop/hbase/replication/SyncReplicationState;
      29: invokeinterface #6,  3            // InterfaceMethod org/apache/hadoop/hbase/client/Admin.transitReplicationPeerSyncReplicationState:(Ljava/lang/String;Lorg/apache/hadoop/hbase/replication/SyncReplicationState;)V
      34: aload_0
      35: getstatic     #7                  // Field UTIL1:Lorg/apache/hadoop/hbase/HBaseTestingUtility;
      38: iconst_1
      39: invokevirtual #9                  // Method verifyReplicationRequestRejection:(Lorg/apache/hadoop/hbase/HBaseTestingUtility;Z)V
      42: aload_0
      43: getstatic     #2                  // Field UTIL2:Lorg/apache/hadoop/hbase/HBaseTestingUtility;
      46: iconst_0
      47: invokevirtual #9                  // Method verifyReplicationRequestRejection:(Lorg/apache/hadoop/hbase/HBaseTestingUtility;Z)V
      50: getstatic     #7                  // Field UTIL1:Lorg/apache/hadoop/hbase/HBaseTestingUtility;
      53: invokevirtual #3                  // Method org/apache/hadoop/hbase/HBaseTestingUtility.getAdmin:()Lorg/apache/hadoop/hbase/client/Admin;
      56: getstatic     #4                  // Field PEER_ID:Ljava/lang/String;
      59: invokeinterface #10,  2           // InterfaceMethod org/apache/hadoop/hbase/client/Admin.disableReplicationPeer:(Ljava/lang/String;)V
      64: aload_0
      65: getstatic     #7                  // Field UTIL1:Lorg/apache/hadoop/hbase/HBaseTestingUtility;
      68: iconst_0
      69: bipush        100
      71: invokevirtual #11                 // Method write:(Lorg/apache/hadoop/hbase/HBaseTestingUtility;II)V
      74: ldc2_w        #12                 // long 2000l
      77: invokestatic  #14                 // Method java/lang/Thread.sleep:(J)V
      80: aload_0
      81: getstatic     #2                  // Field UTIL2:Lorg/apache/hadoop/hbase/HBaseTestingUtility;
      84: iconst_0
      85: bipush        100
      87: invokevirtual #15                 // Method verifyNotReplicatedThroughRegion:(Lorg/apache/hadoop/hbase/HBaseTestingUtility;II)V
      90: aload_0
      91: getstatic     #2                  // Field UTIL2:Lorg/apache/hadoop/hbase/HBaseTestingUtility;
      94: getstatic     #16                 // Field REMOTE_WAL_DIR2:Lorg/apache/hadoop/fs/Path;
      97: getstatic     #4                  // Field PEER_ID:Ljava/lang/String;
     100: invokespecial #17                 // Method verifyNoClusterIdInRemoteLog:(Lorg/apache/hadoop/hbase/HBaseTestingUtility;Lorg/apache/hadoop/fs/Path;Ljava/lang/String;)V
     103: getstatic     #2                  // Field UTIL2:Lorg/apache/hadoop/hbase/HBaseTestingUtility;
     106: invokevirtual #3                  // Method org/apache/hadoop/hbase/HBaseTestingUtility.getAdmin:()Lorg/apache/hadoop/hbase/client/Admin;
     109: getstatic     #4                  // Field PEER_ID:Ljava/lang/String;
     112: getstatic     #18                 // Field org/apache/hadoop/hbase/replication/SyncReplicationState.DOWNGRADE_ACTIVE:Lorg/apache/hadoop/hbase/replication/SyncReplicationState;
     115: invokeinterface #6,  3            // InterfaceMethod org/apache/hadoop/hbase/client/Admin.transitReplicationPeerSyncReplicationState:(Ljava/lang/String;Lorg/apache/hadoop/hbase/replication/SyncReplicationState;)V
     120: aload_0
     121: getstatic     #2                  // Field UTIL2:Lorg/apache/hadoop/hbase/HBaseTestingUtility;
     124: iconst_1
     125: invokevirtual #9                  // Method verifyReplicationRequestRejection:(Lorg/apache/hadoop/hbase/HBaseTestingUtility;Z)V
     128: aload_0
     129: getstatic     #2                  // Field UTIL2:Lorg/apache/hadoop/hbase/HBaseTestingUtility;
     132: iconst_0
     133: bipush        100
     135: invokevirtual #19                 // Method verify:(Lorg/apache/hadoop/hbase/HBaseTestingUtility;II)V
     138: getstatic     #7                  // Field UTIL1:Lorg/apache/hadoop/hbase/HBaseTestingUtility;
     141: invokevirtual #20                 // Method org/apache/hadoop/hbase/HBaseTestingUtility.getConfiguration:()Lorg/apache/hadoop/conf/Configuration;
     144: invokestatic  #21                 // Method org/apache/hadoop/hbase/client/ConnectionFactory.createAsyncConnection:(Lorg/apache/hadoop/conf/Configuration;)Ljava/util/concurrent/CompletableFuture;
     147: invokevirtual #22                 // Method java/util/concurrent/CompletableFuture.get:()Ljava/lang/Object;
     150: checkcast     #23                 // class org/apache/hadoop/hbase/client/AsyncConnection
     153: astore_1
     154: aconst_null
     155: astore_2
     156: aload_1
     157: getstatic     #24                 // Field TABLE_NAME:Lorg/apache/hadoop/hbase/TableName;
     160: invokeinterface #25,  2           // InterfaceMethod org/apache/hadoop/hbase/client/AsyncConnection.getTableBuilder:(Lorg/apache/hadoop/hbase/TableName;)Lorg/apache/hadoop/hbase/client/AsyncTableBuilder;
     165: iconst_1
     166: invokeinterface #26,  2           // InterfaceMethod org/apache/hadoop/hbase/client/AsyncTableBuilder.setMaxAttempts:(I)Lorg/apache/hadoop/hbase/client/AsyncTableBuilder;
     171: invokeinterface #27,  1           // InterfaceMethod org/apache/hadoop/hbase/client/AsyncTableBuilder.build:()Lorg/apache/hadoop/hbase/client/AsyncTable;
     176: astore_3
     177: aload_3
     178: new           #28                 // class org/apache/hadoop/hbase/client/Put
     181: dup
     182: sipush        1000
     185: invokestatic  #29                 // Method org/apache/hadoop/hbase/util/Bytes.toBytes:(I)[B
     188: invokespecial #30                 // Method org/apache/hadoop/hbase/client/Put."<init>":([B)V
     191: getstatic     #31                 // Field CF:[B
     194: getstatic     #32                 // Field CQ:[B
     197: sipush        1000
     200: invokestatic  #29                 // Method org/apache/hadoop/hbase/util/Bytes.toBytes:(I)[B
     203: invokevirtual #33                 // Method org/apache/hadoop/hbase/client/Put.addColumn:([B[B[B)Lorg/apache/hadoop/hbase/client/Put;
     206: invokeinterface #34,  2           // InterfaceMethod org/apache/hadoop/hbase/client/AsyncTable.put:(Lorg/apache/hadoop/hbase/client/Put;)Ljava/util/concurrent/CompletableFuture;
     211: astore        4
     213: ldc2_w        #12                 // long 2000l
     216: invokestatic  #14                 // Method java/lang/Thread.sleep:(J)V
     219: aload         4
     221: invokevirtual #35                 // Method java/util/concurrent/CompletableFuture.isDone:()Z
     224: invokestatic  #36                 // Method org/junit/Assert.assertFalse:(Z)V
     227: getstatic     #7                  // Field UTIL1:Lorg/apache/hadoop/hbase/HBaseTestingUtility;
     230: invokevirtual #3                  // Method org/apache/hadoop/hbase/HBaseTestingUtility.getAdmin:()Lorg/apache/hadoop/hbase/client/Admin;
     233: getstatic     #4                  // Field PEER_ID:Ljava/lang/String;
     236: getstatic     #5                  // Field org/apache/hadoop/hbase/replication/SyncReplicationState.STANDBY:Lorg/apache/hadoop/hbase/replication/SyncReplicationState;
     239: invokeinterface #6,  3            // InterfaceMethod org/apache/hadoop/hbase/client/Admin.transitReplicationPeerSyncReplicationState:(Ljava/lang/String;Lorg/apache/hadoop/hbase/replication/SyncReplicationState;)V
     244: aload         4
     246: invokevirtual #22                 // Method java/util/concurrent/CompletableFuture.get:()Ljava/lang/Object;
     249: pop
     250: ldc           #37                 // String should fail because of the wal is closing
     252: invokestatic  #38                 // Method org/junit/Assert.fail:(Ljava/lang/String;)V
     255: goto          276
     258: astore        5
     260: aload         5
     262: invokevirtual #40                 // Method java/util/concurrent/ExecutionException.getCause:()Ljava/lang/Throwable;
     265: invokevirtual #41                 // Method java/lang/Throwable.getMessage:()Ljava/lang/String;
     268: ldc           #42                 // String only marker edit is allowed
     270: invokestatic  #43                 // Method org/hamcrest/CoreMatchers.containsString:(Ljava/lang/String;)Lorg/hamcrest/Matcher;
     273: invokestatic  #44                 // Method org/junit/Assert.assertThat:(Ljava/lang/Object;Lorg/hamcrest/Matcher;)V
     276: aload_1
     277: ifnull        355
     280: aload_2
     281: ifnull        302
     284: aload_1
     285: invokeinterface #45,  1           // InterfaceMethod org/apache/hadoop/hbase/client/AsyncConnection.close:()V
     290: goto          355
     293: astore_3
     294: aload_2
     295: aload_3
     296: invokevirtual #47                 // Method java/lang/Throwable.addSuppressed:(Ljava/lang/Throwable;)V
     299: goto          355
     302: aload_1
     303: invokeinterface #45,  1           // InterfaceMethod org/apache/hadoop/hbase/client/AsyncConnection.close:()V
     308: goto          355
     311: astore_3
     312: aload_3
     313: astore_2
     314: aload_3
     315: athrow
     316: astore        6
     318: aload_1
     319: ifnull        352
     322: aload_2
     323: ifnull        346
     326: aload_1
     327: invokeinterface #45,  1           // InterfaceMethod org/apache/hadoop/hbase/client/AsyncConnection.close:()V
     332: goto          352
     335: astore        7
     337: aload_2
     338: aload         7
     340: invokevirtual #47                 // Method java/lang/Throwable.addSuppressed:(Ljava/lang/Throwable;)V
     343: goto          352
     346: aload_1
     347: invokeinterface #45,  1           // InterfaceMethod org/apache/hadoop/hbase/client/AsyncConnection.close:()V
     352: aload         6
     354: athrow
     355: getstatic     #7                  // Field UTIL1:Lorg/apache/hadoop/hbase/HBaseTestingUtility;
     358: invokevirtual #48                 // Method org/apache/hadoop/hbase/HBaseTestingUtility.getMiniHBaseCluster:()Lorg/apache/hadoop/hbase/MiniHBaseCluster;
     361: getstatic     #24                 // Field TABLE_NAME:Lorg/apache/hadoop/hbase/TableName;
     364: invokevirtual #49                 // Method org/apache/hadoop/hbase/MiniHBaseCluster.getRegions:(Lorg/apache/hadoop/hbase/TableName;)Ljava/util/List;
     367: iconst_0
     368: invokeinterface #50,  2           // InterfaceMethod java/util/List.get:(I)Ljava/lang/Object;
     373: checkcast     #51                 // class org/apache/hadoop/hbase/regionserver/HRegion
     376: astore_1
     377: aload_1
     378: new           #52                 // class org/apache/hadoop/hbase/client/Get
     381: dup
     382: sipush        1000
     385: invokestatic  #29                 // Method org/apache/hadoop/hbase/util/Bytes.toBytes:(I)[B
     388: invokespecial #53                 // Method org/apache/hadoop/hbase/client/Get."<init>":([B)V
     391: invokevirtual #54                 // Method org/apache/hadoop/hbase/regionserver/HRegion.get:(Lorg/apache/hadoop/hbase/client/Get;)Lorg/apache/hadoop/hbase/client/Result;
     394: invokevirtual #55                 // Method org/apache/hadoop/hbase/client/Result.isEmpty:()Z
     397: invokestatic  #56                 // Method org/junit/Assert.assertTrue:(Z)V
     400: getstatic     #2                  // Field UTIL2:Lorg/apache/hadoop/hbase/HBaseTestingUtility;
     403: invokevirtual #3                  // Method org/apache/hadoop/hbase/HBaseTestingUtility.getAdmin:()Lorg/apache/hadoop/hbase/client/Admin;
     406: getstatic     #4                  // Field PEER_ID:Ljava/lang/String;
     409: getstatic     #8                  // Field org/apache/hadoop/hbase/replication/SyncReplicationState.ACTIVE:Lorg/apache/hadoop/hbase/replication/SyncReplicationState;
     412: invokeinterface #6,  3            // InterfaceMethod org/apache/hadoop/hbase/client/Admin.transitReplicationPeerSyncReplicationState:(Ljava/lang/String;Lorg/apache/hadoop/hbase/replication/SyncReplicationState;)V
     417: aload_0
     418: getstatic     #2                  // Field UTIL2:Lorg/apache/hadoop/hbase/HBaseTestingUtility;
     421: getstatic     #7                  // Field UTIL1:Lorg/apache/hadoop/hbase/HBaseTestingUtility;
     424: bipush        100
     426: sipush        200
     429: invokevirtual #57                 // Method writeAndVerifyReplication:(Lorg/apache/hadoop/hbase/HBaseTestingUtility;Lorg/apache/hadoop/hbase/HBaseTestingUtility;II)V
     432: getstatic     #7                  // Field UTIL1:Lorg/apache/hadoop/hbase/HBaseTestingUtility;
     435: invokevirtual #58                 // Method org/apache/hadoop/hbase/HBaseTestingUtility.shutdownMiniCluster:()V
     438: getstatic     #2                  // Field UTIL2:Lorg/apache/hadoop/hbase/HBaseTestingUtility;
     441: invokevirtual #3                  // Method org/apache/hadoop/hbase/HBaseTestingUtility.getAdmin:()Lorg/apache/hadoop/hbase/client/Admin;
     444: getstatic     #4                  // Field PEER_ID:Ljava/lang/String;
     447: getstatic     #18                 // Field org/apache/hadoop/hbase/replication/SyncReplicationState.DOWNGRADE_ACTIVE:Lorg/apache/hadoop/hbase/replication/SyncReplicationState;
     450: invokeinterface #6,  3            // InterfaceMethod org/apache/hadoop/hbase/client/Admin.transitReplicationPeerSyncReplicationState:(Ljava/lang/String;Lorg/apache/hadoop/hbase/replication/SyncReplicationState;)V
     455: aload_0
     456: getstatic     #2                  // Field UTIL2:Lorg/apache/hadoop/hbase/HBaseTestingUtility;
     459: iconst_1
     460: invokevirtual #9                  // Method verifyReplicationRequestRejection:(Lorg/apache/hadoop/hbase/HBaseTestingUtility;Z)V
     463: aload_0
     464: getstatic     #2                  // Field UTIL2:Lorg/apache/hadoop/hbase/HBaseTestingUtility;
     467: sipush        200
     470: sipush        300
     473: invokevirtual #11                 // Method write:(Lorg/apache/hadoop/hbase/HBaseTestingUtility;II)V
     476: return
    Exception table:
       from    to  target type
         244   255   258   Class java/util/concurrent/ExecutionException
         284   290   293   Class java/lang/Throwable
         156   276   311   Class java/lang/Throwable
         156   276   316   any
         326   332   335   Class java/lang/Throwable
         311   318   316   any

  static {};
    Code:
       0: ldc           #71                 // class org/apache/hadoop/hbase/replication/TestSyncReplicationActive
       2: invokestatic  #72                 // Method org/apache/hadoop/hbase/HBaseClassTestRule.forClass:(Ljava/lang/Class;)Lorg/apache/hadoop/hbase/HBaseClassTestRule;
       5: putstatic     #73                 // Field CLASS_RULE:Lorg/apache/hadoop/hbase/HBaseClassTestRule;
       8: return
}
