Compiled from "TestTablesWithQuotas.java"
class org.apache.hadoop.hbase.quotas.TestTablesWithQuotas$1 extends org.apache.hadoop.hbase.quotas.QuotaObserverChore$TablesWithQuotas {
  final org.apache.hadoop.conf.Configuration val$conf;

  final java.util.Map val$actualRegions;

  final java.util.Map val$reportedRegions;

  final org.apache.hadoop.hbase.quotas.TestTablesWithQuotas this$0;

  org.apache.hadoop.hbase.quotas.TestTablesWithQuotas$1(org.apache.hadoop.hbase.quotas.TestTablesWithQuotas, org.apache.hadoop.hbase.client.Connection, org.apache.hadoop.conf.Configuration, org.apache.hadoop.conf.Configuration, java.util.Map, java.util.Map);
    Code:
       0: aload_0
       1: aload_1
       2: putfield      #1                  // Field this$0:Lorg/apache/hadoop/hbase/quotas/TestTablesWithQuotas;
       5: aload_0
       6: aload         4
       8: putfield      #2                  // Field val$conf:Lorg/apache/hadoop/conf/Configuration;
      11: aload_0
      12: aload         5
      14: putfield      #3                  // Field val$actualRegions:Ljava/util/Map;
      17: aload_0
      18: aload         6
      20: putfield      #4                  // Field val$reportedRegions:Ljava/util/Map;
      23: aload_0
      24: aload_2
      25: aload_3
      26: invokespecial #5                  // Method org/apache/hadoop/hbase/quotas/QuotaObserverChore$TablesWithQuotas."<init>":(Lorg/apache/hadoop/hbase/client/Connection;Lorg/apache/hadoop/conf/Configuration;)V
      29: return

  org.apache.hadoop.conf.Configuration getConfiguration();
    Code:
       0: aload_0
       1: getfield      #2                  // Field val$conf:Lorg/apache/hadoop/conf/Configuration;
       4: areturn

  int getNumRegions(org.apache.hadoop.hbase.TableName);
    Code:
       0: aload_0
       1: getfield      #3                  // Field val$actualRegions:Ljava/util/Map;
       4: aload_1
       5: invokeinterface #6,  2            // InterfaceMethod java/util/Map.get:(Ljava/lang/Object;)Ljava/lang/Object;
      10: checkcast     #7                  // class java/lang/Integer
      13: invokevirtual #8                  // Method java/lang/Integer.intValue:()I
      16: ireturn

  int getNumReportedRegions(org.apache.hadoop.hbase.TableName, org.apache.hadoop.hbase.quotas.QuotaSnapshotStore<org.apache.hadoop.hbase.TableName>);
    Code:
       0: aload_0
       1: getfield      #4                  // Field val$reportedRegions:Ljava/util/Map;
       4: aload_1
       5: invokeinterface #6,  2            // InterfaceMethod java/util/Map.get:(Ljava/lang/Object;)Ljava/lang/Object;
      10: checkcast     #7                  // class java/lang/Integer
      13: invokevirtual #8                  // Method java/lang/Integer.intValue:()I
      16: ireturn
}
