Compiled from "TestAssignmentManagerBase.java"
public class org.apache.hadoop.hbase.master.assignment.TestAssignmentManagerBase$FaultyRsExecutor implements org.apache.hadoop.hbase.master.assignment.TestAssignmentManagerBase$MockRSExecutor {
  public org.apache.hadoop.hbase.master.assignment.TestAssignmentManagerBase$FaultyRsExecutor(java.io.IOException);
    Code:
       0: aload_0
       1: invokespecial #1                  // Method java/lang/Object."<init>":()V
       4: aload_0
       5: aload_1
       6: putfield      #2                  // Field exception:Ljava/io/IOException;
       9: return

  public org.apache.hadoop.hbase.shaded.protobuf.generated.AdminProtos$ExecuteProceduresResponse sendRequest(org.apache.hadoop.hbase.ServerName, org.apache.hadoop.hbase.shaded.protobuf.generated.AdminProtos$ExecuteProceduresRequest) throws java.io.IOException;
    Code:
       0: aload_0
       1: getfield      #2                  // Field exception:Ljava/io/IOException;
       4: athrow
}
