Compiled from "TestTransitPeerSyncReplicationStateProcedureRetry.java"
public class org.apache.hadoop.hbase.master.replication.TestTransitPeerSyncReplicationStateProcedureRetry extends org.apache.hadoop.hbase.replication.SyncReplicationTestBase {
  public static final org.apache.hadoop.hbase.HBaseClassTestRule CLASS_RULE;

  public org.apache.hadoop.hbase.master.replication.TestTransitPeerSyncReplicationStateProcedureRetry();
    Code:
       0: aload_0
       1: invokespecial #3                  // Method org/apache/hadoop/hbase/replication/SyncReplicationTestBase."<init>":()V
       4: return

  public static void setUp() throws java.lang.Exception;
    Code:
       0: getstatic     #1                  // Field UTIL2:Lorg/apache/hadoop/hbase/HBaseTestingUtility;
       3: invokevirtual #4                  // Method org/apache/hadoop/hbase/HBaseTestingUtility.getConfiguration:()Lorg/apache/hadoop/conf/Configuration;
       6: ldc           #6                  // String hbase.master.procedure.threads
       8: iconst_1
       9: invokevirtual #7                  // Method org/apache/hadoop/conf/Configuration.setInt:(Ljava/lang/String;I)V
      12: invokestatic  #8                  // Method org/apache/hadoop/hbase/replication/SyncReplicationTestBase.setUp:()V
      15: return

  public void testRecoveryAndDoubleExecution() throws java.lang.Exception;
    Code:
       0: getstatic     #1                  // Field UTIL2:Lorg/apache/hadoop/hbase/HBaseTestingUtility;
       3: invokevirtual #9                  // Method org/apache/hadoop/hbase/HBaseTestingUtility.getAdmin:()Lorg/apache/hadoop/hbase/client/Admin;
       6: getstatic     #2                  // Field PEER_ID:Ljava/lang/String;
       9: getstatic     #10                 // Field org/apache/hadoop/hbase/replication/SyncReplicationState.STANDBY:Lorg/apache/hadoop/hbase/replication/SyncReplicationState;
      12: invokeinterface #11,  3           // InterfaceMethod org/apache/hadoop/hbase/client/Admin.transitReplicationPeerSyncReplicationState:(Ljava/lang/String;Lorg/apache/hadoop/hbase/replication/SyncReplicationState;)V
      17: getstatic     #12                 // Field UTIL1:Lorg/apache/hadoop/hbase/HBaseTestingUtility;
      20: invokevirtual #9                  // Method org/apache/hadoop/hbase/HBaseTestingUtility.getAdmin:()Lorg/apache/hadoop/hbase/client/Admin;
      23: getstatic     #2                  // Field PEER_ID:Ljava/lang/String;
      26: getstatic     #13                 // Field org/apache/hadoop/hbase/replication/SyncReplicationState.ACTIVE:Lorg/apache/hadoop/hbase/replication/SyncReplicationState;
      29: invokeinterface #11,  3           // InterfaceMethod org/apache/hadoop/hbase/client/Admin.transitReplicationPeerSyncReplicationState:(Ljava/lang/String;Lorg/apache/hadoop/hbase/replication/SyncReplicationState;)V
      34: getstatic     #12                 // Field UTIL1:Lorg/apache/hadoop/hbase/HBaseTestingUtility;
      37: invokevirtual #9                  // Method org/apache/hadoop/hbase/HBaseTestingUtility.getAdmin:()Lorg/apache/hadoop/hbase/client/Admin;
      40: getstatic     #2                  // Field PEER_ID:Ljava/lang/String;
      43: invokeinterface #14,  2           // InterfaceMethod org/apache/hadoop/hbase/client/Admin.disableReplicationPeer:(Ljava/lang/String;)V
      48: aload_0
      49: getstatic     #12                 // Field UTIL1:Lorg/apache/hadoop/hbase/HBaseTestingUtility;
      52: iconst_0
      53: bipush        100
      55: invokevirtual #15                 // Method write:(Lorg/apache/hadoop/hbase/HBaseTestingUtility;II)V
      58: ldc2_w        #16                 // long 2000l
      61: invokestatic  #18                 // Method java/lang/Thread.sleep:(J)V
      64: aload_0
      65: getstatic     #1                  // Field UTIL2:Lorg/apache/hadoop/hbase/HBaseTestingUtility;
      68: iconst_0
      69: bipush        100
      71: invokevirtual #19                 // Method verifyNotReplicatedThroughRegion:(Lorg/apache/hadoop/hbase/HBaseTestingUtility;II)V
      74: getstatic     #12                 // Field UTIL1:Lorg/apache/hadoop/hbase/HBaseTestingUtility;
      77: invokevirtual #9                  // Method org/apache/hadoop/hbase/HBaseTestingUtility.getAdmin:()Lorg/apache/hadoop/hbase/client/Admin;
      80: getstatic     #2                  // Field PEER_ID:Ljava/lang/String;
      83: getstatic     #20                 // Field org/apache/hadoop/hbase/replication/SyncReplicationState.DOWNGRADE_ACTIVE:Lorg/apache/hadoop/hbase/replication/SyncReplicationState;
      86: invokeinterface #11,  3           // InterfaceMethod org/apache/hadoop/hbase/client/Admin.transitReplicationPeerSyncReplicationState:(Ljava/lang/String;Lorg/apache/hadoop/hbase/replication/SyncReplicationState;)V
      91: getstatic     #1                  // Field UTIL2:Lorg/apache/hadoop/hbase/HBaseTestingUtility;
      94: invokevirtual #21                 // Method org/apache/hadoop/hbase/HBaseTestingUtility.getHBaseCluster:()Lorg/apache/hadoop/hbase/MiniHBaseCluster;
      97: invokevirtual #22                 // Method org/apache/hadoop/hbase/MiniHBaseCluster.getMaster:()Lorg/apache/hadoop/hbase/master/HMaster;
     100: astore_1
     101: aload_1
     102: invokevirtual #23                 // Method org/apache/hadoop/hbase/master/HMaster.getMasterProcedureExecutor:()Lorg/apache/hadoop/hbase/procedure2/ProcedureExecutor;
     105: astore_2
     106: aload_2
     107: invokestatic  #24                 // Method org/apache/hadoop/hbase/procedure2/ProcedureTestingUtility.waitNoProcedureRunning:(Lorg/apache/hadoop/hbase/procedure2/ProcedureExecutor;)V
     110: aload_2
     111: iconst_1
     112: invokestatic  #25                 // Method org/apache/hadoop/hbase/procedure2/ProcedureTestingUtility.setKillAndToggleBeforeStoreUpdate:(Lorg/apache/hadoop/hbase/procedure2/ProcedureExecutor;Z)V
     115: new           #26                 // class org/apache/hadoop/hbase/master/replication/TestTransitPeerSyncReplicationStateProcedureRetry$1
     118: dup
     119: aload_0
     120: invokespecial #27                 // Method org/apache/hadoop/hbase/master/replication/TestTransitPeerSyncReplicationStateProcedureRetry$1."<init>":(Lorg/apache/hadoop/hbase/master/replication/TestTransitPeerSyncReplicationStateProcedureRetry;)V
     123: astore_3
     124: aload_3
     125: invokevirtual #28                 // Method java/lang/Thread.start:()V
     128: getstatic     #1                  // Field UTIL2:Lorg/apache/hadoop/hbase/HBaseTestingUtility;
     131: ldc2_w        #29                 // long 30000l
     134: aload_2
     135: invokedynamic #31,  0             // InvokeDynamic #0:evaluate:(Lorg/apache/hadoop/hbase/procedure2/ProcedureExecutor;)Lorg/apache/hadoop/hbase/Waiter$Predicate;
     140: invokevirtual #32                 // Method org/apache/hadoop/hbase/HBaseTestingUtility.waitFor:(JLorg/apache/hadoop/hbase/Waiter$Predicate;)J
     143: pop2
     144: aload_2
     145: invokevirtual #33                 // Method org/apache/hadoop/hbase/procedure2/ProcedureExecutor.getProcedures:()Ljava/util/List;
     148: invokeinterface #34,  1           // InterfaceMethod java/util/List.stream:()Ljava/util/stream/Stream;
     153: invokedynamic #35,  0             // InvokeDynamic #1:test:()Ljava/util/function/Predicate;
     158: invokeinterface #36,  2           // InterfaceMethod java/util/stream/Stream.filter:(Ljava/util/function/Predicate;)Ljava/util/stream/Stream;
     163: invokedynamic #37,  0             // InvokeDynamic #2:applyAsLong:()Ljava/util/function/ToLongFunction;
     168: invokeinterface #38,  2           // InterfaceMethod java/util/stream/Stream.mapToLong:(Ljava/util/function/ToLongFunction;)Ljava/util/stream/LongStream;
     173: invokeinterface #39,  1           // InterfaceMethod java/util/stream/LongStream.min:()Ljava/util/OptionalLong;
     178: invokevirtual #40                 // Method java/util/OptionalLong.getAsLong:()J
     181: lstore        4
     183: aload_2
     184: lload         4
     186: invokestatic  #41                 // Method org/apache/hadoop/hbase/master/procedure/MasterProcedureTestingUtility.testRecoveryAndDoubleExecution:(Lorg/apache/hadoop/hbase/procedure2/ProcedureExecutor;J)V
     189: aload_2
     190: iconst_0
     191: invokestatic  #25                 // Method org/apache/hadoop/hbase/procedure2/ProcedureTestingUtility.setKillAndToggleBeforeStoreUpdate:(Lorg/apache/hadoop/hbase/procedure2/ProcedureExecutor;Z)V
     194: getstatic     #20                 // Field org/apache/hadoop/hbase/replication/SyncReplicationState.DOWNGRADE_ACTIVE:Lorg/apache/hadoop/hbase/replication/SyncReplicationState;
     197: getstatic     #1                  // Field UTIL2:Lorg/apache/hadoop/hbase/HBaseTestingUtility;
     200: invokevirtual #9                  // Method org/apache/hadoop/hbase/HBaseTestingUtility.getAdmin:()Lorg/apache/hadoop/hbase/client/Admin;
     203: getstatic     #2                  // Field PEER_ID:Ljava/lang/String;
     206: invokeinterface #42,  2           // InterfaceMethod org/apache/hadoop/hbase/client/Admin.getReplicationPeerSyncReplicationState:(Ljava/lang/String;)Lorg/apache/hadoop/hbase/replication/SyncReplicationState;
     211: invokestatic  #43                 // Method org/junit/Assert.assertEquals:(Ljava/lang/Object;Ljava/lang/Object;)V
     214: aload_0
     215: getstatic     #1                  // Field UTIL2:Lorg/apache/hadoop/hbase/HBaseTestingUtility;
     218: iconst_0
     219: bipush        100
     221: invokevirtual #44                 // Method verify:(Lorg/apache/hadoop/hbase/HBaseTestingUtility;II)V
     224: return

  static java.lang.String access$000();
    Code:
       0: getstatic     #2                  // Field PEER_ID:Ljava/lang/String;
       3: areturn

  static org.apache.hadoop.hbase.HBaseTestingUtility access$100();
    Code:
       0: getstatic     #1                  // Field UTIL2:Lorg/apache/hadoop/hbase/HBaseTestingUtility;
       3: areturn

  static {};
    Code:
       0: ldc           #49                 // class org/apache/hadoop/hbase/master/replication/TestTransitPeerSyncReplicationStateProcedureRetry
       2: invokestatic  #50                 // Method org/apache/hadoop/hbase/HBaseClassTestRule.forClass:(Ljava/lang/Class;)Lorg/apache/hadoop/hbase/HBaseClassTestRule;
       5: putstatic     #51                 // Field CLASS_RULE:Lorg/apache/hadoop/hbase/HBaseClassTestRule;
       8: return
}
