Compiled from "TestProcedureReplayOrder.java"
public abstract class org.apache.hadoop.hbase.procedure2.TestProcedureReplayOrder$TestProcedure extends org.apache.hadoop.hbase.procedure2.Procedure<org.apache.hadoop.hbase.procedure2.TestProcedureReplayOrder$TestProcedureEnv> {
  protected long execId;

  protected int step;

  public org.apache.hadoop.hbase.procedure2.TestProcedureReplayOrder$TestProcedure();
    Code:
       0: aload_0
       1: invokespecial #1                  // Method org/apache/hadoop/hbase/procedure2/Procedure."<init>":()V
       4: aload_0
       5: lconst_0
       6: putfield      #2                  // Field execId:J
       9: aload_0
      10: iconst_0
      11: putfield      #3                  // Field step:I
      14: return

  public long getExecId();
    Code:
       0: aload_0
       1: getfield      #2                  // Field execId:J
       4: lreturn

  protected void rollback(org.apache.hadoop.hbase.procedure2.TestProcedureReplayOrder$TestProcedureEnv);
    Code:
       0: return

  protected boolean abort(org.apache.hadoop.hbase.procedure2.TestProcedureReplayOrder$TestProcedureEnv);
    Code:
       0: iconst_1
       1: ireturn

  protected void serializeStateData(org.apache.hadoop.hbase.procedure2.ProcedureStateSerializer) throws java.io.IOException;
    Code:
       0: invokestatic  #4                  // Method org/apache/hbase/thirdparty/com/google/protobuf/Int64Value.newBuilder:()Lorg/apache/hbase/thirdparty/com/google/protobuf/Int64Value$Builder;
       3: aload_0
       4: getfield      #2                  // Field execId:J
       7: invokevirtual #5                  // Method org/apache/hbase/thirdparty/com/google/protobuf/Int64Value$Builder.setValue:(J)Lorg/apache/hbase/thirdparty/com/google/protobuf/Int64Value$Builder;
      10: astore_2
      11: aload_1
      12: aload_2
      13: invokevirtual #6                  // Method org/apache/hbase/thirdparty/com/google/protobuf/Int64Value$Builder.build:()Lorg/apache/hbase/thirdparty/com/google/protobuf/Int64Value;
      16: invokeinterface #7,  2            // InterfaceMethod org/apache/hadoop/hbase/procedure2/ProcedureStateSerializer.serialize:(Lorg/apache/hbase/thirdparty/com/google/protobuf/Message;)V
      21: return

  protected void deserializeStateData(org.apache.hadoop.hbase.procedure2.ProcedureStateSerializer) throws java.io.IOException;
    Code:
       0: aload_1
       1: ldc           #8                  // class org/apache/hbase/thirdparty/com/google/protobuf/Int64Value
       3: invokeinterface #9,  2            // InterfaceMethod org/apache/hadoop/hbase/procedure2/ProcedureStateSerializer.deserialize:(Ljava/lang/Class;)Lorg/apache/hbase/thirdparty/com/google/protobuf/Message;
       8: checkcast     #8                  // class org/apache/hbase/thirdparty/com/google/protobuf/Int64Value
      11: astore_2
      12: aload_0
      13: aload_2
      14: invokevirtual #10                 // Method org/apache/hbase/thirdparty/com/google/protobuf/Int64Value.getValue:()J
      17: putfield      #2                  // Field execId:J
      20: aload_0
      21: iconst_2
      22: putfield      #3                  // Field step:I
      25: return

  protected boolean abort(java.lang.Object);
    Code:
       0: aload_0
       1: aload_1
       2: checkcast     #11                 // class org/apache/hadoop/hbase/procedure2/TestProcedureReplayOrder$TestProcedureEnv
       5: invokevirtual #12                 // Method abort:(Lorg/apache/hadoop/hbase/procedure2/TestProcedureReplayOrder$TestProcedureEnv;)Z
       8: ireturn

  protected void rollback(java.lang.Object) throws java.io.IOException, java.lang.InterruptedException;
    Code:
       0: aload_0
       1: aload_1
       2: checkcast     #11                 // class org/apache/hadoop/hbase/procedure2/TestProcedureReplayOrder$TestProcedureEnv
       5: invokevirtual #13                 // Method rollback:(Lorg/apache/hadoop/hbase/procedure2/TestProcedureReplayOrder$TestProcedureEnv;)V
       8: return
}
