Compiled from "TestFSHLogProvider.java"
public class org.apache.hadoop.hbase.wal.TestFSHLogProvider {
  public static final org.apache.hadoop.hbase.HBaseClassTestRule CLASS_RULE;

  public final org.junit.rules.TestName currentTest;

  public org.apache.hadoop.hbase.wal.TestFSHLogProvider();
    Code:
       0: aload_0
       1: invokespecial #1                  // Method java/lang/Object."<init>":()V
       4: aload_0
       5: new           #2                  // class org/junit/rules/TestName
       8: dup
       9: invokespecial #3                  // Method org/junit/rules/TestName."<init>":()V
      12: putfield      #4                  // Field currentTest:Lorg/junit/rules/TestName;
      15: return

  public void setUp() throws java.lang.Exception;
    Code:
       0: aload_0
       1: new           #5                  // class org/apache/hadoop/hbase/regionserver/MultiVersionConcurrencyControl
       4: dup
       5: invokespecial #6                  // Method org/apache/hadoop/hbase/regionserver/MultiVersionConcurrencyControl."<init>":()V
       8: putfield      #7                  // Field mvcc:Lorg/apache/hadoop/hbase/regionserver/MultiVersionConcurrencyControl;
      11: getstatic     #8                  // Field fs:Lorg/apache/hadoop/fs/FileSystem;
      14: new           #9                  // class org/apache/hadoop/fs/Path
      17: dup
      18: ldc           #10                 // String /
      20: invokespecial #11                 // Method org/apache/hadoop/fs/Path."<init>":(Ljava/lang/String;)V
      23: invokevirtual #12                 // Method org/apache/hadoop/fs/FileSystem.listStatus:(Lorg/apache/hadoop/fs/Path;)[Lorg/apache/hadoop/fs/FileStatus;
      26: astore_1
      27: aload_1
      28: astore_2
      29: aload_2
      30: arraylength
      31: istore_3
      32: iconst_0
      33: istore        4
      35: iload         4
      37: iload_3
      38: if_icmpge     66
      41: aload_2
      42: iload         4
      44: aaload
      45: astore        5
      47: getstatic     #8                  // Field fs:Lorg/apache/hadoop/fs/FileSystem;
      50: aload         5
      52: invokevirtual #13                 // Method org/apache/hadoop/fs/FileStatus.getPath:()Lorg/apache/hadoop/fs/Path;
      55: iconst_1
      56: invokevirtual #14                 // Method org/apache/hadoop/fs/FileSystem.delete:(Lorg/apache/hadoop/fs/Path;Z)Z
      59: pop
      60: iinc          4, 1
      63: goto          35
      66: return

  public static void setUpBeforeClass() throws java.lang.Exception;
    Code:
       0: getstatic     #15                 // Field TEST_UTIL:Lorg/apache/hadoop/hbase/HBaseTestingUtility;
       3: invokevirtual #16                 // Method org/apache/hadoop/hbase/HBaseTestingUtility.getConfiguration:()Lorg/apache/hadoop/conf/Configuration;
       6: ldc           #17                 // String dfs.blocksize
       8: ldc           #18                 // int 1048576
      10: invokevirtual #19                 // Method org/apache/hadoop/conf/Configuration.setInt:(Ljava/lang/String;I)V
      13: getstatic     #15                 // Field TEST_UTIL:Lorg/apache/hadoop/hbase/HBaseTestingUtility;
      16: invokevirtual #16                 // Method org/apache/hadoop/hbase/HBaseTestingUtility.getConfiguration:()Lorg/apache/hadoop/conf/Configuration;
      19: ldc           #20                 // String dfs.namenode.heartbeat.recheck-interval
      21: sipush        5000
      24: invokevirtual #19                 // Method org/apache/hadoop/conf/Configuration.setInt:(Ljava/lang/String;I)V
      27: getstatic     #15                 // Field TEST_UTIL:Lorg/apache/hadoop/hbase/HBaseTestingUtility;
      30: invokevirtual #16                 // Method org/apache/hadoop/hbase/HBaseTestingUtility.getConfiguration:()Lorg/apache/hadoop/conf/Configuration;
      33: ldc           #21                 // String dfs.heartbeat.interval
      35: iconst_1
      36: invokevirtual #19                 // Method org/apache/hadoop/conf/Configuration.setInt:(Ljava/lang/String;I)V
      39: getstatic     #15                 // Field TEST_UTIL:Lorg/apache/hadoop/hbase/HBaseTestingUtility;
      42: invokevirtual #16                 // Method org/apache/hadoop/hbase/HBaseTestingUtility.getConfiguration:()Lorg/apache/hadoop/conf/Configuration;
      45: ldc           #22                 // String dfs.client.socket-timeout
      47: sipush        5000
      50: invokevirtual #19                 // Method org/apache/hadoop/conf/Configuration.setInt:(Ljava/lang/String;I)V
      53: getstatic     #15                 // Field TEST_UTIL:Lorg/apache/hadoop/hbase/HBaseTestingUtility;
      56: invokevirtual #16                 // Method org/apache/hadoop/hbase/HBaseTestingUtility.getConfiguration:()Lorg/apache/hadoop/conf/Configuration;
      59: ldc           #23                 // String hbase.ipc.client.connect.max.retries
      61: iconst_1
      62: invokevirtual #19                 // Method org/apache/hadoop/conf/Configuration.setInt:(Ljava/lang/String;I)V
      65: getstatic     #15                 // Field TEST_UTIL:Lorg/apache/hadoop/hbase/HBaseTestingUtility;
      68: invokevirtual #16                 // Method org/apache/hadoop/hbase/HBaseTestingUtility.getConfiguration:()Lorg/apache/hadoop/conf/Configuration;
      71: ldc           #24                 // String dfs.client.block.recovery.retries
      73: iconst_1
      74: invokevirtual #19                 // Method org/apache/hadoop/conf/Configuration.setInt:(Ljava/lang/String;I)V
      77: getstatic     #15                 // Field TEST_UTIL:Lorg/apache/hadoop/hbase/HBaseTestingUtility;
      80: invokevirtual #16                 // Method org/apache/hadoop/hbase/HBaseTestingUtility.getConfiguration:()Lorg/apache/hadoop/conf/Configuration;
      83: ldc           #25                 // String hbase.ipc.client.connection.maxidletime
      85: sipush        500
      88: invokevirtual #19                 // Method org/apache/hadoop/conf/Configuration.setInt:(Ljava/lang/String;I)V
      91: getstatic     #15                 // Field TEST_UTIL:Lorg/apache/hadoop/hbase/HBaseTestingUtility;
      94: iconst_3
      95: invokevirtual #26                 // Method org/apache/hadoop/hbase/HBaseTestingUtility.startMiniDFSCluster:(I)Lorg/apache/hadoop/hdfs/MiniDFSCluster;
      98: pop
      99: getstatic     #15                 // Field TEST_UTIL:Lorg/apache/hadoop/hbase/HBaseTestingUtility;
     102: invokevirtual #27                 // Method org/apache/hadoop/hbase/HBaseTestingUtility.createRootDir:()Lorg/apache/hadoop/fs/Path;
     105: pop
     106: getstatic     #15                 // Field TEST_UTIL:Lorg/apache/hadoop/hbase/HBaseTestingUtility;
     109: invokevirtual #16                 // Method org/apache/hadoop/hbase/HBaseTestingUtility.getConfiguration:()Lorg/apache/hadoop/conf/Configuration;
     112: putstatic     #28                 // Field conf:Lorg/apache/hadoop/conf/Configuration;
     115: getstatic     #15                 // Field TEST_UTIL:Lorg/apache/hadoop/hbase/HBaseTestingUtility;
     118: invokevirtual #29                 // Method org/apache/hadoop/hbase/HBaseTestingUtility.getDFSCluster:()Lorg/apache/hadoop/hdfs/MiniDFSCluster;
     121: invokevirtual #30                 // Method org/apache/hadoop/hdfs/MiniDFSCluster.getFileSystem:()Lorg/apache/hadoop/hdfs/DistributedFileSystem;
     124: putstatic     #8                  // Field fs:Lorg/apache/hadoop/fs/FileSystem;
     127: return

  public static void tearDownAfterClass() throws java.lang.Exception;
    Code:
       0: getstatic     #15                 // Field TEST_UTIL:Lorg/apache/hadoop/hbase/HBaseTestingUtility;
       3: invokevirtual #31                 // Method org/apache/hadoop/hbase/HBaseTestingUtility.shutdownMiniCluster:()V
       6: return

  static java.lang.String getName();
    Code:
       0: ldc           #32                 // String TestDefaultWALProvider
       2: areturn

  public void testGetServerNameFromWALDirectoryName() throws java.io.IOException;
    Code:
       0: ldc           #33                 // String hn
       2: sipush        450
       5: ldc2_w        #34                 // long 1398l
       8: invokestatic  #36                 // Method org/apache/hadoop/hbase/ServerName.valueOf:(Ljava/lang/String;IJ)Lorg/apache/hadoop/hbase/ServerName;
      11: astore_1
      12: new           #37                 // class java/lang/StringBuilder
      15: dup
      16: invokespecial #38                 // Method java/lang/StringBuilder."<init>":()V
      19: getstatic     #28                 // Field conf:Lorg/apache/hadoop/conf/Configuration;
      22: invokestatic  #39                 // Method org/apache/hadoop/hbase/util/FSUtils.getRootDir:(Lorg/apache/hadoop/conf/Configuration;)Lorg/apache/hadoop/fs/Path;
      25: invokevirtual #40                 // Method java/lang/StringBuilder.append:(Ljava/lang/Object;)Ljava/lang/StringBuilder;
      28: ldc           #10                 // String /
      30: invokevirtual #41                 // Method java/lang/StringBuilder.append:(Ljava/lang/String;)Ljava/lang/StringBuilder;
      33: aload_1
      34: invokevirtual #42                 // Method org/apache/hadoop/hbase/ServerName.toString:()Ljava/lang/String;
      37: invokestatic  #43                 // Method org/apache/hadoop/hbase/wal/AbstractFSWALProvider.getWALDirectoryName:(Ljava/lang/String;)Ljava/lang/String;
      40: invokevirtual #41                 // Method java/lang/StringBuilder.append:(Ljava/lang/String;)Ljava/lang/StringBuilder;
      43: invokevirtual #44                 // Method java/lang/StringBuilder.toString:()Ljava/lang/String;
      46: astore_2
      47: getstatic     #28                 // Field conf:Lorg/apache/hadoop/conf/Configuration;
      50: aconst_null
      51: invokestatic  #45                 // Method org/apache/hadoop/hbase/wal/AbstractFSWALProvider.getServerNameFromWALDirectoryName:(Lorg/apache/hadoop/conf/Configuration;Ljava/lang/String;)Lorg/apache/hadoop/hbase/ServerName;
      54: invokestatic  #46                 // Method org/junit/Assert.assertNull:(Ljava/lang/Object;)V
      57: getstatic     #28                 // Field conf:Lorg/apache/hadoop/conf/Configuration;
      60: getstatic     #28                 // Field conf:Lorg/apache/hadoop/conf/Configuration;
      63: invokestatic  #39                 // Method org/apache/hadoop/hbase/util/FSUtils.getRootDir:(Lorg/apache/hadoop/conf/Configuration;)Lorg/apache/hadoop/fs/Path;
      66: invokevirtual #47                 // Method org/apache/hadoop/fs/Path.toUri:()Ljava/net/URI;
      69: invokevirtual #48                 // Method java/net/URI.toString:()Ljava/lang/String;
      72: invokestatic  #45                 // Method org/apache/hadoop/hbase/wal/AbstractFSWALProvider.getServerNameFromWALDirectoryName:(Lorg/apache/hadoop/conf/Configuration;Ljava/lang/String;)Lorg/apache/hadoop/hbase/ServerName;
      75: invokestatic  #46                 // Method org/junit/Assert.assertNull:(Ljava/lang/Object;)V
      78: getstatic     #28                 // Field conf:Lorg/apache/hadoop/conf/Configuration;
      81: ldc           #49                 // String
      83: invokestatic  #45                 // Method org/apache/hadoop/hbase/wal/AbstractFSWALProvider.getServerNameFromWALDirectoryName:(Lorg/apache/hadoop/conf/Configuration;Ljava/lang/String;)Lorg/apache/hadoop/hbase/ServerName;
      86: invokestatic  #46                 // Method org/junit/Assert.assertNull:(Ljava/lang/Object;)V
      89: getstatic     #28                 // Field conf:Lorg/apache/hadoop/conf/Configuration;
      92: ldc           #50                 // String
      94: invokestatic  #45                 // Method org/apache/hadoop/hbase/wal/AbstractFSWALProvider.getServerNameFromWALDirectoryName:(Lorg/apache/hadoop/conf/Configuration;Ljava/lang/String;)Lorg/apache/hadoop/hbase/ServerName;
      97: invokestatic  #46                 // Method org/junit/Assert.assertNull:(Ljava/lang/Object;)V
     100: getstatic     #28                 // Field conf:Lorg/apache/hadoop/conf/Configuration;
     103: aload_2
     104: invokestatic  #45                 // Method org/apache/hadoop/hbase/wal/AbstractFSWALProvider.getServerNameFromWALDirectoryName:(Lorg/apache/hadoop/conf/Configuration;Ljava/lang/String;)Lorg/apache/hadoop/hbase/ServerName;
     107: invokestatic  #46                 // Method org/junit/Assert.assertNull:(Ljava/lang/Object;)V
     110: getstatic     #28                 // Field conf:Lorg/apache/hadoop/conf/Configuration;
     113: new           #37                 // class java/lang/StringBuilder
     116: dup
     117: invokespecial #38                 // Method java/lang/StringBuilder."<init>":()V
     120: aload_2
     121: invokevirtual #41                 // Method java/lang/StringBuilder.append:(Ljava/lang/String;)Ljava/lang/StringBuilder;
     124: ldc           #51                 // String qdf
     126: invokevirtual #41                 // Method java/lang/StringBuilder.append:(Ljava/lang/String;)Ljava/lang/StringBuilder;
     129: invokevirtual #44                 // Method java/lang/StringBuilder.toString:()Ljava/lang/String;
     132: invokestatic  #45                 // Method org/apache/hadoop/hbase/wal/AbstractFSWALProvider.getServerNameFromWALDirectoryName:(Lorg/apache/hadoop/conf/Configuration;Ljava/lang/String;)Lorg/apache/hadoop/hbase/ServerName;
     135: invokestatic  #46                 // Method org/junit/Assert.assertNull:(Ljava/lang/Object;)V
     138: getstatic     #28                 // Field conf:Lorg/apache/hadoop/conf/Configuration;
     141: new           #37                 // class java/lang/StringBuilder
     144: dup
     145: invokespecial #38                 // Method java/lang/StringBuilder."<init>":()V
     148: ldc           #52                 // String sfqf
     150: invokevirtual #41                 // Method java/lang/StringBuilder.append:(Ljava/lang/String;)Ljava/lang/StringBuilder;
     153: aload_2
     154: invokevirtual #41                 // Method java/lang/StringBuilder.append:(Ljava/lang/String;)Ljava/lang/StringBuilder;
     157: ldc           #51                 // String qdf
     159: invokevirtual #41                 // Method java/lang/StringBuilder.append:(Ljava/lang/String;)Ljava/lang/StringBuilder;
     162: invokevirtual #44                 // Method java/lang/StringBuilder.toString:()Ljava/lang/String;
     165: invokestatic  #45                 // Method org/apache/hadoop/hbase/wal/AbstractFSWALProvider.getServerNameFromWALDirectoryName:(Lorg/apache/hadoop/conf/Configuration;Ljava/lang/String;)Lorg/apache/hadoop/hbase/ServerName;
     168: invokestatic  #46                 // Method org/junit/Assert.assertNull:(Ljava/lang/Object;)V
     171: ldc           #53                 // String /WALs/
     173: astore_3
     174: getstatic     #28                 // Field conf:Lorg/apache/hadoop/conf/Configuration;
     177: new           #37                 // class java/lang/StringBuilder
     180: dup
     181: invokespecial #38                 // Method java/lang/StringBuilder."<init>":()V
     184: getstatic     #28                 // Field conf:Lorg/apache/hadoop/conf/Configuration;
     187: invokestatic  #39                 // Method org/apache/hadoop/hbase/util/FSUtils.getRootDir:(Lorg/apache/hadoop/conf/Configuration;)Lorg/apache/hadoop/fs/Path;
     190: invokevirtual #47                 // Method org/apache/hadoop/fs/Path.toUri:()Ljava/net/URI;
     193: invokevirtual #48                 // Method java/net/URI.toString:()Ljava/lang/String;
     196: invokevirtual #41                 // Method java/lang/StringBuilder.append:(Ljava/lang/String;)Ljava/lang/StringBuilder;
     199: ldc           #53                 // String /WALs/
     201: invokevirtual #41                 // Method java/lang/StringBuilder.append:(Ljava/lang/String;)Ljava/lang/StringBuilder;
     204: aload_1
     205: invokevirtual #40                 // Method java/lang/StringBuilder.append:(Ljava/lang/Object;)Ljava/lang/StringBuilder;
     208: ldc           #54                 // String /localhost%2C32984%2C1343316388997.1343316390417
     210: invokevirtual #41                 // Method java/lang/StringBuilder.append:(Ljava/lang/String;)Ljava/lang/StringBuilder;
     213: invokevirtual #44                 // Method java/lang/StringBuilder.toString:()Ljava/lang/String;
     216: invokestatic  #45                 // Method org/apache/hadoop/hbase/wal/AbstractFSWALProvider.getServerNameFromWALDirectoryName:(Lorg/apache/hadoop/conf/Configuration;Ljava/lang/String;)Lorg/apache/hadoop/hbase/ServerName;
     219: astore        4
     221: ldc           #55                 // String standard
     223: aload_1
     224: aload         4
     226: invokestatic  #56                 // Method org/junit/Assert.assertEquals:(Ljava/lang/String;Ljava/lang/Object;Ljava/lang/Object;)V
     229: getstatic     #28                 // Field conf:Lorg/apache/hadoop/conf/Configuration;
     232: new           #37                 // class java/lang/StringBuilder
     235: dup
     236: invokespecial #38                 // Method java/lang/StringBuilder."<init>":()V
     239: aload_2
     240: invokevirtual #41                 // Method java/lang/StringBuilder.append:(Ljava/lang/String;)Ljava/lang/StringBuilder;
     243: ldc           #57                 // String /qdf
     245: invokevirtual #41                 // Method java/lang/StringBuilder.append:(Ljava/lang/String;)Ljava/lang/StringBuilder;
     248: invokevirtual #44                 // Method java/lang/StringBuilder.toString:()Ljava/lang/String;
     251: invokestatic  #45                 // Method org/apache/hadoop/hbase/wal/AbstractFSWALProvider.getServerNameFromWALDirectoryName:(Lorg/apache/hadoop/conf/Configuration;Ljava/lang/String;)Lorg/apache/hadoop/hbase/ServerName;
     254: astore        4
     256: ldc           #58                 // String subdir
     258: aload_1
     259: aload         4
     261: invokestatic  #56                 // Method org/junit/Assert.assertEquals:(Ljava/lang/String;Ljava/lang/Object;Ljava/lang/Object;)V
     264: getstatic     #28                 // Field conf:Lorg/apache/hadoop/conf/Configuration;
     267: new           #37                 // class java/lang/StringBuilder
     270: dup
     271: invokespecial #38                 // Method java/lang/StringBuilder."<init>":()V
     274: getstatic     #28                 // Field conf:Lorg/apache/hadoop/conf/Configuration;
     277: invokestatic  #39                 // Method org/apache/hadoop/hbase/util/FSUtils.getRootDir:(Lorg/apache/hadoop/conf/Configuration;)Lorg/apache/hadoop/fs/Path;
     280: invokevirtual #47                 // Method org/apache/hadoop/fs/Path.toUri:()Ljava/net/URI;
     283: invokevirtual #48                 // Method java/net/URI.toString:()Ljava/lang/String;
     286: invokevirtual #41                 // Method java/lang/StringBuilder.append:(Ljava/lang/String;)Ljava/lang/StringBuilder;
     289: ldc           #53                 // String /WALs/
     291: invokevirtual #41                 // Method java/lang/StringBuilder.append:(Ljava/lang/String;)Ljava/lang/StringBuilder;
     294: aload_1
     295: invokevirtual #40                 // Method java/lang/StringBuilder.append:(Ljava/lang/Object;)Ljava/lang/StringBuilder;
     298: ldc           #59                 // String -splitting/localhost%3A57020.1340474893931
     300: invokevirtual #41                 // Method java/lang/StringBuilder.append:(Ljava/lang/String;)Ljava/lang/StringBuilder;
     303: invokevirtual #44                 // Method java/lang/StringBuilder.toString:()Ljava/lang/String;
     306: invokestatic  #45                 // Method org/apache/hadoop/hbase/wal/AbstractFSWALProvider.getServerNameFromWALDirectoryName:(Lorg/apache/hadoop/conf/Configuration;Ljava/lang/String;)Lorg/apache/hadoop/hbase/ServerName;
     309: astore        4
     311: ldc           #60                 // String split
     313: aload_1
     314: aload         4
     316: invokestatic  #56                 // Method org/junit/Assert.assertEquals:(Ljava/lang/String;Ljava/lang/Object;Ljava/lang/Object;)V
     319: return

  org.apache.hadoop.hbase.wal.WALKeyImpl getWalKey(byte[], org.apache.hadoop.hbase.TableName, long, java.util.NavigableMap<byte[], java.lang.Integer>);
    Code:
       0: new           #74                 // class org/apache/hadoop/hbase/wal/WALKeyImpl
       3: dup
       4: aload_1
       5: aload_2
       6: lload_3
       7: aload_0
       8: getfield      #7                  // Field mvcc:Lorg/apache/hadoop/hbase/regionserver/MultiVersionConcurrencyControl;
      11: aload         5
      13: invokespecial #75                 // Method org/apache/hadoop/hbase/wal/WALKeyImpl."<init>":([BLorg/apache/hadoop/hbase/TableName;JLorg/apache/hadoop/hbase/regionserver/MultiVersionConcurrencyControl;Ljava/util/NavigableMap;)V
      16: areturn

  protected void flushRegion(org.apache.hadoop.hbase.wal.WAL, byte[], java.util.Set<byte[]>);
    Code:
       0: aload_1
       1: aload_2
       2: aload_3
       3: invokeinterface #76,  3           // InterfaceMethod org/apache/hadoop/hbase/wal/WAL.startCacheFlush:([BLjava/util/Set;)Ljava/lang/Long;
       8: pop
       9: aload_1
      10: aload_2
      11: invokeinterface #77,  2           // InterfaceMethod org/apache/hadoop/hbase/wal/WAL.completeCacheFlush:([B)V
      16: return

  public void testLogCleaning() throws java.lang.Exception;
    Code:
       0: getstatic     #78                 // Field LOG:Lorg/slf4j/Logger;
       3: aload_0
       4: getfield      #4                  // Field currentTest:Lorg/junit/rules/TestName;
       7: invokevirtual #79                 // Method org/junit/rules/TestName.getMethodName:()Ljava/lang/String;
      10: invokeinterface #80,  2           // InterfaceMethod org/slf4j/Logger.info:(Ljava/lang/String;)V
      15: aload_0
      16: getfield      #4                  // Field currentTest:Lorg/junit/rules/TestName;
      19: invokevirtual #79                 // Method org/junit/rules/TestName.getMethodName:()Ljava/lang/String;
      22: invokestatic  #81                 // Method org/apache/hadoop/hbase/TableName.valueOf:(Ljava/lang/String;)Lorg/apache/hadoop/hbase/TableName;
      25: invokestatic  #82                 // Method org/apache/hadoop/hbase/client/TableDescriptorBuilder.newBuilder:(Lorg/apache/hadoop/hbase/TableName;)Lorg/apache/hadoop/hbase/client/TableDescriptorBuilder;
      28: ldc           #61                 // String row
      30: invokestatic  #83                 // Method org/apache/hadoop/hbase/client/ColumnFamilyDescriptorBuilder.of:(Ljava/lang/String;)Lorg/apache/hadoop/hbase/client/ColumnFamilyDescriptor;
      33: invokevirtual #84                 // Method org/apache/hadoop/hbase/client/TableDescriptorBuilder.setColumnFamily:(Lorg/apache/hadoop/hbase/client/ColumnFamilyDescriptor;)Lorg/apache/hadoop/hbase/client/TableDescriptorBuilder;
      36: invokevirtual #85                 // Method org/apache/hadoop/hbase/client/TableDescriptorBuilder.build:()Lorg/apache/hadoop/hbase/client/TableDescriptor;
      39: astore_1
      40: new           #37                 // class java/lang/StringBuilder
      43: dup
      44: invokespecial #38                 // Method java/lang/StringBuilder."<init>":()V
      47: aload_0
      48: getfield      #4                  // Field currentTest:Lorg/junit/rules/TestName;
      51: invokevirtual #79                 // Method org/junit/rules/TestName.getMethodName:()Ljava/lang/String;
      54: invokevirtual #41                 // Method java/lang/StringBuilder.append:(Ljava/lang/String;)Ljava/lang/StringBuilder;
      57: ldc           #86                 // String 2
      59: invokevirtual #41                 // Method java/lang/StringBuilder.append:(Ljava/lang/String;)Ljava/lang/StringBuilder;
      62: invokevirtual #44                 // Method java/lang/StringBuilder.toString:()Ljava/lang/String;
      65: invokestatic  #81                 // Method org/apache/hadoop/hbase/TableName.valueOf:(Ljava/lang/String;)Lorg/apache/hadoop/hbase/TableName;
      68: invokestatic  #82                 // Method org/apache/hadoop/hbase/client/TableDescriptorBuilder.newBuilder:(Lorg/apache/hadoop/hbase/TableName;)Lorg/apache/hadoop/hbase/client/TableDescriptorBuilder;
      71: ldc           #61                 // String row
      73: invokestatic  #83                 // Method org/apache/hadoop/hbase/client/ColumnFamilyDescriptorBuilder.of:(Ljava/lang/String;)Lorg/apache/hadoop/hbase/client/ColumnFamilyDescriptor;
      76: invokevirtual #84                 // Method org/apache/hadoop/hbase/client/TableDescriptorBuilder.setColumnFamily:(Lorg/apache/hadoop/hbase/client/ColumnFamilyDescriptor;)Lorg/apache/hadoop/hbase/client/TableDescriptorBuilder;
      79: invokevirtual #85                 // Method org/apache/hadoop/hbase/client/TableDescriptorBuilder.build:()Lorg/apache/hadoop/hbase/client/TableDescriptor;
      82: astore_2
      83: new           #87                 // class java/util/TreeMap
      86: dup
      87: getstatic     #88                 // Field org/apache/hadoop/hbase/util/Bytes.BYTES_COMPARATOR:Ljava/util/Comparator;
      90: invokespecial #89                 // Method java/util/TreeMap."<init>":(Ljava/util/Comparator;)V
      93: astore_3
      94: aload_1
      95: invokeinterface #90,  1           // InterfaceMethod org/apache/hadoop/hbase/client/TableDescriptor.getColumnFamilyNames:()Ljava/util/Set;
     100: invokeinterface #91,  1           // InterfaceMethod java/util/Set.iterator:()Ljava/util/Iterator;
     105: astore        4
     107: aload         4
     109: invokeinterface #92,  1           // InterfaceMethod java/util/Iterator.hasNext:()Z
     114: ifeq          145
     117: aload         4
     119: invokeinterface #93,  1           // InterfaceMethod java/util/Iterator.next:()Ljava/lang/Object;
     124: checkcast     #94                 // class "[B"
     127: astore        5
     129: aload_3
     130: aload         5
     132: iconst_0
     133: invokestatic  #95                 // Method java/lang/Integer.valueOf:(I)Ljava/lang/Integer;
     136: invokeinterface #96,  3           // InterfaceMethod java/util/NavigableMap.put:(Ljava/lang/Object;Ljava/lang/Object;)Ljava/lang/Object;
     141: pop
     142: goto          107
     145: new           #87                 // class java/util/TreeMap
     148: dup
     149: getstatic     #88                 // Field org/apache/hadoop/hbase/util/Bytes.BYTES_COMPARATOR:Ljava/util/Comparator;
     152: invokespecial #89                 // Method java/util/TreeMap."<init>":(Ljava/util/Comparator;)V
     155: astore        4
     157: aload_2
     158: invokeinterface #90,  1           // InterfaceMethod org/apache/hadoop/hbase/client/TableDescriptor.getColumnFamilyNames:()Ljava/util/Set;
     163: invokeinterface #91,  1           // InterfaceMethod java/util/Set.iterator:()Ljava/util/Iterator;
     168: astore        5
     170: aload         5
     172: invokeinterface #92,  1           // InterfaceMethod java/util/Iterator.hasNext:()Z
     177: ifeq          209
     180: aload         5
     182: invokeinterface #93,  1           // InterfaceMethod java/util/Iterator.next:()Ljava/lang/Object;
     187: checkcast     #94                 // class "[B"
     190: astore        6
     192: aload         4
     194: aload         6
     196: iconst_0
     197: invokestatic  #95                 // Method java/lang/Integer.valueOf:(I)Ljava/lang/Integer;
     200: invokeinterface #96,  3           // InterfaceMethod java/util/NavigableMap.put:(Ljava/lang/Object;Ljava/lang/Object;)Ljava/lang/Object;
     205: pop
     206: goto          170
     209: new           #97                 // class org/apache/hadoop/conf/Configuration
     212: dup
     213: getstatic     #28                 // Field conf:Lorg/apache/hadoop/conf/Configuration;
     216: invokespecial #98                 // Method org/apache/hadoop/conf/Configuration."<init>":(Lorg/apache/hadoop/conf/Configuration;)V
     219: astore        5
     221: aload         5
     223: ldc           #100                // String hbase.wal.provider
     225: ldc           #101                // class org/apache/hadoop/hbase/wal/FSHLogProvider
     227: invokevirtual #102                // Method java/lang/Class.getName:()Ljava/lang/String;
     230: invokevirtual #103                // Method org/apache/hadoop/conf/Configuration.set:(Ljava/lang/String;Ljava/lang/String;)V
     233: new           #99                 // class org/apache/hadoop/hbase/wal/WALFactory
     236: dup
     237: aload         5
     239: aload_0
     240: getfield      #4                  // Field currentTest:Lorg/junit/rules/TestName;
     243: invokevirtual #79                 // Method org/junit/rules/TestName.getMethodName:()Ljava/lang/String;
     246: invokespecial #104                // Method org/apache/hadoop/hbase/wal/WALFactory."<init>":(Lorg/apache/hadoop/conf/Configuration;Ljava/lang/String;)V
     249: astore        6
     251: aload_1
     252: invokeinterface #70,  1           // InterfaceMethod org/apache/hadoop/hbase/client/TableDescriptor.getTableName:()Lorg/apache/hadoop/hbase/TableName;
     257: invokestatic  #105                // Method org/apache/hadoop/hbase/client/RegionInfoBuilder.newBuilder:(Lorg/apache/hadoop/hbase/TableName;)Lorg/apache/hadoop/hbase/client/RegionInfoBuilder;
     260: invokevirtual #106                // Method org/apache/hadoop/hbase/client/RegionInfoBuilder.build:()Lorg/apache/hadoop/hbase/client/RegionInfo;
     263: astore        7
     265: aload_2
     266: invokeinterface #70,  1           // InterfaceMethod org/apache/hadoop/hbase/client/TableDescriptor.getTableName:()Lorg/apache/hadoop/hbase/TableName;
     271: invokestatic  #105                // Method org/apache/hadoop/hbase/client/RegionInfoBuilder.newBuilder:(Lorg/apache/hadoop/hbase/TableName;)Lorg/apache/hadoop/hbase/client/RegionInfoBuilder;
     274: invokevirtual #106                // Method org/apache/hadoop/hbase/client/RegionInfoBuilder.build:()Lorg/apache/hadoop/hbase/client/RegionInfo;
     277: astore        8
     279: aload         6
     281: aconst_null
     282: invokevirtual #107                // Method org/apache/hadoop/hbase/wal/WALFactory.getWAL:(Lorg/apache/hadoop/hbase/client/RegionInfo;)Lorg/apache/hadoop/hbase/wal/WAL;
     285: astore        9
     287: aload_0
     288: aload         9
     290: aload         7
     292: aload_1
     293: iconst_1
     294: aload_3
     295: invokespecial #108                // Method addEdits:(Lorg/apache/hadoop/hbase/wal/WAL;Lorg/apache/hadoop/hbase/client/RegionInfo;Lorg/apache/hadoop/hbase/client/TableDescriptor;ILjava/util/NavigableMap;)V
     298: aload         9
     300: invokeinterface #109,  1          // InterfaceMethod org/apache/hadoop/hbase/wal/WAL.rollWriter:()[[B
     305: pop
     306: lconst_1
     307: aload         9
     309: invokestatic  #110                // Method org/apache/hadoop/hbase/wal/AbstractFSWALProvider.getNumRolledLogFiles:(Lorg/apache/hadoop/hbase/wal/WAL;)I
     312: i2l
     313: invokestatic  #111                // Method org/junit/Assert.assertEquals:(JJ)V
     316: aload_0
     317: aload         9
     319: aload         7
     321: aload_1
     322: iconst_2
     323: aload_3
     324: invokespecial #108                // Method addEdits:(Lorg/apache/hadoop/hbase/wal/WAL;Lorg/apache/hadoop/hbase/client/RegionInfo;Lorg/apache/hadoop/hbase/client/TableDescriptor;ILjava/util/NavigableMap;)V
     327: aload         9
     329: invokeinterface #109,  1          // InterfaceMethod org/apache/hadoop/hbase/wal/WAL.rollWriter:()[[B
     334: pop
     335: ldc2_w        #112                // long 2l
     338: aload         9
     340: invokestatic  #114                // Method org/apache/hadoop/hbase/wal/FSHLogProvider.getNumRolledLogFiles:(Lorg/apache/hadoop/hbase/wal/WAL;)I
     343: i2l
     344: invokestatic  #111                // Method org/junit/Assert.assertEquals:(JJ)V
     347: aload_0
     348: aload         9
     350: aload         7
     352: aload_1
     353: iconst_1
     354: aload_3
     355: invokespecial #108                // Method addEdits:(Lorg/apache/hadoop/hbase/wal/WAL;Lorg/apache/hadoop/hbase/client/RegionInfo;Lorg/apache/hadoop/hbase/client/TableDescriptor;ILjava/util/NavigableMap;)V
     358: aload_0
     359: aload         9
     361: aload         8
     363: aload_2
     364: iconst_1
     365: aload         4
     367: invokespecial #108                // Method addEdits:(Lorg/apache/hadoop/hbase/wal/WAL;Lorg/apache/hadoop/hbase/client/RegionInfo;Lorg/apache/hadoop/hbase/client/TableDescriptor;ILjava/util/NavigableMap;)V
     370: aload_0
     371: aload         9
     373: aload         7
     375: aload_1
     376: iconst_1
     377: aload_3
     378: invokespecial #108                // Method addEdits:(Lorg/apache/hadoop/hbase/wal/WAL;Lorg/apache/hadoop/hbase/client/RegionInfo;Lorg/apache/hadoop/hbase/client/TableDescriptor;ILjava/util/NavigableMap;)V
     381: aload_0
     382: aload         9
     384: aload         8
     386: aload_2
     387: iconst_1
     388: aload         4
     390: invokespecial #108                // Method addEdits:(Lorg/apache/hadoop/hbase/wal/WAL;Lorg/apache/hadoop/hbase/client/RegionInfo;Lorg/apache/hadoop/hbase/client/TableDescriptor;ILjava/util/NavigableMap;)V
     393: aload         9
     395: invokeinterface #109,  1          // InterfaceMethod org/apache/hadoop/hbase/wal/WAL.rollWriter:()[[B
     400: pop
     401: ldc2_w        #115                // long 3l
     404: aload         9
     406: invokestatic  #110                // Method org/apache/hadoop/hbase/wal/AbstractFSWALProvider.getNumRolledLogFiles:(Lorg/apache/hadoop/hbase/wal/WAL;)I
     409: i2l
     410: invokestatic  #111                // Method org/junit/Assert.assertEquals:(JJ)V
     413: aload_0
     414: aload         9
     416: aload         8
     418: aload_2
     419: iconst_1
     420: aload         4
     422: invokespecial #108                // Method addEdits:(Lorg/apache/hadoop/hbase/wal/WAL;Lorg/apache/hadoop/hbase/client/RegionInfo;Lorg/apache/hadoop/hbase/client/TableDescriptor;ILjava/util/NavigableMap;)V
     425: aload         9
     427: aload         7
     429: invokeinterface #69,  1           // InterfaceMethod org/apache/hadoop/hbase/client/RegionInfo.getEncodedNameAsBytes:()[B
     434: aload_1
     435: invokeinterface #90,  1           // InterfaceMethod org/apache/hadoop/hbase/client/TableDescriptor.getColumnFamilyNames:()Ljava/util/Set;
     440: invokeinterface #76,  3           // InterfaceMethod org/apache/hadoop/hbase/wal/WAL.startCacheFlush:([BLjava/util/Set;)Ljava/lang/Long;
     445: pop
     446: aload         9
     448: aload         7
     450: invokeinterface #69,  1           // InterfaceMethod org/apache/hadoop/hbase/client/RegionInfo.getEncodedNameAsBytes:()[B
     455: invokeinterface #77,  2           // InterfaceMethod org/apache/hadoop/hbase/wal/WAL.completeCacheFlush:([B)V
     460: aload         9
     462: invokeinterface #109,  1          // InterfaceMethod org/apache/hadoop/hbase/wal/WAL.rollWriter:()[[B
     467: pop
     468: aload         9
     470: invokestatic  #110                // Method org/apache/hadoop/hbase/wal/AbstractFSWALProvider.getNumRolledLogFiles:(Lorg/apache/hadoop/hbase/wal/WAL;)I
     473: istore        10
     475: ldc2_w        #112                // long 2l
     478: iload         10
     480: i2l
     481: invokestatic  #111                // Method org/junit/Assert.assertEquals:(JJ)V
     484: aload_0
     485: aload         9
     487: aload         8
     489: aload_2
     490: iconst_1
     491: aload         4
     493: invokespecial #108                // Method addEdits:(Lorg/apache/hadoop/hbase/wal/WAL;Lorg/apache/hadoop/hbase/client/RegionInfo;Lorg/apache/hadoop/hbase/client/TableDescriptor;ILjava/util/NavigableMap;)V
     496: aload         9
     498: aload         8
     500: invokeinterface #69,  1           // InterfaceMethod org/apache/hadoop/hbase/client/RegionInfo.getEncodedNameAsBytes:()[B
     505: aload_2
     506: invokeinterface #90,  1           // InterfaceMethod org/apache/hadoop/hbase/client/TableDescriptor.getColumnFamilyNames:()Ljava/util/Set;
     511: invokeinterface #76,  3           // InterfaceMethod org/apache/hadoop/hbase/wal/WAL.startCacheFlush:([BLjava/util/Set;)Ljava/lang/Long;
     516: pop
     517: aload         9
     519: aload         8
     521: invokeinterface #69,  1           // InterfaceMethod org/apache/hadoop/hbase/client/RegionInfo.getEncodedNameAsBytes:()[B
     526: invokeinterface #77,  2           // InterfaceMethod org/apache/hadoop/hbase/wal/WAL.completeCacheFlush:([B)V
     531: aload         9
     533: invokeinterface #109,  1          // InterfaceMethod org/apache/hadoop/hbase/wal/WAL.rollWriter:()[[B
     538: pop
     539: lconst_0
     540: aload         9
     542: invokestatic  #110                // Method org/apache/hadoop/hbase/wal/AbstractFSWALProvider.getNumRolledLogFiles:(Lorg/apache/hadoop/hbase/wal/WAL;)I
     545: i2l
     546: invokestatic  #111                // Method org/junit/Assert.assertEquals:(JJ)V
     549: aload         6
     551: ifnull        577
     554: aload         6
     556: invokevirtual #117                // Method org/apache/hadoop/hbase/wal/WALFactory.close:()V
     559: goto          577
     562: astore        11
     564: aload         6
     566: ifnull        574
     569: aload         6
     571: invokevirtual #117                // Method org/apache/hadoop/hbase/wal/WALFactory.close:()V
     574: aload         11
     576: athrow
     577: return
    Exception table:
       from    to  target type
         251   549   562   any
         562   564   562   any

  public void testWALArchiving() throws java.io.IOException;
    Code:
       0: getstatic     #78                 // Field LOG:Lorg/slf4j/Logger;
       3: aload_0
       4: getfield      #4                  // Field currentTest:Lorg/junit/rules/TestName;
       7: invokevirtual #79                 // Method org/junit/rules/TestName.getMethodName:()Ljava/lang/String;
      10: invokeinterface #118,  2          // InterfaceMethod org/slf4j/Logger.debug:(Ljava/lang/String;)V
      15: new           #37                 // class java/lang/StringBuilder
      18: dup
      19: invokespecial #38                 // Method java/lang/StringBuilder."<init>":()V
      22: aload_0
      23: getfield      #4                  // Field currentTest:Lorg/junit/rules/TestName;
      26: invokevirtual #79                 // Method org/junit/rules/TestName.getMethodName:()Ljava/lang/String;
      29: invokevirtual #41                 // Method java/lang/StringBuilder.append:(Ljava/lang/String;)Ljava/lang/StringBuilder;
      32: ldc           #119                // String 1
      34: invokevirtual #41                 // Method java/lang/StringBuilder.append:(Ljava/lang/String;)Ljava/lang/StringBuilder;
      37: invokevirtual #44                 // Method java/lang/StringBuilder.toString:()Ljava/lang/String;
      40: invokestatic  #81                 // Method org/apache/hadoop/hbase/TableName.valueOf:(Ljava/lang/String;)Lorg/apache/hadoop/hbase/TableName;
      43: invokestatic  #82                 // Method org/apache/hadoop/hbase/client/TableDescriptorBuilder.newBuilder:(Lorg/apache/hadoop/hbase/TableName;)Lorg/apache/hadoop/hbase/client/TableDescriptorBuilder;
      46: ldc           #61                 // String row
      48: invokestatic  #83                 // Method org/apache/hadoop/hbase/client/ColumnFamilyDescriptorBuilder.of:(Ljava/lang/String;)Lorg/apache/hadoop/hbase/client/ColumnFamilyDescriptor;
      51: invokevirtual #84                 // Method org/apache/hadoop/hbase/client/TableDescriptorBuilder.setColumnFamily:(Lorg/apache/hadoop/hbase/client/ColumnFamilyDescriptor;)Lorg/apache/hadoop/hbase/client/TableDescriptorBuilder;
      54: invokevirtual #85                 // Method org/apache/hadoop/hbase/client/TableDescriptorBuilder.build:()Lorg/apache/hadoop/hbase/client/TableDescriptor;
      57: astore_1
      58: new           #37                 // class java/lang/StringBuilder
      61: dup
      62: invokespecial #38                 // Method java/lang/StringBuilder."<init>":()V
      65: aload_0
      66: getfield      #4                  // Field currentTest:Lorg/junit/rules/TestName;
      69: invokevirtual #79                 // Method org/junit/rules/TestName.getMethodName:()Ljava/lang/String;
      72: invokevirtual #41                 // Method java/lang/StringBuilder.append:(Ljava/lang/String;)Ljava/lang/StringBuilder;
      75: ldc           #86                 // String 2
      77: invokevirtual #41                 // Method java/lang/StringBuilder.append:(Ljava/lang/String;)Ljava/lang/StringBuilder;
      80: invokevirtual #44                 // Method java/lang/StringBuilder.toString:()Ljava/lang/String;
      83: invokestatic  #81                 // Method org/apache/hadoop/hbase/TableName.valueOf:(Ljava/lang/String;)Lorg/apache/hadoop/hbase/TableName;
      86: invokestatic  #82                 // Method org/apache/hadoop/hbase/client/TableDescriptorBuilder.newBuilder:(Lorg/apache/hadoop/hbase/TableName;)Lorg/apache/hadoop/hbase/client/TableDescriptorBuilder;
      89: ldc           #61                 // String row
      91: invokestatic  #83                 // Method org/apache/hadoop/hbase/client/ColumnFamilyDescriptorBuilder.of:(Ljava/lang/String;)Lorg/apache/hadoop/hbase/client/ColumnFamilyDescriptor;
      94: invokevirtual #84                 // Method org/apache/hadoop/hbase/client/TableDescriptorBuilder.setColumnFamily:(Lorg/apache/hadoop/hbase/client/ColumnFamilyDescriptor;)Lorg/apache/hadoop/hbase/client/TableDescriptorBuilder;
      97: invokevirtual #85                 // Method org/apache/hadoop/hbase/client/TableDescriptorBuilder.build:()Lorg/apache/hadoop/hbase/client/TableDescriptor;
     100: astore_2
     101: new           #87                 // class java/util/TreeMap
     104: dup
     105: getstatic     #88                 // Field org/apache/hadoop/hbase/util/Bytes.BYTES_COMPARATOR:Ljava/util/Comparator;
     108: invokespecial #89                 // Method java/util/TreeMap."<init>":(Ljava/util/Comparator;)V
     111: astore_3
     112: aload_1
     113: invokeinterface #90,  1           // InterfaceMethod org/apache/hadoop/hbase/client/TableDescriptor.getColumnFamilyNames:()Ljava/util/Set;
     118: invokeinterface #91,  1           // InterfaceMethod java/util/Set.iterator:()Ljava/util/Iterator;
     123: astore        4
     125: aload         4
     127: invokeinterface #92,  1           // InterfaceMethod java/util/Iterator.hasNext:()Z
     132: ifeq          163
     135: aload         4
     137: invokeinterface #93,  1           // InterfaceMethod java/util/Iterator.next:()Ljava/lang/Object;
     142: checkcast     #94                 // class "[B"
     145: astore        5
     147: aload_3
     148: aload         5
     150: iconst_0
     151: invokestatic  #95                 // Method java/lang/Integer.valueOf:(I)Ljava/lang/Integer;
     154: invokeinterface #96,  3           // InterfaceMethod java/util/NavigableMap.put:(Ljava/lang/Object;Ljava/lang/Object;)Ljava/lang/Object;
     159: pop
     160: goto          125
     163: new           #87                 // class java/util/TreeMap
     166: dup
     167: getstatic     #88                 // Field org/apache/hadoop/hbase/util/Bytes.BYTES_COMPARATOR:Ljava/util/Comparator;
     170: invokespecial #89                 // Method java/util/TreeMap."<init>":(Ljava/util/Comparator;)V
     173: astore        4
     175: aload_2
     176: invokeinterface #90,  1           // InterfaceMethod org/apache/hadoop/hbase/client/TableDescriptor.getColumnFamilyNames:()Ljava/util/Set;
     181: invokeinterface #91,  1           // InterfaceMethod java/util/Set.iterator:()Ljava/util/Iterator;
     186: astore        5
     188: aload         5
     190: invokeinterface #92,  1           // InterfaceMethod java/util/Iterator.hasNext:()Z
     195: ifeq          227
     198: aload         5
     200: invokeinterface #93,  1           // InterfaceMethod java/util/Iterator.next:()Ljava/lang/Object;
     205: checkcast     #94                 // class "[B"
     208: astore        6
     210: aload         4
     212: aload         6
     214: iconst_0
     215: invokestatic  #95                 // Method java/lang/Integer.valueOf:(I)Ljava/lang/Integer;
     218: invokeinterface #96,  3           // InterfaceMethod java/util/NavigableMap.put:(Ljava/lang/Object;Ljava/lang/Object;)Ljava/lang/Object;
     223: pop
     224: goto          188
     227: new           #97                 // class org/apache/hadoop/conf/Configuration
     230: dup
     231: getstatic     #28                 // Field conf:Lorg/apache/hadoop/conf/Configuration;
     234: invokespecial #98                 // Method org/apache/hadoop/conf/Configuration."<init>":(Lorg/apache/hadoop/conf/Configuration;)V
     237: astore        5
     239: aload         5
     241: ldc           #100                // String hbase.wal.provider
     243: ldc           #101                // class org/apache/hadoop/hbase/wal/FSHLogProvider
     245: invokevirtual #102                // Method java/lang/Class.getName:()Ljava/lang/String;
     248: invokevirtual #103                // Method org/apache/hadoop/conf/Configuration.set:(Ljava/lang/String;Ljava/lang/String;)V
     251: new           #99                 // class org/apache/hadoop/hbase/wal/WALFactory
     254: dup
     255: aload         5
     257: aload_0
     258: getfield      #4                  // Field currentTest:Lorg/junit/rules/TestName;
     261: invokevirtual #79                 // Method org/junit/rules/TestName.getMethodName:()Ljava/lang/String;
     264: invokespecial #104                // Method org/apache/hadoop/hbase/wal/WALFactory."<init>":(Lorg/apache/hadoop/conf/Configuration;Ljava/lang/String;)V
     267: astore        6
     269: aload         6
     271: aconst_null
     272: invokevirtual #107                // Method org/apache/hadoop/hbase/wal/WALFactory.getWAL:(Lorg/apache/hadoop/hbase/client/RegionInfo;)Lorg/apache/hadoop/hbase/wal/WAL;
     275: astore        7
     277: lconst_0
     278: aload         7
     280: invokestatic  #110                // Method org/apache/hadoop/hbase/wal/AbstractFSWALProvider.getNumRolledLogFiles:(Lorg/apache/hadoop/hbase/wal/WAL;)I
     283: i2l
     284: invokestatic  #111                // Method org/junit/Assert.assertEquals:(JJ)V
     287: aload_1
     288: invokeinterface #70,  1           // InterfaceMethod org/apache/hadoop/hbase/client/TableDescriptor.getTableName:()Lorg/apache/hadoop/hbase/TableName;
     293: invokestatic  #105                // Method org/apache/hadoop/hbase/client/RegionInfoBuilder.newBuilder:(Lorg/apache/hadoop/hbase/TableName;)Lorg/apache/hadoop/hbase/client/RegionInfoBuilder;
     296: invokevirtual #106                // Method org/apache/hadoop/hbase/client/RegionInfoBuilder.build:()Lorg/apache/hadoop/hbase/client/RegionInfo;
     299: astore        8
     301: aload_2
     302: invokeinterface #70,  1           // InterfaceMethod org/apache/hadoop/hbase/client/TableDescriptor.getTableName:()Lorg/apache/hadoop/hbase/TableName;
     307: invokestatic  #105                // Method org/apache/hadoop/hbase/client/RegionInfoBuilder.newBuilder:(Lorg/apache/hadoop/hbase/TableName;)Lorg/apache/hadoop/hbase/client/RegionInfoBuilder;
     310: invokevirtual #106                // Method org/apache/hadoop/hbase/client/RegionInfoBuilder.build:()Lorg/apache/hadoop/hbase/client/RegionInfo;
     313: astore        9
     315: aload_0
     316: aload         7
     318: aload         8
     320: aload_1
     321: iconst_1
     322: aload_3
     323: invokespecial #108                // Method addEdits:(Lorg/apache/hadoop/hbase/wal/WAL;Lorg/apache/hadoop/hbase/client/RegionInfo;Lorg/apache/hadoop/hbase/client/TableDescriptor;ILjava/util/NavigableMap;)V
     326: aload         7
     328: invokeinterface #109,  1          // InterfaceMethod org/apache/hadoop/hbase/wal/WAL.rollWriter:()[[B
     333: pop
     334: lconst_1
     335: aload         7
     337: invokestatic  #110                // Method org/apache/hadoop/hbase/wal/AbstractFSWALProvider.getNumRolledLogFiles:(Lorg/apache/hadoop/hbase/wal/WAL;)I
     340: i2l
     341: invokestatic  #111                // Method org/junit/Assert.assertEquals:(JJ)V
     344: aload_0
     345: aload         7
     347: aload         8
     349: aload_1
     350: iconst_1
     351: aload_3
     352: invokespecial #108                // Method addEdits:(Lorg/apache/hadoop/hbase/wal/WAL;Lorg/apache/hadoop/hbase/client/RegionInfo;Lorg/apache/hadoop/hbase/client/TableDescriptor;ILjava/util/NavigableMap;)V
     355: aload         7
     357: invokeinterface #109,  1          // InterfaceMethod org/apache/hadoop/hbase/wal/WAL.rollWriter:()[[B
     362: pop
     363: ldc2_w        #112                // long 2l
     366: aload         7
     368: invokestatic  #110                // Method org/apache/hadoop/hbase/wal/AbstractFSWALProvider.getNumRolledLogFiles:(Lorg/apache/hadoop/hbase/wal/WAL;)I
     371: i2l
     372: invokestatic  #111                // Method org/junit/Assert.assertEquals:(JJ)V
     375: aload_0
     376: aload         7
     378: aload         8
     380: aload_1
     381: iconst_3
     382: aload_3
     383: invokespecial #108                // Method addEdits:(Lorg/apache/hadoop/hbase/wal/WAL;Lorg/apache/hadoop/hbase/client/RegionInfo;Lorg/apache/hadoop/hbase/client/TableDescriptor;ILjava/util/NavigableMap;)V
     386: aload_0
     387: aload         7
     389: aload         8
     391: invokeinterface #69,  1           // InterfaceMethod org/apache/hadoop/hbase/client/RegionInfo.getEncodedNameAsBytes:()[B
     396: aload_1
     397: invokeinterface #90,  1           // InterfaceMethod org/apache/hadoop/hbase/client/TableDescriptor.getColumnFamilyNames:()Ljava/util/Set;
     402: invokevirtual #120                // Method flushRegion:(Lorg/apache/hadoop/hbase/wal/WAL;[BLjava/util/Set;)V
     405: aload         7
     407: invokeinterface #109,  1          // InterfaceMethod org/apache/hadoop/hbase/wal/WAL.rollWriter:()[[B
     412: pop
     413: lconst_0
     414: aload         7
     416: invokestatic  #110                // Method org/apache/hadoop/hbase/wal/AbstractFSWALProvider.getNumRolledLogFiles:(Lorg/apache/hadoop/hbase/wal/WAL;)I
     419: i2l
     420: invokestatic  #111                // Method org/junit/Assert.assertEquals:(JJ)V
     423: aload_0
     424: aload         7
     426: aload         9
     428: aload_2
     429: iconst_1
     430: aload         4
     432: invokespecial #108                // Method addEdits:(Lorg/apache/hadoop/hbase/wal/WAL;Lorg/apache/hadoop/hbase/client/RegionInfo;Lorg/apache/hadoop/hbase/client/TableDescriptor;ILjava/util/NavigableMap;)V
     435: aload         7
     437: invokeinterface #109,  1          // InterfaceMethod org/apache/hadoop/hbase/wal/WAL.rollWriter:()[[B
     442: pop
     443: lconst_1
     444: aload         7
     446: invokestatic  #110                // Method org/apache/hadoop/hbase/wal/AbstractFSWALProvider.getNumRolledLogFiles:(Lorg/apache/hadoop/hbase/wal/WAL;)I
     449: i2l
     450: invokestatic  #111                // Method org/junit/Assert.assertEquals:(JJ)V
     453: aload_0
     454: aload         7
     456: aload         8
     458: aload_1
     459: iconst_2
     460: aload_3
     461: invokespecial #108                // Method addEdits:(Lorg/apache/hadoop/hbase/wal/WAL;Lorg/apache/hadoop/hbase/client/RegionInfo;Lorg/apache/hadoop/hbase/client/TableDescriptor;ILjava/util/NavigableMap;)V
     464: aload         7
     466: invokeinterface #109,  1          // InterfaceMethod org/apache/hadoop/hbase/wal/WAL.rollWriter:()[[B
     471: pop
     472: ldc2_w        #112                // long 2l
     475: aload         7
     477: invokestatic  #110                // Method org/apache/hadoop/hbase/wal/AbstractFSWALProvider.getNumRolledLogFiles:(Lorg/apache/hadoop/hbase/wal/WAL;)I
     480: i2l
     481: invokestatic  #111                // Method org/junit/Assert.assertEquals:(JJ)V
     484: aload_0
     485: aload         7
     487: aload         9
     489: aload_2
     490: iconst_2
     491: aload         4
     493: invokespecial #108                // Method addEdits:(Lorg/apache/hadoop/hbase/wal/WAL;Lorg/apache/hadoop/hbase/client/RegionInfo;Lorg/apache/hadoop/hbase/client/TableDescriptor;ILjava/util/NavigableMap;)V
     496: aload_0
     497: aload         7
     499: aload         8
     501: invokeinterface #69,  1           // InterfaceMethod org/apache/hadoop/hbase/client/RegionInfo.getEncodedNameAsBytes:()[B
     506: aload_2
     507: invokeinterface #90,  1           // InterfaceMethod org/apache/hadoop/hbase/client/TableDescriptor.getColumnFamilyNames:()Ljava/util/Set;
     512: invokevirtual #120                // Method flushRegion:(Lorg/apache/hadoop/hbase/wal/WAL;[BLjava/util/Set;)V
     515: aload         7
     517: invokeinterface #109,  1          // InterfaceMethod org/apache/hadoop/hbase/wal/WAL.rollWriter:()[[B
     522: pop
     523: ldc2_w        #112                // long 2l
     526: aload         7
     528: invokestatic  #110                // Method org/apache/hadoop/hbase/wal/AbstractFSWALProvider.getNumRolledLogFiles:(Lorg/apache/hadoop/hbase/wal/WAL;)I
     531: i2l
     532: invokestatic  #111                // Method org/junit/Assert.assertEquals:(JJ)V
     535: aload_0
     536: aload         7
     538: aload         9
     540: aload_2
     541: iconst_2
     542: aload         4
     544: invokespecial #108                // Method addEdits:(Lorg/apache/hadoop/hbase/wal/WAL;Lorg/apache/hadoop/hbase/client/RegionInfo;Lorg/apache/hadoop/hbase/client/TableDescriptor;ILjava/util/NavigableMap;)V
     547: aload_0
     548: aload         7
     550: aload         9
     552: invokeinterface #69,  1           // InterfaceMethod org/apache/hadoop/hbase/client/RegionInfo.getEncodedNameAsBytes:()[B
     557: aload_2
     558: invokeinterface #90,  1           // InterfaceMethod org/apache/hadoop/hbase/client/TableDescriptor.getColumnFamilyNames:()Ljava/util/Set;
     563: invokevirtual #120                // Method flushRegion:(Lorg/apache/hadoop/hbase/wal/WAL;[BLjava/util/Set;)V
     566: aload         7
     568: invokeinterface #109,  1          // InterfaceMethod org/apache/hadoop/hbase/wal/WAL.rollWriter:()[[B
     573: pop
     574: lconst_0
     575: aload         7
     577: invokestatic  #110                // Method org/apache/hadoop/hbase/wal/AbstractFSWALProvider.getNumRolledLogFiles:(Lorg/apache/hadoop/hbase/wal/WAL;)I
     580: i2l
     581: invokestatic  #111                // Method org/junit/Assert.assertEquals:(JJ)V
     584: aload         6
     586: ifnull        612
     589: aload         6
     591: invokevirtual #117                // Method org/apache/hadoop/hbase/wal/WALFactory.close:()V
     594: goto          612
     597: astore        10
     599: aload         6
     601: ifnull        609
     604: aload         6
     606: invokevirtual #117                // Method org/apache/hadoop/hbase/wal/WALFactory.close:()V
     609: aload         10
     611: athrow
     612: return
    Exception table:
       from    to  target type
         269   584   597   any
         597   599   597   any

  public void testConcurrentWrites() throws java.lang.Exception;
    Code:
       0: new           #97                 // class org/apache/hadoop/conf/Configuration
       3: dup
       4: getstatic     #15                 // Field TEST_UTIL:Lorg/apache/hadoop/hbase/HBaseTestingUtility;
       7: invokevirtual #16                 // Method org/apache/hadoop/hbase/HBaseTestingUtility.getConfiguration:()Lorg/apache/hadoop/conf/Configuration;
      10: invokespecial #98                 // Method org/apache/hadoop/conf/Configuration."<init>":(Lorg/apache/hadoop/conf/Configuration;)V
      13: bipush        6
      15: anewarray     #121                // class java/lang/String
      18: dup
      19: iconst_0
      20: ldc           #122                // String -threads
      22: aastore
      23: dup
      24: iconst_1
      25: ldc           #123                // String 3
      27: aastore
      28: dup
      29: iconst_2
      30: ldc           #124                // String -verify
      32: aastore
      33: dup
      34: iconst_3
      35: ldc           #125                // String -noclosefs
      37: aastore
      38: dup
      39: iconst_4
      40: ldc           #126                // String -iterations
      42: aastore
      43: dup
      44: iconst_5
      45: ldc           #127                // String 3000
      47: aastore
      48: invokestatic  #128                // Method org/apache/hadoop/hbase/wal/WALPerformanceEvaluation.innerMain:(Lorg/apache/hadoop/conf/Configuration;[Ljava/lang/String;)I
      51: istore_1
      52: lconst_0
      53: iload_1
      54: i2l
      55: invokestatic  #111                // Method org/junit/Assert.assertEquals:(JJ)V
      58: return

  public void setMembershipDedups() throws java.io.IOException;
    Code:
       0: new           #97                 // class org/apache/hadoop/conf/Configuration
       3: dup
       4: getstatic     #28                 // Field conf:Lorg/apache/hadoop/conf/Configuration;
       7: invokespecial #98                 // Method org/apache/hadoop/conf/Configuration."<init>":(Lorg/apache/hadoop/conf/Configuration;)V
      10: astore_1
      11: aload_1
      12: ldc           #100                // String hbase.wal.provider
      14: ldc           #101                // class org/apache/hadoop/hbase/wal/FSHLogProvider
      16: invokevirtual #102                // Method java/lang/Class.getName:()Ljava/lang/String;
      19: invokevirtual #103                // Method org/apache/hadoop/conf/Configuration.set:(Ljava/lang/String;Ljava/lang/String;)V
      22: new           #99                 // class org/apache/hadoop/hbase/wal/WALFactory
      25: dup
      26: aload_1
      27: aload_0
      28: getfield      #4                  // Field currentTest:Lorg/junit/rules/TestName;
      31: invokevirtual #79                 // Method org/junit/rules/TestName.getMethodName:()Ljava/lang/String;
      34: invokespecial #104                // Method org/apache/hadoop/hbase/wal/WALFactory."<init>":(Lorg/apache/hadoop/conf/Configuration;Ljava/lang/String;)V
      37: astore_2
      38: new           #129                // class java/util/HashSet
      41: dup
      42: iconst_1
      43: invokespecial #130                // Method java/util/HashSet."<init>":(I)V
      46: astore_3
      47: ldc           #131                // String first attempt to add WAL from default provider should work.
      49: aload_3
      50: aload_2
      51: aconst_null
      52: invokevirtual #107                // Method org/apache/hadoop/hbase/wal/WALFactory.getWAL:(Lorg/apache/hadoop/hbase/client/RegionInfo;)Lorg/apache/hadoop/hbase/wal/WAL;
      55: invokeinterface #132,  2          // InterfaceMethod java/util/Set.add:(Ljava/lang/Object;)Z
      60: invokestatic  #133                // Method org/junit/Assert.assertTrue:(Ljava/lang/String;Z)V
      63: iconst_0
      64: istore        4
      66: iload         4
      68: sipush        1000
      71: if_icmpge     128
      74: ldc           #134                // String default wal provider is only supposed to return a single wal, which should compare as .equals itself.
      76: aload_3
      77: aload_2
      78: new           #37                 // class java/lang/StringBuilder
      81: dup
      82: invokespecial #38                 // Method java/lang/StringBuilder."<init>":()V
      85: ldc           #135                // String Table-
      87: invokevirtual #41                 // Method java/lang/StringBuilder.append:(Ljava/lang/String;)Ljava/lang/StringBuilder;
      90: invokestatic  #136                // Method java/util/concurrent/ThreadLocalRandom.current:()Ljava/util/concurrent/ThreadLocalRandom;
      93: invokevirtual #137                // Method java/util/concurrent/ThreadLocalRandom.nextInt:()I
      96: invokevirtual #138                // Method java/lang/StringBuilder.append:(I)Ljava/lang/StringBuilder;
      99: invokevirtual #44                 // Method java/lang/StringBuilder.toString:()Ljava/lang/String;
     102: invokestatic  #81                 // Method org/apache/hadoop/hbase/TableName.valueOf:(Ljava/lang/String;)Lorg/apache/hadoop/hbase/TableName;
     105: invokestatic  #105                // Method org/apache/hadoop/hbase/client/RegionInfoBuilder.newBuilder:(Lorg/apache/hadoop/hbase/TableName;)Lorg/apache/hadoop/hbase/client/RegionInfoBuilder;
     108: invokevirtual #106                // Method org/apache/hadoop/hbase/client/RegionInfoBuilder.build:()Lorg/apache/hadoop/hbase/client/RegionInfo;
     111: invokevirtual #107                // Method org/apache/hadoop/hbase/wal/WALFactory.getWAL:(Lorg/apache/hadoop/hbase/client/RegionInfo;)Lorg/apache/hadoop/hbase/wal/WAL;
     114: invokeinterface #132,  2          // InterfaceMethod java/util/Set.add:(Ljava/lang/Object;)Z
     119: invokestatic  #139                // Method org/junit/Assert.assertFalse:(Ljava/lang/String;Z)V
     122: iinc          4, 1
     125: goto          66
     128: aload_2
     129: invokevirtual #117                // Method org/apache/hadoop/hbase/wal/WALFactory.close:()V
     132: goto          144
     135: astore        5
     137: aload_2
     138: invokevirtual #117                // Method org/apache/hadoop/hbase/wal/WALFactory.close:()V
     141: aload         5
     143: athrow
     144: return
    Exception table:
       from    to  target type
          38   128   135   any
         135   137   135   any

  static {};
    Code:
       0: ldc           #140                // class org/apache/hadoop/hbase/wal/TestFSHLogProvider
       2: invokestatic  #141                // Method org/apache/hadoop/hbase/HBaseClassTestRule.forClass:(Ljava/lang/Class;)Lorg/apache/hadoop/hbase/HBaseClassTestRule;
       5: putstatic     #142                // Field CLASS_RULE:Lorg/apache/hadoop/hbase/HBaseClassTestRule;
       8: ldc           #140                // class org/apache/hadoop/hbase/wal/TestFSHLogProvider
      10: invokestatic  #143                // Method org/slf4j/LoggerFactory.getLogger:(Ljava/lang/Class;)Lorg/slf4j/Logger;
      13: putstatic     #78                 // Field LOG:Lorg/slf4j/Logger;
      16: new           #144                // class org/apache/hadoop/hbase/HBaseTestingUtility
      19: dup
      20: invokespecial #145                // Method org/apache/hadoop/hbase/HBaseTestingUtility."<init>":()V
      23: putstatic     #15                 // Field TEST_UTIL:Lorg/apache/hadoop/hbase/HBaseTestingUtility;
      26: return
}
