Compiled from "TestCoreMasterCoprocessor.java"
public class org.apache.hadoop.hbase.coprocessor.TestCoreMasterCoprocessor {
  public static final org.apache.hadoop.hbase.HBaseClassTestRule CLASS_RULE;

  public org.junit.rules.TestName name;

  public org.apache.hadoop.hbase.coprocessor.TestCoreMasterCoprocessor();
    Code:
       0: aload_0
       1: invokespecial #1                  // Method java/lang/Object."<init>":()V
       4: aload_0
       5: new           #2                  // class org/junit/rules/TestName
       8: dup
       9: invokespecial #3                  // Method org/junit/rules/TestName."<init>":()V
      12: putfield      #4                  // Field name:Lorg/junit/rules/TestName;
      15: return

  public void before() throws java.io.IOException;
    Code:
       0: aload_0
       1: getfield      #4                  // Field name:Lorg/junit/rules/TestName;
       4: invokevirtual #5                  // Method org/junit/rules/TestName.getMethodName:()Ljava/lang/String;
       7: astore_1
       8: aload_0
       9: new           #6                  // class org/apache/hadoop/hbase/master/assignment/MockMasterServices
      12: dup
      13: getstatic     #7                  // Field HTU:Lorg/apache/hadoop/hbase/HBaseTestingUtility;
      16: invokevirtual #8                  // Method org/apache/hadoop/hbase/HBaseTestingUtility.getConfiguration:()Lorg/apache/hadoop/conf/Configuration;
      19: aconst_null
      20: invokespecial #9                  // Method org/apache/hadoop/hbase/master/assignment/MockMasterServices."<init>":(Lorg/apache/hadoop/conf/Configuration;Ljava/util/NavigableMap;)V
      23: putfield      #10                 // Field ms:Lorg/apache/hadoop/hbase/master/MasterServices;
      26: aload_0
      27: new           #11                 // class org/apache/hadoop/hbase/master/MasterCoprocessorHost
      30: dup
      31: aload_0
      32: getfield      #10                 // Field ms:Lorg/apache/hadoop/hbase/master/MasterServices;
      35: getstatic     #7                  // Field HTU:Lorg/apache/hadoop/hbase/HBaseTestingUtility;
      38: invokevirtual #8                  // Method org/apache/hadoop/hbase/HBaseTestingUtility.getConfiguration:()Lorg/apache/hadoop/conf/Configuration;
      41: invokespecial #12                 // Method org/apache/hadoop/hbase/master/MasterCoprocessorHost."<init>":(Lorg/apache/hadoop/hbase/master/MasterServices;Lorg/apache/hadoop/conf/Configuration;)V
      44: putfield      #13                 // Field mch:Lorg/apache/hadoop/hbase/master/MasterCoprocessorHost;
      47: aload_0
      48: getfield      #13                 // Field mch:Lorg/apache/hadoop/hbase/master/MasterCoprocessorHost;
      51: invokevirtual #14                 // Method org/apache/hadoop/hbase/master/MasterCoprocessorHost.preMasterInitialization:()V
      54: return

  public void after() throws java.io.IOException;
    Code:
       0: aload_0
       1: getfield      #13                 // Field mch:Lorg/apache/hadoop/hbase/master/MasterCoprocessorHost;
       4: invokevirtual #15                 // Method org/apache/hadoop/hbase/master/MasterCoprocessorHost.preStopMaster:()V
       7: return

  public void testCoreRegionCoprocessor() throws java.io.IOException;
    Code:
       0: aload_0
       1: getfield      #13                 // Field mch:Lorg/apache/hadoop/hbase/master/MasterCoprocessorHost;
       4: aconst_null
       5: ldc           #16                 // class org/apache/hadoop/hbase/coprocessor/TestCoreMasterCoprocessor$NotCoreMasterCoprocessor
       7: invokevirtual #17                 // Method java/lang/Class.getName:()Ljava/lang/String;
      10: iconst_0
      11: getstatic     #7                  // Field HTU:Lorg/apache/hadoop/hbase/HBaseTestingUtility;
      14: invokevirtual #8                  // Method org/apache/hadoop/hbase/HBaseTestingUtility.getConfiguration:()Lorg/apache/hadoop/conf/Configuration;
      17: invokevirtual #18                 // Method org/apache/hadoop/hbase/master/MasterCoprocessorHost.load:(Lorg/apache/hadoop/fs/Path;Ljava/lang/String;ILorg/apache/hadoop/conf/Configuration;)Lorg/apache/hadoop/hbase/CoprocessorEnvironment;
      20: checkcast     #19                 // class org/apache/hadoop/hbase/coprocessor/MasterCoprocessorEnvironment
      23: astore_1
      24: aload_1
      25: instanceof    #20                 // class org/apache/hadoop/hbase/coprocessor/HasMasterServices
      28: invokestatic  #21                 // Method org/junit/Assert.assertFalse:(Z)V
      31: aload_0
      32: getfield      #13                 // Field mch:Lorg/apache/hadoop/hbase/master/MasterCoprocessorHost;
      35: aconst_null
      36: ldc           #22                 // class org/apache/hadoop/hbase/coprocessor/TestCoreMasterCoprocessor$CoreMasterCoprocessor
      38: invokevirtual #17                 // Method java/lang/Class.getName:()Ljava/lang/String;
      41: iconst_1
      42: getstatic     #7                  // Field HTU:Lorg/apache/hadoop/hbase/HBaseTestingUtility;
      45: invokevirtual #8                  // Method org/apache/hadoop/hbase/HBaseTestingUtility.getConfiguration:()Lorg/apache/hadoop/conf/Configuration;
      48: invokevirtual #18                 // Method org/apache/hadoop/hbase/master/MasterCoprocessorHost.load:(Lorg/apache/hadoop/fs/Path;Ljava/lang/String;ILorg/apache/hadoop/conf/Configuration;)Lorg/apache/hadoop/hbase/CoprocessorEnvironment;
      51: checkcast     #19                 // class org/apache/hadoop/hbase/coprocessor/MasterCoprocessorEnvironment
      54: astore_1
      55: aload_1
      56: instanceof    #20                 // class org/apache/hadoop/hbase/coprocessor/HasMasterServices
      59: invokestatic  #23                 // Method org/junit/Assert.assertTrue:(Z)V
      62: aload_0
      63: getfield      #10                 // Field ms:Lorg/apache/hadoop/hbase/master/MasterServices;
      66: aload_1
      67: checkcast     #20                 // class org/apache/hadoop/hbase/coprocessor/HasMasterServices
      70: invokeinterface #24,  1           // InterfaceMethod org/apache/hadoop/hbase/coprocessor/HasMasterServices.getMasterServices:()Lorg/apache/hadoop/hbase/master/MasterServices;
      75: invokestatic  #25                 // Method org/junit/Assert.assertEquals:(Ljava/lang/Object;Ljava/lang/Object;)V
      78: return

  static {};
    Code:
       0: ldc           #26                 // class org/apache/hadoop/hbase/coprocessor/TestCoreMasterCoprocessor
       2: invokestatic  #27                 // Method org/apache/hadoop/hbase/HBaseClassTestRule.forClass:(Ljava/lang/Class;)Lorg/apache/hadoop/hbase/HBaseClassTestRule;
       5: putstatic     #28                 // Field CLASS_RULE:Lorg/apache/hadoop/hbase/HBaseClassTestRule;
       8: invokestatic  #29                 // Method org/apache/hadoop/hbase/HBaseTestingUtility.createLocalHTU:()Lorg/apache/hadoop/hbase/HBaseTestingUtility;
      11: putstatic     #7                  // Field HTU:Lorg/apache/hadoop/hbase/HBaseTestingUtility;
      14: return
}
