Compiled from "TestHMasterRPCException.java"
public class org.apache.hadoop.hbase.master.TestHMasterRPCException {
  public static final org.apache.hadoop.hbase.HBaseClassTestRule CLASS_RULE;

  public org.apache.hadoop.hbase.master.TestHMasterRPCException();
    Code:
       0: aload_0
       1: invokespecial #1                  // Method java/lang/Object."<init>":()V
       4: aload_0
       5: invokestatic  #2                  // Method org/apache/hadoop/hbase/HBaseTestingUtility.createLocalHTU:()Lorg/apache/hadoop/hbase/HBaseTestingUtility;
       8: putfield      #3                  // Field testUtil:Lorg/apache/hadoop/hbase/HBaseTestingUtility;
      11: return

  public void setUp() throws java.lang.Exception;
    Code:
       0: aload_0
       1: getfield      #3                  // Field testUtil:Lorg/apache/hadoop/hbase/HBaseTestingUtility;
       4: invokevirtual #4                  // Method org/apache/hadoop/hbase/HBaseTestingUtility.getConfiguration:()Lorg/apache/hadoop/conf/Configuration;
       7: astore_1
       8: aload_1
       9: ldc           #6                  // String hbase.master.port
      11: ldc           #7                  // String 0
      13: invokevirtual #8                  // Method org/apache/hadoop/conf/Configuration.set:(Ljava/lang/String;Ljava/lang/String;)V
      16: aload_1
      17: ldc           #9                  // String zookeeper.session.timeout
      19: sipush        2000
      22: invokevirtual #10                 // Method org/apache/hadoop/conf/Configuration.setInt:(Ljava/lang/String;I)V
      25: aload_0
      26: getfield      #3                  // Field testUtil:Lorg/apache/hadoop/hbase/HBaseTestingUtility;
      29: invokevirtual #11                 // Method org/apache/hadoop/hbase/HBaseTestingUtility.startMiniZKCluster:()Lorg/apache/hadoop/hbase/zookeeper/MiniZooKeeperCluster;
      32: pop
      33: aload_0
      34: getfield      #3                  // Field testUtil:Lorg/apache/hadoop/hbase/HBaseTestingUtility;
      37: invokevirtual #12                 // Method org/apache/hadoop/hbase/HBaseTestingUtility.getZooKeeperWatcher:()Lorg/apache/hadoop/hbase/zookeeper/ZKWatcher;
      40: astore_2
      41: aload_2
      42: aload_2
      43: invokevirtual #13                 // Method org/apache/hadoop/hbase/zookeeper/ZKWatcher.getZNodePaths:()Lorg/apache/hadoop/hbase/zookeeper/ZNodePaths;
      46: getfield      #14                 // Field org/apache/hadoop/hbase/zookeeper/ZNodePaths.masterAddressZNode:Ljava/lang/String;
      49: ldc           #15                 // String fake:123
      51: invokestatic  #16                 // Method org/apache/hadoop/hbase/util/Bytes.toBytes:(Ljava/lang/String;)[B
      54: invokestatic  #17                 // Method org/apache/hadoop/hbase/zookeeper/ZKUtil.createWithParents:(Lorg/apache/hadoop/hbase/zookeeper/ZKWatcher;Ljava/lang/String;[B)V
      57: aload_0
      58: new           #18                 // class org/apache/hadoop/hbase/master/HMaster
      61: dup
      62: aload_1
      63: invokespecial #19                 // Method org/apache/hadoop/hbase/master/HMaster."<init>":(Lorg/apache/hadoop/conf/Configuration;)V
      66: putfield      #20                 // Field master:Lorg/apache/hadoop/hbase/master/HMaster;
      69: aload_0
      70: aload_1
      71: ldc           #21                 // String default-cluster
      73: invokestatic  #22                 // Method org/apache/hadoop/hbase/ipc/RpcClientFactory.createClient:(Lorg/apache/hadoop/conf/Configuration;Ljava/lang/String;)Lorg/apache/hadoop/hbase/ipc/RpcClient;
      76: putfield      #23                 // Field rpcClient:Lorg/apache/hadoop/hbase/ipc/RpcClient;
      79: return

  public void tearDown() throws java.io.IOException;
    Code:
       0: aload_0
       1: getfield      #23                 // Field rpcClient:Lorg/apache/hadoop/hbase/ipc/RpcClient;
       4: ifnull        16
       7: aload_0
       8: getfield      #23                 // Field rpcClient:Lorg/apache/hadoop/hbase/ipc/RpcClient;
      11: invokeinterface #24,  1           // InterfaceMethod org/apache/hadoop/hbase/ipc/RpcClient.close:()V
      16: aload_0
      17: getfield      #20                 // Field master:Lorg/apache/hadoop/hbase/master/HMaster;
      20: ifnull        30
      23: aload_0
      24: getfield      #20                 // Field master:Lorg/apache/hadoop/hbase/master/HMaster;
      27: invokevirtual #25                 // Method org/apache/hadoop/hbase/master/HMaster.stopMaster:()V
      30: aload_0
      31: getfield      #3                  // Field testUtil:Lorg/apache/hadoop/hbase/HBaseTestingUtility;
      34: invokevirtual #26                 // Method org/apache/hadoop/hbase/HBaseTestingUtility.shutdownMiniZKCluster:()V
      37: return

  public void testRPCException() throws java.io.IOException, java.lang.InterruptedException, org.apache.zookeeper.KeeperException;
    Code:
       0: aload_0
       1: getfield      #20                 // Field master:Lorg/apache/hadoop/hbase/master/HMaster;
       4: invokevirtual #27                 // Method org/apache/hadoop/hbase/master/HMaster.getServerName:()Lorg/apache/hadoop/hbase/ServerName;
       7: astore_1
       8: iconst_0
       9: istore_2
      10: iconst_0
      11: istore_3
      12: iload_3
      13: bipush        20
      15: if_icmpge     138
      18: aload_0
      19: getfield      #23                 // Field rpcClient:Lorg/apache/hadoop/hbase/ipc/RpcClient;
      22: aload_1
      23: invokestatic  #28                 // Method org/apache/hadoop/hbase/security/User.getCurrent:()Lorg/apache/hadoop/hbase/security/User;
      26: iconst_0
      27: invokeinterface #29,  4           // InterfaceMethod org/apache/hadoop/hbase/ipc/RpcClient.createBlockingRpcChannel:(Lorg/apache/hadoop/hbase/ServerName;Lorg/apache/hadoop/hbase/security/User;I)Lorg/apache/hbase/thirdparty/com/google/protobuf/BlockingRpcChannel;
      32: astore        4
      34: aload         4
      36: invokestatic  #30                 // Method org/apache/hadoop/hbase/shaded/protobuf/generated/MasterProtos$MasterService.newBlockingStub:(Lorg/apache/hbase/thirdparty/com/google/protobuf/BlockingRpcChannel;)Lorg/apache/hadoop/hbase/shaded/protobuf/generated/MasterProtos$MasterService$BlockingInterface;
      39: astore        5
      41: aload         5
      43: aconst_null
      44: invokestatic  #31                 // Method org/apache/hadoop/hbase/shaded/protobuf/generated/MasterProtos$IsMasterRunningRequest.getDefaultInstance:()Lorg/apache/hadoop/hbase/shaded/protobuf/generated/MasterProtos$IsMasterRunningRequest;
      47: invokeinterface #32,  3           // InterfaceMethod org/apache/hadoop/hbase/shaded/protobuf/generated/MasterProtos$MasterService$BlockingInterface.isMasterRunning:(Lorg/apache/hbase/thirdparty/com/google/protobuf/RpcController;Lorg/apache/hadoop/hbase/shaded/protobuf/generated/MasterProtos$IsMasterRunningRequest;)Lorg/apache/hadoop/hbase/shaded/protobuf/generated/MasterProtos$IsMasterRunningResponse;
      52: invokevirtual #33                 // Method org/apache/hadoop/hbase/shaded/protobuf/generated/MasterProtos$IsMasterRunningResponse.getIsMasterRunning:()Z
      55: invokestatic  #34                 // Method org/junit/Assert.assertTrue:(Z)V
      58: return
      59: astore        4
      61: aload         4
      63: invokestatic  #36                 // Method org/apache/hadoop/hbase/shaded/protobuf/ProtobufUtil.handleRemoteException:(Ljava/lang/Exception;)Ljava/io/IOException;
      66: astore        5
      68: aload         5
      70: invokevirtual #37                 // Method java/io/IOException.getMessage:()Ljava/lang/String;
      73: ldc           #38                 // String org.apache.hadoop.hbase.ipc.ServerNotRunningYetException: Server is not running yet
      75: invokevirtual #39                 // Method java/lang/String.startsWith:(Ljava/lang/String;)Z
      78: invokestatic  #34                 // Method org/junit/Assert.assertTrue:(Z)V
      81: getstatic     #40                 // Field LOG:Lorg/slf4j/Logger;
      84: ldc           #41                 // String Expected exception:
      86: aload         5
      88: invokeinterface #42,  3           // InterfaceMethod org/slf4j/Logger.info:(Ljava/lang/String;Ljava/lang/Throwable;)V
      93: iload_2
      94: ifne          126
      97: aload_0
      98: getfield      #3                  // Field testUtil:Lorg/apache/hadoop/hbase/HBaseTestingUtility;
     101: invokevirtual #12                 // Method org/apache/hadoop/hbase/HBaseTestingUtility.getZooKeeperWatcher:()Lorg/apache/hadoop/hbase/zookeeper/ZKWatcher;
     104: invokevirtual #43                 // Method org/apache/hadoop/hbase/zookeeper/ZKWatcher.getRecoverableZooKeeper:()Lorg/apache/hadoop/hbase/zookeeper/RecoverableZooKeeper;
     107: aload_0
     108: getfield      #3                  // Field testUtil:Lorg/apache/hadoop/hbase/HBaseTestingUtility;
     111: invokevirtual #12                 // Method org/apache/hadoop/hbase/HBaseTestingUtility.getZooKeeperWatcher:()Lorg/apache/hadoop/hbase/zookeeper/ZKWatcher;
     114: invokevirtual #13                 // Method org/apache/hadoop/hbase/zookeeper/ZKWatcher.getZNodePaths:()Lorg/apache/hadoop/hbase/zookeeper/ZNodePaths;
     117: getfield      #14                 // Field org/apache/hadoop/hbase/zookeeper/ZNodePaths.masterAddressZNode:Ljava/lang/String;
     120: iconst_m1
     121: invokevirtual #44                 // Method org/apache/hadoop/hbase/zookeeper/RecoverableZooKeeper.delete:(Ljava/lang/String;I)V
     124: iconst_1
     125: istore_2
     126: ldc2_w        #45                 // long 1000l
     129: invokestatic  #47                 // Method java/lang/Thread.sleep:(J)V
     132: iinc          3, 1
     135: goto          12
     138: return
    Exception table:
       from    to  target type
          18    58    59   Class org/apache/hbase/thirdparty/com/google/protobuf/ServiceException

  static {};
    Code:
       0: ldc           #48                 // class org/apache/hadoop/hbase/master/TestHMasterRPCException
       2: invokestatic  #49                 // Method org/apache/hadoop/hbase/HBaseClassTestRule.forClass:(Ljava/lang/Class;)Lorg/apache/hadoop/hbase/HBaseClassTestRule;
       5: putstatic     #50                 // Field CLASS_RULE:Lorg/apache/hadoop/hbase/HBaseClassTestRule;
       8: ldc           #48                 // class org/apache/hadoop/hbase/master/TestHMasterRPCException
      10: invokestatic  #51                 // Method org/slf4j/LoggerFactory.getLogger:(Ljava/lang/Class;)Lorg/slf4j/Logger;
      13: putstatic     #40                 // Field LOG:Lorg/slf4j/Logger;
      16: return
}
