Compiled from "TestImmutableBytesWritable.java"
public class org.apache.hadoop.hbase.io.TestImmutableBytesWritable extends junit.framework.TestCase {
  public static final org.apache.hadoop.hbase.HBaseClassTestRule CLASS_RULE;

  public org.apache.hadoop.hbase.io.TestImmutableBytesWritable();
    Code:
       0: aload_0
       1: invokespecial #1                  // Method junit/framework/TestCase."<init>":()V
       4: return

  public void testHash() throws java.lang.Exception;
    Code:
       0: new           #2                  // class org/apache/hadoop/hbase/io/ImmutableBytesWritable
       3: dup
       4: ldc           #3                  // String xxabc
       6: invokestatic  #4                  // Method org/apache/hadoop/hbase/util/Bytes.toBytes:(Ljava/lang/String;)[B
       9: iconst_2
      10: iconst_3
      11: invokespecial #5                  // Method org/apache/hadoop/hbase/io/ImmutableBytesWritable."<init>":([BII)V
      14: invokevirtual #6                  // Method org/apache/hadoop/hbase/io/ImmutableBytesWritable.hashCode:()I
      17: new           #2                  // class org/apache/hadoop/hbase/io/ImmutableBytesWritable
      20: dup
      21: ldc           #7                  // String abc
      23: invokestatic  #4                  // Method org/apache/hadoop/hbase/util/Bytes.toBytes:(Ljava/lang/String;)[B
      26: invokespecial #8                  // Method org/apache/hadoop/hbase/io/ImmutableBytesWritable."<init>":([B)V
      29: invokevirtual #6                  // Method org/apache/hadoop/hbase/io/ImmutableBytesWritable.hashCode:()I
      32: invokestatic  #9                  // Method assertEquals:(II)V
      35: new           #2                  // class org/apache/hadoop/hbase/io/ImmutableBytesWritable
      38: dup
      39: ldc           #10                 // String xxabcd
      41: invokestatic  #4                  // Method org/apache/hadoop/hbase/util/Bytes.toBytes:(Ljava/lang/String;)[B
      44: iconst_2
      45: iconst_3
      46: invokespecial #5                  // Method org/apache/hadoop/hbase/io/ImmutableBytesWritable."<init>":([BII)V
      49: invokevirtual #6                  // Method org/apache/hadoop/hbase/io/ImmutableBytesWritable.hashCode:()I
      52: new           #2                  // class org/apache/hadoop/hbase/io/ImmutableBytesWritable
      55: dup
      56: ldc           #7                  // String abc
      58: invokestatic  #4                  // Method org/apache/hadoop/hbase/util/Bytes.toBytes:(Ljava/lang/String;)[B
      61: invokespecial #8                  // Method org/apache/hadoop/hbase/io/ImmutableBytesWritable."<init>":([B)V
      64: invokevirtual #6                  // Method org/apache/hadoop/hbase/io/ImmutableBytesWritable.hashCode:()I
      67: invokestatic  #9                  // Method assertEquals:(II)V
      70: new           #2                  // class org/apache/hadoop/hbase/io/ImmutableBytesWritable
      73: dup
      74: ldc           #3                  // String xxabc
      76: invokestatic  #4                  // Method org/apache/hadoop/hbase/util/Bytes.toBytes:(Ljava/lang/String;)[B
      79: iconst_2
      80: iconst_3
      81: invokespecial #5                  // Method org/apache/hadoop/hbase/io/ImmutableBytesWritable."<init>":([BII)V
      84: invokevirtual #6                  // Method org/apache/hadoop/hbase/io/ImmutableBytesWritable.hashCode:()I
      87: invokestatic  #11                 // Method java/lang/Integer.valueOf:(I)Ljava/lang/Integer;
      90: new           #2                  // class org/apache/hadoop/hbase/io/ImmutableBytesWritable
      93: dup
      94: ldc           #3                  // String xxabc
      96: invokestatic  #4                  // Method org/apache/hadoop/hbase/util/Bytes.toBytes:(Ljava/lang/String;)[B
      99: iconst_2
     100: iconst_2
     101: invokespecial #5                  // Method org/apache/hadoop/hbase/io/ImmutableBytesWritable."<init>":([BII)V
     104: invokevirtual #6                  // Method org/apache/hadoop/hbase/io/ImmutableBytesWritable.hashCode:()I
     107: invokestatic  #11                 // Method java/lang/Integer.valueOf:(I)Ljava/lang/Integer;
     110: invokestatic  #12                 // Method assertNotSame:(Ljava/lang/Object;Ljava/lang/Object;)V
     113: return

  public void testSpecificCompare();
    Code:
       0: new           #2                  // class org/apache/hadoop/hbase/io/ImmutableBytesWritable
       3: dup
       4: iconst_1
       5: newarray       byte
       7: dup
       8: iconst_0
       9: bipush        15
      11: bastore
      12: invokespecial #8                  // Method org/apache/hadoop/hbase/io/ImmutableBytesWritable."<init>":([B)V
      15: astore_1
      16: new           #2                  // class org/apache/hadoop/hbase/io/ImmutableBytesWritable
      19: dup
      20: iconst_2
      21: newarray       byte
      23: dup
      24: iconst_0
      25: iconst_0
      26: bastore
      27: dup
      28: iconst_1
      29: iconst_0
      30: bastore
      31: invokespecial #8                  // Method org/apache/hadoop/hbase/io/ImmutableBytesWritable."<init>":([B)V
      34: astore_2
      35: new           #13                 // class org/apache/hadoop/hbase/io/ImmutableBytesWritable$Comparator
      38: dup
      39: invokespecial #14                 // Method org/apache/hadoop/hbase/io/ImmutableBytesWritable$Comparator."<init>":()V
      42: astore_3
      43: ldc           #15                 // String ibw1 < ibw2
      45: aload_3
      46: aload_1
      47: aload_2
      48: invokevirtual #16                 // Method org/apache/hadoop/hbase/io/ImmutableBytesWritable$Comparator.compare:(Lorg/apache/hadoop/io/WritableComparable;Lorg/apache/hadoop/io/WritableComparable;)I
      51: ifge          58
      54: iconst_1
      55: goto          59
      58: iconst_0
      59: invokestatic  #17                 // Method assertFalse:(Ljava/lang/String;Z)V
      62: return

  public void testComparison() throws java.lang.Exception;
    Code:
       0: aload_0
       1: ldc           #18                 // String aa
       3: ldc           #19                 // String b
       5: iconst_m1
       6: invokespecial #20                 // Method runTests:(Ljava/lang/String;Ljava/lang/String;I)V
       9: aload_0
      10: ldc           #18                 // String aa
      12: ldc           #18                 // String aa
      14: iconst_0
      15: invokespecial #20                 // Method runTests:(Ljava/lang/String;Ljava/lang/String;I)V
      18: aload_0
      19: ldc           #18                 // String aa
      21: ldc           #21                 // String ab
      23: iconst_m1
      24: invokespecial #20                 // Method runTests:(Ljava/lang/String;Ljava/lang/String;I)V
      27: aload_0
      28: ldc           #18                 // String aa
      30: ldc           #22                 // String aaa
      32: iconst_m1
      33: invokespecial #20                 // Method runTests:(Ljava/lang/String;Ljava/lang/String;I)V
      36: aload_0
      37: ldc           #23                 // String
      39: ldc           #23                 // String
      41: iconst_0
      42: invokespecial #20                 // Method runTests:(Ljava/lang/String;Ljava/lang/String;I)V
      45: aload_0
      46: ldc           #23                 // String
      48: ldc           #24                 // String a
      50: iconst_m1
      51: invokespecial #20                 // Method runTests:(Ljava/lang/String;Ljava/lang/String;I)V
      54: return

  static {};
    Code:
       0: ldc           #52                 // class org/apache/hadoop/hbase/io/TestImmutableBytesWritable
       2: invokestatic  #53                 // Method org/apache/hadoop/hbase/HBaseClassTestRule.forClass:(Ljava/lang/Class;)Lorg/apache/hadoop/hbase/HBaseClassTestRule;
       5: putstatic     #54                 // Field CLASS_RULE:Lorg/apache/hadoop/hbase/HBaseClassTestRule;
       8: return
}
