Compiled from "TestReplicaWithCluster.java"
public class org.apache.hadoop.hbase.client.TestReplicaWithCluster$SlowMeCopro implements org.apache.hadoop.hbase.coprocessor.RegionCoprocessor,org.apache.hadoop.hbase.coprocessor.RegionObserver {
  static final java.util.concurrent.atomic.AtomicLong sleepTime;

  static final java.util.concurrent.atomic.AtomicReference<java.util.concurrent.CountDownLatch> cdl;

  public org.apache.hadoop.hbase.client.TestReplicaWithCluster$SlowMeCopro();
    Code:
       0: aload_0
       1: invokespecial #1                  // Method java/lang/Object."<init>":()V
       4: return

  public java.util.Optional<org.apache.hadoop.hbase.coprocessor.RegionObserver> getRegionObserver();
    Code:
       0: aload_0
       1: invokestatic  #2                  // Method java/util/Optional.of:(Ljava/lang/Object;)Ljava/util/Optional;
       4: areturn

  public void preGetOp(org.apache.hadoop.hbase.coprocessor.ObserverContext<org.apache.hadoop.hbase.coprocessor.RegionCoprocessorEnvironment>, org.apache.hadoop.hbase.client.Get, java.util.List<org.apache.hadoop.hbase.Cell>) throws java.io.IOException;
    Code:
       0: aload_1
       1: invokeinterface #3,  1            // InterfaceMethod org/apache/hadoop/hbase/coprocessor/ObserverContext.getEnvironment:()Lorg/apache/hadoop/hbase/CoprocessorEnvironment;
       6: checkcast     #4                  // class org/apache/hadoop/hbase/coprocessor/RegionCoprocessorEnvironment
       9: invokeinterface #5,  1            // InterfaceMethod org/apache/hadoop/hbase/coprocessor/RegionCoprocessorEnvironment.getRegion:()Lorg/apache/hadoop/hbase/regionserver/Region;
      14: invokeinterface #6,  1            // InterfaceMethod org/apache/hadoop/hbase/regionserver/Region.getRegionInfo:()Lorg/apache/hadoop/hbase/client/RegionInfo;
      19: invokeinterface #7,  1            // InterfaceMethod org/apache/hadoop/hbase/client/RegionInfo.getReplicaId:()I
      24: ifne          173
      27: getstatic     #8                  // Field cdl:Ljava/util/concurrent/atomic/AtomicReference;
      30: invokevirtual #9                  // Method java/util/concurrent/atomic/AtomicReference.get:()Ljava/lang/Object;
      33: checkcast     #10                 // class java/util/concurrent/CountDownLatch
      36: astore        4
      38: getstatic     #11                 // Field sleepTime:Ljava/util/concurrent/atomic/AtomicLong;
      41: invokevirtual #12                 // Method java/util/concurrent/atomic/AtomicLong.get:()J
      44: lconst_0
      45: lcmp
      46: ifle          98
      49: invokestatic  #13                 // Method org/apache/hadoop/hbase/client/TestReplicaWithCluster.access$000:()Lorg/slf4j/Logger;
      52: new           #14                 // class java/lang/StringBuilder
      55: dup
      56: invokespecial #15                 // Method java/lang/StringBuilder."<init>":()V
      59: ldc           #16                 // String Sleeping for
      61: invokevirtual #17                 // Method java/lang/StringBuilder.append:(Ljava/lang/String;)Ljava/lang/StringBuilder;
      64: getstatic     #11                 // Field sleepTime:Ljava/util/concurrent/atomic/AtomicLong;
      67: invokevirtual #12                 // Method java/util/concurrent/atomic/AtomicLong.get:()J
      70: invokevirtual #18                 // Method java/lang/StringBuilder.append:(J)Ljava/lang/StringBuilder;
      73: ldc           #19                 // String  ms
      75: invokevirtual #17                 // Method java/lang/StringBuilder.append:(Ljava/lang/String;)Ljava/lang/StringBuilder;
      78: invokevirtual #20                 // Method java/lang/StringBuilder.toString:()Ljava/lang/String;
      81: invokeinterface #21,  2           // InterfaceMethod org/slf4j/Logger.info:(Ljava/lang/String;)V
      86: getstatic     #11                 // Field sleepTime:Ljava/util/concurrent/atomic/AtomicLong;
      89: invokevirtual #12                 // Method java/util/concurrent/atomic/AtomicLong.get:()J
      92: invokestatic  #22                 // Method java/lang/Thread.sleep:(J)V
      95: goto          150
      98: aload         4
     100: invokevirtual #23                 // Method java/util/concurrent/CountDownLatch.getCount:()J
     103: lconst_0
     104: lcmp
     105: ifle          150
     108: invokestatic  #13                 // Method org/apache/hadoop/hbase/client/TestReplicaWithCluster.access$000:()Lorg/slf4j/Logger;
     111: ldc           #24                 // String Waiting for the counterCountDownLatch
     113: invokeinterface #21,  2           // InterfaceMethod org/slf4j/Logger.info:(Ljava/lang/String;)V
     118: aload         4
     120: ldc2_w        #25                 // long 2l
     123: getstatic     #27                 // Field java/util/concurrent/TimeUnit.MINUTES:Ljava/util/concurrent/TimeUnit;
     126: invokevirtual #28                 // Method java/util/concurrent/CountDownLatch.await:(JLjava/util/concurrent/TimeUnit;)Z
     129: pop
     130: aload         4
     132: invokevirtual #23                 // Method java/util/concurrent/CountDownLatch.getCount:()J
     135: lconst_0
     136: lcmp
     137: ifle          150
     140: new           #29                 // class java/lang/RuntimeException
     143: dup
     144: ldc           #30                 // String Can't wait more
     146: invokespecial #31                 // Method java/lang/RuntimeException."<init>":(Ljava/lang/String;)V
     149: athrow
     150: goto          170
     153: astore        5
     155: invokestatic  #13                 // Method org/apache/hadoop/hbase/client/TestReplicaWithCluster.access$000:()Lorg/slf4j/Logger;
     158: aload         5
     160: invokevirtual #33                 // Method java/lang/InterruptedException.toString:()Ljava/lang/String;
     163: aload         5
     165: invokeinterface #34,  3           // InterfaceMethod org/slf4j/Logger.error:(Ljava/lang/String;Ljava/lang/Throwable;)V
     170: goto          183
     173: invokestatic  #13                 // Method org/apache/hadoop/hbase/client/TestReplicaWithCluster.access$000:()Lorg/slf4j/Logger;
     176: ldc           #35                 // String We're not the primary replicas.
     178: invokeinterface #21,  2           // InterfaceMethod org/slf4j/Logger.info:(Ljava/lang/String;)V
     183: return
    Exception table:
       from    to  target type
          38   150   153   Class java/lang/InterruptedException

  static {};
    Code:
       0: new           #36                 // class java/util/concurrent/atomic/AtomicLong
       3: dup
       4: lconst_0
       5: invokespecial #37                 // Method java/util/concurrent/atomic/AtomicLong."<init>":(J)V
       8: putstatic     #11                 // Field sleepTime:Ljava/util/concurrent/atomic/AtomicLong;
      11: new           #38                 // class java/util/concurrent/atomic/AtomicReference
      14: dup
      15: new           #10                 // class java/util/concurrent/CountDownLatch
      18: dup
      19: iconst_0
      20: invokespecial #39                 // Method java/util/concurrent/CountDownLatch."<init>":(I)V
      23: invokespecial #40                 // Method java/util/concurrent/atomic/AtomicReference."<init>":(Ljava/lang/Object;)V
      26: putstatic     #8                  // Field cdl:Ljava/util/concurrent/atomic/AtomicReference;
      29: return
}
