Compiled from "TestCompactor.java"
public class org.apache.hadoop.hbase.regionserver.compactions.TestCompactor$Scanner implements org.apache.hadoop.hbase.regionserver.InternalScanner {
  public org.apache.hadoop.hbase.regionserver.compactions.TestCompactor$Scanner(org.apache.hadoop.hbase.KeyValue...);
    Code:
       0: aload_0
       1: invokespecial #1                  // Method java/lang/Object."<init>":()V
       4: aload_0
       5: new           #2                  // class java/util/ArrayList
       8: dup
       9: aload_1
      10: invokestatic  #3                  // Method java/util/Arrays.asList:([Ljava/lang/Object;)Ljava/util/List;
      13: invokespecial #4                  // Method java/util/ArrayList."<init>":(Ljava/util/Collection;)V
      16: putfield      #5                  // Field kvs:Ljava/util/ArrayList;
      19: return

  public boolean next(java.util.List<org.apache.hadoop.hbase.Cell>, org.apache.hadoop.hbase.regionserver.ScannerContext) throws java.io.IOException;
    Code:
       0: aload_0
       1: getfield      #5                  // Field kvs:Ljava/util/ArrayList;
       4: invokevirtual #6                  // Method java/util/ArrayList.isEmpty:()Z
       7: ifeq          12
      10: iconst_0
      11: ireturn
      12: aload_1
      13: aload_0
      14: getfield      #5                  // Field kvs:Ljava/util/ArrayList;
      17: iconst_0
      18: invokevirtual #7                  // Method java/util/ArrayList.remove:(I)Ljava/lang/Object;
      21: invokeinterface #8,  2            // InterfaceMethod java/util/List.add:(Ljava/lang/Object;)Z
      26: pop
      27: aload_0
      28: getfield      #5                  // Field kvs:Ljava/util/ArrayList;
      31: invokevirtual #6                  // Method java/util/ArrayList.isEmpty:()Z
      34: ifne          41
      37: iconst_1
      38: goto          42
      41: iconst_0
      42: ireturn

  public void close() throws java.io.IOException;
    Code:
       0: return
}
