Compiled from "TestFifoRpcScheduler.java"
public class org.apache.hadoop.hbase.ipc.TestFifoRpcScheduler {
  public static final org.apache.hadoop.hbase.HBaseClassTestRule CLASS_RULE;

  public org.apache.hadoop.hbase.ipc.TestFifoRpcScheduler();
    Code:
       0: aload_0
       1: invokespecial #2                  // Method java/lang/Object."<init>":()V
       4: aload_0
       5: new           #3                  // class org/apache/hadoop/hbase/ipc/TestFifoRpcScheduler$1
       8: dup
       9: aload_0
      10: invokespecial #4                  // Method org/apache/hadoop/hbase/ipc/TestFifoRpcScheduler$1."<init>":(Lorg/apache/hadoop/hbase/ipc/TestFifoRpcScheduler;)V
      13: putfield      #5                  // Field CONTEXT:Lorg/apache/hadoop/hbase/ipc/RpcScheduler$Context;
      16: return

  public void setUp();
    Code:
       0: aload_0
       1: invokestatic  #6                  // Method org/apache/hadoop/hbase/HBaseConfiguration.create:()Lorg/apache/hadoop/conf/Configuration;
       4: putfield      #7                  // Field conf:Lorg/apache/hadoop/conf/Configuration;
       7: aload_0
       8: new           #8                  // class java/util/concurrent/atomic/AtomicInteger
      11: dup
      12: iconst_0
      13: invokespecial #9                  // Method java/util/concurrent/atomic/AtomicInteger."<init>":(I)V
      16: putfield      #1                  // Field callExecutionCount:Ljava/util/concurrent/atomic/AtomicInteger;
      19: return

  public void testCallQueueInfo() throws java.io.IOException, java.lang.InterruptedException;
    Code:
       0: new           #38                 // class org/apache/hadoop/hbase/ipc/FifoRpcScheduler
       3: dup
       4: aload_0
       5: getfield      #7                  // Field conf:Lorg/apache/hadoop/conf/Configuration;
       8: iconst_1
       9: invokespecial #39                 // Method org/apache/hadoop/hbase/ipc/FifoRpcScheduler."<init>":(Lorg/apache/hadoop/conf/Configuration;I)V
      12: astore_2
      13: aload_2
      14: aload_0
      15: getfield      #5                  // Field CONTEXT:Lorg/apache/hadoop/hbase/ipc/RpcScheduler$Context;
      18: invokevirtual #40                 // Method org/apache/hadoop/hbase/ipc/RpcScheduler.init:(Lorg/apache/hadoop/hbase/ipc/RpcScheduler$Context;)V
      21: aload_0
      22: aload_2
      23: invokespecial #41                 // Method disableHandlers:(Lorg/apache/hadoop/hbase/ipc/RpcScheduler;)Ljava/util/concurrent/ThreadPoolExecutor;
      26: pop
      27: bipush        30
      29: istore_3
      30: iconst_0
      31: istore        4
      33: iload_3
      34: istore        5
      36: iload         5
      38: ifle          83
      41: aload_0
      42: invokespecial #42                 // Method createMockTask:()Lorg/apache/hadoop/hbase/ipc/CallRunner;
      45: astore        6
      47: aload         6
      49: new           #43                 // class org/apache/hadoop/hbase/monitoring/MonitoredRPCHandlerImpl
      52: dup
      53: invokespecial #44                 // Method org/apache/hadoop/hbase/monitoring/MonitoredRPCHandlerImpl."<init>":()V
      56: invokevirtual #45                 // Method org/apache/hadoop/hbase/ipc/CallRunner.setStatus:(Lorg/apache/hadoop/hbase/monitoring/MonitoredRPCHandler;)V
      59: aload_2
      60: aload         6
      62: invokevirtual #46                 // Method org/apache/hadoop/hbase/ipc/RpcScheduler.dispatch:(Lorg/apache/hadoop/hbase/ipc/CallRunner;)Z
      65: ifne          71
      68: iinc          4, 1
      71: ldc2_w        #47                 // long 10l
      74: invokestatic  #24                 // Method java/lang/Thread.sleep:(J)V
      77: iinc          5, -1
      80: goto          36
      83: aload_2
      84: invokevirtual #49                 // Method org/apache/hadoop/hbase/ipc/RpcScheduler.getCallQueueInfo:()Lorg/apache/hadoop/hbase/ipc/CallQueueInfo;
      87: astore        5
      89: aload_0
      90: getfield      #1                  // Field callExecutionCount:Ljava/util/concurrent/atomic/AtomicInteger;
      93: invokevirtual #50                 // Method java/util/concurrent/atomic/AtomicInteger.get:()I
      96: istore        6
      98: iconst_0
      99: istore        7
     101: aload         5
     103: invokevirtual #51                 // Method org/apache/hadoop/hbase/ipc/CallQueueInfo.getCallQueueNames:()Ljava/util/Set;
     106: invokeinterface #52,  1           // InterfaceMethod java/util/Set.iterator:()Ljava/util/Iterator;
     111: astore        8
     113: aload         8
     115: invokeinterface #53,  1           // InterfaceMethod java/util/Iterator.hasNext:()Z
     120: ifeq          193
     123: aload         8
     125: invokeinterface #54,  1           // InterfaceMethod java/util/Iterator.next:()Ljava/lang/Object;
     130: checkcast     #55                 // class java/lang/String
     133: astore        9
     135: aload         5
     137: aload         9
     139: invokevirtual #56                 // Method org/apache/hadoop/hbase/ipc/CallQueueInfo.getCalledMethodNames:(Ljava/lang/String;)Ljava/util/Set;
     142: invokeinterface #52,  1           // InterfaceMethod java/util/Set.iterator:()Ljava/util/Iterator;
     147: astore        10
     149: aload         10
     151: invokeinterface #53,  1           // InterfaceMethod java/util/Iterator.hasNext:()Z
     156: ifeq          190
     159: aload         10
     161: invokeinterface #54,  1           // InterfaceMethod java/util/Iterator.next:()Ljava/lang/Object;
     166: checkcast     #55                 // class java/lang/String
     169: astore        11
     171: iload         7
     173: i2l
     174: aload         5
     176: aload         9
     178: aload         11
     180: invokevirtual #57                 // Method org/apache/hadoop/hbase/ipc/CallQueueInfo.getCallMethodCount:(Ljava/lang/String;Ljava/lang/String;)J
     183: ladd
     184: l2i
     185: istore        7
     187: goto          149
     190: goto          113
     193: iload_3
     194: iload         4
     196: isub
     197: i2l
     198: iload         7
     200: iload         6
     202: iadd
     203: i2l
     204: invokestatic  #58                 // Method org/junit/Assert.assertEquals:(JJ)V
     207: aload_2
     208: invokevirtual #59                 // Method org/apache/hadoop/hbase/ipc/RpcScheduler.stop:()V
     211: return

  static java.util.concurrent.atomic.AtomicInteger access$000(org.apache.hadoop.hbase.ipc.TestFifoRpcScheduler);
    Code:
       0: aload_0
       1: getfield      #1                  // Field callExecutionCount:Ljava/util/concurrent/atomic/AtomicInteger;
       4: areturn

  static {};
    Code:
       0: ldc           #71                 // class org/apache/hadoop/hbase/ipc/TestFifoRpcScheduler
       2: invokestatic  #72                 // Method org/apache/hadoop/hbase/HBaseClassTestRule.forClass:(Ljava/lang/Class;)Lorg/apache/hadoop/hbase/HBaseClassTestRule;
       5: putstatic     #73                 // Field CLASS_RULE:Lorg/apache/hadoop/hbase/HBaseClassTestRule;
       8: ldc           #71                 // class org/apache/hadoop/hbase/ipc/TestFifoRpcScheduler
      10: invokestatic  #74                 // Method org/slf4j/LoggerFactory.getLogger:(Ljava/lang/Class;)Lorg/slf4j/Logger;
      13: putstatic     #26                 // Field LOG:Lorg/slf4j/Logger;
      16: return
}
