Compiled from "TestRegionSizeUse.java"
public class org.apache.hadoop.hbase.quotas.TestRegionSizeUse {
  public static final org.apache.hadoop.hbase.HBaseClassTestRule CLASS_RULE;

  public org.junit.rules.TestName testName;

  public org.apache.hadoop.hbase.quotas.TestRegionSizeUse();
    Code:
       0: aload_0
       1: invokespecial #1                  // Method java/lang/Object."<init>":()V
       4: aload_0
       5: new           #2                  // class org/junit/rules/TestName
       8: dup
       9: invokespecial #3                  // Method org/junit/rules/TestName."<init>":()V
      12: putfield      #4                  // Field testName:Lorg/junit/rules/TestName;
      15: return

  public void setUp() throws java.lang.Exception;
    Code:
       0: getstatic     #5                  // Field TEST_UTIL:Lorg/apache/hadoop/hbase/HBaseTestingUtility;
       3: invokevirtual #6                  // Method org/apache/hadoop/hbase/HBaseTestingUtility.getConfiguration:()Lorg/apache/hadoop/conf/Configuration;
       6: astore_1
       7: aload_1
       8: invokestatic  #7                  // Method org/apache/hadoop/hbase/quotas/SpaceQuotaHelperForTests.updateConfigForQuotas:(Lorg/apache/hadoop/conf/Configuration;)V
      11: aload_0
      12: getstatic     #5                  // Field TEST_UTIL:Lorg/apache/hadoop/hbase/HBaseTestingUtility;
      15: iconst_2
      16: invokevirtual #8                  // Method org/apache/hadoop/hbase/HBaseTestingUtility.startMiniCluster:(I)Lorg/apache/hadoop/hbase/MiniHBaseCluster;
      19: putfield      #9                  // Field cluster:Lorg/apache/hadoop/hbase/MiniHBaseCluster;
      22: return

  public void tearDown() throws java.lang.Exception;
    Code:
       0: getstatic     #5                  // Field TEST_UTIL:Lorg/apache/hadoop/hbase/HBaseTestingUtility;
       3: invokevirtual #10                 // Method org/apache/hadoop/hbase/HBaseTestingUtility.shutdownMiniCluster:()V
       6: return

  public void testBasicRegionSizeReports() throws java.lang.Exception;
    Code:
       0: ldc2_w        #11                 // long 5242880l
       3: lstore_1
       4: aload_0
       5: ldc2_w        #11                 // long 5242880l
       8: invokespecial #13                 // Method writeData:(J)Lorg/apache/hadoop/hbase/TableName;
      11: astore_3
      12: getstatic     #14                 // Field LOG:Lorg/slf4j/Logger;
      15: ldc           #15                 // String Data was written to HBase
      17: invokeinterface #16,  2           // InterfaceMethod org/slf4j/Logger.debug:(Ljava/lang/String;)V
      22: getstatic     #5                  // Field TEST_UTIL:Lorg/apache/hadoop/hbase/HBaseTestingUtility;
      25: invokevirtual #17                 // Method org/apache/hadoop/hbase/HBaseTestingUtility.getAdmin:()Lorg/apache/hadoop/hbase/client/Admin;
      28: astore        4
      30: aload         4
      32: aload_3
      33: invokeinterface #18,  2           // InterfaceMethod org/apache/hadoop/hbase/client/Admin.flush:(Lorg/apache/hadoop/hbase/TableName;)V
      38: getstatic     #14                 // Field LOG:Lorg/slf4j/Logger;
      41: ldc           #19                 // String Data flushed to disk
      43: invokeinterface #16,  2           // InterfaceMethod org/slf4j/Logger.debug:(Ljava/lang/String;)V
      48: getstatic     #5                  // Field TEST_UTIL:Lorg/apache/hadoop/hbase/HBaseTestingUtility;
      51: invokevirtual #17                 // Method org/apache/hadoop/hbase/HBaseTestingUtility.getAdmin:()Lorg/apache/hadoop/hbase/client/Admin;
      54: aload_3
      55: invokeinterface #20,  2           // InterfaceMethod org/apache/hadoop/hbase/client/Admin.getRegions:(Lorg/apache/hadoop/hbase/TableName;)Ljava/util/List;
      60: astore        5
      62: aload_0
      63: getfield      #9                  // Field cluster:Lorg/apache/hadoop/hbase/MiniHBaseCluster;
      66: invokevirtual #21                 // Method org/apache/hadoop/hbase/MiniHBaseCluster.getMaster:()Lorg/apache/hadoop/hbase/master/HMaster;
      69: astore        6
      71: aload         6
      73: invokevirtual #22                 // Method org/apache/hadoop/hbase/master/HMaster.getMasterQuotaManager:()Lorg/apache/hadoop/hbase/quotas/MasterQuotaManager;
      76: astore        7
      78: aload         7
      80: invokevirtual #23                 // Method org/apache/hadoop/hbase/quotas/MasterQuotaManager.snapshotRegionSizes:()Ljava/util/Map;
      83: astore        8
      85: aload_0
      86: aload_3
      87: aload         8
      89: invokespecial #24                 // Method numRegionsForTable:(Lorg/apache/hadoop/hbase/TableName;Ljava/util/Map;)I
      92: istore        9
      94: iload         9
      96: aload         5
      98: invokeinterface #25,  1           // InterfaceMethod java/util/List.size:()I
     103: if_icmpge     174
     106: getstatic     #14                 // Field LOG:Lorg/slf4j/Logger;
     109: new           #26                 // class java/lang/StringBuilder
     112: dup
     113: invokespecial #27                 // Method java/lang/StringBuilder."<init>":()V
     116: ldc           #28                 // String Expecting more regions. Saw
     118: invokevirtual #29                 // Method java/lang/StringBuilder.append:(Ljava/lang/String;)Ljava/lang/StringBuilder;
     121: iload         9
     123: invokevirtual #30                 // Method java/lang/StringBuilder.append:(I)Ljava/lang/StringBuilder;
     126: ldc           #31                 // String  region sizes reported, expected at least
     128: invokevirtual #29                 // Method java/lang/StringBuilder.append:(Ljava/lang/String;)Ljava/lang/StringBuilder;
     131: aload         5
     133: invokeinterface #25,  1           // InterfaceMethod java/util/List.size:()I
     138: invokevirtual #30                 // Method java/lang/StringBuilder.append:(I)Ljava/lang/StringBuilder;
     141: invokevirtual #32                 // Method java/lang/StringBuilder.toString:()Ljava/lang/String;
     144: invokeinterface #16,  2           // InterfaceMethod org/slf4j/Logger.debug:(Ljava/lang/String;)V
     149: ldc2_w        #33                 // long 1000l
     152: invokestatic  #35                 // Method java/lang/Thread.sleep:(J)V
     155: aload         7
     157: invokevirtual #23                 // Method org/apache/hadoop/hbase/quotas/MasterQuotaManager.snapshotRegionSizes:()Ljava/util/Map;
     160: astore        8
     162: aload_0
     163: aload_3
     164: aload         8
     166: invokespecial #24                 // Method numRegionsForTable:(Lorg/apache/hadoop/hbase/TableName;Ljava/util/Map;)I
     169: istore        9
     171: goto          94
     174: getstatic     #14                 // Field LOG:Lorg/slf4j/Logger;
     177: new           #26                 // class java/lang/StringBuilder
     180: dup
     181: invokespecial #27                 // Method java/lang/StringBuilder."<init>":()V
     184: ldc           #36                 // String Observed region sizes by the HMaster:
     186: invokevirtual #29                 // Method java/lang/StringBuilder.append:(Ljava/lang/String;)Ljava/lang/StringBuilder;
     189: aload         8
     191: invokevirtual #37                 // Method java/lang/StringBuilder.append:(Ljava/lang/Object;)Ljava/lang/StringBuilder;
     194: invokevirtual #32                 // Method java/lang/StringBuilder.toString:()Ljava/lang/String;
     197: invokeinterface #16,  2           // InterfaceMethod org/slf4j/Logger.debug:(Ljava/lang/String;)V
     202: lconst_0
     203: lstore        10
     205: aload         8
     207: invokeinterface #38,  1           // InterfaceMethod java/util/Map.values:()Ljava/util/Collection;
     212: invokeinterface #39,  1           // InterfaceMethod java/util/Collection.iterator:()Ljava/util/Iterator;
     217: astore        12
     219: aload         12
     221: invokeinterface #40,  1           // InterfaceMethod java/util/Iterator.hasNext:()Z
     226: ifeq          254
     229: aload         12
     231: invokeinterface #41,  1           // InterfaceMethod java/util/Iterator.next:()Ljava/lang/Object;
     236: checkcast     #42                 // class java/lang/Long
     239: astore        13
     241: lload         10
     243: aload         13
     245: invokevirtual #43                 // Method java/lang/Long.longValue:()J
     248: ladd
     249: lstore        10
     251: goto          219
     254: new           #26                 // class java/lang/StringBuilder
     257: dup
     258: invokespecial #27                 // Method java/lang/StringBuilder."<init>":()V
     261: ldc           #44                 // String Expected region size report to exceed 5242880, but was
     263: invokevirtual #29                 // Method java/lang/StringBuilder.append:(Ljava/lang/String;)Ljava/lang/StringBuilder;
     266: lload         10
     268: invokevirtual #45                 // Method java/lang/StringBuilder.append:(J)Ljava/lang/StringBuilder;
     271: ldc           #46                 // String . RegionSizes=
     273: invokevirtual #29                 // Method java/lang/StringBuilder.append:(Ljava/lang/String;)Ljava/lang/StringBuilder;
     276: aload         8
     278: invokevirtual #37                 // Method java/lang/StringBuilder.append:(Ljava/lang/Object;)Ljava/lang/StringBuilder;
     281: invokevirtual #32                 // Method java/lang/StringBuilder.toString:()Ljava/lang/String;
     284: ldc2_w        #11                 // long 5242880l
     287: lload         10
     289: lcmp
     290: ifge          297
     293: iconst_1
     294: goto          298
     297: iconst_0
     298: invokestatic  #47                 // Method org/junit/Assert.assertTrue:(Ljava/lang/String;Z)V
     301: return

  static {};
    Code:
       0: ldc           #57                 // class org/apache/hadoop/hbase/quotas/TestRegionSizeUse
       2: invokestatic  #93                 // Method org/apache/hadoop/hbase/HBaseClassTestRule.forClass:(Ljava/lang/Class;)Lorg/apache/hadoop/hbase/HBaseClassTestRule;
       5: putstatic     #94                 // Field CLASS_RULE:Lorg/apache/hadoop/hbase/HBaseClassTestRule;
       8: ldc           #57                 // class org/apache/hadoop/hbase/quotas/TestRegionSizeUse
      10: invokestatic  #95                 // Method org/slf4j/LoggerFactory.getLogger:(Ljava/lang/Class;)Lorg/slf4j/Logger;
      13: putstatic     #14                 // Field LOG:Lorg/slf4j/Logger;
      16: new           #96                 // class org/apache/hadoop/hbase/HBaseTestingUtility
      19: dup
      20: invokespecial #97                 // Method org/apache/hadoop/hbase/HBaseTestingUtility."<init>":()V
      23: putstatic     #5                  // Field TEST_UTIL:Lorg/apache/hadoop/hbase/HBaseTestingUtility;
      26: return
}
