Compiled from "TestRegionSnapshotTask.java"
class org.apache.hadoop.hbase.snapshot.TestRegionSnapshotTask$1 extends org.apache.hadoop.hbase.snapshot.SnapshotManifestV2$ManifestBuilder {
  final org.apache.hadoop.hbase.snapshot.TestRegionSnapshotTask this$0;

  org.apache.hadoop.hbase.snapshot.TestRegionSnapshotTask$1(org.apache.hadoop.hbase.snapshot.TestRegionSnapshotTask, org.apache.hadoop.conf.Configuration, org.apache.hadoop.fs.FileSystem, org.apache.hadoop.fs.Path);
    Code:
       0: aload_0
       1: aload_1
       2: putfield      #1                  // Field this$0:Lorg/apache/hadoop/hbase/snapshot/TestRegionSnapshotTask;
       5: aload_0
       6: aload_2
       7: aload_3
       8: aload         4
      10: invokespecial #2                  // Method org/apache/hadoop/hbase/snapshot/SnapshotManifestV2$ManifestBuilder."<init>":(Lorg/apache/hadoop/conf/Configuration;Lorg/apache/hadoop/fs/FileSystem;Lorg/apache/hadoop/fs/Path;)V
      13: return

  public void storeFile(org.apache.hadoop.hbase.shaded.protobuf.generated.SnapshotProtos$SnapshotRegionManifest$Builder, org.apache.hadoop.hbase.shaded.protobuf.generated.SnapshotProtos$SnapshotRegionManifest$FamilyFiles$Builder, org.apache.hadoop.hbase.regionserver.StoreFileInfo) throws java.io.IOException;
    Code:
       0: aload_0
       1: getfield      #1                  // Field this$0:Lorg/apache/hadoop/hbase/snapshot/TestRegionSnapshotTask;
       4: invokestatic  #3                  // Method org/apache/hadoop/hbase/snapshot/TestRegionSnapshotTask.access$000:(Lorg/apache/hadoop/hbase/snapshot/TestRegionSnapshotTask;)Lorg/slf4j/Logger;
       7: ldc           #4                  // String Introducing delay before adding store file to manifest
       9: invokeinterface #5,  2            // InterfaceMethod org/slf4j/Logger.debug:(Ljava/lang/String;)V
      14: ldc2_w        #6                  // long 2000l
      17: invokestatic  #8                  // Method java/lang/Thread.sleep:(J)V
      20: goto          57
      23: astore        4
      25: aload_0
      26: getfield      #1                  // Field this$0:Lorg/apache/hadoop/hbase/snapshot/TestRegionSnapshotTask;
      29: invokestatic  #3                  // Method org/apache/hadoop/hbase/snapshot/TestRegionSnapshotTask.access$000:(Lorg/apache/hadoop/hbase/snapshot/TestRegionSnapshotTask;)Lorg/slf4j/Logger;
      32: new           #10                 // class java/lang/StringBuilder
      35: dup
      36: invokespecial #11                 // Method java/lang/StringBuilder."<init>":()V
      39: ldc           #12                 // String Interrupted due to error:
      41: invokevirtual #13                 // Method java/lang/StringBuilder.append:(Ljava/lang/String;)Ljava/lang/StringBuilder;
      44: aload         4
      46: invokevirtual #14                 // Method java/lang/StringBuilder.append:(Ljava/lang/Object;)Ljava/lang/StringBuilder;
      49: invokevirtual #15                 // Method java/lang/StringBuilder.toString:()Ljava/lang/String;
      52: invokeinterface #16,  2           // InterfaceMethod org/slf4j/Logger.error:(Ljava/lang/String;)V
      57: aload_0
      58: aload_1
      59: aload_2
      60: aload_3
      61: invokespecial #17                 // Method org/apache/hadoop/hbase/snapshot/SnapshotManifestV2$ManifestBuilder.storeFile:(Lorg/apache/hadoop/hbase/shaded/protobuf/generated/SnapshotProtos$SnapshotRegionManifest$Builder;Lorg/apache/hadoop/hbase/shaded/protobuf/generated/SnapshotProtos$SnapshotRegionManifest$FamilyFiles$Builder;Lorg/apache/hadoop/hbase/regionserver/StoreFileInfo;)V
      64: return
    Exception table:
       from    to  target type
           0    20    23   Class java/lang/InterruptedException

  public void storeFile(java.lang.Object, java.lang.Object, org.apache.hadoop.hbase.regionserver.StoreFileInfo) throws java.io.IOException;
    Code:
       0: aload_0
       1: aload_1
       2: checkcast     #18                 // class org/apache/hadoop/hbase/shaded/protobuf/generated/SnapshotProtos$SnapshotRegionManifest$Builder
       5: aload_2
       6: checkcast     #19                 // class org/apache/hadoop/hbase/shaded/protobuf/generated/SnapshotProtos$SnapshotRegionManifest$FamilyFiles$Builder
       9: aload_3
      10: invokevirtual #20                 // Method storeFile:(Lorg/apache/hadoop/hbase/shaded/protobuf/generated/SnapshotProtos$SnapshotRegionManifest$Builder;Lorg/apache/hadoop/hbase/shaded/protobuf/generated/SnapshotProtos$SnapshotRegionManifest$FamilyFiles$Builder;Lorg/apache/hadoop/hbase/regionserver/StoreFileInfo;)V
      13: return
}
