Compiled from "TestReplicationEndpointWithMultipleWAL.java"
public class org.apache.hadoop.hbase.replication.multiwal.TestReplicationEndpointWithMultipleWAL extends org.apache.hadoop.hbase.replication.TestReplicationEndpoint {
  public static final org.apache.hadoop.hbase.HBaseClassTestRule CLASS_RULE;

  public org.apache.hadoop.hbase.replication.multiwal.TestReplicationEndpointWithMultipleWAL();
    Code:
       0: aload_0
       1: invokespecial #1                  // Method org/apache/hadoop/hbase/replication/TestReplicationEndpoint."<init>":()V
       4: return

  public static void setUpBeforeClass() throws java.lang.Exception;
    Code:
       0: getstatic     #2                  // Field CONF1:Lorg/apache/hadoop/conf/Configuration;
       3: ldc           #4                  // String hbase.wal.provider
       5: ldc           #5                  // String multiwal
       7: invokevirtual #6                  // Method org/apache/hadoop/conf/Configuration.set:(Ljava/lang/String;Ljava/lang/String;)V
      10: getstatic     #2                  // Field CONF1:Lorg/apache/hadoop/conf/Configuration;
      13: ldc           #8                  // String hbase.wal.regiongrouping.delegate.provider
      15: ldc           #9                  // String filesystem
      17: invokevirtual #6                  // Method org/apache/hadoop/conf/Configuration.set:(Ljava/lang/String;Ljava/lang/String;)V
      20: invokestatic  #10                 // Method org/apache/hadoop/hbase/replication/TestReplicationEndpoint.setUpBeforeClass:()V
      23: return

  static {};
    Code:
       0: ldc           #11                 // class org/apache/hadoop/hbase/replication/multiwal/TestReplicationEndpointWithMultipleWAL
       2: invokestatic  #12                 // Method org/apache/hadoop/hbase/HBaseClassTestRule.forClass:(Ljava/lang/Class;)Lorg/apache/hadoop/hbase/HBaseClassTestRule;
       5: putstatic     #13                 // Field CLASS_RULE:Lorg/apache/hadoop/hbase/HBaseClassTestRule;
       8: return
}
