Compiled from "TestMasterTransitions.java"
public class org.apache.hadoop.hbase.master.TestMasterTransitions {
  public static final org.apache.hadoop.hbase.HBaseClassTestRule CLASS_RULE;

  public org.apache.hadoop.hbase.master.TestMasterTransitions();
    Code:
       0: aload_0
       1: invokespecial #1                  // Method java/lang/Object."<init>":()V
       4: return

  public static void beforeAllTests() throws java.lang.Exception;
    Code:
       0: getstatic     #2                  // Field TEST_UTIL:Lorg/apache/hadoop/hbase/HBaseTestingUtility;
       3: iconst_2
       4: invokevirtual #3                  // Method org/apache/hadoop/hbase/HBaseTestingUtility.startMiniCluster:(I)Lorg/apache/hadoop/hbase/MiniHBaseCluster;
       7: pop
       8: getstatic     #2                  // Field TEST_UTIL:Lorg/apache/hadoop/hbase/HBaseTestingUtility;
      11: getstatic     #4                  // Field TABLENAME:Lorg/apache/hadoop/hbase/TableName;
      14: getstatic     #5                  // Field FAMILIES:[[B
      17: invokevirtual #6                  // Method org/apache/hadoop/hbase/HBaseTestingUtility.createMultiRegionTable:(Lorg/apache/hadoop/hbase/TableName;[[B)Lorg/apache/hadoop/hbase/client/Table;
      20: pop
      21: getstatic     #2                  // Field TEST_UTIL:Lorg/apache/hadoop/hbase/HBaseTestingUtility;
      24: invokevirtual #7                  // Method org/apache/hadoop/hbase/HBaseTestingUtility.getConnection:()Lorg/apache/hadoop/hbase/client/Connection;
      27: getstatic     #4                  // Field TABLENAME:Lorg/apache/hadoop/hbase/TableName;
      30: invokeinterface #8,  2            // InterfaceMethod org/apache/hadoop/hbase/client/Connection.getTable:(Lorg/apache/hadoop/hbase/TableName;)Lorg/apache/hadoop/hbase/client/Table;
      35: astore_0
      36: iconst_m1
      37: istore_1
      38: getstatic     #2                  // Field TEST_UTIL:Lorg/apache/hadoop/hbase/HBaseTestingUtility;
      41: invokevirtual #7                  // Method org/apache/hadoop/hbase/HBaseTestingUtility.getConnection:()Lorg/apache/hadoop/hbase/client/Connection;
      44: getstatic     #4                  // Field TABLENAME:Lorg/apache/hadoop/hbase/TableName;
      47: invokeinterface #9,  2            // InterfaceMethod org/apache/hadoop/hbase/client/Connection.getRegionLocator:(Lorg/apache/hadoop/hbase/TableName;)Lorg/apache/hadoop/hbase/client/RegionLocator;
      52: astore_2
      53: aconst_null
      54: astore_3
      55: aload_2
      56: invokeinterface #10,  1           // InterfaceMethod org/apache/hadoop/hbase/client/RegionLocator.getStartKeys:()[[B
      61: arraylength
      62: istore_1
      63: aload_2
      64: ifnull        147
      67: aload_3
      68: ifnull        91
      71: aload_2
      72: invokeinterface #11,  1           // InterfaceMethod org/apache/hadoop/hbase/client/RegionLocator.close:()V
      77: goto          147
      80: astore        4
      82: aload_3
      83: aload         4
      85: invokevirtual #13                 // Method java/lang/Throwable.addSuppressed:(Ljava/lang/Throwable;)V
      88: goto          147
      91: aload_2
      92: invokeinterface #11,  1           // InterfaceMethod org/apache/hadoop/hbase/client/RegionLocator.close:()V
      97: goto          147
     100: astore        4
     102: aload         4
     104: astore_3
     105: aload         4
     107: athrow
     108: astore        5
     110: aload_2
     111: ifnull        144
     114: aload_3
     115: ifnull        138
     118: aload_2
     119: invokeinterface #11,  1           // InterfaceMethod org/apache/hadoop/hbase/client/RegionLocator.close:()V
     124: goto          144
     127: astore        6
     129: aload_3
     130: aload         6
     132: invokevirtual #13                 // Method java/lang/Throwable.addSuppressed:(Ljava/lang/Throwable;)V
     135: goto          144
     138: aload_2
     139: invokeinterface #11,  1           // InterfaceMethod org/apache/hadoop/hbase/client/RegionLocator.close:()V
     144: aload         5
     146: athrow
     147: getstatic     #2                  // Field TEST_UTIL:Lorg/apache/hadoop/hbase/HBaseTestingUtility;
     150: getstatic     #4                  // Field TABLENAME:Lorg/apache/hadoop/hbase/TableName;
     153: invokevirtual #14                 // Method org/apache/hadoop/hbase/HBaseTestingUtility.waitUntilAllRegionsAssigned:(Lorg/apache/hadoop/hbase/TableName;)V
     156: iload_1
     157: invokestatic  #15                 // Method addToEachStartKey:(I)I
     160: pop
     161: aload_0
     162: invokeinterface #16,  1           // InterfaceMethod org/apache/hadoop/hbase/client/Table.close:()V
     167: return
    Exception table:
       from    to  target type
          71    77    80   Class java/lang/Throwable
          55    63   100   Class java/lang/Throwable
          55    63   108   any
         118   124   127   Class java/lang/Throwable
         100   110   108   any

  public static void afterAllTests() throws java.lang.Exception;
    Code:
       0: getstatic     #2                  // Field TEST_UTIL:Lorg/apache/hadoop/hbase/HBaseTestingUtility;
       3: invokevirtual #17                 // Method org/apache/hadoop/hbase/HBaseTestingUtility.shutdownMiniCluster:()V
       6: return

  public void setup() throws java.io.IOException;
    Code:
       0: getstatic     #2                  // Field TEST_UTIL:Lorg/apache/hadoop/hbase/HBaseTestingUtility;
       3: iconst_2
       4: invokevirtual #18                 // Method org/apache/hadoop/hbase/HBaseTestingUtility.ensureSomeRegionServersAvailable:(I)Z
       7: pop
       8: return

  public void testRegionCloseWhenNoMetaHBase2428() throws java.lang.Exception;
    Code:
       0: return

  public void testAddingServerBeforeOldIsDead2413() throws java.io.IOException;
    Code:
       0: return

  public void testKillRSWithOpeningRegion2482() throws java.lang.Exception;
    Code:
       0: return

  static {};
    Code:
       0: ldc           #46                 // class org/apache/hadoop/hbase/master/TestMasterTransitions
       2: invokestatic  #47                 // Method org/apache/hadoop/hbase/HBaseClassTestRule.forClass:(Ljava/lang/Class;)Lorg/apache/hadoop/hbase/HBaseClassTestRule;
       5: putstatic     #48                 // Field CLASS_RULE:Lorg/apache/hadoop/hbase/HBaseClassTestRule;
       8: ldc           #46                 // class org/apache/hadoop/hbase/master/TestMasterTransitions
      10: invokestatic  #49                 // Method org/slf4j/LoggerFactory.getLogger:(Ljava/lang/Class;)Lorg/slf4j/Logger;
      13: putstatic     #50                 // Field LOG:Lorg/slf4j/Logger;
      16: new           #51                 // class org/apache/hadoop/hbase/HBaseTestingUtility
      19: dup
      20: invokespecial #52                 // Method org/apache/hadoop/hbase/HBaseTestingUtility."<init>":()V
      23: putstatic     #2                  // Field TEST_UTIL:Lorg/apache/hadoop/hbase/HBaseTestingUtility;
      26: ldc           #53                 // String master_transitions
      28: invokestatic  #54                 // Method org/apache/hadoop/hbase/TableName.valueOf:(Ljava/lang/String;)Lorg/apache/hadoop/hbase/TableName;
      31: putstatic     #4                  // Field TABLENAME:Lorg/apache/hadoop/hbase/TableName;
      34: iconst_3
      35: anewarray     #55                 // class "[B"
      38: dup
      39: iconst_0
      40: ldc           #56                 // String a
      42: invokestatic  #45                 // Method org/apache/hadoop/hbase/util/Bytes.toBytes:(Ljava/lang/String;)[B
      45: aastore
      46: dup
      47: iconst_1
      48: ldc           #57                 // String b
      50: invokestatic  #45                 // Method org/apache/hadoop/hbase/util/Bytes.toBytes:(Ljava/lang/String;)[B
      53: aastore
      54: dup
      55: iconst_2
      56: ldc           #58                 // String c
      58: invokestatic  #45                 // Method org/apache/hadoop/hbase/util/Bytes.toBytes:(Ljava/lang/String;)[B
      61: aastore
      62: putstatic     #5                  // Field FAMILIES:[[B
      65: return
}
