Compiled from "TestStochasticLoadBalancer.java"
class org.apache.hadoop.hbase.master.balancer.TestStochasticLoadBalancer$MockCluster extends org.apache.hadoop.hbase.master.balancer.BaseLoadBalancer$Cluster {
  final org.apache.hadoop.hbase.master.balancer.TestStochasticLoadBalancer this$0;

  public org.apache.hadoop.hbase.master.balancer.TestStochasticLoadBalancer$MockCluster(org.apache.hadoop.hbase.master.balancer.TestStochasticLoadBalancer, int[][]);
    Code:
       0: aload_0
       1: aload_1
       2: putfield      #1                  // Field this$0:Lorg/apache/hadoop/hbase/master/balancer/TestStochasticLoadBalancer;
       5: aload_0
       6: aload_1
       7: aload_2
       8: iconst_0
       9: aaload
      10: iconst_1
      11: invokevirtual #2                  // Method org/apache/hadoop/hbase/master/balancer/TestStochasticLoadBalancer.mockClusterServers:([II)Ljava/util/TreeMap;
      14: aconst_null
      15: aconst_null
      16: aconst_null
      17: invokespecial #3                  // Method org/apache/hadoop/hbase/master/balancer/BaseLoadBalancer$Cluster."<init>":(Ljava/util/Map;Ljava/util/Map;Lorg/apache/hadoop/hbase/master/balancer/RegionLocationFinder;Lorg/apache/hadoop/hbase/master/RackManager;)V
      20: aload_0
      21: aconst_null
      22: checkcast     #4                  // class "[[I"
      25: putfield      #5                  // Field localities:[[I
      28: aload_0
      29: aload_2
      30: arraylength
      31: iconst_1
      32: isub
      33: anewarray     #6                  // class "[I"
      36: putfield      #5                  // Field localities:[[I
      39: iconst_1
      40: istore_3
      41: iload_3
      42: aload_2
      43: arraylength
      44: if_icmpge     148
      47: iload_3
      48: iconst_1
      49: isub
      50: istore        4
      52: aload_0
      53: getfield      #5                  // Field localities:[[I
      56: iload         4
      58: aload_2
      59: iload_3
      60: aaload
      61: arraylength
      62: iconst_1
      63: isub
      64: newarray       int
      66: aastore
      67: aload_0
      68: getfield      #7                  // Field regionIndexToServerIndex:[I
      71: iload         4
      73: aload_2
      74: iload_3
      75: aaload
      76: iconst_0
      77: iaload
      78: iastore
      79: iconst_1
      80: istore        5
      82: iload         5
      84: aload_2
      85: iload_3
      86: aaload
      87: arraylength
      88: if_icmpge     142
      91: iload         5
      93: iconst_1
      94: isub
      95: istore        6
      97: aload_0
      98: getfield      #5                  // Field localities:[[I
     101: iload         4
     103: aaload
     104: iload         6
     106: aload_2
     107: iload_3
     108: aaload
     109: iload         5
     111: iaload
     112: bipush        100
     114: if_icmple     129
     117: aload_2
     118: iload_3
     119: aaload
     120: iload         5
     122: iaload
     123: bipush        100
     125: irem
     126: goto          135
     129: aload_2
     130: iload_3
     131: aaload
     132: iload         5
     134: iaload
     135: iastore
     136: iinc          5, 1
     139: goto          82
     142: iinc          3, 1
     145: goto          41
     148: return

  float getLocalityOfRegion(int, int);
    Code:
       0: aload_0
       1: getfield      #5                  // Field localities:[[I
       4: iload_1
       5: aaload
       6: iload_2
       7: iaload
       8: i2f
       9: ldc           #8                  // float 100.0f
      11: fdiv
      12: freturn

  public int getRegionSizeMB(int);
    Code:
       0: iconst_1
       1: ireturn
}
