Compiled from "TestAccessController.java"
class org.apache.hadoop.hbase.security.access.TestAccessController$75 implements org.apache.hadoop.hbase.security.access.SecureTestUtil$AccessTestAction {
  final org.apache.hadoop.hbase.client.Admin val$admin;

  final org.apache.hadoop.hbase.HRegionInfo val$hri;

  final org.apache.hadoop.hbase.regionserver.HRegionServer val$newRs;

  final org.apache.hadoop.hbase.security.access.TestAccessController this$0;

  org.apache.hadoop.hbase.security.access.TestAccessController$75(org.apache.hadoop.hbase.security.access.TestAccessController, org.apache.hadoop.hbase.client.Admin, org.apache.hadoop.hbase.HRegionInfo, org.apache.hadoop.hbase.regionserver.HRegionServer);
    Code:
       0: aload_0
       1: aload_1
       2: putfield      #1                  // Field this$0:Lorg/apache/hadoop/hbase/security/access/TestAccessController;
       5: aload_0
       6: aload_2
       7: putfield      #2                  // Field val$admin:Lorg/apache/hadoop/hbase/client/Admin;
      10: aload_0
      11: aload_3
      12: putfield      #3                  // Field val$hri:Lorg/apache/hadoop/hbase/HRegionInfo;
      15: aload_0
      16: aload         4
      18: putfield      #4                  // Field val$newRs:Lorg/apache/hadoop/hbase/regionserver/HRegionServer;
      21: aload_0
      22: invokespecial #5                  // Method java/lang/Object."<init>":()V
      25: return

  public java.lang.Object run() throws java.lang.Exception;
    Code:
       0: aload_0
       1: getfield      #2                  // Field val$admin:Lorg/apache/hadoop/hbase/client/Admin;
       4: aload_0
       5: getfield      #3                  // Field val$hri:Lorg/apache/hadoop/hbase/HRegionInfo;
       8: invokevirtual #6                  // Method org/apache/hadoop/hbase/HRegionInfo.getEncodedNameAsBytes:()[B
      11: aload_0
      12: getfield      #4                  // Field val$newRs:Lorg/apache/hadoop/hbase/regionserver/HRegionServer;
      15: invokevirtual #7                  // Method org/apache/hadoop/hbase/regionserver/HRegionServer.getServerName:()Lorg/apache/hadoop/hbase/ServerName;
      18: invokeinterface #8,  3            // InterfaceMethod org/apache/hadoop/hbase/client/Admin.move:([BLorg/apache/hadoop/hbase/ServerName;)V
      23: aconst_null
      24: areturn
}
