Compiled from "TestCIIncrementRpcTimeout.java"
public class org.apache.hadoop.hbase.client.TestCIIncrementRpcTimeout extends org.apache.hadoop.hbase.client.AbstractTestCIRpcTimeout {
  public static final org.apache.hadoop.hbase.HBaseClassTestRule CLASS_RULE;

  public org.apache.hadoop.hbase.client.TestCIIncrementRpcTimeout();
    Code:
       0: aload_0
       1: invokespecial #1                  // Method org/apache/hadoop/hbase/client/AbstractTestCIRpcTimeout."<init>":()V
       4: return

  protected void execute(org.apache.hadoop.hbase.client.Table) throws java.io.IOException;
    Code:
       0: aload_1
       1: new           #2                  // class org/apache/hadoop/hbase/client/Increment
       4: dup
       5: getstatic     #3                  // Field FAM_NAM:[B
       8: invokespecial #4                  // Method org/apache/hadoop/hbase/client/Increment."<init>":([B)V
      11: getstatic     #3                  // Field FAM_NAM:[B
      14: getstatic     #3                  // Field FAM_NAM:[B
      17: lconst_1
      18: invokevirtual #5                  // Method org/apache/hadoop/hbase/client/Increment.addColumn:([B[BJ)Lorg/apache/hadoop/hbase/client/Increment;
      21: invokeinterface #6,  2            // InterfaceMethod org/apache/hadoop/hbase/client/Table.increment:(Lorg/apache/hadoop/hbase/client/Increment;)Lorg/apache/hadoop/hbase/client/Result;
      26: pop
      27: return

  static {};
    Code:
       0: ldc           #7                  // class org/apache/hadoop/hbase/client/TestCIIncrementRpcTimeout
       2: invokestatic  #8                  // Method org/apache/hadoop/hbase/HBaseClassTestRule.forClass:(Ljava/lang/Class;)Lorg/apache/hadoop/hbase/HBaseClassTestRule;
       5: putstatic     #9                  // Field CLASS_RULE:Lorg/apache/hadoop/hbase/HBaseClassTestRule;
       8: return
}
