Compiled from "TestAsyncSingleRequestRpcRetryingCaller.java"
public class org.apache.hadoop.hbase.client.TestAsyncSingleRequestRpcRetryingCaller {
  public static final org.apache.hadoop.hbase.HBaseClassTestRule CLASS_RULE;

  public org.apache.hadoop.hbase.client.TestAsyncSingleRequestRpcRetryingCaller();
    Code:
       0: aload_0
       1: invokespecial #2                  // Method java/lang/Object."<init>":()V
       4: return

  public static void setUpBeforeClass() throws java.lang.Exception;
    Code:
       0: getstatic     #3                  // Field TEST_UTIL:Lorg/apache/hadoop/hbase/HBaseTestingUtility;
       3: iconst_2
       4: invokevirtual #4                  // Method org/apache/hadoop/hbase/HBaseTestingUtility.startMiniCluster:(I)Lorg/apache/hadoop/hbase/MiniHBaseCluster;
       7: pop
       8: getstatic     #3                  // Field TEST_UTIL:Lorg/apache/hadoop/hbase/HBaseTestingUtility;
      11: invokevirtual #5                  // Method org/apache/hadoop/hbase/HBaseTestingUtility.getAdmin:()Lorg/apache/hadoop/hbase/client/Admin;
      14: iconst_0
      15: iconst_1
      16: invokeinterface #6,  3            // InterfaceMethod org/apache/hadoop/hbase/client/Admin.balancerSwitch:(ZZ)Z
      21: pop
      22: getstatic     #3                  // Field TEST_UTIL:Lorg/apache/hadoop/hbase/HBaseTestingUtility;
      25: getstatic     #1                  // Field TABLE_NAME:Lorg/apache/hadoop/hbase/TableName;
      28: getstatic     #7                  // Field FAMILY:[B
      31: invokevirtual #8                  // Method org/apache/hadoop/hbase/HBaseTestingUtility.createTable:(Lorg/apache/hadoop/hbase/TableName;[B)Lorg/apache/hadoop/hbase/client/Table;
      34: pop
      35: getstatic     #3                  // Field TEST_UTIL:Lorg/apache/hadoop/hbase/HBaseTestingUtility;
      38: getstatic     #1                  // Field TABLE_NAME:Lorg/apache/hadoop/hbase/TableName;
      41: invokevirtual #9                  // Method org/apache/hadoop/hbase/HBaseTestingUtility.waitTableAvailable:(Lorg/apache/hadoop/hbase/TableName;)V
      44: getstatic     #3                  // Field TEST_UTIL:Lorg/apache/hadoop/hbase/HBaseTestingUtility;
      47: invokevirtual #10                 // Method org/apache/hadoop/hbase/HBaseTestingUtility.getConfiguration:()Lorg/apache/hadoop/conf/Configuration;
      50: invokestatic  #11                 // Method org/apache/hadoop/hbase/client/AsyncRegistryFactory.getRegistry:(Lorg/apache/hadoop/conf/Configuration;)Lorg/apache/hadoop/hbase/client/AsyncRegistry;
      53: astore_0
      54: new           #12                 // class org/apache/hadoop/hbase/client/AsyncConnectionImpl
      57: dup
      58: getstatic     #3                  // Field TEST_UTIL:Lorg/apache/hadoop/hbase/HBaseTestingUtility;
      61: invokevirtual #10                 // Method org/apache/hadoop/hbase/HBaseTestingUtility.getConfiguration:()Lorg/apache/hadoop/conf/Configuration;
      64: aload_0
      65: aload_0
      66: invokeinterface #13,  1           // InterfaceMethod org/apache/hadoop/hbase/client/AsyncRegistry.getClusterId:()Ljava/util/concurrent/CompletableFuture;
      71: invokevirtual #14                 // Method java/util/concurrent/CompletableFuture.get:()Ljava/lang/Object;
      74: checkcast     #15                 // class java/lang/String
      77: invokestatic  #16                 // Method org/apache/hadoop/hbase/security/User.getCurrent:()Lorg/apache/hadoop/hbase/security/User;
      80: invokespecial #17                 // Method org/apache/hadoop/hbase/client/AsyncConnectionImpl."<init>":(Lorg/apache/hadoop/conf/Configuration;Lorg/apache/hadoop/hbase/client/AsyncRegistry;Ljava/lang/String;Lorg/apache/hadoop/hbase/security/User;)V
      83: putstatic     #18                 // Field CONN:Lorg/apache/hadoop/hbase/client/AsyncConnectionImpl;
      86: return

  public static void tearDownAfterClass() throws java.lang.Exception;
    Code:
       0: getstatic     #18                 // Field CONN:Lorg/apache/hadoop/hbase/client/AsyncConnectionImpl;
       3: invokestatic  #19                 // Method org/apache/commons/io/IOUtils.closeQuietly:(Ljava/io/Closeable;)V
       6: getstatic     #3                  // Field TEST_UTIL:Lorg/apache/hadoop/hbase/HBaseTestingUtility;
       9: invokevirtual #20                 // Method org/apache/hadoop/hbase/HBaseTestingUtility.shutdownMiniCluster:()V
      12: return

  public void testRegionMove() throws java.lang.InterruptedException, java.util.concurrent.ExecutionException, java.io.IOException;
    Code:
       0: getstatic     #18                 // Field CONN:Lorg/apache/hadoop/hbase/client/AsyncConnectionImpl;
       3: getstatic     #1                  // Field TABLE_NAME:Lorg/apache/hadoop/hbase/TableName;
       6: invokevirtual #21                 // Method org/apache/hadoop/hbase/client/AsyncConnectionImpl.getRegionLocator:(Lorg/apache/hadoop/hbase/TableName;)Lorg/apache/hadoop/hbase/client/AsyncTableRegionLocator;
       9: getstatic     #22                 // Field ROW:[B
      12: invokeinterface #23,  2           // InterfaceMethod org/apache/hadoop/hbase/client/AsyncTableRegionLocator.getRegionLocation:([B)Ljava/util/concurrent/CompletableFuture;
      17: invokevirtual #14                 // Method java/util/concurrent/CompletableFuture.get:()Ljava/lang/Object;
      20: checkcast     #24                 // class org/apache/hadoop/hbase/HRegionLocation
      23: astore_1
      24: getstatic     #3                  // Field TEST_UTIL:Lorg/apache/hadoop/hbase/HBaseTestingUtility;
      27: invokevirtual #25                 // Method org/apache/hadoop/hbase/HBaseTestingUtility.getHBaseCluster:()Lorg/apache/hadoop/hbase/MiniHBaseCluster;
      30: aload_1
      31: invokevirtual #26                 // Method org/apache/hadoop/hbase/HRegionLocation.getRegion:()Lorg/apache/hadoop/hbase/client/RegionInfo;
      34: invokeinterface #27,  1           // InterfaceMethod org/apache/hadoop/hbase/client/RegionInfo.getRegionName:()[B
      39: invokevirtual #28                 // Method org/apache/hadoop/hbase/MiniHBaseCluster.getServerWith:([B)I
      42: istore_2
      43: getstatic     #3                  // Field TEST_UTIL:Lorg/apache/hadoop/hbase/HBaseTestingUtility;
      46: invokevirtual #5                  // Method org/apache/hadoop/hbase/HBaseTestingUtility.getAdmin:()Lorg/apache/hadoop/hbase/client/Admin;
      49: aload_1
      50: invokevirtual #26                 // Method org/apache/hadoop/hbase/HRegionLocation.getRegion:()Lorg/apache/hadoop/hbase/client/RegionInfo;
      53: invokeinterface #29,  1           // InterfaceMethod org/apache/hadoop/hbase/client/RegionInfo.getEncodedNameAsBytes:()[B
      58: getstatic     #3                  // Field TEST_UTIL:Lorg/apache/hadoop/hbase/HBaseTestingUtility;
      61: invokevirtual #25                 // Method org/apache/hadoop/hbase/HBaseTestingUtility.getHBaseCluster:()Lorg/apache/hadoop/hbase/MiniHBaseCluster;
      64: iconst_1
      65: iload_2
      66: isub
      67: invokevirtual #30                 // Method org/apache/hadoop/hbase/MiniHBaseCluster.getRegionServer:(I)Lorg/apache/hadoop/hbase/regionserver/HRegionServer;
      70: invokevirtual #31                 // Method org/apache/hadoop/hbase/regionserver/HRegionServer.getServerName:()Lorg/apache/hadoop/hbase/ServerName;
      73: invokeinterface #32,  3           // InterfaceMethod org/apache/hadoop/hbase/client/Admin.move:([BLorg/apache/hadoop/hbase/ServerName;)V
      78: getstatic     #18                 // Field CONN:Lorg/apache/hadoop/hbase/client/AsyncConnectionImpl;
      81: getstatic     #1                  // Field TABLE_NAME:Lorg/apache/hadoop/hbase/TableName;
      84: invokevirtual #33                 // Method org/apache/hadoop/hbase/client/AsyncConnectionImpl.getTableBuilder:(Lorg/apache/hadoop/hbase/TableName;)Lorg/apache/hadoop/hbase/client/AsyncTableBuilder;
      87: ldc2_w        #34                 // long 100l
      90: getstatic     #36                 // Field java/util/concurrent/TimeUnit.MILLISECONDS:Ljava/util/concurrent/TimeUnit;
      93: invokeinterface #37,  4           // InterfaceMethod org/apache/hadoop/hbase/client/AsyncTableBuilder.setRetryPause:(JLjava/util/concurrent/TimeUnit;)Lorg/apache/hadoop/hbase/client/AsyncTableBuilder;
      98: bipush        30
     100: invokeinterface #38,  2           // InterfaceMethod org/apache/hadoop/hbase/client/AsyncTableBuilder.setMaxRetries:(I)Lorg/apache/hadoop/hbase/client/AsyncTableBuilder;
     105: invokeinterface #39,  1           // InterfaceMethod org/apache/hadoop/hbase/client/AsyncTableBuilder.build:()Lorg/apache/hadoop/hbase/client/AsyncTable;
     110: astore_3
     111: aload_3
     112: new           #40                 // class org/apache/hadoop/hbase/client/Put
     115: dup
     116: getstatic     #22                 // Field ROW:[B
     119: invokespecial #41                 // Method org/apache/hadoop/hbase/client/Put."<init>":([B)V
     122: getstatic     #7                  // Field FAMILY:[B
     125: getstatic     #42                 // Field QUALIFIER:[B
     128: getstatic     #43                 // Field VALUE:[B
     131: invokevirtual #44                 // Method org/apache/hadoop/hbase/client/Put.addColumn:([B[B[B)Lorg/apache/hadoop/hbase/client/Put;
     134: invokeinterface #45,  2           // InterfaceMethod org/apache/hadoop/hbase/client/AsyncTable.put:(Lorg/apache/hadoop/hbase/client/Put;)Ljava/util/concurrent/CompletableFuture;
     139: invokevirtual #14                 // Method java/util/concurrent/CompletableFuture.get:()Ljava/lang/Object;
     142: pop
     143: getstatic     #3                  // Field TEST_UTIL:Lorg/apache/hadoop/hbase/HBaseTestingUtility;
     146: invokevirtual #5                  // Method org/apache/hadoop/hbase/HBaseTestingUtility.getAdmin:()Lorg/apache/hadoop/hbase/client/Admin;
     149: aload_1
     150: invokevirtual #26                 // Method org/apache/hadoop/hbase/HRegionLocation.getRegion:()Lorg/apache/hadoop/hbase/client/RegionInfo;
     153: invokeinterface #29,  1           // InterfaceMethod org/apache/hadoop/hbase/client/RegionInfo.getEncodedNameAsBytes:()[B
     158: aload_1
     159: invokevirtual #46                 // Method org/apache/hadoop/hbase/HRegionLocation.getServerName:()Lorg/apache/hadoop/hbase/ServerName;
     162: invokeinterface #32,  3           // InterfaceMethod org/apache/hadoop/hbase/client/Admin.move:([BLorg/apache/hadoop/hbase/ServerName;)V
     167: aload_3
     168: new           #47                 // class org/apache/hadoop/hbase/client/Get
     171: dup
     172: getstatic     #22                 // Field ROW:[B
     175: invokespecial #48                 // Method org/apache/hadoop/hbase/client/Get."<init>":([B)V
     178: getstatic     #7                  // Field FAMILY:[B
     181: getstatic     #42                 // Field QUALIFIER:[B
     184: invokevirtual #49                 // Method org/apache/hadoop/hbase/client/Get.addColumn:([B[B)Lorg/apache/hadoop/hbase/client/Get;
     187: invokeinterface #50,  2           // InterfaceMethod org/apache/hadoop/hbase/client/AsyncTable.get:(Lorg/apache/hadoop/hbase/client/Get;)Ljava/util/concurrent/CompletableFuture;
     192: invokevirtual #14                 // Method java/util/concurrent/CompletableFuture.get:()Ljava/lang/Object;
     195: checkcast     #51                 // class org/apache/hadoop/hbase/client/Result
     198: astore        4
     200: getstatic     #43                 // Field VALUE:[B
     203: aload         4
     205: getstatic     #7                  // Field FAMILY:[B
     208: getstatic     #42                 // Field QUALIFIER:[B
     211: invokevirtual #52                 // Method org/apache/hadoop/hbase/client/Result.getValue:([B[B)[B
     214: invokestatic  #53                 // Method org/junit/Assert.assertArrayEquals:([B[B)V
     217: return

  public void testMaxRetries() throws java.io.IOException, java.lang.InterruptedException;
    Code:
       0: getstatic     #18                 // Field CONN:Lorg/apache/hadoop/hbase/client/AsyncConnectionImpl;
       3: getfield      #60                 // Field org/apache/hadoop/hbase/client/AsyncConnectionImpl.callerFactory:Lorg/apache/hadoop/hbase/client/AsyncRpcRetryingCallerFactory;
       6: invokevirtual #61                 // Method org/apache/hadoop/hbase/client/AsyncRpcRetryingCallerFactory.single:()Lorg/apache/hadoop/hbase/client/AsyncRpcRetryingCallerFactory$SingleRequestCallerBuilder;
       9: getstatic     #1                  // Field TABLE_NAME:Lorg/apache/hadoop/hbase/TableName;
      12: invokevirtual #62                 // Method org/apache/hadoop/hbase/client/AsyncRpcRetryingCallerFactory$SingleRequestCallerBuilder.table:(Lorg/apache/hadoop/hbase/TableName;)Lorg/apache/hadoop/hbase/client/AsyncRpcRetryingCallerFactory$SingleRequestCallerBuilder;
      15: getstatic     #22                 // Field ROW:[B
      18: invokevirtual #63                 // Method org/apache/hadoop/hbase/client/AsyncRpcRetryingCallerFactory$SingleRequestCallerBuilder.row:([B)Lorg/apache/hadoop/hbase/client/AsyncRpcRetryingCallerFactory$SingleRequestCallerBuilder;
      21: lconst_1
      22: getstatic     #64                 // Field java/util/concurrent/TimeUnit.DAYS:Ljava/util/concurrent/TimeUnit;
      25: invokevirtual #65                 // Method org/apache/hadoop/hbase/client/AsyncRpcRetryingCallerFactory$SingleRequestCallerBuilder.operationTimeout:(JLjava/util/concurrent/TimeUnit;)Lorg/apache/hadoop/hbase/client/AsyncRpcRetryingCallerFactory$SingleRequestCallerBuilder;
      28: iconst_3
      29: invokevirtual #66                 // Method org/apache/hadoop/hbase/client/AsyncRpcRetryingCallerFactory$SingleRequestCallerBuilder.maxAttempts:(I)Lorg/apache/hadoop/hbase/client/AsyncRpcRetryingCallerFactory$SingleRequestCallerBuilder;
      32: ldc2_w        #67                 // long 10l
      35: getstatic     #36                 // Field java/util/concurrent/TimeUnit.MILLISECONDS:Ljava/util/concurrent/TimeUnit;
      38: invokevirtual #69                 // Method org/apache/hadoop/hbase/client/AsyncRpcRetryingCallerFactory$SingleRequestCallerBuilder.pause:(JLjava/util/concurrent/TimeUnit;)Lorg/apache/hadoop/hbase/client/AsyncRpcRetryingCallerFactory$SingleRequestCallerBuilder;
      41: aload_0
      42: invokedynamic #70,  0             // InvokeDynamic #0:call:(Lorg/apache/hadoop/hbase/client/TestAsyncSingleRequestRpcRetryingCaller;)Lorg/apache/hadoop/hbase/client/AsyncSingleRequestRpcRetryingCaller$Callable;
      47: invokevirtual #71                 // Method org/apache/hadoop/hbase/client/AsyncRpcRetryingCallerFactory$SingleRequestCallerBuilder.action:(Lorg/apache/hadoop/hbase/client/AsyncSingleRequestRpcRetryingCaller$Callable;)Lorg/apache/hadoop/hbase/client/AsyncRpcRetryingCallerFactory$SingleRequestCallerBuilder;
      50: invokevirtual #72                 // Method org/apache/hadoop/hbase/client/AsyncRpcRetryingCallerFactory$SingleRequestCallerBuilder.call:()Ljava/util/concurrent/CompletableFuture;
      53: invokevirtual #14                 // Method java/util/concurrent/CompletableFuture.get:()Ljava/lang/Object;
      56: pop
      57: invokestatic  #73                 // Method org/junit/Assert.fail:()V
      60: goto          76
      63: astore_1
      64: aload_1
      65: invokevirtual #75                 // Method java/util/concurrent/ExecutionException.getCause:()Ljava/lang/Throwable;
      68: ldc           #76                 // class org/apache/hadoop/hbase/client/RetriesExhaustedException
      70: invokestatic  #77                 // Method org/hamcrest/CoreMatchers.instanceOf:(Ljava/lang/Class;)Lorg/hamcrest/Matcher;
      73: invokestatic  #78                 // Method org/junit/Assert.assertThat:(Ljava/lang/Object;Lorg/hamcrest/Matcher;)V
      76: return
    Exception table:
       from    to  target type
           0    60    63   Class java/util/concurrent/ExecutionException

  public void testOperationTimeout() throws java.io.IOException, java.lang.InterruptedException;
    Code:
       0: invokestatic  #79                 // Method java/lang/System.nanoTime:()J
       3: lstore_1
       4: getstatic     #18                 // Field CONN:Lorg/apache/hadoop/hbase/client/AsyncConnectionImpl;
       7: getfield      #60                 // Field org/apache/hadoop/hbase/client/AsyncConnectionImpl.callerFactory:Lorg/apache/hadoop/hbase/client/AsyncRpcRetryingCallerFactory;
      10: invokevirtual #61                 // Method org/apache/hadoop/hbase/client/AsyncRpcRetryingCallerFactory.single:()Lorg/apache/hadoop/hbase/client/AsyncRpcRetryingCallerFactory$SingleRequestCallerBuilder;
      13: getstatic     #1                  // Field TABLE_NAME:Lorg/apache/hadoop/hbase/TableName;
      16: invokevirtual #62                 // Method org/apache/hadoop/hbase/client/AsyncRpcRetryingCallerFactory$SingleRequestCallerBuilder.table:(Lorg/apache/hadoop/hbase/TableName;)Lorg/apache/hadoop/hbase/client/AsyncRpcRetryingCallerFactory$SingleRequestCallerBuilder;
      19: getstatic     #22                 // Field ROW:[B
      22: invokevirtual #63                 // Method org/apache/hadoop/hbase/client/AsyncRpcRetryingCallerFactory$SingleRequestCallerBuilder.row:([B)Lorg/apache/hadoop/hbase/client/AsyncRpcRetryingCallerFactory$SingleRequestCallerBuilder;
      25: lconst_1
      26: getstatic     #80                 // Field java/util/concurrent/TimeUnit.SECONDS:Ljava/util/concurrent/TimeUnit;
      29: invokevirtual #65                 // Method org/apache/hadoop/hbase/client/AsyncRpcRetryingCallerFactory$SingleRequestCallerBuilder.operationTimeout:(JLjava/util/concurrent/TimeUnit;)Lorg/apache/hadoop/hbase/client/AsyncRpcRetryingCallerFactory$SingleRequestCallerBuilder;
      32: ldc2_w        #34                 // long 100l
      35: getstatic     #36                 // Field java/util/concurrent/TimeUnit.MILLISECONDS:Ljava/util/concurrent/TimeUnit;
      38: invokevirtual #69                 // Method org/apache/hadoop/hbase/client/AsyncRpcRetryingCallerFactory$SingleRequestCallerBuilder.pause:(JLjava/util/concurrent/TimeUnit;)Lorg/apache/hadoop/hbase/client/AsyncRpcRetryingCallerFactory$SingleRequestCallerBuilder;
      41: ldc           #82                 // int 2147483647
      43: invokevirtual #66                 // Method org/apache/hadoop/hbase/client/AsyncRpcRetryingCallerFactory$SingleRequestCallerBuilder.maxAttempts:(I)Lorg/apache/hadoop/hbase/client/AsyncRpcRetryingCallerFactory$SingleRequestCallerBuilder;
      46: aload_0
      47: invokedynamic #83,  0             // InvokeDynamic #1:call:(Lorg/apache/hadoop/hbase/client/TestAsyncSingleRequestRpcRetryingCaller;)Lorg/apache/hadoop/hbase/client/AsyncSingleRequestRpcRetryingCaller$Callable;
      52: invokevirtual #71                 // Method org/apache/hadoop/hbase/client/AsyncRpcRetryingCallerFactory$SingleRequestCallerBuilder.action:(Lorg/apache/hadoop/hbase/client/AsyncSingleRequestRpcRetryingCaller$Callable;)Lorg/apache/hadoop/hbase/client/AsyncRpcRetryingCallerFactory$SingleRequestCallerBuilder;
      55: invokevirtual #72                 // Method org/apache/hadoop/hbase/client/AsyncRpcRetryingCallerFactory$SingleRequestCallerBuilder.call:()Ljava/util/concurrent/CompletableFuture;
      58: invokevirtual #14                 // Method java/util/concurrent/CompletableFuture.get:()Ljava/lang/Object;
      61: pop
      62: invokestatic  #73                 // Method org/junit/Assert.fail:()V
      65: goto          85
      68: astore_3
      69: aload_3
      70: invokevirtual #84                 // Method java/util/concurrent/ExecutionException.printStackTrace:()V
      73: aload_3
      74: invokevirtual #75                 // Method java/util/concurrent/ExecutionException.getCause:()Ljava/lang/Throwable;
      77: ldc           #76                 // class org/apache/hadoop/hbase/client/RetriesExhaustedException
      79: invokestatic  #77                 // Method org/hamcrest/CoreMatchers.instanceOf:(Ljava/lang/Class;)Lorg/hamcrest/Matcher;
      82: invokestatic  #78                 // Method org/junit/Assert.assertThat:(Ljava/lang/Object;Lorg/hamcrest/Matcher;)V
      85: invokestatic  #79                 // Method java/lang/System.nanoTime:()J
      88: lload_1
      89: lsub
      90: lstore_3
      91: lload_3
      92: getstatic     #80                 // Field java/util/concurrent/TimeUnit.SECONDS:Ljava/util/concurrent/TimeUnit;
      95: lconst_1
      96: invokevirtual #85                 // Method java/util/concurrent/TimeUnit.toNanos:(J)J
      99: lcmp
     100: iflt          107
     103: iconst_1
     104: goto          108
     107: iconst_0
     108: invokestatic  #86                 // Method org/junit/Assert.assertTrue:(Z)V
     111: lload_3
     112: getstatic     #80                 // Field java/util/concurrent/TimeUnit.SECONDS:Ljava/util/concurrent/TimeUnit;
     115: ldc2_w        #87                 // long 2l
     118: invokevirtual #85                 // Method java/util/concurrent/TimeUnit.toNanos:(J)J
     121: lcmp
     122: ifge          129
     125: iconst_1
     126: goto          130
     129: iconst_0
     130: invokestatic  #86                 // Method org/junit/Assert.assertTrue:(Z)V
     133: return
    Exception table:
       from    to  target type
           4    65    68   Class java/util/concurrent/ExecutionException

  public void testLocateError() throws java.io.IOException, java.lang.InterruptedException, java.util.concurrent.ExecutionException;
    Code:
       0: new           #89                 // class java/util/concurrent/atomic/AtomicBoolean
       3: dup
       4: iconst_0
       5: invokespecial #90                 // Method java/util/concurrent/atomic/AtomicBoolean."<init>":(Z)V
       8: astore_1
       9: new           #91                 // class java/util/concurrent/atomic/AtomicInteger
      12: dup
      13: iconst_0
      14: invokespecial #92                 // Method java/util/concurrent/atomic/AtomicInteger."<init>":(I)V
      17: astore_2
      18: getstatic     #18                 // Field CONN:Lorg/apache/hadoop/hbase/client/AsyncConnectionImpl;
      21: getstatic     #1                  // Field TABLE_NAME:Lorg/apache/hadoop/hbase/TableName;
      24: invokevirtual #21                 // Method org/apache/hadoop/hbase/client/AsyncConnectionImpl.getRegionLocator:(Lorg/apache/hadoop/hbase/TableName;)Lorg/apache/hadoop/hbase/client/AsyncTableRegionLocator;
      27: getstatic     #22                 // Field ROW:[B
      30: invokeinterface #23,  2           // InterfaceMethod org/apache/hadoop/hbase/client/AsyncTableRegionLocator.getRegionLocation:([B)Ljava/util/concurrent/CompletableFuture;
      35: invokevirtual #14                 // Method java/util/concurrent/CompletableFuture.get:()Ljava/lang/Object;
      38: checkcast     #24                 // class org/apache/hadoop/hbase/HRegionLocation
      41: astore_3
      42: new           #93                 // class org/apache/hadoop/hbase/client/TestAsyncSingleRequestRpcRetryingCaller$1
      45: dup
      46: aload_0
      47: getstatic     #18                 // Field CONN:Lorg/apache/hadoop/hbase/client/AsyncConnectionImpl;
      50: getstatic     #94                 // Field org/apache/hadoop/hbase/client/AsyncConnectionImpl.RETRY_TIMER:Lorg/apache/hbase/thirdparty/io/netty/util/HashedWheelTimer;
      53: aload_2
      54: aload_1
      55: aload_3
      56: invokespecial #95                 // Method org/apache/hadoop/hbase/client/TestAsyncSingleRequestRpcRetryingCaller$1."<init>":(Lorg/apache/hadoop/hbase/client/TestAsyncSingleRequestRpcRetryingCaller;Lorg/apache/hadoop/hbase/client/AsyncConnectionImpl;Lorg/apache/hbase/thirdparty/io/netty/util/HashedWheelTimer;Ljava/util/concurrent/atomic/AtomicInteger;Ljava/util/concurrent/atomic/AtomicBoolean;Lorg/apache/hadoop/hbase/HRegionLocation;)V
      59: astore        4
      61: new           #96                 // class org/apache/hadoop/hbase/client/TestAsyncSingleRequestRpcRetryingCaller$2
      64: dup
      65: aload_0
      66: getstatic     #18                 // Field CONN:Lorg/apache/hadoop/hbase/client/AsyncConnectionImpl;
      69: invokevirtual #97                 // Method org/apache/hadoop/hbase/client/AsyncConnectionImpl.getConfiguration:()Lorg/apache/hadoop/conf/Configuration;
      72: getstatic     #18                 // Field CONN:Lorg/apache/hadoop/hbase/client/AsyncConnectionImpl;
      75: getfield      #98                 // Field org/apache/hadoop/hbase/client/AsyncConnectionImpl.registry:Lorg/apache/hadoop/hbase/client/AsyncRegistry;
      78: getstatic     #18                 // Field CONN:Lorg/apache/hadoop/hbase/client/AsyncConnectionImpl;
      81: getfield      #98                 // Field org/apache/hadoop/hbase/client/AsyncConnectionImpl.registry:Lorg/apache/hadoop/hbase/client/AsyncRegistry;
      84: invokeinterface #13,  1           // InterfaceMethod org/apache/hadoop/hbase/client/AsyncRegistry.getClusterId:()Ljava/util/concurrent/CompletableFuture;
      89: invokevirtual #14                 // Method java/util/concurrent/CompletableFuture.get:()Ljava/lang/Object;
      92: checkcast     #15                 // class java/lang/String
      95: invokestatic  #16                 // Method org/apache/hadoop/hbase/security/User.getCurrent:()Lorg/apache/hadoop/hbase/security/User;
      98: aload         4
     100: invokespecial #99                 // Method org/apache/hadoop/hbase/client/TestAsyncSingleRequestRpcRetryingCaller$2."<init>":(Lorg/apache/hadoop/hbase/client/TestAsyncSingleRequestRpcRetryingCaller;Lorg/apache/hadoop/conf/Configuration;Lorg/apache/hadoop/hbase/client/AsyncRegistry;Ljava/lang/String;Lorg/apache/hadoop/hbase/security/User;Lorg/apache/hadoop/hbase/client/AsyncRegionLocator;)V
     103: astore        5
     105: aconst_null
     106: astore        6
     108: aload         5
     110: getstatic     #1                  // Field TABLE_NAME:Lorg/apache/hadoop/hbase/TableName;
     113: invokevirtual #33                 // Method org/apache/hadoop/hbase/client/AsyncConnectionImpl.getTableBuilder:(Lorg/apache/hadoop/hbase/TableName;)Lorg/apache/hadoop/hbase/client/AsyncTableBuilder;
     116: ldc2_w        #34                 // long 100l
     119: getstatic     #36                 // Field java/util/concurrent/TimeUnit.MILLISECONDS:Ljava/util/concurrent/TimeUnit;
     122: invokeinterface #37,  4           // InterfaceMethod org/apache/hadoop/hbase/client/AsyncTableBuilder.setRetryPause:(JLjava/util/concurrent/TimeUnit;)Lorg/apache/hadoop/hbase/client/AsyncTableBuilder;
     127: iconst_5
     128: invokeinterface #38,  2           // InterfaceMethod org/apache/hadoop/hbase/client/AsyncTableBuilder.setMaxRetries:(I)Lorg/apache/hadoop/hbase/client/AsyncTableBuilder;
     133: invokeinterface #39,  1           // InterfaceMethod org/apache/hadoop/hbase/client/AsyncTableBuilder.build:()Lorg/apache/hadoop/hbase/client/AsyncTable;
     138: astore        7
     140: aload         7
     142: new           #40                 // class org/apache/hadoop/hbase/client/Put
     145: dup
     146: getstatic     #22                 // Field ROW:[B
     149: invokespecial #41                 // Method org/apache/hadoop/hbase/client/Put."<init>":([B)V
     152: getstatic     #7                  // Field FAMILY:[B
     155: getstatic     #42                 // Field QUALIFIER:[B
     158: getstatic     #43                 // Field VALUE:[B
     161: invokevirtual #44                 // Method org/apache/hadoop/hbase/client/Put.addColumn:([B[B[B)Lorg/apache/hadoop/hbase/client/Put;
     164: invokeinterface #45,  2           // InterfaceMethod org/apache/hadoop/hbase/client/AsyncTable.put:(Lorg/apache/hadoop/hbase/client/Put;)Ljava/util/concurrent/CompletableFuture;
     169: invokevirtual #14                 // Method java/util/concurrent/CompletableFuture.get:()Ljava/lang/Object;
     172: pop
     173: aload_1
     174: invokevirtual #100                // Method java/util/concurrent/atomic/AtomicBoolean.get:()Z
     177: invokestatic  #86                 // Method org/junit/Assert.assertTrue:(Z)V
     180: aload_1
     181: iconst_0
     182: invokevirtual #101                // Method java/util/concurrent/atomic/AtomicBoolean.set:(Z)V
     185: aload_2
     186: iconst_0
     187: invokevirtual #102                // Method java/util/concurrent/atomic/AtomicInteger.set:(I)V
     190: aload         7
     192: new           #47                 // class org/apache/hadoop/hbase/client/Get
     195: dup
     196: getstatic     #22                 // Field ROW:[B
     199: invokespecial #48                 // Method org/apache/hadoop/hbase/client/Get."<init>":([B)V
     202: getstatic     #7                  // Field FAMILY:[B
     205: getstatic     #42                 // Field QUALIFIER:[B
     208: invokevirtual #49                 // Method org/apache/hadoop/hbase/client/Get.addColumn:([B[B)Lorg/apache/hadoop/hbase/client/Get;
     211: invokeinterface #50,  2           // InterfaceMethod org/apache/hadoop/hbase/client/AsyncTable.get:(Lorg/apache/hadoop/hbase/client/Get;)Ljava/util/concurrent/CompletableFuture;
     216: invokevirtual #14                 // Method java/util/concurrent/CompletableFuture.get:()Ljava/lang/Object;
     219: checkcast     #51                 // class org/apache/hadoop/hbase/client/Result
     222: astore        8
     224: getstatic     #43                 // Field VALUE:[B
     227: aload         8
     229: getstatic     #7                  // Field FAMILY:[B
     232: getstatic     #42                 // Field QUALIFIER:[B
     235: invokevirtual #52                 // Method org/apache/hadoop/hbase/client/Result.getValue:([B[B)[B
     238: invokestatic  #53                 // Method org/junit/Assert.assertArrayEquals:([B[B)V
     241: aload_1
     242: invokevirtual #100                // Method java/util/concurrent/atomic/AtomicBoolean.get:()Z
     245: invokestatic  #86                 // Method org/junit/Assert.assertTrue:(Z)V
     248: aload         5
     250: ifnull        335
     253: aload         6
     255: ifnull        278
     258: aload         5
     260: invokevirtual #103                // Method org/apache/hadoop/hbase/client/AsyncConnectionImpl.close:()V
     263: goto          335
     266: astore        7
     268: aload         6
     270: aload         7
     272: invokevirtual #105                // Method java/lang/Throwable.addSuppressed:(Ljava/lang/Throwable;)V
     275: goto          335
     278: aload         5
     280: invokevirtual #103                // Method org/apache/hadoop/hbase/client/AsyncConnectionImpl.close:()V
     283: goto          335
     286: astore        7
     288: aload         7
     290: astore        6
     292: aload         7
     294: athrow
     295: astore        9
     297: aload         5
     299: ifnull        332
     302: aload         6
     304: ifnull        327
     307: aload         5
     309: invokevirtual #103                // Method org/apache/hadoop/hbase/client/AsyncConnectionImpl.close:()V
     312: goto          332
     315: astore        10
     317: aload         6
     319: aload         10
     321: invokevirtual #105                // Method java/lang/Throwable.addSuppressed:(Ljava/lang/Throwable;)V
     324: goto          332
     327: aload         5
     329: invokevirtual #103                // Method org/apache/hadoop/hbase/client/AsyncConnectionImpl.close:()V
     332: aload         9
     334: athrow
     335: return
    Exception table:
       from    to  target type
         258   263   266   Class java/lang/Throwable
         108   248   286   Class java/lang/Throwable
         108   248   295   any
         307   312   315   Class java/lang/Throwable
         286   297   295   any

  static org.apache.hadoop.hbase.TableName access$000();
    Code:
       0: getstatic     #1                  // Field TABLE_NAME:Lorg/apache/hadoop/hbase/TableName;
       3: areturn

  static {};
    Code:
       0: ldc           #107                // class org/apache/hadoop/hbase/client/TestAsyncSingleRequestRpcRetryingCaller
       2: invokestatic  #108                // Method org/apache/hadoop/hbase/HBaseClassTestRule.forClass:(Ljava/lang/Class;)Lorg/apache/hadoop/hbase/HBaseClassTestRule;
       5: putstatic     #109                // Field CLASS_RULE:Lorg/apache/hadoop/hbase/HBaseClassTestRule;
       8: new           #110                // class org/apache/hadoop/hbase/HBaseTestingUtility
      11: dup
      12: invokespecial #111                // Method org/apache/hadoop/hbase/HBaseTestingUtility."<init>":()V
      15: putstatic     #3                  // Field TEST_UTIL:Lorg/apache/hadoop/hbase/HBaseTestingUtility;
      18: ldc           #112                // String async
      20: invokestatic  #113                // Method org/apache/hadoop/hbase/TableName.valueOf:(Ljava/lang/String;)Lorg/apache/hadoop/hbase/TableName;
      23: putstatic     #1                  // Field TABLE_NAME:Lorg/apache/hadoop/hbase/TableName;
      26: ldc           #114                // String cf
      28: invokestatic  #115                // Method org/apache/hadoop/hbase/util/Bytes.toBytes:(Ljava/lang/String;)[B
      31: putstatic     #7                  // Field FAMILY:[B
      34: ldc           #116                // String cq
      36: invokestatic  #115                // Method org/apache/hadoop/hbase/util/Bytes.toBytes:(Ljava/lang/String;)[B
      39: putstatic     #42                 // Field QUALIFIER:[B
      42: ldc           #117                // String row
      44: invokestatic  #115                // Method org/apache/hadoop/hbase/util/Bytes.toBytes:(Ljava/lang/String;)[B
      47: putstatic     #22                 // Field ROW:[B
      50: ldc           #118                // String value
      52: invokestatic  #115                // Method org/apache/hadoop/hbase/util/Bytes.toBytes:(Ljava/lang/String;)[B
      55: putstatic     #43                 // Field VALUE:[B
      58: return
}
