Compiled from "TestProcedureCoordinator.java"
public class org.apache.hadoop.hbase.procedure.TestProcedureCoordinator {
  public static final org.apache.hadoop.hbase.HBaseClassTestRule CLASS_RULE;

  public org.apache.hadoop.hbase.procedure.TestProcedureCoordinator();
    Code:
       0: aload_0
       1: invokespecial #2                  // Method java/lang/Object."<init>":()V
       4: aload_0
       5: ldc           #3                  // class org/apache/hadoop/hbase/procedure/ProcedureCoordinatorRpcs
       7: invokestatic  #4                  // Method org/mockito/Mockito.mock:(Ljava/lang/Class;)Ljava/lang/Object;
      10: checkcast     #3                  // class org/apache/hadoop/hbase/procedure/ProcedureCoordinatorRpcs
      13: putfield      #5                  // Field controller:Lorg/apache/hadoop/hbase/procedure/ProcedureCoordinatorRpcs;
      16: aload_0
      17: ldc           #6                  // class org/apache/hadoop/hbase/procedure/Procedure
      19: invokestatic  #4                  // Method org/mockito/Mockito.mock:(Ljava/lang/Class;)Ljava/lang/Object;
      22: checkcast     #6                  // class org/apache/hadoop/hbase/procedure/Procedure
      25: putfield      #7                  // Field task:Lorg/apache/hadoop/hbase/procedure/Procedure;
      28: aload_0
      29: ldc           #8                  // class org/apache/hadoop/hbase/errorhandling/ForeignExceptionDispatcher
      31: invokestatic  #4                  // Method org/mockito/Mockito.mock:(Ljava/lang/Class;)Ljava/lang/Object;
      34: checkcast     #8                  // class org/apache/hadoop/hbase/errorhandling/ForeignExceptionDispatcher
      37: putfield      #9                  // Field monitor:Lorg/apache/hadoop/hbase/errorhandling/ForeignExceptionDispatcher;
      40: return

  public void resetTest() throws java.io.IOException;
    Code:
       0: iconst_3
       1: anewarray     #10                 // class java/lang/Object
       4: dup
       5: iconst_0
       6: aload_0
       7: getfield      #5                  // Field controller:Lorg/apache/hadoop/hbase/procedure/ProcedureCoordinatorRpcs;
      10: aastore
      11: dup
      12: iconst_1
      13: aload_0
      14: getfield      #7                  // Field task:Lorg/apache/hadoop/hbase/procedure/Procedure;
      17: aastore
      18: dup
      19: iconst_2
      20: aload_0
      21: getfield      #9                  // Field monitor:Lorg/apache/hadoop/hbase/errorhandling/ForeignExceptionDispatcher;
      24: aastore
      25: invokestatic  #11                 // Method org/mockito/Mockito.reset:([Ljava/lang/Object;)V
      28: aload_0
      29: getfield      #1                  // Field coordinator:Lorg/apache/hadoop/hbase/procedure/ProcedureCoordinator;
      32: ifnull        42
      35: aload_0
      36: getfield      #1                  // Field coordinator:Lorg/apache/hadoop/hbase/procedure/ProcedureCoordinator;
      39: invokevirtual #12                 // Method org/apache/hadoop/hbase/procedure/ProcedureCoordinator.close:()V
      42: return

  public void testThreadPoolSize() throws java.lang.Exception;
    Code:
       0: aload_0
       1: invokespecial #19                 // Method buildNewCoordinator:()Lorg/apache/hadoop/hbase/procedure/ProcedureCoordinator;
       4: astore_1
       5: new           #6                  // class org/apache/hadoop/hbase/procedure/Procedure
       8: dup
       9: aload_1
      10: aload_0
      11: getfield      #9                  // Field monitor:Lorg/apache/hadoop/hbase/errorhandling/ForeignExceptionDispatcher;
      14: ldc2_w        #20                 // long 1000l
      17: ldc2_w        #22                 // long 100000l
      20: ldc           #24                 // String some op
      22: getstatic     #25                 // Field procData:[B
      25: getstatic     #26                 // Field expected:Ljava/util/List;
      28: invokespecial #27                 // Method org/apache/hadoop/hbase/procedure/Procedure."<init>":(Lorg/apache/hadoop/hbase/procedure/ProcedureCoordinator;Lorg/apache/hadoop/hbase/errorhandling/ForeignExceptionDispatcher;JJLjava/lang/String;[BLjava/util/List;)V
      31: astore_2
      32: aload_2
      33: invokestatic  #18                 // Method org/mockito/Mockito.spy:(Ljava/lang/Object;)Ljava/lang/Object;
      36: checkcast     #6                  // class org/apache/hadoop/hbase/procedure/Procedure
      39: astore_3
      40: new           #6                  // class org/apache/hadoop/hbase/procedure/Procedure
      43: dup
      44: aload_1
      45: aload_0
      46: getfield      #9                  // Field monitor:Lorg/apache/hadoop/hbase/errorhandling/ForeignExceptionDispatcher;
      49: ldc2_w        #20                 // long 1000l
      52: ldc2_w        #22                 // long 100000l
      55: ldc           #28                 // String some op2
      57: getstatic     #25                 // Field procData:[B
      60: getstatic     #26                 // Field expected:Ljava/util/List;
      63: invokespecial #27                 // Method org/apache/hadoop/hbase/procedure/Procedure."<init>":(Lorg/apache/hadoop/hbase/procedure/ProcedureCoordinator;Lorg/apache/hadoop/hbase/errorhandling/ForeignExceptionDispatcher;JJLjava/lang/String;[BLjava/util/List;)V
      66: astore        4
      68: aload         4
      70: invokestatic  #18                 // Method org/mockito/Mockito.spy:(Ljava/lang/Object;)Ljava/lang/Object;
      73: checkcast     #6                  // class org/apache/hadoop/hbase/procedure/Procedure
      76: astore        5
      78: aload_1
      79: invokestatic  #29                 // Method org/mockito/Matchers.any:()Ljava/lang/Object;
      82: checkcast     #8                  // class org/apache/hadoop/hbase/errorhandling/ForeignExceptionDispatcher
      85: ldc           #24                 // String some op
      87: invokestatic  #30                 // Method org/mockito/Matchers.eq:(Ljava/lang/Object;)Ljava/lang/Object;
      90: checkcast     #31                 // class java/lang/String
      93: getstatic     #25                 // Field procData:[B
      96: invokestatic  #30                 // Method org/mockito/Matchers.eq:(Ljava/lang/Object;)Ljava/lang/Object;
      99: checkcast     #32                 // class "[B"
     102: ldc           #31                 // class java/lang/String
     104: invokestatic  #33                 // Method org/mockito/Matchers.anyListOf:(Ljava/lang/Class;)Ljava/util/List;
     107: invokevirtual #34                 // Method org/apache/hadoop/hbase/procedure/ProcedureCoordinator.createProcedure:(Lorg/apache/hadoop/hbase/errorhandling/ForeignExceptionDispatcher;Ljava/lang/String;[BLjava/util/List;)Lorg/apache/hadoop/hbase/procedure/Procedure;
     110: invokestatic  #35                 // Method org/mockito/Mockito.when:(Ljava/lang/Object;)Lorg/mockito/stubbing/OngoingStubbing;
     113: aload_3
     114: iconst_1
     115: anewarray     #6                  // class org/apache/hadoop/hbase/procedure/Procedure
     118: dup
     119: iconst_0
     120: aload         5
     122: aastore
     123: invokeinterface #36,  3           // InterfaceMethod org/mockito/stubbing/OngoingStubbing.thenReturn:(Ljava/lang/Object;[Ljava/lang/Object;)Lorg/mockito/stubbing/OngoingStubbing;
     128: pop
     129: aload_1
     130: aload_3
     131: invokevirtual #37                 // Method org/apache/hadoop/hbase/procedure/Procedure.getErrorMonitor:()Lorg/apache/hadoop/hbase/errorhandling/ForeignExceptionDispatcher;
     134: ldc           #24                 // String some op
     136: getstatic     #25                 // Field procData:[B
     139: getstatic     #26                 // Field expected:Ljava/util/List;
     142: invokevirtual #38                 // Method org/apache/hadoop/hbase/procedure/ProcedureCoordinator.startProcedure:(Lorg/apache/hadoop/hbase/errorhandling/ForeignExceptionDispatcher;Ljava/lang/String;[BLjava/util/List;)Lorg/apache/hadoop/hbase/procedure/Procedure;
     145: pop
     146: ldc           #39                 // String Coordinator successfully ran two tasks at once with a single thread pool.
     148: aload_1
     149: aload         4
     151: invokevirtual #37                 // Method org/apache/hadoop/hbase/procedure/Procedure.getErrorMonitor:()Lorg/apache/hadoop/hbase/errorhandling/ForeignExceptionDispatcher;
     154: ldc           #40                 // String another op
     156: getstatic     #25                 // Field procData:[B
     159: getstatic     #26                 // Field expected:Ljava/util/List;
     162: invokevirtual #38                 // Method org/apache/hadoop/hbase/procedure/ProcedureCoordinator.startProcedure:(Lorg/apache/hadoop/hbase/errorhandling/ForeignExceptionDispatcher;Ljava/lang/String;[BLjava/util/List;)Lorg/apache/hadoop/hbase/procedure/Procedure;
     165: invokestatic  #41                 // Method org/junit/Assert.assertNull:(Ljava/lang/String;Ljava/lang/Object;)V
     168: return

  public void testUnreachableControllerDuringPrepare() throws java.lang.Exception;
    Code:
       0: aload_0
       1: aload_0
       2: invokespecial #19                 // Method buildNewCoordinator:()Lorg/apache/hadoop/hbase/procedure/ProcedureCoordinator;
       5: putfield      #1                  // Field coordinator:Lorg/apache/hadoop/hbase/procedure/ProcedureCoordinator;
       8: iconst_1
       9: anewarray     #31                 // class java/lang/String
      12: dup
      13: iconst_0
      14: ldc           #42                 // String cohort
      16: aastore
      17: invokestatic  #43                 // Method java/util/Arrays.asList:([Ljava/lang/Object;)Ljava/util/List;
      20: astore_1
      21: new           #6                  // class org/apache/hadoop/hbase/procedure/Procedure
      24: dup
      25: aload_0
      26: getfield      #1                  // Field coordinator:Lorg/apache/hadoop/hbase/procedure/ProcedureCoordinator;
      29: ldc2_w        #20                 // long 1000l
      32: ldc2_w        #22                 // long 100000l
      35: ldc           #24                 // String some op
      37: getstatic     #25                 // Field procData:[B
      40: aload_1
      41: invokespecial #44                 // Method org/apache/hadoop/hbase/procedure/Procedure."<init>":(Lorg/apache/hadoop/hbase/procedure/ProcedureCoordinator;JJLjava/lang/String;[BLjava/util/List;)V
      44: astore_2
      45: aload_2
      46: invokestatic  #18                 // Method org/mockito/Mockito.spy:(Ljava/lang/Object;)Ljava/lang/Object;
      49: checkcast     #6                  // class org/apache/hadoop/hbase/procedure/Procedure
      52: astore_3
      53: aload_0
      54: getfield      #1                  // Field coordinator:Lorg/apache/hadoop/hbase/procedure/ProcedureCoordinator;
      57: invokestatic  #29                 // Method org/mockito/Matchers.any:()Ljava/lang/Object;
      60: checkcast     #8                  // class org/apache/hadoop/hbase/errorhandling/ForeignExceptionDispatcher
      63: ldc           #24                 // String some op
      65: invokestatic  #30                 // Method org/mockito/Matchers.eq:(Ljava/lang/Object;)Ljava/lang/Object;
      68: checkcast     #31                 // class java/lang/String
      71: getstatic     #25                 // Field procData:[B
      74: invokestatic  #30                 // Method org/mockito/Matchers.eq:(Ljava/lang/Object;)Ljava/lang/Object;
      77: checkcast     #32                 // class "[B"
      80: ldc           #31                 // class java/lang/String
      82: invokestatic  #33                 // Method org/mockito/Matchers.anyListOf:(Ljava/lang/Class;)Ljava/util/List;
      85: invokevirtual #34                 // Method org/apache/hadoop/hbase/procedure/ProcedureCoordinator.createProcedure:(Lorg/apache/hadoop/hbase/errorhandling/ForeignExceptionDispatcher;Ljava/lang/String;[BLjava/util/List;)Lorg/apache/hadoop/hbase/procedure/Procedure;
      88: invokestatic  #35                 // Method org/mockito/Mockito.when:(Ljava/lang/Object;)Lorg/mockito/stubbing/OngoingStubbing;
      91: aload_3
      92: invokeinterface #45,  2           // InterfaceMethod org/mockito/stubbing/OngoingStubbing.thenReturn:(Ljava/lang/Object;)Lorg/mockito/stubbing/OngoingStubbing;
      97: pop
      98: new           #46                 // class java/io/IOException
     101: dup
     102: ldc           #47                 // String Failed to reach comms during acquire
     104: invokespecial #48                 // Method java/io/IOException."<init>":(Ljava/lang/String;)V
     107: astore        4
     109: iconst_1
     110: anewarray     #49                 // class java/lang/Throwable
     113: dup
     114: iconst_0
     115: aload         4
     117: aastore
     118: invokestatic  #50                 // Method org/mockito/Mockito.doThrow:([Ljava/lang/Throwable;)Lorg/mockito/stubbing/Stubber;
     121: aload_0
     122: getfield      #5                  // Field controller:Lorg/apache/hadoop/hbase/procedure/ProcedureCoordinatorRpcs;
     125: invokeinterface #51,  2           // InterfaceMethod org/mockito/stubbing/Stubber.when:(Ljava/lang/Object;)Ljava/lang/Object;
     130: checkcast     #3                  // class org/apache/hadoop/hbase/procedure/ProcedureCoordinatorRpcs
     133: aload_3
     134: invokestatic  #30                 // Method org/mockito/Matchers.eq:(Ljava/lang/Object;)Ljava/lang/Object;
     137: checkcast     #6                  // class org/apache/hadoop/hbase/procedure/Procedure
     140: getstatic     #25                 // Field procData:[B
     143: invokestatic  #30                 // Method org/mockito/Matchers.eq:(Ljava/lang/Object;)Ljava/lang/Object;
     146: checkcast     #32                 // class "[B"
     149: ldc           #31                 // class java/lang/String
     151: invokestatic  #33                 // Method org/mockito/Matchers.anyListOf:(Ljava/lang/Class;)Ljava/util/List;
     154: invokeinterface #52,  4           // InterfaceMethod org/apache/hadoop/hbase/procedure/ProcedureCoordinatorRpcs.sendGlobalBarrierAcquire:(Lorg/apache/hadoop/hbase/procedure/Procedure;[BLjava/util/List;)V
     159: aload_0
     160: getfield      #1                  // Field coordinator:Lorg/apache/hadoop/hbase/procedure/ProcedureCoordinator;
     163: aload_2
     164: invokevirtual #37                 // Method org/apache/hadoop/hbase/procedure/Procedure.getErrorMonitor:()Lorg/apache/hadoop/hbase/errorhandling/ForeignExceptionDispatcher;
     167: ldc           #24                 // String some op
     169: getstatic     #25                 // Field procData:[B
     172: aload_1
     173: invokevirtual #38                 // Method org/apache/hadoop/hbase/procedure/ProcedureCoordinator.startProcedure:(Lorg/apache/hadoop/hbase/errorhandling/ForeignExceptionDispatcher;Ljava/lang/String;[BLjava/util/List;)Lorg/apache/hadoop/hbase/procedure/Procedure;
     176: astore_2
     177: aload_2
     178: getfield      #53                 // Field org/apache/hadoop/hbase/procedure/Procedure.completedLatch:Ljava/util/concurrent/CountDownLatch;
     181: ldc2_w        #20                 // long 1000l
     184: getstatic     #54                 // Field java/util/concurrent/TimeUnit.MILLISECONDS:Ljava/util/concurrent/TimeUnit;
     187: invokevirtual #55                 // Method java/util/concurrent/CountDownLatch.await:(JLjava/util/concurrent/TimeUnit;)Z
     190: ifne          196
     193: goto          177
     196: aload_3
     197: invokestatic  #56                 // Method org/mockito/Mockito.atLeastOnce:()Lorg/mockito/verification/VerificationMode;
     200: invokestatic  #57                 // Method org/mockito/Mockito.verify:(Ljava/lang/Object;Lorg/mockito/verification/VerificationMode;)Ljava/lang/Object;
     203: checkcast     #6                  // class org/apache/hadoop/hbase/procedure/Procedure
     206: invokestatic  #29                 // Method org/mockito/Matchers.any:()Ljava/lang/Object;
     209: checkcast     #58                 // class org/apache/hadoop/hbase/errorhandling/ForeignException
     212: invokevirtual #59                 // Method org/apache/hadoop/hbase/procedure/Procedure.receive:(Lorg/apache/hadoop/hbase/errorhandling/ForeignException;)V
     215: aload_0
     216: getfield      #1                  // Field coordinator:Lorg/apache/hadoop/hbase/procedure/ProcedureCoordinator;
     219: iconst_1
     220: invokestatic  #60                 // Method org/mockito/Mockito.times:(I)Lorg/mockito/verification/VerificationMode;
     223: invokestatic  #57                 // Method org/mockito/Mockito.verify:(Ljava/lang/Object;Lorg/mockito/verification/VerificationMode;)Ljava/lang/Object;
     226: checkcast     #16                 // class org/apache/hadoop/hbase/procedure/ProcedureCoordinator
     229: invokestatic  #61                 // Method org/mockito/Matchers.anyString:()Ljava/lang/String;
     232: aload         4
     234: invokestatic  #30                 // Method org/mockito/Matchers.eq:(Ljava/lang/Object;)Ljava/lang/Object;
     237: checkcast     #46                 // class java/io/IOException
     240: invokevirtual #62                 // Method org/apache/hadoop/hbase/procedure/ProcedureCoordinator.rpcConnectionFailure:(Ljava/lang/String;Ljava/io/IOException;)V
     243: aload_0
     244: getfield      #5                  // Field controller:Lorg/apache/hadoop/hbase/procedure/ProcedureCoordinatorRpcs;
     247: iconst_1
     248: invokestatic  #60                 // Method org/mockito/Mockito.times:(I)Lorg/mockito/verification/VerificationMode;
     251: invokestatic  #57                 // Method org/mockito/Mockito.verify:(Ljava/lang/Object;Lorg/mockito/verification/VerificationMode;)Ljava/lang/Object;
     254: checkcast     #3                  // class org/apache/hadoop/hbase/procedure/ProcedureCoordinatorRpcs
     257: aload_3
     258: getstatic     #25                 // Field procData:[B
     261: aload_1
     262: invokeinterface #52,  4           // InterfaceMethod org/apache/hadoop/hbase/procedure/ProcedureCoordinatorRpcs.sendGlobalBarrierAcquire:(Lorg/apache/hadoop/hbase/procedure/Procedure;[BLjava/util/List;)V
     267: aload_0
     268: getfield      #5                  // Field controller:Lorg/apache/hadoop/hbase/procedure/ProcedureCoordinatorRpcs;
     271: invokestatic  #63                 // Method org/mockito/Mockito.never:()Lorg/mockito/verification/VerificationMode;
     274: invokestatic  #57                 // Method org/mockito/Mockito.verify:(Ljava/lang/Object;Lorg/mockito/verification/VerificationMode;)Ljava/lang/Object;
     277: checkcast     #3                  // class org/apache/hadoop/hbase/procedure/ProcedureCoordinatorRpcs
     280: invokestatic  #29                 // Method org/mockito/Matchers.any:()Ljava/lang/Object;
     283: checkcast     #6                  // class org/apache/hadoop/hbase/procedure/Procedure
     286: ldc           #31                 // class java/lang/String
     288: invokestatic  #33                 // Method org/mockito/Matchers.anyListOf:(Ljava/lang/Class;)Ljava/util/List;
     291: invokeinterface #64,  3           // InterfaceMethod org/apache/hadoop/hbase/procedure/ProcedureCoordinatorRpcs.sendGlobalBarrierReached:(Lorg/apache/hadoop/hbase/procedure/Procedure;Ljava/util/List;)V
     296: return

  public void testUnreachableControllerDuringCommit() throws java.lang.Exception;
    Code:
       0: aload_0
       1: aload_0
       2: invokespecial #19                 // Method buildNewCoordinator:()Lorg/apache/hadoop/hbase/procedure/ProcedureCoordinator;
       5: putfield      #1                  // Field coordinator:Lorg/apache/hadoop/hbase/procedure/ProcedureCoordinator;
       8: iconst_1
       9: anewarray     #31                 // class java/lang/String
      12: dup
      13: iconst_0
      14: ldc           #42                 // String cohort
      16: aastore
      17: invokestatic  #43                 // Method java/util/Arrays.asList:([Ljava/lang/Object;)Ljava/util/List;
      20: astore_1
      21: new           #6                  // class org/apache/hadoop/hbase/procedure/Procedure
      24: dup
      25: aload_0
      26: getfield      #1                  // Field coordinator:Lorg/apache/hadoop/hbase/procedure/ProcedureCoordinator;
      29: ldc2_w        #20                 // long 1000l
      32: ldc2_w        #22                 // long 100000l
      35: ldc           #24                 // String some op
      37: getstatic     #25                 // Field procData:[B
      40: aload_1
      41: invokespecial #44                 // Method org/apache/hadoop/hbase/procedure/Procedure."<init>":(Lorg/apache/hadoop/hbase/procedure/ProcedureCoordinator;JJLjava/lang/String;[BLjava/util/List;)V
      44: invokestatic  #18                 // Method org/mockito/Mockito.spy:(Ljava/lang/Object;)Ljava/lang/Object;
      47: checkcast     #6                  // class org/apache/hadoop/hbase/procedure/Procedure
      50: astore_2
      51: aload_0
      52: getfield      #1                  // Field coordinator:Lorg/apache/hadoop/hbase/procedure/ProcedureCoordinator;
      55: invokestatic  #29                 // Method org/mockito/Matchers.any:()Ljava/lang/Object;
      58: checkcast     #8                  // class org/apache/hadoop/hbase/errorhandling/ForeignExceptionDispatcher
      61: ldc           #24                 // String some op
      63: invokestatic  #30                 // Method org/mockito/Matchers.eq:(Ljava/lang/Object;)Ljava/lang/Object;
      66: checkcast     #31                 // class java/lang/String
      69: getstatic     #25                 // Field procData:[B
      72: invokestatic  #30                 // Method org/mockito/Matchers.eq:(Ljava/lang/Object;)Ljava/lang/Object;
      75: checkcast     #32                 // class "[B"
      78: ldc           #31                 // class java/lang/String
      80: invokestatic  #33                 // Method org/mockito/Matchers.anyListOf:(Ljava/lang/Class;)Ljava/util/List;
      83: invokevirtual #34                 // Method org/apache/hadoop/hbase/procedure/ProcedureCoordinator.createProcedure:(Lorg/apache/hadoop/hbase/errorhandling/ForeignExceptionDispatcher;Ljava/lang/String;[BLjava/util/List;)Lorg/apache/hadoop/hbase/procedure/Procedure;
      86: invokestatic  #35                 // Method org/mockito/Mockito.when:(Ljava/lang/Object;)Lorg/mockito/stubbing/OngoingStubbing;
      89: aload_2
      90: invokeinterface #45,  2           // InterfaceMethod org/mockito/stubbing/OngoingStubbing.thenReturn:(Ljava/lang/Object;)Lorg/mockito/stubbing/OngoingStubbing;
      95: pop
      96: new           #46                 // class java/io/IOException
      99: dup
     100: ldc           #65                 // String Failed to reach controller during prepare
     102: invokespecial #48                 // Method java/io/IOException."<init>":(Ljava/lang/String;)V
     105: astore_3
     106: new           #66                 // class org/apache/hadoop/hbase/procedure/TestProcedureCoordinator$AcquireBarrierAnswer
     109: dup
     110: aload_0
     111: ldc           #24                 // String some op
     113: iconst_1
     114: anewarray     #31                 // class java/lang/String
     117: dup
     118: iconst_0
     119: ldc           #42                 // String cohort
     121: aastore
     122: invokespecial #67                 // Method org/apache/hadoop/hbase/procedure/TestProcedureCoordinator$AcquireBarrierAnswer."<init>":(Lorg/apache/hadoop/hbase/procedure/TestProcedureCoordinator;Ljava/lang/String;[Ljava/lang/String;)V
     125: invokestatic  #68                 // Method org/mockito/Mockito.doAnswer:(Lorg/mockito/stubbing/Answer;)Lorg/mockito/stubbing/Stubber;
     128: aload_0
     129: getfield      #5                  // Field controller:Lorg/apache/hadoop/hbase/procedure/ProcedureCoordinatorRpcs;
     132: invokeinterface #51,  2           // InterfaceMethod org/mockito/stubbing/Stubber.when:(Ljava/lang/Object;)Ljava/lang/Object;
     137: checkcast     #3                  // class org/apache/hadoop/hbase/procedure/ProcedureCoordinatorRpcs
     140: aload_2
     141: invokestatic  #30                 // Method org/mockito/Matchers.eq:(Ljava/lang/Object;)Ljava/lang/Object;
     144: checkcast     #6                  // class org/apache/hadoop/hbase/procedure/Procedure
     147: getstatic     #25                 // Field procData:[B
     150: invokestatic  #30                 // Method org/mockito/Matchers.eq:(Ljava/lang/Object;)Ljava/lang/Object;
     153: checkcast     #32                 // class "[B"
     156: ldc           #31                 // class java/lang/String
     158: invokestatic  #33                 // Method org/mockito/Matchers.anyListOf:(Ljava/lang/Class;)Ljava/util/List;
     161: invokeinterface #52,  4           // InterfaceMethod org/apache/hadoop/hbase/procedure/ProcedureCoordinatorRpcs.sendGlobalBarrierAcquire:(Lorg/apache/hadoop/hbase/procedure/Procedure;[BLjava/util/List;)V
     166: iconst_1
     167: anewarray     #49                 // class java/lang/Throwable
     170: dup
     171: iconst_0
     172: aload_3
     173: aastore
     174: invokestatic  #50                 // Method org/mockito/Mockito.doThrow:([Ljava/lang/Throwable;)Lorg/mockito/stubbing/Stubber;
     177: aload_0
     178: getfield      #5                  // Field controller:Lorg/apache/hadoop/hbase/procedure/ProcedureCoordinatorRpcs;
     181: invokeinterface #51,  2           // InterfaceMethod org/mockito/stubbing/Stubber.when:(Ljava/lang/Object;)Ljava/lang/Object;
     186: checkcast     #3                  // class org/apache/hadoop/hbase/procedure/ProcedureCoordinatorRpcs
     189: aload_2
     190: invokestatic  #30                 // Method org/mockito/Matchers.eq:(Ljava/lang/Object;)Ljava/lang/Object;
     193: checkcast     #6                  // class org/apache/hadoop/hbase/procedure/Procedure
     196: ldc           #31                 // class java/lang/String
     198: invokestatic  #33                 // Method org/mockito/Matchers.anyListOf:(Ljava/lang/Class;)Ljava/util/List;
     201: invokeinterface #64,  3           // InterfaceMethod org/apache/hadoop/hbase/procedure/ProcedureCoordinatorRpcs.sendGlobalBarrierReached:(Lorg/apache/hadoop/hbase/procedure/Procedure;Ljava/util/List;)V
     206: aload_0
     207: getfield      #1                  // Field coordinator:Lorg/apache/hadoop/hbase/procedure/ProcedureCoordinator;
     210: aload_2
     211: invokevirtual #37                 // Method org/apache/hadoop/hbase/procedure/Procedure.getErrorMonitor:()Lorg/apache/hadoop/hbase/errorhandling/ForeignExceptionDispatcher;
     214: ldc           #24                 // String some op
     216: getstatic     #25                 // Field procData:[B
     219: aload_1
     220: invokevirtual #38                 // Method org/apache/hadoop/hbase/procedure/ProcedureCoordinator.startProcedure:(Lorg/apache/hadoop/hbase/errorhandling/ForeignExceptionDispatcher;Ljava/lang/String;[BLjava/util/List;)Lorg/apache/hadoop/hbase/procedure/Procedure;
     223: astore        4
     225: aload         4
     227: getfield      #53                 // Field org/apache/hadoop/hbase/procedure/Procedure.completedLatch:Ljava/util/concurrent/CountDownLatch;
     230: ldc2_w        #20                 // long 1000l
     233: getstatic     #54                 // Field java/util/concurrent/TimeUnit.MILLISECONDS:Ljava/util/concurrent/TimeUnit;
     236: invokevirtual #55                 // Method java/util/concurrent/CountDownLatch.await:(JLjava/util/concurrent/TimeUnit;)Z
     239: ifne          245
     242: goto          225
     245: aload_2
     246: invokestatic  #56                 // Method org/mockito/Mockito.atLeastOnce:()Lorg/mockito/verification/VerificationMode;
     249: invokestatic  #57                 // Method org/mockito/Mockito.verify:(Ljava/lang/Object;Lorg/mockito/verification/VerificationMode;)Ljava/lang/Object;
     252: checkcast     #6                  // class org/apache/hadoop/hbase/procedure/Procedure
     255: invokestatic  #29                 // Method org/mockito/Matchers.any:()Ljava/lang/Object;
     258: checkcast     #58                 // class org/apache/hadoop/hbase/errorhandling/ForeignException
     261: invokevirtual #59                 // Method org/apache/hadoop/hbase/procedure/Procedure.receive:(Lorg/apache/hadoop/hbase/errorhandling/ForeignException;)V
     264: aload_0
     265: getfield      #1                  // Field coordinator:Lorg/apache/hadoop/hbase/procedure/ProcedureCoordinator;
     268: iconst_1
     269: invokestatic  #60                 // Method org/mockito/Mockito.times:(I)Lorg/mockito/verification/VerificationMode;
     272: invokestatic  #57                 // Method org/mockito/Mockito.verify:(Ljava/lang/Object;Lorg/mockito/verification/VerificationMode;)Ljava/lang/Object;
     275: checkcast     #16                 // class org/apache/hadoop/hbase/procedure/ProcedureCoordinator
     278: invokestatic  #61                 // Method org/mockito/Matchers.anyString:()Ljava/lang/String;
     281: aload_3
     282: invokestatic  #30                 // Method org/mockito/Matchers.eq:(Ljava/lang/Object;)Ljava/lang/Object;
     285: checkcast     #46                 // class java/io/IOException
     288: invokevirtual #62                 // Method org/apache/hadoop/hbase/procedure/ProcedureCoordinator.rpcConnectionFailure:(Ljava/lang/String;Ljava/io/IOException;)V
     291: aload_0
     292: getfield      #5                  // Field controller:Lorg/apache/hadoop/hbase/procedure/ProcedureCoordinatorRpcs;
     295: iconst_1
     296: invokestatic  #60                 // Method org/mockito/Mockito.times:(I)Lorg/mockito/verification/VerificationMode;
     299: invokestatic  #57                 // Method org/mockito/Mockito.verify:(Ljava/lang/Object;Lorg/mockito/verification/VerificationMode;)Ljava/lang/Object;
     302: checkcast     #3                  // class org/apache/hadoop/hbase/procedure/ProcedureCoordinatorRpcs
     305: aload_2
     306: invokestatic  #30                 // Method org/mockito/Matchers.eq:(Ljava/lang/Object;)Ljava/lang/Object;
     309: checkcast     #6                  // class org/apache/hadoop/hbase/procedure/Procedure
     312: getstatic     #25                 // Field procData:[B
     315: invokestatic  #30                 // Method org/mockito/Matchers.eq:(Ljava/lang/Object;)Ljava/lang/Object;
     318: checkcast     #32                 // class "[B"
     321: ldc           #31                 // class java/lang/String
     323: invokestatic  #33                 // Method org/mockito/Matchers.anyListOf:(Ljava/lang/Class;)Ljava/util/List;
     326: invokeinterface #52,  4           // InterfaceMethod org/apache/hadoop/hbase/procedure/ProcedureCoordinatorRpcs.sendGlobalBarrierAcquire:(Lorg/apache/hadoop/hbase/procedure/Procedure;[BLjava/util/List;)V
     331: aload_0
     332: getfield      #5                  // Field controller:Lorg/apache/hadoop/hbase/procedure/ProcedureCoordinatorRpcs;
     335: iconst_1
     336: invokestatic  #60                 // Method org/mockito/Mockito.times:(I)Lorg/mockito/verification/VerificationMode;
     339: invokestatic  #57                 // Method org/mockito/Mockito.verify:(Ljava/lang/Object;Lorg/mockito/verification/VerificationMode;)Ljava/lang/Object;
     342: checkcast     #3                  // class org/apache/hadoop/hbase/procedure/ProcedureCoordinatorRpcs
     345: invokestatic  #29                 // Method org/mockito/Matchers.any:()Ljava/lang/Object;
     348: checkcast     #6                  // class org/apache/hadoop/hbase/procedure/Procedure
     351: ldc           #31                 // class java/lang/String
     353: invokestatic  #33                 // Method org/mockito/Matchers.anyListOf:(Ljava/lang/Class;)Ljava/util/List;
     356: invokeinterface #64,  3           // InterfaceMethod org/apache/hadoop/hbase/procedure/ProcedureCoordinatorRpcs.sendGlobalBarrierReached:(Lorg/apache/hadoop/hbase/procedure/Procedure;Ljava/util/List;)V
     361: return

  public void testNoCohort() throws java.lang.Exception;
    Code:
       0: aload_0
       1: iconst_0
       2: anewarray     #31                 // class java/lang/String
       5: invokevirtual #69                 // Method runSimpleProcedure:([Ljava/lang/String;)V
       8: return

  public void testSingleCohortOrchestration() throws java.lang.Exception;
    Code:
       0: aload_0
       1: iconst_1
       2: anewarray     #31                 // class java/lang/String
       5: dup
       6: iconst_0
       7: ldc           #70                 // String one
       9: aastore
      10: invokevirtual #69                 // Method runSimpleProcedure:([Ljava/lang/String;)V
      13: return

  public void testMultipleCohortOrchestration() throws java.lang.Exception;
    Code:
       0: aload_0
       1: iconst_4
       2: anewarray     #31                 // class java/lang/String
       5: dup
       6: iconst_0
       7: ldc           #70                 // String one
       9: aastore
      10: dup
      11: iconst_1
      12: ldc           #71                 // String two
      14: aastore
      15: dup
      16: iconst_2
      17: ldc           #72                 // String three
      19: aastore
      20: dup
      21: iconst_3
      22: ldc           #73                 // String four
      24: aastore
      25: invokevirtual #69                 // Method runSimpleProcedure:([Ljava/lang/String;)V
      28: return

  public void runSimpleProcedure(java.lang.String...) throws java.lang.Exception;
    Code:
       0: aload_0
       1: aload_0
       2: invokespecial #19                 // Method buildNewCoordinator:()Lorg/apache/hadoop/hbase/procedure/ProcedureCoordinator;
       5: putfield      #1                  // Field coordinator:Lorg/apache/hadoop/hbase/procedure/ProcedureCoordinator;
       8: new           #6                  // class org/apache/hadoop/hbase/procedure/Procedure
      11: dup
      12: aload_0
      13: getfield      #1                  // Field coordinator:Lorg/apache/hadoop/hbase/procedure/ProcedureCoordinator;
      16: aload_0
      17: getfield      #9                  // Field monitor:Lorg/apache/hadoop/hbase/errorhandling/ForeignExceptionDispatcher;
      20: ldc2_w        #20                 // long 1000l
      23: ldc2_w        #22                 // long 100000l
      26: ldc           #24                 // String some op
      28: getstatic     #25                 // Field procData:[B
      31: aload_1
      32: invokestatic  #43                 // Method java/util/Arrays.asList:([Ljava/lang/Object;)Ljava/util/List;
      35: invokespecial #27                 // Method org/apache/hadoop/hbase/procedure/Procedure."<init>":(Lorg/apache/hadoop/hbase/procedure/ProcedureCoordinator;Lorg/apache/hadoop/hbase/errorhandling/ForeignExceptionDispatcher;JJLjava/lang/String;[BLjava/util/List;)V
      38: astore_2
      39: aload_2
      40: invokestatic  #18                 // Method org/mockito/Mockito.spy:(Ljava/lang/Object;)Ljava/lang/Object;
      43: checkcast     #6                  // class org/apache/hadoop/hbase/procedure/Procedure
      46: astore_3
      47: aload_0
      48: aload_3
      49: aload_1
      50: invokevirtual #74                 // Method runCoordinatedProcedure:(Lorg/apache/hadoop/hbase/procedure/Procedure;[Ljava/lang/String;)V
      53: return

  public void testEarlyJoiningBarrier() throws java.lang.Exception;
    Code:
       0: iconst_4
       1: anewarray     #31                 // class java/lang/String
       4: dup
       5: iconst_0
       6: ldc           #70                 // String one
       8: aastore
       9: dup
      10: iconst_1
      11: ldc           #71                 // String two
      13: aastore
      14: dup
      15: iconst_2
      16: ldc           #72                 // String three
      18: aastore
      19: dup
      20: iconst_3
      21: ldc           #73                 // String four
      23: aastore
      24: astore_1
      25: aload_0
      26: aload_0
      27: invokespecial #19                 // Method buildNewCoordinator:()Lorg/apache/hadoop/hbase/procedure/ProcedureCoordinator;
      30: putfield      #1                  // Field coordinator:Lorg/apache/hadoop/hbase/procedure/ProcedureCoordinator;
      33: aload_0
      34: getfield      #1                  // Field coordinator:Lorg/apache/hadoop/hbase/procedure/ProcedureCoordinator;
      37: astore_2
      38: new           #6                  // class org/apache/hadoop/hbase/procedure/Procedure
      41: dup
      42: aload_0
      43: getfield      #1                  // Field coordinator:Lorg/apache/hadoop/hbase/procedure/ProcedureCoordinator;
      46: aload_0
      47: getfield      #9                  // Field monitor:Lorg/apache/hadoop/hbase/errorhandling/ForeignExceptionDispatcher;
      50: ldc2_w        #20                 // long 1000l
      53: ldc2_w        #22                 // long 100000l
      56: ldc           #24                 // String some op
      58: getstatic     #25                 // Field procData:[B
      61: aload_1
      62: invokestatic  #43                 // Method java/util/Arrays.asList:([Ljava/lang/Object;)Ljava/util/List;
      65: invokespecial #27                 // Method org/apache/hadoop/hbase/procedure/Procedure."<init>":(Lorg/apache/hadoop/hbase/procedure/ProcedureCoordinator;Lorg/apache/hadoop/hbase/errorhandling/ForeignExceptionDispatcher;JJLjava/lang/String;[BLjava/util/List;)V
      68: astore_3
      69: aload_3
      70: invokestatic  #18                 // Method org/mockito/Mockito.spy:(Ljava/lang/Object;)Ljava/lang/Object;
      73: checkcast     #6                  // class org/apache/hadoop/hbase/procedure/Procedure
      76: astore        4
      78: new           #75                 // class org/apache/hadoop/hbase/procedure/TestProcedureCoordinator$1
      81: dup
      82: aload_0
      83: ldc           #24                 // String some op
      85: aload_1
      86: aload_2
      87: invokespecial #76                 // Method org/apache/hadoop/hbase/procedure/TestProcedureCoordinator$1."<init>":(Lorg/apache/hadoop/hbase/procedure/TestProcedureCoordinator;Ljava/lang/String;[Ljava/lang/String;Lorg/apache/hadoop/hbase/procedure/ProcedureCoordinator;)V
      90: astore        5
      92: new           #77                 // class org/apache/hadoop/hbase/procedure/TestProcedureCoordinator$2
      95: dup
      96: aload_0
      97: ldc           #24                 // String some op
      99: aload_1
     100: aload_2
     101: invokespecial #78                 // Method org/apache/hadoop/hbase/procedure/TestProcedureCoordinator$2."<init>":(Lorg/apache/hadoop/hbase/procedure/TestProcedureCoordinator;Ljava/lang/String;[Ljava/lang/String;Lorg/apache/hadoop/hbase/procedure/ProcedureCoordinator;)V
     104: astore        6
     106: aload_0
     107: aload         4
     109: aload         5
     111: aload         6
     113: aload_1
     114: invokevirtual #79                 // Method runCoordinatedOperation:(Lorg/apache/hadoop/hbase/procedure/Procedure;Lorg/apache/hadoop/hbase/procedure/TestProcedureCoordinator$AcquireBarrierAnswer;Lorg/apache/hadoop/hbase/procedure/TestProcedureCoordinator$BarrierAnswer;[Ljava/lang/String;)V
     117: return

  public void runCoordinatedProcedure(org.apache.hadoop.hbase.procedure.Procedure, java.lang.String...) throws java.lang.Exception;
    Code:
       0: aload_0
       1: aload_1
       2: new           #66                 // class org/apache/hadoop/hbase/procedure/TestProcedureCoordinator$AcquireBarrierAnswer
       5: dup
       6: aload_0
       7: ldc           #24                 // String some op
       9: aload_2
      10: invokespecial #67                 // Method org/apache/hadoop/hbase/procedure/TestProcedureCoordinator$AcquireBarrierAnswer."<init>":(Lorg/apache/hadoop/hbase/procedure/TestProcedureCoordinator;Ljava/lang/String;[Ljava/lang/String;)V
      13: new           #80                 // class org/apache/hadoop/hbase/procedure/TestProcedureCoordinator$BarrierAnswer
      16: dup
      17: aload_0
      18: ldc           #24                 // String some op
      20: aload_2
      21: invokespecial #81                 // Method org/apache/hadoop/hbase/procedure/TestProcedureCoordinator$BarrierAnswer."<init>":(Lorg/apache/hadoop/hbase/procedure/TestProcedureCoordinator;Ljava/lang/String;[Ljava/lang/String;)V
      24: aload_2
      25: invokevirtual #79                 // Method runCoordinatedOperation:(Lorg/apache/hadoop/hbase/procedure/Procedure;Lorg/apache/hadoop/hbase/procedure/TestProcedureCoordinator$AcquireBarrierAnswer;Lorg/apache/hadoop/hbase/procedure/TestProcedureCoordinator$BarrierAnswer;[Ljava/lang/String;)V
      28: return

  public void runCoordinatedOperation(org.apache.hadoop.hbase.procedure.Procedure, org.apache.hadoop.hbase.procedure.TestProcedureCoordinator$AcquireBarrierAnswer, java.lang.String...) throws java.lang.Exception;
    Code:
       0: aload_0
       1: aload_1
       2: aload_2
       3: new           #80                 // class org/apache/hadoop/hbase/procedure/TestProcedureCoordinator$BarrierAnswer
       6: dup
       7: aload_0
       8: ldc           #24                 // String some op
      10: aload_3
      11: invokespecial #81                 // Method org/apache/hadoop/hbase/procedure/TestProcedureCoordinator$BarrierAnswer."<init>":(Lorg/apache/hadoop/hbase/procedure/TestProcedureCoordinator;Ljava/lang/String;[Ljava/lang/String;)V
      14: aload_3
      15: invokevirtual #79                 // Method runCoordinatedOperation:(Lorg/apache/hadoop/hbase/procedure/Procedure;Lorg/apache/hadoop/hbase/procedure/TestProcedureCoordinator$AcquireBarrierAnswer;Lorg/apache/hadoop/hbase/procedure/TestProcedureCoordinator$BarrierAnswer;[Ljava/lang/String;)V
      18: return

  public void runCoordinatedOperation(org.apache.hadoop.hbase.procedure.Procedure, org.apache.hadoop.hbase.procedure.TestProcedureCoordinator$BarrierAnswer, java.lang.String...) throws java.lang.Exception;
    Code:
       0: aload_0
       1: aload_1
       2: new           #66                 // class org/apache/hadoop/hbase/procedure/TestProcedureCoordinator$AcquireBarrierAnswer
       5: dup
       6: aload_0
       7: ldc           #24                 // String some op
       9: aload_3
      10: invokespecial #67                 // Method org/apache/hadoop/hbase/procedure/TestProcedureCoordinator$AcquireBarrierAnswer."<init>":(Lorg/apache/hadoop/hbase/procedure/TestProcedureCoordinator;Ljava/lang/String;[Ljava/lang/String;)V
      13: aload_2
      14: aload_3
      15: invokevirtual #79                 // Method runCoordinatedOperation:(Lorg/apache/hadoop/hbase/procedure/Procedure;Lorg/apache/hadoop/hbase/procedure/TestProcedureCoordinator$AcquireBarrierAnswer;Lorg/apache/hadoop/hbase/procedure/TestProcedureCoordinator$BarrierAnswer;[Ljava/lang/String;)V
      18: return

  public void runCoordinatedOperation(org.apache.hadoop.hbase.procedure.Procedure, org.apache.hadoop.hbase.procedure.TestProcedureCoordinator$AcquireBarrierAnswer, org.apache.hadoop.hbase.procedure.TestProcedureCoordinator$BarrierAnswer, java.lang.String...) throws java.lang.Exception;
    Code:
       0: aload         4
       2: invokestatic  #43                 // Method java/util/Arrays.asList:([Ljava/lang/Object;)Ljava/util/List;
       5: astore        5
       7: aload_0
       8: getfield      #1                  // Field coordinator:Lorg/apache/hadoop/hbase/procedure/ProcedureCoordinator;
      11: invokestatic  #29                 // Method org/mockito/Matchers.any:()Ljava/lang/Object;
      14: checkcast     #8                  // class org/apache/hadoop/hbase/errorhandling/ForeignExceptionDispatcher
      17: ldc           #24                 // String some op
      19: invokestatic  #30                 // Method org/mockito/Matchers.eq:(Ljava/lang/Object;)Ljava/lang/Object;
      22: checkcast     #31                 // class java/lang/String
      25: getstatic     #25                 // Field procData:[B
      28: invokestatic  #30                 // Method org/mockito/Matchers.eq:(Ljava/lang/Object;)Ljava/lang/Object;
      31: checkcast     #32                 // class "[B"
      34: ldc           #31                 // class java/lang/String
      36: invokestatic  #33                 // Method org/mockito/Matchers.anyListOf:(Ljava/lang/Class;)Ljava/util/List;
      39: invokevirtual #34                 // Method org/apache/hadoop/hbase/procedure/ProcedureCoordinator.createProcedure:(Lorg/apache/hadoop/hbase/errorhandling/ForeignExceptionDispatcher;Ljava/lang/String;[BLjava/util/List;)Lorg/apache/hadoop/hbase/procedure/Procedure;
      42: invokestatic  #35                 // Method org/mockito/Mockito.when:(Ljava/lang/Object;)Lorg/mockito/stubbing/OngoingStubbing;
      45: aload_1
      46: invokeinterface #45,  2           // InterfaceMethod org/mockito/stubbing/OngoingStubbing.thenReturn:(Ljava/lang/Object;)Lorg/mockito/stubbing/OngoingStubbing;
      51: pop
      52: aload_2
      53: invokestatic  #68                 // Method org/mockito/Mockito.doAnswer:(Lorg/mockito/stubbing/Answer;)Lorg/mockito/stubbing/Stubber;
      56: aload_0
      57: getfield      #5                  // Field controller:Lorg/apache/hadoop/hbase/procedure/ProcedureCoordinatorRpcs;
      60: invokeinterface #51,  2           // InterfaceMethod org/mockito/stubbing/Stubber.when:(Ljava/lang/Object;)Ljava/lang/Object;
      65: checkcast     #3                  // class org/apache/hadoop/hbase/procedure/ProcedureCoordinatorRpcs
      68: aload_1
      69: getstatic     #25                 // Field procData:[B
      72: aload         5
      74: invokeinterface #52,  4           // InterfaceMethod org/apache/hadoop/hbase/procedure/ProcedureCoordinatorRpcs.sendGlobalBarrierAcquire:(Lorg/apache/hadoop/hbase/procedure/Procedure;[BLjava/util/List;)V
      79: aload_3
      80: invokestatic  #68                 // Method org/mockito/Mockito.doAnswer:(Lorg/mockito/stubbing/Answer;)Lorg/mockito/stubbing/Stubber;
      83: aload_0
      84: getfield      #5                  // Field controller:Lorg/apache/hadoop/hbase/procedure/ProcedureCoordinatorRpcs;
      87: invokeinterface #51,  2           // InterfaceMethod org/mockito/stubbing/Stubber.when:(Ljava/lang/Object;)Ljava/lang/Object;
      92: checkcast     #3                  // class org/apache/hadoop/hbase/procedure/ProcedureCoordinatorRpcs
      95: aload_1
      96: invokestatic  #30                 // Method org/mockito/Matchers.eq:(Ljava/lang/Object;)Ljava/lang/Object;
      99: checkcast     #6                  // class org/apache/hadoop/hbase/procedure/Procedure
     102: ldc           #31                 // class java/lang/String
     104: invokestatic  #33                 // Method org/mockito/Matchers.anyListOf:(Ljava/lang/Class;)Ljava/util/List;
     107: invokeinterface #64,  3           // InterfaceMethod org/apache/hadoop/hbase/procedure/ProcedureCoordinatorRpcs.sendGlobalBarrierReached:(Lorg/apache/hadoop/hbase/procedure/Procedure;Ljava/util/List;)V
     112: aload_0
     113: getfield      #1                  // Field coordinator:Lorg/apache/hadoop/hbase/procedure/ProcedureCoordinator;
     116: aload_1
     117: invokevirtual #37                 // Method org/apache/hadoop/hbase/procedure/Procedure.getErrorMonitor:()Lorg/apache/hadoop/hbase/errorhandling/ForeignExceptionDispatcher;
     120: ldc           #24                 // String some op
     122: getstatic     #25                 // Field procData:[B
     125: aload         5
     127: invokevirtual #38                 // Method org/apache/hadoop/hbase/procedure/ProcedureCoordinator.startProcedure:(Lorg/apache/hadoop/hbase/errorhandling/ForeignExceptionDispatcher;Ljava/lang/String;[BLjava/util/List;)Lorg/apache/hadoop/hbase/procedure/Procedure;
     130: astore        6
     132: aload         6
     134: invokevirtual #82                 // Method org/apache/hadoop/hbase/procedure/Procedure.waitForCompleted:()V
     137: aload_2
     138: invokevirtual #83                 // Method org/apache/hadoop/hbase/procedure/TestProcedureCoordinator$AcquireBarrierAnswer.ensureRan:()V
     141: iconst_2
     142: anewarray     #10                 // class java/lang/Object
     145: dup
     146: iconst_0
     147: aload_1
     148: aastore
     149: dup
     150: iconst_1
     151: aload_0
     152: getfield      #5                  // Field controller:Lorg/apache/hadoop/hbase/procedure/ProcedureCoordinatorRpcs;
     155: aastore
     156: invokestatic  #84                 // Method org/mockito/Mockito.inOrder:([Ljava/lang/Object;)Lorg/mockito/InOrder;
     159: astore        7
     161: aload         7
     163: aload_1
     164: invokeinterface #85,  2           // InterfaceMethod org/mockito/InOrder.verify:(Ljava/lang/Object;)Ljava/lang/Object;
     169: checkcast     #6                  // class org/apache/hadoop/hbase/procedure/Procedure
     172: invokevirtual #86                 // Method org/apache/hadoop/hbase/procedure/Procedure.sendGlobalBarrierStart:()V
     175: aload         7
     177: aload_0
     178: getfield      #5                  // Field controller:Lorg/apache/hadoop/hbase/procedure/ProcedureCoordinatorRpcs;
     181: invokeinterface #85,  2           // InterfaceMethod org/mockito/InOrder.verify:(Ljava/lang/Object;)Ljava/lang/Object;
     186: checkcast     #3                  // class org/apache/hadoop/hbase/procedure/ProcedureCoordinatorRpcs
     189: aload         6
     191: getstatic     #25                 // Field procData:[B
     194: aload         5
     196: invokeinterface #52,  4           // InterfaceMethod org/apache/hadoop/hbase/procedure/ProcedureCoordinatorRpcs.sendGlobalBarrierAcquire:(Lorg/apache/hadoop/hbase/procedure/Procedure;[BLjava/util/List;)V
     201: aload         7
     203: aload_1
     204: invokeinterface #85,  2           // InterfaceMethod org/mockito/InOrder.verify:(Ljava/lang/Object;)Ljava/lang/Object;
     209: checkcast     #6                  // class org/apache/hadoop/hbase/procedure/Procedure
     212: invokevirtual #87                 // Method org/apache/hadoop/hbase/procedure/Procedure.sendGlobalBarrierReached:()V
     215: aload         7
     217: aload_0
     218: getfield      #5                  // Field controller:Lorg/apache/hadoop/hbase/procedure/ProcedureCoordinatorRpcs;
     221: invokeinterface #85,  2           // InterfaceMethod org/mockito/InOrder.verify:(Ljava/lang/Object;)Ljava/lang/Object;
     226: checkcast     #3                  // class org/apache/hadoop/hbase/procedure/ProcedureCoordinatorRpcs
     229: aload         6
     231: invokestatic  #30                 // Method org/mockito/Matchers.eq:(Ljava/lang/Object;)Ljava/lang/Object;
     234: checkcast     #6                  // class org/apache/hadoop/hbase/procedure/Procedure
     237: ldc           #31                 // class java/lang/String
     239: invokestatic  #33                 // Method org/mockito/Matchers.anyListOf:(Ljava/lang/Class;)Ljava/util/List;
     242: invokeinterface #64,  3           // InterfaceMethod org/apache/hadoop/hbase/procedure/ProcedureCoordinatorRpcs.sendGlobalBarrierReached:(Lorg/apache/hadoop/hbase/procedure/Procedure;Ljava/util/List;)V
     247: return

  static org.apache.hadoop.hbase.procedure.ProcedureCoordinator access$100(org.apache.hadoop.hbase.procedure.TestProcedureCoordinator);
    Code:
       0: aload_0
       1: getfield      #1                  // Field coordinator:Lorg/apache/hadoop/hbase/procedure/ProcedureCoordinator;
       4: areturn

  static {};
    Code:
       0: ldc           #13                 // class org/apache/hadoop/hbase/procedure/TestProcedureCoordinator
       2: invokestatic  #88                 // Method org/apache/hadoop/hbase/HBaseClassTestRule.forClass:(Ljava/lang/Class;)Lorg/apache/hadoop/hbase/HBaseClassTestRule;
       5: putstatic     #89                 // Field CLASS_RULE:Lorg/apache/hadoop/hbase/HBaseClassTestRule;
       8: iconst_0
       9: newarray       byte
      11: putstatic     #25                 // Field procData:[B
      14: iconst_2
      15: anewarray     #31                 // class java/lang/String
      18: dup
      19: iconst_0
      20: ldc           #90                 // String remote1
      22: aastore
      23: dup
      24: iconst_1
      25: ldc           #91                 // String remote2
      27: aastore
      28: invokestatic  #92                 // Method org/apache/hbase/thirdparty/com/google/common/collect/Lists.newArrayList:([Ljava/lang/Object;)Ljava/util/ArrayList;
      31: putstatic     #26                 // Field expected:Ljava/util/List;
      34: return
}
