Compiled from "TestRegionObserverInterface.java"
public class org.apache.hadoop.hbase.coprocessor.TestRegionObserverInterface {
  public static final org.apache.hadoop.hbase.HBaseClassTestRule CLASS_RULE;

  public static final org.apache.hadoop.hbase.TableName TEST_TABLE;

  public static final byte[] A;

  public static final byte[] B;

  public static final byte[] C;

  public static final byte[] ROW;

  public org.junit.rules.TestName name;

  public org.apache.hadoop.hbase.coprocessor.TestRegionObserverInterface();
    Code:
       0: aload_0
       1: invokespecial #1                  // Method java/lang/Object."<init>":()V
       4: aload_0
       5: new           #2                  // class org/junit/rules/TestName
       8: dup
       9: invokespecial #3                  // Method org/junit/rules/TestName."<init>":()V
      12: putfield      #4                  // Field name:Lorg/junit/rules/TestName;
      15: return

  public static void setupBeforeClass() throws java.lang.Exception;
    Code:
       0: getstatic     #5                  // Field util:Lorg/apache/hadoop/hbase/HBaseTestingUtility;
       3: invokevirtual #6                  // Method org/apache/hadoop/hbase/HBaseTestingUtility.getConfiguration:()Lorg/apache/hadoop/conf/Configuration;
       6: astore_0
       7: aload_0
       8: ldc           #7                  // String hbase.master.distributed.log.replay
      10: iconst_1
      11: invokevirtual #8                  // Method org/apache/hadoop/conf/Configuration.setBoolean:(Ljava/lang/String;Z)V
      14: aload_0
      15: ldc           #10                 // String hbase.coprocessor.region.classes
      17: iconst_1
      18: anewarray     #11                 // class java/lang/String
      21: dup
      22: iconst_0
      23: ldc           #12                 // class org/apache/hadoop/hbase/coprocessor/SimpleRegionObserver
      25: invokevirtual #13                 // Method java/lang/Class.getName:()Ljava/lang/String;
      28: aastore
      29: invokevirtual #14                 // Method org/apache/hadoop/conf/Configuration.setStrings:(Ljava/lang/String;[Ljava/lang/String;)V
      32: getstatic     #5                  // Field util:Lorg/apache/hadoop/hbase/HBaseTestingUtility;
      35: invokevirtual #15                 // Method org/apache/hadoop/hbase/HBaseTestingUtility.startMiniCluster:()Lorg/apache/hadoop/hbase/MiniHBaseCluster;
      38: pop
      39: getstatic     #5                  // Field util:Lorg/apache/hadoop/hbase/HBaseTestingUtility;
      42: invokevirtual #16                 // Method org/apache/hadoop/hbase/HBaseTestingUtility.getMiniHBaseCluster:()Lorg/apache/hadoop/hbase/MiniHBaseCluster;
      45: putstatic     #17                 // Field cluster:Lorg/apache/hadoop/hbase/MiniHBaseCluster;
      48: return

  public static void tearDownAfterClass() throws java.lang.Exception;
    Code:
       0: getstatic     #5                  // Field util:Lorg/apache/hadoop/hbase/HBaseTestingUtility;
       3: invokevirtual #18                 // Method org/apache/hadoop/hbase/HBaseTestingUtility.shutdownMiniCluster:()V
       6: return

  public void testRegionObserver() throws java.io.IOException;
    Code:
       0: new           #19                 // class java/lang/StringBuilder
       3: dup
       4: invokespecial #20                 // Method java/lang/StringBuilder."<init>":()V
       7: getstatic     #21                 // Field TEST_TABLE:Lorg/apache/hadoop/hbase/TableName;
      10: invokevirtual #22                 // Method org/apache/hadoop/hbase/TableName.getNameAsString:()Ljava/lang/String;
      13: invokevirtual #23                 // Method java/lang/StringBuilder.append:(Ljava/lang/String;)Ljava/lang/StringBuilder;
      16: ldc           #24                 // String .
      18: invokevirtual #23                 // Method java/lang/StringBuilder.append:(Ljava/lang/String;)Ljava/lang/StringBuilder;
      21: aload_0
      22: getfield      #4                  // Field name:Lorg/junit/rules/TestName;
      25: invokevirtual #25                 // Method org/junit/rules/TestName.getMethodName:()Ljava/lang/String;
      28: invokevirtual #23                 // Method java/lang/StringBuilder.append:(Ljava/lang/String;)Ljava/lang/StringBuilder;
      31: invokevirtual #26                 // Method java/lang/StringBuilder.toString:()Ljava/lang/String;
      34: invokestatic  #27                 // Method org/apache/hadoop/hbase/TableName.valueOf:(Ljava/lang/String;)Lorg/apache/hadoop/hbase/TableName;
      37: astore_1
      38: getstatic     #5                  // Field util:Lorg/apache/hadoop/hbase/HBaseTestingUtility;
      41: aload_1
      42: iconst_3
      43: anewarray     #28                 // class "[B"
      46: dup
      47: iconst_0
      48: getstatic     #29                 // Field A:[B
      51: aastore
      52: dup
      53: iconst_1
      54: getstatic     #30                 // Field B:[B
      57: aastore
      58: dup
      59: iconst_2
      60: getstatic     #31                 // Field C:[B
      63: aastore
      64: invokevirtual #32                 // Method org/apache/hadoop/hbase/HBaseTestingUtility.createTable:(Lorg/apache/hadoop/hbase/TableName;[[B)Lorg/apache/hadoop/hbase/client/Table;
      67: astore_2
      68: aload_0
      69: ldc           #12                 // class org/apache/hadoop/hbase/coprocessor/SimpleRegionObserver
      71: bipush        8
      73: anewarray     #11                 // class java/lang/String
      76: dup
      77: iconst_0
      78: ldc           #33                 // String hadPreGet
      80: aastore
      81: dup
      82: iconst_1
      83: ldc           #34                 // String hadPostGet
      85: aastore
      86: dup
      87: iconst_2
      88: ldc           #35                 // String hadPrePut
      90: aastore
      91: dup
      92: iconst_3
      93: ldc           #36                 // String hadPostPut
      95: aastore
      96: dup
      97: iconst_4
      98: ldc           #37                 // String hadDelete
     100: aastore
     101: dup
     102: iconst_5
     103: ldc           #38                 // String hadPostStartRegionOperation
     105: aastore
     106: dup
     107: bipush        6
     109: ldc           #39                 // String hadPostCloseRegionOperation
     111: aastore
     112: dup
     113: bipush        7
     115: ldc           #40                 // String hadPostBatchMutateIndispensably
     117: aastore
     118: aload_1
     119: bipush        8
     121: anewarray     #41                 // class java/lang/Boolean
     124: dup
     125: iconst_0
     126: iconst_0
     127: invokestatic  #42                 // Method java/lang/Boolean.valueOf:(Z)Ljava/lang/Boolean;
     130: aastore
     131: dup
     132: iconst_1
     133: iconst_0
     134: invokestatic  #42                 // Method java/lang/Boolean.valueOf:(Z)Ljava/lang/Boolean;
     137: aastore
     138: dup
     139: iconst_2
     140: iconst_0
     141: invokestatic  #42                 // Method java/lang/Boolean.valueOf:(Z)Ljava/lang/Boolean;
     144: aastore
     145: dup
     146: iconst_3
     147: iconst_0
     148: invokestatic  #42                 // Method java/lang/Boolean.valueOf:(Z)Ljava/lang/Boolean;
     151: aastore
     152: dup
     153: iconst_4
     154: iconst_0
     155: invokestatic  #42                 // Method java/lang/Boolean.valueOf:(Z)Ljava/lang/Boolean;
     158: aastore
     159: dup
     160: iconst_5
     161: iconst_0
     162: invokestatic  #42                 // Method java/lang/Boolean.valueOf:(Z)Ljava/lang/Boolean;
     165: aastore
     166: dup
     167: bipush        6
     169: iconst_0
     170: invokestatic  #42                 // Method java/lang/Boolean.valueOf:(Z)Ljava/lang/Boolean;
     173: aastore
     174: dup
     175: bipush        7
     177: iconst_0
     178: invokestatic  #42                 // Method java/lang/Boolean.valueOf:(Z)Ljava/lang/Boolean;
     181: aastore
     182: invokespecial #43                 // Method verifyMethodResult:(Ljava/lang/Class;[Ljava/lang/String;Lorg/apache/hadoop/hbase/TableName;[Ljava/lang/Object;)V
     185: new           #44                 // class org/apache/hadoop/hbase/client/Put
     188: dup
     189: getstatic     #45                 // Field ROW:[B
     192: invokespecial #46                 // Method org/apache/hadoop/hbase/client/Put."<init>":([B)V
     195: astore_3
     196: aload_3
     197: getstatic     #29                 // Field A:[B
     200: getstatic     #29                 // Field A:[B
     203: getstatic     #29                 // Field A:[B
     206: invokevirtual #47                 // Method org/apache/hadoop/hbase/client/Put.addColumn:([B[B[B)Lorg/apache/hadoop/hbase/client/Put;
     209: pop
     210: aload_3
     211: getstatic     #30                 // Field B:[B
     214: getstatic     #30                 // Field B:[B
     217: getstatic     #30                 // Field B:[B
     220: invokevirtual #47                 // Method org/apache/hadoop/hbase/client/Put.addColumn:([B[B[B)Lorg/apache/hadoop/hbase/client/Put;
     223: pop
     224: aload_3
     225: getstatic     #31                 // Field C:[B
     228: getstatic     #31                 // Field C:[B
     231: getstatic     #31                 // Field C:[B
     234: invokevirtual #47                 // Method org/apache/hadoop/hbase/client/Put.addColumn:([B[B[B)Lorg/apache/hadoop/hbase/client/Put;
     237: pop
     238: aload_2
     239: aload_3
     240: invokeinterface #48,  2           // InterfaceMethod org/apache/hadoop/hbase/client/Table.put:(Lorg/apache/hadoop/hbase/client/Put;)V
     245: aload_0
     246: ldc           #12                 // class org/apache/hadoop/hbase/coprocessor/SimpleRegionObserver
     248: bipush        10
     250: anewarray     #11                 // class java/lang/String
     253: dup
     254: iconst_0
     255: ldc           #33                 // String hadPreGet
     257: aastore
     258: dup
     259: iconst_1
     260: ldc           #34                 // String hadPostGet
     262: aastore
     263: dup
     264: iconst_2
     265: ldc           #35                 // String hadPrePut
     267: aastore
     268: dup
     269: iconst_3
     270: ldc           #36                 // String hadPostPut
     272: aastore
     273: dup
     274: iconst_4
     275: ldc           #49                 // String hadPreBatchMutate
     277: aastore
     278: dup
     279: iconst_5
     280: ldc           #50                 // String hadPostBatchMutate
     282: aastore
     283: dup
     284: bipush        6
     286: ldc           #37                 // String hadDelete
     288: aastore
     289: dup
     290: bipush        7
     292: ldc           #38                 // String hadPostStartRegionOperation
     294: aastore
     295: dup
     296: bipush        8
     298: ldc           #39                 // String hadPostCloseRegionOperation
     300: aastore
     301: dup
     302: bipush        9
     304: ldc           #40                 // String hadPostBatchMutateIndispensably
     306: aastore
     307: getstatic     #21                 // Field TEST_TABLE:Lorg/apache/hadoop/hbase/TableName;
     310: bipush        10
     312: anewarray     #41                 // class java/lang/Boolean
     315: dup
     316: iconst_0
     317: iconst_0
     318: invokestatic  #42                 // Method java/lang/Boolean.valueOf:(Z)Ljava/lang/Boolean;
     321: aastore
     322: dup
     323: iconst_1
     324: iconst_0
     325: invokestatic  #42                 // Method java/lang/Boolean.valueOf:(Z)Ljava/lang/Boolean;
     328: aastore
     329: dup
     330: iconst_2
     331: iconst_1
     332: invokestatic  #42                 // Method java/lang/Boolean.valueOf:(Z)Ljava/lang/Boolean;
     335: aastore
     336: dup
     337: iconst_3
     338: iconst_1
     339: invokestatic  #42                 // Method java/lang/Boolean.valueOf:(Z)Ljava/lang/Boolean;
     342: aastore
     343: dup
     344: iconst_4
     345: iconst_1
     346: invokestatic  #42                 // Method java/lang/Boolean.valueOf:(Z)Ljava/lang/Boolean;
     349: aastore
     350: dup
     351: iconst_5
     352: iconst_1
     353: invokestatic  #42                 // Method java/lang/Boolean.valueOf:(Z)Ljava/lang/Boolean;
     356: aastore
     357: dup
     358: bipush        6
     360: iconst_0
     361: invokestatic  #42                 // Method java/lang/Boolean.valueOf:(Z)Ljava/lang/Boolean;
     364: aastore
     365: dup
     366: bipush        7
     368: iconst_1
     369: invokestatic  #42                 // Method java/lang/Boolean.valueOf:(Z)Ljava/lang/Boolean;
     372: aastore
     373: dup
     374: bipush        8
     376: iconst_1
     377: invokestatic  #42                 // Method java/lang/Boolean.valueOf:(Z)Ljava/lang/Boolean;
     380: aastore
     381: dup
     382: bipush        9
     384: iconst_1
     385: invokestatic  #42                 // Method java/lang/Boolean.valueOf:(Z)Ljava/lang/Boolean;
     388: aastore
     389: invokespecial #43                 // Method verifyMethodResult:(Ljava/lang/Class;[Ljava/lang/String;Lorg/apache/hadoop/hbase/TableName;[Ljava/lang/Object;)V
     392: aload_0
     393: ldc           #12                 // class org/apache/hadoop/hbase/coprocessor/SimpleRegionObserver
     395: iconst_4
     396: anewarray     #11                 // class java/lang/String
     399: dup
     400: iconst_0
     401: ldc           #51                 // String getCtPreOpen
     403: aastore
     404: dup
     405: iconst_1
     406: ldc           #52                 // String getCtPostOpen
     408: aastore
     409: dup
     410: iconst_2
     411: ldc           #53                 // String getCtPreClose
     413: aastore
     414: dup
     415: iconst_3
     416: ldc           #54                 // String getCtPostClose
     418: aastore
     419: aload_1
     420: iconst_4
     421: anewarray     #55                 // class java/lang/Integer
     424: dup
     425: iconst_0
     426: iconst_1
     427: invokestatic  #56                 // Method java/lang/Integer.valueOf:(I)Ljava/lang/Integer;
     430: aastore
     431: dup
     432: iconst_1
     433: iconst_1
     434: invokestatic  #56                 // Method java/lang/Integer.valueOf:(I)Ljava/lang/Integer;
     437: aastore
     438: dup
     439: iconst_2
     440: iconst_0
     441: invokestatic  #56                 // Method java/lang/Integer.valueOf:(I)Ljava/lang/Integer;
     444: aastore
     445: dup
     446: iconst_3
     447: iconst_0
     448: invokestatic  #56                 // Method java/lang/Integer.valueOf:(I)Ljava/lang/Integer;
     451: aastore
     452: invokespecial #43                 // Method verifyMethodResult:(Ljava/lang/Class;[Ljava/lang/String;Lorg/apache/hadoop/hbase/TableName;[Ljava/lang/Object;)V
     455: new           #57                 // class org/apache/hadoop/hbase/client/Get
     458: dup
     459: getstatic     #45                 // Field ROW:[B
     462: invokespecial #58                 // Method org/apache/hadoop/hbase/client/Get."<init>":([B)V
     465: astore        4
     467: aload         4
     469: getstatic     #29                 // Field A:[B
     472: getstatic     #29                 // Field A:[B
     475: invokevirtual #59                 // Method org/apache/hadoop/hbase/client/Get.addColumn:([B[B)Lorg/apache/hadoop/hbase/client/Get;
     478: pop
     479: aload         4
     481: getstatic     #30                 // Field B:[B
     484: getstatic     #30                 // Field B:[B
     487: invokevirtual #59                 // Method org/apache/hadoop/hbase/client/Get.addColumn:([B[B)Lorg/apache/hadoop/hbase/client/Get;
     490: pop
     491: aload         4
     493: getstatic     #31                 // Field C:[B
     496: getstatic     #31                 // Field C:[B
     499: invokevirtual #59                 // Method org/apache/hadoop/hbase/client/Get.addColumn:([B[B)Lorg/apache/hadoop/hbase/client/Get;
     502: pop
     503: aload_2
     504: aload         4
     506: invokeinterface #60,  2           // InterfaceMethod org/apache/hadoop/hbase/client/Table.get:(Lorg/apache/hadoop/hbase/client/Get;)Lorg/apache/hadoop/hbase/client/Result;
     511: pop
     512: aload_0
     513: ldc           #12                 // class org/apache/hadoop/hbase/coprocessor/SimpleRegionObserver
     515: bipush        6
     517: anewarray     #11                 // class java/lang/String
     520: dup
     521: iconst_0
     522: ldc           #33                 // String hadPreGet
     524: aastore
     525: dup
     526: iconst_1
     527: ldc           #34                 // String hadPostGet
     529: aastore
     530: dup
     531: iconst_2
     532: ldc           #35                 // String hadPrePut
     534: aastore
     535: dup
     536: iconst_3
     537: ldc           #36                 // String hadPostPut
     539: aastore
     540: dup
     541: iconst_4
     542: ldc           #37                 // String hadDelete
     544: aastore
     545: dup
     546: iconst_5
     547: ldc           #61                 // String hadPrePreparedDeleteTS
     549: aastore
     550: aload_1
     551: bipush        6
     553: anewarray     #41                 // class java/lang/Boolean
     556: dup
     557: iconst_0
     558: iconst_1
     559: invokestatic  #42                 // Method java/lang/Boolean.valueOf:(Z)Ljava/lang/Boolean;
     562: aastore
     563: dup
     564: iconst_1
     565: iconst_1
     566: invokestatic  #42                 // Method java/lang/Boolean.valueOf:(Z)Ljava/lang/Boolean;
     569: aastore
     570: dup
     571: iconst_2
     572: iconst_1
     573: invokestatic  #42                 // Method java/lang/Boolean.valueOf:(Z)Ljava/lang/Boolean;
     576: aastore
     577: dup
     578: iconst_3
     579: iconst_1
     580: invokestatic  #42                 // Method java/lang/Boolean.valueOf:(Z)Ljava/lang/Boolean;
     583: aastore
     584: dup
     585: iconst_4
     586: iconst_0
     587: invokestatic  #42                 // Method java/lang/Boolean.valueOf:(Z)Ljava/lang/Boolean;
     590: aastore
     591: dup
     592: iconst_5
     593: iconst_0
     594: invokestatic  #42                 // Method java/lang/Boolean.valueOf:(Z)Ljava/lang/Boolean;
     597: aastore
     598: invokespecial #43                 // Method verifyMethodResult:(Ljava/lang/Class;[Ljava/lang/String;Lorg/apache/hadoop/hbase/TableName;[Ljava/lang/Object;)V
     601: new           #62                 // class org/apache/hadoop/hbase/client/Delete
     604: dup
     605: getstatic     #45                 // Field ROW:[B
     608: invokespecial #63                 // Method org/apache/hadoop/hbase/client/Delete."<init>":([B)V
     611: astore        5
     613: aload         5
     615: getstatic     #29                 // Field A:[B
     618: getstatic     #29                 // Field A:[B
     621: invokevirtual #64                 // Method org/apache/hadoop/hbase/client/Delete.addColumn:([B[B)Lorg/apache/hadoop/hbase/client/Delete;
     624: pop
     625: aload         5
     627: getstatic     #30                 // Field B:[B
     630: getstatic     #30                 // Field B:[B
     633: invokevirtual #64                 // Method org/apache/hadoop/hbase/client/Delete.addColumn:([B[B)Lorg/apache/hadoop/hbase/client/Delete;
     636: pop
     637: aload         5
     639: getstatic     #31                 // Field C:[B
     642: getstatic     #31                 // Field C:[B
     645: invokevirtual #64                 // Method org/apache/hadoop/hbase/client/Delete.addColumn:([B[B)Lorg/apache/hadoop/hbase/client/Delete;
     648: pop
     649: aload_2
     650: aload         5
     652: invokeinterface #65,  2           // InterfaceMethod org/apache/hadoop/hbase/client/Table.delete:(Lorg/apache/hadoop/hbase/client/Delete;)V
     657: aload_0
     658: ldc           #12                 // class org/apache/hadoop/hbase/coprocessor/SimpleRegionObserver
     660: bipush        8
     662: anewarray     #11                 // class java/lang/String
     665: dup
     666: iconst_0
     667: ldc           #33                 // String hadPreGet
     669: aastore
     670: dup
     671: iconst_1
     672: ldc           #34                 // String hadPostGet
     674: aastore
     675: dup
     676: iconst_2
     677: ldc           #35                 // String hadPrePut
     679: aastore
     680: dup
     681: iconst_3
     682: ldc           #36                 // String hadPostPut
     684: aastore
     685: dup
     686: iconst_4
     687: ldc           #49                 // String hadPreBatchMutate
     689: aastore
     690: dup
     691: iconst_5
     692: ldc           #50                 // String hadPostBatchMutate
     694: aastore
     695: dup
     696: bipush        6
     698: ldc           #37                 // String hadDelete
     700: aastore
     701: dup
     702: bipush        7
     704: ldc           #61                 // String hadPrePreparedDeleteTS
     706: aastore
     707: aload_1
     708: bipush        8
     710: anewarray     #41                 // class java/lang/Boolean
     713: dup
     714: iconst_0
     715: iconst_1
     716: invokestatic  #42                 // Method java/lang/Boolean.valueOf:(Z)Ljava/lang/Boolean;
     719: aastore
     720: dup
     721: iconst_1
     722: iconst_1
     723: invokestatic  #42                 // Method java/lang/Boolean.valueOf:(Z)Ljava/lang/Boolean;
     726: aastore
     727: dup
     728: iconst_2
     729: iconst_1
     730: invokestatic  #42                 // Method java/lang/Boolean.valueOf:(Z)Ljava/lang/Boolean;
     733: aastore
     734: dup
     735: iconst_3
     736: iconst_1
     737: invokestatic  #42                 // Method java/lang/Boolean.valueOf:(Z)Ljava/lang/Boolean;
     740: aastore
     741: dup
     742: iconst_4
     743: iconst_1
     744: invokestatic  #42                 // Method java/lang/Boolean.valueOf:(Z)Ljava/lang/Boolean;
     747: aastore
     748: dup
     749: iconst_5
     750: iconst_1
     751: invokestatic  #42                 // Method java/lang/Boolean.valueOf:(Z)Ljava/lang/Boolean;
     754: aastore
     755: dup
     756: bipush        6
     758: iconst_1
     759: invokestatic  #42                 // Method java/lang/Boolean.valueOf:(Z)Ljava/lang/Boolean;
     762: aastore
     763: dup
     764: bipush        7
     766: iconst_1
     767: invokestatic  #42                 // Method java/lang/Boolean.valueOf:(Z)Ljava/lang/Boolean;
     770: aastore
     771: invokespecial #43                 // Method verifyMethodResult:(Ljava/lang/Class;[Ljava/lang/String;Lorg/apache/hadoop/hbase/TableName;[Ljava/lang/Object;)V
     774: getstatic     #5                  // Field util:Lorg/apache/hadoop/hbase/HBaseTestingUtility;
     777: aload_1
     778: invokevirtual #66                 // Method org/apache/hadoop/hbase/HBaseTestingUtility.deleteTable:(Lorg/apache/hadoop/hbase/TableName;)V
     781: aload_2
     782: invokeinterface #67,  1           // InterfaceMethod org/apache/hadoop/hbase/client/Table.close:()V
     787: goto          808
     790: astore        6
     792: getstatic     #5                  // Field util:Lorg/apache/hadoop/hbase/HBaseTestingUtility;
     795: aload_1
     796: invokevirtual #66                 // Method org/apache/hadoop/hbase/HBaseTestingUtility.deleteTable:(Lorg/apache/hadoop/hbase/TableName;)V
     799: aload_2
     800: invokeinterface #67,  1           // InterfaceMethod org/apache/hadoop/hbase/client/Table.close:()V
     805: aload         6
     807: athrow
     808: aload_0
     809: ldc           #12                 // class org/apache/hadoop/hbase/coprocessor/SimpleRegionObserver
     811: iconst_4
     812: anewarray     #11                 // class java/lang/String
     815: dup
     816: iconst_0
     817: ldc           #51                 // String getCtPreOpen
     819: aastore
     820: dup
     821: iconst_1
     822: ldc           #52                 // String getCtPostOpen
     824: aastore
     825: dup
     826: iconst_2
     827: ldc           #53                 // String getCtPreClose
     829: aastore
     830: dup
     831: iconst_3
     832: ldc           #54                 // String getCtPostClose
     834: aastore
     835: aload_1
     836: iconst_4
     837: anewarray     #55                 // class java/lang/Integer
     840: dup
     841: iconst_0
     842: iconst_1
     843: invokestatic  #56                 // Method java/lang/Integer.valueOf:(I)Ljava/lang/Integer;
     846: aastore
     847: dup
     848: iconst_1
     849: iconst_1
     850: invokestatic  #56                 // Method java/lang/Integer.valueOf:(I)Ljava/lang/Integer;
     853: aastore
     854: dup
     855: iconst_2
     856: iconst_1
     857: invokestatic  #56                 // Method java/lang/Integer.valueOf:(I)Ljava/lang/Integer;
     860: aastore
     861: dup
     862: iconst_3
     863: iconst_1
     864: invokestatic  #56                 // Method java/lang/Integer.valueOf:(I)Ljava/lang/Integer;
     867: aastore
     868: invokespecial #43                 // Method verifyMethodResult:(Ljava/lang/Class;[Ljava/lang/String;Lorg/apache/hadoop/hbase/TableName;[Ljava/lang/Object;)V
     871: return
    Exception table:
       from    to  target type
          68   774   790   any
         790   792   790   any

  public void testRowMutation() throws java.io.IOException;
    Code:
       0: new           #19                 // class java/lang/StringBuilder
       3: dup
       4: invokespecial #20                 // Method java/lang/StringBuilder."<init>":()V
       7: getstatic     #21                 // Field TEST_TABLE:Lorg/apache/hadoop/hbase/TableName;
      10: invokevirtual #22                 // Method org/apache/hadoop/hbase/TableName.getNameAsString:()Ljava/lang/String;
      13: invokevirtual #23                 // Method java/lang/StringBuilder.append:(Ljava/lang/String;)Ljava/lang/StringBuilder;
      16: ldc           #24                 // String .
      18: invokevirtual #23                 // Method java/lang/StringBuilder.append:(Ljava/lang/String;)Ljava/lang/StringBuilder;
      21: aload_0
      22: getfield      #4                  // Field name:Lorg/junit/rules/TestName;
      25: invokevirtual #25                 // Method org/junit/rules/TestName.getMethodName:()Ljava/lang/String;
      28: invokevirtual #23                 // Method java/lang/StringBuilder.append:(Ljava/lang/String;)Ljava/lang/StringBuilder;
      31: invokevirtual #26                 // Method java/lang/StringBuilder.toString:()Ljava/lang/String;
      34: invokestatic  #27                 // Method org/apache/hadoop/hbase/TableName.valueOf:(Ljava/lang/String;)Lorg/apache/hadoop/hbase/TableName;
      37: astore_1
      38: getstatic     #5                  // Field util:Lorg/apache/hadoop/hbase/HBaseTestingUtility;
      41: aload_1
      42: iconst_3
      43: anewarray     #28                 // class "[B"
      46: dup
      47: iconst_0
      48: getstatic     #29                 // Field A:[B
      51: aastore
      52: dup
      53: iconst_1
      54: getstatic     #30                 // Field B:[B
      57: aastore
      58: dup
      59: iconst_2
      60: getstatic     #31                 // Field C:[B
      63: aastore
      64: invokevirtual #32                 // Method org/apache/hadoop/hbase/HBaseTestingUtility.createTable:(Lorg/apache/hadoop/hbase/TableName;[[B)Lorg/apache/hadoop/hbase/client/Table;
      67: astore_2
      68: aload_0
      69: ldc           #12                 // class org/apache/hadoop/hbase/coprocessor/SimpleRegionObserver
      71: iconst_5
      72: anewarray     #11                 // class java/lang/String
      75: dup
      76: iconst_0
      77: ldc           #33                 // String hadPreGet
      79: aastore
      80: dup
      81: iconst_1
      82: ldc           #34                 // String hadPostGet
      84: aastore
      85: dup
      86: iconst_2
      87: ldc           #35                 // String hadPrePut
      89: aastore
      90: dup
      91: iconst_3
      92: ldc           #36                 // String hadPostPut
      94: aastore
      95: dup
      96: iconst_4
      97: ldc           #68                 // String hadDeleted
      99: aastore
     100: aload_1
     101: iconst_5
     102: anewarray     #41                 // class java/lang/Boolean
     105: dup
     106: iconst_0
     107: iconst_0
     108: invokestatic  #42                 // Method java/lang/Boolean.valueOf:(Z)Ljava/lang/Boolean;
     111: aastore
     112: dup
     113: iconst_1
     114: iconst_0
     115: invokestatic  #42                 // Method java/lang/Boolean.valueOf:(Z)Ljava/lang/Boolean;
     118: aastore
     119: dup
     120: iconst_2
     121: iconst_0
     122: invokestatic  #42                 // Method java/lang/Boolean.valueOf:(Z)Ljava/lang/Boolean;
     125: aastore
     126: dup
     127: iconst_3
     128: iconst_0
     129: invokestatic  #42                 // Method java/lang/Boolean.valueOf:(Z)Ljava/lang/Boolean;
     132: aastore
     133: dup
     134: iconst_4
     135: iconst_0
     136: invokestatic  #42                 // Method java/lang/Boolean.valueOf:(Z)Ljava/lang/Boolean;
     139: aastore
     140: invokespecial #43                 // Method verifyMethodResult:(Ljava/lang/Class;[Ljava/lang/String;Lorg/apache/hadoop/hbase/TableName;[Ljava/lang/Object;)V
     143: new           #44                 // class org/apache/hadoop/hbase/client/Put
     146: dup
     147: getstatic     #45                 // Field ROW:[B
     150: invokespecial #46                 // Method org/apache/hadoop/hbase/client/Put."<init>":([B)V
     153: astore_3
     154: aload_3
     155: getstatic     #29                 // Field A:[B
     158: getstatic     #29                 // Field A:[B
     161: getstatic     #29                 // Field A:[B
     164: invokevirtual #47                 // Method org/apache/hadoop/hbase/client/Put.addColumn:([B[B[B)Lorg/apache/hadoop/hbase/client/Put;
     167: pop
     168: aload_3
     169: getstatic     #30                 // Field B:[B
     172: getstatic     #30                 // Field B:[B
     175: getstatic     #30                 // Field B:[B
     178: invokevirtual #47                 // Method org/apache/hadoop/hbase/client/Put.addColumn:([B[B[B)Lorg/apache/hadoop/hbase/client/Put;
     181: pop
     182: aload_3
     183: getstatic     #31                 // Field C:[B
     186: getstatic     #31                 // Field C:[B
     189: getstatic     #31                 // Field C:[B
     192: invokevirtual #47                 // Method org/apache/hadoop/hbase/client/Put.addColumn:([B[B[B)Lorg/apache/hadoop/hbase/client/Put;
     195: pop
     196: new           #62                 // class org/apache/hadoop/hbase/client/Delete
     199: dup
     200: getstatic     #45                 // Field ROW:[B
     203: invokespecial #63                 // Method org/apache/hadoop/hbase/client/Delete."<init>":([B)V
     206: astore        4
     208: aload         4
     210: getstatic     #29                 // Field A:[B
     213: getstatic     #29                 // Field A:[B
     216: invokevirtual #64                 // Method org/apache/hadoop/hbase/client/Delete.addColumn:([B[B)Lorg/apache/hadoop/hbase/client/Delete;
     219: pop
     220: aload         4
     222: getstatic     #30                 // Field B:[B
     225: getstatic     #30                 // Field B:[B
     228: invokevirtual #64                 // Method org/apache/hadoop/hbase/client/Delete.addColumn:([B[B)Lorg/apache/hadoop/hbase/client/Delete;
     231: pop
     232: aload         4
     234: getstatic     #31                 // Field C:[B
     237: getstatic     #31                 // Field C:[B
     240: invokevirtual #64                 // Method org/apache/hadoop/hbase/client/Delete.addColumn:([B[B)Lorg/apache/hadoop/hbase/client/Delete;
     243: pop
     244: new           #69                 // class org/apache/hadoop/hbase/client/RowMutations
     247: dup
     248: getstatic     #45                 // Field ROW:[B
     251: invokespecial #70                 // Method org/apache/hadoop/hbase/client/RowMutations."<init>":([B)V
     254: astore        5
     256: aload         5
     258: aload_3
     259: invokevirtual #71                 // Method org/apache/hadoop/hbase/client/RowMutations.add:(Lorg/apache/hadoop/hbase/client/Put;)V
     262: aload         5
     264: aload         4
     266: invokevirtual #72                 // Method org/apache/hadoop/hbase/client/RowMutations.add:(Lorg/apache/hadoop/hbase/client/Delete;)V
     269: aload_2
     270: aload         5
     272: invokeinterface #73,  2           // InterfaceMethod org/apache/hadoop/hbase/client/Table.mutateRow:(Lorg/apache/hadoop/hbase/client/RowMutations;)V
     277: aload_0
     278: ldc           #12                 // class org/apache/hadoop/hbase/coprocessor/SimpleRegionObserver
     280: iconst_5
     281: anewarray     #11                 // class java/lang/String
     284: dup
     285: iconst_0
     286: ldc           #33                 // String hadPreGet
     288: aastore
     289: dup
     290: iconst_1
     291: ldc           #34                 // String hadPostGet
     293: aastore
     294: dup
     295: iconst_2
     296: ldc           #35                 // String hadPrePut
     298: aastore
     299: dup
     300: iconst_3
     301: ldc           #36                 // String hadPostPut
     303: aastore
     304: dup
     305: iconst_4
     306: ldc           #68                 // String hadDeleted
     308: aastore
     309: aload_1
     310: iconst_5
     311: anewarray     #41                 // class java/lang/Boolean
     314: dup
     315: iconst_0
     316: iconst_0
     317: invokestatic  #42                 // Method java/lang/Boolean.valueOf:(Z)Ljava/lang/Boolean;
     320: aastore
     321: dup
     322: iconst_1
     323: iconst_0
     324: invokestatic  #42                 // Method java/lang/Boolean.valueOf:(Z)Ljava/lang/Boolean;
     327: aastore
     328: dup
     329: iconst_2
     330: iconst_1
     331: invokestatic  #42                 // Method java/lang/Boolean.valueOf:(Z)Ljava/lang/Boolean;
     334: aastore
     335: dup
     336: iconst_3
     337: iconst_1
     338: invokestatic  #42                 // Method java/lang/Boolean.valueOf:(Z)Ljava/lang/Boolean;
     341: aastore
     342: dup
     343: iconst_4
     344: iconst_1
     345: invokestatic  #42                 // Method java/lang/Boolean.valueOf:(Z)Ljava/lang/Boolean;
     348: aastore
     349: invokespecial #43                 // Method verifyMethodResult:(Ljava/lang/Class;[Ljava/lang/String;Lorg/apache/hadoop/hbase/TableName;[Ljava/lang/Object;)V
     352: getstatic     #5                  // Field util:Lorg/apache/hadoop/hbase/HBaseTestingUtility;
     355: aload_1
     356: invokevirtual #66                 // Method org/apache/hadoop/hbase/HBaseTestingUtility.deleteTable:(Lorg/apache/hadoop/hbase/TableName;)V
     359: aload_2
     360: invokeinterface #67,  1           // InterfaceMethod org/apache/hadoop/hbase/client/Table.close:()V
     365: goto          386
     368: astore        6
     370: getstatic     #5                  // Field util:Lorg/apache/hadoop/hbase/HBaseTestingUtility;
     373: aload_1
     374: invokevirtual #66                 // Method org/apache/hadoop/hbase/HBaseTestingUtility.deleteTable:(Lorg/apache/hadoop/hbase/TableName;)V
     377: aload_2
     378: invokeinterface #67,  1           // InterfaceMethod org/apache/hadoop/hbase/client/Table.close:()V
     383: aload         6
     385: athrow
     386: return
    Exception table:
       from    to  target type
          68   352   368   any
         368   370   368   any

  public void testIncrementHook() throws java.io.IOException;
    Code:
       0: new           #19                 // class java/lang/StringBuilder
       3: dup
       4: invokespecial #20                 // Method java/lang/StringBuilder."<init>":()V
       7: getstatic     #21                 // Field TEST_TABLE:Lorg/apache/hadoop/hbase/TableName;
      10: invokevirtual #22                 // Method org/apache/hadoop/hbase/TableName.getNameAsString:()Ljava/lang/String;
      13: invokevirtual #23                 // Method java/lang/StringBuilder.append:(Ljava/lang/String;)Ljava/lang/StringBuilder;
      16: ldc           #24                 // String .
      18: invokevirtual #23                 // Method java/lang/StringBuilder.append:(Ljava/lang/String;)Ljava/lang/StringBuilder;
      21: aload_0
      22: getfield      #4                  // Field name:Lorg/junit/rules/TestName;
      25: invokevirtual #25                 // Method org/junit/rules/TestName.getMethodName:()Ljava/lang/String;
      28: invokevirtual #23                 // Method java/lang/StringBuilder.append:(Ljava/lang/String;)Ljava/lang/StringBuilder;
      31: invokevirtual #26                 // Method java/lang/StringBuilder.toString:()Ljava/lang/String;
      34: invokestatic  #27                 // Method org/apache/hadoop/hbase/TableName.valueOf:(Ljava/lang/String;)Lorg/apache/hadoop/hbase/TableName;
      37: astore_1
      38: getstatic     #5                  // Field util:Lorg/apache/hadoop/hbase/HBaseTestingUtility;
      41: aload_1
      42: iconst_3
      43: anewarray     #28                 // class "[B"
      46: dup
      47: iconst_0
      48: getstatic     #29                 // Field A:[B
      51: aastore
      52: dup
      53: iconst_1
      54: getstatic     #30                 // Field B:[B
      57: aastore
      58: dup
      59: iconst_2
      60: getstatic     #31                 // Field C:[B
      63: aastore
      64: invokevirtual #32                 // Method org/apache/hadoop/hbase/HBaseTestingUtility.createTable:(Lorg/apache/hadoop/hbase/TableName;[[B)Lorg/apache/hadoop/hbase/client/Table;
      67: astore_2
      68: new           #74                 // class org/apache/hadoop/hbase/client/Increment
      71: dup
      72: iconst_0
      73: invokestatic  #75                 // Method org/apache/hadoop/hbase/util/Bytes.toBytes:(I)[B
      76: invokespecial #76                 // Method org/apache/hadoop/hbase/client/Increment."<init>":([B)V
      79: astore_3
      80: aload_3
      81: getstatic     #29                 // Field A:[B
      84: getstatic     #29                 // Field A:[B
      87: lconst_1
      88: invokevirtual #77                 // Method org/apache/hadoop/hbase/client/Increment.addColumn:([B[BJ)Lorg/apache/hadoop/hbase/client/Increment;
      91: pop
      92: aload_0
      93: ldc           #12                 // class org/apache/hadoop/hbase/coprocessor/SimpleRegionObserver
      95: iconst_3
      96: anewarray     #11                 // class java/lang/String
      99: dup
     100: iconst_0
     101: ldc           #78                 // String hadPreIncrement
     103: aastore
     104: dup
     105: iconst_1
     106: ldc           #79                 // String hadPostIncrement
     108: aastore
     109: dup
     110: iconst_2
     111: ldc           #80                 // String hadPreIncrementAfterRowLock
     113: aastore
     114: aload_1
     115: iconst_3
     116: anewarray     #41                 // class java/lang/Boolean
     119: dup
     120: iconst_0
     121: iconst_0
     122: invokestatic  #42                 // Method java/lang/Boolean.valueOf:(Z)Ljava/lang/Boolean;
     125: aastore
     126: dup
     127: iconst_1
     128: iconst_0
     129: invokestatic  #42                 // Method java/lang/Boolean.valueOf:(Z)Ljava/lang/Boolean;
     132: aastore
     133: dup
     134: iconst_2
     135: iconst_0
     136: invokestatic  #42                 // Method java/lang/Boolean.valueOf:(Z)Ljava/lang/Boolean;
     139: aastore
     140: invokespecial #43                 // Method verifyMethodResult:(Ljava/lang/Class;[Ljava/lang/String;Lorg/apache/hadoop/hbase/TableName;[Ljava/lang/Object;)V
     143: aload_2
     144: aload_3
     145: invokeinterface #81,  2           // InterfaceMethod org/apache/hadoop/hbase/client/Table.increment:(Lorg/apache/hadoop/hbase/client/Increment;)Lorg/apache/hadoop/hbase/client/Result;
     150: pop
     151: aload_0
     152: ldc           #12                 // class org/apache/hadoop/hbase/coprocessor/SimpleRegionObserver
     154: iconst_3
     155: anewarray     #11                 // class java/lang/String
     158: dup
     159: iconst_0
     160: ldc           #78                 // String hadPreIncrement
     162: aastore
     163: dup
     164: iconst_1
     165: ldc           #79                 // String hadPostIncrement
     167: aastore
     168: dup
     169: iconst_2
     170: ldc           #80                 // String hadPreIncrementAfterRowLock
     172: aastore
     173: aload_1
     174: iconst_3
     175: anewarray     #41                 // class java/lang/Boolean
     178: dup
     179: iconst_0
     180: iconst_1
     181: invokestatic  #42                 // Method java/lang/Boolean.valueOf:(Z)Ljava/lang/Boolean;
     184: aastore
     185: dup
     186: iconst_1
     187: iconst_1
     188: invokestatic  #42                 // Method java/lang/Boolean.valueOf:(Z)Ljava/lang/Boolean;
     191: aastore
     192: dup
     193: iconst_2
     194: iconst_1
     195: invokestatic  #42                 // Method java/lang/Boolean.valueOf:(Z)Ljava/lang/Boolean;
     198: aastore
     199: invokespecial #43                 // Method verifyMethodResult:(Ljava/lang/Class;[Ljava/lang/String;Lorg/apache/hadoop/hbase/TableName;[Ljava/lang/Object;)V
     202: getstatic     #5                  // Field util:Lorg/apache/hadoop/hbase/HBaseTestingUtility;
     205: aload_1
     206: invokevirtual #66                 // Method org/apache/hadoop/hbase/HBaseTestingUtility.deleteTable:(Lorg/apache/hadoop/hbase/TableName;)V
     209: aload_2
     210: invokeinterface #67,  1           // InterfaceMethod org/apache/hadoop/hbase/client/Table.close:()V
     215: goto          236
     218: astore        4
     220: getstatic     #5                  // Field util:Lorg/apache/hadoop/hbase/HBaseTestingUtility;
     223: aload_1
     224: invokevirtual #66                 // Method org/apache/hadoop/hbase/HBaseTestingUtility.deleteTable:(Lorg/apache/hadoop/hbase/TableName;)V
     227: aload_2
     228: invokeinterface #67,  1           // InterfaceMethod org/apache/hadoop/hbase/client/Table.close:()V
     233: aload         4
     235: athrow
     236: return
    Exception table:
       from    to  target type
          68   202   218   any
         218   220   218   any

  public void testCheckAndPutHooks() throws java.io.IOException;
    Code:
       0: new           #19                 // class java/lang/StringBuilder
       3: dup
       4: invokespecial #20                 // Method java/lang/StringBuilder."<init>":()V
       7: getstatic     #21                 // Field TEST_TABLE:Lorg/apache/hadoop/hbase/TableName;
      10: invokevirtual #22                 // Method org/apache/hadoop/hbase/TableName.getNameAsString:()Ljava/lang/String;
      13: invokevirtual #23                 // Method java/lang/StringBuilder.append:(Ljava/lang/String;)Ljava/lang/StringBuilder;
      16: ldc           #24                 // String .
      18: invokevirtual #23                 // Method java/lang/StringBuilder.append:(Ljava/lang/String;)Ljava/lang/StringBuilder;
      21: aload_0
      22: getfield      #4                  // Field name:Lorg/junit/rules/TestName;
      25: invokevirtual #25                 // Method org/junit/rules/TestName.getMethodName:()Ljava/lang/String;
      28: invokevirtual #23                 // Method java/lang/StringBuilder.append:(Ljava/lang/String;)Ljava/lang/StringBuilder;
      31: invokevirtual #26                 // Method java/lang/StringBuilder.toString:()Ljava/lang/String;
      34: invokestatic  #27                 // Method org/apache/hadoop/hbase/TableName.valueOf:(Ljava/lang/String;)Lorg/apache/hadoop/hbase/TableName;
      37: astore_1
      38: getstatic     #5                  // Field util:Lorg/apache/hadoop/hbase/HBaseTestingUtility;
      41: aload_1
      42: iconst_3
      43: anewarray     #28                 // class "[B"
      46: dup
      47: iconst_0
      48: getstatic     #29                 // Field A:[B
      51: aastore
      52: dup
      53: iconst_1
      54: getstatic     #30                 // Field B:[B
      57: aastore
      58: dup
      59: iconst_2
      60: getstatic     #31                 // Field C:[B
      63: aastore
      64: invokevirtual #32                 // Method org/apache/hadoop/hbase/HBaseTestingUtility.createTable:(Lorg/apache/hadoop/hbase/TableName;[[B)Lorg/apache/hadoop/hbase/client/Table;
      67: astore_2
      68: aconst_null
      69: astore_3
      70: new           #44                 // class org/apache/hadoop/hbase/client/Put
      73: dup
      74: iconst_0
      75: invokestatic  #75                 // Method org/apache/hadoop/hbase/util/Bytes.toBytes:(I)[B
      78: invokespecial #46                 // Method org/apache/hadoop/hbase/client/Put."<init>":([B)V
      81: astore        4
      83: aload         4
      85: getstatic     #29                 // Field A:[B
      88: getstatic     #29                 // Field A:[B
      91: getstatic     #29                 // Field A:[B
      94: invokevirtual #47                 // Method org/apache/hadoop/hbase/client/Put.addColumn:([B[B[B)Lorg/apache/hadoop/hbase/client/Put;
      97: pop
      98: aload_2
      99: aload         4
     101: invokeinterface #48,  2           // InterfaceMethod org/apache/hadoop/hbase/client/Table.put:(Lorg/apache/hadoop/hbase/client/Put;)V
     106: new           #44                 // class org/apache/hadoop/hbase/client/Put
     109: dup
     110: iconst_0
     111: invokestatic  #75                 // Method org/apache/hadoop/hbase/util/Bytes.toBytes:(I)[B
     114: invokespecial #46                 // Method org/apache/hadoop/hbase/client/Put."<init>":([B)V
     117: astore        4
     119: aload         4
     121: getstatic     #29                 // Field A:[B
     124: getstatic     #29                 // Field A:[B
     127: getstatic     #29                 // Field A:[B
     130: invokevirtual #47                 // Method org/apache/hadoop/hbase/client/Put.addColumn:([B[B[B)Lorg/apache/hadoop/hbase/client/Put;
     133: pop
     134: aload_0
     135: ldc           #12                 // class org/apache/hadoop/hbase/coprocessor/SimpleRegionObserver
     137: iconst_3
     138: anewarray     #11                 // class java/lang/String
     141: dup
     142: iconst_0
     143: ldc           #82                 // String hadPreCheckAndPut
     145: aastore
     146: dup
     147: iconst_1
     148: ldc           #83                 // String hadPreCheckAndPutAfterRowLock
     150: aastore
     151: dup
     152: iconst_2
     153: ldc           #84                 // String hadPostCheckAndPut
     155: aastore
     156: aload_1
     157: iconst_3
     158: anewarray     #41                 // class java/lang/Boolean
     161: dup
     162: iconst_0
     163: iconst_0
     164: invokestatic  #42                 // Method java/lang/Boolean.valueOf:(Z)Ljava/lang/Boolean;
     167: aastore
     168: dup
     169: iconst_1
     170: iconst_0
     171: invokestatic  #42                 // Method java/lang/Boolean.valueOf:(Z)Ljava/lang/Boolean;
     174: aastore
     175: dup
     176: iconst_2
     177: iconst_0
     178: invokestatic  #42                 // Method java/lang/Boolean.valueOf:(Z)Ljava/lang/Boolean;
     181: aastore
     182: invokespecial #43                 // Method verifyMethodResult:(Ljava/lang/Class;[Ljava/lang/String;Lorg/apache/hadoop/hbase/TableName;[Ljava/lang/Object;)V
     185: aload_2
     186: iconst_0
     187: invokestatic  #75                 // Method org/apache/hadoop/hbase/util/Bytes.toBytes:(I)[B
     190: getstatic     #29                 // Field A:[B
     193: invokeinterface #85,  3           // InterfaceMethod org/apache/hadoop/hbase/client/Table.checkAndMutate:([B[B)Lorg/apache/hadoop/hbase/client/Table$CheckAndMutateBuilder;
     198: getstatic     #29                 // Field A:[B
     201: invokeinterface #86,  2           // InterfaceMethod org/apache/hadoop/hbase/client/Table$CheckAndMutateBuilder.qualifier:([B)Lorg/apache/hadoop/hbase/client/Table$CheckAndMutateBuilder;
     206: getstatic     #29                 // Field A:[B
     209: invokeinterface #87,  2           // InterfaceMethod org/apache/hadoop/hbase/client/Table$CheckAndMutateBuilder.ifEquals:([B)Lorg/apache/hadoop/hbase/client/Table$CheckAndMutateBuilder;
     214: aload         4
     216: invokeinterface #88,  2           // InterfaceMethod org/apache/hadoop/hbase/client/Table$CheckAndMutateBuilder.thenPut:(Lorg/apache/hadoop/hbase/client/Put;)Z
     221: pop
     222: aload_0
     223: ldc           #12                 // class org/apache/hadoop/hbase/coprocessor/SimpleRegionObserver
     225: iconst_3
     226: anewarray     #11                 // class java/lang/String
     229: dup
     230: iconst_0
     231: ldc           #82                 // String hadPreCheckAndPut
     233: aastore
     234: dup
     235: iconst_1
     236: ldc           #83                 // String hadPreCheckAndPutAfterRowLock
     238: aastore
     239: dup
     240: iconst_2
     241: ldc           #84                 // String hadPostCheckAndPut
     243: aastore
     244: aload_1
     245: iconst_3
     246: anewarray     #41                 // class java/lang/Boolean
     249: dup
     250: iconst_0
     251: iconst_1
     252: invokestatic  #42                 // Method java/lang/Boolean.valueOf:(Z)Ljava/lang/Boolean;
     255: aastore
     256: dup
     257: iconst_1
     258: iconst_1
     259: invokestatic  #42                 // Method java/lang/Boolean.valueOf:(Z)Ljava/lang/Boolean;
     262: aastore
     263: dup
     264: iconst_2
     265: iconst_1
     266: invokestatic  #42                 // Method java/lang/Boolean.valueOf:(Z)Ljava/lang/Boolean;
     269: aastore
     270: invokespecial #43                 // Method verifyMethodResult:(Ljava/lang/Class;[Ljava/lang/String;Lorg/apache/hadoop/hbase/TableName;[Ljava/lang/Object;)V
     273: aload_2
     274: ifnull        357
     277: aload_3
     278: ifnull        301
     281: aload_2
     282: invokeinterface #67,  1           // InterfaceMethod org/apache/hadoop/hbase/client/Table.close:()V
     287: goto          357
     290: astore        4
     292: aload_3
     293: aload         4
     295: invokevirtual #90                 // Method java/lang/Throwable.addSuppressed:(Ljava/lang/Throwable;)V
     298: goto          357
     301: aload_2
     302: invokeinterface #67,  1           // InterfaceMethod org/apache/hadoop/hbase/client/Table.close:()V
     307: goto          357
     310: astore        4
     312: aload         4
     314: astore_3
     315: aload         4
     317: athrow
     318: astore        5
     320: aload_2
     321: ifnull        354
     324: aload_3
     325: ifnull        348
     328: aload_2
     329: invokeinterface #67,  1           // InterfaceMethod org/apache/hadoop/hbase/client/Table.close:()V
     334: goto          354
     337: astore        6
     339: aload_3
     340: aload         6
     342: invokevirtual #90                 // Method java/lang/Throwable.addSuppressed:(Ljava/lang/Throwable;)V
     345: goto          354
     348: aload_2
     349: invokeinterface #67,  1           // InterfaceMethod org/apache/hadoop/hbase/client/Table.close:()V
     354: aload         5
     356: athrow
     357: getstatic     #5                  // Field util:Lorg/apache/hadoop/hbase/HBaseTestingUtility;
     360: aload_1
     361: invokevirtual #66                 // Method org/apache/hadoop/hbase/HBaseTestingUtility.deleteTable:(Lorg/apache/hadoop/hbase/TableName;)V
     364: goto          379
     367: astore        7
     369: getstatic     #5                  // Field util:Lorg/apache/hadoop/hbase/HBaseTestingUtility;
     372: aload_1
     373: invokevirtual #66                 // Method org/apache/hadoop/hbase/HBaseTestingUtility.deleteTable:(Lorg/apache/hadoop/hbase/TableName;)V
     376: aload         7
     378: athrow
     379: return
    Exception table:
       from    to  target type
         281   287   290   Class java/lang/Throwable
          70   273   310   Class java/lang/Throwable
          70   273   318   any
         328   334   337   Class java/lang/Throwable
         310   320   318   any
          38   357   367   any
         367   369   367   any

  public void testCheckAndDeleteHooks() throws java.io.IOException;
    Code:
       0: new           #19                 // class java/lang/StringBuilder
       3: dup
       4: invokespecial #20                 // Method java/lang/StringBuilder."<init>":()V
       7: getstatic     #21                 // Field TEST_TABLE:Lorg/apache/hadoop/hbase/TableName;
      10: invokevirtual #22                 // Method org/apache/hadoop/hbase/TableName.getNameAsString:()Ljava/lang/String;
      13: invokevirtual #23                 // Method java/lang/StringBuilder.append:(Ljava/lang/String;)Ljava/lang/StringBuilder;
      16: ldc           #24                 // String .
      18: invokevirtual #23                 // Method java/lang/StringBuilder.append:(Ljava/lang/String;)Ljava/lang/StringBuilder;
      21: aload_0
      22: getfield      #4                  // Field name:Lorg/junit/rules/TestName;
      25: invokevirtual #25                 // Method org/junit/rules/TestName.getMethodName:()Ljava/lang/String;
      28: invokevirtual #23                 // Method java/lang/StringBuilder.append:(Ljava/lang/String;)Ljava/lang/StringBuilder;
      31: invokevirtual #26                 // Method java/lang/StringBuilder.toString:()Ljava/lang/String;
      34: invokestatic  #27                 // Method org/apache/hadoop/hbase/TableName.valueOf:(Ljava/lang/String;)Lorg/apache/hadoop/hbase/TableName;
      37: astore_1
      38: getstatic     #5                  // Field util:Lorg/apache/hadoop/hbase/HBaseTestingUtility;
      41: aload_1
      42: iconst_3
      43: anewarray     #28                 // class "[B"
      46: dup
      47: iconst_0
      48: getstatic     #29                 // Field A:[B
      51: aastore
      52: dup
      53: iconst_1
      54: getstatic     #30                 // Field B:[B
      57: aastore
      58: dup
      59: iconst_2
      60: getstatic     #31                 // Field C:[B
      63: aastore
      64: invokevirtual #32                 // Method org/apache/hadoop/hbase/HBaseTestingUtility.createTable:(Lorg/apache/hadoop/hbase/TableName;[[B)Lorg/apache/hadoop/hbase/client/Table;
      67: astore_2
      68: new           #44                 // class org/apache/hadoop/hbase/client/Put
      71: dup
      72: iconst_0
      73: invokestatic  #75                 // Method org/apache/hadoop/hbase/util/Bytes.toBytes:(I)[B
      76: invokespecial #46                 // Method org/apache/hadoop/hbase/client/Put."<init>":([B)V
      79: astore_3
      80: aload_3
      81: getstatic     #29                 // Field A:[B
      84: getstatic     #29                 // Field A:[B
      87: getstatic     #29                 // Field A:[B
      90: invokevirtual #47                 // Method org/apache/hadoop/hbase/client/Put.addColumn:([B[B[B)Lorg/apache/hadoop/hbase/client/Put;
      93: pop
      94: aload_2
      95: aload_3
      96: invokeinterface #48,  2           // InterfaceMethod org/apache/hadoop/hbase/client/Table.put:(Lorg/apache/hadoop/hbase/client/Put;)V
     101: new           #62                 // class org/apache/hadoop/hbase/client/Delete
     104: dup
     105: iconst_0
     106: invokestatic  #75                 // Method org/apache/hadoop/hbase/util/Bytes.toBytes:(I)[B
     109: invokespecial #63                 // Method org/apache/hadoop/hbase/client/Delete."<init>":([B)V
     112: astore        4
     114: aload_2
     115: aload         4
     117: invokeinterface #65,  2           // InterfaceMethod org/apache/hadoop/hbase/client/Table.delete:(Lorg/apache/hadoop/hbase/client/Delete;)V
     122: aload_0
     123: ldc           #12                 // class org/apache/hadoop/hbase/coprocessor/SimpleRegionObserver
     125: iconst_3
     126: anewarray     #11                 // class java/lang/String
     129: dup
     130: iconst_0
     131: ldc           #91                 // String hadPreCheckAndDelete
     133: aastore
     134: dup
     135: iconst_1
     136: ldc           #92                 // String hadPreCheckAndDeleteAfterRowLock
     138: aastore
     139: dup
     140: iconst_2
     141: ldc           #93                 // String hadPostCheckAndDelete
     143: aastore
     144: aload_1
     145: iconst_3
     146: anewarray     #41                 // class java/lang/Boolean
     149: dup
     150: iconst_0
     151: iconst_0
     152: invokestatic  #42                 // Method java/lang/Boolean.valueOf:(Z)Ljava/lang/Boolean;
     155: aastore
     156: dup
     157: iconst_1
     158: iconst_0
     159: invokestatic  #42                 // Method java/lang/Boolean.valueOf:(Z)Ljava/lang/Boolean;
     162: aastore
     163: dup
     164: iconst_2
     165: iconst_0
     166: invokestatic  #42                 // Method java/lang/Boolean.valueOf:(Z)Ljava/lang/Boolean;
     169: aastore
     170: invokespecial #43                 // Method verifyMethodResult:(Ljava/lang/Class;[Ljava/lang/String;Lorg/apache/hadoop/hbase/TableName;[Ljava/lang/Object;)V
     173: aload_2
     174: iconst_0
     175: invokestatic  #75                 // Method org/apache/hadoop/hbase/util/Bytes.toBytes:(I)[B
     178: getstatic     #29                 // Field A:[B
     181: invokeinterface #85,  3           // InterfaceMethod org/apache/hadoop/hbase/client/Table.checkAndMutate:([B[B)Lorg/apache/hadoop/hbase/client/Table$CheckAndMutateBuilder;
     186: getstatic     #29                 // Field A:[B
     189: invokeinterface #86,  2           // InterfaceMethod org/apache/hadoop/hbase/client/Table$CheckAndMutateBuilder.qualifier:([B)Lorg/apache/hadoop/hbase/client/Table$CheckAndMutateBuilder;
     194: getstatic     #29                 // Field A:[B
     197: invokeinterface #87,  2           // InterfaceMethod org/apache/hadoop/hbase/client/Table$CheckAndMutateBuilder.ifEquals:([B)Lorg/apache/hadoop/hbase/client/Table$CheckAndMutateBuilder;
     202: aload         4
     204: invokeinterface #94,  2           // InterfaceMethod org/apache/hadoop/hbase/client/Table$CheckAndMutateBuilder.thenDelete:(Lorg/apache/hadoop/hbase/client/Delete;)Z
     209: pop
     210: aload_0
     211: ldc           #12                 // class org/apache/hadoop/hbase/coprocessor/SimpleRegionObserver
     213: iconst_3
     214: anewarray     #11                 // class java/lang/String
     217: dup
     218: iconst_0
     219: ldc           #91                 // String hadPreCheckAndDelete
     221: aastore
     222: dup
     223: iconst_1
     224: ldc           #92                 // String hadPreCheckAndDeleteAfterRowLock
     226: aastore
     227: dup
     228: iconst_2
     229: ldc           #93                 // String hadPostCheckAndDelete
     231: aastore
     232: aload_1
     233: iconst_3
     234: anewarray     #41                 // class java/lang/Boolean
     237: dup
     238: iconst_0
     239: iconst_1
     240: invokestatic  #42                 // Method java/lang/Boolean.valueOf:(Z)Ljava/lang/Boolean;
     243: aastore
     244: dup
     245: iconst_1
     246: iconst_1
     247: invokestatic  #42                 // Method java/lang/Boolean.valueOf:(Z)Ljava/lang/Boolean;
     250: aastore
     251: dup
     252: iconst_2
     253: iconst_1
     254: invokestatic  #42                 // Method java/lang/Boolean.valueOf:(Z)Ljava/lang/Boolean;
     257: aastore
     258: invokespecial #43                 // Method verifyMethodResult:(Ljava/lang/Class;[Ljava/lang/String;Lorg/apache/hadoop/hbase/TableName;[Ljava/lang/Object;)V
     261: getstatic     #5                  // Field util:Lorg/apache/hadoop/hbase/HBaseTestingUtility;
     264: aload_1
     265: invokevirtual #66                 // Method org/apache/hadoop/hbase/HBaseTestingUtility.deleteTable:(Lorg/apache/hadoop/hbase/TableName;)V
     268: aload_2
     269: invokeinterface #67,  1           // InterfaceMethod org/apache/hadoop/hbase/client/Table.close:()V
     274: goto          295
     277: astore        5
     279: getstatic     #5                  // Field util:Lorg/apache/hadoop/hbase/HBaseTestingUtility;
     282: aload_1
     283: invokevirtual #66                 // Method org/apache/hadoop/hbase/HBaseTestingUtility.deleteTable:(Lorg/apache/hadoop/hbase/TableName;)V
     286: aload_2
     287: invokeinterface #67,  1           // InterfaceMethod org/apache/hadoop/hbase/client/Table.close:()V
     292: aload         5
     294: athrow
     295: return
    Exception table:
       from    to  target type
          68   261   277   any
         277   279   277   any

  public void testAppendHook() throws java.io.IOException;
    Code:
       0: new           #19                 // class java/lang/StringBuilder
       3: dup
       4: invokespecial #20                 // Method java/lang/StringBuilder."<init>":()V
       7: getstatic     #21                 // Field TEST_TABLE:Lorg/apache/hadoop/hbase/TableName;
      10: invokevirtual #22                 // Method org/apache/hadoop/hbase/TableName.getNameAsString:()Ljava/lang/String;
      13: invokevirtual #23                 // Method java/lang/StringBuilder.append:(Ljava/lang/String;)Ljava/lang/StringBuilder;
      16: ldc           #24                 // String .
      18: invokevirtual #23                 // Method java/lang/StringBuilder.append:(Ljava/lang/String;)Ljava/lang/StringBuilder;
      21: aload_0
      22: getfield      #4                  // Field name:Lorg/junit/rules/TestName;
      25: invokevirtual #25                 // Method org/junit/rules/TestName.getMethodName:()Ljava/lang/String;
      28: invokevirtual #23                 // Method java/lang/StringBuilder.append:(Ljava/lang/String;)Ljava/lang/StringBuilder;
      31: invokevirtual #26                 // Method java/lang/StringBuilder.toString:()Ljava/lang/String;
      34: invokestatic  #27                 // Method org/apache/hadoop/hbase/TableName.valueOf:(Ljava/lang/String;)Lorg/apache/hadoop/hbase/TableName;
      37: astore_1
      38: getstatic     #5                  // Field util:Lorg/apache/hadoop/hbase/HBaseTestingUtility;
      41: aload_1
      42: iconst_3
      43: anewarray     #28                 // class "[B"
      46: dup
      47: iconst_0
      48: getstatic     #29                 // Field A:[B
      51: aastore
      52: dup
      53: iconst_1
      54: getstatic     #30                 // Field B:[B
      57: aastore
      58: dup
      59: iconst_2
      60: getstatic     #31                 // Field C:[B
      63: aastore
      64: invokevirtual #32                 // Method org/apache/hadoop/hbase/HBaseTestingUtility.createTable:(Lorg/apache/hadoop/hbase/TableName;[[B)Lorg/apache/hadoop/hbase/client/Table;
      67: astore_2
      68: new           #95                 // class org/apache/hadoop/hbase/client/Append
      71: dup
      72: iconst_0
      73: invokestatic  #75                 // Method org/apache/hadoop/hbase/util/Bytes.toBytes:(I)[B
      76: invokespecial #96                 // Method org/apache/hadoop/hbase/client/Append."<init>":([B)V
      79: astore_3
      80: aload_3
      81: getstatic     #29                 // Field A:[B
      84: getstatic     #29                 // Field A:[B
      87: getstatic     #29                 // Field A:[B
      90: invokevirtual #97                 // Method org/apache/hadoop/hbase/client/Append.addColumn:([B[B[B)Lorg/apache/hadoop/hbase/client/Append;
      93: pop
      94: aload_0
      95: ldc           #12                 // class org/apache/hadoop/hbase/coprocessor/SimpleRegionObserver
      97: iconst_3
      98: anewarray     #11                 // class java/lang/String
     101: dup
     102: iconst_0
     103: ldc           #98                 // String hadPreAppend
     105: aastore
     106: dup
     107: iconst_1
     108: ldc           #99                 // String hadPostAppend
     110: aastore
     111: dup
     112: iconst_2
     113: ldc           #100                // String hadPreAppendAfterRowLock
     115: aastore
     116: aload_1
     117: iconst_3
     118: anewarray     #41                 // class java/lang/Boolean
     121: dup
     122: iconst_0
     123: iconst_0
     124: invokestatic  #42                 // Method java/lang/Boolean.valueOf:(Z)Ljava/lang/Boolean;
     127: aastore
     128: dup
     129: iconst_1
     130: iconst_0
     131: invokestatic  #42                 // Method java/lang/Boolean.valueOf:(Z)Ljava/lang/Boolean;
     134: aastore
     135: dup
     136: iconst_2
     137: iconst_0
     138: invokestatic  #42                 // Method java/lang/Boolean.valueOf:(Z)Ljava/lang/Boolean;
     141: aastore
     142: invokespecial #43                 // Method verifyMethodResult:(Ljava/lang/Class;[Ljava/lang/String;Lorg/apache/hadoop/hbase/TableName;[Ljava/lang/Object;)V
     145: aload_2
     146: aload_3
     147: invokeinterface #101,  2          // InterfaceMethod org/apache/hadoop/hbase/client/Table.append:(Lorg/apache/hadoop/hbase/client/Append;)Lorg/apache/hadoop/hbase/client/Result;
     152: pop
     153: aload_0
     154: ldc           #12                 // class org/apache/hadoop/hbase/coprocessor/SimpleRegionObserver
     156: iconst_3
     157: anewarray     #11                 // class java/lang/String
     160: dup
     161: iconst_0
     162: ldc           #98                 // String hadPreAppend
     164: aastore
     165: dup
     166: iconst_1
     167: ldc           #99                 // String hadPostAppend
     169: aastore
     170: dup
     171: iconst_2
     172: ldc           #100                // String hadPreAppendAfterRowLock
     174: aastore
     175: aload_1
     176: iconst_3
     177: anewarray     #41                 // class java/lang/Boolean
     180: dup
     181: iconst_0
     182: iconst_1
     183: invokestatic  #42                 // Method java/lang/Boolean.valueOf:(Z)Ljava/lang/Boolean;
     186: aastore
     187: dup
     188: iconst_1
     189: iconst_1
     190: invokestatic  #42                 // Method java/lang/Boolean.valueOf:(Z)Ljava/lang/Boolean;
     193: aastore
     194: dup
     195: iconst_2
     196: iconst_1
     197: invokestatic  #42                 // Method java/lang/Boolean.valueOf:(Z)Ljava/lang/Boolean;
     200: aastore
     201: invokespecial #43                 // Method verifyMethodResult:(Ljava/lang/Class;[Ljava/lang/String;Lorg/apache/hadoop/hbase/TableName;[Ljava/lang/Object;)V
     204: getstatic     #5                  // Field util:Lorg/apache/hadoop/hbase/HBaseTestingUtility;
     207: aload_1
     208: invokevirtual #66                 // Method org/apache/hadoop/hbase/HBaseTestingUtility.deleteTable:(Lorg/apache/hadoop/hbase/TableName;)V
     211: aload_2
     212: invokeinterface #67,  1           // InterfaceMethod org/apache/hadoop/hbase/client/Table.close:()V
     217: goto          238
     220: astore        4
     222: getstatic     #5                  // Field util:Lorg/apache/hadoop/hbase/HBaseTestingUtility;
     225: aload_1
     226: invokevirtual #66                 // Method org/apache/hadoop/hbase/HBaseTestingUtility.deleteTable:(Lorg/apache/hadoop/hbase/TableName;)V
     229: aload_2
     230: invokeinterface #67,  1           // InterfaceMethod org/apache/hadoop/hbase/client/Table.close:()V
     235: aload         4
     237: athrow
     238: return
    Exception table:
       from    to  target type
          68   204   220   any
         220   222   220   any

  public void testHBase3583() throws java.io.IOException;
    Code:
       0: aload_0
       1: getfield      #4                  // Field name:Lorg/junit/rules/TestName;
       4: invokevirtual #25                 // Method org/junit/rules/TestName.getMethodName:()Ljava/lang/String;
       7: invokestatic  #27                 // Method org/apache/hadoop/hbase/TableName.valueOf:(Ljava/lang/String;)Lorg/apache/hadoop/hbase/TableName;
      10: astore_1
      11: getstatic     #5                  // Field util:Lorg/apache/hadoop/hbase/HBaseTestingUtility;
      14: aload_1
      15: iconst_3
      16: anewarray     #28                 // class "[B"
      19: dup
      20: iconst_0
      21: getstatic     #29                 // Field A:[B
      24: aastore
      25: dup
      26: iconst_1
      27: getstatic     #30                 // Field B:[B
      30: aastore
      31: dup
      32: iconst_2
      33: getstatic     #31                 // Field C:[B
      36: aastore
      37: invokevirtual #32                 // Method org/apache/hadoop/hbase/HBaseTestingUtility.createTable:(Lorg/apache/hadoop/hbase/TableName;[[B)Lorg/apache/hadoop/hbase/client/Table;
      40: pop
      41: getstatic     #5                  // Field util:Lorg/apache/hadoop/hbase/HBaseTestingUtility;
      44: aload_1
      45: invokevirtual #102                // Method org/apache/hadoop/hbase/HBaseTestingUtility.waitUntilAllRegionsAssigned:(Lorg/apache/hadoop/hbase/TableName;)V
      48: aload_0
      49: ldc           #12                 // class org/apache/hadoop/hbase/coprocessor/SimpleRegionObserver
      51: iconst_4
      52: anewarray     #11                 // class java/lang/String
      55: dup
      56: iconst_0
      57: ldc           #33                 // String hadPreGet
      59: aastore
      60: dup
      61: iconst_1
      62: ldc           #34                 // String hadPostGet
      64: aastore
      65: dup
      66: iconst_2
      67: ldc           #103                // String wasScannerNextCalled
      69: aastore
      70: dup
      71: iconst_3
      72: ldc           #104                // String wasScannerCloseCalled
      74: aastore
      75: aload_1
      76: iconst_4
      77: anewarray     #41                 // class java/lang/Boolean
      80: dup
      81: iconst_0
      82: iconst_0
      83: invokestatic  #42                 // Method java/lang/Boolean.valueOf:(Z)Ljava/lang/Boolean;
      86: aastore
      87: dup
      88: iconst_1
      89: iconst_0
      90: invokestatic  #42                 // Method java/lang/Boolean.valueOf:(Z)Ljava/lang/Boolean;
      93: aastore
      94: dup
      95: iconst_2
      96: iconst_0
      97: invokestatic  #42                 // Method java/lang/Boolean.valueOf:(Z)Ljava/lang/Boolean;
     100: aastore
     101: dup
     102: iconst_3
     103: iconst_0
     104: invokestatic  #42                 // Method java/lang/Boolean.valueOf:(Z)Ljava/lang/Boolean;
     107: aastore
     108: invokespecial #43                 // Method verifyMethodResult:(Ljava/lang/Class;[Ljava/lang/String;Lorg/apache/hadoop/hbase/TableName;[Ljava/lang/Object;)V
     111: getstatic     #5                  // Field util:Lorg/apache/hadoop/hbase/HBaseTestingUtility;
     114: invokevirtual #105                // Method org/apache/hadoop/hbase/HBaseTestingUtility.getConnection:()Lorg/apache/hadoop/hbase/client/Connection;
     117: aload_1
     118: invokeinterface #106,  2          // InterfaceMethod org/apache/hadoop/hbase/client/Connection.getTable:(Lorg/apache/hadoop/hbase/TableName;)Lorg/apache/hadoop/hbase/client/Table;
     123: astore_2
     124: new           #44                 // class org/apache/hadoop/hbase/client/Put
     127: dup
     128: getstatic     #45                 // Field ROW:[B
     131: invokespecial #46                 // Method org/apache/hadoop/hbase/client/Put."<init>":([B)V
     134: astore_3
     135: aload_3
     136: getstatic     #29                 // Field A:[B
     139: getstatic     #29                 // Field A:[B
     142: getstatic     #29                 // Field A:[B
     145: invokevirtual #47                 // Method org/apache/hadoop/hbase/client/Put.addColumn:([B[B[B)Lorg/apache/hadoop/hbase/client/Put;
     148: pop
     149: aload_2
     150: aload_3
     151: invokeinterface #48,  2           // InterfaceMethod org/apache/hadoop/hbase/client/Table.put:(Lorg/apache/hadoop/hbase/client/Put;)V
     156: new           #57                 // class org/apache/hadoop/hbase/client/Get
     159: dup
     160: getstatic     #45                 // Field ROW:[B
     163: invokespecial #58                 // Method org/apache/hadoop/hbase/client/Get."<init>":([B)V
     166: astore        4
     168: aload         4
     170: getstatic     #29                 // Field A:[B
     173: getstatic     #29                 // Field A:[B
     176: invokevirtual #59                 // Method org/apache/hadoop/hbase/client/Get.addColumn:([B[B)Lorg/apache/hadoop/hbase/client/Get;
     179: pop
     180: aload_2
     181: aload         4
     183: invokeinterface #60,  2           // InterfaceMethod org/apache/hadoop/hbase/client/Table.get:(Lorg/apache/hadoop/hbase/client/Get;)Lorg/apache/hadoop/hbase/client/Result;
     188: pop
     189: aload_0
     190: ldc           #12                 // class org/apache/hadoop/hbase/coprocessor/SimpleRegionObserver
     192: iconst_4
     193: anewarray     #11                 // class java/lang/String
     196: dup
     197: iconst_0
     198: ldc           #33                 // String hadPreGet
     200: aastore
     201: dup
     202: iconst_1
     203: ldc           #34                 // String hadPostGet
     205: aastore
     206: dup
     207: iconst_2
     208: ldc           #103                // String wasScannerNextCalled
     210: aastore
     211: dup
     212: iconst_3
     213: ldc           #104                // String wasScannerCloseCalled
     215: aastore
     216: aload_1
     217: iconst_4
     218: anewarray     #41                 // class java/lang/Boolean
     221: dup
     222: iconst_0
     223: iconst_1
     224: invokestatic  #42                 // Method java/lang/Boolean.valueOf:(Z)Ljava/lang/Boolean;
     227: aastore
     228: dup
     229: iconst_1
     230: iconst_1
     231: invokestatic  #42                 // Method java/lang/Boolean.valueOf:(Z)Ljava/lang/Boolean;
     234: aastore
     235: dup
     236: iconst_2
     237: iconst_0
     238: invokestatic  #42                 // Method java/lang/Boolean.valueOf:(Z)Ljava/lang/Boolean;
     241: aastore
     242: dup
     243: iconst_3
     244: iconst_0
     245: invokestatic  #42                 // Method java/lang/Boolean.valueOf:(Z)Ljava/lang/Boolean;
     248: aastore
     249: invokespecial #43                 // Method verifyMethodResult:(Ljava/lang/Class;[Ljava/lang/String;Lorg/apache/hadoop/hbase/TableName;[Ljava/lang/Object;)V
     252: new           #107                // class org/apache/hadoop/hbase/client/Scan
     255: dup
     256: invokespecial #108                // Method org/apache/hadoop/hbase/client/Scan."<init>":()V
     259: astore        5
     261: aload_2
     262: aload         5
     264: invokeinterface #109,  2          // InterfaceMethod org/apache/hadoop/hbase/client/Table.getScanner:(Lorg/apache/hadoop/hbase/client/Scan;)Lorg/apache/hadoop/hbase/client/ResultScanner;
     269: astore        6
     271: aload         6
     273: invokeinterface #110,  1          // InterfaceMethod org/apache/hadoop/hbase/client/ResultScanner.next:()Lorg/apache/hadoop/hbase/client/Result;
     278: astore        7
     280: aload         7
     282: ifnull        297
     285: aload         6
     287: invokeinterface #110,  1          // InterfaceMethod org/apache/hadoop/hbase/client/ResultScanner.next:()Lorg/apache/hadoop/hbase/client/Result;
     292: astore        7
     294: goto          280
     297: aload         6
     299: invokeinterface #111,  1          // InterfaceMethod org/apache/hadoop/hbase/client/ResultScanner.close:()V
     304: goto          319
     307: astore        8
     309: aload         6
     311: invokeinterface #111,  1          // InterfaceMethod org/apache/hadoop/hbase/client/ResultScanner.close:()V
     316: aload         8
     318: athrow
     319: aload_0
     320: ldc           #12                 // class org/apache/hadoop/hbase/coprocessor/SimpleRegionObserver
     322: iconst_2
     323: anewarray     #11                 // class java/lang/String
     326: dup
     327: iconst_0
     328: ldc           #103                // String wasScannerNextCalled
     330: aastore
     331: dup
     332: iconst_1
     333: ldc           #104                // String wasScannerCloseCalled
     335: aastore
     336: aload_1
     337: iconst_2
     338: anewarray     #41                 // class java/lang/Boolean
     341: dup
     342: iconst_0
     343: iconst_1
     344: invokestatic  #42                 // Method java/lang/Boolean.valueOf:(Z)Ljava/lang/Boolean;
     347: aastore
     348: dup
     349: iconst_1
     350: iconst_1
     351: invokestatic  #42                 // Method java/lang/Boolean.valueOf:(Z)Ljava/lang/Boolean;
     354: aastore
     355: invokespecial #43                 // Method verifyMethodResult:(Ljava/lang/Class;[Ljava/lang/String;Lorg/apache/hadoop/hbase/TableName;[Ljava/lang/Object;)V
     358: getstatic     #5                  // Field util:Lorg/apache/hadoop/hbase/HBaseTestingUtility;
     361: aload_1
     362: invokevirtual #66                 // Method org/apache/hadoop/hbase/HBaseTestingUtility.deleteTable:(Lorg/apache/hadoop/hbase/TableName;)V
     365: aload_2
     366: invokeinterface #67,  1           // InterfaceMethod org/apache/hadoop/hbase/client/Table.close:()V
     371: return
    Exception table:
       from    to  target type
         271   297   307   any
         307   309   307   any

  public void testHBASE14489() throws java.io.IOException;
    Code:
       0: aload_0
       1: getfield      #4                  // Field name:Lorg/junit/rules/TestName;
       4: invokevirtual #25                 // Method org/junit/rules/TestName.getMethodName:()Ljava/lang/String;
       7: invokestatic  #27                 // Method org/apache/hadoop/hbase/TableName.valueOf:(Ljava/lang/String;)Lorg/apache/hadoop/hbase/TableName;
      10: astore_1
      11: getstatic     #5                  // Field util:Lorg/apache/hadoop/hbase/HBaseTestingUtility;
      14: aload_1
      15: iconst_1
      16: anewarray     #28                 // class "[B"
      19: dup
      20: iconst_0
      21: getstatic     #29                 // Field A:[B
      24: aastore
      25: invokevirtual #32                 // Method org/apache/hadoop/hbase/HBaseTestingUtility.createTable:(Lorg/apache/hadoop/hbase/TableName;[[B)Lorg/apache/hadoop/hbase/client/Table;
      28: astore_2
      29: new           #44                 // class org/apache/hadoop/hbase/client/Put
      32: dup
      33: getstatic     #45                 // Field ROW:[B
      36: invokespecial #46                 // Method org/apache/hadoop/hbase/client/Put."<init>":([B)V
      39: astore_3
      40: aload_3
      41: getstatic     #29                 // Field A:[B
      44: getstatic     #29                 // Field A:[B
      47: getstatic     #29                 // Field A:[B
      50: invokevirtual #47                 // Method org/apache/hadoop/hbase/client/Put.addColumn:([B[B[B)Lorg/apache/hadoop/hbase/client/Put;
      53: pop
      54: aload_2
      55: aload_3
      56: invokeinterface #48,  2           // InterfaceMethod org/apache/hadoop/hbase/client/Table.put:(Lorg/apache/hadoop/hbase/client/Put;)V
      61: new           #107                // class org/apache/hadoop/hbase/client/Scan
      64: dup
      65: invokespecial #108                // Method org/apache/hadoop/hbase/client/Scan."<init>":()V
      68: astore        4
      70: aload         4
      72: new           #112                // class org/apache/hadoop/hbase/filter/FilterAllFilter
      75: dup
      76: invokespecial #113                // Method org/apache/hadoop/hbase/filter/FilterAllFilter."<init>":()V
      79: invokevirtual #114                // Method org/apache/hadoop/hbase/client/Scan.setFilter:(Lorg/apache/hadoop/hbase/filter/Filter;)Lorg/apache/hadoop/hbase/client/Scan;
      82: pop
      83: aload_2
      84: aload         4
      86: invokeinterface #109,  2          // InterfaceMethod org/apache/hadoop/hbase/client/Table.getScanner:(Lorg/apache/hadoop/hbase/client/Scan;)Lorg/apache/hadoop/hbase/client/ResultScanner;
      91: astore        5
      93: aload         5
      95: invokeinterface #110,  1          // InterfaceMethod org/apache/hadoop/hbase/client/ResultScanner.next:()Lorg/apache/hadoop/hbase/client/Result;
     100: astore        6
     102: aload         6
     104: ifnull        119
     107: aload         5
     109: invokeinterface #110,  1          // InterfaceMethod org/apache/hadoop/hbase/client/ResultScanner.next:()Lorg/apache/hadoop/hbase/client/Result;
     114: astore        6
     116: goto          102
     119: aload         5
     121: invokeinterface #111,  1          // InterfaceMethod org/apache/hadoop/hbase/client/ResultScanner.close:()V
     126: goto          141
     129: astore        7
     131: aload         5
     133: invokeinterface #111,  1          // InterfaceMethod org/apache/hadoop/hbase/client/ResultScanner.close:()V
     138: aload         7
     140: athrow
     141: aload_0
     142: ldc           #12                 // class org/apache/hadoop/hbase/coprocessor/SimpleRegionObserver
     144: iconst_1
     145: anewarray     #11                 // class java/lang/String
     148: dup
     149: iconst_0
     150: ldc           #115                // String wasScannerFilterRowCalled
     152: aastore
     153: aload_1
     154: iconst_1
     155: anewarray     #41                 // class java/lang/Boolean
     158: dup
     159: iconst_0
     160: iconst_1
     161: invokestatic  #42                 // Method java/lang/Boolean.valueOf:(Z)Ljava/lang/Boolean;
     164: aastore
     165: invokespecial #43                 // Method verifyMethodResult:(Ljava/lang/Class;[Ljava/lang/String;Lorg/apache/hadoop/hbase/TableName;[Ljava/lang/Object;)V
     168: getstatic     #5                  // Field util:Lorg/apache/hadoop/hbase/HBaseTestingUtility;
     171: aload_1
     172: invokevirtual #66                 // Method org/apache/hadoop/hbase/HBaseTestingUtility.deleteTable:(Lorg/apache/hadoop/hbase/TableName;)V
     175: aload_2
     176: invokeinterface #67,  1           // InterfaceMethod org/apache/hadoop/hbase/client/Table.close:()V
     181: return
    Exception table:
       from    to  target type
          93   119   129   any
         129   131   129   any

  public void testHBase3758() throws java.io.IOException;
    Code:
       0: aload_0
       1: getfield      #4                  // Field name:Lorg/junit/rules/TestName;
       4: invokevirtual #25                 // Method org/junit/rules/TestName.getMethodName:()Ljava/lang/String;
       7: invokestatic  #27                 // Method org/apache/hadoop/hbase/TableName.valueOf:(Ljava/lang/String;)Lorg/apache/hadoop/hbase/TableName;
      10: astore_1
      11: getstatic     #5                  // Field util:Lorg/apache/hadoop/hbase/HBaseTestingUtility;
      14: aload_1
      15: iconst_3
      16: anewarray     #28                 // class "[B"
      19: dup
      20: iconst_0
      21: getstatic     #29                 // Field A:[B
      24: aastore
      25: dup
      26: iconst_1
      27: getstatic     #30                 // Field B:[B
      30: aastore
      31: dup
      32: iconst_2
      33: getstatic     #31                 // Field C:[B
      36: aastore
      37: invokevirtual #32                 // Method org/apache/hadoop/hbase/HBaseTestingUtility.createTable:(Lorg/apache/hadoop/hbase/TableName;[[B)Lorg/apache/hadoop/hbase/client/Table;
      40: pop
      41: aload_0
      42: ldc           #12                 // class org/apache/hadoop/hbase/coprocessor/SimpleRegionObserver
      44: iconst_2
      45: anewarray     #11                 // class java/lang/String
      48: dup
      49: iconst_0
      50: ldc           #68                 // String hadDeleted
      52: aastore
      53: dup
      54: iconst_1
      55: ldc           #116                // String wasScannerOpenCalled
      57: aastore
      58: aload_1
      59: iconst_2
      60: anewarray     #41                 // class java/lang/Boolean
      63: dup
      64: iconst_0
      65: iconst_0
      66: invokestatic  #42                 // Method java/lang/Boolean.valueOf:(Z)Ljava/lang/Boolean;
      69: aastore
      70: dup
      71: iconst_1
      72: iconst_0
      73: invokestatic  #42                 // Method java/lang/Boolean.valueOf:(Z)Ljava/lang/Boolean;
      76: aastore
      77: invokespecial #43                 // Method verifyMethodResult:(Ljava/lang/Class;[Ljava/lang/String;Lorg/apache/hadoop/hbase/TableName;[Ljava/lang/Object;)V
      80: getstatic     #5                  // Field util:Lorg/apache/hadoop/hbase/HBaseTestingUtility;
      83: invokevirtual #105                // Method org/apache/hadoop/hbase/HBaseTestingUtility.getConnection:()Lorg/apache/hadoop/hbase/client/Connection;
      86: aload_1
      87: invokeinterface #106,  2          // InterfaceMethod org/apache/hadoop/hbase/client/Connection.getTable:(Lorg/apache/hadoop/hbase/TableName;)Lorg/apache/hadoop/hbase/client/Table;
      92: astore_2
      93: new           #44                 // class org/apache/hadoop/hbase/client/Put
      96: dup
      97: getstatic     #45                 // Field ROW:[B
     100: invokespecial #46                 // Method org/apache/hadoop/hbase/client/Put."<init>":([B)V
     103: astore_3
     104: aload_3
     105: getstatic     #29                 // Field A:[B
     108: getstatic     #29                 // Field A:[B
     111: getstatic     #29                 // Field A:[B
     114: invokevirtual #47                 // Method org/apache/hadoop/hbase/client/Put.addColumn:([B[B[B)Lorg/apache/hadoop/hbase/client/Put;
     117: pop
     118: aload_2
     119: aload_3
     120: invokeinterface #48,  2           // InterfaceMethod org/apache/hadoop/hbase/client/Table.put:(Lorg/apache/hadoop/hbase/client/Put;)V
     125: new           #62                 // class org/apache/hadoop/hbase/client/Delete
     128: dup
     129: getstatic     #45                 // Field ROW:[B
     132: invokespecial #63                 // Method org/apache/hadoop/hbase/client/Delete."<init>":([B)V
     135: astore        4
     137: aload_2
     138: aload         4
     140: invokeinterface #65,  2           // InterfaceMethod org/apache/hadoop/hbase/client/Table.delete:(Lorg/apache/hadoop/hbase/client/Delete;)V
     145: aload_0
     146: ldc           #12                 // class org/apache/hadoop/hbase/coprocessor/SimpleRegionObserver
     148: iconst_2
     149: anewarray     #11                 // class java/lang/String
     152: dup
     153: iconst_0
     154: ldc           #68                 // String hadDeleted
     156: aastore
     157: dup
     158: iconst_1
     159: ldc           #116                // String wasScannerOpenCalled
     161: aastore
     162: aload_1
     163: iconst_2
     164: anewarray     #41                 // class java/lang/Boolean
     167: dup
     168: iconst_0
     169: iconst_1
     170: invokestatic  #42                 // Method java/lang/Boolean.valueOf:(Z)Ljava/lang/Boolean;
     173: aastore
     174: dup
     175: iconst_1
     176: iconst_0
     177: invokestatic  #42                 // Method java/lang/Boolean.valueOf:(Z)Ljava/lang/Boolean;
     180: aastore
     181: invokespecial #43                 // Method verifyMethodResult:(Ljava/lang/Class;[Ljava/lang/String;Lorg/apache/hadoop/hbase/TableName;[Ljava/lang/Object;)V
     184: new           #107                // class org/apache/hadoop/hbase/client/Scan
     187: dup
     188: invokespecial #108                // Method org/apache/hadoop/hbase/client/Scan."<init>":()V
     191: astore        5
     193: aload_2
     194: aload         5
     196: invokeinterface #109,  2          // InterfaceMethod org/apache/hadoop/hbase/client/Table.getScanner:(Lorg/apache/hadoop/hbase/client/Scan;)Lorg/apache/hadoop/hbase/client/ResultScanner;
     201: astore        6
     203: aload         6
     205: invokeinterface #110,  1          // InterfaceMethod org/apache/hadoop/hbase/client/ResultScanner.next:()Lorg/apache/hadoop/hbase/client/Result;
     210: astore        7
     212: aload         7
     214: ifnull        229
     217: aload         6
     219: invokeinterface #110,  1          // InterfaceMethod org/apache/hadoop/hbase/client/ResultScanner.next:()Lorg/apache/hadoop/hbase/client/Result;
     224: astore        7
     226: goto          212
     229: aload         6
     231: invokeinterface #111,  1          // InterfaceMethod org/apache/hadoop/hbase/client/ResultScanner.close:()V
     236: goto          251
     239: astore        8
     241: aload         6
     243: invokeinterface #111,  1          // InterfaceMethod org/apache/hadoop/hbase/client/ResultScanner.close:()V
     248: aload         8
     250: athrow
     251: aload_0
     252: ldc           #12                 // class org/apache/hadoop/hbase/coprocessor/SimpleRegionObserver
     254: iconst_1
     255: anewarray     #11                 // class java/lang/String
     258: dup
     259: iconst_0
     260: ldc           #116                // String wasScannerOpenCalled
     262: aastore
     263: aload_1
     264: iconst_1
     265: anewarray     #41                 // class java/lang/Boolean
     268: dup
     269: iconst_0
     270: iconst_1
     271: invokestatic  #42                 // Method java/lang/Boolean.valueOf:(Z)Ljava/lang/Boolean;
     274: aastore
     275: invokespecial #43                 // Method verifyMethodResult:(Ljava/lang/Class;[Ljava/lang/String;Lorg/apache/hadoop/hbase/TableName;[Ljava/lang/Object;)V
     278: getstatic     #5                  // Field util:Lorg/apache/hadoop/hbase/HBaseTestingUtility;
     281: aload_1
     282: invokevirtual #66                 // Method org/apache/hadoop/hbase/HBaseTestingUtility.deleteTable:(Lorg/apache/hadoop/hbase/TableName;)V
     285: aload_2
     286: invokeinterface #67,  1           // InterfaceMethod org/apache/hadoop/hbase/client/Table.close:()V
     291: return
    Exception table:
       from    to  target type
         203   229   239   any
         239   241   239   any

  public void testCompactionOverride() throws java.lang.Exception;
    Code:
       0: aload_0
       1: getfield      #4                  // Field name:Lorg/junit/rules/TestName;
       4: invokevirtual #25                 // Method org/junit/rules/TestName.getMethodName:()Ljava/lang/String;
       7: invokestatic  #27                 // Method org/apache/hadoop/hbase/TableName.valueOf:(Ljava/lang/String;)Lorg/apache/hadoop/hbase/TableName;
      10: astore_1
      11: getstatic     #5                  // Field util:Lorg/apache/hadoop/hbase/HBaseTestingUtility;
      14: invokevirtual #117                // Method org/apache/hadoop/hbase/HBaseTestingUtility.getAdmin:()Lorg/apache/hadoop/hbase/client/Admin;
      17: astore_2
      18: aload_2
      19: aload_1
      20: invokeinterface #118,  2          // InterfaceMethod org/apache/hadoop/hbase/client/Admin.tableExists:(Lorg/apache/hadoop/hbase/TableName;)Z
      25: ifeq          42
      28: aload_2
      29: aload_1
      30: invokeinterface #119,  2          // InterfaceMethod org/apache/hadoop/hbase/client/Admin.disableTable:(Lorg/apache/hadoop/hbase/TableName;)V
      35: aload_2
      36: aload_1
      37: invokeinterface #120,  2          // InterfaceMethod org/apache/hadoop/hbase/client/Admin.deleteTable:(Lorg/apache/hadoop/hbase/TableName;)V
      42: new           #121                // class org/apache/hadoop/hbase/HTableDescriptor
      45: dup
      46: aload_1
      47: invokespecial #122                // Method org/apache/hadoop/hbase/HTableDescriptor."<init>":(Lorg/apache/hadoop/hbase/TableName;)V
      50: astore_3
      51: aload_3
      52: new           #123                // class org/apache/hadoop/hbase/HColumnDescriptor
      55: dup
      56: getstatic     #29                 // Field A:[B
      59: invokespecial #124                // Method org/apache/hadoop/hbase/HColumnDescriptor."<init>":([B)V
      62: invokevirtual #125                // Method org/apache/hadoop/hbase/HTableDescriptor.addFamily:(Lorg/apache/hadoop/hbase/HColumnDescriptor;)Lorg/apache/hadoop/hbase/HTableDescriptor;
      65: pop
      66: aload_3
      67: ldc           #126                // class org/apache/hadoop/hbase/coprocessor/TestRegionObserverInterface$EvenOnlyCompactor
      69: invokevirtual #13                 // Method java/lang/Class.getName:()Ljava/lang/String;
      72: invokevirtual #127                // Method org/apache/hadoop/hbase/HTableDescriptor.addCoprocessor:(Ljava/lang/String;)Lorg/apache/hadoop/hbase/HTableDescriptor;
      75: pop
      76: aload_2
      77: aload_3
      78: invokeinterface #128,  2          // InterfaceMethod org/apache/hadoop/hbase/client/Admin.createTable:(Lorg/apache/hadoop/hbase/client/TableDescriptor;)V
      83: getstatic     #5                  // Field util:Lorg/apache/hadoop/hbase/HBaseTestingUtility;
      86: invokevirtual #105                // Method org/apache/hadoop/hbase/HBaseTestingUtility.getConnection:()Lorg/apache/hadoop/hbase/client/Connection;
      89: aload_1
      90: invokeinterface #106,  2          // InterfaceMethod org/apache/hadoop/hbase/client/Connection.getTable:(Lorg/apache/hadoop/hbase/TableName;)Lorg/apache/hadoop/hbase/client/Table;
      95: astore        4
      97: lconst_1
      98: lstore        5
     100: lload         5
     102: ldc2_w        #129                // long 10l
     105: lcmp
     106: ifgt          168
     109: lload         5
     111: invokestatic  #131                // Method org/apache/hadoop/hbase/util/Bytes.toBytes:(J)[B
     114: astore        7
     116: new           #44                 // class org/apache/hadoop/hbase/client/Put
     119: dup
     120: aload         7
     122: invokespecial #46                 // Method org/apache/hadoop/hbase/client/Put."<init>":([B)V
     125: astore        8
     127: aload         8
     129: getstatic     #132                // Field org/apache/hadoop/hbase/client/Durability.SKIP_WAL:Lorg/apache/hadoop/hbase/client/Durability;
     132: invokevirtual #133                // Method org/apache/hadoop/hbase/client/Put.setDurability:(Lorg/apache/hadoop/hbase/client/Durability;)Lorg/apache/hadoop/hbase/client/Put;
     135: pop
     136: aload         8
     138: getstatic     #29                 // Field A:[B
     141: getstatic     #29                 // Field A:[B
     144: aload         7
     146: invokevirtual #47                 // Method org/apache/hadoop/hbase/client/Put.addColumn:([B[B[B)Lorg/apache/hadoop/hbase/client/Put;
     149: pop
     150: aload         4
     152: aload         8
     154: invokeinterface #48,  2           // InterfaceMethod org/apache/hadoop/hbase/client/Table.put:(Lorg/apache/hadoop/hbase/client/Put;)V
     159: lload         5
     161: lconst_1
     162: ladd
     163: lstore        5
     165: goto          100
     168: getstatic     #17                 // Field cluster:Lorg/apache/hadoop/hbase/MiniHBaseCluster;
     171: aload_1
     172: invokevirtual #134                // Method org/apache/hadoop/hbase/MiniHBaseCluster.getRegions:(Lorg/apache/hadoop/hbase/TableName;)Ljava/util/List;
     175: iconst_0
     176: invokeinterface #135,  2          // InterfaceMethod java/util/List.get:(I)Ljava/lang/Object;
     181: checkcast     #136                // class org/apache/hadoop/hbase/regionserver/HRegion
     184: astore        5
     186: aload         5
     188: invokevirtual #137                // Method org/apache/hadoop/hbase/regionserver/HRegion.getCoprocessorHost:()Lorg/apache/hadoop/hbase/regionserver/RegionCoprocessorHost;
     191: ldc           #126                // class org/apache/hadoop/hbase/coprocessor/TestRegionObserverInterface$EvenOnlyCompactor
     193: invokevirtual #138                // Method org/apache/hadoop/hbase/regionserver/RegionCoprocessorHost.findCoprocessor:(Ljava/lang/Class;)Lorg/apache/hadoop/hbase/Coprocessor;
     196: astore        6
     198: ldc           #139                // String EvenOnlyCompactor coprocessor should be loaded
     200: aload         6
     202: invokestatic  #140                // Method org/junit/Assert.assertNotNull:(Ljava/lang/String;Ljava/lang/Object;)V
     205: aload         6
     207: checkcast     #126                // class org/apache/hadoop/hbase/coprocessor/TestRegionObserverInterface$EvenOnlyCompactor
     210: astore        7
     212: invokestatic  #141                // Method java/lang/System.currentTimeMillis:()J
     215: lstore        8
     217: aload_2
     218: aload_1
     219: invokeinterface #142,  2          // InterfaceMethod org/apache/hadoop/hbase/client/Admin.flush:(Lorg/apache/hadoop/hbase/TableName;)V
     224: iconst_0
     225: istore        10
     227: iload         10
     229: bipush        10
     231: if_icmpge     260
     234: aload         7
     236: getfield      #143                // Field org/apache/hadoop/hbase/coprocessor/TestRegionObserverInterface$EvenOnlyCompactor.lastFlush:J
     239: lload         8
     241: lcmp
     242: iflt          248
     245: goto          260
     248: ldc2_w        #144                // long 1000l
     251: invokestatic  #146                // Method java/lang/Thread.sleep:(J)V
     254: iinc          10, 1
     257: goto          227
     260: ldc           #147                // String Flush didn't complete
     262: aload         7
     264: getfield      #143                // Field org/apache/hadoop/hbase/coprocessor/TestRegionObserverInterface$EvenOnlyCompactor.lastFlush:J
     267: lload         8
     269: lcmp
     270: iflt          277
     273: iconst_1
     274: goto          278
     277: iconst_0
     278: invokestatic  #148                // Method org/junit/Assert.assertTrue:(Ljava/lang/String;Z)V
     281: getstatic     #149                // Field LOG:Lorg/slf4j/Logger;
     284: ldc           #150                // String Flush complete
     286: invokeinterface #151,  2          // InterfaceMethod org/slf4j/Logger.debug:(Ljava/lang/String;)V
     291: aload         7
     293: getfield      #143                // Field org/apache/hadoop/hbase/coprocessor/TestRegionObserverInterface$EvenOnlyCompactor.lastFlush:J
     296: lstore        8
     298: aload_2
     299: aload_1
     300: invokeinterface #152,  2          // InterfaceMethod org/apache/hadoop/hbase/client/Admin.majorCompact:(Lorg/apache/hadoop/hbase/TableName;)V
     305: iconst_0
     306: istore        10
     308: iload         10
     310: bipush        30
     312: if_icmpge     341
     315: aload         7
     317: getfield      #153                // Field org/apache/hadoop/hbase/coprocessor/TestRegionObserverInterface$EvenOnlyCompactor.lastCompaction:J
     320: lload         8
     322: lcmp
     323: iflt          329
     326: goto          341
     329: ldc2_w        #144                // long 1000l
     332: invokestatic  #146                // Method java/lang/Thread.sleep:(J)V
     335: iinc          10, 1
     338: goto          308
     341: getstatic     #149                // Field LOG:Lorg/slf4j/Logger;
     344: new           #19                 // class java/lang/StringBuilder
     347: dup
     348: invokespecial #20                 // Method java/lang/StringBuilder."<init>":()V
     351: ldc           #154                // String Last compaction was at
     353: invokevirtual #23                 // Method java/lang/StringBuilder.append:(Ljava/lang/String;)Ljava/lang/StringBuilder;
     356: aload         7
     358: getfield      #153                // Field org/apache/hadoop/hbase/coprocessor/TestRegionObserverInterface$EvenOnlyCompactor.lastCompaction:J
     361: invokevirtual #155                // Method java/lang/StringBuilder.append:(J)Ljava/lang/StringBuilder;
     364: invokevirtual #26                 // Method java/lang/StringBuilder.toString:()Ljava/lang/String;
     367: invokeinterface #151,  2          // InterfaceMethod org/slf4j/Logger.debug:(Ljava/lang/String;)V
     372: ldc           #156                // String Compaction didn't complete
     374: aload         7
     376: getfield      #153                // Field org/apache/hadoop/hbase/coprocessor/TestRegionObserverInterface$EvenOnlyCompactor.lastCompaction:J
     379: lload         8
     381: lcmp
     382: iflt          389
     385: iconst_1
     386: goto          390
     389: iconst_0
     390: invokestatic  #148                // Method org/junit/Assert.assertTrue:(Ljava/lang/String;Z)V
     393: aload         4
     395: new           #107                // class org/apache/hadoop/hbase/client/Scan
     398: dup
     399: invokespecial #108                // Method org/apache/hadoop/hbase/client/Scan."<init>":()V
     402: invokeinterface #109,  2          // InterfaceMethod org/apache/hadoop/hbase/client/Table.getScanner:(Lorg/apache/hadoop/hbase/client/Scan;)Lorg/apache/hadoop/hbase/client/ResultScanner;
     407: astore        10
     409: ldc2_w        #157                // long 2l
     412: lstore        11
     414: lload         11
     416: ldc2_w        #129                // long 10l
     419: lcmp
     420: ifgt          529
     423: aload         10
     425: invokeinterface #110,  1          // InterfaceMethod org/apache/hadoop/hbase/client/ResultScanner.next:()Lorg/apache/hadoop/hbase/client/Result;
     430: astore        13
     432: aload         13
     434: invokestatic  #159                // Method org/junit/Assert.assertNotNull:(Ljava/lang/Object;)V
     437: aload         13
     439: invokevirtual #160                // Method org/apache/hadoop/hbase/client/Result.isEmpty:()Z
     442: invokestatic  #161                // Method org/junit/Assert.assertFalse:(Z)V
     445: lload         11
     447: invokestatic  #131                // Method org/apache/hadoop/hbase/util/Bytes.toBytes:(J)[B
     450: astore        14
     452: new           #19                 // class java/lang/StringBuilder
     455: dup
     456: invokespecial #20                 // Method java/lang/StringBuilder."<init>":()V
     459: ldc           #162                // String Row should be
     461: invokevirtual #23                 // Method java/lang/StringBuilder.append:(Ljava/lang/String;)Ljava/lang/StringBuilder;
     464: lload         11
     466: invokevirtual #155                // Method java/lang/StringBuilder.append:(J)Ljava/lang/StringBuilder;
     469: invokevirtual #26                 // Method java/lang/StringBuilder.toString:()Ljava/lang/String;
     472: aload         13
     474: invokevirtual #163                // Method org/apache/hadoop/hbase/client/Result.getRow:()[B
     477: aload         14
     479: invokestatic  #164                // Method org/junit/Assert.assertArrayEquals:(Ljava/lang/String;[B[B)V
     482: new           #19                 // class java/lang/StringBuilder
     485: dup
     486: invokespecial #20                 // Method java/lang/StringBuilder."<init>":()V
     489: ldc           #165                // String Value should be
     491: invokevirtual #23                 // Method java/lang/StringBuilder.append:(Ljava/lang/String;)Ljava/lang/StringBuilder;
     494: lload         11
     496: invokevirtual #155                // Method java/lang/StringBuilder.append:(J)Ljava/lang/StringBuilder;
     499: invokevirtual #26                 // Method java/lang/StringBuilder.toString:()Ljava/lang/String;
     502: aload         13
     504: getstatic     #29                 // Field A:[B
     507: getstatic     #29                 // Field A:[B
     510: invokevirtual #166                // Method org/apache/hadoop/hbase/client/Result.getValue:([B[B)[B
     513: aload         14
     515: invokestatic  #164                // Method org/junit/Assert.assertArrayEquals:(Ljava/lang/String;[B[B)V
     518: lload         11
     520: ldc2_w        #157                // long 2l
     523: ladd
     524: lstore        11
     526: goto          414
     529: aload         10
     531: invokeinterface #111,  1          // InterfaceMethod org/apache/hadoop/hbase/client/ResultScanner.close:()V
     536: goto          551
     539: astore        15
     541: aload         10
     543: invokeinterface #111,  1          // InterfaceMethod org/apache/hadoop/hbase/client/ResultScanner.close:()V
     548: aload         15
     550: athrow
     551: aload         4
     553: invokeinterface #67,  1           // InterfaceMethod org/apache/hadoop/hbase/client/Table.close:()V
     558: return
    Exception table:
       from    to  target type
         409   529   539   any
         539   541   539   any

  public void bulkLoadHFileTest() throws java.lang.Exception;
    Code:
       0: new           #19                 // class java/lang/StringBuilder
       3: dup
       4: invokespecial #20                 // Method java/lang/StringBuilder."<init>":()V
       7: ldc           #167                // class org/apache/hadoop/hbase/coprocessor/TestRegionObserverInterface
       9: invokevirtual #13                 // Method java/lang/Class.getName:()Ljava/lang/String;
      12: invokevirtual #23                 // Method java/lang/StringBuilder.append:(Ljava/lang/String;)Ljava/lang/StringBuilder;
      15: ldc           #24                 // String .
      17: invokevirtual #23                 // Method java/lang/StringBuilder.append:(Ljava/lang/String;)Ljava/lang/StringBuilder;
      20: aload_0
      21: getfield      #4                  // Field name:Lorg/junit/rules/TestName;
      24: invokevirtual #25                 // Method org/junit/rules/TestName.getMethodName:()Ljava/lang/String;
      27: invokevirtual #23                 // Method java/lang/StringBuilder.append:(Ljava/lang/String;)Ljava/lang/StringBuilder;
      30: invokevirtual #26                 // Method java/lang/StringBuilder.toString:()Ljava/lang/String;
      33: astore_1
      34: new           #19                 // class java/lang/StringBuilder
      37: dup
      38: invokespecial #20                 // Method java/lang/StringBuilder."<init>":()V
      41: getstatic     #21                 // Field TEST_TABLE:Lorg/apache/hadoop/hbase/TableName;
      44: invokevirtual #22                 // Method org/apache/hadoop/hbase/TableName.getNameAsString:()Ljava/lang/String;
      47: invokevirtual #23                 // Method java/lang/StringBuilder.append:(Ljava/lang/String;)Ljava/lang/StringBuilder;
      50: ldc           #24                 // String .
      52: invokevirtual #23                 // Method java/lang/StringBuilder.append:(Ljava/lang/String;)Ljava/lang/StringBuilder;
      55: aload_0
      56: getfield      #4                  // Field name:Lorg/junit/rules/TestName;
      59: invokevirtual #25                 // Method org/junit/rules/TestName.getMethodName:()Ljava/lang/String;
      62: invokevirtual #23                 // Method java/lang/StringBuilder.append:(Ljava/lang/String;)Ljava/lang/StringBuilder;
      65: invokevirtual #26                 // Method java/lang/StringBuilder.toString:()Ljava/lang/String;
      68: invokestatic  #27                 // Method org/apache/hadoop/hbase/TableName.valueOf:(Ljava/lang/String;)Lorg/apache/hadoop/hbase/TableName;
      71: astore_2
      72: getstatic     #5                  // Field util:Lorg/apache/hadoop/hbase/HBaseTestingUtility;
      75: invokevirtual #6                  // Method org/apache/hadoop/hbase/HBaseTestingUtility.getConfiguration:()Lorg/apache/hadoop/conf/Configuration;
      78: astore_3
      79: getstatic     #5                  // Field util:Lorg/apache/hadoop/hbase/HBaseTestingUtility;
      82: aload_2
      83: iconst_3
      84: anewarray     #28                 // class "[B"
      87: dup
      88: iconst_0
      89: getstatic     #29                 // Field A:[B
      92: aastore
      93: dup
      94: iconst_1
      95: getstatic     #30                 // Field B:[B
      98: aastore
      99: dup
     100: iconst_2
     101: getstatic     #31                 // Field C:[B
     104: aastore
     105: invokevirtual #32                 // Method org/apache/hadoop/hbase/HBaseTestingUtility.createTable:(Lorg/apache/hadoop/hbase/TableName;[[B)Lorg/apache/hadoop/hbase/client/Table;
     108: astore        4
     110: getstatic     #5                  // Field util:Lorg/apache/hadoop/hbase/HBaseTestingUtility;
     113: invokevirtual #105                // Method org/apache/hadoop/hbase/HBaseTestingUtility.getConnection:()Lorg/apache/hadoop/hbase/client/Connection;
     116: aload_2
     117: invokeinterface #168,  2          // InterfaceMethod org/apache/hadoop/hbase/client/Connection.getRegionLocator:(Lorg/apache/hadoop/hbase/TableName;)Lorg/apache/hadoop/hbase/client/RegionLocator;
     122: astore        5
     124: aconst_null
     125: astore        6
     127: aload_0
     128: ldc           #12                 // class org/apache/hadoop/hbase/coprocessor/SimpleRegionObserver
     130: iconst_2
     131: anewarray     #11                 // class java/lang/String
     134: dup
     135: iconst_0
     136: ldc           #169                // String hadPreBulkLoadHFile
     138: aastore
     139: dup
     140: iconst_1
     141: ldc           #170                // String hadPostBulkLoadHFile
     143: aastore
     144: aload_2
     145: iconst_2
     146: anewarray     #41                 // class java/lang/Boolean
     149: dup
     150: iconst_0
     151: iconst_0
     152: invokestatic  #42                 // Method java/lang/Boolean.valueOf:(Z)Ljava/lang/Boolean;
     155: aastore
     156: dup
     157: iconst_1
     158: iconst_0
     159: invokestatic  #42                 // Method java/lang/Boolean.valueOf:(Z)Ljava/lang/Boolean;
     162: aastore
     163: invokespecial #43                 // Method verifyMethodResult:(Ljava/lang/Class;[Ljava/lang/String;Lorg/apache/hadoop/hbase/TableName;[Ljava/lang/Object;)V
     166: getstatic     #5                  // Field util:Lorg/apache/hadoop/hbase/HBaseTestingUtility;
     169: invokevirtual #171                // Method org/apache/hadoop/hbase/HBaseTestingUtility.getTestFileSystem:()Lorg/apache/hadoop/fs/FileSystem;
     172: astore        7
     174: getstatic     #5                  // Field util:Lorg/apache/hadoop/hbase/HBaseTestingUtility;
     177: aload_1
     178: invokevirtual #172                // Method org/apache/hadoop/hbase/HBaseTestingUtility.getDataTestDirOnTestFS:(Ljava/lang/String;)Lorg/apache/hadoop/fs/Path;
     181: aload         7
     183: invokevirtual #173                // Method org/apache/hadoop/fs/Path.makeQualified:(Lorg/apache/hadoop/fs/FileSystem;)Lorg/apache/hadoop/fs/Path;
     186: astore        8
     188: new           #174                // class org/apache/hadoop/fs/Path
     191: dup
     192: aload         8
     194: getstatic     #29                 // Field A:[B
     197: invokestatic  #175                // Method org/apache/hadoop/hbase/util/Bytes.toString:([B)Ljava/lang/String;
     200: invokespecial #176                // Method org/apache/hadoop/fs/Path."<init>":(Lorg/apache/hadoop/fs/Path;Ljava/lang/String;)V
     203: astore        9
     205: getstatic     #5                  // Field util:Lorg/apache/hadoop/hbase/HBaseTestingUtility;
     208: invokevirtual #6                  // Method org/apache/hadoop/hbase/HBaseTestingUtility.getConfiguration:()Lorg/apache/hadoop/conf/Configuration;
     211: aload         7
     213: new           #174                // class org/apache/hadoop/fs/Path
     216: dup
     217: aload         9
     219: getstatic     #29                 // Field A:[B
     222: invokestatic  #175                // Method org/apache/hadoop/hbase/util/Bytes.toString:([B)Ljava/lang/String;
     225: invokespecial #176                // Method org/apache/hadoop/fs/Path."<init>":(Lorg/apache/hadoop/fs/Path;Ljava/lang/String;)V
     228: getstatic     #29                 // Field A:[B
     231: getstatic     #29                 // Field A:[B
     234: invokestatic  #177                // Method createHFile:(Lorg/apache/hadoop/conf/Configuration;Lorg/apache/hadoop/fs/FileSystem;Lorg/apache/hadoop/fs/Path;[B[B)V
     237: new           #178                // class org/apache/hadoop/hbase/tool/LoadIncrementalHFiles
     240: dup
     241: aload_3
     242: invokespecial #179                // Method org/apache/hadoop/hbase/tool/LoadIncrementalHFiles."<init>":(Lorg/apache/hadoop/conf/Configuration;)V
     245: aload         8
     247: getstatic     #5                  // Field util:Lorg/apache/hadoop/hbase/HBaseTestingUtility;
     250: invokevirtual #117                // Method org/apache/hadoop/hbase/HBaseTestingUtility.getAdmin:()Lorg/apache/hadoop/hbase/client/Admin;
     253: aload         4
     255: aload         5
     257: invokevirtual #180                // Method org/apache/hadoop/hbase/tool/LoadIncrementalHFiles.doBulkLoad:(Lorg/apache/hadoop/fs/Path;Lorg/apache/hadoop/hbase/client/Admin;Lorg/apache/hadoop/hbase/client/Table;Lorg/apache/hadoop/hbase/client/RegionLocator;)Ljava/util/Map;
     260: pop
     261: aload_0
     262: ldc           #12                 // class org/apache/hadoop/hbase/coprocessor/SimpleRegionObserver
     264: iconst_2
     265: anewarray     #11                 // class java/lang/String
     268: dup
     269: iconst_0
     270: ldc           #169                // String hadPreBulkLoadHFile
     272: aastore
     273: dup
     274: iconst_1
     275: ldc           #170                // String hadPostBulkLoadHFile
     277: aastore
     278: aload_2
     279: iconst_2
     280: anewarray     #41                 // class java/lang/Boolean
     283: dup
     284: iconst_0
     285: iconst_1
     286: invokestatic  #42                 // Method java/lang/Boolean.valueOf:(Z)Ljava/lang/Boolean;
     289: aastore
     290: dup
     291: iconst_1
     292: iconst_1
     293: invokestatic  #42                 // Method java/lang/Boolean.valueOf:(Z)Ljava/lang/Boolean;
     296: aastore
     297: invokespecial #43                 // Method verifyMethodResult:(Ljava/lang/Class;[Ljava/lang/String;Lorg/apache/hadoop/hbase/TableName;[Ljava/lang/Object;)V
     300: aload         5
     302: ifnull        395
     305: aload         6
     307: ifnull        332
     310: aload         5
     312: invokeinterface #181,  1          // InterfaceMethod org/apache/hadoop/hbase/client/RegionLocator.close:()V
     317: goto          395
     320: astore        7
     322: aload         6
     324: aload         7
     326: invokevirtual #90                 // Method java/lang/Throwable.addSuppressed:(Ljava/lang/Throwable;)V
     329: goto          395
     332: aload         5
     334: invokeinterface #181,  1          // InterfaceMethod org/apache/hadoop/hbase/client/RegionLocator.close:()V
     339: goto          395
     342: astore        7
     344: aload         7
     346: astore        6
     348: aload         7
     350: athrow
     351: astore        10
     353: aload         5
     355: ifnull        392
     358: aload         6
     360: ifnull        385
     363: aload         5
     365: invokeinterface #181,  1          // InterfaceMethod org/apache/hadoop/hbase/client/RegionLocator.close:()V
     370: goto          392
     373: astore        11
     375: aload         6
     377: aload         11
     379: invokevirtual #90                 // Method java/lang/Throwable.addSuppressed:(Ljava/lang/Throwable;)V
     382: goto          392
     385: aload         5
     387: invokeinterface #181,  1          // InterfaceMethod org/apache/hadoop/hbase/client/RegionLocator.close:()V
     392: aload         10
     394: athrow
     395: getstatic     #5                  // Field util:Lorg/apache/hadoop/hbase/HBaseTestingUtility;
     398: aload_2
     399: invokevirtual #66                 // Method org/apache/hadoop/hbase/HBaseTestingUtility.deleteTable:(Lorg/apache/hadoop/hbase/TableName;)V
     402: aload         4
     404: invokeinterface #67,  1           // InterfaceMethod org/apache/hadoop/hbase/client/Table.close:()V
     409: goto          431
     412: astore        12
     414: getstatic     #5                  // Field util:Lorg/apache/hadoop/hbase/HBaseTestingUtility;
     417: aload_2
     418: invokevirtual #66                 // Method org/apache/hadoop/hbase/HBaseTestingUtility.deleteTable:(Lorg/apache/hadoop/hbase/TableName;)V
     421: aload         4
     423: invokeinterface #67,  1           // InterfaceMethod org/apache/hadoop/hbase/client/Table.close:()V
     428: aload         12
     430: athrow
     431: return
    Exception table:
       from    to  target type
         310   317   320   Class java/lang/Throwable
         127   300   342   Class java/lang/Throwable
         127   300   351   any
         363   370   373   Class java/lang/Throwable
         342   353   351   any
         110   395   412   any
         412   414   412   any

  public void testRecovery() throws java.lang.Exception;
    Code:
       0: getstatic     #149                // Field LOG:Lorg/slf4j/Logger;
       3: new           #19                 // class java/lang/StringBuilder
       6: dup
       7: invokespecial #20                 // Method java/lang/StringBuilder."<init>":()V
      10: ldc           #167                // class org/apache/hadoop/hbase/coprocessor/TestRegionObserverInterface
      12: invokevirtual #13                 // Method java/lang/Class.getName:()Ljava/lang/String;
      15: invokevirtual #23                 // Method java/lang/StringBuilder.append:(Ljava/lang/String;)Ljava/lang/StringBuilder;
      18: ldc           #24                 // String .
      20: invokevirtual #23                 // Method java/lang/StringBuilder.append:(Ljava/lang/String;)Ljava/lang/StringBuilder;
      23: aload_0
      24: getfield      #4                  // Field name:Lorg/junit/rules/TestName;
      27: invokevirtual #25                 // Method org/junit/rules/TestName.getMethodName:()Ljava/lang/String;
      30: invokevirtual #23                 // Method java/lang/StringBuilder.append:(Ljava/lang/String;)Ljava/lang/StringBuilder;
      33: invokevirtual #26                 // Method java/lang/StringBuilder.toString:()Ljava/lang/String;
      36: invokeinterface #182,  2          // InterfaceMethod org/slf4j/Logger.info:(Ljava/lang/String;)V
      41: new           #19                 // class java/lang/StringBuilder
      44: dup
      45: invokespecial #20                 // Method java/lang/StringBuilder."<init>":()V
      48: getstatic     #21                 // Field TEST_TABLE:Lorg/apache/hadoop/hbase/TableName;
      51: invokevirtual #22                 // Method org/apache/hadoop/hbase/TableName.getNameAsString:()Ljava/lang/String;
      54: invokevirtual #23                 // Method java/lang/StringBuilder.append:(Ljava/lang/String;)Ljava/lang/StringBuilder;
      57: ldc           #24                 // String .
      59: invokevirtual #23                 // Method java/lang/StringBuilder.append:(Ljava/lang/String;)Ljava/lang/StringBuilder;
      62: aload_0
      63: getfield      #4                  // Field name:Lorg/junit/rules/TestName;
      66: invokevirtual #25                 // Method org/junit/rules/TestName.getMethodName:()Ljava/lang/String;
      69: invokevirtual #23                 // Method java/lang/StringBuilder.append:(Ljava/lang/String;)Ljava/lang/StringBuilder;
      72: invokevirtual #26                 // Method java/lang/StringBuilder.toString:()Ljava/lang/String;
      75: invokestatic  #27                 // Method org/apache/hadoop/hbase/TableName.valueOf:(Ljava/lang/String;)Lorg/apache/hadoop/hbase/TableName;
      78: astore_1
      79: getstatic     #5                  // Field util:Lorg/apache/hadoop/hbase/HBaseTestingUtility;
      82: aload_1
      83: iconst_3
      84: anewarray     #28                 // class "[B"
      87: dup
      88: iconst_0
      89: getstatic     #29                 // Field A:[B
      92: aastore
      93: dup
      94: iconst_1
      95: getstatic     #30                 // Field B:[B
      98: aastore
      99: dup
     100: iconst_2
     101: getstatic     #31                 // Field C:[B
     104: aastore
     105: invokevirtual #32                 // Method org/apache/hadoop/hbase/HBaseTestingUtility.createTable:(Lorg/apache/hadoop/hbase/TableName;[[B)Lorg/apache/hadoop/hbase/client/Table;
     108: astore_2
     109: getstatic     #5                  // Field util:Lorg/apache/hadoop/hbase/HBaseTestingUtility;
     112: invokevirtual #105                // Method org/apache/hadoop/hbase/HBaseTestingUtility.getConnection:()Lorg/apache/hadoop/hbase/client/Connection;
     115: aload_1
     116: invokeinterface #168,  2          // InterfaceMethod org/apache/hadoop/hbase/client/Connection.getRegionLocator:(Lorg/apache/hadoop/hbase/TableName;)Lorg/apache/hadoop/hbase/client/RegionLocator;
     121: astore_3
     122: aconst_null
     123: astore        4
     125: getstatic     #17                 // Field cluster:Lorg/apache/hadoop/hbase/MiniHBaseCluster;
     128: invokevirtual #183                // Method org/apache/hadoop/hbase/MiniHBaseCluster.startRegionServer:()Lorg/apache/hadoop/hbase/util/JVMClusterUtil$RegionServerThread;
     131: astore        5
     133: aload         5
     135: invokevirtual #184                // Method org/apache/hadoop/hbase/util/JVMClusterUtil$RegionServerThread.getRegionServer:()Lorg/apache/hadoop/hbase/regionserver/HRegionServer;
     138: invokevirtual #185                // Method org/apache/hadoop/hbase/regionserver/HRegionServer.getServerName:()Lorg/apache/hadoop/hbase/ServerName;
     141: astore        6
     143: aload_3
     144: invokeinterface #186,  1          // InterfaceMethod org/apache/hadoop/hbase/client/RegionLocator.getAllRegionLocations:()Ljava/util/List;
     149: iconst_0
     150: invokeinterface #135,  2          // InterfaceMethod java/util/List.get:(I)Ljava/lang/Object;
     155: checkcast     #187                // class org/apache/hadoop/hbase/HRegionLocation
     158: invokevirtual #188                // Method org/apache/hadoop/hbase/HRegionLocation.getRegionInfo:()Lorg/apache/hadoop/hbase/HRegionInfo;
     161: invokevirtual #189                // Method org/apache/hadoop/hbase/HRegionInfo.getEncodedName:()Ljava/lang/String;
     164: astore        7
     166: getstatic     #5                  // Field util:Lorg/apache/hadoop/hbase/HBaseTestingUtility;
     169: invokevirtual #117                // Method org/apache/hadoop/hbase/HBaseTestingUtility.getAdmin:()Lorg/apache/hadoop/hbase/client/Admin;
     172: aload         7
     174: invokestatic  #190                // Method org/apache/hadoop/hbase/util/Bytes.toBytes:(Ljava/lang/String;)[B
     177: aload         6
     179: invokeinterface #191,  3          // InterfaceMethod org/apache/hadoop/hbase/client/Admin.move:([BLorg/apache/hadoop/hbase/ServerName;)V
     184: aload         6
     186: aload_3
     187: invokeinterface #186,  1          // InterfaceMethod org/apache/hadoop/hbase/client/RegionLocator.getAllRegionLocations:()Ljava/util/List;
     192: iconst_0
     193: invokeinterface #135,  2          // InterfaceMethod java/util/List.get:(I)Ljava/lang/Object;
     198: checkcast     #187                // class org/apache/hadoop/hbase/HRegionLocation
     201: invokevirtual #192                // Method org/apache/hadoop/hbase/HRegionLocation.getServerName:()Lorg/apache/hadoop/hbase/ServerName;
     204: invokevirtual #193                // Method org/apache/hadoop/hbase/ServerName.equals:(Ljava/lang/Object;)Z
     207: ifne          219
     210: ldc2_w        #194                // long 100l
     213: invokestatic  #146                // Method java/lang/Thread.sleep:(J)V
     216: goto          184
     219: new           #44                 // class org/apache/hadoop/hbase/client/Put
     222: dup
     223: getstatic     #45                 // Field ROW:[B
     226: invokespecial #46                 // Method org/apache/hadoop/hbase/client/Put."<init>":([B)V
     229: astore        8
     231: aload         8
     233: getstatic     #29                 // Field A:[B
     236: getstatic     #29                 // Field A:[B
     239: getstatic     #29                 // Field A:[B
     242: invokevirtual #47                 // Method org/apache/hadoop/hbase/client/Put.addColumn:([B[B[B)Lorg/apache/hadoop/hbase/client/Put;
     245: pop
     246: aload         8
     248: getstatic     #30                 // Field B:[B
     251: getstatic     #30                 // Field B:[B
     254: getstatic     #30                 // Field B:[B
     257: invokevirtual #47                 // Method org/apache/hadoop/hbase/client/Put.addColumn:([B[B[B)Lorg/apache/hadoop/hbase/client/Put;
     260: pop
     261: aload         8
     263: getstatic     #31                 // Field C:[B
     266: getstatic     #31                 // Field C:[B
     269: getstatic     #31                 // Field C:[B
     272: invokevirtual #47                 // Method org/apache/hadoop/hbase/client/Put.addColumn:([B[B[B)Lorg/apache/hadoop/hbase/client/Put;
     275: pop
     276: aload_2
     277: aload         8
     279: invokeinterface #48,  2           // InterfaceMethod org/apache/hadoop/hbase/client/Table.put:(Lorg/apache/hadoop/hbase/client/Put;)V
     284: aload_2
     285: aload         8
     287: invokeinterface #48,  2           // InterfaceMethod org/apache/hadoop/hbase/client/Table.put:(Lorg/apache/hadoop/hbase/client/Put;)V
     292: aload_0
     293: ldc           #12                 // class org/apache/hadoop/hbase/coprocessor/SimpleRegionObserver
     295: bipush        7
     297: anewarray     #11                 // class java/lang/String
     300: dup
     301: iconst_0
     302: ldc           #33                 // String hadPreGet
     304: aastore
     305: dup
     306: iconst_1
     307: ldc           #34                 // String hadPostGet
     309: aastore
     310: dup
     311: iconst_2
     312: ldc           #35                 // String hadPrePut
     314: aastore
     315: dup
     316: iconst_3
     317: ldc           #36                 // String hadPostPut
     319: aastore
     320: dup
     321: iconst_4
     322: ldc           #49                 // String hadPreBatchMutate
     324: aastore
     325: dup
     326: iconst_5
     327: ldc           #50                 // String hadPostBatchMutate
     329: aastore
     330: dup
     331: bipush        6
     333: ldc           #37                 // String hadDelete
     335: aastore
     336: aload_1
     337: bipush        7
     339: anewarray     #41                 // class java/lang/Boolean
     342: dup
     343: iconst_0
     344: iconst_0
     345: invokestatic  #42                 // Method java/lang/Boolean.valueOf:(Z)Ljava/lang/Boolean;
     348: aastore
     349: dup
     350: iconst_1
     351: iconst_0
     352: invokestatic  #42                 // Method java/lang/Boolean.valueOf:(Z)Ljava/lang/Boolean;
     355: aastore
     356: dup
     357: iconst_2
     358: iconst_1
     359: invokestatic  #42                 // Method java/lang/Boolean.valueOf:(Z)Ljava/lang/Boolean;
     362: aastore
     363: dup
     364: iconst_3
     365: iconst_1
     366: invokestatic  #42                 // Method java/lang/Boolean.valueOf:(Z)Ljava/lang/Boolean;
     369: aastore
     370: dup
     371: iconst_4
     372: iconst_1
     373: invokestatic  #42                 // Method java/lang/Boolean.valueOf:(Z)Ljava/lang/Boolean;
     376: aastore
     377: dup
     378: iconst_5
     379: iconst_1
     380: invokestatic  #42                 // Method java/lang/Boolean.valueOf:(Z)Ljava/lang/Boolean;
     383: aastore
     384: dup
     385: bipush        6
     387: iconst_0
     388: invokestatic  #42                 // Method java/lang/Boolean.valueOf:(Z)Ljava/lang/Boolean;
     391: aastore
     392: invokespecial #43                 // Method verifyMethodResult:(Ljava/lang/Class;[Ljava/lang/String;Lorg/apache/hadoop/hbase/TableName;[Ljava/lang/Object;)V
     395: aload_0
     396: ldc           #12                 // class org/apache/hadoop/hbase/coprocessor/SimpleRegionObserver
     398: bipush        6
     400: anewarray     #11                 // class java/lang/String
     403: dup
     404: iconst_0
     405: ldc           #196                // String getCtPreReplayWALs
     407: aastore
     408: dup
     409: iconst_1
     410: ldc           #197                // String getCtPostReplayWALs
     412: aastore
     413: dup
     414: iconst_2
     415: ldc           #198                // String getCtPreWALRestore
     417: aastore
     418: dup
     419: iconst_3
     420: ldc           #199                // String getCtPostWALRestore
     422: aastore
     423: dup
     424: iconst_4
     425: ldc           #200                // String getCtPrePut
     427: aastore
     428: dup
     429: iconst_5
     430: ldc           #201                // String getCtPostPut
     432: aastore
     433: aload_1
     434: bipush        6
     436: anewarray     #55                 // class java/lang/Integer
     439: dup
     440: iconst_0
     441: iconst_0
     442: invokestatic  #56                 // Method java/lang/Integer.valueOf:(I)Ljava/lang/Integer;
     445: aastore
     446: dup
     447: iconst_1
     448: iconst_0
     449: invokestatic  #56                 // Method java/lang/Integer.valueOf:(I)Ljava/lang/Integer;
     452: aastore
     453: dup
     454: iconst_2
     455: iconst_0
     456: invokestatic  #56                 // Method java/lang/Integer.valueOf:(I)Ljava/lang/Integer;
     459: aastore
     460: dup
     461: iconst_3
     462: iconst_0
     463: invokestatic  #56                 // Method java/lang/Integer.valueOf:(I)Ljava/lang/Integer;
     466: aastore
     467: dup
     468: iconst_4
     469: iconst_2
     470: invokestatic  #56                 // Method java/lang/Integer.valueOf:(I)Ljava/lang/Integer;
     473: aastore
     474: dup
     475: iconst_5
     476: iconst_2
     477: invokestatic  #56                 // Method java/lang/Integer.valueOf:(I)Ljava/lang/Integer;
     480: aastore
     481: invokespecial #43                 // Method verifyMethodResult:(Ljava/lang/Class;[Ljava/lang/String;Lorg/apache/hadoop/hbase/TableName;[Ljava/lang/Object;)V
     484: getstatic     #17                 // Field cluster:Lorg/apache/hadoop/hbase/MiniHBaseCluster;
     487: aload         5
     489: invokevirtual #184                // Method org/apache/hadoop/hbase/util/JVMClusterUtil$RegionServerThread.getRegionServer:()Lorg/apache/hadoop/hbase/regionserver/HRegionServer;
     492: invokevirtual #185                // Method org/apache/hadoop/hbase/regionserver/HRegionServer.getServerName:()Lorg/apache/hadoop/hbase/ServerName;
     495: invokevirtual #202                // Method org/apache/hadoop/hbase/MiniHBaseCluster.killRegionServer:(Lorg/apache/hadoop/hbase/ServerName;)V
     498: ldc2_w        #144                // long 1000l
     501: invokestatic  #203                // Method org/apache/hadoop/hbase/util/Threads.sleep:(J)V
     504: getstatic     #5                  // Field util:Lorg/apache/hadoop/hbase/HBaseTestingUtility;
     507: aload_1
     508: invokevirtual #102                // Method org/apache/hadoop/hbase/HBaseTestingUtility.waitUntilAllRegionsAssigned:(Lorg/apache/hadoop/hbase/TableName;)V
     511: getstatic     #149                // Field LOG:Lorg/slf4j/Logger;
     514: ldc           #204                // String All regions assigned
     516: invokeinterface #182,  2          // InterfaceMethod org/slf4j/Logger.info:(Ljava/lang/String;)V
     521: aload_0
     522: ldc           #12                 // class org/apache/hadoop/hbase/coprocessor/SimpleRegionObserver
     524: bipush        6
     526: anewarray     #11                 // class java/lang/String
     529: dup
     530: iconst_0
     531: ldc           #196                // String getCtPreReplayWALs
     533: aastore
     534: dup
     535: iconst_1
     536: ldc           #197                // String getCtPostReplayWALs
     538: aastore
     539: dup
     540: iconst_2
     541: ldc           #198                // String getCtPreWALRestore
     543: aastore
     544: dup
     545: iconst_3
     546: ldc           #199                // String getCtPostWALRestore
     548: aastore
     549: dup
     550: iconst_4
     551: ldc           #200                // String getCtPrePut
     553: aastore
     554: dup
     555: iconst_5
     556: ldc           #201                // String getCtPostPut
     558: aastore
     559: aload_1
     560: bipush        6
     562: anewarray     #55                 // class java/lang/Integer
     565: dup
     566: iconst_0
     567: iconst_1
     568: invokestatic  #56                 // Method java/lang/Integer.valueOf:(I)Ljava/lang/Integer;
     571: aastore
     572: dup
     573: iconst_1
     574: iconst_1
     575: invokestatic  #56                 // Method java/lang/Integer.valueOf:(I)Ljava/lang/Integer;
     578: aastore
     579: dup
     580: iconst_2
     581: iconst_2
     582: invokestatic  #56                 // Method java/lang/Integer.valueOf:(I)Ljava/lang/Integer;
     585: aastore
     586: dup
     587: iconst_3
     588: iconst_2
     589: invokestatic  #56                 // Method java/lang/Integer.valueOf:(I)Ljava/lang/Integer;
     592: aastore
     593: dup
     594: iconst_4
     595: iconst_0
     596: invokestatic  #56                 // Method java/lang/Integer.valueOf:(I)Ljava/lang/Integer;
     599: aastore
     600: dup
     601: iconst_5
     602: iconst_0
     603: invokestatic  #56                 // Method java/lang/Integer.valueOf:(I)Ljava/lang/Integer;
     606: aastore
     607: invokespecial #43                 // Method verifyMethodResult:(Ljava/lang/Class;[Ljava/lang/String;Lorg/apache/hadoop/hbase/TableName;[Ljava/lang/Object;)V
     610: aload_3
     611: ifnull        699
     614: aload         4
     616: ifnull        640
     619: aload_3
     620: invokeinterface #181,  1          // InterfaceMethod org/apache/hadoop/hbase/client/RegionLocator.close:()V
     625: goto          699
     628: astore        5
     630: aload         4
     632: aload         5
     634: invokevirtual #90                 // Method java/lang/Throwable.addSuppressed:(Ljava/lang/Throwable;)V
     637: goto          699
     640: aload_3
     641: invokeinterface #181,  1          // InterfaceMethod org/apache/hadoop/hbase/client/RegionLocator.close:()V
     646: goto          699
     649: astore        5
     651: aload         5
     653: astore        4
     655: aload         5
     657: athrow
     658: astore        9
     660: aload_3
     661: ifnull        696
     664: aload         4
     666: ifnull        690
     669: aload_3
     670: invokeinterface #181,  1          // InterfaceMethod org/apache/hadoop/hbase/client/RegionLocator.close:()V
     675: goto          696
     678: astore        10
     680: aload         4
     682: aload         10
     684: invokevirtual #90                 // Method java/lang/Throwable.addSuppressed:(Ljava/lang/Throwable;)V
     687: goto          696
     690: aload_3
     691: invokeinterface #181,  1          // InterfaceMethod org/apache/hadoop/hbase/client/RegionLocator.close:()V
     696: aload         9
     698: athrow
     699: getstatic     #5                  // Field util:Lorg/apache/hadoop/hbase/HBaseTestingUtility;
     702: aload_1
     703: invokevirtual #66                 // Method org/apache/hadoop/hbase/HBaseTestingUtility.deleteTable:(Lorg/apache/hadoop/hbase/TableName;)V
     706: aload_2
     707: invokeinterface #67,  1           // InterfaceMethod org/apache/hadoop/hbase/client/Table.close:()V
     712: goto          733
     715: astore        11
     717: getstatic     #5                  // Field util:Lorg/apache/hadoop/hbase/HBaseTestingUtility;
     720: aload_1
     721: invokevirtual #66                 // Method org/apache/hadoop/hbase/HBaseTestingUtility.deleteTable:(Lorg/apache/hadoop/hbase/TableName;)V
     724: aload_2
     725: invokeinterface #67,  1           // InterfaceMethod org/apache/hadoop/hbase/client/Table.close:()V
     730: aload         11
     732: athrow
     733: return
    Exception table:
       from    to  target type
         619   625   628   Class java/lang/Throwable
         125   610   649   Class java/lang/Throwable
         125   610   658   any
         669   675   678   Class java/lang/Throwable
         649   660   658   any
         109   699   715   any
         715   717   715   any

  public void testPreWALRestoreSkip() throws java.lang.Exception;
    Code:
       0: getstatic     #149                // Field LOG:Lorg/slf4j/Logger;
       3: new           #19                 // class java/lang/StringBuilder
       6: dup
       7: invokespecial #20                 // Method java/lang/StringBuilder."<init>":()V
      10: ldc           #167                // class org/apache/hadoop/hbase/coprocessor/TestRegionObserverInterface
      12: invokevirtual #13                 // Method java/lang/Class.getName:()Ljava/lang/String;
      15: invokevirtual #23                 // Method java/lang/StringBuilder.append:(Ljava/lang/String;)Ljava/lang/StringBuilder;
      18: ldc           #24                 // String .
      20: invokevirtual #23                 // Method java/lang/StringBuilder.append:(Ljava/lang/String;)Ljava/lang/StringBuilder;
      23: aload_0
      24: getfield      #4                  // Field name:Lorg/junit/rules/TestName;
      27: invokevirtual #25                 // Method org/junit/rules/TestName.getMethodName:()Ljava/lang/String;
      30: invokevirtual #23                 // Method java/lang/StringBuilder.append:(Ljava/lang/String;)Ljava/lang/StringBuilder;
      33: invokevirtual #26                 // Method java/lang/StringBuilder.toString:()Ljava/lang/String;
      36: invokeinterface #182,  2          // InterfaceMethod org/slf4j/Logger.info:(Ljava/lang/String;)V
      41: ldc           #205                // String SKIPPED_BY_PREWALRESTORE
      43: invokestatic  #27                 // Method org/apache/hadoop/hbase/TableName.valueOf:(Ljava/lang/String;)Lorg/apache/hadoop/hbase/TableName;
      46: astore_1
      47: getstatic     #5                  // Field util:Lorg/apache/hadoop/hbase/HBaseTestingUtility;
      50: aload_1
      51: iconst_3
      52: anewarray     #28                 // class "[B"
      55: dup
      56: iconst_0
      57: getstatic     #29                 // Field A:[B
      60: aastore
      61: dup
      62: iconst_1
      63: getstatic     #30                 // Field B:[B
      66: aastore
      67: dup
      68: iconst_2
      69: getstatic     #31                 // Field C:[B
      72: aastore
      73: invokevirtual #32                 // Method org/apache/hadoop/hbase/HBaseTestingUtility.createTable:(Lorg/apache/hadoop/hbase/TableName;[[B)Lorg/apache/hadoop/hbase/client/Table;
      76: astore_2
      77: getstatic     #5                  // Field util:Lorg/apache/hadoop/hbase/HBaseTestingUtility;
      80: invokevirtual #105                // Method org/apache/hadoop/hbase/HBaseTestingUtility.getConnection:()Lorg/apache/hadoop/hbase/client/Connection;
      83: aload_1
      84: invokeinterface #168,  2          // InterfaceMethod org/apache/hadoop/hbase/client/Connection.getRegionLocator:(Lorg/apache/hadoop/hbase/TableName;)Lorg/apache/hadoop/hbase/client/RegionLocator;
      89: astore_3
      90: aconst_null
      91: astore        4
      93: getstatic     #17                 // Field cluster:Lorg/apache/hadoop/hbase/MiniHBaseCluster;
      96: invokevirtual #183                // Method org/apache/hadoop/hbase/MiniHBaseCluster.startRegionServer:()Lorg/apache/hadoop/hbase/util/JVMClusterUtil$RegionServerThread;
      99: astore        5
     101: aload         5
     103: invokevirtual #184                // Method org/apache/hadoop/hbase/util/JVMClusterUtil$RegionServerThread.getRegionServer:()Lorg/apache/hadoop/hbase/regionserver/HRegionServer;
     106: invokevirtual #185                // Method org/apache/hadoop/hbase/regionserver/HRegionServer.getServerName:()Lorg/apache/hadoop/hbase/ServerName;
     109: astore        6
     111: aload_3
     112: invokeinterface #186,  1          // InterfaceMethod org/apache/hadoop/hbase/client/RegionLocator.getAllRegionLocations:()Ljava/util/List;
     117: iconst_0
     118: invokeinterface #135,  2          // InterfaceMethod java/util/List.get:(I)Ljava/lang/Object;
     123: checkcast     #187                // class org/apache/hadoop/hbase/HRegionLocation
     126: invokevirtual #188                // Method org/apache/hadoop/hbase/HRegionLocation.getRegionInfo:()Lorg/apache/hadoop/hbase/HRegionInfo;
     129: invokevirtual #189                // Method org/apache/hadoop/hbase/HRegionInfo.getEncodedName:()Ljava/lang/String;
     132: astore        7
     134: getstatic     #5                  // Field util:Lorg/apache/hadoop/hbase/HBaseTestingUtility;
     137: invokevirtual #117                // Method org/apache/hadoop/hbase/HBaseTestingUtility.getAdmin:()Lorg/apache/hadoop/hbase/client/Admin;
     140: aload         7
     142: invokestatic  #190                // Method org/apache/hadoop/hbase/util/Bytes.toBytes:(Ljava/lang/String;)[B
     145: aload         6
     147: invokeinterface #191,  3          // InterfaceMethod org/apache/hadoop/hbase/client/Admin.move:([BLorg/apache/hadoop/hbase/ServerName;)V
     152: aload         6
     154: aload_3
     155: invokeinterface #186,  1          // InterfaceMethod org/apache/hadoop/hbase/client/RegionLocator.getAllRegionLocations:()Ljava/util/List;
     160: iconst_0
     161: invokeinterface #135,  2          // InterfaceMethod java/util/List.get:(I)Ljava/lang/Object;
     166: checkcast     #187                // class org/apache/hadoop/hbase/HRegionLocation
     169: invokevirtual #192                // Method org/apache/hadoop/hbase/HRegionLocation.getServerName:()Lorg/apache/hadoop/hbase/ServerName;
     172: invokevirtual #193                // Method org/apache/hadoop/hbase/ServerName.equals:(Ljava/lang/Object;)Z
     175: ifne          187
     178: ldc2_w        #194                // long 100l
     181: invokestatic  #146                // Method java/lang/Thread.sleep:(J)V
     184: goto          152
     187: new           #44                 // class org/apache/hadoop/hbase/client/Put
     190: dup
     191: getstatic     #45                 // Field ROW:[B
     194: invokespecial #46                 // Method org/apache/hadoop/hbase/client/Put."<init>":([B)V
     197: astore        8
     199: aload         8
     201: getstatic     #29                 // Field A:[B
     204: getstatic     #29                 // Field A:[B
     207: getstatic     #29                 // Field A:[B
     210: invokevirtual #47                 // Method org/apache/hadoop/hbase/client/Put.addColumn:([B[B[B)Lorg/apache/hadoop/hbase/client/Put;
     213: pop
     214: aload         8
     216: getstatic     #30                 // Field B:[B
     219: getstatic     #30                 // Field B:[B
     222: getstatic     #30                 // Field B:[B
     225: invokevirtual #47                 // Method org/apache/hadoop/hbase/client/Put.addColumn:([B[B[B)Lorg/apache/hadoop/hbase/client/Put;
     228: pop
     229: aload         8
     231: getstatic     #31                 // Field C:[B
     234: getstatic     #31                 // Field C:[B
     237: getstatic     #31                 // Field C:[B
     240: invokevirtual #47                 // Method org/apache/hadoop/hbase/client/Put.addColumn:([B[B[B)Lorg/apache/hadoop/hbase/client/Put;
     243: pop
     244: aload_2
     245: aload         8
     247: invokeinterface #48,  2           // InterfaceMethod org/apache/hadoop/hbase/client/Table.put:(Lorg/apache/hadoop/hbase/client/Put;)V
     252: getstatic     #17                 // Field cluster:Lorg/apache/hadoop/hbase/MiniHBaseCluster;
     255: aload         5
     257: invokevirtual #184                // Method org/apache/hadoop/hbase/util/JVMClusterUtil$RegionServerThread.getRegionServer:()Lorg/apache/hadoop/hbase/regionserver/HRegionServer;
     260: invokevirtual #185                // Method org/apache/hadoop/hbase/regionserver/HRegionServer.getServerName:()Lorg/apache/hadoop/hbase/ServerName;
     263: invokevirtual #202                // Method org/apache/hadoop/hbase/MiniHBaseCluster.killRegionServer:(Lorg/apache/hadoop/hbase/ServerName;)V
     266: ldc2_w        #206                // long 20000l
     269: invokestatic  #203                // Method org/apache/hadoop/hbase/util/Threads.sleep:(J)V
     272: getstatic     #5                  // Field util:Lorg/apache/hadoop/hbase/HBaseTestingUtility;
     275: aload_1
     276: invokevirtual #102                // Method org/apache/hadoop/hbase/HBaseTestingUtility.waitUntilAllRegionsAssigned:(Lorg/apache/hadoop/hbase/TableName;)V
     279: aload_3
     280: ifnull        368
     283: aload         4
     285: ifnull        309
     288: aload_3
     289: invokeinterface #181,  1          // InterfaceMethod org/apache/hadoop/hbase/client/RegionLocator.close:()V
     294: goto          368
     297: astore        5
     299: aload         4
     301: aload         5
     303: invokevirtual #90                 // Method java/lang/Throwable.addSuppressed:(Ljava/lang/Throwable;)V
     306: goto          368
     309: aload_3
     310: invokeinterface #181,  1          // InterfaceMethod org/apache/hadoop/hbase/client/RegionLocator.close:()V
     315: goto          368
     318: astore        5
     320: aload         5
     322: astore        4
     324: aload         5
     326: athrow
     327: astore        9
     329: aload_3
     330: ifnull        365
     333: aload         4
     335: ifnull        359
     338: aload_3
     339: invokeinterface #181,  1          // InterfaceMethod org/apache/hadoop/hbase/client/RegionLocator.close:()V
     344: goto          365
     347: astore        10
     349: aload         4
     351: aload         10
     353: invokevirtual #90                 // Method java/lang/Throwable.addSuppressed:(Ljava/lang/Throwable;)V
     356: goto          365
     359: aload_3
     360: invokeinterface #181,  1          // InterfaceMethod org/apache/hadoop/hbase/client/RegionLocator.close:()V
     365: aload         9
     367: athrow
     368: aload_0
     369: ldc           #12                 // class org/apache/hadoop/hbase/coprocessor/SimpleRegionObserver
     371: iconst_2
     372: anewarray     #11                 // class java/lang/String
     375: dup
     376: iconst_0
     377: ldc           #198                // String getCtPreWALRestore
     379: aastore
     380: dup
     381: iconst_1
     382: ldc           #199                // String getCtPostWALRestore
     384: aastore
     385: aload_1
     386: iconst_2
     387: anewarray     #55                 // class java/lang/Integer
     390: dup
     391: iconst_0
     392: iconst_0
     393: invokestatic  #56                 // Method java/lang/Integer.valueOf:(I)Ljava/lang/Integer;
     396: aastore
     397: dup
     398: iconst_1
     399: iconst_0
     400: invokestatic  #56                 // Method java/lang/Integer.valueOf:(I)Ljava/lang/Integer;
     403: aastore
     404: invokespecial #43                 // Method verifyMethodResult:(Ljava/lang/Class;[Ljava/lang/String;Lorg/apache/hadoop/hbase/TableName;[Ljava/lang/Object;)V
     407: getstatic     #5                  // Field util:Lorg/apache/hadoop/hbase/HBaseTestingUtility;
     410: aload_1
     411: invokevirtual #66                 // Method org/apache/hadoop/hbase/HBaseTestingUtility.deleteTable:(Lorg/apache/hadoop/hbase/TableName;)V
     414: aload_2
     415: invokeinterface #67,  1           // InterfaceMethod org/apache/hadoop/hbase/client/Table.close:()V
     420: return
    Exception table:
       from    to  target type
         288   294   297   Class java/lang/Throwable
          93   279   318   Class java/lang/Throwable
          93   279   327   any
         338   344   347   Class java/lang/Throwable
         318   329   327   any

  static {};
    Code:
       0: ldc           #167                // class org/apache/hadoop/hbase/coprocessor/TestRegionObserverInterface
       2: invokestatic  #252                // Method org/apache/hadoop/hbase/HBaseClassTestRule.forClass:(Ljava/lang/Class;)Lorg/apache/hadoop/hbase/HBaseClassTestRule;
       5: putstatic     #253                // Field CLASS_RULE:Lorg/apache/hadoop/hbase/HBaseClassTestRule;
       8: ldc           #167                // class org/apache/hadoop/hbase/coprocessor/TestRegionObserverInterface
      10: invokestatic  #254                // Method org/slf4j/LoggerFactory.getLogger:(Ljava/lang/Class;)Lorg/slf4j/Logger;
      13: putstatic     #149                // Field LOG:Lorg/slf4j/Logger;
      16: ldc           #255                // String TestTable
      18: invokestatic  #27                 // Method org/apache/hadoop/hbase/TableName.valueOf:(Ljava/lang/String;)Lorg/apache/hadoop/hbase/TableName;
      21: putstatic     #21                 // Field TEST_TABLE:Lorg/apache/hadoop/hbase/TableName;
      24: ldc_w         #256                // String a
      27: invokestatic  #190                // Method org/apache/hadoop/hbase/util/Bytes.toBytes:(Ljava/lang/String;)[B
      30: putstatic     #29                 // Field A:[B
      33: ldc_w         #257                // String b
      36: invokestatic  #190                // Method org/apache/hadoop/hbase/util/Bytes.toBytes:(Ljava/lang/String;)[B
      39: putstatic     #30                 // Field B:[B
      42: ldc_w         #258                // String c
      45: invokestatic  #190                // Method org/apache/hadoop/hbase/util/Bytes.toBytes:(Ljava/lang/String;)[B
      48: putstatic     #31                 // Field C:[B
      51: ldc_w         #259                // String testrow
      54: invokestatic  #190                // Method org/apache/hadoop/hbase/util/Bytes.toBytes:(Ljava/lang/String;)[B
      57: putstatic     #45                 // Field ROW:[B
      60: new           #260                // class org/apache/hadoop/hbase/HBaseTestingUtility
      63: dup
      64: invokespecial #261                // Method org/apache/hadoop/hbase/HBaseTestingUtility."<init>":()V
      67: putstatic     #5                  // Field util:Lorg/apache/hadoop/hbase/HBaseTestingUtility;
      70: aconst_null
      71: putstatic     #17                 // Field cluster:Lorg/apache/hadoop/hbase/MiniHBaseCluster;
      74: return
}
