Compiled from "TestAsyncNonMetaRegionLocatorConcurrenyLimit.java"
public class org.apache.hadoop.hbase.client.TestAsyncNonMetaRegionLocatorConcurrenyLimit {
  public static final org.apache.hadoop.hbase.HBaseClassTestRule CLASS_RULE;

  public org.apache.hadoop.hbase.client.TestAsyncNonMetaRegionLocatorConcurrenyLimit();
    Code:
       0: aload_0
       1: invokespecial #5                  // Method java/lang/Object."<init>":()V
       4: return

  public static void setUp() throws java.lang.Exception;
    Code:
       0: getstatic     #6                  // Field TEST_UTIL:Lorg/apache/hadoop/hbase/HBaseTestingUtility;
       3: invokevirtual #7                  // Method org/apache/hadoop/hbase/HBaseTestingUtility.getConfiguration:()Lorg/apache/hadoop/conf/Configuration;
       6: astore_0
       7: aload_0
       8: ldc           #8                  // String hbase.coprocessor.region.classes
      10: ldc           #9                  // class org/apache/hadoop/hbase/client/TestAsyncNonMetaRegionLocatorConcurrenyLimit$CountingRegionObserver
      12: invokevirtual #10                 // Method java/lang/Class.getName:()Ljava/lang/String;
      15: invokevirtual #11                 // Method org/apache/hadoop/conf/Configuration.set:(Ljava/lang/String;Ljava/lang/String;)V
      18: aload_0
      19: ldc           #12                 // String hbase.client.meta.max.concurrent.locate.per.table
      21: getstatic     #13                 // Field MAX_ALLOWED:I
      24: invokevirtual #14                 // Method org/apache/hadoop/conf/Configuration.setInt:(Ljava/lang/String;I)V
      27: getstatic     #6                  // Field TEST_UTIL:Lorg/apache/hadoop/hbase/HBaseTestingUtility;
      30: iconst_3
      31: invokevirtual #15                 // Method org/apache/hadoop/hbase/HBaseTestingUtility.startMiniCluster:(I)Lorg/apache/hadoop/hbase/MiniHBaseCluster;
      34: pop
      35: getstatic     #6                  // Field TEST_UTIL:Lorg/apache/hadoop/hbase/HBaseTestingUtility;
      38: invokevirtual #16                 // Method org/apache/hadoop/hbase/HBaseTestingUtility.getAdmin:()Lorg/apache/hadoop/hbase/client/Admin;
      41: iconst_0
      42: iconst_1
      43: invokeinterface #17,  3           // InterfaceMethod org/apache/hadoop/hbase/client/Admin.balancerSwitch:(ZZ)Z
      48: pop
      49: getstatic     #6                  // Field TEST_UTIL:Lorg/apache/hadoop/hbase/HBaseTestingUtility;
      52: invokevirtual #7                  // Method org/apache/hadoop/hbase/HBaseTestingUtility.getConfiguration:()Lorg/apache/hadoop/conf/Configuration;
      55: invokestatic  #18                 // Method org/apache/hadoop/hbase/client/AsyncRegistryFactory.getRegistry:(Lorg/apache/hadoop/conf/Configuration;)Lorg/apache/hadoop/hbase/client/AsyncRegistry;
      58: astore_1
      59: new           #19                 // class org/apache/hadoop/hbase/client/AsyncConnectionImpl
      62: dup
      63: getstatic     #6                  // Field TEST_UTIL:Lorg/apache/hadoop/hbase/HBaseTestingUtility;
      66: invokevirtual #7                  // Method org/apache/hadoop/hbase/HBaseTestingUtility.getConfiguration:()Lorg/apache/hadoop/conf/Configuration;
      69: aload_1
      70: aload_1
      71: invokeinterface #20,  1           // InterfaceMethod org/apache/hadoop/hbase/client/AsyncRegistry.getClusterId:()Ljava/util/concurrent/CompletableFuture;
      76: invokevirtual #21                 // Method java/util/concurrent/CompletableFuture.get:()Ljava/lang/Object;
      79: checkcast     #22                 // class java/lang/String
      82: invokestatic  #23                 // Method org/apache/hadoop/hbase/security/User.getCurrent:()Lorg/apache/hadoop/hbase/security/User;
      85: invokespecial #24                 // Method org/apache/hadoop/hbase/client/AsyncConnectionImpl."<init>":(Lorg/apache/hadoop/conf/Configuration;Lorg/apache/hadoop/hbase/client/AsyncRegistry;Ljava/lang/String;Lorg/apache/hadoop/hbase/security/User;)V
      88: putstatic     #25                 // Field CONN:Lorg/apache/hadoop/hbase/client/AsyncConnectionImpl;
      91: new           #1                  // class org/apache/hadoop/hbase/client/AsyncNonMetaRegionLocator
      94: dup
      95: getstatic     #25                 // Field CONN:Lorg/apache/hadoop/hbase/client/AsyncConnectionImpl;
      98: invokespecial #26                 // Method org/apache/hadoop/hbase/client/AsyncNonMetaRegionLocator."<init>":(Lorg/apache/hadoop/hbase/client/AsyncConnectionImpl;)V
     101: putstatic     #27                 // Field LOCATOR:Lorg/apache/hadoop/hbase/client/AsyncNonMetaRegionLocator;
     104: iconst_1
     105: sipush        256
     108: invokestatic  #28                 // InterfaceMethod java/util/stream/IntStream.range:(II)Ljava/util/stream/IntStream;
     111: invokedynamic #29,  0             // InvokeDynamic #0:apply:()Ljava/util/function/IntFunction;
     116: invokeinterface #30,  2           // InterfaceMethod java/util/stream/IntStream.mapToObj:(Ljava/util/function/IntFunction;)Ljava/util/stream/Stream;
     121: invokedynamic #31,  0             // InvokeDynamic #1:apply:()Ljava/util/function/IntFunction;
     126: invokeinterface #32,  2           // InterfaceMethod java/util/stream/Stream.toArray:(Ljava/util/function/IntFunction;)[Ljava/lang/Object;
     131: checkcast     #33                 // class "[[B"
     134: putstatic     #34                 // Field SPLIT_KEYS:[[B
     137: getstatic     #6                  // Field TEST_UTIL:Lorg/apache/hadoop/hbase/HBaseTestingUtility;
     140: getstatic     #35                 // Field TABLE_NAME:Lorg/apache/hadoop/hbase/TableName;
     143: getstatic     #36                 // Field FAMILY:[B
     146: getstatic     #34                 // Field SPLIT_KEYS:[[B
     149: invokevirtual #37                 // Method org/apache/hadoop/hbase/HBaseTestingUtility.createTable:(Lorg/apache/hadoop/hbase/TableName;[B[[B)Lorg/apache/hadoop/hbase/client/Table;
     152: pop
     153: getstatic     #6                  // Field TEST_UTIL:Lorg/apache/hadoop/hbase/HBaseTestingUtility;
     156: getstatic     #35                 // Field TABLE_NAME:Lorg/apache/hadoop/hbase/TableName;
     159: invokevirtual #38                 // Method org/apache/hadoop/hbase/HBaseTestingUtility.waitTableAvailable:(Lorg/apache/hadoop/hbase/TableName;)V
     162: return

  public static void tearDown() throws java.lang.Exception;
    Code:
       0: getstatic     #25                 // Field CONN:Lorg/apache/hadoop/hbase/client/AsyncConnectionImpl;
       3: invokestatic  #39                 // Method org/apache/commons/io/IOUtils.closeQuietly:(Ljava/io/Closeable;)V
       6: getstatic     #6                  // Field TEST_UTIL:Lorg/apache/hadoop/hbase/HBaseTestingUtility;
       9: invokevirtual #40                 // Method org/apache/hadoop/hbase/HBaseTestingUtility.shutdownMiniCluster:()V
      12: return

  public void test() throws java.lang.InterruptedException, java.util.concurrent.ExecutionException;
    Code:
       0: iconst_0
       1: sipush        256
       4: invokestatic  #28                 // InterfaceMethod java/util/stream/IntStream.range:(II)Ljava/util/stream/IntStream;
       7: invokedynamic #61,  0             // InvokeDynamic #2:apply:()Ljava/util/function/IntFunction;
      12: invokeinterface #30,  2           // InterfaceMethod java/util/stream/IntStream.mapToObj:(Ljava/util/function/IntFunction;)Ljava/util/stream/Stream;
      17: invokedynamic #62,  0             // InvokeDynamic #3:apply:()Ljava/util/function/Function;
      22: invokeinterface #63,  2           // InterfaceMethod java/util/stream/Stream.map:(Ljava/util/function/Function;)Ljava/util/stream/Stream;
      27: invokestatic  #64                 // Method java/util/stream/Collectors.toList:()Ljava/util/stream/Collector;
      30: invokeinterface #65,  2           // InterfaceMethod java/util/stream/Stream.collect:(Ljava/util/stream/Collector;)Ljava/lang/Object;
      35: checkcast     #66                 // class java/util/List
      38: astore_1
      39: aload_0
      40: aload_1
      41: invokespecial #67                 // Method assertLocs:(Ljava/util/List;)V
      44: new           #68                 // class java/lang/StringBuilder
      47: dup
      48: invokespecial #69                 // Method java/lang/StringBuilder."<init>":()V
      51: ldc           #70                 // String max allowed is
      53: invokevirtual #71                 // Method java/lang/StringBuilder.append:(Ljava/lang/String;)Ljava/lang/StringBuilder;
      56: getstatic     #13                 // Field MAX_ALLOWED:I
      59: invokevirtual #72                 // Method java/lang/StringBuilder.append:(I)Ljava/lang/StringBuilder;
      62: ldc           #73                 // String  but actual is
      64: invokevirtual #71                 // Method java/lang/StringBuilder.append:(Ljava/lang/String;)Ljava/lang/StringBuilder;
      67: getstatic     #3                  // Field MAX_CONCURRENCY:Ljava/util/concurrent/atomic/AtomicInteger;
      70: invokevirtual #74                 // Method java/util/concurrent/atomic/AtomicInteger.get:()I
      73: invokevirtual #72                 // Method java/lang/StringBuilder.append:(I)Ljava/lang/StringBuilder;
      76: invokevirtual #75                 // Method java/lang/StringBuilder.toString:()Ljava/lang/String;
      79: getstatic     #3                  // Field MAX_CONCURRENCY:Ljava/util/concurrent/atomic/AtomicInteger;
      82: invokevirtual #74                 // Method java/util/concurrent/atomic/AtomicInteger.get:()I
      85: getstatic     #13                 // Field MAX_ALLOWED:I
      88: if_icmpgt     95
      91: iconst_1
      92: goto          96
      95: iconst_0
      96: invokestatic  #76                 // Method org/junit/Assert.assertTrue:(Ljava/lang/String;Z)V
      99: return

  static java.util.concurrent.atomic.AtomicInteger access$000();
    Code:
       0: getstatic     #4                  // Field CONCURRENCY:Ljava/util/concurrent/atomic/AtomicInteger;
       3: areturn

  static java.util.concurrent.atomic.AtomicInteger access$100();
    Code:
       0: getstatic     #3                  // Field MAX_CONCURRENCY:Ljava/util/concurrent/atomic/AtomicInteger;
       3: areturn

  static {};
    Code:
       0: ldc           #82                 // class org/apache/hadoop/hbase/client/TestAsyncNonMetaRegionLocatorConcurrenyLimit
       2: invokestatic  #83                 // Method org/apache/hadoop/hbase/HBaseClassTestRule.forClass:(Ljava/lang/Class;)Lorg/apache/hadoop/hbase/HBaseClassTestRule;
       5: putstatic     #84                 // Field CLASS_RULE:Lorg/apache/hadoop/hbase/HBaseClassTestRule;
       8: new           #85                 // class org/apache/hadoop/hbase/HBaseTestingUtility
      11: dup
      12: invokespecial #86                 // Method org/apache/hadoop/hbase/HBaseTestingUtility."<init>":()V
      15: putstatic     #6                  // Field TEST_UTIL:Lorg/apache/hadoop/hbase/HBaseTestingUtility;
      18: ldc           #87                 // String async
      20: invokestatic  #88                 // Method org/apache/hadoop/hbase/TableName.valueOf:(Ljava/lang/String;)Lorg/apache/hadoop/hbase/TableName;
      23: putstatic     #35                 // Field TABLE_NAME:Lorg/apache/hadoop/hbase/TableName;
      26: ldc           #89                 // String cf
      28: invokestatic  #80                 // Method org/apache/hadoop/hbase/util/Bytes.toBytes:(Ljava/lang/String;)[B
      31: putstatic     #36                 // Field FAMILY:[B
      34: iconst_2
      35: putstatic     #13                 // Field MAX_ALLOWED:I
      38: new           #90                 // class java/util/concurrent/atomic/AtomicInteger
      41: dup
      42: iconst_0
      43: invokespecial #91                 // Method java/util/concurrent/atomic/AtomicInteger."<init>":(I)V
      46: putstatic     #4                  // Field CONCURRENCY:Ljava/util/concurrent/atomic/AtomicInteger;
      49: new           #90                 // class java/util/concurrent/atomic/AtomicInteger
      52: dup
      53: iconst_0
      54: invokespecial #91                 // Method java/util/concurrent/atomic/AtomicInteger."<init>":(I)V
      57: putstatic     #3                  // Field MAX_CONCURRENCY:Ljava/util/concurrent/atomic/AtomicInteger;
      60: return
}
