Compiled from "TestStripeStoreEngine.java"
public class org.apache.hadoop.hbase.regionserver.TestStripeStoreEngine {
  public static final org.apache.hadoop.hbase.HBaseClassTestRule CLASS_RULE;

  public org.apache.hadoop.hbase.regionserver.TestStripeStoreEngine();
    Code:
       0: aload_0
       1: invokespecial #1                  // Method java/lang/Object."<init>":()V
       4: return

  public void testCreateBasedOnConfig() throws java.lang.Exception;
    Code:
       0: invokestatic  #2                  // Method org/apache/hadoop/hbase/HBaseConfiguration.create:()Lorg/apache/hadoop/conf/Configuration;
       3: astore_1
       4: aload_1
       5: ldc           #4                  // String hbase.hstore.engine.class
       7: ldc           #5                  // class org/apache/hadoop/hbase/regionserver/TestStripeStoreEngine$TestStoreEngine
       9: invokevirtual #6                  // Method java/lang/Class.getName:()Ljava/lang/String;
      12: invokevirtual #7                  // Method org/apache/hadoop/conf/Configuration.set:(Ljava/lang/String;Ljava/lang/String;)V
      15: aload_1
      16: invokestatic  #8                  // Method createEngine:(Lorg/apache/hadoop/conf/Configuration;)Lorg/apache/hadoop/hbase/regionserver/TestStripeStoreEngine$TestStoreEngine;
      19: astore_2
      20: aload_2
      21: invokevirtual #9                  // Method org/apache/hadoop/hbase/regionserver/StripeStoreEngine.getCompactionPolicy:()Lorg/apache/hadoop/hbase/regionserver/compactions/CompactionPolicy;
      24: instanceof    #10                 // class org/apache/hadoop/hbase/regionserver/compactions/StripeCompactionPolicy
      27: invokestatic  #11                 // Method org/junit/Assert.assertTrue:(Z)V
      30: return

  public void testCompactionContextForceSelect() throws java.lang.Exception;
    Code:
       0: invokestatic  #2                  // Method org/apache/hadoop/hbase/HBaseConfiguration.create:()Lorg/apache/hadoop/conf/Configuration;
       3: astore_1
       4: iconst_2
       5: istore_2
       6: aload_1
       7: ldc           #13                 // String hbase.store.stripe.initialStripeCount
       9: iload_2
      10: invokevirtual #14                 // Method org/apache/hadoop/conf/Configuration.setInt:(Ljava/lang/String;I)V
      13: aload_1
      14: ldc           #15                 // String hbase.store.stripe.compaction.minFilesL0
      16: iconst_2
      17: invokevirtual #14                 // Method org/apache/hadoop/conf/Configuration.setInt:(Ljava/lang/String;I)V
      20: aload_1
      21: ldc           #4                  // String hbase.hstore.engine.class
      23: ldc           #5                  // class org/apache/hadoop/hbase/regionserver/TestStripeStoreEngine$TestStoreEngine
      25: invokevirtual #6                  // Method java/lang/Class.getName:()Ljava/lang/String;
      28: invokevirtual #7                  // Method org/apache/hadoop/conf/Configuration.set:(Ljava/lang/String;Ljava/lang/String;)V
      31: aload_1
      32: invokestatic  #8                  // Method createEngine:(Lorg/apache/hadoop/conf/Configuration;)Lorg/apache/hadoop/hbase/regionserver/TestStripeStoreEngine$TestStoreEngine;
      35: astore_3
      36: ldc           #16                 // class org/apache/hadoop/hbase/regionserver/compactions/StripeCompactor
      38: invokestatic  #17                 // Method org/mockito/Mockito.mock:(Ljava/lang/Class;)Ljava/lang/Object;
      41: checkcast     #16                 // class org/apache/hadoop/hbase/regionserver/compactions/StripeCompactor
      44: astore        4
      46: aload_3
      47: aload         4
      49: invokevirtual #18                 // Method org/apache/hadoop/hbase/regionserver/TestStripeStoreEngine$TestStoreEngine.setCompactorOverride:(Lorg/apache/hadoop/hbase/regionserver/compactions/StripeCompactor;)V
      52: aload         4
      54: invokestatic  #19                 // Method org/mockito/Matchers.any:()Ljava/lang/Object;
      57: checkcast     #20                 // class org/apache/hadoop/hbase/regionserver/compactions/CompactionRequestImpl
      60: invokestatic  #21                 // Method org/mockito/Matchers.anyInt:()I
      63: invokestatic  #22                 // Method org/mockito/Matchers.anyLong:()J
      66: invokestatic  #19                 // Method org/mockito/Matchers.any:()Ljava/lang/Object;
      69: checkcast     #23                 // class "[B"
      72: invokestatic  #19                 // Method org/mockito/Matchers.any:()Ljava/lang/Object;
      75: checkcast     #23                 // class "[B"
      78: invokestatic  #19                 // Method org/mockito/Matchers.any:()Ljava/lang/Object;
      81: checkcast     #23                 // class "[B"
      84: invokestatic  #19                 // Method org/mockito/Matchers.any:()Ljava/lang/Object;
      87: checkcast     #23                 // class "[B"
      90: invokestatic  #19                 // Method org/mockito/Matchers.any:()Ljava/lang/Object;
      93: checkcast     #24                 // class org/apache/hadoop/hbase/regionserver/throttle/ThroughputController
      96: invokestatic  #19                 // Method org/mockito/Matchers.any:()Ljava/lang/Object;
      99: checkcast     #25                 // class org/apache/hadoop/hbase/security/User
     102: invokevirtual #26                 // Method org/apache/hadoop/hbase/regionserver/compactions/StripeCompactor.compact:(Lorg/apache/hadoop/hbase/regionserver/compactions/CompactionRequestImpl;IJ[B[B[B[BLorg/apache/hadoop/hbase/regionserver/throttle/ThroughputController;Lorg/apache/hadoop/hbase/security/User;)Ljava/util/List;
     105: invokestatic  #27                 // Method org/mockito/Mockito.when:(Ljava/lang/Object;)Lorg/mockito/stubbing/OngoingStubbing;
     108: new           #28                 // class java/util/ArrayList
     111: dup
     112: invokespecial #29                 // Method java/util/ArrayList."<init>":()V
     115: invokeinterface #30,  2           // InterfaceMethod org/mockito/stubbing/OngoingStubbing.thenReturn:(Ljava/lang/Object;)Lorg/mockito/stubbing/OngoingStubbing;
     120: pop
     121: invokestatic  #31                 // Method createFile:()Lorg/apache/hadoop/hbase/regionserver/HStoreFile;
     124: astore        5
     126: iconst_3
     127: anewarray     #32                 // class org/apache/hadoop/hbase/regionserver/HStoreFile
     130: dup
     131: iconst_0
     132: aload         5
     134: aastore
     135: dup
     136: iconst_1
     137: invokestatic  #31                 // Method createFile:()Lorg/apache/hadoop/hbase/regionserver/HStoreFile;
     140: aastore
     141: dup
     142: iconst_2
     143: invokestatic  #31                 // Method createFile:()Lorg/apache/hadoop/hbase/regionserver/HStoreFile;
     146: aastore
     147: invokestatic  #33                 // Method al:([Lorg/apache/hadoop/hbase/regionserver/HStoreFile;)Ljava/util/ArrayList;
     150: astore        6
     152: aload_3
     153: invokevirtual #34                 // Method org/apache/hadoop/hbase/regionserver/TestStripeStoreEngine$TestStoreEngine.getStoreFileManager:()Lorg/apache/hadoop/hbase/regionserver/StoreFileManager;
     156: aload         6
     158: invokeinterface #35,  2           // InterfaceMethod org/apache/hadoop/hbase/regionserver/StoreFileManager.loadFiles:(Ljava/util/List;)V
     163: aload_3
     164: invokevirtual #36                 // Method org/apache/hadoop/hbase/regionserver/TestStripeStoreEngine$TestStoreEngine.createCompaction:()Lorg/apache/hadoop/hbase/regionserver/compactions/CompactionContext;
     167: astore        7
     169: aload         7
     171: iconst_0
     172: anewarray     #32                 // class org/apache/hadoop/hbase/regionserver/HStoreFile
     175: invokestatic  #33                 // Method al:([Lorg/apache/hadoop/hbase/regionserver/HStoreFile;)Ljava/util/ArrayList;
     178: iconst_0
     179: iconst_0
     180: iconst_0
     181: invokevirtual #37                 // Method org/apache/hadoop/hbase/regionserver/compactions/CompactionContext.select:(Ljava/util/List;ZZZ)Z
     184: pop
     185: ldc2_w        #38                 // long 3l
     188: aload         7
     190: invokevirtual #40                 // Method org/apache/hadoop/hbase/regionserver/compactions/CompactionContext.getRequest:()Lorg/apache/hadoop/hbase/regionserver/compactions/CompactionRequestImpl;
     193: invokevirtual #41                 // Method org/apache/hadoop/hbase/regionserver/compactions/CompactionRequestImpl.getFiles:()Ljava/util/Collection;
     196: invokeinterface #42,  1           // InterfaceMethod java/util/Collection.size:()I
     201: i2l
     202: invokestatic  #43                 // Method org/junit/Assert.assertEquals:(JJ)V
     205: aload         6
     207: aload         5
     209: invokevirtual #44                 // Method java/util/ArrayList.remove:(Ljava/lang/Object;)Z
     212: pop
     213: new           #20                 // class org/apache/hadoop/hbase/regionserver/compactions/CompactionRequestImpl
     216: dup
     217: aload         6
     219: invokespecial #45                 // Method org/apache/hadoop/hbase/regionserver/compactions/CompactionRequestImpl."<init>":(Ljava/util/Collection;)V
     222: astore        8
     224: aload         7
     226: aload         8
     228: invokevirtual #46                 // Method org/apache/hadoop/hbase/regionserver/compactions/CompactionContext.forceSelect:(Lorg/apache/hadoop/hbase/regionserver/compactions/CompactionRequestImpl;)V
     231: ldc2_w        #47                 // long 2l
     234: aload         7
     236: invokevirtual #40                 // Method org/apache/hadoop/hbase/regionserver/compactions/CompactionContext.getRequest:()Lorg/apache/hadoop/hbase/regionserver/compactions/CompactionRequestImpl;
     239: invokevirtual #41                 // Method org/apache/hadoop/hbase/regionserver/compactions/CompactionRequestImpl.getFiles:()Ljava/util/Collection;
     242: invokeinterface #42,  1           // InterfaceMethod java/util/Collection.size:()I
     247: i2l
     248: invokestatic  #43                 // Method org/junit/Assert.assertEquals:(JJ)V
     251: aload         7
     253: invokevirtual #40                 // Method org/apache/hadoop/hbase/regionserver/compactions/CompactionContext.getRequest:()Lorg/apache/hadoop/hbase/regionserver/compactions/CompactionRequestImpl;
     256: invokevirtual #41                 // Method org/apache/hadoop/hbase/regionserver/compactions/CompactionRequestImpl.getFiles:()Ljava/util/Collection;
     259: aload         5
     261: invokeinterface #49,  2           // InterfaceMethod java/util/Collection.contains:(Ljava/lang/Object;)Z
     266: invokestatic  #50                 // Method org/junit/Assert.assertFalse:(Z)V
     269: aload         7
     271: getstatic     #51                 // Field org/apache/hadoop/hbase/regionserver/throttle/NoLimitThroughputController.INSTANCE:Lorg/apache/hadoop/hbase/regionserver/throttle/NoLimitThroughputController;
     274: aconst_null
     275: invokevirtual #52                 // Method org/apache/hadoop/hbase/regionserver/compactions/CompactionContext.compact:(Lorg/apache/hadoop/hbase/regionserver/throttle/ThroughputController;Lorg/apache/hadoop/hbase/security/User;)Ljava/util/List;
     278: pop
     279: aload         4
     281: iconst_1
     282: invokestatic  #53                 // Method org/mockito/Mockito.times:(I)Lorg/mockito/verification/VerificationMode;
     285: invokestatic  #54                 // Method org/mockito/Mockito.verify:(Ljava/lang/Object;Lorg/mockito/verification/VerificationMode;)Ljava/lang/Object;
     288: checkcast     #16                 // class org/apache/hadoop/hbase/regionserver/compactions/StripeCompactor
     291: aload         7
     293: invokevirtual #40                 // Method org/apache/hadoop/hbase/regionserver/compactions/CompactionContext.getRequest:()Lorg/apache/hadoop/hbase/regionserver/compactions/CompactionRequestImpl;
     296: iload_2
     297: lconst_0
     298: getstatic     #55                 // Field org/apache/hadoop/hbase/regionserver/StripeStoreFileManager.OPEN_KEY:[B
     301: getstatic     #55                 // Field org/apache/hadoop/hbase/regionserver/StripeStoreFileManager.OPEN_KEY:[B
     304: aconst_null
     305: aconst_null
     306: getstatic     #51                 // Field org/apache/hadoop/hbase/regionserver/throttle/NoLimitThroughputController.INSTANCE:Lorg/apache/hadoop/hbase/regionserver/throttle/NoLimitThroughputController;
     309: aconst_null
     310: invokevirtual #26                 // Method org/apache/hadoop/hbase/regionserver/compactions/StripeCompactor.compact:(Lorg/apache/hadoop/hbase/regionserver/compactions/CompactionRequestImpl;IJ[B[B[B[BLorg/apache/hadoop/hbase/regionserver/throttle/ThroughputController;Lorg/apache/hadoop/hbase/security/User;)Ljava/util/List;
     313: pop
     314: return

  static {};
    Code:
       0: ldc           #71                 // class org/apache/hadoop/hbase/regionserver/TestStripeStoreEngine
       2: invokestatic  #72                 // Method org/apache/hadoop/hbase/HBaseClassTestRule.forClass:(Ljava/lang/Class;)Lorg/apache/hadoop/hbase/HBaseClassTestRule;
       5: putstatic     #73                 // Field CLASS_RULE:Lorg/apache/hadoop/hbase/HBaseClassTestRule;
       8: return
}
