Compiled from "TestParallelPut.java"
public class org.apache.hadoop.hbase.regionserver.TestParallelPut {
  public static final org.apache.hadoop.hbase.HBaseClassTestRule CLASS_RULE;

  public org.junit.rules.TestName name;

  static byte[] tableName;

  static final byte[] qual1;

  static final byte[] qual2;

  static final byte[] qual3;

  static final byte[] value1;

  static final byte[] value2;

  static final byte[] row;

  static final byte[] row2;

  public org.apache.hadoop.hbase.regionserver.TestParallelPut();
    Code:
       0: aload_0
       1: invokespecial #2                  // Method java/lang/Object."<init>":()V
       4: aload_0
       5: new           #3                  // class org/junit/rules/TestName
       8: dup
       9: invokespecial #4                  // Method org/junit/rules/TestName."<init>":()V
      12: putfield      #5                  // Field name:Lorg/junit/rules/TestName;
      15: aload_0
      16: aconst_null
      17: putfield      #6                  // Field region:Lorg/apache/hadoop/hbase/regionserver/HRegion;
      20: return

  public static void beforeClass();
    Code:
       0: getstatic     #7                  // Field HBTU:Lorg/apache/hadoop/hbase/HBaseTestingUtility;
       3: invokevirtual #8                  // Method org/apache/hadoop/hbase/HBaseTestingUtility.getConfiguration:()Lorg/apache/hadoop/conf/Configuration;
       6: ldc           #10                 // String hbase.regionserver.handler.count
       8: bipush        100
      10: invokevirtual #12                 // Method org/apache/hadoop/conf/Configuration.setInt:(Ljava/lang/String;I)V
      13: return

  public void setUp() throws java.lang.Exception;
    Code:
       0: aload_0
       1: getfield      #5                  // Field name:Lorg/junit/rules/TestName;
       4: invokevirtual #13                 // Method org/junit/rules/TestName.getMethodName:()Ljava/lang/String;
       7: invokestatic  #14                 // Method org/apache/hadoop/hbase/util/Bytes.toBytes:(Ljava/lang/String;)[B
      10: putstatic     #15                 // Field tableName:[B
      13: return

  public void tearDown() throws java.lang.Exception;
    Code:
       0: invokestatic  #16                 // Method org/apache/hadoop/hbase/util/EnvironmentEdgeManagerTestHelper.reset:()V
       3: aload_0
       4: getfield      #6                  // Field region:Lorg/apache/hadoop/hbase/regionserver/HRegion;
       7: ifnull        19
      10: aload_0
      11: getfield      #6                  // Field region:Lorg/apache/hadoop/hbase/regionserver/HRegion;
      14: iconst_1
      15: invokevirtual #17                 // Method org/apache/hadoop/hbase/regionserver/HRegion.close:(Z)Ljava/util/Map;
      18: pop
      19: return

  public java.lang.String getName();
    Code:
       0: aload_0
       1: getfield      #5                  // Field name:Lorg/junit/rules/TestName;
       4: invokevirtual #13                 // Method org/junit/rules/TestName.getMethodName:()Ljava/lang/String;
       7: areturn

  public void testPut() throws java.io.IOException;
    Code:
       0: getstatic     #18                 // Field LOG:Lorg/slf4j/Logger;
       3: ldc           #19                 // String Starting testPut
       5: invokeinterface #20,  2           // InterfaceMethod org/slf4j/Logger.info:(Ljava/lang/String;)V
      10: aload_0
      11: aload_0
      12: getstatic     #15                 // Field tableName:[B
      15: aload_0
      16: invokevirtual #21                 // Method getName:()Ljava/lang/String;
      19: iconst_1
      20: anewarray     #22                 // class "[B"
      23: dup
      24: iconst_0
      25: getstatic     #23                 // Field org/apache/hadoop/hbase/HBaseTestingUtility.fam1:[B
      28: aastore
      29: invokespecial #24                 // Method initHRegion:([BLjava/lang/String;[[B)Lorg/apache/hadoop/hbase/regionserver/HRegion;
      32: putfield      #6                  // Field region:Lorg/apache/hadoop/hbase/regionserver/HRegion;
      35: lconst_1
      36: lstore_1
      37: new           #25                 // class org/apache/hadoop/hbase/client/Put
      40: dup
      41: getstatic     #26                 // Field row:[B
      44: invokespecial #27                 // Method org/apache/hadoop/hbase/client/Put."<init>":([B)V
      47: astore_3
      48: aload_3
      49: getstatic     #23                 // Field org/apache/hadoop/hbase/HBaseTestingUtility.fam1:[B
      52: getstatic     #28                 // Field qual1:[B
      55: lload_1
      56: invokestatic  #29                 // Method org/apache/hadoop/hbase/util/Bytes.toBytes:(J)[B
      59: invokevirtual #30                 // Method org/apache/hadoop/hbase/client/Put.addColumn:([B[B[B)Lorg/apache/hadoop/hbase/client/Put;
      62: pop
      63: aload_0
      64: getfield      #6                  // Field region:Lorg/apache/hadoop/hbase/regionserver/HRegion;
      67: aload_3
      68: invokevirtual #31                 // Method org/apache/hadoop/hbase/regionserver/HRegion.put:(Lorg/apache/hadoop/hbase/client/Put;)V
      71: aload_0
      72: getfield      #6                  // Field region:Lorg/apache/hadoop/hbase/regionserver/HRegion;
      75: getstatic     #26                 // Field row:[B
      78: getstatic     #23                 // Field org/apache/hadoop/hbase/HBaseTestingUtility.fam1:[B
      81: getstatic     #28                 // Field qual1:[B
      84: lload_1
      85: invokestatic  #29                 // Method org/apache/hadoop/hbase/util/Bytes.toBytes:(J)[B
      88: invokestatic  #1                  // Method assertGet:(Lorg/apache/hadoop/hbase/regionserver/HRegion;[B[B[B[B)V
      91: return

  public void testParallelPuts() throws java.io.IOException;
    Code:
       0: getstatic     #18                 // Field LOG:Lorg/slf4j/Logger;
       3: ldc           #32                 // String Starting testParallelPuts
       5: invokeinterface #20,  2           // InterfaceMethod org/slf4j/Logger.info:(Ljava/lang/String;)V
      10: aload_0
      11: aload_0
      12: getstatic     #15                 // Field tableName:[B
      15: aload_0
      16: invokevirtual #21                 // Method getName:()Ljava/lang/String;
      19: iconst_1
      20: anewarray     #22                 // class "[B"
      23: dup
      24: iconst_0
      25: getstatic     #23                 // Field org/apache/hadoop/hbase/HBaseTestingUtility.fam1:[B
      28: aastore
      29: invokespecial #24                 // Method initHRegion:([BLjava/lang/String;[[B)Lorg/apache/hadoop/hbase/regionserver/HRegion;
      32: putfield      #6                  // Field region:Lorg/apache/hadoop/hbase/regionserver/HRegion;
      35: sipush        1000
      38: istore_1
      39: bipush        100
      41: anewarray     #33                 // class org/apache/hadoop/hbase/regionserver/TestParallelPut$Putter
      44: astore_2
      45: iconst_0
      46: istore_3
      47: iload_3
      48: bipush        100
      50: if_icmpge     75
      53: aload_2
      54: iload_3
      55: new           #33                 // class org/apache/hadoop/hbase/regionserver/TestParallelPut$Putter
      58: dup
      59: aload_0
      60: getfield      #6                  // Field region:Lorg/apache/hadoop/hbase/regionserver/HRegion;
      63: iload_3
      64: iload_1
      65: invokespecial #34                 // Method org/apache/hadoop/hbase/regionserver/TestParallelPut$Putter."<init>":(Lorg/apache/hadoop/hbase/regionserver/HRegion;II)V
      68: aastore
      69: iinc          3, 1
      72: goto          47
      75: iconst_0
      76: istore_3
      77: iload_3
      78: bipush        100
      80: if_icmpge     95
      83: aload_2
      84: iload_3
      85: aaload
      86: invokevirtual #35                 // Method org/apache/hadoop/hbase/regionserver/TestParallelPut$Putter.start:()V
      89: iinc          3, 1
      92: goto          77
      95: iconst_0
      96: istore_3
      97: iload_3
      98: bipush        100
     100: if_icmpge     132
     103: aload_2
     104: iload_3
     105: aaload
     106: invokevirtual #36                 // Method org/apache/hadoop/hbase/regionserver/TestParallelPut$Putter.join:()V
     109: goto          126
     112: astore        4
     114: getstatic     #18                 // Field LOG:Lorg/slf4j/Logger;
     117: ldc           #38                 // String testParallelPuts encountered InterruptedException. Ignoring....
     119: aload         4
     121: invokeinterface #39,  3           // InterfaceMethod org/slf4j/Logger.warn:(Ljava/lang/String;Ljava/lang/Throwable;)V
     126: iinc          3, 1
     129: goto          97
     132: getstatic     #18                 // Field LOG:Lorg/slf4j/Logger;
     135: new           #40                 // class java/lang/StringBuilder
     138: dup
     139: invokespecial #41                 // Method java/lang/StringBuilder."<init>":()V
     142: ldc           #42                 // String testParallelPuts successfully verified
     144: invokevirtual #43                 // Method java/lang/StringBuilder.append:(Ljava/lang/String;)Ljava/lang/StringBuilder;
     147: iload_1
     148: bipush        100
     150: imul
     151: invokevirtual #44                 // Method java/lang/StringBuilder.append:(I)Ljava/lang/StringBuilder;
     154: ldc           #45                 // String  put operations.
     156: invokevirtual #43                 // Method java/lang/StringBuilder.append:(Ljava/lang/String;)Ljava/lang/StringBuilder;
     159: invokevirtual #46                 // Method java/lang/StringBuilder.toString:()Ljava/lang/String;
     162: invokeinterface #20,  2           // InterfaceMethod org/slf4j/Logger.info:(Ljava/lang/String;)V
     167: return
    Exception table:
       from    to  target type
         103   109   112   Class java/lang/InterruptedException

  static void access$000(org.apache.hadoop.hbase.regionserver.HRegion, byte[], byte[], byte[], byte[]) throws java.io.IOException;
    Code:
       0: aload_0
       1: aload_1
       2: aload_2
       3: aload_3
       4: aload         4
       6: invokestatic  #1                  // Method assertGet:(Lorg/apache/hadoop/hbase/regionserver/HRegion;[B[B[B[B)V
       9: return

  static {};
    Code:
       0: ldc           #11                 // class org/apache/hadoop/hbase/regionserver/TestParallelPut
       2: invokestatic  #67                 // Method org/apache/hadoop/hbase/HBaseClassTestRule.forClass:(Ljava/lang/Class;)Lorg/apache/hadoop/hbase/HBaseClassTestRule;
       5: putstatic     #68                 // Field CLASS_RULE:Lorg/apache/hadoop/hbase/HBaseClassTestRule;
       8: ldc           #11                 // class org/apache/hadoop/hbase/regionserver/TestParallelPut
      10: invokestatic  #69                 // Method org/slf4j/LoggerFactory.getLogger:(Ljava/lang/Class;)Lorg/slf4j/Logger;
      13: putstatic     #18                 // Field LOG:Lorg/slf4j/Logger;
      16: new           #70                 // class org/apache/hadoop/hbase/HBaseTestingUtility
      19: dup
      20: invokespecial #71                 // Method org/apache/hadoop/hbase/HBaseTestingUtility."<init>":()V
      23: putstatic     #7                  // Field HBTU:Lorg/apache/hadoop/hbase/HBaseTestingUtility;
      26: ldc           #72                 // String qual1
      28: invokestatic  #14                 // Method org/apache/hadoop/hbase/util/Bytes.toBytes:(Ljava/lang/String;)[B
      31: putstatic     #28                 // Field qual1:[B
      34: ldc           #73                 // String qual2
      36: invokestatic  #14                 // Method org/apache/hadoop/hbase/util/Bytes.toBytes:(Ljava/lang/String;)[B
      39: putstatic     #74                 // Field qual2:[B
      42: ldc           #75                 // String qual3
      44: invokestatic  #14                 // Method org/apache/hadoop/hbase/util/Bytes.toBytes:(Ljava/lang/String;)[B
      47: putstatic     #76                 // Field qual3:[B
      50: ldc           #77                 // String value1
      52: invokestatic  #14                 // Method org/apache/hadoop/hbase/util/Bytes.toBytes:(Ljava/lang/String;)[B
      55: putstatic     #78                 // Field value1:[B
      58: ldc           #79                 // String value2
      60: invokestatic  #14                 // Method org/apache/hadoop/hbase/util/Bytes.toBytes:(Ljava/lang/String;)[B
      63: putstatic     #80                 // Field value2:[B
      66: ldc           #81                 // String rowA
      68: invokestatic  #14                 // Method org/apache/hadoop/hbase/util/Bytes.toBytes:(Ljava/lang/String;)[B
      71: putstatic     #26                 // Field row:[B
      74: ldc           #82                 // String rowB
      76: invokestatic  #14                 // Method org/apache/hadoop/hbase/util/Bytes.toBytes:(Ljava/lang/String;)[B
      79: putstatic     #83                 // Field row2:[B
      82: return
}
