Compiled from "TestWideScanner.java"
public class org.apache.hadoop.hbase.regionserver.TestWideScanner extends org.apache.hadoop.hbase.HBaseTestCase {
  public static final org.apache.hadoop.hbase.HBaseClassTestRule CLASS_RULE;

  static final byte[] A;

  static final byte[] B;

  static final byte[] C;

  static byte[][] COLUMNS;

  static final java.util.Random rng;

  static final org.apache.hadoop.hbase.HTableDescriptor TESTTABLEDESC;

  org.apache.hadoop.hbase.regionserver.HRegion r;

  public org.apache.hadoop.hbase.regionserver.TestWideScanner();
    Code:
       0: aload_0
       1: invokespecial #1                  // Method org/apache/hadoop/hbase/HBaseTestCase."<init>":()V
       4: return

  public void testWideScanBatching() throws java.io.IOException;
    Code:
       0: sipush        256
       3: istore_1
       4: aload_0
       5: aload_0
       6: getstatic     #23                 // Field TESTTABLEDESC:Lorg/apache/hadoop/hbase/HTableDescriptor;
       9: aconst_null
      10: aconst_null
      11: invokevirtual #24                 // Method createNewHRegion:(Lorg/apache/hadoop/hbase/HTableDescriptor;[B[B)Lorg/apache/hadoop/hbase/regionserver/HRegion;
      14: putfield      #25                 // Field r:Lorg/apache/hadoop/hbase/regionserver/HRegion;
      17: aload_0
      18: aload_0
      19: getfield      #25                 // Field r:Lorg/apache/hadoop/hbase/regionserver/HRegion;
      22: invokespecial #26                 // Method addWideContent:(Lorg/apache/hadoop/hbase/regionserver/HRegion;)I
      25: istore_2
      26: new           #27                 // class java/util/ArrayList
      29: dup
      30: invokespecial #28                 // Method java/util/ArrayList."<init>":()V
      33: astore_3
      34: new           #29                 // class org/apache/hadoop/hbase/client/Scan
      37: dup
      38: invokespecial #30                 // Method org/apache/hadoop/hbase/client/Scan."<init>":()V
      41: astore        4
      43: aload         4
      45: getstatic     #31                 // Field A:[B
      48: invokevirtual #32                 // Method org/apache/hadoop/hbase/client/Scan.addFamily:([B)Lorg/apache/hadoop/hbase/client/Scan;
      51: pop
      52: aload         4
      54: getstatic     #33                 // Field B:[B
      57: invokevirtual #32                 // Method org/apache/hadoop/hbase/client/Scan.addFamily:([B)Lorg/apache/hadoop/hbase/client/Scan;
      60: pop
      61: aload         4
      63: getstatic     #34                 // Field C:[B
      66: invokevirtual #32                 // Method org/apache/hadoop/hbase/client/Scan.addFamily:([B)Lorg/apache/hadoop/hbase/client/Scan;
      69: pop
      70: aload         4
      72: bipush        100
      74: invokevirtual #35                 // Method org/apache/hadoop/hbase/client/Scan.setMaxVersions:(I)Lorg/apache/hadoop/hbase/client/Scan;
      77: pop
      78: aload         4
      80: sipush        256
      83: invokevirtual #36                 // Method org/apache/hadoop/hbase/client/Scan.setBatch:(I)Lorg/apache/hadoop/hbase/client/Scan;
      86: pop
      87: aload_0
      88: getfield      #25                 // Field r:Lorg/apache/hadoop/hbase/regionserver/HRegion;
      91: aload         4
      93: invokevirtual #37                 // Method org/apache/hadoop/hbase/regionserver/HRegion.getScanner:(Lorg/apache/hadoop/hbase/client/Scan;)Lorg/apache/hadoop/hbase/regionserver/HRegion$RegionScannerImpl;
      96: astore        5
      98: iconst_0
      99: istore        6
     101: iconst_0
     102: istore        7
     104: aload         5
     106: aload_3
     107: invokeinterface #38,  2           // InterfaceMethod org/apache/hadoop/hbase/regionserver/InternalScanner.next:(Ljava/util/List;)Z
     112: istore        8
     114: iinc          7, 1
     117: getstatic     #39                 // Field LOG:Lorg/slf4j/Logger;
     120: new           #2                  // class java/lang/StringBuilder
     123: dup
     124: invokespecial #3                  // Method java/lang/StringBuilder."<init>":()V
     127: ldc           #40                 // String iteration #
     129: invokevirtual #5                  // Method java/lang/StringBuilder.append:(Ljava/lang/String;)Ljava/lang/StringBuilder;
     132: iload         7
     134: invokevirtual #41                 // Method java/lang/StringBuilder.append:(I)Ljava/lang/StringBuilder;
     137: ldc           #42                 // String , results.size=
     139: invokevirtual #5                  // Method java/lang/StringBuilder.append:(Ljava/lang/String;)Ljava/lang/StringBuilder;
     142: aload_3
     143: invokeinterface #43,  1           // InterfaceMethod java/util/List.size:()I
     148: invokevirtual #41                 // Method java/lang/StringBuilder.append:(I)Ljava/lang/StringBuilder;
     151: invokevirtual #7                  // Method java/lang/StringBuilder.toString:()Ljava/lang/String;
     154: invokeinterface #44,  2           // InterfaceMethod org/slf4j/Logger.info:(Ljava/lang/String;)V
     159: aload_3
     160: invokeinterface #43,  1           // InterfaceMethod java/util/List.size:()I
     165: sipush        256
     168: if_icmpgt     175
     171: iconst_1
     172: goto          176
     175: iconst_0
     176: invokestatic  #45                 // Method assertTrue:(Z)V
     179: iload         6
     181: aload_3
     182: invokeinterface #43,  1           // InterfaceMethod java/util/List.size:()I
     187: iadd
     188: istore        6
     190: aload_3
     191: invokeinterface #43,  1           // InterfaceMethod java/util/List.size:()I
     196: ifle          260
     199: aload_3
     200: iconst_0
     201: invokeinterface #46,  2           // InterfaceMethod java/util/List.get:(I)Ljava/lang/Object;
     206: checkcast     #47                 // class org/apache/hadoop/hbase/Cell
     209: invokestatic  #48                 // Method org/apache/hadoop/hbase/CellUtil.cloneRow:(Lorg/apache/hadoop/hbase/Cell;)[B
     212: astore        9
     214: aload_3
     215: invokeinterface #49,  1           // InterfaceMethod java/util/List.iterator:()Ljava/util/Iterator;
     220: astore        10
     222: aload         10
     224: invokeinterface #50,  1           // InterfaceMethod java/util/Iterator.hasNext:()Z
     229: ifeq          260
     232: aload         10
     234: invokeinterface #51,  1           // InterfaceMethod java/util/Iterator.next:()Ljava/lang/Object;
     239: checkcast     #47                 // class org/apache/hadoop/hbase/Cell
     242: astore        11
     244: aload         9
     246: aload         11
     248: invokestatic  #48                 // Method org/apache/hadoop/hbase/CellUtil.cloneRow:(Lorg/apache/hadoop/hbase/Cell;)[B
     251: invokestatic  #52                 // Method org/apache/hadoop/hbase/util/Bytes.equals:([B[B)Z
     254: invokestatic  #45                 // Method assertTrue:(Z)V
     257: goto          222
     260: aload_3
     261: invokeinterface #53,  1           // InterfaceMethod java/util/List.clear:()V
     266: aload         5
     268: checkcast     #54                 // class org/apache/hadoop/hbase/regionserver/HRegion$RegionScannerImpl
     271: getfield      #55                 // Field org/apache/hadoop/hbase/regionserver/HRegion$RegionScannerImpl.storeHeap:Lorg/apache/hadoop/hbase/regionserver/KeyValueHeap;
     274: invokevirtual #56                 // Method org/apache/hadoop/hbase/regionserver/KeyValueHeap.getHeap:()Ljava/util/PriorityQueue;
     277: invokevirtual #57                 // Method java/util/PriorityQueue.iterator:()Ljava/util/Iterator;
     280: astore        9
     282: aload         9
     284: invokeinterface #50,  1           // InterfaceMethod java/util/Iterator.hasNext:()Z
     289: ifeq          318
     292: aload         9
     294: invokeinterface #51,  1           // InterfaceMethod java/util/Iterator.next:()Ljava/lang/Object;
     299: checkcast     #58                 // class org/apache/hadoop/hbase/regionserver/StoreScanner
     302: astore        10
     304: aload         10
     306: getstatic     #59                 // Field java/util/Collections.EMPTY_LIST:Ljava/util/List;
     309: getstatic     #59                 // Field java/util/Collections.EMPTY_LIST:Ljava/util/List;
     312: invokevirtual #60                 // Method org/apache/hadoop/hbase/regionserver/StoreScanner.updateReaders:(Ljava/util/List;Ljava/util/List;)V
     315: goto          282
     318: iload         8
     320: ifne          104
     323: getstatic     #39                 // Field LOG:Lorg/slf4j/Logger;
     326: new           #2                  // class java/lang/StringBuilder
     329: dup
     330: invokespecial #3                  // Method java/lang/StringBuilder."<init>":()V
     333: ldc           #61                 // String inserted
     335: invokevirtual #5                  // Method java/lang/StringBuilder.append:(Ljava/lang/String;)Ljava/lang/StringBuilder;
     338: iload_2
     339: invokevirtual #41                 // Method java/lang/StringBuilder.append:(I)Ljava/lang/StringBuilder;
     342: ldc           #62                 // String , scanned
     344: invokevirtual #5                  // Method java/lang/StringBuilder.append:(Ljava/lang/String;)Ljava/lang/StringBuilder;
     347: iload         6
     349: invokevirtual #41                 // Method java/lang/StringBuilder.append:(I)Ljava/lang/StringBuilder;
     352: invokevirtual #7                  // Method java/lang/StringBuilder.toString:()Ljava/lang/String;
     355: invokeinterface #44,  2           // InterfaceMethod org/slf4j/Logger.info:(Ljava/lang/String;)V
     360: iload         6
     362: iload_2
     363: invokestatic  #63                 // Method assertEquals:(II)V
     366: aload         5
     368: invokeinterface #64,  1           // InterfaceMethod org/apache/hadoop/hbase/regionserver/InternalScanner.close:()V
     373: aload_0
     374: getfield      #25                 // Field r:Lorg/apache/hadoop/hbase/regionserver/HRegion;
     377: invokestatic  #65                 // Method org/apache/hadoop/hbase/HBaseTestingUtility.closeRegionAndWAL:(Lorg/apache/hadoop/hbase/regionserver/HRegion;)V
     380: goto          395
     383: astore        12
     385: aload_0
     386: getfield      #25                 // Field r:Lorg/apache/hadoop/hbase/regionserver/HRegion;
     389: invokestatic  #65                 // Method org/apache/hadoop/hbase/HBaseTestingUtility.closeRegionAndWAL:(Lorg/apache/hadoop/hbase/regionserver/HRegion;)V
     392: aload         12
     394: athrow
     395: return
    Exception table:
       from    to  target type
           4   373   383   any
         383   385   383   any

  static {};
    Code:
       0: ldc           #66                 // class org/apache/hadoop/hbase/regionserver/TestWideScanner
       2: invokestatic  #67                 // Method org/apache/hadoop/hbase/HBaseClassTestRule.forClass:(Ljava/lang/Class;)Lorg/apache/hadoop/hbase/HBaseClassTestRule;
       5: putstatic     #68                 // Field CLASS_RULE:Lorg/apache/hadoop/hbase/HBaseClassTestRule;
       8: ldc           #66                 // class org/apache/hadoop/hbase/regionserver/TestWideScanner
      10: invokestatic  #69                 // Method org/slf4j/LoggerFactory.getLogger:(Ljava/lang/Class;)Lorg/slf4j/Logger;
      13: putstatic     #39                 // Field LOG:Lorg/slf4j/Logger;
      16: ldc           #70                 // String A
      18: invokestatic  #8                  // Method org/apache/hadoop/hbase/util/Bytes.toBytes:(Ljava/lang/String;)[B
      21: putstatic     #31                 // Field A:[B
      24: ldc           #71                 // String B
      26: invokestatic  #8                  // Method org/apache/hadoop/hbase/util/Bytes.toBytes:(Ljava/lang/String;)[B
      29: putstatic     #33                 // Field B:[B
      32: ldc           #72                 // String C
      34: invokestatic  #8                  // Method org/apache/hadoop/hbase/util/Bytes.toBytes:(Ljava/lang/String;)[B
      37: putstatic     #34                 // Field C:[B
      40: iconst_3
      41: anewarray     #73                 // class "[B"
      44: dup
      45: iconst_0
      46: getstatic     #31                 // Field A:[B
      49: aastore
      50: dup
      51: iconst_1
      52: getstatic     #33                 // Field B:[B
      55: aastore
      56: dup
      57: iconst_2
      58: getstatic     #34                 // Field C:[B
      61: aastore
      62: putstatic     #18                 // Field COLUMNS:[[B
      65: new           #74                 // class java/util/Random
      68: dup
      69: invokespecial #75                 // Method java/util/Random."<init>":()V
      72: putstatic     #19                 // Field rng:Ljava/util/Random;
      75: new           #76                 // class org/apache/hadoop/hbase/HTableDescriptor
      78: dup
      79: ldc           #77                 // String testwidescan
      81: invokestatic  #78                 // Method org/apache/hadoop/hbase/TableName.valueOf:(Ljava/lang/String;)Lorg/apache/hadoop/hbase/TableName;
      84: invokespecial #79                 // Method org/apache/hadoop/hbase/HTableDescriptor."<init>":(Lorg/apache/hadoop/hbase/TableName;)V
      87: putstatic     #23                 // Field TESTTABLEDESC:Lorg/apache/hadoop/hbase/HTableDescriptor;
      90: iconst_3
      91: anewarray     #73                 // class "[B"
      94: dup
      95: iconst_0
      96: getstatic     #31                 // Field A:[B
      99: aastore
     100: dup
     101: iconst_1
     102: getstatic     #33                 // Field B:[B
     105: aastore
     106: dup
     107: iconst_2
     108: getstatic     #34                 // Field C:[B
     111: aastore
     112: astore_0
     113: aload_0
     114: arraylength
     115: istore_1
     116: iconst_0
     117: istore_2
     118: iload_2
     119: iload_1
     120: if_icmpge     159
     123: aload_0
     124: iload_2
     125: aaload
     126: astore_3
     127: getstatic     #23                 // Field TESTTABLEDESC:Lorg/apache/hadoop/hbase/HTableDescriptor;
     130: new           #80                 // class org/apache/hadoop/hbase/HColumnDescriptor
     133: dup
     134: aload_3
     135: invokespecial #81                 // Method org/apache/hadoop/hbase/HColumnDescriptor."<init>":([B)V
     138: bipush        100
     140: invokevirtual #82                 // Method org/apache/hadoop/hbase/HColumnDescriptor.setMaxVersions:(I)Lorg/apache/hadoop/hbase/HColumnDescriptor;
     143: sipush        8192
     146: invokevirtual #83                 // Method org/apache/hadoop/hbase/HColumnDescriptor.setBlocksize:(I)Lorg/apache/hadoop/hbase/HColumnDescriptor;
     149: invokevirtual #84                 // Method org/apache/hadoop/hbase/HTableDescriptor.addFamily:(Lorg/apache/hadoop/hbase/HColumnDescriptor;)Lorg/apache/hadoop/hbase/HTableDescriptor;
     152: pop
     153: iinc          2, 1
     156: goto          118
     159: return
}
