Compiled from "TestCatalogJanitor.java"
public class org.apache.hadoop.hbase.master.TestCatalogJanitor {
  public static final org.apache.hadoop.hbase.HBaseClassTestRule CLASS_RULE;

  public final org.junit.rules.TestName name;

  public org.apache.hadoop.hbase.master.TestCatalogJanitor();
    Code:
       0: aload_0
       1: invokespecial #1                  // Method java/lang/Object."<init>":()V
       4: aload_0
       5: new           #2                  // class org/junit/rules/TestName
       8: dup
       9: invokespecial #3                  // Method org/junit/rules/TestName."<init>":()V
      12: putfield      #4                  // Field name:Lorg/junit/rules/TestName;
      15: return

  public static void beforeClass() throws java.lang.Exception;
    Code:
       0: ldc           #6                  // int 2097152
       2: iconst_0
       3: lconst_0
       4: fconst_0
       5: fconst_0
       6: aconst_null
       7: invokestatic  #7                  // Method org/apache/hadoop/hbase/regionserver/ChunkCreator.initialize:(IZJFFLorg/apache/hadoop/hbase/regionserver/HeapMemoryManager;)Lorg/apache/hadoop/hbase/regionserver/ChunkCreator;
      10: pop
      11: return

  public void setup() throws java.io.IOException, org.apache.zookeeper.KeeperException;
    Code:
       0: aload_0
       1: getstatic     #8                  // Field HTU:Lorg/apache/hadoop/hbase/HBaseTestingUtility;
       4: aload_0
       5: getfield      #4                  // Field name:Lorg/junit/rules/TestName;
       8: invokevirtual #9                  // Method org/junit/rules/TestName.getMethodName:()Ljava/lang/String;
      11: invokespecial #10                 // Method setRootDirAndCleanIt:(Lorg/apache/hadoop/hbase/HBaseTestingUtility;Ljava/lang/String;)Ljava/lang/String;
      14: pop
      15: new           #11                 // class java/util/concurrent/ConcurrentSkipListMap
      18: dup
      19: invokespecial #12                 // Method java/util/concurrent/ConcurrentSkipListMap."<init>":()V
      22: astore_1
      23: aload_0
      24: new           #13                 // class org/apache/hadoop/hbase/master/assignment/MockMasterServices
      27: dup
      28: getstatic     #8                  // Field HTU:Lorg/apache/hadoop/hbase/HBaseTestingUtility;
      31: invokevirtual #14                 // Method org/apache/hadoop/hbase/HBaseTestingUtility.getConfiguration:()Lorg/apache/hadoop/conf/Configuration;
      34: aload_1
      35: invokespecial #15                 // Method org/apache/hadoop/hbase/master/assignment/MockMasterServices."<init>":(Lorg/apache/hadoop/conf/Configuration;Ljava/util/NavigableMap;)V
      38: putfield      #16                 // Field masterServices:Lorg/apache/hadoop/hbase/master/assignment/MockMasterServices;
      41: aload_0
      42: getfield      #16                 // Field masterServices:Lorg/apache/hadoop/hbase/master/assignment/MockMasterServices;
      45: bipush        10
      47: aconst_null
      48: invokevirtual #17                 // Method org/apache/hadoop/hbase/master/assignment/MockMasterServices.start:(ILorg/apache/hadoop/hbase/master/procedure/RSProcedureDispatcher;)V
      51: aload_0
      52: new           #18                 // class org/apache/hadoop/hbase/master/CatalogJanitor
      55: dup
      56: aload_0
      57: getfield      #16                 // Field masterServices:Lorg/apache/hadoop/hbase/master/assignment/MockMasterServices;
      60: invokespecial #19                 // Method org/apache/hadoop/hbase/master/CatalogJanitor."<init>":(Lorg/apache/hadoop/hbase/master/MasterServices;)V
      63: putfield      #20                 // Field janitor:Lorg/apache/hadoop/hbase/master/CatalogJanitor;
      66: return

  public void teardown();
    Code:
       0: aload_0
       1: getfield      #20                 // Field janitor:Lorg/apache/hadoop/hbase/master/CatalogJanitor;
       4: iconst_1
       5: invokevirtual #21                 // Method org/apache/hadoop/hbase/master/CatalogJanitor.cancel:(Z)V
       8: aload_0
       9: getfield      #16                 // Field masterServices:Lorg/apache/hadoop/hbase/master/assignment/MockMasterServices;
      12: ldc           #22                 // String DONE
      14: invokevirtual #23                 // Method org/apache/hadoop/hbase/master/assignment/MockMasterServices.stop:(Ljava/lang/String;)V
      17: return

  public void testCleanParent() throws java.io.IOException, java.lang.InterruptedException;
    Code:
       0: aload_0
       1: invokespecial #24                 // Method createTableDescriptorForCurrentMethod:()Lorg/apache/hadoop/hbase/client/TableDescriptor;
       4: astore_1
       5: new           #25                 // class org/apache/hadoop/hbase/HRegionInfo
       8: dup
       9: aload_1
      10: invokeinterface #26,  1           // InterfaceMethod org/apache/hadoop/hbase/client/TableDescriptor.getTableName:()Lorg/apache/hadoop/hbase/TableName;
      15: ldc           #27                 // String aaa
      17: invokestatic  #28                 // Method org/apache/hadoop/hbase/util/Bytes.toBytes:(Ljava/lang/String;)[B
      20: ldc           #29                 // String eee
      22: invokestatic  #28                 // Method org/apache/hadoop/hbase/util/Bytes.toBytes:(Ljava/lang/String;)[B
      25: invokespecial #30                 // Method org/apache/hadoop/hbase/HRegionInfo."<init>":(Lorg/apache/hadoop/hbase/TableName;[B[B)V
      28: astore_2
      29: new           #25                 // class org/apache/hadoop/hbase/HRegionInfo
      32: dup
      33: aload_1
      34: invokeinterface #26,  1           // InterfaceMethod org/apache/hadoop/hbase/client/TableDescriptor.getTableName:()Lorg/apache/hadoop/hbase/TableName;
      39: ldc           #27                 // String aaa
      41: invokestatic  #28                 // Method org/apache/hadoop/hbase/util/Bytes.toBytes:(Ljava/lang/String;)[B
      44: ldc           #31                 // String ccc
      46: invokestatic  #28                 // Method org/apache/hadoop/hbase/util/Bytes.toBytes:(Ljava/lang/String;)[B
      49: invokespecial #30                 // Method org/apache/hadoop/hbase/HRegionInfo."<init>":(Lorg/apache/hadoop/hbase/TableName;[B[B)V
      52: astore_3
      53: new           #25                 // class org/apache/hadoop/hbase/HRegionInfo
      56: dup
      57: aload_1
      58: invokeinterface #26,  1           // InterfaceMethod org/apache/hadoop/hbase/client/TableDescriptor.getTableName:()Lorg/apache/hadoop/hbase/TableName;
      63: ldc           #31                 // String ccc
      65: invokestatic  #28                 // Method org/apache/hadoop/hbase/util/Bytes.toBytes:(Ljava/lang/String;)[B
      68: ldc           #29                 // String eee
      70: invokestatic  #28                 // Method org/apache/hadoop/hbase/util/Bytes.toBytes:(Ljava/lang/String;)[B
      73: invokespecial #30                 // Method org/apache/hadoop/hbase/HRegionInfo."<init>":(Lorg/apache/hadoop/hbase/TableName;[B[B)V
      76: astore        4
      78: aload_0
      79: aload_2
      80: aload_3
      81: aload         4
      83: invokespecial #32                 // Method createResult:(Lorg/apache/hadoop/hbase/HRegionInfo;Lorg/apache/hadoop/hbase/HRegionInfo;Lorg/apache/hadoop/hbase/HRegionInfo;)Lorg/apache/hadoop/hbase/client/Result;
      86: astore        5
      88: aload_0
      89: getfield      #16                 // Field masterServices:Lorg/apache/hadoop/hbase/master/assignment/MockMasterServices;
      92: invokevirtual #33                 // Method org/apache/hadoop/hbase/master/assignment/MockMasterServices.getMasterFileSystem:()Lorg/apache/hadoop/hbase/master/MasterFileSystem;
      95: invokevirtual #34                 // Method org/apache/hadoop/hbase/master/MasterFileSystem.getRootDir:()Lorg/apache/hadoop/fs/Path;
      98: astore        6
     100: aload         6
     102: aload_1
     103: invokeinterface #26,  1           // InterfaceMethod org/apache/hadoop/hbase/client/TableDescriptor.getTableName:()Lorg/apache/hadoop/hbase/TableName;
     108: invokestatic  #35                 // Method org/apache/hadoop/hbase/util/FSUtils.getTableDir:(Lorg/apache/hadoop/fs/Path;Lorg/apache/hadoop/hbase/TableName;)Lorg/apache/hadoop/fs/Path;
     111: astore        7
     113: new           #36                 // class org/apache/hadoop/fs/Path
     116: dup
     117: aload         7
     119: aload_2
     120: invokevirtual #37                 // Method org/apache/hadoop/hbase/HRegionInfo.getEncodedName:()Ljava/lang/String;
     123: invokespecial #38                 // Method org/apache/hadoop/fs/Path."<init>":(Lorg/apache/hadoop/fs/Path;Ljava/lang/String;)V
     126: astore        8
     128: aload         7
     130: aload_3
     131: aload_1
     132: invokeinterface #39,  1           // InterfaceMethod org/apache/hadoop/hbase/client/TableDescriptor.getColumnFamilies:()[Lorg/apache/hadoop/hbase/client/ColumnFamilyDescriptor;
     137: iconst_0
     138: aaload
     139: invokeinterface #40,  1           // InterfaceMethod org/apache/hadoop/hbase/client/ColumnFamilyDescriptor.getName:()[B
     144: invokestatic  #41                 // Method org/apache/hadoop/hbase/regionserver/HStore.getStoreHomedir:(Lorg/apache/hadoop/fs/Path;Lorg/apache/hadoop/hbase/client/RegionInfo;[B)Lorg/apache/hadoop/fs/Path;
     147: astore        9
     149: ldc           #31                 // String ccc
     151: invokestatic  #28                 // Method org/apache/hadoop/hbase/util/Bytes.toBytes:(Ljava/lang/String;)[B
     154: invokestatic  #42                 // Method org/apache/hadoop/hbase/io/Reference.createTopReference:([B)Lorg/apache/hadoop/hbase/io/Reference;
     157: astore        10
     159: invokestatic  #43                 // Method java/lang/System.currentTimeMillis:()J
     162: lstore        11
     164: new           #36                 // class org/apache/hadoop/fs/Path
     167: dup
     168: aload         9
     170: new           #44                 // class java/lang/StringBuilder
     173: dup
     174: invokespecial #45                 // Method java/lang/StringBuilder."<init>":()V
     177: lload         11
     179: invokestatic  #46                 // Method java/lang/Long.toString:(J)Ljava/lang/String;
     182: invokevirtual #47                 // Method java/lang/StringBuilder.append:(Ljava/lang/String;)Ljava/lang/StringBuilder;
     185: ldc           #48                 // String .
     187: invokevirtual #47                 // Method java/lang/StringBuilder.append:(Ljava/lang/String;)Ljava/lang/StringBuilder;
     190: aload_2
     191: invokevirtual #37                 // Method org/apache/hadoop/hbase/HRegionInfo.getEncodedName:()Ljava/lang/String;
     194: invokevirtual #47                 // Method java/lang/StringBuilder.append:(Ljava/lang/String;)Ljava/lang/StringBuilder;
     197: invokevirtual #49                 // Method java/lang/StringBuilder.toString:()Ljava/lang/String;
     200: invokespecial #38                 // Method org/apache/hadoop/fs/Path."<init>":(Lorg/apache/hadoop/fs/Path;Ljava/lang/String;)V
     203: astore        13
     205: aload_0
     206: getfield      #16                 // Field masterServices:Lorg/apache/hadoop/hbase/master/assignment/MockMasterServices;
     209: invokevirtual #33                 // Method org/apache/hadoop/hbase/master/assignment/MockMasterServices.getMasterFileSystem:()Lorg/apache/hadoop/hbase/master/MasterFileSystem;
     212: invokevirtual #50                 // Method org/apache/hadoop/hbase/master/MasterFileSystem.getFileSystem:()Lorg/apache/hadoop/fs/FileSystem;
     215: astore        14
     217: aload         10
     219: aload         14
     221: aload         13
     223: invokevirtual #51                 // Method org/apache/hadoop/hbase/io/Reference.write:(Lorg/apache/hadoop/fs/FileSystem;Lorg/apache/hadoop/fs/Path;)Lorg/apache/hadoop/fs/Path;
     226: astore        15
     228: aload         14
     230: aload         15
     232: invokevirtual #52                 // Method org/apache/hadoop/fs/FileSystem.exists:(Lorg/apache/hadoop/fs/Path;)Z
     235: invokestatic  #53                 // Method org/junit/Assert.assertTrue:(Z)V
     238: getstatic     #54                 // Field LOG:Lorg/slf4j/Logger;
     241: new           #44                 // class java/lang/StringBuilder
     244: dup
     245: invokespecial #45                 // Method java/lang/StringBuilder."<init>":()V
     248: ldc           #55                 // String Created reference
     250: invokevirtual #47                 // Method java/lang/StringBuilder.append:(Ljava/lang/String;)Ljava/lang/StringBuilder;
     253: aload         15
     255: invokevirtual #56                 // Method java/lang/StringBuilder.append:(Ljava/lang/Object;)Ljava/lang/StringBuilder;
     258: invokevirtual #49                 // Method java/lang/StringBuilder.toString:()Ljava/lang/String;
     261: invokeinterface #57,  2           // InterfaceMethod org/slf4j/Logger.info:(Ljava/lang/String;)V
     266: aload         14
     268: aload         8
     270: invokevirtual #58                 // Method org/apache/hadoop/fs/FileSystem.mkdirs:(Lorg/apache/hadoop/fs/Path;)Z
     273: pop
     274: aload_0
     275: getfield      #20                 // Field janitor:Lorg/apache/hadoop/hbase/master/CatalogJanitor;
     278: aload_2
     279: aload         5
     281: invokevirtual #59                 // Method org/apache/hadoop/hbase/master/CatalogJanitor.cleanParent:(Lorg/apache/hadoop/hbase/client/RegionInfo;Lorg/apache/hadoop/hbase/client/Result;)Z
     284: invokestatic  #60                 // Method org/junit/Assert.assertFalse:(Z)V
     287: aload_0
     288: getfield      #16                 // Field masterServices:Lorg/apache/hadoop/hbase/master/assignment/MockMasterServices;
     291: invokevirtual #61                 // Method org/apache/hadoop/hbase/master/assignment/MockMasterServices.getMasterProcedureExecutor:()Lorg/apache/hadoop/hbase/procedure2/ProcedureExecutor;
     294: invokestatic  #62                 // Method org/apache/hadoop/hbase/procedure2/ProcedureTestingUtility.waitAllProcedures:(Lorg/apache/hadoop/hbase/procedure2/ProcedureExecutor;)V
     297: aload         14
     299: aload         8
     301: invokevirtual #52                 // Method org/apache/hadoop/fs/FileSystem.exists:(Lorg/apache/hadoop/fs/Path;)Z
     304: invokestatic  #53                 // Method org/junit/Assert.assertTrue:(Z)V
     307: aload         14
     309: aload         13
     311: iconst_1
     312: invokevirtual #63                 // Method org/apache/hadoop/fs/FileSystem.delete:(Lorg/apache/hadoop/fs/Path;Z)Z
     315: invokestatic  #53                 // Method org/junit/Assert.assertTrue:(Z)V
     318: aload_0
     319: getfield      #20                 // Field janitor:Lorg/apache/hadoop/hbase/master/CatalogJanitor;
     322: aload_2
     323: aload         5
     325: invokevirtual #59                 // Method org/apache/hadoop/hbase/master/CatalogJanitor.cleanParent:(Lorg/apache/hadoop/hbase/client/RegionInfo;Lorg/apache/hadoop/hbase/client/Result;)Z
     328: invokestatic  #53                 // Method org/junit/Assert.assertTrue:(Z)V
     331: aload_0
     332: getfield      #16                 // Field masterServices:Lorg/apache/hadoop/hbase/master/assignment/MockMasterServices;
     335: invokevirtual #61                 // Method org/apache/hadoop/hbase/master/assignment/MockMasterServices.getMasterProcedureExecutor:()Lorg/apache/hadoop/hbase/procedure2/ProcedureExecutor;
     338: invokestatic  #62                 // Method org/apache/hadoop/hbase/procedure2/ProcedureTestingUtility.waitAllProcedures:(Lorg/apache/hadoop/hbase/procedure2/ProcedureExecutor;)V
     341: aload         14
     343: aload         8
     345: invokevirtual #52                 // Method org/apache/hadoop/fs/FileSystem.exists:(Lorg/apache/hadoop/fs/Path;)Z
     348: ifne          355
     351: iconst_1
     352: goto          356
     355: iconst_0
     356: invokestatic  #53                 // Method org/junit/Assert.assertTrue:(Z)V
     359: return

  public void testParentCleanedEvenIfDaughterGoneFirst() throws java.io.IOException, java.lang.InterruptedException;
    Code:
       0: aload_0
       1: aload_0
       2: getfield      #4                  // Field name:Lorg/junit/rules/TestName;
       5: invokevirtual #9                  // Method org/junit/rules/TestName.getMethodName:()Ljava/lang/String;
       8: ldc           #29                 // String eee
      10: invokestatic  #28                 // Method org/apache/hadoop/hbase/util/Bytes.toBytes:(Ljava/lang/String;)[B
      13: invokespecial #64                 // Method parentWithSpecifiedEndKeyCleanedEvenIfDaughterGoneFirst:(Ljava/lang/String;[B)V
      16: return

  public void testLastParentCleanedEvenIfDaughterGoneFirst() throws java.io.IOException, java.lang.InterruptedException;
    Code:
       0: aload_0
       1: aload_0
       2: getfield      #4                  // Field name:Lorg/junit/rules/TestName;
       5: invokevirtual #9                  // Method org/junit/rules/TestName.getMethodName:()Ljava/lang/String;
       8: iconst_0
       9: newarray       byte
      11: invokespecial #64                 // Method parentWithSpecifiedEndKeyCleanedEvenIfDaughterGoneFirst:(Ljava/lang/String;[B)V
      14: return

  public void testScanDoesNotCleanRegionsWithExistingParents() throws java.lang.Exception;
    Code:
       0: aload_0
       1: invokespecial #24                 // Method createTableDescriptorForCurrentMethod:()Lorg/apache/hadoop/hbase/client/TableDescriptor;
       4: astore_1
       5: new           #25                 // class org/apache/hadoop/hbase/HRegionInfo
       8: dup
       9: aload_1
      10: invokeinterface #26,  1           // InterfaceMethod org/apache/hadoop/hbase/client/TableDescriptor.getTableName:()Lorg/apache/hadoop/hbase/TableName;
      15: ldc           #27                 // String aaa
      17: invokestatic  #28                 // Method org/apache/hadoop/hbase/util/Bytes.toBytes:(Ljava/lang/String;)[B
      20: getstatic     #93                 // Field org/apache/hadoop/hbase/HConstants.EMPTY_BYTE_ARRAY:[B
      23: iconst_1
      24: invokespecial #94                 // Method org/apache/hadoop/hbase/HRegionInfo."<init>":(Lorg/apache/hadoop/hbase/TableName;[B[BZ)V
      27: astore_2
      28: ldc2_w        #72                 // long 1001l
      31: invokestatic  #74                 // Method java/lang/Thread.sleep:(J)V
      34: new           #25                 // class org/apache/hadoop/hbase/HRegionInfo
      37: dup
      38: aload_1
      39: invokeinterface #26,  1           // InterfaceMethod org/apache/hadoop/hbase/client/TableDescriptor.getTableName:()Lorg/apache/hadoop/hbase/TableName;
      44: ldc           #27                 // String aaa
      46: invokestatic  #28                 // Method org/apache/hadoop/hbase/util/Bytes.toBytes:(Ljava/lang/String;)[B
      49: ldc           #31                 // String ccc
      51: invokestatic  #28                 // Method org/apache/hadoop/hbase/util/Bytes.toBytes:(Ljava/lang/String;)[B
      54: iconst_1
      55: invokespecial #94                 // Method org/apache/hadoop/hbase/HRegionInfo."<init>":(Lorg/apache/hadoop/hbase/TableName;[B[BZ)V
      58: astore_3
      59: ldc2_w        #72                 // long 1001l
      62: invokestatic  #74                 // Method java/lang/Thread.sleep:(J)V
      65: new           #25                 // class org/apache/hadoop/hbase/HRegionInfo
      68: dup
      69: aload_1
      70: invokeinterface #26,  1           // InterfaceMethod org/apache/hadoop/hbase/client/TableDescriptor.getTableName:()Lorg/apache/hadoop/hbase/TableName;
      75: ldc           #27                 // String aaa
      77: invokestatic  #28                 // Method org/apache/hadoop/hbase/util/Bytes.toBytes:(Ljava/lang/String;)[B
      80: ldc           #75                 // String bbb
      82: invokestatic  #28                 // Method org/apache/hadoop/hbase/util/Bytes.toBytes:(Ljava/lang/String;)[B
      85: iconst_0
      86: invokespecial #94                 // Method org/apache/hadoop/hbase/HRegionInfo."<init>":(Lorg/apache/hadoop/hbase/TableName;[B[BZ)V
      89: astore        4
      91: new           #25                 // class org/apache/hadoop/hbase/HRegionInfo
      94: dup
      95: aload_1
      96: invokeinterface #26,  1           // InterfaceMethod org/apache/hadoop/hbase/client/TableDescriptor.getTableName:()Lorg/apache/hadoop/hbase/TableName;
     101: ldc           #75                 // String bbb
     103: invokestatic  #28                 // Method org/apache/hadoop/hbase/util/Bytes.toBytes:(Ljava/lang/String;)[B
     106: ldc           #31                 // String ccc
     108: invokestatic  #28                 // Method org/apache/hadoop/hbase/util/Bytes.toBytes:(Ljava/lang/String;)[B
     111: iconst_0
     112: invokespecial #94                 // Method org/apache/hadoop/hbase/HRegionInfo."<init>":(Lorg/apache/hadoop/hbase/TableName;[B[BZ)V
     115: astore        5
     117: new           #25                 // class org/apache/hadoop/hbase/HRegionInfo
     120: dup
     121: aload_1
     122: invokeinterface #26,  1           // InterfaceMethod org/apache/hadoop/hbase/client/TableDescriptor.getTableName:()Lorg/apache/hadoop/hbase/TableName;
     127: ldc           #31                 // String ccc
     129: invokestatic  #28                 // Method org/apache/hadoop/hbase/util/Bytes.toBytes:(Ljava/lang/String;)[B
     132: getstatic     #93                 // Field org/apache/hadoop/hbase/HConstants.EMPTY_BYTE_ARRAY:[B
     135: invokespecial #30                 // Method org/apache/hadoop/hbase/HRegionInfo."<init>":(Lorg/apache/hadoop/hbase/TableName;[B[B)V
     138: astore        6
     140: ldc2_w        #72                 // long 1001l
     143: invokestatic  #74                 // Method java/lang/Thread.sleep:(J)V
     146: new           #77                 // class java/util/TreeMap
     149: dup
     150: new           #78                 // class org/apache/hadoop/hbase/master/CatalogJanitor$SplitParentFirstComparator
     153: dup
     154: invokespecial #79                 // Method org/apache/hadoop/hbase/master/CatalogJanitor$SplitParentFirstComparator."<init>":()V
     157: invokespecial #80                 // Method java/util/TreeMap."<init>":(Ljava/util/Comparator;)V
     160: astore        7
     162: aload         7
     164: aload_2
     165: aload_0
     166: aload_2
     167: aload_3
     168: aload         6
     170: invokespecial #32                 // Method createResult:(Lorg/apache/hadoop/hbase/HRegionInfo;Lorg/apache/hadoop/hbase/HRegionInfo;Lorg/apache/hadoop/hbase/HRegionInfo;)Lorg/apache/hadoop/hbase/client/Result;
     173: invokeinterface #95,  3           // InterfaceMethod java/util/Map.put:(Ljava/lang/Object;Ljava/lang/Object;)Ljava/lang/Object;
     178: pop
     179: aload_3
     180: iconst_1
     181: invokevirtual #96                 // Method org/apache/hadoop/hbase/HRegionInfo.setOffline:(Z)V
     184: aload         7
     186: aload_3
     187: aload_0
     188: aload_3
     189: aload         4
     191: aload         5
     193: invokespecial #32                 // Method createResult:(Lorg/apache/hadoop/hbase/HRegionInfo;Lorg/apache/hadoop/hbase/HRegionInfo;Lorg/apache/hadoop/hbase/HRegionInfo;)Lorg/apache/hadoop/hbase/client/Result;
     196: invokeinterface #95,  3           // InterfaceMethod java/util/Map.put:(Ljava/lang/Object;Ljava/lang/Object;)Ljava/lang/Object;
     201: pop
     202: new           #77                 // class java/util/TreeMap
     205: dup
     206: invokespecial #97                 // Method java/util/TreeMap."<init>":()V
     209: astore        8
     211: aload_0
     212: getfield      #20                 // Field janitor:Lorg/apache/hadoop/hbase/master/CatalogJanitor;
     215: invokestatic  #98                 // Method org/mockito/Mockito.spy:(Ljava/lang/Object;)Ljava/lang/Object;
     218: checkcast     #18                 // class org/apache/hadoop/hbase/master/CatalogJanitor
     221: astore        9
     223: new           #99                 // class org/apache/hadoop/hbase/util/Triple
     226: dup
     227: bipush        10
     229: invokestatic  #100                // Method java/lang/Integer.valueOf:(I)Ljava/lang/Integer;
     232: aload         8
     234: aload         7
     236: invokespecial #101                // Method org/apache/hadoop/hbase/util/Triple."<init>":(Ljava/lang/Object;Ljava/lang/Object;Ljava/lang/Object;)V
     239: invokestatic  #102                // Method org/mockito/Mockito.doReturn:(Ljava/lang/Object;)Lorg/mockito/stubbing/Stubber;
     242: aload         9
     244: invokeinterface #103,  2          // InterfaceMethod org/mockito/stubbing/Stubber.when:(Ljava/lang/Object;)Ljava/lang/Object;
     249: checkcast     #18                 // class org/apache/hadoop/hbase/master/CatalogJanitor
     252: invokevirtual #104                // Method org/apache/hadoop/hbase/master/CatalogJanitor.getMergedRegionsAndSplitParents:()Lorg/apache/hadoop/hbase/util/Triple;
     255: pop
     256: getstatic     #54                 // Field LOG:Lorg/slf4j/Logger;
     259: new           #44                 // class java/lang/StringBuilder
     262: dup
     263: invokespecial #45                 // Method java/lang/StringBuilder."<init>":()V
     266: ldc           #105                // String parent=
     268: invokevirtual #47                 // Method java/lang/StringBuilder.append:(Ljava/lang/String;)Ljava/lang/StringBuilder;
     271: aload_2
     272: invokevirtual #106                // Method org/apache/hadoop/hbase/HRegionInfo.getShortNameToLog:()Ljava/lang/String;
     275: invokevirtual #47                 // Method java/lang/StringBuilder.append:(Ljava/lang/String;)Ljava/lang/StringBuilder;
     278: ldc           #107                // String , splita=
     280: invokevirtual #47                 // Method java/lang/StringBuilder.append:(Ljava/lang/String;)Ljava/lang/StringBuilder;
     283: aload_3
     284: invokevirtual #106                // Method org/apache/hadoop/hbase/HRegionInfo.getShortNameToLog:()Ljava/lang/String;
     287: invokevirtual #47                 // Method java/lang/StringBuilder.append:(Ljava/lang/String;)Ljava/lang/StringBuilder;
     290: invokevirtual #49                 // Method java/lang/StringBuilder.toString:()Ljava/lang/String;
     293: invokeinterface #57,  2           // InterfaceMethod org/slf4j/Logger.info:(Ljava/lang/String;)V
     298: aload_0
     299: aload_0
     300: getfield      #16                 // Field masterServices:Lorg/apache/hadoop/hbase/master/assignment/MockMasterServices;
     303: aload_1
     304: aload_2
     305: aload_3
     306: ldc           #31                 // String ccc
     308: invokestatic  #28                 // Method org/apache/hadoop/hbase/util/Bytes.toBytes:(Ljava/lang/String;)[B
     311: iconst_0
     312: invokespecial #89                 // Method createReferences:(Lorg/apache/hadoop/hbase/master/MasterServices;Lorg/apache/hadoop/hbase/client/TableDescriptor;Lorg/apache/hadoop/hbase/HRegionInfo;Lorg/apache/hadoop/hbase/HRegionInfo;[BZ)Lorg/apache/hadoop/fs/Path;
     315: astore        10
     317: getstatic     #54                 // Field LOG:Lorg/slf4j/Logger;
     320: new           #44                 // class java/lang/StringBuilder
     323: dup
     324: invokespecial #45                 // Method java/lang/StringBuilder."<init>":()V
     327: ldc           #55                 // String Created reference
     329: invokevirtual #47                 // Method java/lang/StringBuilder.append:(Ljava/lang/String;)Ljava/lang/StringBuilder;
     332: aload         10
     334: invokevirtual #56                 // Method java/lang/StringBuilder.append:(Ljava/lang/Object;)Ljava/lang/StringBuilder;
     337: invokevirtual #49                 // Method java/lang/StringBuilder.toString:()Ljava/lang/String;
     340: invokeinterface #57,  2           // InterfaceMethod org/slf4j/Logger.info:(Ljava/lang/String;)V
     345: lconst_0
     346: aload         9
     348: invokevirtual #108                // Method org/apache/hadoop/hbase/master/CatalogJanitor.scan:()I
     351: i2l
     352: invokestatic  #109                // Method org/junit/Assert.assertEquals:(JJ)V
     355: getstatic     #8                  // Field HTU:Lorg/apache/hadoop/hbase/HBaseTestingUtility;
     358: invokevirtual #14                 // Method org/apache/hadoop/hbase/HBaseTestingUtility.getConfiguration:()Lorg/apache/hadoop/conf/Configuration;
     361: invokestatic  #92                 // Method org/apache/hadoop/fs/FileSystem.get:(Lorg/apache/hadoop/conf/Configuration;)Lorg/apache/hadoop/fs/FileSystem;
     364: astore        11
     366: aload         11
     368: aload         10
     370: iconst_1
     371: invokevirtual #63                 // Method org/apache/hadoop/fs/FileSystem.delete:(Lorg/apache/hadoop/fs/Path;Z)Z
     374: invokestatic  #53                 // Method org/junit/Assert.assertTrue:(Z)V
     377: ldc2_w        #110                // long 2l
     380: aload         9
     382: invokevirtual #108                // Method org/apache/hadoop/hbase/master/CatalogJanitor.scan:()I
     385: i2l
     386: invokestatic  #109                // Method org/junit/Assert.assertEquals:(JJ)V
     389: return

  public void testSplitParentFirstComparator();
    Code:
       0: new           #78                 // class org/apache/hadoop/hbase/master/CatalogJanitor$SplitParentFirstComparator
       3: dup
       4: invokespecial #79                 // Method org/apache/hadoop/hbase/master/CatalogJanitor$SplitParentFirstComparator."<init>":()V
       7: astore_1
       8: aload_0
       9: invokespecial #24                 // Method createTableDescriptorForCurrentMethod:()Lorg/apache/hadoop/hbase/client/TableDescriptor;
      12: astore_2
      13: new           #25                 // class org/apache/hadoop/hbase/HRegionInfo
      16: dup
      17: aload_2
      18: invokeinterface #26,  1           // InterfaceMethod org/apache/hadoop/hbase/client/TableDescriptor.getTableName:()Lorg/apache/hadoop/hbase/TableName;
      23: getstatic     #112                // Field org/apache/hadoop/hbase/HConstants.EMPTY_START_ROW:[B
      26: getstatic     #113                // Field org/apache/hadoop/hbase/HConstants.EMPTY_END_ROW:[B
      29: iconst_1
      30: invokespecial #94                 // Method org/apache/hadoop/hbase/HRegionInfo."<init>":(Lorg/apache/hadoop/hbase/TableName;[B[BZ)V
      33: astore_3
      34: new           #25                 // class org/apache/hadoop/hbase/HRegionInfo
      37: dup
      38: aload_2
      39: invokeinterface #26,  1           // InterfaceMethod org/apache/hadoop/hbase/client/TableDescriptor.getTableName:()Lorg/apache/hadoop/hbase/TableName;
      44: getstatic     #112                // Field org/apache/hadoop/hbase/HConstants.EMPTY_START_ROW:[B
      47: ldc           #75                 // String bbb
      49: invokestatic  #28                 // Method org/apache/hadoop/hbase/util/Bytes.toBytes:(Ljava/lang/String;)[B
      52: iconst_1
      53: invokespecial #94                 // Method org/apache/hadoop/hbase/HRegionInfo."<init>":(Lorg/apache/hadoop/hbase/TableName;[B[BZ)V
      56: astore        4
      58: new           #25                 // class org/apache/hadoop/hbase/HRegionInfo
      61: dup
      62: aload_2
      63: invokeinterface #26,  1           // InterfaceMethod org/apache/hadoop/hbase/client/TableDescriptor.getTableName:()Lorg/apache/hadoop/hbase/TableName;
      68: ldc           #75                 // String bbb
      70: invokestatic  #28                 // Method org/apache/hadoop/hbase/util/Bytes.toBytes:(Ljava/lang/String;)[B
      73: getstatic     #113                // Field org/apache/hadoop/hbase/HConstants.EMPTY_END_ROW:[B
      76: iconst_1
      77: invokespecial #94                 // Method org/apache/hadoop/hbase/HRegionInfo."<init>":(Lorg/apache/hadoop/hbase/TableName;[B[BZ)V
      80: astore        5
      82: aload_1
      83: aload_3
      84: aload_3
      85: invokevirtual #114                // Method org/apache/hadoop/hbase/master/CatalogJanitor$SplitParentFirstComparator.compare:(Lorg/apache/hadoop/hbase/client/RegionInfo;Lorg/apache/hadoop/hbase/client/RegionInfo;)I
      88: ifne          95
      91: iconst_1
      92: goto          96
      95: iconst_0
      96: invokestatic  #53                 // Method org/junit/Assert.assertTrue:(Z)V
      99: aload_1
     100: aload         4
     102: aload         4
     104: invokevirtual #114                // Method org/apache/hadoop/hbase/master/CatalogJanitor$SplitParentFirstComparator.compare:(Lorg/apache/hadoop/hbase/client/RegionInfo;Lorg/apache/hadoop/hbase/client/RegionInfo;)I
     107: ifne          114
     110: iconst_1
     111: goto          115
     114: iconst_0
     115: invokestatic  #53                 // Method org/junit/Assert.assertTrue:(Z)V
     118: aload_1
     119: aload         5
     121: aload         5
     123: invokevirtual #114                // Method org/apache/hadoop/hbase/master/CatalogJanitor$SplitParentFirstComparator.compare:(Lorg/apache/hadoop/hbase/client/RegionInfo;Lorg/apache/hadoop/hbase/client/RegionInfo;)I
     126: ifne          133
     129: iconst_1
     130: goto          134
     133: iconst_0
     134: invokestatic  #53                 // Method org/junit/Assert.assertTrue:(Z)V
     137: aload_1
     138: aload_3
     139: aload         4
     141: invokevirtual #114                // Method org/apache/hadoop/hbase/master/CatalogJanitor$SplitParentFirstComparator.compare:(Lorg/apache/hadoop/hbase/client/RegionInfo;Lorg/apache/hadoop/hbase/client/RegionInfo;)I
     144: ifge          151
     147: iconst_1
     148: goto          152
     151: iconst_0
     152: invokestatic  #53                 // Method org/junit/Assert.assertTrue:(Z)V
     155: aload_1
     156: aload_3
     157: aload         5
     159: invokevirtual #114                // Method org/apache/hadoop/hbase/master/CatalogJanitor$SplitParentFirstComparator.compare:(Lorg/apache/hadoop/hbase/client/RegionInfo;Lorg/apache/hadoop/hbase/client/RegionInfo;)I
     162: ifge          169
     165: iconst_1
     166: goto          170
     169: iconst_0
     170: invokestatic  #53                 // Method org/junit/Assert.assertTrue:(Z)V
     173: aload_1
     174: aload         4
     176: aload         5
     178: invokevirtual #114                // Method org/apache/hadoop/hbase/master/CatalogJanitor$SplitParentFirstComparator.compare:(Lorg/apache/hadoop/hbase/client/RegionInfo;Lorg/apache/hadoop/hbase/client/RegionInfo;)I
     181: ifge          188
     184: iconst_1
     185: goto          189
     188: iconst_0
     189: invokestatic  #53                 // Method org/junit/Assert.assertTrue:(Z)V
     192: new           #25                 // class org/apache/hadoop/hbase/HRegionInfo
     195: dup
     196: aload_2
     197: invokeinterface #26,  1           // InterfaceMethod org/apache/hadoop/hbase/client/TableDescriptor.getTableName:()Lorg/apache/hadoop/hbase/TableName;
     202: getstatic     #112                // Field org/apache/hadoop/hbase/HConstants.EMPTY_START_ROW:[B
     205: ldc           #27                 // String aaa
     207: invokestatic  #28                 // Method org/apache/hadoop/hbase/util/Bytes.toBytes:(Ljava/lang/String;)[B
     210: iconst_1
     211: invokespecial #94                 // Method org/apache/hadoop/hbase/HRegionInfo."<init>":(Lorg/apache/hadoop/hbase/TableName;[B[BZ)V
     214: astore        6
     216: new           #25                 // class org/apache/hadoop/hbase/HRegionInfo
     219: dup
     220: aload_2
     221: invokeinterface #26,  1           // InterfaceMethod org/apache/hadoop/hbase/client/TableDescriptor.getTableName:()Lorg/apache/hadoop/hbase/TableName;
     226: ldc           #27                 // String aaa
     228: invokestatic  #28                 // Method org/apache/hadoop/hbase/util/Bytes.toBytes:(Ljava/lang/String;)[B
     231: ldc           #75                 // String bbb
     233: invokestatic  #28                 // Method org/apache/hadoop/hbase/util/Bytes.toBytes:(Ljava/lang/String;)[B
     236: iconst_1
     237: invokespecial #94                 // Method org/apache/hadoop/hbase/HRegionInfo."<init>":(Lorg/apache/hadoop/hbase/TableName;[B[BZ)V
     240: astore        7
     242: new           #25                 // class org/apache/hadoop/hbase/HRegionInfo
     245: dup
     246: aload_2
     247: invokeinterface #26,  1           // InterfaceMethod org/apache/hadoop/hbase/client/TableDescriptor.getTableName:()Lorg/apache/hadoop/hbase/TableName;
     252: ldc           #75                 // String bbb
     254: invokestatic  #28                 // Method org/apache/hadoop/hbase/util/Bytes.toBytes:(Ljava/lang/String;)[B
     257: ldc           #76                 // String ddd
     259: invokestatic  #28                 // Method org/apache/hadoop/hbase/util/Bytes.toBytes:(Ljava/lang/String;)[B
     262: iconst_1
     263: invokespecial #94                 // Method org/apache/hadoop/hbase/HRegionInfo."<init>":(Lorg/apache/hadoop/hbase/TableName;[B[BZ)V
     266: astore        8
     268: new           #25                 // class org/apache/hadoop/hbase/HRegionInfo
     271: dup
     272: aload_2
     273: invokeinterface #26,  1           // InterfaceMethod org/apache/hadoop/hbase/client/TableDescriptor.getTableName:()Lorg/apache/hadoop/hbase/TableName;
     278: ldc           #76                 // String ddd
     280: invokestatic  #28                 // Method org/apache/hadoop/hbase/util/Bytes.toBytes:(Ljava/lang/String;)[B
     283: getstatic     #113                // Field org/apache/hadoop/hbase/HConstants.EMPTY_END_ROW:[B
     286: iconst_1
     287: invokespecial #94                 // Method org/apache/hadoop/hbase/HRegionInfo."<init>":(Lorg/apache/hadoop/hbase/TableName;[B[BZ)V
     290: astore        9
     292: aload_1
     293: aload         6
     295: aload         6
     297: invokevirtual #114                // Method org/apache/hadoop/hbase/master/CatalogJanitor$SplitParentFirstComparator.compare:(Lorg/apache/hadoop/hbase/client/RegionInfo;Lorg/apache/hadoop/hbase/client/RegionInfo;)I
     300: ifne          307
     303: iconst_1
     304: goto          308
     307: iconst_0
     308: invokestatic  #53                 // Method org/junit/Assert.assertTrue:(Z)V
     311: aload_1
     312: aload         7
     314: aload         7
     316: invokevirtual #114                // Method org/apache/hadoop/hbase/master/CatalogJanitor$SplitParentFirstComparator.compare:(Lorg/apache/hadoop/hbase/client/RegionInfo;Lorg/apache/hadoop/hbase/client/RegionInfo;)I
     319: ifne          326
     322: iconst_1
     323: goto          327
     326: iconst_0
     327: invokestatic  #53                 // Method org/junit/Assert.assertTrue:(Z)V
     330: aload_1
     331: aload_3
     332: aload         6
     334: invokevirtual #114                // Method org/apache/hadoop/hbase/master/CatalogJanitor$SplitParentFirstComparator.compare:(Lorg/apache/hadoop/hbase/client/RegionInfo;Lorg/apache/hadoop/hbase/client/RegionInfo;)I
     337: ifge          344
     340: iconst_1
     341: goto          345
     344: iconst_0
     345: invokestatic  #53                 // Method org/junit/Assert.assertTrue:(Z)V
     348: aload_1
     349: aload_3
     350: aload         7
     352: invokevirtual #114                // Method org/apache/hadoop/hbase/master/CatalogJanitor$SplitParentFirstComparator.compare:(Lorg/apache/hadoop/hbase/client/RegionInfo;Lorg/apache/hadoop/hbase/client/RegionInfo;)I
     355: ifge          362
     358: iconst_1
     359: goto          363
     362: iconst_0
     363: invokestatic  #53                 // Method org/junit/Assert.assertTrue:(Z)V
     366: aload_1
     367: aload         4
     369: aload         6
     371: invokevirtual #114                // Method org/apache/hadoop/hbase/master/CatalogJanitor$SplitParentFirstComparator.compare:(Lorg/apache/hadoop/hbase/client/RegionInfo;Lorg/apache/hadoop/hbase/client/RegionInfo;)I
     374: ifge          381
     377: iconst_1
     378: goto          382
     381: iconst_0
     382: invokestatic  #53                 // Method org/junit/Assert.assertTrue:(Z)V
     385: aload_1
     386: aload         4
     388: aload         7
     390: invokevirtual #114                // Method org/apache/hadoop/hbase/master/CatalogJanitor$SplitParentFirstComparator.compare:(Lorg/apache/hadoop/hbase/client/RegionInfo;Lorg/apache/hadoop/hbase/client/RegionInfo;)I
     393: ifge          400
     396: iconst_1
     397: goto          401
     400: iconst_0
     401: invokestatic  #53                 // Method org/junit/Assert.assertTrue:(Z)V
     404: aload_1
     405: aload         6
     407: aload         7
     409: invokevirtual #114                // Method org/apache/hadoop/hbase/master/CatalogJanitor$SplitParentFirstComparator.compare:(Lorg/apache/hadoop/hbase/client/RegionInfo;Lorg/apache/hadoop/hbase/client/RegionInfo;)I
     412: ifge          419
     415: iconst_1
     416: goto          420
     419: iconst_0
     420: invokestatic  #53                 // Method org/junit/Assert.assertTrue:(Z)V
     423: aload_1
     424: aload         8
     426: aload         8
     428: invokevirtual #114                // Method org/apache/hadoop/hbase/master/CatalogJanitor$SplitParentFirstComparator.compare:(Lorg/apache/hadoop/hbase/client/RegionInfo;Lorg/apache/hadoop/hbase/client/RegionInfo;)I
     431: ifne          438
     434: iconst_1
     435: goto          439
     438: iconst_0
     439: invokestatic  #53                 // Method org/junit/Assert.assertTrue:(Z)V
     442: aload_1
     443: aload         9
     445: aload         9
     447: invokevirtual #114                // Method org/apache/hadoop/hbase/master/CatalogJanitor$SplitParentFirstComparator.compare:(Lorg/apache/hadoop/hbase/client/RegionInfo;Lorg/apache/hadoop/hbase/client/RegionInfo;)I
     450: ifne          457
     453: iconst_1
     454: goto          458
     457: iconst_0
     458: invokestatic  #53                 // Method org/junit/Assert.assertTrue:(Z)V
     461: aload_1
     462: aload_3
     463: aload         8
     465: invokevirtual #114                // Method org/apache/hadoop/hbase/master/CatalogJanitor$SplitParentFirstComparator.compare:(Lorg/apache/hadoop/hbase/client/RegionInfo;Lorg/apache/hadoop/hbase/client/RegionInfo;)I
     468: ifge          475
     471: iconst_1
     472: goto          476
     475: iconst_0
     476: invokestatic  #53                 // Method org/junit/Assert.assertTrue:(Z)V
     479: aload_1
     480: aload_3
     481: aload         9
     483: invokevirtual #114                // Method org/apache/hadoop/hbase/master/CatalogJanitor$SplitParentFirstComparator.compare:(Lorg/apache/hadoop/hbase/client/RegionInfo;Lorg/apache/hadoop/hbase/client/RegionInfo;)I
     486: ifge          493
     489: iconst_1
     490: goto          494
     493: iconst_0
     494: invokestatic  #53                 // Method org/junit/Assert.assertTrue:(Z)V
     497: aload_1
     498: aload         5
     500: aload         8
     502: invokevirtual #114                // Method org/apache/hadoop/hbase/master/CatalogJanitor$SplitParentFirstComparator.compare:(Lorg/apache/hadoop/hbase/client/RegionInfo;Lorg/apache/hadoop/hbase/client/RegionInfo;)I
     505: ifge          512
     508: iconst_1
     509: goto          513
     512: iconst_0
     513: invokestatic  #53                 // Method org/junit/Assert.assertTrue:(Z)V
     516: aload_1
     517: aload         5
     519: aload         9
     521: invokevirtual #114                // Method org/apache/hadoop/hbase/master/CatalogJanitor$SplitParentFirstComparator.compare:(Lorg/apache/hadoop/hbase/client/RegionInfo;Lorg/apache/hadoop/hbase/client/RegionInfo;)I
     524: ifge          531
     527: iconst_1
     528: goto          532
     531: iconst_0
     532: invokestatic  #53                 // Method org/junit/Assert.assertTrue:(Z)V
     535: aload_1
     536: aload         8
     538: aload         9
     540: invokevirtual #114                // Method org/apache/hadoop/hbase/master/CatalogJanitor$SplitParentFirstComparator.compare:(Lorg/apache/hadoop/hbase/client/RegionInfo;Lorg/apache/hadoop/hbase/client/RegionInfo;)I
     543: ifge          550
     546: iconst_1
     547: goto          551
     550: iconst_0
     551: invokestatic  #53                 // Method org/junit/Assert.assertTrue:(Z)V
     554: aload_1
     555: aload         6
     557: aload         8
     559: invokevirtual #114                // Method org/apache/hadoop/hbase/master/CatalogJanitor$SplitParentFirstComparator.compare:(Lorg/apache/hadoop/hbase/client/RegionInfo;Lorg/apache/hadoop/hbase/client/RegionInfo;)I
     562: ifge          569
     565: iconst_1
     566: goto          570
     569: iconst_0
     570: invokestatic  #53                 // Method org/junit/Assert.assertTrue:(Z)V
     573: aload_1
     574: aload         6
     576: aload         9
     578: invokevirtual #114                // Method org/apache/hadoop/hbase/master/CatalogJanitor$SplitParentFirstComparator.compare:(Lorg/apache/hadoop/hbase/client/RegionInfo;Lorg/apache/hadoop/hbase/client/RegionInfo;)I
     581: ifge          588
     584: iconst_1
     585: goto          589
     588: iconst_0
     589: invokestatic  #53                 // Method org/junit/Assert.assertTrue:(Z)V
     592: aload_1
     593: aload         7
     595: aload         8
     597: invokevirtual #114                // Method org/apache/hadoop/hbase/master/CatalogJanitor$SplitParentFirstComparator.compare:(Lorg/apache/hadoop/hbase/client/RegionInfo;Lorg/apache/hadoop/hbase/client/RegionInfo;)I
     600: ifge          607
     603: iconst_1
     604: goto          608
     607: iconst_0
     608: invokestatic  #53                 // Method org/junit/Assert.assertTrue:(Z)V
     611: aload_1
     612: aload         7
     614: aload         9
     616: invokevirtual #114                // Method org/apache/hadoop/hbase/master/CatalogJanitor$SplitParentFirstComparator.compare:(Lorg/apache/hadoop/hbase/client/RegionInfo;Lorg/apache/hadoop/hbase/client/RegionInfo;)I
     619: ifge          626
     622: iconst_1
     623: goto          627
     626: iconst_0
     627: invokestatic  #53                 // Method org/junit/Assert.assertTrue:(Z)V
     630: new           #25                 // class org/apache/hadoop/hbase/HRegionInfo
     633: dup
     634: aload_2
     635: invokeinterface #26,  1           // InterfaceMethod org/apache/hadoop/hbase/client/TableDescriptor.getTableName:()Lorg/apache/hadoop/hbase/TableName;
     640: ldc           #75                 // String bbb
     642: invokestatic  #28                 // Method org/apache/hadoop/hbase/util/Bytes.toBytes:(Ljava/lang/String;)[B
     645: ldc           #31                 // String ccc
     647: invokestatic  #28                 // Method org/apache/hadoop/hbase/util/Bytes.toBytes:(Ljava/lang/String;)[B
     650: iconst_0
     651: invokespecial #94                 // Method org/apache/hadoop/hbase/HRegionInfo."<init>":(Lorg/apache/hadoop/hbase/TableName;[B[BZ)V
     654: astore        10
     656: new           #25                 // class org/apache/hadoop/hbase/HRegionInfo
     659: dup
     660: aload_2
     661: invokeinterface #26,  1           // InterfaceMethod org/apache/hadoop/hbase/client/TableDescriptor.getTableName:()Lorg/apache/hadoop/hbase/TableName;
     666: ldc           #31                 // String ccc
     668: invokestatic  #28                 // Method org/apache/hadoop/hbase/util/Bytes.toBytes:(Ljava/lang/String;)[B
     671: ldc           #76                 // String ddd
     673: invokestatic  #28                 // Method org/apache/hadoop/hbase/util/Bytes.toBytes:(Ljava/lang/String;)[B
     676: iconst_0
     677: invokespecial #94                 // Method org/apache/hadoop/hbase/HRegionInfo."<init>":(Lorg/apache/hadoop/hbase/TableName;[B[BZ)V
     680: astore        11
     682: aload_1
     683: aload         8
     685: aload         10
     687: invokevirtual #114                // Method org/apache/hadoop/hbase/master/CatalogJanitor$SplitParentFirstComparator.compare:(Lorg/apache/hadoop/hbase/client/RegionInfo;Lorg/apache/hadoop/hbase/client/RegionInfo;)I
     690: ifge          697
     693: iconst_1
     694: goto          698
     697: iconst_0
     698: invokestatic  #53                 // Method org/junit/Assert.assertTrue:(Z)V
     701: aload_1
     702: aload         8
     704: aload         11
     706: invokevirtual #114                // Method org/apache/hadoop/hbase/master/CatalogJanitor$SplitParentFirstComparator.compare:(Lorg/apache/hadoop/hbase/client/RegionInfo;Lorg/apache/hadoop/hbase/client/RegionInfo;)I
     709: ifge          716
     712: iconst_1
     713: goto          717
     716: iconst_0
     717: invokestatic  #53                 // Method org/junit/Assert.assertTrue:(Z)V
     720: aload_1
     721: aload         10
     723: aload         11
     725: invokevirtual #114                // Method org/apache/hadoop/hbase/master/CatalogJanitor$SplitParentFirstComparator.compare:(Lorg/apache/hadoop/hbase/client/RegionInfo;Lorg/apache/hadoop/hbase/client/RegionInfo;)I
     728: ifge          735
     731: iconst_1
     732: goto          736
     735: iconst_0
     736: invokestatic  #53                 // Method org/junit/Assert.assertTrue:(Z)V
     739: return

  public void testArchiveOldRegion() throws java.lang.Exception;
    Code:
       0: aload_0
       1: invokespecial #24                 // Method createTableDescriptorForCurrentMethod:()Lorg/apache/hadoop/hbase/client/TableDescriptor;
       4: astore_1
       5: new           #25                 // class org/apache/hadoop/hbase/HRegionInfo
       8: dup
       9: aload_1
      10: invokeinterface #26,  1           // InterfaceMethod org/apache/hadoop/hbase/client/TableDescriptor.getTableName:()Lorg/apache/hadoop/hbase/TableName;
      15: ldc           #27                 // String aaa
      17: invokestatic  #28                 // Method org/apache/hadoop/hbase/util/Bytes.toBytes:(Ljava/lang/String;)[B
      20: ldc           #29                 // String eee
      22: invokestatic  #28                 // Method org/apache/hadoop/hbase/util/Bytes.toBytes:(Ljava/lang/String;)[B
      25: invokespecial #30                 // Method org/apache/hadoop/hbase/HRegionInfo."<init>":(Lorg/apache/hadoop/hbase/TableName;[B[B)V
      28: astore_2
      29: new           #25                 // class org/apache/hadoop/hbase/HRegionInfo
      32: dup
      33: aload_1
      34: invokeinterface #26,  1           // InterfaceMethod org/apache/hadoop/hbase/client/TableDescriptor.getTableName:()Lorg/apache/hadoop/hbase/TableName;
      39: ldc           #27                 // String aaa
      41: invokestatic  #28                 // Method org/apache/hadoop/hbase/util/Bytes.toBytes:(Ljava/lang/String;)[B
      44: ldc           #31                 // String ccc
      46: invokestatic  #28                 // Method org/apache/hadoop/hbase/util/Bytes.toBytes:(Ljava/lang/String;)[B
      49: invokespecial #30                 // Method org/apache/hadoop/hbase/HRegionInfo."<init>":(Lorg/apache/hadoop/hbase/TableName;[B[B)V
      52: astore_3
      53: new           #25                 // class org/apache/hadoop/hbase/HRegionInfo
      56: dup
      57: aload_1
      58: invokeinterface #26,  1           // InterfaceMethod org/apache/hadoop/hbase/client/TableDescriptor.getTableName:()Lorg/apache/hadoop/hbase/TableName;
      63: ldc           #31                 // String ccc
      65: invokestatic  #28                 // Method org/apache/hadoop/hbase/util/Bytes.toBytes:(Ljava/lang/String;)[B
      68: ldc           #29                 // String eee
      70: invokestatic  #28                 // Method org/apache/hadoop/hbase/util/Bytes.toBytes:(Ljava/lang/String;)[B
      73: invokespecial #30                 // Method org/apache/hadoop/hbase/HRegionInfo."<init>":(Lorg/apache/hadoop/hbase/TableName;[B[B)V
      76: astore        4
      78: aload_0
      79: aload_2
      80: aload_3
      81: aload         4
      83: invokespecial #32                 // Method createResult:(Lorg/apache/hadoop/hbase/HRegionInfo;Lorg/apache/hadoop/hbase/HRegionInfo;Lorg/apache/hadoop/hbase/HRegionInfo;)Lorg/apache/hadoop/hbase/client/Result;
      86: astore        5
      88: getstatic     #8                  // Field HTU:Lorg/apache/hadoop/hbase/HBaseTestingUtility;
      91: invokevirtual #14                 // Method org/apache/hadoop/hbase/HBaseTestingUtility.getConfiguration:()Lorg/apache/hadoop/conf/Configuration;
      94: invokestatic  #92                 // Method org/apache/hadoop/fs/FileSystem.get:(Lorg/apache/hadoop/conf/Configuration;)Lorg/apache/hadoop/fs/FileSystem;
      97: astore        6
      99: aload_0
     100: getfield      #16                 // Field masterServices:Lorg/apache/hadoop/hbase/master/assignment/MockMasterServices;
     103: invokevirtual #33                 // Method org/apache/hadoop/hbase/master/assignment/MockMasterServices.getMasterFileSystem:()Lorg/apache/hadoop/hbase/master/MasterFileSystem;
     106: invokevirtual #34                 // Method org/apache/hadoop/hbase/master/MasterFileSystem.getRootDir:()Lorg/apache/hadoop/fs/Path;
     109: astore        7
     111: aload         6
     113: invokevirtual #115                // Method org/apache/hadoop/fs/FileSystem.getConf:()Lorg/apache/hadoop/conf/Configuration;
     116: aload         7
     118: invokestatic  #116                // Method org/apache/hadoop/hbase/util/FSUtils.setRootDir:(Lorg/apache/hadoop/conf/Configuration;Lorg/apache/hadoop/fs/Path;)V
     121: aload         7
     123: aload_1
     124: invokeinterface #26,  1           // InterfaceMethod org/apache/hadoop/hbase/client/TableDescriptor.getTableName:()Lorg/apache/hadoop/hbase/TableName;
     129: invokestatic  #35                 // Method org/apache/hadoop/hbase/util/FSUtils.getTableDir:(Lorg/apache/hadoop/fs/Path;Lorg/apache/hadoop/hbase/TableName;)Lorg/apache/hadoop/fs/Path;
     132: astore        8
     134: aload         8
     136: aload_2
     137: aload_1
     138: invokeinterface #39,  1           // InterfaceMethod org/apache/hadoop/hbase/client/TableDescriptor.getColumnFamilies:()[Lorg/apache/hadoop/hbase/client/ColumnFamilyDescriptor;
     143: iconst_0
     144: aaload
     145: invokeinterface #40,  1           // InterfaceMethod org/apache/hadoop/hbase/client/ColumnFamilyDescriptor.getName:()[B
     150: invokestatic  #41                 // Method org/apache/hadoop/hbase/regionserver/HStore.getStoreHomedir:(Lorg/apache/hadoop/fs/Path;Lorg/apache/hadoop/hbase/client/RegionInfo;[B)Lorg/apache/hadoop/fs/Path;
     153: astore        9
     155: aload_0
     156: getfield      #16                 // Field masterServices:Lorg/apache/hadoop/hbase/master/assignment/MockMasterServices;
     159: invokevirtual #117                // Method org/apache/hadoop/hbase/master/assignment/MockMasterServices.getConfiguration:()Lorg/apache/hadoop/conf/Configuration;
     162: aload_2
     163: aload         8
     165: aload_1
     166: invokeinterface #39,  1           // InterfaceMethod org/apache/hadoop/hbase/client/TableDescriptor.getColumnFamilies:()[Lorg/apache/hadoop/hbase/client/ColumnFamilyDescriptor;
     171: iconst_0
     172: aaload
     173: invokeinterface #40,  1           // InterfaceMethod org/apache/hadoop/hbase/client/ColumnFamilyDescriptor.getName:()[B
     178: invokestatic  #118                // Method org/apache/hadoop/hbase/util/HFileArchiveUtil.getStoreArchivePath:(Lorg/apache/hadoop/conf/Configuration;Lorg/apache/hadoop/hbase/client/RegionInfo;Lorg/apache/hadoop/fs/Path;[B)Lorg/apache/hadoop/fs/Path;
     181: astore        10
     183: getstatic     #54                 // Field LOG:Lorg/slf4j/Logger;
     186: new           #44                 // class java/lang/StringBuilder
     189: dup
     190: invokespecial #45                 // Method java/lang/StringBuilder."<init>":()V
     193: ldc           #119                // String Table dir:
     195: invokevirtual #47                 // Method java/lang/StringBuilder.append:(Ljava/lang/String;)Ljava/lang/StringBuilder;
     198: aload         8
     200: invokevirtual #56                 // Method java/lang/StringBuilder.append:(Ljava/lang/Object;)Ljava/lang/StringBuilder;
     203: invokevirtual #49                 // Method java/lang/StringBuilder.toString:()Ljava/lang/String;
     206: invokeinterface #120,  2          // InterfaceMethod org/slf4j/Logger.debug:(Ljava/lang/String;)V
     211: getstatic     #54                 // Field LOG:Lorg/slf4j/Logger;
     214: new           #44                 // class java/lang/StringBuilder
     217: dup
     218: invokespecial #45                 // Method java/lang/StringBuilder."<init>":()V
     221: ldc           #121                // String Store dir:
     223: invokevirtual #47                 // Method java/lang/StringBuilder.append:(Ljava/lang/String;)Ljava/lang/StringBuilder;
     226: aload         9
     228: invokevirtual #56                 // Method java/lang/StringBuilder.append:(Ljava/lang/Object;)Ljava/lang/StringBuilder;
     231: invokevirtual #49                 // Method java/lang/StringBuilder.toString:()Ljava/lang/String;
     234: invokeinterface #120,  2          // InterfaceMethod org/slf4j/Logger.debug:(Ljava/lang/String;)V
     239: getstatic     #54                 // Field LOG:Lorg/slf4j/Logger;
     242: new           #44                 // class java/lang/StringBuilder
     245: dup
     246: invokespecial #45                 // Method java/lang/StringBuilder."<init>":()V
     249: ldc           #122                // String Store archive dir:
     251: invokevirtual #47                 // Method java/lang/StringBuilder.append:(Ljava/lang/String;)Ljava/lang/StringBuilder;
     254: aload         10
     256: invokevirtual #56                 // Method java/lang/StringBuilder.append:(Ljava/lang/Object;)Ljava/lang/StringBuilder;
     259: invokevirtual #49                 // Method java/lang/StringBuilder.toString:()Ljava/lang/String;
     262: invokeinterface #120,  2          // InterfaceMethod org/slf4j/Logger.debug:(Ljava/lang/String;)V
     267: aload_0
     268: iconst_2
     269: aload_0
     270: getfield      #16                 // Field masterServices:Lorg/apache/hadoop/hbase/master/assignment/MockMasterServices;
     273: aload         9
     275: invokespecial #123                // Method addMockStoreFiles:(ILorg/apache/hadoop/hbase/master/MasterServices;Lorg/apache/hadoop/fs/Path;)[Lorg/apache/hadoop/fs/FileStatus;
     278: astore        11
     280: aload         6
     282: aload         9
     284: invokevirtual #124                // Method org/apache/hadoop/fs/FileSystem.listStatus:(Lorg/apache/hadoop/fs/Path;)[Lorg/apache/hadoop/fs/FileStatus;
     287: astore        12
     289: iconst_0
     290: istore        13
     292: aload         12
     294: astore        14
     296: aload         14
     298: arraylength
     299: istore        15
     301: iconst_0
     302: istore        16
     304: iload         16
     306: iload         15
     308: if_icmpge     379
     311: aload         14
     313: iload         16
     315: aaload
     316: astore        17
     318: getstatic     #54                 // Field LOG:Lorg/slf4j/Logger;
     321: new           #44                 // class java/lang/StringBuilder
     324: dup
     325: invokespecial #45                 // Method java/lang/StringBuilder."<init>":()V
     328: ldc           #125                // String Have store file:
     330: invokevirtual #47                 // Method java/lang/StringBuilder.append:(Ljava/lang/String;)Ljava/lang/StringBuilder;
     333: aload         17
     335: invokevirtual #126                // Method org/apache/hadoop/fs/FileStatus.getPath:()Lorg/apache/hadoop/fs/Path;
     338: invokevirtual #56                 // Method java/lang/StringBuilder.append:(Ljava/lang/Object;)Ljava/lang/StringBuilder;
     341: invokevirtual #49                 // Method java/lang/StringBuilder.toString:()Ljava/lang/String;
     344: invokeinterface #120,  2          // InterfaceMethod org/slf4j/Logger.debug:(Ljava/lang/String;)V
     349: ldc           #127                // String Got unexpected store file
     351: aload         11
     353: iload         13
     355: aaload
     356: invokevirtual #126                // Method org/apache/hadoop/fs/FileStatus.getPath:()Lorg/apache/hadoop/fs/Path;
     359: aload         12
     361: iload         13
     363: aaload
     364: invokevirtual #126                // Method org/apache/hadoop/fs/FileStatus.getPath:()Lorg/apache/hadoop/fs/Path;
     367: invokestatic  #128                // Method org/junit/Assert.assertEquals:(Ljava/lang/String;Ljava/lang/Object;Ljava/lang/Object;)V
     370: iinc          13, 1
     373: iinc          16, 1
     376: goto          304
     379: aload_0
     380: getfield      #20                 // Field janitor:Lorg/apache/hadoop/hbase/master/CatalogJanitor;
     383: aload_2
     384: aload         5
     386: invokevirtual #59                 // Method org/apache/hadoop/hbase/master/CatalogJanitor.cleanParent:(Lorg/apache/hadoop/hbase/client/RegionInfo;Lorg/apache/hadoop/hbase/client/Result;)Z
     389: invokestatic  #53                 // Method org/junit/Assert.assertTrue:(Z)V
     392: new           #36                 // class org/apache/hadoop/fs/Path
     395: dup
     396: aload         8
     398: aload_2
     399: invokevirtual #37                 // Method org/apache/hadoop/hbase/HRegionInfo.getEncodedName:()Ljava/lang/String;
     402: invokespecial #38                 // Method org/apache/hadoop/fs/Path."<init>":(Lorg/apache/hadoop/fs/Path;Ljava/lang/String;)V
     405: astore        14
     407: aload_0
     408: getfield      #16                 // Field masterServices:Lorg/apache/hadoop/hbase/master/assignment/MockMasterServices;
     411: invokevirtual #61                 // Method org/apache/hadoop/hbase/master/assignment/MockMasterServices.getMasterProcedureExecutor:()Lorg/apache/hadoop/hbase/procedure2/ProcedureExecutor;
     414: invokestatic  #62                 // Method org/apache/hadoop/hbase/procedure2/ProcedureTestingUtility.waitAllProcedures:(Lorg/apache/hadoop/hbase/procedure2/ProcedureExecutor;)V
     417: aload         6
     419: aload         14
     421: invokevirtual #52                 // Method org/apache/hadoop/fs/FileSystem.exists:(Lorg/apache/hadoop/fs/Path;)Z
     424: ifne          431
     427: iconst_1
     428: goto          432
     431: iconst_0
     432: invokestatic  #53                 // Method org/junit/Assert.assertTrue:(Z)V
     435: getstatic     #54                 // Field LOG:Lorg/slf4j/Logger;
     438: ldc           #129                // String Finished cleanup of parent region
     440: invokeinterface #120,  2          // InterfaceMethod org/slf4j/Logger.debug:(Ljava/lang/String;)V
     445: aload         6
     447: aload         10
     449: invokevirtual #124                // Method org/apache/hadoop/fs/FileSystem.listStatus:(Lorg/apache/hadoop/fs/Path;)[Lorg/apache/hadoop/fs/FileStatus;
     452: astore        15
     454: aload_0
     455: ldc           #130                // String archived files
     457: aload         12
     459: invokespecial #131                // Method logFiles:(Ljava/lang/String;[Lorg/apache/hadoop/fs/FileStatus;)V
     462: aload_0
     463: ldc           #130                // String archived files
     465: aload         15
     467: invokespecial #131                // Method logFiles:(Ljava/lang/String;[Lorg/apache/hadoop/fs/FileStatus;)V
     470: aload         12
     472: aload         15
     474: aload         6
     476: invokestatic  #132                // Method org/apache/hadoop/hbase/util/HFileArchiveTestingUtil.assertArchiveEqualToOriginal:([Lorg/apache/hadoop/fs/FileStatus;[Lorg/apache/hadoop/fs/FileStatus;Lorg/apache/hadoop/fs/FileSystem;)V
     479: aload         6
     481: aload         7
     483: iconst_1
     484: invokestatic  #133                // Method org/apache/hadoop/hbase/util/FSUtils.delete:(Lorg/apache/hadoop/fs/FileSystem;Lorg/apache/hadoop/fs/Path;Z)Z
     487: pop
     488: return

  public void testDuplicateHFileResolution() throws java.lang.Exception;
    Code:
       0: aload_0
       1: invokespecial #24                 // Method createTableDescriptorForCurrentMethod:()Lorg/apache/hadoop/hbase/client/TableDescriptor;
       4: astore_1
       5: new           #25                 // class org/apache/hadoop/hbase/HRegionInfo
       8: dup
       9: aload_1
      10: invokeinterface #26,  1           // InterfaceMethod org/apache/hadoop/hbase/client/TableDescriptor.getTableName:()Lorg/apache/hadoop/hbase/TableName;
      15: ldc           #27                 // String aaa
      17: invokestatic  #28                 // Method org/apache/hadoop/hbase/util/Bytes.toBytes:(Ljava/lang/String;)[B
      20: ldc           #29                 // String eee
      22: invokestatic  #28                 // Method org/apache/hadoop/hbase/util/Bytes.toBytes:(Ljava/lang/String;)[B
      25: invokespecial #30                 // Method org/apache/hadoop/hbase/HRegionInfo."<init>":(Lorg/apache/hadoop/hbase/TableName;[B[B)V
      28: astore_2
      29: new           #25                 // class org/apache/hadoop/hbase/HRegionInfo
      32: dup
      33: aload_1
      34: invokeinterface #26,  1           // InterfaceMethod org/apache/hadoop/hbase/client/TableDescriptor.getTableName:()Lorg/apache/hadoop/hbase/TableName;
      39: ldc           #27                 // String aaa
      41: invokestatic  #28                 // Method org/apache/hadoop/hbase/util/Bytes.toBytes:(Ljava/lang/String;)[B
      44: ldc           #31                 // String ccc
      46: invokestatic  #28                 // Method org/apache/hadoop/hbase/util/Bytes.toBytes:(Ljava/lang/String;)[B
      49: invokespecial #30                 // Method org/apache/hadoop/hbase/HRegionInfo."<init>":(Lorg/apache/hadoop/hbase/TableName;[B[B)V
      52: astore_3
      53: new           #25                 // class org/apache/hadoop/hbase/HRegionInfo
      56: dup
      57: aload_1
      58: invokeinterface #26,  1           // InterfaceMethod org/apache/hadoop/hbase/client/TableDescriptor.getTableName:()Lorg/apache/hadoop/hbase/TableName;
      63: ldc           #31                 // String ccc
      65: invokestatic  #28                 // Method org/apache/hadoop/hbase/util/Bytes.toBytes:(Ljava/lang/String;)[B
      68: ldc           #29                 // String eee
      70: invokestatic  #28                 // Method org/apache/hadoop/hbase/util/Bytes.toBytes:(Ljava/lang/String;)[B
      73: invokespecial #30                 // Method org/apache/hadoop/hbase/HRegionInfo."<init>":(Lorg/apache/hadoop/hbase/TableName;[B[B)V
      76: astore        4
      78: aload_0
      79: aload_2
      80: aload_3
      81: aload         4
      83: invokespecial #32                 // Method createResult:(Lorg/apache/hadoop/hbase/HRegionInfo;Lorg/apache/hadoop/hbase/HRegionInfo;Lorg/apache/hadoop/hbase/HRegionInfo;)Lorg/apache/hadoop/hbase/client/Result;
      86: astore        5
      88: getstatic     #8                  // Field HTU:Lorg/apache/hadoop/hbase/HBaseTestingUtility;
      91: invokevirtual #14                 // Method org/apache/hadoop/hbase/HBaseTestingUtility.getConfiguration:()Lorg/apache/hadoop/conf/Configuration;
      94: invokestatic  #92                 // Method org/apache/hadoop/fs/FileSystem.get:(Lorg/apache/hadoop/conf/Configuration;)Lorg/apache/hadoop/fs/FileSystem;
      97: astore        6
      99: aload_0
     100: getfield      #16                 // Field masterServices:Lorg/apache/hadoop/hbase/master/assignment/MockMasterServices;
     103: invokevirtual #33                 // Method org/apache/hadoop/hbase/master/assignment/MockMasterServices.getMasterFileSystem:()Lorg/apache/hadoop/hbase/master/MasterFileSystem;
     106: invokevirtual #34                 // Method org/apache/hadoop/hbase/master/MasterFileSystem.getRootDir:()Lorg/apache/hadoop/fs/Path;
     109: astore        7
     111: aload         6
     113: invokevirtual #115                // Method org/apache/hadoop/fs/FileSystem.getConf:()Lorg/apache/hadoop/conf/Configuration;
     116: aload         7
     118: invokestatic  #116                // Method org/apache/hadoop/hbase/util/FSUtils.setRootDir:(Lorg/apache/hadoop/conf/Configuration;Lorg/apache/hadoop/fs/Path;)V
     121: aload         7
     123: aload_2
     124: invokevirtual #137                // Method org/apache/hadoop/hbase/HRegionInfo.getTable:()Lorg/apache/hadoop/hbase/TableName;
     127: invokestatic  #35                 // Method org/apache/hadoop/hbase/util/FSUtils.getTableDir:(Lorg/apache/hadoop/fs/Path;Lorg/apache/hadoop/hbase/TableName;)Lorg/apache/hadoop/fs/Path;
     130: astore        8
     132: aload         8
     134: aload_2
     135: aload_1
     136: invokeinterface #39,  1           // InterfaceMethod org/apache/hadoop/hbase/client/TableDescriptor.getColumnFamilies:()[Lorg/apache/hadoop/hbase/client/ColumnFamilyDescriptor;
     141: iconst_0
     142: aaload
     143: invokeinterface #40,  1           // InterfaceMethod org/apache/hadoop/hbase/client/ColumnFamilyDescriptor.getName:()[B
     148: invokestatic  #41                 // Method org/apache/hadoop/hbase/regionserver/HStore.getStoreHomedir:(Lorg/apache/hadoop/fs/Path;Lorg/apache/hadoop/hbase/client/RegionInfo;[B)Lorg/apache/hadoop/fs/Path;
     151: astore        9
     153: getstatic     #138                // Field java/lang/System.out:Ljava/io/PrintStream;
     156: new           #44                 // class java/lang/StringBuilder
     159: dup
     160: invokespecial #45                 // Method java/lang/StringBuilder."<init>":()V
     163: ldc           #139                // String Old root:
     165: invokevirtual #47                 // Method java/lang/StringBuilder.append:(Ljava/lang/String;)Ljava/lang/StringBuilder;
     168: aload         7
     170: invokevirtual #56                 // Method java/lang/StringBuilder.append:(Ljava/lang/Object;)Ljava/lang/StringBuilder;
     173: invokevirtual #49                 // Method java/lang/StringBuilder.toString:()Ljava/lang/String;
     176: invokevirtual #140                // Method java/io/PrintStream.println:(Ljava/lang/String;)V
     179: getstatic     #138                // Field java/lang/System.out:Ljava/io/PrintStream;
     182: new           #44                 // class java/lang/StringBuilder
     185: dup
     186: invokespecial #45                 // Method java/lang/StringBuilder."<init>":()V
     189: ldc           #141                // String Old table:
     191: invokevirtual #47                 // Method java/lang/StringBuilder.append:(Ljava/lang/String;)Ljava/lang/StringBuilder;
     194: aload         8
     196: invokevirtual #56                 // Method java/lang/StringBuilder.append:(Ljava/lang/Object;)Ljava/lang/StringBuilder;
     199: invokevirtual #49                 // Method java/lang/StringBuilder.toString:()Ljava/lang/String;
     202: invokevirtual #140                // Method java/io/PrintStream.println:(Ljava/lang/String;)V
     205: getstatic     #138                // Field java/lang/System.out:Ljava/io/PrintStream;
     208: new           #44                 // class java/lang/StringBuilder
     211: dup
     212: invokespecial #45                 // Method java/lang/StringBuilder."<init>":()V
     215: ldc           #142                // String Old store:
     217: invokevirtual #47                 // Method java/lang/StringBuilder.append:(Ljava/lang/String;)Ljava/lang/StringBuilder;
     220: aload         9
     222: invokevirtual #56                 // Method java/lang/StringBuilder.append:(Ljava/lang/Object;)Ljava/lang/StringBuilder;
     225: invokevirtual #49                 // Method java/lang/StringBuilder.toString:()Ljava/lang/String;
     228: invokevirtual #140                // Method java/io/PrintStream.println:(Ljava/lang/String;)V
     231: aload_0
     232: getfield      #16                 // Field masterServices:Lorg/apache/hadoop/hbase/master/assignment/MockMasterServices;
     235: invokevirtual #117                // Method org/apache/hadoop/hbase/master/assignment/MockMasterServices.getConfiguration:()Lorg/apache/hadoop/conf/Configuration;
     238: aload_2
     239: aload         8
     241: aload_1
     242: invokeinterface #39,  1           // InterfaceMethod org/apache/hadoop/hbase/client/TableDescriptor.getColumnFamilies:()[Lorg/apache/hadoop/hbase/client/ColumnFamilyDescriptor;
     247: iconst_0
     248: aaload
     249: invokeinterface #40,  1           // InterfaceMethod org/apache/hadoop/hbase/client/ColumnFamilyDescriptor.getName:()[B
     254: invokestatic  #118                // Method org/apache/hadoop/hbase/util/HFileArchiveUtil.getStoreArchivePath:(Lorg/apache/hadoop/conf/Configuration;Lorg/apache/hadoop/hbase/client/RegionInfo;Lorg/apache/hadoop/fs/Path;[B)Lorg/apache/hadoop/fs/Path;
     257: astore        10
     259: getstatic     #138                // Field java/lang/System.out:Ljava/io/PrintStream;
     262: new           #44                 // class java/lang/StringBuilder
     265: dup
     266: invokespecial #45                 // Method java/lang/StringBuilder."<init>":()V
     269: ldc           #143                // String Old archive:
     271: invokevirtual #47                 // Method java/lang/StringBuilder.append:(Ljava/lang/String;)Ljava/lang/StringBuilder;
     274: aload         10
     276: invokevirtual #56                 // Method java/lang/StringBuilder.append:(Ljava/lang/Object;)Ljava/lang/StringBuilder;
     279: invokevirtual #49                 // Method java/lang/StringBuilder.toString:()Ljava/lang/String;
     282: invokevirtual #140                // Method java/io/PrintStream.println:(Ljava/lang/String;)V
     285: aload_0
     286: iconst_2
     287: aload_0
     288: getfield      #16                 // Field masterServices:Lorg/apache/hadoop/hbase/master/assignment/MockMasterServices;
     291: aload         9
     293: invokespecial #123                // Method addMockStoreFiles:(ILorg/apache/hadoop/hbase/master/MasterServices;Lorg/apache/hadoop/fs/Path;)[Lorg/apache/hadoop/fs/FileStatus;
     296: pop
     297: aload         6
     299: aload         9
     301: invokevirtual #124                // Method org/apache/hadoop/fs/FileSystem.listStatus:(Lorg/apache/hadoop/fs/Path;)[Lorg/apache/hadoop/fs/FileStatus;
     304: astore        11
     306: aload_0
     307: getfield      #20                 // Field janitor:Lorg/apache/hadoop/hbase/master/CatalogJanitor;
     310: aload_2
     311: aload         5
     313: invokevirtual #59                 // Method org/apache/hadoop/hbase/master/CatalogJanitor.cleanParent:(Lorg/apache/hadoop/hbase/client/RegionInfo;Lorg/apache/hadoop/hbase/client/Result;)Z
     316: invokestatic  #53                 // Method org/junit/Assert.assertTrue:(Z)V
     319: new           #36                 // class org/apache/hadoop/fs/Path
     322: dup
     323: aload         8
     325: aload_2
     326: invokevirtual #37                 // Method org/apache/hadoop/hbase/HRegionInfo.getEncodedName:()Ljava/lang/String;
     329: invokespecial #38                 // Method org/apache/hadoop/fs/Path."<init>":(Lorg/apache/hadoop/fs/Path;Ljava/lang/String;)V
     332: astore        12
     334: aload_0
     335: getfield      #16                 // Field masterServices:Lorg/apache/hadoop/hbase/master/assignment/MockMasterServices;
     338: invokevirtual #61                 // Method org/apache/hadoop/hbase/master/assignment/MockMasterServices.getMasterProcedureExecutor:()Lorg/apache/hadoop/hbase/procedure2/ProcedureExecutor;
     341: invokestatic  #62                 // Method org/apache/hadoop/hbase/procedure2/ProcedureTestingUtility.waitAllProcedures:(Lorg/apache/hadoop/hbase/procedure2/ProcedureExecutor;)V
     344: aload         6
     346: aload         12
     348: invokevirtual #52                 // Method org/apache/hadoop/fs/FileSystem.exists:(Lorg/apache/hadoop/fs/Path;)Z
     351: ifne          358
     354: iconst_1
     355: goto          359
     358: iconst_0
     359: invokestatic  #53                 // Method org/junit/Assert.assertTrue:(Z)V
     362: aload         6
     364: aload         10
     366: invokevirtual #124                // Method org/apache/hadoop/fs/FileSystem.listStatus:(Lorg/apache/hadoop/fs/Path;)[Lorg/apache/hadoop/fs/FileStatus;
     369: astore        13
     371: aload         11
     373: aload         13
     375: aload         6
     377: invokestatic  #132                // Method org/apache/hadoop/hbase/util/HFileArchiveTestingUtil.assertArchiveEqualToOriginal:([Lorg/apache/hadoop/fs/FileStatus;[Lorg/apache/hadoop/fs/FileStatus;Lorg/apache/hadoop/fs/FileSystem;)V
     380: aload_0
     381: iconst_2
     382: aload_0
     383: getfield      #16                 // Field masterServices:Lorg/apache/hadoop/hbase/master/assignment/MockMasterServices;
     386: aload         9
     388: invokespecial #123                // Method addMockStoreFiles:(ILorg/apache/hadoop/hbase/master/MasterServices;Lorg/apache/hadoop/fs/Path;)[Lorg/apache/hadoop/fs/FileStatus;
     391: pop
     392: aload_0
     393: getfield      #20                 // Field janitor:Lorg/apache/hadoop/hbase/master/CatalogJanitor;
     396: aload_2
     397: aload         5
     399: invokevirtual #59                 // Method org/apache/hadoop/hbase/master/CatalogJanitor.cleanParent:(Lorg/apache/hadoop/hbase/client/RegionInfo;Lorg/apache/hadoop/hbase/client/Result;)Z
     402: invokestatic  #53                 // Method org/junit/Assert.assertTrue:(Z)V
     405: aload_0
     406: getfield      #16                 // Field masterServices:Lorg/apache/hadoop/hbase/master/assignment/MockMasterServices;
     409: invokevirtual #61                 // Method org/apache/hadoop/hbase/master/assignment/MockMasterServices.getMasterProcedureExecutor:()Lorg/apache/hadoop/hbase/procedure2/ProcedureExecutor;
     412: invokestatic  #62                 // Method org/apache/hadoop/hbase/procedure2/ProcedureTestingUtility.waitAllProcedures:(Lorg/apache/hadoop/hbase/procedure2/ProcedureExecutor;)V
     415: aload         6
     417: aload         12
     419: invokevirtual #52                 // Method org/apache/hadoop/fs/FileSystem.exists:(Lorg/apache/hadoop/fs/Path;)Z
     422: ifne          429
     425: iconst_1
     426: goto          430
     429: iconst_0
     430: invokestatic  #53                 // Method org/junit/Assert.assertTrue:(Z)V
     433: aload         6
     435: aload         10
     437: invokevirtual #124                // Method org/apache/hadoop/fs/FileSystem.listStatus:(Lorg/apache/hadoop/fs/Path;)[Lorg/apache/hadoop/fs/FileStatus;
     440: astore        13
     442: aload         11
     444: aload         13
     446: aload         6
     448: iconst_1
     449: invokestatic  #144                // Method org/apache/hadoop/hbase/util/HFileArchiveTestingUtil.assertArchiveEqualToOriginal:([Lorg/apache/hadoop/fs/FileStatus;[Lorg/apache/hadoop/fs/FileStatus;Lorg/apache/hadoop/fs/FileSystem;Z)V
     452: return

  static {};
    Code:
       0: ldc           #161                // class org/apache/hadoop/hbase/master/TestCatalogJanitor
       2: invokestatic  #162                // Method org/apache/hadoop/hbase/HBaseClassTestRule.forClass:(Ljava/lang/Class;)Lorg/apache/hadoop/hbase/HBaseClassTestRule;
       5: putstatic     #163                // Field CLASS_RULE:Lorg/apache/hadoop/hbase/HBaseClassTestRule;
       8: ldc           #161                // class org/apache/hadoop/hbase/master/TestCatalogJanitor
      10: invokestatic  #164                // Method org/slf4j/LoggerFactory.getLogger:(Ljava/lang/Class;)Lorg/slf4j/Logger;
      13: putstatic     #54                 // Field LOG:Lorg/slf4j/Logger;
      16: new           #165                // class org/apache/hadoop/hbase/HBaseTestingUtility
      19: dup
      20: invokespecial #166                // Method org/apache/hadoop/hbase/HBaseTestingUtility."<init>":()V
      23: putstatic     #8                  // Field HTU:Lorg/apache/hadoop/hbase/HBaseTestingUtility;
      26: return
}
