Compiled from "TestServerCrashProcedureStuck.java"
public class org.apache.hadoop.hbase.master.TestServerCrashProcedureStuck {
  public static final org.apache.hadoop.hbase.HBaseClassTestRule CLASS_RULE;

  public org.apache.hadoop.hbase.master.TestServerCrashProcedureStuck();
    Code:
       0: aload_0
       1: invokespecial #1                  // Method java/lang/Object."<init>":()V
       4: return

  public static void setUp() throws java.lang.Exception;
    Code:
       0: getstatic     #2                  // Field UTIL:Lorg/apache/hadoop/hbase/HBaseTestingUtility;
       3: iconst_3
       4: invokevirtual #3                  // Method org/apache/hadoop/hbase/HBaseTestingUtility.startMiniCluster:(I)Lorg/apache/hadoop/hbase/MiniHBaseCluster;
       7: pop
       8: getstatic     #2                  // Field UTIL:Lorg/apache/hadoop/hbase/HBaseTestingUtility;
      11: invokevirtual #4                  // Method org/apache/hadoop/hbase/HBaseTestingUtility.getAdmin:()Lorg/apache/hadoop/hbase/client/Admin;
      14: iconst_0
      15: iconst_1
      16: invokeinterface #5,  3            // InterfaceMethod org/apache/hadoop/hbase/client/Admin.balancerSwitch:(ZZ)Z
      21: pop
      22: getstatic     #2                  // Field UTIL:Lorg/apache/hadoop/hbase/HBaseTestingUtility;
      25: getstatic     #6                  // Field TABLE_NAME:Lorg/apache/hadoop/hbase/TableName;
      28: getstatic     #7                  // Field CF:[B
      31: invokevirtual #8                  // Method org/apache/hadoop/hbase/HBaseTestingUtility.createTable:(Lorg/apache/hadoop/hbase/TableName;[B)Lorg/apache/hadoop/hbase/client/Table;
      34: pop
      35: getstatic     #2                  // Field UTIL:Lorg/apache/hadoop/hbase/HBaseTestingUtility;
      38: getstatic     #6                  // Field TABLE_NAME:Lorg/apache/hadoop/hbase/TableName;
      41: invokevirtual #9                  // Method org/apache/hadoop/hbase/HBaseTestingUtility.waitTableAvailable:(Lorg/apache/hadoop/hbase/TableName;)V
      44: return

  public static void tearDown() throws java.lang.Exception;
    Code:
       0: getstatic     #2                  // Field UTIL:Lorg/apache/hadoop/hbase/HBaseTestingUtility;
       3: invokevirtual #10                 // Method org/apache/hadoop/hbase/HBaseTestingUtility.shutdownMiniCluster:()V
       6: return

  public void test() throws java.lang.Exception;
    Code:
       0: aconst_null
       1: astore_1
       2: getstatic     #2                  // Field UTIL:Lorg/apache/hadoop/hbase/HBaseTestingUtility;
       5: invokevirtual #11                 // Method org/apache/hadoop/hbase/HBaseTestingUtility.getMiniHBaseCluster:()Lorg/apache/hadoop/hbase/MiniHBaseCluster;
       8: invokevirtual #12                 // Method org/apache/hadoop/hbase/MiniHBaseCluster.getRegionServerThreads:()Ljava/util/List;
      11: invokeinterface #13,  1           // InterfaceMethod java/util/List.iterator:()Ljava/util/Iterator;
      16: astore_2
      17: aload_2
      18: invokeinterface #14,  1           // InterfaceMethod java/util/Iterator.hasNext:()Z
      23: ifeq          62
      26: aload_2
      27: invokeinterface #15,  1           // InterfaceMethod java/util/Iterator.next:()Ljava/lang/Object;
      32: checkcast     #16                 // class org/apache/hadoop/hbase/util/JVMClusterUtil$RegionServerThread
      35: astore_3
      36: aload_3
      37: invokevirtual #17                 // Method org/apache/hadoop/hbase/util/JVMClusterUtil$RegionServerThread.getRegionServer:()Lorg/apache/hadoop/hbase/regionserver/HRegionServer;
      40: getstatic     #6                  // Field TABLE_NAME:Lorg/apache/hadoop/hbase/TableName;
      43: invokevirtual #18                 // Method org/apache/hadoop/hbase/regionserver/HRegionServer.getRegions:(Lorg/apache/hadoop/hbase/TableName;)Ljava/util/List;
      46: invokeinterface #19,  1           // InterfaceMethod java/util/List.isEmpty:()Z
      51: ifne          59
      54: aload_3
      55: astore_1
      56: goto          62
      59: goto          17
      62: aload_1
      63: invokevirtual #17                 // Method org/apache/hadoop/hbase/util/JVMClusterUtil$RegionServerThread.getRegionServer:()Lorg/apache/hadoop/hbase/regionserver/HRegionServer;
      66: astore_2
      67: aload_2
      68: getstatic     #6                  // Field TABLE_NAME:Lorg/apache/hadoop/hbase/TableName;
      71: invokevirtual #18                 // Method org/apache/hadoop/hbase/regionserver/HRegionServer.getRegions:(Lorg/apache/hadoop/hbase/TableName;)Ljava/util/List;
      74: iconst_0
      75: invokeinterface #20,  2           // InterfaceMethod java/util/List.get:(I)Ljava/lang/Object;
      80: checkcast     #21                 // class org/apache/hadoop/hbase/regionserver/HRegion
      83: invokevirtual #22                 // Method org/apache/hadoop/hbase/regionserver/HRegion.getRegionInfo:()Lorg/apache/hadoop/hbase/client/RegionInfo;
      86: astore_3
      87: getstatic     #2                  // Field UTIL:Lorg/apache/hadoop/hbase/HBaseTestingUtility;
      90: invokevirtual #11                 // Method org/apache/hadoop/hbase/HBaseTestingUtility.getMiniHBaseCluster:()Lorg/apache/hadoop/hbase/MiniHBaseCluster;
      93: invokevirtual #23                 // Method org/apache/hadoop/hbase/MiniHBaseCluster.getMaster:()Lorg/apache/hadoop/hbase/master/HMaster;
      96: astore        4
      98: aload         4
     100: invokevirtual #24                 // Method org/apache/hadoop/hbase/master/HMaster.getMasterProcedureExecutor:()Lorg/apache/hadoop/hbase/procedure2/ProcedureExecutor;
     103: astore        5
     105: new           #25                 // class org/apache/hadoop/hbase/master/DummyRegionProcedure
     108: dup
     109: aload         5
     111: invokevirtual #26                 // Method org/apache/hadoop/hbase/procedure2/ProcedureExecutor.getEnvironment:()Ljava/lang/Object;
     114: checkcast     #27                 // class org/apache/hadoop/hbase/master/procedure/MasterProcedureEnv
     117: aload_3
     118: invokespecial #28                 // Method org/apache/hadoop/hbase/master/DummyRegionProcedure."<init>":(Lorg/apache/hadoop/hbase/master/procedure/MasterProcedureEnv;Lorg/apache/hadoop/hbase/client/RegionInfo;)V
     121: astore        6
     123: aload         4
     125: invokevirtual #24                 // Method org/apache/hadoop/hbase/master/HMaster.getMasterProcedureExecutor:()Lorg/apache/hadoop/hbase/procedure2/ProcedureExecutor;
     128: aload         6
     130: invokevirtual #29                 // Method org/apache/hadoop/hbase/procedure2/ProcedureExecutor.submitProcedure:(Lorg/apache/hadoop/hbase/procedure2/Procedure;)J
     133: lstore        7
     135: aload         6
     137: invokevirtual #30                 // Method org/apache/hadoop/hbase/master/DummyRegionProcedure.waitUntilArrive:()V
     140: getstatic     #2                  // Field UTIL:Lorg/apache/hadoop/hbase/HBaseTestingUtility;
     143: invokevirtual #31                 // Method org/apache/hadoop/hbase/HBaseTestingUtility.getConfiguration:()Lorg/apache/hadoop/conf/Configuration;
     146: invokestatic  #32                 // Method org/apache/hadoop/hbase/client/ConnectionFactory.createAsyncConnection:(Lorg/apache/hadoop/conf/Configuration;)Ljava/util/concurrent/CompletableFuture;
     149: invokevirtual #33                 // Method java/util/concurrent/CompletableFuture.get:()Ljava/lang/Object;
     152: checkcast     #34                 // class org/apache/hadoop/hbase/client/AsyncConnection
     155: astore        9
     157: aconst_null
     158: astore        10
     160: aload         9
     162: invokeinterface #35,  1           // InterfaceMethod org/apache/hadoop/hbase/client/AsyncConnection.getAdmin:()Lorg/apache/hadoop/hbase/client/AsyncAdmin;
     167: astore        11
     169: aload         11
     171: aload_3
     172: invokeinterface #36,  1           // InterfaceMethod org/apache/hadoop/hbase/client/RegionInfo.getRegionName:()[B
     177: invokeinterface #37,  2           // InterfaceMethod org/apache/hadoop/hbase/client/AsyncAdmin.move:([B)Ljava/util/concurrent/CompletableFuture;
     182: astore        12
     184: aload_2
     185: ldc           #38                 // String For testing!
     187: invokevirtual #39                 // Method org/apache/hadoop/hbase/regionserver/HRegionServer.abort:(Ljava/lang/String;)V
     190: getstatic     #2                  // Field UTIL:Lorg/apache/hadoop/hbase/HBaseTestingUtility;
     193: ldc2_w        #40                 // long 30000l
     196: aload         5
     198: aload_3
     199: invokedynamic #42,  0             // InvokeDynamic #0:evaluate:(Lorg/apache/hadoop/hbase/procedure2/ProcedureExecutor;Lorg/apache/hadoop/hbase/client/RegionInfo;)Lorg/apache/hadoop/hbase/Waiter$Predicate;
     204: invokevirtual #43                 // Method org/apache/hadoop/hbase/HBaseTestingUtility.waitFor:(JLorg/apache/hadoop/hbase/Waiter$Predicate;)J
     207: pop2
     208: aload         6
     210: invokevirtual #44                 // Method org/apache/hadoop/hbase/master/DummyRegionProcedure.resume:()V
     213: getstatic     #2                  // Field UTIL:Lorg/apache/hadoop/hbase/HBaseTestingUtility;
     216: ldc2_w        #40                 // long 30000l
     219: aload         5
     221: lload         7
     223: invokedynamic #45,  0             // InvokeDynamic #1:evaluate:(Lorg/apache/hadoop/hbase/procedure2/ProcedureExecutor;J)Lorg/apache/hadoop/hbase/Waiter$Predicate;
     228: invokevirtual #43                 // Method org/apache/hadoop/hbase/HBaseTestingUtility.waitFor:(JLorg/apache/hadoop/hbase/Waiter$Predicate;)J
     231: pop2
     232: aload         12
     234: ldc2_w        #46                 // long 30l
     237: getstatic     #48                 // Field java/util/concurrent/TimeUnit.SECONDS:Ljava/util/concurrent/TimeUnit;
     240: invokevirtual #49                 // Method java/util/concurrent/CompletableFuture.get:(JLjava/util/concurrent/TimeUnit;)Ljava/lang/Object;
     243: pop
     244: aload         9
     246: ifnull        339
     249: aload         10
     251: ifnull        276
     254: aload         9
     256: invokeinterface #50,  1           // InterfaceMethod org/apache/hadoop/hbase/client/AsyncConnection.close:()V
     261: goto          339
     264: astore        11
     266: aload         10
     268: aload         11
     270: invokevirtual #52                 // Method java/lang/Throwable.addSuppressed:(Ljava/lang/Throwable;)V
     273: goto          339
     276: aload         9
     278: invokeinterface #50,  1           // InterfaceMethod org/apache/hadoop/hbase/client/AsyncConnection.close:()V
     283: goto          339
     286: astore        11
     288: aload         11
     290: astore        10
     292: aload         11
     294: athrow
     295: astore        13
     297: aload         9
     299: ifnull        336
     302: aload         10
     304: ifnull        329
     307: aload         9
     309: invokeinterface #50,  1           // InterfaceMethod org/apache/hadoop/hbase/client/AsyncConnection.close:()V
     314: goto          336
     317: astore        14
     319: aload         10
     321: aload         14
     323: invokevirtual #52                 // Method java/lang/Throwable.addSuppressed:(Ljava/lang/Throwable;)V
     326: goto          336
     329: aload         9
     331: invokeinterface #50,  1           // InterfaceMethod org/apache/hadoop/hbase/client/AsyncConnection.close:()V
     336: aload         13
     338: athrow
     339: return
    Exception table:
       from    to  target type
         254   261   264   Class java/lang/Throwable
         160   244   286   Class java/lang/Throwable
         160   244   295   any
         307   314   317   Class java/lang/Throwable
         286   297   295   any

  static {};
    Code:
       0: ldc           #65                 // class org/apache/hadoop/hbase/master/TestServerCrashProcedureStuck
       2: invokestatic  #66                 // Method org/apache/hadoop/hbase/HBaseClassTestRule.forClass:(Ljava/lang/Class;)Lorg/apache/hadoop/hbase/HBaseClassTestRule;
       5: putstatic     #67                 // Field CLASS_RULE:Lorg/apache/hadoop/hbase/HBaseClassTestRule;
       8: new           #68                 // class org/apache/hadoop/hbase/HBaseTestingUtility
      11: dup
      12: invokespecial #69                 // Method org/apache/hadoop/hbase/HBaseTestingUtility."<init>":()V
      15: putstatic     #2                  // Field UTIL:Lorg/apache/hadoop/hbase/HBaseTestingUtility;
      18: ldc           #70                 // String test
      20: invokestatic  #71                 // Method org/apache/hadoop/hbase/TableName.valueOf:(Ljava/lang/String;)Lorg/apache/hadoop/hbase/TableName;
      23: putstatic     #6                  // Field TABLE_NAME:Lorg/apache/hadoop/hbase/TableName;
      26: ldc           #72                 // String cf
      28: invokestatic  #73                 // Method org/apache/hadoop/hbase/util/Bytes.toBytes:(Ljava/lang/String;)[B
      31: putstatic     #7                  // Field CF:[B
      34: return
}
