Compiled from "TestIndividualBytesFieldCell.java"
public class org.apache.hadoop.hbase.TestIndividualBytesFieldCell {
  public static final org.apache.hadoop.hbase.HBaseClassTestRule CLASS_RULE;

  public org.apache.hadoop.hbase.TestIndividualBytesFieldCell();
    Code:
       0: aload_0
       1: invokespecial #1                  // Method java/lang/Object."<init>":()V
       4: return

  public static void testConstructorAndVerify();
    Code:
       0: ldc           #2                  // String immutable-row
       2: invokestatic  #3                  // Method org/apache/hadoop/hbase/util/Bytes.toBytes:(Ljava/lang/String;)[B
       5: astore_0
       6: ldc           #4                  // String immutable-family
       8: invokestatic  #3                  // Method org/apache/hadoop/hbase/util/Bytes.toBytes:(Ljava/lang/String;)[B
      11: astore_1
      12: ldc           #5                  // String immutable-qualifier
      14: invokestatic  #3                  // Method org/apache/hadoop/hbase/util/Bytes.toBytes:(Ljava/lang/String;)[B
      17: astore_2
      18: ldc           #6                  // String immutable-value
      20: invokestatic  #3                  // Method org/apache/hadoop/hbase/util/Bytes.toBytes:(Ljava/lang/String;)[B
      23: astore_3
      24: ldc           #7                  // String immutable-tags
      26: invokestatic  #3                  // Method org/apache/hadoop/hbase/util/Bytes.toBytes:(Ljava/lang/String;)[B
      29: astore        4
      31: ldc2_w        #8                  // long 5000l
      34: lstore        5
      36: lconst_0
      37: lstore        7
      39: getstatic     #10                 // Field org/apache/hadoop/hbase/KeyValue$Type.Put:Lorg/apache/hadoop/hbase/KeyValue$Type;
      42: astore        9
      44: new           #11                 // class org/apache/hadoop/hbase/IndividualBytesFieldCell
      47: dup
      48: aload_0
      49: aload_1
      50: aload_2
      51: lload         5
      53: aload         9
      55: lload         7
      57: aload_3
      58: aload         4
      60: invokespecial #12                 // Method org/apache/hadoop/hbase/IndividualBytesFieldCell."<init>":([B[B[BJLorg/apache/hadoop/hbase/KeyValue$Type;J[B[B)V
      63: putstatic     #13                 // Field ic0:Lorg/apache/hadoop/hbase/IndividualBytesFieldCell;
      66: new           #14                 // class org/apache/hadoop/hbase/KeyValue
      69: dup
      70: aload_0
      71: aload_1
      72: aload_2
      73: lload         5
      75: aload         9
      77: aload_3
      78: aload         4
      80: invokespecial #15                 // Method org/apache/hadoop/hbase/KeyValue."<init>":([B[B[BJLorg/apache/hadoop/hbase/KeyValue$Type;[B[B)V
      83: putstatic     #16                 // Field kv0:Lorg/apache/hadoop/hbase/KeyValue;
      86: getstatic     #13                 // Field ic0:Lorg/apache/hadoop/hbase/IndividualBytesFieldCell;
      89: invokevirtual #17                 // Method org/apache/hadoop/hbase/IndividualBytesFieldCell.getRowArray:()[B
      92: aload_0
      93: if_acmpne     100
      96: iconst_1
      97: goto          101
     100: iconst_0
     101: invokestatic  #18                 // Method org/junit/Assert.assertTrue:(Z)V
     104: getstatic     #13                 // Field ic0:Lorg/apache/hadoop/hbase/IndividualBytesFieldCell;
     107: invokevirtual #19                 // Method org/apache/hadoop/hbase/IndividualBytesFieldCell.getFamilyArray:()[B
     110: aload_1
     111: if_acmpne     118
     114: iconst_1
     115: goto          119
     118: iconst_0
     119: invokestatic  #18                 // Method org/junit/Assert.assertTrue:(Z)V
     122: getstatic     #13                 // Field ic0:Lorg/apache/hadoop/hbase/IndividualBytesFieldCell;
     125: invokevirtual #20                 // Method org/apache/hadoop/hbase/IndividualBytesFieldCell.getQualifierArray:()[B
     128: aload_2
     129: if_acmpne     136
     132: iconst_1
     133: goto          137
     136: iconst_0
     137: invokestatic  #18                 // Method org/junit/Assert.assertTrue:(Z)V
     140: getstatic     #13                 // Field ic0:Lorg/apache/hadoop/hbase/IndividualBytesFieldCell;
     143: invokevirtual #21                 // Method org/apache/hadoop/hbase/IndividualBytesFieldCell.getValueArray:()[B
     146: aload_3
     147: if_acmpne     154
     150: iconst_1
     151: goto          155
     154: iconst_0
     155: invokestatic  #18                 // Method org/junit/Assert.assertTrue:(Z)V
     158: getstatic     #13                 // Field ic0:Lorg/apache/hadoop/hbase/IndividualBytesFieldCell;
     161: invokevirtual #22                 // Method org/apache/hadoop/hbase/IndividualBytesFieldCell.getTagsArray:()[B
     164: aload         4
     166: if_acmpne     173
     169: iconst_1
     170: goto          174
     173: iconst_0
     174: invokestatic  #18                 // Method org/junit/Assert.assertTrue:(Z)V
     177: lload         5
     179: getstatic     #13                 // Field ic0:Lorg/apache/hadoop/hbase/IndividualBytesFieldCell;
     182: invokevirtual #23                 // Method org/apache/hadoop/hbase/IndividualBytesFieldCell.getTimestamp:()J
     185: invokestatic  #24                 // Method org/junit/Assert.assertEquals:(JJ)V
     188: lload         7
     190: getstatic     #13                 // Field ic0:Lorg/apache/hadoop/hbase/IndividualBytesFieldCell;
     193: invokevirtual #25                 // Method org/apache/hadoop/hbase/IndividualBytesFieldCell.getSequenceId:()J
     196: invokestatic  #24                 // Method org/junit/Assert.assertEquals:(JJ)V
     199: aload         9
     201: invokevirtual #26                 // Method org/apache/hadoop/hbase/KeyValue$Type.getCode:()B
     204: i2l
     205: getstatic     #13                 // Field ic0:Lorg/apache/hadoop/hbase/IndividualBytesFieldCell;
     208: invokevirtual #27                 // Method org/apache/hadoop/hbase/IndividualBytesFieldCell.getTypeByte:()B
     211: i2l
     212: invokestatic  #24                 // Method org/junit/Assert.assertEquals:(JJ)V
     215: lconst_0
     216: getstatic     #13                 // Field ic0:Lorg/apache/hadoop/hbase/IndividualBytesFieldCell;
     219: invokevirtual #28                 // Method org/apache/hadoop/hbase/IndividualBytesFieldCell.getRowOffset:()I
     222: i2l
     223: invokestatic  #24                 // Method org/junit/Assert.assertEquals:(JJ)V
     226: lconst_0
     227: getstatic     #13                 // Field ic0:Lorg/apache/hadoop/hbase/IndividualBytesFieldCell;
     230: invokevirtual #29                 // Method org/apache/hadoop/hbase/IndividualBytesFieldCell.getFamilyOffset:()I
     233: i2l
     234: invokestatic  #24                 // Method org/junit/Assert.assertEquals:(JJ)V
     237: lconst_0
     238: getstatic     #13                 // Field ic0:Lorg/apache/hadoop/hbase/IndividualBytesFieldCell;
     241: invokevirtual #30                 // Method org/apache/hadoop/hbase/IndividualBytesFieldCell.getQualifierOffset:()I
     244: i2l
     245: invokestatic  #24                 // Method org/junit/Assert.assertEquals:(JJ)V
     248: lconst_0
     249: getstatic     #13                 // Field ic0:Lorg/apache/hadoop/hbase/IndividualBytesFieldCell;
     252: invokevirtual #31                 // Method org/apache/hadoop/hbase/IndividualBytesFieldCell.getValueOffset:()I
     255: i2l
     256: invokestatic  #24                 // Method org/junit/Assert.assertEquals:(JJ)V
     259: lconst_0
     260: getstatic     #13                 // Field ic0:Lorg/apache/hadoop/hbase/IndividualBytesFieldCell;
     263: invokevirtual #32                 // Method org/apache/hadoop/hbase/IndividualBytesFieldCell.getTagsOffset:()I
     266: i2l
     267: invokestatic  #24                 // Method org/junit/Assert.assertEquals:(JJ)V
     270: return

  public void testClone() throws java.lang.CloneNotSupportedException;
    Code:
       0: getstatic     #13                 // Field ic0:Lorg/apache/hadoop/hbase/IndividualBytesFieldCell;
       3: invokevirtual #33                 // Method org/apache/hadoop/hbase/IndividualBytesFieldCell.clone:()Ljava/lang/Object;
       6: checkcast     #11                 // class org/apache/hadoop/hbase/IndividualBytesFieldCell
       9: astore_1
      10: aload_1
      11: invokevirtual #17                 // Method org/apache/hadoop/hbase/IndividualBytesFieldCell.getRowArray:()[B
      14: getstatic     #13                 // Field ic0:Lorg/apache/hadoop/hbase/IndividualBytesFieldCell;
      17: invokevirtual #17                 // Method org/apache/hadoop/hbase/IndividualBytesFieldCell.getRowArray:()[B
      20: if_acmpne     27
      23: iconst_1
      24: goto          28
      27: iconst_0
      28: invokestatic  #18                 // Method org/junit/Assert.assertTrue:(Z)V
      31: aload_1
      32: invokevirtual #19                 // Method org/apache/hadoop/hbase/IndividualBytesFieldCell.getFamilyArray:()[B
      35: getstatic     #13                 // Field ic0:Lorg/apache/hadoop/hbase/IndividualBytesFieldCell;
      38: invokevirtual #19                 // Method org/apache/hadoop/hbase/IndividualBytesFieldCell.getFamilyArray:()[B
      41: if_acmpne     48
      44: iconst_1
      45: goto          49
      48: iconst_0
      49: invokestatic  #18                 // Method org/junit/Assert.assertTrue:(Z)V
      52: aload_1
      53: invokevirtual #20                 // Method org/apache/hadoop/hbase/IndividualBytesFieldCell.getQualifierArray:()[B
      56: getstatic     #13                 // Field ic0:Lorg/apache/hadoop/hbase/IndividualBytesFieldCell;
      59: invokevirtual #20                 // Method org/apache/hadoop/hbase/IndividualBytesFieldCell.getQualifierArray:()[B
      62: if_acmpne     69
      65: iconst_1
      66: goto          70
      69: iconst_0
      70: invokestatic  #18                 // Method org/junit/Assert.assertTrue:(Z)V
      73: aload_1
      74: invokevirtual #21                 // Method org/apache/hadoop/hbase/IndividualBytesFieldCell.getValueArray:()[B
      77: getstatic     #13                 // Field ic0:Lorg/apache/hadoop/hbase/IndividualBytesFieldCell;
      80: invokevirtual #21                 // Method org/apache/hadoop/hbase/IndividualBytesFieldCell.getValueArray:()[B
      83: if_acmpne     90
      86: iconst_1
      87: goto          91
      90: iconst_0
      91: invokestatic  #18                 // Method org/junit/Assert.assertTrue:(Z)V
      94: aload_1
      95: invokevirtual #22                 // Method org/apache/hadoop/hbase/IndividualBytesFieldCell.getTagsArray:()[B
      98: getstatic     #13                 // Field ic0:Lorg/apache/hadoop/hbase/IndividualBytesFieldCell;
     101: invokevirtual #22                 // Method org/apache/hadoop/hbase/IndividualBytesFieldCell.getTagsArray:()[B
     104: if_acmpne     111
     107: iconst_1
     108: goto          112
     111: iconst_0
     112: invokestatic  #18                 // Method org/junit/Assert.assertTrue:(Z)V
     115: getstatic     #13                 // Field ic0:Lorg/apache/hadoop/hbase/IndividualBytesFieldCell;
     118: invokevirtual #34                 // Method org/apache/hadoop/hbase/IndividualBytesFieldCell.deepClone:()Lorg/apache/hadoop/hbase/ExtendedCell;
     121: instanceof    #14                 // class org/apache/hadoop/hbase/KeyValue
     124: invokestatic  #18                 // Method org/junit/Assert.assertTrue:(Z)V
     127: return

  public void testWriteIntoKeyValueFormat() throws java.io.IOException;
    Code:
       0: getstatic     #16                 // Field kv0:Lorg/apache/hadoop/hbase/KeyValue;
       3: iconst_1
       4: invokevirtual #35                 // Method org/apache/hadoop/hbase/KeyValue.getSerializedSize:(Z)I
       7: i2l
       8: getstatic     #13                 // Field ic0:Lorg/apache/hadoop/hbase/IndividualBytesFieldCell;
      11: iconst_1
      12: invokevirtual #36                 // Method org/apache/hadoop/hbase/IndividualBytesFieldCell.getSerializedSize:(Z)I
      15: i2l
      16: invokestatic  #24                 // Method org/junit/Assert.assertEquals:(JJ)V
      19: getstatic     #16                 // Field kv0:Lorg/apache/hadoop/hbase/KeyValue;
      22: iconst_0
      23: invokevirtual #35                 // Method org/apache/hadoop/hbase/KeyValue.getSerializedSize:(Z)I
      26: i2l
      27: getstatic     #13                 // Field ic0:Lorg/apache/hadoop/hbase/IndividualBytesFieldCell;
      30: iconst_0
      31: invokevirtual #36                 // Method org/apache/hadoop/hbase/IndividualBytesFieldCell.getSerializedSize:(Z)I
      34: i2l
      35: invokestatic  #24                 // Method org/junit/Assert.assertEquals:(JJ)V
      38: getstatic     #13                 // Field ic0:Lorg/apache/hadoop/hbase/IndividualBytesFieldCell;
      41: iconst_1
      42: invokevirtual #36                 // Method org/apache/hadoop/hbase/IndividualBytesFieldCell.getSerializedSize:(Z)I
      45: invokestatic  #37                 // Method java/nio/ByteBuffer.allocate:(I)Ljava/nio/ByteBuffer;
      48: astore_1
      49: getstatic     #13                 // Field ic0:Lorg/apache/hadoop/hbase/IndividualBytesFieldCell;
      52: aload_1
      53: iconst_0
      54: invokevirtual #38                 // Method org/apache/hadoop/hbase/IndividualBytesFieldCell.write:(Ljava/nio/ByteBuffer;I)V
      57: getstatic     #16                 // Field kv0:Lorg/apache/hadoop/hbase/KeyValue;
      60: iconst_1
      61: invokevirtual #35                 // Method org/apache/hadoop/hbase/KeyValue.getSerializedSize:(Z)I
      64: invokestatic  #37                 // Method java/nio/ByteBuffer.allocate:(I)Ljava/nio/ByteBuffer;
      67: astore_2
      68: getstatic     #16                 // Field kv0:Lorg/apache/hadoop/hbase/KeyValue;
      71: aload_2
      72: iconst_0
      73: invokevirtual #39                 // Method org/apache/hadoop/hbase/KeyValue.write:(Ljava/nio/ByteBuffer;I)V
      76: aload_1
      77: aload_2
      78: invokevirtual #40                 // Method java/nio/ByteBuffer.equals:(Ljava/lang/Object;)Z
      81: invokestatic  #18                 // Method org/junit/Assert.assertTrue:(Z)V
      84: aload_0
      85: getstatic     #13                 // Field ic0:Lorg/apache/hadoop/hbase/IndividualBytesFieldCell;
      88: getstatic     #16                 // Field kv0:Lorg/apache/hadoop/hbase/KeyValue;
      91: iconst_1
      92: invokespecial #41                 // Method testWriteIntoOutputStream:(Lorg/apache/hadoop/hbase/IndividualBytesFieldCell;Lorg/apache/hadoop/hbase/KeyValue;Z)V
      95: aload_0
      96: getstatic     #13                 // Field ic0:Lorg/apache/hadoop/hbase/IndividualBytesFieldCell;
      99: getstatic     #16                 // Field kv0:Lorg/apache/hadoop/hbase/KeyValue;
     102: iconst_0
     103: invokespecial #41                 // Method testWriteIntoOutputStream:(Lorg/apache/hadoop/hbase/IndividualBytesFieldCell;Lorg/apache/hadoop/hbase/KeyValue;Z)V
     106: return

  public void testNullFamilyQualifierValueTags();
    Code:
       0: ldc           #48                 // String row1
       2: invokestatic  #3                  // Method org/apache/hadoop/hbase/util/Bytes.toBytes:(Ljava/lang/String;)[B
       5: astore_1
       6: ldc2_w        #8                  // long 5000l
       9: lstore_2
      10: lconst_0
      11: lstore        4
      13: getstatic     #10                 // Field org/apache/hadoop/hbase/KeyValue$Type.Put:Lorg/apache/hadoop/hbase/KeyValue$Type;
      16: astore        6
      18: aconst_null
      19: astore        7
      21: aconst_null
      22: astore        8
      24: aconst_null
      25: astore        9
      27: aconst_null
      28: astore        10
      30: new           #11                 // class org/apache/hadoop/hbase/IndividualBytesFieldCell
      33: dup
      34: aload_1
      35: aload         7
      37: aload         8
      39: lload_2
      40: aload         6
      42: lload         4
      44: aload         9
      46: aload         10
      48: invokespecial #12                 // Method org/apache/hadoop/hbase/IndividualBytesFieldCell."<init>":([B[B[BJLorg/apache/hadoop/hbase/KeyValue$Type;J[B[B)V
      51: astore        11
      53: new           #14                 // class org/apache/hadoop/hbase/KeyValue
      56: dup
      57: aload_1
      58: aload         7
      60: aload         8
      62: lload_2
      63: aload         6
      65: aload         9
      67: aload         10
      69: invokespecial #15                 // Method org/apache/hadoop/hbase/KeyValue."<init>":([B[B[BJLorg/apache/hadoop/hbase/KeyValue$Type;[B[B)V
      72: astore        12
      74: aload         12
      76: invokeinterface #49,  1           // InterfaceMethod org/apache/hadoop/hbase/Cell.getFamilyArray:()[B
      81: aload         12
      83: invokeinterface #50,  1           // InterfaceMethod org/apache/hadoop/hbase/Cell.getFamilyOffset:()I
      88: aload         12
      90: invokeinterface #51,  1           // InterfaceMethod org/apache/hadoop/hbase/Cell.getFamilyLength:()B
      95: invokestatic  #52                 // Method org/apache/hadoop/hbase/util/Bytes.copy:([BII)[B
      98: astore        13
     100: aload         12
     102: invokeinterface #53,  1           // InterfaceMethod org/apache/hadoop/hbase/Cell.getQualifierArray:()[B
     107: aload         12
     109: invokeinterface #54,  1           // InterfaceMethod org/apache/hadoop/hbase/Cell.getQualifierOffset:()I
     114: aload         12
     116: invokeinterface #55,  1           // InterfaceMethod org/apache/hadoop/hbase/Cell.getQualifierLength:()I
     121: invokestatic  #52                 // Method org/apache/hadoop/hbase/util/Bytes.copy:([BII)[B
     124: astore        14
     126: aload         12
     128: invokeinterface #56,  1           // InterfaceMethod org/apache/hadoop/hbase/Cell.getValueArray:()[B
     133: aload         12
     135: invokeinterface #57,  1           // InterfaceMethod org/apache/hadoop/hbase/Cell.getValueOffset:()I
     140: aload         12
     142: invokeinterface #58,  1           // InterfaceMethod org/apache/hadoop/hbase/Cell.getValueLength:()I
     147: invokestatic  #52                 // Method org/apache/hadoop/hbase/util/Bytes.copy:([BII)[B
     150: astore        15
     152: aload         12
     154: invokeinterface #59,  1           // InterfaceMethod org/apache/hadoop/hbase/Cell.getTagsArray:()[B
     159: aload         12
     161: invokeinterface #60,  1           // InterfaceMethod org/apache/hadoop/hbase/Cell.getTagsOffset:()I
     166: aload         12
     168: invokeinterface #61,  1           // InterfaceMethod org/apache/hadoop/hbase/Cell.getTagsLength:()I
     173: invokestatic  #52                 // Method org/apache/hadoop/hbase/util/Bytes.copy:([BII)[B
     176: astore        16
     178: aload         13
     180: aload         11
     182: invokeinterface #49,  1           // InterfaceMethod org/apache/hadoop/hbase/Cell.getFamilyArray:()[B
     187: invokestatic  #47                 // Method org/junit/Assert.assertArrayEquals:([B[B)V
     190: aload         14
     192: aload         11
     194: invokeinterface #53,  1           // InterfaceMethod org/apache/hadoop/hbase/Cell.getQualifierArray:()[B
     199: invokestatic  #47                 // Method org/junit/Assert.assertArrayEquals:([B[B)V
     202: aload         15
     204: aload         11
     206: invokeinterface #56,  1           // InterfaceMethod org/apache/hadoop/hbase/Cell.getValueArray:()[B
     211: invokestatic  #47                 // Method org/junit/Assert.assertArrayEquals:([B[B)V
     214: aload         16
     216: aload         11
     218: invokeinterface #59,  1           // InterfaceMethod org/apache/hadoop/hbase/Cell.getTagsArray:()[B
     223: invokestatic  #47                 // Method org/junit/Assert.assertArrayEquals:([B[B)V
     226: aload         12
     228: invokeinterface #51,  1           // InterfaceMethod org/apache/hadoop/hbase/Cell.getFamilyLength:()B
     233: i2l
     234: aload         11
     236: invokeinterface #51,  1           // InterfaceMethod org/apache/hadoop/hbase/Cell.getFamilyLength:()B
     241: i2l
     242: invokestatic  #24                 // Method org/junit/Assert.assertEquals:(JJ)V
     245: aload         12
     247: invokeinterface #55,  1           // InterfaceMethod org/apache/hadoop/hbase/Cell.getQualifierLength:()I
     252: i2l
     253: aload         11
     255: invokeinterface #55,  1           // InterfaceMethod org/apache/hadoop/hbase/Cell.getQualifierLength:()I
     260: i2l
     261: invokestatic  #24                 // Method org/junit/Assert.assertEquals:(JJ)V
     264: aload         12
     266: invokeinterface #58,  1           // InterfaceMethod org/apache/hadoop/hbase/Cell.getValueLength:()I
     271: i2l
     272: aload         11
     274: invokeinterface #58,  1           // InterfaceMethod org/apache/hadoop/hbase/Cell.getValueLength:()I
     279: i2l
     280: invokestatic  #24                 // Method org/junit/Assert.assertEquals:(JJ)V
     283: aload         12
     285: invokeinterface #61,  1           // InterfaceMethod org/apache/hadoop/hbase/Cell.getTagsLength:()I
     290: i2l
     291: aload         11
     293: invokeinterface #61,  1           // InterfaceMethod org/apache/hadoop/hbase/Cell.getTagsLength:()I
     298: i2l
     299: invokestatic  #24                 // Method org/junit/Assert.assertEquals:(JJ)V
     302: return

  public void testIfExtendedCellImplemented();
    Code:
       0: getstatic     #13                 // Field ic0:Lorg/apache/hadoop/hbase/IndividualBytesFieldCell;
       3: instanceof    #62                 // class org/apache/hadoop/hbase/ExtendedCell
       6: invokestatic  #18                 // Method org/junit/Assert.assertTrue:(Z)V
       9: return

  public void testIllegalRow();
    Code:
       0: new           #11                 // class org/apache/hadoop/hbase/IndividualBytesFieldCell
       3: dup
       4: ldc           #63                 // String row
       6: invokestatic  #3                  // Method org/apache/hadoop/hbase/util/Bytes.toBytes:(Ljava/lang/String;)[B
       9: iconst_0
      10: bipush        100
      12: getstatic     #64                 // Field org/apache/hadoop/hbase/HConstants.EMPTY_BYTE_ARRAY:[B
      15: iconst_0
      16: iconst_0
      17: getstatic     #64                 // Field org/apache/hadoop/hbase/HConstants.EMPTY_BYTE_ARRAY:[B
      20: iconst_0
      21: iconst_0
      22: lconst_0
      23: getstatic     #10                 // Field org/apache/hadoop/hbase/KeyValue$Type.Put:Lorg/apache/hadoop/hbase/KeyValue$Type;
      26: lconst_0
      27: getstatic     #64                 // Field org/apache/hadoop/hbase/HConstants.EMPTY_BYTE_ARRAY:[B
      30: iconst_0
      31: iconst_0
      32: getstatic     #64                 // Field org/apache/hadoop/hbase/HConstants.EMPTY_BYTE_ARRAY:[B
      35: iconst_0
      36: iconst_0
      37: invokespecial #65                 // Method org/apache/hadoop/hbase/IndividualBytesFieldCell."<init>":([BII[BII[BIIJLorg/apache/hadoop/hbase/KeyValue$Type;J[BII[BII)V
      40: pop
      41: return

  public void testIllegalFamily();
    Code:
       0: new           #11                 // class org/apache/hadoop/hbase/IndividualBytesFieldCell
       3: dup
       4: ldc           #63                 // String row
       6: invokestatic  #3                  // Method org/apache/hadoop/hbase/util/Bytes.toBytes:(Ljava/lang/String;)[B
       9: iconst_0
      10: iconst_3
      11: ldc           #66                 // String family
      13: invokestatic  #3                  // Method org/apache/hadoop/hbase/util/Bytes.toBytes:(Ljava/lang/String;)[B
      16: iconst_0
      17: bipush        100
      19: getstatic     #64                 // Field org/apache/hadoop/hbase/HConstants.EMPTY_BYTE_ARRAY:[B
      22: iconst_0
      23: iconst_0
      24: lconst_0
      25: getstatic     #10                 // Field org/apache/hadoop/hbase/KeyValue$Type.Put:Lorg/apache/hadoop/hbase/KeyValue$Type;
      28: lconst_0
      29: getstatic     #64                 // Field org/apache/hadoop/hbase/HConstants.EMPTY_BYTE_ARRAY:[B
      32: iconst_0
      33: iconst_0
      34: getstatic     #64                 // Field org/apache/hadoop/hbase/HConstants.EMPTY_BYTE_ARRAY:[B
      37: iconst_0
      38: iconst_0
      39: invokespecial #65                 // Method org/apache/hadoop/hbase/IndividualBytesFieldCell."<init>":([BII[BII[BIIJLorg/apache/hadoop/hbase/KeyValue$Type;J[BII[BII)V
      42: pop
      43: return

  public void testIllegalQualifier();
    Code:
       0: new           #11                 // class org/apache/hadoop/hbase/IndividualBytesFieldCell
       3: dup
       4: ldc           #63                 // String row
       6: invokestatic  #3                  // Method org/apache/hadoop/hbase/util/Bytes.toBytes:(Ljava/lang/String;)[B
       9: iconst_0
      10: iconst_3
      11: ldc           #66                 // String family
      13: invokestatic  #3                  // Method org/apache/hadoop/hbase/util/Bytes.toBytes:(Ljava/lang/String;)[B
      16: iconst_0
      17: bipush        6
      19: ldc           #67                 // String qualifier
      21: invokestatic  #3                  // Method org/apache/hadoop/hbase/util/Bytes.toBytes:(Ljava/lang/String;)[B
      24: iconst_0
      25: bipush        100
      27: lconst_0
      28: getstatic     #10                 // Field org/apache/hadoop/hbase/KeyValue$Type.Put:Lorg/apache/hadoop/hbase/KeyValue$Type;
      31: lconst_0
      32: getstatic     #64                 // Field org/apache/hadoop/hbase/HConstants.EMPTY_BYTE_ARRAY:[B
      35: iconst_0
      36: iconst_0
      37: getstatic     #64                 // Field org/apache/hadoop/hbase/HConstants.EMPTY_BYTE_ARRAY:[B
      40: iconst_0
      41: iconst_0
      42: invokespecial #65                 // Method org/apache/hadoop/hbase/IndividualBytesFieldCell."<init>":([BII[BII[BIIJLorg/apache/hadoop/hbase/KeyValue$Type;J[BII[BII)V
      45: pop
      46: return

  public void testIllegalTimestamp();
    Code:
       0: new           #11                 // class org/apache/hadoop/hbase/IndividualBytesFieldCell
       3: dup
       4: ldc           #63                 // String row
       6: invokestatic  #3                  // Method org/apache/hadoop/hbase/util/Bytes.toBytes:(Ljava/lang/String;)[B
       9: iconst_0
      10: iconst_3
      11: ldc           #66                 // String family
      13: invokestatic  #3                  // Method org/apache/hadoop/hbase/util/Bytes.toBytes:(Ljava/lang/String;)[B
      16: iconst_0
      17: bipush        6
      19: ldc           #67                 // String qualifier
      21: invokestatic  #3                  // Method org/apache/hadoop/hbase/util/Bytes.toBytes:(Ljava/lang/String;)[B
      24: iconst_0
      25: bipush        9
      27: ldc2_w        #68                 // long -100l
      30: getstatic     #10                 // Field org/apache/hadoop/hbase/KeyValue$Type.Put:Lorg/apache/hadoop/hbase/KeyValue$Type;
      33: lconst_0
      34: getstatic     #64                 // Field org/apache/hadoop/hbase/HConstants.EMPTY_BYTE_ARRAY:[B
      37: iconst_0
      38: iconst_0
      39: getstatic     #64                 // Field org/apache/hadoop/hbase/HConstants.EMPTY_BYTE_ARRAY:[B
      42: iconst_0
      43: iconst_0
      44: invokespecial #65                 // Method org/apache/hadoop/hbase/IndividualBytesFieldCell."<init>":([BII[BII[BIIJLorg/apache/hadoop/hbase/KeyValue$Type;J[BII[BII)V
      47: pop
      48: return

  public void testIllegalValue();
    Code:
       0: new           #11                 // class org/apache/hadoop/hbase/IndividualBytesFieldCell
       3: dup
       4: ldc           #63                 // String row
       6: invokestatic  #3                  // Method org/apache/hadoop/hbase/util/Bytes.toBytes:(Ljava/lang/String;)[B
       9: iconst_0
      10: iconst_3
      11: ldc           #66                 // String family
      13: invokestatic  #3                  // Method org/apache/hadoop/hbase/util/Bytes.toBytes:(Ljava/lang/String;)[B
      16: iconst_0
      17: bipush        6
      19: ldc           #67                 // String qualifier
      21: invokestatic  #3                  // Method org/apache/hadoop/hbase/util/Bytes.toBytes:(Ljava/lang/String;)[B
      24: iconst_0
      25: bipush        9
      27: lconst_0
      28: getstatic     #10                 // Field org/apache/hadoop/hbase/KeyValue$Type.Put:Lorg/apache/hadoop/hbase/KeyValue$Type;
      31: lconst_0
      32: ldc           #70                 // String value
      34: invokestatic  #3                  // Method org/apache/hadoop/hbase/util/Bytes.toBytes:(Ljava/lang/String;)[B
      37: iconst_0
      38: bipush        100
      40: getstatic     #64                 // Field org/apache/hadoop/hbase/HConstants.EMPTY_BYTE_ARRAY:[B
      43: iconst_0
      44: iconst_0
      45: invokespecial #65                 // Method org/apache/hadoop/hbase/IndividualBytesFieldCell."<init>":([BII[BII[BIIJLorg/apache/hadoop/hbase/KeyValue$Type;J[BII[BII)V
      48: pop
      49: return

  public void testIllegalTags();
    Code:
       0: new           #11                 // class org/apache/hadoop/hbase/IndividualBytesFieldCell
       3: dup
       4: ldc           #63                 // String row
       6: invokestatic  #3                  // Method org/apache/hadoop/hbase/util/Bytes.toBytes:(Ljava/lang/String;)[B
       9: iconst_0
      10: iconst_3
      11: ldc           #66                 // String family
      13: invokestatic  #3                  // Method org/apache/hadoop/hbase/util/Bytes.toBytes:(Ljava/lang/String;)[B
      16: iconst_0
      17: bipush        6
      19: ldc           #67                 // String qualifier
      21: invokestatic  #3                  // Method org/apache/hadoop/hbase/util/Bytes.toBytes:(Ljava/lang/String;)[B
      24: iconst_0
      25: bipush        9
      27: lconst_0
      28: getstatic     #10                 // Field org/apache/hadoop/hbase/KeyValue$Type.Put:Lorg/apache/hadoop/hbase/KeyValue$Type;
      31: lconst_0
      32: ldc           #70                 // String value
      34: invokestatic  #3                  // Method org/apache/hadoop/hbase/util/Bytes.toBytes:(Ljava/lang/String;)[B
      37: iconst_0
      38: iconst_5
      39: ldc           #71                 // String tags
      41: invokestatic  #3                  // Method org/apache/hadoop/hbase/util/Bytes.toBytes:(Ljava/lang/String;)[B
      44: iconst_0
      45: bipush        100
      47: invokespecial #65                 // Method org/apache/hadoop/hbase/IndividualBytesFieldCell."<init>":([BII[BII[BIIJLorg/apache/hadoop/hbase/KeyValue$Type;J[BII[BII)V
      50: pop
      51: return

  public void testWriteTag() throws java.io.IOException;
    Code:
       0: ldc           #72                 // String ---tags---
       2: invokestatic  #3                  // Method org/apache/hadoop/hbase/util/Bytes.toBytes:(Ljava/lang/String;)[B
       5: astore_1
       6: iconst_3
       7: istore_2
       8: iconst_4
       9: istore_3
      10: new           #11                 // class org/apache/hadoop/hbase/IndividualBytesFieldCell
      13: dup
      14: ldc           #63                 // String row
      16: invokestatic  #3                  // Method org/apache/hadoop/hbase/util/Bytes.toBytes:(Ljava/lang/String;)[B
      19: iconst_0
      20: iconst_3
      21: ldc           #66                 // String family
      23: invokestatic  #3                  // Method org/apache/hadoop/hbase/util/Bytes.toBytes:(Ljava/lang/String;)[B
      26: iconst_0
      27: bipush        6
      29: ldc           #67                 // String qualifier
      31: invokestatic  #3                  // Method org/apache/hadoop/hbase/util/Bytes.toBytes:(Ljava/lang/String;)[B
      34: iconst_0
      35: bipush        9
      37: lconst_0
      38: getstatic     #10                 // Field org/apache/hadoop/hbase/KeyValue$Type.Put:Lorg/apache/hadoop/hbase/KeyValue$Type;
      41: lconst_0
      42: ldc           #70                 // String value
      44: invokestatic  #3                  // Method org/apache/hadoop/hbase/util/Bytes.toBytes:(Ljava/lang/String;)[B
      47: iconst_0
      48: iconst_5
      49: aload_1
      50: iload_2
      51: iload_3
      52: invokespecial #65                 // Method org/apache/hadoop/hbase/IndividualBytesFieldCell."<init>":([BII[BII[BIIJLorg/apache/hadoop/hbase/KeyValue$Type;J[BII[BII)V
      55: astore        4
      57: new           #42                 // class org/apache/hadoop/hbase/io/ByteArrayOutputStream
      60: dup
      61: sipush        300
      64: invokespecial #43                 // Method org/apache/hadoop/hbase/io/ByteArrayOutputStream."<init>":(I)V
      67: astore        5
      69: aconst_null
      70: astore        6
      72: aload         4
      74: aload         5
      76: iconst_1
      77: invokevirtual #45                 // Method org/apache/hadoop/hbase/IndividualBytesFieldCell.write:(Ljava/io/OutputStream;Z)I
      80: pop
      81: aload         5
      83: invokevirtual #73                 // Method org/apache/hadoop/hbase/io/ByteArrayOutputStream.toByteArray:()[B
      86: astore        7
      88: aload         4
      90: iconst_1
      91: invokevirtual #36                 // Method org/apache/hadoop/hbase/IndividualBytesFieldCell.getSerializedSize:(Z)I
      94: i2l
      95: aload         7
      97: arraylength
      98: i2l
      99: invokestatic  #24                 // Method org/junit/Assert.assertEquals:(JJ)V
     102: aload         5
     104: ifnull        189
     107: aload         6
     109: ifnull        132
     112: aload         5
     114: invokevirtual #74                 // Method org/apache/hadoop/hbase/io/ByteArrayOutputStream.close:()V
     117: goto          189
     120: astore        7
     122: aload         6
     124: aload         7
     126: invokevirtual #76                 // Method java/lang/Throwable.addSuppressed:(Ljava/lang/Throwable;)V
     129: goto          189
     132: aload         5
     134: invokevirtual #74                 // Method org/apache/hadoop/hbase/io/ByteArrayOutputStream.close:()V
     137: goto          189
     140: astore        7
     142: aload         7
     144: astore        6
     146: aload         7
     148: athrow
     149: astore        8
     151: aload         5
     153: ifnull        186
     156: aload         6
     158: ifnull        181
     161: aload         5
     163: invokevirtual #74                 // Method org/apache/hadoop/hbase/io/ByteArrayOutputStream.close:()V
     166: goto          186
     169: astore        9
     171: aload         6
     173: aload         9
     175: invokevirtual #76                 // Method java/lang/Throwable.addSuppressed:(Ljava/lang/Throwable;)V
     178: goto          186
     181: aload         5
     183: invokevirtual #74                 // Method org/apache/hadoop/hbase/io/ByteArrayOutputStream.close:()V
     186: aload         8
     188: athrow
     189: return
    Exception table:
       from    to  target type
         112   117   120   Class java/lang/Throwable
          72   102   140   Class java/lang/Throwable
          72   102   149   any
         161   166   169   Class java/lang/Throwable
         140   151   149   any

  public void testWriteValue() throws java.io.IOException;
    Code:
       0: ldc           #77                 // String ---value---
       2: invokestatic  #3                  // Method org/apache/hadoop/hbase/util/Bytes.toBytes:(Ljava/lang/String;)[B
       5: astore_1
       6: iconst_3
       7: istore_2
       8: iconst_5
       9: istore_3
      10: new           #11                 // class org/apache/hadoop/hbase/IndividualBytesFieldCell
      13: dup
      14: ldc           #63                 // String row
      16: invokestatic  #3                  // Method org/apache/hadoop/hbase/util/Bytes.toBytes:(Ljava/lang/String;)[B
      19: iconst_0
      20: iconst_3
      21: ldc           #66                 // String family
      23: invokestatic  #3                  // Method org/apache/hadoop/hbase/util/Bytes.toBytes:(Ljava/lang/String;)[B
      26: iconst_0
      27: bipush        6
      29: ldc           #67                 // String qualifier
      31: invokestatic  #3                  // Method org/apache/hadoop/hbase/util/Bytes.toBytes:(Ljava/lang/String;)[B
      34: iconst_0
      35: bipush        9
      37: lconst_0
      38: getstatic     #10                 // Field org/apache/hadoop/hbase/KeyValue$Type.Put:Lorg/apache/hadoop/hbase/KeyValue$Type;
      41: lconst_0
      42: aload_1
      43: iload_2
      44: iload_3
      45: ldc           #70                 // String value
      47: invokestatic  #3                  // Method org/apache/hadoop/hbase/util/Bytes.toBytes:(Ljava/lang/String;)[B
      50: iconst_0
      51: iconst_5
      52: invokespecial #65                 // Method org/apache/hadoop/hbase/IndividualBytesFieldCell."<init>":([BII[BII[BIIJLorg/apache/hadoop/hbase/KeyValue$Type;J[BII[BII)V
      55: astore        4
      57: new           #42                 // class org/apache/hadoop/hbase/io/ByteArrayOutputStream
      60: dup
      61: sipush        300
      64: invokespecial #43                 // Method org/apache/hadoop/hbase/io/ByteArrayOutputStream."<init>":(I)V
      67: astore        5
      69: aconst_null
      70: astore        6
      72: aload         4
      74: aload         5
      76: iconst_1
      77: invokevirtual #45                 // Method org/apache/hadoop/hbase/IndividualBytesFieldCell.write:(Ljava/io/OutputStream;Z)I
      80: pop
      81: aload         5
      83: invokevirtual #73                 // Method org/apache/hadoop/hbase/io/ByteArrayOutputStream.toByteArray:()[B
      86: astore        7
      88: aload         4
      90: iconst_1
      91: invokevirtual #36                 // Method org/apache/hadoop/hbase/IndividualBytesFieldCell.getSerializedSize:(Z)I
      94: i2l
      95: aload         7
      97: arraylength
      98: i2l
      99: invokestatic  #24                 // Method org/junit/Assert.assertEquals:(JJ)V
     102: aload         5
     104: ifnull        189
     107: aload         6
     109: ifnull        132
     112: aload         5
     114: invokevirtual #74                 // Method org/apache/hadoop/hbase/io/ByteArrayOutputStream.close:()V
     117: goto          189
     120: astore        7
     122: aload         6
     124: aload         7
     126: invokevirtual #76                 // Method java/lang/Throwable.addSuppressed:(Ljava/lang/Throwable;)V
     129: goto          189
     132: aload         5
     134: invokevirtual #74                 // Method org/apache/hadoop/hbase/io/ByteArrayOutputStream.close:()V
     137: goto          189
     140: astore        7
     142: aload         7
     144: astore        6
     146: aload         7
     148: athrow
     149: astore        8
     151: aload         5
     153: ifnull        186
     156: aload         6
     158: ifnull        181
     161: aload         5
     163: invokevirtual #74                 // Method org/apache/hadoop/hbase/io/ByteArrayOutputStream.close:()V
     166: goto          186
     169: astore        9
     171: aload         6
     173: aload         9
     175: invokevirtual #76                 // Method java/lang/Throwable.addSuppressed:(Ljava/lang/Throwable;)V
     178: goto          186
     181: aload         5
     183: invokevirtual #74                 // Method org/apache/hadoop/hbase/io/ByteArrayOutputStream.close:()V
     186: aload         8
     188: athrow
     189: return
    Exception table:
       from    to  target type
         112   117   120   Class java/lang/Throwable
          72   102   140   Class java/lang/Throwable
          72   102   149   any
         161   166   169   Class java/lang/Throwable
         140   151   149   any

  static {};
    Code:
       0: ldc           #78                 // class org/apache/hadoop/hbase/TestIndividualBytesFieldCell
       2: invokestatic  #79                 // Method org/apache/hadoop/hbase/HBaseClassTestRule.forClass:(Ljava/lang/Class;)Lorg/apache/hadoop/hbase/HBaseClassTestRule;
       5: putstatic     #80                 // Field CLASS_RULE:Lorg/apache/hadoop/hbase/HBaseClassTestRule;
       8: aconst_null
       9: putstatic     #13                 // Field ic0:Lorg/apache/hadoop/hbase/IndividualBytesFieldCell;
      12: aconst_null
      13: putstatic     #16                 // Field kv0:Lorg/apache/hadoop/hbase/KeyValue;
      16: return
}
