Compiled from "TestZNodePaths.java"
public class org.apache.hadoop.hbase.zookeeper.TestZNodePaths {
  public static final org.apache.hadoop.hbase.HBaseClassTestRule CLASS_RULE;

  public org.apache.hadoop.hbase.zookeeper.TestZNodePaths();
    Code:
       0: aload_0
       1: invokespecial #1                  // Method java/lang/Object."<init>":()V
       4: return

  public void testIsClientReadable();
    Code:
       0: new           #2                  // class org/apache/hadoop/hbase/zookeeper/ZNodePaths
       3: dup
       4: invokestatic  #3                  // Method org/apache/hadoop/hbase/HBaseConfiguration.create:()Lorg/apache/hadoop/conf/Configuration;
       7: invokespecial #4                  // Method org/apache/hadoop/hbase/zookeeper/ZNodePaths."<init>":(Lorg/apache/hadoop/conf/Configuration;)V
      10: astore_1
      11: aload_1
      12: aload_1
      13: getfield      #5                  // Field org/apache/hadoop/hbase/zookeeper/ZNodePaths.baseZNode:Ljava/lang/String;
      16: invokevirtual #6                  // Method org/apache/hadoop/hbase/zookeeper/ZNodePaths.isClientReadable:(Ljava/lang/String;)Z
      19: invokestatic  #7                  // Method org/junit/Assert.assertTrue:(Z)V
      22: aload_1
      23: aload_1
      24: iconst_0
      25: invokevirtual #8                  // Method org/apache/hadoop/hbase/zookeeper/ZNodePaths.getZNodeForReplica:(I)Ljava/lang/String;
      28: invokevirtual #6                  // Method org/apache/hadoop/hbase/zookeeper/ZNodePaths.isClientReadable:(Ljava/lang/String;)Z
      31: invokestatic  #7                  // Method org/junit/Assert.assertTrue:(Z)V
      34: aload_1
      35: aload_1
      36: getfield      #9                  // Field org/apache/hadoop/hbase/zookeeper/ZNodePaths.masterAddressZNode:Ljava/lang/String;
      39: invokevirtual #6                  // Method org/apache/hadoop/hbase/zookeeper/ZNodePaths.isClientReadable:(Ljava/lang/String;)Z
      42: invokestatic  #7                  // Method org/junit/Assert.assertTrue:(Z)V
      45: aload_1
      46: aload_1
      47: getfield      #10                 // Field org/apache/hadoop/hbase/zookeeper/ZNodePaths.clusterIdZNode:Ljava/lang/String;
      50: invokevirtual #6                  // Method org/apache/hadoop/hbase/zookeeper/ZNodePaths.isClientReadable:(Ljava/lang/String;)Z
      53: invokestatic  #7                  // Method org/junit/Assert.assertTrue:(Z)V
      56: aload_1
      57: aload_1
      58: getfield      #11                 // Field org/apache/hadoop/hbase/zookeeper/ZNodePaths.tableZNode:Ljava/lang/String;
      61: invokevirtual #6                  // Method org/apache/hadoop/hbase/zookeeper/ZNodePaths.isClientReadable:(Ljava/lang/String;)Z
      64: invokestatic  #7                  // Method org/junit/Assert.assertTrue:(Z)V
      67: aload_1
      68: aload_1
      69: getfield      #11                 // Field org/apache/hadoop/hbase/zookeeper/ZNodePaths.tableZNode:Ljava/lang/String;
      72: ldc           #12                 // String foo
      74: invokestatic  #13                 // Method org/apache/hadoop/hbase/zookeeper/ZNodePaths.joinZNode:(Ljava/lang/String;Ljava/lang/String;)Ljava/lang/String;
      77: invokevirtual #6                  // Method org/apache/hadoop/hbase/zookeeper/ZNodePaths.isClientReadable:(Ljava/lang/String;)Z
      80: invokestatic  #7                  // Method org/junit/Assert.assertTrue:(Z)V
      83: aload_1
      84: aload_1
      85: getfield      #14                 // Field org/apache/hadoop/hbase/zookeeper/ZNodePaths.rsZNode:Ljava/lang/String;
      88: invokevirtual #6                  // Method org/apache/hadoop/hbase/zookeeper/ZNodePaths.isClientReadable:(Ljava/lang/String;)Z
      91: invokestatic  #7                  // Method org/junit/Assert.assertTrue:(Z)V
      94: aload_1
      95: aload_1
      96: getfield      #15                 // Field org/apache/hadoop/hbase/zookeeper/ZNodePaths.tableLockZNode:Ljava/lang/String;
      99: invokevirtual #6                  // Method org/apache/hadoop/hbase/zookeeper/ZNodePaths.isClientReadable:(Ljava/lang/String;)Z
     102: invokestatic  #16                 // Method org/junit/Assert.assertFalse:(Z)V
     105: aload_1
     106: aload_1
     107: getfield      #17                 // Field org/apache/hadoop/hbase/zookeeper/ZNodePaths.balancerZNode:Ljava/lang/String;
     110: invokevirtual #6                  // Method org/apache/hadoop/hbase/zookeeper/ZNodePaths.isClientReadable:(Ljava/lang/String;)Z
     113: invokestatic  #16                 // Method org/junit/Assert.assertFalse:(Z)V
     116: aload_1
     117: aload_1
     118: getfield      #18                 // Field org/apache/hadoop/hbase/zookeeper/ZNodePaths.regionNormalizerZNode:Ljava/lang/String;
     121: invokevirtual #6                  // Method org/apache/hadoop/hbase/zookeeper/ZNodePaths.isClientReadable:(Ljava/lang/String;)Z
     124: invokestatic  #16                 // Method org/junit/Assert.assertFalse:(Z)V
     127: aload_1
     128: aload_1
     129: getfield      #19                 // Field org/apache/hadoop/hbase/zookeeper/ZNodePaths.clusterStateZNode:Ljava/lang/String;
     132: invokevirtual #6                  // Method org/apache/hadoop/hbase/zookeeper/ZNodePaths.isClientReadable:(Ljava/lang/String;)Z
     135: invokestatic  #16                 // Method org/junit/Assert.assertFalse:(Z)V
     138: aload_1
     139: aload_1
     140: getfield      #20                 // Field org/apache/hadoop/hbase/zookeeper/ZNodePaths.drainingZNode:Ljava/lang/String;
     143: invokevirtual #6                  // Method org/apache/hadoop/hbase/zookeeper/ZNodePaths.isClientReadable:(Ljava/lang/String;)Z
     146: invokestatic  #16                 // Method org/junit/Assert.assertFalse:(Z)V
     149: aload_1
     150: aload_1
     151: getfield      #21                 // Field org/apache/hadoop/hbase/zookeeper/ZNodePaths.splitLogZNode:Ljava/lang/String;
     154: invokevirtual #6                  // Method org/apache/hadoop/hbase/zookeeper/ZNodePaths.isClientReadable:(Ljava/lang/String;)Z
     157: invokestatic  #16                 // Method org/junit/Assert.assertFalse:(Z)V
     160: aload_1
     161: aload_1
     162: getfield      #22                 // Field org/apache/hadoop/hbase/zookeeper/ZNodePaths.backupMasterAddressesZNode:Ljava/lang/String;
     165: invokevirtual #6                  // Method org/apache/hadoop/hbase/zookeeper/ZNodePaths.isClientReadable:(Ljava/lang/String;)Z
     168: invokestatic  #16                 // Method org/junit/Assert.assertFalse:(Z)V
     171: return

  static {};
    Code:
       0: ldc           #23                 // class org/apache/hadoop/hbase/zookeeper/TestZNodePaths
       2: invokestatic  #24                 // Method org/apache/hadoop/hbase/HBaseClassTestRule.forClass:(Ljava/lang/Class;)Lorg/apache/hadoop/hbase/HBaseClassTestRule;
       5: putstatic     #25                 // Field CLASS_RULE:Lorg/apache/hadoop/hbase/HBaseClassTestRule;
       8: return
}
