Compiled from "TestCompactingMemStore.java"
public class org.apache.hadoop.hbase.regionserver.TestCompactingMemStore$MyCompactingMemStore extends org.apache.hadoop.hbase.regionserver.CompactingMemStore {
  public org.apache.hadoop.hbase.regionserver.TestCompactingMemStore$MyCompactingMemStore(org.apache.hadoop.conf.Configuration, org.apache.hadoop.hbase.CellComparator, org.apache.hadoop.hbase.regionserver.HStore, org.apache.hadoop.hbase.regionserver.RegionServicesForStores, org.apache.hadoop.hbase.MemoryCompactionPolicy) throws java.io.IOException;
    Code:
       0: aload_0
       1: aload_1
       2: aload_2
       3: aload_3
       4: aload         4
       6: aload         5
       8: invokespecial #1                  // Method org/apache/hadoop/hbase/regionserver/CompactingMemStore."<init>":(Lorg/apache/hadoop/conf/Configuration;Lorg/apache/hadoop/hbase/CellComparator;Lorg/apache/hadoop/hbase/regionserver/HStore;Lorg/apache/hadoop/hbase/regionserver/RegionServicesForStores;Lorg/apache/hadoop/hbase/MemoryCompactionPolicy;)V
      11: return

  void disableCompaction();
    Code:
       0: aload_0
       1: getfield      #2                  // Field allowCompaction:Ljava/util/concurrent/atomic/AtomicBoolean;
       4: iconst_0
       5: invokevirtual #3                  // Method java/util/concurrent/atomic/AtomicBoolean.set:(Z)V
       8: return

  void enableCompaction();
    Code:
       0: aload_0
       1: getfield      #2                  // Field allowCompaction:Ljava/util/concurrent/atomic/AtomicBoolean;
       4: iconst_1
       5: invokevirtual #3                  // Method java/util/concurrent/atomic/AtomicBoolean.set:(Z)V
       8: return

  void initiateType(org.apache.hadoop.hbase.MemoryCompactionPolicy, org.apache.hadoop.conf.Configuration) throws org.apache.hadoop.hbase.exceptions.IllegalArgumentIOException;
    Code:
       0: aload_0
       1: getfield      #4                  // Field compactor:Lorg/apache/hadoop/hbase/regionserver/MemStoreCompactor;
       4: aload_1
       5: aload_2
       6: ldc           #5                  // String CF_TEST
       8: invokevirtual #6                  // Method org/apache/hadoop/hbase/regionserver/MemStoreCompactor.initiateCompactionStrategy:(Lorg/apache/hadoop/hbase/MemoryCompactionPolicy;Lorg/apache/hadoop/conf/Configuration;Ljava/lang/String;)V
      11: return
}
