Compiled from "TestReplicationEndpoint.java"
public class org.apache.hadoop.hbase.replication.TestReplicationEndpoint$EverythingPassesWALEntryFilter implements org.apache.hadoop.hbase.replication.WALEntryFilter {
  public org.apache.hadoop.hbase.replication.TestReplicationEndpoint$EverythingPassesWALEntryFilter();
    Code:
       0: aload_0
       1: invokespecial #1                  // Method java/lang/Object."<init>":()V
       4: return

  public org.apache.hadoop.hbase.wal.WAL$Entry filter(org.apache.hadoop.hbase.wal.WAL$Entry);
    Code:
       0: iconst_1
       1: putstatic     #2                  // Field passedEntry:Z
       4: aload_1
       5: areturn

  public static boolean hasPassedAnEntry();
    Code:
       0: getstatic     #2                  // Field passedEntry:Z
       3: ireturn

  static {};
    Code:
       0: iconst_0
       1: putstatic     #2                  // Field passedEntry:Z
       4: return
}
