Compiled from "TestFutureUtils.java"
public class org.apache.hadoop.hbase.util.TestFutureUtils {
  public static final org.apache.hadoop.hbase.HBaseClassTestRule CLASS_RULE;

  public org.apache.hadoop.hbase.util.TestFutureUtils();
    Code:
       0: aload_0
       1: invokespecial #1                  // Method java/lang/Object."<init>":()V
       4: return

  public void setUp();
    Code:
       0: aload_0
       1: iconst_1
       2: new           #2                  // class org/apache/hbase/thirdparty/com/google/common/util/concurrent/ThreadFactoryBuilder
       5: dup
       6: invokespecial #3                  // Method org/apache/hbase/thirdparty/com/google/common/util/concurrent/ThreadFactoryBuilder."<init>":()V
       9: iconst_1
      10: invokevirtual #4                  // Method org/apache/hbase/thirdparty/com/google/common/util/concurrent/ThreadFactoryBuilder.setDaemon:(Z)Lorg/apache/hbase/thirdparty/com/google/common/util/concurrent/ThreadFactoryBuilder;
      13: invokevirtual #5                  // Method org/apache/hbase/thirdparty/com/google/common/util/concurrent/ThreadFactoryBuilder.build:()Ljava/util/concurrent/ThreadFactory;
      16: invokestatic  #6                  // Method java/util/concurrent/Executors.newFixedThreadPool:(ILjava/util/concurrent/ThreadFactory;)Ljava/util/concurrent/ExecutorService;
      19: putfield      #7                  // Field executor:Ljava/util/concurrent/ExecutorService;
      22: return

  public void tearDown();
    Code:
       0: aload_0
       1: getfield      #7                  // Field executor:Ljava/util/concurrent/ExecutorService;
       4: invokeinterface #8,  1            // InterfaceMethod java/util/concurrent/ExecutorService.shutdownNow:()Ljava/util/List;
       9: pop
      10: return

  public void testRecordStackTrace() throws java.io.IOException;
    Code:
       0: new           #9                  // class java/util/concurrent/CompletableFuture
       3: dup
       4: invokespecial #10                 // Method java/util/concurrent/CompletableFuture."<init>":()V
       7: astore_1
       8: aload_0
       9: getfield      #7                  // Field executor:Ljava/util/concurrent/ExecutorService;
      12: aload_1
      13: invokedynamic #11,  0             // InvokeDynamic #0:run:(Ljava/util/concurrent/CompletableFuture;)Ljava/lang/Runnable;
      18: invokeinterface #12,  2           // InterfaceMethod java/util/concurrent/ExecutorService.execute:(Ljava/lang/Runnable;)V
      23: aload_1
      24: invokestatic  #13                 // Method org/apache/hadoop/hbase/util/FutureUtils.get:(Ljava/util/concurrent/Future;)Ljava/lang/Object;
      27: pop
      28: ldc           #14                 // String The future should have been completed exceptionally
      30: invokestatic  #15                 // Method org/junit/Assert.fail:(Ljava/lang/String;)V
      33: goto          138
      36: astore_2
      37: ldc           #17                 // String Inject error!
      39: aload_2
      40: invokevirtual #18                 // Method org/apache/hadoop/hbase/HBaseIOException.getMessage:()Ljava/lang/String;
      43: invokestatic  #19                 // Method org/junit/Assert.assertEquals:(Ljava/lang/Object;Ljava/lang/Object;)V
      46: aload_2
      47: invokevirtual #20                 // Method org/apache/hadoop/hbase/HBaseIOException.getStackTrace:()[Ljava/lang/StackTraceElement;
      50: astore_3
      51: aload_3
      52: iconst_0
      53: aaload
      54: invokevirtual #21                 // Method java/lang/StackTraceElement.toString:()Ljava/lang/String;
      57: ldc           #22                 // String java.lang.Thread.getStackTrace
      59: invokestatic  #23                 // Method org/hamcrest/CoreMatchers.startsWith:(Ljava/lang/String;)Lorg/hamcrest/Matcher;
      62: invokestatic  #24                 // Method org/junit/Assert.assertThat:(Ljava/lang/Object;Lorg/hamcrest/Matcher;)V
      65: aload_3
      66: iconst_1
      67: aaload
      68: invokevirtual #21                 // Method java/lang/StackTraceElement.toString:()Ljava/lang/String;
      71: ldc           #25                 // String org.apache.hadoop.hbase.util.FutureUtils.setStackTrace
      73: invokestatic  #23                 // Method org/hamcrest/CoreMatchers.startsWith:(Ljava/lang/String;)Lorg/hamcrest/Matcher;
      76: invokestatic  #24                 // Method org/junit/Assert.assertThat:(Ljava/lang/Object;Lorg/hamcrest/Matcher;)V
      79: aload_3
      80: iconst_2
      81: aaload
      82: invokevirtual #21                 // Method java/lang/StackTraceElement.toString:()Ljava/lang/String;
      85: ldc           #26                 // String org.apache.hadoop.hbase.util.FutureUtils.rethrow
      87: invokestatic  #23                 // Method org/hamcrest/CoreMatchers.startsWith:(Ljava/lang/String;)Lorg/hamcrest/Matcher;
      90: invokestatic  #24                 // Method org/junit/Assert.assertThat:(Ljava/lang/Object;Lorg/hamcrest/Matcher;)V
      93: aload_3
      94: iconst_3
      95: aaload
      96: invokevirtual #21                 // Method java/lang/StackTraceElement.toString:()Ljava/lang/String;
      99: ldc           #27                 // String org.apache.hadoop.hbase.util.FutureUtils.get
     101: invokestatic  #23                 // Method org/hamcrest/CoreMatchers.startsWith:(Ljava/lang/String;)Lorg/hamcrest/Matcher;
     104: invokestatic  #24                 // Method org/junit/Assert.assertThat:(Ljava/lang/Object;Lorg/hamcrest/Matcher;)V
     107: aload_3
     108: iconst_4
     109: aaload
     110: invokevirtual #21                 // Method java/lang/StackTraceElement.toString:()Ljava/lang/String;
     113: ldc           #28                 // String org.apache.hadoop.hbase.util.TestFutureUtils.testRecordStackTrace
     115: invokestatic  #23                 // Method org/hamcrest/CoreMatchers.startsWith:(Ljava/lang/String;)Lorg/hamcrest/Matcher;
     118: invokestatic  #24                 // Method org/junit/Assert.assertThat:(Ljava/lang/Object;Lorg/hamcrest/Matcher;)V
     121: aload_3
     122: invokestatic  #29                 // InterfaceMethod java/util/stream/Stream.of:([Ljava/lang/Object;)Ljava/util/stream/Stream;
     125: invokedynamic #30,  0             // InvokeDynamic #1:test:()Ljava/util/function/Predicate;
     130: invokeinterface #31,  2           // InterfaceMethod java/util/stream/Stream.anyMatch:(Ljava/util/function/Predicate;)Z
     135: invokestatic  #32                 // Method org/junit/Assert.assertTrue:(Z)V
     138: return
    Exception table:
       from    to  target type
          23    33    36   Class org/apache/hadoop/hbase/HBaseIOException

  static {};
    Code:
       0: ldc           #37                 // class org/apache/hadoop/hbase/util/TestFutureUtils
       2: invokestatic  #38                 // Method org/apache/hadoop/hbase/HBaseClassTestRule.forClass:(Ljava/lang/Class;)Lorg/apache/hadoop/hbase/HBaseClassTestRule;
       5: putstatic     #39                 // Field CLASS_RULE:Lorg/apache/hadoop/hbase/HBaseClassTestRule;
       8: return
}
