Compiled from "TestWithDisabledAuthorization.java"
class org.apache.hadoop.hbase.security.access.TestWithDisabledAuthorization$53 implements org.apache.hadoop.hbase.security.access.SecureTestUtil$AccessTestAction {
  final org.apache.hadoop.hbase.security.access.TestWithDisabledAuthorization this$0;

  org.apache.hadoop.hbase.security.access.TestWithDisabledAuthorization$53(org.apache.hadoop.hbase.security.access.TestWithDisabledAuthorization);
    Code:
       0: aload_0
       1: aload_1
       2: putfield      #1                  // Field this$0:Lorg/apache/hadoop/hbase/security/access/TestWithDisabledAuthorization;
       5: aload_0
       6: invokespecial #2                  // Method java/lang/Object."<init>":()V
       9: return

  public java.lang.Object run() throws java.lang.Exception;
    Code:
       0: invokestatic  #3                  // Method org/apache/hadoop/hbase/security/access/TestWithDisabledAuthorization.access$600:()Lorg/apache/hadoop/hbase/security/access/AccessController;
       3: aload_0
       4: getfield      #1                  // Field this$0:Lorg/apache/hadoop/hbase/security/access/TestWithDisabledAuthorization;
       7: invokestatic  #4                  // Method org/apache/hadoop/hbase/security/access/TestWithDisabledAuthorization.access$900:(Lorg/apache/hadoop/hbase/security/access/TestWithDisabledAuthorization;)Lorg/apache/hadoop/hbase/coprocessor/RegionCoprocessorEnvironment;
      10: invokestatic  #5                  // Method org/apache/hadoop/hbase/coprocessor/ObserverContextImpl.createAndPrepare:(Lorg/apache/hadoop/hbase/CoprocessorEnvironment;)Lorg/apache/hadoop/hbase/coprocessor/ObserverContext;
      13: invokestatic  #6                  // Method org/apache/hadoop/hbase/security/access/TestWithDisabledAuthorization.access$400:()[B
      16: invokestatic  #7                  // Method org/apache/hadoop/hbase/security/access/TestWithDisabledAuthorization.access$100:()[B
      19: invokestatic  #8                  // Method org/apache/hadoop/hbase/security/access/TestWithDisabledAuthorization.access$200:()[B
      22: getstatic     #9                  // Field org/apache/hadoop/hbase/CompareOperator.EQUAL:Lorg/apache/hadoop/hbase/CompareOperator;
      25: new           #10                 // class org/apache/hadoop/hbase/filter/BinaryComparator
      28: dup
      29: ldc           #11                 // String foo
      31: invokestatic  #12                 // Method org/apache/hadoop/hbase/util/Bytes.toBytes:(Ljava/lang/String;)[B
      34: invokespecial #13                 // Method org/apache/hadoop/hbase/filter/BinaryComparator."<init>":([B)V
      37: new           #14                 // class org/apache/hadoop/hbase/client/Delete
      40: dup
      41: invokestatic  #6                  // Method org/apache/hadoop/hbase/security/access/TestWithDisabledAuthorization.access$400:()[B
      44: invokespecial #15                 // Method org/apache/hadoop/hbase/client/Delete."<init>":([B)V
      47: iconst_1
      48: invokevirtual #16                 // Method org/apache/hadoop/hbase/security/access/AccessController.preCheckAndDelete:(Lorg/apache/hadoop/hbase/coprocessor/ObserverContext;[B[B[BLorg/apache/hadoop/hbase/CompareOperator;Lorg/apache/hadoop/hbase/filter/ByteArrayComparable;Lorg/apache/hadoop/hbase/client/Delete;Z)Z
      51: pop
      52: aconst_null
      53: areturn
}
