Compiled from "TestSecureWALReplay.java"
public class org.apache.hadoop.hbase.regionserver.wal.TestSecureWALReplay extends org.apache.hadoop.hbase.regionserver.wal.TestWALReplay {
  public static final org.apache.hadoop.hbase.HBaseClassTestRule CLASS_RULE;

  public org.apache.hadoop.hbase.regionserver.wal.TestSecureWALReplay();
    Code:
       0: aload_0
       1: invokespecial #1                  // Method org/apache/hadoop/hbase/regionserver/wal/TestWALReplay."<init>":()V
       4: return

  public static void setUpBeforeClass() throws java.lang.Exception;
    Code:
       0: getstatic     #2                  // Field org/apache/hadoop/hbase/regionserver/wal/AbstractTestWALReplay.TEST_UTIL:Lorg/apache/hadoop/hbase/HBaseTestingUtility;
       3: invokevirtual #3                  // Method org/apache/hadoop/hbase/HBaseTestingUtility.getConfiguration:()Lorg/apache/hadoop/conf/Configuration;
       6: astore_0
       7: aload_0
       8: ldc           #5                  // String hbase.crypto.keyprovider
      10: ldc           #6                  // class org/apache/hadoop/hbase/io/crypto/KeyProviderForTesting
      12: invokevirtual #7                  // Method java/lang/Class.getName:()Ljava/lang/String;
      15: invokevirtual #8                  // Method org/apache/hadoop/conf/Configuration.set:(Ljava/lang/String;Ljava/lang/String;)V
      18: aload_0
      19: ldc           #9                  // String hbase.crypto.master.key.name
      21: ldc           #10                 // String hbase
      23: invokevirtual #8                  // Method org/apache/hadoop/conf/Configuration.set:(Ljava/lang/String;Ljava/lang/String;)V
      26: aload_0
      27: ldc           #11                 // String hbase.regionserver.hlog.reader.impl
      29: ldc           #12                 // class org/apache/hadoop/hbase/regionserver/wal/SecureProtobufLogReader
      31: ldc           #13                 // class org/apache/hadoop/hbase/wal/WAL$Reader
      33: invokevirtual #14                 // Method org/apache/hadoop/conf/Configuration.setClass:(Ljava/lang/String;Ljava/lang/Class;Ljava/lang/Class;)V
      36: aload_0
      37: ldc           #15                 // String hbase.regionserver.hlog.writer.impl
      39: ldc           #16                 // class org/apache/hadoop/hbase/regionserver/wal/SecureProtobufLogWriter
      41: ldc           #17                 // class org/apache/hadoop/hbase/wal/WALProvider$Writer
      43: invokevirtual #14                 // Method org/apache/hadoop/conf/Configuration.setClass:(Ljava/lang/String;Ljava/lang/Class;Ljava/lang/Class;)V
      46: aload_0
      47: ldc           #18                 // String hbase.regionserver.wal.encryption
      49: iconst_1
      50: invokevirtual #19                 // Method org/apache/hadoop/conf/Configuration.setBoolean:(Ljava/lang/String;Z)V
      53: invokestatic  #20                 // Method org/apache/hadoop/hbase/regionserver/wal/AbstractTestWALReplay.setUpBeforeClass:()V
      56: return

  static {};
    Code:
       0: ldc           #21                 // class org/apache/hadoop/hbase/regionserver/wal/TestSecureWALReplay
       2: invokestatic  #22                 // Method org/apache/hadoop/hbase/HBaseClassTestRule.forClass:(Ljava/lang/Class;)Lorg/apache/hadoop/hbase/HBaseClassTestRule;
       5: putstatic     #23                 // Field CLASS_RULE:Lorg/apache/hadoop/hbase/HBaseClassTestRule;
       8: return
}
