Compiled from "TestMasterFifoRpcScheduler.java"
class org.apache.hadoop.hbase.ipc.TestMasterFifoRpcScheduler$1 implements org.mockito.stubbing.Answer<java.lang.Void> {
  final java.util.concurrent.atomic.AtomicInteger val$callExecutionCount;

  final org.apache.hadoop.hbase.ipc.TestMasterFifoRpcScheduler this$0;

  org.apache.hadoop.hbase.ipc.TestMasterFifoRpcScheduler$1(org.apache.hadoop.hbase.ipc.TestMasterFifoRpcScheduler, java.util.concurrent.atomic.AtomicInteger);
    Code:
       0: aload_0
       1: aload_1
       2: putfield      #1                  // Field this$0:Lorg/apache/hadoop/hbase/ipc/TestMasterFifoRpcScheduler;
       5: aload_0
       6: aload_2
       7: putfield      #2                  // Field val$callExecutionCount:Ljava/util/concurrent/atomic/AtomicInteger;
      10: aload_0
      11: invokespecial #3                  // Method java/lang/Object."<init>":()V
      14: return

  public java.lang.Void answer(org.mockito.invocation.InvocationOnMock) throws java.lang.Throwable;
    Code:
       0: aload_0
       1: getfield      #2                  // Field val$callExecutionCount:Ljava/util/concurrent/atomic/AtomicInteger;
       4: invokevirtual #4                  // Method java/util/concurrent/atomic/AtomicInteger.incrementAndGet:()I
       7: pop
       8: ldc2_w        #5                  // long 1000l
      11: invokestatic  #7                  // Method java/lang/Thread.sleep:(J)V
      14: aconst_null
      15: areturn

  public java.lang.Object answer(org.mockito.invocation.InvocationOnMock) throws java.lang.Throwable;
    Code:
       0: aload_0
       1: aload_1
       2: invokevirtual #8                  // Method answer:(Lorg/mockito/invocation/InvocationOnMock;)Ljava/lang/Void;
       5: areturn
}
