Compiled from "TestSyncReplicationMoreLogsInLocalCopyToRemote.java"
public class org.apache.hadoop.hbase.replication.TestSyncReplicationMoreLogsInLocalCopyToRemote extends org.apache.hadoop.hbase.replication.SyncReplicationTestBase {
  public static final org.apache.hadoop.hbase.HBaseClassTestRule CLASS_RULE;

  public org.apache.hadoop.hbase.replication.TestSyncReplicationMoreLogsInLocalCopyToRemote();
    Code:
       0: aload_0
       1: invokespecial #1                  // Method org/apache/hadoop/hbase/replication/SyncReplicationTestBase."<init>":()V
       4: return

  public static void setUp() throws java.lang.Exception;
    Code:
       0: getstatic     #2                  // Field UTIL1:Lorg/apache/hadoop/hbase/HBaseTestingUtility;
       3: invokevirtual #3                  // Method org/apache/hadoop/hbase/HBaseTestingUtility.getConfiguration:()Lorg/apache/hadoop/conf/Configuration;
       6: ldc           #5                  // String hbase.wal.sync.impl
       8: ldc           #6                  // class org/apache/hadoop/hbase/replication/DualAsyncFSWALForTest
      10: ldc           #7                  // class org/apache/hadoop/hbase/regionserver/wal/DualAsyncFSWAL
      12: invokevirtual #8                  // Method org/apache/hadoop/conf/Configuration.setClass:(Ljava/lang/String;Ljava/lang/Class;Ljava/lang/Class;)V
      15: getstatic     #9                  // Field UTIL2:Lorg/apache/hadoop/hbase/HBaseTestingUtility;
      18: invokevirtual #3                  // Method org/apache/hadoop/hbase/HBaseTestingUtility.getConfiguration:()Lorg/apache/hadoop/conf/Configuration;
      21: ldc           #5                  // String hbase.wal.sync.impl
      23: ldc           #6                  // class org/apache/hadoop/hbase/replication/DualAsyncFSWALForTest
      25: ldc           #7                  // class org/apache/hadoop/hbase/regionserver/wal/DualAsyncFSWAL
      27: invokevirtual #8                  // Method org/apache/hadoop/conf/Configuration.setClass:(Ljava/lang/String;Ljava/lang/Class;Ljava/lang/Class;)V
      30: invokestatic  #10                 // Method org/apache/hadoop/hbase/replication/SyncReplicationTestBase.setUp:()V
      33: return

  public void testSplitLog() throws java.lang.Exception;
    Code:
       0: getstatic     #2                  // Field UTIL1:Lorg/apache/hadoop/hbase/HBaseTestingUtility;
       3: invokevirtual #11                 // Method org/apache/hadoop/hbase/HBaseTestingUtility.getAdmin:()Lorg/apache/hadoop/hbase/client/Admin;
       6: getstatic     #12                 // Field PEER_ID:Ljava/lang/String;
       9: invokeinterface #13,  2           // InterfaceMethod org/apache/hadoop/hbase/client/Admin.disableReplicationPeer:(Ljava/lang/String;)V
      14: getstatic     #9                  // Field UTIL2:Lorg/apache/hadoop/hbase/HBaseTestingUtility;
      17: invokevirtual #11                 // Method org/apache/hadoop/hbase/HBaseTestingUtility.getAdmin:()Lorg/apache/hadoop/hbase/client/Admin;
      20: getstatic     #12                 // Field PEER_ID:Ljava/lang/String;
      23: getstatic     #14                 // Field org/apache/hadoop/hbase/replication/SyncReplicationState.STANDBY:Lorg/apache/hadoop/hbase/replication/SyncReplicationState;
      26: invokeinterface #15,  3           // InterfaceMethod org/apache/hadoop/hbase/client/Admin.transitReplicationPeerSyncReplicationState:(Ljava/lang/String;Lorg/apache/hadoop/hbase/replication/SyncReplicationState;)V
      31: getstatic     #2                  // Field UTIL1:Lorg/apache/hadoop/hbase/HBaseTestingUtility;
      34: invokevirtual #11                 // Method org/apache/hadoop/hbase/HBaseTestingUtility.getAdmin:()Lorg/apache/hadoop/hbase/client/Admin;
      37: getstatic     #12                 // Field PEER_ID:Ljava/lang/String;
      40: getstatic     #16                 // Field org/apache/hadoop/hbase/replication/SyncReplicationState.ACTIVE:Lorg/apache/hadoop/hbase/replication/SyncReplicationState;
      43: invokeinterface #15,  3           // InterfaceMethod org/apache/hadoop/hbase/client/Admin.transitReplicationPeerSyncReplicationState:(Ljava/lang/String;Lorg/apache/hadoop/hbase/replication/SyncReplicationState;)V
      48: getstatic     #2                  // Field UTIL1:Lorg/apache/hadoop/hbase/HBaseTestingUtility;
      51: getstatic     #17                 // Field TABLE_NAME:Lorg/apache/hadoop/hbase/TableName;
      54: invokevirtual #18                 // Method org/apache/hadoop/hbase/HBaseTestingUtility.getRSForFirstRegionInTable:(Lorg/apache/hadoop/hbase/TableName;)Lorg/apache/hadoop/hbase/regionserver/HRegionServer;
      57: astore_1
      58: aload_1
      59: getstatic     #17                 // Field TABLE_NAME:Lorg/apache/hadoop/hbase/TableName;
      62: invokestatic  #19                 // Method org/apache/hadoop/hbase/client/RegionInfoBuilder.newBuilder:(Lorg/apache/hadoop/hbase/TableName;)Lorg/apache/hadoop/hbase/client/RegionInfoBuilder;
      65: invokevirtual #20                 // Method org/apache/hadoop/hbase/client/RegionInfoBuilder.build:()Lorg/apache/hadoop/hbase/client/RegionInfo;
      68: invokevirtual #21                 // Method org/apache/hadoop/hbase/regionserver/HRegionServer.getWAL:(Lorg/apache/hadoop/hbase/client/RegionInfo;)Lorg/apache/hadoop/hbase/wal/WAL;
      71: checkcast     #6                  // class org/apache/hadoop/hbase/replication/DualAsyncFSWALForTest
      74: astore_2
      75: aload_2
      76: invokevirtual #22                 // Method org/apache/hadoop/hbase/replication/DualAsyncFSWALForTest.setRemoteBroken:()V
      79: getstatic     #2                  // Field UTIL1:Lorg/apache/hadoop/hbase/HBaseTestingUtility;
      82: invokevirtual #3                  // Method org/apache/hadoop/hbase/HBaseTestingUtility.getConfiguration:()Lorg/apache/hadoop/conf/Configuration;
      85: invokestatic  #23                 // Method org/apache/hadoop/hbase/client/ConnectionFactory.createAsyncConnection:(Lorg/apache/hadoop/conf/Configuration;)Ljava/util/concurrent/CompletableFuture;
      88: invokevirtual #24                 // Method java/util/concurrent/CompletableFuture.get:()Ljava/lang/Object;
      91: checkcast     #25                 // class org/apache/hadoop/hbase/client/AsyncConnection
      94: astore_3
      95: aconst_null
      96: astore        4
      98: aload_3
      99: getstatic     #17                 // Field TABLE_NAME:Lorg/apache/hadoop/hbase/TableName;
     102: invokeinterface #26,  2           // InterfaceMethod org/apache/hadoop/hbase/client/AsyncConnection.getTableBuilder:(Lorg/apache/hadoop/hbase/TableName;)Lorg/apache/hadoop/hbase/client/AsyncTableBuilder;
     107: iconst_1
     108: invokeinterface #27,  2           // InterfaceMethod org/apache/hadoop/hbase/client/AsyncTableBuilder.setMaxAttempts:(I)Lorg/apache/hadoop/hbase/client/AsyncTableBuilder;
     113: invokeinterface #28,  1           // InterfaceMethod org/apache/hadoop/hbase/client/AsyncTableBuilder.build:()Lorg/apache/hadoop/hbase/client/AsyncTable;
     118: astore        5
     120: aload         5
     122: new           #29                 // class org/apache/hadoop/hbase/client/Put
     125: dup
     126: iconst_0
     127: invokestatic  #30                 // Method org/apache/hadoop/hbase/util/Bytes.toBytes:(I)[B
     130: invokespecial #31                 // Method org/apache/hadoop/hbase/client/Put."<init>":([B)V
     133: getstatic     #32                 // Field CF:[B
     136: getstatic     #33                 // Field CQ:[B
     139: iconst_0
     140: invokestatic  #30                 // Method org/apache/hadoop/hbase/util/Bytes.toBytes:(I)[B
     143: invokevirtual #34                 // Method org/apache/hadoop/hbase/client/Put.addColumn:([B[B[B)Lorg/apache/hadoop/hbase/client/Put;
     146: invokeinterface #35,  2           // InterfaceMethod org/apache/hadoop/hbase/client/AsyncTable.put:(Lorg/apache/hadoop/hbase/client/Put;)Ljava/util/concurrent/CompletableFuture;
     151: invokevirtual #24                 // Method java/util/concurrent/CompletableFuture.get:()Ljava/lang/Object;
     154: pop
     155: ldc           #36                 // String Should fail since the rs will crash and we will not retry
     157: invokestatic  #37                 // Method org/junit/Assert.fail:(Ljava/lang/String;)V
     160: goto          177
     163: astore        6
     165: getstatic     #39                 // Field LOG:Lorg/slf4j/Logger;
     168: ldc           #40                 // String Expected error:
     170: aload         6
     172: invokeinterface #41,  3           // InterfaceMethod org/slf4j/Logger.info:(Ljava/lang/String;Ljava/lang/Throwable;)V
     177: aload_3
     178: ifnull        266
     181: aload         4
     183: ifnull        207
     186: aload_3
     187: invokeinterface #42,  1           // InterfaceMethod org/apache/hadoop/hbase/client/AsyncConnection.close:()V
     192: goto          266
     195: astore        5
     197: aload         4
     199: aload         5
     201: invokevirtual #44                 // Method java/lang/Throwable.addSuppressed:(Ljava/lang/Throwable;)V
     204: goto          266
     207: aload_3
     208: invokeinterface #42,  1           // InterfaceMethod org/apache/hadoop/hbase/client/AsyncConnection.close:()V
     213: goto          266
     216: astore        5
     218: aload         5
     220: astore        4
     222: aload         5
     224: athrow
     225: astore        7
     227: aload_3
     228: ifnull        263
     231: aload         4
     233: ifnull        257
     236: aload_3
     237: invokeinterface #42,  1           // InterfaceMethod org/apache/hadoop/hbase/client/AsyncConnection.close:()V
     242: goto          263
     245: astore        8
     247: aload         4
     249: aload         8
     251: invokevirtual #44                 // Method java/lang/Throwable.addSuppressed:(Ljava/lang/Throwable;)V
     254: goto          263
     257: aload_3
     258: invokeinterface #42,  1           // InterfaceMethod org/apache/hadoop/hbase/client/AsyncConnection.close:()V
     263: aload         7
     265: athrow
     266: getstatic     #2                  // Field UTIL1:Lorg/apache/hadoop/hbase/HBaseTestingUtility;
     269: ldc2_w        #45                 // long 60000l
     272: new           #47                 // class org/apache/hadoop/hbase/replication/TestSyncReplicationMoreLogsInLocalCopyToRemote$1
     275: dup
     276: aload_0
     277: invokespecial #48                 // Method org/apache/hadoop/hbase/replication/TestSyncReplicationMoreLogsInLocalCopyToRemote$1."<init>":(Lorg/apache/hadoop/hbase/replication/TestSyncReplicationMoreLogsInLocalCopyToRemote;)V
     280: invokevirtual #49                 // Method org/apache/hadoop/hbase/HBaseTestingUtility.waitFor:(JLorg/apache/hadoop/hbase/Waiter$Predicate;)J
     283: pop2
     284: getstatic     #9                  // Field UTIL2:Lorg/apache/hadoop/hbase/HBaseTestingUtility;
     287: invokevirtual #11                 // Method org/apache/hadoop/hbase/HBaseTestingUtility.getAdmin:()Lorg/apache/hadoop/hbase/client/Admin;
     290: getstatic     #12                 // Field PEER_ID:Ljava/lang/String;
     293: getstatic     #50                 // Field org/apache/hadoop/hbase/replication/SyncReplicationState.DOWNGRADE_ACTIVE:Lorg/apache/hadoop/hbase/replication/SyncReplicationState;
     296: invokeinterface #15,  3           // InterfaceMethod org/apache/hadoop/hbase/client/Admin.transitReplicationPeerSyncReplicationState:(Ljava/lang/String;Lorg/apache/hadoop/hbase/replication/SyncReplicationState;)V
     301: getstatic     #9                  // Field UTIL2:Lorg/apache/hadoop/hbase/HBaseTestingUtility;
     304: invokevirtual #51                 // Method org/apache/hadoop/hbase/HBaseTestingUtility.getConnection:()Lorg/apache/hadoop/hbase/client/Connection;
     307: getstatic     #17                 // Field TABLE_NAME:Lorg/apache/hadoop/hbase/TableName;
     310: invokeinterface #52,  2           // InterfaceMethod org/apache/hadoop/hbase/client/Connection.getTable:(Lorg/apache/hadoop/hbase/TableName;)Lorg/apache/hadoop/hbase/client/Table;
     315: astore_3
     316: aconst_null
     317: astore        4
     319: lconst_0
     320: aload_3
     321: new           #53                 // class org/apache/hadoop/hbase/client/Get
     324: dup
     325: iconst_0
     326: invokestatic  #30                 // Method org/apache/hadoop/hbase/util/Bytes.toBytes:(I)[B
     329: invokespecial #54                 // Method org/apache/hadoop/hbase/client/Get."<init>":([B)V
     332: invokeinterface #55,  2           // InterfaceMethod org/apache/hadoop/hbase/client/Table.get:(Lorg/apache/hadoop/hbase/client/Get;)Lorg/apache/hadoop/hbase/client/Result;
     337: getstatic     #32                 // Field CF:[B
     340: getstatic     #33                 // Field CQ:[B
     343: invokevirtual #56                 // Method org/apache/hadoop/hbase/client/Result.getValue:([B[B)[B
     346: invokestatic  #57                 // Method org/apache/hadoop/hbase/util/Bytes.toInt:([B)I
     349: i2l
     350: invokestatic  #58                 // Method org/junit/Assert.assertEquals:(JJ)V
     353: aload_3
     354: ifnull        442
     357: aload         4
     359: ifnull        383
     362: aload_3
     363: invokeinterface #59,  1           // InterfaceMethod org/apache/hadoop/hbase/client/Table.close:()V
     368: goto          442
     371: astore        5
     373: aload         4
     375: aload         5
     377: invokevirtual #44                 // Method java/lang/Throwable.addSuppressed:(Ljava/lang/Throwable;)V
     380: goto          442
     383: aload_3
     384: invokeinterface #59,  1           // InterfaceMethod org/apache/hadoop/hbase/client/Table.close:()V
     389: goto          442
     392: astore        5
     394: aload         5
     396: astore        4
     398: aload         5
     400: athrow
     401: astore        9
     403: aload_3
     404: ifnull        439
     407: aload         4
     409: ifnull        433
     412: aload_3
     413: invokeinterface #59,  1           // InterfaceMethod org/apache/hadoop/hbase/client/Table.close:()V
     418: goto          439
     421: astore        10
     423: aload         4
     425: aload         10
     427: invokevirtual #44                 // Method java/lang/Throwable.addSuppressed:(Ljava/lang/Throwable;)V
     430: goto          439
     433: aload_3
     434: invokeinterface #59,  1           // InterfaceMethod org/apache/hadoop/hbase/client/Table.close:()V
     439: aload         9
     441: athrow
     442: return
    Exception table:
       from    to  target type
         120   160   163   Class java/util/concurrent/ExecutionException
         186   192   195   Class java/lang/Throwable
          98   177   216   Class java/lang/Throwable
          98   177   225   any
         236   242   245   Class java/lang/Throwable
         216   227   225   any
         362   368   371   Class java/lang/Throwable
         319   353   392   Class java/lang/Throwable
         319   353   401   any
         412   418   421   Class java/lang/Throwable
         392   403   401   any

  static {};
    Code:
       0: ldc           #60                 // class org/apache/hadoop/hbase/replication/TestSyncReplicationMoreLogsInLocalCopyToRemote
       2: invokestatic  #61                 // Method org/apache/hadoop/hbase/HBaseClassTestRule.forClass:(Ljava/lang/Class;)Lorg/apache/hadoop/hbase/HBaseClassTestRule;
       5: putstatic     #62                 // Field CLASS_RULE:Lorg/apache/hadoop/hbase/HBaseClassTestRule;
       8: ldc           #60                 // class org/apache/hadoop/hbase/replication/TestSyncReplicationMoreLogsInLocalCopyToRemote
      10: invokestatic  #63                 // Method org/slf4j/LoggerFactory.getLogger:(Ljava/lang/Class;)Lorg/slf4j/Logger;
      13: putstatic     #39                 // Field LOG:Lorg/slf4j/Logger;
      16: return
}
