Compiled from "TestHRegion.java"
class org.apache.hadoop.hbase.regionserver.TestHRegion$10 implements java.lang.Runnable {
  final java.util.concurrent.atomic.AtomicBoolean val$appendDone;

  final org.apache.hadoop.hbase.regionserver.HRegion val$region;

  final org.apache.hadoop.hbase.regionserver.TestHRegion this$0;

  org.apache.hadoop.hbase.regionserver.TestHRegion$10(org.apache.hadoop.hbase.regionserver.TestHRegion, java.util.concurrent.atomic.AtomicBoolean, org.apache.hadoop.hbase.regionserver.HRegion);
    Code:
       0: aload_0
       1: aload_1
       2: putfield      #1                  // Field this$0:Lorg/apache/hadoop/hbase/regionserver/TestHRegion;
       5: aload_0
       6: aload_2
       7: putfield      #2                  // Field val$appendDone:Ljava/util/concurrent/atomic/AtomicBoolean;
      10: aload_0
      11: aload_3
      12: putfield      #3                  // Field val$region:Lorg/apache/hadoop/hbase/regionserver/HRegion;
      15: aload_0
      16: invokespecial #4                  // Method java/lang/Object."<init>":()V
      19: return

  public void run();
    Code:
       0: aload_0
       1: getfield      #2                  // Field val$appendDone:Ljava/util/concurrent/atomic/AtomicBoolean;
       4: invokevirtual #5                  // Method java/util/concurrent/atomic/AtomicBoolean.get:()Z
       7: ifne          30
      10: aload_0
      11: getfield      #3                  // Field val$region:Lorg/apache/hadoop/hbase/regionserver/HRegion;
      14: iconst_1
      15: invokevirtual #6                  // Method org/apache/hadoop/hbase/regionserver/HRegion.flush:(Z)Lorg/apache/hadoop/hbase/regionserver/HRegion$FlushResult;
      18: pop
      19: goto          0
      22: astore_1
      23: aload_1
      24: invokevirtual #8                  // Method java/lang/Exception.printStackTrace:()V
      27: goto          0
      30: return
    Exception table:
       from    to  target type
          10    19    22   Class java/lang/Exception
}
