Compiled from "TestAsyncTableRpcPriority.java"
public class org.apache.hadoop.hbase.client.TestAsyncTableRpcPriority {
  public static final org.apache.hadoop.hbase.HBaseClassTestRule CLASS_RULE;

  public org.junit.rules.TestName name;

  public org.apache.hadoop.hbase.client.TestAsyncTableRpcPriority();
    Code:
       0: aload_0
       1: invokespecial #3                  // Method java/lang/Object."<init>":()V
       4: aload_0
       5: new           #4                  // class org/junit/rules/TestName
       8: dup
       9: invokespecial #5                  // Method org/junit/rules/TestName."<init>":()V
      12: putfield      #6                  // Field name:Lorg/junit/rules/TestName;
      15: return

  public void setUp() throws java.io.IOException;
    Code:
       0: aload_0
       1: ldc           #7                  // class org/apache/hadoop/hbase/shaded/protobuf/generated/ClientProtos$ClientService$Interface
       3: invokestatic  #8                  // Method org/mockito/Mockito.mock:(Ljava/lang/Class;)Ljava/lang/Object;
       6: checkcast     #7                  // class org/apache/hadoop/hbase/shaded/protobuf/generated/ClientProtos$ClientService$Interface
       9: putfield      #2                  // Field stub:Lorg/apache/hadoop/hbase/shaded/protobuf/generated/ClientProtos$ClientService$Interface;
      12: new           #9                  // class java/util/concurrent/atomic/AtomicInteger
      15: dup
      16: iconst_0
      17: invokespecial #10                 // Method java/util/concurrent/atomic/AtomicInteger."<init>":(I)V
      20: astore_1
      21: new           #11                 // class org/apache/hadoop/hbase/client/TestAsyncTableRpcPriority$1
      24: dup
      25: aload_0
      26: aload_1
      27: invokespecial #12                 // Method org/apache/hadoop/hbase/client/TestAsyncTableRpcPriority$1."<init>":(Lorg/apache/hadoop/hbase/client/TestAsyncTableRpcPriority;Ljava/util/concurrent/atomic/AtomicInteger;)V
      30: invokestatic  #13                 // Method org/mockito/Mockito.doAnswer:(Lorg/mockito/stubbing/Answer;)Lorg/mockito/stubbing/Stubber;
      33: aload_0
      34: getfield      #2                  // Field stub:Lorg/apache/hadoop/hbase/shaded/protobuf/generated/ClientProtos$ClientService$Interface;
      37: invokeinterface #14,  2           // InterfaceMethod org/mockito/stubbing/Stubber.when:(Ljava/lang/Object;)Ljava/lang/Object;
      42: checkcast     #7                  // class org/apache/hadoop/hbase/shaded/protobuf/generated/ClientProtos$ClientService$Interface
      45: ldc           #15                 // class org/apache/hadoop/hbase/ipc/HBaseRpcController
      47: invokestatic  #16                 // Method org/mockito/ArgumentMatchers.any:(Ljava/lang/Class;)Ljava/lang/Object;
      50: checkcast     #17                 // class org/apache/hbase/thirdparty/com/google/protobuf/RpcController
      53: ldc           #18                 // class org/apache/hadoop/hbase/shaded/protobuf/generated/ClientProtos$ScanRequest
      55: invokestatic  #16                 // Method org/mockito/ArgumentMatchers.any:(Ljava/lang/Class;)Ljava/lang/Object;
      58: checkcast     #18                 // class org/apache/hadoop/hbase/shaded/protobuf/generated/ClientProtos$ScanRequest
      61: invokestatic  #19                 // Method org/mockito/ArgumentMatchers.any:()Ljava/lang/Object;
      64: checkcast     #20                 // class org/apache/hbase/thirdparty/com/google/protobuf/RpcCallback
      67: invokeinterface #21,  4           // InterfaceMethod org/apache/hadoop/hbase/shaded/protobuf/generated/ClientProtos$ClientService$Interface.scan:(Lorg/apache/hbase/thirdparty/com/google/protobuf/RpcController;Lorg/apache/hadoop/hbase/shaded/protobuf/generated/ClientProtos$ScanRequest;Lorg/apache/hbase/thirdparty/com/google/protobuf/RpcCallback;)V
      72: new           #22                 // class org/apache/hadoop/hbase/client/TestAsyncTableRpcPriority$2
      75: dup
      76: aload_0
      77: invokespecial #23                 // Method org/apache/hadoop/hbase/client/TestAsyncTableRpcPriority$2."<init>":(Lorg/apache/hadoop/hbase/client/TestAsyncTableRpcPriority;)V
      80: invokestatic  #13                 // Method org/mockito/Mockito.doAnswer:(Lorg/mockito/stubbing/Answer;)Lorg/mockito/stubbing/Stubber;
      83: aload_0
      84: getfield      #2                  // Field stub:Lorg/apache/hadoop/hbase/shaded/protobuf/generated/ClientProtos$ClientService$Interface;
      87: invokeinterface #14,  2           // InterfaceMethod org/mockito/stubbing/Stubber.when:(Ljava/lang/Object;)Ljava/lang/Object;
      92: checkcast     #7                  // class org/apache/hadoop/hbase/shaded/protobuf/generated/ClientProtos$ClientService$Interface
      95: ldc           #15                 // class org/apache/hadoop/hbase/ipc/HBaseRpcController
      97: invokestatic  #16                 // Method org/mockito/ArgumentMatchers.any:(Ljava/lang/Class;)Ljava/lang/Object;
     100: checkcast     #17                 // class org/apache/hbase/thirdparty/com/google/protobuf/RpcController
     103: ldc           #24                 // class org/apache/hadoop/hbase/shaded/protobuf/generated/ClientProtos$MultiRequest
     105: invokestatic  #16                 // Method org/mockito/ArgumentMatchers.any:(Ljava/lang/Class;)Ljava/lang/Object;
     108: checkcast     #24                 // class org/apache/hadoop/hbase/shaded/protobuf/generated/ClientProtos$MultiRequest
     111: invokestatic  #19                 // Method org/mockito/ArgumentMatchers.any:()Ljava/lang/Object;
     114: checkcast     #20                 // class org/apache/hbase/thirdparty/com/google/protobuf/RpcCallback
     117: invokeinterface #25,  4           // InterfaceMethod org/apache/hadoop/hbase/shaded/protobuf/generated/ClientProtos$ClientService$Interface.multi:(Lorg/apache/hbase/thirdparty/com/google/protobuf/RpcController;Lorg/apache/hadoop/hbase/shaded/protobuf/generated/ClientProtos$MultiRequest;Lorg/apache/hbase/thirdparty/com/google/protobuf/RpcCallback;)V
     122: new           #26                 // class org/apache/hadoop/hbase/client/TestAsyncTableRpcPriority$3
     125: dup
     126: aload_0
     127: invokespecial #27                 // Method org/apache/hadoop/hbase/client/TestAsyncTableRpcPriority$3."<init>":(Lorg/apache/hadoop/hbase/client/TestAsyncTableRpcPriority;)V
     130: invokestatic  #13                 // Method org/mockito/Mockito.doAnswer:(Lorg/mockito/stubbing/Answer;)Lorg/mockito/stubbing/Stubber;
     133: aload_0
     134: getfield      #2                  // Field stub:Lorg/apache/hadoop/hbase/shaded/protobuf/generated/ClientProtos$ClientService$Interface;
     137: invokeinterface #14,  2           // InterfaceMethod org/mockito/stubbing/Stubber.when:(Ljava/lang/Object;)Ljava/lang/Object;
     142: checkcast     #7                  // class org/apache/hadoop/hbase/shaded/protobuf/generated/ClientProtos$ClientService$Interface
     145: ldc           #15                 // class org/apache/hadoop/hbase/ipc/HBaseRpcController
     147: invokestatic  #16                 // Method org/mockito/ArgumentMatchers.any:(Ljava/lang/Class;)Ljava/lang/Object;
     150: checkcast     #17                 // class org/apache/hbase/thirdparty/com/google/protobuf/RpcController
     153: ldc           #28                 // class org/apache/hadoop/hbase/shaded/protobuf/generated/ClientProtos$MutateRequest
     155: invokestatic  #16                 // Method org/mockito/ArgumentMatchers.any:(Ljava/lang/Class;)Ljava/lang/Object;
     158: checkcast     #28                 // class org/apache/hadoop/hbase/shaded/protobuf/generated/ClientProtos$MutateRequest
     161: invokestatic  #19                 // Method org/mockito/ArgumentMatchers.any:()Ljava/lang/Object;
     164: checkcast     #20                 // class org/apache/hbase/thirdparty/com/google/protobuf/RpcCallback
     167: invokeinterface #29,  4           // InterfaceMethod org/apache/hadoop/hbase/shaded/protobuf/generated/ClientProtos$ClientService$Interface.mutate:(Lorg/apache/hbase/thirdparty/com/google/protobuf/RpcController;Lorg/apache/hadoop/hbase/shaded/protobuf/generated/ClientProtos$MutateRequest;Lorg/apache/hbase/thirdparty/com/google/protobuf/RpcCallback;)V
     172: new           #30                 // class org/apache/hadoop/hbase/client/TestAsyncTableRpcPriority$4
     175: dup
     176: aload_0
     177: invokespecial #31                 // Method org/apache/hadoop/hbase/client/TestAsyncTableRpcPriority$4."<init>":(Lorg/apache/hadoop/hbase/client/TestAsyncTableRpcPriority;)V
     180: invokestatic  #13                 // Method org/mockito/Mockito.doAnswer:(Lorg/mockito/stubbing/Answer;)Lorg/mockito/stubbing/Stubber;
     183: aload_0
     184: getfield      #2                  // Field stub:Lorg/apache/hadoop/hbase/shaded/protobuf/generated/ClientProtos$ClientService$Interface;
     187: invokeinterface #14,  2           // InterfaceMethod org/mockito/stubbing/Stubber.when:(Ljava/lang/Object;)Ljava/lang/Object;
     192: checkcast     #7                  // class org/apache/hadoop/hbase/shaded/protobuf/generated/ClientProtos$ClientService$Interface
     195: ldc           #15                 // class org/apache/hadoop/hbase/ipc/HBaseRpcController
     197: invokestatic  #16                 // Method org/mockito/ArgumentMatchers.any:(Ljava/lang/Class;)Ljava/lang/Object;
     200: checkcast     #17                 // class org/apache/hbase/thirdparty/com/google/protobuf/RpcController
     203: ldc           #32                 // class org/apache/hadoop/hbase/shaded/protobuf/generated/ClientProtos$GetRequest
     205: invokestatic  #16                 // Method org/mockito/ArgumentMatchers.any:(Ljava/lang/Class;)Ljava/lang/Object;
     208: checkcast     #32                 // class org/apache/hadoop/hbase/shaded/protobuf/generated/ClientProtos$GetRequest
     211: invokestatic  #19                 // Method org/mockito/ArgumentMatchers.any:()Ljava/lang/Object;
     214: checkcast     #20                 // class org/apache/hbase/thirdparty/com/google/protobuf/RpcCallback
     217: invokeinterface #33,  4           // InterfaceMethod org/apache/hadoop/hbase/shaded/protobuf/generated/ClientProtos$ClientService$Interface.get:(Lorg/apache/hbase/thirdparty/com/google/protobuf/RpcController;Lorg/apache/hadoop/hbase/shaded/protobuf/generated/ClientProtos$GetRequest;Lorg/apache/hbase/thirdparty/com/google/protobuf/RpcCallback;)V
     222: aload_0
     223: new           #34                 // class org/apache/hadoop/hbase/client/TestAsyncTableRpcPriority$5
     226: dup
     227: aload_0
     228: getstatic     #35                 // Field CONF:Lorg/apache/hadoop/conf/Configuration;
     231: new           #36                 // class org/apache/hadoop/hbase/client/DoNothingAsyncRegistry
     234: dup
     235: getstatic     #35                 // Field CONF:Lorg/apache/hadoop/conf/Configuration;
     238: invokespecial #37                 // Method org/apache/hadoop/hbase/client/DoNothingAsyncRegistry."<init>":(Lorg/apache/hadoop/conf/Configuration;)V
     241: ldc           #38                 // String test
     243: getstatic     #35                 // Field CONF:Lorg/apache/hadoop/conf/Configuration;
     246: invokestatic  #39                 // Method org/apache/hadoop/hbase/security/UserProvider.instantiate:(Lorg/apache/hadoop/conf/Configuration;)Lorg/apache/hadoop/hbase/security/UserProvider;
     249: invokevirtual #40                 // Method org/apache/hadoop/hbase/security/UserProvider.getCurrent:()Lorg/apache/hadoop/hbase/security/User;
     252: invokespecial #41                 // Method org/apache/hadoop/hbase/client/TestAsyncTableRpcPriority$5."<init>":(Lorg/apache/hadoop/hbase/client/TestAsyncTableRpcPriority;Lorg/apache/hadoop/conf/Configuration;Lorg/apache/hadoop/hbase/client/AsyncRegistry;Ljava/lang/String;Lorg/apache/hadoop/hbase/security/User;)V
     255: putfield      #42                 // Field conn:Lorg/apache/hadoop/hbase/client/AsyncConnection;
     258: return

  public void testGet();
    Code:
       0: aload_0
       1: getfield      #42                 // Field conn:Lorg/apache/hadoop/hbase/client/AsyncConnection;
       4: aload_0
       5: getfield      #6                  // Field name:Lorg/junit/rules/TestName;
       8: invokevirtual #46                 // Method org/junit/rules/TestName.getMethodName:()Ljava/lang/String;
      11: invokestatic  #47                 // Method org/apache/hadoop/hbase/TableName.valueOf:(Ljava/lang/String;)Lorg/apache/hadoop/hbase/TableName;
      14: invokeinterface #48,  2           // InterfaceMethod org/apache/hadoop/hbase/client/AsyncConnection.getTable:(Lorg/apache/hadoop/hbase/TableName;)Lorg/apache/hadoop/hbase/client/AsyncTable;
      19: new           #49                 // class org/apache/hadoop/hbase/client/Get
      22: dup
      23: iconst_0
      24: invokestatic  #50                 // Method org/apache/hadoop/hbase/util/Bytes.toBytes:(I)[B
      27: invokespecial #51                 // Method org/apache/hadoop/hbase/client/Get."<init>":([B)V
      30: bipush        11
      32: invokevirtual #52                 // Method org/apache/hadoop/hbase/client/Get.setPriority:(I)Lorg/apache/hadoop/hbase/client/Get;
      35: invokeinterface #53,  2           // InterfaceMethod org/apache/hadoop/hbase/client/AsyncTable.get:(Lorg/apache/hadoop/hbase/client/Get;)Ljava/util/concurrent/CompletableFuture;
      40: invokevirtual #54                 // Method java/util/concurrent/CompletableFuture.join:()Ljava/lang/Object;
      43: pop
      44: aload_0
      45: getfield      #2                  // Field stub:Lorg/apache/hadoop/hbase/shaded/protobuf/generated/ClientProtos$ClientService$Interface;
      48: iconst_1
      49: invokestatic  #55                 // Method org/mockito/Mockito.times:(I)Lorg/mockito/verification/VerificationMode;
      52: invokestatic  #56                 // Method org/mockito/Mockito.verify:(Ljava/lang/Object;Lorg/mockito/verification/VerificationMode;)Ljava/lang/Object;
      55: checkcast     #7                  // class org/apache/hadoop/hbase/shaded/protobuf/generated/ClientProtos$ClientService$Interface
      58: aload_0
      59: bipush        11
      61: invokespecial #57                 // Method assertPriority:(I)Lorg/apache/hadoop/hbase/ipc/HBaseRpcController;
      64: ldc           #32                 // class org/apache/hadoop/hbase/shaded/protobuf/generated/ClientProtos$GetRequest
      66: invokestatic  #16                 // Method org/mockito/ArgumentMatchers.any:(Ljava/lang/Class;)Ljava/lang/Object;
      69: checkcast     #32                 // class org/apache/hadoop/hbase/shaded/protobuf/generated/ClientProtos$GetRequest
      72: invokestatic  #19                 // Method org/mockito/ArgumentMatchers.any:()Ljava/lang/Object;
      75: checkcast     #20                 // class org/apache/hbase/thirdparty/com/google/protobuf/RpcCallback
      78: invokeinterface #33,  4           // InterfaceMethod org/apache/hadoop/hbase/shaded/protobuf/generated/ClientProtos$ClientService$Interface.get:(Lorg/apache/hbase/thirdparty/com/google/protobuf/RpcController;Lorg/apache/hadoop/hbase/shaded/protobuf/generated/ClientProtos$GetRequest;Lorg/apache/hbase/thirdparty/com/google/protobuf/RpcCallback;)V
      83: return

  public void testGetNormalTable();
    Code:
       0: aload_0
       1: getfield      #42                 // Field conn:Lorg/apache/hadoop/hbase/client/AsyncConnection;
       4: aload_0
       5: getfield      #6                  // Field name:Lorg/junit/rules/TestName;
       8: invokevirtual #46                 // Method org/junit/rules/TestName.getMethodName:()Ljava/lang/String;
      11: invokestatic  #47                 // Method org/apache/hadoop/hbase/TableName.valueOf:(Ljava/lang/String;)Lorg/apache/hadoop/hbase/TableName;
      14: invokeinterface #48,  2           // InterfaceMethod org/apache/hadoop/hbase/client/AsyncConnection.getTable:(Lorg/apache/hadoop/hbase/TableName;)Lorg/apache/hadoop/hbase/client/AsyncTable;
      19: new           #49                 // class org/apache/hadoop/hbase/client/Get
      22: dup
      23: iconst_0
      24: invokestatic  #50                 // Method org/apache/hadoop/hbase/util/Bytes.toBytes:(I)[B
      27: invokespecial #51                 // Method org/apache/hadoop/hbase/client/Get."<init>":([B)V
      30: invokeinterface #53,  2           // InterfaceMethod org/apache/hadoop/hbase/client/AsyncTable.get:(Lorg/apache/hadoop/hbase/client/Get;)Ljava/util/concurrent/CompletableFuture;
      35: invokevirtual #54                 // Method java/util/concurrent/CompletableFuture.join:()Ljava/lang/Object;
      38: pop
      39: aload_0
      40: getfield      #2                  // Field stub:Lorg/apache/hadoop/hbase/shaded/protobuf/generated/ClientProtos$ClientService$Interface;
      43: iconst_1
      44: invokestatic  #55                 // Method org/mockito/Mockito.times:(I)Lorg/mockito/verification/VerificationMode;
      47: invokestatic  #56                 // Method org/mockito/Mockito.verify:(Ljava/lang/Object;Lorg/mockito/verification/VerificationMode;)Ljava/lang/Object;
      50: checkcast     #7                  // class org/apache/hadoop/hbase/shaded/protobuf/generated/ClientProtos$ClientService$Interface
      53: aload_0
      54: iconst_0
      55: invokespecial #57                 // Method assertPriority:(I)Lorg/apache/hadoop/hbase/ipc/HBaseRpcController;
      58: ldc           #32                 // class org/apache/hadoop/hbase/shaded/protobuf/generated/ClientProtos$GetRequest
      60: invokestatic  #16                 // Method org/mockito/ArgumentMatchers.any:(Ljava/lang/Class;)Ljava/lang/Object;
      63: checkcast     #32                 // class org/apache/hadoop/hbase/shaded/protobuf/generated/ClientProtos$GetRequest
      66: invokestatic  #19                 // Method org/mockito/ArgumentMatchers.any:()Ljava/lang/Object;
      69: checkcast     #20                 // class org/apache/hbase/thirdparty/com/google/protobuf/RpcCallback
      72: invokeinterface #33,  4           // InterfaceMethod org/apache/hadoop/hbase/shaded/protobuf/generated/ClientProtos$ClientService$Interface.get:(Lorg/apache/hbase/thirdparty/com/google/protobuf/RpcController;Lorg/apache/hadoop/hbase/shaded/protobuf/generated/ClientProtos$GetRequest;Lorg/apache/hbase/thirdparty/com/google/protobuf/RpcCallback;)V
      77: return

  public void testGetSystemTable();
    Code:
       0: aload_0
       1: getfield      #42                 // Field conn:Lorg/apache/hadoop/hbase/client/AsyncConnection;
       4: getstatic     #58                 // Field org/apache/hadoop/hbase/NamespaceDescriptor.SYSTEM_NAMESPACE_NAME_STR:Ljava/lang/String;
       7: aload_0
       8: getfield      #6                  // Field name:Lorg/junit/rules/TestName;
      11: invokevirtual #46                 // Method org/junit/rules/TestName.getMethodName:()Ljava/lang/String;
      14: invokestatic  #59                 // Method org/apache/hadoop/hbase/TableName.valueOf:(Ljava/lang/String;Ljava/lang/String;)Lorg/apache/hadoop/hbase/TableName;
      17: invokeinterface #48,  2           // InterfaceMethod org/apache/hadoop/hbase/client/AsyncConnection.getTable:(Lorg/apache/hadoop/hbase/TableName;)Lorg/apache/hadoop/hbase/client/AsyncTable;
      22: new           #49                 // class org/apache/hadoop/hbase/client/Get
      25: dup
      26: iconst_0
      27: invokestatic  #50                 // Method org/apache/hadoop/hbase/util/Bytes.toBytes:(I)[B
      30: invokespecial #51                 // Method org/apache/hadoop/hbase/client/Get."<init>":([B)V
      33: invokeinterface #53,  2           // InterfaceMethod org/apache/hadoop/hbase/client/AsyncTable.get:(Lorg/apache/hadoop/hbase/client/Get;)Ljava/util/concurrent/CompletableFuture;
      38: invokevirtual #54                 // Method java/util/concurrent/CompletableFuture.join:()Ljava/lang/Object;
      41: pop
      42: aload_0
      43: getfield      #2                  // Field stub:Lorg/apache/hadoop/hbase/shaded/protobuf/generated/ClientProtos$ClientService$Interface;
      46: iconst_1
      47: invokestatic  #55                 // Method org/mockito/Mockito.times:(I)Lorg/mockito/verification/VerificationMode;
      50: invokestatic  #56                 // Method org/mockito/Mockito.verify:(Ljava/lang/Object;Lorg/mockito/verification/VerificationMode;)Ljava/lang/Object;
      53: checkcast     #7                  // class org/apache/hadoop/hbase/shaded/protobuf/generated/ClientProtos$ClientService$Interface
      56: aload_0
      57: sipush        200
      60: invokespecial #57                 // Method assertPriority:(I)Lorg/apache/hadoop/hbase/ipc/HBaseRpcController;
      63: ldc           #32                 // class org/apache/hadoop/hbase/shaded/protobuf/generated/ClientProtos$GetRequest
      65: invokestatic  #16                 // Method org/mockito/ArgumentMatchers.any:(Ljava/lang/Class;)Ljava/lang/Object;
      68: checkcast     #32                 // class org/apache/hadoop/hbase/shaded/protobuf/generated/ClientProtos$GetRequest
      71: invokestatic  #19                 // Method org/mockito/ArgumentMatchers.any:()Ljava/lang/Object;
      74: checkcast     #20                 // class org/apache/hbase/thirdparty/com/google/protobuf/RpcCallback
      77: invokeinterface #33,  4           // InterfaceMethod org/apache/hadoop/hbase/shaded/protobuf/generated/ClientProtos$ClientService$Interface.get:(Lorg/apache/hbase/thirdparty/com/google/protobuf/RpcController;Lorg/apache/hadoop/hbase/shaded/protobuf/generated/ClientProtos$GetRequest;Lorg/apache/hbase/thirdparty/com/google/protobuf/RpcCallback;)V
      82: return

  public void testGetMetaTable();
    Code:
       0: aload_0
       1: getfield      #42                 // Field conn:Lorg/apache/hadoop/hbase/client/AsyncConnection;
       4: getstatic     #60                 // Field org/apache/hadoop/hbase/TableName.META_TABLE_NAME:Lorg/apache/hadoop/hbase/TableName;
       7: invokeinterface #48,  2           // InterfaceMethod org/apache/hadoop/hbase/client/AsyncConnection.getTable:(Lorg/apache/hadoop/hbase/TableName;)Lorg/apache/hadoop/hbase/client/AsyncTable;
      12: new           #49                 // class org/apache/hadoop/hbase/client/Get
      15: dup
      16: iconst_0
      17: invokestatic  #50                 // Method org/apache/hadoop/hbase/util/Bytes.toBytes:(I)[B
      20: invokespecial #51                 // Method org/apache/hadoop/hbase/client/Get."<init>":([B)V
      23: invokeinterface #53,  2           // InterfaceMethod org/apache/hadoop/hbase/client/AsyncTable.get:(Lorg/apache/hadoop/hbase/client/Get;)Ljava/util/concurrent/CompletableFuture;
      28: invokevirtual #54                 // Method java/util/concurrent/CompletableFuture.join:()Ljava/lang/Object;
      31: pop
      32: aload_0
      33: getfield      #2                  // Field stub:Lorg/apache/hadoop/hbase/shaded/protobuf/generated/ClientProtos$ClientService$Interface;
      36: iconst_1
      37: invokestatic  #55                 // Method org/mockito/Mockito.times:(I)Lorg/mockito/verification/VerificationMode;
      40: invokestatic  #56                 // Method org/mockito/Mockito.verify:(Ljava/lang/Object;Lorg/mockito/verification/VerificationMode;)Ljava/lang/Object;
      43: checkcast     #7                  // class org/apache/hadoop/hbase/shaded/protobuf/generated/ClientProtos$ClientService$Interface
      46: aload_0
      47: sipush        200
      50: invokespecial #57                 // Method assertPriority:(I)Lorg/apache/hadoop/hbase/ipc/HBaseRpcController;
      53: ldc           #32                 // class org/apache/hadoop/hbase/shaded/protobuf/generated/ClientProtos$GetRequest
      55: invokestatic  #16                 // Method org/mockito/ArgumentMatchers.any:(Ljava/lang/Class;)Ljava/lang/Object;
      58: checkcast     #32                 // class org/apache/hadoop/hbase/shaded/protobuf/generated/ClientProtos$GetRequest
      61: invokestatic  #19                 // Method org/mockito/ArgumentMatchers.any:()Ljava/lang/Object;
      64: checkcast     #20                 // class org/apache/hbase/thirdparty/com/google/protobuf/RpcCallback
      67: invokeinterface #33,  4           // InterfaceMethod org/apache/hadoop/hbase/shaded/protobuf/generated/ClientProtos$ClientService$Interface.get:(Lorg/apache/hbase/thirdparty/com/google/protobuf/RpcController;Lorg/apache/hadoop/hbase/shaded/protobuf/generated/ClientProtos$GetRequest;Lorg/apache/hbase/thirdparty/com/google/protobuf/RpcCallback;)V
      72: return

  public void testPut();
    Code:
       0: aload_0
       1: getfield      #42                 // Field conn:Lorg/apache/hadoop/hbase/client/AsyncConnection;
       4: aload_0
       5: getfield      #6                  // Field name:Lorg/junit/rules/TestName;
       8: invokevirtual #46                 // Method org/junit/rules/TestName.getMethodName:()Ljava/lang/String;
      11: invokestatic  #47                 // Method org/apache/hadoop/hbase/TableName.valueOf:(Ljava/lang/String;)Lorg/apache/hadoop/hbase/TableName;
      14: invokeinterface #48,  2           // InterfaceMethod org/apache/hadoop/hbase/client/AsyncConnection.getTable:(Lorg/apache/hadoop/hbase/TableName;)Lorg/apache/hadoop/hbase/client/AsyncTable;
      19: new           #61                 // class org/apache/hadoop/hbase/client/Put
      22: dup
      23: iconst_0
      24: invokestatic  #50                 // Method org/apache/hadoop/hbase/util/Bytes.toBytes:(I)[B
      27: invokespecial #62                 // Method org/apache/hadoop/hbase/client/Put."<init>":([B)V
      30: bipush        12
      32: invokevirtual #63                 // Method org/apache/hadoop/hbase/client/Put.setPriority:(I)Lorg/apache/hadoop/hbase/client/Put;
      35: ldc           #64                 // String cf
      37: invokestatic  #65                 // Method org/apache/hadoop/hbase/util/Bytes.toBytes:(Ljava/lang/String;)[B
      40: ldc           #66                 // String cq
      42: invokestatic  #65                 // Method org/apache/hadoop/hbase/util/Bytes.toBytes:(Ljava/lang/String;)[B
      45: ldc           #67                 // String v
      47: invokestatic  #65                 // Method org/apache/hadoop/hbase/util/Bytes.toBytes:(Ljava/lang/String;)[B
      50: invokevirtual #68                 // Method org/apache/hadoop/hbase/client/Put.addColumn:([B[B[B)Lorg/apache/hadoop/hbase/client/Put;
      53: invokeinterface #69,  2           // InterfaceMethod org/apache/hadoop/hbase/client/AsyncTable.put:(Lorg/apache/hadoop/hbase/client/Put;)Ljava/util/concurrent/CompletableFuture;
      58: invokevirtual #54                 // Method java/util/concurrent/CompletableFuture.join:()Ljava/lang/Object;
      61: pop
      62: aload_0
      63: getfield      #2                  // Field stub:Lorg/apache/hadoop/hbase/shaded/protobuf/generated/ClientProtos$ClientService$Interface;
      66: iconst_1
      67: invokestatic  #55                 // Method org/mockito/Mockito.times:(I)Lorg/mockito/verification/VerificationMode;
      70: invokestatic  #56                 // Method org/mockito/Mockito.verify:(Ljava/lang/Object;Lorg/mockito/verification/VerificationMode;)Ljava/lang/Object;
      73: checkcast     #7                  // class org/apache/hadoop/hbase/shaded/protobuf/generated/ClientProtos$ClientService$Interface
      76: aload_0
      77: bipush        12
      79: invokespecial #57                 // Method assertPriority:(I)Lorg/apache/hadoop/hbase/ipc/HBaseRpcController;
      82: ldc           #28                 // class org/apache/hadoop/hbase/shaded/protobuf/generated/ClientProtos$MutateRequest
      84: invokestatic  #16                 // Method org/mockito/ArgumentMatchers.any:(Ljava/lang/Class;)Ljava/lang/Object;
      87: checkcast     #28                 // class org/apache/hadoop/hbase/shaded/protobuf/generated/ClientProtos$MutateRequest
      90: invokestatic  #19                 // Method org/mockito/ArgumentMatchers.any:()Ljava/lang/Object;
      93: checkcast     #20                 // class org/apache/hbase/thirdparty/com/google/protobuf/RpcCallback
      96: invokeinterface #29,  4           // InterfaceMethod org/apache/hadoop/hbase/shaded/protobuf/generated/ClientProtos$ClientService$Interface.mutate:(Lorg/apache/hbase/thirdparty/com/google/protobuf/RpcController;Lorg/apache/hadoop/hbase/shaded/protobuf/generated/ClientProtos$MutateRequest;Lorg/apache/hbase/thirdparty/com/google/protobuf/RpcCallback;)V
     101: return

  public void testPutNormalTable();
    Code:
       0: aload_0
       1: getfield      #42                 // Field conn:Lorg/apache/hadoop/hbase/client/AsyncConnection;
       4: aload_0
       5: getfield      #6                  // Field name:Lorg/junit/rules/TestName;
       8: invokevirtual #46                 // Method org/junit/rules/TestName.getMethodName:()Ljava/lang/String;
      11: invokestatic  #47                 // Method org/apache/hadoop/hbase/TableName.valueOf:(Ljava/lang/String;)Lorg/apache/hadoop/hbase/TableName;
      14: invokeinterface #48,  2           // InterfaceMethod org/apache/hadoop/hbase/client/AsyncConnection.getTable:(Lorg/apache/hadoop/hbase/TableName;)Lorg/apache/hadoop/hbase/client/AsyncTable;
      19: new           #61                 // class org/apache/hadoop/hbase/client/Put
      22: dup
      23: iconst_0
      24: invokestatic  #50                 // Method org/apache/hadoop/hbase/util/Bytes.toBytes:(I)[B
      27: invokespecial #62                 // Method org/apache/hadoop/hbase/client/Put."<init>":([B)V
      30: ldc           #64                 // String cf
      32: invokestatic  #65                 // Method org/apache/hadoop/hbase/util/Bytes.toBytes:(Ljava/lang/String;)[B
      35: ldc           #66                 // String cq
      37: invokestatic  #65                 // Method org/apache/hadoop/hbase/util/Bytes.toBytes:(Ljava/lang/String;)[B
      40: ldc           #67                 // String v
      42: invokestatic  #65                 // Method org/apache/hadoop/hbase/util/Bytes.toBytes:(Ljava/lang/String;)[B
      45: invokevirtual #68                 // Method org/apache/hadoop/hbase/client/Put.addColumn:([B[B[B)Lorg/apache/hadoop/hbase/client/Put;
      48: invokeinterface #69,  2           // InterfaceMethod org/apache/hadoop/hbase/client/AsyncTable.put:(Lorg/apache/hadoop/hbase/client/Put;)Ljava/util/concurrent/CompletableFuture;
      53: invokevirtual #54                 // Method java/util/concurrent/CompletableFuture.join:()Ljava/lang/Object;
      56: pop
      57: aload_0
      58: getfield      #2                  // Field stub:Lorg/apache/hadoop/hbase/shaded/protobuf/generated/ClientProtos$ClientService$Interface;
      61: iconst_1
      62: invokestatic  #55                 // Method org/mockito/Mockito.times:(I)Lorg/mockito/verification/VerificationMode;
      65: invokestatic  #56                 // Method org/mockito/Mockito.verify:(Ljava/lang/Object;Lorg/mockito/verification/VerificationMode;)Ljava/lang/Object;
      68: checkcast     #7                  // class org/apache/hadoop/hbase/shaded/protobuf/generated/ClientProtos$ClientService$Interface
      71: aload_0
      72: iconst_0
      73: invokespecial #57                 // Method assertPriority:(I)Lorg/apache/hadoop/hbase/ipc/HBaseRpcController;
      76: ldc           #28                 // class org/apache/hadoop/hbase/shaded/protobuf/generated/ClientProtos$MutateRequest
      78: invokestatic  #16                 // Method org/mockito/ArgumentMatchers.any:(Ljava/lang/Class;)Ljava/lang/Object;
      81: checkcast     #28                 // class org/apache/hadoop/hbase/shaded/protobuf/generated/ClientProtos$MutateRequest
      84: invokestatic  #19                 // Method org/mockito/ArgumentMatchers.any:()Ljava/lang/Object;
      87: checkcast     #20                 // class org/apache/hbase/thirdparty/com/google/protobuf/RpcCallback
      90: invokeinterface #29,  4           // InterfaceMethod org/apache/hadoop/hbase/shaded/protobuf/generated/ClientProtos$ClientService$Interface.mutate:(Lorg/apache/hbase/thirdparty/com/google/protobuf/RpcController;Lorg/apache/hadoop/hbase/shaded/protobuf/generated/ClientProtos$MutateRequest;Lorg/apache/hbase/thirdparty/com/google/protobuf/RpcCallback;)V
      95: return

  public void testPutSystemTable();
    Code:
       0: aload_0
       1: getfield      #42                 // Field conn:Lorg/apache/hadoop/hbase/client/AsyncConnection;
       4: getstatic     #58                 // Field org/apache/hadoop/hbase/NamespaceDescriptor.SYSTEM_NAMESPACE_NAME_STR:Ljava/lang/String;
       7: aload_0
       8: getfield      #6                  // Field name:Lorg/junit/rules/TestName;
      11: invokevirtual #46                 // Method org/junit/rules/TestName.getMethodName:()Ljava/lang/String;
      14: invokestatic  #59                 // Method org/apache/hadoop/hbase/TableName.valueOf:(Ljava/lang/String;Ljava/lang/String;)Lorg/apache/hadoop/hbase/TableName;
      17: invokeinterface #48,  2           // InterfaceMethod org/apache/hadoop/hbase/client/AsyncConnection.getTable:(Lorg/apache/hadoop/hbase/TableName;)Lorg/apache/hadoop/hbase/client/AsyncTable;
      22: new           #61                 // class org/apache/hadoop/hbase/client/Put
      25: dup
      26: iconst_0
      27: invokestatic  #50                 // Method org/apache/hadoop/hbase/util/Bytes.toBytes:(I)[B
      30: invokespecial #62                 // Method org/apache/hadoop/hbase/client/Put."<init>":([B)V
      33: ldc           #64                 // String cf
      35: invokestatic  #65                 // Method org/apache/hadoop/hbase/util/Bytes.toBytes:(Ljava/lang/String;)[B
      38: ldc           #66                 // String cq
      40: invokestatic  #65                 // Method org/apache/hadoop/hbase/util/Bytes.toBytes:(Ljava/lang/String;)[B
      43: ldc           #67                 // String v
      45: invokestatic  #65                 // Method org/apache/hadoop/hbase/util/Bytes.toBytes:(Ljava/lang/String;)[B
      48: invokevirtual #68                 // Method org/apache/hadoop/hbase/client/Put.addColumn:([B[B[B)Lorg/apache/hadoop/hbase/client/Put;
      51: invokeinterface #69,  2           // InterfaceMethod org/apache/hadoop/hbase/client/AsyncTable.put:(Lorg/apache/hadoop/hbase/client/Put;)Ljava/util/concurrent/CompletableFuture;
      56: invokevirtual #54                 // Method java/util/concurrent/CompletableFuture.join:()Ljava/lang/Object;
      59: pop
      60: aload_0
      61: getfield      #2                  // Field stub:Lorg/apache/hadoop/hbase/shaded/protobuf/generated/ClientProtos$ClientService$Interface;
      64: iconst_1
      65: invokestatic  #55                 // Method org/mockito/Mockito.times:(I)Lorg/mockito/verification/VerificationMode;
      68: invokestatic  #56                 // Method org/mockito/Mockito.verify:(Ljava/lang/Object;Lorg/mockito/verification/VerificationMode;)Ljava/lang/Object;
      71: checkcast     #7                  // class org/apache/hadoop/hbase/shaded/protobuf/generated/ClientProtos$ClientService$Interface
      74: aload_0
      75: sipush        200
      78: invokespecial #57                 // Method assertPriority:(I)Lorg/apache/hadoop/hbase/ipc/HBaseRpcController;
      81: ldc           #28                 // class org/apache/hadoop/hbase/shaded/protobuf/generated/ClientProtos$MutateRequest
      83: invokestatic  #16                 // Method org/mockito/ArgumentMatchers.any:(Ljava/lang/Class;)Ljava/lang/Object;
      86: checkcast     #28                 // class org/apache/hadoop/hbase/shaded/protobuf/generated/ClientProtos$MutateRequest
      89: invokestatic  #19                 // Method org/mockito/ArgumentMatchers.any:()Ljava/lang/Object;
      92: checkcast     #20                 // class org/apache/hbase/thirdparty/com/google/protobuf/RpcCallback
      95: invokeinterface #29,  4           // InterfaceMethod org/apache/hadoop/hbase/shaded/protobuf/generated/ClientProtos$ClientService$Interface.mutate:(Lorg/apache/hbase/thirdparty/com/google/protobuf/RpcController;Lorg/apache/hadoop/hbase/shaded/protobuf/generated/ClientProtos$MutateRequest;Lorg/apache/hbase/thirdparty/com/google/protobuf/RpcCallback;)V
     100: return

  public void testPutMetaTable();
    Code:
       0: aload_0
       1: getfield      #42                 // Field conn:Lorg/apache/hadoop/hbase/client/AsyncConnection;
       4: getstatic     #60                 // Field org/apache/hadoop/hbase/TableName.META_TABLE_NAME:Lorg/apache/hadoop/hbase/TableName;
       7: invokeinterface #48,  2           // InterfaceMethod org/apache/hadoop/hbase/client/AsyncConnection.getTable:(Lorg/apache/hadoop/hbase/TableName;)Lorg/apache/hadoop/hbase/client/AsyncTable;
      12: new           #61                 // class org/apache/hadoop/hbase/client/Put
      15: dup
      16: iconst_0
      17: invokestatic  #50                 // Method org/apache/hadoop/hbase/util/Bytes.toBytes:(I)[B
      20: invokespecial #62                 // Method org/apache/hadoop/hbase/client/Put."<init>":([B)V
      23: ldc           #64                 // String cf
      25: invokestatic  #65                 // Method org/apache/hadoop/hbase/util/Bytes.toBytes:(Ljava/lang/String;)[B
      28: ldc           #66                 // String cq
      30: invokestatic  #65                 // Method org/apache/hadoop/hbase/util/Bytes.toBytes:(Ljava/lang/String;)[B
      33: ldc           #67                 // String v
      35: invokestatic  #65                 // Method org/apache/hadoop/hbase/util/Bytes.toBytes:(Ljava/lang/String;)[B
      38: invokevirtual #68                 // Method org/apache/hadoop/hbase/client/Put.addColumn:([B[B[B)Lorg/apache/hadoop/hbase/client/Put;
      41: invokeinterface #69,  2           // InterfaceMethod org/apache/hadoop/hbase/client/AsyncTable.put:(Lorg/apache/hadoop/hbase/client/Put;)Ljava/util/concurrent/CompletableFuture;
      46: invokevirtual #54                 // Method java/util/concurrent/CompletableFuture.join:()Ljava/lang/Object;
      49: pop
      50: aload_0
      51: getfield      #2                  // Field stub:Lorg/apache/hadoop/hbase/shaded/protobuf/generated/ClientProtos$ClientService$Interface;
      54: iconst_1
      55: invokestatic  #55                 // Method org/mockito/Mockito.times:(I)Lorg/mockito/verification/VerificationMode;
      58: invokestatic  #56                 // Method org/mockito/Mockito.verify:(Ljava/lang/Object;Lorg/mockito/verification/VerificationMode;)Ljava/lang/Object;
      61: checkcast     #7                  // class org/apache/hadoop/hbase/shaded/protobuf/generated/ClientProtos$ClientService$Interface
      64: aload_0
      65: sipush        200
      68: invokespecial #57                 // Method assertPriority:(I)Lorg/apache/hadoop/hbase/ipc/HBaseRpcController;
      71: ldc           #28                 // class org/apache/hadoop/hbase/shaded/protobuf/generated/ClientProtos$MutateRequest
      73: invokestatic  #16                 // Method org/mockito/ArgumentMatchers.any:(Ljava/lang/Class;)Ljava/lang/Object;
      76: checkcast     #28                 // class org/apache/hadoop/hbase/shaded/protobuf/generated/ClientProtos$MutateRequest
      79: invokestatic  #19                 // Method org/mockito/ArgumentMatchers.any:()Ljava/lang/Object;
      82: checkcast     #20                 // class org/apache/hbase/thirdparty/com/google/protobuf/RpcCallback
      85: invokeinterface #29,  4           // InterfaceMethod org/apache/hadoop/hbase/shaded/protobuf/generated/ClientProtos$ClientService$Interface.mutate:(Lorg/apache/hbase/thirdparty/com/google/protobuf/RpcController;Lorg/apache/hadoop/hbase/shaded/protobuf/generated/ClientProtos$MutateRequest;Lorg/apache/hbase/thirdparty/com/google/protobuf/RpcCallback;)V
      90: return

  public void testDelete();
    Code:
       0: aload_0
       1: getfield      #42                 // Field conn:Lorg/apache/hadoop/hbase/client/AsyncConnection;
       4: aload_0
       5: getfield      #6                  // Field name:Lorg/junit/rules/TestName;
       8: invokevirtual #46                 // Method org/junit/rules/TestName.getMethodName:()Ljava/lang/String;
      11: invokestatic  #47                 // Method org/apache/hadoop/hbase/TableName.valueOf:(Ljava/lang/String;)Lorg/apache/hadoop/hbase/TableName;
      14: invokeinterface #48,  2           // InterfaceMethod org/apache/hadoop/hbase/client/AsyncConnection.getTable:(Lorg/apache/hadoop/hbase/TableName;)Lorg/apache/hadoop/hbase/client/AsyncTable;
      19: new           #70                 // class org/apache/hadoop/hbase/client/Delete
      22: dup
      23: iconst_0
      24: invokestatic  #50                 // Method org/apache/hadoop/hbase/util/Bytes.toBytes:(I)[B
      27: invokespecial #71                 // Method org/apache/hadoop/hbase/client/Delete."<init>":([B)V
      30: bipush        13
      32: invokevirtual #72                 // Method org/apache/hadoop/hbase/client/Delete.setPriority:(I)Lorg/apache/hadoop/hbase/client/Delete;
      35: invokeinterface #73,  2           // InterfaceMethod org/apache/hadoop/hbase/client/AsyncTable.delete:(Lorg/apache/hadoop/hbase/client/Delete;)Ljava/util/concurrent/CompletableFuture;
      40: invokevirtual #54                 // Method java/util/concurrent/CompletableFuture.join:()Ljava/lang/Object;
      43: pop
      44: aload_0
      45: getfield      #2                  // Field stub:Lorg/apache/hadoop/hbase/shaded/protobuf/generated/ClientProtos$ClientService$Interface;
      48: iconst_1
      49: invokestatic  #55                 // Method org/mockito/Mockito.times:(I)Lorg/mockito/verification/VerificationMode;
      52: invokestatic  #56                 // Method org/mockito/Mockito.verify:(Ljava/lang/Object;Lorg/mockito/verification/VerificationMode;)Ljava/lang/Object;
      55: checkcast     #7                  // class org/apache/hadoop/hbase/shaded/protobuf/generated/ClientProtos$ClientService$Interface
      58: aload_0
      59: bipush        13
      61: invokespecial #57                 // Method assertPriority:(I)Lorg/apache/hadoop/hbase/ipc/HBaseRpcController;
      64: ldc           #28                 // class org/apache/hadoop/hbase/shaded/protobuf/generated/ClientProtos$MutateRequest
      66: invokestatic  #16                 // Method org/mockito/ArgumentMatchers.any:(Ljava/lang/Class;)Ljava/lang/Object;
      69: checkcast     #28                 // class org/apache/hadoop/hbase/shaded/protobuf/generated/ClientProtos$MutateRequest
      72: invokestatic  #19                 // Method org/mockito/ArgumentMatchers.any:()Ljava/lang/Object;
      75: checkcast     #20                 // class org/apache/hbase/thirdparty/com/google/protobuf/RpcCallback
      78: invokeinterface #29,  4           // InterfaceMethod org/apache/hadoop/hbase/shaded/protobuf/generated/ClientProtos$ClientService$Interface.mutate:(Lorg/apache/hbase/thirdparty/com/google/protobuf/RpcController;Lorg/apache/hadoop/hbase/shaded/protobuf/generated/ClientProtos$MutateRequest;Lorg/apache/hbase/thirdparty/com/google/protobuf/RpcCallback;)V
      83: return

  public void testDeleteNormalTable();
    Code:
       0: aload_0
       1: getfield      #42                 // Field conn:Lorg/apache/hadoop/hbase/client/AsyncConnection;
       4: aload_0
       5: getfield      #6                  // Field name:Lorg/junit/rules/TestName;
       8: invokevirtual #46                 // Method org/junit/rules/TestName.getMethodName:()Ljava/lang/String;
      11: invokestatic  #47                 // Method org/apache/hadoop/hbase/TableName.valueOf:(Ljava/lang/String;)Lorg/apache/hadoop/hbase/TableName;
      14: invokeinterface #48,  2           // InterfaceMethod org/apache/hadoop/hbase/client/AsyncConnection.getTable:(Lorg/apache/hadoop/hbase/TableName;)Lorg/apache/hadoop/hbase/client/AsyncTable;
      19: new           #70                 // class org/apache/hadoop/hbase/client/Delete
      22: dup
      23: iconst_0
      24: invokestatic  #50                 // Method org/apache/hadoop/hbase/util/Bytes.toBytes:(I)[B
      27: invokespecial #71                 // Method org/apache/hadoop/hbase/client/Delete."<init>":([B)V
      30: invokeinterface #73,  2           // InterfaceMethod org/apache/hadoop/hbase/client/AsyncTable.delete:(Lorg/apache/hadoop/hbase/client/Delete;)Ljava/util/concurrent/CompletableFuture;
      35: invokevirtual #54                 // Method java/util/concurrent/CompletableFuture.join:()Ljava/lang/Object;
      38: pop
      39: aload_0
      40: getfield      #2                  // Field stub:Lorg/apache/hadoop/hbase/shaded/protobuf/generated/ClientProtos$ClientService$Interface;
      43: iconst_1
      44: invokestatic  #55                 // Method org/mockito/Mockito.times:(I)Lorg/mockito/verification/VerificationMode;
      47: invokestatic  #56                 // Method org/mockito/Mockito.verify:(Ljava/lang/Object;Lorg/mockito/verification/VerificationMode;)Ljava/lang/Object;
      50: checkcast     #7                  // class org/apache/hadoop/hbase/shaded/protobuf/generated/ClientProtos$ClientService$Interface
      53: aload_0
      54: iconst_0
      55: invokespecial #57                 // Method assertPriority:(I)Lorg/apache/hadoop/hbase/ipc/HBaseRpcController;
      58: ldc           #28                 // class org/apache/hadoop/hbase/shaded/protobuf/generated/ClientProtos$MutateRequest
      60: invokestatic  #16                 // Method org/mockito/ArgumentMatchers.any:(Ljava/lang/Class;)Ljava/lang/Object;
      63: checkcast     #28                 // class org/apache/hadoop/hbase/shaded/protobuf/generated/ClientProtos$MutateRequest
      66: invokestatic  #19                 // Method org/mockito/ArgumentMatchers.any:()Ljava/lang/Object;
      69: checkcast     #20                 // class org/apache/hbase/thirdparty/com/google/protobuf/RpcCallback
      72: invokeinterface #29,  4           // InterfaceMethod org/apache/hadoop/hbase/shaded/protobuf/generated/ClientProtos$ClientService$Interface.mutate:(Lorg/apache/hbase/thirdparty/com/google/protobuf/RpcController;Lorg/apache/hadoop/hbase/shaded/protobuf/generated/ClientProtos$MutateRequest;Lorg/apache/hbase/thirdparty/com/google/protobuf/RpcCallback;)V
      77: return

  public void testDeleteSystemTable();
    Code:
       0: aload_0
       1: getfield      #42                 // Field conn:Lorg/apache/hadoop/hbase/client/AsyncConnection;
       4: getstatic     #58                 // Field org/apache/hadoop/hbase/NamespaceDescriptor.SYSTEM_NAMESPACE_NAME_STR:Ljava/lang/String;
       7: aload_0
       8: getfield      #6                  // Field name:Lorg/junit/rules/TestName;
      11: invokevirtual #46                 // Method org/junit/rules/TestName.getMethodName:()Ljava/lang/String;
      14: invokestatic  #59                 // Method org/apache/hadoop/hbase/TableName.valueOf:(Ljava/lang/String;Ljava/lang/String;)Lorg/apache/hadoop/hbase/TableName;
      17: invokeinterface #48,  2           // InterfaceMethod org/apache/hadoop/hbase/client/AsyncConnection.getTable:(Lorg/apache/hadoop/hbase/TableName;)Lorg/apache/hadoop/hbase/client/AsyncTable;
      22: new           #70                 // class org/apache/hadoop/hbase/client/Delete
      25: dup
      26: iconst_0
      27: invokestatic  #50                 // Method org/apache/hadoop/hbase/util/Bytes.toBytes:(I)[B
      30: invokespecial #71                 // Method org/apache/hadoop/hbase/client/Delete."<init>":([B)V
      33: invokeinterface #73,  2           // InterfaceMethod org/apache/hadoop/hbase/client/AsyncTable.delete:(Lorg/apache/hadoop/hbase/client/Delete;)Ljava/util/concurrent/CompletableFuture;
      38: invokevirtual #54                 // Method java/util/concurrent/CompletableFuture.join:()Ljava/lang/Object;
      41: pop
      42: aload_0
      43: getfield      #2                  // Field stub:Lorg/apache/hadoop/hbase/shaded/protobuf/generated/ClientProtos$ClientService$Interface;
      46: iconst_1
      47: invokestatic  #55                 // Method org/mockito/Mockito.times:(I)Lorg/mockito/verification/VerificationMode;
      50: invokestatic  #56                 // Method org/mockito/Mockito.verify:(Ljava/lang/Object;Lorg/mockito/verification/VerificationMode;)Ljava/lang/Object;
      53: checkcast     #7                  // class org/apache/hadoop/hbase/shaded/protobuf/generated/ClientProtos$ClientService$Interface
      56: aload_0
      57: sipush        200
      60: invokespecial #57                 // Method assertPriority:(I)Lorg/apache/hadoop/hbase/ipc/HBaseRpcController;
      63: ldc           #28                 // class org/apache/hadoop/hbase/shaded/protobuf/generated/ClientProtos$MutateRequest
      65: invokestatic  #16                 // Method org/mockito/ArgumentMatchers.any:(Ljava/lang/Class;)Ljava/lang/Object;
      68: checkcast     #28                 // class org/apache/hadoop/hbase/shaded/protobuf/generated/ClientProtos$MutateRequest
      71: invokestatic  #19                 // Method org/mockito/ArgumentMatchers.any:()Ljava/lang/Object;
      74: checkcast     #20                 // class org/apache/hbase/thirdparty/com/google/protobuf/RpcCallback
      77: invokeinterface #29,  4           // InterfaceMethod org/apache/hadoop/hbase/shaded/protobuf/generated/ClientProtos$ClientService$Interface.mutate:(Lorg/apache/hbase/thirdparty/com/google/protobuf/RpcController;Lorg/apache/hadoop/hbase/shaded/protobuf/generated/ClientProtos$MutateRequest;Lorg/apache/hbase/thirdparty/com/google/protobuf/RpcCallback;)V
      82: return

  public void testDeleteMetaTable();
    Code:
       0: aload_0
       1: getfield      #42                 // Field conn:Lorg/apache/hadoop/hbase/client/AsyncConnection;
       4: getstatic     #60                 // Field org/apache/hadoop/hbase/TableName.META_TABLE_NAME:Lorg/apache/hadoop/hbase/TableName;
       7: invokeinterface #48,  2           // InterfaceMethod org/apache/hadoop/hbase/client/AsyncConnection.getTable:(Lorg/apache/hadoop/hbase/TableName;)Lorg/apache/hadoop/hbase/client/AsyncTable;
      12: new           #70                 // class org/apache/hadoop/hbase/client/Delete
      15: dup
      16: iconst_0
      17: invokestatic  #50                 // Method org/apache/hadoop/hbase/util/Bytes.toBytes:(I)[B
      20: invokespecial #71                 // Method org/apache/hadoop/hbase/client/Delete."<init>":([B)V
      23: invokeinterface #73,  2           // InterfaceMethod org/apache/hadoop/hbase/client/AsyncTable.delete:(Lorg/apache/hadoop/hbase/client/Delete;)Ljava/util/concurrent/CompletableFuture;
      28: invokevirtual #54                 // Method java/util/concurrent/CompletableFuture.join:()Ljava/lang/Object;
      31: pop
      32: aload_0
      33: getfield      #2                  // Field stub:Lorg/apache/hadoop/hbase/shaded/protobuf/generated/ClientProtos$ClientService$Interface;
      36: iconst_1
      37: invokestatic  #55                 // Method org/mockito/Mockito.times:(I)Lorg/mockito/verification/VerificationMode;
      40: invokestatic  #56                 // Method org/mockito/Mockito.verify:(Ljava/lang/Object;Lorg/mockito/verification/VerificationMode;)Ljava/lang/Object;
      43: checkcast     #7                  // class org/apache/hadoop/hbase/shaded/protobuf/generated/ClientProtos$ClientService$Interface
      46: aload_0
      47: sipush        200
      50: invokespecial #57                 // Method assertPriority:(I)Lorg/apache/hadoop/hbase/ipc/HBaseRpcController;
      53: ldc           #28                 // class org/apache/hadoop/hbase/shaded/protobuf/generated/ClientProtos$MutateRequest
      55: invokestatic  #16                 // Method org/mockito/ArgumentMatchers.any:(Ljava/lang/Class;)Ljava/lang/Object;
      58: checkcast     #28                 // class org/apache/hadoop/hbase/shaded/protobuf/generated/ClientProtos$MutateRequest
      61: invokestatic  #19                 // Method org/mockito/ArgumentMatchers.any:()Ljava/lang/Object;
      64: checkcast     #20                 // class org/apache/hbase/thirdparty/com/google/protobuf/RpcCallback
      67: invokeinterface #29,  4           // InterfaceMethod org/apache/hadoop/hbase/shaded/protobuf/generated/ClientProtos$ClientService$Interface.mutate:(Lorg/apache/hbase/thirdparty/com/google/protobuf/RpcController;Lorg/apache/hadoop/hbase/shaded/protobuf/generated/ClientProtos$MutateRequest;Lorg/apache/hbase/thirdparty/com/google/protobuf/RpcCallback;)V
      72: return

  public void testAppend();
    Code:
       0: aload_0
       1: getfield      #42                 // Field conn:Lorg/apache/hadoop/hbase/client/AsyncConnection;
       4: aload_0
       5: getfield      #6                  // Field name:Lorg/junit/rules/TestName;
       8: invokevirtual #46                 // Method org/junit/rules/TestName.getMethodName:()Ljava/lang/String;
      11: invokestatic  #47                 // Method org/apache/hadoop/hbase/TableName.valueOf:(Ljava/lang/String;)Lorg/apache/hadoop/hbase/TableName;
      14: invokeinterface #48,  2           // InterfaceMethod org/apache/hadoop/hbase/client/AsyncConnection.getTable:(Lorg/apache/hadoop/hbase/TableName;)Lorg/apache/hadoop/hbase/client/AsyncTable;
      19: new           #74                 // class org/apache/hadoop/hbase/client/Append
      22: dup
      23: iconst_0
      24: invokestatic  #50                 // Method org/apache/hadoop/hbase/util/Bytes.toBytes:(I)[B
      27: invokespecial #75                 // Method org/apache/hadoop/hbase/client/Append."<init>":([B)V
      30: bipush        14
      32: invokevirtual #76                 // Method org/apache/hadoop/hbase/client/Append.setPriority:(I)Lorg/apache/hadoop/hbase/client/Append;
      35: ldc           #64                 // String cf
      37: invokestatic  #65                 // Method org/apache/hadoop/hbase/util/Bytes.toBytes:(Ljava/lang/String;)[B
      40: ldc           #66                 // String cq
      42: invokestatic  #65                 // Method org/apache/hadoop/hbase/util/Bytes.toBytes:(Ljava/lang/String;)[B
      45: ldc           #67                 // String v
      47: invokestatic  #65                 // Method org/apache/hadoop/hbase/util/Bytes.toBytes:(Ljava/lang/String;)[B
      50: invokevirtual #77                 // Method org/apache/hadoop/hbase/client/Append.addColumn:([B[B[B)Lorg/apache/hadoop/hbase/client/Append;
      53: invokeinterface #78,  2           // InterfaceMethod org/apache/hadoop/hbase/client/AsyncTable.append:(Lorg/apache/hadoop/hbase/client/Append;)Ljava/util/concurrent/CompletableFuture;
      58: invokevirtual #54                 // Method java/util/concurrent/CompletableFuture.join:()Ljava/lang/Object;
      61: pop
      62: aload_0
      63: getfield      #2                  // Field stub:Lorg/apache/hadoop/hbase/shaded/protobuf/generated/ClientProtos$ClientService$Interface;
      66: iconst_1
      67: invokestatic  #55                 // Method org/mockito/Mockito.times:(I)Lorg/mockito/verification/VerificationMode;
      70: invokestatic  #56                 // Method org/mockito/Mockito.verify:(Ljava/lang/Object;Lorg/mockito/verification/VerificationMode;)Ljava/lang/Object;
      73: checkcast     #7                  // class org/apache/hadoop/hbase/shaded/protobuf/generated/ClientProtos$ClientService$Interface
      76: aload_0
      77: bipush        14
      79: invokespecial #57                 // Method assertPriority:(I)Lorg/apache/hadoop/hbase/ipc/HBaseRpcController;
      82: ldc           #28                 // class org/apache/hadoop/hbase/shaded/protobuf/generated/ClientProtos$MutateRequest
      84: invokestatic  #16                 // Method org/mockito/ArgumentMatchers.any:(Ljava/lang/Class;)Ljava/lang/Object;
      87: checkcast     #28                 // class org/apache/hadoop/hbase/shaded/protobuf/generated/ClientProtos$MutateRequest
      90: invokestatic  #19                 // Method org/mockito/ArgumentMatchers.any:()Ljava/lang/Object;
      93: checkcast     #20                 // class org/apache/hbase/thirdparty/com/google/protobuf/RpcCallback
      96: invokeinterface #29,  4           // InterfaceMethod org/apache/hadoop/hbase/shaded/protobuf/generated/ClientProtos$ClientService$Interface.mutate:(Lorg/apache/hbase/thirdparty/com/google/protobuf/RpcController;Lorg/apache/hadoop/hbase/shaded/protobuf/generated/ClientProtos$MutateRequest;Lorg/apache/hbase/thirdparty/com/google/protobuf/RpcCallback;)V
     101: return

  public void testAppendNormalTable();
    Code:
       0: aload_0
       1: getfield      #42                 // Field conn:Lorg/apache/hadoop/hbase/client/AsyncConnection;
       4: aload_0
       5: getfield      #6                  // Field name:Lorg/junit/rules/TestName;
       8: invokevirtual #46                 // Method org/junit/rules/TestName.getMethodName:()Ljava/lang/String;
      11: invokestatic  #47                 // Method org/apache/hadoop/hbase/TableName.valueOf:(Ljava/lang/String;)Lorg/apache/hadoop/hbase/TableName;
      14: invokeinterface #48,  2           // InterfaceMethod org/apache/hadoop/hbase/client/AsyncConnection.getTable:(Lorg/apache/hadoop/hbase/TableName;)Lorg/apache/hadoop/hbase/client/AsyncTable;
      19: new           #74                 // class org/apache/hadoop/hbase/client/Append
      22: dup
      23: iconst_0
      24: invokestatic  #50                 // Method org/apache/hadoop/hbase/util/Bytes.toBytes:(I)[B
      27: invokespecial #75                 // Method org/apache/hadoop/hbase/client/Append."<init>":([B)V
      30: ldc           #64                 // String cf
      32: invokestatic  #65                 // Method org/apache/hadoop/hbase/util/Bytes.toBytes:(Ljava/lang/String;)[B
      35: ldc           #66                 // String cq
      37: invokestatic  #65                 // Method org/apache/hadoop/hbase/util/Bytes.toBytes:(Ljava/lang/String;)[B
      40: ldc           #67                 // String v
      42: invokestatic  #65                 // Method org/apache/hadoop/hbase/util/Bytes.toBytes:(Ljava/lang/String;)[B
      45: invokevirtual #77                 // Method org/apache/hadoop/hbase/client/Append.addColumn:([B[B[B)Lorg/apache/hadoop/hbase/client/Append;
      48: invokeinterface #78,  2           // InterfaceMethod org/apache/hadoop/hbase/client/AsyncTable.append:(Lorg/apache/hadoop/hbase/client/Append;)Ljava/util/concurrent/CompletableFuture;
      53: invokevirtual #54                 // Method java/util/concurrent/CompletableFuture.join:()Ljava/lang/Object;
      56: pop
      57: aload_0
      58: getfield      #2                  // Field stub:Lorg/apache/hadoop/hbase/shaded/protobuf/generated/ClientProtos$ClientService$Interface;
      61: iconst_1
      62: invokestatic  #55                 // Method org/mockito/Mockito.times:(I)Lorg/mockito/verification/VerificationMode;
      65: invokestatic  #56                 // Method org/mockito/Mockito.verify:(Ljava/lang/Object;Lorg/mockito/verification/VerificationMode;)Ljava/lang/Object;
      68: checkcast     #7                  // class org/apache/hadoop/hbase/shaded/protobuf/generated/ClientProtos$ClientService$Interface
      71: aload_0
      72: iconst_0
      73: invokespecial #57                 // Method assertPriority:(I)Lorg/apache/hadoop/hbase/ipc/HBaseRpcController;
      76: ldc           #28                 // class org/apache/hadoop/hbase/shaded/protobuf/generated/ClientProtos$MutateRequest
      78: invokestatic  #16                 // Method org/mockito/ArgumentMatchers.any:(Ljava/lang/Class;)Ljava/lang/Object;
      81: checkcast     #28                 // class org/apache/hadoop/hbase/shaded/protobuf/generated/ClientProtos$MutateRequest
      84: invokestatic  #19                 // Method org/mockito/ArgumentMatchers.any:()Ljava/lang/Object;
      87: checkcast     #20                 // class org/apache/hbase/thirdparty/com/google/protobuf/RpcCallback
      90: invokeinterface #29,  4           // InterfaceMethod org/apache/hadoop/hbase/shaded/protobuf/generated/ClientProtos$ClientService$Interface.mutate:(Lorg/apache/hbase/thirdparty/com/google/protobuf/RpcController;Lorg/apache/hadoop/hbase/shaded/protobuf/generated/ClientProtos$MutateRequest;Lorg/apache/hbase/thirdparty/com/google/protobuf/RpcCallback;)V
      95: return

  public void testAppendSystemTable();
    Code:
       0: aload_0
       1: getfield      #42                 // Field conn:Lorg/apache/hadoop/hbase/client/AsyncConnection;
       4: getstatic     #58                 // Field org/apache/hadoop/hbase/NamespaceDescriptor.SYSTEM_NAMESPACE_NAME_STR:Ljava/lang/String;
       7: aload_0
       8: getfield      #6                  // Field name:Lorg/junit/rules/TestName;
      11: invokevirtual #46                 // Method org/junit/rules/TestName.getMethodName:()Ljava/lang/String;
      14: invokestatic  #59                 // Method org/apache/hadoop/hbase/TableName.valueOf:(Ljava/lang/String;Ljava/lang/String;)Lorg/apache/hadoop/hbase/TableName;
      17: invokeinterface #48,  2           // InterfaceMethod org/apache/hadoop/hbase/client/AsyncConnection.getTable:(Lorg/apache/hadoop/hbase/TableName;)Lorg/apache/hadoop/hbase/client/AsyncTable;
      22: new           #74                 // class org/apache/hadoop/hbase/client/Append
      25: dup
      26: iconst_0
      27: invokestatic  #50                 // Method org/apache/hadoop/hbase/util/Bytes.toBytes:(I)[B
      30: invokespecial #75                 // Method org/apache/hadoop/hbase/client/Append."<init>":([B)V
      33: ldc           #64                 // String cf
      35: invokestatic  #65                 // Method org/apache/hadoop/hbase/util/Bytes.toBytes:(Ljava/lang/String;)[B
      38: ldc           #66                 // String cq
      40: invokestatic  #65                 // Method org/apache/hadoop/hbase/util/Bytes.toBytes:(Ljava/lang/String;)[B
      43: ldc           #67                 // String v
      45: invokestatic  #65                 // Method org/apache/hadoop/hbase/util/Bytes.toBytes:(Ljava/lang/String;)[B
      48: invokevirtual #77                 // Method org/apache/hadoop/hbase/client/Append.addColumn:([B[B[B)Lorg/apache/hadoop/hbase/client/Append;
      51: invokeinterface #78,  2           // InterfaceMethod org/apache/hadoop/hbase/client/AsyncTable.append:(Lorg/apache/hadoop/hbase/client/Append;)Ljava/util/concurrent/CompletableFuture;
      56: invokevirtual #54                 // Method java/util/concurrent/CompletableFuture.join:()Ljava/lang/Object;
      59: pop
      60: aload_0
      61: getfield      #2                  // Field stub:Lorg/apache/hadoop/hbase/shaded/protobuf/generated/ClientProtos$ClientService$Interface;
      64: iconst_1
      65: invokestatic  #55                 // Method org/mockito/Mockito.times:(I)Lorg/mockito/verification/VerificationMode;
      68: invokestatic  #56                 // Method org/mockito/Mockito.verify:(Ljava/lang/Object;Lorg/mockito/verification/VerificationMode;)Ljava/lang/Object;
      71: checkcast     #7                  // class org/apache/hadoop/hbase/shaded/protobuf/generated/ClientProtos$ClientService$Interface
      74: aload_0
      75: sipush        200
      78: invokespecial #57                 // Method assertPriority:(I)Lorg/apache/hadoop/hbase/ipc/HBaseRpcController;
      81: ldc           #28                 // class org/apache/hadoop/hbase/shaded/protobuf/generated/ClientProtos$MutateRequest
      83: invokestatic  #16                 // Method org/mockito/ArgumentMatchers.any:(Ljava/lang/Class;)Ljava/lang/Object;
      86: checkcast     #28                 // class org/apache/hadoop/hbase/shaded/protobuf/generated/ClientProtos$MutateRequest
      89: invokestatic  #19                 // Method org/mockito/ArgumentMatchers.any:()Ljava/lang/Object;
      92: checkcast     #20                 // class org/apache/hbase/thirdparty/com/google/protobuf/RpcCallback
      95: invokeinterface #29,  4           // InterfaceMethod org/apache/hadoop/hbase/shaded/protobuf/generated/ClientProtos$ClientService$Interface.mutate:(Lorg/apache/hbase/thirdparty/com/google/protobuf/RpcController;Lorg/apache/hadoop/hbase/shaded/protobuf/generated/ClientProtos$MutateRequest;Lorg/apache/hbase/thirdparty/com/google/protobuf/RpcCallback;)V
     100: return

  public void testAppendMetaTable();
    Code:
       0: aload_0
       1: getfield      #42                 // Field conn:Lorg/apache/hadoop/hbase/client/AsyncConnection;
       4: getstatic     #60                 // Field org/apache/hadoop/hbase/TableName.META_TABLE_NAME:Lorg/apache/hadoop/hbase/TableName;
       7: invokeinterface #48,  2           // InterfaceMethod org/apache/hadoop/hbase/client/AsyncConnection.getTable:(Lorg/apache/hadoop/hbase/TableName;)Lorg/apache/hadoop/hbase/client/AsyncTable;
      12: new           #74                 // class org/apache/hadoop/hbase/client/Append
      15: dup
      16: iconst_0
      17: invokestatic  #50                 // Method org/apache/hadoop/hbase/util/Bytes.toBytes:(I)[B
      20: invokespecial #75                 // Method org/apache/hadoop/hbase/client/Append."<init>":([B)V
      23: ldc           #64                 // String cf
      25: invokestatic  #65                 // Method org/apache/hadoop/hbase/util/Bytes.toBytes:(Ljava/lang/String;)[B
      28: ldc           #66                 // String cq
      30: invokestatic  #65                 // Method org/apache/hadoop/hbase/util/Bytes.toBytes:(Ljava/lang/String;)[B
      33: ldc           #67                 // String v
      35: invokestatic  #65                 // Method org/apache/hadoop/hbase/util/Bytes.toBytes:(Ljava/lang/String;)[B
      38: invokevirtual #77                 // Method org/apache/hadoop/hbase/client/Append.addColumn:([B[B[B)Lorg/apache/hadoop/hbase/client/Append;
      41: invokeinterface #78,  2           // InterfaceMethod org/apache/hadoop/hbase/client/AsyncTable.append:(Lorg/apache/hadoop/hbase/client/Append;)Ljava/util/concurrent/CompletableFuture;
      46: invokevirtual #54                 // Method java/util/concurrent/CompletableFuture.join:()Ljava/lang/Object;
      49: pop
      50: aload_0
      51: getfield      #2                  // Field stub:Lorg/apache/hadoop/hbase/shaded/protobuf/generated/ClientProtos$ClientService$Interface;
      54: iconst_1
      55: invokestatic  #55                 // Method org/mockito/Mockito.times:(I)Lorg/mockito/verification/VerificationMode;
      58: invokestatic  #56                 // Method org/mockito/Mockito.verify:(Ljava/lang/Object;Lorg/mockito/verification/VerificationMode;)Ljava/lang/Object;
      61: checkcast     #7                  // class org/apache/hadoop/hbase/shaded/protobuf/generated/ClientProtos$ClientService$Interface
      64: aload_0
      65: sipush        200
      68: invokespecial #57                 // Method assertPriority:(I)Lorg/apache/hadoop/hbase/ipc/HBaseRpcController;
      71: ldc           #28                 // class org/apache/hadoop/hbase/shaded/protobuf/generated/ClientProtos$MutateRequest
      73: invokestatic  #16                 // Method org/mockito/ArgumentMatchers.any:(Ljava/lang/Class;)Ljava/lang/Object;
      76: checkcast     #28                 // class org/apache/hadoop/hbase/shaded/protobuf/generated/ClientProtos$MutateRequest
      79: invokestatic  #19                 // Method org/mockito/ArgumentMatchers.any:()Ljava/lang/Object;
      82: checkcast     #20                 // class org/apache/hbase/thirdparty/com/google/protobuf/RpcCallback
      85: invokeinterface #29,  4           // InterfaceMethod org/apache/hadoop/hbase/shaded/protobuf/generated/ClientProtos$ClientService$Interface.mutate:(Lorg/apache/hbase/thirdparty/com/google/protobuf/RpcController;Lorg/apache/hadoop/hbase/shaded/protobuf/generated/ClientProtos$MutateRequest;Lorg/apache/hbase/thirdparty/com/google/protobuf/RpcCallback;)V
      90: return

  public void testIncrement();
    Code:
       0: aload_0
       1: getfield      #42                 // Field conn:Lorg/apache/hadoop/hbase/client/AsyncConnection;
       4: aload_0
       5: getfield      #6                  // Field name:Lorg/junit/rules/TestName;
       8: invokevirtual #46                 // Method org/junit/rules/TestName.getMethodName:()Ljava/lang/String;
      11: invokestatic  #47                 // Method org/apache/hadoop/hbase/TableName.valueOf:(Ljava/lang/String;)Lorg/apache/hadoop/hbase/TableName;
      14: invokeinterface #48,  2           // InterfaceMethod org/apache/hadoop/hbase/client/AsyncConnection.getTable:(Lorg/apache/hadoop/hbase/TableName;)Lorg/apache/hadoop/hbase/client/AsyncTable;
      19: new           #79                 // class org/apache/hadoop/hbase/client/Increment
      22: dup
      23: iconst_0
      24: invokestatic  #50                 // Method org/apache/hadoop/hbase/util/Bytes.toBytes:(I)[B
      27: invokespecial #80                 // Method org/apache/hadoop/hbase/client/Increment."<init>":([B)V
      30: ldc           #64                 // String cf
      32: invokestatic  #65                 // Method org/apache/hadoop/hbase/util/Bytes.toBytes:(Ljava/lang/String;)[B
      35: ldc           #66                 // String cq
      37: invokestatic  #65                 // Method org/apache/hadoop/hbase/util/Bytes.toBytes:(Ljava/lang/String;)[B
      40: lconst_1
      41: invokevirtual #81                 // Method org/apache/hadoop/hbase/client/Increment.addColumn:([B[BJ)Lorg/apache/hadoop/hbase/client/Increment;
      44: bipush        15
      46: invokevirtual #82                 // Method org/apache/hadoop/hbase/client/Increment.setPriority:(I)Lorg/apache/hadoop/hbase/client/Increment;
      49: invokeinterface #83,  2           // InterfaceMethod org/apache/hadoop/hbase/client/AsyncTable.increment:(Lorg/apache/hadoop/hbase/client/Increment;)Ljava/util/concurrent/CompletableFuture;
      54: invokevirtual #54                 // Method java/util/concurrent/CompletableFuture.join:()Ljava/lang/Object;
      57: pop
      58: aload_0
      59: getfield      #2                  // Field stub:Lorg/apache/hadoop/hbase/shaded/protobuf/generated/ClientProtos$ClientService$Interface;
      62: iconst_1
      63: invokestatic  #55                 // Method org/mockito/Mockito.times:(I)Lorg/mockito/verification/VerificationMode;
      66: invokestatic  #56                 // Method org/mockito/Mockito.verify:(Ljava/lang/Object;Lorg/mockito/verification/VerificationMode;)Ljava/lang/Object;
      69: checkcast     #7                  // class org/apache/hadoop/hbase/shaded/protobuf/generated/ClientProtos$ClientService$Interface
      72: aload_0
      73: bipush        15
      75: invokespecial #57                 // Method assertPriority:(I)Lorg/apache/hadoop/hbase/ipc/HBaseRpcController;
      78: ldc           #28                 // class org/apache/hadoop/hbase/shaded/protobuf/generated/ClientProtos$MutateRequest
      80: invokestatic  #16                 // Method org/mockito/ArgumentMatchers.any:(Ljava/lang/Class;)Ljava/lang/Object;
      83: checkcast     #28                 // class org/apache/hadoop/hbase/shaded/protobuf/generated/ClientProtos$MutateRequest
      86: invokestatic  #19                 // Method org/mockito/ArgumentMatchers.any:()Ljava/lang/Object;
      89: checkcast     #20                 // class org/apache/hbase/thirdparty/com/google/protobuf/RpcCallback
      92: invokeinterface #29,  4           // InterfaceMethod org/apache/hadoop/hbase/shaded/protobuf/generated/ClientProtos$ClientService$Interface.mutate:(Lorg/apache/hbase/thirdparty/com/google/protobuf/RpcController;Lorg/apache/hadoop/hbase/shaded/protobuf/generated/ClientProtos$MutateRequest;Lorg/apache/hbase/thirdparty/com/google/protobuf/RpcCallback;)V
      97: return

  public void testIncrementNormalTable();
    Code:
       0: aload_0
       1: getfield      #42                 // Field conn:Lorg/apache/hadoop/hbase/client/AsyncConnection;
       4: aload_0
       5: getfield      #6                  // Field name:Lorg/junit/rules/TestName;
       8: invokevirtual #46                 // Method org/junit/rules/TestName.getMethodName:()Ljava/lang/String;
      11: invokestatic  #47                 // Method org/apache/hadoop/hbase/TableName.valueOf:(Ljava/lang/String;)Lorg/apache/hadoop/hbase/TableName;
      14: invokeinterface #48,  2           // InterfaceMethod org/apache/hadoop/hbase/client/AsyncConnection.getTable:(Lorg/apache/hadoop/hbase/TableName;)Lorg/apache/hadoop/hbase/client/AsyncTable;
      19: iconst_0
      20: invokestatic  #50                 // Method org/apache/hadoop/hbase/util/Bytes.toBytes:(I)[B
      23: ldc           #64                 // String cf
      25: invokestatic  #65                 // Method org/apache/hadoop/hbase/util/Bytes.toBytes:(Ljava/lang/String;)[B
      28: ldc           #66                 // String cq
      30: invokestatic  #65                 // Method org/apache/hadoop/hbase/util/Bytes.toBytes:(Ljava/lang/String;)[B
      33: lconst_1
      34: invokeinterface #84,  6           // InterfaceMethod org/apache/hadoop/hbase/client/AsyncTable.incrementColumnValue:([B[B[BJ)Ljava/util/concurrent/CompletableFuture;
      39: invokevirtual #54                 // Method java/util/concurrent/CompletableFuture.join:()Ljava/lang/Object;
      42: pop
      43: aload_0
      44: getfield      #2                  // Field stub:Lorg/apache/hadoop/hbase/shaded/protobuf/generated/ClientProtos$ClientService$Interface;
      47: iconst_1
      48: invokestatic  #55                 // Method org/mockito/Mockito.times:(I)Lorg/mockito/verification/VerificationMode;
      51: invokestatic  #56                 // Method org/mockito/Mockito.verify:(Ljava/lang/Object;Lorg/mockito/verification/VerificationMode;)Ljava/lang/Object;
      54: checkcast     #7                  // class org/apache/hadoop/hbase/shaded/protobuf/generated/ClientProtos$ClientService$Interface
      57: aload_0
      58: iconst_0
      59: invokespecial #57                 // Method assertPriority:(I)Lorg/apache/hadoop/hbase/ipc/HBaseRpcController;
      62: ldc           #28                 // class org/apache/hadoop/hbase/shaded/protobuf/generated/ClientProtos$MutateRequest
      64: invokestatic  #16                 // Method org/mockito/ArgumentMatchers.any:(Ljava/lang/Class;)Ljava/lang/Object;
      67: checkcast     #28                 // class org/apache/hadoop/hbase/shaded/protobuf/generated/ClientProtos$MutateRequest
      70: invokestatic  #19                 // Method org/mockito/ArgumentMatchers.any:()Ljava/lang/Object;
      73: checkcast     #20                 // class org/apache/hbase/thirdparty/com/google/protobuf/RpcCallback
      76: invokeinterface #29,  4           // InterfaceMethod org/apache/hadoop/hbase/shaded/protobuf/generated/ClientProtos$ClientService$Interface.mutate:(Lorg/apache/hbase/thirdparty/com/google/protobuf/RpcController;Lorg/apache/hadoop/hbase/shaded/protobuf/generated/ClientProtos$MutateRequest;Lorg/apache/hbase/thirdparty/com/google/protobuf/RpcCallback;)V
      81: return

  public void testIncrementSystemTable();
    Code:
       0: aload_0
       1: getfield      #42                 // Field conn:Lorg/apache/hadoop/hbase/client/AsyncConnection;
       4: getstatic     #58                 // Field org/apache/hadoop/hbase/NamespaceDescriptor.SYSTEM_NAMESPACE_NAME_STR:Ljava/lang/String;
       7: aload_0
       8: getfield      #6                  // Field name:Lorg/junit/rules/TestName;
      11: invokevirtual #46                 // Method org/junit/rules/TestName.getMethodName:()Ljava/lang/String;
      14: invokestatic  #59                 // Method org/apache/hadoop/hbase/TableName.valueOf:(Ljava/lang/String;Ljava/lang/String;)Lorg/apache/hadoop/hbase/TableName;
      17: invokeinterface #48,  2           // InterfaceMethod org/apache/hadoop/hbase/client/AsyncConnection.getTable:(Lorg/apache/hadoop/hbase/TableName;)Lorg/apache/hadoop/hbase/client/AsyncTable;
      22: iconst_0
      23: invokestatic  #50                 // Method org/apache/hadoop/hbase/util/Bytes.toBytes:(I)[B
      26: ldc           #64                 // String cf
      28: invokestatic  #65                 // Method org/apache/hadoop/hbase/util/Bytes.toBytes:(Ljava/lang/String;)[B
      31: ldc           #66                 // String cq
      33: invokestatic  #65                 // Method org/apache/hadoop/hbase/util/Bytes.toBytes:(Ljava/lang/String;)[B
      36: lconst_1
      37: invokeinterface #84,  6           // InterfaceMethod org/apache/hadoop/hbase/client/AsyncTable.incrementColumnValue:([B[B[BJ)Ljava/util/concurrent/CompletableFuture;
      42: invokevirtual #54                 // Method java/util/concurrent/CompletableFuture.join:()Ljava/lang/Object;
      45: pop
      46: aload_0
      47: getfield      #2                  // Field stub:Lorg/apache/hadoop/hbase/shaded/protobuf/generated/ClientProtos$ClientService$Interface;
      50: iconst_1
      51: invokestatic  #55                 // Method org/mockito/Mockito.times:(I)Lorg/mockito/verification/VerificationMode;
      54: invokestatic  #56                 // Method org/mockito/Mockito.verify:(Ljava/lang/Object;Lorg/mockito/verification/VerificationMode;)Ljava/lang/Object;
      57: checkcast     #7                  // class org/apache/hadoop/hbase/shaded/protobuf/generated/ClientProtos$ClientService$Interface
      60: aload_0
      61: sipush        200
      64: invokespecial #57                 // Method assertPriority:(I)Lorg/apache/hadoop/hbase/ipc/HBaseRpcController;
      67: ldc           #28                 // class org/apache/hadoop/hbase/shaded/protobuf/generated/ClientProtos$MutateRequest
      69: invokestatic  #16                 // Method org/mockito/ArgumentMatchers.any:(Ljava/lang/Class;)Ljava/lang/Object;
      72: checkcast     #28                 // class org/apache/hadoop/hbase/shaded/protobuf/generated/ClientProtos$MutateRequest
      75: invokestatic  #19                 // Method org/mockito/ArgumentMatchers.any:()Ljava/lang/Object;
      78: checkcast     #20                 // class org/apache/hbase/thirdparty/com/google/protobuf/RpcCallback
      81: invokeinterface #29,  4           // InterfaceMethod org/apache/hadoop/hbase/shaded/protobuf/generated/ClientProtos$ClientService$Interface.mutate:(Lorg/apache/hbase/thirdparty/com/google/protobuf/RpcController;Lorg/apache/hadoop/hbase/shaded/protobuf/generated/ClientProtos$MutateRequest;Lorg/apache/hbase/thirdparty/com/google/protobuf/RpcCallback;)V
      86: return

  public void testIncrementMetaTable();
    Code:
       0: aload_0
       1: getfield      #42                 // Field conn:Lorg/apache/hadoop/hbase/client/AsyncConnection;
       4: getstatic     #60                 // Field org/apache/hadoop/hbase/TableName.META_TABLE_NAME:Lorg/apache/hadoop/hbase/TableName;
       7: invokeinterface #48,  2           // InterfaceMethod org/apache/hadoop/hbase/client/AsyncConnection.getTable:(Lorg/apache/hadoop/hbase/TableName;)Lorg/apache/hadoop/hbase/client/AsyncTable;
      12: iconst_0
      13: invokestatic  #50                 // Method org/apache/hadoop/hbase/util/Bytes.toBytes:(I)[B
      16: ldc           #64                 // String cf
      18: invokestatic  #65                 // Method org/apache/hadoop/hbase/util/Bytes.toBytes:(Ljava/lang/String;)[B
      21: ldc           #66                 // String cq
      23: invokestatic  #65                 // Method org/apache/hadoop/hbase/util/Bytes.toBytes:(Ljava/lang/String;)[B
      26: lconst_1
      27: invokeinterface #84,  6           // InterfaceMethod org/apache/hadoop/hbase/client/AsyncTable.incrementColumnValue:([B[B[BJ)Ljava/util/concurrent/CompletableFuture;
      32: invokevirtual #54                 // Method java/util/concurrent/CompletableFuture.join:()Ljava/lang/Object;
      35: pop
      36: aload_0
      37: getfield      #2                  // Field stub:Lorg/apache/hadoop/hbase/shaded/protobuf/generated/ClientProtos$ClientService$Interface;
      40: iconst_1
      41: invokestatic  #55                 // Method org/mockito/Mockito.times:(I)Lorg/mockito/verification/VerificationMode;
      44: invokestatic  #56                 // Method org/mockito/Mockito.verify:(Ljava/lang/Object;Lorg/mockito/verification/VerificationMode;)Ljava/lang/Object;
      47: checkcast     #7                  // class org/apache/hadoop/hbase/shaded/protobuf/generated/ClientProtos$ClientService$Interface
      50: aload_0
      51: sipush        200
      54: invokespecial #57                 // Method assertPriority:(I)Lorg/apache/hadoop/hbase/ipc/HBaseRpcController;
      57: ldc           #28                 // class org/apache/hadoop/hbase/shaded/protobuf/generated/ClientProtos$MutateRequest
      59: invokestatic  #16                 // Method org/mockito/ArgumentMatchers.any:(Ljava/lang/Class;)Ljava/lang/Object;
      62: checkcast     #28                 // class org/apache/hadoop/hbase/shaded/protobuf/generated/ClientProtos$MutateRequest
      65: invokestatic  #19                 // Method org/mockito/ArgumentMatchers.any:()Ljava/lang/Object;
      68: checkcast     #20                 // class org/apache/hbase/thirdparty/com/google/protobuf/RpcCallback
      71: invokeinterface #29,  4           // InterfaceMethod org/apache/hadoop/hbase/shaded/protobuf/generated/ClientProtos$ClientService$Interface.mutate:(Lorg/apache/hbase/thirdparty/com/google/protobuf/RpcController;Lorg/apache/hadoop/hbase/shaded/protobuf/generated/ClientProtos$MutateRequest;Lorg/apache/hbase/thirdparty/com/google/protobuf/RpcCallback;)V
      76: return

  public void testCheckAndPut();
    Code:
       0: aload_0
       1: getfield      #42                 // Field conn:Lorg/apache/hadoop/hbase/client/AsyncConnection;
       4: aload_0
       5: getfield      #6                  // Field name:Lorg/junit/rules/TestName;
       8: invokevirtual #46                 // Method org/junit/rules/TestName.getMethodName:()Ljava/lang/String;
      11: invokestatic  #47                 // Method org/apache/hadoop/hbase/TableName.valueOf:(Ljava/lang/String;)Lorg/apache/hadoop/hbase/TableName;
      14: invokeinterface #48,  2           // InterfaceMethod org/apache/hadoop/hbase/client/AsyncConnection.getTable:(Lorg/apache/hadoop/hbase/TableName;)Lorg/apache/hadoop/hbase/client/AsyncTable;
      19: iconst_0
      20: invokestatic  #50                 // Method org/apache/hadoop/hbase/util/Bytes.toBytes:(I)[B
      23: ldc           #64                 // String cf
      25: invokestatic  #65                 // Method org/apache/hadoop/hbase/util/Bytes.toBytes:(Ljava/lang/String;)[B
      28: invokeinterface #85,  3           // InterfaceMethod org/apache/hadoop/hbase/client/AsyncTable.checkAndMutate:([B[B)Lorg/apache/hadoop/hbase/client/AsyncTable$CheckAndMutateBuilder;
      33: ldc           #66                 // String cq
      35: invokestatic  #65                 // Method org/apache/hadoop/hbase/util/Bytes.toBytes:(Ljava/lang/String;)[B
      38: invokeinterface #86,  2           // InterfaceMethod org/apache/hadoop/hbase/client/AsyncTable$CheckAndMutateBuilder.qualifier:([B)Lorg/apache/hadoop/hbase/client/AsyncTable$CheckAndMutateBuilder;
      43: invokeinterface #87,  1           // InterfaceMethod org/apache/hadoop/hbase/client/AsyncTable$CheckAndMutateBuilder.ifNotExists:()Lorg/apache/hadoop/hbase/client/AsyncTable$CheckAndMutateBuilder;
      48: new           #61                 // class org/apache/hadoop/hbase/client/Put
      51: dup
      52: iconst_0
      53: invokestatic  #50                 // Method org/apache/hadoop/hbase/util/Bytes.toBytes:(I)[B
      56: invokespecial #62                 // Method org/apache/hadoop/hbase/client/Put."<init>":([B)V
      59: ldc           #64                 // String cf
      61: invokestatic  #65                 // Method org/apache/hadoop/hbase/util/Bytes.toBytes:(Ljava/lang/String;)[B
      64: ldc           #66                 // String cq
      66: invokestatic  #65                 // Method org/apache/hadoop/hbase/util/Bytes.toBytes:(Ljava/lang/String;)[B
      69: ldc           #67                 // String v
      71: invokestatic  #65                 // Method org/apache/hadoop/hbase/util/Bytes.toBytes:(Ljava/lang/String;)[B
      74: invokevirtual #68                 // Method org/apache/hadoop/hbase/client/Put.addColumn:([B[B[B)Lorg/apache/hadoop/hbase/client/Put;
      77: bipush        16
      79: invokevirtual #63                 // Method org/apache/hadoop/hbase/client/Put.setPriority:(I)Lorg/apache/hadoop/hbase/client/Put;
      82: invokeinterface #88,  2           // InterfaceMethod org/apache/hadoop/hbase/client/AsyncTable$CheckAndMutateBuilder.thenPut:(Lorg/apache/hadoop/hbase/client/Put;)Ljava/util/concurrent/CompletableFuture;
      87: invokevirtual #54                 // Method java/util/concurrent/CompletableFuture.join:()Ljava/lang/Object;
      90: pop
      91: aload_0
      92: getfield      #2                  // Field stub:Lorg/apache/hadoop/hbase/shaded/protobuf/generated/ClientProtos$ClientService$Interface;
      95: iconst_1
      96: invokestatic  #55                 // Method org/mockito/Mockito.times:(I)Lorg/mockito/verification/VerificationMode;
      99: invokestatic  #56                 // Method org/mockito/Mockito.verify:(Ljava/lang/Object;Lorg/mockito/verification/VerificationMode;)Ljava/lang/Object;
     102: checkcast     #7                  // class org/apache/hadoop/hbase/shaded/protobuf/generated/ClientProtos$ClientService$Interface
     105: aload_0
     106: bipush        16
     108: invokespecial #57                 // Method assertPriority:(I)Lorg/apache/hadoop/hbase/ipc/HBaseRpcController;
     111: ldc           #28                 // class org/apache/hadoop/hbase/shaded/protobuf/generated/ClientProtos$MutateRequest
     113: invokestatic  #16                 // Method org/mockito/ArgumentMatchers.any:(Ljava/lang/Class;)Ljava/lang/Object;
     116: checkcast     #28                 // class org/apache/hadoop/hbase/shaded/protobuf/generated/ClientProtos$MutateRequest
     119: invokestatic  #19                 // Method org/mockito/ArgumentMatchers.any:()Ljava/lang/Object;
     122: checkcast     #20                 // class org/apache/hbase/thirdparty/com/google/protobuf/RpcCallback
     125: invokeinterface #29,  4           // InterfaceMethod org/apache/hadoop/hbase/shaded/protobuf/generated/ClientProtos$ClientService$Interface.mutate:(Lorg/apache/hbase/thirdparty/com/google/protobuf/RpcController;Lorg/apache/hadoop/hbase/shaded/protobuf/generated/ClientProtos$MutateRequest;Lorg/apache/hbase/thirdparty/com/google/protobuf/RpcCallback;)V
     130: return

  public void testCheckAndPutNormalTable();
    Code:
       0: aload_0
       1: getfield      #42                 // Field conn:Lorg/apache/hadoop/hbase/client/AsyncConnection;
       4: aload_0
       5: getfield      #6                  // Field name:Lorg/junit/rules/TestName;
       8: invokevirtual #46                 // Method org/junit/rules/TestName.getMethodName:()Ljava/lang/String;
      11: invokestatic  #47                 // Method org/apache/hadoop/hbase/TableName.valueOf:(Ljava/lang/String;)Lorg/apache/hadoop/hbase/TableName;
      14: invokeinterface #48,  2           // InterfaceMethod org/apache/hadoop/hbase/client/AsyncConnection.getTable:(Lorg/apache/hadoop/hbase/TableName;)Lorg/apache/hadoop/hbase/client/AsyncTable;
      19: iconst_0
      20: invokestatic  #50                 // Method org/apache/hadoop/hbase/util/Bytes.toBytes:(I)[B
      23: ldc           #64                 // String cf
      25: invokestatic  #65                 // Method org/apache/hadoop/hbase/util/Bytes.toBytes:(Ljava/lang/String;)[B
      28: invokeinterface #85,  3           // InterfaceMethod org/apache/hadoop/hbase/client/AsyncTable.checkAndMutate:([B[B)Lorg/apache/hadoop/hbase/client/AsyncTable$CheckAndMutateBuilder;
      33: ldc           #66                 // String cq
      35: invokestatic  #65                 // Method org/apache/hadoop/hbase/util/Bytes.toBytes:(Ljava/lang/String;)[B
      38: invokeinterface #86,  2           // InterfaceMethod org/apache/hadoop/hbase/client/AsyncTable$CheckAndMutateBuilder.qualifier:([B)Lorg/apache/hadoop/hbase/client/AsyncTable$CheckAndMutateBuilder;
      43: invokeinterface #87,  1           // InterfaceMethod org/apache/hadoop/hbase/client/AsyncTable$CheckAndMutateBuilder.ifNotExists:()Lorg/apache/hadoop/hbase/client/AsyncTable$CheckAndMutateBuilder;
      48: new           #61                 // class org/apache/hadoop/hbase/client/Put
      51: dup
      52: iconst_0
      53: invokestatic  #50                 // Method org/apache/hadoop/hbase/util/Bytes.toBytes:(I)[B
      56: invokespecial #62                 // Method org/apache/hadoop/hbase/client/Put."<init>":([B)V
      59: ldc           #64                 // String cf
      61: invokestatic  #65                 // Method org/apache/hadoop/hbase/util/Bytes.toBytes:(Ljava/lang/String;)[B
      64: ldc           #66                 // String cq
      66: invokestatic  #65                 // Method org/apache/hadoop/hbase/util/Bytes.toBytes:(Ljava/lang/String;)[B
      69: ldc           #67                 // String v
      71: invokestatic  #65                 // Method org/apache/hadoop/hbase/util/Bytes.toBytes:(Ljava/lang/String;)[B
      74: invokevirtual #68                 // Method org/apache/hadoop/hbase/client/Put.addColumn:([B[B[B)Lorg/apache/hadoop/hbase/client/Put;
      77: invokeinterface #88,  2           // InterfaceMethod org/apache/hadoop/hbase/client/AsyncTable$CheckAndMutateBuilder.thenPut:(Lorg/apache/hadoop/hbase/client/Put;)Ljava/util/concurrent/CompletableFuture;
      82: invokevirtual #54                 // Method java/util/concurrent/CompletableFuture.join:()Ljava/lang/Object;
      85: pop
      86: aload_0
      87: getfield      #2                  // Field stub:Lorg/apache/hadoop/hbase/shaded/protobuf/generated/ClientProtos$ClientService$Interface;
      90: iconst_1
      91: invokestatic  #55                 // Method org/mockito/Mockito.times:(I)Lorg/mockito/verification/VerificationMode;
      94: invokestatic  #56                 // Method org/mockito/Mockito.verify:(Ljava/lang/Object;Lorg/mockito/verification/VerificationMode;)Ljava/lang/Object;
      97: checkcast     #7                  // class org/apache/hadoop/hbase/shaded/protobuf/generated/ClientProtos$ClientService$Interface
     100: aload_0
     101: iconst_0
     102: invokespecial #57                 // Method assertPriority:(I)Lorg/apache/hadoop/hbase/ipc/HBaseRpcController;
     105: ldc           #28                 // class org/apache/hadoop/hbase/shaded/protobuf/generated/ClientProtos$MutateRequest
     107: invokestatic  #16                 // Method org/mockito/ArgumentMatchers.any:(Ljava/lang/Class;)Ljava/lang/Object;
     110: checkcast     #28                 // class org/apache/hadoop/hbase/shaded/protobuf/generated/ClientProtos$MutateRequest
     113: invokestatic  #19                 // Method org/mockito/ArgumentMatchers.any:()Ljava/lang/Object;
     116: checkcast     #20                 // class org/apache/hbase/thirdparty/com/google/protobuf/RpcCallback
     119: invokeinterface #29,  4           // InterfaceMethod org/apache/hadoop/hbase/shaded/protobuf/generated/ClientProtos$ClientService$Interface.mutate:(Lorg/apache/hbase/thirdparty/com/google/protobuf/RpcController;Lorg/apache/hadoop/hbase/shaded/protobuf/generated/ClientProtos$MutateRequest;Lorg/apache/hbase/thirdparty/com/google/protobuf/RpcCallback;)V
     124: return

  public void testCheckAndPutSystemTable();
    Code:
       0: aload_0
       1: getfield      #42                 // Field conn:Lorg/apache/hadoop/hbase/client/AsyncConnection;
       4: getstatic     #58                 // Field org/apache/hadoop/hbase/NamespaceDescriptor.SYSTEM_NAMESPACE_NAME_STR:Ljava/lang/String;
       7: aload_0
       8: getfield      #6                  // Field name:Lorg/junit/rules/TestName;
      11: invokevirtual #46                 // Method org/junit/rules/TestName.getMethodName:()Ljava/lang/String;
      14: invokestatic  #59                 // Method org/apache/hadoop/hbase/TableName.valueOf:(Ljava/lang/String;Ljava/lang/String;)Lorg/apache/hadoop/hbase/TableName;
      17: invokeinterface #48,  2           // InterfaceMethod org/apache/hadoop/hbase/client/AsyncConnection.getTable:(Lorg/apache/hadoop/hbase/TableName;)Lorg/apache/hadoop/hbase/client/AsyncTable;
      22: iconst_0
      23: invokestatic  #50                 // Method org/apache/hadoop/hbase/util/Bytes.toBytes:(I)[B
      26: ldc           #64                 // String cf
      28: invokestatic  #65                 // Method org/apache/hadoop/hbase/util/Bytes.toBytes:(Ljava/lang/String;)[B
      31: invokeinterface #85,  3           // InterfaceMethod org/apache/hadoop/hbase/client/AsyncTable.checkAndMutate:([B[B)Lorg/apache/hadoop/hbase/client/AsyncTable$CheckAndMutateBuilder;
      36: ldc           #66                 // String cq
      38: invokestatic  #65                 // Method org/apache/hadoop/hbase/util/Bytes.toBytes:(Ljava/lang/String;)[B
      41: invokeinterface #86,  2           // InterfaceMethod org/apache/hadoop/hbase/client/AsyncTable$CheckAndMutateBuilder.qualifier:([B)Lorg/apache/hadoop/hbase/client/AsyncTable$CheckAndMutateBuilder;
      46: invokeinterface #87,  1           // InterfaceMethod org/apache/hadoop/hbase/client/AsyncTable$CheckAndMutateBuilder.ifNotExists:()Lorg/apache/hadoop/hbase/client/AsyncTable$CheckAndMutateBuilder;
      51: new           #61                 // class org/apache/hadoop/hbase/client/Put
      54: dup
      55: iconst_0
      56: invokestatic  #50                 // Method org/apache/hadoop/hbase/util/Bytes.toBytes:(I)[B
      59: invokespecial #62                 // Method org/apache/hadoop/hbase/client/Put."<init>":([B)V
      62: ldc           #64                 // String cf
      64: invokestatic  #65                 // Method org/apache/hadoop/hbase/util/Bytes.toBytes:(Ljava/lang/String;)[B
      67: ldc           #66                 // String cq
      69: invokestatic  #65                 // Method org/apache/hadoop/hbase/util/Bytes.toBytes:(Ljava/lang/String;)[B
      72: ldc           #67                 // String v
      74: invokestatic  #65                 // Method org/apache/hadoop/hbase/util/Bytes.toBytes:(Ljava/lang/String;)[B
      77: invokevirtual #68                 // Method org/apache/hadoop/hbase/client/Put.addColumn:([B[B[B)Lorg/apache/hadoop/hbase/client/Put;
      80: invokeinterface #88,  2           // InterfaceMethod org/apache/hadoop/hbase/client/AsyncTable$CheckAndMutateBuilder.thenPut:(Lorg/apache/hadoop/hbase/client/Put;)Ljava/util/concurrent/CompletableFuture;
      85: invokevirtual #54                 // Method java/util/concurrent/CompletableFuture.join:()Ljava/lang/Object;
      88: pop
      89: aload_0
      90: getfield      #2                  // Field stub:Lorg/apache/hadoop/hbase/shaded/protobuf/generated/ClientProtos$ClientService$Interface;
      93: iconst_1
      94: invokestatic  #55                 // Method org/mockito/Mockito.times:(I)Lorg/mockito/verification/VerificationMode;
      97: invokestatic  #56                 // Method org/mockito/Mockito.verify:(Ljava/lang/Object;Lorg/mockito/verification/VerificationMode;)Ljava/lang/Object;
     100: checkcast     #7                  // class org/apache/hadoop/hbase/shaded/protobuf/generated/ClientProtos$ClientService$Interface
     103: aload_0
     104: sipush        200
     107: invokespecial #57                 // Method assertPriority:(I)Lorg/apache/hadoop/hbase/ipc/HBaseRpcController;
     110: ldc           #28                 // class org/apache/hadoop/hbase/shaded/protobuf/generated/ClientProtos$MutateRequest
     112: invokestatic  #16                 // Method org/mockito/ArgumentMatchers.any:(Ljava/lang/Class;)Ljava/lang/Object;
     115: checkcast     #28                 // class org/apache/hadoop/hbase/shaded/protobuf/generated/ClientProtos$MutateRequest
     118: invokestatic  #19                 // Method org/mockito/ArgumentMatchers.any:()Ljava/lang/Object;
     121: checkcast     #20                 // class org/apache/hbase/thirdparty/com/google/protobuf/RpcCallback
     124: invokeinterface #29,  4           // InterfaceMethod org/apache/hadoop/hbase/shaded/protobuf/generated/ClientProtos$ClientService$Interface.mutate:(Lorg/apache/hbase/thirdparty/com/google/protobuf/RpcController;Lorg/apache/hadoop/hbase/shaded/protobuf/generated/ClientProtos$MutateRequest;Lorg/apache/hbase/thirdparty/com/google/protobuf/RpcCallback;)V
     129: return

  public void testCheckAndPutMetaTable();
    Code:
       0: aload_0
       1: getfield      #42                 // Field conn:Lorg/apache/hadoop/hbase/client/AsyncConnection;
       4: getstatic     #60                 // Field org/apache/hadoop/hbase/TableName.META_TABLE_NAME:Lorg/apache/hadoop/hbase/TableName;
       7: invokeinterface #48,  2           // InterfaceMethod org/apache/hadoop/hbase/client/AsyncConnection.getTable:(Lorg/apache/hadoop/hbase/TableName;)Lorg/apache/hadoop/hbase/client/AsyncTable;
      12: iconst_0
      13: invokestatic  #50                 // Method org/apache/hadoop/hbase/util/Bytes.toBytes:(I)[B
      16: ldc           #64                 // String cf
      18: invokestatic  #65                 // Method org/apache/hadoop/hbase/util/Bytes.toBytes:(Ljava/lang/String;)[B
      21: invokeinterface #85,  3           // InterfaceMethod org/apache/hadoop/hbase/client/AsyncTable.checkAndMutate:([B[B)Lorg/apache/hadoop/hbase/client/AsyncTable$CheckAndMutateBuilder;
      26: ldc           #66                 // String cq
      28: invokestatic  #65                 // Method org/apache/hadoop/hbase/util/Bytes.toBytes:(Ljava/lang/String;)[B
      31: invokeinterface #86,  2           // InterfaceMethod org/apache/hadoop/hbase/client/AsyncTable$CheckAndMutateBuilder.qualifier:([B)Lorg/apache/hadoop/hbase/client/AsyncTable$CheckAndMutateBuilder;
      36: invokeinterface #87,  1           // InterfaceMethod org/apache/hadoop/hbase/client/AsyncTable$CheckAndMutateBuilder.ifNotExists:()Lorg/apache/hadoop/hbase/client/AsyncTable$CheckAndMutateBuilder;
      41: new           #61                 // class org/apache/hadoop/hbase/client/Put
      44: dup
      45: iconst_0
      46: invokestatic  #50                 // Method org/apache/hadoop/hbase/util/Bytes.toBytes:(I)[B
      49: invokespecial #62                 // Method org/apache/hadoop/hbase/client/Put."<init>":([B)V
      52: ldc           #64                 // String cf
      54: invokestatic  #65                 // Method org/apache/hadoop/hbase/util/Bytes.toBytes:(Ljava/lang/String;)[B
      57: ldc           #66                 // String cq
      59: invokestatic  #65                 // Method org/apache/hadoop/hbase/util/Bytes.toBytes:(Ljava/lang/String;)[B
      62: ldc           #67                 // String v
      64: invokestatic  #65                 // Method org/apache/hadoop/hbase/util/Bytes.toBytes:(Ljava/lang/String;)[B
      67: invokevirtual #68                 // Method org/apache/hadoop/hbase/client/Put.addColumn:([B[B[B)Lorg/apache/hadoop/hbase/client/Put;
      70: invokeinterface #88,  2           // InterfaceMethod org/apache/hadoop/hbase/client/AsyncTable$CheckAndMutateBuilder.thenPut:(Lorg/apache/hadoop/hbase/client/Put;)Ljava/util/concurrent/CompletableFuture;
      75: invokevirtual #54                 // Method java/util/concurrent/CompletableFuture.join:()Ljava/lang/Object;
      78: pop
      79: aload_0
      80: getfield      #2                  // Field stub:Lorg/apache/hadoop/hbase/shaded/protobuf/generated/ClientProtos$ClientService$Interface;
      83: iconst_1
      84: invokestatic  #55                 // Method org/mockito/Mockito.times:(I)Lorg/mockito/verification/VerificationMode;
      87: invokestatic  #56                 // Method org/mockito/Mockito.verify:(Ljava/lang/Object;Lorg/mockito/verification/VerificationMode;)Ljava/lang/Object;
      90: checkcast     #7                  // class org/apache/hadoop/hbase/shaded/protobuf/generated/ClientProtos$ClientService$Interface
      93: aload_0
      94: sipush        200
      97: invokespecial #57                 // Method assertPriority:(I)Lorg/apache/hadoop/hbase/ipc/HBaseRpcController;
     100: ldc           #28                 // class org/apache/hadoop/hbase/shaded/protobuf/generated/ClientProtos$MutateRequest
     102: invokestatic  #16                 // Method org/mockito/ArgumentMatchers.any:(Ljava/lang/Class;)Ljava/lang/Object;
     105: checkcast     #28                 // class org/apache/hadoop/hbase/shaded/protobuf/generated/ClientProtos$MutateRequest
     108: invokestatic  #19                 // Method org/mockito/ArgumentMatchers.any:()Ljava/lang/Object;
     111: checkcast     #20                 // class org/apache/hbase/thirdparty/com/google/protobuf/RpcCallback
     114: invokeinterface #29,  4           // InterfaceMethod org/apache/hadoop/hbase/shaded/protobuf/generated/ClientProtos$ClientService$Interface.mutate:(Lorg/apache/hbase/thirdparty/com/google/protobuf/RpcController;Lorg/apache/hadoop/hbase/shaded/protobuf/generated/ClientProtos$MutateRequest;Lorg/apache/hbase/thirdparty/com/google/protobuf/RpcCallback;)V
     119: return

  public void testCheckAndDelete();
    Code:
       0: aload_0
       1: getfield      #42                 // Field conn:Lorg/apache/hadoop/hbase/client/AsyncConnection;
       4: aload_0
       5: getfield      #6                  // Field name:Lorg/junit/rules/TestName;
       8: invokevirtual #46                 // Method org/junit/rules/TestName.getMethodName:()Ljava/lang/String;
      11: invokestatic  #47                 // Method org/apache/hadoop/hbase/TableName.valueOf:(Ljava/lang/String;)Lorg/apache/hadoop/hbase/TableName;
      14: invokeinterface #48,  2           // InterfaceMethod org/apache/hadoop/hbase/client/AsyncConnection.getTable:(Lorg/apache/hadoop/hbase/TableName;)Lorg/apache/hadoop/hbase/client/AsyncTable;
      19: iconst_0
      20: invokestatic  #50                 // Method org/apache/hadoop/hbase/util/Bytes.toBytes:(I)[B
      23: ldc           #64                 // String cf
      25: invokestatic  #65                 // Method org/apache/hadoop/hbase/util/Bytes.toBytes:(Ljava/lang/String;)[B
      28: invokeinterface #85,  3           // InterfaceMethod org/apache/hadoop/hbase/client/AsyncTable.checkAndMutate:([B[B)Lorg/apache/hadoop/hbase/client/AsyncTable$CheckAndMutateBuilder;
      33: ldc           #66                 // String cq
      35: invokestatic  #65                 // Method org/apache/hadoop/hbase/util/Bytes.toBytes:(Ljava/lang/String;)[B
      38: invokeinterface #86,  2           // InterfaceMethod org/apache/hadoop/hbase/client/AsyncTable$CheckAndMutateBuilder.qualifier:([B)Lorg/apache/hadoop/hbase/client/AsyncTable$CheckAndMutateBuilder;
      43: ldc           #67                 // String v
      45: invokestatic  #65                 // Method org/apache/hadoop/hbase/util/Bytes.toBytes:(Ljava/lang/String;)[B
      48: invokeinterface #89,  2           // InterfaceMethod org/apache/hadoop/hbase/client/AsyncTable$CheckAndMutateBuilder.ifEquals:([B)Lorg/apache/hadoop/hbase/client/AsyncTable$CheckAndMutateBuilder;
      53: new           #70                 // class org/apache/hadoop/hbase/client/Delete
      56: dup
      57: iconst_0
      58: invokestatic  #50                 // Method org/apache/hadoop/hbase/util/Bytes.toBytes:(I)[B
      61: invokespecial #71                 // Method org/apache/hadoop/hbase/client/Delete."<init>":([B)V
      64: bipush        17
      66: invokevirtual #72                 // Method org/apache/hadoop/hbase/client/Delete.setPriority:(I)Lorg/apache/hadoop/hbase/client/Delete;
      69: invokeinterface #90,  2           // InterfaceMethod org/apache/hadoop/hbase/client/AsyncTable$CheckAndMutateBuilder.thenDelete:(Lorg/apache/hadoop/hbase/client/Delete;)Ljava/util/concurrent/CompletableFuture;
      74: invokevirtual #54                 // Method java/util/concurrent/CompletableFuture.join:()Ljava/lang/Object;
      77: pop
      78: aload_0
      79: getfield      #2                  // Field stub:Lorg/apache/hadoop/hbase/shaded/protobuf/generated/ClientProtos$ClientService$Interface;
      82: iconst_1
      83: invokestatic  #55                 // Method org/mockito/Mockito.times:(I)Lorg/mockito/verification/VerificationMode;
      86: invokestatic  #56                 // Method org/mockito/Mockito.verify:(Ljava/lang/Object;Lorg/mockito/verification/VerificationMode;)Ljava/lang/Object;
      89: checkcast     #7                  // class org/apache/hadoop/hbase/shaded/protobuf/generated/ClientProtos$ClientService$Interface
      92: aload_0
      93: bipush        17
      95: invokespecial #57                 // Method assertPriority:(I)Lorg/apache/hadoop/hbase/ipc/HBaseRpcController;
      98: ldc           #28                 // class org/apache/hadoop/hbase/shaded/protobuf/generated/ClientProtos$MutateRequest
     100: invokestatic  #16                 // Method org/mockito/ArgumentMatchers.any:(Ljava/lang/Class;)Ljava/lang/Object;
     103: checkcast     #28                 // class org/apache/hadoop/hbase/shaded/protobuf/generated/ClientProtos$MutateRequest
     106: invokestatic  #19                 // Method org/mockito/ArgumentMatchers.any:()Ljava/lang/Object;
     109: checkcast     #20                 // class org/apache/hbase/thirdparty/com/google/protobuf/RpcCallback
     112: invokeinterface #29,  4           // InterfaceMethod org/apache/hadoop/hbase/shaded/protobuf/generated/ClientProtos$ClientService$Interface.mutate:(Lorg/apache/hbase/thirdparty/com/google/protobuf/RpcController;Lorg/apache/hadoop/hbase/shaded/protobuf/generated/ClientProtos$MutateRequest;Lorg/apache/hbase/thirdparty/com/google/protobuf/RpcCallback;)V
     117: return

  public void testCheckAndDeleteNormalTable();
    Code:
       0: aload_0
       1: getfield      #42                 // Field conn:Lorg/apache/hadoop/hbase/client/AsyncConnection;
       4: aload_0
       5: getfield      #6                  // Field name:Lorg/junit/rules/TestName;
       8: invokevirtual #46                 // Method org/junit/rules/TestName.getMethodName:()Ljava/lang/String;
      11: invokestatic  #47                 // Method org/apache/hadoop/hbase/TableName.valueOf:(Ljava/lang/String;)Lorg/apache/hadoop/hbase/TableName;
      14: invokeinterface #48,  2           // InterfaceMethod org/apache/hadoop/hbase/client/AsyncConnection.getTable:(Lorg/apache/hadoop/hbase/TableName;)Lorg/apache/hadoop/hbase/client/AsyncTable;
      19: iconst_0
      20: invokestatic  #50                 // Method org/apache/hadoop/hbase/util/Bytes.toBytes:(I)[B
      23: ldc           #64                 // String cf
      25: invokestatic  #65                 // Method org/apache/hadoop/hbase/util/Bytes.toBytes:(Ljava/lang/String;)[B
      28: invokeinterface #85,  3           // InterfaceMethod org/apache/hadoop/hbase/client/AsyncTable.checkAndMutate:([B[B)Lorg/apache/hadoop/hbase/client/AsyncTable$CheckAndMutateBuilder;
      33: ldc           #66                 // String cq
      35: invokestatic  #65                 // Method org/apache/hadoop/hbase/util/Bytes.toBytes:(Ljava/lang/String;)[B
      38: invokeinterface #86,  2           // InterfaceMethod org/apache/hadoop/hbase/client/AsyncTable$CheckAndMutateBuilder.qualifier:([B)Lorg/apache/hadoop/hbase/client/AsyncTable$CheckAndMutateBuilder;
      43: ldc           #67                 // String v
      45: invokestatic  #65                 // Method org/apache/hadoop/hbase/util/Bytes.toBytes:(Ljava/lang/String;)[B
      48: invokeinterface #89,  2           // InterfaceMethod org/apache/hadoop/hbase/client/AsyncTable$CheckAndMutateBuilder.ifEquals:([B)Lorg/apache/hadoop/hbase/client/AsyncTable$CheckAndMutateBuilder;
      53: new           #70                 // class org/apache/hadoop/hbase/client/Delete
      56: dup
      57: iconst_0
      58: invokestatic  #50                 // Method org/apache/hadoop/hbase/util/Bytes.toBytes:(I)[B
      61: invokespecial #71                 // Method org/apache/hadoop/hbase/client/Delete."<init>":([B)V
      64: invokeinterface #90,  2           // InterfaceMethod org/apache/hadoop/hbase/client/AsyncTable$CheckAndMutateBuilder.thenDelete:(Lorg/apache/hadoop/hbase/client/Delete;)Ljava/util/concurrent/CompletableFuture;
      69: invokevirtual #54                 // Method java/util/concurrent/CompletableFuture.join:()Ljava/lang/Object;
      72: pop
      73: aload_0
      74: getfield      #2                  // Field stub:Lorg/apache/hadoop/hbase/shaded/protobuf/generated/ClientProtos$ClientService$Interface;
      77: iconst_1
      78: invokestatic  #55                 // Method org/mockito/Mockito.times:(I)Lorg/mockito/verification/VerificationMode;
      81: invokestatic  #56                 // Method org/mockito/Mockito.verify:(Ljava/lang/Object;Lorg/mockito/verification/VerificationMode;)Ljava/lang/Object;
      84: checkcast     #7                  // class org/apache/hadoop/hbase/shaded/protobuf/generated/ClientProtos$ClientService$Interface
      87: aload_0
      88: iconst_0
      89: invokespecial #57                 // Method assertPriority:(I)Lorg/apache/hadoop/hbase/ipc/HBaseRpcController;
      92: ldc           #28                 // class org/apache/hadoop/hbase/shaded/protobuf/generated/ClientProtos$MutateRequest
      94: invokestatic  #16                 // Method org/mockito/ArgumentMatchers.any:(Ljava/lang/Class;)Ljava/lang/Object;
      97: checkcast     #28                 // class org/apache/hadoop/hbase/shaded/protobuf/generated/ClientProtos$MutateRequest
     100: invokestatic  #19                 // Method org/mockito/ArgumentMatchers.any:()Ljava/lang/Object;
     103: checkcast     #20                 // class org/apache/hbase/thirdparty/com/google/protobuf/RpcCallback
     106: invokeinterface #29,  4           // InterfaceMethod org/apache/hadoop/hbase/shaded/protobuf/generated/ClientProtos$ClientService$Interface.mutate:(Lorg/apache/hbase/thirdparty/com/google/protobuf/RpcController;Lorg/apache/hadoop/hbase/shaded/protobuf/generated/ClientProtos$MutateRequest;Lorg/apache/hbase/thirdparty/com/google/protobuf/RpcCallback;)V
     111: return

  public void testCheckAndDeleteSystemTable();
    Code:
       0: aload_0
       1: getfield      #42                 // Field conn:Lorg/apache/hadoop/hbase/client/AsyncConnection;
       4: getstatic     #58                 // Field org/apache/hadoop/hbase/NamespaceDescriptor.SYSTEM_NAMESPACE_NAME_STR:Ljava/lang/String;
       7: aload_0
       8: getfield      #6                  // Field name:Lorg/junit/rules/TestName;
      11: invokevirtual #46                 // Method org/junit/rules/TestName.getMethodName:()Ljava/lang/String;
      14: invokestatic  #59                 // Method org/apache/hadoop/hbase/TableName.valueOf:(Ljava/lang/String;Ljava/lang/String;)Lorg/apache/hadoop/hbase/TableName;
      17: invokeinterface #48,  2           // InterfaceMethod org/apache/hadoop/hbase/client/AsyncConnection.getTable:(Lorg/apache/hadoop/hbase/TableName;)Lorg/apache/hadoop/hbase/client/AsyncTable;
      22: iconst_0
      23: invokestatic  #50                 // Method org/apache/hadoop/hbase/util/Bytes.toBytes:(I)[B
      26: ldc           #64                 // String cf
      28: invokestatic  #65                 // Method org/apache/hadoop/hbase/util/Bytes.toBytes:(Ljava/lang/String;)[B
      31: invokeinterface #85,  3           // InterfaceMethod org/apache/hadoop/hbase/client/AsyncTable.checkAndMutate:([B[B)Lorg/apache/hadoop/hbase/client/AsyncTable$CheckAndMutateBuilder;
      36: ldc           #66                 // String cq
      38: invokestatic  #65                 // Method org/apache/hadoop/hbase/util/Bytes.toBytes:(Ljava/lang/String;)[B
      41: invokeinterface #86,  2           // InterfaceMethod org/apache/hadoop/hbase/client/AsyncTable$CheckAndMutateBuilder.qualifier:([B)Lorg/apache/hadoop/hbase/client/AsyncTable$CheckAndMutateBuilder;
      46: ldc           #67                 // String v
      48: invokestatic  #65                 // Method org/apache/hadoop/hbase/util/Bytes.toBytes:(Ljava/lang/String;)[B
      51: invokeinterface #89,  2           // InterfaceMethod org/apache/hadoop/hbase/client/AsyncTable$CheckAndMutateBuilder.ifEquals:([B)Lorg/apache/hadoop/hbase/client/AsyncTable$CheckAndMutateBuilder;
      56: new           #70                 // class org/apache/hadoop/hbase/client/Delete
      59: dup
      60: iconst_0
      61: invokestatic  #50                 // Method org/apache/hadoop/hbase/util/Bytes.toBytes:(I)[B
      64: invokespecial #71                 // Method org/apache/hadoop/hbase/client/Delete."<init>":([B)V
      67: invokeinterface #90,  2           // InterfaceMethod org/apache/hadoop/hbase/client/AsyncTable$CheckAndMutateBuilder.thenDelete:(Lorg/apache/hadoop/hbase/client/Delete;)Ljava/util/concurrent/CompletableFuture;
      72: invokevirtual #54                 // Method java/util/concurrent/CompletableFuture.join:()Ljava/lang/Object;
      75: pop
      76: aload_0
      77: getfield      #2                  // Field stub:Lorg/apache/hadoop/hbase/shaded/protobuf/generated/ClientProtos$ClientService$Interface;
      80: iconst_1
      81: invokestatic  #55                 // Method org/mockito/Mockito.times:(I)Lorg/mockito/verification/VerificationMode;
      84: invokestatic  #56                 // Method org/mockito/Mockito.verify:(Ljava/lang/Object;Lorg/mockito/verification/VerificationMode;)Ljava/lang/Object;
      87: checkcast     #7                  // class org/apache/hadoop/hbase/shaded/protobuf/generated/ClientProtos$ClientService$Interface
      90: aload_0
      91: sipush        200
      94: invokespecial #57                 // Method assertPriority:(I)Lorg/apache/hadoop/hbase/ipc/HBaseRpcController;
      97: ldc           #28                 // class org/apache/hadoop/hbase/shaded/protobuf/generated/ClientProtos$MutateRequest
      99: invokestatic  #16                 // Method org/mockito/ArgumentMatchers.any:(Ljava/lang/Class;)Ljava/lang/Object;
     102: checkcast     #28                 // class org/apache/hadoop/hbase/shaded/protobuf/generated/ClientProtos$MutateRequest
     105: invokestatic  #19                 // Method org/mockito/ArgumentMatchers.any:()Ljava/lang/Object;
     108: checkcast     #20                 // class org/apache/hbase/thirdparty/com/google/protobuf/RpcCallback
     111: invokeinterface #29,  4           // InterfaceMethod org/apache/hadoop/hbase/shaded/protobuf/generated/ClientProtos$ClientService$Interface.mutate:(Lorg/apache/hbase/thirdparty/com/google/protobuf/RpcController;Lorg/apache/hadoop/hbase/shaded/protobuf/generated/ClientProtos$MutateRequest;Lorg/apache/hbase/thirdparty/com/google/protobuf/RpcCallback;)V
     116: return

  public void testCheckAndDeleteMetaTable();
    Code:
       0: aload_0
       1: getfield      #42                 // Field conn:Lorg/apache/hadoop/hbase/client/AsyncConnection;
       4: getstatic     #60                 // Field org/apache/hadoop/hbase/TableName.META_TABLE_NAME:Lorg/apache/hadoop/hbase/TableName;
       7: invokeinterface #48,  2           // InterfaceMethod org/apache/hadoop/hbase/client/AsyncConnection.getTable:(Lorg/apache/hadoop/hbase/TableName;)Lorg/apache/hadoop/hbase/client/AsyncTable;
      12: iconst_0
      13: invokestatic  #50                 // Method org/apache/hadoop/hbase/util/Bytes.toBytes:(I)[B
      16: ldc           #64                 // String cf
      18: invokestatic  #65                 // Method org/apache/hadoop/hbase/util/Bytes.toBytes:(Ljava/lang/String;)[B
      21: invokeinterface #85,  3           // InterfaceMethod org/apache/hadoop/hbase/client/AsyncTable.checkAndMutate:([B[B)Lorg/apache/hadoop/hbase/client/AsyncTable$CheckAndMutateBuilder;
      26: ldc           #66                 // String cq
      28: invokestatic  #65                 // Method org/apache/hadoop/hbase/util/Bytes.toBytes:(Ljava/lang/String;)[B
      31: invokeinterface #86,  2           // InterfaceMethod org/apache/hadoop/hbase/client/AsyncTable$CheckAndMutateBuilder.qualifier:([B)Lorg/apache/hadoop/hbase/client/AsyncTable$CheckAndMutateBuilder;
      36: invokeinterface #87,  1           // InterfaceMethod org/apache/hadoop/hbase/client/AsyncTable$CheckAndMutateBuilder.ifNotExists:()Lorg/apache/hadoop/hbase/client/AsyncTable$CheckAndMutateBuilder;
      41: new           #61                 // class org/apache/hadoop/hbase/client/Put
      44: dup
      45: iconst_0
      46: invokestatic  #50                 // Method org/apache/hadoop/hbase/util/Bytes.toBytes:(I)[B
      49: invokespecial #62                 // Method org/apache/hadoop/hbase/client/Put."<init>":([B)V
      52: ldc           #64                 // String cf
      54: invokestatic  #65                 // Method org/apache/hadoop/hbase/util/Bytes.toBytes:(Ljava/lang/String;)[B
      57: ldc           #66                 // String cq
      59: invokestatic  #65                 // Method org/apache/hadoop/hbase/util/Bytes.toBytes:(Ljava/lang/String;)[B
      62: ldc           #67                 // String v
      64: invokestatic  #65                 // Method org/apache/hadoop/hbase/util/Bytes.toBytes:(Ljava/lang/String;)[B
      67: invokevirtual #68                 // Method org/apache/hadoop/hbase/client/Put.addColumn:([B[B[B)Lorg/apache/hadoop/hbase/client/Put;
      70: invokeinterface #88,  2           // InterfaceMethod org/apache/hadoop/hbase/client/AsyncTable$CheckAndMutateBuilder.thenPut:(Lorg/apache/hadoop/hbase/client/Put;)Ljava/util/concurrent/CompletableFuture;
      75: invokevirtual #54                 // Method java/util/concurrent/CompletableFuture.join:()Ljava/lang/Object;
      78: pop
      79: aload_0
      80: getfield      #2                  // Field stub:Lorg/apache/hadoop/hbase/shaded/protobuf/generated/ClientProtos$ClientService$Interface;
      83: iconst_1
      84: invokestatic  #55                 // Method org/mockito/Mockito.times:(I)Lorg/mockito/verification/VerificationMode;
      87: invokestatic  #56                 // Method org/mockito/Mockito.verify:(Ljava/lang/Object;Lorg/mockito/verification/VerificationMode;)Ljava/lang/Object;
      90: checkcast     #7                  // class org/apache/hadoop/hbase/shaded/protobuf/generated/ClientProtos$ClientService$Interface
      93: aload_0
      94: sipush        200
      97: invokespecial #57                 // Method assertPriority:(I)Lorg/apache/hadoop/hbase/ipc/HBaseRpcController;
     100: ldc           #28                 // class org/apache/hadoop/hbase/shaded/protobuf/generated/ClientProtos$MutateRequest
     102: invokestatic  #16                 // Method org/mockito/ArgumentMatchers.any:(Ljava/lang/Class;)Ljava/lang/Object;
     105: checkcast     #28                 // class org/apache/hadoop/hbase/shaded/protobuf/generated/ClientProtos$MutateRequest
     108: invokestatic  #19                 // Method org/mockito/ArgumentMatchers.any:()Ljava/lang/Object;
     111: checkcast     #20                 // class org/apache/hbase/thirdparty/com/google/protobuf/RpcCallback
     114: invokeinterface #29,  4           // InterfaceMethod org/apache/hadoop/hbase/shaded/protobuf/generated/ClientProtos$ClientService$Interface.mutate:(Lorg/apache/hbase/thirdparty/com/google/protobuf/RpcController;Lorg/apache/hadoop/hbase/shaded/protobuf/generated/ClientProtos$MutateRequest;Lorg/apache/hbase/thirdparty/com/google/protobuf/RpcCallback;)V
     119: return

  public void testCheckAndMutate() throws java.io.IOException;
    Code:
       0: aload_0
       1: getfield      #42                 // Field conn:Lorg/apache/hadoop/hbase/client/AsyncConnection;
       4: aload_0
       5: getfield      #6                  // Field name:Lorg/junit/rules/TestName;
       8: invokevirtual #46                 // Method org/junit/rules/TestName.getMethodName:()Ljava/lang/String;
      11: invokestatic  #47                 // Method org/apache/hadoop/hbase/TableName.valueOf:(Ljava/lang/String;)Lorg/apache/hadoop/hbase/TableName;
      14: invokeinterface #48,  2           // InterfaceMethod org/apache/hadoop/hbase/client/AsyncConnection.getTable:(Lorg/apache/hadoop/hbase/TableName;)Lorg/apache/hadoop/hbase/client/AsyncTable;
      19: iconst_0
      20: invokestatic  #50                 // Method org/apache/hadoop/hbase/util/Bytes.toBytes:(I)[B
      23: ldc           #64                 // String cf
      25: invokestatic  #65                 // Method org/apache/hadoop/hbase/util/Bytes.toBytes:(Ljava/lang/String;)[B
      28: invokeinterface #85,  3           // InterfaceMethod org/apache/hadoop/hbase/client/AsyncTable.checkAndMutate:([B[B)Lorg/apache/hadoop/hbase/client/AsyncTable$CheckAndMutateBuilder;
      33: ldc           #66                 // String cq
      35: invokestatic  #65                 // Method org/apache/hadoop/hbase/util/Bytes.toBytes:(Ljava/lang/String;)[B
      38: invokeinterface #86,  2           // InterfaceMethod org/apache/hadoop/hbase/client/AsyncTable$CheckAndMutateBuilder.qualifier:([B)Lorg/apache/hadoop/hbase/client/AsyncTable$CheckAndMutateBuilder;
      43: ldc           #67                 // String v
      45: invokestatic  #65                 // Method org/apache/hadoop/hbase/util/Bytes.toBytes:(Ljava/lang/String;)[B
      48: invokeinterface #89,  2           // InterfaceMethod org/apache/hadoop/hbase/client/AsyncTable$CheckAndMutateBuilder.ifEquals:([B)Lorg/apache/hadoop/hbase/client/AsyncTable$CheckAndMutateBuilder;
      53: new           #91                 // class org/apache/hadoop/hbase/client/RowMutations
      56: dup
      57: iconst_0
      58: invokestatic  #50                 // Method org/apache/hadoop/hbase/util/Bytes.toBytes:(I)[B
      61: invokespecial #92                 // Method org/apache/hadoop/hbase/client/RowMutations."<init>":([B)V
      64: new           #70                 // class org/apache/hadoop/hbase/client/Delete
      67: dup
      68: iconst_0
      69: invokestatic  #50                 // Method org/apache/hadoop/hbase/util/Bytes.toBytes:(I)[B
      72: invokespecial #71                 // Method org/apache/hadoop/hbase/client/Delete."<init>":([B)V
      75: bipush        18
      77: invokevirtual #72                 // Method org/apache/hadoop/hbase/client/Delete.setPriority:(I)Lorg/apache/hadoop/hbase/client/Delete;
      80: invokevirtual #93                 // Method org/apache/hadoop/hbase/client/RowMutations.add:(Lorg/apache/hadoop/hbase/client/Mutation;)Lorg/apache/hadoop/hbase/client/RowMutations;
      83: invokeinterface #94,  2           // InterfaceMethod org/apache/hadoop/hbase/client/AsyncTable$CheckAndMutateBuilder.thenMutate:(Lorg/apache/hadoop/hbase/client/RowMutations;)Ljava/util/concurrent/CompletableFuture;
      88: invokevirtual #54                 // Method java/util/concurrent/CompletableFuture.join:()Ljava/lang/Object;
      91: pop
      92: aload_0
      93: getfield      #2                  // Field stub:Lorg/apache/hadoop/hbase/shaded/protobuf/generated/ClientProtos$ClientService$Interface;
      96: iconst_1
      97: invokestatic  #55                 // Method org/mockito/Mockito.times:(I)Lorg/mockito/verification/VerificationMode;
     100: invokestatic  #56                 // Method org/mockito/Mockito.verify:(Ljava/lang/Object;Lorg/mockito/verification/VerificationMode;)Ljava/lang/Object;
     103: checkcast     #7                  // class org/apache/hadoop/hbase/shaded/protobuf/generated/ClientProtos$ClientService$Interface
     106: aload_0
     107: bipush        18
     109: invokespecial #57                 // Method assertPriority:(I)Lorg/apache/hadoop/hbase/ipc/HBaseRpcController;
     112: ldc           #24                 // class org/apache/hadoop/hbase/shaded/protobuf/generated/ClientProtos$MultiRequest
     114: invokestatic  #16                 // Method org/mockito/ArgumentMatchers.any:(Ljava/lang/Class;)Ljava/lang/Object;
     117: checkcast     #24                 // class org/apache/hadoop/hbase/shaded/protobuf/generated/ClientProtos$MultiRequest
     120: invokestatic  #19                 // Method org/mockito/ArgumentMatchers.any:()Ljava/lang/Object;
     123: checkcast     #20                 // class org/apache/hbase/thirdparty/com/google/protobuf/RpcCallback
     126: invokeinterface #25,  4           // InterfaceMethod org/apache/hadoop/hbase/shaded/protobuf/generated/ClientProtos$ClientService$Interface.multi:(Lorg/apache/hbase/thirdparty/com/google/protobuf/RpcController;Lorg/apache/hadoop/hbase/shaded/protobuf/generated/ClientProtos$MultiRequest;Lorg/apache/hbase/thirdparty/com/google/protobuf/RpcCallback;)V
     131: return

  public void testCheckAndMutateNormalTable() throws java.io.IOException;
    Code:
       0: aload_0
       1: getfield      #42                 // Field conn:Lorg/apache/hadoop/hbase/client/AsyncConnection;
       4: aload_0
       5: getfield      #6                  // Field name:Lorg/junit/rules/TestName;
       8: invokevirtual #46                 // Method org/junit/rules/TestName.getMethodName:()Ljava/lang/String;
      11: invokestatic  #47                 // Method org/apache/hadoop/hbase/TableName.valueOf:(Ljava/lang/String;)Lorg/apache/hadoop/hbase/TableName;
      14: invokeinterface #48,  2           // InterfaceMethod org/apache/hadoop/hbase/client/AsyncConnection.getTable:(Lorg/apache/hadoop/hbase/TableName;)Lorg/apache/hadoop/hbase/client/AsyncTable;
      19: iconst_0
      20: invokestatic  #50                 // Method org/apache/hadoop/hbase/util/Bytes.toBytes:(I)[B
      23: ldc           #64                 // String cf
      25: invokestatic  #65                 // Method org/apache/hadoop/hbase/util/Bytes.toBytes:(Ljava/lang/String;)[B
      28: invokeinterface #85,  3           // InterfaceMethod org/apache/hadoop/hbase/client/AsyncTable.checkAndMutate:([B[B)Lorg/apache/hadoop/hbase/client/AsyncTable$CheckAndMutateBuilder;
      33: ldc           #66                 // String cq
      35: invokestatic  #65                 // Method org/apache/hadoop/hbase/util/Bytes.toBytes:(Ljava/lang/String;)[B
      38: invokeinterface #86,  2           // InterfaceMethod org/apache/hadoop/hbase/client/AsyncTable$CheckAndMutateBuilder.qualifier:([B)Lorg/apache/hadoop/hbase/client/AsyncTable$CheckAndMutateBuilder;
      43: ldc           #67                 // String v
      45: invokestatic  #65                 // Method org/apache/hadoop/hbase/util/Bytes.toBytes:(Ljava/lang/String;)[B
      48: invokeinterface #89,  2           // InterfaceMethod org/apache/hadoop/hbase/client/AsyncTable$CheckAndMutateBuilder.ifEquals:([B)Lorg/apache/hadoop/hbase/client/AsyncTable$CheckAndMutateBuilder;
      53: new           #91                 // class org/apache/hadoop/hbase/client/RowMutations
      56: dup
      57: iconst_0
      58: invokestatic  #50                 // Method org/apache/hadoop/hbase/util/Bytes.toBytes:(I)[B
      61: invokespecial #92                 // Method org/apache/hadoop/hbase/client/RowMutations."<init>":([B)V
      64: new           #70                 // class org/apache/hadoop/hbase/client/Delete
      67: dup
      68: iconst_0
      69: invokestatic  #50                 // Method org/apache/hadoop/hbase/util/Bytes.toBytes:(I)[B
      72: invokespecial #71                 // Method org/apache/hadoop/hbase/client/Delete."<init>":([B)V
      75: invokevirtual #93                 // Method org/apache/hadoop/hbase/client/RowMutations.add:(Lorg/apache/hadoop/hbase/client/Mutation;)Lorg/apache/hadoop/hbase/client/RowMutations;
      78: invokeinterface #94,  2           // InterfaceMethod org/apache/hadoop/hbase/client/AsyncTable$CheckAndMutateBuilder.thenMutate:(Lorg/apache/hadoop/hbase/client/RowMutations;)Ljava/util/concurrent/CompletableFuture;
      83: invokevirtual #54                 // Method java/util/concurrent/CompletableFuture.join:()Ljava/lang/Object;
      86: pop
      87: aload_0
      88: getfield      #2                  // Field stub:Lorg/apache/hadoop/hbase/shaded/protobuf/generated/ClientProtos$ClientService$Interface;
      91: iconst_1
      92: invokestatic  #55                 // Method org/mockito/Mockito.times:(I)Lorg/mockito/verification/VerificationMode;
      95: invokestatic  #56                 // Method org/mockito/Mockito.verify:(Ljava/lang/Object;Lorg/mockito/verification/VerificationMode;)Ljava/lang/Object;
      98: checkcast     #7                  // class org/apache/hadoop/hbase/shaded/protobuf/generated/ClientProtos$ClientService$Interface
     101: aload_0
     102: iconst_0
     103: invokespecial #57                 // Method assertPriority:(I)Lorg/apache/hadoop/hbase/ipc/HBaseRpcController;
     106: ldc           #24                 // class org/apache/hadoop/hbase/shaded/protobuf/generated/ClientProtos$MultiRequest
     108: invokestatic  #16                 // Method org/mockito/ArgumentMatchers.any:(Ljava/lang/Class;)Ljava/lang/Object;
     111: checkcast     #24                 // class org/apache/hadoop/hbase/shaded/protobuf/generated/ClientProtos$MultiRequest
     114: invokestatic  #19                 // Method org/mockito/ArgumentMatchers.any:()Ljava/lang/Object;
     117: checkcast     #20                 // class org/apache/hbase/thirdparty/com/google/protobuf/RpcCallback
     120: invokeinterface #25,  4           // InterfaceMethod org/apache/hadoop/hbase/shaded/protobuf/generated/ClientProtos$ClientService$Interface.multi:(Lorg/apache/hbase/thirdparty/com/google/protobuf/RpcController;Lorg/apache/hadoop/hbase/shaded/protobuf/generated/ClientProtos$MultiRequest;Lorg/apache/hbase/thirdparty/com/google/protobuf/RpcCallback;)V
     125: return

  public void testCheckAndMutateSystemTable() throws java.io.IOException;
    Code:
       0: aload_0
       1: getfield      #42                 // Field conn:Lorg/apache/hadoop/hbase/client/AsyncConnection;
       4: getstatic     #58                 // Field org/apache/hadoop/hbase/NamespaceDescriptor.SYSTEM_NAMESPACE_NAME_STR:Ljava/lang/String;
       7: aload_0
       8: getfield      #6                  // Field name:Lorg/junit/rules/TestName;
      11: invokevirtual #46                 // Method org/junit/rules/TestName.getMethodName:()Ljava/lang/String;
      14: invokestatic  #59                 // Method org/apache/hadoop/hbase/TableName.valueOf:(Ljava/lang/String;Ljava/lang/String;)Lorg/apache/hadoop/hbase/TableName;
      17: invokeinterface #48,  2           // InterfaceMethod org/apache/hadoop/hbase/client/AsyncConnection.getTable:(Lorg/apache/hadoop/hbase/TableName;)Lorg/apache/hadoop/hbase/client/AsyncTable;
      22: iconst_0
      23: invokestatic  #50                 // Method org/apache/hadoop/hbase/util/Bytes.toBytes:(I)[B
      26: ldc           #64                 // String cf
      28: invokestatic  #65                 // Method org/apache/hadoop/hbase/util/Bytes.toBytes:(Ljava/lang/String;)[B
      31: invokeinterface #85,  3           // InterfaceMethod org/apache/hadoop/hbase/client/AsyncTable.checkAndMutate:([B[B)Lorg/apache/hadoop/hbase/client/AsyncTable$CheckAndMutateBuilder;
      36: ldc           #66                 // String cq
      38: invokestatic  #65                 // Method org/apache/hadoop/hbase/util/Bytes.toBytes:(Ljava/lang/String;)[B
      41: invokeinterface #86,  2           // InterfaceMethod org/apache/hadoop/hbase/client/AsyncTable$CheckAndMutateBuilder.qualifier:([B)Lorg/apache/hadoop/hbase/client/AsyncTable$CheckAndMutateBuilder;
      46: ldc           #67                 // String v
      48: invokestatic  #65                 // Method org/apache/hadoop/hbase/util/Bytes.toBytes:(Ljava/lang/String;)[B
      51: invokeinterface #89,  2           // InterfaceMethod org/apache/hadoop/hbase/client/AsyncTable$CheckAndMutateBuilder.ifEquals:([B)Lorg/apache/hadoop/hbase/client/AsyncTable$CheckAndMutateBuilder;
      56: new           #91                 // class org/apache/hadoop/hbase/client/RowMutations
      59: dup
      60: iconst_0
      61: invokestatic  #50                 // Method org/apache/hadoop/hbase/util/Bytes.toBytes:(I)[B
      64: invokespecial #92                 // Method org/apache/hadoop/hbase/client/RowMutations."<init>":([B)V
      67: new           #70                 // class org/apache/hadoop/hbase/client/Delete
      70: dup
      71: iconst_0
      72: invokestatic  #50                 // Method org/apache/hadoop/hbase/util/Bytes.toBytes:(I)[B
      75: invokespecial #71                 // Method org/apache/hadoop/hbase/client/Delete."<init>":([B)V
      78: invokevirtual #93                 // Method org/apache/hadoop/hbase/client/RowMutations.add:(Lorg/apache/hadoop/hbase/client/Mutation;)Lorg/apache/hadoop/hbase/client/RowMutations;
      81: invokeinterface #94,  2           // InterfaceMethod org/apache/hadoop/hbase/client/AsyncTable$CheckAndMutateBuilder.thenMutate:(Lorg/apache/hadoop/hbase/client/RowMutations;)Ljava/util/concurrent/CompletableFuture;
      86: invokevirtual #54                 // Method java/util/concurrent/CompletableFuture.join:()Ljava/lang/Object;
      89: pop
      90: aload_0
      91: getfield      #2                  // Field stub:Lorg/apache/hadoop/hbase/shaded/protobuf/generated/ClientProtos$ClientService$Interface;
      94: iconst_1
      95: invokestatic  #55                 // Method org/mockito/Mockito.times:(I)Lorg/mockito/verification/VerificationMode;
      98: invokestatic  #56                 // Method org/mockito/Mockito.verify:(Ljava/lang/Object;Lorg/mockito/verification/VerificationMode;)Ljava/lang/Object;
     101: checkcast     #7                  // class org/apache/hadoop/hbase/shaded/protobuf/generated/ClientProtos$ClientService$Interface
     104: aload_0
     105: sipush        200
     108: invokespecial #57                 // Method assertPriority:(I)Lorg/apache/hadoop/hbase/ipc/HBaseRpcController;
     111: ldc           #24                 // class org/apache/hadoop/hbase/shaded/protobuf/generated/ClientProtos$MultiRequest
     113: invokestatic  #16                 // Method org/mockito/ArgumentMatchers.any:(Ljava/lang/Class;)Ljava/lang/Object;
     116: checkcast     #24                 // class org/apache/hadoop/hbase/shaded/protobuf/generated/ClientProtos$MultiRequest
     119: invokestatic  #19                 // Method org/mockito/ArgumentMatchers.any:()Ljava/lang/Object;
     122: checkcast     #20                 // class org/apache/hbase/thirdparty/com/google/protobuf/RpcCallback
     125: invokeinterface #25,  4           // InterfaceMethod org/apache/hadoop/hbase/shaded/protobuf/generated/ClientProtos$ClientService$Interface.multi:(Lorg/apache/hbase/thirdparty/com/google/protobuf/RpcController;Lorg/apache/hadoop/hbase/shaded/protobuf/generated/ClientProtos$MultiRequest;Lorg/apache/hbase/thirdparty/com/google/protobuf/RpcCallback;)V
     130: return

  public void testCheckAndMutateMetaTable() throws java.io.IOException;
    Code:
       0: aload_0
       1: getfield      #42                 // Field conn:Lorg/apache/hadoop/hbase/client/AsyncConnection;
       4: getstatic     #60                 // Field org/apache/hadoop/hbase/TableName.META_TABLE_NAME:Lorg/apache/hadoop/hbase/TableName;
       7: invokeinterface #48,  2           // InterfaceMethod org/apache/hadoop/hbase/client/AsyncConnection.getTable:(Lorg/apache/hadoop/hbase/TableName;)Lorg/apache/hadoop/hbase/client/AsyncTable;
      12: iconst_0
      13: invokestatic  #50                 // Method org/apache/hadoop/hbase/util/Bytes.toBytes:(I)[B
      16: ldc           #64                 // String cf
      18: invokestatic  #65                 // Method org/apache/hadoop/hbase/util/Bytes.toBytes:(Ljava/lang/String;)[B
      21: invokeinterface #85,  3           // InterfaceMethod org/apache/hadoop/hbase/client/AsyncTable.checkAndMutate:([B[B)Lorg/apache/hadoop/hbase/client/AsyncTable$CheckAndMutateBuilder;
      26: ldc           #66                 // String cq
      28: invokestatic  #65                 // Method org/apache/hadoop/hbase/util/Bytes.toBytes:(Ljava/lang/String;)[B
      31: invokeinterface #86,  2           // InterfaceMethod org/apache/hadoop/hbase/client/AsyncTable$CheckAndMutateBuilder.qualifier:([B)Lorg/apache/hadoop/hbase/client/AsyncTable$CheckAndMutateBuilder;
      36: ldc           #67                 // String v
      38: invokestatic  #65                 // Method org/apache/hadoop/hbase/util/Bytes.toBytes:(Ljava/lang/String;)[B
      41: invokeinterface #89,  2           // InterfaceMethod org/apache/hadoop/hbase/client/AsyncTable$CheckAndMutateBuilder.ifEquals:([B)Lorg/apache/hadoop/hbase/client/AsyncTable$CheckAndMutateBuilder;
      46: new           #91                 // class org/apache/hadoop/hbase/client/RowMutations
      49: dup
      50: iconst_0
      51: invokestatic  #50                 // Method org/apache/hadoop/hbase/util/Bytes.toBytes:(I)[B
      54: invokespecial #92                 // Method org/apache/hadoop/hbase/client/RowMutations."<init>":([B)V
      57: new           #70                 // class org/apache/hadoop/hbase/client/Delete
      60: dup
      61: iconst_0
      62: invokestatic  #50                 // Method org/apache/hadoop/hbase/util/Bytes.toBytes:(I)[B
      65: invokespecial #71                 // Method org/apache/hadoop/hbase/client/Delete."<init>":([B)V
      68: invokevirtual #93                 // Method org/apache/hadoop/hbase/client/RowMutations.add:(Lorg/apache/hadoop/hbase/client/Mutation;)Lorg/apache/hadoop/hbase/client/RowMutations;
      71: invokeinterface #94,  2           // InterfaceMethod org/apache/hadoop/hbase/client/AsyncTable$CheckAndMutateBuilder.thenMutate:(Lorg/apache/hadoop/hbase/client/RowMutations;)Ljava/util/concurrent/CompletableFuture;
      76: invokevirtual #54                 // Method java/util/concurrent/CompletableFuture.join:()Ljava/lang/Object;
      79: pop
      80: aload_0
      81: getfield      #2                  // Field stub:Lorg/apache/hadoop/hbase/shaded/protobuf/generated/ClientProtos$ClientService$Interface;
      84: iconst_1
      85: invokestatic  #55                 // Method org/mockito/Mockito.times:(I)Lorg/mockito/verification/VerificationMode;
      88: invokestatic  #56                 // Method org/mockito/Mockito.verify:(Ljava/lang/Object;Lorg/mockito/verification/VerificationMode;)Ljava/lang/Object;
      91: checkcast     #7                  // class org/apache/hadoop/hbase/shaded/protobuf/generated/ClientProtos$ClientService$Interface
      94: aload_0
      95: sipush        200
      98: invokespecial #57                 // Method assertPriority:(I)Lorg/apache/hadoop/hbase/ipc/HBaseRpcController;
     101: ldc           #24                 // class org/apache/hadoop/hbase/shaded/protobuf/generated/ClientProtos$MultiRequest
     103: invokestatic  #16                 // Method org/mockito/ArgumentMatchers.any:(Ljava/lang/Class;)Ljava/lang/Object;
     106: checkcast     #24                 // class org/apache/hadoop/hbase/shaded/protobuf/generated/ClientProtos$MultiRequest
     109: invokestatic  #19                 // Method org/mockito/ArgumentMatchers.any:()Ljava/lang/Object;
     112: checkcast     #20                 // class org/apache/hbase/thirdparty/com/google/protobuf/RpcCallback
     115: invokeinterface #25,  4           // InterfaceMethod org/apache/hadoop/hbase/shaded/protobuf/generated/ClientProtos$ClientService$Interface.multi:(Lorg/apache/hbase/thirdparty/com/google/protobuf/RpcController;Lorg/apache/hadoop/hbase/shaded/protobuf/generated/ClientProtos$MultiRequest;Lorg/apache/hbase/thirdparty/com/google/protobuf/RpcCallback;)V
     120: return

  public void testScan() throws java.io.IOException, java.lang.InterruptedException;
    Code:
       0: aload_0
       1: getfield      #42                 // Field conn:Lorg/apache/hadoop/hbase/client/AsyncConnection;
       4: aload_0
       5: getfield      #6                  // Field name:Lorg/junit/rules/TestName;
       8: invokevirtual #46                 // Method org/junit/rules/TestName.getMethodName:()Ljava/lang/String;
      11: invokestatic  #47                 // Method org/apache/hadoop/hbase/TableName.valueOf:(Ljava/lang/String;)Lorg/apache/hadoop/hbase/TableName;
      14: invokeinterface #48,  2           // InterfaceMethod org/apache/hadoop/hbase/client/AsyncConnection.getTable:(Lorg/apache/hadoop/hbase/TableName;)Lorg/apache/hadoop/hbase/client/AsyncTable;
      19: new           #95                 // class org/apache/hadoop/hbase/client/Scan
      22: dup
      23: invokespecial #96                 // Method org/apache/hadoop/hbase/client/Scan."<init>":()V
      26: iconst_1
      27: invokevirtual #97                 // Method org/apache/hadoop/hbase/client/Scan.setCaching:(I)Lorg/apache/hadoop/hbase/client/Scan;
      30: lconst_1
      31: invokevirtual #98                 // Method org/apache/hadoop/hbase/client/Scan.setMaxResultSize:(J)Lorg/apache/hadoop/hbase/client/Scan;
      34: bipush        19
      36: invokevirtual #99                 // Method org/apache/hadoop/hbase/client/Scan.setPriority:(I)Lorg/apache/hadoop/hbase/client/Scan;
      39: invokeinterface #100,  2          // InterfaceMethod org/apache/hadoop/hbase/client/AsyncTable.getScanner:(Lorg/apache/hadoop/hbase/client/Scan;)Lorg/apache/hadoop/hbase/client/ResultScanner;
      44: astore_1
      45: aconst_null
      46: astore_2
      47: aload_1
      48: invokeinterface #101,  1          // InterfaceMethod org/apache/hadoop/hbase/client/ResultScanner.next:()Lorg/apache/hadoop/hbase/client/Result;
      53: invokestatic  #102                // Method org/junit/Assert.assertNotNull:(Ljava/lang/Object;)V
      56: ldc2_w        #103                // long 1000l
      59: invokestatic  #105                // Method java/lang/Thread.sleep:(J)V
      62: aload_1
      63: ifnull        141
      66: aload_2
      67: ifnull        88
      70: aload_1
      71: invokeinterface #106,  1          // InterfaceMethod org/apache/hadoop/hbase/client/ResultScanner.close:()V
      76: goto          141
      79: astore_3
      80: aload_2
      81: aload_3
      82: invokevirtual #108                // Method java/lang/Throwable.addSuppressed:(Ljava/lang/Throwable;)V
      85: goto          141
      88: aload_1
      89: invokeinterface #106,  1          // InterfaceMethod org/apache/hadoop/hbase/client/ResultScanner.close:()V
      94: goto          141
      97: astore_3
      98: aload_3
      99: astore_2
     100: aload_3
     101: athrow
     102: astore        4
     104: aload_1
     105: ifnull        138
     108: aload_2
     109: ifnull        132
     112: aload_1
     113: invokeinterface #106,  1          // InterfaceMethod org/apache/hadoop/hbase/client/ResultScanner.close:()V
     118: goto          138
     121: astore        5
     123: aload_2
     124: aload         5
     126: invokevirtual #108                // Method java/lang/Throwable.addSuppressed:(Ljava/lang/Throwable;)V
     129: goto          138
     132: aload_1
     133: invokeinterface #106,  1          // InterfaceMethod org/apache/hadoop/hbase/client/ResultScanner.close:()V
     138: aload         4
     140: athrow
     141: ldc2_w        #103                // long 1000l
     144: invokestatic  #105                // Method java/lang/Thread.sleep:(J)V
     147: aload_0
     148: getfield      #2                  // Field stub:Lorg/apache/hadoop/hbase/shaded/protobuf/generated/ClientProtos$ClientService$Interface;
     151: iconst_4
     152: invokestatic  #109                // Method org/mockito/Mockito.atLeast:(I)Lorg/mockito/verification/VerificationMode;
     155: invokestatic  #56                 // Method org/mockito/Mockito.verify:(Ljava/lang/Object;Lorg/mockito/verification/VerificationMode;)Ljava/lang/Object;
     158: checkcast     #7                  // class org/apache/hadoop/hbase/shaded/protobuf/generated/ClientProtos$ClientService$Interface
     161: aload_0
     162: bipush        19
     164: invokespecial #57                 // Method assertPriority:(I)Lorg/apache/hadoop/hbase/ipc/HBaseRpcController;
     167: ldc           #18                 // class org/apache/hadoop/hbase/shaded/protobuf/generated/ClientProtos$ScanRequest
     169: invokestatic  #16                 // Method org/mockito/ArgumentMatchers.any:(Ljava/lang/Class;)Ljava/lang/Object;
     172: checkcast     #18                 // class org/apache/hadoop/hbase/shaded/protobuf/generated/ClientProtos$ScanRequest
     175: invokestatic  #19                 // Method org/mockito/ArgumentMatchers.any:()Ljava/lang/Object;
     178: checkcast     #20                 // class org/apache/hbase/thirdparty/com/google/protobuf/RpcCallback
     181: invokeinterface #21,  4           // InterfaceMethod org/apache/hadoop/hbase/shaded/protobuf/generated/ClientProtos$ClientService$Interface.scan:(Lorg/apache/hbase/thirdparty/com/google/protobuf/RpcController;Lorg/apache/hadoop/hbase/shaded/protobuf/generated/ClientProtos$ScanRequest;Lorg/apache/hbase/thirdparty/com/google/protobuf/RpcCallback;)V
     186: return
    Exception table:
       from    to  target type
          70    76    79   Class java/lang/Throwable
          47    62    97   Class java/lang/Throwable
          47    62   102   any
         112   118   121   Class java/lang/Throwable
          97   104   102   any

  public void testScanNormalTable() throws java.io.IOException, java.lang.InterruptedException;
    Code:
       0: aload_0
       1: getfield      #42                 // Field conn:Lorg/apache/hadoop/hbase/client/AsyncConnection;
       4: aload_0
       5: getfield      #6                  // Field name:Lorg/junit/rules/TestName;
       8: invokevirtual #46                 // Method org/junit/rules/TestName.getMethodName:()Ljava/lang/String;
      11: invokestatic  #47                 // Method org/apache/hadoop/hbase/TableName.valueOf:(Ljava/lang/String;)Lorg/apache/hadoop/hbase/TableName;
      14: invokeinterface #48,  2           // InterfaceMethod org/apache/hadoop/hbase/client/AsyncConnection.getTable:(Lorg/apache/hadoop/hbase/TableName;)Lorg/apache/hadoop/hbase/client/AsyncTable;
      19: new           #95                 // class org/apache/hadoop/hbase/client/Scan
      22: dup
      23: invokespecial #96                 // Method org/apache/hadoop/hbase/client/Scan."<init>":()V
      26: iconst_1
      27: invokevirtual #97                 // Method org/apache/hadoop/hbase/client/Scan.setCaching:(I)Lorg/apache/hadoop/hbase/client/Scan;
      30: lconst_1
      31: invokevirtual #98                 // Method org/apache/hadoop/hbase/client/Scan.setMaxResultSize:(J)Lorg/apache/hadoop/hbase/client/Scan;
      34: invokeinterface #100,  2          // InterfaceMethod org/apache/hadoop/hbase/client/AsyncTable.getScanner:(Lorg/apache/hadoop/hbase/client/Scan;)Lorg/apache/hadoop/hbase/client/ResultScanner;
      39: astore_1
      40: aconst_null
      41: astore_2
      42: aload_1
      43: invokeinterface #101,  1          // InterfaceMethod org/apache/hadoop/hbase/client/ResultScanner.next:()Lorg/apache/hadoop/hbase/client/Result;
      48: invokestatic  #102                // Method org/junit/Assert.assertNotNull:(Ljava/lang/Object;)V
      51: ldc2_w        #103                // long 1000l
      54: invokestatic  #105                // Method java/lang/Thread.sleep:(J)V
      57: aload_1
      58: ifnull        136
      61: aload_2
      62: ifnull        83
      65: aload_1
      66: invokeinterface #106,  1          // InterfaceMethod org/apache/hadoop/hbase/client/ResultScanner.close:()V
      71: goto          136
      74: astore_3
      75: aload_2
      76: aload_3
      77: invokevirtual #108                // Method java/lang/Throwable.addSuppressed:(Ljava/lang/Throwable;)V
      80: goto          136
      83: aload_1
      84: invokeinterface #106,  1          // InterfaceMethod org/apache/hadoop/hbase/client/ResultScanner.close:()V
      89: goto          136
      92: astore_3
      93: aload_3
      94: astore_2
      95: aload_3
      96: athrow
      97: astore        4
      99: aload_1
     100: ifnull        133
     103: aload_2
     104: ifnull        127
     107: aload_1
     108: invokeinterface #106,  1          // InterfaceMethod org/apache/hadoop/hbase/client/ResultScanner.close:()V
     113: goto          133
     116: astore        5
     118: aload_2
     119: aload         5
     121: invokevirtual #108                // Method java/lang/Throwable.addSuppressed:(Ljava/lang/Throwable;)V
     124: goto          133
     127: aload_1
     128: invokeinterface #106,  1          // InterfaceMethod org/apache/hadoop/hbase/client/ResultScanner.close:()V
     133: aload         4
     135: athrow
     136: ldc2_w        #103                // long 1000l
     139: invokestatic  #105                // Method java/lang/Thread.sleep:(J)V
     142: aload_0
     143: getfield      #2                  // Field stub:Lorg/apache/hadoop/hbase/shaded/protobuf/generated/ClientProtos$ClientService$Interface;
     146: iconst_4
     147: invokestatic  #109                // Method org/mockito/Mockito.atLeast:(I)Lorg/mockito/verification/VerificationMode;
     150: invokestatic  #56                 // Method org/mockito/Mockito.verify:(Ljava/lang/Object;Lorg/mockito/verification/VerificationMode;)Ljava/lang/Object;
     153: checkcast     #7                  // class org/apache/hadoop/hbase/shaded/protobuf/generated/ClientProtos$ClientService$Interface
     156: aload_0
     157: iconst_0
     158: invokespecial #57                 // Method assertPriority:(I)Lorg/apache/hadoop/hbase/ipc/HBaseRpcController;
     161: ldc           #18                 // class org/apache/hadoop/hbase/shaded/protobuf/generated/ClientProtos$ScanRequest
     163: invokestatic  #16                 // Method org/mockito/ArgumentMatchers.any:(Ljava/lang/Class;)Ljava/lang/Object;
     166: checkcast     #18                 // class org/apache/hadoop/hbase/shaded/protobuf/generated/ClientProtos$ScanRequest
     169: invokestatic  #19                 // Method org/mockito/ArgumentMatchers.any:()Ljava/lang/Object;
     172: checkcast     #20                 // class org/apache/hbase/thirdparty/com/google/protobuf/RpcCallback
     175: invokeinterface #21,  4           // InterfaceMethod org/apache/hadoop/hbase/shaded/protobuf/generated/ClientProtos$ClientService$Interface.scan:(Lorg/apache/hbase/thirdparty/com/google/protobuf/RpcController;Lorg/apache/hadoop/hbase/shaded/protobuf/generated/ClientProtos$ScanRequest;Lorg/apache/hbase/thirdparty/com/google/protobuf/RpcCallback;)V
     180: return
    Exception table:
       from    to  target type
          65    71    74   Class java/lang/Throwable
          42    57    92   Class java/lang/Throwable
          42    57    97   any
         107   113   116   Class java/lang/Throwable
          92    99    97   any

  public void testScanSystemTable() throws java.io.IOException, java.lang.InterruptedException;
    Code:
       0: aload_0
       1: getfield      #42                 // Field conn:Lorg/apache/hadoop/hbase/client/AsyncConnection;
       4: getstatic     #58                 // Field org/apache/hadoop/hbase/NamespaceDescriptor.SYSTEM_NAMESPACE_NAME_STR:Ljava/lang/String;
       7: aload_0
       8: getfield      #6                  // Field name:Lorg/junit/rules/TestName;
      11: invokevirtual #46                 // Method org/junit/rules/TestName.getMethodName:()Ljava/lang/String;
      14: invokestatic  #59                 // Method org/apache/hadoop/hbase/TableName.valueOf:(Ljava/lang/String;Ljava/lang/String;)Lorg/apache/hadoop/hbase/TableName;
      17: invokeinterface #48,  2           // InterfaceMethod org/apache/hadoop/hbase/client/AsyncConnection.getTable:(Lorg/apache/hadoop/hbase/TableName;)Lorg/apache/hadoop/hbase/client/AsyncTable;
      22: new           #95                 // class org/apache/hadoop/hbase/client/Scan
      25: dup
      26: invokespecial #96                 // Method org/apache/hadoop/hbase/client/Scan."<init>":()V
      29: iconst_1
      30: invokevirtual #97                 // Method org/apache/hadoop/hbase/client/Scan.setCaching:(I)Lorg/apache/hadoop/hbase/client/Scan;
      33: lconst_1
      34: invokevirtual #98                 // Method org/apache/hadoop/hbase/client/Scan.setMaxResultSize:(J)Lorg/apache/hadoop/hbase/client/Scan;
      37: invokeinterface #100,  2          // InterfaceMethod org/apache/hadoop/hbase/client/AsyncTable.getScanner:(Lorg/apache/hadoop/hbase/client/Scan;)Lorg/apache/hadoop/hbase/client/ResultScanner;
      42: astore_1
      43: aconst_null
      44: astore_2
      45: aload_1
      46: invokeinterface #101,  1          // InterfaceMethod org/apache/hadoop/hbase/client/ResultScanner.next:()Lorg/apache/hadoop/hbase/client/Result;
      51: invokestatic  #102                // Method org/junit/Assert.assertNotNull:(Ljava/lang/Object;)V
      54: ldc2_w        #103                // long 1000l
      57: invokestatic  #105                // Method java/lang/Thread.sleep:(J)V
      60: aload_1
      61: ifnull        139
      64: aload_2
      65: ifnull        86
      68: aload_1
      69: invokeinterface #106,  1          // InterfaceMethod org/apache/hadoop/hbase/client/ResultScanner.close:()V
      74: goto          139
      77: astore_3
      78: aload_2
      79: aload_3
      80: invokevirtual #108                // Method java/lang/Throwable.addSuppressed:(Ljava/lang/Throwable;)V
      83: goto          139
      86: aload_1
      87: invokeinterface #106,  1          // InterfaceMethod org/apache/hadoop/hbase/client/ResultScanner.close:()V
      92: goto          139
      95: astore_3
      96: aload_3
      97: astore_2
      98: aload_3
      99: athrow
     100: astore        4
     102: aload_1
     103: ifnull        136
     106: aload_2
     107: ifnull        130
     110: aload_1
     111: invokeinterface #106,  1          // InterfaceMethod org/apache/hadoop/hbase/client/ResultScanner.close:()V
     116: goto          136
     119: astore        5
     121: aload_2
     122: aload         5
     124: invokevirtual #108                // Method java/lang/Throwable.addSuppressed:(Ljava/lang/Throwable;)V
     127: goto          136
     130: aload_1
     131: invokeinterface #106,  1          // InterfaceMethod org/apache/hadoop/hbase/client/ResultScanner.close:()V
     136: aload         4
     138: athrow
     139: ldc2_w        #103                // long 1000l
     142: invokestatic  #105                // Method java/lang/Thread.sleep:(J)V
     145: aload_0
     146: getfield      #2                  // Field stub:Lorg/apache/hadoop/hbase/shaded/protobuf/generated/ClientProtos$ClientService$Interface;
     149: iconst_4
     150: invokestatic  #109                // Method org/mockito/Mockito.atLeast:(I)Lorg/mockito/verification/VerificationMode;
     153: invokestatic  #56                 // Method org/mockito/Mockito.verify:(Ljava/lang/Object;Lorg/mockito/verification/VerificationMode;)Ljava/lang/Object;
     156: checkcast     #7                  // class org/apache/hadoop/hbase/shaded/protobuf/generated/ClientProtos$ClientService$Interface
     159: aload_0
     160: sipush        200
     163: invokespecial #57                 // Method assertPriority:(I)Lorg/apache/hadoop/hbase/ipc/HBaseRpcController;
     166: ldc           #18                 // class org/apache/hadoop/hbase/shaded/protobuf/generated/ClientProtos$ScanRequest
     168: invokestatic  #16                 // Method org/mockito/ArgumentMatchers.any:(Ljava/lang/Class;)Ljava/lang/Object;
     171: checkcast     #18                 // class org/apache/hadoop/hbase/shaded/protobuf/generated/ClientProtos$ScanRequest
     174: invokestatic  #19                 // Method org/mockito/ArgumentMatchers.any:()Ljava/lang/Object;
     177: checkcast     #20                 // class org/apache/hbase/thirdparty/com/google/protobuf/RpcCallback
     180: invokeinterface #21,  4           // InterfaceMethod org/apache/hadoop/hbase/shaded/protobuf/generated/ClientProtos$ClientService$Interface.scan:(Lorg/apache/hbase/thirdparty/com/google/protobuf/RpcController;Lorg/apache/hadoop/hbase/shaded/protobuf/generated/ClientProtos$ScanRequest;Lorg/apache/hbase/thirdparty/com/google/protobuf/RpcCallback;)V
     185: return
    Exception table:
       from    to  target type
          68    74    77   Class java/lang/Throwable
          45    60    95   Class java/lang/Throwable
          45    60   100   any
         110   116   119   Class java/lang/Throwable
          95   102   100   any

  public void testScanMetaTable() throws java.io.IOException, java.lang.InterruptedException;
    Code:
       0: aload_0
       1: getfield      #42                 // Field conn:Lorg/apache/hadoop/hbase/client/AsyncConnection;
       4: getstatic     #60                 // Field org/apache/hadoop/hbase/TableName.META_TABLE_NAME:Lorg/apache/hadoop/hbase/TableName;
       7: invokeinterface #48,  2           // InterfaceMethod org/apache/hadoop/hbase/client/AsyncConnection.getTable:(Lorg/apache/hadoop/hbase/TableName;)Lorg/apache/hadoop/hbase/client/AsyncTable;
      12: new           #95                 // class org/apache/hadoop/hbase/client/Scan
      15: dup
      16: invokespecial #96                 // Method org/apache/hadoop/hbase/client/Scan."<init>":()V
      19: iconst_1
      20: invokevirtual #97                 // Method org/apache/hadoop/hbase/client/Scan.setCaching:(I)Lorg/apache/hadoop/hbase/client/Scan;
      23: lconst_1
      24: invokevirtual #98                 // Method org/apache/hadoop/hbase/client/Scan.setMaxResultSize:(J)Lorg/apache/hadoop/hbase/client/Scan;
      27: invokeinterface #100,  2          // InterfaceMethod org/apache/hadoop/hbase/client/AsyncTable.getScanner:(Lorg/apache/hadoop/hbase/client/Scan;)Lorg/apache/hadoop/hbase/client/ResultScanner;
      32: astore_1
      33: aconst_null
      34: astore_2
      35: aload_1
      36: invokeinterface #101,  1          // InterfaceMethod org/apache/hadoop/hbase/client/ResultScanner.next:()Lorg/apache/hadoop/hbase/client/Result;
      41: invokestatic  #102                // Method org/junit/Assert.assertNotNull:(Ljava/lang/Object;)V
      44: ldc2_w        #103                // long 1000l
      47: invokestatic  #105                // Method java/lang/Thread.sleep:(J)V
      50: aload_1
      51: ifnull        129
      54: aload_2
      55: ifnull        76
      58: aload_1
      59: invokeinterface #106,  1          // InterfaceMethod org/apache/hadoop/hbase/client/ResultScanner.close:()V
      64: goto          129
      67: astore_3
      68: aload_2
      69: aload_3
      70: invokevirtual #108                // Method java/lang/Throwable.addSuppressed:(Ljava/lang/Throwable;)V
      73: goto          129
      76: aload_1
      77: invokeinterface #106,  1          // InterfaceMethod org/apache/hadoop/hbase/client/ResultScanner.close:()V
      82: goto          129
      85: astore_3
      86: aload_3
      87: astore_2
      88: aload_3
      89: athrow
      90: astore        4
      92: aload_1
      93: ifnull        126
      96: aload_2
      97: ifnull        120
     100: aload_1
     101: invokeinterface #106,  1          // InterfaceMethod org/apache/hadoop/hbase/client/ResultScanner.close:()V
     106: goto          126
     109: astore        5
     111: aload_2
     112: aload         5
     114: invokevirtual #108                // Method java/lang/Throwable.addSuppressed:(Ljava/lang/Throwable;)V
     117: goto          126
     120: aload_1
     121: invokeinterface #106,  1          // InterfaceMethod org/apache/hadoop/hbase/client/ResultScanner.close:()V
     126: aload         4
     128: athrow
     129: ldc2_w        #103                // long 1000l
     132: invokestatic  #105                // Method java/lang/Thread.sleep:(J)V
     135: aload_0
     136: getfield      #2                  // Field stub:Lorg/apache/hadoop/hbase/shaded/protobuf/generated/ClientProtos$ClientService$Interface;
     139: iconst_4
     140: invokestatic  #109                // Method org/mockito/Mockito.atLeast:(I)Lorg/mockito/verification/VerificationMode;
     143: invokestatic  #56                 // Method org/mockito/Mockito.verify:(Ljava/lang/Object;Lorg/mockito/verification/VerificationMode;)Ljava/lang/Object;
     146: checkcast     #7                  // class org/apache/hadoop/hbase/shaded/protobuf/generated/ClientProtos$ClientService$Interface
     149: aload_0
     150: sipush        200
     153: invokespecial #57                 // Method assertPriority:(I)Lorg/apache/hadoop/hbase/ipc/HBaseRpcController;
     156: ldc           #18                 // class org/apache/hadoop/hbase/shaded/protobuf/generated/ClientProtos$ScanRequest
     158: invokestatic  #16                 // Method org/mockito/ArgumentMatchers.any:(Ljava/lang/Class;)Ljava/lang/Object;
     161: checkcast     #18                 // class org/apache/hadoop/hbase/shaded/protobuf/generated/ClientProtos$ScanRequest
     164: invokestatic  #19                 // Method org/mockito/ArgumentMatchers.any:()Ljava/lang/Object;
     167: checkcast     #20                 // class org/apache/hbase/thirdparty/com/google/protobuf/RpcCallback
     170: invokeinterface #21,  4           // InterfaceMethod org/apache/hadoop/hbase/shaded/protobuf/generated/ClientProtos$ClientService$Interface.scan:(Lorg/apache/hbase/thirdparty/com/google/protobuf/RpcController;Lorg/apache/hadoop/hbase/shaded/protobuf/generated/ClientProtos$ScanRequest;Lorg/apache/hbase/thirdparty/com/google/protobuf/RpcCallback;)V
     175: return
    Exception table:
       from    to  target type
          58    64    67   Class java/lang/Throwable
          35    50    85   Class java/lang/Throwable
          35    50    90   any
         100   106   109   Class java/lang/Throwable
          85    92    90   any

  public void testBatchNormalTable();
    Code:
       0: aload_0
       1: getfield      #42                 // Field conn:Lorg/apache/hadoop/hbase/client/AsyncConnection;
       4: aload_0
       5: getfield      #6                  // Field name:Lorg/junit/rules/TestName;
       8: invokevirtual #46                 // Method org/junit/rules/TestName.getMethodName:()Ljava/lang/String;
      11: invokestatic  #47                 // Method org/apache/hadoop/hbase/TableName.valueOf:(Ljava/lang/String;)Lorg/apache/hadoop/hbase/TableName;
      14: invokeinterface #48,  2           // InterfaceMethod org/apache/hadoop/hbase/client/AsyncConnection.getTable:(Lorg/apache/hadoop/hbase/TableName;)Lorg/apache/hadoop/hbase/client/AsyncTable;
      19: iconst_1
      20: anewarray     #70                 // class org/apache/hadoop/hbase/client/Delete
      23: dup
      24: iconst_0
      25: new           #70                 // class org/apache/hadoop/hbase/client/Delete
      28: dup
      29: iconst_0
      30: invokestatic  #50                 // Method org/apache/hadoop/hbase/util/Bytes.toBytes:(I)[B
      33: invokespecial #71                 // Method org/apache/hadoop/hbase/client/Delete."<init>":([B)V
      36: aastore
      37: invokestatic  #110                // Method java/util/Arrays.asList:([Ljava/lang/Object;)Ljava/util/List;
      40: invokeinterface #111,  2          // InterfaceMethod org/apache/hadoop/hbase/client/AsyncTable.batchAll:(Ljava/util/List;)Ljava/util/concurrent/CompletableFuture;
      45: invokevirtual #54                 // Method java/util/concurrent/CompletableFuture.join:()Ljava/lang/Object;
      48: pop
      49: aload_0
      50: getfield      #2                  // Field stub:Lorg/apache/hadoop/hbase/shaded/protobuf/generated/ClientProtos$ClientService$Interface;
      53: iconst_1
      54: invokestatic  #55                 // Method org/mockito/Mockito.times:(I)Lorg/mockito/verification/VerificationMode;
      57: invokestatic  #56                 // Method org/mockito/Mockito.verify:(Ljava/lang/Object;Lorg/mockito/verification/VerificationMode;)Ljava/lang/Object;
      60: checkcast     #7                  // class org/apache/hadoop/hbase/shaded/protobuf/generated/ClientProtos$ClientService$Interface
      63: aload_0
      64: iconst_0
      65: invokespecial #57                 // Method assertPriority:(I)Lorg/apache/hadoop/hbase/ipc/HBaseRpcController;
      68: ldc           #24                 // class org/apache/hadoop/hbase/shaded/protobuf/generated/ClientProtos$MultiRequest
      70: invokestatic  #16                 // Method org/mockito/ArgumentMatchers.any:(Ljava/lang/Class;)Ljava/lang/Object;
      73: checkcast     #24                 // class org/apache/hadoop/hbase/shaded/protobuf/generated/ClientProtos$MultiRequest
      76: invokestatic  #19                 // Method org/mockito/ArgumentMatchers.any:()Ljava/lang/Object;
      79: checkcast     #20                 // class org/apache/hbase/thirdparty/com/google/protobuf/RpcCallback
      82: invokeinterface #25,  4           // InterfaceMethod org/apache/hadoop/hbase/shaded/protobuf/generated/ClientProtos$ClientService$Interface.multi:(Lorg/apache/hbase/thirdparty/com/google/protobuf/RpcController;Lorg/apache/hadoop/hbase/shaded/protobuf/generated/ClientProtos$MultiRequest;Lorg/apache/hbase/thirdparty/com/google/protobuf/RpcCallback;)V
      87: return

  public void testBatchSystemTable();
    Code:
       0: aload_0
       1: getfield      #42                 // Field conn:Lorg/apache/hadoop/hbase/client/AsyncConnection;
       4: getstatic     #58                 // Field org/apache/hadoop/hbase/NamespaceDescriptor.SYSTEM_NAMESPACE_NAME_STR:Ljava/lang/String;
       7: aload_0
       8: getfield      #6                  // Field name:Lorg/junit/rules/TestName;
      11: invokevirtual #46                 // Method org/junit/rules/TestName.getMethodName:()Ljava/lang/String;
      14: invokestatic  #59                 // Method org/apache/hadoop/hbase/TableName.valueOf:(Ljava/lang/String;Ljava/lang/String;)Lorg/apache/hadoop/hbase/TableName;
      17: invokeinterface #48,  2           // InterfaceMethod org/apache/hadoop/hbase/client/AsyncConnection.getTable:(Lorg/apache/hadoop/hbase/TableName;)Lorg/apache/hadoop/hbase/client/AsyncTable;
      22: iconst_1
      23: anewarray     #70                 // class org/apache/hadoop/hbase/client/Delete
      26: dup
      27: iconst_0
      28: new           #70                 // class org/apache/hadoop/hbase/client/Delete
      31: dup
      32: iconst_0
      33: invokestatic  #50                 // Method org/apache/hadoop/hbase/util/Bytes.toBytes:(I)[B
      36: invokespecial #71                 // Method org/apache/hadoop/hbase/client/Delete."<init>":([B)V
      39: aastore
      40: invokestatic  #110                // Method java/util/Arrays.asList:([Ljava/lang/Object;)Ljava/util/List;
      43: invokeinterface #111,  2          // InterfaceMethod org/apache/hadoop/hbase/client/AsyncTable.batchAll:(Ljava/util/List;)Ljava/util/concurrent/CompletableFuture;
      48: invokevirtual #54                 // Method java/util/concurrent/CompletableFuture.join:()Ljava/lang/Object;
      51: pop
      52: aload_0
      53: getfield      #2                  // Field stub:Lorg/apache/hadoop/hbase/shaded/protobuf/generated/ClientProtos$ClientService$Interface;
      56: iconst_1
      57: invokestatic  #55                 // Method org/mockito/Mockito.times:(I)Lorg/mockito/verification/VerificationMode;
      60: invokestatic  #56                 // Method org/mockito/Mockito.verify:(Ljava/lang/Object;Lorg/mockito/verification/VerificationMode;)Ljava/lang/Object;
      63: checkcast     #7                  // class org/apache/hadoop/hbase/shaded/protobuf/generated/ClientProtos$ClientService$Interface
      66: aload_0
      67: sipush        200
      70: invokespecial #57                 // Method assertPriority:(I)Lorg/apache/hadoop/hbase/ipc/HBaseRpcController;
      73: ldc           #24                 // class org/apache/hadoop/hbase/shaded/protobuf/generated/ClientProtos$MultiRequest
      75: invokestatic  #16                 // Method org/mockito/ArgumentMatchers.any:(Ljava/lang/Class;)Ljava/lang/Object;
      78: checkcast     #24                 // class org/apache/hadoop/hbase/shaded/protobuf/generated/ClientProtos$MultiRequest
      81: invokestatic  #19                 // Method org/mockito/ArgumentMatchers.any:()Ljava/lang/Object;
      84: checkcast     #20                 // class org/apache/hbase/thirdparty/com/google/protobuf/RpcCallback
      87: invokeinterface #25,  4           // InterfaceMethod org/apache/hadoop/hbase/shaded/protobuf/generated/ClientProtos$ClientService$Interface.multi:(Lorg/apache/hbase/thirdparty/com/google/protobuf/RpcController;Lorg/apache/hadoop/hbase/shaded/protobuf/generated/ClientProtos$MultiRequest;Lorg/apache/hbase/thirdparty/com/google/protobuf/RpcCallback;)V
      92: return

  public void testBatchMetaTable();
    Code:
       0: aload_0
       1: getfield      #42                 // Field conn:Lorg/apache/hadoop/hbase/client/AsyncConnection;
       4: getstatic     #60                 // Field org/apache/hadoop/hbase/TableName.META_TABLE_NAME:Lorg/apache/hadoop/hbase/TableName;
       7: invokeinterface #48,  2           // InterfaceMethod org/apache/hadoop/hbase/client/AsyncConnection.getTable:(Lorg/apache/hadoop/hbase/TableName;)Lorg/apache/hadoop/hbase/client/AsyncTable;
      12: iconst_1
      13: anewarray     #70                 // class org/apache/hadoop/hbase/client/Delete
      16: dup
      17: iconst_0
      18: new           #70                 // class org/apache/hadoop/hbase/client/Delete
      21: dup
      22: iconst_0
      23: invokestatic  #50                 // Method org/apache/hadoop/hbase/util/Bytes.toBytes:(I)[B
      26: invokespecial #71                 // Method org/apache/hadoop/hbase/client/Delete."<init>":([B)V
      29: aastore
      30: invokestatic  #110                // Method java/util/Arrays.asList:([Ljava/lang/Object;)Ljava/util/List;
      33: invokeinterface #111,  2          // InterfaceMethod org/apache/hadoop/hbase/client/AsyncTable.batchAll:(Ljava/util/List;)Ljava/util/concurrent/CompletableFuture;
      38: invokevirtual #54                 // Method java/util/concurrent/CompletableFuture.join:()Ljava/lang/Object;
      41: pop
      42: aload_0
      43: getfield      #2                  // Field stub:Lorg/apache/hadoop/hbase/shaded/protobuf/generated/ClientProtos$ClientService$Interface;
      46: iconst_1
      47: invokestatic  #55                 // Method org/mockito/Mockito.times:(I)Lorg/mockito/verification/VerificationMode;
      50: invokestatic  #56                 // Method org/mockito/Mockito.verify:(Ljava/lang/Object;Lorg/mockito/verification/VerificationMode;)Ljava/lang/Object;
      53: checkcast     #7                  // class org/apache/hadoop/hbase/shaded/protobuf/generated/ClientProtos$ClientService$Interface
      56: aload_0
      57: sipush        200
      60: invokespecial #57                 // Method assertPriority:(I)Lorg/apache/hadoop/hbase/ipc/HBaseRpcController;
      63: ldc           #24                 // class org/apache/hadoop/hbase/shaded/protobuf/generated/ClientProtos$MultiRequest
      65: invokestatic  #16                 // Method org/mockito/ArgumentMatchers.any:(Ljava/lang/Class;)Ljava/lang/Object;
      68: checkcast     #24                 // class org/apache/hadoop/hbase/shaded/protobuf/generated/ClientProtos$MultiRequest
      71: invokestatic  #19                 // Method org/mockito/ArgumentMatchers.any:()Ljava/lang/Object;
      74: checkcast     #20                 // class org/apache/hbase/thirdparty/com/google/protobuf/RpcCallback
      77: invokeinterface #25,  4           // InterfaceMethod org/apache/hadoop/hbase/shaded/protobuf/generated/ClientProtos$ClientService$Interface.multi:(Lorg/apache/hbase/thirdparty/com/google/protobuf/RpcController;Lorg/apache/hadoop/hbase/shaded/protobuf/generated/ClientProtos$MultiRequest;Lorg/apache/hbase/thirdparty/com/google/protobuf/RpcCallback;)V
      82: return

  static org.apache.hadoop.hbase.shaded.protobuf.generated.ClientProtos$ClientService$Interface access$000(org.apache.hadoop.hbase.client.TestAsyncTableRpcPriority);
    Code:
       0: aload_0
       1: getfield      #2                  // Field stub:Lorg/apache/hadoop/hbase/shaded/protobuf/generated/ClientProtos$ClientService$Interface;
       4: areturn

  static {};
    Code:
       0: ldc           #112                // class org/apache/hadoop/hbase/client/TestAsyncTableRpcPriority
       2: invokestatic  #113                // Method org/apache/hadoop/hbase/HBaseClassTestRule.forClass:(Ljava/lang/Class;)Lorg/apache/hadoop/hbase/HBaseClassTestRule;
       5: putstatic     #114                // Field CLASS_RULE:Lorg/apache/hadoop/hbase/HBaseClassTestRule;
       8: invokestatic  #115                // Method org/apache/hadoop/hbase/HBaseConfiguration.create:()Lorg/apache/hadoop/conf/Configuration;
      11: putstatic     #35                 // Field CONF:Lorg/apache/hadoop/conf/Configuration;
      14: return
}
