Compiled from "TestRecoverableZooKeeper.java"
public class org.apache.hadoop.hbase.zookeeper.TestRecoverableZooKeeper {
  public static final org.apache.hadoop.hbase.HBaseClassTestRule CLASS_RULE;

  org.apache.hadoop.hbase.Abortable abortable;

  public org.apache.hadoop.hbase.zookeeper.TestRecoverableZooKeeper();
    Code:
       0: aload_0
       1: invokespecial #1                  // Method java/lang/Object."<init>":()V
       4: aload_0
       5: new           #2                  // class org/apache/hadoop/hbase/zookeeper/TestRecoverableZooKeeper$1
       8: dup
       9: aload_0
      10: invokespecial #3                  // Method org/apache/hadoop/hbase/zookeeper/TestRecoverableZooKeeper$1."<init>":(Lorg/apache/hadoop/hbase/zookeeper/TestRecoverableZooKeeper;)V
      13: putfield      #4                  // Field abortable:Lorg/apache/hadoop/hbase/Abortable;
      16: return

  public static void setUpBeforeClass() throws java.lang.Exception;
    Code:
       0: getstatic     #5                  // Field TEST_UTIL:Lorg/apache/hadoop/hbase/HBaseZKTestingUtility;
       3: invokevirtual #6                  // Method org/apache/hadoop/hbase/HBaseZKTestingUtility.startMiniZKCluster:()Lorg/apache/hadoop/hbase/zookeeper/MiniZooKeeperCluster;
       6: pop
       7: return

  public static void tearDownAfterClass() throws java.lang.Exception;
    Code:
       0: getstatic     #5                  // Field TEST_UTIL:Lorg/apache/hadoop/hbase/HBaseZKTestingUtility;
       3: invokevirtual #7                  // Method org/apache/hadoop/hbase/HBaseZKTestingUtility.shutdownMiniZKCluster:()V
       6: return

  public void testSetDataVersionMismatchInLoop() throws java.lang.Exception;
    Code:
       0: ldc           #8                  // String /hbase/splitWAL/9af7cfc9b15910a0b3d714bf40a3248f
       2: astore_1
       3: getstatic     #5                  // Field TEST_UTIL:Lorg/apache/hadoop/hbase/HBaseZKTestingUtility;
       6: invokevirtual #9                  // Method org/apache/hadoop/hbase/HBaseZKTestingUtility.getConfiguration:()Lorg/apache/hadoop/conf/Configuration;
       9: astore_2
      10: new           #10                 // class org/apache/hadoop/hbase/zookeeper/ZKWatcher
      13: dup
      14: aload_2
      15: ldc           #11                 // String testSetDataVersionMismatchInLoop
      17: aload_0
      18: getfield      #4                  // Field abortable:Lorg/apache/hadoop/hbase/Abortable;
      21: iconst_1
      22: invokespecial #12                 // Method org/apache/hadoop/hbase/zookeeper/ZKWatcher."<init>":(Lorg/apache/hadoop/conf/Configuration;Ljava/lang/String;Lorg/apache/hadoop/hbase/Abortable;Z)V
      25: astore_3
      26: aload_2
      27: invokestatic  #13                 // Method org/apache/hadoop/hbase/zookeeper/ZKConfig.getZKQuorumServersString:(Lorg/apache/hadoop/conf/Configuration;)Ljava/lang/String;
      30: astore        4
      32: aload_2
      33: aload         4
      35: aload_3
      36: invokestatic  #14                 // Method org/apache/hadoop/hbase/zookeeper/ZKUtil.connect:(Lorg/apache/hadoop/conf/Configuration;Ljava/lang/String;Lorg/apache/zookeeper/Watcher;)Lorg/apache/hadoop/hbase/zookeeper/RecoverableZooKeeper;
      39: astore        5
      41: aload         5
      43: aload_1
      44: iconst_0
      45: newarray       byte
      47: getstatic     #15                 // Field org/apache/zookeeper/ZooDefs$Ids.OPEN_ACL_UNSAFE:Ljava/util/ArrayList;
      50: getstatic     #16                 // Field org/apache/zookeeper/CreateMode.PERSISTENT:Lorg/apache/zookeeper/CreateMode;
      53: invokevirtual #17                 // Method org/apache/hadoop/hbase/zookeeper/RecoverableZooKeeper.create:(Ljava/lang/String;[BLjava/util/List;Lorg/apache/zookeeper/CreateMode;)Ljava/lang/String;
      56: pop
      57: aload         5
      59: aload_1
      60: ldc           #18                 // String OPENING
      62: invokestatic  #19                 // Method org/apache/hadoop/hbase/util/Bytes.toBytes:(Ljava/lang/String;)[B
      65: iconst_0
      66: invokevirtual #20                 // Method org/apache/hadoop/hbase/zookeeper/RecoverableZooKeeper.setData:(Ljava/lang/String;[BI)Lorg/apache/zookeeper/data/Stat;
      69: pop
      70: ldc           #21                 // class org/apache/hadoop/hbase/zookeeper/RecoverableZooKeeper
      72: ldc           #22                 // String zk
      74: invokevirtual #23                 // Method java/lang/Class.getDeclaredField:(Ljava/lang/String;)Ljava/lang/reflect/Field;
      77: astore        6
      79: aload         6
      81: iconst_1
      82: invokevirtual #24                 // Method java/lang/reflect/Field.setAccessible:(Z)V
      85: aload_2
      86: ldc           #26                 // String zookeeper.session.timeout
      88: ldc           #27                 // int 90000
      90: invokevirtual #28                 // Method org/apache/hadoop/conf/Configuration.getInt:(Ljava/lang/String;I)I
      93: istore        7
      95: new           #29                 // class org/apache/hadoop/hbase/zookeeper/TestRecoverableZooKeeper$ZookeeperStub
      98: dup
      99: aload_0
     100: aload         4
     102: iload         7
     104: aload_3
     105: invokespecial #30                 // Method org/apache/hadoop/hbase/zookeeper/TestRecoverableZooKeeper$ZookeeperStub."<init>":(Lorg/apache/hadoop/hbase/zookeeper/TestRecoverableZooKeeper;Ljava/lang/String;ILorg/apache/zookeeper/Watcher;)V
     108: astore        8
     110: aload         8
     112: iconst_1
     113: invokevirtual #31                 // Method org/apache/hadoop/hbase/zookeeper/TestRecoverableZooKeeper$ZookeeperStub.setThrowExceptionInNumOperations:(I)V
     116: aload         6
     118: aload         5
     120: aload         8
     122: invokevirtual #32                 // Method java/lang/reflect/Field.set:(Ljava/lang/Object;Ljava/lang/Object;)V
     125: ldc           #33                 // String OPENED
     127: invokestatic  #19                 // Method org/apache/hadoop/hbase/util/Bytes.toBytes:(Ljava/lang/String;)[B
     130: astore        9
     132: aload         5
     134: aload_1
     135: aload         9
     137: iconst_1
     138: invokevirtual #20                 // Method org/apache/hadoop/hbase/zookeeper/RecoverableZooKeeper.setData:(Ljava/lang/String;[BI)Lorg/apache/zookeeper/data/Stat;
     141: pop
     142: aload         5
     144: aload_1
     145: iconst_0
     146: new           #34                 // class org/apache/zookeeper/data/Stat
     149: dup
     150: invokespecial #35                 // Method org/apache/zookeeper/data/Stat."<init>":()V
     153: invokevirtual #36                 // Method org/apache/hadoop/hbase/zookeeper/RecoverableZooKeeper.getData:(Ljava/lang/String;ZLorg/apache/zookeeper/data/Stat;)[B
     156: astore        10
     158: aload         9
     160: aload         10
     162: invokestatic  #37                 // Method org/apache/hadoop/hbase/util/Bytes.equals:([B[B)Z
     165: invokestatic  #38                 // Method org/junit/Assert.assertTrue:(Z)V
     168: return

  static {};
    Code:
       0: ldc           #39                 // class org/apache/hadoop/hbase/zookeeper/TestRecoverableZooKeeper
       2: invokestatic  #40                 // Method org/apache/hadoop/hbase/HBaseClassTestRule.forClass:(Ljava/lang/Class;)Lorg/apache/hadoop/hbase/HBaseClassTestRule;
       5: putstatic     #41                 // Field CLASS_RULE:Lorg/apache/hadoop/hbase/HBaseClassTestRule;
       8: new           #42                 // class org/apache/hadoop/hbase/HBaseZKTestingUtility
      11: dup
      12: invokespecial #43                 // Method org/apache/hadoop/hbase/HBaseZKTestingUtility."<init>":()V
      15: putstatic     #5                  // Field TEST_UTIL:Lorg/apache/hadoop/hbase/HBaseZKTestingUtility;
      18: return
}
