Compiled from "TestSplitTransactionOnCluster.java"
class org.apache.hadoop.hbase.regionserver.TestSplitTransactionOnCluster$CustomSplitPolicy extends org.apache.hadoop.hbase.regionserver.IncreasingToUpperBoundRegionSplitPolicy {
  org.apache.hadoop.hbase.regionserver.TestSplitTransactionOnCluster$CustomSplitPolicy();
    Code:
       0: aload_0
       1: invokespecial #1                  // Method org/apache/hadoop/hbase/regionserver/IncreasingToUpperBoundRegionSplitPolicy."<init>":()V
       4: return

  protected boolean shouldSplit();
    Code:
       0: iconst_1
       1: ireturn

  public boolean skipStoreFileRangeCheck(java.lang.String);
    Code:
       0: aload_1
       1: ldc           #2                  // String i_
       3: invokevirtual #3                  // Method java/lang/String.startsWith:(Ljava/lang/String;)Z
       6: ifeq          11
       9: iconst_1
      10: ireturn
      11: iconst_0
      12: ireturn
}
