Compiled from "TestHFileBlockIndex.java"
class org.apache.hadoop.hbase.io.hfile.TestHFileBlockIndex$BlockReaderWrapper implements org.apache.hadoop.hbase.io.hfile.HFile$CachingBlockReader {
  public int hitCount;

  public int missCount;

  public org.apache.hadoop.hbase.io.hfile.TestHFileBlockIndex$BlockReaderWrapper(org.apache.hadoop.hbase.io.hfile.HFileBlock$FSReader);
    Code:
       0: aload_0
       1: invokespecial #1                  // Method java/lang/Object."<init>":()V
       4: aload_0
       5: iconst_0
       6: putfield      #2                  // Field hitCount:I
       9: aload_0
      10: iconst_0
      11: putfield      #3                  // Field missCount:I
      14: aload_0
      15: aload_1
      16: putfield      #4                  // Field realReader:Lorg/apache/hadoop/hbase/io/hfile/HFileBlock$FSReader;
      19: return

  public void returnBlock(org.apache.hadoop.hbase.io.hfile.HFileBlock);
    Code:
       0: return

  public org.apache.hadoop.hbase.io.hfile.HFileBlock readBlock(long, long, boolean, boolean, boolean, boolean, org.apache.hadoop.hbase.io.hfile.BlockType, org.apache.hadoop.hbase.io.encoding.DataBlockEncoding) throws java.io.IOException;
    Code:
       0: lload_1
       1: aload_0
       2: getfield      #5                  // Field prevOffset:J
       5: lcmp
       6: ifne          42
       9: lload_3
      10: aload_0
      11: getfield      #6                  // Field prevOnDiskSize:J
      14: lcmp
      15: ifne          42
      18: iload         6
      20: aload_0
      21: getfield      #7                  // Field prevPread:Z
      24: if_icmpne     42
      27: aload_0
      28: dup
      29: getfield      #2                  // Field hitCount:I
      32: iconst_1
      33: iadd
      34: putfield      #2                  // Field hitCount:I
      37: aload_0
      38: getfield      #8                  // Field prevBlock:Lorg/apache/hadoop/hbase/io/hfile/HFileBlock;
      41: areturn
      42: aload_0
      43: dup
      44: getfield      #3                  // Field missCount:I
      47: iconst_1
      48: iadd
      49: putfield      #3                  // Field missCount:I
      52: aload_0
      53: aload_0
      54: getfield      #4                  // Field realReader:Lorg/apache/hadoop/hbase/io/hfile/HFileBlock$FSReader;
      57: lload_1
      58: lload_3
      59: iload         6
      61: iconst_0
      62: invokeinterface #9,  7            // InterfaceMethod org/apache/hadoop/hbase/io/hfile/HFileBlock$FSReader.readBlockData:(JJZZ)Lorg/apache/hadoop/hbase/io/hfile/HFileBlock;
      67: putfield      #8                  // Field prevBlock:Lorg/apache/hadoop/hbase/io/hfile/HFileBlock;
      70: aload_0
      71: lload_1
      72: putfield      #5                  // Field prevOffset:J
      75: aload_0
      76: lload_3
      77: putfield      #6                  // Field prevOnDiskSize:J
      80: aload_0
      81: iload         6
      83: putfield      #7                  // Field prevPread:Z
      86: aload_0
      87: getfield      #8                  // Field prevBlock:Lorg/apache/hadoop/hbase/io/hfile/HFileBlock;
      90: areturn
}
