Compiled from "TestProcedureToString.java"
public class org.apache.hadoop.hbase.procedure2.TestProcedureToString {
  public static final org.apache.hadoop.hbase.HBaseClassTestRule CLASS_RULE;

  public org.apache.hadoop.hbase.procedure2.TestProcedureToString();
    Code:
       0: aload_0
       1: invokespecial #1                  // Method java/lang/Object."<init>":()V
       4: return

  public void testBasicToString();
    Code:
       0: new           #2                  // class org/apache/hadoop/hbase/procedure2/TestProcedureToString$BasicProcedure
       3: dup
       4: invokespecial #3                  // Method org/apache/hadoop/hbase/procedure2/TestProcedureToString$BasicProcedure."<init>":()V
       7: astore_1
       8: getstatic     #4                  // Field org/apache/hadoop/hbase/shaded/protobuf/generated/ProcedureProtos$ProcedureState.RUNNABLE:Lorg/apache/hadoop/hbase/shaded/protobuf/generated/ProcedureProtos$ProcedureState;
      11: astore_2
      12: aload_1
      13: aload_2
      14: invokevirtual #5                  // Method org/apache/hadoop/hbase/procedure2/TestProcedureToString$BasicProcedure.setState:(Lorg/apache/hadoop/hbase/shaded/protobuf/generated/ProcedureProtos$ProcedureState;)V
      17: aload_1
      18: invokevirtual #6                  // Method org/apache/hadoop/hbase/procedure2/TestProcedureToString$BasicProcedure.toString:()Ljava/lang/String;
      21: aload_2
      22: invokevirtual #7                  // Method org/apache/hadoop/hbase/shaded/protobuf/generated/ProcedureProtos$ProcedureState.toString:()Ljava/lang/String;
      25: invokevirtual #8                  // Method java/lang/String.contains:(Ljava/lang/CharSequence;)Z
      28: invokestatic  #9                  // Method org/junit/Assert.assertTrue:(Z)V
      31: new           #10                 // class org/apache/hadoop/hbase/procedure2/TestProcedureToString$DoublingStateStringBasicProcedure
      34: dup
      35: invokespecial #11                 // Method org/apache/hadoop/hbase/procedure2/TestProcedureToString$DoublingStateStringBasicProcedure."<init>":()V
      38: astore_1
      39: aload_1
      40: aload_2
      41: invokevirtual #5                  // Method org/apache/hadoop/hbase/procedure2/TestProcedureToString$BasicProcedure.setState:(Lorg/apache/hadoop/hbase/shaded/protobuf/generated/ProcedureProtos$ProcedureState;)V
      44: new           #12                 // class java/lang/StringBuilder
      47: dup
      48: invokespecial #13                 // Method java/lang/StringBuilder."<init>":()V
      51: aload_2
      52: invokevirtual #7                  // Method org/apache/hadoop/hbase/shaded/protobuf/generated/ProcedureProtos$ProcedureState.toString:()Ljava/lang/String;
      55: invokevirtual #14                 // Method java/lang/StringBuilder.append:(Ljava/lang/String;)Ljava/lang/StringBuilder;
      58: aload_2
      59: invokevirtual #7                  // Method org/apache/hadoop/hbase/shaded/protobuf/generated/ProcedureProtos$ProcedureState.toString:()Ljava/lang/String;
      62: invokevirtual #14                 // Method java/lang/StringBuilder.append:(Ljava/lang/String;)Ljava/lang/StringBuilder;
      65: invokevirtual #15                 // Method java/lang/StringBuilder.toString:()Ljava/lang/String;
      68: astore_3
      69: aload_1
      70: invokevirtual #6                  // Method org/apache/hadoop/hbase/procedure2/TestProcedureToString$BasicProcedure.toString:()Ljava/lang/String;
      73: aload_3
      74: invokevirtual #8                  // Method java/lang/String.contains:(Ljava/lang/CharSequence;)Z
      77: invokestatic  #9                  // Method org/junit/Assert.assertTrue:(Z)V
      80: return

  public void testStateMachineProcedure();
    Code:
       0: new           #16                 // class org/apache/hadoop/hbase/procedure2/TestProcedureToString$SimpleStateMachineProcedure
       3: dup
       4: invokespecial #17                 // Method org/apache/hadoop/hbase/procedure2/TestProcedureToString$SimpleStateMachineProcedure."<init>":()V
       7: astore_1
       8: getstatic     #4                  // Field org/apache/hadoop/hbase/shaded/protobuf/generated/ProcedureProtos$ProcedureState.RUNNABLE:Lorg/apache/hadoop/hbase/shaded/protobuf/generated/ProcedureProtos$ProcedureState;
      11: astore_2
      12: aload_1
      13: aload_2
      14: invokevirtual #18                 // Method org/apache/hadoop/hbase/procedure2/TestProcedureToString$SimpleStateMachineProcedure.setState:(Lorg/apache/hadoop/hbase/shaded/protobuf/generated/ProcedureProtos$ProcedureState;)V
      17: aload_1
      18: getstatic     #19                 // Field org/apache/hadoop/hbase/shaded/protobuf/generated/MasterProcedureProtos$ServerCrashState.SERVER_CRASH_ASSIGN:Lorg/apache/hadoop/hbase/shaded/protobuf/generated/MasterProcedureProtos$ServerCrashState;
      21: invokevirtual #20                 // Method org/apache/hadoop/hbase/procedure2/TestProcedureToString$SimpleStateMachineProcedure.setNextState:(Ljava/lang/Object;)V
      24: aload_1
      25: invokevirtual #21                 // Method org/apache/hadoop/hbase/procedure2/TestProcedureToString$SimpleStateMachineProcedure.toString:()Ljava/lang/String;
      28: aload_2
      29: invokevirtual #7                  // Method org/apache/hadoop/hbase/shaded/protobuf/generated/ProcedureProtos$ProcedureState.toString:()Ljava/lang/String;
      32: invokevirtual #8                  // Method java/lang/String.contains:(Ljava/lang/CharSequence;)Z
      35: invokestatic  #9                  // Method org/junit/Assert.assertTrue:(Z)V
      38: aload_1
      39: invokevirtual #21                 // Method org/apache/hadoop/hbase/procedure2/TestProcedureToString$SimpleStateMachineProcedure.toString:()Ljava/lang/String;
      42: getstatic     #19                 // Field org/apache/hadoop/hbase/shaded/protobuf/generated/MasterProcedureProtos$ServerCrashState.SERVER_CRASH_ASSIGN:Lorg/apache/hadoop/hbase/shaded/protobuf/generated/MasterProcedureProtos$ServerCrashState;
      45: invokevirtual #22                 // Method org/apache/hadoop/hbase/shaded/protobuf/generated/MasterProcedureProtos$ServerCrashState.toString:()Ljava/lang/String;
      48: invokevirtual #8                  // Method java/lang/String.contains:(Ljava/lang/CharSequence;)Z
      51: invokestatic  #9                  // Method org/junit/Assert.assertTrue:(Z)V
      54: return

  static {};
    Code:
       0: ldc           #23                 // class org/apache/hadoop/hbase/procedure2/TestProcedureToString
       2: invokestatic  #24                 // Method org/apache/hadoop/hbase/HBaseClassTestRule.forClass:(Ljava/lang/Class;)Lorg/apache/hadoop/hbase/HBaseClassTestRule;
       5: putstatic     #25                 // Field CLASS_RULE:Lorg/apache/hadoop/hbase/HBaseClassTestRule;
       8: return
}
