Compiled from "TestMetricRegistryImpl.java"
class org.apache.hadoop.hbase.metrics.impl.TestMetricRegistryImpl$1 implements org.apache.hadoop.hbase.metrics.Gauge<java.lang.Long> {
  final org.apache.hadoop.hbase.metrics.impl.TestMetricRegistryImpl this$0;

  org.apache.hadoop.hbase.metrics.impl.TestMetricRegistryImpl$1(org.apache.hadoop.hbase.metrics.impl.TestMetricRegistryImpl);
    Code:
       0: aload_0
       1: aload_1
       2: putfield      #1                  // Field this$0:Lorg/apache/hadoop/hbase/metrics/impl/TestMetricRegistryImpl;
       5: aload_0
       6: invokespecial #2                  // Method java/lang/Object."<init>":()V
       9: return

  public java.lang.Long getValue();
    Code:
       0: ldc2_w        #3                  // long 42l
       3: invokestatic  #5                  // Method java/lang/Long.valueOf:(J)Ljava/lang/Long;
       6: areturn

  public java.lang.Object getValue();
    Code:
       0: aload_0
       1: invokevirtual #6                  // Method getValue:()Ljava/lang/Long;
       4: areturn
}
