Compiled from "TestRecoverableZooKeeper.java"
class org.apache.hadoop.hbase.zookeeper.TestRecoverableZooKeeper$1 implements org.apache.hadoop.hbase.Abortable {
  final org.apache.hadoop.hbase.zookeeper.TestRecoverableZooKeeper this$0;

  org.apache.hadoop.hbase.zookeeper.TestRecoverableZooKeeper$1(org.apache.hadoop.hbase.zookeeper.TestRecoverableZooKeeper);
    Code:
       0: aload_0
       1: aload_1
       2: putfield      #1                  // Field this$0:Lorg/apache/hadoop/hbase/zookeeper/TestRecoverableZooKeeper;
       5: aload_0
       6: invokespecial #2                  // Method java/lang/Object."<init>":()V
       9: return

  public void abort(java.lang.String, java.lang.Throwable);
    Code:
       0: return

  public boolean isAborted();
    Code:
       0: iconst_0
       1: ireturn
}
