Compiled from "TestMetaTableAccessor.java"
public class org.apache.hadoop.hbase.TestMetaTableAccessor$SpyingRpcScheduler extends org.apache.hadoop.hbase.ipc.DelegatingRpcScheduler {
  long numPriorityCalls;

  public org.apache.hadoop.hbase.TestMetaTableAccessor$SpyingRpcScheduler(org.apache.hadoop.hbase.ipc.RpcScheduler);
    Code:
       0: aload_0
       1: aload_1
       2: invokespecial #1                  // Method org/apache/hadoop/hbase/ipc/DelegatingRpcScheduler."<init>":(Lorg/apache/hadoop/hbase/ipc/RpcScheduler;)V
       5: aload_0
       6: lconst_0
       7: putfield      #2                  // Field numPriorityCalls:J
      10: return

  public boolean dispatch(org.apache.hadoop.hbase.ipc.CallRunner) throws java.io.IOException, java.lang.InterruptedException;
    Code:
       0: aload_1
       1: invokevirtual #3                  // Method org/apache/hadoop/hbase/ipc/CallRunner.getRpcCall:()Lorg/apache/hadoop/hbase/ipc/RpcCall;
       4: invokeinterface #4,  1            // InterfaceMethod org/apache/hadoop/hbase/ipc/RpcCall.getPriority:()I
       9: istore_2
      10: iload_2
      11: bipush        10
      13: if_icmple     26
      16: aload_0
      17: dup
      18: getfield      #2                  // Field numPriorityCalls:J
      21: lconst_1
      22: ladd
      23: putfield      #2                  // Field numPriorityCalls:J
      26: aload_0
      27: aload_1
      28: invokespecial #6                  // Method org/apache/hadoop/hbase/ipc/DelegatingRpcScheduler.dispatch:(Lorg/apache/hadoop/hbase/ipc/CallRunner;)Z
      31: ireturn
}
