Compiled from "TestMasterFileSystem.java"
public class org.apache.hadoop.hbase.master.TestMasterFileSystem {
  public static final org.apache.hadoop.hbase.HBaseClassTestRule CLASS_RULE;

  public org.junit.rules.TestName name;

  public org.apache.hadoop.hbase.master.TestMasterFileSystem();
    Code:
       0: aload_0
       1: invokespecial #1                  // Method java/lang/Object."<init>":()V
       4: aload_0
       5: new           #2                  // class org/junit/rules/TestName
       8: dup
       9: invokespecial #3                  // Method org/junit/rules/TestName."<init>":()V
      12: putfield      #4                  // Field name:Lorg/junit/rules/TestName;
      15: return

  public static void setupTest() throws java.lang.Exception;
    Code:
       0: getstatic     #5                  // Field UTIL:Lorg/apache/hadoop/hbase/HBaseTestingUtility;
       3: invokevirtual #6                  // Method org/apache/hadoop/hbase/HBaseTestingUtility.startMiniCluster:()Lorg/apache/hadoop/hbase/MiniHBaseCluster;
       6: pop
       7: return

  public static void teardownTest() throws java.lang.Exception;
    Code:
       0: getstatic     #5                  // Field UTIL:Lorg/apache/hadoop/hbase/HBaseTestingUtility;
       3: invokevirtual #7                  // Method org/apache/hadoop/hbase/HBaseTestingUtility.shutdownMiniCluster:()V
       6: return

  public void testFsUriSetProperly() throws java.lang.Exception;
    Code:
       0: getstatic     #5                  // Field UTIL:Lorg/apache/hadoop/hbase/HBaseTestingUtility;
       3: invokevirtual #8                  // Method org/apache/hadoop/hbase/HBaseTestingUtility.getMiniHBaseCluster:()Lorg/apache/hadoop/hbase/MiniHBaseCluster;
       6: invokevirtual #9                  // Method org/apache/hadoop/hbase/MiniHBaseCluster.getMaster:()Lorg/apache/hadoop/hbase/master/HMaster;
       9: astore_1
      10: aload_1
      11: invokevirtual #10                 // Method org/apache/hadoop/hbase/master/HMaster.getMasterFileSystem:()Lorg/apache/hadoop/hbase/master/MasterFileSystem;
      14: astore_2
      15: aload_2
      16: invokevirtual #11                 // Method org/apache/hadoop/hbase/master/MasterFileSystem.getConfiguration:()Lorg/apache/hadoop/conf/Configuration;
      19: invokestatic  #12                 // Method org/apache/hadoop/hbase/util/FSUtils.getRootDir:(Lorg/apache/hadoop/conf/Configuration;)Lorg/apache/hadoop/fs/Path;
      22: astore_3
      23: aload_2
      24: invokevirtual #13                 // Method org/apache/hadoop/hbase/master/MasterFileSystem.getFileSystem:()Lorg/apache/hadoop/fs/FileSystem;
      27: invokevirtual #14                 // Method org/apache/hadoop/fs/FileSystem.getConf:()Lorg/apache/hadoop/conf/Configuration;
      30: invokestatic  #12                 // Method org/apache/hadoop/hbase/util/FSUtils.getRootDir:(Lorg/apache/hadoop/conf/Configuration;)Lorg/apache/hadoop/fs/Path;
      33: astore        4
      35: getstatic     #15                 // Field LOG:Lorg/slf4j/Logger;
      38: new           #16                 // class java/lang/StringBuilder
      41: dup
      42: invokespecial #17                 // Method java/lang/StringBuilder."<init>":()V
      45: ldc           #18                 // String from fs uri:
      47: invokevirtual #19                 // Method java/lang/StringBuilder.append:(Ljava/lang/String;)Ljava/lang/StringBuilder;
      50: aload_2
      51: invokevirtual #13                 // Method org/apache/hadoop/hbase/master/MasterFileSystem.getFileSystem:()Lorg/apache/hadoop/fs/FileSystem;
      54: invokevirtual #14                 // Method org/apache/hadoop/fs/FileSystem.getConf:()Lorg/apache/hadoop/conf/Configuration;
      57: invokestatic  #20                 // Method org/apache/hadoop/fs/FileSystem.getDefaultUri:(Lorg/apache/hadoop/conf/Configuration;)Ljava/net/URI;
      60: invokevirtual #21                 // Method java/lang/StringBuilder.append:(Ljava/lang/Object;)Ljava/lang/StringBuilder;
      63: invokevirtual #22                 // Method java/lang/StringBuilder.toString:()Ljava/lang/String;
      66: invokeinterface #23,  2           // InterfaceMethod org/slf4j/Logger.debug:(Ljava/lang/String;)V
      71: getstatic     #15                 // Field LOG:Lorg/slf4j/Logger;
      74: new           #16                 // class java/lang/StringBuilder
      77: dup
      78: invokespecial #17                 // Method java/lang/StringBuilder."<init>":()V
      81: ldc           #24                 // String from configuration uri:
      83: invokevirtual #19                 // Method java/lang/StringBuilder.append:(Ljava/lang/String;)Ljava/lang/StringBuilder;
      86: aload_2
      87: invokevirtual #11                 // Method org/apache/hadoop/hbase/master/MasterFileSystem.getConfiguration:()Lorg/apache/hadoop/conf/Configuration;
      90: invokestatic  #20                 // Method org/apache/hadoop/fs/FileSystem.getDefaultUri:(Lorg/apache/hadoop/conf/Configuration;)Ljava/net/URI;
      93: invokevirtual #21                 // Method java/lang/StringBuilder.append:(Ljava/lang/Object;)Ljava/lang/StringBuilder;
      96: invokevirtual #22                 // Method java/lang/StringBuilder.toString:()Ljava/lang/String;
      99: invokeinterface #23,  2           // InterfaceMethod org/slf4j/Logger.debug:(Ljava/lang/String;)V
     104: aload_3
     105: aload         4
     107: invokestatic  #25                 // Method org/junit/Assert.assertEquals:(Ljava/lang/Object;Ljava/lang/Object;)V
     110: return

  public void testCheckTempDir() throws java.lang.Exception;
    Code:
       0: getstatic     #5                  // Field UTIL:Lorg/apache/hadoop/hbase/HBaseTestingUtility;
       3: invokevirtual #8                  // Method org/apache/hadoop/hbase/HBaseTestingUtility.getMiniHBaseCluster:()Lorg/apache/hadoop/hbase/MiniHBaseCluster;
       6: invokevirtual #9                  // Method org/apache/hadoop/hbase/MiniHBaseCluster.getMaster:()Lorg/apache/hadoop/hbase/master/HMaster;
       9: invokevirtual #10                 // Method org/apache/hadoop/hbase/master/HMaster.getMasterFileSystem:()Lorg/apache/hadoop/hbase/master/MasterFileSystem;
      12: astore_1
      13: aload_0
      14: getfield      #4                  // Field name:Lorg/junit/rules/TestName;
      17: invokevirtual #26                 // Method org/junit/rules/TestName.getMethodName:()Ljava/lang/String;
      20: invokestatic  #27                 // Method org/apache/hadoop/hbase/TableName.valueOf:(Ljava/lang/String;)Lorg/apache/hadoop/hbase/TableName;
      23: astore_2
      24: ldc           #28                 // String fam
      26: invokestatic  #29                 // Method org/apache/hadoop/hbase/util/Bytes.toBytes:(Ljava/lang/String;)[B
      29: astore_3
      30: iconst_3
      31: anewarray     #30                 // class "[B"
      34: dup
      35: iconst_0
      36: ldc           #31                 // String b
      38: invokestatic  #29                 // Method org/apache/hadoop/hbase/util/Bytes.toBytes:(Ljava/lang/String;)[B
      41: aastore
      42: dup
      43: iconst_1
      44: ldc           #32                 // String c
      46: invokestatic  #29                 // Method org/apache/hadoop/hbase/util/Bytes.toBytes:(Ljava/lang/String;)[B
      49: aastore
      50: dup
      51: iconst_2
      52: ldc           #33                 // String d
      54: invokestatic  #29                 // Method org/apache/hadoop/hbase/util/Bytes.toBytes:(Ljava/lang/String;)[B
      57: aastore
      58: astore        4
      60: getstatic     #5                  // Field UTIL:Lorg/apache/hadoop/hbase/HBaseTestingUtility;
      63: aload_2
      64: aload_3
      65: aload         4
      67: invokevirtual #34                 // Method org/apache/hadoop/hbase/HBaseTestingUtility.createTable:(Lorg/apache/hadoop/hbase/TableName;[B[[B)Lorg/apache/hadoop/hbase/client/Table;
      70: pop
      71: getstatic     #5                  // Field UTIL:Lorg/apache/hadoop/hbase/HBaseTestingUtility;
      74: invokevirtual #35                 // Method org/apache/hadoop/hbase/HBaseTestingUtility.getHBaseCluster:()Lorg/apache/hadoop/hbase/MiniHBaseCluster;
      77: aload_2
      78: invokevirtual #36                 // Method org/apache/hadoop/hbase/MiniHBaseCluster.getRegions:(Lorg/apache/hadoop/hbase/TableName;)Ljava/util/List;
      81: astore        5
      83: ldc2_w        #37                 // long 4l
      86: aload         5
      88: invokeinterface #39,  1           // InterfaceMethod java/util/List.size:()I
      93: i2l
      94: invokestatic  #40                 // Method org/junit/Assert.assertEquals:(JJ)V
      97: getstatic     #5                  // Field UTIL:Lorg/apache/hadoop/hbase/HBaseTestingUtility;
     100: invokevirtual #41                 // Method org/apache/hadoop/hbase/HBaseTestingUtility.getConnection:()Lorg/apache/hadoop/hbase/client/Connection;
     103: aload_2
     104: invokeinterface #42,  2           // InterfaceMethod org/apache/hadoop/hbase/client/Connection.getTable:(Lorg/apache/hadoop/hbase/TableName;)Lorg/apache/hadoop/hbase/client/Table;
     109: astore        6
     111: aconst_null
     112: astore        7
     114: getstatic     #5                  // Field UTIL:Lorg/apache/hadoop/hbase/HBaseTestingUtility;
     117: aload         6
     119: aload_3
     120: invokevirtual #43                 // Method org/apache/hadoop/hbase/HBaseTestingUtility.loadTable:(Lorg/apache/hadoop/hbase/client/Table;[B)I
     123: pop
     124: aload         6
     126: ifnull        219
     129: aload         7
     131: ifnull        156
     134: aload         6
     136: invokeinterface #44,  1           // InterfaceMethod org/apache/hadoop/hbase/client/Table.close:()V
     141: goto          219
     144: astore        8
     146: aload         7
     148: aload         8
     150: invokevirtual #46                 // Method java/lang/Throwable.addSuppressed:(Ljava/lang/Throwable;)V
     153: goto          219
     156: aload         6
     158: invokeinterface #44,  1           // InterfaceMethod org/apache/hadoop/hbase/client/Table.close:()V
     163: goto          219
     166: astore        8
     168: aload         8
     170: astore        7
     172: aload         8
     174: athrow
     175: astore        9
     177: aload         6
     179: ifnull        216
     182: aload         7
     184: ifnull        209
     187: aload         6
     189: invokeinterface #44,  1           // InterfaceMethod org/apache/hadoop/hbase/client/Table.close:()V
     194: goto          216
     197: astore        10
     199: aload         7
     201: aload         10
     203: invokevirtual #46                 // Method java/lang/Throwable.addSuppressed:(Ljava/lang/Throwable;)V
     206: goto          216
     209: aload         6
     211: invokeinterface #44,  1           // InterfaceMethod org/apache/hadoop/hbase/client/Table.close:()V
     216: aload         9
     218: athrow
     219: getstatic     #5                  // Field UTIL:Lorg/apache/hadoop/hbase/HBaseTestingUtility;
     222: invokevirtual #47                 // Method org/apache/hadoop/hbase/HBaseTestingUtility.getAdmin:()Lorg/apache/hadoop/hbase/client/Admin;
     225: aload_2
     226: invokeinterface #48,  2           // InterfaceMethod org/apache/hadoop/hbase/client/Admin.disableTable:(Lorg/apache/hadoop/hbase/TableName;)V
     231: aload_1
     232: invokevirtual #49                 // Method org/apache/hadoop/hbase/master/MasterFileSystem.getRootDir:()Lorg/apache/hadoop/fs/Path;
     235: aload_2
     236: invokestatic  #50                 // Method org/apache/hadoop/hbase/util/FSUtils.getTableDir:(Lorg/apache/hadoop/fs/Path;Lorg/apache/hadoop/hbase/TableName;)Lorg/apache/hadoop/fs/Path;
     239: astore        6
     241: aload_1
     242: invokevirtual #51                 // Method org/apache/hadoop/hbase/master/MasterFileSystem.getTempDir:()Lorg/apache/hadoop/fs/Path;
     245: astore        7
     247: aload         7
     249: aload_2
     250: invokestatic  #50                 // Method org/apache/hadoop/hbase/util/FSUtils.getTableDir:(Lorg/apache/hadoop/fs/Path;Lorg/apache/hadoop/hbase/TableName;)Lorg/apache/hadoop/fs/Path;
     253: astore        8
     255: aload_1
     256: invokevirtual #13                 // Method org/apache/hadoop/hbase/master/MasterFileSystem.getFileSystem:()Lorg/apache/hadoop/fs/FileSystem;
     259: astore        9
     261: aload         9
     263: aload         6
     265: aload         8
     267: invokevirtual #52                 // Method org/apache/hadoop/fs/FileSystem.rename:(Lorg/apache/hadoop/fs/Path;Lorg/apache/hadoop/fs/Path;)Z
     270: ifne          276
     273: invokestatic  #53                 // Method org/junit/Assert.fail:()V
     276: aload_1
     277: aload         7
     279: getstatic     #5                  // Field UTIL:Lorg/apache/hadoop/hbase/HBaseTestingUtility;
     282: invokevirtual #54                 // Method org/apache/hadoop/hbase/HBaseTestingUtility.getConfiguration:()Lorg/apache/hadoop/conf/Configuration;
     285: aload         9
     287: invokevirtual #55                 // Method org/apache/hadoop/hbase/master/MasterFileSystem.checkTempDir:(Lorg/apache/hadoop/fs/Path;Lorg/apache/hadoop/conf/Configuration;Lorg/apache/hadoop/fs/FileSystem;)V
     290: aload         9
     292: aload         7
     294: invokevirtual #56                 // Method org/apache/hadoop/fs/FileSystem.exists:(Lorg/apache/hadoop/fs/Path;)Z
     297: invokestatic  #57                 // Method org/junit/Assert.assertTrue:(Z)V
     300: lconst_0
     301: aload         9
     303: aload         7
     305: invokevirtual #58                 // Method org/apache/hadoop/fs/FileSystem.listStatus:(Lorg/apache/hadoop/fs/Path;)[Lorg/apache/hadoop/fs/FileStatus;
     308: arraylength
     309: i2l
     310: invokestatic  #40                 // Method org/junit/Assert.assertEquals:(JJ)V
     313: aload         5
     315: invokeinterface #59,  1           // InterfaceMethod java/util/List.iterator:()Ljava/util/Iterator;
     320: astore        10
     322: aload         10
     324: invokeinterface #60,  1           // InterfaceMethod java/util/Iterator.hasNext:()Z
     329: ifeq          370
     332: aload         10
     334: invokeinterface #61,  1           // InterfaceMethod java/util/Iterator.next:()Ljava/lang/Object;
     339: checkcast     #62                 // class org/apache/hadoop/hbase/regionserver/HRegion
     342: astore        11
     344: getstatic     #5                  // Field UTIL:Lorg/apache/hadoop/hbase/HBaseTestingUtility;
     347: invokevirtual #54                 // Method org/apache/hadoop/hbase/HBaseTestingUtility.getConfiguration:()Lorg/apache/hadoop/conf/Configuration;
     350: aload         11
     352: invokestatic  #63                 // Method org/apache/hadoop/hbase/util/HFileArchiveTestingUtil.getRegionArchiveDir:(Lorg/apache/hadoop/conf/Configuration;Lorg/apache/hadoop/hbase/regionserver/HRegion;)Lorg/apache/hadoop/fs/Path;
     355: astore        12
     357: aload         9
     359: aload         12
     361: invokevirtual #56                 // Method org/apache/hadoop/fs/FileSystem.exists:(Lorg/apache/hadoop/fs/Path;)Z
     364: invokestatic  #57                 // Method org/junit/Assert.assertTrue:(Z)V
     367: goto          322
     370: getstatic     #5                  // Field UTIL:Lorg/apache/hadoop/hbase/HBaseTestingUtility;
     373: aload_2
     374: invokevirtual #64                 // Method org/apache/hadoop/hbase/HBaseTestingUtility.deleteTable:(Lorg/apache/hadoop/hbase/TableName;)V
     377: return
    Exception table:
       from    to  target type
         134   141   144   Class java/lang/Throwable
         114   124   166   Class java/lang/Throwable
         114   124   175   any
         187   194   197   Class java/lang/Throwable
         166   177   175   any

  static {};
    Code:
       0: ldc           #65                 // class org/apache/hadoop/hbase/master/TestMasterFileSystem
       2: invokestatic  #66                 // Method org/apache/hadoop/hbase/HBaseClassTestRule.forClass:(Ljava/lang/Class;)Lorg/apache/hadoop/hbase/HBaseClassTestRule;
       5: putstatic     #67                 // Field CLASS_RULE:Lorg/apache/hadoop/hbase/HBaseClassTestRule;
       8: ldc           #65                 // class org/apache/hadoop/hbase/master/TestMasterFileSystem
      10: invokestatic  #68                 // Method org/slf4j/LoggerFactory.getLogger:(Ljava/lang/Class;)Lorg/slf4j/Logger;
      13: putstatic     #15                 // Field LOG:Lorg/slf4j/Logger;
      16: new           #69                 // class org/apache/hadoop/hbase/HBaseTestingUtility
      19: dup
      20: invokespecial #70                 // Method org/apache/hadoop/hbase/HBaseTestingUtility."<init>":()V
      23: putstatic     #5                  // Field UTIL:Lorg/apache/hadoop/hbase/HBaseTestingUtility;
      26: return
}
