Compiled from "TestNamespaceAuditor.java"
public class org.apache.hadoop.hbase.namespace.TestNamespaceAuditor$CPRegionServerObserver implements org.apache.hadoop.hbase.coprocessor.RegionServerCoprocessor,org.apache.hadoop.hbase.coprocessor.RegionServerObserver {
  public org.apache.hadoop.hbase.namespace.TestNamespaceAuditor$CPRegionServerObserver();
    Code:
       0: aload_0
       1: invokespecial #1                  // Method java/lang/Object."<init>":()V
       4: aload_0
       5: iconst_0
       6: putfield      #2                  // Field shouldFailMerge:Z
       9: aload_0
      10: iconst_0
      11: putfield      #3                  // Field triggered:Z
      14: return

  public void failMerge(boolean);
    Code:
       0: aload_0
       1: iload_1
       2: putfield      #2                  // Field shouldFailMerge:Z
       5: return

  public synchronized void waitUtilTriggered() throws java.lang.InterruptedException;
    Code:
       0: aload_0
       1: getfield      #3                  // Field triggered:Z
       4: ifne          14
       7: aload_0
       8: invokevirtual #4                  // Method java/lang/Object.wait:()V
      11: goto          0
      14: return

  public java.util.Optional<org.apache.hadoop.hbase.coprocessor.RegionServerObserver> getRegionServerObserver();
    Code:
       0: aload_0
       1: invokestatic  #5                  // Method java/util/Optional.of:(Ljava/lang/Object;)Ljava/util/Optional;
       4: areturn
}
