Compiled from "TestHFileBlockIndex.java"
public class org.apache.hadoop.hbase.io.hfile.TestHFileBlockIndex {
  public static final org.apache.hadoop.hbase.HBaseClassTestRule CLASS_RULE;

  static final boolean $assertionsDisabled;

  public static java.util.Collection<java.lang.Object[]> compressionAlgorithms();
    Code:
       0: getstatic     #1                  // Field org/apache/hadoop/hbase/HBaseCommonTestingUtility.COMPRESSION_ALGORITHMS_PARAMETERIZED:Ljava/util/List;
       3: areturn

  public org.apache.hadoop.hbase.io.hfile.TestHFileBlockIndex(org.apache.hadoop.hbase.io.compress.Compression$Algorithm);
    Code:
       0: aload_0
       1: invokespecial #2                  // Method java/lang/Object."<init>":()V
       4: aload_0
       5: aload_1
       6: putfield      #3                  // Field compr:Lorg/apache/hadoop/hbase/io/compress/Compression$Algorithm;
       9: return

  public void setUp() throws java.io.IOException;
    Code:
       0: getstatic     #4                  // Field keys:Ljava/util/List;
       3: invokeinterface #5,  1            // InterfaceMethod java/util/List.clear:()V
       8: aload_0
       9: new           #6                  // class java/util/Random
      12: dup
      13: ldc2_w        #7                  // long 2389757l
      16: invokespecial #9                  // Method java/util/Random."<init>":(J)V
      19: putfield      #10                 // Field rand:Ljava/util/Random;
      22: aload_0
      23: aconst_null
      24: putfield      #11                 // Field firstKeyInFile:[B
      27: aload_0
      28: getstatic     #12                 // Field TEST_UTIL:Lorg/apache/hadoop/hbase/HBaseTestingUtility;
      31: invokevirtual #13                 // Method org/apache/hadoop/hbase/HBaseTestingUtility.getConfiguration:()Lorg/apache/hadoop/conf/Configuration;
      34: putfield      #14                 // Field conf:Lorg/apache/hadoop/conf/Configuration;
      37: aload_0
      38: getfield      #14                 // Field conf:Lorg/apache/hadoop/conf/Configuration;
      41: ldc           #16                 // String hfile.format.version
      43: iconst_3
      44: invokevirtual #17                 // Method org/apache/hadoop/conf/Configuration.setInt:(Ljava/lang/String;I)V
      47: aload_0
      48: getfield      #14                 // Field conf:Lorg/apache/hadoop/conf/Configuration;
      51: invokestatic  #18                 // Method org/apache/hadoop/hbase/fs/HFileSystem.get:(Lorg/apache/hadoop/conf/Configuration;)Lorg/apache/hadoop/fs/FileSystem;
      54: putstatic     #19                 // Field fs:Lorg/apache/hadoop/fs/FileSystem;
      57: return

  public void testBlockIndex() throws java.io.IOException;
    Code:
       0: aload_0
       1: iconst_0
       2: invokespecial #20                 // Method testBlockIndexInternals:(Z)V
       5: aload_0
       6: invokespecial #21                 // Method clear:()V
       9: aload_0
      10: iconst_1
      11: invokespecial #20                 // Method testBlockIndexInternals:(Z)V
      14: return

  public void testSecondaryIndexBinarySearch() throws java.io.IOException;
    Code:
       0: bipush        99
       2: istore_1
       3: iload_1
       4: iconst_2
       5: irem
       6: iconst_1
       7: if_icmpne     14
      10: iconst_1
      11: goto          15
      14: iconst_0
      15: invokestatic  #76                 // Method org/junit/Assert.assertTrue:(Z)V
      18: iload_1
      19: iconst_1
      20: isub
      21: iconst_2
      22: idiv
      23: istore_2
      24: new           #135                // class java/io/ByteArrayOutputStream
      27: dup
      28: invokespecial #136                // Method java/io/ByteArrayOutputStream."<init>":()V
      31: astore_3
      32: new           #137                // class java/io/DataOutputStream
      35: dup
      36: aload_3
      37: invokespecial #138                // Method java/io/DataOutputStream."<init>":(Ljava/io/OutputStream;)V
      40: astore        4
      42: aload         4
      44: iload_2
      45: invokevirtual #139                // Method java/io/DataOutputStream.writeInt:(I)V
      48: iconst_0
      49: istore        5
      51: iconst_0
      52: istore        6
      54: iload_1
      55: newarray       int
      57: astore        7
      59: iconst_0
      60: istore        8
      62: iload         8
      64: iload_1
      65: if_icmpge     348
      68: aload_0
      69: getfield      #10                 // Field rand:Ljava/util/Random;
      72: iload         8
      74: iconst_2
      75: imul
      76: invokestatic  #112                // Method org/apache/hadoop/hbase/io/hfile/RandomKeyValueUtil.randomOrderedKey:(Ljava/util/Random;I)[B
      79: astore        9
      81: new           #111                // class org/apache/hadoop/hbase/KeyValue
      84: dup
      85: aload         9
      87: ldc           #109                // String f
      89: invokestatic  #105                // Method org/apache/hadoop/hbase/util/Bytes.toBytes:(Ljava/lang/String;)[B
      92: ldc           #110                // String q
      94: invokestatic  #105                // Method org/apache/hadoop/hbase/util/Bytes.toBytes:(Ljava/lang/String;)[B
      97: ldc           #140                // String val
      99: invokestatic  #105                // Method org/apache/hadoop/hbase/util/Bytes.toBytes:(Ljava/lang/String;)[B
     102: invokespecial #141                // Method org/apache/hadoop/hbase/KeyValue."<init>":([B[B[B[B)V
     105: astore        10
     107: getstatic     #4                  // Field keys:Ljava/util/List;
     110: aload         10
     112: invokevirtual #116                // Method org/apache/hadoop/hbase/KeyValue.getKey:()[B
     115: invokeinterface #117,  2          // InterfaceMethod java/util/List.add:(Ljava/lang/Object;)Z
     120: pop
     121: new           #24                 // class java/lang/StringBuilder
     124: dup
     125: invokespecial #25                 // Method java/lang/StringBuilder."<init>":()V
     128: ldc           #142                // String Key #
     130: invokevirtual #27                 // Method java/lang/StringBuilder.append:(Ljava/lang/String;)Ljava/lang/StringBuilder;
     133: iload         8
     135: invokevirtual #70                 // Method java/lang/StringBuilder.append:(I)Ljava/lang/StringBuilder;
     138: ldc           #143                // String  (
     140: invokevirtual #27                 // Method java/lang/StringBuilder.append:(Ljava/lang/String;)Ljava/lang/StringBuilder;
     143: aload         9
     145: invokestatic  #83                 // Method org/apache/hadoop/hbase/util/Bytes.toStringBinary:([B)Ljava/lang/String;
     148: invokevirtual #27                 // Method java/lang/StringBuilder.append:(Ljava/lang/String;)Ljava/lang/StringBuilder;
     151: ldc           #144                // String ):
     153: invokevirtual #27                 // Method java/lang/StringBuilder.append:(Ljava/lang/String;)Ljava/lang/StringBuilder;
     156: invokevirtual #30                 // Method java/lang/StringBuilder.toString:()Ljava/lang/String;
     159: astore        11
     161: new           #24                 // class java/lang/StringBuilder
     164: dup
     165: invokespecial #25                 // Method java/lang/StringBuilder."<init>":()V
     168: astore        12
     170: aload         11
     172: invokevirtual #145                // Method java/lang/String.length:()I
     175: aload         12
     177: invokevirtual #146                // Method java/lang/StringBuilder.length:()I
     180: iadd
     181: bipush        70
     183: if_icmpge     197
     186: aload         12
     188: bipush        32
     190: invokevirtual #147                // Method java/lang/StringBuilder.append:(C)Ljava/lang/StringBuilder;
     193: pop
     194: goto          170
     197: new           #24                 // class java/lang/StringBuilder
     200: dup
     201: invokespecial #25                 // Method java/lang/StringBuilder."<init>":()V
     204: aload         11
     206: invokevirtual #27                 // Method java/lang/StringBuilder.append:(Ljava/lang/String;)Ljava/lang/StringBuilder;
     209: aload         12
     211: invokevirtual #28                 // Method java/lang/StringBuilder.append:(Ljava/lang/Object;)Ljava/lang/StringBuilder;
     214: invokevirtual #30                 // Method java/lang/StringBuilder.toString:()Ljava/lang/String;
     217: astore        11
     219: iload         8
     221: iconst_2
     222: irem
     223: iconst_1
     224: if_icmpne     308
     227: aload         4
     229: iload         5
     231: invokevirtual #139                // Method java/io/DataOutputStream.writeInt:(I)V
     234: aload         7
     236: iload         8
     238: iload         5
     240: iastore
     241: getstatic     #37                 // Field LOG:Lorg/slf4j/Logger;
     244: new           #24                 // class java/lang/StringBuilder
     247: dup
     248: invokespecial #25                 // Method java/lang/StringBuilder."<init>":()V
     251: aload         11
     253: invokevirtual #27                 // Method java/lang/StringBuilder.append:(Ljava/lang/String;)Ljava/lang/StringBuilder;
     256: ldc           #148                // String secondary index entry #
     258: invokevirtual #27                 // Method java/lang/StringBuilder.append:(Ljava/lang/String;)Ljava/lang/StringBuilder;
     261: iload         8
     263: iconst_1
     264: isub
     265: iconst_2
     266: idiv
     267: invokevirtual #70                 // Method java/lang/StringBuilder.append:(I)Ljava/lang/StringBuilder;
     270: ldc           #149                // String , offset
     272: invokevirtual #27                 // Method java/lang/StringBuilder.append:(Ljava/lang/String;)Ljava/lang/StringBuilder;
     275: iload         5
     277: invokevirtual #70                 // Method java/lang/StringBuilder.append:(I)Ljava/lang/StringBuilder;
     280: invokevirtual #30                 // Method java/lang/StringBuilder.toString:()Ljava/lang/String;
     283: invokeinterface #71,  2           // InterfaceMethod org/slf4j/Logger.info:(Ljava/lang/String;)V
     288: iload         5
     290: aload         10
     292: invokevirtual #116                // Method org/apache/hadoop/hbase/KeyValue.getKey:()[B
     295: arraylength
     296: bipush        12
     298: iadd
     299: iadd
     300: istore        5
     302: iinc          6, 1
     305: goto          342
     308: aload         7
     310: iload         8
     312: iconst_m1
     313: iastore
     314: getstatic     #37                 // Field LOG:Lorg/slf4j/Logger;
     317: new           #24                 // class java/lang/StringBuilder
     320: dup
     321: invokespecial #25                 // Method java/lang/StringBuilder."<init>":()V
     324: aload         11
     326: invokevirtual #27                 // Method java/lang/StringBuilder.append:(Ljava/lang/String;)Ljava/lang/StringBuilder;
     329: ldc           #151                // String not in the searched array
     331: invokevirtual #27                 // Method java/lang/StringBuilder.append:(Ljava/lang/String;)Ljava/lang/StringBuilder;
     334: invokevirtual #30                 // Method java/lang/StringBuilder.toString:()Ljava/lang/String;
     337: invokeinterface #71,  2           // InterfaceMethod org/slf4j/Logger.info:(Ljava/lang/String;)V
     342: iinc          8, 1
     345: goto          62
     348: iconst_0
     349: istore        8
     351: iload         8
     353: getstatic     #4                  // Field keys:Ljava/util/List;
     356: invokeinterface #69,  1           // InterfaceMethod java/util/List.size:()I
     361: iconst_1
     362: isub
     363: if_icmpge     463
     366: getstatic     #57                 // Field org/apache/hadoop/hbase/CellComparatorImpl.COMPARATOR:Lorg/apache/hadoop/hbase/CellComparatorImpl;
     369: new           #77                 // class org/apache/hadoop/hbase/KeyValue$KeyOnlyKeyValue
     372: dup
     373: getstatic     #4                  // Field keys:Ljava/util/List;
     376: iload         8
     378: invokeinterface #152,  2          // InterfaceMethod java/util/List.get:(I)Ljava/lang/Object;
     383: checkcast     #75                 // class "[B"
     386: iconst_0
     387: getstatic     #4                  // Field keys:Ljava/util/List;
     390: iload         8
     392: invokeinterface #152,  2          // InterfaceMethod java/util/List.get:(I)Ljava/lang/Object;
     397: checkcast     #75                 // class "[B"
     400: arraylength
     401: invokespecial #78                 // Method org/apache/hadoop/hbase/KeyValue$KeyOnlyKeyValue."<init>":([BII)V
     404: new           #77                 // class org/apache/hadoop/hbase/KeyValue$KeyOnlyKeyValue
     407: dup
     408: getstatic     #4                  // Field keys:Ljava/util/List;
     411: iload         8
     413: iconst_1
     414: iadd
     415: invokeinterface #152,  2          // InterfaceMethod java/util/List.get:(I)Ljava/lang/Object;
     420: checkcast     #75                 // class "[B"
     423: iconst_0
     424: getstatic     #4                  // Field keys:Ljava/util/List;
     427: iload         8
     429: iconst_1
     430: iadd
     431: invokeinterface #152,  2          // InterfaceMethod java/util/List.get:(I)Ljava/lang/Object;
     436: checkcast     #75                 // class "[B"
     439: arraylength
     440: invokespecial #78                 // Method org/apache/hadoop/hbase/KeyValue$KeyOnlyKeyValue."<init>":([BII)V
     443: invokevirtual #153                // Method org/apache/hadoop/hbase/CellComparatorImpl.compare:(Lorg/apache/hadoop/hbase/Cell;Lorg/apache/hadoop/hbase/Cell;)I
     446: ifge          453
     449: iconst_1
     450: goto          454
     453: iconst_0
     454: invokestatic  #76                 // Method org/junit/Assert.assertTrue:(Z)V
     457: iinc          8, 1
     460: goto          351
     463: aload         4
     465: iload         5
     467: invokevirtual #139                // Method java/io/DataOutputStream.writeInt:(I)V
     470: iload_2
     471: i2l
     472: iload         6
     474: i2l
     475: invokestatic  #88                 // Method org/junit/Assert.assertEquals:(JJ)V
     478: aload         4
     480: invokevirtual #154                // Method java/io/DataOutputStream.size:()I
     483: istore        8
     485: iconst_4
     486: iload_2
     487: iconst_2
     488: iadd
     489: imul
     490: i2l
     491: iload         8
     493: i2l
     494: invokestatic  #88                 // Method org/junit/Assert.assertEquals:(JJ)V
     497: iconst_1
     498: istore        9
     500: iload         9
     502: iload_1
     503: iconst_1
     504: isub
     505: if_icmpgt     674
     508: aload         4
     510: invokevirtual #154                // Method java/io/DataOutputStream.size:()I
     513: i2l
     514: iload         8
     516: aload         7
     518: iload         9
     520: iaload
     521: iadd
     522: i2l
     523: invokestatic  #88                 // Method org/junit/Assert.assertEquals:(JJ)V
     526: iload         9
     528: invokestatic  #156                // Method getDummyFileOffset:(I)J
     531: lstore        10
     533: iload         9
     535: invokestatic  #157                // Method getDummyOnDiskSize:(I)I
     538: istore        12
     540: getstatic     #37                 // Field LOG:Lorg/slf4j/Logger;
     543: new           #24                 // class java/lang/StringBuilder
     546: dup
     547: invokespecial #25                 // Method java/lang/StringBuilder."<init>":()V
     550: ldc           #158                // String Storing file offset=
     552: invokevirtual #27                 // Method java/lang/StringBuilder.append:(Ljava/lang/String;)Ljava/lang/StringBuilder;
     555: lload         10
     557: invokevirtual #91                 // Method java/lang/StringBuilder.append:(J)Ljava/lang/StringBuilder;
     560: ldc           #159                // String  and onDiskSize=
     562: invokevirtual #27                 // Method java/lang/StringBuilder.append:(Ljava/lang/String;)Ljava/lang/StringBuilder;
     565: iload         12
     567: invokevirtual #70                 // Method java/lang/StringBuilder.append:(I)Ljava/lang/StringBuilder;
     570: ldc           #160                // String  at offset
     572: invokevirtual #27                 // Method java/lang/StringBuilder.append:(Ljava/lang/String;)Ljava/lang/StringBuilder;
     575: aload         4
     577: invokevirtual #154                // Method java/io/DataOutputStream.size:()I
     580: invokevirtual #70                 // Method java/lang/StringBuilder.append:(I)Ljava/lang/StringBuilder;
     583: invokevirtual #30                 // Method java/lang/StringBuilder.toString:()Ljava/lang/String;
     586: invokeinterface #161,  2          // InterfaceMethod org/slf4j/Logger.debug:(Ljava/lang/String;)V
     591: aload         4
     593: lload         10
     595: invokevirtual #162                // Method java/io/DataOutputStream.writeLong:(J)V
     598: aload         4
     600: iload         12
     602: invokevirtual #139                // Method java/io/DataOutputStream.writeInt:(I)V
     605: getstatic     #37                 // Field LOG:Lorg/slf4j/Logger;
     608: new           #24                 // class java/lang/StringBuilder
     611: dup
     612: invokespecial #25                 // Method java/lang/StringBuilder."<init>":()V
     615: ldc           #163                // String Stored key
     617: invokevirtual #27                 // Method java/lang/StringBuilder.append:(Ljava/lang/String;)Ljava/lang/StringBuilder;
     620: iload         9
     622: iconst_1
     623: isub
     624: iconst_2
     625: idiv
     626: invokevirtual #70                 // Method java/lang/StringBuilder.append:(I)Ljava/lang/StringBuilder;
     629: ldc           #160                // String  at offset
     631: invokevirtual #27                 // Method java/lang/StringBuilder.append:(Ljava/lang/String;)Ljava/lang/StringBuilder;
     634: aload         4
     636: invokevirtual #154                // Method java/io/DataOutputStream.size:()I
     639: invokevirtual #70                 // Method java/lang/StringBuilder.append:(I)Ljava/lang/StringBuilder;
     642: invokevirtual #30                 // Method java/lang/StringBuilder.toString:()Ljava/lang/String;
     645: invokeinterface #161,  2          // InterfaceMethod org/slf4j/Logger.debug:(Ljava/lang/String;)V
     650: aload         4
     652: getstatic     #4                  // Field keys:Ljava/util/List;
     655: iload         9
     657: invokeinterface #152,  2          // InterfaceMethod java/util/List.get:(I)Ljava/lang/Object;
     662: checkcast     #75                 // class "[B"
     665: invokevirtual #106                // Method java/io/DataOutputStream.write:([B)V
     668: iinc          9, 2
     671: goto          500
     674: aload         4
     676: iload         5
     678: invokevirtual #139                // Method java/io/DataOutputStream.writeInt:(I)V
     681: aload_3
     682: invokevirtual #164                // Method java/io/ByteArrayOutputStream.toByteArray:()[B
     685: invokestatic  #165                // Method java/nio/ByteBuffer.wrap:([B)Ljava/nio/ByteBuffer;
     688: astore        9
     690: iconst_0
     691: istore        10
     693: iload         10
     695: iload_1
     696: if_icmpge     1002
     699: getstatic     #4                  // Field keys:Ljava/util/List;
     702: iload         10
     704: invokeinterface #152,  2          // InterfaceMethod java/util/List.get:(I)Ljava/lang/Object;
     709: checkcast     #75                 // class "[B"
     712: astore        11
     714: aload         11
     716: arraylength
     717: aload         11
     719: arraylength
     720: iconst_2
     721: idiv
     722: iadd
     723: newarray       byte
     725: astore        12
     727: aload         11
     729: iconst_0
     730: aload         12
     732: aload         11
     734: arraylength
     735: iconst_2
     736: idiv
     737: aload         11
     739: arraylength
     740: invokestatic  #166                // Method java/lang/System.arraycopy:(Ljava/lang/Object;ILjava/lang/Object;II)V
     743: new           #77                 // class org/apache/hadoop/hbase/KeyValue$KeyOnlyKeyValue
     746: dup
     747: aload         12
     749: aload         11
     751: arraylength
     752: iconst_2
     753: idiv
     754: aload         11
     756: arraylength
     757: invokespecial #78                 // Method org/apache/hadoop/hbase/KeyValue$KeyOnlyKeyValue."<init>":([BII)V
     760: astore        13
     762: aload         13
     764: new           #167                // class org/apache/hadoop/hbase/nio/MultiByteBuff
     767: dup
     768: iconst_1
     769: anewarray     #168                // class java/nio/ByteBuffer
     772: dup
     773: iconst_0
     774: aload         9
     776: aastore
     777: invokespecial #169                // Method org/apache/hadoop/hbase/nio/MultiByteBuff."<init>":([Ljava/nio/ByteBuffer;)V
     780: getstatic     #57                 // Field org/apache/hadoop/hbase/CellComparatorImpl.COMPARATOR:Lorg/apache/hadoop/hbase/CellComparatorImpl;
     783: invokestatic  #170                // Method org/apache/hadoop/hbase/io/hfile/HFileBlockIndex$BlockIndexReader.binarySearchNonRootIndex:(Lorg/apache/hadoop/hbase/Cell;Lorg/apache/hadoop/hbase/nio/ByteBuff;Lorg/apache/hadoop/hbase/CellComparator;)I
     786: istore        14
     788: new           #24                 // class java/lang/StringBuilder
     791: dup
     792: invokespecial #25                 // Method java/lang/StringBuilder."<init>":()V
     795: ldc           #171                // String Failed to look up key #
     797: invokevirtual #27                 // Method java/lang/StringBuilder.append:(Ljava/lang/String;)Ljava/lang/StringBuilder;
     800: iload         10
     802: invokevirtual #70                 // Method java/lang/StringBuilder.append:(I)Ljava/lang/StringBuilder;
     805: ldc           #143                // String  (
     807: invokevirtual #27                 // Method java/lang/StringBuilder.append:(Ljava/lang/String;)Ljava/lang/StringBuilder;
     810: aload         11
     812: invokestatic  #83                 // Method org/apache/hadoop/hbase/util/Bytes.toStringBinary:([B)Ljava/lang/String;
     815: invokevirtual #27                 // Method java/lang/StringBuilder.append:(Ljava/lang/String;)Ljava/lang/StringBuilder;
     818: ldc           #92                 // String )
     820: invokevirtual #27                 // Method java/lang/StringBuilder.append:(Ljava/lang/String;)Ljava/lang/StringBuilder;
     823: invokevirtual #30                 // Method java/lang/StringBuilder.toString:()Ljava/lang/String;
     826: astore        15
     828: iload         10
     830: iconst_2
     831: irem
     832: iconst_1
     833: if_icmpne     851
     836: iload         10
     838: iconst_1
     839: isub
     840: iconst_2
     841: idiv
     842: istore        16
     844: iload         10
     846: istore        17
     848: goto          865
     851: iload         10
     853: iconst_2
     854: idiv
     855: iconst_1
     856: isub
     857: istore        16
     859: iload         10
     861: iconst_1
     862: isub
     863: istore        17
     865: aload         15
     867: iload         16
     869: i2l
     870: iload         14
     872: i2l
     873: invokestatic  #172                // Method org/junit/Assert.assertEquals:(Ljava/lang/String;JJ)V
     876: new           #167                // class org/apache/hadoop/hbase/nio/MultiByteBuff
     879: dup
     880: iconst_1
     881: anewarray     #168                // class java/nio/ByteBuffer
     884: dup
     885: iconst_0
     886: aload         9
     888: aastore
     889: invokespecial #169                // Method org/apache/hadoop/hbase/nio/MultiByteBuff."<init>":([Ljava/nio/ByteBuffer;)V
     892: aload         13
     894: getstatic     #57                 // Field org/apache/hadoop/hbase/CellComparatorImpl.COMPARATOR:Lorg/apache/hadoop/hbase/CellComparatorImpl;
     897: invokestatic  #173                // Method org/apache/hadoop/hbase/io/hfile/HFileBlockIndex$BlockIndexReader.locateNonRootIndexEntry:(Lorg/apache/hadoop/hbase/nio/ByteBuff;Lorg/apache/hadoop/hbase/Cell;Lorg/apache/hadoop/hbase/CellComparator;)I
     900: iconst_m1
     901: if_icmpeq     908
     904: iconst_1
     905: goto          909
     908: iconst_0
     909: istore        18
     911: iload         10
     913: ifne          924
     916: iload         18
     918: invokestatic  #174                // Method org/junit/Assert.assertFalse:(Z)V
     921: goto          996
     924: iload         18
     926: invokestatic  #76                 // Method org/junit/Assert.assertTrue:(Z)V
     929: new           #24                 // class java/lang/StringBuilder
     932: dup
     933: invokespecial #25                 // Method java/lang/StringBuilder."<init>":()V
     936: ldc           #175                // String i=
     938: invokevirtual #27                 // Method java/lang/StringBuilder.append:(Ljava/lang/String;)Ljava/lang/StringBuilder;
     941: iload         10
     943: invokevirtual #70                 // Method java/lang/StringBuilder.append:(I)Ljava/lang/StringBuilder;
     946: ldc           #176                // String , position=
     948: invokevirtual #27                 // Method java/lang/StringBuilder.append:(Ljava/lang/String;)Ljava/lang/StringBuilder;
     951: aload         9
     953: invokevirtual #177                // Method java/nio/ByteBuffer.position:()I
     956: invokevirtual #70                 // Method java/lang/StringBuilder.append:(I)Ljava/lang/StringBuilder;
     959: invokevirtual #30                 // Method java/lang/StringBuilder.toString:()Ljava/lang/String;
     962: astore        19
     964: aload         19
     966: iload         17
     968: invokestatic  #156                // Method getDummyFileOffset:(I)J
     971: aload         9
     973: invokevirtual #178                // Method java/nio/ByteBuffer.getLong:()J
     976: invokestatic  #172                // Method org/junit/Assert.assertEquals:(Ljava/lang/String;JJ)V
     979: aload         19
     981: iload         17
     983: invokestatic  #157                // Method getDummyOnDiskSize:(I)I
     986: i2l
     987: aload         9
     989: invokevirtual #179                // Method java/nio/ByteBuffer.getInt:()I
     992: i2l
     993: invokestatic  #172                // Method org/junit/Assert.assertEquals:(Ljava/lang/String;JJ)V
     996: iinc          10, 1
     999: goto          693
    1002: return

  public void testBlockIndexChunk() throws java.io.IOException;
    Code:
       0: new           #180                // class org/apache/hadoop/hbase/io/hfile/HFileBlockIndex$BlockIndexChunk
       3: dup
       4: invokespecial #181                // Method org/apache/hadoop/hbase/io/hfile/HFileBlockIndex$BlockIndexChunk."<init>":()V
       7: astore_1
       8: new           #135                // class java/io/ByteArrayOutputStream
      11: dup
      12: invokespecial #136                // Method java/io/ByteArrayOutputStream."<init>":()V
      15: astore_2
      16: sipush        1000
      19: istore_3
      20: iload_3
      21: newarray       int
      23: astore        4
      25: iconst_0
      26: istore        5
      28: iconst_0
      29: istore        6
      31: iload         6
      33: iload_3
      34: if_icmpge     167
      37: aload_2
      38: invokevirtual #182                // Method java/io/ByteArrayOutputStream.reset:()V
      41: new           #137                // class java/io/DataOutputStream
      44: dup
      45: aload_2
      46: invokespecial #138                // Method java/io/DataOutputStream."<init>":(Ljava/io/OutputStream;)V
      49: astore        7
      51: aload_1
      52: aload         7
      54: invokevirtual #183                // Method org/apache/hadoop/hbase/io/hfile/HFileBlockIndex$BlockIndexChunk.writeNonRoot:(Ljava/io/DataOutput;)V
      57: aload_1
      58: invokevirtual #184                // Method org/apache/hadoop/hbase/io/hfile/HFileBlockIndex$BlockIndexChunk.getNonRootSize:()I
      61: i2l
      62: aload         7
      64: invokevirtual #154                // Method java/io/DataOutputStream.size:()I
      67: i2l
      68: invokestatic  #88                 // Method org/junit/Assert.assertEquals:(JJ)V
      71: aload_2
      72: invokevirtual #182                // Method java/io/ByteArrayOutputStream.reset:()V
      75: new           #137                // class java/io/DataOutputStream
      78: dup
      79: aload_2
      80: invokespecial #138                // Method java/io/DataOutputStream."<init>":(Ljava/io/OutputStream;)V
      83: astore        7
      85: aload_1
      86: aload         7
      88: invokevirtual #185                // Method org/apache/hadoop/hbase/io/hfile/HFileBlockIndex$BlockIndexChunk.writeRoot:(Ljava/io/DataOutput;)V
      91: aload_1
      92: invokevirtual #186                // Method org/apache/hadoop/hbase/io/hfile/HFileBlockIndex$BlockIndexChunk.getRootSize:()I
      95: i2l
      96: aload         7
      98: invokevirtual #154                // Method java/io/DataOutputStream.size:()I
     101: i2l
     102: invokestatic  #88                 // Method org/junit/Assert.assertEquals:(JJ)V
     105: aload_0
     106: getfield      #10                 // Field rand:Ljava/util/Random;
     109: iload         6
     111: invokestatic  #112                // Method org/apache/hadoop/hbase/io/hfile/RandomKeyValueUtil.randomOrderedKey:(Ljava/util/Random;I)[B
     114: astore        8
     116: iload         5
     118: aload_0
     119: getfield      #10                 // Field rand:Ljava/util/Random;
     122: iconst_5
     123: invokevirtual #103                // Method java/util/Random.nextInt:(I)I
     126: iconst_1
     127: iadd
     128: iadd
     129: istore        5
     131: getstatic     #4                  // Field keys:Ljava/util/List;
     134: aload         8
     136: invokeinterface #117,  2          // InterfaceMethod java/util/List.add:(Ljava/lang/Object;)Z
     141: pop
     142: aload_1
     143: aload         8
     145: iload         6
     147: invokestatic  #156                // Method getDummyFileOffset:(I)J
     150: iload         6
     152: invokestatic  #157                // Method getDummyOnDiskSize:(I)I
     155: iload         5
     157: i2l
     158: invokevirtual #187                // Method org/apache/hadoop/hbase/io/hfile/HFileBlockIndex$BlockIndexChunk.add:([BJIJ)V
     161: iinc          6, 1
     164: goto          31
     167: iconst_0
     168: istore        6
     170: iload         6
     172: iload_3
     173: if_icmpge     230
     176: iload         6
     178: ifne          185
     181: iconst_0
     182: goto          192
     185: aload         4
     187: iload         6
     189: iconst_1
     190: isub
     191: iaload
     192: istore        7
     194: iload         7
     196: aload         4
     198: iload         6
     200: iaload
     201: if_icmpge     224
     204: iload         6
     206: i2l
     207: aload_1
     208: iload         7
     210: i2l
     211: invokevirtual #188                // Method org/apache/hadoop/hbase/io/hfile/HFileBlockIndex$BlockIndexChunk.getEntryBySubEntry:(J)I
     214: i2l
     215: invokestatic  #88                 // Method org/junit/Assert.assertEquals:(JJ)V
     218: iinc          7, 1
     221: goto          194
     224: iinc          6, 1
     227: goto          170
     230: return

  public void testHeapSizeForBlockIndex() throws java.io.IOException;
    Code:
       0: ldc           #189                // class org/apache/hadoop/hbase/io/hfile/HFileBlockIndex$BlockIndexReader
       2: astore_1
       3: aload_1
       4: iconst_0
       5: invokestatic  #190                // Method org/apache/hadoop/hbase/util/ClassSize.estimateBase:(Ljava/lang/Class;Z)J
       8: lstore_2
       9: new           #191                // class org/apache/hadoop/hbase/io/hfile/HFileBlockIndex$ByteArrayKeyBlockIndexReader
      12: dup
      13: iconst_1
      14: invokespecial #192                // Method org/apache/hadoop/hbase/io/hfile/HFileBlockIndex$ByteArrayKeyBlockIndexReader."<init>":(I)V
      17: astore        4
      19: aload         4
      21: invokevirtual #193                // Method org/apache/hadoop/hbase/io/hfile/HFileBlockIndex$BlockIndexReader.heapSize:()J
      24: lstore        5
      26: lload_2
      27: iconst_2
      28: getstatic     #194                // Field org/apache/hadoop/hbase/util/ClassSize.ARRAY:I
      31: imul
      32: invokestatic  #195                // Method org/apache/hadoop/hbase/util/ClassSize.align:(I)I
      35: i2l
      36: lsub
      37: lstore_2
      38: lload_2
      39: lload         5
      41: lcmp
      42: ifeq          57
      45: aload_1
      46: iconst_1
      47: invokestatic  #190                // Method org/apache/hadoop/hbase/util/ClassSize.estimateBase:(Ljava/lang/Class;Z)J
      50: lstore_2
      51: lload_2
      52: lload         5
      54: invokestatic  #88                 // Method org/junit/Assert.assertEquals:(JJ)V
      57: return

  public void testMidKeyOnLeafIndexBlockBoundary() throws java.io.IOException;
    Code:
       0: new           #22                 // class org/apache/hadoop/fs/Path
       3: dup
       4: getstatic     #12                 // Field TEST_UTIL:Lorg/apache/hadoop/hbase/HBaseTestingUtility;
       7: invokevirtual #23                 // Method org/apache/hadoop/hbase/HBaseTestingUtility.getDataTestDir:()Lorg/apache/hadoop/fs/Path;
      10: ldc           #196                // String hfile_for_midkey
      12: invokespecial #31                 // Method org/apache/hadoop/fs/Path."<init>":(Lorg/apache/hadoop/fs/Path;Ljava/lang/String;)V
      15: astore_1
      16: sipush        512
      19: istore_2
      20: aload_0
      21: getfield      #14                 // Field conf:Lorg/apache/hadoop/conf/Configuration;
      24: ldc           #197                // String hfile.index.block.max.size
      26: iload_2
      27: invokevirtual #17                 // Method org/apache/hadoop/conf/Configuration.setInt:(Ljava/lang/String;I)V
      30: aload_0
      31: getfield      #14                 // Field conf:Lorg/apache/hadoop/conf/Configuration;
      34: ldc           #199                // String hfile.block.index.cacheonwrite
      36: iconst_1
      37: invokevirtual #200                // Method org/apache/hadoop/conf/Configuration.setBoolean:(Ljava/lang/String;Z)V
      40: new           #198                // class org/apache/hadoop/hbase/io/hfile/CacheConfig
      43: dup
      44: aload_0
      45: getfield      #14                 // Field conf:Lorg/apache/hadoop/conf/Configuration;
      48: aload_0
      49: getfield      #14                 // Field conf:Lorg/apache/hadoop/conf/Configuration;
      52: invokestatic  #201                // Method org/apache/hadoop/hbase/io/hfile/BlockCacheFactory.createBlockCache:(Lorg/apache/hadoop/conf/Configuration;)Lorg/apache/hadoop/hbase/io/hfile/BlockCache;
      55: invokespecial #202                // Method org/apache/hadoop/hbase/io/hfile/CacheConfig."<init>":(Lorg/apache/hadoop/conf/Configuration;Lorg/apache/hadoop/hbase/io/hfile/BlockCache;)V
      58: astore_3
      59: aload_3
      60: invokevirtual #203                // Method org/apache/hadoop/hbase/io/hfile/CacheConfig.getBlockCache:()Ljava/util/Optional;
      63: invokevirtual #204                // Method java/util/Optional.get:()Ljava/lang/Object;
      66: checkcast     #205                // class org/apache/hadoop/hbase/io/hfile/BlockCache
      69: astore        4
      71: aload         4
      73: aload_1
      74: invokevirtual #206                // Method org/apache/hadoop/fs/Path.getName:()Ljava/lang/String;
      77: invokeinterface #207,  2          // InterfaceMethod org/apache/hadoop/hbase/io/hfile/BlockCache.evictBlocksByHfileName:(Ljava/lang/String;)I
      82: pop
      83: new           #44                 // class org/apache/hadoop/hbase/io/hfile/HFileContextBuilder
      86: dup
      87: invokespecial #45                 // Method org/apache/hadoop/hbase/io/hfile/HFileContextBuilder."<init>":()V
      90: sipush        4096
      93: invokevirtual #208                // Method org/apache/hadoop/hbase/io/hfile/HFileContextBuilder.withBlockSize:(I)Lorg/apache/hadoop/hbase/io/hfile/HFileContextBuilder;
      96: getstatic     #209                // Field org/apache/hadoop/hbase/io/compress/Compression$Algorithm.NONE:Lorg/apache/hadoop/hbase/io/compress/Compression$Algorithm;
      99: invokevirtual #50                 // Method org/apache/hadoop/hbase/io/hfile/HFileContextBuilder.withCompression:(Lorg/apache/hadoop/hbase/io/compress/Compression$Algorithm;)Lorg/apache/hadoop/hbase/io/hfile/HFileContextBuilder;
     102: getstatic     #210                // Field org/apache/hadoop/hbase/io/encoding/DataBlockEncoding.NONE:Lorg/apache/hadoop/hbase/io/encoding/DataBlockEncoding;
     105: invokevirtual #211                // Method org/apache/hadoop/hbase/io/hfile/HFileContextBuilder.withDataBlockEncoding:(Lorg/apache/hadoop/hbase/io/encoding/DataBlockEncoding;)Lorg/apache/hadoop/hbase/io/hfile/HFileContextBuilder;
     108: invokevirtual #51                 // Method org/apache/hadoop/hbase/io/hfile/HFileContextBuilder.build:()Lorg/apache/hadoop/hbase/io/hfile/HFileContext;
     111: astore        5
     113: aload_0
     114: getfield      #14                 // Field conf:Lorg/apache/hadoop/conf/Configuration;
     117: aload_3
     118: invokestatic  #212                // Method org/apache/hadoop/hbase/io/hfile/HFile.getWriterFactory:(Lorg/apache/hadoop/conf/Configuration;Lorg/apache/hadoop/hbase/io/hfile/CacheConfig;)Lorg/apache/hadoop/hbase/io/hfile/HFile$WriterFactory;
     121: getstatic     #19                 // Field fs:Lorg/apache/hadoop/fs/FileSystem;
     124: aload_1
     125: invokevirtual #213                // Method org/apache/hadoop/hbase/io/hfile/HFile$WriterFactory.withPath:(Lorg/apache/hadoop/fs/FileSystem;Lorg/apache/hadoop/fs/Path;)Lorg/apache/hadoop/hbase/io/hfile/HFile$WriterFactory;
     128: aload         5
     130: invokevirtual #214                // Method org/apache/hadoop/hbase/io/hfile/HFile$WriterFactory.withFileContext:(Lorg/apache/hadoop/hbase/io/hfile/HFileContext;)Lorg/apache/hadoop/hbase/io/hfile/HFile$WriterFactory;
     133: invokevirtual #215                // Method org/apache/hadoop/hbase/io/hfile/HFile$WriterFactory.create:()Lorg/apache/hadoop/hbase/io/hfile/HFile$Writer;
     136: astore        6
     138: new           #6                  // class java/util/Random
     141: dup
     142: ldc2_w        #216                // long 19231737l
     145: invokespecial #9                  // Method java/util/Random."<init>":(J)V
     148: astore        7
     150: ldc           #109                // String f
     152: invokestatic  #105                // Method org/apache/hadoop/hbase/util/Bytes.toBytes:(Ljava/lang/String;)[B
     155: astore        8
     157: ldc           #110                // String q
     159: invokestatic  #105                // Method org/apache/hadoop/hbase/util/Bytes.toBytes:(Ljava/lang/String;)[B
     162: astore        9
     164: bipush        16
     166: istore        10
     168: iconst_0
     169: istore        11
     171: iload         11
     173: iload         10
     175: if_icmpge     230
     178: aload         7
     180: iload         11
     182: bipush        30
     184: invokestatic  #218                // Method org/apache/hadoop/hbase/io/hfile/RandomKeyValueUtil.randomOrderedFixedLengthKey:(Ljava/util/Random;II)[B
     187: astore        12
     189: new           #111                // class org/apache/hadoop/hbase/KeyValue
     192: dup
     193: aload         12
     195: aload         8
     197: aload         9
     199: invokestatic  #113                // Method org/apache/hadoop/hbase/util/EnvironmentEdgeManager.currentTime:()J
     202: aload         7
     204: sipush        4096
     207: invokestatic  #219                // Method org/apache/hadoop/hbase/io/hfile/RandomKeyValueUtil.randomFixedLengthValue:(Ljava/util/Random;I)[B
     210: invokespecial #220                // Method org/apache/hadoop/hbase/KeyValue."<init>":([B[B[BJ[B)V
     213: astore        13
     215: aload         6
     217: aload         13
     219: invokeinterface #221,  2          // InterfaceMethod org/apache/hadoop/hbase/io/hfile/HFile$Writer.append:(Lorg/apache/hadoop/hbase/Cell;)V
     224: iinc          11, 1
     227: goto          171
     230: aload         6
     232: invokeinterface #222,  1          // InterfaceMethod org/apache/hadoop/hbase/io/hfile/HFile$Writer.close:()V
     237: aload_0
     238: getfield      #14                 // Field conf:Lorg/apache/hadoop/conf/Configuration;
     241: ldc           #199                // String hfile.block.index.cacheonwrite
     243: iconst_0
     244: invokevirtual #200                // Method org/apache/hadoop/conf/Configuration.setBoolean:(Ljava/lang/String;Z)V
     247: getstatic     #19                 // Field fs:Lorg/apache/hadoop/fs/FileSystem;
     250: aload_1
     251: aload_3
     252: iconst_1
     253: aload_0
     254: getfield      #14                 // Field conf:Lorg/apache/hadoop/conf/Configuration;
     257: invokestatic  #223                // Method org/apache/hadoop/hbase/io/hfile/HFile.createReader:(Lorg/apache/hadoop/fs/FileSystem;Lorg/apache/hadoop/fs/Path;Lorg/apache/hadoop/hbase/io/hfile/CacheConfig;ZLorg/apache/hadoop/conf/Configuration;)Lorg/apache/hadoop/hbase/io/hfile/HFile$Reader;
     260: astore        11
     262: iconst_0
     263: istore        12
     265: aload         11
     267: invokeinterface #224,  1          // InterfaceMethod org/apache/hadoop/hbase/io/hfile/HFile$Reader.midKey:()Ljava/util/Optional;
     272: pop
     273: aload         11
     275: invokeinterface #225,  1          // InterfaceMethod org/apache/hadoop/hbase/io/hfile/HFile$Reader.close:()V
     280: goto          310
     283: astore        13
     285: iconst_1
     286: istore        12
     288: aload         11
     290: invokeinterface #225,  1          // InterfaceMethod org/apache/hadoop/hbase/io/hfile/HFile$Reader.close:()V
     295: goto          310
     298: astore        14
     300: aload         11
     302: invokeinterface #225,  1          // InterfaceMethod org/apache/hadoop/hbase/io/hfile/HFile$Reader.close:()V
     307: aload         14
     309: athrow
     310: iload         12
     312: invokestatic  #174                // Method org/junit/Assert.assertFalse:(Z)V
     315: return
    Exception table:
       from    to  target type
         265   273   283   Class java/lang/ArrayIndexOutOfBoundsException
         265   273   298   any
         283   288   298   any
         298   300   298   any

  public void testHFileWriterAndReader() throws java.io.IOException;
    Code:
       0: new           #22                 // class org/apache/hadoop/fs/Path
       3: dup
       4: getstatic     #12                 // Field TEST_UTIL:Lorg/apache/hadoop/hbase/HBaseTestingUtility;
       7: invokevirtual #23                 // Method org/apache/hadoop/hbase/HBaseTestingUtility.getDataTestDir:()Lorg/apache/hadoop/fs/Path;
      10: ldc           #227                // String hfile_for_block_index
      12: invokespecial #31                 // Method org/apache/hadoop/fs/Path."<init>":(Lorg/apache/hadoop/fs/Path;Ljava/lang/String;)V
      15: astore_1
      16: new           #198                // class org/apache/hadoop/hbase/io/hfile/CacheConfig
      19: dup
      20: aload_0
      21: getfield      #14                 // Field conf:Lorg/apache/hadoop/conf/Configuration;
      24: aload_0
      25: getfield      #14                 // Field conf:Lorg/apache/hadoop/conf/Configuration;
      28: invokestatic  #201                // Method org/apache/hadoop/hbase/io/hfile/BlockCacheFactory.createBlockCache:(Lorg/apache/hadoop/conf/Configuration;)Lorg/apache/hadoop/hbase/io/hfile/BlockCache;
      31: invokespecial #202                // Method org/apache/hadoop/hbase/io/hfile/CacheConfig."<init>":(Lorg/apache/hadoop/conf/Configuration;Lorg/apache/hadoop/hbase/io/hfile/BlockCache;)V
      34: astore_2
      35: aload_2
      36: invokevirtual #203                // Method org/apache/hadoop/hbase/io/hfile/CacheConfig.getBlockCache:()Ljava/util/Optional;
      39: invokevirtual #204                // Method java/util/Optional.get:()Ljava/lang/Object;
      42: checkcast     #205                // class org/apache/hadoop/hbase/io/hfile/BlockCache
      45: astore_3
      46: iconst_0
      47: istore        4
      49: iload         4
      51: getstatic     #228                // Field INDEX_CHUNK_SIZES:[I
      54: arraylength
      55: if_icmpge     1029
      58: getstatic     #228                // Field INDEX_CHUNK_SIZES:[I
      61: iload         4
      63: iaload
      64: istore        5
      66: getstatic     #229                // Field EXPECTED_NUM_LEVELS:[I
      69: iload         4
      71: iaload
      72: istore        6
      74: getstatic     #37                 // Field LOG:Lorg/slf4j/Logger;
      77: new           #24                 // class java/lang/StringBuilder
      80: dup
      81: invokespecial #25                 // Method java/lang/StringBuilder."<init>":()V
      84: ldc           #230                // String Index block size:
      86: invokevirtual #27                 // Method java/lang/StringBuilder.append:(Ljava/lang/String;)Ljava/lang/StringBuilder;
      89: iload         5
      91: invokevirtual #70                 // Method java/lang/StringBuilder.append:(I)Ljava/lang/StringBuilder;
      94: ldc           #231                // String , compression:
      96: invokevirtual #27                 // Method java/lang/StringBuilder.append:(Ljava/lang/String;)Ljava/lang/StringBuilder;
      99: aload_0
     100: getfield      #3                  // Field compr:Lorg/apache/hadoop/hbase/io/compress/Compression$Algorithm;
     103: invokevirtual #28                 // Method java/lang/StringBuilder.append:(Ljava/lang/Object;)Ljava/lang/StringBuilder;
     106: invokevirtual #30                 // Method java/lang/StringBuilder.toString:()Ljava/lang/String;
     109: invokeinterface #71,  2           // InterfaceMethod org/slf4j/Logger.info:(Ljava/lang/String;)V
     114: aload_3
     115: aload_1
     116: invokevirtual #206                // Method org/apache/hadoop/fs/Path.getName:()Ljava/lang/String;
     119: invokeinterface #207,  2          // InterfaceMethod org/apache/hadoop/hbase/io/hfile/BlockCache.evictBlocksByHfileName:(Ljava/lang/String;)I
     124: pop
     125: aload_0
     126: getfield      #14                 // Field conf:Lorg/apache/hadoop/conf/Configuration;
     129: ldc           #197                // String hfile.index.block.max.size
     131: iload         5
     133: invokevirtual #17                 // Method org/apache/hadoop/conf/Configuration.setInt:(Ljava/lang/String;I)V
     136: new           #232                // class java/util/HashSet
     139: dup
     140: invokespecial #233                // Method java/util/HashSet."<init>":()V
     143: astore        7
     145: sipush        10000
     148: anewarray     #75                 // class "[B"
     151: astore        8
     153: sipush        10000
     156: anewarray     #75                 // class "[B"
     159: astore        9
     161: new           #44                 // class org/apache/hadoop/hbase/io/hfile/HFileContextBuilder
     164: dup
     165: invokespecial #45                 // Method org/apache/hadoop/hbase/io/hfile/HFileContextBuilder."<init>":()V
     168: sipush        4096
     171: invokevirtual #208                // Method org/apache/hadoop/hbase/io/hfile/HFileContextBuilder.withBlockSize:(I)Lorg/apache/hadoop/hbase/io/hfile/HFileContextBuilder;
     174: aload_0
     175: getfield      #3                  // Field compr:Lorg/apache/hadoop/hbase/io/compress/Compression$Algorithm;
     178: invokevirtual #50                 // Method org/apache/hadoop/hbase/io/hfile/HFileContextBuilder.withCompression:(Lorg/apache/hadoop/hbase/io/compress/Compression$Algorithm;)Lorg/apache/hadoop/hbase/io/hfile/HFileContextBuilder;
     181: invokevirtual #51                 // Method org/apache/hadoop/hbase/io/hfile/HFileContextBuilder.build:()Lorg/apache/hadoop/hbase/io/hfile/HFileContext;
     184: astore        10
     186: aload_0
     187: getfield      #14                 // Field conf:Lorg/apache/hadoop/conf/Configuration;
     190: aload_2
     191: invokestatic  #212                // Method org/apache/hadoop/hbase/io/hfile/HFile.getWriterFactory:(Lorg/apache/hadoop/conf/Configuration;Lorg/apache/hadoop/hbase/io/hfile/CacheConfig;)Lorg/apache/hadoop/hbase/io/hfile/HFile$WriterFactory;
     194: getstatic     #19                 // Field fs:Lorg/apache/hadoop/fs/FileSystem;
     197: aload_1
     198: invokevirtual #213                // Method org/apache/hadoop/hbase/io/hfile/HFile$WriterFactory.withPath:(Lorg/apache/hadoop/fs/FileSystem;Lorg/apache/hadoop/fs/Path;)Lorg/apache/hadoop/hbase/io/hfile/HFile$WriterFactory;
     201: aload         10
     203: invokevirtual #214                // Method org/apache/hadoop/hbase/io/hfile/HFile$WriterFactory.withFileContext:(Lorg/apache/hadoop/hbase/io/hfile/HFileContext;)Lorg/apache/hadoop/hbase/io/hfile/HFile$WriterFactory;
     206: invokevirtual #215                // Method org/apache/hadoop/hbase/io/hfile/HFile$WriterFactory.create:()Lorg/apache/hadoop/hbase/io/hfile/HFile$Writer;
     209: astore        11
     211: new           #6                  // class java/util/Random
     214: dup
     215: ldc2_w        #216                // long 19231737l
     218: invokespecial #9                  // Method java/util/Random."<init>":(J)V
     221: astore        12
     223: ldc           #109                // String f
     225: invokestatic  #105                // Method org/apache/hadoop/hbase/util/Bytes.toBytes:(Ljava/lang/String;)[B
     228: astore        13
     230: ldc           #110                // String q
     232: invokestatic  #105                // Method org/apache/hadoop/hbase/util/Bytes.toBytes:(Ljava/lang/String;)[B
     235: astore        14
     237: iconst_0
     238: istore        15
     240: iload         15
     242: sipush        10000
     245: if_icmpge     372
     248: aload         12
     250: iload         15
     252: invokestatic  #112                // Method org/apache/hadoop/hbase/io/hfile/RandomKeyValueUtil.randomOrderedKey:(Ljava/util/Random;I)[B
     255: astore        16
     257: new           #111                // class org/apache/hadoop/hbase/KeyValue
     260: dup
     261: aload         16
     263: aload         13
     265: aload         14
     267: invokestatic  #113                // Method org/apache/hadoop/hbase/util/EnvironmentEdgeManager.currentTime:()J
     270: aload         12
     272: invokestatic  #234                // Method org/apache/hadoop/hbase/io/hfile/RandomKeyValueUtil.randomValue:(Ljava/util/Random;)[B
     275: invokespecial #220                // Method org/apache/hadoop/hbase/KeyValue."<init>":([B[B[BJ[B)V
     278: astore        17
     280: aload         17
     282: invokevirtual #116                // Method org/apache/hadoop/hbase/KeyValue.getKey:()[B
     285: astore        18
     287: aload         11
     289: aload         17
     291: invokeinterface #221,  2          // InterfaceMethod org/apache/hadoop/hbase/io/hfile/HFile$Writer.append:(Lorg/apache/hadoop/hbase/Cell;)V
     296: aload         8
     298: iload         15
     300: aload         18
     302: aastore
     303: aload         9
     305: iload         15
     307: aload         17
     309: invokestatic  #235                // Method org/apache/hadoop/hbase/CellUtil.cloneValue:(Lorg/apache/hadoop/hbase/Cell;)[B
     312: aastore
     313: aload         7
     315: aload         18
     317: invokestatic  #83                 // Method org/apache/hadoop/hbase/util/Bytes.toStringBinary:([B)Ljava/lang/String;
     320: invokeinterface #236,  2          // InterfaceMethod java/util/Set.add:(Ljava/lang/Object;)Z
     325: pop
     326: iload         15
     328: ifle          366
     331: getstatic     #57                 // Field org/apache/hadoop/hbase/CellComparatorImpl.COMPARATOR:Lorg/apache/hadoop/hbase/CellComparatorImpl;
     334: aload         17
     336: aload         8
     338: iload         15
     340: iconst_1
     341: isub
     342: aaload
     343: iconst_0
     344: aload         8
     346: iload         15
     348: iconst_1
     349: isub
     350: aaload
     351: arraylength
     352: invokestatic  #80                 // Method org/apache/hadoop/hbase/PrivateCellUtil.compare:(Lorg/apache/hadoop/hbase/CellComparator;Lorg/apache/hadoop/hbase/Cell;[BII)I
     355: ifle          362
     358: iconst_1
     359: goto          363
     362: iconst_0
     363: invokestatic  #76                 // Method org/junit/Assert.assertTrue:(Z)V
     366: iinc          15, 1
     369: goto          240
     372: aload         11
     374: invokeinterface #222,  1          // InterfaceMethod org/apache/hadoop/hbase/io/hfile/HFile$Writer.close:()V
     379: getstatic     #19                 // Field fs:Lorg/apache/hadoop/fs/FileSystem;
     382: aload_1
     383: aload_2
     384: iconst_1
     385: aload_0
     386: getfield      #14                 // Field conf:Lorg/apache/hadoop/conf/Configuration;
     389: invokestatic  #223                // Method org/apache/hadoop/hbase/io/hfile/HFile.createReader:(Lorg/apache/hadoop/fs/FileSystem;Lorg/apache/hadoop/fs/Path;Lorg/apache/hadoop/hbase/io/hfile/CacheConfig;ZLorg/apache/hadoop/conf/Configuration;)Lorg/apache/hadoop/hbase/io/hfile/HFile$Reader;
     392: astore        10
     394: iload         6
     396: i2l
     397: aload         10
     399: invokeinterface #237,  1          // InterfaceMethod org/apache/hadoop/hbase/io/hfile/HFile$Reader.getTrailer:()Lorg/apache/hadoop/hbase/io/hfile/FixedFileTrailer;
     404: invokevirtual #238                // Method org/apache/hadoop/hbase/io/hfile/FixedFileTrailer.getNumDataIndexLevels:()I
     407: i2l
     408: invokestatic  #88                 // Method org/junit/Assert.assertEquals:(JJ)V
     411: aload         8
     413: iconst_0
     414: aaload
     415: aload         10
     417: invokeinterface #239,  1          // InterfaceMethod org/apache/hadoop/hbase/io/hfile/HFile$Reader.getFirstKey:()Ljava/util/Optional;
     422: invokevirtual #204                // Method java/util/Optional.get:()Ljava/lang/Object;
     425: checkcast     #111                // class org/apache/hadoop/hbase/KeyValue
     428: invokevirtual #116                // Method org/apache/hadoop/hbase/KeyValue.getKey:()[B
     431: invokestatic  #240                // Method org/apache/hadoop/hbase/util/Bytes.equals:([B[B)Z
     434: invokestatic  #76                 // Method org/junit/Assert.assertTrue:(Z)V
     437: aload         8
     439: sipush        9999
     442: aaload
     443: aload         10
     445: invokeinterface #241,  1          // InterfaceMethod org/apache/hadoop/hbase/io/hfile/HFile$Reader.getLastKey:()Ljava/util/Optional;
     450: invokevirtual #204                // Method java/util/Optional.get:()Ljava/lang/Object;
     453: checkcast     #111                // class org/apache/hadoop/hbase/KeyValue
     456: invokevirtual #116                // Method org/apache/hadoop/hbase/KeyValue.getKey:()[B
     459: invokestatic  #240                // Method org/apache/hadoop/hbase/util/Bytes.equals:([B[B)Z
     462: invokestatic  #76                 // Method org/junit/Assert.assertTrue:(Z)V
     465: getstatic     #37                 // Field LOG:Lorg/slf4j/Logger;
     468: new           #24                 // class java/lang/StringBuilder
     471: dup
     472: invokespecial #25                 // Method java/lang/StringBuilder."<init>":()V
     475: ldc           #242                // String Last key:
     477: invokevirtual #27                 // Method java/lang/StringBuilder.append:(Ljava/lang/String;)Ljava/lang/StringBuilder;
     480: aload         8
     482: sipush        9999
     485: aaload
     486: invokestatic  #83                 // Method org/apache/hadoop/hbase/util/Bytes.toStringBinary:([B)Ljava/lang/String;
     489: invokevirtual #27                 // Method java/lang/StringBuilder.append:(Ljava/lang/String;)Ljava/lang/StringBuilder;
     492: invokevirtual #30                 // Method java/lang/StringBuilder.toString:()Ljava/lang/String;
     495: invokeinterface #71,  2           // InterfaceMethod org/slf4j/Logger.info:(Ljava/lang/String;)V
     500: iconst_2
     501: newarray       boolean
     503: dup
     504: iconst_0
     505: iconst_0
     506: bastore
     507: dup
     508: iconst_1
     509: iconst_1
     510: bastore
     511: astore        11
     513: aload         11
     515: arraylength
     516: istore        12
     518: iconst_0
     519: istore        13
     521: iload         13
     523: iload         12
     525: if_icmpge     730
     528: aload         11
     530: iload         13
     532: baload
     533: istore        14
     535: aload         10
     537: iconst_1
     538: iload         14
     540: invokeinterface #243,  3          // InterfaceMethod org/apache/hadoop/hbase/io/hfile/HFile$Reader.getScanner:(ZZ)Lorg/apache/hadoop/hbase/io/hfile/HFileScanner;
     545: astore        15
     547: iconst_0
     548: istore        16
     550: iload         16
     552: sipush        10000
     555: if_icmpge     631
     558: aload_0
     559: aload         8
     561: aload         15
     563: iload         16
     565: invokespecial #244                // Method checkSeekTo:([[BLorg/apache/hadoop/hbase/io/hfile/HFileScanner;I)V
     568: aload_0
     569: new           #24                 // class java/lang/StringBuilder
     572: dup
     573: invokespecial #25                 // Method java/lang/StringBuilder."<init>":()V
     576: ldc           #175                // String i=
     578: invokevirtual #27                 // Method java/lang/StringBuilder.append:(Ljava/lang/String;)Ljava/lang/StringBuilder;
     581: iload         16
     583: invokevirtual #70                 // Method java/lang/StringBuilder.append:(I)Ljava/lang/StringBuilder;
     586: invokevirtual #30                 // Method java/lang/StringBuilder.toString:()Ljava/lang/String;
     589: aload         8
     591: iload         16
     593: aaload
     594: aload         9
     596: iload         16
     598: aaload
     599: aload         15
     601: invokeinterface #245,  1          // InterfaceMethod org/apache/hadoop/hbase/io/hfile/HFileScanner.getKey:()Lorg/apache/hadoop/hbase/Cell;
     606: checkcast     #111                // class org/apache/hadoop/hbase/KeyValue
     609: invokevirtual #116                // Method org/apache/hadoop/hbase/KeyValue.getKey:()[B
     612: invokestatic  #165                // Method java/nio/ByteBuffer.wrap:([B)Ljava/nio/ByteBuffer;
     615: aload         15
     617: invokeinterface #246,  1          // InterfaceMethod org/apache/hadoop/hbase/io/hfile/HFileScanner.getValue:()Ljava/nio/ByteBuffer;
     622: invokespecial #247                // Method checkKeyValue:(Ljava/lang/String;[B[BLjava/nio/ByteBuffer;Ljava/nio/ByteBuffer;)V
     625: iinc          16, 1
     628: goto          550
     631: aload         15
     633: invokeinterface #248,  1          // InterfaceMethod org/apache/hadoop/hbase/io/hfile/HFileScanner.seekTo:()Z
     638: invokestatic  #76                 // Method org/junit/Assert.assertTrue:(Z)V
     641: sipush        9999
     644: istore        16
     646: iload         16
     648: iflt          724
     651: aload_0
     652: aload         8
     654: aload         15
     656: iload         16
     658: invokespecial #244                // Method checkSeekTo:([[BLorg/apache/hadoop/hbase/io/hfile/HFileScanner;I)V
     661: aload_0
     662: new           #24                 // class java/lang/StringBuilder
     665: dup
     666: invokespecial #25                 // Method java/lang/StringBuilder."<init>":()V
     669: ldc           #175                // String i=
     671: invokevirtual #27                 // Method java/lang/StringBuilder.append:(Ljava/lang/String;)Ljava/lang/StringBuilder;
     674: iload         16
     676: invokevirtual #70                 // Method java/lang/StringBuilder.append:(I)Ljava/lang/StringBuilder;
     679: invokevirtual #30                 // Method java/lang/StringBuilder.toString:()Ljava/lang/String;
     682: aload         8
     684: iload         16
     686: aaload
     687: aload         9
     689: iload         16
     691: aaload
     692: aload         15
     694: invokeinterface #245,  1          // InterfaceMethod org/apache/hadoop/hbase/io/hfile/HFileScanner.getKey:()Lorg/apache/hadoop/hbase/Cell;
     699: checkcast     #111                // class org/apache/hadoop/hbase/KeyValue
     702: invokevirtual #116                // Method org/apache/hadoop/hbase/KeyValue.getKey:()[B
     705: invokestatic  #165                // Method java/nio/ByteBuffer.wrap:([B)Ljava/nio/ByteBuffer;
     708: aload         15
     710: invokeinterface #246,  1          // InterfaceMethod org/apache/hadoop/hbase/io/hfile/HFileScanner.getValue:()Ljava/nio/ByteBuffer;
     715: invokespecial #247                // Method checkKeyValue:(Ljava/lang/String;[B[BLjava/nio/ByteBuffer;Ljava/nio/ByteBuffer;)V
     718: iinc          16, -1
     721: goto          646
     724: iinc          13, 1
     727: goto          521
     730: aload         10
     732: astore        11
     734: aload         11
     736: invokeinterface #249,  1          // InterfaceMethod org/apache/hadoop/hbase/io/hfile/HFile$Reader.getUncachedBlockReader:()Lorg/apache/hadoop/hbase/io/hfile/HFileBlock$FSReader;
     741: astore        12
     743: aload         12
     745: lconst_0
     746: aload         10
     748: invokeinterface #237,  1          // InterfaceMethod org/apache/hadoop/hbase/io/hfile/HFile$Reader.getTrailer:()Lorg/apache/hadoop/hbase/io/hfile/FixedFileTrailer;
     753: invokevirtual #250                // Method org/apache/hadoop/hbase/io/hfile/FixedFileTrailer.getLoadOnOpenDataOffset:()J
     756: invokeinterface #61,  5           // InterfaceMethod org/apache/hadoop/hbase/io/hfile/HFileBlock$FSReader.blockRange:(JJ)Lorg/apache/hadoop/hbase/io/hfile/HFileBlock$BlockIterator;
     761: astore        13
     763: new           #251                // class java/util/ArrayList
     766: dup
     767: invokespecial #252                // Method java/util/ArrayList."<init>":()V
     770: astore        15
     772: aload         13
     774: invokeinterface #253,  1          // InterfaceMethod org/apache/hadoop/hbase/io/hfile/HFileBlock$BlockIterator.nextBlock:()Lorg/apache/hadoop/hbase/io/hfile/HFileBlock;
     779: dup
     780: astore        14
     782: ifnull        955
     785: aload         14
     787: invokevirtual #254                // Method org/apache/hadoop/hbase/io/hfile/HFileBlock.getBlockType:()Lorg/apache/hadoop/hbase/io/hfile/BlockType;
     790: getstatic     #255                // Field org/apache/hadoop/hbase/io/hfile/BlockType.LEAF_INDEX:Lorg/apache/hadoop/hbase/io/hfile/BlockType;
     793: if_acmpeq     797
     796: return
     797: aload         14
     799: invokevirtual #256                // Method org/apache/hadoop/hbase/io/hfile/HFileBlock.getBufferReadOnly:()Lorg/apache/hadoop/hbase/nio/ByteBuff;
     802: astore        16
     804: aload         16
     806: iconst_0
     807: invokevirtual #257                // Method org/apache/hadoop/hbase/nio/ByteBuff.getIntAfterPosition:(I)I
     810: istore        17
     812: iconst_4
     813: iload         17
     815: iconst_2
     816: iadd
     817: imul
     818: istore        18
     820: iconst_0
     821: istore        19
     823: iload         19
     825: iload         17
     827: if_icmpge     952
     830: aload         16
     832: iconst_4
     833: iload         19
     835: iconst_1
     836: iadd
     837: imul
     838: invokevirtual #257                // Method org/apache/hadoop/hbase/nio/ByteBuff.getIntAfterPosition:(I)I
     841: istore        20
     843: aload         16
     845: iconst_4
     846: iload         19
     848: iconst_2
     849: iadd
     850: imul
     851: invokevirtual #257                // Method org/apache/hadoop/hbase/nio/ByteBuff.getIntAfterPosition:(I)I
     854: istore        21
     856: iload         21
     858: iload         20
     860: isub
     861: istore        22
     863: aload         16
     865: invokevirtual #258                // Method org/apache/hadoop/hbase/nio/ByteBuff.arrayOffset:()I
     868: iload         18
     870: iadd
     871: iload         20
     873: iadd
     874: bipush        12
     876: iadd
     877: istore        23
     879: aload         16
     881: invokevirtual #259                // Method org/apache/hadoop/hbase/nio/ByteBuff.array:()[B
     884: iload         23
     886: iload         23
     888: iload         22
     890: iadd
     891: invokestatic  #260                // Method java/util/Arrays.copyOfRange:([BII)[B
     894: astore        24
     896: aload         24
     898: invokestatic  #261                // Method org/apache/hadoop/hbase/util/Bytes.toString:([B)Ljava/lang/String;
     901: astore        25
     903: aload         15
     905: aload         24
     907: invokeinterface #117,  2          // InterfaceMethod java/util/List.add:(Ljava/lang/Object;)Z
     912: pop
     913: new           #24                 // class java/lang/StringBuilder
     916: dup
     917: invokespecial #25                 // Method java/lang/StringBuilder."<init>":()V
     920: ldc_w         #262                // String Invalid block key from leaf-level block:
     923: invokevirtual #27                 // Method java/lang/StringBuilder.append:(Ljava/lang/String;)Ljava/lang/StringBuilder;
     926: aload         25
     928: invokevirtual #27                 // Method java/lang/StringBuilder.append:(Ljava/lang/String;)Ljava/lang/StringBuilder;
     931: invokevirtual #30                 // Method java/lang/StringBuilder.toString:()Ljava/lang/String;
     934: aload         7
     936: aload         25
     938: invokeinterface #263,  2          // InterfaceMethod java/util/Set.contains:(Ljava/lang/Object;)Z
     943: invokestatic  #85                 // Method org/junit/Assert.assertTrue:(Ljava/lang/String;Z)V
     946: iinc          19, 1
     949: goto          823
     952: goto          772
     955: aload         15
     957: aload         15
     959: invokeinterface #69,  1           // InterfaceMethod java/util/List.size:()I
     964: iconst_1
     965: isub
     966: iconst_2
     967: idiv
     968: invokeinterface #152,  2          // InterfaceMethod java/util/List.get:(I)Ljava/lang/Object;
     973: checkcast     #75                 // class "[B"
     976: invokestatic  #83                 // Method org/apache/hadoop/hbase/util/Bytes.toStringBinary:([B)Ljava/lang/String;
     979: aload         10
     981: invokeinterface #224,  1          // InterfaceMethod org/apache/hadoop/hbase/io/hfile/HFile$Reader.midKey:()Ljava/util/Optional;
     986: invokestatic  #264                // Method org/junit/Assert.assertEquals:(Ljava/lang/Object;Ljava/lang/Object;)V
     989: getstatic     #265                // Field UNCOMPRESSED_INDEX_SIZES:[I
     992: iload         4
     994: iaload
     995: i2l
     996: aload         10
     998: invokeinterface #237,  1          // InterfaceMethod org/apache/hadoop/hbase/io/hfile/HFile$Reader.getTrailer:()Lorg/apache/hadoop/hbase/io/hfile/FixedFileTrailer;
    1003: invokevirtual #266                // Method org/apache/hadoop/hbase/io/hfile/FixedFileTrailer.getUncompressedDataIndexSize:()J
    1006: invokestatic  #88                 // Method org/junit/Assert.assertEquals:(JJ)V
    1009: aload         10
    1011: invokeinterface #225,  1          // InterfaceMethod org/apache/hadoop/hbase/io/hfile/HFile$Reader.close:()V
    1016: aload         11
    1018: invokeinterface #225,  1          // InterfaceMethod org/apache/hadoop/hbase/io/hfile/HFile$Reader.close:()V
    1023: iinc          4, 1
    1026: goto          49
    1029: return

  public void testIntermediateLevelIndicesWithLargeKeys() throws java.io.IOException;
    Code:
       0: aload_0
       1: bipush        16
       3: invokevirtual #282                // Method testIntermediateLevelIndicesWithLargeKeys:(I)V
       6: return

  public void testIntermediateLevelIndicesWithLargeKeysWithMinNumEntries() throws java.io.IOException;
    Code:
       0: aload_0
       1: iconst_2
       2: invokevirtual #282                // Method testIntermediateLevelIndicesWithLargeKeys:(I)V
       5: return

  public void testIntermediateLevelIndicesWithLargeKeys(int) throws java.io.IOException;
    Code:
       0: new           #22                 // class org/apache/hadoop/fs/Path
       3: dup
       4: getstatic     #12                 // Field TEST_UTIL:Lorg/apache/hadoop/hbase/HBaseTestingUtility;
       7: invokevirtual #23                 // Method org/apache/hadoop/hbase/HBaseTestingUtility.getDataTestDir:()Lorg/apache/hadoop/fs/Path;
      10: ldc_w         #283                // String testIntermediateLevelIndicesWithLargeKeys.hfile
      13: invokespecial #31                 // Method org/apache/hadoop/fs/Path."<init>":(Lorg/apache/hadoop/fs/Path;Ljava/lang/String;)V
      16: astore_2
      17: sipush        1024
      20: istore_3
      21: aload_0
      22: getfield      #14                 // Field conf:Lorg/apache/hadoop/conf/Configuration;
      25: invokestatic  #284                // Method org/apache/hadoop/fs/FileSystem.get:(Lorg/apache/hadoop/conf/Configuration;)Lorg/apache/hadoop/fs/FileSystem;
      28: astore        4
      30: new           #198                // class org/apache/hadoop/hbase/io/hfile/CacheConfig
      33: dup
      34: aload_0
      35: getfield      #14                 // Field conf:Lorg/apache/hadoop/conf/Configuration;
      38: invokespecial #285                // Method org/apache/hadoop/hbase/io/hfile/CacheConfig."<init>":(Lorg/apache/hadoop/conf/Configuration;)V
      41: astore        5
      43: aload_0
      44: getfield      #14                 // Field conf:Lorg/apache/hadoop/conf/Configuration;
      47: ldc           #197                // String hfile.index.block.max.size
      49: iload_3
      50: invokevirtual #17                 // Method org/apache/hadoop/conf/Configuration.setInt:(Ljava/lang/String;I)V
      53: aload_0
      54: getfield      #14                 // Field conf:Lorg/apache/hadoop/conf/Configuration;
      57: ldc_w         #286                // String hfile.index.block.min.entries
      60: iload_1
      61: invokevirtual #17                 // Method org/apache/hadoop/conf/Configuration.setInt:(Ljava/lang/String;I)V
      64: new           #44                 // class org/apache/hadoop/hbase/io/hfile/HFileContextBuilder
      67: dup
      68: invokespecial #45                 // Method org/apache/hadoop/hbase/io/hfile/HFileContextBuilder."<init>":()V
      71: bipush        16
      73: invokevirtual #208                // Method org/apache/hadoop/hbase/io/hfile/HFileContextBuilder.withBlockSize:(I)Lorg/apache/hadoop/hbase/io/hfile/HFileContextBuilder;
      76: invokevirtual #51                 // Method org/apache/hadoop/hbase/io/hfile/HFileContextBuilder.build:()Lorg/apache/hadoop/hbase/io/hfile/HFileContext;
      79: astore        6
      81: new           #287                // class org/apache/hadoop/hbase/io/hfile/HFile$WriterFactory
      84: dup
      85: aload_0
      86: getfield      #14                 // Field conf:Lorg/apache/hadoop/conf/Configuration;
      89: aload         5
      91: invokespecial #288                // Method org/apache/hadoop/hbase/io/hfile/HFile$WriterFactory."<init>":(Lorg/apache/hadoop/conf/Configuration;Lorg/apache/hadoop/hbase/io/hfile/CacheConfig;)V
      94: aload         6
      96: invokevirtual #214                // Method org/apache/hadoop/hbase/io/hfile/HFile$WriterFactory.withFileContext:(Lorg/apache/hadoop/hbase/io/hfile/HFileContext;)Lorg/apache/hadoop/hbase/io/hfile/HFile$WriterFactory;
      99: aload         4
     101: aload_2
     102: invokevirtual #213                // Method org/apache/hadoop/hbase/io/hfile/HFile$WriterFactory.withPath:(Lorg/apache/hadoop/fs/FileSystem;Lorg/apache/hadoop/fs/Path;)Lorg/apache/hadoop/hbase/io/hfile/HFile$WriterFactory;
     105: invokevirtual #215                // Method org/apache/hadoop/hbase/io/hfile/HFile$WriterFactory.create:()Lorg/apache/hadoop/hbase/io/hfile/HFile$Writer;
     108: astore        7
     110: new           #251                // class java/util/ArrayList
     113: dup
     114: invokespecial #252                // Method java/util/ArrayList."<init>":()V
     117: astore        8
     119: iconst_0
     120: istore        9
     122: iload         9
     124: bipush        100
     126: if_icmpge     189
     129: iload_3
     130: iconst_1
     131: iadd
     132: newarray       byte
     134: astore        10
     136: iload         9
     138: invokestatic  #289                // Method org/apache/hadoop/hbase/util/Bytes.toBytes:(I)[B
     141: astore        11
     143: aload         11
     145: iconst_0
     146: aload         10
     148: aload         10
     150: arraylength
     151: aload         11
     153: arraylength
     154: isub
     155: aload         11
     157: arraylength
     158: invokestatic  #166                // Method java/lang/System.arraycopy:(Ljava/lang/Object;ILjava/lang/Object;II)V
     161: aload         8
     163: aload         10
     165: invokeinterface #117,  2          // InterfaceMethod java/util/List.add:(Ljava/lang/Object;)Z
     170: pop
     171: aload         7
     173: aload         10
     175: invokestatic  #290                // Method org/apache/hadoop/hbase/CellUtil.createCell:([B)Lorg/apache/hadoop/hbase/Cell;
     178: invokeinterface #221,  2          // InterfaceMethod org/apache/hadoop/hbase/io/hfile/HFile$Writer.append:(Lorg/apache/hadoop/hbase/Cell;)V
     183: iinc          9, 1
     186: goto          122
     189: aload         7
     191: invokeinterface #222,  1          // InterfaceMethod org/apache/hadoop/hbase/io/hfile/HFile$Writer.close:()V
     196: aload         4
     198: aload_2
     199: aload         5
     201: iconst_1
     202: aload_0
     203: getfield      #14                 // Field conf:Lorg/apache/hadoop/conf/Configuration;
     206: invokestatic  #223                // Method org/apache/hadoop/hbase/io/hfile/HFile.createReader:(Lorg/apache/hadoop/fs/FileSystem;Lorg/apache/hadoop/fs/Path;Lorg/apache/hadoop/hbase/io/hfile/CacheConfig;ZLorg/apache/hadoop/conf/Configuration;)Lorg/apache/hadoop/hbase/io/hfile/HFile$Reader;
     209: astore        9
     211: aload         9
     213: iconst_1
     214: iconst_1
     215: invokeinterface #243,  3          // InterfaceMethod org/apache/hadoop/hbase/io/hfile/HFile$Reader.getScanner:(ZZ)Lorg/apache/hadoop/hbase/io/hfile/HFileScanner;
     220: astore        10
     222: iconst_0
     223: istore        11
     225: iload         11
     227: aload         8
     229: invokeinterface #69,  1           // InterfaceMethod java/util/List.size:()I
     234: if_icmpge     266
     237: aload         10
     239: aload         8
     241: iload         11
     243: invokeinterface #152,  2          // InterfaceMethod java/util/List.get:(I)Ljava/lang/Object;
     248: checkcast     #75                 // class "[B"
     251: invokestatic  #290                // Method org/apache/hadoop/hbase/CellUtil.createCell:([B)Lorg/apache/hadoop/hbase/Cell;
     254: invokeinterface #269,  2          // InterfaceMethod org/apache/hadoop/hbase/io/hfile/HFileScanner.seekTo:(Lorg/apache/hadoop/hbase/Cell;)I
     259: pop
     260: iinc          11, 1
     263: goto          225
     266: aload         9
     268: invokeinterface #225,  1          // InterfaceMethod org/apache/hadoop/hbase/io/hfile/HFile$Reader.close:()V
     273: return

  static {};
    Code:
       0: ldc           #47                 // class org/apache/hadoop/hbase/io/hfile/TestHFileBlockIndex
       2: invokevirtual #291                // Method java/lang/Class.desiredAssertionStatus:()Z
       5: ifne          12
       8: iconst_1
       9: goto          13
      12: iconst_0
      13: putstatic     #292                // Field $assertionsDisabled:Z
      16: ldc           #47                 // class org/apache/hadoop/hbase/io/hfile/TestHFileBlockIndex
      18: invokestatic  #293                // Method org/apache/hadoop/hbase/HBaseClassTestRule.forClass:(Ljava/lang/Class;)Lorg/apache/hadoop/hbase/HBaseClassTestRule;
      21: putstatic     #294                // Field CLASS_RULE:Lorg/apache/hadoop/hbase/HBaseClassTestRule;
      24: ldc           #47                 // class org/apache/hadoop/hbase/io/hfile/TestHFileBlockIndex
      26: invokestatic  #295                // Method org/slf4j/LoggerFactory.getLogger:(Ljava/lang/Class;)Lorg/slf4j/Logger;
      29: putstatic     #37                 // Field LOG:Lorg/slf4j/Logger;
      32: new           #296                // class org/apache/hadoop/hbase/HBaseTestingUtility
      35: dup
      36: invokespecial #297                // Method org/apache/hadoop/hbase/HBaseTestingUtility."<init>":()V
      39: putstatic     #12                 // Field TEST_UTIL:Lorg/apache/hadoop/hbase/HBaseTestingUtility;
      42: new           #251                // class java/util/ArrayList
      45: dup
      46: invokespecial #252                // Method java/util/ArrayList."<init>":()V
      49: putstatic     #4                  // Field keys:Ljava/util/List;
      52: iconst_3
      53: newarray       int
      55: dup
      56: iconst_0
      57: sipush        4096
      60: iastore
      61: dup
      62: iconst_1
      63: sipush        512
      66: iastore
      67: dup
      68: iconst_2
      69: sipush        384
      72: iastore
      73: putstatic     #228                // Field INDEX_CHUNK_SIZES:[I
      76: iconst_3
      77: newarray       int
      79: dup
      80: iconst_0
      81: iconst_2
      82: iastore
      83: dup
      84: iconst_1
      85: iconst_3
      86: iastore
      87: dup
      88: iconst_2
      89: iconst_4
      90: iastore
      91: putstatic     #229                // Field EXPECTED_NUM_LEVELS:[I
      94: iconst_3
      95: newarray       int
      97: dup
      98: iconst_0
      99: sipush        19187
     102: iastore
     103: dup
     104: iconst_1
     105: sipush        21813
     108: iastore
     109: dup
     110: iconst_2
     111: sipush        23086
     114: iastore
     115: putstatic     #265                // Field UNCOMPRESSED_INDEX_SIZES:[I
     118: getstatic     #292                // Field $assertionsDisabled:Z
     121: ifne          143
     124: getstatic     #228                // Field INDEX_CHUNK_SIZES:[I
     127: arraylength
     128: getstatic     #229                // Field EXPECTED_NUM_LEVELS:[I
     131: arraylength
     132: if_icmpeq     143
     135: new           #298                // class java/lang/AssertionError
     138: dup
     139: invokespecial #299                // Method java/lang/AssertionError."<init>":()V
     142: athrow
     143: getstatic     #292                // Field $assertionsDisabled:Z
     146: ifne          168
     149: getstatic     #228                // Field INDEX_CHUNK_SIZES:[I
     152: arraylength
     153: getstatic     #265                // Field UNCOMPRESSED_INDEX_SIZES:[I
     156: arraylength
     157: if_icmpeq     168
     160: new           #298                // class java/lang/AssertionError
     163: dup
     164: invokespecial #299                // Method java/lang/AssertionError."<init>":()V
     167: athrow
     168: return
}
