Compiled from "TestDataBlockEncoding.java"
public class org.apache.hadoop.hbase.io.encoding.TestDataBlockEncoding {
  public static final org.apache.hadoop.hbase.HBaseClassTestRule CLASS_RULE;

  public org.apache.hadoop.hbase.io.encoding.TestDataBlockEncoding();
    Code:
       0: aload_0
       1: invokespecial #1                  // Method java/lang/Object."<init>":()V
       4: return

  public void testGetDataBlockEncoder() throws java.lang.Exception;
    Code:
       0: invokestatic  #2                  // Method org/apache/hadoop/hbase/io/encoding/DataBlockEncoding.values:()[Lorg/apache/hadoop/hbase/io/encoding/DataBlockEncoding;
       3: astore_1
       4: aload_1
       5: arraylength
       6: istore_2
       7: iconst_0
       8: istore_3
       9: iload_3
      10: iload_2
      11: if_icmpge     56
      14: aload_1
      15: iload_3
      16: aaload
      17: astore        4
      19: aload         4
      21: invokevirtual #3                  // Method org/apache/hadoop/hbase/io/encoding/DataBlockEncoding.getId:()S
      24: invokestatic  #4                  // Method org/apache/hadoop/hbase/io/encoding/DataBlockEncoding.getDataBlockEncoderById:(S)Lorg/apache/hadoop/hbase/io/encoding/DataBlockEncoder;
      27: astore        5
      29: aload         4
      31: invokevirtual #3                  // Method org/apache/hadoop/hbase/io/encoding/DataBlockEncoding.getId:()S
      34: ifeq          50
      37: aload         5
      39: aload         4
      41: invokevirtual #3                  // Method org/apache/hadoop/hbase/io/encoding/DataBlockEncoding.getId:()S
      44: invokestatic  #5                  // Method org/apache/hadoop/hbase/io/encoding/DataBlockEncoding.isCorrectEncoder:(Lorg/apache/hadoop/hbase/io/encoding/DataBlockEncoder;S)Z
      47: invokestatic  #6                  // Method org/junit/Assert.assertTrue:(Z)V
      50: iinc          3, 1
      53: goto          9
      56: iconst_m1
      57: invokestatic  #4                  // Method org/apache/hadoop/hbase/io/encoding/DataBlockEncoding.getDataBlockEncoderById:(S)Lorg/apache/hadoop/hbase/io/encoding/DataBlockEncoder;
      60: pop
      61: ldc           #7                  // String Illegal encoderId, should get IllegalArgumentException.
      63: invokestatic  #8                  // Method org/junit/Assert.fail:(Ljava/lang/String;)V
      66: goto          70
      69: astore_1
      70: bipush        127
      72: invokestatic  #4                  // Method org/apache/hadoop/hbase/io/encoding/DataBlockEncoding.getDataBlockEncoderById:(S)Lorg/apache/hadoop/hbase/io/encoding/DataBlockEncoder;
      75: pop
      76: ldc           #7                  // String Illegal encoderId, should get IllegalArgumentException.
      78: invokestatic  #8                  // Method org/junit/Assert.fail:(Ljava/lang/String;)V
      81: goto          85
      84: astore_1
      85: return
    Exception table:
       from    to  target type
          56    66    69   Class java/lang/IllegalArgumentException
          70    81    84   Class java/lang/IllegalArgumentException

  static {};
    Code:
       0: ldc           #11                 // class org/apache/hadoop/hbase/io/encoding/TestDataBlockEncoding
       2: invokestatic  #12                 // Method org/apache/hadoop/hbase/HBaseClassTestRule.forClass:(Ljava/lang/Class;)Lorg/apache/hadoop/hbase/HBaseClassTestRule;
       5: putstatic     #13                 // Field CLASS_RULE:Lorg/apache/hadoop/hbase/HBaseClassTestRule;
       8: return
}
