Compiled from "TestSpaceQuotasWithSnapshots.java"
class org.apache.hadoop.hbase.quotas.TestSpaceQuotasWithSnapshots$14 implements org.apache.hadoop.hbase.Waiter$Predicate<java.lang.Exception> {
  final java.util.concurrent.atomic.AtomicLong val$lastValue;

  final org.apache.hadoop.hbase.client.Connection val$conn;

  final org.apache.hadoop.hbase.TableName val$tn;

  final java.util.concurrent.atomic.AtomicInteger val$counter;

  final org.apache.hadoop.hbase.quotas.TestSpaceQuotasWithSnapshots this$0;

  org.apache.hadoop.hbase.quotas.TestSpaceQuotasWithSnapshots$14(org.apache.hadoop.hbase.quotas.TestSpaceQuotasWithSnapshots, java.util.concurrent.atomic.AtomicLong, org.apache.hadoop.hbase.client.Connection, org.apache.hadoop.hbase.TableName, java.util.concurrent.atomic.AtomicInteger);
    Code:
       0: aload_0
       1: aload_1
       2: putfield      #1                  // Field this$0:Lorg/apache/hadoop/hbase/quotas/TestSpaceQuotasWithSnapshots;
       5: aload_0
       6: aload_2
       7: putfield      #2                  // Field val$lastValue:Ljava/util/concurrent/atomic/AtomicLong;
      10: aload_0
      11: aload_3
      12: putfield      #3                  // Field val$conn:Lorg/apache/hadoop/hbase/client/Connection;
      15: aload_0
      16: aload         4
      18: putfield      #4                  // Field val$tn:Lorg/apache/hadoop/hbase/TableName;
      21: aload_0
      22: aload         5
      24: putfield      #5                  // Field val$counter:Ljava/util/concurrent/atomic/AtomicInteger;
      27: aload_0
      28: invokespecial #6                  // Method java/lang/Object."<init>":()V
      31: return

  public boolean evaluate() throws java.lang.Exception;
    Code:
       0: invokestatic  #7                  // Method org/apache/hadoop/hbase/quotas/TestSpaceQuotasWithSnapshots.access$100:()Lorg/slf4j/Logger;
       3: new           #8                  // class java/lang/StringBuilder
       6: dup
       7: invokespecial #9                  // Method java/lang/StringBuilder."<init>":()V
      10: ldc           #10                 // String Last observed size=
      12: invokevirtual #11                 // Method java/lang/StringBuilder.append:(Ljava/lang/String;)Ljava/lang/StringBuilder;
      15: aload_0
      16: getfield      #2                  // Field val$lastValue:Ljava/util/concurrent/atomic/AtomicLong;
      19: invokevirtual #12                 // Method java/util/concurrent/atomic/AtomicLong.get:()J
      22: invokevirtual #13                 // Method java/lang/StringBuilder.append:(J)Ljava/lang/StringBuilder;
      25: invokevirtual #14                 // Method java/lang/StringBuilder.toString:()Ljava/lang/String;
      28: invokeinterface #15,  2           // InterfaceMethod org/slf4j/Logger.debug:(Ljava/lang/String;)V
      33: aload_0
      34: getfield      #1                  // Field this$0:Lorg/apache/hadoop/hbase/quotas/TestSpaceQuotasWithSnapshots;
      37: aload_0
      38: getfield      #3                  // Field val$conn:Lorg/apache/hadoop/hbase/client/Connection;
      41: aload_0
      42: getfield      #4                  // Field val$tn:Lorg/apache/hadoop/hbase/TableName;
      45: invokevirtual #16                 // Method org/apache/hadoop/hbase/quotas/TestSpaceQuotasWithSnapshots.getRegionSizeReportForTable:(Lorg/apache/hadoop/hbase/client/Connection;Lorg/apache/hadoop/hbase/TableName;)J
      48: lstore_1
      49: lload_1
      50: aload_0
      51: getfield      #2                  // Field val$lastValue:Ljava/util/concurrent/atomic/AtomicLong;
      54: invokevirtual #12                 // Method java/util/concurrent/atomic/AtomicLong.get:()J
      57: lcmp
      58: ifne          78
      61: aload_0
      62: getfield      #5                  // Field val$counter:Ljava/util/concurrent/atomic/AtomicInteger;
      65: invokevirtual #17                 // Method java/util/concurrent/atomic/AtomicInteger.incrementAndGet:()I
      68: istore_3
      69: iload_3
      70: iconst_5
      71: if_icmplt     76
      74: iconst_1
      75: ireturn
      76: iconst_0
      77: ireturn
      78: aload_0
      79: getfield      #5                  // Field val$counter:Ljava/util/concurrent/atomic/AtomicInteger;
      82: iconst_0
      83: invokevirtual #18                 // Method java/util/concurrent/atomic/AtomicInteger.set:(I)V
      86: aload_0
      87: getfield      #2                  // Field val$lastValue:Ljava/util/concurrent/atomic/AtomicLong;
      90: lload_1
      91: invokevirtual #19                 // Method java/util/concurrent/atomic/AtomicLong.set:(J)V
      94: iconst_0
      95: ireturn
}
