Compiled from "TestHRegion.java"
public class org.apache.hadoop.hbase.regionserver.TestHRegion$HRegionForTesting extends org.apache.hadoop.hbase.regionserver.HRegion {
  public org.apache.hadoop.hbase.regionserver.TestHRegion$HRegionForTesting(org.apache.hadoop.fs.Path, org.apache.hadoop.hbase.wal.WAL, org.apache.hadoop.fs.FileSystem, org.apache.hadoop.conf.Configuration, org.apache.hadoop.hbase.client.RegionInfo, org.apache.hadoop.hbase.client.TableDescriptor, org.apache.hadoop.hbase.regionserver.RegionServerServices);
    Code:
       0: aload_0
       1: new           #1                  // class org/apache/hadoop/hbase/regionserver/HRegionFileSystem
       4: dup
       5: aload         4
       7: aload_3
       8: aload_1
       9: aload         5
      11: invokespecial #2                  // Method org/apache/hadoop/hbase/regionserver/HRegionFileSystem."<init>":(Lorg/apache/hadoop/conf/Configuration;Lorg/apache/hadoop/fs/FileSystem;Lorg/apache/hadoop/fs/Path;Lorg/apache/hadoop/hbase/client/RegionInfo;)V
      14: aload_2
      15: aload         4
      17: aload         6
      19: aload         7
      21: invokespecial #3                  // Method "<init>":(Lorg/apache/hadoop/hbase/regionserver/HRegionFileSystem;Lorg/apache/hadoop/hbase/wal/WAL;Lorg/apache/hadoop/conf/Configuration;Lorg/apache/hadoop/hbase/client/TableDescriptor;Lorg/apache/hadoop/hbase/regionserver/RegionServerServices;)V
      24: return

  public org.apache.hadoop.hbase.regionserver.TestHRegion$HRegionForTesting(org.apache.hadoop.hbase.regionserver.HRegionFileSystem, org.apache.hadoop.hbase.wal.WAL, org.apache.hadoop.conf.Configuration, org.apache.hadoop.hbase.client.TableDescriptor, org.apache.hadoop.hbase.regionserver.RegionServerServices);
    Code:
       0: aload_0
       1: aload_1
       2: aload_2
       3: aload_3
       4: aload         4
       6: aload         5
       8: invokespecial #4                  // Method org/apache/hadoop/hbase/regionserver/HRegion."<init>":(Lorg/apache/hadoop/hbase/regionserver/HRegionFileSystem;Lorg/apache/hadoop/hbase/wal/WAL;Lorg/apache/hadoop/conf/Configuration;Lorg/apache/hadoop/hbase/client/TableDescriptor;Lorg/apache/hadoop/hbase/regionserver/RegionServerServices;)V
      11: return

  protected org.apache.hadoop.hbase.regionserver.HStore instantiateHStore(org.apache.hadoop.hbase.client.ColumnFamilyDescriptor, boolean) throws java.io.IOException;
    Code:
       0: aload_1
       1: invokeinterface #5,  1            // InterfaceMethod org/apache/hadoop/hbase/client/ColumnFamilyDescriptor.isMobEnabled:()Z
       6: ifeq          45
       9: aload_0
      10: getfield      #6                  // Field conf:Lorg/apache/hadoop/conf/Configuration;
      13: invokestatic  #7                  // Method org/apache/hadoop/hbase/io/hfile/HFile.getFormatVersion:(Lorg/apache/hadoop/conf/Configuration;)I
      16: iconst_3
      17: if_icmpge     30
      20: new           #9                  // class java/io/IOException
      23: dup
      24: ldc           #10                 // String A minimum HFile version of 3 is required for MOB feature. Consider setting hfile.format.version accordingly.
      26: invokespecial #11                 // Method java/io/IOException."<init>":(Ljava/lang/String;)V
      29: athrow
      30: new           #12                 // class org/apache/hadoop/hbase/regionserver/HMobStore
      33: dup
      34: aload_0
      35: aload_1
      36: aload_0
      37: getfield      #6                  // Field conf:Lorg/apache/hadoop/conf/Configuration;
      40: iload_2
      41: invokespecial #13                 // Method org/apache/hadoop/hbase/regionserver/HMobStore."<init>":(Lorg/apache/hadoop/hbase/regionserver/HRegion;Lorg/apache/hadoop/hbase/client/ColumnFamilyDescriptor;Lorg/apache/hadoop/conf/Configuration;Z)V
      44: areturn
      45: new           #14                 // class org/apache/hadoop/hbase/regionserver/TestHRegion$HStoreForTesting
      48: dup
      49: aload_0
      50: aload_1
      51: aload_0
      52: getfield      #6                  // Field conf:Lorg/apache/hadoop/conf/Configuration;
      55: iload_2
      56: invokespecial #15                 // Method org/apache/hadoop/hbase/regionserver/TestHRegion$HStoreForTesting."<init>":(Lorg/apache/hadoop/hbase/regionserver/HRegion;Lorg/apache/hadoop/hbase/client/ColumnFamilyDescriptor;Lorg/apache/hadoop/conf/Configuration;Z)V
      59: areturn
}
