Compiled from "TestMasterMetricsWrapper.java"
public class org.apache.hadoop.hbase.master.TestMasterMetricsWrapper {
  public static final org.apache.hadoop.hbase.HBaseClassTestRule CLASS_RULE;

  public org.apache.hadoop.hbase.master.TestMasterMetricsWrapper();
    Code:
       0: aload_0
       1: invokespecial #1                  // Method java/lang/Object."<init>":()V
       4: return

  public static void setup() throws java.lang.Exception;
    Code:
       0: getstatic     #2                  // Field TEST_UTIL:Lorg/apache/hadoop/hbase/HBaseTestingUtility;
       3: iconst_4
       4: invokevirtual #4                  // Method org/apache/hadoop/hbase/HBaseTestingUtility.startMiniCluster:(I)Lorg/apache/hadoop/hbase/MiniHBaseCluster;
       7: pop
       8: return

  public static void teardown() throws java.lang.Exception;
    Code:
       0: getstatic     #2                  // Field TEST_UTIL:Lorg/apache/hadoop/hbase/HBaseTestingUtility;
       3: invokevirtual #5                  // Method org/apache/hadoop/hbase/HBaseTestingUtility.shutdownMiniCluster:()V
       6: return

  public void testInfo();
    Code:
       0: getstatic     #2                  // Field TEST_UTIL:Lorg/apache/hadoop/hbase/HBaseTestingUtility;
       3: invokevirtual #6                  // Method org/apache/hadoop/hbase/HBaseTestingUtility.getHBaseCluster:()Lorg/apache/hadoop/hbase/MiniHBaseCluster;
       6: invokevirtual #7                  // Method org/apache/hadoop/hbase/MiniHBaseCluster.getMaster:()Lorg/apache/hadoop/hbase/master/HMaster;
       9: astore_1
      10: new           #8                  // class org/apache/hadoop/hbase/master/MetricsMasterWrapperImpl
      13: dup
      14: aload_1
      15: invokespecial #9                  // Method org/apache/hadoop/hbase/master/MetricsMasterWrapperImpl."<init>":(Lorg/apache/hadoop/hbase/master/HMaster;)V
      18: astore_2
      19: aload_1
      20: invokevirtual #10                 // Method org/apache/hadoop/hbase/master/HMaster.getSplitPlanCount:()J
      23: l2f
      24: aload_2
      25: invokevirtual #11                 // Method org/apache/hadoop/hbase/master/MetricsMasterWrapperImpl.getSplitPlanCount:()J
      28: l2f
      29: fconst_0
      30: invokestatic  #12                 // Method org/junit/Assert.assertEquals:(FFF)V
      33: aload_1
      34: invokevirtual #13                 // Method org/apache/hadoop/hbase/master/HMaster.getMergePlanCount:()J
      37: l2f
      38: aload_2
      39: invokevirtual #14                 // Method org/apache/hadoop/hbase/master/MetricsMasterWrapperImpl.getMergePlanCount:()J
      42: l2f
      43: fconst_0
      44: invokestatic  #12                 // Method org/junit/Assert.assertEquals:(FFF)V
      47: aload_1
      48: invokevirtual #15                 // Method org/apache/hadoop/hbase/master/HMaster.getAverageLoad:()D
      51: aload_2
      52: invokevirtual #16                 // Method org/apache/hadoop/hbase/master/MetricsMasterWrapperImpl.getAverageLoad:()D
      55: dconst_0
      56: invokestatic  #17                 // Method org/junit/Assert.assertEquals:(DDD)V
      59: aload_1
      60: invokevirtual #18                 // Method org/apache/hadoop/hbase/master/HMaster.getClusterId:()Ljava/lang/String;
      63: aload_2
      64: invokevirtual #19                 // Method org/apache/hadoop/hbase/master/MetricsMasterWrapperImpl.getClusterId:()Ljava/lang/String;
      67: invokestatic  #20                 // Method org/junit/Assert.assertEquals:(Ljava/lang/Object;Ljava/lang/Object;)V
      70: aload_1
      71: invokevirtual #21                 // Method org/apache/hadoop/hbase/master/HMaster.getMasterActiveTime:()J
      74: aload_2
      75: invokevirtual #22                 // Method org/apache/hadoop/hbase/master/MetricsMasterWrapperImpl.getActiveTime:()J
      78: invokestatic  #23                 // Method org/junit/Assert.assertEquals:(JJ)V
      81: aload_1
      82: invokevirtual #24                 // Method org/apache/hadoop/hbase/master/HMaster.getMasterStartTime:()J
      85: aload_2
      86: invokevirtual #25                 // Method org/apache/hadoop/hbase/master/MetricsMasterWrapperImpl.getStartTime:()J
      89: invokestatic  #23                 // Method org/junit/Assert.assertEquals:(JJ)V
      92: aload_1
      93: invokevirtual #26                 // Method org/apache/hadoop/hbase/master/HMaster.getMasterCoprocessors:()[Ljava/lang/String;
      96: arraylength
      97: i2l
      98: aload_2
      99: invokevirtual #27                 // Method org/apache/hadoop/hbase/master/MetricsMasterWrapperImpl.getCoprocessors:()[Ljava/lang/String;
     102: arraylength
     103: i2l
     104: invokestatic  #23                 // Method org/junit/Assert.assertEquals:(JJ)V
     107: aload_1
     108: invokevirtual #28                 // Method org/apache/hadoop/hbase/master/HMaster.getServerManager:()Lorg/apache/hadoop/hbase/master/ServerManager;
     111: invokevirtual #29                 // Method org/apache/hadoop/hbase/master/ServerManager.getOnlineServersList:()Ljava/util/List;
     114: invokeinterface #30,  1           // InterfaceMethod java/util/List.size:()I
     119: i2l
     120: aload_2
     121: invokevirtual #31                 // Method org/apache/hadoop/hbase/master/MetricsMasterWrapperImpl.getNumRegionServers:()I
     124: i2l
     125: invokestatic  #23                 // Method org/junit/Assert.assertEquals:(JJ)V
     128: iconst_4
     129: getstatic     #2                  // Field TEST_UTIL:Lorg/apache/hadoop/hbase/HBaseTestingUtility;
     132: invokevirtual #32                 // Method org/apache/hadoop/hbase/HBaseTestingUtility.getConfiguration:()Lorg/apache/hadoop/conf/Configuration;
     135: invokestatic  #33                 // InterfaceMethod org/apache/hadoop/hbase/master/LoadBalancer.isTablesOnMaster:(Lorg/apache/hadoop/conf/Configuration;)Z
     138: ifeq          145
     141: iconst_1
     142: goto          146
     145: iconst_0
     146: iadd
     147: istore_3
     148: iload_3
     149: i2l
     150: aload_2
     151: invokevirtual #31                 // Method org/apache/hadoop/hbase/master/MetricsMasterWrapperImpl.getNumRegionServers:()I
     154: i2l
     155: invokestatic  #23                 // Method org/junit/Assert.assertEquals:(JJ)V
     158: aload_2
     159: invokevirtual #34                 // Method org/apache/hadoop/hbase/master/MetricsMasterWrapperImpl.getZookeeperQuorum:()Ljava/lang/String;
     162: astore        4
     164: aload         4
     166: ldc           #35                 // String ,
     168: invokevirtual #36                 // Method java/lang/String.split:(Ljava/lang/String;)[Ljava/lang/String;
     171: arraylength
     172: i2l
     173: getstatic     #2                  // Field TEST_UTIL:Lorg/apache/hadoop/hbase/HBaseTestingUtility;
     176: invokevirtual #37                 // Method org/apache/hadoop/hbase/HBaseTestingUtility.getZkCluster:()Lorg/apache/hadoop/hbase/zookeeper/MiniZooKeeperCluster;
     179: invokevirtual #38                 // Method org/apache/hadoop/hbase/zookeeper/MiniZooKeeperCluster.getZooKeeperServerNum:()I
     182: i2l
     183: invokestatic  #23                 // Method org/junit/Assert.assertEquals:(JJ)V
     186: iconst_3
     187: istore        5
     189: getstatic     #39                 // Field LOG:Lorg/slf4j/Logger;
     192: new           #40                 // class java/lang/StringBuilder
     195: dup
     196: invokespecial #41                 // Method java/lang/StringBuilder."<init>":()V
     199: ldc           #42                 // String Stopping
     201: invokevirtual #43                 // Method java/lang/StringBuilder.append:(Ljava/lang/String;)Ljava/lang/StringBuilder;
     204: getstatic     #2                  // Field TEST_UTIL:Lorg/apache/hadoop/hbase/HBaseTestingUtility;
     207: invokevirtual #44                 // Method org/apache/hadoop/hbase/HBaseTestingUtility.getMiniHBaseCluster:()Lorg/apache/hadoop/hbase/MiniHBaseCluster;
     210: iconst_3
     211: invokevirtual #45                 // Method org/apache/hadoop/hbase/MiniHBaseCluster.getRegionServer:(I)Lorg/apache/hadoop/hbase/regionserver/HRegionServer;
     214: invokevirtual #46                 // Method java/lang/StringBuilder.append:(Ljava/lang/Object;)Ljava/lang/StringBuilder;
     217: invokevirtual #47                 // Method java/lang/StringBuilder.toString:()Ljava/lang/String;
     220: invokeinterface #48,  2           // InterfaceMethod org/slf4j/Logger.info:(Ljava/lang/String;)V
     225: getstatic     #2                  // Field TEST_UTIL:Lorg/apache/hadoop/hbase/HBaseTestingUtility;
     228: invokevirtual #44                 // Method org/apache/hadoop/hbase/HBaseTestingUtility.getMiniHBaseCluster:()Lorg/apache/hadoop/hbase/MiniHBaseCluster;
     231: iconst_3
     232: iconst_0
     233: invokevirtual #49                 // Method org/apache/hadoop/hbase/MiniHBaseCluster.stopRegionServer:(IZ)Lorg/apache/hadoop/hbase/util/JVMClusterUtil$RegionServerThread;
     236: pop
     237: getstatic     #2                  // Field TEST_UTIL:Lorg/apache/hadoop/hbase/HBaseTestingUtility;
     240: invokevirtual #44                 // Method org/apache/hadoop/hbase/HBaseTestingUtility.getMiniHBaseCluster:()Lorg/apache/hadoop/hbase/MiniHBaseCluster;
     243: iconst_3
     244: invokevirtual #50                 // Method org/apache/hadoop/hbase/MiniHBaseCluster.waitOnRegionServer:(I)Ljava/lang/String;
     247: pop
     248: getstatic     #2                  // Field TEST_UTIL:Lorg/apache/hadoop/hbase/HBaseTestingUtility;
     251: invokevirtual #6                  // Method org/apache/hadoop/hbase/HBaseTestingUtility.getHBaseCluster:()Lorg/apache/hadoop/hbase/MiniHBaseCluster;
     254: invokevirtual #7                  // Method org/apache/hadoop/hbase/MiniHBaseCluster.getMaster:()Lorg/apache/hadoop/hbase/master/HMaster;
     257: invokevirtual #28                 // Method org/apache/hadoop/hbase/master/HMaster.getServerManager:()Lorg/apache/hadoop/hbase/master/ServerManager;
     260: invokevirtual #51                 // Method org/apache/hadoop/hbase/master/ServerManager.getOnlineServers:()Ljava/util/Map;
     263: invokeinterface #52,  1           // InterfaceMethod java/util/Map.size:()I
     268: iload_3
     269: if_icmpne     281
     272: ldc2_w        #53                 // long 10l
     275: invokestatic  #55                 // Method org/apache/hadoop/hbase/util/Threads.sleep:(J)V
     278: goto          248
     281: iload_3
     282: iconst_1
     283: isub
     284: i2l
     285: aload_2
     286: invokevirtual #31                 // Method org/apache/hadoop/hbase/master/MetricsMasterWrapperImpl.getNumRegionServers:()I
     289: i2l
     290: invokestatic  #23                 // Method org/junit/Assert.assertEquals:(JJ)V
     293: lconst_1
     294: aload_2
     295: invokevirtual #56                 // Method org/apache/hadoop/hbase/master/MetricsMasterWrapperImpl.getNumDeadRegionServers:()I
     298: i2l
     299: invokestatic  #23                 // Method org/junit/Assert.assertEquals:(JJ)V
     302: lconst_1
     303: aload_2
     304: invokevirtual #57                 // Method org/apache/hadoop/hbase/master/MetricsMasterWrapperImpl.getNumWALFiles:()J
     307: invokestatic  #23                 // Method org/junit/Assert.assertEquals:(JJ)V
     310: return

  public void testQuotaSnapshotConversion();
    Code:
       0: new           #8                  // class org/apache/hadoop/hbase/master/MetricsMasterWrapperImpl
       3: dup
       4: getstatic     #2                  // Field TEST_UTIL:Lorg/apache/hadoop/hbase/HBaseTestingUtility;
       7: invokevirtual #6                  // Method org/apache/hadoop/hbase/HBaseTestingUtility.getHBaseCluster:()Lorg/apache/hadoop/hbase/MiniHBaseCluster;
      10: invokevirtual #7                  // Method org/apache/hadoop/hbase/MiniHBaseCluster.getMaster:()Lorg/apache/hadoop/hbase/master/HMaster;
      13: invokespecial #9                  // Method org/apache/hadoop/hbase/master/MetricsMasterWrapperImpl."<init>":(Lorg/apache/hadoop/hbase/master/HMaster;)V
      16: astore_1
      17: new           #58                 // class java/util/AbstractMap$SimpleImmutableEntry
      20: dup
      21: ldc2_w        #59                 // long 1024l
      24: invokestatic  #61                 // Method java/lang/Long.valueOf:(J)Ljava/lang/Long;
      27: ldc2_w        #62                 // long 2048l
      30: invokestatic  #61                 // Method java/lang/Long.valueOf:(J)Ljava/lang/Long;
      33: invokespecial #64                 // Method java/util/AbstractMap$SimpleImmutableEntry."<init>":(Ljava/lang/Object;Ljava/lang/Object;)V
      36: aload_1
      37: new           #65                 // class org/apache/hadoop/hbase/quotas/SpaceQuotaSnapshot
      40: dup
      41: invokestatic  #66                 // Method org/apache/hadoop/hbase/quotas/SpaceQuotaSnapshot$SpaceQuotaStatus.notInViolation:()Lorg/apache/hadoop/hbase/quotas/SpaceQuotaSnapshot$SpaceQuotaStatus;
      44: ldc2_w        #59                 // long 1024l
      47: ldc2_w        #62                 // long 2048l
      50: invokespecial #67                 // Method org/apache/hadoop/hbase/quotas/SpaceQuotaSnapshot."<init>":(Lorg/apache/hadoop/hbase/quotas/SpaceQuotaSnapshot$SpaceQuotaStatus;JJ)V
      53: invokevirtual #68                 // Method org/apache/hadoop/hbase/master/MetricsMasterWrapperImpl.convertSnapshot:(Lorg/apache/hadoop/hbase/quotas/SpaceQuotaSnapshot;)Ljava/util/Map$Entry;
      56: invokestatic  #20                 // Method org/junit/Assert.assertEquals:(Ljava/lang/Object;Ljava/lang/Object;)V
      59: new           #58                 // class java/util/AbstractMap$SimpleImmutableEntry
      62: dup
      63: ldc2_w        #69                 // long 4096l
      66: invokestatic  #61                 // Method java/lang/Long.valueOf:(J)Ljava/lang/Long;
      69: ldc2_w        #62                 // long 2048l
      72: invokestatic  #61                 // Method java/lang/Long.valueOf:(J)Ljava/lang/Long;
      75: invokespecial #64                 // Method java/util/AbstractMap$SimpleImmutableEntry."<init>":(Ljava/lang/Object;Ljava/lang/Object;)V
      78: aload_1
      79: new           #65                 // class org/apache/hadoop/hbase/quotas/SpaceQuotaSnapshot
      82: dup
      83: new           #71                 // class org/apache/hadoop/hbase/quotas/SpaceQuotaSnapshot$SpaceQuotaStatus
      86: dup
      87: getstatic     #72                 // Field org/apache/hadoop/hbase/quotas/SpaceViolationPolicy.NO_INSERTS:Lorg/apache/hadoop/hbase/quotas/SpaceViolationPolicy;
      90: invokespecial #73                 // Method org/apache/hadoop/hbase/quotas/SpaceQuotaSnapshot$SpaceQuotaStatus."<init>":(Lorg/apache/hadoop/hbase/quotas/SpaceViolationPolicy;)V
      93: ldc2_w        #69                 // long 4096l
      96: ldc2_w        #62                 // long 2048l
      99: invokespecial #67                 // Method org/apache/hadoop/hbase/quotas/SpaceQuotaSnapshot."<init>":(Lorg/apache/hadoop/hbase/quotas/SpaceQuotaSnapshot$SpaceQuotaStatus;JJ)V
     102: invokevirtual #68                 // Method org/apache/hadoop/hbase/master/MetricsMasterWrapperImpl.convertSnapshot:(Lorg/apache/hadoop/hbase/quotas/SpaceQuotaSnapshot;)Ljava/util/Map$Entry;
     105: invokestatic  #20                 // Method org/junit/Assert.assertEquals:(Ljava/lang/Object;Ljava/lang/Object;)V
     108: return

  public void testOfflineRegion() throws java.lang.Exception;
    Code:
       0: getstatic     #2                  // Field TEST_UTIL:Lorg/apache/hadoop/hbase/HBaseTestingUtility;
       3: invokevirtual #6                  // Method org/apache/hadoop/hbase/HBaseTestingUtility.getHBaseCluster:()Lorg/apache/hadoop/hbase/MiniHBaseCluster;
       6: invokevirtual #7                  // Method org/apache/hadoop/hbase/MiniHBaseCluster.getMaster:()Lorg/apache/hadoop/hbase/master/HMaster;
       9: astore_1
      10: new           #8                  // class org/apache/hadoop/hbase/master/MetricsMasterWrapperImpl
      13: dup
      14: aload_1
      15: invokespecial #9                  // Method org/apache/hadoop/hbase/master/MetricsMasterWrapperImpl."<init>":(Lorg/apache/hadoop/hbase/master/HMaster;)V
      18: astore_2
      19: ldc           #74                 // String testRegionNumber
      21: invokestatic  #75                 // Method org/apache/hadoop/hbase/TableName.valueOf:(Ljava/lang/String;)Lorg/apache/hadoop/hbase/TableName;
      24: astore_3
      25: new           #76                 // class org/apache/hadoop/hbase/HTableDescriptor
      28: dup
      29: aload_3
      30: invokespecial #77                 // Method org/apache/hadoop/hbase/HTableDescriptor."<init>":(Lorg/apache/hadoop/hbase/TableName;)V
      33: astore        5
      35: ldc           #78                 // String FAMILY
      37: invokestatic  #79                 // Method org/apache/hadoop/hbase/util/Bytes.toBytes:(Ljava/lang/String;)[B
      40: astore        6
      42: aload         5
      44: new           #80                 // class org/apache/hadoop/hbase/HColumnDescriptor
      47: dup
      48: aload         6
      50: invokespecial #81                 // Method org/apache/hadoop/hbase/HColumnDescriptor."<init>":([B)V
      53: invokevirtual #82                 // Method org/apache/hadoop/hbase/HTableDescriptor.addFamily:(Lorg/apache/hadoop/hbase/HColumnDescriptor;)Lorg/apache/hadoop/hbase/HTableDescriptor;
      56: pop
      57: getstatic     #2                  // Field TEST_UTIL:Lorg/apache/hadoop/hbase/HBaseTestingUtility;
      60: invokevirtual #83                 // Method org/apache/hadoop/hbase/HBaseTestingUtility.getHBaseAdmin:()Lorg/apache/hadoop/hbase/client/HBaseAdmin;
      63: aload         5
      65: ldc           #84                 // String A
      67: invokestatic  #79                 // Method org/apache/hadoop/hbase/util/Bytes.toBytes:(Ljava/lang/String;)[B
      70: ldc           #85                 // String Z
      72: invokestatic  #79                 // Method org/apache/hadoop/hbase/util/Bytes.toBytes:(Ljava/lang/String;)[B
      75: iconst_5
      76: invokevirtual #86                 // Method org/apache/hadoop/hbase/client/HBaseAdmin.createTable:(Lorg/apache/hadoop/hbase/client/TableDescriptor;[B[BI)V
      79: invokestatic  #87                 // Method java/lang/System.currentTimeMillis:()J
      82: ldc2_w        #88                 // long 1000l
      85: ladd
      86: lstore        7
      88: aload_1
      89: invokevirtual #90                 // Method org/apache/hadoop/hbase/master/HMaster.getAssignmentManager:()Lorg/apache/hadoop/hbase/master/assignment/AssignmentManager;
      92: invokevirtual #91                 // Method org/apache/hadoop/hbase/master/assignment/AssignmentManager.getRegionStates:()Lorg/apache/hadoop/hbase/master/assignment/RegionStates;
      95: aload_3
      96: invokevirtual #92                 // Method org/apache/hadoop/hbase/master/assignment/RegionStates.getRegionsOfTable:(Lorg/apache/hadoop/hbase/TableName;)Ljava/util/List;
      99: astore        9
     101: aload         9
     103: invokeinterface #30,  1           // InterfaceMethod java/util/List.size:()I
     108: iconst_3
     109: if_icmple     128
     112: aload         9
     114: iconst_2
     115: invokeinterface #93,  2           // InterfaceMethod java/util/List.get:(I)Ljava/lang/Object;
     120: checkcast     #94                 // class org/apache/hadoop/hbase/client/RegionInfo
     123: astore        4
     125: goto          155
     128: invokestatic  #87                 // Method java/lang/System.currentTimeMillis:()J
     131: lstore        10
     133: lload         10
     135: lload         7
     137: lcmp
     138: ifle          146
     141: ldc           #95                 // String Could not find an online region
     143: invokestatic  #96                 // Method org/junit/Assert.fail:(Ljava/lang/String;)V
     146: ldc2_w        #53                 // long 10l
     149: invokestatic  #97                 // Method java/lang/Thread.sleep:(J)V
     152: goto          88
     155: aload_2
     156: invokevirtual #98                 // Method org/apache/hadoop/hbase/master/MetricsMasterWrapperImpl.getRegionCounts:()Lorg/apache/hadoop/hbase/util/PairOfSameType;
     159: astore        9
     161: ldc2_w        #99                 // long 5l
     164: aload         9
     166: invokevirtual #101                // Method org/apache/hadoop/hbase/util/PairOfSameType.getFirst:()Ljava/lang/Object;
     169: checkcast     #102                // class java/lang/Integer
     172: invokevirtual #103                // Method java/lang/Integer.intValue:()I
     175: i2l
     176: invokestatic  #23                 // Method org/junit/Assert.assertEquals:(JJ)V
     179: lconst_0
     180: aload         9
     182: invokevirtual #104                // Method org/apache/hadoop/hbase/util/PairOfSameType.getSecond:()Ljava/lang/Object;
     185: checkcast     #102                // class java/lang/Integer
     188: invokevirtual #103                // Method java/lang/Integer.intValue:()I
     191: i2l
     192: invokestatic  #23                 // Method org/junit/Assert.assertEquals:(JJ)V
     195: getstatic     #2                  // Field TEST_UTIL:Lorg/apache/hadoop/hbase/HBaseTestingUtility;
     198: invokevirtual #83                 // Method org/apache/hadoop/hbase/HBaseTestingUtility.getHBaseAdmin:()Lorg/apache/hadoop/hbase/client/HBaseAdmin;
     201: aload         4
     203: invokeinterface #105,  1          // InterfaceMethod org/apache/hadoop/hbase/client/RegionInfo.getRegionName:()[B
     208: invokevirtual #106                // Method org/apache/hadoop/hbase/client/HBaseAdmin.offline:([B)V
     211: invokestatic  #87                 // Method java/lang/System.currentTimeMillis:()J
     214: ldc2_w        #107                // long 800l
     217: ladd
     218: lstore        7
     220: aload_1
     221: invokevirtual #90                 // Method org/apache/hadoop/hbase/master/HMaster.getAssignmentManager:()Lorg/apache/hadoop/hbase/master/assignment/AssignmentManager;
     224: invokevirtual #91                 // Method org/apache/hadoop/hbase/master/assignment/AssignmentManager.getRegionStates:()Lorg/apache/hadoop/hbase/master/assignment/RegionStates;
     227: astore        10
     229: aload         10
     231: aload_3
     232: invokevirtual #109                // Method org/apache/hadoop/hbase/master/assignment/RegionStates.getRegionByStateOfTable:(Lorg/apache/hadoop/hbase/TableName;)Ljava/util/Map;
     235: getstatic     #110                // Field org/apache/hadoop/hbase/master/RegionState$State.OFFLINE:Lorg/apache/hadoop/hbase/master/RegionState$State;
     238: invokeinterface #111,  2          // InterfaceMethod java/util/Map.get:(Ljava/lang/Object;)Ljava/lang/Object;
     243: checkcast     #112                // class java/util/List
     246: aload         4
     248: invokeinterface #113,  2          // InterfaceMethod java/util/List.contains:(Ljava/lang/Object;)Z
     253: ifeq          259
     256: goto          289
     259: invokestatic  #87                 // Method java/lang/System.currentTimeMillis:()J
     262: lstore        11
     264: lload         11
     266: lload         7
     268: lcmp
     269: ifle          280
     272: ldc           #114                // String Failed to offline the region in time
     274: invokestatic  #96                 // Method org/junit/Assert.fail:(Ljava/lang/String;)V
     277: goto          289
     280: ldc2_w        #53                 // long 10l
     283: invokestatic  #97                 // Method java/lang/Thread.sleep:(J)V
     286: goto          229
     289: aload_2
     290: invokevirtual #98                 // Method org/apache/hadoop/hbase/master/MetricsMasterWrapperImpl.getRegionCounts:()Lorg/apache/hadoop/hbase/util/PairOfSameType;
     293: astore        9
     295: ldc2_w        #115                // long 4l
     298: aload         9
     300: invokevirtual #101                // Method org/apache/hadoop/hbase/util/PairOfSameType.getFirst:()Ljava/lang/Object;
     303: checkcast     #102                // class java/lang/Integer
     306: invokevirtual #103                // Method java/lang/Integer.intValue:()I
     309: i2l
     310: invokestatic  #23                 // Method org/junit/Assert.assertEquals:(JJ)V
     313: lconst_1
     314: aload         9
     316: invokevirtual #104                // Method org/apache/hadoop/hbase/util/PairOfSameType.getSecond:()Ljava/lang/Object;
     319: checkcast     #102                // class java/lang/Integer
     322: invokevirtual #103                // Method java/lang/Integer.intValue:()I
     325: i2l
     326: invokestatic  #23                 // Method org/junit/Assert.assertEquals:(JJ)V
     329: getstatic     #2                  // Field TEST_UTIL:Lorg/apache/hadoop/hbase/HBaseTestingUtility;
     332: aload_3
     333: invokevirtual #117                // Method org/apache/hadoop/hbase/HBaseTestingUtility.deleteTable:(Lorg/apache/hadoop/hbase/TableName;)V
     336: goto          351
     339: astore        13
     341: getstatic     #2                  // Field TEST_UTIL:Lorg/apache/hadoop/hbase/HBaseTestingUtility;
     344: aload_3
     345: invokevirtual #117                // Method org/apache/hadoop/hbase/HBaseTestingUtility.deleteTable:(Lorg/apache/hadoop/hbase/TableName;)V
     348: aload         13
     350: athrow
     351: return
    Exception table:
       from    to  target type
          25   329   339   any
         339   341   339   any

  static {};
    Code:
       0: ldc           #3                  // class org/apache/hadoop/hbase/master/TestMasterMetricsWrapper
       2: invokestatic  #118                // Method org/apache/hadoop/hbase/HBaseClassTestRule.forClass:(Ljava/lang/Class;)Lorg/apache/hadoop/hbase/HBaseClassTestRule;
       5: putstatic     #119                // Field CLASS_RULE:Lorg/apache/hadoop/hbase/HBaseClassTestRule;
       8: ldc           #3                  // class org/apache/hadoop/hbase/master/TestMasterMetricsWrapper
      10: invokestatic  #120                // Method org/slf4j/LoggerFactory.getLogger:(Ljava/lang/Class;)Lorg/slf4j/Logger;
      13: putstatic     #39                 // Field LOG:Lorg/slf4j/Logger;
      16: new           #121                // class org/apache/hadoop/hbase/HBaseTestingUtility
      19: dup
      20: invokespecial #122                // Method org/apache/hadoop/hbase/HBaseTestingUtility."<init>":()V
      23: putstatic     #2                  // Field TEST_UTIL:Lorg/apache/hadoop/hbase/HBaseTestingUtility;
      26: return
}
