Compiled from "TestHFileSeek.java"
class org.apache.hadoop.hbase.io.hfile.TestHFileSeek$IntegerRange {
  public org.apache.hadoop.hbase.io.hfile.TestHFileSeek$IntegerRange(int, int);
    Code:
       0: aload_0
       1: invokespecial #1                  // Method java/lang/Object."<init>":()V
       4: aload_0
       5: iload_1
       6: putfield      #2                  // Field from:I
       9: aload_0
      10: iload_2
      11: putfield      #3                  // Field to:I
      14: return

  public static org.apache.hadoop.hbase.io.hfile.TestHFileSeek$IntegerRange parse(java.lang.String) throws org.apache.hbase.thirdparty.org.apache.commons.cli.ParseException;
    Code:
       0: new           #4                  // class java/util/StringTokenizer
       3: dup
       4: aload_0
       5: ldc           #5                  // String  \t,
       7: invokespecial #6                  // Method java/util/StringTokenizer."<init>":(Ljava/lang/String;Ljava/lang/String;)V
      10: astore_1
      11: aload_1
      12: invokevirtual #7                  // Method java/util/StringTokenizer.countTokens:()I
      15: iconst_2
      16: if_icmpeq     46
      19: new           #8                  // class org/apache/hbase/thirdparty/org/apache/commons/cli/ParseException
      22: dup
      23: new           #9                  // class java/lang/StringBuilder
      26: dup
      27: invokespecial #10                 // Method java/lang/StringBuilder."<init>":()V
      30: ldc           #11                 // String Bad integer specification:
      32: invokevirtual #12                 // Method java/lang/StringBuilder.append:(Ljava/lang/String;)Ljava/lang/StringBuilder;
      35: aload_0
      36: invokevirtual #12                 // Method java/lang/StringBuilder.append:(Ljava/lang/String;)Ljava/lang/StringBuilder;
      39: invokevirtual #13                 // Method java/lang/StringBuilder.toString:()Ljava/lang/String;
      42: invokespecial #14                 // Method org/apache/hbase/thirdparty/org/apache/commons/cli/ParseException."<init>":(Ljava/lang/String;)V
      45: athrow
      46: aload_1
      47: invokevirtual #15                 // Method java/util/StringTokenizer.nextToken:()Ljava/lang/String;
      50: invokestatic  #16                 // Method java/lang/Integer.parseInt:(Ljava/lang/String;)I
      53: istore_2
      54: aload_1
      55: invokevirtual #15                 // Method java/util/StringTokenizer.nextToken:()Ljava/lang/String;
      58: invokestatic  #16                 // Method java/lang/Integer.parseInt:(Ljava/lang/String;)I
      61: istore_3
      62: new           #17                 // class org/apache/hadoop/hbase/io/hfile/TestHFileSeek$IntegerRange
      65: dup
      66: iload_2
      67: iload_3
      68: invokespecial #18                 // Method "<init>":(II)V
      71: areturn

  public int from();
    Code:
       0: aload_0
       1: getfield      #2                  // Field from:I
       4: ireturn

  public int to();
    Code:
       0: aload_0
       1: getfield      #3                  // Field to:I
       4: ireturn
}
