Compiled from "TestAccessController3.java"
public class org.apache.hadoop.hbase.security.access.TestAccessController3 extends org.apache.hadoop.hbase.security.access.SecureTestUtil {
  public static final org.apache.hadoop.hbase.HBaseClassTestRule CLASS_RULE;

  public org.junit.rules.TestName name;

  public org.apache.hadoop.hbase.security.access.TestAccessController3();
    Code:
       0: aload_0
       1: invokespecial #5                  // Method org/apache/hadoop/hbase/security/access/SecureTestUtil."<init>":()V
       4: aload_0
       5: new           #6                  // class org/junit/rules/TestName
       8: dup
       9: invokespecial #7                  // Method org/junit/rules/TestName."<init>":()V
      12: putfield      #8                  // Field name:Lorg/junit/rules/TestName;
      15: return

  public static void setupBeforeClass() throws java.lang.Exception;
    Code:
       0: getstatic     #9                  // Field TEST_UTIL:Lorg/apache/hadoop/hbase/HBaseTestingUtility;
       3: invokevirtual #10                 // Method org/apache/hadoop/hbase/HBaseTestingUtility.getConfiguration:()Lorg/apache/hadoop/conf/Configuration;
       6: putstatic     #11                 // Field conf:Lorg/apache/hadoop/conf/Configuration;
       9: getstatic     #11                 // Field conf:Lorg/apache/hadoop/conf/Configuration;
      12: invokestatic  #12                 // Method enableSecurity:(Lorg/apache/hadoop/conf/Configuration;)V
      15: ldc           #13                 // class org/apache/hadoop/hbase/security/access/TestAccessController3$FaultyAccessController
      17: invokevirtual #14                 // Method java/lang/Class.getName:()Ljava/lang/String;
      20: astore_0
      21: getstatic     #11                 // Field conf:Lorg/apache/hadoop/conf/Configuration;
      24: ldc           #16                 // String hbase.coprocessor.region.classes
      26: aload_0
      27: invokevirtual #17                 // Method org/apache/hadoop/conf/Configuration.set:(Ljava/lang/String;Ljava/lang/String;)V
      30: getstatic     #11                 // Field conf:Lorg/apache/hadoop/conf/Configuration;
      33: invokestatic  #18                 // Method verifyConfiguration:(Lorg/apache/hadoop/conf/Configuration;)V
      36: getstatic     #11                 // Field conf:Lorg/apache/hadoop/conf/Configuration;
      39: ldc           #20                 // String hbase.security.exec.permission.checks
      41: iconst_1
      42: invokevirtual #21                 // Method org/apache/hadoop/conf/Configuration.setBoolean:(Ljava/lang/String;Z)V
      45: getstatic     #9                  // Field TEST_UTIL:Lorg/apache/hadoop/hbase/HBaseTestingUtility;
      48: invokevirtual #22                 // Method org/apache/hadoop/hbase/HBaseTestingUtility.startMiniCluster:()Lorg/apache/hadoop/hbase/MiniHBaseCluster;
      51: pop
      52: getstatic     #9                  // Field TEST_UTIL:Lorg/apache/hadoop/hbase/HBaseTestingUtility;
      55: invokevirtual #23                 // Method org/apache/hadoop/hbase/HBaseTestingUtility.getMiniHBaseCluster:()Lorg/apache/hadoop/hbase/MiniHBaseCluster;
      58: invokevirtual #24                 // Method org/apache/hadoop/hbase/MiniHBaseCluster.getMaster:()Lorg/apache/hadoop/hbase/master/HMaster;
      61: invokevirtual #25                 // Method org/apache/hadoop/hbase/master/HMaster.getMasterCoprocessorHost:()Lorg/apache/hadoop/hbase/master/MasterCoprocessorHost;
      64: astore_1
      65: aload_1
      66: ldc           #13                 // class org/apache/hadoop/hbase/security/access/TestAccessController3$FaultyAccessController
      68: iconst_0
      69: getstatic     #11                 // Field conf:Lorg/apache/hadoop/conf/Configuration;
      72: invokevirtual #27                 // Method org/apache/hadoop/hbase/master/MasterCoprocessorHost.load:(Ljava/lang/Class;ILorg/apache/hadoop/conf/Configuration;)V
      75: aload_1
      76: aload_0
      77: invokevirtual #28                 // Method org/apache/hadoop/hbase/master/MasterCoprocessorHost.findCoprocessor:(Ljava/lang/String;)Lorg/apache/hadoop/hbase/Coprocessor;
      80: checkcast     #29                 // class org/apache/hadoop/hbase/security/access/AccessController
      83: putstatic     #1                  // Field ACCESS_CONTROLLER:Lorg/apache/hadoop/hbase/security/access/AccessController;
      86: aload_1
      87: getstatic     #1                  // Field ACCESS_CONTROLLER:Lorg/apache/hadoop/hbase/security/access/AccessController;
      90: iconst_0
      91: iconst_1
      92: getstatic     #11                 // Field conf:Lorg/apache/hadoop/conf/Configuration;
      95: invokevirtual #30                 // Method org/apache/hadoop/hbase/master/MasterCoprocessorHost.createEnvironment:(Lorg/apache/hadoop/hbase/coprocessor/MasterCoprocessor;IILorg/apache/hadoop/conf/Configuration;)Lorg/apache/hadoop/hbase/master/MasterCoprocessorHost$MasterEnvironment;
      98: putstatic     #2                  // Field CP_ENV:Lorg/apache/hadoop/hbase/coprocessor/MasterCoprocessorEnvironment;
     101: getstatic     #9                  // Field TEST_UTIL:Lorg/apache/hadoop/hbase/HBaseTestingUtility;
     104: invokevirtual #23                 // Method org/apache/hadoop/hbase/HBaseTestingUtility.getMiniHBaseCluster:()Lorg/apache/hadoop/hbase/MiniHBaseCluster;
     107: iconst_0
     108: invokevirtual #31                 // Method org/apache/hadoop/hbase/MiniHBaseCluster.getRegionServer:(I)Lorg/apache/hadoop/hbase/regionserver/HRegionServer;
     111: invokevirtual #32                 // Method org/apache/hadoop/hbase/regionserver/HRegionServer.getRegionServerCoprocessorHost:()Lorg/apache/hadoop/hbase/regionserver/RegionServerCoprocessorHost;
     114: astore_2
     115: aload_2
     116: ifnull        101
     119: aload_2
     120: getstatic     #1                  // Field ACCESS_CONTROLLER:Lorg/apache/hadoop/hbase/security/access/AccessController;
     123: iconst_0
     124: iconst_1
     125: getstatic     #11                 // Field conf:Lorg/apache/hadoop/conf/Configuration;
     128: invokevirtual #33                 // Method org/apache/hadoop/hbase/regionserver/RegionServerCoprocessorHost.createEnvironment:(Lorg/apache/hadoop/hbase/coprocessor/RegionServerCoprocessor;IILorg/apache/hadoop/conf/Configuration;)Lorg/apache/hadoop/hbase/regionserver/RegionServerCoprocessorHost$RegionServerEnvironment;
     131: putstatic     #34                 // Field RSCP_ENV:Lorg/apache/hadoop/hbase/coprocessor/RegionServerCoprocessorEnvironment;
     134: getstatic     #9                  // Field TEST_UTIL:Lorg/apache/hadoop/hbase/HBaseTestingUtility;
     137: getstatic     #35                 // Field org/apache/hadoop/hbase/security/access/PermissionStorage.ACL_TABLE_NAME:Lorg/apache/hadoop/hbase/TableName;
     140: invokevirtual #36                 // Method org/apache/hadoop/hbase/HBaseTestingUtility.waitUntilAllRegionsAssigned:(Lorg/apache/hadoop/hbase/TableName;)V
     143: getstatic     #11                 // Field conf:Lorg/apache/hadoop/conf/Configuration;
     146: ldc           #37                 // String admin
     148: iconst_1
     149: anewarray     #38                 // class java/lang/String
     152: dup
     153: iconst_0
     154: ldc           #39                 // String supergroup
     156: aastore
     157: invokestatic  #40                 // Method org/apache/hadoop/hbase/security/User.createUserForTesting:(Lorg/apache/hadoop/conf/Configuration;Ljava/lang/String;[Ljava/lang/String;)Lorg/apache/hadoop/hbase/security/User;
     160: putstatic     #41                 // Field SUPERUSER:Lorg/apache/hadoop/hbase/security/User;
     163: getstatic     #11                 // Field conf:Lorg/apache/hadoop/conf/Configuration;
     166: ldc           #42                 // String admin2
     168: iconst_0
     169: anewarray     #38                 // class java/lang/String
     172: invokestatic  #40                 // Method org/apache/hadoop/hbase/security/User.createUserForTesting:(Lorg/apache/hadoop/conf/Configuration;Ljava/lang/String;[Ljava/lang/String;)Lorg/apache/hadoop/hbase/security/User;
     175: putstatic     #43                 // Field USER_ADMIN:Lorg/apache/hadoop/hbase/security/User;
     178: getstatic     #11                 // Field conf:Lorg/apache/hadoop/conf/Configuration;
     181: ldc           #44                 // String rwuser
     183: iconst_0
     184: anewarray     #38                 // class java/lang/String
     187: invokestatic  #40                 // Method org/apache/hadoop/hbase/security/User.createUserForTesting:(Lorg/apache/hadoop/conf/Configuration;Ljava/lang/String;[Ljava/lang/String;)Lorg/apache/hadoop/hbase/security/User;
     190: putstatic     #45                 // Field USER_RW:Lorg/apache/hadoop/hbase/security/User;
     193: getstatic     #11                 // Field conf:Lorg/apache/hadoop/conf/Configuration;
     196: ldc           #46                 // String rouser
     198: iconst_0
     199: anewarray     #38                 // class java/lang/String
     202: invokestatic  #40                 // Method org/apache/hadoop/hbase/security/User.createUserForTesting:(Lorg/apache/hadoop/conf/Configuration;Ljava/lang/String;[Ljava/lang/String;)Lorg/apache/hadoop/hbase/security/User;
     205: putstatic     #47                 // Field USER_RO:Lorg/apache/hadoop/hbase/security/User;
     208: getstatic     #11                 // Field conf:Lorg/apache/hadoop/conf/Configuration;
     211: ldc           #48                 // String owner
     213: iconst_0
     214: anewarray     #38                 // class java/lang/String
     217: invokestatic  #40                 // Method org/apache/hadoop/hbase/security/User.createUserForTesting:(Lorg/apache/hadoop/conf/Configuration;Ljava/lang/String;[Ljava/lang/String;)Lorg/apache/hadoop/hbase/security/User;
     220: putstatic     #49                 // Field USER_OWNER:Lorg/apache/hadoop/hbase/security/User;
     223: getstatic     #11                 // Field conf:Lorg/apache/hadoop/conf/Configuration;
     226: ldc           #50                 // String tbl_create
     228: iconst_0
     229: anewarray     #38                 // class java/lang/String
     232: invokestatic  #40                 // Method org/apache/hadoop/hbase/security/User.createUserForTesting:(Lorg/apache/hadoop/conf/Configuration;Ljava/lang/String;[Ljava/lang/String;)Lorg/apache/hadoop/hbase/security/User;
     235: putstatic     #51                 // Field USER_CREATE:Lorg/apache/hadoop/hbase/security/User;
     238: getstatic     #11                 // Field conf:Lorg/apache/hadoop/conf/Configuration;
     241: ldc           #52                 // String nouser
     243: iconst_0
     244: anewarray     #38                 // class java/lang/String
     247: invokestatic  #40                 // Method org/apache/hadoop/hbase/security/User.createUserForTesting:(Lorg/apache/hadoop/conf/Configuration;Ljava/lang/String;[Ljava/lang/String;)Lorg/apache/hadoop/hbase/security/User;
     250: putstatic     #53                 // Field USER_NONE:Lorg/apache/hadoop/hbase/security/User;
     253: getstatic     #11                 // Field conf:Lorg/apache/hadoop/conf/Configuration;
     256: ldc           #54                 // String col_family_admin
     258: iconst_0
     259: anewarray     #38                 // class java/lang/String
     262: invokestatic  #40                 // Method org/apache/hadoop/hbase/security/User.createUserForTesting:(Lorg/apache/hadoop/conf/Configuration;Ljava/lang/String;[Ljava/lang/String;)Lorg/apache/hadoop/hbase/security/User;
     265: putstatic     #55                 // Field USER_ADMIN_CF:Lorg/apache/hadoop/hbase/security/User;
     268: getstatic     #11                 // Field conf:Lorg/apache/hadoop/conf/Configuration;
     271: ldc           #56                 // String user_group_admin
     273: iconst_1
     274: anewarray     #38                 // class java/lang/String
     277: dup
     278: iconst_0
     279: ldc           #58                 // String group_admin
     281: aastore
     282: invokestatic  #40                 // Method org/apache/hadoop/hbase/security/User.createUserForTesting:(Lorg/apache/hadoop/conf/Configuration;Ljava/lang/String;[Ljava/lang/String;)Lorg/apache/hadoop/hbase/security/User;
     285: putstatic     #59                 // Field USER_GROUP_ADMIN:Lorg/apache/hadoop/hbase/security/User;
     288: getstatic     #11                 // Field conf:Lorg/apache/hadoop/conf/Configuration;
     291: ldc           #60                 // String user_group_create
     293: iconst_1
     294: anewarray     #38                 // class java/lang/String
     297: dup
     298: iconst_0
     299: ldc           #61                 // String group_create
     301: aastore
     302: invokestatic  #40                 // Method org/apache/hadoop/hbase/security/User.createUserForTesting:(Lorg/apache/hadoop/conf/Configuration;Ljava/lang/String;[Ljava/lang/String;)Lorg/apache/hadoop/hbase/security/User;
     305: putstatic     #62                 // Field USER_GROUP_CREATE:Lorg/apache/hadoop/hbase/security/User;
     308: getstatic     #11                 // Field conf:Lorg/apache/hadoop/conf/Configuration;
     311: ldc           #63                 // String user_group_read
     313: iconst_1
     314: anewarray     #38                 // class java/lang/String
     317: dup
     318: iconst_0
     319: ldc           #64                 // String group_read
     321: aastore
     322: invokestatic  #40                 // Method org/apache/hadoop/hbase/security/User.createUserForTesting:(Lorg/apache/hadoop/conf/Configuration;Ljava/lang/String;[Ljava/lang/String;)Lorg/apache/hadoop/hbase/security/User;
     325: putstatic     #65                 // Field USER_GROUP_READ:Lorg/apache/hadoop/hbase/security/User;
     328: getstatic     #11                 // Field conf:Lorg/apache/hadoop/conf/Configuration;
     331: ldc           #66                 // String user_group_write
     333: iconst_1
     334: anewarray     #38                 // class java/lang/String
     337: dup
     338: iconst_0
     339: ldc           #67                 // String group_write
     341: aastore
     342: invokestatic  #40                 // Method org/apache/hadoop/hbase/security/User.createUserForTesting:(Lorg/apache/hadoop/conf/Configuration;Ljava/lang/String;[Ljava/lang/String;)Lorg/apache/hadoop/hbase/security/User;
     345: putstatic     #68                 // Field USER_GROUP_WRITE:Lorg/apache/hadoop/hbase/security/User;
     348: getstatic     #9                  // Field TEST_UTIL:Lorg/apache/hadoop/hbase/HBaseTestingUtility;
     351: invokevirtual #69                 // Method org/apache/hadoop/hbase/HBaseTestingUtility.getConnection:()Lorg/apache/hadoop/hbase/client/Connection;
     354: putstatic     #70                 // Field systemUserConnection:Lorg/apache/hadoop/hbase/client/Connection;
     357: invokestatic  #71                 // Method setUpTableAndUserPermissions:()V
     360: return

  public static void tearDownAfterClass() throws java.lang.Exception;
    Code:
       0: aconst_null
       1: astore_0
       2: getstatic     #9                  // Field TEST_UTIL:Lorg/apache/hadoop/hbase/HBaseTestingUtility;
       5: invokevirtual #23                 // Method org/apache/hadoop/hbase/HBaseTestingUtility.getMiniHBaseCluster:()Lorg/apache/hadoop/hbase/MiniHBaseCluster;
       8: invokevirtual #72                 // Method org/apache/hadoop/hbase/MiniHBaseCluster.getRegionServerThreads:()Ljava/util/List;
      11: invokeinterface #73,  1           // InterfaceMethod java/util/List.iterator:()Ljava/util/Iterator;
      16: astore_1
      17: aload_1
      18: invokeinterface #74,  1           // InterfaceMethod java/util/Iterator.hasNext:()Z
      23: ifeq          44
      26: aload_1
      27: invokeinterface #75,  1           // InterfaceMethod java/util/Iterator.next:()Ljava/lang/Object;
      32: checkcast     #76                 // class org/apache/hadoop/hbase/util/JVMClusterUtil$RegionServerThread
      35: astore_2
      36: aload_2
      37: invokevirtual #77                 // Method org/apache/hadoop/hbase/util/JVMClusterUtil$RegionServerThread.getRegionServer:()Lorg/apache/hadoop/hbase/regionserver/HRegionServer;
      40: astore_0
      41: goto          17
      44: invokestatic  #78                 // Method cleanUp:()V
      47: getstatic     #9                  // Field TEST_UTIL:Lorg/apache/hadoop/hbase/HBaseTestingUtility;
      50: invokevirtual #79                 // Method org/apache/hadoop/hbase/HBaseTestingUtility.shutdownMiniCluster:()V
      53: ldc           #80                 // String region server should have aborted due to FaultyAccessController
      55: aload_0
      56: invokevirtual #81                 // Method org/apache/hadoop/hbase/regionserver/HRegionServer.isAborted:()Z
      59: invokestatic  #82                 // Method org/junit/Assert.assertFalse:(Ljava/lang/String;Z)V
      62: return

  public void testTableCreate() throws java.lang.Exception;
    Code:
       0: new           #134                // class org/apache/hadoop/hbase/security/access/TestAccessController3$1
       3: dup
       4: aload_0
       5: invokespecial #135                // Method org/apache/hadoop/hbase/security/access/TestAccessController3$1."<init>":(Lorg/apache/hadoop/hbase/security/access/TestAccessController3;)V
       8: astore_1
       9: aload_1
      10: iconst_3
      11: anewarray     #136                // class org/apache/hadoop/hbase/security/User
      14: dup
      15: iconst_0
      16: getstatic     #41                 // Field SUPERUSER:Lorg/apache/hadoop/hbase/security/User;
      19: aastore
      20: dup
      21: iconst_1
      22: getstatic     #43                 // Field USER_ADMIN:Lorg/apache/hadoop/hbase/security/User;
      25: aastore
      26: dup
      27: iconst_2
      28: getstatic     #62                 // Field USER_GROUP_CREATE:Lorg/apache/hadoop/hbase/security/User;
      31: aastore
      32: invokestatic  #137                // Method verifyAllowed:(Lorg/apache/hadoop/hbase/security/access/SecureTestUtil$AccessTestAction;[Lorg/apache/hadoop/hbase/security/User;)V
      35: aload_1
      36: bipush        7
      38: anewarray     #136                // class org/apache/hadoop/hbase/security/User
      41: dup
      42: iconst_0
      43: getstatic     #51                 // Field USER_CREATE:Lorg/apache/hadoop/hbase/security/User;
      46: aastore
      47: dup
      48: iconst_1
      49: getstatic     #45                 // Field USER_RW:Lorg/apache/hadoop/hbase/security/User;
      52: aastore
      53: dup
      54: iconst_2
      55: getstatic     #47                 // Field USER_RO:Lorg/apache/hadoop/hbase/security/User;
      58: aastore
      59: dup
      60: iconst_3
      61: getstatic     #53                 // Field USER_NONE:Lorg/apache/hadoop/hbase/security/User;
      64: aastore
      65: dup
      66: iconst_4
      67: getstatic     #59                 // Field USER_GROUP_ADMIN:Lorg/apache/hadoop/hbase/security/User;
      70: aastore
      71: dup
      72: iconst_5
      73: getstatic     #65                 // Field USER_GROUP_READ:Lorg/apache/hadoop/hbase/security/User;
      76: aastore
      77: dup
      78: bipush        6
      80: getstatic     #68                 // Field USER_GROUP_WRITE:Lorg/apache/hadoop/hbase/security/User;
      83: aastore
      84: invokestatic  #138                // Method verifyDenied:(Lorg/apache/hadoop/hbase/security/access/SecureTestUtil$AccessTestAction;[Lorg/apache/hadoop/hbase/security/User;)V
      87: return

  static boolean access$000();
    Code:
       0: getstatic     #4                  // Field callSuperTwice:Z
       3: ireturn

  static byte[] access$100();
    Code:
       0: getstatic     #3                  // Field TEST_FAMILY:[B
       3: areturn

  static org.apache.hadoop.hbase.coprocessor.MasterCoprocessorEnvironment access$200();
    Code:
       0: getstatic     #2                  // Field CP_ENV:Lorg/apache/hadoop/hbase/coprocessor/MasterCoprocessorEnvironment;
       3: areturn

  static org.apache.hadoop.hbase.security.access.AccessController access$300();
    Code:
       0: getstatic     #1                  // Field ACCESS_CONTROLLER:Lorg/apache/hadoop/hbase/security/access/AccessController;
       3: areturn

  static {};
    Code:
       0: ldc           #57                 // class org/apache/hadoop/hbase/security/access/TestAccessController3
       2: invokestatic  #139                // Method org/apache/hadoop/hbase/HBaseClassTestRule.forClass:(Ljava/lang/Class;)Lorg/apache/hadoop/hbase/HBaseClassTestRule;
       5: putstatic     #140                // Field CLASS_RULE:Lorg/apache/hadoop/hbase/HBaseClassTestRule;
       8: ldc           #141                // class org/apache/hadoop/hbase/security/access/TestAccessController
      10: invokestatic  #142                // Method org/slf4j/LoggerFactory.getLogger:(Ljava/lang/Class;)Lorg/slf4j/Logger;
      13: putstatic     #120                // Field LOG:Lorg/slf4j/Logger;
      16: ldc           #143                // String testtable1
      18: invokestatic  #144                // Method org/apache/hadoop/hbase/TableName.valueOf:(Ljava/lang/String;)Lorg/apache/hadoop/hbase/TableName;
      21: putstatic     #84                 // Field TEST_TABLE:Lorg/apache/hadoop/hbase/TableName;
      24: new           #145                // class org/apache/hadoop/hbase/HBaseTestingUtility
      27: dup
      28: invokespecial #146                // Method org/apache/hadoop/hbase/HBaseTestingUtility."<init>":()V
      31: putstatic     #9                  // Field TEST_UTIL:Lorg/apache/hadoop/hbase/HBaseTestingUtility;
      34: ldc           #147                // String f1
      36: invokestatic  #93                 // Method org/apache/hadoop/hbase/util/Bytes.toBytes:(Ljava/lang/String;)[B
      39: putstatic     #3                  // Field TEST_FAMILY:[B
      42: iconst_1
      43: putstatic     #4                  // Field callSuperTwice:Z
      46: return
}
