Compiled from "TestCoprocessorScanPolicy.java"
class org.apache.hadoop.hbase.util.TestCoprocessorScanPolicy$ScanObserver$1 extends org.apache.hadoop.hbase.regionserver.DelegatingInternalScanner {
  final java.lang.Long val$ttl;

  final java.lang.Integer val$version;

  final org.apache.hadoop.hbase.util.TestCoprocessorScanPolicy$ScanObserver this$0;

  org.apache.hadoop.hbase.util.TestCoprocessorScanPolicy$ScanObserver$1(org.apache.hadoop.hbase.util.TestCoprocessorScanPolicy$ScanObserver, org.apache.hadoop.hbase.regionserver.InternalScanner, java.lang.Long, java.lang.Integer);
    Code:
       0: aload_0
       1: aload_1
       2: putfield      #1                  // Field this$0:Lorg/apache/hadoop/hbase/util/TestCoprocessorScanPolicy$ScanObserver;
       5: aload_0
       6: aload_3
       7: putfield      #2                  // Field val$ttl:Ljava/lang/Long;
      10: aload_0
      11: aload         4
      13: putfield      #3                  // Field val$version:Ljava/lang/Integer;
      16: aload_0
      17: aload_2
      18: invokespecial #4                  // Method org/apache/hadoop/hbase/regionserver/DelegatingInternalScanner."<init>":(Lorg/apache/hadoop/hbase/regionserver/InternalScanner;)V
      21: return

  public boolean next(java.util.List<org.apache.hadoop.hbase.Cell>, org.apache.hadoop.hbase.regionserver.ScannerContext) throws java.io.IOException;
    Code:
       0: aload_0
       1: getfield      #12                 // Field scanner:Lorg/apache/hadoop/hbase/regionserver/InternalScanner;
       4: aload_1
       5: aload_2
       6: invokeinterface #13,  3           // InterfaceMethod org/apache/hadoop/hbase/regionserver/InternalScanner.next:(Ljava/util/List;Lorg/apache/hadoop/hbase/regionserver/ScannerContext;)Z
      11: istore_3
      12: aload_1
      13: invokeinterface #14,  1           // InterfaceMethod java/util/List.isEmpty:()Z
      18: ifeq          23
      21: iload_3
      22: ireturn
      23: invokestatic  #15                 // Method org/apache/hadoop/hbase/util/EnvironmentEdgeManager.currentTime:()J
      26: lstore        4
      28: aconst_null
      29: astore        6
      31: aload_0
      32: getfield      #2                  // Field val$ttl:Ljava/lang/Long;
      35: ifnull        53
      38: aload_0
      39: lload         4
      41: aload_0
      42: getfield      #2                  // Field val$ttl:Ljava/lang/Long;
      45: invokevirtual #16                 // Method java/lang/Long.longValue:()J
      48: invokespecial #17                 // Method checkTtl:(JJ)Ljava/util/function/Predicate;
      51: astore        6
      53: aload_0
      54: getfield      #3                  // Field val$version:Ljava/lang/Integer;
      57: ifnull        106
      60: aload_0
      61: aload_1
      62: iconst_0
      63: invokeinterface #18,  2           // InterfaceMethod java/util/List.get:(I)Ljava/lang/Object;
      68: checkcast     #19                 // class org/apache/hadoop/hbase/Cell
      71: aload_0
      72: getfield      #3                  // Field val$version:Ljava/lang/Integer;
      75: invokevirtual #20                 // Method java/lang/Integer.intValue:()I
      78: invokespecial #21                 // Method checkVersion:(Lorg/apache/hadoop/hbase/Cell;I)Ljava/util/function/Predicate;
      81: astore        7
      83: aload         6
      85: ifnull        102
      88: aload         6
      90: aload         7
      92: invokeinterface #22,  2           // InterfaceMethod java/util/function/Predicate.and:(Ljava/util/function/Predicate;)Ljava/util/function/Predicate;
      97: astore        6
      99: goto          106
     102: aload         7
     104: astore        6
     106: aload         6
     108: ifnull        120
     111: aload_1
     112: aload         6
     114: invokeinterface #23,  2           // InterfaceMethod java/util/List.removeIf:(Ljava/util/function/Predicate;)Z
     119: pop
     120: iload_3
     121: ireturn
}
