Compiled from "TestIncrementTimeRange.java"
public class org.apache.hadoop.hbase.coprocessor.TestIncrementTimeRange$MyObserver extends org.apache.hadoop.hbase.coprocessor.SimpleRegionObserver {
  static org.apache.hadoop.hbase.io.TimeRange tr10;

  static org.apache.hadoop.hbase.io.TimeRange tr2;

  public org.apache.hadoop.hbase.coprocessor.TestIncrementTimeRange$MyObserver();
    Code:
       0: aload_0
       1: invokespecial #1                  // Method org/apache/hadoop/hbase/coprocessor/SimpleRegionObserver."<init>":()V
       4: return

  public org.apache.hadoop.hbase.client.Result preIncrement(org.apache.hadoop.hbase.coprocessor.ObserverContext<org.apache.hadoop.hbase.coprocessor.RegionCoprocessorEnvironment>, org.apache.hadoop.hbase.client.Increment) throws java.io.IOException;
    Code:
       0: aload_2
       1: invokevirtual #2                  // Method org/apache/hadoop/hbase/client/Increment.getFamilyCellMap:()Ljava/util/NavigableMap;
       4: astore_3
       5: aload_3
       6: invokeinterface #3,  1            // InterfaceMethod java/util/NavigableMap.entrySet:()Ljava/util/Set;
      11: invokeinterface #4,  1            // InterfaceMethod java/util/Set.iterator:()Ljava/util/Iterator;
      16: astore        4
      18: aload         4
      20: invokeinterface #5,  1            // InterfaceMethod java/util/Iterator.hasNext:()Z
      25: ifeq          156
      28: aload         4
      30: invokeinterface #6,  1            // InterfaceMethod java/util/Iterator.next:()Ljava/lang/Object;
      35: checkcast     #7                  // class java/util/Map$Entry
      38: astore        5
      40: aload         5
      42: invokeinterface #8,  1            // InterfaceMethod java/util/Map$Entry.getValue:()Ljava/lang/Object;
      47: checkcast     #9                  // class java/util/List
      50: invokeinterface #10,  1           // InterfaceMethod java/util/List.iterator:()Ljava/util/Iterator;
      55: astore        6
      57: aload         6
      59: invokeinterface #5,  1            // InterfaceMethod java/util/Iterator.hasNext:()Z
      64: ifeq          153
      67: aload         6
      69: invokeinterface #6,  1            // InterfaceMethod java/util/Iterator.next:()Ljava/lang/Object;
      74: checkcast     #11                 // class org/apache/hadoop/hbase/Cell
      77: astore        7
      79: aload         7
      81: invokeinterface #12,  1           // InterfaceMethod org/apache/hadoop/hbase/Cell.getValueArray:()[B
      86: aload         7
      88: invokeinterface #13,  1           // InterfaceMethod org/apache/hadoop/hbase/Cell.getValueOffset:()I
      93: aload         7
      95: invokeinterface #14,  1           // InterfaceMethod org/apache/hadoop/hbase/Cell.getValueLength:()I
     100: invokestatic  #15                 // Method org/apache/hadoop/hbase/util/Bytes.toLong:([BII)J
     103: lstore        8
     105: lload         8
     107: ldc2_w        #16                 // long 10l
     110: lcmp
     111: ifne          124
     114: aload_2
     115: invokevirtual #18                 // Method org/apache/hadoop/hbase/client/Increment.getTimeRange:()Lorg/apache/hadoop/hbase/io/TimeRange;
     118: putstatic     #19                 // Field tr10:Lorg/apache/hadoop/hbase/io/TimeRange;
     121: goto          150
     124: lload         8
     126: ldc2_w        #20                 // long 2l
     129: lcmp
     130: ifne          150
     133: aload_2
     134: invokevirtual #18                 // Method org/apache/hadoop/hbase/client/Increment.getTimeRange:()Lorg/apache/hadoop/hbase/io/TimeRange;
     137: invokevirtual #22                 // Method org/apache/hadoop/hbase/io/TimeRange.isAllTime:()Z
     140: ifne          150
     143: aload_2
     144: invokevirtual #18                 // Method org/apache/hadoop/hbase/client/Increment.getTimeRange:()Lorg/apache/hadoop/hbase/io/TimeRange;
     147: putstatic     #23                 // Field tr2:Lorg/apache/hadoop/hbase/io/TimeRange;
     150: goto          57
     153: goto          18
     156: aload_0
     157: aload_1
     158: aload_2
     159: invokespecial #24                 // Method org/apache/hadoop/hbase/coprocessor/SimpleRegionObserver.preIncrement:(Lorg/apache/hadoop/hbase/coprocessor/ObserverContext;Lorg/apache/hadoop/hbase/client/Increment;)Lorg/apache/hadoop/hbase/client/Result;
     162: areturn

  static {};
    Code:
       0: aconst_null
       1: putstatic     #19                 // Field tr10:Lorg/apache/hadoop/hbase/io/TimeRange;
       4: aconst_null
       5: putstatic     #23                 // Field tr2:Lorg/apache/hadoop/hbase/io/TimeRange;
       8: return
}
