Compiled from "TestProcedureSchedulerConcurrency.java"
public class org.apache.hadoop.hbase.procedure2.TestProcedureSchedulerConcurrency {
  public static final org.apache.hadoop.hbase.HBaseClassTestRule CLASS_RULE;

  public org.apache.hadoop.hbase.procedure2.TestProcedureSchedulerConcurrency();
    Code:
       0: aload_0
       1: invokespecial #3                  // Method java/lang/Object."<init>":()V
       4: return

  public void setUp() throws java.io.IOException;
    Code:
       0: aload_0
       1: new           #4                  // class org/apache/hadoop/hbase/procedure2/SimpleProcedureScheduler
       4: dup
       5: invokespecial #5                  // Method org/apache/hadoop/hbase/procedure2/SimpleProcedureScheduler."<init>":()V
       8: putfield      #1                  // Field procSched:Lorg/apache/hadoop/hbase/procedure2/SimpleProcedureScheduler;
      11: aload_0
      12: getfield      #1                  // Field procSched:Lorg/apache/hadoop/hbase/procedure2/SimpleProcedureScheduler;
      15: invokevirtual #6                  // Method org/apache/hadoop/hbase/procedure2/SimpleProcedureScheduler.start:()V
      18: return

  public void tearDown() throws java.io.IOException;
    Code:
       0: aload_0
       1: getfield      #1                  // Field procSched:Lorg/apache/hadoop/hbase/procedure2/SimpleProcedureScheduler;
       4: invokevirtual #7                  // Method org/apache/hadoop/hbase/procedure2/SimpleProcedureScheduler.stop:()V
       7: return

  public void testConcurrentWaitWake() throws java.lang.Exception;
    Code:
       0: aload_0
       1: iconst_0
       2: invokespecial #8                  // Method testConcurrentWaitWake:(Z)V
       5: return

  public void testConcurrentWaitWakeBatch() throws java.lang.Exception;
    Code:
       0: aload_0
       1: iconst_1
       2: invokespecial #8                  // Method testConcurrentWaitWake:(Z)V
       5: return

  static org.slf4j.Logger access$000();
    Code:
       0: getstatic     #2                  // Field LOG:Lorg/slf4j/Logger;
       3: areturn

  static org.apache.hadoop.hbase.procedure2.SimpleProcedureScheduler access$100(org.apache.hadoop.hbase.procedure2.TestProcedureSchedulerConcurrency);
    Code:
       0: aload_0
       1: getfield      #1                  // Field procSched:Lorg/apache/hadoop/hbase/procedure2/SimpleProcedureScheduler;
       4: areturn

  static {};
    Code:
       0: ldc           #26                 // class org/apache/hadoop/hbase/procedure2/TestProcedureSchedulerConcurrency
       2: invokestatic  #27                 // Method org/apache/hadoop/hbase/HBaseClassTestRule.forClass:(Ljava/lang/Class;)Lorg/apache/hadoop/hbase/HBaseClassTestRule;
       5: putstatic     #28                 // Field CLASS_RULE:Lorg/apache/hadoop/hbase/HBaseClassTestRule;
       8: ldc           #29                 // class org/apache/hadoop/hbase/procedure2/TestProcedureEvents
      10: invokestatic  #30                 // Method org/slf4j/LoggerFactory.getLogger:(Ljava/lang/Class;)Lorg/slf4j/Logger;
      13: putstatic     #2                  // Field LOG:Lorg/slf4j/Logger;
      16: return
}
