Compiled from "TestSplitTransactionOnCluster.java"
class org.apache.hadoop.hbase.regionserver.TestSplitTransactionOnCluster$MyMasterRpcServices extends org.apache.hadoop.hbase.master.MasterRpcServices {
  static java.util.concurrent.atomic.AtomicBoolean enabled;

  public org.apache.hadoop.hbase.regionserver.TestSplitTransactionOnCluster$MyMasterRpcServices(org.apache.hadoop.hbase.master.HMaster) throws java.io.IOException;
    Code:
       0: aload_0
       1: aload_1
       2: invokespecial #1                  // Method org/apache/hadoop/hbase/master/MasterRpcServices."<init>":(Lorg/apache/hadoop/hbase/master/HMaster;)V
       5: aload_0
       6: aload_1
       7: putfield      #2                  // Field myMaster:Lorg/apache/hadoop/hbase/master/HMaster;
      10: return

  public org.apache.hadoop.hbase.shaded.protobuf.generated.RegionServerStatusProtos$ReportRegionStateTransitionResponse reportRegionStateTransition(org.apache.hbase.thirdparty.com.google.protobuf.RpcController, org.apache.hadoop.hbase.shaded.protobuf.generated.RegionServerStatusProtos$ReportRegionStateTransitionRequest) throws org.apache.hbase.thirdparty.com.google.protobuf.ServiceException;
    Code:
       0: aload_0
       1: aload_1
       2: aload_2
       3: invokespecial #3                  // Method org/apache/hadoop/hbase/master/MasterRpcServices.reportRegionStateTransition:(Lorg/apache/hbase/thirdparty/com/google/protobuf/RpcController;Lorg/apache/hadoop/hbase/shaded/protobuf/generated/RegionServerStatusProtos$ReportRegionStateTransitionRequest;)Lorg/apache/hadoop/hbase/shaded/protobuf/generated/RegionServerStatusProtos$ReportRegionStateTransitionResponse;
       6: astore_3
       7: getstatic     #4                  // Field enabled:Ljava/util/concurrent/atomic/AtomicBoolean;
      10: invokevirtual #5                  // Method java/util/concurrent/atomic/AtomicBoolean.get:()Z
      13: ifeq          89
      16: aload_2
      17: iconst_0
      18: invokevirtual #6                  // Method org/apache/hadoop/hbase/shaded/protobuf/generated/RegionServerStatusProtos$ReportRegionStateTransitionRequest.getTransition:(I)Lorg/apache/hadoop/hbase/shaded/protobuf/generated/RegionServerStatusProtos$RegionStateTransition;
      21: invokevirtual #7                  // Method org/apache/hadoop/hbase/shaded/protobuf/generated/RegionServerStatusProtos$RegionStateTransition.getTransitionCode:()Lorg/apache/hadoop/hbase/shaded/protobuf/generated/RegionServerStatusProtos$RegionStateTransition$TransitionCode;
      24: getstatic     #8                  // Field org/apache/hadoop/hbase/shaded/protobuf/generated/RegionServerStatusProtos$RegionStateTransition$TransitionCode.READY_TO_SPLIT:Lorg/apache/hadoop/hbase/shaded/protobuf/generated/RegionServerStatusProtos$RegionStateTransition$TransitionCode;
      27: invokevirtual #9                  // Method org/apache/hadoop/hbase/shaded/protobuf/generated/RegionServerStatusProtos$RegionStateTransition$TransitionCode.equals:(Ljava/lang/Object;)Z
      30: ifeq          89
      33: aload_3
      34: invokevirtual #10                 // Method org/apache/hadoop/hbase/shaded/protobuf/generated/RegionServerStatusProtos$ReportRegionStateTransitionResponse.hasErrorMessage:()Z
      37: ifne          89
      40: aload_0
      41: getfield      #2                  // Field myMaster:Lorg/apache/hadoop/hbase/master/HMaster;
      44: invokevirtual #11                 // Method org/apache/hadoop/hbase/master/HMaster.getAssignmentManager:()Lorg/apache/hadoop/hbase/master/assignment/AssignmentManager;
      47: invokevirtual #12                 // Method org/apache/hadoop/hbase/master/assignment/AssignmentManager.getRegionStates:()Lorg/apache/hadoop/hbase/master/assignment/RegionStates;
      50: astore        4
      52: aload         4
      54: invokevirtual #13                 // Method org/apache/hadoop/hbase/master/assignment/RegionStates.getRegionsInTransition:()Ljava/util/List;
      57: invokeinterface #14,  1           // InterfaceMethod java/util/List.iterator:()Ljava/util/Iterator;
      62: astore        5
      64: aload         5
      66: invokeinterface #15,  1           // InterfaceMethod java/util/Iterator.hasNext:()Z
      71: ifeq          89
      74: aload         5
      76: invokeinterface #16,  1           // InterfaceMethod java/util/Iterator.next:()Ljava/lang/Object;
      81: checkcast     #17                 // class org/apache/hadoop/hbase/master/assignment/RegionStateNode
      84: astore        6
      86: goto          64
      89: aload_3
      90: areturn

  static {};
    Code:
       0: new           #18                 // class java/util/concurrent/atomic/AtomicBoolean
       3: dup
       4: iconst_0
       5: invokespecial #19                 // Method java/util/concurrent/atomic/AtomicBoolean."<init>":(Z)V
       8: putstatic     #4                  // Field enabled:Ljava/util/concurrent/atomic/AtomicBoolean;
      11: return
}
