Compiled from "TestClientExceptionsUtil.java"
public class org.apache.hadoop.hbase.exceptions.TestClientExceptionsUtil {
  public static final org.apache.hadoop.hbase.HBaseClassTestRule CLASS_RULE;

  public org.apache.hadoop.hbase.exceptions.TestClientExceptionsUtil();
    Code:
       0: aload_0
       1: invokespecial #1                  // Method java/lang/Object."<init>":()V
       4: return

  public void testFindException() throws java.lang.Exception;
    Code:
       0: new           #2                  // class java/io/IOException
       3: dup
       4: ldc           #3                  // String Tesst
       6: invokespecial #4                  // Method java/io/IOException."<init>":(Ljava/lang/String;)V
       9: astore_1
      10: new           #5                  // class org/apache/hbase/thirdparty/com/google/protobuf/ServiceException
      13: dup
      14: aload_1
      15: invokespecial #6                  // Method org/apache/hbase/thirdparty/com/google/protobuf/ServiceException."<init>":(Ljava/lang/Throwable;)V
      18: astore_2
      19: aload_1
      20: aload_2
      21: invokestatic  #7                  // Method org/apache/hadoop/hbase/exceptions/ClientExceptionsUtil.findException:(Ljava/lang/Object;)Ljava/lang/Throwable;
      24: invokestatic  #8                  // Method org/junit/Assert.assertEquals:(Ljava/lang/Object;Ljava/lang/Object;)V
      27: return

  static {};
    Code:
       0: ldc           #9                  // class org/apache/hadoop/hbase/exceptions/TestClientExceptionsUtil
       2: invokestatic  #10                 // Method org/apache/hadoop/hbase/HBaseClassTestRule.forClass:(Ljava/lang/Class;)Lorg/apache/hadoop/hbase/HBaseClassTestRule;
       5: putstatic     #11                 // Field CLASS_RULE:Lorg/apache/hadoop/hbase/HBaseClassTestRule;
       8: return
}
