Compiled from "TestCellACLWithMultipleVersions.java"
class org.apache.hadoop.hbase.security.access.TestCellACLWithMultipleVersions$29 implements java.security.PrivilegedExceptionAction<java.lang.Void> {
  final byte[] val$row;

  final byte[] val$value;

  final org.apache.hadoop.hbase.security.User val$user;

  final org.apache.hadoop.hbase.security.access.TestCellACLWithMultipleVersions this$0;

  org.apache.hadoop.hbase.security.access.TestCellACLWithMultipleVersions$29(org.apache.hadoop.hbase.security.access.TestCellACLWithMultipleVersions, byte[], byte[], org.apache.hadoop.hbase.security.User);
    Code:
       0: aload_0
       1: aload_1
       2: putfield      #1                  // Field this$0:Lorg/apache/hadoop/hbase/security/access/TestCellACLWithMultipleVersions;
       5: aload_0
       6: aload_2
       7: putfield      #2                  // Field val$row:[B
      10: aload_0
      11: aload_3
      12: putfield      #3                  // Field val$value:[B
      15: aload_0
      16: aload         4
      18: putfield      #4                  // Field val$user:Lorg/apache/hadoop/hbase/security/User;
      21: aload_0
      22: invokespecial #5                  // Method java/lang/Object."<init>":()V
      25: return

  public java.lang.Void run() throws java.lang.Exception;
    Code:
       0: invokestatic  #6                  // Method org/apache/hadoop/hbase/security/access/TestCellACLWithMultipleVersions.access$000:()Lorg/apache/hadoop/conf/Configuration;
       3: invokestatic  #7                  // Method org/apache/hadoop/hbase/client/ConnectionFactory.createConnection:(Lorg/apache/hadoop/conf/Configuration;)Lorg/apache/hadoop/hbase/client/Connection;
       6: astore_1
       7: aconst_null
       8: astore_2
       9: aload_1
      10: aload_0
      11: getfield      #1                  // Field this$0:Lorg/apache/hadoop/hbase/security/access/TestCellACLWithMultipleVersions;
      14: getfield      #8                  // Field org/apache/hadoop/hbase/security/access/TestCellACLWithMultipleVersions.TEST_TABLE:Lorg/apache/hadoop/hbase/TestTableName;
      17: invokevirtual #9                  // Method org/apache/hadoop/hbase/TestTableName.getTableName:()Lorg/apache/hadoop/hbase/TableName;
      20: invokeinterface #10,  2           // InterfaceMethod org/apache/hadoop/hbase/client/Connection.getTable:(Lorg/apache/hadoop/hbase/TableName;)Lorg/apache/hadoop/hbase/client/Table;
      25: astore_3
      26: aconst_null
      27: astore        4
      29: new           #11                 // class org/apache/hadoop/hbase/client/Delete
      32: dup
      33: aload_0
      34: getfield      #2                  // Field val$row:[B
      37: invokespecial #12                 // Method org/apache/hadoop/hbase/client/Delete."<init>":([B)V
      40: astore        5
      42: aload         5
      44: invokestatic  #13                 // Method org/apache/hadoop/hbase/security/access/TestCellACLWithMultipleVersions.access$100:()[B
      47: invokestatic  #14                 // Method org/apache/hadoop/hbase/security/access/TestCellACLWithMultipleVersions.access$200:()[B
      50: invokevirtual #15                 // Method org/apache/hadoop/hbase/client/Delete.addColumns:([B[B)Lorg/apache/hadoop/hbase/client/Delete;
      53: pop
      54: aload_3
      55: aload_0
      56: getfield      #2                  // Field val$row:[B
      59: invokestatic  #13                 // Method org/apache/hadoop/hbase/security/access/TestCellACLWithMultipleVersions.access$100:()[B
      62: invokeinterface #16,  3           // InterfaceMethod org/apache/hadoop/hbase/client/Table.checkAndMutate:([B[B)Lorg/apache/hadoop/hbase/client/Table$CheckAndMutateBuilder;
      67: invokestatic  #14                 // Method org/apache/hadoop/hbase/security/access/TestCellACLWithMultipleVersions.access$200:()[B
      70: invokeinterface #17,  2           // InterfaceMethod org/apache/hadoop/hbase/client/Table$CheckAndMutateBuilder.qualifier:([B)Lorg/apache/hadoop/hbase/client/Table$CheckAndMutateBuilder;
      75: aload_0
      76: getfield      #3                  // Field val$value:[B
      79: invokeinterface #18,  2           // InterfaceMethod org/apache/hadoop/hbase/client/Table$CheckAndMutateBuilder.ifEquals:([B)Lorg/apache/hadoop/hbase/client/Table$CheckAndMutateBuilder;
      84: aload         5
      86: invokeinterface #19,  2           // InterfaceMethod org/apache/hadoop/hbase/client/Table$CheckAndMutateBuilder.thenDelete:(Lorg/apache/hadoop/hbase/client/Delete;)Z
      91: pop
      92: new           #20                 // class java/lang/StringBuilder
      95: dup
      96: invokespecial #21                 // Method java/lang/StringBuilder."<init>":()V
      99: aload_0
     100: getfield      #4                  // Field val$user:Lorg/apache/hadoop/hbase/security/User;
     103: invokevirtual #22                 // Method org/apache/hadoop/hbase/security/User.getShortName:()Ljava/lang/String;
     106: invokevirtual #23                 // Method java/lang/StringBuilder.append:(Ljava/lang/String;)Ljava/lang/StringBuilder;
     109: ldc           #24                 // String  should not be allowed to do checkAndDelete
     111: invokevirtual #23                 // Method java/lang/StringBuilder.append:(Ljava/lang/String;)Ljava/lang/StringBuilder;
     114: invokevirtual #25                 // Method java/lang/StringBuilder.toString:()Ljava/lang/String;
     117: invokestatic  #26                 // Method org/junit/Assert.fail:(Ljava/lang/String;)V
     120: aload_3
     121: ifnull        209
     124: aload         4
     126: ifnull        150
     129: aload_3
     130: invokeinterface #27,  1           // InterfaceMethod org/apache/hadoop/hbase/client/Table.close:()V
     135: goto          209
     138: astore        5
     140: aload         4
     142: aload         5
     144: invokevirtual #29                 // Method java/lang/Throwable.addSuppressed:(Ljava/lang/Throwable;)V
     147: goto          209
     150: aload_3
     151: invokeinterface #27,  1           // InterfaceMethod org/apache/hadoop/hbase/client/Table.close:()V
     156: goto          209
     159: astore        5
     161: aload         5
     163: astore        4
     165: aload         5
     167: athrow
     168: astore        6
     170: aload_3
     171: ifnull        206
     174: aload         4
     176: ifnull        200
     179: aload_3
     180: invokeinterface #27,  1           // InterfaceMethod org/apache/hadoop/hbase/client/Table.close:()V
     185: goto          206
     188: astore        7
     190: aload         4
     192: aload         7
     194: invokevirtual #29                 // Method java/lang/Throwable.addSuppressed:(Ljava/lang/Throwable;)V
     197: goto          206
     200: aload_3
     201: invokeinterface #27,  1           // InterfaceMethod org/apache/hadoop/hbase/client/Table.close:()V
     206: aload         6
     208: athrow
     209: goto          213
     212: astore_3
     213: aload_1
     214: ifnull        292
     217: aload_2
     218: ifnull        239
     221: aload_1
     222: invokeinterface #31,  1           // InterfaceMethod org/apache/hadoop/hbase/client/Connection.close:()V
     227: goto          292
     230: astore_3
     231: aload_2
     232: aload_3
     233: invokevirtual #29                 // Method java/lang/Throwable.addSuppressed:(Ljava/lang/Throwable;)V
     236: goto          292
     239: aload_1
     240: invokeinterface #31,  1           // InterfaceMethod org/apache/hadoop/hbase/client/Connection.close:()V
     245: goto          292
     248: astore_3
     249: aload_3
     250: astore_2
     251: aload_3
     252: athrow
     253: astore        8
     255: aload_1
     256: ifnull        289
     259: aload_2
     260: ifnull        283
     263: aload_1
     264: invokeinterface #31,  1           // InterfaceMethod org/apache/hadoop/hbase/client/Connection.close:()V
     269: goto          289
     272: astore        9
     274: aload_2
     275: aload         9
     277: invokevirtual #29                 // Method java/lang/Throwable.addSuppressed:(Ljava/lang/Throwable;)V
     280: goto          289
     283: aload_1
     284: invokeinterface #31,  1           // InterfaceMethod org/apache/hadoop/hbase/client/Connection.close:()V
     289: aload         8
     291: athrow
     292: aconst_null
     293: areturn
    Exception table:
       from    to  target type
         129   135   138   Class java/lang/Throwable
          29   120   159   Class java/lang/Throwable
          29   120   168   any
         179   185   188   Class java/lang/Throwable
         159   170   168   any
           9   209   212   Class java/lang/Exception
         221   227   230   Class java/lang/Throwable
           9   213   248   Class java/lang/Throwable
           9   213   253   any
         263   269   272   Class java/lang/Throwable
         248   255   253   any

  public java.lang.Object run() throws java.lang.Exception;
    Code:
       0: aload_0
       1: invokevirtual #32                 // Method run:()Ljava/lang/Void;
       4: areturn
}
