Compiled from "TestKeyLocker.java"
public class org.apache.hadoop.hbase.util.TestKeyLocker {
  public static final org.apache.hadoop.hbase.HBaseClassTestRule CLASS_RULE;

  public org.apache.hadoop.hbase.util.TestKeyLocker();
    Code:
       0: aload_0
       1: invokespecial #1                  // Method java/lang/Object."<init>":()V
       4: return

  public void testLocker();
    Code:
       0: new           #2                  // class org/apache/hadoop/hbase/util/KeyLocker
       3: dup
       4: invokespecial #3                  // Method org/apache/hadoop/hbase/util/KeyLocker."<init>":()V
       7: astore_1
       8: aload_1
       9: ldc           #4                  // String l1
      11: invokevirtual #5                  // Method org/apache/hadoop/hbase/util/KeyLocker.acquireLock:(Ljava/lang/Object;)Ljava/util/concurrent/locks/ReentrantLock;
      14: astore_2
      15: aload_2
      16: invokevirtual #6                  // Method java/util/concurrent/locks/ReentrantLock.isHeldByCurrentThread:()Z
      19: invokestatic  #7                  // Method org/junit/Assert.assertTrue:(Z)V
      22: aload_1
      23: ldc           #8                  // String l2
      25: invokevirtual #5                  // Method org/apache/hadoop/hbase/util/KeyLocker.acquireLock:(Ljava/lang/Object;)Ljava/util/concurrent/locks/ReentrantLock;
      28: astore_3
      29: aload_3
      30: invokevirtual #6                  // Method java/util/concurrent/locks/ReentrantLock.isHeldByCurrentThread:()Z
      33: invokestatic  #7                  // Method org/junit/Assert.assertTrue:(Z)V
      36: aload_2
      37: aload_3
      38: if_acmpeq     45
      41: iconst_1
      42: goto          46
      45: iconst_0
      46: invokestatic  #7                  // Method org/junit/Assert.assertTrue:(Z)V
      49: aload_1
      50: ldc           #8                  // String l2
      52: invokevirtual #5                  // Method org/apache/hadoop/hbase/util/KeyLocker.acquireLock:(Ljava/lang/Object;)Ljava/util/concurrent/locks/ReentrantLock;
      55: astore        4
      57: aload         4
      59: aload_3
      60: if_acmpne     67
      63: iconst_1
      64: goto          68
      67: iconst_0
      68: invokestatic  #7                  // Method org/junit/Assert.assertTrue:(Z)V
      71: aload_3
      72: invokevirtual #6                  // Method java/util/concurrent/locks/ReentrantLock.isHeldByCurrentThread:()Z
      75: invokestatic  #7                  // Method org/junit/Assert.assertTrue:(Z)V
      78: aload         4
      80: invokevirtual #6                  // Method java/util/concurrent/locks/ReentrantLock.isHeldByCurrentThread:()Z
      83: invokestatic  #7                  // Method org/junit/Assert.assertTrue:(Z)V
      86: aload         4
      88: invokevirtual #9                  // Method java/util/concurrent/locks/ReentrantLock.unlock:()V
      91: aload         4
      93: invokevirtual #6                  // Method java/util/concurrent/locks/ReentrantLock.isHeldByCurrentThread:()Z
      96: invokestatic  #7                  // Method org/junit/Assert.assertTrue:(Z)V
      99: aload_3
     100: invokevirtual #9                  // Method java/util/concurrent/locks/ReentrantLock.unlock:()V
     103: aload         4
     105: invokevirtual #6                  // Method java/util/concurrent/locks/ReentrantLock.isHeldByCurrentThread:()Z
     108: invokestatic  #10                 // Method org/junit/Assert.assertFalse:(Z)V
     111: aload_3
     112: invokestatic  #11                 // Method java/lang/System.identityHashCode:(Ljava/lang/Object;)I
     115: istore        5
     117: aconst_null
     118: astore_3
     119: aconst_null
     120: astore        4
     122: invokestatic  #12                 // Method java/lang/System.gc:()V
     125: invokestatic  #12                 // Method java/lang/System.gc:()V
     128: invokestatic  #12                 // Method java/lang/System.gc:()V
     131: aload_1
     132: ldc           #8                  // String l2
     134: invokevirtual #5                  // Method org/apache/hadoop/hbase/util/KeyLocker.acquireLock:(Ljava/lang/Object;)Ljava/util/concurrent/locks/ReentrantLock;
     137: astore        6
     139: iload         5
     141: i2l
     142: aload         6
     144: invokestatic  #11                 // Method java/lang/System.identityHashCode:(Ljava/lang/Object;)I
     147: i2l
     148: invokestatic  #13                 // Method org/junit/Assert.assertNotEquals:(JJ)V
     151: aload         6
     153: invokevirtual #9                  // Method java/util/concurrent/locks/ReentrantLock.unlock:()V
     156: aload         6
     158: invokevirtual #6                  // Method java/util/concurrent/locks/ReentrantLock.isHeldByCurrentThread:()Z
     161: invokestatic  #10                 // Method org/junit/Assert.assertFalse:(Z)V
     164: aload_2
     165: invokevirtual #6                  // Method java/util/concurrent/locks/ReentrantLock.isHeldByCurrentThread:()Z
     168: invokestatic  #7                  // Method org/junit/Assert.assertTrue:(Z)V
     171: aload_2
     172: invokevirtual #9                  // Method java/util/concurrent/locks/ReentrantLock.unlock:()V
     175: aload_2
     176: invokevirtual #6                  // Method java/util/concurrent/locks/ReentrantLock.isHeldByCurrentThread:()Z
     179: invokestatic  #10                 // Method org/junit/Assert.assertFalse:(Z)V
     182: return

  static {};
    Code:
       0: ldc           #14                 // class org/apache/hadoop/hbase/util/TestKeyLocker
       2: invokestatic  #15                 // Method org/apache/hadoop/hbase/HBaseClassTestRule.forClass:(Ljava/lang/Class;)Lorg/apache/hadoop/hbase/HBaseClassTestRule;
       5: putstatic     #16                 // Field CLASS_RULE:Lorg/apache/hadoop/hbase/HBaseClassTestRule;
       8: return
}
