Compiled from "TestMasterNoCluster.java"
class org.apache.hadoop.hbase.master.TestMasterNoCluster$2 extends org.apache.hadoop.hbase.master.HMaster {
  final org.apache.hadoop.hbase.ServerName[] val$sns;

  final org.apache.hadoop.hbase.client.ClusterConnection val$mockedConnection;

  final org.apache.hadoop.hbase.master.TestMasterNoCluster this$0;

  org.apache.hadoop.hbase.master.TestMasterNoCluster$2(org.apache.hadoop.hbase.master.TestMasterNoCluster, org.apache.hadoop.conf.Configuration, org.apache.hadoop.hbase.ServerName[], org.apache.hadoop.hbase.client.ClusterConnection);
    Code:
       0: aload_0
       1: aload_1
       2: putfield      #1                  // Field this$0:Lorg/apache/hadoop/hbase/master/TestMasterNoCluster;
       5: aload_0
       6: aload_3
       7: putfield      #2                  // Field val$sns:[Lorg/apache/hadoop/hbase/ServerName;
      10: aload_0
      11: aload         4
      13: putfield      #3                  // Field val$mockedConnection:Lorg/apache/hadoop/hbase/client/ClusterConnection;
      16: aload_0
      17: aload_2
      18: invokespecial #4                  // Method org/apache/hadoop/hbase/master/HMaster."<init>":(Lorg/apache/hadoop/conf/Configuration;)V
      21: return

  java.net.InetAddress getRemoteInetAddress(int, long) throws java.net.UnknownHostException;
    Code:
       0: iload_1
       1: aload_0
       2: getfield      #2                  // Field val$sns:[Lorg/apache/hadoop/hbase/ServerName;
       5: arraylength
       6: if_icmple     16
       9: aload_0
      10: iload_1
      11: lload_2
      12: invokespecial #5                  // Method org/apache/hadoop/hbase/master/HMaster.getRemoteInetAddress:(IJ)Ljava/net/InetAddress;
      15: areturn
      16: aload_0
      17: getfield      #2                  // Field val$sns:[Lorg/apache/hadoop/hbase/ServerName;
      20: iload_1
      21: aaload
      22: astore        4
      24: aload         4
      26: invokevirtual #6                  // Method org/apache/hadoop/hbase/ServerName.getHostname:()Ljava/lang/String;
      29: iconst_4
      30: newarray       byte
      32: dup
      33: iconst_0
      34: bipush        10
      36: bastore
      37: dup
      38: iconst_1
      39: iconst_0
      40: bastore
      41: dup
      42: iconst_2
      43: iconst_0
      44: bastore
      45: dup
      46: iconst_3
      47: aload         4
      49: invokevirtual #7                  // Method org/apache/hadoop/hbase/ServerName.getPort:()I
      52: i2b
      53: bastore
      54: invokestatic  #8                  // Method java/net/InetAddress.getByAddress:(Ljava/lang/String;[B)Ljava/net/InetAddress;
      57: areturn

  protected void initClusterSchemaService() throws java.io.IOException, java.lang.InterruptedException;
    Code:
       0: return

  protected org.apache.hadoop.hbase.master.ServerManager createServerManager(org.apache.hadoop.hbase.master.MasterServices) throws java.io.IOException;
    Code:
       0: aload_0
       1: aload_1
       2: invokespecial #9                  // Method org/apache/hadoop/hbase/master/HMaster.createServerManager:(Lorg/apache/hadoop/hbase/master/MasterServices;)Lorg/apache/hadoop/hbase/master/ServerManager;
       5: astore_2
       6: aload_2
       7: invokestatic  #10                 // Method org/mockito/Mockito.spy:(Ljava/lang/Object;)Ljava/lang/Object;
      10: checkcast     #11                 // class org/apache/hadoop/hbase/master/ServerManager
      13: astore_3
      14: aload_3
      15: areturn

  public org.apache.hadoop.hbase.client.ClusterConnection getConnection();
    Code:
       0: aload_0
       1: getfield      #3                  // Field val$mockedConnection:Lorg/apache/hadoop/hbase/client/ClusterConnection;
       4: areturn

  public org.apache.hadoop.hbase.client.ClusterConnection getClusterConnection();
    Code:
       0: aload_0
       1: getfield      #3                  // Field val$mockedConnection:Lorg/apache/hadoop/hbase/client/ClusterConnection;
       4: areturn

  public org.apache.hadoop.hbase.client.Connection getConnection();
    Code:
       0: aload_0
       1: invokevirtual #12                 // Method getConnection:()Lorg/apache/hadoop/hbase/client/ClusterConnection;
       4: areturn
}
