Compiled from "TestInterfaceAlign.java"
public class org.apache.hadoop.hbase.client.TestInterfaceAlign {
  public static final org.apache.hadoop.hbase.HBaseClassTestRule CLASS_RULE;

  public org.apache.hadoop.hbase.client.TestInterfaceAlign();
    Code:
       0: aload_0
       1: invokespecial #1                  // Method java/lang/Object."<init>":()V
       4: return

  public void testAdminWithAsyncAdmin();
    Code:
       0: aload_0
       1: ldc           #2                  // class org/apache/hadoop/hbase/client/Admin
       3: invokespecial #3                  // Method getMethodNames:(Ljava/lang/Class;)Ljava/util/List;
       6: astore_1
       7: aload_0
       8: ldc           #4                  // class org/apache/hadoop/hbase/client/AsyncAdmin
      10: invokespecial #3                  // Method getMethodNames:(Ljava/lang/Class;)Ljava/util/List;
      13: astore_2
      14: aload_1
      15: ldc           #5                  // String getOperationTimeout
      17: invokeinterface #6,  2            // InterfaceMethod java/util/List.remove:(Ljava/lang/Object;)Z
      22: pop
      23: aload_1
      24: ldc           #7                  // String getSyncWaitTimeout
      26: invokeinterface #6,  2            // InterfaceMethod java/util/List.remove:(Ljava/lang/Object;)Z
      31: pop
      32: aload_1
      33: ldc           #8                  // String getConnection
      35: invokeinterface #6,  2            // InterfaceMethod java/util/List.remove:(Ljava/lang/Object;)Z
      40: pop
      41: aload_1
      42: ldc           #9                  // String getConfiguration
      44: invokeinterface #6,  2            // InterfaceMethod java/util/List.remove:(Ljava/lang/Object;)Z
      49: pop
      50: aload_1
      51: aload_0
      52: ldc           #10                 // class org/apache/hadoop/hbase/Abortable
      54: invokespecial #3                  // Method getMethodNames:(Ljava/lang/Class;)Ljava/util/List;
      57: invokeinterface #11,  2           // InterfaceMethod java/util/List.removeAll:(Ljava/util/Collection;)Z
      62: pop
      63: aload_1
      64: aload_0
      65: ldc           #12                 // class java/io/Closeable
      67: invokespecial #3                  // Method getMethodNames:(Ljava/lang/Class;)Ljava/util/List;
      70: invokeinterface #11,  2           // InterfaceMethod java/util/List.removeAll:(Ljava/util/Collection;)Z
      75: pop
      76: aload_1
      77: aload_2
      78: invokedynamic #13,  0             // InvokeDynamic #0:accept:(Ljava/util/List;)Ljava/util/function/Consumer;
      83: invokeinterface #14,  2           // InterfaceMethod java/util/List.forEach:(Ljava/util/function/Consumer;)V
      88: aload_2
      89: aload_1
      90: invokedynamic #15,  0             // InvokeDynamic #1:accept:(Ljava/util/List;)Ljava/util/function/Consumer;
      95: invokeinterface #14,  2           // InterfaceMethod java/util/List.forEach:(Ljava/util/function/Consumer;)V
     100: return

  static {};
    Code:
       0: ldc           #47                 // class org/apache/hadoop/hbase/client/TestInterfaceAlign
       2: invokestatic  #48                 // Method org/apache/hadoop/hbase/HBaseClassTestRule.forClass:(Ljava/lang/Class;)Lorg/apache/hadoop/hbase/HBaseClassTestRule;
       5: putstatic     #49                 // Field CLASS_RULE:Lorg/apache/hadoop/hbase/HBaseClassTestRule;
       8: return
}
