Compiled from "TestHttpServer.java"
public class org.apache.hadoop.hbase.http.TestHttpServer$DummyServletFilter implements javax.servlet.Filter {
  public org.apache.hadoop.hbase.http.TestHttpServer$DummyServletFilter();
    Code:
       0: aload_0
       1: invokespecial #1                  // Method java/lang/Object."<init>":()V
       4: return

  public void destroy();
    Code:
       0: return

  public void doFilter(javax.servlet.ServletRequest, javax.servlet.ServletResponse, javax.servlet.FilterChain) throws java.io.IOException, javax.servlet.ServletException;
    Code:
       0: aload_1
       1: ldc           #2                  // String user.name
       3: invokeinterface #3,  2            // InterfaceMethod javax/servlet/ServletRequest.getParameter:(Ljava/lang/String;)Ljava/lang/String;
       8: astore        4
      10: new           #4                  // class org/apache/hadoop/hbase/http/TestHttpServer$DummyServletFilter$1
      13: dup
      14: aload_0
      15: aload_1
      16: checkcast     #5                  // class javax/servlet/http/HttpServletRequest
      19: aload         4
      21: invokespecial #6                  // Method org/apache/hadoop/hbase/http/TestHttpServer$DummyServletFilter$1."<init>":(Lorg/apache/hadoop/hbase/http/TestHttpServer$DummyServletFilter;Ljavax/servlet/http/HttpServletRequest;Ljava/lang/String;)V
      24: astore        5
      26: aload_3
      27: aload         5
      29: aload_2
      30: invokeinterface #7,  3            // InterfaceMethod javax/servlet/FilterChain.doFilter:(Ljavax/servlet/ServletRequest;Ljavax/servlet/ServletResponse;)V
      35: return

  public void init(javax.servlet.FilterConfig);
    Code:
       0: return
}
