Compiled from "TestBufferedMutatorParams.java"
public class org.apache.hadoop.hbase.client.TestBufferedMutatorParams {
  public static final org.apache.hadoop.hbase.HBaseClassTestRule CLASS_RULE;

  public org.junit.rules.TestName name;

  public org.apache.hadoop.hbase.client.TestBufferedMutatorParams();
    Code:
       0: aload_0
       1: invokespecial #1                  // Method java/lang/Object."<init>":()V
       4: aload_0
       5: new           #2                  // class org/junit/rules/TestName
       8: dup
       9: invokespecial #3                  // Method org/junit/rules/TestName."<init>":()V
      12: putfield      #4                  // Field name:Lorg/junit/rules/TestName;
      15: return

  public void testClone();
    Code:
       0: new           #5                  // class org/apache/hadoop/hbase/client/TestBufferedMutatorParams$MockExecutorService
       3: dup
       4: aload_0
       5: aconst_null
       6: invokespecial #6                  // Method org/apache/hadoop/hbase/client/TestBufferedMutatorParams$MockExecutorService."<init>":(Lorg/apache/hadoop/hbase/client/TestBufferedMutatorParams;Lorg/apache/hadoop/hbase/client/TestBufferedMutatorParams$1;)V
       9: astore_1
      10: aload_0
      11: getfield      #4                  // Field name:Lorg/junit/rules/TestName;
      14: invokevirtual #7                  // Method org/junit/rules/TestName.getMethodName:()Ljava/lang/String;
      17: astore_2
      18: new           #8                  // class org/apache/hadoop/hbase/client/BufferedMutatorParams
      21: dup
      22: aload_2
      23: invokestatic  #9                  // Method org/apache/hadoop/hbase/TableName.valueOf:(Ljava/lang/String;)Lorg/apache/hadoop/hbase/TableName;
      26: invokespecial #10                 // Method org/apache/hadoop/hbase/client/BufferedMutatorParams."<init>":(Lorg/apache/hadoop/hbase/TableName;)V
      29: astore_3
      30: new           #11                 // class org/apache/hadoop/hbase/client/TestBufferedMutatorParams$MockExceptionListener
      33: dup
      34: aconst_null
      35: invokespecial #12                 // Method org/apache/hadoop/hbase/client/TestBufferedMutatorParams$MockExceptionListener."<init>":(Lorg/apache/hadoop/hbase/client/TestBufferedMutatorParams$1;)V
      38: astore        4
      40: aload_3
      41: ldc2_w        #13                 // long 17l
      44: invokevirtual #15                 // Method org/apache/hadoop/hbase/client/BufferedMutatorParams.writeBufferSize:(J)Lorg/apache/hadoop/hbase/client/BufferedMutatorParams;
      47: ldc2_w        #16                 // long 123l
      50: invokevirtual #18                 // Method org/apache/hadoop/hbase/client/BufferedMutatorParams.setWriteBufferPeriodicFlushTimeoutMs:(J)Lorg/apache/hadoop/hbase/client/BufferedMutatorParams;
      53: ldc2_w        #19                 // long 456l
      56: invokevirtual #21                 // Method org/apache/hadoop/hbase/client/BufferedMutatorParams.setWriteBufferPeriodicFlushTimerTickMs:(J)Lorg/apache/hadoop/hbase/client/BufferedMutatorParams;
      59: bipush        13
      61: invokevirtual #22                 // Method org/apache/hadoop/hbase/client/BufferedMutatorParams.maxKeyValueSize:(I)Lorg/apache/hadoop/hbase/client/BufferedMutatorParams;
      64: aload_1
      65: invokevirtual #23                 // Method org/apache/hadoop/hbase/client/BufferedMutatorParams.pool:(Ljava/util/concurrent/ExecutorService;)Lorg/apache/hadoop/hbase/client/BufferedMutatorParams;
      68: aload         4
      70: invokevirtual #24                 // Method org/apache/hadoop/hbase/client/BufferedMutatorParams.listener:(Lorg/apache/hadoop/hbase/client/BufferedMutator$ExceptionListener;)Lorg/apache/hadoop/hbase/client/BufferedMutatorParams;
      73: pop
      74: aload_3
      75: ldc           #25                 // String someClassName
      77: invokevirtual #26                 // Method org/apache/hadoop/hbase/client/BufferedMutatorParams.implementationClassName:(Ljava/lang/String;)Lorg/apache/hadoop/hbase/client/BufferedMutatorParams;
      80: pop
      81: aload_3
      82: invokevirtual #27                 // Method org/apache/hadoop/hbase/client/BufferedMutatorParams.clone:()Lorg/apache/hadoop/hbase/client/BufferedMutatorParams;
      85: astore        5
      87: aload_2
      88: aload         5
      90: invokevirtual #28                 // Method org/apache/hadoop/hbase/client/BufferedMutatorParams.getTableName:()Lorg/apache/hadoop/hbase/TableName;
      93: invokevirtual #29                 // Method org/apache/hadoop/hbase/TableName.toString:()Ljava/lang/String;
      96: invokestatic  #30                 // Method org/junit/Assert.assertEquals:(Ljava/lang/Object;Ljava/lang/Object;)V
      99: ldc2_w        #13                 // long 17l
     102: aload         5
     104: invokevirtual #31                 // Method org/apache/hadoop/hbase/client/BufferedMutatorParams.getWriteBufferSize:()J
     107: invokestatic  #32                 // Method org/junit/Assert.assertEquals:(JJ)V
     110: ldc2_w        #16                 // long 123l
     113: aload         5
     115: invokevirtual #33                 // Method org/apache/hadoop/hbase/client/BufferedMutatorParams.getWriteBufferPeriodicFlushTimeoutMs:()J
     118: invokestatic  #32                 // Method org/junit/Assert.assertEquals:(JJ)V
     121: ldc2_w        #19                 // long 456l
     124: aload         5
     126: invokevirtual #34                 // Method org/apache/hadoop/hbase/client/BufferedMutatorParams.getWriteBufferPeriodicFlushTimerTickMs:()J
     129: invokestatic  #32                 // Method org/junit/Assert.assertEquals:(JJ)V
     132: ldc2_w        #35                 // long 13l
     135: aload         5
     137: invokevirtual #37                 // Method org/apache/hadoop/hbase/client/BufferedMutatorParams.getMaxKeyValueSize:()I
     140: i2l
     141: invokestatic  #32                 // Method org/junit/Assert.assertEquals:(JJ)V
     144: ldc           #25                 // String someClassName
     146: aload         5
     148: invokevirtual #38                 // Method org/apache/hadoop/hbase/client/BufferedMutatorParams.getImplementationClassName:()Ljava/lang/String;
     151: invokestatic  #30                 // Method org/junit/Assert.assertEquals:(Ljava/lang/Object;Ljava/lang/Object;)V
     154: aload_0
     155: aload_3
     156: aload         5
     158: invokespecial #39                 // Method cloneTest:(Lorg/apache/hadoop/hbase/client/BufferedMutatorParams;Lorg/apache/hadoop/hbase/client/BufferedMutatorParams;)V
     161: aload         5
     163: invokevirtual #27                 // Method org/apache/hadoop/hbase/client/BufferedMutatorParams.clone:()Lorg/apache/hadoop/hbase/client/BufferedMutatorParams;
     166: astore        6
     168: aload_0
     169: aload         5
     171: aload         6
     173: invokespecial #39                 // Method cloneTest:(Lorg/apache/hadoop/hbase/client/BufferedMutatorParams;Lorg/apache/hadoop/hbase/client/BufferedMutatorParams;)V
     176: aload_0
     177: aload_3
     178: aload         6
     180: invokespecial #39                 // Method cloneTest:(Lorg/apache/hadoop/hbase/client/BufferedMutatorParams;Lorg/apache/hadoop/hbase/client/BufferedMutatorParams;)V
     183: aload         5
     185: aconst_null
     186: invokevirtual #26                 // Method org/apache/hadoop/hbase/client/BufferedMutatorParams.implementationClassName:(Ljava/lang/String;)Lorg/apache/hadoop/hbase/client/BufferedMutatorParams;
     189: pop
     190: ldc           #25                 // String someClassName
     192: aload_3
     193: invokevirtual #38                 // Method org/apache/hadoop/hbase/client/BufferedMutatorParams.getImplementationClassName:()Ljava/lang/String;
     196: invokestatic  #30                 // Method org/junit/Assert.assertEquals:(Ljava/lang/Object;Ljava/lang/Object;)V
     199: return

  static {};
    Code:
       0: ldc           #44                 // class org/apache/hadoop/hbase/client/TestBufferedMutatorParams
       2: invokestatic  #45                 // Method org/apache/hadoop/hbase/HBaseClassTestRule.forClass:(Ljava/lang/Class;)Lorg/apache/hadoop/hbase/HBaseClassTestRule;
       5: putstatic     #46                 // Field CLASS_RULE:Lorg/apache/hadoop/hbase/HBaseClassTestRule;
       8: return
}
