Compiled from "TestAsyncAdminRpcPriority.java"
class org.apache.hadoop.hbase.client.TestAsyncAdminRpcPriority$1 implements org.mockito.stubbing.Answer<java.lang.Void> {
  final org.apache.hadoop.hbase.client.TestAsyncAdminRpcPriority this$0;

  org.apache.hadoop.hbase.client.TestAsyncAdminRpcPriority$1(org.apache.hadoop.hbase.client.TestAsyncAdminRpcPriority);
    Code:
       0: aload_0
       1: aload_1
       2: putfield      #1                  // Field this$0:Lorg/apache/hadoop/hbase/client/TestAsyncAdminRpcPriority;
       5: aload_0
       6: invokespecial #2                  // Method java/lang/Object."<init>":()V
       9: return

  public java.lang.Void answer(org.mockito.invocation.InvocationOnMock) throws java.lang.Throwable;
    Code:
       0: aload_1
       1: iconst_2
       2: invokeinterface #3,  2            // InterfaceMethod org/mockito/invocation/InvocationOnMock.getArgument:(I)Ljava/lang/Object;
       7: checkcast     #4                  // class org/apache/hbase/thirdparty/com/google/protobuf/RpcCallback
      10: astore_2
      11: aload_2
      12: invokestatic  #5                  // Method org/apache/hadoop/hbase/shaded/protobuf/generated/MasterProtos$GetProcedureResultResponse.newBuilder:()Lorg/apache/hadoop/hbase/shaded/protobuf/generated/MasterProtos$GetProcedureResultResponse$Builder;
      15: getstatic     #6                  // Field org/apache/hadoop/hbase/shaded/protobuf/generated/MasterProtos$GetProcedureResultResponse$State.FINISHED:Lorg/apache/hadoop/hbase/shaded/protobuf/generated/MasterProtos$GetProcedureResultResponse$State;
      18: invokevirtual #7                  // Method org/apache/hadoop/hbase/shaded/protobuf/generated/MasterProtos$GetProcedureResultResponse$Builder.setState:(Lorg/apache/hadoop/hbase/shaded/protobuf/generated/MasterProtos$GetProcedureResultResponse$State;)Lorg/apache/hadoop/hbase/shaded/protobuf/generated/MasterProtos$GetProcedureResultResponse$Builder;
      21: invokevirtual #8                  // Method org/apache/hadoop/hbase/shaded/protobuf/generated/MasterProtos$GetProcedureResultResponse$Builder.build:()Lorg/apache/hadoop/hbase/shaded/protobuf/generated/MasterProtos$GetProcedureResultResponse;
      24: invokeinterface #9,  2            // InterfaceMethod org/apache/hbase/thirdparty/com/google/protobuf/RpcCallback.run:(Ljava/lang/Object;)V
      29: aconst_null
      30: areturn

  public java.lang.Object answer(org.mockito.invocation.InvocationOnMock) throws java.lang.Throwable;
    Code:
       0: aload_0
       1: aload_1
       2: invokevirtual #10                 // Method answer:(Lorg/mockito/invocation/InvocationOnMock;)Ljava/lang/Void;
       5: areturn
}
