Compiled from "TestHRegion.java"
class org.apache.hadoop.hbase.regionserver.TestHRegion$HRegionWithSeqId extends org.apache.hadoop.hbase.regionserver.HRegion {
  public org.apache.hadoop.hbase.regionserver.TestHRegion$HRegionWithSeqId(org.apache.hadoop.fs.Path, org.apache.hadoop.hbase.wal.WAL, org.apache.hadoop.fs.FileSystem, org.apache.hadoop.conf.Configuration, org.apache.hadoop.hbase.client.RegionInfo, org.apache.hadoop.hbase.client.TableDescriptor, org.apache.hadoop.hbase.regionserver.RegionServerServices);
    Code:
       0: aload_0
       1: aload_1
       2: aload_2
       3: aload_3
       4: aload         4
       6: aload         5
       8: aload         6
      10: aload         7
      12: invokespecial #1                  // Method org/apache/hadoop/hbase/regionserver/HRegion."<init>":(Lorg/apache/hadoop/fs/Path;Lorg/apache/hadoop/hbase/wal/WAL;Lorg/apache/hadoop/fs/FileSystem;Lorg/apache/hadoop/conf/Configuration;Lorg/apache/hadoop/hbase/client/RegionInfo;Lorg/apache/hadoop/hbase/client/TableDescriptor;Lorg/apache/hadoop/hbase/regionserver/RegionServerServices;)V
      15: return

  protected long getNextSequenceId(org.apache.hadoop.hbase.wal.WAL) throws java.io.IOException;
    Code:
       0: ldc2_w        #2                  // long 42l
       3: lreturn
}
