Compiled from "TestChoreService.java"
public class org.apache.hadoop.hbase.TestChoreService$ScheduledChoreSamples$DoNothingChore extends org.apache.hadoop.hbase.ScheduledChore {
  public org.apache.hadoop.hbase.TestChoreService$ScheduledChoreSamples$DoNothingChore(java.lang.String, int);
    Code:
       0: aload_0
       1: aload_1
       2: new           #1                  // class org/apache/hadoop/hbase/TestChoreService$ScheduledChoreSamples$SampleStopper
       5: dup
       6: invokespecial #2                  // Method org/apache/hadoop/hbase/TestChoreService$ScheduledChoreSamples$SampleStopper."<init>":()V
       9: iload_2
      10: invokespecial #3                  // Method org/apache/hadoop/hbase/ScheduledChore."<init>":(Ljava/lang/String;Lorg/apache/hadoop/hbase/Stoppable;I)V
      13: return

  public org.apache.hadoop.hbase.TestChoreService$ScheduledChoreSamples$DoNothingChore(java.lang.String, org.apache.hadoop.hbase.Stoppable, int);
    Code:
       0: aload_0
       1: aload_1
       2: aload_2
       3: iload_3
       4: invokespecial #3                  // Method org/apache/hadoop/hbase/ScheduledChore."<init>":(Ljava/lang/String;Lorg/apache/hadoop/hbase/Stoppable;I)V
       7: return

  protected void chore();
    Code:
       0: return
}
