Compiled from "TestMultiVersions.java"
public class org.apache.hadoop.hbase.TestMultiVersions {
  public static final org.apache.hadoop.hbase.HBaseClassTestRule CLASS_RULE;

  public org.junit.rules.TestName name;

  public org.apache.hadoop.hbase.TestMultiVersions();
    Code:
       0: aload_0
       1: invokespecial #2                  // Method java/lang/Object."<init>":()V
       4: aload_0
       5: new           #3                  // class org/junit/rules/TestName
       8: dup
       9: invokespecial #4                  // Method org/junit/rules/TestName."<init>":()V
      12: putfield      #5                  // Field name:Lorg/junit/rules/TestName;
      15: return

  public static void setUpBeforeClass() throws java.lang.Exception;
    Code:
       0: getstatic     #1                  // Field UTIL:Lorg/apache/hadoop/hbase/HBaseTestingUtility;
       3: iconst_3
       4: invokevirtual #7                  // Method org/apache/hadoop/hbase/HBaseTestingUtility.startMiniCluster:(I)Lorg/apache/hadoop/hbase/MiniHBaseCluster;
       7: pop
       8: return

  public static void tearDownAfterClass() throws java.lang.Exception;
    Code:
       0: getstatic     #1                  // Field UTIL:Lorg/apache/hadoop/hbase/HBaseTestingUtility;
       3: invokevirtual #8                  // Method org/apache/hadoop/hbase/HBaseTestingUtility.shutdownMiniCluster:()V
       6: return

  public void before() throws org.apache.hadoop.hbase.MasterNotRunningException, org.apache.hadoop.hbase.ZooKeeperConnectionException, java.io.IOException;
    Code:
       0: aload_0
       1: getstatic     #1                  // Field UTIL:Lorg/apache/hadoop/hbase/HBaseTestingUtility;
       4: invokevirtual #9                  // Method org/apache/hadoop/hbase/HBaseTestingUtility.getAdmin:()Lorg/apache/hadoop/hbase/client/Admin;
       7: putfield      #10                 // Field admin:Lorg/apache/hadoop/hbase/client/Admin;
      10: return

  public void testTimestamps() throws java.lang.Exception;
    Code:
       0: new           #11                 // class org/apache/hadoop/hbase/HTableDescriptor
       3: dup
       4: aload_0
       5: getfield      #5                  // Field name:Lorg/junit/rules/TestName;
       8: invokevirtual #12                 // Method org/junit/rules/TestName.getMethodName:()Ljava/lang/String;
      11: invokestatic  #13                 // Method org/apache/hadoop/hbase/TableName.valueOf:(Ljava/lang/String;)Lorg/apache/hadoop/hbase/TableName;
      14: invokespecial #14                 // Method org/apache/hadoop/hbase/HTableDescriptor."<init>":(Lorg/apache/hadoop/hbase/TableName;)V
      17: astore_1
      18: new           #15                 // class org/apache/hadoop/hbase/HColumnDescriptor
      21: dup
      22: getstatic     #16                 // Field org/apache/hadoop/hbase/TimestampTestBase.FAMILY_NAME:[B
      25: invokespecial #17                 // Method org/apache/hadoop/hbase/HColumnDescriptor."<init>":([B)V
      28: astore_2
      29: aload_2
      30: iconst_3
      31: invokevirtual #18                 // Method org/apache/hadoop/hbase/HColumnDescriptor.setMaxVersions:(I)Lorg/apache/hadoop/hbase/HColumnDescriptor;
      34: pop
      35: aload_1
      36: aload_2
      37: invokevirtual #19                 // Method org/apache/hadoop/hbase/HTableDescriptor.addFamily:(Lorg/apache/hadoop/hbase/HColumnDescriptor;)Lorg/apache/hadoop/hbase/HTableDescriptor;
      40: pop
      41: aload_0
      42: getfield      #10                 // Field admin:Lorg/apache/hadoop/hbase/client/Admin;
      45: aload_1
      46: invokeinterface #20,  2           // InterfaceMethod org/apache/hadoop/hbase/client/Admin.createTable:(Lorg/apache/hadoop/hbase/client/TableDescriptor;)V
      51: getstatic     #1                  // Field UTIL:Lorg/apache/hadoop/hbase/HBaseTestingUtility;
      54: invokevirtual #21                 // Method org/apache/hadoop/hbase/HBaseTestingUtility.getConnection:()Lorg/apache/hadoop/hbase/client/Connection;
      57: aload_1
      58: invokevirtual #22                 // Method org/apache/hadoop/hbase/HTableDescriptor.getTableName:()Lorg/apache/hadoop/hbase/TableName;
      61: invokeinterface #23,  2           // InterfaceMethod org/apache/hadoop/hbase/client/Connection.getTable:(Lorg/apache/hadoop/hbase/TableName;)Lorg/apache/hadoop/hbase/client/Table;
      66: astore_3
      67: aload_3
      68: new           #24                 // class org/apache/hadoop/hbase/TestMultiVersions$1
      71: dup
      72: aload_0
      73: invokespecial #25                 // Method org/apache/hadoop/hbase/TestMultiVersions$1."<init>":(Lorg/apache/hadoop/hbase/TestMultiVersions;)V
      76: invokestatic  #26                 // Method org/apache/hadoop/hbase/TimestampTestBase.doTestDelete:(Lorg/apache/hadoop/hbase/client/Table;Lorg/apache/hadoop/hbase/TimestampTestBase$FlushCache;)V
      79: aload_3
      80: new           #27                 // class org/apache/hadoop/hbase/TestMultiVersions$2
      83: dup
      84: aload_0
      85: invokespecial #28                 // Method org/apache/hadoop/hbase/TestMultiVersions$2."<init>":(Lorg/apache/hadoop/hbase/TestMultiVersions;)V
      88: invokestatic  #29                 // Method org/apache/hadoop/hbase/TimestampTestBase.doTestTimestampScanning:(Lorg/apache/hadoop/hbase/client/Table;Lorg/apache/hadoop/hbase/TimestampTestBase$FlushCache;)V
      91: aload_3
      92: invokeinterface #30,  1           // InterfaceMethod org/apache/hadoop/hbase/client/Table.close:()V
      97: return

  public void testGetRowVersions() throws java.lang.Exception;
    Code:
       0: ldc           #31                 // String contents
       2: invokestatic  #32                 // Method org/apache/hadoop/hbase/util/Bytes.toBytes:(Ljava/lang/String;)[B
       5: astore_1
       6: ldc           #33                 // String row
       8: invokestatic  #32                 // Method org/apache/hadoop/hbase/util/Bytes.toBytes:(Ljava/lang/String;)[B
      11: astore_2
      12: ldc           #34                 // String value1
      14: invokestatic  #32                 // Method org/apache/hadoop/hbase/util/Bytes.toBytes:(Ljava/lang/String;)[B
      17: astore_3
      18: ldc           #35                 // String value2
      20: invokestatic  #32                 // Method org/apache/hadoop/hbase/util/Bytes.toBytes:(Ljava/lang/String;)[B
      23: astore        4
      25: ldc2_w        #36                 // long 100l
      28: lstore        5
      30: ldc2_w        #38                 // long 200l
      33: lstore        7
      35: new           #11                 // class org/apache/hadoop/hbase/HTableDescriptor
      38: dup
      39: aload_0
      40: getfield      #5                  // Field name:Lorg/junit/rules/TestName;
      43: invokevirtual #12                 // Method org/junit/rules/TestName.getMethodName:()Ljava/lang/String;
      46: invokestatic  #13                 // Method org/apache/hadoop/hbase/TableName.valueOf:(Ljava/lang/String;)Lorg/apache/hadoop/hbase/TableName;
      49: invokespecial #14                 // Method org/apache/hadoop/hbase/HTableDescriptor."<init>":(Lorg/apache/hadoop/hbase/TableName;)V
      52: astore        9
      54: new           #15                 // class org/apache/hadoop/hbase/HColumnDescriptor
      57: dup
      58: aload_1
      59: invokespecial #17                 // Method org/apache/hadoop/hbase/HColumnDescriptor."<init>":([B)V
      62: astore        10
      64: aload         10
      66: iconst_3
      67: invokevirtual #18                 // Method org/apache/hadoop/hbase/HColumnDescriptor.setMaxVersions:(I)Lorg/apache/hadoop/hbase/HColumnDescriptor;
      70: pop
      71: aload         9
      73: aload         10
      75: invokevirtual #19                 // Method org/apache/hadoop/hbase/HTableDescriptor.addFamily:(Lorg/apache/hadoop/hbase/HColumnDescriptor;)Lorg/apache/hadoop/hbase/HTableDescriptor;
      78: pop
      79: aload_0
      80: getfield      #10                 // Field admin:Lorg/apache/hadoop/hbase/client/Admin;
      83: aload         9
      85: invokeinterface #20,  2           // InterfaceMethod org/apache/hadoop/hbase/client/Admin.createTable:(Lorg/apache/hadoop/hbase/client/TableDescriptor;)V
      90: new           #40                 // class org/apache/hadoop/hbase/client/Put
      93: dup
      94: aload_2
      95: ldc2_w        #36                 // long 100l
      98: invokespecial #41                 // Method org/apache/hadoop/hbase/client/Put."<init>":([BJ)V
     101: astore        11
     103: aload         11
     105: aload_1
     106: aload_1
     107: aload_3
     108: invokevirtual #42                 // Method org/apache/hadoop/hbase/client/Put.addColumn:([B[B[B)Lorg/apache/hadoop/hbase/client/Put;
     111: pop
     112: getstatic     #1                  // Field UTIL:Lorg/apache/hadoop/hbase/HBaseTestingUtility;
     115: invokevirtual #21                 // Method org/apache/hadoop/hbase/HBaseTestingUtility.getConnection:()Lorg/apache/hadoop/hbase/client/Connection;
     118: aload         9
     120: invokevirtual #22                 // Method org/apache/hadoop/hbase/HTableDescriptor.getTableName:()Lorg/apache/hadoop/hbase/TableName;
     123: invokeinterface #23,  2           // InterfaceMethod org/apache/hadoop/hbase/client/Connection.getTable:(Lorg/apache/hadoop/hbase/TableName;)Lorg/apache/hadoop/hbase/client/Table;
     128: astore        12
     130: aload         12
     132: aload         11
     134: invokeinterface #43,  2           // InterfaceMethod org/apache/hadoop/hbase/client/Table.put:(Lorg/apache/hadoop/hbase/client/Put;)V
     139: aload         12
     141: invokeinterface #30,  1           // InterfaceMethod org/apache/hadoop/hbase/client/Table.close:()V
     146: getstatic     #1                  // Field UTIL:Lorg/apache/hadoop/hbase/HBaseTestingUtility;
     149: invokevirtual #44                 // Method org/apache/hadoop/hbase/HBaseTestingUtility.shutdownMiniHBaseCluster:()V
     152: getstatic     #45                 // Field LOG:Lorg/slf4j/Logger;
     155: ldc           #46                 // String HBase cluster shut down -- restarting
     157: invokeinterface #47,  2           // InterfaceMethod org/slf4j/Logger.debug:(Ljava/lang/String;)V
     162: invokestatic  #48                 // Method org/apache/hadoop/hbase/StartMiniClusterOption.builder:()Lorg/apache/hadoop/hbase/StartMiniClusterOption$Builder;
     165: iconst_3
     166: invokevirtual #49                 // Method org/apache/hadoop/hbase/StartMiniClusterOption$Builder.numRegionServers:(I)Lorg/apache/hadoop/hbase/StartMiniClusterOption$Builder;
     169: invokevirtual #50                 // Method org/apache/hadoop/hbase/StartMiniClusterOption$Builder.build:()Lorg/apache/hadoop/hbase/StartMiniClusterOption;
     172: astore        13
     174: getstatic     #1                  // Field UTIL:Lorg/apache/hadoop/hbase/HBaseTestingUtility;
     177: aload         13
     179: invokevirtual #51                 // Method org/apache/hadoop/hbase/HBaseTestingUtility.startMiniHBaseCluster:(Lorg/apache/hadoop/hbase/StartMiniClusterOption;)Lorg/apache/hadoop/hbase/MiniHBaseCluster;
     182: pop
     183: getstatic     #1                  // Field UTIL:Lorg/apache/hadoop/hbase/HBaseTestingUtility;
     186: invokevirtual #21                 // Method org/apache/hadoop/hbase/HBaseTestingUtility.getConnection:()Lorg/apache/hadoop/hbase/client/Connection;
     189: aload         9
     191: invokevirtual #22                 // Method org/apache/hadoop/hbase/HTableDescriptor.getTableName:()Lorg/apache/hadoop/hbase/TableName;
     194: invokeinterface #23,  2           // InterfaceMethod org/apache/hadoop/hbase/client/Connection.getTable:(Lorg/apache/hadoop/hbase/TableName;)Lorg/apache/hadoop/hbase/client/Table;
     199: astore        12
     201: new           #40                 // class org/apache/hadoop/hbase/client/Put
     204: dup
     205: aload_2
     206: ldc2_w        #38                 // long 200l
     209: invokespecial #41                 // Method org/apache/hadoop/hbase/client/Put."<init>":([BJ)V
     212: astore        11
     214: aload         11
     216: aload_1
     217: aload_1
     218: aload         4
     220: invokevirtual #42                 // Method org/apache/hadoop/hbase/client/Put.addColumn:([B[B[B)Lorg/apache/hadoop/hbase/client/Put;
     223: pop
     224: aload         12
     226: aload         11
     228: invokeinterface #43,  2           // InterfaceMethod org/apache/hadoop/hbase/client/Table.put:(Lorg/apache/hadoop/hbase/client/Put;)V
     233: new           #52                 // class org/apache/hadoop/hbase/client/Get
     236: dup
     237: aload_2
     238: invokespecial #53                 // Method org/apache/hadoop/hbase/client/Get."<init>":([B)V
     241: astore        14
     243: aload         12
     245: aload         14
     247: invokeinterface #54,  2           // InterfaceMethod org/apache/hadoop/hbase/client/Table.get:(Lorg/apache/hadoop/hbase/client/Get;)Lorg/apache/hadoop/hbase/client/Result;
     252: astore        15
     254: aload         15
     256: invokestatic  #55                 // Method org/junit/Assert.assertNotNull:(Ljava/lang/Object;)V
     259: aload         15
     261: invokevirtual #56                 // Method org/apache/hadoop/hbase/client/Result.isEmpty:()Z
     264: invokestatic  #57                 // Method org/junit/Assert.assertFalse:(Z)V
     267: aload         15
     269: invokevirtual #58                 // Method org/apache/hadoop/hbase/client/Result.size:()I
     272: iconst_1
     273: if_icmpne     280
     276: iconst_1
     277: goto          281
     280: iconst_0
     281: invokestatic  #59                 // Method org/junit/Assert.assertTrue:(Z)V
     284: aload         15
     286: aload_1
     287: aload_1
     288: invokevirtual #60                 // Method org/apache/hadoop/hbase/client/Result.getValue:([B[B)[B
     291: astore        16
     293: aload         16
     295: arraylength
     296: ifeq          303
     299: iconst_1
     300: goto          304
     303: iconst_0
     304: invokestatic  #59                 // Method org/junit/Assert.assertTrue:(Z)V
     307: aload         16
     309: aload         4
     311: invokestatic  #61                 // Method org/apache/hadoop/hbase/util/Bytes.equals:([B[B)Z
     314: invokestatic  #59                 // Method org/junit/Assert.assertTrue:(Z)V
     317: new           #52                 // class org/apache/hadoop/hbase/client/Get
     320: dup
     321: aload_2
     322: invokespecial #53                 // Method org/apache/hadoop/hbase/client/Get."<init>":([B)V
     325: astore        14
     327: aload         14
     329: invokevirtual #62                 // Method org/apache/hadoop/hbase/client/Get.readAllVersions:()Lorg/apache/hadoop/hbase/client/Get;
     332: pop
     333: aload         12
     335: aload         14
     337: invokeinterface #54,  2           // InterfaceMethod org/apache/hadoop/hbase/client/Table.get:(Lorg/apache/hadoop/hbase/client/Get;)Lorg/apache/hadoop/hbase/client/Result;
     342: astore        15
     344: aload         15
     346: invokevirtual #58                 // Method org/apache/hadoop/hbase/client/Result.size:()I
     349: iconst_2
     350: if_icmpne     357
     353: iconst_1
     354: goto          358
     357: iconst_0
     358: invokestatic  #59                 // Method org/junit/Assert.assertTrue:(Z)V
     361: aload         15
     363: aload_1
     364: aload_1
     365: invokevirtual #60                 // Method org/apache/hadoop/hbase/client/Result.getValue:([B[B)[B
     368: astore        16
     370: aload         16
     372: arraylength
     373: ifeq          380
     376: iconst_1
     377: goto          381
     380: iconst_0
     381: invokestatic  #59                 // Method org/junit/Assert.assertTrue:(Z)V
     384: aload         16
     386: aload         4
     388: invokestatic  #61                 // Method org/apache/hadoop/hbase/util/Bytes.equals:([B[B)Z
     391: invokestatic  #59                 // Method org/junit/Assert.assertTrue:(Z)V
     394: aload         15
     396: invokevirtual #63                 // Method org/apache/hadoop/hbase/client/Result.getMap:()Ljava/util/NavigableMap;
     399: astore        17
     401: aload         17
     403: aload_1
     404: invokeinterface #64,  2           // InterfaceMethod java/util/NavigableMap.get:(Ljava/lang/Object;)Ljava/lang/Object;
     409: checkcast     #65                 // class java/util/NavigableMap
     412: astore        18
     414: aload         18
     416: aload_1
     417: invokeinterface #64,  2           // InterfaceMethod java/util/NavigableMap.get:(Ljava/lang/Object;)Ljava/lang/Object;
     422: checkcast     #65                 // class java/util/NavigableMap
     425: astore        19
     427: aload         19
     429: invokeinterface #66,  1           // InterfaceMethod java/util/NavigableMap.size:()I
     434: iconst_2
     435: if_icmpne     442
     438: iconst_1
     439: goto          443
     442: iconst_0
     443: invokestatic  #59                 // Method org/junit/Assert.assertTrue:(Z)V
     446: aload_3
     447: aload         19
     449: ldc2_w        #36                 // long 100l
     452: invokestatic  #67                 // Method java/lang/Long.valueOf:(J)Ljava/lang/Long;
     455: invokeinterface #64,  2           // InterfaceMethod java/util/NavigableMap.get:(Ljava/lang/Object;)Ljava/lang/Object;
     460: checkcast     #68                 // class "[B"
     463: invokestatic  #61                 // Method org/apache/hadoop/hbase/util/Bytes.equals:([B[B)Z
     466: invokestatic  #59                 // Method org/junit/Assert.assertTrue:(Z)V
     469: aload         4
     471: aload         19
     473: ldc2_w        #38                 // long 200l
     476: invokestatic  #67                 // Method java/lang/Long.valueOf:(J)Ljava/lang/Long;
     479: invokeinterface #64,  2           // InterfaceMethod java/util/NavigableMap.get:(Ljava/lang/Object;)Ljava/lang/Object;
     484: checkcast     #68                 // class "[B"
     487: invokestatic  #61                 // Method org/apache/hadoop/hbase/util/Bytes.equals:([B[B)Z
     490: invokestatic  #59                 // Method org/junit/Assert.assertTrue:(Z)V
     493: aload         12
     495: invokeinterface #30,  1           // InterfaceMethod org/apache/hadoop/hbase/client/Table.close:()V
     500: return

  public void testScanMultipleVersions() throws java.lang.Exception;
    Code:
       0: aload_0
       1: getfield      #5                  // Field name:Lorg/junit/rules/TestName;
       4: invokevirtual #12                 // Method org/junit/rules/TestName.getMethodName:()Ljava/lang/String;
       7: invokestatic  #13                 // Method org/apache/hadoop/hbase/TableName.valueOf:(Ljava/lang/String;)Lorg/apache/hadoop/hbase/TableName;
      10: astore_1
      11: new           #11                 // class org/apache/hadoop/hbase/HTableDescriptor
      14: dup
      15: aload_1
      16: invokespecial #14                 // Method org/apache/hadoop/hbase/HTableDescriptor."<init>":(Lorg/apache/hadoop/hbase/TableName;)V
      19: astore_2
      20: aload_2
      21: new           #15                 // class org/apache/hadoop/hbase/HColumnDescriptor
      24: dup
      25: getstatic     #69                 // Field org/apache/hadoop/hbase/HConstants.CATALOG_FAMILY:[B
      28: invokespecial #17                 // Method org/apache/hadoop/hbase/HColumnDescriptor."<init>":([B)V
      31: invokevirtual #19                 // Method org/apache/hadoop/hbase/HTableDescriptor.addFamily:(Lorg/apache/hadoop/hbase/HColumnDescriptor;)Lorg/apache/hadoop/hbase/HTableDescriptor;
      34: pop
      35: iconst_2
      36: anewarray     #68                 // class "[B"
      39: dup
      40: iconst_0
      41: ldc           #70                 // String row_0200
      43: invokestatic  #32                 // Method org/apache/hadoop/hbase/util/Bytes.toBytes:(Ljava/lang/String;)[B
      46: aastore
      47: dup
      48: iconst_1
      49: ldc           #71                 // String row_0800
      51: invokestatic  #32                 // Method org/apache/hadoop/hbase/util/Bytes.toBytes:(Ljava/lang/String;)[B
      54: aastore
      55: astore_3
      56: iconst_1
      57: anewarray     #68                 // class "[B"
      60: dup
      61: iconst_0
      62: ldc           #72                 // String row_0500
      64: invokestatic  #32                 // Method org/apache/hadoop/hbase/util/Bytes.toBytes:(Ljava/lang/String;)[B
      67: aastore
      68: astore        4
      70: iconst_2
      71: newarray       long
      73: dup
      74: iconst_0
      75: ldc2_w        #36                 // long 100l
      78: lastore
      79: dup
      80: iconst_1
      81: ldc2_w        #73                 // long 1000l
      84: lastore
      85: astore        5
      87: aload_0
      88: getfield      #10                 // Field admin:Lorg/apache/hadoop/hbase/client/Admin;
      91: aload_2
      92: aload         4
      94: invokeinterface #75,  3           // InterfaceMethod org/apache/hadoop/hbase/client/Admin.createTable:(Lorg/apache/hadoop/hbase/client/TableDescriptor;[[B)V
      99: getstatic     #1                  // Field UTIL:Lorg/apache/hadoop/hbase/HBaseTestingUtility;
     102: invokevirtual #21                 // Method org/apache/hadoop/hbase/HBaseTestingUtility.getConnection:()Lorg/apache/hadoop/hbase/client/Connection;
     105: aload_1
     106: invokeinterface #23,  2           // InterfaceMethod org/apache/hadoop/hbase/client/Connection.getTable:(Lorg/apache/hadoop/hbase/TableName;)Lorg/apache/hadoop/hbase/client/Table;
     111: astore        6
     113: getstatic     #1                  // Field UTIL:Lorg/apache/hadoop/hbase/HBaseTestingUtility;
     116: invokevirtual #21                 // Method org/apache/hadoop/hbase/HBaseTestingUtility.getConnection:()Lorg/apache/hadoop/hbase/client/Connection;
     119: aload_1
     120: invokeinterface #76,  2           // InterfaceMethod org/apache/hadoop/hbase/client/Connection.getRegionLocator:(Lorg/apache/hadoop/hbase/TableName;)Lorg/apache/hadoop/hbase/client/RegionLocator;
     125: invokeinterface #77,  1           // InterfaceMethod org/apache/hadoop/hbase/client/RegionLocator.getStartEndKeys:()Lorg/apache/hadoop/hbase/util/Pair;
     130: astore        7
     132: ldc2_w        #78                 // long 2l
     135: aload         7
     137: invokevirtual #80                 // Method org/apache/hadoop/hbase/util/Pair.getFirst:()Ljava/lang/Object;
     140: checkcast     #81                 // class "[[B"
     143: arraylength
     144: i2l
     145: invokestatic  #82                 // Method org/junit/Assert.assertEquals:(JJ)V
     148: aload         7
     150: invokevirtual #80                 // Method org/apache/hadoop/hbase/util/Pair.getFirst:()Ljava/lang/Object;
     153: checkcast     #81                 // class "[[B"
     156: astore        8
     158: aload         7
     160: invokevirtual #83                 // Method org/apache/hadoop/hbase/util/Pair.getSecond:()Ljava/lang/Object;
     163: checkcast     #81                 // class "[[B"
     166: astore        9
     168: iconst_0
     169: istore        10
     171: iload         10
     173: aload         8
     175: arraylength
     176: if_icmpge     257
     179: iload         10
     181: ifne          216
     184: getstatic     #84                 // Field org/apache/hadoop/hbase/HConstants.EMPTY_START_ROW:[B
     187: aload         8
     189: iload         10
     191: aaload
     192: invokestatic  #61                 // Method org/apache/hadoop/hbase/util/Bytes.equals:([B[B)Z
     195: invokestatic  #59                 // Method org/junit/Assert.assertTrue:(Z)V
     198: aload         9
     200: iload         10
     202: aaload
     203: aload         4
     205: iconst_0
     206: aaload
     207: invokestatic  #61                 // Method org/apache/hadoop/hbase/util/Bytes.equals:([B[B)Z
     210: invokestatic  #59                 // Method org/junit/Assert.assertTrue:(Z)V
     213: goto          251
     216: iload         10
     218: iconst_1
     219: if_icmpne     251
     222: aload         4
     224: iconst_0
     225: aaload
     226: aload         8
     228: iload         10
     230: aaload
     231: invokestatic  #61                 // Method org/apache/hadoop/hbase/util/Bytes.equals:([B[B)Z
     234: invokestatic  #59                 // Method org/junit/Assert.assertTrue:(Z)V
     237: aload         9
     239: iload         10
     241: aaload
     242: getstatic     #85                 // Field org/apache/hadoop/hbase/HConstants.EMPTY_END_ROW:[B
     245: invokestatic  #61                 // Method org/apache/hadoop/hbase/util/Bytes.equals:([B[B)Z
     248: invokestatic  #59                 // Method org/junit/Assert.assertTrue:(Z)V
     251: iinc          10, 1
     254: goto          171
     257: new           #86                 // class java/util/ArrayList
     260: dup
     261: invokespecial #87                 // Method java/util/ArrayList."<init>":()V
     264: astore        10
     266: iconst_0
     267: istore        11
     269: iload         11
     271: aload         8
     273: arraylength
     274: if_icmpge     351
     277: iconst_0
     278: istore        12
     280: iload         12
     282: aload         5
     284: arraylength
     285: if_icmpge     345
     288: new           #40                 // class org/apache/hadoop/hbase/client/Put
     291: dup
     292: aload_3
     293: iload         11
     295: aaload
     296: aload         5
     298: iload         12
     300: laload
     301: invokespecial #41                 // Method org/apache/hadoop/hbase/client/Put."<init>":([BJ)V
     304: astore        13
     306: aload         13
     308: getstatic     #69                 // Field org/apache/hadoop/hbase/HConstants.CATALOG_FAMILY:[B
     311: aconst_null
     312: aload         5
     314: iload         12
     316: laload
     317: aload         5
     319: iload         12
     321: laload
     322: invokestatic  #88                 // Method org/apache/hadoop/hbase/util/Bytes.toBytes:(J)[B
     325: invokevirtual #89                 // Method org/apache/hadoop/hbase/client/Put.addColumn:([B[BJ[B)Lorg/apache/hadoop/hbase/client/Put;
     328: pop
     329: aload         10
     331: aload         13
     333: invokeinterface #90,  2           // InterfaceMethod java/util/List.add:(Ljava/lang/Object;)Z
     338: pop
     339: iinc          12, 1
     342: goto          280
     345: iinc          11, 1
     348: goto          269
     351: aload         6
     353: aload         10
     355: invokeinterface #91,  2           // InterfaceMethod org/apache/hadoop/hbase/client/Table.put:(Ljava/util/List;)V
     360: iconst_0
     361: istore        11
     363: iload         11
     365: aload_3
     366: arraylength
     367: if_icmpge     494
     370: iconst_0
     371: istore        12
     373: iload         12
     375: aload         5
     377: arraylength
     378: if_icmpge     488
     381: new           #52                 // class org/apache/hadoop/hbase/client/Get
     384: dup
     385: aload_3
     386: iload         11
     388: aaload
     389: invokespecial #53                 // Method org/apache/hadoop/hbase/client/Get."<init>":([B)V
     392: astore        13
     394: aload         13
     396: getstatic     #69                 // Field org/apache/hadoop/hbase/HConstants.CATALOG_FAMILY:[B
     399: invokevirtual #92                 // Method org/apache/hadoop/hbase/client/Get.addFamily:([B)Lorg/apache/hadoop/hbase/client/Get;
     402: pop
     403: aload         13
     405: aload         5
     407: iload         12
     409: laload
     410: invokevirtual #93                 // Method org/apache/hadoop/hbase/client/Get.setTimestamp:(J)Lorg/apache/hadoop/hbase/client/Get;
     413: pop
     414: aload         6
     416: aload         13
     418: invokeinterface #54,  2           // InterfaceMethod org/apache/hadoop/hbase/client/Table.get:(Lorg/apache/hadoop/hbase/client/Get;)Lorg/apache/hadoop/hbase/client/Result;
     423: astore        14
     425: iconst_0
     426: istore        15
     428: aload         14
     430: invokevirtual #94                 // Method org/apache/hadoop/hbase/client/Result.listCells:()Ljava/util/List;
     433: invokeinterface #95,  1           // InterfaceMethod java/util/List.iterator:()Ljava/util/Iterator;
     438: astore        16
     440: aload         16
     442: invokeinterface #96,  1           // InterfaceMethod java/util/Iterator.hasNext:()Z
     447: ifeq          468
     450: aload         16
     452: invokeinterface #97,  1           // InterfaceMethod java/util/Iterator.next:()Ljava/lang/Object;
     457: checkcast     #98                 // class org/apache/hadoop/hbase/Cell
     460: astore        17
     462: iinc          15, 1
     465: goto          440
     468: iload         15
     470: iconst_1
     471: if_icmpne     478
     474: iconst_1
     475: goto          479
     478: iconst_0
     479: invokestatic  #59                 // Method org/junit/Assert.assertTrue:(Z)V
     482: iinc          12, 1
     485: goto          373
     488: iinc          11, 1
     491: goto          363
     494: iconst_0
     495: istore        11
     497: new           #99                 // class org/apache/hadoop/hbase/client/Scan
     500: dup
     501: invokespecial #100                // Method org/apache/hadoop/hbase/client/Scan."<init>":()V
     504: astore        12
     506: aload         12
     508: getstatic     #69                 // Field org/apache/hadoop/hbase/HConstants.CATALOG_FAMILY:[B
     511: invokevirtual #101                // Method org/apache/hadoop/hbase/client/Scan.addFamily:([B)Lorg/apache/hadoop/hbase/client/Scan;
     514: pop
     515: aload         6
     517: aload         12
     519: invokeinterface #102,  2          // InterfaceMethod org/apache/hadoop/hbase/client/Table.getScanner:(Lorg/apache/hadoop/hbase/client/Scan;)Lorg/apache/hadoop/hbase/client/ResultScanner;
     524: astore        13
     526: aconst_null
     527: astore        14
     529: aload         13
     531: invokeinterface #103,  1          // InterfaceMethod org/apache/hadoop/hbase/client/ResultScanner.next:()Lorg/apache/hadoop/hbase/client/Result;
     536: dup
     537: astore        14
     539: ifnull        559
     542: getstatic     #104                // Field java/lang/System.out:Ljava/io/PrintStream;
     545: aload         14
     547: invokevirtual #105                // Method org/apache/hadoop/hbase/client/Result.toString:()Ljava/lang/String;
     550: invokevirtual #106                // Method java/io/PrintStream.println:(Ljava/lang/String;)V
     553: iinc          11, 1
     556: goto          529
     559: ldc           #107                // String Number of rows should be 2
     561: ldc2_w        #78                 // long 2l
     564: iload         11
     566: i2l
     567: invokestatic  #108                // Method org/junit/Assert.assertEquals:(Ljava/lang/String;JJ)V
     570: aload         13
     572: invokeinterface #109,  1          // InterfaceMethod org/apache/hadoop/hbase/client/ResultScanner.close:()V
     577: goto          592
     580: astore        18
     582: aload         13
     584: invokeinterface #109,  1          // InterfaceMethod org/apache/hadoop/hbase/client/ResultScanner.close:()V
     589: aload         18
     591: athrow
     592: iconst_0
     593: istore        11
     595: new           #99                 // class org/apache/hadoop/hbase/client/Scan
     598: dup
     599: invokespecial #100                // Method org/apache/hadoop/hbase/client/Scan."<init>":()V
     602: astore        12
     604: aload         12
     606: ldc2_w        #73                 // long 1000l
     609: ldc2_w        #111                // long 9223372036854775807l
     612: invokevirtual #113                // Method org/apache/hadoop/hbase/client/Scan.setTimeRange:(JJ)Lorg/apache/hadoop/hbase/client/Scan;
     615: pop
     616: aload         12
     618: getstatic     #69                 // Field org/apache/hadoop/hbase/HConstants.CATALOG_FAMILY:[B
     621: invokevirtual #101                // Method org/apache/hadoop/hbase/client/Scan.addFamily:([B)Lorg/apache/hadoop/hbase/client/Scan;
     624: pop
     625: aload         6
     627: aload         12
     629: invokeinterface #102,  2          // InterfaceMethod org/apache/hadoop/hbase/client/Table.getScanner:(Lorg/apache/hadoop/hbase/client/Scan;)Lorg/apache/hadoop/hbase/client/ResultScanner;
     634: astore        13
     636: aload         13
     638: invokeinterface #103,  1          // InterfaceMethod org/apache/hadoop/hbase/client/ResultScanner.next:()Lorg/apache/hadoop/hbase/client/Result;
     643: ifnull        652
     646: iinc          11, 1
     649: goto          636
     652: ldc           #107                // String Number of rows should be 2
     654: ldc2_w        #78                 // long 2l
     657: iload         11
     659: i2l
     660: invokestatic  #108                // Method org/junit/Assert.assertEquals:(Ljava/lang/String;JJ)V
     663: aload         13
     665: invokeinterface #109,  1          // InterfaceMethod org/apache/hadoop/hbase/client/ResultScanner.close:()V
     670: goto          685
     673: astore        19
     675: aload         13
     677: invokeinterface #109,  1          // InterfaceMethod org/apache/hadoop/hbase/client/ResultScanner.close:()V
     682: aload         19
     684: athrow
     685: iconst_0
     686: istore        11
     688: new           #99                 // class org/apache/hadoop/hbase/client/Scan
     691: dup
     692: invokespecial #100                // Method org/apache/hadoop/hbase/client/Scan."<init>":()V
     695: astore        12
     697: aload         12
     699: ldc2_w        #73                 // long 1000l
     702: invokevirtual #114                // Method org/apache/hadoop/hbase/client/Scan.setTimestamp:(J)Lorg/apache/hadoop/hbase/client/Scan;
     705: pop
     706: aload         12
     708: getstatic     #69                 // Field org/apache/hadoop/hbase/HConstants.CATALOG_FAMILY:[B
     711: invokevirtual #101                // Method org/apache/hadoop/hbase/client/Scan.addFamily:([B)Lorg/apache/hadoop/hbase/client/Scan;
     714: pop
     715: aload         6
     717: aload         12
     719: invokeinterface #102,  2          // InterfaceMethod org/apache/hadoop/hbase/client/Table.getScanner:(Lorg/apache/hadoop/hbase/client/Scan;)Lorg/apache/hadoop/hbase/client/ResultScanner;
     724: astore        13
     726: aload         13
     728: invokeinterface #103,  1          // InterfaceMethod org/apache/hadoop/hbase/client/ResultScanner.next:()Lorg/apache/hadoop/hbase/client/Result;
     733: ifnull        742
     736: iinc          11, 1
     739: goto          726
     742: ldc           #107                // String Number of rows should be 2
     744: ldc2_w        #78                 // long 2l
     747: iload         11
     749: i2l
     750: invokestatic  #108                // Method org/junit/Assert.assertEquals:(Ljava/lang/String;JJ)V
     753: aload         13
     755: invokeinterface #109,  1          // InterfaceMethod org/apache/hadoop/hbase/client/ResultScanner.close:()V
     760: goto          775
     763: astore        20
     765: aload         13
     767: invokeinterface #109,  1          // InterfaceMethod org/apache/hadoop/hbase/client/ResultScanner.close:()V
     772: aload         20
     774: athrow
     775: iconst_0
     776: istore        11
     778: new           #99                 // class org/apache/hadoop/hbase/client/Scan
     781: dup
     782: invokespecial #100                // Method org/apache/hadoop/hbase/client/Scan."<init>":()V
     785: astore        12
     787: aload         12
     789: ldc2_w        #36                 // long 100l
     792: ldc2_w        #73                 // long 1000l
     795: invokevirtual #113                // Method org/apache/hadoop/hbase/client/Scan.setTimeRange:(JJ)Lorg/apache/hadoop/hbase/client/Scan;
     798: pop
     799: aload         12
     801: getstatic     #69                 // Field org/apache/hadoop/hbase/HConstants.CATALOG_FAMILY:[B
     804: invokevirtual #101                // Method org/apache/hadoop/hbase/client/Scan.addFamily:([B)Lorg/apache/hadoop/hbase/client/Scan;
     807: pop
     808: aload         6
     810: aload         12
     812: invokeinterface #102,  2          // InterfaceMethod org/apache/hadoop/hbase/client/Table.getScanner:(Lorg/apache/hadoop/hbase/client/Scan;)Lorg/apache/hadoop/hbase/client/ResultScanner;
     817: astore        13
     819: aload         13
     821: invokeinterface #103,  1          // InterfaceMethod org/apache/hadoop/hbase/client/ResultScanner.next:()Lorg/apache/hadoop/hbase/client/Result;
     826: ifnull        835
     829: iinc          11, 1
     832: goto          819
     835: ldc           #107                // String Number of rows should be 2
     837: ldc2_w        #78                 // long 2l
     840: iload         11
     842: i2l
     843: invokestatic  #108                // Method org/junit/Assert.assertEquals:(Ljava/lang/String;JJ)V
     846: aload         13
     848: invokeinterface #109,  1          // InterfaceMethod org/apache/hadoop/hbase/client/ResultScanner.close:()V
     853: goto          868
     856: astore        21
     858: aload         13
     860: invokeinterface #109,  1          // InterfaceMethod org/apache/hadoop/hbase/client/ResultScanner.close:()V
     865: aload         21
     867: athrow
     868: iconst_0
     869: istore        11
     871: new           #99                 // class org/apache/hadoop/hbase/client/Scan
     874: dup
     875: invokespecial #100                // Method org/apache/hadoop/hbase/client/Scan."<init>":()V
     878: astore        12
     880: aload         12
     882: ldc2_w        #36                 // long 100l
     885: invokevirtual #114                // Method org/apache/hadoop/hbase/client/Scan.setTimestamp:(J)Lorg/apache/hadoop/hbase/client/Scan;
     888: pop
     889: aload         12
     891: getstatic     #69                 // Field org/apache/hadoop/hbase/HConstants.CATALOG_FAMILY:[B
     894: invokevirtual #101                // Method org/apache/hadoop/hbase/client/Scan.addFamily:([B)Lorg/apache/hadoop/hbase/client/Scan;
     897: pop
     898: aload         6
     900: aload         12
     902: invokeinterface #102,  2          // InterfaceMethod org/apache/hadoop/hbase/client/Table.getScanner:(Lorg/apache/hadoop/hbase/client/Scan;)Lorg/apache/hadoop/hbase/client/ResultScanner;
     907: astore        13
     909: aload         13
     911: invokeinterface #103,  1          // InterfaceMethod org/apache/hadoop/hbase/client/ResultScanner.next:()Lorg/apache/hadoop/hbase/client/Result;
     916: ifnull        925
     919: iinc          11, 1
     922: goto          909
     925: ldc           #107                // String Number of rows should be 2
     927: ldc2_w        #78                 // long 2l
     930: iload         11
     932: i2l
     933: invokestatic  #108                // Method org/junit/Assert.assertEquals:(Ljava/lang/String;JJ)V
     936: aload         13
     938: invokeinterface #109,  1          // InterfaceMethod org/apache/hadoop/hbase/client/ResultScanner.close:()V
     943: goto          958
     946: astore        22
     948: aload         13
     950: invokeinterface #109,  1          // InterfaceMethod org/apache/hadoop/hbase/client/ResultScanner.close:()V
     955: aload         22
     957: athrow
     958: return
    Exception table:
       from    to  target type
         526   570   580   any
         580   582   580   any
         636   663   673   any
         673   675   673   any
         726   753   763   any
         763   765   763   any
         819   846   856   any
         856   858   856   any
         909   936   946   any
         946   948   946   any

  static org.apache.hadoop.hbase.HBaseTestingUtility access$000();
    Code:
       0: getstatic     #1                  // Field UTIL:Lorg/apache/hadoop/hbase/HBaseTestingUtility;
       3: areturn

  static {};
    Code:
       0: ldc           #6                  // class org/apache/hadoop/hbase/TestMultiVersions
       2: invokestatic  #115                // Method org/apache/hadoop/hbase/HBaseClassTestRule.forClass:(Ljava/lang/Class;)Lorg/apache/hadoop/hbase/HBaseClassTestRule;
       5: putstatic     #116                // Field CLASS_RULE:Lorg/apache/hadoop/hbase/HBaseClassTestRule;
       8: ldc           #6                  // class org/apache/hadoop/hbase/TestMultiVersions
      10: invokestatic  #117                // Method org/slf4j/LoggerFactory.getLogger:(Ljava/lang/Class;)Lorg/slf4j/Logger;
      13: putstatic     #45                 // Field LOG:Lorg/slf4j/Logger;
      16: new           #118                // class org/apache/hadoop/hbase/HBaseTestingUtility
      19: dup
      20: invokespecial #119                // Method org/apache/hadoop/hbase/HBaseTestingUtility."<init>":()V
      23: putstatic     #1                  // Field UTIL:Lorg/apache/hadoop/hbase/HBaseTestingUtility;
      26: return
}
