Compiled from "TestAsyncTableUseMetaReplicas.java"
public final class org.apache.hadoop.hbase.client.TestAsyncTableUseMetaReplicas$FailPrimaryMetaScanCp implements org.apache.hadoop.hbase.coprocessor.RegionObserver,org.apache.hadoop.hbase.coprocessor.RegionCoprocessor {
  public org.apache.hadoop.hbase.client.TestAsyncTableUseMetaReplicas$FailPrimaryMetaScanCp();
    Code:
       0: aload_0
       1: invokespecial #1                  // Method java/lang/Object."<init>":()V
       4: return

  public java.util.Optional<org.apache.hadoop.hbase.coprocessor.RegionObserver> getRegionObserver();
    Code:
       0: aload_0
       1: invokestatic  #2                  // Method java/util/Optional.of:(Ljava/lang/Object;)Ljava/util/Optional;
       4: areturn

  public void preScannerOpen(org.apache.hadoop.hbase.coprocessor.ObserverContext<org.apache.hadoop.hbase.coprocessor.RegionCoprocessorEnvironment>, org.apache.hadoop.hbase.client.Scan) throws java.io.IOException;
    Code:
       0: aload_1
       1: invokeinterface #3,  1            // InterfaceMethod org/apache/hadoop/hbase/coprocessor/ObserverContext.getEnvironment:()Lorg/apache/hadoop/hbase/CoprocessorEnvironment;
       6: checkcast     #4                  // class org/apache/hadoop/hbase/coprocessor/RegionCoprocessorEnvironment
       9: invokeinterface #5,  1            // InterfaceMethod org/apache/hadoop/hbase/coprocessor/RegionCoprocessorEnvironment.getRegionInfo:()Lorg/apache/hadoop/hbase/client/RegionInfo;
      14: astore_3
      15: invokestatic  #6                  // Method org/apache/hadoop/hbase/client/TestAsyncTableUseMetaReplicas.access$000:()Z
      18: ifeq          52
      21: aload_3
      22: invokeinterface #7,  1            // InterfaceMethod org/apache/hadoop/hbase/client/RegionInfo.getTable:()Lorg/apache/hadoop/hbase/TableName;
      27: invokestatic  #8                  // Method org/apache/hadoop/hbase/TableName.isMetaTableName:(Lorg/apache/hadoop/hbase/TableName;)Z
      30: ifeq          52
      33: aload_3
      34: invokeinterface #9,  1            // InterfaceMethod org/apache/hadoop/hbase/client/RegionInfo.getReplicaId:()I
      39: ifne          52
      42: new           #10                 // class java/io/IOException
      45: dup
      46: ldc           #11                 // String Inject error
      48: invokespecial #12                 // Method java/io/IOException."<init>":(Ljava/lang/String;)V
      51: athrow
      52: return
}
