Compiled from "TestBloomFilterChunk.java"
public class org.apache.hadoop.hbase.util.TestBloomFilterChunk extends junit.framework.TestCase {
  public static final org.apache.hadoop.hbase.HBaseClassTestRule CLASS_RULE;

  public org.apache.hadoop.hbase.util.TestBloomFilterChunk();
    Code:
       0: aload_0
       1: invokespecial #1                  // Method junit/framework/TestCase."<init>":()V
       4: return

  public void testBasicBloom() throws java.lang.Exception;
    Code:
       0: new           #2                  // class org/apache/hadoop/hbase/util/BloomFilterChunk
       3: dup
       4: sipush        1000
       7: ldc2_w        #3                  // double 0.009999999776482582d
      10: iconst_1
      11: iconst_0
      12: invokespecial #6                  // Method org/apache/hadoop/hbase/util/BloomFilterChunk."<init>":(IDII)V
      15: astore_1
      16: new           #2                  // class org/apache/hadoop/hbase/util/BloomFilterChunk
      19: dup
      20: sipush        1000
      23: ldc2_w        #3                  // double 0.009999999776482582d
      26: iconst_1
      27: iconst_0
      28: invokespecial #6                  // Method org/apache/hadoop/hbase/util/BloomFilterChunk."<init>":(IDII)V
      31: astore_2
      32: aload_1
      33: invokevirtual #7                  // Method org/apache/hadoop/hbase/util/BloomFilterChunk.allocBloom:()V
      36: aload_2
      37: invokevirtual #7                  // Method org/apache/hadoop/hbase/util/BloomFilterChunk.allocBloom:()V
      40: bipush        9
      42: newarray       byte
      44: dup
      45: iconst_0
      46: iconst_1
      47: bastore
      48: dup
      49: iconst_1
      50: iconst_2
      51: bastore
      52: dup
      53: iconst_2
      54: iconst_3
      55: bastore
      56: dup
      57: iconst_3
      58: iconst_4
      59: bastore
      60: dup
      61: iconst_4
      62: iconst_5
      63: bastore
      64: dup
      65: iconst_5
      66: bipush        6
      68: bastore
      69: dup
      70: bipush        6
      72: bipush        7
      74: bastore
      75: dup
      76: bipush        7
      78: bipush        8
      80: bastore
      81: dup
      82: bipush        8
      84: bipush        9
      86: bastore
      87: astore_3
      88: bipush        9
      90: newarray       byte
      92: dup
      93: iconst_0
      94: iconst_1
      95: bastore
      96: dup
      97: iconst_1
      98: iconst_2
      99: bastore
     100: dup
     101: iconst_2
     102: iconst_3
     103: bastore
     104: dup
     105: iconst_3
     106: iconst_4
     107: bastore
     108: dup
     109: iconst_4
     110: iconst_5
     111: bastore
     112: dup
     113: iconst_5
     114: bipush        6
     116: bastore
     117: dup
     118: bipush        6
     120: bipush        7
     122: bastore
     123: dup
     124: bipush        7
     126: bipush        8
     128: bastore
     129: dup
     130: bipush        8
     132: bipush        7
     134: bastore
     135: astore        4
     137: aload_1
     138: aload_3
     139: iconst_0
     140: aload_3
     141: arraylength
     142: invokevirtual #8                  // Method org/apache/hadoop/hbase/util/BloomFilterChunk.add:([BII)V
     145: aload_2
     146: aload         4
     148: iconst_0
     149: aload         4
     151: arraylength
     152: invokevirtual #8                  // Method org/apache/hadoop/hbase/util/BloomFilterChunk.add:([BII)V
     155: aload_3
     156: iconst_0
     157: aload_3
     158: arraylength
     159: new           #9                  // class org/apache/hadoop/hbase/nio/MultiByteBuff
     162: dup
     163: iconst_1
     164: anewarray     #10                 // class java/nio/ByteBuffer
     167: dup
     168: iconst_0
     169: aload_1
     170: getfield      #11                 // Field org/apache/hadoop/hbase/util/BloomFilterChunk.bloom:Ljava/nio/ByteBuffer;
     173: aastore
     174: invokespecial #12                 // Method org/apache/hadoop/hbase/nio/MultiByteBuff."<init>":([Ljava/nio/ByteBuffer;)V
     177: iconst_0
     178: aload_1
     179: getfield      #13                 // Field org/apache/hadoop/hbase/util/BloomFilterChunk.byteSize:J
     182: l2i
     183: aload_1
     184: getfield      #14                 // Field org/apache/hadoop/hbase/util/BloomFilterChunk.hash:Lorg/apache/hadoop/hbase/util/Hash;
     187: aload_1
     188: getfield      #15                 // Field org/apache/hadoop/hbase/util/BloomFilterChunk.hashCount:I
     191: invokestatic  #16                 // Method org/apache/hadoop/hbase/util/BloomFilterUtil.contains:([BIILorg/apache/hadoop/hbase/nio/ByteBuff;IILorg/apache/hadoop/hbase/util/Hash;I)Z
     194: invokestatic  #17                 // Method assertTrue:(Z)V
     197: aload         4
     199: iconst_0
     200: aload         4
     202: arraylength
     203: new           #9                  // class org/apache/hadoop/hbase/nio/MultiByteBuff
     206: dup
     207: iconst_1
     208: anewarray     #10                 // class java/nio/ByteBuffer
     211: dup
     212: iconst_0
     213: aload_1
     214: getfield      #11                 // Field org/apache/hadoop/hbase/util/BloomFilterChunk.bloom:Ljava/nio/ByteBuffer;
     217: aastore
     218: invokespecial #12                 // Method org/apache/hadoop/hbase/nio/MultiByteBuff."<init>":([Ljava/nio/ByteBuffer;)V
     221: iconst_0
     222: aload_1
     223: getfield      #13                 // Field org/apache/hadoop/hbase/util/BloomFilterChunk.byteSize:J
     226: l2i
     227: aload_1
     228: getfield      #14                 // Field org/apache/hadoop/hbase/util/BloomFilterChunk.hash:Lorg/apache/hadoop/hbase/util/Hash;
     231: aload_1
     232: getfield      #15                 // Field org/apache/hadoop/hbase/util/BloomFilterChunk.hashCount:I
     235: invokestatic  #16                 // Method org/apache/hadoop/hbase/util/BloomFilterUtil.contains:([BIILorg/apache/hadoop/hbase/nio/ByteBuff;IILorg/apache/hadoop/hbase/util/Hash;I)Z
     238: invokestatic  #18                 // Method assertFalse:(Z)V
     241: aload_3
     242: iconst_0
     243: aload_3
     244: arraylength
     245: new           #9                  // class org/apache/hadoop/hbase/nio/MultiByteBuff
     248: dup
     249: iconst_1
     250: anewarray     #10                 // class java/nio/ByteBuffer
     253: dup
     254: iconst_0
     255: aload_2
     256: getfield      #11                 // Field org/apache/hadoop/hbase/util/BloomFilterChunk.bloom:Ljava/nio/ByteBuffer;
     259: aastore
     260: invokespecial #12                 // Method org/apache/hadoop/hbase/nio/MultiByteBuff."<init>":([Ljava/nio/ByteBuffer;)V
     263: iconst_0
     264: aload_2
     265: getfield      #13                 // Field org/apache/hadoop/hbase/util/BloomFilterChunk.byteSize:J
     268: l2i
     269: aload_2
     270: getfield      #14                 // Field org/apache/hadoop/hbase/util/BloomFilterChunk.hash:Lorg/apache/hadoop/hbase/util/Hash;
     273: aload_2
     274: getfield      #15                 // Field org/apache/hadoop/hbase/util/BloomFilterChunk.hashCount:I
     277: invokestatic  #16                 // Method org/apache/hadoop/hbase/util/BloomFilterUtil.contains:([BIILorg/apache/hadoop/hbase/nio/ByteBuff;IILorg/apache/hadoop/hbase/util/Hash;I)Z
     280: invokestatic  #18                 // Method assertFalse:(Z)V
     283: aload         4
     285: iconst_0
     286: aload         4
     288: arraylength
     289: new           #9                  // class org/apache/hadoop/hbase/nio/MultiByteBuff
     292: dup
     293: iconst_1
     294: anewarray     #10                 // class java/nio/ByteBuffer
     297: dup
     298: iconst_0
     299: aload_2
     300: getfield      #11                 // Field org/apache/hadoop/hbase/util/BloomFilterChunk.bloom:Ljava/nio/ByteBuffer;
     303: aastore
     304: invokespecial #12                 // Method org/apache/hadoop/hbase/nio/MultiByteBuff."<init>":([Ljava/nio/ByteBuffer;)V
     307: iconst_0
     308: aload_2
     309: getfield      #13                 // Field org/apache/hadoop/hbase/util/BloomFilterChunk.byteSize:J
     312: l2i
     313: aload_2
     314: getfield      #14                 // Field org/apache/hadoop/hbase/util/BloomFilterChunk.hash:Lorg/apache/hadoop/hbase/util/Hash;
     317: aload_2
     318: getfield      #15                 // Field org/apache/hadoop/hbase/util/BloomFilterChunk.hashCount:I
     321: invokestatic  #16                 // Method org/apache/hadoop/hbase/util/BloomFilterUtil.contains:([BIILorg/apache/hadoop/hbase/nio/ByteBuff;IILorg/apache/hadoop/hbase/util/Hash;I)Z
     324: invokestatic  #17                 // Method assertTrue:(Z)V
     327: iconst_4
     328: newarray       byte
     330: dup
     331: iconst_0
     332: iconst_1
     333: bastore
     334: dup
     335: iconst_1
     336: iconst_2
     337: bastore
     338: dup
     339: iconst_2
     340: iconst_3
     341: bastore
     342: dup
     343: iconst_3
     344: iconst_4
     345: bastore
     346: astore        5
     348: ldc           #19                 // String this is a much larger byte array
     350: invokestatic  #20                 // Method org/apache/hadoop/hbase/util/Bytes.toBytes:(Ljava/lang/String;)[B
     353: astore        6
     355: aload_1
     356: aload         5
     358: iconst_0
     359: aload         5
     361: arraylength
     362: invokevirtual #8                  // Method org/apache/hadoop/hbase/util/BloomFilterChunk.add:([BII)V
     365: aload_1
     366: aload         6
     368: iconst_1
     369: aload         6
     371: arraylength
     372: iconst_1
     373: isub
     374: invokevirtual #8                  // Method org/apache/hadoop/hbase/util/BloomFilterChunk.add:([BII)V
     377: aload         5
     379: iconst_0
     380: aload         5
     382: arraylength
     383: new           #9                  // class org/apache/hadoop/hbase/nio/MultiByteBuff
     386: dup
     387: iconst_1
     388: anewarray     #10                 // class java/nio/ByteBuffer
     391: dup
     392: iconst_0
     393: aload_1
     394: getfield      #11                 // Field org/apache/hadoop/hbase/util/BloomFilterChunk.bloom:Ljava/nio/ByteBuffer;
     397: aastore
     398: invokespecial #12                 // Method org/apache/hadoop/hbase/nio/MultiByteBuff."<init>":([Ljava/nio/ByteBuffer;)V
     401: iconst_0
     402: aload_1
     403: getfield      #13                 // Field org/apache/hadoop/hbase/util/BloomFilterChunk.byteSize:J
     406: l2i
     407: aload_1
     408: getfield      #14                 // Field org/apache/hadoop/hbase/util/BloomFilterChunk.hash:Lorg/apache/hadoop/hbase/util/Hash;
     411: aload_1
     412: getfield      #15                 // Field org/apache/hadoop/hbase/util/BloomFilterChunk.hashCount:I
     415: invokestatic  #16                 // Method org/apache/hadoop/hbase/util/BloomFilterUtil.contains:([BIILorg/apache/hadoop/hbase/nio/ByteBuff;IILorg/apache/hadoop/hbase/util/Hash;I)Z
     418: invokestatic  #17                 // Method assertTrue:(Z)V
     421: aload         6
     423: iconst_1
     424: aload         6
     426: arraylength
     427: iconst_1
     428: isub
     429: new           #9                  // class org/apache/hadoop/hbase/nio/MultiByteBuff
     432: dup
     433: iconst_1
     434: anewarray     #10                 // class java/nio/ByteBuffer
     437: dup
     438: iconst_0
     439: aload_1
     440: getfield      #11                 // Field org/apache/hadoop/hbase/util/BloomFilterChunk.bloom:Ljava/nio/ByteBuffer;
     443: aastore
     444: invokespecial #12                 // Method org/apache/hadoop/hbase/nio/MultiByteBuff."<init>":([Ljava/nio/ByteBuffer;)V
     447: iconst_0
     448: aload_1
     449: getfield      #13                 // Field org/apache/hadoop/hbase/util/BloomFilterChunk.byteSize:J
     452: l2i
     453: aload_1
     454: getfield      #14                 // Field org/apache/hadoop/hbase/util/BloomFilterChunk.hash:Lorg/apache/hadoop/hbase/util/Hash;
     457: aload_1
     458: getfield      #15                 // Field org/apache/hadoop/hbase/util/BloomFilterChunk.hashCount:I
     461: invokestatic  #16                 // Method org/apache/hadoop/hbase/util/BloomFilterUtil.contains:([BIILorg/apache/hadoop/hbase/nio/ByteBuff;IILorg/apache/hadoop/hbase/util/Hash;I)Z
     464: invokestatic  #17                 // Method assertTrue:(Z)V
     467: aload         6
     469: iconst_0
     470: aload         6
     472: arraylength
     473: new           #9                  // class org/apache/hadoop/hbase/nio/MultiByteBuff
     476: dup
     477: iconst_1
     478: anewarray     #10                 // class java/nio/ByteBuffer
     481: dup
     482: iconst_0
     483: aload_1
     484: getfield      #11                 // Field org/apache/hadoop/hbase/util/BloomFilterChunk.bloom:Ljava/nio/ByteBuffer;
     487: aastore
     488: invokespecial #12                 // Method org/apache/hadoop/hbase/nio/MultiByteBuff."<init>":([Ljava/nio/ByteBuffer;)V
     491: iconst_0
     492: aload_1
     493: getfield      #13                 // Field org/apache/hadoop/hbase/util/BloomFilterChunk.byteSize:J
     496: l2i
     497: aload_1
     498: getfield      #14                 // Field org/apache/hadoop/hbase/util/BloomFilterChunk.hash:Lorg/apache/hadoop/hbase/util/Hash;
     501: aload_1
     502: getfield      #15                 // Field org/apache/hadoop/hbase/util/BloomFilterChunk.hashCount:I
     505: invokestatic  #16                 // Method org/apache/hadoop/hbase/util/BloomFilterUtil.contains:([BIILorg/apache/hadoop/hbase/nio/ByteBuff;IILorg/apache/hadoop/hbase/util/Hash;I)Z
     508: invokestatic  #18                 // Method assertFalse:(Z)V
     511: new           #21                 // class java/io/ByteArrayOutputStream
     514: dup
     515: invokespecial #22                 // Method java/io/ByteArrayOutputStream."<init>":()V
     518: astore        7
     520: aload_1
     521: new           #23                 // class java/io/DataOutputStream
     524: dup
     525: aload         7
     527: invokespecial #24                 // Method java/io/DataOutputStream."<init>":(Ljava/io/OutputStream;)V
     530: invokevirtual #25                 // Method org/apache/hadoop/hbase/util/BloomFilterChunk.writeBloom:(Ljava/io/DataOutput;)V
     533: aload         7
     535: invokevirtual #26                 // Method java/io/ByteArrayOutputStream.toByteArray:()[B
     538: invokestatic  #27                 // Method java/nio/ByteBuffer.wrap:([B)Ljava/nio/ByteBuffer;
     541: astore        8
     543: new           #2                  // class org/apache/hadoop/hbase/util/BloomFilterChunk
     546: dup
     547: sipush        1000
     550: ldc2_w        #3                  // double 0.009999999776482582d
     553: iconst_1
     554: iconst_0
     555: invokespecial #6                  // Method org/apache/hadoop/hbase/util/BloomFilterChunk."<init>":(IDII)V
     558: astore        9
     560: aload_3
     561: iconst_0
     562: aload_3
     563: arraylength
     564: new           #9                  // class org/apache/hadoop/hbase/nio/MultiByteBuff
     567: dup
     568: iconst_1
     569: anewarray     #10                 // class java/nio/ByteBuffer
     572: dup
     573: iconst_0
     574: aload         8
     576: aastore
     577: invokespecial #12                 // Method org/apache/hadoop/hbase/nio/MultiByteBuff."<init>":([Ljava/nio/ByteBuffer;)V
     580: iconst_0
     581: aload         9
     583: getfield      #13                 // Field org/apache/hadoop/hbase/util/BloomFilterChunk.byteSize:J
     586: l2i
     587: aload         9
     589: getfield      #14                 // Field org/apache/hadoop/hbase/util/BloomFilterChunk.hash:Lorg/apache/hadoop/hbase/util/Hash;
     592: aload         9
     594: getfield      #15                 // Field org/apache/hadoop/hbase/util/BloomFilterChunk.hashCount:I
     597: invokestatic  #16                 // Method org/apache/hadoop/hbase/util/BloomFilterUtil.contains:([BIILorg/apache/hadoop/hbase/nio/ByteBuff;IILorg/apache/hadoop/hbase/util/Hash;I)Z
     600: invokestatic  #17                 // Method assertTrue:(Z)V
     603: aload         4
     605: iconst_0
     606: aload         4
     608: arraylength
     609: new           #9                  // class org/apache/hadoop/hbase/nio/MultiByteBuff
     612: dup
     613: iconst_1
     614: anewarray     #10                 // class java/nio/ByteBuffer
     617: dup
     618: iconst_0
     619: aload         8
     621: aastore
     622: invokespecial #12                 // Method org/apache/hadoop/hbase/nio/MultiByteBuff."<init>":([Ljava/nio/ByteBuffer;)V
     625: iconst_0
     626: aload         9
     628: getfield      #13                 // Field org/apache/hadoop/hbase/util/BloomFilterChunk.byteSize:J
     631: l2i
     632: aload         9
     634: getfield      #14                 // Field org/apache/hadoop/hbase/util/BloomFilterChunk.hash:Lorg/apache/hadoop/hbase/util/Hash;
     637: aload         9
     639: getfield      #15                 // Field org/apache/hadoop/hbase/util/BloomFilterChunk.hashCount:I
     642: invokestatic  #16                 // Method org/apache/hadoop/hbase/util/BloomFilterUtil.contains:([BIILorg/apache/hadoop/hbase/nio/ByteBuff;IILorg/apache/hadoop/hbase/util/Hash;I)Z
     645: invokestatic  #18                 // Method assertFalse:(Z)V
     648: aload         5
     650: iconst_0
     651: aload         5
     653: arraylength
     654: new           #9                  // class org/apache/hadoop/hbase/nio/MultiByteBuff
     657: dup
     658: iconst_1
     659: anewarray     #10                 // class java/nio/ByteBuffer
     662: dup
     663: iconst_0
     664: aload         8
     666: aastore
     667: invokespecial #12                 // Method org/apache/hadoop/hbase/nio/MultiByteBuff."<init>":([Ljava/nio/ByteBuffer;)V
     670: iconst_0
     671: aload         9
     673: getfield      #13                 // Field org/apache/hadoop/hbase/util/BloomFilterChunk.byteSize:J
     676: l2i
     677: aload         9
     679: getfield      #14                 // Field org/apache/hadoop/hbase/util/BloomFilterChunk.hash:Lorg/apache/hadoop/hbase/util/Hash;
     682: aload         9
     684: getfield      #15                 // Field org/apache/hadoop/hbase/util/BloomFilterChunk.hashCount:I
     687: invokestatic  #16                 // Method org/apache/hadoop/hbase/util/BloomFilterUtil.contains:([BIILorg/apache/hadoop/hbase/nio/ByteBuff;IILorg/apache/hadoop/hbase/util/Hash;I)Z
     690: invokestatic  #17                 // Method assertTrue:(Z)V
     693: aload         6
     695: iconst_1
     696: aload         6
     698: arraylength
     699: iconst_1
     700: isub
     701: new           #9                  // class org/apache/hadoop/hbase/nio/MultiByteBuff
     704: dup
     705: iconst_1
     706: anewarray     #10                 // class java/nio/ByteBuffer
     709: dup
     710: iconst_0
     711: aload         8
     713: aastore
     714: invokespecial #12                 // Method org/apache/hadoop/hbase/nio/MultiByteBuff."<init>":([Ljava/nio/ByteBuffer;)V
     717: iconst_0
     718: aload         9
     720: getfield      #13                 // Field org/apache/hadoop/hbase/util/BloomFilterChunk.byteSize:J
     723: l2i
     724: aload         9
     726: getfield      #14                 // Field org/apache/hadoop/hbase/util/BloomFilterChunk.hash:Lorg/apache/hadoop/hbase/util/Hash;
     729: aload         9
     731: getfield      #15                 // Field org/apache/hadoop/hbase/util/BloomFilterChunk.hashCount:I
     734: invokestatic  #16                 // Method org/apache/hadoop/hbase/util/BloomFilterUtil.contains:([BIILorg/apache/hadoop/hbase/nio/ByteBuff;IILorg/apache/hadoop/hbase/util/Hash;I)Z
     737: invokestatic  #17                 // Method assertTrue:(Z)V
     740: aload         6
     742: iconst_0
     743: aload         6
     745: arraylength
     746: new           #9                  // class org/apache/hadoop/hbase/nio/MultiByteBuff
     749: dup
     750: iconst_1
     751: anewarray     #10                 // class java/nio/ByteBuffer
     754: dup
     755: iconst_0
     756: aload         8
     758: aastore
     759: invokespecial #12                 // Method org/apache/hadoop/hbase/nio/MultiByteBuff."<init>":([Ljava/nio/ByteBuffer;)V
     762: iconst_0
     763: aload         9
     765: getfield      #13                 // Field org/apache/hadoop/hbase/util/BloomFilterChunk.byteSize:J
     768: l2i
     769: aload         9
     771: getfield      #14                 // Field org/apache/hadoop/hbase/util/BloomFilterChunk.hash:Lorg/apache/hadoop/hbase/util/Hash;
     774: aload         9
     776: getfield      #15                 // Field org/apache/hadoop/hbase/util/BloomFilterChunk.hashCount:I
     779: invokestatic  #16                 // Method org/apache/hadoop/hbase/util/BloomFilterUtil.contains:([BIILorg/apache/hadoop/hbase/nio/ByteBuff;IILorg/apache/hadoop/hbase/util/Hash;I)Z
     782: invokestatic  #18                 // Method assertFalse:(Z)V
     785: aload         6
     787: iconst_0
     788: aload         6
     790: arraylength
     791: new           #9                  // class org/apache/hadoop/hbase/nio/MultiByteBuff
     794: dup
     795: iconst_1
     796: anewarray     #10                 // class java/nio/ByteBuffer
     799: dup
     800: iconst_0
     801: aload         8
     803: aastore
     804: invokespecial #12                 // Method org/apache/hadoop/hbase/nio/MultiByteBuff."<init>":([Ljava/nio/ByteBuffer;)V
     807: iconst_0
     808: aload         9
     810: getfield      #13                 // Field org/apache/hadoop/hbase/util/BloomFilterChunk.byteSize:J
     813: l2i
     814: aload         9
     816: getfield      #14                 // Field org/apache/hadoop/hbase/util/BloomFilterChunk.hash:Lorg/apache/hadoop/hbase/util/Hash;
     819: aload         9
     821: getfield      #15                 // Field org/apache/hadoop/hbase/util/BloomFilterChunk.hashCount:I
     824: invokestatic  #16                 // Method org/apache/hadoop/hbase/util/BloomFilterUtil.contains:([BIILorg/apache/hadoop/hbase/nio/ByteBuff;IILorg/apache/hadoop/hbase/util/Hash;I)Z
     827: invokestatic  #18                 // Method assertFalse:(Z)V
     830: getstatic     #28                 // Field java/lang/System.out:Ljava/io/PrintStream;
     833: new           #29                 // class java/lang/StringBuilder
     836: dup
     837: invokespecial #30                 // Method java/lang/StringBuilder."<init>":()V
     840: ldc           #31                 // String Serialized as
     842: invokevirtual #32                 // Method java/lang/StringBuilder.append:(Ljava/lang/String;)Ljava/lang/StringBuilder;
     845: aload         7
     847: invokevirtual #33                 // Method java/io/ByteArrayOutputStream.size:()I
     850: invokevirtual #34                 // Method java/lang/StringBuilder.append:(I)Ljava/lang/StringBuilder;
     853: ldc           #35                 // String  bytes
     855: invokevirtual #32                 // Method java/lang/StringBuilder.append:(Ljava/lang/String;)Ljava/lang/StringBuilder;
     858: invokevirtual #36                 // Method java/lang/StringBuilder.toString:()Ljava/lang/String;
     861: invokevirtual #37                 // Method java/io/PrintStream.println:(Ljava/lang/String;)V
     864: aload         7
     866: invokevirtual #33                 // Method java/io/ByteArrayOutputStream.size:()I
     869: i2l
     870: aload_1
     871: getfield      #13                 // Field org/apache/hadoop/hbase/util/BloomFilterChunk.byteSize:J
     874: lsub
     875: ldc2_w        #38                 // long 10l
     878: lcmp
     879: ifge          886
     882: iconst_1
     883: goto          887
     886: iconst_0
     887: invokestatic  #17                 // Method assertTrue:(Z)V
     890: return

  public void testBloomFold() throws java.lang.Exception;
    Code:
       0: new           #2                  // class org/apache/hadoop/hbase/util/BloomFilterChunk
       3: dup
       4: sipush        1003
       7: ldc2_w        #3                  // double 0.009999999776482582d
      10: iconst_1
      11: iconst_2
      12: invokespecial #6                  // Method org/apache/hadoop/hbase/util/BloomFilterChunk."<init>":(IDII)V
      15: astore_1
      16: aload_1
      17: invokevirtual #7                  // Method org/apache/hadoop/hbase/util/BloomFilterChunk.allocBloom:()V
      20: aload_1
      21: invokevirtual #40                 // Method org/apache/hadoop/hbase/util/BloomFilterChunk.getByteSize:()J
      24: lstore_2
      25: ldc2_w        #41                 // long 1204l
      28: lload_2
      29: invokestatic  #43                 // Method assertEquals:(JJ)V
      32: iconst_0
      33: istore        4
      35: iload         4
      37: bipush        12
      39: if_icmpge     65
      42: iload         4
      44: invokestatic  #44                 // Method org/apache/hadoop/hbase/util/Bytes.toBytes:(I)[B
      47: astore        5
      49: aload_1
      50: aload         5
      52: iconst_0
      53: aload         5
      55: arraylength
      56: invokevirtual #8                  // Method org/apache/hadoop/hbase/util/BloomFilterChunk.add:([BII)V
      59: iinc          4, 1
      62: goto          35
      65: aload_1
      66: invokevirtual #45                 // Method org/apache/hadoop/hbase/util/BloomFilterChunk.compactBloom:()V
      69: lload_2
      70: iconst_2
      71: lshr
      72: aload_1
      73: invokevirtual #40                 // Method org/apache/hadoop/hbase/util/BloomFilterChunk.getByteSize:()J
      76: invokestatic  #43                 // Method assertEquals:(JJ)V
      79: iconst_0
      80: istore        4
      82: iconst_0
      83: istore        5
      85: iload         5
      87: bipush        25
      89: if_icmpge     177
      92: iload         5
      94: invokestatic  #44                 // Method org/apache/hadoop/hbase/util/Bytes.toBytes:(I)[B
      97: astore        6
      99: aload         6
     101: iconst_0
     102: aload         6
     104: arraylength
     105: new           #9                  // class org/apache/hadoop/hbase/nio/MultiByteBuff
     108: dup
     109: iconst_1
     110: anewarray     #10                 // class java/nio/ByteBuffer
     113: dup
     114: iconst_0
     115: aload_1
     116: getfield      #11                 // Field org/apache/hadoop/hbase/util/BloomFilterChunk.bloom:Ljava/nio/ByteBuffer;
     119: aastore
     120: invokespecial #12                 // Method org/apache/hadoop/hbase/nio/MultiByteBuff."<init>":([Ljava/nio/ByteBuffer;)V
     123: iconst_0
     124: aload_1
     125: getfield      #13                 // Field org/apache/hadoop/hbase/util/BloomFilterChunk.byteSize:J
     128: l2i
     129: aload_1
     130: getfield      #14                 // Field org/apache/hadoop/hbase/util/BloomFilterChunk.hash:Lorg/apache/hadoop/hbase/util/Hash;
     133: aload_1
     134: getfield      #15                 // Field org/apache/hadoop/hbase/util/BloomFilterChunk.hashCount:I
     137: invokestatic  #16                 // Method org/apache/hadoop/hbase/util/BloomFilterUtil.contains:([BIILorg/apache/hadoop/hbase/nio/ByteBuff;IILorg/apache/hadoop/hbase/util/Hash;I)Z
     140: ifeq          156
     143: iload         5
     145: bipush        12
     147: if_icmplt     171
     150: iinc          4, 1
     153: goto          171
     156: iload         5
     158: bipush        12
     160: if_icmpge     167
     163: iconst_1
     164: goto          168
     167: iconst_0
     168: invokestatic  #18                 // Method assertFalse:(Z)V
     171: iinc          5, 1
     174: goto          85
     177: iload         4
     179: iconst_1
     180: if_icmpgt     187
     183: iconst_1
     184: goto          188
     187: iconst_0
     188: invokestatic  #17                 // Method assertTrue:(Z)V
     191: return

  public void testBloomPerf() throws java.lang.Exception;
    Code:
       0: ldc           #46                 // float 0.01f
       2: fstore_1
       3: new           #2                  // class org/apache/hadoop/hbase/util/BloomFilterChunk
       6: dup
       7: ldc           #47                 // int 10000000
       9: fload_1
      10: f2d
      11: iconst_1
      12: iconst_3
      13: invokespecial #6                  // Method org/apache/hadoop/hbase/util/BloomFilterChunk."<init>":(IDII)V
      16: astore_2
      17: aload_2
      18: invokevirtual #7                  // Method org/apache/hadoop/hbase/util/BloomFilterChunk.allocBloom:()V
      21: invokestatic  #48                 // Method java/lang/System.currentTimeMillis:()J
      24: lstore_3
      25: aload_2
      26: invokevirtual #40                 // Method org/apache/hadoop/hbase/util/BloomFilterChunk.getByteSize:()J
      29: lstore        5
      31: iconst_0
      32: istore        7
      34: iload         7
      36: ldc           #49                 // int 1000000
      38: if_icmpge     64
      41: iload         7
      43: invokestatic  #44                 // Method org/apache/hadoop/hbase/util/Bytes.toBytes:(I)[B
      46: astore        8
      48: aload_2
      49: aload         8
      51: iconst_0
      52: aload         8
      54: arraylength
      55: invokevirtual #8                  // Method org/apache/hadoop/hbase/util/BloomFilterChunk.add:([BII)V
      58: iinc          7, 1
      61: goto          34
      64: invokestatic  #48                 // Method java/lang/System.currentTimeMillis:()J
      67: lstore        7
      69: getstatic     #28                 // Field java/lang/System.out:Ljava/io/PrintStream;
      72: new           #29                 // class java/lang/StringBuilder
      75: dup
      76: invokespecial #30                 // Method java/lang/StringBuilder."<init>":()V
      79: ldc           #50                 // String Total Add time =
      81: invokevirtual #32                 // Method java/lang/StringBuilder.append:(Ljava/lang/String;)Ljava/lang/StringBuilder;
      84: lload         7
      86: lload_3
      87: lsub
      88: invokevirtual #51                 // Method java/lang/StringBuilder.append:(J)Ljava/lang/StringBuilder;
      91: ldc           #52                 // String ms
      93: invokevirtual #32                 // Method java/lang/StringBuilder.append:(Ljava/lang/String;)Ljava/lang/StringBuilder;
      96: invokevirtual #36                 // Method java/lang/StringBuilder.toString:()Ljava/lang/String;
      99: invokevirtual #37                 // Method java/io/PrintStream.println:(Ljava/lang/String;)V
     102: invokestatic  #48                 // Method java/lang/System.currentTimeMillis:()J
     105: lstore_3
     106: aload_2
     107: invokevirtual #45                 // Method org/apache/hadoop/hbase/util/BloomFilterChunk.compactBloom:()V
     110: invokestatic  #48                 // Method java/lang/System.currentTimeMillis:()J
     113: lstore        7
     115: getstatic     #28                 // Field java/lang/System.out:Ljava/io/PrintStream;
     118: new           #29                 // class java/lang/StringBuilder
     121: dup
     122: invokespecial #30                 // Method java/lang/StringBuilder."<init>":()V
     125: ldc           #53                 // String Total Fold time =
     127: invokevirtual #32                 // Method java/lang/StringBuilder.append:(Ljava/lang/String;)Ljava/lang/StringBuilder;
     130: lload         7
     132: lload_3
     133: lsub
     134: invokevirtual #51                 // Method java/lang/StringBuilder.append:(J)Ljava/lang/StringBuilder;
     137: ldc           #52                 // String ms
     139: invokevirtual #32                 // Method java/lang/StringBuilder.append:(Ljava/lang/String;)Ljava/lang/StringBuilder;
     142: invokevirtual #36                 // Method java/lang/StringBuilder.toString:()Ljava/lang/String;
     145: invokevirtual #37                 // Method java/io/PrintStream.println:(Ljava/lang/String;)V
     148: lload         5
     150: aload_2
     151: invokevirtual #40                 // Method org/apache/hadoop/hbase/util/BloomFilterChunk.getByteSize:()J
     154: iconst_3
     155: lshl
     156: lcmp
     157: iflt          164
     160: iconst_1
     161: goto          165
     164: iconst_0
     165: invokestatic  #17                 // Method assertTrue:(Z)V
     168: invokestatic  #48                 // Method java/lang/System.currentTimeMillis:()J
     171: lstore_3
     172: iconst_0
     173: istore        9
     175: iconst_0
     176: istore        10
     178: iload         10
     180: ldc           #54                 // int 2000000
     182: if_icmpge     270
     185: iload         10
     187: invokestatic  #44                 // Method org/apache/hadoop/hbase/util/Bytes.toBytes:(I)[B
     190: astore        11
     192: aload         11
     194: iconst_0
     195: aload         11
     197: arraylength
     198: new           #9                  // class org/apache/hadoop/hbase/nio/MultiByteBuff
     201: dup
     202: iconst_1
     203: anewarray     #10                 // class java/nio/ByteBuffer
     206: dup
     207: iconst_0
     208: aload_2
     209: getfield      #11                 // Field org/apache/hadoop/hbase/util/BloomFilterChunk.bloom:Ljava/nio/ByteBuffer;
     212: aastore
     213: invokespecial #12                 // Method org/apache/hadoop/hbase/nio/MultiByteBuff."<init>":([Ljava/nio/ByteBuffer;)V
     216: iconst_0
     217: aload_2
     218: getfield      #13                 // Field org/apache/hadoop/hbase/util/BloomFilterChunk.byteSize:J
     221: l2i
     222: aload_2
     223: getfield      #14                 // Field org/apache/hadoop/hbase/util/BloomFilterChunk.hash:Lorg/apache/hadoop/hbase/util/Hash;
     226: aload_2
     227: getfield      #15                 // Field org/apache/hadoop/hbase/util/BloomFilterChunk.hashCount:I
     230: invokestatic  #16                 // Method org/apache/hadoop/hbase/util/BloomFilterUtil.contains:([BIILorg/apache/hadoop/hbase/nio/ByteBuff;IILorg/apache/hadoop/hbase/util/Hash;I)Z
     233: ifeq          249
     236: iload         10
     238: ldc           #49                 // int 1000000
     240: if_icmplt     264
     243: iinc          9, 1
     246: goto          264
     249: iload         10
     251: ldc           #49                 // int 1000000
     253: if_icmpge     260
     256: iconst_1
     257: goto          261
     260: iconst_0
     261: invokestatic  #18                 // Method assertFalse:(Z)V
     264: iinc          10, 1
     267: goto          178
     270: invokestatic  #48                 // Method java/lang/System.currentTimeMillis:()J
     273: lstore        7
     275: getstatic     #28                 // Field java/lang/System.out:Ljava/io/PrintStream;
     278: new           #29                 // class java/lang/StringBuilder
     281: dup
     282: invokespecial #30                 // Method java/lang/StringBuilder."<init>":()V
     285: ldc           #55                 // String Total Contains time =
     287: invokevirtual #32                 // Method java/lang/StringBuilder.append:(Ljava/lang/String;)Ljava/lang/StringBuilder;
     290: lload         7
     292: lload_3
     293: lsub
     294: invokevirtual #51                 // Method java/lang/StringBuilder.append:(J)Ljava/lang/StringBuilder;
     297: ldc           #52                 // String ms
     299: invokevirtual #32                 // Method java/lang/StringBuilder.append:(Ljava/lang/String;)Ljava/lang/StringBuilder;
     302: invokevirtual #36                 // Method java/lang/StringBuilder.toString:()Ljava/lang/String;
     305: invokevirtual #37                 // Method java/io/PrintStream.println:(Ljava/lang/String;)V
     308: getstatic     #28                 // Field java/lang/System.out:Ljava/io/PrintStream;
     311: new           #29                 // class java/lang/StringBuilder
     314: dup
     315: invokespecial #30                 // Method java/lang/StringBuilder."<init>":()V
     318: ldc           #56                 // String False Positive =
     320: invokevirtual #32                 // Method java/lang/StringBuilder.append:(Ljava/lang/String;)Ljava/lang/StringBuilder;
     323: iload         9
     325: invokevirtual #34                 // Method java/lang/StringBuilder.append:(I)Ljava/lang/StringBuilder;
     328: invokevirtual #36                 // Method java/lang/StringBuilder.toString:()Ljava/lang/String;
     331: invokevirtual #37                 // Method java/io/PrintStream.println:(Ljava/lang/String;)V
     334: iload         9
     336: i2f
     337: ldc           #57                 // float 1000000.0f
     339: fload_1
     340: fmul
     341: fcmpg
     342: ifgt          349
     345: iconst_1
     346: goto          350
     349: iconst_0
     350: invokestatic  #17                 // Method assertTrue:(Z)V
     353: return

  public void testSizing();
    Code:
       0: ldc           #58                 // int 1048576
       2: istore_1
       3: ldc2_w        #59                 // double 0.025d
       6: dstore_2
       7: iload_1
       8: i2l
       9: dload_2
      10: invokestatic  #61                 // Method org/apache/hadoop/hbase/util/BloomFilterUtil.idealMaxKeys:(JD)J
      13: lstore        4
      15: ldc2_w        #62                 // long 136570l
      18: lload         4
      20: invokestatic  #43                 // Method assertEquals:(JJ)V
      23: lload         4
      25: dload_2
      26: invokestatic  #64                 // Method org/apache/hadoop/hbase/util/BloomFilterUtil.computeBitSize:(JD)J
      29: lstore        6
      31: lload         6
      33: iload_1
      34: i2l
      35: lsub
      36: invokestatic  #65                 // Method java/lang/Math.abs:(J)J
      39: l2d
      40: dconst_1
      41: dmul
      42: iload_1
      43: i2d
      44: ddiv
      45: ldc2_w        #66                 // double 1.0E-5d
      48: dcmpg
      49: ifge          56
      52: iconst_1
      53: goto          57
      56: iconst_0
      57: invokestatic  #17                 // Method assertTrue:(Z)V
      60: return

  public void testFoldableByteSize();
    Code:
       0: sipush        128
       3: ldc2_w        #68                 // long 1000l
       6: iconst_5
       7: invokestatic  #70                 // Method org/apache/hadoop/hbase/util/BloomFilterUtil.computeFoldableByteSize:(JI)I
      10: invokestatic  #71                 // Method assertEquals:(II)V
      13: sipush        640
      16: ldc2_w        #72                 // long 5001l
      19: iconst_4
      20: invokestatic  #70                 // Method org/apache/hadoop/hbase/util/BloomFilterUtil.computeFoldableByteSize:(JI)I
      23: invokestatic  #71                 // Method assertEquals:(II)V
      26: return

  static {};
    Code:
       0: ldc           #74                 // class org/apache/hadoop/hbase/util/TestBloomFilterChunk
       2: invokestatic  #75                 // Method org/apache/hadoop/hbase/HBaseClassTestRule.forClass:(Ljava/lang/Class;)Lorg/apache/hadoop/hbase/HBaseClassTestRule;
       5: putstatic     #76                 // Field CLASS_RULE:Lorg/apache/hadoop/hbase/HBaseClassTestRule;
       8: return
}
