Compiled from "TestThreads.java"
class org.apache.hadoop.hbase.util.TestThreads$1 implements java.lang.Runnable {
  final org.apache.hadoop.hbase.util.TestThreads this$0;

  org.apache.hadoop.hbase.util.TestThreads$1(org.apache.hadoop.hbase.util.TestThreads);
    Code:
       0: aload_0
       1: aload_1
       2: putfield      #2                  // Field this$0:Lorg/apache/hadoop/hbase/util/TestThreads;
       5: aload_0
       6: invokespecial #3                  // Method java/lang/Object."<init>":()V
       9: return

  public void run();
    Code:
       0: invokestatic  #4                  // Method org/apache/hadoop/hbase/util/TestThreads.access$000:()Lorg/slf4j/Logger;
       3: ldc           #5                  // String Sleeper thread: sleeping for 3000
       5: invokeinterface #6,  2            // InterfaceMethod org/slf4j/Logger.debug:(Ljava/lang/String;)V
      10: ldc2_w        #7                  // long 3000l
      13: invokestatic  #9                  // Method org/apache/hadoop/hbase/util/Threads.sleepWithoutInterrupt:(J)V
      16: invokestatic  #4                  // Method org/apache/hadoop/hbase/util/TestThreads.access$000:()Lorg/slf4j/Logger;
      19: ldc           #10                 // String Sleeper thread: finished sleeping
      21: invokeinterface #6,  2            // InterfaceMethod org/slf4j/Logger.debug:(Ljava/lang/String;)V
      26: aload_0
      27: getfield      #2                  // Field this$0:Lorg/apache/hadoop/hbase/util/TestThreads;
      30: invokestatic  #11                 // Method org/apache/hadoop/hbase/util/TestThreads.access$100:(Lorg/apache/hadoop/hbase/util/TestThreads;)Ljava/util/concurrent/atomic/AtomicBoolean;
      33: invokestatic  #12                 // Method java/lang/Thread.currentThread:()Ljava/lang/Thread;
      36: invokevirtual #13                 // Method java/lang/Thread.isInterrupted:()Z
      39: invokevirtual #14                 // Method java/util/concurrent/atomic/AtomicBoolean.set:(Z)V
      42: return
}
