Compiled from "TestProcedureFuture.java"
class org.apache.hadoop.hbase.client.TestProcedureFuture$TestFuture extends org.apache.hadoop.hbase.client.HBaseAdmin$ProcedureFuture<java.lang.Void> {
  public org.apache.hadoop.hbase.client.TestProcedureFuture$TestFuture(org.apache.hadoop.hbase.client.HBaseAdmin, java.lang.Long);
    Code:
       0: aload_0
       1: aload_1
       2: aload_2
       3: invokespecial #1                  // Method org/apache/hadoop/hbase/client/HBaseAdmin$ProcedureFuture."<init>":(Lorg/apache/hadoop/hbase/client/HBaseAdmin;Ljava/lang/Long;)V
       6: aload_0
       7: iconst_0
       8: putfield      #2                  // Field postOperationResultCalled:Z
      11: aload_0
      12: iconst_0
      13: putfield      #3                  // Field waitOperationResultCalled:Z
      16: aload_0
      17: iconst_0
      18: putfield      #4                  // Field getProcedureResultCalled:Z
      21: aload_0
      22: iconst_0
      23: putfield      #5                  // Field convertResultCalled:Z
      26: return

  public boolean wasPostOperationResultCalled();
    Code:
       0: aload_0
       1: getfield      #2                  // Field postOperationResultCalled:Z
       4: ireturn

  public boolean wasWaitOperationResultCalled();
    Code:
       0: aload_0
       1: getfield      #3                  // Field waitOperationResultCalled:Z
       4: ireturn

  public boolean wasGetProcedureResultCalled();
    Code:
       0: aload_0
       1: getfield      #4                  // Field getProcedureResultCalled:Z
       4: ireturn

  public boolean wasConvertResultCalled();
    Code:
       0: aload_0
       1: getfield      #5                  // Field convertResultCalled:Z
       4: ireturn

  protected org.apache.hadoop.hbase.shaded.protobuf.generated.MasterProtos$GetProcedureResultResponse getProcedureResult(org.apache.hadoop.hbase.shaded.protobuf.generated.MasterProtos$GetProcedureResultRequest) throws java.io.IOException;
    Code:
       0: aload_0
       1: iconst_1
       2: putfield      #4                  // Field getProcedureResultCalled:Z
       5: invokestatic  #6                  // Method org/apache/hadoop/hbase/shaded/protobuf/generated/MasterProtos$GetProcedureResultResponse.newBuilder:()Lorg/apache/hadoop/hbase/shaded/protobuf/generated/MasterProtos$GetProcedureResultResponse$Builder;
       8: getstatic     #7                  // Field org/apache/hadoop/hbase/shaded/protobuf/generated/MasterProtos$GetProcedureResultResponse$State.FINISHED:Lorg/apache/hadoop/hbase/shaded/protobuf/generated/MasterProtos$GetProcedureResultResponse$State;
      11: invokevirtual #8                  // Method org/apache/hadoop/hbase/shaded/protobuf/generated/MasterProtos$GetProcedureResultResponse$Builder.setState:(Lorg/apache/hadoop/hbase/shaded/protobuf/generated/MasterProtos$GetProcedureResultResponse$State;)Lorg/apache/hadoop/hbase/shaded/protobuf/generated/MasterProtos$GetProcedureResultResponse$Builder;
      14: invokevirtual #9                  // Method org/apache/hadoop/hbase/shaded/protobuf/generated/MasterProtos$GetProcedureResultResponse$Builder.build:()Lorg/apache/hadoop/hbase/shaded/protobuf/generated/MasterProtos$GetProcedureResultResponse;
      17: areturn

  protected java.lang.Void convertResult(org.apache.hadoop.hbase.shaded.protobuf.generated.MasterProtos$GetProcedureResultResponse) throws java.io.IOException;
    Code:
       0: aload_0
       1: iconst_1
       2: putfield      #5                  // Field convertResultCalled:Z
       5: aconst_null
       6: areturn

  protected java.lang.Void waitOperationResult(long) throws java.io.IOException, java.util.concurrent.TimeoutException;
    Code:
       0: aload_0
       1: iconst_1
       2: putfield      #3                  // Field waitOperationResultCalled:Z
       5: aconst_null
       6: areturn

  protected java.lang.Void postOperationResult(java.lang.Void, long) throws java.io.IOException, java.util.concurrent.TimeoutException;
    Code:
       0: aload_0
       1: iconst_1
       2: putfield      #2                  // Field postOperationResultCalled:Z
       5: aload_1
       6: areturn

  protected java.lang.Object postOperationResult(java.lang.Object, long) throws java.io.IOException, java.util.concurrent.TimeoutException;
    Code:
       0: aload_0
       1: aload_1
       2: checkcast     #10                 // class java/lang/Void
       5: lload_2
       6: invokevirtual #11                 // Method postOperationResult:(Ljava/lang/Void;J)Ljava/lang/Void;
       9: areturn

  protected java.lang.Object waitOperationResult(long) throws java.io.IOException, java.util.concurrent.TimeoutException;
    Code:
       0: aload_0
       1: lload_1
       2: invokevirtual #12                 // Method waitOperationResult:(J)Ljava/lang/Void;
       5: areturn

  protected java.lang.Object convertResult(org.apache.hadoop.hbase.shaded.protobuf.generated.MasterProtos$GetProcedureResultResponse) throws java.io.IOException;
    Code:
       0: aload_0
       1: aload_1
       2: invokevirtual #13                 // Method convertResult:(Lorg/apache/hadoop/hbase/shaded/protobuf/generated/MasterProtos$GetProcedureResultResponse;)Ljava/lang/Void;
       5: areturn
}
