Compiled from "TestMultiColumnScanner.java"
public abstract class org.apache.hadoop.hbase.regionserver.TestMultiColumnScanner {
  static final int MAX_VERSIONS;

  public org.apache.hadoop.hbase.io.compress.Compression$Algorithm comprAlgo;

  public org.apache.hadoop.hbase.regionserver.BloomType bloomType;

  public org.apache.hadoop.hbase.io.encoding.DataBlockEncoding dataBlockEncoding;

  public org.apache.hadoop.hbase.regionserver.TestMultiColumnScanner();
    Code:
       0: aload_0
       1: invokespecial #2                  // Method java/lang/Object."<init>":()V
       4: return

  public static java.util.Collection<java.lang.Object[]> generateParams(org.apache.hadoop.hbase.io.compress.Compression$Algorithm, boolean);
    Code:
       0: new           #3                  // class java/util/ArrayList
       3: dup
       4: invokespecial #4                  // Method java/util/ArrayList."<init>":()V
       7: astore_2
       8: invokestatic  #5                  // Method org/apache/hadoop/hbase/regionserver/BloomType.values:()[Lorg/apache/hadoop/hbase/regionserver/BloomType;
      11: astore_3
      12: aload_3
      13: arraylength
      14: istore        4
      16: iconst_0
      17: istore        5
      19: iload         5
      21: iload         4
      23: if_icmpge     78
      26: aload_3
      27: iload         5
      29: aaload
      30: astore        6
      32: iload_1
      33: ifeq          42
      36: getstatic     #6                  // Field org/apache/hadoop/hbase/io/encoding/DataBlockEncoding.PREFIX:Lorg/apache/hadoop/hbase/io/encoding/DataBlockEncoding;
      39: goto          45
      42: getstatic     #7                  // Field org/apache/hadoop/hbase/io/encoding/DataBlockEncoding.NONE:Lorg/apache/hadoop/hbase/io/encoding/DataBlockEncoding;
      45: astore        7
      47: aload_2
      48: iconst_3
      49: anewarray     #8                  // class java/lang/Object
      52: dup
      53: iconst_0
      54: aload_0
      55: aastore
      56: dup
      57: iconst_1
      58: aload         6
      60: aastore
      61: dup
      62: iconst_2
      63: aload         7
      65: aastore
      66: invokeinterface #9,  2            // InterfaceMethod java/util/List.add:(Ljava/lang/Object;)Z
      71: pop
      72: iinc          5, 1
      75: goto          19
      78: aload_2
      79: areturn

  public void testMultiColumnScanner() throws java.io.IOException;
    Code:
       0: getstatic     #10                 // Field TEST_UTIL:Lorg/apache/hadoop/hbase/HBaseTestingUtility;
       3: invokevirtual #11                 // Method org/apache/hadoop/hbase/HBaseTestingUtility.getConfiguration:()Lorg/apache/hadoop/conf/Configuration;
       6: ldc           #13                 // String RowPrefixBloomFilter.prefix_length
       8: bipush        10
      10: invokevirtual #14                 // Method org/apache/hadoop/conf/Configuration.setInt:(Ljava/lang/String;I)V
      13: getstatic     #10                 // Field TEST_UTIL:Lorg/apache/hadoop/hbase/HBaseTestingUtility;
      16: getstatic     #15                 // Field TABLE_NAME:Ljava/lang/String;
      19: getstatic     #16                 // Field FAMILY_BYTES:[B
      22: invokestatic  #17                 // Method org/apache/hadoop/hbase/client/ColumnFamilyDescriptorBuilder.newBuilder:([B)Lorg/apache/hadoop/hbase/client/ColumnFamilyDescriptorBuilder;
      25: aload_0
      26: getfield      #18                 // Field comprAlgo:Lorg/apache/hadoop/hbase/io/compress/Compression$Algorithm;
      29: invokevirtual #19                 // Method org/apache/hadoop/hbase/client/ColumnFamilyDescriptorBuilder.setCompressionType:(Lorg/apache/hadoop/hbase/io/compress/Compression$Algorithm;)Lorg/apache/hadoop/hbase/client/ColumnFamilyDescriptorBuilder;
      32: aload_0
      33: getfield      #20                 // Field bloomType:Lorg/apache/hadoop/hbase/regionserver/BloomType;
      36: invokevirtual #21                 // Method org/apache/hadoop/hbase/client/ColumnFamilyDescriptorBuilder.setBloomFilterType:(Lorg/apache/hadoop/hbase/regionserver/BloomType;)Lorg/apache/hadoop/hbase/client/ColumnFamilyDescriptorBuilder;
      39: bipush        50
      41: invokevirtual #22                 // Method org/apache/hadoop/hbase/client/ColumnFamilyDescriptorBuilder.setMaxVersions:(I)Lorg/apache/hadoop/hbase/client/ColumnFamilyDescriptorBuilder;
      44: aload_0
      45: getfield      #23                 // Field dataBlockEncoding:Lorg/apache/hadoop/hbase/io/encoding/DataBlockEncoding;
      48: invokevirtual #24                 // Method org/apache/hadoop/hbase/client/ColumnFamilyDescriptorBuilder.setDataBlockEncoding:(Lorg/apache/hadoop/hbase/io/encoding/DataBlockEncoding;)Lorg/apache/hadoop/hbase/client/ColumnFamilyDescriptorBuilder;
      51: invokevirtual #25                 // Method org/apache/hadoop/hbase/client/ColumnFamilyDescriptorBuilder.build:()Lorg/apache/hadoop/hbase/client/ColumnFamilyDescriptor;
      54: getstatic     #10                 // Field TEST_UTIL:Lorg/apache/hadoop/hbase/HBaseTestingUtility;
      57: invokevirtual #11                 // Method org/apache/hadoop/hbase/HBaseTestingUtility.getConfiguration:()Lorg/apache/hadoop/conf/Configuration;
      60: invokestatic  #26                 // Method org/apache/hadoop/hbase/io/hfile/BlockCacheFactory.createBlockCache:(Lorg/apache/hadoop/conf/Configuration;)Lorg/apache/hadoop/hbase/io/hfile/BlockCache;
      63: invokevirtual #27                 // Method org/apache/hadoop/hbase/HBaseTestingUtility.createTestRegion:(Ljava/lang/String;Lorg/apache/hadoop/hbase/client/ColumnFamilyDescriptor;Lorg/apache/hadoop/hbase/io/hfile/BlockCache;)Lorg/apache/hadoop/hbase/regionserver/HRegion;
      66: astore_1
      67: ldc           #28                 // String row
      69: bipush        20
      71: invokestatic  #29                 // Method sequentialStrings:(Ljava/lang/String;I)Ljava/util/List;
      74: astore_2
      75: ldc           #30                 // String qual
      77: bipush        8
      79: invokestatic  #29                 // Method sequentialStrings:(Ljava/lang/String;I)Ljava/util/List;
      82: astore_3
      83: new           #3                  // class java/util/ArrayList
      86: dup
      87: invokespecial #4                  // Method java/util/ArrayList."<init>":()V
      90: astore        4
      92: new           #31                 // class java/util/HashSet
      95: dup
      96: invokespecial #32                 // Method java/util/HashSet."<init>":()V
      99: astore        5
     101: new           #33                 // class java/util/HashMap
     104: dup
     105: invokespecial #34                 // Method java/util/HashMap."<init>":()V
     108: astore        6
     110: new           #35                 // class java/util/Random
     113: dup
     114: ldc2_w        #36                 // long 29372937l
     117: invokespecial #38                 // Method java/util/Random."<init>":(J)V
     120: astore        7
     122: iconst_0
     123: istore        8
     125: iload         8
     127: bipush        10
     129: if_icmpge     531
     132: aload_3
     133: invokeinterface #39,  1           // InterfaceMethod java/util/List.iterator:()Ljava/util/Iterator;
     138: astore        9
     140: aload         9
     142: invokeinterface #40,  1           // InterfaceMethod java/util/Iterator.hasNext:()Z
     147: ifeq          519
     150: aload         9
     152: invokeinterface #41,  1           // InterfaceMethod java/util/Iterator.next:()Ljava/lang/Object;
     157: checkcast     #42                 // class java/lang/String
     160: astore        10
     162: aload         7
     164: invokevirtual #43                 // Method java/util/Random.nextDouble:()D
     167: ldc2_w        #44                 // double 0.7d
     170: dcmpg
     171: ifge          177
     174: goto          140
     177: aload         10
     179: invokestatic  #46                 // Method org/apache/hadoop/hbase/util/Bytes.toBytes:(Ljava/lang/String;)[B
     182: astore        11
     184: aload_2
     185: invokeinterface #39,  1           // InterfaceMethod java/util/List.iterator:()Ljava/util/Iterator;
     190: astore        12
     192: aload         12
     194: invokeinterface #40,  1           // InterfaceMethod java/util/Iterator.hasNext:()Z
     199: ifeq          516
     202: aload         12
     204: invokeinterface #41,  1           // InterfaceMethod java/util/Iterator.next:()Ljava/lang/Object;
     209: checkcast     #42                 // class java/lang/String
     212: astore        13
     214: new           #47                 // class org/apache/hadoop/hbase/client/Put
     217: dup
     218: aload         13
     220: invokestatic  #46                 // Method org/apache/hadoop/hbase/util/Bytes.toBytes:(Ljava/lang/String;)[B
     223: invokespecial #48                 // Method org/apache/hadoop/hbase/client/Put."<init>":([B)V
     226: astore        14
     228: getstatic     #49                 // Field TIMESTAMPS:[J
     231: astore        15
     233: aload         15
     235: arraylength
     236: istore        16
     238: iconst_0
     239: istore        17
     241: iload         17
     243: iload         16
     245: if_icmpge     344
     248: aload         15
     250: iload         17
     252: laload
     253: lstore        18
     255: aload         13
     257: aload         10
     259: lload         18
     261: invokestatic  #50                 // Method createValue:(Ljava/lang/String;Ljava/lang/String;J)Ljava/lang/String;
     264: astore        20
     266: aload         13
     268: ldc           #51                 // String CF
     270: aload         10
     272: lload         18
     274: aload         20
     276: invokestatic  #52                 // Method org/apache/hadoop/hbase/KeyValueTestUtil.create:(Ljava/lang/String;Ljava/lang/String;Ljava/lang/String;JLjava/lang/String;)Lorg/apache/hadoop/hbase/KeyValue;
     279: astore        21
     281: aload         21
     283: invokevirtual #53                 // Method org/apache/hadoop/hbase/KeyValue.getTimestamp:()J
     286: lload         18
     288: invokestatic  #54                 // Method org/junit/Assert.assertEquals:(JJ)V
     291: aload         14
     293: aload         21
     295: invokevirtual #55                 // Method org/apache/hadoop/hbase/client/Put.add:(Lorg/apache/hadoop/hbase/Cell;)Lorg/apache/hadoop/hbase/client/Put;
     298: pop
     299: aload         21
     301: invokevirtual #56                 // Method org/apache/hadoop/hbase/KeyValue.toString:()Ljava/lang/String;
     304: astore        22
     306: aload         5
     308: aload         22
     310: invokeinterface #57,  2           // InterfaceMethod java/util/Set.contains:(Ljava/lang/Object;)Z
     315: ifne          338
     318: aload         5
     320: aload         22
     322: invokeinterface #58,  2           // InterfaceMethod java/util/Set.add:(Ljava/lang/Object;)Z
     327: pop
     328: aload         4
     330: aload         21
     332: invokeinterface #9,  2            // InterfaceMethod java/util/List.add:(Ljava/lang/Object;)Z
     337: pop
     338: iinc          17, 1
     341: goto          241
     344: aload_1
     345: aload         14
     347: invokevirtual #59                 // Method org/apache/hadoop/hbase/regionserver/HRegion.put:(Lorg/apache/hadoop/hbase/client/Put;)V
     350: new           #60                 // class org/apache/hadoop/hbase/client/Delete
     353: dup
     354: aload         13
     356: invokestatic  #46                 // Method org/apache/hadoop/hbase/util/Bytes.toBytes:(Ljava/lang/String;)[B
     359: invokespecial #61                 // Method org/apache/hadoop/hbase/client/Delete."<init>":([B)V
     362: astore        15
     364: iconst_0
     365: istore        16
     367: getstatic     #49                 // Field TIMESTAMPS:[J
     370: astore        17
     372: aload         17
     374: arraylength
     375: istore        18
     377: iconst_0
     378: istore        19
     380: iload         19
     382: iload         18
     384: if_icmpge     502
     387: aload         17
     389: iload         19
     391: laload
     392: lstore        20
     394: aload         7
     396: invokevirtual #43                 // Method java/util/Random.nextDouble:()D
     399: ldc2_w        #62                 // double 0.02d
     402: dcmpg
     403: ifge          496
     406: aload         15
     408: getstatic     #16                 // Field FAMILY_BYTES:[B
     411: aload         11
     413: lload         20
     415: invokevirtual #64                 // Method org/apache/hadoop/hbase/client/Delete.addColumns:([B[BJ)Lorg/apache/hadoop/hbase/client/Delete;
     418: pop
     419: new           #65                 // class java/lang/StringBuilder
     422: dup
     423: invokespecial #66                 // Method java/lang/StringBuilder."<init>":()V
     426: aload         13
     428: invokevirtual #67                 // Method java/lang/StringBuilder.append:(Ljava/lang/String;)Ljava/lang/StringBuilder;
     431: ldc           #68                 // String _
     433: invokevirtual #67                 // Method java/lang/StringBuilder.append:(Ljava/lang/String;)Ljava/lang/StringBuilder;
     436: aload         10
     438: invokevirtual #67                 // Method java/lang/StringBuilder.append:(Ljava/lang/String;)Ljava/lang/StringBuilder;
     441: invokevirtual #69                 // Method java/lang/StringBuilder.toString:()Ljava/lang/String;
     444: astore        22
     446: aload         6
     448: aload         22
     450: invokeinterface #70,  2           // InterfaceMethod java/util/Map.get:(Ljava/lang/Object;)Ljava/lang/Object;
     455: checkcast     #71                 // class java/lang/Long
     458: astore        23
     460: aload         6
     462: aload         22
     464: aload         23
     466: ifnonnull     474
     469: lload         20
     471: goto          484
     474: lload         20
     476: aload         23
     478: invokevirtual #72                 // Method java/lang/Long.longValue:()J
     481: invokestatic  #73                 // Method java/lang/Math.max:(JJ)J
     484: invokestatic  #74                 // Method java/lang/Long.valueOf:(J)Ljava/lang/Long;
     487: invokeinterface #75,  3           // InterfaceMethod java/util/Map.put:(Ljava/lang/Object;Ljava/lang/Object;)Ljava/lang/Object;
     492: pop
     493: iconst_1
     494: istore        16
     496: iinc          19, 1
     499: goto          380
     502: iload         16
     504: ifeq          513
     507: aload_1
     508: aload         15
     510: invokevirtual #76                 // Method org/apache/hadoop/hbase/regionserver/HRegion.delete:(Lorg/apache/hadoop/hbase/client/Delete;)V
     513: goto          192
     516: goto          140
     519: aload_1
     520: iconst_1
     521: invokevirtual #77                 // Method org/apache/hadoop/hbase/regionserver/HRegion.flush:(Z)Lorg/apache/hadoop/hbase/regionserver/HRegion$FlushResult;
     524: pop
     525: iinc          8, 1
     528: goto          125
     531: aload         4
     533: getstatic     #78                 // Field org/apache/hadoop/hbase/CellComparatorImpl.COMPARATOR:Lorg/apache/hadoop/hbase/CellComparatorImpl;
     536: invokestatic  #79                 // Method java/util/Collections.sort:(Ljava/util/List;Ljava/util/Comparator;)V
     539: iconst_1
     540: istore        8
     542: iload         8
     544: getstatic     #49                 // Field TIMESTAMPS:[J
     547: arraylength
     548: if_icmpgt     1118
     551: iconst_1
     552: istore        9
     554: iload         9
     556: sipush        128
     559: if_icmpgt     1112
     562: new           #80                 // class org/apache/hadoop/hbase/client/Scan
     565: dup
     566: invokespecial #81                 // Method org/apache/hadoop/hbase/client/Scan."<init>":()V
     569: astore        10
     571: aload         10
     573: iload         8
     575: invokevirtual #82                 // Method org/apache/hadoop/hbase/client/Scan.readVersions:(I)Lorg/apache/hadoop/hbase/client/Scan;
     578: pop
     579: new           #83                 // class java/util/TreeSet
     582: dup
     583: invokespecial #84                 // Method java/util/TreeSet."<init>":()V
     586: astore        11
     588: iload         9
     590: istore        12
     592: aload_3
     593: invokeinterface #39,  1           // InterfaceMethod java/util/List.iterator:()Ljava/util/Iterator;
     598: astore        13
     600: aload         13
     602: invokeinterface #40,  1           // InterfaceMethod java/util/Iterator.hasNext:()Z
     607: ifeq          662
     610: aload         13
     612: invokeinterface #41,  1           // InterfaceMethod java/util/Iterator.next:()Ljava/lang/Object;
     617: checkcast     #42                 // class java/lang/String
     620: astore        14
     622: iload         12
     624: iconst_1
     625: iand
     626: ifeq          653
     629: aload         10
     631: getstatic     #16                 // Field FAMILY_BYTES:[B
     634: aload         14
     636: invokestatic  #46                 // Method org/apache/hadoop/hbase/util/Bytes.toBytes:(Ljava/lang/String;)[B
     639: invokevirtual #85                 // Method org/apache/hadoop/hbase/client/Scan.addColumn:([B[B)Lorg/apache/hadoop/hbase/client/Scan;
     642: pop
     643: aload         11
     645: aload         14
     647: invokeinterface #58,  2           // InterfaceMethod java/util/Set.add:(Ljava/lang/Object;)Z
     652: pop
     653: iload         12
     655: iconst_1
     656: ishr
     657: istore        12
     659: goto          600
     662: lconst_0
     663: iload         12
     665: i2l
     666: invokestatic  #54                 // Method org/junit/Assert.assertEquals:(JJ)V
     669: aload_1
     670: aload         10
     672: invokevirtual #86                 // Method org/apache/hadoop/hbase/regionserver/HRegion.getScanner:(Lorg/apache/hadoop/hbase/client/Scan;)Lorg/apache/hadoop/hbase/regionserver/HRegion$RegionScannerImpl;
     675: astore        12
     677: new           #3                  // class java/util/ArrayList
     680: dup
     681: invokespecial #4                  // Method java/util/ArrayList."<init>":()V
     684: astore        13
     686: iconst_0
     687: istore        14
     689: iconst_0
     690: istore        15
     692: new           #65                 // class java/lang/StringBuilder
     695: dup
     696: invokespecial #66                 // Method java/lang/StringBuilder."<init>":()V
     699: ldc           #87                 // String columns queried:
     701: invokevirtual #67                 // Method java/lang/StringBuilder.append:(Ljava/lang/String;)Ljava/lang/StringBuilder;
     704: aload         11
     706: invokevirtual #88                 // Method java/lang/StringBuilder.append:(Ljava/lang/Object;)Ljava/lang/StringBuilder;
     709: ldc           #89                 // String  (columnBitMask=
     711: invokevirtual #67                 // Method java/lang/StringBuilder.append:(Ljava/lang/String;)Ljava/lang/StringBuilder;
     714: iload         9
     716: invokevirtual #90                 // Method java/lang/StringBuilder.append:(I)Ljava/lang/StringBuilder;
     719: ldc           #91                 // String ), maxVersions=
     721: invokevirtual #67                 // Method java/lang/StringBuilder.append:(Ljava/lang/String;)Ljava/lang/StringBuilder;
     724: iload         8
     726: invokevirtual #90                 // Method java/lang/StringBuilder.append:(I)Ljava/lang/StringBuilder;
     729: invokevirtual #69                 // Method java/lang/StringBuilder.toString:()Ljava/lang/String;
     732: astore        16
     734: aload         12
     736: aload         13
     738: invokeinterface #92,  2           // InterfaceMethod org/apache/hadoop/hbase/regionserver/InternalScanner.next:(Ljava/util/List;)Z
     743: ifne          756
     746: aload         13
     748: invokeinterface #93,  1           // InterfaceMethod java/util/List.size:()I
     753: ifle          1020
     756: aload         13
     758: invokeinterface #39,  1           // InterfaceMethod java/util/List.iterator:()Ljava/util/Iterator;
     763: astore        17
     765: aload         17
     767: invokeinterface #40,  1           // InterfaceMethod java/util/Iterator.hasNext:()Z
     772: ifeq          1010
     775: aload         17
     777: invokeinterface #41,  1           // InterfaceMethod java/util/Iterator.next:()Ljava/lang/Object;
     782: checkcast     #94                 // class org/apache/hadoop/hbase/Cell
     785: astore        18
     787: iload         14
     789: aload         4
     791: invokeinterface #93,  1           // InterfaceMethod java/util/List.size:()I
     796: if_icmpge     829
     799: aload         4
     801: iload         14
     803: invokeinterface #95,  2           // InterfaceMethod java/util/List.get:(I)Ljava/lang/Object;
     808: checkcast     #96                 // class org/apache/hadoop/hbase/KeyValue
     811: aload         11
     813: iload         8
     815: aload         6
     817: invokestatic  #97                 // Method matchesQuery:(Lorg/apache/hadoop/hbase/KeyValue;Ljava/util/Set;ILjava/util/Map;)Z
     820: ifne          829
     823: iinc          14, 1
     826: goto          787
     829: aload         18
     831: invokestatic  #98                 // Method getRowQualStr:(Lorg/apache/hadoop/hbase/Cell;)Ljava/lang/String;
     834: astore        19
     836: ldc           #99                 // String
     838: astore        20
     840: aload         6
     842: aload         19
     844: invokeinterface #70,  2           // InterfaceMethod java/util/Map.get:(Ljava/lang/Object;)Ljava/lang/Object;
     849: checkcast     #71                 // class java/lang/Long
     852: astore        21
     854: aload         21
     856: ifnull        891
     859: new           #65                 // class java/lang/StringBuilder
     862: dup
     863: invokespecial #66                 // Method java/lang/StringBuilder."<init>":()V
     866: ldc           #100                // String ; last timestamp when row/column
     868: invokevirtual #67                 // Method java/lang/StringBuilder.append:(Ljava/lang/String;)Ljava/lang/StringBuilder;
     871: aload         19
     873: invokevirtual #67                 // Method java/lang/StringBuilder.append:(Ljava/lang/String;)Ljava/lang/StringBuilder;
     876: ldc           #101                // String  was deleted:
     878: invokevirtual #67                 // Method java/lang/StringBuilder.append:(Ljava/lang/String;)Ljava/lang/StringBuilder;
     881: aload         21
     883: invokevirtual #88                 // Method java/lang/StringBuilder.append:(Ljava/lang/Object;)Ljava/lang/StringBuilder;
     886: invokevirtual #69                 // Method java/lang/StringBuilder.toString:()Ljava/lang/String;
     889: astore        20
     891: new           #65                 // class java/lang/StringBuilder
     894: dup
     895: invokespecial #66                 // Method java/lang/StringBuilder."<init>":()V
     898: ldc           #102                // String Scanner returned additional key/value:
     900: invokevirtual #67                 // Method java/lang/StringBuilder.append:(Ljava/lang/String;)Ljava/lang/StringBuilder;
     903: aload         18
     905: invokevirtual #88                 // Method java/lang/StringBuilder.append:(Ljava/lang/Object;)Ljava/lang/StringBuilder;
     908: ldc           #103                // String ,
     910: invokevirtual #67                 // Method java/lang/StringBuilder.append:(Ljava/lang/String;)Ljava/lang/StringBuilder;
     913: aload         16
     915: invokevirtual #67                 // Method java/lang/StringBuilder.append:(Ljava/lang/String;)Ljava/lang/StringBuilder;
     918: aload         20
     920: invokevirtual #67                 // Method java/lang/StringBuilder.append:(Ljava/lang/String;)Ljava/lang/StringBuilder;
     923: ldc           #104                // String ;
     925: invokevirtual #67                 // Method java/lang/StringBuilder.append:(Ljava/lang/String;)Ljava/lang/StringBuilder;
     928: invokevirtual #69                 // Method java/lang/StringBuilder.toString:()Ljava/lang/String;
     931: iload         14
     933: aload         4
     935: invokeinterface #93,  1           // InterfaceMethod java/util/List.size:()I
     940: if_icmpge     947
     943: iconst_1
     944: goto          948
     947: iconst_0
     948: invokestatic  #105                // Method org/junit/Assert.assertTrue:(Ljava/lang/String;Z)V
     951: new           #65                 // class java/lang/StringBuilder
     954: dup
     955: invokespecial #66                 // Method java/lang/StringBuilder."<init>":()V
     958: ldc           #106                // String Scanner returned wrong key/value;
     960: invokevirtual #67                 // Method java/lang/StringBuilder.append:(Ljava/lang/String;)Ljava/lang/StringBuilder;
     963: aload         16
     965: invokevirtual #67                 // Method java/lang/StringBuilder.append:(Ljava/lang/String;)Ljava/lang/StringBuilder;
     968: aload         20
     970: invokevirtual #67                 // Method java/lang/StringBuilder.append:(Ljava/lang/String;)Ljava/lang/StringBuilder;
     973: ldc           #104                // String ;
     975: invokevirtual #67                 // Method java/lang/StringBuilder.append:(Ljava/lang/String;)Ljava/lang/StringBuilder;
     978: invokevirtual #69                 // Method java/lang/StringBuilder.toString:()Ljava/lang/String;
     981: aload         4
     983: iload         14
     985: invokeinterface #95,  2           // InterfaceMethod java/util/List.get:(I)Ljava/lang/Object;
     990: checkcast     #94                 // class org/apache/hadoop/hbase/Cell
     993: aload         18
     995: invokestatic  #107                // Method org/apache/hadoop/hbase/PrivateCellUtil.equalsIgnoreMvccVersion:(Lorg/apache/hadoop/hbase/Cell;Lorg/apache/hadoop/hbase/Cell;)Z
     998: invokestatic  #105                // Method org/junit/Assert.assertTrue:(Ljava/lang/String;Z)V
    1001: iinc          14, 1
    1004: iinc          15, 1
    1007: goto          765
    1010: aload         13
    1012: invokeinterface #108,  1          // InterfaceMethod java/util/List.clear:()V
    1017: goto          734
    1020: iload         14
    1022: aload         4
    1024: invokeinterface #93,  1           // InterfaceMethod java/util/List.size:()I
    1029: if_icmpge     1106
    1032: aload         4
    1034: iload         14
    1036: invokeinterface #95,  2           // InterfaceMethod java/util/List.get:(I)Ljava/lang/Object;
    1041: checkcast     #96                 // class org/apache/hadoop/hbase/KeyValue
    1044: astore        17
    1046: new           #65                 // class java/lang/StringBuilder
    1049: dup
    1050: invokespecial #66                 // Method java/lang/StringBuilder."<init>":()V
    1053: ldc           #109                // String Matching column not returned by scanner:
    1055: invokevirtual #67                 // Method java/lang/StringBuilder.append:(Ljava/lang/String;)Ljava/lang/StringBuilder;
    1058: aload         17
    1060: invokevirtual #88                 // Method java/lang/StringBuilder.append:(Ljava/lang/Object;)Ljava/lang/StringBuilder;
    1063: ldc           #103                // String ,
    1065: invokevirtual #67                 // Method java/lang/StringBuilder.append:(Ljava/lang/String;)Ljava/lang/StringBuilder;
    1068: aload         16
    1070: invokevirtual #67                 // Method java/lang/StringBuilder.append:(Ljava/lang/String;)Ljava/lang/StringBuilder;
    1073: ldc           #110                // String , results returned:
    1075: invokevirtual #67                 // Method java/lang/StringBuilder.append:(Ljava/lang/String;)Ljava/lang/StringBuilder;
    1078: iload         15
    1080: invokevirtual #90                 // Method java/lang/StringBuilder.append:(I)Ljava/lang/StringBuilder;
    1083: invokevirtual #69                 // Method java/lang/StringBuilder.toString:()Ljava/lang/String;
    1086: aload         17
    1088: aload         11
    1090: iload         8
    1092: aload         6
    1094: invokestatic  #97                 // Method matchesQuery:(Lorg/apache/hadoop/hbase/KeyValue;Ljava/util/Set;ILjava/util/Map;)Z
    1097: invokestatic  #111                // Method org/junit/Assert.assertFalse:(Ljava/lang/String;Z)V
    1100: iinc          14, 1
    1103: goto          1020
    1106: iinc          9, 1
    1109: goto          554
    1112: iinc          8, 1
    1115: goto          542
    1118: ldc           #112                // String This test is supposed to delete at least some row/column pairs
    1120: aload         6
    1122: invokeinterface #113,  1          // InterfaceMethod java/util/Map.size:()I
    1127: ifle          1134
    1130: iconst_1
    1131: goto          1135
    1134: iconst_0
    1135: invokestatic  #105                // Method org/junit/Assert.assertTrue:(Ljava/lang/String;Z)V
    1138: getstatic     #114                // Field LOG:Lorg/slf4j/Logger;
    1141: new           #65                 // class java/lang/StringBuilder
    1144: dup
    1145: invokespecial #66                 // Method java/lang/StringBuilder."<init>":()V
    1148: ldc           #115                // String Number of row/col pairs deleted at least once:
    1150: invokevirtual #67                 // Method java/lang/StringBuilder.append:(Ljava/lang/String;)Ljava/lang/StringBuilder;
    1153: aload         6
    1155: invokeinterface #113,  1          // InterfaceMethod java/util/Map.size:()I
    1160: invokevirtual #90                 // Method java/lang/StringBuilder.append:(I)Ljava/lang/StringBuilder;
    1163: invokevirtual #69                 // Method java/lang/StringBuilder.toString:()Ljava/lang/String;
    1166: invokeinterface #116,  2          // InterfaceMethod org/slf4j/Logger.info:(Ljava/lang/String;)V
    1171: aload_1
    1172: invokestatic  #117                // Method org/apache/hadoop/hbase/HBaseTestingUtility.closeRegionAndWAL:(Lorg/apache/hadoop/hbase/regionserver/HRegion;)V
    1175: return

  static java.lang.String createValue(java.lang.String, java.lang.String, long);
    Code:
       0: new           #65                 // class java/lang/StringBuilder
       3: dup
       4: invokespecial #66                 // Method java/lang/StringBuilder."<init>":()V
       7: ldc           #126                // String value_for_
       9: invokevirtual #67                 // Method java/lang/StringBuilder.append:(Ljava/lang/String;)Ljava/lang/StringBuilder;
      12: aload_0
      13: invokevirtual #67                 // Method java/lang/StringBuilder.append:(Ljava/lang/String;)Ljava/lang/StringBuilder;
      16: ldc           #68                 // String _
      18: invokevirtual #67                 // Method java/lang/StringBuilder.append:(Ljava/lang/String;)Ljava/lang/StringBuilder;
      21: aload_1
      22: invokevirtual #67                 // Method java/lang/StringBuilder.append:(Ljava/lang/String;)Ljava/lang/StringBuilder;
      25: ldc           #68                 // String _
      27: invokevirtual #67                 // Method java/lang/StringBuilder.append:(Ljava/lang/String;)Ljava/lang/StringBuilder;
      30: lload_2
      31: invokevirtual #127                // Method java/lang/StringBuilder.append:(J)Ljava/lang/StringBuilder;
      34: invokevirtual #69                 // Method java/lang/StringBuilder.toString:()Ljava/lang/String;
      37: areturn

  static {};
    Code:
       0: ldc           #1                  // class org/apache/hadoop/hbase/regionserver/TestMultiColumnScanner
       2: invokestatic  #129                // Method org/slf4j/LoggerFactory.getLogger:(Ljava/lang/Class;)Lorg/slf4j/Logger;
       5: putstatic     #114                // Field LOG:Lorg/slf4j/Logger;
       8: ldc           #1                  // class org/apache/hadoop/hbase/regionserver/TestMultiColumnScanner
      10: invokevirtual #130                // Method java/lang/Class.getSimpleName:()Ljava/lang/String;
      13: putstatic     #15                 // Field TABLE_NAME:Ljava/lang/String;
      16: ldc           #51                 // String CF
      18: invokestatic  #46                 // Method org/apache/hadoop/hbase/util/Bytes.toBytes:(Ljava/lang/String;)[B
      21: putstatic     #16                 // Field FAMILY_BYTES:[B
      24: bipush        6
      26: newarray       long
      28: dup
      29: iconst_0
      30: lconst_1
      31: lastore
      32: dup
      33: iconst_1
      34: ldc2_w        #131                // long 3l
      37: lastore
      38: dup
      39: iconst_2
      40: ldc2_w        #133                // long 5l
      43: lastore
      44: dup
      45: iconst_3
      46: ldc2_w        #136                // long 2147483647l
      49: lastore
      50: dup
      51: iconst_4
      52: ldc2_w        #138                // long 9111222333444555666l
      55: lastore
      56: dup
      57: iconst_5
      58: ldc2_w        #140                // long 9223372036854775806l
      61: lastore
      62: putstatic     #49                 // Field TIMESTAMPS:[J
      65: invokestatic  #142                // Method org/apache/hadoop/hbase/HBaseTestingUtility.createLocalHTU:()Lorg/apache/hadoop/hbase/HBaseTestingUtility;
      68: putstatic     #10                 // Field TEST_UTIL:Lorg/apache/hadoop/hbase/HBaseTestingUtility;
      71: iconst_1
      72: invokestatic  #143                // Method org/junit/Assert.assertTrue:(Z)V
      75: iconst_0
      76: istore_0
      77: iload_0
      78: getstatic     #49                 // Field TIMESTAMPS:[J
      81: arraylength
      82: iconst_1
      83: isub
      84: if_icmpge     117
      87: getstatic     #49                 // Field TIMESTAMPS:[J
      90: iload_0
      91: laload
      92: getstatic     #49                 // Field TIMESTAMPS:[J
      95: iload_0
      96: iconst_1
      97: iadd
      98: laload
      99: lcmp
     100: ifge          107
     103: iconst_1
     104: goto          108
     107: iconst_0
     108: invokestatic  #143                // Method org/junit/Assert.assertTrue:(Z)V
     111: iinc          0, 1
     114: goto          77
     117: return
}
