Compiled from "TestAsyncProcess.java"
class org.apache.hadoop.hbase.client.TestAsyncProcess$4 extends java.lang.Thread {
  final org.apache.hadoop.hbase.client.SimpleRequestController val$controller;

  final org.apache.hadoop.hbase.client.TestAsyncProcess$MyAsyncProcess val$ap;

  final org.apache.hadoop.hbase.client.TestAsyncProcess this$0;

  org.apache.hadoop.hbase.client.TestAsyncProcess$4(org.apache.hadoop.hbase.client.TestAsyncProcess, org.apache.hadoop.hbase.client.SimpleRequestController, org.apache.hadoop.hbase.client.TestAsyncProcess$MyAsyncProcess);
    Code:
       0: aload_0
       1: aload_1
       2: putfield      #1                  // Field this$0:Lorg/apache/hadoop/hbase/client/TestAsyncProcess;
       5: aload_0
       6: aload_2
       7: putfield      #2                  // Field val$controller:Lorg/apache/hadoop/hbase/client/SimpleRequestController;
      10: aload_0
      11: aload_3
      12: putfield      #3                  // Field val$ap:Lorg/apache/hadoop/hbase/client/TestAsyncProcess$MyAsyncProcess;
      15: aload_0
      16: invokespecial #4                  // Method java/lang/Thread."<init>":()V
      19: return

  public void run();
    Code:
       0: ldc2_w        #5                  // long 2000l
       3: invokestatic  #7                  // Method org/apache/hadoop/hbase/util/Threads.sleep:(J)V
       6: aload_0
       7: getfield      #2                  // Field val$controller:Lorg/apache/hadoop/hbase/client/SimpleRequestController;
      10: getfield      #8                  // Field org/apache/hadoop/hbase/client/SimpleRequestController.tasksInProgress:Ljava/util/concurrent/atomic/AtomicLong;
      13: invokevirtual #9                  // Method java/util/concurrent/atomic/AtomicLong.get:()J
      16: lconst_0
      17: lcmp
      18: ifle          42
      21: aload_0
      22: getfield      #3                  // Field val$ap:Lorg/apache/hadoop/hbase/client/TestAsyncProcess$MyAsyncProcess;
      25: ldc           #10                 // String dummy
      27: invokestatic  #11                 // Method org/apache/hadoop/hbase/util/Bytes.toBytes:(Ljava/lang/String;)[B
      30: invokestatic  #12                 // Method java/util/Collections.singleton:(Ljava/lang/Object;)Ljava/util/Set;
      33: invokestatic  #13                 // Method org/apache/hadoop/hbase/client/TestAsyncProcess.access$900:()Lorg/apache/hadoop/hbase/ServerName;
      36: invokevirtual #14                 // Method org/apache/hadoop/hbase/client/TestAsyncProcess$MyAsyncProcess.decTaskCounters:(Ljava/util/Collection;Lorg/apache/hadoop/hbase/ServerName;)V
      39: goto          6
      42: return
}
