Compiled from "TestRegionBypass.java"
public class org.apache.hadoop.hbase.master.assignment.TestRegionBypass {
  public static final org.apache.hadoop.hbase.HBaseClassTestRule CLASS_RULE;

  public org.junit.rules.TestName name;

  public org.apache.hadoop.hbase.master.assignment.TestRegionBypass();
    Code:
       0: aload_0
       1: invokespecial #2                  // Method java/lang/Object."<init>":()V
       4: aload_0
       5: new           #3                  // class org/junit/rules/TestName
       8: dup
       9: invokespecial #4                  // Method org/junit/rules/TestName."<init>":()V
      12: putfield      #5                  // Field name:Lorg/junit/rules/TestName;
      15: return

  public static void startCluster() throws java.lang.Exception;
    Code:
       0: getstatic     #6                  // Field TEST_UTIL:Lorg/apache/hadoop/hbase/HBaseTestingUtility;
       3: iconst_2
       4: invokevirtual #7                  // Method org/apache/hadoop/hbase/HBaseTestingUtility.startMiniCluster:(I)Lorg/apache/hadoop/hbase/MiniHBaseCluster;
       7: pop
       8: return

  public static void stopCluster() throws java.lang.Exception;
    Code:
       0: getstatic     #6                  // Field TEST_UTIL:Lorg/apache/hadoop/hbase/HBaseTestingUtility;
       3: invokevirtual #8                  // Method org/apache/hadoop/hbase/HBaseTestingUtility.shutdownMiniCluster:()V
       6: return

  public void before() throws java.io.IOException;
    Code:
       0: aload_0
       1: aload_0
       2: getfield      #5                  // Field name:Lorg/junit/rules/TestName;
       5: invokevirtual #9                  // Method org/junit/rules/TestName.getMethodName:()Ljava/lang/String;
       8: invokestatic  #10                 // Method org/apache/hadoop/hbase/TableName.valueOf:(Ljava/lang/String;)Lorg/apache/hadoop/hbase/TableName;
      11: putfield      #11                 // Field tableName:Lorg/apache/hadoop/hbase/TableName;
      14: getstatic     #6                  // Field TEST_UTIL:Lorg/apache/hadoop/hbase/HBaseTestingUtility;
      17: aload_0
      18: getfield      #11                 // Field tableName:Lorg/apache/hadoop/hbase/TableName;
      21: ldc           #12                 // String cf
      23: invokestatic  #13                 // Method org/apache/hadoop/hbase/util/Bytes.toBytes:(Ljava/lang/String;)[B
      26: invokevirtual #14                 // Method org/apache/hadoop/hbase/HBaseTestingUtility.createTable:(Lorg/apache/hadoop/hbase/TableName;[B)Lorg/apache/hadoop/hbase/client/Table;
      29: pop
      30: return

  public void testBypass() throws java.io.IOException, java.lang.InterruptedException;
    Code:
       0: getstatic     #6                  // Field TEST_UTIL:Lorg/apache/hadoop/hbase/HBaseTestingUtility;
       3: invokevirtual #15                 // Method org/apache/hadoop/hbase/HBaseTestingUtility.getAdmin:()Lorg/apache/hadoop/hbase/client/Admin;
       6: astore_1
       7: getstatic     #6                  // Field TEST_UTIL:Lorg/apache/hadoop/hbase/HBaseTestingUtility;
      10: invokevirtual #16                 // Method org/apache/hadoop/hbase/HBaseTestingUtility.getHBaseCluster:()Lorg/apache/hadoop/hbase/MiniHBaseCluster;
      13: invokevirtual #17                 // Method org/apache/hadoop/hbase/MiniHBaseCluster.getMaster:()Lorg/apache/hadoop/hbase/master/HMaster;
      16: invokevirtual #18                 // Method org/apache/hadoop/hbase/master/HMaster.getMasterProcedureExecutor:()Lorg/apache/hadoop/hbase/procedure2/ProcedureExecutor;
      19: invokevirtual #19                 // Method org/apache/hadoop/hbase/procedure2/ProcedureExecutor.getEnvironment:()Ljava/lang/Object;
      22: checkcast     #20                 // class org/apache/hadoop/hbase/master/procedure/MasterProcedureEnv
      25: astore_2
      26: aload_1
      27: aload_0
      28: getfield      #11                 // Field tableName:Lorg/apache/hadoop/hbase/TableName;
      31: invokeinterface #21,  2           // InterfaceMethod org/apache/hadoop/hbase/client/Admin.getRegions:(Lorg/apache/hadoop/hbase/TableName;)Ljava/util/List;
      36: astore_3
      37: aload_3
      38: invokeinterface #22,  1           // InterfaceMethod java/util/List.iterator:()Ljava/util/Iterator;
      43: astore        4
      45: aload         4
      47: invokeinterface #23,  1           // InterfaceMethod java/util/Iterator.hasNext:()Z
      52: ifeq          84
      55: aload         4
      57: invokeinterface #24,  1           // InterfaceMethod java/util/Iterator.next:()Ljava/lang/Object;
      62: checkcast     #25                 // class org/apache/hadoop/hbase/client/RegionInfo
      65: astore        5
      67: aload_1
      68: aload         5
      70: invokeinterface #26,  1           // InterfaceMethod org/apache/hadoop/hbase/client/RegionInfo.getRegionName:()[B
      75: iconst_0
      76: invokeinterface #27,  3           // InterfaceMethod org/apache/hadoop/hbase/client/Admin.unassign:([BZ)V
      81: goto          45
      84: new           #28                 // class java/util/ArrayList
      87: dup
      88: aload_3
      89: invokeinterface #29,  1           // InterfaceMethod java/util/List.size:()I
      94: invokespecial #30                 // Method java/util/ArrayList."<init>":(I)V
      97: astore        4
      99: aload_3
     100: invokeinterface #22,  1           // InterfaceMethod java/util/List.iterator:()Ljava/util/Iterator;
     105: astore        5
     107: aload         5
     109: invokeinterface #23,  1           // InterfaceMethod java/util/Iterator.hasNext:()Z
     114: ifeq          177
     117: aload         5
     119: invokeinterface #24,  1           // InterfaceMethod java/util/Iterator.next:()Ljava/lang/Object;
     124: checkcast     #25                 // class org/apache/hadoop/hbase/client/RegionInfo
     127: astore        6
     129: new           #31                 // class org/apache/hadoop/hbase/master/assignment/TestRegionBypass$StallingAssignProcedure
     132: dup
     133: aload_2
     134: aload         6
     136: aconst_null
     137: iconst_0
     138: getstatic     #32                 // Field org/apache/hadoop/hbase/master/assignment/TransitRegionStateProcedure$TransitionType.ASSIGN:Lorg/apache/hadoop/hbase/master/assignment/TransitRegionStateProcedure$TransitionType;
     141: invokespecial #33                 // Method org/apache/hadoop/hbase/master/assignment/TestRegionBypass$StallingAssignProcedure."<init>":(Lorg/apache/hadoop/hbase/master/procedure/MasterProcedureEnv;Lorg/apache/hadoop/hbase/client/RegionInfo;Lorg/apache/hadoop/hbase/ServerName;ZLorg/apache/hadoop/hbase/master/assignment/TransitRegionStateProcedure$TransitionType;)V
     144: astore        7
     146: aload         4
     148: getstatic     #6                  // Field TEST_UTIL:Lorg/apache/hadoop/hbase/HBaseTestingUtility;
     151: invokevirtual #16                 // Method org/apache/hadoop/hbase/HBaseTestingUtility.getHBaseCluster:()Lorg/apache/hadoop/hbase/MiniHBaseCluster;
     154: invokevirtual #17                 // Method org/apache/hadoop/hbase/MiniHBaseCluster.getMaster:()Lorg/apache/hadoop/hbase/master/HMaster;
     157: invokevirtual #18                 // Method org/apache/hadoop/hbase/master/HMaster.getMasterProcedureExecutor:()Lorg/apache/hadoop/hbase/procedure2/ProcedureExecutor;
     160: aload         7
     162: invokevirtual #34                 // Method org/apache/hadoop/hbase/procedure2/ProcedureExecutor.submitProcedure:(Lorg/apache/hadoop/hbase/procedure2/Procedure;)J
     165: invokestatic  #35                 // Method java/lang/Long.valueOf:(J)Ljava/lang/Long;
     168: invokeinterface #36,  2           // InterfaceMethod java/util/List.add:(Ljava/lang/Object;)Z
     173: pop
     174: goto          107
     177: aload         4
     179: invokeinterface #22,  1           // InterfaceMethod java/util/List.iterator:()Ljava/util/Iterator;
     184: astore        5
     186: aload         5
     188: invokeinterface #23,  1           // InterfaceMethod java/util/Iterator.hasNext:()Z
     193: ifeq          243
     196: aload         5
     198: invokeinterface #24,  1           // InterfaceMethod java/util/Iterator.next:()Ljava/lang/Object;
     203: checkcast     #37                 // class java/lang/Long
     206: astore        6
     208: getstatic     #6                  // Field TEST_UTIL:Lorg/apache/hadoop/hbase/HBaseTestingUtility;
     211: invokevirtual #16                 // Method org/apache/hadoop/hbase/HBaseTestingUtility.getHBaseCluster:()Lorg/apache/hadoop/hbase/MiniHBaseCluster;
     214: invokevirtual #17                 // Method org/apache/hadoop/hbase/MiniHBaseCluster.getMaster:()Lorg/apache/hadoop/hbase/master/HMaster;
     217: invokevirtual #18                 // Method org/apache/hadoop/hbase/master/HMaster.getMasterProcedureExecutor:()Lorg/apache/hadoop/hbase/procedure2/ProcedureExecutor;
     220: aload         6
     222: invokevirtual #38                 // Method java/lang/Long.longValue:()J
     225: invokevirtual #39                 // Method org/apache/hadoop/hbase/procedure2/ProcedureExecutor.isStarted:(J)Z
     228: ifne          240
     231: ldc2_w        #40                 // long 100l
     234: invokestatic  #42                 // Method java/lang/Thread.sleep:(J)V
     237: goto          208
     240: goto          186
     243: getstatic     #6                  // Field TEST_UTIL:Lorg/apache/hadoop/hbase/HBaseTestingUtility;
     246: invokevirtual #16                 // Method org/apache/hadoop/hbase/HBaseTestingUtility.getHBaseCluster:()Lorg/apache/hadoop/hbase/MiniHBaseCluster;
     249: invokevirtual #17                 // Method org/apache/hadoop/hbase/MiniHBaseCluster.getMaster:()Lorg/apache/hadoop/hbase/master/HMaster;
     252: invokevirtual #18                 // Method org/apache/hadoop/hbase/master/HMaster.getMasterProcedureExecutor:()Lorg/apache/hadoop/hbase/procedure2/ProcedureExecutor;
     255: invokevirtual #43                 // Method org/apache/hadoop/hbase/procedure2/ProcedureExecutor.getProcedures:()Ljava/util/List;
     258: astore        5
     260: aload         5
     262: invokeinterface #22,  1           // InterfaceMethod java/util/List.iterator:()Ljava/util/Iterator;
     267: astore        6
     269: aload         6
     271: invokeinterface #23,  1           // InterfaceMethod java/util/Iterator.hasNext:()Z
     276: ifeq          392
     279: aload         6
     281: invokeinterface #24,  1           // InterfaceMethod java/util/Iterator.next:()Ljava/lang/Object;
     286: checkcast     #44                 // class org/apache/hadoop/hbase/procedure2/Procedure
     289: astore        7
     291: aload         7
     293: instanceof    #31                 // class org/apache/hadoop/hbase/master/assignment/TestRegionBypass$StallingAssignProcedure
     296: ifeq          389
     299: getstatic     #6                  // Field TEST_UTIL:Lorg/apache/hadoop/hbase/HBaseTestingUtility;
     302: invokevirtual #45                 // Method org/apache/hadoop/hbase/HBaseTestingUtility.getHbck:()Lorg/apache/hadoop/hbase/client/Hbck;
     305: iconst_1
     306: anewarray     #37                 // class java/lang/Long
     309: dup
     310: iconst_0
     311: aload         7
     313: invokevirtual #46                 // Method org/apache/hadoop/hbase/procedure2/Procedure.getProcId:()J
     316: invokestatic  #35                 // Method java/lang/Long.valueOf:(J)Ljava/lang/Long;
     319: aastore
     320: invokestatic  #47                 // Method java/util/Arrays.asList:([Ljava/lang/Object;)Ljava/util/List;
     323: ldc2_w        #48                 // long 1000l
     326: iconst_1
     327: iconst_0
     328: invokeinterface #50,  6           // InterfaceMethod org/apache/hadoop/hbase/client/Hbck.bypassProcedure:(Ljava/util/List;JZZ)Ljava/util/List;
     333: astore        8
     335: aload         8
     337: invokeinterface #22,  1           // InterfaceMethod java/util/List.iterator:()Ljava/util/Iterator;
     342: astore        9
     344: aload         9
     346: invokeinterface #23,  1           // InterfaceMethod java/util/Iterator.hasNext:()Z
     351: ifeq          389
     354: aload         9
     356: invokeinterface #24,  1           // InterfaceMethod java/util/Iterator.next:()Ljava/lang/Object;
     361: checkcast     #51                 // class java/lang/Boolean
     364: astore        10
     366: getstatic     #1                  // Field LOG:Lorg/slf4j/Logger;
     369: ldc           #52                 // String BYPASSED {} {}
     371: aload         7
     373: invokevirtual #46                 // Method org/apache/hadoop/hbase/procedure2/Procedure.getProcId:()J
     376: invokestatic  #35                 // Method java/lang/Long.valueOf:(J)Ljava/lang/Long;
     379: aload         10
     381: invokeinterface #53,  4           // InterfaceMethod org/slf4j/Logger.info:(Ljava/lang/String;Ljava/lang/Object;Ljava/lang/Object;)V
     386: goto          344
     389: goto          269
     392: aload_3
     393: invokeinterface #22,  1           // InterfaceMethod java/util/List.iterator:()Ljava/util/Iterator;
     398: astore        6
     400: aload         6
     402: invokeinterface #23,  1           // InterfaceMethod java/util/Iterator.hasNext:()Z
     407: ifeq          455
     410: aload         6
     412: invokeinterface #24,  1           // InterfaceMethod java/util/Iterator.next:()Ljava/lang/Object;
     417: checkcast     #25                 // class org/apache/hadoop/hbase/client/RegionInfo
     420: astore        7
     422: aload_1
     423: aload         7
     425: invokeinterface #26,  1           // InterfaceMethod org/apache/hadoop/hbase/client/RegionInfo.getRegionName:()[B
     430: invokeinterface #54,  2           // InterfaceMethod org/apache/hadoop/hbase/client/Admin.assign:([B)V
     435: goto          452
     438: astore        8
     440: getstatic     #1                  // Field LOG:Lorg/slf4j/Logger;
     443: ldc           #56                 // String Expected {}
     445: aload         8
     447: invokeinterface #57,  3           // InterfaceMethod org/slf4j/Logger.info:(Ljava/lang/String;Ljava/lang/Throwable;)V
     452: goto          400
     455: getstatic     #6                  // Field TEST_UTIL:Lorg/apache/hadoop/hbase/HBaseTestingUtility;
     458: invokevirtual #16                 // Method org/apache/hadoop/hbase/HBaseTestingUtility.getHBaseCluster:()Lorg/apache/hadoop/hbase/MiniHBaseCluster;
     461: invokevirtual #17                 // Method org/apache/hadoop/hbase/MiniHBaseCluster.getMaster:()Lorg/apache/hadoop/hbase/master/HMaster;
     464: invokevirtual #18                 // Method org/apache/hadoop/hbase/master/HMaster.getMasterProcedureExecutor:()Lorg/apache/hadoop/hbase/procedure2/ProcedureExecutor;
     467: invokevirtual #58                 // Method org/apache/hadoop/hbase/procedure2/ProcedureExecutor.getActiveProcIds:()Ljava/util/Set;
     470: invokeinterface #59,  1           // InterfaceMethod java/util/Set.isEmpty:()Z
     475: ifne          487
     478: ldc2_w        #40                 // long 100l
     481: invokestatic  #42                 // Method java/lang/Thread.sleep:(J)V
     484: goto          455
     487: aload_3
     488: invokeinterface #22,  1           // InterfaceMethod java/util/List.iterator:()Ljava/util/Iterator;
     493: astore        6
     495: aload         6
     497: invokeinterface #23,  1           // InterfaceMethod java/util/Iterator.hasNext:()Z
     502: ifeq          550
     505: aload         6
     507: invokeinterface #24,  1           // InterfaceMethod java/util/Iterator.next:()Ljava/lang/Object;
     512: checkcast     #25                 // class org/apache/hadoop/hbase/client/RegionInfo
     515: astore        7
     517: getstatic     #6                  // Field TEST_UTIL:Lorg/apache/hadoop/hbase/HBaseTestingUtility;
     520: invokevirtual #45                 // Method org/apache/hadoop/hbase/HBaseTestingUtility.getHbck:()Lorg/apache/hadoop/hbase/client/Hbck;
     523: iconst_1
     524: anewarray     #60                 // class java/lang/String
     527: dup
     528: iconst_0
     529: aload         7
     531: invokeinterface #61,  1           // InterfaceMethod org/apache/hadoop/hbase/client/RegionInfo.getEncodedName:()Ljava/lang/String;
     536: aastore
     537: invokestatic  #47                 // Method java/util/Arrays.asList:([Ljava/lang/Object;)Ljava/util/List;
     540: iconst_1
     541: invokeinterface #62,  3           // InterfaceMethod org/apache/hadoop/hbase/client/Hbck.assigns:(Ljava/util/List;Z)Ljava/util/List;
     546: pop
     547: goto          495
     550: getstatic     #6                  // Field TEST_UTIL:Lorg/apache/hadoop/hbase/HBaseTestingUtility;
     553: invokevirtual #16                 // Method org/apache/hadoop/hbase/HBaseTestingUtility.getHBaseCluster:()Lorg/apache/hadoop/hbase/MiniHBaseCluster;
     556: invokevirtual #17                 // Method org/apache/hadoop/hbase/MiniHBaseCluster.getMaster:()Lorg/apache/hadoop/hbase/master/HMaster;
     559: invokevirtual #18                 // Method org/apache/hadoop/hbase/master/HMaster.getMasterProcedureExecutor:()Lorg/apache/hadoop/hbase/procedure2/ProcedureExecutor;
     562: invokevirtual #58                 // Method org/apache/hadoop/hbase/procedure2/ProcedureExecutor.getActiveProcIds:()Ljava/util/Set;
     565: invokeinterface #59,  1           // InterfaceMethod java/util/Set.isEmpty:()Z
     570: ifne          582
     573: ldc2_w        #40                 // long 100l
     576: invokestatic  #42                 // Method java/lang/Thread.sleep:(J)V
     579: goto          550
     582: aload_3
     583: invokeinterface #22,  1           // InterfaceMethod java/util/List.iterator:()Ljava/util/Iterator;
     588: astore        6
     590: aload         6
     592: invokeinterface #23,  1           // InterfaceMethod java/util/Iterator.hasNext:()Z
     597: ifeq          643
     600: aload         6
     602: invokeinterface #24,  1           // InterfaceMethod java/util/Iterator.next:()Ljava/lang/Object;
     607: checkcast     #25                 // class org/apache/hadoop/hbase/client/RegionInfo
     610: astore        7
     612: aload         7
     614: invokevirtual #63                 // Method java/lang/Object.toString:()Ljava/lang/String;
     617: getstatic     #6                  // Field TEST_UTIL:Lorg/apache/hadoop/hbase/HBaseTestingUtility;
     620: invokevirtual #64                 // Method org/apache/hadoop/hbase/HBaseTestingUtility.getMiniHBaseCluster:()Lorg/apache/hadoop/hbase/MiniHBaseCluster;
     623: invokevirtual #17                 // Method org/apache/hadoop/hbase/MiniHBaseCluster.getMaster:()Lorg/apache/hadoop/hbase/master/HMaster;
     626: invokevirtual #65                 // Method org/apache/hadoop/hbase/master/HMaster.getAssignmentManager:()Lorg/apache/hadoop/hbase/master/assignment/AssignmentManager;
     629: invokevirtual #66                 // Method org/apache/hadoop/hbase/master/assignment/AssignmentManager.getRegionStates:()Lorg/apache/hadoop/hbase/master/assignment/RegionStates;
     632: aload         7
     634: invokevirtual #67                 // Method org/apache/hadoop/hbase/master/assignment/RegionStates.isRegionOnline:(Lorg/apache/hadoop/hbase/client/RegionInfo;)Z
     637: invokestatic  #68                 // Method org/junit/Assert.assertTrue:(Ljava/lang/String;Z)V
     640: goto          590
     643: return
    Exception table:
       from    to  target type
         422   435   438   Class java/lang/Throwable

  static org.slf4j.Logger access$000();
    Code:
       0: getstatic     #1                  // Field LOG:Lorg/slf4j/Logger;
       3: areturn

  static {};
    Code:
       0: ldc           #69                 // class org/apache/hadoop/hbase/master/assignment/TestRegionBypass
       2: invokestatic  #70                 // Method org/slf4j/LoggerFactory.getLogger:(Ljava/lang/Class;)Lorg/slf4j/Logger;
       5: putstatic     #1                  // Field LOG:Lorg/slf4j/Logger;
       8: ldc           #69                 // class org/apache/hadoop/hbase/master/assignment/TestRegionBypass
      10: invokestatic  #71                 // Method org/apache/hadoop/hbase/HBaseClassTestRule.forClass:(Ljava/lang/Class;)Lorg/apache/hadoop/hbase/HBaseClassTestRule;
      13: putstatic     #72                 // Field CLASS_RULE:Lorg/apache/hadoop/hbase/HBaseClassTestRule;
      16: new           #73                 // class org/apache/hadoop/hbase/HBaseTestingUtility
      19: dup
      20: invokespecial #74                 // Method org/apache/hadoop/hbase/HBaseTestingUtility."<init>":()V
      23: putstatic     #6                  // Field TEST_UTIL:Lorg/apache/hadoop/hbase/HBaseTestingUtility;
      26: return
}
