Compiled from "TestProcedureCoordinator.java"
class org.apache.hadoop.hbase.procedure.TestProcedureCoordinator$1 extends org.apache.hadoop.hbase.procedure.TestProcedureCoordinator$AcquireBarrierAnswer {
  final org.apache.hadoop.hbase.procedure.ProcedureCoordinator val$ref;

  final org.apache.hadoop.hbase.procedure.TestProcedureCoordinator this$0;

  org.apache.hadoop.hbase.procedure.TestProcedureCoordinator$1(org.apache.hadoop.hbase.procedure.TestProcedureCoordinator, java.lang.String, java.lang.String..., org.apache.hadoop.hbase.procedure.ProcedureCoordinator);
    Code:
       0: aload_0
       1: aload_1
       2: putfield      #1                  // Field this$0:Lorg/apache/hadoop/hbase/procedure/TestProcedureCoordinator;
       5: aload_0
       6: aload         4
       8: putfield      #2                  // Field val$ref:Lorg/apache/hadoop/hbase/procedure/ProcedureCoordinator;
      11: aload_0
      12: aload_1
      13: aload_2
      14: aload_3
      15: invokespecial #3                  // Method org/apache/hadoop/hbase/procedure/TestProcedureCoordinator$AcquireBarrierAnswer."<init>":(Lorg/apache/hadoop/hbase/procedure/TestProcedureCoordinator;Ljava/lang/String;[Ljava/lang/String;)V
      18: return

  public void doWork();
    Code:
       0: aload_0
       1: getfield      #2                  // Field val$ref:Lorg/apache/hadoop/hbase/procedure/ProcedureCoordinator;
       4: aload_0
       5: getfield      #4                  // Field opName:Ljava/lang/String;
       8: aload_0
       9: getfield      #5                  // Field cohort:[Ljava/lang/String;
      12: iconst_0
      13: aaload
      14: invokevirtual #6                  // Method org/apache/hadoop/hbase/procedure/ProcedureCoordinator.memberAcquiredBarrier:(Ljava/lang/String;Ljava/lang/String;)V
      17: aload_0
      18: getfield      #2                  // Field val$ref:Lorg/apache/hadoop/hbase/procedure/ProcedureCoordinator;
      21: aload_0
      22: getfield      #4                  // Field opName:Ljava/lang/String;
      25: aload_0
      26: getfield      #5                  // Field cohort:[Ljava/lang/String;
      29: iconst_0
      30: aaload
      31: iconst_0
      32: newarray       byte
      34: invokevirtual #7                  // Method org/apache/hadoop/hbase/procedure/ProcedureCoordinator.memberFinishedBarrier:(Ljava/lang/String;Ljava/lang/String;[B)V
      37: aload_0
      38: getfield      #2                  // Field val$ref:Lorg/apache/hadoop/hbase/procedure/ProcedureCoordinator;
      41: aload_0
      42: getfield      #4                  // Field opName:Ljava/lang/String;
      45: aload_0
      46: getfield      #5                  // Field cohort:[Ljava/lang/String;
      49: iconst_1
      50: aaload
      51: invokevirtual #6                  // Method org/apache/hadoop/hbase/procedure/ProcedureCoordinator.memberAcquiredBarrier:(Ljava/lang/String;Ljava/lang/String;)V
      54: aload_0
      55: getfield      #2                  // Field val$ref:Lorg/apache/hadoop/hbase/procedure/ProcedureCoordinator;
      58: aload_0
      59: getfield      #4                  // Field opName:Ljava/lang/String;
      62: aload_0
      63: getfield      #5                  // Field cohort:[Ljava/lang/String;
      66: iconst_2
      67: aaload
      68: invokevirtual #6                  // Method org/apache/hadoop/hbase/procedure/ProcedureCoordinator.memberAcquiredBarrier:(Ljava/lang/String;Ljava/lang/String;)V
      71: aload_0
      72: getfield      #2                  // Field val$ref:Lorg/apache/hadoop/hbase/procedure/ProcedureCoordinator;
      75: aload_0
      76: getfield      #4                  // Field opName:Ljava/lang/String;
      79: aload_0
      80: getfield      #5                  // Field cohort:[Ljava/lang/String;
      83: iconst_2
      84: aaload
      85: iconst_0
      86: newarray       byte
      88: invokevirtual #7                  // Method org/apache/hadoop/hbase/procedure/ProcedureCoordinator.memberFinishedBarrier:(Ljava/lang/String;Ljava/lang/String;[B)V
      91: aload_0
      92: getfield      #2                  // Field val$ref:Lorg/apache/hadoop/hbase/procedure/ProcedureCoordinator;
      95: aload_0
      96: getfield      #4                  // Field opName:Ljava/lang/String;
      99: aload_0
     100: getfield      #5                  // Field cohort:[Ljava/lang/String;
     103: iconst_3
     104: aaload
     105: invokevirtual #6                  // Method org/apache/hadoop/hbase/procedure/ProcedureCoordinator.memberAcquiredBarrier:(Ljava/lang/String;Ljava/lang/String;)V
     108: return
}
