Compiled from "TestHBaseTestingUtility.java"
public class org.apache.hadoop.hbase.TestHBaseTestingUtility {
  public static final org.apache.hadoop.hbase.HBaseClassTestRule CLASS_RULE;

  public org.junit.rules.TestName name;

  public org.apache.hadoop.hbase.TestHBaseTestingUtility();
    Code:
       0: aload_0
       1: invokespecial #1                  // Method java/lang/Object."<init>":()V
       4: aload_0
       5: new           #2                  // class org/junit/rules/TestName
       8: dup
       9: invokespecial #3                  // Method org/junit/rules/TestName."<init>":()V
      12: putfield      #4                  // Field name:Lorg/junit/rules/TestName;
      15: return

  public void testMultiClusters() throws java.lang.Exception;
    Code:
       0: new           #5                  // class org/apache/hadoop/hbase/HBaseTestingUtility
       3: dup
       4: invokespecial #6                  // Method org/apache/hadoop/hbase/HBaseTestingUtility."<init>":()V
       7: astore_1
       8: aload_1
       9: invokevirtual #7                  // Method org/apache/hadoop/hbase/HBaseTestingUtility.getConfiguration:()Lorg/apache/hadoop/conf/Configuration;
      12: ldc           #9                  // String zookeeper.znode.parent
      14: ldc           #10                 // String /1
      16: invokevirtual #11                 // Method org/apache/hadoop/conf/Configuration.set:(Ljava/lang/String;Ljava/lang/String;)V
      19: aload_1
      20: invokevirtual #12                 // Method org/apache/hadoop/hbase/HBaseTestingUtility.startMiniZKCluster:()Lorg/apache/hadoop/hbase/zookeeper/MiniZooKeeperCluster;
      23: pop
      24: new           #5                  // class org/apache/hadoop/hbase/HBaseTestingUtility
      27: dup
      28: invokespecial #6                  // Method org/apache/hadoop/hbase/HBaseTestingUtility."<init>":()V
      31: astore_2
      32: aload_2
      33: invokevirtual #7                  // Method org/apache/hadoop/hbase/HBaseTestingUtility.getConfiguration:()Lorg/apache/hadoop/conf/Configuration;
      36: ldc           #9                  // String zookeeper.znode.parent
      38: ldc           #13                 // String /2
      40: invokevirtual #11                 // Method org/apache/hadoop/conf/Configuration.set:(Ljava/lang/String;Ljava/lang/String;)V
      43: aload_2
      44: invokevirtual #7                  // Method org/apache/hadoop/hbase/HBaseTestingUtility.getConfiguration:()Lorg/apache/hadoop/conf/Configuration;
      47: ldc           #14                 // String hbase.zookeeper.property.clientPort
      49: aload_1
      50: invokevirtual #7                  // Method org/apache/hadoop/hbase/HBaseTestingUtility.getConfiguration:()Lorg/apache/hadoop/conf/Configuration;
      53: ldc           #14                 // String hbase.zookeeper.property.clientPort
      55: ldc           #15                 // String -1
      57: invokevirtual #16                 // Method org/apache/hadoop/conf/Configuration.get:(Ljava/lang/String;Ljava/lang/String;)Ljava/lang/String;
      60: invokevirtual #11                 // Method org/apache/hadoop/conf/Configuration.set:(Ljava/lang/String;Ljava/lang/String;)V
      63: aload_2
      64: aload_1
      65: invokevirtual #17                 // Method org/apache/hadoop/hbase/HBaseTestingUtility.getZkCluster:()Lorg/apache/hadoop/hbase/zookeeper/MiniZooKeeperCluster;
      68: invokevirtual #18                 // Method org/apache/hadoop/hbase/HBaseTestingUtility.setZkCluster:(Lorg/apache/hadoop/hbase/zookeeper/MiniZooKeeperCluster;)V
      71: new           #5                  // class org/apache/hadoop/hbase/HBaseTestingUtility
      74: dup
      75: invokespecial #6                  // Method org/apache/hadoop/hbase/HBaseTestingUtility."<init>":()V
      78: astore_3
      79: aload_3
      80: invokevirtual #7                  // Method org/apache/hadoop/hbase/HBaseTestingUtility.getConfiguration:()Lorg/apache/hadoop/conf/Configuration;
      83: ldc           #9                  // String zookeeper.znode.parent
      85: ldc           #19                 // String /3
      87: invokevirtual #11                 // Method org/apache/hadoop/conf/Configuration.set:(Ljava/lang/String;Ljava/lang/String;)V
      90: aload_3
      91: invokevirtual #7                  // Method org/apache/hadoop/hbase/HBaseTestingUtility.getConfiguration:()Lorg/apache/hadoop/conf/Configuration;
      94: ldc           #14                 // String hbase.zookeeper.property.clientPort
      96: aload_1
      97: invokevirtual #7                  // Method org/apache/hadoop/hbase/HBaseTestingUtility.getConfiguration:()Lorg/apache/hadoop/conf/Configuration;
     100: ldc           #14                 // String hbase.zookeeper.property.clientPort
     102: ldc           #15                 // String -1
     104: invokevirtual #16                 // Method org/apache/hadoop/conf/Configuration.get:(Ljava/lang/String;Ljava/lang/String;)Ljava/lang/String;
     107: invokevirtual #11                 // Method org/apache/hadoop/conf/Configuration.set:(Ljava/lang/String;Ljava/lang/String;)V
     110: aload_3
     111: aload_1
     112: invokevirtual #17                 // Method org/apache/hadoop/hbase/HBaseTestingUtility.getZkCluster:()Lorg/apache/hadoop/hbase/zookeeper/MiniZooKeeperCluster;
     115: invokevirtual #18                 // Method org/apache/hadoop/hbase/HBaseTestingUtility.setZkCluster:(Lorg/apache/hadoop/hbase/zookeeper/MiniZooKeeperCluster;)V
     118: aload_1
     119: invokevirtual #20                 // Method org/apache/hadoop/hbase/HBaseTestingUtility.startMiniCluster:()Lorg/apache/hadoop/hbase/MiniHBaseCluster;
     122: pop
     123: aload_2
     124: invokevirtual #20                 // Method org/apache/hadoop/hbase/HBaseTestingUtility.startMiniCluster:()Lorg/apache/hadoop/hbase/MiniHBaseCluster;
     127: pop
     128: aload_3
     129: invokevirtual #20                 // Method org/apache/hadoop/hbase/HBaseTestingUtility.startMiniCluster:()Lorg/apache/hadoop/hbase/MiniHBaseCluster;
     132: pop
     133: aload_0
     134: getfield      #4                  // Field name:Lorg/junit/rules/TestName;
     137: invokevirtual #21                 // Method org/junit/rules/TestName.getMethodName:()Ljava/lang/String;
     140: invokestatic  #22                 // Method org/apache/hadoop/hbase/TableName.valueOf:(Ljava/lang/String;)Lorg/apache/hadoop/hbase/TableName;
     143: astore        4
     145: ldc           #23                 // String fam
     147: invokestatic  #24                 // Method org/apache/hadoop/hbase/util/Bytes.toBytes:(Ljava/lang/String;)[B
     150: astore        5
     152: ldc           #25                 // String row
     154: invokestatic  #24                 // Method org/apache/hadoop/hbase/util/Bytes.toBytes:(Ljava/lang/String;)[B
     157: astore        6
     159: ldc           #26                 // String qual
     161: invokestatic  #24                 // Method org/apache/hadoop/hbase/util/Bytes.toBytes:(Ljava/lang/String;)[B
     164: astore        7
     166: ldc           #27                 // String value
     168: invokestatic  #24                 // Method org/apache/hadoop/hbase/util/Bytes.toBytes:(Ljava/lang/String;)[B
     171: astore        8
     173: aload_1
     174: aload         4
     176: aload         5
     178: invokevirtual #28                 // Method org/apache/hadoop/hbase/HBaseTestingUtility.createTable:(Lorg/apache/hadoop/hbase/TableName;[B)Lorg/apache/hadoop/hbase/client/Table;
     181: astore        9
     183: aload_2
     184: aload         4
     186: aload         5
     188: invokevirtual #28                 // Method org/apache/hadoop/hbase/HBaseTestingUtility.createTable:(Lorg/apache/hadoop/hbase/TableName;[B)Lorg/apache/hadoop/hbase/client/Table;
     191: astore        10
     193: new           #29                 // class org/apache/hadoop/hbase/client/Put
     196: dup
     197: aload         6
     199: invokespecial #30                 // Method org/apache/hadoop/hbase/client/Put."<init>":([B)V
     202: astore        11
     204: aload         11
     206: aload         5
     208: aload         7
     210: aload         8
     212: invokevirtual #31                 // Method org/apache/hadoop/hbase/client/Put.addColumn:([B[B[B)Lorg/apache/hadoop/hbase/client/Put;
     215: pop
     216: aload         9
     218: aload         11
     220: invokeinterface #32,  2           // InterfaceMethod org/apache/hadoop/hbase/client/Table.put:(Lorg/apache/hadoop/hbase/client/Put;)V
     225: new           #33                 // class org/apache/hadoop/hbase/client/Get
     228: dup
     229: aload         6
     231: invokespecial #34                 // Method org/apache/hadoop/hbase/client/Get."<init>":([B)V
     234: astore        12
     236: aload         12
     238: aload         5
     240: aload         7
     242: invokevirtual #35                 // Method org/apache/hadoop/hbase/client/Get.addColumn:([B[B)Lorg/apache/hadoop/hbase/client/Get;
     245: pop
     246: aload         9
     248: aload         12
     250: invokeinterface #36,  2           // InterfaceMethod org/apache/hadoop/hbase/client/Table.get:(Lorg/apache/hadoop/hbase/client/Get;)Lorg/apache/hadoop/hbase/client/Result;
     255: astore        13
     257: lconst_1
     258: aload         13
     260: invokevirtual #37                 // Method org/apache/hadoop/hbase/client/Result.size:()I
     263: i2l
     264: invokestatic  #38                 // Method org/junit/Assert.assertEquals:(JJ)V
     267: aload         10
     269: aload         12
     271: invokeinterface #36,  2           // InterfaceMethod org/apache/hadoop/hbase/client/Table.get:(Lorg/apache/hadoop/hbase/client/Get;)Lorg/apache/hadoop/hbase/client/Result;
     276: astore        13
     278: lconst_0
     279: aload         13
     281: invokevirtual #37                 // Method org/apache/hadoop/hbase/client/Result.size:()I
     284: i2l
     285: invokestatic  #38                 // Method org/junit/Assert.assertEquals:(JJ)V
     288: aload         9
     290: invokeinterface #39,  1           // InterfaceMethod org/apache/hadoop/hbase/client/Table.close:()V
     295: aload         10
     297: invokeinterface #39,  1           // InterfaceMethod org/apache/hadoop/hbase/client/Table.close:()V
     302: aload_3
     303: invokevirtual #40                 // Method org/apache/hadoop/hbase/HBaseTestingUtility.shutdownMiniCluster:()V
     306: aload_2
     307: invokevirtual #40                 // Method org/apache/hadoop/hbase/HBaseTestingUtility.shutdownMiniCluster:()V
     310: aload_1
     311: invokevirtual #40                 // Method org/apache/hadoop/hbase/HBaseTestingUtility.shutdownMiniCluster:()V
     314: goto          334
     317: astore        14
     319: aload_3
     320: invokevirtual #40                 // Method org/apache/hadoop/hbase/HBaseTestingUtility.shutdownMiniCluster:()V
     323: aload_2
     324: invokevirtual #40                 // Method org/apache/hadoop/hbase/HBaseTestingUtility.shutdownMiniCluster:()V
     327: aload_1
     328: invokevirtual #40                 // Method org/apache/hadoop/hbase/HBaseTestingUtility.shutdownMiniCluster:()V
     331: aload         14
     333: athrow
     334: return
    Exception table:
       from    to  target type
         118   302   317   any
         317   319   317   any

  public void testMiniCluster() throws java.lang.Exception;
    Code:
       0: new           #5                  // class org/apache/hadoop/hbase/HBaseTestingUtility
       3: dup
       4: invokespecial #6                  // Method org/apache/hadoop/hbase/HBaseTestingUtility."<init>":()V
       7: astore_1
       8: aload_1
       9: invokevirtual #20                 // Method org/apache/hadoop/hbase/HBaseTestingUtility.startMiniCluster:()Lorg/apache/hadoop/hbase/MiniHBaseCluster;
      12: astore_2
      13: lconst_1
      14: aload_2
      15: invokevirtual #41                 // Method org/apache/hadoop/hbase/MiniHBaseCluster.getLiveRegionServerThreads:()Ljava/util/List;
      18: invokeinterface #42,  1           // InterfaceMethod java/util/List.size:()I
      23: i2l
      24: invokestatic  #38                 // Method org/junit/Assert.assertEquals:(JJ)V
      27: aload_1
      28: invokevirtual #40                 // Method org/apache/hadoop/hbase/HBaseTestingUtility.shutdownMiniCluster:()V
      31: goto          41
      34: astore_3
      35: aload_1
      36: invokevirtual #40                 // Method org/apache/hadoop/hbase/HBaseTestingUtility.shutdownMiniCluster:()V
      39: aload_3
      40: athrow
      41: return
    Exception table:
       from    to  target type
          13    27    34   any

  public void testMiniClusterBindToWildcard() throws java.lang.Exception;
    Code:
       0: new           #5                  // class org/apache/hadoop/hbase/HBaseTestingUtility
       3: dup
       4: invokespecial #6                  // Method org/apache/hadoop/hbase/HBaseTestingUtility."<init>":()V
       7: astore_1
       8: aload_1
       9: invokevirtual #7                  // Method org/apache/hadoop/hbase/HBaseTestingUtility.getConfiguration:()Lorg/apache/hadoop/conf/Configuration;
      12: ldc           #43                 // String hbase.regionserver.ipc.address
      14: ldc           #44                 // String 0.0.0.0
      16: invokevirtual #11                 // Method org/apache/hadoop/conf/Configuration.set:(Ljava/lang/String;Ljava/lang/String;)V
      19: aload_1
      20: invokevirtual #20                 // Method org/apache/hadoop/hbase/HBaseTestingUtility.startMiniCluster:()Lorg/apache/hadoop/hbase/MiniHBaseCluster;
      23: astore_2
      24: lconst_1
      25: aload_2
      26: invokevirtual #41                 // Method org/apache/hadoop/hbase/MiniHBaseCluster.getLiveRegionServerThreads:()Ljava/util/List;
      29: invokeinterface #42,  1           // InterfaceMethod java/util/List.size:()I
      34: i2l
      35: invokestatic  #38                 // Method org/junit/Assert.assertEquals:(JJ)V
      38: aload_1
      39: invokevirtual #40                 // Method org/apache/hadoop/hbase/HBaseTestingUtility.shutdownMiniCluster:()V
      42: goto          52
      45: astore_3
      46: aload_1
      47: invokevirtual #40                 // Method org/apache/hadoop/hbase/HBaseTestingUtility.shutdownMiniCluster:()V
      50: aload_3
      51: athrow
      52: return
    Exception table:
       from    to  target type
          24    38    45   any

  public void testMiniClusterWithSSLOn() throws java.lang.Exception;
    Code:
       0: new           #45                 // class java/lang/StringBuilder
       3: dup
       4: invokespecial #46                 // Method java/lang/StringBuilder."<init>":()V
       7: ldc           #47                 // String test.build.dir
       9: ldc           #48                 // String target/test-dir
      11: invokestatic  #49                 // Method java/lang/System.getProperty:(Ljava/lang/String;Ljava/lang/String;)Ljava/lang/String;
      14: invokevirtual #50                 // Method java/lang/StringBuilder.append:(Ljava/lang/String;)Ljava/lang/StringBuilder;
      17: ldc           #51                 // String /
      19: invokevirtual #50                 // Method java/lang/StringBuilder.append:(Ljava/lang/String;)Ljava/lang/StringBuilder;
      22: ldc           #52                 // class org/apache/hadoop/hbase/TestHBaseTestingUtility
      24: invokevirtual #53                 // Method java/lang/Class.getSimpleName:()Ljava/lang/String;
      27: invokevirtual #50                 // Method java/lang/StringBuilder.append:(Ljava/lang/String;)Ljava/lang/StringBuilder;
      30: invokevirtual #54                 // Method java/lang/StringBuilder.toString:()Ljava/lang/String;
      33: astore_1
      34: ldc           #52                 // class org/apache/hadoop/hbase/TestHBaseTestingUtility
      36: invokestatic  #55                 // Method org/apache/hadoop/hbase/http/ssl/KeyStoreTestUtil.getClasspathDir:(Ljava/lang/Class;)Ljava/lang/String;
      39: astore_2
      40: new           #56                 // class java/io/File
      43: dup
      44: aload_1
      45: invokespecial #57                 // Method java/io/File."<init>":(Ljava/lang/String;)V
      48: invokevirtual #58                 // Method java/io/File.getAbsolutePath:()Ljava/lang/String;
      51: astore_3
      52: new           #5                  // class org/apache/hadoop/hbase/HBaseTestingUtility
      55: dup
      56: invokespecial #6                  // Method org/apache/hadoop/hbase/HBaseTestingUtility."<init>":()V
      59: astore        4
      61: new           #56                 // class java/io/File
      64: dup
      65: aload_1
      66: invokespecial #57                 // Method java/io/File."<init>":(Ljava/lang/String;)V
      69: astore        5
      71: aload         5
      73: invokestatic  #59                 // Method org/apache/hadoop/fs/FileUtil.fullyDelete:(Ljava/io/File;)Z
      76: pop
      77: aload         5
      79: invokevirtual #60                 // Method java/io/File.mkdirs:()Z
      82: pop
      83: aload_3
      84: aload_2
      85: aload         4
      87: invokevirtual #7                  // Method org/apache/hadoop/hbase/HBaseTestingUtility.getConfiguration:()Lorg/apache/hadoop/conf/Configuration;
      90: iconst_0
      91: invokestatic  #61                 // Method org/apache/hadoop/hbase/http/ssl/KeyStoreTestUtil.setupSSLConfig:(Ljava/lang/String;Ljava/lang/String;Lorg/apache/hadoop/conf/Configuration;Z)V
      94: aload         4
      96: invokevirtual #7                  // Method org/apache/hadoop/hbase/HBaseTestingUtility.getConfiguration:()Lorg/apache/hadoop/conf/Configuration;
      99: ldc           #62                 // String hbase.ssl.enabled
     101: ldc           #63                 // String true
     103: invokevirtual #11                 // Method org/apache/hadoop/conf/Configuration.set:(Ljava/lang/String;Ljava/lang/String;)V
     106: aload         4
     108: invokevirtual #7                  // Method org/apache/hadoop/hbase/HBaseTestingUtility.getConfiguration:()Lorg/apache/hadoop/conf/Configuration;
     111: ldc           #64                 // String ssl-server.xml
     113: invokevirtual #65                 // Method org/apache/hadoop/conf/Configuration.addResource:(Ljava/lang/String;)V
     116: aload         4
     118: invokevirtual #7                  // Method org/apache/hadoop/hbase/HBaseTestingUtility.getConfiguration:()Lorg/apache/hadoop/conf/Configuration;
     121: ldc           #66                 // String ssl-client.xml
     123: invokevirtual #65                 // Method org/apache/hadoop/conf/Configuration.addResource:(Ljava/lang/String;)V
     126: aload         4
     128: invokevirtual #20                 // Method org/apache/hadoop/hbase/HBaseTestingUtility.startMiniCluster:()Lorg/apache/hadoop/hbase/MiniHBaseCluster;
     131: astore        6
     133: lconst_1
     134: aload         6
     136: invokevirtual #41                 // Method org/apache/hadoop/hbase/MiniHBaseCluster.getLiveRegionServerThreads:()Ljava/util/List;
     139: invokeinterface #42,  1           // InterfaceMethod java/util/List.size:()I
     144: i2l
     145: invokestatic  #38                 // Method org/junit/Assert.assertEquals:(JJ)V
     148: aload         4
     150: invokevirtual #40                 // Method org/apache/hadoop/hbase/HBaseTestingUtility.shutdownMiniCluster:()V
     153: goto          166
     156: astore        7
     158: aload         4
     160: invokevirtual #40                 // Method org/apache/hadoop/hbase/HBaseTestingUtility.shutdownMiniCluster:()V
     163: aload         7
     165: athrow
     166: return
    Exception table:
       from    to  target type
         133   148   156   any
         156   158   156   any

  public void testMultipleStartStop() throws java.lang.Exception;
    Code:
       0: new           #5                  // class org/apache/hadoop/hbase/HBaseTestingUtility
       3: dup
       4: invokespecial #6                  // Method org/apache/hadoop/hbase/HBaseTestingUtility."<init>":()V
       7: astore_1
       8: new           #67                 // class org/apache/hadoop/fs/Path
      11: dup
      12: ldc           #68                 // String foo
      14: invokespecial #69                 // Method org/apache/hadoop/fs/Path."<init>":(Ljava/lang/String;)V
      17: astore_2
      18: aload_1
      19: invokevirtual #20                 // Method org/apache/hadoop/hbase/HBaseTestingUtility.startMiniCluster:()Lorg/apache/hadoop/hbase/MiniHBaseCluster;
      22: pop
      23: aload_1
      24: invokevirtual #70                 // Method org/apache/hadoop/hbase/HBaseTestingUtility.getDFSCluster:()Lorg/apache/hadoop/hdfs/MiniDFSCluster;
      27: invokevirtual #71                 // Method org/apache/hadoop/hdfs/MiniDFSCluster.getFileSystem:()Lorg/apache/hadoop/hdfs/DistributedFileSystem;
      30: aload_2
      31: invokevirtual #72                 // Method org/apache/hadoop/hdfs/DistributedFileSystem.create:(Lorg/apache/hadoop/fs/Path;)Lorg/apache/hadoop/fs/FSDataOutputStream;
      34: pop
      35: aload_1
      36: invokevirtual #70                 // Method org/apache/hadoop/hbase/HBaseTestingUtility.getDFSCluster:()Lorg/apache/hadoop/hdfs/MiniDFSCluster;
      39: invokevirtual #71                 // Method org/apache/hadoop/hdfs/MiniDFSCluster.getFileSystem:()Lorg/apache/hadoop/hdfs/DistributedFileSystem;
      42: aload_2
      43: invokevirtual #73                 // Method org/apache/hadoop/hdfs/DistributedFileSystem.exists:(Lorg/apache/hadoop/fs/Path;)Z
      46: invokestatic  #74                 // Method org/junit/Assert.assertTrue:(Z)V
      49: aload_1
      50: invokevirtual #40                 // Method org/apache/hadoop/hbase/HBaseTestingUtility.shutdownMiniCluster:()V
      53: aload_1
      54: invokevirtual #20                 // Method org/apache/hadoop/hbase/HBaseTestingUtility.startMiniCluster:()Lorg/apache/hadoop/hbase/MiniHBaseCluster;
      57: pop
      58: aload_1
      59: invokevirtual #70                 // Method org/apache/hadoop/hbase/HBaseTestingUtility.getDFSCluster:()Lorg/apache/hadoop/hdfs/MiniDFSCluster;
      62: invokevirtual #71                 // Method org/apache/hadoop/hdfs/MiniDFSCluster.getFileSystem:()Lorg/apache/hadoop/hdfs/DistributedFileSystem;
      65: aload_2
      66: invokevirtual #73                 // Method org/apache/hadoop/hdfs/DistributedFileSystem.exists:(Lorg/apache/hadoop/fs/Path;)Z
      69: invokestatic  #75                 // Method org/junit/Assert.assertFalse:(Z)V
      72: aload_1
      73: invokevirtual #70                 // Method org/apache/hadoop/hbase/HBaseTestingUtility.getDFSCluster:()Lorg/apache/hadoop/hdfs/MiniDFSCluster;
      76: invokevirtual #71                 // Method org/apache/hadoop/hdfs/MiniDFSCluster.getFileSystem:()Lorg/apache/hadoop/hdfs/DistributedFileSystem;
      79: aload_2
      80: invokevirtual #72                 // Method org/apache/hadoop/hdfs/DistributedFileSystem.create:(Lorg/apache/hadoop/fs/Path;)Lorg/apache/hadoop/fs/FSDataOutputStream;
      83: pop
      84: aload_1
      85: invokevirtual #70                 // Method org/apache/hadoop/hbase/HBaseTestingUtility.getDFSCluster:()Lorg/apache/hadoop/hdfs/MiniDFSCluster;
      88: invokevirtual #71                 // Method org/apache/hadoop/hdfs/MiniDFSCluster.getFileSystem:()Lorg/apache/hadoop/hdfs/DistributedFileSystem;
      91: aload_2
      92: invokevirtual #73                 // Method org/apache/hadoop/hdfs/DistributedFileSystem.exists:(Lorg/apache/hadoop/fs/Path;)Z
      95: invokestatic  #74                 // Method org/junit/Assert.assertTrue:(Z)V
      98: aload_1
      99: invokevirtual #40                 // Method org/apache/hadoop/hbase/HBaseTestingUtility.shutdownMiniCluster:()V
     102: return

  public void testMiniZooKeeperWithOneServer() throws java.lang.Exception;
    Code:
       0: new           #5                  // class org/apache/hadoop/hbase/HBaseTestingUtility
       3: dup
       4: invokespecial #6                  // Method org/apache/hadoop/hbase/HBaseTestingUtility."<init>":()V
       7: astore_1
       8: aload_1
       9: invokevirtual #12                 // Method org/apache/hadoop/hbase/HBaseTestingUtility.startMiniZKCluster:()Lorg/apache/hadoop/hbase/zookeeper/MiniZooKeeperCluster;
      12: astore_2
      13: lconst_0
      14: aload_2
      15: invokevirtual #76                 // Method org/apache/hadoop/hbase/zookeeper/MiniZooKeeperCluster.getBackupZooKeeperServerNum:()I
      18: i2l
      19: invokestatic  #38                 // Method org/junit/Assert.assertEquals:(JJ)V
      22: aload_2
      23: invokevirtual #77                 // Method org/apache/hadoop/hbase/zookeeper/MiniZooKeeperCluster.killCurrentActiveZooKeeperServer:()I
      26: iconst_m1
      27: if_icmpne     34
      30: iconst_1
      31: goto          35
      34: iconst_0
      35: invokestatic  #74                 // Method org/junit/Assert.assertTrue:(Z)V
      38: aload_1
      39: invokevirtual #78                 // Method org/apache/hadoop/hbase/HBaseTestingUtility.shutdownMiniZKCluster:()V
      42: goto          52
      45: astore_3
      46: aload_1
      47: invokevirtual #78                 // Method org/apache/hadoop/hbase/HBaseTestingUtility.shutdownMiniZKCluster:()V
      50: aload_3
      51: athrow
      52: return
    Exception table:
       from    to  target type
          13    38    45   any

  public void testMiniZooKeeperWithMultipleServers() throws java.lang.Exception;
    Code:
       0: new           #5                  // class org/apache/hadoop/hbase/HBaseTestingUtility
       3: dup
       4: invokespecial #6                  // Method org/apache/hadoop/hbase/HBaseTestingUtility."<init>":()V
       7: astore_1
       8: aload_1
       9: iconst_5
      10: iconst_0
      11: newarray       int
      13: invokevirtual #79                 // Method org/apache/hadoop/hbase/HBaseTestingUtility.startMiniZKCluster:(I[I)Lorg/apache/hadoop/hbase/zookeeper/MiniZooKeeperCluster;
      16: astore_2
      17: sipush        21818
      20: istore_3
      21: aload_2
      22: iload_3
      23: invokevirtual #80                 // Method org/apache/hadoop/hbase/zookeeper/MiniZooKeeperCluster.setDefaultClientPort:(I)V
      26: ldc2_w        #81                 // long 4l
      29: aload_2
      30: invokevirtual #76                 // Method org/apache/hadoop/hbase/zookeeper/MiniZooKeeperCluster.getBackupZooKeeperServerNum:()I
      33: i2l
      34: invokestatic  #38                 // Method org/junit/Assert.assertEquals:(JJ)V
      37: aload_2
      38: invokevirtual #77                 // Method org/apache/hadoop/hbase/zookeeper/MiniZooKeeperCluster.killCurrentActiveZooKeeperServer:()I
      41: istore        4
      43: iload         4
      45: iload_3
      46: if_icmplt     53
      49: iconst_1
      50: goto          54
      53: iconst_0
      54: invokestatic  #74                 // Method org/junit/Assert.assertTrue:(Z)V
      57: aload_2
      58: invokevirtual #83                 // Method org/apache/hadoop/hbase/zookeeper/MiniZooKeeperCluster.getClientPort:()I
      61: iload         4
      63: if_icmpne     70
      66: iconst_1
      67: goto          71
      70: iconst_0
      71: invokestatic  #74                 // Method org/junit/Assert.assertTrue:(Z)V
      74: aload_2
      75: invokevirtual #77                 // Method org/apache/hadoop/hbase/zookeeper/MiniZooKeeperCluster.killCurrentActiveZooKeeperServer:()I
      78: istore        4
      80: iload         4
      82: iload_3
      83: if_icmplt     90
      86: iconst_1
      87: goto          91
      90: iconst_0
      91: invokestatic  #74                 // Method org/junit/Assert.assertTrue:(Z)V
      94: aload_2
      95: invokevirtual #83                 // Method org/apache/hadoop/hbase/zookeeper/MiniZooKeeperCluster.getClientPort:()I
      98: iload         4
     100: if_icmpne     107
     103: iconst_1
     104: goto          108
     107: iconst_0
     108: invokestatic  #74                 // Method org/junit/Assert.assertTrue:(Z)V
     111: ldc2_w        #84                 // long 2l
     114: aload_2
     115: invokevirtual #76                 // Method org/apache/hadoop/hbase/zookeeper/MiniZooKeeperCluster.getBackupZooKeeperServerNum:()I
     118: i2l
     119: invokestatic  #38                 // Method org/junit/Assert.assertEquals:(JJ)V
     122: ldc2_w        #86                 // long 3l
     125: aload_2
     126: invokevirtual #88                 // Method org/apache/hadoop/hbase/zookeeper/MiniZooKeeperCluster.getZooKeeperServerNum:()I
     129: i2l
     130: invokestatic  #38                 // Method org/junit/Assert.assertEquals:(JJ)V
     133: aload_2
     134: invokevirtual #89                 // Method org/apache/hadoop/hbase/zookeeper/MiniZooKeeperCluster.killOneBackupZooKeeperServer:()V
     137: aload_2
     138: invokevirtual #89                 // Method org/apache/hadoop/hbase/zookeeper/MiniZooKeeperCluster.killOneBackupZooKeeperServer:()V
     141: lconst_0
     142: aload_2
     143: invokevirtual #76                 // Method org/apache/hadoop/hbase/zookeeper/MiniZooKeeperCluster.getBackupZooKeeperServerNum:()I
     146: i2l
     147: invokestatic  #38                 // Method org/junit/Assert.assertEquals:(JJ)V
     150: lconst_1
     151: aload_2
     152: invokevirtual #88                 // Method org/apache/hadoop/hbase/zookeeper/MiniZooKeeperCluster.getZooKeeperServerNum:()I
     155: i2l
     156: invokestatic  #38                 // Method org/junit/Assert.assertEquals:(JJ)V
     159: aload_2
     160: invokevirtual #77                 // Method org/apache/hadoop/hbase/zookeeper/MiniZooKeeperCluster.killCurrentActiveZooKeeperServer:()I
     163: istore        4
     165: iload         4
     167: iconst_m1
     168: if_icmpne     175
     171: iconst_1
     172: goto          176
     175: iconst_0
     176: invokestatic  #74                 // Method org/junit/Assert.assertTrue:(Z)V
     179: aload_2
     180: invokevirtual #83                 // Method org/apache/hadoop/hbase/zookeeper/MiniZooKeeperCluster.getClientPort:()I
     183: iload         4
     185: if_icmpne     192
     188: iconst_1
     189: goto          193
     192: iconst_0
     193: invokestatic  #74                 // Method org/junit/Assert.assertTrue:(Z)V
     196: aload_2
     197: invokevirtual #89                 // Method org/apache/hadoop/hbase/zookeeper/MiniZooKeeperCluster.killOneBackupZooKeeperServer:()V
     200: ldc2_w        #90                 // long -1l
     203: aload_2
     204: invokevirtual #76                 // Method org/apache/hadoop/hbase/zookeeper/MiniZooKeeperCluster.getBackupZooKeeperServerNum:()I
     207: i2l
     208: invokestatic  #38                 // Method org/junit/Assert.assertEquals:(JJ)V
     211: lconst_0
     212: aload_2
     213: invokevirtual #88                 // Method org/apache/hadoop/hbase/zookeeper/MiniZooKeeperCluster.getZooKeeperServerNum:()I
     216: i2l
     217: invokestatic  #38                 // Method org/junit/Assert.assertEquals:(JJ)V
     220: aload_1
     221: invokevirtual #78                 // Method org/apache/hadoop/hbase/HBaseTestingUtility.shutdownMiniZKCluster:()V
     224: goto          236
     227: astore        5
     229: aload_1
     230: invokevirtual #78                 // Method org/apache/hadoop/hbase/HBaseTestingUtility.shutdownMiniZKCluster:()V
     233: aload         5
     235: athrow
     236: return
    Exception table:
       from    to  target type
          26   220   227   any
         227   229   227   any

  public void testMiniZooKeeperWithMultipleClientPorts() throws java.lang.Exception;
    Code:
       0: sipush        8888
       3: istore_1
       4: new           #5                  // class org/apache/hadoop/hbase/HBaseTestingUtility
       7: dup
       8: invokespecial #6                  // Method org/apache/hadoop/hbase/HBaseTestingUtility."<init>":()V
      11: astore        4
      13: iconst_3
      14: newarray       int
      16: dup
      17: iconst_0
      18: sipush        1111
      21: iastore
      22: dup
      23: iconst_1
      24: sipush        1112
      27: iastore
      28: dup
      29: iconst_2
      30: sipush        1113
      33: iastore
      34: astore        5
      36: aload         4
      38: aload         5
      40: arraylength
      41: aload         5
      43: invokevirtual #79                 // Method org/apache/hadoop/hbase/HBaseTestingUtility.startMiniZKCluster:(I[I)Lorg/apache/hadoop/hbase/zookeeper/MiniZooKeeperCluster;
      46: astore        6
      48: aload         6
      50: invokevirtual #92                 // Method org/apache/hadoop/hbase/zookeeper/MiniZooKeeperCluster.getClientPortList:()Ljava/util/List;
      53: astore        7
      55: iconst_0
      56: istore_2
      57: iload_2
      58: aload         7
      60: invokeinterface #42,  1           // InterfaceMethod java/util/List.size:()I
      65: if_icmpge     103
      68: aload         7
      70: iload_2
      71: invokeinterface #93,  2           // InterfaceMethod java/util/List.get:(I)Ljava/lang/Object;
      76: checkcast     #94                 // class java/lang/Integer
      79: invokevirtual #95                 // Method java/lang/Integer.intValue:()I
      82: aload         5
      84: iload_2
      85: iaload
      86: if_icmplt     93
      89: iconst_1
      90: goto          94
      93: iconst_0
      94: invokestatic  #74                 // Method org/junit/Assert.assertTrue:(Z)V
      97: iinc          2, 1
     100: goto          57
     103: aload         4
     105: invokevirtual #78                 // Method org/apache/hadoop/hbase/HBaseTestingUtility.shutdownMiniZKCluster:()V
     108: goto          121
     111: astore        8
     113: aload         4
     115: invokevirtual #78                 // Method org/apache/hadoop/hbase/HBaseTestingUtility.shutdownMiniZKCluster:()V
     118: aload         8
     120: athrow
     121: aload         4
     123: invokevirtual #7                  // Method org/apache/hadoop/hbase/HBaseTestingUtility.getConfiguration:()Lorg/apache/hadoop/conf/Configuration;
     126: ldc           #96                 // String test.hbase.zookeeper.property.clientPort
     128: iload_1
     129: invokevirtual #97                 // Method org/apache/hadoop/conf/Configuration.setInt:(Ljava/lang/String;I)V
     132: iconst_2
     133: newarray       int
     135: dup
     136: iconst_0
     137: sipush        2222
     140: iastore
     141: dup
     142: iconst_1
     143: sipush        2223
     146: iastore
     147: astore        7
     149: aload         4
     151: aload         7
     153: arraylength
     154: iconst_2
     155: iadd
     156: aload         7
     158: invokevirtual #79                 // Method org/apache/hadoop/hbase/HBaseTestingUtility.startMiniZKCluster:(I[I)Lorg/apache/hadoop/hbase/zookeeper/MiniZooKeeperCluster;
     161: astore        8
     163: aload         8
     165: invokevirtual #92                 // Method org/apache/hadoop/hbase/zookeeper/MiniZooKeeperCluster.getClientPortList:()Ljava/util/List;
     168: astore        9
     170: iconst_0
     171: istore_2
     172: iconst_0
     173: istore_3
     174: iload_2
     175: aload         9
     177: invokeinterface #42,  1           // InterfaceMethod java/util/List.size:()I
     182: if_icmpge     261
     185: iload_2
     186: aload         7
     188: arraylength
     189: if_icmpge     224
     192: aload         9
     194: iload_2
     195: invokeinterface #93,  2           // InterfaceMethod java/util/List.get:(I)Ljava/lang/Object;
     200: checkcast     #94                 // class java/lang/Integer
     203: invokevirtual #95                 // Method java/lang/Integer.intValue:()I
     206: aload         7
     208: iload_2
     209: iaload
     210: if_icmplt     217
     213: iconst_1
     214: goto          218
     217: iconst_0
     218: invokestatic  #74                 // Method org/junit/Assert.assertTrue:(Z)V
     221: goto          255
     224: aload         9
     226: iload_2
     227: invokeinterface #93,  2           // InterfaceMethod java/util/List.get:(I)Ljava/lang/Object;
     232: checkcast     #94                 // class java/lang/Integer
     235: invokevirtual #95                 // Method java/lang/Integer.intValue:()I
     238: iload_1
     239: iload_3
     240: iadd
     241: if_icmplt     248
     244: iconst_1
     245: goto          249
     248: iconst_0
     249: invokestatic  #74                 // Method org/junit/Assert.assertTrue:(Z)V
     252: iinc          3, 1
     255: iinc          2, 1
     258: goto          174
     261: aload         4
     263: invokevirtual #78                 // Method org/apache/hadoop/hbase/HBaseTestingUtility.shutdownMiniZKCluster:()V
     266: goto          279
     269: astore        10
     271: aload         4
     273: invokevirtual #78                 // Method org/apache/hadoop/hbase/HBaseTestingUtility.shutdownMiniZKCluster:()V
     276: aload         10
     278: athrow
     279: aload         4
     281: invokevirtual #7                  // Method org/apache/hadoop/hbase/HBaseTestingUtility.getConfiguration:()Lorg/apache/hadoop/conf/Configuration;
     284: ldc           #96                 // String test.hbase.zookeeper.property.clientPort
     286: iload_1
     287: invokevirtual #97                 // Method org/apache/hadoop/conf/Configuration.setInt:(Ljava/lang/String;I)V
     290: iconst_4
     291: newarray       int
     293: dup
     294: iconst_0
     295: sipush        3333
     298: iastore
     299: dup
     300: iconst_1
     301: sipush        -3334
     304: iastore
     305: dup
     306: iconst_2
     307: sipush        3335
     310: iastore
     311: dup
     312: iconst_3
     313: iconst_0
     314: iastore
     315: astore        9
     317: aload         4
     319: aload         9
     321: arraylength
     322: iconst_1
     323: iadd
     324: aload         9
     326: invokevirtual #79                 // Method org/apache/hadoop/hbase/HBaseTestingUtility.startMiniZKCluster:(I[I)Lorg/apache/hadoop/hbase/zookeeper/MiniZooKeeperCluster;
     329: astore        10
     331: aload         10
     333: invokevirtual #92                 // Method org/apache/hadoop/hbase/zookeeper/MiniZooKeeperCluster.getClientPortList:()Ljava/util/List;
     336: astore        11
     338: iconst_0
     339: istore_2
     340: iconst_0
     341: istore_3
     342: iload_2
     343: aload         11
     345: invokeinterface #42,  1           // InterfaceMethod java/util/List.size:()I
     350: if_icmpge     436
     353: iload_2
     354: aload         9
     356: arraylength
     357: if_icmpge     399
     360: aload         9
     362: iload_2
     363: iaload
     364: ifle          399
     367: aload         11
     369: iload_2
     370: invokeinterface #93,  2           // InterfaceMethod java/util/List.get:(I)Ljava/lang/Object;
     375: checkcast     #94                 // class java/lang/Integer
     378: invokevirtual #95                 // Method java/lang/Integer.intValue:()I
     381: aload         9
     383: iload_2
     384: iaload
     385: if_icmplt     392
     388: iconst_1
     389: goto          393
     392: iconst_0
     393: invokestatic  #74                 // Method org/junit/Assert.assertTrue:(Z)V
     396: goto          430
     399: aload         11
     401: iload_2
     402: invokeinterface #93,  2           // InterfaceMethod java/util/List.get:(I)Ljava/lang/Object;
     407: checkcast     #94                 // class java/lang/Integer
     410: invokevirtual #95                 // Method java/lang/Integer.intValue:()I
     413: iload_1
     414: iload_3
     415: iadd
     416: if_icmplt     423
     419: iconst_1
     420: goto          424
     423: iconst_0
     424: invokestatic  #74                 // Method org/junit/Assert.assertTrue:(Z)V
     427: iinc          3, 1
     430: iinc          2, 1
     433: goto          342
     436: aload         4
     438: invokevirtual #78                 // Method org/apache/hadoop/hbase/HBaseTestingUtility.shutdownMiniZKCluster:()V
     441: goto          454
     444: astore        12
     446: aload         4
     448: invokevirtual #78                 // Method org/apache/hadoop/hbase/HBaseTestingUtility.shutdownMiniZKCluster:()V
     451: aload         12
     453: athrow
     454: aload         4
     456: invokevirtual #7                  // Method org/apache/hadoop/hbase/HBaseTestingUtility.getConfiguration:()Lorg/apache/hadoop/conf/Configuration;
     459: ldc           #96                 // String test.hbase.zookeeper.property.clientPort
     461: iload_1
     462: invokevirtual #97                 // Method org/apache/hadoop/conf/Configuration.setInt:(Ljava/lang/String;I)V
     465: iconst_4
     466: newarray       int
     468: dup
     469: iconst_0
     470: sipush        -4444
     473: iastore
     474: dup
     475: iconst_1
     476: iload_1
     477: iconst_2
     478: iadd
     479: iastore
     480: dup
     481: iconst_2
     482: sipush        4446
     485: iastore
     486: dup
     487: iconst_3
     488: iload_1
     489: iastore
     490: astore        11
     492: aload         4
     494: aload         11
     496: arraylength
     497: iconst_1
     498: iadd
     499: aload         11
     501: invokevirtual #79                 // Method org/apache/hadoop/hbase/HBaseTestingUtility.startMiniZKCluster:(I[I)Lorg/apache/hadoop/hbase/zookeeper/MiniZooKeeperCluster;
     504: astore        12
     506: aload         12
     508: invokevirtual #92                 // Method org/apache/hadoop/hbase/zookeeper/MiniZooKeeperCluster.getClientPortList:()Ljava/util/List;
     511: astore        13
     513: iconst_0
     514: istore_2
     515: iconst_1
     516: istore_3
     517: iload_2
     518: aload         13
     520: invokeinterface #42,  1           // InterfaceMethod java/util/List.size:()I
     525: if_icmpge     611
     528: iload_2
     529: aload         11
     531: arraylength
     532: if_icmpge     574
     535: aload         11
     537: iload_2
     538: iaload
     539: ifle          574
     542: aload         13
     544: iload_2
     545: invokeinterface #93,  2           // InterfaceMethod java/util/List.get:(I)Ljava/lang/Object;
     550: checkcast     #94                 // class java/lang/Integer
     553: invokevirtual #95                 // Method java/lang/Integer.intValue:()I
     556: aload         11
     558: iload_2
     559: iaload
     560: if_icmplt     567
     563: iconst_1
     564: goto          568
     567: iconst_0
     568: invokestatic  #74                 // Method org/junit/Assert.assertTrue:(Z)V
     571: goto          605
     574: aload         13
     576: iload_2
     577: invokeinterface #93,  2           // InterfaceMethod java/util/List.get:(I)Ljava/lang/Object;
     582: checkcast     #94                 // class java/lang/Integer
     585: invokevirtual #95                 // Method java/lang/Integer.intValue:()I
     588: iload_1
     589: iload_3
     590: iadd
     591: if_icmplt     598
     594: iconst_1
     595: goto          599
     598: iconst_0
     599: invokestatic  #74                 // Method org/junit/Assert.assertTrue:(Z)V
     602: iinc          3, 2
     605: iinc          2, 1
     608: goto          517
     611: aload         4
     613: invokevirtual #78                 // Method org/apache/hadoop/hbase/HBaseTestingUtility.shutdownMiniZKCluster:()V
     616: goto          629
     619: astore        14
     621: aload         4
     623: invokevirtual #78                 // Method org/apache/hadoop/hbase/HBaseTestingUtility.shutdownMiniZKCluster:()V
     626: aload         14
     628: athrow
     629: iconst_3
     630: newarray       int
     632: dup
     633: iconst_0
     634: sipush        5555
     637: iastore
     638: dup
     639: iconst_1
     640: sipush        5556
     643: iastore
     644: dup
     645: iconst_2
     646: sipush        5556
     649: iastore
     650: astore        13
     652: aload         4
     654: aload         13
     656: arraylength
     657: aload         13
     659: invokevirtual #79                 // Method org/apache/hadoop/hbase/HBaseTestingUtility.startMiniZKCluster:(I[I)Lorg/apache/hadoop/hbase/zookeeper/MiniZooKeeperCluster;
     662: astore        14
     664: aload         14
     666: invokevirtual #83                 // Method org/apache/hadoop/hbase/zookeeper/MiniZooKeeperCluster.getClientPort:()I
     669: iconst_m1
     670: if_icmpne     677
     673: iconst_1
     674: goto          678
     677: iconst_0
     678: invokestatic  #74                 // Method org/junit/Assert.assertTrue:(Z)V
     681: aload         4
     683: invokevirtual #78                 // Method org/apache/hadoop/hbase/HBaseTestingUtility.shutdownMiniZKCluster:()V
     686: goto          709
     689: astore        14
     691: aload         4
     693: invokevirtual #78                 // Method org/apache/hadoop/hbase/HBaseTestingUtility.shutdownMiniZKCluster:()V
     696: goto          709
     699: astore        15
     701: aload         4
     703: invokevirtual #78                 // Method org/apache/hadoop/hbase/HBaseTestingUtility.shutdownMiniZKCluster:()V
     706: aload         15
     708: athrow
     709: return
    Exception table:
       from    to  target type
          48   103   111   any
         111   113   111   any
         163   261   269   any
         269   271   269   any
         331   436   444   any
         444   446   444   any
         506   611   619   any
         619   621   619   any
         652   681   689   Class java/lang/Exception
         652   681   699   any
         689   691   699   any
         699   701   699   any

  public void testMiniDFSCluster() throws java.lang.Exception;
    Code:
       0: new           #5                  // class org/apache/hadoop/hbase/HBaseTestingUtility
       3: dup
       4: invokespecial #6                  // Method org/apache/hadoop/hbase/HBaseTestingUtility."<init>":()V
       7: astore_1
       8: aload_1
       9: aconst_null
      10: invokevirtual #99                 // Method org/apache/hadoop/hbase/HBaseTestingUtility.startMiniDFSCluster:([Ljava/lang/String;)Lorg/apache/hadoop/hdfs/MiniDFSCluster;
      13: astore_2
      14: aload_2
      15: invokevirtual #71                 // Method org/apache/hadoop/hdfs/MiniDFSCluster.getFileSystem:()Lorg/apache/hadoop/hdfs/DistributedFileSystem;
      18: astore_3
      19: new           #67                 // class org/apache/hadoop/fs/Path
      22: dup
      23: ldc           #100                // String dir
      25: invokespecial #69                 // Method org/apache/hadoop/fs/Path."<init>":(Ljava/lang/String;)V
      28: astore        4
      30: aload_3
      31: aload         4
      33: invokevirtual #101                // Method org/apache/hadoop/fs/FileSystem.makeQualified:(Lorg/apache/hadoop/fs/Path;)Lorg/apache/hadoop/fs/Path;
      36: astore        5
      38: getstatic     #102                // Field LOG:Lorg/slf4j/Logger;
      41: new           #45                 // class java/lang/StringBuilder
      44: dup
      45: invokespecial #46                 // Method java/lang/StringBuilder."<init>":()V
      48: ldc           #103                // String dir=
      50: invokevirtual #50                 // Method java/lang/StringBuilder.append:(Ljava/lang/String;)Ljava/lang/StringBuilder;
      53: aload         4
      55: invokevirtual #104                // Method java/lang/StringBuilder.append:(Ljava/lang/Object;)Ljava/lang/StringBuilder;
      58: ldc           #105                // String , qualifiedDir=
      60: invokevirtual #50                 // Method java/lang/StringBuilder.append:(Ljava/lang/String;)Ljava/lang/StringBuilder;
      63: aload         5
      65: invokevirtual #104                // Method java/lang/StringBuilder.append:(Ljava/lang/Object;)Ljava/lang/StringBuilder;
      68: invokevirtual #54                 // Method java/lang/StringBuilder.toString:()Ljava/lang/String;
      71: invokeinterface #106,  2          // InterfaceMethod org/slf4j/Logger.info:(Ljava/lang/String;)V
      76: aload_3
      77: aload         5
      79: invokevirtual #107                // Method org/apache/hadoop/fs/FileSystem.exists:(Lorg/apache/hadoop/fs/Path;)Z
      82: invokestatic  #75                 // Method org/junit/Assert.assertFalse:(Z)V
      85: aload_3
      86: aload         5
      88: invokevirtual #108                // Method org/apache/hadoop/fs/FileSystem.mkdirs:(Lorg/apache/hadoop/fs/Path;)Z
      91: invokestatic  #74                 // Method org/junit/Assert.assertTrue:(Z)V
      94: aload_3
      95: aload         5
      97: iconst_1
      98: invokevirtual #109                // Method org/apache/hadoop/fs/FileSystem.delete:(Lorg/apache/hadoop/fs/Path;Z)Z
     101: invokestatic  #74                 // Method org/junit/Assert.assertTrue:(Z)V
     104: aload_1
     105: invokevirtual #40                 // Method org/apache/hadoop/hbase/HBaseTestingUtility.shutdownMiniCluster:()V
     108: return

  public void testSetupClusterTestBuildDir() throws java.lang.Exception;
    Code:
       0: new           #5                  // class org/apache/hadoop/hbase/HBaseTestingUtility
       3: dup
       4: invokespecial #6                  // Method org/apache/hadoop/hbase/HBaseTestingUtility."<init>":()V
       7: astore_1
       8: aload_1
       9: invokevirtual #110                // Method org/apache/hadoop/hbase/HBaseTestingUtility.getClusterTestDir:()Lorg/apache/hadoop/fs/Path;
      12: astore_2
      13: getstatic     #102                // Field LOG:Lorg/slf4j/Logger;
      16: new           #45                 // class java/lang/StringBuilder
      19: dup
      20: invokespecial #46                 // Method java/lang/StringBuilder."<init>":()V
      23: ldc           #111                // String uuid-subdir=
      25: invokevirtual #50                 // Method java/lang/StringBuilder.append:(Ljava/lang/String;)Ljava/lang/StringBuilder;
      28: aload_2
      29: invokevirtual #104                // Method java/lang/StringBuilder.append:(Ljava/lang/Object;)Ljava/lang/StringBuilder;
      32: invokevirtual #54                 // Method java/lang/StringBuilder.toString:()Ljava/lang/String;
      35: invokeinterface #106,  2          // InterfaceMethod org/slf4j/Logger.info:(Ljava/lang/String;)V
      40: aload_1
      41: invokevirtual #112                // Method org/apache/hadoop/hbase/HBaseTestingUtility.getTestFileSystem:()Lorg/apache/hadoop/fs/FileSystem;
      44: astore_3
      45: aload_3
      46: aload_2
      47: invokevirtual #107                // Method org/apache/hadoop/fs/FileSystem.exists:(Lorg/apache/hadoop/fs/Path;)Z
      50: invokestatic  #75                 // Method org/junit/Assert.assertFalse:(Z)V
      53: aload_1
      54: aconst_null
      55: invokevirtual #99                 // Method org/apache/hadoop/hbase/HBaseTestingUtility.startMiniDFSCluster:([Ljava/lang/String;)Lorg/apache/hadoop/hdfs/MiniDFSCluster;
      58: pop
      59: aload_3
      60: aload_2
      61: invokevirtual #107                // Method org/apache/hadoop/fs/FileSystem.exists:(Lorg/apache/hadoop/fs/Path;)Z
      64: invokestatic  #74                 // Method org/junit/Assert.assertTrue:(Z)V
      67: aload_1
      68: invokevirtual #40                 // Method org/apache/hadoop/hbase/HBaseTestingUtility.shutdownMiniCluster:()V
      71: aload_3
      72: aload_2
      73: invokevirtual #107                // Method org/apache/hadoop/fs/FileSystem.exists:(Lorg/apache/hadoop/fs/Path;)Z
      76: invokestatic  #75                 // Method org/junit/Assert.assertFalse:(Z)V
      79: return

  public void testTestDir() throws java.lang.Exception;
    Code:
       0: new           #5                  // class org/apache/hadoop/hbase/HBaseTestingUtility
       3: dup
       4: invokespecial #6                  // Method org/apache/hadoop/hbase/HBaseTestingUtility."<init>":()V
       7: astore_1
       8: aload_1
       9: invokevirtual #113                // Method org/apache/hadoop/hbase/HBaseTestingUtility.getDataTestDir:()Lorg/apache/hadoop/fs/Path;
      12: astore_2
      13: getstatic     #102                // Field LOG:Lorg/slf4j/Logger;
      16: new           #45                 // class java/lang/StringBuilder
      19: dup
      20: invokespecial #46                 // Method java/lang/StringBuilder."<init>":()V
      23: ldc           #114                // String testdir=
      25: invokevirtual #50                 // Method java/lang/StringBuilder.append:(Ljava/lang/String;)Ljava/lang/StringBuilder;
      28: aload_2
      29: invokevirtual #104                // Method java/lang/StringBuilder.append:(Ljava/lang/Object;)Ljava/lang/StringBuilder;
      32: invokevirtual #54                 // Method java/lang/StringBuilder.toString:()Ljava/lang/String;
      35: invokeinterface #106,  2          // InterfaceMethod org/slf4j/Logger.info:(Ljava/lang/String;)V
      40: aload_1
      41: invokevirtual #112                // Method org/apache/hadoop/hbase/HBaseTestingUtility.getTestFileSystem:()Lorg/apache/hadoop/fs/FileSystem;
      44: astore_3
      45: aload_3
      46: aload_2
      47: invokevirtual #107                // Method org/apache/hadoop/fs/FileSystem.exists:(Lorg/apache/hadoop/fs/Path;)Z
      50: ifne          57
      53: iconst_1
      54: goto          58
      57: iconst_0
      58: invokestatic  #74                 // Method org/junit/Assert.assertTrue:(Z)V
      61: aload_3
      62: aload_2
      63: invokevirtual #108                // Method org/apache/hadoop/fs/FileSystem.mkdirs:(Lorg/apache/hadoop/fs/Path;)Z
      66: invokestatic  #74                 // Method org/junit/Assert.assertTrue:(Z)V
      69: aload_1
      70: invokevirtual #115                // Method org/apache/hadoop/hbase/HBaseTestingUtility.cleanupTestDir:()Z
      73: invokestatic  #74                 // Method org/junit/Assert.assertTrue:(Z)V
      76: return

  public void testResolvePortConflict() throws java.lang.Exception;
    Code:
       0: ldc           #116                // class java/util/Random
       2: invokestatic  #117                // Method org/mockito/Mockito.mock:(Ljava/lang/Class;)Ljava/lang/Object;
       5: checkcast     #116                // class java/util/Random
       8: astore_1
       9: aload_1
      10: invokestatic  #118                // Method org/mockito/ArgumentMatchers.anyInt:()I
      13: invokevirtual #119                // Method java/util/Random.nextInt:(I)I
      16: invokestatic  #120                // Method java/lang/Integer.valueOf:(I)Ljava/lang/Integer;
      19: invokestatic  #121                // Method org/mockito/Mockito.when:(Ljava/lang/Object;)Lorg/mockito/stubbing/OngoingStubbing;
      22: new           #122                // class org/apache/hadoop/hbase/TestHBaseTestingUtility$1
      25: dup
      26: aload_0
      27: invokespecial #123                // Method org/apache/hadoop/hbase/TestHBaseTestingUtility$1."<init>":(Lorg/apache/hadoop/hbase/TestHBaseTestingUtility;)V
      30: invokeinterface #124,  2          // InterfaceMethod org/mockito/stubbing/OngoingStubbing.thenAnswer:(Lorg/mockito/stubbing/Answer;)Lorg/mockito/stubbing/OngoingStubbing;
      35: pop
      36: ldc           #125                // class org/apache/hadoop/hbase/HBaseTestingUtility$PortAllocator$AvailablePortChecker
      38: invokestatic  #117                // Method org/mockito/Mockito.mock:(Ljava/lang/Class;)Ljava/lang/Object;
      41: checkcast     #125                // class org/apache/hadoop/hbase/HBaseTestingUtility$PortAllocator$AvailablePortChecker
      44: astore_2
      45: aload_2
      46: invokestatic  #118                // Method org/mockito/ArgumentMatchers.anyInt:()I
      49: invokeinterface #126,  2          // InterfaceMethod org/apache/hadoop/hbase/HBaseTestingUtility$PortAllocator$AvailablePortChecker.available:(I)Z
      54: invokestatic  #127                // Method java/lang/Boolean.valueOf:(Z)Ljava/lang/Boolean;
      57: invokestatic  #121                // Method org/mockito/Mockito.when:(Ljava/lang/Object;)Lorg/mockito/stubbing/OngoingStubbing;
      60: iconst_1
      61: invokestatic  #127                // Method java/lang/Boolean.valueOf:(Z)Ljava/lang/Boolean;
      64: invokeinterface #128,  2          // InterfaceMethod org/mockito/stubbing/OngoingStubbing.thenReturn:(Ljava/lang/Object;)Lorg/mockito/stubbing/OngoingStubbing;
      69: pop
      70: new           #129                // class org/apache/hadoop/hbase/HBaseTestingUtility$PortAllocator
      73: dup
      74: aload_1
      75: aload_2
      76: invokespecial #130                // Method org/apache/hadoop/hbase/HBaseTestingUtility$PortAllocator."<init>":(Ljava/util/Random;Lorg/apache/hadoop/hbase/HBaseTestingUtility$PortAllocator$AvailablePortChecker;)V
      79: astore_3
      80: aload_3
      81: invokevirtual #131                // Method org/apache/hadoop/hbase/HBaseTestingUtility$PortAllocator.randomFreePort:()I
      84: istore        4
      86: aload_3
      87: invokevirtual #131                // Method org/apache/hadoop/hbase/HBaseTestingUtility$PortAllocator.randomFreePort:()I
      90: istore        5
      92: iload         4
      94: i2l
      95: iload         5
      97: i2l
      98: invokestatic  #132                // Method org/junit/Assert.assertNotEquals:(JJ)V
     101: aload_1
     102: iconst_3
     103: invokestatic  #133                // Method org/mockito/Mockito.times:(I)Lorg/mockito/verification/VerificationMode;
     106: invokestatic  #134                // Method org/mockito/Mockito.verify:(Ljava/lang/Object;Lorg/mockito/verification/VerificationMode;)Ljava/lang/Object;
     109: checkcast     #116                // class java/util/Random
     112: invokestatic  #118                // Method org/mockito/ArgumentMatchers.anyInt:()I
     115: invokevirtual #119                // Method java/util/Random.nextInt:(I)I
     118: pop
     119: return

  public void testOverridingOfDefaultPorts() throws java.lang.Exception;
    Code:
       0: invokestatic  #135                // Method org/apache/hadoop/hbase/HBaseConfiguration.create:()Lorg/apache/hadoop/conf/Configuration;
       3: astore_1
       4: aload_1
       5: ldc           #136                // String hbase.master.info.port
       7: sipush        16010
      10: invokevirtual #97                 // Method org/apache/hadoop/conf/Configuration.setInt:(Ljava/lang/String;I)V
      13: aload_1
      14: ldc           #137                // String hbase.regionserver.info.port
      16: sipush        16030
      19: invokevirtual #97                 // Method org/apache/hadoop/conf/Configuration.setInt:(Ljava/lang/String;I)V
      22: new           #5                  // class org/apache/hadoop/hbase/HBaseTestingUtility
      25: dup
      26: aload_1
      27: invokespecial #138                // Method org/apache/hadoop/hbase/HBaseTestingUtility."<init>":(Lorg/apache/hadoop/conf/Configuration;)V
      30: astore_2
      31: aload_2
      32: invokevirtual #20                 // Method org/apache/hadoop/hbase/HBaseTestingUtility.startMiniCluster:()Lorg/apache/hadoop/hbase/MiniHBaseCluster;
      35: astore_3
      36: ldc2_w        #139                // long 16010l
      39: aload_3
      40: invokevirtual #141                // Method org/apache/hadoop/hbase/MiniHBaseCluster.getConfiguration:()Lorg/apache/hadoop/conf/Configuration;
      43: ldc           #136                // String hbase.master.info.port
      45: iconst_0
      46: invokevirtual #142                // Method org/apache/hadoop/conf/Configuration.getInt:(Ljava/lang/String;I)I
      49: i2l
      50: invokestatic  #132                // Method org/junit/Assert.assertNotEquals:(JJ)V
      53: ldc2_w        #143                // long 16030l
      56: aload_3
      57: invokevirtual #141                // Method org/apache/hadoop/hbase/MiniHBaseCluster.getConfiguration:()Lorg/apache/hadoop/conf/Configuration;
      60: ldc           #137                // String hbase.regionserver.info.port
      62: iconst_0
      63: invokevirtual #142                // Method org/apache/hadoop/conf/Configuration.getInt:(Ljava/lang/String;I)I
      66: i2l
      67: invokestatic  #132                // Method org/junit/Assert.assertNotEquals:(JJ)V
      70: aload_2
      71: invokevirtual #40                 // Method org/apache/hadoop/hbase/HBaseTestingUtility.shutdownMiniCluster:()V
      74: goto          86
      77: astore        4
      79: aload_2
      80: invokevirtual #40                 // Method org/apache/hadoop/hbase/HBaseTestingUtility.shutdownMiniCluster:()V
      83: aload         4
      85: athrow
      86: invokestatic  #135                // Method org/apache/hadoop/hbase/HBaseConfiguration.create:()Lorg/apache/hadoop/conf/Configuration;
      89: astore_3
      90: sipush        3333
      93: istore        4
      95: sipush        4444
      98: istore        5
     100: aload_3
     101: ldc           #136                // String hbase.master.info.port
     103: sipush        3333
     106: invokevirtual #97                 // Method org/apache/hadoop/conf/Configuration.setInt:(Ljava/lang/String;I)V
     109: aload_3
     110: ldc           #137                // String hbase.regionserver.info.port
     112: sipush        4444
     115: invokevirtual #97                 // Method org/apache/hadoop/conf/Configuration.setInt:(Ljava/lang/String;I)V
     118: new           #5                  // class org/apache/hadoop/hbase/HBaseTestingUtility
     121: dup
     122: aload_3
     123: invokespecial #138                // Method org/apache/hadoop/hbase/HBaseTestingUtility."<init>":(Lorg/apache/hadoop/conf/Configuration;)V
     126: astore_2
     127: aload_2
     128: invokevirtual #20                 // Method org/apache/hadoop/hbase/HBaseTestingUtility.startMiniCluster:()Lorg/apache/hadoop/hbase/MiniHBaseCluster;
     131: astore        6
     133: ldc2_w        #145                // long 3333l
     136: aload         6
     138: invokevirtual #141                // Method org/apache/hadoop/hbase/MiniHBaseCluster.getConfiguration:()Lorg/apache/hadoop/conf/Configuration;
     141: ldc           #136                // String hbase.master.info.port
     143: iconst_0
     144: invokevirtual #142                // Method org/apache/hadoop/conf/Configuration.getInt:(Ljava/lang/String;I)I
     147: i2l
     148: invokestatic  #38                 // Method org/junit/Assert.assertEquals:(JJ)V
     151: ldc2_w        #147                // long 4444l
     154: aload         6
     156: invokevirtual #141                // Method org/apache/hadoop/hbase/MiniHBaseCluster.getConfiguration:()Lorg/apache/hadoop/conf/Configuration;
     159: ldc           #137                // String hbase.regionserver.info.port
     161: iconst_0
     162: invokevirtual #142                // Method org/apache/hadoop/conf/Configuration.getInt:(Ljava/lang/String;I)I
     165: i2l
     166: invokestatic  #38                 // Method org/junit/Assert.assertEquals:(JJ)V
     169: aload_2
     170: invokevirtual #40                 // Method org/apache/hadoop/hbase/HBaseTestingUtility.shutdownMiniCluster:()V
     173: goto          185
     176: astore        7
     178: aload_2
     179: invokevirtual #40                 // Method org/apache/hadoop/hbase/HBaseTestingUtility.shutdownMiniCluster:()V
     182: aload         7
     184: athrow
     185: return
    Exception table:
       from    to  target type
          31    70    77   any
          77    79    77   any
         127   169   176   any
         176   178   176   any

  public void testKillMiniHBaseCluster() throws java.lang.Exception;
    Code:
       0: new           #5                  // class org/apache/hadoop/hbase/HBaseTestingUtility
       3: dup
       4: invokespecial #6                  // Method org/apache/hadoop/hbase/HBaseTestingUtility."<init>":()V
       7: astore_1
       8: aload_1
       9: invokevirtual #12                 // Method org/apache/hadoop/hbase/HBaseTestingUtility.startMiniZKCluster:()Lorg/apache/hadoop/hbase/zookeeper/MiniZooKeeperCluster;
      12: pop
      13: aload_1
      14: invokevirtual #149                // Method org/apache/hadoop/hbase/HBaseTestingUtility.startMiniHBaseCluster:()Lorg/apache/hadoop/hbase/MiniHBaseCluster;
      17: pop
      18: iconst_0
      19: istore        4
      21: iload         4
      23: iconst_1
      24: if_icmpge     205
      27: new           #45                 // class java/lang/StringBuilder
      30: dup
      31: invokespecial #46                 // Method java/lang/StringBuilder."<init>":()V
      34: aload_0
      35: getfield      #4                  // Field name:Lorg/junit/rules/TestName;
      38: invokevirtual #21                 // Method org/junit/rules/TestName.getMethodName:()Ljava/lang/String;
      41: invokevirtual #50                 // Method java/lang/StringBuilder.append:(Ljava/lang/String;)Ljava/lang/StringBuilder;
      44: iload         4
      46: invokevirtual #150                // Method java/lang/StringBuilder.append:(I)Ljava/lang/StringBuilder;
      49: invokevirtual #54                 // Method java/lang/StringBuilder.toString:()Ljava/lang/String;
      52: invokestatic  #22                 // Method org/apache/hadoop/hbase/TableName.valueOf:(Ljava/lang/String;)Lorg/apache/hadoop/hbase/TableName;
      55: astore_2
      56: new           #45                 // class java/lang/StringBuilder
      59: dup
      60: invokespecial #46                 // Method java/lang/StringBuilder."<init>":()V
      63: ldc           #23                 // String fam
      65: invokevirtual #50                 // Method java/lang/StringBuilder.append:(Ljava/lang/String;)Ljava/lang/StringBuilder;
      68: iload         4
      70: invokevirtual #150                // Method java/lang/StringBuilder.append:(I)Ljava/lang/StringBuilder;
      73: invokevirtual #54                 // Method java/lang/StringBuilder.toString:()Ljava/lang/String;
      76: invokestatic  #24                 // Method org/apache/hadoop/hbase/util/Bytes.toBytes:(Ljava/lang/String;)[B
      79: astore_3
      80: aload_1
      81: aload_2
      82: aload_3
      83: bipush        10
      85: invokevirtual #151                // Method org/apache/hadoop/hbase/HBaseTestingUtility.createMultiRegionTable:(Lorg/apache/hadoop/hbase/TableName;[BI)Lorg/apache/hadoop/hbase/client/Table;
      88: astore        5
      90: aconst_null
      91: astore        6
      93: aload_1
      94: aload         5
      96: aload_3
      97: bipush        100
      99: bipush        100
     101: invokevirtual #152                // Method org/apache/hadoop/hbase/HBaseTestingUtility.loadRandomRows:(Lorg/apache/hadoop/hbase/client/Table;[BII)V
     104: aload         5
     106: ifnull        199
     109: aload         6
     111: ifnull        136
     114: aload         5
     116: invokeinterface #39,  1           // InterfaceMethod org/apache/hadoop/hbase/client/Table.close:()V
     121: goto          199
     124: astore        7
     126: aload         6
     128: aload         7
     130: invokevirtual #154                // Method java/lang/Throwable.addSuppressed:(Ljava/lang/Throwable;)V
     133: goto          199
     136: aload         5
     138: invokeinterface #39,  1           // InterfaceMethod org/apache/hadoop/hbase/client/Table.close:()V
     143: goto          199
     146: astore        7
     148: aload         7
     150: astore        6
     152: aload         7
     154: athrow
     155: astore        8
     157: aload         5
     159: ifnull        196
     162: aload         6
     164: ifnull        189
     167: aload         5
     169: invokeinterface #39,  1           // InterfaceMethod org/apache/hadoop/hbase/client/Table.close:()V
     174: goto          196
     177: astore        9
     179: aload         6
     181: aload         9
     183: invokevirtual #154                // Method java/lang/Throwable.addSuppressed:(Ljava/lang/Throwable;)V
     186: goto          196
     189: aload         5
     191: invokeinterface #39,  1           // InterfaceMethod org/apache/hadoop/hbase/client/Table.close:()V
     196: aload         8
     198: athrow
     199: iinc          4, 1
     202: goto          21
     205: aload_1
     206: invokevirtual #155                // Method org/apache/hadoop/hbase/HBaseTestingUtility.killMiniHBaseCluster:()V
     209: aload_1
     210: invokevirtual #78                 // Method org/apache/hadoop/hbase/HBaseTestingUtility.shutdownMiniZKCluster:()V
     213: goto          229
     216: astore        10
     218: aload_1
     219: invokevirtual #155                // Method org/apache/hadoop/hbase/HBaseTestingUtility.killMiniHBaseCluster:()V
     222: aload_1
     223: invokevirtual #78                 // Method org/apache/hadoop/hbase/HBaseTestingUtility.shutdownMiniZKCluster:()V
     226: aload         10
     228: athrow
     229: return
    Exception table:
       from    to  target type
         114   121   124   Class java/lang/Throwable
          93   104   146   Class java/lang/Throwable
          93   104   155   any
         167   174   177   Class java/lang/Throwable
         146   157   155   any
          13   205   216   any
         216   218   216   any

  static {};
    Code:
       0: ldc           #52                 // class org/apache/hadoop/hbase/TestHBaseTestingUtility
       2: invokestatic  #156                // Method org/apache/hadoop/hbase/HBaseClassTestRule.forClass:(Ljava/lang/Class;)Lorg/apache/hadoop/hbase/HBaseClassTestRule;
       5: putstatic     #157                // Field CLASS_RULE:Lorg/apache/hadoop/hbase/HBaseClassTestRule;
       8: ldc           #52                 // class org/apache/hadoop/hbase/TestHBaseTestingUtility
      10: invokestatic  #158                // Method org/slf4j/LoggerFactory.getLogger:(Ljava/lang/Class;)Lorg/slf4j/Logger;
      13: putstatic     #102                // Field LOG:Lorg/slf4j/Logger;
      16: return
}
