Compiled from "TestMasterProcedureScheduler.java"
public class org.apache.hadoop.hbase.master.procedure.TestMasterProcedureScheduler$TestRegionProcedure extends org.apache.hadoop.hbase.master.procedure.TestMasterProcedureScheduler$TestTableProcedure {
  public org.apache.hadoop.hbase.master.procedure.TestMasterProcedureScheduler$TestRegionProcedure();
    Code:
       0: aload_0
       1: invokespecial #1                  // Method org/apache/hadoop/hbase/master/procedure/TestMasterProcedureScheduler$TestTableProcedure."<init>":()V
       4: new           #2                  // class java/lang/UnsupportedOperationException
       7: dup
       8: ldc           #3                  // String recovery should not be triggered here
      10: invokespecial #4                  // Method java/lang/UnsupportedOperationException."<init>":(Ljava/lang/String;)V
      13: athrow

  public org.apache.hadoop.hbase.master.procedure.TestMasterProcedureScheduler$TestRegionProcedure(long, org.apache.hadoop.hbase.TableName, org.apache.hadoop.hbase.master.procedure.TableProcedureInterface$TableOperationType, org.apache.hadoop.hbase.client.RegionInfo...);
    Code:
       0: aload_0
       1: ldc2_w        #5                  // long -1l
       4: lload_1
       5: aload_3
       6: aload         4
       8: aload         5
      10: invokespecial #7                  // Method "<init>":(JJLorg/apache/hadoop/hbase/TableName;Lorg/apache/hadoop/hbase/master/procedure/TableProcedureInterface$TableOperationType;[Lorg/apache/hadoop/hbase/client/RegionInfo;)V
      13: return

  public org.apache.hadoop.hbase.master.procedure.TestMasterProcedureScheduler$TestRegionProcedure(long, long, org.apache.hadoop.hbase.TableName, org.apache.hadoop.hbase.master.procedure.TableProcedureInterface$TableOperationType, org.apache.hadoop.hbase.client.RegionInfo...);
    Code:
       0: aload_0
       1: ldc2_w        #5                  // long -1l
       4: lload_1
       5: lload_3
       6: aload         5
       8: aload         6
      10: aload         7
      12: invokespecial #8                  // Method "<init>":(JJJLorg/apache/hadoop/hbase/TableName;Lorg/apache/hadoop/hbase/master/procedure/TableProcedureInterface$TableOperationType;[Lorg/apache/hadoop/hbase/client/RegionInfo;)V
      15: return

  public org.apache.hadoop.hbase.master.procedure.TestMasterProcedureScheduler$TestRegionProcedure(long, long, long, org.apache.hadoop.hbase.TableName, org.apache.hadoop.hbase.master.procedure.TableProcedureInterface$TableOperationType, org.apache.hadoop.hbase.client.RegionInfo...);
    Code:
       0: aload_0
       1: lload_1
       2: lload_3
       3: lload         5
       5: aload         7
       7: aload         8
       9: invokespecial #9                  // Method org/apache/hadoop/hbase/master/procedure/TestMasterProcedureScheduler$TestTableProcedure."<init>":(JJJLorg/apache/hadoop/hbase/TableName;Lorg/apache/hadoop/hbase/master/procedure/TableProcedureInterface$TableOperationType;)V
      12: aload_0
      13: aload         9
      15: putfield      #10                 // Field regionInfo:[Lorg/apache/hadoop/hbase/client/RegionInfo;
      18: return

  public org.apache.hadoop.hbase.client.RegionInfo[] getRegionInfo();
    Code:
       0: aload_0
       1: getfield      #10                 // Field regionInfo:[Lorg/apache/hadoop/hbase/client/RegionInfo;
       4: areturn

  public void toStringClassDetails(java.lang.StringBuilder);
    Code:
       0: aload_1
       1: aload_0
       2: invokevirtual #11                 // Method java/lang/Object.getClass:()Ljava/lang/Class;
       5: invokevirtual #12                 // Method java/lang/Class.getSimpleName:()Ljava/lang/String;
       8: invokevirtual #13                 // Method java/lang/StringBuilder.append:(Ljava/lang/String;)Ljava/lang/StringBuilder;
      11: pop
      12: aload_1
      13: ldc           #14                 // String (regions=
      15: invokevirtual #13                 // Method java/lang/StringBuilder.append:(Ljava/lang/String;)Ljava/lang/StringBuilder;
      18: pop
      19: aload_1
      20: aload_0
      21: invokevirtual #15                 // Method getRegionInfo:()[Lorg/apache/hadoop/hbase/client/RegionInfo;
      24: invokestatic  #16                 // Method java/util/Arrays.toString:([Ljava/lang/Object;)Ljava/lang/String;
      27: invokevirtual #13                 // Method java/lang/StringBuilder.append:(Ljava/lang/String;)Ljava/lang/StringBuilder;
      30: pop
      31: aload_1
      32: ldc           #17                 // String )
      34: invokevirtual #13                 // Method java/lang/StringBuilder.append:(Ljava/lang/String;)Ljava/lang/StringBuilder;
      37: pop
      38: return
}
