Compiled from "TestRegionSizeReportingChore.java"
public class org.apache.hadoop.hbase.quotas.TestRegionSizeReportingChore {
  public static final org.apache.hadoop.hbase.HBaseClassTestRule CLASS_RULE;

  public org.apache.hadoop.hbase.quotas.TestRegionSizeReportingChore();
    Code:
       0: aload_0
       1: invokespecial #1                  // Method java/lang/Object."<init>":()V
       4: return

  public void testDefaultConfigurationProperties();
    Code:
       0: aload_0
       1: invokespecial #2                  // Method getDefaultHBaseConfiguration:()Lorg/apache/hadoop/conf/Configuration;
       4: astore_1
       5: aload_0
       6: aload_1
       7: invokespecial #3                  // Method mockRegionServer:(Lorg/apache/hadoop/conf/Configuration;)Lorg/apache/hadoop/hbase/regionserver/HRegionServer;
      10: astore_2
      11: new           #4                  // class org/apache/hadoop/hbase/quotas/RegionSizeReportingChore
      14: dup
      15: aload_2
      16: invokespecial #5                  // Method org/apache/hadoop/hbase/quotas/RegionSizeReportingChore."<init>":(Lorg/apache/hadoop/hbase/regionserver/RegionServerServices;)V
      19: astore_3
      20: ldc2_w        #6                  // long 30000l
      23: aload_3
      24: invokevirtual #8                  // Method org/apache/hadoop/hbase/quotas/RegionSizeReportingChore.getInitialDelay:()J
      27: invokestatic  #9                  // Method org/junit/Assert.assertEquals:(JJ)V
      30: ldc2_w        #10                 // long 60000l
      33: aload_3
      34: invokevirtual #12                 // Method org/apache/hadoop/hbase/quotas/RegionSizeReportingChore.getPeriod:()I
      37: i2l
      38: invokestatic  #9                  // Method org/junit/Assert.assertEquals:(JJ)V
      41: getstatic     #13                 // Field org/apache/hadoop/hbase/quotas/RegionSizeReportingChore.REGION_SIZE_REPORTING_CHORE_TIMEUNIT_DEFAULT:Ljava/lang/String;
      44: invokestatic  #14                 // Method java/util/concurrent/TimeUnit.valueOf:(Ljava/lang/String;)Ljava/util/concurrent/TimeUnit;
      47: aload_3
      48: invokevirtual #15                 // Method org/apache/hadoop/hbase/quotas/RegionSizeReportingChore.getTimeUnit:()Ljava/util/concurrent/TimeUnit;
      51: invokestatic  #16                 // Method org/junit/Assert.assertEquals:(Ljava/lang/Object;Ljava/lang/Object;)V
      54: return

  public void testNonDefaultConfigurationProperties();
    Code:
       0: aload_0
       1: invokespecial #2                  // Method getDefaultHBaseConfiguration:()Lorg/apache/hadoop/conf/Configuration;
       4: astore_1
       5: aload_0
       6: aload_1
       7: invokespecial #3                  // Method mockRegionServer:(Lorg/apache/hadoop/conf/Configuration;)Lorg/apache/hadoop/hbase/regionserver/HRegionServer;
      10: astore_2
      11: ldc           #17                 // int 60001
      13: istore_3
      14: ldc2_w        #18                 // long 30001l
      17: lstore        4
      19: getstatic     #20                 // Field java/util/concurrent/TimeUnit.SECONDS:Ljava/util/concurrent/TimeUnit;
      22: invokevirtual #21                 // Method java/util/concurrent/TimeUnit.name:()Ljava/lang/String;
      25: astore        6
      27: aload_1
      28: ldc           #22                 // String hbase.regionserver.quotas.region.size.reporting.chore.period
      30: ldc           #17                 // int 60001
      32: invokevirtual #23                 // Method org/apache/hadoop/conf/Configuration.setInt:(Ljava/lang/String;I)V
      35: aload_1
      36: ldc           #24                 // String hbase.regionserver.quotas.region.size.reporting.chore.delay
      38: ldc2_w        #18                 // long 30001l
      41: invokevirtual #25                 // Method org/apache/hadoop/conf/Configuration.setLong:(Ljava/lang/String;J)V
      44: aload_1
      45: ldc           #26                 // String hbase.regionserver.quotas.region.size.reporting.chore.timeunit
      47: aload         6
      49: invokevirtual #27                 // Method org/apache/hadoop/conf/Configuration.set:(Ljava/lang/String;Ljava/lang/String;)V
      52: new           #4                  // class org/apache/hadoop/hbase/quotas/RegionSizeReportingChore
      55: dup
      56: aload_2
      57: invokespecial #5                  // Method org/apache/hadoop/hbase/quotas/RegionSizeReportingChore."<init>":(Lorg/apache/hadoop/hbase/regionserver/RegionServerServices;)V
      60: astore        7
      62: ldc2_w        #18                 // long 30001l
      65: aload         7
      67: invokevirtual #8                  // Method org/apache/hadoop/hbase/quotas/RegionSizeReportingChore.getInitialDelay:()J
      70: invokestatic  #9                  // Method org/junit/Assert.assertEquals:(JJ)V
      73: ldc2_w        #28                 // long 60001l
      76: aload         7
      78: invokevirtual #12                 // Method org/apache/hadoop/hbase/quotas/RegionSizeReportingChore.getPeriod:()I
      81: i2l
      82: invokestatic  #9                  // Method org/junit/Assert.assertEquals:(JJ)V
      85: aload         6
      87: invokestatic  #14                 // Method java/util/concurrent/TimeUnit.valueOf:(Ljava/lang/String;)Ljava/util/concurrent/TimeUnit;
      90: aload         7
      92: invokevirtual #15                 // Method org/apache/hadoop/hbase/quotas/RegionSizeReportingChore.getTimeUnit:()Ljava/util/concurrent/TimeUnit;
      95: invokestatic  #16                 // Method org/junit/Assert.assertEquals:(Ljava/lang/Object;Ljava/lang/Object;)V
      98: return

  public void testRemovableOfNonOnlineRegions();
    Code:
       0: aload_0
       1: invokespecial #2                  // Method getDefaultHBaseConfiguration:()Lorg/apache/hadoop/conf/Configuration;
       4: astore_1
       5: aload_0
       6: aload_1
       7: invokespecial #3                  // Method mockRegionServer:(Lorg/apache/hadoop/conf/Configuration;)Lorg/apache/hadoop/hbase/regionserver/HRegionServer;
      10: astore_2
      11: new           #4                  // class org/apache/hadoop/hbase/quotas/RegionSizeReportingChore
      14: dup
      15: aload_2
      16: invokespecial #5                  // Method org/apache/hadoop/hbase/quotas/RegionSizeReportingChore."<init>":(Lorg/apache/hadoop/hbase/regionserver/RegionServerServices;)V
      19: astore_3
      20: ldc           #30                 // String T1
      22: invokestatic  #31                 // Method org/apache/hadoop/hbase/TableName.valueOf:(Ljava/lang/String;)Lorg/apache/hadoop/hbase/TableName;
      25: invokestatic  #32                 // Method org/apache/hadoop/hbase/client/RegionInfoBuilder.newBuilder:(Lorg/apache/hadoop/hbase/TableName;)Lorg/apache/hadoop/hbase/client/RegionInfoBuilder;
      28: ldc           #33                 // String a
      30: invokestatic  #34                 // Method org/apache/hadoop/hbase/util/Bytes.toBytes:(Ljava/lang/String;)[B
      33: invokevirtual #35                 // Method org/apache/hadoop/hbase/client/RegionInfoBuilder.setStartKey:([B)Lorg/apache/hadoop/hbase/client/RegionInfoBuilder;
      36: ldc           #36                 // String b
      38: invokestatic  #34                 // Method org/apache/hadoop/hbase/util/Bytes.toBytes:(Ljava/lang/String;)[B
      41: invokevirtual #37                 // Method org/apache/hadoop/hbase/client/RegionInfoBuilder.setEndKey:([B)Lorg/apache/hadoop/hbase/client/RegionInfoBuilder;
      44: invokevirtual #38                 // Method org/apache/hadoop/hbase/client/RegionInfoBuilder.build:()Lorg/apache/hadoop/hbase/client/RegionInfo;
      47: astore        4
      49: ldc           #30                 // String T1
      51: invokestatic  #31                 // Method org/apache/hadoop/hbase/TableName.valueOf:(Ljava/lang/String;)Lorg/apache/hadoop/hbase/TableName;
      54: invokestatic  #32                 // Method org/apache/hadoop/hbase/client/RegionInfoBuilder.newBuilder:(Lorg/apache/hadoop/hbase/TableName;)Lorg/apache/hadoop/hbase/client/RegionInfoBuilder;
      57: ldc           #36                 // String b
      59: invokestatic  #34                 // Method org/apache/hadoop/hbase/util/Bytes.toBytes:(Ljava/lang/String;)[B
      62: invokevirtual #35                 // Method org/apache/hadoop/hbase/client/RegionInfoBuilder.setStartKey:([B)Lorg/apache/hadoop/hbase/client/RegionInfoBuilder;
      65: ldc           #39                 // String d
      67: invokestatic  #34                 // Method org/apache/hadoop/hbase/util/Bytes.toBytes:(Ljava/lang/String;)[B
      70: invokevirtual #37                 // Method org/apache/hadoop/hbase/client/RegionInfoBuilder.setEndKey:([B)Lorg/apache/hadoop/hbase/client/RegionInfoBuilder;
      73: invokevirtual #38                 // Method org/apache/hadoop/hbase/client/RegionInfoBuilder.build:()Lorg/apache/hadoop/hbase/client/RegionInfo;
      76: astore        5
      78: ldc           #30                 // String T1
      80: invokestatic  #31                 // Method org/apache/hadoop/hbase/TableName.valueOf:(Ljava/lang/String;)Lorg/apache/hadoop/hbase/TableName;
      83: invokestatic  #32                 // Method org/apache/hadoop/hbase/client/RegionInfoBuilder.newBuilder:(Lorg/apache/hadoop/hbase/TableName;)Lorg/apache/hadoop/hbase/client/RegionInfoBuilder;
      86: ldc           #40                 // String c
      88: invokestatic  #34                 // Method org/apache/hadoop/hbase/util/Bytes.toBytes:(Ljava/lang/String;)[B
      91: invokevirtual #35                 // Method org/apache/hadoop/hbase/client/RegionInfoBuilder.setStartKey:([B)Lorg/apache/hadoop/hbase/client/RegionInfoBuilder;
      94: ldc           #39                 // String d
      96: invokestatic  #34                 // Method org/apache/hadoop/hbase/util/Bytes.toBytes:(Ljava/lang/String;)[B
      99: invokevirtual #37                 // Method org/apache/hadoop/hbase/client/RegionInfoBuilder.setEndKey:([B)Lorg/apache/hadoop/hbase/client/RegionInfoBuilder;
     102: invokevirtual #38                 // Method org/apache/hadoop/hbase/client/RegionInfoBuilder.build:()Lorg/apache/hadoop/hbase/client/RegionInfo;
     105: astore        6
     107: new           #41                 // class org/apache/hadoop/hbase/quotas/RegionSizeStoreImpl
     110: dup
     111: invokespecial #42                 // Method org/apache/hadoop/hbase/quotas/RegionSizeStoreImpl."<init>":()V
     114: astore        7
     116: aload         7
     118: aload         4
     120: ldc2_w        #43                 // long 1024l
     123: invokeinterface #45,  4           // InterfaceMethod org/apache/hadoop/hbase/quotas/RegionSizeStore.put:(Lorg/apache/hadoop/hbase/client/RegionInfo;J)V
     128: aload         7
     130: aload         5
     132: ldc2_w        #43                 // long 1024l
     135: invokeinterface #45,  4           // InterfaceMethod org/apache/hadoop/hbase/quotas/RegionSizeStore.put:(Lorg/apache/hadoop/hbase/client/RegionInfo;J)V
     140: aload         7
     142: aload         6
     144: ldc2_w        #43                 // long 1024l
     147: invokeinterface #45,  4           // InterfaceMethod org/apache/hadoop/hbase/quotas/RegionSizeStore.put:(Lorg/apache/hadoop/hbase/client/RegionInfo;J)V
     152: aload_3
     153: aload         7
     155: invokestatic  #46                 // Method java/util/Collections.emptySet:()Ljava/util/Set;
     158: invokevirtual #47                 // Method org/apache/hadoop/hbase/quotas/RegionSizeReportingChore.removeNonOnlineRegions:(Lorg/apache/hadoop/hbase/quotas/RegionSizeStore;Ljava/util/Set;)V
     161: aload         7
     163: invokeinterface #48,  1           // InterfaceMethod org/apache/hadoop/hbase/quotas/RegionSizeStore.isEmpty:()Z
     168: invokestatic  #49                 // Method org/junit/Assert.assertTrue:(Z)V
     171: aload         7
     173: aload         4
     175: ldc2_w        #43                 // long 1024l
     178: invokeinterface #45,  4           // InterfaceMethod org/apache/hadoop/hbase/quotas/RegionSizeStore.put:(Lorg/apache/hadoop/hbase/client/RegionInfo;J)V
     183: aload         7
     185: aload         5
     187: ldc2_w        #43                 // long 1024l
     190: invokeinterface #45,  4           // InterfaceMethod org/apache/hadoop/hbase/quotas/RegionSizeStore.put:(Lorg/apache/hadoop/hbase/client/RegionInfo;J)V
     195: aload         7
     197: aload         6
     199: ldc2_w        #43                 // long 1024l
     202: invokeinterface #45,  4           // InterfaceMethod org/apache/hadoop/hbase/quotas/RegionSizeStore.put:(Lorg/apache/hadoop/hbase/client/RegionInfo;J)V
     207: aload_3
     208: aload         7
     210: new           #50                 // class java/util/HashSet
     213: dup
     214: iconst_2
     215: anewarray     #51                 // class org/apache/hadoop/hbase/client/RegionInfo
     218: dup
     219: iconst_0
     220: aload         4
     222: aastore
     223: dup
     224: iconst_1
     225: aload         6
     227: aastore
     228: invokestatic  #52                 // Method java/util/Arrays.asList:([Ljava/lang/Object;)Ljava/util/List;
     231: invokespecial #53                 // Method java/util/HashSet."<init>":(Ljava/util/Collection;)V
     234: invokevirtual #47                 // Method org/apache/hadoop/hbase/quotas/RegionSizeReportingChore.removeNonOnlineRegions:(Lorg/apache/hadoop/hbase/quotas/RegionSizeStore;Ljava/util/Set;)V
     237: ldc2_w        #54                 // long 2l
     240: aload         7
     242: invokeinterface #56,  1           // InterfaceMethod org/apache/hadoop/hbase/quotas/RegionSizeStore.size:()I
     247: i2l
     248: invokestatic  #9                  // Method org/junit/Assert.assertEquals:(JJ)V
     251: aload         7
     253: aload         4
     255: invokeinterface #57,  2           // InterfaceMethod org/apache/hadoop/hbase/quotas/RegionSizeStore.getRegionSize:(Lorg/apache/hadoop/hbase/client/RegionInfo;)Lorg/apache/hadoop/hbase/quotas/RegionSize;
     260: invokestatic  #58                 // Method org/junit/Assert.assertNotNull:(Ljava/lang/Object;)V
     263: aload         7
     265: aload         6
     267: invokeinterface #57,  2           // InterfaceMethod org/apache/hadoop/hbase/quotas/RegionSizeStore.getRegionSize:(Lorg/apache/hadoop/hbase/client/RegionInfo;)Lorg/apache/hadoop/hbase/quotas/RegionSize;
     272: invokestatic  #58                 // Method org/junit/Assert.assertNotNull:(Ljava/lang/Object;)V
     275: return

  static {};
    Code:
       0: ldc           #67                 // class org/apache/hadoop/hbase/quotas/TestRegionSizeReportingChore
       2: invokestatic  #68                 // Method org/apache/hadoop/hbase/HBaseClassTestRule.forClass:(Ljava/lang/Class;)Lorg/apache/hadoop/hbase/HBaseClassTestRule;
       5: putstatic     #69                 // Field CLASS_RULE:Lorg/apache/hadoop/hbase/HBaseClassTestRule;
       8: return
}
