Compiled from "TestReplicaWithCluster.java"
public class org.apache.hadoop.hbase.client.TestReplicaWithCluster {
  public static final org.apache.hadoop.hbase.HBaseClassTestRule CLASS_RULE;

  public org.apache.hadoop.hbase.client.TestReplicaWithCluster();
    Code:
       0: aload_0
       1: invokespecial #4                  // Method java/lang/Object."<init>":()V
       4: return

  public static void beforeClass() throws java.lang.Exception;
    Code:
       0: getstatic     #1                  // Field HTU:Lorg/apache/hadoop/hbase/HBaseTestingUtility;
       3: invokevirtual #5                  // Method org/apache/hadoop/hbase/HBaseTestingUtility.getConfiguration:()Lorg/apache/hadoop/conf/Configuration;
       6: ldc           #7                  // String hbase.regionserver.storefile.refresh.period
       8: sipush        1000
      11: invokevirtual #9                  // Method org/apache/hadoop/conf/Configuration.setInt:(Ljava/lang/String;I)V
      14: getstatic     #1                  // Field HTU:Lorg/apache/hadoop/hbase/HBaseTestingUtility;
      17: invokevirtual #5                  // Method org/apache/hadoop/hbase/HBaseTestingUtility.getConfiguration:()Lorg/apache/hadoop/conf/Configuration;
      20: ldc           #10                 // String hbase.regionserver.logroll.multiplier
      22: ldc           #11                 // float 1.0E-4f
      24: invokevirtual #12                 // Method org/apache/hadoop/conf/Configuration.setFloat:(Ljava/lang/String;F)V
      27: getstatic     #1                  // Field HTU:Lorg/apache/hadoop/hbase/HBaseTestingUtility;
      30: invokevirtual #5                  // Method org/apache/hadoop/hbase/HBaseTestingUtility.getConfiguration:()Lorg/apache/hadoop/conf/Configuration;
      33: ldc           #13                 // String replication.source.size.capacity
      35: sipush        10240
      38: invokevirtual #9                  // Method org/apache/hadoop/conf/Configuration.setInt:(Ljava/lang/String;I)V
      41: getstatic     #1                  // Field HTU:Lorg/apache/hadoop/hbase/HBaseTestingUtility;
      44: invokevirtual #5                  // Method org/apache/hadoop/hbase/HBaseTestingUtility.getConfiguration:()Lorg/apache/hadoop/conf/Configuration;
      47: ldc           #14                 // String replication.source.sleepforretries
      49: ldc2_w        #15                 // long 100l
      52: invokevirtual #17                 // Method org/apache/hadoop/conf/Configuration.setLong:(Ljava/lang/String;J)V
      55: getstatic     #1                  // Field HTU:Lorg/apache/hadoop/hbase/HBaseTestingUtility;
      58: invokevirtual #5                  // Method org/apache/hadoop/hbase/HBaseTestingUtility.getConfiguration:()Lorg/apache/hadoop/conf/Configuration;
      61: ldc           #18                 // String hbase.regionserver.maxlogs
      63: iconst_2
      64: invokevirtual #9                  // Method org/apache/hadoop/conf/Configuration.setInt:(Ljava/lang/String;I)V
      67: getstatic     #1                  // Field HTU:Lorg/apache/hadoop/hbase/HBaseTestingUtility;
      70: invokevirtual #5                  // Method org/apache/hadoop/hbase/HBaseTestingUtility.getConfiguration:()Lorg/apache/hadoop/conf/Configuration;
      73: ldc           #19                 // String hbase.master.logcleaner.ttl
      75: ldc2_w        #20                 // long 10l
      78: invokevirtual #17                 // Method org/apache/hadoop/conf/Configuration.setLong:(Ljava/lang/String;J)V
      81: getstatic     #1                  // Field HTU:Lorg/apache/hadoop/hbase/HBaseTestingUtility;
      84: invokevirtual #5                  // Method org/apache/hadoop/hbase/HBaseTestingUtility.getConfiguration:()Lorg/apache/hadoop/conf/Configuration;
      87: ldc           #22                 // String zookeeper.recovery.retry
      89: iconst_1
      90: invokevirtual #9                  // Method org/apache/hadoop/conf/Configuration.setInt:(Ljava/lang/String;I)V
      93: getstatic     #1                  // Field HTU:Lorg/apache/hadoop/hbase/HBaseTestingUtility;
      96: invokevirtual #5                  // Method org/apache/hadoop/hbase/HBaseTestingUtility.getConfiguration:()Lorg/apache/hadoop/conf/Configuration;
      99: ldc           #23                 // String zookeeper.recovery.retry.intervalmill
     101: bipush        10
     103: invokevirtual #9                  // Method org/apache/hadoop/conf/Configuration.setInt:(Ljava/lang/String;I)V
     106: getstatic     #1                  // Field HTU:Lorg/apache/hadoop/hbase/HBaseTestingUtility;
     109: invokevirtual #5                  // Method org/apache/hadoop/hbase/HBaseTestingUtility.getConfiguration:()Lorg/apache/hadoop/conf/Configuration;
     112: ldc           #24                 // String hbase.client.primaryCallTimeout.get
     114: ldc           #25                 // int 1000000
     116: invokevirtual #9                  // Method org/apache/hadoop/conf/Configuration.setInt:(Ljava/lang/String;I)V
     119: getstatic     #1                  // Field HTU:Lorg/apache/hadoop/hbase/HBaseTestingUtility;
     122: invokevirtual #5                  // Method org/apache/hadoop/hbase/HBaseTestingUtility.getConfiguration:()Lorg/apache/hadoop/conf/Configuration;
     125: ldc           #26                 // String hbase.client.primaryCallTimeout.scan
     127: ldc           #25                 // int 1000000
     129: invokevirtual #9                  // Method org/apache/hadoop/conf/Configuration.setInt:(Ljava/lang/String;I)V
     132: getstatic     #1                  // Field HTU:Lorg/apache/hadoop/hbase/HBaseTestingUtility;
     135: invokevirtual #5                  // Method org/apache/hadoop/hbase/HBaseTestingUtility.getConfiguration:()Lorg/apache/hadoop/conf/Configuration;
     138: ldc           #27                 // String hbase.client.retries.number
     140: iconst_1
     141: invokevirtual #9                  // Method org/apache/hadoop/conf/Configuration.setInt:(Ljava/lang/String;I)V
     144: getstatic     #1                  // Field HTU:Lorg/apache/hadoop/hbase/HBaseTestingUtility;
     147: invokevirtual #5                  // Method org/apache/hadoop/hbase/HBaseTestingUtility.getConfiguration:()Lorg/apache/hadoop/conf/Configuration;
     150: ldc           #28                 // String hbase.meta.replica.count
     152: iconst_2
     153: invokevirtual #9                  // Method org/apache/hadoop/conf/Configuration.setInt:(Ljava/lang/String;I)V
     156: getstatic     #1                  // Field HTU:Lorg/apache/hadoop/hbase/HBaseTestingUtility;
     159: invokevirtual #5                  // Method org/apache/hadoop/hbase/HBaseTestingUtility.getConfiguration:()Lorg/apache/hadoop/conf/Configuration;
     162: ldc           #29                 // String hbase.balancer.tablesOnMaster
     164: ldc           #30                 // String none
     166: invokevirtual #31                 // Method org/apache/hadoop/conf/Configuration.set:(Ljava/lang/String;Ljava/lang/String;)V
     169: getstatic     #1                  // Field HTU:Lorg/apache/hadoop/hbase/HBaseTestingUtility;
     172: invokevirtual #5                  // Method org/apache/hadoop/hbase/HBaseTestingUtility.getConfiguration:()Lorg/apache/hadoop/conf/Configuration;
     175: ldc           #32                 // String hbase.coprocessor.region.classes
     177: ldc           #33                 // class org/apache/hadoop/hbase/client/TestReplicaWithCluster$RegionServerHostingPrimayMetaRegionSlowOrStopCopro
     179: invokevirtual #34                 // Method java/lang/Class.getName:()Ljava/lang/String;
     182: invokevirtual #31                 // Method org/apache/hadoop/conf/Configuration.set:(Ljava/lang/String;Ljava/lang/String;)V
     185: getstatic     #1                  // Field HTU:Lorg/apache/hadoop/hbase/HBaseTestingUtility;
     188: invokevirtual #5                  // Method org/apache/hadoop/hbase/HBaseTestingUtility.getConfiguration:()Lorg/apache/hadoop/conf/Configuration;
     191: ldc           #36                 // String hbase.client.meta.replica.scan.timeout
     193: ldc           #37                 // int 200000
     195: invokevirtual #9                  // Method org/apache/hadoop/conf/Configuration.setInt:(Ljava/lang/String;I)V
     198: getstatic     #1                  // Field HTU:Lorg/apache/hadoop/hbase/HBaseTestingUtility;
     201: iconst_3
     202: invokevirtual #38                 // Method org/apache/hadoop/hbase/HBaseTestingUtility.startMiniCluster:(I)Lorg/apache/hadoop/hbase/MiniHBaseCluster;
     205: pop
     206: getstatic     #1                  // Field HTU:Lorg/apache/hadoop/hbase/HBaseTestingUtility;
     209: invokevirtual #39                 // Method org/apache/hadoop/hbase/HBaseTestingUtility.getHBaseCluster:()Lorg/apache/hadoop/hbase/MiniHBaseCluster;
     212: invokevirtual #40                 // Method org/apache/hadoop/hbase/MiniHBaseCluster.startMaster:()Lorg/apache/hadoop/hbase/util/JVMClusterUtil$MasterThread;
     215: pop
     216: return

  public static void afterClass() throws java.lang.Exception;
    Code:
       0: getstatic     #41                 // Field HTU2:Lorg/apache/hadoop/hbase/HBaseTestingUtility;
       3: ifnull        12
       6: getstatic     #41                 // Field HTU2:Lorg/apache/hadoop/hbase/HBaseTestingUtility;
       9: invokevirtual #42                 // Method org/apache/hadoop/hbase/HBaseTestingUtility.shutdownMiniCluster:()V
      12: getstatic     #1                  // Field HTU:Lorg/apache/hadoop/hbase/HBaseTestingUtility;
      15: invokevirtual #42                 // Method org/apache/hadoop/hbase/HBaseTestingUtility.shutdownMiniCluster:()V
      18: return

  public void testCreateDeleteTable() throws java.io.IOException;
    Code:
       0: getstatic     #1                  // Field HTU:Lorg/apache/hadoop/hbase/HBaseTestingUtility;
       3: ldc           #43                 // String testCreateDeleteTable
       5: invokevirtual #44                 // Method org/apache/hadoop/hbase/HBaseTestingUtility.createTableDescriptor:(Ljava/lang/String;)Lorg/apache/hadoop/hbase/HTableDescriptor;
       8: astore_1
       9: aload_1
      10: iconst_3
      11: invokevirtual #45                 // Method org/apache/hadoop/hbase/HTableDescriptor.setRegionReplication:(I)Lorg/apache/hadoop/hbase/HTableDescriptor;
      14: pop
      15: aload_1
      16: ldc           #46                 // class org/apache/hadoop/hbase/client/TestReplicaWithCluster$SlowMeCopro
      18: invokevirtual #34                 // Method java/lang/Class.getName:()Ljava/lang/String;
      21: invokevirtual #47                 // Method org/apache/hadoop/hbase/HTableDescriptor.addCoprocessor:(Ljava/lang/String;)Lorg/apache/hadoop/hbase/HTableDescriptor;
      24: pop
      25: getstatic     #1                  // Field HTU:Lorg/apache/hadoop/hbase/HBaseTestingUtility;
      28: aload_1
      29: iconst_1
      30: anewarray     #48                 // class "[B"
      33: dup
      34: iconst_0
      35: getstatic     #49                 // Field f:[B
      38: aastore
      39: aconst_null
      40: invokevirtual #50                 // Method org/apache/hadoop/hbase/HBaseTestingUtility.createTable:(Lorg/apache/hadoop/hbase/client/TableDescriptor;[[BLorg/apache/hadoop/conf/Configuration;)Lorg/apache/hadoop/hbase/client/Table;
      43: astore_2
      44: new           #51                 // class org/apache/hadoop/hbase/client/Put
      47: dup
      48: getstatic     #2                  // Field row:[B
      51: invokespecial #52                 // Method org/apache/hadoop/hbase/client/Put."<init>":([B)V
      54: astore_3
      55: aload_3
      56: getstatic     #49                 // Field f:[B
      59: getstatic     #2                  // Field row:[B
      62: getstatic     #2                  // Field row:[B
      65: invokevirtual #53                 // Method org/apache/hadoop/hbase/client/Put.addColumn:([B[B[B)Lorg/apache/hadoop/hbase/client/Put;
      68: pop
      69: aload_2
      70: aload_3
      71: invokeinterface #54,  2           // InterfaceMethod org/apache/hadoop/hbase/client/Table.put:(Lorg/apache/hadoop/hbase/client/Put;)V
      76: new           #55                 // class org/apache/hadoop/hbase/client/Get
      79: dup
      80: getstatic     #2                  // Field row:[B
      83: invokespecial #56                 // Method org/apache/hadoop/hbase/client/Get."<init>":([B)V
      86: astore        4
      88: aload_2
      89: aload         4
      91: invokeinterface #57,  2           // InterfaceMethod org/apache/hadoop/hbase/client/Table.get:(Lorg/apache/hadoop/hbase/client/Get;)Lorg/apache/hadoop/hbase/client/Result;
      96: astore        5
      98: aload         5
     100: invokevirtual #58                 // Method org/apache/hadoop/hbase/client/Result.isStale:()Z
     103: invokestatic  #59                 // Method org/junit/Assert.assertFalse:(Z)V
     106: getstatic     #60                 // Field org/apache/hadoop/hbase/client/TestReplicaWithCluster$SlowMeCopro.cdl:Ljava/util/concurrent/atomic/AtomicReference;
     109: new           #61                 // class java/util/concurrent/CountDownLatch
     112: dup
     113: iconst_1
     114: invokespecial #62                 // Method java/util/concurrent/CountDownLatch."<init>":(I)V
     117: invokevirtual #63                 // Method java/util/concurrent/atomic/AtomicReference.set:(Ljava/lang/Object;)V
     120: new           #55                 // class org/apache/hadoop/hbase/client/Get
     123: dup
     124: getstatic     #2                  // Field row:[B
     127: invokespecial #56                 // Method org/apache/hadoop/hbase/client/Get."<init>":([B)V
     130: astore        4
     132: aload         4
     134: getstatic     #64                 // Field org/apache/hadoop/hbase/client/Consistency.TIMELINE:Lorg/apache/hadoop/hbase/client/Consistency;
     137: invokevirtual #65                 // Method org/apache/hadoop/hbase/client/Get.setConsistency:(Lorg/apache/hadoop/hbase/client/Consistency;)Lorg/apache/hadoop/hbase/client/Get;
     140: pop
     141: aload_2
     142: aload         4
     144: invokeinterface #57,  2           // InterfaceMethod org/apache/hadoop/hbase/client/Table.get:(Lorg/apache/hadoop/hbase/client/Get;)Lorg/apache/hadoop/hbase/client/Result;
     149: astore        5
     151: aload         5
     153: invokevirtual #58                 // Method org/apache/hadoop/hbase/client/Result.isStale:()Z
     156: invokestatic  #66                 // Method org/junit/Assert.assertTrue:(Z)V
     159: getstatic     #60                 // Field org/apache/hadoop/hbase/client/TestReplicaWithCluster$SlowMeCopro.cdl:Ljava/util/concurrent/atomic/AtomicReference;
     162: invokevirtual #67                 // Method java/util/concurrent/atomic/AtomicReference.get:()Ljava/lang/Object;
     165: checkcast     #61                 // class java/util/concurrent/CountDownLatch
     168: invokevirtual #68                 // Method java/util/concurrent/CountDownLatch.countDown:()V
     171: getstatic     #60                 // Field org/apache/hadoop/hbase/client/TestReplicaWithCluster$SlowMeCopro.cdl:Ljava/util/concurrent/atomic/AtomicReference;
     174: invokevirtual #67                 // Method java/util/concurrent/atomic/AtomicReference.get:()Ljava/lang/Object;
     177: checkcast     #61                 // class java/util/concurrent/CountDownLatch
     180: invokevirtual #68                 // Method java/util/concurrent/CountDownLatch.countDown:()V
     183: getstatic     #69                 // Field org/apache/hadoop/hbase/client/TestReplicaWithCluster$SlowMeCopro.sleepTime:Ljava/util/concurrent/atomic/AtomicLong;
     186: lconst_0
     187: invokevirtual #70                 // Method java/util/concurrent/atomic/AtomicLong.set:(J)V
     190: goto          217
     193: astore        6
     195: getstatic     #60                 // Field org/apache/hadoop/hbase/client/TestReplicaWithCluster$SlowMeCopro.cdl:Ljava/util/concurrent/atomic/AtomicReference;
     198: invokevirtual #67                 // Method java/util/concurrent/atomic/AtomicReference.get:()Ljava/lang/Object;
     201: checkcast     #61                 // class java/util/concurrent/CountDownLatch
     204: invokevirtual #68                 // Method java/util/concurrent/CountDownLatch.countDown:()V
     207: getstatic     #69                 // Field org/apache/hadoop/hbase/client/TestReplicaWithCluster$SlowMeCopro.sleepTime:Ljava/util/concurrent/atomic/AtomicLong;
     210: lconst_0
     211: invokevirtual #70                 // Method java/util/concurrent/atomic/AtomicLong.set:(J)V
     214: aload         6
     216: athrow
     217: getstatic     #1                  // Field HTU:Lorg/apache/hadoop/hbase/HBaseTestingUtility;
     220: invokevirtual #71                 // Method org/apache/hadoop/hbase/HBaseTestingUtility.getAdmin:()Lorg/apache/hadoop/hbase/client/Admin;
     223: aload_1
     224: invokevirtual #72                 // Method org/apache/hadoop/hbase/HTableDescriptor.getTableName:()Lorg/apache/hadoop/hbase/TableName;
     227: invokeinterface #73,  2           // InterfaceMethod org/apache/hadoop/hbase/client/Admin.disableTable:(Lorg/apache/hadoop/hbase/TableName;)V
     232: getstatic     #1                  // Field HTU:Lorg/apache/hadoop/hbase/HBaseTestingUtility;
     235: aload_1
     236: invokevirtual #72                 // Method org/apache/hadoop/hbase/HTableDescriptor.getTableName:()Lorg/apache/hadoop/hbase/TableName;
     239: invokevirtual #74                 // Method org/apache/hadoop/hbase/HBaseTestingUtility.deleteTable:(Lorg/apache/hadoop/hbase/TableName;)V
     242: return
    Exception table:
       from    to  target type
         106   171   193   any
         193   195   193   any

  public void testChangeTable() throws java.lang.Exception;
    Code:
       0: ldc           #75                 // String testChangeTable
       2: invokestatic  #76                 // Method org/apache/hadoop/hbase/TableName.valueOf:(Ljava/lang/String;)Lorg/apache/hadoop/hbase/TableName;
       5: invokestatic  #77                 // Method org/apache/hadoop/hbase/client/TableDescriptorBuilder.newBuilder:(Lorg/apache/hadoop/hbase/TableName;)Lorg/apache/hadoop/hbase/client/TableDescriptorBuilder;
       8: iconst_3
       9: invokevirtual #78                 // Method org/apache/hadoop/hbase/client/TableDescriptorBuilder.setRegionReplication:(I)Lorg/apache/hadoop/hbase/client/TableDescriptorBuilder;
      12: ldc           #46                 // class org/apache/hadoop/hbase/client/TestReplicaWithCluster$SlowMeCopro
      14: invokevirtual #34                 // Method java/lang/Class.getName:()Ljava/lang/String;
      17: invokevirtual #79                 // Method org/apache/hadoop/hbase/client/TableDescriptorBuilder.setCoprocessor:(Ljava/lang/String;)Lorg/apache/hadoop/hbase/client/TableDescriptorBuilder;
      20: getstatic     #49                 // Field f:[B
      23: invokestatic  #80                 // Method org/apache/hadoop/hbase/client/ColumnFamilyDescriptorBuilder.of:([B)Lorg/apache/hadoop/hbase/client/ColumnFamilyDescriptor;
      26: invokevirtual #81                 // Method org/apache/hadoop/hbase/client/TableDescriptorBuilder.setColumnFamily:(Lorg/apache/hadoop/hbase/client/ColumnFamilyDescriptor;)Lorg/apache/hadoop/hbase/client/TableDescriptorBuilder;
      29: invokevirtual #82                 // Method org/apache/hadoop/hbase/client/TableDescriptorBuilder.build:()Lorg/apache/hadoop/hbase/client/TableDescriptor;
      32: astore_1
      33: getstatic     #1                  // Field HTU:Lorg/apache/hadoop/hbase/HBaseTestingUtility;
      36: invokevirtual #71                 // Method org/apache/hadoop/hbase/HBaseTestingUtility.getAdmin:()Lorg/apache/hadoop/hbase/client/Admin;
      39: aload_1
      40: invokeinterface #83,  2           // InterfaceMethod org/apache/hadoop/hbase/client/Admin.createTable:(Lorg/apache/hadoop/hbase/client/TableDescriptor;)V
      45: getstatic     #1                  // Field HTU:Lorg/apache/hadoop/hbase/HBaseTestingUtility;
      48: invokevirtual #84                 // Method org/apache/hadoop/hbase/HBaseTestingUtility.getConnection:()Lorg/apache/hadoop/hbase/client/Connection;
      51: aload_1
      52: invokeinterface #85,  1           // InterfaceMethod org/apache/hadoop/hbase/client/TableDescriptor.getTableName:()Lorg/apache/hadoop/hbase/TableName;
      57: invokeinterface #86,  2           // InterfaceMethod org/apache/hadoop/hbase/client/Connection.getTable:(Lorg/apache/hadoop/hbase/TableName;)Lorg/apache/hadoop/hbase/client/Table;
      62: astore_2
      63: new           #51                 // class org/apache/hadoop/hbase/client/Put
      66: dup
      67: getstatic     #2                  // Field row:[B
      70: invokespecial #52                 // Method org/apache/hadoop/hbase/client/Put."<init>":([B)V
      73: astore_3
      74: aload_3
      75: getstatic     #49                 // Field f:[B
      78: getstatic     #2                  // Field row:[B
      81: getstatic     #2                  // Field row:[B
      84: invokevirtual #53                 // Method org/apache/hadoop/hbase/client/Put.addColumn:([B[B[B)Lorg/apache/hadoop/hbase/client/Put;
      87: pop
      88: aload_2
      89: aload_3
      90: invokeinterface #54,  2           // InterfaceMethod org/apache/hadoop/hbase/client/Table.put:(Lorg/apache/hadoop/hbase/client/Put;)V
      95: new           #55                 // class org/apache/hadoop/hbase/client/Get
      98: dup
      99: getstatic     #2                  // Field row:[B
     102: invokespecial #56                 // Method org/apache/hadoop/hbase/client/Get."<init>":([B)V
     105: astore        4
     107: aload_2
     108: aload         4
     110: invokeinterface #57,  2           // InterfaceMethod org/apache/hadoop/hbase/client/Table.get:(Lorg/apache/hadoop/hbase/client/Get;)Lorg/apache/hadoop/hbase/client/Result;
     115: astore        5
     117: aload         5
     119: invokevirtual #58                 // Method org/apache/hadoop/hbase/client/Result.isStale:()Z
     122: invokestatic  #59                 // Method org/junit/Assert.assertFalse:(Z)V
     125: getstatic     #1                  // Field HTU:Lorg/apache/hadoop/hbase/HBaseTestingUtility;
     128: invokevirtual #71                 // Method org/apache/hadoop/hbase/HBaseTestingUtility.getAdmin:()Lorg/apache/hadoop/hbase/client/Admin;
     131: aload_1
     132: invokeinterface #85,  1           // InterfaceMethod org/apache/hadoop/hbase/client/TableDescriptor.getTableName:()Lorg/apache/hadoop/hbase/TableName;
     137: invokeinterface #87,  2           // InterfaceMethod org/apache/hadoop/hbase/client/Admin.getDescriptor:(Lorg/apache/hadoop/hbase/TableName;)Lorg/apache/hadoop/hbase/client/TableDescriptor;
     142: astore        6
     144: aload_1
     145: invokestatic  #88                 // Method org/apache/hadoop/hbase/client/TableDescriptorBuilder.newBuilder:(Lorg/apache/hadoop/hbase/client/TableDescriptor;)Lorg/apache/hadoop/hbase/client/TableDescriptorBuilder;
     148: getstatic     #2                  // Field row:[B
     151: invokestatic  #80                 // Method org/apache/hadoop/hbase/client/ColumnFamilyDescriptorBuilder.of:([B)Lorg/apache/hadoop/hbase/client/ColumnFamilyDescriptor;
     154: invokevirtual #81                 // Method org/apache/hadoop/hbase/client/TableDescriptorBuilder.setColumnFamily:(Lorg/apache/hadoop/hbase/client/ColumnFamilyDescriptor;)Lorg/apache/hadoop/hbase/client/TableDescriptorBuilder;
     157: invokevirtual #82                 // Method org/apache/hadoop/hbase/client/TableDescriptorBuilder.build:()Lorg/apache/hadoop/hbase/client/TableDescriptor;
     160: astore_1
     161: getstatic     #1                  // Field HTU:Lorg/apache/hadoop/hbase/HBaseTestingUtility;
     164: invokevirtual #71                 // Method org/apache/hadoop/hbase/HBaseTestingUtility.getAdmin:()Lorg/apache/hadoop/hbase/client/Admin;
     167: aload_1
     168: invokeinterface #85,  1           // InterfaceMethod org/apache/hadoop/hbase/client/TableDescriptor.getTableName:()Lorg/apache/hadoop/hbase/TableName;
     173: invokeinterface #73,  2           // InterfaceMethod org/apache/hadoop/hbase/client/Admin.disableTable:(Lorg/apache/hadoop/hbase/TableName;)V
     178: getstatic     #1                  // Field HTU:Lorg/apache/hadoop/hbase/HBaseTestingUtility;
     181: invokevirtual #71                 // Method org/apache/hadoop/hbase/HBaseTestingUtility.getAdmin:()Lorg/apache/hadoop/hbase/client/Admin;
     184: aload_1
     185: invokeinterface #89,  2           // InterfaceMethod org/apache/hadoop/hbase/client/Admin.modifyTable:(Lorg/apache/hadoop/hbase/client/TableDescriptor;)V
     190: getstatic     #1                  // Field HTU:Lorg/apache/hadoop/hbase/HBaseTestingUtility;
     193: invokevirtual #71                 // Method org/apache/hadoop/hbase/HBaseTestingUtility.getAdmin:()Lorg/apache/hadoop/hbase/client/Admin;
     196: aload_1
     197: invokeinterface #85,  1           // InterfaceMethod org/apache/hadoop/hbase/client/TableDescriptor.getTableName:()Lorg/apache/hadoop/hbase/TableName;
     202: invokeinterface #90,  2           // InterfaceMethod org/apache/hadoop/hbase/client/Admin.enableTable:(Lorg/apache/hadoop/hbase/TableName;)V
     207: getstatic     #1                  // Field HTU:Lorg/apache/hadoop/hbase/HBaseTestingUtility;
     210: invokevirtual #71                 // Method org/apache/hadoop/hbase/HBaseTestingUtility.getAdmin:()Lorg/apache/hadoop/hbase/client/Admin;
     213: aload_1
     214: invokeinterface #85,  1           // InterfaceMethod org/apache/hadoop/hbase/client/TableDescriptor.getTableName:()Lorg/apache/hadoop/hbase/TableName;
     219: invokeinterface #87,  2           // InterfaceMethod org/apache/hadoop/hbase/client/Admin.getDescriptor:(Lorg/apache/hadoop/hbase/TableName;)Lorg/apache/hadoop/hbase/client/TableDescriptor;
     224: astore        7
     226: new           #91                 // class java/lang/StringBuilder
     229: dup
     230: invokespecial #92                 // Method java/lang/StringBuilder."<init>":()V
     233: ldc           #93                 // String fams=
     235: invokevirtual #94                 // Method java/lang/StringBuilder.append:(Ljava/lang/String;)Ljava/lang/StringBuilder;
     238: aload         7
     240: invokeinterface #95,  1           // InterfaceMethod org/apache/hadoop/hbase/client/TableDescriptor.getColumnFamilies:()[Lorg/apache/hadoop/hbase/client/ColumnFamilyDescriptor;
     245: invokestatic  #96                 // Method java/util/Arrays.toString:([Ljava/lang/Object;)Ljava/lang/String;
     248: invokevirtual #94                 // Method java/lang/StringBuilder.append:(Ljava/lang/String;)Ljava/lang/StringBuilder;
     251: invokevirtual #97                 // Method java/lang/StringBuilder.toString:()Ljava/lang/String;
     254: aload         6
     256: invokeinterface #98,  1           // InterfaceMethod org/apache/hadoop/hbase/client/TableDescriptor.getColumnFamilyCount:()I
     261: iconst_1
     262: iadd
     263: i2l
     264: aload         7
     266: invokeinterface #98,  1           // InterfaceMethod org/apache/hadoop/hbase/client/TableDescriptor.getColumnFamilyCount:()I
     271: i2l
     272: invokestatic  #99                 // Method org/junit/Assert.assertEquals:(Ljava/lang/String;JJ)V
     275: new           #51                 // class org/apache/hadoop/hbase/client/Put
     278: dup
     279: getstatic     #2                  // Field row:[B
     282: invokespecial #52                 // Method org/apache/hadoop/hbase/client/Put."<init>":([B)V
     285: astore_3
     286: aload_3
     287: getstatic     #2                  // Field row:[B
     290: getstatic     #2                  // Field row:[B
     293: getstatic     #2                  // Field row:[B
     296: invokevirtual #53                 // Method org/apache/hadoop/hbase/client/Put.addColumn:([B[B[B)Lorg/apache/hadoop/hbase/client/Put;
     299: pop
     300: aload_2
     301: aload_3
     302: invokeinterface #54,  2           // InterfaceMethod org/apache/hadoop/hbase/client/Table.put:(Lorg/apache/hadoop/hbase/client/Put;)V
     307: new           #55                 // class org/apache/hadoop/hbase/client/Get
     310: dup
     311: getstatic     #2                  // Field row:[B
     314: invokespecial #56                 // Method org/apache/hadoop/hbase/client/Get."<init>":([B)V
     317: astore        4
     319: aload_2
     320: aload         4
     322: invokeinterface #57,  2           // InterfaceMethod org/apache/hadoop/hbase/client/Table.get:(Lorg/apache/hadoop/hbase/client/Get;)Lorg/apache/hadoop/hbase/client/Result;
     327: astore        5
     329: aload         5
     331: invokevirtual #58                 // Method org/apache/hadoop/hbase/client/Result.isStale:()Z
     334: invokestatic  #59                 // Method org/junit/Assert.assertFalse:(Z)V
     337: getstatic     #60                 // Field org/apache/hadoop/hbase/client/TestReplicaWithCluster$SlowMeCopro.cdl:Ljava/util/concurrent/atomic/AtomicReference;
     340: new           #61                 // class java/util/concurrent/CountDownLatch
     343: dup
     344: iconst_1
     345: invokespecial #62                 // Method java/util/concurrent/CountDownLatch."<init>":(I)V
     348: invokevirtual #63                 // Method java/util/concurrent/atomic/AtomicReference.set:(Ljava/lang/Object;)V
     351: new           #55                 // class org/apache/hadoop/hbase/client/Get
     354: dup
     355: getstatic     #2                  // Field row:[B
     358: invokespecial #56                 // Method org/apache/hadoop/hbase/client/Get."<init>":([B)V
     361: astore        4
     363: aload         4
     365: getstatic     #64                 // Field org/apache/hadoop/hbase/client/Consistency.TIMELINE:Lorg/apache/hadoop/hbase/client/Consistency;
     368: invokevirtual #65                 // Method org/apache/hadoop/hbase/client/Get.setConsistency:(Lorg/apache/hadoop/hbase/client/Consistency;)Lorg/apache/hadoop/hbase/client/Get;
     371: pop
     372: aload_2
     373: aload         4
     375: invokeinterface #57,  2           // InterfaceMethod org/apache/hadoop/hbase/client/Table.get:(Lorg/apache/hadoop/hbase/client/Get;)Lorg/apache/hadoop/hbase/client/Result;
     380: astore        5
     382: aload         5
     384: invokevirtual #58                 // Method org/apache/hadoop/hbase/client/Result.isStale:()Z
     387: invokestatic  #66                 // Method org/junit/Assert.assertTrue:(Z)V
     390: getstatic     #60                 // Field org/apache/hadoop/hbase/client/TestReplicaWithCluster$SlowMeCopro.cdl:Ljava/util/concurrent/atomic/AtomicReference;
     393: invokevirtual #67                 // Method java/util/concurrent/atomic/AtomicReference.get:()Ljava/lang/Object;
     396: checkcast     #61                 // class java/util/concurrent/CountDownLatch
     399: invokevirtual #68                 // Method java/util/concurrent/CountDownLatch.countDown:()V
     402: getstatic     #69                 // Field org/apache/hadoop/hbase/client/TestReplicaWithCluster$SlowMeCopro.sleepTime:Ljava/util/concurrent/atomic/AtomicLong;
     405: lconst_0
     406: invokevirtual #70                 // Method java/util/concurrent/atomic/AtomicLong.set:(J)V
     409: goto          436
     412: astore        8
     414: getstatic     #60                 // Field org/apache/hadoop/hbase/client/TestReplicaWithCluster$SlowMeCopro.cdl:Ljava/util/concurrent/atomic/AtomicReference;
     417: invokevirtual #67                 // Method java/util/concurrent/atomic/AtomicReference.get:()Ljava/lang/Object;
     420: checkcast     #61                 // class java/util/concurrent/CountDownLatch
     423: invokevirtual #68                 // Method java/util/concurrent/CountDownLatch.countDown:()V
     426: getstatic     #69                 // Field org/apache/hadoop/hbase/client/TestReplicaWithCluster$SlowMeCopro.sleepTime:Ljava/util/concurrent/atomic/AtomicLong;
     429: lconst_0
     430: invokevirtual #70                 // Method java/util/concurrent/atomic/AtomicLong.set:(J)V
     433: aload         8
     435: athrow
     436: getstatic     #1                  // Field HTU:Lorg/apache/hadoop/hbase/HBaseTestingUtility;
     439: invokevirtual #71                 // Method org/apache/hadoop/hbase/HBaseTestingUtility.getAdmin:()Lorg/apache/hadoop/hbase/client/Admin;
     442: astore        8
     444: aload         8
     446: aload_1
     447: invokeinterface #85,  1           // InterfaceMethod org/apache/hadoop/hbase/client/TableDescriptor.getTableName:()Lorg/apache/hadoop/hbase/TableName;
     452: invokeinterface #87,  2           // InterfaceMethod org/apache/hadoop/hbase/client/Admin.getDescriptor:(Lorg/apache/hadoop/hbase/TableName;)Lorg/apache/hadoop/hbase/client/TableDescriptor;
     457: astore        7
     459: new           #91                 // class java/lang/StringBuilder
     462: dup
     463: invokespecial #92                 // Method java/lang/StringBuilder."<init>":()V
     466: ldc           #93                 // String fams=
     468: invokevirtual #94                 // Method java/lang/StringBuilder.append:(Ljava/lang/String;)Ljava/lang/StringBuilder;
     471: aload         7
     473: invokeinterface #95,  1           // InterfaceMethod org/apache/hadoop/hbase/client/TableDescriptor.getColumnFamilies:()[Lorg/apache/hadoop/hbase/client/ColumnFamilyDescriptor;
     478: invokestatic  #96                 // Method java/util/Arrays.toString:([Ljava/lang/Object;)Ljava/lang/String;
     481: invokevirtual #94                 // Method java/lang/StringBuilder.append:(Ljava/lang/String;)Ljava/lang/StringBuilder;
     484: invokevirtual #97                 // Method java/lang/StringBuilder.toString:()Ljava/lang/String;
     487: aload         6
     489: invokeinterface #98,  1           // InterfaceMethod org/apache/hadoop/hbase/client/TableDescriptor.getColumnFamilyCount:()I
     494: iconst_1
     495: iadd
     496: i2l
     497: aload         7
     499: invokeinterface #98,  1           // InterfaceMethod org/apache/hadoop/hbase/client/TableDescriptor.getColumnFamilyCount:()I
     504: i2l
     505: invokestatic  #99                 // Method org/junit/Assert.assertEquals:(Ljava/lang/String;JJ)V
     508: aload         8
     510: aload_1
     511: invokeinterface #85,  1           // InterfaceMethod org/apache/hadoop/hbase/client/TableDescriptor.getTableName:()Lorg/apache/hadoop/hbase/TableName;
     516: invokeinterface #73,  2           // InterfaceMethod org/apache/hadoop/hbase/client/Admin.disableTable:(Lorg/apache/hadoop/hbase/TableName;)V
     521: aload         8
     523: aload_1
     524: invokeinterface #85,  1           // InterfaceMethod org/apache/hadoop/hbase/client/TableDescriptor.getTableName:()Lorg/apache/hadoop/hbase/TableName;
     529: invokeinterface #100,  2          // InterfaceMethod org/apache/hadoop/hbase/client/Admin.deleteTable:(Lorg/apache/hadoop/hbase/TableName;)V
     534: aload         8
     536: invokeinterface #101,  1          // InterfaceMethod org/apache/hadoop/hbase/client/Admin.close:()V
     541: return
    Exception table:
       from    to  target type
         337   390   412   any
         412   414   412   any

  public void testReplicaAndReplication() throws java.lang.Exception;
    Code:
       0: getstatic     #1                  // Field HTU:Lorg/apache/hadoop/hbase/HBaseTestingUtility;
       3: ldc           #102                // String testReplicaAndReplication
       5: invokevirtual #44                 // Method org/apache/hadoop/hbase/HBaseTestingUtility.createTableDescriptor:(Ljava/lang/String;)Lorg/apache/hadoop/hbase/HTableDescriptor;
       8: astore_1
       9: aload_1
      10: iconst_3
      11: invokevirtual #45                 // Method org/apache/hadoop/hbase/HTableDescriptor.setRegionReplication:(I)Lorg/apache/hadoop/hbase/HTableDescriptor;
      14: pop
      15: new           #103                // class org/apache/hadoop/hbase/HColumnDescriptor
      18: dup
      19: getstatic     #2                  // Field row:[B
      22: invokespecial #104                // Method org/apache/hadoop/hbase/HColumnDescriptor."<init>":([B)V
      25: astore_2
      26: aload_2
      27: iconst_1
      28: invokevirtual #105                // Method org/apache/hadoop/hbase/HColumnDescriptor.setScope:(I)Lorg/apache/hadoop/hbase/HColumnDescriptor;
      31: pop
      32: aload_1
      33: aload_2
      34: invokevirtual #106                // Method org/apache/hadoop/hbase/HTableDescriptor.addFamily:(Lorg/apache/hadoop/hbase/HColumnDescriptor;)Lorg/apache/hadoop/hbase/HTableDescriptor;
      37: pop
      38: aload_1
      39: ldc           #46                 // class org/apache/hadoop/hbase/client/TestReplicaWithCluster$SlowMeCopro
      41: invokevirtual #34                 // Method java/lang/Class.getName:()Ljava/lang/String;
      44: invokevirtual #47                 // Method org/apache/hadoop/hbase/HTableDescriptor.addCoprocessor:(Ljava/lang/String;)Lorg/apache/hadoop/hbase/HTableDescriptor;
      47: pop
      48: getstatic     #1                  // Field HTU:Lorg/apache/hadoop/hbase/HBaseTestingUtility;
      51: invokevirtual #71                 // Method org/apache/hadoop/hbase/HBaseTestingUtility.getAdmin:()Lorg/apache/hadoop/hbase/client/Admin;
      54: aload_1
      55: getstatic     #107                // Field org/apache/hadoop/hbase/HBaseTestingUtility.KEYS_FOR_HBA_CREATE_TABLE:[[B
      58: invokeinterface #108,  3          // InterfaceMethod org/apache/hadoop/hbase/client/Admin.createTable:(Lorg/apache/hadoop/hbase/client/TableDescriptor;[[B)V
      63: getstatic     #1                  // Field HTU:Lorg/apache/hadoop/hbase/HBaseTestingUtility;
      66: invokevirtual #5                  // Method org/apache/hadoop/hbase/HBaseTestingUtility.getConfiguration:()Lorg/apache/hadoop/conf/Configuration;
      69: invokestatic  #109                // Method org/apache/hadoop/hbase/HBaseConfiguration.create:(Lorg/apache/hadoop/conf/Configuration;)Lorg/apache/hadoop/conf/Configuration;
      72: astore_3
      73: aload_3
      74: ldc           #110                // String hbase.client.instance.id
      76: iconst_m1
      77: invokestatic  #111                // Method java/lang/String.valueOf:(I)Ljava/lang/String;
      80: invokevirtual #31                 // Method org/apache/hadoop/conf/Configuration.set:(Ljava/lang/String;Ljava/lang/String;)V
      83: aload_3
      84: ldc           #112                // String zookeeper.znode.parent
      86: ldc           #113                // String /2
      88: invokevirtual #31                 // Method org/apache/hadoop/conf/Configuration.set:(Ljava/lang/String;Ljava/lang/String;)V
      91: getstatic     #1                  // Field HTU:Lorg/apache/hadoop/hbase/HBaseTestingUtility;
      94: invokevirtual #114                // Method org/apache/hadoop/hbase/HBaseTestingUtility.getZkCluster:()Lorg/apache/hadoop/hbase/zookeeper/MiniZooKeeperCluster;
      97: astore        4
      99: new           #115                // class org/apache/hadoop/hbase/HBaseTestingUtility
     102: dup
     103: aload_3
     104: invokespecial #116                // Method org/apache/hadoop/hbase/HBaseTestingUtility."<init>":(Lorg/apache/hadoop/conf/Configuration;)V
     107: putstatic     #41                 // Field HTU2:Lorg/apache/hadoop/hbase/HBaseTestingUtility;
     110: getstatic     #41                 // Field HTU2:Lorg/apache/hadoop/hbase/HBaseTestingUtility;
     113: aload         4
     115: invokevirtual #117                // Method org/apache/hadoop/hbase/HBaseTestingUtility.setZkCluster:(Lorg/apache/hadoop/hbase/zookeeper/MiniZooKeeperCluster;)V
     118: getstatic     #41                 // Field HTU2:Lorg/apache/hadoop/hbase/HBaseTestingUtility;
     121: iconst_3
     122: invokevirtual #38                 // Method org/apache/hadoop/hbase/HBaseTestingUtility.startMiniCluster:(I)Lorg/apache/hadoop/hbase/MiniHBaseCluster;
     125: pop
     126: getstatic     #3                  // Field LOG:Lorg/slf4j/Logger;
     129: ldc           #118                // String Setup second Zk
     131: invokeinterface #119,  2          // InterfaceMethod org/slf4j/Logger.info:(Ljava/lang/String;)V
     136: getstatic     #41                 // Field HTU2:Lorg/apache/hadoop/hbase/HBaseTestingUtility;
     139: invokevirtual #71                 // Method org/apache/hadoop/hbase/HBaseTestingUtility.getAdmin:()Lorg/apache/hadoop/hbase/client/Admin;
     142: aload_1
     143: getstatic     #107                // Field org/apache/hadoop/hbase/HBaseTestingUtility.KEYS_FOR_HBA_CREATE_TABLE:[[B
     146: invokeinterface #108,  3          // InterfaceMethod org/apache/hadoop/hbase/client/Admin.createTable:(Lorg/apache/hadoop/hbase/client/TableDescriptor;[[B)V
     151: new           #120                // class org/apache/hadoop/hbase/client/replication/ReplicationAdmin
     154: dup
     155: getstatic     #1                  // Field HTU:Lorg/apache/hadoop/hbase/HBaseTestingUtility;
     158: invokevirtual #5                  // Method org/apache/hadoop/hbase/HBaseTestingUtility.getConfiguration:()Lorg/apache/hadoop/conf/Configuration;
     161: invokespecial #121                // Method org/apache/hadoop/hbase/client/replication/ReplicationAdmin."<init>":(Lorg/apache/hadoop/conf/Configuration;)V
     164: astore        5
     166: new           #122                // class org/apache/hadoop/hbase/replication/ReplicationPeerConfig
     169: dup
     170: invokespecial #123                // Method org/apache/hadoop/hbase/replication/ReplicationPeerConfig."<init>":()V
     173: astore        6
     175: aload         6
     177: getstatic     #41                 // Field HTU2:Lorg/apache/hadoop/hbase/HBaseTestingUtility;
     180: invokevirtual #124                // Method org/apache/hadoop/hbase/HBaseTestingUtility.getClusterKey:()Ljava/lang/String;
     183: invokevirtual #125                // Method org/apache/hadoop/hbase/replication/ReplicationPeerConfig.setClusterKey:(Ljava/lang/String;)Lorg/apache/hadoop/hbase/replication/ReplicationPeerConfig;
     186: pop
     187: aload         5
     189: ldc           #126                // String 2
     191: aload         6
     193: aconst_null
     194: invokevirtual #127                // Method org/apache/hadoop/hbase/client/replication/ReplicationAdmin.addPeer:(Ljava/lang/String;Lorg/apache/hadoop/hbase/replication/ReplicationPeerConfig;Ljava/util/Map;)V
     197: aload         5
     199: invokevirtual #128                // Method org/apache/hadoop/hbase/client/replication/ReplicationAdmin.close:()V
     202: new           #51                 // class org/apache/hadoop/hbase/client/Put
     205: dup
     206: getstatic     #2                  // Field row:[B
     209: invokespecial #52                 // Method org/apache/hadoop/hbase/client/Put."<init>":([B)V
     212: astore        7
     214: aload         7
     216: getstatic     #2                  // Field row:[B
     219: getstatic     #2                  // Field row:[B
     222: getstatic     #2                  // Field row:[B
     225: invokevirtual #53                 // Method org/apache/hadoop/hbase/client/Put.addColumn:([B[B[B)Lorg/apache/hadoop/hbase/client/Put;
     228: pop
     229: getstatic     #1                  // Field HTU:Lorg/apache/hadoop/hbase/HBaseTestingUtility;
     232: invokevirtual #84                 // Method org/apache/hadoop/hbase/HBaseTestingUtility.getConnection:()Lorg/apache/hadoop/hbase/client/Connection;
     235: aload_1
     236: invokevirtual #72                 // Method org/apache/hadoop/hbase/HTableDescriptor.getTableName:()Lorg/apache/hadoop/hbase/TableName;
     239: invokeinterface #86,  2           // InterfaceMethod org/apache/hadoop/hbase/client/Connection.getTable:(Lorg/apache/hadoop/hbase/TableName;)Lorg/apache/hadoop/hbase/client/Table;
     244: astore        8
     246: aload         8
     248: aload         7
     250: invokeinterface #54,  2           // InterfaceMethod org/apache/hadoop/hbase/client/Table.put:(Lorg/apache/hadoop/hbase/client/Put;)V
     255: getstatic     #1                  // Field HTU:Lorg/apache/hadoop/hbase/HBaseTestingUtility;
     258: invokevirtual #71                 // Method org/apache/hadoop/hbase/HBaseTestingUtility.getAdmin:()Lorg/apache/hadoop/hbase/client/Admin;
     261: aload         8
     263: invokeinterface #129,  1          // InterfaceMethod org/apache/hadoop/hbase/client/Table.getName:()Lorg/apache/hadoop/hbase/TableName;
     268: invokeinterface #130,  2          // InterfaceMethod org/apache/hadoop/hbase/client/Admin.flush:(Lorg/apache/hadoop/hbase/TableName;)V
     273: getstatic     #3                  // Field LOG:Lorg/slf4j/Logger;
     276: ldc           #131                // String Put & flush done on the first cluster. Now doing a get on the same cluster.
     278: invokeinterface #119,  2          // InterfaceMethod org/slf4j/Logger.info:(Ljava/lang/String;)V
     283: getstatic     #1                  // Field HTU:Lorg/apache/hadoop/hbase/HBaseTestingUtility;
     286: invokevirtual #5                  // Method org/apache/hadoop/hbase/HBaseTestingUtility.getConfiguration:()Lorg/apache/hadoop/conf/Configuration;
     289: ldc2_w        #132                // long 1000l
     292: new           #134                // class org/apache/hadoop/hbase/client/TestReplicaWithCluster$1
     295: dup
     296: aload_0
     297: aload         8
     299: invokespecial #135                // Method org/apache/hadoop/hbase/client/TestReplicaWithCluster$1."<init>":(Lorg/apache/hadoop/hbase/client/TestReplicaWithCluster;Lorg/apache/hadoop/hbase/client/Table;)V
     302: invokestatic  #136                // Method org/apache/hadoop/hbase/Waiter.waitFor:(Lorg/apache/hadoop/conf/Configuration;JLorg/apache/hadoop/hbase/Waiter$Predicate;)J
     305: pop2
     306: aload         8
     308: invokeinterface #137,  1          // InterfaceMethod org/apache/hadoop/hbase/client/Table.close:()V
     313: getstatic     #3                  // Field LOG:Lorg/slf4j/Logger;
     316: ldc           #138                // String stale get on the first cluster done. Now for the second.
     318: invokeinterface #119,  2          // InterfaceMethod org/slf4j/Logger.info:(Ljava/lang/String;)V
     323: getstatic     #1                  // Field HTU:Lorg/apache/hadoop/hbase/HBaseTestingUtility;
     326: invokevirtual #84                 // Method org/apache/hadoop/hbase/HBaseTestingUtility.getConnection:()Lorg/apache/hadoop/hbase/client/Connection;
     329: aload_1
     330: invokevirtual #72                 // Method org/apache/hadoop/hbase/HTableDescriptor.getTableName:()Lorg/apache/hadoop/hbase/TableName;
     333: invokeinterface #86,  2           // InterfaceMethod org/apache/hadoop/hbase/client/Connection.getTable:(Lorg/apache/hadoop/hbase/TableName;)Lorg/apache/hadoop/hbase/client/Table;
     338: astore        9
     340: getstatic     #1                  // Field HTU:Lorg/apache/hadoop/hbase/HBaseTestingUtility;
     343: invokevirtual #5                  // Method org/apache/hadoop/hbase/HBaseTestingUtility.getConfiguration:()Lorg/apache/hadoop/conf/Configuration;
     346: ldc2_w        #132                // long 1000l
     349: new           #139                // class org/apache/hadoop/hbase/client/TestReplicaWithCluster$2
     352: dup
     353: aload_0
     354: aload         9
     356: invokespecial #140                // Method org/apache/hadoop/hbase/client/TestReplicaWithCluster$2."<init>":(Lorg/apache/hadoop/hbase/client/TestReplicaWithCluster;Lorg/apache/hadoop/hbase/client/Table;)V
     359: invokestatic  #136                // Method org/apache/hadoop/hbase/Waiter.waitFor:(Lorg/apache/hadoop/conf/Configuration;JLorg/apache/hadoop/hbase/Waiter$Predicate;)J
     362: pop2
     363: aload         9
     365: invokeinterface #137,  1          // InterfaceMethod org/apache/hadoop/hbase/client/Table.close:()V
     370: getstatic     #1                  // Field HTU:Lorg/apache/hadoop/hbase/HBaseTestingUtility;
     373: invokevirtual #71                 // Method org/apache/hadoop/hbase/HBaseTestingUtility.getAdmin:()Lorg/apache/hadoop/hbase/client/Admin;
     376: aload_1
     377: invokevirtual #72                 // Method org/apache/hadoop/hbase/HTableDescriptor.getTableName:()Lorg/apache/hadoop/hbase/TableName;
     380: invokeinterface #73,  2           // InterfaceMethod org/apache/hadoop/hbase/client/Admin.disableTable:(Lorg/apache/hadoop/hbase/TableName;)V
     385: getstatic     #1                  // Field HTU:Lorg/apache/hadoop/hbase/HBaseTestingUtility;
     388: aload_1
     389: invokevirtual #72                 // Method org/apache/hadoop/hbase/HTableDescriptor.getTableName:()Lorg/apache/hadoop/hbase/TableName;
     392: invokevirtual #74                 // Method org/apache/hadoop/hbase/HBaseTestingUtility.deleteTable:(Lorg/apache/hadoop/hbase/TableName;)V
     395: getstatic     #41                 // Field HTU2:Lorg/apache/hadoop/hbase/HBaseTestingUtility;
     398: invokevirtual #71                 // Method org/apache/hadoop/hbase/HBaseTestingUtility.getAdmin:()Lorg/apache/hadoop/hbase/client/Admin;
     401: aload_1
     402: invokevirtual #72                 // Method org/apache/hadoop/hbase/HTableDescriptor.getTableName:()Lorg/apache/hadoop/hbase/TableName;
     405: invokeinterface #73,  2           // InterfaceMethod org/apache/hadoop/hbase/client/Admin.disableTable:(Lorg/apache/hadoop/hbase/TableName;)V
     410: getstatic     #41                 // Field HTU2:Lorg/apache/hadoop/hbase/HBaseTestingUtility;
     413: aload_1
     414: invokevirtual #72                 // Method org/apache/hadoop/hbase/HTableDescriptor.getTableName:()Lorg/apache/hadoop/hbase/TableName;
     417: invokevirtual #74                 // Method org/apache/hadoop/hbase/HBaseTestingUtility.deleteTable:(Lorg/apache/hadoop/hbase/TableName;)V
     420: return

  public void testBulkLoad() throws java.io.IOException;
    Code:
       0: getstatic     #3                  // Field LOG:Lorg/slf4j/Logger;
       3: ldc           #141                // String Creating test table
       5: invokeinterface #142,  2          // InterfaceMethod org/slf4j/Logger.debug:(Ljava/lang/String;)V
      10: getstatic     #1                  // Field HTU:Lorg/apache/hadoop/hbase/HBaseTestingUtility;
      13: ldc           #143                // String testBulkLoad
      15: invokevirtual #44                 // Method org/apache/hadoop/hbase/HBaseTestingUtility.createTableDescriptor:(Ljava/lang/String;)Lorg/apache/hadoop/hbase/HTableDescriptor;
      18: astore_1
      19: aload_1
      20: iconst_3
      21: invokevirtual #45                 // Method org/apache/hadoop/hbase/HTableDescriptor.setRegionReplication:(I)Lorg/apache/hadoop/hbase/HTableDescriptor;
      24: pop
      25: aload_1
      26: ldc           #46                 // class org/apache/hadoop/hbase/client/TestReplicaWithCluster$SlowMeCopro
      28: invokevirtual #34                 // Method java/lang/Class.getName:()Ljava/lang/String;
      31: invokevirtual #47                 // Method org/apache/hadoop/hbase/HTableDescriptor.addCoprocessor:(Ljava/lang/String;)Lorg/apache/hadoop/hbase/HTableDescriptor;
      34: pop
      35: getstatic     #1                  // Field HTU:Lorg/apache/hadoop/hbase/HBaseTestingUtility;
      38: aload_1
      39: iconst_1
      40: anewarray     #48                 // class "[B"
      43: dup
      44: iconst_0
      45: getstatic     #49                 // Field f:[B
      48: aastore
      49: aconst_null
      50: invokevirtual #50                 // Method org/apache/hadoop/hbase/HBaseTestingUtility.createTable:(Lorg/apache/hadoop/hbase/client/TableDescriptor;[[BLorg/apache/hadoop/conf/Configuration;)Lorg/apache/hadoop/hbase/client/Table;
      53: astore_2
      54: getstatic     #3                  // Field LOG:Lorg/slf4j/Logger;
      57: ldc           #144                // String Creating test data
      59: invokeinterface #142,  2          // InterfaceMethod org/slf4j/Logger.debug:(Ljava/lang/String;)V
      64: getstatic     #1                  // Field HTU:Lorg/apache/hadoop/hbase/HBaseTestingUtility;
      67: ldc           #143                // String testBulkLoad
      69: invokevirtual #145                // Method org/apache/hadoop/hbase/HBaseTestingUtility.getDataTestDirOnTestFS:(Ljava/lang/String;)Lorg/apache/hadoop/fs/Path;
      72: astore_3
      73: bipush        10
      75: istore        4
      77: ldc           #146                // String qual
      79: invokestatic  #147                // Method org/apache/hadoop/hbase/util/Bytes.toBytes:(Ljava/lang/String;)[B
      82: astore        5
      84: ldc           #148                // String val
      86: invokestatic  #147                // Method org/apache/hadoop/hbase/util/Bytes.toBytes:(Ljava/lang/String;)[B
      89: astore        6
      91: new           #149                // class java/util/ArrayList
      94: dup
      95: invokespecial #150                // Method java/util/ArrayList."<init>":()V
      98: astore        7
     100: aload_1
     101: invokevirtual #151                // Method org/apache/hadoop/hbase/HTableDescriptor.getColumnFamilies:()[Lorg/apache/hadoop/hbase/HColumnDescriptor;
     104: astore        8
     106: aload         8
     108: arraylength
     109: istore        9
     111: iconst_0
     112: istore        10
     114: iload         10
     116: iload         9
     118: if_icmpge     196
     121: aload         8
     123: iload         10
     125: aaload
     126: astore        11
     128: new           #152                // class org/apache/hadoop/fs/Path
     131: dup
     132: aload_3
     133: aload         11
     135: invokevirtual #153                // Method org/apache/hadoop/hbase/HColumnDescriptor.getNameAsString:()Ljava/lang/String;
     138: invokespecial #154                // Method org/apache/hadoop/fs/Path."<init>":(Lorg/apache/hadoop/fs/Path;Ljava/lang/String;)V
     141: astore        12
     143: getstatic     #1                  // Field HTU:Lorg/apache/hadoop/hbase/HBaseTestingUtility;
     146: invokevirtual #155                // Method org/apache/hadoop/hbase/HBaseTestingUtility.getTestFileSystem:()Lorg/apache/hadoop/fs/FileSystem;
     149: aload         12
     151: aload         11
     153: invokevirtual #156                // Method org/apache/hadoop/hbase/HColumnDescriptor.getName:()[B
     156: aload         5
     158: aload         6
     160: bipush        10
     162: invokestatic  #157                // Method org/apache/hadoop/hbase/regionserver/TestHRegionServerBulkLoad.createHFile:(Lorg/apache/hadoop/fs/FileSystem;Lorg/apache/hadoop/fs/Path;[B[B[BI)V
     165: aload         7
     167: new           #158                // class org/apache/hadoop/hbase/util/Pair
     170: dup
     171: aload         11
     173: invokevirtual #156                // Method org/apache/hadoop/hbase/HColumnDescriptor.getName:()[B
     176: aload         12
     178: invokevirtual #159                // Method org/apache/hadoop/fs/Path.toString:()Ljava/lang/String;
     181: invokespecial #160                // Method org/apache/hadoop/hbase/util/Pair."<init>":(Ljava/lang/Object;Ljava/lang/Object;)V
     184: invokeinterface #161,  2          // InterfaceMethod java/util/List.add:(Ljava/lang/Object;)Z
     189: pop
     190: iinc          10, 1
     193: goto          114
     196: getstatic     #3                  // Field LOG:Lorg/slf4j/Logger;
     199: ldc           #162                // String Loading test data
     201: invokeinterface #142,  2          // InterfaceMethod org/slf4j/Logger.debug:(Ljava/lang/String;)V
     206: getstatic     #1                  // Field HTU:Lorg/apache/hadoop/hbase/HBaseTestingUtility;
     209: invokevirtual #71                 // Method org/apache/hadoop/hbase/HBaseTestingUtility.getAdmin:()Lorg/apache/hadoop/hbase/client/Admin;
     212: invokeinterface #163,  1          // InterfaceMethod org/apache/hadoop/hbase/client/Admin.getConnection:()Lorg/apache/hadoop/hbase/client/Connection;
     217: checkcast     #164                // class org/apache/hadoop/hbase/client/ClusterConnection
     220: astore        8
     222: aload         8
     224: aload_1
     225: invokevirtual #72                 // Method org/apache/hadoop/hbase/HTableDescriptor.getTableName:()Lorg/apache/hadoop/hbase/TableName;
     228: invokeinterface #165,  2          // InterfaceMethod org/apache/hadoop/hbase/client/ClusterConnection.getTable:(Lorg/apache/hadoop/hbase/TableName;)Lorg/apache/hadoop/hbase/client/Table;
     233: astore_2
     234: new           #166                // class org/apache/hadoop/hbase/client/SecureBulkLoadClient
     237: dup
     238: getstatic     #1                  // Field HTU:Lorg/apache/hadoop/hbase/HBaseTestingUtility;
     241: invokevirtual #5                  // Method org/apache/hadoop/hbase/HBaseTestingUtility.getConfiguration:()Lorg/apache/hadoop/conf/Configuration;
     244: aload_2
     245: invokespecial #167                // Method org/apache/hadoop/hbase/client/SecureBulkLoadClient."<init>":(Lorg/apache/hadoop/conf/Configuration;Lorg/apache/hadoop/hbase/client/Table;)V
     248: aload         8
     250: invokevirtual #168                // Method org/apache/hadoop/hbase/client/SecureBulkLoadClient.prepareBulkLoad:(Lorg/apache/hadoop/hbase/client/Connection;)Ljava/lang/String;
     253: astore        9
     255: new           #169                // class org/apache/hadoop/hbase/client/TestReplicaWithCluster$3
     258: dup
     259: aload_0
     260: aload         8
     262: aload_1
     263: invokevirtual #72                 // Method org/apache/hadoop/hbase/HTableDescriptor.getTableName:()Lorg/apache/hadoop/hbase/TableName;
     266: iconst_0
     267: invokestatic  #170                // Method org/apache/hadoop/hbase/regionserver/TestHRegionServerBulkLoad.rowkey:(I)[B
     270: new           #171                // class org/apache/hadoop/hbase/ipc/RpcControllerFactory
     273: dup
     274: getstatic     #1                  // Field HTU:Lorg/apache/hadoop/hbase/HBaseTestingUtility;
     277: invokevirtual #5                  // Method org/apache/hadoop/hbase/HBaseTestingUtility.getConfiguration:()Lorg/apache/hadoop/conf/Configuration;
     280: invokespecial #172                // Method org/apache/hadoop/hbase/ipc/RpcControllerFactory."<init>":(Lorg/apache/hadoop/conf/Configuration;)V
     283: invokevirtual #173                // Method org/apache/hadoop/hbase/ipc/RpcControllerFactory.newController:()Lorg/apache/hadoop/hbase/ipc/HBaseRpcController;
     286: iconst_m1
     287: aload         8
     289: aload         7
     291: aload         9
     293: invokespecial #174                // Method org/apache/hadoop/hbase/client/TestReplicaWithCluster$3."<init>":(Lorg/apache/hadoop/hbase/client/TestReplicaWithCluster;Lorg/apache/hadoop/hbase/client/Connection;Lorg/apache/hadoop/hbase/TableName;[BLorg/apache/hbase/thirdparty/com/google/protobuf/RpcController;ILorg/apache/hadoop/hbase/client/ClusterConnection;Ljava/util/List;Ljava/lang/String;)V
     296: astore        10
     298: new           #175                // class org/apache/hadoop/hbase/client/RpcRetryingCallerFactory
     301: dup
     302: getstatic     #1                  // Field HTU:Lorg/apache/hadoop/hbase/HBaseTestingUtility;
     305: invokevirtual #5                  // Method org/apache/hadoop/hbase/HBaseTestingUtility.getConfiguration:()Lorg/apache/hadoop/conf/Configuration;
     308: invokespecial #176                // Method org/apache/hadoop/hbase/client/RpcRetryingCallerFactory."<init>":(Lorg/apache/hadoop/conf/Configuration;)V
     311: astore        11
     313: aload         11
     315: invokevirtual #177                // Method org/apache/hadoop/hbase/client/RpcRetryingCallerFactory.newCaller:()Lorg/apache/hadoop/hbase/client/RpcRetryingCaller;
     318: astore        12
     320: aload         12
     322: aload         10
     324: sipush        10000
     327: invokeinterface #178,  3          // InterfaceMethod org/apache/hadoop/hbase/client/RpcRetryingCaller.callWithRetries:(Lorg/apache/hadoop/hbase/client/RetryingCallable;I)Ljava/lang/Object;
     332: pop
     333: getstatic     #3                  // Field LOG:Lorg/slf4j/Logger;
     336: ldc           #179                // String Verifying data load
     338: invokeinterface #142,  2          // InterfaceMethod org/slf4j/Logger.debug:(Ljava/lang/String;)V
     343: iconst_0
     344: istore        13
     346: iload         13
     348: bipush        10
     350: if_icmpge     395
     353: iload         13
     355: invokestatic  #170                // Method org/apache/hadoop/hbase/regionserver/TestHRegionServerBulkLoad.rowkey:(I)[B
     358: astore        14
     360: new           #55                 // class org/apache/hadoop/hbase/client/Get
     363: dup
     364: aload         14
     366: invokespecial #56                 // Method org/apache/hadoop/hbase/client/Get."<init>":([B)V
     369: astore        15
     371: aload_2
     372: aload         15
     374: invokeinterface #57,  2           // InterfaceMethod org/apache/hadoop/hbase/client/Table.get:(Lorg/apache/hadoop/hbase/client/Get;)Lorg/apache/hadoop/hbase/client/Result;
     379: astore        16
     381: aload         16
     383: invokevirtual #58                 // Method org/apache/hadoop/hbase/client/Result.isStale:()Z
     386: invokestatic  #59                 // Method org/junit/Assert.assertFalse:(Z)V
     389: iinc          13, 1
     392: goto          346
     395: getstatic     #3                  // Field LOG:Lorg/slf4j/Logger;
     398: ldc           #180                // String Verifying replica queries
     400: invokeinterface #142,  2          // InterfaceMethod org/slf4j/Logger.debug:(Ljava/lang/String;)V
     405: getstatic     #60                 // Field org/apache/hadoop/hbase/client/TestReplicaWithCluster$SlowMeCopro.cdl:Ljava/util/concurrent/atomic/AtomicReference;
     408: new           #61                 // class java/util/concurrent/CountDownLatch
     411: dup
     412: iconst_1
     413: invokespecial #62                 // Method java/util/concurrent/CountDownLatch."<init>":(I)V
     416: invokevirtual #63                 // Method java/util/concurrent/atomic/AtomicReference.set:(Ljava/lang/Object;)V
     419: iconst_0
     420: istore        13
     422: iload         13
     424: bipush        10
     426: if_icmpge     480
     429: iload         13
     431: invokestatic  #170                // Method org/apache/hadoop/hbase/regionserver/TestHRegionServerBulkLoad.rowkey:(I)[B
     434: astore        14
     436: new           #55                 // class org/apache/hadoop/hbase/client/Get
     439: dup
     440: aload         14
     442: invokespecial #56                 // Method org/apache/hadoop/hbase/client/Get."<init>":([B)V
     445: astore        15
     447: aload         15
     449: getstatic     #64                 // Field org/apache/hadoop/hbase/client/Consistency.TIMELINE:Lorg/apache/hadoop/hbase/client/Consistency;
     452: invokevirtual #65                 // Method org/apache/hadoop/hbase/client/Get.setConsistency:(Lorg/apache/hadoop/hbase/client/Consistency;)Lorg/apache/hadoop/hbase/client/Get;
     455: pop
     456: aload_2
     457: aload         15
     459: invokeinterface #57,  2           // InterfaceMethod org/apache/hadoop/hbase/client/Table.get:(Lorg/apache/hadoop/hbase/client/Get;)Lorg/apache/hadoop/hbase/client/Result;
     464: astore        16
     466: aload         16
     468: invokevirtual #58                 // Method org/apache/hadoop/hbase/client/Result.isStale:()Z
     471: invokestatic  #66                 // Method org/junit/Assert.assertTrue:(Z)V
     474: iinc          13, 1
     477: goto          422
     480: getstatic     #60                 // Field org/apache/hadoop/hbase/client/TestReplicaWithCluster$SlowMeCopro.cdl:Ljava/util/concurrent/atomic/AtomicReference;
     483: invokevirtual #67                 // Method java/util/concurrent/atomic/AtomicReference.get:()Ljava/lang/Object;
     486: checkcast     #61                 // class java/util/concurrent/CountDownLatch
     489: invokevirtual #68                 // Method java/util/concurrent/CountDownLatch.countDown:()V
     492: getstatic     #60                 // Field org/apache/hadoop/hbase/client/TestReplicaWithCluster$SlowMeCopro.cdl:Ljava/util/concurrent/atomic/AtomicReference;
     495: invokevirtual #67                 // Method java/util/concurrent/atomic/AtomicReference.get:()Ljava/lang/Object;
     498: checkcast     #61                 // class java/util/concurrent/CountDownLatch
     501: invokevirtual #68                 // Method java/util/concurrent/CountDownLatch.countDown:()V
     504: getstatic     #69                 // Field org/apache/hadoop/hbase/client/TestReplicaWithCluster$SlowMeCopro.sleepTime:Ljava/util/concurrent/atomic/AtomicLong;
     507: lconst_0
     508: invokevirtual #70                 // Method java/util/concurrent/atomic/AtomicLong.set:(J)V
     511: goto          538
     514: astore        17
     516: getstatic     #60                 // Field org/apache/hadoop/hbase/client/TestReplicaWithCluster$SlowMeCopro.cdl:Ljava/util/concurrent/atomic/AtomicReference;
     519: invokevirtual #67                 // Method java/util/concurrent/atomic/AtomicReference.get:()Ljava/lang/Object;
     522: checkcast     #61                 // class java/util/concurrent/CountDownLatch
     525: invokevirtual #68                 // Method java/util/concurrent/CountDownLatch.countDown:()V
     528: getstatic     #69                 // Field org/apache/hadoop/hbase/client/TestReplicaWithCluster$SlowMeCopro.sleepTime:Ljava/util/concurrent/atomic/AtomicLong;
     531: lconst_0
     532: invokevirtual #70                 // Method java/util/concurrent/atomic/AtomicLong.set:(J)V
     535: aload         17
     537: athrow
     538: getstatic     #1                  // Field HTU:Lorg/apache/hadoop/hbase/HBaseTestingUtility;
     541: invokevirtual #71                 // Method org/apache/hadoop/hbase/HBaseTestingUtility.getAdmin:()Lorg/apache/hadoop/hbase/client/Admin;
     544: aload_1
     545: invokevirtual #72                 // Method org/apache/hadoop/hbase/HTableDescriptor.getTableName:()Lorg/apache/hadoop/hbase/TableName;
     548: invokeinterface #73,  2           // InterfaceMethod org/apache/hadoop/hbase/client/Admin.disableTable:(Lorg/apache/hadoop/hbase/TableName;)V
     553: getstatic     #1                  // Field HTU:Lorg/apache/hadoop/hbase/HBaseTestingUtility;
     556: aload_1
     557: invokevirtual #72                 // Method org/apache/hadoop/hbase/HTableDescriptor.getTableName:()Lorg/apache/hadoop/hbase/TableName;
     560: invokevirtual #74                 // Method org/apache/hadoop/hbase/HBaseTestingUtility.deleteTable:(Lorg/apache/hadoop/hbase/TableName;)V
     563: return
    Exception table:
       from    to  target type
         405   492   514   any
         514   516   514   any

  public void testReplicaGetWithPrimaryDown() throws java.io.IOException;
    Code:
       0: getstatic     #1                  // Field HTU:Lorg/apache/hadoop/hbase/HBaseTestingUtility;
       3: ldc           #43                 // String testCreateDeleteTable
       5: invokevirtual #44                 // Method org/apache/hadoop/hbase/HBaseTestingUtility.createTableDescriptor:(Ljava/lang/String;)Lorg/apache/hadoop/hbase/HTableDescriptor;
       8: astore_1
       9: aload_1
      10: iconst_3
      11: invokevirtual #45                 // Method org/apache/hadoop/hbase/HTableDescriptor.setRegionReplication:(I)Lorg/apache/hadoop/hbase/HTableDescriptor;
      14: pop
      15: aload_1
      16: ldc           #181                // class org/apache/hadoop/hbase/client/TestReplicaWithCluster$RegionServerStoppedCopro
      18: invokevirtual #34                 // Method java/lang/Class.getName:()Ljava/lang/String;
      21: invokevirtual #47                 // Method org/apache/hadoop/hbase/HTableDescriptor.addCoprocessor:(Ljava/lang/String;)Lorg/apache/hadoop/hbase/HTableDescriptor;
      24: pop
      25: getstatic     #1                  // Field HTU:Lorg/apache/hadoop/hbase/HBaseTestingUtility;
      28: aload_1
      29: iconst_1
      30: anewarray     #48                 // class "[B"
      33: dup
      34: iconst_0
      35: getstatic     #49                 // Field f:[B
      38: aastore
      39: aconst_null
      40: invokevirtual #50                 // Method org/apache/hadoop/hbase/HBaseTestingUtility.createTable:(Lorg/apache/hadoop/hbase/client/TableDescriptor;[[BLorg/apache/hadoop/conf/Configuration;)Lorg/apache/hadoop/hbase/client/Table;
      43: astore_2
      44: new           #51                 // class org/apache/hadoop/hbase/client/Put
      47: dup
      48: getstatic     #2                  // Field row:[B
      51: invokespecial #52                 // Method org/apache/hadoop/hbase/client/Put."<init>":([B)V
      54: astore_3
      55: aload_3
      56: getstatic     #49                 // Field f:[B
      59: getstatic     #2                  // Field row:[B
      62: getstatic     #2                  // Field row:[B
      65: invokevirtual #53                 // Method org/apache/hadoop/hbase/client/Put.addColumn:([B[B[B)Lorg/apache/hadoop/hbase/client/Put;
      68: pop
      69: aload_2
      70: aload_3
      71: invokeinterface #54,  2           // InterfaceMethod org/apache/hadoop/hbase/client/Table.put:(Lorg/apache/hadoop/hbase/client/Put;)V
      76: getstatic     #1                  // Field HTU:Lorg/apache/hadoop/hbase/HBaseTestingUtility;
      79: aload_2
      80: invokeinterface #129,  1          // InterfaceMethod org/apache/hadoop/hbase/client/Table.getName:()Lorg/apache/hadoop/hbase/TableName;
      85: invokevirtual #182                // Method org/apache/hadoop/hbase/HBaseTestingUtility.flush:(Lorg/apache/hadoop/hbase/TableName;)V
      88: ldc2_w        #183                // long 2000l
      91: invokestatic  #185                // Method java/lang/Thread.sleep:(J)V
      94: goto          114
      97: astore        4
      99: getstatic     #3                  // Field LOG:Lorg/slf4j/Logger;
     102: aload         4
     104: invokevirtual #187                // Method java/lang/InterruptedException.toString:()Ljava/lang/String;
     107: aload         4
     109: invokeinterface #188,  3          // InterfaceMethod org/slf4j/Logger.error:(Ljava/lang/String;Ljava/lang/Throwable;)V
     114: new           #55                 // class org/apache/hadoop/hbase/client/Get
     117: dup
     118: getstatic     #2                  // Field row:[B
     121: invokespecial #56                 // Method org/apache/hadoop/hbase/client/Get."<init>":([B)V
     124: astore        4
     126: aload         4
     128: getstatic     #64                 // Field org/apache/hadoop/hbase/client/Consistency.TIMELINE:Lorg/apache/hadoop/hbase/client/Consistency;
     131: invokevirtual #65                 // Method org/apache/hadoop/hbase/client/Get.setConsistency:(Lorg/apache/hadoop/hbase/client/Consistency;)Lorg/apache/hadoop/hbase/client/Get;
     134: pop
     135: aload_2
     136: aload         4
     138: invokeinterface #57,  2           // InterfaceMethod org/apache/hadoop/hbase/client/Table.get:(Lorg/apache/hadoop/hbase/client/Get;)Lorg/apache/hadoop/hbase/client/Result;
     143: astore        5
     145: aload         5
     147: invokevirtual #58                 // Method org/apache/hadoop/hbase/client/Result.isStale:()Z
     150: invokestatic  #66                 // Method org/junit/Assert.assertTrue:(Z)V
     153: getstatic     #1                  // Field HTU:Lorg/apache/hadoop/hbase/HBaseTestingUtility;
     156: invokevirtual #71                 // Method org/apache/hadoop/hbase/HBaseTestingUtility.getAdmin:()Lorg/apache/hadoop/hbase/client/Admin;
     159: aload_1
     160: invokevirtual #72                 // Method org/apache/hadoop/hbase/HTableDescriptor.getTableName:()Lorg/apache/hadoop/hbase/TableName;
     163: invokeinterface #73,  2           // InterfaceMethod org/apache/hadoop/hbase/client/Admin.disableTable:(Lorg/apache/hadoop/hbase/TableName;)V
     168: getstatic     #1                  // Field HTU:Lorg/apache/hadoop/hbase/HBaseTestingUtility;
     171: aload_1
     172: invokevirtual #72                 // Method org/apache/hadoop/hbase/HTableDescriptor.getTableName:()Lorg/apache/hadoop/hbase/TableName;
     175: invokevirtual #74                 // Method org/apache/hadoop/hbase/HBaseTestingUtility.deleteTable:(Lorg/apache/hadoop/hbase/TableName;)V
     178: goto          211
     181: astore        6
     183: getstatic     #1                  // Field HTU:Lorg/apache/hadoop/hbase/HBaseTestingUtility;
     186: invokevirtual #71                 // Method org/apache/hadoop/hbase/HBaseTestingUtility.getAdmin:()Lorg/apache/hadoop/hbase/client/Admin;
     189: aload_1
     190: invokevirtual #72                 // Method org/apache/hadoop/hbase/HTableDescriptor.getTableName:()Lorg/apache/hadoop/hbase/TableName;
     193: invokeinterface #73,  2           // InterfaceMethod org/apache/hadoop/hbase/client/Admin.disableTable:(Lorg/apache/hadoop/hbase/TableName;)V
     198: getstatic     #1                  // Field HTU:Lorg/apache/hadoop/hbase/HBaseTestingUtility;
     201: aload_1
     202: invokevirtual #72                 // Method org/apache/hadoop/hbase/HTableDescriptor.getTableName:()Lorg/apache/hadoop/hbase/TableName;
     205: invokevirtual #74                 // Method org/apache/hadoop/hbase/HBaseTestingUtility.deleteTable:(Lorg/apache/hadoop/hbase/TableName;)V
     208: aload         6
     210: athrow
     211: return
    Exception table:
       from    to  target type
          88    94    97   Class java/lang/InterruptedException
          25   153   181   any
         181   183   181   any

  public void testReplicaScanWithPrimaryDown() throws java.io.IOException;
    Code:
       0: getstatic     #1                  // Field HTU:Lorg/apache/hadoop/hbase/HBaseTestingUtility;
       3: ldc           #43                 // String testCreateDeleteTable
       5: invokevirtual #44                 // Method org/apache/hadoop/hbase/HBaseTestingUtility.createTableDescriptor:(Ljava/lang/String;)Lorg/apache/hadoop/hbase/HTableDescriptor;
       8: astore_1
       9: aload_1
      10: iconst_3
      11: invokevirtual #45                 // Method org/apache/hadoop/hbase/HTableDescriptor.setRegionReplication:(I)Lorg/apache/hadoop/hbase/HTableDescriptor;
      14: pop
      15: aload_1
      16: ldc           #181                // class org/apache/hadoop/hbase/client/TestReplicaWithCluster$RegionServerStoppedCopro
      18: invokevirtual #34                 // Method java/lang/Class.getName:()Ljava/lang/String;
      21: invokevirtual #47                 // Method org/apache/hadoop/hbase/HTableDescriptor.addCoprocessor:(Ljava/lang/String;)Lorg/apache/hadoop/hbase/HTableDescriptor;
      24: pop
      25: getstatic     #1                  // Field HTU:Lorg/apache/hadoop/hbase/HBaseTestingUtility;
      28: aload_1
      29: iconst_1
      30: anewarray     #48                 // class "[B"
      33: dup
      34: iconst_0
      35: getstatic     #49                 // Field f:[B
      38: aastore
      39: aconst_null
      40: invokevirtual #50                 // Method org/apache/hadoop/hbase/HBaseTestingUtility.createTable:(Lorg/apache/hadoop/hbase/client/TableDescriptor;[[BLorg/apache/hadoop/conf/Configuration;)Lorg/apache/hadoop/hbase/client/Table;
      43: astore_2
      44: new           #51                 // class org/apache/hadoop/hbase/client/Put
      47: dup
      48: getstatic     #2                  // Field row:[B
      51: invokespecial #52                 // Method org/apache/hadoop/hbase/client/Put."<init>":([B)V
      54: astore_3
      55: aload_3
      56: getstatic     #49                 // Field f:[B
      59: getstatic     #2                  // Field row:[B
      62: getstatic     #2                  // Field row:[B
      65: invokevirtual #53                 // Method org/apache/hadoop/hbase/client/Put.addColumn:([B[B[B)Lorg/apache/hadoop/hbase/client/Put;
      68: pop
      69: aload_2
      70: aload_3
      71: invokeinterface #54,  2           // InterfaceMethod org/apache/hadoop/hbase/client/Table.put:(Lorg/apache/hadoop/hbase/client/Put;)V
      76: getstatic     #1                  // Field HTU:Lorg/apache/hadoop/hbase/HBaseTestingUtility;
      79: aload_2
      80: invokeinterface #129,  1          // InterfaceMethod org/apache/hadoop/hbase/client/Table.getName:()Lorg/apache/hadoop/hbase/TableName;
      85: invokevirtual #182                // Method org/apache/hadoop/hbase/HBaseTestingUtility.flush:(Lorg/apache/hadoop/hbase/TableName;)V
      88: ldc2_w        #183                // long 2000l
      91: invokestatic  #185                // Method java/lang/Thread.sleep:(J)V
      94: goto          114
      97: astore        4
      99: getstatic     #3                  // Field LOG:Lorg/slf4j/Logger;
     102: aload         4
     104: invokevirtual #187                // Method java/lang/InterruptedException.toString:()Ljava/lang/String;
     107: aload         4
     109: invokeinterface #188,  3          // InterfaceMethod org/slf4j/Logger.error:(Ljava/lang/String;Ljava/lang/Throwable;)V
     114: new           #189                // class org/apache/hadoop/hbase/client/Scan
     117: dup
     118: invokespecial #190                // Method org/apache/hadoop/hbase/client/Scan."<init>":()V
     121: astore        4
     123: aload         4
     125: getstatic     #49                 // Field f:[B
     128: invokevirtual #191                // Method org/apache/hadoop/hbase/client/Scan.addFamily:([B)Lorg/apache/hadoop/hbase/client/Scan;
     131: pop
     132: aload         4
     134: getstatic     #64                 // Field org/apache/hadoop/hbase/client/Consistency.TIMELINE:Lorg/apache/hadoop/hbase/client/Consistency;
     137: invokevirtual #192                // Method org/apache/hadoop/hbase/client/Scan.setConsistency:(Lorg/apache/hadoop/hbase/client/Consistency;)Lorg/apache/hadoop/hbase/client/Scan;
     140: pop
     141: aload_2
     142: aload         4
     144: invokeinterface #193,  2          // InterfaceMethod org/apache/hadoop/hbase/client/Table.getScanner:(Lorg/apache/hadoop/hbase/client/Scan;)Lorg/apache/hadoop/hbase/client/ResultScanner;
     149: astore        5
     151: aload         5
     153: invokeinterface #194,  1          // InterfaceMethod org/apache/hadoop/hbase/client/ResultScanner.next:()Lorg/apache/hadoop/hbase/client/Result;
     158: astore        6
     160: aload         6
     162: invokevirtual #58                 // Method org/apache/hadoop/hbase/client/Result.isStale:()Z
     165: invokestatic  #66                 // Method org/junit/Assert.assertTrue:(Z)V
     168: getstatic     #1                  // Field HTU:Lorg/apache/hadoop/hbase/HBaseTestingUtility;
     171: invokevirtual #71                 // Method org/apache/hadoop/hbase/HBaseTestingUtility.getAdmin:()Lorg/apache/hadoop/hbase/client/Admin;
     174: aload_1
     175: invokevirtual #72                 // Method org/apache/hadoop/hbase/HTableDescriptor.getTableName:()Lorg/apache/hadoop/hbase/TableName;
     178: invokeinterface #73,  2           // InterfaceMethod org/apache/hadoop/hbase/client/Admin.disableTable:(Lorg/apache/hadoop/hbase/TableName;)V
     183: getstatic     #1                  // Field HTU:Lorg/apache/hadoop/hbase/HBaseTestingUtility;
     186: aload_1
     187: invokevirtual #72                 // Method org/apache/hadoop/hbase/HTableDescriptor.getTableName:()Lorg/apache/hadoop/hbase/TableName;
     190: invokevirtual #74                 // Method org/apache/hadoop/hbase/HBaseTestingUtility.deleteTable:(Lorg/apache/hadoop/hbase/TableName;)V
     193: goto          226
     196: astore        7
     198: getstatic     #1                  // Field HTU:Lorg/apache/hadoop/hbase/HBaseTestingUtility;
     201: invokevirtual #71                 // Method org/apache/hadoop/hbase/HBaseTestingUtility.getAdmin:()Lorg/apache/hadoop/hbase/client/Admin;
     204: aload_1
     205: invokevirtual #72                 // Method org/apache/hadoop/hbase/HTableDescriptor.getTableName:()Lorg/apache/hadoop/hbase/TableName;
     208: invokeinterface #73,  2           // InterfaceMethod org/apache/hadoop/hbase/client/Admin.disableTable:(Lorg/apache/hadoop/hbase/TableName;)V
     213: getstatic     #1                  // Field HTU:Lorg/apache/hadoop/hbase/HBaseTestingUtility;
     216: aload_1
     217: invokevirtual #72                 // Method org/apache/hadoop/hbase/HTableDescriptor.getTableName:()Lorg/apache/hadoop/hbase/TableName;
     220: invokevirtual #74                 // Method org/apache/hadoop/hbase/HBaseTestingUtility.deleteTable:(Lorg/apache/hadoop/hbase/TableName;)V
     223: aload         7
     225: athrow
     226: return
    Exception table:
       from    to  target type
          88    94    97   Class java/lang/InterruptedException
          25   168   196   any
         196   198   196   any

  public void testReplicaGetWithRpcClientImpl() throws java.io.IOException;
    Code:
       0: getstatic     #1                  // Field HTU:Lorg/apache/hadoop/hbase/HBaseTestingUtility;
       3: invokevirtual #5                  // Method org/apache/hadoop/hbase/HBaseTestingUtility.getConfiguration:()Lorg/apache/hadoop/conf/Configuration;
       6: ldc           #195                // String hbase.ipc.client.specificThreadForWriting
       8: iconst_1
       9: invokevirtual #196                // Method org/apache/hadoop/conf/Configuration.setBoolean:(Ljava/lang/String;Z)V
      12: getstatic     #1                  // Field HTU:Lorg/apache/hadoop/hbase/HBaseTestingUtility;
      15: invokevirtual #5                  // Method org/apache/hadoop/hbase/HBaseTestingUtility.getConfiguration:()Lorg/apache/hadoop/conf/Configuration;
      18: ldc           #197                // String hbase.rpc.client.impl
      20: ldc           #198                // String org.apache.hadoop.hbase.ipc.RpcClientImpl
      22: invokevirtual #31                 // Method org/apache/hadoop/conf/Configuration.set:(Ljava/lang/String;Ljava/lang/String;)V
      25: getstatic     #1                  // Field HTU:Lorg/apache/hadoop/hbase/HBaseTestingUtility;
      28: ldc           #199                // String testReplicaGetWithRpcClientImpl
      30: invokevirtual #44                 // Method org/apache/hadoop/hbase/HBaseTestingUtility.createTableDescriptor:(Ljava/lang/String;)Lorg/apache/hadoop/hbase/HTableDescriptor;
      33: astore_1
      34: aload_1
      35: iconst_3
      36: invokevirtual #45                 // Method org/apache/hadoop/hbase/HTableDescriptor.setRegionReplication:(I)Lorg/apache/hadoop/hbase/HTableDescriptor;
      39: pop
      40: aload_1
      41: ldc           #46                 // class org/apache/hadoop/hbase/client/TestReplicaWithCluster$SlowMeCopro
      43: invokevirtual #34                 // Method java/lang/Class.getName:()Ljava/lang/String;
      46: invokevirtual #47                 // Method org/apache/hadoop/hbase/HTableDescriptor.addCoprocessor:(Ljava/lang/String;)Lorg/apache/hadoop/hbase/HTableDescriptor;
      49: pop
      50: getstatic     #1                  // Field HTU:Lorg/apache/hadoop/hbase/HBaseTestingUtility;
      53: aload_1
      54: iconst_1
      55: anewarray     #48                 // class "[B"
      58: dup
      59: iconst_0
      60: getstatic     #49                 // Field f:[B
      63: aastore
      64: aconst_null
      65: invokevirtual #50                 // Method org/apache/hadoop/hbase/HBaseTestingUtility.createTable:(Lorg/apache/hadoop/hbase/client/TableDescriptor;[[BLorg/apache/hadoop/conf/Configuration;)Lorg/apache/hadoop/hbase/client/Table;
      68: astore_2
      69: new           #51                 // class org/apache/hadoop/hbase/client/Put
      72: dup
      73: getstatic     #2                  // Field row:[B
      76: invokespecial #52                 // Method org/apache/hadoop/hbase/client/Put."<init>":([B)V
      79: astore_3
      80: aload_3
      81: getstatic     #49                 // Field f:[B
      84: getstatic     #2                  // Field row:[B
      87: getstatic     #2                  // Field row:[B
      90: invokevirtual #53                 // Method org/apache/hadoop/hbase/client/Put.addColumn:([B[B[B)Lorg/apache/hadoop/hbase/client/Put;
      93: pop
      94: aload_2
      95: aload_3
      96: invokeinterface #54,  2           // InterfaceMethod org/apache/hadoop/hbase/client/Table.put:(Lorg/apache/hadoop/hbase/client/Put;)V
     101: getstatic     #1                  // Field HTU:Lorg/apache/hadoop/hbase/HBaseTestingUtility;
     104: aload_2
     105: invokeinterface #129,  1          // InterfaceMethod org/apache/hadoop/hbase/client/Table.getName:()Lorg/apache/hadoop/hbase/TableName;
     110: invokevirtual #182                // Method org/apache/hadoop/hbase/HBaseTestingUtility.flush:(Lorg/apache/hadoop/hbase/TableName;)V
     113: ldc2_w        #183                // long 2000l
     116: invokestatic  #185                // Method java/lang/Thread.sleep:(J)V
     119: goto          139
     122: astore        4
     124: getstatic     #3                  // Field LOG:Lorg/slf4j/Logger;
     127: aload         4
     129: invokevirtual #187                // Method java/lang/InterruptedException.toString:()Ljava/lang/String;
     132: aload         4
     134: invokeinterface #188,  3          // InterfaceMethod org/slf4j/Logger.error:(Ljava/lang/String;Ljava/lang/Throwable;)V
     139: getstatic     #1                  // Field HTU:Lorg/apache/hadoop/hbase/HBaseTestingUtility;
     142: invokevirtual #5                  // Method org/apache/hadoop/hbase/HBaseTestingUtility.getConfiguration:()Lorg/apache/hadoop/conf/Configuration;
     145: invokestatic  #200                // Method org/apache/hadoop/hbase/client/ConnectionFactory.createConnection:(Lorg/apache/hadoop/conf/Configuration;)Lorg/apache/hadoop/hbase/client/Connection;
     148: astore        4
     150: aload         4
     152: aload_1
     153: invokevirtual #72                 // Method org/apache/hadoop/hbase/HTableDescriptor.getTableName:()Lorg/apache/hadoop/hbase/TableName;
     156: invokeinterface #86,  2           // InterfaceMethod org/apache/hadoop/hbase/client/Connection.getTable:(Lorg/apache/hadoop/hbase/TableName;)Lorg/apache/hadoop/hbase/client/Table;
     161: astore        5
     163: getstatic     #60                 // Field org/apache/hadoop/hbase/client/TestReplicaWithCluster$SlowMeCopro.cdl:Ljava/util/concurrent/atomic/AtomicReference;
     166: new           #61                 // class java/util/concurrent/CountDownLatch
     169: dup
     170: iconst_1
     171: invokespecial #62                 // Method java/util/concurrent/CountDownLatch."<init>":(I)V
     174: invokevirtual #63                 // Method java/util/concurrent/atomic/AtomicReference.set:(Ljava/lang/Object;)V
     177: new           #55                 // class org/apache/hadoop/hbase/client/Get
     180: dup
     181: getstatic     #2                  // Field row:[B
     184: invokespecial #56                 // Method org/apache/hadoop/hbase/client/Get."<init>":([B)V
     187: astore        6
     189: aload         6
     191: getstatic     #64                 // Field org/apache/hadoop/hbase/client/Consistency.TIMELINE:Lorg/apache/hadoop/hbase/client/Consistency;
     194: invokevirtual #65                 // Method org/apache/hadoop/hbase/client/Get.setConsistency:(Lorg/apache/hadoop/hbase/client/Consistency;)Lorg/apache/hadoop/hbase/client/Get;
     197: pop
     198: aload         5
     200: aload         6
     202: invokeinterface #57,  2           // InterfaceMethod org/apache/hadoop/hbase/client/Table.get:(Lorg/apache/hadoop/hbase/client/Get;)Lorg/apache/hadoop/hbase/client/Result;
     207: astore        7
     209: aload         7
     211: invokevirtual #58                 // Method org/apache/hadoop/hbase/client/Result.isStale:()Z
     214: invokestatic  #66                 // Method org/junit/Assert.assertTrue:(Z)V
     217: getstatic     #60                 // Field org/apache/hadoop/hbase/client/TestReplicaWithCluster$SlowMeCopro.cdl:Ljava/util/concurrent/atomic/AtomicReference;
     220: invokevirtual #67                 // Method java/util/concurrent/atomic/AtomicReference.get:()Ljava/lang/Object;
     223: checkcast     #61                 // class java/util/concurrent/CountDownLatch
     226: invokevirtual #68                 // Method java/util/concurrent/CountDownLatch.countDown:()V
     229: getstatic     #60                 // Field org/apache/hadoop/hbase/client/TestReplicaWithCluster$SlowMeCopro.cdl:Ljava/util/concurrent/atomic/AtomicReference;
     232: invokevirtual #67                 // Method java/util/concurrent/atomic/AtomicReference.get:()Ljava/lang/Object;
     235: checkcast     #61                 // class java/util/concurrent/CountDownLatch
     238: invokevirtual #68                 // Method java/util/concurrent/CountDownLatch.countDown:()V
     241: getstatic     #69                 // Field org/apache/hadoop/hbase/client/TestReplicaWithCluster$SlowMeCopro.sleepTime:Ljava/util/concurrent/atomic/AtomicLong;
     244: lconst_0
     245: invokevirtual #70                 // Method java/util/concurrent/atomic/AtomicLong.set:(J)V
     248: goto          275
     251: astore        8
     253: getstatic     #60                 // Field org/apache/hadoop/hbase/client/TestReplicaWithCluster$SlowMeCopro.cdl:Ljava/util/concurrent/atomic/AtomicReference;
     256: invokevirtual #67                 // Method java/util/concurrent/atomic/AtomicReference.get:()Ljava/lang/Object;
     259: checkcast     #61                 // class java/util/concurrent/CountDownLatch
     262: invokevirtual #68                 // Method java/util/concurrent/CountDownLatch.countDown:()V
     265: getstatic     #69                 // Field org/apache/hadoop/hbase/client/TestReplicaWithCluster$SlowMeCopro.sleepTime:Ljava/util/concurrent/atomic/AtomicLong;
     268: lconst_0
     269: invokevirtual #70                 // Method java/util/concurrent/atomic/AtomicLong.set:(J)V
     272: aload         8
     274: athrow
     275: getstatic     #1                  // Field HTU:Lorg/apache/hadoop/hbase/HBaseTestingUtility;
     278: invokevirtual #5                  // Method org/apache/hadoop/hbase/HBaseTestingUtility.getConfiguration:()Lorg/apache/hadoop/conf/Configuration;
     281: ldc           #195                // String hbase.ipc.client.specificThreadForWriting
     283: invokevirtual #201                // Method org/apache/hadoop/conf/Configuration.unset:(Ljava/lang/String;)V
     286: getstatic     #1                  // Field HTU:Lorg/apache/hadoop/hbase/HBaseTestingUtility;
     289: invokevirtual #5                  // Method org/apache/hadoop/hbase/HBaseTestingUtility.getConfiguration:()Lorg/apache/hadoop/conf/Configuration;
     292: ldc           #197                // String hbase.rpc.client.impl
     294: invokevirtual #201                // Method org/apache/hadoop/conf/Configuration.unset:(Ljava/lang/String;)V
     297: getstatic     #1                  // Field HTU:Lorg/apache/hadoop/hbase/HBaseTestingUtility;
     300: invokevirtual #71                 // Method org/apache/hadoop/hbase/HBaseTestingUtility.getAdmin:()Lorg/apache/hadoop/hbase/client/Admin;
     303: aload_1
     304: invokevirtual #72                 // Method org/apache/hadoop/hbase/HTableDescriptor.getTableName:()Lorg/apache/hadoop/hbase/TableName;
     307: invokeinterface #73,  2           // InterfaceMethod org/apache/hadoop/hbase/client/Admin.disableTable:(Lorg/apache/hadoop/hbase/TableName;)V
     312: getstatic     #1                  // Field HTU:Lorg/apache/hadoop/hbase/HBaseTestingUtility;
     315: aload_1
     316: invokevirtual #72                 // Method org/apache/hadoop/hbase/HTableDescriptor.getTableName:()Lorg/apache/hadoop/hbase/TableName;
     319: invokevirtual #74                 // Method org/apache/hadoop/hbase/HBaseTestingUtility.deleteTable:(Lorg/apache/hadoop/hbase/TableName;)V
     322: goto          377
     325: astore        9
     327: getstatic     #1                  // Field HTU:Lorg/apache/hadoop/hbase/HBaseTestingUtility;
     330: invokevirtual #5                  // Method org/apache/hadoop/hbase/HBaseTestingUtility.getConfiguration:()Lorg/apache/hadoop/conf/Configuration;
     333: ldc           #195                // String hbase.ipc.client.specificThreadForWriting
     335: invokevirtual #201                // Method org/apache/hadoop/conf/Configuration.unset:(Ljava/lang/String;)V
     338: getstatic     #1                  // Field HTU:Lorg/apache/hadoop/hbase/HBaseTestingUtility;
     341: invokevirtual #5                  // Method org/apache/hadoop/hbase/HBaseTestingUtility.getConfiguration:()Lorg/apache/hadoop/conf/Configuration;
     344: ldc           #197                // String hbase.rpc.client.impl
     346: invokevirtual #201                // Method org/apache/hadoop/conf/Configuration.unset:(Ljava/lang/String;)V
     349: getstatic     #1                  // Field HTU:Lorg/apache/hadoop/hbase/HBaseTestingUtility;
     352: invokevirtual #71                 // Method org/apache/hadoop/hbase/HBaseTestingUtility.getAdmin:()Lorg/apache/hadoop/hbase/client/Admin;
     355: aload_1
     356: invokevirtual #72                 // Method org/apache/hadoop/hbase/HTableDescriptor.getTableName:()Lorg/apache/hadoop/hbase/TableName;
     359: invokeinterface #73,  2           // InterfaceMethod org/apache/hadoop/hbase/client/Admin.disableTable:(Lorg/apache/hadoop/hbase/TableName;)V
     364: getstatic     #1                  // Field HTU:Lorg/apache/hadoop/hbase/HBaseTestingUtility;
     367: aload_1
     368: invokevirtual #72                 // Method org/apache/hadoop/hbase/HTableDescriptor.getTableName:()Lorg/apache/hadoop/hbase/TableName;
     371: invokevirtual #74                 // Method org/apache/hadoop/hbase/HBaseTestingUtility.deleteTable:(Lorg/apache/hadoop/hbase/TableName;)V
     374: aload         9
     376: athrow
     377: return
    Exception table:
       from    to  target type
         113   119   122   Class java/lang/InterruptedException
         139   229   251   any
         251   253   251   any
          50   275   325   any
         325   327   325   any

  public void testGetRegionLocationFromPrimaryMetaRegion() throws java.io.IOException, java.lang.InterruptedException;
    Code:
       0: getstatic     #1                  // Field HTU:Lorg/apache/hadoop/hbase/HBaseTestingUtility;
       3: invokevirtual #71                 // Method org/apache/hadoop/hbase/HBaseTestingUtility.getAdmin:()Lorg/apache/hadoop/hbase/client/Admin;
       6: iconst_0
       7: iconst_1
       8: invokeinterface #202,  3          // InterfaceMethod org/apache/hadoop/hbase/client/Admin.balancerSwitch:(ZZ)Z
      13: pop
      14: getstatic     #1                  // Field HTU:Lorg/apache/hadoop/hbase/HBaseTestingUtility;
      17: invokevirtual #71                 // Method org/apache/hadoop/hbase/HBaseTestingUtility.getAdmin:()Lorg/apache/hadoop/hbase/client/Admin;
      20: invokeinterface #163,  1          // InterfaceMethod org/apache/hadoop/hbase/client/Admin.getConnection:()Lorg/apache/hadoop/hbase/client/Connection;
      25: checkcast     #203                // class org/apache/hadoop/hbase/client/ConnectionImplementation
      28: iconst_1
      29: invokevirtual #204                // Method org/apache/hadoop/hbase/client/ConnectionImplementation.setUseMetaReplicas:(Z)V
      32: getstatic     #1                  // Field HTU:Lorg/apache/hadoop/hbase/HBaseTestingUtility;
      35: ldc           #205                // String testGetRegionLocationFromPrimaryMetaRegion
      37: invokevirtual #44                 // Method org/apache/hadoop/hbase/HBaseTestingUtility.createTableDescriptor:(Ljava/lang/String;)Lorg/apache/hadoop/hbase/HTableDescriptor;
      40: astore_1
      41: aload_1
      42: iconst_2
      43: invokevirtual #45                 // Method org/apache/hadoop/hbase/HTableDescriptor.setRegionReplication:(I)Lorg/apache/hadoop/hbase/HTableDescriptor;
      46: pop
      47: getstatic     #1                  // Field HTU:Lorg/apache/hadoop/hbase/HBaseTestingUtility;
      50: aload_1
      51: iconst_1
      52: anewarray     #48                 // class "[B"
      55: dup
      56: iconst_0
      57: getstatic     #49                 // Field f:[B
      60: aastore
      61: aconst_null
      62: invokevirtual #50                 // Method org/apache/hadoop/hbase/HBaseTestingUtility.createTable:(Lorg/apache/hadoop/hbase/client/TableDescriptor;[[BLorg/apache/hadoop/conf/Configuration;)Lorg/apache/hadoop/hbase/client/Table;
      65: pop
      66: iconst_1
      67: putstatic     #206                // Field org/apache/hadoop/hbase/client/TestReplicaWithCluster$RegionServerHostingPrimayMetaRegionSlowOrStopCopro.slowDownPrimaryMetaScan:Z
      70: getstatic     #1                  // Field HTU:Lorg/apache/hadoop/hbase/HBaseTestingUtility;
      73: invokevirtual #84                 // Method org/apache/hadoop/hbase/HBaseTestingUtility.getConnection:()Lorg/apache/hadoop/hbase/client/Connection;
      76: checkcast     #164                // class org/apache/hadoop/hbase/client/ClusterConnection
      79: aload_1
      80: invokevirtual #72                 // Method org/apache/hadoop/hbase/HTableDescriptor.getTableName:()Lorg/apache/hadoop/hbase/TableName;
      83: getstatic     #2                  // Field row:[B
      86: iconst_0
      87: iconst_0
      88: invokeinterface #207,  5          // InterfaceMethod org/apache/hadoop/hbase/client/ClusterConnection.locateRegion:(Lorg/apache/hadoop/hbase/TableName;[BZZ)Lorg/apache/hadoop/hbase/RegionLocations;
      93: astore_2
      94: iconst_0
      95: putstatic     #206                // Field org/apache/hadoop/hbase/client/TestReplicaWithCluster$RegionServerHostingPrimayMetaRegionSlowOrStopCopro.slowDownPrimaryMetaScan:Z
      98: getstatic     #1                  // Field HTU:Lorg/apache/hadoop/hbase/HBaseTestingUtility;
     101: invokevirtual #71                 // Method org/apache/hadoop/hbase/HBaseTestingUtility.getAdmin:()Lorg/apache/hadoop/hbase/client/Admin;
     104: invokeinterface #163,  1          // InterfaceMethod org/apache/hadoop/hbase/client/Admin.getConnection:()Lorg/apache/hadoop/hbase/client/Connection;
     109: checkcast     #203                // class org/apache/hadoop/hbase/client/ConnectionImplementation
     112: iconst_0
     113: invokevirtual #204                // Method org/apache/hadoop/hbase/client/ConnectionImplementation.setUseMetaReplicas:(Z)V
     116: getstatic     #1                  // Field HTU:Lorg/apache/hadoop/hbase/HBaseTestingUtility;
     119: invokevirtual #71                 // Method org/apache/hadoop/hbase/HBaseTestingUtility.getAdmin:()Lorg/apache/hadoop/hbase/client/Admin;
     122: iconst_1
     123: iconst_1
     124: invokeinterface #202,  3          // InterfaceMethod org/apache/hadoop/hbase/client/Admin.balancerSwitch:(ZZ)Z
     129: pop
     130: getstatic     #1                  // Field HTU:Lorg/apache/hadoop/hbase/HBaseTestingUtility;
     133: invokevirtual #71                 // Method org/apache/hadoop/hbase/HBaseTestingUtility.getAdmin:()Lorg/apache/hadoop/hbase/client/Admin;
     136: aload_1
     137: invokevirtual #72                 // Method org/apache/hadoop/hbase/HTableDescriptor.getTableName:()Lorg/apache/hadoop/hbase/TableName;
     140: invokeinterface #73,  2           // InterfaceMethod org/apache/hadoop/hbase/client/Admin.disableTable:(Lorg/apache/hadoop/hbase/TableName;)V
     145: getstatic     #1                  // Field HTU:Lorg/apache/hadoop/hbase/HBaseTestingUtility;
     148: aload_1
     149: invokevirtual #72                 // Method org/apache/hadoop/hbase/HTableDescriptor.getTableName:()Lorg/apache/hadoop/hbase/TableName;
     152: invokevirtual #74                 // Method org/apache/hadoop/hbase/HBaseTestingUtility.deleteTable:(Lorg/apache/hadoop/hbase/TableName;)V
     155: goto          222
     158: astore_3
     159: iconst_0
     160: putstatic     #206                // Field org/apache/hadoop/hbase/client/TestReplicaWithCluster$RegionServerHostingPrimayMetaRegionSlowOrStopCopro.slowDownPrimaryMetaScan:Z
     163: getstatic     #1                  // Field HTU:Lorg/apache/hadoop/hbase/HBaseTestingUtility;
     166: invokevirtual #71                 // Method org/apache/hadoop/hbase/HBaseTestingUtility.getAdmin:()Lorg/apache/hadoop/hbase/client/Admin;
     169: invokeinterface #163,  1          // InterfaceMethod org/apache/hadoop/hbase/client/Admin.getConnection:()Lorg/apache/hadoop/hbase/client/Connection;
     174: checkcast     #203                // class org/apache/hadoop/hbase/client/ConnectionImplementation
     177: iconst_0
     178: invokevirtual #204                // Method org/apache/hadoop/hbase/client/ConnectionImplementation.setUseMetaReplicas:(Z)V
     181: getstatic     #1                  // Field HTU:Lorg/apache/hadoop/hbase/HBaseTestingUtility;
     184: invokevirtual #71                 // Method org/apache/hadoop/hbase/HBaseTestingUtility.getAdmin:()Lorg/apache/hadoop/hbase/client/Admin;
     187: iconst_1
     188: iconst_1
     189: invokeinterface #202,  3          // InterfaceMethod org/apache/hadoop/hbase/client/Admin.balancerSwitch:(ZZ)Z
     194: pop
     195: getstatic     #1                  // Field HTU:Lorg/apache/hadoop/hbase/HBaseTestingUtility;
     198: invokevirtual #71                 // Method org/apache/hadoop/hbase/HBaseTestingUtility.getAdmin:()Lorg/apache/hadoop/hbase/client/Admin;
     201: aload_1
     202: invokevirtual #72                 // Method org/apache/hadoop/hbase/HTableDescriptor.getTableName:()Lorg/apache/hadoop/hbase/TableName;
     205: invokeinterface #73,  2           // InterfaceMethod org/apache/hadoop/hbase/client/Admin.disableTable:(Lorg/apache/hadoop/hbase/TableName;)V
     210: getstatic     #1                  // Field HTU:Lorg/apache/hadoop/hbase/HBaseTestingUtility;
     213: aload_1
     214: invokevirtual #72                 // Method org/apache/hadoop/hbase/HTableDescriptor.getTableName:()Lorg/apache/hadoop/hbase/TableName;
     217: invokevirtual #74                 // Method org/apache/hadoop/hbase/HBaseTestingUtility.deleteTable:(Lorg/apache/hadoop/hbase/TableName;)V
     220: aload_3
     221: athrow
     222: return
    Exception table:
       from    to  target type
          47    94   158   any

  public void testReplicaGetWithPrimaryAndMetaDown() throws java.io.IOException, java.lang.InterruptedException;
    Code:
       0: getstatic     #1                  // Field HTU:Lorg/apache/hadoop/hbase/HBaseTestingUtility;
       3: invokevirtual #71                 // Method org/apache/hadoop/hbase/HBaseTestingUtility.getAdmin:()Lorg/apache/hadoop/hbase/client/Admin;
       6: iconst_0
       7: iconst_1
       8: invokeinterface #202,  3          // InterfaceMethod org/apache/hadoop/hbase/client/Admin.balancerSwitch:(ZZ)Z
      13: pop
      14: getstatic     #1                  // Field HTU:Lorg/apache/hadoop/hbase/HBaseTestingUtility;
      17: invokevirtual #71                 // Method org/apache/hadoop/hbase/HBaseTestingUtility.getAdmin:()Lorg/apache/hadoop/hbase/client/Admin;
      20: invokeinterface #163,  1          // InterfaceMethod org/apache/hadoop/hbase/client/Admin.getConnection:()Lorg/apache/hadoop/hbase/client/Connection;
      25: checkcast     #203                // class org/apache/hadoop/hbase/client/ConnectionImplementation
      28: iconst_1
      29: invokevirtual #204                // Method org/apache/hadoop/hbase/client/ConnectionImplementation.setUseMetaReplicas:(Z)V
      32: getstatic     #1                  // Field HTU:Lorg/apache/hadoop/hbase/HBaseTestingUtility;
      35: ldc           #208                // String testReplicaGetWithPrimaryAndMetaDown
      37: invokevirtual #44                 // Method org/apache/hadoop/hbase/HBaseTestingUtility.createTableDescriptor:(Ljava/lang/String;)Lorg/apache/hadoop/hbase/HTableDescriptor;
      40: astore_1
      41: aload_1
      42: iconst_2
      43: invokevirtual #45                 // Method org/apache/hadoop/hbase/HTableDescriptor.setRegionReplication:(I)Lorg/apache/hadoop/hbase/HTableDescriptor;
      46: pop
      47: getstatic     #1                  // Field HTU:Lorg/apache/hadoop/hbase/HBaseTestingUtility;
      50: aload_1
      51: iconst_1
      52: anewarray     #48                 // class "[B"
      55: dup
      56: iconst_0
      57: getstatic     #49                 // Field f:[B
      60: aastore
      61: aconst_null
      62: invokevirtual #50                 // Method org/apache/hadoop/hbase/HBaseTestingUtility.createTable:(Lorg/apache/hadoop/hbase/client/TableDescriptor;[[BLorg/apache/hadoop/conf/Configuration;)Lorg/apache/hadoop/hbase/client/Table;
      65: astore_2
      66: getstatic     #1                  // Field HTU:Lorg/apache/hadoop/hbase/HBaseTestingUtility;
      69: invokevirtual #84                 // Method org/apache/hadoop/hbase/HBaseTestingUtility.getConnection:()Lorg/apache/hadoop/hbase/client/Connection;
      72: checkcast     #164                // class org/apache/hadoop/hbase/client/ClusterConnection
      75: getstatic     #209                // Field org/apache/hadoop/hbase/TableName.META_TABLE_NAME:Lorg/apache/hadoop/hbase/TableName;
      78: getstatic     #210                // Field org/apache/hadoop/hbase/HConstants.EMPTY_START_ROW:[B
      81: iconst_0
      82: iconst_0
      83: invokeinterface #207,  5          // InterfaceMethod org/apache/hadoop/hbase/client/ClusterConnection.locateRegion:(Lorg/apache/hadoop/hbase/TableName;[BZZ)Lorg/apache/hadoop/hbase/RegionLocations;
      88: astore_3
      89: getstatic     #1                  // Field HTU:Lorg/apache/hadoop/hbase/HBaseTestingUtility;
      92: invokevirtual #84                 // Method org/apache/hadoop/hbase/HBaseTestingUtility.getConnection:()Lorg/apache/hadoop/hbase/client/Connection;
      95: checkcast     #164                // class org/apache/hadoop/hbase/client/ClusterConnection
      98: aload_1
      99: invokevirtual #72                 // Method org/apache/hadoop/hbase/HTableDescriptor.getTableName:()Lorg/apache/hadoop/hbase/TableName;
     102: getstatic     #2                  // Field row:[B
     105: iconst_0
     106: iconst_0
     107: invokeinterface #207,  5          // InterfaceMethod org/apache/hadoop/hbase/client/ClusterConnection.locateRegion:(Lorg/apache/hadoop/hbase/TableName;[BZZ)Lorg/apache/hadoop/hbase/RegionLocations;
     112: astore        4
     114: aload         4
     116: invokevirtual #211                // Method org/apache/hadoop/hbase/RegionLocations.getDefaultRegionLocation:()Lorg/apache/hadoop/hbase/HRegionLocation;
     119: invokevirtual #212                // Method org/apache/hadoop/hbase/HRegionLocation.getServerName:()Lorg/apache/hadoop/hbase/ServerName;
     122: aload_3
     123: invokevirtual #211                // Method org/apache/hadoop/hbase/RegionLocations.getDefaultRegionLocation:()Lorg/apache/hadoop/hbase/HRegionLocation;
     126: invokevirtual #212                // Method org/apache/hadoop/hbase/HRegionLocation.getServerName:()Lorg/apache/hadoop/hbase/ServerName;
     129: invokevirtual #213                // Method org/apache/hadoop/hbase/ServerName.equals:(Ljava/lang/Object;)Z
     132: ifne          156
     135: getstatic     #1                  // Field HTU:Lorg/apache/hadoop/hbase/HBaseTestingUtility;
     138: aload         4
     140: invokevirtual #211                // Method org/apache/hadoop/hbase/RegionLocations.getDefaultRegionLocation:()Lorg/apache/hadoop/hbase/HRegionLocation;
     143: invokevirtual #214                // Method org/apache/hadoop/hbase/HRegionLocation.getRegionInfo:()Lorg/apache/hadoop/hbase/HRegionInfo;
     146: aload_3
     147: invokevirtual #211                // Method org/apache/hadoop/hbase/RegionLocations.getDefaultRegionLocation:()Lorg/apache/hadoop/hbase/HRegionLocation;
     150: invokevirtual #212                // Method org/apache/hadoop/hbase/HRegionLocation.getServerName:()Lorg/apache/hadoop/hbase/ServerName;
     153: invokevirtual #215                // Method org/apache/hadoop/hbase/HBaseTestingUtility.moveRegionAndWait:(Lorg/apache/hadoop/hbase/client/RegionInfo;Lorg/apache/hadoop/hbase/ServerName;)V
     156: aload         4
     158: iconst_1
     159: invokevirtual #216                // Method org/apache/hadoop/hbase/RegionLocations.getRegionLocation:(I)Lorg/apache/hadoop/hbase/HRegionLocation;
     162: invokevirtual #212                // Method org/apache/hadoop/hbase/HRegionLocation.getServerName:()Lorg/apache/hadoop/hbase/ServerName;
     165: aload_3
     166: invokevirtual #211                // Method org/apache/hadoop/hbase/RegionLocations.getDefaultRegionLocation:()Lorg/apache/hadoop/hbase/HRegionLocation;
     169: invokevirtual #212                // Method org/apache/hadoop/hbase/HRegionLocation.getServerName:()Lorg/apache/hadoop/hbase/ServerName;
     172: invokevirtual #213                // Method org/apache/hadoop/hbase/ServerName.equals:(Ljava/lang/Object;)Z
     175: ifeq          201
     178: getstatic     #1                  // Field HTU:Lorg/apache/hadoop/hbase/HBaseTestingUtility;
     181: aload         4
     183: iconst_1
     184: invokevirtual #216                // Method org/apache/hadoop/hbase/RegionLocations.getRegionLocation:(I)Lorg/apache/hadoop/hbase/HRegionLocation;
     187: invokevirtual #214                // Method org/apache/hadoop/hbase/HRegionLocation.getRegionInfo:()Lorg/apache/hadoop/hbase/HRegionInfo;
     190: aload         4
     192: invokevirtual #211                // Method org/apache/hadoop/hbase/RegionLocations.getDefaultRegionLocation:()Lorg/apache/hadoop/hbase/HRegionLocation;
     195: invokevirtual #212                // Method org/apache/hadoop/hbase/HRegionLocation.getServerName:()Lorg/apache/hadoop/hbase/ServerName;
     198: invokevirtual #215                // Method org/apache/hadoop/hbase/HBaseTestingUtility.moveRegionAndWait:(Lorg/apache/hadoop/hbase/client/RegionInfo;Lorg/apache/hadoop/hbase/ServerName;)V
     201: getstatic     #1                  // Field HTU:Lorg/apache/hadoop/hbase/HBaseTestingUtility;
     204: invokevirtual #84                 // Method org/apache/hadoop/hbase/HBaseTestingUtility.getConnection:()Lorg/apache/hadoop/hbase/client/Connection;
     207: checkcast     #164                // class org/apache/hadoop/hbase/client/ClusterConnection
     210: getstatic     #209                // Field org/apache/hadoop/hbase/TableName.META_TABLE_NAME:Lorg/apache/hadoop/hbase/TableName;
     213: getstatic     #210                // Field org/apache/hadoop/hbase/HConstants.EMPTY_START_ROW:[B
     216: iconst_0
     217: iconst_0
     218: invokeinterface #207,  5          // InterfaceMethod org/apache/hadoop/hbase/client/ClusterConnection.locateRegion:(Lorg/apache/hadoop/hbase/TableName;[BZZ)Lorg/apache/hadoop/hbase/RegionLocations;
     223: astore_3
     224: getstatic     #1                  // Field HTU:Lorg/apache/hadoop/hbase/HBaseTestingUtility;
     227: invokevirtual #84                 // Method org/apache/hadoop/hbase/HBaseTestingUtility.getConnection:()Lorg/apache/hadoop/hbase/client/Connection;
     230: checkcast     #164                // class org/apache/hadoop/hbase/client/ClusterConnection
     233: aload_1
     234: invokevirtual #72                 // Method org/apache/hadoop/hbase/HTableDescriptor.getTableName:()Lorg/apache/hadoop/hbase/TableName;
     237: getstatic     #2                  // Field row:[B
     240: iconst_0
     241: iconst_1
     242: invokeinterface #207,  5          // InterfaceMethod org/apache/hadoop/hbase/client/ClusterConnection.locateRegion:(Lorg/apache/hadoop/hbase/TableName;[BZZ)Lorg/apache/hadoop/hbase/RegionLocations;
     247: astore        4
     249: getstatic     #3                  // Field LOG:Lorg/slf4j/Logger;
     252: new           #91                 // class java/lang/StringBuilder
     255: dup
     256: invokespecial #92                 // Method java/lang/StringBuilder."<init>":()V
     259: ldc           #217                // String meta locations
     261: invokevirtual #94                 // Method java/lang/StringBuilder.append:(Ljava/lang/String;)Ljava/lang/StringBuilder;
     264: aload_3
     265: invokevirtual #218                // Method java/lang/StringBuilder.append:(Ljava/lang/Object;)Ljava/lang/StringBuilder;
     268: invokevirtual #97                 // Method java/lang/StringBuilder.toString:()Ljava/lang/String;
     271: invokeinterface #119,  2          // InterfaceMethod org/slf4j/Logger.info:(Ljava/lang/String;)V
     276: getstatic     #3                  // Field LOG:Lorg/slf4j/Logger;
     279: new           #91                 // class java/lang/StringBuilder
     282: dup
     283: invokespecial #92                 // Method java/lang/StringBuilder."<init>":()V
     286: ldc           #219                // String table locations
     288: invokevirtual #94                 // Method java/lang/StringBuilder.append:(Ljava/lang/String;)Ljava/lang/StringBuilder;
     291: aload         4
     293: invokevirtual #218                // Method java/lang/StringBuilder.append:(Ljava/lang/Object;)Ljava/lang/StringBuilder;
     296: invokevirtual #97                 // Method java/lang/StringBuilder.toString:()Ljava/lang/String;
     299: invokeinterface #119,  2          // InterfaceMethod org/slf4j/Logger.info:(Ljava/lang/String;)V
     304: aload         4
     306: invokevirtual #211                // Method org/apache/hadoop/hbase/RegionLocations.getDefaultRegionLocation:()Lorg/apache/hadoop/hbase/HRegionLocation;
     309: invokevirtual #212                // Method org/apache/hadoop/hbase/HRegionLocation.getServerName:()Lorg/apache/hadoop/hbase/ServerName;
     312: astore        5
     314: aload_3
     315: invokevirtual #211                // Method org/apache/hadoop/hbase/RegionLocations.getDefaultRegionLocation:()Lorg/apache/hadoop/hbase/HRegionLocation;
     318: invokevirtual #212                // Method org/apache/hadoop/hbase/HRegionLocation.getServerName:()Lorg/apache/hadoop/hbase/ServerName;
     321: astore        6
     323: aload         5
     325: aload         6
     327: invokevirtual #213                // Method org/apache/hadoop/hbase/ServerName.equals:(Ljava/lang/Object;)Z
     330: ifeq          336
     333: goto          355
     336: getstatic     #3                  // Field LOG:Lorg/slf4j/Logger;
     339: ldc           #220                // String Waiting for new region info to be updated in meta table
     341: invokeinterface #119,  2          // InterfaceMethod org/slf4j/Logger.info:(Ljava/lang/String;)V
     346: ldc2_w        #15                 // long 100l
     349: invokestatic  #185                // Method java/lang/Thread.sleep:(J)V
     352: goto          201
     355: new           #51                 // class org/apache/hadoop/hbase/client/Put
     358: dup
     359: getstatic     #2                  // Field row:[B
     362: invokespecial #52                 // Method org/apache/hadoop/hbase/client/Put."<init>":([B)V
     365: astore        5
     367: aload         5
     369: getstatic     #49                 // Field f:[B
     372: getstatic     #2                  // Field row:[B
     375: getstatic     #2                  // Field row:[B
     378: invokevirtual #53                 // Method org/apache/hadoop/hbase/client/Put.addColumn:([B[B[B)Lorg/apache/hadoop/hbase/client/Put;
     381: pop
     382: aload_2
     383: aload         5
     385: invokeinterface #54,  2           // InterfaceMethod org/apache/hadoop/hbase/client/Table.put:(Lorg/apache/hadoop/hbase/client/Put;)V
     390: getstatic     #1                  // Field HTU:Lorg/apache/hadoop/hbase/HBaseTestingUtility;
     393: aload_2
     394: invokeinterface #129,  1          // InterfaceMethod org/apache/hadoop/hbase/client/Table.getName:()Lorg/apache/hadoop/hbase/TableName;
     399: invokevirtual #182                // Method org/apache/hadoop/hbase/HBaseTestingUtility.flush:(Lorg/apache/hadoop/hbase/TableName;)V
     402: ldc2_w        #183                // long 2000l
     405: invokestatic  #185                // Method java/lang/Thread.sleep:(J)V
     408: goto          428
     411: astore        6
     413: getstatic     #3                  // Field LOG:Lorg/slf4j/Logger;
     416: aload         6
     418: invokevirtual #187                // Method java/lang/InterruptedException.toString:()Ljava/lang/String;
     421: aload         6
     423: invokeinterface #188,  3          // InterfaceMethod org/slf4j/Logger.error:(Ljava/lang/String;Ljava/lang/Throwable;)V
     428: iconst_1
     429: putstatic     #221                // Field org/apache/hadoop/hbase/client/TestReplicaWithCluster$RegionServerHostingPrimayMetaRegionSlowOrStopCopro.throwException:Z
     432: new           #55                 // class org/apache/hadoop/hbase/client/Get
     435: dup
     436: getstatic     #2                  // Field row:[B
     439: invokespecial #56                 // Method org/apache/hadoop/hbase/client/Get."<init>":([B)V
     442: astore        6
     444: aload         6
     446: getstatic     #64                 // Field org/apache/hadoop/hbase/client/Consistency.TIMELINE:Lorg/apache/hadoop/hbase/client/Consistency;
     449: invokevirtual #65                 // Method org/apache/hadoop/hbase/client/Get.setConsistency:(Lorg/apache/hadoop/hbase/client/Consistency;)Lorg/apache/hadoop/hbase/client/Get;
     452: pop
     453: aload_2
     454: aload         6
     456: invokeinterface #57,  2           // InterfaceMethod org/apache/hadoop/hbase/client/Table.get:(Lorg/apache/hadoop/hbase/client/Get;)Lorg/apache/hadoop/hbase/client/Result;
     461: astore        7
     463: aload         7
     465: invokevirtual #58                 // Method org/apache/hadoop/hbase/client/Result.isStale:()Z
     468: invokestatic  #66                 // Method org/junit/Assert.assertTrue:(Z)V
     471: aload_2
     472: aload         6
     474: invokeinterface #57,  2           // InterfaceMethod org/apache/hadoop/hbase/client/Table.get:(Lorg/apache/hadoop/hbase/client/Get;)Lorg/apache/hadoop/hbase/client/Result;
     479: astore        7
     481: aload         7
     483: invokevirtual #58                 // Method org/apache/hadoop/hbase/client/Result.isStale:()Z
     486: invokestatic  #66                 // Method org/junit/Assert.assertTrue:(Z)V
     489: getstatic     #1                  // Field HTU:Lorg/apache/hadoop/hbase/HBaseTestingUtility;
     492: invokevirtual #71                 // Method org/apache/hadoop/hbase/HBaseTestingUtility.getAdmin:()Lorg/apache/hadoop/hbase/client/Admin;
     495: invokeinterface #163,  1          // InterfaceMethod org/apache/hadoop/hbase/client/Admin.getConnection:()Lorg/apache/hadoop/hbase/client/Connection;
     500: checkcast     #203                // class org/apache/hadoop/hbase/client/ConnectionImplementation
     503: iconst_0
     504: invokevirtual #204                // Method org/apache/hadoop/hbase/client/ConnectionImplementation.setUseMetaReplicas:(Z)V
     507: iconst_0
     508: putstatic     #221                // Field org/apache/hadoop/hbase/client/TestReplicaWithCluster$RegionServerHostingPrimayMetaRegionSlowOrStopCopro.throwException:Z
     511: getstatic     #1                  // Field HTU:Lorg/apache/hadoop/hbase/HBaseTestingUtility;
     514: invokevirtual #71                 // Method org/apache/hadoop/hbase/HBaseTestingUtility.getAdmin:()Lorg/apache/hadoop/hbase/client/Admin;
     517: iconst_1
     518: iconst_1
     519: invokeinterface #202,  3          // InterfaceMethod org/apache/hadoop/hbase/client/Admin.balancerSwitch:(ZZ)Z
     524: pop
     525: getstatic     #1                  // Field HTU:Lorg/apache/hadoop/hbase/HBaseTestingUtility;
     528: invokevirtual #71                 // Method org/apache/hadoop/hbase/HBaseTestingUtility.getAdmin:()Lorg/apache/hadoop/hbase/client/Admin;
     531: aload_1
     532: invokevirtual #72                 // Method org/apache/hadoop/hbase/HTableDescriptor.getTableName:()Lorg/apache/hadoop/hbase/TableName;
     535: invokeinterface #73,  2           // InterfaceMethod org/apache/hadoop/hbase/client/Admin.disableTable:(Lorg/apache/hadoop/hbase/TableName;)V
     540: getstatic     #1                  // Field HTU:Lorg/apache/hadoop/hbase/HBaseTestingUtility;
     543: aload_1
     544: invokevirtual #72                 // Method org/apache/hadoop/hbase/HTableDescriptor.getTableName:()Lorg/apache/hadoop/hbase/TableName;
     547: invokevirtual #74                 // Method org/apache/hadoop/hbase/HBaseTestingUtility.deleteTable:(Lorg/apache/hadoop/hbase/TableName;)V
     550: goto          619
     553: astore        8
     555: getstatic     #1                  // Field HTU:Lorg/apache/hadoop/hbase/HBaseTestingUtility;
     558: invokevirtual #71                 // Method org/apache/hadoop/hbase/HBaseTestingUtility.getAdmin:()Lorg/apache/hadoop/hbase/client/Admin;
     561: invokeinterface #163,  1          // InterfaceMethod org/apache/hadoop/hbase/client/Admin.getConnection:()Lorg/apache/hadoop/hbase/client/Connection;
     566: checkcast     #203                // class org/apache/hadoop/hbase/client/ConnectionImplementation
     569: iconst_0
     570: invokevirtual #204                // Method org/apache/hadoop/hbase/client/ConnectionImplementation.setUseMetaReplicas:(Z)V
     573: iconst_0
     574: putstatic     #221                // Field org/apache/hadoop/hbase/client/TestReplicaWithCluster$RegionServerHostingPrimayMetaRegionSlowOrStopCopro.throwException:Z
     577: getstatic     #1                  // Field HTU:Lorg/apache/hadoop/hbase/HBaseTestingUtility;
     580: invokevirtual #71                 // Method org/apache/hadoop/hbase/HBaseTestingUtility.getAdmin:()Lorg/apache/hadoop/hbase/client/Admin;
     583: iconst_1
     584: iconst_1
     585: invokeinterface #202,  3          // InterfaceMethod org/apache/hadoop/hbase/client/Admin.balancerSwitch:(ZZ)Z
     590: pop
     591: getstatic     #1                  // Field HTU:Lorg/apache/hadoop/hbase/HBaseTestingUtility;
     594: invokevirtual #71                 // Method org/apache/hadoop/hbase/HBaseTestingUtility.getAdmin:()Lorg/apache/hadoop/hbase/client/Admin;
     597: aload_1
     598: invokevirtual #72                 // Method org/apache/hadoop/hbase/HTableDescriptor.getTableName:()Lorg/apache/hadoop/hbase/TableName;
     601: invokeinterface #73,  2           // InterfaceMethod org/apache/hadoop/hbase/client/Admin.disableTable:(Lorg/apache/hadoop/hbase/TableName;)V
     606: getstatic     #1                  // Field HTU:Lorg/apache/hadoop/hbase/HBaseTestingUtility;
     609: aload_1
     610: invokevirtual #72                 // Method org/apache/hadoop/hbase/HTableDescriptor.getTableName:()Lorg/apache/hadoop/hbase/TableName;
     613: invokevirtual #74                 // Method org/apache/hadoop/hbase/HBaseTestingUtility.deleteTable:(Lorg/apache/hadoop/hbase/TableName;)V
     616: aload         8
     618: athrow
     619: return
    Exception table:
       from    to  target type
         402   408   411   Class java/lang/InterruptedException
          47   489   553   any
         553   555   553   any

  static org.slf4j.Logger access$000();
    Code:
       0: getstatic     #3                  // Field LOG:Lorg/slf4j/Logger;
       3: areturn

  static byte[] access$100();
    Code:
       0: getstatic     #2                  // Field row:[B
       3: areturn

  static org.apache.hadoop.hbase.HBaseTestingUtility access$200();
    Code:
       0: getstatic     #1                  // Field HTU:Lorg/apache/hadoop/hbase/HBaseTestingUtility;
       3: areturn

  static {};
    Code:
       0: ldc           #8                  // class org/apache/hadoop/hbase/client/TestReplicaWithCluster
       2: invokestatic  #222                // Method org/apache/hadoop/hbase/HBaseClassTestRule.forClass:(Ljava/lang/Class;)Lorg/apache/hadoop/hbase/HBaseClassTestRule;
       5: putstatic     #223                // Field CLASS_RULE:Lorg/apache/hadoop/hbase/HBaseClassTestRule;
       8: ldc           #8                  // class org/apache/hadoop/hbase/client/TestReplicaWithCluster
      10: invokestatic  #224                // Method org/slf4j/LoggerFactory.getLogger:(Ljava/lang/Class;)Lorg/slf4j/Logger;
      13: putstatic     #3                  // Field LOG:Lorg/slf4j/Logger;
      16: ldc           #8                  // class org/apache/hadoop/hbase/client/TestReplicaWithCluster
      18: invokevirtual #34                 // Method java/lang/Class.getName:()Ljava/lang/String;
      21: invokestatic  #147                // Method org/apache/hadoop/hbase/util/Bytes.toBytes:(Ljava/lang/String;)[B
      24: putstatic     #2                  // Field row:[B
      27: new           #115                // class org/apache/hadoop/hbase/HBaseTestingUtility
      30: dup
      31: invokespecial #225                // Method org/apache/hadoop/hbase/HBaseTestingUtility."<init>":()V
      34: putstatic     #1                  // Field HTU:Lorg/apache/hadoop/hbase/HBaseTestingUtility;
      37: getstatic     #226                // Field org/apache/hadoop/hbase/HConstants.CATALOG_FAMILY:[B
      40: putstatic     #49                 // Field f:[B
      43: return
}
