Compiled from "TestAssignmentOnRSCrash.java"
public class org.apache.hadoop.hbase.master.assignment.TestAssignmentOnRSCrash {
  public static final org.apache.hadoop.hbase.HBaseClassTestRule CLASS_RULE;

  public org.apache.hadoop.hbase.master.assignment.TestAssignmentOnRSCrash();
    Code:
       0: aload_0
       1: invokespecial #1                  // Method java/lang/Object."<init>":()V
       4: return

  public void setup() throws java.lang.Exception;
    Code:
       0: aload_0
       1: new           #8                  // class org/apache/hadoop/hbase/HBaseTestingUtility
       4: dup
       5: invokespecial #9                  // Method org/apache/hadoop/hbase/HBaseTestingUtility."<init>":()V
       8: putfield      #10                 // Field UTIL:Lorg/apache/hadoop/hbase/HBaseTestingUtility;
      11: aload_0
      12: getfield      #10                 // Field UTIL:Lorg/apache/hadoop/hbase/HBaseTestingUtility;
      15: invokevirtual #11                 // Method org/apache/hadoop/hbase/HBaseTestingUtility.getConfiguration:()Lorg/apache/hadoop/conf/Configuration;
      18: invokestatic  #12                 // Method setupConf:(Lorg/apache/hadoop/conf/Configuration;)V
      21: aload_0
      22: getfield      #10                 // Field UTIL:Lorg/apache/hadoop/hbase/HBaseTestingUtility;
      25: iconst_3
      26: invokevirtual #14                 // Method org/apache/hadoop/hbase/HBaseTestingUtility.startMiniCluster:(I)Lorg/apache/hadoop/hbase/MiniHBaseCluster;
      29: pop
      30: aload_0
      31: getfield      #10                 // Field UTIL:Lorg/apache/hadoop/hbase/HBaseTestingUtility;
      34: getstatic     #15                 // Field TEST_TABLE:Lorg/apache/hadoop/hbase/TableName;
      37: iconst_1
      38: anewarray     #16                 // class "[B"
      41: dup
      42: iconst_0
      43: getstatic     #17                 // Field FAMILY:[B
      46: aastore
      47: iconst_4
      48: anewarray     #16                 // class "[B"
      51: dup
      52: iconst_0
      53: ldc           #18                 // String B
      55: invokestatic  #19                 // Method org/apache/hadoop/hbase/util/Bytes.toBytes:(Ljava/lang/String;)[B
      58: aastore
      59: dup
      60: iconst_1
      61: ldc           #20                 // String D
      63: invokestatic  #19                 // Method org/apache/hadoop/hbase/util/Bytes.toBytes:(Ljava/lang/String;)[B
      66: aastore
      67: dup
      68: iconst_2
      69: ldc           #21                 // String F
      71: invokestatic  #19                 // Method org/apache/hadoop/hbase/util/Bytes.toBytes:(Ljava/lang/String;)[B
      74: aastore
      75: dup
      76: iconst_3
      77: ldc           #22                 // String L
      79: invokestatic  #19                 // Method org/apache/hadoop/hbase/util/Bytes.toBytes:(Ljava/lang/String;)[B
      82: aastore
      83: invokevirtual #23                 // Method org/apache/hadoop/hbase/HBaseTestingUtility.createTable:(Lorg/apache/hadoop/hbase/TableName;[[B[[B)Lorg/apache/hadoop/hbase/client/Table;
      86: pop
      87: return

  public void tearDown() throws java.lang.Exception;
    Code:
       0: aload_0
       1: getfield      #10                 // Field UTIL:Lorg/apache/hadoop/hbase/HBaseTestingUtility;
       4: invokevirtual #24                 // Method org/apache/hadoop/hbase/HBaseTestingUtility.shutdownMiniCluster:()V
       7: return

  public void testKillRsWithUserRegionWithData() throws java.lang.Exception;
    Code:
       0: aload_0
       1: iconst_1
       2: iconst_1
       3: invokespecial #25                 // Method testCrashRsWithUserRegion:(ZZ)V
       6: return

  public void testKillRsWithUserRegionWithoutData() throws java.lang.Exception;
    Code:
       0: aload_0
       1: iconst_1
       2: iconst_0
       3: invokespecial #25                 // Method testCrashRsWithUserRegion:(ZZ)V
       6: return

  public void testStopRsWithUserRegionWithData() throws java.lang.Exception;
    Code:
       0: aload_0
       1: iconst_0
       2: iconst_1
       3: invokespecial #25                 // Method testCrashRsWithUserRegion:(ZZ)V
       6: return

  public void testStopRsWithUserRegionWithoutData() throws java.lang.Exception;
    Code:
       0: aload_0
       1: iconst_0
       2: iconst_0
       3: invokespecial #25                 // Method testCrashRsWithUserRegion:(ZZ)V
       6: return

  public void testKillRsWithMetaRegion() throws java.lang.Exception;
    Code:
       0: aload_0
       1: iconst_1
       2: invokespecial #45                 // Method testCrashRsWithMetaRegion:(Z)V
       5: return

  public void testStopRsWithMetaRegion() throws java.lang.Exception;
    Code:
       0: aload_0
       1: iconst_0
       2: invokespecial #45                 // Method testCrashRsWithMetaRegion:(Z)V
       5: return

  public int testGet(org.apache.hadoop.hbase.client.RegionInfo, int) throws java.io.IOException;
    Code:
       0: iconst_0
       1: istore_3
       2: aload_0
       3: getfield      #10                 // Field UTIL:Lorg/apache/hadoop/hbase/HBaseTestingUtility;
       6: invokevirtual #49                 // Method org/apache/hadoop/hbase/HBaseTestingUtility.getConnection:()Lorg/apache/hadoop/hbase/client/Connection;
       9: aload_1
      10: invokeinterface #50,  1           // InterfaceMethod org/apache/hadoop/hbase/client/RegionInfo.getTable:()Lorg/apache/hadoop/hbase/TableName;
      15: invokeinterface #51,  2           // InterfaceMethod org/apache/hadoop/hbase/client/Connection.getTable:(Lorg/apache/hadoop/hbase/TableName;)Lorg/apache/hadoop/hbase/client/Table;
      20: astore        4
      22: iconst_0
      23: istore        5
      25: iload         5
      27: iload_2
      28: if_icmpge     104
      31: aload_1
      32: invokeinterface #52,  1           // InterfaceMethod org/apache/hadoop/hbase/client/RegionInfo.getStartKey:()[B
      37: iload         5
      39: invokestatic  #53                 // Method org/apache/hadoop/hbase/util/Bytes.toBytes:(I)[B
      42: invokestatic  #54                 // Method org/apache/hadoop/hbase/util/Bytes.add:([B[B)[B
      45: astore        6
      47: aload         4
      49: new           #59                 // class org/apache/hadoop/hbase/client/Get
      52: dup
      53: aload         6
      55: invokespecial #60                 // Method org/apache/hadoop/hbase/client/Get."<init>":([B)V
      58: invokeinterface #61,  2           // InterfaceMethod org/apache/hadoop/hbase/client/Table.get:(Lorg/apache/hadoop/hbase/client/Get;)Lorg/apache/hadoop/hbase/client/Result;
      63: astore        7
      65: aload         7
      67: ifnull        98
      70: aload         7
      72: invokevirtual #62                 // Method org/apache/hadoop/hbase/client/Result.isEmpty:()Z
      75: ifne          98
      78: aload         6
      80: aload         7
      82: getstatic     #17                 // Field FAMILY:[B
      85: aconst_null
      86: invokevirtual #63                 // Method org/apache/hadoop/hbase/client/Result.getValue:([B[B)[B
      89: invokestatic  #64                 // Method org/apache/hadoop/hbase/util/Bytes.equals:([B[B)Z
      92: ifeq          98
      95: iinc          3, 1
      98: iinc          5, 1
     101: goto          25
     104: iload_3
     105: ireturn

  static {};
    Code:
       0: ldc           #13                 // class org/apache/hadoop/hbase/master/assignment/TestAssignmentOnRSCrash
       2: invokestatic  #65                 // Method org/apache/hadoop/hbase/HBaseClassTestRule.forClass:(Ljava/lang/Class;)Lorg/apache/hadoop/hbase/HBaseClassTestRule;
       5: putstatic     #66                 // Field CLASS_RULE:Lorg/apache/hadoop/hbase/HBaseClassTestRule;
       8: ldc           #13                 // class org/apache/hadoop/hbase/master/assignment/TestAssignmentOnRSCrash
      10: invokestatic  #67                 // Method org/slf4j/LoggerFactory.getLogger:(Ljava/lang/Class;)Lorg/slf4j/Logger;
      13: putstatic     #68                 // Field LOG:Lorg/slf4j/Logger;
      16: ldc           #69                 // String testb
      18: invokestatic  #70                 // Method org/apache/hadoop/hbase/TableName.valueOf:(Ljava/lang/String;)Lorg/apache/hadoop/hbase/TableName;
      21: putstatic     #15                 // Field TEST_TABLE:Lorg/apache/hadoop/hbase/TableName;
      24: ldc           #71                 // String f
      26: invokestatic  #19                 // Method org/apache/hadoop/hbase/util/Bytes.toBytes:(Ljava/lang/String;)[B
      29: putstatic     #17                 // Field FAMILY:[B
      32: return
}
